Compiled from "GatherNodesStream.java"
public class org.apache.solr.client.solrj.io.graph.GatherNodesStream extends org.apache.solr.client.solrj.io.stream.TupleStream implements org.apache.solr.client.solrj.io.stream.expr.Expressible {
  private java.lang.String zkHost;

  private java.lang.String collection;

  private org.apache.solr.client.solrj.io.stream.StreamContext streamContext;

  private java.util.Map<java.lang.String, java.lang.String> queryParams;

  private java.lang.String traverseFrom;

  private java.lang.String traverseTo;

  private java.lang.String gather;

  private boolean trackTraversal;

  private boolean useDefaultTraversal;

  private org.apache.solr.client.solrj.io.stream.TupleStream tupleStream;

  private java.util.Set<org.apache.solr.client.solrj.io.graph.Traversal$Scatter> scatter;

  private java.util.Iterator<org.apache.solr.client.solrj.io.Tuple> out;

  private org.apache.solr.client.solrj.io.graph.Traversal traversal;

  private java.util.List<org.apache.solr.client.solrj.io.stream.metrics.Metric> metrics;

  private int maxDocFreq;

  public org.apache.solr.client.solrj.io.graph.GatherNodesStream(java.lang.String, java.lang.String, org.apache.solr.client.solrj.io.stream.TupleStream, java.lang.String, java.lang.String, java.lang.String, java.util.Map, java.util.List<org.apache.solr.client.solrj.io.stream.metrics.Metric>, boolean, java.util.Set<org.apache.solr.client.solrj.io.graph.Traversal$Scatter>, int);
    Code:
       0: aload_0
       1: invokespecial #9                  // Method org/apache/solr/client/solrj/io/stream/TupleStream."<init>":()V
       4: aload_0
       5: aload_1
       6: aload_2
       7: aload_3
       8: aload         4
      10: aload         5
      12: aload         6
      14: aload         7
      16: aload         8
      18: iload         9
      20: aload         10
      22: iload         11
      24: invokespecial #10                 // Method init:(Ljava/lang/String;Ljava/lang/String;Lorg/apache/solr/client/solrj/io/stream/TupleStream;Ljava/lang/String;Ljava/lang/String;Ljava/lang/String;Ljava/util/Map;Ljava/util/List;ZLjava/util/Set;I)V
      27: return

  public org.apache.solr.client.solrj.io.graph.GatherNodesStream(org.apache.solr.client.solrj.io.stream.expr.StreamExpression, org.apache.solr.client.solrj.io.stream.expr.StreamFactory) throws java.io.IOException;
    Code:
       0: aload_0
       1: invokespecial #9                  // Method org/apache/solr/client/solrj/io/stream/TupleStream."<init>":()V
       4: aload_2
       5: aload_1
       6: iconst_0
       7: invokevirtual #11                 // Method org/apache/solr/client/solrj/io/stream/expr/StreamFactory.getValueOperand:(Lorg/apache/solr/client/solrj/io/stream/expr/StreamExpression;I)Ljava/lang/String;
      10: astore_3
      11: aload_2
      12: aload_1
      13: invokevirtual #12                 // Method org/apache/solr/client/solrj/io/stream/expr/StreamFactory.getNamedOperands:(Lorg/apache/solr/client/solrj/io/stream/expr/StreamExpression;)Ljava/util/List;
      16: astore        4
      18: aload_2
      19: aload_1
      20: ldc           #13                 // String zkHost
      22: invokevirtual #14                 // Method org/apache/solr/client/solrj/io/stream/expr/StreamFactory.getNamedOperand:(Lorg/apache/solr/client/solrj/io/stream/expr/StreamExpression;Ljava/lang/String;)Lorg/apache/solr/client/solrj/io/stream/expr/StreamExpressionNamedParameter;
      25: astore        5
      27: aload_2
      28: aload_1
      29: iconst_2
      30: anewarray     #15                 // class java/lang/Class
      33: dup
      34: iconst_0
      35: ldc           #16                 // class org/apache/solr/client/solrj/io/stream/expr/Expressible
      37: aastore
      38: dup
      39: iconst_1
      40: ldc           #17                 // class org/apache/solr/client/solrj/io/stream/TupleStream
      42: aastore
      43: invokevirtual #18                 // Method org/apache/solr/client/solrj/io/stream/expr/StreamFactory.getExpressionOperandsRepresentingTypes:(Lorg/apache/solr/client/solrj/io/stream/expr/StreamExpression;[Ljava/lang/Class;)Ljava/util/List;
      46: astore        6
      48: aconst_null
      49: aload_3
      50: if_acmpne     77
      53: new           #19                 // class java/io/IOException
      56: dup
      57: getstatic     #20                 // Field java/util/Locale.ROOT:Ljava/util/Locale;
      60: ldc           #21                 // String invalid expression %s - collectionName expected as first operand
      62: iconst_1
      63: anewarray     #22                 // class java/lang/Object
      66: dup
      67: iconst_0
      68: aload_1
      69: aastore
      70: invokestatic  #23                 // Method java/lang/String.format:(Ljava/util/Locale;Ljava/lang/String;[Ljava/lang/Object;)Ljava/lang/String;
      73: invokespecial #24                 // Method java/io/IOException."<init>":(Ljava/lang/String;)V
      76: athrow
      77: new           #25                 // class java/util/HashSet
      80: dup
      81: invokespecial #26                 // Method java/util/HashSet."<init>":()V
      84: astore        7
      86: aload_2
      87: aload_1
      88: ldc           #27                 // String scatter
      90: invokevirtual #14                 // Method org/apache/solr/client/solrj/io/stream/expr/StreamFactory.getNamedOperand:(Lorg/apache/solr/client/solrj/io/stream/expr/StreamExpression;Ljava/lang/String;)Lorg/apache/solr/client/solrj/io/stream/expr/StreamExpressionNamedParameter;
      93: astore        8
      95: aload         8
      97: ifnonnull     114
     100: aload         7
     102: getstatic     #28                 // Field org/apache/solr/client/solrj/io/graph/Traversal$Scatter.LEAVES:Lorg/apache/solr/client/solrj/io/graph/Traversal$Scatter;
     105: invokeinterface #29,  2           // InterfaceMethod java/util/Set.add:(Ljava/lang/Object;)Z
     110: pop
     111: goto          228
     114: aload         8
     116: invokevirtual #30                 // Method org/apache/solr/client/solrj/io/stream/expr/StreamExpressionNamedParameter.getParameter:()Lorg/apache/solr/client/solrj/io/stream/expr/StreamExpressionParameter;
     119: checkcast     #31                 // class org/apache/solr/client/solrj/io/stream/expr/StreamExpressionValue
     122: invokevirtual #32                 // Method org/apache/solr/client/solrj/io/stream/expr/StreamExpressionValue.getValue:()Ljava/lang/String;
     125: astore        9
     127: aload         9
     129: ldc           #33                 // String ,
     131: invokevirtual #34                 // Method java/lang/String.split:(Ljava/lang/String;)[Ljava/lang/String;
     134: astore        10
     136: aload         10
     138: astore        11
     140: aload         11
     142: arraylength
     143: istore        12
     145: iconst_0
     146: istore        13
     148: iload         13
     150: iload         12
     152: if_icmpge     228
     155: aload         11
     157: iload         13
     159: aaload
     160: astore        14
     162: aload         14
     164: invokevirtual #35                 // Method java/lang/String.trim:()Ljava/lang/String;
     167: astore        14
     169: getstatic     #36                 // Field org/apache/solr/client/solrj/io/graph/Traversal$Scatter.BRANCHES:Lorg/apache/solr/client/solrj/io/graph/Traversal$Scatter;
     172: invokevirtual #37                 // Method org/apache/solr/client/solrj/io/graph/Traversal$Scatter.toString:()Ljava/lang/String;
     175: aload         14
     177: invokevirtual #38                 // Method java/lang/String.equalsIgnoreCase:(Ljava/lang/String;)Z
     180: ifeq          197
     183: aload         7
     185: getstatic     #36                 // Field org/apache/solr/client/solrj/io/graph/Traversal$Scatter.BRANCHES:Lorg/apache/solr/client/solrj/io/graph/Traversal$Scatter;
     188: invokeinterface #29,  2           // InterfaceMethod java/util/Set.add:(Ljava/lang/Object;)Z
     193: pop
     194: goto          222
     197: getstatic     #28                 // Field org/apache/solr/client/solrj/io/graph/Traversal$Scatter.LEAVES:Lorg/apache/solr/client/solrj/io/graph/Traversal$Scatter;
     200: invokevirtual #37                 // Method org/apache/solr/client/solrj/io/graph/Traversal$Scatter.toString:()Ljava/lang/String;
     203: aload         14
     205: invokevirtual #38                 // Method java/lang/String.equalsIgnoreCase:(Ljava/lang/String;)Z
     208: ifeq          222
     211: aload         7
     213: getstatic     #28                 // Field org/apache/solr/client/solrj/io/graph/Traversal$Scatter.LEAVES:Lorg/apache/solr/client/solrj/io/graph/Traversal$Scatter;
     216: invokeinterface #29,  2           // InterfaceMethod java/util/Set.add:(Ljava/lang/Object;)Z
     221: pop
     222: iinc          13, 1
     225: goto          148
     228: aconst_null
     229: astore        9
     231: aload_2
     232: aload_1
     233: ldc           #39                 // String gather
     235: invokevirtual #14                 // Method org/apache/solr/client/solrj/io/stream/expr/StreamFactory.getNamedOperand:(Lorg/apache/solr/client/solrj/io/stream/expr/StreamExpression;Ljava/lang/String;)Lorg/apache/solr/client/solrj/io/stream/expr/StreamExpressionNamedParameter;
     238: astore        10
     240: aload         10
     242: ifnonnull     269
     245: new           #19                 // class java/io/IOException
     248: dup
     249: getstatic     #20                 // Field java/util/Locale.ROOT:Ljava/util/Locale;
     252: ldc           #40                 // String invalid expression %s - from param is required
     254: iconst_1
     255: anewarray     #22                 // class java/lang/Object
     258: dup
     259: iconst_0
     260: aload_1
     261: aastore
     262: invokestatic  #23                 // Method java/lang/String.format:(Ljava/util/Locale;Ljava/lang/String;[Ljava/lang/Object;)Ljava/lang/String;
     265: invokespecial #24                 // Method java/io/IOException."<init>":(Ljava/lang/String;)V
     268: athrow
     269: aload         10
     271: invokevirtual #30                 // Method org/apache/solr/client/solrj/io/stream/expr/StreamExpressionNamedParameter.getParameter:()Lorg/apache/solr/client/solrj/io/stream/expr/StreamExpressionParameter;
     274: checkcast     #31                 // class org/apache/solr/client/solrj/io/stream/expr/StreamExpressionValue
     277: invokevirtual #32                 // Method org/apache/solr/client/solrj/io/stream/expr/StreamExpressionValue.getValue:()Ljava/lang/String;
     280: astore        9
     282: aconst_null
     283: astore        11
     285: aconst_null
     286: astore        12
     288: aload_2
     289: aload_1
     290: ldc           #41                 // String walk
     292: invokevirtual #14                 // Method org/apache/solr/client/solrj/io/stream/expr/StreamFactory.getNamedOperand:(Lorg/apache/solr/client/solrj/io/stream/expr/StreamExpression;Ljava/lang/String;)Lorg/apache/solr/client/solrj/io/stream/expr/StreamExpressionNamedParameter;
     295: astore        13
     297: aconst_null
     298: astore        14
     300: aload         13
     302: ifnonnull     329
     305: new           #19                 // class java/io/IOException
     308: dup
     309: getstatic     #20                 // Field java/util/Locale.ROOT:Ljava/util/Locale;
     312: ldc           #42                 // String invalid expression %s - walk param is required
     314: iconst_1
     315: anewarray     #22                 // class java/lang/Object
     318: dup
     319: iconst_0
     320: aload_1
     321: aastore
     322: invokestatic  #23                 // Method java/lang/String.format:(Ljava/util/Locale;Ljava/lang/String;[Ljava/lang/Object;)Ljava/lang/String;
     325: invokespecial #24                 // Method java/io/IOException."<init>":(Ljava/lang/String;)V
     328: athrow
     329: aload         6
     331: invokeinterface #43,  1           // InterfaceMethod java/util/List.size:()I
     336: ifle          430
     339: aload_2
     340: aload         6
     342: iconst_0
     343: invokeinterface #44,  2           // InterfaceMethod java/util/List.get:(I)Ljava/lang/Object;
     348: checkcast     #45                 // class org/apache/solr/client/solrj/io/stream/expr/StreamExpression
     351: invokevirtual #46                 // Method org/apache/solr/client/solrj/io/stream/expr/StreamFactory.constructStream:(Lorg/apache/solr/client/solrj/io/stream/expr/StreamExpression;)Lorg/apache/solr/client/solrj/io/stream/TupleStream;
     354: astore        14
     356: aload         13
     358: invokevirtual #30                 // Method org/apache/solr/client/solrj/io/stream/expr/StreamExpressionNamedParameter.getParameter:()Lorg/apache/solr/client/solrj/io/stream/expr/StreamExpressionParameter;
     361: checkcast     #31                 // class org/apache/solr/client/solrj/io/stream/expr/StreamExpressionValue
     364: invokevirtual #32                 // Method org/apache/solr/client/solrj/io/stream/expr/StreamExpressionValue.getValue:()Ljava/lang/String;
     367: astore        15
     369: aload         15
     371: ldc           #47                 // String ->
     373: invokevirtual #34                 // Method java/lang/String.split:(Ljava/lang/String;)[Ljava/lang/String;
     376: astore        16
     378: aload         16
     380: arraylength
     381: iconst_2
     382: if_icmpeq     409
     385: new           #19                 // class java/io/IOException
     388: dup
     389: getstatic     #20                 // Field java/util/Locale.ROOT:Ljava/util/Locale;
     392: ldc           #48                 // String invalid expression %s - walk param separated by an -> and must contain two fields
     394: iconst_1
     395: anewarray     #22                 // class java/lang/Object
     398: dup
     399: iconst_0
     400: aload_1
     401: aastore
     402: invokestatic  #23                 // Method java/lang/String.format:(Ljava/util/Locale;Ljava/lang/String;[Ljava/lang/Object;)Ljava/lang/String;
     405: invokespecial #24                 // Method java/io/IOException."<init>":(Ljava/lang/String;)V
     408: athrow
     409: aload         16
     411: iconst_0
     412: aaload
     413: invokevirtual #35                 // Method java/lang/String.trim:()Ljava/lang/String;
     416: astore        11
     418: aload         16
     420: iconst_1
     421: aaload
     422: invokevirtual #35                 // Method java/lang/String.trim:()Ljava/lang/String;
     425: astore        12
     427: goto          573
     430: aload         13
     432: invokevirtual #30                 // Method org/apache/solr/client/solrj/io/stream/expr/StreamExpressionNamedParameter.getParameter:()Lorg/apache/solr/client/solrj/io/stream/expr/StreamExpressionParameter;
     435: checkcast     #31                 // class org/apache/solr/client/solrj/io/stream/expr/StreamExpressionValue
     438: invokevirtual #32                 // Method org/apache/solr/client/solrj/io/stream/expr/StreamExpressionValue.getValue:()Ljava/lang/String;
     441: astore        15
     443: aload         15
     445: ldc           #47                 // String ->
     447: invokevirtual #34                 // Method java/lang/String.split:(Ljava/lang/String;)[Ljava/lang/String;
     450: astore        16
     452: aload         16
     454: arraylength
     455: iconst_2
     456: if_icmpeq     483
     459: new           #19                 // class java/io/IOException
     462: dup
     463: getstatic     #20                 // Field java/util/Locale.ROOT:Ljava/util/Locale;
     466: ldc           #48                 // String invalid expression %s - walk param separated by an -> and must contain two fields
     468: iconst_1
     469: anewarray     #22                 // class java/lang/Object
     472: dup
     473: iconst_0
     474: aload_1
     475: aastore
     476: invokestatic  #23                 // Method java/lang/String.format:(Ljava/util/Locale;Ljava/lang/String;[Ljava/lang/Object;)Ljava/lang/String;
     479: invokespecial #24                 // Method java/io/IOException."<init>":(Ljava/lang/String;)V
     482: athrow
     483: aload         16
     485: iconst_0
     486: aaload
     487: ldc           #33                 // String ,
     489: invokevirtual #34                 // Method java/lang/String.split:(Ljava/lang/String;)[Ljava/lang/String;
     492: astore        17
     494: new           #49                 // class java/util/ArrayList
     497: dup
     498: invokespecial #50                 // Method java/util/ArrayList."<init>":()V
     501: astore        18
     503: aload         17
     505: astore        19
     507: aload         19
     509: arraylength
     510: istore        20
     512: iconst_0
     513: istore        21
     515: iload         21
     517: iload         20
     519: if_icmpge     548
     522: aload         19
     524: iload         21
     526: aaload
     527: astore        22
     529: aload         18
     531: aload         22
     533: invokevirtual #35                 // Method java/lang/String.trim:()Ljava/lang/String;
     536: invokeinterface #51,  2           // InterfaceMethod java/util/List.add:(Ljava/lang/Object;)Z
     541: pop
     542: iinc          21, 1
     545: goto          515
     548: new           #52                 // class org/apache/solr/client/solrj/io/graph/GatherNodesStream$NodeStream
     551: dup
     552: aload_0
     553: aload         18
     555: invokespecial #53                 // Method org/apache/solr/client/solrj/io/graph/GatherNodesStream$NodeStream."<init>":(Lorg/apache/solr/client/solrj/io/graph/GatherNodesStream;Ljava/util/List;)V
     558: astore        14
     560: ldc           #54                 // String node
     562: astore        11
     564: aload         16
     566: iconst_1
     567: aaload
     568: invokevirtual #35                 // Method java/lang/String.trim:()Ljava/lang/String;
     571: astore        12
     573: aload_2
     574: aload_1
     575: iconst_2
     576: anewarray     #15                 // class java/lang/Class
     579: dup
     580: iconst_0
     581: ldc           #16                 // class org/apache/solr/client/solrj/io/stream/expr/Expressible
     583: aastore
     584: dup
     585: iconst_1
     586: ldc           #55                 // class org/apache/solr/client/solrj/io/stream/metrics/Metric
     588: aastore
     589: invokevirtual #18                 // Method org/apache/solr/client/solrj/io/stream/expr/StreamFactory.getExpressionOperandsRepresentingTypes:(Lorg/apache/solr/client/solrj/io/stream/expr/StreamExpression;[Ljava/lang/Class;)Ljava/util/List;
     592: astore        15
     594: new           #49                 // class java/util/ArrayList
     597: dup
     598: invokespecial #50                 // Method java/util/ArrayList."<init>":()V
     601: astore        16
     603: iconst_0
     604: istore        17
     606: iload         17
     608: aload         15
     610: invokeinterface #43,  1           // InterfaceMethod java/util/List.size:()I
     615: if_icmpge     648
     618: aload         16
     620: aload_2
     621: aload         15
     623: iload         17
     625: invokeinterface #44,  2           // InterfaceMethod java/util/List.get:(I)Ljava/lang/Object;
     630: checkcast     #45                 // class org/apache/solr/client/solrj/io/stream/expr/StreamExpression
     633: invokevirtual #56                 // Method org/apache/solr/client/solrj/io/stream/expr/StreamFactory.constructMetric:(Lorg/apache/solr/client/solrj/io/stream/expr/StreamExpression;)Lorg/apache/solr/client/solrj/io/stream/metrics/Metric;
     636: invokeinterface #51,  2           // InterfaceMethod java/util/List.add:(Ljava/lang/Object;)Z
     641: pop
     642: iinc          17, 1
     645: goto          606
     648: iconst_0
     649: istore        17
     651: aload_2
     652: aload_1
     653: ldc           #57                 // String trackTraversal
     655: invokevirtual #14                 // Method org/apache/solr/client/solrj/io/stream/expr/StreamFactory.getNamedOperand:(Lorg/apache/solr/client/solrj/io/stream/expr/StreamExpression;Ljava/lang/String;)Lorg/apache/solr/client/solrj/io/stream/expr/StreamExpressionNamedParameter;
     658: astore        18
     660: aload         18
     662: ifnull        684
     665: aload         18
     667: invokevirtual #30                 // Method org/apache/solr/client/solrj/io/stream/expr/StreamExpressionNamedParameter.getParameter:()Lorg/apache/solr/client/solrj/io/stream/expr/StreamExpressionParameter;
     670: checkcast     #31                 // class org/apache/solr/client/solrj/io/stream/expr/StreamExpressionValue
     673: invokevirtual #32                 // Method org/apache/solr/client/solrj/io/stream/expr/StreamExpressionValue.getValue:()Ljava/lang/String;
     676: invokestatic  #58                 // Method java/lang/Boolean.parseBoolean:(Ljava/lang/String;)Z
     679: istore        17
     681: goto          689
     684: aload_0
     685: iconst_1
     686: putfield      #59                 // Field useDefaultTraversal:Z
     689: aload_2
     690: aload_1
     691: ldc           #60                 // String maxDocFreq
     693: invokevirtual #14                 // Method org/apache/solr/client/solrj/io/stream/expr/StreamFactory.getNamedOperand:(Lorg/apache/solr/client/solrj/io/stream/expr/StreamExpression;Ljava/lang/String;)Lorg/apache/solr/client/solrj/io/stream/expr/StreamExpressionNamedParameter;
     696: astore        19
     698: iconst_m1
     699: istore        20
     701: aload         19
     703: ifnull        722
     706: aload         19
     708: invokevirtual #30                 // Method org/apache/solr/client/solrj/io/stream/expr/StreamExpressionNamedParameter.getParameter:()Lorg/apache/solr/client/solrj/io/stream/expr/StreamExpressionParameter;
     711: checkcast     #31                 // class org/apache/solr/client/solrj/io/stream/expr/StreamExpressionValue
     714: invokevirtual #32                 // Method org/apache/solr/client/solrj/io/stream/expr/StreamExpressionValue.getValue:()Ljava/lang/String;
     717: invokestatic  #61                 // Method java/lang/Integer.parseInt:(Ljava/lang/String;)I
     720: istore        20
     722: new           #62                 // class java/util/HashMap
     725: dup
     726: invokespecial #63                 // Method java/util/HashMap."<init>":()V
     729: astore        21
     731: aload         4
     733: invokeinterface #64,  1           // InterfaceMethod java/util/List.iterator:()Ljava/util/Iterator;
     738: astore        22
     740: aload         22
     742: invokeinterface #65,  1           // InterfaceMethod java/util/Iterator.hasNext:()Z
     747: ifeq          867
     750: aload         22
     752: invokeinterface #66,  1           // InterfaceMethod java/util/Iterator.next:()Ljava/lang/Object;
     757: checkcast     #67                 // class org/apache/solr/client/solrj/io/stream/expr/StreamExpressionNamedParameter
     760: astore        23
     762: aload         23
     764: invokevirtual #68                 // Method org/apache/solr/client/solrj/io/stream/expr/StreamExpressionNamedParameter.getName:()Ljava/lang/String;
     767: ldc           #13                 // String zkHost
     769: invokevirtual #69                 // Method java/lang/String.equals:(Ljava/lang/Object;)Z
     772: ifne          864
     775: aload         23
     777: invokevirtual #68                 // Method org/apache/solr/client/solrj/io/stream/expr/StreamExpressionNamedParameter.getName:()Ljava/lang/String;
     780: ldc           #39                 // String gather
     782: invokevirtual #69                 // Method java/lang/String.equals:(Ljava/lang/Object;)Z
     785: ifne          864
     788: aload         23
     790: invokevirtual #68                 // Method org/apache/solr/client/solrj/io/stream/expr/StreamExpressionNamedParameter.getName:()Ljava/lang/String;
     793: ldc           #41                 // String walk
     795: invokevirtual #69                 // Method java/lang/String.equals:(Ljava/lang/Object;)Z
     798: ifne          864
     801: aload         23
     803: invokevirtual #68                 // Method org/apache/solr/client/solrj/io/stream/expr/StreamExpressionNamedParameter.getName:()Ljava/lang/String;
     806: ldc           #27                 // String scatter
     808: invokevirtual #69                 // Method java/lang/String.equals:(Ljava/lang/Object;)Z
     811: ifne          864
     814: aload         23
     816: invokevirtual #68                 // Method org/apache/solr/client/solrj/io/stream/expr/StreamExpressionNamedParameter.getName:()Ljava/lang/String;
     819: ldc           #60                 // String maxDocFreq
     821: invokevirtual #69                 // Method java/lang/String.equals:(Ljava/lang/Object;)Z
     824: ifne          864
     827: aload         23
     829: invokevirtual #68                 // Method org/apache/solr/client/solrj/io/stream/expr/StreamExpressionNamedParameter.getName:()Ljava/lang/String;
     832: ldc           #57                 // String trackTraversal
     834: invokevirtual #69                 // Method java/lang/String.equals:(Ljava/lang/Object;)Z
     837: ifne          864
     840: aload         21
     842: aload         23
     844: invokevirtual #68                 // Method org/apache/solr/client/solrj/io/stream/expr/StreamExpressionNamedParameter.getName:()Ljava/lang/String;
     847: aload         23
     849: invokevirtual #30                 // Method org/apache/solr/client/solrj/io/stream/expr/StreamExpressionNamedParameter.getParameter:()Lorg/apache/solr/client/solrj/io/stream/expr/StreamExpressionParameter;
     852: invokevirtual #70                 // Method java/lang/Object.toString:()Ljava/lang/String;
     855: invokevirtual #35                 // Method java/lang/String.trim:()Ljava/lang/String;
     858: invokeinterface #71,  3           // InterfaceMethod java/util/Map.put:(Ljava/lang/Object;Ljava/lang/Object;)Ljava/lang/Object;
     863: pop
     864: goto          740
     867: aconst_null
     868: astore        22
     870: aconst_null
     871: aload         5
     873: if_acmpne     897
     876: aload_2
     877: aload_3
     878: invokevirtual #72                 // Method org/apache/solr/client/solrj/io/stream/expr/StreamFactory.getCollectionZkHost:(Ljava/lang/String;)Ljava/lang/String;
     881: astore        22
     883: aload         22
     885: ifnonnull     921
     888: aload_2
     889: invokevirtual #73                 // Method org/apache/solr/client/solrj/io/stream/expr/StreamFactory.getDefaultZkHost:()Ljava/lang/String;
     892: astore        22
     894: goto          921
     897: aload         5
     899: invokevirtual #30                 // Method org/apache/solr/client/solrj/io/stream/expr/StreamExpressionNamedParameter.getParameter:()Lorg/apache/solr/client/solrj/io/stream/expr/StreamExpressionParameter;
     902: instanceof    #31                 // class org/apache/solr/client/solrj/io/stream/expr/StreamExpressionValue
     905: ifeq          921
     908: aload         5
     910: invokevirtual #30                 // Method org/apache/solr/client/solrj/io/stream/expr/StreamExpressionNamedParameter.getParameter:()Lorg/apache/solr/client/solrj/io/stream/expr/StreamExpressionParameter;
     913: checkcast     #31                 // class org/apache/solr/client/solrj/io/stream/expr/StreamExpressionValue
     916: invokevirtual #32                 // Method org/apache/solr/client/solrj/io/stream/expr/StreamExpressionValue.getValue:()Ljava/lang/String;
     919: astore        22
     921: aconst_null
     922: aload         22
     924: if_acmpne     955
     927: new           #19                 // class java/io/IOException
     930: dup
     931: getstatic     #20                 // Field java/util/Locale.ROOT:Ljava/util/Locale;
     934: ldc           #74                 // String invalid expression %s - zkHost not found for collection \'%s\'
     936: iconst_2
     937: anewarray     #22                 // class java/lang/Object
     940: dup
     941: iconst_0
     942: aload_1
     943: aastore
     944: dup
     945: iconst_1
     946: aload_3
     947: aastore
     948: invokestatic  #23                 // Method java/lang/String.format:(Ljava/util/Locale;Ljava/lang/String;[Ljava/lang/Object;)Ljava/lang/String;
     951: invokespecial #24                 // Method java/io/IOException."<init>":(Ljava/lang/String;)V
     954: athrow
     955: aload_0
     956: aload         22
     958: aload_3
     959: aload         14
     961: aload         11
     963: aload         12
     965: aload         9
     967: aload         21
     969: aload         16
     971: iload         17
     973: aload         7
     975: iload         20
     977: invokespecial #10                 // Method init:(Ljava/lang/String;Ljava/lang/String;Lorg/apache/solr/client/solrj/io/stream/TupleStream;Ljava/lang/String;Ljava/lang/String;Ljava/lang/String;Ljava/util/Map;Ljava/util/List;ZLjava/util/Set;I)V
     980: return

  private void init(java.lang.String, java.lang.String, org.apache.solr.client.solrj.io.stream.TupleStream, java.lang.String, java.lang.String, java.lang.String, java.util.Map, java.util.List<org.apache.solr.client.solrj.io.stream.metrics.Metric>, boolean, java.util.Set<org.apache.solr.client.solrj.io.graph.Traversal$Scatter>, int);
    Code:
       0: aload_0
       1: aload_1
       2: putfield      #3                  // Field zkHost:Ljava/lang/String;
       5: aload_0
       6: aload_2
       7: putfield      #2                  // Field collection:Ljava/lang/String;
      10: aload_0
      11: aload_3
      12: putfield      #75                 // Field tupleStream:Lorg/apache/solr/client/solrj/io/stream/TupleStream;
      15: aload_0
      16: aload         4
      18: putfield      #76                 // Field traverseFrom:Ljava/lang/String;
      21: aload_0
      22: aload         5
      24: putfield      #7                  // Field traverseTo:Ljava/lang/String;
      27: aload_0
      28: aload         6
      30: putfield      #8                  // Field gather:Ljava/lang/String;
      33: aload_0
      34: aload         7
      36: putfield      #5                  // Field queryParams:Ljava/util/Map;
      39: aload_0
      40: aload         8
      42: putfield      #6                  // Field metrics:Ljava/util/List;
      45: aload_0
      46: iload         9
      48: putfield      #77                 // Field trackTraversal:Z
      51: aload_0
      52: aload         10
      54: putfield      #78                 // Field scatter:Ljava/util/Set;
      57: aload_0
      58: iload         11
      60: putfield      #4                  // Field maxDocFreq:I
      63: return

  public org.apache.solr.client.solrj.io.stream.expr.StreamExpression toExpression(org.apache.solr.client.solrj.io.stream.expr.StreamFactory) throws java.io.IOException;
    Code:
       0: aload_0
       1: aload_1
       2: iconst_1
       3: invokespecial #79                 // Method toExpression:(Lorg/apache/solr/client/solrj/io/stream/expr/StreamFactory;Z)Lorg/apache/solr/client/solrj/io/stream/expr/StreamExpression;
       6: areturn

  private org.apache.solr.client.solrj.io.stream.expr.StreamExpression toExpression(org.apache.solr.client.solrj.io.stream.expr.StreamFactory, boolean) throws java.io.IOException;
    Code:
       0: new           #45                 // class org/apache/solr/client/solrj/io/stream/expr/StreamExpression
       3: dup
       4: aload_1
       5: aload_0
       6: invokevirtual #80                 // Method java/lang/Object.getClass:()Ljava/lang/Class;
       9: invokevirtual #81                 // Method org/apache/solr/client/solrj/io/stream/expr/StreamFactory.getFunctionName:(Ljava/lang/Class;)Ljava/lang/String;
      12: invokespecial #82                 // Method org/apache/solr/client/solrj/io/stream/expr/StreamExpression."<init>":(Ljava/lang/String;)V
      15: astore_3
      16: aload_3
      17: aload_0
      18: getfield      #2                  // Field collection:Ljava/lang/String;
      21: invokevirtual #83                 // Method org/apache/solr/client/solrj/io/stream/expr/StreamExpression.addParameter:(Ljava/lang/String;)V
      24: iload_2
      25: ifeq          78
      28: aload_0
      29: getfield      #75                 // Field tupleStream:Lorg/apache/solr/client/solrj/io/stream/TupleStream;
      32: instanceof    #52                 // class org/apache/solr/client/solrj/io/graph/GatherNodesStream$NodeStream
      35: ifne          78
      38: aload_0
      39: getfield      #75                 // Field tupleStream:Lorg/apache/solr/client/solrj/io/stream/TupleStream;
      42: instanceof    #16                 // class org/apache/solr/client/solrj/io/stream/expr/Expressible
      45: ifeq          68
      48: aload_3
      49: aload_0
      50: getfield      #75                 // Field tupleStream:Lorg/apache/solr/client/solrj/io/stream/TupleStream;
      53: checkcast     #16                 // class org/apache/solr/client/solrj/io/stream/expr/Expressible
      56: aload_1
      57: invokeinterface #84,  2           // InterfaceMethod org/apache/solr/client/solrj/io/stream/expr/Expressible.toExpression:(Lorg/apache/solr/client/solrj/io/stream/expr/StreamFactory;)Lorg/apache/solr/client/solrj/io/stream/expr/StreamExpressionParameter;
      62: invokevirtual #85                 // Method org/apache/solr/client/solrj/io/stream/expr/StreamExpression.addParameter:(Lorg/apache/solr/client/solrj/io/stream/expr/StreamExpressionParameter;)V
      65: goto          84
      68: new           #19                 // class java/io/IOException
      71: dup
      72: ldc           #86                 // String This GatherNodesStream contains a non-expressible TupleStream - it cannot be converted to an expression
      74: invokespecial #24                 // Method java/io/IOException."<init>":(Ljava/lang/String;)V
      77: athrow
      78: aload_3
      79: ldc           #87                 // String <stream>
      81: invokevirtual #83                 // Method org/apache/solr/client/solrj/io/stream/expr/StreamExpression.addParameter:(Ljava/lang/String;)V
      84: aload_0
      85: getfield      #5                  // Field queryParams:Ljava/util/Map;
      88: invokeinterface #88,  1           // InterfaceMethod java/util/Map.entrySet:()Ljava/util/Set;
      93: astore        4
      95: aload         4
      97: invokeinterface #89,  1           // InterfaceMethod java/util/Set.iterator:()Ljava/util/Iterator;
     102: astore        5
     104: aload         5
     106: invokeinterface #65,  1           // InterfaceMethod java/util/Iterator.hasNext:()Z
     111: ifeq          175
     114: aload         5
     116: invokeinterface #66,  1           // InterfaceMethod java/util/Iterator.next:()Ljava/lang/Object;
     121: checkcast     #90                 // class java/util/Map$Entry
     124: astore        6
     126: aload         6
     128: invokeinterface #91,  1           // InterfaceMethod java/util/Map$Entry.getValue:()Ljava/lang/Object;
     133: invokevirtual #70                 // Method java/lang/Object.toString:()Ljava/lang/String;
     136: astore        7
     138: aload         7
     140: ldc           #92                 // String \"
     142: ldc           #93                 // String \\\"
     144: invokevirtual #94                 // Method java/lang/String.replace:(Ljava/lang/CharSequence;Ljava/lang/CharSequence;)Ljava/lang/String;
     147: astore        7
     149: aload_3
     150: new           #67                 // class org/apache/solr/client/solrj/io/stream/expr/StreamExpressionNamedParameter
     153: dup
     154: aload         6
     156: invokeinterface #95,  1           // InterfaceMethod java/util/Map$Entry.getKey:()Ljava/lang/Object;
     161: invokevirtual #70                 // Method java/lang/Object.toString:()Ljava/lang/String;
     164: aload         7
     166: invokespecial #96                 // Method org/apache/solr/client/solrj/io/stream/expr/StreamExpressionNamedParameter."<init>":(Ljava/lang/String;Ljava/lang/String;)V
     169: invokevirtual #85                 // Method org/apache/solr/client/solrj/io/stream/expr/StreamExpression.addParameter:(Lorg/apache/solr/client/solrj/io/stream/expr/StreamExpressionParameter;)V
     172: goto          104
     175: aload_0
     176: getfield      #6                  // Field metrics:Ljava/util/List;
     179: ifnull        228
     182: aload_0
     183: getfield      #6                  // Field metrics:Ljava/util/List;
     186: invokeinterface #64,  1           // InterfaceMethod java/util/List.iterator:()Ljava/util/Iterator;
     191: astore        5
     193: aload         5
     195: invokeinterface #65,  1           // InterfaceMethod java/util/Iterator.hasNext:()Z
     200: ifeq          228
     203: aload         5
     205: invokeinterface #66,  1           // InterfaceMethod java/util/Iterator.next:()Ljava/lang/Object;
     210: checkcast     #55                 // class org/apache/solr/client/solrj/io/stream/metrics/Metric
     213: astore        6
     215: aload_3
     216: aload         6
     218: aload_1
     219: invokevirtual #97                 // Method org/apache/solr/client/solrj/io/stream/metrics/Metric.toExpression:(Lorg/apache/solr/client/solrj/io/stream/expr/StreamFactory;)Lorg/apache/solr/client/solrj/io/stream/expr/StreamExpressionParameter;
     222: invokevirtual #85                 // Method org/apache/solr/client/solrj/io/stream/expr/StreamExpression.addParameter:(Lorg/apache/solr/client/solrj/io/stream/expr/StreamExpressionParameter;)V
     225: goto          193
     228: aload_3
     229: new           #67                 // class org/apache/solr/client/solrj/io/stream/expr/StreamExpressionNamedParameter
     232: dup
     233: ldc           #13                 // String zkHost
     235: aload_0
     236: getfield      #3                  // Field zkHost:Ljava/lang/String;
     239: invokespecial #96                 // Method org/apache/solr/client/solrj/io/stream/expr/StreamExpressionNamedParameter."<init>":(Ljava/lang/String;Ljava/lang/String;)V
     242: invokevirtual #85                 // Method org/apache/solr/client/solrj/io/stream/expr/StreamExpression.addParameter:(Lorg/apache/solr/client/solrj/io/stream/expr/StreamExpressionParameter;)V
     245: aload_3
     246: new           #67                 // class org/apache/solr/client/solrj/io/stream/expr/StreamExpressionNamedParameter
     249: dup
     250: ldc           #39                 // String gather
     252: aload_0
     253: getfield      #3                  // Field zkHost:Ljava/lang/String;
     256: invokespecial #96                 // Method org/apache/solr/client/solrj/io/stream/expr/StreamExpressionNamedParameter."<init>":(Ljava/lang/String;Ljava/lang/String;)V
     259: invokevirtual #85                 // Method org/apache/solr/client/solrj/io/stream/expr/StreamExpression.addParameter:(Lorg/apache/solr/client/solrj/io/stream/expr/StreamExpressionParameter;)V
     262: aload_0
     263: getfield      #4                  // Field maxDocFreq:I
     266: iconst_m1
     267: if_icmple     290
     270: aload_3
     271: new           #67                 // class org/apache/solr/client/solrj/io/stream/expr/StreamExpressionNamedParameter
     274: dup
     275: ldc           #60                 // String maxDocFreq
     277: aload_0
     278: getfield      #4                  // Field maxDocFreq:I
     281: invokestatic  #98                 // Method java/lang/Integer.toString:(I)Ljava/lang/String;
     284: invokespecial #96                 // Method org/apache/solr/client/solrj/io/stream/expr/StreamExpressionNamedParameter."<init>":(Ljava/lang/String;Ljava/lang/String;)V
     287: invokevirtual #85                 // Method org/apache/solr/client/solrj/io/stream/expr/StreamExpression.addParameter:(Lorg/apache/solr/client/solrj/io/stream/expr/StreamExpressionParameter;)V
     290: aload_0
     291: getfield      #75                 // Field tupleStream:Lorg/apache/solr/client/solrj/io/stream/TupleStream;
     294: instanceof    #52                 // class org/apache/solr/client/solrj/io/graph/GatherNodesStream$NodeStream
     297: ifeq          355
     300: aload_0
     301: getfield      #75                 // Field tupleStream:Lorg/apache/solr/client/solrj/io/stream/TupleStream;
     304: checkcast     #52                 // class org/apache/solr/client/solrj/io/graph/GatherNodesStream$NodeStream
     307: astore        5
     309: aload_3
     310: new           #67                 // class org/apache/solr/client/solrj/io/stream/expr/StreamExpressionNamedParameter
     313: dup
     314: ldc           #41                 // String walk
     316: new           #99                 // class java/lang/StringBuilder
     319: dup
     320: invokespecial #100                // Method java/lang/StringBuilder."<init>":()V
     323: aload         5
     325: invokevirtual #101                // Method org/apache/solr/client/solrj/io/graph/GatherNodesStream$NodeStream.toString:()Ljava/lang/String;
     328: invokevirtual #102                // Method java/lang/StringBuilder.append:(Ljava/lang/String;)Ljava/lang/StringBuilder;
     331: ldc           #47                 // String ->
     333: invokevirtual #102                // Method java/lang/StringBuilder.append:(Ljava/lang/String;)Ljava/lang/StringBuilder;
     336: aload_0
     337: getfield      #7                  // Field traverseTo:Ljava/lang/String;
     340: invokevirtual #102                // Method java/lang/StringBuilder.append:(Ljava/lang/String;)Ljava/lang/StringBuilder;
     343: invokevirtual #103                // Method java/lang/StringBuilder.toString:()Ljava/lang/String;
     346: invokespecial #96                 // Method org/apache/solr/client/solrj/io/stream/expr/StreamExpressionNamedParameter."<init>":(Ljava/lang/String;Ljava/lang/String;)V
     349: invokevirtual #85                 // Method org/apache/solr/client/solrj/io/stream/expr/StreamExpression.addParameter:(Lorg/apache/solr/client/solrj/io/stream/expr/StreamExpressionParameter;)V
     352: goto          397
     355: aload_3
     356: new           #67                 // class org/apache/solr/client/solrj/io/stream/expr/StreamExpressionNamedParameter
     359: dup
     360: ldc           #41                 // String walk
     362: new           #99                 // class java/lang/StringBuilder
     365: dup
     366: invokespecial #100                // Method java/lang/StringBuilder."<init>":()V
     369: aload_0
     370: getfield      #76                 // Field traverseFrom:Ljava/lang/String;
     373: invokevirtual #102                // Method java/lang/StringBuilder.append:(Ljava/lang/String;)Ljava/lang/StringBuilder;
     376: ldc           #47                 // String ->
     378: invokevirtual #102                // Method java/lang/StringBuilder.append:(Ljava/lang/String;)Ljava/lang/StringBuilder;
     381: aload_0
     382: getfield      #7                  // Field traverseTo:Ljava/lang/String;
     385: invokevirtual #102                // Method java/lang/StringBuilder.append:(Ljava/lang/String;)Ljava/lang/StringBuilder;
     388: invokevirtual #103                // Method java/lang/StringBuilder.toString:()Ljava/lang/String;
     391: invokespecial #96                 // Method org/apache/solr/client/solrj/io/stream/expr/StreamExpressionNamedParameter."<init>":(Ljava/lang/String;Ljava/lang/String;)V
     394: invokevirtual #85                 // Method org/apache/solr/client/solrj/io/stream/expr/StreamExpression.addParameter:(Lorg/apache/solr/client/solrj/io/stream/expr/StreamExpressionParameter;)V
     397: aload_3
     398: new           #67                 // class org/apache/solr/client/solrj/io/stream/expr/StreamExpressionNamedParameter
     401: dup
     402: ldc           #57                 // String trackTraversal
     404: aload_0
     405: getfield      #77                 // Field trackTraversal:Z
     408: invokestatic  #104                // Method java/lang/Boolean.toString:(Z)Ljava/lang/String;
     411: invokespecial #96                 // Method org/apache/solr/client/solrj/io/stream/expr/StreamExpressionNamedParameter."<init>":(Ljava/lang/String;Ljava/lang/String;)V
     414: invokevirtual #85                 // Method org/apache/solr/client/solrj/io/stream/expr/StreamExpression.addParameter:(Lorg/apache/solr/client/solrj/io/stream/expr/StreamExpressionParameter;)V
     417: new           #99                 // class java/lang/StringBuilder
     420: dup
     421: invokespecial #100                // Method java/lang/StringBuilder."<init>":()V
     424: astore        5
     426: aload_0
     427: getfield      #78                 // Field scatter:Ljava/util/Set;
     430: invokeinterface #89,  1           // InterfaceMethod java/util/Set.iterator:()Ljava/util/Iterator;
     435: astore        6
     437: aload         6
     439: invokeinterface #65,  1           // InterfaceMethod java/util/Iterator.hasNext:()Z
     444: ifeq          489
     447: aload         6
     449: invokeinterface #66,  1           // InterfaceMethod java/util/Iterator.next:()Ljava/lang/Object;
     454: checkcast     #105                // class org/apache/solr/client/solrj/io/graph/Traversal$Scatter
     457: astore        7
     459: aload         5
     461: invokevirtual #106                // Method java/lang/StringBuilder.length:()I
     464: ifle          475
     467: aload         5
     469: ldc           #33                 // String ,
     471: invokevirtual #102                // Method java/lang/StringBuilder.append:(Ljava/lang/String;)Ljava/lang/StringBuilder;
     474: pop
     475: aload         5
     477: aload         7
     479: invokevirtual #37                 // Method org/apache/solr/client/solrj/io/graph/Traversal$Scatter.toString:()Ljava/lang/String;
     482: invokevirtual #102                // Method java/lang/StringBuilder.append:(Ljava/lang/String;)Ljava/lang/StringBuilder;
     485: pop
     486: goto          437
     489: aload_3
     490: new           #67                 // class org/apache/solr/client/solrj/io/stream/expr/StreamExpressionNamedParameter
     493: dup
     494: ldc           #27                 // String scatter
     496: aload         5
     498: invokevirtual #103                // Method java/lang/StringBuilder.toString:()Ljava/lang/String;
     501: invokespecial #96                 // Method org/apache/solr/client/solrj/io/stream/expr/StreamExpressionNamedParameter."<init>":(Ljava/lang/String;Ljava/lang/String;)V
     504: invokevirtual #85                 // Method org/apache/solr/client/solrj/io/stream/expr/StreamExpression.addParameter:(Lorg/apache/solr/client/solrj/io/stream/expr/StreamExpressionParameter;)V
     507: aload_3
     508: areturn

  public org.apache.solr.client.solrj.io.stream.expr.Explanation toExplanation(org.apache.solr.client.solrj.io.stream.expr.StreamFactory) throws java.io.IOException;
    Code:
       0: new           #107                // class org/apache/solr/client/solrj/io/stream/expr/StreamExplanation
       3: dup
       4: aload_0
       5: invokevirtual #108                // Method getStreamNodeId:()Ljava/util/UUID;
       8: invokevirtual #109                // Method java/util/UUID.toString:()Ljava/lang/String;
      11: invokespecial #110                // Method org/apache/solr/client/solrj/io/stream/expr/StreamExplanation."<init>":(Ljava/lang/String;)V
      14: astore_2
      15: aload_2
      16: aload_1
      17: aload_0
      18: invokevirtual #80                 // Method java/lang/Object.getClass:()Ljava/lang/Class;
      21: invokevirtual #81                 // Method org/apache/solr/client/solrj/io/stream/expr/StreamFactory.getFunctionName:(Ljava/lang/Class;)Ljava/lang/String;
      24: invokevirtual #111                // Method org/apache/solr/client/solrj/io/stream/expr/StreamExplanation.setFunctionName:(Ljava/lang/String;)V
      27: aload_2
      28: aload_0
      29: invokevirtual #80                 // Method java/lang/Object.getClass:()Ljava/lang/Class;
      32: invokevirtual #112                // Method java/lang/Class.getName:()Ljava/lang/String;
      35: invokevirtual #113                // Method org/apache/solr/client/solrj/io/stream/expr/StreamExplanation.setImplementingClass:(Ljava/lang/String;)V
      38: aload_2
      39: ldc           #115                // String graph-source
      41: invokevirtual #116                // Method org/apache/solr/client/solrj/io/stream/expr/StreamExplanation.setExpressionType:(Ljava/lang/String;)V
      44: aload_2
      45: aload_0
      46: aload_1
      47: invokevirtual #117                // Method toExpression:(Lorg/apache/solr/client/solrj/io/stream/expr/StreamFactory;)Lorg/apache/solr/client/solrj/io/stream/expr/StreamExpression;
      50: invokevirtual #118                // Method org/apache/solr/client/solrj/io/stream/expr/StreamExpression.toString:()Ljava/lang/String;
      53: invokevirtual #119                // Method org/apache/solr/client/solrj/io/stream/expr/StreamExplanation.setExpression:(Ljava/lang/String;)V
      56: aload_2
      57: aload_0
      58: getfield      #75                 // Field tupleStream:Lorg/apache/solr/client/solrj/io/stream/TupleStream;
      61: aload_1
      62: invokevirtual #120                // Method org/apache/solr/client/solrj/io/stream/TupleStream.toExplanation:(Lorg/apache/solr/client/solrj/io/stream/expr/StreamFactory;)Lorg/apache/solr/client/solrj/io/stream/expr/Explanation;
      65: invokevirtual #121                // Method org/apache/solr/client/solrj/io/stream/expr/StreamExplanation.addChild:(Lorg/apache/solr/client/solrj/io/stream/expr/Explanation;)V
      68: new           #107                // class org/apache/solr/client/solrj/io/stream/expr/StreamExplanation
      71: dup
      72: new           #99                 // class java/lang/StringBuilder
      75: dup
      76: invokespecial #100                // Method java/lang/StringBuilder."<init>":()V
      79: aload_0
      80: invokevirtual #108                // Method getStreamNodeId:()Ljava/util/UUID;
      83: invokevirtual #122                // Method java/lang/StringBuilder.append:(Ljava/lang/Object;)Ljava/lang/StringBuilder;
      86: ldc           #123                // String -datastore
      88: invokevirtual #102                // Method java/lang/StringBuilder.append:(Ljava/lang/String;)Ljava/lang/StringBuilder;
      91: invokevirtual #103                // Method java/lang/StringBuilder.toString:()Ljava/lang/String;
      94: invokespecial #110                // Method org/apache/solr/client/solrj/io/stream/expr/StreamExplanation."<init>":(Ljava/lang/String;)V
      97: astore_3
      98: aload_3
      99: ldc           #124                // String solr (graph)
     101: invokevirtual #111                // Method org/apache/solr/client/solrj/io/stream/expr/StreamExplanation.setFunctionName:(Ljava/lang/String;)V
     104: aload_3
     105: ldc           #125                // String Solr/Lucene
     107: invokevirtual #113                // Method org/apache/solr/client/solrj/io/stream/expr/StreamExplanation.setImplementingClass:(Ljava/lang/String;)V
     110: aload_3
     111: ldc           #126                // String datastore
     113: invokevirtual #116                // Method org/apache/solr/client/solrj/io/stream/expr/StreamExplanation.setExpressionType:(Ljava/lang/String;)V
     116: aload_3
     117: aload_0
     118: getfield      #5                  // Field queryParams:Ljava/util/Map;
     121: invokeinterface #88,  1           // InterfaceMethod java/util/Map.entrySet:()Ljava/util/Set;
     126: invokeinterface #127,  1          // InterfaceMethod java/util/Set.stream:()Ljava/util/stream/Stream;
     131: invokedynamic #128,  0            // InvokeDynamic #0:apply:()Ljava/util/function/Function;
     136: invokeinterface #129,  2          // InterfaceMethod java/util/stream/Stream.map:(Ljava/util/function/Function;)Ljava/util/stream/Stream;
     141: ldc           #33                 // String ,
     143: invokestatic  #130                // Method java/util/stream/Collectors.joining:(Ljava/lang/CharSequence;)Ljava/util/stream/Collector;
     146: invokeinterface #131,  2          // InterfaceMethod java/util/stream/Stream.collect:(Ljava/util/stream/Collector;)Ljava/lang/Object;
     151: checkcast     #132                // class java/lang/String
     154: invokevirtual #119                // Method org/apache/solr/client/solrj/io/stream/expr/StreamExplanation.setExpression:(Ljava/lang/String;)V
     157: aload_2
     158: aload_3
     159: invokevirtual #121                // Method org/apache/solr/client/solrj/io/stream/expr/StreamExplanation.addChild:(Lorg/apache/solr/client/solrj/io/stream/expr/Explanation;)V
     162: aconst_null
     163: aload_0
     164: getfield      #6                  // Field metrics:Ljava/util/List;
     167: if_acmpeq     216
     170: aload_0
     171: getfield      #6                  // Field metrics:Ljava/util/List;
     174: invokeinterface #64,  1           // InterfaceMethod java/util/List.iterator:()Ljava/util/Iterator;
     179: astore        4
     181: aload         4
     183: invokeinterface #65,  1           // InterfaceMethod java/util/Iterator.hasNext:()Z
     188: ifeq          216
     191: aload         4
     193: invokeinterface #66,  1           // InterfaceMethod java/util/Iterator.next:()Ljava/lang/Object;
     198: checkcast     #55                 // class org/apache/solr/client/solrj/io/stream/metrics/Metric
     201: astore        5
     203: aload_2
     204: aload         5
     206: aload_1
     207: invokevirtual #133                // Method org/apache/solr/client/solrj/io/stream/metrics/Metric.toExplanation:(Lorg/apache/solr/client/solrj/io/stream/expr/StreamFactory;)Lorg/apache/solr/client/solrj/io/stream/expr/Explanation;
     210: invokevirtual #134                // Method org/apache/solr/client/solrj/io/stream/expr/StreamExplanation.addHelper:(Lorg/apache/solr/client/solrj/io/stream/expr/Explanation;)V
     213: goto          181
     216: aload_2
     217: areturn

  public void setStreamContext(org.apache.solr.client.solrj.io.stream.StreamContext);
    Code:
       0: aload_0
       1: aload_1
       2: ldc           #135                // String traversal
       4: invokevirtual #136                // Method org/apache/solr/client/solrj/io/stream/StreamContext.get:(Ljava/lang/Object;)Ljava/lang/Object;
       7: checkcast     #137                // class org/apache/solr/client/solrj/io/graph/Traversal
      10: putfield      #138                // Field traversal:Lorg/apache/solr/client/solrj/io/graph/Traversal;
      13: aload_0
      14: getfield      #138                // Field traversal:Lorg/apache/solr/client/solrj/io/graph/Traversal;
      17: ifnonnull     144
      20: new           #139                // class org/apache/solr/client/solrj/io/stream/StreamContext
      23: dup
      24: invokespecial #140                // Method org/apache/solr/client/solrj/io/stream/StreamContext."<init>":()V
      27: astore_2
      28: aload_2
      29: aload_1
      30: getfield      #141                // Field org/apache/solr/client/solrj/io/stream/StreamContext.numWorkers:I
      33: putfield      #141                // Field org/apache/solr/client/solrj/io/stream/StreamContext.numWorkers:I
      36: aload_2
      37: aload_1
      38: getfield      #142                // Field org/apache/solr/client/solrj/io/stream/StreamContext.workerID:I
      41: putfield      #142                // Field org/apache/solr/client/solrj/io/stream/StreamContext.workerID:I
      44: aload_2
      45: aload_1
      46: invokevirtual #143                // Method org/apache/solr/client/solrj/io/stream/StreamContext.getSolrClientCache:()Lorg/apache/solr/client/solrj/io/SolrClientCache;
      49: invokevirtual #144                // Method org/apache/solr/client/solrj/io/stream/StreamContext.setSolrClientCache:(Lorg/apache/solr/client/solrj/io/SolrClientCache;)V
      52: aload_2
      53: aload_1
      54: invokevirtual #145                // Method org/apache/solr/client/solrj/io/stream/StreamContext.getStreamFactory:()Lorg/apache/solr/client/solrj/io/stream/expr/StreamFactory;
      57: invokevirtual #146                // Method org/apache/solr/client/solrj/io/stream/StreamContext.setStreamFactory:(Lorg/apache/solr/client/solrj/io/stream/expr/StreamFactory;)V
      60: aload_1
      61: invokevirtual #147                // Method org/apache/solr/client/solrj/io/stream/StreamContext.getEntries:()Ljava/util/Map;
      64: invokeinterface #148,  1          // InterfaceMethod java/util/Map.keySet:()Ljava/util/Set;
      69: invokeinterface #89,  1           // InterfaceMethod java/util/Set.iterator:()Ljava/util/Iterator;
      74: astore_3
      75: aload_3
      76: invokeinterface #65,  1           // InterfaceMethod java/util/Iterator.hasNext:()Z
      81: ifeq          107
      84: aload_3
      85: invokeinterface #66,  1           // InterfaceMethod java/util/Iterator.next:()Ljava/lang/Object;
      90: astore        4
      92: aload_2
      93: aload         4
      95: aload_1
      96: aload         4
      98: invokevirtual #136                // Method org/apache/solr/client/solrj/io/stream/StreamContext.get:(Ljava/lang/Object;)Ljava/lang/Object;
     101: invokevirtual #149                // Method org/apache/solr/client/solrj/io/stream/StreamContext.put:(Ljava/lang/Object;Ljava/lang/Object;)V
     104: goto          75
     107: aload_0
     108: new           #137                // class org/apache/solr/client/solrj/io/graph/Traversal
     111: dup
     112: invokespecial #150                // Method org/apache/solr/client/solrj/io/graph/Traversal."<init>":()V
     115: putfield      #138                // Field traversal:Lorg/apache/solr/client/solrj/io/graph/Traversal;
     118: aload_2
     119: ldc           #135                // String traversal
     121: aload_0
     122: getfield      #138                // Field traversal:Lorg/apache/solr/client/solrj/io/graph/Traversal;
     125: invokevirtual #149                // Method org/apache/solr/client/solrj/io/stream/StreamContext.put:(Ljava/lang/Object;Ljava/lang/Object;)V
     128: aload_0
     129: getfield      #75                 // Field tupleStream:Lorg/apache/solr/client/solrj/io/stream/TupleStream;
     132: aload_2
     133: invokevirtual #151                // Method org/apache/solr/client/solrj/io/stream/TupleStream.setStreamContext:(Lorg/apache/solr/client/solrj/io/stream/StreamContext;)V
     136: aload_0
     137: aload_2
     138: putfield      #1                  // Field streamContext:Lorg/apache/solr/client/solrj/io/stream/StreamContext;
     141: goto          157
     144: aload_0
     145: getfield      #75                 // Field tupleStream:Lorg/apache/solr/client/solrj/io/stream/TupleStream;
     148: aload_1
     149: invokevirtual #151                // Method org/apache/solr/client/solrj/io/stream/TupleStream.setStreamContext:(Lorg/apache/solr/client/solrj/io/stream/StreamContext;)V
     152: aload_0
     153: aload_1
     154: putfield      #1                  // Field streamContext:Lorg/apache/solr/client/solrj/io/stream/StreamContext;
     157: return

  public java.util.List<org.apache.solr.client.solrj.io.stream.TupleStream> children();
    Code:
       0: new           #49                 // class java/util/ArrayList
       3: dup
       4: invokespecial #50                 // Method java/util/ArrayList."<init>":()V
       7: astore_1
       8: aload_1
       9: aload_0
      10: getfield      #75                 // Field tupleStream:Lorg/apache/solr/client/solrj/io/stream/TupleStream;
      13: invokeinterface #51,  2           // InterfaceMethod java/util/List.add:(Ljava/lang/Object;)Z
      18: pop
      19: aload_1
      20: areturn

  public void open() throws java.io.IOException;
    Code:
       0: aload_0
       1: getfield      #75                 // Field tupleStream:Lorg/apache/solr/client/solrj/io/stream/TupleStream;
       4: invokevirtual #152                // Method org/apache/solr/client/solrj/io/stream/TupleStream.open:()V
       7: return

  public void close() throws java.io.IOException;
    Code:
       0: aload_0
       1: getfield      #75                 // Field tupleStream:Lorg/apache/solr/client/solrj/io/stream/TupleStream;
       4: invokevirtual #153                // Method org/apache/solr/client/solrj/io/stream/TupleStream.close:()V
       7: return

  public org.apache.solr.client.solrj.io.Tuple read() throws java.io.IOException;
    Code:
       0: aload_0
       1: getfield      #154                // Field out:Ljava/util/Iterator;
       4: ifnonnull     816
       7: new           #49                 // class java/util/ArrayList
      10: dup
      11: invokespecial #50                 // Method java/util/ArrayList."<init>":()V
      14: astore_1
      15: new           #49                 // class java/util/ArrayList
      18: dup
      19: invokespecial #50                 // Method java/util/ArrayList."<init>":()V
      22: astore_2
      23: new           #62                 // class java/util/HashMap
      26: dup
      27: invokespecial #63                 // Method java/util/HashMap."<init>":()V
      30: astore_3
      31: aconst_null
      32: astore        4
      34: iconst_4
      35: new           #155                // class org/apache/solr/common/util/SolrjNamedThreadFactory
      38: dup
      39: ldc           #156                // String GatherNodesStream
      41: invokespecial #157                // Method org/apache/solr/common/util/SolrjNamedThreadFactory."<init>":(Ljava/lang/String;)V
      44: invokestatic  #158                // Method org/apache/solr/common/util/ExecutorUtil.newMDCAwareFixedThreadPool:(ILjava/util/concurrent/ThreadFactory;)Ljava/util/concurrent/ExecutorService;
      47: astore        4
      49: new           #62                 // class java/util/HashMap
      52: dup
      53: invokespecial #63                 // Method java/util/HashMap."<init>":()V
      56: astore        5
      58: aload_0
      59: getfield      #75                 // Field tupleStream:Lorg/apache/solr/client/solrj/io/stream/TupleStream;
      62: invokevirtual #159                // Method org/apache/solr/client/solrj/io/stream/TupleStream.read:()Lorg/apache/solr/client/solrj/io/Tuple;
      65: astore        6
      67: aload         6
      69: getfield      #160                // Field org/apache/solr/client/solrj/io/Tuple.EOF:Z
      72: ifeq          118
      75: aload_1
      76: invokeinterface #43,  1           // InterfaceMethod java/util/List.size:()I
      81: ifle          342
      84: new           #161                // class org/apache/solr/client/solrj/io/graph/GatherNodesStream$JoinRunner
      87: dup
      88: aload_0
      89: aload_1
      90: invokespecial #162                // Method org/apache/solr/client/solrj/io/graph/GatherNodesStream$JoinRunner."<init>":(Lorg/apache/solr/client/solrj/io/graph/GatherNodesStream;Ljava/util/List;)V
      93: astore        7
      95: aload         4
      97: aload         7
      99: invokeinterface #163,  2          // InterfaceMethod java/util/concurrent/ExecutorService.submit:(Ljava/util/concurrent/Callable;)Ljava/util/concurrent/Future;
     104: astore        8
     106: aload_2
     107: aload         8
     109: invokeinterface #51,  2           // InterfaceMethod java/util/List.add:(Ljava/lang/Object;)Z
     114: pop
     115: goto          342
     118: aload         6
     120: aload_0
     121: getfield      #76                 // Field traverseFrom:Ljava/lang/String;
     124: invokevirtual #164                // Method org/apache/solr/client/solrj/io/Tuple.getString:(Ljava/lang/Object;)Ljava/lang/String;
     127: astore        7
     129: aload_0
     130: getfield      #138                // Field traversal:Lorg/apache/solr/client/solrj/io/graph/Traversal;
     133: invokevirtual #165                // Method org/apache/solr/client/solrj/io/graph/Traversal.getDepth:()I
     136: ifne          279
     139: new           #99                 // class java/lang/StringBuilder
     142: dup
     143: invokespecial #100                // Method java/lang/StringBuilder."<init>":()V
     146: aload_0
     147: getfield      #2                  // Field collection:Ljava/lang/String;
     150: invokevirtual #102                // Method java/lang/StringBuilder.append:(Ljava/lang/String;)Ljava/lang/StringBuilder;
     153: ldc           #166                // String .
     155: invokevirtual #102                // Method java/lang/StringBuilder.append:(Ljava/lang/String;)Ljava/lang/StringBuilder;
     158: aload         7
     160: invokevirtual #102                // Method java/lang/StringBuilder.append:(Ljava/lang/String;)Ljava/lang/StringBuilder;
     163: invokevirtual #103                // Method java/lang/StringBuilder.toString:()Ljava/lang/String;
     166: astore        8
     168: aload         5
     170: aload         8
     172: invokeinterface #167,  2          // InterfaceMethod java/util/Map.containsKey:(Ljava/lang/Object;)Z
     177: ifne          58
     180: new           #168                // class org/apache/solr/client/solrj/io/graph/Node
     183: dup
     184: aload         7
     186: aload_0
     187: getfield      #77                 // Field trackTraversal:Z
     190: invokespecial #169                // Method org/apache/solr/client/solrj/io/graph/Node."<init>":(Ljava/lang/String;Z)V
     193: astore        9
     195: aload_0
     196: getfield      #6                  // Field metrics:Ljava/util/List;
     199: ifnull        267
     202: new           #49                 // class java/util/ArrayList
     205: dup
     206: invokespecial #50                 // Method java/util/ArrayList."<init>":()V
     209: astore        10
     211: aload_0
     212: getfield      #6                  // Field metrics:Ljava/util/List;
     215: invokeinterface #64,  1           // InterfaceMethod java/util/List.iterator:()Ljava/util/Iterator;
     220: astore        11
     222: aload         11
     224: invokeinterface #65,  1           // InterfaceMethod java/util/Iterator.hasNext:()Z
     229: ifeq          260
     232: aload         11
     234: invokeinterface #66,  1           // InterfaceMethod java/util/Iterator.next:()Ljava/lang/Object;
     239: checkcast     #55                 // class org/apache/solr/client/solrj/io/stream/metrics/Metric
     242: astore        12
     244: aload         10
     246: aload         12
     248: invokevirtual #170                // Method org/apache/solr/client/solrj/io/stream/metrics/Metric.newInstance:()Lorg/apache/solr/client/solrj/io/stream/metrics/Metric;
     251: invokeinterface #51,  2           // InterfaceMethod java/util/List.add:(Ljava/lang/Object;)Z
     256: pop
     257: goto          222
     260: aload         9
     262: aload         10
     264: invokevirtual #171                // Method org/apache/solr/client/solrj/io/graph/Node.setMetrics:(Ljava/util/List;)V
     267: aload         5
     269: aload         8
     271: aload         9
     273: invokeinterface #71,  3           // InterfaceMethod java/util/Map.put:(Ljava/lang/Object;Ljava/lang/Object;)Ljava/lang/Object;
     278: pop
     279: aload_1
     280: aload         7
     282: invokeinterface #51,  2           // InterfaceMethod java/util/List.add:(Ljava/lang/Object;)Z
     287: pop
     288: aload_1
     289: invokeinterface #43,  1           // InterfaceMethod java/util/List.size:()I
     294: sipush        400
     297: if_icmpne     339
     300: new           #161                // class org/apache/solr/client/solrj/io/graph/GatherNodesStream$JoinRunner
     303: dup
     304: aload_0
     305: aload_1
     306: invokespecial #162                // Method org/apache/solr/client/solrj/io/graph/GatherNodesStream$JoinRunner."<init>":(Lorg/apache/solr/client/solrj/io/graph/GatherNodesStream;Ljava/util/List;)V
     309: astore        8
     311: aload         4
     313: aload         8
     315: invokeinterface #163,  2          // InterfaceMethod java/util/concurrent/ExecutorService.submit:(Ljava/util/concurrent/Callable;)Ljava/util/concurrent/Future;
     320: astore        9
     322: aload_2
     323: aload         9
     325: invokeinterface #51,  2           // InterfaceMethod java/util/List.add:(Ljava/lang/Object;)Z
     330: pop
     331: new           #49                 // class java/util/ArrayList
     334: dup
     335: invokespecial #50                 // Method java/util/ArrayList."<init>":()V
     338: astore_1
     339: goto          58
     342: aload_0
     343: getfield      #138                // Field traversal:Lorg/apache/solr/client/solrj/io/graph/Traversal;
     346: invokevirtual #165                // Method org/apache/solr/client/solrj/io/graph/Traversal.getDepth:()I
     349: ifne          369
     352: aload_0
     353: getfield      #138                // Field traversal:Lorg/apache/solr/client/solrj/io/graph/Traversal;
     356: aload         5
     358: aload_0
     359: getfield      #2                  // Field collection:Ljava/lang/String;
     362: aload_0
     363: getfield      #76                 // Field traverseFrom:Ljava/lang/String;
     366: invokevirtual #172                // Method org/apache/solr/client/solrj/io/graph/Traversal.addLevel:(Ljava/util/Map;Ljava/lang/String;Ljava/lang/String;)V
     369: aload_0
     370: getfield      #138                // Field traversal:Lorg/apache/solr/client/solrj/io/graph/Traversal;
     373: aload_0
     374: getfield      #78                 // Field scatter:Ljava/util/Set;
     377: invokevirtual #173                // Method org/apache/solr/client/solrj/io/graph/Traversal.setScatter:(Ljava/util/Set;)V
     380: aload_0
     381: getfield      #59                 // Field useDefaultTraversal:Z
     384: ifeq          401
     387: aload_0
     388: aload_0
     389: getfield      #138                // Field traversal:Lorg/apache/solr/client/solrj/io/graph/Traversal;
     392: invokevirtual #174                // Method org/apache/solr/client/solrj/io/graph/Traversal.getTrackTraversal:()Z
     395: putfield      #77                 // Field trackTraversal:Z
     398: goto          412
     401: aload_0
     402: getfield      #138                // Field traversal:Lorg/apache/solr/client/solrj/io/graph/Traversal;
     405: aload_0
     406: getfield      #77                 // Field trackTraversal:Z
     409: invokevirtual #175                // Method org/apache/solr/client/solrj/io/graph/Traversal.setTrackTraversal:(Z)V
     412: aload_2
     413: invokeinterface #64,  1           // InterfaceMethod java/util/List.iterator:()Ljava/util/Iterator;
     418: astore        6
     420: aload         6
     422: invokeinterface #65,  1           // InterfaceMethod java/util/Iterator.hasNext:()Z
     427: ifeq          755
     430: aload         6
     432: invokeinterface #66,  1           // InterfaceMethod java/util/Iterator.next:()Ljava/lang/Object;
     437: checkcast     #176                // class java/util/concurrent/Future
     440: astore        7
     442: aload         7
     444: invokeinterface #177,  1          // InterfaceMethod java/util/concurrent/Future.get:()Ljava/lang/Object;
     449: checkcast     #178                // class java/util/List
     452: astore        8
     454: aload         8
     456: invokeinterface #64,  1           // InterfaceMethod java/util/List.iterator:()Ljava/util/Iterator;
     461: astore        9
     463: aload         9
     465: invokeinterface #65,  1           // InterfaceMethod java/util/Iterator.hasNext:()Z
     470: ifeq          752
     473: aload         9
     475: invokeinterface #66,  1           // InterfaceMethod java/util/Iterator.next:()Ljava/lang/Object;
     480: checkcast     #179                // class org/apache/solr/client/solrj/io/Tuple
     483: astore        10
     485: aload         10
     487: aload_0
     488: getfield      #7                  // Field traverseTo:Ljava/lang/String;
     491: invokevirtual #164                // Method org/apache/solr/client/solrj/io/Tuple.getString:(Ljava/lang/Object;)Ljava/lang/String;
     494: astore        11
     496: aload         10
     498: aload_0
     499: getfield      #8                  // Field gather:Ljava/lang/String;
     502: invokevirtual #164                // Method org/apache/solr/client/solrj/io/Tuple.getString:(Ljava/lang/Object;)Ljava/lang/String;
     505: astore        12
     507: new           #99                 // class java/lang/StringBuilder
     510: dup
     511: invokespecial #100                // Method java/lang/StringBuilder."<init>":()V
     514: aload_0
     515: getfield      #2                  // Field collection:Ljava/lang/String;
     518: invokevirtual #102                // Method java/lang/StringBuilder.append:(Ljava/lang/String;)Ljava/lang/StringBuilder;
     521: ldc           #166                // String .
     523: invokevirtual #102                // Method java/lang/StringBuilder.append:(Ljava/lang/String;)Ljava/lang/StringBuilder;
     526: aload         12
     528: invokevirtual #102                // Method java/lang/StringBuilder.append:(Ljava/lang/String;)Ljava/lang/StringBuilder;
     531: invokevirtual #103                // Method java/lang/StringBuilder.toString:()Ljava/lang/String;
     534: astore        13
     536: aload_0
     537: getfield      #138                // Field traversal:Lorg/apache/solr/client/solrj/io/graph/Traversal;
     540: aload         13
     542: aload         11
     544: aload         10
     546: invokevirtual #180                // Method org/apache/solr/client/solrj/io/graph/Traversal.visited:(Ljava/lang/String;Ljava/lang/String;Lorg/apache/solr/client/solrj/io/Tuple;)Z
     549: ifne          749
     552: aload_3
     553: aload         13
     555: invokeinterface #181,  2          // InterfaceMethod java/util/Map.get:(Ljava/lang/Object;)Ljava/lang/Object;
     560: checkcast     #168                // class org/apache/solr/client/solrj/io/graph/Node
     563: astore        14
     565: aload         14
     567: ifnull        612
     570: aload         14
     572: new           #99                 // class java/lang/StringBuilder
     575: dup
     576: invokespecial #100                // Method java/lang/StringBuilder."<init>":()V
     579: aload_0
     580: getfield      #138                // Field traversal:Lorg/apache/solr/client/solrj/io/graph/Traversal;
     583: invokevirtual #165                // Method org/apache/solr/client/solrj/io/graph/Traversal.getDepth:()I
     586: iconst_1
     587: isub
     588: invokevirtual #182                // Method java/lang/StringBuilder.append:(I)Ljava/lang/StringBuilder;
     591: ldc           #183                // String ^
     593: invokevirtual #102                // Method java/lang/StringBuilder.append:(Ljava/lang/String;)Ljava/lang/StringBuilder;
     596: aload         11
     598: invokevirtual #102                // Method java/lang/StringBuilder.append:(Ljava/lang/String;)Ljava/lang/StringBuilder;
     601: invokevirtual #103                // Method java/lang/StringBuilder.toString:()Ljava/lang/String;
     604: aload         10
     606: invokevirtual #184                // Method org/apache/solr/client/solrj/io/graph/Node.add:(Ljava/lang/String;Lorg/apache/solr/client/solrj/io/Tuple;)V
     609: goto          749
     612: new           #168                // class org/apache/solr/client/solrj/io/graph/Node
     615: dup
     616: aload         12
     618: aload_0
     619: getfield      #77                 // Field trackTraversal:Z
     622: invokespecial #169                // Method org/apache/solr/client/solrj/io/graph/Node."<init>":(Ljava/lang/String;Z)V
     625: astore        14
     627: aload_0
     628: getfield      #6                  // Field metrics:Ljava/util/List;
     631: ifnull        699
     634: new           #49                 // class java/util/ArrayList
     637: dup
     638: invokespecial #50                 // Method java/util/ArrayList."<init>":()V
     641: astore        15
     643: aload_0
     644: getfield      #6                  // Field metrics:Ljava/util/List;
     647: invokeinterface #64,  1           // InterfaceMethod java/util/List.iterator:()Ljava/util/Iterator;
     652: astore        16
     654: aload         16
     656: invokeinterface #65,  1           // InterfaceMethod java/util/Iterator.hasNext:()Z
     661: ifeq          692
     664: aload         16
     666: invokeinterface #66,  1           // InterfaceMethod java/util/Iterator.next:()Ljava/lang/Object;
     671: checkcast     #55                 // class org/apache/solr/client/solrj/io/stream/metrics/Metric
     674: astore        17
     676: aload         15
     678: aload         17
     680: invokevirtual #170                // Method org/apache/solr/client/solrj/io/stream/metrics/Metric.newInstance:()Lorg/apache/solr/client/solrj/io/stream/metrics/Metric;
     683: invokeinterface #51,  2           // InterfaceMethod java/util/List.add:(Ljava/lang/Object;)Z
     688: pop
     689: goto          654
     692: aload         14
     694: aload         15
     696: invokevirtual #171                // Method org/apache/solr/client/solrj/io/graph/Node.setMetrics:(Ljava/util/List;)V
     699: aload         14
     701: new           #99                 // class java/lang/StringBuilder
     704: dup
     705: invokespecial #100                // Method java/lang/StringBuilder."<init>":()V
     708: aload_0
     709: getfield      #138                // Field traversal:Lorg/apache/solr/client/solrj/io/graph/Traversal;
     712: invokevirtual #165                // Method org/apache/solr/client/solrj/io/graph/Traversal.getDepth:()I
     715: iconst_1
     716: isub
     717: invokevirtual #182                // Method java/lang/StringBuilder.append:(I)Ljava/lang/StringBuilder;
     720: ldc           #183                // String ^
     722: invokevirtual #102                // Method java/lang/StringBuilder.append:(Ljava/lang/String;)Ljava/lang/StringBuilder;
     725: aload         11
     727: invokevirtual #102                // Method java/lang/StringBuilder.append:(Ljava/lang/String;)Ljava/lang/StringBuilder;
     730: invokevirtual #103                // Method java/lang/StringBuilder.toString:()Ljava/lang/String;
     733: aload         10
     735: invokevirtual #184                // Method org/apache/solr/client/solrj/io/graph/Node.add:(Ljava/lang/String;Lorg/apache/solr/client/solrj/io/Tuple;)V
     738: aload_3
     739: aload         13
     741: aload         14
     743: invokeinterface #71,  3           // InterfaceMethod java/util/Map.put:(Ljava/lang/Object;Ljava/lang/Object;)Ljava/lang/Object;
     748: pop
     749: goto          463
     752: goto          420
     755: aload_0
     756: getfield      #138                // Field traversal:Lorg/apache/solr/client/solrj/io/graph/Traversal;
     759: aload_3
     760: aload_0
     761: getfield      #2                  // Field collection:Ljava/lang/String;
     764: aload_0
     765: getfield      #8                  // Field gather:Ljava/lang/String;
     768: invokevirtual #172                // Method org/apache/solr/client/solrj/io/graph/Traversal.addLevel:(Ljava/util/Map;Ljava/lang/String;Ljava/lang/String;)V
     771: aload_0
     772: aload_0
     773: getfield      #138                // Field traversal:Lorg/apache/solr/client/solrj/io/graph/Traversal;
     776: invokevirtual #185                // Method org/apache/solr/client/solrj/io/graph/Traversal.iterator:()Ljava/util/Iterator;
     779: putfield      #154                // Field out:Ljava/util/Iterator;
     782: aload         4
     784: invokeinterface #186,  1          // InterfaceMethod java/util/concurrent/ExecutorService.shutdown:()V
     789: goto          816
     792: astore        5
     794: new           #188                // class java/lang/RuntimeException
     797: dup
     798: aload         5
     800: invokespecial #189                // Method java/lang/RuntimeException."<init>":(Ljava/lang/Throwable;)V
     803: athrow
     804: astore        18
     806: aload         4
     808: invokeinterface #186,  1          // InterfaceMethod java/util/concurrent/ExecutorService.shutdown:()V
     813: aload         18
     815: athrow
     816: aload_0
     817: getfield      #154                // Field out:Ljava/util/Iterator;
     820: invokeinterface #65,  1           // InterfaceMethod java/util/Iterator.hasNext:()Z
     825: ifeq          841
     828: aload_0
     829: getfield      #154                // Field out:Ljava/util/Iterator;
     832: invokeinterface #66,  1           // InterfaceMethod java/util/Iterator.next:()Ljava/lang/Object;
     837: checkcast     #179                // class org/apache/solr/client/solrj/io/Tuple
     840: areturn
     841: new           #62                 // class java/util/HashMap
     844: dup
     845: invokespecial #63                 // Method java/util/HashMap."<init>":()V
     848: astore_1
     849: aload_1
     850: ldc           #190                // String EOF
     852: iconst_1
     853: invokestatic  #191                // Method java/lang/Boolean.valueOf:(Z)Ljava/lang/Boolean;
     856: invokeinterface #71,  3           // InterfaceMethod java/util/Map.put:(Ljava/lang/Object;Ljava/lang/Object;)Ljava/lang/Object;
     861: pop
     862: new           #179                // class org/apache/solr/client/solrj/io/Tuple
     865: dup
     866: aload_1
     867: invokespecial #192                // Method org/apache/solr/client/solrj/io/Tuple."<init>":(Ljava/util/Map;)V
     870: astore_2
     871: aload_2
     872: areturn
    Exception table:
       from    to  target type
          34   782   792   Class java/lang/Exception
          34   782   804   any
         792   806   804   any

  public int getCost();
    Code:
       0: iconst_0
       1: ireturn

  public org.apache.solr.client.solrj.io.comp.StreamComparator getStreamSort();
    Code:
       0: aconst_null
       1: areturn

  public org.apache.solr.client.solrj.io.stream.expr.StreamExpressionParameter toExpression(org.apache.solr.client.solrj.io.stream.expr.StreamFactory) throws java.io.IOException;
    Code:
       0: aload_0
       1: aload_1
       2: invokevirtual #117                // Method toExpression:(Lorg/apache/solr/client/solrj/io/stream/expr/StreamFactory;)Lorg/apache/solr/client/solrj/io/stream/expr/StreamExpression;
       5: areturn

  private static java.lang.String lambda$toExplanation$0(java.util.Map$Entry);
    Code:
       0: getstatic     #20                 // Field java/util/Locale.ROOT:Ljava/util/Locale;
       3: ldc           #193                // String %s=%s
       5: iconst_2
       6: anewarray     #22                 // class java/lang/Object
       9: dup
      10: iconst_0
      11: aload_0
      12: invokeinterface #95,  1           // InterfaceMethod java/util/Map$Entry.getKey:()Ljava/lang/Object;
      17: aastore
      18: dup
      19: iconst_1
      20: aload_0
      21: invokeinterface #91,  1           // InterfaceMethod java/util/Map$Entry.getValue:()Ljava/lang/Object;
      26: aastore
      27: invokestatic  #23                 // Method java/lang/String.format:(Ljava/util/Locale;Ljava/lang/String;[Ljava/lang/Object;)Ljava/lang/String;
      30: areturn

  static java.lang.String access$000(org.apache.solr.client.solrj.io.graph.GatherNodesStream);
    Code:
       0: aload_0
       1: getfield      #8                  // Field gather:Ljava/lang/String;
       4: areturn

  static java.lang.String access$100(org.apache.solr.client.solrj.io.graph.GatherNodesStream);
    Code:
       0: aload_0
       1: getfield      #7                  // Field traverseTo:Ljava/lang/String;
       4: areturn

  static java.util.List access$200(org.apache.solr.client.solrj.io.graph.GatherNodesStream);
    Code:
       0: aload_0
       1: getfield      #6                  // Field metrics:Ljava/util/List;
       4: areturn

  static java.util.Map access$300(org.apache.solr.client.solrj.io.graph.GatherNodesStream);
    Code:
       0: aload_0
       1: getfield      #5                  // Field queryParams:Ljava/util/Map;
       4: areturn

  static int access$400(org.apache.solr.client.solrj.io.graph.GatherNodesStream);
    Code:
       0: aload_0
       1: getfield      #4                  // Field maxDocFreq:I
       4: ireturn

  static java.lang.String access$500(org.apache.solr.client.solrj.io.graph.GatherNodesStream);
    Code:
       0: aload_0
       1: getfield      #3                  // Field zkHost:Ljava/lang/String;
       4: areturn

  static java.lang.String access$600(org.apache.solr.client.solrj.io.graph.GatherNodesStream);
    Code:
       0: aload_0
       1: getfield      #2                  // Field collection:Ljava/lang/String;
       4: areturn

  static org.apache.solr.client.solrj.io.stream.StreamContext access$700(org.apache.solr.client.solrj.io.graph.GatherNodesStream);
    Code:
       0: aload_0
       1: getfield      #1                  // Field streamContext:Lorg/apache/solr/client/solrj/io/stream/StreamContext;
       4: areturn
}
