Compiled from "ListAppAssessmentsOperationSerializer.kt"
final class aws.sdk.kotlin.services.resiliencehub.transform.ListAppAssessmentsOperationSerializer$serialize$2$1 extends kotlin.jvm.internal.Lambda implements kotlin.jvm.functions.Function1<aws.smithy.kotlin.runtime.http.QueryParametersBuilder, kotlin.Unit> {
  final aws.sdk.kotlin.services.resiliencehub.model.ListAppAssessmentsRequest $input;

  aws.sdk.kotlin.services.resiliencehub.transform.ListAppAssessmentsOperationSerializer$serialize$2$1(aws.sdk.kotlin.services.resiliencehub.model.ListAppAssessmentsRequest);
    Code:
       0: aload_0
       1: aload_1
       2: putfield      #13                 // Field $input:Laws/sdk/kotlin/services/resiliencehub/model/ListAppAssessmentsRequest;
       5: aload_0
       6: iconst_1
       7: invokespecial #16                 // Method kotlin/jvm/internal/Lambda."<init>":(I)V
      10: return

  public final void invoke(aws.smithy.kotlin.runtime.http.QueryParametersBuilder);
    Code:
       0: aload_1
       1: ldc           #23                 // String $this$parameters
       3: invokestatic  #29                 // Method kotlin/jvm/internal/Intrinsics.checkNotNullParameter:(Ljava/lang/Object;Ljava/lang/String;)V
       6: aload_0
       7: getfield      #13                 // Field $input:Laws/sdk/kotlin/services/resiliencehub/model/ListAppAssessmentsRequest;
      10: invokevirtual #35                 // Method aws/sdk/kotlin/services/resiliencehub/model/ListAppAssessmentsRequest.getAppArn:()Ljava/lang/String;
      13: ifnull        29
      16: aload_1
      17: ldc           #37                 // String appArn
      19: aload_0
      20: getfield      #13                 // Field $input:Laws/sdk/kotlin/services/resiliencehub/model/ListAppAssessmentsRequest;
      23: invokevirtual #35                 // Method aws/sdk/kotlin/services/resiliencehub/model/ListAppAssessmentsRequest.getAppArn:()Ljava/lang/String;
      26: invokevirtual #43                 // Method aws/smithy/kotlin/runtime/http/QueryParametersBuilder.append:(Ljava/lang/String;Ljava/lang/String;)V
      29: aload_0
      30: getfield      #13                 // Field $input:Laws/sdk/kotlin/services/resiliencehub/model/ListAppAssessmentsRequest;
      33: invokevirtual #46                 // Method aws/sdk/kotlin/services/resiliencehub/model/ListAppAssessmentsRequest.getAssessmentName:()Ljava/lang/String;
      36: ifnull        52
      39: aload_1
      40: ldc           #48                 // String assessmentName
      42: aload_0
      43: getfield      #13                 // Field $input:Laws/sdk/kotlin/services/resiliencehub/model/ListAppAssessmentsRequest;
      46: invokevirtual #46                 // Method aws/sdk/kotlin/services/resiliencehub/model/ListAppAssessmentsRequest.getAssessmentName:()Ljava/lang/String;
      49: invokevirtual #43                 // Method aws/smithy/kotlin/runtime/http/QueryParametersBuilder.append:(Ljava/lang/String;Ljava/lang/String;)V
      52: aload_0
      53: getfield      #13                 // Field $input:Laws/sdk/kotlin/services/resiliencehub/model/ListAppAssessmentsRequest;
      56: invokevirtual #52                 // Method aws/sdk/kotlin/services/resiliencehub/model/ListAppAssessmentsRequest.getAssessmentStatus:()Ljava/util/List;
      59: dup
      60: ifnull        91
      63: checkcast     #54                 // class java/util/Collection
      66: invokeinterface #58,  1           // InterfaceMethod java/util/Collection.isEmpty:()Z
      71: ifne          78
      74: iconst_1
      75: goto          79
      78: iconst_0
      79: iconst_1
      80: if_icmpne     87
      83: iconst_1
      84: goto          93
      87: iconst_0
      88: goto          93
      91: pop
      92: iconst_0
      93: ifeq          219
      96: aload_1
      97: ldc           #60                 // String assessmentStatus
      99: aload_0
     100: getfield      #13                 // Field $input:Laws/sdk/kotlin/services/resiliencehub/model/ListAppAssessmentsRequest;
     103: invokevirtual #52                 // Method aws/sdk/kotlin/services/resiliencehub/model/ListAppAssessmentsRequest.getAssessmentStatus:()Ljava/util/List;
     106: checkcast     #62                 // class java/lang/Iterable
     109: astore_2
     110: astore        12
     112: astore        11
     114: iconst_0
     115: istore_3
     116: aload_2
     117: astore        4
     119: new           #64                 // class java/util/ArrayList
     122: dup
     123: aload_2
     124: bipush        10
     126: invokestatic  #70                 // Method kotlin/collections/CollectionsKt.collectionSizeOrDefault:(Ljava/lang/Iterable;I)I
     129: invokespecial #71                 // Method java/util/ArrayList."<init>":(I)V
     132: checkcast     #54                 // class java/util/Collection
     135: astore        5
     137: iconst_0
     138: istore        6
     140: aload         4
     142: invokeinterface #75,  1           // InterfaceMethod java/lang/Iterable.iterator:()Ljava/util/Iterator;
     147: astore        7
     149: aload         7
     151: invokeinterface #80,  1           // InterfaceMethod java/util/Iterator.hasNext:()Z
     156: ifeq          199
     159: aload         7
     161: invokeinterface #84,  1           // InterfaceMethod java/util/Iterator.next:()Ljava/lang/Object;
     166: astore        8
     168: aload         5
     170: aload         8
     172: checkcast     #86                 // class aws/sdk/kotlin/services/resiliencehub/model/AssessmentStatus
     175: astore        9
     177: astore        13
     179: iconst_0
     180: istore        10
     182: aload         9
     184: invokevirtual #89                 // Method aws/sdk/kotlin/services/resiliencehub/model/AssessmentStatus.getValue:()Ljava/lang/String;
     187: aload         13
     189: swap
     190: invokeinterface #93,  2           // InterfaceMethod java/util/Collection.add:(Ljava/lang/Object;)Z
     195: pop
     196: goto          149
     199: aload         5
     201: checkcast     #95                 // class java/util/List
     204: nop
     205: astore        13
     207: aload         11
     209: aload         12
     211: aload         13
     213: checkcast     #62                 // class java/lang/Iterable
     216: invokevirtual #99                 // Method aws/smithy/kotlin/runtime/http/QueryParametersBuilder.appendAll:(Ljava/lang/String;Ljava/lang/Iterable;)V
     219: aload_0
     220: getfield      #13                 // Field $input:Laws/sdk/kotlin/services/resiliencehub/model/ListAppAssessmentsRequest;
     223: invokevirtual #103                // Method aws/sdk/kotlin/services/resiliencehub/model/ListAppAssessmentsRequest.getComplianceStatus:()Laws/sdk/kotlin/services/resiliencehub/model/ComplianceStatus;
     226: ifnull        245
     229: aload_1
     230: ldc           #105                // String complianceStatus
     232: aload_0
     233: getfield      #13                 // Field $input:Laws/sdk/kotlin/services/resiliencehub/model/ListAppAssessmentsRequest;
     236: invokevirtual #103                // Method aws/sdk/kotlin/services/resiliencehub/model/ListAppAssessmentsRequest.getComplianceStatus:()Laws/sdk/kotlin/services/resiliencehub/model/ComplianceStatus;
     239: invokevirtual #108                // Method aws/sdk/kotlin/services/resiliencehub/model/ComplianceStatus.getValue:()Ljava/lang/String;
     242: invokevirtual #43                 // Method aws/smithy/kotlin/runtime/http/QueryParametersBuilder.append:(Ljava/lang/String;Ljava/lang/String;)V
     245: aload_0
     246: getfield      #13                 // Field $input:Laws/sdk/kotlin/services/resiliencehub/model/ListAppAssessmentsRequest;
     249: invokevirtual #112                // Method aws/sdk/kotlin/services/resiliencehub/model/ListAppAssessmentsRequest.getInvoker:()Laws/sdk/kotlin/services/resiliencehub/model/AssessmentInvoker;
     252: ifnull        271
     255: aload_1
     256: ldc           #114                // String invoker
     258: aload_0
     259: getfield      #13                 // Field $input:Laws/sdk/kotlin/services/resiliencehub/model/ListAppAssessmentsRequest;
     262: invokevirtual #112                // Method aws/sdk/kotlin/services/resiliencehub/model/ListAppAssessmentsRequest.getInvoker:()Laws/sdk/kotlin/services/resiliencehub/model/AssessmentInvoker;
     265: invokevirtual #117                // Method aws/sdk/kotlin/services/resiliencehub/model/AssessmentInvoker.getValue:()Ljava/lang/String;
     268: invokevirtual #43                 // Method aws/smithy/kotlin/runtime/http/QueryParametersBuilder.append:(Ljava/lang/String;Ljava/lang/String;)V
     271: aload_0
     272: getfield      #13                 // Field $input:Laws/sdk/kotlin/services/resiliencehub/model/ListAppAssessmentsRequest;
     275: invokevirtual #121                // Method aws/sdk/kotlin/services/resiliencehub/model/ListAppAssessmentsRequest.getMaxResults:()Ljava/lang/Integer;
     278: ifnull        297
     281: aload_1
     282: ldc           #123                // String maxResults
     284: aload_0
     285: getfield      #13                 // Field $input:Laws/sdk/kotlin/services/resiliencehub/model/ListAppAssessmentsRequest;
     288: invokevirtual #121                // Method aws/sdk/kotlin/services/resiliencehub/model/ListAppAssessmentsRequest.getMaxResults:()Ljava/lang/Integer;
     291: invokestatic  #129                // Method java/lang/String.valueOf:(Ljava/lang/Object;)Ljava/lang/String;
     294: invokevirtual #43                 // Method aws/smithy/kotlin/runtime/http/QueryParametersBuilder.append:(Ljava/lang/String;Ljava/lang/String;)V
     297: aload_0
     298: getfield      #13                 // Field $input:Laws/sdk/kotlin/services/resiliencehub/model/ListAppAssessmentsRequest;
     301: invokevirtual #132                // Method aws/sdk/kotlin/services/resiliencehub/model/ListAppAssessmentsRequest.getNextToken:()Ljava/lang/String;
     304: ifnull        320
     307: aload_1
     308: ldc           #134                // String nextToken
     310: aload_0
     311: getfield      #13                 // Field $input:Laws/sdk/kotlin/services/resiliencehub/model/ListAppAssessmentsRequest;
     314: invokevirtual #132                // Method aws/sdk/kotlin/services/resiliencehub/model/ListAppAssessmentsRequest.getNextToken:()Ljava/lang/String;
     317: invokevirtual #43                 // Method aws/smithy/kotlin/runtime/http/QueryParametersBuilder.append:(Ljava/lang/String;Ljava/lang/String;)V
     320: aload_0
     321: getfield      #13                 // Field $input:Laws/sdk/kotlin/services/resiliencehub/model/ListAppAssessmentsRequest;
     324: invokevirtual #138                // Method aws/sdk/kotlin/services/resiliencehub/model/ListAppAssessmentsRequest.getReverseOrder:()Ljava/lang/Boolean;
     327: ifnull        346
     330: aload_1
     331: ldc           #140                // String reverseOrder
     333: aload_0
     334: getfield      #13                 // Field $input:Laws/sdk/kotlin/services/resiliencehub/model/ListAppAssessmentsRequest;
     337: invokevirtual #138                // Method aws/sdk/kotlin/services/resiliencehub/model/ListAppAssessmentsRequest.getReverseOrder:()Ljava/lang/Boolean;
     340: invokestatic  #129                // Method java/lang/String.valueOf:(Ljava/lang/Object;)Ljava/lang/String;
     343: invokevirtual #43                 // Method aws/smithy/kotlin/runtime/http/QueryParametersBuilder.append:(Ljava/lang/String;Ljava/lang/String;)V
     346: return

  public java.lang.Object invoke(java.lang.Object);
    Code:
       0: aload_0
       1: aload_1
       2: checkcast     #39                 // class aws/smithy/kotlin/runtime/http/QueryParametersBuilder
       5: invokevirtual #157                // Method invoke:(Laws/smithy/kotlin/runtime/http/QueryParametersBuilder;)V
       8: getstatic     #163                // Field kotlin/Unit.INSTANCE:Lkotlin/Unit;
      11: areturn
}
