Compiled from "MapperFeature.java"
public final class org.apache.htrace.shaded.fasterxml.jackson.databind.MapperFeature extends java.lang.Enum<org.apache.htrace.shaded.fasterxml.jackson.databind.MapperFeature> implements org.apache.htrace.shaded.fasterxml.jackson.databind.cfg.ConfigFeature {
  public static final org.apache.htrace.shaded.fasterxml.jackson.databind.MapperFeature USE_ANNOTATIONS;

  public static final org.apache.htrace.shaded.fasterxml.jackson.databind.MapperFeature AUTO_DETECT_CREATORS;

  public static final org.apache.htrace.shaded.fasterxml.jackson.databind.MapperFeature AUTO_DETECT_FIELDS;

  public static final org.apache.htrace.shaded.fasterxml.jackson.databind.MapperFeature AUTO_DETECT_GETTERS;

  public static final org.apache.htrace.shaded.fasterxml.jackson.databind.MapperFeature AUTO_DETECT_IS_GETTERS;

  public static final org.apache.htrace.shaded.fasterxml.jackson.databind.MapperFeature AUTO_DETECT_SETTERS;

  public static final org.apache.htrace.shaded.fasterxml.jackson.databind.MapperFeature REQUIRE_SETTERS_FOR_GETTERS;

  public static final org.apache.htrace.shaded.fasterxml.jackson.databind.MapperFeature USE_GETTERS_AS_SETTERS;

  public static final org.apache.htrace.shaded.fasterxml.jackson.databind.MapperFeature CAN_OVERRIDE_ACCESS_MODIFIERS;

  public static final org.apache.htrace.shaded.fasterxml.jackson.databind.MapperFeature INFER_PROPERTY_MUTATORS;

  public static final org.apache.htrace.shaded.fasterxml.jackson.databind.MapperFeature ALLOW_FINAL_FIELDS_AS_MUTATORS;

  public static final org.apache.htrace.shaded.fasterxml.jackson.databind.MapperFeature USE_STATIC_TYPING;

  public static final org.apache.htrace.shaded.fasterxml.jackson.databind.MapperFeature DEFAULT_VIEW_INCLUSION;

  public static final org.apache.htrace.shaded.fasterxml.jackson.databind.MapperFeature SORT_PROPERTIES_ALPHABETICALLY;

  public static final org.apache.htrace.shaded.fasterxml.jackson.databind.MapperFeature USE_WRAPPER_NAME_AS_PROPERTY_NAME;

  private final boolean _defaultState;

  private static final org.apache.htrace.shaded.fasterxml.jackson.databind.MapperFeature[] $VALUES;

  public static org.apache.htrace.shaded.fasterxml.jackson.databind.MapperFeature[] values();
    Code:
       0: getstatic     #32                 // Field $VALUES:[Lorg/apache/htrace/shaded/fasterxml/jackson/databind/MapperFeature;
       3: invokevirtual #37                 // Method "[Lorg/apache/htrace/shaded/fasterxml/jackson/databind/MapperFeature;".clone:()Ljava/lang/Object;
       6: checkcast     #33                 // class "[Lorg/apache/htrace/shaded/fasterxml/jackson/databind/MapperFeature;"
       9: areturn

  public static org.apache.htrace.shaded.fasterxml.jackson.databind.MapperFeature valueOf(java.lang.String);
    Code:
       0: ldc           #2                  // class org/apache/htrace/shaded/fasterxml/jackson/databind/MapperFeature
       2: aload_0
       3: invokestatic  #42                 // Method java/lang/Enum.valueOf:(Ljava/lang/Class;Ljava/lang/String;)Ljava/lang/Enum;
       6: checkcast     #2                  // class org/apache/htrace/shaded/fasterxml/jackson/databind/MapperFeature
       9: areturn

  private org.apache.htrace.shaded.fasterxml.jackson.databind.MapperFeature(boolean);
    Code:
       0: aload_0
       1: aload_1
       2: iload_2
       3: invokespecial #49                 // Method java/lang/Enum."<init>":(Ljava/lang/String;I)V
       6: aload_0
       7: iload_3
       8: putfield      #51                 // Field _defaultState:Z
      11: return

  public boolean enabledByDefault();
    Code:
       0: aload_0
       1: getfield      #51                 // Field _defaultState:Z
       4: ireturn

  public int getMask();
    Code:
       0: iconst_1
       1: aload_0
       2: invokevirtual #60                 // Method ordinal:()I
       5: ishl
       6: ireturn

  static {};
    Code:
       0: new           #2                  // class org/apache/htrace/shaded/fasterxml/jackson/databind/MapperFeature
       3: dup
       4: ldc           #63                 // String USE_ANNOTATIONS
       6: iconst_0
       7: iconst_1
       8: invokespecial #65                 // Method "<init>":(Ljava/lang/String;IZ)V
      11: putstatic     #67                 // Field USE_ANNOTATIONS:Lorg/apache/htrace/shaded/fasterxml/jackson/databind/MapperFeature;
      14: new           #2                  // class org/apache/htrace/shaded/fasterxml/jackson/databind/MapperFeature
      17: dup
      18: ldc           #68                 // String AUTO_DETECT_CREATORS
      20: iconst_1
      21: iconst_1
      22: invokespecial #65                 // Method "<init>":(Ljava/lang/String;IZ)V
      25: putstatic     #70                 // Field AUTO_DETECT_CREATORS:Lorg/apache/htrace/shaded/fasterxml/jackson/databind/MapperFeature;
      28: new           #2                  // class org/apache/htrace/shaded/fasterxml/jackson/databind/MapperFeature
      31: dup
      32: ldc           #71                 // String AUTO_DETECT_FIELDS
      34: iconst_2
      35: iconst_1
      36: invokespecial #65                 // Method "<init>":(Ljava/lang/String;IZ)V
      39: putstatic     #73                 // Field AUTO_DETECT_FIELDS:Lorg/apache/htrace/shaded/fasterxml/jackson/databind/MapperFeature;
      42: new           #2                  // class org/apache/htrace/shaded/fasterxml/jackson/databind/MapperFeature
      45: dup
      46: ldc           #74                 // String AUTO_DETECT_GETTERS
      48: iconst_3
      49: iconst_1
      50: invokespecial #65                 // Method "<init>":(Ljava/lang/String;IZ)V
      53: putstatic     #76                 // Field AUTO_DETECT_GETTERS:Lorg/apache/htrace/shaded/fasterxml/jackson/databind/MapperFeature;
      56: new           #2                  // class org/apache/htrace/shaded/fasterxml/jackson/databind/MapperFeature
      59: dup
      60: ldc           #77                 // String AUTO_DETECT_IS_GETTERS
      62: iconst_4
      63: iconst_1
      64: invokespecial #65                 // Method "<init>":(Ljava/lang/String;IZ)V
      67: putstatic     #79                 // Field AUTO_DETECT_IS_GETTERS:Lorg/apache/htrace/shaded/fasterxml/jackson/databind/MapperFeature;
      70: new           #2                  // class org/apache/htrace/shaded/fasterxml/jackson/databind/MapperFeature
      73: dup
      74: ldc           #80                 // String AUTO_DETECT_SETTERS
      76: iconst_5
      77: iconst_1
      78: invokespecial #65                 // Method "<init>":(Ljava/lang/String;IZ)V
      81: putstatic     #82                 // Field AUTO_DETECT_SETTERS:Lorg/apache/htrace/shaded/fasterxml/jackson/databind/MapperFeature;
      84: new           #2                  // class org/apache/htrace/shaded/fasterxml/jackson/databind/MapperFeature
      87: dup
      88: ldc           #83                 // String REQUIRE_SETTERS_FOR_GETTERS
      90: bipush        6
      92: iconst_0
      93: invokespecial #65                 // Method "<init>":(Ljava/lang/String;IZ)V
      96: putstatic     #85                 // Field REQUIRE_SETTERS_FOR_GETTERS:Lorg/apache/htrace/shaded/fasterxml/jackson/databind/MapperFeature;
      99: new           #2                  // class org/apache/htrace/shaded/fasterxml/jackson/databind/MapperFeature
     102: dup
     103: ldc           #86                 // String USE_GETTERS_AS_SETTERS
     105: bipush        7
     107: iconst_1
     108: invokespecial #65                 // Method "<init>":(Ljava/lang/String;IZ)V
     111: putstatic     #88                 // Field USE_GETTERS_AS_SETTERS:Lorg/apache/htrace/shaded/fasterxml/jackson/databind/MapperFeature;
     114: new           #2                  // class org/apache/htrace/shaded/fasterxml/jackson/databind/MapperFeature
     117: dup
     118: ldc           #89                 // String CAN_OVERRIDE_ACCESS_MODIFIERS
     120: bipush        8
     122: iconst_1
     123: invokespecial #65                 // Method "<init>":(Ljava/lang/String;IZ)V
     126: putstatic     #91                 // Field CAN_OVERRIDE_ACCESS_MODIFIERS:Lorg/apache/htrace/shaded/fasterxml/jackson/databind/MapperFeature;
     129: new           #2                  // class org/apache/htrace/shaded/fasterxml/jackson/databind/MapperFeature
     132: dup
     133: ldc           #92                 // String INFER_PROPERTY_MUTATORS
     135: bipush        9
     137: iconst_1
     138: invokespecial #65                 // Method "<init>":(Ljava/lang/String;IZ)V
     141: putstatic     #94                 // Field INFER_PROPERTY_MUTATORS:Lorg/apache/htrace/shaded/fasterxml/jackson/databind/MapperFeature;
     144: new           #2                  // class org/apache/htrace/shaded/fasterxml/jackson/databind/MapperFeature
     147: dup
     148: ldc           #95                 // String ALLOW_FINAL_FIELDS_AS_MUTATORS
     150: bipush        10
     152: iconst_1
     153: invokespecial #65                 // Method "<init>":(Ljava/lang/String;IZ)V
     156: putstatic     #97                 // Field ALLOW_FINAL_FIELDS_AS_MUTATORS:Lorg/apache/htrace/shaded/fasterxml/jackson/databind/MapperFeature;
     159: new           #2                  // class org/apache/htrace/shaded/fasterxml/jackson/databind/MapperFeature
     162: dup
     163: ldc           #98                 // String USE_STATIC_TYPING
     165: bipush        11
     167: iconst_0
     168: invokespecial #65                 // Method "<init>":(Ljava/lang/String;IZ)V
     171: putstatic     #100                // Field USE_STATIC_TYPING:Lorg/apache/htrace/shaded/fasterxml/jackson/databind/MapperFeature;
     174: new           #2                  // class org/apache/htrace/shaded/fasterxml/jackson/databind/MapperFeature
     177: dup
     178: ldc           #101                // String DEFAULT_VIEW_INCLUSION
     180: bipush        12
     182: iconst_1
     183: invokespecial #65                 // Method "<init>":(Ljava/lang/String;IZ)V
     186: putstatic     #103                // Field DEFAULT_VIEW_INCLUSION:Lorg/apache/htrace/shaded/fasterxml/jackson/databind/MapperFeature;
     189: new           #2                  // class org/apache/htrace/shaded/fasterxml/jackson/databind/MapperFeature
     192: dup
     193: ldc           #104                // String SORT_PROPERTIES_ALPHABETICALLY
     195: bipush        13
     197: iconst_0
     198: invokespecial #65                 // Method "<init>":(Ljava/lang/String;IZ)V
     201: putstatic     #106                // Field SORT_PROPERTIES_ALPHABETICALLY:Lorg/apache/htrace/shaded/fasterxml/jackson/databind/MapperFeature;
     204: new           #2                  // class org/apache/htrace/shaded/fasterxml/jackson/databind/MapperFeature
     207: dup
     208: ldc           #107                // String USE_WRAPPER_NAME_AS_PROPERTY_NAME
     210: bipush        14
     212: iconst_0
     213: invokespecial #65                 // Method "<init>":(Ljava/lang/String;IZ)V
     216: putstatic     #109                // Field USE_WRAPPER_NAME_AS_PROPERTY_NAME:Lorg/apache/htrace/shaded/fasterxml/jackson/databind/MapperFeature;
     219: bipush        15
     221: anewarray     #2                  // class org/apache/htrace/shaded/fasterxml/jackson/databind/MapperFeature
     224: dup
     225: iconst_0
     226: getstatic     #67                 // Field USE_ANNOTATIONS:Lorg/apache/htrace/shaded/fasterxml/jackson/databind/MapperFeature;
     229: aastore
     230: dup
     231: iconst_1
     232: getstatic     #70                 // Field AUTO_DETECT_CREATORS:Lorg/apache/htrace/shaded/fasterxml/jackson/databind/MapperFeature;
     235: aastore
     236: dup
     237: iconst_2
     238: getstatic     #73                 // Field AUTO_DETECT_FIELDS:Lorg/apache/htrace/shaded/fasterxml/jackson/databind/MapperFeature;
     241: aastore
     242: dup
     243: iconst_3
     244: getstatic     #76                 // Field AUTO_DETECT_GETTERS:Lorg/apache/htrace/shaded/fasterxml/jackson/databind/MapperFeature;
     247: aastore
     248: dup
     249: iconst_4
     250: getstatic     #79                 // Field AUTO_DETECT_IS_GETTERS:Lorg/apache/htrace/shaded/fasterxml/jackson/databind/MapperFeature;
     253: aastore
     254: dup
     255: iconst_5
     256: getstatic     #82                 // Field AUTO_DETECT_SETTERS:Lorg/apache/htrace/shaded/fasterxml/jackson/databind/MapperFeature;
     259: aastore
     260: dup
     261: bipush        6
     263: getstatic     #85                 // Field REQUIRE_SETTERS_FOR_GETTERS:Lorg/apache/htrace/shaded/fasterxml/jackson/databind/MapperFeature;
     266: aastore
     267: dup
     268: bipush        7
     270: getstatic     #88                 // Field USE_GETTERS_AS_SETTERS:Lorg/apache/htrace/shaded/fasterxml/jackson/databind/MapperFeature;
     273: aastore
     274: dup
     275: bipush        8
     277: getstatic     #91                 // Field CAN_OVERRIDE_ACCESS_MODIFIERS:Lorg/apache/htrace/shaded/fasterxml/jackson/databind/MapperFeature;
     280: aastore
     281: dup
     282: bipush        9
     284: getstatic     #94                 // Field INFER_PROPERTY_MUTATORS:Lorg/apache/htrace/shaded/fasterxml/jackson/databind/MapperFeature;
     287: aastore
     288: dup
     289: bipush        10
     291: getstatic     #97                 // Field ALLOW_FINAL_FIELDS_AS_MUTATORS:Lorg/apache/htrace/shaded/fasterxml/jackson/databind/MapperFeature;
     294: aastore
     295: dup
     296: bipush        11
     298: getstatic     #100                // Field USE_STATIC_TYPING:Lorg/apache/htrace/shaded/fasterxml/jackson/databind/MapperFeature;
     301: aastore
     302: dup
     303: bipush        12
     305: getstatic     #103                // Field DEFAULT_VIEW_INCLUSION:Lorg/apache/htrace/shaded/fasterxml/jackson/databind/MapperFeature;
     308: aastore
     309: dup
     310: bipush        13
     312: getstatic     #106                // Field SORT_PROPERTIES_ALPHABETICALLY:Lorg/apache/htrace/shaded/fasterxml/jackson/databind/MapperFeature;
     315: aastore
     316: dup
     317: bipush        14
     319: getstatic     #109                // Field USE_WRAPPER_NAME_AS_PROPERTY_NAME:Lorg/apache/htrace/shaded/fasterxml/jackson/databind/MapperFeature;
     322: aastore
     323: putstatic     #32                 // Field $VALUES:[Lorg/apache/htrace/shaded/fasterxml/jackson/databind/MapperFeature;
     326: return
}
