Compiled from "Jsr250SecurityConfig.java"
public class org.springframework.security.access.annotation.Jsr250SecurityConfig extends org.springframework.security.access.SecurityConfig {
  public static final org.springframework.security.access.annotation.Jsr250SecurityConfig PERMIT_ALL_ATTRIBUTE;

  public static final org.springframework.security.access.annotation.Jsr250SecurityConfig DENY_ALL_ATTRIBUTE;

  public org.springframework.security.access.annotation.Jsr250SecurityConfig(java.lang.String);
    Code:
       0: aload_0
       1: aload_1
       2: invokespecial #1                  // Method org/springframework/security/access/SecurityConfig."<init>":(Ljava/lang/String;)V
       5: return

  static {};
    Code:
       0: new           #2                  // class org/springframework/security/access/annotation/Jsr250SecurityConfig
       3: dup
       4: ldc           #3                  // class javax/annotation/security/PermitAll
       6: invokevirtual #4                  // Method java/lang/Class.getName:()Ljava/lang/String;
       9: invokespecial #5                  // Method "<init>":(Ljava/lang/String;)V
      12: putstatic     #6                  // Field PERMIT_ALL_ATTRIBUTE:Lorg/springframework/security/access/annotation/Jsr250SecurityConfig;
      15: new           #2                  // class org/springframework/security/access/annotation/Jsr250SecurityConfig
      18: dup
      19: ldc           #7                  // class javax/annotation/security/DenyAll
      21: invokevirtual #4                  // Method java/lang/Class.getName:()Ljava/lang/String;
      24: invokespecial #5                  // Method "<init>":(Ljava/lang/String;)V
      27: putstatic     #8                  // Field DENY_ALL_ATTRIBUTE:Lorg/springframework/security/access/annotation/Jsr250SecurityConfig;
      30: return
}
