Compiled from "JRockitAgent.java"
public class org.aspectj.weaver.loadtime.JRockitAgent implements com.bea.jvm.ClassPreProcessor {
  private org.aspectj.weaver.loadtime.ClassPreProcessor preProcessor;

  private static org.aspectj.weaver.loadtime.JRockitAgent$ThreadLocalStack stack;

  public org.aspectj.weaver.loadtime.JRockitAgent();
    Code:
       0: aload_0
       1: invokespecial #1                  // Method java/lang/Object."<init>":()V
       4: aload_0
       5: new           #2                  // class org/aspectj/weaver/loadtime/Aj
       8: dup
       9: invokespecial #3                  // Method org/aspectj/weaver/loadtime/Aj."<init>":()V
      12: putfield      #4                  // Field preProcessor:Lorg/aspectj/weaver/loadtime/ClassPreProcessor;
      15: invokestatic  #5                  // Method com/bea/jvm/JVMFactory.getJVM:()Lcom/bea/jvm/JVM;
      18: invokeinterface #6,  1            // InterfaceMethod com/bea/jvm/JVM.getClassLibrary:()Lcom/bea/jvm/ClassLibrary;
      23: astore_1
      24: aload_1
      25: aload_0
      26: invokeinterface #7,  2            // InterfaceMethod com/bea/jvm/ClassLibrary.setClassPreProcessor:(Lcom/bea/jvm/ClassPreProcessor;)V
      31: return

  public byte[] preProcess(java.lang.ClassLoader, java.lang.String, byte[]);
    Code:
       0: aload_3
       1: astore        4
       3: getstatic     #8                  // Field stack:Lorg/aspectj/weaver/loadtime/JRockitAgent$ThreadLocalStack;
       6: invokevirtual #9                  // Method org/aspectj/weaver/loadtime/JRockitAgent$ThreadLocalStack.empty:()Z
       9: ifeq          41
      12: getstatic     #8                  // Field stack:Lorg/aspectj/weaver/loadtime/JRockitAgent$ThreadLocalStack;
      15: aload_2
      16: invokevirtual #10                 // Method org/aspectj/weaver/loadtime/JRockitAgent$ThreadLocalStack.push:(Ljava/lang/Object;)V
      19: aload_0
      20: getfield      #4                  // Field preProcessor:Lorg/aspectj/weaver/loadtime/ClassPreProcessor;
      23: aload_2
      24: aload_3
      25: aload_1
      26: aconst_null
      27: invokeinterface #11,  5           // InterfaceMethod org/aspectj/weaver/loadtime/ClassPreProcessor.preProcess:(Ljava/lang/String;[BLjava/lang/ClassLoader;Ljava/security/ProtectionDomain;)[B
      32: astore        4
      34: getstatic     #8                  // Field stack:Lorg/aspectj/weaver/loadtime/JRockitAgent$ThreadLocalStack;
      37: invokevirtual #12                 // Method org/aspectj/weaver/loadtime/JRockitAgent$ThreadLocalStack.pop:()Ljava/lang/Object;
      40: pop
      41: aload         4
      43: areturn

  static {};
    Code:
       0: new           #13                 // class org/aspectj/weaver/loadtime/JRockitAgent$ThreadLocalStack
       3: dup
       4: aconst_null
       5: invokespecial #14                 // Method org/aspectj/weaver/loadtime/JRockitAgent$ThreadLocalStack."<init>":(Lorg/aspectj/weaver/loadtime/JRockitAgent$1;)V
       8: putstatic     #8                  // Field stack:Lorg/aspectj/weaver/loadtime/JRockitAgent$ThreadLocalStack;
      11: return
}
