Compiled from "MessageCounter.java"
public final class org.apache.activemq.artemis.core.messagecounter.MessageCounter$DayCounter {
  static final int HOURS;

  java.util.GregorianCalendar date;

  int[] counters;

  org.apache.activemq.artemis.core.messagecounter.MessageCounter$DayCounter(java.util.GregorianCalendar, boolean);
    Code:
       0: aload_0
       1: invokespecial #3                  // Method java/lang/Object."<init>":()V
       4: aload_0
       5: aconst_null
       6: putfield      #4                  // Field date:Ljava/util/GregorianCalendar;
       9: aload_0
      10: bipush        24
      12: newarray       int
      14: putfield      #6                  // Field counters:[I
      17: aload_0
      18: aload_1
      19: invokevirtual #7                  // Method java/util/GregorianCalendar.clone:()Ljava/lang/Object;
      22: checkcast     #8                  // class java/util/GregorianCalendar
      25: putfield      #4                  // Field date:Ljava/util/GregorianCalendar;
      28: aload_1
      29: bipush        11
      31: invokevirtual #10                 // Method java/util/GregorianCalendar.get:(I)I
      34: istore_3
      35: iconst_0
      36: istore        4
      38: iload         4
      40: bipush        24
      42: if_icmpge     91
      45: iload         4
      47: iload_3
      48: if_icmpge     77
      51: iload_2
      52: ifeq          66
      55: aload_0
      56: getfield      #6                  // Field counters:[I
      59: iload         4
      61: iconst_m1
      62: iastore
      63: goto          85
      66: aload_0
      67: getfield      #6                  // Field counters:[I
      70: iload         4
      72: iconst_0
      73: iastore
      74: goto          85
      77: aload_0
      78: getfield      #6                  // Field counters:[I
      81: iload         4
      83: iconst_m1
      84: iastore
      85: iinc          4, 1
      88: goto          38
      91: aload_0
      92: getfield      #6                  // Field counters:[I
      95: iload_3
      96: iconst_0
      97: iastore
      98: return

  public java.util.GregorianCalendar getDate();
    Code:
       0: aload_0
       1: getfield      #4                  // Field date:Ljava/util/GregorianCalendar;
       4: invokevirtual #7                  // Method java/util/GregorianCalendar.clone:()Ljava/lang/Object;
       7: checkcast     #8                  // class java/util/GregorianCalendar
      10: areturn

  public int[] getCounters();
    Code:
       0: aload_0
       1: getfield      #6                  // Field counters:[I
       4: areturn

  void updateDayCounter(long);
    Code:
       0: new           #8                  // class java/util/GregorianCalendar
       3: dup
       4: invokespecial #11                 // Method java/util/GregorianCalendar."<init>":()V
       7: astore_3
       8: aload_3
       9: bipush        11
      11: invokevirtual #10                 // Method java/util/GregorianCalendar.get:(I)I
      14: istore        4
      16: iconst_0
      17: istore        5
      19: iconst_0
      20: istore        6
      22: iload         6
      24: iload         4
      26: if_icmpgt     74
      29: aload_0
      30: getfield      #6                  // Field counters:[I
      33: iload         6
      35: iaload
      36: iconst_m1
      37: if_icmple     43
      40: iconst_1
      41: istore        5
      43: iload         5
      45: iconst_1
      46: if_icmpne     68
      49: aload_0
      50: getfield      #6                  // Field counters:[I
      53: iload         6
      55: iaload
      56: iconst_m1
      57: if_icmpne     68
      60: aload_0
      61: getfield      #6                  // Field counters:[I
      64: iload         6
      66: iconst_0
      67: iastore
      68: iinc          6, 1
      71: goto          22
      74: aload_0
      75: getfield      #6                  // Field counters:[I
      78: iload         4
      80: dup2
      81: iaload
      82: i2l
      83: lload_1
      84: ladd
      85: l2i
      86: iastore
      87: return

  private void finalizeDayCounter();
    Code:
       0: iconst_0
       1: istore_1
       2: iconst_0
       3: istore_2
       4: iload_2
       5: bipush        24
       7: if_icmpge     49
      10: aload_0
      11: getfield      #6                  // Field counters:[I
      14: iload_2
      15: iaload
      16: iconst_m1
      17: if_icmple     22
      20: iconst_1
      21: istore_1
      22: iload_1
      23: ifeq          43
      26: aload_0
      27: getfield      #6                  // Field counters:[I
      30: iload_2
      31: iaload
      32: iconst_m1
      33: if_icmpne     43
      36: aload_0
      37: getfield      #6                  // Field counters:[I
      40: iload_2
      41: iconst_0
      42: iastore
      43: iinc          2, 1
      46: goto          4
      49: return

  private java.lang.String getDayCounterAsString();
    Code:
       0: iconst_3
       1: invokestatic  #13                 // Method java/text/DateFormat.getDateInstance:(I)Ljava/text/DateFormat;
       4: astore_1
       5: new           #14                 // class java/lang/StringBuilder
       8: dup
       9: aload_1
      10: aload_0
      11: getfield      #4                  // Field date:Ljava/util/GregorianCalendar;
      14: invokevirtual #15                 // Method java/util/GregorianCalendar.getTime:()Ljava/util/Date;
      17: invokevirtual #16                 // Method java/text/DateFormat.format:(Ljava/util/Date;)Ljava/lang/String;
      20: invokespecial #17                 // Method java/lang/StringBuilder."<init>":(Ljava/lang/String;)V
      23: astore_2
      24: iconst_0
      25: istore_3
      26: iload_3
      27: bipush        24
      29: if_icmpge     67
      32: aload_2
      33: new           #14                 // class java/lang/StringBuilder
      36: dup
      37: invokespecial #18                 // Method java/lang/StringBuilder."<init>":()V
      40: ldc           #19                 // String ,
      42: invokevirtual #20                 // Method java/lang/StringBuilder.append:(Ljava/lang/String;)Ljava/lang/StringBuilder;
      45: aload_0
      46: getfield      #6                  // Field counters:[I
      49: iload_3
      50: iaload
      51: invokevirtual #21                 // Method java/lang/StringBuilder.append:(I)Ljava/lang/StringBuilder;
      54: invokevirtual #22                 // Method java/lang/StringBuilder.toString:()Ljava/lang/String;
      57: invokevirtual #20                 // Method java/lang/StringBuilder.append:(Ljava/lang/String;)Ljava/lang/StringBuilder;
      60: pop
      61: iinc          3, 1
      64: goto          26
      67: aload_2
      68: invokevirtual #22                 // Method java/lang/StringBuilder.toString:()Ljava/lang/String;
      71: areturn

  static java.lang.String access$600(org.apache.activemq.artemis.core.messagecounter.MessageCounter$DayCounter);
    Code:
       0: aload_0
       1: invokespecial #2                  // Method getDayCounterAsString:()Ljava/lang/String;
       4: areturn

  static void access$700(org.apache.activemq.artemis.core.messagecounter.MessageCounter$DayCounter);
    Code:
       0: aload_0
       1: invokespecial #1                  // Method finalizeDayCounter:()V
       4: return
}
