Compiled from "RespondNotFoundException.scala"
public final class org.sisioh.trinity.domain.controller.RespondNotFoundException$ extends scala.runtime.AbstractFunction2<scala.Option<java.lang.String>, scala.Option<java.lang.Throwable>, org.sisioh.trinity.domain.controller.RespondNotFoundException> implements scala.Serializable {
  public static final org.sisioh.trinity.domain.controller.RespondNotFoundException$ MODULE$;

  public static {};
    Code:
       0: new           #2                  // class org/sisioh/trinity/domain/controller/RespondNotFoundException$
       3: invokespecial #15                 // Method "<init>":()V
       6: return

  public final java.lang.String toString();
    Code:
       0: ldc           #19                 // String RespondNotFoundException
       2: areturn

  public org.sisioh.trinity.domain.controller.RespondNotFoundException apply(scala.Option<java.lang.String>, scala.Option<java.lang.Throwable>);
    Code:
       0: new           #24                 // class org/sisioh/trinity/domain/controller/RespondNotFoundException
       3: dup
       4: aload_1
       5: aload_2
       6: invokespecial #27                 // Method org/sisioh/trinity/domain/controller/RespondNotFoundException."<init>":(Lscala/Option;Lscala/Option;)V
       9: areturn

  public scala.Option<scala.Tuple2<scala.Option<java.lang.String>, scala.Option<java.lang.Throwable>>> unapply(org.sisioh.trinity.domain.controller.RespondNotFoundException);
    Code:
       0: aload_1
       1: ifnonnull     10
       4: getstatic     #37                 // Field scala/None$.MODULE$:Lscala/None$;
       7: goto          32
      10: new           #39                 // class scala/Some
      13: dup
      14: new           #41                 // class scala/Tuple2
      17: dup
      18: aload_1
      19: invokevirtual #44                 // Method org/sisioh/trinity/domain/controller/RespondNotFoundException.message:()Lscala/Option;
      22: aload_1
      23: invokevirtual #46                 // Method org/sisioh/trinity/domain/controller/RespondNotFoundException.cause:()Lscala/Option;
      26: invokespecial #49                 // Method scala/Tuple2."<init>":(Ljava/lang/Object;Ljava/lang/Object;)V
      29: invokespecial #52                 // Method scala/Some."<init>":(Ljava/lang/Object;)V
      32: areturn

  public scala.Option<java.lang.String> $lessinit$greater$default$1();
    Code:
       0: getstatic     #37                 // Field scala/None$.MODULE$:Lscala/None$;
       3: areturn

  public scala.Option<java.lang.Throwable> $lessinit$greater$default$2();
    Code:
       0: getstatic     #37                 // Field scala/None$.MODULE$:Lscala/None$;
       3: areturn

  public scala.Option<java.lang.String> apply$default$1();
    Code:
       0: getstatic     #37                 // Field scala/None$.MODULE$:Lscala/None$;
       3: areturn

  public scala.Option<java.lang.Throwable> apply$default$2();
    Code:
       0: getstatic     #37                 // Field scala/None$.MODULE$:Lscala/None$;
       3: areturn

  private java.lang.Object readResolve();
    Code:
       0: getstatic     #64                 // Field MODULE$:Lorg/sisioh/trinity/domain/controller/RespondNotFoundException$;
       3: areturn

  public java.lang.Object apply(java.lang.Object, java.lang.Object);
    Code:
       0: aload_0
       1: aload_1
       2: checkcast     #56                 // class scala/Option
       5: aload_2
       6: checkcast     #56                 // class scala/Option
       9: invokevirtual #67                 // Method apply:(Lscala/Option;Lscala/Option;)Lorg/sisioh/trinity/domain/controller/RespondNotFoundException;
      12: areturn

  private org.sisioh.trinity.domain.controller.RespondNotFoundException$();
    Code:
       0: aload_0
       1: invokespecial #71                 // Method scala/runtime/AbstractFunction2."<init>":()V
       4: aload_0
       5: putstatic     #64                 // Field MODULE$:Lorg/sisioh/trinity/domain/controller/RespondNotFoundException$;
       8: return
}
