Compiled from "SimpleController.scala"
public final class org.sisioh.trinity.domain.controller.SimpleController$$anonfun$addRoute$1 extends scala.runtime.AbstractFunction1<org.sisioh.trinity.domain.http.TrinityRequest, com.twitter.util.Future<com.twitter.finagle.http.Response>> implements scala.Serializable {
  public static final long serialVersionUID;

  private final org.sisioh.trinity.domain.controller.SimpleController $outer;

  private final org.jboss.netty.handler.codec.http.HttpMethod method$1;

  private final java.lang.String path$1;

  public final scala.Function1 callback$1;

  public final com.twitter.util.Future<com.twitter.finagle.http.Response> apply(org.sisioh.trinity.domain.http.TrinityRequest);
    Code:
       0: aload_0
       1: getfield      #29                 // Field $outer:Lorg/sisioh/trinity/domain/controller/SimpleController;
       4: invokevirtual #33                 // Method org/sisioh/trinity/domain/controller/SimpleController.stats:()Lcom/twitter/finagle/stats/StatsReceiver;
       7: getstatic     #39                 // Field scala/Predef$.MODULE$:Lscala/Predef$;
      10: iconst_1
      11: anewarray     #41                 // class java/lang/String
      14: dup
      15: iconst_0
      16: new           #43                 // class scala/collection/immutable/StringOps
      19: dup
      20: getstatic     #39                 // Field scala/Predef$.MODULE$:Lscala/Predef$;
      23: ldc           #45                 // String %s/Root/%s
      25: invokevirtual #49                 // Method scala/Predef$.augmentString:(Ljava/lang/String;)Ljava/lang/String;
      28: invokespecial #53                 // Method scala/collection/immutable/StringOps."<init>":(Ljava/lang/String;)V
      31: getstatic     #39                 // Field scala/Predef$.MODULE$:Lscala/Predef$;
      34: iconst_2
      35: anewarray     #55                 // class java/lang/Object
      38: dup
      39: iconst_0
      40: aload_0
      41: getfield      #57                 // Field method$1:Lorg/jboss/netty/handler/codec/http/HttpMethod;
      44: invokevirtual #63                 // Method org/jboss/netty/handler/codec/http/HttpMethod.toString:()Ljava/lang/String;
      47: aastore
      48: dup
      49: iconst_1
      50: new           #43                 // class scala/collection/immutable/StringOps
      53: dup
      54: getstatic     #39                 // Field scala/Predef$.MODULE$:Lscala/Predef$;
      57: aload_0
      58: getfield      #65                 // Field path$1:Ljava/lang/String;
      61: invokevirtual #49                 // Method scala/Predef$.augmentString:(Ljava/lang/String;)Ljava/lang/String;
      64: invokespecial #53                 // Method scala/collection/immutable/StringOps."<init>":(Ljava/lang/String;)V
      67: ldc           #67                 // String /
      69: invokevirtual #70                 // Method scala/collection/immutable/StringOps.stripPrefix:(Ljava/lang/String;)Ljava/lang/String;
      72: aastore
      73: invokevirtual #74                 // Method scala/Predef$.genericWrapArray:(Ljava/lang/Object;)Lscala/collection/mutable/WrappedArray;
      76: invokevirtual #78                 // Method scala/collection/immutable/StringOps.format:(Lscala/collection/Seq;)Ljava/lang/String;
      79: aastore
      80: checkcast     #80                 // class "[Ljava/lang/Object;"
      83: invokevirtual #84                 // Method scala/Predef$.wrapRefArray:([Ljava/lang/Object;)Lscala/collection/mutable/WrappedArray;
      86: new           #86                 // class org/sisioh/trinity/domain/controller/SimpleController$$anonfun$addRoute$1$$anonfun$apply$1
      89: dup
      90: aload_0
      91: aload_1
      92: invokespecial #89                 // Method org/sisioh/trinity/domain/controller/SimpleController$$anonfun$addRoute$1$$anonfun$apply$1."<init>":(Lorg/sisioh/trinity/domain/controller/SimpleController$$anonfun$addRoute$1;Lorg/sisioh/trinity/domain/http/TrinityRequest;)V
      95: invokeinterface #95,  3           // InterfaceMethod com/twitter/finagle/stats/StatsReceiver.timeFuture:(Lscala/collection/Seq;Lscala/Function0;)Lcom/twitter/util/Future;
     100: areturn

  public final java.lang.Object apply(java.lang.Object);
    Code:
       0: aload_0
       1: aload_1
       2: checkcast     #102                // class org/sisioh/trinity/domain/http/TrinityRequest
       5: invokevirtual #104                // Method apply:(Lorg/sisioh/trinity/domain/http/TrinityRequest;)Lcom/twitter/util/Future;
       8: areturn

  public org.sisioh.trinity.domain.controller.SimpleController$$anonfun$addRoute$1(org.sisioh.trinity.domain.controller.SimpleController, org.jboss.netty.handler.codec.http.HttpMethod, java.lang.String, scala.Function1);
    Code:
       0: aload_1
       1: ifnonnull     12
       4: new           #109                // class java/lang/NullPointerException
       7: dup
       8: invokespecial #112                // Method java/lang/NullPointerException."<init>":()V
      11: athrow
      12: aload_0
      13: aload_1
      14: putfield      #29                 // Field $outer:Lorg/sisioh/trinity/domain/controller/SimpleController;
      17: aload_0
      18: aload_2
      19: putfield      #57                 // Field method$1:Lorg/jboss/netty/handler/codec/http/HttpMethod;
      22: aload_0
      23: aload_3
      24: putfield      #65                 // Field path$1:Ljava/lang/String;
      27: aload_0
      28: aload         4
      30: putfield      #114                // Field callback$1:Lscala/Function1;
      33: aload_0
      34: invokespecial #115                // Method scala/runtime/AbstractFunction1."<init>":()V
      37: return
}
