Compiled from "MongoIndexSetRegistry.java"
class org.graylog2.indexer.MongoIndexSetRegistry$IndexSetsCache {
  private final org.graylog2.indexer.indexset.IndexSetService indexSetService;

  private java.util.concurrent.atomic.AtomicReference<com.google.common.base.Supplier<java.util.List<org.graylog2.indexer.indexset.IndexSetConfig>>> indexSetConfigs;

  org.graylog2.indexer.MongoIndexSetRegistry$IndexSetsCache(org.graylog2.indexer.indexset.IndexSetService, com.google.common.eventbus.EventBus);
    Code:
       0: aload_0
       1: invokespecial #1                  // Method java/lang/Object."<init>":()V
       4: aload_0
       5: aload_1
       6: invokestatic  #2                  // Method java/util/Objects.requireNonNull:(Ljava/lang/Object;)Ljava/lang/Object;
       9: checkcast     #3                  // class org/graylog2/indexer/indexset/IndexSetService
      12: putfield      #4                  // Field indexSetService:Lorg/graylog2/indexer/indexset/IndexSetService;
      15: aload_0
      16: new           #5                  // class java/util/concurrent/atomic/AtomicReference
      19: dup
      20: aload_0
      21: getfield      #4                  // Field indexSetService:Lorg/graylog2/indexer/indexset/IndexSetService;
      24: dup
      25: invokestatic  #2                  // Method java/util/Objects.requireNonNull:(Ljava/lang/Object;)Ljava/lang/Object;
      28: pop
      29: invokedynamic #6,  0              // InvokeDynamic #0:get:(Lorg/graylog2/indexer/indexset/IndexSetService;)Lcom/google/common/base/Supplier;
      34: invokestatic  #7                  // Method com/google/common/base/Suppliers.memoize:(Lcom/google/common/base/Supplier;)Lcom/google/common/base/Supplier;
      37: invokespecial #8                  // Method java/util/concurrent/atomic/AtomicReference."<init>":(Ljava/lang/Object;)V
      40: putfield      #9                  // Field indexSetConfigs:Ljava/util/concurrent/atomic/AtomicReference;
      43: aload_2
      44: aload_0
      45: invokevirtual #10                 // Method com/google/common/eventbus/EventBus.register:(Ljava/lang/Object;)V
      48: return

  java.util.List<org.graylog2.indexer.indexset.IndexSetConfig> get();
    Code:
       0: aload_0
       1: getfield      #9                  // Field indexSetConfigs:Ljava/util/concurrent/atomic/AtomicReference;
       4: invokevirtual #11                 // Method java/util/concurrent/atomic/AtomicReference.get:()Ljava/lang/Object;
       7: checkcast     #12                 // class com/google/common/base/Supplier
      10: invokeinterface #13,  1           // InterfaceMethod com/google/common/base/Supplier.get:()Ljava/lang/Object;
      15: checkcast     #14                 // class java/util/List
      18: invokestatic  #15                 // Method java/util/Collections.unmodifiableList:(Ljava/util/List;)Ljava/util/List;
      21: areturn

  void invalidate();
    Code:
       0: aload_0
       1: getfield      #9                  // Field indexSetConfigs:Ljava/util/concurrent/atomic/AtomicReference;
       4: aload_0
       5: getfield      #4                  // Field indexSetService:Lorg/graylog2/indexer/indexset/IndexSetService;
       8: dup
       9: invokestatic  #2                  // Method java/util/Objects.requireNonNull:(Ljava/lang/Object;)Ljava/lang/Object;
      12: pop
      13: invokedynamic #6,  0              // InvokeDynamic #0:get:(Lorg/graylog2/indexer/indexset/IndexSetService;)Lcom/google/common/base/Supplier;
      18: invokestatic  #7                  // Method com/google/common/base/Suppliers.memoize:(Lcom/google/common/base/Supplier;)Lcom/google/common/base/Supplier;
      21: invokevirtual #16                 // Method java/util/concurrent/atomic/AtomicReference.set:(Ljava/lang/Object;)V
      24: return

  void handleIndexSetCreation(org.graylog2.indexer.indexset.events.IndexSetCreatedEvent);
    Code:
       0: aload_0
       1: invokevirtual #17                 // Method invalidate:()V
       4: return

  void handleIndexSetDeletion(org.graylog2.indexer.indexset.events.IndexSetDeletedEvent);
    Code:
       0: aload_0
       1: invokevirtual #17                 // Method invalidate:()V
       4: return
}
