Compiled from "SimpleKey.java"
public class org.springframework.cache.interceptor.SimpleKey implements java.io.Serializable {
  public static final org.springframework.cache.interceptor.SimpleKey EMPTY;

  private final java.lang.Object[] params;

  private final int hashCode;

  public org.springframework.cache.interceptor.SimpleKey(java.lang.Object...);
    Code:
       0: aload_0
       1: invokespecial #1                  // Method java/lang/Object."<init>":()V
       4: aload_1
       5: ldc           #2                  // String Elements must not be null
       7: invokestatic  #3                  // Method org/springframework/util/Assert.notNull:(Ljava/lang/Object;Ljava/lang/String;)V
      10: aload_0
      11: aload_1
      12: arraylength
      13: anewarray     #4                  // class java/lang/Object
      16: putfield      #5                  // Field params:[Ljava/lang/Object;
      19: aload_1
      20: iconst_0
      21: aload_0
      22: getfield      #5                  // Field params:[Ljava/lang/Object;
      25: iconst_0
      26: aload_1
      27: arraylength
      28: invokestatic  #6                  // Method java/lang/System.arraycopy:(Ljava/lang/Object;ILjava/lang/Object;II)V
      31: aload_0
      32: aload_0
      33: getfield      #5                  // Field params:[Ljava/lang/Object;
      36: invokestatic  #7                  // Method java/util/Arrays.deepHashCode:([Ljava/lang/Object;)I
      39: putfield      #8                  // Field hashCode:I
      42: return

  public boolean equals(java.lang.Object);
    Code:
       0: aload_0
       1: aload_1
       2: if_acmpeq     29
       5: aload_1
       6: instanceof    #9                  // class org/springframework/cache/interceptor/SimpleKey
       9: ifeq          33
      12: aload_0
      13: getfield      #5                  // Field params:[Ljava/lang/Object;
      16: aload_1
      17: checkcast     #9                  // class org/springframework/cache/interceptor/SimpleKey
      20: getfield      #5                  // Field params:[Ljava/lang/Object;
      23: invokestatic  #10                 // Method java/util/Arrays.deepEquals:([Ljava/lang/Object;[Ljava/lang/Object;)Z
      26: ifeq          33
      29: iconst_1
      30: goto          34
      33: iconst_0
      34: ireturn

  public final int hashCode();
    Code:
       0: aload_0
       1: getfield      #8                  // Field hashCode:I
       4: ireturn

  public java.lang.String toString();
    Code:
       0: new           #11                 // class java/lang/StringBuilder
       3: dup
       4: invokespecial #12                 // Method java/lang/StringBuilder."<init>":()V
       7: aload_0
       8: invokevirtual #13                 // Method java/lang/Object.getClass:()Ljava/lang/Class;
      11: invokevirtual #14                 // Method java/lang/Class.getSimpleName:()Ljava/lang/String;
      14: invokevirtual #15                 // Method java/lang/StringBuilder.append:(Ljava/lang/String;)Ljava/lang/StringBuilder;
      17: ldc           #16                 // String  [
      19: invokevirtual #15                 // Method java/lang/StringBuilder.append:(Ljava/lang/String;)Ljava/lang/StringBuilder;
      22: aload_0
      23: getfield      #5                  // Field params:[Ljava/lang/Object;
      26: invokestatic  #17                 // Method org/springframework/util/StringUtils.arrayToCommaDelimitedString:([Ljava/lang/Object;)Ljava/lang/String;
      29: invokevirtual #15                 // Method java/lang/StringBuilder.append:(Ljava/lang/String;)Ljava/lang/StringBuilder;
      32: ldc           #18                 // String ]
      34: invokevirtual #15                 // Method java/lang/StringBuilder.append:(Ljava/lang/String;)Ljava/lang/StringBuilder;
      37: invokevirtual #19                 // Method java/lang/StringBuilder.toString:()Ljava/lang/String;
      40: areturn

  static {};
    Code:
       0: new           #9                  // class org/springframework/cache/interceptor/SimpleKey
       3: dup
       4: iconst_0
       5: anewarray     #4                  // class java/lang/Object
       8: invokespecial #20                 // Method "<init>":([Ljava/lang/Object;)V
      11: putstatic     #21                 // Field EMPTY:Lorg/springframework/cache/interceptor/SimpleKey;
      14: return
}
