Compiled from "HornetQChannelHandler.java"
public class org.hornetq.core.remoting.impl.netty.HornetQChannelHandler extends io.netty.channel.ChannelDuplexHandler {
  private final io.netty.channel.group.ChannelGroup group;

  private final org.hornetq.spi.core.remoting.BufferHandler handler;

  private final org.hornetq.spi.core.remoting.ConnectionLifeCycleListener listener;

  volatile boolean active;

  protected org.hornetq.core.remoting.impl.netty.HornetQChannelHandler(io.netty.channel.group.ChannelGroup, org.hornetq.spi.core.remoting.BufferHandler, org.hornetq.spi.core.remoting.ConnectionLifeCycleListener);
    Code:
       0: aload_0
       1: invokespecial #1                  // Method io/netty/channel/ChannelDuplexHandler."<init>":()V
       4: aload_0
       5: aload_1
       6: putfield      #2                  // Field group:Lio/netty/channel/group/ChannelGroup;
       9: aload_0
      10: aload_2
      11: putfield      #3                  // Field handler:Lorg/hornetq/spi/core/remoting/BufferHandler;
      14: aload_0
      15: aload_3
      16: putfield      #4                  // Field listener:Lorg/hornetq/spi/core/remoting/ConnectionLifeCycleListener;
      19: return

  public void channelActive(io.netty.channel.ChannelHandlerContext) throws java.lang.Exception;
    Code:
       0: aload_0
       1: getfield      #2                  // Field group:Lio/netty/channel/group/ChannelGroup;
       4: aload_1
       5: invokeinterface #5,  1            // InterfaceMethod io/netty/channel/ChannelHandlerContext.channel:()Lio/netty/channel/Channel;
      10: invokeinterface #6,  2            // InterfaceMethod io/netty/channel/group/ChannelGroup.add:(Ljava/lang/Object;)Z
      15: pop
      16: aload_1
      17: invokeinterface #7,  1            // InterfaceMethod io/netty/channel/ChannelHandlerContext.fireChannelActive:()Lio/netty/channel/ChannelHandlerContext;
      22: pop
      23: return

  public void channelWritabilityChanged(io.netty.channel.ChannelHandlerContext) throws java.lang.Exception;
    Code:
       0: aload_0
       1: getfield      #4                  // Field listener:Lorg/hornetq/spi/core/remoting/ConnectionLifeCycleListener;
       4: aload_1
       5: invokeinterface #5,  1            // InterfaceMethod io/netty/channel/ChannelHandlerContext.channel:()Lio/netty/channel/Channel;
      10: invokestatic  #8                  // Method channelId:(Lio/netty/channel/Channel;)I
      13: invokestatic  #9                  // Method java/lang/Integer.valueOf:(I)Ljava/lang/Integer;
      16: aload_1
      17: invokeinterface #5,  1            // InterfaceMethod io/netty/channel/ChannelHandlerContext.channel:()Lio/netty/channel/Channel;
      22: invokeinterface #10,  1           // InterfaceMethod io/netty/channel/Channel.isWritable:()Z
      27: invokeinterface #11,  3           // InterfaceMethod org/hornetq/spi/core/remoting/ConnectionLifeCycleListener.connectionReadyForWrites:(Ljava/lang/Object;Z)V
      32: return

  public void channelRead(io.netty.channel.ChannelHandlerContext, java.lang.Object) throws java.lang.Exception;
    Code:
       0: aload_2
       1: checkcast     #12                 // class io/netty/buffer/ByteBuf
       4: astore_3
       5: aload_0
       6: getfield      #3                  // Field handler:Lorg/hornetq/spi/core/remoting/BufferHandler;
       9: aload_1
      10: invokeinterface #5,  1            // InterfaceMethod io/netty/channel/ChannelHandlerContext.channel:()Lio/netty/channel/Channel;
      15: invokestatic  #8                  // Method channelId:(Lio/netty/channel/Channel;)I
      18: invokestatic  #9                  // Method java/lang/Integer.valueOf:(I)Ljava/lang/Integer;
      21: new           #13                 // class org/hornetq/core/buffers/impl/ChannelBufferWrapper
      24: dup
      25: aload_3
      26: invokespecial #14                 // Method org/hornetq/core/buffers/impl/ChannelBufferWrapper."<init>":(Lio/netty/buffer/ByteBuf;)V
      29: invokeinterface #15,  3           // InterfaceMethod org/hornetq/spi/core/remoting/BufferHandler.bufferReceived:(Ljava/lang/Object;Lorg/hornetq/api/core/HornetQBuffer;)V
      34: return

  public void channelInactive(io.netty.channel.ChannelHandlerContext) throws java.lang.Exception;
    Code:
       0: aload_0
       1: dup
       2: astore_2
       3: monitorenter
       4: aload_0
       5: getfield      #16                 // Field active:Z
       8: ifeq          37
      11: aload_0
      12: getfield      #4                  // Field listener:Lorg/hornetq/spi/core/remoting/ConnectionLifeCycleListener;
      15: aload_1
      16: invokeinterface #5,  1            // InterfaceMethod io/netty/channel/ChannelHandlerContext.channel:()Lio/netty/channel/Channel;
      21: invokestatic  #8                  // Method channelId:(Lio/netty/channel/Channel;)I
      24: invokestatic  #9                  // Method java/lang/Integer.valueOf:(I)Ljava/lang/Integer;
      27: invokeinterface #17,  2           // InterfaceMethod org/hornetq/spi/core/remoting/ConnectionLifeCycleListener.connectionDestroyed:(Ljava/lang/Object;)V
      32: aload_0
      33: iconst_0
      34: putfield      #16                 // Field active:Z
      37: aload_2
      38: monitorexit
      39: goto          47
      42: astore_3
      43: aload_2
      44: monitorexit
      45: aload_3
      46: athrow
      47: return
    Exception table:
       from    to  target type
           4    39    42   any
          42    45    42   any

  public void exceptionCaught(io.netty.channel.ChannelHandlerContext, java.lang.Throwable) throws java.lang.Exception;
    Code:
       0: aload_0
       1: getfield      #16                 // Field active:Z
       4: ifne          8
       7: return
       8: getstatic     #18                 // Field org/hornetq/core/client/HornetQClientMessageBundle.BUNDLE:Lorg/hornetq/core/client/HornetQClientMessageBundle;
      11: invokeinterface #19,  1           // InterfaceMethod org/hornetq/core/client/HornetQClientMessageBundle.nettyError:()Lorg/hornetq/api/core/HornetQInternalErrorException;
      16: astore_3
      17: aload_3
      18: aload_2
      19: invokevirtual #20                 // Method org/hornetq/api/core/HornetQException.initCause:(Ljava/lang/Throwable;)Ljava/lang/Throwable;
      22: pop
      23: aload_0
      24: getfield      #4                  // Field listener:Lorg/hornetq/spi/core/remoting/ConnectionLifeCycleListener;
      27: dup
      28: astore        4
      30: monitorenter
      31: aload_0
      32: getfield      #4                  // Field listener:Lorg/hornetq/spi/core/remoting/ConnectionLifeCycleListener;
      35: aload_1
      36: invokeinterface #5,  1            // InterfaceMethod io/netty/channel/ChannelHandlerContext.channel:()Lio/netty/channel/Channel;
      41: invokestatic  #8                  // Method channelId:(Lio/netty/channel/Channel;)I
      44: invokestatic  #9                  // Method java/lang/Integer.valueOf:(I)Ljava/lang/Integer;
      47: aload_3
      48: invokeinterface #21,  3           // InterfaceMethod org/hornetq/spi/core/remoting/ConnectionLifeCycleListener.connectionException:(Ljava/lang/Object;Lorg/hornetq/api/core/HornetQException;)V
      53: aload_0
      54: iconst_0
      55: putfield      #16                 // Field active:Z
      58: goto          73
      61: astore        5
      63: getstatic     #23                 // Field org/hornetq/core/client/HornetQClientLogger.LOGGER:Lorg/hornetq/core/client/HornetQClientLogger;
      66: aload         5
      68: invokeinterface #24,  2           // InterfaceMethod org/hornetq/core/client/HornetQClientLogger.errorCallingLifeCycleListener:(Ljava/lang/Throwable;)V
      73: aload         4
      75: monitorexit
      76: goto          87
      79: astore        6
      81: aload         4
      83: monitorexit
      84: aload         6
      86: athrow
      87: return
    Exception table:
       from    to  target type
          31    58    61   Class java/lang/Exception
          31    76    79   any
          79    84    79   any

  protected static int channelId(io.netty.channel.Channel);
    Code:
       0: aload_0
       1: invokevirtual #25                 // Method java/lang/Object.hashCode:()I
       4: ireturn
}
