Compiled from "NettyConnector.java"
class org.hornetq.core.remoting.impl.netty.NettyConnector$HttpHandler$HttpIdleTimer implements java.lang.Runnable {
  private boolean closed;

  private java.util.concurrent.Future<?> future;

  final org.hornetq.core.remoting.impl.netty.NettyConnector$HttpHandler this$1;

  private org.hornetq.core.remoting.impl.netty.NettyConnector$HttpHandler$HttpIdleTimer(org.hornetq.core.remoting.impl.netty.NettyConnector$HttpHandler);
    Code:
       0: aload_0
       1: aload_1
       2: putfield      #2                  // Field this$1:Lorg/hornetq/core/remoting/impl/netty/NettyConnector$HttpHandler;
       5: aload_0
       6: invokespecial #3                  // Method java/lang/Object."<init>":()V
       9: aload_0
      10: iconst_0
      11: putfield      #4                  // Field closed:Z
      14: return

  public synchronized void run();
    Code:
       0: aload_0
       1: getfield      #4                  // Field closed:Z
       4: ifeq          8
       7: return
       8: aload_0
       9: getfield      #2                  // Field this$1:Lorg/hornetq/core/remoting/impl/netty/NettyConnector$HttpHandler;
      12: invokestatic  #5                  // Method org/hornetq/core/remoting/impl/netty/NettyConnector$HttpHandler.access$1800:(Lorg/hornetq/core/remoting/impl/netty/NettyConnector$HttpHandler;)Z
      15: ifne          109
      18: invokestatic  #6                  // Method java/lang/System.currentTimeMillis:()J
      21: aload_0
      22: getfield      #2                  // Field this$1:Lorg/hornetq/core/remoting/impl/netty/NettyConnector$HttpHandler;
      25: invokestatic  #7                  // Method org/hornetq/core/remoting/impl/netty/NettyConnector$HttpHandler.access$1900:(Lorg/hornetq/core/remoting/impl/netty/NettyConnector$HttpHandler;)J
      28: aload_0
      29: getfield      #2                  // Field this$1:Lorg/hornetq/core/remoting/impl/netty/NettyConnector$HttpHandler;
      32: getfield      #8                  // Field org/hornetq/core/remoting/impl/netty/NettyConnector$HttpHandler.this$0:Lorg/hornetq/core/remoting/impl/netty/NettyConnector;
      35: invokestatic  #9                  // Method org/hornetq/core/remoting/impl/netty/NettyConnector.access$2000:(Lorg/hornetq/core/remoting/impl/netty/NettyConnector;)J
      38: ladd
      39: lcmp
      40: ifle          109
      43: new           #10                 // class io/netty/handler/codec/http/DefaultFullHttpRequest
      46: dup
      47: getstatic     #11                 // Field io/netty/handler/codec/http/HttpVersion.HTTP_1_1:Lio/netty/handler/codec/http/HttpVersion;
      50: getstatic     #12                 // Field io/netty/handler/codec/http/HttpMethod.GET:Lio/netty/handler/codec/http/HttpMethod;
      53: aload_0
      54: getfield      #2                  // Field this$1:Lorg/hornetq/core/remoting/impl/netty/NettyConnector$HttpHandler;
      57: invokestatic  #13                 // Method org/hornetq/core/remoting/impl/netty/NettyConnector$HttpHandler.access$2100:(Lorg/hornetq/core/remoting/impl/netty/NettyConnector$HttpHandler;)Ljava/lang/String;
      60: invokespecial #14                 // Method io/netty/handler/codec/http/DefaultFullHttpRequest."<init>":(Lio/netty/handler/codec/http/HttpVersion;Lio/netty/handler/codec/http/HttpMethod;Ljava/lang/String;)V
      63: astore_1
      64: aload_1
      65: invokeinterface #15,  1           // InterfaceMethod io/netty/handler/codec/http/FullHttpRequest.headers:()Lio/netty/handler/codec/http/HttpHeaders;
      70: ldc           #17                 // String Host
      72: aload_0
      73: getfield      #2                  // Field this$1:Lorg/hornetq/core/remoting/impl/netty/NettyConnector$HttpHandler;
      76: getfield      #8                  // Field org/hornetq/core/remoting/impl/netty/NettyConnector$HttpHandler.this$0:Lorg/hornetq/core/remoting/impl/netty/NettyConnector;
      79: invokestatic  #18                 // Method org/hornetq/core/remoting/impl/netty/NettyConnector.access$1100:(Lorg/hornetq/core/remoting/impl/netty/NettyConnector;)Ljava/lang/String;
      82: invokevirtual #19                 // Method io/netty/handler/codec/http/HttpHeaders.add:(Ljava/lang/String;Ljava/lang/Object;)Lio/netty/handler/codec/http/HttpHeaders;
      85: pop
      86: aload_0
      87: getfield      #2                  // Field this$1:Lorg/hornetq/core/remoting/impl/netty/NettyConnector$HttpHandler;
      90: iconst_1
      91: invokestatic  #20                 // Method org/hornetq/core/remoting/impl/netty/NettyConnector$HttpHandler.access$1802:(Lorg/hornetq/core/remoting/impl/netty/NettyConnector$HttpHandler;Z)Z
      94: pop
      95: aload_0
      96: getfield      #2                  // Field this$1:Lorg/hornetq/core/remoting/impl/netty/NettyConnector$HttpHandler;
      99: invokestatic  #21                 // Method org/hornetq/core/remoting/impl/netty/NettyConnector$HttpHandler.access$2200:(Lorg/hornetq/core/remoting/impl/netty/NettyConnector$HttpHandler;)Lio/netty/channel/Channel;
     102: aload_1
     103: invokeinterface #22,  2           // InterfaceMethod io/netty/channel/Channel.writeAndFlush:(Ljava/lang/Object;)Lio/netty/channel/ChannelFuture;
     108: pop
     109: return

  public synchronized void setFuture(java.util.concurrent.Future<?>);
    Code:
       0: aload_0
       1: aload_1
       2: putfield      #23                 // Field future:Ljava/util/concurrent/Future;
       5: return

  public void close();
    Code:
       0: aload_0
       1: getfield      #23                 // Field future:Ljava/util/concurrent/Future;
       4: ifnull        18
       7: aload_0
       8: getfield      #23                 // Field future:Ljava/util/concurrent/Future;
      11: iconst_0
      12: invokeinterface #24,  2           // InterfaceMethod java/util/concurrent/Future.cancel:(Z)Z
      17: pop
      18: aload_0
      19: iconst_1
      20: putfield      #4                  // Field closed:Z
      23: return

  org.hornetq.core.remoting.impl.netty.NettyConnector$HttpHandler$HttpIdleTimer(org.hornetq.core.remoting.impl.netty.NettyConnector$HttpHandler, org.hornetq.core.remoting.impl.netty.NettyConnector$1);
    Code:
       0: aload_0
       1: aload_1
       2: invokespecial #1                  // Method "<init>":(Lorg/hornetq/core/remoting/impl/netty/NettyConnector$HttpHandler;)V
       5: return
}
