Compiled from "GJMonthOfYearDateTimeField.java"
final class org.joda.time.chrono.GJMonthOfYearDateTimeField extends org.joda.time.chrono.BasicMonthOfYearDateTimeField {
  private static final long serialVersionUID;

  org.joda.time.chrono.GJMonthOfYearDateTimeField(org.joda.time.chrono.BasicChronology);
    Code:
       0: aload_0
       1: aload_1
       2: iconst_2
       3: invokespecial #1                  // Method org/joda/time/chrono/BasicMonthOfYearDateTimeField."<init>":(Lorg/joda/time/chrono/BasicChronology;I)V
       6: return

  public java.lang.String getAsText(int, java.util.Locale);
    Code:
       0: aload_2
       1: invokestatic  #2                  // Method org/joda/time/chrono/GJLocaleSymbols.forLocale:(Ljava/util/Locale;)Lorg/joda/time/chrono/GJLocaleSymbols;
       4: iload_1
       5: invokevirtual #3                  // Method org/joda/time/chrono/GJLocaleSymbols.monthOfYearValueToText:(I)Ljava/lang/String;
       8: areturn

  public java.lang.String getAsShortText(int, java.util.Locale);
    Code:
       0: aload_2
       1: invokestatic  #2                  // Method org/joda/time/chrono/GJLocaleSymbols.forLocale:(Ljava/util/Locale;)Lorg/joda/time/chrono/GJLocaleSymbols;
       4: iload_1
       5: invokevirtual #4                  // Method org/joda/time/chrono/GJLocaleSymbols.monthOfYearValueToShortText:(I)Ljava/lang/String;
       8: areturn

  protected int convertText(java.lang.String, java.util.Locale);
    Code:
       0: aload_2
       1: invokestatic  #2                  // Method org/joda/time/chrono/GJLocaleSymbols.forLocale:(Ljava/util/Locale;)Lorg/joda/time/chrono/GJLocaleSymbols;
       4: aload_1
       5: invokevirtual #5                  // Method org/joda/time/chrono/GJLocaleSymbols.monthOfYearTextToValue:(Ljava/lang/String;)I
       8: ireturn

  public int getMaximumTextLength(java.util.Locale);
    Code:
       0: aload_1
       1: invokestatic  #2                  // Method org/joda/time/chrono/GJLocaleSymbols.forLocale:(Ljava/util/Locale;)Lorg/joda/time/chrono/GJLocaleSymbols;
       4: invokevirtual #6                  // Method org/joda/time/chrono/GJLocaleSymbols.getMonthMaxTextLength:()I
       7: ireturn

  public int getMaximumShortTextLength(java.util.Locale);
    Code:
       0: aload_1
       1: invokestatic  #2                  // Method org/joda/time/chrono/GJLocaleSymbols.forLocale:(Ljava/util/Locale;)Lorg/joda/time/chrono/GJLocaleSymbols;
       4: invokevirtual #7                  // Method org/joda/time/chrono/GJLocaleSymbols.getMonthMaxShortTextLength:()I
       7: ireturn
}
