Compiled from "ReactiveWrapperConverters.java"
public final class org.springframework.data.repository.util.ReactiveWrapperConverters {
  private static final java.util.List<org.springframework.data.repository.util.ReactiveWrapperConverters$ReactiveTypeWrapper<?>> REACTIVE_WRAPPERS;

  private static final org.springframework.core.convert.support.GenericConversionService GENERIC_CONVERSION_SERVICE;

  private static org.springframework.core.convert.ConversionService registerConvertersIn(org.springframework.core.convert.support.ConfigurableConversionService);
    Code:
       0: aload_0
       1: ldc           #2                  // String ConversionService must not be null!
       3: invokestatic  #3                  // Method org/springframework/util/Assert.notNull:(Ljava/lang/Object;Ljava/lang/String;)V
       6: getstatic     #4                  // Field org/springframework/data/repository/util/ReactiveWrappers$ReactiveLibrary.PROJECT_REACTOR:Lorg/springframework/data/repository/util/ReactiveWrappers$ReactiveLibrary;
       9: invokestatic  #5                  // Method org/springframework/data/repository/util/ReactiveWrappers.isAvailable:(Lorg/springframework/data/repository/util/ReactiveWrappers$ReactiveLibrary;)Z
      12: ifeq          366
      15: getstatic     #6                  // Field org/springframework/data/repository/util/ReactiveWrappers$ReactiveLibrary.RXJAVA1:Lorg/springframework/data/repository/util/ReactiveWrappers$ReactiveLibrary;
      18: invokestatic  #5                  // Method org/springframework/data/repository/util/ReactiveWrappers.isAvailable:(Lorg/springframework/data/repository/util/ReactiveWrappers$ReactiveLibrary;)Z
      21: ifeq          123
      24: aload_0
      25: getstatic     #7                  // Field org/springframework/data/repository/util/ReactiveWrapperConverters$PublisherToRxJava1CompletableConverter.INSTANCE:Lorg/springframework/data/repository/util/ReactiveWrapperConverters$PublisherToRxJava1CompletableConverter;
      28: invokeinterface #8,  2            // InterfaceMethod org/springframework/core/convert/support/ConfigurableConversionService.addConverter:(Lorg/springframework/core/convert/converter/Converter;)V
      33: aload_0
      34: getstatic     #9                  // Field org/springframework/data/repository/util/ReactiveWrapperConverters$RxJava1CompletableToPublisherConverter.INSTANCE:Lorg/springframework/data/repository/util/ReactiveWrapperConverters$RxJava1CompletableToPublisherConverter;
      37: invokeinterface #8,  2            // InterfaceMethod org/springframework/core/convert/support/ConfigurableConversionService.addConverter:(Lorg/springframework/core/convert/converter/Converter;)V
      42: aload_0
      43: getstatic     #10                 // Field org/springframework/data/repository/util/ReactiveWrapperConverters$RxJava1CompletableToMonoConverter.INSTANCE:Lorg/springframework/data/repository/util/ReactiveWrapperConverters$RxJava1CompletableToMonoConverter;
      46: invokeinterface #8,  2            // InterfaceMethod org/springframework/core/convert/support/ConfigurableConversionService.addConverter:(Lorg/springframework/core/convert/converter/Converter;)V
      51: aload_0
      52: getstatic     #11                 // Field org/springframework/data/repository/util/ReactiveWrapperConverters$PublisherToRxJava1SingleConverter.INSTANCE:Lorg/springframework/data/repository/util/ReactiveWrapperConverters$PublisherToRxJava1SingleConverter;
      55: invokeinterface #8,  2            // InterfaceMethod org/springframework/core/convert/support/ConfigurableConversionService.addConverter:(Lorg/springframework/core/convert/converter/Converter;)V
      60: aload_0
      61: getstatic     #12                 // Field org/springframework/data/repository/util/ReactiveWrapperConverters$RxJava1SingleToPublisherConverter.INSTANCE:Lorg/springframework/data/repository/util/ReactiveWrapperConverters$RxJava1SingleToPublisherConverter;
      64: invokeinterface #8,  2            // InterfaceMethod org/springframework/core/convert/support/ConfigurableConversionService.addConverter:(Lorg/springframework/core/convert/converter/Converter;)V
      69: aload_0
      70: getstatic     #13                 // Field org/springframework/data/repository/util/ReactiveWrapperConverters$RxJava1SingleToMonoConverter.INSTANCE:Lorg/springframework/data/repository/util/ReactiveWrapperConverters$RxJava1SingleToMonoConverter;
      73: invokeinterface #8,  2            // InterfaceMethod org/springframework/core/convert/support/ConfigurableConversionService.addConverter:(Lorg/springframework/core/convert/converter/Converter;)V
      78: aload_0
      79: getstatic     #14                 // Field org/springframework/data/repository/util/ReactiveWrapperConverters$RxJava1SingleToFluxConverter.INSTANCE:Lorg/springframework/data/repository/util/ReactiveWrapperConverters$RxJava1SingleToFluxConverter;
      82: invokeinterface #8,  2            // InterfaceMethod org/springframework/core/convert/support/ConfigurableConversionService.addConverter:(Lorg/springframework/core/convert/converter/Converter;)V
      87: aload_0
      88: getstatic     #15                 // Field org/springframework/data/repository/util/ReactiveWrapperConverters$PublisherToRxJava1ObservableConverter.INSTANCE:Lorg/springframework/data/repository/util/ReactiveWrapperConverters$PublisherToRxJava1ObservableConverter;
      91: invokeinterface #8,  2            // InterfaceMethod org/springframework/core/convert/support/ConfigurableConversionService.addConverter:(Lorg/springframework/core/convert/converter/Converter;)V
      96: aload_0
      97: getstatic     #16                 // Field org/springframework/data/repository/util/ReactiveWrapperConverters$RxJava1ObservableToPublisherConverter.INSTANCE:Lorg/springframework/data/repository/util/ReactiveWrapperConverters$RxJava1ObservableToPublisherConverter;
     100: invokeinterface #8,  2            // InterfaceMethod org/springframework/core/convert/support/ConfigurableConversionService.addConverter:(Lorg/springframework/core/convert/converter/Converter;)V
     105: aload_0
     106: getstatic     #17                 // Field org/springframework/data/repository/util/ReactiveWrapperConverters$RxJava1ObservableToMonoConverter.INSTANCE:Lorg/springframework/data/repository/util/ReactiveWrapperConverters$RxJava1ObservableToMonoConverter;
     109: invokeinterface #8,  2            // InterfaceMethod org/springframework/core/convert/support/ConfigurableConversionService.addConverter:(Lorg/springframework/core/convert/converter/Converter;)V
     114: aload_0
     115: getstatic     #18                 // Field org/springframework/data/repository/util/ReactiveWrapperConverters$RxJava1ObservableToFluxConverter.INSTANCE:Lorg/springframework/data/repository/util/ReactiveWrapperConverters$RxJava1ObservableToFluxConverter;
     118: invokeinterface #8,  2            // InterfaceMethod org/springframework/core/convert/support/ConfigurableConversionService.addConverter:(Lorg/springframework/core/convert/converter/Converter;)V
     123: getstatic     #19                 // Field org/springframework/data/repository/util/ReactiveWrappers$ReactiveLibrary.RXJAVA2:Lorg/springframework/data/repository/util/ReactiveWrappers$ReactiveLibrary;
     126: invokestatic  #5                  // Method org/springframework/data/repository/util/ReactiveWrappers.isAvailable:(Lorg/springframework/data/repository/util/ReactiveWrappers$ReactiveLibrary;)Z
     129: ifeq          285
     132: aload_0
     133: getstatic     #20                 // Field org/springframework/data/repository/util/ReactiveWrapperConverters$PublisherToRxJava2CompletableConverter.INSTANCE:Lorg/springframework/data/repository/util/ReactiveWrapperConverters$PublisherToRxJava2CompletableConverter;
     136: invokeinterface #8,  2            // InterfaceMethod org/springframework/core/convert/support/ConfigurableConversionService.addConverter:(Lorg/springframework/core/convert/converter/Converter;)V
     141: aload_0
     142: getstatic     #21                 // Field org/springframework/data/repository/util/ReactiveWrapperConverters$RxJava2CompletableToPublisherConverter.INSTANCE:Lorg/springframework/data/repository/util/ReactiveWrapperConverters$RxJava2CompletableToPublisherConverter;
     145: invokeinterface #8,  2            // InterfaceMethod org/springframework/core/convert/support/ConfigurableConversionService.addConverter:(Lorg/springframework/core/convert/converter/Converter;)V
     150: aload_0
     151: getstatic     #22                 // Field org/springframework/data/repository/util/ReactiveWrapperConverters$RxJava2CompletableToMonoConverter.INSTANCE:Lorg/springframework/data/repository/util/ReactiveWrapperConverters$RxJava2CompletableToMonoConverter;
     154: invokeinterface #8,  2            // InterfaceMethod org/springframework/core/convert/support/ConfigurableConversionService.addConverter:(Lorg/springframework/core/convert/converter/Converter;)V
     159: aload_0
     160: getstatic     #23                 // Field org/springframework/data/repository/util/ReactiveWrapperConverters$PublisherToRxJava2SingleConverter.INSTANCE:Lorg/springframework/data/repository/util/ReactiveWrapperConverters$PublisherToRxJava2SingleConverter;
     163: invokeinterface #8,  2            // InterfaceMethod org/springframework/core/convert/support/ConfigurableConversionService.addConverter:(Lorg/springframework/core/convert/converter/Converter;)V
     168: aload_0
     169: getstatic     #24                 // Field org/springframework/data/repository/util/ReactiveWrapperConverters$RxJava2SingleToPublisherConverter.INSTANCE:Lorg/springframework/data/repository/util/ReactiveWrapperConverters$RxJava2SingleToPublisherConverter;
     172: invokeinterface #8,  2            // InterfaceMethod org/springframework/core/convert/support/ConfigurableConversionService.addConverter:(Lorg/springframework/core/convert/converter/Converter;)V
     177: aload_0
     178: getstatic     #25                 // Field org/springframework/data/repository/util/ReactiveWrapperConverters$RxJava2SingleToMonoConverter.INSTANCE:Lorg/springframework/data/repository/util/ReactiveWrapperConverters$RxJava2SingleToMonoConverter;
     181: invokeinterface #8,  2            // InterfaceMethod org/springframework/core/convert/support/ConfigurableConversionService.addConverter:(Lorg/springframework/core/convert/converter/Converter;)V
     186: aload_0
     187: getstatic     #26                 // Field org/springframework/data/repository/util/ReactiveWrapperConverters$RxJava2SingleToFluxConverter.INSTANCE:Lorg/springframework/data/repository/util/ReactiveWrapperConverters$RxJava2SingleToFluxConverter;
     190: invokeinterface #8,  2            // InterfaceMethod org/springframework/core/convert/support/ConfigurableConversionService.addConverter:(Lorg/springframework/core/convert/converter/Converter;)V
     195: aload_0
     196: getstatic     #27                 // Field org/springframework/data/repository/util/ReactiveWrapperConverters$PublisherToRxJava2ObservableConverter.INSTANCE:Lorg/springframework/data/repository/util/ReactiveWrapperConverters$PublisherToRxJava2ObservableConverter;
     199: invokeinterface #8,  2            // InterfaceMethod org/springframework/core/convert/support/ConfigurableConversionService.addConverter:(Lorg/springframework/core/convert/converter/Converter;)V
     204: aload_0
     205: getstatic     #28                 // Field org/springframework/data/repository/util/ReactiveWrapperConverters$RxJava2ObservableToPublisherConverter.INSTANCE:Lorg/springframework/data/repository/util/ReactiveWrapperConverters$RxJava2ObservableToPublisherConverter;
     208: invokeinterface #8,  2            // InterfaceMethod org/springframework/core/convert/support/ConfigurableConversionService.addConverter:(Lorg/springframework/core/convert/converter/Converter;)V
     213: aload_0
     214: getstatic     #29                 // Field org/springframework/data/repository/util/ReactiveWrapperConverters$RxJava2ObservableToMonoConverter.INSTANCE:Lorg/springframework/data/repository/util/ReactiveWrapperConverters$RxJava2ObservableToMonoConverter;
     217: invokeinterface #8,  2            // InterfaceMethod org/springframework/core/convert/support/ConfigurableConversionService.addConverter:(Lorg/springframework/core/convert/converter/Converter;)V
     222: aload_0
     223: getstatic     #30                 // Field org/springframework/data/repository/util/ReactiveWrapperConverters$RxJava2ObservableToFluxConverter.INSTANCE:Lorg/springframework/data/repository/util/ReactiveWrapperConverters$RxJava2ObservableToFluxConverter;
     226: invokeinterface #8,  2            // InterfaceMethod org/springframework/core/convert/support/ConfigurableConversionService.addConverter:(Lorg/springframework/core/convert/converter/Converter;)V
     231: aload_0
     232: getstatic     #31                 // Field org/springframework/data/repository/util/ReactiveWrapperConverters$PublisherToRxJava2FlowableConverter.INSTANCE:Lorg/springframework/data/repository/util/ReactiveWrapperConverters$PublisherToRxJava2FlowableConverter;
     235: invokeinterface #8,  2            // InterfaceMethod org/springframework/core/convert/support/ConfigurableConversionService.addConverter:(Lorg/springframework/core/convert/converter/Converter;)V
     240: aload_0
     241: getstatic     #32                 // Field org/springframework/data/repository/util/ReactiveWrapperConverters$RxJava2FlowableToPublisherConverter.INSTANCE:Lorg/springframework/data/repository/util/ReactiveWrapperConverters$RxJava2FlowableToPublisherConverter;
     244: invokeinterface #8,  2            // InterfaceMethod org/springframework/core/convert/support/ConfigurableConversionService.addConverter:(Lorg/springframework/core/convert/converter/Converter;)V
     249: aload_0
     250: getstatic     #33                 // Field org/springframework/data/repository/util/ReactiveWrapperConverters$PublisherToRxJava2MaybeConverter.INSTANCE:Lorg/springframework/data/repository/util/ReactiveWrapperConverters$PublisherToRxJava2MaybeConverter;
     253: invokeinterface #8,  2            // InterfaceMethod org/springframework/core/convert/support/ConfigurableConversionService.addConverter:(Lorg/springframework/core/convert/converter/Converter;)V
     258: aload_0
     259: getstatic     #34                 // Field org/springframework/data/repository/util/ReactiveWrapperConverters$RxJava2MaybeToPublisherConverter.INSTANCE:Lorg/springframework/data/repository/util/ReactiveWrapperConverters$RxJava2MaybeToPublisherConverter;
     262: invokeinterface #8,  2            // InterfaceMethod org/springframework/core/convert/support/ConfigurableConversionService.addConverter:(Lorg/springframework/core/convert/converter/Converter;)V
     267: aload_0
     268: getstatic     #35                 // Field org/springframework/data/repository/util/ReactiveWrapperConverters$RxJava2MaybeToMonoConverter.INSTANCE:Lorg/springframework/data/repository/util/ReactiveWrapperConverters$RxJava2MaybeToMonoConverter;
     271: invokeinterface #8,  2            // InterfaceMethod org/springframework/core/convert/support/ConfigurableConversionService.addConverter:(Lorg/springframework/core/convert/converter/Converter;)V
     276: aload_0
     277: getstatic     #36                 // Field org/springframework/data/repository/util/ReactiveWrapperConverters$RxJava2MaybeToFluxConverter.INSTANCE:Lorg/springframework/data/repository/util/ReactiveWrapperConverters$RxJava2MaybeToFluxConverter;
     280: invokeinterface #8,  2            // InterfaceMethod org/springframework/core/convert/support/ConfigurableConversionService.addConverter:(Lorg/springframework/core/convert/converter/Converter;)V
     285: aload_0
     286: getstatic     #37                 // Field org/springframework/data/repository/util/ReactiveWrapperConverters$PublisherToMonoConverter.INSTANCE:Lorg/springframework/data/repository/util/ReactiveWrapperConverters$PublisherToMonoConverter;
     289: invokeinterface #8,  2            // InterfaceMethod org/springframework/core/convert/support/ConfigurableConversionService.addConverter:(Lorg/springframework/core/convert/converter/Converter;)V
     294: aload_0
     295: getstatic     #38                 // Field org/springframework/data/repository/util/ReactiveWrapperConverters$PublisherToFluxConverter.INSTANCE:Lorg/springframework/data/repository/util/ReactiveWrapperConverters$PublisherToFluxConverter;
     298: invokeinterface #8,  2            // InterfaceMethod org/springframework/core/convert/support/ConfigurableConversionService.addConverter:(Lorg/springframework/core/convert/converter/Converter;)V
     303: getstatic     #6                  // Field org/springframework/data/repository/util/ReactiveWrappers$ReactiveLibrary.RXJAVA1:Lorg/springframework/data/repository/util/ReactiveWrappers$ReactiveLibrary;
     306: invokestatic  #5                  // Method org/springframework/data/repository/util/ReactiveWrappers.isAvailable:(Lorg/springframework/data/repository/util/ReactiveWrappers$ReactiveLibrary;)Z
     309: ifeq          330
     312: aload_0
     313: getstatic     #39                 // Field org/springframework/data/repository/util/ReactiveWrapperConverters$RxJava1SingleToObservableConverter.INSTANCE:Lorg/springframework/data/repository/util/ReactiveWrapperConverters$RxJava1SingleToObservableConverter;
     316: invokeinterface #8,  2            // InterfaceMethod org/springframework/core/convert/support/ConfigurableConversionService.addConverter:(Lorg/springframework/core/convert/converter/Converter;)V
     321: aload_0
     322: getstatic     #40                 // Field org/springframework/data/repository/util/ReactiveWrapperConverters$RxJava1ObservableToSingleConverter.INSTANCE:Lorg/springframework/data/repository/util/ReactiveWrapperConverters$RxJava1ObservableToSingleConverter;
     325: invokeinterface #8,  2            // InterfaceMethod org/springframework/core/convert/support/ConfigurableConversionService.addConverter:(Lorg/springframework/core/convert/converter/Converter;)V
     330: getstatic     #19                 // Field org/springframework/data/repository/util/ReactiveWrappers$ReactiveLibrary.RXJAVA2:Lorg/springframework/data/repository/util/ReactiveWrappers$ReactiveLibrary;
     333: invokestatic  #5                  // Method org/springframework/data/repository/util/ReactiveWrappers.isAvailable:(Lorg/springframework/data/repository/util/ReactiveWrappers$ReactiveLibrary;)Z
     336: ifeq          366
     339: aload_0
     340: getstatic     #41                 // Field org/springframework/data/repository/util/ReactiveWrapperConverters$RxJava2SingleToObservableConverter.INSTANCE:Lorg/springframework/data/repository/util/ReactiveWrapperConverters$RxJava2SingleToObservableConverter;
     343: invokeinterface #8,  2            // InterfaceMethod org/springframework/core/convert/support/ConfigurableConversionService.addConverter:(Lorg/springframework/core/convert/converter/Converter;)V
     348: aload_0
     349: getstatic     #42                 // Field org/springframework/data/repository/util/ReactiveWrapperConverters$RxJava2ObservableToSingleConverter.INSTANCE:Lorg/springframework/data/repository/util/ReactiveWrapperConverters$RxJava2ObservableToSingleConverter;
     352: invokeinterface #8,  2            // InterfaceMethod org/springframework/core/convert/support/ConfigurableConversionService.addConverter:(Lorg/springframework/core/convert/converter/Converter;)V
     357: aload_0
     358: getstatic     #43                 // Field org/springframework/data/repository/util/ReactiveWrapperConverters$RxJava2ObservableToMaybeConverter.INSTANCE:Lorg/springframework/data/repository/util/ReactiveWrapperConverters$RxJava2ObservableToMaybeConverter;
     361: invokeinterface #8,  2            // InterfaceMethod org/springframework/core/convert/support/ConfigurableConversionService.addConverter:(Lorg/springframework/core/convert/converter/Converter;)V
     366: aload_0
     367: areturn

  public static boolean supports(java.lang.Class<?>);
    Code:
       0: getstatic     #44                 // Field org/springframework/data/repository/util/ReactiveWrapperConverters$RegistryHolder.REACTIVE_ADAPTER_REGISTRY:Lorg/springframework/core/ReactiveAdapterRegistry;
       3: ifnull        20
       6: getstatic     #44                 // Field org/springframework/data/repository/util/ReactiveWrapperConverters$RegistryHolder.REACTIVE_ADAPTER_REGISTRY:Lorg/springframework/core/ReactiveAdapterRegistry;
       9: aload_0
      10: invokevirtual #45                 // Method org/springframework/core/ReactiveAdapterRegistry.getAdapter:(Ljava/lang/Class;)Lorg/springframework/core/ReactiveAdapter;
      13: ifnull        20
      16: iconst_1
      17: goto          21
      20: iconst_0
      21: ireturn

  public static <T> T toWrapper(java.lang.Object, java.lang.Class<? extends T>);
    Code:
       0: aload_0
       1: ldc           #46                 // String Reactive source object must not be null!
       3: invokestatic  #3                  // Method org/springframework/util/Assert.notNull:(Ljava/lang/Object;Ljava/lang/String;)V
       6: aload_1
       7: ldc           #47                 // String Reactive target type must not be null!
       9: invokestatic  #3                  // Method org/springframework/util/Assert.notNull:(Ljava/lang/Object;Ljava/lang/String;)V
      12: aload_1
      13: aload_0
      14: invokevirtual #48                 // Method java/lang/Object.getClass:()Ljava/lang/Class;
      17: invokevirtual #49                 // Method java/lang/Class.isAssignableFrom:(Ljava/lang/Class;)Z
      20: ifeq          25
      23: aload_0
      24: areturn
      25: getstatic     #50                 // Field GENERIC_CONVERSION_SERVICE:Lorg/springframework/core/convert/support/GenericConversionService;
      28: aload_0
      29: aload_1
      30: invokevirtual #51                 // Method org/springframework/core/convert/support/GenericConversionService.convert:(Ljava/lang/Object;Ljava/lang/Class;)Ljava/lang/Object;
      33: areturn

  public static <T> T map(java.lang.Object, java.util.function.Function<java.lang.Object, java.lang.Object>);
    Code:
       0: aload_0
       1: ldc           #46                 // String Reactive source object must not be null!
       3: invokestatic  #3                  // Method org/springframework/util/Assert.notNull:(Ljava/lang/Object;Ljava/lang/String;)V
       6: aload_1
       7: ldc           #52                 // String Converter must not be null!
       9: invokestatic  #3                  // Method org/springframework/util/Assert.notNull:(Ljava/lang/Object;Ljava/lang/String;)V
      12: getstatic     #53                 // Field REACTIVE_WRAPPERS:Ljava/util/List;
      15: invokeinterface #54,  1           // InterfaceMethod java/util/List.stream:()Ljava/util/stream/Stream;
      20: aload_0
      21: invokedynamic #55,  0             // InvokeDynamic #0:test:(Ljava/lang/Object;)Ljava/util/function/Predicate;
      26: invokeinterface #56,  2           // InterfaceMethod java/util/stream/Stream.filter:(Ljava/util/function/Predicate;)Ljava/util/stream/Stream;
      31: invokeinterface #57,  1           // InterfaceMethod java/util/stream/Stream.findFirst:()Ljava/util/Optional;
      36: aload_0
      37: aload_1
      38: invokedynamic #58,  0             // InvokeDynamic #1:apply:(Ljava/lang/Object;Ljava/util/function/Function;)Ljava/util/function/Function;
      43: invokevirtual #59                 // Method java/util/Optional.map:(Ljava/util/function/Function;)Ljava/util/Optional;
      46: aload_0
      47: invokedynamic #60,  0             // InvokeDynamic #2:get:(Ljava/lang/Object;)Ljava/util/function/Supplier;
      52: invokevirtual #61                 // Method java/util/Optional.orElseThrow:(Ljava/util/function/Supplier;)Ljava/lang/Object;
      55: areturn

  public static boolean canConvert(java.lang.Class<?>, java.lang.Class<?>);
    Code:
       0: aload_0
       1: ldc           #62                 // String Source type must not be null!
       3: invokestatic  #3                  // Method org/springframework/util/Assert.notNull:(Ljava/lang/Object;Ljava/lang/String;)V
       6: aload_1
       7: ldc           #63                 // String Target type must not be null!
       9: invokestatic  #3                  // Method org/springframework/util/Assert.notNull:(Ljava/lang/Object;Ljava/lang/String;)V
      12: getstatic     #50                 // Field GENERIC_CONVERSION_SERVICE:Lorg/springframework/core/convert/support/GenericConversionService;
      15: aload_0
      16: aload_1
      17: invokevirtual #64                 // Method org/springframework/core/convert/support/GenericConversionService.canConvert:(Ljava/lang/Class;Ljava/lang/Class;)Z
      20: ireturn

  private static org.springframework.core.ReactiveAdapter getRequiredAdapter(java.lang.Class<?>);
    Code:
       0: getstatic     #44                 // Field org/springframework/data/repository/util/ReactiveWrapperConverters$RegistryHolder.REACTIVE_ADAPTER_REGISTRY:Lorg/springframework/core/ReactiveAdapterRegistry;
       3: astore_1
       4: aload_1
       5: ifnonnull     18
       8: new           #65                 // class java/lang/IllegalStateException
      11: dup
      12: ldc           #66                 // String No reactive adapter registry found!
      14: invokespecial #67                 // Method java/lang/IllegalStateException."<init>":(Ljava/lang/String;)V
      17: athrow
      18: aload_1
      19: aload_0
      20: invokevirtual #45                 // Method org/springframework/core/ReactiveAdapterRegistry.getAdapter:(Ljava/lang/Class;)Lorg/springframework/core/ReactiveAdapter;
      23: astore_2
      24: aload_2
      25: ifnonnull     49
      28: new           #68                 // class java/lang/IllegalArgumentException
      31: dup
      32: ldc           #69                 // String Expected to find reactive adapter for %s but couldn\'t!
      34: iconst_1
      35: anewarray     #70                 // class java/lang/Object
      38: dup
      39: iconst_0
      40: aload_0
      41: aastore
      42: invokestatic  #71                 // Method java/lang/String.format:(Ljava/lang/String;[Ljava/lang/Object;)Ljava/lang/String;
      45: invokespecial #72                 // Method java/lang/IllegalArgumentException."<init>":(Ljava/lang/String;)V
      48: athrow
      49: aload_2
      50: areturn

  private org.springframework.data.repository.util.ReactiveWrapperConverters();
    Code:
       0: aload_0
       1: invokespecial #73                 // Method java/lang/Object."<init>":()V
       4: new           #74                 // class java/lang/UnsupportedOperationException
       7: dup
       8: ldc           #75                 // String This is a utility class and cannot be instantiated
      10: invokespecial #76                 // Method java/lang/UnsupportedOperationException."<init>":(Ljava/lang/String;)V
      13: athrow

  private static java.lang.IllegalStateException lambda$map$2(java.lang.Object);
    Code:
       0: new           #65                 // class java/lang/IllegalStateException
       3: dup
       4: ldc           #77                 // String Cannot apply converter to %s
       6: iconst_1
       7: anewarray     #70                 // class java/lang/Object
      10: dup
      11: iconst_0
      12: aload_0
      13: aastore
      14: invokestatic  #71                 // Method java/lang/String.format:(Ljava/lang/String;[Ljava/lang/Object;)Ljava/lang/String;
      17: invokespecial #67                 // Method java/lang/IllegalStateException."<init>":(Ljava/lang/String;)V
      20: areturn

  private static java.lang.Object lambda$map$1(java.lang.Object, java.util.function.Function, org.springframework.data.repository.util.ReactiveWrapperConverters$ReactiveTypeWrapper);
    Code:
       0: aload_2
       1: aload_0
       2: aload_1
       3: invokeinterface #78,  3           // InterfaceMethod org/springframework/data/repository/util/ReactiveWrapperConverters$ReactiveTypeWrapper.map:(Ljava/lang/Object;Ljava/util/function/Function;)Ljava/lang/Object;
       8: areturn

  private static boolean lambda$map$0(java.lang.Object, org.springframework.data.repository.util.ReactiveWrapperConverters$ReactiveTypeWrapper);
    Code:
       0: aload_1
       1: invokeinterface #79,  1           // InterfaceMethod org/springframework/data/repository/util/ReactiveWrapperConverters$ReactiveTypeWrapper.getWrapperClass:()Ljava/lang/Class;
       6: aload_0
       7: invokevirtual #48                 // Method java/lang/Object.getClass:()Ljava/lang/Class;
      10: invokestatic  #80                 // Method org/springframework/util/ClassUtils.isAssignable:(Ljava/lang/Class;Ljava/lang/Class;)Z
      13: ireturn

  static org.springframework.core.ReactiveAdapter access$000(java.lang.Class);
    Code:
       0: aload_0
       1: invokestatic  #1                  // Method getRequiredAdapter:(Ljava/lang/Class;)Lorg/springframework/core/ReactiveAdapter;
       4: areturn

  static {};
    Code:
       0: new           #81                 // class java/util/ArrayList
       3: dup
       4: invokespecial #82                 // Method java/util/ArrayList."<init>":()V
       7: putstatic     #53                 // Field REACTIVE_WRAPPERS:Ljava/util/List;
      10: new           #83                 // class org/springframework/core/convert/support/GenericConversionService
      13: dup
      14: invokespecial #84                 // Method org/springframework/core/convert/support/GenericConversionService."<init>":()V
      17: putstatic     #50                 // Field GENERIC_CONVERSION_SERVICE:Lorg/springframework/core/convert/support/GenericConversionService;
      20: getstatic     #6                  // Field org/springframework/data/repository/util/ReactiveWrappers$ReactiveLibrary.RXJAVA1:Lorg/springframework/data/repository/util/ReactiveWrappers$ReactiveLibrary;
      23: invokestatic  #5                  // Method org/springframework/data/repository/util/ReactiveWrappers.isAvailable:(Lorg/springframework/data/repository/util/ReactiveWrappers$ReactiveLibrary;)Z
      26: ifeq          53
      29: getstatic     #53                 // Field REACTIVE_WRAPPERS:Ljava/util/List;
      32: getstatic     #85                 // Field org/springframework/data/repository/util/ReactiveWrapperConverters$RxJava1SingleWrapper.INSTANCE:Lorg/springframework/data/repository/util/ReactiveWrapperConverters$RxJava1SingleWrapper;
      35: invokeinterface #86,  2           // InterfaceMethod java/util/List.add:(Ljava/lang/Object;)Z
      40: pop
      41: getstatic     #53                 // Field REACTIVE_WRAPPERS:Ljava/util/List;
      44: getstatic     #87                 // Field org/springframework/data/repository/util/ReactiveWrapperConverters$RxJava1ObservableWrapper.INSTANCE:Lorg/springframework/data/repository/util/ReactiveWrapperConverters$RxJava1ObservableWrapper;
      47: invokeinterface #86,  2           // InterfaceMethod java/util/List.add:(Ljava/lang/Object;)Z
      52: pop
      53: getstatic     #19                 // Field org/springframework/data/repository/util/ReactiveWrappers$ReactiveLibrary.RXJAVA2:Lorg/springframework/data/repository/util/ReactiveWrappers$ReactiveLibrary;
      56: invokestatic  #5                  // Method org/springframework/data/repository/util/ReactiveWrappers.isAvailable:(Lorg/springframework/data/repository/util/ReactiveWrappers$ReactiveLibrary;)Z
      59: ifeq          110
      62: getstatic     #53                 // Field REACTIVE_WRAPPERS:Ljava/util/List;
      65: getstatic     #88                 // Field org/springframework/data/repository/util/ReactiveWrapperConverters$RxJava2SingleWrapper.INSTANCE:Lorg/springframework/data/repository/util/ReactiveWrapperConverters$RxJava2SingleWrapper;
      68: invokeinterface #86,  2           // InterfaceMethod java/util/List.add:(Ljava/lang/Object;)Z
      73: pop
      74: getstatic     #53                 // Field REACTIVE_WRAPPERS:Ljava/util/List;
      77: getstatic     #89                 // Field org/springframework/data/repository/util/ReactiveWrapperConverters$RxJava2MaybeWrapper.INSTANCE:Lorg/springframework/data/repository/util/ReactiveWrapperConverters$RxJava2MaybeWrapper;
      80: invokeinterface #86,  2           // InterfaceMethod java/util/List.add:(Ljava/lang/Object;)Z
      85: pop
      86: getstatic     #53                 // Field REACTIVE_WRAPPERS:Ljava/util/List;
      89: getstatic     #90                 // Field org/springframework/data/repository/util/ReactiveWrapperConverters$RxJava2ObservableWrapper.INSTANCE:Lorg/springframework/data/repository/util/ReactiveWrapperConverters$RxJava2ObservableWrapper;
      92: invokeinterface #86,  2           // InterfaceMethod java/util/List.add:(Ljava/lang/Object;)Z
      97: pop
      98: getstatic     #53                 // Field REACTIVE_WRAPPERS:Ljava/util/List;
     101: getstatic     #91                 // Field org/springframework/data/repository/util/ReactiveWrapperConverters$RxJava2FlowableWrapper.INSTANCE:Lorg/springframework/data/repository/util/ReactiveWrapperConverters$RxJava2FlowableWrapper;
     104: invokeinterface #86,  2           // InterfaceMethod java/util/List.add:(Ljava/lang/Object;)Z
     109: pop
     110: getstatic     #4                  // Field org/springframework/data/repository/util/ReactiveWrappers$ReactiveLibrary.PROJECT_REACTOR:Lorg/springframework/data/repository/util/ReactiveWrappers$ReactiveLibrary;
     113: invokestatic  #5                  // Method org/springframework/data/repository/util/ReactiveWrappers.isAvailable:(Lorg/springframework/data/repository/util/ReactiveWrappers$ReactiveLibrary;)Z
     116: ifeq          155
     119: getstatic     #53                 // Field REACTIVE_WRAPPERS:Ljava/util/List;
     122: getstatic     #92                 // Field org/springframework/data/repository/util/ReactiveWrapperConverters$FluxWrapper.INSTANCE:Lorg/springframework/data/repository/util/ReactiveWrapperConverters$FluxWrapper;
     125: invokeinterface #86,  2           // InterfaceMethod java/util/List.add:(Ljava/lang/Object;)Z
     130: pop
     131: getstatic     #53                 // Field REACTIVE_WRAPPERS:Ljava/util/List;
     134: getstatic     #93                 // Field org/springframework/data/repository/util/ReactiveWrapperConverters$MonoWrapper.INSTANCE:Lorg/springframework/data/repository/util/ReactiveWrapperConverters$MonoWrapper;
     137: invokeinterface #86,  2           // InterfaceMethod java/util/List.add:(Ljava/lang/Object;)Z
     142: pop
     143: getstatic     #53                 // Field REACTIVE_WRAPPERS:Ljava/util/List;
     146: getstatic     #94                 // Field org/springframework/data/repository/util/ReactiveWrapperConverters$PublisherWrapper.INSTANCE:Lorg/springframework/data/repository/util/ReactiveWrapperConverters$PublisherWrapper;
     149: invokeinterface #86,  2           // InterfaceMethod java/util/List.add:(Ljava/lang/Object;)Z
     154: pop
     155: getstatic     #50                 // Field GENERIC_CONVERSION_SERVICE:Lorg/springframework/core/convert/support/GenericConversionService;
     158: invokestatic  #95                 // Method registerConvertersIn:(Lorg/springframework/core/convert/support/ConfigurableConversionService;)Lorg/springframework/core/convert/ConversionService;
     161: pop
     162: return
}
