Compiled from "ArrayTable.java"
class com.google.common.collect.ArrayTable$RowEntrySet$1$1 extends com.google.common.collect.AbstractMapEntry<C, V> {
  final int val$columnIndex;

  final com.google.common.collect.ArrayTable$RowEntrySet$1 this$2;

  com.google.common.collect.ArrayTable$RowEntrySet$1$1(com.google.common.collect.ArrayTable$RowEntrySet$1, int);
    Code:
       0: aload_0
       1: aload_1
       2: putfield      #1                  // Field this$2:Lcom/google/common/collect/ArrayTable$RowEntrySet$1;
       5: aload_0
       6: iload_2
       7: putfield      #2                  // Field val$columnIndex:I
      10: aload_0
      11: invokespecial #3                  // Method com/google/common/collect/AbstractMapEntry."<init>":()V
      14: return

  public C getKey();
    Code:
       0: aload_0
       1: getfield      #1                  // Field this$2:Lcom/google/common/collect/ArrayTable$RowEntrySet$1;
       4: getfield      #4                  // Field com/google/common/collect/ArrayTable$RowEntrySet$1.this$1:Lcom/google/common/collect/ArrayTable$RowEntrySet;
       7: getfield      #5                  // Field com/google/common/collect/ArrayTable$RowEntrySet.this$0:Lcom/google/common/collect/ArrayTable;
      10: invokestatic  #6                  // Method com/google/common/collect/ArrayTable.access$100:(Lcom/google/common/collect/ArrayTable;)Lcom/google/common/collect/ImmutableList;
      13: aload_0
      14: getfield      #2                  // Field val$columnIndex:I
      17: invokevirtual #7                  // Method com/google/common/collect/ImmutableList.get:(I)Ljava/lang/Object;
      20: areturn

  public V getValue();
    Code:
       0: aload_0
       1: getfield      #1                  // Field this$2:Lcom/google/common/collect/ArrayTable$RowEntrySet$1;
       4: getfield      #4                  // Field com/google/common/collect/ArrayTable$RowEntrySet$1.this$1:Lcom/google/common/collect/ArrayTable$RowEntrySet;
       7: getfield      #5                  // Field com/google/common/collect/ArrayTable$RowEntrySet.this$0:Lcom/google/common/collect/ArrayTable;
      10: invokestatic  #8                  // Method com/google/common/collect/ArrayTable.access$300:(Lcom/google/common/collect/ArrayTable;)[[Ljava/lang/Object;
      13: aload_0
      14: getfield      #1                  // Field this$2:Lcom/google/common/collect/ArrayTable$RowEntrySet$1;
      17: getfield      #4                  // Field com/google/common/collect/ArrayTable$RowEntrySet$1.this$1:Lcom/google/common/collect/ArrayTable$RowEntrySet;
      20: getfield      #9                  // Field com/google/common/collect/ArrayTable$RowEntrySet.rowIndex:I
      23: aaload
      24: aload_0
      25: getfield      #2                  // Field val$columnIndex:I
      28: aaload
      29: areturn

  public V setValue(V);
    Code:
       0: aload_0
       1: getfield      #1                  // Field this$2:Lcom/google/common/collect/ArrayTable$RowEntrySet$1;
       4: getfield      #4                  // Field com/google/common/collect/ArrayTable$RowEntrySet$1.this$1:Lcom/google/common/collect/ArrayTable$RowEntrySet;
       7: getfield      #5                  // Field com/google/common/collect/ArrayTable$RowEntrySet.this$0:Lcom/google/common/collect/ArrayTable;
      10: aload_0
      11: getfield      #1                  // Field this$2:Lcom/google/common/collect/ArrayTable$RowEntrySet$1;
      14: getfield      #4                  // Field com/google/common/collect/ArrayTable$RowEntrySet$1.this$1:Lcom/google/common/collect/ArrayTable$RowEntrySet;
      17: getfield      #9                  // Field com/google/common/collect/ArrayTable$RowEntrySet.rowIndex:I
      20: aload_0
      21: getfield      #2                  // Field val$columnIndex:I
      24: aload_1
      25: invokevirtual #10                 // Method com/google/common/collect/ArrayTable.set:(IILjava/lang/Object;)Ljava/lang/Object;
      28: areturn
}
