Compiled from "Sets.java"
abstract class com.google.common.collect.Sets$InvertibleFunction<A, B> implements com.google.common.base.Function<A, B> {
  com.google.common.collect.Sets$InvertibleFunction();
    Code:
       0: aload_0
       1: invokespecial #1                  // Method java/lang/Object."<init>":()V
       4: return

  abstract A invert(B);

  public com.google.common.collect.Sets$InvertibleFunction<B, A> inverse();
    Code:
       0: new           #2                  // class com/google/common/collect/Sets$InvertibleFunction$1
       3: dup
       4: aload_0
       5: invokespecial #3                  // Method com/google/common/collect/Sets$InvertibleFunction$1."<init>":(Lcom/google/common/collect/Sets$InvertibleFunction;)V
       8: areturn
}
