Compiled from "BeanMethods.java"
public class org.jboss.weld.util.BeanMethods {
  private static final com.google.common.base.Predicate<org.jboss.weld.annotated.enhanced.EnhancedAnnotatedMethod<?, ?>> METHOD_FILTER_PREDICATE;

  private org.jboss.weld.util.BeanMethods();
    Code:
       0: aload_0
       1: invokespecial #1                  // Method java/lang/Object."<init>":()V
       4: return

  private static <T, R> R getMethods(org.jboss.weld.annotated.enhanced.EnhancedAnnotatedType<T>, org.jboss.weld.util.BeanMethods$MethodListBuilder<T, R>);
    Code:
       0: aload_1
       1: aload_0
       2: invokeinterface #2,  2            // InterfaceMethod org/jboss/weld/util/BeanMethods$MethodListBuilder.getAllMethods:(Lorg/jboss/weld/annotated/enhanced/EnhancedAnnotatedType;)Ljava/util/Collection;
       7: invokestatic  #3                  // Method filterMethods:(Ljava/util/Collection;)Ljava/util/Collection;
      10: astore_2
      11: aload_0
      12: invokeinterface #4,  1            // InterfaceMethod org/jboss/weld/annotated/enhanced/EnhancedAnnotatedType.getJavaClass:()Ljava/lang/Class;
      17: astore_3
      18: aload_3
      19: ifnull        107
      22: aload_3
      23: ldc           #5                  // class java/lang/Object
      25: if_acmpeq     107
      28: aload_1
      29: aload_3
      30: invokeinterface #6,  2            // InterfaceMethod org/jboss/weld/util/BeanMethods$MethodListBuilder.levelStart:(Ljava/lang/Class;)V
      35: aload_2
      36: invokeinterface #7,  1            // InterfaceMethod java/util/Collection.iterator:()Ljava/util/Iterator;
      41: astore        4
      43: aload         4
      45: invokeinterface #8,  1            // InterfaceMethod java/util/Iterator.hasNext:()Z
      50: ifeq          93
      53: aload         4
      55: invokeinterface #9,  1            // InterfaceMethod java/util/Iterator.next:()Ljava/lang/Object;
      60: checkcast     #10                 // class org/jboss/weld/annotated/enhanced/EnhancedAnnotatedMethod
      63: astore        5
      65: aload         5
      67: invokeinterface #11,  1           // InterfaceMethod org/jboss/weld/annotated/enhanced/EnhancedAnnotatedMethod.getJavaMember:()Ljava/lang/reflect/Method;
      72: invokevirtual #12                 // Method java/lang/reflect/Method.getDeclaringClass:()Ljava/lang/Class;
      75: aload_3
      76: invokevirtual #13                 // Method java/lang/Object.equals:(Ljava/lang/Object;)Z
      79: ifeq          90
      82: aload_1
      83: aload         5
      85: invokeinterface #14,  2           // InterfaceMethod org/jboss/weld/util/BeanMethods$MethodListBuilder.processMethod:(Lorg/jboss/weld/annotated/enhanced/EnhancedAnnotatedMethod;)V
      90: goto          43
      93: aload_1
      94: invokeinterface #15,  1           // InterfaceMethod org/jboss/weld/util/BeanMethods$MethodListBuilder.levelFinish:()V
      99: aload_3
     100: invokevirtual #16                 // Method java/lang/Class.getSuperclass:()Ljava/lang/Class;
     103: astore_3
     104: goto          18
     107: aload_1
     108: invokeinterface #17,  1           // InterfaceMethod org/jboss/weld/util/BeanMethods$MethodListBuilder.create:()Ljava/lang/Object;
     113: areturn

  public static <T> java.util.List<javax.enterprise.inject.spi.AnnotatedMethod<? super T>> getPostConstructMethods(org.jboss.weld.annotated.enhanced.EnhancedAnnotatedType<T>);
    Code:
       0: aload_0
       1: new           #18                 // class org/jboss/weld/util/BeanMethods$2
       4: dup
       5: aload_0
       6: invokespecial #19                 // Method org/jboss/weld/util/BeanMethods$2."<init>":(Lorg/jboss/weld/annotated/enhanced/EnhancedAnnotatedType;)V
       9: invokestatic  #20                 // Method getMethods:(Lorg/jboss/weld/annotated/enhanced/EnhancedAnnotatedType;Lorg/jboss/weld/util/BeanMethods$MethodListBuilder;)Ljava/lang/Object;
      12: checkcast     #21                 // class java/util/List
      15: areturn

  public static <T> java.util.List<javax.enterprise.inject.spi.AnnotatedMethod<? super T>> getPreDestroyMethods(org.jboss.weld.annotated.enhanced.EnhancedAnnotatedType<T>);
    Code:
       0: aload_0
       1: new           #22                 // class org/jboss/weld/util/BeanMethods$3
       4: dup
       5: aload_0
       6: invokespecial #23                 // Method org/jboss/weld/util/BeanMethods$3."<init>":(Lorg/jboss/weld/annotated/enhanced/EnhancedAnnotatedType;)V
       9: invokestatic  #20                 // Method getMethods:(Lorg/jboss/weld/annotated/enhanced/EnhancedAnnotatedType;Lorg/jboss/weld/util/BeanMethods$MethodListBuilder;)Ljava/lang/Object;
      12: checkcast     #21                 // class java/util/List
      15: areturn

  public static <T> java.util.List<java.util.Set<org.jboss.weld.injection.MethodInjectionPoint<?, ?>>> getInitializerMethods(javax.enterprise.inject.spi.Bean<?>, org.jboss.weld.annotated.enhanced.EnhancedAnnotatedType<T>, org.jboss.weld.manager.BeanManagerImpl);
    Code:
       0: aload_1
       1: new           #24                 // class org/jboss/weld/util/BeanMethods$InitializerMethodListBuilder
       4: dup
       5: aload_1
       6: aload_0
       7: aload_2
       8: invokespecial #25                 // Method org/jboss/weld/util/BeanMethods$InitializerMethodListBuilder."<init>":(Lorg/jboss/weld/annotated/enhanced/EnhancedAnnotatedType;Ljavax/enterprise/inject/spi/Bean;Lorg/jboss/weld/manager/BeanManagerImpl;)V
      11: invokestatic  #20                 // Method getMethods:(Lorg/jboss/weld/annotated/enhanced/EnhancedAnnotatedType;Lorg/jboss/weld/util/BeanMethods$MethodListBuilder;)Ljava/lang/Object;
      14: checkcast     #21                 // class java/util/List
      17: areturn

  public static <T> java.util.Collection<org.jboss.weld.annotated.enhanced.EnhancedAnnotatedMethod<?, ? super T>> getObserverMethods(org.jboss.weld.annotated.enhanced.EnhancedAnnotatedType<T>);
    Code:
       0: aload_0
       1: ldc           #26                 // class javax/enterprise/event/Observes
       3: invokeinterface #27,  2           // InterfaceMethod org/jboss/weld/annotated/enhanced/EnhancedAnnotatedType.getEnhancedMethodsWithAnnotatedParameters:(Ljava/lang/Class;)Ljava/util/Collection;
       8: invokestatic  #3                  // Method filterMethods:(Ljava/util/Collection;)Ljava/util/Collection;
      11: areturn

  public static <T> java.util.Collection<org.jboss.weld.annotated.enhanced.EnhancedAnnotatedMethod<?, ? super T>> filterMethods(java.util.Collection<org.jboss.weld.annotated.enhanced.EnhancedAnnotatedMethod<?, ? super T>>);
    Code:
       0: aload_0
       1: getstatic     #28                 // Field METHOD_FILTER_PREDICATE:Lcom/google/common/base/Predicate;
       4: invokestatic  #29                 // Method com/google/common/collect/Collections2.filter:(Ljava/util/Collection;Lcom/google/common/base/Predicate;)Ljava/util/Collection;
       7: areturn

  public static <T> java.util.List<java.lang.reflect.Method> getInterceptorMethods(org.jboss.weld.annotated.enhanced.EnhancedAnnotatedType<T>, org.jboss.weld.interceptor.spi.model.InterceptionType, boolean);
    Code:
       0: aload_0
       1: new           #30                 // class org/jboss/weld/util/BeanMethods$4
       4: dup
       5: aload_1
       6: iload_2
       7: invokespecial #31                 // Method org/jboss/weld/util/BeanMethods$4."<init>":(Lorg/jboss/weld/interceptor/spi/model/InterceptionType;Z)V
      10: invokestatic  #20                 // Method getMethods:(Lorg/jboss/weld/annotated/enhanced/EnhancedAnnotatedType;Lorg/jboss/weld/util/BeanMethods$MethodListBuilder;)Ljava/lang/Object;
      13: checkcast     #21                 // class java/util/List
      16: areturn

  static {};
    Code:
       0: new           #32                 // class org/jboss/weld/util/BeanMethods$1
       3: dup
       4: invokespecial #33                 // Method org/jboss/weld/util/BeanMethods$1."<init>":()V
       7: putstatic     #28                 // Field METHOD_FILTER_PREDICATE:Lcom/google/common/base/Predicate;
      10: return
}
