Compiled from "EjbJaccService.java"
public class org.jboss.as.ejb3.security.EjbJaccService extends org.jboss.as.security.service.JaccService<org.jboss.as.server.deployment.AttachmentList<org.jboss.as.ejb3.security.EjbJaccConfig>> {
  public org.jboss.as.ejb3.security.EjbJaccService(java.lang.String, org.jboss.as.server.deployment.AttachmentList<org.jboss.as.ejb3.security.EjbJaccConfig>, java.lang.Boolean);
    Code:
       0: aload_0
       1: aload_1
       2: aload_2
       3: aload_3
       4: invokespecial #1                  // Method org/jboss/as/security/service/JaccService."<init>":(Ljava/lang/String;Ljava/lang/Object;Ljava/lang/Boolean;)V
       7: return

  public void createPermissions(org.jboss.as.server.deployment.AttachmentList<org.jboss.as.ejb3.security.EjbJaccConfig>, javax.security.jacc.PolicyConfiguration) throws javax.security.jacc.PolicyContextException;
    Code:
       0: aload_1
       1: invokevirtual #2                  // Method org/jboss/as/server/deployment/AttachmentList.iterator:()Ljava/util/Iterator;
       4: astore_3
       5: aload_3
       6: invokeinterface #3,  1            // InterfaceMethod java/util/Iterator.hasNext:()Z
      11: ifeq          181
      14: aload_3
      15: invokeinterface #4,  1            // InterfaceMethod java/util/Iterator.next:()Ljava/lang/Object;
      20: checkcast     #5                  // class org/jboss/as/ejb3/security/EjbJaccConfig
      23: astore        4
      25: aload         4
      27: invokevirtual #6                  // Method org/jboss/as/ejb3/security/EjbJaccConfig.getDeny:()Ljava/util/List;
      30: invokeinterface #7,  1            // InterfaceMethod java/util/List.iterator:()Ljava/util/Iterator;
      35: astore        5
      37: aload         5
      39: invokeinterface #3,  1            // InterfaceMethod java/util/Iterator.hasNext:()Z
      44: ifeq          70
      47: aload         5
      49: invokeinterface #4,  1            // InterfaceMethod java/util/Iterator.next:()Ljava/lang/Object;
      54: checkcast     #8                  // class java/security/Permission
      57: astore        6
      59: aload_2
      60: aload         6
      62: invokeinterface #9,  2            // InterfaceMethod javax/security/jacc/PolicyConfiguration.addToExcludedPolicy:(Ljava/security/Permission;)V
      67: goto          37
      70: aload         4
      72: invokevirtual #10                 // Method org/jboss/as/ejb3/security/EjbJaccConfig.getPermit:()Ljava/util/List;
      75: invokeinterface #7,  1            // InterfaceMethod java/util/List.iterator:()Ljava/util/Iterator;
      80: astore        5
      82: aload         5
      84: invokeinterface #3,  1            // InterfaceMethod java/util/Iterator.hasNext:()Z
      89: ifeq          115
      92: aload         5
      94: invokeinterface #4,  1            // InterfaceMethod java/util/Iterator.next:()Ljava/lang/Object;
      99: checkcast     #8                  // class java/security/Permission
     102: astore        6
     104: aload_2
     105: aload         6
     107: invokeinterface #11,  2           // InterfaceMethod javax/security/jacc/PolicyConfiguration.addToUncheckedPolicy:(Ljava/security/Permission;)V
     112: goto          82
     115: aload         4
     117: invokevirtual #12                 // Method org/jboss/as/ejb3/security/EjbJaccConfig.getRoles:()Ljava/util/List;
     120: invokeinterface #7,  1            // InterfaceMethod java/util/List.iterator:()Ljava/util/Iterator;
     125: astore        5
     127: aload         5
     129: invokeinterface #3,  1            // InterfaceMethod java/util/Iterator.hasNext:()Z
     134: ifeq          178
     137: aload         5
     139: invokeinterface #4,  1            // InterfaceMethod java/util/Iterator.next:()Ljava/lang/Object;
     144: checkcast     #13                 // class java/util/Map$Entry
     147: astore        6
     149: aload_2
     150: aload         6
     152: invokeinterface #14,  1           // InterfaceMethod java/util/Map$Entry.getKey:()Ljava/lang/Object;
     157: checkcast     #15                 // class java/lang/String
     160: aload         6
     162: invokeinterface #16,  1           // InterfaceMethod java/util/Map$Entry.getValue:()Ljava/lang/Object;
     167: checkcast     #8                  // class java/security/Permission
     170: invokeinterface #17,  3           // InterfaceMethod javax/security/jacc/PolicyConfiguration.addToRole:(Ljava/lang/String;Ljava/security/Permission;)V
     175: goto          127
     178: goto          5
     181: return

  public void createPermissions(java.lang.Object, javax.security.jacc.PolicyConfiguration) throws javax.security.jacc.PolicyContextException;
    Code:
       0: aload_0
       1: aload_1
       2: checkcast     #18                 // class org/jboss/as/server/deployment/AttachmentList
       5: aload_2
       6: invokevirtual #19                 // Method createPermissions:(Lorg/jboss/as/server/deployment/AttachmentList;Ljavax/security/jacc/PolicyConfiguration;)V
       9: return
}
