Compiled from "MatchItem.java"
public class edu.indiana.lib.twinpeaks.search.MatchItem$PartPair {
  private org.osid.shared.Id __id;

  private java.io.Serializable __value;

  private edu.indiana.lib.twinpeaks.search.MatchItem$PartPair();
    Code:
       0: aload_0
       1: invokespecial #1                  // Method java/lang/Object."<init>":()V
       4: return

  private edu.indiana.lib.twinpeaks.search.MatchItem$PartPair(org.osid.shared.Id, java.io.Serializable);
    Code:
       0: aload_0
       1: invokespecial #1                  // Method java/lang/Object."<init>":()V
       4: aload_0
       5: aload_1
       6: putfield      #2                  // Field __id:Lorg/osid/shared/Id;
       9: aload_0
      10: aload_2
      11: putfield      #3                  // Field __value:Ljava/io/Serializable;
      14: return

  public org.osid.shared.Id getId();
    Code:
       0: aload_0
       1: getfield      #2                  // Field __id:Lorg/osid/shared/Id;
       4: areturn

  public java.io.Serializable getValue();
    Code:
       0: aload_0
       1: getfield      #3                  // Field __value:Ljava/io/Serializable;
       4: areturn
}
