Compiled from "CommonIronJacamarParser.java"
class org.jboss.jca.common.metadata.common.CommonIronJacamarParser$1 {
  static final int[] $SwitchMap$org$jboss$jca$common$api$metadata$resourceadapter$AdminObject$Attribute;

  static final int[] $SwitchMap$org$jboss$jca$common$api$metadata$resourceadapter$AdminObject$Tag;

  static final int[] $SwitchMap$org$jboss$jca$common$api$metadata$resourceadapter$WorkManager$Tag;

  static final int[] $SwitchMap$org$jboss$jca$common$api$metadata$resourceadapter$WorkManagerSecurity$Tag;

  static final int[] $SwitchMap$org$jboss$jca$common$api$metadata$resourceadapter$ConnectionDefinition$Attribute;

  static final int[] $SwitchMap$org$jboss$jca$common$api$metadata$resourceadapter$ConnectionDefinition$Tag;

  static {};
    Code:
       0: invokestatic  #1                  // Method org/jboss/jca/common/api/metadata/resourceadapter/ConnectionDefinition$Tag.values:()[Lorg/jboss/jca/common/api/metadata/resourceadapter/ConnectionDefinition$Tag;
       3: arraylength
       4: newarray       int
       6: putstatic     #2                  // Field $SwitchMap$org$jboss$jca$common$api$metadata$resourceadapter$ConnectionDefinition$Tag:[I
       9: getstatic     #2                  // Field $SwitchMap$org$jboss$jca$common$api$metadata$resourceadapter$ConnectionDefinition$Tag:[I
      12: getstatic     #3                  // Field org/jboss/jca/common/api/metadata/resourceadapter/ConnectionDefinition$Tag.CONFIG_PROPERTY:Lorg/jboss/jca/common/api/metadata/resourceadapter/ConnectionDefinition$Tag;
      15: invokevirtual #4                  // Method org/jboss/jca/common/api/metadata/resourceadapter/ConnectionDefinition$Tag.ordinal:()I
      18: iconst_1
      19: iastore
      20: goto          24
      23: astore_0
      24: getstatic     #2                  // Field $SwitchMap$org$jboss$jca$common$api$metadata$resourceadapter$ConnectionDefinition$Tag:[I
      27: getstatic     #6                  // Field org/jboss/jca/common/api/metadata/resourceadapter/ConnectionDefinition$Tag.SECURITY:Lorg/jboss/jca/common/api/metadata/resourceadapter/ConnectionDefinition$Tag;
      30: invokevirtual #4                  // Method org/jboss/jca/common/api/metadata/resourceadapter/ConnectionDefinition$Tag.ordinal:()I
      33: iconst_2
      34: iastore
      35: goto          39
      38: astore_0
      39: getstatic     #2                  // Field $SwitchMap$org$jboss$jca$common$api$metadata$resourceadapter$ConnectionDefinition$Tag:[I
      42: getstatic     #7                  // Field org/jboss/jca/common/api/metadata/resourceadapter/ConnectionDefinition$Tag.TIMEOUT:Lorg/jboss/jca/common/api/metadata/resourceadapter/ConnectionDefinition$Tag;
      45: invokevirtual #4                  // Method org/jboss/jca/common/api/metadata/resourceadapter/ConnectionDefinition$Tag.ordinal:()I
      48: iconst_3
      49: iastore
      50: goto          54
      53: astore_0
      54: getstatic     #2                  // Field $SwitchMap$org$jboss$jca$common$api$metadata$resourceadapter$ConnectionDefinition$Tag:[I
      57: getstatic     #8                  // Field org/jboss/jca/common/api/metadata/resourceadapter/ConnectionDefinition$Tag.VALIDATION:Lorg/jboss/jca/common/api/metadata/resourceadapter/ConnectionDefinition$Tag;
      60: invokevirtual #4                  // Method org/jboss/jca/common/api/metadata/resourceadapter/ConnectionDefinition$Tag.ordinal:()I
      63: iconst_4
      64: iastore
      65: goto          69
      68: astore_0
      69: getstatic     #2                  // Field $SwitchMap$org$jboss$jca$common$api$metadata$resourceadapter$ConnectionDefinition$Tag:[I
      72: getstatic     #9                  // Field org/jboss/jca/common/api/metadata/resourceadapter/ConnectionDefinition$Tag.XA_POOL:Lorg/jboss/jca/common/api/metadata/resourceadapter/ConnectionDefinition$Tag;
      75: invokevirtual #4                  // Method org/jboss/jca/common/api/metadata/resourceadapter/ConnectionDefinition$Tag.ordinal:()I
      78: iconst_5
      79: iastore
      80: goto          84
      83: astore_0
      84: getstatic     #2                  // Field $SwitchMap$org$jboss$jca$common$api$metadata$resourceadapter$ConnectionDefinition$Tag:[I
      87: getstatic     #10                 // Field org/jboss/jca/common/api/metadata/resourceadapter/ConnectionDefinition$Tag.POOL:Lorg/jboss/jca/common/api/metadata/resourceadapter/ConnectionDefinition$Tag;
      90: invokevirtual #4                  // Method org/jboss/jca/common/api/metadata/resourceadapter/ConnectionDefinition$Tag.ordinal:()I
      93: bipush        6
      95: iastore
      96: goto          100
      99: astore_0
     100: getstatic     #2                  // Field $SwitchMap$org$jboss$jca$common$api$metadata$resourceadapter$ConnectionDefinition$Tag:[I
     103: getstatic     #11                 // Field org/jboss/jca/common/api/metadata/resourceadapter/ConnectionDefinition$Tag.RECOVERY:Lorg/jboss/jca/common/api/metadata/resourceadapter/ConnectionDefinition$Tag;
     106: invokevirtual #4                  // Method org/jboss/jca/common/api/metadata/resourceadapter/ConnectionDefinition$Tag.ordinal:()I
     109: bipush        7
     111: iastore
     112: goto          116
     115: astore_0
     116: invokestatic  #12                 // Method org/jboss/jca/common/api/metadata/resourceadapter/ConnectionDefinition$Attribute.values:()[Lorg/jboss/jca/common/api/metadata/resourceadapter/ConnectionDefinition$Attribute;
     119: arraylength
     120: newarray       int
     122: putstatic     #13                 // Field $SwitchMap$org$jboss$jca$common$api$metadata$resourceadapter$ConnectionDefinition$Attribute:[I
     125: getstatic     #13                 // Field $SwitchMap$org$jboss$jca$common$api$metadata$resourceadapter$ConnectionDefinition$Attribute:[I
     128: getstatic     #14                 // Field org/jboss/jca/common/api/metadata/resourceadapter/ConnectionDefinition$Attribute.ENABLED:Lorg/jboss/jca/common/api/metadata/resourceadapter/ConnectionDefinition$Attribute;
     131: invokevirtual #15                 // Method org/jboss/jca/common/api/metadata/resourceadapter/ConnectionDefinition$Attribute.ordinal:()I
     134: iconst_1
     135: iastore
     136: goto          140
     139: astore_0
     140: getstatic     #13                 // Field $SwitchMap$org$jboss$jca$common$api$metadata$resourceadapter$ConnectionDefinition$Attribute:[I
     143: getstatic     #16                 // Field org/jboss/jca/common/api/metadata/resourceadapter/ConnectionDefinition$Attribute.JNDI_NAME:Lorg/jboss/jca/common/api/metadata/resourceadapter/ConnectionDefinition$Attribute;
     146: invokevirtual #15                 // Method org/jboss/jca/common/api/metadata/resourceadapter/ConnectionDefinition$Attribute.ordinal:()I
     149: iconst_2
     150: iastore
     151: goto          155
     154: astore_0
     155: getstatic     #13                 // Field $SwitchMap$org$jboss$jca$common$api$metadata$resourceadapter$ConnectionDefinition$Attribute:[I
     158: getstatic     #17                 // Field org/jboss/jca/common/api/metadata/resourceadapter/ConnectionDefinition$Attribute.CLASS_NAME:Lorg/jboss/jca/common/api/metadata/resourceadapter/ConnectionDefinition$Attribute;
     161: invokevirtual #15                 // Method org/jboss/jca/common/api/metadata/resourceadapter/ConnectionDefinition$Attribute.ordinal:()I
     164: iconst_3
     165: iastore
     166: goto          170
     169: astore_0
     170: getstatic     #13                 // Field $SwitchMap$org$jboss$jca$common$api$metadata$resourceadapter$ConnectionDefinition$Attribute:[I
     173: getstatic     #18                 // Field org/jboss/jca/common/api/metadata/resourceadapter/ConnectionDefinition$Attribute.POOL_NAME:Lorg/jboss/jca/common/api/metadata/resourceadapter/ConnectionDefinition$Attribute;
     176: invokevirtual #15                 // Method org/jboss/jca/common/api/metadata/resourceadapter/ConnectionDefinition$Attribute.ordinal:()I
     179: iconst_4
     180: iastore
     181: goto          185
     184: astore_0
     185: getstatic     #13                 // Field $SwitchMap$org$jboss$jca$common$api$metadata$resourceadapter$ConnectionDefinition$Attribute:[I
     188: getstatic     #19                 // Field org/jboss/jca/common/api/metadata/resourceadapter/ConnectionDefinition$Attribute.USE_JAVA_CONTEXT:Lorg/jboss/jca/common/api/metadata/resourceadapter/ConnectionDefinition$Attribute;
     191: invokevirtual #15                 // Method org/jboss/jca/common/api/metadata/resourceadapter/ConnectionDefinition$Attribute.ordinal:()I
     194: iconst_5
     195: iastore
     196: goto          200
     199: astore_0
     200: getstatic     #13                 // Field $SwitchMap$org$jboss$jca$common$api$metadata$resourceadapter$ConnectionDefinition$Attribute:[I
     203: getstatic     #20                 // Field org/jboss/jca/common/api/metadata/resourceadapter/ConnectionDefinition$Attribute.USE_CCM:Lorg/jboss/jca/common/api/metadata/resourceadapter/ConnectionDefinition$Attribute;
     206: invokevirtual #15                 // Method org/jboss/jca/common/api/metadata/resourceadapter/ConnectionDefinition$Attribute.ordinal:()I
     209: bipush        6
     211: iastore
     212: goto          216
     215: astore_0
     216: getstatic     #13                 // Field $SwitchMap$org$jboss$jca$common$api$metadata$resourceadapter$ConnectionDefinition$Attribute:[I
     219: getstatic     #21                 // Field org/jboss/jca/common/api/metadata/resourceadapter/ConnectionDefinition$Attribute.SHARABLE:Lorg/jboss/jca/common/api/metadata/resourceadapter/ConnectionDefinition$Attribute;
     222: invokevirtual #15                 // Method org/jboss/jca/common/api/metadata/resourceadapter/ConnectionDefinition$Attribute.ordinal:()I
     225: bipush        7
     227: iastore
     228: goto          232
     231: astore_0
     232: getstatic     #13                 // Field $SwitchMap$org$jboss$jca$common$api$metadata$resourceadapter$ConnectionDefinition$Attribute:[I
     235: getstatic     #22                 // Field org/jboss/jca/common/api/metadata/resourceadapter/ConnectionDefinition$Attribute.ENLISTMENT:Lorg/jboss/jca/common/api/metadata/resourceadapter/ConnectionDefinition$Attribute;
     238: invokevirtual #15                 // Method org/jboss/jca/common/api/metadata/resourceadapter/ConnectionDefinition$Attribute.ordinal:()I
     241: bipush        8
     243: iastore
     244: goto          248
     247: astore_0
     248: getstatic     #13                 // Field $SwitchMap$org$jboss$jca$common$api$metadata$resourceadapter$ConnectionDefinition$Attribute:[I
     251: getstatic     #23                 // Field org/jboss/jca/common/api/metadata/resourceadapter/ConnectionDefinition$Attribute.CONNECTABLE:Lorg/jboss/jca/common/api/metadata/resourceadapter/ConnectionDefinition$Attribute;
     254: invokevirtual #15                 // Method org/jboss/jca/common/api/metadata/resourceadapter/ConnectionDefinition$Attribute.ordinal:()I
     257: bipush        9
     259: iastore
     260: goto          264
     263: astore_0
     264: getstatic     #13                 // Field $SwitchMap$org$jboss$jca$common$api$metadata$resourceadapter$ConnectionDefinition$Attribute:[I
     267: getstatic     #24                 // Field org/jboss/jca/common/api/metadata/resourceadapter/ConnectionDefinition$Attribute.TRACKING:Lorg/jboss/jca/common/api/metadata/resourceadapter/ConnectionDefinition$Attribute;
     270: invokevirtual #15                 // Method org/jboss/jca/common/api/metadata/resourceadapter/ConnectionDefinition$Attribute.ordinal:()I
     273: bipush        10
     275: iastore
     276: goto          280
     279: astore_0
     280: getstatic     #13                 // Field $SwitchMap$org$jboss$jca$common$api$metadata$resourceadapter$ConnectionDefinition$Attribute:[I
     283: getstatic     #25                 // Field org/jboss/jca/common/api/metadata/resourceadapter/ConnectionDefinition$Attribute.MCP:Lorg/jboss/jca/common/api/metadata/resourceadapter/ConnectionDefinition$Attribute;
     286: invokevirtual #15                 // Method org/jboss/jca/common/api/metadata/resourceadapter/ConnectionDefinition$Attribute.ordinal:()I
     289: bipush        11
     291: iastore
     292: goto          296
     295: astore_0
     296: getstatic     #13                 // Field $SwitchMap$org$jboss$jca$common$api$metadata$resourceadapter$ConnectionDefinition$Attribute:[I
     299: getstatic     #26                 // Field org/jboss/jca/common/api/metadata/resourceadapter/ConnectionDefinition$Attribute.ENLISTMENT_TRACE:Lorg/jboss/jca/common/api/metadata/resourceadapter/ConnectionDefinition$Attribute;
     302: invokevirtual #15                 // Method org/jboss/jca/common/api/metadata/resourceadapter/ConnectionDefinition$Attribute.ordinal:()I
     305: bipush        12
     307: iastore
     308: goto          312
     311: astore_0
     312: invokestatic  #27                 // Method org/jboss/jca/common/api/metadata/resourceadapter/WorkManagerSecurity$Tag.values:()[Lorg/jboss/jca/common/api/metadata/resourceadapter/WorkManagerSecurity$Tag;
     315: arraylength
     316: newarray       int
     318: putstatic     #28                 // Field $SwitchMap$org$jboss$jca$common$api$metadata$resourceadapter$WorkManagerSecurity$Tag:[I
     321: getstatic     #28                 // Field $SwitchMap$org$jboss$jca$common$api$metadata$resourceadapter$WorkManagerSecurity$Tag:[I
     324: getstatic     #29                 // Field org/jboss/jca/common/api/metadata/resourceadapter/WorkManagerSecurity$Tag.DEFAULT_GROUPS:Lorg/jboss/jca/common/api/metadata/resourceadapter/WorkManagerSecurity$Tag;
     327: invokevirtual #30                 // Method org/jboss/jca/common/api/metadata/resourceadapter/WorkManagerSecurity$Tag.ordinal:()I
     330: iconst_1
     331: iastore
     332: goto          336
     335: astore_0
     336: getstatic     #28                 // Field $SwitchMap$org$jboss$jca$common$api$metadata$resourceadapter$WorkManagerSecurity$Tag:[I
     339: getstatic     #31                 // Field org/jboss/jca/common/api/metadata/resourceadapter/WorkManagerSecurity$Tag.MAPPINGS:Lorg/jboss/jca/common/api/metadata/resourceadapter/WorkManagerSecurity$Tag;
     342: invokevirtual #30                 // Method org/jboss/jca/common/api/metadata/resourceadapter/WorkManagerSecurity$Tag.ordinal:()I
     345: iconst_2
     346: iastore
     347: goto          351
     350: astore_0
     351: getstatic     #28                 // Field $SwitchMap$org$jboss$jca$common$api$metadata$resourceadapter$WorkManagerSecurity$Tag:[I
     354: getstatic     #32                 // Field org/jboss/jca/common/api/metadata/resourceadapter/WorkManagerSecurity$Tag.MAPPING_REQUIRED:Lorg/jboss/jca/common/api/metadata/resourceadapter/WorkManagerSecurity$Tag;
     357: invokevirtual #30                 // Method org/jboss/jca/common/api/metadata/resourceadapter/WorkManagerSecurity$Tag.ordinal:()I
     360: iconst_3
     361: iastore
     362: goto          366
     365: astore_0
     366: getstatic     #28                 // Field $SwitchMap$org$jboss$jca$common$api$metadata$resourceadapter$WorkManagerSecurity$Tag:[I
     369: getstatic     #33                 // Field org/jboss/jca/common/api/metadata/resourceadapter/WorkManagerSecurity$Tag.DOMAIN:Lorg/jboss/jca/common/api/metadata/resourceadapter/WorkManagerSecurity$Tag;
     372: invokevirtual #30                 // Method org/jboss/jca/common/api/metadata/resourceadapter/WorkManagerSecurity$Tag.ordinal:()I
     375: iconst_4
     376: iastore
     377: goto          381
     380: astore_0
     381: getstatic     #28                 // Field $SwitchMap$org$jboss$jca$common$api$metadata$resourceadapter$WorkManagerSecurity$Tag:[I
     384: getstatic     #34                 // Field org/jboss/jca/common/api/metadata/resourceadapter/WorkManagerSecurity$Tag.DEFAULT_PRINCIPAL:Lorg/jboss/jca/common/api/metadata/resourceadapter/WorkManagerSecurity$Tag;
     387: invokevirtual #30                 // Method org/jboss/jca/common/api/metadata/resourceadapter/WorkManagerSecurity$Tag.ordinal:()I
     390: iconst_5
     391: iastore
     392: goto          396
     395: astore_0
     396: getstatic     #28                 // Field $SwitchMap$org$jboss$jca$common$api$metadata$resourceadapter$WorkManagerSecurity$Tag:[I
     399: getstatic     #35                 // Field org/jboss/jca/common/api/metadata/resourceadapter/WorkManagerSecurity$Tag.GROUP:Lorg/jboss/jca/common/api/metadata/resourceadapter/WorkManagerSecurity$Tag;
     402: invokevirtual #30                 // Method org/jboss/jca/common/api/metadata/resourceadapter/WorkManagerSecurity$Tag.ordinal:()I
     405: bipush        6
     407: iastore
     408: goto          412
     411: astore_0
     412: getstatic     #28                 // Field $SwitchMap$org$jboss$jca$common$api$metadata$resourceadapter$WorkManagerSecurity$Tag:[I
     415: getstatic     #36                 // Field org/jboss/jca/common/api/metadata/resourceadapter/WorkManagerSecurity$Tag.USERS:Lorg/jboss/jca/common/api/metadata/resourceadapter/WorkManagerSecurity$Tag;
     418: invokevirtual #30                 // Method org/jboss/jca/common/api/metadata/resourceadapter/WorkManagerSecurity$Tag.ordinal:()I
     421: bipush        7
     423: iastore
     424: goto          428
     427: astore_0
     428: getstatic     #28                 // Field $SwitchMap$org$jboss$jca$common$api$metadata$resourceadapter$WorkManagerSecurity$Tag:[I
     431: getstatic     #37                 // Field org/jboss/jca/common/api/metadata/resourceadapter/WorkManagerSecurity$Tag.GROUPS:Lorg/jboss/jca/common/api/metadata/resourceadapter/WorkManagerSecurity$Tag;
     434: invokevirtual #30                 // Method org/jboss/jca/common/api/metadata/resourceadapter/WorkManagerSecurity$Tag.ordinal:()I
     437: bipush        8
     439: iastore
     440: goto          444
     443: astore_0
     444: getstatic     #28                 // Field $SwitchMap$org$jboss$jca$common$api$metadata$resourceadapter$WorkManagerSecurity$Tag:[I
     447: getstatic     #38                 // Field org/jboss/jca/common/api/metadata/resourceadapter/WorkManagerSecurity$Tag.MAP:Lorg/jboss/jca/common/api/metadata/resourceadapter/WorkManagerSecurity$Tag;
     450: invokevirtual #30                 // Method org/jboss/jca/common/api/metadata/resourceadapter/WorkManagerSecurity$Tag.ordinal:()I
     453: bipush        9
     455: iastore
     456: goto          460
     459: astore_0
     460: invokestatic  #39                 // Method org/jboss/jca/common/api/metadata/resourceadapter/WorkManager$Tag.values:()[Lorg/jboss/jca/common/api/metadata/resourceadapter/WorkManager$Tag;
     463: arraylength
     464: newarray       int
     466: putstatic     #40                 // Field $SwitchMap$org$jboss$jca$common$api$metadata$resourceadapter$WorkManager$Tag:[I
     469: getstatic     #40                 // Field $SwitchMap$org$jboss$jca$common$api$metadata$resourceadapter$WorkManager$Tag:[I
     472: getstatic     #41                 // Field org/jboss/jca/common/api/metadata/resourceadapter/WorkManager$Tag.SECURITY:Lorg/jboss/jca/common/api/metadata/resourceadapter/WorkManager$Tag;
     475: invokevirtual #42                 // Method org/jboss/jca/common/api/metadata/resourceadapter/WorkManager$Tag.ordinal:()I
     478: iconst_1
     479: iastore
     480: goto          484
     483: astore_0
     484: invokestatic  #43                 // Method org/jboss/jca/common/api/metadata/resourceadapter/AdminObject$Tag.values:()[Lorg/jboss/jca/common/api/metadata/resourceadapter/AdminObject$Tag;
     487: arraylength
     488: newarray       int
     490: putstatic     #44                 // Field $SwitchMap$org$jboss$jca$common$api$metadata$resourceadapter$AdminObject$Tag:[I
     493: getstatic     #44                 // Field $SwitchMap$org$jboss$jca$common$api$metadata$resourceadapter$AdminObject$Tag:[I
     496: getstatic     #45                 // Field org/jboss/jca/common/api/metadata/resourceadapter/AdminObject$Tag.CONFIG_PROPERTY:Lorg/jboss/jca/common/api/metadata/resourceadapter/AdminObject$Tag;
     499: invokevirtual #46                 // Method org/jboss/jca/common/api/metadata/resourceadapter/AdminObject$Tag.ordinal:()I
     502: iconst_1
     503: iastore
     504: goto          508
     507: astore_0
     508: invokestatic  #47                 // Method org/jboss/jca/common/api/metadata/resourceadapter/AdminObject$Attribute.values:()[Lorg/jboss/jca/common/api/metadata/resourceadapter/AdminObject$Attribute;
     511: arraylength
     512: newarray       int
     514: putstatic     #48                 // Field $SwitchMap$org$jboss$jca$common$api$metadata$resourceadapter$AdminObject$Attribute:[I
     517: getstatic     #48                 // Field $SwitchMap$org$jboss$jca$common$api$metadata$resourceadapter$AdminObject$Attribute:[I
     520: getstatic     #49                 // Field org/jboss/jca/common/api/metadata/resourceadapter/AdminObject$Attribute.ENABLED:Lorg/jboss/jca/common/api/metadata/resourceadapter/AdminObject$Attribute;
     523: invokevirtual #50                 // Method org/jboss/jca/common/api/metadata/resourceadapter/AdminObject$Attribute.ordinal:()I
     526: iconst_1
     527: iastore
     528: goto          532
     531: astore_0
     532: getstatic     #48                 // Field $SwitchMap$org$jboss$jca$common$api$metadata$resourceadapter$AdminObject$Attribute:[I
     535: getstatic     #51                 // Field org/jboss/jca/common/api/metadata/resourceadapter/AdminObject$Attribute.JNDI_NAME:Lorg/jboss/jca/common/api/metadata/resourceadapter/AdminObject$Attribute;
     538: invokevirtual #50                 // Method org/jboss/jca/common/api/metadata/resourceadapter/AdminObject$Attribute.ordinal:()I
     541: iconst_2
     542: iastore
     543: goto          547
     546: astore_0
     547: getstatic     #48                 // Field $SwitchMap$org$jboss$jca$common$api$metadata$resourceadapter$AdminObject$Attribute:[I
     550: getstatic     #52                 // Field org/jboss/jca/common/api/metadata/resourceadapter/AdminObject$Attribute.CLASS_NAME:Lorg/jboss/jca/common/api/metadata/resourceadapter/AdminObject$Attribute;
     553: invokevirtual #50                 // Method org/jboss/jca/common/api/metadata/resourceadapter/AdminObject$Attribute.ordinal:()I
     556: iconst_3
     557: iastore
     558: goto          562
     561: astore_0
     562: getstatic     #48                 // Field $SwitchMap$org$jboss$jca$common$api$metadata$resourceadapter$AdminObject$Attribute:[I
     565: getstatic     #53                 // Field org/jboss/jca/common/api/metadata/resourceadapter/AdminObject$Attribute.USE_JAVA_CONTEXT:Lorg/jboss/jca/common/api/metadata/resourceadapter/AdminObject$Attribute;
     568: invokevirtual #50                 // Method org/jboss/jca/common/api/metadata/resourceadapter/AdminObject$Attribute.ordinal:()I
     571: iconst_4
     572: iastore
     573: goto          577
     576: astore_0
     577: getstatic     #48                 // Field $SwitchMap$org$jboss$jca$common$api$metadata$resourceadapter$AdminObject$Attribute:[I
     580: getstatic     #54                 // Field org/jboss/jca/common/api/metadata/resourceadapter/AdminObject$Attribute.POOL_NAME:Lorg/jboss/jca/common/api/metadata/resourceadapter/AdminObject$Attribute;
     583: invokevirtual #50                 // Method org/jboss/jca/common/api/metadata/resourceadapter/AdminObject$Attribute.ordinal:()I
     586: iconst_5
     587: iastore
     588: goto          592
     591: astore_0
     592: return
    Exception table:
       from    to  target type
           9    20    23   Class java/lang/NoSuchFieldError
          24    35    38   Class java/lang/NoSuchFieldError
          39    50    53   Class java/lang/NoSuchFieldError
          54    65    68   Class java/lang/NoSuchFieldError
          69    80    83   Class java/lang/NoSuchFieldError
          84    96    99   Class java/lang/NoSuchFieldError
         100   112   115   Class java/lang/NoSuchFieldError
         125   136   139   Class java/lang/NoSuchFieldError
         140   151   154   Class java/lang/NoSuchFieldError
         155   166   169   Class java/lang/NoSuchFieldError
         170   181   184   Class java/lang/NoSuchFieldError
         185   196   199   Class java/lang/NoSuchFieldError
         200   212   215   Class java/lang/NoSuchFieldError
         216   228   231   Class java/lang/NoSuchFieldError
         232   244   247   Class java/lang/NoSuchFieldError
         248   260   263   Class java/lang/NoSuchFieldError
         264   276   279   Class java/lang/NoSuchFieldError
         280   292   295   Class java/lang/NoSuchFieldError
         296   308   311   Class java/lang/NoSuchFieldError
         321   332   335   Class java/lang/NoSuchFieldError
         336   347   350   Class java/lang/NoSuchFieldError
         351   362   365   Class java/lang/NoSuchFieldError
         366   377   380   Class java/lang/NoSuchFieldError
         381   392   395   Class java/lang/NoSuchFieldError
         396   408   411   Class java/lang/NoSuchFieldError
         412   424   427   Class java/lang/NoSuchFieldError
         428   440   443   Class java/lang/NoSuchFieldError
         444   456   459   Class java/lang/NoSuchFieldError
         469   480   483   Class java/lang/NoSuchFieldError
         493   504   507   Class java/lang/NoSuchFieldError
         517   528   531   Class java/lang/NoSuchFieldError
         532   543   546   Class java/lang/NoSuchFieldError
         547   558   561   Class java/lang/NoSuchFieldError
         562   573   576   Class java/lang/NoSuchFieldError
         577   588   591   Class java/lang/NoSuchFieldError
}
