Compiled from "ValidationImpl.java"
public class org.jboss.jca.common.metadata.common.ValidationImpl implements org.jboss.jca.common.api.metadata.common.Validation {
  private static final long serialVersionUID;

  private static org.jboss.jca.common.CommonBundle bundle;

  protected java.lang.Boolean validateOnMatch;

  protected java.lang.Boolean backgroundValidation;

  protected java.lang.Long backgroundValidationMillis;

  protected java.lang.Boolean useFastFail;

  public org.jboss.jca.common.metadata.common.ValidationImpl(java.lang.Boolean, java.lang.Boolean, java.lang.Long, java.lang.Boolean) throws org.jboss.jca.common.api.validator.ValidateException;
    Code:
       0: aload_0
       1: invokespecial #1                  // Method java/lang/Object."<init>":()V
       4: aload_0
       5: aload_1
       6: putfield      #2                  // Field validateOnMatch:Ljava/lang/Boolean;
       9: aload_0
      10: aload_2
      11: putfield      #3                  // Field backgroundValidation:Ljava/lang/Boolean;
      14: aload_0
      15: aload_3
      16: putfield      #4                  // Field backgroundValidationMillis:Ljava/lang/Long;
      19: aload_0
      20: aload         4
      22: putfield      #5                  // Field useFastFail:Ljava/lang/Boolean;
      25: aload_0
      26: invokespecial #6                  // Method partialCommonValidate:()V
      29: return

  public java.lang.Boolean isValidateOnMatch();
    Code:
       0: aload_0
       1: getfield      #2                  // Field validateOnMatch:Ljava/lang/Boolean;
       4: areturn

  public java.lang.Boolean isBackgroundValidation();
    Code:
       0: aload_0
       1: getfield      #3                  // Field backgroundValidation:Ljava/lang/Boolean;
       4: areturn

  public java.lang.Long getBackgroundValidationMillis();
    Code:
       0: aload_0
       1: getfield      #4                  // Field backgroundValidationMillis:Ljava/lang/Long;
       4: areturn

  public java.lang.Boolean isUseFastFail();
    Code:
       0: aload_0
       1: getfield      #5                  // Field useFastFail:Ljava/lang/Boolean;
       4: areturn

  private void partialCommonValidate() throws org.jboss.jca.common.api.validator.ValidateException;
    Code:
       0: aload_0
       1: getfield      #4                  // Field backgroundValidationMillis:Ljava/lang/Long;
       4: ifnull        41
       7: aload_0
       8: getfield      #4                  // Field backgroundValidationMillis:Ljava/lang/Long;
      11: invokevirtual #7                  // Method java/lang/Long.longValue:()J
      14: lconst_0
      15: lcmp
      16: ifge          41
      19: new           #8                  // class org/jboss/jca/common/api/validator/ValidateException
      22: dup
      23: getstatic     #9                  // Field bundle:Lorg/jboss/jca/common/CommonBundle;
      26: getstatic     #10                 // Field org/jboss/jca/common/api/metadata/common/Validation$Tag.BACKGROUND_VALIDATION_MILLIS:Lorg/jboss/jca/common/api/metadata/common/Validation$Tag;
      29: invokevirtual #11                 // Method org/jboss/jca/common/api/metadata/common/Validation$Tag.getLocalName:()Ljava/lang/String;
      32: invokeinterface #12,  2           // InterfaceMethod org/jboss/jca/common/CommonBundle.invalidNegative:(Ljava/lang/String;)Ljava/lang/String;
      37: invokespecial #13                 // Method org/jboss/jca/common/api/validator/ValidateException."<init>":(Ljava/lang/String;)V
      40: athrow
      41: return

  public int hashCode();
    Code:
       0: bipush        31
       2: istore_1
       3: iconst_1
       4: istore_2
       5: bipush        31
       7: iload_2
       8: imul
       9: aload_0
      10: getfield      #2                  // Field validateOnMatch:Ljava/lang/Boolean;
      13: ifnonnull     20
      16: iconst_0
      17: goto          27
      20: aload_0
      21: getfield      #2                  // Field validateOnMatch:Ljava/lang/Boolean;
      24: invokevirtual #14                 // Method java/lang/Boolean.hashCode:()I
      27: iadd
      28: istore_2
      29: bipush        31
      31: iload_2
      32: imul
      33: aload_0
      34: getfield      #3                  // Field backgroundValidation:Ljava/lang/Boolean;
      37: ifnonnull     44
      40: iconst_0
      41: goto          51
      44: aload_0
      45: getfield      #3                  // Field backgroundValidation:Ljava/lang/Boolean;
      48: invokevirtual #14                 // Method java/lang/Boolean.hashCode:()I
      51: iadd
      52: istore_2
      53: bipush        31
      55: iload_2
      56: imul
      57: aload_0
      58: getfield      #4                  // Field backgroundValidationMillis:Ljava/lang/Long;
      61: ifnonnull     68
      64: iconst_0
      65: goto          75
      68: aload_0
      69: getfield      #4                  // Field backgroundValidationMillis:Ljava/lang/Long;
      72: invokevirtual #15                 // Method java/lang/Long.hashCode:()I
      75: iadd
      76: istore_2
      77: bipush        31
      79: iload_2
      80: imul
      81: aload_0
      82: getfield      #5                  // Field useFastFail:Ljava/lang/Boolean;
      85: ifnonnull     92
      88: iconst_0
      89: goto          99
      92: aload_0
      93: getfield      #5                  // Field useFastFail:Ljava/lang/Boolean;
      96: invokevirtual #14                 // Method java/lang/Boolean.hashCode:()I
      99: iadd
     100: istore_2
     101: iload_2
     102: ireturn

  public boolean equals(java.lang.Object);
    Code:
       0: aload_0
       1: aload_1
       2: if_acmpne     7
       5: iconst_1
       6: ireturn
       7: aload_1
       8: ifnonnull     13
      11: iconst_0
      12: ireturn
      13: aload_1
      14: instanceof    #16                 // class org/jboss/jca/common/metadata/common/ValidationImpl
      17: ifne          22
      20: iconst_0
      21: ireturn
      22: aload_1
      23: checkcast     #16                 // class org/jboss/jca/common/metadata/common/ValidationImpl
      26: astore_2
      27: aload_0
      28: getfield      #2                  // Field validateOnMatch:Ljava/lang/Boolean;
      31: ifnonnull     43
      34: aload_2
      35: getfield      #2                  // Field validateOnMatch:Ljava/lang/Boolean;
      38: ifnull        59
      41: iconst_0
      42: ireturn
      43: aload_0
      44: getfield      #2                  // Field validateOnMatch:Ljava/lang/Boolean;
      47: aload_2
      48: getfield      #2                  // Field validateOnMatch:Ljava/lang/Boolean;
      51: invokevirtual #17                 // Method java/lang/Boolean.equals:(Ljava/lang/Object;)Z
      54: ifne          59
      57: iconst_0
      58: ireturn
      59: aload_0
      60: getfield      #3                  // Field backgroundValidation:Ljava/lang/Boolean;
      63: ifnonnull     75
      66: aload_2
      67: getfield      #3                  // Field backgroundValidation:Ljava/lang/Boolean;
      70: ifnull        91
      73: iconst_0
      74: ireturn
      75: aload_0
      76: getfield      #3                  // Field backgroundValidation:Ljava/lang/Boolean;
      79: aload_2
      80: getfield      #3                  // Field backgroundValidation:Ljava/lang/Boolean;
      83: invokevirtual #17                 // Method java/lang/Boolean.equals:(Ljava/lang/Object;)Z
      86: ifne          91
      89: iconst_0
      90: ireturn
      91: aload_0
      92: getfield      #4                  // Field backgroundValidationMillis:Ljava/lang/Long;
      95: ifnonnull     107
      98: aload_2
      99: getfield      #4                  // Field backgroundValidationMillis:Ljava/lang/Long;
     102: ifnull        123
     105: iconst_0
     106: ireturn
     107: aload_0
     108: getfield      #4                  // Field backgroundValidationMillis:Ljava/lang/Long;
     111: aload_2
     112: getfield      #4                  // Field backgroundValidationMillis:Ljava/lang/Long;
     115: invokevirtual #18                 // Method java/lang/Long.equals:(Ljava/lang/Object;)Z
     118: ifne          123
     121: iconst_0
     122: ireturn
     123: aload_0
     124: getfield      #5                  // Field useFastFail:Ljava/lang/Boolean;
     127: ifnonnull     139
     130: aload_2
     131: getfield      #5                  // Field useFastFail:Ljava/lang/Boolean;
     134: ifnull        155
     137: iconst_0
     138: ireturn
     139: aload_0
     140: getfield      #5                  // Field useFastFail:Ljava/lang/Boolean;
     143: aload_2
     144: getfield      #5                  // Field useFastFail:Ljava/lang/Boolean;
     147: invokevirtual #17                 // Method java/lang/Boolean.equals:(Ljava/lang/Object;)Z
     150: ifne          155
     153: iconst_0
     154: ireturn
     155: iconst_1
     156: ireturn

  public java.lang.String toString();
    Code:
       0: new           #19                 // class java/lang/StringBuilder
       3: dup
       4: sipush        1024
       7: invokespecial #20                 // Method java/lang/StringBuilder."<init>":(I)V
      10: astore_1
      11: aload_1
      12: ldc           #21                 // String <validation>
      14: invokevirtual #22                 // Method java/lang/StringBuilder.append:(Ljava/lang/String;)Ljava/lang/StringBuilder;
      17: pop
      18: aload_0
      19: getfield      #2                  // Field validateOnMatch:Ljava/lang/Boolean;
      22: ifnull        70
      25: aload_1
      26: ldc           #23                 // String <
      28: invokevirtual #22                 // Method java/lang/StringBuilder.append:(Ljava/lang/String;)Ljava/lang/StringBuilder;
      31: getstatic     #24                 // Field org/jboss/jca/common/api/metadata/common/Validation$Tag.VALIDATE_ON_MATCH:Lorg/jboss/jca/common/api/metadata/common/Validation$Tag;
      34: invokevirtual #25                 // Method java/lang/StringBuilder.append:(Ljava/lang/Object;)Ljava/lang/StringBuilder;
      37: ldc           #26                 // String >
      39: invokevirtual #22                 // Method java/lang/StringBuilder.append:(Ljava/lang/String;)Ljava/lang/StringBuilder;
      42: pop
      43: aload_1
      44: aload_0
      45: getfield      #2                  // Field validateOnMatch:Ljava/lang/Boolean;
      48: invokevirtual #25                 // Method java/lang/StringBuilder.append:(Ljava/lang/Object;)Ljava/lang/StringBuilder;
      51: pop
      52: aload_1
      53: ldc           #27                 // String </
      55: invokevirtual #22                 // Method java/lang/StringBuilder.append:(Ljava/lang/String;)Ljava/lang/StringBuilder;
      58: getstatic     #24                 // Field org/jboss/jca/common/api/metadata/common/Validation$Tag.VALIDATE_ON_MATCH:Lorg/jboss/jca/common/api/metadata/common/Validation$Tag;
      61: invokevirtual #25                 // Method java/lang/StringBuilder.append:(Ljava/lang/Object;)Ljava/lang/StringBuilder;
      64: ldc           #26                 // String >
      66: invokevirtual #22                 // Method java/lang/StringBuilder.append:(Ljava/lang/String;)Ljava/lang/StringBuilder;
      69: pop
      70: aload_0
      71: getfield      #3                  // Field backgroundValidation:Ljava/lang/Boolean;
      74: ifnull        122
      77: aload_1
      78: ldc           #23                 // String <
      80: invokevirtual #22                 // Method java/lang/StringBuilder.append:(Ljava/lang/String;)Ljava/lang/StringBuilder;
      83: getstatic     #28                 // Field org/jboss/jca/common/api/metadata/common/Validation$Tag.BACKGROUND_VALIDATION:Lorg/jboss/jca/common/api/metadata/common/Validation$Tag;
      86: invokevirtual #25                 // Method java/lang/StringBuilder.append:(Ljava/lang/Object;)Ljava/lang/StringBuilder;
      89: ldc           #26                 // String >
      91: invokevirtual #22                 // Method java/lang/StringBuilder.append:(Ljava/lang/String;)Ljava/lang/StringBuilder;
      94: pop
      95: aload_1
      96: aload_0
      97: getfield      #3                  // Field backgroundValidation:Ljava/lang/Boolean;
     100: invokevirtual #25                 // Method java/lang/StringBuilder.append:(Ljava/lang/Object;)Ljava/lang/StringBuilder;
     103: pop
     104: aload_1
     105: ldc           #27                 // String </
     107: invokevirtual #22                 // Method java/lang/StringBuilder.append:(Ljava/lang/String;)Ljava/lang/StringBuilder;
     110: getstatic     #28                 // Field org/jboss/jca/common/api/metadata/common/Validation$Tag.BACKGROUND_VALIDATION:Lorg/jboss/jca/common/api/metadata/common/Validation$Tag;
     113: invokevirtual #25                 // Method java/lang/StringBuilder.append:(Ljava/lang/Object;)Ljava/lang/StringBuilder;
     116: ldc           #26                 // String >
     118: invokevirtual #22                 // Method java/lang/StringBuilder.append:(Ljava/lang/String;)Ljava/lang/StringBuilder;
     121: pop
     122: aload_0
     123: getfield      #4                  // Field backgroundValidationMillis:Ljava/lang/Long;
     126: ifnull        174
     129: aload_1
     130: ldc           #23                 // String <
     132: invokevirtual #22                 // Method java/lang/StringBuilder.append:(Ljava/lang/String;)Ljava/lang/StringBuilder;
     135: getstatic     #10                 // Field org/jboss/jca/common/api/metadata/common/Validation$Tag.BACKGROUND_VALIDATION_MILLIS:Lorg/jboss/jca/common/api/metadata/common/Validation$Tag;
     138: invokevirtual #25                 // Method java/lang/StringBuilder.append:(Ljava/lang/Object;)Ljava/lang/StringBuilder;
     141: ldc           #26                 // String >
     143: invokevirtual #22                 // Method java/lang/StringBuilder.append:(Ljava/lang/String;)Ljava/lang/StringBuilder;
     146: pop
     147: aload_1
     148: aload_0
     149: getfield      #4                  // Field backgroundValidationMillis:Ljava/lang/Long;
     152: invokevirtual #25                 // Method java/lang/StringBuilder.append:(Ljava/lang/Object;)Ljava/lang/StringBuilder;
     155: pop
     156: aload_1
     157: ldc           #27                 // String </
     159: invokevirtual #22                 // Method java/lang/StringBuilder.append:(Ljava/lang/String;)Ljava/lang/StringBuilder;
     162: getstatic     #10                 // Field org/jboss/jca/common/api/metadata/common/Validation$Tag.BACKGROUND_VALIDATION_MILLIS:Lorg/jboss/jca/common/api/metadata/common/Validation$Tag;
     165: invokevirtual #25                 // Method java/lang/StringBuilder.append:(Ljava/lang/Object;)Ljava/lang/StringBuilder;
     168: ldc           #26                 // String >
     170: invokevirtual #22                 // Method java/lang/StringBuilder.append:(Ljava/lang/String;)Ljava/lang/StringBuilder;
     173: pop
     174: aload_0
     175: getfield      #5                  // Field useFastFail:Ljava/lang/Boolean;
     178: ifnull        226
     181: aload_1
     182: ldc           #23                 // String <
     184: invokevirtual #22                 // Method java/lang/StringBuilder.append:(Ljava/lang/String;)Ljava/lang/StringBuilder;
     187: getstatic     #29                 // Field org/jboss/jca/common/api/metadata/common/Validation$Tag.USE_FAST_FAIL:Lorg/jboss/jca/common/api/metadata/common/Validation$Tag;
     190: invokevirtual #25                 // Method java/lang/StringBuilder.append:(Ljava/lang/Object;)Ljava/lang/StringBuilder;
     193: ldc           #26                 // String >
     195: invokevirtual #22                 // Method java/lang/StringBuilder.append:(Ljava/lang/String;)Ljava/lang/StringBuilder;
     198: pop
     199: aload_1
     200: aload_0
     201: getfield      #5                  // Field useFastFail:Ljava/lang/Boolean;
     204: invokevirtual #25                 // Method java/lang/StringBuilder.append:(Ljava/lang/Object;)Ljava/lang/StringBuilder;
     207: pop
     208: aload_1
     209: ldc           #27                 // String </
     211: invokevirtual #22                 // Method java/lang/StringBuilder.append:(Ljava/lang/String;)Ljava/lang/StringBuilder;
     214: getstatic     #29                 // Field org/jboss/jca/common/api/metadata/common/Validation$Tag.USE_FAST_FAIL:Lorg/jboss/jca/common/api/metadata/common/Validation$Tag;
     217: invokevirtual #25                 // Method java/lang/StringBuilder.append:(Ljava/lang/Object;)Ljava/lang/StringBuilder;
     220: ldc           #26                 // String >
     222: invokevirtual #22                 // Method java/lang/StringBuilder.append:(Ljava/lang/String;)Ljava/lang/StringBuilder;
     225: pop
     226: aload_1
     227: ldc           #30                 // String </validation>
     229: invokevirtual #22                 // Method java/lang/StringBuilder.append:(Ljava/lang/String;)Ljava/lang/StringBuilder;
     232: pop
     233: aload_1
     234: invokevirtual #31                 // Method java/lang/StringBuilder.toString:()Ljava/lang/String;
     237: areturn

  static {};
    Code:
       0: ldc_w         #32                 // class org/jboss/jca/common/CommonBundle
       3: invokestatic  #33                 // Method org/jboss/logging/Messages.getBundle:(Ljava/lang/Class;)Ljava/lang/Object;
       6: checkcast     #32                 // class org/jboss/jca/common/CommonBundle
       9: putstatic     #9                  // Field bundle:Lorg/jboss/jca/common/CommonBundle;
      12: return
}
