Compiled from "MapValidator.java"
public class org.graylog2.database.validators.MapValidator implements org.graylog2.plugin.database.validators.Validator {
  public org.graylog2.database.validators.MapValidator();
    Code:
       0: aload_0
       1: invokespecial #1                  // Method java/lang/Object."<init>":()V
       4: return

  public org.graylog2.plugin.database.validators.ValidationResult validate(java.lang.Object);
    Code:
       0: aload_1
       1: instanceof    #2                  // class java/util/Map
       4: ifeq          15
       7: new           #3                  // class org/graylog2/plugin/database/validators/ValidationResult$ValidationPassed
      10: dup
      11: invokespecial #4                  // Method org/graylog2/plugin/database/validators/ValidationResult$ValidationPassed."<init>":()V
      14: areturn
      15: new           #5                  // class org/graylog2/plugin/database/validators/ValidationResult$ValidationFailed
      18: dup
      19: ldc           #6                  // String Value is not a Map!
      21: invokespecial #7                  // Method org/graylog2/plugin/database/validators/ValidationResult$ValidationFailed."<init>":(Ljava/lang/String;)V
      24: areturn
}
