Compiled from "HandlerMethodResolver.java"
class springfox.documentation.spring.web.readers.operation.HandlerMethodResolver$7 implements com.google.common.base.Predicate<com.fasterxml.classmate.members.ResolvedMethod> {
  final java.lang.reflect.Method val$methodToResolve;

  final springfox.documentation.spring.web.readers.operation.HandlerMethodResolver this$0;

  springfox.documentation.spring.web.readers.operation.HandlerMethodResolver$7(springfox.documentation.spring.web.readers.operation.HandlerMethodResolver, java.lang.reflect.Method);
    Code:
       0: aload_0
       1: aload_1
       2: putfield      #1                  // Field this$0:Lspringfox/documentation/spring/web/readers/operation/HandlerMethodResolver;
       5: aload_0
       6: aload_2
       7: putfield      #2                  // Field val$methodToResolve:Ljava/lang/reflect/Method;
      10: aload_0
      11: invokespecial #3                  // Method java/lang/Object."<init>":()V
      14: return

  public boolean apply(com.fasterxml.classmate.members.ResolvedMethod);
    Code:
       0: iconst_0
       1: istore_2
       2: iload_2
       3: aload_1
       4: invokevirtual #4                  // Method com/fasterxml/classmate/members/ResolvedMethod.getArgumentCount:()I
       7: if_icmpge     42
      10: aload_0
      11: getfield      #1                  // Field this$0:Lspringfox/documentation/spring/web/readers/operation/HandlerMethodResolver;
      14: aload_1
      15: iload_2
      16: invokevirtual #5                  // Method com/fasterxml/classmate/members/ResolvedMethod.getArgumentType:(I)Lcom/fasterxml/classmate/ResolvedType;
      19: aload_0
      20: getfield      #2                  // Field val$methodToResolve:Ljava/lang/reflect/Method;
      23: invokevirtual #6                  // Method java/lang/reflect/Method.getGenericParameterTypes:()[Ljava/lang/reflect/Type;
      26: iload_2
      27: aaload
      28: invokevirtual #7                  // Method springfox/documentation/spring/web/readers/operation/HandlerMethodResolver.covariant:(Lcom/fasterxml/classmate/ResolvedType;Ljava/lang/reflect/Type;)Z
      31: ifne          36
      34: iconst_0
      35: ireturn
      36: iinc          2, 1
      39: goto          2
      42: aload_0
      43: getfield      #1                  // Field this$0:Lspringfox/documentation/spring/web/readers/operation/HandlerMethodResolver;
      46: aload_1
      47: invokestatic  #8                  // Method springfox/documentation/spring/web/readers/operation/HandlerMethodResolver.access$100:(Lspringfox/documentation/spring/web/readers/operation/HandlerMethodResolver;Lcom/fasterxml/classmate/members/ResolvedMethod;)Lcom/fasterxml/classmate/ResolvedType;
      50: astore_2
      51: aload_0
      52: getfield      #1                  // Field this$0:Lspringfox/documentation/spring/web/readers/operation/HandlerMethodResolver;
      55: aload_2
      56: aload_0
      57: getfield      #2                  // Field val$methodToResolve:Ljava/lang/reflect/Method;
      60: invokevirtual #9                  // Method java/lang/reflect/Method.getGenericReturnType:()Ljava/lang/reflect/Type;
      63: invokevirtual #10                 // Method springfox/documentation/spring/web/readers/operation/HandlerMethodResolver.bothAreVoids:(Lcom/fasterxml/classmate/ResolvedType;Ljava/lang/reflect/Type;)Z
      66: ifne          87
      69: aload_0
      70: getfield      #1                  // Field this$0:Lspringfox/documentation/spring/web/readers/operation/HandlerMethodResolver;
      73: aload_2
      74: aload_0
      75: getfield      #2                  // Field val$methodToResolve:Ljava/lang/reflect/Method;
      78: invokevirtual #9                  // Method java/lang/reflect/Method.getGenericReturnType:()Ljava/lang/reflect/Type;
      81: invokevirtual #11                 // Method springfox/documentation/spring/web/readers/operation/HandlerMethodResolver.contravariant:(Lcom/fasterxml/classmate/ResolvedType;Ljava/lang/reflect/Type;)Z
      84: ifeq          91
      87: iconst_1
      88: goto          92
      91: iconst_0
      92: ireturn

  public boolean apply(java.lang.Object);
    Code:
       0: aload_0
       1: aload_1
       2: checkcast     #12                 // class com/fasterxml/classmate/members/ResolvedMethod
       5: invokevirtual #13                 // Method apply:(Lcom/fasterxml/classmate/members/ResolvedMethod;)Z
       8: ireturn
}
