Compiled from "ViewData.java"
class io.opencensus.stats.ViewData$9 implements io.opencensus.common.Function<io.opencensus.stats.Aggregation, java.lang.Void> {
  final io.opencensus.stats.AggregationData val$aggregationData;

  final io.opencensus.stats.Aggregation val$aggregation;

  io.opencensus.stats.ViewData$9(io.opencensus.stats.AggregationData, io.opencensus.stats.Aggregation);
    Code:
       0: aload_0
       1: aload_1
       2: putfield      #1                  // Field val$aggregationData:Lio/opencensus/stats/AggregationData;
       5: aload_0
       6: aload_2
       7: putfield      #2                  // Field val$aggregation:Lio/opencensus/stats/Aggregation;
      10: aload_0
      11: invokespecial #3                  // Method java/lang/Object."<init>":()V
      14: return

  public java.lang.Void apply(io.opencensus.stats.Aggregation);
    Code:
       0: aload_1
       1: instanceof    #4                  // class io/opencensus/stats/Aggregation$Mean
       4: ifeq          27
       7: aload_0
       8: getfield      #1                  // Field val$aggregationData:Lio/opencensus/stats/AggregationData;
      11: instanceof    #5                  // class io/opencensus/stats/AggregationData$MeanData
      14: aload_0
      15: getfield      #2                  // Field val$aggregation:Lio/opencensus/stats/Aggregation;
      18: aload_0
      19: getfield      #1                  // Field val$aggregationData:Lio/opencensus/stats/AggregationData;
      22: invokestatic  #6                  // Method io/opencensus/stats/ViewData.access$200:(ZLio/opencensus/stats/Aggregation;Lio/opencensus/stats/AggregationData;)V
      25: aconst_null
      26: areturn
      27: new           #7                  // class java/lang/AssertionError
      30: dup
      31: invokespecial #8                  // Method java/lang/AssertionError."<init>":()V
      34: athrow

  public java.lang.Object apply(java.lang.Object);
    Code:
       0: aload_0
       1: aload_1
       2: checkcast     #9                  // class io/opencensus/stats/Aggregation
       5: invokevirtual #10                 // Method apply:(Lio/opencensus/stats/Aggregation;)Ljava/lang/Void;
       8: areturn
}
