Compiled from "BloopInstallTask.scala"
public final class bloop.integrations.gradle.tasks.AndroidInstall$ {
  public static final bloop.integrations.gradle.tasks.AndroidInstall$ MODULE$;

  public static {};
    Code:
       0: new           #2                  // class bloop/integrations/gradle/tasks/AndroidInstall$
       3: invokespecial #12                 // Method "<init>":()V
       6: return

  public void install(org.gradle.api.Project, java.io.File, bloop.integrations.gradle.model.BloopConverter, scala.Function1<java.lang.String, scala.runtime.BoxedUnit>);
    Code:
       0: getstatic     #19                 // Field bloop/integrations/gradle/syntax$.MODULE$:Lbloop/integrations/gradle/syntax$;
       3: aload_1
       4: invokevirtual #23                 // Method bloop/integrations/gradle/syntax$.ProjectExtension:(Lorg/gradle/api/Project;)Lbloop/integrations/gradle/syntax$ProjectExtension;
       7: invokevirtual #29                 // Method bloop/integrations/gradle/syntax$ProjectExtension.androidVariants:()Lscala/collection/immutable/Set;
      10: new           #31                 // class bloop/integrations/gradle/tasks/AndroidInstall$$anonfun$install$2
      13: dup
      14: aload_1
      15: aload_2
      16: aload_3
      17: aload         4
      19: invokespecial #33                 // Method bloop/integrations/gradle/tasks/AndroidInstall$$anonfun$install$2."<init>":(Lorg/gradle/api/Project;Ljava/io/File;Lbloop/integrations/gradle/model/BloopConverter;Lscala/Function1;)V
      22: invokeinterface #39,  2           // InterfaceMethod scala/collection/immutable/Set.foreach:(Lscala/Function1;)V
      27: return

  public void bloop$integrations$gradle$tasks$AndroidInstall$$generateBloopConfiguration(org.gradle.api.Project, com.android.build.gradle.api.BaseVariant, java.io.File, bloop.integrations.gradle.model.BloopConverter, scala.Function1<java.lang.String, scala.runtime.BoxedUnit>);
    Code:
       0: aload         4
       2: aload_1
       3: aload_2
       4: invokevirtual #56                 // Method bloop/integrations/gradle/model/BloopConverter.getAndroidProjectName:(Lorg/gradle/api/Project;Lcom/android/build/gradle/api/BaseVariant;)Ljava/lang/String;
       7: astore        6
       9: aload_0
      10: aload_1
      11: aload         6
      13: aload_2
      14: getstatic     #61                 // Field scala/collection/JavaConverters$.MODULE$:Lscala/collection/JavaConverters$;
      17: aload_2
      18: invokeinterface #67,  1           // InterfaceMethod com/android/build/gradle/api/BaseVariant.getSourceSets:()Ljava/util/List;
      23: invokevirtual #71                 // Method scala/collection/JavaConverters$.asScalaBufferConverter:(Ljava/util/List;)Lscala/collection/convert/Decorators$AsScala;
      26: invokevirtual #77                 // Method scala/collection/convert/Decorators$AsScala.asScala:()Ljava/lang/Object;
      29: checkcast     #79                 // class scala/collection/TraversableOnce
      32: invokeinterface #83,  1           // InterfaceMethod scala/collection/TraversableOnce.toList:()Lscala/collection/immutable/List;
      37: aload_3
      38: aload         4
      40: aload         5
      42: invokespecial #87                 // Method generateBloopConfiguration:(Lorg/gradle/api/Project;Ljava/lang/String;Lcom/android/build/gradle/api/BaseVariant;Lscala/collection/immutable/List;Ljava/io/File;Lbloop/integrations/gradle/model/BloopConverter;Lscala/Function1;)V
      45: return

  private void generateBloopConfiguration(org.gradle.api.Project, java.lang.String, com.android.build.gradle.api.BaseVariant, scala.collection.immutable.List<com.android.builder.model.SourceProvider>, java.io.File, bloop.integrations.gradle.model.BloopConverter, scala.Function1<java.lang.String, scala.runtime.BoxedUnit>);
    Code:
       0: getstatic     #19                 // Field bloop/integrations/gradle/syntax$.MODULE$:Lbloop/integrations/gradle/syntax$;
       3: aload         5
       5: invokevirtual #95                 // Method bloop/integrations/gradle/syntax$.FileExtension:(Ljava/io/File;)Lbloop/integrations/gradle/syntax$FileExtension;
       8: new           #97                 // class scala/StringContext
      11: dup
      12: getstatic     #102                // Field scala/Predef$.MODULE$:Lscala/Predef$;
      15: iconst_2
      16: anewarray     #104                // class java/lang/String
      19: dup
      20: iconst_0
      21: ldc           #106                // String
      23: aastore
      24: dup
      25: iconst_1
      26: ldc           #108                // String .json
      28: aastore
      29: checkcast     #110                // class "[Ljava/lang/Object;"
      32: invokevirtual #114                // Method scala/Predef$.wrapRefArray:([Ljava/lang/Object;)Lscala/collection/mutable/WrappedArray;
      35: invokespecial #117                // Method scala/StringContext."<init>":(Lscala/collection/Seq;)V
      38: getstatic     #102                // Field scala/Predef$.MODULE$:Lscala/Predef$;
      41: iconst_1
      42: anewarray     #4                  // class java/lang/Object
      45: dup
      46: iconst_0
      47: aload_2
      48: aastore
      49: invokevirtual #121                // Method scala/Predef$.genericWrapArray:(Ljava/lang/Object;)Lscala/collection/mutable/WrappedArray;
      52: invokevirtual #125                // Method scala/StringContext.s:(Lscala/collection/Seq;)Ljava/lang/String;
      55: invokevirtual #131                // Method bloop/integrations/gradle/syntax$FileExtension.$div:(Ljava/lang/String;)Ljava/io/File;
      58: astore        8
      60: aload         7
      62: new           #97                 // class scala/StringContext
      65: dup
      66: getstatic     #102                // Field scala/Predef$.MODULE$:Lscala/Predef$;
      69: iconst_2
      70: anewarray     #104                // class java/lang/String
      73: dup
      74: iconst_0
      75: ldc           #133                // String Generated
      77: aastore
      78: dup
      79: iconst_1
      80: ldc           #106                // String
      82: aastore
      83: checkcast     #110                // class "[Ljava/lang/Object;"
      86: invokevirtual #114                // Method scala/Predef$.wrapRefArray:([Ljava/lang/Object;)Lscala/collection/mutable/WrappedArray;
      89: invokespecial #117                // Method scala/StringContext."<init>":(Lscala/collection/Seq;)V
      92: getstatic     #102                // Field scala/Predef$.MODULE$:Lscala/Predef$;
      95: iconst_1
      96: anewarray     #4                  // class java/lang/Object
      99: dup
     100: iconst_0
     101: aload         8
     103: invokevirtual #139                // Method java/io/File.getAbsolutePath:()Ljava/lang/String;
     106: aastore
     107: invokevirtual #121                // Method scala/Predef$.genericWrapArray:(Ljava/lang/Object;)Lscala/collection/mutable/WrappedArray;
     110: invokevirtual #125                // Method scala/StringContext.s:(Lscala/collection/Seq;)Ljava/lang/String;
     113: invokeinterface #145,  2          // InterfaceMethod scala/Function1.apply:(Ljava/lang/Object;)Ljava/lang/Object;
     118: pop
     119: aload         6
     121: aload_2
     122: aload_1
     123: aload_3
     124: aload         4
     126: aload         5
     128: invokevirtual #149                // Method bloop/integrations/gradle/model/BloopConverter.toBloopConfig:(Ljava/lang/String;Lorg/gradle/api/Project;Lcom/android/build/gradle/api/BaseVariant;Lscala/collection/immutable/List;Ljava/io/File;)Lscala/util/Try;
     131: astore        9
     133: aload         9
     135: instanceof    #151                // class scala/util/Failure
     138: ifeq          232
     141: aload         9
     143: checkcast     #151                // class scala/util/Failure
     146: astore        10
     148: aload         10
     150: invokevirtual #155                // Method scala/util/Failure.exception:()Ljava/lang/Throwable;
     153: astore        11
     155: aload         7
     157: new           #97                 // class scala/StringContext
     160: dup
     161: getstatic     #102                // Field scala/Predef$.MODULE$:Lscala/Predef$;
     164: iconst_3
     165: anewarray     #104                // class java/lang/String
     168: dup
     169: iconst_0
     170: ldc           #157                // String Skipping
     172: aastore
     173: dup
     174: iconst_1
     175: ldc           #159                // String  because:
     177: aastore
     178: dup
     179: iconst_2
     180: ldc           #106                // String
     182: aastore
     183: checkcast     #110                // class "[Ljava/lang/Object;"
     186: invokevirtual #114                // Method scala/Predef$.wrapRefArray:([Ljava/lang/Object;)Lscala/collection/mutable/WrappedArray;
     189: invokespecial #117                // Method scala/StringContext."<init>":(Lscala/collection/Seq;)V
     192: getstatic     #102                // Field scala/Predef$.MODULE$:Lscala/Predef$;
     195: iconst_2
     196: anewarray     #4                  // class java/lang/Object
     199: dup
     200: iconst_0
     201: aload_1
     202: invokeinterface #164,  1          // InterfaceMethod org/gradle/api/Project.getName:()Ljava/lang/String;
     207: aastore
     208: dup
     209: iconst_1
     210: aload         11
     212: aastore
     213: invokevirtual #121                // Method scala/Predef$.genericWrapArray:(Ljava/lang/Object;)Lscala/collection/mutable/WrappedArray;
     216: invokevirtual #125                // Method scala/StringContext.s:(Lscala/collection/Seq;)Ljava/lang/String;
     219: invokeinterface #145,  2          // InterfaceMethod scala/Function1.apply:(Ljava/lang/Object;)Ljava/lang/Object;
     224: checkcast     #166                // class scala/runtime/BoxedUnit
     227: astore        12
     229: goto          275
     232: aload         9
     234: instanceof    #168                // class scala/util/Success
     237: ifeq          276
     240: aload         9
     242: checkcast     #168                // class scala/util/Success
     245: astore        13
     247: aload         13
     249: invokevirtual #171                // Method scala/util/Success.value:()Ljava/lang/Object;
     252: checkcast     #173                // class bloop/config/Config$File
     255: astore        14
     257: getstatic     #178                // Field bloop/config/package$.MODULE$:Lbloop/config/package$;
     260: aload         14
     262: aload         8
     264: invokevirtual #182                // Method java/io/File.toPath:()Ljava/nio/file/Path;
     267: invokevirtual #186                // Method bloop/config/package$.write:(Lbloop/config/Config$File;Ljava/nio/file/Path;)V
     270: getstatic     #190                // Field scala/runtime/BoxedUnit.UNIT:Lscala/runtime/BoxedUnit;
     273: astore        12
     275: return
     276: new           #192                // class scala/MatchError
     279: dup
     280: aload         9
     282: invokespecial #195                // Method scala/MatchError."<init>":(Ljava/lang/Object;)V
     285: athrow

  private bloop.integrations.gradle.tasks.AndroidInstall$();
    Code:
       0: aload_0
       1: invokespecial #205                // Method java/lang/Object."<init>":()V
       4: aload_0
       5: putstatic     #207                // Field MODULE$:Lbloop/integrations/gradle/tasks/AndroidInstall$;
       8: return
}
