Compiled from "Route53RecoveryControlConfigAsyncClient.java"
public interface software.amazon.awssdk.services.route53recoverycontrolconfig.Route53RecoveryControlConfigAsyncClient extends software.amazon.awssdk.core.SdkClient {
  public static final java.lang.String SERVICE_NAME;

  public static final java.lang.String SERVICE_METADATA_ID;

  public static software.amazon.awssdk.services.route53recoverycontrolconfig.Route53RecoveryControlConfigAsyncClient create();
    Code:
       0: invokestatic  #1                  // InterfaceMethod builder:()Lsoftware/amazon/awssdk/services/route53recoverycontrolconfig/Route53RecoveryControlConfigAsyncClientBuilder;
       3: invokeinterface #2,  1            // InterfaceMethod software/amazon/awssdk/services/route53recoverycontrolconfig/Route53RecoveryControlConfigAsyncClientBuilder.build:()Ljava/lang/Object;
       8: checkcast     #3                  // class software/amazon/awssdk/services/route53recoverycontrolconfig/Route53RecoveryControlConfigAsyncClient
      11: areturn

  public static software.amazon.awssdk.services.route53recoverycontrolconfig.Route53RecoveryControlConfigAsyncClientBuilder builder();
    Code:
       0: new           #4                  // class software/amazon/awssdk/services/route53recoverycontrolconfig/DefaultRoute53RecoveryControlConfigAsyncClientBuilder
       3: dup
       4: invokespecial #5                  // Method software/amazon/awssdk/services/route53recoverycontrolconfig/DefaultRoute53RecoveryControlConfigAsyncClientBuilder."<init>":()V
       7: areturn

  public default java.util.concurrent.CompletableFuture<software.amazon.awssdk.services.route53recoverycontrolconfig.model.CreateClusterResponse> createCluster(software.amazon.awssdk.services.route53recoverycontrolconfig.model.CreateClusterRequest);
    Code:
       0: new           #6                  // class java/lang/UnsupportedOperationException
       3: dup
       4: invokespecial #7                  // Method java/lang/UnsupportedOperationException."<init>":()V
       7: athrow

  public default java.util.concurrent.CompletableFuture<software.amazon.awssdk.services.route53recoverycontrolconfig.model.CreateClusterResponse> createCluster(java.util.function.Consumer<software.amazon.awssdk.services.route53recoverycontrolconfig.model.CreateClusterRequest$Builder>);
    Code:
       0: aload_0
       1: invokestatic  #8                  // Method software/amazon/awssdk/services/route53recoverycontrolconfig/model/CreateClusterRequest.builder:()Lsoftware/amazon/awssdk/services/route53recoverycontrolconfig/model/CreateClusterRequest$Builder;
       4: aload_1
       5: invokeinterface #9,  2            // InterfaceMethod software/amazon/awssdk/services/route53recoverycontrolconfig/model/CreateClusterRequest$Builder.applyMutation:(Ljava/util/function/Consumer;)Lsoftware/amazon/awssdk/utils/builder/SdkBuilder;
      10: checkcast     #10                 // class software/amazon/awssdk/services/route53recoverycontrolconfig/model/CreateClusterRequest$Builder
      13: invokeinterface #11,  1           // InterfaceMethod software/amazon/awssdk/services/route53recoverycontrolconfig/model/CreateClusterRequest$Builder.build:()Ljava/lang/Object;
      18: checkcast     #12                 // class software/amazon/awssdk/services/route53recoverycontrolconfig/model/CreateClusterRequest
      21: invokeinterface #13,  2           // InterfaceMethod createCluster:(Lsoftware/amazon/awssdk/services/route53recoverycontrolconfig/model/CreateClusterRequest;)Ljava/util/concurrent/CompletableFuture;
      26: areturn

  public default java.util.concurrent.CompletableFuture<software.amazon.awssdk.services.route53recoverycontrolconfig.model.CreateControlPanelResponse> createControlPanel(software.amazon.awssdk.services.route53recoverycontrolconfig.model.CreateControlPanelRequest);
    Code:
       0: new           #6                  // class java/lang/UnsupportedOperationException
       3: dup
       4: invokespecial #7                  // Method java/lang/UnsupportedOperationException."<init>":()V
       7: athrow

  public default java.util.concurrent.CompletableFuture<software.amazon.awssdk.services.route53recoverycontrolconfig.model.CreateControlPanelResponse> createControlPanel(java.util.function.Consumer<software.amazon.awssdk.services.route53recoverycontrolconfig.model.CreateControlPanelRequest$Builder>);
    Code:
       0: aload_0
       1: invokestatic  #14                 // Method software/amazon/awssdk/services/route53recoverycontrolconfig/model/CreateControlPanelRequest.builder:()Lsoftware/amazon/awssdk/services/route53recoverycontrolconfig/model/CreateControlPanelRequest$Builder;
       4: aload_1
       5: invokeinterface #15,  2           // InterfaceMethod software/amazon/awssdk/services/route53recoverycontrolconfig/model/CreateControlPanelRequest$Builder.applyMutation:(Ljava/util/function/Consumer;)Lsoftware/amazon/awssdk/utils/builder/SdkBuilder;
      10: checkcast     #16                 // class software/amazon/awssdk/services/route53recoverycontrolconfig/model/CreateControlPanelRequest$Builder
      13: invokeinterface #17,  1           // InterfaceMethod software/amazon/awssdk/services/route53recoverycontrolconfig/model/CreateControlPanelRequest$Builder.build:()Ljava/lang/Object;
      18: checkcast     #18                 // class software/amazon/awssdk/services/route53recoverycontrolconfig/model/CreateControlPanelRequest
      21: invokeinterface #19,  2           // InterfaceMethod createControlPanel:(Lsoftware/amazon/awssdk/services/route53recoverycontrolconfig/model/CreateControlPanelRequest;)Ljava/util/concurrent/CompletableFuture;
      26: areturn

  public default java.util.concurrent.CompletableFuture<software.amazon.awssdk.services.route53recoverycontrolconfig.model.CreateRoutingControlResponse> createRoutingControl(software.amazon.awssdk.services.route53recoverycontrolconfig.model.CreateRoutingControlRequest);
    Code:
       0: new           #6                  // class java/lang/UnsupportedOperationException
       3: dup
       4: invokespecial #7                  // Method java/lang/UnsupportedOperationException."<init>":()V
       7: athrow

  public default java.util.concurrent.CompletableFuture<software.amazon.awssdk.services.route53recoverycontrolconfig.model.CreateRoutingControlResponse> createRoutingControl(java.util.function.Consumer<software.amazon.awssdk.services.route53recoverycontrolconfig.model.CreateRoutingControlRequest$Builder>);
    Code:
       0: aload_0
       1: invokestatic  #20                 // Method software/amazon/awssdk/services/route53recoverycontrolconfig/model/CreateRoutingControlRequest.builder:()Lsoftware/amazon/awssdk/services/route53recoverycontrolconfig/model/CreateRoutingControlRequest$Builder;
       4: aload_1
       5: invokeinterface #21,  2           // InterfaceMethod software/amazon/awssdk/services/route53recoverycontrolconfig/model/CreateRoutingControlRequest$Builder.applyMutation:(Ljava/util/function/Consumer;)Lsoftware/amazon/awssdk/utils/builder/SdkBuilder;
      10: checkcast     #22                 // class software/amazon/awssdk/services/route53recoverycontrolconfig/model/CreateRoutingControlRequest$Builder
      13: invokeinterface #23,  1           // InterfaceMethod software/amazon/awssdk/services/route53recoverycontrolconfig/model/CreateRoutingControlRequest$Builder.build:()Ljava/lang/Object;
      18: checkcast     #24                 // class software/amazon/awssdk/services/route53recoverycontrolconfig/model/CreateRoutingControlRequest
      21: invokeinterface #25,  2           // InterfaceMethod createRoutingControl:(Lsoftware/amazon/awssdk/services/route53recoverycontrolconfig/model/CreateRoutingControlRequest;)Ljava/util/concurrent/CompletableFuture;
      26: areturn

  public default java.util.concurrent.CompletableFuture<software.amazon.awssdk.services.route53recoverycontrolconfig.model.CreateSafetyRuleResponse> createSafetyRule(software.amazon.awssdk.services.route53recoverycontrolconfig.model.CreateSafetyRuleRequest);
    Code:
       0: new           #6                  // class java/lang/UnsupportedOperationException
       3: dup
       4: invokespecial #7                  // Method java/lang/UnsupportedOperationException."<init>":()V
       7: athrow

  public default java.util.concurrent.CompletableFuture<software.amazon.awssdk.services.route53recoverycontrolconfig.model.CreateSafetyRuleResponse> createSafetyRule(java.util.function.Consumer<software.amazon.awssdk.services.route53recoverycontrolconfig.model.CreateSafetyRuleRequest$Builder>);
    Code:
       0: aload_0
       1: invokestatic  #26                 // Method software/amazon/awssdk/services/route53recoverycontrolconfig/model/CreateSafetyRuleRequest.builder:()Lsoftware/amazon/awssdk/services/route53recoverycontrolconfig/model/CreateSafetyRuleRequest$Builder;
       4: aload_1
       5: invokeinterface #27,  2           // InterfaceMethod software/amazon/awssdk/services/route53recoverycontrolconfig/model/CreateSafetyRuleRequest$Builder.applyMutation:(Ljava/util/function/Consumer;)Lsoftware/amazon/awssdk/utils/builder/SdkBuilder;
      10: checkcast     #28                 // class software/amazon/awssdk/services/route53recoverycontrolconfig/model/CreateSafetyRuleRequest$Builder
      13: invokeinterface #29,  1           // InterfaceMethod software/amazon/awssdk/services/route53recoverycontrolconfig/model/CreateSafetyRuleRequest$Builder.build:()Ljava/lang/Object;
      18: checkcast     #30                 // class software/amazon/awssdk/services/route53recoverycontrolconfig/model/CreateSafetyRuleRequest
      21: invokeinterface #31,  2           // InterfaceMethod createSafetyRule:(Lsoftware/amazon/awssdk/services/route53recoverycontrolconfig/model/CreateSafetyRuleRequest;)Ljava/util/concurrent/CompletableFuture;
      26: areturn

  public default java.util.concurrent.CompletableFuture<software.amazon.awssdk.services.route53recoverycontrolconfig.model.DeleteClusterResponse> deleteCluster(software.amazon.awssdk.services.route53recoverycontrolconfig.model.DeleteClusterRequest);
    Code:
       0: new           #6                  // class java/lang/UnsupportedOperationException
       3: dup
       4: invokespecial #7                  // Method java/lang/UnsupportedOperationException."<init>":()V
       7: athrow

  public default java.util.concurrent.CompletableFuture<software.amazon.awssdk.services.route53recoverycontrolconfig.model.DeleteClusterResponse> deleteCluster(java.util.function.Consumer<software.amazon.awssdk.services.route53recoverycontrolconfig.model.DeleteClusterRequest$Builder>);
    Code:
       0: aload_0
       1: invokestatic  #32                 // Method software/amazon/awssdk/services/route53recoverycontrolconfig/model/DeleteClusterRequest.builder:()Lsoftware/amazon/awssdk/services/route53recoverycontrolconfig/model/DeleteClusterRequest$Builder;
       4: aload_1
       5: invokeinterface #33,  2           // InterfaceMethod software/amazon/awssdk/services/route53recoverycontrolconfig/model/DeleteClusterRequest$Builder.applyMutation:(Ljava/util/function/Consumer;)Lsoftware/amazon/awssdk/utils/builder/SdkBuilder;
      10: checkcast     #34                 // class software/amazon/awssdk/services/route53recoverycontrolconfig/model/DeleteClusterRequest$Builder
      13: invokeinterface #35,  1           // InterfaceMethod software/amazon/awssdk/services/route53recoverycontrolconfig/model/DeleteClusterRequest$Builder.build:()Ljava/lang/Object;
      18: checkcast     #36                 // class software/amazon/awssdk/services/route53recoverycontrolconfig/model/DeleteClusterRequest
      21: invokeinterface #37,  2           // InterfaceMethod deleteCluster:(Lsoftware/amazon/awssdk/services/route53recoverycontrolconfig/model/DeleteClusterRequest;)Ljava/util/concurrent/CompletableFuture;
      26: areturn

  public default java.util.concurrent.CompletableFuture<software.amazon.awssdk.services.route53recoverycontrolconfig.model.DeleteControlPanelResponse> deleteControlPanel(software.amazon.awssdk.services.route53recoverycontrolconfig.model.DeleteControlPanelRequest);
    Code:
       0: new           #6                  // class java/lang/UnsupportedOperationException
       3: dup
       4: invokespecial #7                  // Method java/lang/UnsupportedOperationException."<init>":()V
       7: athrow

  public default java.util.concurrent.CompletableFuture<software.amazon.awssdk.services.route53recoverycontrolconfig.model.DeleteControlPanelResponse> deleteControlPanel(java.util.function.Consumer<software.amazon.awssdk.services.route53recoverycontrolconfig.model.DeleteControlPanelRequest$Builder>);
    Code:
       0: aload_0
       1: invokestatic  #38                 // Method software/amazon/awssdk/services/route53recoverycontrolconfig/model/DeleteControlPanelRequest.builder:()Lsoftware/amazon/awssdk/services/route53recoverycontrolconfig/model/DeleteControlPanelRequest$Builder;
       4: aload_1
       5: invokeinterface #39,  2           // InterfaceMethod software/amazon/awssdk/services/route53recoverycontrolconfig/model/DeleteControlPanelRequest$Builder.applyMutation:(Ljava/util/function/Consumer;)Lsoftware/amazon/awssdk/utils/builder/SdkBuilder;
      10: checkcast     #40                 // class software/amazon/awssdk/services/route53recoverycontrolconfig/model/DeleteControlPanelRequest$Builder
      13: invokeinterface #41,  1           // InterfaceMethod software/amazon/awssdk/services/route53recoverycontrolconfig/model/DeleteControlPanelRequest$Builder.build:()Ljava/lang/Object;
      18: checkcast     #42                 // class software/amazon/awssdk/services/route53recoverycontrolconfig/model/DeleteControlPanelRequest
      21: invokeinterface #43,  2           // InterfaceMethod deleteControlPanel:(Lsoftware/amazon/awssdk/services/route53recoverycontrolconfig/model/DeleteControlPanelRequest;)Ljava/util/concurrent/CompletableFuture;
      26: areturn

  public default java.util.concurrent.CompletableFuture<software.amazon.awssdk.services.route53recoverycontrolconfig.model.DeleteRoutingControlResponse> deleteRoutingControl(software.amazon.awssdk.services.route53recoverycontrolconfig.model.DeleteRoutingControlRequest);
    Code:
       0: new           #6                  // class java/lang/UnsupportedOperationException
       3: dup
       4: invokespecial #7                  // Method java/lang/UnsupportedOperationException."<init>":()V
       7: athrow

  public default java.util.concurrent.CompletableFuture<software.amazon.awssdk.services.route53recoverycontrolconfig.model.DeleteRoutingControlResponse> deleteRoutingControl(java.util.function.Consumer<software.amazon.awssdk.services.route53recoverycontrolconfig.model.DeleteRoutingControlRequest$Builder>);
    Code:
       0: aload_0
       1: invokestatic  #44                 // Method software/amazon/awssdk/services/route53recoverycontrolconfig/model/DeleteRoutingControlRequest.builder:()Lsoftware/amazon/awssdk/services/route53recoverycontrolconfig/model/DeleteRoutingControlRequest$Builder;
       4: aload_1
       5: invokeinterface #45,  2           // InterfaceMethod software/amazon/awssdk/services/route53recoverycontrolconfig/model/DeleteRoutingControlRequest$Builder.applyMutation:(Ljava/util/function/Consumer;)Lsoftware/amazon/awssdk/utils/builder/SdkBuilder;
      10: checkcast     #46                 // class software/amazon/awssdk/services/route53recoverycontrolconfig/model/DeleteRoutingControlRequest$Builder
      13: invokeinterface #47,  1           // InterfaceMethod software/amazon/awssdk/services/route53recoverycontrolconfig/model/DeleteRoutingControlRequest$Builder.build:()Ljava/lang/Object;
      18: checkcast     #48                 // class software/amazon/awssdk/services/route53recoverycontrolconfig/model/DeleteRoutingControlRequest
      21: invokeinterface #49,  2           // InterfaceMethod deleteRoutingControl:(Lsoftware/amazon/awssdk/services/route53recoverycontrolconfig/model/DeleteRoutingControlRequest;)Ljava/util/concurrent/CompletableFuture;
      26: areturn

  public default java.util.concurrent.CompletableFuture<software.amazon.awssdk.services.route53recoverycontrolconfig.model.DeleteSafetyRuleResponse> deleteSafetyRule(software.amazon.awssdk.services.route53recoverycontrolconfig.model.DeleteSafetyRuleRequest);
    Code:
       0: new           #6                  // class java/lang/UnsupportedOperationException
       3: dup
       4: invokespecial #7                  // Method java/lang/UnsupportedOperationException."<init>":()V
       7: athrow

  public default java.util.concurrent.CompletableFuture<software.amazon.awssdk.services.route53recoverycontrolconfig.model.DeleteSafetyRuleResponse> deleteSafetyRule(java.util.function.Consumer<software.amazon.awssdk.services.route53recoverycontrolconfig.model.DeleteSafetyRuleRequest$Builder>);
    Code:
       0: aload_0
       1: invokestatic  #50                 // Method software/amazon/awssdk/services/route53recoverycontrolconfig/model/DeleteSafetyRuleRequest.builder:()Lsoftware/amazon/awssdk/services/route53recoverycontrolconfig/model/DeleteSafetyRuleRequest$Builder;
       4: aload_1
       5: invokeinterface #51,  2           // InterfaceMethod software/amazon/awssdk/services/route53recoverycontrolconfig/model/DeleteSafetyRuleRequest$Builder.applyMutation:(Ljava/util/function/Consumer;)Lsoftware/amazon/awssdk/utils/builder/SdkBuilder;
      10: checkcast     #52                 // class software/amazon/awssdk/services/route53recoverycontrolconfig/model/DeleteSafetyRuleRequest$Builder
      13: invokeinterface #53,  1           // InterfaceMethod software/amazon/awssdk/services/route53recoverycontrolconfig/model/DeleteSafetyRuleRequest$Builder.build:()Ljava/lang/Object;
      18: checkcast     #54                 // class software/amazon/awssdk/services/route53recoverycontrolconfig/model/DeleteSafetyRuleRequest
      21: invokeinterface #55,  2           // InterfaceMethod deleteSafetyRule:(Lsoftware/amazon/awssdk/services/route53recoverycontrolconfig/model/DeleteSafetyRuleRequest;)Ljava/util/concurrent/CompletableFuture;
      26: areturn

  public default java.util.concurrent.CompletableFuture<software.amazon.awssdk.services.route53recoverycontrolconfig.model.DescribeClusterResponse> describeCluster(software.amazon.awssdk.services.route53recoverycontrolconfig.model.DescribeClusterRequest);
    Code:
       0: new           #6                  // class java/lang/UnsupportedOperationException
       3: dup
       4: invokespecial #7                  // Method java/lang/UnsupportedOperationException."<init>":()V
       7: athrow

  public default java.util.concurrent.CompletableFuture<software.amazon.awssdk.services.route53recoverycontrolconfig.model.DescribeClusterResponse> describeCluster(java.util.function.Consumer<software.amazon.awssdk.services.route53recoverycontrolconfig.model.DescribeClusterRequest$Builder>);
    Code:
       0: aload_0
       1: invokestatic  #56                 // Method software/amazon/awssdk/services/route53recoverycontrolconfig/model/DescribeClusterRequest.builder:()Lsoftware/amazon/awssdk/services/route53recoverycontrolconfig/model/DescribeClusterRequest$Builder;
       4: aload_1
       5: invokeinterface #57,  2           // InterfaceMethod software/amazon/awssdk/services/route53recoverycontrolconfig/model/DescribeClusterRequest$Builder.applyMutation:(Ljava/util/function/Consumer;)Lsoftware/amazon/awssdk/utils/builder/SdkBuilder;
      10: checkcast     #58                 // class software/amazon/awssdk/services/route53recoverycontrolconfig/model/DescribeClusterRequest$Builder
      13: invokeinterface #59,  1           // InterfaceMethod software/amazon/awssdk/services/route53recoverycontrolconfig/model/DescribeClusterRequest$Builder.build:()Ljava/lang/Object;
      18: checkcast     #60                 // class software/amazon/awssdk/services/route53recoverycontrolconfig/model/DescribeClusterRequest
      21: invokeinterface #61,  2           // InterfaceMethod describeCluster:(Lsoftware/amazon/awssdk/services/route53recoverycontrolconfig/model/DescribeClusterRequest;)Ljava/util/concurrent/CompletableFuture;
      26: areturn

  public default java.util.concurrent.CompletableFuture<software.amazon.awssdk.services.route53recoverycontrolconfig.model.DescribeControlPanelResponse> describeControlPanel(software.amazon.awssdk.services.route53recoverycontrolconfig.model.DescribeControlPanelRequest);
    Code:
       0: new           #6                  // class java/lang/UnsupportedOperationException
       3: dup
       4: invokespecial #7                  // Method java/lang/UnsupportedOperationException."<init>":()V
       7: athrow

  public default java.util.concurrent.CompletableFuture<software.amazon.awssdk.services.route53recoverycontrolconfig.model.DescribeControlPanelResponse> describeControlPanel(java.util.function.Consumer<software.amazon.awssdk.services.route53recoverycontrolconfig.model.DescribeControlPanelRequest$Builder>);
    Code:
       0: aload_0
       1: invokestatic  #62                 // Method software/amazon/awssdk/services/route53recoverycontrolconfig/model/DescribeControlPanelRequest.builder:()Lsoftware/amazon/awssdk/services/route53recoverycontrolconfig/model/DescribeControlPanelRequest$Builder;
       4: aload_1
       5: invokeinterface #63,  2           // InterfaceMethod software/amazon/awssdk/services/route53recoverycontrolconfig/model/DescribeControlPanelRequest$Builder.applyMutation:(Ljava/util/function/Consumer;)Lsoftware/amazon/awssdk/utils/builder/SdkBuilder;
      10: checkcast     #64                 // class software/amazon/awssdk/services/route53recoverycontrolconfig/model/DescribeControlPanelRequest$Builder
      13: invokeinterface #65,  1           // InterfaceMethod software/amazon/awssdk/services/route53recoverycontrolconfig/model/DescribeControlPanelRequest$Builder.build:()Ljava/lang/Object;
      18: checkcast     #66                 // class software/amazon/awssdk/services/route53recoverycontrolconfig/model/DescribeControlPanelRequest
      21: invokeinterface #67,  2           // InterfaceMethod describeControlPanel:(Lsoftware/amazon/awssdk/services/route53recoverycontrolconfig/model/DescribeControlPanelRequest;)Ljava/util/concurrent/CompletableFuture;
      26: areturn

  public default java.util.concurrent.CompletableFuture<software.amazon.awssdk.services.route53recoverycontrolconfig.model.DescribeRoutingControlResponse> describeRoutingControl(software.amazon.awssdk.services.route53recoverycontrolconfig.model.DescribeRoutingControlRequest);
    Code:
       0: new           #6                  // class java/lang/UnsupportedOperationException
       3: dup
       4: invokespecial #7                  // Method java/lang/UnsupportedOperationException."<init>":()V
       7: athrow

  public default java.util.concurrent.CompletableFuture<software.amazon.awssdk.services.route53recoverycontrolconfig.model.DescribeRoutingControlResponse> describeRoutingControl(java.util.function.Consumer<software.amazon.awssdk.services.route53recoverycontrolconfig.model.DescribeRoutingControlRequest$Builder>);
    Code:
       0: aload_0
       1: invokestatic  #68                 // Method software/amazon/awssdk/services/route53recoverycontrolconfig/model/DescribeRoutingControlRequest.builder:()Lsoftware/amazon/awssdk/services/route53recoverycontrolconfig/model/DescribeRoutingControlRequest$Builder;
       4: aload_1
       5: invokeinterface #69,  2           // InterfaceMethod software/amazon/awssdk/services/route53recoverycontrolconfig/model/DescribeRoutingControlRequest$Builder.applyMutation:(Ljava/util/function/Consumer;)Lsoftware/amazon/awssdk/utils/builder/SdkBuilder;
      10: checkcast     #70                 // class software/amazon/awssdk/services/route53recoverycontrolconfig/model/DescribeRoutingControlRequest$Builder
      13: invokeinterface #71,  1           // InterfaceMethod software/amazon/awssdk/services/route53recoverycontrolconfig/model/DescribeRoutingControlRequest$Builder.build:()Ljava/lang/Object;
      18: checkcast     #72                 // class software/amazon/awssdk/services/route53recoverycontrolconfig/model/DescribeRoutingControlRequest
      21: invokeinterface #73,  2           // InterfaceMethod describeRoutingControl:(Lsoftware/amazon/awssdk/services/route53recoverycontrolconfig/model/DescribeRoutingControlRequest;)Ljava/util/concurrent/CompletableFuture;
      26: areturn

  public default java.util.concurrent.CompletableFuture<software.amazon.awssdk.services.route53recoverycontrolconfig.model.DescribeSafetyRuleResponse> describeSafetyRule(software.amazon.awssdk.services.route53recoverycontrolconfig.model.DescribeSafetyRuleRequest);
    Code:
       0: new           #6                  // class java/lang/UnsupportedOperationException
       3: dup
       4: invokespecial #7                  // Method java/lang/UnsupportedOperationException."<init>":()V
       7: athrow

  public default java.util.concurrent.CompletableFuture<software.amazon.awssdk.services.route53recoverycontrolconfig.model.DescribeSafetyRuleResponse> describeSafetyRule(java.util.function.Consumer<software.amazon.awssdk.services.route53recoverycontrolconfig.model.DescribeSafetyRuleRequest$Builder>);
    Code:
       0: aload_0
       1: invokestatic  #74                 // Method software/amazon/awssdk/services/route53recoverycontrolconfig/model/DescribeSafetyRuleRequest.builder:()Lsoftware/amazon/awssdk/services/route53recoverycontrolconfig/model/DescribeSafetyRuleRequest$Builder;
       4: aload_1
       5: invokeinterface #75,  2           // InterfaceMethod software/amazon/awssdk/services/route53recoverycontrolconfig/model/DescribeSafetyRuleRequest$Builder.applyMutation:(Ljava/util/function/Consumer;)Lsoftware/amazon/awssdk/utils/builder/SdkBuilder;
      10: checkcast     #76                 // class software/amazon/awssdk/services/route53recoverycontrolconfig/model/DescribeSafetyRuleRequest$Builder
      13: invokeinterface #77,  1           // InterfaceMethod software/amazon/awssdk/services/route53recoverycontrolconfig/model/DescribeSafetyRuleRequest$Builder.build:()Ljava/lang/Object;
      18: checkcast     #78                 // class software/amazon/awssdk/services/route53recoverycontrolconfig/model/DescribeSafetyRuleRequest
      21: invokeinterface #79,  2           // InterfaceMethod describeSafetyRule:(Lsoftware/amazon/awssdk/services/route53recoverycontrolconfig/model/DescribeSafetyRuleRequest;)Ljava/util/concurrent/CompletableFuture;
      26: areturn

  public default java.util.concurrent.CompletableFuture<software.amazon.awssdk.services.route53recoverycontrolconfig.model.ListAssociatedRoute53HealthChecksResponse> listAssociatedRoute53HealthChecks(software.amazon.awssdk.services.route53recoverycontrolconfig.model.ListAssociatedRoute53HealthChecksRequest);
    Code:
       0: new           #6                  // class java/lang/UnsupportedOperationException
       3: dup
       4: invokespecial #7                  // Method java/lang/UnsupportedOperationException."<init>":()V
       7: athrow

  public default java.util.concurrent.CompletableFuture<software.amazon.awssdk.services.route53recoverycontrolconfig.model.ListAssociatedRoute53HealthChecksResponse> listAssociatedRoute53HealthChecks(java.util.function.Consumer<software.amazon.awssdk.services.route53recoverycontrolconfig.model.ListAssociatedRoute53HealthChecksRequest$Builder>);
    Code:
       0: aload_0
       1: invokestatic  #80                 // Method software/amazon/awssdk/services/route53recoverycontrolconfig/model/ListAssociatedRoute53HealthChecksRequest.builder:()Lsoftware/amazon/awssdk/services/route53recoverycontrolconfig/model/ListAssociatedRoute53HealthChecksRequest$Builder;
       4: aload_1
       5: invokeinterface #81,  2           // InterfaceMethod software/amazon/awssdk/services/route53recoverycontrolconfig/model/ListAssociatedRoute53HealthChecksRequest$Builder.applyMutation:(Ljava/util/function/Consumer;)Lsoftware/amazon/awssdk/utils/builder/SdkBuilder;
      10: checkcast     #82                 // class software/amazon/awssdk/services/route53recoverycontrolconfig/model/ListAssociatedRoute53HealthChecksRequest$Builder
      13: invokeinterface #83,  1           // InterfaceMethod software/amazon/awssdk/services/route53recoverycontrolconfig/model/ListAssociatedRoute53HealthChecksRequest$Builder.build:()Ljava/lang/Object;
      18: checkcast     #84                 // class software/amazon/awssdk/services/route53recoverycontrolconfig/model/ListAssociatedRoute53HealthChecksRequest
      21: invokeinterface #85,  2           // InterfaceMethod listAssociatedRoute53HealthChecks:(Lsoftware/amazon/awssdk/services/route53recoverycontrolconfig/model/ListAssociatedRoute53HealthChecksRequest;)Ljava/util/concurrent/CompletableFuture;
      26: areturn

  public default software.amazon.awssdk.services.route53recoverycontrolconfig.paginators.ListAssociatedRoute53HealthChecksPublisher listAssociatedRoute53HealthChecksPaginator(software.amazon.awssdk.services.route53recoverycontrolconfig.model.ListAssociatedRoute53HealthChecksRequest);
    Code:
       0: new           #6                  // class java/lang/UnsupportedOperationException
       3: dup
       4: invokespecial #7                  // Method java/lang/UnsupportedOperationException."<init>":()V
       7: athrow

  public default software.amazon.awssdk.services.route53recoverycontrolconfig.paginators.ListAssociatedRoute53HealthChecksPublisher listAssociatedRoute53HealthChecksPaginator(java.util.function.Consumer<software.amazon.awssdk.services.route53recoverycontrolconfig.model.ListAssociatedRoute53HealthChecksRequest$Builder>);
    Code:
       0: aload_0
       1: invokestatic  #80                 // Method software/amazon/awssdk/services/route53recoverycontrolconfig/model/ListAssociatedRoute53HealthChecksRequest.builder:()Lsoftware/amazon/awssdk/services/route53recoverycontrolconfig/model/ListAssociatedRoute53HealthChecksRequest$Builder;
       4: aload_1
       5: invokeinterface #81,  2           // InterfaceMethod software/amazon/awssdk/services/route53recoverycontrolconfig/model/ListAssociatedRoute53HealthChecksRequest$Builder.applyMutation:(Ljava/util/function/Consumer;)Lsoftware/amazon/awssdk/utils/builder/SdkBuilder;
      10: checkcast     #82                 // class software/amazon/awssdk/services/route53recoverycontrolconfig/model/ListAssociatedRoute53HealthChecksRequest$Builder
      13: invokeinterface #83,  1           // InterfaceMethod software/amazon/awssdk/services/route53recoverycontrolconfig/model/ListAssociatedRoute53HealthChecksRequest$Builder.build:()Ljava/lang/Object;
      18: checkcast     #84                 // class software/amazon/awssdk/services/route53recoverycontrolconfig/model/ListAssociatedRoute53HealthChecksRequest
      21: invokeinterface #86,  2           // InterfaceMethod listAssociatedRoute53HealthChecksPaginator:(Lsoftware/amazon/awssdk/services/route53recoverycontrolconfig/model/ListAssociatedRoute53HealthChecksRequest;)Lsoftware/amazon/awssdk/services/route53recoverycontrolconfig/paginators/ListAssociatedRoute53HealthChecksPublisher;
      26: areturn

  public default java.util.concurrent.CompletableFuture<software.amazon.awssdk.services.route53recoverycontrolconfig.model.ListClustersResponse> listClusters(software.amazon.awssdk.services.route53recoverycontrolconfig.model.ListClustersRequest);
    Code:
       0: new           #6                  // class java/lang/UnsupportedOperationException
       3: dup
       4: invokespecial #7                  // Method java/lang/UnsupportedOperationException."<init>":()V
       7: athrow

  public default java.util.concurrent.CompletableFuture<software.amazon.awssdk.services.route53recoverycontrolconfig.model.ListClustersResponse> listClusters(java.util.function.Consumer<software.amazon.awssdk.services.route53recoverycontrolconfig.model.ListClustersRequest$Builder>);
    Code:
       0: aload_0
       1: invokestatic  #87                 // Method software/amazon/awssdk/services/route53recoverycontrolconfig/model/ListClustersRequest.builder:()Lsoftware/amazon/awssdk/services/route53recoverycontrolconfig/model/ListClustersRequest$Builder;
       4: aload_1
       5: invokeinterface #88,  2           // InterfaceMethod software/amazon/awssdk/services/route53recoverycontrolconfig/model/ListClustersRequest$Builder.applyMutation:(Ljava/util/function/Consumer;)Lsoftware/amazon/awssdk/utils/builder/SdkBuilder;
      10: checkcast     #89                 // class software/amazon/awssdk/services/route53recoverycontrolconfig/model/ListClustersRequest$Builder
      13: invokeinterface #90,  1           // InterfaceMethod software/amazon/awssdk/services/route53recoverycontrolconfig/model/ListClustersRequest$Builder.build:()Ljava/lang/Object;
      18: checkcast     #91                 // class software/amazon/awssdk/services/route53recoverycontrolconfig/model/ListClustersRequest
      21: invokeinterface #92,  2           // InterfaceMethod listClusters:(Lsoftware/amazon/awssdk/services/route53recoverycontrolconfig/model/ListClustersRequest;)Ljava/util/concurrent/CompletableFuture;
      26: areturn

  public default software.amazon.awssdk.services.route53recoverycontrolconfig.paginators.ListClustersPublisher listClustersPaginator(software.amazon.awssdk.services.route53recoverycontrolconfig.model.ListClustersRequest);
    Code:
       0: new           #6                  // class java/lang/UnsupportedOperationException
       3: dup
       4: invokespecial #7                  // Method java/lang/UnsupportedOperationException."<init>":()V
       7: athrow

  public default software.amazon.awssdk.services.route53recoverycontrolconfig.paginators.ListClustersPublisher listClustersPaginator(java.util.function.Consumer<software.amazon.awssdk.services.route53recoverycontrolconfig.model.ListClustersRequest$Builder>);
    Code:
       0: aload_0
       1: invokestatic  #87                 // Method software/amazon/awssdk/services/route53recoverycontrolconfig/model/ListClustersRequest.builder:()Lsoftware/amazon/awssdk/services/route53recoverycontrolconfig/model/ListClustersRequest$Builder;
       4: aload_1
       5: invokeinterface #88,  2           // InterfaceMethod software/amazon/awssdk/services/route53recoverycontrolconfig/model/ListClustersRequest$Builder.applyMutation:(Ljava/util/function/Consumer;)Lsoftware/amazon/awssdk/utils/builder/SdkBuilder;
      10: checkcast     #89                 // class software/amazon/awssdk/services/route53recoverycontrolconfig/model/ListClustersRequest$Builder
      13: invokeinterface #90,  1           // InterfaceMethod software/amazon/awssdk/services/route53recoverycontrolconfig/model/ListClustersRequest$Builder.build:()Ljava/lang/Object;
      18: checkcast     #91                 // class software/amazon/awssdk/services/route53recoverycontrolconfig/model/ListClustersRequest
      21: invokeinterface #93,  2           // InterfaceMethod listClustersPaginator:(Lsoftware/amazon/awssdk/services/route53recoverycontrolconfig/model/ListClustersRequest;)Lsoftware/amazon/awssdk/services/route53recoverycontrolconfig/paginators/ListClustersPublisher;
      26: areturn

  public default java.util.concurrent.CompletableFuture<software.amazon.awssdk.services.route53recoverycontrolconfig.model.ListControlPanelsResponse> listControlPanels(software.amazon.awssdk.services.route53recoverycontrolconfig.model.ListControlPanelsRequest);
    Code:
       0: new           #6                  // class java/lang/UnsupportedOperationException
       3: dup
       4: invokespecial #7                  // Method java/lang/UnsupportedOperationException."<init>":()V
       7: athrow

  public default java.util.concurrent.CompletableFuture<software.amazon.awssdk.services.route53recoverycontrolconfig.model.ListControlPanelsResponse> listControlPanels(java.util.function.Consumer<software.amazon.awssdk.services.route53recoverycontrolconfig.model.ListControlPanelsRequest$Builder>);
    Code:
       0: aload_0
       1: invokestatic  #94                 // Method software/amazon/awssdk/services/route53recoverycontrolconfig/model/ListControlPanelsRequest.builder:()Lsoftware/amazon/awssdk/services/route53recoverycontrolconfig/model/ListControlPanelsRequest$Builder;
       4: aload_1
       5: invokeinterface #95,  2           // InterfaceMethod software/amazon/awssdk/services/route53recoverycontrolconfig/model/ListControlPanelsRequest$Builder.applyMutation:(Ljava/util/function/Consumer;)Lsoftware/amazon/awssdk/utils/builder/SdkBuilder;
      10: checkcast     #96                 // class software/amazon/awssdk/services/route53recoverycontrolconfig/model/ListControlPanelsRequest$Builder
      13: invokeinterface #97,  1           // InterfaceMethod software/amazon/awssdk/services/route53recoverycontrolconfig/model/ListControlPanelsRequest$Builder.build:()Ljava/lang/Object;
      18: checkcast     #98                 // class software/amazon/awssdk/services/route53recoverycontrolconfig/model/ListControlPanelsRequest
      21: invokeinterface #99,  2           // InterfaceMethod listControlPanels:(Lsoftware/amazon/awssdk/services/route53recoverycontrolconfig/model/ListControlPanelsRequest;)Ljava/util/concurrent/CompletableFuture;
      26: areturn

  public default software.amazon.awssdk.services.route53recoverycontrolconfig.paginators.ListControlPanelsPublisher listControlPanelsPaginator(software.amazon.awssdk.services.route53recoverycontrolconfig.model.ListControlPanelsRequest);
    Code:
       0: new           #6                  // class java/lang/UnsupportedOperationException
       3: dup
       4: invokespecial #7                  // Method java/lang/UnsupportedOperationException."<init>":()V
       7: athrow

  public default software.amazon.awssdk.services.route53recoverycontrolconfig.paginators.ListControlPanelsPublisher listControlPanelsPaginator(java.util.function.Consumer<software.amazon.awssdk.services.route53recoverycontrolconfig.model.ListControlPanelsRequest$Builder>);
    Code:
       0: aload_0
       1: invokestatic  #94                 // Method software/amazon/awssdk/services/route53recoverycontrolconfig/model/ListControlPanelsRequest.builder:()Lsoftware/amazon/awssdk/services/route53recoverycontrolconfig/model/ListControlPanelsRequest$Builder;
       4: aload_1
       5: invokeinterface #95,  2           // InterfaceMethod software/amazon/awssdk/services/route53recoverycontrolconfig/model/ListControlPanelsRequest$Builder.applyMutation:(Ljava/util/function/Consumer;)Lsoftware/amazon/awssdk/utils/builder/SdkBuilder;
      10: checkcast     #96                 // class software/amazon/awssdk/services/route53recoverycontrolconfig/model/ListControlPanelsRequest$Builder
      13: invokeinterface #97,  1           // InterfaceMethod software/amazon/awssdk/services/route53recoverycontrolconfig/model/ListControlPanelsRequest$Builder.build:()Ljava/lang/Object;
      18: checkcast     #98                 // class software/amazon/awssdk/services/route53recoverycontrolconfig/model/ListControlPanelsRequest
      21: invokeinterface #100,  2          // InterfaceMethod listControlPanelsPaginator:(Lsoftware/amazon/awssdk/services/route53recoverycontrolconfig/model/ListControlPanelsRequest;)Lsoftware/amazon/awssdk/services/route53recoverycontrolconfig/paginators/ListControlPanelsPublisher;
      26: areturn

  public default java.util.concurrent.CompletableFuture<software.amazon.awssdk.services.route53recoverycontrolconfig.model.ListRoutingControlsResponse> listRoutingControls(software.amazon.awssdk.services.route53recoverycontrolconfig.model.ListRoutingControlsRequest);
    Code:
       0: new           #6                  // class java/lang/UnsupportedOperationException
       3: dup
       4: invokespecial #7                  // Method java/lang/UnsupportedOperationException."<init>":()V
       7: athrow

  public default java.util.concurrent.CompletableFuture<software.amazon.awssdk.services.route53recoverycontrolconfig.model.ListRoutingControlsResponse> listRoutingControls(java.util.function.Consumer<software.amazon.awssdk.services.route53recoverycontrolconfig.model.ListRoutingControlsRequest$Builder>);
    Code:
       0: aload_0
       1: invokestatic  #101                // Method software/amazon/awssdk/services/route53recoverycontrolconfig/model/ListRoutingControlsRequest.builder:()Lsoftware/amazon/awssdk/services/route53recoverycontrolconfig/model/ListRoutingControlsRequest$Builder;
       4: aload_1
       5: invokeinterface #102,  2          // InterfaceMethod software/amazon/awssdk/services/route53recoverycontrolconfig/model/ListRoutingControlsRequest$Builder.applyMutation:(Ljava/util/function/Consumer;)Lsoftware/amazon/awssdk/utils/builder/SdkBuilder;
      10: checkcast     #103                // class software/amazon/awssdk/services/route53recoverycontrolconfig/model/ListRoutingControlsRequest$Builder
      13: invokeinterface #104,  1          // InterfaceMethod software/amazon/awssdk/services/route53recoverycontrolconfig/model/ListRoutingControlsRequest$Builder.build:()Ljava/lang/Object;
      18: checkcast     #105                // class software/amazon/awssdk/services/route53recoverycontrolconfig/model/ListRoutingControlsRequest
      21: invokeinterface #106,  2          // InterfaceMethod listRoutingControls:(Lsoftware/amazon/awssdk/services/route53recoverycontrolconfig/model/ListRoutingControlsRequest;)Ljava/util/concurrent/CompletableFuture;
      26: areturn

  public default software.amazon.awssdk.services.route53recoverycontrolconfig.paginators.ListRoutingControlsPublisher listRoutingControlsPaginator(software.amazon.awssdk.services.route53recoverycontrolconfig.model.ListRoutingControlsRequest);
    Code:
       0: new           #6                  // class java/lang/UnsupportedOperationException
       3: dup
       4: invokespecial #7                  // Method java/lang/UnsupportedOperationException."<init>":()V
       7: athrow

  public default software.amazon.awssdk.services.route53recoverycontrolconfig.paginators.ListRoutingControlsPublisher listRoutingControlsPaginator(java.util.function.Consumer<software.amazon.awssdk.services.route53recoverycontrolconfig.model.ListRoutingControlsRequest$Builder>);
    Code:
       0: aload_0
       1: invokestatic  #101                // Method software/amazon/awssdk/services/route53recoverycontrolconfig/model/ListRoutingControlsRequest.builder:()Lsoftware/amazon/awssdk/services/route53recoverycontrolconfig/model/ListRoutingControlsRequest$Builder;
       4: aload_1
       5: invokeinterface #102,  2          // InterfaceMethod software/amazon/awssdk/services/route53recoverycontrolconfig/model/ListRoutingControlsRequest$Builder.applyMutation:(Ljava/util/function/Consumer;)Lsoftware/amazon/awssdk/utils/builder/SdkBuilder;
      10: checkcast     #103                // class software/amazon/awssdk/services/route53recoverycontrolconfig/model/ListRoutingControlsRequest$Builder
      13: invokeinterface #104,  1          // InterfaceMethod software/amazon/awssdk/services/route53recoverycontrolconfig/model/ListRoutingControlsRequest$Builder.build:()Ljava/lang/Object;
      18: checkcast     #105                // class software/amazon/awssdk/services/route53recoverycontrolconfig/model/ListRoutingControlsRequest
      21: invokeinterface #107,  2          // InterfaceMethod listRoutingControlsPaginator:(Lsoftware/amazon/awssdk/services/route53recoverycontrolconfig/model/ListRoutingControlsRequest;)Lsoftware/amazon/awssdk/services/route53recoverycontrolconfig/paginators/ListRoutingControlsPublisher;
      26: areturn

  public default java.util.concurrent.CompletableFuture<software.amazon.awssdk.services.route53recoverycontrolconfig.model.ListSafetyRulesResponse> listSafetyRules(software.amazon.awssdk.services.route53recoverycontrolconfig.model.ListSafetyRulesRequest);
    Code:
       0: new           #6                  // class java/lang/UnsupportedOperationException
       3: dup
       4: invokespecial #7                  // Method java/lang/UnsupportedOperationException."<init>":()V
       7: athrow

  public default java.util.concurrent.CompletableFuture<software.amazon.awssdk.services.route53recoverycontrolconfig.model.ListSafetyRulesResponse> listSafetyRules(java.util.function.Consumer<software.amazon.awssdk.services.route53recoverycontrolconfig.model.ListSafetyRulesRequest$Builder>);
    Code:
       0: aload_0
       1: invokestatic  #108                // Method software/amazon/awssdk/services/route53recoverycontrolconfig/model/ListSafetyRulesRequest.builder:()Lsoftware/amazon/awssdk/services/route53recoverycontrolconfig/model/ListSafetyRulesRequest$Builder;
       4: aload_1
       5: invokeinterface #109,  2          // InterfaceMethod software/amazon/awssdk/services/route53recoverycontrolconfig/model/ListSafetyRulesRequest$Builder.applyMutation:(Ljava/util/function/Consumer;)Lsoftware/amazon/awssdk/utils/builder/SdkBuilder;
      10: checkcast     #110                // class software/amazon/awssdk/services/route53recoverycontrolconfig/model/ListSafetyRulesRequest$Builder
      13: invokeinterface #111,  1          // InterfaceMethod software/amazon/awssdk/services/route53recoverycontrolconfig/model/ListSafetyRulesRequest$Builder.build:()Ljava/lang/Object;
      18: checkcast     #112                // class software/amazon/awssdk/services/route53recoverycontrolconfig/model/ListSafetyRulesRequest
      21: invokeinterface #113,  2          // InterfaceMethod listSafetyRules:(Lsoftware/amazon/awssdk/services/route53recoverycontrolconfig/model/ListSafetyRulesRequest;)Ljava/util/concurrent/CompletableFuture;
      26: areturn

  public default software.amazon.awssdk.services.route53recoverycontrolconfig.paginators.ListSafetyRulesPublisher listSafetyRulesPaginator(software.amazon.awssdk.services.route53recoverycontrolconfig.model.ListSafetyRulesRequest);
    Code:
       0: new           #6                  // class java/lang/UnsupportedOperationException
       3: dup
       4: invokespecial #7                  // Method java/lang/UnsupportedOperationException."<init>":()V
       7: athrow

  public default software.amazon.awssdk.services.route53recoverycontrolconfig.paginators.ListSafetyRulesPublisher listSafetyRulesPaginator(java.util.function.Consumer<software.amazon.awssdk.services.route53recoverycontrolconfig.model.ListSafetyRulesRequest$Builder>);
    Code:
       0: aload_0
       1: invokestatic  #108                // Method software/amazon/awssdk/services/route53recoverycontrolconfig/model/ListSafetyRulesRequest.builder:()Lsoftware/amazon/awssdk/services/route53recoverycontrolconfig/model/ListSafetyRulesRequest$Builder;
       4: aload_1
       5: invokeinterface #109,  2          // InterfaceMethod software/amazon/awssdk/services/route53recoverycontrolconfig/model/ListSafetyRulesRequest$Builder.applyMutation:(Ljava/util/function/Consumer;)Lsoftware/amazon/awssdk/utils/builder/SdkBuilder;
      10: checkcast     #110                // class software/amazon/awssdk/services/route53recoverycontrolconfig/model/ListSafetyRulesRequest$Builder
      13: invokeinterface #111,  1          // InterfaceMethod software/amazon/awssdk/services/route53recoverycontrolconfig/model/ListSafetyRulesRequest$Builder.build:()Ljava/lang/Object;
      18: checkcast     #112                // class software/amazon/awssdk/services/route53recoverycontrolconfig/model/ListSafetyRulesRequest
      21: invokeinterface #114,  2          // InterfaceMethod listSafetyRulesPaginator:(Lsoftware/amazon/awssdk/services/route53recoverycontrolconfig/model/ListSafetyRulesRequest;)Lsoftware/amazon/awssdk/services/route53recoverycontrolconfig/paginators/ListSafetyRulesPublisher;
      26: areturn

  public default java.util.concurrent.CompletableFuture<software.amazon.awssdk.services.route53recoverycontrolconfig.model.UpdateControlPanelResponse> updateControlPanel(software.amazon.awssdk.services.route53recoverycontrolconfig.model.UpdateControlPanelRequest);
    Code:
       0: new           #6                  // class java/lang/UnsupportedOperationException
       3: dup
       4: invokespecial #7                  // Method java/lang/UnsupportedOperationException."<init>":()V
       7: athrow

  public default java.util.concurrent.CompletableFuture<software.amazon.awssdk.services.route53recoverycontrolconfig.model.UpdateControlPanelResponse> updateControlPanel(java.util.function.Consumer<software.amazon.awssdk.services.route53recoverycontrolconfig.model.UpdateControlPanelRequest$Builder>);
    Code:
       0: aload_0
       1: invokestatic  #115                // Method software/amazon/awssdk/services/route53recoverycontrolconfig/model/UpdateControlPanelRequest.builder:()Lsoftware/amazon/awssdk/services/route53recoverycontrolconfig/model/UpdateControlPanelRequest$Builder;
       4: aload_1
       5: invokeinterface #116,  2          // InterfaceMethod software/amazon/awssdk/services/route53recoverycontrolconfig/model/UpdateControlPanelRequest$Builder.applyMutation:(Ljava/util/function/Consumer;)Lsoftware/amazon/awssdk/utils/builder/SdkBuilder;
      10: checkcast     #117                // class software/amazon/awssdk/services/route53recoverycontrolconfig/model/UpdateControlPanelRequest$Builder
      13: invokeinterface #118,  1          // InterfaceMethod software/amazon/awssdk/services/route53recoverycontrolconfig/model/UpdateControlPanelRequest$Builder.build:()Ljava/lang/Object;
      18: checkcast     #119                // class software/amazon/awssdk/services/route53recoverycontrolconfig/model/UpdateControlPanelRequest
      21: invokeinterface #120,  2          // InterfaceMethod updateControlPanel:(Lsoftware/amazon/awssdk/services/route53recoverycontrolconfig/model/UpdateControlPanelRequest;)Ljava/util/concurrent/CompletableFuture;
      26: areturn

  public default java.util.concurrent.CompletableFuture<software.amazon.awssdk.services.route53recoverycontrolconfig.model.UpdateRoutingControlResponse> updateRoutingControl(software.amazon.awssdk.services.route53recoverycontrolconfig.model.UpdateRoutingControlRequest);
    Code:
       0: new           #6                  // class java/lang/UnsupportedOperationException
       3: dup
       4: invokespecial #7                  // Method java/lang/UnsupportedOperationException."<init>":()V
       7: athrow

  public default java.util.concurrent.CompletableFuture<software.amazon.awssdk.services.route53recoverycontrolconfig.model.UpdateRoutingControlResponse> updateRoutingControl(java.util.function.Consumer<software.amazon.awssdk.services.route53recoverycontrolconfig.model.UpdateRoutingControlRequest$Builder>);
    Code:
       0: aload_0
       1: invokestatic  #121                // Method software/amazon/awssdk/services/route53recoverycontrolconfig/model/UpdateRoutingControlRequest.builder:()Lsoftware/amazon/awssdk/services/route53recoverycontrolconfig/model/UpdateRoutingControlRequest$Builder;
       4: aload_1
       5: invokeinterface #122,  2          // InterfaceMethod software/amazon/awssdk/services/route53recoverycontrolconfig/model/UpdateRoutingControlRequest$Builder.applyMutation:(Ljava/util/function/Consumer;)Lsoftware/amazon/awssdk/utils/builder/SdkBuilder;
      10: checkcast     #123                // class software/amazon/awssdk/services/route53recoverycontrolconfig/model/UpdateRoutingControlRequest$Builder
      13: invokeinterface #124,  1          // InterfaceMethod software/amazon/awssdk/services/route53recoverycontrolconfig/model/UpdateRoutingControlRequest$Builder.build:()Ljava/lang/Object;
      18: checkcast     #125                // class software/amazon/awssdk/services/route53recoverycontrolconfig/model/UpdateRoutingControlRequest
      21: invokeinterface #126,  2          // InterfaceMethod updateRoutingControl:(Lsoftware/amazon/awssdk/services/route53recoverycontrolconfig/model/UpdateRoutingControlRequest;)Ljava/util/concurrent/CompletableFuture;
      26: areturn

  public default java.util.concurrent.CompletableFuture<software.amazon.awssdk.services.route53recoverycontrolconfig.model.UpdateSafetyRuleResponse> updateSafetyRule(software.amazon.awssdk.services.route53recoverycontrolconfig.model.UpdateSafetyRuleRequest);
    Code:
       0: new           #6                  // class java/lang/UnsupportedOperationException
       3: dup
       4: invokespecial #7                  // Method java/lang/UnsupportedOperationException."<init>":()V
       7: athrow

  public default java.util.concurrent.CompletableFuture<software.amazon.awssdk.services.route53recoverycontrolconfig.model.UpdateSafetyRuleResponse> updateSafetyRule(java.util.function.Consumer<software.amazon.awssdk.services.route53recoverycontrolconfig.model.UpdateSafetyRuleRequest$Builder>);
    Code:
       0: aload_0
       1: invokestatic  #127                // Method software/amazon/awssdk/services/route53recoverycontrolconfig/model/UpdateSafetyRuleRequest.builder:()Lsoftware/amazon/awssdk/services/route53recoverycontrolconfig/model/UpdateSafetyRuleRequest$Builder;
       4: aload_1
       5: invokeinterface #128,  2          // InterfaceMethod software/amazon/awssdk/services/route53recoverycontrolconfig/model/UpdateSafetyRuleRequest$Builder.applyMutation:(Ljava/util/function/Consumer;)Lsoftware/amazon/awssdk/utils/builder/SdkBuilder;
      10: checkcast     #129                // class software/amazon/awssdk/services/route53recoverycontrolconfig/model/UpdateSafetyRuleRequest$Builder
      13: invokeinterface #130,  1          // InterfaceMethod software/amazon/awssdk/services/route53recoverycontrolconfig/model/UpdateSafetyRuleRequest$Builder.build:()Ljava/lang/Object;
      18: checkcast     #131                // class software/amazon/awssdk/services/route53recoverycontrolconfig/model/UpdateSafetyRuleRequest
      21: invokeinterface #132,  2          // InterfaceMethod updateSafetyRule:(Lsoftware/amazon/awssdk/services/route53recoverycontrolconfig/model/UpdateSafetyRuleRequest;)Ljava/util/concurrent/CompletableFuture;
      26: areturn

  public default software.amazon.awssdk.services.route53recoverycontrolconfig.waiters.Route53RecoveryControlConfigAsyncWaiter waiter();
    Code:
       0: new           #6                  // class java/lang/UnsupportedOperationException
       3: dup
       4: invokespecial #7                  // Method java/lang/UnsupportedOperationException."<init>":()V
       7: athrow
}
