Compiled from "BasicIntegerNumberEncryptor.java"
public final class org.jasypt.util.numeric.BasicIntegerNumberEncryptor implements org.jasypt.util.numeric.IntegerNumberEncryptor {
  private final org.jasypt.encryption.pbe.StandardPBEBigIntegerEncryptor encryptor;

  public org.jasypt.util.numeric.BasicIntegerNumberEncryptor();
    Code:
       0: aload_0
       1: invokespecial #1                  // Method java/lang/Object."<init>":()V
       4: aload_0
       5: new           #2                  // class org/jasypt/encryption/pbe/StandardPBEBigIntegerEncryptor
       8: dup
       9: invokespecial #3                  // Method org/jasypt/encryption/pbe/StandardPBEBigIntegerEncryptor."<init>":()V
      12: putfield      #4                  // Field encryptor:Lorg/jasypt/encryption/pbe/StandardPBEBigIntegerEncryptor;
      15: aload_0
      16: getfield      #4                  // Field encryptor:Lorg/jasypt/encryption/pbe/StandardPBEBigIntegerEncryptor;
      19: ldc           #5                  // String PBEWithMD5AndDES
      21: invokevirtual #6                  // Method org/jasypt/encryption/pbe/StandardPBEBigIntegerEncryptor.setAlgorithm:(Ljava/lang/String;)V
      24: return

  public void setPassword(java.lang.String);
    Code:
       0: aload_0
       1: getfield      #4                  // Field encryptor:Lorg/jasypt/encryption/pbe/StandardPBEBigIntegerEncryptor;
       4: aload_1
       5: invokevirtual #7                  // Method org/jasypt/encryption/pbe/StandardPBEBigIntegerEncryptor.setPassword:(Ljava/lang/String;)V
       8: return

  public void setPasswordCharArray(char[]);
    Code:
       0: aload_0
       1: getfield      #4                  // Field encryptor:Lorg/jasypt/encryption/pbe/StandardPBEBigIntegerEncryptor;
       4: aload_1
       5: invokevirtual #8                  // Method org/jasypt/encryption/pbe/StandardPBEBigIntegerEncryptor.setPasswordCharArray:([C)V
       8: return

  public java.math.BigInteger encrypt(java.math.BigInteger);
    Code:
       0: aload_0
       1: getfield      #4                  // Field encryptor:Lorg/jasypt/encryption/pbe/StandardPBEBigIntegerEncryptor;
       4: aload_1
       5: invokevirtual #9                  // Method org/jasypt/encryption/pbe/StandardPBEBigIntegerEncryptor.encrypt:(Ljava/math/BigInteger;)Ljava/math/BigInteger;
       8: areturn

  public java.math.BigInteger decrypt(java.math.BigInteger);
    Code:
       0: aload_0
       1: getfield      #4                  // Field encryptor:Lorg/jasypt/encryption/pbe/StandardPBEBigIntegerEncryptor;
       4: aload_1
       5: invokevirtual #10                 // Method org/jasypt/encryption/pbe/StandardPBEBigIntegerEncryptor.decrypt:(Ljava/math/BigInteger;)Ljava/math/BigInteger;
       8: areturn
}
