Compiled from "ChainingResourceFilter.java"
public class org.opensaml.util.resource.ChainingResourceFilter implements org.opensaml.util.resource.ResourceFilter {
  private org.slf4j.Logger log;

  private java.util.List<org.opensaml.util.resource.ResourceFilter> resourceFilters;

  public org.opensaml.util.resource.ChainingResourceFilter(java.util.List<org.opensaml.util.resource.ResourceFilter>);
    Code:
       0: aload_0
       1: invokespecial #1                  // Method java/lang/Object."<init>":()V
       4: aload_0
       5: ldc_w         #2                  // class org/opensaml/util/resource/ChainingResourceFilter
       8: invokestatic  #3                  // Method org/slf4j/LoggerFactory.getLogger:(Ljava/lang/Class;)Lorg/slf4j/Logger;
      11: putfield      #4                  // Field log:Lorg/slf4j/Logger;
      14: aload_0
      15: aload_1
      16: putfield      #5                  // Field resourceFilters:Ljava/util/List;
      19: return

  public java.io.InputStream applyFilter(java.io.InputStream) throws org.opensaml.util.resource.ResourceException;
    Code:
       0: aload_0
       1: getfield      #5                  // Field resourceFilters:Ljava/util/List;
       4: ifnull        19
       7: aload_0
       8: getfield      #5                  // Field resourceFilters:Ljava/util/List;
      11: invokeinterface #6,  1            // InterfaceMethod java/util/List.isEmpty:()Z
      16: ifeq          32
      19: aload_0
      20: getfield      #4                  // Field log:Lorg/slf4j/Logger;
      23: ldc           #7                  // String No resource filters configured, nothing to do
      25: invokeinterface #8,  2            // InterfaceMethod org/slf4j/Logger.debug:(Ljava/lang/String;)V
      30: aload_1
      31: areturn
      32: aload_0
      33: getfield      #5                  // Field resourceFilters:Ljava/util/List;
      36: invokeinterface #9,  1            // InterfaceMethod java/util/List.iterator:()Ljava/util/Iterator;
      41: astore_2
      42: aload_2
      43: invokeinterface #10,  1           // InterfaceMethod java/util/Iterator.hasNext:()Z
      48: ifeq          90
      51: aload_2
      52: invokeinterface #11,  1           // InterfaceMethod java/util/Iterator.next:()Ljava/lang/Object;
      57: checkcast     #12                 // class org/opensaml/util/resource/ResourceFilter
      60: astore_3
      61: aload_0
      62: getfield      #4                  // Field log:Lorg/slf4j/Logger;
      65: ldc           #13                 // String Applying filter \'{}\'
      67: aload_3
      68: invokevirtual #14                 // Method java/lang/Object.getClass:()Ljava/lang/Class;
      71: invokevirtual #15                 // Method java/lang/Class.getName:()Ljava/lang/String;
      74: invokeinterface #16,  3           // InterfaceMethod org/slf4j/Logger.debug:(Ljava/lang/String;Ljava/lang/Object;)V
      79: aload_3
      80: aload_1
      81: invokeinterface #17,  2           // InterfaceMethod org/opensaml/util/resource/ResourceFilter.applyFilter:(Ljava/io/InputStream;)Ljava/io/InputStream;
      86: astore_1
      87: goto          42
      90: aload_1
      91: areturn
}
