Compiled from "CreateNodeFromTemplateJobRequest.java"
final class software.amazon.awssdk.services.panorama.model.CreateNodeFromTemplateJobRequest$BuilderImpl extends software.amazon.awssdk.services.panorama.model.PanoramaRequest$BuilderImpl implements software.amazon.awssdk.services.panorama.model.CreateNodeFromTemplateJobRequest$Builder {
  private java.util.List<software.amazon.awssdk.services.panorama.model.JobResourceTags> jobTags;

  private java.lang.String nodeDescription;

  private java.lang.String nodeName;

  private java.lang.String outputPackageName;

  private java.lang.String outputPackageVersion;

  private java.util.Map<java.lang.String, java.lang.String> templateParameters;

  private java.lang.String templateType;

  private software.amazon.awssdk.services.panorama.model.CreateNodeFromTemplateJobRequest$BuilderImpl();
    Code:
       0: aload_0
       1: invokespecial #10                 // Method software/amazon/awssdk/services/panorama/model/PanoramaRequest$BuilderImpl."<init>":()V
       4: aload_0
       5: invokestatic  #11                 // Method software/amazon/awssdk/core/util/DefaultSdkAutoConstructList.getInstance:()Lsoftware/amazon/awssdk/core/util/DefaultSdkAutoConstructList;
       8: putfield      #9                  // Field jobTags:Ljava/util/List;
      11: aload_0
      12: invokestatic  #12                 // Method software/amazon/awssdk/core/util/DefaultSdkAutoConstructMap.getInstance:()Lsoftware/amazon/awssdk/core/util/DefaultSdkAutoConstructMap;
      15: putfield      #4                  // Field templateParameters:Ljava/util/Map;
      18: return

  private software.amazon.awssdk.services.panorama.model.CreateNodeFromTemplateJobRequest$BuilderImpl(software.amazon.awssdk.services.panorama.model.CreateNodeFromTemplateJobRequest);
    Code:
       0: aload_0
       1: aload_1
       2: invokespecial #13                 // Method software/amazon/awssdk/services/panorama/model/PanoramaRequest$BuilderImpl."<init>":(Lsoftware/amazon/awssdk/services/panorama/model/PanoramaRequest;)V
       5: aload_0
       6: invokestatic  #11                 // Method software/amazon/awssdk/core/util/DefaultSdkAutoConstructList.getInstance:()Lsoftware/amazon/awssdk/core/util/DefaultSdkAutoConstructList;
       9: putfield      #9                  // Field jobTags:Ljava/util/List;
      12: aload_0
      13: invokestatic  #12                 // Method software/amazon/awssdk/core/util/DefaultSdkAutoConstructMap.getInstance:()Lsoftware/amazon/awssdk/core/util/DefaultSdkAutoConstructMap;
      16: putfield      #4                  // Field templateParameters:Ljava/util/Map;
      19: aload_0
      20: aload_1
      21: invokestatic  #14                 // Method software/amazon/awssdk/services/panorama/model/CreateNodeFromTemplateJobRequest.access$900:(Lsoftware/amazon/awssdk/services/panorama/model/CreateNodeFromTemplateJobRequest;)Ljava/util/List;
      24: invokevirtual #15                 // Method jobTags:(Ljava/util/Collection;)Lsoftware/amazon/awssdk/services/panorama/model/CreateNodeFromTemplateJobRequest$Builder;
      27: pop
      28: aload_0
      29: aload_1
      30: invokestatic  #16                 // Method software/amazon/awssdk/services/panorama/model/CreateNodeFromTemplateJobRequest.access$1000:(Lsoftware/amazon/awssdk/services/panorama/model/CreateNodeFromTemplateJobRequest;)Ljava/lang/String;
      33: invokevirtual #17                 // Method nodeDescription:(Ljava/lang/String;)Lsoftware/amazon/awssdk/services/panorama/model/CreateNodeFromTemplateJobRequest$Builder;
      36: pop
      37: aload_0
      38: aload_1
      39: invokestatic  #18                 // Method software/amazon/awssdk/services/panorama/model/CreateNodeFromTemplateJobRequest.access$1100:(Lsoftware/amazon/awssdk/services/panorama/model/CreateNodeFromTemplateJobRequest;)Ljava/lang/String;
      42: invokevirtual #19                 // Method nodeName:(Ljava/lang/String;)Lsoftware/amazon/awssdk/services/panorama/model/CreateNodeFromTemplateJobRequest$Builder;
      45: pop
      46: aload_0
      47: aload_1
      48: invokestatic  #20                 // Method software/amazon/awssdk/services/panorama/model/CreateNodeFromTemplateJobRequest.access$1200:(Lsoftware/amazon/awssdk/services/panorama/model/CreateNodeFromTemplateJobRequest;)Ljava/lang/String;
      51: invokevirtual #21                 // Method outputPackageName:(Ljava/lang/String;)Lsoftware/amazon/awssdk/services/panorama/model/CreateNodeFromTemplateJobRequest$Builder;
      54: pop
      55: aload_0
      56: aload_1
      57: invokestatic  #22                 // Method software/amazon/awssdk/services/panorama/model/CreateNodeFromTemplateJobRequest.access$1300:(Lsoftware/amazon/awssdk/services/panorama/model/CreateNodeFromTemplateJobRequest;)Ljava/lang/String;
      60: invokevirtual #23                 // Method outputPackageVersion:(Ljava/lang/String;)Lsoftware/amazon/awssdk/services/panorama/model/CreateNodeFromTemplateJobRequest$Builder;
      63: pop
      64: aload_0
      65: aload_1
      66: invokestatic  #24                 // Method software/amazon/awssdk/services/panorama/model/CreateNodeFromTemplateJobRequest.access$1400:(Lsoftware/amazon/awssdk/services/panorama/model/CreateNodeFromTemplateJobRequest;)Ljava/util/Map;
      69: invokevirtual #25                 // Method templateParameters:(Ljava/util/Map;)Lsoftware/amazon/awssdk/services/panorama/model/CreateNodeFromTemplateJobRequest$Builder;
      72: pop
      73: aload_0
      74: aload_1
      75: invokestatic  #26                 // Method software/amazon/awssdk/services/panorama/model/CreateNodeFromTemplateJobRequest.access$1500:(Lsoftware/amazon/awssdk/services/panorama/model/CreateNodeFromTemplateJobRequest;)Ljava/lang/String;
      78: invokevirtual #27                 // Method templateType:(Ljava/lang/String;)Lsoftware/amazon/awssdk/services/panorama/model/CreateNodeFromTemplateJobRequest$Builder;
      81: pop
      82: return

  public final java.util.List<software.amazon.awssdk.services.panorama.model.JobResourceTags$Builder> getJobTags();
    Code:
       0: aload_0
       1: getfield      #9                  // Field jobTags:Ljava/util/List;
       4: invokestatic  #28                 // Method software/amazon/awssdk/services/panorama/model/JobTagsListCopier.copyToBuilder:(Ljava/util/Collection;)Ljava/util/List;
       7: astore_1
       8: aload_1
       9: instanceof    #29                 // class software/amazon/awssdk/core/util/SdkAutoConstructList
      12: ifeq          17
      15: aconst_null
      16: areturn
      17: aload_1
      18: areturn

  public final void setJobTags(java.util.Collection<software.amazon.awssdk.services.panorama.model.JobResourceTags$BuilderImpl>);
    Code:
       0: aload_0
       1: aload_1
       2: invokestatic  #30                 // Method software/amazon/awssdk/services/panorama/model/JobTagsListCopier.copyFromBuilder:(Ljava/util/Collection;)Ljava/util/List;
       5: putfield      #9                  // Field jobTags:Ljava/util/List;
       8: return

  public final software.amazon.awssdk.services.panorama.model.CreateNodeFromTemplateJobRequest$Builder jobTags(java.util.Collection<software.amazon.awssdk.services.panorama.model.JobResourceTags>);
    Code:
       0: aload_0
       1: aload_1
       2: invokestatic  #31                 // Method software/amazon/awssdk/services/panorama/model/JobTagsListCopier.copy:(Ljava/util/Collection;)Ljava/util/List;
       5: putfield      #9                  // Field jobTags:Ljava/util/List;
       8: aload_0
       9: areturn

  public final software.amazon.awssdk.services.panorama.model.CreateNodeFromTemplateJobRequest$Builder jobTags(software.amazon.awssdk.services.panorama.model.JobResourceTags...);
    Code:
       0: aload_0
       1: aload_1
       2: invokestatic  #32                 // Method java/util/Arrays.asList:([Ljava/lang/Object;)Ljava/util/List;
       5: invokevirtual #15                 // Method jobTags:(Ljava/util/Collection;)Lsoftware/amazon/awssdk/services/panorama/model/CreateNodeFromTemplateJobRequest$Builder;
       8: pop
       9: aload_0
      10: areturn

  public final software.amazon.awssdk.services.panorama.model.CreateNodeFromTemplateJobRequest$Builder jobTags(java.util.function.Consumer<software.amazon.awssdk.services.panorama.model.JobResourceTags$Builder>...);
    Code:
       0: aload_0
       1: aload_1
       2: invokestatic  #33                 // InterfaceMethod java/util/stream/Stream.of:([Ljava/lang/Object;)Ljava/util/stream/Stream;
       5: invokedynamic #34,  0             // InvokeDynamic #0:apply:()Ljava/util/function/Function;
      10: invokeinterface #35,  2           // InterfaceMethod java/util/stream/Stream.map:(Ljava/util/function/Function;)Ljava/util/stream/Stream;
      15: invokestatic  #36                 // Method java/util/stream/Collectors.toList:()Ljava/util/stream/Collector;
      18: invokeinterface #37,  2           // InterfaceMethod java/util/stream/Stream.collect:(Ljava/util/stream/Collector;)Ljava/lang/Object;
      23: checkcast     #38                 // class java/util/Collection
      26: invokevirtual #15                 // Method jobTags:(Ljava/util/Collection;)Lsoftware/amazon/awssdk/services/panorama/model/CreateNodeFromTemplateJobRequest$Builder;
      29: pop
      30: aload_0
      31: areturn

  public final java.lang.String getNodeDescription();
    Code:
       0: aload_0
       1: getfield      #8                  // Field nodeDescription:Ljava/lang/String;
       4: areturn

  public final void setNodeDescription(java.lang.String);
    Code:
       0: aload_0
       1: aload_1
       2: putfield      #8                  // Field nodeDescription:Ljava/lang/String;
       5: return

  public final software.amazon.awssdk.services.panorama.model.CreateNodeFromTemplateJobRequest$Builder nodeDescription(java.lang.String);
    Code:
       0: aload_0
       1: aload_1
       2: putfield      #8                  // Field nodeDescription:Ljava/lang/String;
       5: aload_0
       6: areturn

  public final java.lang.String getNodeName();
    Code:
       0: aload_0
       1: getfield      #7                  // Field nodeName:Ljava/lang/String;
       4: areturn

  public final void setNodeName(java.lang.String);
    Code:
       0: aload_0
       1: aload_1
       2: putfield      #7                  // Field nodeName:Ljava/lang/String;
       5: return

  public final software.amazon.awssdk.services.panorama.model.CreateNodeFromTemplateJobRequest$Builder nodeName(java.lang.String);
    Code:
       0: aload_0
       1: aload_1
       2: putfield      #7                  // Field nodeName:Ljava/lang/String;
       5: aload_0
       6: areturn

  public final java.lang.String getOutputPackageName();
    Code:
       0: aload_0
       1: getfield      #6                  // Field outputPackageName:Ljava/lang/String;
       4: areturn

  public final void setOutputPackageName(java.lang.String);
    Code:
       0: aload_0
       1: aload_1
       2: putfield      #6                  // Field outputPackageName:Ljava/lang/String;
       5: return

  public final software.amazon.awssdk.services.panorama.model.CreateNodeFromTemplateJobRequest$Builder outputPackageName(java.lang.String);
    Code:
       0: aload_0
       1: aload_1
       2: putfield      #6                  // Field outputPackageName:Ljava/lang/String;
       5: aload_0
       6: areturn

  public final java.lang.String getOutputPackageVersion();
    Code:
       0: aload_0
       1: getfield      #5                  // Field outputPackageVersion:Ljava/lang/String;
       4: areturn

  public final void setOutputPackageVersion(java.lang.String);
    Code:
       0: aload_0
       1: aload_1
       2: putfield      #5                  // Field outputPackageVersion:Ljava/lang/String;
       5: return

  public final software.amazon.awssdk.services.panorama.model.CreateNodeFromTemplateJobRequest$Builder outputPackageVersion(java.lang.String);
    Code:
       0: aload_0
       1: aload_1
       2: putfield      #5                  // Field outputPackageVersion:Ljava/lang/String;
       5: aload_0
       6: areturn

  public final java.util.Map<java.lang.String, java.lang.String> getTemplateParameters();
    Code:
       0: aload_0
       1: getfield      #4                  // Field templateParameters:Ljava/util/Map;
       4: instanceof    #39                 // class software/amazon/awssdk/core/util/SdkAutoConstructMap
       7: ifeq          12
      10: aconst_null
      11: areturn
      12: aload_0
      13: getfield      #4                  // Field templateParameters:Ljava/util/Map;
      16: areturn

  public final void setTemplateParameters(java.util.Map<java.lang.String, java.lang.String>);
    Code:
       0: aload_0
       1: aload_1
       2: invokestatic  #40                 // Method software/amazon/awssdk/services/panorama/model/TemplateParametersMapCopier.copy:(Ljava/util/Map;)Ljava/util/Map;
       5: putfield      #4                  // Field templateParameters:Ljava/util/Map;
       8: return

  public final software.amazon.awssdk.services.panorama.model.CreateNodeFromTemplateJobRequest$Builder templateParameters(java.util.Map<java.lang.String, java.lang.String>);
    Code:
       0: aload_0
       1: aload_1
       2: invokestatic  #40                 // Method software/amazon/awssdk/services/panorama/model/TemplateParametersMapCopier.copy:(Ljava/util/Map;)Ljava/util/Map;
       5: putfield      #4                  // Field templateParameters:Ljava/util/Map;
       8: aload_0
       9: areturn

  public final java.lang.String getTemplateType();
    Code:
       0: aload_0
       1: getfield      #3                  // Field templateType:Ljava/lang/String;
       4: areturn

  public final void setTemplateType(java.lang.String);
    Code:
       0: aload_0
       1: aload_1
       2: putfield      #3                  // Field templateType:Ljava/lang/String;
       5: return

  public final software.amazon.awssdk.services.panorama.model.CreateNodeFromTemplateJobRequest$Builder templateType(java.lang.String);
    Code:
       0: aload_0
       1: aload_1
       2: putfield      #3                  // Field templateType:Ljava/lang/String;
       5: aload_0
       6: areturn

  public final software.amazon.awssdk.services.panorama.model.CreateNodeFromTemplateJobRequest$Builder templateType(software.amazon.awssdk.services.panorama.model.TemplateType);
    Code:
       0: aload_0
       1: aload_1
       2: ifnonnull     9
       5: aconst_null
       6: goto          13
       9: aload_1
      10: invokevirtual #41                 // Method software/amazon/awssdk/services/panorama/model/TemplateType.toString:()Ljava/lang/String;
      13: invokevirtual #27                 // Method templateType:(Ljava/lang/String;)Lsoftware/amazon/awssdk/services/panorama/model/CreateNodeFromTemplateJobRequest$Builder;
      16: pop
      17: aload_0
      18: areturn

  public software.amazon.awssdk.services.panorama.model.CreateNodeFromTemplateJobRequest$Builder overrideConfiguration(software.amazon.awssdk.awscore.AwsRequestOverrideConfiguration);
    Code:
       0: aload_0
       1: aload_1
       2: invokespecial #42                 // Method software/amazon/awssdk/services/panorama/model/PanoramaRequest$BuilderImpl.overrideConfiguration:(Lsoftware/amazon/awssdk/awscore/AwsRequestOverrideConfiguration;)Lsoftware/amazon/awssdk/awscore/AwsRequest$Builder;
       5: pop
       6: aload_0
       7: areturn

  public software.amazon.awssdk.services.panorama.model.CreateNodeFromTemplateJobRequest$Builder overrideConfiguration(java.util.function.Consumer<software.amazon.awssdk.awscore.AwsRequestOverrideConfiguration$Builder>);
    Code:
       0: aload_0
       1: aload_1
       2: invokespecial #43                 // Method software/amazon/awssdk/services/panorama/model/PanoramaRequest$BuilderImpl.overrideConfiguration:(Ljava/util/function/Consumer;)Lsoftware/amazon/awssdk/awscore/AwsRequest$Builder;
       5: pop
       6: aload_0
       7: areturn

  public software.amazon.awssdk.services.panorama.model.CreateNodeFromTemplateJobRequest build();
    Code:
       0: new           #44                 // class software/amazon/awssdk/services/panorama/model/CreateNodeFromTemplateJobRequest
       3: dup
       4: aload_0
       5: aconst_null
       6: invokespecial #45                 // Method software/amazon/awssdk/services/panorama/model/CreateNodeFromTemplateJobRequest."<init>":(Lsoftware/amazon/awssdk/services/panorama/model/CreateNodeFromTemplateJobRequest$BuilderImpl;Lsoftware/amazon/awssdk/services/panorama/model/CreateNodeFromTemplateJobRequest$1;)V
       9: areturn

  public java.util.List<software.amazon.awssdk.core.SdkField<?>> sdkFields();
    Code:
       0: invokestatic  #46                 // Method software/amazon/awssdk/services/panorama/model/CreateNodeFromTemplateJobRequest.access$1700:()Ljava/util/List;
       3: areturn

  public software.amazon.awssdk.services.panorama.model.PanoramaRequest build();
    Code:
       0: aload_0
       1: invokevirtual #47                 // Method build:()Lsoftware/amazon/awssdk/services/panorama/model/CreateNodeFromTemplateJobRequest;
       4: areturn

  public software.amazon.awssdk.awscore.AwsRequest build();
    Code:
       0: aload_0
       1: invokevirtual #47                 // Method build:()Lsoftware/amazon/awssdk/services/panorama/model/CreateNodeFromTemplateJobRequest;
       4: areturn

  public software.amazon.awssdk.awscore.AwsRequest$Builder overrideConfiguration(java.util.function.Consumer);
    Code:
       0: aload_0
       1: aload_1
       2: invokevirtual #48                 // Method overrideConfiguration:(Ljava/util/function/Consumer;)Lsoftware/amazon/awssdk/services/panorama/model/CreateNodeFromTemplateJobRequest$Builder;
       5: areturn

  public software.amazon.awssdk.awscore.AwsRequest$Builder overrideConfiguration(software.amazon.awssdk.awscore.AwsRequestOverrideConfiguration);
    Code:
       0: aload_0
       1: aload_1
       2: invokevirtual #49                 // Method overrideConfiguration:(Lsoftware/amazon/awssdk/awscore/AwsRequestOverrideConfiguration;)Lsoftware/amazon/awssdk/services/panorama/model/CreateNodeFromTemplateJobRequest$Builder;
       5: areturn

  public software.amazon.awssdk.core.SdkRequest build();
    Code:
       0: aload_0
       1: invokevirtual #47                 // Method build:()Lsoftware/amazon/awssdk/services/panorama/model/CreateNodeFromTemplateJobRequest;
       4: areturn

  public java.lang.Object build();
    Code:
       0: aload_0
       1: invokevirtual #47                 // Method build:()Lsoftware/amazon/awssdk/services/panorama/model/CreateNodeFromTemplateJobRequest;
       4: areturn

  private static software.amazon.awssdk.services.panorama.model.JobResourceTags lambda$jobTags$0(java.util.function.Consumer);
    Code:
       0: invokestatic  #50                 // Method software/amazon/awssdk/services/panorama/model/JobResourceTags.builder:()Lsoftware/amazon/awssdk/services/panorama/model/JobResourceTags$Builder;
       3: aload_0
       4: invokeinterface #51,  2           // InterfaceMethod software/amazon/awssdk/services/panorama/model/JobResourceTags$Builder.applyMutation:(Ljava/util/function/Consumer;)Lsoftware/amazon/awssdk/utils/builder/SdkBuilder;
       9: checkcast     #52                 // class software/amazon/awssdk/services/panorama/model/JobResourceTags$Builder
      12: invokeinterface #53,  1           // InterfaceMethod software/amazon/awssdk/services/panorama/model/JobResourceTags$Builder.build:()Ljava/lang/Object;
      17: checkcast     #54                 // class software/amazon/awssdk/services/panorama/model/JobResourceTags
      20: areturn

  static java.util.List access$000(software.amazon.awssdk.services.panorama.model.CreateNodeFromTemplateJobRequest$BuilderImpl);
    Code:
       0: aload_0
       1: getfield      #9                  // Field jobTags:Ljava/util/List;
       4: areturn

  static java.lang.String access$100(software.amazon.awssdk.services.panorama.model.CreateNodeFromTemplateJobRequest$BuilderImpl);
    Code:
       0: aload_0
       1: getfield      #8                  // Field nodeDescription:Ljava/lang/String;
       4: areturn

  static java.lang.String access$200(software.amazon.awssdk.services.panorama.model.CreateNodeFromTemplateJobRequest$BuilderImpl);
    Code:
       0: aload_0
       1: getfield      #7                  // Field nodeName:Ljava/lang/String;
       4: areturn

  static java.lang.String access$300(software.amazon.awssdk.services.panorama.model.CreateNodeFromTemplateJobRequest$BuilderImpl);
    Code:
       0: aload_0
       1: getfield      #6                  // Field outputPackageName:Ljava/lang/String;
       4: areturn

  static java.lang.String access$400(software.amazon.awssdk.services.panorama.model.CreateNodeFromTemplateJobRequest$BuilderImpl);
    Code:
       0: aload_0
       1: getfield      #5                  // Field outputPackageVersion:Ljava/lang/String;
       4: areturn

  static java.util.Map access$500(software.amazon.awssdk.services.panorama.model.CreateNodeFromTemplateJobRequest$BuilderImpl);
    Code:
       0: aload_0
       1: getfield      #4                  // Field templateParameters:Ljava/util/Map;
       4: areturn

  static java.lang.String access$600(software.amazon.awssdk.services.panorama.model.CreateNodeFromTemplateJobRequest$BuilderImpl);
    Code:
       0: aload_0
       1: getfield      #3                  // Field templateType:Ljava/lang/String;
       4: areturn

  software.amazon.awssdk.services.panorama.model.CreateNodeFromTemplateJobRequest$BuilderImpl(software.amazon.awssdk.services.panorama.model.CreateNodeFromTemplateJobRequest, software.amazon.awssdk.services.panorama.model.CreateNodeFromTemplateJobRequest$1);
    Code:
       0: aload_0
       1: aload_1
       2: invokespecial #2                  // Method "<init>":(Lsoftware/amazon/awssdk/services/panorama/model/CreateNodeFromTemplateJobRequest;)V
       5: return

  software.amazon.awssdk.services.panorama.model.CreateNodeFromTemplateJobRequest$BuilderImpl(software.amazon.awssdk.services.panorama.model.CreateNodeFromTemplateJobRequest$1);
    Code:
       0: aload_0
       1: invokespecial #1                  // Method "<init>":()V
       4: return
}
