Compiled from "DeletePackageRequest.java"
final class software.amazon.awssdk.services.panorama.model.DeletePackageRequest$BuilderImpl extends software.amazon.awssdk.services.panorama.model.PanoramaRequest$BuilderImpl implements software.amazon.awssdk.services.panorama.model.DeletePackageRequest$Builder {
  private java.lang.Boolean forceDelete;

  private java.lang.String packageId;

  private software.amazon.awssdk.services.panorama.model.DeletePackageRequest$BuilderImpl();
    Code:
       0: aload_0
       1: invokespecial #5                  // Method software/amazon/awssdk/services/panorama/model/PanoramaRequest$BuilderImpl."<init>":()V
       4: return

  private software.amazon.awssdk.services.panorama.model.DeletePackageRequest$BuilderImpl(software.amazon.awssdk.services.panorama.model.DeletePackageRequest);
    Code:
       0: aload_0
       1: aload_1
       2: invokespecial #6                  // Method software/amazon/awssdk/services/panorama/model/PanoramaRequest$BuilderImpl."<init>":(Lsoftware/amazon/awssdk/services/panorama/model/PanoramaRequest;)V
       5: aload_0
       6: aload_1
       7: invokestatic  #7                  // Method software/amazon/awssdk/services/panorama/model/DeletePackageRequest.access$400:(Lsoftware/amazon/awssdk/services/panorama/model/DeletePackageRequest;)Ljava/lang/Boolean;
      10: invokevirtual #8                  // Method forceDelete:(Ljava/lang/Boolean;)Lsoftware/amazon/awssdk/services/panorama/model/DeletePackageRequest$Builder;
      13: pop
      14: aload_0
      15: aload_1
      16: invokestatic  #9                  // Method software/amazon/awssdk/services/panorama/model/DeletePackageRequest.access$500:(Lsoftware/amazon/awssdk/services/panorama/model/DeletePackageRequest;)Ljava/lang/String;
      19: invokevirtual #10                 // Method packageId:(Ljava/lang/String;)Lsoftware/amazon/awssdk/services/panorama/model/DeletePackageRequest$Builder;
      22: pop
      23: return

  public final java.lang.Boolean getForceDelete();
    Code:
       0: aload_0
       1: getfield      #4                  // Field forceDelete:Ljava/lang/Boolean;
       4: areturn

  public final void setForceDelete(java.lang.Boolean);
    Code:
       0: aload_0
       1: aload_1
       2: putfield      #4                  // Field forceDelete:Ljava/lang/Boolean;
       5: return

  public final software.amazon.awssdk.services.panorama.model.DeletePackageRequest$Builder forceDelete(java.lang.Boolean);
    Code:
       0: aload_0
       1: aload_1
       2: putfield      #4                  // Field forceDelete:Ljava/lang/Boolean;
       5: aload_0
       6: areturn

  public final java.lang.String getPackageId();
    Code:
       0: aload_0
       1: getfield      #3                  // Field packageId:Ljava/lang/String;
       4: areturn

  public final void setPackageId(java.lang.String);
    Code:
       0: aload_0
       1: aload_1
       2: putfield      #3                  // Field packageId:Ljava/lang/String;
       5: return

  public final software.amazon.awssdk.services.panorama.model.DeletePackageRequest$Builder packageId(java.lang.String);
    Code:
       0: aload_0
       1: aload_1
       2: putfield      #3                  // Field packageId:Ljava/lang/String;
       5: aload_0
       6: areturn

  public software.amazon.awssdk.services.panorama.model.DeletePackageRequest$Builder overrideConfiguration(software.amazon.awssdk.awscore.AwsRequestOverrideConfiguration);
    Code:
       0: aload_0
       1: aload_1
       2: invokespecial #11                 // Method software/amazon/awssdk/services/panorama/model/PanoramaRequest$BuilderImpl.overrideConfiguration:(Lsoftware/amazon/awssdk/awscore/AwsRequestOverrideConfiguration;)Lsoftware/amazon/awssdk/awscore/AwsRequest$Builder;
       5: pop
       6: aload_0
       7: areturn

  public software.amazon.awssdk.services.panorama.model.DeletePackageRequest$Builder overrideConfiguration(java.util.function.Consumer<software.amazon.awssdk.awscore.AwsRequestOverrideConfiguration$Builder>);
    Code:
       0: aload_0
       1: aload_1
       2: invokespecial #12                 // Method software/amazon/awssdk/services/panorama/model/PanoramaRequest$BuilderImpl.overrideConfiguration:(Ljava/util/function/Consumer;)Lsoftware/amazon/awssdk/awscore/AwsRequest$Builder;
       5: pop
       6: aload_0
       7: areturn

  public software.amazon.awssdk.services.panorama.model.DeletePackageRequest build();
    Code:
       0: new           #13                 // class software/amazon/awssdk/services/panorama/model/DeletePackageRequest
       3: dup
       4: aload_0
       5: aconst_null
       6: invokespecial #14                 // Method software/amazon/awssdk/services/panorama/model/DeletePackageRequest."<init>":(Lsoftware/amazon/awssdk/services/panorama/model/DeletePackageRequest$BuilderImpl;Lsoftware/amazon/awssdk/services/panorama/model/DeletePackageRequest$1;)V
       9: areturn

  public java.util.List<software.amazon.awssdk.core.SdkField<?>> sdkFields();
    Code:
       0: invokestatic  #15                 // Method software/amazon/awssdk/services/panorama/model/DeletePackageRequest.access$700:()Ljava/util/List;
       3: areturn

  public software.amazon.awssdk.services.panorama.model.PanoramaRequest build();
    Code:
       0: aload_0
       1: invokevirtual #16                 // Method build:()Lsoftware/amazon/awssdk/services/panorama/model/DeletePackageRequest;
       4: areturn

  public software.amazon.awssdk.awscore.AwsRequest build();
    Code:
       0: aload_0
       1: invokevirtual #16                 // Method build:()Lsoftware/amazon/awssdk/services/panorama/model/DeletePackageRequest;
       4: areturn

  public software.amazon.awssdk.awscore.AwsRequest$Builder overrideConfiguration(java.util.function.Consumer);
    Code:
       0: aload_0
       1: aload_1
       2: invokevirtual #17                 // Method overrideConfiguration:(Ljava/util/function/Consumer;)Lsoftware/amazon/awssdk/services/panorama/model/DeletePackageRequest$Builder;
       5: areturn

  public software.amazon.awssdk.awscore.AwsRequest$Builder overrideConfiguration(software.amazon.awssdk.awscore.AwsRequestOverrideConfiguration);
    Code:
       0: aload_0
       1: aload_1
       2: invokevirtual #18                 // Method overrideConfiguration:(Lsoftware/amazon/awssdk/awscore/AwsRequestOverrideConfiguration;)Lsoftware/amazon/awssdk/services/panorama/model/DeletePackageRequest$Builder;
       5: areturn

  public software.amazon.awssdk.core.SdkRequest build();
    Code:
       0: aload_0
       1: invokevirtual #16                 // Method build:()Lsoftware/amazon/awssdk/services/panorama/model/DeletePackageRequest;
       4: areturn

  public java.lang.Object build();
    Code:
       0: aload_0
       1: invokevirtual #16                 // Method build:()Lsoftware/amazon/awssdk/services/panorama/model/DeletePackageRequest;
       4: areturn

  static java.lang.Boolean access$000(software.amazon.awssdk.services.panorama.model.DeletePackageRequest$BuilderImpl);
    Code:
       0: aload_0
       1: getfield      #4                  // Field forceDelete:Ljava/lang/Boolean;
       4: areturn

  static java.lang.String access$100(software.amazon.awssdk.services.panorama.model.DeletePackageRequest$BuilderImpl);
    Code:
       0: aload_0
       1: getfield      #3                  // Field packageId:Ljava/lang/String;
       4: areturn

  software.amazon.awssdk.services.panorama.model.DeletePackageRequest$BuilderImpl(software.amazon.awssdk.services.panorama.model.DeletePackageRequest, software.amazon.awssdk.services.panorama.model.DeletePackageRequest$1);
    Code:
       0: aload_0
       1: aload_1
       2: invokespecial #2                  // Method "<init>":(Lsoftware/amazon/awssdk/services/panorama/model/DeletePackageRequest;)V
       5: return

  software.amazon.awssdk.services.panorama.model.DeletePackageRequest$BuilderImpl(software.amazon.awssdk.services.panorama.model.DeletePackageRequest$1);
    Code:
       0: aload_0
       1: invokespecial #1                  // Method "<init>":()V
       4: return
}
