Compiled from "DeletePackageResponse.java"
final class software.amazon.awssdk.services.panorama.model.DeletePackageResponse$BuilderImpl extends software.amazon.awssdk.services.panorama.model.PanoramaResponse$BuilderImpl implements software.amazon.awssdk.services.panorama.model.DeletePackageResponse$Builder {
  private software.amazon.awssdk.services.panorama.model.DeletePackageResponse$BuilderImpl();
    Code:
       0: aload_0
       1: invokespecial #3                  // Method software/amazon/awssdk/services/panorama/model/PanoramaResponse$BuilderImpl."<init>":()V
       4: return

  private software.amazon.awssdk.services.panorama.model.DeletePackageResponse$BuilderImpl(software.amazon.awssdk.services.panorama.model.DeletePackageResponse);
    Code:
       0: aload_0
       1: aload_1
       2: invokespecial #4                  // Method software/amazon/awssdk/services/panorama/model/PanoramaResponse$BuilderImpl."<init>":(Lsoftware/amazon/awssdk/services/panorama/model/PanoramaResponse;)V
       5: return

  public software.amazon.awssdk.services.panorama.model.DeletePackageResponse build();
    Code:
       0: new           #5                  // class software/amazon/awssdk/services/panorama/model/DeletePackageResponse
       3: dup
       4: aload_0
       5: aconst_null
       6: invokespecial #6                  // Method software/amazon/awssdk/services/panorama/model/DeletePackageResponse."<init>":(Lsoftware/amazon/awssdk/services/panorama/model/DeletePackageResponse$BuilderImpl;Lsoftware/amazon/awssdk/services/panorama/model/DeletePackageResponse$1;)V
       9: areturn

  public java.util.List<software.amazon.awssdk.core.SdkField<?>> sdkFields();
    Code:
       0: invokestatic  #7                  // Method software/amazon/awssdk/services/panorama/model/DeletePackageResponse.access$300:()Ljava/util/List;
       3: areturn

  public software.amazon.awssdk.services.panorama.model.PanoramaResponse build();
    Code:
       0: aload_0
       1: invokevirtual #8                  // Method build:()Lsoftware/amazon/awssdk/services/panorama/model/DeletePackageResponse;
       4: areturn

  public software.amazon.awssdk.awscore.AwsResponse build();
    Code:
       0: aload_0
       1: invokevirtual #8                  // Method build:()Lsoftware/amazon/awssdk/services/panorama/model/DeletePackageResponse;
       4: areturn

  public software.amazon.awssdk.core.SdkResponse build();
    Code:
       0: aload_0
       1: invokevirtual #8                  // Method build:()Lsoftware/amazon/awssdk/services/panorama/model/DeletePackageResponse;
       4: areturn

  public java.lang.Object build();
    Code:
       0: aload_0
       1: invokevirtual #8                  // Method build:()Lsoftware/amazon/awssdk/services/panorama/model/DeletePackageResponse;
       4: areturn

  software.amazon.awssdk.services.panorama.model.DeletePackageResponse$BuilderImpl(software.amazon.awssdk.services.panorama.model.DeletePackageResponse, software.amazon.awssdk.services.panorama.model.DeletePackageResponse$1);
    Code:
       0: aload_0
       1: aload_1
       2: invokespecial #2                  // Method "<init>":(Lsoftware/amazon/awssdk/services/panorama/model/DeletePackageResponse;)V
       5: return

  software.amazon.awssdk.services.panorama.model.DeletePackageResponse$BuilderImpl(software.amazon.awssdk.services.panorama.model.DeletePackageResponse$1);
    Code:
       0: aload_0
       1: invokespecial #1                  // Method "<init>":()V
       4: return
}
