Compiled from "DescribeDeviceResponse.java"
public final class software.amazon.awssdk.services.panorama.model.DescribeDeviceResponse extends software.amazon.awssdk.services.panorama.model.PanoramaResponse implements software.amazon.awssdk.utils.builder.ToCopyableBuilder<software.amazon.awssdk.services.panorama.model.DescribeDeviceResponse$Builder, software.amazon.awssdk.services.panorama.model.DescribeDeviceResponse> {
  private static final software.amazon.awssdk.core.SdkField<java.util.List<software.amazon.awssdk.services.panorama.model.AlternateSoftwareMetadata>> ALTERNATE_SOFTWARES_FIELD;

  private static final software.amazon.awssdk.core.SdkField<java.lang.String> ARN_FIELD;

  private static final software.amazon.awssdk.core.SdkField<java.lang.String> BRAND_FIELD;

  private static final software.amazon.awssdk.core.SdkField<java.time.Instant> CREATED_TIME_FIELD;

  private static final software.amazon.awssdk.core.SdkField<software.amazon.awssdk.services.panorama.model.NetworkStatus> CURRENT_NETWORKING_STATUS_FIELD;

  private static final software.amazon.awssdk.core.SdkField<java.lang.String> CURRENT_SOFTWARE_FIELD;

  private static final software.amazon.awssdk.core.SdkField<java.lang.String> DESCRIPTION_FIELD;

  private static final software.amazon.awssdk.core.SdkField<java.lang.String> DEVICE_AGGREGATED_STATUS_FIELD;

  private static final software.amazon.awssdk.core.SdkField<java.lang.String> DEVICE_CONNECTION_STATUS_FIELD;

  private static final software.amazon.awssdk.core.SdkField<java.lang.String> DEVICE_ID_FIELD;

  private static final software.amazon.awssdk.core.SdkField<java.lang.String> LATEST_ALTERNATE_SOFTWARE_FIELD;

  private static final software.amazon.awssdk.core.SdkField<software.amazon.awssdk.services.panorama.model.LatestDeviceJob> LATEST_DEVICE_JOB_FIELD;

  private static final software.amazon.awssdk.core.SdkField<java.lang.String> LATEST_SOFTWARE_FIELD;

  private static final software.amazon.awssdk.core.SdkField<java.time.Instant> LEASE_EXPIRATION_TIME_FIELD;

  private static final software.amazon.awssdk.core.SdkField<java.lang.String> NAME_FIELD;

  private static final software.amazon.awssdk.core.SdkField<software.amazon.awssdk.services.panorama.model.NetworkPayload> NETWORKING_CONFIGURATION_FIELD;

  private static final software.amazon.awssdk.core.SdkField<java.lang.String> PROVISIONING_STATUS_FIELD;

  private static final software.amazon.awssdk.core.SdkField<java.lang.String> SERIAL_NUMBER_FIELD;

  private static final software.amazon.awssdk.core.SdkField<java.util.Map<java.lang.String, java.lang.String>> TAGS_FIELD;

  private static final software.amazon.awssdk.core.SdkField<java.lang.String> TYPE_FIELD;

  private static final java.util.List<software.amazon.awssdk.core.SdkField<?>> SDK_FIELDS;

  private final java.util.List<software.amazon.awssdk.services.panorama.model.AlternateSoftwareMetadata> alternateSoftwares;

  private final java.lang.String arn;

  private final java.lang.String brand;

  private final java.time.Instant createdTime;

  private final software.amazon.awssdk.services.panorama.model.NetworkStatus currentNetworkingStatus;

  private final java.lang.String currentSoftware;

  private final java.lang.String description;

  private final java.lang.String deviceAggregatedStatus;

  private final java.lang.String deviceConnectionStatus;

  private final java.lang.String deviceId;

  private final java.lang.String latestAlternateSoftware;

  private final software.amazon.awssdk.services.panorama.model.LatestDeviceJob latestDeviceJob;

  private final java.lang.String latestSoftware;

  private final java.time.Instant leaseExpirationTime;

  private final java.lang.String name;

  private final software.amazon.awssdk.services.panorama.model.NetworkPayload networkingConfiguration;

  private final java.lang.String provisioningStatus;

  private final java.lang.String serialNumber;

  private final java.util.Map<java.lang.String, java.lang.String> tags;

  private final java.lang.String type;

  private software.amazon.awssdk.services.panorama.model.DescribeDeviceResponse(software.amazon.awssdk.services.panorama.model.DescribeDeviceResponse$BuilderImpl);
    Code:
       0: aload_0
       1: aload_1
       2: invokespecial #23                 // Method software/amazon/awssdk/services/panorama/model/PanoramaResponse."<init>":(Lsoftware/amazon/awssdk/services/panorama/model/PanoramaResponse$Builder;)V
       5: aload_0
       6: aload_1
       7: invokestatic  #24                 // Method software/amazon/awssdk/services/panorama/model/DescribeDeviceResponse$BuilderImpl.access$000:(Lsoftware/amazon/awssdk/services/panorama/model/DescribeDeviceResponse$BuilderImpl;)Ljava/util/List;
      10: putfield      #22                 // Field alternateSoftwares:Ljava/util/List;
      13: aload_0
      14: aload_1
      15: invokestatic  #25                 // Method software/amazon/awssdk/services/panorama/model/DescribeDeviceResponse$BuilderImpl.access$100:(Lsoftware/amazon/awssdk/services/panorama/model/DescribeDeviceResponse$BuilderImpl;)Ljava/lang/String;
      18: putfield      #21                 // Field arn:Ljava/lang/String;
      21: aload_0
      22: aload_1
      23: invokestatic  #26                 // Method software/amazon/awssdk/services/panorama/model/DescribeDeviceResponse$BuilderImpl.access$200:(Lsoftware/amazon/awssdk/services/panorama/model/DescribeDeviceResponse$BuilderImpl;)Ljava/lang/String;
      26: putfield      #20                 // Field brand:Ljava/lang/String;
      29: aload_0
      30: aload_1
      31: invokestatic  #27                 // Method software/amazon/awssdk/services/panorama/model/DescribeDeviceResponse$BuilderImpl.access$300:(Lsoftware/amazon/awssdk/services/panorama/model/DescribeDeviceResponse$BuilderImpl;)Ljava/time/Instant;
      34: putfield      #19                 // Field createdTime:Ljava/time/Instant;
      37: aload_0
      38: aload_1
      39: invokestatic  #28                 // Method software/amazon/awssdk/services/panorama/model/DescribeDeviceResponse$BuilderImpl.access$400:(Lsoftware/amazon/awssdk/services/panorama/model/DescribeDeviceResponse$BuilderImpl;)Lsoftware/amazon/awssdk/services/panorama/model/NetworkStatus;
      42: putfield      #18                 // Field currentNetworkingStatus:Lsoftware/amazon/awssdk/services/panorama/model/NetworkStatus;
      45: aload_0
      46: aload_1
      47: invokestatic  #29                 // Method software/amazon/awssdk/services/panorama/model/DescribeDeviceResponse$BuilderImpl.access$500:(Lsoftware/amazon/awssdk/services/panorama/model/DescribeDeviceResponse$BuilderImpl;)Ljava/lang/String;
      50: putfield      #17                 // Field currentSoftware:Ljava/lang/String;
      53: aload_0
      54: aload_1
      55: invokestatic  #30                 // Method software/amazon/awssdk/services/panorama/model/DescribeDeviceResponse$BuilderImpl.access$600:(Lsoftware/amazon/awssdk/services/panorama/model/DescribeDeviceResponse$BuilderImpl;)Ljava/lang/String;
      58: putfield      #16                 // Field description:Ljava/lang/String;
      61: aload_0
      62: aload_1
      63: invokestatic  #31                 // Method software/amazon/awssdk/services/panorama/model/DescribeDeviceResponse$BuilderImpl.access$700:(Lsoftware/amazon/awssdk/services/panorama/model/DescribeDeviceResponse$BuilderImpl;)Ljava/lang/String;
      66: putfield      #15                 // Field deviceAggregatedStatus:Ljava/lang/String;
      69: aload_0
      70: aload_1
      71: invokestatic  #32                 // Method software/amazon/awssdk/services/panorama/model/DescribeDeviceResponse$BuilderImpl.access$800:(Lsoftware/amazon/awssdk/services/panorama/model/DescribeDeviceResponse$BuilderImpl;)Ljava/lang/String;
      74: putfield      #14                 // Field deviceConnectionStatus:Ljava/lang/String;
      77: aload_0
      78: aload_1
      79: invokestatic  #33                 // Method software/amazon/awssdk/services/panorama/model/DescribeDeviceResponse$BuilderImpl.access$900:(Lsoftware/amazon/awssdk/services/panorama/model/DescribeDeviceResponse$BuilderImpl;)Ljava/lang/String;
      82: putfield      #13                 // Field deviceId:Ljava/lang/String;
      85: aload_0
      86: aload_1
      87: invokestatic  #34                 // Method software/amazon/awssdk/services/panorama/model/DescribeDeviceResponse$BuilderImpl.access$1000:(Lsoftware/amazon/awssdk/services/panorama/model/DescribeDeviceResponse$BuilderImpl;)Ljava/lang/String;
      90: putfield      #12                 // Field latestAlternateSoftware:Ljava/lang/String;
      93: aload_0
      94: aload_1
      95: invokestatic  #35                 // Method software/amazon/awssdk/services/panorama/model/DescribeDeviceResponse$BuilderImpl.access$1100:(Lsoftware/amazon/awssdk/services/panorama/model/DescribeDeviceResponse$BuilderImpl;)Lsoftware/amazon/awssdk/services/panorama/model/LatestDeviceJob;
      98: putfield      #11                 // Field latestDeviceJob:Lsoftware/amazon/awssdk/services/panorama/model/LatestDeviceJob;
     101: aload_0
     102: aload_1
     103: invokestatic  #36                 // Method software/amazon/awssdk/services/panorama/model/DescribeDeviceResponse$BuilderImpl.access$1200:(Lsoftware/amazon/awssdk/services/panorama/model/DescribeDeviceResponse$BuilderImpl;)Ljava/lang/String;
     106: putfield      #10                 // Field latestSoftware:Ljava/lang/String;
     109: aload_0
     110: aload_1
     111: invokestatic  #37                 // Method software/amazon/awssdk/services/panorama/model/DescribeDeviceResponse$BuilderImpl.access$1300:(Lsoftware/amazon/awssdk/services/panorama/model/DescribeDeviceResponse$BuilderImpl;)Ljava/time/Instant;
     114: putfield      #9                  // Field leaseExpirationTime:Ljava/time/Instant;
     117: aload_0
     118: aload_1
     119: invokestatic  #38                 // Method software/amazon/awssdk/services/panorama/model/DescribeDeviceResponse$BuilderImpl.access$1400:(Lsoftware/amazon/awssdk/services/panorama/model/DescribeDeviceResponse$BuilderImpl;)Ljava/lang/String;
     122: putfield      #8                  // Field name:Ljava/lang/String;
     125: aload_0
     126: aload_1
     127: invokestatic  #39                 // Method software/amazon/awssdk/services/panorama/model/DescribeDeviceResponse$BuilderImpl.access$1500:(Lsoftware/amazon/awssdk/services/panorama/model/DescribeDeviceResponse$BuilderImpl;)Lsoftware/amazon/awssdk/services/panorama/model/NetworkPayload;
     130: putfield      #7                  // Field networkingConfiguration:Lsoftware/amazon/awssdk/services/panorama/model/NetworkPayload;
     133: aload_0
     134: aload_1
     135: invokestatic  #40                 // Method software/amazon/awssdk/services/panorama/model/DescribeDeviceResponse$BuilderImpl.access$1600:(Lsoftware/amazon/awssdk/services/panorama/model/DescribeDeviceResponse$BuilderImpl;)Ljava/lang/String;
     138: putfield      #6                  // Field provisioningStatus:Ljava/lang/String;
     141: aload_0
     142: aload_1
     143: invokestatic  #41                 // Method software/amazon/awssdk/services/panorama/model/DescribeDeviceResponse$BuilderImpl.access$1700:(Lsoftware/amazon/awssdk/services/panorama/model/DescribeDeviceResponse$BuilderImpl;)Ljava/lang/String;
     146: putfield      #5                  // Field serialNumber:Ljava/lang/String;
     149: aload_0
     150: aload_1
     151: invokestatic  #42                 // Method software/amazon/awssdk/services/panorama/model/DescribeDeviceResponse$BuilderImpl.access$1800:(Lsoftware/amazon/awssdk/services/panorama/model/DescribeDeviceResponse$BuilderImpl;)Ljava/util/Map;
     154: putfield      #4                  // Field tags:Ljava/util/Map;
     157: aload_0
     158: aload_1
     159: invokestatic  #43                 // Method software/amazon/awssdk/services/panorama/model/DescribeDeviceResponse$BuilderImpl.access$1900:(Lsoftware/amazon/awssdk/services/panorama/model/DescribeDeviceResponse$BuilderImpl;)Ljava/lang/String;
     162: putfield      #3                  // Field type:Ljava/lang/String;
     165: return

  public final boolean hasAlternateSoftwares();
    Code:
       0: aload_0
       1: getfield      #22                 // Field alternateSoftwares:Ljava/util/List;
       4: ifnull        21
       7: aload_0
       8: getfield      #22                 // Field alternateSoftwares:Ljava/util/List;
      11: instanceof    #44                 // class software/amazon/awssdk/core/util/SdkAutoConstructList
      14: ifne          21
      17: iconst_1
      18: goto          22
      21: iconst_0
      22: ireturn

  public final java.util.List<software.amazon.awssdk.services.panorama.model.AlternateSoftwareMetadata> alternateSoftwares();
    Code:
       0: aload_0
       1: getfield      #22                 // Field alternateSoftwares:Ljava/util/List;
       4: areturn

  public final java.lang.String arn();
    Code:
       0: aload_0
       1: getfield      #21                 // Field arn:Ljava/lang/String;
       4: areturn

  public final software.amazon.awssdk.services.panorama.model.DeviceBrand brand();
    Code:
       0: aload_0
       1: getfield      #20                 // Field brand:Ljava/lang/String;
       4: invokestatic  #45                 // Method software/amazon/awssdk/services/panorama/model/DeviceBrand.fromValue:(Ljava/lang/String;)Lsoftware/amazon/awssdk/services/panorama/model/DeviceBrand;
       7: areturn

  public final java.lang.String brandAsString();
    Code:
       0: aload_0
       1: getfield      #20                 // Field brand:Ljava/lang/String;
       4: areturn

  public final java.time.Instant createdTime();
    Code:
       0: aload_0
       1: getfield      #19                 // Field createdTime:Ljava/time/Instant;
       4: areturn

  public final software.amazon.awssdk.services.panorama.model.NetworkStatus currentNetworkingStatus();
    Code:
       0: aload_0
       1: getfield      #18                 // Field currentNetworkingStatus:Lsoftware/amazon/awssdk/services/panorama/model/NetworkStatus;
       4: areturn

  public final java.lang.String currentSoftware();
    Code:
       0: aload_0
       1: getfield      #17                 // Field currentSoftware:Ljava/lang/String;
       4: areturn

  public final java.lang.String description();
    Code:
       0: aload_0
       1: getfield      #16                 // Field description:Ljava/lang/String;
       4: areturn

  public final software.amazon.awssdk.services.panorama.model.DeviceAggregatedStatus deviceAggregatedStatus();
    Code:
       0: aload_0
       1: getfield      #15                 // Field deviceAggregatedStatus:Ljava/lang/String;
       4: invokestatic  #46                 // Method software/amazon/awssdk/services/panorama/model/DeviceAggregatedStatus.fromValue:(Ljava/lang/String;)Lsoftware/amazon/awssdk/services/panorama/model/DeviceAggregatedStatus;
       7: areturn

  public final java.lang.String deviceAggregatedStatusAsString();
    Code:
       0: aload_0
       1: getfield      #15                 // Field deviceAggregatedStatus:Ljava/lang/String;
       4: areturn

  public final software.amazon.awssdk.services.panorama.model.DeviceConnectionStatus deviceConnectionStatus();
    Code:
       0: aload_0
       1: getfield      #14                 // Field deviceConnectionStatus:Ljava/lang/String;
       4: invokestatic  #47                 // Method software/amazon/awssdk/services/panorama/model/DeviceConnectionStatus.fromValue:(Ljava/lang/String;)Lsoftware/amazon/awssdk/services/panorama/model/DeviceConnectionStatus;
       7: areturn

  public final java.lang.String deviceConnectionStatusAsString();
    Code:
       0: aload_0
       1: getfield      #14                 // Field deviceConnectionStatus:Ljava/lang/String;
       4: areturn

  public final java.lang.String deviceId();
    Code:
       0: aload_0
       1: getfield      #13                 // Field deviceId:Ljava/lang/String;
       4: areturn

  public final java.lang.String latestAlternateSoftware();
    Code:
       0: aload_0
       1: getfield      #12                 // Field latestAlternateSoftware:Ljava/lang/String;
       4: areturn

  public final software.amazon.awssdk.services.panorama.model.LatestDeviceJob latestDeviceJob();
    Code:
       0: aload_0
       1: getfield      #11                 // Field latestDeviceJob:Lsoftware/amazon/awssdk/services/panorama/model/LatestDeviceJob;
       4: areturn

  public final java.lang.String latestSoftware();
    Code:
       0: aload_0
       1: getfield      #10                 // Field latestSoftware:Ljava/lang/String;
       4: areturn

  public final java.time.Instant leaseExpirationTime();
    Code:
       0: aload_0
       1: getfield      #9                  // Field leaseExpirationTime:Ljava/time/Instant;
       4: areturn

  public final java.lang.String name();
    Code:
       0: aload_0
       1: getfield      #8                  // Field name:Ljava/lang/String;
       4: areturn

  public final software.amazon.awssdk.services.panorama.model.NetworkPayload networkingConfiguration();
    Code:
       0: aload_0
       1: getfield      #7                  // Field networkingConfiguration:Lsoftware/amazon/awssdk/services/panorama/model/NetworkPayload;
       4: areturn

  public final software.amazon.awssdk.services.panorama.model.DeviceStatus provisioningStatus();
    Code:
       0: aload_0
       1: getfield      #6                  // Field provisioningStatus:Ljava/lang/String;
       4: invokestatic  #48                 // Method software/amazon/awssdk/services/panorama/model/DeviceStatus.fromValue:(Ljava/lang/String;)Lsoftware/amazon/awssdk/services/panorama/model/DeviceStatus;
       7: areturn

  public final java.lang.String provisioningStatusAsString();
    Code:
       0: aload_0
       1: getfield      #6                  // Field provisioningStatus:Ljava/lang/String;
       4: areturn

  public final java.lang.String serialNumber();
    Code:
       0: aload_0
       1: getfield      #5                  // Field serialNumber:Ljava/lang/String;
       4: areturn

  public final boolean hasTags();
    Code:
       0: aload_0
       1: getfield      #4                  // Field tags:Ljava/util/Map;
       4: ifnull        21
       7: aload_0
       8: getfield      #4                  // Field tags:Ljava/util/Map;
      11: instanceof    #49                 // class software/amazon/awssdk/core/util/SdkAutoConstructMap
      14: ifne          21
      17: iconst_1
      18: goto          22
      21: iconst_0
      22: ireturn

  public final java.util.Map<java.lang.String, java.lang.String> tags();
    Code:
       0: aload_0
       1: getfield      #4                  // Field tags:Ljava/util/Map;
       4: areturn

  public final software.amazon.awssdk.services.panorama.model.DeviceType type();
    Code:
       0: aload_0
       1: getfield      #3                  // Field type:Ljava/lang/String;
       4: invokestatic  #50                 // Method software/amazon/awssdk/services/panorama/model/DeviceType.fromValue:(Ljava/lang/String;)Lsoftware/amazon/awssdk/services/panorama/model/DeviceType;
       7: areturn

  public final java.lang.String typeAsString();
    Code:
       0: aload_0
       1: getfield      #3                  // Field type:Ljava/lang/String;
       4: areturn

  public software.amazon.awssdk.services.panorama.model.DescribeDeviceResponse$Builder toBuilder();
    Code:
       0: new           #51                 // class software/amazon/awssdk/services/panorama/model/DescribeDeviceResponse$BuilderImpl
       3: dup
       4: aload_0
       5: aconst_null
       6: invokespecial #52                 // Method software/amazon/awssdk/services/panorama/model/DescribeDeviceResponse$BuilderImpl."<init>":(Lsoftware/amazon/awssdk/services/panorama/model/DescribeDeviceResponse;Lsoftware/amazon/awssdk/services/panorama/model/DescribeDeviceResponse$1;)V
       9: areturn

  public static software.amazon.awssdk.services.panorama.model.DescribeDeviceResponse$Builder builder();
    Code:
       0: new           #51                 // class software/amazon/awssdk/services/panorama/model/DescribeDeviceResponse$BuilderImpl
       3: dup
       4: aconst_null
       5: invokespecial #53                 // Method software/amazon/awssdk/services/panorama/model/DescribeDeviceResponse$BuilderImpl."<init>":(Lsoftware/amazon/awssdk/services/panorama/model/DescribeDeviceResponse$1;)V
       8: areturn

  public static java.lang.Class<? extends software.amazon.awssdk.services.panorama.model.DescribeDeviceResponse$Builder> serializableBuilderClass();
    Code:
       0: ldc           #51                 // class software/amazon/awssdk/services/panorama/model/DescribeDeviceResponse$BuilderImpl
       2: areturn

  public final int hashCode();
    Code:
       0: iconst_1
       1: istore_1
       2: bipush        31
       4: iload_1
       5: imul
       6: aload_0
       7: invokespecial #54                 // Method software/amazon/awssdk/services/panorama/model/PanoramaResponse.hashCode:()I
      10: iadd
      11: istore_1
      12: bipush        31
      14: iload_1
      15: imul
      16: aload_0
      17: invokevirtual #55                 // Method hasAlternateSoftwares:()Z
      20: ifeq          30
      23: aload_0
      24: invokevirtual #56                 // Method alternateSoftwares:()Ljava/util/List;
      27: goto          31
      30: aconst_null
      31: invokestatic  #57                 // Method java/util/Objects.hashCode:(Ljava/lang/Object;)I
      34: iadd
      35: istore_1
      36: bipush        31
      38: iload_1
      39: imul
      40: aload_0
      41: invokevirtual #58                 // Method arn:()Ljava/lang/String;
      44: invokestatic  #57                 // Method java/util/Objects.hashCode:(Ljava/lang/Object;)I
      47: iadd
      48: istore_1
      49: bipush        31
      51: iload_1
      52: imul
      53: aload_0
      54: invokevirtual #59                 // Method brandAsString:()Ljava/lang/String;
      57: invokestatic  #57                 // Method java/util/Objects.hashCode:(Ljava/lang/Object;)I
      60: iadd
      61: istore_1
      62: bipush        31
      64: iload_1
      65: imul
      66: aload_0
      67: invokevirtual #60                 // Method createdTime:()Ljava/time/Instant;
      70: invokestatic  #57                 // Method java/util/Objects.hashCode:(Ljava/lang/Object;)I
      73: iadd
      74: istore_1
      75: bipush        31
      77: iload_1
      78: imul
      79: aload_0
      80: invokevirtual #61                 // Method currentNetworkingStatus:()Lsoftware/amazon/awssdk/services/panorama/model/NetworkStatus;
      83: invokestatic  #57                 // Method java/util/Objects.hashCode:(Ljava/lang/Object;)I
      86: iadd
      87: istore_1
      88: bipush        31
      90: iload_1
      91: imul
      92: aload_0
      93: invokevirtual #62                 // Method currentSoftware:()Ljava/lang/String;
      96: invokestatic  #57                 // Method java/util/Objects.hashCode:(Ljava/lang/Object;)I
      99: iadd
     100: istore_1
     101: bipush        31
     103: iload_1
     104: imul
     105: aload_0
     106: invokevirtual #63                 // Method description:()Ljava/lang/String;
     109: invokestatic  #57                 // Method java/util/Objects.hashCode:(Ljava/lang/Object;)I
     112: iadd
     113: istore_1
     114: bipush        31
     116: iload_1
     117: imul
     118: aload_0
     119: invokevirtual #64                 // Method deviceAggregatedStatusAsString:()Ljava/lang/String;
     122: invokestatic  #57                 // Method java/util/Objects.hashCode:(Ljava/lang/Object;)I
     125: iadd
     126: istore_1
     127: bipush        31
     129: iload_1
     130: imul
     131: aload_0
     132: invokevirtual #65                 // Method deviceConnectionStatusAsString:()Ljava/lang/String;
     135: invokestatic  #57                 // Method java/util/Objects.hashCode:(Ljava/lang/Object;)I
     138: iadd
     139: istore_1
     140: bipush        31
     142: iload_1
     143: imul
     144: aload_0
     145: invokevirtual #66                 // Method deviceId:()Ljava/lang/String;
     148: invokestatic  #57                 // Method java/util/Objects.hashCode:(Ljava/lang/Object;)I
     151: iadd
     152: istore_1
     153: bipush        31
     155: iload_1
     156: imul
     157: aload_0
     158: invokevirtual #67                 // Method latestAlternateSoftware:()Ljava/lang/String;
     161: invokestatic  #57                 // Method java/util/Objects.hashCode:(Ljava/lang/Object;)I
     164: iadd
     165: istore_1
     166: bipush        31
     168: iload_1
     169: imul
     170: aload_0
     171: invokevirtual #68                 // Method latestDeviceJob:()Lsoftware/amazon/awssdk/services/panorama/model/LatestDeviceJob;
     174: invokestatic  #57                 // Method java/util/Objects.hashCode:(Ljava/lang/Object;)I
     177: iadd
     178: istore_1
     179: bipush        31
     181: iload_1
     182: imul
     183: aload_0
     184: invokevirtual #69                 // Method latestSoftware:()Ljava/lang/String;
     187: invokestatic  #57                 // Method java/util/Objects.hashCode:(Ljava/lang/Object;)I
     190: iadd
     191: istore_1
     192: bipush        31
     194: iload_1
     195: imul
     196: aload_0
     197: invokevirtual #70                 // Method leaseExpirationTime:()Ljava/time/Instant;
     200: invokestatic  #57                 // Method java/util/Objects.hashCode:(Ljava/lang/Object;)I
     203: iadd
     204: istore_1
     205: bipush        31
     207: iload_1
     208: imul
     209: aload_0
     210: invokevirtual #71                 // Method name:()Ljava/lang/String;
     213: invokestatic  #57                 // Method java/util/Objects.hashCode:(Ljava/lang/Object;)I
     216: iadd
     217: istore_1
     218: bipush        31
     220: iload_1
     221: imul
     222: aload_0
     223: invokevirtual #72                 // Method networkingConfiguration:()Lsoftware/amazon/awssdk/services/panorama/model/NetworkPayload;
     226: invokestatic  #57                 // Method java/util/Objects.hashCode:(Ljava/lang/Object;)I
     229: iadd
     230: istore_1
     231: bipush        31
     233: iload_1
     234: imul
     235: aload_0
     236: invokevirtual #73                 // Method provisioningStatusAsString:()Ljava/lang/String;
     239: invokestatic  #57                 // Method java/util/Objects.hashCode:(Ljava/lang/Object;)I
     242: iadd
     243: istore_1
     244: bipush        31
     246: iload_1
     247: imul
     248: aload_0
     249: invokevirtual #74                 // Method serialNumber:()Ljava/lang/String;
     252: invokestatic  #57                 // Method java/util/Objects.hashCode:(Ljava/lang/Object;)I
     255: iadd
     256: istore_1
     257: bipush        31
     259: iload_1
     260: imul
     261: aload_0
     262: invokevirtual #75                 // Method hasTags:()Z
     265: ifeq          275
     268: aload_0
     269: invokevirtual #76                 // Method tags:()Ljava/util/Map;
     272: goto          276
     275: aconst_null
     276: invokestatic  #57                 // Method java/util/Objects.hashCode:(Ljava/lang/Object;)I
     279: iadd
     280: istore_1
     281: bipush        31
     283: iload_1
     284: imul
     285: aload_0
     286: invokevirtual #77                 // Method typeAsString:()Ljava/lang/String;
     289: invokestatic  #57                 // Method java/util/Objects.hashCode:(Ljava/lang/Object;)I
     292: iadd
     293: istore_1
     294: iload_1
     295: ireturn

  public final boolean equals(java.lang.Object);
    Code:
       0: aload_0
       1: aload_1
       2: invokespecial #78                 // Method software/amazon/awssdk/services/panorama/model/PanoramaResponse.equals:(Ljava/lang/Object;)Z
       5: ifeq          20
       8: aload_0
       9: aload_1
      10: invokevirtual #79                 // Method equalsBySdkFields:(Ljava/lang/Object;)Z
      13: ifeq          20
      16: iconst_1
      17: goto          21
      20: iconst_0
      21: ireturn

  public final boolean equalsBySdkFields(java.lang.Object);
    Code:
       0: aload_0
       1: aload_1
       2: if_acmpne     7
       5: iconst_1
       6: ireturn
       7: aload_1
       8: ifnonnull     13
      11: iconst_0
      12: ireturn
      13: aload_1
      14: instanceof    #80                 // class software/amazon/awssdk/services/panorama/model/DescribeDeviceResponse
      17: ifne          22
      20: iconst_0
      21: ireturn
      22: aload_1
      23: checkcast     #80                 // class software/amazon/awssdk/services/panorama/model/DescribeDeviceResponse
      26: astore_2
      27: aload_0
      28: invokevirtual #55                 // Method hasAlternateSoftwares:()Z
      31: aload_2
      32: invokevirtual #55                 // Method hasAlternateSoftwares:()Z
      35: if_icmpne     333
      38: aload_0
      39: invokevirtual #56                 // Method alternateSoftwares:()Ljava/util/List;
      42: aload_2
      43: invokevirtual #56                 // Method alternateSoftwares:()Ljava/util/List;
      46: invokestatic  #81                 // Method java/util/Objects.equals:(Ljava/lang/Object;Ljava/lang/Object;)Z
      49: ifeq          333
      52: aload_0
      53: invokevirtual #58                 // Method arn:()Ljava/lang/String;
      56: aload_2
      57: invokevirtual #58                 // Method arn:()Ljava/lang/String;
      60: invokestatic  #81                 // Method java/util/Objects.equals:(Ljava/lang/Object;Ljava/lang/Object;)Z
      63: ifeq          333
      66: aload_0
      67: invokevirtual #59                 // Method brandAsString:()Ljava/lang/String;
      70: aload_2
      71: invokevirtual #59                 // Method brandAsString:()Ljava/lang/String;
      74: invokestatic  #81                 // Method java/util/Objects.equals:(Ljava/lang/Object;Ljava/lang/Object;)Z
      77: ifeq          333
      80: aload_0
      81: invokevirtual #60                 // Method createdTime:()Ljava/time/Instant;
      84: aload_2
      85: invokevirtual #60                 // Method createdTime:()Ljava/time/Instant;
      88: invokestatic  #81                 // Method java/util/Objects.equals:(Ljava/lang/Object;Ljava/lang/Object;)Z
      91: ifeq          333
      94: aload_0
      95: invokevirtual #61                 // Method currentNetworkingStatus:()Lsoftware/amazon/awssdk/services/panorama/model/NetworkStatus;
      98: aload_2
      99: invokevirtual #61                 // Method currentNetworkingStatus:()Lsoftware/amazon/awssdk/services/panorama/model/NetworkStatus;
     102: invokestatic  #81                 // Method java/util/Objects.equals:(Ljava/lang/Object;Ljava/lang/Object;)Z
     105: ifeq          333
     108: aload_0
     109: invokevirtual #62                 // Method currentSoftware:()Ljava/lang/String;
     112: aload_2
     113: invokevirtual #62                 // Method currentSoftware:()Ljava/lang/String;
     116: invokestatic  #81                 // Method java/util/Objects.equals:(Ljava/lang/Object;Ljava/lang/Object;)Z
     119: ifeq          333
     122: aload_0
     123: invokevirtual #63                 // Method description:()Ljava/lang/String;
     126: aload_2
     127: invokevirtual #63                 // Method description:()Ljava/lang/String;
     130: invokestatic  #81                 // Method java/util/Objects.equals:(Ljava/lang/Object;Ljava/lang/Object;)Z
     133: ifeq          333
     136: aload_0
     137: invokevirtual #64                 // Method deviceAggregatedStatusAsString:()Ljava/lang/String;
     140: aload_2
     141: invokevirtual #64                 // Method deviceAggregatedStatusAsString:()Ljava/lang/String;
     144: invokestatic  #81                 // Method java/util/Objects.equals:(Ljava/lang/Object;Ljava/lang/Object;)Z
     147: ifeq          333
     150: aload_0
     151: invokevirtual #65                 // Method deviceConnectionStatusAsString:()Ljava/lang/String;
     154: aload_2
     155: invokevirtual #65                 // Method deviceConnectionStatusAsString:()Ljava/lang/String;
     158: invokestatic  #81                 // Method java/util/Objects.equals:(Ljava/lang/Object;Ljava/lang/Object;)Z
     161: ifeq          333
     164: aload_0
     165: invokevirtual #66                 // Method deviceId:()Ljava/lang/String;
     168: aload_2
     169: invokevirtual #66                 // Method deviceId:()Ljava/lang/String;
     172: invokestatic  #81                 // Method java/util/Objects.equals:(Ljava/lang/Object;Ljava/lang/Object;)Z
     175: ifeq          333
     178: aload_0
     179: invokevirtual #67                 // Method latestAlternateSoftware:()Ljava/lang/String;
     182: aload_2
     183: invokevirtual #67                 // Method latestAlternateSoftware:()Ljava/lang/String;
     186: invokestatic  #81                 // Method java/util/Objects.equals:(Ljava/lang/Object;Ljava/lang/Object;)Z
     189: ifeq          333
     192: aload_0
     193: invokevirtual #68                 // Method latestDeviceJob:()Lsoftware/amazon/awssdk/services/panorama/model/LatestDeviceJob;
     196: aload_2
     197: invokevirtual #68                 // Method latestDeviceJob:()Lsoftware/amazon/awssdk/services/panorama/model/LatestDeviceJob;
     200: invokestatic  #81                 // Method java/util/Objects.equals:(Ljava/lang/Object;Ljava/lang/Object;)Z
     203: ifeq          333
     206: aload_0
     207: invokevirtual #69                 // Method latestSoftware:()Ljava/lang/String;
     210: aload_2
     211: invokevirtual #69                 // Method latestSoftware:()Ljava/lang/String;
     214: invokestatic  #81                 // Method java/util/Objects.equals:(Ljava/lang/Object;Ljava/lang/Object;)Z
     217: ifeq          333
     220: aload_0
     221: invokevirtual #70                 // Method leaseExpirationTime:()Ljava/time/Instant;
     224: aload_2
     225: invokevirtual #70                 // Method leaseExpirationTime:()Ljava/time/Instant;
     228: invokestatic  #81                 // Method java/util/Objects.equals:(Ljava/lang/Object;Ljava/lang/Object;)Z
     231: ifeq          333
     234: aload_0
     235: invokevirtual #71                 // Method name:()Ljava/lang/String;
     238: aload_2
     239: invokevirtual #71                 // Method name:()Ljava/lang/String;
     242: invokestatic  #81                 // Method java/util/Objects.equals:(Ljava/lang/Object;Ljava/lang/Object;)Z
     245: ifeq          333
     248: aload_0
     249: invokevirtual #72                 // Method networkingConfiguration:()Lsoftware/amazon/awssdk/services/panorama/model/NetworkPayload;
     252: aload_2
     253: invokevirtual #72                 // Method networkingConfiguration:()Lsoftware/amazon/awssdk/services/panorama/model/NetworkPayload;
     256: invokestatic  #81                 // Method java/util/Objects.equals:(Ljava/lang/Object;Ljava/lang/Object;)Z
     259: ifeq          333
     262: aload_0
     263: invokevirtual #73                 // Method provisioningStatusAsString:()Ljava/lang/String;
     266: aload_2
     267: invokevirtual #73                 // Method provisioningStatusAsString:()Ljava/lang/String;
     270: invokestatic  #81                 // Method java/util/Objects.equals:(Ljava/lang/Object;Ljava/lang/Object;)Z
     273: ifeq          333
     276: aload_0
     277: invokevirtual #74                 // Method serialNumber:()Ljava/lang/String;
     280: aload_2
     281: invokevirtual #74                 // Method serialNumber:()Ljava/lang/String;
     284: invokestatic  #81                 // Method java/util/Objects.equals:(Ljava/lang/Object;Ljava/lang/Object;)Z
     287: ifeq          333
     290: aload_0
     291: invokevirtual #75                 // Method hasTags:()Z
     294: aload_2
     295: invokevirtual #75                 // Method hasTags:()Z
     298: if_icmpne     333
     301: aload_0
     302: invokevirtual #76                 // Method tags:()Ljava/util/Map;
     305: aload_2
     306: invokevirtual #76                 // Method tags:()Ljava/util/Map;
     309: invokestatic  #81                 // Method java/util/Objects.equals:(Ljava/lang/Object;Ljava/lang/Object;)Z
     312: ifeq          333
     315: aload_0
     316: invokevirtual #77                 // Method typeAsString:()Ljava/lang/String;
     319: aload_2
     320: invokevirtual #77                 // Method typeAsString:()Ljava/lang/String;
     323: invokestatic  #81                 // Method java/util/Objects.equals:(Ljava/lang/Object;Ljava/lang/Object;)Z
     326: ifeq          333
     329: iconst_1
     330: goto          334
     333: iconst_0
     334: ireturn

  public final java.lang.String toString();
    Code:
       0: ldc           #82                 // String DescribeDeviceResponse
       2: invokestatic  #83                 // Method software/amazon/awssdk/utils/ToString.builder:(Ljava/lang/String;)Lsoftware/amazon/awssdk/utils/ToString;
       5: ldc           #84                 // String AlternateSoftwares
       7: aload_0
       8: invokevirtual #55                 // Method hasAlternateSoftwares:()Z
      11: ifeq          21
      14: aload_0
      15: invokevirtual #56                 // Method alternateSoftwares:()Ljava/util/List;
      18: goto          22
      21: aconst_null
      22: invokevirtual #85                 // Method software/amazon/awssdk/utils/ToString.add:(Ljava/lang/String;Ljava/lang/Object;)Lsoftware/amazon/awssdk/utils/ToString;
      25: ldc           #86                 // String Arn
      27: aload_0
      28: invokevirtual #58                 // Method arn:()Ljava/lang/String;
      31: invokevirtual #85                 // Method software/amazon/awssdk/utils/ToString.add:(Ljava/lang/String;Ljava/lang/Object;)Lsoftware/amazon/awssdk/utils/ToString;
      34: ldc           #87                 // String Brand
      36: aload_0
      37: invokevirtual #59                 // Method brandAsString:()Ljava/lang/String;
      40: invokevirtual #85                 // Method software/amazon/awssdk/utils/ToString.add:(Ljava/lang/String;Ljava/lang/Object;)Lsoftware/amazon/awssdk/utils/ToString;
      43: ldc           #88                 // String CreatedTime
      45: aload_0
      46: invokevirtual #60                 // Method createdTime:()Ljava/time/Instant;
      49: invokevirtual #85                 // Method software/amazon/awssdk/utils/ToString.add:(Ljava/lang/String;Ljava/lang/Object;)Lsoftware/amazon/awssdk/utils/ToString;
      52: ldc           #89                 // String CurrentNetworkingStatus
      54: aload_0
      55: invokevirtual #61                 // Method currentNetworkingStatus:()Lsoftware/amazon/awssdk/services/panorama/model/NetworkStatus;
      58: invokevirtual #85                 // Method software/amazon/awssdk/utils/ToString.add:(Ljava/lang/String;Ljava/lang/Object;)Lsoftware/amazon/awssdk/utils/ToString;
      61: ldc           #90                 // String CurrentSoftware
      63: aload_0
      64: invokevirtual #62                 // Method currentSoftware:()Ljava/lang/String;
      67: invokevirtual #85                 // Method software/amazon/awssdk/utils/ToString.add:(Ljava/lang/String;Ljava/lang/Object;)Lsoftware/amazon/awssdk/utils/ToString;
      70: ldc           #91                 // String Description
      72: aload_0
      73: invokevirtual #63                 // Method description:()Ljava/lang/String;
      76: invokevirtual #85                 // Method software/amazon/awssdk/utils/ToString.add:(Ljava/lang/String;Ljava/lang/Object;)Lsoftware/amazon/awssdk/utils/ToString;
      79: ldc           #92                 // String DeviceAggregatedStatus
      81: aload_0
      82: invokevirtual #64                 // Method deviceAggregatedStatusAsString:()Ljava/lang/String;
      85: invokevirtual #85                 // Method software/amazon/awssdk/utils/ToString.add:(Ljava/lang/String;Ljava/lang/Object;)Lsoftware/amazon/awssdk/utils/ToString;
      88: ldc           #93                 // String DeviceConnectionStatus
      90: aload_0
      91: invokevirtual #65                 // Method deviceConnectionStatusAsString:()Ljava/lang/String;
      94: invokevirtual #85                 // Method software/amazon/awssdk/utils/ToString.add:(Ljava/lang/String;Ljava/lang/Object;)Lsoftware/amazon/awssdk/utils/ToString;
      97: ldc           #94                 // String DeviceId
      99: aload_0
     100: invokevirtual #66                 // Method deviceId:()Ljava/lang/String;
     103: invokevirtual #85                 // Method software/amazon/awssdk/utils/ToString.add:(Ljava/lang/String;Ljava/lang/Object;)Lsoftware/amazon/awssdk/utils/ToString;
     106: ldc           #95                 // String LatestAlternateSoftware
     108: aload_0
     109: invokevirtual #67                 // Method latestAlternateSoftware:()Ljava/lang/String;
     112: invokevirtual #85                 // Method software/amazon/awssdk/utils/ToString.add:(Ljava/lang/String;Ljava/lang/Object;)Lsoftware/amazon/awssdk/utils/ToString;
     115: ldc           #96                 // String LatestDeviceJob
     117: aload_0
     118: invokevirtual #68                 // Method latestDeviceJob:()Lsoftware/amazon/awssdk/services/panorama/model/LatestDeviceJob;
     121: invokevirtual #85                 // Method software/amazon/awssdk/utils/ToString.add:(Ljava/lang/String;Ljava/lang/Object;)Lsoftware/amazon/awssdk/utils/ToString;
     124: ldc           #97                 // String LatestSoftware
     126: aload_0
     127: invokevirtual #69                 // Method latestSoftware:()Ljava/lang/String;
     130: invokevirtual #85                 // Method software/amazon/awssdk/utils/ToString.add:(Ljava/lang/String;Ljava/lang/Object;)Lsoftware/amazon/awssdk/utils/ToString;
     133: ldc           #98                 // String LeaseExpirationTime
     135: aload_0
     136: invokevirtual #70                 // Method leaseExpirationTime:()Ljava/time/Instant;
     139: invokevirtual #85                 // Method software/amazon/awssdk/utils/ToString.add:(Ljava/lang/String;Ljava/lang/Object;)Lsoftware/amazon/awssdk/utils/ToString;
     142: ldc           #99                 // String Name
     144: aload_0
     145: invokevirtual #71                 // Method name:()Ljava/lang/String;
     148: invokevirtual #85                 // Method software/amazon/awssdk/utils/ToString.add:(Ljava/lang/String;Ljava/lang/Object;)Lsoftware/amazon/awssdk/utils/ToString;
     151: ldc           #100                // String NetworkingConfiguration
     153: aload_0
     154: invokevirtual #72                 // Method networkingConfiguration:()Lsoftware/amazon/awssdk/services/panorama/model/NetworkPayload;
     157: invokevirtual #85                 // Method software/amazon/awssdk/utils/ToString.add:(Ljava/lang/String;Ljava/lang/Object;)Lsoftware/amazon/awssdk/utils/ToString;
     160: ldc           #101                // String ProvisioningStatus
     162: aload_0
     163: invokevirtual #73                 // Method provisioningStatusAsString:()Ljava/lang/String;
     166: invokevirtual #85                 // Method software/amazon/awssdk/utils/ToString.add:(Ljava/lang/String;Ljava/lang/Object;)Lsoftware/amazon/awssdk/utils/ToString;
     169: ldc           #102                // String SerialNumber
     171: aload_0
     172: invokevirtual #74                 // Method serialNumber:()Ljava/lang/String;
     175: invokevirtual #85                 // Method software/amazon/awssdk/utils/ToString.add:(Ljava/lang/String;Ljava/lang/Object;)Lsoftware/amazon/awssdk/utils/ToString;
     178: ldc           #103                // String Tags
     180: aload_0
     181: invokevirtual #75                 // Method hasTags:()Z
     184: ifeq          194
     187: aload_0
     188: invokevirtual #76                 // Method tags:()Ljava/util/Map;
     191: goto          195
     194: aconst_null
     195: invokevirtual #85                 // Method software/amazon/awssdk/utils/ToString.add:(Ljava/lang/String;Ljava/lang/Object;)Lsoftware/amazon/awssdk/utils/ToString;
     198: ldc           #104                // String Type
     200: aload_0
     201: invokevirtual #77                 // Method typeAsString:()Ljava/lang/String;
     204: invokevirtual #85                 // Method software/amazon/awssdk/utils/ToString.add:(Ljava/lang/String;Ljava/lang/Object;)Lsoftware/amazon/awssdk/utils/ToString;
     207: invokevirtual #105                // Method software/amazon/awssdk/utils/ToString.build:()Ljava/lang/String;
     210: areturn

  public final <T> java.util.Optional<T> getValueForField(java.lang.String, java.lang.Class<T>);
    Code:
       0: aload_1
       1: astore_3
       2: iconst_m1
       3: istore        4
       5: aload_3
       6: invokevirtual #106                // Method java/lang/String.hashCode:()I
       9: lookupswitch  { // 20
           -1861689610: 382
           -1719160288: 255
           -1403732218: 302
            -424367506: 366
             -56677412: 270
                 66109: 195
               2420395: 398
               2598969: 462
               2622298: 478
              64445287: 210
             248107645: 446
             412574061: 286
             543851074: 414
            1137337215: 240
            1173835313: 318
            1177958837: 225
            1504552287: 430
            1804818546: 180
            1805135264: 350
            2011468634: 334
               default: 491
          }
     180: aload_3
     181: ldc           #84                 // String AlternateSoftwares
     183: invokevirtual #107                // Method java/lang/String.equals:(Ljava/lang/Object;)Z
     186: ifeq          491
     189: iconst_0
     190: istore        4
     192: goto          491
     195: aload_3
     196: ldc           #86                 // String Arn
     198: invokevirtual #107                // Method java/lang/String.equals:(Ljava/lang/Object;)Z
     201: ifeq          491
     204: iconst_1
     205: istore        4
     207: goto          491
     210: aload_3
     211: ldc           #87                 // String Brand
     213: invokevirtual #107                // Method java/lang/String.equals:(Ljava/lang/Object;)Z
     216: ifeq          491
     219: iconst_2
     220: istore        4
     222: goto          491
     225: aload_3
     226: ldc           #88                 // String CreatedTime
     228: invokevirtual #107                // Method java/lang/String.equals:(Ljava/lang/Object;)Z
     231: ifeq          491
     234: iconst_3
     235: istore        4
     237: goto          491
     240: aload_3
     241: ldc           #89                 // String CurrentNetworkingStatus
     243: invokevirtual #107                // Method java/lang/String.equals:(Ljava/lang/Object;)Z
     246: ifeq          491
     249: iconst_4
     250: istore        4
     252: goto          491
     255: aload_3
     256: ldc           #90                 // String CurrentSoftware
     258: invokevirtual #107                // Method java/lang/String.equals:(Ljava/lang/Object;)Z
     261: ifeq          491
     264: iconst_5
     265: istore        4
     267: goto          491
     270: aload_3
     271: ldc           #91                 // String Description
     273: invokevirtual #107                // Method java/lang/String.equals:(Ljava/lang/Object;)Z
     276: ifeq          491
     279: bipush        6
     281: istore        4
     283: goto          491
     286: aload_3
     287: ldc           #92                 // String DeviceAggregatedStatus
     289: invokevirtual #107                // Method java/lang/String.equals:(Ljava/lang/Object;)Z
     292: ifeq          491
     295: bipush        7
     297: istore        4
     299: goto          491
     302: aload_3
     303: ldc           #93                 // String DeviceConnectionStatus
     305: invokevirtual #107                // Method java/lang/String.equals:(Ljava/lang/Object;)Z
     308: ifeq          491
     311: bipush        8
     313: istore        4
     315: goto          491
     318: aload_3
     319: ldc           #94                 // String DeviceId
     321: invokevirtual #107                // Method java/lang/String.equals:(Ljava/lang/Object;)Z
     324: ifeq          491
     327: bipush        9
     329: istore        4
     331: goto          491
     334: aload_3
     335: ldc           #95                 // String LatestAlternateSoftware
     337: invokevirtual #107                // Method java/lang/String.equals:(Ljava/lang/Object;)Z
     340: ifeq          491
     343: bipush        10
     345: istore        4
     347: goto          491
     350: aload_3
     351: ldc           #96                 // String LatestDeviceJob
     353: invokevirtual #107                // Method java/lang/String.equals:(Ljava/lang/Object;)Z
     356: ifeq          491
     359: bipush        11
     361: istore        4
     363: goto          491
     366: aload_3
     367: ldc           #97                 // String LatestSoftware
     369: invokevirtual #107                // Method java/lang/String.equals:(Ljava/lang/Object;)Z
     372: ifeq          491
     375: bipush        12
     377: istore        4
     379: goto          491
     382: aload_3
     383: ldc           #98                 // String LeaseExpirationTime
     385: invokevirtual #107                // Method java/lang/String.equals:(Ljava/lang/Object;)Z
     388: ifeq          491
     391: bipush        13
     393: istore        4
     395: goto          491
     398: aload_3
     399: ldc           #99                 // String Name
     401: invokevirtual #107                // Method java/lang/String.equals:(Ljava/lang/Object;)Z
     404: ifeq          491
     407: bipush        14
     409: istore        4
     411: goto          491
     414: aload_3
     415: ldc           #100                // String NetworkingConfiguration
     417: invokevirtual #107                // Method java/lang/String.equals:(Ljava/lang/Object;)Z
     420: ifeq          491
     423: bipush        15
     425: istore        4
     427: goto          491
     430: aload_3
     431: ldc           #101                // String ProvisioningStatus
     433: invokevirtual #107                // Method java/lang/String.equals:(Ljava/lang/Object;)Z
     436: ifeq          491
     439: bipush        16
     441: istore        4
     443: goto          491
     446: aload_3
     447: ldc           #102                // String SerialNumber
     449: invokevirtual #107                // Method java/lang/String.equals:(Ljava/lang/Object;)Z
     452: ifeq          491
     455: bipush        17
     457: istore        4
     459: goto          491
     462: aload_3
     463: ldc           #103                // String Tags
     465: invokevirtual #107                // Method java/lang/String.equals:(Ljava/lang/Object;)Z
     468: ifeq          491
     471: bipush        18
     473: istore        4
     475: goto          491
     478: aload_3
     479: ldc           #104                // String Type
     481: invokevirtual #107                // Method java/lang/String.equals:(Ljava/lang/Object;)Z
     484: ifeq          491
     487: bipush        19
     489: istore        4
     491: iload         4
     493: tableswitch   { // 0 to 19
                     0: 588
                     1: 600
                     2: 612
                     3: 624
                     4: 636
                     5: 648
                     6: 660
                     7: 672
                     8: 684
                     9: 696
                    10: 708
                    11: 720
                    12: 732
                    13: 744
                    14: 756
                    15: 768
                    16: 780
                    17: 792
                    18: 804
                    19: 816
               default: 828
          }
     588: aload_2
     589: aload_0
     590: invokevirtual #56                 // Method alternateSoftwares:()Ljava/util/List;
     593: invokevirtual #108                // Method java/lang/Class.cast:(Ljava/lang/Object;)Ljava/lang/Object;
     596: invokestatic  #109                // Method java/util/Optional.ofNullable:(Ljava/lang/Object;)Ljava/util/Optional;
     599: areturn
     600: aload_2
     601: aload_0
     602: invokevirtual #58                 // Method arn:()Ljava/lang/String;
     605: invokevirtual #108                // Method java/lang/Class.cast:(Ljava/lang/Object;)Ljava/lang/Object;
     608: invokestatic  #109                // Method java/util/Optional.ofNullable:(Ljava/lang/Object;)Ljava/util/Optional;
     611: areturn
     612: aload_2
     613: aload_0
     614: invokevirtual #59                 // Method brandAsString:()Ljava/lang/String;
     617: invokevirtual #108                // Method java/lang/Class.cast:(Ljava/lang/Object;)Ljava/lang/Object;
     620: invokestatic  #109                // Method java/util/Optional.ofNullable:(Ljava/lang/Object;)Ljava/util/Optional;
     623: areturn
     624: aload_2
     625: aload_0
     626: invokevirtual #60                 // Method createdTime:()Ljava/time/Instant;
     629: invokevirtual #108                // Method java/lang/Class.cast:(Ljava/lang/Object;)Ljava/lang/Object;
     632: invokestatic  #109                // Method java/util/Optional.ofNullable:(Ljava/lang/Object;)Ljava/util/Optional;
     635: areturn
     636: aload_2
     637: aload_0
     638: invokevirtual #61                 // Method currentNetworkingStatus:()Lsoftware/amazon/awssdk/services/panorama/model/NetworkStatus;
     641: invokevirtual #108                // Method java/lang/Class.cast:(Ljava/lang/Object;)Ljava/lang/Object;
     644: invokestatic  #109                // Method java/util/Optional.ofNullable:(Ljava/lang/Object;)Ljava/util/Optional;
     647: areturn
     648: aload_2
     649: aload_0
     650: invokevirtual #62                 // Method currentSoftware:()Ljava/lang/String;
     653: invokevirtual #108                // Method java/lang/Class.cast:(Ljava/lang/Object;)Ljava/lang/Object;
     656: invokestatic  #109                // Method java/util/Optional.ofNullable:(Ljava/lang/Object;)Ljava/util/Optional;
     659: areturn
     660: aload_2
     661: aload_0
     662: invokevirtual #63                 // Method description:()Ljava/lang/String;
     665: invokevirtual #108                // Method java/lang/Class.cast:(Ljava/lang/Object;)Ljava/lang/Object;
     668: invokestatic  #109                // Method java/util/Optional.ofNullable:(Ljava/lang/Object;)Ljava/util/Optional;
     671: areturn
     672: aload_2
     673: aload_0
     674: invokevirtual #64                 // Method deviceAggregatedStatusAsString:()Ljava/lang/String;
     677: invokevirtual #108                // Method java/lang/Class.cast:(Ljava/lang/Object;)Ljava/lang/Object;
     680: invokestatic  #109                // Method java/util/Optional.ofNullable:(Ljava/lang/Object;)Ljava/util/Optional;
     683: areturn
     684: aload_2
     685: aload_0
     686: invokevirtual #65                 // Method deviceConnectionStatusAsString:()Ljava/lang/String;
     689: invokevirtual #108                // Method java/lang/Class.cast:(Ljava/lang/Object;)Ljava/lang/Object;
     692: invokestatic  #109                // Method java/util/Optional.ofNullable:(Ljava/lang/Object;)Ljava/util/Optional;
     695: areturn
     696: aload_2
     697: aload_0
     698: invokevirtual #66                 // Method deviceId:()Ljava/lang/String;
     701: invokevirtual #108                // Method java/lang/Class.cast:(Ljava/lang/Object;)Ljava/lang/Object;
     704: invokestatic  #109                // Method java/util/Optional.ofNullable:(Ljava/lang/Object;)Ljava/util/Optional;
     707: areturn
     708: aload_2
     709: aload_0
     710: invokevirtual #67                 // Method latestAlternateSoftware:()Ljava/lang/String;
     713: invokevirtual #108                // Method java/lang/Class.cast:(Ljava/lang/Object;)Ljava/lang/Object;
     716: invokestatic  #109                // Method java/util/Optional.ofNullable:(Ljava/lang/Object;)Ljava/util/Optional;
     719: areturn
     720: aload_2
     721: aload_0
     722: invokevirtual #68                 // Method latestDeviceJob:()Lsoftware/amazon/awssdk/services/panorama/model/LatestDeviceJob;
     725: invokevirtual #108                // Method java/lang/Class.cast:(Ljava/lang/Object;)Ljava/lang/Object;
     728: invokestatic  #109                // Method java/util/Optional.ofNullable:(Ljava/lang/Object;)Ljava/util/Optional;
     731: areturn
     732: aload_2
     733: aload_0
     734: invokevirtual #69                 // Method latestSoftware:()Ljava/lang/String;
     737: invokevirtual #108                // Method java/lang/Class.cast:(Ljava/lang/Object;)Ljava/lang/Object;
     740: invokestatic  #109                // Method java/util/Optional.ofNullable:(Ljava/lang/Object;)Ljava/util/Optional;
     743: areturn
     744: aload_2
     745: aload_0
     746: invokevirtual #70                 // Method leaseExpirationTime:()Ljava/time/Instant;
     749: invokevirtual #108                // Method java/lang/Class.cast:(Ljava/lang/Object;)Ljava/lang/Object;
     752: invokestatic  #109                // Method java/util/Optional.ofNullable:(Ljava/lang/Object;)Ljava/util/Optional;
     755: areturn
     756: aload_2
     757: aload_0
     758: invokevirtual #71                 // Method name:()Ljava/lang/String;
     761: invokevirtual #108                // Method java/lang/Class.cast:(Ljava/lang/Object;)Ljava/lang/Object;
     764: invokestatic  #109                // Method java/util/Optional.ofNullable:(Ljava/lang/Object;)Ljava/util/Optional;
     767: areturn
     768: aload_2
     769: aload_0
     770: invokevirtual #72                 // Method networkingConfiguration:()Lsoftware/amazon/awssdk/services/panorama/model/NetworkPayload;
     773: invokevirtual #108                // Method java/lang/Class.cast:(Ljava/lang/Object;)Ljava/lang/Object;
     776: invokestatic  #109                // Method java/util/Optional.ofNullable:(Ljava/lang/Object;)Ljava/util/Optional;
     779: areturn
     780: aload_2
     781: aload_0
     782: invokevirtual #73                 // Method provisioningStatusAsString:()Ljava/lang/String;
     785: invokevirtual #108                // Method java/lang/Class.cast:(Ljava/lang/Object;)Ljava/lang/Object;
     788: invokestatic  #109                // Method java/util/Optional.ofNullable:(Ljava/lang/Object;)Ljava/util/Optional;
     791: areturn
     792: aload_2
     793: aload_0
     794: invokevirtual #74                 // Method serialNumber:()Ljava/lang/String;
     797: invokevirtual #108                // Method java/lang/Class.cast:(Ljava/lang/Object;)Ljava/lang/Object;
     800: invokestatic  #109                // Method java/util/Optional.ofNullable:(Ljava/lang/Object;)Ljava/util/Optional;
     803: areturn
     804: aload_2
     805: aload_0
     806: invokevirtual #76                 // Method tags:()Ljava/util/Map;
     809: invokevirtual #108                // Method java/lang/Class.cast:(Ljava/lang/Object;)Ljava/lang/Object;
     812: invokestatic  #109                // Method java/util/Optional.ofNullable:(Ljava/lang/Object;)Ljava/util/Optional;
     815: areturn
     816: aload_2
     817: aload_0
     818: invokevirtual #77                 // Method typeAsString:()Ljava/lang/String;
     821: invokevirtual #108                // Method java/lang/Class.cast:(Ljava/lang/Object;)Ljava/lang/Object;
     824: invokestatic  #109                // Method java/util/Optional.ofNullable:(Ljava/lang/Object;)Ljava/util/Optional;
     827: areturn
     828: invokestatic  #110                // Method java/util/Optional.empty:()Ljava/util/Optional;
     831: areturn

  public final java.util.List<software.amazon.awssdk.core.SdkField<?>> sdkFields();
    Code:
       0: getstatic     #1                  // Field SDK_FIELDS:Ljava/util/List;
       3: areturn

  private static <T> java.util.function.Function<java.lang.Object, T> getter(java.util.function.Function<software.amazon.awssdk.services.panorama.model.DescribeDeviceResponse, T>);
    Code:
       0: aload_0
       1: invokedynamic #111,  0            // InvokeDynamic #0:apply:(Ljava/util/function/Function;)Ljava/util/function/Function;
       6: areturn

  private static <T> java.util.function.BiConsumer<java.lang.Object, T> setter(java.util.function.BiConsumer<software.amazon.awssdk.services.panorama.model.DescribeDeviceResponse$Builder, T>);
    Code:
       0: aload_0
       1: invokedynamic #112,  0            // InvokeDynamic #1:accept:(Ljava/util/function/BiConsumer;)Ljava/util/function/BiConsumer;
       6: areturn

  public software.amazon.awssdk.awscore.AwsResponse$Builder toBuilder();
    Code:
       0: aload_0
       1: invokevirtual #113                // Method toBuilder:()Lsoftware/amazon/awssdk/services/panorama/model/DescribeDeviceResponse$Builder;
       4: areturn

  public software.amazon.awssdk.core.SdkResponse$Builder toBuilder();
    Code:
       0: aload_0
       1: invokevirtual #113                // Method toBuilder:()Lsoftware/amazon/awssdk/services/panorama/model/DescribeDeviceResponse$Builder;
       4: areturn

  public software.amazon.awssdk.utils.builder.CopyableBuilder toBuilder();
    Code:
       0: aload_0
       1: invokevirtual #113                // Method toBuilder:()Lsoftware/amazon/awssdk/services/panorama/model/DescribeDeviceResponse$Builder;
       4: areturn

  private static void lambda$setter$1(java.util.function.BiConsumer, java.lang.Object, java.lang.Object);
    Code:
       0: aload_0
       1: aload_1
       2: checkcast     #114                // class software/amazon/awssdk/services/panorama/model/DescribeDeviceResponse$Builder
       5: aload_2
       6: invokeinterface #115,  3          // InterfaceMethod java/util/function/BiConsumer.accept:(Ljava/lang/Object;Ljava/lang/Object;)V
      11: return

  private static java.lang.Object lambda$getter$0(java.util.function.Function, java.lang.Object);
    Code:
       0: aload_0
       1: aload_1
       2: checkcast     #80                 // class software/amazon/awssdk/services/panorama/model/DescribeDeviceResponse
       5: invokeinterface #116,  2          // InterfaceMethod java/util/function/Function.apply:(Ljava/lang/Object;)Ljava/lang/Object;
      10: areturn

  static java.util.List access$2200(software.amazon.awssdk.services.panorama.model.DescribeDeviceResponse);
    Code:
       0: aload_0
       1: getfield      #22                 // Field alternateSoftwares:Ljava/util/List;
       4: areturn

  static java.lang.String access$2300(software.amazon.awssdk.services.panorama.model.DescribeDeviceResponse);
    Code:
       0: aload_0
       1: getfield      #21                 // Field arn:Ljava/lang/String;
       4: areturn

  static java.lang.String access$2400(software.amazon.awssdk.services.panorama.model.DescribeDeviceResponse);
    Code:
       0: aload_0
       1: getfield      #20                 // Field brand:Ljava/lang/String;
       4: areturn

  static java.time.Instant access$2500(software.amazon.awssdk.services.panorama.model.DescribeDeviceResponse);
    Code:
       0: aload_0
       1: getfield      #19                 // Field createdTime:Ljava/time/Instant;
       4: areturn

  static software.amazon.awssdk.services.panorama.model.NetworkStatus access$2600(software.amazon.awssdk.services.panorama.model.DescribeDeviceResponse);
    Code:
       0: aload_0
       1: getfield      #18                 // Field currentNetworkingStatus:Lsoftware/amazon/awssdk/services/panorama/model/NetworkStatus;
       4: areturn

  static java.lang.String access$2700(software.amazon.awssdk.services.panorama.model.DescribeDeviceResponse);
    Code:
       0: aload_0
       1: getfield      #17                 // Field currentSoftware:Ljava/lang/String;
       4: areturn

  static java.lang.String access$2800(software.amazon.awssdk.services.panorama.model.DescribeDeviceResponse);
    Code:
       0: aload_0
       1: getfield      #16                 // Field description:Ljava/lang/String;
       4: areturn

  static java.lang.String access$2900(software.amazon.awssdk.services.panorama.model.DescribeDeviceResponse);
    Code:
       0: aload_0
       1: getfield      #15                 // Field deviceAggregatedStatus:Ljava/lang/String;
       4: areturn

  static java.lang.String access$3000(software.amazon.awssdk.services.panorama.model.DescribeDeviceResponse);
    Code:
       0: aload_0
       1: getfield      #14                 // Field deviceConnectionStatus:Ljava/lang/String;
       4: areturn

  static java.lang.String access$3100(software.amazon.awssdk.services.panorama.model.DescribeDeviceResponse);
    Code:
       0: aload_0
       1: getfield      #13                 // Field deviceId:Ljava/lang/String;
       4: areturn

  static java.lang.String access$3200(software.amazon.awssdk.services.panorama.model.DescribeDeviceResponse);
    Code:
       0: aload_0
       1: getfield      #12                 // Field latestAlternateSoftware:Ljava/lang/String;
       4: areturn

  static software.amazon.awssdk.services.panorama.model.LatestDeviceJob access$3300(software.amazon.awssdk.services.panorama.model.DescribeDeviceResponse);
    Code:
       0: aload_0
       1: getfield      #11                 // Field latestDeviceJob:Lsoftware/amazon/awssdk/services/panorama/model/LatestDeviceJob;
       4: areturn

  static java.lang.String access$3400(software.amazon.awssdk.services.panorama.model.DescribeDeviceResponse);
    Code:
       0: aload_0
       1: getfield      #10                 // Field latestSoftware:Ljava/lang/String;
       4: areturn

  static java.time.Instant access$3500(software.amazon.awssdk.services.panorama.model.DescribeDeviceResponse);
    Code:
       0: aload_0
       1: getfield      #9                  // Field leaseExpirationTime:Ljava/time/Instant;
       4: areturn

  static java.lang.String access$3600(software.amazon.awssdk.services.panorama.model.DescribeDeviceResponse);
    Code:
       0: aload_0
       1: getfield      #8                  // Field name:Ljava/lang/String;
       4: areturn

  static software.amazon.awssdk.services.panorama.model.NetworkPayload access$3700(software.amazon.awssdk.services.panorama.model.DescribeDeviceResponse);
    Code:
       0: aload_0
       1: getfield      #7                  // Field networkingConfiguration:Lsoftware/amazon/awssdk/services/panorama/model/NetworkPayload;
       4: areturn

  static java.lang.String access$3800(software.amazon.awssdk.services.panorama.model.DescribeDeviceResponse);
    Code:
       0: aload_0
       1: getfield      #6                  // Field provisioningStatus:Ljava/lang/String;
       4: areturn

  static java.lang.String access$3900(software.amazon.awssdk.services.panorama.model.DescribeDeviceResponse);
    Code:
       0: aload_0
       1: getfield      #5                  // Field serialNumber:Ljava/lang/String;
       4: areturn

  static java.util.Map access$4000(software.amazon.awssdk.services.panorama.model.DescribeDeviceResponse);
    Code:
       0: aload_0
       1: getfield      #4                  // Field tags:Ljava/util/Map;
       4: areturn

  static java.lang.String access$4100(software.amazon.awssdk.services.panorama.model.DescribeDeviceResponse);
    Code:
       0: aload_0
       1: getfield      #3                  // Field type:Ljava/lang/String;
       4: areturn

  software.amazon.awssdk.services.panorama.model.DescribeDeviceResponse(software.amazon.awssdk.services.panorama.model.DescribeDeviceResponse$BuilderImpl, software.amazon.awssdk.services.panorama.model.DescribeDeviceResponse$1);
    Code:
       0: aload_0
       1: aload_1
       2: invokespecial #2                  // Method "<init>":(Lsoftware/amazon/awssdk/services/panorama/model/DescribeDeviceResponse$BuilderImpl;)V
       5: return

  static java.util.List access$4300();
    Code:
       0: getstatic     #1                  // Field SDK_FIELDS:Ljava/util/List;
       3: areturn

  static {};
    Code:
       0: getstatic     #117                // Field software/amazon/awssdk/core/protocol/MarshallingType.LIST:Lsoftware/amazon/awssdk/core/protocol/MarshallingType;
       3: invokestatic  #118                // Method software/amazon/awssdk/core/SdkField.builder:(Lsoftware/amazon/awssdk/core/protocol/MarshallingType;)Lsoftware/amazon/awssdk/core/SdkField$Builder;
       6: ldc           #84                 // String AlternateSoftwares
       8: invokevirtual #119                // Method software/amazon/awssdk/core/SdkField$Builder.memberName:(Ljava/lang/String;)Lsoftware/amazon/awssdk/core/SdkField$Builder;
      11: invokedynamic #120,  0            // InvokeDynamic #2:apply:()Ljava/util/function/Function;
      16: invokestatic  #121                // Method getter:(Ljava/util/function/Function;)Ljava/util/function/Function;
      19: invokevirtual #122                // Method software/amazon/awssdk/core/SdkField$Builder.getter:(Ljava/util/function/Function;)Lsoftware/amazon/awssdk/core/SdkField$Builder;
      22: invokedynamic #123,  0            // InvokeDynamic #3:accept:()Ljava/util/function/BiConsumer;
      27: invokestatic  #124                // Method setter:(Ljava/util/function/BiConsumer;)Ljava/util/function/BiConsumer;
      30: invokevirtual #125                // Method software/amazon/awssdk/core/SdkField$Builder.setter:(Ljava/util/function/BiConsumer;)Lsoftware/amazon/awssdk/core/SdkField$Builder;
      33: iconst_2
      34: anewarray     #126                // class software/amazon/awssdk/core/traits/Trait
      37: dup
      38: iconst_0
      39: invokestatic  #127                // Method software/amazon/awssdk/core/traits/LocationTrait.builder:()Lsoftware/amazon/awssdk/core/traits/LocationTrait$Builder;
      42: getstatic     #128                // Field software/amazon/awssdk/core/protocol/MarshallLocation.PAYLOAD:Lsoftware/amazon/awssdk/core/protocol/MarshallLocation;
      45: invokevirtual #129                // Method software/amazon/awssdk/core/traits/LocationTrait$Builder.location:(Lsoftware/amazon/awssdk/core/protocol/MarshallLocation;)Lsoftware/amazon/awssdk/core/traits/LocationTrait$Builder;
      48: ldc           #84                 // String AlternateSoftwares
      50: invokevirtual #130                // Method software/amazon/awssdk/core/traits/LocationTrait$Builder.locationName:(Ljava/lang/String;)Lsoftware/amazon/awssdk/core/traits/LocationTrait$Builder;
      53: invokevirtual #131                // Method software/amazon/awssdk/core/traits/LocationTrait$Builder.build:()Lsoftware/amazon/awssdk/core/traits/LocationTrait;
      56: aastore
      57: dup
      58: iconst_1
      59: invokestatic  #132                // Method software/amazon/awssdk/core/traits/ListTrait.builder:()Lsoftware/amazon/awssdk/core/traits/ListTrait$Builder;
      62: aconst_null
      63: invokevirtual #133                // Method software/amazon/awssdk/core/traits/ListTrait$Builder.memberLocationName:(Ljava/lang/String;)Lsoftware/amazon/awssdk/core/traits/ListTrait$Builder;
      66: getstatic     #134                // Field software/amazon/awssdk/core/protocol/MarshallingType.SDK_POJO:Lsoftware/amazon/awssdk/core/protocol/MarshallingType;
      69: invokestatic  #118                // Method software/amazon/awssdk/core/SdkField.builder:(Lsoftware/amazon/awssdk/core/protocol/MarshallingType;)Lsoftware/amazon/awssdk/core/SdkField$Builder;
      72: invokedynamic #135,  0            // InvokeDynamic #4:get:()Ljava/util/function/Supplier;
      77: invokevirtual #136                // Method software/amazon/awssdk/core/SdkField$Builder.constructor:(Ljava/util/function/Supplier;)Lsoftware/amazon/awssdk/core/SdkField$Builder;
      80: iconst_1
      81: anewarray     #126                // class software/amazon/awssdk/core/traits/Trait
      84: dup
      85: iconst_0
      86: invokestatic  #127                // Method software/amazon/awssdk/core/traits/LocationTrait.builder:()Lsoftware/amazon/awssdk/core/traits/LocationTrait$Builder;
      89: getstatic     #128                // Field software/amazon/awssdk/core/protocol/MarshallLocation.PAYLOAD:Lsoftware/amazon/awssdk/core/protocol/MarshallLocation;
      92: invokevirtual #129                // Method software/amazon/awssdk/core/traits/LocationTrait$Builder.location:(Lsoftware/amazon/awssdk/core/protocol/MarshallLocation;)Lsoftware/amazon/awssdk/core/traits/LocationTrait$Builder;
      95: ldc           #137                // String member
      97: invokevirtual #130                // Method software/amazon/awssdk/core/traits/LocationTrait$Builder.locationName:(Ljava/lang/String;)Lsoftware/amazon/awssdk/core/traits/LocationTrait$Builder;
     100: invokevirtual #131                // Method software/amazon/awssdk/core/traits/LocationTrait$Builder.build:()Lsoftware/amazon/awssdk/core/traits/LocationTrait;
     103: aastore
     104: invokevirtual #138                // Method software/amazon/awssdk/core/SdkField$Builder.traits:([Lsoftware/amazon/awssdk/core/traits/Trait;)Lsoftware/amazon/awssdk/core/SdkField$Builder;
     107: invokevirtual #139                // Method software/amazon/awssdk/core/SdkField$Builder.build:()Lsoftware/amazon/awssdk/core/SdkField;
     110: invokevirtual #140                // Method software/amazon/awssdk/core/traits/ListTrait$Builder.memberFieldInfo:(Lsoftware/amazon/awssdk/core/SdkField;)Lsoftware/amazon/awssdk/core/traits/ListTrait$Builder;
     113: invokevirtual #141                // Method software/amazon/awssdk/core/traits/ListTrait$Builder.build:()Lsoftware/amazon/awssdk/core/traits/ListTrait;
     116: aastore
     117: invokevirtual #138                // Method software/amazon/awssdk/core/SdkField$Builder.traits:([Lsoftware/amazon/awssdk/core/traits/Trait;)Lsoftware/amazon/awssdk/core/SdkField$Builder;
     120: invokevirtual #139                // Method software/amazon/awssdk/core/SdkField$Builder.build:()Lsoftware/amazon/awssdk/core/SdkField;
     123: putstatic     #142                // Field ALTERNATE_SOFTWARES_FIELD:Lsoftware/amazon/awssdk/core/SdkField;
     126: getstatic     #143                // Field software/amazon/awssdk/core/protocol/MarshallingType.STRING:Lsoftware/amazon/awssdk/core/protocol/MarshallingType;
     129: invokestatic  #118                // Method software/amazon/awssdk/core/SdkField.builder:(Lsoftware/amazon/awssdk/core/protocol/MarshallingType;)Lsoftware/amazon/awssdk/core/SdkField$Builder;
     132: ldc           #86                 // String Arn
     134: invokevirtual #119                // Method software/amazon/awssdk/core/SdkField$Builder.memberName:(Ljava/lang/String;)Lsoftware/amazon/awssdk/core/SdkField$Builder;
     137: invokedynamic #144,  0            // InvokeDynamic #5:apply:()Ljava/util/function/Function;
     142: invokestatic  #121                // Method getter:(Ljava/util/function/Function;)Ljava/util/function/Function;
     145: invokevirtual #122                // Method software/amazon/awssdk/core/SdkField$Builder.getter:(Ljava/util/function/Function;)Lsoftware/amazon/awssdk/core/SdkField$Builder;
     148: invokedynamic #145,  0            // InvokeDynamic #6:accept:()Ljava/util/function/BiConsumer;
     153: invokestatic  #124                // Method setter:(Ljava/util/function/BiConsumer;)Ljava/util/function/BiConsumer;
     156: invokevirtual #125                // Method software/amazon/awssdk/core/SdkField$Builder.setter:(Ljava/util/function/BiConsumer;)Lsoftware/amazon/awssdk/core/SdkField$Builder;
     159: iconst_1
     160: anewarray     #126                // class software/amazon/awssdk/core/traits/Trait
     163: dup
     164: iconst_0
     165: invokestatic  #127                // Method software/amazon/awssdk/core/traits/LocationTrait.builder:()Lsoftware/amazon/awssdk/core/traits/LocationTrait$Builder;
     168: getstatic     #128                // Field software/amazon/awssdk/core/protocol/MarshallLocation.PAYLOAD:Lsoftware/amazon/awssdk/core/protocol/MarshallLocation;
     171: invokevirtual #129                // Method software/amazon/awssdk/core/traits/LocationTrait$Builder.location:(Lsoftware/amazon/awssdk/core/protocol/MarshallLocation;)Lsoftware/amazon/awssdk/core/traits/LocationTrait$Builder;
     174: ldc           #86                 // String Arn
     176: invokevirtual #130                // Method software/amazon/awssdk/core/traits/LocationTrait$Builder.locationName:(Ljava/lang/String;)Lsoftware/amazon/awssdk/core/traits/LocationTrait$Builder;
     179: invokevirtual #131                // Method software/amazon/awssdk/core/traits/LocationTrait$Builder.build:()Lsoftware/amazon/awssdk/core/traits/LocationTrait;
     182: aastore
     183: invokevirtual #138                // Method software/amazon/awssdk/core/SdkField$Builder.traits:([Lsoftware/amazon/awssdk/core/traits/Trait;)Lsoftware/amazon/awssdk/core/SdkField$Builder;
     186: invokevirtual #139                // Method software/amazon/awssdk/core/SdkField$Builder.build:()Lsoftware/amazon/awssdk/core/SdkField;
     189: putstatic     #146                // Field ARN_FIELD:Lsoftware/amazon/awssdk/core/SdkField;
     192: getstatic     #143                // Field software/amazon/awssdk/core/protocol/MarshallingType.STRING:Lsoftware/amazon/awssdk/core/protocol/MarshallingType;
     195: invokestatic  #118                // Method software/amazon/awssdk/core/SdkField.builder:(Lsoftware/amazon/awssdk/core/protocol/MarshallingType;)Lsoftware/amazon/awssdk/core/SdkField$Builder;
     198: ldc           #87                 // String Brand
     200: invokevirtual #119                // Method software/amazon/awssdk/core/SdkField$Builder.memberName:(Ljava/lang/String;)Lsoftware/amazon/awssdk/core/SdkField$Builder;
     203: invokedynamic #147,  0            // InvokeDynamic #7:apply:()Ljava/util/function/Function;
     208: invokestatic  #121                // Method getter:(Ljava/util/function/Function;)Ljava/util/function/Function;
     211: invokevirtual #122                // Method software/amazon/awssdk/core/SdkField$Builder.getter:(Ljava/util/function/Function;)Lsoftware/amazon/awssdk/core/SdkField$Builder;
     214: invokedynamic #148,  0            // InvokeDynamic #8:accept:()Ljava/util/function/BiConsumer;
     219: invokestatic  #124                // Method setter:(Ljava/util/function/BiConsumer;)Ljava/util/function/BiConsumer;
     222: invokevirtual #125                // Method software/amazon/awssdk/core/SdkField$Builder.setter:(Ljava/util/function/BiConsumer;)Lsoftware/amazon/awssdk/core/SdkField$Builder;
     225: iconst_1
     226: anewarray     #126                // class software/amazon/awssdk/core/traits/Trait
     229: dup
     230: iconst_0
     231: invokestatic  #127                // Method software/amazon/awssdk/core/traits/LocationTrait.builder:()Lsoftware/amazon/awssdk/core/traits/LocationTrait$Builder;
     234: getstatic     #128                // Field software/amazon/awssdk/core/protocol/MarshallLocation.PAYLOAD:Lsoftware/amazon/awssdk/core/protocol/MarshallLocation;
     237: invokevirtual #129                // Method software/amazon/awssdk/core/traits/LocationTrait$Builder.location:(Lsoftware/amazon/awssdk/core/protocol/MarshallLocation;)Lsoftware/amazon/awssdk/core/traits/LocationTrait$Builder;
     240: ldc           #87                 // String Brand
     242: invokevirtual #130                // Method software/amazon/awssdk/core/traits/LocationTrait$Builder.locationName:(Ljava/lang/String;)Lsoftware/amazon/awssdk/core/traits/LocationTrait$Builder;
     245: invokevirtual #131                // Method software/amazon/awssdk/core/traits/LocationTrait$Builder.build:()Lsoftware/amazon/awssdk/core/traits/LocationTrait;
     248: aastore
     249: invokevirtual #138                // Method software/amazon/awssdk/core/SdkField$Builder.traits:([Lsoftware/amazon/awssdk/core/traits/Trait;)Lsoftware/amazon/awssdk/core/SdkField$Builder;
     252: invokevirtual #139                // Method software/amazon/awssdk/core/SdkField$Builder.build:()Lsoftware/amazon/awssdk/core/SdkField;
     255: putstatic     #149                // Field BRAND_FIELD:Lsoftware/amazon/awssdk/core/SdkField;
     258: getstatic     #150                // Field software/amazon/awssdk/core/protocol/MarshallingType.INSTANT:Lsoftware/amazon/awssdk/core/protocol/MarshallingType;
     261: invokestatic  #118                // Method software/amazon/awssdk/core/SdkField.builder:(Lsoftware/amazon/awssdk/core/protocol/MarshallingType;)Lsoftware/amazon/awssdk/core/SdkField$Builder;
     264: ldc           #88                 // String CreatedTime
     266: invokevirtual #119                // Method software/amazon/awssdk/core/SdkField$Builder.memberName:(Ljava/lang/String;)Lsoftware/amazon/awssdk/core/SdkField$Builder;
     269: invokedynamic #151,  0            // InvokeDynamic #9:apply:()Ljava/util/function/Function;
     274: invokestatic  #121                // Method getter:(Ljava/util/function/Function;)Ljava/util/function/Function;
     277: invokevirtual #122                // Method software/amazon/awssdk/core/SdkField$Builder.getter:(Ljava/util/function/Function;)Lsoftware/amazon/awssdk/core/SdkField$Builder;
     280: invokedynamic #152,  0            // InvokeDynamic #10:accept:()Ljava/util/function/BiConsumer;
     285: invokestatic  #124                // Method setter:(Ljava/util/function/BiConsumer;)Ljava/util/function/BiConsumer;
     288: invokevirtual #125                // Method software/amazon/awssdk/core/SdkField$Builder.setter:(Ljava/util/function/BiConsumer;)Lsoftware/amazon/awssdk/core/SdkField$Builder;
     291: iconst_1
     292: anewarray     #126                // class software/amazon/awssdk/core/traits/Trait
     295: dup
     296: iconst_0
     297: invokestatic  #127                // Method software/amazon/awssdk/core/traits/LocationTrait.builder:()Lsoftware/amazon/awssdk/core/traits/LocationTrait$Builder;
     300: getstatic     #128                // Field software/amazon/awssdk/core/protocol/MarshallLocation.PAYLOAD:Lsoftware/amazon/awssdk/core/protocol/MarshallLocation;
     303: invokevirtual #129                // Method software/amazon/awssdk/core/traits/LocationTrait$Builder.location:(Lsoftware/amazon/awssdk/core/protocol/MarshallLocation;)Lsoftware/amazon/awssdk/core/traits/LocationTrait$Builder;
     306: ldc           #88                 // String CreatedTime
     308: invokevirtual #130                // Method software/amazon/awssdk/core/traits/LocationTrait$Builder.locationName:(Ljava/lang/String;)Lsoftware/amazon/awssdk/core/traits/LocationTrait$Builder;
     311: invokevirtual #131                // Method software/amazon/awssdk/core/traits/LocationTrait$Builder.build:()Lsoftware/amazon/awssdk/core/traits/LocationTrait;
     314: aastore
     315: invokevirtual #138                // Method software/amazon/awssdk/core/SdkField$Builder.traits:([Lsoftware/amazon/awssdk/core/traits/Trait;)Lsoftware/amazon/awssdk/core/SdkField$Builder;
     318: invokevirtual #139                // Method software/amazon/awssdk/core/SdkField$Builder.build:()Lsoftware/amazon/awssdk/core/SdkField;
     321: putstatic     #153                // Field CREATED_TIME_FIELD:Lsoftware/amazon/awssdk/core/SdkField;
     324: getstatic     #134                // Field software/amazon/awssdk/core/protocol/MarshallingType.SDK_POJO:Lsoftware/amazon/awssdk/core/protocol/MarshallingType;
     327: invokestatic  #118                // Method software/amazon/awssdk/core/SdkField.builder:(Lsoftware/amazon/awssdk/core/protocol/MarshallingType;)Lsoftware/amazon/awssdk/core/SdkField$Builder;
     330: ldc           #89                 // String CurrentNetworkingStatus
     332: invokevirtual #119                // Method software/amazon/awssdk/core/SdkField$Builder.memberName:(Ljava/lang/String;)Lsoftware/amazon/awssdk/core/SdkField$Builder;
     335: invokedynamic #154,  0            // InvokeDynamic #11:apply:()Ljava/util/function/Function;
     340: invokestatic  #121                // Method getter:(Ljava/util/function/Function;)Ljava/util/function/Function;
     343: invokevirtual #122                // Method software/amazon/awssdk/core/SdkField$Builder.getter:(Ljava/util/function/Function;)Lsoftware/amazon/awssdk/core/SdkField$Builder;
     346: invokedynamic #155,  0            // InvokeDynamic #12:accept:()Ljava/util/function/BiConsumer;
     351: invokestatic  #124                // Method setter:(Ljava/util/function/BiConsumer;)Ljava/util/function/BiConsumer;
     354: invokevirtual #125                // Method software/amazon/awssdk/core/SdkField$Builder.setter:(Ljava/util/function/BiConsumer;)Lsoftware/amazon/awssdk/core/SdkField$Builder;
     357: invokedynamic #156,  0            // InvokeDynamic #13:get:()Ljava/util/function/Supplier;
     362: invokevirtual #136                // Method software/amazon/awssdk/core/SdkField$Builder.constructor:(Ljava/util/function/Supplier;)Lsoftware/amazon/awssdk/core/SdkField$Builder;
     365: iconst_1
     366: anewarray     #126                // class software/amazon/awssdk/core/traits/Trait
     369: dup
     370: iconst_0
     371: invokestatic  #127                // Method software/amazon/awssdk/core/traits/LocationTrait.builder:()Lsoftware/amazon/awssdk/core/traits/LocationTrait$Builder;
     374: getstatic     #128                // Field software/amazon/awssdk/core/protocol/MarshallLocation.PAYLOAD:Lsoftware/amazon/awssdk/core/protocol/MarshallLocation;
     377: invokevirtual #129                // Method software/amazon/awssdk/core/traits/LocationTrait$Builder.location:(Lsoftware/amazon/awssdk/core/protocol/MarshallLocation;)Lsoftware/amazon/awssdk/core/traits/LocationTrait$Builder;
     380: ldc           #89                 // String CurrentNetworkingStatus
     382: invokevirtual #130                // Method software/amazon/awssdk/core/traits/LocationTrait$Builder.locationName:(Ljava/lang/String;)Lsoftware/amazon/awssdk/core/traits/LocationTrait$Builder;
     385: invokevirtual #131                // Method software/amazon/awssdk/core/traits/LocationTrait$Builder.build:()Lsoftware/amazon/awssdk/core/traits/LocationTrait;
     388: aastore
     389: invokevirtual #138                // Method software/amazon/awssdk/core/SdkField$Builder.traits:([Lsoftware/amazon/awssdk/core/traits/Trait;)Lsoftware/amazon/awssdk/core/SdkField$Builder;
     392: invokevirtual #139                // Method software/amazon/awssdk/core/SdkField$Builder.build:()Lsoftware/amazon/awssdk/core/SdkField;
     395: putstatic     #157                // Field CURRENT_NETWORKING_STATUS_FIELD:Lsoftware/amazon/awssdk/core/SdkField;
     398: getstatic     #143                // Field software/amazon/awssdk/core/protocol/MarshallingType.STRING:Lsoftware/amazon/awssdk/core/protocol/MarshallingType;
     401: invokestatic  #118                // Method software/amazon/awssdk/core/SdkField.builder:(Lsoftware/amazon/awssdk/core/protocol/MarshallingType;)Lsoftware/amazon/awssdk/core/SdkField$Builder;
     404: ldc           #90                 // String CurrentSoftware
     406: invokevirtual #119                // Method software/amazon/awssdk/core/SdkField$Builder.memberName:(Ljava/lang/String;)Lsoftware/amazon/awssdk/core/SdkField$Builder;
     409: invokedynamic #158,  0            // InvokeDynamic #14:apply:()Ljava/util/function/Function;
     414: invokestatic  #121                // Method getter:(Ljava/util/function/Function;)Ljava/util/function/Function;
     417: invokevirtual #122                // Method software/amazon/awssdk/core/SdkField$Builder.getter:(Ljava/util/function/Function;)Lsoftware/amazon/awssdk/core/SdkField$Builder;
     420: invokedynamic #159,  0            // InvokeDynamic #15:accept:()Ljava/util/function/BiConsumer;
     425: invokestatic  #124                // Method setter:(Ljava/util/function/BiConsumer;)Ljava/util/function/BiConsumer;
     428: invokevirtual #125                // Method software/amazon/awssdk/core/SdkField$Builder.setter:(Ljava/util/function/BiConsumer;)Lsoftware/amazon/awssdk/core/SdkField$Builder;
     431: iconst_1
     432: anewarray     #126                // class software/amazon/awssdk/core/traits/Trait
     435: dup
     436: iconst_0
     437: invokestatic  #127                // Method software/amazon/awssdk/core/traits/LocationTrait.builder:()Lsoftware/amazon/awssdk/core/traits/LocationTrait$Builder;
     440: getstatic     #128                // Field software/amazon/awssdk/core/protocol/MarshallLocation.PAYLOAD:Lsoftware/amazon/awssdk/core/protocol/MarshallLocation;
     443: invokevirtual #129                // Method software/amazon/awssdk/core/traits/LocationTrait$Builder.location:(Lsoftware/amazon/awssdk/core/protocol/MarshallLocation;)Lsoftware/amazon/awssdk/core/traits/LocationTrait$Builder;
     446: ldc           #90                 // String CurrentSoftware
     448: invokevirtual #130                // Method software/amazon/awssdk/core/traits/LocationTrait$Builder.locationName:(Ljava/lang/String;)Lsoftware/amazon/awssdk/core/traits/LocationTrait$Builder;
     451: invokevirtual #131                // Method software/amazon/awssdk/core/traits/LocationTrait$Builder.build:()Lsoftware/amazon/awssdk/core/traits/LocationTrait;
     454: aastore
     455: invokevirtual #138                // Method software/amazon/awssdk/core/SdkField$Builder.traits:([Lsoftware/amazon/awssdk/core/traits/Trait;)Lsoftware/amazon/awssdk/core/SdkField$Builder;
     458: invokevirtual #139                // Method software/amazon/awssdk/core/SdkField$Builder.build:()Lsoftware/amazon/awssdk/core/SdkField;
     461: putstatic     #160                // Field CURRENT_SOFTWARE_FIELD:Lsoftware/amazon/awssdk/core/SdkField;
     464: getstatic     #143                // Field software/amazon/awssdk/core/protocol/MarshallingType.STRING:Lsoftware/amazon/awssdk/core/protocol/MarshallingType;
     467: invokestatic  #118                // Method software/amazon/awssdk/core/SdkField.builder:(Lsoftware/amazon/awssdk/core/protocol/MarshallingType;)Lsoftware/amazon/awssdk/core/SdkField$Builder;
     470: ldc           #91                 // String Description
     472: invokevirtual #119                // Method software/amazon/awssdk/core/SdkField$Builder.memberName:(Ljava/lang/String;)Lsoftware/amazon/awssdk/core/SdkField$Builder;
     475: invokedynamic #161,  0            // InvokeDynamic #16:apply:()Ljava/util/function/Function;
     480: invokestatic  #121                // Method getter:(Ljava/util/function/Function;)Ljava/util/function/Function;
     483: invokevirtual #122                // Method software/amazon/awssdk/core/SdkField$Builder.getter:(Ljava/util/function/Function;)Lsoftware/amazon/awssdk/core/SdkField$Builder;
     486: invokedynamic #162,  0            // InvokeDynamic #17:accept:()Ljava/util/function/BiConsumer;
     491: invokestatic  #124                // Method setter:(Ljava/util/function/BiConsumer;)Ljava/util/function/BiConsumer;
     494: invokevirtual #125                // Method software/amazon/awssdk/core/SdkField$Builder.setter:(Ljava/util/function/BiConsumer;)Lsoftware/amazon/awssdk/core/SdkField$Builder;
     497: iconst_1
     498: anewarray     #126                // class software/amazon/awssdk/core/traits/Trait
     501: dup
     502: iconst_0
     503: invokestatic  #127                // Method software/amazon/awssdk/core/traits/LocationTrait.builder:()Lsoftware/amazon/awssdk/core/traits/LocationTrait$Builder;
     506: getstatic     #128                // Field software/amazon/awssdk/core/protocol/MarshallLocation.PAYLOAD:Lsoftware/amazon/awssdk/core/protocol/MarshallLocation;
     509: invokevirtual #129                // Method software/amazon/awssdk/core/traits/LocationTrait$Builder.location:(Lsoftware/amazon/awssdk/core/protocol/MarshallLocation;)Lsoftware/amazon/awssdk/core/traits/LocationTrait$Builder;
     512: ldc           #91                 // String Description
     514: invokevirtual #130                // Method software/amazon/awssdk/core/traits/LocationTrait$Builder.locationName:(Ljava/lang/String;)Lsoftware/amazon/awssdk/core/traits/LocationTrait$Builder;
     517: invokevirtual #131                // Method software/amazon/awssdk/core/traits/LocationTrait$Builder.build:()Lsoftware/amazon/awssdk/core/traits/LocationTrait;
     520: aastore
     521: invokevirtual #138                // Method software/amazon/awssdk/core/SdkField$Builder.traits:([Lsoftware/amazon/awssdk/core/traits/Trait;)Lsoftware/amazon/awssdk/core/SdkField$Builder;
     524: invokevirtual #139                // Method software/amazon/awssdk/core/SdkField$Builder.build:()Lsoftware/amazon/awssdk/core/SdkField;
     527: putstatic     #163                // Field DESCRIPTION_FIELD:Lsoftware/amazon/awssdk/core/SdkField;
     530: getstatic     #143                // Field software/amazon/awssdk/core/protocol/MarshallingType.STRING:Lsoftware/amazon/awssdk/core/protocol/MarshallingType;
     533: invokestatic  #118                // Method software/amazon/awssdk/core/SdkField.builder:(Lsoftware/amazon/awssdk/core/protocol/MarshallingType;)Lsoftware/amazon/awssdk/core/SdkField$Builder;
     536: ldc           #92                 // String DeviceAggregatedStatus
     538: invokevirtual #119                // Method software/amazon/awssdk/core/SdkField$Builder.memberName:(Ljava/lang/String;)Lsoftware/amazon/awssdk/core/SdkField$Builder;
     541: invokedynamic #164,  0            // InvokeDynamic #18:apply:()Ljava/util/function/Function;
     546: invokestatic  #121                // Method getter:(Ljava/util/function/Function;)Ljava/util/function/Function;
     549: invokevirtual #122                // Method software/amazon/awssdk/core/SdkField$Builder.getter:(Ljava/util/function/Function;)Lsoftware/amazon/awssdk/core/SdkField$Builder;
     552: invokedynamic #165,  0            // InvokeDynamic #19:accept:()Ljava/util/function/BiConsumer;
     557: invokestatic  #124                // Method setter:(Ljava/util/function/BiConsumer;)Ljava/util/function/BiConsumer;
     560: invokevirtual #125                // Method software/amazon/awssdk/core/SdkField$Builder.setter:(Ljava/util/function/BiConsumer;)Lsoftware/amazon/awssdk/core/SdkField$Builder;
     563: iconst_1
     564: anewarray     #126                // class software/amazon/awssdk/core/traits/Trait
     567: dup
     568: iconst_0
     569: invokestatic  #127                // Method software/amazon/awssdk/core/traits/LocationTrait.builder:()Lsoftware/amazon/awssdk/core/traits/LocationTrait$Builder;
     572: getstatic     #128                // Field software/amazon/awssdk/core/protocol/MarshallLocation.PAYLOAD:Lsoftware/amazon/awssdk/core/protocol/MarshallLocation;
     575: invokevirtual #129                // Method software/amazon/awssdk/core/traits/LocationTrait$Builder.location:(Lsoftware/amazon/awssdk/core/protocol/MarshallLocation;)Lsoftware/amazon/awssdk/core/traits/LocationTrait$Builder;
     578: ldc           #92                 // String DeviceAggregatedStatus
     580: invokevirtual #130                // Method software/amazon/awssdk/core/traits/LocationTrait$Builder.locationName:(Ljava/lang/String;)Lsoftware/amazon/awssdk/core/traits/LocationTrait$Builder;
     583: invokevirtual #131                // Method software/amazon/awssdk/core/traits/LocationTrait$Builder.build:()Lsoftware/amazon/awssdk/core/traits/LocationTrait;
     586: aastore
     587: invokevirtual #138                // Method software/amazon/awssdk/core/SdkField$Builder.traits:([Lsoftware/amazon/awssdk/core/traits/Trait;)Lsoftware/amazon/awssdk/core/SdkField$Builder;
     590: invokevirtual #139                // Method software/amazon/awssdk/core/SdkField$Builder.build:()Lsoftware/amazon/awssdk/core/SdkField;
     593: putstatic     #166                // Field DEVICE_AGGREGATED_STATUS_FIELD:Lsoftware/amazon/awssdk/core/SdkField;
     596: getstatic     #143                // Field software/amazon/awssdk/core/protocol/MarshallingType.STRING:Lsoftware/amazon/awssdk/core/protocol/MarshallingType;
     599: invokestatic  #118                // Method software/amazon/awssdk/core/SdkField.builder:(Lsoftware/amazon/awssdk/core/protocol/MarshallingType;)Lsoftware/amazon/awssdk/core/SdkField$Builder;
     602: ldc           #93                 // String DeviceConnectionStatus
     604: invokevirtual #119                // Method software/amazon/awssdk/core/SdkField$Builder.memberName:(Ljava/lang/String;)Lsoftware/amazon/awssdk/core/SdkField$Builder;
     607: invokedynamic #167,  0            // InvokeDynamic #20:apply:()Ljava/util/function/Function;
     612: invokestatic  #121                // Method getter:(Ljava/util/function/Function;)Ljava/util/function/Function;
     615: invokevirtual #122                // Method software/amazon/awssdk/core/SdkField$Builder.getter:(Ljava/util/function/Function;)Lsoftware/amazon/awssdk/core/SdkField$Builder;
     618: invokedynamic #168,  0            // InvokeDynamic #21:accept:()Ljava/util/function/BiConsumer;
     623: invokestatic  #124                // Method setter:(Ljava/util/function/BiConsumer;)Ljava/util/function/BiConsumer;
     626: invokevirtual #125                // Method software/amazon/awssdk/core/SdkField$Builder.setter:(Ljava/util/function/BiConsumer;)Lsoftware/amazon/awssdk/core/SdkField$Builder;
     629: iconst_1
     630: anewarray     #126                // class software/amazon/awssdk/core/traits/Trait
     633: dup
     634: iconst_0
     635: invokestatic  #127                // Method software/amazon/awssdk/core/traits/LocationTrait.builder:()Lsoftware/amazon/awssdk/core/traits/LocationTrait$Builder;
     638: getstatic     #128                // Field software/amazon/awssdk/core/protocol/MarshallLocation.PAYLOAD:Lsoftware/amazon/awssdk/core/protocol/MarshallLocation;
     641: invokevirtual #129                // Method software/amazon/awssdk/core/traits/LocationTrait$Builder.location:(Lsoftware/amazon/awssdk/core/protocol/MarshallLocation;)Lsoftware/amazon/awssdk/core/traits/LocationTrait$Builder;
     644: ldc           #93                 // String DeviceConnectionStatus
     646: invokevirtual #130                // Method software/amazon/awssdk/core/traits/LocationTrait$Builder.locationName:(Ljava/lang/String;)Lsoftware/amazon/awssdk/core/traits/LocationTrait$Builder;
     649: invokevirtual #131                // Method software/amazon/awssdk/core/traits/LocationTrait$Builder.build:()Lsoftware/amazon/awssdk/core/traits/LocationTrait;
     652: aastore
     653: invokevirtual #138                // Method software/amazon/awssdk/core/SdkField$Builder.traits:([Lsoftware/amazon/awssdk/core/traits/Trait;)Lsoftware/amazon/awssdk/core/SdkField$Builder;
     656: invokevirtual #139                // Method software/amazon/awssdk/core/SdkField$Builder.build:()Lsoftware/amazon/awssdk/core/SdkField;
     659: putstatic     #169                // Field DEVICE_CONNECTION_STATUS_FIELD:Lsoftware/amazon/awssdk/core/SdkField;
     662: getstatic     #143                // Field software/amazon/awssdk/core/protocol/MarshallingType.STRING:Lsoftware/amazon/awssdk/core/protocol/MarshallingType;
     665: invokestatic  #118                // Method software/amazon/awssdk/core/SdkField.builder:(Lsoftware/amazon/awssdk/core/protocol/MarshallingType;)Lsoftware/amazon/awssdk/core/SdkField$Builder;
     668: ldc           #94                 // String DeviceId
     670: invokevirtual #119                // Method software/amazon/awssdk/core/SdkField$Builder.memberName:(Ljava/lang/String;)Lsoftware/amazon/awssdk/core/SdkField$Builder;
     673: invokedynamic #170,  0            // InvokeDynamic #22:apply:()Ljava/util/function/Function;
     678: invokestatic  #121                // Method getter:(Ljava/util/function/Function;)Ljava/util/function/Function;
     681: invokevirtual #122                // Method software/amazon/awssdk/core/SdkField$Builder.getter:(Ljava/util/function/Function;)Lsoftware/amazon/awssdk/core/SdkField$Builder;
     684: invokedynamic #171,  0            // InvokeDynamic #23:accept:()Ljava/util/function/BiConsumer;
     689: invokestatic  #124                // Method setter:(Ljava/util/function/BiConsumer;)Ljava/util/function/BiConsumer;
     692: invokevirtual #125                // Method software/amazon/awssdk/core/SdkField$Builder.setter:(Ljava/util/function/BiConsumer;)Lsoftware/amazon/awssdk/core/SdkField$Builder;
     695: iconst_1
     696: anewarray     #126                // class software/amazon/awssdk/core/traits/Trait
     699: dup
     700: iconst_0
     701: invokestatic  #127                // Method software/amazon/awssdk/core/traits/LocationTrait.builder:()Lsoftware/amazon/awssdk/core/traits/LocationTrait$Builder;
     704: getstatic     #128                // Field software/amazon/awssdk/core/protocol/MarshallLocation.PAYLOAD:Lsoftware/amazon/awssdk/core/protocol/MarshallLocation;
     707: invokevirtual #129                // Method software/amazon/awssdk/core/traits/LocationTrait$Builder.location:(Lsoftware/amazon/awssdk/core/protocol/MarshallLocation;)Lsoftware/amazon/awssdk/core/traits/LocationTrait$Builder;
     710: ldc           #94                 // String DeviceId
     712: invokevirtual #130                // Method software/amazon/awssdk/core/traits/LocationTrait$Builder.locationName:(Ljava/lang/String;)Lsoftware/amazon/awssdk/core/traits/LocationTrait$Builder;
     715: invokevirtual #131                // Method software/amazon/awssdk/core/traits/LocationTrait$Builder.build:()Lsoftware/amazon/awssdk/core/traits/LocationTrait;
     718: aastore
     719: invokevirtual #138                // Method software/amazon/awssdk/core/SdkField$Builder.traits:([Lsoftware/amazon/awssdk/core/traits/Trait;)Lsoftware/amazon/awssdk/core/SdkField$Builder;
     722: invokevirtual #139                // Method software/amazon/awssdk/core/SdkField$Builder.build:()Lsoftware/amazon/awssdk/core/SdkField;
     725: putstatic     #172                // Field DEVICE_ID_FIELD:Lsoftware/amazon/awssdk/core/SdkField;
     728: getstatic     #143                // Field software/amazon/awssdk/core/protocol/MarshallingType.STRING:Lsoftware/amazon/awssdk/core/protocol/MarshallingType;
     731: invokestatic  #118                // Method software/amazon/awssdk/core/SdkField.builder:(Lsoftware/amazon/awssdk/core/protocol/MarshallingType;)Lsoftware/amazon/awssdk/core/SdkField$Builder;
     734: ldc           #95                 // String LatestAlternateSoftware
     736: invokevirtual #119                // Method software/amazon/awssdk/core/SdkField$Builder.memberName:(Ljava/lang/String;)Lsoftware/amazon/awssdk/core/SdkField$Builder;
     739: invokedynamic #173,  0            // InvokeDynamic #24:apply:()Ljava/util/function/Function;
     744: invokestatic  #121                // Method getter:(Ljava/util/function/Function;)Ljava/util/function/Function;
     747: invokevirtual #122                // Method software/amazon/awssdk/core/SdkField$Builder.getter:(Ljava/util/function/Function;)Lsoftware/amazon/awssdk/core/SdkField$Builder;
     750: invokedynamic #174,  0            // InvokeDynamic #25:accept:()Ljava/util/function/BiConsumer;
     755: invokestatic  #124                // Method setter:(Ljava/util/function/BiConsumer;)Ljava/util/function/BiConsumer;
     758: invokevirtual #125                // Method software/amazon/awssdk/core/SdkField$Builder.setter:(Ljava/util/function/BiConsumer;)Lsoftware/amazon/awssdk/core/SdkField$Builder;
     761: iconst_1
     762: anewarray     #126                // class software/amazon/awssdk/core/traits/Trait
     765: dup
     766: iconst_0
     767: invokestatic  #127                // Method software/amazon/awssdk/core/traits/LocationTrait.builder:()Lsoftware/amazon/awssdk/core/traits/LocationTrait$Builder;
     770: getstatic     #128                // Field software/amazon/awssdk/core/protocol/MarshallLocation.PAYLOAD:Lsoftware/amazon/awssdk/core/protocol/MarshallLocation;
     773: invokevirtual #129                // Method software/amazon/awssdk/core/traits/LocationTrait$Builder.location:(Lsoftware/amazon/awssdk/core/protocol/MarshallLocation;)Lsoftware/amazon/awssdk/core/traits/LocationTrait$Builder;
     776: ldc           #95                 // String LatestAlternateSoftware
     778: invokevirtual #130                // Method software/amazon/awssdk/core/traits/LocationTrait$Builder.locationName:(Ljava/lang/String;)Lsoftware/amazon/awssdk/core/traits/LocationTrait$Builder;
     781: invokevirtual #131                // Method software/amazon/awssdk/core/traits/LocationTrait$Builder.build:()Lsoftware/amazon/awssdk/core/traits/LocationTrait;
     784: aastore
     785: invokevirtual #138                // Method software/amazon/awssdk/core/SdkField$Builder.traits:([Lsoftware/amazon/awssdk/core/traits/Trait;)Lsoftware/amazon/awssdk/core/SdkField$Builder;
     788: invokevirtual #139                // Method software/amazon/awssdk/core/SdkField$Builder.build:()Lsoftware/amazon/awssdk/core/SdkField;
     791: putstatic     #175                // Field LATEST_ALTERNATE_SOFTWARE_FIELD:Lsoftware/amazon/awssdk/core/SdkField;
     794: getstatic     #134                // Field software/amazon/awssdk/core/protocol/MarshallingType.SDK_POJO:Lsoftware/amazon/awssdk/core/protocol/MarshallingType;
     797: invokestatic  #118                // Method software/amazon/awssdk/core/SdkField.builder:(Lsoftware/amazon/awssdk/core/protocol/MarshallingType;)Lsoftware/amazon/awssdk/core/SdkField$Builder;
     800: ldc           #96                 // String LatestDeviceJob
     802: invokevirtual #119                // Method software/amazon/awssdk/core/SdkField$Builder.memberName:(Ljava/lang/String;)Lsoftware/amazon/awssdk/core/SdkField$Builder;
     805: invokedynamic #176,  0            // InvokeDynamic #26:apply:()Ljava/util/function/Function;
     810: invokestatic  #121                // Method getter:(Ljava/util/function/Function;)Ljava/util/function/Function;
     813: invokevirtual #122                // Method software/amazon/awssdk/core/SdkField$Builder.getter:(Ljava/util/function/Function;)Lsoftware/amazon/awssdk/core/SdkField$Builder;
     816: invokedynamic #177,  0            // InvokeDynamic #27:accept:()Ljava/util/function/BiConsumer;
     821: invokestatic  #124                // Method setter:(Ljava/util/function/BiConsumer;)Ljava/util/function/BiConsumer;
     824: invokevirtual #125                // Method software/amazon/awssdk/core/SdkField$Builder.setter:(Ljava/util/function/BiConsumer;)Lsoftware/amazon/awssdk/core/SdkField$Builder;
     827: invokedynamic #178,  0            // InvokeDynamic #28:get:()Ljava/util/function/Supplier;
     832: invokevirtual #136                // Method software/amazon/awssdk/core/SdkField$Builder.constructor:(Ljava/util/function/Supplier;)Lsoftware/amazon/awssdk/core/SdkField$Builder;
     835: iconst_1
     836: anewarray     #126                // class software/amazon/awssdk/core/traits/Trait
     839: dup
     840: iconst_0
     841: invokestatic  #127                // Method software/amazon/awssdk/core/traits/LocationTrait.builder:()Lsoftware/amazon/awssdk/core/traits/LocationTrait$Builder;
     844: getstatic     #128                // Field software/amazon/awssdk/core/protocol/MarshallLocation.PAYLOAD:Lsoftware/amazon/awssdk/core/protocol/MarshallLocation;
     847: invokevirtual #129                // Method software/amazon/awssdk/core/traits/LocationTrait$Builder.location:(Lsoftware/amazon/awssdk/core/protocol/MarshallLocation;)Lsoftware/amazon/awssdk/core/traits/LocationTrait$Builder;
     850: ldc           #96                 // String LatestDeviceJob
     852: invokevirtual #130                // Method software/amazon/awssdk/core/traits/LocationTrait$Builder.locationName:(Ljava/lang/String;)Lsoftware/amazon/awssdk/core/traits/LocationTrait$Builder;
     855: invokevirtual #131                // Method software/amazon/awssdk/core/traits/LocationTrait$Builder.build:()Lsoftware/amazon/awssdk/core/traits/LocationTrait;
     858: aastore
     859: invokevirtual #138                // Method software/amazon/awssdk/core/SdkField$Builder.traits:([Lsoftware/amazon/awssdk/core/traits/Trait;)Lsoftware/amazon/awssdk/core/SdkField$Builder;
     862: invokevirtual #139                // Method software/amazon/awssdk/core/SdkField$Builder.build:()Lsoftware/amazon/awssdk/core/SdkField;
     865: putstatic     #179                // Field LATEST_DEVICE_JOB_FIELD:Lsoftware/amazon/awssdk/core/SdkField;
     868: getstatic     #143                // Field software/amazon/awssdk/core/protocol/MarshallingType.STRING:Lsoftware/amazon/awssdk/core/protocol/MarshallingType;
     871: invokestatic  #118                // Method software/amazon/awssdk/core/SdkField.builder:(Lsoftware/amazon/awssdk/core/protocol/MarshallingType;)Lsoftware/amazon/awssdk/core/SdkField$Builder;
     874: ldc           #97                 // String LatestSoftware
     876: invokevirtual #119                // Method software/amazon/awssdk/core/SdkField$Builder.memberName:(Ljava/lang/String;)Lsoftware/amazon/awssdk/core/SdkField$Builder;
     879: invokedynamic #180,  0            // InvokeDynamic #29:apply:()Ljava/util/function/Function;
     884: invokestatic  #121                // Method getter:(Ljava/util/function/Function;)Ljava/util/function/Function;
     887: invokevirtual #122                // Method software/amazon/awssdk/core/SdkField$Builder.getter:(Ljava/util/function/Function;)Lsoftware/amazon/awssdk/core/SdkField$Builder;
     890: invokedynamic #181,  0            // InvokeDynamic #30:accept:()Ljava/util/function/BiConsumer;
     895: invokestatic  #124                // Method setter:(Ljava/util/function/BiConsumer;)Ljava/util/function/BiConsumer;
     898: invokevirtual #125                // Method software/amazon/awssdk/core/SdkField$Builder.setter:(Ljava/util/function/BiConsumer;)Lsoftware/amazon/awssdk/core/SdkField$Builder;
     901: iconst_1
     902: anewarray     #126                // class software/amazon/awssdk/core/traits/Trait
     905: dup
     906: iconst_0
     907: invokestatic  #127                // Method software/amazon/awssdk/core/traits/LocationTrait.builder:()Lsoftware/amazon/awssdk/core/traits/LocationTrait$Builder;
     910: getstatic     #128                // Field software/amazon/awssdk/core/protocol/MarshallLocation.PAYLOAD:Lsoftware/amazon/awssdk/core/protocol/MarshallLocation;
     913: invokevirtual #129                // Method software/amazon/awssdk/core/traits/LocationTrait$Builder.location:(Lsoftware/amazon/awssdk/core/protocol/MarshallLocation;)Lsoftware/amazon/awssdk/core/traits/LocationTrait$Builder;
     916: ldc           #97                 // String LatestSoftware
     918: invokevirtual #130                // Method software/amazon/awssdk/core/traits/LocationTrait$Builder.locationName:(Ljava/lang/String;)Lsoftware/amazon/awssdk/core/traits/LocationTrait$Builder;
     921: invokevirtual #131                // Method software/amazon/awssdk/core/traits/LocationTrait$Builder.build:()Lsoftware/amazon/awssdk/core/traits/LocationTrait;
     924: aastore
     925: invokevirtual #138                // Method software/amazon/awssdk/core/SdkField$Builder.traits:([Lsoftware/amazon/awssdk/core/traits/Trait;)Lsoftware/amazon/awssdk/core/SdkField$Builder;
     928: invokevirtual #139                // Method software/amazon/awssdk/core/SdkField$Builder.build:()Lsoftware/amazon/awssdk/core/SdkField;
     931: putstatic     #182                // Field LATEST_SOFTWARE_FIELD:Lsoftware/amazon/awssdk/core/SdkField;
     934: getstatic     #150                // Field software/amazon/awssdk/core/protocol/MarshallingType.INSTANT:Lsoftware/amazon/awssdk/core/protocol/MarshallingType;
     937: invokestatic  #118                // Method software/amazon/awssdk/core/SdkField.builder:(Lsoftware/amazon/awssdk/core/protocol/MarshallingType;)Lsoftware/amazon/awssdk/core/SdkField$Builder;
     940: ldc           #98                 // String LeaseExpirationTime
     942: invokevirtual #119                // Method software/amazon/awssdk/core/SdkField$Builder.memberName:(Ljava/lang/String;)Lsoftware/amazon/awssdk/core/SdkField$Builder;
     945: invokedynamic #183,  0            // InvokeDynamic #31:apply:()Ljava/util/function/Function;
     950: invokestatic  #121                // Method getter:(Ljava/util/function/Function;)Ljava/util/function/Function;
     953: invokevirtual #122                // Method software/amazon/awssdk/core/SdkField$Builder.getter:(Ljava/util/function/Function;)Lsoftware/amazon/awssdk/core/SdkField$Builder;
     956: invokedynamic #184,  0            // InvokeDynamic #32:accept:()Ljava/util/function/BiConsumer;
     961: invokestatic  #124                // Method setter:(Ljava/util/function/BiConsumer;)Ljava/util/function/BiConsumer;
     964: invokevirtual #125                // Method software/amazon/awssdk/core/SdkField$Builder.setter:(Ljava/util/function/BiConsumer;)Lsoftware/amazon/awssdk/core/SdkField$Builder;
     967: iconst_1
     968: anewarray     #126                // class software/amazon/awssdk/core/traits/Trait
     971: dup
     972: iconst_0
     973: invokestatic  #127                // Method software/amazon/awssdk/core/traits/LocationTrait.builder:()Lsoftware/amazon/awssdk/core/traits/LocationTrait$Builder;
     976: getstatic     #128                // Field software/amazon/awssdk/core/protocol/MarshallLocation.PAYLOAD:Lsoftware/amazon/awssdk/core/protocol/MarshallLocation;
     979: invokevirtual #129                // Method software/amazon/awssdk/core/traits/LocationTrait$Builder.location:(Lsoftware/amazon/awssdk/core/protocol/MarshallLocation;)Lsoftware/amazon/awssdk/core/traits/LocationTrait$Builder;
     982: ldc           #98                 // String LeaseExpirationTime
     984: invokevirtual #130                // Method software/amazon/awssdk/core/traits/LocationTrait$Builder.locationName:(Ljava/lang/String;)Lsoftware/amazon/awssdk/core/traits/LocationTrait$Builder;
     987: invokevirtual #131                // Method software/amazon/awssdk/core/traits/LocationTrait$Builder.build:()Lsoftware/amazon/awssdk/core/traits/LocationTrait;
     990: aastore
     991: invokevirtual #138                // Method software/amazon/awssdk/core/SdkField$Builder.traits:([Lsoftware/amazon/awssdk/core/traits/Trait;)Lsoftware/amazon/awssdk/core/SdkField$Builder;
     994: invokevirtual #139                // Method software/amazon/awssdk/core/SdkField$Builder.build:()Lsoftware/amazon/awssdk/core/SdkField;
     997: putstatic     #185                // Field LEASE_EXPIRATION_TIME_FIELD:Lsoftware/amazon/awssdk/core/SdkField;
    1000: getstatic     #143                // Field software/amazon/awssdk/core/protocol/MarshallingType.STRING:Lsoftware/amazon/awssdk/core/protocol/MarshallingType;
    1003: invokestatic  #118                // Method software/amazon/awssdk/core/SdkField.builder:(Lsoftware/amazon/awssdk/core/protocol/MarshallingType;)Lsoftware/amazon/awssdk/core/SdkField$Builder;
    1006: ldc           #99                 // String Name
    1008: invokevirtual #119                // Method software/amazon/awssdk/core/SdkField$Builder.memberName:(Ljava/lang/String;)Lsoftware/amazon/awssdk/core/SdkField$Builder;
    1011: invokedynamic #186,  0            // InvokeDynamic #33:apply:()Ljava/util/function/Function;
    1016: invokestatic  #121                // Method getter:(Ljava/util/function/Function;)Ljava/util/function/Function;
    1019: invokevirtual #122                // Method software/amazon/awssdk/core/SdkField$Builder.getter:(Ljava/util/function/Function;)Lsoftware/amazon/awssdk/core/SdkField$Builder;
    1022: invokedynamic #187,  0            // InvokeDynamic #34:accept:()Ljava/util/function/BiConsumer;
    1027: invokestatic  #124                // Method setter:(Ljava/util/function/BiConsumer;)Ljava/util/function/BiConsumer;
    1030: invokevirtual #125                // Method software/amazon/awssdk/core/SdkField$Builder.setter:(Ljava/util/function/BiConsumer;)Lsoftware/amazon/awssdk/core/SdkField$Builder;
    1033: iconst_1
    1034: anewarray     #126                // class software/amazon/awssdk/core/traits/Trait
    1037: dup
    1038: iconst_0
    1039: invokestatic  #127                // Method software/amazon/awssdk/core/traits/LocationTrait.builder:()Lsoftware/amazon/awssdk/core/traits/LocationTrait$Builder;
    1042: getstatic     #128                // Field software/amazon/awssdk/core/protocol/MarshallLocation.PAYLOAD:Lsoftware/amazon/awssdk/core/protocol/MarshallLocation;
    1045: invokevirtual #129                // Method software/amazon/awssdk/core/traits/LocationTrait$Builder.location:(Lsoftware/amazon/awssdk/core/protocol/MarshallLocation;)Lsoftware/amazon/awssdk/core/traits/LocationTrait$Builder;
    1048: ldc           #99                 // String Name
    1050: invokevirtual #130                // Method software/amazon/awssdk/core/traits/LocationTrait$Builder.locationName:(Ljava/lang/String;)Lsoftware/amazon/awssdk/core/traits/LocationTrait$Builder;
    1053: invokevirtual #131                // Method software/amazon/awssdk/core/traits/LocationTrait$Builder.build:()Lsoftware/amazon/awssdk/core/traits/LocationTrait;
    1056: aastore
    1057: invokevirtual #138                // Method software/amazon/awssdk/core/SdkField$Builder.traits:([Lsoftware/amazon/awssdk/core/traits/Trait;)Lsoftware/amazon/awssdk/core/SdkField$Builder;
    1060: invokevirtual #139                // Method software/amazon/awssdk/core/SdkField$Builder.build:()Lsoftware/amazon/awssdk/core/SdkField;
    1063: putstatic     #188                // Field NAME_FIELD:Lsoftware/amazon/awssdk/core/SdkField;
    1066: getstatic     #134                // Field software/amazon/awssdk/core/protocol/MarshallingType.SDK_POJO:Lsoftware/amazon/awssdk/core/protocol/MarshallingType;
    1069: invokestatic  #118                // Method software/amazon/awssdk/core/SdkField.builder:(Lsoftware/amazon/awssdk/core/protocol/MarshallingType;)Lsoftware/amazon/awssdk/core/SdkField$Builder;
    1072: ldc           #100                // String NetworkingConfiguration
    1074: invokevirtual #119                // Method software/amazon/awssdk/core/SdkField$Builder.memberName:(Ljava/lang/String;)Lsoftware/amazon/awssdk/core/SdkField$Builder;
    1077: invokedynamic #189,  0            // InvokeDynamic #35:apply:()Ljava/util/function/Function;
    1082: invokestatic  #121                // Method getter:(Ljava/util/function/Function;)Ljava/util/function/Function;
    1085: invokevirtual #122                // Method software/amazon/awssdk/core/SdkField$Builder.getter:(Ljava/util/function/Function;)Lsoftware/amazon/awssdk/core/SdkField$Builder;
    1088: invokedynamic #190,  0            // InvokeDynamic #36:accept:()Ljava/util/function/BiConsumer;
    1093: invokestatic  #124                // Method setter:(Ljava/util/function/BiConsumer;)Ljava/util/function/BiConsumer;
    1096: invokevirtual #125                // Method software/amazon/awssdk/core/SdkField$Builder.setter:(Ljava/util/function/BiConsumer;)Lsoftware/amazon/awssdk/core/SdkField$Builder;
    1099: invokedynamic #191,  0            // InvokeDynamic #37:get:()Ljava/util/function/Supplier;
    1104: invokevirtual #136                // Method software/amazon/awssdk/core/SdkField$Builder.constructor:(Ljava/util/function/Supplier;)Lsoftware/amazon/awssdk/core/SdkField$Builder;
    1107: iconst_1
    1108: anewarray     #126                // class software/amazon/awssdk/core/traits/Trait
    1111: dup
    1112: iconst_0
    1113: invokestatic  #127                // Method software/amazon/awssdk/core/traits/LocationTrait.builder:()Lsoftware/amazon/awssdk/core/traits/LocationTrait$Builder;
    1116: getstatic     #128                // Field software/amazon/awssdk/core/protocol/MarshallLocation.PAYLOAD:Lsoftware/amazon/awssdk/core/protocol/MarshallLocation;
    1119: invokevirtual #129                // Method software/amazon/awssdk/core/traits/LocationTrait$Builder.location:(Lsoftware/amazon/awssdk/core/protocol/MarshallLocation;)Lsoftware/amazon/awssdk/core/traits/LocationTrait$Builder;
    1122: ldc           #100                // String NetworkingConfiguration
    1124: invokevirtual #130                // Method software/amazon/awssdk/core/traits/LocationTrait$Builder.locationName:(Ljava/lang/String;)Lsoftware/amazon/awssdk/core/traits/LocationTrait$Builder;
    1127: invokevirtual #131                // Method software/amazon/awssdk/core/traits/LocationTrait$Builder.build:()Lsoftware/amazon/awssdk/core/traits/LocationTrait;
    1130: aastore
    1131: invokevirtual #138                // Method software/amazon/awssdk/core/SdkField$Builder.traits:([Lsoftware/amazon/awssdk/core/traits/Trait;)Lsoftware/amazon/awssdk/core/SdkField$Builder;
    1134: invokevirtual #139                // Method software/amazon/awssdk/core/SdkField$Builder.build:()Lsoftware/amazon/awssdk/core/SdkField;
    1137: putstatic     #192                // Field NETWORKING_CONFIGURATION_FIELD:Lsoftware/amazon/awssdk/core/SdkField;
    1140: getstatic     #143                // Field software/amazon/awssdk/core/protocol/MarshallingType.STRING:Lsoftware/amazon/awssdk/core/protocol/MarshallingType;
    1143: invokestatic  #118                // Method software/amazon/awssdk/core/SdkField.builder:(Lsoftware/amazon/awssdk/core/protocol/MarshallingType;)Lsoftware/amazon/awssdk/core/SdkField$Builder;
    1146: ldc           #101                // String ProvisioningStatus
    1148: invokevirtual #119                // Method software/amazon/awssdk/core/SdkField$Builder.memberName:(Ljava/lang/String;)Lsoftware/amazon/awssdk/core/SdkField$Builder;
    1151: invokedynamic #193,  0            // InvokeDynamic #38:apply:()Ljava/util/function/Function;
    1156: invokestatic  #121                // Method getter:(Ljava/util/function/Function;)Ljava/util/function/Function;
    1159: invokevirtual #122                // Method software/amazon/awssdk/core/SdkField$Builder.getter:(Ljava/util/function/Function;)Lsoftware/amazon/awssdk/core/SdkField$Builder;
    1162: invokedynamic #194,  0            // InvokeDynamic #39:accept:()Ljava/util/function/BiConsumer;
    1167: invokestatic  #124                // Method setter:(Ljava/util/function/BiConsumer;)Ljava/util/function/BiConsumer;
    1170: invokevirtual #125                // Method software/amazon/awssdk/core/SdkField$Builder.setter:(Ljava/util/function/BiConsumer;)Lsoftware/amazon/awssdk/core/SdkField$Builder;
    1173: iconst_1
    1174: anewarray     #126                // class software/amazon/awssdk/core/traits/Trait
    1177: dup
    1178: iconst_0
    1179: invokestatic  #127                // Method software/amazon/awssdk/core/traits/LocationTrait.builder:()Lsoftware/amazon/awssdk/core/traits/LocationTrait$Builder;
    1182: getstatic     #128                // Field software/amazon/awssdk/core/protocol/MarshallLocation.PAYLOAD:Lsoftware/amazon/awssdk/core/protocol/MarshallLocation;
    1185: invokevirtual #129                // Method software/amazon/awssdk/core/traits/LocationTrait$Builder.location:(Lsoftware/amazon/awssdk/core/protocol/MarshallLocation;)Lsoftware/amazon/awssdk/core/traits/LocationTrait$Builder;
    1188: ldc           #101                // String ProvisioningStatus
    1190: invokevirtual #130                // Method software/amazon/awssdk/core/traits/LocationTrait$Builder.locationName:(Ljava/lang/String;)Lsoftware/amazon/awssdk/core/traits/LocationTrait$Builder;
    1193: invokevirtual #131                // Method software/amazon/awssdk/core/traits/LocationTrait$Builder.build:()Lsoftware/amazon/awssdk/core/traits/LocationTrait;
    1196: aastore
    1197: invokevirtual #138                // Method software/amazon/awssdk/core/SdkField$Builder.traits:([Lsoftware/amazon/awssdk/core/traits/Trait;)Lsoftware/amazon/awssdk/core/SdkField$Builder;
    1200: invokevirtual #139                // Method software/amazon/awssdk/core/SdkField$Builder.build:()Lsoftware/amazon/awssdk/core/SdkField;
    1203: putstatic     #195                // Field PROVISIONING_STATUS_FIELD:Lsoftware/amazon/awssdk/core/SdkField;
    1206: getstatic     #143                // Field software/amazon/awssdk/core/protocol/MarshallingType.STRING:Lsoftware/amazon/awssdk/core/protocol/MarshallingType;
    1209: invokestatic  #118                // Method software/amazon/awssdk/core/SdkField.builder:(Lsoftware/amazon/awssdk/core/protocol/MarshallingType;)Lsoftware/amazon/awssdk/core/SdkField$Builder;
    1212: ldc           #102                // String SerialNumber
    1214: invokevirtual #119                // Method software/amazon/awssdk/core/SdkField$Builder.memberName:(Ljava/lang/String;)Lsoftware/amazon/awssdk/core/SdkField$Builder;
    1217: invokedynamic #196,  0            // InvokeDynamic #40:apply:()Ljava/util/function/Function;
    1222: invokestatic  #121                // Method getter:(Ljava/util/function/Function;)Ljava/util/function/Function;
    1225: invokevirtual #122                // Method software/amazon/awssdk/core/SdkField$Builder.getter:(Ljava/util/function/Function;)Lsoftware/amazon/awssdk/core/SdkField$Builder;
    1228: invokedynamic #197,  0            // InvokeDynamic #41:accept:()Ljava/util/function/BiConsumer;
    1233: invokestatic  #124                // Method setter:(Ljava/util/function/BiConsumer;)Ljava/util/function/BiConsumer;
    1236: invokevirtual #125                // Method software/amazon/awssdk/core/SdkField$Builder.setter:(Ljava/util/function/BiConsumer;)Lsoftware/amazon/awssdk/core/SdkField$Builder;
    1239: iconst_1
    1240: anewarray     #126                // class software/amazon/awssdk/core/traits/Trait
    1243: dup
    1244: iconst_0
    1245: invokestatic  #127                // Method software/amazon/awssdk/core/traits/LocationTrait.builder:()Lsoftware/amazon/awssdk/core/traits/LocationTrait$Builder;
    1248: getstatic     #128                // Field software/amazon/awssdk/core/protocol/MarshallLocation.PAYLOAD:Lsoftware/amazon/awssdk/core/protocol/MarshallLocation;
    1251: invokevirtual #129                // Method software/amazon/awssdk/core/traits/LocationTrait$Builder.location:(Lsoftware/amazon/awssdk/core/protocol/MarshallLocation;)Lsoftware/amazon/awssdk/core/traits/LocationTrait$Builder;
    1254: ldc           #102                // String SerialNumber
    1256: invokevirtual #130                // Method software/amazon/awssdk/core/traits/LocationTrait$Builder.locationName:(Ljava/lang/String;)Lsoftware/amazon/awssdk/core/traits/LocationTrait$Builder;
    1259: invokevirtual #131                // Method software/amazon/awssdk/core/traits/LocationTrait$Builder.build:()Lsoftware/amazon/awssdk/core/traits/LocationTrait;
    1262: aastore
    1263: invokevirtual #138                // Method software/amazon/awssdk/core/SdkField$Builder.traits:([Lsoftware/amazon/awssdk/core/traits/Trait;)Lsoftware/amazon/awssdk/core/SdkField$Builder;
    1266: invokevirtual #139                // Method software/amazon/awssdk/core/SdkField$Builder.build:()Lsoftware/amazon/awssdk/core/SdkField;
    1269: putstatic     #198                // Field SERIAL_NUMBER_FIELD:Lsoftware/amazon/awssdk/core/SdkField;
    1272: getstatic     #199                // Field software/amazon/awssdk/core/protocol/MarshallingType.MAP:Lsoftware/amazon/awssdk/core/protocol/MarshallingType;
    1275: invokestatic  #118                // Method software/amazon/awssdk/core/SdkField.builder:(Lsoftware/amazon/awssdk/core/protocol/MarshallingType;)Lsoftware/amazon/awssdk/core/SdkField$Builder;
    1278: ldc           #103                // String Tags
    1280: invokevirtual #119                // Method software/amazon/awssdk/core/SdkField$Builder.memberName:(Ljava/lang/String;)Lsoftware/amazon/awssdk/core/SdkField$Builder;
    1283: invokedynamic #200,  0            // InvokeDynamic #42:apply:()Ljava/util/function/Function;
    1288: invokestatic  #121                // Method getter:(Ljava/util/function/Function;)Ljava/util/function/Function;
    1291: invokevirtual #122                // Method software/amazon/awssdk/core/SdkField$Builder.getter:(Ljava/util/function/Function;)Lsoftware/amazon/awssdk/core/SdkField$Builder;
    1294: invokedynamic #201,  0            // InvokeDynamic #43:accept:()Ljava/util/function/BiConsumer;
    1299: invokestatic  #124                // Method setter:(Ljava/util/function/BiConsumer;)Ljava/util/function/BiConsumer;
    1302: invokevirtual #125                // Method software/amazon/awssdk/core/SdkField$Builder.setter:(Ljava/util/function/BiConsumer;)Lsoftware/amazon/awssdk/core/SdkField$Builder;
    1305: iconst_2
    1306: anewarray     #126                // class software/amazon/awssdk/core/traits/Trait
    1309: dup
    1310: iconst_0
    1311: invokestatic  #127                // Method software/amazon/awssdk/core/traits/LocationTrait.builder:()Lsoftware/amazon/awssdk/core/traits/LocationTrait$Builder;
    1314: getstatic     #128                // Field software/amazon/awssdk/core/protocol/MarshallLocation.PAYLOAD:Lsoftware/amazon/awssdk/core/protocol/MarshallLocation;
    1317: invokevirtual #129                // Method software/amazon/awssdk/core/traits/LocationTrait$Builder.location:(Lsoftware/amazon/awssdk/core/protocol/MarshallLocation;)Lsoftware/amazon/awssdk/core/traits/LocationTrait$Builder;
    1320: ldc           #103                // String Tags
    1322: invokevirtual #130                // Method software/amazon/awssdk/core/traits/LocationTrait$Builder.locationName:(Ljava/lang/String;)Lsoftware/amazon/awssdk/core/traits/LocationTrait$Builder;
    1325: invokevirtual #131                // Method software/amazon/awssdk/core/traits/LocationTrait$Builder.build:()Lsoftware/amazon/awssdk/core/traits/LocationTrait;
    1328: aastore
    1329: dup
    1330: iconst_1
    1331: invokestatic  #202                // Method software/amazon/awssdk/core/traits/MapTrait.builder:()Lsoftware/amazon/awssdk/core/traits/MapTrait$Builder;
    1334: ldc           #203                // String key
    1336: invokevirtual #204                // Method software/amazon/awssdk/core/traits/MapTrait$Builder.keyLocationName:(Ljava/lang/String;)Lsoftware/amazon/awssdk/core/traits/MapTrait$Builder;
    1339: ldc           #205                // String value
    1341: invokevirtual #206                // Method software/amazon/awssdk/core/traits/MapTrait$Builder.valueLocationName:(Ljava/lang/String;)Lsoftware/amazon/awssdk/core/traits/MapTrait$Builder;
    1344: getstatic     #143                // Field software/amazon/awssdk/core/protocol/MarshallingType.STRING:Lsoftware/amazon/awssdk/core/protocol/MarshallingType;
    1347: invokestatic  #118                // Method software/amazon/awssdk/core/SdkField.builder:(Lsoftware/amazon/awssdk/core/protocol/MarshallingType;)Lsoftware/amazon/awssdk/core/SdkField$Builder;
    1350: iconst_1
    1351: anewarray     #126                // class software/amazon/awssdk/core/traits/Trait
    1354: dup
    1355: iconst_0
    1356: invokestatic  #127                // Method software/amazon/awssdk/core/traits/LocationTrait.builder:()Lsoftware/amazon/awssdk/core/traits/LocationTrait$Builder;
    1359: getstatic     #128                // Field software/amazon/awssdk/core/protocol/MarshallLocation.PAYLOAD:Lsoftware/amazon/awssdk/core/protocol/MarshallLocation;
    1362: invokevirtual #129                // Method software/amazon/awssdk/core/traits/LocationTrait$Builder.location:(Lsoftware/amazon/awssdk/core/protocol/MarshallLocation;)Lsoftware/amazon/awssdk/core/traits/LocationTrait$Builder;
    1365: ldc           #205                // String value
    1367: invokevirtual #130                // Method software/amazon/awssdk/core/traits/LocationTrait$Builder.locationName:(Ljava/lang/String;)Lsoftware/amazon/awssdk/core/traits/LocationTrait$Builder;
    1370: invokevirtual #131                // Method software/amazon/awssdk/core/traits/LocationTrait$Builder.build:()Lsoftware/amazon/awssdk/core/traits/LocationTrait;
    1373: aastore
    1374: invokevirtual #138                // Method software/amazon/awssdk/core/SdkField$Builder.traits:([Lsoftware/amazon/awssdk/core/traits/Trait;)Lsoftware/amazon/awssdk/core/SdkField$Builder;
    1377: invokevirtual #139                // Method software/amazon/awssdk/core/SdkField$Builder.build:()Lsoftware/amazon/awssdk/core/SdkField;
    1380: invokevirtual #207                // Method software/amazon/awssdk/core/traits/MapTrait$Builder.valueFieldInfo:(Lsoftware/amazon/awssdk/core/SdkField;)Lsoftware/amazon/awssdk/core/traits/MapTrait$Builder;
    1383: invokevirtual #208                // Method software/amazon/awssdk/core/traits/MapTrait$Builder.build:()Lsoftware/amazon/awssdk/core/traits/MapTrait;
    1386: aastore
    1387: invokevirtual #138                // Method software/amazon/awssdk/core/SdkField$Builder.traits:([Lsoftware/amazon/awssdk/core/traits/Trait;)Lsoftware/amazon/awssdk/core/SdkField$Builder;
    1390: invokevirtual #139                // Method software/amazon/awssdk/core/SdkField$Builder.build:()Lsoftware/amazon/awssdk/core/SdkField;
    1393: putstatic     #209                // Field TAGS_FIELD:Lsoftware/amazon/awssdk/core/SdkField;
    1396: getstatic     #143                // Field software/amazon/awssdk/core/protocol/MarshallingType.STRING:Lsoftware/amazon/awssdk/core/protocol/MarshallingType;
    1399: invokestatic  #118                // Method software/amazon/awssdk/core/SdkField.builder:(Lsoftware/amazon/awssdk/core/protocol/MarshallingType;)Lsoftware/amazon/awssdk/core/SdkField$Builder;
    1402: ldc           #104                // String Type
    1404: invokevirtual #119                // Method software/amazon/awssdk/core/SdkField$Builder.memberName:(Ljava/lang/String;)Lsoftware/amazon/awssdk/core/SdkField$Builder;
    1407: invokedynamic #210,  0            // InvokeDynamic #44:apply:()Ljava/util/function/Function;
    1412: invokestatic  #121                // Method getter:(Ljava/util/function/Function;)Ljava/util/function/Function;
    1415: invokevirtual #122                // Method software/amazon/awssdk/core/SdkField$Builder.getter:(Ljava/util/function/Function;)Lsoftware/amazon/awssdk/core/SdkField$Builder;
    1418: invokedynamic #211,  0            // InvokeDynamic #45:accept:()Ljava/util/function/BiConsumer;
    1423: invokestatic  #124                // Method setter:(Ljava/util/function/BiConsumer;)Ljava/util/function/BiConsumer;
    1426: invokevirtual #125                // Method software/amazon/awssdk/core/SdkField$Builder.setter:(Ljava/util/function/BiConsumer;)Lsoftware/amazon/awssdk/core/SdkField$Builder;
    1429: iconst_1
    1430: anewarray     #126                // class software/amazon/awssdk/core/traits/Trait
    1433: dup
    1434: iconst_0
    1435: invokestatic  #127                // Method software/amazon/awssdk/core/traits/LocationTrait.builder:()Lsoftware/amazon/awssdk/core/traits/LocationTrait$Builder;
    1438: getstatic     #128                // Field software/amazon/awssdk/core/protocol/MarshallLocation.PAYLOAD:Lsoftware/amazon/awssdk/core/protocol/MarshallLocation;
    1441: invokevirtual #129                // Method software/amazon/awssdk/core/traits/LocationTrait$Builder.location:(Lsoftware/amazon/awssdk/core/protocol/MarshallLocation;)Lsoftware/amazon/awssdk/core/traits/LocationTrait$Builder;
    1444: ldc           #104                // String Type
    1446: invokevirtual #130                // Method software/amazon/awssdk/core/traits/LocationTrait$Builder.locationName:(Ljava/lang/String;)Lsoftware/amazon/awssdk/core/traits/LocationTrait$Builder;
    1449: invokevirtual #131                // Method software/amazon/awssdk/core/traits/LocationTrait$Builder.build:()Lsoftware/amazon/awssdk/core/traits/LocationTrait;
    1452: aastore
    1453: invokevirtual #138                // Method software/amazon/awssdk/core/SdkField$Builder.traits:([Lsoftware/amazon/awssdk/core/traits/Trait;)Lsoftware/amazon/awssdk/core/SdkField$Builder;
    1456: invokevirtual #139                // Method software/amazon/awssdk/core/SdkField$Builder.build:()Lsoftware/amazon/awssdk/core/SdkField;
    1459: putstatic     #212                // Field TYPE_FIELD:Lsoftware/amazon/awssdk/core/SdkField;
    1462: bipush        20
    1464: anewarray     #213                // class software/amazon/awssdk/core/SdkField
    1467: dup
    1468: iconst_0
    1469: getstatic     #142                // Field ALTERNATE_SOFTWARES_FIELD:Lsoftware/amazon/awssdk/core/SdkField;
    1472: aastore
    1473: dup
    1474: iconst_1
    1475: getstatic     #146                // Field ARN_FIELD:Lsoftware/amazon/awssdk/core/SdkField;
    1478: aastore
    1479: dup
    1480: iconst_2
    1481: getstatic     #149                // Field BRAND_FIELD:Lsoftware/amazon/awssdk/core/SdkField;
    1484: aastore
    1485: dup
    1486: iconst_3
    1487: getstatic     #153                // Field CREATED_TIME_FIELD:Lsoftware/amazon/awssdk/core/SdkField;
    1490: aastore
    1491: dup
    1492: iconst_4
    1493: getstatic     #157                // Field CURRENT_NETWORKING_STATUS_FIELD:Lsoftware/amazon/awssdk/core/SdkField;
    1496: aastore
    1497: dup
    1498: iconst_5
    1499: getstatic     #160                // Field CURRENT_SOFTWARE_FIELD:Lsoftware/amazon/awssdk/core/SdkField;
    1502: aastore
    1503: dup
    1504: bipush        6
    1506: getstatic     #163                // Field DESCRIPTION_FIELD:Lsoftware/amazon/awssdk/core/SdkField;
    1509: aastore
    1510: dup
    1511: bipush        7
    1513: getstatic     #166                // Field DEVICE_AGGREGATED_STATUS_FIELD:Lsoftware/amazon/awssdk/core/SdkField;
    1516: aastore
    1517: dup
    1518: bipush        8
    1520: getstatic     #169                // Field DEVICE_CONNECTION_STATUS_FIELD:Lsoftware/amazon/awssdk/core/SdkField;
    1523: aastore
    1524: dup
    1525: bipush        9
    1527: getstatic     #172                // Field DEVICE_ID_FIELD:Lsoftware/amazon/awssdk/core/SdkField;
    1530: aastore
    1531: dup
    1532: bipush        10
    1534: getstatic     #175                // Field LATEST_ALTERNATE_SOFTWARE_FIELD:Lsoftware/amazon/awssdk/core/SdkField;
    1537: aastore
    1538: dup
    1539: bipush        11
    1541: getstatic     #179                // Field LATEST_DEVICE_JOB_FIELD:Lsoftware/amazon/awssdk/core/SdkField;
    1544: aastore
    1545: dup
    1546: bipush        12
    1548: getstatic     #182                // Field LATEST_SOFTWARE_FIELD:Lsoftware/amazon/awssdk/core/SdkField;
    1551: aastore
    1552: dup
    1553: bipush        13
    1555: getstatic     #185                // Field LEASE_EXPIRATION_TIME_FIELD:Lsoftware/amazon/awssdk/core/SdkField;
    1558: aastore
    1559: dup
    1560: bipush        14
    1562: getstatic     #188                // Field NAME_FIELD:Lsoftware/amazon/awssdk/core/SdkField;
    1565: aastore
    1566: dup
    1567: bipush        15
    1569: getstatic     #192                // Field NETWORKING_CONFIGURATION_FIELD:Lsoftware/amazon/awssdk/core/SdkField;
    1572: aastore
    1573: dup
    1574: bipush        16
    1576: getstatic     #195                // Field PROVISIONING_STATUS_FIELD:Lsoftware/amazon/awssdk/core/SdkField;
    1579: aastore
    1580: dup
    1581: bipush        17
    1583: getstatic     #198                // Field SERIAL_NUMBER_FIELD:Lsoftware/amazon/awssdk/core/SdkField;
    1586: aastore
    1587: dup
    1588: bipush        18
    1590: getstatic     #209                // Field TAGS_FIELD:Lsoftware/amazon/awssdk/core/SdkField;
    1593: aastore
    1594: dup
    1595: bipush        19
    1597: getstatic     #212                // Field TYPE_FIELD:Lsoftware/amazon/awssdk/core/SdkField;
    1600: aastore
    1601: invokestatic  #214                // Method java/util/Arrays.asList:([Ljava/lang/Object;)Ljava/util/List;
    1604: invokestatic  #215                // Method java/util/Collections.unmodifiableList:(Ljava/util/List;)Ljava/util/List;
    1607: putstatic     #1                  // Field SDK_FIELDS:Ljava/util/List;
    1610: return
}
