Compiled from "PackageImportJob.java"
final class software.amazon.awssdk.services.panorama.model.PackageImportJob$BuilderImpl implements software.amazon.awssdk.services.panorama.model.PackageImportJob$Builder {
  private java.time.Instant createdTime;

  private java.lang.String jobId;

  private java.lang.String jobType;

  private java.time.Instant lastUpdatedTime;

  private java.lang.String status;

  private java.lang.String statusMessage;

  private software.amazon.awssdk.services.panorama.model.PackageImportJob$BuilderImpl();
    Code:
       0: aload_0
       1: invokespecial #9                  // Method java/lang/Object."<init>":()V
       4: return

  private software.amazon.awssdk.services.panorama.model.PackageImportJob$BuilderImpl(software.amazon.awssdk.services.panorama.model.PackageImportJob);
    Code:
       0: aload_0
       1: invokespecial #9                  // Method java/lang/Object."<init>":()V
       4: aload_0
       5: aload_1
       6: invokestatic  #10                 // Method software/amazon/awssdk/services/panorama/model/PackageImportJob.access$800:(Lsoftware/amazon/awssdk/services/panorama/model/PackageImportJob;)Ljava/time/Instant;
       9: invokevirtual #11                 // Method createdTime:(Ljava/time/Instant;)Lsoftware/amazon/awssdk/services/panorama/model/PackageImportJob$Builder;
      12: pop
      13: aload_0
      14: aload_1
      15: invokestatic  #12                 // Method software/amazon/awssdk/services/panorama/model/PackageImportJob.access$900:(Lsoftware/amazon/awssdk/services/panorama/model/PackageImportJob;)Ljava/lang/String;
      18: invokevirtual #13                 // Method jobId:(Ljava/lang/String;)Lsoftware/amazon/awssdk/services/panorama/model/PackageImportJob$Builder;
      21: pop
      22: aload_0
      23: aload_1
      24: invokestatic  #14                 // Method software/amazon/awssdk/services/panorama/model/PackageImportJob.access$1000:(Lsoftware/amazon/awssdk/services/panorama/model/PackageImportJob;)Ljava/lang/String;
      27: invokevirtual #15                 // Method jobType:(Ljava/lang/String;)Lsoftware/amazon/awssdk/services/panorama/model/PackageImportJob$Builder;
      30: pop
      31: aload_0
      32: aload_1
      33: invokestatic  #16                 // Method software/amazon/awssdk/services/panorama/model/PackageImportJob.access$1100:(Lsoftware/amazon/awssdk/services/panorama/model/PackageImportJob;)Ljava/time/Instant;
      36: invokevirtual #17                 // Method lastUpdatedTime:(Ljava/time/Instant;)Lsoftware/amazon/awssdk/services/panorama/model/PackageImportJob$Builder;
      39: pop
      40: aload_0
      41: aload_1
      42: invokestatic  #18                 // Method software/amazon/awssdk/services/panorama/model/PackageImportJob.access$1200:(Lsoftware/amazon/awssdk/services/panorama/model/PackageImportJob;)Ljava/lang/String;
      45: invokevirtual #19                 // Method status:(Ljava/lang/String;)Lsoftware/amazon/awssdk/services/panorama/model/PackageImportJob$Builder;
      48: pop
      49: aload_0
      50: aload_1
      51: invokestatic  #20                 // Method software/amazon/awssdk/services/panorama/model/PackageImportJob.access$1300:(Lsoftware/amazon/awssdk/services/panorama/model/PackageImportJob;)Ljava/lang/String;
      54: invokevirtual #21                 // Method statusMessage:(Ljava/lang/String;)Lsoftware/amazon/awssdk/services/panorama/model/PackageImportJob$Builder;
      57: pop
      58: return

  public final java.time.Instant getCreatedTime();
    Code:
       0: aload_0
       1: getfield      #8                  // Field createdTime:Ljava/time/Instant;
       4: areturn

  public final void setCreatedTime(java.time.Instant);
    Code:
       0: aload_0
       1: aload_1
       2: putfield      #8                  // Field createdTime:Ljava/time/Instant;
       5: return

  public final software.amazon.awssdk.services.panorama.model.PackageImportJob$Builder createdTime(java.time.Instant);
    Code:
       0: aload_0
       1: aload_1
       2: putfield      #8                  // Field createdTime:Ljava/time/Instant;
       5: aload_0
       6: areturn

  public final java.lang.String getJobId();
    Code:
       0: aload_0
       1: getfield      #7                  // Field jobId:Ljava/lang/String;
       4: areturn

  public final void setJobId(java.lang.String);
    Code:
       0: aload_0
       1: aload_1
       2: putfield      #7                  // Field jobId:Ljava/lang/String;
       5: return

  public final software.amazon.awssdk.services.panorama.model.PackageImportJob$Builder jobId(java.lang.String);
    Code:
       0: aload_0
       1: aload_1
       2: putfield      #7                  // Field jobId:Ljava/lang/String;
       5: aload_0
       6: areturn

  public final java.lang.String getJobType();
    Code:
       0: aload_0
       1: getfield      #6                  // Field jobType:Ljava/lang/String;
       4: areturn

  public final void setJobType(java.lang.String);
    Code:
       0: aload_0
       1: aload_1
       2: putfield      #6                  // Field jobType:Ljava/lang/String;
       5: return

  public final software.amazon.awssdk.services.panorama.model.PackageImportJob$Builder jobType(java.lang.String);
    Code:
       0: aload_0
       1: aload_1
       2: putfield      #6                  // Field jobType:Ljava/lang/String;
       5: aload_0
       6: areturn

  public final software.amazon.awssdk.services.panorama.model.PackageImportJob$Builder jobType(software.amazon.awssdk.services.panorama.model.PackageImportJobType);
    Code:
       0: aload_0
       1: aload_1
       2: ifnonnull     9
       5: aconst_null
       6: goto          13
       9: aload_1
      10: invokevirtual #22                 // Method software/amazon/awssdk/services/panorama/model/PackageImportJobType.toString:()Ljava/lang/String;
      13: invokevirtual #15                 // Method jobType:(Ljava/lang/String;)Lsoftware/amazon/awssdk/services/panorama/model/PackageImportJob$Builder;
      16: pop
      17: aload_0
      18: areturn

  public final java.time.Instant getLastUpdatedTime();
    Code:
       0: aload_0
       1: getfield      #5                  // Field lastUpdatedTime:Ljava/time/Instant;
       4: areturn

  public final void setLastUpdatedTime(java.time.Instant);
    Code:
       0: aload_0
       1: aload_1
       2: putfield      #5                  // Field lastUpdatedTime:Ljava/time/Instant;
       5: return

  public final software.amazon.awssdk.services.panorama.model.PackageImportJob$Builder lastUpdatedTime(java.time.Instant);
    Code:
       0: aload_0
       1: aload_1
       2: putfield      #5                  // Field lastUpdatedTime:Ljava/time/Instant;
       5: aload_0
       6: areturn

  public final java.lang.String getStatus();
    Code:
       0: aload_0
       1: getfield      #4                  // Field status:Ljava/lang/String;
       4: areturn

  public final void setStatus(java.lang.String);
    Code:
       0: aload_0
       1: aload_1
       2: putfield      #4                  // Field status:Ljava/lang/String;
       5: return

  public final software.amazon.awssdk.services.panorama.model.PackageImportJob$Builder status(java.lang.String);
    Code:
       0: aload_0
       1: aload_1
       2: putfield      #4                  // Field status:Ljava/lang/String;
       5: aload_0
       6: areturn

  public final software.amazon.awssdk.services.panorama.model.PackageImportJob$Builder status(software.amazon.awssdk.services.panorama.model.PackageImportJobStatus);
    Code:
       0: aload_0
       1: aload_1
       2: ifnonnull     9
       5: aconst_null
       6: goto          13
       9: aload_1
      10: invokevirtual #23                 // Method software/amazon/awssdk/services/panorama/model/PackageImportJobStatus.toString:()Ljava/lang/String;
      13: invokevirtual #19                 // Method status:(Ljava/lang/String;)Lsoftware/amazon/awssdk/services/panorama/model/PackageImportJob$Builder;
      16: pop
      17: aload_0
      18: areturn

  public final java.lang.String getStatusMessage();
    Code:
       0: aload_0
       1: getfield      #3                  // Field statusMessage:Ljava/lang/String;
       4: areturn

  public final void setStatusMessage(java.lang.String);
    Code:
       0: aload_0
       1: aload_1
       2: putfield      #3                  // Field statusMessage:Ljava/lang/String;
       5: return

  public final software.amazon.awssdk.services.panorama.model.PackageImportJob$Builder statusMessage(java.lang.String);
    Code:
       0: aload_0
       1: aload_1
       2: putfield      #3                  // Field statusMessage:Ljava/lang/String;
       5: aload_0
       6: areturn

  public software.amazon.awssdk.services.panorama.model.PackageImportJob build();
    Code:
       0: new           #24                 // class software/amazon/awssdk/services/panorama/model/PackageImportJob
       3: dup
       4: aload_0
       5: aconst_null
       6: invokespecial #25                 // Method software/amazon/awssdk/services/panorama/model/PackageImportJob."<init>":(Lsoftware/amazon/awssdk/services/panorama/model/PackageImportJob$BuilderImpl;Lsoftware/amazon/awssdk/services/panorama/model/PackageImportJob$1;)V
       9: areturn

  public java.util.List<software.amazon.awssdk.core.SdkField<?>> sdkFields();
    Code:
       0: invokestatic  #26                 // Method software/amazon/awssdk/services/panorama/model/PackageImportJob.access$1500:()Ljava/util/List;
       3: areturn

  public java.lang.Object build();
    Code:
       0: aload_0
       1: invokevirtual #27                 // Method build:()Lsoftware/amazon/awssdk/services/panorama/model/PackageImportJob;
       4: areturn

  static java.time.Instant access$000(software.amazon.awssdk.services.panorama.model.PackageImportJob$BuilderImpl);
    Code:
       0: aload_0
       1: getfield      #8                  // Field createdTime:Ljava/time/Instant;
       4: areturn

  static java.lang.String access$100(software.amazon.awssdk.services.panorama.model.PackageImportJob$BuilderImpl);
    Code:
       0: aload_0
       1: getfield      #7                  // Field jobId:Ljava/lang/String;
       4: areturn

  static java.lang.String access$200(software.amazon.awssdk.services.panorama.model.PackageImportJob$BuilderImpl);
    Code:
       0: aload_0
       1: getfield      #6                  // Field jobType:Ljava/lang/String;
       4: areturn

  static java.time.Instant access$300(software.amazon.awssdk.services.panorama.model.PackageImportJob$BuilderImpl);
    Code:
       0: aload_0
       1: getfield      #5                  // Field lastUpdatedTime:Ljava/time/Instant;
       4: areturn

  static java.lang.String access$400(software.amazon.awssdk.services.panorama.model.PackageImportJob$BuilderImpl);
    Code:
       0: aload_0
       1: getfield      #4                  // Field status:Ljava/lang/String;
       4: areturn

  static java.lang.String access$500(software.amazon.awssdk.services.panorama.model.PackageImportJob$BuilderImpl);
    Code:
       0: aload_0
       1: getfield      #3                  // Field statusMessage:Ljava/lang/String;
       4: areturn

  software.amazon.awssdk.services.panorama.model.PackageImportJob$BuilderImpl(software.amazon.awssdk.services.panorama.model.PackageImportJob, software.amazon.awssdk.services.panorama.model.PackageImportJob$1);
    Code:
       0: aload_0
       1: aload_1
       2: invokespecial #2                  // Method "<init>":(Lsoftware/amazon/awssdk/services/panorama/model/PackageImportJob;)V
       5: return

  software.amazon.awssdk.services.panorama.model.PackageImportJob$BuilderImpl(software.amazon.awssdk.services.panorama.model.PackageImportJob$1);
    Code:
       0: aload_0
       1: invokespecial #1                  // Method "<init>":()V
       4: return
}
