Compiled from "S3Location.java"
final class software.amazon.awssdk.services.panorama.model.S3Location$BuilderImpl implements software.amazon.awssdk.services.panorama.model.S3Location$Builder {
  private java.lang.String bucketName;

  private java.lang.String objectKey;

  private java.lang.String region;

  private software.amazon.awssdk.services.panorama.model.S3Location$BuilderImpl();
    Code:
       0: aload_0
       1: invokespecial #6                  // Method java/lang/Object."<init>":()V
       4: return

  private software.amazon.awssdk.services.panorama.model.S3Location$BuilderImpl(software.amazon.awssdk.services.panorama.model.S3Location);
    Code:
       0: aload_0
       1: invokespecial #6                  // Method java/lang/Object."<init>":()V
       4: aload_0
       5: aload_1
       6: invokestatic  #7                  // Method software/amazon/awssdk/services/panorama/model/S3Location.access$500:(Lsoftware/amazon/awssdk/services/panorama/model/S3Location;)Ljava/lang/String;
       9: invokevirtual #8                  // Method bucketName:(Ljava/lang/String;)Lsoftware/amazon/awssdk/services/panorama/model/S3Location$Builder;
      12: pop
      13: aload_0
      14: aload_1
      15: invokestatic  #9                  // Method software/amazon/awssdk/services/panorama/model/S3Location.access$600:(Lsoftware/amazon/awssdk/services/panorama/model/S3Location;)Ljava/lang/String;
      18: invokevirtual #10                 // Method objectKey:(Ljava/lang/String;)Lsoftware/amazon/awssdk/services/panorama/model/S3Location$Builder;
      21: pop
      22: aload_0
      23: aload_1
      24: invokestatic  #11                 // Method software/amazon/awssdk/services/panorama/model/S3Location.access$700:(Lsoftware/amazon/awssdk/services/panorama/model/S3Location;)Ljava/lang/String;
      27: invokevirtual #12                 // Method region:(Ljava/lang/String;)Lsoftware/amazon/awssdk/services/panorama/model/S3Location$Builder;
      30: pop
      31: return

  public final java.lang.String getBucketName();
    Code:
       0: aload_0
       1: getfield      #5                  // Field bucketName:Ljava/lang/String;
       4: areturn

  public final void setBucketName(java.lang.String);
    Code:
       0: aload_0
       1: aload_1
       2: putfield      #5                  // Field bucketName:Ljava/lang/String;
       5: return

  public final software.amazon.awssdk.services.panorama.model.S3Location$Builder bucketName(java.lang.String);
    Code:
       0: aload_0
       1: aload_1
       2: putfield      #5                  // Field bucketName:Ljava/lang/String;
       5: aload_0
       6: areturn

  public final java.lang.String getObjectKey();
    Code:
       0: aload_0
       1: getfield      #4                  // Field objectKey:Ljava/lang/String;
       4: areturn

  public final void setObjectKey(java.lang.String);
    Code:
       0: aload_0
       1: aload_1
       2: putfield      #4                  // Field objectKey:Ljava/lang/String;
       5: return

  public final software.amazon.awssdk.services.panorama.model.S3Location$Builder objectKey(java.lang.String);
    Code:
       0: aload_0
       1: aload_1
       2: putfield      #4                  // Field objectKey:Ljava/lang/String;
       5: aload_0
       6: areturn

  public final java.lang.String getRegion();
    Code:
       0: aload_0
       1: getfield      #3                  // Field region:Ljava/lang/String;
       4: areturn

  public final void setRegion(java.lang.String);
    Code:
       0: aload_0
       1: aload_1
       2: putfield      #3                  // Field region:Ljava/lang/String;
       5: return

  public final software.amazon.awssdk.services.panorama.model.S3Location$Builder region(java.lang.String);
    Code:
       0: aload_0
       1: aload_1
       2: putfield      #3                  // Field region:Ljava/lang/String;
       5: aload_0
       6: areturn

  public software.amazon.awssdk.services.panorama.model.S3Location build();
    Code:
       0: new           #13                 // class software/amazon/awssdk/services/panorama/model/S3Location
       3: dup
       4: aload_0
       5: aconst_null
       6: invokespecial #14                 // Method software/amazon/awssdk/services/panorama/model/S3Location."<init>":(Lsoftware/amazon/awssdk/services/panorama/model/S3Location$BuilderImpl;Lsoftware/amazon/awssdk/services/panorama/model/S3Location$1;)V
       9: areturn

  public java.util.List<software.amazon.awssdk.core.SdkField<?>> sdkFields();
    Code:
       0: invokestatic  #15                 // Method software/amazon/awssdk/services/panorama/model/S3Location.access$900:()Ljava/util/List;
       3: areturn

  public java.lang.Object build();
    Code:
       0: aload_0
       1: invokevirtual #16                 // Method build:()Lsoftware/amazon/awssdk/services/panorama/model/S3Location;
       4: areturn

  static java.lang.String access$000(software.amazon.awssdk.services.panorama.model.S3Location$BuilderImpl);
    Code:
       0: aload_0
       1: getfield      #5                  // Field bucketName:Ljava/lang/String;
       4: areturn

  static java.lang.String access$100(software.amazon.awssdk.services.panorama.model.S3Location$BuilderImpl);
    Code:
       0: aload_0
       1: getfield      #4                  // Field objectKey:Ljava/lang/String;
       4: areturn

  static java.lang.String access$200(software.amazon.awssdk.services.panorama.model.S3Location$BuilderImpl);
    Code:
       0: aload_0
       1: getfield      #3                  // Field region:Ljava/lang/String;
       4: areturn

  software.amazon.awssdk.services.panorama.model.S3Location$BuilderImpl(software.amazon.awssdk.services.panorama.model.S3Location, software.amazon.awssdk.services.panorama.model.S3Location$1);
    Code:
       0: aload_0
       1: aload_1
       2: invokespecial #2                  // Method "<init>":(Lsoftware/amazon/awssdk/services/panorama/model/S3Location;)V
       5: return

  software.amazon.awssdk.services.panorama.model.S3Location$BuilderImpl(software.amazon.awssdk.services.panorama.model.S3Location$1);
    Code:
       0: aload_0
       1: invokespecial #1                  // Method "<init>":()V
       4: return
}
