Compiled from "BrokerSubsystemDefinition.java"
public class org.hawkular.bus.broker.extension.BrokerSubsystemDefinition extends org.jboss.as.controller.SimpleResourceDefinition {
  public static final org.hawkular.bus.broker.extension.BrokerSubsystemDefinition INSTANCE;

  protected static final org.jboss.as.controller.SimpleAttributeDefinition BROKER_ENABLED_ATTRIBDEF;

  protected static final org.jboss.as.controller.SimpleAttributeDefinition BROKER_CONFIG_FILE_ATTRIBDEF;

  protected static final org.jboss.as.controller.SimpleAttributeDefinition BROKER_NAME_ATTRIBDEF;

  protected static final org.jboss.as.controller.SimpleAttributeDefinition BROKER_PERSISTENT_ATTRIBDEF;

  protected static final org.jboss.as.controller.SimpleAttributeDefinition BROKER_USE_JMX_ATTRIBDEF;

  protected static final org.hawkular.bus.broker.extension.CustomConfigAttributeDefinition CUSTOM_CONFIG_ATTRIBDEF;

  protected static final org.jboss.as.controller.SimpleAttributeDefinition CONNECTOR_NAME_ATTRIBDEF;

  protected static final org.jboss.as.controller.SimpleAttributeDefinition CONNECTOR_PROTOCOL_ATTRIBDEF;

  protected static final org.jboss.as.controller.SimpleAttributeDefinition SOCKET_BINDING_ATTRIBDEF;

  protected static final org.jboss.as.controller.SimpleAttributeDefinition DISCOVERY_SOCKET_BINDING_ATTRIBDEF;

  protected static final org.jboss.as.controller.SimpleAttributeDefinition START_OP_PARAM_RESTART;

  private org.hawkular.bus.broker.extension.BrokerSubsystemDefinition();
    Code:
       0: aload_0
       1: getstatic     #1                  // Field org/hawkular/bus/broker/extension/BrokerSubsystemExtension.SUBSYSTEM_PATH:Lorg/jboss/as/controller/PathElement;
       4: aconst_null
       5: invokestatic  #2                  // Method org/hawkular/bus/broker/extension/BrokerSubsystemExtension.getResourceDescriptionResolver:(Ljava/lang/String;)Lorg/jboss/as/controller/descriptions/StandardResourceDescriptionResolver;
       8: getstatic     #3                  // Field org/hawkular/bus/broker/extension/BrokerSubsystemAdd.INSTANCE:Lorg/hawkular/bus/broker/extension/BrokerSubsystemAdd;
      11: getstatic     #4                  // Field org/hawkular/bus/broker/extension/BrokerSubsystemRemove.INSTANCE:Lorg/hawkular/bus/broker/extension/BrokerSubsystemRemove;
      14: invokespecial #5                  // Method org/jboss/as/controller/SimpleResourceDefinition."<init>":(Lorg/jboss/as/controller/PathElement;Lorg/jboss/as/controller/descriptions/ResourceDescriptionResolver;Lorg/jboss/as/controller/OperationStepHandler;Lorg/jboss/as/controller/OperationStepHandler;)V
      17: return

  public void registerAttributes(org.jboss.as.controller.registry.ManagementResourceRegistration);
    Code:
       0: aload_1
       1: getstatic     #6                  // Field BROKER_ENABLED_ATTRIBDEF:Lorg/jboss/as/controller/SimpleAttributeDefinition;
       4: aconst_null
       5: getstatic     #7                  // Field org/hawkular/bus/broker/extension/BrokerEnabledAttributeHandler.INSTANCE:Lorg/hawkular/bus/broker/extension/BrokerEnabledAttributeHandler;
       8: invokeinterface #8,  4            // InterfaceMethod org/jboss/as/controller/registry/ManagementResourceRegistration.registerReadWriteAttribute:(Lorg/jboss/as/controller/AttributeDefinition;Lorg/jboss/as/controller/OperationStepHandler;Lorg/jboss/as/controller/OperationStepHandler;)V
      13: aload_0
      14: aload_1
      15: getstatic     #9                  // Field BROKER_CONFIG_FILE_ATTRIBDEF:Lorg/jboss/as/controller/SimpleAttributeDefinition;
      18: invokespecial #10                 // Method registerReloadRequiredWriteAttributeHandler:(Lorg/jboss/as/controller/registry/ManagementResourceRegistration;Lorg/jboss/as/controller/AttributeDefinition;)V
      21: aload_0
      22: aload_1
      23: getstatic     #11                 // Field BROKER_NAME_ATTRIBDEF:Lorg/jboss/as/controller/SimpleAttributeDefinition;
      26: invokespecial #10                 // Method registerReloadRequiredWriteAttributeHandler:(Lorg/jboss/as/controller/registry/ManagementResourceRegistration;Lorg/jboss/as/controller/AttributeDefinition;)V
      29: aload_0
      30: aload_1
      31: getstatic     #12                 // Field BROKER_PERSISTENT_ATTRIBDEF:Lorg/jboss/as/controller/SimpleAttributeDefinition;
      34: invokespecial #10                 // Method registerReloadRequiredWriteAttributeHandler:(Lorg/jboss/as/controller/registry/ManagementResourceRegistration;Lorg/jboss/as/controller/AttributeDefinition;)V
      37: aload_0
      38: aload_1
      39: getstatic     #13                 // Field BROKER_USE_JMX_ATTRIBDEF:Lorg/jboss/as/controller/SimpleAttributeDefinition;
      42: invokespecial #10                 // Method registerReloadRequiredWriteAttributeHandler:(Lorg/jboss/as/controller/registry/ManagementResourceRegistration;Lorg/jboss/as/controller/AttributeDefinition;)V
      45: aload_0
      46: aload_1
      47: getstatic     #14                 // Field CUSTOM_CONFIG_ATTRIBDEF:Lorg/hawkular/bus/broker/extension/CustomConfigAttributeDefinition;
      50: invokespecial #10                 // Method registerReloadRequiredWriteAttributeHandler:(Lorg/jboss/as/controller/registry/ManagementResourceRegistration;Lorg/jboss/as/controller/AttributeDefinition;)V
      53: aload_0
      54: aload_1
      55: getstatic     #15                 // Field CONNECTOR_NAME_ATTRIBDEF:Lorg/jboss/as/controller/SimpleAttributeDefinition;
      58: invokespecial #10                 // Method registerReloadRequiredWriteAttributeHandler:(Lorg/jboss/as/controller/registry/ManagementResourceRegistration;Lorg/jboss/as/controller/AttributeDefinition;)V
      61: aload_0
      62: aload_1
      63: getstatic     #16                 // Field CONNECTOR_PROTOCOL_ATTRIBDEF:Lorg/jboss/as/controller/SimpleAttributeDefinition;
      66: invokespecial #10                 // Method registerReloadRequiredWriteAttributeHandler:(Lorg/jboss/as/controller/registry/ManagementResourceRegistration;Lorg/jboss/as/controller/AttributeDefinition;)V
      69: aload_0
      70: aload_1
      71: getstatic     #17                 // Field SOCKET_BINDING_ATTRIBDEF:Lorg/jboss/as/controller/SimpleAttributeDefinition;
      74: invokespecial #10                 // Method registerReloadRequiredWriteAttributeHandler:(Lorg/jboss/as/controller/registry/ManagementResourceRegistration;Lorg/jboss/as/controller/AttributeDefinition;)V
      77: aload_0
      78: aload_1
      79: getstatic     #18                 // Field DISCOVERY_SOCKET_BINDING_ATTRIBDEF:Lorg/jboss/as/controller/SimpleAttributeDefinition;
      82: invokespecial #10                 // Method registerReloadRequiredWriteAttributeHandler:(Lorg/jboss/as/controller/registry/ManagementResourceRegistration;Lorg/jboss/as/controller/AttributeDefinition;)V
      85: return

  private void registerReloadRequiredWriteAttributeHandler(org.jboss.as.controller.registry.ManagementResourceRegistration, org.jboss.as.controller.AttributeDefinition);
    Code:
       0: aload_1
       1: aload_2
       2: aconst_null
       3: new           #19                 // class org/jboss/as/controller/ReloadRequiredWriteAttributeHandler
       6: dup
       7: iconst_1
       8: anewarray     #20                 // class org/jboss/as/controller/AttributeDefinition
      11: dup
      12: iconst_0
      13: aload_2
      14: aastore
      15: invokespecial #21                 // Method org/jboss/as/controller/ReloadRequiredWriteAttributeHandler."<init>":([Lorg/jboss/as/controller/AttributeDefinition;)V
      18: invokeinterface #8,  4            // InterfaceMethod org/jboss/as/controller/registry/ManagementResourceRegistration.registerReadWriteAttribute:(Lorg/jboss/as/controller/AttributeDefinition;Lorg/jboss/as/controller/OperationStepHandler;Lorg/jboss/as/controller/OperationStepHandler;)V
      23: return

  public void registerOperations(org.jboss.as.controller.registry.ManagementResourceRegistration);
    Code:
       0: aload_0
       1: aload_1
       2: invokespecial #22                 // Method org/jboss/as/controller/SimpleResourceDefinition.registerOperations:(Lorg/jboss/as/controller/registry/ManagementResourceRegistration;)V
       5: aload_1
       6: getstatic     #23                 // Field org/jboss/as/controller/operations/common/GenericSubsystemDescribeHandler.DEFINITION:Lorg/jboss/as/controller/SimpleOperationDefinition;
       9: getstatic     #24                 // Field org/jboss/as/controller/operations/common/GenericSubsystemDescribeHandler.INSTANCE:Lorg/jboss/as/controller/operations/common/GenericSubsystemDescribeHandler;
      12: invokeinterface #25,  3           // InterfaceMethod org/jboss/as/controller/registry/ManagementResourceRegistration.registerOperationHandler:(Lorg/jboss/as/controller/OperationDefinition;Lorg/jboss/as/controller/OperationStepHandler;)V
      17: aload_1
      18: new           #26                 // class org/jboss/as/controller/SimpleOperationDefinitionBuilder
      21: dup
      22: ldc           #28                 // String start
      24: aconst_null
      25: invokestatic  #2                  // Method org/hawkular/bus/broker/extension/BrokerSubsystemExtension.getResourceDescriptionResolver:(Ljava/lang/String;)Lorg/jboss/as/controller/descriptions/StandardResourceDescriptionResolver;
      28: invokespecial #29                 // Method org/jboss/as/controller/SimpleOperationDefinitionBuilder."<init>":(Ljava/lang/String;Lorg/jboss/as/controller/descriptions/ResourceDescriptionResolver;)V
      31: getstatic     #30                 // Field START_OP_PARAM_RESTART:Lorg/jboss/as/controller/SimpleAttributeDefinition;
      34: invokevirtual #31                 // Method org/jboss/as/controller/SimpleOperationDefinitionBuilder.addParameter:(Lorg/jboss/as/controller/AttributeDefinition;)Lorg/jboss/as/controller/SimpleOperationDefinitionBuilder;
      37: invokevirtual #32                 // Method org/jboss/as/controller/SimpleOperationDefinitionBuilder.build:()Lorg/jboss/as/controller/SimpleOperationDefinition;
      40: getstatic     #33                 // Field org/hawkular/bus/broker/extension/BrokerSubsystemStart.INSTANCE:Lorg/hawkular/bus/broker/extension/BrokerSubsystemStart;
      43: invokeinterface #25,  3           // InterfaceMethod org/jboss/as/controller/registry/ManagementResourceRegistration.registerOperationHandler:(Lorg/jboss/as/controller/OperationDefinition;Lorg/jboss/as/controller/OperationStepHandler;)V
      48: aload_1
      49: new           #26                 // class org/jboss/as/controller/SimpleOperationDefinitionBuilder
      52: dup
      53: ldc           #34                 // String stop
      55: aconst_null
      56: invokestatic  #2                  // Method org/hawkular/bus/broker/extension/BrokerSubsystemExtension.getResourceDescriptionResolver:(Ljava/lang/String;)Lorg/jboss/as/controller/descriptions/StandardResourceDescriptionResolver;
      59: invokespecial #29                 // Method org/jboss/as/controller/SimpleOperationDefinitionBuilder."<init>":(Ljava/lang/String;Lorg/jboss/as/controller/descriptions/ResourceDescriptionResolver;)V
      62: invokevirtual #32                 // Method org/jboss/as/controller/SimpleOperationDefinitionBuilder.build:()Lorg/jboss/as/controller/SimpleOperationDefinition;
      65: getstatic     #35                 // Field org/hawkular/bus/broker/extension/BrokerSubsystemStop.INSTANCE:Lorg/hawkular/bus/broker/extension/BrokerSubsystemStop;
      68: invokeinterface #25,  3           // InterfaceMethod org/jboss/as/controller/registry/ManagementResourceRegistration.registerOperationHandler:(Lorg/jboss/as/controller/OperationDefinition;Lorg/jboss/as/controller/OperationStepHandler;)V
      73: aload_1
      74: new           #26                 // class org/jboss/as/controller/SimpleOperationDefinitionBuilder
      77: dup
      78: ldc           #36                 // String status
      80: aconst_null
      81: invokestatic  #2                  // Method org/hawkular/bus/broker/extension/BrokerSubsystemExtension.getResourceDescriptionResolver:(Ljava/lang/String;)Lorg/jboss/as/controller/descriptions/StandardResourceDescriptionResolver;
      84: invokespecial #29                 // Method org/jboss/as/controller/SimpleOperationDefinitionBuilder."<init>":(Ljava/lang/String;Lorg/jboss/as/controller/descriptions/ResourceDescriptionResolver;)V
      87: invokevirtual #32                 // Method org/jboss/as/controller/SimpleOperationDefinitionBuilder.build:()Lorg/jboss/as/controller/SimpleOperationDefinition;
      90: getstatic     #37                 // Field org/hawkular/bus/broker/extension/BrokerSubsystemStatus.INSTANCE:Lorg/hawkular/bus/broker/extension/BrokerSubsystemStatus;
      93: invokeinterface #25,  3           // InterfaceMethod org/jboss/as/controller/registry/ManagementResourceRegistration.registerOperationHandler:(Lorg/jboss/as/controller/OperationDefinition;Lorg/jboss/as/controller/OperationStepHandler;)V
      98: return

  static {};
    Code:
       0: new           #38                 // class org/hawkular/bus/broker/extension/BrokerSubsystemDefinition
       3: dup
       4: invokespecial #39                 // Method "<init>":()V
       7: putstatic     #40                 // Field INSTANCE:Lorg/hawkular/bus/broker/extension/BrokerSubsystemDefinition;
      10: new           #41                 // class org/jboss/as/controller/SimpleAttributeDefinitionBuilder
      13: dup
      14: ldc           #42                 // String enabled
      16: getstatic     #43                 // Field org/jboss/dmr/ModelType.BOOLEAN:Lorg/jboss/dmr/ModelType;
      19: invokespecial #44                 // Method org/jboss/as/controller/SimpleAttributeDefinitionBuilder."<init>":(Ljava/lang/String;Lorg/jboss/dmr/ModelType;)V
      22: iconst_1
      23: invokevirtual #45                 // Method org/jboss/as/controller/SimpleAttributeDefinitionBuilder.setAllowExpression:(Z)Lorg/jboss/as/controller/AbstractAttributeDefinitionBuilder;
      26: checkcast     #41                 // class org/jboss/as/controller/SimpleAttributeDefinitionBuilder
      29: ldc           #42                 // String enabled
      31: invokevirtual #46                 // Method org/jboss/as/controller/SimpleAttributeDefinitionBuilder.setXmlName:(Ljava/lang/String;)Lorg/jboss/as/controller/AbstractAttributeDefinitionBuilder;
      34: checkcast     #41                 // class org/jboss/as/controller/SimpleAttributeDefinitionBuilder
      37: iconst_1
      38: anewarray     #47                 // class org/jboss/as/controller/registry/AttributeAccess$Flag
      41: dup
      42: iconst_0
      43: getstatic     #48                 // Field org/jboss/as/controller/registry/AttributeAccess$Flag.RESTART_RESOURCE_SERVICES:Lorg/jboss/as/controller/registry/AttributeAccess$Flag;
      46: aastore
      47: invokevirtual #49                 // Method org/jboss/as/controller/SimpleAttributeDefinitionBuilder.setFlags:([Lorg/jboss/as/controller/registry/AttributeAccess$Flag;)Lorg/jboss/as/controller/AbstractAttributeDefinitionBuilder;
      50: checkcast     #41                 // class org/jboss/as/controller/SimpleAttributeDefinitionBuilder
      53: new           #50                 // class org/jboss/dmr/ModelNode
      56: dup
      57: iconst_0
      58: invokespecial #51                 // Method org/jboss/dmr/ModelNode."<init>":(Z)V
      61: invokevirtual #52                 // Method org/jboss/as/controller/SimpleAttributeDefinitionBuilder.setDefaultValue:(Lorg/jboss/dmr/ModelNode;)Lorg/jboss/as/controller/AbstractAttributeDefinitionBuilder;
      64: checkcast     #41                 // class org/jboss/as/controller/SimpleAttributeDefinitionBuilder
      67: iconst_0
      68: invokevirtual #53                 // Method org/jboss/as/controller/SimpleAttributeDefinitionBuilder.setAllowNull:(Z)Lorg/jboss/as/controller/AbstractAttributeDefinitionBuilder;
      71: checkcast     #41                 // class org/jboss/as/controller/SimpleAttributeDefinitionBuilder
      74: invokevirtual #54                 // Method org/jboss/as/controller/SimpleAttributeDefinitionBuilder.build:()Lorg/jboss/as/controller/SimpleAttributeDefinition;
      77: putstatic     #6                  // Field BROKER_ENABLED_ATTRIBDEF:Lorg/jboss/as/controller/SimpleAttributeDefinition;
      80: new           #41                 // class org/jboss/as/controller/SimpleAttributeDefinitionBuilder
      83: dup
      84: ldc           #55                 // String configuration-file
      86: getstatic     #56                 // Field org/jboss/dmr/ModelType.STRING:Lorg/jboss/dmr/ModelType;
      89: invokespecial #44                 // Method org/jboss/as/controller/SimpleAttributeDefinitionBuilder."<init>":(Ljava/lang/String;Lorg/jboss/dmr/ModelType;)V
      92: iconst_1
      93: invokevirtual #45                 // Method org/jboss/as/controller/SimpleAttributeDefinitionBuilder.setAllowExpression:(Z)Lorg/jboss/as/controller/AbstractAttributeDefinitionBuilder;
      96: checkcast     #41                 // class org/jboss/as/controller/SimpleAttributeDefinitionBuilder
      99: iconst_1
     100: anewarray     #47                 // class org/jboss/as/controller/registry/AttributeAccess$Flag
     103: dup
     104: iconst_0
     105: getstatic     #48                 // Field org/jboss/as/controller/registry/AttributeAccess$Flag.RESTART_RESOURCE_SERVICES:Lorg/jboss/as/controller/registry/AttributeAccess$Flag;
     108: aastore
     109: invokevirtual #49                 // Method org/jboss/as/controller/SimpleAttributeDefinitionBuilder.setFlags:([Lorg/jboss/as/controller/registry/AttributeAccess$Flag;)Lorg/jboss/as/controller/AbstractAttributeDefinitionBuilder;
     112: checkcast     #41                 // class org/jboss/as/controller/SimpleAttributeDefinitionBuilder
     115: new           #50                 // class org/jboss/dmr/ModelNode
     118: dup
     119: ldc           #57                 // String default-broker.xml
     121: invokespecial #58                 // Method org/jboss/dmr/ModelNode."<init>":(Ljava/lang/String;)V
     124: invokevirtual #52                 // Method org/jboss/as/controller/SimpleAttributeDefinitionBuilder.setDefaultValue:(Lorg/jboss/dmr/ModelNode;)Lorg/jboss/as/controller/AbstractAttributeDefinitionBuilder;
     127: checkcast     #41                 // class org/jboss/as/controller/SimpleAttributeDefinitionBuilder
     130: iconst_1
     131: invokevirtual #53                 // Method org/jboss/as/controller/SimpleAttributeDefinitionBuilder.setAllowNull:(Z)Lorg/jboss/as/controller/AbstractAttributeDefinitionBuilder;
     134: checkcast     #41                 // class org/jboss/as/controller/SimpleAttributeDefinitionBuilder
     137: invokevirtual #54                 // Method org/jboss/as/controller/SimpleAttributeDefinitionBuilder.build:()Lorg/jboss/as/controller/SimpleAttributeDefinition;
     140: putstatic     #9                  // Field BROKER_CONFIG_FILE_ATTRIBDEF:Lorg/jboss/as/controller/SimpleAttributeDefinition;
     143: new           #41                 // class org/jboss/as/controller/SimpleAttributeDefinitionBuilder
     146: dup
     147: ldc           #59                 // String org-hawkular-bus-broker-name
     149: getstatic     #56                 // Field org/jboss/dmr/ModelType.STRING:Lorg/jboss/dmr/ModelType;
     152: invokespecial #44                 // Method org/jboss/as/controller/SimpleAttributeDefinitionBuilder."<init>":(Ljava/lang/String;Lorg/jboss/dmr/ModelType;)V
     155: iconst_1
     156: invokevirtual #45                 // Method org/jboss/as/controller/SimpleAttributeDefinitionBuilder.setAllowExpression:(Z)Lorg/jboss/as/controller/AbstractAttributeDefinitionBuilder;
     159: checkcast     #41                 // class org/jboss/as/controller/SimpleAttributeDefinitionBuilder
     162: iconst_1
     163: anewarray     #47                 // class org/jboss/as/controller/registry/AttributeAccess$Flag
     166: dup
     167: iconst_0
     168: getstatic     #48                 // Field org/jboss/as/controller/registry/AttributeAccess$Flag.RESTART_RESOURCE_SERVICES:Lorg/jboss/as/controller/registry/AttributeAccess$Flag;
     171: aastore
     172: invokevirtual #49                 // Method org/jboss/as/controller/SimpleAttributeDefinitionBuilder.setFlags:([Lorg/jboss/as/controller/registry/AttributeAccess$Flag;)Lorg/jboss/as/controller/AbstractAttributeDefinitionBuilder;
     175: checkcast     #41                 // class org/jboss/as/controller/SimpleAttributeDefinitionBuilder
     178: new           #50                 // class org/jboss/dmr/ModelNode
     181: dup
     182: ldc           #60                 // String org.hawkular.bus.broker
     184: invokespecial #58                 // Method org/jboss/dmr/ModelNode."<init>":(Ljava/lang/String;)V
     187: invokevirtual #52                 // Method org/jboss/as/controller/SimpleAttributeDefinitionBuilder.setDefaultValue:(Lorg/jboss/dmr/ModelNode;)Lorg/jboss/as/controller/AbstractAttributeDefinitionBuilder;
     190: checkcast     #41                 // class org/jboss/as/controller/SimpleAttributeDefinitionBuilder
     193: iconst_1
     194: invokevirtual #53                 // Method org/jboss/as/controller/SimpleAttributeDefinitionBuilder.setAllowNull:(Z)Lorg/jboss/as/controller/AbstractAttributeDefinitionBuilder;
     197: checkcast     #41                 // class org/jboss/as/controller/SimpleAttributeDefinitionBuilder
     200: invokevirtual #54                 // Method org/jboss/as/controller/SimpleAttributeDefinitionBuilder.build:()Lorg/jboss/as/controller/SimpleAttributeDefinition;
     203: putstatic     #11                 // Field BROKER_NAME_ATTRIBDEF:Lorg/jboss/as/controller/SimpleAttributeDefinition;
     206: new           #41                 // class org/jboss/as/controller/SimpleAttributeDefinitionBuilder
     209: dup
     210: ldc           #61                 // String org-hawkular-bus-broker-persistent
     212: getstatic     #43                 // Field org/jboss/dmr/ModelType.BOOLEAN:Lorg/jboss/dmr/ModelType;
     215: invokespecial #44                 // Method org/jboss/as/controller/SimpleAttributeDefinitionBuilder."<init>":(Ljava/lang/String;Lorg/jboss/dmr/ModelType;)V
     218: iconst_1
     219: invokevirtual #45                 // Method org/jboss/as/controller/SimpleAttributeDefinitionBuilder.setAllowExpression:(Z)Lorg/jboss/as/controller/AbstractAttributeDefinitionBuilder;
     222: checkcast     #41                 // class org/jboss/as/controller/SimpleAttributeDefinitionBuilder
     225: ldc           #61                 // String org-hawkular-bus-broker-persistent
     227: invokevirtual #46                 // Method org/jboss/as/controller/SimpleAttributeDefinitionBuilder.setXmlName:(Ljava/lang/String;)Lorg/jboss/as/controller/AbstractAttributeDefinitionBuilder;
     230: checkcast     #41                 // class org/jboss/as/controller/SimpleAttributeDefinitionBuilder
     233: iconst_1
     234: anewarray     #47                 // class org/jboss/as/controller/registry/AttributeAccess$Flag
     237: dup
     238: iconst_0
     239: getstatic     #48                 // Field org/jboss/as/controller/registry/AttributeAccess$Flag.RESTART_RESOURCE_SERVICES:Lorg/jboss/as/controller/registry/AttributeAccess$Flag;
     242: aastore
     243: invokevirtual #49                 // Method org/jboss/as/controller/SimpleAttributeDefinitionBuilder.setFlags:([Lorg/jboss/as/controller/registry/AttributeAccess$Flag;)Lorg/jboss/as/controller/AbstractAttributeDefinitionBuilder;
     246: checkcast     #41                 // class org/jboss/as/controller/SimpleAttributeDefinitionBuilder
     249: new           #50                 // class org/jboss/dmr/ModelNode
     252: dup
     253: iconst_0
     254: invokespecial #51                 // Method org/jboss/dmr/ModelNode."<init>":(Z)V
     257: invokevirtual #52                 // Method org/jboss/as/controller/SimpleAttributeDefinitionBuilder.setDefaultValue:(Lorg/jboss/dmr/ModelNode;)Lorg/jboss/as/controller/AbstractAttributeDefinitionBuilder;
     260: checkcast     #41                 // class org/jboss/as/controller/SimpleAttributeDefinitionBuilder
     263: iconst_1
     264: invokevirtual #53                 // Method org/jboss/as/controller/SimpleAttributeDefinitionBuilder.setAllowNull:(Z)Lorg/jboss/as/controller/AbstractAttributeDefinitionBuilder;
     267: checkcast     #41                 // class org/jboss/as/controller/SimpleAttributeDefinitionBuilder
     270: invokevirtual #54                 // Method org/jboss/as/controller/SimpleAttributeDefinitionBuilder.build:()Lorg/jboss/as/controller/SimpleAttributeDefinition;
     273: putstatic     #12                 // Field BROKER_PERSISTENT_ATTRIBDEF:Lorg/jboss/as/controller/SimpleAttributeDefinition;
     276: new           #41                 // class org/jboss/as/controller/SimpleAttributeDefinitionBuilder
     279: dup
     280: ldc           #62                 // String org-hawkular-bus-broker-use-jmx
     282: getstatic     #43                 // Field org/jboss/dmr/ModelType.BOOLEAN:Lorg/jboss/dmr/ModelType;
     285: invokespecial #44                 // Method org/jboss/as/controller/SimpleAttributeDefinitionBuilder."<init>":(Ljava/lang/String;Lorg/jboss/dmr/ModelType;)V
     288: iconst_1
     289: invokevirtual #45                 // Method org/jboss/as/controller/SimpleAttributeDefinitionBuilder.setAllowExpression:(Z)Lorg/jboss/as/controller/AbstractAttributeDefinitionBuilder;
     292: checkcast     #41                 // class org/jboss/as/controller/SimpleAttributeDefinitionBuilder
     295: ldc           #62                 // String org-hawkular-bus-broker-use-jmx
     297: invokevirtual #46                 // Method org/jboss/as/controller/SimpleAttributeDefinitionBuilder.setXmlName:(Ljava/lang/String;)Lorg/jboss/as/controller/AbstractAttributeDefinitionBuilder;
     300: checkcast     #41                 // class org/jboss/as/controller/SimpleAttributeDefinitionBuilder
     303: iconst_1
     304: anewarray     #47                 // class org/jboss/as/controller/registry/AttributeAccess$Flag
     307: dup
     308: iconst_0
     309: getstatic     #48                 // Field org/jboss/as/controller/registry/AttributeAccess$Flag.RESTART_RESOURCE_SERVICES:Lorg/jboss/as/controller/registry/AttributeAccess$Flag;
     312: aastore
     313: invokevirtual #49                 // Method org/jboss/as/controller/SimpleAttributeDefinitionBuilder.setFlags:([Lorg/jboss/as/controller/registry/AttributeAccess$Flag;)Lorg/jboss/as/controller/AbstractAttributeDefinitionBuilder;
     316: checkcast     #41                 // class org/jboss/as/controller/SimpleAttributeDefinitionBuilder
     319: new           #50                 // class org/jboss/dmr/ModelNode
     322: dup
     323: iconst_0
     324: invokespecial #51                 // Method org/jboss/dmr/ModelNode."<init>":(Z)V
     327: invokevirtual #52                 // Method org/jboss/as/controller/SimpleAttributeDefinitionBuilder.setDefaultValue:(Lorg/jboss/dmr/ModelNode;)Lorg/jboss/as/controller/AbstractAttributeDefinitionBuilder;
     330: checkcast     #41                 // class org/jboss/as/controller/SimpleAttributeDefinitionBuilder
     333: iconst_1
     334: invokevirtual #53                 // Method org/jboss/as/controller/SimpleAttributeDefinitionBuilder.setAllowNull:(Z)Lorg/jboss/as/controller/AbstractAttributeDefinitionBuilder;
     337: checkcast     #41                 // class org/jboss/as/controller/SimpleAttributeDefinitionBuilder
     340: invokevirtual #54                 // Method org/jboss/as/controller/SimpleAttributeDefinitionBuilder.build:()Lorg/jboss/as/controller/SimpleAttributeDefinition;
     343: putstatic     #13                 // Field BROKER_USE_JMX_ATTRIBDEF:Lorg/jboss/as/controller/SimpleAttributeDefinition;
     346: new           #63                 // class org/hawkular/bus/broker/extension/CustomConfigAttributeDefinition
     349: dup
     350: invokespecial #64                 // Method org/hawkular/bus/broker/extension/CustomConfigAttributeDefinition."<init>":()V
     353: putstatic     #14                 // Field CUSTOM_CONFIG_ATTRIBDEF:Lorg/hawkular/bus/broker/extension/CustomConfigAttributeDefinition;
     356: new           #41                 // class org/jboss/as/controller/SimpleAttributeDefinitionBuilder
     359: dup
     360: ldc           #65                 // String org-hawkular-bus-broker-connector-name
     362: getstatic     #56                 // Field org/jboss/dmr/ModelType.STRING:Lorg/jboss/dmr/ModelType;
     365: invokespecial #44                 // Method org/jboss/as/controller/SimpleAttributeDefinitionBuilder."<init>":(Ljava/lang/String;Lorg/jboss/dmr/ModelType;)V
     368: iconst_1
     369: invokevirtual #45                 // Method org/jboss/as/controller/SimpleAttributeDefinitionBuilder.setAllowExpression:(Z)Lorg/jboss/as/controller/AbstractAttributeDefinitionBuilder;
     372: checkcast     #41                 // class org/jboss/as/controller/SimpleAttributeDefinitionBuilder
     375: ldc           #65                 // String org-hawkular-bus-broker-connector-name
     377: invokevirtual #46                 // Method org/jboss/as/controller/SimpleAttributeDefinitionBuilder.setXmlName:(Ljava/lang/String;)Lorg/jboss/as/controller/AbstractAttributeDefinitionBuilder;
     380: checkcast     #41                 // class org/jboss/as/controller/SimpleAttributeDefinitionBuilder
     383: iconst_1
     384: anewarray     #47                 // class org/jboss/as/controller/registry/AttributeAccess$Flag
     387: dup
     388: iconst_0
     389: getstatic     #48                 // Field org/jboss/as/controller/registry/AttributeAccess$Flag.RESTART_RESOURCE_SERVICES:Lorg/jboss/as/controller/registry/AttributeAccess$Flag;
     392: aastore
     393: invokevirtual #49                 // Method org/jboss/as/controller/SimpleAttributeDefinitionBuilder.setFlags:([Lorg/jboss/as/controller/registry/AttributeAccess$Flag;)Lorg/jboss/as/controller/AbstractAttributeDefinitionBuilder;
     396: checkcast     #41                 // class org/jboss/as/controller/SimpleAttributeDefinitionBuilder
     399: new           #50                 // class org/jboss/dmr/ModelNode
     402: dup
     403: ldc           #66                 // String openwire
     405: invokespecial #58                 // Method org/jboss/dmr/ModelNode."<init>":(Ljava/lang/String;)V
     408: invokevirtual #52                 // Method org/jboss/as/controller/SimpleAttributeDefinitionBuilder.setDefaultValue:(Lorg/jboss/dmr/ModelNode;)Lorg/jboss/as/controller/AbstractAttributeDefinitionBuilder;
     411: checkcast     #41                 // class org/jboss/as/controller/SimpleAttributeDefinitionBuilder
     414: iconst_1
     415: invokevirtual #53                 // Method org/jboss/as/controller/SimpleAttributeDefinitionBuilder.setAllowNull:(Z)Lorg/jboss/as/controller/AbstractAttributeDefinitionBuilder;
     418: checkcast     #41                 // class org/jboss/as/controller/SimpleAttributeDefinitionBuilder
     421: invokevirtual #54                 // Method org/jboss/as/controller/SimpleAttributeDefinitionBuilder.build:()Lorg/jboss/as/controller/SimpleAttributeDefinition;
     424: putstatic     #15                 // Field CONNECTOR_NAME_ATTRIBDEF:Lorg/jboss/as/controller/SimpleAttributeDefinition;
     427: new           #41                 // class org/jboss/as/controller/SimpleAttributeDefinitionBuilder
     430: dup
     431: ldc           #67                 // String org-hawkular-bus-broker-connector-protocol
     433: getstatic     #56                 // Field org/jboss/dmr/ModelType.STRING:Lorg/jboss/dmr/ModelType;
     436: invokespecial #44                 // Method org/jboss/as/controller/SimpleAttributeDefinitionBuilder."<init>":(Ljava/lang/String;Lorg/jboss/dmr/ModelType;)V
     439: iconst_1
     440: invokevirtual #45                 // Method org/jboss/as/controller/SimpleAttributeDefinitionBuilder.setAllowExpression:(Z)Lorg/jboss/as/controller/AbstractAttributeDefinitionBuilder;
     443: checkcast     #41                 // class org/jboss/as/controller/SimpleAttributeDefinitionBuilder
     446: ldc           #67                 // String org-hawkular-bus-broker-connector-protocol
     448: invokevirtual #46                 // Method org/jboss/as/controller/SimpleAttributeDefinitionBuilder.setXmlName:(Ljava/lang/String;)Lorg/jboss/as/controller/AbstractAttributeDefinitionBuilder;
     451: checkcast     #41                 // class org/jboss/as/controller/SimpleAttributeDefinitionBuilder
     454: iconst_1
     455: anewarray     #47                 // class org/jboss/as/controller/registry/AttributeAccess$Flag
     458: dup
     459: iconst_0
     460: getstatic     #48                 // Field org/jboss/as/controller/registry/AttributeAccess$Flag.RESTART_RESOURCE_SERVICES:Lorg/jboss/as/controller/registry/AttributeAccess$Flag;
     463: aastore
     464: invokevirtual #49                 // Method org/jboss/as/controller/SimpleAttributeDefinitionBuilder.setFlags:([Lorg/jboss/as/controller/registry/AttributeAccess$Flag;)Lorg/jboss/as/controller/AbstractAttributeDefinitionBuilder;
     467: checkcast     #41                 // class org/jboss/as/controller/SimpleAttributeDefinitionBuilder
     470: new           #50                 // class org/jboss/dmr/ModelNode
     473: dup
     474: ldc           #68                 // String tcp
     476: invokespecial #58                 // Method org/jboss/dmr/ModelNode."<init>":(Ljava/lang/String;)V
     479: invokevirtual #52                 // Method org/jboss/as/controller/SimpleAttributeDefinitionBuilder.setDefaultValue:(Lorg/jboss/dmr/ModelNode;)Lorg/jboss/as/controller/AbstractAttributeDefinitionBuilder;
     482: checkcast     #41                 // class org/jboss/as/controller/SimpleAttributeDefinitionBuilder
     485: iconst_1
     486: invokevirtual #53                 // Method org/jboss/as/controller/SimpleAttributeDefinitionBuilder.setAllowNull:(Z)Lorg/jboss/as/controller/AbstractAttributeDefinitionBuilder;
     489: checkcast     #41                 // class org/jboss/as/controller/SimpleAttributeDefinitionBuilder
     492: invokevirtual #54                 // Method org/jboss/as/controller/SimpleAttributeDefinitionBuilder.build:()Lorg/jboss/as/controller/SimpleAttributeDefinition;
     495: putstatic     #16                 // Field CONNECTOR_PROTOCOL_ATTRIBDEF:Lorg/jboss/as/controller/SimpleAttributeDefinition;
     498: new           #41                 // class org/jboss/as/controller/SimpleAttributeDefinitionBuilder
     501: dup
     502: ldc           #69                 // String socket-binding
     504: getstatic     #56                 // Field org/jboss/dmr/ModelType.STRING:Lorg/jboss/dmr/ModelType;
     507: invokespecial #44                 // Method org/jboss/as/controller/SimpleAttributeDefinitionBuilder."<init>":(Ljava/lang/String;Lorg/jboss/dmr/ModelType;)V
     510: iconst_1
     511: anewarray     #47                 // class org/jboss/as/controller/registry/AttributeAccess$Flag
     514: dup
     515: iconst_0
     516: getstatic     #48                 // Field org/jboss/as/controller/registry/AttributeAccess$Flag.RESTART_RESOURCE_SERVICES:Lorg/jboss/as/controller/registry/AttributeAccess$Flag;
     519: aastore
     520: invokevirtual #49                 // Method org/jboss/as/controller/SimpleAttributeDefinitionBuilder.setFlags:([Lorg/jboss/as/controller/registry/AttributeAccess$Flag;)Lorg/jboss/as/controller/AbstractAttributeDefinitionBuilder;
     523: checkcast     #41                 // class org/jboss/as/controller/SimpleAttributeDefinitionBuilder
     526: new           #50                 // class org/jboss/dmr/ModelNode
     529: dup
     530: ldc           #60                 // String org.hawkular.bus.broker
     532: invokespecial #58                 // Method org/jboss/dmr/ModelNode."<init>":(Ljava/lang/String;)V
     535: invokevirtual #52                 // Method org/jboss/as/controller/SimpleAttributeDefinitionBuilder.setDefaultValue:(Lorg/jboss/dmr/ModelNode;)Lorg/jboss/as/controller/AbstractAttributeDefinitionBuilder;
     538: checkcast     #41                 // class org/jboss/as/controller/SimpleAttributeDefinitionBuilder
     541: new           #70                 // class org/jboss/as/controller/operations/validation/StringLengthValidator
     544: dup
     545: iconst_1
     546: invokespecial #71                 // Method org/jboss/as/controller/operations/validation/StringLengthValidator."<init>":(I)V
     549: invokevirtual #72                 // Method org/jboss/as/controller/SimpleAttributeDefinitionBuilder.setValidator:(Lorg/jboss/as/controller/operations/validation/ParameterValidator;)Lorg/jboss/as/controller/AbstractAttributeDefinitionBuilder;
     552: checkcast     #41                 // class org/jboss/as/controller/SimpleAttributeDefinitionBuilder
     555: iconst_0
     556: invokevirtual #53                 // Method org/jboss/as/controller/SimpleAttributeDefinitionBuilder.setAllowNull:(Z)Lorg/jboss/as/controller/AbstractAttributeDefinitionBuilder;
     559: checkcast     #41                 // class org/jboss/as/controller/SimpleAttributeDefinitionBuilder
     562: invokevirtual #54                 // Method org/jboss/as/controller/SimpleAttributeDefinitionBuilder.build:()Lorg/jboss/as/controller/SimpleAttributeDefinition;
     565: putstatic     #17                 // Field SOCKET_BINDING_ATTRIBDEF:Lorg/jboss/as/controller/SimpleAttributeDefinition;
     568: new           #41                 // class org/jboss/as/controller/SimpleAttributeDefinitionBuilder
     571: dup
     572: ldc           #73                 // String discovery-socket-binding
     574: getstatic     #56                 // Field org/jboss/dmr/ModelType.STRING:Lorg/jboss/dmr/ModelType;
     577: invokespecial #44                 // Method org/jboss/as/controller/SimpleAttributeDefinitionBuilder."<init>":(Ljava/lang/String;Lorg/jboss/dmr/ModelType;)V
     580: iconst_1
     581: anewarray     #47                 // class org/jboss/as/controller/registry/AttributeAccess$Flag
     584: dup
     585: iconst_0
     586: getstatic     #48                 // Field org/jboss/as/controller/registry/AttributeAccess$Flag.RESTART_RESOURCE_SERVICES:Lorg/jboss/as/controller/registry/AttributeAccess$Flag;
     589: aastore
     590: invokevirtual #49                 // Method org/jboss/as/controller/SimpleAttributeDefinitionBuilder.setFlags:([Lorg/jboss/as/controller/registry/AttributeAccess$Flag;)Lorg/jboss/as/controller/AbstractAttributeDefinitionBuilder;
     593: checkcast     #41                 // class org/jboss/as/controller/SimpleAttributeDefinitionBuilder
     596: new           #50                 // class org/jboss/dmr/ModelNode
     599: dup
     600: ldc           #74                 // String org.hawkular.bus.broker.discovery
     602: invokespecial #58                 // Method org/jboss/dmr/ModelNode."<init>":(Ljava/lang/String;)V
     605: invokevirtual #52                 // Method org/jboss/as/controller/SimpleAttributeDefinitionBuilder.setDefaultValue:(Lorg/jboss/dmr/ModelNode;)Lorg/jboss/as/controller/AbstractAttributeDefinitionBuilder;
     608: checkcast     #41                 // class org/jboss/as/controller/SimpleAttributeDefinitionBuilder
     611: new           #70                 // class org/jboss/as/controller/operations/validation/StringLengthValidator
     614: dup
     615: iconst_1
     616: invokespecial #71                 // Method org/jboss/as/controller/operations/validation/StringLengthValidator."<init>":(I)V
     619: invokevirtual #72                 // Method org/jboss/as/controller/SimpleAttributeDefinitionBuilder.setValidator:(Lorg/jboss/as/controller/operations/validation/ParameterValidator;)Lorg/jboss/as/controller/AbstractAttributeDefinitionBuilder;
     622: checkcast     #41                 // class org/jboss/as/controller/SimpleAttributeDefinitionBuilder
     625: iconst_0
     626: invokevirtual #53                 // Method org/jboss/as/controller/SimpleAttributeDefinitionBuilder.setAllowNull:(Z)Lorg/jboss/as/controller/AbstractAttributeDefinitionBuilder;
     629: checkcast     #41                 // class org/jboss/as/controller/SimpleAttributeDefinitionBuilder
     632: invokevirtual #54                 // Method org/jboss/as/controller/SimpleAttributeDefinitionBuilder.build:()Lorg/jboss/as/controller/SimpleAttributeDefinition;
     635: putstatic     #18                 // Field DISCOVERY_SOCKET_BINDING_ATTRIBDEF:Lorg/jboss/as/controller/SimpleAttributeDefinition;
     638: new           #41                 // class org/jboss/as/controller/SimpleAttributeDefinitionBuilder
     641: dup
     642: ldc           #75                 // String restart
     644: getstatic     #43                 // Field org/jboss/dmr/ModelType.BOOLEAN:Lorg/jboss/dmr/ModelType;
     647: invokespecial #44                 // Method org/jboss/as/controller/SimpleAttributeDefinitionBuilder."<init>":(Ljava/lang/String;Lorg/jboss/dmr/ModelType;)V
     650: iconst_1
     651: invokevirtual #45                 // Method org/jboss/as/controller/SimpleAttributeDefinitionBuilder.setAllowExpression:(Z)Lorg/jboss/as/controller/AbstractAttributeDefinitionBuilder;
     654: checkcast     #41                 // class org/jboss/as/controller/SimpleAttributeDefinitionBuilder
     657: new           #50                 // class org/jboss/dmr/ModelNode
     660: dup
     661: iconst_0
     662: invokespecial #51                 // Method org/jboss/dmr/ModelNode."<init>":(Z)V
     665: invokevirtual #52                 // Method org/jboss/as/controller/SimpleAttributeDefinitionBuilder.setDefaultValue:(Lorg/jboss/dmr/ModelNode;)Lorg/jboss/as/controller/AbstractAttributeDefinitionBuilder;
     668: checkcast     #41                 // class org/jboss/as/controller/SimpleAttributeDefinitionBuilder
     671: invokevirtual #54                 // Method org/jboss/as/controller/SimpleAttributeDefinitionBuilder.build:()Lorg/jboss/as/controller/SimpleAttributeDefinition;
     674: putstatic     #30                 // Field START_OP_PARAM_RESTART:Lorg/jboss/as/controller/SimpleAttributeDefinition;
     677: return
}
