Compiled from "BrokerSubsystemAdd.java"
class org.hawkular.bus.broker.extension.BrokerSubsystemAdd extends org.jboss.as.controller.AbstractAddStepHandler {
  static final org.hawkular.bus.broker.extension.BrokerSubsystemAdd INSTANCE;

  private final org.hawkular.bus.broker.extension.log.MsgLogger msglog;

  private final org.jboss.logging.Logger log;

  private org.hawkular.bus.broker.extension.BrokerSubsystemAdd();
    Code:
       0: aload_0
       1: invokespecial #2                  // Method org/jboss/as/controller/AbstractAddStepHandler."<init>":()V
       4: aload_0
       5: getstatic     #3                  // Field org/hawkular/bus/broker/extension/log/MsgLogger.LOGGER:Lorg/hawkular/bus/broker/extension/log/MsgLogger;
       8: putfield      #4                  // Field msglog:Lorg/hawkular/bus/broker/extension/log/MsgLogger;
      11: aload_0
      12: ldc           #5                  // class org/hawkular/bus/broker/extension/BrokerSubsystemAdd
      14: invokestatic  #6                  // Method org/jboss/logging/Logger.getLogger:(Ljava/lang/Class;)Lorg/jboss/logging/Logger;
      17: putfield      #7                  // Field log:Lorg/jboss/logging/Logger;
      20: return

  protected void populateModel(org.jboss.as.controller.OperationContext, org.jboss.dmr.ModelNode, org.jboss.as.controller.registry.Resource) throws org.jboss.as.controller.OperationFailedException;
    Code:
       0: aload_0
       1: aload_1
       2: invokevirtual #8                  // Method requiresRuntime:(Lorg/jboss/as/controller/OperationContext;)Z
       5: ifeq          240
       8: iconst_1
       9: anewarray     #9                  // class org/jboss/as/controller/PathElement
      12: dup
      13: iconst_0
      14: ldc           #10                 // String deployment
      16: ldc           #12                 // String rest.war
      18: invokestatic  #13                 // Method org/jboss/as/controller/PathElement.pathElement:(Ljava/lang/String;Ljava/lang/String;)Lorg/jboss/as/controller/PathElement;
      21: aastore
      22: invokestatic  #14                 // Method org/jboss/as/controller/PathAddress.pathAddress:([Lorg/jboss/as/controller/PathElement;)Lorg/jboss/as/controller/PathAddress;
      25: astore        4
      27: ldc           #15                 // String add
      29: aload         4
      31: invokevirtual #16                 // Method org/jboss/as/controller/PathAddress.toModelNode:()Lorg/jboss/dmr/ModelNode;
      34: invokestatic  #17                 // Method org/jboss/as/controller/operations/common/Util.getEmptyOperation:(Ljava/lang/String;Lorg/jboss/dmr/ModelNode;)Lorg/jboss/dmr/ModelNode;
      37: astore        5
      39: aload         5
      41: ldc           #18                 // String enabled
      43: invokevirtual #19                 // Method org/jboss/dmr/ModelNode.get:(Ljava/lang/String;)Lorg/jboss/dmr/ModelNode;
      46: iconst_1
      47: invokevirtual #20                 // Method org/jboss/dmr/ModelNode.set:(Z)Lorg/jboss/dmr/ModelNode;
      50: pop
      51: aload         5
      53: ldc           #21                 // String persistent
      55: invokevirtual #19                 // Method org/jboss/dmr/ModelNode.get:(Ljava/lang/String;)Lorg/jboss/dmr/ModelNode;
      58: iconst_0
      59: invokevirtual #20                 // Method org/jboss/dmr/ModelNode.set:(Z)Lorg/jboss/dmr/ModelNode;
      62: pop
      63: ldc           #22                 // class org/hawkular/bus/broker/extension/BrokerService
      65: invokestatic  #23                 // Method org/jboss/modules/Module.forClass:(Ljava/lang/Class;)Lorg/jboss/modules/Module;
      68: astore        6
      70: aload         6
      72: ldc           #12                 // String rest.war
      74: invokevirtual #24                 // Method org/jboss/modules/Module.getExportedResource:(Ljava/lang/String;)Ljava/net/URL;
      77: astore        7
      79: aload         7
      81: ifnonnull     94
      84: new           #25                 // class java/io/FileNotFoundException
      87: dup
      88: ldc           #26                 // String Could not find the REST WAR
      90: invokespecial #27                 // Method java/io/FileNotFoundException."<init>":(Ljava/lang/String;)V
      93: athrow
      94: new           #28                 // class org/jboss/dmr/ModelNode
      97: dup
      98: invokespecial #29                 // Method org/jboss/dmr/ModelNode."<init>":()V
     101: astore        8
     103: new           #30                 // class java/io/File
     106: dup
     107: aload         7
     109: invokevirtual #31                 // Method java/net/URL.toURI:()Ljava/net/URI;
     112: invokespecial #32                 // Method java/io/File."<init>":(Ljava/net/URI;)V
     115: invokevirtual #33                 // Method java/io/File.getAbsolutePath:()Ljava/lang/String;
     118: astore        9
     120: new           #30                 // class java/io/File
     123: dup
     124: aload         9
     126: invokespecial #34                 // Method java/io/File."<init>":(Ljava/lang/String;)V
     129: invokevirtual #35                 // Method java/io/File.exists:()Z
     132: ifne          168
     135: new           #25                 // class java/io/FileNotFoundException
     138: dup
     139: new           #36                 // class java/lang/StringBuilder
     142: dup
     143: invokespecial #37                 // Method java/lang/StringBuilder."<init>":()V
     146: ldc           #38                 // String Missing the WAR at [
     148: invokevirtual #39                 // Method java/lang/StringBuilder.append:(Ljava/lang/String;)Ljava/lang/StringBuilder;
     151: aload         9
     153: invokevirtual #39                 // Method java/lang/StringBuilder.append:(Ljava/lang/String;)Ljava/lang/StringBuilder;
     156: ldc           #40                 // String ]
     158: invokevirtual #39                 // Method java/lang/StringBuilder.append:(Ljava/lang/String;)Ljava/lang/StringBuilder;
     161: invokevirtual #41                 // Method java/lang/StringBuilder.toString:()Ljava/lang/String;
     164: invokespecial #27                 // Method java/io/FileNotFoundException."<init>":(Ljava/lang/String;)V
     167: athrow
     168: aload         8
     170: ldc           #42                 // String path
     172: invokevirtual #19                 // Method org/jboss/dmr/ModelNode.get:(Ljava/lang/String;)Lorg/jboss/dmr/ModelNode;
     175: aload         9
     177: invokevirtual #43                 // Method org/jboss/dmr/ModelNode.set:(Ljava/lang/String;)Lorg/jboss/dmr/ModelNode;
     180: pop
     181: aload         8
     183: ldc           #44                 // String archive
     185: invokevirtual #19                 // Method org/jboss/dmr/ModelNode.get:(Ljava/lang/String;)Lorg/jboss/dmr/ModelNode;
     188: iconst_0
     189: invokevirtual #20                 // Method org/jboss/dmr/ModelNode.set:(Z)Lorg/jboss/dmr/ModelNode;
     192: pop
     193: aload         5
     195: ldc           #45                 // String content
     197: invokevirtual #19                 // Method org/jboss/dmr/ModelNode.get:(Ljava/lang/String;)Lorg/jboss/dmr/ModelNode;
     200: aload         8
     202: invokevirtual #46                 // Method org/jboss/dmr/ModelNode.add:(Lorg/jboss/dmr/ModelNode;)Lorg/jboss/dmr/ModelNode;
     205: pop
     206: aload_1
     207: invokeinterface #47,  1           // InterfaceMethod org/jboss/as/controller/OperationContext.getRootResourceRegistration:()Lorg/jboss/as/controller/registry/ImmutableManagementResourceRegistration;
     212: astore        10
     214: aload         10
     216: aload         4
     218: ldc           #15                 // String add
     220: invokeinterface #48,  3           // InterfaceMethod org/jboss/as/controller/registry/ImmutableManagementResourceRegistration.getOperationHandler:(Lorg/jboss/as/controller/PathAddress;Ljava/lang/String;)Lorg/jboss/as/controller/OperationStepHandler;
     225: astore        11
     227: aload_1
     228: aload         5
     230: aload         11
     232: getstatic     #49                 // Field org/jboss/as/controller/OperationContext$Stage.MODEL:Lorg/jboss/as/controller/OperationContext$Stage;
     235: invokeinterface #50,  4           // InterfaceMethod org/jboss/as/controller/OperationContext.addStep:(Lorg/jboss/dmr/ModelNode;Lorg/jboss/as/controller/OperationStepHandler;Lorg/jboss/as/controller/OperationContext$Stage;)V
     240: goto          270
     243: astore        4
     245: aload_0
     246: getfield      #4                  // Field msglog:Lorg/hawkular/bus/broker/extension/log/MsgLogger;
     249: aload         4
     251: invokevirtual #52                 // Method java/lang/Exception.toString:()Ljava/lang/String;
     254: invokeinterface #53,  2           // InterfaceMethod org/hawkular/bus/broker/extension/log/MsgLogger.errorRestWarCouldNotBeDeployed:(Ljava/lang/String;)V
     259: aload_0
     260: getfield      #7                  // Field log:Lorg/jboss/logging/Logger;
     263: ldc           #54                 // String The REST WAR deployment exception stack is logged with this message
     265: aload         4
     267: invokevirtual #55                 // Method org/jboss/logging/Logger.debug:(Ljava/lang/Object;Ljava/lang/Throwable;)V
     270: aload_0
     271: aload_2
     272: aload_3
     273: invokeinterface #56,  1           // InterfaceMethod org/jboss/as/controller/registry/Resource.getModel:()Lorg/jboss/dmr/ModelNode;
     278: invokevirtual #57                 // Method populateModel:(Lorg/jboss/dmr/ModelNode;Lorg/jboss/dmr/ModelNode;)V
     281: return
    Exception table:
       from    to  target type
           0   240   243   Class java/lang/Exception

  protected void populateModel(org.jboss.dmr.ModelNode, org.jboss.dmr.ModelNode) throws org.jboss.as.controller.OperationFailedException;
    Code:
       0: getstatic     #58                 // Field org/hawkular/bus/broker/extension/BrokerSubsystemDefinition.BROKER_ENABLED_ATTRIBDEF:Lorg/jboss/as/controller/SimpleAttributeDefinition;
       3: aload_1
       4: aload_2
       5: invokevirtual #59                 // Method org/jboss/as/controller/SimpleAttributeDefinition.validateAndSet:(Lorg/jboss/dmr/ModelNode;Lorg/jboss/dmr/ModelNode;)V
       8: getstatic     #60                 // Field org/hawkular/bus/broker/extension/BrokerSubsystemDefinition.BROKER_CONFIG_FILE_ATTRIBDEF:Lorg/jboss/as/controller/SimpleAttributeDefinition;
      11: aload_1
      12: aload_2
      13: invokevirtual #59                 // Method org/jboss/as/controller/SimpleAttributeDefinition.validateAndSet:(Lorg/jboss/dmr/ModelNode;Lorg/jboss/dmr/ModelNode;)V
      16: getstatic     #61                 // Field org/hawkular/bus/broker/extension/BrokerSubsystemDefinition.BROKER_NAME_ATTRIBDEF:Lorg/jboss/as/controller/SimpleAttributeDefinition;
      19: aload_1
      20: aload_2
      21: invokevirtual #59                 // Method org/jboss/as/controller/SimpleAttributeDefinition.validateAndSet:(Lorg/jboss/dmr/ModelNode;Lorg/jboss/dmr/ModelNode;)V
      24: getstatic     #62                 // Field org/hawkular/bus/broker/extension/BrokerSubsystemDefinition.BROKER_PERSISTENT_ATTRIBDEF:Lorg/jboss/as/controller/SimpleAttributeDefinition;
      27: aload_1
      28: aload_2
      29: invokevirtual #59                 // Method org/jboss/as/controller/SimpleAttributeDefinition.validateAndSet:(Lorg/jboss/dmr/ModelNode;Lorg/jboss/dmr/ModelNode;)V
      32: getstatic     #63                 // Field org/hawkular/bus/broker/extension/BrokerSubsystemDefinition.BROKER_USE_JMX_ATTRIBDEF:Lorg/jboss/as/controller/SimpleAttributeDefinition;
      35: aload_1
      36: aload_2
      37: invokevirtual #59                 // Method org/jboss/as/controller/SimpleAttributeDefinition.validateAndSet:(Lorg/jboss/dmr/ModelNode;Lorg/jboss/dmr/ModelNode;)V
      40: getstatic     #64                 // Field org/hawkular/bus/broker/extension/BrokerSubsystemDefinition.CUSTOM_CONFIG_ATTRIBDEF:Lorg/hawkular/bus/broker/extension/CustomConfigAttributeDefinition;
      43: aload_1
      44: aload_2
      45: invokevirtual #65                 // Method org/hawkular/bus/broker/extension/CustomConfigAttributeDefinition.validateAndSet:(Lorg/jboss/dmr/ModelNode;Lorg/jboss/dmr/ModelNode;)V
      48: getstatic     #66                 // Field org/hawkular/bus/broker/extension/BrokerSubsystemDefinition.CONNECTOR_NAME_ATTRIBDEF:Lorg/jboss/as/controller/SimpleAttributeDefinition;
      51: aload_1
      52: aload_2
      53: invokevirtual #59                 // Method org/jboss/as/controller/SimpleAttributeDefinition.validateAndSet:(Lorg/jboss/dmr/ModelNode;Lorg/jboss/dmr/ModelNode;)V
      56: getstatic     #67                 // Field org/hawkular/bus/broker/extension/BrokerSubsystemDefinition.CONNECTOR_PROTOCOL_ATTRIBDEF:Lorg/jboss/as/controller/SimpleAttributeDefinition;
      59: aload_1
      60: aload_2
      61: invokevirtual #59                 // Method org/jboss/as/controller/SimpleAttributeDefinition.validateAndSet:(Lorg/jboss/dmr/ModelNode;Lorg/jboss/dmr/ModelNode;)V
      64: getstatic     #68                 // Field org/hawkular/bus/broker/extension/BrokerSubsystemDefinition.SOCKET_BINDING_ATTRIBDEF:Lorg/jboss/as/controller/SimpleAttributeDefinition;
      67: aload_1
      68: aload_2
      69: invokevirtual #59                 // Method org/jboss/as/controller/SimpleAttributeDefinition.validateAndSet:(Lorg/jboss/dmr/ModelNode;Lorg/jboss/dmr/ModelNode;)V
      72: getstatic     #69                 // Field org/hawkular/bus/broker/extension/BrokerSubsystemDefinition.DISCOVERY_SOCKET_BINDING_ATTRIBDEF:Lorg/jboss/as/controller/SimpleAttributeDefinition;
      75: aload_1
      76: aload_2
      77: invokevirtual #59                 // Method org/jboss/as/controller/SimpleAttributeDefinition.validateAndSet:(Lorg/jboss/dmr/ModelNode;Lorg/jboss/dmr/ModelNode;)V
      80: aload_0
      81: getfield      #7                  // Field log:Lorg/jboss/logging/Logger;
      84: ldc           #70                 // String Populating the Broker subsystem model: [%s=%s]
      86: aload_1
      87: aload_2
      88: invokevirtual #71                 // Method org/jboss/logging/Logger.debugf:(Ljava/lang/String;Ljava/lang/Object;Ljava/lang/Object;)V
      91: return

  protected void performRuntime(org.jboss.as.controller.OperationContext, org.jboss.dmr.ModelNode, org.jboss.dmr.ModelNode, org.jboss.as.controller.ServiceVerificationHandler, java.util.List<org.jboss.msc.service.ServiceController<?>>) throws org.jboss.as.controller.OperationFailedException;
    Code:
       0: getstatic     #58                 // Field org/hawkular/bus/broker/extension/BrokerSubsystemDefinition.BROKER_ENABLED_ATTRIBDEF:Lorg/jboss/as/controller/SimpleAttributeDefinition;
       3: aload_1
       4: aload_3
       5: invokevirtual #72                 // Method org/jboss/as/controller/SimpleAttributeDefinition.resolveModelAttribute:(Lorg/jboss/as/controller/OperationContext;Lorg/jboss/dmr/ModelNode;)Lorg/jboss/dmr/ModelNode;
       8: iconst_0
       9: invokevirtual #73                 // Method org/jboss/dmr/ModelNode.asBoolean:(Z)Z
      12: istore        6
      14: iload         6
      16: ifne          29
      19: aload_0
      20: getfield      #4                  // Field msglog:Lorg/hawkular/bus/broker/extension/log/MsgLogger;
      23: invokeinterface #74,  1           // InterfaceMethod org/hawkular/bus/broker/extension/log/MsgLogger.infoBrokerNotEnabled:()V
      28: return
      29: getstatic     #60                 // Field org/hawkular/bus/broker/extension/BrokerSubsystemDefinition.BROKER_CONFIG_FILE_ATTRIBDEF:Lorg/jboss/as/controller/SimpleAttributeDefinition;
      32: aload_1
      33: aload_3
      34: invokevirtual #72                 // Method org/jboss/as/controller/SimpleAttributeDefinition.resolveModelAttribute:(Lorg/jboss/as/controller/OperationContext;Lorg/jboss/dmr/ModelNode;)Lorg/jboss/dmr/ModelNode;
      37: invokevirtual #75                 // Method org/jboss/dmr/ModelNode.asString:()Ljava/lang/String;
      40: astore        7
      42: aload         7
      44: ifnull        58
      47: aload         7
      49: invokevirtual #76                 // Method java/lang/String.trim:()Ljava/lang/String;
      52: invokevirtual #77                 // Method java/lang/String.isEmpty:()Z
      55: ifeq          62
      58: ldc           #78                 // String default-broker.xml
      60: astore        7
      62: aload_0
      63: getfield      #4                  // Field msglog:Lorg/hawkular/bus/broker/extension/log/MsgLogger;
      66: aload         7
      68: invokeinterface #79,  2           // InterfaceMethod org/hawkular/bus/broker/extension/log/MsgLogger.infoBrokerEnabledWithConfigFile:(Ljava/lang/String;)V
      73: new           #80                 // class java/util/HashMap
      76: dup
      77: invokespecial #81                 // Method java/util/HashMap."<init>":()V
      80: astore        8
      82: aload_0
      83: aload_1
      84: aload_3
      85: aload         8
      87: getstatic     #61                 // Field org/hawkular/bus/broker/extension/BrokerSubsystemDefinition.BROKER_NAME_ATTRIBDEF:Lorg/jboss/as/controller/SimpleAttributeDefinition;
      90: invokespecial #82                 // Method addCustomConfigProperty:(Lorg/jboss/as/controller/OperationContext;Lorg/jboss/dmr/ModelNode;Ljava/util/Map;Lorg/jboss/as/controller/AttributeDefinition;)V
      93: aload_0
      94: aload_1
      95: aload_3
      96: aload         8
      98: getstatic     #62                 // Field org/hawkular/bus/broker/extension/BrokerSubsystemDefinition.BROKER_PERSISTENT_ATTRIBDEF:Lorg/jboss/as/controller/SimpleAttributeDefinition;
     101: invokespecial #82                 // Method addCustomConfigProperty:(Lorg/jboss/as/controller/OperationContext;Lorg/jboss/dmr/ModelNode;Ljava/util/Map;Lorg/jboss/as/controller/AttributeDefinition;)V
     104: aload_0
     105: aload_1
     106: aload_3
     107: aload         8
     109: getstatic     #63                 // Field org/hawkular/bus/broker/extension/BrokerSubsystemDefinition.BROKER_USE_JMX_ATTRIBDEF:Lorg/jboss/as/controller/SimpleAttributeDefinition;
     112: invokespecial #82                 // Method addCustomConfigProperty:(Lorg/jboss/as/controller/OperationContext;Lorg/jboss/dmr/ModelNode;Ljava/util/Map;Lorg/jboss/as/controller/AttributeDefinition;)V
     115: aload_0
     116: aload_1
     117: aload_3
     118: aload         8
     120: getstatic     #66                 // Field org/hawkular/bus/broker/extension/BrokerSubsystemDefinition.CONNECTOR_NAME_ATTRIBDEF:Lorg/jboss/as/controller/SimpleAttributeDefinition;
     123: invokespecial #82                 // Method addCustomConfigProperty:(Lorg/jboss/as/controller/OperationContext;Lorg/jboss/dmr/ModelNode;Ljava/util/Map;Lorg/jboss/as/controller/AttributeDefinition;)V
     126: aload_0
     127: aload_1
     128: aload_3
     129: aload         8
     131: getstatic     #67                 // Field org/hawkular/bus/broker/extension/BrokerSubsystemDefinition.CONNECTOR_PROTOCOL_ATTRIBDEF:Lorg/jboss/as/controller/SimpleAttributeDefinition;
     134: invokespecial #82                 // Method addCustomConfigProperty:(Lorg/jboss/as/controller/OperationContext;Lorg/jboss/dmr/ModelNode;Ljava/util/Map;Lorg/jboss/as/controller/AttributeDefinition;)V
     137: getstatic     #64                 // Field org/hawkular/bus/broker/extension/BrokerSubsystemDefinition.CUSTOM_CONFIG_ATTRIBDEF:Lorg/hawkular/bus/broker/extension/CustomConfigAttributeDefinition;
     140: aload_1
     141: aload_3
     142: invokevirtual #83                 // Method org/hawkular/bus/broker/extension/CustomConfigAttributeDefinition.resolveModelAttribute:(Lorg/jboss/as/controller/OperationContext;Lorg/jboss/dmr/ModelNode;)Lorg/jboss/dmr/ModelNode;
     145: astore        9
     147: aload         9
     149: ifnull        246
     152: aload         9
     154: invokevirtual #84                 // Method org/jboss/dmr/ModelNode.isDefined:()Z
     157: ifeq          246
     160: new           #80                 // class java/util/HashMap
     163: dup
     164: invokespecial #81                 // Method java/util/HashMap."<init>":()V
     167: astore        10
     169: aload         9
     171: invokevirtual #85                 // Method org/jboss/dmr/ModelNode.asPropertyList:()Ljava/util/List;
     174: astore        11
     176: aload         11
     178: invokeinterface #86,  1           // InterfaceMethod java/util/List.iterator:()Ljava/util/Iterator;
     183: astore        12
     185: aload         12
     187: invokeinterface #87,  1           // InterfaceMethod java/util/Iterator.hasNext:()Z
     192: ifeq          237
     195: aload         12
     197: invokeinterface #88,  1           // InterfaceMethod java/util/Iterator.next:()Ljava/lang/Object;
     202: checkcast     #89                 // class org/jboss/dmr/Property
     205: astore        13
     207: aload         13
     209: invokevirtual #90                 // Method org/jboss/dmr/Property.getName:()Ljava/lang/String;
     212: astore        14
     214: aload         13
     216: invokevirtual #91                 // Method org/jboss/dmr/Property.getValue:()Lorg/jboss/dmr/ModelNode;
     219: invokevirtual #75                 // Method org/jboss/dmr/ModelNode.asString:()Ljava/lang/String;
     222: astore        15
     224: aload         10
     226: aload         14
     228: aload         15
     230: invokevirtual #92                 // Method java/util/HashMap.put:(Ljava/lang/Object;Ljava/lang/Object;)Ljava/lang/Object;
     233: pop
     234: goto          185
     237: aload         8
     239: aload         10
     241: invokeinterface #93,  2           // InterfaceMethod java/util/Map.putAll:(Ljava/util/Map;)V
     246: new           #22                 // class org/hawkular/bus/broker/extension/BrokerService
     249: dup
     250: invokespecial #94                 // Method org/hawkular/bus/broker/extension/BrokerService."<init>":()V
     253: astore        10
     255: aload         10
     257: aload         7
     259: invokevirtual #95                 // Method org/hawkular/bus/broker/extension/BrokerService.setConfigurationFile:(Ljava/lang/String;)V
     262: aload         10
     264: aload         8
     266: invokevirtual #96                 // Method org/hawkular/bus/broker/extension/BrokerService.setCustomConfigurationProperties:(Ljava/util/Map;)V
     269: getstatic     #68                 // Field org/hawkular/bus/broker/extension/BrokerSubsystemDefinition.SOCKET_BINDING_ATTRIBDEF:Lorg/jboss/as/controller/SimpleAttributeDefinition;
     272: aload_1
     273: aload_3
     274: invokevirtual #72                 // Method org/jboss/as/controller/SimpleAttributeDefinition.resolveModelAttribute:(Lorg/jboss/as/controller/OperationContext;Lorg/jboss/dmr/ModelNode;)Lorg/jboss/dmr/ModelNode;
     277: invokevirtual #75                 // Method org/jboss/dmr/ModelNode.asString:()Ljava/lang/String;
     280: astore        11
     282: getstatic     #69                 // Field org/hawkular/bus/broker/extension/BrokerSubsystemDefinition.DISCOVERY_SOCKET_BINDING_ATTRIBDEF:Lorg/jboss/as/controller/SimpleAttributeDefinition;
     285: aload_1
     286: aload_3
     287: invokevirtual #72                 // Method org/jboss/as/controller/SimpleAttributeDefinition.resolveModelAttribute:(Lorg/jboss/as/controller/OperationContext;Lorg/jboss/dmr/ModelNode;)Lorg/jboss/dmr/ModelNode;
     290: invokevirtual #75                 // Method org/jboss/dmr/ModelNode.asString:()Ljava/lang/String;
     293: astore        12
     295: getstatic     #97                 // Field org/hawkular/bus/broker/extension/BrokerService.SERVICE_NAME:Lorg/jboss/msc/service/ServiceName;
     298: astore        13
     300: aload_1
     301: invokeinterface #98,  1           // InterfaceMethod org/jboss/as/controller/OperationContext.getServiceTarget:()Lorg/jboss/msc/service/ServiceTarget;
     306: aload         13
     308: aload         10
     310: invokeinterface #99,  3           // InterfaceMethod org/jboss/msc/service/ServiceTarget.addService:(Lorg/jboss/msc/service/ServiceName;Lorg/jboss/msc/service/Service;)Lorg/jboss/msc/service/ServiceBuilder;
     315: getstatic     #100                // Field org/jboss/as/server/ServerEnvironmentService.SERVICE_NAME:Lorg/jboss/msc/service/ServiceName;
     318: ldc           #101                // class org/jboss/as/server/ServerEnvironment
     320: aload         10
     322: getfield      #102                // Field org/hawkular/bus/broker/extension/BrokerService.envServiceValue:Lorg/jboss/msc/value/InjectedValue;
     325: invokeinterface #103,  4          // InterfaceMethod org/jboss/msc/service/ServiceBuilder.addDependency:(Lorg/jboss/msc/service/ServiceName;Ljava/lang/Class;Lorg/jboss/msc/inject/Injector;)Lorg/jboss/msc/service/ServiceBuilder;
     330: getstatic     #104                // Field org/jboss/as/network/SocketBinding.JBOSS_BINDING_NAME:Lorg/jboss/msc/service/ServiceName;
     333: iconst_1
     334: anewarray     #105                // class java/lang/String
     337: dup
     338: iconst_0
     339: aload         11
     341: aastore
     342: invokevirtual #106                // Method org/jboss/msc/service/ServiceName.append:([Ljava/lang/String;)Lorg/jboss/msc/service/ServiceName;
     345: ldc           #107                // class org/jboss/as/network/SocketBinding
     347: aload         10
     349: getfield      #108                // Field org/hawkular/bus/broker/extension/BrokerService.connectorSocketBinding:Lorg/jboss/msc/value/InjectedValue;
     352: invokeinterface #103,  4          // InterfaceMethod org/jboss/msc/service/ServiceBuilder.addDependency:(Lorg/jboss/msc/service/ServiceName;Ljava/lang/Class;Lorg/jboss/msc/inject/Injector;)Lorg/jboss/msc/service/ServiceBuilder;
     357: getstatic     #104                // Field org/jboss/as/network/SocketBinding.JBOSS_BINDING_NAME:Lorg/jboss/msc/service/ServiceName;
     360: iconst_1
     361: anewarray     #105                // class java/lang/String
     364: dup
     365: iconst_0
     366: aload         12
     368: aastore
     369: invokevirtual #106                // Method org/jboss/msc/service/ServiceName.append:([Ljava/lang/String;)Lorg/jboss/msc/service/ServiceName;
     372: ldc           #107                // class org/jboss/as/network/SocketBinding
     374: aload         10
     376: getfield      #109                // Field org/hawkular/bus/broker/extension/BrokerService.discoverySocketBinding:Lorg/jboss/msc/value/InjectedValue;
     379: invokeinterface #103,  4          // InterfaceMethod org/jboss/msc/service/ServiceBuilder.addDependency:(Lorg/jboss/msc/service/ServiceName;Ljava/lang/Class;Lorg/jboss/msc/inject/Injector;)Lorg/jboss/msc/service/ServiceBuilder;
     384: aload         4
     386: invokeinterface #110,  2          // InterfaceMethod org/jboss/msc/service/ServiceBuilder.addListener:(Lorg/jboss/msc/service/ServiceListener;)Lorg/jboss/msc/service/ServiceBuilder;
     391: getstatic     #111                // Field org/jboss/msc/service/ServiceController$Mode.ACTIVE:Lorg/jboss/msc/service/ServiceController$Mode;
     394: invokeinterface #112,  2          // InterfaceMethod org/jboss/msc/service/ServiceBuilder.setInitialMode:(Lorg/jboss/msc/service/ServiceController$Mode;)Lorg/jboss/msc/service/ServiceBuilder;
     399: invokeinterface #113,  1          // InterfaceMethod org/jboss/msc/service/ServiceBuilder.install:()Lorg/jboss/msc/service/ServiceController;
     404: astore        14
     406: aload         5
     408: aload         14
     410: invokeinterface #114,  2          // InterfaceMethod java/util/List.add:(Ljava/lang/Object;)Z
     415: pop
     416: return

  private void addCustomConfigProperty(org.jboss.as.controller.OperationContext, org.jboss.dmr.ModelNode, java.util.Map<java.lang.String, java.lang.String>, org.jboss.as.controller.AttributeDefinition) throws org.jboss.as.controller.OperationFailedException;
    Code:
       0: aload_0
       1: aload_1
       2: aload_2
       3: aload_3
       4: aload         4
       6: aconst_null
       7: invokespecial #115                // Method addCustomConfigProperty:(Lorg/jboss/as/controller/OperationContext;Lorg/jboss/dmr/ModelNode;Ljava/util/Map;Lorg/jboss/as/controller/AttributeDefinition;Ljava/lang/String;)V
      10: return

  private void addCustomConfigProperty(org.jboss.as.controller.OperationContext, org.jboss.dmr.ModelNode, java.util.Map<java.lang.String, java.lang.String>, org.jboss.as.controller.AttributeDefinition, java.lang.String) throws org.jboss.as.controller.OperationFailedException;
    Code:
       0: aload         4
       2: aload_1
       3: aload_2
       4: invokevirtual #116                // Method org/jboss/as/controller/AttributeDefinition.resolveModelAttribute:(Lorg/jboss/as/controller/OperationContext;Lorg/jboss/dmr/ModelNode;)Lorg/jboss/dmr/ModelNode;
       7: astore        6
       9: aload         6
      11: invokevirtual #84                 // Method org/jboss/dmr/ModelNode.isDefined:()Z
      14: ifeq          44
      17: aload_3
      18: aload         5
      20: ifnonnull     31
      23: aload         4
      25: invokevirtual #117                // Method org/jboss/as/controller/AttributeDefinition.getName:()Ljava/lang/String;
      28: goto          33
      31: aload         5
      33: aload         6
      35: invokevirtual #75                 // Method org/jboss/dmr/ModelNode.asString:()Ljava/lang/String;
      38: invokeinterface #118,  3          // InterfaceMethod java/util/Map.put:(Ljava/lang/Object;Ljava/lang/Object;)Ljava/lang/Object;
      43: pop
      44: return

  static {};
    Code:
       0: new           #5                  // class org/hawkular/bus/broker/extension/BrokerSubsystemAdd
       3: dup
       4: invokespecial #119                // Method "<init>":()V
       7: putstatic     #120                // Field INSTANCE:Lorg/hawkular/bus/broker/extension/BrokerSubsystemAdd;
      10: return
}
