Compiled from "LevelRangeFilter.java"
public final class org.jboss.logmanager.filters.LevelRangeFilter implements java.util.logging.Filter {
  private final int min;

  private final int max;

  private final boolean minInclusive;

  private final boolean maxInclusive;

  public org.jboss.logmanager.filters.LevelRangeFilter(java.util.logging.Level, boolean, java.util.logging.Level, boolean);
    Code:
       0: aload_0
       1: invokespecial #1                  // Method java/lang/Object."<init>":()V
       4: aload_0
       5: iload_2
       6: putfield      #2                  // Field minInclusive:Z
       9: aload_0
      10: iload         4
      12: putfield      #3                  // Field maxInclusive:Z
      15: aload_0
      16: aload_1
      17: invokevirtual #4                  // Method java/util/logging/Level.intValue:()I
      20: putfield      #5                  // Field min:I
      23: aload_0
      24: aload_3
      25: invokevirtual #4                  // Method java/util/logging/Level.intValue:()I
      28: putfield      #6                  // Field max:I
      31: aload_0
      32: getfield      #6                  // Field max:I
      35: aload_0
      36: getfield      #5                  // Field min:I
      39: if_icmpge     52
      42: new           #7                  // class java/lang/IllegalArgumentException
      45: dup
      46: ldc           #8                  // String Max level cannot be less than min level
      48: invokespecial #9                  // Method java/lang/IllegalArgumentException."<init>":(Ljava/lang/String;)V
      51: athrow
      52: return

  public boolean isLoggable(java.util.logging.LogRecord);
    Code:
       0: aload_1
       1: invokevirtual #10                 // Method java/util/logging/LogRecord.getLevel:()Ljava/util/logging/Level;
       4: invokevirtual #4                  // Method java/util/logging/Level.intValue:()I
       7: istore_2
       8: aload_0
       9: getfield      #2                  // Field minInclusive:Z
      12: ifeq          26
      15: aload_0
      16: getfield      #5                  // Field min:I
      19: iload_2
      20: if_icmpgt     64
      23: goto          34
      26: aload_0
      27: getfield      #5                  // Field min:I
      30: iload_2
      31: if_icmpge     64
      34: aload_0
      35: getfield      #3                  // Field maxInclusive:Z
      38: ifeq          52
      41: iload_2
      42: aload_0
      43: getfield      #6                  // Field max:I
      46: if_icmpgt     64
      49: goto          60
      52: iload_2
      53: aload_0
      54: getfield      #6                  // Field max:I
      57: if_icmpge     64
      60: iconst_1
      61: goto          65
      64: iconst_0
      65: ireturn
}
