Compiled from "ElementAssign.java"
public class org.apache.jena.sparql.syntax.ElementAssign extends org.apache.jena.sparql.syntax.Element {
  private org.apache.jena.sparql.core.Var var;

  private org.apache.jena.sparql.expr.Expr expr;

  public org.apache.jena.sparql.syntax.ElementAssign(org.apache.jena.sparql.core.Var, org.apache.jena.sparql.expr.Expr);
    Code:
       0: aload_0
       1: invokespecial #1                  // Method org/apache/jena/sparql/syntax/Element."<init>":()V
       4: aload_0
       5: aload_1
       6: putfield      #2                  // Field var:Lorg/apache/jena/sparql/core/Var;
       9: aload_0
      10: aload_2
      11: putfield      #3                  // Field expr:Lorg/apache/jena/sparql/expr/Expr;
      14: return

  public org.apache.jena.sparql.core.Var getVar();
    Code:
       0: aload_0
       1: getfield      #2                  // Field var:Lorg/apache/jena/sparql/core/Var;
       4: areturn

  public org.apache.jena.sparql.expr.Expr getExpr();
    Code:
       0: aload_0
       1: getfield      #3                  // Field expr:Lorg/apache/jena/sparql/expr/Expr;
       4: areturn

  public boolean equalTo(org.apache.jena.sparql.syntax.Element, org.apache.jena.sparql.util.NodeIsomorphismMap);
    Code:
       0: aload_1
       1: instanceof    #4                  // class org/apache/jena/sparql/syntax/ElementAssign
       4: ifne          9
       7: iconst_0
       8: ireturn
       9: aload_1
      10: checkcast     #4                  // class org/apache/jena/sparql/syntax/ElementAssign
      13: astore_3
      14: aload_0
      15: invokevirtual #5                  // Method getVar:()Lorg/apache/jena/sparql/core/Var;
      18: aload_3
      19: invokevirtual #5                  // Method getVar:()Lorg/apache/jena/sparql/core/Var;
      22: invokevirtual #6                  // Method org/apache/jena/sparql/core/Var.equals:(Ljava/lang/Object;)Z
      25: ifne          30
      28: iconst_0
      29: ireturn
      30: aload_0
      31: invokevirtual #7                  // Method getExpr:()Lorg/apache/jena/sparql/expr/Expr;
      34: aload_3
      35: invokevirtual #7                  // Method getExpr:()Lorg/apache/jena/sparql/expr/Expr;
      38: invokeinterface #8,  2            // InterfaceMethod org/apache/jena/sparql/expr/Expr.equals:(Ljava/lang/Object;)Z
      43: ifne          48
      46: iconst_0
      47: ireturn
      48: iconst_1
      49: ireturn

  public int hashCode();
    Code:
       0: aload_0
       1: getfield      #2                  // Field var:Lorg/apache/jena/sparql/core/Var;
       4: invokevirtual #9                  // Method org/apache/jena/sparql/core/Var.hashCode:()I
       7: aload_0
       8: getfield      #3                  // Field expr:Lorg/apache/jena/sparql/expr/Expr;
      11: invokeinterface #10,  1           // InterfaceMethod org/apache/jena/sparql/expr/Expr.hashCode:()I
      16: ixor
      17: ireturn

  public void visit(org.apache.jena.sparql.syntax.ElementVisitor);
    Code:
       0: aload_1
       1: aload_0
       2: invokeinterface #11,  2           // InterfaceMethod org/apache/jena/sparql/syntax/ElementVisitor.visit:(Lorg/apache/jena/sparql/syntax/ElementAssign;)V
       7: return
}
