Compiled from "PatternVars.java"
public class org.apache.jena.sparql.syntax.PatternVars$WalkerSkipMinus extends org.apache.jena.sparql.syntax.ElementWalker$EltWalker {
  protected org.apache.jena.sparql.syntax.PatternVars$WalkerSkipMinus(org.apache.jena.sparql.syntax.ElementVisitor);
    Code:
       0: aload_0
       1: aload_1
       2: aconst_null
       3: aconst_null
       4: invokespecial #1                  // Method org/apache/jena/sparql/syntax/ElementWalker$EltWalker."<init>":(Lorg/apache/jena/sparql/syntax/ElementVisitor;Lorg/apache/jena/sparql/syntax/ElementVisitor;Lorg/apache/jena/sparql/syntax/ElementVisitor;)V
       7: return

  public void visit(org.apache.jena.sparql.syntax.ElementMinus);
    Code:
       0: aload_0
       1: getfield      #2                  // Field proc:Lorg/apache/jena/sparql/syntax/ElementVisitor;
       4: aload_1
       5: invokeinterface #3,  2            // InterfaceMethod org/apache/jena/sparql/syntax/ElementVisitor.visit:(Lorg/apache/jena/sparql/syntax/ElementMinus;)V
      10: return

  public void visit(org.apache.jena.sparql.syntax.ElementPathBlock);
    Code:
       0: aload_0
       1: aload_1
       2: invokespecial #4                  // Method org/apache/jena/sparql/syntax/ElementWalker$EltWalker.visit:(Lorg/apache/jena/sparql/syntax/ElementPathBlock;)V
       5: return

  public void visit(org.apache.jena.sparql.syntax.ElementSubQuery);
    Code:
       0: aload_0
       1: aload_1
       2: invokespecial #5                  // Method org/apache/jena/sparql/syntax/ElementWalker$EltWalker.visit:(Lorg/apache/jena/sparql/syntax/ElementSubQuery;)V
       5: return

  public void visit(org.apache.jena.sparql.syntax.ElementNotExists);
    Code:
       0: aload_0
       1: aload_1
       2: invokespecial #6                  // Method org/apache/jena/sparql/syntax/ElementWalker$EltWalker.visit:(Lorg/apache/jena/sparql/syntax/ElementNotExists;)V
       5: return

  public void visit(org.apache.jena.sparql.syntax.ElementExists);
    Code:
       0: aload_0
       1: aload_1
       2: invokespecial #7                  // Method org/apache/jena/sparql/syntax/ElementWalker$EltWalker.visit:(Lorg/apache/jena/sparql/syntax/ElementExists;)V
       5: return

  public void visit(org.apache.jena.sparql.syntax.ElementService);
    Code:
       0: aload_0
       1: aload_1
       2: invokespecial #8                  // Method org/apache/jena/sparql/syntax/ElementWalker$EltWalker.visit:(Lorg/apache/jena/sparql/syntax/ElementService;)V
       5: return

  public void visit(org.apache.jena.sparql.syntax.ElementNamedGraph);
    Code:
       0: aload_0
       1: aload_1
       2: invokespecial #9                  // Method org/apache/jena/sparql/syntax/ElementWalker$EltWalker.visit:(Lorg/apache/jena/sparql/syntax/ElementNamedGraph;)V
       5: return

  public void visit(org.apache.jena.sparql.syntax.ElementDataset);
    Code:
       0: aload_0
       1: aload_1
       2: invokespecial #10                 // Method org/apache/jena/sparql/syntax/ElementWalker$EltWalker.visit:(Lorg/apache/jena/sparql/syntax/ElementDataset;)V
       5: return

  public void visit(org.apache.jena.sparql.syntax.ElementOptional);
    Code:
       0: aload_0
       1: aload_1
       2: invokespecial #11                 // Method org/apache/jena/sparql/syntax/ElementWalker$EltWalker.visit:(Lorg/apache/jena/sparql/syntax/ElementOptional;)V
       5: return

  public void visit(org.apache.jena.sparql.syntax.ElementGroup);
    Code:
       0: aload_0
       1: aload_1
       2: invokespecial #12                 // Method org/apache/jena/sparql/syntax/ElementWalker$EltWalker.visit:(Lorg/apache/jena/sparql/syntax/ElementGroup;)V
       5: return

  public void visit(org.apache.jena.sparql.syntax.ElementUnion);
    Code:
       0: aload_0
       1: aload_1
       2: invokespecial #13                 // Method org/apache/jena/sparql/syntax/ElementWalker$EltWalker.visit:(Lorg/apache/jena/sparql/syntax/ElementUnion;)V
       5: return

  public void visit(org.apache.jena.sparql.syntax.ElementData);
    Code:
       0: aload_0
       1: aload_1
       2: invokespecial #14                 // Method org/apache/jena/sparql/syntax/ElementWalker$EltWalker.visit:(Lorg/apache/jena/sparql/syntax/ElementData;)V
       5: return

  public void visit(org.apache.jena.sparql.syntax.ElementBind);
    Code:
       0: aload_0
       1: aload_1
       2: invokespecial #15                 // Method org/apache/jena/sparql/syntax/ElementWalker$EltWalker.visit:(Lorg/apache/jena/sparql/syntax/ElementBind;)V
       5: return

  public void visit(org.apache.jena.sparql.syntax.ElementAssign);
    Code:
       0: aload_0
       1: aload_1
       2: invokespecial #16                 // Method org/apache/jena/sparql/syntax/ElementWalker$EltWalker.visit:(Lorg/apache/jena/sparql/syntax/ElementAssign;)V
       5: return

  public void visit(org.apache.jena.sparql.syntax.ElementFilter);
    Code:
       0: aload_0
       1: aload_1
       2: invokespecial #17                 // Method org/apache/jena/sparql/syntax/ElementWalker$EltWalker.visit:(Lorg/apache/jena/sparql/syntax/ElementFilter;)V
       5: return

  public void visit(org.apache.jena.sparql.syntax.ElementTriplesBlock);
    Code:
       0: aload_0
       1: aload_1
       2: invokespecial #18                 // Method org/apache/jena/sparql/syntax/ElementWalker$EltWalker.visit:(Lorg/apache/jena/sparql/syntax/ElementTriplesBlock;)V
       5: return
}
