Compiled from "BeanPropertyDefinitions.java"
final class springfox.documentation.schema.property.BeanPropertyDefinitions$2 implements com.google.common.base.Function<com.fasterxml.jackson.databind.PropertyNamingStrategy, java.lang.String> {
  final com.fasterxml.jackson.databind.introspect.BeanPropertyDefinition val$beanProperty;

  final com.fasterxml.jackson.databind.cfg.MapperConfig val$config;

  springfox.documentation.schema.property.BeanPropertyDefinitions$2(com.fasterxml.jackson.databind.introspect.BeanPropertyDefinition, com.fasterxml.jackson.databind.cfg.MapperConfig);
    Code:
       0: aload_0
       1: aload_1
       2: putfield      #1                  // Field val$beanProperty:Lcom/fasterxml/jackson/databind/introspect/BeanPropertyDefinition;
       5: aload_0
       6: aload_2
       7: putfield      #2                  // Field val$config:Lcom/fasterxml/jackson/databind/cfg/MapperConfig;
      10: aload_0
      11: invokespecial #3                  // Method java/lang/Object."<init>":()V
      14: return

  public java.lang.String apply(com.fasterxml.jackson.databind.PropertyNamingStrategy);
    Code:
       0: aload_1
       1: aload_0
       2: getfield      #1                  // Field val$beanProperty:Lcom/fasterxml/jackson/databind/introspect/BeanPropertyDefinition;
       5: aload_0
       6: getfield      #2                  // Field val$config:Lcom/fasterxml/jackson/databind/cfg/MapperConfig;
       9: invokestatic  #4                  // Method springfox/documentation/schema/property/BeanPropertyDefinitions.access$000:(Lcom/fasterxml/jackson/databind/PropertyNamingStrategy;Lcom/fasterxml/jackson/databind/introspect/BeanPropertyDefinition;Lcom/fasterxml/jackson/databind/cfg/MapperConfig;)Ljava/lang/String;
      12: areturn

  public java.lang.Object apply(java.lang.Object);
    Code:
       0: aload_0
       1: aload_1
       2: checkcast     #5                  // class com/fasterxml/jackson/databind/PropertyNamingStrategy
       5: invokevirtual #6                  // Method apply:(Lcom/fasterxml/jackson/databind/PropertyNamingStrategy;)Ljava/lang/String;
       8: areturn
}
