Compiled from "BeanDeserializerModifier.java"
public abstract class org.apache.htrace.shaded.fasterxml.jackson.databind.deser.BeanDeserializerModifier {
  public org.apache.htrace.shaded.fasterxml.jackson.databind.deser.BeanDeserializerModifier();
    Code:
       0: aload_0
       1: invokespecial #9                  // Method java/lang/Object."<init>":()V
       4: return

  public java.util.List<org.apache.htrace.shaded.fasterxml.jackson.databind.introspect.BeanPropertyDefinition> updateProperties(org.apache.htrace.shaded.fasterxml.jackson.databind.DeserializationConfig, org.apache.htrace.shaded.fasterxml.jackson.databind.BeanDescription, java.util.List<org.apache.htrace.shaded.fasterxml.jackson.databind.introspect.BeanPropertyDefinition>);
    Code:
       0: aload_3
       1: areturn

  public org.apache.htrace.shaded.fasterxml.jackson.databind.deser.BeanDeserializerBuilder updateBuilder(org.apache.htrace.shaded.fasterxml.jackson.databind.DeserializationConfig, org.apache.htrace.shaded.fasterxml.jackson.databind.BeanDescription, org.apache.htrace.shaded.fasterxml.jackson.databind.deser.BeanDeserializerBuilder);
    Code:
       0: aload_3
       1: areturn

  public org.apache.htrace.shaded.fasterxml.jackson.databind.JsonDeserializer<?> modifyDeserializer(org.apache.htrace.shaded.fasterxml.jackson.databind.DeserializationConfig, org.apache.htrace.shaded.fasterxml.jackson.databind.BeanDescription, org.apache.htrace.shaded.fasterxml.jackson.databind.JsonDeserializer<?>);
    Code:
       0: aload_3
       1: areturn

  public org.apache.htrace.shaded.fasterxml.jackson.databind.JsonDeserializer<?> modifyArrayDeserializer(org.apache.htrace.shaded.fasterxml.jackson.databind.DeserializationConfig, org.apache.htrace.shaded.fasterxml.jackson.databind.type.ArrayType, org.apache.htrace.shaded.fasterxml.jackson.databind.BeanDescription, org.apache.htrace.shaded.fasterxml.jackson.databind.JsonDeserializer<?>);
    Code:
       0: aload         4
       2: areturn

  public org.apache.htrace.shaded.fasterxml.jackson.databind.JsonDeserializer<?> modifyCollectionDeserializer(org.apache.htrace.shaded.fasterxml.jackson.databind.DeserializationConfig, org.apache.htrace.shaded.fasterxml.jackson.databind.type.CollectionType, org.apache.htrace.shaded.fasterxml.jackson.databind.BeanDescription, org.apache.htrace.shaded.fasterxml.jackson.databind.JsonDeserializer<?>);
    Code:
       0: aload         4
       2: areturn

  public org.apache.htrace.shaded.fasterxml.jackson.databind.JsonDeserializer<?> modifyCollectionLikeDeserializer(org.apache.htrace.shaded.fasterxml.jackson.databind.DeserializationConfig, org.apache.htrace.shaded.fasterxml.jackson.databind.type.CollectionLikeType, org.apache.htrace.shaded.fasterxml.jackson.databind.BeanDescription, org.apache.htrace.shaded.fasterxml.jackson.databind.JsonDeserializer<?>);
    Code:
       0: aload         4
       2: areturn

  public org.apache.htrace.shaded.fasterxml.jackson.databind.JsonDeserializer<?> modifyMapDeserializer(org.apache.htrace.shaded.fasterxml.jackson.databind.DeserializationConfig, org.apache.htrace.shaded.fasterxml.jackson.databind.type.MapType, org.apache.htrace.shaded.fasterxml.jackson.databind.BeanDescription, org.apache.htrace.shaded.fasterxml.jackson.databind.JsonDeserializer<?>);
    Code:
       0: aload         4
       2: areturn

  public org.apache.htrace.shaded.fasterxml.jackson.databind.JsonDeserializer<?> modifyMapLikeDeserializer(org.apache.htrace.shaded.fasterxml.jackson.databind.DeserializationConfig, org.apache.htrace.shaded.fasterxml.jackson.databind.type.MapLikeType, org.apache.htrace.shaded.fasterxml.jackson.databind.BeanDescription, org.apache.htrace.shaded.fasterxml.jackson.databind.JsonDeserializer<?>);
    Code:
       0: aload         4
       2: areturn

  public org.apache.htrace.shaded.fasterxml.jackson.databind.JsonDeserializer<?> modifyEnumDeserializer(org.apache.htrace.shaded.fasterxml.jackson.databind.DeserializationConfig, org.apache.htrace.shaded.fasterxml.jackson.databind.JavaType, org.apache.htrace.shaded.fasterxml.jackson.databind.BeanDescription, org.apache.htrace.shaded.fasterxml.jackson.databind.JsonDeserializer<?>);
    Code:
       0: aload         4
       2: areturn

  public org.apache.htrace.shaded.fasterxml.jackson.databind.KeyDeserializer modifyKeyDeserializer(org.apache.htrace.shaded.fasterxml.jackson.databind.DeserializationConfig, org.apache.htrace.shaded.fasterxml.jackson.databind.JavaType, org.apache.htrace.shaded.fasterxml.jackson.databind.KeyDeserializer);
    Code:
       0: aload_3
       1: areturn
}
