Compiled from "ComboBox.java"
class javafx.scene.control.ComboBox$3 implements javafx.beans.value.ChangeListener<T> {
  final javafx.scene.control.ComboBox this$0;

  javafx.scene.control.ComboBox$3(javafx.scene.control.ComboBox);
    Code:
       0: aload_0
       1: aload_1
       2: putfield      #1                  // Field this$0:Ljavafx/scene/control/ComboBox;
       5: aload_0
       6: invokespecial #2                  // Method java/lang/Object."<init>":()V
       9: return

  public void changed(javafx.beans.value.ObservableValue<? extends T>, T, T);
    Code:
       0: aload_0
       1: getfield      #1                  // Field this$0:Ljavafx/scene/control/ComboBox;
       4: invokestatic  #3                  // Method javafx/scene/control/ComboBox.access$100:(Ljavafx/scene/control/ComboBox;)Z
       7: ifeq          17
      10: aload_3
      11: ifnonnull     17
      14: goto          25
      17: aload_0
      18: getfield      #1                  // Field this$0:Ljavafx/scene/control/ComboBox;
      21: aload_3
      22: invokestatic  #4                  // Method javafx/scene/control/ComboBox.access$200:(Ljavafx/scene/control/ComboBox;Ljava/lang/Object;)V
      25: aload_0
      26: getfield      #1                  // Field this$0:Ljavafx/scene/control/ComboBox;
      29: iconst_0
      30: invokestatic  #5                  // Method javafx/scene/control/ComboBox.access$102:(Ljavafx/scene/control/ComboBox;Z)Z
      33: pop
      34: return
}
