Compiled from "Pagination.java"
public class javafx.scene.control.Pagination extends javafx.scene.control.Control {
  private static final int DEFAULT_MAX_PAGE_INDICATOR_COUNT;

  public static final java.lang.String STYLE_CLASS_BULLET;

  public static final int INDETERMINATE;

  private int oldMaxPageIndicatorCount;

  private javafx.beans.property.IntegerProperty maxPageIndicatorCount;

  private int oldPageCount;

  private javafx.beans.property.IntegerProperty pageCount;

  private final javafx.beans.property.IntegerProperty currentPageIndex;

  private javafx.beans.property.ObjectProperty<javafx.util.Callback<java.lang.Integer, javafx.scene.Node>> pageFactory;

  private static final java.lang.String DEFAULT_STYLE_CLASS;

  public javafx.scene.control.Pagination(int, int);
    Code:
       0: aload_0
       1: invokespecial #7                  // Method javafx/scene/control/Control."<init>":()V
       4: aload_0
       5: bipush        10
       7: putfield      #5                  // Field oldMaxPageIndicatorCount:I
      10: aload_0
      11: ldc           #9                  // int 2147483647
      13: putfield      #3                  // Field oldPageCount:I
      16: aload_0
      17: new           #10                 // class javafx/scene/control/Pagination$2
      20: dup
      21: aload_0
      22: aload_0
      23: ldc           #11                 // String pageCount
      25: ldc           #9                  // int 2147483647
      27: invokespecial #12                 // Method javafx/scene/control/Pagination$2."<init>":(Ljavafx/scene/control/Pagination;Ljava/lang/Object;Ljava/lang/String;I)V
      30: putfield      #4                  // Field pageCount:Ljavafx/beans/property/IntegerProperty;
      33: aload_0
      34: new           #13                 // class javafx/scene/control/Pagination$3
      37: dup
      38: aload_0
      39: aload_0
      40: ldc           #14                 // String currentPageIndex
      42: iconst_0
      43: invokespecial #15                 // Method javafx/scene/control/Pagination$3."<init>":(Ljavafx/scene/control/Pagination;Ljava/lang/Object;Ljava/lang/String;I)V
      46: putfield      #2                  // Field currentPageIndex:Ljavafx/beans/property/IntegerProperty;
      49: aload_0
      50: new           #16                 // class javafx/beans/property/SimpleObjectProperty
      53: dup
      54: aload_0
      55: ldc           #17                 // String pageFactory
      57: invokespecial #18                 // Method javafx/beans/property/SimpleObjectProperty."<init>":(Ljava/lang/Object;Ljava/lang/String;)V
      60: putfield      #19                 // Field pageFactory:Ljavafx/beans/property/ObjectProperty;
      63: aload_0
      64: invokevirtual #20                 // Method getStyleClass:()Ljavafx/collections/ObservableList;
      67: iconst_1
      68: anewarray     #21                 // class java/lang/String
      71: dup
      72: iconst_0
      73: ldc           #22                 // String pagination
      75: aastore
      76: invokeinterface #23,  2           // InterfaceMethod javafx/collections/ObservableList.setAll:([Ljava/lang/Object;)Z
      81: pop
      82: aload_0
      83: getstatic     #24                 // Field javafx/scene/AccessibleRole.PAGINATION:Ljavafx/scene/AccessibleRole;
      86: invokevirtual #25                 // Method setAccessibleRole:(Ljavafx/scene/AccessibleRole;)V
      89: aload_0
      90: iload_1
      91: invokevirtual #26                 // Method setPageCount:(I)V
      94: aload_0
      95: iload_2
      96: invokevirtual #27                 // Method setCurrentPageIndex:(I)V
      99: return

  public javafx.scene.control.Pagination(int);
    Code:
       0: aload_0
       1: iload_1
       2: iconst_0
       3: invokespecial #28                 // Method "<init>":(II)V
       6: return

  public javafx.scene.control.Pagination();
    Code:
       0: aload_0
       1: ldc           #9                  // int 2147483647
       3: iconst_0
       4: invokespecial #28                 // Method "<init>":(II)V
       7: return

  public final void setMaxPageIndicatorCount(int);
    Code:
       0: aload_0
       1: invokevirtual #29                 // Method maxPageIndicatorCountProperty:()Ljavafx/beans/property/IntegerProperty;
       4: iload_1
       5: invokevirtual #30                 // Method javafx/beans/property/IntegerProperty.set:(I)V
       8: return

  public final int getMaxPageIndicatorCount();
    Code:
       0: aload_0
       1: getfield      #6                  // Field maxPageIndicatorCount:Ljavafx/beans/property/IntegerProperty;
       4: ifnonnull     12
       7: bipush        10
       9: goto          19
      12: aload_0
      13: getfield      #6                  // Field maxPageIndicatorCount:Ljavafx/beans/property/IntegerProperty;
      16: invokevirtual #31                 // Method javafx/beans/property/IntegerProperty.get:()I
      19: ireturn

  public final javafx.beans.property.IntegerProperty maxPageIndicatorCountProperty();
    Code:
       0: aload_0
       1: getfield      #6                  // Field maxPageIndicatorCount:Ljavafx/beans/property/IntegerProperty;
       4: ifnonnull     21
       7: aload_0
       8: new           #32                 // class javafx/scene/control/Pagination$1
      11: dup
      12: aload_0
      13: bipush        10
      15: invokespecial #33                 // Method javafx/scene/control/Pagination$1."<init>":(Ljavafx/scene/control/Pagination;I)V
      18: putfield      #6                  // Field maxPageIndicatorCount:Ljavafx/beans/property/IntegerProperty;
      21: aload_0
      22: getfield      #6                  // Field maxPageIndicatorCount:Ljavafx/beans/property/IntegerProperty;
      25: areturn

  public final void setPageCount(int);
    Code:
       0: aload_0
       1: getfield      #4                  // Field pageCount:Ljavafx/beans/property/IntegerProperty;
       4: iload_1
       5: invokevirtual #30                 // Method javafx/beans/property/IntegerProperty.set:(I)V
       8: return

  public final int getPageCount();
    Code:
       0: aload_0
       1: getfield      #4                  // Field pageCount:Ljavafx/beans/property/IntegerProperty;
       4: invokevirtual #31                 // Method javafx/beans/property/IntegerProperty.get:()I
       7: ireturn

  public final javafx.beans.property.IntegerProperty pageCountProperty();
    Code:
       0: aload_0
       1: getfield      #4                  // Field pageCount:Ljavafx/beans/property/IntegerProperty;
       4: areturn

  public final void setCurrentPageIndex(int);
    Code:
       0: aload_0
       1: getfield      #2                  // Field currentPageIndex:Ljavafx/beans/property/IntegerProperty;
       4: iload_1
       5: invokevirtual #30                 // Method javafx/beans/property/IntegerProperty.set:(I)V
       8: return

  public final int getCurrentPageIndex();
    Code:
       0: aload_0
       1: getfield      #2                  // Field currentPageIndex:Ljavafx/beans/property/IntegerProperty;
       4: invokevirtual #31                 // Method javafx/beans/property/IntegerProperty.get:()I
       7: ireturn

  public final javafx.beans.property.IntegerProperty currentPageIndexProperty();
    Code:
       0: aload_0
       1: getfield      #2                  // Field currentPageIndex:Ljavafx/beans/property/IntegerProperty;
       4: areturn

  public final void setPageFactory(javafx.util.Callback<java.lang.Integer, javafx.scene.Node>);
    Code:
       0: aload_0
       1: getfield      #19                 // Field pageFactory:Ljavafx/beans/property/ObjectProperty;
       4: aload_1
       5: invokevirtual #34                 // Method javafx/beans/property/ObjectProperty.set:(Ljava/lang/Object;)V
       8: return

  public final javafx.util.Callback<java.lang.Integer, javafx.scene.Node> getPageFactory();
    Code:
       0: aload_0
       1: getfield      #19                 // Field pageFactory:Ljavafx/beans/property/ObjectProperty;
       4: invokevirtual #35                 // Method javafx/beans/property/ObjectProperty.get:()Ljava/lang/Object;
       7: checkcast     #36                 // class javafx/util/Callback
      10: areturn

  public final javafx.beans.property.ObjectProperty<javafx.util.Callback<java.lang.Integer, javafx.scene.Node>> pageFactoryProperty();
    Code:
       0: aload_0
       1: getfield      #19                 // Field pageFactory:Ljavafx/beans/property/ObjectProperty;
       4: areturn

  protected javafx.scene.control.Skin<?> createDefaultSkin();
    Code:
       0: new           #37                 // class javafx/scene/control/skin/PaginationSkin
       3: dup
       4: aload_0
       5: invokespecial #38                 // Method javafx/scene/control/skin/PaginationSkin."<init>":(Ljavafx/scene/control/Pagination;)V
       8: areturn

  public static java.util.List<javafx.css.CssMetaData<? extends javafx.css.Styleable, ?>> getClassCssMetaData();
    Code:
       0: invokestatic  #39                 // Method javafx/scene/control/Pagination$StyleableProperties.access$600:()Ljava/util/List;
       3: areturn

  public java.util.List<javafx.css.CssMetaData<? extends javafx.css.Styleable, ?>> getControlCssMetaData();
    Code:
       0: invokestatic  #40                 // Method getClassCssMetaData:()Ljava/util/List;
       3: areturn

  static javafx.beans.property.IntegerProperty access$000(javafx.scene.control.Pagination);
    Code:
       0: aload_0
       1: getfield      #6                  // Field maxPageIndicatorCount:Ljavafx/beans/property/IntegerProperty;
       4: areturn

  static int access$100(javafx.scene.control.Pagination);
    Code:
       0: aload_0
       1: getfield      #5                  // Field oldMaxPageIndicatorCount:I
       4: ireturn

  static int access$102(javafx.scene.control.Pagination, int);
    Code:
       0: aload_0
       1: iload_1
       2: dup_x1
       3: putfield      #5                  // Field oldMaxPageIndicatorCount:I
       6: ireturn

  static javafx.beans.property.IntegerProperty access$300(javafx.scene.control.Pagination);
    Code:
       0: aload_0
       1: getfield      #4                  // Field pageCount:Ljavafx/beans/property/IntegerProperty;
       4: areturn

  static int access$400(javafx.scene.control.Pagination);
    Code:
       0: aload_0
       1: getfield      #3                  // Field oldPageCount:I
       4: ireturn

  static int access$402(javafx.scene.control.Pagination, int);
    Code:
       0: aload_0
       1: iload_1
       2: dup_x1
       3: putfield      #3                  // Field oldPageCount:I
       6: ireturn

  static javafx.beans.property.IntegerProperty access$500(javafx.scene.control.Pagination);
    Code:
       0: aload_0
       1: getfield      #2                  // Field currentPageIndex:Ljavafx/beans/property/IntegerProperty;
       4: areturn
}
