Compiled from "TabPane.java"
public class javafx.scene.control.TabPane extends javafx.scene.control.Control {
  private static final double DEFAULT_TAB_MIN_WIDTH;

  private static final double DEFAULT_TAB_MAX_WIDTH;

  private static final double DEFAULT_TAB_MIN_HEIGHT;

  private static final double DEFAULT_TAB_MAX_HEIGHT;

  public static final java.lang.String STYLE_CLASS_FLOATING;

  private javafx.collections.ObservableList<javafx.scene.control.Tab> tabs;

  private javafx.beans.property.ObjectProperty<javafx.scene.control.SingleSelectionModel<javafx.scene.control.Tab>> selectionModel;

  private javafx.beans.property.ObjectProperty<javafx.geometry.Side> side;

  private javafx.beans.property.ObjectProperty<javafx.scene.control.TabPane$TabClosingPolicy> tabClosingPolicy;

  private javafx.beans.property.BooleanProperty rotateGraphic;

  private javafx.beans.property.DoubleProperty tabMinWidth;

  private javafx.beans.property.DoubleProperty tabMaxWidth;

  private javafx.beans.property.DoubleProperty tabMinHeight;

  private javafx.beans.property.DoubleProperty tabMaxHeight;

  private static final javafx.css.PseudoClass TOP_PSEUDOCLASS_STATE;

  private static final javafx.css.PseudoClass BOTTOM_PSEUDOCLASS_STATE;

  private static final javafx.css.PseudoClass LEFT_PSEUDOCLASS_STATE;

  private static final javafx.css.PseudoClass RIGHT_PSEUDOCLASS_STATE;

  private javafx.beans.property.ObjectProperty<javafx.scene.control.TabPane$TabDragPolicy> tabDragPolicy;

  public javafx.scene.control.TabPane();
    Code:
       0: aload_0
       1: aconst_null
       2: checkcast     #10                 // class "[Ljavafx/scene/control/Tab;"
       5: invokespecial #11                 // Method "<init>":([Ljavafx/scene/control/Tab;)V
       8: return

  public javafx.scene.control.TabPane(javafx.scene.control.Tab...);
    Code:
       0: aload_0
       1: invokespecial #12                 // Method javafx/scene/control/Control."<init>":()V
       4: aload_0
       5: new           #13                 // class com/sun/javafx/scene/control/TabObservableList
       8: dup
       9: new           #14                 // class java/util/ArrayList
      12: dup
      13: invokespecial #15                 // Method java/util/ArrayList."<init>":()V
      16: invokespecial #16                 // Method com/sun/javafx/scene/control/TabObservableList."<init>":(Ljava/util/List;)V
      19: putfield      #17                 // Field tabs:Ljavafx/collections/ObservableList;
      22: aload_0
      23: new           #18                 // class javafx/beans/property/SimpleObjectProperty
      26: dup
      27: aload_0
      28: ldc           #19                 // String selectionModel
      30: invokespecial #20                 // Method javafx/beans/property/SimpleObjectProperty."<init>":(Ljava/lang/Object;Ljava/lang/String;)V
      33: putfield      #21                 // Field selectionModel:Ljavafx/beans/property/ObjectProperty;
      36: aload_0
      37: invokevirtual #22                 // Method getStyleClass:()Ljavafx/collections/ObservableList;
      40: iconst_1
      41: anewarray     #23                 // class java/lang/String
      44: dup
      45: iconst_0
      46: ldc           #24                 // String tab-pane
      48: aastore
      49: invokeinterface #25,  2           // InterfaceMethod javafx/collections/ObservableList.setAll:([Ljava/lang/Object;)Z
      54: pop
      55: aload_0
      56: getstatic     #26                 // Field javafx/scene/AccessibleRole.TAB_PANE:Ljavafx/scene/AccessibleRole;
      59: invokevirtual #27                 // Method setAccessibleRole:(Ljavafx/scene/AccessibleRole;)V
      62: aload_0
      63: new           #28                 // class javafx/scene/control/TabPane$TabPaneSelectionModel
      66: dup
      67: aload_0
      68: invokespecial #29                 // Method javafx/scene/control/TabPane$TabPaneSelectionModel."<init>":(Ljavafx/scene/control/TabPane;)V
      71: invokevirtual #30                 // Method setSelectionModel:(Ljavafx/scene/control/SingleSelectionModel;)V
      74: aload_0
      75: getfield      #17                 // Field tabs:Ljavafx/collections/ObservableList;
      78: aload_0
      79: invokedynamic #31,  0             // InvokeDynamic #0:onChanged:(Ljavafx/scene/control/TabPane;)Ljavafx/collections/ListChangeListener;
      84: invokeinterface #32,  2           // InterfaceMethod javafx/collections/ObservableList.addListener:(Ljavafx/collections/ListChangeListener;)V
      89: aload_1
      90: ifnull        104
      93: aload_0
      94: invokevirtual #33                 // Method getTabs:()Ljavafx/collections/ObservableList;
      97: aload_1
      98: invokeinterface #34,  2           // InterfaceMethod javafx/collections/ObservableList.addAll:([Ljava/lang/Object;)Z
     103: pop
     104: aload_0
     105: invokevirtual #35                 // Method getSide:()Ljavafx/geometry/Side;
     108: astore_2
     109: aload_0
     110: getstatic     #9                  // Field TOP_PSEUDOCLASS_STATE:Ljavafx/css/PseudoClass;
     113: aload_2
     114: getstatic     #36                 // Field javafx/geometry/Side.TOP:Ljavafx/geometry/Side;
     117: if_acmpne     124
     120: iconst_1
     121: goto          125
     124: iconst_0
     125: invokevirtual #37                 // Method pseudoClassStateChanged:(Ljavafx/css/PseudoClass;Z)V
     128: aload_0
     129: getstatic     #8                  // Field RIGHT_PSEUDOCLASS_STATE:Ljavafx/css/PseudoClass;
     132: aload_2
     133: getstatic     #38                 // Field javafx/geometry/Side.RIGHT:Ljavafx/geometry/Side;
     136: if_acmpne     143
     139: iconst_1
     140: goto          144
     143: iconst_0
     144: invokevirtual #37                 // Method pseudoClassStateChanged:(Ljavafx/css/PseudoClass;Z)V
     147: aload_0
     148: getstatic     #7                  // Field BOTTOM_PSEUDOCLASS_STATE:Ljavafx/css/PseudoClass;
     151: aload_2
     152: getstatic     #39                 // Field javafx/geometry/Side.BOTTOM:Ljavafx/geometry/Side;
     155: if_acmpne     162
     158: iconst_1
     159: goto          163
     162: iconst_0
     163: invokevirtual #37                 // Method pseudoClassStateChanged:(Ljavafx/css/PseudoClass;Z)V
     166: aload_0
     167: getstatic     #6                  // Field LEFT_PSEUDOCLASS_STATE:Ljavafx/css/PseudoClass;
     170: aload_2
     171: getstatic     #40                 // Field javafx/geometry/Side.LEFT:Ljavafx/geometry/Side;
     174: if_acmpne     181
     177: iconst_1
     178: goto          182
     181: iconst_0
     182: invokevirtual #37                 // Method pseudoClassStateChanged:(Ljavafx/css/PseudoClass;Z)V
     185: return

  public final javafx.collections.ObservableList<javafx.scene.control.Tab> getTabs();
    Code:
       0: aload_0
       1: getfield      #17                 // Field tabs:Ljavafx/collections/ObservableList;
       4: areturn

  public final void setSelectionModel(javafx.scene.control.SingleSelectionModel<javafx.scene.control.Tab>);
    Code:
       0: aload_0
       1: getfield      #21                 // Field selectionModel:Ljavafx/beans/property/ObjectProperty;
       4: aload_1
       5: invokevirtual #41                 // Method javafx/beans/property/ObjectProperty.set:(Ljava/lang/Object;)V
       8: return

  public final javafx.scene.control.SingleSelectionModel<javafx.scene.control.Tab> getSelectionModel();
    Code:
       0: aload_0
       1: getfield      #21                 // Field selectionModel:Ljavafx/beans/property/ObjectProperty;
       4: invokevirtual #42                 // Method javafx/beans/property/ObjectProperty.get:()Ljava/lang/Object;
       7: checkcast     #43                 // class javafx/scene/control/SingleSelectionModel
      10: areturn

  public final javafx.beans.property.ObjectProperty<javafx.scene.control.SingleSelectionModel<javafx.scene.control.Tab>> selectionModelProperty();
    Code:
       0: aload_0
       1: getfield      #21                 // Field selectionModel:Ljavafx/beans/property/ObjectProperty;
       4: areturn

  public final void setSide(javafx.geometry.Side);
    Code:
       0: aload_0
       1: invokevirtual #44                 // Method sideProperty:()Ljavafx/beans/property/ObjectProperty;
       4: aload_1
       5: invokevirtual #41                 // Method javafx/beans/property/ObjectProperty.set:(Ljava/lang/Object;)V
       8: return

  public final javafx.geometry.Side getSide();
    Code:
       0: aload_0
       1: getfield      #45                 // Field side:Ljavafx/beans/property/ObjectProperty;
       4: ifnonnull     13
       7: getstatic     #36                 // Field javafx/geometry/Side.TOP:Ljavafx/geometry/Side;
      10: goto          23
      13: aload_0
      14: getfield      #45                 // Field side:Ljavafx/beans/property/ObjectProperty;
      17: invokevirtual #42                 // Method javafx/beans/property/ObjectProperty.get:()Ljava/lang/Object;
      20: checkcast     #46                 // class javafx/geometry/Side
      23: areturn

  public final javafx.beans.property.ObjectProperty<javafx.geometry.Side> sideProperty();
    Code:
       0: aload_0
       1: getfield      #45                 // Field side:Ljavafx/beans/property/ObjectProperty;
       4: ifnonnull     22
       7: aload_0
       8: new           #47                 // class javafx/scene/control/TabPane$1
      11: dup
      12: aload_0
      13: getstatic     #36                 // Field javafx/geometry/Side.TOP:Ljavafx/geometry/Side;
      16: invokespecial #48                 // Method javafx/scene/control/TabPane$1."<init>":(Ljavafx/scene/control/TabPane;Ljavafx/geometry/Side;)V
      19: putfield      #45                 // Field side:Ljavafx/beans/property/ObjectProperty;
      22: aload_0
      23: getfield      #45                 // Field side:Ljavafx/beans/property/ObjectProperty;
      26: areturn

  public final void setTabClosingPolicy(javafx.scene.control.TabPane$TabClosingPolicy);
    Code:
       0: aload_0
       1: invokevirtual #49                 // Method tabClosingPolicyProperty:()Ljavafx/beans/property/ObjectProperty;
       4: aload_1
       5: invokevirtual #41                 // Method javafx/beans/property/ObjectProperty.set:(Ljava/lang/Object;)V
       8: return

  public final javafx.scene.control.TabPane$TabClosingPolicy getTabClosingPolicy();
    Code:
       0: aload_0
       1: getfield      #50                 // Field tabClosingPolicy:Ljavafx/beans/property/ObjectProperty;
       4: ifnonnull     13
       7: getstatic     #51                 // Field javafx/scene/control/TabPane$TabClosingPolicy.SELECTED_TAB:Ljavafx/scene/control/TabPane$TabClosingPolicy;
      10: goto          23
      13: aload_0
      14: getfield      #50                 // Field tabClosingPolicy:Ljavafx/beans/property/ObjectProperty;
      17: invokevirtual #42                 // Method javafx/beans/property/ObjectProperty.get:()Ljava/lang/Object;
      20: checkcast     #52                 // class javafx/scene/control/TabPane$TabClosingPolicy
      23: areturn

  public final javafx.beans.property.ObjectProperty<javafx.scene.control.TabPane$TabClosingPolicy> tabClosingPolicyProperty();
    Code:
       0: aload_0
       1: getfield      #50                 // Field tabClosingPolicy:Ljavafx/beans/property/ObjectProperty;
       4: ifnonnull     24
       7: aload_0
       8: new           #18                 // class javafx/beans/property/SimpleObjectProperty
      11: dup
      12: aload_0
      13: ldc           #53                 // String tabClosingPolicy
      15: getstatic     #51                 // Field javafx/scene/control/TabPane$TabClosingPolicy.SELECTED_TAB:Ljavafx/scene/control/TabPane$TabClosingPolicy;
      18: invokespecial #54                 // Method javafx/beans/property/SimpleObjectProperty."<init>":(Ljava/lang/Object;Ljava/lang/String;Ljava/lang/Object;)V
      21: putfield      #50                 // Field tabClosingPolicy:Ljavafx/beans/property/ObjectProperty;
      24: aload_0
      25: getfield      #50                 // Field tabClosingPolicy:Ljavafx/beans/property/ObjectProperty;
      28: areturn

  public final void setRotateGraphic(boolean);
    Code:
       0: aload_0
       1: invokevirtual #55                 // Method rotateGraphicProperty:()Ljavafx/beans/property/BooleanProperty;
       4: iload_1
       5: invokevirtual #56                 // Method javafx/beans/property/BooleanProperty.set:(Z)V
       8: return

  public final boolean isRotateGraphic();
    Code:
       0: aload_0
       1: getfield      #57                 // Field rotateGraphic:Ljavafx/beans/property/BooleanProperty;
       4: ifnonnull     11
       7: iconst_0
       8: goto          18
      11: aload_0
      12: getfield      #57                 // Field rotateGraphic:Ljavafx/beans/property/BooleanProperty;
      15: invokevirtual #58                 // Method javafx/beans/property/BooleanProperty.get:()Z
      18: ireturn

  public final javafx.beans.property.BooleanProperty rotateGraphicProperty();
    Code:
       0: aload_0
       1: getfield      #57                 // Field rotateGraphic:Ljavafx/beans/property/BooleanProperty;
       4: ifnonnull     22
       7: aload_0
       8: new           #59                 // class javafx/beans/property/SimpleBooleanProperty
      11: dup
      12: aload_0
      13: ldc           #60                 // String rotateGraphic
      15: iconst_0
      16: invokespecial #61                 // Method javafx/beans/property/SimpleBooleanProperty."<init>":(Ljava/lang/Object;Ljava/lang/String;Z)V
      19: putfield      #57                 // Field rotateGraphic:Ljavafx/beans/property/BooleanProperty;
      22: aload_0
      23: getfield      #57                 // Field rotateGraphic:Ljavafx/beans/property/BooleanProperty;
      26: areturn

  public final void setTabMinWidth(double);
    Code:
       0: aload_0
       1: invokevirtual #62                 // Method tabMinWidthProperty:()Ljavafx/beans/property/DoubleProperty;
       4: dload_1
       5: invokestatic  #63                 // Method java/lang/Double.valueOf:(D)Ljava/lang/Double;
       8: invokevirtual #64                 // Method javafx/beans/property/DoubleProperty.setValue:(Ljava/lang/Number;)V
      11: return

  public final double getTabMinWidth();
    Code:
       0: aload_0
       1: getfield      #5                  // Field tabMinWidth:Ljavafx/beans/property/DoubleProperty;
       4: ifnonnull     11
       7: dconst_0
       8: goto          21
      11: aload_0
      12: getfield      #5                  // Field tabMinWidth:Ljavafx/beans/property/DoubleProperty;
      15: invokevirtual #66                 // Method javafx/beans/property/DoubleProperty.getValue:()Ljava/lang/Double;
      18: invokevirtual #67                 // Method java/lang/Double.doubleValue:()D
      21: dreturn

  public final javafx.beans.property.DoubleProperty tabMinWidthProperty();
    Code:
       0: aload_0
       1: getfield      #5                  // Field tabMinWidth:Ljavafx/beans/property/DoubleProperty;
       4: ifnonnull     20
       7: aload_0
       8: new           #68                 // class javafx/scene/control/TabPane$2
      11: dup
      12: aload_0
      13: dconst_0
      14: invokespecial #69                 // Method javafx/scene/control/TabPane$2."<init>":(Ljavafx/scene/control/TabPane;D)V
      17: putfield      #5                  // Field tabMinWidth:Ljavafx/beans/property/DoubleProperty;
      20: aload_0
      21: getfield      #5                  // Field tabMinWidth:Ljavafx/beans/property/DoubleProperty;
      24: areturn

  public final void setTabMaxWidth(double);
    Code:
       0: aload_0
       1: invokevirtual #70                 // Method tabMaxWidthProperty:()Ljavafx/beans/property/DoubleProperty;
       4: dload_1
       5: invokestatic  #63                 // Method java/lang/Double.valueOf:(D)Ljava/lang/Double;
       8: invokevirtual #64                 // Method javafx/beans/property/DoubleProperty.setValue:(Ljava/lang/Number;)V
      11: return

  public final double getTabMaxWidth();
    Code:
       0: aload_0
       1: getfield      #4                  // Field tabMaxWidth:Ljavafx/beans/property/DoubleProperty;
       4: ifnonnull     13
       7: ldc2_w        #71                 // double 1.7976931348623157E308d
      10: goto          23
      13: aload_0
      14: getfield      #4                  // Field tabMaxWidth:Ljavafx/beans/property/DoubleProperty;
      17: invokevirtual #66                 // Method javafx/beans/property/DoubleProperty.getValue:()Ljava/lang/Double;
      20: invokevirtual #67                 // Method java/lang/Double.doubleValue:()D
      23: dreturn

  public final javafx.beans.property.DoubleProperty tabMaxWidthProperty();
    Code:
       0: aload_0
       1: getfield      #4                  // Field tabMaxWidth:Ljavafx/beans/property/DoubleProperty;
       4: ifnonnull     22
       7: aload_0
       8: new           #73                 // class javafx/scene/control/TabPane$3
      11: dup
      12: aload_0
      13: ldc2_w        #71                 // double 1.7976931348623157E308d
      16: invokespecial #74                 // Method javafx/scene/control/TabPane$3."<init>":(Ljavafx/scene/control/TabPane;D)V
      19: putfield      #4                  // Field tabMaxWidth:Ljavafx/beans/property/DoubleProperty;
      22: aload_0
      23: getfield      #4                  // Field tabMaxWidth:Ljavafx/beans/property/DoubleProperty;
      26: areturn

  public final void setTabMinHeight(double);
    Code:
       0: aload_0
       1: invokevirtual #75                 // Method tabMinHeightProperty:()Ljavafx/beans/property/DoubleProperty;
       4: dload_1
       5: invokestatic  #63                 // Method java/lang/Double.valueOf:(D)Ljava/lang/Double;
       8: invokevirtual #64                 // Method javafx/beans/property/DoubleProperty.setValue:(Ljava/lang/Number;)V
      11: return

  public final double getTabMinHeight();
    Code:
       0: aload_0
       1: getfield      #3                  // Field tabMinHeight:Ljavafx/beans/property/DoubleProperty;
       4: ifnonnull     11
       7: dconst_0
       8: goto          21
      11: aload_0
      12: getfield      #3                  // Field tabMinHeight:Ljavafx/beans/property/DoubleProperty;
      15: invokevirtual #66                 // Method javafx/beans/property/DoubleProperty.getValue:()Ljava/lang/Double;
      18: invokevirtual #67                 // Method java/lang/Double.doubleValue:()D
      21: dreturn

  public final javafx.beans.property.DoubleProperty tabMinHeightProperty();
    Code:
       0: aload_0
       1: getfield      #3                  // Field tabMinHeight:Ljavafx/beans/property/DoubleProperty;
       4: ifnonnull     20
       7: aload_0
       8: new           #76                 // class javafx/scene/control/TabPane$4
      11: dup
      12: aload_0
      13: dconst_0
      14: invokespecial #77                 // Method javafx/scene/control/TabPane$4."<init>":(Ljavafx/scene/control/TabPane;D)V
      17: putfield      #3                  // Field tabMinHeight:Ljavafx/beans/property/DoubleProperty;
      20: aload_0
      21: getfield      #3                  // Field tabMinHeight:Ljavafx/beans/property/DoubleProperty;
      24: areturn

  public final void setTabMaxHeight(double);
    Code:
       0: aload_0
       1: invokevirtual #78                 // Method tabMaxHeightProperty:()Ljavafx/beans/property/DoubleProperty;
       4: dload_1
       5: invokestatic  #63                 // Method java/lang/Double.valueOf:(D)Ljava/lang/Double;
       8: invokevirtual #64                 // Method javafx/beans/property/DoubleProperty.setValue:(Ljava/lang/Number;)V
      11: return

  public final double getTabMaxHeight();
    Code:
       0: aload_0
       1: getfield      #2                  // Field tabMaxHeight:Ljavafx/beans/property/DoubleProperty;
       4: ifnonnull     13
       7: ldc2_w        #71                 // double 1.7976931348623157E308d
      10: goto          23
      13: aload_0
      14: getfield      #2                  // Field tabMaxHeight:Ljavafx/beans/property/DoubleProperty;
      17: invokevirtual #66                 // Method javafx/beans/property/DoubleProperty.getValue:()Ljava/lang/Double;
      20: invokevirtual #67                 // Method java/lang/Double.doubleValue:()D
      23: dreturn

  public final javafx.beans.property.DoubleProperty tabMaxHeightProperty();
    Code:
       0: aload_0
       1: getfield      #2                  // Field tabMaxHeight:Ljavafx/beans/property/DoubleProperty;
       4: ifnonnull     22
       7: aload_0
       8: new           #79                 // class javafx/scene/control/TabPane$5
      11: dup
      12: aload_0
      13: ldc2_w        #71                 // double 1.7976931348623157E308d
      16: invokespecial #80                 // Method javafx/scene/control/TabPane$5."<init>":(Ljavafx/scene/control/TabPane;D)V
      19: putfield      #2                  // Field tabMaxHeight:Ljavafx/beans/property/DoubleProperty;
      22: aload_0
      23: getfield      #2                  // Field tabMaxHeight:Ljavafx/beans/property/DoubleProperty;
      26: areturn

  protected javafx.scene.control.Skin<?> createDefaultSkin();
    Code:
       0: new           #81                 // class javafx/scene/control/skin/TabPaneSkin
       3: dup
       4: aload_0
       5: invokespecial #82                 // Method javafx/scene/control/skin/TabPaneSkin."<init>":(Ljavafx/scene/control/TabPane;)V
       8: areturn

  public javafx.scene.Node lookup(java.lang.String);
    Code:
       0: aload_0
       1: aload_1
       2: invokespecial #83                 // Method javafx/scene/control/Control.lookup:(Ljava/lang/String;)Ljavafx/scene/Node;
       5: astore_2
       6: aload_2
       7: ifnonnull     57
      10: aload_0
      11: getfield      #17                 // Field tabs:Ljavafx/collections/ObservableList;
      14: invokeinterface #84,  1           // InterfaceMethod javafx/collections/ObservableList.iterator:()Ljava/util/Iterator;
      19: astore_3
      20: aload_3
      21: invokeinterface #85,  1           // InterfaceMethod java/util/Iterator.hasNext:()Z
      26: ifeq          57
      29: aload_3
      30: invokeinterface #86,  1           // InterfaceMethod java/util/Iterator.next:()Ljava/lang/Object;
      35: checkcast     #87                 // class javafx/scene/control/Tab
      38: astore        4
      40: aload         4
      42: aload_1
      43: invokevirtual #88                 // Method javafx/scene/control/Tab.lookup:(Ljava/lang/String;)Ljavafx/scene/Node;
      46: astore_2
      47: aload_2
      48: ifnull        54
      51: goto          57
      54: goto          20
      57: aload_2
      58: areturn

  public java.util.Set<javafx.scene.Node> lookupAll(java.lang.String);
    Code:
       0: aload_1
       1: ifnonnull     6
       4: aconst_null
       5: areturn
       6: new           #14                 // class java/util/ArrayList
       9: dup
      10: invokespecial #15                 // Method java/util/ArrayList."<init>":()V
      13: astore_2
      14: aload_2
      15: aload_0
      16: aload_1
      17: invokespecial #89                 // Method javafx/scene/control/Control.lookupAll:(Ljava/lang/String;)Ljava/util/Set;
      20: invokeinterface #90,  2           // InterfaceMethod java/util/List.addAll:(Ljava/util/Collection;)Z
      25: pop
      26: aload_0
      27: getfield      #17                 // Field tabs:Ljavafx/collections/ObservableList;
      30: invokeinterface #84,  1           // InterfaceMethod javafx/collections/ObservableList.iterator:()Ljava/util/Iterator;
      35: astore_3
      36: aload_3
      37: invokeinterface #85,  1           // InterfaceMethod java/util/Iterator.hasNext:()Z
      42: ifeq          72
      45: aload_3
      46: invokeinterface #86,  1           // InterfaceMethod java/util/Iterator.next:()Ljava/lang/Object;
      51: checkcast     #87                 // class javafx/scene/control/Tab
      54: astore        4
      56: aload_2
      57: aload         4
      59: aload_1
      60: invokevirtual #91                 // Method javafx/scene/control/Tab.lookupAll:(Ljava/lang/String;)Ljava/util/List;
      63: invokeinterface #90,  2           // InterfaceMethod java/util/List.addAll:(Ljava/util/Collection;)Z
      68: pop
      69: goto          36
      72: new           #92                 // class com/sun/javafx/collections/UnmodifiableListSet
      75: dup
      76: aload_2
      77: invokespecial #93                 // Method com/sun/javafx/collections/UnmodifiableListSet."<init>":(Ljava/util/List;)V
      80: areturn

  public static java.util.List<javafx.css.CssMetaData<? extends javafx.css.Styleable, ?>> getClassCssMetaData();
    Code:
       0: invokestatic  #94                 // Method javafx/scene/control/TabPane$StyleableProperties.access$1200:()Ljava/util/List;
       3: areturn

  public java.util.List<javafx.css.CssMetaData<? extends javafx.css.Styleable, ?>> getControlCssMetaData();
    Code:
       0: invokestatic  #95                 // Method getClassCssMetaData:()Ljava/util/List;
       3: areturn

  public final javafx.beans.property.ObjectProperty<javafx.scene.control.TabPane$TabDragPolicy> tabDragPolicyProperty();
    Code:
       0: aload_0
       1: getfield      #96                 // Field tabDragPolicy:Ljavafx/beans/property/ObjectProperty;
       4: ifnonnull     24
       7: aload_0
       8: new           #18                 // class javafx/beans/property/SimpleObjectProperty
      11: dup
      12: aload_0
      13: ldc           #97                 // String tabDragPolicy
      15: getstatic     #98                 // Field javafx/scene/control/TabPane$TabDragPolicy.FIXED:Ljavafx/scene/control/TabPane$TabDragPolicy;
      18: invokespecial #54                 // Method javafx/beans/property/SimpleObjectProperty."<init>":(Ljava/lang/Object;Ljava/lang/String;Ljava/lang/Object;)V
      21: putfield      #96                 // Field tabDragPolicy:Ljavafx/beans/property/ObjectProperty;
      24: aload_0
      25: getfield      #96                 // Field tabDragPolicy:Ljavafx/beans/property/ObjectProperty;
      28: areturn

  public final void setTabDragPolicy(javafx.scene.control.TabPane$TabDragPolicy);
    Code:
       0: aload_0
       1: invokevirtual #99                 // Method tabDragPolicyProperty:()Ljavafx/beans/property/ObjectProperty;
       4: aload_1
       5: invokevirtual #41                 // Method javafx/beans/property/ObjectProperty.set:(Ljava/lang/Object;)V
       8: return

  public final javafx.scene.control.TabPane$TabDragPolicy getTabDragPolicy();
    Code:
       0: aload_0
       1: invokevirtual #99                 // Method tabDragPolicyProperty:()Ljavafx/beans/property/ObjectProperty;
       4: invokevirtual #42                 // Method javafx/beans/property/ObjectProperty.get:()Ljava/lang/Object;
       7: checkcast     #100                // class javafx/scene/control/TabPane$TabDragPolicy
      10: areturn

  private void lambda$new$0(javafx.collections.ListChangeListener$Change);
    Code:
       0: aload_1
       1: invokevirtual #101                // Method javafx/collections/ListChangeListener$Change.next:()Z
       4: ifeq          105
       7: aload_1
       8: invokevirtual #102                // Method javafx/collections/ListChangeListener$Change.getRemoved:()Ljava/util/List;
      11: invokeinterface #103,  1          // InterfaceMethod java/util/List.iterator:()Ljava/util/Iterator;
      16: astore_2
      17: aload_2
      18: invokeinterface #85,  1           // InterfaceMethod java/util/Iterator.hasNext:()Z
      23: ifeq          61
      26: aload_2
      27: invokeinterface #86,  1           // InterfaceMethod java/util/Iterator.next:()Ljava/lang/Object;
      32: checkcast     #87                 // class javafx/scene/control/Tab
      35: astore_3
      36: aload_3
      37: ifnull        58
      40: aload_0
      41: invokevirtual #33                 // Method getTabs:()Ljavafx/collections/ObservableList;
      44: aload_3
      45: invokeinterface #104,  2          // InterfaceMethod javafx/collections/ObservableList.contains:(Ljava/lang/Object;)Z
      50: ifne          58
      53: aload_3
      54: aconst_null
      55: invokevirtual #105                // Method javafx/scene/control/Tab.setTabPane:(Ljavafx/scene/control/TabPane;)V
      58: goto          17
      61: aload_1
      62: invokevirtual #106                // Method javafx/collections/ListChangeListener$Change.getAddedSubList:()Ljava/util/List;
      65: invokeinterface #103,  1          // InterfaceMethod java/util/List.iterator:()Ljava/util/Iterator;
      70: astore_2
      71: aload_2
      72: invokeinterface #85,  1           // InterfaceMethod java/util/Iterator.hasNext:()Z
      77: ifeq          102
      80: aload_2
      81: invokeinterface #86,  1           // InterfaceMethod java/util/Iterator.next:()Ljava/lang/Object;
      86: checkcast     #87                 // class javafx/scene/control/Tab
      89: astore_3
      90: aload_3
      91: ifnull        99
      94: aload_3
      95: aload_0
      96: invokevirtual #105                // Method javafx/scene/control/Tab.setTabPane:(Ljavafx/scene/control/TabPane;)V
      99: goto          71
     102: goto          0
     105: return

  static javafx.css.PseudoClass access$000();
    Code:
       0: getstatic     #9                  // Field TOP_PSEUDOCLASS_STATE:Ljavafx/css/PseudoClass;
       3: areturn

  static javafx.css.PseudoClass access$100();
    Code:
       0: getstatic     #8                  // Field RIGHT_PSEUDOCLASS_STATE:Ljavafx/css/PseudoClass;
       3: areturn

  static javafx.css.PseudoClass access$200();
    Code:
       0: getstatic     #7                  // Field BOTTOM_PSEUDOCLASS_STATE:Ljavafx/css/PseudoClass;
       3: areturn

  static javafx.css.PseudoClass access$300();
    Code:
       0: getstatic     #6                  // Field LEFT_PSEUDOCLASS_STATE:Ljavafx/css/PseudoClass;
       3: areturn

  static javafx.beans.property.DoubleProperty access$800(javafx.scene.control.TabPane);
    Code:
       0: aload_0
       1: getfield      #5                  // Field tabMinWidth:Ljavafx/beans/property/DoubleProperty;
       4: areturn

  static javafx.beans.property.DoubleProperty access$900(javafx.scene.control.TabPane);
    Code:
       0: aload_0
       1: getfield      #4                  // Field tabMaxWidth:Ljavafx/beans/property/DoubleProperty;
       4: areturn

  static javafx.beans.property.DoubleProperty access$1000(javafx.scene.control.TabPane);
    Code:
       0: aload_0
       1: getfield      #3                  // Field tabMinHeight:Ljavafx/beans/property/DoubleProperty;
       4: areturn

  static javafx.beans.property.DoubleProperty access$1100(javafx.scene.control.TabPane);
    Code:
       0: aload_0
       1: getfield      #2                  // Field tabMaxHeight:Ljavafx/beans/property/DoubleProperty;
       4: areturn

  static {};
    Code:
       0: ldc           #107                // String top
       2: invokestatic  #108                // Method javafx/css/PseudoClass.getPseudoClass:(Ljava/lang/String;)Ljavafx/css/PseudoClass;
       5: putstatic     #9                  // Field TOP_PSEUDOCLASS_STATE:Ljavafx/css/PseudoClass;
       8: ldc           #109                // String bottom
      10: invokestatic  #108                // Method javafx/css/PseudoClass.getPseudoClass:(Ljava/lang/String;)Ljavafx/css/PseudoClass;
      13: putstatic     #7                  // Field BOTTOM_PSEUDOCLASS_STATE:Ljavafx/css/PseudoClass;
      16: ldc           #110                // String left
      18: invokestatic  #108                // Method javafx/css/PseudoClass.getPseudoClass:(Ljava/lang/String;)Ljavafx/css/PseudoClass;
      21: putstatic     #6                  // Field LEFT_PSEUDOCLASS_STATE:Ljavafx/css/PseudoClass;
      24: ldc           #111                // String right
      26: invokestatic  #108                // Method javafx/css/PseudoClass.getPseudoClass:(Ljava/lang/String;)Ljavafx/css/PseudoClass;
      29: putstatic     #8                  // Field RIGHT_PSEUDOCLASS_STATE:Ljavafx/css/PseudoClass;
      32: return
}
