Compiled from "Tooltip.java"
class javafx.scene.control.Tooltip$1 extends javafx.beans.property.SimpleStringProperty {
  final javafx.scene.control.Tooltip this$0;

  javafx.scene.control.Tooltip$1(javafx.scene.control.Tooltip, java.lang.Object, java.lang.String, java.lang.String);
    Code:
       0: aload_0
       1: aload_1
       2: putfield      #1                  // Field this$0:Ljavafx/scene/control/Tooltip;
       5: aload_0
       6: aload_2
       7: aload_3
       8: aload         4
      10: invokespecial #2                  // Method javafx/beans/property/SimpleStringProperty."<init>":(Ljava/lang/Object;Ljava/lang/String;Ljava/lang/String;)V
      13: return

  protected void invalidated();
    Code:
       0: aload_0
       1: invokespecial #3                  // Method javafx/beans/property/SimpleStringProperty.invalidated:()V
       4: aload_0
       5: invokevirtual #4                  // Method get:()Ljava/lang/String;
       8: astore_1
       9: aload_0
      10: getfield      #1                  // Field this$0:Ljavafx/scene/control/Tooltip;
      13: invokevirtual #5                  // Method javafx/scene/control/Tooltip.isShowing:()Z
      16: ifeq          63
      19: aload_1
      20: ifnull        63
      23: aload_1
      24: aload_0
      25: getfield      #1                  // Field this$0:Ljavafx/scene/control/Tooltip;
      28: invokevirtual #6                  // Method javafx/scene/control/Tooltip.getText:()Ljava/lang/String;
      31: invokevirtual #7                  // Method java/lang/String.equals:(Ljava/lang/Object;)Z
      34: ifne          63
      37: aload_0
      38: getfield      #1                  // Field this$0:Ljavafx/scene/control/Tooltip;
      41: invokestatic  #8                  // Method javafx/scene/control/Tooltip.access$200:()Ljavafx/scene/control/Tooltip$TooltipBehavior;
      44: invokestatic  #9                  // Method javafx/scene/control/Tooltip$TooltipBehavior.access$300:(Ljavafx/scene/control/Tooltip$TooltipBehavior;)D
      47: invokevirtual #10                 // Method javafx/scene/control/Tooltip.setAnchorX:(D)V
      50: aload_0
      51: getfield      #1                  // Field this$0:Ljavafx/scene/control/Tooltip;
      54: invokestatic  #8                  // Method javafx/scene/control/Tooltip.access$200:()Ljavafx/scene/control/Tooltip$TooltipBehavior;
      57: invokestatic  #11                 // Method javafx/scene/control/Tooltip$TooltipBehavior.access$400:(Ljavafx/scene/control/Tooltip$TooltipBehavior;)D
      60: invokevirtual #12                 // Method javafx/scene/control/Tooltip.setAnchorY:(D)V
      63: return
}
