Compiled from "TreeTableView.java"
public class javafx.scene.control.TreeTableView$EditEvent<S> extends javafx.event.Event {
  private static final long serialVersionUID;

  public static final javafx.event.EventType<?> ANY;

  private final javafx.scene.control.TreeTableView<S> source;

  private final S oldValue;

  private final S newValue;

  private final transient javafx.scene.control.TreeItem<S> treeItem;

  public javafx.scene.control.TreeTableView$EditEvent(javafx.scene.control.TreeTableView<S>, javafx.event.EventType<? extends javafx.scene.control.TreeTableView$EditEvent>, javafx.scene.control.TreeItem<S>, S, S);
    Code:
       0: aload_0
       1: aload_1
       2: getstatic     #1                  // Field javafx/event/Event.NULL_SOURCE_TARGET:Ljavafx/event/EventTarget;
       5: aload_2
       6: invokespecial #2                  // Method javafx/event/Event."<init>":(Ljava/lang/Object;Ljavafx/event/EventTarget;Ljavafx/event/EventType;)V
       9: aload_0
      10: aload_1
      11: putfield      #3                  // Field source:Ljavafx/scene/control/TreeTableView;
      14: aload_0
      15: aload         4
      17: putfield      #4                  // Field oldValue:Ljava/lang/Object;
      20: aload_0
      21: aload         5
      23: putfield      #5                  // Field newValue:Ljava/lang/Object;
      26: aload_0
      27: aload_3
      28: putfield      #6                  // Field treeItem:Ljavafx/scene/control/TreeItem;
      31: return

  public javafx.scene.control.TreeTableView<S> getSource();
    Code:
       0: aload_0
       1: getfield      #3                  // Field source:Ljavafx/scene/control/TreeTableView;
       4: areturn

  public javafx.scene.control.TreeItem<S> getTreeItem();
    Code:
       0: aload_0
       1: getfield      #6                  // Field treeItem:Ljavafx/scene/control/TreeItem;
       4: areturn

  public S getNewValue();
    Code:
       0: aload_0
       1: getfield      #5                  // Field newValue:Ljava/lang/Object;
       4: areturn

  public S getOldValue();
    Code:
       0: aload_0
       1: getfield      #4                  // Field oldValue:Ljava/lang/Object;
       4: areturn

  public java.lang.Object getSource();
    Code:
       0: aload_0
       1: invokevirtual #7                  // Method getSource:()Ljavafx/scene/control/TreeTableView;
       4: areturn

  static {};
    Code:
       0: invokestatic  #8                  // Method javafx/scene/control/TreeTableView.access$2400:()Ljavafx/event/EventType;
       3: putstatic     #9                  // Field ANY:Ljavafx/event/EventType;
       6: return
}
