Compiled from "BasicCollectionLoadQueryDetails.java"
public class org.hibernate.loader.plan.exec.internal.BasicCollectionLoadQueryDetails extends org.hibernate.loader.plan.exec.internal.AbstractCollectionLoadQueryDetails {
  org.hibernate.loader.plan.exec.internal.BasicCollectionLoadQueryDetails(org.hibernate.loader.plan.spi.LoadPlan, org.hibernate.loader.plan.exec.internal.AliasResolutionContextImpl, org.hibernate.loader.plan.spi.CollectionReturn, org.hibernate.loader.plan.exec.query.spi.QueryBuildingParameters, org.hibernate.engine.spi.SessionFactoryImplementor);
    Code:
       0: aload_0
       1: aload_1
       2: aload_2
       3: aload_3
       4: aload         4
       6: aload         5
       8: invokespecial #1                  // Method org/hibernate/loader/plan/exec/internal/AbstractCollectionLoadQueryDetails."<init>":(Lorg/hibernate/loader/plan/spi/LoadPlan;Lorg/hibernate/loader/plan/exec/internal/AliasResolutionContextImpl;Lorg/hibernate/loader/plan/spi/CollectionReturn;Lorg/hibernate/loader/plan/exec/query/spi/QueryBuildingParameters;Lorg/hibernate/engine/spi/SessionFactoryImplementor;)V
      11: aload_0
      12: invokevirtual #2                  // Method generate:()V
      15: return

  protected java.lang.String getRootTableAlias();
    Code:
       0: aload_0
       1: invokevirtual #3                  // Method getCollectionReferenceAliases:()Lorg/hibernate/loader/plan/exec/spi/CollectionReferenceAliases;
       4: invokeinterface #4,  1            // InterfaceMethod org/hibernate/loader/plan/exec/spi/CollectionReferenceAliases.getCollectionTableAlias:()Ljava/lang/String;
       9: areturn

  protected void applyRootReturnSelectFragments(org.hibernate.loader.plan.exec.query.internal.SelectStatementBuilder);
    Code:
       0: aload_1
       1: aload_0
       2: invokevirtual #5                  // Method getQueryableCollection:()Lorg/hibernate/persister/collection/QueryableCollection;
       5: aload_0
       6: invokevirtual #3                  // Method getCollectionReferenceAliases:()Lorg/hibernate/loader/plan/exec/spi/CollectionReferenceAliases;
       9: invokeinterface #4,  1            // InterfaceMethod org/hibernate/loader/plan/exec/spi/CollectionReferenceAliases.getCollectionTableAlias:()Ljava/lang/String;
      14: aload_0
      15: invokevirtual #3                  // Method getCollectionReferenceAliases:()Lorg/hibernate/loader/plan/exec/spi/CollectionReferenceAliases;
      18: invokeinterface #6,  1            // InterfaceMethod org/hibernate/loader/plan/exec/spi/CollectionReferenceAliases.getCollectionColumnAliases:()Lorg/hibernate/loader/CollectionAliases;
      23: invokeinterface #7,  1            // InterfaceMethod org/hibernate/loader/CollectionAliases.getSuffix:()Ljava/lang/String;
      28: invokeinterface #8,  3            // InterfaceMethod org/hibernate/persister/collection/QueryableCollection.selectFragment:(Ljava/lang/String;Ljava/lang/String;)Ljava/lang/String;
      33: invokevirtual #9                  // Method org/hibernate/loader/plan/exec/query/internal/SelectStatementBuilder.appendSelectClauseFragment:(Ljava/lang/String;)V
      36: aload_0
      37: invokevirtual #5                  // Method getQueryableCollection:()Lorg/hibernate/persister/collection/QueryableCollection;
      40: invokeinterface #10,  1           // InterfaceMethod org/hibernate/persister/collection/QueryableCollection.isManyToMany:()Z
      45: ifeq          99
      48: aload_0
      49: invokevirtual #5                  // Method getQueryableCollection:()Lorg/hibernate/persister/collection/QueryableCollection;
      52: invokeinterface #11,  1           // InterfaceMethod org/hibernate/persister/collection/QueryableCollection.getElementPersister:()Lorg/hibernate/persister/entity/EntityPersister;
      57: checkcast     #12                 // class org/hibernate/persister/entity/OuterJoinLoadable
      60: astore_2
      61: aload_1
      62: aload_2
      63: aload_0
      64: invokevirtual #3                  // Method getCollectionReferenceAliases:()Lorg/hibernate/loader/plan/exec/spi/CollectionReferenceAliases;
      67: invokeinterface #13,  1           // InterfaceMethod org/hibernate/loader/plan/exec/spi/CollectionReferenceAliases.getElementTableAlias:()Ljava/lang/String;
      72: aload_0
      73: invokevirtual #3                  // Method getCollectionReferenceAliases:()Lorg/hibernate/loader/plan/exec/spi/CollectionReferenceAliases;
      76: invokeinterface #14,  1           // InterfaceMethod org/hibernate/loader/plan/exec/spi/CollectionReferenceAliases.getEntityElementAliases:()Lorg/hibernate/loader/plan/exec/spi/EntityReferenceAliases;
      81: invokeinterface #15,  1           // InterfaceMethod org/hibernate/loader/plan/exec/spi/EntityReferenceAliases.getColumnAliases:()Lorg/hibernate/loader/EntityAliases;
      86: invokeinterface #16,  1           // InterfaceMethod org/hibernate/loader/EntityAliases.getSuffix:()Ljava/lang/String;
      91: invokeinterface #17,  3           // InterfaceMethod org/hibernate/persister/entity/OuterJoinLoadable.selectFragment:(Ljava/lang/String;Ljava/lang/String;)Ljava/lang/String;
      96: invokevirtual #9                  // Method org/hibernate/loader/plan/exec/query/internal/SelectStatementBuilder.appendSelectClauseFragment:(Ljava/lang/String;)V
      99: aload_0
     100: aload_1
     101: invokespecial #18                 // Method org/hibernate/loader/plan/exec/internal/AbstractCollectionLoadQueryDetails.applyRootReturnSelectFragments:(Lorg/hibernate/loader/plan/exec/query/internal/SelectStatementBuilder;)V
     104: return

  protected void applyRootReturnTableFragments(org.hibernate.loader.plan.exec.query.internal.SelectStatementBuilder);
    Code:
       0: aload_1
       1: aload_0
       2: invokevirtual #5                  // Method getQueryableCollection:()Lorg/hibernate/persister/collection/QueryableCollection;
       5: invokeinterface #19,  1           // InterfaceMethod org/hibernate/persister/collection/QueryableCollection.getTableName:()Ljava/lang/String;
      10: aload_0
      11: invokevirtual #3                  // Method getCollectionReferenceAliases:()Lorg/hibernate/loader/plan/exec/spi/CollectionReferenceAliases;
      14: invokeinterface #4,  1            // InterfaceMethod org/hibernate/loader/plan/exec/spi/CollectionReferenceAliases.getCollectionTableAlias:()Ljava/lang/String;
      19: invokevirtual #20                 // Method org/hibernate/loader/plan/exec/query/internal/SelectStatementBuilder.appendFromClauseFragment:(Ljava/lang/String;Ljava/lang/String;)V
      22: return

  protected void applyRootReturnOrderByFragments(org.hibernate.loader.plan.exec.query.internal.SelectStatementBuilder);
    Code:
       0: aload_0
       1: invokevirtual #5                  // Method getQueryableCollection:()Lorg/hibernate/persister/collection/QueryableCollection;
       4: aload_0
       5: invokevirtual #3                  // Method getCollectionReferenceAliases:()Lorg/hibernate/loader/plan/exec/spi/CollectionReferenceAliases;
       8: invokeinterface #13,  1           // InterfaceMethod org/hibernate/loader/plan/exec/spi/CollectionReferenceAliases.getElementTableAlias:()Ljava/lang/String;
      13: invokeinterface #21,  2           // InterfaceMethod org/hibernate/persister/collection/QueryableCollection.getManyToManyOrderByString:(Ljava/lang/String;)Ljava/lang/String;
      18: astore_2
      19: aload_2
      20: invokestatic  #22                 // Method org/hibernate/internal/util/StringHelper.isNotEmpty:(Ljava/lang/String;)Z
      23: ifeq          31
      26: aload_1
      27: aload_2
      28: invokevirtual #23                 // Method org/hibernate/loader/plan/exec/query/internal/SelectStatementBuilder.appendOrderByFragment:(Ljava/lang/String;)V
      31: aload_0
      32: aload_1
      33: invokespecial #24                 // Method org/hibernate/loader/plan/exec/internal/AbstractCollectionLoadQueryDetails.applyRootReturnOrderByFragments:(Lorg/hibernate/loader/plan/exec/query/internal/SelectStatementBuilder;)V
      36: return
}
