Compiled from "ArchiveValidationConsumer.java"
public interface org.wildfly.swarm.config.jca.ArchiveValidationConsumer<T extends org.wildfly.swarm.config.jca.ArchiveValidation<T>> {
  public abstract void accept(T);

  public default org.wildfly.swarm.config.jca.ArchiveValidationConsumer<T> andThen(org.wildfly.swarm.config.jca.ArchiveValidationConsumer<T>);
    Code:
       0: aload_0
       1: aload_1
       2: invokedynamic #1,  0              // InvokeDynamic #0:accept:(Lorg/wildfly/swarm/config/jca/ArchiveValidationConsumer;Lorg/wildfly/swarm/config/jca/ArchiveValidationConsumer;)Lorg/wildfly/swarm/config/jca/ArchiveValidationConsumer;
       7: areturn

  private void lambda$andThen$504(org.wildfly.swarm.config.jca.ArchiveValidationConsumer, org.wildfly.swarm.config.jca.ArchiveValidation);
    Code:
       0: aload_0
       1: aload_2
       2: invokeinterface #2,  2            // InterfaceMethod accept:(Lorg/wildfly/swarm/config/jca/ArchiveValidation;)V
       7: aload_1
       8: aload_2
       9: invokeinterface #2,  2            // InterfaceMethod accept:(Lorg/wildfly/swarm/config/jca/ArchiveValidation;)V
      14: return
}
