Compiled from "AsyncLoadBalancerAutoConfiguration.java"
class org.springframework.cloud.client.loadbalancer.AsyncLoadBalancerAutoConfiguration$AsyncRestTemplateCustomizerConfig$1 implements org.springframework.beans.factory.SmartInitializingSingleton {
  final java.util.List val$customizers;

  final org.springframework.cloud.client.loadbalancer.AsyncLoadBalancerAutoConfiguration$AsyncRestTemplateCustomizerConfig this$0;

  org.springframework.cloud.client.loadbalancer.AsyncLoadBalancerAutoConfiguration$AsyncRestTemplateCustomizerConfig$1(org.springframework.cloud.client.loadbalancer.AsyncLoadBalancerAutoConfiguration$AsyncRestTemplateCustomizerConfig, java.util.List);
    Code:
       0: aload_0
       1: aload_1
       2: putfield      #1                  // Field this$0:Lorg/springframework/cloud/client/loadbalancer/AsyncLoadBalancerAutoConfiguration$AsyncRestTemplateCustomizerConfig;
       5: aload_0
       6: aload_2
       7: putfield      #2                  // Field val$customizers:Ljava/util/List;
      10: aload_0
      11: invokespecial #3                  // Method java/lang/Object."<init>":()V
      14: return

  public void afterSingletonsInstantiated();
    Code:
       0: aload_0
       1: getfield      #1                  // Field this$0:Lorg/springframework/cloud/client/loadbalancer/AsyncLoadBalancerAutoConfiguration$AsyncRestTemplateCustomizerConfig;
       4: invokestatic  #4                  // Method org/springframework/cloud/client/loadbalancer/AsyncLoadBalancerAutoConfiguration$AsyncRestTemplateCustomizerConfig.access$000:(Lorg/springframework/cloud/client/loadbalancer/AsyncLoadBalancerAutoConfiguration$AsyncRestTemplateCustomizerConfig;)Ljava/util/List;
       7: invokeinterface #5,  1            // InterfaceMethod java/util/List.iterator:()Ljava/util/Iterator;
      12: astore_1
      13: aload_1
      14: invokeinterface #6,  1            // InterfaceMethod java/util/Iterator.hasNext:()Z
      19: ifeq          76
      22: aload_1
      23: invokeinterface #7,  1            // InterfaceMethod java/util/Iterator.next:()Ljava/lang/Object;
      28: checkcast     #8                  // class org/springframework/web/client/AsyncRestTemplate
      31: astore_2
      32: aload_0
      33: getfield      #2                  // Field val$customizers:Ljava/util/List;
      36: invokeinterface #5,  1            // InterfaceMethod java/util/List.iterator:()Ljava/util/Iterator;
      41: astore_3
      42: aload_3
      43: invokeinterface #6,  1            // InterfaceMethod java/util/Iterator.hasNext:()Z
      48: ifeq          73
      51: aload_3
      52: invokeinterface #7,  1            // InterfaceMethod java/util/Iterator.next:()Ljava/lang/Object;
      57: checkcast     #9                  // class org/springframework/cloud/client/loadbalancer/AsyncRestTemplateCustomizer
      60: astore        4
      62: aload         4
      64: aload_2
      65: invokeinterface #10,  2           // InterfaceMethod org/springframework/cloud/client/loadbalancer/AsyncRestTemplateCustomizer.customize:(Lorg/springframework/web/client/AsyncRestTemplate;)V
      70: goto          42
      73: goto          13
      76: return
}
