Compiled from "ServiceRequestWrapper.java"
public class org.springframework.cloud.client.loadbalancer.ServiceRequestWrapper extends org.springframework.http.client.support.HttpRequestWrapper {
  private final org.springframework.cloud.client.ServiceInstance instance;

  private final org.springframework.cloud.client.loadbalancer.LoadBalancerClient loadBalancer;

  public org.springframework.cloud.client.loadbalancer.ServiceRequestWrapper(org.springframework.http.HttpRequest, org.springframework.cloud.client.ServiceInstance, org.springframework.cloud.client.loadbalancer.LoadBalancerClient);
    Code:
       0: aload_0
       1: aload_1
       2: invokespecial #1                  // Method org/springframework/http/client/support/HttpRequestWrapper."<init>":(Lorg/springframework/http/HttpRequest;)V
       5: aload_0
       6: aload_2
       7: putfield      #2                  // Field instance:Lorg/springframework/cloud/client/ServiceInstance;
      10: aload_0
      11: aload_3
      12: putfield      #3                  // Field loadBalancer:Lorg/springframework/cloud/client/loadbalancer/LoadBalancerClient;
      15: return

  public java.net.URI getURI();
    Code:
       0: aload_0
       1: getfield      #3                  // Field loadBalancer:Lorg/springframework/cloud/client/loadbalancer/LoadBalancerClient;
       4: aload_0
       5: getfield      #2                  // Field instance:Lorg/springframework/cloud/client/ServiceInstance;
       8: aload_0
       9: invokevirtual #4                  // Method getRequest:()Lorg/springframework/http/HttpRequest;
      12: invokeinterface #5,  1            // InterfaceMethod org/springframework/http/HttpRequest.getURI:()Ljava/net/URI;
      17: invokeinterface #6,  3            // InterfaceMethod org/springframework/cloud/client/loadbalancer/LoadBalancerClient.reconstructURI:(Lorg/springframework/cloud/client/ServiceInstance;Ljava/net/URI;)Ljava/net/URI;
      22: astore_1
      23: aload_1
      24: areturn
}
