Compiled from "PlacementConstraintTransformations.java"
public class org.apache.hadoop.yarn.api.resource.PlacementConstraintTransformations$SpecializedConstraintTransformer extends org.apache.hadoop.yarn.api.resource.PlacementConstraintTransformations$AbstractTransformer {
  public org.apache.hadoop.yarn.api.resource.PlacementConstraintTransformations$SpecializedConstraintTransformer(org.apache.hadoop.yarn.api.resource.PlacementConstraint);
    Code:
       0: aload_0
       1: aload_1
       2: invokespecial #1                  // Method org/apache/hadoop/yarn/api/resource/PlacementConstraintTransformations$AbstractTransformer."<init>":(Lorg/apache/hadoop/yarn/api/resource/PlacementConstraint;)V
       5: return

  public org.apache.hadoop.yarn.api.resource.PlacementConstraint$AbstractConstraint visit(org.apache.hadoop.yarn.api.resource.PlacementConstraint$SingleConstraint);
    Code:
       0: aload_1
       1: astore_2
       2: aload_1
       3: invokevirtual #2                  // Method org/apache/hadoop/yarn/api/resource/PlacementConstraint$SingleConstraint.getMinCardinality:()I
       6: iconst_1
       7: if_icmpne     41
      10: aload_1
      11: invokevirtual #3                  // Method org/apache/hadoop/yarn/api/resource/PlacementConstraint$SingleConstraint.getMaxCardinality:()I
      14: ldc           #5                  // int 2147483647
      16: if_icmpne     41
      19: new           #6                  // class org/apache/hadoop/yarn/api/resource/PlacementConstraint$TargetConstraint
      22: dup
      23: getstatic     #7                  // Field org/apache/hadoop/yarn/api/resource/PlacementConstraint$TargetConstraint$TargetOperator.IN:Lorg/apache/hadoop/yarn/api/resource/PlacementConstraint$TargetConstraint$TargetOperator;
      26: aload_1
      27: invokevirtual #8                  // Method org/apache/hadoop/yarn/api/resource/PlacementConstraint$SingleConstraint.getScope:()Ljava/lang/String;
      30: aload_1
      31: invokevirtual #9                  // Method org/apache/hadoop/yarn/api/resource/PlacementConstraint$SingleConstraint.getTargetExpressions:()Ljava/util/Set;
      34: invokespecial #10                 // Method org/apache/hadoop/yarn/api/resource/PlacementConstraint$TargetConstraint."<init>":(Lorg/apache/hadoop/yarn/api/resource/PlacementConstraint$TargetConstraint$TargetOperator;Ljava/lang/String;Ljava/util/Set;)V
      37: astore_2
      38: goto          74
      41: aload_1
      42: invokevirtual #2                  // Method org/apache/hadoop/yarn/api/resource/PlacementConstraint$SingleConstraint.getMinCardinality:()I
      45: ifne          74
      48: aload_1
      49: invokevirtual #3                  // Method org/apache/hadoop/yarn/api/resource/PlacementConstraint$SingleConstraint.getMaxCardinality:()I
      52: ifne          74
      55: new           #6                  // class org/apache/hadoop/yarn/api/resource/PlacementConstraint$TargetConstraint
      58: dup
      59: getstatic     #11                 // Field org/apache/hadoop/yarn/api/resource/PlacementConstraint$TargetConstraint$TargetOperator.NOT_IN:Lorg/apache/hadoop/yarn/api/resource/PlacementConstraint$TargetConstraint$TargetOperator;
      62: aload_1
      63: invokevirtual #8                  // Method org/apache/hadoop/yarn/api/resource/PlacementConstraint$SingleConstraint.getScope:()Ljava/lang/String;
      66: aload_1
      67: invokevirtual #9                  // Method org/apache/hadoop/yarn/api/resource/PlacementConstraint$SingleConstraint.getTargetExpressions:()Ljava/util/Set;
      70: invokespecial #10                 // Method org/apache/hadoop/yarn/api/resource/PlacementConstraint$TargetConstraint."<init>":(Lorg/apache/hadoop/yarn/api/resource/PlacementConstraint$TargetConstraint$TargetOperator;Ljava/lang/String;Ljava/util/Set;)V
      73: astore_2
      74: aload_2
      75: areturn

  public java.lang.Object visit(org.apache.hadoop.yarn.api.resource.PlacementConstraint$SingleConstraint);
    Code:
       0: aload_0
       1: aload_1
       2: invokevirtual #12                 // Method visit:(Lorg/apache/hadoop/yarn/api/resource/PlacementConstraint$SingleConstraint;)Lorg/apache/hadoop/yarn/api/resource/PlacementConstraint$AbstractConstraint;
       5: areturn
}
