Compiled from "SessionStore.java"
public interface io.vertx.ext.web.sstore.SessionStore {
  public static final int DEFAULT_SESSIONID_LENGTH;

  public static io.vertx.ext.web.sstore.SessionStore create(io.vertx.core.Vertx);
    Code:
       0: aload_0
       1: new           #1                  // class io/vertx/core/json/JsonObject
       4: dup
       5: invokespecial #2                  // Method io/vertx/core/json/JsonObject."<init>":()V
       8: invokestatic  #3                  // InterfaceMethod create:(Lio/vertx/core/Vertx;Lio/vertx/core/json/JsonObject;)Lio/vertx/ext/web/sstore/SessionStore;
      11: areturn

  public static io.vertx.ext.web.sstore.SessionStore create(io.vertx.core.Vertx, io.vertx.core.json.JsonObject);
    Code:
       0: ldc           #4                  // class io/vertx/ext/web/sstore/SessionStore
       2: invokestatic  #5                  // Method io/vertx/core/ServiceHelper.loadFactoryOrNull:(Ljava/lang/Class;)Ljava/lang/Object;
       5: checkcast     #4                  // class io/vertx/ext/web/sstore/SessionStore
       8: astore_2
       9: aload_2
      10: ifnull        22
      13: aload_2
      14: aload_0
      15: aload_1
      16: invokeinterface #6,  3            // InterfaceMethod init:(Lio/vertx/core/Vertx;Lio/vertx/core/json/JsonObject;)Lio/vertx/ext/web/sstore/SessionStore;
      21: areturn
      22: goto          26
      25: astore_3
      26: aload_0
      27: invokeinterface #8,  1            // InterfaceMethod io/vertx/core/Vertx.isClustered:()Z
      32: ifeq          46
      35: new           #9                  // class io/vertx/ext/web/sstore/impl/ClusteredSessionStoreImpl
      38: dup
      39: invokespecial #10                 // Method io/vertx/ext/web/sstore/impl/ClusteredSessionStoreImpl."<init>":()V
      42: astore_2
      43: goto          54
      46: new           #11                 // class io/vertx/ext/web/sstore/impl/LocalSessionStoreImpl
      49: dup
      50: invokespecial #12                 // Method io/vertx/ext/web/sstore/impl/LocalSessionStoreImpl."<init>":()V
      53: astore_2
      54: aload_2
      55: aload_0
      56: aload_1
      57: invokeinterface #6,  3            // InterfaceMethod init:(Lio/vertx/core/Vertx;Lio/vertx/core/json/JsonObject;)Lio/vertx/ext/web/sstore/SessionStore;
      62: areturn
    Exception table:
       from    to  target type
           0    21    25   Class java/lang/RuntimeException

  public abstract io.vertx.ext.web.sstore.SessionStore init(io.vertx.core.Vertx, io.vertx.core.json.JsonObject);

  public abstract long retryTimeout();

  public abstract io.vertx.ext.web.Session createSession(long);

  public abstract io.vertx.ext.web.Session createSession(long, int);

  public default io.vertx.ext.web.sstore.SessionStore get(java.lang.String, io.vertx.core.Handler<io.vertx.core.AsyncResult<io.vertx.ext.web.Session>>);
    Code:
       0: aload_0
       1: aload_1
       2: invokeinterface #13,  2           // InterfaceMethod get:(Ljava/lang/String;)Lio/vertx/core/Future;
       7: aload_2
       8: invokeinterface #14,  2           // InterfaceMethod io/vertx/core/Future.onComplete:(Lio/vertx/core/Handler;)Lio/vertx/core/Future;
      13: pop
      14: aload_0
      15: areturn

  public abstract io.vertx.core.Future<io.vertx.ext.web.Session> get(java.lang.String);

  public default io.vertx.ext.web.sstore.SessionStore delete(java.lang.String, io.vertx.core.Handler<io.vertx.core.AsyncResult<java.lang.Void>>);
    Code:
       0: aload_0
       1: aload_1
       2: invokeinterface #15,  2           // InterfaceMethod delete:(Ljava/lang/String;)Lio/vertx/core/Future;
       7: aload_2
       8: invokeinterface #14,  2           // InterfaceMethod io/vertx/core/Future.onComplete:(Lio/vertx/core/Handler;)Lio/vertx/core/Future;
      13: pop
      14: aload_0
      15: areturn

  public abstract io.vertx.core.Future<java.lang.Void> delete(java.lang.String);

  public default io.vertx.ext.web.sstore.SessionStore put(io.vertx.ext.web.Session, io.vertx.core.Handler<io.vertx.core.AsyncResult<java.lang.Void>>);
    Code:
       0: aload_0
       1: aload_1
       2: invokeinterface #16,  2           // InterfaceMethod put:(Lio/vertx/ext/web/Session;)Lio/vertx/core/Future;
       7: aload_2
       8: invokeinterface #14,  2           // InterfaceMethod io/vertx/core/Future.onComplete:(Lio/vertx/core/Handler;)Lio/vertx/core/Future;
      13: pop
      14: aload_0
      15: areturn

  public abstract io.vertx.core.Future<java.lang.Void> put(io.vertx.ext.web.Session);

  public default io.vertx.ext.web.sstore.SessionStore clear(io.vertx.core.Handler<io.vertx.core.AsyncResult<java.lang.Void>>);
    Code:
       0: aload_0
       1: invokeinterface #17,  1           // InterfaceMethod clear:()Lio/vertx/core/Future;
       6: aload_1
       7: invokeinterface #14,  2           // InterfaceMethod io/vertx/core/Future.onComplete:(Lio/vertx/core/Handler;)Lio/vertx/core/Future;
      12: pop
      13: aload_0
      14: areturn

  public abstract io.vertx.core.Future<java.lang.Void> clear();

  public default io.vertx.ext.web.sstore.SessionStore size(io.vertx.core.Handler<io.vertx.core.AsyncResult<java.lang.Integer>>);
    Code:
       0: aload_0
       1: invokeinterface #18,  1           // InterfaceMethod size:()Lio/vertx/core/Future;
       6: aload_1
       7: invokeinterface #14,  2           // InterfaceMethod io/vertx/core/Future.onComplete:(Lio/vertx/core/Handler;)Lio/vertx/core/Future;
      12: pop
      13: aload_0
      14: areturn

  public abstract io.vertx.core.Future<java.lang.Integer> size();

  public abstract void close();
}
