Compiled from "ProvisionDeviceResponse.scala"
public final class zio.aws.panorama.model.ProvisionDeviceResponse$Wrapper implements zio.aws.panorama.model.ProvisionDeviceResponse$ReadOnly {
  private final java.lang.String arn;

  private final zio.prelude.data.Optional<zio.Chunk> certificates;

  private final zio.prelude.data.Optional<java.lang.String> deviceId;

  private final zio.prelude.data.Optional<java.lang.String> iotThingName;

  private final zio.aws.panorama.model.DeviceStatus status;

  public zio.aws.panorama.model.ProvisionDeviceResponse asEditable();
    Code:
       0: aload_0
       1: invokestatic  #49                 // InterfaceMethod zio/aws/panorama/model/ProvisionDeviceResponse$ReadOnly.asEditable$:(Lzio/aws/panorama/model/ProvisionDeviceResponse$ReadOnly;)Lzio/aws/panorama/model/ProvisionDeviceResponse;
       4: areturn

  public zio.ZIO<java.lang.Object, scala.runtime.Nothing$, java.lang.String> getArn();
    Code:
       0: aload_0
       1: invokestatic  #58                 // InterfaceMethod zio/aws/panorama/model/ProvisionDeviceResponse$ReadOnly.getArn$:(Lzio/aws/panorama/model/ProvisionDeviceResponse$ReadOnly;)Lzio/ZIO;
       4: areturn

  public zio.ZIO<java.lang.Object, zio.aws.core.AwsError, zio.Chunk> getCertificates();
    Code:
       0: aload_0
       1: invokestatic  #63                 // InterfaceMethod zio/aws/panorama/model/ProvisionDeviceResponse$ReadOnly.getCertificates$:(Lzio/aws/panorama/model/ProvisionDeviceResponse$ReadOnly;)Lzio/ZIO;
       4: areturn

  public zio.ZIO<java.lang.Object, zio.aws.core.AwsError, java.lang.String> getDeviceId();
    Code:
       0: aload_0
       1: invokestatic  #68                 // InterfaceMethod zio/aws/panorama/model/ProvisionDeviceResponse$ReadOnly.getDeviceId$:(Lzio/aws/panorama/model/ProvisionDeviceResponse$ReadOnly;)Lzio/ZIO;
       4: areturn

  public zio.ZIO<java.lang.Object, zio.aws.core.AwsError, java.lang.String> getIotThingName();
    Code:
       0: aload_0
       1: invokestatic  #72                 // InterfaceMethod zio/aws/panorama/model/ProvisionDeviceResponse$ReadOnly.getIotThingName$:(Lzio/aws/panorama/model/ProvisionDeviceResponse$ReadOnly;)Lzio/ZIO;
       4: areturn

  public zio.ZIO<java.lang.Object, scala.runtime.Nothing$, zio.aws.panorama.model.DeviceStatus> getStatus();
    Code:
       0: aload_0
       1: invokestatic  #77                 // InterfaceMethod zio/aws/panorama/model/ProvisionDeviceResponse$ReadOnly.getStatus$:(Lzio/aws/panorama/model/ProvisionDeviceResponse$ReadOnly;)Lzio/ZIO;
       4: areturn

  public java.lang.String arn();
    Code:
       0: aload_0
       1: getfield      #80                 // Field arn:Ljava/lang/String;
       4: areturn

  public zio.prelude.data.Optional<zio.Chunk> certificates();
    Code:
       0: aload_0
       1: getfield      #84                 // Field certificates:Lzio/prelude/data/Optional;
       4: areturn

  public zio.prelude.data.Optional<java.lang.String> deviceId();
    Code:
       0: aload_0
       1: getfield      #87                 // Field deviceId:Lzio/prelude/data/Optional;
       4: areturn

  public zio.prelude.data.Optional<java.lang.String> iotThingName();
    Code:
       0: aload_0
       1: getfield      #89                 // Field iotThingName:Lzio/prelude/data/Optional;
       4: areturn

  public zio.aws.panorama.model.DeviceStatus status();
    Code:
       0: aload_0
       1: getfield      #92                 // Field status:Lzio/aws/panorama/model/DeviceStatus;
       4: areturn

  public static final zio.Chunk $anonfun$certificates$1(software.amazon.awssdk.core.SdkBytes);
    Code:
       0: getstatic     #101                // Field zio/prelude/Newtype$.MODULE$:Lzio/prelude/Newtype$;
       3: getstatic     #104                // Field zio/aws/panorama/model/package$primitives$Certificates$.MODULE$:Lzio/aws/panorama/model/package$primitives$Certificates$;
       6: getstatic     #109                // Field zio/Chunk$.MODULE$:Lzio/Chunk$;
       9: aload_0
      10: invokevirtual #115                // Method software/amazon/awssdk/core/SdkBytes.asByteArrayUnsafe:()[B
      13: invokevirtual #119                // Method zio/Chunk$.fromArray:(Ljava/lang/Object;)Lzio/Chunk;
      16: invokevirtual #123                // Method zio/prelude/Newtype$.unsafeWrap:(Lzio/prelude/Newtype;Ljava/lang/Object;)Ljava/lang/Object;
      19: checkcast     #125                // class zio/Chunk
      22: areturn

  public static final java.lang.String $anonfun$deviceId$1(java.lang.String);
    Code:
       0: getstatic     #101                // Field zio/prelude/Newtype$.MODULE$:Lzio/prelude/Newtype$;
       3: getstatic     #131                // Field zio/aws/panorama/model/package$primitives$DeviceId$.MODULE$:Lzio/aws/panorama/model/package$primitives$DeviceId$;
       6: aload_0
       7: invokevirtual #123                // Method zio/prelude/Newtype$.unsafeWrap:(Lzio/prelude/Newtype;Ljava/lang/Object;)Ljava/lang/Object;
      10: checkcast     #133                // class java/lang/String
      13: areturn

  public static final java.lang.String $anonfun$iotThingName$1(java.lang.String);
    Code:
       0: getstatic     #101                // Field zio/prelude/Newtype$.MODULE$:Lzio/prelude/Newtype$;
       3: getstatic     #137                // Field zio/aws/panorama/model/package$primitives$IotThingName$.MODULE$:Lzio/aws/panorama/model/package$primitives$IotThingName$;
       6: aload_0
       7: invokevirtual #123                // Method zio/prelude/Newtype$.unsafeWrap:(Lzio/prelude/Newtype;Ljava/lang/Object;)Ljava/lang/Object;
      10: checkcast     #133                // class java/lang/String
      13: areturn

  public zio.aws.panorama.model.ProvisionDeviceResponse$Wrapper(software.amazon.awssdk.services.panorama.model.ProvisionDeviceResponse);
    Code:
       0: aload_0
       1: invokespecial #143                // Method java/lang/Object."<init>":()V
       4: aload_0
       5: invokestatic  #147                // InterfaceMethod zio/aws/panorama/model/ProvisionDeviceResponse$ReadOnly.$init$:(Lzio/aws/panorama/model/ProvisionDeviceResponse$ReadOnly;)V
       8: aload_0
       9: getstatic     #101                // Field zio/prelude/Newtype$.MODULE$:Lzio/prelude/Newtype$;
      12: getstatic     #150                // Field zio/aws/panorama/model/package$primitives$DeviceArn$.MODULE$:Lzio/aws/panorama/model/package$primitives$DeviceArn$;
      15: aload_1
      16: invokevirtual #154                // Method software/amazon/awssdk/services/panorama/model/ProvisionDeviceResponse.arn:()Ljava/lang/String;
      19: invokevirtual #123                // Method zio/prelude/Newtype$.unsafeWrap:(Lzio/prelude/Newtype;Ljava/lang/Object;)Ljava/lang/Object;
      22: checkcast     #133                // class java/lang/String
      25: putfield      #80                 // Field arn:Ljava/lang/String;
      28: aload_0
      29: getstatic     #159                // Field zio/aws/core/internal/package$.MODULE$:Lzio/aws/core/internal/package$;
      32: aload_1
      33: invokevirtual #162                // Method software/amazon/awssdk/services/panorama/model/ProvisionDeviceResponse.certificates:()Lsoftware/amazon/awssdk/core/SdkBytes;
      36: invokevirtual #166                // Method zio/aws/core/internal/package$.optionalFromNullable:(Ljava/lang/Object;)Lzio/prelude/data/Optional;
      39: invokedynamic #187,  0            // InvokeDynamic #0:apply:()Lscala/Function1;
      44: invokeinterface #193,  2          // InterfaceMethod zio/prelude/data/Optional.map:(Lscala/Function1;)Lzio/prelude/data/Optional;
      49: putfield      #84                 // Field certificates:Lzio/prelude/data/Optional;
      52: aload_0
      53: getstatic     #159                // Field zio/aws/core/internal/package$.MODULE$:Lzio/aws/core/internal/package$;
      56: aload_1
      57: invokevirtual #195                // Method software/amazon/awssdk/services/panorama/model/ProvisionDeviceResponse.deviceId:()Ljava/lang/String;
      60: invokevirtual #166                // Method zio/aws/core/internal/package$.optionalFromNullable:(Ljava/lang/Object;)Lzio/prelude/data/Optional;
      63: invokedynamic #200,  0            // InvokeDynamic #1:apply:()Lscala/Function1;
      68: invokeinterface #193,  2          // InterfaceMethod zio/prelude/data/Optional.map:(Lscala/Function1;)Lzio/prelude/data/Optional;
      73: putfield      #87                 // Field deviceId:Lzio/prelude/data/Optional;
      76: aload_0
      77: getstatic     #159                // Field zio/aws/core/internal/package$.MODULE$:Lzio/aws/core/internal/package$;
      80: aload_1
      81: invokevirtual #202                // Method software/amazon/awssdk/services/panorama/model/ProvisionDeviceResponse.iotThingName:()Ljava/lang/String;
      84: invokevirtual #166                // Method zio/aws/core/internal/package$.optionalFromNullable:(Ljava/lang/Object;)Lzio/prelude/data/Optional;
      87: invokedynamic #206,  0            // InvokeDynamic #2:apply:()Lscala/Function1;
      92: invokeinterface #193,  2          // InterfaceMethod zio/prelude/data/Optional.map:(Lscala/Function1;)Lzio/prelude/data/Optional;
      97: putfield      #89                 // Field iotThingName:Lzio/prelude/data/Optional;
     100: aload_0
     101: getstatic     #211                // Field zio/aws/panorama/model/DeviceStatus$.MODULE$:Lzio/aws/panorama/model/DeviceStatus$;
     104: aload_1
     105: invokevirtual #214                // Method software/amazon/awssdk/services/panorama/model/ProvisionDeviceResponse.status:()Lsoftware/amazon/awssdk/services/panorama/model/DeviceStatus;
     108: invokevirtual #218                // Method zio/aws/panorama/model/DeviceStatus$.wrap:(Lsoftware/amazon/awssdk/services/panorama/model/DeviceStatus;)Lzio/aws/panorama/model/DeviceStatus;
     111: putfield      #92                 // Field status:Lzio/aws/panorama/model/DeviceStatus;
     114: return

  private static java.lang.Object $deserializeLambda$(java.lang.invoke.SerializedLambda);
    Code:
       0: aload_0
       1: invokedynamic #231,  0            // InvokeDynamic #3:lambdaDeserialize:(Ljava/lang/invoke/SerializedLambda;)Ljava/lang/Object;
       6: areturn
}
