Compiled from "UpdateDeviceMetadataRequest.scala"
public final class zio.aws.panorama.model.UpdateDeviceMetadataRequest$Wrapper implements zio.aws.panorama.model.UpdateDeviceMetadataRequest$ReadOnly {
  private final zio.prelude.data.Optional<java.lang.String> description;

  private final java.lang.String deviceId;

  public zio.aws.panorama.model.UpdateDeviceMetadataRequest asEditable();
    Code:
       0: aload_0
       1: invokestatic  #38                 // InterfaceMethod zio/aws/panorama/model/UpdateDeviceMetadataRequest$ReadOnly.asEditable$:(Lzio/aws/panorama/model/UpdateDeviceMetadataRequest$ReadOnly;)Lzio/aws/panorama/model/UpdateDeviceMetadataRequest;
       4: areturn

  public zio.ZIO<java.lang.Object, zio.aws.core.AwsError, java.lang.String> getDescription();
    Code:
       0: aload_0
       1: invokestatic  #47                 // InterfaceMethod zio/aws/panorama/model/UpdateDeviceMetadataRequest$ReadOnly.getDescription$:(Lzio/aws/panorama/model/UpdateDeviceMetadataRequest$ReadOnly;)Lzio/ZIO;
       4: areturn

  public zio.ZIO<java.lang.Object, scala.runtime.Nothing$, java.lang.String> getDeviceId();
    Code:
       0: aload_0
       1: invokestatic  #52                 // InterfaceMethod zio/aws/panorama/model/UpdateDeviceMetadataRequest$ReadOnly.getDeviceId$:(Lzio/aws/panorama/model/UpdateDeviceMetadataRequest$ReadOnly;)Lzio/ZIO;
       4: areturn

  public zio.prelude.data.Optional<java.lang.String> description();
    Code:
       0: aload_0
       1: getfield      #56                 // Field description:Lzio/prelude/data/Optional;
       4: areturn

  public java.lang.String deviceId();
    Code:
       0: aload_0
       1: getfield      #59                 // Field deviceId:Ljava/lang/String;
       4: areturn

  public static final java.lang.String $anonfun$description$1(java.lang.String);
    Code:
       0: getstatic     #68                 // Field zio/prelude/Newtype$.MODULE$:Lzio/prelude/Newtype$;
       3: getstatic     #71                 // Field zio/aws/panorama/model/package$primitives$Description$.MODULE$:Lzio/aws/panorama/model/package$primitives$Description$;
       6: aload_0
       7: invokevirtual #75                 // Method zio/prelude/Newtype$.unsafeWrap:(Lzio/prelude/Newtype;Ljava/lang/Object;)Ljava/lang/Object;
      10: checkcast     #77                 // class java/lang/String
      13: areturn

  public zio.aws.panorama.model.UpdateDeviceMetadataRequest$Wrapper(software.amazon.awssdk.services.panorama.model.UpdateDeviceMetadataRequest);
    Code:
       0: aload_0
       1: invokespecial #83                 // Method java/lang/Object."<init>":()V
       4: aload_0
       5: invokestatic  #87                 // InterfaceMethod zio/aws/panorama/model/UpdateDeviceMetadataRequest$ReadOnly.$init$:(Lzio/aws/panorama/model/UpdateDeviceMetadataRequest$ReadOnly;)V
       8: aload_0
       9: getstatic     #92                 // Field zio/aws/core/internal/package$.MODULE$:Lzio/aws/core/internal/package$;
      12: aload_1
      13: invokevirtual #96                 // Method software/amazon/awssdk/services/panorama/model/UpdateDeviceMetadataRequest.description:()Ljava/lang/String;
      16: invokevirtual #100                // Method zio/aws/core/internal/package$.optionalFromNullable:(Ljava/lang/Object;)Lzio/prelude/data/Optional;
      19: invokedynamic #121,  0            // InvokeDynamic #0:apply:()Lscala/Function1;
      24: invokeinterface #127,  2          // InterfaceMethod zio/prelude/data/Optional.map:(Lscala/Function1;)Lzio/prelude/data/Optional;
      29: putfield      #56                 // Field description:Lzio/prelude/data/Optional;
      32: aload_0
      33: getstatic     #68                 // Field zio/prelude/Newtype$.MODULE$:Lzio/prelude/Newtype$;
      36: getstatic     #130                // Field zio/aws/panorama/model/package$primitives$DeviceId$.MODULE$:Lzio/aws/panorama/model/package$primitives$DeviceId$;
      39: aload_1
      40: invokevirtual #132                // Method software/amazon/awssdk/services/panorama/model/UpdateDeviceMetadataRequest.deviceId:()Ljava/lang/String;
      43: invokevirtual #75                 // Method zio/prelude/Newtype$.unsafeWrap:(Lzio/prelude/Newtype;Ljava/lang/Object;)Ljava/lang/Object;
      46: checkcast     #77                 // class java/lang/String
      49: putfield      #59                 // Field deviceId:Ljava/lang/String;
      52: return

  private static java.lang.Object $deserializeLambda$(java.lang.invoke.SerializedLambda);
    Code:
       0: aload_0
       1: invokedynamic #145,  0            // InvokeDynamic #1:lambdaDeserialize:(Ljava/lang/invoke/SerializedLambda;)Ljava/lang/Object;
       6: areturn
}
