Compiled from "Bookie.java"
public class org.apache.bookkeeper.bookie.Bookie extends org.apache.bookkeeper.bookie.BookieCriticalThread {
  private static final org.slf4j.Logger LOG;

  final java.util.List<java.io.File> journalDirectories;

  final org.apache.bookkeeper.conf.ServerConfiguration conf;

  final org.apache.bookkeeper.bookie.SyncThread syncThread;

  final org.apache.bookkeeper.meta.LedgerManagerFactory ledgerManagerFactory;

  final org.apache.bookkeeper.meta.LedgerManager ledgerManager;

  final org.apache.bookkeeper.bookie.LedgerStorage ledgerStorage;

  final java.util.List<org.apache.bookkeeper.bookie.Journal> journals;

  final org.apache.bookkeeper.bookie.HandleFactory handles;

  final boolean entryLogPerLedgerEnabled;

  public static final long METAENTRY_ID_LEDGER_KEY;

  public static final long METAENTRY_ID_FENCE_KEY;

  public static final long METAENTRY_ID_FORCE_LEDGER;

  static final long METAENTRY_ID_LEDGER_EXPLICITLAC;

  private final org.apache.bookkeeper.bookie.LedgerDirsManager ledgerDirsManager;

  protected final java.util.function.Supplier<org.apache.bookkeeper.discover.BookieServiceInfo> bookieServiceInfoProvider;

  private final org.apache.bookkeeper.bookie.LedgerDirsManager indexDirsManager;

  org.apache.bookkeeper.bookie.LedgerDirsMonitor dirsMonitor;

  protected final org.apache.bookkeeper.meta.MetadataBookieDriver metadataDriver;

  private int exitCode;

  private final org.apache.bookkeeper.util.collections.ConcurrentLongHashMap<byte[]> masterKeyCache;

  protected org.apache.bookkeeper.bookie.StateManager stateManager;

  final org.apache.bookkeeper.stats.StatsLogger statsLogger;

  private final org.apache.bookkeeper.bookie.stats.BookieStats bookieStats;

  private final io.netty.buffer.ByteBufAllocator allocator;

  private final boolean writeDataToJournal;

  private final org.apache.bookkeeper.stats.Gauge<java.lang.Long> journalMemoryMaxStats;

  private final org.apache.bookkeeper.stats.Gauge<java.lang.Long> journalMemoryUsedStats;

  java.util.concurrent.atomic.AtomicBoolean shutdownTriggered;

  public static void checkDirectoryStructure(java.io.File) throws java.io.IOException;
    Code:
       0: aload_0
       1: invokevirtual #4                  // Method java/io/File.exists:()Z
       4: ifne          134
       7: aload_0
       8: invokevirtual #5                  // Method java/io/File.getParentFile:()Ljava/io/File;
      11: astore_1
      12: new           #6                  // class java/io/File
      15: dup
      16: aload_0
      17: invokevirtual #7                  // Method java/io/File.getParent:()Ljava/lang/String;
      20: ldc           #9                  // String VERSION
      22: invokespecial #10                 // Method java/io/File."<init>":(Ljava/lang/String;Ljava/lang/String;)V
      25: astore_2
      26: new           #11                 // class java/util/concurrent/atomic/AtomicBoolean
      29: dup
      30: iconst_0
      31: invokespecial #12                 // Method java/util/concurrent/atomic/AtomicBoolean."<init>":(Z)V
      34: astore_3
      35: aload_1
      36: new           #13                 // class org/apache/bookkeeper/bookie/Bookie$1
      39: dup
      40: aload_3
      41: invokespecial #14                 // Method org/apache/bookkeeper/bookie/Bookie$1."<init>":(Ljava/util/concurrent/atomic/AtomicBoolean;)V
      44: invokevirtual #15                 // Method java/io/File.list:(Ljava/io/FilenameFilter;)[Ljava/lang/String;
      47: pop
      48: aload_2
      49: invokevirtual #4                  // Method java/io/File.exists:()Z
      52: ifne          62
      55: aload_3
      56: invokevirtual #16                 // Method java/util/concurrent/atomic/AtomicBoolean.get:()Z
      59: ifeq          86
      62: ldc           #17                 // String Directory layout version is less than 3, upgrade needed
      64: astore        4
      66: getstatic     #3                  // Field LOG:Lorg/slf4j/Logger;
      69: aload         4
      71: invokeinterface #18,  2           // InterfaceMethod org/slf4j/Logger.error:(Ljava/lang/String;)V
      76: new           #19                 // class java/io/IOException
      79: dup
      80: aload         4
      82: invokespecial #20                 // Method java/io/IOException."<init>":(Ljava/lang/String;)V
      85: athrow
      86: aload_0
      87: invokevirtual #21                 // Method java/io/File.mkdirs:()Z
      90: ifne          134
      93: new           #22                 // class java/lang/StringBuilder
      96: dup
      97: invokespecial #23                 // Method java/lang/StringBuilder."<init>":()V
     100: ldc           #24                 // String Unable to create directory
     102: invokevirtual #25                 // Method java/lang/StringBuilder.append:(Ljava/lang/String;)Ljava/lang/StringBuilder;
     105: aload_0
     106: invokevirtual #26                 // Method java/lang/StringBuilder.append:(Ljava/lang/Object;)Ljava/lang/StringBuilder;
     109: invokevirtual #27                 // Method java/lang/StringBuilder.toString:()Ljava/lang/String;
     112: astore        4
     114: getstatic     #3                  // Field LOG:Lorg/slf4j/Logger;
     117: aload         4
     119: invokeinterface #18,  2           // InterfaceMethod org/slf4j/Logger.error:(Ljava/lang/String;)V
     124: new           #19                 // class java/io/IOException
     127: dup
     128: aload         4
     130: invokespecial #20                 // Method java/io/IOException."<init>":(Ljava/lang/String;)V
     133: athrow
     134: return

  private void checkEnvironment(org.apache.bookkeeper.meta.MetadataBookieDriver) throws org.apache.bookkeeper.bookie.BookieException, java.io.IOException;
    Code:
       0: new           #28                 // class java/util/ArrayList
       3: dup
       4: aload_0
       5: getfield      #29                 // Field ledgerDirsManager:Lorg/apache/bookkeeper/bookie/LedgerDirsManager;
       8: invokevirtual #30                 // Method org/apache/bookkeeper/bookie/LedgerDirsManager.getAllLedgerDirs:()Ljava/util/List;
      11: invokeinterface #31,  1           // InterfaceMethod java/util/List.size:()I
      16: aload_0
      17: getfield      #32                 // Field indexDirsManager:Lorg/apache/bookkeeper/bookie/LedgerDirsManager;
      20: invokevirtual #30                 // Method org/apache/bookkeeper/bookie/LedgerDirsManager.getAllLedgerDirs:()Ljava/util/List;
      23: invokeinterface #31,  1           // InterfaceMethod java/util/List.size:()I
      28: iadd
      29: invokespecial #33                 // Method java/util/ArrayList."<init>":(I)V
      32: astore_2
      33: aload_2
      34: aload_0
      35: getfield      #29                 // Field ledgerDirsManager:Lorg/apache/bookkeeper/bookie/LedgerDirsManager;
      38: invokevirtual #30                 // Method org/apache/bookkeeper/bookie/LedgerDirsManager.getAllLedgerDirs:()Ljava/util/List;
      41: invokeinterface #34,  2           // InterfaceMethod java/util/List.addAll:(Ljava/util/Collection;)Z
      46: pop
      47: aload_0
      48: getfield      #32                 // Field indexDirsManager:Lorg/apache/bookkeeper/bookie/LedgerDirsManager;
      51: aload_0
      52: getfield      #29                 // Field ledgerDirsManager:Lorg/apache/bookkeeper/bookie/LedgerDirsManager;
      55: if_acmpeq     72
      58: aload_2
      59: aload_0
      60: getfield      #32                 // Field indexDirsManager:Lorg/apache/bookkeeper/bookie/LedgerDirsManager;
      63: invokevirtual #30                 // Method org/apache/bookkeeper/bookie/LedgerDirsManager.getAllLedgerDirs:()Ljava/util/List;
      66: invokeinterface #34,  2           // InterfaceMethod java/util/List.addAll:(Ljava/util/Collection;)Z
      71: pop
      72: aload_1
      73: ifnonnull     150
      76: aload_0
      77: getfield      #35                 // Field journalDirectories:Ljava/util/List;
      80: invokeinterface #36,  1           // InterfaceMethod java/util/List.iterator:()Ljava/util/Iterator;
      85: astore_3
      86: aload_3
      87: invokeinterface #37,  1           // InterfaceMethod java/util/Iterator.hasNext:()Z
      92: ifeq          114
      95: aload_3
      96: invokeinterface #38,  1           // InterfaceMethod java/util/Iterator.next:()Ljava/lang/Object;
     101: checkcast     #6                  // class java/io/File
     104: astore        4
     106: aload         4
     108: invokestatic  #39                 // Method checkDirectoryStructure:(Ljava/io/File;)V
     111: goto          86
     114: aload_2
     115: invokeinterface #36,  1           // InterfaceMethod java/util/List.iterator:()Ljava/util/Iterator;
     120: astore_3
     121: aload_3
     122: invokeinterface #37,  1           // InterfaceMethod java/util/Iterator.hasNext:()Z
     127: ifeq          149
     130: aload_3
     131: invokeinterface #38,  1           // InterfaceMethod java/util/Iterator.next:()Ljava/lang/Object;
     136: checkcast     #6                  // class java/io/File
     139: astore        4
     141: aload         4
     143: invokestatic  #39                 // Method checkDirectoryStructure:(Ljava/io/File;)V
     146: goto          121
     149: return
     150: aload_0
     151: getfield      #40                 // Field conf:Lorg/apache/bookkeeper/conf/ServerConfiguration;
     154: aload_1
     155: aload_0
     156: getfield      #35                 // Field journalDirectories:Ljava/util/List;
     159: aload_2
     160: invokestatic  #41                 // Method checkEnvironmentWithStorageExpansion:(Lorg/apache/bookkeeper/conf/ServerConfiguration;Lorg/apache/bookkeeper/meta/MetadataBookieDriver;Ljava/util/List;Ljava/util/List;)V
     163: aload_0
     164: aload_2
     165: invokespecial #42                 // Method checkIfDirsOnSameDiskPartition:(Ljava/util/List;)V
     168: aload_0
     169: aload_0
     170: getfield      #35                 // Field journalDirectories:Ljava/util/List;
     173: invokespecial #42                 // Method checkIfDirsOnSameDiskPartition:(Ljava/util/List;)V
     176: return

  private void checkIfDirsOnSameDiskPartition(java.util.List<java.io.File>) throws org.apache.bookkeeper.bookie.BookieException$DiskPartitionDuplicationException;
    Code:
       0: aload_0
       1: getfield      #40                 // Field conf:Lorg/apache/bookkeeper/conf/ServerConfiguration;
       4: invokevirtual #43                 // Method org/apache/bookkeeper/conf/ServerConfiguration.isAllowMultipleDirsUnderSameDiskPartition:()Z
       7: istore_2
       8: new           #44                 // class org/apache/commons/lang3/mutable/MutableBoolean
      11: dup
      12: iconst_0
      13: invokespecial #45                 // Method org/apache/commons/lang3/mutable/MutableBoolean."<init>":(Z)V
      16: astore_3
      17: new           #46                 // class java/util/HashMap
      20: dup
      21: invokespecial #47                 // Method java/util/HashMap."<init>":()V
      24: astore        4
      26: aload_1
      27: invokeinterface #36,  1           // InterfaceMethod java/util/List.iterator:()Ljava/util/Iterator;
      32: astore        5
      34: aload         5
      36: invokeinterface #37,  1           // InterfaceMethod java/util/Iterator.hasNext:()Z
      41: ifeq          162
      44: aload         5
      46: invokeinterface #38,  1           // InterfaceMethod java/util/Iterator.next:()Ljava/lang/Object;
      51: checkcast     #6                  // class java/io/File
      54: astore        6
      56: aload         6
      58: invokevirtual #48                 // Method java/io/File.toPath:()Ljava/nio/file/Path;
      61: invokestatic  #49                 // Method java/nio/file/Files.getFileStore:(Ljava/nio/file/Path;)Ljava/nio/file/FileStore;
      64: astore        7
      66: goto          93
      69: astore        8
      71: getstatic     #3                  // Field LOG:Lorg/slf4j/Logger;
      74: ldc           #50                 // String Got IOException while trying to FileStore of {}
      76: aload         6
      78: invokeinterface #51,  3           // InterfaceMethod org/slf4j/Logger.error:(Ljava/lang/String;Ljava/lang/Object;)V
      83: new           #52                 // class org/apache/bookkeeper/bookie/BookieException$DiskPartitionDuplicationException
      86: dup
      87: aload         8
      89: invokespecial #53                 // Method org/apache/bookkeeper/bookie/BookieException$DiskPartitionDuplicationException."<init>":(Ljava/lang/Throwable;)V
      92: athrow
      93: aload         4
      95: aload         7
      97: invokeinterface #54,  2           // InterfaceMethod java/util/Map.containsKey:(Ljava/lang/Object;)Z
     102: ifeq          128
     105: aload         4
     107: aload         7
     109: invokeinterface #55,  2           // InterfaceMethod java/util/Map.get:(Ljava/lang/Object;)Ljava/lang/Object;
     114: checkcast     #56                 // class java/util/List
     117: aload         6
     119: invokeinterface #57,  2           // InterfaceMethod java/util/List.add:(Ljava/lang/Object;)Z
     124: pop
     125: goto          159
     128: new           #28                 // class java/util/ArrayList
     131: dup
     132: invokespecial #58                 // Method java/util/ArrayList."<init>":()V
     135: astore        8
     137: aload         8
     139: aload         6
     141: invokeinterface #57,  2           // InterfaceMethod java/util/List.add:(Ljava/lang/Object;)Z
     146: pop
     147: aload         4
     149: aload         7
     151: aload         8
     153: invokeinterface #59,  3           // InterfaceMethod java/util/Map.put:(Ljava/lang/Object;Ljava/lang/Object;)Ljava/lang/Object;
     158: pop
     159: goto          34
     162: aload         4
     164: iload_2
     165: aload_3
     166: invokedynamic #60,  0             // InvokeDynamic #0:accept:(ZLorg/apache/commons/lang3/mutable/MutableBoolean;)Ljava/util/function/BiConsumer;
     171: invokeinterface #61,  2           // InterfaceMethod java/util/Map.forEach:(Ljava/util/function/BiConsumer;)V
     176: aload_3
     177: invokevirtual #62                 // Method org/apache/commons/lang3/mutable/MutableBoolean.getValue:()Ljava/lang/Boolean;
     180: invokevirtual #63                 // Method java/lang/Boolean.booleanValue:()Z
     183: ifeq          194
     186: new           #52                 // class org/apache/bookkeeper/bookie/BookieException$DiskPartitionDuplicationException
     189: dup
     190: invokespecial #64                 // Method org/apache/bookkeeper/bookie/BookieException$DiskPartitionDuplicationException."<init>":()V
     193: athrow
     194: return
    Exception table:
       from    to  target type
          56    66    69   Class java/io/IOException

  static java.util.List<org.apache.bookkeeper.net.BookieId> possibleBookieIds(org.apache.bookkeeper.conf.ServerConfiguration) throws org.apache.bookkeeper.bookie.BookieException;
    Code:
       0: iconst_3
       1: invokestatic  #65                 // Method com/google/common/collect/Lists.newArrayListWithExpectedSize:(I)Ljava/util/ArrayList;
       4: astore_1
       5: aload_1
       6: new           #66                 // class org/apache/bookkeeper/conf/ServerConfiguration
       9: dup
      10: aload_0
      11: invokespecial #67                 // Method org/apache/bookkeeper/conf/ServerConfiguration."<init>":(Lorg/apache/bookkeeper/conf/AbstractConfiguration;)V
      14: iconst_0
      15: invokevirtual #68                 // Method org/apache/bookkeeper/conf/ServerConfiguration.setUseHostNameAsBookieID:(Z)Lorg/apache/bookkeeper/conf/ServerConfiguration;
      18: aconst_null
      19: invokevirtual #69                 // Method org/apache/bookkeeper/conf/ServerConfiguration.setAdvertisedAddress:(Ljava/lang/String;)Lorg/apache/bookkeeper/conf/ServerConfiguration;
      22: iconst_1
      23: invokevirtual #70                 // Method org/apache/bookkeeper/conf/ServerConfiguration.setAllowLoopback:(Z)Lorg/apache/bookkeeper/conf/ServerConfiguration;
      26: invokestatic  #71                 // Method getBookieAddress:(Lorg/apache/bookkeeper/conf/ServerConfiguration;)Lorg/apache/bookkeeper/net/BookieSocketAddress;
      29: invokevirtual #72                 // Method org/apache/bookkeeper/net/BookieSocketAddress.toBookieId:()Lorg/apache/bookkeeper/net/BookieId;
      32: invokeinterface #57,  2           // InterfaceMethod java/util/List.add:(Ljava/lang/Object;)Z
      37: pop
      38: aload_1
      39: new           #66                 // class org/apache/bookkeeper/conf/ServerConfiguration
      42: dup
      43: aload_0
      44: invokespecial #67                 // Method org/apache/bookkeeper/conf/ServerConfiguration."<init>":(Lorg/apache/bookkeeper/conf/AbstractConfiguration;)V
      47: iconst_1
      48: invokevirtual #68                 // Method org/apache/bookkeeper/conf/ServerConfiguration.setUseHostNameAsBookieID:(Z)Lorg/apache/bookkeeper/conf/ServerConfiguration;
      51: aconst_null
      52: invokevirtual #69                 // Method org/apache/bookkeeper/conf/ServerConfiguration.setAdvertisedAddress:(Ljava/lang/String;)Lorg/apache/bookkeeper/conf/ServerConfiguration;
      55: iconst_1
      56: invokevirtual #70                 // Method org/apache/bookkeeper/conf/ServerConfiguration.setAllowLoopback:(Z)Lorg/apache/bookkeeper/conf/ServerConfiguration;
      59: invokestatic  #71                 // Method getBookieAddress:(Lorg/apache/bookkeeper/conf/ServerConfiguration;)Lorg/apache/bookkeeper/net/BookieSocketAddress;
      62: invokevirtual #72                 // Method org/apache/bookkeeper/net/BookieSocketAddress.toBookieId:()Lorg/apache/bookkeeper/net/BookieId;
      65: invokeinterface #57,  2           // InterfaceMethod java/util/List.add:(Ljava/lang/Object;)Z
      70: pop
      71: aconst_null
      72: aload_0
      73: invokevirtual #73                 // Method org/apache/bookkeeper/conf/ServerConfiguration.getAdvertisedAddress:()Ljava/lang/String;
      76: if_acmpeq     93
      79: aload_1
      80: aload_0
      81: invokestatic  #71                 // Method getBookieAddress:(Lorg/apache/bookkeeper/conf/ServerConfiguration;)Lorg/apache/bookkeeper/net/BookieSocketAddress;
      84: invokevirtual #72                 // Method org/apache/bookkeeper/net/BookieSocketAddress.toBookieId:()Lorg/apache/bookkeeper/net/BookieId;
      87: invokeinterface #57,  2           // InterfaceMethod java/util/List.add:(Ljava/lang/Object;)Z
      92: pop
      93: aconst_null
      94: aload_0
      95: invokevirtual #74                 // Method org/apache/bookkeeper/conf/ServerConfiguration.getBookieId:()Ljava/lang/String;
      98: if_acmpeq     115
     101: aload_1
     102: aload_0
     103: invokevirtual #74                 // Method org/apache/bookkeeper/conf/ServerConfiguration.getBookieId:()Ljava/lang/String;
     106: invokestatic  #75                 // Method org/apache/bookkeeper/net/BookieId.parse:(Ljava/lang/String;)Lorg/apache/bookkeeper/net/BookieId;
     109: invokeinterface #57,  2           // InterfaceMethod java/util/List.add:(Ljava/lang/Object;)Z
     114: pop
     115: goto          128
     118: astore_2
     119: new           #77                 // class org/apache/bookkeeper/bookie/BookieException$UnknownBookieIdException
     122: dup
     123: aload_2
     124: invokespecial #78                 // Method org/apache/bookkeeper/bookie/BookieException$UnknownBookieIdException."<init>":(Ljava/lang/Throwable;)V
     127: athrow
     128: aload_1
     129: areturn
    Exception table:
       from    to  target type
           5   115   118   Class java/net/UnknownHostException

  static org.apache.bookkeeper.versioning.Versioned<org.apache.bookkeeper.bookie.Cookie> readAndVerifyCookieFromRegistrationManager(org.apache.bookkeeper.bookie.Cookie, org.apache.bookkeeper.discover.RegistrationManager, java.util.List<org.apache.bookkeeper.net.BookieId>, boolean) throws org.apache.bookkeeper.bookie.BookieException;
    Code:
       0: aconst_null
       1: astore        4
       3: aload_2
       4: invokeinterface #36,  1           // InterfaceMethod java/util/List.iterator:()Ljava/util/Iterator;
       9: astore        5
      11: aload         5
      13: invokeinterface #37,  1           // InterfaceMethod java/util/Iterator.hasNext:()Z
      18: ifeq          83
      21: aload         5
      23: invokeinterface #38,  1           // InterfaceMethod java/util/Iterator.next:()Ljava/lang/Object;
      28: checkcast     #79                 // class org/apache/bookkeeper/net/BookieId
      31: astore        6
      33: aload_1
      34: aload         6
      36: invokestatic  #80                 // Method org/apache/bookkeeper/bookie/Cookie.readFromRegistrationManager:(Lorg/apache/bookkeeper/discover/RegistrationManager;Lorg/apache/bookkeeper/net/BookieId;)Lorg/apache/bookkeeper/versioning/Versioned;
      39: astore        4
      41: iload_3
      42: ifeq          60
      45: aload_0
      46: aload         4
      48: invokevirtual #81                 // Method org/apache/bookkeeper/versioning/Versioned.getValue:()Ljava/lang/Object;
      51: checkcast     #82                 // class org/apache/bookkeeper/bookie/Cookie
      54: invokevirtual #83                 // Method org/apache/bookkeeper/bookie/Cookie.verifyIsSuperSet:(Lorg/apache/bookkeeper/bookie/Cookie;)V
      57: goto          72
      60: aload_0
      61: aload         4
      63: invokevirtual #81                 // Method org/apache/bookkeeper/versioning/Versioned.getValue:()Ljava/lang/Object;
      66: checkcast     #82                 // class org/apache/bookkeeper/bookie/Cookie
      69: invokevirtual #84                 // Method org/apache/bookkeeper/bookie/Cookie.verify:(Lorg/apache/bookkeeper/bookie/Cookie;)V
      72: goto          80
      75: astore        7
      77: goto          11
      80: goto          11
      83: aload         4
      85: areturn
    Exception table:
       from    to  target type
          33    72    75   Class org/apache/bookkeeper/bookie/BookieException$CookieNotFoundException

  private static org.apache.commons.lang3.tuple.Pair<java.util.List<java.io.File>, java.util.List<org.apache.bookkeeper.bookie.Cookie>> verifyAndGetMissingDirs(org.apache.bookkeeper.bookie.Cookie, boolean, java.util.List<java.io.File>) throws org.apache.bookkeeper.bookie.BookieException$InvalidCookieException, java.io.IOException;
    Code:
       0: invokestatic  #86                 // Method com/google/common/collect/Lists.newArrayList:()Ljava/util/ArrayList;
       3: astore_3
       4: invokestatic  #86                 // Method com/google/common/collect/Lists.newArrayList:()Ljava/util/ArrayList;
       7: astore        4
       9: aload_2
      10: invokeinterface #36,  1           // InterfaceMethod java/util/List.iterator:()Ljava/util/Iterator;
      15: astore        5
      17: aload         5
      19: invokeinterface #37,  1           // InterfaceMethod java/util/Iterator.hasNext:()Z
      24: ifeq          97
      27: aload         5
      29: invokeinterface #38,  1           // InterfaceMethod java/util/Iterator.next:()Ljava/lang/Object;
      34: checkcast     #6                  // class java/io/File
      37: astore        6
      39: aload         6
      41: invokestatic  #39                 // Method checkDirectoryStructure:(Ljava/io/File;)V
      44: aload         6
      46: invokestatic  #87                 // Method org/apache/bookkeeper/bookie/Cookie.readFromDirectory:(Ljava/io/File;)Lorg/apache/bookkeeper/bookie/Cookie;
      49: astore        7
      51: iload_1
      52: ifeq          64
      55: aload_0
      56: aload         7
      58: invokevirtual #83                 // Method org/apache/bookkeeper/bookie/Cookie.verifyIsSuperSet:(Lorg/apache/bookkeeper/bookie/Cookie;)V
      61: goto          70
      64: aload_0
      65: aload         7
      67: invokevirtual #84                 // Method org/apache/bookkeeper/bookie/Cookie.verify:(Lorg/apache/bookkeeper/bookie/Cookie;)V
      70: aload         4
      72: aload         7
      74: invokeinterface #57,  2           // InterfaceMethod java/util/List.add:(Ljava/lang/Object;)Z
      79: pop
      80: goto          94
      83: astore        7
      85: aload_3
      86: aload         6
      88: invokeinterface #57,  2           // InterfaceMethod java/util/List.add:(Ljava/lang/Object;)Z
      93: pop
      94: goto          17
      97: aload_3
      98: aload         4
     100: invokestatic  #89                 // Method org/apache/commons/lang3/tuple/Pair.of:(Ljava/lang/Object;Ljava/lang/Object;)Lorg/apache/commons/lang3/tuple/Pair;
     103: areturn
    Exception table:
       from    to  target type
          44    80    83   Class java/io/FileNotFoundException

  private static void stampNewCookie(org.apache.bookkeeper.conf.ServerConfiguration, org.apache.bookkeeper.bookie.Cookie, org.apache.bookkeeper.discover.RegistrationManager, org.apache.bookkeeper.versioning.Version, java.util.List<java.io.File>, java.util.List<java.io.File>) throws org.apache.bookkeeper.bookie.BookieException, java.io.IOException;
    Code:
       0: getstatic     #3                  // Field LOG:Lorg/slf4j/Logger;
       3: ldc           #90                 // String Stamping new cookies on all dirs {} {}
       5: aload         4
       7: aload         5
       9: invokeinterface #91,  4           // InterfaceMethod org/slf4j/Logger.info:(Ljava/lang/String;Ljava/lang/Object;Ljava/lang/Object;)V
      14: aload         4
      16: invokeinterface #36,  1           // InterfaceMethod java/util/List.iterator:()Ljava/util/Iterator;
      21: astore        6
      23: aload         6
      25: invokeinterface #37,  1           // InterfaceMethod java/util/Iterator.hasNext:()Z
      30: ifeq          54
      33: aload         6
      35: invokeinterface #38,  1           // InterfaceMethod java/util/Iterator.next:()Ljava/lang/Object;
      40: checkcast     #6                  // class java/io/File
      43: astore        7
      45: aload_1
      46: aload         7
      48: invokevirtual #92                 // Method org/apache/bookkeeper/bookie/Cookie.writeToDirectory:(Ljava/io/File;)V
      51: goto          23
      54: aload         5
      56: invokeinterface #36,  1           // InterfaceMethod java/util/List.iterator:()Ljava/util/Iterator;
      61: astore        6
      63: aload         6
      65: invokeinterface #37,  1           // InterfaceMethod java/util/Iterator.hasNext:()Z
      70: ifeq          94
      73: aload         6
      75: invokeinterface #38,  1           // InterfaceMethod java/util/Iterator.next:()Ljava/lang/Object;
      80: checkcast     #6                  // class java/io/File
      83: astore        7
      85: aload_1
      86: aload         7
      88: invokevirtual #92                 // Method org/apache/bookkeeper/bookie/Cookie.writeToDirectory:(Ljava/io/File;)V
      91: goto          63
      94: aload_1
      95: aload_2
      96: aload_0
      97: aload_3
      98: invokevirtual #93                 // Method org/apache/bookkeeper/bookie/Cookie.writeToRegistrationManager:(Lorg/apache/bookkeeper/discover/RegistrationManager;Lorg/apache/bookkeeper/conf/ServerConfiguration;Lorg/apache/bookkeeper/versioning/Version;)V
     101: return

  public static void checkEnvironmentWithStorageExpansion(org.apache.bookkeeper.conf.ServerConfiguration, org.apache.bookkeeper.meta.MetadataBookieDriver, java.util.List<java.io.File>, java.util.List<java.io.File>) throws org.apache.bookkeeper.bookie.BookieException;
    Code:
       0: aload_1
       1: invokeinterface #94,  1           // InterfaceMethod org/apache/bookkeeper/meta/MetadataBookieDriver.getRegistrationManager:()Lorg/apache/bookkeeper/discover/RegistrationManager;
       6: astore        4
       8: aload         4
      10: invokeinterface #95,  1           // InterfaceMethod org/apache/bookkeeper/discover/RegistrationManager.getClusterInstanceId:()Ljava/lang/String;
      15: astore        5
      17: aload_0
      18: invokestatic  #96                 // Method org/apache/bookkeeper/bookie/Cookie.generateCookie:(Lorg/apache/bookkeeper/conf/ServerConfiguration;)Lorg/apache/bookkeeper/bookie/Cookie$Builder;
      21: astore        6
      23: aconst_null
      24: aload         5
      26: if_acmpeq     37
      29: aload         6
      31: aload         5
      33: invokevirtual #97                 // Method org/apache/bookkeeper/bookie/Cookie$Builder.setInstanceId:(Ljava/lang/String;)Lorg/apache/bookkeeper/bookie/Cookie$Builder;
      36: pop
      37: aload         6
      39: invokevirtual #98                 // Method org/apache/bookkeeper/bookie/Cookie$Builder.build:()Lorg/apache/bookkeeper/bookie/Cookie;
      42: astore        7
      44: aload_0
      45: invokevirtual #99                 // Method org/apache/bookkeeper/conf/ServerConfiguration.getAllowStorageExpansion:()Z
      48: istore        8
      50: aload_0
      51: invokestatic  #100                // Method possibleBookieIds:(Lorg/apache/bookkeeper/conf/ServerConfiguration;)Ljava/util/List;
      54: astore        9
      56: aload         7
      58: aload         4
      60: aload         9
      62: iload         8
      64: invokestatic  #101                // Method readAndVerifyCookieFromRegistrationManager:(Lorg/apache/bookkeeper/bookie/Cookie;Lorg/apache/bookkeeper/discover/RegistrationManager;Ljava/util/List;Z)Lorg/apache/bookkeeper/versioning/Versioned;
      67: astore        10
      69: new           #28                 // class java/util/ArrayList
      72: dup
      73: invokespecial #58                 // Method java/util/ArrayList."<init>":()V
      76: astore        11
      78: invokestatic  #86                 // Method com/google/common/collect/Lists.newArrayList:()Ljava/util/ArrayList;
      81: astore        12
      83: aconst_null
      84: aload         10
      86: if_acmpeq     102
      89: aload         12
      91: aload         10
      93: invokevirtual #81                 // Method org/apache/bookkeeper/versioning/Versioned.getValue:()Ljava/lang/Object;
      96: invokeinterface #57,  2           // InterfaceMethod java/util/List.add:(Ljava/lang/Object;)Z
     101: pop
     102: aload         7
     104: iload         8
     106: aload_2
     107: invokestatic  #102                // Method verifyAndGetMissingDirs:(Lorg/apache/bookkeeper/bookie/Cookie;ZLjava/util/List;)Lorg/apache/commons/lang3/tuple/Pair;
     110: astore        13
     112: aload         11
     114: aload         13
     116: invokevirtual #103                // Method org/apache/commons/lang3/tuple/Pair.getLeft:()Ljava/lang/Object;
     119: checkcast     #104                // class java/util/Collection
     122: invokeinterface #34,  2           // InterfaceMethod java/util/List.addAll:(Ljava/util/Collection;)Z
     127: pop
     128: aload         12
     130: aload         13
     132: invokevirtual #105                // Method org/apache/commons/lang3/tuple/Pair.getRight:()Ljava/lang/Object;
     135: checkcast     #104                // class java/util/Collection
     138: invokeinterface #34,  2           // InterfaceMethod java/util/List.addAll:(Ljava/util/Collection;)Z
     143: pop
     144: aload         7
     146: iload         8
     148: aload_3
     149: invokestatic  #102                // Method verifyAndGetMissingDirs:(Lorg/apache/bookkeeper/bookie/Cookie;ZLjava/util/List;)Lorg/apache/commons/lang3/tuple/Pair;
     152: astore        14
     154: aload         11
     156: aload         14
     158: invokevirtual #103                // Method org/apache/commons/lang3/tuple/Pair.getLeft:()Ljava/lang/Object;
     161: checkcast     #104                // class java/util/Collection
     164: invokeinterface #34,  2           // InterfaceMethod java/util/List.addAll:(Ljava/util/Collection;)Z
     169: pop
     170: aload         12
     172: aload         14
     174: invokevirtual #105                // Method org/apache/commons/lang3/tuple/Pair.getRight:()Ljava/lang/Object;
     177: checkcast     #104                // class java/util/Collection
     180: invokeinterface #34,  2           // InterfaceMethod java/util/List.addAll:(Ljava/util/Collection;)Z
     185: pop
     186: aload         11
     188: invokeinterface #106,  1          // InterfaceMethod java/util/List.isEmpty:()Z
     193: ifne          279
     196: aload         10
     198: ifnonnull     222
     201: aload         11
     203: invokestatic  #107                // Method verifyDirsForNewEnvironment:(Ljava/util/List;)V
     206: aload_0
     207: aload         7
     209: aload         4
     211: getstatic     #108                // Field org/apache/bookkeeper/versioning/Version.NEW:Lorg/apache/bookkeeper/versioning/Version;
     214: aload_2
     215: aload_3
     216: invokestatic  #109                // Method stampNewCookie:(Lorg/apache/bookkeeper/conf/ServerConfiguration;Lorg/apache/bookkeeper/bookie/Cookie;Lorg/apache/bookkeeper/discover/RegistrationManager;Lorg/apache/bookkeeper/versioning/Version;Ljava/util/List;Ljava/util/List;)V
     219: goto          302
     222: iload         8
     224: ifeq          259
     227: aload         12
     229: invokestatic  #110                // Method getKnownDirs:(Ljava/util/List;)Ljava/util/Set;
     232: astore        15
     234: aload         11
     236: aload         15
     238: invokestatic  #111                // Method verifyDirsForStorageExpansion:(Ljava/util/List;Ljava/util/Set;)V
     241: aload_0
     242: aload         7
     244: aload         4
     246: aload         10
     248: invokevirtual #112                // Method org/apache/bookkeeper/versioning/Versioned.getVersion:()Lorg/apache/bookkeeper/versioning/Version;
     251: aload_2
     252: aload_3
     253: invokestatic  #109                // Method stampNewCookie:(Lorg/apache/bookkeeper/conf/ServerConfiguration;Lorg/apache/bookkeeper/bookie/Cookie;Lorg/apache/bookkeeper/discover/RegistrationManager;Lorg/apache/bookkeeper/versioning/Version;Ljava/util/List;Ljava/util/List;)V
     256: goto          302
     259: getstatic     #3                  // Field LOG:Lorg/slf4j/Logger;
     262: ldc           #113                // String There are directories without a cookie, and this is neither a new environment, nor is storage expansion enabled. Empty directories are {}
     264: aload         11
     266: invokeinterface #51,  3           // InterfaceMethod org/slf4j/Logger.error:(Ljava/lang/String;Ljava/lang/Object;)V
     271: new           #114                // class org/apache/bookkeeper/bookie/BookieException$InvalidCookieException
     274: dup
     275: invokespecial #115                // Method org/apache/bookkeeper/bookie/BookieException$InvalidCookieException."<init>":()V
     278: athrow
     279: aload         10
     281: ifnonnull     302
     284: getstatic     #3                  // Field LOG:Lorg/slf4j/Logger;
     287: ldc           #116                // String Cookie for this bookie is not stored in metadata store. Bookie failing to come up
     289: invokeinterface #18,  2           // InterfaceMethod org/slf4j/Logger.error:(Ljava/lang/String;)V
     294: new           #114                // class org/apache/bookkeeper/bookie/BookieException$InvalidCookieException
     297: dup
     298: invokespecial #115                // Method org/apache/bookkeeper/bookie/BookieException$InvalidCookieException."<init>":()V
     301: athrow
     302: goto          329
     305: astore        5
     307: getstatic     #3                  // Field LOG:Lorg/slf4j/Logger;
     310: ldc           #117                // String Error accessing cookie on disks
     312: aload         5
     314: invokeinterface #118,  3          // InterfaceMethod org/slf4j/Logger.error:(Ljava/lang/String;Ljava/lang/Throwable;)V
     319: new           #114                // class org/apache/bookkeeper/bookie/BookieException$InvalidCookieException
     322: dup
     323: aload         5
     325: invokespecial #119                // Method org/apache/bookkeeper/bookie/BookieException$InvalidCookieException."<init>":(Ljava/lang/Throwable;)V
     328: athrow
     329: return
    Exception table:
       from    to  target type
           8   302   305   Class java/io/IOException

  private static void verifyDirsForNewEnvironment(java.util.List<java.io.File>) throws org.apache.bookkeeper.bookie.BookieException$InvalidCookieException;
    Code:
       0: new           #28                 // class java/util/ArrayList
       3: dup
       4: invokespecial #58                 // Method java/util/ArrayList."<init>":()V
       7: astore_1
       8: aload_0
       9: invokeinterface #36,  1           // InterfaceMethod java/util/List.iterator:()Ljava/util/Iterator;
      14: astore_2
      15: aload_2
      16: invokeinterface #37,  1           // InterfaceMethod java/util/Iterator.hasNext:()Z
      21: ifeq          62
      24: aload_2
      25: invokeinterface #38,  1           // InterfaceMethod java/util/Iterator.next:()Ljava/lang/Object;
      30: checkcast     #6                  // class java/io/File
      33: astore_3
      34: aload_3
      35: invokevirtual #120                // Method java/io/File.list:()[Ljava/lang/String;
      38: astore        4
      40: aload         4
      42: ifnull        59
      45: aload         4
      47: arraylength
      48: ifeq          59
      51: aload_1
      52: aload_3
      53: invokeinterface #57,  2           // InterfaceMethod java/util/List.add:(Ljava/lang/Object;)Z
      58: pop
      59: goto          15
      62: aload_1
      63: invokeinterface #106,  1          // InterfaceMethod java/util/List.isEmpty:()Z
      68: ifne          106
      71: getstatic     #3                  // Field LOG:Lorg/slf4j/Logger;
      74: new           #22                 // class java/lang/StringBuilder
      77: dup
      78: invokespecial #23                 // Method java/lang/StringBuilder."<init>":()V
      81: ldc           #121                // String Not all the new directories are empty. New directories that are not empty are:
      83: invokevirtual #25                 // Method java/lang/StringBuilder.append:(Ljava/lang/String;)Ljava/lang/StringBuilder;
      86: aload_1
      87: invokevirtual #26                 // Method java/lang/StringBuilder.append:(Ljava/lang/Object;)Ljava/lang/StringBuilder;
      90: invokevirtual #27                 // Method java/lang/StringBuilder.toString:()Ljava/lang/String;
      93: invokeinterface #18,  2           // InterfaceMethod org/slf4j/Logger.error:(Ljava/lang/String;)V
      98: new           #114                // class org/apache/bookkeeper/bookie/BookieException$InvalidCookieException
     101: dup
     102: invokespecial #115                // Method org/apache/bookkeeper/bookie/BookieException$InvalidCookieException."<init>":()V
     105: athrow
     106: return

  private static java.util.Set<java.io.File> getKnownDirs(java.util.List<org.apache.bookkeeper.bookie.Cookie>);
    Code:
       0: aload_0
       1: invokeinterface #122,  1          // InterfaceMethod java/util/List.stream:()Ljava/util/stream/Stream;
       6: invokedynamic #123,  0            // InvokeDynamic #1:apply:()Ljava/util/function/Function;
      11: invokeinterface #124,  2          // InterfaceMethod java/util/stream/Stream.flatMap:(Ljava/util/function/Function;)Ljava/util/stream/Stream;
      16: invokedynamic #125,  0            // InvokeDynamic #2:apply:()Ljava/util/function/Function;
      21: invokeinterface #126,  2          // InterfaceMethod java/util/stream/Stream.map:(Ljava/util/function/Function;)Ljava/util/stream/Stream;
      26: invokestatic  #127                // Method java/util/stream/Collectors.toSet:()Ljava/util/stream/Collector;
      29: invokeinterface #128,  2          // InterfaceMethod java/util/stream/Stream.collect:(Ljava/util/stream/Collector;)Ljava/lang/Object;
      34: checkcast     #129                // class java/util/Set
      37: areturn

  private static void verifyDirsForStorageExpansion(java.util.List<java.io.File>, java.util.Set<java.io.File>) throws org.apache.bookkeeper.bookie.BookieException$InvalidCookieException;
    Code:
       0: new           #28                 // class java/util/ArrayList
       3: dup
       4: invokespecial #58                 // Method java/util/ArrayList."<init>":()V
       7: astore_2
       8: new           #28                 // class java/util/ArrayList
      11: dup
      12: invokespecial #58                 // Method java/util/ArrayList."<init>":()V
      15: astore_3
      16: aload_0
      17: invokeinterface #36,  1           // InterfaceMethod java/util/List.iterator:()Ljava/util/Iterator;
      22: astore        4
      24: aload         4
      26: invokeinterface #37,  1           // InterfaceMethod java/util/Iterator.hasNext:()Z
      31: ifeq          102
      34: aload         4
      36: invokeinterface #38,  1           // InterfaceMethod java/util/Iterator.next:()Ljava/lang/Object;
      41: checkcast     #6                  // class java/io/File
      44: astore        5
      46: aload_1
      47: aload         5
      49: invokevirtual #5                  // Method java/io/File.getParentFile:()Ljava/io/File;
      52: invokeinterface #130,  2          // InterfaceMethod java/util/Set.contains:(Ljava/lang/Object;)Z
      57: ifeq          72
      60: aload_2
      61: aload         5
      63: invokeinterface #57,  2           // InterfaceMethod java/util/List.add:(Ljava/lang/Object;)Z
      68: pop
      69: goto          24
      72: aload         5
      74: invokevirtual #120                // Method java/io/File.list:()[Ljava/lang/String;
      77: astore        6
      79: aload         6
      81: ifnull        99
      84: aload         6
      86: arraylength
      87: ifeq          99
      90: aload_3
      91: aload         5
      93: invokeinterface #57,  2           // InterfaceMethod java/util/List.add:(Ljava/lang/Object;)Z
      98: pop
      99: goto          24
     102: aload_2
     103: invokeinterface #31,  1           // InterfaceMethod java/util/List.size:()I
     108: ifgt          120
     111: aload_3
     112: invokeinterface #31,  1           // InterfaceMethod java/util/List.size:()I
     117: ifle          164
     120: getstatic     #3                  // Field LOG:Lorg/slf4j/Logger;
     123: new           #22                 // class java/lang/StringBuilder
     126: dup
     127: invokespecial #23                 // Method java/lang/StringBuilder."<init>":()V
     130: ldc           #131                // String Either not all local directories have cookies or directories being added  newly are not empty. Directories missing cookie file are:
     132: invokevirtual #25                 // Method java/lang/StringBuilder.append:(Ljava/lang/String;)Ljava/lang/StringBuilder;
     135: aload_2
     136: invokevirtual #26                 // Method java/lang/StringBuilder.append:(Ljava/lang/Object;)Ljava/lang/StringBuilder;
     139: ldc           #132                // String  New directories that are not empty are:
     141: invokevirtual #25                 // Method java/lang/StringBuilder.append:(Ljava/lang/String;)Ljava/lang/StringBuilder;
     144: aload_3
     145: invokevirtual #26                 // Method java/lang/StringBuilder.append:(Ljava/lang/Object;)Ljava/lang/StringBuilder;
     148: invokevirtual #27                 // Method java/lang/StringBuilder.toString:()Ljava/lang/String;
     151: invokeinterface #18,  2           // InterfaceMethod org/slf4j/Logger.error:(Ljava/lang/String;)V
     156: new           #114                // class org/apache/bookkeeper/bookie/BookieException$InvalidCookieException
     159: dup
     160: invokespecial #115                // Method org/apache/bookkeeper/bookie/BookieException$InvalidCookieException."<init>":()V
     163: athrow
     164: return

  public static org.apache.bookkeeper.net.BookieId getBookieId(org.apache.bookkeeper.conf.ServerConfiguration) throws java.net.UnknownHostException;
    Code:
       0: aload_0
       1: invokevirtual #74                 // Method org/apache/bookkeeper/conf/ServerConfiguration.getBookieId:()Ljava/lang/String;
       4: astore_1
       5: aload_1
       6: ifnull        14
       9: aload_1
      10: invokestatic  #75                 // Method org/apache/bookkeeper/net/BookieId.parse:(Ljava/lang/String;)Lorg/apache/bookkeeper/net/BookieId;
      13: areturn
      14: aload_0
      15: invokestatic  #71                 // Method getBookieAddress:(Lorg/apache/bookkeeper/conf/ServerConfiguration;)Lorg/apache/bookkeeper/net/BookieSocketAddress;
      18: invokevirtual #72                 // Method org/apache/bookkeeper/net/BookieSocketAddress.toBookieId:()Lorg/apache/bookkeeper/net/BookieId;
      21: areturn

  public static org.apache.bookkeeper.net.BookieSocketAddress getBookieAddress(org.apache.bookkeeper.conf.ServerConfiguration) throws java.net.UnknownHostException;
    Code:
       0: aload_0
       1: invokevirtual #73                 // Method org/apache/bookkeeper/conf/ServerConfiguration.getAdvertisedAddress:()Ljava/lang/String;
       4: ifnull        41
       7: aload_0
       8: invokevirtual #73                 // Method org/apache/bookkeeper/conf/ServerConfiguration.getAdvertisedAddress:()Ljava/lang/String;
      11: invokevirtual #133                // Method java/lang/String.trim:()Ljava/lang/String;
      14: invokevirtual #134                // Method java/lang/String.length:()I
      17: ifle          41
      20: aload_0
      21: invokevirtual #73                 // Method org/apache/bookkeeper/conf/ServerConfiguration.getAdvertisedAddress:()Ljava/lang/String;
      24: invokevirtual #133                // Method java/lang/String.trim:()Ljava/lang/String;
      27: astore_1
      28: new           #135                // class org/apache/bookkeeper/net/BookieSocketAddress
      31: dup
      32: aload_1
      33: aload_0
      34: invokevirtual #136                // Method org/apache/bookkeeper/conf/ServerConfiguration.getBookiePort:()I
      37: invokespecial #137                // Method org/apache/bookkeeper/net/BookieSocketAddress."<init>":(Ljava/lang/String;I)V
      40: areturn
      41: aload_0
      42: invokevirtual #138                // Method org/apache/bookkeeper/conf/ServerConfiguration.getListeningInterface:()Ljava/lang/String;
      45: astore_1
      46: aload_1
      47: ifnonnull     53
      50: ldc           #139                // String default
      52: astore_1
      53: aload_1
      54: invokestatic  #140                // Method org/apache/bookkeeper/net/DNS.getDefaultHost:(Ljava/lang/String;)Ljava/lang/String;
      57: astore_2
      58: new           #141                // class java/net/InetSocketAddress
      61: dup
      62: aload_2
      63: aload_0
      64: invokevirtual #136                // Method org/apache/bookkeeper/conf/ServerConfiguration.getBookiePort:()I
      67: invokespecial #142                // Method java/net/InetSocketAddress."<init>":(Ljava/lang/String;I)V
      70: astore_3
      71: aload_3
      72: invokevirtual #143                // Method java/net/InetSocketAddress.isUnresolved:()Z
      75: ifeq          114
      78: new           #76                 // class java/net/UnknownHostException
      81: dup
      82: new           #22                 // class java/lang/StringBuilder
      85: dup
      86: invokespecial #23                 // Method java/lang/StringBuilder."<init>":()V
      89: ldc           #144                // String Unable to resolve default hostname:
      91: invokevirtual #25                 // Method java/lang/StringBuilder.append:(Ljava/lang/String;)Ljava/lang/StringBuilder;
      94: aload_2
      95: invokevirtual #25                 // Method java/lang/StringBuilder.append:(Ljava/lang/String;)Ljava/lang/StringBuilder;
      98: ldc           #145                // String  for interface:
     100: invokevirtual #25                 // Method java/lang/StringBuilder.append:(Ljava/lang/String;)Ljava/lang/StringBuilder;
     103: aload_1
     104: invokevirtual #25                 // Method java/lang/StringBuilder.append:(Ljava/lang/String;)Ljava/lang/StringBuilder;
     107: invokevirtual #27                 // Method java/lang/StringBuilder.toString:()Ljava/lang/String;
     110: invokespecial #146                // Method java/net/UnknownHostException."<init>":(Ljava/lang/String;)V
     113: athrow
     114: aconst_null
     115: astore        4
     117: aload_3
     118: invokevirtual #147                // Method java/net/InetSocketAddress.getAddress:()Ljava/net/InetAddress;
     121: astore        5
     123: aload_0
     124: invokevirtual #148                // Method org/apache/bookkeeper/conf/ServerConfiguration.getUseHostNameAsBookieID:()Z
     127: ifeq          159
     130: aload         5
     132: invokevirtual #149                // Method java/net/InetAddress.getCanonicalHostName:()Ljava/lang/String;
     135: astore        4
     137: aload_0
     138: invokevirtual #150                // Method org/apache/bookkeeper/conf/ServerConfiguration.getUseShortHostName:()Z
     141: ifeq          166
     144: aload         4
     146: ldc           #151                // String \\.
     148: iconst_2
     149: invokevirtual #152                // Method java/lang/String.split:(Ljava/lang/String;I)[Ljava/lang/String;
     152: iconst_0
     153: aaload
     154: astore        4
     156: goto          166
     159: aload         5
     161: invokevirtual #153                // Method java/net/InetAddress.getHostAddress:()Ljava/lang/String;
     164: astore        4
     166: new           #135                // class org/apache/bookkeeper/net/BookieSocketAddress
     169: dup
     170: aload         4
     172: aload_0
     173: invokevirtual #136                // Method org/apache/bookkeeper/conf/ServerConfiguration.getBookiePort:()I
     176: invokespecial #137                // Method org/apache/bookkeeper/net/BookieSocketAddress."<init>":(Ljava/lang/String;I)V
     179: astore        6
     181: aload         6
     183: invokevirtual #154                // Method org/apache/bookkeeper/net/BookieSocketAddress.getSocketAddress:()Ljava/net/InetSocketAddress;
     186: invokevirtual #147                // Method java/net/InetSocketAddress.getAddress:()Ljava/net/InetAddress;
     189: invokevirtual #155                // Method java/net/InetAddress.isLoopbackAddress:()Z
     192: ifeq          235
     195: aload_0
     196: invokevirtual #156                // Method org/apache/bookkeeper/conf/ServerConfiguration.getAllowLoopback:()Z
     199: ifne          235
     202: new           #76                 // class java/net/UnknownHostException
     205: dup
     206: new           #22                 // class java/lang/StringBuilder
     209: dup
     210: invokespecial #23                 // Method java/lang/StringBuilder."<init>":()V
     213: ldc           #157                // String Trying to listen on loopback address,
     215: invokevirtual #25                 // Method java/lang/StringBuilder.append:(Ljava/lang/String;)Ljava/lang/StringBuilder;
     218: aload         6
     220: invokevirtual #26                 // Method java/lang/StringBuilder.append:(Ljava/lang/Object;)Ljava/lang/StringBuilder;
     223: ldc           #158                // String  but this is forbidden by default (see ServerConfiguration#getAllowLoopback()).\nIf this happen, you can consider specifying the network interface to listen on (e.g. listeningInterface=eth0) or specifying the advertised address (e.g. advertisedAddress=172.x.y.z)
     225: invokevirtual #25                 // Method java/lang/StringBuilder.append:(Ljava/lang/String;)Ljava/lang/StringBuilder;
     228: invokevirtual #27                 // Method java/lang/StringBuilder.toString:()Ljava/lang/String;
     231: invokespecial #146                // Method java/net/UnknownHostException."<init>":(Ljava/lang/String;)V
     234: athrow
     235: aload         6
     237: areturn

  public org.apache.bookkeeper.bookie.LedgerDirsManager getLedgerDirsManager();
    Code:
       0: aload_0
       1: getfield      #29                 // Field ledgerDirsManager:Lorg/apache/bookkeeper/bookie/LedgerDirsManager;
       4: areturn

  org.apache.bookkeeper.bookie.LedgerDirsManager getIndexDirsManager();
    Code:
       0: aload_0
       1: getfield      #32                 // Field indexDirsManager:Lorg/apache/bookkeeper/bookie/LedgerDirsManager;
       4: areturn

  public long getTotalDiskSpace() throws java.io.IOException;
    Code:
       0: aload_0
       1: invokevirtual #159                // Method getLedgerDirsManager:()Lorg/apache/bookkeeper/bookie/LedgerDirsManager;
       4: aload_0
       5: getfield      #29                 // Field ledgerDirsManager:Lorg/apache/bookkeeper/bookie/LedgerDirsManager;
       8: invokevirtual #30                 // Method org/apache/bookkeeper/bookie/LedgerDirsManager.getAllLedgerDirs:()Ljava/util/List;
      11: invokevirtual #160                // Method org/apache/bookkeeper/bookie/LedgerDirsManager.getTotalDiskSpace:(Ljava/util/List;)J
      14: lreturn

  public long getTotalFreeSpace() throws java.io.IOException;
    Code:
       0: aload_0
       1: invokevirtual #159                // Method getLedgerDirsManager:()Lorg/apache/bookkeeper/bookie/LedgerDirsManager;
       4: aload_0
       5: getfield      #29                 // Field ledgerDirsManager:Lorg/apache/bookkeeper/bookie/LedgerDirsManager;
       8: invokevirtual #30                 // Method org/apache/bookkeeper/bookie/LedgerDirsManager.getAllLedgerDirs:()Ljava/util/List;
      11: invokevirtual #161                // Method org/apache/bookkeeper/bookie/LedgerDirsManager.getTotalFreeSpace:(Ljava/util/List;)J
      14: lreturn

  public static java.io.File getCurrentDirectory(java.io.File);
    Code:
       0: new           #6                  // class java/io/File
       3: dup
       4: aload_0
       5: ldc           #162                // String current
       7: invokespecial #163                // Method java/io/File."<init>":(Ljava/io/File;Ljava/lang/String;)V
      10: areturn

  public static java.io.File[] getCurrentDirectories(java.io.File[]);
    Code:
       0: aload_0
       1: arraylength
       2: anewarray     #6                  // class java/io/File
       5: astore_1
       6: iconst_0
       7: istore_2
       8: iload_2
       9: aload_0
      10: arraylength
      11: if_icmpge     29
      14: aload_1
      15: iload_2
      16: aload_0
      17: iload_2
      18: aaload
      19: invokestatic  #164                // Method getCurrentDirectory:(Ljava/io/File;)Ljava/io/File;
      22: aastore
      23: iinc          2, 1
      26: goto          8
      29: aload_1
      30: areturn

  public org.apache.bookkeeper.bookie.Bookie(org.apache.bookkeeper.conf.ServerConfiguration) throws java.io.IOException, java.lang.InterruptedException, org.apache.bookkeeper.bookie.BookieException;
    Code:
       0: aload_0
       1: aload_1
       2: getstatic     #165                // Field org/apache/bookkeeper/stats/NullStatsLogger.INSTANCE:Lorg/apache/bookkeeper/stats/NullStatsLogger;
       5: getstatic     #166                // Field io/netty/buffer/PooledByteBufAllocator.DEFAULT:Lio/netty/buffer/PooledByteBufAllocator;
       8: new           #167                // class org/apache/bookkeeper/proto/SimpleBookieServiceInfoProvider
      11: dup
      12: aload_1
      13: invokespecial #168                // Method org/apache/bookkeeper/proto/SimpleBookieServiceInfoProvider."<init>":(Lorg/apache/bookkeeper/conf/ServerConfiguration;)V
      16: invokespecial #169                // Method "<init>":(Lorg/apache/bookkeeper/conf/ServerConfiguration;Lorg/apache/bookkeeper/stats/StatsLogger;Lio/netty/buffer/ByteBufAllocator;Ljava/util/function/Supplier;)V
      19: return

  private static org.apache.bookkeeper.bookie.LedgerStorage buildLedgerStorage(org.apache.bookkeeper.conf.ServerConfiguration) throws java.io.IOException;
    Code:
       0: aload_0
       1: invokevirtual #170                // Method org/apache/bookkeeper/conf/ServerConfiguration.getLedgerStorageClass:()Ljava/lang/String;
       4: astore_1
       5: getstatic     #3                  // Field LOG:Lorg/slf4j/Logger;
       8: ldc           #171                // String Using ledger storage: {}
      10: aload_1
      11: invokeinterface #172,  3          // InterfaceMethod org/slf4j/Logger.info:(Ljava/lang/String;Ljava/lang/Object;)V
      16: aload_1
      17: invokestatic  #173                // Method org/apache/bookkeeper/bookie/LedgerStorageFactory.createLedgerStorage:(Ljava/lang/String;)Lorg/apache/bookkeeper/bookie/LedgerStorage;
      20: areturn

  public static org.apache.bookkeeper.bookie.LedgerStorage mountLedgerStorageOffline(org.apache.bookkeeper.conf.ServerConfiguration, org.apache.bookkeeper.bookie.LedgerStorage) throws java.io.IOException;
    Code:
       0: getstatic     #165                // Field org/apache/bookkeeper/stats/NullStatsLogger.INSTANCE:Lorg/apache/bookkeeper/stats/NullStatsLogger;
       3: astore_2
       4: new           #174                // class org/apache/bookkeeper/util/DiskChecker
       7: dup
       8: aload_0
       9: invokevirtual #175                // Method org/apache/bookkeeper/conf/ServerConfiguration.getDiskUsageThreshold:()F
      12: aload_0
      13: invokevirtual #176                // Method org/apache/bookkeeper/conf/ServerConfiguration.getDiskUsageWarnThreshold:()F
      16: invokespecial #177                // Method org/apache/bookkeeper/util/DiskChecker."<init>":(FF)V
      19: astore_3
      20: aload_0
      21: aload_3
      22: aload_2
      23: ldc           #178                // String ledger
      25: invokeinterface #179,  2          // InterfaceMethod org/apache/bookkeeper/stats/StatsLogger.scope:(Ljava/lang/String;)Lorg/apache/bookkeeper/stats/StatsLogger;
      30: invokestatic  #180                // Method createLedgerDirsManager:(Lorg/apache/bookkeeper/conf/ServerConfiguration;Lorg/apache/bookkeeper/util/DiskChecker;Lorg/apache/bookkeeper/stats/StatsLogger;)Lorg/apache/bookkeeper/bookie/LedgerDirsManager;
      33: astore        4
      35: aload_0
      36: aload_3
      37: aload_2
      38: ldc           #181                // String index
      40: invokeinterface #179,  2          // InterfaceMethod org/apache/bookkeeper/stats/StatsLogger.scope:(Ljava/lang/String;)Lorg/apache/bookkeeper/stats/StatsLogger;
      45: aload         4
      47: invokestatic  #182                // Method createIndexDirsManager:(Lorg/apache/bookkeeper/conf/ServerConfiguration;Lorg/apache/bookkeeper/util/DiskChecker;Lorg/apache/bookkeeper/stats/StatsLogger;Lorg/apache/bookkeeper/bookie/LedgerDirsManager;)Lorg/apache/bookkeeper/bookie/LedgerDirsManager;
      50: astore        5
      52: aconst_null
      53: aload_1
      54: if_acmpne     62
      57: aload_0
      58: invokestatic  #183                // Method buildLedgerStorage:(Lorg/apache/bookkeeper/conf/ServerConfiguration;)Lorg/apache/bookkeeper/bookie/LedgerStorage;
      61: astore_1
      62: new           #184                // class org/apache/bookkeeper/bookie/Bookie$2
      65: dup
      66: invokespecial #185                // Method org/apache/bookkeeper/bookie/Bookie$2."<init>":()V
      69: astore        6
      71: getstatic     #186                // Field org/apache/bookkeeper/bookie/Checkpointer.NULL:Lorg/apache/bookkeeper/bookie/Checkpointer;
      74: astore        7
      76: aload_1
      77: aload_0
      78: aconst_null
      79: aload         4
      81: aload         5
      83: aconst_null
      84: aload         6
      86: aload         7
      88: aload_2
      89: getstatic     #187                // Field io/netty/buffer/UnpooledByteBufAllocator.DEFAULT:Lio/netty/buffer/UnpooledByteBufAllocator;
      92: invokeinterface #188,  10         // InterfaceMethod org/apache/bookkeeper/bookie/LedgerStorage.initialize:(Lorg/apache/bookkeeper/conf/ServerConfiguration;Lorg/apache/bookkeeper/meta/LedgerManager;Lorg/apache/bookkeeper/bookie/LedgerDirsManager;Lorg/apache/bookkeeper/bookie/LedgerDirsManager;Lorg/apache/bookkeeper/bookie/StateManager;Lorg/apache/bookkeeper/bookie/CheckpointSource;Lorg/apache/bookkeeper/bookie/Checkpointer;Lorg/apache/bookkeeper/stats/StatsLogger;Lio/netty/buffer/ByteBufAllocator;)V
      97: aload_1
      98: areturn

  public org.apache.bookkeeper.bookie.Bookie(org.apache.bookkeeper.conf.ServerConfiguration, org.apache.bookkeeper.stats.StatsLogger, io.netty.buffer.ByteBufAllocator, java.util.function.Supplier<org.apache.bookkeeper.discover.BookieServiceInfo>) throws java.io.IOException, java.lang.InterruptedException, org.apache.bookkeeper.bookie.BookieException;
    Code:
       0: aload_0
       1: new           #22                 // class java/lang/StringBuilder
       4: dup
       5: invokespecial #23                 // Method java/lang/StringBuilder."<init>":()V
       8: ldc           #189                // String Bookie-
      10: invokevirtual #25                 // Method java/lang/StringBuilder.append:(Ljava/lang/String;)Ljava/lang/StringBuilder;
      13: aload_1
      14: invokevirtual #136                // Method org/apache/bookkeeper/conf/ServerConfiguration.getBookiePort:()I
      17: invokevirtual #190                // Method java/lang/StringBuilder.append:(I)Ljava/lang/StringBuilder;
      20: invokevirtual #27                 // Method java/lang/StringBuilder.toString:()Ljava/lang/String;
      23: invokespecial #191                // Method org/apache/bookkeeper/bookie/BookieCriticalThread."<init>":(Ljava/lang/String;)V
      26: aload_0
      27: iconst_0
      28: putfield      #193                // Field exitCode:I
      31: aload_0
      32: new           #194                // class org/apache/bookkeeper/util/collections/ConcurrentLongHashMap
      35: dup
      36: invokespecial #195                // Method org/apache/bookkeeper/util/collections/ConcurrentLongHashMap."<init>":()V
      39: putfield      #2                  // Field masterKeyCache:Lorg/apache/bookkeeper/util/collections/ConcurrentLongHashMap;
      42: aload_0
      43: new           #11                 // class java/util/concurrent/atomic/AtomicBoolean
      46: dup
      47: iconst_0
      48: invokespecial #12                 // Method java/util/concurrent/atomic/AtomicBoolean."<init>":(Z)V
      51: putfield      #196                // Field shutdownTriggered:Ljava/util/concurrent/atomic/AtomicBoolean;
      54: aload_0
      55: aload         4
      57: putfield      #197                // Field bookieServiceInfoProvider:Ljava/util/function/Supplier;
      60: aload_0
      61: aload_2
      62: putfield      #198                // Field statsLogger:Lorg/apache/bookkeeper/stats/StatsLogger;
      65: aload_0
      66: aload_1
      67: putfield      #40                 // Field conf:Lorg/apache/bookkeeper/conf/ServerConfiguration;
      70: aload_0
      71: invokestatic  #86                 // Method com/google/common/collect/Lists.newArrayList:()Ljava/util/ArrayList;
      74: putfield      #35                 // Field journalDirectories:Ljava/util/List;
      77: aload_1
      78: invokevirtual #199                // Method org/apache/bookkeeper/conf/ServerConfiguration.getJournalDirs:()[Ljava/io/File;
      81: astore        5
      83: aload         5
      85: arraylength
      86: istore        6
      88: iconst_0
      89: istore        7
      91: iload         7
      93: iload         6
      95: if_icmpge     126
      98: aload         5
     100: iload         7
     102: aaload
     103: astore        8
     105: aload_0
     106: getfield      #35                 // Field journalDirectories:Ljava/util/List;
     109: aload         8
     111: invokestatic  #164                // Method getCurrentDirectory:(Ljava/io/File;)Ljava/io/File;
     114: invokeinterface #57,  2           // InterfaceMethod java/util/List.add:(Ljava/lang/Object;)Z
     119: pop
     120: iinc          7, 1
     123: goto          91
     126: aload_1
     127: invokestatic  #200                // Method createDiskChecker:(Lorg/apache/bookkeeper/conf/ServerConfiguration;)Lorg/apache/bookkeeper/util/DiskChecker;
     130: astore        5
     132: aload_0
     133: aload_1
     134: aload         5
     136: aload_2
     137: ldc           #178                // String ledger
     139: invokeinterface #179,  2          // InterfaceMethod org/apache/bookkeeper/stats/StatsLogger.scope:(Ljava/lang/String;)Lorg/apache/bookkeeper/stats/StatsLogger;
     144: invokestatic  #180                // Method createLedgerDirsManager:(Lorg/apache/bookkeeper/conf/ServerConfiguration;Lorg/apache/bookkeeper/util/DiskChecker;Lorg/apache/bookkeeper/stats/StatsLogger;)Lorg/apache/bookkeeper/bookie/LedgerDirsManager;
     147: putfield      #29                 // Field ledgerDirsManager:Lorg/apache/bookkeeper/bookie/LedgerDirsManager;
     150: aload_0
     151: aload_1
     152: aload         5
     154: aload_2
     155: ldc           #181                // String index
     157: invokeinterface #179,  2          // InterfaceMethod org/apache/bookkeeper/stats/StatsLogger.scope:(Ljava/lang/String;)Lorg/apache/bookkeeper/stats/StatsLogger;
     162: aload_0
     163: getfield      #29                 // Field ledgerDirsManager:Lorg/apache/bookkeeper/bookie/LedgerDirsManager;
     166: invokestatic  #182                // Method createIndexDirsManager:(Lorg/apache/bookkeeper/conf/ServerConfiguration;Lorg/apache/bookkeeper/util/DiskChecker;Lorg/apache/bookkeeper/stats/StatsLogger;Lorg/apache/bookkeeper/bookie/LedgerDirsManager;)Lorg/apache/bookkeeper/bookie/LedgerDirsManager;
     169: putfield      #32                 // Field indexDirsManager:Lorg/apache/bookkeeper/bookie/LedgerDirsManager;
     172: aload_0
     173: aload_1
     174: invokevirtual #201                // Method org/apache/bookkeeper/conf/ServerConfiguration.getJournalWriteData:()Z
     177: putfield      #202                // Field writeDataToJournal:Z
     180: aload_0
     181: aload_3
     182: putfield      #203                // Field allocator:Lio/netty/buffer/ByteBufAllocator;
     185: aload_0
     186: aload_0
     187: aload_1
     188: invokespecial #204                // Method instantiateMetadataDriver:(Lorg/apache/bookkeeper/conf/ServerConfiguration;)Lorg/apache/bookkeeper/meta/MetadataBookieDriver;
     191: putfield      #205                // Field metadataDriver:Lorg/apache/bookkeeper/meta/MetadataBookieDriver;
     194: aload_0
     195: aload_0
     196: getfield      #205                // Field metadataDriver:Lorg/apache/bookkeeper/meta/MetadataBookieDriver;
     199: invokespecial #206                // Method checkEnvironment:(Lorg/apache/bookkeeper/meta/MetadataBookieDriver;)V
     202: aload_0
     203: getfield      #205                // Field metadataDriver:Lorg/apache/bookkeeper/meta/MetadataBookieDriver;
     206: ifnull        258
     209: aload_0
     210: aload_0
     211: getfield      #205                // Field metadataDriver:Lorg/apache/bookkeeper/meta/MetadataBookieDriver;
     214: invokeinterface #207,  1          // InterfaceMethod org/apache/bookkeeper/meta/MetadataBookieDriver.getLedgerManagerFactory:()Lorg/apache/bookkeeper/meta/LedgerManagerFactory;
     219: putfield      #208                // Field ledgerManagerFactory:Lorg/apache/bookkeeper/meta/LedgerManagerFactory;
     222: getstatic     #3                  // Field LOG:Lorg/slf4j/Logger;
     225: ldc           #209                // String instantiate ledger manager {}
     227: aload_0
     228: getfield      #208                // Field ledgerManagerFactory:Lorg/apache/bookkeeper/meta/LedgerManagerFactory;
     231: invokevirtual #210                // Method java/lang/Object.getClass:()Ljava/lang/Class;
     234: invokevirtual #211                // Method java/lang/Class.getName:()Ljava/lang/String;
     237: invokeinterface #172,  3          // InterfaceMethod org/slf4j/Logger.info:(Ljava/lang/String;Ljava/lang/Object;)V
     242: aload_0
     243: aload_0
     244: getfield      #208                // Field ledgerManagerFactory:Lorg/apache/bookkeeper/meta/LedgerManagerFactory;
     247: invokeinterface #212,  1          // InterfaceMethod org/apache/bookkeeper/meta/LedgerManagerFactory.newLedgerManager:()Lorg/apache/bookkeeper/meta/LedgerManager;
     252: putfield      #213                // Field ledgerManager:Lorg/apache/bookkeeper/meta/LedgerManager;
     255: goto          268
     258: aload_0
     259: aconst_null
     260: putfield      #208                // Field ledgerManagerFactory:Lorg/apache/bookkeeper/meta/LedgerManagerFactory;
     263: aload_0
     264: aconst_null
     265: putfield      #213                // Field ledgerManager:Lorg/apache/bookkeeper/meta/LedgerManager;
     268: goto          285
     271: astore        6
     273: new           #215                // class org/apache/bookkeeper/bookie/BookieException$MetadataStoreException
     276: dup
     277: ldc           #216                // String Failed to initialize ledger manager
     279: aload         6
     281: invokespecial #217                // Method org/apache/bookkeeper/bookie/BookieException$MetadataStoreException."<init>":(Ljava/lang/String;Ljava/lang/Throwable;)V
     284: athrow
     285: aload_0
     286: aload_0
     287: invokevirtual #218                // Method initializeStateManager:()Lorg/apache/bookkeeper/bookie/StateManager;
     290: putfield      #219                // Field stateManager:Lorg/apache/bookkeeper/bookie/StateManager;
     293: aload_0
     294: getfield      #219                // Field stateManager:Lorg/apache/bookkeeper/bookie/StateManager;
     297: aload_0
     298: invokedynamic #220,  0            // InvokeDynamic #3:shutdown:(Lorg/apache/bookkeeper/bookie/Bookie;)Lorg/apache/bookkeeper/bookie/StateManager$ShutdownHandler;
     303: invokeinterface #221,  2          // InterfaceMethod org/apache/bookkeeper/bookie/StateManager.setShutdownHandler:(Lorg/apache/bookkeeper/bookie/StateManager$ShutdownHandler;)V
     308: new           #28                 // class java/util/ArrayList
     311: dup
     312: invokespecial #58                 // Method java/util/ArrayList."<init>":()V
     315: astore        6
     317: aload         6
     319: aload_0
     320: getfield      #29                 // Field ledgerDirsManager:Lorg/apache/bookkeeper/bookie/LedgerDirsManager;
     323: invokeinterface #57,  2           // InterfaceMethod java/util/List.add:(Ljava/lang/Object;)Z
     328: pop
     329: aload_0
     330: getfield      #32                 // Field indexDirsManager:Lorg/apache/bookkeeper/bookie/LedgerDirsManager;
     333: aload_0
     334: getfield      #29                 // Field ledgerDirsManager:Lorg/apache/bookkeeper/bookie/LedgerDirsManager;
     337: if_acmpeq     352
     340: aload         6
     342: aload_0
     343: getfield      #32                 // Field indexDirsManager:Lorg/apache/bookkeeper/bookie/LedgerDirsManager;
     346: invokeinterface #57,  2           // InterfaceMethod java/util/List.add:(Ljava/lang/Object;)Z
     351: pop
     352: aload_0
     353: new           #222                // class org/apache/bookkeeper/bookie/LedgerDirsMonitor
     356: dup
     357: aload_1
     358: aload         5
     360: aload         6
     362: invokespecial #223                // Method org/apache/bookkeeper/bookie/LedgerDirsMonitor."<init>":(Lorg/apache/bookkeeper/conf/ServerConfiguration;Lorg/apache/bookkeeper/util/DiskChecker;Ljava/util/List;)V
     365: putfield      #224                // Field dirsMonitor:Lorg/apache/bookkeeper/bookie/LedgerDirsMonitor;
     368: aload_0
     369: getfield      #224                // Field dirsMonitor:Lorg/apache/bookkeeper/bookie/LedgerDirsMonitor;
     372: invokevirtual #225                // Method org/apache/bookkeeper/bookie/LedgerDirsMonitor.init:()V
     375: goto          400
     378: astore        7
     380: aload_1
     381: invokevirtual #227                // Method org/apache/bookkeeper/conf/ServerConfiguration.isReadOnlyModeEnabled:()Z
     384: ifne          390
     387: aload         7
     389: athrow
     390: aload_0
     391: getfield      #219                // Field stateManager:Lorg/apache/bookkeeper/bookie/StateManager;
     394: invokeinterface #228,  1          // InterfaceMethod org/apache/bookkeeper/bookie/StateManager.transitionToReadOnlyMode:()Ljava/util/concurrent/Future;
     399: pop
     400: aload_0
     401: invokestatic  #86                 // Method com/google/common/collect/Lists.newArrayList:()Ljava/util/ArrayList;
     404: putfield      #229                // Field journals:Ljava/util/List;
     407: iconst_0
     408: istore        7
     410: iload         7
     412: aload_0
     413: getfield      #35                 // Field journalDirectories:Ljava/util/List;
     416: invokeinterface #31,  1           // InterfaceMethod java/util/List.size:()I
     421: if_icmpge     477
     424: aload_0
     425: getfield      #229                // Field journals:Ljava/util/List;
     428: new           #230                // class org/apache/bookkeeper/bookie/Journal
     431: dup
     432: iload         7
     434: aload_0
     435: getfield      #35                 // Field journalDirectories:Ljava/util/List;
     438: iload         7
     440: invokeinterface #231,  2          // InterfaceMethod java/util/List.get:(I)Ljava/lang/Object;
     445: checkcast     #6                  // class java/io/File
     448: aload_1
     449: aload_0
     450: getfield      #29                 // Field ledgerDirsManager:Lorg/apache/bookkeeper/bookie/LedgerDirsManager;
     453: aload_2
     454: ldc           #232                // String journal
     456: invokeinterface #179,  2          // InterfaceMethod org/apache/bookkeeper/stats/StatsLogger.scope:(Ljava/lang/String;)Lorg/apache/bookkeeper/stats/StatsLogger;
     461: aload_3
     462: invokespecial #233                // Method org/apache/bookkeeper/bookie/Journal."<init>":(ILjava/io/File;Lorg/apache/bookkeeper/conf/ServerConfiguration;Lorg/apache/bookkeeper/bookie/LedgerDirsManager;Lorg/apache/bookkeeper/stats/StatsLogger;Lio/netty/buffer/ByteBufAllocator;)V
     465: invokeinterface #57,  2           // InterfaceMethod java/util/List.add:(Ljava/lang/Object;)Z
     470: pop
     471: iinc          7, 1
     474: goto          410
     477: aload_0
     478: aload_1
     479: invokevirtual #234                // Method org/apache/bookkeeper/conf/ServerConfiguration.isEntryLogPerLedgerEnabled:()Z
     482: putfield      #235                // Field entryLogPerLedgerEnabled:Z
     485: new           #236                // class org/apache/bookkeeper/bookie/CheckpointSourceList
     488: dup
     489: aload_0
     490: getfield      #229                // Field journals:Ljava/util/List;
     493: invokespecial #237                // Method org/apache/bookkeeper/bookie/CheckpointSourceList."<init>":(Ljava/util/List;)V
     496: astore        7
     498: aload_0
     499: aload_1
     500: invokestatic  #183                // Method buildLedgerStorage:(Lorg/apache/bookkeeper/conf/ServerConfiguration;)Lorg/apache/bookkeeper/bookie/LedgerStorage;
     503: putfield      #238                // Field ledgerStorage:Lorg/apache/bookkeeper/bookie/LedgerStorage;
     506: aload_0
     507: getfield      #238                // Field ledgerStorage:Lorg/apache/bookkeeper/bookie/LedgerStorage;
     510: instanceof    #239                // class org/apache/bookkeeper/bookie/storage/ldb/DbLedgerStorage
     513: istore        8
     515: aload_0
     516: getfield      #235                // Field entryLogPerLedgerEnabled:Z
     519: ifne          527
     522: iload         8
     524: ifeq          554
     527: aload_0
     528: new           #240                // class org/apache/bookkeeper/bookie/Bookie$3
     531: dup
     532: aload_0
     533: aload_1
     534: aload_0
     535: invokespecial #241                // Method getLedgerDirsListener:()Lorg/apache/bookkeeper/bookie/LedgerDirsManager$LedgerDirsListener;
     538: aload_0
     539: getfield      #238                // Field ledgerStorage:Lorg/apache/bookkeeper/bookie/LedgerStorage;
     542: aload         7
     544: aload_1
     545: invokespecial #242                // Method org/apache/bookkeeper/bookie/Bookie$3."<init>":(Lorg/apache/bookkeeper/bookie/Bookie;Lorg/apache/bookkeeper/conf/ServerConfiguration;Lorg/apache/bookkeeper/bookie/LedgerDirsManager$LedgerDirsListener;Lorg/apache/bookkeeper/bookie/LedgerStorage;Lorg/apache/bookkeeper/bookie/CheckpointSource;Lorg/apache/bookkeeper/conf/ServerConfiguration;)V
     548: putfield      #243                // Field syncThread:Lorg/apache/bookkeeper/bookie/SyncThread;
     551: goto          576
     554: aload_0
     555: new           #244                // class org/apache/bookkeeper/bookie/SyncThread
     558: dup
     559: aload_1
     560: aload_0
     561: invokespecial #241                // Method getLedgerDirsListener:()Lorg/apache/bookkeeper/bookie/LedgerDirsManager$LedgerDirsListener;
     564: aload_0
     565: getfield      #238                // Field ledgerStorage:Lorg/apache/bookkeeper/bookie/LedgerStorage;
     568: aload         7
     570: invokespecial #245                // Method org/apache/bookkeeper/bookie/SyncThread."<init>":(Lorg/apache/bookkeeper/conf/ServerConfiguration;Lorg/apache/bookkeeper/bookie/LedgerDirsManager$LedgerDirsListener;Lorg/apache/bookkeeper/bookie/LedgerStorage;Lorg/apache/bookkeeper/bookie/CheckpointSource;)V
     573: putfield      #243                // Field syncThread:Lorg/apache/bookkeeper/bookie/SyncThread;
     576: aload_0
     577: getfield      #238                // Field ledgerStorage:Lorg/apache/bookkeeper/bookie/LedgerStorage;
     580: aload_1
     581: aload_0
     582: getfield      #213                // Field ledgerManager:Lorg/apache/bookkeeper/meta/LedgerManager;
     585: aload_0
     586: getfield      #29                 // Field ledgerDirsManager:Lorg/apache/bookkeeper/bookie/LedgerDirsManager;
     589: aload_0
     590: getfield      #32                 // Field indexDirsManager:Lorg/apache/bookkeeper/bookie/LedgerDirsManager;
     593: aload_0
     594: getfield      #219                // Field stateManager:Lorg/apache/bookkeeper/bookie/StateManager;
     597: aload         7
     599: aload_0
     600: getfield      #243                // Field syncThread:Lorg/apache/bookkeeper/bookie/SyncThread;
     603: aload_2
     604: aload_3
     605: invokeinterface #188,  10         // InterfaceMethod org/apache/bookkeeper/bookie/LedgerStorage.initialize:(Lorg/apache/bookkeeper/conf/ServerConfiguration;Lorg/apache/bookkeeper/meta/LedgerManager;Lorg/apache/bookkeeper/bookie/LedgerDirsManager;Lorg/apache/bookkeeper/bookie/LedgerDirsManager;Lorg/apache/bookkeeper/bookie/StateManager;Lorg/apache/bookkeeper/bookie/CheckpointSource;Lorg/apache/bookkeeper/bookie/Checkpointer;Lorg/apache/bookkeeper/stats/StatsLogger;Lio/netty/buffer/ByteBufAllocator;)V
     610: aload_0
     611: new           #246                // class org/apache/bookkeeper/bookie/HandleFactoryImpl
     614: dup
     615: aload_0
     616: getfield      #238                // Field ledgerStorage:Lorg/apache/bookkeeper/bookie/LedgerStorage;
     619: invokespecial #247                // Method org/apache/bookkeeper/bookie/HandleFactoryImpl."<init>":(Lorg/apache/bookkeeper/bookie/LedgerStorage;)V
     622: putfield      #248                // Field handles:Lorg/apache/bookkeeper/bookie/HandleFactory;
     625: aload_0
     626: new           #249                // class org/apache/bookkeeper/bookie/stats/BookieStats
     629: dup
     630: aload_2
     631: invokespecial #250                // Method org/apache/bookkeeper/bookie/stats/BookieStats."<init>":(Lorg/apache/bookkeeper/stats/StatsLogger;)V
     634: putfield      #251                // Field bookieStats:Lorg/apache/bookkeeper/bookie/stats/BookieStats;
     637: aload_0
     638: new           #252                // class org/apache/bookkeeper/bookie/Bookie$4
     641: dup
     642: aload_0
     643: aload_1
     644: invokespecial #253                // Method org/apache/bookkeeper/bookie/Bookie$4."<init>":(Lorg/apache/bookkeeper/bookie/Bookie;Lorg/apache/bookkeeper/conf/ServerConfiguration;)V
     647: putfield      #254                // Field journalMemoryMaxStats:Lorg/apache/bookkeeper/stats/Gauge;
     650: aload_2
     651: ldc           #232                // String journal
     653: invokeinterface #179,  2          // InterfaceMethod org/apache/bookkeeper/stats/StatsLogger.scope:(Ljava/lang/String;)Lorg/apache/bookkeeper/stats/StatsLogger;
     658: ldc           #255                // String JOURNAL_MEMORY_MAX
     660: aload_0
     661: getfield      #254                // Field journalMemoryMaxStats:Lorg/apache/bookkeeper/stats/Gauge;
     664: invokeinterface #256,  3          // InterfaceMethod org/apache/bookkeeper/stats/StatsLogger.registerGauge:(Ljava/lang/String;Lorg/apache/bookkeeper/stats/Gauge;)V
     669: aload_0
     670: new           #257                // class org/apache/bookkeeper/bookie/Bookie$5
     673: dup
     674: aload_0
     675: invokespecial #258                // Method org/apache/bookkeeper/bookie/Bookie$5."<init>":(Lorg/apache/bookkeeper/bookie/Bookie;)V
     678: putfield      #259                // Field journalMemoryUsedStats:Lorg/apache/bookkeeper/stats/Gauge;
     681: aload_2
     682: ldc           #232                // String journal
     684: invokeinterface #179,  2          // InterfaceMethod org/apache/bookkeeper/stats/StatsLogger.scope:(Ljava/lang/String;)Lorg/apache/bookkeeper/stats/StatsLogger;
     689: ldc_w         #260                // String JOURNAL_MEMORY_USED
     692: aload_0
     693: getfield      #259                // Field journalMemoryUsedStats:Lorg/apache/bookkeeper/stats/Gauge;
     696: invokeinterface #256,  3          // InterfaceMethod org/apache/bookkeeper/stats/StatsLogger.registerGauge:(Ljava/lang/String;Lorg/apache/bookkeeper/stats/Gauge;)V
     701: return
    Exception table:
       from    to  target type
         202   268   271   Class org/apache/bookkeeper/meta/exceptions/MetadataException
         368   375   378   Class org/apache/bookkeeper/bookie/LedgerDirsManager$NoWritableLedgerDirException

  org.apache.bookkeeper.bookie.StateManager initializeStateManager() throws java.io.IOException;
    Code:
       0: new           #261                // class org/apache/bookkeeper/bookie/BookieStateManager
       3: dup
       4: aload_0
       5: getfield      #40                 // Field conf:Lorg/apache/bookkeeper/conf/ServerConfiguration;
       8: aload_0
       9: getfield      #198                // Field statsLogger:Lorg/apache/bookkeeper/stats/StatsLogger;
      12: aload_0
      13: getfield      #205                // Field metadataDriver:Lorg/apache/bookkeeper/meta/MetadataBookieDriver;
      16: aload_0
      17: getfield      #29                 // Field ledgerDirsManager:Lorg/apache/bookkeeper/bookie/LedgerDirsManager;
      20: aload_0
      21: getfield      #197                // Field bookieServiceInfoProvider:Ljava/util/function/Supplier;
      24: invokespecial #262                // Method org/apache/bookkeeper/bookie/BookieStateManager."<init>":(Lorg/apache/bookkeeper/conf/ServerConfiguration;Lorg/apache/bookkeeper/stats/StatsLogger;Lorg/apache/bookkeeper/meta/MetadataBookieDriver;Lorg/apache/bookkeeper/bookie/LedgerDirsManager;Ljava/util/function/Supplier;)V
      27: areturn

  void readJournal() throws java.io.IOException, org.apache.bookkeeper.bookie.BookieException;
    Code:
       0: invokestatic  #263                // Method java/lang/System.currentTimeMillis:()J
       3: lstore_1
       4: new           #264                // class org/apache/bookkeeper/bookie/Bookie$6
       7: dup
       8: aload_0
       9: invokespecial #265                // Method org/apache/bookkeeper/bookie/Bookie$6."<init>":(Lorg/apache/bookkeeper/bookie/Bookie;)V
      12: astore_3
      13: aload_0
      14: getfield      #229                // Field journals:Ljava/util/List;
      17: invokeinterface #36,  1           // InterfaceMethod java/util/List.iterator:()Ljava/util/Iterator;
      22: astore        4
      24: aload         4
      26: invokeinterface #37,  1           // InterfaceMethod java/util/Iterator.hasNext:()Z
      31: ifeq          56
      34: aload         4
      36: invokeinterface #38,  1           // InterfaceMethod java/util/Iterator.next:()Ljava/lang/Object;
      41: checkcast     #230                // class org/apache/bookkeeper/bookie/Journal
      44: astore        5
      46: aload_0
      47: aload         5
      49: aload_3
      50: invokespecial #266                // Method replay:(Lorg/apache/bookkeeper/bookie/Journal;Lorg/apache/bookkeeper/bookie/Journal$JournalScanner;)V
      53: goto          24
      56: invokestatic  #263                // Method java/lang/System.currentTimeMillis:()J
      59: lload_1
      60: lsub
      61: lstore        4
      63: getstatic     #3                  // Field LOG:Lorg/slf4j/Logger;
      66: ldc_w         #267                // String Finished replaying journal in {} ms.
      69: lload         4
      71: invokestatic  #268                // Method java/lang/Long.valueOf:(J)Ljava/lang/Long;
      74: invokeinterface #172,  3          // InterfaceMethod org/slf4j/Logger.info:(Ljava/lang/String;Ljava/lang/Object;)V
      79: return

  private void replay(org.apache.bookkeeper.bookie.Journal, org.apache.bookkeeper.bookie.Journal$JournalScanner) throws java.io.IOException;
    Code:
       0: aload_1
       1: invokevirtual #269                // Method org/apache/bookkeeper/bookie/Journal.getLastLogMark:()Lorg/apache/bookkeeper/bookie/Journal$LastLogMark;
       4: invokevirtual #270                // Method org/apache/bookkeeper/bookie/Journal$LastLogMark.getCurMark:()Lorg/apache/bookkeeper/bookie/LogMark;
       7: astore_3
       8: aload_1
       9: invokevirtual #271                // Method org/apache/bookkeeper/bookie/Journal.getJournalDirectory:()Ljava/io/File;
      12: aload_3
      13: invokedynamic #272,  0            // InvokeDynamic #4:accept:(Lorg/apache/bookkeeper/bookie/LogMark;)Lorg/apache/bookkeeper/bookie/Journal$JournalIdFilter;
      18: invokestatic  #273                // Method org/apache/bookkeeper/bookie/Journal.listJournalIds:(Ljava/io/File;Lorg/apache/bookkeeper/bookie/Journal$JournalIdFilter;)Ljava/util/List;
      21: astore        4
      23: aload_3
      24: invokevirtual #274                // Method org/apache/bookkeeper/bookie/LogMark.getLogFileId:()J
      27: lconst_0
      28: lcmp
      29: ifle          101
      32: aload         4
      34: invokeinterface #31,  1           // InterfaceMethod java/util/List.size:()I
      39: ifeq          64
      42: aload         4
      44: iconst_0
      45: invokeinterface #231,  2          // InterfaceMethod java/util/List.get:(I)Ljava/lang/Object;
      50: checkcast     #275                // class java/lang/Long
      53: invokevirtual #276                // Method java/lang/Long.longValue:()J
      56: aload_3
      57: invokevirtual #274                // Method org/apache/bookkeeper/bookie/LogMark.getLogFileId:()J
      60: lcmp
      61: ifeq          101
      64: new           #19                 // class java/io/IOException
      67: dup
      68: new           #22                 // class java/lang/StringBuilder
      71: dup
      72: invokespecial #23                 // Method java/lang/StringBuilder."<init>":()V
      75: ldc_w         #277                // String Recovery log
      78: invokevirtual #25                 // Method java/lang/StringBuilder.append:(Ljava/lang/String;)Ljava/lang/StringBuilder;
      81: aload_3
      82: invokevirtual #274                // Method org/apache/bookkeeper/bookie/LogMark.getLogFileId:()J
      85: invokevirtual #278                // Method java/lang/StringBuilder.append:(J)Ljava/lang/StringBuilder;
      88: ldc_w         #279                // String  is missing
      91: invokevirtual #25                 // Method java/lang/StringBuilder.append:(Ljava/lang/String;)Ljava/lang/StringBuilder;
      94: invokevirtual #27                 // Method java/lang/StringBuilder.toString:()Ljava/lang/String;
      97: invokespecial #20                 // Method java/io/IOException."<init>":(Ljava/lang/String;)V
     100: athrow
     101: aload         4
     103: invokeinterface #36,  1           // InterfaceMethod java/util/List.iterator:()Ljava/util/Iterator;
     108: astore        5
     110: aload         5
     112: invokeinterface #37,  1           // InterfaceMethod java/util/Iterator.hasNext:()Z
     117: ifeq          197
     120: aload         5
     122: invokeinterface #38,  1           // InterfaceMethod java/util/Iterator.next:()Ljava/lang/Object;
     127: checkcast     #275                // class java/lang/Long
     130: astore        6
     132: lconst_0
     133: lstore        7
     135: aload         6
     137: invokevirtual #276                // Method java/lang/Long.longValue:()J
     140: aload_3
     141: invokevirtual #274                // Method org/apache/bookkeeper/bookie/LogMark.getLogFileId:()J
     144: lcmp
     145: ifne          154
     148: aload_3
     149: invokevirtual #280                // Method org/apache/bookkeeper/bookie/LogMark.getLogFileOffset:()J
     152: lstore        7
     154: getstatic     #3                  // Field LOG:Lorg/slf4j/Logger;
     157: ldc_w         #281                // String Replaying journal {} from position {}
     160: aload         6
     162: lload         7
     164: invokestatic  #268                // Method java/lang/Long.valueOf:(J)Ljava/lang/Long;
     167: invokeinterface #91,  4           // InterfaceMethod org/slf4j/Logger.info:(Ljava/lang/String;Ljava/lang/Object;Ljava/lang/Object;)V
     172: aload_1
     173: aload         6
     175: invokevirtual #276                // Method java/lang/Long.longValue:()J
     178: lload         7
     180: aload_2
     181: invokevirtual #282                // Method org/apache/bookkeeper/bookie/Journal.scanJournal:(JJLorg/apache/bookkeeper/bookie/Journal$JournalScanner;)J
     184: lstore        9
     186: aload_1
     187: aload         6
     189: lload         9
     191: invokevirtual #283                // Method org/apache/bookkeeper/bookie/Journal.setLastLogMark:(Ljava/lang/Long;J)V
     194: goto          110
     197: return

  public synchronized void start();
    Code:
       0: aload_0
       1: iconst_1
       2: invokevirtual #284                // Method setDaemon:(Z)V
       5: getstatic     #3                  // Field LOG:Lorg/slf4j/Logger;
       8: invokeinterface #285,  1          // InterfaceMethod org/slf4j/Logger.isDebugEnabled:()Z
      13: ifeq          57
      16: getstatic     #3                  // Field LOG:Lorg/slf4j/Logger;
      19: ldc_w         #286                // String I\'m starting a bookie with journal directories {}
      22: aload_0
      23: getfield      #35                 // Field journalDirectories:Ljava/util/List;
      26: invokeinterface #122,  1          // InterfaceMethod java/util/List.stream:()Ljava/util/stream/Stream;
      31: invokedynamic #287,  0            // InvokeDynamic #5:apply:()Ljava/util/function/Function;
      36: invokeinterface #126,  2          // InterfaceMethod java/util/stream/Stream.map:(Ljava/util/function/Function;)Ljava/util/stream/Stream;
      41: ldc_w         #288                // String ,
      44: invokestatic  #289                // Method java/util/stream/Collectors.joining:(Ljava/lang/CharSequence;)Ljava/util/stream/Collector;
      47: invokeinterface #128,  2          // InterfaceMethod java/util/stream/Stream.collect:(Ljava/util/stream/Collector;)Ljava/lang/Object;
      52: invokeinterface #290,  3          // InterfaceMethod org/slf4j/Logger.debug:(Ljava/lang/String;Ljava/lang/Object;)V
      57: aload_0
      58: getfield      #224                // Field dirsMonitor:Lorg/apache/bookkeeper/bookie/LedgerDirsMonitor;
      61: invokevirtual #291                // Method org/apache/bookkeeper/bookie/LedgerDirsMonitor.start:()V
      64: aload_0
      65: invokevirtual #292                // Method readJournal:()V
      68: goto          91
      71: astore_1
      72: getstatic     #3                  // Field LOG:Lorg/slf4j/Logger;
      75: ldc_w         #294                // String Exception while replaying journals, shutting down
      78: aload_1
      79: invokeinterface #118,  3          // InterfaceMethod org/slf4j/Logger.error:(Ljava/lang/String;Ljava/lang/Throwable;)V
      84: aload_0
      85: iconst_5
      86: invokevirtual #295                // Method shutdown:(I)I
      89: pop
      90: return
      91: aload_0
      92: getfield      #243                // Field syncThread:Lorg/apache/bookkeeper/bookie/SyncThread;
      95: invokevirtual #296                // Method org/apache/bookkeeper/bookie/SyncThread.requestFlush:()Ljava/util/concurrent/Future;
      98: invokeinterface #297,  1          // InterfaceMethod java/util/concurrent/Future.get:()Ljava/lang/Object;
     103: pop
     104: goto          148
     107: astore_1
     108: getstatic     #3                  // Field LOG:Lorg/slf4j/Logger;
     111: ldc_w         #299                // String Interrupting the fully flush after replaying journals :
     114: aload_1
     115: invokeinterface #300,  3          // InterfaceMethod org/slf4j/Logger.warn:(Ljava/lang/String;Ljava/lang/Throwable;)V
     120: invokestatic  #301                // Method java/lang/Thread.currentThread:()Ljava/lang/Thread;
     123: invokevirtual #302                // Method java/lang/Thread.interrupt:()V
     126: goto          148
     129: astore_1
     130: getstatic     #3                  // Field LOG:Lorg/slf4j/Logger;
     133: ldc_w         #304                // String Error on executing a fully flush after replaying journals.
     136: invokeinterface #18,  2           // InterfaceMethod org/slf4j/Logger.error:(Ljava/lang/String;)V
     141: aload_0
     142: iconst_5
     143: invokevirtual #295                // Method shutdown:(I)I
     146: pop
     147: return
     148: aload_0
     149: getfield      #40                 // Field conf:Lorg/apache/bookkeeper/conf/ServerConfiguration;
     152: invokevirtual #305                // Method org/apache/bookkeeper/conf/ServerConfiguration.isLocalConsistencyCheckOnStartup:()Z
     155: ifeq          309
     158: getstatic     #3                  // Field LOG:Lorg/slf4j/Logger;
     161: ldc_w         #306                // String Running local consistency check on startup prior to accepting IO.
     164: invokeinterface #307,  2          // InterfaceMethod org/slf4j/Logger.info:(Ljava/lang/String;)V
     169: aconst_null
     170: astore_1
     171: aload_0
     172: getfield      #238                // Field ledgerStorage:Lorg/apache/bookkeeper/bookie/LedgerStorage;
     175: invokestatic  #308                // Method java/util/Optional.empty:()Ljava/util/Optional;
     178: invokeinterface #309,  2          // InterfaceMethod org/apache/bookkeeper/bookie/LedgerStorage.localConsistencyCheck:(Ljava/util/Optional;)Ljava/util/List;
     183: astore_1
     184: goto          207
     187: astore_2
     188: getstatic     #3                  // Field LOG:Lorg/slf4j/Logger;
     191: ldc_w         #310                // String Got a fatal exception while checking store
     194: aload_2
     195: invokeinterface #118,  3          // InterfaceMethod org/slf4j/Logger.error:(Ljava/lang/String;Ljava/lang/Throwable;)V
     200: aload_0
     201: iconst_5
     202: invokevirtual #295                // Method shutdown:(I)I
     205: pop
     206: return
     207: aload_1
     208: ifnull        309
     211: aload_1
     212: invokeinterface #31,  1           // InterfaceMethod java/util/List.size:()I
     217: ifle          309
     220: getstatic     #3                  // Field LOG:Lorg/slf4j/Logger;
     223: ldc_w         #311                // String Bookie failed local consistency check:
     226: invokeinterface #18,  2           // InterfaceMethod org/slf4j/Logger.error:(Ljava/lang/String;)V
     231: aload_1
     232: invokeinterface #36,  1           // InterfaceMethod java/util/List.iterator:()Ljava/util/Iterator;
     237: astore_2
     238: aload_2
     239: invokeinterface #37,  1           // InterfaceMethod java/util/Iterator.hasNext:()Z
     244: ifeq          302
     247: aload_2
     248: invokeinterface #38,  1           // InterfaceMethod java/util/Iterator.next:()Ljava/lang/Object;
     253: checkcast     #312                // class org/apache/bookkeeper/bookie/LedgerStorage$DetectedInconsistency
     256: astore_3
     257: getstatic     #3                  // Field LOG:Lorg/slf4j/Logger;
     260: ldc_w         #313                // String Ledger {}, entry {}:
     263: iconst_3
     264: anewarray     #314                // class java/lang/Object
     267: dup
     268: iconst_0
     269: aload_3
     270: invokevirtual #315                // Method org/apache/bookkeeper/bookie/LedgerStorage$DetectedInconsistency.getLedgerId:()J
     273: invokestatic  #268                // Method java/lang/Long.valueOf:(J)Ljava/lang/Long;
     276: aastore
     277: dup
     278: iconst_1
     279: aload_3
     280: invokevirtual #316                // Method org/apache/bookkeeper/bookie/LedgerStorage$DetectedInconsistency.getEntryId:()J
     283: invokestatic  #268                // Method java/lang/Long.valueOf:(J)Ljava/lang/Long;
     286: aastore
     287: dup
     288: iconst_2
     289: aload_3
     290: invokevirtual #317                // Method org/apache/bookkeeper/bookie/LedgerStorage$DetectedInconsistency.getException:()Ljava/lang/Exception;
     293: aastore
     294: invokeinterface #318,  3          // InterfaceMethod org/slf4j/Logger.error:(Ljava/lang/String;[Ljava/lang/Object;)V
     299: goto          238
     302: aload_0
     303: iconst_5
     304: invokevirtual #295                // Method shutdown:(I)I
     307: pop
     308: return
     309: getstatic     #3                  // Field LOG:Lorg/slf4j/Logger;
     312: ldc_w         #319                // String Finished reading journal, starting bookie
     315: invokeinterface #307,  2          // InterfaceMethod org/slf4j/Logger.info:(Ljava/lang/String;)V
     320: aload_0
     321: getfield      #243                // Field syncThread:Lorg/apache/bookkeeper/bookie/SyncThread;
     324: invokevirtual #320                // Method org/apache/bookkeeper/bookie/SyncThread.start:()V
     327: aload_0
     328: invokespecial #321                // Method org/apache/bookkeeper/bookie/BookieCriticalThread.start:()V
     331: aload_0
     332: getfield      #29                 // Field ledgerDirsManager:Lorg/apache/bookkeeper/bookie/LedgerDirsManager;
     335: aload_0
     336: invokespecial #241                // Method getLedgerDirsListener:()Lorg/apache/bookkeeper/bookie/LedgerDirsManager$LedgerDirsListener;
     339: invokevirtual #322                // Method org/apache/bookkeeper/bookie/LedgerDirsManager.addLedgerDirsListener:(Lorg/apache/bookkeeper/bookie/LedgerDirsManager$LedgerDirsListener;)V
     342: aload_0
     343: getfield      #32                 // Field indexDirsManager:Lorg/apache/bookkeeper/bookie/LedgerDirsManager;
     346: aload_0
     347: getfield      #29                 // Field ledgerDirsManager:Lorg/apache/bookkeeper/bookie/LedgerDirsManager;
     350: if_acmpeq     364
     353: aload_0
     354: getfield      #32                 // Field indexDirsManager:Lorg/apache/bookkeeper/bookie/LedgerDirsManager;
     357: aload_0
     358: invokespecial #241                // Method getLedgerDirsListener:()Lorg/apache/bookkeeper/bookie/LedgerDirsManager$LedgerDirsListener;
     361: invokevirtual #322                // Method org/apache/bookkeeper/bookie/LedgerDirsManager.addLedgerDirsListener:(Lorg/apache/bookkeeper/bookie/LedgerDirsManager$LedgerDirsListener;)V
     364: aload_0
     365: getfield      #238                // Field ledgerStorage:Lorg/apache/bookkeeper/bookie/LedgerStorage;
     368: invokeinterface #323,  1          // InterfaceMethod org/apache/bookkeeper/bookie/LedgerStorage.start:()V
     373: aload_0
     374: getfield      #219                // Field stateManager:Lorg/apache/bookkeeper/bookie/StateManager;
     377: invokeinterface #324,  1          // InterfaceMethod org/apache/bookkeeper/bookie/StateManager.initState:()V
     382: aload_0
     383: getfield      #219                // Field stateManager:Lorg/apache/bookkeeper/bookie/StateManager;
     386: iconst_1
     387: invokeinterface #325,  2          // InterfaceMethod org/apache/bookkeeper/bookie/StateManager.registerBookie:(Z)Ljava/util/concurrent/Future;
     392: invokeinterface #297,  1          // InterfaceMethod java/util/concurrent/Future.get:()Ljava/lang/Object;
     397: pop
     398: goto          420
     401: astore_1
     402: getstatic     #3                  // Field LOG:Lorg/slf4j/Logger;
     405: ldc_w         #327                // String Couldn\'t register bookie with zookeeper, shutting down :
     408: aload_1
     409: invokeinterface #118,  3          // InterfaceMethod org/slf4j/Logger.error:(Ljava/lang/String;Ljava/lang/Throwable;)V
     414: aload_0
     415: iconst_4
     416: invokevirtual #295                // Method shutdown:(I)I
     419: pop
     420: return
    Exception table:
       from    to  target type
          64    68    71   Class java/io/IOException
          64    68    71   Class org/apache/bookkeeper/bookie/BookieException
          91   104   107   Class java/lang/InterruptedException
          91   104   129   Class java/util/concurrent/ExecutionException
         171   184   187   Class java/io/IOException
         382   398   401   Class java/lang/Exception

  private org.apache.bookkeeper.bookie.LedgerDirsManager$LedgerDirsListener getLedgerDirsListener();
    Code:
       0: new           #328                // class org/apache/bookkeeper/bookie/Bookie$7
       3: dup
       4: aload_0
       5: invokespecial #329                // Method org/apache/bookkeeper/bookie/Bookie$7."<init>":(Lorg/apache/bookkeeper/bookie/Bookie;)V
       8: areturn

  private org.apache.bookkeeper.meta.MetadataBookieDriver instantiateMetadataDriver(org.apache.bookkeeper.conf.ServerConfiguration) throws org.apache.bookkeeper.bookie.BookieException;
    Code:
       0: aload_1
       1: invokevirtual #330                // Method org/apache/bookkeeper/conf/ServerConfiguration.getMetadataServiceUri:()Ljava/lang/String;
       4: astore_2
       5: aconst_null
       6: aload_2
       7: if_acmpne     12
      10: aconst_null
      11: areturn
      12: aload_2
      13: invokestatic  #331                // Method java/net/URI.create:(Ljava/lang/String;)Ljava/net/URI;
      16: invokestatic  #332                // Method org/apache/bookkeeper/meta/MetadataDrivers.getBookieDriver:(Ljava/net/URI;)Lorg/apache/bookkeeper/meta/MetadataBookieDriver;
      19: astore_3
      20: aload_3
      21: aload_1
      22: aload_0
      23: invokedynamic #333,  0            // InvokeDynamic #6:onRegistrationExpired:(Lorg/apache/bookkeeper/bookie/Bookie;)Lorg/apache/bookkeeper/discover/RegistrationManager$RegistrationListener;
      28: aload_0
      29: getfield      #198                // Field statsLogger:Lorg/apache/bookkeeper/stats/StatsLogger;
      32: invokeinterface #334,  4          // InterfaceMethod org/apache/bookkeeper/meta/MetadataBookieDriver.initialize:(Lorg/apache/bookkeeper/conf/ServerConfiguration;Lorg/apache/bookkeeper/discover/RegistrationManager$RegistrationListener;Lorg/apache/bookkeeper/stats/StatsLogger;)Lorg/apache/bookkeeper/meta/MetadataBookieDriver;
      37: pop
      38: aload_3
      39: areturn
      40: astore_2
      41: new           #215                // class org/apache/bookkeeper/bookie/BookieException$MetadataStoreException
      44: dup
      45: ldc_w         #335                // String Failed to initialize metadata bookie driver
      48: aload_2
      49: invokespecial #217                // Method org/apache/bookkeeper/bookie/BookieException$MetadataStoreException."<init>":(Ljava/lang/String;Ljava/lang/Throwable;)V
      52: athrow
      53: astore_2
      54: new           #337                // class org/apache/bookkeeper/bookie/BookieException$BookieIllegalOpException
      57: dup
      58: aload_2
      59: invokespecial #338                // Method org/apache/bookkeeper/bookie/BookieException$BookieIllegalOpException."<init>":(Ljava/lang/Throwable;)V
      62: athrow
    Exception table:
       from    to  target type
           0    11    40   Class org/apache/bookkeeper/meta/exceptions/MetadataException
          12    39    40   Class org/apache/bookkeeper/meta/exceptions/MetadataException
           0    11    53   Class org/apache/commons/configuration/ConfigurationException
          12    39    53   Class org/apache/commons/configuration/ConfigurationException

  public boolean isReadOnly();
    Code:
       0: aload_0
       1: getfield      #219                // Field stateManager:Lorg/apache/bookkeeper/bookie/StateManager;
       4: invokeinterface #339,  1          // InterfaceMethod org/apache/bookkeeper/bookie/StateManager.isReadOnly:()Z
       9: ireturn

  public boolean isAvailableForHighPriorityWrites();
    Code:
       0: aload_0
       1: getfield      #219                // Field stateManager:Lorg/apache/bookkeeper/bookie/StateManager;
       4: invokeinterface #340,  1          // InterfaceMethod org/apache/bookkeeper/bookie/StateManager.isAvailableForHighPriorityWrites:()Z
       9: ireturn

  public boolean isRunning();
    Code:
       0: aload_0
       1: getfield      #219                // Field stateManager:Lorg/apache/bookkeeper/bookie/StateManager;
       4: invokeinterface #341,  1          // InterfaceMethod org/apache/bookkeeper/bookie/StateManager.isRunning:()Z
       9: ireturn

  public void run();
    Code:
       0: aload_0
       1: getfield      #229                // Field journals:Ljava/util/List;
       4: invokeinterface #36,  1           // InterfaceMethod java/util/List.iterator:()Ljava/util/Iterator;
       9: astore_1
      10: aload_1
      11: invokeinterface #37,  1           // InterfaceMethod java/util/Iterator.hasNext:()Z
      16: ifeq          36
      19: aload_1
      20: invokeinterface #38,  1           // InterfaceMethod java/util/Iterator.next:()Ljava/lang/Object;
      25: checkcast     #230                // class org/apache/bookkeeper/bookie/Journal
      28: astore_2
      29: aload_2
      30: invokevirtual #342                // Method org/apache/bookkeeper/bookie/Journal.start:()V
      33: goto          10
      36: aload_0
      37: getfield      #229                // Field journals:Ljava/util/List;
      40: invokeinterface #36,  1           // InterfaceMethod java/util/List.iterator:()Ljava/util/Iterator;
      45: astore_1
      46: aload_1
      47: invokeinterface #37,  1           // InterfaceMethod java/util/Iterator.hasNext:()Z
      52: ifeq          72
      55: aload_1
      56: invokeinterface #38,  1           // InterfaceMethod java/util/Iterator.next:()Ljava/lang/Object;
      61: checkcast     #230                // class org/apache/bookkeeper/bookie/Journal
      64: astore_2
      65: aload_2
      66: invokevirtual #343                // Method org/apache/bookkeeper/bookie/Journal.joinThread:()V
      69: goto          46
      72: getstatic     #3                  // Field LOG:Lorg/slf4j/Logger;
      75: ldc_w         #344                // String Journal thread(s) quit.
      78: invokeinterface #307,  2          // InterfaceMethod org/slf4j/Logger.info:(Ljava/lang/String;)V
      83: goto          105
      86: astore_1
      87: invokestatic  #301                // Method java/lang/Thread.currentThread:()Ljava/lang/Thread;
      90: invokevirtual #302                // Method java/lang/Thread.interrupt:()V
      93: getstatic     #3                  // Field LOG:Lorg/slf4j/Logger;
      96: ldc_w         #345                // String Interrupted on running journal thread :
      99: aload_1
     100: invokeinterface #300,  3          // InterfaceMethod org/slf4j/Logger.warn:(Ljava/lang/String;Ljava/lang/Throwable;)V
     105: aload_0
     106: getfield      #219                // Field stateManager:Lorg/apache/bookkeeper/bookie/StateManager;
     109: invokeinterface #346,  1          // InterfaceMethod org/apache/bookkeeper/bookie/StateManager.isShuttingDown:()Z
     114: ifne          133
     117: getstatic     #3                  // Field LOG:Lorg/slf4j/Logger;
     120: ldc_w         #347                // String Journal manager quits unexpectedly.
     123: invokeinterface #18,  2           // InterfaceMethod org/slf4j/Logger.error:(Ljava/lang/String;)V
     128: aload_0
     129: iconst_5
     130: invokevirtual #348                // Method triggerBookieShutdown:(I)V
     133: return
    Exception table:
       from    to  target type
           0    83    86   Class java/lang/InterruptedException

  void triggerBookieShutdown(int);
    Code:
       0: aload_0
       1: getfield      #196                // Field shutdownTriggered:Ljava/util/concurrent/atomic/AtomicBoolean;
       4: iconst_0
       5: iconst_1
       6: invokevirtual #349                // Method java/util/concurrent/atomic/AtomicBoolean.compareAndSet:(ZZ)Z
       9: ifne          13
      12: return
      13: getstatic     #3                  // Field LOG:Lorg/slf4j/Logger;
      16: ldc_w         #350                // String Triggering shutdown of Bookie-{} with exitCode {}
      19: aload_0
      20: getfield      #40                 // Field conf:Lorg/apache/bookkeeper/conf/ServerConfiguration;
      23: invokevirtual #136                // Method org/apache/bookkeeper/conf/ServerConfiguration.getBookiePort:()I
      26: invokestatic  #351                // Method java/lang/Integer.valueOf:(I)Ljava/lang/Integer;
      29: iload_1
      30: invokestatic  #351                // Method java/lang/Integer.valueOf:(I)Ljava/lang/Integer;
      33: invokeinterface #91,  4           // InterfaceMethod org/slf4j/Logger.info:(Ljava/lang/String;Ljava/lang/Object;Ljava/lang/Object;)V
      38: new           #352                // class org/apache/bookkeeper/bookie/Bookie$8
      41: dup
      42: aload_0
      43: ldc_w         #353                // String BookieShutdownTrigger
      46: iload_1
      47: invokespecial #354                // Method org/apache/bookkeeper/bookie/Bookie$8."<init>":(Lorg/apache/bookkeeper/bookie/Bookie;Ljava/lang/String;I)V
      50: astore_2
      51: aload_2
      52: invokevirtual #355                // Method org/apache/bookkeeper/bookie/BookieThread.start:()V
      55: return

  public int shutdown();
    Code:
       0: aload_0
       1: iconst_0
       2: invokevirtual #295                // Method shutdown:(I)I
       5: ireturn

  synchronized int shutdown(int);
    Code:
       0: aload_0
       1: invokevirtual #356                // Method isRunning:()Z
       4: ifeq          186
       7: getstatic     #3                  // Field LOG:Lorg/slf4j/Logger;
      10: ldc_w         #357                // String Shutting down Bookie-{} with exitCode {}
      13: aload_0
      14: getfield      #40                 // Field conf:Lorg/apache/bookkeeper/conf/ServerConfiguration;
      17: invokevirtual #136                // Method org/apache/bookkeeper/conf/ServerConfiguration.getBookiePort:()I
      20: invokestatic  #351                // Method java/lang/Integer.valueOf:(I)Ljava/lang/Integer;
      23: iload_1
      24: invokestatic  #351                // Method java/lang/Integer.valueOf:(I)Ljava/lang/Integer;
      27: invokeinterface #91,  4           // InterfaceMethod org/slf4j/Logger.info:(Ljava/lang/String;Ljava/lang/Object;Ljava/lang/Object;)V
      32: aload_0
      33: getfield      #193                // Field exitCode:I
      36: ifne          44
      39: aload_0
      40: iload_1
      41: putfield      #193                // Field exitCode:I
      44: aload_0
      45: getfield      #219                // Field stateManager:Lorg/apache/bookkeeper/bookie/StateManager;
      48: invokeinterface #358,  1          // InterfaceMethod org/apache/bookkeeper/bookie/StateManager.forceToShuttingDown:()V
      53: getstatic     #3                  // Field LOG:Lorg/slf4j/Logger;
      56: ldc_w         #359                // String Turning bookie to read only during shut down
      59: invokeinterface #307,  2          // InterfaceMethod org/slf4j/Logger.info:(Ljava/lang/String;)V
      64: aload_0
      65: getfield      #219                // Field stateManager:Lorg/apache/bookkeeper/bookie/StateManager;
      68: invokeinterface #360,  1          // InterfaceMethod org/apache/bookkeeper/bookie/StateManager.forceToReadOnly:()V
      73: aload_0
      74: getfield      #243                // Field syncThread:Lorg/apache/bookkeeper/bookie/SyncThread;
      77: invokevirtual #361                // Method org/apache/bookkeeper/bookie/SyncThread.shutdown:()V
      80: aload_0
      81: getfield      #229                // Field journals:Ljava/util/List;
      84: invokeinterface #36,  1           // InterfaceMethod java/util/List.iterator:()Ljava/util/Iterator;
      89: astore_2
      90: aload_2
      91: invokeinterface #37,  1           // InterfaceMethod java/util/Iterator.hasNext:()Z
      96: ifeq          116
      99: aload_2
     100: invokeinterface #38,  1           // InterfaceMethod java/util/Iterator.next:()Ljava/lang/Object;
     105: checkcast     #230                // class org/apache/bookkeeper/bookie/Journal
     108: astore_3
     109: aload_3
     110: invokevirtual #362                // Method org/apache/bookkeeper/bookie/Journal.shutdown:()V
     113: goto          90
     116: aload_0
     117: invokevirtual #363                // Method join:()V
     120: aload_0
     121: getfield      #238                // Field ledgerStorage:Lorg/apache/bookkeeper/bookie/LedgerStorage;
     124: invokeinterface #364,  1          // InterfaceMethod org/apache/bookkeeper/bookie/LedgerStorage.shutdown:()V
     129: aconst_null
     130: aload_0
     131: getfield      #213                // Field ledgerManager:Lorg/apache/bookkeeper/meta/LedgerManager;
     134: if_acmpeq     146
     137: aload_0
     138: getfield      #213                // Field ledgerManager:Lorg/apache/bookkeeper/meta/LedgerManager;
     141: invokeinterface #365,  1          // InterfaceMethod org/apache/bookkeeper/meta/LedgerManager.close:()V
     146: aconst_null
     147: aload_0
     148: getfield      #208                // Field ledgerManagerFactory:Lorg/apache/bookkeeper/meta/LedgerManagerFactory;
     151: if_acmpeq     163
     154: aload_0
     155: getfield      #208                // Field ledgerManagerFactory:Lorg/apache/bookkeeper/meta/LedgerManagerFactory;
     158: invokeinterface #366,  1          // InterfaceMethod org/apache/bookkeeper/meta/LedgerManagerFactory.close:()V
     163: goto          179
     166: astore_2
     167: getstatic     #3                  // Field LOG:Lorg/slf4j/Logger;
     170: ldc_w         #367                // String Failed to close active ledger manager :
     173: aload_2
     174: invokeinterface #118,  3          // InterfaceMethod org/slf4j/Logger.error:(Ljava/lang/String;Ljava/lang/Throwable;)V
     179: aload_0
     180: getfield      #224                // Field dirsMonitor:Lorg/apache/bookkeeper/bookie/LedgerDirsMonitor;
     183: invokevirtual #368                // Method org/apache/bookkeeper/bookie/LedgerDirsMonitor.shutdown:()V
     186: aload_0
     187: getfield      #205                // Field metadataDriver:Lorg/apache/bookkeeper/meta/MetadataBookieDriver;
     190: ifnull        202
     193: aload_0
     194: getfield      #205                // Field metadataDriver:Lorg/apache/bookkeeper/meta/MetadataBookieDriver;
     197: invokeinterface #369,  1          // InterfaceMethod org/apache/bookkeeper/meta/MetadataBookieDriver.close:()V
     202: aload_0
     203: getfield      #219                // Field stateManager:Lorg/apache/bookkeeper/bookie/StateManager;
     206: invokeinterface #370,  1          // InterfaceMethod org/apache/bookkeeper/bookie/StateManager.close:()V
     211: goto          274
     214: astore_2
     215: invokestatic  #301                // Method java/lang/Thread.currentThread:()Ljava/lang/Thread;
     218: invokevirtual #302                // Method java/lang/Thread.interrupt:()V
     221: getstatic     #3                  // Field LOG:Lorg/slf4j/Logger;
     224: ldc_w         #371                // String Interrupted during shutting down bookie :
     227: aload_2
     228: invokeinterface #118,  3          // InterfaceMethod org/slf4j/Logger.error:(Ljava/lang/String;Ljava/lang/Throwable;)V
     233: aload_0
     234: getfield      #219                // Field stateManager:Lorg/apache/bookkeeper/bookie/StateManager;
     237: invokeinterface #370,  1          // InterfaceMethod org/apache/bookkeeper/bookie/StateManager.close:()V
     242: goto          274
     245: astore_2
     246: getstatic     #3                  // Field LOG:Lorg/slf4j/Logger;
     249: ldc_w         #372                // String Got Exception while trying to shutdown Bookie
     252: aload_2
     253: invokeinterface #118,  3          // InterfaceMethod org/slf4j/Logger.error:(Ljava/lang/String;Ljava/lang/Throwable;)V
     258: aload_2
     259: athrow
     260: astore        4
     262: aload_0
     263: getfield      #219                // Field stateManager:Lorg/apache/bookkeeper/bookie/StateManager;
     266: invokeinterface #370,  1          // InterfaceMethod org/apache/bookkeeper/bookie/StateManager.close:()V
     271: aload         4
     273: athrow
     274: aload_0
     275: getfield      #193                // Field exitCode:I
     278: ireturn
    Exception table:
       from    to  target type
         129   163   166   Class java/io/IOException
           0   202   214   Class java/lang/InterruptedException
           0   202   245   Class java/lang/Exception
           0   202   260   any
         214   233   260   any
         245   262   260   any

  org.apache.bookkeeper.bookie.LedgerDescriptor getLedgerForEntry(io.netty.buffer.ByteBuf, byte[]) throws java.io.IOException, org.apache.bookkeeper.bookie.BookieException;
    Code:
       0: aload_1
       1: aload_1
       2: invokevirtual #373                // Method io/netty/buffer/ByteBuf.readerIndex:()I
       5: invokevirtual #374                // Method io/netty/buffer/ByteBuf.getLong:(I)J
       8: lstore_3
       9: aload_0
      10: getfield      #248                // Field handles:Lorg/apache/bookkeeper/bookie/HandleFactory;
      13: lload_3
      14: aload_2
      15: invokeinterface #375,  4          // InterfaceMethod org/apache/bookkeeper/bookie/HandleFactory.getHandle:(J[B)Lorg/apache/bookkeeper/bookie/LedgerDescriptor;
      20: areturn

  private org.apache.bookkeeper.bookie.Journal getJournal(long);
    Code:
       0: aload_0
       1: getfield      #229                // Field journals:Ljava/util/List;
       4: lload_1
       5: aload_0
       6: getfield      #229                // Field journals:Ljava/util/List;
       9: invokeinterface #31,  1           // InterfaceMethod java/util/List.size:()I
      14: invokestatic  #376                // Method org/apache/bookkeeper/util/MathUtils.signSafeMod:(JI)I
      17: invokeinterface #231,  2          // InterfaceMethod java/util/List.get:(I)Ljava/lang/Object;
      22: checkcast     #230                // class org/apache/bookkeeper/bookie/Journal
      25: areturn

  private void addEntryInternal(org.apache.bookkeeper.bookie.LedgerDescriptor, io.netty.buffer.ByteBuf, boolean, org.apache.bookkeeper.proto.BookkeeperInternalCallbacks$WriteCallback, java.lang.Object, byte[]) throws java.io.IOException, org.apache.bookkeeper.bookie.BookieException, java.lang.InterruptedException;
    Code:
       0: aload_1
       1: invokevirtual #377                // Method org/apache/bookkeeper/bookie/LedgerDescriptor.getLedgerId:()J
       4: lstore        7
       6: aload_1
       7: aload_2
       8: invokevirtual #378                // Method org/apache/bookkeeper/bookie/LedgerDescriptor.addEntry:(Lio/netty/buffer/ByteBuf;)J
      11: lstore        9
      13: aload_0
      14: getfield      #251                // Field bookieStats:Lorg/apache/bookkeeper/bookie/stats/BookieStats;
      17: invokevirtual #379                // Method org/apache/bookkeeper/bookie/stats/BookieStats.getWriteBytes:()Lorg/apache/bookkeeper/stats/Counter;
      20: aload_2
      21: invokevirtual #380                // Method io/netty/buffer/ByteBuf.readableBytes:()I
      24: i2l
      25: invokeinterface #381,  3          // InterfaceMethod org/apache/bookkeeper/stats/Counter.add:(J)V
      30: aload_0
      31: getfield      #2                  // Field masterKeyCache:Lorg/apache/bookkeeper/util/collections/ConcurrentLongHashMap;
      34: lload         7
      36: invokevirtual #382                // Method org/apache/bookkeeper/util/collections/ConcurrentLongHashMap.get:(J)Ljava/lang/Object;
      39: ifnonnull     134
      42: aload_0
      43: getfield      #2                  // Field masterKeyCache:Lorg/apache/bookkeeper/util/collections/ConcurrentLongHashMap;
      46: lload         7
      48: aload         6
      50: invokevirtual #383                // Method org/apache/bookkeeper/util/collections/ConcurrentLongHashMap.putIfAbsent:(JLjava/lang/Object;)Ljava/lang/Object;
      53: checkcast     #384                // class "[B"
      56: astore        11
      58: aload         11
      60: ifnonnull     134
      63: bipush        20
      65: aload         6
      67: arraylength
      68: iadd
      69: invokestatic  #385                // Method java/nio/ByteBuffer.allocate:(I)Ljava/nio/ByteBuffer;
      72: astore        12
      74: aload         12
      76: lload         7
      78: invokevirtual #386                // Method java/nio/ByteBuffer.putLong:(J)Ljava/nio/ByteBuffer;
      81: pop
      82: aload         12
      84: ldc2_w        #388                // long -4096l
      87: invokevirtual #386                // Method java/nio/ByteBuffer.putLong:(J)Ljava/nio/ByteBuffer;
      90: pop
      91: aload         12
      93: aload         6
      95: arraylength
      96: invokevirtual #390                // Method java/nio/ByteBuffer.putInt:(I)Ljava/nio/ByteBuffer;
      99: pop
     100: aload         12
     102: aload         6
     104: invokevirtual #391                // Method java/nio/ByteBuffer.put:([B)Ljava/nio/ByteBuffer;
     107: pop
     108: aload         12
     110: invokevirtual #392                // Method java/nio/ByteBuffer.flip:()Ljava/nio/Buffer;
     113: pop
     114: aload_0
     115: lload         7
     117: invokespecial #393                // Method getJournal:(J)Lorg/apache/bookkeeper/bookie/Journal;
     120: aload         12
     122: iconst_0
     123: new           #394                // class org/apache/bookkeeper/bookie/Bookie$NopWriteCallback
     126: dup
     127: invokespecial #395                // Method org/apache/bookkeeper/bookie/Bookie$NopWriteCallback."<init>":()V
     130: aconst_null
     131: invokevirtual #396                // Method org/apache/bookkeeper/bookie/Journal.logAddEntry:(Ljava/nio/ByteBuffer;ZLorg/apache/bookkeeper/proto/BookkeeperInternalCallbacks$WriteCallback;Ljava/lang/Object;)V
     134: aload_0
     135: getfield      #202                // Field writeDataToJournal:Z
     138: ifne          157
     141: aload         4
     143: iconst_0
     144: lload         7
     146: lload         9
     148: aconst_null
     149: aload         5
     151: invokeinterface #397,  8          // InterfaceMethod org/apache/bookkeeper/proto/BookkeeperInternalCallbacks$WriteCallback.writeComplete:(IJJLorg/apache/bookkeeper/net/BookieId;Ljava/lang/Object;)V
     156: return
     157: getstatic     #3                  // Field LOG:Lorg/slf4j/Logger;
     160: invokeinterface #398,  1          // InterfaceMethod org/slf4j/Logger.isTraceEnabled:()Z
     165: ifeq          189
     168: getstatic     #3                  // Field LOG:Lorg/slf4j/Logger;
     171: ldc_w         #399                // String Adding {}@{}
     174: lload         9
     176: invokestatic  #268                // Method java/lang/Long.valueOf:(J)Ljava/lang/Long;
     179: lload         7
     181: invokestatic  #268                // Method java/lang/Long.valueOf:(J)Ljava/lang/Long;
     184: invokeinterface #400,  4          // InterfaceMethod org/slf4j/Logger.trace:(Ljava/lang/String;Ljava/lang/Object;Ljava/lang/Object;)V
     189: aload_0
     190: lload         7
     192: invokespecial #393                // Method getJournal:(J)Lorg/apache/bookkeeper/bookie/Journal;
     195: aload_2
     196: iload_3
     197: aload         4
     199: aload         5
     201: invokevirtual #401                // Method org/apache/bookkeeper/bookie/Journal.logAddEntry:(Lio/netty/buffer/ByteBuf;ZLorg/apache/bookkeeper/proto/BookkeeperInternalCallbacks$WriteCallback;Ljava/lang/Object;)V
     204: return

  public void recoveryAddEntry(io.netty.buffer.ByteBuf, org.apache.bookkeeper.proto.BookkeeperInternalCallbacks$WriteCallback, java.lang.Object, byte[]) throws java.io.IOException, org.apache.bookkeeper.bookie.BookieException, java.lang.InterruptedException;
    Code:
       0: invokestatic  #402                // Method org/apache/bookkeeper/util/MathUtils.nowInNano:()J
       3: lstore        5
       5: iconst_0
       6: istore        7
       8: iconst_0
       9: istore        8
      11: aload_0
      12: aload_1
      13: aload         4
      15: invokevirtual #403                // Method getLedgerForEntry:(Lio/netty/buffer/ByteBuf;[B)Lorg/apache/bookkeeper/bookie/LedgerDescriptor;
      18: astore        9
      20: aload         9
      22: dup
      23: astore        10
      25: monitorenter
      26: aload_1
      27: invokevirtual #380                // Method io/netty/buffer/ByteBuf.readableBytes:()I
      30: istore        8
      32: aload_0
      33: aload         9
      35: aload_1
      36: iconst_0
      37: aload_2
      38: aload_3
      39: aload         4
      41: invokespecial #404                // Method addEntryInternal:(Lorg/apache/bookkeeper/bookie/LedgerDescriptor;Lio/netty/buffer/ByteBuf;ZLorg/apache/bookkeeper/proto/BookkeeperInternalCallbacks$WriteCallback;Ljava/lang/Object;[B)V
      44: aload         10
      46: monitorexit
      47: goto          58
      50: astore        11
      52: aload         10
      54: monitorexit
      55: aload         11
      57: athrow
      58: iconst_1
      59: istore        7
      61: lload         5
      63: invokestatic  #405                // Method org/apache/bookkeeper/util/MathUtils.elapsedNanos:(J)J
      66: lstore        9
      68: iload         7
      70: ifeq          108
      73: aload_0
      74: getfield      #251                // Field bookieStats:Lorg/apache/bookkeeper/bookie/stats/BookieStats;
      77: invokevirtual #406                // Method org/apache/bookkeeper/bookie/stats/BookieStats.getRecoveryAddEntryStats:()Lorg/apache/bookkeeper/stats/OpStatsLogger;
      80: lload         9
      82: getstatic     #407                // Field java/util/concurrent/TimeUnit.NANOSECONDS:Ljava/util/concurrent/TimeUnit;
      85: invokeinterface #408,  4          // InterfaceMethod org/apache/bookkeeper/stats/OpStatsLogger.registerSuccessfulEvent:(JLjava/util/concurrent/TimeUnit;)V
      90: aload_0
      91: getfield      #251                // Field bookieStats:Lorg/apache/bookkeeper/bookie/stats/BookieStats;
      94: invokevirtual #409                // Method org/apache/bookkeeper/bookie/stats/BookieStats.getAddBytesStats:()Lorg/apache/bookkeeper/stats/OpStatsLogger;
      97: iload         8
      99: i2l
     100: invokeinterface #410,  3          // InterfaceMethod org/apache/bookkeeper/stats/OpStatsLogger.registerSuccessfulValue:(J)V
     105: goto          140
     108: aload_0
     109: getfield      #251                // Field bookieStats:Lorg/apache/bookkeeper/bookie/stats/BookieStats;
     112: invokevirtual #406                // Method org/apache/bookkeeper/bookie/stats/BookieStats.getRecoveryAddEntryStats:()Lorg/apache/bookkeeper/stats/OpStatsLogger;
     115: lload         9
     117: getstatic     #407                // Field java/util/concurrent/TimeUnit.NANOSECONDS:Ljava/util/concurrent/TimeUnit;
     120: invokeinterface #411,  4          // InterfaceMethod org/apache/bookkeeper/stats/OpStatsLogger.registerFailedEvent:(JLjava/util/concurrent/TimeUnit;)V
     125: aload_0
     126: getfield      #251                // Field bookieStats:Lorg/apache/bookkeeper/bookie/stats/BookieStats;
     129: invokevirtual #409                // Method org/apache/bookkeeper/bookie/stats/BookieStats.getAddBytesStats:()Lorg/apache/bookkeeper/stats/OpStatsLogger;
     132: iload         8
     134: i2l
     135: invokeinterface #412,  3          // InterfaceMethod org/apache/bookkeeper/stats/OpStatsLogger.registerFailedValue:(J)V
     140: aload_1
     141: invokevirtual #413                // Method io/netty/buffer/ByteBuf.release:()Z
     144: pop
     145: goto          259
     148: astore        9
     150: aload_0
     151: getfield      #219                // Field stateManager:Lorg/apache/bookkeeper/bookie/StateManager;
     154: invokeinterface #228,  1          // InterfaceMethod org/apache/bookkeeper/bookie/StateManager.transitionToReadOnlyMode:()Ljava/util/concurrent/Future;
     159: pop
     160: new           #19                 // class java/io/IOException
     163: dup
     164: aload         9
     166: invokespecial #414                // Method java/io/IOException."<init>":(Ljava/lang/Throwable;)V
     169: athrow
     170: astore        12
     172: lload         5
     174: invokestatic  #405                // Method org/apache/bookkeeper/util/MathUtils.elapsedNanos:(J)J
     177: lstore        13
     179: iload         7
     181: ifeq          219
     184: aload_0
     185: getfield      #251                // Field bookieStats:Lorg/apache/bookkeeper/bookie/stats/BookieStats;
     188: invokevirtual #406                // Method org/apache/bookkeeper/bookie/stats/BookieStats.getRecoveryAddEntryStats:()Lorg/apache/bookkeeper/stats/OpStatsLogger;
     191: lload         13
     193: getstatic     #407                // Field java/util/concurrent/TimeUnit.NANOSECONDS:Ljava/util/concurrent/TimeUnit;
     196: invokeinterface #408,  4          // InterfaceMethod org/apache/bookkeeper/stats/OpStatsLogger.registerSuccessfulEvent:(JLjava/util/concurrent/TimeUnit;)V
     201: aload_0
     202: getfield      #251                // Field bookieStats:Lorg/apache/bookkeeper/bookie/stats/BookieStats;
     205: invokevirtual #409                // Method org/apache/bookkeeper/bookie/stats/BookieStats.getAddBytesStats:()Lorg/apache/bookkeeper/stats/OpStatsLogger;
     208: iload         8
     210: i2l
     211: invokeinterface #410,  3          // InterfaceMethod org/apache/bookkeeper/stats/OpStatsLogger.registerSuccessfulValue:(J)V
     216: goto          251
     219: aload_0
     220: getfield      #251                // Field bookieStats:Lorg/apache/bookkeeper/bookie/stats/BookieStats;
     223: invokevirtual #406                // Method org/apache/bookkeeper/bookie/stats/BookieStats.getRecoveryAddEntryStats:()Lorg/apache/bookkeeper/stats/OpStatsLogger;
     226: lload         13
     228: getstatic     #407                // Field java/util/concurrent/TimeUnit.NANOSECONDS:Ljava/util/concurrent/TimeUnit;
     231: invokeinterface #411,  4          // InterfaceMethod org/apache/bookkeeper/stats/OpStatsLogger.registerFailedEvent:(JLjava/util/concurrent/TimeUnit;)V
     236: aload_0
     237: getfield      #251                // Field bookieStats:Lorg/apache/bookkeeper/bookie/stats/BookieStats;
     240: invokevirtual #409                // Method org/apache/bookkeeper/bookie/stats/BookieStats.getAddBytesStats:()Lorg/apache/bookkeeper/stats/OpStatsLogger;
     243: iload         8
     245: i2l
     246: invokeinterface #412,  3          // InterfaceMethod org/apache/bookkeeper/stats/OpStatsLogger.registerFailedValue:(J)V
     251: aload_1
     252: invokevirtual #413                // Method io/netty/buffer/ByteBuf.release:()Z
     255: pop
     256: aload         12
     258: athrow
     259: return
    Exception table:
       from    to  target type
          26    47    50   any
          50    55    50   any
          11    61   148   Class org/apache/bookkeeper/bookie/LedgerDirsManager$NoWritableLedgerDirException
          11    61   170   any
         148   172   170   any

  private io.netty.buffer.ByteBuf createExplicitLACEntry(long, io.netty.buffer.ByteBuf);
    Code:
       0: aload_0
       1: getfield      #203                // Field allocator:Lio/netty/buffer/ByteBufAllocator;
       4: bipush        20
       6: aload_3
       7: invokevirtual #415                // Method io/netty/buffer/ByteBuf.capacity:()I
      10: iadd
      11: invokeinterface #416,  2          // InterfaceMethod io/netty/buffer/ByteBufAllocator.directBuffer:(I)Lio/netty/buffer/ByteBuf;
      16: astore        4
      18: aload         4
      20: lload_1
      21: invokevirtual #417                // Method io/netty/buffer/ByteBuf.writeLong:(J)Lio/netty/buffer/ByteBuf;
      24: pop
      25: aload         4
      27: ldc2_w        #418                // long -32768l
      30: invokevirtual #417                // Method io/netty/buffer/ByteBuf.writeLong:(J)Lio/netty/buffer/ByteBuf;
      33: pop
      34: aload         4
      36: aload_3
      37: invokevirtual #415                // Method io/netty/buffer/ByteBuf.capacity:()I
      40: invokevirtual #420                // Method io/netty/buffer/ByteBuf.writeInt:(I)Lio/netty/buffer/ByteBuf;
      43: pop
      44: aload         4
      46: aload_3
      47: invokevirtual #421                // Method io/netty/buffer/ByteBuf.writeBytes:(Lio/netty/buffer/ByteBuf;)Lio/netty/buffer/ByteBuf;
      50: pop
      51: aload         4
      53: areturn

  public void setExplicitLac(io.netty.buffer.ByteBuf, org.apache.bookkeeper.proto.BookkeeperInternalCallbacks$WriteCallback, java.lang.Object, byte[]) throws java.io.IOException, java.lang.InterruptedException, org.apache.bookkeeper.bookie.BookieException;
    Code:
       0: aload_1
       1: aload_1
       2: invokevirtual #373                // Method io/netty/buffer/ByteBuf.readerIndex:()I
       5: invokevirtual #374                // Method io/netty/buffer/ByteBuf.getLong:(I)J
       8: lstore        5
      10: aload_0
      11: getfield      #248                // Field handles:Lorg/apache/bookkeeper/bookie/HandleFactory;
      14: lload         5
      16: aload         4
      18: invokeinterface #375,  4          // InterfaceMethod org/apache/bookkeeper/bookie/HandleFactory.getHandle:(J[B)Lorg/apache/bookkeeper/bookie/LedgerDescriptor;
      23: astore        7
      25: aload         7
      27: dup
      28: astore        8
      30: monitorenter
      31: aload_1
      32: invokevirtual #422                // Method io/netty/buffer/ByteBuf.markReaderIndex:()Lio/netty/buffer/ByteBuf;
      35: pop
      36: aload         7
      38: aload_1
      39: invokevirtual #423                // Method org/apache/bookkeeper/bookie/LedgerDescriptor.setExplicitLac:(Lio/netty/buffer/ByteBuf;)V
      42: aload_1
      43: invokevirtual #424                // Method io/netty/buffer/ByteBuf.resetReaderIndex:()Lio/netty/buffer/ByteBuf;
      46: pop
      47: aload_0
      48: lload         5
      50: aload_1
      51: invokespecial #425                // Method createExplicitLACEntry:(JLio/netty/buffer/ByteBuf;)Lio/netty/buffer/ByteBuf;
      54: astore        9
      56: aload_0
      57: lload         5
      59: invokespecial #393                // Method getJournal:(J)Lorg/apache/bookkeeper/bookie/Journal;
      62: aload         9
      64: iconst_0
      65: aload_2
      66: aload_3
      67: invokevirtual #401                // Method org/apache/bookkeeper/bookie/Journal.logAddEntry:(Lio/netty/buffer/ByteBuf;ZLorg/apache/bookkeeper/proto/BookkeeperInternalCallbacks$WriteCallback;Ljava/lang/Object;)V
      70: aload         8
      72: monitorexit
      73: goto          84
      76: astore        10
      78: aload         8
      80: monitorexit
      81: aload         10
      83: athrow
      84: goto          109
      87: astore        5
      89: aload_0
      90: getfield      #219                // Field stateManager:Lorg/apache/bookkeeper/bookie/StateManager;
      93: invokeinterface #228,  1          // InterfaceMethod org/apache/bookkeeper/bookie/StateManager.transitionToReadOnlyMode:()Ljava/util/concurrent/Future;
      98: pop
      99: new           #19                 // class java/io/IOException
     102: dup
     103: aload         5
     105: invokespecial #414                // Method java/io/IOException."<init>":(Ljava/lang/Throwable;)V
     108: athrow
     109: return
    Exception table:
       from    to  target type
          31    73    76   any
          76    81    76   any
           0    84    87   Class org/apache/bookkeeper/bookie/LedgerDirsManager$NoWritableLedgerDirException

  public io.netty.buffer.ByteBuf getExplicitLac(long) throws java.io.IOException, org.apache.bookkeeper.bookie.Bookie$NoLedgerException;
    Code:
       0: aload_0
       1: getfield      #248                // Field handles:Lorg/apache/bookkeeper/bookie/HandleFactory;
       4: lload_1
       5: invokeinterface #426,  3          // InterfaceMethod org/apache/bookkeeper/bookie/HandleFactory.getReadOnlyHandle:(J)Lorg/apache/bookkeeper/bookie/LedgerDescriptor;
      10: astore        4
      12: aload         4
      14: dup
      15: astore        5
      17: monitorenter
      18: aload         4
      20: invokevirtual #427                // Method org/apache/bookkeeper/bookie/LedgerDescriptor.getExplicitLac:()Lio/netty/buffer/ByteBuf;
      23: astore_3
      24: aload         5
      26: monitorexit
      27: goto          38
      30: astore        6
      32: aload         5
      34: monitorexit
      35: aload         6
      37: athrow
      38: aload_3
      39: areturn
    Exception table:
       from    to  target type
          18    27    30   any
          30    35    30   any

  public void forceLedger(long, org.apache.bookkeeper.proto.BookkeeperInternalCallbacks$WriteCallback, java.lang.Object);
    Code:
       0: getstatic     #3                  // Field LOG:Lorg/slf4j/Logger;
       3: invokeinterface #398,  1          // InterfaceMethod org/slf4j/Logger.isTraceEnabled:()Z
       8: ifeq          26
      11: getstatic     #3                  // Field LOG:Lorg/slf4j/Logger;
      14: ldc_w         #428                // String Forcing ledger {}
      17: lload_1
      18: invokestatic  #268                // Method java/lang/Long.valueOf:(J)Ljava/lang/Long;
      21: invokeinterface #429,  3          // InterfaceMethod org/slf4j/Logger.trace:(Ljava/lang/String;Ljava/lang/Object;)V
      26: aload_0
      27: lload_1
      28: invokespecial #393                // Method getJournal:(J)Lorg/apache/bookkeeper/bookie/Journal;
      31: astore        5
      33: aload         5
      35: lload_1
      36: aload_3
      37: aload         4
      39: invokevirtual #430                // Method org/apache/bookkeeper/bookie/Journal.forceLedger:(JLorg/apache/bookkeeper/proto/BookkeeperInternalCallbacks$WriteCallback;Ljava/lang/Object;)V
      42: aload_0
      43: getfield      #251                // Field bookieStats:Lorg/apache/bookkeeper/bookie/stats/BookieStats;
      46: invokevirtual #431                // Method org/apache/bookkeeper/bookie/stats/BookieStats.getForceLedgerOps:()Lorg/apache/bookkeeper/stats/Counter;
      49: invokeinterface #432,  1          // InterfaceMethod org/apache/bookkeeper/stats/Counter.inc:()V
      54: return

  public void addEntry(io.netty.buffer.ByteBuf, boolean, org.apache.bookkeeper.proto.BookkeeperInternalCallbacks$WriteCallback, java.lang.Object, byte[]) throws java.io.IOException, org.apache.bookkeeper.bookie.BookieException, java.lang.InterruptedException;
    Code:
       0: invokestatic  #402                // Method org/apache/bookkeeper/util/MathUtils.nowInNano:()J
       3: lstore        6
       5: iconst_0
       6: istore        8
       8: iconst_0
       9: istore        9
      11: aload_0
      12: aload_1
      13: aload         5
      15: invokevirtual #403                // Method getLedgerForEntry:(Lio/netty/buffer/ByteBuf;[B)Lorg/apache/bookkeeper/bookie/LedgerDescriptor;
      18: astore        10
      20: aload         10
      22: dup
      23: astore        11
      25: monitorenter
      26: aload         10
      28: invokevirtual #433                // Method org/apache/bookkeeper/bookie/LedgerDescriptor.isFenced:()Z
      31: ifeq          40
      34: bipush        -101
      36: invokestatic  #435                // Method org/apache/bookkeeper/bookie/BookieException.create:(I)Lorg/apache/bookkeeper/bookie/BookieException;
      39: athrow
      40: aload_1
      41: invokevirtual #380                // Method io/netty/buffer/ByteBuf.readableBytes:()I
      44: istore        9
      46: aload_0
      47: aload         10
      49: aload_1
      50: iload_2
      51: aload_3
      52: aload         4
      54: aload         5
      56: invokespecial #404                // Method addEntryInternal:(Lorg/apache/bookkeeper/bookie/LedgerDescriptor;Lio/netty/buffer/ByteBuf;ZLorg/apache/bookkeeper/proto/BookkeeperInternalCallbacks$WriteCallback;Ljava/lang/Object;[B)V
      59: aload         11
      61: monitorexit
      62: goto          73
      65: astore        12
      67: aload         11
      69: monitorexit
      70: aload         12
      72: athrow
      73: iconst_1
      74: istore        8
      76: lload         6
      78: invokestatic  #405                // Method org/apache/bookkeeper/util/MathUtils.elapsedNanos:(J)J
      81: lstore        10
      83: iload         8
      85: ifeq          123
      88: aload_0
      89: getfield      #251                // Field bookieStats:Lorg/apache/bookkeeper/bookie/stats/BookieStats;
      92: invokevirtual #436                // Method org/apache/bookkeeper/bookie/stats/BookieStats.getAddEntryStats:()Lorg/apache/bookkeeper/stats/OpStatsLogger;
      95: lload         10
      97: getstatic     #407                // Field java/util/concurrent/TimeUnit.NANOSECONDS:Ljava/util/concurrent/TimeUnit;
     100: invokeinterface #408,  4          // InterfaceMethod org/apache/bookkeeper/stats/OpStatsLogger.registerSuccessfulEvent:(JLjava/util/concurrent/TimeUnit;)V
     105: aload_0
     106: getfield      #251                // Field bookieStats:Lorg/apache/bookkeeper/bookie/stats/BookieStats;
     109: invokevirtual #409                // Method org/apache/bookkeeper/bookie/stats/BookieStats.getAddBytesStats:()Lorg/apache/bookkeeper/stats/OpStatsLogger;
     112: iload         9
     114: i2l
     115: invokeinterface #410,  3          // InterfaceMethod org/apache/bookkeeper/stats/OpStatsLogger.registerSuccessfulValue:(J)V
     120: goto          155
     123: aload_0
     124: getfield      #251                // Field bookieStats:Lorg/apache/bookkeeper/bookie/stats/BookieStats;
     127: invokevirtual #436                // Method org/apache/bookkeeper/bookie/stats/BookieStats.getAddEntryStats:()Lorg/apache/bookkeeper/stats/OpStatsLogger;
     130: lload         10
     132: getstatic     #407                // Field java/util/concurrent/TimeUnit.NANOSECONDS:Ljava/util/concurrent/TimeUnit;
     135: invokeinterface #411,  4          // InterfaceMethod org/apache/bookkeeper/stats/OpStatsLogger.registerFailedEvent:(JLjava/util/concurrent/TimeUnit;)V
     140: aload_0
     141: getfield      #251                // Field bookieStats:Lorg/apache/bookkeeper/bookie/stats/BookieStats;
     144: invokevirtual #409                // Method org/apache/bookkeeper/bookie/stats/BookieStats.getAddBytesStats:()Lorg/apache/bookkeeper/stats/OpStatsLogger;
     147: iload         9
     149: i2l
     150: invokeinterface #412,  3          // InterfaceMethod org/apache/bookkeeper/stats/OpStatsLogger.registerFailedValue:(J)V
     155: aload_1
     156: invokevirtual #413                // Method io/netty/buffer/ByteBuf.release:()Z
     159: pop
     160: goto          274
     163: astore        10
     165: aload_0
     166: getfield      #219                // Field stateManager:Lorg/apache/bookkeeper/bookie/StateManager;
     169: invokeinterface #228,  1          // InterfaceMethod org/apache/bookkeeper/bookie/StateManager.transitionToReadOnlyMode:()Ljava/util/concurrent/Future;
     174: pop
     175: new           #19                 // class java/io/IOException
     178: dup
     179: aload         10
     181: invokespecial #414                // Method java/io/IOException."<init>":(Ljava/lang/Throwable;)V
     184: athrow
     185: astore        13
     187: lload         6
     189: invokestatic  #405                // Method org/apache/bookkeeper/util/MathUtils.elapsedNanos:(J)J
     192: lstore        14
     194: iload         8
     196: ifeq          234
     199: aload_0
     200: getfield      #251                // Field bookieStats:Lorg/apache/bookkeeper/bookie/stats/BookieStats;
     203: invokevirtual #436                // Method org/apache/bookkeeper/bookie/stats/BookieStats.getAddEntryStats:()Lorg/apache/bookkeeper/stats/OpStatsLogger;
     206: lload         14
     208: getstatic     #407                // Field java/util/concurrent/TimeUnit.NANOSECONDS:Ljava/util/concurrent/TimeUnit;
     211: invokeinterface #408,  4          // InterfaceMethod org/apache/bookkeeper/stats/OpStatsLogger.registerSuccessfulEvent:(JLjava/util/concurrent/TimeUnit;)V
     216: aload_0
     217: getfield      #251                // Field bookieStats:Lorg/apache/bookkeeper/bookie/stats/BookieStats;
     220: invokevirtual #409                // Method org/apache/bookkeeper/bookie/stats/BookieStats.getAddBytesStats:()Lorg/apache/bookkeeper/stats/OpStatsLogger;
     223: iload         9
     225: i2l
     226: invokeinterface #410,  3          // InterfaceMethod org/apache/bookkeeper/stats/OpStatsLogger.registerSuccessfulValue:(J)V
     231: goto          266
     234: aload_0
     235: getfield      #251                // Field bookieStats:Lorg/apache/bookkeeper/bookie/stats/BookieStats;
     238: invokevirtual #436                // Method org/apache/bookkeeper/bookie/stats/BookieStats.getAddEntryStats:()Lorg/apache/bookkeeper/stats/OpStatsLogger;
     241: lload         14
     243: getstatic     #407                // Field java/util/concurrent/TimeUnit.NANOSECONDS:Ljava/util/concurrent/TimeUnit;
     246: invokeinterface #411,  4          // InterfaceMethod org/apache/bookkeeper/stats/OpStatsLogger.registerFailedEvent:(JLjava/util/concurrent/TimeUnit;)V
     251: aload_0
     252: getfield      #251                // Field bookieStats:Lorg/apache/bookkeeper/bookie/stats/BookieStats;
     255: invokevirtual #409                // Method org/apache/bookkeeper/bookie/stats/BookieStats.getAddBytesStats:()Lorg/apache/bookkeeper/stats/OpStatsLogger;
     258: iload         9
     260: i2l
     261: invokeinterface #412,  3          // InterfaceMethod org/apache/bookkeeper/stats/OpStatsLogger.registerFailedValue:(J)V
     266: aload_1
     267: invokevirtual #413                // Method io/netty/buffer/ByteBuf.release:()Z
     270: pop
     271: aload         13
     273: athrow
     274: return
    Exception table:
       from    to  target type
          26    62    65   any
          65    70    65   any
          11    76   163   Class org/apache/bookkeeper/bookie/LedgerDirsManager$NoWritableLedgerDirException
          11    76   185   any
         163   187   185   any

  public com.google.common.util.concurrent.SettableFuture<java.lang.Boolean> fenceLedger(long, byte[]) throws java.io.IOException, org.apache.bookkeeper.bookie.BookieException;
    Code:
       0: aload_0
       1: getfield      #248                // Field handles:Lorg/apache/bookkeeper/bookie/HandleFactory;
       4: lload_1
       5: aload_3
       6: invokeinterface #375,  4          // InterfaceMethod org/apache/bookkeeper/bookie/HandleFactory.getHandle:(J[B)Lorg/apache/bookkeeper/bookie/LedgerDescriptor;
      11: astore        4
      13: aload         4
      15: aload_0
      16: lload_1
      17: invokespecial #393                // Method getJournal:(J)Lorg/apache/bookkeeper/bookie/Journal;
      20: invokevirtual #437                // Method org/apache/bookkeeper/bookie/LedgerDescriptor.fenceAndLogInJournal:(Lorg/apache/bookkeeper/bookie/Journal;)Lcom/google/common/util/concurrent/SettableFuture;
      23: areturn

  public io.netty.buffer.ByteBuf readEntry(long, long) throws java.io.IOException, org.apache.bookkeeper.bookie.Bookie$NoLedgerException;
    Code:
       0: invokestatic  #402                // Method org/apache/bookkeeper/util/MathUtils.nowInNano:()J
       3: lstore        5
       5: iconst_0
       6: istore        7
       8: iconst_0
       9: istore        8
      11: aload_0
      12: getfield      #248                // Field handles:Lorg/apache/bookkeeper/bookie/HandleFactory;
      15: lload_1
      16: invokeinterface #426,  3          // InterfaceMethod org/apache/bookkeeper/bookie/HandleFactory.getReadOnlyHandle:(J)Lorg/apache/bookkeeper/bookie/LedgerDescriptor;
      21: astore        9
      23: getstatic     #3                  // Field LOG:Lorg/slf4j/Logger;
      26: invokeinterface #398,  1          // InterfaceMethod org/slf4j/Logger.isTraceEnabled:()Z
      31: ifeq          53
      34: getstatic     #3                  // Field LOG:Lorg/slf4j/Logger;
      37: ldc_w         #438                // String Reading {}@{}
      40: lload_3
      41: invokestatic  #268                // Method java/lang/Long.valueOf:(J)Ljava/lang/Long;
      44: lload_1
      45: invokestatic  #268                // Method java/lang/Long.valueOf:(J)Ljava/lang/Long;
      48: invokeinterface #400,  4          // InterfaceMethod org/slf4j/Logger.trace:(Ljava/lang/String;Ljava/lang/Object;Ljava/lang/Object;)V
      53: aload         9
      55: lload_3
      56: invokevirtual #439                // Method org/apache/bookkeeper/bookie/LedgerDescriptor.readEntry:(J)Lio/netty/buffer/ByteBuf;
      59: astore        10
      61: aload_0
      62: getfield      #251                // Field bookieStats:Lorg/apache/bookkeeper/bookie/stats/BookieStats;
      65: invokevirtual #440                // Method org/apache/bookkeeper/bookie/stats/BookieStats.getReadBytes:()Lorg/apache/bookkeeper/stats/Counter;
      68: aload         10
      70: invokevirtual #380                // Method io/netty/buffer/ByteBuf.readableBytes:()I
      73: i2l
      74: invokeinterface #381,  3          // InterfaceMethod org/apache/bookkeeper/stats/Counter.add:(J)V
      79: iconst_1
      80: istore        7
      82: aload         10
      84: astore        11
      86: lload         5
      88: invokestatic  #405                // Method org/apache/bookkeeper/util/MathUtils.elapsedNanos:(J)J
      91: lstore        12
      93: iload         7
      95: ifeq          133
      98: aload_0
      99: getfield      #251                // Field bookieStats:Lorg/apache/bookkeeper/bookie/stats/BookieStats;
     102: invokevirtual #441                // Method org/apache/bookkeeper/bookie/stats/BookieStats.getReadEntryStats:()Lorg/apache/bookkeeper/stats/OpStatsLogger;
     105: lload         12
     107: getstatic     #407                // Field java/util/concurrent/TimeUnit.NANOSECONDS:Ljava/util/concurrent/TimeUnit;
     110: invokeinterface #408,  4          // InterfaceMethod org/apache/bookkeeper/stats/OpStatsLogger.registerSuccessfulEvent:(JLjava/util/concurrent/TimeUnit;)V
     115: aload_0
     116: getfield      #251                // Field bookieStats:Lorg/apache/bookkeeper/bookie/stats/BookieStats;
     119: invokevirtual #442                // Method org/apache/bookkeeper/bookie/stats/BookieStats.getReadBytesStats:()Lorg/apache/bookkeeper/stats/OpStatsLogger;
     122: iload         8
     124: i2l
     125: invokeinterface #410,  3          // InterfaceMethod org/apache/bookkeeper/stats/OpStatsLogger.registerSuccessfulValue:(J)V
     130: goto          165
     133: aload_0
     134: getfield      #251                // Field bookieStats:Lorg/apache/bookkeeper/bookie/stats/BookieStats;
     137: invokevirtual #441                // Method org/apache/bookkeeper/bookie/stats/BookieStats.getReadEntryStats:()Lorg/apache/bookkeeper/stats/OpStatsLogger;
     140: lload         12
     142: getstatic     #407                // Field java/util/concurrent/TimeUnit.NANOSECONDS:Ljava/util/concurrent/TimeUnit;
     145: invokeinterface #411,  4          // InterfaceMethod org/apache/bookkeeper/stats/OpStatsLogger.registerFailedEvent:(JLjava/util/concurrent/TimeUnit;)V
     150: aload_0
     151: getfield      #251                // Field bookieStats:Lorg/apache/bookkeeper/bookie/stats/BookieStats;
     154: invokevirtual #441                // Method org/apache/bookkeeper/bookie/stats/BookieStats.getReadEntryStats:()Lorg/apache/bookkeeper/stats/OpStatsLogger;
     157: iload         8
     159: i2l
     160: invokeinterface #412,  3          // InterfaceMethod org/apache/bookkeeper/stats/OpStatsLogger.registerFailedValue:(J)V
     165: aload         11
     167: areturn
     168: astore        14
     170: lload         5
     172: invokestatic  #405                // Method org/apache/bookkeeper/util/MathUtils.elapsedNanos:(J)J
     175: lstore        15
     177: iload         7
     179: ifeq          217
     182: aload_0
     183: getfield      #251                // Field bookieStats:Lorg/apache/bookkeeper/bookie/stats/BookieStats;
     186: invokevirtual #441                // Method org/apache/bookkeeper/bookie/stats/BookieStats.getReadEntryStats:()Lorg/apache/bookkeeper/stats/OpStatsLogger;
     189: lload         15
     191: getstatic     #407                // Field java/util/concurrent/TimeUnit.NANOSECONDS:Ljava/util/concurrent/TimeUnit;
     194: invokeinterface #408,  4          // InterfaceMethod org/apache/bookkeeper/stats/OpStatsLogger.registerSuccessfulEvent:(JLjava/util/concurrent/TimeUnit;)V
     199: aload_0
     200: getfield      #251                // Field bookieStats:Lorg/apache/bookkeeper/bookie/stats/BookieStats;
     203: invokevirtual #442                // Method org/apache/bookkeeper/bookie/stats/BookieStats.getReadBytesStats:()Lorg/apache/bookkeeper/stats/OpStatsLogger;
     206: iload         8
     208: i2l
     209: invokeinterface #410,  3          // InterfaceMethod org/apache/bookkeeper/stats/OpStatsLogger.registerSuccessfulValue:(J)V
     214: goto          249
     217: aload_0
     218: getfield      #251                // Field bookieStats:Lorg/apache/bookkeeper/bookie/stats/BookieStats;
     221: invokevirtual #441                // Method org/apache/bookkeeper/bookie/stats/BookieStats.getReadEntryStats:()Lorg/apache/bookkeeper/stats/OpStatsLogger;
     224: lload         15
     226: getstatic     #407                // Field java/util/concurrent/TimeUnit.NANOSECONDS:Ljava/util/concurrent/TimeUnit;
     229: invokeinterface #411,  4          // InterfaceMethod org/apache/bookkeeper/stats/OpStatsLogger.registerFailedEvent:(JLjava/util/concurrent/TimeUnit;)V
     234: aload_0
     235: getfield      #251                // Field bookieStats:Lorg/apache/bookkeeper/bookie/stats/BookieStats;
     238: invokevirtual #441                // Method org/apache/bookkeeper/bookie/stats/BookieStats.getReadEntryStats:()Lorg/apache/bookkeeper/stats/OpStatsLogger;
     241: iload         8
     243: i2l
     244: invokeinterface #412,  3          // InterfaceMethod org/apache/bookkeeper/stats/OpStatsLogger.registerFailedValue:(J)V
     249: aload         14
     251: athrow
    Exception table:
       from    to  target type
          11    86   168   any
         168   170   168   any

  public long readLastAddConfirmed(long) throws java.io.IOException;
    Code:
       0: aload_0
       1: getfield      #248                // Field handles:Lorg/apache/bookkeeper/bookie/HandleFactory;
       4: lload_1
       5: invokeinterface #426,  3          // InterfaceMethod org/apache/bookkeeper/bookie/HandleFactory.getReadOnlyHandle:(J)Lorg/apache/bookkeeper/bookie/LedgerDescriptor;
      10: astore_3
      11: aload_3
      12: invokevirtual #443                // Method org/apache/bookkeeper/bookie/LedgerDescriptor.getLastAddConfirmed:()J
      15: lreturn

  public boolean waitForLastAddConfirmedUpdate(long, long, org.apache.bookkeeper.common.util.Watcher<org.apache.bookkeeper.bookie.LastAddConfirmedUpdateNotification>) throws java.io.IOException;
    Code:
       0: aload_0
       1: getfield      #248                // Field handles:Lorg/apache/bookkeeper/bookie/HandleFactory;
       4: lload_1
       5: invokeinterface #426,  3          // InterfaceMethod org/apache/bookkeeper/bookie/HandleFactory.getReadOnlyHandle:(J)Lorg/apache/bookkeeper/bookie/LedgerDescriptor;
      10: astore        6
      12: aload         6
      14: lload_3
      15: aload         5
      17: invokevirtual #444                // Method org/apache/bookkeeper/bookie/LedgerDescriptor.waitForLastAddConfirmedUpdate:(JLorg/apache/bookkeeper/common/util/Watcher;)Z
      20: ireturn

  public void cancelWaitForLastAddConfirmedUpdate(long, org.apache.bookkeeper.common.util.Watcher<org.apache.bookkeeper.bookie.LastAddConfirmedUpdateNotification>) throws java.io.IOException;
    Code:
       0: aload_0
       1: getfield      #248                // Field handles:Lorg/apache/bookkeeper/bookie/HandleFactory;
       4: lload_1
       5: invokeinterface #426,  3          // InterfaceMethod org/apache/bookkeeper/bookie/HandleFactory.getReadOnlyHandle:(J)Lorg/apache/bookkeeper/bookie/LedgerDescriptor;
      10: astore        4
      12: aload         4
      14: aload_3
      15: invokevirtual #445                // Method org/apache/bookkeeper/bookie/LedgerDescriptor.cancelWaitForLastAddConfirmedUpdate:(Lorg/apache/bookkeeper/common/util/Watcher;)V
      18: return

  public org.apache.bookkeeper.bookie.LedgerStorage getLedgerStorage();
    Code:
       0: aload_0
       1: getfield      #238                // Field ledgerStorage:Lorg/apache/bookkeeper/bookie/LedgerStorage;
       4: areturn

  public org.apache.bookkeeper.bookie.BookieStateManager getStateManager();
    Code:
       0: aload_0
       1: getfield      #219                // Field stateManager:Lorg/apache/bookkeeper/bookie/StateManager;
       4: checkcast     #261                // class org/apache/bookkeeper/bookie/BookieStateManager
       7: areturn

  public org.apache.bookkeeper.meta.LedgerManagerFactory getLedgerManagerFactory();
    Code:
       0: aload_0
       1: getfield      #208                // Field ledgerManagerFactory:Lorg/apache/bookkeeper/meta/LedgerManagerFactory;
       4: areturn

  public io.netty.buffer.ByteBufAllocator getAllocator();
    Code:
       0: aload_0
       1: getfield      #203                // Field allocator:Lio/netty/buffer/ByteBufAllocator;
       4: areturn

  public static boolean format(org.apache.bookkeeper.conf.ServerConfiguration, boolean, boolean);
    Code:
       0: aload_0
       1: invokevirtual #199                // Method org/apache/bookkeeper/conf/ServerConfiguration.getJournalDirs:()[Ljava/io/File;
       4: astore_3
       5: aload_3
       6: arraylength
       7: istore        4
       9: iconst_0
      10: istore        5
      12: iload         5
      14: iload         4
      16: if_icmpge     149
      19: aload_3
      20: iload         5
      22: aaload
      23: astore        6
      25: aload         6
      27: invokevirtual #4                  // Method java/io/File.exists:()Z
      30: ifeq          49
      33: aload         6
      35: invokevirtual #446                // Method java/io/File.isDirectory:()Z
      38: ifeq          49
      41: aload         6
      43: invokevirtual #120                // Method java/io/File.list:()[Ljava/lang/String;
      46: goto          50
      49: aconst_null
      50: astore        7
      52: aload         7
      54: ifnull        122
      57: aload         7
      59: arraylength
      60: ifeq          122
      63: iconst_0
      64: istore        8
      66: iload_1
      67: ifne          76
      70: iload_2
      71: istore        8
      73: goto          84
      76: ldc_w         #447                // String Are you sure to format Bookie data..?
      79: invokestatic  #448                // Method org/apache/bookkeeper/util/IOUtils.confirmPrompt:(Ljava/lang/String;)Z
      82: istore        8
      84: iload         8
      86: ifne          102
      89: getstatic     #3                  // Field LOG:Lorg/slf4j/Logger;
      92: ldc_w         #449                // String Bookie format aborted!!
      95: invokeinterface #18,  2           // InterfaceMethod org/slf4j/Logger.error:(Ljava/lang/String;)V
     100: iconst_0
     101: ireturn
     102: goto          122
     105: astore        8
     107: getstatic     #3                  // Field LOG:Lorg/slf4j/Logger;
     110: ldc_w         #450                // String Error during bookie format
     113: aload         8
     115: invokeinterface #118,  3          // InterfaceMethod org/slf4j/Logger.error:(Ljava/lang/String;Ljava/lang/Throwable;)V
     120: iconst_0
     121: ireturn
     122: aload         6
     124: invokestatic  #451                // Method cleanDir:(Ljava/io/File;)Z
     127: ifne          143
     130: getstatic     #3                  // Field LOG:Lorg/slf4j/Logger;
     133: ldc_w         #452                // String Formatting journal directory failed
     136: invokeinterface #18,  2           // InterfaceMethod org/slf4j/Logger.error:(Ljava/lang/String;)V
     141: iconst_0
     142: ireturn
     143: iinc          5, 1
     146: goto          12
     149: aload_0
     150: invokevirtual #453                // Method org/apache/bookkeeper/conf/ServerConfiguration.getLedgerDirs:()[Ljava/io/File;
     153: astore_3
     154: aload_3
     155: astore        4
     157: aload         4
     159: arraylength
     160: istore        5
     162: iconst_0
     163: istore        6
     165: iload         6
     167: iload         5
     169: if_icmpge     230
     172: aload         4
     174: iload         6
     176: aaload
     177: astore        7
     179: aload         7
     181: invokestatic  #451                // Method cleanDir:(Ljava/io/File;)Z
     184: ifne          224
     187: getstatic     #3                  // Field LOG:Lorg/slf4j/Logger;
     190: new           #22                 // class java/lang/StringBuilder
     193: dup
     194: invokespecial #23                 // Method java/lang/StringBuilder."<init>":()V
     197: ldc_w         #454                // String Formatting ledger directory
     200: invokevirtual #25                 // Method java/lang/StringBuilder.append:(Ljava/lang/String;)Ljava/lang/StringBuilder;
     203: aload         7
     205: invokevirtual #26                 // Method java/lang/StringBuilder.append:(Ljava/lang/Object;)Ljava/lang/StringBuilder;
     208: ldc_w         #455                // String  failed
     211: invokevirtual #25                 // Method java/lang/StringBuilder.append:(Ljava/lang/String;)Ljava/lang/StringBuilder;
     214: invokevirtual #27                 // Method java/lang/StringBuilder.toString:()Ljava/lang/String;
     217: invokeinterface #18,  2           // InterfaceMethod org/slf4j/Logger.error:(Ljava/lang/String;)V
     222: iconst_0
     223: ireturn
     224: iinc          6, 1
     227: goto          165
     230: aload_0
     231: invokevirtual #456                // Method org/apache/bookkeeper/conf/ServerConfiguration.getIndexDirs:()[Ljava/io/File;
     234: astore        4
     236: aconst_null
     237: aload         4
     239: if_acmpeq     319
     242: aload         4
     244: astore        5
     246: aload         5
     248: arraylength
     249: istore        6
     251: iconst_0
     252: istore        7
     254: iload         7
     256: iload         6
     258: if_icmpge     319
     261: aload         5
     263: iload         7
     265: aaload
     266: astore        8
     268: aload         8
     270: invokestatic  #451                // Method cleanDir:(Ljava/io/File;)Z
     273: ifne          313
     276: getstatic     #3                  // Field LOG:Lorg/slf4j/Logger;
     279: new           #22                 // class java/lang/StringBuilder
     282: dup
     283: invokespecial #23                 // Method java/lang/StringBuilder."<init>":()V
     286: ldc_w         #457                // String Formatting index directory
     289: invokevirtual #25                 // Method java/lang/StringBuilder.append:(Ljava/lang/String;)Ljava/lang/StringBuilder;
     292: aload         8
     294: invokevirtual #26                 // Method java/lang/StringBuilder.append:(Ljava/lang/Object;)Ljava/lang/StringBuilder;
     297: ldc_w         #455                // String  failed
     300: invokevirtual #25                 // Method java/lang/StringBuilder.append:(Ljava/lang/String;)Ljava/lang/StringBuilder;
     303: invokevirtual #27                 // Method java/lang/StringBuilder.toString:()Ljava/lang/String;
     306: invokeinterface #18,  2           // InterfaceMethod org/slf4j/Logger.error:(Ljava/lang/String;)V
     311: iconst_0
     312: ireturn
     313: iinc          7, 1
     316: goto          254
     319: getstatic     #3                  // Field LOG:Lorg/slf4j/Logger;
     322: ldc_w         #458                // String Bookie format completed successfully
     325: invokeinterface #307,  2          // InterfaceMethod org/slf4j/Logger.info:(Ljava/lang/String;)V
     330: iconst_1
     331: ireturn
    Exception table:
       from    to  target type
          63   101   105   Class java/io/IOException

  private static boolean cleanDir(java.io.File);
    Code:
       0: aload_0
       1: invokevirtual #4                  // Method java/io/File.exists:()Z
       4: ifeq          88
       7: aload_0
       8: invokevirtual #459                // Method java/io/File.listFiles:()[Ljava/io/File;
      11: astore_1
      12: aload_1
      13: ifnull        85
      16: aload_1
      17: astore_2
      18: aload_2
      19: arraylength
      20: istore_3
      21: iconst_0
      22: istore        4
      24: iload         4
      26: iload_3
      27: if_icmpge     85
      30: aload_2
      31: iload         4
      33: aaload
      34: astore        5
      36: aload         5
      38: invokestatic  #460                // Method org/apache/commons/io/FileUtils.deleteQuietly:(Ljava/io/File;)Z
      41: istore        6
      43: iload         6
      45: ifne          79
      48: getstatic     #3                  // Field LOG:Lorg/slf4j/Logger;
      51: new           #22                 // class java/lang/StringBuilder
      54: dup
      55: invokespecial #23                 // Method java/lang/StringBuilder."<init>":()V
      58: ldc_w         #461                // String Not able to delete
      61: invokevirtual #25                 // Method java/lang/StringBuilder.append:(Ljava/lang/String;)Ljava/lang/StringBuilder;
      64: aload         5
      66: invokevirtual #26                 // Method java/lang/StringBuilder.append:(Ljava/lang/Object;)Ljava/lang/StringBuilder;
      69: invokevirtual #27                 // Method java/lang/StringBuilder.toString:()Ljava/lang/String;
      72: invokeinterface #18,  2           // InterfaceMethod org/slf4j/Logger.error:(Ljava/lang/String;)V
      77: iconst_0
      78: ireturn
      79: iinc          4, 1
      82: goto          24
      85: goto          125
      88: aload_0
      89: invokevirtual #21                 // Method java/io/File.mkdirs:()Z
      92: ifne          125
      95: getstatic     #3                  // Field LOG:Lorg/slf4j/Logger;
      98: new           #22                 // class java/lang/StringBuilder
     101: dup
     102: invokespecial #23                 // Method java/lang/StringBuilder."<init>":()V
     105: ldc_w         #462                // String Not able to create the directory
     108: invokevirtual #25                 // Method java/lang/StringBuilder.append:(Ljava/lang/String;)Ljava/lang/StringBuilder;
     111: aload_0
     112: invokevirtual #26                 // Method java/lang/StringBuilder.append:(Ljava/lang/Object;)Ljava/lang/StringBuilder;
     115: invokevirtual #27                 // Method java/lang/StringBuilder.toString:()Ljava/lang/String;
     118: invokeinterface #18,  2           // InterfaceMethod org/slf4j/Logger.error:(Ljava/lang/String;)V
     123: iconst_0
     124: ireturn
     125: iconst_1
     126: ireturn

  public int getExitCode();
    Code:
       0: aload_0
       1: getfield      #193                // Field exitCode:I
       4: ireturn

  static org.apache.bookkeeper.util.DiskChecker createDiskChecker(org.apache.bookkeeper.conf.ServerConfiguration);
    Code:
       0: new           #174                // class org/apache/bookkeeper/util/DiskChecker
       3: dup
       4: aload_0
       5: invokevirtual #175                // Method org/apache/bookkeeper/conf/ServerConfiguration.getDiskUsageThreshold:()F
       8: aload_0
       9: invokevirtual #176                // Method org/apache/bookkeeper/conf/ServerConfiguration.getDiskUsageWarnThreshold:()F
      12: invokespecial #177                // Method org/apache/bookkeeper/util/DiskChecker."<init>":(FF)V
      15: areturn

  static org.apache.bookkeeper.bookie.LedgerDirsManager createLedgerDirsManager(org.apache.bookkeeper.conf.ServerConfiguration, org.apache.bookkeeper.util.DiskChecker, org.apache.bookkeeper.stats.StatsLogger);
    Code:
       0: new           #463                // class org/apache/bookkeeper/bookie/LedgerDirsManager
       3: dup
       4: aload_0
       5: aload_0
       6: invokevirtual #453                // Method org/apache/bookkeeper/conf/ServerConfiguration.getLedgerDirs:()[Ljava/io/File;
       9: aload_1
      10: aload_2
      11: invokespecial #464                // Method org/apache/bookkeeper/bookie/LedgerDirsManager."<init>":(Lorg/apache/bookkeeper/conf/ServerConfiguration;[Ljava/io/File;Lorg/apache/bookkeeper/util/DiskChecker;Lorg/apache/bookkeeper/stats/StatsLogger;)V
      14: areturn

  static org.apache.bookkeeper.bookie.LedgerDirsManager createIndexDirsManager(org.apache.bookkeeper.conf.ServerConfiguration, org.apache.bookkeeper.util.DiskChecker, org.apache.bookkeeper.stats.StatsLogger, org.apache.bookkeeper.bookie.LedgerDirsManager);
    Code:
       0: aload_0
       1: invokevirtual #456                // Method org/apache/bookkeeper/conf/ServerConfiguration.getIndexDirs:()[Ljava/io/File;
       4: astore        4
       6: aconst_null
       7: aload         4
       9: if_acmpne     14
      12: aload_3
      13: areturn
      14: new           #463                // class org/apache/bookkeeper/bookie/LedgerDirsManager
      17: dup
      18: aload_0
      19: aload         4
      21: aload_1
      22: aload_2
      23: invokespecial #464                // Method org/apache/bookkeeper/bookie/LedgerDirsManager."<init>":(Lorg/apache/bookkeeper/conf/ServerConfiguration;[Ljava/io/File;Lorg/apache/bookkeeper/util/DiskChecker;Lorg/apache/bookkeeper/stats/StatsLogger;)V
      26: areturn

  public java.util.PrimitiveIterator$OfLong getListOfEntriesOfLedger(long) throws java.io.IOException, org.apache.bookkeeper.bookie.Bookie$NoLedgerException;
    Code:
       0: invokestatic  #402                // Method org/apache/bookkeeper/util/MathUtils.nowInNano:()J
       3: lstore_3
       4: iconst_0
       5: istore        5
       7: aload_0
       8: getfield      #248                // Field handles:Lorg/apache/bookkeeper/bookie/HandleFactory;
      11: lload_1
      12: invokeinterface #426,  3          // InterfaceMethod org/apache/bookkeeper/bookie/HandleFactory.getReadOnlyHandle:(J)Lorg/apache/bookkeeper/bookie/LedgerDescriptor;
      17: astore        6
      19: getstatic     #3                  // Field LOG:Lorg/slf4j/Logger;
      22: invokeinterface #398,  1          // InterfaceMethod org/slf4j/Logger.isTraceEnabled:()Z
      27: ifeq          45
      30: getstatic     #3                  // Field LOG:Lorg/slf4j/Logger;
      33: ldc_w         #465                // String GetEntriesOfLedger {}
      36: lload_1
      37: invokestatic  #268                // Method java/lang/Long.valueOf:(J)Ljava/lang/Long;
      40: invokeinterface #429,  3          // InterfaceMethod org/slf4j/Logger.trace:(Ljava/lang/String;Ljava/lang/Object;)V
      45: aload         6
      47: lload_1
      48: invokevirtual #466                // Method org/apache/bookkeeper/bookie/LedgerDescriptor.getListOfEntriesOfLedger:(J)Ljava/util/PrimitiveIterator$OfLong;
      51: astore        7
      53: iconst_1
      54: istore        5
      56: aload         7
      58: astore        8
      60: lload_3
      61: invokestatic  #405                // Method org/apache/bookkeeper/util/MathUtils.elapsedNanos:(J)J
      64: lstore        9
      66: iload         5
      68: ifeq          91
      71: aload_0
      72: getfield      #251                // Field bookieStats:Lorg/apache/bookkeeper/bookie/stats/BookieStats;
      75: invokevirtual #441                // Method org/apache/bookkeeper/bookie/stats/BookieStats.getReadEntryStats:()Lorg/apache/bookkeeper/stats/OpStatsLogger;
      78: lload         9
      80: getstatic     #407                // Field java/util/concurrent/TimeUnit.NANOSECONDS:Ljava/util/concurrent/TimeUnit;
      83: invokeinterface #408,  4          // InterfaceMethod org/apache/bookkeeper/stats/OpStatsLogger.registerSuccessfulEvent:(JLjava/util/concurrent/TimeUnit;)V
      88: goto          108
      91: aload_0
      92: getfield      #251                // Field bookieStats:Lorg/apache/bookkeeper/bookie/stats/BookieStats;
      95: invokevirtual #441                // Method org/apache/bookkeeper/bookie/stats/BookieStats.getReadEntryStats:()Lorg/apache/bookkeeper/stats/OpStatsLogger;
      98: lload         9
     100: getstatic     #407                // Field java/util/concurrent/TimeUnit.NANOSECONDS:Ljava/util/concurrent/TimeUnit;
     103: invokeinterface #411,  4          // InterfaceMethod org/apache/bookkeeper/stats/OpStatsLogger.registerFailedEvent:(JLjava/util/concurrent/TimeUnit;)V
     108: aload         8
     110: areturn
     111: astore        11
     113: lload_3
     114: invokestatic  #405                // Method org/apache/bookkeeper/util/MathUtils.elapsedNanos:(J)J
     117: lstore        12
     119: iload         5
     121: ifeq          144
     124: aload_0
     125: getfield      #251                // Field bookieStats:Lorg/apache/bookkeeper/bookie/stats/BookieStats;
     128: invokevirtual #441                // Method org/apache/bookkeeper/bookie/stats/BookieStats.getReadEntryStats:()Lorg/apache/bookkeeper/stats/OpStatsLogger;
     131: lload         12
     133: getstatic     #407                // Field java/util/concurrent/TimeUnit.NANOSECONDS:Ljava/util/concurrent/TimeUnit;
     136: invokeinterface #408,  4          // InterfaceMethod org/apache/bookkeeper/stats/OpStatsLogger.registerSuccessfulEvent:(JLjava/util/concurrent/TimeUnit;)V
     141: goto          161
     144: aload_0
     145: getfield      #251                // Field bookieStats:Lorg/apache/bookkeeper/bookie/stats/BookieStats;
     148: invokevirtual #441                // Method org/apache/bookkeeper/bookie/stats/BookieStats.getReadEntryStats:()Lorg/apache/bookkeeper/stats/OpStatsLogger;
     151: lload         12
     153: getstatic     #407                // Field java/util/concurrent/TimeUnit.NANOSECONDS:Ljava/util/concurrent/TimeUnit;
     156: invokeinterface #411,  4          // InterfaceMethod org/apache/bookkeeper/stats/OpStatsLogger.registerFailedEvent:(JLjava/util/concurrent/TimeUnit;)V
     161: aload         11
     163: athrow
    Exception table:
       from    to  target type
           7    60   111   any
         111   113   111   any

  private void lambda$instantiateMetadataDriver$5();
    Code:
       0: aload_0
       1: getfield      #219                // Field stateManager:Lorg/apache/bookkeeper/bookie/StateManager;
       4: invokeinterface #467,  1          // InterfaceMethod org/apache/bookkeeper/bookie/StateManager.forceToUnregistered:()V
       9: aload_0
      10: getfield      #219                // Field stateManager:Lorg/apache/bookkeeper/bookie/StateManager;
      13: iconst_0
      14: invokeinterface #325,  2          // InterfaceMethod org/apache/bookkeeper/bookie/StateManager.registerBookie:(Z)Ljava/util/concurrent/Future;
      19: pop
      20: return

  private static boolean lambda$replay$4(org.apache.bookkeeper.bookie.LogMark, long);
    Code:
       0: lload_1
       1: aload_0
       2: invokevirtual #274                // Method org/apache/bookkeeper/bookie/LogMark.getLogFileId:()J
       5: lcmp
       6: iflt          13
       9: iconst_1
      10: goto          14
      13: iconst_0
      14: ireturn

  private void lambda$new$3(int);
    Code:
       0: aload_0
       1: iload_1
       2: invokevirtual #348                // Method triggerBookieShutdown:(I)V
       5: return

  private static java.io.File lambda$getKnownDirs$2(java.lang.String);
    Code:
       0: new           #6                  // class java/io/File
       3: dup
       4: aload_0
       5: invokespecial #468                // Method java/io/File."<init>":(Ljava/lang/String;)V
       8: areturn

  private static java.util.stream.Stream lambda$getKnownDirs$1(org.apache.bookkeeper.bookie.Cookie);
    Code:
       0: aload_0
       1: invokevirtual #469                // Method org/apache/bookkeeper/bookie/Cookie.getLedgerDirPathsFromCookie:()[Ljava/lang/String;
       4: invokestatic  #470                // Method java/util/Arrays.stream:([Ljava/lang/Object;)Ljava/util/stream/Stream;
       7: areturn

  private static void lambda$checkIfDirsOnSameDiskPartition$0(boolean, org.apache.commons.lang3.mutable.MutableBoolean, java.nio.file.FileStore, java.util.List);
    Code:
       0: aload_3
       1: invokeinterface #31,  1           // InterfaceMethod java/util/List.size:()I
       6: iconst_1
       7: if_icmple     48
      10: iload_0
      11: ifeq          30
      14: getstatic     #3                  // Field LOG:Lorg/slf4j/Logger;
      17: ldc_w         #471                // String Dirs: {} are in same DiskPartition/FileSystem: {}
      20: aload_3
      21: aload_2
      22: invokeinterface #472,  4          // InterfaceMethod org/slf4j/Logger.warn:(Ljava/lang/String;Ljava/lang/Object;Ljava/lang/Object;)V
      27: goto          48
      30: getstatic     #3                  // Field LOG:Lorg/slf4j/Logger;
      33: ldc_w         #471                // String Dirs: {} are in same DiskPartition/FileSystem: {}
      36: aload_3
      37: aload_2
      38: invokeinterface #473,  4          // InterfaceMethod org/slf4j/Logger.error:(Ljava/lang/String;Ljava/lang/Object;Ljava/lang/Object;)V
      43: aload_1
      44: iconst_1
      45: invokevirtual #474                // Method org/apache/commons/lang3/mutable/MutableBoolean.setValue:(Z)V
      48: return

  static org.slf4j.Logger access$000();
    Code:
       0: getstatic     #3                  // Field LOG:Lorg/slf4j/Logger;
       3: areturn

  static org.apache.bookkeeper.util.collections.ConcurrentLongHashMap access$100(org.apache.bookkeeper.bookie.Bookie);
    Code:
       0: aload_0
       1: getfield      #2                  // Field masterKeyCache:Lorg/apache/bookkeeper/util/collections/ConcurrentLongHashMap;
       4: areturn

  static {};
    Code:
       0: ldc_w         #387                // class org/apache/bookkeeper/bookie/Bookie
       3: invokestatic  #475                // Method org/slf4j/LoggerFactory.getLogger:(Ljava/lang/Class;)Lorg/slf4j/Logger;
       6: putstatic     #3                  // Field LOG:Lorg/slf4j/Logger;
       9: return
}
