Compiled from "Bookie.java"
class org.apache.bookkeeper.bookie.Bookie$NopWriteCallback implements org.apache.bookkeeper.proto.BookkeeperInternalCallbacks$WriteCallback {
  org.apache.bookkeeper.bookie.Bookie$NopWriteCallback();
    Code:
       0: aload_0
       1: invokespecial #1                  // Method java/lang/Object."<init>":()V
       4: return

  public void writeComplete(int, long, long, org.apache.bookkeeper.net.BookieId, java.lang.Object);
    Code:
       0: invokestatic  #2                  // Method org/apache/bookkeeper/bookie/Bookie.access$000:()Lorg/slf4j/Logger;
       3: invokeinterface #3,  1            // InterfaceMethod org/slf4j/Logger.isDebugEnabled:()Z
       8: ifeq          52
      11: invokestatic  #2                  // Method org/apache/bookkeeper/bookie/Bookie.access$000:()Lorg/slf4j/Logger;
      14: ldc           #4                  // String Finished writing entry {} @ ledger {} for {} : {}
      16: iconst_4
      17: anewarray     #5                  // class java/lang/Object
      20: dup
      21: iconst_0
      22: lload         4
      24: invokestatic  #6                  // Method java/lang/Long.valueOf:(J)Ljava/lang/Long;
      27: aastore
      28: dup
      29: iconst_1
      30: lload_2
      31: invokestatic  #6                  // Method java/lang/Long.valueOf:(J)Ljava/lang/Long;
      34: aastore
      35: dup
      36: iconst_2
      37: aload         6
      39: aastore
      40: dup
      41: iconst_3
      42: iload_1
      43: invokestatic  #7                  // Method java/lang/Integer.valueOf:(I)Ljava/lang/Integer;
      46: aastore
      47: invokeinterface #8,  3            // InterfaceMethod org/slf4j/Logger.debug:(Ljava/lang/String;[Ljava/lang/Object;)V
      52: return
}
