Compiled from "BookieStateManager.java"
class org.apache.bookkeeper.bookie.BookieStateManager$3 implements java.util.concurrent.Callable<java.lang.Void> {
  final org.apache.bookkeeper.bookie.BookieStateManager this$0;

  org.apache.bookkeeper.bookie.BookieStateManager$3(org.apache.bookkeeper.bookie.BookieStateManager);
    Code:
       0: aload_0
       1: aload_1
       2: putfield      #1                  // Field this$0:Lorg/apache/bookkeeper/bookie/BookieStateManager;
       5: aload_0
       6: invokespecial #2                  // Method java/lang/Object."<init>":()V
       9: return

  public java.lang.Void call() throws java.lang.Exception;
    Code:
       0: aload_0
       1: getfield      #1                  // Field this$0:Lorg/apache/bookkeeper/bookie/BookieStateManager;
       4: invokevirtual #3                  // Method org/apache/bookkeeper/bookie/BookieStateManager.doTransitionToWritableMode:()V
       7: aconst_null
       8: areturn

  public java.lang.Object call() throws java.lang.Exception;
    Code:
       0: aload_0
       1: invokevirtual #4                  // Method call:()Ljava/lang/Void;
       4: areturn
}
