Compiled from "BookieShell.java"
class org.apache.bookkeeper.bookie.BookieShell$ListLedgersCmd extends org.apache.bookkeeper.bookie.BookieShell$MyCommand {
  org.apache.commons.cli.Options lOpts;

  final org.apache.bookkeeper.bookie.BookieShell this$0;

  org.apache.bookkeeper.bookie.BookieShell$ListLedgersCmd(org.apache.bookkeeper.bookie.BookieShell);
    Code:
       0: aload_0
       1: aload_1
       2: putfield      #2                  // Field this$0:Lorg/apache/bookkeeper/bookie/BookieShell;
       5: aload_0
       6: aload_1
       7: ldc           #3                  // String listledgers
       9: invokespecial #4                  // Method org/apache/bookkeeper/bookie/BookieShell$MyCommand."<init>":(Lorg/apache/bookkeeper/bookie/BookieShell;Ljava/lang/String;)V
      12: aload_0
      13: new           #5                  // class org/apache/commons/cli/Options
      16: dup
      17: invokespecial #6                  // Method org/apache/commons/cli/Options."<init>":()V
      20: putfield      #7                  // Field lOpts:Lorg/apache/commons/cli/Options;
      23: aload_0
      24: getfield      #7                  // Field lOpts:Lorg/apache/commons/cli/Options;
      27: ldc           #8                  // String m
      29: ldc           #9                  // String meta
      31: iconst_0
      32: ldc           #10                 // String Print metadata
      34: invokevirtual #11                 // Method org/apache/commons/cli/Options.addOption:(Ljava/lang/String;Ljava/lang/String;ZLjava/lang/String;)Lorg/apache/commons/cli/Options;
      37: pop
      38: aload_0
      39: getfield      #7                  // Field lOpts:Lorg/apache/commons/cli/Options;
      42: ldc           #12                 // String bookieid
      44: iconst_1
      45: ldc           #13                 // String List ledgers residing in this bookie
      47: invokevirtual #14                 // Method org/apache/commons/cli/Options.addOption:(Ljava/lang/String;ZLjava/lang/String;)Lorg/apache/commons/cli/Options;
      50: pop
      51: return

  public int runCmd(org.apache.commons.cli.CommandLine) throws java.lang.Exception;
    Code:
       0: aload_1
       1: ldc           #8                  // String m
       3: invokevirtual #15                 // Method org/apache/commons/cli/CommandLine.hasOption:(Ljava/lang/String;)Z
       6: istore_2
       7: aload_1
       8: ldc           #12                 // String bookieid
      10: invokevirtual #16                 // Method org/apache/commons/cli/CommandLine.getOptionValue:(Ljava/lang/String;)Ljava/lang/String;
      13: astore_3
      14: new           #17                 // class org/apache/bookkeeper/tools/cli/commands/bookie/ListLedgersCommand$ListLedgersFlags
      17: dup
      18: invokespecial #18                 // Method org/apache/bookkeeper/tools/cli/commands/bookie/ListLedgersCommand$ListLedgersFlags."<init>":()V
      21: aload_3
      22: invokevirtual #19                 // Method org/apache/bookkeeper/tools/cli/commands/bookie/ListLedgersCommand$ListLedgersFlags.bookieId:(Ljava/lang/String;)Lorg/apache/bookkeeper/tools/cli/commands/bookie/ListLedgersCommand$ListLedgersFlags;
      25: iload_2
      26: invokevirtual #20                 // Method org/apache/bookkeeper/tools/cli/commands/bookie/ListLedgersCommand$ListLedgersFlags.meta:(Z)Lorg/apache/bookkeeper/tools/cli/commands/bookie/ListLedgersCommand$ListLedgersFlags;
      29: astore        4
      31: new           #21                 // class org/apache/bookkeeper/tools/cli/commands/bookie/ListLedgersCommand
      34: dup
      35: aload_0
      36: getfield      #2                  // Field this$0:Lorg/apache/bookkeeper/bookie/BookieShell;
      39: getfield      #22                 // Field org/apache/bookkeeper/bookie/BookieShell.ledgerIdFormatter:Lorg/apache/bookkeeper/util/LedgerIdFormatter;
      42: invokespecial #23                 // Method org/apache/bookkeeper/tools/cli/commands/bookie/ListLedgersCommand."<init>":(Lorg/apache/bookkeeper/util/LedgerIdFormatter;)V
      45: astore        5
      47: aload         5
      49: aload_0
      50: getfield      #2                  // Field this$0:Lorg/apache/bookkeeper/bookie/BookieShell;
      53: getfield      #24                 // Field org/apache/bookkeeper/bookie/BookieShell.bkConf:Lorg/apache/bookkeeper/conf/ServerConfiguration;
      56: aload         4
      58: invokevirtual #25                 // Method org/apache/bookkeeper/tools/cli/commands/bookie/ListLedgersCommand.apply:(Lorg/apache/bookkeeper/conf/ServerConfiguration;Lorg/apache/bookkeeper/tools/cli/commands/bookie/ListLedgersCommand$ListLedgersFlags;)Z
      61: pop
      62: iconst_0
      63: ireturn

  java.lang.String getDescription();
    Code:
       0: ldc           #26                 // String List all ledgers on the cluster (this may take a long time).
       2: areturn

  java.lang.String getUsage();
    Code:
       0: ldc           #27                 // String listledgers  [-meta] [-bookieid <bookieaddress>]
       2: areturn

  org.apache.commons.cli.Options getOptions();
    Code:
       0: aload_0
       1: getfield      #7                  // Field lOpts:Lorg/apache/commons/cli/Options;
       4: areturn
}
