Compiled from "EntryLogger.java"
class org.apache.bookkeeper.bookie.EntryLogger$BufferedLogChannel$1 implements org.apache.bookkeeper.util.collections.ConcurrentLongLongHashMap$BiConsumerLong {
  int remainingLedgers;

  boolean startNewBatch;

  int remainingInBatch;

  final int val$numberOfLedgers;

  final io.netty.buffer.ByteBuf val$serializedMap;

  final org.apache.bookkeeper.bookie.EntryLogger$BufferedLogChannel this$0;

  org.apache.bookkeeper.bookie.EntryLogger$BufferedLogChannel$1(org.apache.bookkeeper.bookie.EntryLogger$BufferedLogChannel, int, io.netty.buffer.ByteBuf);
    Code:
       0: aload_0
       1: aload_1
       2: putfield      #2                  // Field this$0:Lorg/apache/bookkeeper/bookie/EntryLogger$BufferedLogChannel;
       5: aload_0
       6: iload_2
       7: putfield      #3                  // Field val$numberOfLedgers:I
      10: aload_0
      11: aload_3
      12: putfield      #4                  // Field val$serializedMap:Lio/netty/buffer/ByteBuf;
      15: aload_0
      16: invokespecial #5                  // Method java/lang/Object."<init>":()V
      19: aload_0
      20: aload_0
      21: getfield      #3                  // Field val$numberOfLedgers:I
      24: putfield      #6                  // Field remainingLedgers:I
      27: aload_0
      28: iconst_1
      29: putfield      #7                  // Field startNewBatch:Z
      32: aload_0
      33: iconst_0
      34: putfield      #8                  // Field remainingInBatch:I
      37: return

  public void accept(long, long);
    Code:
       0: aload_0
       1: getfield      #7                  // Field startNewBatch:Z
       4: ifeq          92
       7: aload_0
       8: getfield      #6                  // Field remainingLedgers:I
      11: sipush        10000
      14: invokestatic  #9                  // Method java/lang/Math.min:(II)I
      17: istore        5
      19: bipush        24
      21: bipush        16
      23: iload         5
      25: imul
      26: iadd
      27: istore        6
      29: aload_0
      30: getfield      #4                  // Field val$serializedMap:Lio/netty/buffer/ByteBuf;
      33: invokevirtual #10                 // Method io/netty/buffer/ByteBuf.clear:()Lio/netty/buffer/ByteBuf;
      36: pop
      37: aload_0
      38: getfield      #4                  // Field val$serializedMap:Lio/netty/buffer/ByteBuf;
      41: iload         6
      43: iconst_4
      44: isub
      45: invokevirtual #11                 // Method io/netty/buffer/ByteBuf.writeInt:(I)Lio/netty/buffer/ByteBuf;
      48: pop
      49: aload_0
      50: getfield      #4                  // Field val$serializedMap:Lio/netty/buffer/ByteBuf;
      53: ldc2_w        #12                 // long -1l
      56: invokevirtual #14                 // Method io/netty/buffer/ByteBuf.writeLong:(J)Lio/netty/buffer/ByteBuf;
      59: pop
      60: aload_0
      61: getfield      #4                  // Field val$serializedMap:Lio/netty/buffer/ByteBuf;
      64: ldc2_w        #15                 // long -2l
      67: invokevirtual #14                 // Method io/netty/buffer/ByteBuf.writeLong:(J)Lio/netty/buffer/ByteBuf;
      70: pop
      71: aload_0
      72: getfield      #4                  // Field val$serializedMap:Lio/netty/buffer/ByteBuf;
      75: iload         5
      77: invokevirtual #11                 // Method io/netty/buffer/ByteBuf.writeInt:(I)Lio/netty/buffer/ByteBuf;
      80: pop
      81: aload_0
      82: iconst_0
      83: putfield      #7                  // Field startNewBatch:Z
      86: aload_0
      87: iload         5
      89: putfield      #8                  // Field remainingInBatch:I
      92: aload_0
      93: getfield      #4                  // Field val$serializedMap:Lio/netty/buffer/ByteBuf;
      96: lload_1
      97: invokevirtual #14                 // Method io/netty/buffer/ByteBuf.writeLong:(J)Lio/netty/buffer/ByteBuf;
     100: pop
     101: aload_0
     102: getfield      #4                  // Field val$serializedMap:Lio/netty/buffer/ByteBuf;
     105: lload_3
     106: invokevirtual #14                 // Method io/netty/buffer/ByteBuf.writeLong:(J)Lio/netty/buffer/ByteBuf;
     109: pop
     110: aload_0
     111: dup
     112: getfield      #6                  // Field remainingLedgers:I
     115: iconst_1
     116: isub
     117: putfield      #6                  // Field remainingLedgers:I
     120: aload_0
     121: dup
     122: getfield      #8                  // Field remainingInBatch:I
     125: iconst_1
     126: isub
     127: dup_x1
     128: putfield      #8                  // Field remainingInBatch:I
     131: ifne          165
     134: aload_0
     135: getfield      #2                  // Field this$0:Lorg/apache/bookkeeper/bookie/EntryLogger$BufferedLogChannel;
     138: aload_0
     139: getfield      #4                  // Field val$serializedMap:Lio/netty/buffer/ByteBuf;
     142: invokevirtual #17                 // Method org/apache/bookkeeper/bookie/EntryLogger$BufferedLogChannel.write:(Lio/netty/buffer/ByteBuf;)V
     145: goto          160
     148: astore        5
     150: new           #19                 // class java/lang/RuntimeException
     153: dup
     154: aload         5
     156: invokespecial #20                 // Method java/lang/RuntimeException."<init>":(Ljava/lang/Throwable;)V
     159: athrow
     160: aload_0
     161: iconst_1
     162: putfield      #7                  // Field startNewBatch:Z
     165: return
    Exception table:
       from    to  target type
         134   145   148   Class java/io/IOException
}
