Compiled from "Journal.java"
class org.apache.bookkeeper.bookie.Journal$QueueEntry implements java.lang.Runnable {
  io.netty.buffer.ByteBuf entry;

  long ledgerId;

  long entryId;

  org.apache.bookkeeper.proto.BookkeeperInternalCallbacks$WriteCallback cb;

  java.lang.Object ctx;

  long enqueueTime;

  boolean ackBeforeSync;

  org.apache.bookkeeper.stats.OpStatsLogger journalAddEntryStats;

  org.apache.bookkeeper.stats.Counter journalCbQueueSize;

  private final io.netty.util.Recycler$Handle<org.apache.bookkeeper.bookie.Journal$QueueEntry> recyclerHandle;

  private static final io.netty.util.Recycler<org.apache.bookkeeper.bookie.Journal$QueueEntry> RECYCLER;

  static org.apache.bookkeeper.bookie.Journal$QueueEntry create(io.netty.buffer.ByteBuf, boolean, long, long, org.apache.bookkeeper.proto.BookkeeperInternalCallbacks$WriteCallback, java.lang.Object, long, org.apache.bookkeeper.stats.OpStatsLogger, org.apache.bookkeeper.stats.Counter);
    Code:
       0: getstatic     #2                  // Field RECYCLER:Lio/netty/util/Recycler;
       3: invokevirtual #3                  // Method io/netty/util/Recycler.get:()Ljava/lang/Object;
       6: checkcast     #4                  // class org/apache/bookkeeper/bookie/Journal$QueueEntry
       9: astore        12
      11: aload         12
      13: aload_0
      14: putfield      #5                  // Field entry:Lio/netty/buffer/ByteBuf;
      17: aload         12
      19: iload_1
      20: putfield      #6                  // Field ackBeforeSync:Z
      23: aload         12
      25: aload         6
      27: putfield      #7                  // Field cb:Lorg/apache/bookkeeper/proto/BookkeeperInternalCallbacks$WriteCallback;
      30: aload         12
      32: aload         7
      34: putfield      #8                  // Field ctx:Ljava/lang/Object;
      37: aload         12
      39: lload_2
      40: putfield      #9                  // Field ledgerId:J
      43: aload         12
      45: lload         4
      47: putfield      #10                 // Field entryId:J
      50: aload         12
      52: lload         8
      54: putfield      #11                 // Field enqueueTime:J
      57: aload         12
      59: aload         10
      61: putfield      #12                 // Field journalAddEntryStats:Lorg/apache/bookkeeper/stats/OpStatsLogger;
      64: aload         12
      66: aload         11
      68: putfield      #13                 // Field journalCbQueueSize:Lorg/apache/bookkeeper/stats/Counter;
      71: aload         12
      73: areturn

  public void run();
    Code:
       0: invokestatic  #14                 // Method org/apache/bookkeeper/bookie/Journal.access$000:()Lorg/slf4j/Logger;
       3: invokeinterface #15,  1           // InterfaceMethod org/slf4j/Logger.isDebugEnabled:()Z
       8: ifeq          35
      11: invokestatic  #14                 // Method org/apache/bookkeeper/bookie/Journal.access$000:()Lorg/slf4j/Logger;
      14: ldc           #16                 // String Acknowledge Ledger: {}, Entry: {}
      16: aload_0
      17: getfield      #9                  // Field ledgerId:J
      20: invokestatic  #17                 // Method java/lang/Long.valueOf:(J)Ljava/lang/Long;
      23: aload_0
      24: getfield      #10                 // Field entryId:J
      27: invokestatic  #17                 // Method java/lang/Long.valueOf:(J)Ljava/lang/Long;
      30: invokeinterface #18,  4           // InterfaceMethod org/slf4j/Logger.debug:(Ljava/lang/String;Ljava/lang/Object;Ljava/lang/Object;)V
      35: aload_0
      36: getfield      #13                 // Field journalCbQueueSize:Lorg/apache/bookkeeper/stats/Counter;
      39: invokeinterface #19,  1           // InterfaceMethod org/apache/bookkeeper/stats/Counter.dec:()V
      44: aload_0
      45: getfield      #12                 // Field journalAddEntryStats:Lorg/apache/bookkeeper/stats/OpStatsLogger;
      48: aload_0
      49: getfield      #11                 // Field enqueueTime:J
      52: invokestatic  #20                 // Method org/apache/bookkeeper/util/MathUtils.elapsedNanos:(J)J
      55: getstatic     #21                 // Field java/util/concurrent/TimeUnit.NANOSECONDS:Ljava/util/concurrent/TimeUnit;
      58: invokeinterface #22,  4           // InterfaceMethod org/apache/bookkeeper/stats/OpStatsLogger.registerSuccessfulEvent:(JLjava/util/concurrent/TimeUnit;)V
      63: aload_0
      64: getfield      #7                  // Field cb:Lorg/apache/bookkeeper/proto/BookkeeperInternalCallbacks$WriteCallback;
      67: iconst_0
      68: aload_0
      69: getfield      #9                  // Field ledgerId:J
      72: aload_0
      73: getfield      #10                 // Field entryId:J
      76: aconst_null
      77: aload_0
      78: getfield      #8                  // Field ctx:Ljava/lang/Object;
      81: invokeinterface #23,  8           // InterfaceMethod org/apache/bookkeeper/proto/BookkeeperInternalCallbacks$WriteCallback.writeComplete:(IJJLorg/apache/bookkeeper/net/BookieId;Ljava/lang/Object;)V
      86: aload_0
      87: invokespecial #24                 // Method recycle:()V
      90: return

  private org.apache.bookkeeper.bookie.Journal$QueueEntry(io.netty.util.Recycler$Handle<org.apache.bookkeeper.bookie.Journal$QueueEntry>);
    Code:
       0: aload_0
       1: invokespecial #25                 // Method java/lang/Object."<init>":()V
       4: aload_0
       5: aload_1
       6: putfield      #26                 // Field recyclerHandle:Lio/netty/util/Recycler$Handle;
       9: return

  private void recycle();
    Code:
       0: aload_0
       1: getfield      #26                 // Field recyclerHandle:Lio/netty/util/Recycler$Handle;
       4: aload_0
       5: invokeinterface #27,  2           // InterfaceMethod io/netty/util/Recycler$Handle.recycle:(Ljava/lang/Object;)V
      10: return

  org.apache.bookkeeper.bookie.Journal$QueueEntry(io.netty.util.Recycler$Handle, org.apache.bookkeeper.bookie.Journal$1);
    Code:
       0: aload_0
       1: aload_1
       2: invokespecial #1                  // Method "<init>":(Lio/netty/util/Recycler$Handle;)V
       5: return

  static {};
    Code:
       0: new           #28                 // class org/apache/bookkeeper/bookie/Journal$QueueEntry$1
       3: dup
       4: invokespecial #29                 // Method org/apache/bookkeeper/bookie/Journal$QueueEntry$1."<init>":()V
       7: putstatic     #2                  // Field RECYCLER:Lio/netty/util/Recycler;
      10: return
}
