Compiled from "Journal.java"
class org.apache.bookkeeper.bookie.Journal$ForceWriteThread extends org.apache.bookkeeper.bookie.BookieCriticalThread {
  volatile boolean running;

  java.lang.Thread threadToNotifyOnEx;

  private final boolean enableGroupForceWrites;

  final org.apache.bookkeeper.bookie.Journal this$0;

  public org.apache.bookkeeper.bookie.Journal$ForceWriteThread(org.apache.bookkeeper.bookie.Journal, java.lang.Thread, boolean);
    Code:
       0: aload_0
       1: aload_1
       2: putfield      #1                  // Field this$0:Lorg/apache/bookkeeper/bookie/Journal;
       5: aload_0
       6: ldc           #2                  // String ForceWriteThread
       8: invokespecial #3                  // Method org/apache/bookkeeper/bookie/BookieCriticalThread."<init>":(Ljava/lang/String;)V
      11: aload_0
      12: iconst_1
      13: putfield      #4                  // Field running:Z
      16: aload_0
      17: aload_2
      18: putfield      #5                  // Field threadToNotifyOnEx:Ljava/lang/Thread;
      21: aload_0
      22: iload_3
      23: putfield      #6                  // Field enableGroupForceWrites:Z
      26: return

  public void run();
    Code:
       0: invokestatic  #7                  // Method org/apache/bookkeeper/bookie/Journal.access$000:()Lorg/slf4j/Logger;
       3: ldc           #8                  // String ForceWrite Thread started
       5: invokeinterface #9,  2            // InterfaceMethod org/slf4j/Logger.info:(Ljava/lang/String;)V
      10: aload_0
      11: getfield      #1                  // Field this$0:Lorg/apache/bookkeeper/bookie/Journal;
      14: getfield      #10                 // Field org/apache/bookkeeper/bookie/Journal.conf:Lorg/apache/bookkeeper/conf/ServerConfiguration;
      17: invokevirtual #11                 // Method org/apache/bookkeeper/conf/ServerConfiguration.isBusyWaitEnabled:()Z
      20: ifeq          45
      23: invokestatic  #12                 // Method org/apache/bookkeeper/common/util/affinity/CpuAffinity.acquireCore:()V
      26: goto          45
      29: astore_1
      30: invokestatic  #7                  // Method org/apache/bookkeeper/bookie/Journal.access$000:()Lorg/slf4j/Logger;
      33: ldc           #14                 // String Unable to acquire CPU core for Journal ForceWrite thread: {}
      35: aload_1
      36: invokevirtual #15                 // Method java/lang/Exception.getMessage:()Ljava/lang/String;
      39: aload_1
      40: invokeinterface #16,  4           // InterfaceMethod org/slf4j/Logger.warn:(Ljava/lang/String;Ljava/lang/Object;Ljava/lang/Object;)V
      45: iconst_1
      46: istore_1
      47: iconst_0
      48: istore_2
      49: aload_0
      50: getfield      #4                  // Field running:Z
      53: ifeq          285
      56: aconst_null
      57: astore_3
      58: aload_0
      59: getfield      #1                  // Field this$0:Lorg/apache/bookkeeper/bookie/Journal;
      62: getfield      #17                 // Field org/apache/bookkeeper/bookie/Journal.forceWriteRequests:Ljava/util/concurrent/BlockingQueue;
      65: invokeinterface #18,  1           // InterfaceMethod java/util/concurrent/BlockingQueue.take:()Ljava/lang/Object;
      70: checkcast     #19                 // class org/apache/bookkeeper/bookie/Journal$ForceWriteRequest
      73: astore_3
      74: aload_3
      75: invokestatic  #20                 // Method org/apache/bookkeeper/bookie/Journal$ForceWriteRequest.access$1200:(Lorg/apache/bookkeeper/bookie/Journal$ForceWriteRequest;)Z
      78: ifne          143
      81: iload_1
      82: ifeq          143
      85: aload_0
      86: getfield      #6                  // Field enableGroupForceWrites:Z
      89: ifeq          120
      92: aload_0
      93: getfield      #1                  // Field this$0:Lorg/apache/bookkeeper/bookie/Journal;
      96: getfield      #17                 // Field org/apache/bookkeeper/bookie/Journal.forceWriteRequests:Ljava/util/concurrent/BlockingQueue;
      99: aload_0
     100: getfield      #1                  // Field this$0:Lorg/apache/bookkeeper/bookie/Journal;
     103: aload_3
     104: invokestatic  #21                 // Method org/apache/bookkeeper/bookie/Journal$ForceWriteRequest.access$800:(Lorg/apache/bookkeeper/bookie/Journal$ForceWriteRequest;)Lorg/apache/bookkeeper/bookie/JournalChannel;
     107: lconst_0
     108: lconst_0
     109: aconst_null
     110: iconst_0
     111: iconst_1
     112: invokestatic  #22                 // Method org/apache/bookkeeper/bookie/Journal.access$1500:(Lorg/apache/bookkeeper/bookie/Journal;Lorg/apache/bookkeeper/bookie/JournalChannel;JJLorg/apache/bookkeeper/common/collections/RecyclableArrayList;ZZ)Lorg/apache/bookkeeper/bookie/Journal$ForceWriteRequest;
     115: invokeinterface #23,  2           // InterfaceMethod java/util/concurrent/BlockingQueue.put:(Ljava/lang/Object;)V
     120: iload_2
     121: ifle          143
     124: aload_0
     125: getfield      #1                  // Field this$0:Lorg/apache/bookkeeper/bookie/Journal;
     128: invokestatic  #24                 // Method org/apache/bookkeeper/bookie/Journal.access$400:(Lorg/apache/bookkeeper/bookie/Journal;)Lorg/apache/bookkeeper/bookie/stats/JournalStats;
     131: invokevirtual #25                 // Method org/apache/bookkeeper/bookie/stats/JournalStats.getForceWriteGroupingCountStats:()Lorg/apache/bookkeeper/stats/OpStatsLogger;
     134: iload_2
     135: i2l
     136: invokeinterface #26,  3           // InterfaceMethod org/apache/bookkeeper/stats/OpStatsLogger.registerSuccessfulValue:(J)V
     141: iconst_0
     142: istore_2
     143: iload_2
     144: aload_3
     145: iload_1
     146: invokevirtual #27                 // Method org/apache/bookkeeper/bookie/Journal$ForceWriteRequest.process:(Z)I
     149: iadd
     150: istore_2
     151: aload_0
     152: getfield      #6                  // Field enableGroupForceWrites:Z
     155: ifeq          177
     158: aload_3
     159: invokestatic  #20                 // Method org/apache/bookkeeper/bookie/Journal$ForceWriteRequest.access$1200:(Lorg/apache/bookkeeper/bookie/Journal$ForceWriteRequest;)Z
     162: ifne          177
     165: aload_3
     166: invokestatic  #28                 // Method org/apache/bookkeeper/bookie/Journal$ForceWriteRequest.access$1100:(Lorg/apache/bookkeeper/bookie/Journal$ForceWriteRequest;)Z
     169: ifne          177
     172: iconst_0
     173: istore_1
     174: goto          179
     177: iconst_1
     178: istore_1
     179: aload_3
     180: ifnull        282
     183: aload_3
     184: invokestatic  #29                 // Method org/apache/bookkeeper/bookie/Journal$ForceWriteRequest.access$1600:(Lorg/apache/bookkeeper/bookie/Journal$ForceWriteRequest;)V
     187: goto          282
     190: astore        4
     192: invokestatic  #7                  // Method org/apache/bookkeeper/bookie/Journal.access$000:()Lorg/slf4j/Logger;
     195: ldc           #31                 // String I/O exception in ForceWrite thread
     197: aload         4
     199: invokeinterface #32,  3           // InterfaceMethod org/slf4j/Logger.error:(Ljava/lang/String;Ljava/lang/Throwable;)V
     204: aload_0
     205: iconst_0
     206: putfield      #4                  // Field running:Z
     209: aload_3
     210: ifnull        282
     213: aload_3
     214: invokestatic  #29                 // Method org/apache/bookkeeper/bookie/Journal$ForceWriteRequest.access$1600:(Lorg/apache/bookkeeper/bookie/Journal$ForceWriteRequest;)V
     217: goto          282
     220: astore        4
     222: invokestatic  #34                 // Method java/lang/Thread.currentThread:()Ljava/lang/Thread;
     225: invokevirtual #35                 // Method java/lang/Thread.interrupt:()V
     228: invokestatic  #7                  // Method org/apache/bookkeeper/bookie/Journal.access$000:()Lorg/slf4j/Logger;
     231: ldc           #36                 // String ForceWrite thread interrupted
     233: invokeinterface #9,  2            // InterfaceMethod org/slf4j/Logger.info:(Ljava/lang/String;)V
     238: aconst_null
     239: aload_3
     240: if_acmpeq     253
     243: aload_3
     244: iconst_1
     245: invokestatic  #37                 // Method org/apache/bookkeeper/bookie/Journal$ForceWriteRequest.access$1102:(Lorg/apache/bookkeeper/bookie/Journal$ForceWriteRequest;Z)Z
     248: pop
     249: aload_3
     250: invokevirtual #38                 // Method org/apache/bookkeeper/bookie/Journal$ForceWriteRequest.closeFileIfNecessary:()V
     253: aload_0
     254: iconst_0
     255: putfield      #4                  // Field running:Z
     258: aload_3
     259: ifnull        282
     262: aload_3
     263: invokestatic  #29                 // Method org/apache/bookkeeper/bookie/Journal$ForceWriteRequest.access$1600:(Lorg/apache/bookkeeper/bookie/Journal$ForceWriteRequest;)V
     266: goto          282
     269: astore        5
     271: aload_3
     272: ifnull        279
     275: aload_3
     276: invokestatic  #29                 // Method org/apache/bookkeeper/bookie/Journal$ForceWriteRequest.access$1600:(Lorg/apache/bookkeeper/bookie/Journal$ForceWriteRequest;)V
     279: aload         5
     281: athrow
     282: goto          49
     285: aload_0
     286: getfield      #5                  // Field threadToNotifyOnEx:Ljava/lang/Thread;
     289: invokevirtual #35                 // Method java/lang/Thread.interrupt:()V
     292: return
    Exception table:
       from    to  target type
          23    26    29   Class java/lang/Exception
          58   179   190   Class java/io/IOException
          58   179   220   Class java/lang/InterruptedException
          58   179   269   any
         190   209   269   any
         220   258   269   any
         269   271   269   any

  void shutdown() throws java.lang.InterruptedException;
    Code:
       0: aload_0
       1: iconst_0
       2: putfield      #4                  // Field running:Z
       5: aload_0
       6: invokevirtual #39                 // Method interrupt:()V
       9: aload_0
      10: invokevirtual #40                 // Method join:()V
      13: return
}
