Compiled from "SortedLedgerStorage.java"
public class org.apache.bookkeeper.bookie.SortedLedgerStorage implements org.apache.bookkeeper.bookie.LedgerStorage,org.apache.bookkeeper.bookie.CacheCallback,org.apache.bookkeeper.bookie.SkipListFlusher,org.apache.bookkeeper.bookie.CompactableLedgerStorage,org.apache.bookkeeper.bookie.EntryLogger$EntryLogListener {
  private static final org.slf4j.Logger LOG;

  org.apache.bookkeeper.bookie.EntryMemTable memTable;

  private java.util.concurrent.ScheduledExecutorService scheduler;

  private org.apache.bookkeeper.bookie.StateManager stateManager;

  private final org.apache.bookkeeper.bookie.InterleavedLedgerStorage interleavedLedgerStorage;

  public org.apache.bookkeeper.bookie.SortedLedgerStorage();
    Code:
       0: aload_0
       1: new           #4                  // class org/apache/bookkeeper/bookie/InterleavedLedgerStorage
       4: dup
       5: invokespecial #5                  // Method org/apache/bookkeeper/bookie/InterleavedLedgerStorage."<init>":()V
       8: invokespecial #6                  // Method "<init>":(Lorg/apache/bookkeeper/bookie/InterleavedLedgerStorage;)V
      11: return

  protected org.apache.bookkeeper.bookie.SortedLedgerStorage(org.apache.bookkeeper.bookie.InterleavedLedgerStorage);
    Code:
       0: aload_0
       1: invokespecial #7                  // Method java/lang/Object."<init>":()V
       4: aload_0
       5: aload_1
       6: putfield      #2                  // Field interleavedLedgerStorage:Lorg/apache/bookkeeper/bookie/InterleavedLedgerStorage;
       9: return

  public void initialize(org.apache.bookkeeper.conf.ServerConfiguration, org.apache.bookkeeper.meta.LedgerManager, org.apache.bookkeeper.bookie.LedgerDirsManager, org.apache.bookkeeper.bookie.LedgerDirsManager, org.apache.bookkeeper.bookie.StateManager, org.apache.bookkeeper.bookie.CheckpointSource, org.apache.bookkeeper.bookie.Checkpointer, org.apache.bookkeeper.stats.StatsLogger, io.netty.buffer.ByteBufAllocator) throws java.io.IOException;
    Code:
       0: aload_0
       1: getfield      #2                  // Field interleavedLedgerStorage:Lorg/apache/bookkeeper/bookie/InterleavedLedgerStorage;
       4: aload_1
       5: aload_2
       6: aload_3
       7: aload         4
       9: aload         5
      11: aload         6
      13: aload         7
      15: aload_0
      16: aload         8
      18: aload         9
      20: invokevirtual #8                  // Method org/apache/bookkeeper/bookie/InterleavedLedgerStorage.initializeWithEntryLogListener:(Lorg/apache/bookkeeper/conf/ServerConfiguration;Lorg/apache/bookkeeper/meta/LedgerManager;Lorg/apache/bookkeeper/bookie/LedgerDirsManager;Lorg/apache/bookkeeper/bookie/LedgerDirsManager;Lorg/apache/bookkeeper/bookie/StateManager;Lorg/apache/bookkeeper/bookie/CheckpointSource;Lorg/apache/bookkeeper/bookie/Checkpointer;Lorg/apache/bookkeeper/bookie/EntryLogger$EntryLogListener;Lorg/apache/bookkeeper/stats/StatsLogger;Lio/netty/buffer/ByteBufAllocator;)V
      23: aload_1
      24: invokevirtual #9                  // Method org/apache/bookkeeper/conf/ServerConfiguration.isEntryLogPerLedgerEnabled:()Z
      27: ifeq          49
      30: aload_0
      31: new           #10                 // class org/apache/bookkeeper/bookie/EntryMemTableWithParallelFlusher
      34: dup
      35: aload_1
      36: aload         6
      38: aload         8
      40: invokespecial #11                 // Method org/apache/bookkeeper/bookie/EntryMemTableWithParallelFlusher."<init>":(Lorg/apache/bookkeeper/conf/ServerConfiguration;Lorg/apache/bookkeeper/bookie/CheckpointSource;Lorg/apache/bookkeeper/stats/StatsLogger;)V
      43: putfield      #12                 // Field memTable:Lorg/apache/bookkeeper/bookie/EntryMemTable;
      46: goto          65
      49: aload_0
      50: new           #13                 // class org/apache/bookkeeper/bookie/EntryMemTable
      53: dup
      54: aload_1
      55: aload         6
      57: aload         8
      59: invokespecial #14                 // Method org/apache/bookkeeper/bookie/EntryMemTable."<init>":(Lorg/apache/bookkeeper/conf/ServerConfiguration;Lorg/apache/bookkeeper/bookie/CheckpointSource;Lorg/apache/bookkeeper/stats/StatsLogger;)V
      62: putfield      #12                 // Field memTable:Lorg/apache/bookkeeper/bookie/EntryMemTable;
      65: aload_0
      66: new           #15                 // class com/google/common/util/concurrent/ThreadFactoryBuilder
      69: dup
      70: invokespecial #16                 // Method com/google/common/util/concurrent/ThreadFactoryBuilder."<init>":()V
      73: ldc           #17                 // String SortedLedgerStorage-%d
      75: invokevirtual #18                 // Method com/google/common/util/concurrent/ThreadFactoryBuilder.setNameFormat:(Ljava/lang/String;)Lcom/google/common/util/concurrent/ThreadFactoryBuilder;
      78: bipush        7
      80: invokevirtual #20                 // Method com/google/common/util/concurrent/ThreadFactoryBuilder.setPriority:(I)Lcom/google/common/util/concurrent/ThreadFactoryBuilder;
      83: invokevirtual #21                 // Method com/google/common/util/concurrent/ThreadFactoryBuilder.build:()Ljava/util/concurrent/ThreadFactory;
      86: invokestatic  #22                 // Method java/util/concurrent/Executors.newSingleThreadScheduledExecutor:(Ljava/util/concurrent/ThreadFactory;)Ljava/util/concurrent/ScheduledExecutorService;
      89: putfield      #23                 // Field scheduler:Ljava/util/concurrent/ScheduledExecutorService;
      92: aload_0
      93: aload         5
      95: putfield      #1                  // Field stateManager:Lorg/apache/bookkeeper/bookie/StateManager;
      98: return

  java.util.concurrent.ScheduledExecutorService getScheduler();
    Code:
       0: aload_0
       1: getfield      #23                 // Field scheduler:Ljava/util/concurrent/ScheduledExecutorService;
       4: areturn

  public void start();
    Code:
       0: aload_0
       1: invokevirtual #24                 // Method flush:()V
       4: goto          19
       7: astore_1
       8: getstatic     #3                  // Field LOG:Lorg/slf4j/Logger;
      11: ldc           #26                 // String Exception thrown while flushing ledger cache.
      13: aload_1
      14: invokeinterface #27,  3           // InterfaceMethod org/slf4j/Logger.error:(Ljava/lang/String;Ljava/lang/Throwable;)V
      19: aload_0
      20: getfield      #2                  // Field interleavedLedgerStorage:Lorg/apache/bookkeeper/bookie/InterleavedLedgerStorage;
      23: invokevirtual #28                 // Method org/apache/bookkeeper/bookie/InterleavedLedgerStorage.start:()V
      26: return
    Exception table:
       from    to  target type
           0     4     7   Class java/io/IOException

  public void shutdown() throws java.lang.InterruptedException;
    Code:
       0: aload_0
       1: getfield      #23                 // Field scheduler:Ljava/util/concurrent/ScheduledExecutorService;
       4: invokeinterface #29,  1           // InterfaceMethod java/util/concurrent/ScheduledExecutorService.shutdown:()V
       9: aload_0
      10: getfield      #23                 // Field scheduler:Ljava/util/concurrent/ScheduledExecutorService;
      13: ldc2_w        #30                 // long 3l
      16: getstatic     #32                 // Field java/util/concurrent/TimeUnit.SECONDS:Ljava/util/concurrent/TimeUnit;
      19: invokeinterface #33,  4           // InterfaceMethod java/util/concurrent/ScheduledExecutorService.awaitTermination:(JLjava/util/concurrent/TimeUnit;)Z
      24: ifne          37
      27: aload_0
      28: getfield      #23                 // Field scheduler:Ljava/util/concurrent/ScheduledExecutorService;
      31: invokeinterface #34,  1           // InterfaceMethod java/util/concurrent/ScheduledExecutorService.shutdownNow:()Ljava/util/List;
      36: pop
      37: aload_0
      38: getfield      #12                 // Field memTable:Lorg/apache/bookkeeper/bookie/EntryMemTable;
      41: invokevirtual #35                 // Method org/apache/bookkeeper/bookie/EntryMemTable.close:()V
      44: goto          59
      47: astore_1
      48: getstatic     #3                  // Field LOG:Lorg/slf4j/Logger;
      51: ldc           #37                 // String Error while closing the memtable
      53: aload_1
      54: invokeinterface #27,  3           // InterfaceMethod org/slf4j/Logger.error:(Ljava/lang/String;Ljava/lang/Throwable;)V
      59: aload_0
      60: getfield      #2                  // Field interleavedLedgerStorage:Lorg/apache/bookkeeper/bookie/InterleavedLedgerStorage;
      63: invokevirtual #38                 // Method org/apache/bookkeeper/bookie/InterleavedLedgerStorage.shutdown:()V
      66: return
    Exception table:
       from    to  target type
          37    44    47   Class java/lang/Exception

  public boolean ledgerExists(long) throws java.io.IOException;
    Code:
       0: aload_0
       1: getfield      #2                  // Field interleavedLedgerStorage:Lorg/apache/bookkeeper/bookie/InterleavedLedgerStorage;
       4: lload_1
       5: invokevirtual #39                 // Method org/apache/bookkeeper/bookie/InterleavedLedgerStorage.ledgerExists:(J)Z
       8: ifne          34
      11: aload_0
      12: getfield      #12                 // Field memTable:Lorg/apache/bookkeeper/bookie/EntryMemTable;
      15: lload_1
      16: invokevirtual #40                 // Method org/apache/bookkeeper/bookie/EntryMemTable.getLastEntry:(J)Lorg/apache/bookkeeper/bookie/EntryKeyValue;
      19: astore_3
      20: aconst_null
      21: aload_3
      22: if_acmpne     34
      25: aload_0
      26: getfield      #2                  // Field interleavedLedgerStorage:Lorg/apache/bookkeeper/bookie/InterleavedLedgerStorage;
      29: lload_1
      30: invokevirtual #39                 // Method org/apache/bookkeeper/bookie/InterleavedLedgerStorage.ledgerExists:(J)Z
      33: ireturn
      34: iconst_1
      35: ireturn

  public boolean setFenced(long) throws java.io.IOException;
    Code:
       0: aload_0
       1: getfield      #2                  // Field interleavedLedgerStorage:Lorg/apache/bookkeeper/bookie/InterleavedLedgerStorage;
       4: lload_1
       5: invokevirtual #41                 // Method org/apache/bookkeeper/bookie/InterleavedLedgerStorage.setFenced:(J)Z
       8: ireturn

  public boolean isFenced(long) throws java.io.IOException;
    Code:
       0: aload_0
       1: getfield      #2                  // Field interleavedLedgerStorage:Lorg/apache/bookkeeper/bookie/InterleavedLedgerStorage;
       4: lload_1
       5: invokevirtual #42                 // Method org/apache/bookkeeper/bookie/InterleavedLedgerStorage.isFenced:(J)Z
       8: ireturn

  public void setMasterKey(long, byte[]) throws java.io.IOException;
    Code:
       0: aload_0
       1: getfield      #2                  // Field interleavedLedgerStorage:Lorg/apache/bookkeeper/bookie/InterleavedLedgerStorage;
       4: lload_1
       5: aload_3
       6: invokevirtual #43                 // Method org/apache/bookkeeper/bookie/InterleavedLedgerStorage.setMasterKey:(J[B)V
       9: return

  public byte[] readMasterKey(long) throws java.io.IOException, org.apache.bookkeeper.bookie.BookieException;
    Code:
       0: aload_0
       1: getfield      #2                  // Field interleavedLedgerStorage:Lorg/apache/bookkeeper/bookie/InterleavedLedgerStorage;
       4: lload_1
       5: invokevirtual #44                 // Method org/apache/bookkeeper/bookie/InterleavedLedgerStorage.readMasterKey:(J)[B
       8: areturn

  public long addEntry(io.netty.buffer.ByteBuf) throws java.io.IOException;
    Code:
       0: aload_1
       1: aload_1
       2: invokevirtual #45                 // Method io/netty/buffer/ByteBuf.readerIndex:()I
       5: iconst_0
       6: iadd
       7: invokevirtual #46                 // Method io/netty/buffer/ByteBuf.getLong:(I)J
      10: lstore_2
      11: aload_1
      12: aload_1
      13: invokevirtual #45                 // Method io/netty/buffer/ByteBuf.readerIndex:()I
      16: bipush        8
      18: iadd
      19: invokevirtual #46                 // Method io/netty/buffer/ByteBuf.getLong:(I)J
      22: lstore        4
      24: aload_1
      25: aload_1
      26: invokevirtual #45                 // Method io/netty/buffer/ByteBuf.readerIndex:()I
      29: bipush        16
      31: iadd
      32: invokevirtual #46                 // Method io/netty/buffer/ByteBuf.getLong:(I)J
      35: lstore        6
      37: aload_0
      38: getfield      #12                 // Field memTable:Lorg/apache/bookkeeper/bookie/EntryMemTable;
      41: lload_2
      42: lload         4
      44: aload_1
      45: invokevirtual #47                 // Method io/netty/buffer/ByteBuf.nioBuffer:()Ljava/nio/ByteBuffer;
      48: aload_0
      49: invokevirtual #48                 // Method org/apache/bookkeeper/bookie/EntryMemTable.addEntry:(JJLjava/nio/ByteBuffer;Lorg/apache/bookkeeper/bookie/CacheCallback;)J
      52: pop2
      53: aload_0
      54: getfield      #2                  // Field interleavedLedgerStorage:Lorg/apache/bookkeeper/bookie/InterleavedLedgerStorage;
      57: getfield      #49                 // Field org/apache/bookkeeper/bookie/InterleavedLedgerStorage.ledgerCache:Lorg/apache/bookkeeper/bookie/LedgerCache;
      60: lload_2
      61: lload         6
      63: invokeinterface #50,  5           // InterfaceMethod org/apache/bookkeeper/bookie/LedgerCache.updateLastAddConfirmed:(JJ)J
      68: pop2
      69: lload         4
      71: lreturn

  private io.netty.buffer.ByteBuf getLastEntryId(long) throws java.io.IOException;
    Code:
       0: aload_0
       1: getfield      #12                 // Field memTable:Lorg/apache/bookkeeper/bookie/EntryMemTable;
       4: lload_1
       5: invokevirtual #40                 // Method org/apache/bookkeeper/bookie/EntryMemTable.getLastEntry:(J)Lorg/apache/bookkeeper/bookie/EntryKeyValue;
       8: astore_3
       9: aconst_null
      10: aload_3
      11: if_acmpeq     19
      14: aload_3
      15: invokevirtual #51                 // Method org/apache/bookkeeper/bookie/EntryKeyValue.getValueAsByteBuffer:()Lio/netty/buffer/ByteBuf;
      18: areturn
      19: aload_0
      20: getfield      #2                  // Field interleavedLedgerStorage:Lorg/apache/bookkeeper/bookie/InterleavedLedgerStorage;
      23: lload_1
      24: ldc2_w        #53                 // long -1l
      27: invokevirtual #55                 // Method org/apache/bookkeeper/bookie/InterleavedLedgerStorage.getEntry:(JJ)Lio/netty/buffer/ByteBuf;
      30: areturn

  public io.netty.buffer.ByteBuf getEntry(long, long) throws java.io.IOException;
    Code:
       0: lload_3
       1: ldc2_w        #53                 // long -1l
       4: lcmp
       5: ifne          14
       8: aload_0
       9: lload_1
      10: invokespecial #56                 // Method getLastEntryId:(J)Lio/netty/buffer/ByteBuf;
      13: areturn
      14: aload_0
      15: getfield      #2                  // Field interleavedLedgerStorage:Lorg/apache/bookkeeper/bookie/InterleavedLedgerStorage;
      18: lload_1
      19: lload_3
      20: invokevirtual #55                 // Method org/apache/bookkeeper/bookie/InterleavedLedgerStorage.getEntry:(JJ)Lio/netty/buffer/ByteBuf;
      23: astore        5
      25: goto          68
      28: astore        6
      30: aload_0
      31: getfield      #12                 // Field memTable:Lorg/apache/bookkeeper/bookie/EntryMemTable;
      34: lload_1
      35: lload_3
      36: invokevirtual #58                 // Method org/apache/bookkeeper/bookie/EntryMemTable.getEntry:(JJ)Lorg/apache/bookkeeper/bookie/EntryKeyValue;
      39: astore        7
      41: aconst_null
      42: aload         7
      44: if_acmpne     61
      47: aload_0
      48: getfield      #2                  // Field interleavedLedgerStorage:Lorg/apache/bookkeeper/bookie/InterleavedLedgerStorage;
      51: lload_1
      52: lload_3
      53: invokevirtual #55                 // Method org/apache/bookkeeper/bookie/InterleavedLedgerStorage.getEntry:(JJ)Lio/netty/buffer/ByteBuf;
      56: astore        5
      58: goto          68
      61: aload         7
      63: invokevirtual #51                 // Method org/apache/bookkeeper/bookie/EntryKeyValue.getValueAsByteBuffer:()Lio/netty/buffer/ByteBuf;
      66: astore        5
      68: aload         5
      70: areturn
    Exception table:
       from    to  target type
          14    25    28   Class org/apache/bookkeeper/bookie/Bookie$NoEntryException

  public long getLastAddConfirmed(long) throws java.io.IOException;
    Code:
       0: aload_0
       1: getfield      #2                  // Field interleavedLedgerStorage:Lorg/apache/bookkeeper/bookie/InterleavedLedgerStorage;
       4: lload_1
       5: invokevirtual #59                 // Method org/apache/bookkeeper/bookie/InterleavedLedgerStorage.getLastAddConfirmed:(J)J
       8: lreturn

  public boolean waitForLastAddConfirmedUpdate(long, long, org.apache.bookkeeper.common.util.Watcher<org.apache.bookkeeper.bookie.LastAddConfirmedUpdateNotification>) throws java.io.IOException;
    Code:
       0: aload_0
       1: getfield      #2                  // Field interleavedLedgerStorage:Lorg/apache/bookkeeper/bookie/InterleavedLedgerStorage;
       4: lload_1
       5: lload_3
       6: aload         5
       8: invokevirtual #60                 // Method org/apache/bookkeeper/bookie/InterleavedLedgerStorage.waitForLastAddConfirmedUpdate:(JJLorg/apache/bookkeeper/common/util/Watcher;)Z
      11: ireturn

  public void cancelWaitForLastAddConfirmedUpdate(long, org.apache.bookkeeper.common.util.Watcher<org.apache.bookkeeper.bookie.LastAddConfirmedUpdateNotification>) throws java.io.IOException;
    Code:
       0: aload_0
       1: getfield      #2                  // Field interleavedLedgerStorage:Lorg/apache/bookkeeper/bookie/InterleavedLedgerStorage;
       4: lload_1
       5: aload_3
       6: invokevirtual #61                 // Method org/apache/bookkeeper/bookie/InterleavedLedgerStorage.cancelWaitForLastAddConfirmedUpdate:(JLorg/apache/bookkeeper/common/util/Watcher;)V
       9: return

  public void checkpoint(org.apache.bookkeeper.bookie.CheckpointSource$Checkpoint) throws java.io.IOException;
    Code:
       0: aload_0
       1: getfield      #12                 // Field memTable:Lorg/apache/bookkeeper/bookie/EntryMemTable;
       4: aload_0
       5: aload_1
       6: invokevirtual #62                 // Method org/apache/bookkeeper/bookie/EntryMemTable.flush:(Lorg/apache/bookkeeper/bookie/SkipListFlusher;Lorg/apache/bookkeeper/bookie/CheckpointSource$Checkpoint;)J
       9: lstore_2
      10: aload_0
      11: getfield      #2                  // Field interleavedLedgerStorage:Lorg/apache/bookkeeper/bookie/InterleavedLedgerStorage;
      14: invokevirtual #63                 // Method org/apache/bookkeeper/bookie/InterleavedLedgerStorage.getEntryLogger:()Lorg/apache/bookkeeper/bookie/EntryLogger;
      17: lload_2
      18: invokevirtual #64                 // Method org/apache/bookkeeper/bookie/EntryLogger.prepareSortedLedgerStorageCheckpoint:(J)V
      21: aload_0
      22: getfield      #2                  // Field interleavedLedgerStorage:Lorg/apache/bookkeeper/bookie/InterleavedLedgerStorage;
      25: aload_1
      26: invokevirtual #65                 // Method org/apache/bookkeeper/bookie/InterleavedLedgerStorage.checkpoint:(Lorg/apache/bookkeeper/bookie/CheckpointSource$Checkpoint;)V
      29: return

  public void deleteLedger(long) throws java.io.IOException;
    Code:
       0: aload_0
       1: getfield      #2                  // Field interleavedLedgerStorage:Lorg/apache/bookkeeper/bookie/InterleavedLedgerStorage;
       4: lload_1
       5: invokevirtual #66                 // Method org/apache/bookkeeper/bookie/InterleavedLedgerStorage.deleteLedger:(J)V
       8: return

  public void registerLedgerDeletionListener(org.apache.bookkeeper.bookie.LedgerStorage$LedgerDeletionListener);
    Code:
       0: aload_0
       1: getfield      #2                  // Field interleavedLedgerStorage:Lorg/apache/bookkeeper/bookie/InterleavedLedgerStorage;
       4: aload_1
       5: invokevirtual #67                 // Method org/apache/bookkeeper/bookie/InterleavedLedgerStorage.registerLedgerDeletionListener:(Lorg/apache/bookkeeper/bookie/LedgerStorage$LedgerDeletionListener;)V
       8: return

  public void setExplicitLac(long, io.netty.buffer.ByteBuf) throws java.io.IOException;
    Code:
       0: aload_0
       1: getfield      #2                  // Field interleavedLedgerStorage:Lorg/apache/bookkeeper/bookie/InterleavedLedgerStorage;
       4: lload_1
       5: aload_3
       6: invokevirtual #68                 // Method org/apache/bookkeeper/bookie/InterleavedLedgerStorage.setExplicitLac:(JLio/netty/buffer/ByteBuf;)V
       9: return

  public io.netty.buffer.ByteBuf getExplicitLac(long);
    Code:
       0: aload_0
       1: getfield      #2                  // Field interleavedLedgerStorage:Lorg/apache/bookkeeper/bookie/InterleavedLedgerStorage;
       4: lload_1
       5: invokevirtual #69                 // Method org/apache/bookkeeper/bookie/InterleavedLedgerStorage.getExplicitLac:(J)Lio/netty/buffer/ByteBuf;
       8: areturn

  public void process(long, long, io.netty.buffer.ByteBuf) throws java.io.IOException;
    Code:
       0: aload_0
       1: getfield      #2                  // Field interleavedLedgerStorage:Lorg/apache/bookkeeper/bookie/InterleavedLedgerStorage;
       4: lload_1
       5: lload_3
       6: aload         5
       8: iconst_0
       9: invokevirtual #70                 // Method org/apache/bookkeeper/bookie/InterleavedLedgerStorage.processEntry:(JJLio/netty/buffer/ByteBuf;Z)V
      12: return

  public void flush() throws java.io.IOException;
    Code:
       0: aload_0
       1: getfield      #12                 // Field memTable:Lorg/apache/bookkeeper/bookie/EntryMemTable;
       4: aload_0
       5: getstatic     #71                 // Field org/apache/bookkeeper/bookie/CheckpointSource$Checkpoint.MAX:Lorg/apache/bookkeeper/bookie/CheckpointSource$Checkpoint;
       8: invokevirtual #62                 // Method org/apache/bookkeeper/bookie/EntryMemTable.flush:(Lorg/apache/bookkeeper/bookie/SkipListFlusher;Lorg/apache/bookkeeper/bookie/CheckpointSource$Checkpoint;)J
      11: pop2
      12: aload_0
      13: getfield      #2                  // Field interleavedLedgerStorage:Lorg/apache/bookkeeper/bookie/InterleavedLedgerStorage;
      16: invokevirtual #72                 // Method org/apache/bookkeeper/bookie/InterleavedLedgerStorage.flush:()V
      19: return

  public void onSizeLimitReached(org.apache.bookkeeper.bookie.CheckpointSource$Checkpoint) throws java.io.IOException;
    Code:
       0: getstatic     #3                  // Field LOG:Lorg/slf4j/Logger;
       3: ldc           #73                 // String Reached size {}
       5: aload_1
       6: invokeinterface #74,  3           // InterfaceMethod org/slf4j/Logger.info:(Ljava/lang/String;Ljava/lang/Object;)V
      11: aload_0
      12: getfield      #23                 // Field scheduler:Ljava/util/concurrent/ScheduledExecutorService;
      15: new           #75                 // class org/apache/bookkeeper/bookie/SortedLedgerStorage$1
      18: dup
      19: aload_0
      20: aload_1
      21: invokespecial #76                 // Method org/apache/bookkeeper/bookie/SortedLedgerStorage$1."<init>":(Lorg/apache/bookkeeper/bookie/SortedLedgerStorage;Lorg/apache/bookkeeper/bookie/CheckpointSource$Checkpoint;)V
      24: invokeinterface #77,  2           // InterfaceMethod java/util/concurrent/ScheduledExecutorService.execute:(Ljava/lang/Runnable;)V
      29: return

  public void onRotateEntryLog();
    Code:
       0: return

  org.apache.bookkeeper.bookie.BookieStateManager getStateManager();
    Code:
       0: aload_0
       1: getfield      #1                  // Field stateManager:Lorg/apache/bookkeeper/bookie/StateManager;
       4: checkcast     #78                 // class org/apache/bookkeeper/bookie/BookieStateManager
       7: areturn

  public org.apache.bookkeeper.bookie.EntryLogger getEntryLogger();
    Code:
       0: aload_0
       1: getfield      #2                  // Field interleavedLedgerStorage:Lorg/apache/bookkeeper/bookie/InterleavedLedgerStorage;
       4: invokevirtual #63                 // Method org/apache/bookkeeper/bookie/InterleavedLedgerStorage.getEntryLogger:()Lorg/apache/bookkeeper/bookie/EntryLogger;
       7: areturn

  public java.lang.Iterable<java.lang.Long> getActiveLedgersInRange(long, long) throws java.io.IOException;
    Code:
       0: aload_0
       1: getfield      #2                  // Field interleavedLedgerStorage:Lorg/apache/bookkeeper/bookie/InterleavedLedgerStorage;
       4: lload_1
       5: lload_3
       6: invokevirtual #79                 // Method org/apache/bookkeeper/bookie/InterleavedLedgerStorage.getActiveLedgersInRange:(JJ)Ljava/lang/Iterable;
       9: areturn

  public void updateEntriesLocations(java.lang.Iterable<org.apache.bookkeeper.bookie.EntryLocation>) throws java.io.IOException;
    Code:
       0: aload_0
       1: getfield      #2                  // Field interleavedLedgerStorage:Lorg/apache/bookkeeper/bookie/InterleavedLedgerStorage;
       4: aload_1
       5: invokevirtual #80                 // Method org/apache/bookkeeper/bookie/InterleavedLedgerStorage.updateEntriesLocations:(Ljava/lang/Iterable;)V
       8: return

  public void flushEntriesLocationsIndex() throws java.io.IOException;
    Code:
       0: aload_0
       1: getfield      #2                  // Field interleavedLedgerStorage:Lorg/apache/bookkeeper/bookie/InterleavedLedgerStorage;
       4: invokevirtual #81                 // Method org/apache/bookkeeper/bookie/InterleavedLedgerStorage.flushEntriesLocationsIndex:()V
       7: return

  public org.apache.bookkeeper.bookie.LedgerStorage getUnderlyingLedgerStorage();
    Code:
       0: aload_0
       1: getfield      #2                  // Field interleavedLedgerStorage:Lorg/apache/bookkeeper/bookie/InterleavedLedgerStorage;
       4: areturn

  public void forceGC();
    Code:
       0: aload_0
       1: getfield      #2                  // Field interleavedLedgerStorage:Lorg/apache/bookkeeper/bookie/InterleavedLedgerStorage;
       4: invokevirtual #82                 // Method org/apache/bookkeeper/bookie/InterleavedLedgerStorage.forceGC:()V
       7: return

  public java.util.List<org.apache.bookkeeper.bookie.LedgerStorage$DetectedInconsistency> localConsistencyCheck(java.util.Optional<com.google.common.util.concurrent.RateLimiter>) throws java.io.IOException;
    Code:
       0: aload_0
       1: getfield      #2                  // Field interleavedLedgerStorage:Lorg/apache/bookkeeper/bookie/InterleavedLedgerStorage;
       4: aload_1
       5: invokevirtual #83                 // Method org/apache/bookkeeper/bookie/InterleavedLedgerStorage.localConsistencyCheck:(Ljava/util/Optional;)Ljava/util/List;
       8: areturn

  public boolean isInForceGC();
    Code:
       0: aload_0
       1: getfield      #2                  // Field interleavedLedgerStorage:Lorg/apache/bookkeeper/bookie/InterleavedLedgerStorage;
       4: invokevirtual #84                 // Method org/apache/bookkeeper/bookie/InterleavedLedgerStorage.isInForceGC:()Z
       7: ireturn

  public java.util.List<org.apache.bookkeeper.bookie.GarbageCollectionStatus> getGarbageCollectionStatus();
    Code:
       0: aload_0
       1: getfield      #2                  // Field interleavedLedgerStorage:Lorg/apache/bookkeeper/bookie/InterleavedLedgerStorage;
       4: invokevirtual #85                 // Method org/apache/bookkeeper/bookie/InterleavedLedgerStorage.getGarbageCollectionStatus:()Ljava/util/List;
       7: areturn

  public java.util.PrimitiveIterator$OfLong getListOfEntriesOfLedger(long) throws java.io.IOException;
    Code:
       0: aload_0
       1: getfield      #12                 // Field memTable:Lorg/apache/bookkeeper/bookie/EntryMemTable;
       4: lload_1
       5: invokevirtual #86                 // Method org/apache/bookkeeper/bookie/EntryMemTable.getListOfEntriesOfLedger:(J)Ljava/util/PrimitiveIterator$OfLong;
       8: astore_3
       9: aload_0
      10: getfield      #2                  // Field interleavedLedgerStorage:Lorg/apache/bookkeeper/bookie/InterleavedLedgerStorage;
      13: lload_1
      14: invokevirtual #87                 // Method org/apache/bookkeeper/bookie/InterleavedLedgerStorage.getListOfEntriesOfLedger:(J)Ljava/util/PrimitiveIterator$OfLong;
      17: astore        4
      19: aload_3
      20: aload         4
      22: invokestatic  #88                 // Method org/apache/bookkeeper/util/IteratorUtility.mergePrimitiveLongIterator:(Ljava/util/PrimitiveIterator$OfLong;Ljava/util/PrimitiveIterator$OfLong;)Ljava/util/PrimitiveIterator$OfLong;
      25: areturn

  static org.slf4j.Logger access$000();
    Code:
       0: getstatic     #3                  // Field LOG:Lorg/slf4j/Logger;
       3: areturn

  static org.apache.bookkeeper.bookie.InterleavedLedgerStorage access$100(org.apache.bookkeeper.bookie.SortedLedgerStorage);
    Code:
       0: aload_0
       1: getfield      #2                  // Field interleavedLedgerStorage:Lorg/apache/bookkeeper/bookie/InterleavedLedgerStorage;
       4: areturn

  static org.apache.bookkeeper.bookie.StateManager access$200(org.apache.bookkeeper.bookie.SortedLedgerStorage);
    Code:
       0: aload_0
       1: getfield      #1                  // Field stateManager:Lorg/apache/bookkeeper/bookie/StateManager;
       4: areturn

  static {};
    Code:
       0: ldc           #89                 // class org/apache/bookkeeper/bookie/SortedLedgerStorage
       2: invokestatic  #90                 // Method org/slf4j/LoggerFactory.getLogger:(Ljava/lang/Class;)Lorg/slf4j/Logger;
       5: putstatic     #3                  // Field LOG:Lorg/slf4j/Logger;
       8: return
}
