Compiled from "DebtRemediationFunction.java"
public class org.sonar.api.batch.debt.DebtRemediationFunction {
  private org.sonar.api.batch.debt.DebtRemediationFunction$Type type;

  private org.sonar.api.utils.Duration coefficient;

  private org.sonar.api.utils.Duration offset;

  private org.sonar.api.batch.debt.DebtRemediationFunction(org.sonar.api.batch.debt.DebtRemediationFunction$Type, org.sonar.api.utils.Duration, org.sonar.api.utils.Duration);
    Code:
       0: aload_0
       1: invokespecial #19                 // Method java/lang/Object."<init>":()V
       4: aload_0
       5: aload_1
       6: putfield      #21                 // Field type:Lorg/sonar/api/batch/debt/DebtRemediationFunction$Type;
       9: aload_0
      10: aload_2
      11: putfield      #23                 // Field coefficient:Lorg/sonar/api/utils/Duration;
      14: aload_0
      15: aload_3
      16: putfield      #25                 // Field offset:Lorg/sonar/api/utils/Duration;
      19: return

  public static org.sonar.api.batch.debt.DebtRemediationFunction create(org.sonar.api.batch.debt.DebtRemediationFunction$Type, org.sonar.api.utils.Duration, org.sonar.api.utils.Duration);
    Code:
       0: new           #2                  // class org/sonar/api/batch/debt/DebtRemediationFunction
       3: dup
       4: aload_0
       5: aload_1
       6: aload_2
       7: invokespecial #31                 // Method "<init>":(Lorg/sonar/api/batch/debt/DebtRemediationFunction$Type;Lorg/sonar/api/utils/Duration;Lorg/sonar/api/utils/Duration;)V
      10: areturn

  public static org.sonar.api.batch.debt.DebtRemediationFunction createLinear(org.sonar.api.utils.Duration);
    Code:
       0: new           #2                  // class org/sonar/api/batch/debt/DebtRemediationFunction
       3: dup
       4: getstatic     #36                 // Field org/sonar/api/batch/debt/DebtRemediationFunction$Type.LINEAR:Lorg/sonar/api/batch/debt/DebtRemediationFunction$Type;
       7: aload_0
       8: aconst_null
       9: invokespecial #31                 // Method "<init>":(Lorg/sonar/api/batch/debt/DebtRemediationFunction$Type;Lorg/sonar/api/utils/Duration;Lorg/sonar/api/utils/Duration;)V
      12: areturn

  public static org.sonar.api.batch.debt.DebtRemediationFunction createLinearWithOffset(org.sonar.api.utils.Duration, org.sonar.api.utils.Duration);
    Code:
       0: new           #2                  // class org/sonar/api/batch/debt/DebtRemediationFunction
       3: dup
       4: getstatic     #41                 // Field org/sonar/api/batch/debt/DebtRemediationFunction$Type.LINEAR_OFFSET:Lorg/sonar/api/batch/debt/DebtRemediationFunction$Type;
       7: aload_0
       8: aload_1
       9: invokespecial #31                 // Method "<init>":(Lorg/sonar/api/batch/debt/DebtRemediationFunction$Type;Lorg/sonar/api/utils/Duration;Lorg/sonar/api/utils/Duration;)V
      12: areturn

  public static org.sonar.api.batch.debt.DebtRemediationFunction createConstantPerIssue(org.sonar.api.utils.Duration);
    Code:
       0: new           #2                  // class org/sonar/api/batch/debt/DebtRemediationFunction
       3: dup
       4: getstatic     #45                 // Field org/sonar/api/batch/debt/DebtRemediationFunction$Type.CONSTANT_ISSUE:Lorg/sonar/api/batch/debt/DebtRemediationFunction$Type;
       7: aconst_null
       8: aload_0
       9: invokespecial #31                 // Method "<init>":(Lorg/sonar/api/batch/debt/DebtRemediationFunction$Type;Lorg/sonar/api/utils/Duration;Lorg/sonar/api/utils/Duration;)V
      12: areturn

  public org.sonar.api.batch.debt.DebtRemediationFunction$Type type();
    Code:
       0: aload_0
       1: getfield      #21                 // Field type:Lorg/sonar/api/batch/debt/DebtRemediationFunction$Type;
       4: areturn

  public org.sonar.api.utils.Duration coefficient();
    Code:
       0: aload_0
       1: getfield      #23                 // Field coefficient:Lorg/sonar/api/utils/Duration;
       4: areturn

  public org.sonar.api.utils.Duration offset();
    Code:
       0: aload_0
       1: getfield      #25                 // Field offset:Lorg/sonar/api/utils/Duration;
       4: areturn

  public boolean equals(java.lang.Object);
    Code:
       0: aload_0
       1: aload_1
       2: if_acmpne     7
       5: iconst_1
       6: ireturn
       7: aload_1
       8: ifnull        22
      11: aload_0
      12: invokevirtual #54                 // Method java/lang/Object.getClass:()Ljava/lang/Class;
      15: aload_1
      16: invokevirtual #54                 // Method java/lang/Object.getClass:()Ljava/lang/Class;
      19: if_acmpeq     24
      22: iconst_0
      23: ireturn
      24: aload_1
      25: checkcast     #2                  // class org/sonar/api/batch/debt/DebtRemediationFunction
      28: astore_2
      29: new           #56                 // class org/sonar/api/internal/apachecommons/lang/builder/EqualsBuilder
      32: dup
      33: invokespecial #57                 // Method org/sonar/api/internal/apachecommons/lang/builder/EqualsBuilder."<init>":()V
      36: aload_0
      37: getfield      #21                 // Field type:Lorg/sonar/api/batch/debt/DebtRemediationFunction$Type;
      40: aload_2
      41: invokevirtual #59                 // Method type:()Lorg/sonar/api/batch/debt/DebtRemediationFunction$Type;
      44: invokevirtual #63                 // Method org/sonar/api/internal/apachecommons/lang/builder/EqualsBuilder.append:(Ljava/lang/Object;Ljava/lang/Object;)Lorg/sonar/api/internal/apachecommons/lang/builder/EqualsBuilder;
      47: aload_0
      48: getfield      #23                 // Field coefficient:Lorg/sonar/api/utils/Duration;
      51: aload_2
      52: invokevirtual #65                 // Method coefficient:()Lorg/sonar/api/utils/Duration;
      55: invokevirtual #63                 // Method org/sonar/api/internal/apachecommons/lang/builder/EqualsBuilder.append:(Ljava/lang/Object;Ljava/lang/Object;)Lorg/sonar/api/internal/apachecommons/lang/builder/EqualsBuilder;
      58: aload_0
      59: getfield      #25                 // Field offset:Lorg/sonar/api/utils/Duration;
      62: aload_2
      63: invokevirtual #67                 // Method offset:()Lorg/sonar/api/utils/Duration;
      66: invokevirtual #63                 // Method org/sonar/api/internal/apachecommons/lang/builder/EqualsBuilder.append:(Ljava/lang/Object;Ljava/lang/Object;)Lorg/sonar/api/internal/apachecommons/lang/builder/EqualsBuilder;
      69: invokevirtual #71                 // Method org/sonar/api/internal/apachecommons/lang/builder/EqualsBuilder.isEquals:()Z
      72: ireturn

  public int hashCode();
    Code:
       0: new           #78                 // class org/sonar/api/internal/apachecommons/lang/builder/HashCodeBuilder
       3: dup
       4: bipush        15
       6: bipush        31
       8: invokespecial #81                 // Method org/sonar/api/internal/apachecommons/lang/builder/HashCodeBuilder."<init>":(II)V
      11: aload_0
      12: getfield      #21                 // Field type:Lorg/sonar/api/batch/debt/DebtRemediationFunction$Type;
      15: invokevirtual #84                 // Method org/sonar/api/internal/apachecommons/lang/builder/HashCodeBuilder.append:(Ljava/lang/Object;)Lorg/sonar/api/internal/apachecommons/lang/builder/HashCodeBuilder;
      18: aload_0
      19: getfield      #23                 // Field coefficient:Lorg/sonar/api/utils/Duration;
      22: invokevirtual #84                 // Method org/sonar/api/internal/apachecommons/lang/builder/HashCodeBuilder.append:(Ljava/lang/Object;)Lorg/sonar/api/internal/apachecommons/lang/builder/HashCodeBuilder;
      25: aload_0
      26: getfield      #25                 // Field offset:Lorg/sonar/api/utils/Duration;
      29: invokevirtual #84                 // Method org/sonar/api/internal/apachecommons/lang/builder/HashCodeBuilder.append:(Ljava/lang/Object;)Lorg/sonar/api/internal/apachecommons/lang/builder/HashCodeBuilder;
      32: invokevirtual #87                 // Method org/sonar/api/internal/apachecommons/lang/builder/HashCodeBuilder.toHashCode:()I
      35: ireturn

  public java.lang.String toString();
    Code:
       0: new           #91                 // class org/sonar/api/internal/apachecommons/lang/builder/ReflectionToStringBuilder
       3: dup
       4: aload_0
       5: getstatic     #97                 // Field org/sonar/api/internal/apachecommons/lang/builder/ToStringStyle.SHORT_PREFIX_STYLE:Lorg/sonar/api/internal/apachecommons/lang/builder/ToStringStyle;
       8: invokespecial #100                // Method org/sonar/api/internal/apachecommons/lang/builder/ReflectionToStringBuilder."<init>":(Ljava/lang/Object;Lorg/sonar/api/internal/apachecommons/lang/builder/ToStringStyle;)V
      11: invokevirtual #102                // Method org/sonar/api/internal/apachecommons/lang/builder/ReflectionToStringBuilder.toString:()Ljava/lang/String;
      14: areturn
}
