Compiled from "BlowfishSerializer.java"
class com.esotericsoftware.kryo.serializers.BlowfishSerializer$1 extends com.esotericsoftware.kryo.io.Output {
  final com.esotericsoftware.kryo.serializers.BlowfishSerializer this$0;

  com.esotericsoftware.kryo.serializers.BlowfishSerializer$1(com.esotericsoftware.kryo.serializers.BlowfishSerializer, java.io.OutputStream, int);
    Code:
       0: aload_0
       1: aload_1
       2: putfield      #1                  // Field this$0:Lcom/esotericsoftware/kryo/serializers/BlowfishSerializer;
       5: aload_0
       6: aload_2
       7: iload_3
       8: invokespecial #2                  // Method com/esotericsoftware/kryo/io/Output."<init>":(Ljava/io/OutputStream;I)V
      11: return

  public void close() throws com.esotericsoftware.kryo.KryoException;
    Code:
       0: return
}
