Compiled from "DefaultSerializers.java"
public class com.esotericsoftware.kryo.serializers.DefaultSerializers$StringBufferSerializer extends com.esotericsoftware.kryo.Serializer<java.lang.StringBuffer> {
  public com.esotericsoftware.kryo.serializers.DefaultSerializers$StringBufferSerializer();
    Code:
       0: aload_0
       1: invokespecial #1                  // Method com/esotericsoftware/kryo/Serializer."<init>":()V
       4: aload_0
       5: iconst_1
       6: invokevirtual #2                  // Method setAcceptsNull:(Z)V
       9: return

  public void write(com.esotericsoftware.kryo.Kryo, com.esotericsoftware.kryo.io.Output, java.lang.StringBuffer);
    Code:
       0: aload_2
       1: aload_3
       2: invokevirtual #3                  // Method com/esotericsoftware/kryo/io/Output.writeString:(Ljava/lang/CharSequence;)V
       5: return

  public java.lang.StringBuffer read(com.esotericsoftware.kryo.Kryo, com.esotericsoftware.kryo.io.Input, java.lang.Class<java.lang.StringBuffer>);
    Code:
       0: aload_2
       1: invokevirtual #4                  // Method com/esotericsoftware/kryo/io/Input.readString:()Ljava/lang/String;
       4: astore        4
       6: aload         4
       8: ifnonnull     13
      11: aconst_null
      12: areturn
      13: new           #5                  // class java/lang/StringBuffer
      16: dup
      17: aload         4
      19: invokespecial #6                  // Method java/lang/StringBuffer."<init>":(Ljava/lang/String;)V
      22: areturn

  public java.lang.StringBuffer copy(com.esotericsoftware.kryo.Kryo, java.lang.StringBuffer);
    Code:
       0: new           #5                  // class java/lang/StringBuffer
       3: dup
       4: aload_2
       5: invokespecial #7                  // Method java/lang/StringBuffer."<init>":(Ljava/lang/CharSequence;)V
       8: areturn

  public java.lang.Object copy(com.esotericsoftware.kryo.Kryo, java.lang.Object);
    Code:
       0: aload_0
       1: aload_1
       2: aload_2
       3: checkcast     #5                  // class java/lang/StringBuffer
       6: invokevirtual #8                  // Method copy:(Lcom/esotericsoftware/kryo/Kryo;Ljava/lang/StringBuffer;)Ljava/lang/StringBuffer;
       9: areturn

  public java.lang.Object read(com.esotericsoftware.kryo.Kryo, com.esotericsoftware.kryo.io.Input, java.lang.Class);
    Code:
       0: aload_0
       1: aload_1
       2: aload_2
       3: aload_3
       4: invokevirtual #9                  // Method read:(Lcom/esotericsoftware/kryo/Kryo;Lcom/esotericsoftware/kryo/io/Input;Ljava/lang/Class;)Ljava/lang/StringBuffer;
       7: areturn

  public void write(com.esotericsoftware.kryo.Kryo, com.esotericsoftware.kryo.io.Output, java.lang.Object);
    Code:
       0: aload_0
       1: aload_1
       2: aload_2
       3: aload_3
       4: checkcast     #5                  // class java/lang/StringBuffer
       7: invokevirtual #10                 // Method write:(Lcom/esotericsoftware/kryo/Kryo;Lcom/esotericsoftware/kryo/io/Output;Ljava/lang/StringBuffer;)V
      10: return
}
