Compiled from "UnsafeCacheFields.java"
final class com.esotericsoftware.kryo.serializers.UnsafeCacheFields$UnsafeFloatField extends com.esotericsoftware.kryo.serializers.UnsafeCacheFields$UnsafeCachedField {
  public com.esotericsoftware.kryo.serializers.UnsafeCacheFields$UnsafeFloatField(java.lang.reflect.Field);
    Code:
       0: aload_0
       1: invokestatic  #1                  // Method com/esotericsoftware/kryo/util/UnsafeUtil.unsafe:()Lsun/misc/Unsafe;
       4: aload_1
       5: invokevirtual #2                  // Method sun/misc/Unsafe.objectFieldOffset:(Ljava/lang/reflect/Field;)J
       8: invokespecial #3                  // Method com/esotericsoftware/kryo/serializers/UnsafeCacheFields$UnsafeCachedField."<init>":(J)V
      11: return

  public void write(com.esotericsoftware.kryo.io.Output, java.lang.Object);
    Code:
       0: aload_1
       1: invokestatic  #1                  // Method com/esotericsoftware/kryo/util/UnsafeUtil.unsafe:()Lsun/misc/Unsafe;
       4: aload_2
       5: aload_0
       6: getfield      #4                  // Field offset:J
       9: invokevirtual #5                  // Method sun/misc/Unsafe.getFloat:(Ljava/lang/Object;J)F
      12: invokevirtual #6                  // Method com/esotericsoftware/kryo/io/Output.writeFloat:(F)V
      15: return

  public void read(com.esotericsoftware.kryo.io.Input, java.lang.Object);
    Code:
       0: invokestatic  #1                  // Method com/esotericsoftware/kryo/util/UnsafeUtil.unsafe:()Lsun/misc/Unsafe;
       3: aload_2
       4: aload_0
       5: getfield      #4                  // Field offset:J
       8: aload_1
       9: invokevirtual #7                  // Method com/esotericsoftware/kryo/io/Input.readFloat:()F
      12: invokevirtual #8                  // Method sun/misc/Unsafe.putFloat:(Ljava/lang/Object;JF)V
      15: return

  public void copy(java.lang.Object, java.lang.Object);
    Code:
       0: invokestatic  #1                  // Method com/esotericsoftware/kryo/util/UnsafeUtil.unsafe:()Lsun/misc/Unsafe;
       3: aload_2
       4: aload_0
       5: getfield      #4                  // Field offset:J
       8: invokestatic  #1                  // Method com/esotericsoftware/kryo/util/UnsafeUtil.unsafe:()Lsun/misc/Unsafe;
      11: aload_1
      12: aload_0
      13: getfield      #4                  // Field offset:J
      16: invokevirtual #5                  // Method sun/misc/Unsafe.getFloat:(Ljava/lang/Object;J)F
      19: invokevirtual #8                  // Method sun/misc/Unsafe.putFloat:(Ljava/lang/Object;JF)V
      22: return
}
