Compiled from "UserEvent.java"
public class org.webswing.toolkit.api.security.UserEvent {
  private org.webswing.toolkit.api.security.WebswingUser user;

  public org.webswing.toolkit.api.security.UserEvent(org.webswing.toolkit.api.security.WebswingUser);
    Code:
       0: aload_0
       1: invokespecial #1                  // Method java/lang/Object."<init>":()V
       4: aload_0
       5: aload_1
       6: putfield      #2                  // Field user:Lorg/webswing/toolkit/api/security/WebswingUser;
       9: return

  public org.webswing.toolkit.api.security.WebswingUser getUser();
    Code:
       0: aload_0
       1: getfield      #2                  // Field user:Lorg/webswing/toolkit/api/security/WebswingUser;
       4: areturn

  public void setUser(org.webswing.toolkit.api.security.WebswingUser);
    Code:
       0: aload_0
       1: aload_1
       2: putfield      #2                  // Field user:Lorg/webswing/toolkit/api/security/WebswingUser;
       5: return
}
