Compiled from "LocalVariableTableParameterNameDiscoverer.java"
class org.springframework.core.LocalVariableTableParameterNameDiscoverer$ParameterNameDiscoveringVisitor extends org.springframework.asm.ClassVisitor {
  private static final java.lang.String STATIC_CLASS_INIT;

  private final java.lang.Class<?> clazz;

  private final java.util.Map<java.lang.reflect.Member, java.lang.String[]> memberMap;

  public org.springframework.core.LocalVariableTableParameterNameDiscoverer$ParameterNameDiscoveringVisitor(java.lang.Class<?>, java.util.Map<java.lang.reflect.Member, java.lang.String[]>);
    Code:
       0: aload_0
       1: ldc           #2                  // int 458752
       3: invokespecial #3                  // Method org/springframework/asm/ClassVisitor."<init>":(I)V
       6: aload_0
       7: aload_1
       8: putfield      #4                  // Field clazz:Ljava/lang/Class;
      11: aload_0
      12: aload_2
      13: putfield      #5                  // Field memberMap:Ljava/util/Map;
      16: return

  public org.springframework.asm.MethodVisitor visitMethod(int, java.lang.String, java.lang.String, java.lang.String, java.lang.String[]);
    Code:
       0: iload_1
       1: invokestatic  #6                  // Method isSyntheticOrBridged:(I)Z
       4: ifne          38
       7: ldc           #8                  // String <clinit>
       9: aload_2
      10: invokevirtual #9                  // Method java/lang/String.equals:(Ljava/lang/Object;)Z
      13: ifne          38
      16: new           #10                 // class org/springframework/core/LocalVariableTableParameterNameDiscoverer$LocalVariableTableVisitor
      19: dup
      20: aload_0
      21: getfield      #4                  // Field clazz:Ljava/lang/Class;
      24: aload_0
      25: getfield      #5                  // Field memberMap:Ljava/util/Map;
      28: aload_2
      29: aload_3
      30: iload_1
      31: invokestatic  #11                 // Method isStatic:(I)Z
      34: invokespecial #12                 // Method org/springframework/core/LocalVariableTableParameterNameDiscoverer$LocalVariableTableVisitor."<init>":(Ljava/lang/Class;Ljava/util/Map;Ljava/lang/String;Ljava/lang/String;Z)V
      37: areturn
      38: aconst_null
      39: areturn

  private static boolean isSyntheticOrBridged(int);
    Code:
       0: iload_0
       1: sipush        4096
       4: iand
       5: iload_0
       6: bipush        64
       8: iand
       9: ior
      10: ifle          17
      13: iconst_1
      14: goto          18
      17: iconst_0
      18: ireturn

  private static boolean isStatic(int);
    Code:
       0: iload_0
       1: bipush        8
       3: iand
       4: ifle          11
       7: iconst_1
       8: goto          12
      11: iconst_0
      12: ireturn
}
