Compiled from "ProtobufDataFormat.java"
public class org.apache.camel.model.dataformat.ProtobufDataFormat extends org.apache.camel.model.DataFormatDefinition {
  private java.lang.String instanceClass;

  private java.lang.Object defaultInstance;

  public org.apache.camel.model.dataformat.ProtobufDataFormat();
    Code:
       0: aload_0
       1: ldc           #26                 // String protobuf
       3: invokespecial #29                 // Method org/apache/camel/model/DataFormatDefinition."<init>":(Ljava/lang/String;)V
       6: return

  public org.apache.camel.model.dataformat.ProtobufDataFormat(java.lang.String);
    Code:
       0: aload_0
       1: invokespecial #33                 // Method "<init>":()V
       4: aload_0
       5: aload_1
       6: invokevirtual #36                 // Method setInstanceClass:(Ljava/lang/String;)V
       9: return

  public java.lang.String getInstanceClass();
    Code:
       0: aload_0
       1: getfield      #40                 // Field instanceClass:Ljava/lang/String;
       4: areturn

  public void setInstanceClass(java.lang.String);
    Code:
       0: aload_0
       1: aload_1
       2: putfield      #40                 // Field instanceClass:Ljava/lang/String;
       5: return

  public java.lang.Object getDefaultInstance();
    Code:
       0: aload_0
       1: getfield      #44                 // Field defaultInstance:Ljava/lang/Object;
       4: areturn

  public void setDefaultInstance(java.lang.Object);
    Code:
       0: aload_0
       1: aload_1
       2: putfield      #44                 // Field defaultInstance:Ljava/lang/Object;
       5: return

  protected void configureDataFormat(org.apache.camel.spi.DataFormat, org.apache.camel.CamelContext);
    Code:
       0: aload_0
       1: getfield      #40                 // Field instanceClass:Ljava/lang/String;
       4: ifnull        19
       7: aload_0
       8: aload_2
       9: aload_1
      10: ldc           #49                 // String instanceClass
      12: aload_0
      13: getfield      #40                 // Field instanceClass:Ljava/lang/String;
      16: invokevirtual #53                 // Method setProperty:(Lorg/apache/camel/CamelContext;Ljava/lang/Object;Ljava/lang/String;Ljava/lang/Object;)V
      19: aload_0
      20: getfield      #44                 // Field defaultInstance:Ljava/lang/Object;
      23: ifnull        38
      26: aload_0
      27: aload_2
      28: aload_1
      29: ldc           #54                 // String defaultInstance
      31: aload_0
      32: getfield      #44                 // Field defaultInstance:Ljava/lang/Object;
      35: invokevirtual #53                 // Method setProperty:(Lorg/apache/camel/CamelContext;Ljava/lang/Object;Ljava/lang/String;Ljava/lang/Object;)V
      38: return
}
