Compiled from "SerializationDataFormat.java"
public class org.apache.camel.model.dataformat.SerializationDataFormat extends org.apache.camel.model.DataFormatDefinition {
  public org.apache.camel.model.dataformat.SerializationDataFormat();
    Code:
       0: aload_0
       1: ldc           #16                 // String serialization
       3: invokespecial #19                 // Method org/apache/camel/model/DataFormatDefinition."<init>":(Ljava/lang/String;)V
       6: return

  protected org.apache.camel.spi.DataFormat createDataFormat(org.apache.camel.spi.RouteContext);
    Code:
       0: new           #25                 // class org/apache/camel/impl/SerializationDataFormat
       3: dup
       4: invokespecial #27                 // Method org/apache/camel/impl/SerializationDataFormat."<init>":()V
       7: areturn
}
