Compiled from "SAAJUtil.java"
public class org.apache.axis2.saaj.util.SAAJUtil {
  public org.apache.axis2.saaj.util.SAAJUtil();
    Code:
       0: aload_0
       1: invokespecial #1                  // Method java/lang/Object."<init>":()V
       4: return

  public static org.w3c.dom.Document getDocumentFromSOAPEnvelope(org.apache.axiom.soap.SOAPEnvelope);
    Code:
       0: aload_0
       1: invokeinterface #2,  1            // InterfaceMethod org/apache/axiom/soap/SOAPEnvelope.build:()V
       6: ldc           #4                  // String dom
       8: invokestatic  #5                  // Method org/apache/axiom/om/OMAbstractFactory.getMetaFactory:(Ljava/lang/String;)Lorg/apache/axiom/om/OMMetaFactory;
      11: astore_2
      12: aload_0
      13: invokeinterface #6,  1            // InterfaceMethod org/apache/axiom/soap/SOAPEnvelope.getNamespace:()Lorg/apache/axiom/om/OMNamespace;
      18: invokeinterface #7,  1            // InterfaceMethod org/apache/axiom/om/OMNamespace.getNamespaceURI:()Ljava/lang/String;
      23: ldc           #9                  // String http://schemas.xmlsoap.org/soap/envelope/
      25: invokevirtual #10                 // Method java/lang/String.equals:(Ljava/lang/Object;)Z
      28: ifeq          44
      31: ldc           #9                  // String http://schemas.xmlsoap.org/soap/envelope/
      33: astore_1
      34: aload_2
      35: invokeinterface #11,  1           // InterfaceMethod org/apache/axiom/om/OMMetaFactory.getSOAP11Factory:()Lorg/apache/axiom/soap/SOAPFactory;
      40: astore_3
      41: goto          54
      44: ldc           #13                 // String http://www.w3.org/2003/05/soap-envelope
      46: astore_1
      47: aload_2
      48: invokeinterface #14,  1           // InterfaceMethod org/apache/axiom/om/OMMetaFactory.getSOAP12Factory:()Lorg/apache/axiom/soap/SOAPFactory;
      53: astore_3
      54: new           #15                 // class org/apache/axiom/soap/impl/builder/StAXSOAPModelBuilder
      57: dup
      58: aload_0
      59: invokeinterface #16,  1           // InterfaceMethod org/apache/axiom/soap/SOAPEnvelope.getXMLStreamReader:()Ljavax/xml/stream/XMLStreamReader;
      64: aload_3
      65: aload_1
      66: invokespecial #17                 // Method org/apache/axiom/soap/impl/builder/StAXSOAPModelBuilder."<init>":(Ljavax/xml/stream/XMLStreamReader;Lorg/apache/axiom/soap/SOAPFactory;Ljava/lang/String;)V
      69: astore        4
      71: aload         4
      73: invokevirtual #18                 // Method org/apache/axiom/soap/impl/builder/StAXSOAPModelBuilder.getSOAPEnvelope:()Lorg/apache/axiom/soap/SOAPEnvelope;
      76: astore        5
      78: aload         5
      80: invokeinterface #2,  1            // InterfaceMethod org/apache/axiom/soap/SOAPEnvelope.build:()V
      85: aload         5
      87: checkcast     #19                 // class org/w3c/dom/Element
      90: astore        6
      92: aload         6
      94: invokeinterface #20,  1           // InterfaceMethod org/w3c/dom/Element.getOwnerDocument:()Lorg/w3c/dom/Document;
      99: areturn

  public static org.w3c.dom.Element toDOOMSOAPEnvelope(org.apache.axiom.soap.SOAPEnvelope);
    Code:
       0: aload_0
       1: invokeinterface #2,  1            // InterfaceMethod org/apache/axiom/soap/SOAPEnvelope.build:()V
       6: ldc           #4                  // String dom
       8: invokestatic  #5                  // Method org/apache/axiom/om/OMAbstractFactory.getMetaFactory:(Ljava/lang/String;)Lorg/apache/axiom/om/OMMetaFactory;
      11: astore_2
      12: aload_0
      13: invokeinterface #6,  1            // InterfaceMethod org/apache/axiom/soap/SOAPEnvelope.getNamespace:()Lorg/apache/axiom/om/OMNamespace;
      18: invokeinterface #7,  1            // InterfaceMethod org/apache/axiom/om/OMNamespace.getNamespaceURI:()Ljava/lang/String;
      23: ldc           #9                  // String http://schemas.xmlsoap.org/soap/envelope/
      25: invokevirtual #10                 // Method java/lang/String.equals:(Ljava/lang/Object;)Z
      28: ifeq          44
      31: ldc           #9                  // String http://schemas.xmlsoap.org/soap/envelope/
      33: astore_1
      34: aload_2
      35: invokeinterface #11,  1           // InterfaceMethod org/apache/axiom/om/OMMetaFactory.getSOAP11Factory:()Lorg/apache/axiom/soap/SOAPFactory;
      40: astore_3
      41: goto          54
      44: ldc           #13                 // String http://www.w3.org/2003/05/soap-envelope
      46: astore_1
      47: aload_2
      48: invokeinterface #11,  1           // InterfaceMethod org/apache/axiom/om/OMMetaFactory.getSOAP11Factory:()Lorg/apache/axiom/soap/SOAPFactory;
      53: astore_3
      54: new           #15                 // class org/apache/axiom/soap/impl/builder/StAXSOAPModelBuilder
      57: dup
      58: aload_0
      59: invokeinterface #16,  1           // InterfaceMethod org/apache/axiom/soap/SOAPEnvelope.getXMLStreamReader:()Ljavax/xml/stream/XMLStreamReader;
      64: aload_3
      65: aload_1
      66: invokespecial #17                 // Method org/apache/axiom/soap/impl/builder/StAXSOAPModelBuilder."<init>":(Ljavax/xml/stream/XMLStreamReader;Lorg/apache/axiom/soap/SOAPFactory;Ljava/lang/String;)V
      69: astore        4
      71: aload         4
      73: invokevirtual #18                 // Method org/apache/axiom/soap/impl/builder/StAXSOAPModelBuilder.getSOAPEnvelope:()Lorg/apache/axiom/soap/SOAPEnvelope;
      76: astore        5
      78: aload         5
      80: invokeinterface #2,  1            // InterfaceMethod org/apache/axiom/soap/SOAPEnvelope.build:()V
      85: aload         5
      87: checkcast     #19                 // class org/w3c/dom/Element
      90: areturn

  public static org.apache.axiom.soap.SOAPEnvelope getSOAPEnvelopeFromDOOMDocument(org.w3c.dom.Document);
    Code:
       0: aload_0
       1: invokeinterface #21,  1           // InterfaceMethod org/w3c/dom/Document.getDocumentElement:()Lorg/w3c/dom/Element;
       6: checkcast     #22                 // class org/apache/axiom/om/OMElement
       9: astore_1
      10: new           #15                 // class org/apache/axiom/soap/impl/builder/StAXSOAPModelBuilder
      13: dup
      14: aload_1
      15: invokeinterface #23,  1           // InterfaceMethod org/apache/axiom/om/OMElement.getXMLStreamReader:()Ljavax/xml/stream/XMLStreamReader;
      20: aconst_null
      21: invokespecial #24                 // Method org/apache/axiom/soap/impl/builder/StAXSOAPModelBuilder."<init>":(Ljavax/xml/stream/XMLStreamReader;Ljava/lang/String;)V
      24: astore_2
      25: aload_2
      26: invokevirtual #18                 // Method org/apache/axiom/soap/impl/builder/StAXSOAPModelBuilder.getSOAPEnvelope:()Lorg/apache/axiom/soap/SOAPEnvelope;
      29: areturn

  public static org.apache.axiom.soap.SOAPEnvelope toOMSOAPEnvelope(org.w3c.dom.Element);
    Code:
       0: aload_0
       1: checkcast     #22                 // class org/apache/axiom/om/OMElement
       4: astore_1
       5: new           #15                 // class org/apache/axiom/soap/impl/builder/StAXSOAPModelBuilder
       8: dup
       9: aload_1
      10: invokeinterface #23,  1           // InterfaceMethod org/apache/axiom/om/OMElement.getXMLStreamReader:()Ljavax/xml/stream/XMLStreamReader;
      15: aconst_null
      16: invokespecial #24                 // Method org/apache/axiom/soap/impl/builder/StAXSOAPModelBuilder."<init>":(Ljavax/xml/stream/XMLStreamReader;Ljava/lang/String;)V
      19: astore_2
      20: aload_2
      21: invokevirtual #18                 // Method org/apache/axiom/soap/impl/builder/StAXSOAPModelBuilder.getSOAPEnvelope:()Lorg/apache/axiom/soap/SOAPEnvelope;
      24: areturn

  public static org.apache.axiom.soap.SOAPEnvelope toOMSOAPEnvelope(javax.xml.soap.SOAPMessage) throws javax.xml.soap.SOAPException;
    Code:
       0: new           #25                 // class org/apache/axiom/attachments/Attachments
       3: dup
       4: invokespecial #26                 // Method org/apache/axiom/attachments/Attachments."<init>":()V
       7: astore_1
       8: aload_0
       9: invokevirtual #27                 // Method javax/xml/soap/SOAPMessage.getAttachments:()Ljava/util/Iterator;
      12: astore_2
      13: aload_2
      14: invokeinterface #28,  1           // InterfaceMethod java/util/Iterator.hasNext:()Z
      19: ifeq          110
      22: aload_2
      23: invokeinterface #29,  1           // InterfaceMethod java/util/Iterator.next:()Ljava/lang/Object;
      28: checkcast     #30                 // class javax/xml/soap/AttachmentPart
      31: astore_3
      32: aload_3
      33: invokevirtual #31                 // Method javax/xml/soap/AttachmentPart.getContentId:()Ljava/lang/String;
      36: astore        4
      38: aload         4
      40: ifnull        107
      43: aload_3
      44: invokevirtual #32                 // Method javax/xml/soap/AttachmentPart.getDataHandler:()Ljavax/activation/DataHandler;
      47: astore        5
      49: aload         5
      51: ifnonnull     64
      54: new           #33                 // class javax/xml/soap/SOAPException
      57: dup
      58: ldc           #34                 // String Attachment with NULL DataHandler
      60: invokespecial #35                 // Method javax/xml/soap/SOAPException."<init>":(Ljava/lang/String;)V
      63: athrow
      64: aload         4
      66: ldc           #36                 // String <
      68: invokevirtual #37                 // Method java/lang/String.startsWith:(Ljava/lang/String;)Z
      71: ifeq          99
      74: aload         4
      76: ldc           #38                 // String >
      78: invokevirtual #39                 // Method java/lang/String.endsWith:(Ljava/lang/String;)Z
      81: ifeq          99
      84: aload         4
      86: iconst_1
      87: aload         4
      89: invokevirtual #40                 // Method java/lang/String.length:()I
      92: iconst_1
      93: isub
      94: invokevirtual #41                 // Method java/lang/String.substring:(II)Ljava/lang/String;
      97: astore        4
      99: aload_1
     100: aload         4
     102: aload         5
     104: invokevirtual #42                 // Method org/apache/axiom/attachments/Attachments.addDataHandler:(Ljava/lang/String;Ljavax/activation/DataHandler;)V
     107: goto          13
     110: aload_0
     111: invokevirtual #43                 // Method javax/xml/soap/SOAPMessage.getSOAPPart:()Ljavax/xml/soap/SOAPPart;
     114: invokevirtual #44                 // Method javax/xml/soap/SOAPPart.getDocumentElement:()Lorg/w3c/dom/Element;
     117: checkcast     #22                 // class org/apache/axiom/om/OMElement
     120: astore_2
     121: new           #45                 // class org/apache/axiom/soap/impl/builder/MTOMStAXSOAPModelBuilder
     124: dup
     125: aload_2
     126: invokeinterface #23,  1           // InterfaceMethod org/apache/axiom/om/OMElement.getXMLStreamReader:()Ljavax/xml/stream/XMLStreamReader;
     131: aload_1
     132: invokespecial #46                 // Method org/apache/axiom/soap/impl/builder/MTOMStAXSOAPModelBuilder."<init>":(Ljavax/xml/stream/XMLStreamReader;Lorg/apache/axiom/attachments/Attachments;)V
     135: astore_3
     136: aload_3
     137: invokevirtual #47                 // Method org/apache/axiom/soap/impl/builder/MTOMStAXSOAPModelBuilder.getSOAPEnvelope:()Lorg/apache/axiom/soap/SOAPEnvelope;
     140: areturn

  public static org.w3c.dom.Element toDOM(org.apache.axiom.om.OMElement) throws java.lang.Exception;
    Code:
       0: new           #48                 // class java/io/ByteArrayOutputStream
       3: dup
       4: invokespecial #49                 // Method java/io/ByteArrayOutputStream."<init>":()V
       7: astore_1
       8: aload_0
       9: aload_1
      10: invokeinterface #50,  2           // InterfaceMethod org/apache/axiom/om/OMElement.serialize:(Ljava/io/OutputStream;)V
      15: new           #51                 // class java/io/ByteArrayInputStream
      18: dup
      19: aload_1
      20: invokevirtual #52                 // Method java/io/ByteArrayOutputStream.toByteArray:()[B
      23: invokespecial #53                 // Method java/io/ByteArrayInputStream."<init>":([B)V
      26: astore_2
      27: invokestatic  #54                 // Method javax/xml/parsers/DocumentBuilderFactory.newInstance:()Ljavax/xml/parsers/DocumentBuilderFactory;
      30: astore_3
      31: aload_3
      32: iconst_1
      33: invokevirtual #55                 // Method javax/xml/parsers/DocumentBuilderFactory.setNamespaceAware:(Z)V
      36: aload_3
      37: invokevirtual #56                 // Method javax/xml/parsers/DocumentBuilderFactory.newDocumentBuilder:()Ljavax/xml/parsers/DocumentBuilder;
      40: aload_2
      41: invokevirtual #57                 // Method javax/xml/parsers/DocumentBuilder.parse:(Ljava/io/InputStream;)Lorg/w3c/dom/Document;
      44: invokeinterface #21,  1           // InterfaceMethod org/w3c/dom/Document.getDocumentElement:()Lorg/w3c/dom/Element;
      49: areturn

  public static javax.xml.soap.MimeHeaders copyMimeHeaders(javax.xml.soap.MimeHeaders);
    Code:
       0: new           #58                 // class javax/xml/soap/MimeHeaders
       3: dup
       4: invokespecial #59                 // Method javax/xml/soap/MimeHeaders."<init>":()V
       7: astore_1
       8: aload_0
       9: invokevirtual #60                 // Method javax/xml/soap/MimeHeaders.getAllHeaders:()Ljava/util/Iterator;
      12: astore_2
      13: aload_2
      14: invokeinterface #28,  1           // InterfaceMethod java/util/Iterator.hasNext:()Z
      19: ifeq          47
      22: aload_2
      23: invokeinterface #29,  1           // InterfaceMethod java/util/Iterator.next:()Ljava/lang/Object;
      28: checkcast     #61                 // class javax/xml/soap/MimeHeader
      31: astore_3
      32: aload_1
      33: aload_3
      34: invokevirtual #62                 // Method javax/xml/soap/MimeHeader.getName:()Ljava/lang/String;
      37: aload_3
      38: invokevirtual #63                 // Method javax/xml/soap/MimeHeader.getValue:()Ljava/lang/String;
      41: invokevirtual #64                 // Method javax/xml/soap/MimeHeaders.addHeader:(Ljava/lang/String;Ljava/lang/String;)V
      44: goto          13
      47: aload_1
      48: areturn

  public static java.lang.String normalizeContentType(java.lang.String);
    Code:
       0: aload_0
       1: ldc           #65                 // String ;
       3: invokevirtual #66                 // Method java/lang/String.indexOf:(Ljava/lang/String;)I
       6: istore_1
       7: iload_1
       8: iconst_m1
       9: if_icmpne     16
      12: aload_0
      13: goto          22
      16: aload_0
      17: iconst_0
      18: iload_1
      19: invokevirtual #41                 // Method java/lang/String.substring:(II)Ljava/lang/String;
      22: invokevirtual #67                 // Method java/lang/String.trim:()Ljava/lang/String;
      25: invokevirtual #68                 // Method java/lang/String.toLowerCase:()Ljava/lang/String;
      28: areturn

  public static boolean compareContentTypes(java.lang.String, java.lang.String);
    Code:
       0: aload_0
       1: ifnonnull     9
       4: ldc           #69                 // String
       6: goto          16
       9: aload_0
      10: invokevirtual #67                 // Method java/lang/String.trim:()Ljava/lang/String;
      13: invokevirtual #68                 // Method java/lang/String.toLowerCase:()Ljava/lang/String;
      16: astore_2
      17: aload_1
      18: ifnonnull     26
      21: ldc           #69                 // String
      23: goto          33
      26: aload_1
      27: invokevirtual #67                 // Method java/lang/String.trim:()Ljava/lang/String;
      30: invokevirtual #68                 // Method java/lang/String.toLowerCase:()Ljava/lang/String;
      33: astore_3
      34: aload_2
      35: aload_3
      36: invokevirtual #10                 // Method java/lang/String.equals:(Ljava/lang/Object;)Z
      39: ireturn
}
