Compiled from "DefaultAccessTimeoutService.java"
public class org.jboss.as.ejb3.component.DefaultAccessTimeoutService implements org.jboss.msc.service.Service<org.jboss.as.ejb3.component.DefaultAccessTimeoutService> {
  public static final org.jboss.msc.service.ServiceName STATEFUL_SERVICE_NAME;

  public static final org.jboss.msc.service.ServiceName SINGLETON_SERVICE_NAME;

  private volatile org.jboss.as.ejb3.concurrency.AccessTimeoutDetails value;

  public org.jboss.as.ejb3.component.DefaultAccessTimeoutService(long);
    Code:
       0: aload_0
       1: invokespecial #1                  // Method java/lang/Object."<init>":()V
       4: aload_0
       5: new           #2                  // class org/jboss/as/ejb3/concurrency/AccessTimeoutDetails
       8: dup
       9: lload_1
      10: getstatic     #3                  // Field java/util/concurrent/TimeUnit.MILLISECONDS:Ljava/util/concurrent/TimeUnit;
      13: invokespecial #4                  // Method org/jboss/as/ejb3/concurrency/AccessTimeoutDetails."<init>":(JLjava/util/concurrent/TimeUnit;)V
      16: putfield      #5                  // Field value:Lorg/jboss/as/ejb3/concurrency/AccessTimeoutDetails;
      19: return

  public final org.jboss.as.ejb3.concurrency.AccessTimeoutDetails getDefaultAccessTimeout();
    Code:
       0: aload_0
       1: getfield      #5                  // Field value:Lorg/jboss/as/ejb3/concurrency/AccessTimeoutDetails;
       4: areturn

  public void setDefaultAccessTimeout(long);
    Code:
       0: aload_0
       1: new           #2                  // class org/jboss/as/ejb3/concurrency/AccessTimeoutDetails
       4: dup
       5: lload_1
       6: getstatic     #3                  // Field java/util/concurrent/TimeUnit.MILLISECONDS:Ljava/util/concurrent/TimeUnit;
       9: invokespecial #4                  // Method org/jboss/as/ejb3/concurrency/AccessTimeoutDetails."<init>":(JLjava/util/concurrent/TimeUnit;)V
      12: putfield      #5                  // Field value:Lorg/jboss/as/ejb3/concurrency/AccessTimeoutDetails;
      15: return

  public void start(org.jboss.msc.service.StartContext) throws org.jboss.msc.service.StartException;
    Code:
       0: return

  public void stop(org.jboss.msc.service.StopContext);
    Code:
       0: return

  public org.jboss.as.ejb3.component.DefaultAccessTimeoutService getValue() throws java.lang.IllegalStateException, java.lang.IllegalArgumentException;
    Code:
       0: aload_0
       1: areturn

  public java.lang.Object getValue() throws java.lang.IllegalStateException, java.lang.IllegalArgumentException;
    Code:
       0: aload_0
       1: invokevirtual #6                  // Method getValue:()Lorg/jboss/as/ejb3/component/DefaultAccessTimeoutService;
       4: areturn

  static {};
    Code:
       0: getstatic     #7                  // Field org/jboss/msc/service/ServiceName.JBOSS:Lorg/jboss/msc/service/ServiceName;
       3: iconst_2
       4: anewarray     #8                  // class java/lang/String
       7: dup
       8: iconst_0
       9: ldc           #9                  // String ejb3
      11: aastore
      12: dup
      13: iconst_1
      14: ldc           #10                 // String statefulDefaultTimeout
      16: aastore
      17: invokevirtual #11                 // Method org/jboss/msc/service/ServiceName.append:([Ljava/lang/String;)Lorg/jboss/msc/service/ServiceName;
      20: putstatic     #12                 // Field STATEFUL_SERVICE_NAME:Lorg/jboss/msc/service/ServiceName;
      23: getstatic     #7                  // Field org/jboss/msc/service/ServiceName.JBOSS:Lorg/jboss/msc/service/ServiceName;
      26: iconst_2
      27: anewarray     #8                  // class java/lang/String
      30: dup
      31: iconst_0
      32: ldc           #9                  // String ejb3
      34: aastore
      35: dup
      36: iconst_1
      37: ldc           #13                 // String singletonDefaultTimeout
      39: aastore
      40: invokevirtual #11                 // Method org/jboss/msc/service/ServiceName.append:([Ljava/lang/String;)Lorg/jboss/msc/service/ServiceName;
      43: putstatic     #14                 // Field SINGLETON_SERVICE_NAME:Lorg/jboss/msc/service/ServiceName;
      46: return
}
