Compiled from "EJBBusinessMethod.java"
public class org.jboss.as.ejb3.component.EJBBusinessMethod implements java.io.Serializable {
  private final java.lang.String methodName;

  private final java.lang.Class<?>[] methodParamTypes;

  private final org.jboss.as.ejb3.component.MethodIntf viewType;

  private final int hashCode;

  public org.jboss.as.ejb3.component.EJBBusinessMethod(java.lang.reflect.Method);
    Code:
       0: aload_0
       1: aload_1
       2: invokevirtual #1                  // Method java/lang/reflect/Method.getName:()Ljava/lang/String;
       5: aload_1
       6: invokevirtual #2                  // Method java/lang/reflect/Method.getParameterTypes:()[Ljava/lang/Class;
       9: invokespecial #3                  // Method "<init>":(Ljava/lang/String;[Ljava/lang/Class;)V
      12: return

  public org.jboss.as.ejb3.component.EJBBusinessMethod(java.lang.String, java.lang.Class<?>...);
    Code:
       0: aload_0
       1: getstatic     #4                  // Field org/jboss/as/ejb3/component/MethodIntf.BEAN:Lorg/jboss/as/ejb3/component/MethodIntf;
       4: aload_1
       5: aload_2
       6: invokespecial #5                  // Method "<init>":(Lorg/jboss/as/ejb3/component/MethodIntf;Ljava/lang/String;[Ljava/lang/Class;)V
       9: return

  public org.jboss.as.ejb3.component.EJBBusinessMethod(org.jboss.as.ejb3.component.MethodIntf, java.lang.String, java.lang.Class<?>...);
    Code:
       0: aload_0
       1: invokespecial #6                  // Method java/lang/Object."<init>":()V
       4: aload_2
       5: ifnonnull     17
       8: getstatic     #7                  // Field org/jboss/as/ejb3/logging/EjbLogger.ROOT_LOGGER:Lorg/jboss/as/ejb3/logging/EjbLogger;
      11: invokeinterface #8,  1            // InterfaceMethod org/jboss/as/ejb3/logging/EjbLogger.methodNameIsNull:()Ljava/lang/IllegalArgumentException;
      16: athrow
      17: aload_0
      18: aload_2
      19: putfield      #9                  // Field methodName:Ljava/lang/String;
      22: aload_0
      23: aload_3
      24: ifnonnull     34
      27: iconst_0
      28: anewarray     #10                 // class java/lang/Class
      31: goto          35
      34: aload_3
      35: putfield      #11                 // Field methodParamTypes:[Ljava/lang/Class;
      38: aload_0
      39: aload_1
      40: ifnonnull     49
      43: getstatic     #4                  // Field org/jboss/as/ejb3/component/MethodIntf.BEAN:Lorg/jboss/as/ejb3/component/MethodIntf;
      46: goto          50
      49: aload_1
      50: putfield      #12                 // Field viewType:Lorg/jboss/as/ejb3/component/MethodIntf;
      53: aload_0
      54: aload_0
      55: invokespecial #13                 // Method generateHashCode:()I
      58: putfield      #14                 // Field hashCode:I
      61: return

  public boolean equals(java.lang.Object);
    Code:
       0: aload_0
       1: aload_1
       2: if_acmpne     7
       5: iconst_1
       6: ireturn
       7: aload_1
       8: ifnull        22
      11: aload_0
      12: invokevirtual #15                 // Method java/lang/Object.getClass:()Ljava/lang/Class;
      15: aload_1
      16: invokevirtual #15                 // Method java/lang/Object.getClass:()Ljava/lang/Class;
      19: if_acmpeq     24
      22: iconst_0
      23: ireturn
      24: aload_1
      25: checkcast     #16                 // class org/jboss/as/ejb3/component/EJBBusinessMethod
      28: astore_2
      29: aload_0
      30: getfield      #9                  // Field methodName:Ljava/lang/String;
      33: aload_2
      34: getfield      #9                  // Field methodName:Ljava/lang/String;
      37: invokevirtual #17                 // Method java/lang/String.equals:(Ljava/lang/Object;)Z
      40: ifne          45
      43: iconst_0
      44: ireturn
      45: aload_0
      46: getfield      #11                 // Field methodParamTypes:[Ljava/lang/Class;
      49: aload_2
      50: getfield      #11                 // Field methodParamTypes:[Ljava/lang/Class;
      53: invokestatic  #18                 // Method java/util/Arrays.equals:([Ljava/lang/Object;[Ljava/lang/Object;)Z
      56: ifne          61
      59: iconst_0
      60: ireturn
      61: aload_0
      62: getfield      #12                 // Field viewType:Lorg/jboss/as/ejb3/component/MethodIntf;
      65: aload_2
      66: getfield      #12                 // Field viewType:Lorg/jboss/as/ejb3/component/MethodIntf;
      69: if_acmpeq     74
      72: iconst_0
      73: ireturn
      74: iconst_1
      75: ireturn

  public int hashCode();
    Code:
       0: aload_0
       1: getfield      #14                 // Field hashCode:I
       4: ireturn

  private int generateHashCode();
    Code:
       0: aload_0
       1: getfield      #9                  // Field methodName:Ljava/lang/String;
       4: invokevirtual #19                 // Method java/lang/String.hashCode:()I
       7: istore_1
       8: bipush        31
      10: iload_1
      11: imul
      12: aload_0
      13: getfield      #11                 // Field methodParamTypes:[Ljava/lang/Class;
      16: invokestatic  #20                 // Method java/util/Arrays.hashCode:([Ljava/lang/Object;)I
      19: iadd
      20: istore_1
      21: bipush        31
      23: iload_1
      24: imul
      25: aload_0
      26: getfield      #12                 // Field viewType:Lorg/jboss/as/ejb3/component/MethodIntf;
      29: invokevirtual #21                 // Method org/jboss/as/ejb3/component/MethodIntf.hashCode:()I
      32: iadd
      33: istore_1
      34: iload_1
      35: ireturn
}
