Compiled from "EJBComponentDescription.java"
class org.jboss.as.ejb3.component.EJBComponentDescription$EjbJarConfigurationConfigurator implements org.jboss.as.ee.component.ComponentConfigurator {
  final org.jboss.as.ejb3.component.EJBComponentDescription this$0;

  private org.jboss.as.ejb3.component.EJBComponentDescription$EjbJarConfigurationConfigurator(org.jboss.as.ejb3.component.EJBComponentDescription);
    Code:
       0: aload_0
       1: aload_1
       2: putfield      #2                  // Field this$0:Lorg/jboss/as/ejb3/component/EJBComponentDescription;
       5: aload_0
       6: invokespecial #3                  // Method java/lang/Object."<init>":()V
       9: return

  public void configure(org.jboss.as.server.deployment.DeploymentPhaseContext, org.jboss.as.ee.component.ComponentDescription, org.jboss.as.ee.component.ComponentConfiguration) throws org.jboss.as.server.deployment.DeploymentUnitProcessingException;
    Code:
       0: aload_1
       1: invokeinterface #4,  1            // InterfaceMethod org/jboss/as/server/deployment/DeploymentPhaseContext.getDeploymentUnit:()Lorg/jboss/as/server/deployment/DeploymentUnit;
       6: astore        4
       8: aload         4
      10: getstatic     #5                  // Field org/jboss/as/ejb3/deployment/EjbDeploymentAttachmentKeys.APPLICATION_EXCEPTION_DETAILS:Lorg/jboss/as/server/deployment/AttachmentKey;
      13: invokeinterface #6,  2            // InterfaceMethod org/jboss/as/server/deployment/DeploymentUnit.getAttachment:(Lorg/jboss/as/server/deployment/AttachmentKey;)Ljava/lang/Object;
      18: checkcast     #7                  // class org/jboss/as/ejb3/deployment/ApplicationExceptions
      21: astore        5
      23: aload         5
      25: ifnonnull     39
      28: getstatic     #8                  // Field org/jboss/as/ejb3/logging/EjbLogger.ROOT_LOGGER:Lorg/jboss/as/ejb3/logging/EjbLogger;
      31: aload         4
      33: invokeinterface #9,  2            // InterfaceMethod org/jboss/as/ejb3/logging/EjbLogger.ejbJarConfigNotFound:(Lorg/jboss/as/server/deployment/DeploymentUnit;)Lorg/jboss/as/server/deployment/DeploymentUnitProcessingException;
      38: athrow
      39: aload_3
      40: invokevirtual #10                 // Method org/jboss/as/ee/component/ComponentConfiguration.getComponentCreateServiceFactory:()Lorg/jboss/as/ee/component/ComponentCreateServiceFactory;
      43: checkcast     #11                 // class org/jboss/as/ejb3/component/EJBComponentCreateServiceFactory
      46: astore        6
      48: aload         6
      50: aload         5
      52: invokevirtual #12                 // Method org/jboss/as/ejb3/component/EJBComponentCreateServiceFactory.setEjbJarConfiguration:(Lorg/jboss/as/ejb3/deployment/ApplicationExceptions;)V
      55: return

  org.jboss.as.ejb3.component.EJBComponentDescription$EjbJarConfigurationConfigurator(org.jboss.as.ejb3.component.EJBComponentDescription, org.jboss.as.ejb3.component.EJBComponentDescription$1);
    Code:
       0: aload_0
       1: aload_1
       2: invokespecial #1                  // Method "<init>":(Lorg/jboss/as/ejb3/component/EJBComponentDescription;)V
       5: return
}
