Compiled from "EJBComponentDescription.java"
class org.jboss.as.ejb3.component.EJBComponentDescription$ToStringMethodInterceptor implements org.jboss.invocation.Interceptor {
  private final java.lang.String name;

  public org.jboss.as.ejb3.component.EJBComponentDescription$ToStringMethodInterceptor(java.lang.String);
    Code:
       0: aload_0
       1: invokespecial #1                  // Method java/lang/Object."<init>":()V
       4: aload_0
       5: aload_1
       6: putfield      #2                  // Field name:Ljava/lang/String;
       9: return

  public java.lang.Object processInvocation(org.jboss.invocation.InterceptorContext) throws java.lang.Exception;
    Code:
       0: aload_1
       1: ldc           #3                  // class org/jboss/as/ee/component/ComponentView
       3: invokevirtual #4                  // Method org/jboss/invocation/InterceptorContext.getPrivateData:(Ljava/lang/Class;)Ljava/lang/Object;
       6: checkcast     #3                  // class org/jboss/as/ee/component/ComponentView
       9: astore_2
      10: aload_2
      11: ifnonnull     24
      14: getstatic     #5                  // Field org/jboss/as/ejb3/logging/EjbLogger.ROOT_LOGGER:Lorg/jboss/as/ejb3/logging/EjbLogger;
      17: aload_1
      18: invokeinterface #6,  2            // InterfaceMethod org/jboss/as/ejb3/logging/EjbLogger.componentViewNotAvailableInContext:(Lorg/jboss/invocation/InterceptorContext;)Ljava/lang/IllegalStateException;
      23: athrow
      24: new           #7                  // class java/lang/StringBuilder
      27: dup
      28: invokespecial #8                  // Method java/lang/StringBuilder."<init>":()V
      31: ldc           #9                  // String Proxy for view class:
      33: invokevirtual #10                 // Method java/lang/StringBuilder.append:(Ljava/lang/String;)Ljava/lang/StringBuilder;
      36: aload_2
      37: invokeinterface #11,  1           // InterfaceMethod org/jboss/as/ee/component/ComponentView.getViewClass:()Ljava/lang/Class;
      42: invokevirtual #12                 // Method java/lang/Class.getName:()Ljava/lang/String;
      45: invokevirtual #10                 // Method java/lang/StringBuilder.append:(Ljava/lang/String;)Ljava/lang/StringBuilder;
      48: ldc           #13                 // String  of EJB:
      50: invokevirtual #10                 // Method java/lang/StringBuilder.append:(Ljava/lang/String;)Ljava/lang/StringBuilder;
      53: aload_0
      54: getfield      #2                  // Field name:Ljava/lang/String;
      57: invokevirtual #10                 // Method java/lang/StringBuilder.append:(Ljava/lang/String;)Ljava/lang/StringBuilder;
      60: invokevirtual #14                 // Method java/lang/StringBuilder.toString:()Ljava/lang/String;
      63: areturn
}
