Compiled from "JacksonMapper.java"
public class org.springframework.cloud.function.json.JacksonMapper implements org.springframework.cloud.function.json.JsonMapper {
  private final com.fasterxml.jackson.databind.ObjectMapper mapper;

  public org.springframework.cloud.function.json.JacksonMapper(com.fasterxml.jackson.databind.ObjectMapper);
    Code:
       0: aload_0
       1: invokespecial #1                  // Method java/lang/Object."<init>":()V
       4: aload_0
       5: aload_1
       6: putfield      #2                  // Field mapper:Lcom/fasterxml/jackson/databind/ObjectMapper;
       9: return

  public <T> T toObject(java.lang.String, java.lang.reflect.Type);
    Code:
       0: aload_0
       1: getfield      #2                  // Field mapper:Lcom/fasterxml/jackson/databind/ObjectMapper;
       4: aload_1
       5: invokestatic  #3                  // Method com/fasterxml/jackson/databind/type/TypeFactory.defaultInstance:()Lcom/fasterxml/jackson/databind/type/TypeFactory;
       8: aload_2
       9: invokevirtual #4                  // Method com/fasterxml/jackson/databind/type/TypeFactory.constructType:(Ljava/lang/reflect/Type;)Lcom/fasterxml/jackson/databind/JavaType;
      12: invokevirtual #5                  // Method com/fasterxml/jackson/databind/ObjectMapper.readValue:(Ljava/lang/String;Lcom/fasterxml/jackson/databind/JavaType;)Ljava/lang/Object;
      15: areturn
      16: astore_3
      17: new           #7                  // class java/lang/IllegalArgumentException
      20: dup
      21: new           #8                  // class java/lang/StringBuilder
      24: dup
      25: invokespecial #9                  // Method java/lang/StringBuilder."<init>":()V
      28: ldc           #10                 // String Cannot convert JSON
      30: invokevirtual #11                 // Method java/lang/StringBuilder.append:(Ljava/lang/String;)Ljava/lang/StringBuilder;
      33: aload_1
      34: invokevirtual #11                 // Method java/lang/StringBuilder.append:(Ljava/lang/String;)Ljava/lang/StringBuilder;
      37: invokevirtual #12                 // Method java/lang/StringBuilder.toString:()Ljava/lang/String;
      40: aload_3
      41: invokespecial #13                 // Method java/lang/IllegalArgumentException."<init>":(Ljava/lang/String;Ljava/lang/Throwable;)V
      44: athrow
    Exception table:
       from    to  target type
           0    15    16   Class java/lang/Exception

  public java.lang.String toString(java.lang.Object);
    Code:
       0: aload_0
       1: getfield      #2                  // Field mapper:Lcom/fasterxml/jackson/databind/ObjectMapper;
       4: aload_1
       5: invokevirtual #14                 // Method com/fasterxml/jackson/databind/ObjectMapper.writeValueAsString:(Ljava/lang/Object;)Ljava/lang/String;
       8: areturn
       9: astore_2
      10: new           #7                  // class java/lang/IllegalArgumentException
      13: dup
      14: ldc           #16                 // String Cannot convert to JSON
      16: aload_2
      17: invokespecial #13                 // Method java/lang/IllegalArgumentException."<init>":(Ljava/lang/String;Ljava/lang/Throwable;)V
      20: athrow
    Exception table:
       from    to  target type
           0     8     9   Class com/fasterxml/jackson/core/JsonProcessingException
}
