Compiled from "TypeList.java"
public class org.assertj.core.internal.bytebuddy.description.type.TypeList$Generic$Empty extends org.assertj.core.internal.bytebuddy.matcher.FilterableList$Empty<org.assertj.core.internal.bytebuddy.description.type.TypeDescription$Generic, org.assertj.core.internal.bytebuddy.description.type.TypeList$Generic> implements org.assertj.core.internal.bytebuddy.description.type.TypeList$Generic {
  public org.assertj.core.internal.bytebuddy.description.type.TypeList$Generic$Empty();
    Code:
       0: aload_0
       1: invokespecial #35                 // Method org/assertj/core/internal/bytebuddy/matcher/FilterableList$Empty."<init>":()V
       4: return

  public org.assertj.core.internal.bytebuddy.description.type.TypeList asErasures();
    Code:
       0: new           #31                 // class org/assertj/core/internal/bytebuddy/description/type/TypeList$Empty
       3: dup
       4: invokespecial #40                 // Method org/assertj/core/internal/bytebuddy/description/type/TypeList$Empty."<init>":()V
       7: areturn

  public org.assertj.core.internal.bytebuddy.description.type.TypeList$Generic asRawTypes();
    Code:
       0: aload_0
       1: areturn

  public org.assertj.core.internal.bytebuddy.description.type.TypeList$Generic accept(org.assertj.core.internal.bytebuddy.description.type.TypeDescription$Generic$Visitor<? extends org.assertj.core.internal.bytebuddy.description.type.TypeDescription$Generic>);
    Code:
       0: new           #2                  // class org/assertj/core/internal/bytebuddy/description/type/TypeList$Generic$Empty
       3: dup
       4: invokespecial #45                 // Method "<init>":()V
       7: areturn

  public org.assertj.core.internal.bytebuddy.description.ByteCodeElement$Token$TokenList<org.assertj.core.internal.bytebuddy.description.type.TypeVariableToken> asTokenList(org.assertj.core.internal.bytebuddy.matcher.ElementMatcher<? super org.assertj.core.internal.bytebuddy.description.type.TypeDescription>);
    Code:
       0: new           #26                 // class org/assertj/core/internal/bytebuddy/description/ByteCodeElement$Token$TokenList
       3: dup
       4: iconst_0
       5: anewarray     #52                 // class org/assertj/core/internal/bytebuddy/description/type/TypeVariableToken
       8: invokespecial #55                 // Method org/assertj/core/internal/bytebuddy/description/ByteCodeElement$Token$TokenList."<init>":([Lorg/assertj/core/internal/bytebuddy/description/ByteCodeElement$Token;)V
      11: areturn

  public int getStackSize();
    Code:
       0: iconst_0
       1: ireturn
}
