Compiled from "TypeDescription.java"
public final class org.assertj.core.internal.bytebuddy.description.type.TypeDescription$Generic$Visitor$Assigner$Dispatcher$ForParameterizedType$ParameterAssigner extends java.lang.Enum<org.assertj.core.internal.bytebuddy.description.type.TypeDescription$Generic$Visitor$Assigner$Dispatcher$ForParameterizedType$ParameterAssigner> implements org.assertj.core.internal.bytebuddy.description.type.TypeDescription$Generic$Visitor<org.assertj.core.internal.bytebuddy.description.type.TypeDescription$Generic$Visitor$Assigner$Dispatcher> {
  public static final org.assertj.core.internal.bytebuddy.description.type.TypeDescription$Generic$Visitor$Assigner$Dispatcher$ForParameterizedType$ParameterAssigner INSTANCE;

  private static final org.assertj.core.internal.bytebuddy.description.type.TypeDescription$Generic$Visitor$Assigner$Dispatcher$ForParameterizedType$ParameterAssigner[] $VALUES;

  public static org.assertj.core.internal.bytebuddy.description.type.TypeDescription$Generic$Visitor$Assigner$Dispatcher$ForParameterizedType$ParameterAssigner[] values();
    Code:
       0: getstatic     #45                 // Field $VALUES:[Lorg/assertj/core/internal/bytebuddy/description/type/TypeDescription$Generic$Visitor$Assigner$Dispatcher$ForParameterizedType$ParameterAssigner;
       3: invokevirtual #50                 // Method "[Lorg/assertj/core/internal/bytebuddy/description/type/TypeDescription$Generic$Visitor$Assigner$Dispatcher$ForParameterizedType$ParameterAssigner;".clone:()Ljava/lang/Object;
       6: checkcast     #46                 // class "[Lorg/assertj/core/internal/bytebuddy/description/type/TypeDescription$Generic$Visitor$Assigner$Dispatcher$ForParameterizedType$ParameterAssigner;"
       9: areturn

  public static org.assertj.core.internal.bytebuddy.description.type.TypeDescription$Generic$Visitor$Assigner$Dispatcher$ForParameterizedType$ParameterAssigner valueOf(java.lang.String);
    Code:
       0: ldc           #2                  // class org/assertj/core/internal/bytebuddy/description/type/TypeDescription$Generic$Visitor$Assigner$Dispatcher$ForParameterizedType$ParameterAssigner
       2: aload_0
       3: invokestatic  #55                 // Method java/lang/Enum.valueOf:(Ljava/lang/Class;Ljava/lang/String;)Ljava/lang/Enum;
       6: checkcast     #2                  // class org/assertj/core/internal/bytebuddy/description/type/TypeDescription$Generic$Visitor$Assigner$Dispatcher$ForParameterizedType$ParameterAssigner
       9: areturn

  private org.assertj.core.internal.bytebuddy.description.type.TypeDescription$Generic$Visitor$Assigner$Dispatcher$ForParameterizedType$ParameterAssigner();
    Code:
       0: aload_0
       1: aload_1
       2: iload_2
       3: invokespecial #61                 // Method java/lang/Enum."<init>":(Ljava/lang/String;I)V
       6: return

  public org.assertj.core.internal.bytebuddy.description.type.TypeDescription$Generic$Visitor$Assigner$Dispatcher onGenericArray(org.assertj.core.internal.bytebuddy.description.type.TypeDescription$Generic);
    Code:
       0: new           #32                 // class org/assertj/core/internal/bytebuddy/description/type/TypeDescription$Generic$Visitor$Assigner$Dispatcher$ForParameterizedType$ParameterAssigner$InvariantBinding
       3: dup
       4: aload_1
       5: invokespecial #67                 // Method org/assertj/core/internal/bytebuddy/description/type/TypeDescription$Generic$Visitor$Assigner$Dispatcher$ForParameterizedType$ParameterAssigner$InvariantBinding."<init>":(Lorg/assertj/core/internal/bytebuddy/description/type/TypeDescription$Generic;)V
       8: areturn

  public org.assertj.core.internal.bytebuddy.description.type.TypeDescription$Generic$Visitor$Assigner$Dispatcher onWildcard(org.assertj.core.internal.bytebuddy.description.type.TypeDescription$Generic);
    Code:
       0: aload_1
       1: invokeinterface #74,  1           // InterfaceMethod org/assertj/core/internal/bytebuddy/description/type/TypeDescription$Generic.getLowerBounds:()Lorg/assertj/core/internal/bytebuddy/description/type/TypeList$Generic;
       6: astore_2
       7: aload_2
       8: invokeinterface #78,  1           // InterfaceMethod org/assertj/core/internal/bytebuddy/description/type/TypeList$Generic.isEmpty:()Z
      13: ifeq          40
      16: new           #29                 // class org/assertj/core/internal/bytebuddy/description/type/TypeDescription$Generic$Visitor$Assigner$Dispatcher$ForParameterizedType$ParameterAssigner$CovariantBinding
      19: dup
      20: aload_1
      21: invokeinterface #81,  1           // InterfaceMethod org/assertj/core/internal/bytebuddy/description/type/TypeDescription$Generic.getUpperBounds:()Lorg/assertj/core/internal/bytebuddy/description/type/TypeList$Generic;
      26: invokeinterface #84,  1           // InterfaceMethod org/assertj/core/internal/bytebuddy/description/type/TypeList$Generic.getOnly:()Ljava/lang/Object;
      31: checkcast     #10                 // class org/assertj/core/internal/bytebuddy/description/type/TypeDescription$Generic
      34: invokespecial #85                 // Method org/assertj/core/internal/bytebuddy/description/type/TypeDescription$Generic$Visitor$Assigner$Dispatcher$ForParameterizedType$ParameterAssigner$CovariantBinding."<init>":(Lorg/assertj/core/internal/bytebuddy/description/type/TypeDescription$Generic;)V
      37: goto          56
      40: new           #26                 // class org/assertj/core/internal/bytebuddy/description/type/TypeDescription$Generic$Visitor$Assigner$Dispatcher$ForParameterizedType$ParameterAssigner$ContravariantBinding
      43: dup
      44: aload_2
      45: invokeinterface #84,  1           // InterfaceMethod org/assertj/core/internal/bytebuddy/description/type/TypeList$Generic.getOnly:()Ljava/lang/Object;
      50: checkcast     #10                 // class org/assertj/core/internal/bytebuddy/description/type/TypeDescription$Generic
      53: invokespecial #86                 // Method org/assertj/core/internal/bytebuddy/description/type/TypeDescription$Generic$Visitor$Assigner$Dispatcher$ForParameterizedType$ParameterAssigner$ContravariantBinding."<init>":(Lorg/assertj/core/internal/bytebuddy/description/type/TypeDescription$Generic;)V
      56: areturn

  public org.assertj.core.internal.bytebuddy.description.type.TypeDescription$Generic$Visitor$Assigner$Dispatcher onParameterizedType(org.assertj.core.internal.bytebuddy.description.type.TypeDescription$Generic);
    Code:
       0: new           #32                 // class org/assertj/core/internal/bytebuddy/description/type/TypeDescription$Generic$Visitor$Assigner$Dispatcher$ForParameterizedType$ParameterAssigner$InvariantBinding
       3: dup
       4: aload_1
       5: invokespecial #67                 // Method org/assertj/core/internal/bytebuddy/description/type/TypeDescription$Generic$Visitor$Assigner$Dispatcher$ForParameterizedType$ParameterAssigner$InvariantBinding."<init>":(Lorg/assertj/core/internal/bytebuddy/description/type/TypeDescription$Generic;)V
       8: areturn

  public org.assertj.core.internal.bytebuddy.description.type.TypeDescription$Generic$Visitor$Assigner$Dispatcher onTypeVariable(org.assertj.core.internal.bytebuddy.description.type.TypeDescription$Generic);
    Code:
       0: new           #32                 // class org/assertj/core/internal/bytebuddy/description/type/TypeDescription$Generic$Visitor$Assigner$Dispatcher$ForParameterizedType$ParameterAssigner$InvariantBinding
       3: dup
       4: aload_1
       5: invokespecial #67                 // Method org/assertj/core/internal/bytebuddy/description/type/TypeDescription$Generic$Visitor$Assigner$Dispatcher$ForParameterizedType$ParameterAssigner$InvariantBinding."<init>":(Lorg/assertj/core/internal/bytebuddy/description/type/TypeDescription$Generic;)V
       8: areturn

  public org.assertj.core.internal.bytebuddy.description.type.TypeDescription$Generic$Visitor$Assigner$Dispatcher onNonGenericType(org.assertj.core.internal.bytebuddy.description.type.TypeDescription$Generic);
    Code:
       0: new           #32                 // class org/assertj/core/internal/bytebuddy/description/type/TypeDescription$Generic$Visitor$Assigner$Dispatcher$ForParameterizedType$ParameterAssigner$InvariantBinding
       3: dup
       4: aload_1
       5: invokespecial #67                 // Method org/assertj/core/internal/bytebuddy/description/type/TypeDescription$Generic$Visitor$Assigner$Dispatcher$ForParameterizedType$ParameterAssigner$InvariantBinding."<init>":(Lorg/assertj/core/internal/bytebuddy/description/type/TypeDescription$Generic;)V
       8: areturn

  public java.lang.Object onNonGenericType(org.assertj.core.internal.bytebuddy.description.type.TypeDescription$Generic);
    Code:
       0: aload_0
       1: aload_1
       2: invokevirtual #98                 // Method onNonGenericType:(Lorg/assertj/core/internal/bytebuddy/description/type/TypeDescription$Generic;)Lorg/assertj/core/internal/bytebuddy/description/type/TypeDescription$Generic$Visitor$Assigner$Dispatcher;
       5: areturn

  public java.lang.Object onTypeVariable(org.assertj.core.internal.bytebuddy.description.type.TypeDescription$Generic);
    Code:
       0: aload_0
       1: aload_1
       2: invokevirtual #100                // Method onTypeVariable:(Lorg/assertj/core/internal/bytebuddy/description/type/TypeDescription$Generic;)Lorg/assertj/core/internal/bytebuddy/description/type/TypeDescription$Generic$Visitor$Assigner$Dispatcher;
       5: areturn

  public java.lang.Object onParameterizedType(org.assertj.core.internal.bytebuddy.description.type.TypeDescription$Generic);
    Code:
       0: aload_0
       1: aload_1
       2: invokevirtual #102                // Method onParameterizedType:(Lorg/assertj/core/internal/bytebuddy/description/type/TypeDescription$Generic;)Lorg/assertj/core/internal/bytebuddy/description/type/TypeDescription$Generic$Visitor$Assigner$Dispatcher;
       5: areturn

  public java.lang.Object onWildcard(org.assertj.core.internal.bytebuddy.description.type.TypeDescription$Generic);
    Code:
       0: aload_0
       1: aload_1
       2: invokevirtual #104                // Method onWildcard:(Lorg/assertj/core/internal/bytebuddy/description/type/TypeDescription$Generic;)Lorg/assertj/core/internal/bytebuddy/description/type/TypeDescription$Generic$Visitor$Assigner$Dispatcher;
       5: areturn

  public java.lang.Object onGenericArray(org.assertj.core.internal.bytebuddy.description.type.TypeDescription$Generic);
    Code:
       0: aload_0
       1: aload_1
       2: invokevirtual #106                // Method onGenericArray:(Lorg/assertj/core/internal/bytebuddy/description/type/TypeDescription$Generic;)Lorg/assertj/core/internal/bytebuddy/description/type/TypeDescription$Generic$Visitor$Assigner$Dispatcher;
       5: areturn

  static {};
    Code:
       0: new           #2                  // class org/assertj/core/internal/bytebuddy/description/type/TypeDescription$Generic$Visitor$Assigner$Dispatcher$ForParameterizedType$ParameterAssigner
       3: dup
       4: ldc           #109                // String INSTANCE
       6: iconst_0
       7: invokespecial #110                // Method "<init>":(Ljava/lang/String;I)V
      10: putstatic     #112                // Field INSTANCE:Lorg/assertj/core/internal/bytebuddy/description/type/TypeDescription$Generic$Visitor$Assigner$Dispatcher$ForParameterizedType$ParameterAssigner;
      13: iconst_1
      14: anewarray     #2                  // class org/assertj/core/internal/bytebuddy/description/type/TypeDescription$Generic$Visitor$Assigner$Dispatcher$ForParameterizedType$ParameterAssigner
      17: dup
      18: iconst_0
      19: getstatic     #112                // Field INSTANCE:Lorg/assertj/core/internal/bytebuddy/description/type/TypeDescription$Generic$Visitor$Assigner$Dispatcher$ForParameterizedType$ParameterAssigner;
      22: aastore
      23: putstatic     #45                 // Field $VALUES:[Lorg/assertj/core/internal/bytebuddy/description/type/TypeDescription$Generic$Visitor$Assigner$Dispatcher$ForParameterizedType$ParameterAssigner;
      26: return
}
