Compiled from "RequestOp.java"
public final class org.apache.bookkeeper.stream.proto.kv.rpc.RequestOp$Builder extends com.google.protobuf.GeneratedMessageV3$Builder<org.apache.bookkeeper.stream.proto.kv.rpc.RequestOp$Builder> implements org.apache.bookkeeper.stream.proto.kv.rpc.RequestOpOrBuilder {
  private int requestCase_;

  private java.lang.Object request_;

  private com.google.protobuf.SingleFieldBuilderV3<org.apache.bookkeeper.stream.proto.kv.rpc.RangeRequest, org.apache.bookkeeper.stream.proto.kv.rpc.RangeRequest$Builder, org.apache.bookkeeper.stream.proto.kv.rpc.RangeRequestOrBuilder> requestRangeBuilder_;

  private com.google.protobuf.SingleFieldBuilderV3<org.apache.bookkeeper.stream.proto.kv.rpc.PutRequest, org.apache.bookkeeper.stream.proto.kv.rpc.PutRequest$Builder, org.apache.bookkeeper.stream.proto.kv.rpc.PutRequestOrBuilder> requestPutBuilder_;

  private com.google.protobuf.SingleFieldBuilderV3<org.apache.bookkeeper.stream.proto.kv.rpc.DeleteRangeRequest, org.apache.bookkeeper.stream.proto.kv.rpc.DeleteRangeRequest$Builder, org.apache.bookkeeper.stream.proto.kv.rpc.DeleteRangeRequestOrBuilder> requestDeleteRangeBuilder_;

  public static final com.google.protobuf.Descriptors$Descriptor getDescriptor();
    Code:
       0: getstatic     #3                  // Field org/apache/bookkeeper/stream/proto/kv/rpc/KvRpc.internal_static_bookkeeper_proto_kv_rpc_RequestOp_descriptor:Lcom/google/protobuf/Descriptors$Descriptor;
       3: areturn

  protected com.google.protobuf.GeneratedMessageV3$FieldAccessorTable internalGetFieldAccessorTable();
    Code:
       0: getstatic     #4                  // Field org/apache/bookkeeper/stream/proto/kv/rpc/KvRpc.internal_static_bookkeeper_proto_kv_rpc_RequestOp_fieldAccessorTable:Lcom/google/protobuf/GeneratedMessageV3$FieldAccessorTable;
       3: ldc           #5                  // class org/apache/bookkeeper/stream/proto/kv/rpc/RequestOp
       5: ldc           #6                  // class org/apache/bookkeeper/stream/proto/kv/rpc/RequestOp$Builder
       7: invokevirtual #7                  // Method com/google/protobuf/GeneratedMessageV3$FieldAccessorTable.ensureFieldAccessorsInitialized:(Ljava/lang/Class;Ljava/lang/Class;)Lcom/google/protobuf/GeneratedMessageV3$FieldAccessorTable;
      10: areturn

  private org.apache.bookkeeper.stream.proto.kv.rpc.RequestOp$Builder();
    Code:
       0: aload_0
       1: invokespecial #8                  // Method com/google/protobuf/GeneratedMessageV3$Builder."<init>":()V
       4: aload_0
       5: iconst_0
       6: putfield      #9                  // Field requestCase_:I
       9: aload_0
      10: invokespecial #10                 // Method maybeForceBuilderInitialization:()V
      13: return

  private org.apache.bookkeeper.stream.proto.kv.rpc.RequestOp$Builder(com.google.protobuf.GeneratedMessageV3$BuilderParent);
    Code:
       0: aload_0
       1: aload_1
       2: invokespecial #11                 // Method com/google/protobuf/GeneratedMessageV3$Builder."<init>":(Lcom/google/protobuf/GeneratedMessageV3$BuilderParent;)V
       5: aload_0
       6: iconst_0
       7: putfield      #9                  // Field requestCase_:I
      10: aload_0
      11: invokespecial #10                 // Method maybeForceBuilderInitialization:()V
      14: return

  private void maybeForceBuilderInitialization();
    Code:
       0: invokestatic  #12                 // Method org/apache/bookkeeper/stream/proto/kv/rpc/RequestOp.access$200:()Z
       3: ifeq          6
       6: return

  public org.apache.bookkeeper.stream.proto.kv.rpc.RequestOp$Builder clear();
    Code:
       0: aload_0
       1: invokespecial #13                 // Method com/google/protobuf/GeneratedMessageV3$Builder.clear:()Lcom/google/protobuf/GeneratedMessageV3$Builder;
       4: pop
       5: aload_0
       6: iconst_0
       7: putfield      #9                  // Field requestCase_:I
      10: aload_0
      11: aconst_null
      12: putfield      #14                 // Field request_:Ljava/lang/Object;
      15: aload_0
      16: areturn

  public com.google.protobuf.Descriptors$Descriptor getDescriptorForType();
    Code:
       0: getstatic     #3                  // Field org/apache/bookkeeper/stream/proto/kv/rpc/KvRpc.internal_static_bookkeeper_proto_kv_rpc_RequestOp_descriptor:Lcom/google/protobuf/Descriptors$Descriptor;
       3: areturn

  public org.apache.bookkeeper.stream.proto.kv.rpc.RequestOp getDefaultInstanceForType();
    Code:
       0: invokestatic  #15                 // Method org/apache/bookkeeper/stream/proto/kv/rpc/RequestOp.getDefaultInstance:()Lorg/apache/bookkeeper/stream/proto/kv/rpc/RequestOp;
       3: areturn

  public org.apache.bookkeeper.stream.proto.kv.rpc.RequestOp build();
    Code:
       0: aload_0
       1: invokevirtual #16                 // Method buildPartial:()Lorg/apache/bookkeeper/stream/proto/kv/rpc/RequestOp;
       4: astore_1
       5: aload_1
       6: invokevirtual #17                 // Method org/apache/bookkeeper/stream/proto/kv/rpc/RequestOp.isInitialized:()Z
       9: ifne          17
      12: aload_1
      13: invokestatic  #18                 // Method newUninitializedMessageException:(Lcom/google/protobuf/Message;)Lcom/google/protobuf/UninitializedMessageException;
      16: athrow
      17: aload_1
      18: areturn

  public org.apache.bookkeeper.stream.proto.kv.rpc.RequestOp buildPartial();
    Code:
       0: new           #5                  // class org/apache/bookkeeper/stream/proto/kv/rpc/RequestOp
       3: dup
       4: aload_0
       5: aconst_null
       6: invokespecial #19                 // Method org/apache/bookkeeper/stream/proto/kv/rpc/RequestOp."<init>":(Lcom/google/protobuf/GeneratedMessageV3$Builder;Lorg/apache/bookkeeper/stream/proto/kv/rpc/RequestOp$1;)V
       9: astore_1
      10: aload_0
      11: getfield      #9                  // Field requestCase_:I
      14: iconst_1
      15: if_icmpne     49
      18: aload_0
      19: getfield      #20                 // Field requestRangeBuilder_:Lcom/google/protobuf/SingleFieldBuilderV3;
      22: ifnonnull     37
      25: aload_1
      26: aload_0
      27: getfield      #14                 // Field request_:Ljava/lang/Object;
      30: invokestatic  #21                 // Method org/apache/bookkeeper/stream/proto/kv/rpc/RequestOp.access$402:(Lorg/apache/bookkeeper/stream/proto/kv/rpc/RequestOp;Ljava/lang/Object;)Ljava/lang/Object;
      33: pop
      34: goto          49
      37: aload_1
      38: aload_0
      39: getfield      #20                 // Field requestRangeBuilder_:Lcom/google/protobuf/SingleFieldBuilderV3;
      42: invokevirtual #22                 // Method com/google/protobuf/SingleFieldBuilderV3.build:()Lcom/google/protobuf/AbstractMessage;
      45: invokestatic  #21                 // Method org/apache/bookkeeper/stream/proto/kv/rpc/RequestOp.access$402:(Lorg/apache/bookkeeper/stream/proto/kv/rpc/RequestOp;Ljava/lang/Object;)Ljava/lang/Object;
      48: pop
      49: aload_0
      50: getfield      #9                  // Field requestCase_:I
      53: iconst_2
      54: if_icmpne     88
      57: aload_0
      58: getfield      #23                 // Field requestPutBuilder_:Lcom/google/protobuf/SingleFieldBuilderV3;
      61: ifnonnull     76
      64: aload_1
      65: aload_0
      66: getfield      #14                 // Field request_:Ljava/lang/Object;
      69: invokestatic  #21                 // Method org/apache/bookkeeper/stream/proto/kv/rpc/RequestOp.access$402:(Lorg/apache/bookkeeper/stream/proto/kv/rpc/RequestOp;Ljava/lang/Object;)Ljava/lang/Object;
      72: pop
      73: goto          88
      76: aload_1
      77: aload_0
      78: getfield      #23                 // Field requestPutBuilder_:Lcom/google/protobuf/SingleFieldBuilderV3;
      81: invokevirtual #22                 // Method com/google/protobuf/SingleFieldBuilderV3.build:()Lcom/google/protobuf/AbstractMessage;
      84: invokestatic  #21                 // Method org/apache/bookkeeper/stream/proto/kv/rpc/RequestOp.access$402:(Lorg/apache/bookkeeper/stream/proto/kv/rpc/RequestOp;Ljava/lang/Object;)Ljava/lang/Object;
      87: pop
      88: aload_0
      89: getfield      #9                  // Field requestCase_:I
      92: iconst_3
      93: if_icmpne     127
      96: aload_0
      97: getfield      #24                 // Field requestDeleteRangeBuilder_:Lcom/google/protobuf/SingleFieldBuilderV3;
     100: ifnonnull     115
     103: aload_1
     104: aload_0
     105: getfield      #14                 // Field request_:Ljava/lang/Object;
     108: invokestatic  #21                 // Method org/apache/bookkeeper/stream/proto/kv/rpc/RequestOp.access$402:(Lorg/apache/bookkeeper/stream/proto/kv/rpc/RequestOp;Ljava/lang/Object;)Ljava/lang/Object;
     111: pop
     112: goto          127
     115: aload_1
     116: aload_0
     117: getfield      #24                 // Field requestDeleteRangeBuilder_:Lcom/google/protobuf/SingleFieldBuilderV3;
     120: invokevirtual #22                 // Method com/google/protobuf/SingleFieldBuilderV3.build:()Lcom/google/protobuf/AbstractMessage;
     123: invokestatic  #21                 // Method org/apache/bookkeeper/stream/proto/kv/rpc/RequestOp.access$402:(Lorg/apache/bookkeeper/stream/proto/kv/rpc/RequestOp;Ljava/lang/Object;)Ljava/lang/Object;
     126: pop
     127: aload_1
     128: aload_0
     129: getfield      #9                  // Field requestCase_:I
     132: invokestatic  #25                 // Method org/apache/bookkeeper/stream/proto/kv/rpc/RequestOp.access$502:(Lorg/apache/bookkeeper/stream/proto/kv/rpc/RequestOp;I)I
     135: pop
     136: aload_0
     137: invokevirtual #26                 // Method onBuilt:()V
     140: aload_1
     141: areturn

  public org.apache.bookkeeper.stream.proto.kv.rpc.RequestOp$Builder clone();
    Code:
       0: aload_0
       1: invokespecial #27                 // Method com/google/protobuf/GeneratedMessageV3$Builder.clone:()Lcom/google/protobuf/GeneratedMessageV3$Builder;
       4: checkcast     #6                  // class org/apache/bookkeeper/stream/proto/kv/rpc/RequestOp$Builder
       7: areturn

  public org.apache.bookkeeper.stream.proto.kv.rpc.RequestOp$Builder setField(com.google.protobuf.Descriptors$FieldDescriptor, java.lang.Object);
    Code:
       0: aload_0
       1: aload_1
       2: aload_2
       3: invokespecial #28                 // Method com/google/protobuf/GeneratedMessageV3$Builder.setField:(Lcom/google/protobuf/Descriptors$FieldDescriptor;Ljava/lang/Object;)Lcom/google/protobuf/GeneratedMessageV3$Builder;
       6: checkcast     #6                  // class org/apache/bookkeeper/stream/proto/kv/rpc/RequestOp$Builder
       9: areturn

  public org.apache.bookkeeper.stream.proto.kv.rpc.RequestOp$Builder clearField(com.google.protobuf.Descriptors$FieldDescriptor);
    Code:
       0: aload_0
       1: aload_1
       2: invokespecial #29                 // Method com/google/protobuf/GeneratedMessageV3$Builder.clearField:(Lcom/google/protobuf/Descriptors$FieldDescriptor;)Lcom/google/protobuf/GeneratedMessageV3$Builder;
       5: checkcast     #6                  // class org/apache/bookkeeper/stream/proto/kv/rpc/RequestOp$Builder
       8: areturn

  public org.apache.bookkeeper.stream.proto.kv.rpc.RequestOp$Builder clearOneof(com.google.protobuf.Descriptors$OneofDescriptor);
    Code:
       0: aload_0
       1: aload_1
       2: invokespecial #30                 // Method com/google/protobuf/GeneratedMessageV3$Builder.clearOneof:(Lcom/google/protobuf/Descriptors$OneofDescriptor;)Lcom/google/protobuf/GeneratedMessageV3$Builder;
       5: checkcast     #6                  // class org/apache/bookkeeper/stream/proto/kv/rpc/RequestOp$Builder
       8: areturn

  public org.apache.bookkeeper.stream.proto.kv.rpc.RequestOp$Builder setRepeatedField(com.google.protobuf.Descriptors$FieldDescriptor, int, java.lang.Object);
    Code:
       0: aload_0
       1: aload_1
       2: iload_2
       3: aload_3
       4: invokespecial #31                 // Method com/google/protobuf/GeneratedMessageV3$Builder.setRepeatedField:(Lcom/google/protobuf/Descriptors$FieldDescriptor;ILjava/lang/Object;)Lcom/google/protobuf/GeneratedMessageV3$Builder;
       7: checkcast     #6                  // class org/apache/bookkeeper/stream/proto/kv/rpc/RequestOp$Builder
      10: areturn

  public org.apache.bookkeeper.stream.proto.kv.rpc.RequestOp$Builder addRepeatedField(com.google.protobuf.Descriptors$FieldDescriptor, java.lang.Object);
    Code:
       0: aload_0
       1: aload_1
       2: aload_2
       3: invokespecial #32                 // Method com/google/protobuf/GeneratedMessageV3$Builder.addRepeatedField:(Lcom/google/protobuf/Descriptors$FieldDescriptor;Ljava/lang/Object;)Lcom/google/protobuf/GeneratedMessageV3$Builder;
       6: checkcast     #6                  // class org/apache/bookkeeper/stream/proto/kv/rpc/RequestOp$Builder
       9: areturn

  public org.apache.bookkeeper.stream.proto.kv.rpc.RequestOp$Builder mergeFrom(com.google.protobuf.Message);
    Code:
       0: aload_1
       1: instanceof    #5                  // class org/apache/bookkeeper/stream/proto/kv/rpc/RequestOp
       4: ifeq          16
       7: aload_0
       8: aload_1
       9: checkcast     #5                  // class org/apache/bookkeeper/stream/proto/kv/rpc/RequestOp
      12: invokevirtual #33                 // Method mergeFrom:(Lorg/apache/bookkeeper/stream/proto/kv/rpc/RequestOp;)Lorg/apache/bookkeeper/stream/proto/kv/rpc/RequestOp$Builder;
      15: areturn
      16: aload_0
      17: aload_1
      18: invokespecial #34                 // Method com/google/protobuf/GeneratedMessageV3$Builder.mergeFrom:(Lcom/google/protobuf/Message;)Lcom/google/protobuf/AbstractMessage$Builder;
      21: pop
      22: aload_0
      23: areturn

  public org.apache.bookkeeper.stream.proto.kv.rpc.RequestOp$Builder mergeFrom(org.apache.bookkeeper.stream.proto.kv.rpc.RequestOp);
    Code:
       0: aload_1
       1: invokestatic  #15                 // Method org/apache/bookkeeper/stream/proto/kv/rpc/RequestOp.getDefaultInstance:()Lorg/apache/bookkeeper/stream/proto/kv/rpc/RequestOp;
       4: if_acmpne     9
       7: aload_0
       8: areturn
       9: getstatic     #35                 // Field org/apache/bookkeeper/stream/proto/kv/rpc/RequestOp$2.$SwitchMap$org$apache$bookkeeper$stream$proto$kv$rpc$RequestOp$RequestCase:[I
      12: aload_1
      13: invokevirtual #36                 // Method org/apache/bookkeeper/stream/proto/kv/rpc/RequestOp.getRequestCase:()Lorg/apache/bookkeeper/stream/proto/kv/rpc/RequestOp$RequestCase;
      16: invokevirtual #37                 // Method org/apache/bookkeeper/stream/proto/kv/rpc/RequestOp$RequestCase.ordinal:()I
      19: iaload
      20: tableswitch   { // 1 to 4
                     1: 52
                     2: 64
                     3: 76
                     4: 88
               default: 88
          }
      52: aload_0
      53: aload_1
      54: invokevirtual #38                 // Method org/apache/bookkeeper/stream/proto/kv/rpc/RequestOp.getRequestRange:()Lorg/apache/bookkeeper/stream/proto/kv/rpc/RangeRequest;
      57: invokevirtual #39                 // Method mergeRequestRange:(Lorg/apache/bookkeeper/stream/proto/kv/rpc/RangeRequest;)Lorg/apache/bookkeeper/stream/proto/kv/rpc/RequestOp$Builder;
      60: pop
      61: goto          88
      64: aload_0
      65: aload_1
      66: invokevirtual #40                 // Method org/apache/bookkeeper/stream/proto/kv/rpc/RequestOp.getRequestPut:()Lorg/apache/bookkeeper/stream/proto/kv/rpc/PutRequest;
      69: invokevirtual #41                 // Method mergeRequestPut:(Lorg/apache/bookkeeper/stream/proto/kv/rpc/PutRequest;)Lorg/apache/bookkeeper/stream/proto/kv/rpc/RequestOp$Builder;
      72: pop
      73: goto          88
      76: aload_0
      77: aload_1
      78: invokevirtual #42                 // Method org/apache/bookkeeper/stream/proto/kv/rpc/RequestOp.getRequestDeleteRange:()Lorg/apache/bookkeeper/stream/proto/kv/rpc/DeleteRangeRequest;
      81: invokevirtual #43                 // Method mergeRequestDeleteRange:(Lorg/apache/bookkeeper/stream/proto/kv/rpc/DeleteRangeRequest;)Lorg/apache/bookkeeper/stream/proto/kv/rpc/RequestOp$Builder;
      84: pop
      85: goto          88
      88: aload_0
      89: aload_1
      90: invokestatic  #44                 // Method org/apache/bookkeeper/stream/proto/kv/rpc/RequestOp.access$600:(Lorg/apache/bookkeeper/stream/proto/kv/rpc/RequestOp;)Lcom/google/protobuf/UnknownFieldSet;
      93: invokevirtual #45                 // Method mergeUnknownFields:(Lcom/google/protobuf/UnknownFieldSet;)Lorg/apache/bookkeeper/stream/proto/kv/rpc/RequestOp$Builder;
      96: pop
      97: aload_0
      98: invokevirtual #46                 // Method onChanged:()V
     101: aload_0
     102: areturn

  public final boolean isInitialized();
    Code:
       0: iconst_1
       1: ireturn

  public org.apache.bookkeeper.stream.proto.kv.rpc.RequestOp$Builder mergeFrom(com.google.protobuf.CodedInputStream, com.google.protobuf.ExtensionRegistryLite) throws java.io.IOException;
    Code:
       0: aconst_null
       1: astore_3
       2: invokestatic  #47                 // Method org/apache/bookkeeper/stream/proto/kv/rpc/RequestOp.access$700:()Lcom/google/protobuf/Parser;
       5: aload_1
       6: aload_2
       7: invokeinterface #48,  3           // InterfaceMethod com/google/protobuf/Parser.parsePartialFrom:(Lcom/google/protobuf/CodedInputStream;Lcom/google/protobuf/ExtensionRegistryLite;)Ljava/lang/Object;
      12: checkcast     #5                  // class org/apache/bookkeeper/stream/proto/kv/rpc/RequestOp
      15: astore_3
      16: aload_3
      17: ifnull        61
      20: aload_0
      21: aload_3
      22: invokevirtual #33                 // Method mergeFrom:(Lorg/apache/bookkeeper/stream/proto/kv/rpc/RequestOp;)Lorg/apache/bookkeeper/stream/proto/kv/rpc/RequestOp$Builder;
      25: pop
      26: goto          61
      29: astore        4
      31: aload         4
      33: invokevirtual #50                 // Method com/google/protobuf/InvalidProtocolBufferException.getUnfinishedMessage:()Lcom/google/protobuf/MessageLite;
      36: checkcast     #5                  // class org/apache/bookkeeper/stream/proto/kv/rpc/RequestOp
      39: astore_3
      40: aload         4
      42: invokevirtual #51                 // Method com/google/protobuf/InvalidProtocolBufferException.unwrapIOException:()Ljava/io/IOException;
      45: athrow
      46: astore        5
      48: aload_3
      49: ifnull        58
      52: aload_0
      53: aload_3
      54: invokevirtual #33                 // Method mergeFrom:(Lorg/apache/bookkeeper/stream/proto/kv/rpc/RequestOp;)Lorg/apache/bookkeeper/stream/proto/kv/rpc/RequestOp$Builder;
      57: pop
      58: aload         5
      60: athrow
      61: aload_0
      62: areturn
    Exception table:
       from    to  target type
           2    16    29   Class com/google/protobuf/InvalidProtocolBufferException
           2    16    46   any
          29    48    46   any

  public org.apache.bookkeeper.stream.proto.kv.rpc.RequestOp$RequestCase getRequestCase();
    Code:
       0: aload_0
       1: getfield      #9                  // Field requestCase_:I
       4: invokestatic  #52                 // Method org/apache/bookkeeper/stream/proto/kv/rpc/RequestOp$RequestCase.forNumber:(I)Lorg/apache/bookkeeper/stream/proto/kv/rpc/RequestOp$RequestCase;
       7: areturn

  public org.apache.bookkeeper.stream.proto.kv.rpc.RequestOp$Builder clearRequest();
    Code:
       0: aload_0
       1: iconst_0
       2: putfield      #9                  // Field requestCase_:I
       5: aload_0
       6: aconst_null
       7: putfield      #14                 // Field request_:Ljava/lang/Object;
      10: aload_0
      11: invokevirtual #46                 // Method onChanged:()V
      14: aload_0
      15: areturn

  public boolean hasRequestRange();
    Code:
       0: aload_0
       1: getfield      #9                  // Field requestCase_:I
       4: iconst_1
       5: if_icmpne     12
       8: iconst_1
       9: goto          13
      12: iconst_0
      13: ireturn

  public org.apache.bookkeeper.stream.proto.kv.rpc.RangeRequest getRequestRange();
    Code:
       0: aload_0
       1: getfield      #20                 // Field requestRangeBuilder_:Lcom/google/protobuf/SingleFieldBuilderV3;
       4: ifnonnull     27
       7: aload_0
       8: getfield      #9                  // Field requestCase_:I
      11: iconst_1
      12: if_icmpne     23
      15: aload_0
      16: getfield      #14                 // Field request_:Ljava/lang/Object;
      19: checkcast     #53                 // class org/apache/bookkeeper/stream/proto/kv/rpc/RangeRequest
      22: areturn
      23: invokestatic  #54                 // Method org/apache/bookkeeper/stream/proto/kv/rpc/RangeRequest.getDefaultInstance:()Lorg/apache/bookkeeper/stream/proto/kv/rpc/RangeRequest;
      26: areturn
      27: aload_0
      28: getfield      #9                  // Field requestCase_:I
      31: iconst_1
      32: if_icmpne     46
      35: aload_0
      36: getfield      #20                 // Field requestRangeBuilder_:Lcom/google/protobuf/SingleFieldBuilderV3;
      39: invokevirtual #55                 // Method com/google/protobuf/SingleFieldBuilderV3.getMessage:()Lcom/google/protobuf/AbstractMessage;
      42: checkcast     #53                 // class org/apache/bookkeeper/stream/proto/kv/rpc/RangeRequest
      45: areturn
      46: invokestatic  #54                 // Method org/apache/bookkeeper/stream/proto/kv/rpc/RangeRequest.getDefaultInstance:()Lorg/apache/bookkeeper/stream/proto/kv/rpc/RangeRequest;
      49: areturn

  public org.apache.bookkeeper.stream.proto.kv.rpc.RequestOp$Builder setRequestRange(org.apache.bookkeeper.stream.proto.kv.rpc.RangeRequest);
    Code:
       0: aload_0
       1: getfield      #20                 // Field requestRangeBuilder_:Lcom/google/protobuf/SingleFieldBuilderV3;
       4: ifnonnull     31
       7: aload_1
       8: ifnonnull     19
      11: new           #56                 // class java/lang/NullPointerException
      14: dup
      15: invokespecial #57                 // Method java/lang/NullPointerException."<init>":()V
      18: athrow
      19: aload_0
      20: aload_1
      21: putfield      #14                 // Field request_:Ljava/lang/Object;
      24: aload_0
      25: invokevirtual #46                 // Method onChanged:()V
      28: goto          40
      31: aload_0
      32: getfield      #20                 // Field requestRangeBuilder_:Lcom/google/protobuf/SingleFieldBuilderV3;
      35: aload_1
      36: invokevirtual #58                 // Method com/google/protobuf/SingleFieldBuilderV3.setMessage:(Lcom/google/protobuf/AbstractMessage;)Lcom/google/protobuf/SingleFieldBuilderV3;
      39: pop
      40: aload_0
      41: iconst_1
      42: putfield      #9                  // Field requestCase_:I
      45: aload_0
      46: areturn

  public org.apache.bookkeeper.stream.proto.kv.rpc.RequestOp$Builder setRequestRange(org.apache.bookkeeper.stream.proto.kv.rpc.RangeRequest$Builder);
    Code:
       0: aload_0
       1: getfield      #20                 // Field requestRangeBuilder_:Lcom/google/protobuf/SingleFieldBuilderV3;
       4: ifnonnull     22
       7: aload_0
       8: aload_1
       9: invokevirtual #59                 // Method org/apache/bookkeeper/stream/proto/kv/rpc/RangeRequest$Builder.build:()Lorg/apache/bookkeeper/stream/proto/kv/rpc/RangeRequest;
      12: putfield      #14                 // Field request_:Ljava/lang/Object;
      15: aload_0
      16: invokevirtual #46                 // Method onChanged:()V
      19: goto          34
      22: aload_0
      23: getfield      #20                 // Field requestRangeBuilder_:Lcom/google/protobuf/SingleFieldBuilderV3;
      26: aload_1
      27: invokevirtual #59                 // Method org/apache/bookkeeper/stream/proto/kv/rpc/RangeRequest$Builder.build:()Lorg/apache/bookkeeper/stream/proto/kv/rpc/RangeRequest;
      30: invokevirtual #58                 // Method com/google/protobuf/SingleFieldBuilderV3.setMessage:(Lcom/google/protobuf/AbstractMessage;)Lcom/google/protobuf/SingleFieldBuilderV3;
      33: pop
      34: aload_0
      35: iconst_1
      36: putfield      #9                  // Field requestCase_:I
      39: aload_0
      40: areturn

  public org.apache.bookkeeper.stream.proto.kv.rpc.RequestOp$Builder mergeRequestRange(org.apache.bookkeeper.stream.proto.kv.rpc.RangeRequest);
    Code:
       0: aload_0
       1: getfield      #20                 // Field requestRangeBuilder_:Lcom/google/protobuf/SingleFieldBuilderV3;
       4: ifnonnull     61
       7: aload_0
       8: getfield      #9                  // Field requestCase_:I
      11: iconst_1
      12: if_icmpne     49
      15: aload_0
      16: getfield      #14                 // Field request_:Ljava/lang/Object;
      19: invokestatic  #54                 // Method org/apache/bookkeeper/stream/proto/kv/rpc/RangeRequest.getDefaultInstance:()Lorg/apache/bookkeeper/stream/proto/kv/rpc/RangeRequest;
      22: if_acmpeq     49
      25: aload_0
      26: aload_0
      27: getfield      #14                 // Field request_:Ljava/lang/Object;
      30: checkcast     #53                 // class org/apache/bookkeeper/stream/proto/kv/rpc/RangeRequest
      33: invokestatic  #60                 // Method org/apache/bookkeeper/stream/proto/kv/rpc/RangeRequest.newBuilder:(Lorg/apache/bookkeeper/stream/proto/kv/rpc/RangeRequest;)Lorg/apache/bookkeeper/stream/proto/kv/rpc/RangeRequest$Builder;
      36: aload_1
      37: invokevirtual #61                 // Method org/apache/bookkeeper/stream/proto/kv/rpc/RangeRequest$Builder.mergeFrom:(Lorg/apache/bookkeeper/stream/proto/kv/rpc/RangeRequest;)Lorg/apache/bookkeeper/stream/proto/kv/rpc/RangeRequest$Builder;
      40: invokevirtual #62                 // Method org/apache/bookkeeper/stream/proto/kv/rpc/RangeRequest$Builder.buildPartial:()Lorg/apache/bookkeeper/stream/proto/kv/rpc/RangeRequest;
      43: putfield      #14                 // Field request_:Ljava/lang/Object;
      46: goto          54
      49: aload_0
      50: aload_1
      51: putfield      #14                 // Field request_:Ljava/lang/Object;
      54: aload_0
      55: invokevirtual #46                 // Method onChanged:()V
      58: goto          87
      61: aload_0
      62: getfield      #9                  // Field requestCase_:I
      65: iconst_1
      66: if_icmpne     78
      69: aload_0
      70: getfield      #20                 // Field requestRangeBuilder_:Lcom/google/protobuf/SingleFieldBuilderV3;
      73: aload_1
      74: invokevirtual #63                 // Method com/google/protobuf/SingleFieldBuilderV3.mergeFrom:(Lcom/google/protobuf/AbstractMessage;)Lcom/google/protobuf/SingleFieldBuilderV3;
      77: pop
      78: aload_0
      79: getfield      #20                 // Field requestRangeBuilder_:Lcom/google/protobuf/SingleFieldBuilderV3;
      82: aload_1
      83: invokevirtual #58                 // Method com/google/protobuf/SingleFieldBuilderV3.setMessage:(Lcom/google/protobuf/AbstractMessage;)Lcom/google/protobuf/SingleFieldBuilderV3;
      86: pop
      87: aload_0
      88: iconst_1
      89: putfield      #9                  // Field requestCase_:I
      92: aload_0
      93: areturn

  public org.apache.bookkeeper.stream.proto.kv.rpc.RequestOp$Builder clearRequestRange();
    Code:
       0: aload_0
       1: getfield      #20                 // Field requestRangeBuilder_:Lcom/google/protobuf/SingleFieldBuilderV3;
       4: ifnonnull     32
       7: aload_0
       8: getfield      #9                  // Field requestCase_:I
      11: iconst_1
      12: if_icmpne     58
      15: aload_0
      16: iconst_0
      17: putfield      #9                  // Field requestCase_:I
      20: aload_0
      21: aconst_null
      22: putfield      #14                 // Field request_:Ljava/lang/Object;
      25: aload_0
      26: invokevirtual #46                 // Method onChanged:()V
      29: goto          58
      32: aload_0
      33: getfield      #9                  // Field requestCase_:I
      36: iconst_1
      37: if_icmpne     50
      40: aload_0
      41: iconst_0
      42: putfield      #9                  // Field requestCase_:I
      45: aload_0
      46: aconst_null
      47: putfield      #14                 // Field request_:Ljava/lang/Object;
      50: aload_0
      51: getfield      #20                 // Field requestRangeBuilder_:Lcom/google/protobuf/SingleFieldBuilderV3;
      54: invokevirtual #64                 // Method com/google/protobuf/SingleFieldBuilderV3.clear:()Lcom/google/protobuf/SingleFieldBuilderV3;
      57: pop
      58: aload_0
      59: areturn

  public org.apache.bookkeeper.stream.proto.kv.rpc.RangeRequest$Builder getRequestRangeBuilder();
    Code:
       0: aload_0
       1: invokespecial #65                 // Method getRequestRangeFieldBuilder:()Lcom/google/protobuf/SingleFieldBuilderV3;
       4: invokevirtual #66                 // Method com/google/protobuf/SingleFieldBuilderV3.getBuilder:()Lcom/google/protobuf/AbstractMessage$Builder;
       7: checkcast     #67                 // class org/apache/bookkeeper/stream/proto/kv/rpc/RangeRequest$Builder
      10: areturn

  public org.apache.bookkeeper.stream.proto.kv.rpc.RangeRequestOrBuilder getRequestRangeOrBuilder();
    Code:
       0: aload_0
       1: getfield      #9                  // Field requestCase_:I
       4: iconst_1
       5: if_icmpne     26
       8: aload_0
       9: getfield      #20                 // Field requestRangeBuilder_:Lcom/google/protobuf/SingleFieldBuilderV3;
      12: ifnull        26
      15: aload_0
      16: getfield      #20                 // Field requestRangeBuilder_:Lcom/google/protobuf/SingleFieldBuilderV3;
      19: invokevirtual #68                 // Method com/google/protobuf/SingleFieldBuilderV3.getMessageOrBuilder:()Lcom/google/protobuf/MessageOrBuilder;
      22: checkcast     #69                 // class org/apache/bookkeeper/stream/proto/kv/rpc/RangeRequestOrBuilder
      25: areturn
      26: aload_0
      27: getfield      #9                  // Field requestCase_:I
      30: iconst_1
      31: if_icmpne     42
      34: aload_0
      35: getfield      #14                 // Field request_:Ljava/lang/Object;
      38: checkcast     #53                 // class org/apache/bookkeeper/stream/proto/kv/rpc/RangeRequest
      41: areturn
      42: invokestatic  #54                 // Method org/apache/bookkeeper/stream/proto/kv/rpc/RangeRequest.getDefaultInstance:()Lorg/apache/bookkeeper/stream/proto/kv/rpc/RangeRequest;
      45: areturn

  private com.google.protobuf.SingleFieldBuilderV3<org.apache.bookkeeper.stream.proto.kv.rpc.RangeRequest, org.apache.bookkeeper.stream.proto.kv.rpc.RangeRequest$Builder, org.apache.bookkeeper.stream.proto.kv.rpc.RangeRequestOrBuilder> getRequestRangeFieldBuilder();
    Code:
       0: aload_0
       1: getfield      #20                 // Field requestRangeBuilder_:Lcom/google/protobuf/SingleFieldBuilderV3;
       4: ifnonnull     53
       7: aload_0
       8: getfield      #9                  // Field requestCase_:I
      11: iconst_1
      12: if_icmpeq     22
      15: aload_0
      16: invokestatic  #54                 // Method org/apache/bookkeeper/stream/proto/kv/rpc/RangeRequest.getDefaultInstance:()Lorg/apache/bookkeeper/stream/proto/kv/rpc/RangeRequest;
      19: putfield      #14                 // Field request_:Ljava/lang/Object;
      22: aload_0
      23: new           #70                 // class com/google/protobuf/SingleFieldBuilderV3
      26: dup
      27: aload_0
      28: getfield      #14                 // Field request_:Ljava/lang/Object;
      31: checkcast     #53                 // class org/apache/bookkeeper/stream/proto/kv/rpc/RangeRequest
      34: aload_0
      35: invokevirtual #71                 // Method getParentForChildren:()Lcom/google/protobuf/GeneratedMessageV3$BuilderParent;
      38: aload_0
      39: invokevirtual #72                 // Method isClean:()Z
      42: invokespecial #73                 // Method com/google/protobuf/SingleFieldBuilderV3."<init>":(Lcom/google/protobuf/AbstractMessage;Lcom/google/protobuf/AbstractMessage$BuilderParent;Z)V
      45: putfield      #20                 // Field requestRangeBuilder_:Lcom/google/protobuf/SingleFieldBuilderV3;
      48: aload_0
      49: aconst_null
      50: putfield      #14                 // Field request_:Ljava/lang/Object;
      53: aload_0
      54: iconst_1
      55: putfield      #9                  // Field requestCase_:I
      58: aload_0
      59: invokevirtual #46                 // Method onChanged:()V
      62: aload_0
      63: getfield      #20                 // Field requestRangeBuilder_:Lcom/google/protobuf/SingleFieldBuilderV3;
      66: areturn

  public boolean hasRequestPut();
    Code:
       0: aload_0
       1: getfield      #9                  // Field requestCase_:I
       4: iconst_2
       5: if_icmpne     12
       8: iconst_1
       9: goto          13
      12: iconst_0
      13: ireturn

  public org.apache.bookkeeper.stream.proto.kv.rpc.PutRequest getRequestPut();
    Code:
       0: aload_0
       1: getfield      #23                 // Field requestPutBuilder_:Lcom/google/protobuf/SingleFieldBuilderV3;
       4: ifnonnull     27
       7: aload_0
       8: getfield      #9                  // Field requestCase_:I
      11: iconst_2
      12: if_icmpne     23
      15: aload_0
      16: getfield      #14                 // Field request_:Ljava/lang/Object;
      19: checkcast     #74                 // class org/apache/bookkeeper/stream/proto/kv/rpc/PutRequest
      22: areturn
      23: invokestatic  #75                 // Method org/apache/bookkeeper/stream/proto/kv/rpc/PutRequest.getDefaultInstance:()Lorg/apache/bookkeeper/stream/proto/kv/rpc/PutRequest;
      26: areturn
      27: aload_0
      28: getfield      #9                  // Field requestCase_:I
      31: iconst_2
      32: if_icmpne     46
      35: aload_0
      36: getfield      #23                 // Field requestPutBuilder_:Lcom/google/protobuf/SingleFieldBuilderV3;
      39: invokevirtual #55                 // Method com/google/protobuf/SingleFieldBuilderV3.getMessage:()Lcom/google/protobuf/AbstractMessage;
      42: checkcast     #74                 // class org/apache/bookkeeper/stream/proto/kv/rpc/PutRequest
      45: areturn
      46: invokestatic  #75                 // Method org/apache/bookkeeper/stream/proto/kv/rpc/PutRequest.getDefaultInstance:()Lorg/apache/bookkeeper/stream/proto/kv/rpc/PutRequest;
      49: areturn

  public org.apache.bookkeeper.stream.proto.kv.rpc.RequestOp$Builder setRequestPut(org.apache.bookkeeper.stream.proto.kv.rpc.PutRequest);
    Code:
       0: aload_0
       1: getfield      #23                 // Field requestPutBuilder_:Lcom/google/protobuf/SingleFieldBuilderV3;
       4: ifnonnull     31
       7: aload_1
       8: ifnonnull     19
      11: new           #56                 // class java/lang/NullPointerException
      14: dup
      15: invokespecial #57                 // Method java/lang/NullPointerException."<init>":()V
      18: athrow
      19: aload_0
      20: aload_1
      21: putfield      #14                 // Field request_:Ljava/lang/Object;
      24: aload_0
      25: invokevirtual #46                 // Method onChanged:()V
      28: goto          40
      31: aload_0
      32: getfield      #23                 // Field requestPutBuilder_:Lcom/google/protobuf/SingleFieldBuilderV3;
      35: aload_1
      36: invokevirtual #58                 // Method com/google/protobuf/SingleFieldBuilderV3.setMessage:(Lcom/google/protobuf/AbstractMessage;)Lcom/google/protobuf/SingleFieldBuilderV3;
      39: pop
      40: aload_0
      41: iconst_2
      42: putfield      #9                  // Field requestCase_:I
      45: aload_0
      46: areturn

  public org.apache.bookkeeper.stream.proto.kv.rpc.RequestOp$Builder setRequestPut(org.apache.bookkeeper.stream.proto.kv.rpc.PutRequest$Builder);
    Code:
       0: aload_0
       1: getfield      #23                 // Field requestPutBuilder_:Lcom/google/protobuf/SingleFieldBuilderV3;
       4: ifnonnull     22
       7: aload_0
       8: aload_1
       9: invokevirtual #76                 // Method org/apache/bookkeeper/stream/proto/kv/rpc/PutRequest$Builder.build:()Lorg/apache/bookkeeper/stream/proto/kv/rpc/PutRequest;
      12: putfield      #14                 // Field request_:Ljava/lang/Object;
      15: aload_0
      16: invokevirtual #46                 // Method onChanged:()V
      19: goto          34
      22: aload_0
      23: getfield      #23                 // Field requestPutBuilder_:Lcom/google/protobuf/SingleFieldBuilderV3;
      26: aload_1
      27: invokevirtual #76                 // Method org/apache/bookkeeper/stream/proto/kv/rpc/PutRequest$Builder.build:()Lorg/apache/bookkeeper/stream/proto/kv/rpc/PutRequest;
      30: invokevirtual #58                 // Method com/google/protobuf/SingleFieldBuilderV3.setMessage:(Lcom/google/protobuf/AbstractMessage;)Lcom/google/protobuf/SingleFieldBuilderV3;
      33: pop
      34: aload_0
      35: iconst_2
      36: putfield      #9                  // Field requestCase_:I
      39: aload_0
      40: areturn

  public org.apache.bookkeeper.stream.proto.kv.rpc.RequestOp$Builder mergeRequestPut(org.apache.bookkeeper.stream.proto.kv.rpc.PutRequest);
    Code:
       0: aload_0
       1: getfield      #23                 // Field requestPutBuilder_:Lcom/google/protobuf/SingleFieldBuilderV3;
       4: ifnonnull     61
       7: aload_0
       8: getfield      #9                  // Field requestCase_:I
      11: iconst_2
      12: if_icmpne     49
      15: aload_0
      16: getfield      #14                 // Field request_:Ljava/lang/Object;
      19: invokestatic  #75                 // Method org/apache/bookkeeper/stream/proto/kv/rpc/PutRequest.getDefaultInstance:()Lorg/apache/bookkeeper/stream/proto/kv/rpc/PutRequest;
      22: if_acmpeq     49
      25: aload_0
      26: aload_0
      27: getfield      #14                 // Field request_:Ljava/lang/Object;
      30: checkcast     #74                 // class org/apache/bookkeeper/stream/proto/kv/rpc/PutRequest
      33: invokestatic  #77                 // Method org/apache/bookkeeper/stream/proto/kv/rpc/PutRequest.newBuilder:(Lorg/apache/bookkeeper/stream/proto/kv/rpc/PutRequest;)Lorg/apache/bookkeeper/stream/proto/kv/rpc/PutRequest$Builder;
      36: aload_1
      37: invokevirtual #78                 // Method org/apache/bookkeeper/stream/proto/kv/rpc/PutRequest$Builder.mergeFrom:(Lorg/apache/bookkeeper/stream/proto/kv/rpc/PutRequest;)Lorg/apache/bookkeeper/stream/proto/kv/rpc/PutRequest$Builder;
      40: invokevirtual #79                 // Method org/apache/bookkeeper/stream/proto/kv/rpc/PutRequest$Builder.buildPartial:()Lorg/apache/bookkeeper/stream/proto/kv/rpc/PutRequest;
      43: putfield      #14                 // Field request_:Ljava/lang/Object;
      46: goto          54
      49: aload_0
      50: aload_1
      51: putfield      #14                 // Field request_:Ljava/lang/Object;
      54: aload_0
      55: invokevirtual #46                 // Method onChanged:()V
      58: goto          87
      61: aload_0
      62: getfield      #9                  // Field requestCase_:I
      65: iconst_2
      66: if_icmpne     78
      69: aload_0
      70: getfield      #23                 // Field requestPutBuilder_:Lcom/google/protobuf/SingleFieldBuilderV3;
      73: aload_1
      74: invokevirtual #63                 // Method com/google/protobuf/SingleFieldBuilderV3.mergeFrom:(Lcom/google/protobuf/AbstractMessage;)Lcom/google/protobuf/SingleFieldBuilderV3;
      77: pop
      78: aload_0
      79: getfield      #23                 // Field requestPutBuilder_:Lcom/google/protobuf/SingleFieldBuilderV3;
      82: aload_1
      83: invokevirtual #58                 // Method com/google/protobuf/SingleFieldBuilderV3.setMessage:(Lcom/google/protobuf/AbstractMessage;)Lcom/google/protobuf/SingleFieldBuilderV3;
      86: pop
      87: aload_0
      88: iconst_2
      89: putfield      #9                  // Field requestCase_:I
      92: aload_0
      93: areturn

  public org.apache.bookkeeper.stream.proto.kv.rpc.RequestOp$Builder clearRequestPut();
    Code:
       0: aload_0
       1: getfield      #23                 // Field requestPutBuilder_:Lcom/google/protobuf/SingleFieldBuilderV3;
       4: ifnonnull     32
       7: aload_0
       8: getfield      #9                  // Field requestCase_:I
      11: iconst_2
      12: if_icmpne     58
      15: aload_0
      16: iconst_0
      17: putfield      #9                  // Field requestCase_:I
      20: aload_0
      21: aconst_null
      22: putfield      #14                 // Field request_:Ljava/lang/Object;
      25: aload_0
      26: invokevirtual #46                 // Method onChanged:()V
      29: goto          58
      32: aload_0
      33: getfield      #9                  // Field requestCase_:I
      36: iconst_2
      37: if_icmpne     50
      40: aload_0
      41: iconst_0
      42: putfield      #9                  // Field requestCase_:I
      45: aload_0
      46: aconst_null
      47: putfield      #14                 // Field request_:Ljava/lang/Object;
      50: aload_0
      51: getfield      #23                 // Field requestPutBuilder_:Lcom/google/protobuf/SingleFieldBuilderV3;
      54: invokevirtual #64                 // Method com/google/protobuf/SingleFieldBuilderV3.clear:()Lcom/google/protobuf/SingleFieldBuilderV3;
      57: pop
      58: aload_0
      59: areturn

  public org.apache.bookkeeper.stream.proto.kv.rpc.PutRequest$Builder getRequestPutBuilder();
    Code:
       0: aload_0
       1: invokespecial #80                 // Method getRequestPutFieldBuilder:()Lcom/google/protobuf/SingleFieldBuilderV3;
       4: invokevirtual #66                 // Method com/google/protobuf/SingleFieldBuilderV3.getBuilder:()Lcom/google/protobuf/AbstractMessage$Builder;
       7: checkcast     #81                 // class org/apache/bookkeeper/stream/proto/kv/rpc/PutRequest$Builder
      10: areturn

  public org.apache.bookkeeper.stream.proto.kv.rpc.PutRequestOrBuilder getRequestPutOrBuilder();
    Code:
       0: aload_0
       1: getfield      #9                  // Field requestCase_:I
       4: iconst_2
       5: if_icmpne     26
       8: aload_0
       9: getfield      #23                 // Field requestPutBuilder_:Lcom/google/protobuf/SingleFieldBuilderV3;
      12: ifnull        26
      15: aload_0
      16: getfield      #23                 // Field requestPutBuilder_:Lcom/google/protobuf/SingleFieldBuilderV3;
      19: invokevirtual #68                 // Method com/google/protobuf/SingleFieldBuilderV3.getMessageOrBuilder:()Lcom/google/protobuf/MessageOrBuilder;
      22: checkcast     #82                 // class org/apache/bookkeeper/stream/proto/kv/rpc/PutRequestOrBuilder
      25: areturn
      26: aload_0
      27: getfield      #9                  // Field requestCase_:I
      30: iconst_2
      31: if_icmpne     42
      34: aload_0
      35: getfield      #14                 // Field request_:Ljava/lang/Object;
      38: checkcast     #74                 // class org/apache/bookkeeper/stream/proto/kv/rpc/PutRequest
      41: areturn
      42: invokestatic  #75                 // Method org/apache/bookkeeper/stream/proto/kv/rpc/PutRequest.getDefaultInstance:()Lorg/apache/bookkeeper/stream/proto/kv/rpc/PutRequest;
      45: areturn

  private com.google.protobuf.SingleFieldBuilderV3<org.apache.bookkeeper.stream.proto.kv.rpc.PutRequest, org.apache.bookkeeper.stream.proto.kv.rpc.PutRequest$Builder, org.apache.bookkeeper.stream.proto.kv.rpc.PutRequestOrBuilder> getRequestPutFieldBuilder();
    Code:
       0: aload_0
       1: getfield      #23                 // Field requestPutBuilder_:Lcom/google/protobuf/SingleFieldBuilderV3;
       4: ifnonnull     53
       7: aload_0
       8: getfield      #9                  // Field requestCase_:I
      11: iconst_2
      12: if_icmpeq     22
      15: aload_0
      16: invokestatic  #75                 // Method org/apache/bookkeeper/stream/proto/kv/rpc/PutRequest.getDefaultInstance:()Lorg/apache/bookkeeper/stream/proto/kv/rpc/PutRequest;
      19: putfield      #14                 // Field request_:Ljava/lang/Object;
      22: aload_0
      23: new           #70                 // class com/google/protobuf/SingleFieldBuilderV3
      26: dup
      27: aload_0
      28: getfield      #14                 // Field request_:Ljava/lang/Object;
      31: checkcast     #74                 // class org/apache/bookkeeper/stream/proto/kv/rpc/PutRequest
      34: aload_0
      35: invokevirtual #71                 // Method getParentForChildren:()Lcom/google/protobuf/GeneratedMessageV3$BuilderParent;
      38: aload_0
      39: invokevirtual #72                 // Method isClean:()Z
      42: invokespecial #73                 // Method com/google/protobuf/SingleFieldBuilderV3."<init>":(Lcom/google/protobuf/AbstractMessage;Lcom/google/protobuf/AbstractMessage$BuilderParent;Z)V
      45: putfield      #23                 // Field requestPutBuilder_:Lcom/google/protobuf/SingleFieldBuilderV3;
      48: aload_0
      49: aconst_null
      50: putfield      #14                 // Field request_:Ljava/lang/Object;
      53: aload_0
      54: iconst_2
      55: putfield      #9                  // Field requestCase_:I
      58: aload_0
      59: invokevirtual #46                 // Method onChanged:()V
      62: aload_0
      63: getfield      #23                 // Field requestPutBuilder_:Lcom/google/protobuf/SingleFieldBuilderV3;
      66: areturn

  public boolean hasRequestDeleteRange();
    Code:
       0: aload_0
       1: getfield      #9                  // Field requestCase_:I
       4: iconst_3
       5: if_icmpne     12
       8: iconst_1
       9: goto          13
      12: iconst_0
      13: ireturn

  public org.apache.bookkeeper.stream.proto.kv.rpc.DeleteRangeRequest getRequestDeleteRange();
    Code:
       0: aload_0
       1: getfield      #24                 // Field requestDeleteRangeBuilder_:Lcom/google/protobuf/SingleFieldBuilderV3;
       4: ifnonnull     27
       7: aload_0
       8: getfield      #9                  // Field requestCase_:I
      11: iconst_3
      12: if_icmpne     23
      15: aload_0
      16: getfield      #14                 // Field request_:Ljava/lang/Object;
      19: checkcast     #83                 // class org/apache/bookkeeper/stream/proto/kv/rpc/DeleteRangeRequest
      22: areturn
      23: invokestatic  #84                 // Method org/apache/bookkeeper/stream/proto/kv/rpc/DeleteRangeRequest.getDefaultInstance:()Lorg/apache/bookkeeper/stream/proto/kv/rpc/DeleteRangeRequest;
      26: areturn
      27: aload_0
      28: getfield      #9                  // Field requestCase_:I
      31: iconst_3
      32: if_icmpne     46
      35: aload_0
      36: getfield      #24                 // Field requestDeleteRangeBuilder_:Lcom/google/protobuf/SingleFieldBuilderV3;
      39: invokevirtual #55                 // Method com/google/protobuf/SingleFieldBuilderV3.getMessage:()Lcom/google/protobuf/AbstractMessage;
      42: checkcast     #83                 // class org/apache/bookkeeper/stream/proto/kv/rpc/DeleteRangeRequest
      45: areturn
      46: invokestatic  #84                 // Method org/apache/bookkeeper/stream/proto/kv/rpc/DeleteRangeRequest.getDefaultInstance:()Lorg/apache/bookkeeper/stream/proto/kv/rpc/DeleteRangeRequest;
      49: areturn

  public org.apache.bookkeeper.stream.proto.kv.rpc.RequestOp$Builder setRequestDeleteRange(org.apache.bookkeeper.stream.proto.kv.rpc.DeleteRangeRequest);
    Code:
       0: aload_0
       1: getfield      #24                 // Field requestDeleteRangeBuilder_:Lcom/google/protobuf/SingleFieldBuilderV3;
       4: ifnonnull     31
       7: aload_1
       8: ifnonnull     19
      11: new           #56                 // class java/lang/NullPointerException
      14: dup
      15: invokespecial #57                 // Method java/lang/NullPointerException."<init>":()V
      18: athrow
      19: aload_0
      20: aload_1
      21: putfield      #14                 // Field request_:Ljava/lang/Object;
      24: aload_0
      25: invokevirtual #46                 // Method onChanged:()V
      28: goto          40
      31: aload_0
      32: getfield      #24                 // Field requestDeleteRangeBuilder_:Lcom/google/protobuf/SingleFieldBuilderV3;
      35: aload_1
      36: invokevirtual #58                 // Method com/google/protobuf/SingleFieldBuilderV3.setMessage:(Lcom/google/protobuf/AbstractMessage;)Lcom/google/protobuf/SingleFieldBuilderV3;
      39: pop
      40: aload_0
      41: iconst_3
      42: putfield      #9                  // Field requestCase_:I
      45: aload_0
      46: areturn

  public org.apache.bookkeeper.stream.proto.kv.rpc.RequestOp$Builder setRequestDeleteRange(org.apache.bookkeeper.stream.proto.kv.rpc.DeleteRangeRequest$Builder);
    Code:
       0: aload_0
       1: getfield      #24                 // Field requestDeleteRangeBuilder_:Lcom/google/protobuf/SingleFieldBuilderV3;
       4: ifnonnull     22
       7: aload_0
       8: aload_1
       9: invokevirtual #85                 // Method org/apache/bookkeeper/stream/proto/kv/rpc/DeleteRangeRequest$Builder.build:()Lorg/apache/bookkeeper/stream/proto/kv/rpc/DeleteRangeRequest;
      12: putfield      #14                 // Field request_:Ljava/lang/Object;
      15: aload_0
      16: invokevirtual #46                 // Method onChanged:()V
      19: goto          34
      22: aload_0
      23: getfield      #24                 // Field requestDeleteRangeBuilder_:Lcom/google/protobuf/SingleFieldBuilderV3;
      26: aload_1
      27: invokevirtual #85                 // Method org/apache/bookkeeper/stream/proto/kv/rpc/DeleteRangeRequest$Builder.build:()Lorg/apache/bookkeeper/stream/proto/kv/rpc/DeleteRangeRequest;
      30: invokevirtual #58                 // Method com/google/protobuf/SingleFieldBuilderV3.setMessage:(Lcom/google/protobuf/AbstractMessage;)Lcom/google/protobuf/SingleFieldBuilderV3;
      33: pop
      34: aload_0
      35: iconst_3
      36: putfield      #9                  // Field requestCase_:I
      39: aload_0
      40: areturn

  public org.apache.bookkeeper.stream.proto.kv.rpc.RequestOp$Builder mergeRequestDeleteRange(org.apache.bookkeeper.stream.proto.kv.rpc.DeleteRangeRequest);
    Code:
       0: aload_0
       1: getfield      #24                 // Field requestDeleteRangeBuilder_:Lcom/google/protobuf/SingleFieldBuilderV3;
       4: ifnonnull     61
       7: aload_0
       8: getfield      #9                  // Field requestCase_:I
      11: iconst_3
      12: if_icmpne     49
      15: aload_0
      16: getfield      #14                 // Field request_:Ljava/lang/Object;
      19: invokestatic  #84                 // Method org/apache/bookkeeper/stream/proto/kv/rpc/DeleteRangeRequest.getDefaultInstance:()Lorg/apache/bookkeeper/stream/proto/kv/rpc/DeleteRangeRequest;
      22: if_acmpeq     49
      25: aload_0
      26: aload_0
      27: getfield      #14                 // Field request_:Ljava/lang/Object;
      30: checkcast     #83                 // class org/apache/bookkeeper/stream/proto/kv/rpc/DeleteRangeRequest
      33: invokestatic  #86                 // Method org/apache/bookkeeper/stream/proto/kv/rpc/DeleteRangeRequest.newBuilder:(Lorg/apache/bookkeeper/stream/proto/kv/rpc/DeleteRangeRequest;)Lorg/apache/bookkeeper/stream/proto/kv/rpc/DeleteRangeRequest$Builder;
      36: aload_1
      37: invokevirtual #87                 // Method org/apache/bookkeeper/stream/proto/kv/rpc/DeleteRangeRequest$Builder.mergeFrom:(Lorg/apache/bookkeeper/stream/proto/kv/rpc/DeleteRangeRequest;)Lorg/apache/bookkeeper/stream/proto/kv/rpc/DeleteRangeRequest$Builder;
      40: invokevirtual #88                 // Method org/apache/bookkeeper/stream/proto/kv/rpc/DeleteRangeRequest$Builder.buildPartial:()Lorg/apache/bookkeeper/stream/proto/kv/rpc/DeleteRangeRequest;
      43: putfield      #14                 // Field request_:Ljava/lang/Object;
      46: goto          54
      49: aload_0
      50: aload_1
      51: putfield      #14                 // Field request_:Ljava/lang/Object;
      54: aload_0
      55: invokevirtual #46                 // Method onChanged:()V
      58: goto          87
      61: aload_0
      62: getfield      #9                  // Field requestCase_:I
      65: iconst_3
      66: if_icmpne     78
      69: aload_0
      70: getfield      #24                 // Field requestDeleteRangeBuilder_:Lcom/google/protobuf/SingleFieldBuilderV3;
      73: aload_1
      74: invokevirtual #63                 // Method com/google/protobuf/SingleFieldBuilderV3.mergeFrom:(Lcom/google/protobuf/AbstractMessage;)Lcom/google/protobuf/SingleFieldBuilderV3;
      77: pop
      78: aload_0
      79: getfield      #24                 // Field requestDeleteRangeBuilder_:Lcom/google/protobuf/SingleFieldBuilderV3;
      82: aload_1
      83: invokevirtual #58                 // Method com/google/protobuf/SingleFieldBuilderV3.setMessage:(Lcom/google/protobuf/AbstractMessage;)Lcom/google/protobuf/SingleFieldBuilderV3;
      86: pop
      87: aload_0
      88: iconst_3
      89: putfield      #9                  // Field requestCase_:I
      92: aload_0
      93: areturn

  public org.apache.bookkeeper.stream.proto.kv.rpc.RequestOp$Builder clearRequestDeleteRange();
    Code:
       0: aload_0
       1: getfield      #24                 // Field requestDeleteRangeBuilder_:Lcom/google/protobuf/SingleFieldBuilderV3;
       4: ifnonnull     32
       7: aload_0
       8: getfield      #9                  // Field requestCase_:I
      11: iconst_3
      12: if_icmpne     58
      15: aload_0
      16: iconst_0
      17: putfield      #9                  // Field requestCase_:I
      20: aload_0
      21: aconst_null
      22: putfield      #14                 // Field request_:Ljava/lang/Object;
      25: aload_0
      26: invokevirtual #46                 // Method onChanged:()V
      29: goto          58
      32: aload_0
      33: getfield      #9                  // Field requestCase_:I
      36: iconst_3
      37: if_icmpne     50
      40: aload_0
      41: iconst_0
      42: putfield      #9                  // Field requestCase_:I
      45: aload_0
      46: aconst_null
      47: putfield      #14                 // Field request_:Ljava/lang/Object;
      50: aload_0
      51: getfield      #24                 // Field requestDeleteRangeBuilder_:Lcom/google/protobuf/SingleFieldBuilderV3;
      54: invokevirtual #64                 // Method com/google/protobuf/SingleFieldBuilderV3.clear:()Lcom/google/protobuf/SingleFieldBuilderV3;
      57: pop
      58: aload_0
      59: areturn

  public org.apache.bookkeeper.stream.proto.kv.rpc.DeleteRangeRequest$Builder getRequestDeleteRangeBuilder();
    Code:
       0: aload_0
       1: invokespecial #89                 // Method getRequestDeleteRangeFieldBuilder:()Lcom/google/protobuf/SingleFieldBuilderV3;
       4: invokevirtual #66                 // Method com/google/protobuf/SingleFieldBuilderV3.getBuilder:()Lcom/google/protobuf/AbstractMessage$Builder;
       7: checkcast     #90                 // class org/apache/bookkeeper/stream/proto/kv/rpc/DeleteRangeRequest$Builder
      10: areturn

  public org.apache.bookkeeper.stream.proto.kv.rpc.DeleteRangeRequestOrBuilder getRequestDeleteRangeOrBuilder();
    Code:
       0: aload_0
       1: getfield      #9                  // Field requestCase_:I
       4: iconst_3
       5: if_icmpne     26
       8: aload_0
       9: getfield      #24                 // Field requestDeleteRangeBuilder_:Lcom/google/protobuf/SingleFieldBuilderV3;
      12: ifnull        26
      15: aload_0
      16: getfield      #24                 // Field requestDeleteRangeBuilder_:Lcom/google/protobuf/SingleFieldBuilderV3;
      19: invokevirtual #68                 // Method com/google/protobuf/SingleFieldBuilderV3.getMessageOrBuilder:()Lcom/google/protobuf/MessageOrBuilder;
      22: checkcast     #91                 // class org/apache/bookkeeper/stream/proto/kv/rpc/DeleteRangeRequestOrBuilder
      25: areturn
      26: aload_0
      27: getfield      #9                  // Field requestCase_:I
      30: iconst_3
      31: if_icmpne     42
      34: aload_0
      35: getfield      #14                 // Field request_:Ljava/lang/Object;
      38: checkcast     #83                 // class org/apache/bookkeeper/stream/proto/kv/rpc/DeleteRangeRequest
      41: areturn
      42: invokestatic  #84                 // Method org/apache/bookkeeper/stream/proto/kv/rpc/DeleteRangeRequest.getDefaultInstance:()Lorg/apache/bookkeeper/stream/proto/kv/rpc/DeleteRangeRequest;
      45: areturn

  private com.google.protobuf.SingleFieldBuilderV3<org.apache.bookkeeper.stream.proto.kv.rpc.DeleteRangeRequest, org.apache.bookkeeper.stream.proto.kv.rpc.DeleteRangeRequest$Builder, org.apache.bookkeeper.stream.proto.kv.rpc.DeleteRangeRequestOrBuilder> getRequestDeleteRangeFieldBuilder();
    Code:
       0: aload_0
       1: getfield      #24                 // Field requestDeleteRangeBuilder_:Lcom/google/protobuf/SingleFieldBuilderV3;
       4: ifnonnull     53
       7: aload_0
       8: getfield      #9                  // Field requestCase_:I
      11: iconst_3
      12: if_icmpeq     22
      15: aload_0
      16: invokestatic  #84                 // Method org/apache/bookkeeper/stream/proto/kv/rpc/DeleteRangeRequest.getDefaultInstance:()Lorg/apache/bookkeeper/stream/proto/kv/rpc/DeleteRangeRequest;
      19: putfield      #14                 // Field request_:Ljava/lang/Object;
      22: aload_0
      23: new           #70                 // class com/google/protobuf/SingleFieldBuilderV3
      26: dup
      27: aload_0
      28: getfield      #14                 // Field request_:Ljava/lang/Object;
      31: checkcast     #83                 // class org/apache/bookkeeper/stream/proto/kv/rpc/DeleteRangeRequest
      34: aload_0
      35: invokevirtual #71                 // Method getParentForChildren:()Lcom/google/protobuf/GeneratedMessageV3$BuilderParent;
      38: aload_0
      39: invokevirtual #72                 // Method isClean:()Z
      42: invokespecial #73                 // Method com/google/protobuf/SingleFieldBuilderV3."<init>":(Lcom/google/protobuf/AbstractMessage;Lcom/google/protobuf/AbstractMessage$BuilderParent;Z)V
      45: putfield      #24                 // Field requestDeleteRangeBuilder_:Lcom/google/protobuf/SingleFieldBuilderV3;
      48: aload_0
      49: aconst_null
      50: putfield      #14                 // Field request_:Ljava/lang/Object;
      53: aload_0
      54: iconst_3
      55: putfield      #9                  // Field requestCase_:I
      58: aload_0
      59: invokevirtual #46                 // Method onChanged:()V
      62: aload_0
      63: getfield      #24                 // Field requestDeleteRangeBuilder_:Lcom/google/protobuf/SingleFieldBuilderV3;
      66: areturn

  public final org.apache.bookkeeper.stream.proto.kv.rpc.RequestOp$Builder setUnknownFields(com.google.protobuf.UnknownFieldSet);
    Code:
       0: aload_0
       1: aload_1
       2: invokespecial #92                 // Method com/google/protobuf/GeneratedMessageV3$Builder.setUnknownFields:(Lcom/google/protobuf/UnknownFieldSet;)Lcom/google/protobuf/GeneratedMessageV3$Builder;
       5: checkcast     #6                  // class org/apache/bookkeeper/stream/proto/kv/rpc/RequestOp$Builder
       8: areturn

  public final org.apache.bookkeeper.stream.proto.kv.rpc.RequestOp$Builder mergeUnknownFields(com.google.protobuf.UnknownFieldSet);
    Code:
       0: aload_0
       1: aload_1
       2: invokespecial #93                 // Method com/google/protobuf/GeneratedMessageV3$Builder.mergeUnknownFields:(Lcom/google/protobuf/UnknownFieldSet;)Lcom/google/protobuf/GeneratedMessageV3$Builder;
       5: checkcast     #6                  // class org/apache/bookkeeper/stream/proto/kv/rpc/RequestOp$Builder
       8: areturn

  public com.google.protobuf.GeneratedMessageV3$Builder mergeUnknownFields(com.google.protobuf.UnknownFieldSet);
    Code:
       0: aload_0
       1: aload_1
       2: invokevirtual #45                 // Method mergeUnknownFields:(Lcom/google/protobuf/UnknownFieldSet;)Lorg/apache/bookkeeper/stream/proto/kv/rpc/RequestOp$Builder;
       5: areturn

  public com.google.protobuf.GeneratedMessageV3$Builder setUnknownFields(com.google.protobuf.UnknownFieldSet);
    Code:
       0: aload_0
       1: aload_1
       2: invokevirtual #94                 // Method setUnknownFields:(Lcom/google/protobuf/UnknownFieldSet;)Lorg/apache/bookkeeper/stream/proto/kv/rpc/RequestOp$Builder;
       5: areturn

  public com.google.protobuf.GeneratedMessageV3$Builder addRepeatedField(com.google.protobuf.Descriptors$FieldDescriptor, java.lang.Object);
    Code:
       0: aload_0
       1: aload_1
       2: aload_2
       3: invokevirtual #95                 // Method addRepeatedField:(Lcom/google/protobuf/Descriptors$FieldDescriptor;Ljava/lang/Object;)Lorg/apache/bookkeeper/stream/proto/kv/rpc/RequestOp$Builder;
       6: areturn

  public com.google.protobuf.GeneratedMessageV3$Builder setRepeatedField(com.google.protobuf.Descriptors$FieldDescriptor, int, java.lang.Object);
    Code:
       0: aload_0
       1: aload_1
       2: iload_2
       3: aload_3
       4: invokevirtual #96                 // Method setRepeatedField:(Lcom/google/protobuf/Descriptors$FieldDescriptor;ILjava/lang/Object;)Lorg/apache/bookkeeper/stream/proto/kv/rpc/RequestOp$Builder;
       7: areturn

  public com.google.protobuf.GeneratedMessageV3$Builder clearOneof(com.google.protobuf.Descriptors$OneofDescriptor);
    Code:
       0: aload_0
       1: aload_1
       2: invokevirtual #97                 // Method clearOneof:(Lcom/google/protobuf/Descriptors$OneofDescriptor;)Lorg/apache/bookkeeper/stream/proto/kv/rpc/RequestOp$Builder;
       5: areturn

  public com.google.protobuf.GeneratedMessageV3$Builder clearField(com.google.protobuf.Descriptors$FieldDescriptor);
    Code:
       0: aload_0
       1: aload_1
       2: invokevirtual #98                 // Method clearField:(Lcom/google/protobuf/Descriptors$FieldDescriptor;)Lorg/apache/bookkeeper/stream/proto/kv/rpc/RequestOp$Builder;
       5: areturn

  public com.google.protobuf.GeneratedMessageV3$Builder setField(com.google.protobuf.Descriptors$FieldDescriptor, java.lang.Object);
    Code:
       0: aload_0
       1: aload_1
       2: aload_2
       3: invokevirtual #99                 // Method setField:(Lcom/google/protobuf/Descriptors$FieldDescriptor;Ljava/lang/Object;)Lorg/apache/bookkeeper/stream/proto/kv/rpc/RequestOp$Builder;
       6: areturn

  public com.google.protobuf.GeneratedMessageV3$Builder clear();
    Code:
       0: aload_0
       1: invokevirtual #100                // Method clear:()Lorg/apache/bookkeeper/stream/proto/kv/rpc/RequestOp$Builder;
       4: areturn

  public com.google.protobuf.GeneratedMessageV3$Builder clone();
    Code:
       0: aload_0
       1: invokevirtual #101                // Method clone:()Lorg/apache/bookkeeper/stream/proto/kv/rpc/RequestOp$Builder;
       4: areturn

  public com.google.protobuf.AbstractMessage$Builder mergeUnknownFields(com.google.protobuf.UnknownFieldSet);
    Code:
       0: aload_0
       1: aload_1
       2: invokevirtual #45                 // Method mergeUnknownFields:(Lcom/google/protobuf/UnknownFieldSet;)Lorg/apache/bookkeeper/stream/proto/kv/rpc/RequestOp$Builder;
       5: areturn

  public com.google.protobuf.AbstractMessage$Builder mergeFrom(com.google.protobuf.CodedInputStream, com.google.protobuf.ExtensionRegistryLite) throws java.io.IOException;
    Code:
       0: aload_0
       1: aload_1
       2: aload_2
       3: invokevirtual #102                // Method mergeFrom:(Lcom/google/protobuf/CodedInputStream;Lcom/google/protobuf/ExtensionRegistryLite;)Lorg/apache/bookkeeper/stream/proto/kv/rpc/RequestOp$Builder;
       6: areturn

  public com.google.protobuf.AbstractMessage$Builder mergeFrom(com.google.protobuf.Message);
    Code:
       0: aload_0
       1: aload_1
       2: invokevirtual #103                // Method mergeFrom:(Lcom/google/protobuf/Message;)Lorg/apache/bookkeeper/stream/proto/kv/rpc/RequestOp$Builder;
       5: areturn

  public com.google.protobuf.AbstractMessage$Builder clear();
    Code:
       0: aload_0
       1: invokevirtual #100                // Method clear:()Lorg/apache/bookkeeper/stream/proto/kv/rpc/RequestOp$Builder;
       4: areturn

  public com.google.protobuf.AbstractMessage$Builder clearOneof(com.google.protobuf.Descriptors$OneofDescriptor);
    Code:
       0: aload_0
       1: aload_1
       2: invokevirtual #97                 // Method clearOneof:(Lcom/google/protobuf/Descriptors$OneofDescriptor;)Lorg/apache/bookkeeper/stream/proto/kv/rpc/RequestOp$Builder;
       5: areturn

  public com.google.protobuf.AbstractMessage$Builder clone();
    Code:
       0: aload_0
       1: invokevirtual #101                // Method clone:()Lorg/apache/bookkeeper/stream/proto/kv/rpc/RequestOp$Builder;
       4: areturn

  public com.google.protobuf.Message$Builder mergeUnknownFields(com.google.protobuf.UnknownFieldSet);
    Code:
       0: aload_0
       1: aload_1
       2: invokevirtual #45                 // Method mergeUnknownFields:(Lcom/google/protobuf/UnknownFieldSet;)Lorg/apache/bookkeeper/stream/proto/kv/rpc/RequestOp$Builder;
       5: areturn

  public com.google.protobuf.Message$Builder setUnknownFields(com.google.protobuf.UnknownFieldSet);
    Code:
       0: aload_0
       1: aload_1
       2: invokevirtual #94                 // Method setUnknownFields:(Lcom/google/protobuf/UnknownFieldSet;)Lorg/apache/bookkeeper/stream/proto/kv/rpc/RequestOp$Builder;
       5: areturn

  public com.google.protobuf.Message$Builder addRepeatedField(com.google.protobuf.Descriptors$FieldDescriptor, java.lang.Object);
    Code:
       0: aload_0
       1: aload_1
       2: aload_2
       3: invokevirtual #95                 // Method addRepeatedField:(Lcom/google/protobuf/Descriptors$FieldDescriptor;Ljava/lang/Object;)Lorg/apache/bookkeeper/stream/proto/kv/rpc/RequestOp$Builder;
       6: areturn

  public com.google.protobuf.Message$Builder setRepeatedField(com.google.protobuf.Descriptors$FieldDescriptor, int, java.lang.Object);
    Code:
       0: aload_0
       1: aload_1
       2: iload_2
       3: aload_3
       4: invokevirtual #96                 // Method setRepeatedField:(Lcom/google/protobuf/Descriptors$FieldDescriptor;ILjava/lang/Object;)Lorg/apache/bookkeeper/stream/proto/kv/rpc/RequestOp$Builder;
       7: areturn

  public com.google.protobuf.Message$Builder clearOneof(com.google.protobuf.Descriptors$OneofDescriptor);
    Code:
       0: aload_0
       1: aload_1
       2: invokevirtual #97                 // Method clearOneof:(Lcom/google/protobuf/Descriptors$OneofDescriptor;)Lorg/apache/bookkeeper/stream/proto/kv/rpc/RequestOp$Builder;
       5: areturn

  public com.google.protobuf.Message$Builder clearField(com.google.protobuf.Descriptors$FieldDescriptor);
    Code:
       0: aload_0
       1: aload_1
       2: invokevirtual #98                 // Method clearField:(Lcom/google/protobuf/Descriptors$FieldDescriptor;)Lorg/apache/bookkeeper/stream/proto/kv/rpc/RequestOp$Builder;
       5: areturn

  public com.google.protobuf.Message$Builder setField(com.google.protobuf.Descriptors$FieldDescriptor, java.lang.Object);
    Code:
       0: aload_0
       1: aload_1
       2: aload_2
       3: invokevirtual #99                 // Method setField:(Lcom/google/protobuf/Descriptors$FieldDescriptor;Ljava/lang/Object;)Lorg/apache/bookkeeper/stream/proto/kv/rpc/RequestOp$Builder;
       6: areturn

  public com.google.protobuf.Message$Builder mergeFrom(com.google.protobuf.CodedInputStream, com.google.protobuf.ExtensionRegistryLite) throws java.io.IOException;
    Code:
       0: aload_0
       1: aload_1
       2: aload_2
       3: invokevirtual #102                // Method mergeFrom:(Lcom/google/protobuf/CodedInputStream;Lcom/google/protobuf/ExtensionRegistryLite;)Lorg/apache/bookkeeper/stream/proto/kv/rpc/RequestOp$Builder;
       6: areturn

  public com.google.protobuf.Message$Builder clone();
    Code:
       0: aload_0
       1: invokevirtual #101                // Method clone:()Lorg/apache/bookkeeper/stream/proto/kv/rpc/RequestOp$Builder;
       4: areturn

  public com.google.protobuf.Message buildPartial();
    Code:
       0: aload_0
       1: invokevirtual #16                 // Method buildPartial:()Lorg/apache/bookkeeper/stream/proto/kv/rpc/RequestOp;
       4: areturn

  public com.google.protobuf.Message build();
    Code:
       0: aload_0
       1: invokevirtual #104                // Method build:()Lorg/apache/bookkeeper/stream/proto/kv/rpc/RequestOp;
       4: areturn

  public com.google.protobuf.Message$Builder mergeFrom(com.google.protobuf.Message);
    Code:
       0: aload_0
       1: aload_1
       2: invokevirtual #103                // Method mergeFrom:(Lcom/google/protobuf/Message;)Lorg/apache/bookkeeper/stream/proto/kv/rpc/RequestOp$Builder;
       5: areturn

  public com.google.protobuf.Message$Builder clear();
    Code:
       0: aload_0
       1: invokevirtual #100                // Method clear:()Lorg/apache/bookkeeper/stream/proto/kv/rpc/RequestOp$Builder;
       4: areturn

  public com.google.protobuf.MessageLite$Builder mergeFrom(com.google.protobuf.CodedInputStream, com.google.protobuf.ExtensionRegistryLite) throws java.io.IOException;
    Code:
       0: aload_0
       1: aload_1
       2: aload_2
       3: invokevirtual #102                // Method mergeFrom:(Lcom/google/protobuf/CodedInputStream;Lcom/google/protobuf/ExtensionRegistryLite;)Lorg/apache/bookkeeper/stream/proto/kv/rpc/RequestOp$Builder;
       6: areturn

  public com.google.protobuf.MessageLite$Builder clone();
    Code:
       0: aload_0
       1: invokevirtual #101                // Method clone:()Lorg/apache/bookkeeper/stream/proto/kv/rpc/RequestOp$Builder;
       4: areturn

  public com.google.protobuf.MessageLite buildPartial();
    Code:
       0: aload_0
       1: invokevirtual #16                 // Method buildPartial:()Lorg/apache/bookkeeper/stream/proto/kv/rpc/RequestOp;
       4: areturn

  public com.google.protobuf.MessageLite build();
    Code:
       0: aload_0
       1: invokevirtual #104                // Method build:()Lorg/apache/bookkeeper/stream/proto/kv/rpc/RequestOp;
       4: areturn

  public com.google.protobuf.MessageLite$Builder clear();
    Code:
       0: aload_0
       1: invokevirtual #100                // Method clear:()Lorg/apache/bookkeeper/stream/proto/kv/rpc/RequestOp$Builder;
       4: areturn

  public com.google.protobuf.MessageLite getDefaultInstanceForType();
    Code:
       0: aload_0
       1: invokevirtual #105                // Method getDefaultInstanceForType:()Lorg/apache/bookkeeper/stream/proto/kv/rpc/RequestOp;
       4: areturn

  public com.google.protobuf.Message getDefaultInstanceForType();
    Code:
       0: aload_0
       1: invokevirtual #105                // Method getDefaultInstanceForType:()Lorg/apache/bookkeeper/stream/proto/kv/rpc/RequestOp;
       4: areturn

  public com.google.protobuf.AbstractMessageLite$Builder mergeFrom(com.google.protobuf.CodedInputStream, com.google.protobuf.ExtensionRegistryLite) throws java.io.IOException;
    Code:
       0: aload_0
       1: aload_1
       2: aload_2
       3: invokevirtual #102                // Method mergeFrom:(Lcom/google/protobuf/CodedInputStream;Lcom/google/protobuf/ExtensionRegistryLite;)Lorg/apache/bookkeeper/stream/proto/kv/rpc/RequestOp$Builder;
       6: areturn

  public com.google.protobuf.AbstractMessageLite$Builder clone();
    Code:
       0: aload_0
       1: invokevirtual #101                // Method clone:()Lorg/apache/bookkeeper/stream/proto/kv/rpc/RequestOp$Builder;
       4: areturn

  public java.lang.Object clone() throws java.lang.CloneNotSupportedException;
    Code:
       0: aload_0
       1: invokevirtual #101                // Method clone:()Lorg/apache/bookkeeper/stream/proto/kv/rpc/RequestOp$Builder;
       4: areturn

  org.apache.bookkeeper.stream.proto.kv.rpc.RequestOp$Builder(org.apache.bookkeeper.stream.proto.kv.rpc.RequestOp$1);
    Code:
       0: aload_0
       1: invokespecial #2                  // Method "<init>":()V
       4: return

  org.apache.bookkeeper.stream.proto.kv.rpc.RequestOp$Builder(com.google.protobuf.GeneratedMessageV3$BuilderParent, org.apache.bookkeeper.stream.proto.kv.rpc.RequestOp$1);
    Code:
       0: aload_0
       1: aload_1
       2: invokespecial #1                  // Method "<init>":(Lcom/google/protobuf/GeneratedMessageV3$BuilderParent;)V
       5: return
}
