Compiled from "Jdbc42CallableStatement.java"
class org.postgresql.jdbc42.Jdbc42CallableStatement extends org.postgresql.jdbc42.Jdbc42PreparedStatement implements java.sql.CallableStatement {
  org.postgresql.jdbc42.Jdbc42CallableStatement(org.postgresql.jdbc42.Jdbc42Connection, java.lang.String, int, int, int) throws java.sql.SQLException;
    Code:
       0: aload_0
       1: aload_1
       2: aload_2
       3: iconst_1
       4: iload_3
       5: iload         4
       7: iload         5
       9: invokespecial #1                  // Method org/postgresql/jdbc42/Jdbc42PreparedStatement."<init>":(Lorg/postgresql/jdbc42/Jdbc42Connection;Ljava/lang/String;ZIII)V
      12: return

  public java.lang.Object getObject(int, java.util.Map<java.lang.String, java.lang.Class<?>>) throws java.sql.SQLException;
    Code:
       0: aload_0
       1: iload_1
       2: aload_2
       3: invokevirtual #2                  // Method getObjectImpl:(ILjava/util/Map;)Ljava/lang/Object;
       6: areturn

  public java.lang.Object getObject(java.lang.String, java.util.Map<java.lang.String, java.lang.Class<?>>) throws java.sql.SQLException;
    Code:
       0: aload_0
       1: aload_1
       2: aload_2
       3: invokevirtual #3                  // Method getObjectImpl:(Ljava/lang/String;Ljava/util/Map;)Ljava/lang/Object;
       6: areturn
}
