Compiled from "ServletSessionConfig.java"
public class io.undertow.servlet.api.ServletSessionConfig {
  public static final java.lang.String DEFAULT_SESSION_ID;

  private java.util.Set<javax.servlet.SessionTrackingMode> sessionTrackingModes;

  private java.lang.String name;

  private java.lang.String path;

  private java.lang.String domain;

  private boolean secure;

  private boolean httpOnly;

  private int maxAge;

  private java.lang.String comment;

  public io.undertow.servlet.api.ServletSessionConfig();
    Code:
       0: aload_0
       1: invokespecial #1                  // Method java/lang/Object."<init>":()V
       4: aload_0
       5: ldc           #3                  // String JSESSIONID
       7: putfield      #4                  // Field name:Ljava/lang/String;
      10: return

  public java.lang.String getName();
    Code:
       0: aload_0
       1: getfield      #4                  // Field name:Ljava/lang/String;
       4: areturn

  public io.undertow.servlet.api.ServletSessionConfig setName(java.lang.String);
    Code:
       0: aload_0
       1: aload_1
       2: putfield      #4                  // Field name:Ljava/lang/String;
       5: aload_0
       6: areturn

  public java.lang.String getDomain();
    Code:
       0: aload_0
       1: getfield      #5                  // Field domain:Ljava/lang/String;
       4: areturn

  public io.undertow.servlet.api.ServletSessionConfig setDomain(java.lang.String);
    Code:
       0: aload_0
       1: aload_1
       2: putfield      #5                  // Field domain:Ljava/lang/String;
       5: aload_0
       6: areturn

  public java.lang.String getPath();
    Code:
       0: aload_0
       1: getfield      #6                  // Field path:Ljava/lang/String;
       4: areturn

  public io.undertow.servlet.api.ServletSessionConfig setPath(java.lang.String);
    Code:
       0: aload_0
       1: aload_1
       2: putfield      #6                  // Field path:Ljava/lang/String;
       5: aload_0
       6: areturn

  public java.lang.String getComment();
    Code:
       0: aload_0
       1: getfield      #7                  // Field comment:Ljava/lang/String;
       4: areturn

  public io.undertow.servlet.api.ServletSessionConfig setComment(java.lang.String);
    Code:
       0: aload_0
       1: aload_1
       2: putfield      #7                  // Field comment:Ljava/lang/String;
       5: aload_0
       6: areturn

  public boolean isHttpOnly();
    Code:
       0: aload_0
       1: getfield      #8                  // Field httpOnly:Z
       4: ireturn

  public io.undertow.servlet.api.ServletSessionConfig setHttpOnly(boolean);
    Code:
       0: aload_0
       1: iload_1
       2: putfield      #8                  // Field httpOnly:Z
       5: aload_0
       6: areturn

  public boolean isSecure();
    Code:
       0: aload_0
       1: getfield      #9                  // Field secure:Z
       4: ireturn

  public io.undertow.servlet.api.ServletSessionConfig setSecure(boolean);
    Code:
       0: aload_0
       1: iload_1
       2: putfield      #9                  // Field secure:Z
       5: aload_0
       6: areturn

  public int getMaxAge();
    Code:
       0: aload_0
       1: getfield      #10                 // Field maxAge:I
       4: ireturn

  public io.undertow.servlet.api.ServletSessionConfig setMaxAge(int);
    Code:
       0: aload_0
       1: iload_1
       2: putfield      #10                 // Field maxAge:I
       5: aload_0
       6: areturn

  public java.util.Set<javax.servlet.SessionTrackingMode> getSessionTrackingModes();
    Code:
       0: aload_0
       1: getfield      #11                 // Field sessionTrackingModes:Ljava/util/Set;
       4: areturn

  public io.undertow.servlet.api.ServletSessionConfig setSessionTrackingModes(java.util.Set<javax.servlet.SessionTrackingMode>);
    Code:
       0: aload_0
       1: aload_1
       2: putfield      #11                 // Field sessionTrackingModes:Ljava/util/Set;
       5: aload_0
       6: areturn
}
