Compiled from "SdbOperations.java"
public final class org.apache.camel.component.aws.sdb.SdbOperations extends java.lang.Enum<org.apache.camel.component.aws.sdb.SdbOperations> {
  public static final org.apache.camel.component.aws.sdb.SdbOperations BatchDeleteAttributes;

  public static final org.apache.camel.component.aws.sdb.SdbOperations BatchPutAttributes;

  public static final org.apache.camel.component.aws.sdb.SdbOperations DeleteAttributes;

  public static final org.apache.camel.component.aws.sdb.SdbOperations DeleteDomain;

  public static final org.apache.camel.component.aws.sdb.SdbOperations DomainMetadata;

  public static final org.apache.camel.component.aws.sdb.SdbOperations GetAttributes;

  public static final org.apache.camel.component.aws.sdb.SdbOperations ListDomains;

  public static final org.apache.camel.component.aws.sdb.SdbOperations PutAttributes;

  public static final org.apache.camel.component.aws.sdb.SdbOperations Select;

  private static final org.apache.camel.component.aws.sdb.SdbOperations[] $VALUES;

  public static org.apache.camel.component.aws.sdb.SdbOperations[] values();
    Code:
       0: getstatic     #1                  // Field $VALUES:[Lorg/apache/camel/component/aws/sdb/SdbOperations;
       3: invokevirtual #2                  // Method "[Lorg/apache/camel/component/aws/sdb/SdbOperations;".clone:()Ljava/lang/Object;
       6: checkcast     #3                  // class "[Lorg/apache/camel/component/aws/sdb/SdbOperations;"
       9: areturn

  public static org.apache.camel.component.aws.sdb.SdbOperations valueOf(java.lang.String);
    Code:
       0: ldc           #4                  // class org/apache/camel/component/aws/sdb/SdbOperations
       2: aload_0
       3: invokestatic  #5                  // Method java/lang/Enum.valueOf:(Ljava/lang/Class;Ljava/lang/String;)Ljava/lang/Enum;
       6: checkcast     #4                  // class org/apache/camel/component/aws/sdb/SdbOperations
       9: areturn

  private org.apache.camel.component.aws.sdb.SdbOperations();
    Code:
       0: aload_0
       1: aload_1
       2: iload_2
       3: invokespecial #6                  // Method java/lang/Enum."<init>":(Ljava/lang/String;I)V
       6: return

  static {};
    Code:
       0: new           #4                  // class org/apache/camel/component/aws/sdb/SdbOperations
       3: dup
       4: ldc           #7                  // String BatchDeleteAttributes
       6: iconst_0
       7: invokespecial #8                  // Method "<init>":(Ljava/lang/String;I)V
      10: putstatic     #9                  // Field BatchDeleteAttributes:Lorg/apache/camel/component/aws/sdb/SdbOperations;
      13: new           #4                  // class org/apache/camel/component/aws/sdb/SdbOperations
      16: dup
      17: ldc           #10                 // String BatchPutAttributes
      19: iconst_1
      20: invokespecial #8                  // Method "<init>":(Ljava/lang/String;I)V
      23: putstatic     #11                 // Field BatchPutAttributes:Lorg/apache/camel/component/aws/sdb/SdbOperations;
      26: new           #4                  // class org/apache/camel/component/aws/sdb/SdbOperations
      29: dup
      30: ldc           #12                 // String DeleteAttributes
      32: iconst_2
      33: invokespecial #8                  // Method "<init>":(Ljava/lang/String;I)V
      36: putstatic     #13                 // Field DeleteAttributes:Lorg/apache/camel/component/aws/sdb/SdbOperations;
      39: new           #4                  // class org/apache/camel/component/aws/sdb/SdbOperations
      42: dup
      43: ldc           #14                 // String DeleteDomain
      45: iconst_3
      46: invokespecial #8                  // Method "<init>":(Ljava/lang/String;I)V
      49: putstatic     #15                 // Field DeleteDomain:Lorg/apache/camel/component/aws/sdb/SdbOperations;
      52: new           #4                  // class org/apache/camel/component/aws/sdb/SdbOperations
      55: dup
      56: ldc           #16                 // String DomainMetadata
      58: iconst_4
      59: invokespecial #8                  // Method "<init>":(Ljava/lang/String;I)V
      62: putstatic     #17                 // Field DomainMetadata:Lorg/apache/camel/component/aws/sdb/SdbOperations;
      65: new           #4                  // class org/apache/camel/component/aws/sdb/SdbOperations
      68: dup
      69: ldc           #18                 // String GetAttributes
      71: iconst_5
      72: invokespecial #8                  // Method "<init>":(Ljava/lang/String;I)V
      75: putstatic     #19                 // Field GetAttributes:Lorg/apache/camel/component/aws/sdb/SdbOperations;
      78: new           #4                  // class org/apache/camel/component/aws/sdb/SdbOperations
      81: dup
      82: ldc           #20                 // String ListDomains
      84: bipush        6
      86: invokespecial #8                  // Method "<init>":(Ljava/lang/String;I)V
      89: putstatic     #21                 // Field ListDomains:Lorg/apache/camel/component/aws/sdb/SdbOperations;
      92: new           #4                  // class org/apache/camel/component/aws/sdb/SdbOperations
      95: dup
      96: ldc           #22                 // String PutAttributes
      98: bipush        7
     100: invokespecial #8                  // Method "<init>":(Ljava/lang/String;I)V
     103: putstatic     #23                 // Field PutAttributes:Lorg/apache/camel/component/aws/sdb/SdbOperations;
     106: new           #4                  // class org/apache/camel/component/aws/sdb/SdbOperations
     109: dup
     110: ldc           #24                 // String Select
     112: bipush        8
     114: invokespecial #8                  // Method "<init>":(Ljava/lang/String;I)V
     117: putstatic     #25                 // Field Select:Lorg/apache/camel/component/aws/sdb/SdbOperations;
     120: bipush        9
     122: anewarray     #4                  // class org/apache/camel/component/aws/sdb/SdbOperations
     125: dup
     126: iconst_0
     127: getstatic     #9                  // Field BatchDeleteAttributes:Lorg/apache/camel/component/aws/sdb/SdbOperations;
     130: aastore
     131: dup
     132: iconst_1
     133: getstatic     #11                 // Field BatchPutAttributes:Lorg/apache/camel/component/aws/sdb/SdbOperations;
     136: aastore
     137: dup
     138: iconst_2
     139: getstatic     #13                 // Field DeleteAttributes:Lorg/apache/camel/component/aws/sdb/SdbOperations;
     142: aastore
     143: dup
     144: iconst_3
     145: getstatic     #15                 // Field DeleteDomain:Lorg/apache/camel/component/aws/sdb/SdbOperations;
     148: aastore
     149: dup
     150: iconst_4
     151: getstatic     #17                 // Field DomainMetadata:Lorg/apache/camel/component/aws/sdb/SdbOperations;
     154: aastore
     155: dup
     156: iconst_5
     157: getstatic     #19                 // Field GetAttributes:Lorg/apache/camel/component/aws/sdb/SdbOperations;
     160: aastore
     161: dup
     162: bipush        6
     164: getstatic     #21                 // Field ListDomains:Lorg/apache/camel/component/aws/sdb/SdbOperations;
     167: aastore
     168: dup
     169: bipush        7
     171: getstatic     #23                 // Field PutAttributes:Lorg/apache/camel/component/aws/sdb/SdbOperations;
     174: aastore
     175: dup
     176: bipush        8
     178: getstatic     #25                 // Field Select:Lorg/apache/camel/component/aws/sdb/SdbOperations;
     181: aastore
     182: putstatic     #1                  // Field $VALUES:[Lorg/apache/camel/component/aws/sdb/SdbOperations;
     185: return
}
