Compiled from "SubmissionAddressingFeature.java"
public final class org.apache.axis2.jaxws.addressing.SubmissionAddressingFeature extends javax.xml.ws.WebServiceFeature {
  public static final java.lang.String ID;

  protected boolean required;

  public org.apache.axis2.jaxws.addressing.SubmissionAddressingFeature();
    Code:
       0: aload_0
       1: iconst_1
       2: iconst_0
       3: invokespecial #1                  // Method "<init>":(ZZ)V
       6: return

  public org.apache.axis2.jaxws.addressing.SubmissionAddressingFeature(boolean);
    Code:
       0: aload_0
       1: iload_1
       2: iconst_0
       3: invokespecial #1                  // Method "<init>":(ZZ)V
       6: return

  public org.apache.axis2.jaxws.addressing.SubmissionAddressingFeature(boolean, boolean);
    Code:
       0: aload_0
       1: invokespecial #2                  // Method javax/xml/ws/WebServiceFeature."<init>":()V
       4: aload_0
       5: iload_1
       6: putfield      #3                  // Field enabled:Z
       9: aload_0
      10: iload_2
      11: putfield      #4                  // Field required:Z
      14: return

  public boolean isRequired();
    Code:
       0: aload_0
       1: getfield      #4                  // Field required:Z
       4: ireturn

  public java.lang.String getID();
    Code:
       0: ldc           #6                  // String http://schemas.xmlsoap.org/ws/2004/08/addressing
       2: areturn
}
