Compiled from "CamelBeanPostProcessor.java"
class org.apache.camel.spring.CamelBeanPostProcessor$1$1 extends org.apache.camel.impl.CamelPostProcessorHelper {
  final org.apache.camel.spring.CamelBeanPostProcessor$1 this$1;

  org.apache.camel.spring.CamelBeanPostProcessor$1$1(org.apache.camel.spring.CamelBeanPostProcessor$1);
    Code:
       0: aload_0
       1: aload_1
       2: putfield      #1                  // Field this$1:Lorg/apache/camel/spring/CamelBeanPostProcessor$1;
       5: aload_0
       6: invokespecial #2                  // Method org/apache/camel/impl/CamelPostProcessorHelper."<init>":()V
       9: return

  public org.apache.camel.CamelContext getCamelContext();
    Code:
       0: aload_0
       1: getfield      #1                  // Field this$1:Lorg/apache/camel/spring/CamelBeanPostProcessor$1;
       4: getfield      #3                  // Field org/apache/camel/spring/CamelBeanPostProcessor$1.this$0:Lorg/apache/camel/spring/CamelBeanPostProcessor;
       7: invokestatic  #4                  // Method org/apache/camel/spring/CamelBeanPostProcessor.access$200:(Lorg/apache/camel/spring/CamelBeanPostProcessor;)Lorg/apache/camel/impl/DefaultCamelBeanPostProcessor;
      10: invokevirtual #5                  // Method org/apache/camel/impl/DefaultCamelBeanPostProcessor.getOrLookupCamelContext:()Lorg/apache/camel/CamelContext;
      13: areturn

  protected java.lang.RuntimeException createProxyInstantiationRuntimeException(java.lang.Class<?>, org.apache.camel.Endpoint, java.lang.Exception);
    Code:
       0: new           #6                  // class org/springframework/beans/BeanInstantiationException
       3: dup
       4: aload_1
       5: new           #7                  // class java/lang/StringBuilder
       8: dup
       9: invokespecial #8                  // Method java/lang/StringBuilder."<init>":()V
      12: ldc           #9                  // String Could not instantiate proxy of type
      14: invokevirtual #10                 // Method java/lang/StringBuilder.append:(Ljava/lang/String;)Ljava/lang/StringBuilder;
      17: aload_1
      18: invokevirtual #11                 // Method java/lang/Class.getName:()Ljava/lang/String;
      21: invokevirtual #10                 // Method java/lang/StringBuilder.append:(Ljava/lang/String;)Ljava/lang/StringBuilder;
      24: ldc           #12                 // String  on endpoint
      26: invokevirtual #10                 // Method java/lang/StringBuilder.append:(Ljava/lang/String;)Ljava/lang/StringBuilder;
      29: aload_2
      30: invokevirtual #13                 // Method java/lang/StringBuilder.append:(Ljava/lang/Object;)Ljava/lang/StringBuilder;
      33: invokevirtual #14                 // Method java/lang/StringBuilder.toString:()Ljava/lang/String;
      36: aload_3
      37: invokespecial #15                 // Method org/springframework/beans/BeanInstantiationException."<init>":(Ljava/lang/Class;Ljava/lang/String;Ljava/lang/Throwable;)V
      40: areturn

  protected boolean isSingleton(java.lang.Object, java.lang.String);
    Code:
       0: aload_0
       1: getfield      #1                  // Field this$1:Lorg/apache/camel/spring/CamelBeanPostProcessor$1;
       4: getfield      #3                  // Field org/apache/camel/spring/CamelBeanPostProcessor$1.this$0:Lorg/apache/camel/spring/CamelBeanPostProcessor;
       7: invokestatic  #16                 // Method org/apache/camel/spring/CamelBeanPostProcessor.access$100:(Lorg/apache/camel/spring/CamelBeanPostProcessor;)Lorg/springframework/context/ApplicationContext;
      10: ifnull        17
      13: aload_2
      14: ifnonnull     24
      17: aload_0
      18: aload_1
      19: aload_2
      20: invokespecial #17                 // Method org/apache/camel/impl/CamelPostProcessorHelper.isSingleton:(Ljava/lang/Object;Ljava/lang/String;)Z
      23: ireturn
      24: aload_0
      25: getfield      #1                  // Field this$1:Lorg/apache/camel/spring/CamelBeanPostProcessor$1;
      28: getfield      #3                  // Field org/apache/camel/spring/CamelBeanPostProcessor$1.this$0:Lorg/apache/camel/spring/CamelBeanPostProcessor;
      31: invokestatic  #16                 // Method org/apache/camel/spring/CamelBeanPostProcessor.access$100:(Lorg/apache/camel/spring/CamelBeanPostProcessor;)Lorg/springframework/context/ApplicationContext;
      34: aload_2
      35: invokeinterface #18,  2           // InterfaceMethod org/springframework/context/ApplicationContext.isSingleton:(Ljava/lang/String;)Z
      40: ireturn

  protected void startService(org.apache.camel.Service, java.lang.Object, java.lang.String) throws java.lang.Exception;
    Code:
       0: aload_0
       1: aload_2
       2: aload_3
       3: invokevirtual #19                 // Method isSingleton:(Ljava/lang/Object;Ljava/lang/String;)Z
       6: ifeq          22
       9: aload_0
      10: invokevirtual #20                 // Method getCamelContext:()Lorg/apache/camel/CamelContext;
      13: aload_1
      14: invokeinterface #21,  2           // InterfaceMethod org/apache/camel/CamelContext.addService:(Ljava/lang/Object;)V
      19: goto          86
      22: aload_1
      23: invokestatic  #22                 // Method org/apache/camel/util/ServiceHelper.startService:(Lorg/apache/camel/Service;)V
      26: aload_0
      27: getfield      #1                  // Field this$1:Lorg/apache/camel/spring/CamelBeanPostProcessor$1;
      30: getfield      #3                  // Field org/apache/camel/spring/CamelBeanPostProcessor$1.this$0:Lorg/apache/camel/spring/CamelBeanPostProcessor;
      33: getfield      #23                 // Field org/apache/camel/spring/CamelBeanPostProcessor.prototypeBeans:Ljava/util/Set;
      36: aload_3
      37: invokeinterface #24,  2           // InterfaceMethod java/util/Set.add:(Ljava/lang/Object;)Z
      42: ifeq          86
      45: invokestatic  #25                 // Method org/apache/camel/spring/CamelBeanPostProcessor.access$300:()Lorg/slf4j/Logger;
      48: new           #7                  // class java/lang/StringBuilder
      51: dup
      52: invokespecial #8                  // Method java/lang/StringBuilder."<init>":()V
      55: ldc           #26                 // String The bean with id [
      57: invokevirtual #10                 // Method java/lang/StringBuilder.append:(Ljava/lang/String;)Ljava/lang/StringBuilder;
      60: aload_3
      61: invokevirtual #10                 // Method java/lang/StringBuilder.append:(Ljava/lang/String;)Ljava/lang/StringBuilder;
      64: ldc           #27                 // String ] is prototype scoped and cannot stop the injected service when bean is destroyed:
      66: invokevirtual #10                 // Method java/lang/StringBuilder.append:(Ljava/lang/String;)Ljava/lang/StringBuilder;
      69: aload_1
      70: invokevirtual #13                 // Method java/lang/StringBuilder.append:(Ljava/lang/Object;)Ljava/lang/StringBuilder;
      73: ldc           #28                 // String . You may want to stop the service manually from the bean.
      75: invokevirtual #10                 // Method java/lang/StringBuilder.append:(Ljava/lang/String;)Ljava/lang/StringBuilder;
      78: invokevirtual #14                 // Method java/lang/StringBuilder.toString:()Ljava/lang/String;
      81: invokeinterface #29,  2           // InterfaceMethod org/slf4j/Logger.warn:(Ljava/lang/String;)V
      86: return
}
