Compiled from "WebappClassLoaderBase.java"
public final class org.apache.catalina.loader.WebappClassLoaderBase$PrivilegedJavaseGetResource implements java.security.PrivilegedAction<java.net.URL> {
  private final java.lang.String name;

  final org.apache.catalina.loader.WebappClassLoaderBase this$0;

  public org.apache.catalina.loader.WebappClassLoaderBase$PrivilegedJavaseGetResource(org.apache.catalina.loader.WebappClassLoaderBase, java.lang.String);
    Code:
       0: aload_0
       1: aload_1
       2: putfield      #1                  // Field this$0:Lorg/apache/catalina/loader/WebappClassLoaderBase;
       5: aload_0
       6: invokespecial #2                  // Method java/lang/Object."<init>":()V
       9: aload_0
      10: aload_2
      11: putfield      #3                  // Field name:Ljava/lang/String;
      14: return

  public java.net.URL run();
    Code:
       0: aload_0
       1: getfield      #1                  // Field this$0:Lorg/apache/catalina/loader/WebappClassLoaderBase;
       4: invokestatic  #4                  // Method org/apache/catalina/loader/WebappClassLoaderBase.access$000:(Lorg/apache/catalina/loader/WebappClassLoaderBase;)Ljava/lang/ClassLoader;
       7: aload_0
       8: getfield      #3                  // Field name:Ljava/lang/String;
      11: invokevirtual #5                  // Method java/lang/ClassLoader.getResource:(Ljava/lang/String;)Ljava/net/URL;
      14: areturn

  public java.lang.Object run();
    Code:
       0: aload_0
       1: invokevirtual #6                  // Method run:()Ljava/net/URL;
       4: areturn
}
