Compiled from "ListFindingAggregationsIterable.java"
class software.amazon.awssdk.services.inspector2.paginators.ListFindingAggregationsIterable$ListFindingAggregationsResponseFetcher implements software.amazon.awssdk.core.pagination.sync.SyncPageFetcher<software.amazon.awssdk.services.inspector2.model.ListFindingAggregationsResponse> {
  final software.amazon.awssdk.services.inspector2.paginators.ListFindingAggregationsIterable this$0;

  private software.amazon.awssdk.services.inspector2.paginators.ListFindingAggregationsIterable$ListFindingAggregationsResponseFetcher(software.amazon.awssdk.services.inspector2.paginators.ListFindingAggregationsIterable);
    Code:
       0: aload_0
       1: aload_1
       2: putfield      #2                  // Field this$0:Lsoftware/amazon/awssdk/services/inspector2/paginators/ListFindingAggregationsIterable;
       5: aload_0
       6: invokespecial #3                  // Method java/lang/Object."<init>":()V
       9: return

  public boolean hasNextPage(software.amazon.awssdk.services.inspector2.model.ListFindingAggregationsResponse);
    Code:
       0: aload_1
       1: invokevirtual #4                  // Method software/amazon/awssdk/services/inspector2/model/ListFindingAggregationsResponse.nextToken:()Ljava/lang/String;
       4: invokestatic  #5                  // Method software/amazon/awssdk/core/util/PaginatorUtils.isOutputTokenAvailable:(Ljava/lang/Object;)Z
       7: ireturn

  public software.amazon.awssdk.services.inspector2.model.ListFindingAggregationsResponse nextPage(software.amazon.awssdk.services.inspector2.model.ListFindingAggregationsResponse);
    Code:
       0: aload_1
       1: ifnonnull     24
       4: aload_0
       5: getfield      #2                  // Field this$0:Lsoftware/amazon/awssdk/services/inspector2/paginators/ListFindingAggregationsIterable;
       8: invokestatic  #6                  // Method software/amazon/awssdk/services/inspector2/paginators/ListFindingAggregationsIterable.access$200:(Lsoftware/amazon/awssdk/services/inspector2/paginators/ListFindingAggregationsIterable;)Lsoftware/amazon/awssdk/services/inspector2/Inspector2Client;
      11: aload_0
      12: getfield      #2                  // Field this$0:Lsoftware/amazon/awssdk/services/inspector2/paginators/ListFindingAggregationsIterable;
      15: invokestatic  #7                  // Method software/amazon/awssdk/services/inspector2/paginators/ListFindingAggregationsIterable.access$100:(Lsoftware/amazon/awssdk/services/inspector2/paginators/ListFindingAggregationsIterable;)Lsoftware/amazon/awssdk/services/inspector2/model/ListFindingAggregationsRequest;
      18: invokeinterface #8,  2            // InterfaceMethod software/amazon/awssdk/services/inspector2/Inspector2Client.listFindingAggregations:(Lsoftware/amazon/awssdk/services/inspector2/model/ListFindingAggregationsRequest;)Lsoftware/amazon/awssdk/services/inspector2/model/ListFindingAggregationsResponse;
      23: areturn
      24: aload_0
      25: getfield      #2                  // Field this$0:Lsoftware/amazon/awssdk/services/inspector2/paginators/ListFindingAggregationsIterable;
      28: invokestatic  #6                  // Method software/amazon/awssdk/services/inspector2/paginators/ListFindingAggregationsIterable.access$200:(Lsoftware/amazon/awssdk/services/inspector2/paginators/ListFindingAggregationsIterable;)Lsoftware/amazon/awssdk/services/inspector2/Inspector2Client;
      31: aload_0
      32: getfield      #2                  // Field this$0:Lsoftware/amazon/awssdk/services/inspector2/paginators/ListFindingAggregationsIterable;
      35: invokestatic  #7                  // Method software/amazon/awssdk/services/inspector2/paginators/ListFindingAggregationsIterable.access$100:(Lsoftware/amazon/awssdk/services/inspector2/paginators/ListFindingAggregationsIterable;)Lsoftware/amazon/awssdk/services/inspector2/model/ListFindingAggregationsRequest;
      38: invokevirtual #9                  // Method software/amazon/awssdk/services/inspector2/model/ListFindingAggregationsRequest.toBuilder:()Lsoftware/amazon/awssdk/services/inspector2/model/ListFindingAggregationsRequest$Builder;
      41: aload_1
      42: invokevirtual #4                  // Method software/amazon/awssdk/services/inspector2/model/ListFindingAggregationsResponse.nextToken:()Ljava/lang/String;
      45: invokeinterface #10,  2           // InterfaceMethod software/amazon/awssdk/services/inspector2/model/ListFindingAggregationsRequest$Builder.nextToken:(Ljava/lang/String;)Lsoftware/amazon/awssdk/services/inspector2/model/ListFindingAggregationsRequest$Builder;
      50: invokeinterface #11,  1           // InterfaceMethod software/amazon/awssdk/services/inspector2/model/ListFindingAggregationsRequest$Builder.build:()Ljava/lang/Object;
      55: checkcast     #12                 // class software/amazon/awssdk/services/inspector2/model/ListFindingAggregationsRequest
      58: invokeinterface #8,  2            // InterfaceMethod software/amazon/awssdk/services/inspector2/Inspector2Client.listFindingAggregations:(Lsoftware/amazon/awssdk/services/inspector2/model/ListFindingAggregationsRequest;)Lsoftware/amazon/awssdk/services/inspector2/model/ListFindingAggregationsResponse;
      63: areturn

  public java.lang.Object nextPage(java.lang.Object);
    Code:
       0: aload_0
       1: aload_1
       2: checkcast     #13                 // class software/amazon/awssdk/services/inspector2/model/ListFindingAggregationsResponse
       5: invokevirtual #14                 // Method nextPage:(Lsoftware/amazon/awssdk/services/inspector2/model/ListFindingAggregationsResponse;)Lsoftware/amazon/awssdk/services/inspector2/model/ListFindingAggregationsResponse;
       8: areturn

  public boolean hasNextPage(java.lang.Object);
    Code:
       0: aload_0
       1: aload_1
       2: checkcast     #13                 // class software/amazon/awssdk/services/inspector2/model/ListFindingAggregationsResponse
       5: invokevirtual #15                 // Method hasNextPage:(Lsoftware/amazon/awssdk/services/inspector2/model/ListFindingAggregationsResponse;)Z
       8: ireturn

  software.amazon.awssdk.services.inspector2.paginators.ListFindingAggregationsIterable$ListFindingAggregationsResponseFetcher(software.amazon.awssdk.services.inspector2.paginators.ListFindingAggregationsIterable, software.amazon.awssdk.services.inspector2.paginators.ListFindingAggregationsIterable$1);
    Code:
       0: aload_0
       1: aload_1
       2: invokespecial #1                  // Method "<init>":(Lsoftware/amazon/awssdk/services/inspector2/paginators/ListFindingAggregationsIterable;)V
       5: return
}
