Compiled from "XMLConfigurator.java"
public class org.opensaml.core.xml.config.XMLConfigurator {
  public static final java.lang.String XMLTOOLING_CONFIG_NS;

  public static final java.lang.String XMLTOOLING_CONFIG_PREFIX;

  public static final java.lang.String XMLTOOLING_DEFAULT_OBJECT_PROVIDER;

  public static final java.lang.String XMLTOOLING_SCHEMA_LOCATION;

  private final org.slf4j.Logger log;

  private net.shibboleth.utilities.java.support.xml.BasicParserPool parserPool;

  private javax.xml.validation.Schema configurationSchema;

  private final org.opensaml.core.xml.config.XMLObjectProviderRegistry registry;

  public org.opensaml.core.xml.config.XMLConfigurator() throws org.opensaml.core.xml.config.XMLConfigurationException;
    Code:
       0: aload_0
       1: invokespecial #1                  // Method java/lang/Object."<init>":()V
       4: aload_0
       5: ldc_w         #2                  // class org/opensaml/core/xml/config/XMLConfigurator
       8: invokestatic  #3                  // Method org/slf4j/LoggerFactory.getLogger:(Ljava/lang/Class;)Lorg/slf4j/Logger;
      11: putfield      #4                  // Field log:Lorg/slf4j/Logger;
      14: aload_0
      15: new           #5                  // class net/shibboleth/utilities/java/support/xml/BasicParserPool
      18: dup
      19: invokespecial #6                  // Method net/shibboleth/utilities/java/support/xml/BasicParserPool."<init>":()V
      22: putfield      #7                  // Field parserPool:Lnet/shibboleth/utilities/java/support/xml/BasicParserPool;
      25: ldc           #8                  // String http://www.w3.org/2001/XMLSchema
      27: invokestatic  #9                  // Method javax/xml/validation/SchemaFactory.newInstance:(Ljava/lang/String;)Ljavax/xml/validation/SchemaFactory;
      30: astore_1
      31: new           #10                 // class javax/xml/transform/stream/StreamSource
      34: dup
      35: ldc_w         #2                  // class org/opensaml/core/xml/config/XMLConfigurator
      38: ldc           #11                 // String /schema/xmltooling-config.xsd
      40: invokevirtual #12                 // Method java/lang/Class.getResourceAsStream:(Ljava/lang/String;)Ljava/io/InputStream;
      43: invokespecial #13                 // Method javax/xml/transform/stream/StreamSource."<init>":(Ljava/io/InputStream;)V
      46: astore_2
      47: aload_0
      48: aload_1
      49: aload_2
      50: invokevirtual #14                 // Method javax/xml/validation/SchemaFactory.newSchema:(Ljavax/xml/transform/Source;)Ljavax/xml/validation/Schema;
      53: putfield      #15                 // Field configurationSchema:Ljavax/xml/validation/Schema;
      56: aload_0
      57: getfield      #7                  // Field parserPool:Lnet/shibboleth/utilities/java/support/xml/BasicParserPool;
      60: iconst_1
      61: invokevirtual #16                 // Method net/shibboleth/utilities/java/support/xml/BasicParserPool.setIgnoreComments:(Z)V
      64: aload_0
      65: getfield      #7                  // Field parserPool:Lnet/shibboleth/utilities/java/support/xml/BasicParserPool;
      68: iconst_1
      69: invokevirtual #17                 // Method net/shibboleth/utilities/java/support/xml/BasicParserPool.setIgnoreElementContentWhitespace:(Z)V
      72: aload_0
      73: getfield      #7                  // Field parserPool:Lnet/shibboleth/utilities/java/support/xml/BasicParserPool;
      76: aload_0
      77: getfield      #15                 // Field configurationSchema:Ljavax/xml/validation/Schema;
      80: invokevirtual #18                 // Method net/shibboleth/utilities/java/support/xml/BasicParserPool.setSchema:(Ljavax/xml/validation/Schema;)V
      83: aload_0
      84: getfield      #7                  // Field parserPool:Lnet/shibboleth/utilities/java/support/xml/BasicParserPool;
      87: invokevirtual #19                 // Method net/shibboleth/utilities/java/support/xml/BasicParserPool.initialize:()V
      90: goto          117
      93: astore_3
      94: new           #21                 // class org/opensaml/core/xml/config/XMLConfigurationException
      97: dup
      98: ldc           #22                 // String Unable to read XMLTooling configuration schema
     100: aload_3
     101: invokespecial #23                 // Method org/opensaml/core/xml/config/XMLConfigurationException."<init>":(Ljava/lang/String;Ljava/lang/Exception;)V
     104: athrow
     105: astore_3
     106: new           #21                 // class org/opensaml/core/xml/config/XMLConfigurationException
     109: dup
     110: ldc           #25                 // String Unable to initialize parser pool
     112: aload_3
     113: invokespecial #23                 // Method org/opensaml/core/xml/config/XMLConfigurationException."<init>":(Ljava/lang/String;Ljava/lang/Exception;)V
     116: athrow
     117: ldc_w         #26                 // class org/opensaml/core/config/ConfigurationService
     120: dup
     121: astore_3
     122: monitorenter
     123: ldc_w         #27                 // class org/opensaml/core/xml/config/XMLObjectProviderRegistry
     126: invokestatic  #28                 // Method org/opensaml/core/config/ConfigurationService.get:(Ljava/lang/Class;)Ljava/lang/Object;
     129: checkcast     #27                 // class org/opensaml/core/xml/config/XMLObjectProviderRegistry
     132: astore        4
     134: aload         4
     136: ifnonnull     167
     139: aload_0
     140: getfield      #4                  // Field log:Lorg/slf4j/Logger;
     143: ldc           #29                 // String XMLObjectProviderRegistry did not exist in ConfigurationService, will be created
     145: invokeinterface #30,  2           // InterfaceMethod org/slf4j/Logger.debug:(Ljava/lang/String;)V
     150: new           #27                 // class org/opensaml/core/xml/config/XMLObjectProviderRegistry
     153: dup
     154: invokespecial #31                 // Method org/opensaml/core/xml/config/XMLObjectProviderRegistry."<init>":()V
     157: astore        4
     159: ldc_w         #27                 // class org/opensaml/core/xml/config/XMLObjectProviderRegistry
     162: aload         4
     164: invokestatic  #32                 // Method org/opensaml/core/config/ConfigurationService.register:(Ljava/lang/Class;Ljava/lang/Object;)V
     167: aload_0
     168: aload         4
     170: putfield      #33                 // Field registry:Lorg/opensaml/core/xml/config/XMLObjectProviderRegistry;
     173: aload_3
     174: monitorexit
     175: goto          185
     178: astore        5
     180: aload_3
     181: monitorexit
     182: aload         5
     184: athrow
     185: return
    Exception table:
       from    to  target type
          47    90    93   Class org/xml/sax/SAXException
          47    90   105   Class net/shibboleth/utilities/java/support/component/ComponentInitializationException
         123   175   178   any
         178   182   178   any

  public void load(java.io.File) throws org.opensaml.core.xml.config.XMLConfigurationException;
    Code:
       0: aload_1
       1: ifnull        11
       4: aload_1
       5: invokevirtual #34                 // Method java/io/File.canRead:()Z
       8: ifne          24
      11: aload_0
      12: getfield      #4                  // Field log:Lorg/slf4j/Logger;
      15: ldc           #35                 // String Unable to read configuration file {}
      17: aload_1
      18: invokeinterface #36,  3           // InterfaceMethod org/slf4j/Logger.error:(Ljava/lang/String;Ljava/lang/Object;)V
      23: return
      24: aload_1
      25: invokevirtual #37                 // Method java/io/File.isDirectory:()Z
      28: ifeq          84
      31: aload_1
      32: invokevirtual #38                 // Method java/io/File.listFiles:()[Ljava/io/File;
      35: astore_2
      36: iconst_0
      37: istore_3
      38: iload_3
      39: aload_2
      40: arraylength
      41: if_icmpge     81
      44: aload_0
      45: getfield      #4                  // Field log:Lorg/slf4j/Logger;
      48: ldc           #39                 // String Parsing configuration file {}
      50: aload_2
      51: iload_3
      52: aaload
      53: invokevirtual #40                 // Method java/io/File.getAbsolutePath:()Ljava/lang/String;
      56: invokeinterface #41,  3           // InterfaceMethod org/slf4j/Logger.debug:(Ljava/lang/String;Ljava/lang/Object;)V
      61: aload_0
      62: new           #42                 // class java/io/FileInputStream
      65: dup
      66: aload_2
      67: iload_3
      68: aaload
      69: invokespecial #43                 // Method java/io/FileInputStream."<init>":(Ljava/io/File;)V
      72: invokevirtual #44                 // Method load:(Ljava/io/InputStream;)V
      75: iinc          3, 1
      78: goto          38
      81: goto          111
      84: aload_0
      85: getfield      #4                  // Field log:Lorg/slf4j/Logger;
      88: ldc           #39                 // String Parsing configuration file {}
      90: aload_1
      91: invokevirtual #40                 // Method java/io/File.getAbsolutePath:()Ljava/lang/String;
      94: invokeinterface #41,  3           // InterfaceMethod org/slf4j/Logger.debug:(Ljava/lang/String;Ljava/lang/Object;)V
      99: aload_0
     100: new           #42                 // class java/io/FileInputStream
     103: dup
     104: aload_1
     105: invokespecial #43                 // Method java/io/FileInputStream."<init>":(Ljava/io/File;)V
     108: invokevirtual #44                 // Method load:(Ljava/io/InputStream;)V
     111: goto          115
     114: astore_2
     115: return
    Exception table:
       from    to  target type
          24   111   114   Class java/io/FileNotFoundException

  public void load(java.io.InputStream) throws org.opensaml.core.xml.config.XMLConfigurationException;
    Code:
       0: aload_0
       1: getfield      #7                  // Field parserPool:Lnet/shibboleth/utilities/java/support/xml/BasicParserPool;
       4: aload_1
       5: invokevirtual #46                 // Method net/shibboleth/utilities/java/support/xml/BasicParserPool.parse:(Ljava/io/InputStream;)Lorg/w3c/dom/Document;
       8: astore_2
       9: aload_0
      10: aload_2
      11: invokevirtual #47                 // Method load:(Lorg/w3c/dom/Document;)V
      14: goto          41
      17: astore_2
      18: aload_0
      19: getfield      #4                  // Field log:Lorg/slf4j/Logger;
      22: ldc           #49                 // String Invalid configuration file
      24: aload_2
      25: invokeinterface #50,  3           // InterfaceMethod org/slf4j/Logger.error:(Ljava/lang/String;Ljava/lang/Throwable;)V
      30: new           #21                 // class org/opensaml/core/xml/config/XMLConfigurationException
      33: dup
      34: ldc           #51                 // String Unable to create DocumentBuilder
      36: aload_2
      37: invokespecial #23                 // Method org/opensaml/core/xml/config/XMLConfigurationException."<init>":(Ljava/lang/String;Ljava/lang/Exception;)V
      40: athrow
      41: return
    Exception table:
       from    to  target type
           0    14    17   Class net/shibboleth/utilities/java/support/xml/XMLParserException

  public void load(org.w3c.dom.Document) throws org.opensaml.core.xml.config.XMLConfigurationException;
    Code:
       0: aload_1
       1: invokeinterface #52,  1           // InterfaceMethod org/w3c/dom/Document.getDocumentElement:()Lorg/w3c/dom/Element;
       6: ldc           #53                 // String Document element cannot be null
       8: invokestatic  #54                 // Method net/shibboleth/utilities/java/support/logic/Constraint.isNotNull:(Ljava/lang/Object;Ljava/lang/String;)Ljava/lang/Object;
      11: checkcast     #55                 // class org/w3c/dom/Element
      14: astore_2
      15: aload_0
      16: getfield      #4                  // Field log:Lorg/slf4j/Logger;
      19: ldc           #56                 // String Loading configuration from XML Document
      21: invokeinterface #30,  2           // InterfaceMethod org/slf4j/Logger.debug:(Ljava/lang/String;)V
      26: aload_0
      27: getfield      #4                  // Field log:Lorg/slf4j/Logger;
      30: ldc           #57                 // String {}
      32: aload_2
      33: invokestatic  #58                 // Method net/shibboleth/utilities/java/support/xml/SerializeSupport.nodeToString:(Lorg/w3c/dom/Node;)Ljava/lang/String;
      36: invokeinterface #59,  3           // InterfaceMethod org/slf4j/Logger.trace:(Ljava/lang/String;Ljava/lang/Object;)V
      41: aload_0
      42: getfield      #4                  // Field log:Lorg/slf4j/Logger;
      45: ldc           #60                 // String Schema validating configuration Document
      47: invokeinterface #30,  2           // InterfaceMethod org/slf4j/Logger.debug:(Ljava/lang/String;)V
      52: aload_0
      53: aload_1
      54: invokevirtual #61                 // Method validateConfiguration:(Lorg/w3c/dom/Document;)V
      57: aload_0
      58: getfield      #4                  // Field log:Lorg/slf4j/Logger;
      61: ldc           #62                 // String Configuration document validated
      63: invokeinterface #30,  2           // InterfaceMethod org/slf4j/Logger.debug:(Ljava/lang/String;)V
      68: aload_0
      69: aload_2
      70: invokevirtual #63                 // Method load:(Lorg/w3c/dom/Element;)V
      73: return

  protected void load(org.w3c.dom.Element) throws org.opensaml.core.xml.config.XMLConfigurationException;
    Code:
       0: aload_1
       1: ldc           #64                 // String http://www.opensaml.org/xmltooling-config
       3: ldc           #65                 // String ObjectProviders
       5: invokeinterface #66,  3           // InterfaceMethod org/w3c/dom/Element.getElementsByTagNameNS:(Ljava/lang/String;Ljava/lang/String;)Lorg/w3c/dom/NodeList;
      10: astore_2
      11: aload_2
      12: invokeinterface #67,  1           // InterfaceMethod org/w3c/dom/NodeList.getLength:()I
      17: ifle          56
      20: aload_0
      21: getfield      #4                  // Field log:Lorg/slf4j/Logger;
      24: ldc           #68                 // String Preparing to load ObjectProviders
      26: invokeinterface #30,  2           // InterfaceMethod org/slf4j/Logger.debug:(Ljava/lang/String;)V
      31: aload_0
      32: aload_2
      33: iconst_0
      34: invokeinterface #69,  2           // InterfaceMethod org/w3c/dom/NodeList.item:(I)Lorg/w3c/dom/Node;
      39: checkcast     #55                 // class org/w3c/dom/Element
      42: invokevirtual #70                 // Method initializeObjectProviders:(Lorg/w3c/dom/Element;)V
      45: aload_0
      46: getfield      #4                  // Field log:Lorg/slf4j/Logger;
      49: ldc           #71                 // String ObjectProviders load complete
      51: invokeinterface #30,  2           // InterfaceMethod org/slf4j/Logger.debug:(Ljava/lang/String;)V
      56: aload_1
      57: ldc           #64                 // String http://www.opensaml.org/xmltooling-config
      59: ldc           #72                 // String IDAttributes
      61: invokeinterface #66,  3           // InterfaceMethod org/w3c/dom/Element.getElementsByTagNameNS:(Ljava/lang/String;Ljava/lang/String;)Lorg/w3c/dom/NodeList;
      66: astore_3
      67: aload_3
      68: invokeinterface #67,  1           // InterfaceMethod org/w3c/dom/NodeList.getLength:()I
      73: ifle          112
      76: aload_0
      77: getfield      #4                  // Field log:Lorg/slf4j/Logger;
      80: ldc           #73                 // String Preparing to load IDAttributes
      82: invokeinterface #30,  2           // InterfaceMethod org/slf4j/Logger.debug:(Ljava/lang/String;)V
      87: aload_0
      88: aload_3
      89: iconst_0
      90: invokeinterface #69,  2           // InterfaceMethod org/w3c/dom/NodeList.item:(I)Lorg/w3c/dom/Node;
      95: checkcast     #55                 // class org/w3c/dom/Element
      98: invokevirtual #74                 // Method initializeIDAttributes:(Lorg/w3c/dom/Element;)V
     101: aload_0
     102: getfield      #4                  // Field log:Lorg/slf4j/Logger;
     105: ldc           #75                 // String IDAttributes load complete
     107: invokeinterface #30,  2           // InterfaceMethod org/slf4j/Logger.debug:(Ljava/lang/String;)V
     112: return

  protected void initializeObjectProviders(org.w3c.dom.Element) throws org.opensaml.core.xml.config.XMLConfigurationException;
    Code:
       0: aload_1
       1: ldc           #64                 // String http://www.opensaml.org/xmltooling-config
       3: ldc           #76                 // String ObjectProvider
       5: invokeinterface #66,  3           // InterfaceMethod org/w3c/dom/Element.getElementsByTagNameNS:(Ljava/lang/String;Ljava/lang/String;)Lorg/w3c/dom/NodeList;
      10: astore_2
      11: iconst_0
      12: istore_3
      13: iload_3
      14: aload_2
      15: invokeinterface #67,  1           // InterfaceMethod org/w3c/dom/NodeList.getLength:()I
      20: if_icmpge     232
      23: aload_2
      24: iload_3
      25: invokeinterface #69,  2           // InterfaceMethod org/w3c/dom/NodeList.item:(I)Lorg/w3c/dom/Node;
      30: checkcast     #55                 // class org/w3c/dom/Element
      33: astore        4
      35: aload         4
      37: aconst_null
      38: ldc           #77                 // String qualifiedName
      40: invokeinterface #78,  3           // InterfaceMethod org/w3c/dom/Element.getAttributeNodeNS:(Ljava/lang/String;Ljava/lang/String;)Lorg/w3c/dom/Attr;
      45: astore        5
      47: aload         5
      49: invokestatic  #79                 // Method net/shibboleth/utilities/java/support/xml/AttributeSupport.getAttributeValueAsQName:(Lorg/w3c/dom/Attr;)Ljavax/xml/namespace/QName;
      52: astore        6
      54: aload_0
      55: getfield      #4                  // Field log:Lorg/slf4j/Logger;
      58: ldc           #80                 // String Initializing object provider {}
      60: aload         6
      62: invokeinterface #41,  3           // InterfaceMethod org/slf4j/Logger.debug:(Ljava/lang/String;Ljava/lang/Object;)V
      67: aload         4
      69: ldc           #64                 // String http://www.opensaml.org/xmltooling-config
      71: ldc           #81                 // String BuilderClass
      73: invokeinterface #66,  3           // InterfaceMethod org/w3c/dom/Element.getElementsByTagNameNS:(Ljava/lang/String;Ljava/lang/String;)Lorg/w3c/dom/NodeList;
      78: iconst_0
      79: invokeinterface #69,  2           // InterfaceMethod org/w3c/dom/NodeList.item:(I)Lorg/w3c/dom/Node;
      84: checkcast     #55                 // class org/w3c/dom/Element
      87: astore        7
      89: aload_0
      90: aload         7
      92: invokevirtual #82                 // Method createClassInstance:(Lorg/w3c/dom/Element;)Ljava/lang/Object;
      95: checkcast     #83                 // class org/opensaml/core/xml/XMLObjectBuilder
      98: astore        8
     100: aload         4
     102: ldc           #64                 // String http://www.opensaml.org/xmltooling-config
     104: ldc           #84                 // String MarshallingClass
     106: invokeinterface #66,  3           // InterfaceMethod org/w3c/dom/Element.getElementsByTagNameNS:(Ljava/lang/String;Ljava/lang/String;)Lorg/w3c/dom/NodeList;
     111: iconst_0
     112: invokeinterface #69,  2           // InterfaceMethod org/w3c/dom/NodeList.item:(I)Lorg/w3c/dom/Node;
     117: checkcast     #55                 // class org/w3c/dom/Element
     120: astore        7
     122: aload_0
     123: aload         7
     125: invokevirtual #82                 // Method createClassInstance:(Lorg/w3c/dom/Element;)Ljava/lang/Object;
     128: checkcast     #85                 // class org/opensaml/core/xml/io/Marshaller
     131: astore        9
     133: aload         4
     135: ldc           #64                 // String http://www.opensaml.org/xmltooling-config
     137: ldc           #86                 // String UnmarshallingClass
     139: invokeinterface #66,  3           // InterfaceMethod org/w3c/dom/Element.getElementsByTagNameNS:(Ljava/lang/String;Ljava/lang/String;)Lorg/w3c/dom/NodeList;
     144: iconst_0
     145: invokeinterface #69,  2           // InterfaceMethod org/w3c/dom/NodeList.item:(I)Lorg/w3c/dom/Node;
     150: checkcast     #55                 // class org/w3c/dom/Element
     153: astore        7
     155: aload_0
     156: aload         7
     158: invokevirtual #82                 // Method createClassInstance:(Lorg/w3c/dom/Element;)Ljava/lang/Object;
     161: checkcast     #87                 // class org/opensaml/core/xml/io/Unmarshaller
     164: astore        10
     166: aload_0
     167: invokevirtual #88                 // Method getRegistry:()Lorg/opensaml/core/xml/config/XMLObjectProviderRegistry;
     170: aload         6
     172: aload         8
     174: aload         9
     176: aload         10
     178: invokevirtual #89                 // Method org/opensaml/core/xml/config/XMLObjectProviderRegistry.registerObjectProvider:(Ljavax/xml/namespace/QName;Lorg/opensaml/core/xml/XMLObjectBuilder;Lorg/opensaml/core/xml/io/Marshaller;Lorg/opensaml/core/xml/io/Unmarshaller;)V
     181: aload_0
     182: getfield      #4                  // Field log:Lorg/slf4j/Logger;
     185: ldc           #90                 // String {} intialized and configuration cached
     187: aload         6
     189: invokeinterface #41,  3           // InterfaceMethod org/slf4j/Logger.debug:(Ljava/lang/String;Ljava/lang/Object;)V
     194: goto          226
     197: astore        7
     199: aload_0
     200: getfield      #4                  // Field log:Lorg/slf4j/Logger;
     203: ldc           #91                 // String Error initializing object provier {}
     205: aload         4
     207: aload         7
     209: invokeinterface #92,  4           // InterfaceMethod org/slf4j/Logger.error:(Ljava/lang/String;Ljava/lang/Object;Ljava/lang/Object;)V
     214: aload_0
     215: invokevirtual #88                 // Method getRegistry:()Lorg/opensaml/core/xml/config/XMLObjectProviderRegistry;
     218: aload         6
     220: invokevirtual #93                 // Method org/opensaml/core/xml/config/XMLObjectProviderRegistry.deregisterObjectProvider:(Ljavax/xml/namespace/QName;)V
     223: aload         7
     225: athrow
     226: iinc          3, 1
     229: goto          13
     232: return
    Exception table:
       from    to  target type
          67   194   197   Class org/opensaml/core/xml/config/XMLConfigurationException

  protected void initializeIDAttributes(org.w3c.dom.Element) throws org.opensaml.core.xml.config.XMLConfigurationException;
    Code:
       0: aload_1
       1: ldc           #64                 // String http://www.opensaml.org/xmltooling-config
       3: ldc           #94                 // String IDAttribute
       5: invokeinterface #66,  3           // InterfaceMethod org/w3c/dom/Element.getElementsByTagNameNS:(Ljava/lang/String;Ljava/lang/String;)Lorg/w3c/dom/NodeList;
      10: astore        4
      12: iconst_0
      13: istore        5
      15: iload         5
      17: aload         4
      19: invokeinterface #67,  1           // InterfaceMethod org/w3c/dom/NodeList.getLength:()I
      24: if_icmpge     89
      27: aload         4
      29: iload         5
      31: invokeinterface #69,  2           // InterfaceMethod org/w3c/dom/NodeList.item:(I)Lorg/w3c/dom/Node;
      36: checkcast     #55                 // class org/w3c/dom/Element
      39: astore_2
      40: aload_2
      41: invokestatic  #95                 // Method net/shibboleth/utilities/java/support/xml/ElementSupport.getElementContentAsQName:(Lorg/w3c/dom/Element;)Ljavax/xml/namespace/QName;
      44: astore_3
      45: aload_3
      46: ifnonnull     63
      49: aload_0
      50: getfield      #4                  // Field log:Lorg/slf4j/Logger;
      53: ldc           #96                 // String IDAttribute element was empty, no registration performed
      55: invokeinterface #30,  2           // InterfaceMethod org/slf4j/Logger.debug:(Ljava/lang/String;)V
      60: goto          83
      63: aload_0
      64: invokevirtual #88                 // Method getRegistry:()Lorg/opensaml/core/xml/config/XMLObjectProviderRegistry;
      67: aload_3
      68: invokevirtual #97                 // Method org/opensaml/core/xml/config/XMLObjectProviderRegistry.registerIDAttribute:(Ljavax/xml/namespace/QName;)V
      71: aload_0
      72: getfield      #4                  // Field log:Lorg/slf4j/Logger;
      75: ldc           #98                 // String IDAttribute {} has been registered
      77: aload_3
      78: invokeinterface #41,  3           // InterfaceMethod org/slf4j/Logger.debug:(Ljava/lang/String;Ljava/lang/Object;)V
      83: iinc          5, 1
      86: goto          15
      89: return

  protected java.lang.Object createClassInstance(org.w3c.dom.Element) throws org.opensaml.core.xml.config.XMLConfigurationException;
    Code:
       0: aload_1
       1: aconst_null
       2: ldc           #99                 // String className
       4: invokeinterface #100,  3          // InterfaceMethod org/w3c/dom/Element.getAttributeNS:(Ljava/lang/String;Ljava/lang/String;)Ljava/lang/String;
       9: invokestatic  #101                // Method net/shibboleth/utilities/java/support/primitive/StringSupport.trimOrNull:(Ljava/lang/String;)Ljava/lang/String;
      12: astore_2
      13: aload_2
      14: ifnonnull     19
      17: aconst_null
      18: areturn
      19: aload_0
      20: getfield      #4                  // Field log:Lorg/slf4j/Logger;
      23: ldc           #102                // String Creating instance of {}
      25: aload_2
      26: invokeinterface #59,  3           // InterfaceMethod org/slf4j/Logger.trace:(Ljava/lang/String;Ljava/lang/Object;)V
      31: invokestatic  #103                // Method java/lang/Thread.currentThread:()Ljava/lang/Thread;
      34: invokevirtual #104                // Method java/lang/Thread.getContextClassLoader:()Ljava/lang/ClassLoader;
      37: astore_3
      38: aload_3
      39: aload_2
      40: invokevirtual #105                // Method java/lang/ClassLoader.loadClass:(Ljava/lang/String;)Ljava/lang/Class;
      43: astore        4
      45: aload         4
      47: iconst_0
      48: anewarray     #106                // class java/lang/Class
      51: invokevirtual #107                // Method java/lang/Class.getConstructor:([Ljava/lang/Class;)Ljava/lang/reflect/Constructor;
      54: astore        5
      56: aload         5
      58: iconst_0
      59: anewarray     #108                // class java/lang/Object
      62: invokevirtual #109                // Method java/lang/reflect/Constructor.newInstance:([Ljava/lang/Object;)Ljava/lang/Object;
      65: areturn
      66: astore_3
      67: new           #111                // class java/lang/StringBuilder
      70: dup
      71: invokespecial #112                // Method java/lang/StringBuilder."<init>":()V
      74: ldc           #113                // String Cannot create instance of
      76: invokevirtual #114                // Method java/lang/StringBuilder.append:(Ljava/lang/String;)Ljava/lang/StringBuilder;
      79: aload_2
      80: invokevirtual #114                // Method java/lang/StringBuilder.append:(Ljava/lang/String;)Ljava/lang/StringBuilder;
      83: invokevirtual #115                // Method java/lang/StringBuilder.toString:()Ljava/lang/String;
      86: astore        4
      88: aload_0
      89: getfield      #4                  // Field log:Lorg/slf4j/Logger;
      92: aload         4
      94: aload_3
      95: invokeinterface #50,  3           // InterfaceMethod org/slf4j/Logger.error:(Ljava/lang/String;Ljava/lang/Throwable;)V
     100: new           #21                 // class org/opensaml/core/xml/config/XMLConfigurationException
     103: dup
     104: aload         4
     106: aload_3
     107: invokespecial #23                 // Method org/opensaml/core/xml/config/XMLConfigurationException."<init>":(Ljava/lang/String;Ljava/lang/Exception;)V
     110: athrow
    Exception table:
       from    to  target type
          19    65    66   Class java/lang/Exception

  protected void validateConfiguration(org.w3c.dom.Document) throws org.opensaml.core.xml.config.XMLConfigurationException;
    Code:
       0: aload_0
       1: getfield      #15                 // Field configurationSchema:Ljavax/xml/validation/Schema;
       4: invokevirtual #116                // Method javax/xml/validation/Schema.newValidator:()Ljavax/xml/validation/Validator;
       7: astore_2
       8: aload_2
       9: new           #117                // class javax/xml/transform/dom/DOMSource
      12: dup
      13: aload_1
      14: invokespecial #118                // Method javax/xml/transform/dom/DOMSource."<init>":(Lorg/w3c/dom/Node;)V
      17: invokevirtual #119                // Method javax/xml/validation/Validator.validate:(Ljavax/xml/transform/Source;)V
      20: goto          73
      23: astore_2
      24: ldc           #121                // String Unable to read configuration file DOM
      26: astore_3
      27: aload_0
      28: getfield      #4                  // Field log:Lorg/slf4j/Logger;
      31: aload_3
      32: aload_2
      33: invokeinterface #50,  3           // InterfaceMethod org/slf4j/Logger.error:(Ljava/lang/String;Ljava/lang/Throwable;)V
      38: new           #21                 // class org/opensaml/core/xml/config/XMLConfigurationException
      41: dup
      42: aload_3
      43: aload_2
      44: invokespecial #23                 // Method org/opensaml/core/xml/config/XMLConfigurationException."<init>":(Ljava/lang/String;Ljava/lang/Exception;)V
      47: athrow
      48: astore_2
      49: ldc           #122                // String Configuration file does not validate against schema
      51: astore_3
      52: aload_0
      53: getfield      #4                  // Field log:Lorg/slf4j/Logger;
      56: aload_3
      57: aload_2
      58: invokeinterface #50,  3           // InterfaceMethod org/slf4j/Logger.error:(Ljava/lang/String;Ljava/lang/Throwable;)V
      63: new           #21                 // class org/opensaml/core/xml/config/XMLConfigurationException
      66: dup
      67: aload_3
      68: aload_2
      69: invokespecial #23                 // Method org/opensaml/core/xml/config/XMLConfigurationException."<init>":(Ljava/lang/String;Ljava/lang/Exception;)V
      72: athrow
      73: return
    Exception table:
       from    to  target type
           0    20    23   Class java/io/IOException
           0    20    48   Class org/xml/sax/SAXException

  protected org.opensaml.core.xml.config.XMLObjectProviderRegistry getRegistry();
    Code:
       0: aload_0
       1: getfield      #33                 // Field registry:Lorg/opensaml/core/xml/config/XMLObjectProviderRegistry;
       4: areturn
}
