Compiled from "AuditLogXml_4.java"
public class org.jboss.as.domain.management.parsing.AuditLogXml_4 extends org.jboss.as.domain.management.parsing.AuditLogXml {
  final boolean host;

  public org.jboss.as.domain.management.parsing.AuditLogXml_4(boolean);
    Code:
       0: aload_0
       1: invokespecial #3                  // Method org/jboss/as/domain/management/parsing/AuditLogXml."<init>":()V
       4: aload_0
       5: iload_1
       6: putfield      #4                  // Field host:Z
       9: return

  public void parseAuditLog(org.jboss.staxmapper.XMLExtendedStreamReader, org.jboss.dmr.ModelNode, org.jboss.as.controller.parsing.Namespace, java.util.List<org.jboss.dmr.ModelNode>) throws javax.xml.stream.XMLStreamException;
    Code:
       0: aload_1
       1: aload_3
       2: invokestatic  #5                  // Method org/jboss/as/controller/parsing/ParseUtils.requireNamespace:(Lorg/jboss/staxmapper/XMLExtendedStreamReader;Lorg/jboss/as/controller/parsing/Namespace;)V
       5: aload_2
       6: invokevirtual #6                  // Method org/jboss/dmr/ModelNode.clone:()Lorg/jboss/dmr/ModelNode;
       9: getstatic     #7                  // Field org/jboss/as/domain/management/audit/AccessAuditResourceDefinition.PATH_ELEMENT:Lorg/jboss/as/controller/PathElement;
      12: invokevirtual #8                  // Method org/jboss/as/controller/PathElement.getKey:()Ljava/lang/String;
      15: getstatic     #7                  // Field org/jboss/as/domain/management/audit/AccessAuditResourceDefinition.PATH_ELEMENT:Lorg/jboss/as/controller/PathElement;
      18: invokevirtual #9                  // Method org/jboss/as/controller/PathElement.getValue:()Ljava/lang/String;
      21: invokevirtual #10                 // Method org/jboss/dmr/ModelNode.add:(Ljava/lang/String;Ljava/lang/String;)Lorg/jboss/dmr/ModelNode;
      24: astore        5
      26: new           #11                 // class org/jboss/dmr/ModelNode
      29: dup
      30: invokespecial #12                 // Method org/jboss/dmr/ModelNode."<init>":()V
      33: astore        6
      35: aload         6
      37: ldc           #13                 // String operation
      39: invokevirtual #14                 // Method org/jboss/dmr/ModelNode.get:(Ljava/lang/String;)Lorg/jboss/dmr/ModelNode;
      42: ldc           #15                 // String add
      44: invokevirtual #16                 // Method org/jboss/dmr/ModelNode.set:(Ljava/lang/String;)Lorg/jboss/dmr/ModelNode;
      47: pop
      48: aload         6
      50: ldc           #17                 // String address
      52: invokevirtual #14                 // Method org/jboss/dmr/ModelNode.get:(Ljava/lang/String;)Lorg/jboss/dmr/ModelNode;
      55: aload         5
      57: invokevirtual #18                 // Method org/jboss/dmr/ModelNode.set:(Lorg/jboss/dmr/ModelNode;)Lorg/jboss/dmr/ModelNode;
      60: pop
      61: aload         4
      63: aload         6
      65: invokeinterface #19,  2           // InterfaceMethod java/util/List.add:(Ljava/lang/Object;)Z
      70: pop
      71: aload_1
      72: invokestatic  #20                 // Method org/jboss/as/controller/parsing/ParseUtils.requireNoAttributes:(Lorg/jboss/staxmapper/XMLExtendedStreamReader;)V
      75: aload_1
      76: invokeinterface #21,  1           // InterfaceMethod org/jboss/staxmapper/XMLExtendedStreamReader.hasNext:()Z
      81: ifeq          221
      84: aload_1
      85: invokeinterface #22,  1           // InterfaceMethod org/jboss/staxmapper/XMLExtendedStreamReader.nextTag:()I
      90: iconst_2
      91: if_icmpeq     221
      94: aload_1
      95: aload_3
      96: invokestatic  #5                  // Method org/jboss/as/controller/parsing/ParseUtils.requireNamespace:(Lorg/jboss/staxmapper/XMLExtendedStreamReader;Lorg/jboss/as/controller/parsing/Namespace;)V
      99: aload_1
     100: invokeinterface #23,  1           // InterfaceMethod org/jboss/staxmapper/XMLExtendedStreamReader.getLocalName:()Ljava/lang/String;
     105: invokestatic  #24                 // Method org/jboss/as/controller/parsing/Element.forName:(Ljava/lang/String;)Lorg/jboss/as/controller/parsing/Element;
     108: astore        7
     110: getstatic     #25                 // Field org/jboss/as/domain/management/parsing/AuditLogXml_4$1.$SwitchMap$org$jboss$as$controller$parsing$Element:[I
     113: aload         7
     115: invokevirtual #26                 // Method org/jboss/as/controller/parsing/Element.ordinal:()I
     118: iaload
     119: tableswitch   { // 1 to 4
                     1: 148
                     2: 161
                     3: 174
                     4: 190
               default: 213
          }
     148: aload_0
     149: aload_1
     150: aload         5
     152: aload_3
     153: aload         4
     155: invokespecial #27                 // Method parseAuditLogFormatters:(Lorg/jboss/staxmapper/XMLExtendedStreamReader;Lorg/jboss/dmr/ModelNode;Lorg/jboss/as/controller/parsing/Namespace;Ljava/util/List;)V
     158: goto          218
     161: aload_0
     162: aload_1
     163: aload         5
     165: aload_3
     166: aload         4
     168: invokespecial #28                 // Method parseAuditLogHandlers:(Lorg/jboss/staxmapper/XMLExtendedStreamReader;Lorg/jboss/dmr/ModelNode;Lorg/jboss/as/controller/parsing/Namespace;Ljava/util/List;)V
     171: goto          218
     174: aload_0
     175: aload_1
     176: aload         5
     178: aload_3
     179: getstatic     #29                 // Field org/jboss/as/domain/management/audit/AuditLogLoggerResourceDefinition.PATH_ELEMENT:Lorg/jboss/as/controller/PathElement;
     182: aload         4
     184: invokespecial #30                 // Method parseAuditLogConfig:(Lorg/jboss/staxmapper/XMLExtendedStreamReader;Lorg/jboss/dmr/ModelNode;Lorg/jboss/as/controller/parsing/Namespace;Lorg/jboss/as/controller/PathElement;Ljava/util/List;)V
     187: goto          218
     190: aload_0
     191: getfield      #4                  // Field host:Z
     194: ifeq          213
     197: aload_0
     198: aload_1
     199: aload         5
     201: aload_3
     202: getstatic     #31                 // Field org/jboss/as/domain/management/audit/AuditLogLoggerResourceDefinition.HOST_SERVER_PATH_ELEMENT:Lorg/jboss/as/controller/PathElement;
     205: aload         4
     207: invokespecial #30                 // Method parseAuditLogConfig:(Lorg/jboss/staxmapper/XMLExtendedStreamReader;Lorg/jboss/dmr/ModelNode;Lorg/jboss/as/controller/parsing/Namespace;Lorg/jboss/as/controller/PathElement;Ljava/util/List;)V
     210: goto          218
     213: aload_1
     214: invokestatic  #32                 // Method org/jboss/as/controller/parsing/ParseUtils.unexpectedElement:(Lorg/jboss/staxmapper/XMLExtendedStreamReader;)Ljavax/xml/stream/XMLStreamException;
     217: athrow
     218: goto          75
     221: return

  private void parseAuditLogFormatters(org.jboss.staxmapper.XMLExtendedStreamReader, org.jboss.dmr.ModelNode, org.jboss.as.controller.parsing.Namespace, java.util.List<org.jboss.dmr.ModelNode>) throws javax.xml.stream.XMLStreamException;
    Code:
       0: aload_1
       1: aload_3
       2: invokestatic  #5                  // Method org/jboss/as/controller/parsing/ParseUtils.requireNamespace:(Lorg/jboss/staxmapper/XMLExtendedStreamReader;Lorg/jboss/as/controller/parsing/Namespace;)V
       5: aload_1
       6: invokeinterface #21,  1           // InterfaceMethod org/jboss/staxmapper/XMLExtendedStreamReader.hasNext:()Z
      11: ifeq          88
      14: aload_1
      15: invokeinterface #22,  1           // InterfaceMethod org/jboss/staxmapper/XMLExtendedStreamReader.nextTag:()I
      20: iconst_2
      21: if_icmpeq     88
      24: aload_1
      25: aload_3
      26: invokestatic  #5                  // Method org/jboss/as/controller/parsing/ParseUtils.requireNamespace:(Lorg/jboss/staxmapper/XMLExtendedStreamReader;Lorg/jboss/as/controller/parsing/Namespace;)V
      29: aload_1
      30: invokeinterface #23,  1           // InterfaceMethod org/jboss/staxmapper/XMLExtendedStreamReader.getLocalName:()Ljava/lang/String;
      35: invokestatic  #24                 // Method org/jboss/as/controller/parsing/Element.forName:(Ljava/lang/String;)Lorg/jboss/as/controller/parsing/Element;
      38: astore        5
      40: getstatic     #25                 // Field org/jboss/as/domain/management/parsing/AuditLogXml_4$1.$SwitchMap$org$jboss$as$controller$parsing$Element:[I
      43: aload         5
      45: invokevirtual #26                 // Method org/jboss/as/controller/parsing/Element.ordinal:()I
      48: iaload
      49: lookupswitch  { // 1
                     5: 68
               default: 80
          }
      68: aload_0
      69: aload_1
      70: aload_2
      71: aload_3
      72: aload         4
      74: invokespecial #33                 // Method parseFileAuditLogFormatter:(Lorg/jboss/staxmapper/XMLExtendedStreamReader;Lorg/jboss/dmr/ModelNode;Lorg/jboss/as/controller/parsing/Namespace;Ljava/util/List;)V
      77: goto          85
      80: aload_1
      81: invokestatic  #32                 // Method org/jboss/as/controller/parsing/ParseUtils.unexpectedElement:(Lorg/jboss/staxmapper/XMLExtendedStreamReader;)Ljavax/xml/stream/XMLStreamException;
      84: athrow
      85: goto          5
      88: return

  private void parseFileAuditLogFormatter(org.jboss.staxmapper.XMLExtendedStreamReader, org.jboss.dmr.ModelNode, org.jboss.as.controller.parsing.Namespace, java.util.List<org.jboss.dmr.ModelNode>) throws javax.xml.stream.XMLStreamException;
    Code:
       0: invokestatic  #34                 // Method org/jboss/as/controller/operations/common/Util.createAddOperation:()Lorg/jboss/dmr/ModelNode;
       3: astore        5
       5: aload         4
       7: aload         5
       9: invokeinterface #19,  2           // InterfaceMethod java/util/List.add:(Ljava/lang/Object;)Z
      14: pop
      15: aload_1
      16: invokeinterface #35,  1           // InterfaceMethod org/jboss/staxmapper/XMLExtendedStreamReader.getAttributeCount:()I
      21: istore        6
      23: iconst_0
      24: istore        7
      26: iload         7
      28: iload         6
      30: if_icmpge     243
      33: aload_1
      34: iload         7
      36: invokeinterface #36,  2           // InterfaceMethod org/jboss/staxmapper/XMLExtendedStreamReader.getAttributeValue:(I)Ljava/lang/String;
      41: astore        8
      43: aload_1
      44: iload         7
      46: invokestatic  #37                 // Method org/jboss/as/controller/parsing/ParseUtils.isNoNamespaceAttribute:(Lorg/jboss/staxmapper/XMLExtendedStreamReader;I)Z
      49: ifne          59
      52: aload_1
      53: iload         7
      55: invokestatic  #38                 // Method org/jboss/as/controller/parsing/ParseUtils.unexpectedAttribute:(Lorg/jboss/staxmapper/XMLExtendedStreamReader;I)Ljavax/xml/stream/XMLStreamException;
      58: athrow
      59: aload_1
      60: iload         7
      62: invokeinterface #39,  2           // InterfaceMethod org/jboss/staxmapper/XMLExtendedStreamReader.getAttributeLocalName:(I)Ljava/lang/String;
      67: invokestatic  #40                 // Method org/jboss/as/controller/parsing/Attribute.forName:(Ljava/lang/String;)Lorg/jboss/as/controller/parsing/Attribute;
      70: astore        9
      72: getstatic     #41                 // Field org/jboss/as/domain/management/parsing/AuditLogXml_4$1.$SwitchMap$org$jboss$as$controller$parsing$Attribute:[I
      75: aload         9
      77: invokevirtual #42                 // Method org/jboss/as/controller/parsing/Attribute.ordinal:()I
      80: iaload
      81: tableswitch   { // 1 to 7
                     1: 124
                     2: 146
                     3: 160
                     4: 174
                     5: 188
                     6: 202
                     7: 216
               default: 230
          }
     124: aload         5
     126: ldc           #17                 // String address
     128: invokevirtual #14                 // Method org/jboss/dmr/ModelNode.get:(Ljava/lang/String;)Lorg/jboss/dmr/ModelNode;
     131: aload_2
     132: invokevirtual #18                 // Method org/jboss/dmr/ModelNode.set:(Lorg/jboss/dmr/ModelNode;)Lorg/jboss/dmr/ModelNode;
     135: ldc           #43                 // String json-formatter
     137: aload         8
     139: invokevirtual #10                 // Method org/jboss/dmr/ModelNode.add:(Ljava/lang/String;Ljava/lang/String;)Lorg/jboss/dmr/ModelNode;
     142: pop
     143: goto          237
     146: getstatic     #44                 // Field org/jboss/as/domain/management/audit/JsonAuditLogFormatterResourceDefinition.COMPACT:Lorg/jboss/as/controller/SimpleAttributeDefinition;
     149: aload         8
     151: aload         5
     153: aload_1
     154: invokevirtual #45                 // Method org/jboss/as/controller/SimpleAttributeDefinition.parseAndSetParameter:(Ljava/lang/String;Lorg/jboss/dmr/ModelNode;Ljavax/xml/stream/XMLStreamReader;)V
     157: goto          237
     160: getstatic     #46                 // Field org/jboss/as/domain/management/audit/JsonAuditLogFormatterResourceDefinition.DATE_FORMAT:Lorg/jboss/as/controller/SimpleAttributeDefinition;
     163: aload         8
     165: aload         5
     167: aload_1
     168: invokevirtual #45                 // Method org/jboss/as/controller/SimpleAttributeDefinition.parseAndSetParameter:(Ljava/lang/String;Lorg/jboss/dmr/ModelNode;Ljavax/xml/stream/XMLStreamReader;)V
     171: goto          237
     174: getstatic     #47                 // Field org/jboss/as/domain/management/audit/JsonAuditLogFormatterResourceDefinition.DATE_SEPARATOR:Lorg/jboss/as/controller/SimpleAttributeDefinition;
     177: aload         8
     179: aload         5
     181: aload_1
     182: invokevirtual #45                 // Method org/jboss/as/controller/SimpleAttributeDefinition.parseAndSetParameter:(Ljava/lang/String;Lorg/jboss/dmr/ModelNode;Ljavax/xml/stream/XMLStreamReader;)V
     185: goto          237
     188: getstatic     #48                 // Field org/jboss/as/domain/management/audit/JsonAuditLogFormatterResourceDefinition.ESCAPE_CONTROL_CHARACTERS:Lorg/jboss/as/controller/SimpleAttributeDefinition;
     191: aload         8
     193: aload         5
     195: aload_1
     196: invokevirtual #45                 // Method org/jboss/as/controller/SimpleAttributeDefinition.parseAndSetParameter:(Ljava/lang/String;Lorg/jboss/dmr/ModelNode;Ljavax/xml/stream/XMLStreamReader;)V
     199: goto          237
     202: getstatic     #49                 // Field org/jboss/as/domain/management/audit/JsonAuditLogFormatterResourceDefinition.ESCAPE_NEW_LINE:Lorg/jboss/as/controller/SimpleAttributeDefinition;
     205: aload         8
     207: aload         5
     209: aload_1
     210: invokevirtual #45                 // Method org/jboss/as/controller/SimpleAttributeDefinition.parseAndSetParameter:(Ljava/lang/String;Lorg/jboss/dmr/ModelNode;Ljavax/xml/stream/XMLStreamReader;)V
     213: goto          237
     216: getstatic     #50                 // Field org/jboss/as/domain/management/audit/JsonAuditLogFormatterResourceDefinition.INCLUDE_DATE:Lorg/jboss/as/controller/SimpleAttributeDefinition;
     219: aload         8
     221: aload         5
     223: aload_1
     224: invokevirtual #45                 // Method org/jboss/as/controller/SimpleAttributeDefinition.parseAndSetParameter:(Ljava/lang/String;Lorg/jboss/dmr/ModelNode;Ljavax/xml/stream/XMLStreamReader;)V
     227: goto          237
     230: aload_1
     231: iload         7
     233: invokestatic  #38                 // Method org/jboss/as/controller/parsing/ParseUtils.unexpectedAttribute:(Lorg/jboss/staxmapper/XMLExtendedStreamReader;I)Ljavax/xml/stream/XMLStreamException;
     236: athrow
     237: iinc          7, 1
     240: goto          26
     243: aload_1
     244: invokestatic  #51                 // Method org/jboss/as/controller/parsing/ParseUtils.requireNoContent:(Lorg/jboss/staxmapper/XMLExtendedStreamReader;)V
     247: return

  private void parseAuditLogHandlers(org.jboss.staxmapper.XMLExtendedStreamReader, org.jboss.dmr.ModelNode, org.jboss.as.controller.parsing.Namespace, java.util.List<org.jboss.dmr.ModelNode>) throws javax.xml.stream.XMLStreamException;
    Code:
       0: aload_1
       1: aload_3
       2: invokestatic  #5                  // Method org/jboss/as/controller/parsing/ParseUtils.requireNamespace:(Lorg/jboss/staxmapper/XMLExtendedStreamReader;Lorg/jboss/as/controller/parsing/Namespace;)V
       5: iconst_0
       6: istore        5
       8: aload_1
       9: invokeinterface #21,  1           // InterfaceMethod org/jboss/staxmapper/XMLExtendedStreamReader.hasNext:()Z
      14: ifeq          169
      17: aload_1
      18: invokeinterface #22,  1           // InterfaceMethod org/jboss/staxmapper/XMLExtendedStreamReader.nextTag:()I
      23: iconst_2
      24: if_icmpeq     169
      27: aload_1
      28: aload_3
      29: invokestatic  #5                  // Method org/jboss/as/controller/parsing/ParseUtils.requireNamespace:(Lorg/jboss/staxmapper/XMLExtendedStreamReader;Lorg/jboss/as/controller/parsing/Namespace;)V
      32: aload_1
      33: invokeinterface #23,  1           // InterfaceMethod org/jboss/staxmapper/XMLExtendedStreamReader.getLocalName:()Ljava/lang/String;
      38: invokestatic  #24                 // Method org/jboss/as/controller/parsing/Element.forName:(Ljava/lang/String;)Lorg/jboss/as/controller/parsing/Element;
      41: astore        6
      43: getstatic     #25                 // Field org/jboss/as/domain/management/parsing/AuditLogXml_4$1.$SwitchMap$org$jboss$as$controller$parsing$Element:[I
      46: aload         6
      48: invokevirtual #26                 // Method org/jboss/as/controller/parsing/Element.ordinal:()I
      51: iaload
      52: tableswitch   { // 6 to 10
                     6: 88
                     7: 113
                     8: 125
                     9: 137
                    10: 149
               default: 161
          }
      88: iload         5
      90: ifeq          98
      93: aload_1
      94: invokestatic  #32                 // Method org/jboss/as/controller/parsing/ParseUtils.unexpectedElement:(Lorg/jboss/staxmapper/XMLExtendedStreamReader;)Ljavax/xml/stream/XMLStreamException;
      97: athrow
      98: aload_0
      99: aload_1
     100: aload_2
     101: aload_3
     102: aload         4
     104: invokespecial #52                 // Method parseConfigurationChangesAuditLogHandler:(Lorg/jboss/staxmapper/XMLExtendedStreamReader;Lorg/jboss/dmr/ModelNode;Lorg/jboss/as/controller/parsing/Namespace;Ljava/util/List;)V
     107: iconst_1
     108: istore        5
     110: goto          166
     113: aload_0
     114: aload_1
     115: aload_2
     116: aload_3
     117: aload         4
     119: invokespecial #53                 // Method parseFileAuditLogHandler:(Lorg/jboss/staxmapper/XMLExtendedStreamReader;Lorg/jboss/dmr/ModelNode;Lorg/jboss/as/controller/parsing/Namespace;Ljava/util/List;)V
     122: goto          166
     125: aload_0
     126: aload_1
     127: aload_2
     128: aload_3
     129: aload         4
     131: invokespecial #54                 // Method parsePeriodicRotatingFileAuditLogHandler:(Lorg/jboss/staxmapper/XMLExtendedStreamReader;Lorg/jboss/dmr/ModelNode;Lorg/jboss/as/controller/parsing/Namespace;Ljava/util/List;)V
     134: goto          166
     137: aload_0
     138: aload_1
     139: aload_2
     140: aload_3
     141: aload         4
     143: invokespecial #55                 // Method parseSizeRotatingFileAuditLogHandler:(Lorg/jboss/staxmapper/XMLExtendedStreamReader;Lorg/jboss/dmr/ModelNode;Lorg/jboss/as/controller/parsing/Namespace;Ljava/util/List;)V
     146: goto          166
     149: aload_0
     150: aload_1
     151: aload_2
     152: aload_3
     153: aload         4
     155: invokespecial #56                 // Method parseSyslogAuditLogHandler:(Lorg/jboss/staxmapper/XMLExtendedStreamReader;Lorg/jboss/dmr/ModelNode;Lorg/jboss/as/controller/parsing/Namespace;Ljava/util/List;)V
     158: goto          166
     161: aload_1
     162: invokestatic  #32                 // Method org/jboss/as/controller/parsing/ParseUtils.unexpectedElement:(Lorg/jboss/staxmapper/XMLExtendedStreamReader;)Ljavax/xml/stream/XMLStreamException;
     165: athrow
     166: goto          8
     169: return

  private void parseConfigurationChangesAuditLogHandler(org.jboss.staxmapper.XMLExtendedStreamReader, org.jboss.dmr.ModelNode, org.jboss.as.controller.parsing.Namespace, java.util.List<org.jboss.dmr.ModelNode>) throws javax.xml.stream.XMLStreamException;
    Code:
       0: invokestatic  #34                 // Method org/jboss/as/controller/operations/common/Util.createAddOperation:()Lorg/jboss/dmr/ModelNode;
       3: astore        5
       5: aload         4
       7: aload         5
       9: invokeinterface #19,  2           // InterfaceMethod java/util/List.add:(Ljava/lang/Object;)Z
      14: pop
      15: aload_1
      16: invokeinterface #35,  1           // InterfaceMethod org/jboss/staxmapper/XMLExtendedStreamReader.getAttributeCount:()I
      21: istore        6
      23: iconst_0
      24: istore        7
      26: iload         7
      28: iload         6
      30: if_icmpge     157
      33: aload_1
      34: iload         7
      36: invokeinterface #36,  2           // InterfaceMethod org/jboss/staxmapper/XMLExtendedStreamReader.getAttributeValue:(I)Ljava/lang/String;
      41: astore        8
      43: aload_1
      44: iload         7
      46: invokestatic  #37                 // Method org/jboss/as/controller/parsing/ParseUtils.isNoNamespaceAttribute:(Lorg/jboss/staxmapper/XMLExtendedStreamReader;I)Z
      49: ifne          59
      52: aload_1
      53: iload         7
      55: invokestatic  #38                 // Method org/jboss/as/controller/parsing/ParseUtils.unexpectedAttribute:(Lorg/jboss/staxmapper/XMLExtendedStreamReader;I)Ljavax/xml/stream/XMLStreamException;
      58: athrow
      59: aload_1
      60: iload         7
      62: invokeinterface #39,  2           // InterfaceMethod org/jboss/staxmapper/XMLExtendedStreamReader.getAttributeLocalName:(I)Ljava/lang/String;
      67: invokestatic  #40                 // Method org/jboss/as/controller/parsing/Attribute.forName:(Ljava/lang/String;)Lorg/jboss/as/controller/parsing/Attribute;
      70: astore        9
      72: getstatic     #41                 // Field org/jboss/as/domain/management/parsing/AuditLogXml_4$1.$SwitchMap$org$jboss$as$controller$parsing$Attribute:[I
      75: aload         9
      77: invokevirtual #42                 // Method org/jboss/as/controller/parsing/Attribute.ordinal:()I
      80: iaload
      81: lookupswitch  { // 2
                     1: 108
                     8: 130
               default: 144
          }
     108: aload         5
     110: ldc           #17                 // String address
     112: invokevirtual #14                 // Method org/jboss/dmr/ModelNode.get:(Ljava/lang/String;)Lorg/jboss/dmr/ModelNode;
     115: aload_2
     116: invokevirtual #18                 // Method org/jboss/dmr/ModelNode.set:(Lorg/jboss/dmr/ModelNode;)Lorg/jboss/dmr/ModelNode;
     119: ldc           #57                 // String in-memory-handler
     121: aload         8
     123: invokevirtual #10                 // Method org/jboss/dmr/ModelNode.add:(Ljava/lang/String;Ljava/lang/String;)Lorg/jboss/dmr/ModelNode;
     126: pop
     127: goto          151
     130: getstatic     #58                 // Field org/jboss/as/domain/management/audit/InMemoryAuditLogHandlerResourceDefinition.MAX_OPERATION_COUNT:Lorg/jboss/as/controller/SimpleAttributeDefinition;
     133: aload         8
     135: aload         5
     137: aload_1
     138: invokevirtual #45                 // Method org/jboss/as/controller/SimpleAttributeDefinition.parseAndSetParameter:(Ljava/lang/String;Lorg/jboss/dmr/ModelNode;Ljavax/xml/stream/XMLStreamReader;)V
     141: goto          151
     144: aload_1
     145: iload         7
     147: invokestatic  #38                 // Method org/jboss/as/controller/parsing/ParseUtils.unexpectedAttribute:(Lorg/jboss/staxmapper/XMLExtendedStreamReader;I)Ljavax/xml/stream/XMLStreamException;
     150: athrow
     151: iinc          7, 1
     154: goto          26
     157: aload_1
     158: invokestatic  #51                 // Method org/jboss/as/controller/parsing/ParseUtils.requireNoContent:(Lorg/jboss/staxmapper/XMLExtendedStreamReader;)V
     161: return

  private void parseFileAuditLogHandler(org.jboss.staxmapper.XMLExtendedStreamReader, org.jboss.dmr.ModelNode, org.jboss.as.controller.parsing.Namespace, java.util.List<org.jboss.dmr.ModelNode>) throws javax.xml.stream.XMLStreamException;
    Code:
       0: invokestatic  #34                 // Method org/jboss/as/controller/operations/common/Util.createAddOperation:()Lorg/jboss/dmr/ModelNode;
       3: astore        5
       5: aload         4
       7: aload         5
       9: invokeinterface #19,  2           // InterfaceMethod java/util/List.add:(Ljava/lang/Object;)Z
      14: pop
      15: aload_1
      16: invokeinterface #35,  1           // InterfaceMethod org/jboss/staxmapper/XMLExtendedStreamReader.getAttributeCount:()I
      21: istore        6
      23: iconst_0
      24: istore        7
      26: iload         7
      28: iload         6
      30: if_icmpge     235
      33: aload_1
      34: iload         7
      36: invokeinterface #36,  2           // InterfaceMethod org/jboss/staxmapper/XMLExtendedStreamReader.getAttributeValue:(I)Ljava/lang/String;
      41: astore        8
      43: aload_1
      44: iload         7
      46: invokestatic  #37                 // Method org/jboss/as/controller/parsing/ParseUtils.isNoNamespaceAttribute:(Lorg/jboss/staxmapper/XMLExtendedStreamReader;I)Z
      49: ifne          59
      52: aload_1
      53: iload         7
      55: invokestatic  #38                 // Method org/jboss/as/controller/parsing/ParseUtils.unexpectedAttribute:(Lorg/jboss/staxmapper/XMLExtendedStreamReader;I)Ljavax/xml/stream/XMLStreamException;
      58: athrow
      59: aload_1
      60: iload         7
      62: invokeinterface #39,  2           // InterfaceMethod org/jboss/staxmapper/XMLExtendedStreamReader.getAttributeLocalName:(I)Ljava/lang/String;
      67: invokestatic  #40                 // Method org/jboss/as/controller/parsing/Attribute.forName:(Ljava/lang/String;)Lorg/jboss/as/controller/parsing/Attribute;
      70: astore        9
      72: getstatic     #41                 // Field org/jboss/as/domain/management/parsing/AuditLogXml_4$1.$SwitchMap$org$jboss$as$controller$parsing$Attribute:[I
      75: aload         9
      77: invokevirtual #42                 // Method org/jboss/as/controller/parsing/Attribute.ordinal:()I
      80: iaload
      81: tableswitch   { // 1 to 12
                     1: 144
                     2: 222
                     3: 222
                     4: 222
                     5: 222
                     6: 222
                     7: 222
                     8: 222
                     9: 166
                    10: 180
                    11: 194
                    12: 208
               default: 222
          }
     144: aload         5
     146: ldc           #17                 // String address
     148: invokevirtual #14                 // Method org/jboss/dmr/ModelNode.get:(Ljava/lang/String;)Lorg/jboss/dmr/ModelNode;
     151: aload_2
     152: invokevirtual #18                 // Method org/jboss/dmr/ModelNode.set:(Lorg/jboss/dmr/ModelNode;)Lorg/jboss/dmr/ModelNode;
     155: ldc           #59                 // String file-handler
     157: aload         8
     159: invokevirtual #10                 // Method org/jboss/dmr/ModelNode.add:(Ljava/lang/String;Ljava/lang/String;)Lorg/jboss/dmr/ModelNode;
     162: pop
     163: goto          229
     166: getstatic     #60                 // Field org/jboss/as/domain/management/audit/FileAuditLogHandlerResourceDefinition.MAX_FAILURE_COUNT:Lorg/jboss/as/controller/SimpleAttributeDefinition;
     169: aload         8
     171: aload         5
     173: aload_1
     174: invokevirtual #45                 // Method org/jboss/as/controller/SimpleAttributeDefinition.parseAndSetParameter:(Ljava/lang/String;Lorg/jboss/dmr/ModelNode;Ljavax/xml/stream/XMLStreamReader;)V
     177: goto          229
     180: getstatic     #61                 // Field org/jboss/as/domain/management/audit/FileAuditLogHandlerResourceDefinition.FORMATTER:Lorg/jboss/as/controller/SimpleAttributeDefinition;
     183: aload         8
     185: aload         5
     187: aload_1
     188: invokevirtual #45                 // Method org/jboss/as/controller/SimpleAttributeDefinition.parseAndSetParameter:(Ljava/lang/String;Lorg/jboss/dmr/ModelNode;Ljavax/xml/stream/XMLStreamReader;)V
     191: goto          229
     194: getstatic     #62                 // Field org/jboss/as/domain/management/audit/FileAuditLogHandlerResourceDefinition.PATH:Lorg/jboss/as/controller/SimpleAttributeDefinition;
     197: aload         8
     199: aload         5
     201: aload_1
     202: invokevirtual #45                 // Method org/jboss/as/controller/SimpleAttributeDefinition.parseAndSetParameter:(Ljava/lang/String;Lorg/jboss/dmr/ModelNode;Ljavax/xml/stream/XMLStreamReader;)V
     205: goto          229
     208: getstatic     #63                 // Field org/jboss/as/domain/management/audit/FileAuditLogHandlerResourceDefinition.RELATIVE_TO:Lorg/jboss/as/controller/SimpleAttributeDefinition;
     211: aload         8
     213: aload         5
     215: aload_1
     216: invokevirtual #45                 // Method org/jboss/as/controller/SimpleAttributeDefinition.parseAndSetParameter:(Ljava/lang/String;Lorg/jboss/dmr/ModelNode;Ljavax/xml/stream/XMLStreamReader;)V
     219: goto          229
     222: aload_1
     223: iload         7
     225: invokestatic  #38                 // Method org/jboss/as/controller/parsing/ParseUtils.unexpectedAttribute:(Lorg/jboss/staxmapper/XMLExtendedStreamReader;I)Ljavax/xml/stream/XMLStreamException;
     228: athrow
     229: iinc          7, 1
     232: goto          26
     235: aload_1
     236: invokestatic  #51                 // Method org/jboss/as/controller/parsing/ParseUtils.requireNoContent:(Lorg/jboss/staxmapper/XMLExtendedStreamReader;)V
     239: return

  private void parseSizeRotatingFileAuditLogHandler(org.jboss.staxmapper.XMLExtendedStreamReader, org.jboss.dmr.ModelNode, org.jboss.as.controller.parsing.Namespace, java.util.List<org.jboss.dmr.ModelNode>) throws javax.xml.stream.XMLStreamException;
    Code:
       0: invokestatic  #34                 // Method org/jboss/as/controller/operations/common/Util.createAddOperation:()Lorg/jboss/dmr/ModelNode;
       3: astore        5
       5: aload         4
       7: aload         5
       9: invokeinterface #19,  2           // InterfaceMethod java/util/List.add:(Ljava/lang/Object;)Z
      14: pop
      15: aload_1
      16: invokeinterface #35,  1           // InterfaceMethod org/jboss/staxmapper/XMLExtendedStreamReader.getAttributeCount:()I
      21: istore        6
      23: iconst_0
      24: istore        7
      26: iload         7
      28: iload         6
      30: if_icmpge     271
      33: aload_1
      34: iload         7
      36: invokeinterface #36,  2           // InterfaceMethod org/jboss/staxmapper/XMLExtendedStreamReader.getAttributeValue:(I)Ljava/lang/String;
      41: astore        8
      43: aload_1
      44: iload         7
      46: invokestatic  #37                 // Method org/jboss/as/controller/parsing/ParseUtils.isNoNamespaceAttribute:(Lorg/jboss/staxmapper/XMLExtendedStreamReader;I)Z
      49: ifne          59
      52: aload_1
      53: iload         7
      55: invokestatic  #38                 // Method org/jboss/as/controller/parsing/ParseUtils.unexpectedAttribute:(Lorg/jboss/staxmapper/XMLExtendedStreamReader;I)Ljavax/xml/stream/XMLStreamException;
      58: athrow
      59: aload_1
      60: iload         7
      62: invokeinterface #39,  2           // InterfaceMethod org/jboss/staxmapper/XMLExtendedStreamReader.getAttributeLocalName:(I)Ljava/lang/String;
      67: invokestatic  #40                 // Method org/jboss/as/controller/parsing/Attribute.forName:(Ljava/lang/String;)Lorg/jboss/as/controller/parsing/Attribute;
      70: astore        9
      72: getstatic     #41                 // Field org/jboss/as/domain/management/parsing/AuditLogXml_4$1.$SwitchMap$org$jboss$as$controller$parsing$Attribute:[I
      75: aload         9
      77: invokevirtual #42                 // Method org/jboss/as/controller/parsing/Attribute.ordinal:()I
      80: iaload
      81: tableswitch   { // 1 to 14
                     1: 152
                     2: 258
                     3: 258
                     4: 258
                     5: 258
                     6: 258
                     7: 258
                     8: 258
                     9: 174
                    10: 188
                    11: 202
                    12: 216
                    13: 230
                    14: 244
               default: 258
          }
     152: aload         5
     154: ldc           #17                 // String address
     156: invokevirtual #14                 // Method org/jboss/dmr/ModelNode.get:(Ljava/lang/String;)Lorg/jboss/dmr/ModelNode;
     159: aload_2
     160: invokevirtual #18                 // Method org/jboss/dmr/ModelNode.set:(Lorg/jboss/dmr/ModelNode;)Lorg/jboss/dmr/ModelNode;
     163: ldc           #64                 // String size-rotating-file-handler
     165: aload         8
     167: invokevirtual #10                 // Method org/jboss/dmr/ModelNode.add:(Ljava/lang/String;Ljava/lang/String;)Lorg/jboss/dmr/ModelNode;
     170: pop
     171: goto          265
     174: getstatic     #65                 // Field org/jboss/as/domain/management/audit/SizeRotatingFileAuditLogHandlerResourceDefinition.MAX_FAILURE_COUNT:Lorg/jboss/as/controller/SimpleAttributeDefinition;
     177: aload         8
     179: aload         5
     181: aload_1
     182: invokevirtual #45                 // Method org/jboss/as/controller/SimpleAttributeDefinition.parseAndSetParameter:(Ljava/lang/String;Lorg/jboss/dmr/ModelNode;Ljavax/xml/stream/XMLStreamReader;)V
     185: goto          265
     188: getstatic     #66                 // Field org/jboss/as/domain/management/audit/SizeRotatingFileAuditLogHandlerResourceDefinition.FORMATTER:Lorg/jboss/as/controller/SimpleAttributeDefinition;
     191: aload         8
     193: aload         5
     195: aload_1
     196: invokevirtual #45                 // Method org/jboss/as/controller/SimpleAttributeDefinition.parseAndSetParameter:(Ljava/lang/String;Lorg/jboss/dmr/ModelNode;Ljavax/xml/stream/XMLStreamReader;)V
     199: goto          265
     202: getstatic     #67                 // Field org/jboss/as/domain/management/audit/SizeRotatingFileAuditLogHandlerResourceDefinition.PATH:Lorg/jboss/as/controller/SimpleAttributeDefinition;
     205: aload         8
     207: aload         5
     209: aload_1
     210: invokevirtual #45                 // Method org/jboss/as/controller/SimpleAttributeDefinition.parseAndSetParameter:(Ljava/lang/String;Lorg/jboss/dmr/ModelNode;Ljavax/xml/stream/XMLStreamReader;)V
     213: goto          265
     216: getstatic     #68                 // Field org/jboss/as/domain/management/audit/SizeRotatingFileAuditLogHandlerResourceDefinition.RELATIVE_TO:Lorg/jboss/as/controller/SimpleAttributeDefinition;
     219: aload         8
     221: aload         5
     223: aload_1
     224: invokevirtual #45                 // Method org/jboss/as/controller/SimpleAttributeDefinition.parseAndSetParameter:(Ljava/lang/String;Lorg/jboss/dmr/ModelNode;Ljavax/xml/stream/XMLStreamReader;)V
     227: goto          265
     230: getstatic     #69                 // Field org/jboss/as/domain/management/audit/SizeRotatingFileAuditLogHandlerResourceDefinition.ROTATE_SIZE:Lorg/jboss/as/controller/SimpleAttributeDefinition;
     233: aload         8
     235: aload         5
     237: aload_1
     238: invokevirtual #45                 // Method org/jboss/as/controller/SimpleAttributeDefinition.parseAndSetParameter:(Ljava/lang/String;Lorg/jboss/dmr/ModelNode;Ljavax/xml/stream/XMLStreamReader;)V
     241: goto          265
     244: getstatic     #70                 // Field org/jboss/as/domain/management/audit/SizeRotatingFileAuditLogHandlerResourceDefinition.MAX_BACKUP_INDEX:Lorg/jboss/as/controller/SimpleAttributeDefinition;
     247: aload         8
     249: aload         5
     251: aload_1
     252: invokevirtual #45                 // Method org/jboss/as/controller/SimpleAttributeDefinition.parseAndSetParameter:(Ljava/lang/String;Lorg/jboss/dmr/ModelNode;Ljavax/xml/stream/XMLStreamReader;)V
     255: goto          265
     258: aload_1
     259: iload         7
     261: invokestatic  #38                 // Method org/jboss/as/controller/parsing/ParseUtils.unexpectedAttribute:(Lorg/jboss/staxmapper/XMLExtendedStreamReader;I)Ljavax/xml/stream/XMLStreamException;
     264: athrow
     265: iinc          7, 1
     268: goto          26
     271: aload_1
     272: invokestatic  #51                 // Method org/jboss/as/controller/parsing/ParseUtils.requireNoContent:(Lorg/jboss/staxmapper/XMLExtendedStreamReader;)V
     275: return

  private void parsePeriodicRotatingFileAuditLogHandler(org.jboss.staxmapper.XMLExtendedStreamReader, org.jboss.dmr.ModelNode, org.jboss.as.controller.parsing.Namespace, java.util.List<org.jboss.dmr.ModelNode>) throws javax.xml.stream.XMLStreamException;
    Code:
       0: invokestatic  #34                 // Method org/jboss/as/controller/operations/common/Util.createAddOperation:()Lorg/jboss/dmr/ModelNode;
       3: astore        5
       5: aload         4
       7: aload         5
       9: invokeinterface #19,  2           // InterfaceMethod java/util/List.add:(Ljava/lang/Object;)Z
      14: pop
      15: aload_1
      16: invokeinterface #35,  1           // InterfaceMethod org/jboss/staxmapper/XMLExtendedStreamReader.getAttributeCount:()I
      21: istore        6
      23: iconst_0
      24: istore        7
      26: iload         7
      28: iload         6
      30: if_icmpge     261
      33: aload_1
      34: iload         7
      36: invokeinterface #36,  2           // InterfaceMethod org/jboss/staxmapper/XMLExtendedStreamReader.getAttributeValue:(I)Ljava/lang/String;
      41: astore        8
      43: aload_1
      44: iload         7
      46: invokestatic  #37                 // Method org/jboss/as/controller/parsing/ParseUtils.isNoNamespaceAttribute:(Lorg/jboss/staxmapper/XMLExtendedStreamReader;I)Z
      49: ifne          59
      52: aload_1
      53: iload         7
      55: invokestatic  #38                 // Method org/jboss/as/controller/parsing/ParseUtils.unexpectedAttribute:(Lorg/jboss/staxmapper/XMLExtendedStreamReader;I)Ljavax/xml/stream/XMLStreamException;
      58: athrow
      59: aload_1
      60: iload         7
      62: invokeinterface #39,  2           // InterfaceMethod org/jboss/staxmapper/XMLExtendedStreamReader.getAttributeLocalName:(I)Ljava/lang/String;
      67: invokestatic  #40                 // Method org/jboss/as/controller/parsing/Attribute.forName:(Ljava/lang/String;)Lorg/jboss/as/controller/parsing/Attribute;
      70: astore        9
      72: getstatic     #41                 // Field org/jboss/as/domain/management/parsing/AuditLogXml_4$1.$SwitchMap$org$jboss$as$controller$parsing$Attribute:[I
      75: aload         9
      77: invokevirtual #42                 // Method org/jboss/as/controller/parsing/Attribute.ordinal:()I
      80: iaload
      81: tableswitch   { // 1 to 15
                     1: 156
                     2: 248
                     3: 248
                     4: 248
                     5: 248
                     6: 248
                     7: 248
                     8: 248
                     9: 178
                    10: 192
                    11: 206
                    12: 220
                    13: 248
                    14: 248
                    15: 234
               default: 248
          }
     156: aload         5
     158: ldc           #17                 // String address
     160: invokevirtual #14                 // Method org/jboss/dmr/ModelNode.get:(Ljava/lang/String;)Lorg/jboss/dmr/ModelNode;
     163: aload_2
     164: invokevirtual #18                 // Method org/jboss/dmr/ModelNode.set:(Lorg/jboss/dmr/ModelNode;)Lorg/jboss/dmr/ModelNode;
     167: ldc           #71                 // String periodic-rotating-file-handler
     169: aload         8
     171: invokevirtual #10                 // Method org/jboss/dmr/ModelNode.add:(Ljava/lang/String;Ljava/lang/String;)Lorg/jboss/dmr/ModelNode;
     174: pop
     175: goto          255
     178: getstatic     #72                 // Field org/jboss/as/domain/management/audit/PeriodicRotatingFileAuditLogHandlerResourceDefinition.MAX_FAILURE_COUNT:Lorg/jboss/as/controller/SimpleAttributeDefinition;
     181: aload         8
     183: aload         5
     185: aload_1
     186: invokevirtual #45                 // Method org/jboss/as/controller/SimpleAttributeDefinition.parseAndSetParameter:(Ljava/lang/String;Lorg/jboss/dmr/ModelNode;Ljavax/xml/stream/XMLStreamReader;)V
     189: goto          255
     192: getstatic     #73                 // Field org/jboss/as/domain/management/audit/PeriodicRotatingFileAuditLogHandlerResourceDefinition.FORMATTER:Lorg/jboss/as/controller/SimpleAttributeDefinition;
     195: aload         8
     197: aload         5
     199: aload_1
     200: invokevirtual #45                 // Method org/jboss/as/controller/SimpleAttributeDefinition.parseAndSetParameter:(Ljava/lang/String;Lorg/jboss/dmr/ModelNode;Ljavax/xml/stream/XMLStreamReader;)V
     203: goto          255
     206: getstatic     #74                 // Field org/jboss/as/domain/management/audit/PeriodicRotatingFileAuditLogHandlerResourceDefinition.PATH:Lorg/jboss/as/controller/SimpleAttributeDefinition;
     209: aload         8
     211: aload         5
     213: aload_1
     214: invokevirtual #45                 // Method org/jboss/as/controller/SimpleAttributeDefinition.parseAndSetParameter:(Ljava/lang/String;Lorg/jboss/dmr/ModelNode;Ljavax/xml/stream/XMLStreamReader;)V
     217: goto          255
     220: getstatic     #75                 // Field org/jboss/as/domain/management/audit/PeriodicRotatingFileAuditLogHandlerResourceDefinition.RELATIVE_TO:Lorg/jboss/as/controller/SimpleAttributeDefinition;
     223: aload         8
     225: aload         5
     227: aload_1
     228: invokevirtual #45                 // Method org/jboss/as/controller/SimpleAttributeDefinition.parseAndSetParameter:(Ljava/lang/String;Lorg/jboss/dmr/ModelNode;Ljavax/xml/stream/XMLStreamReader;)V
     231: goto          255
     234: getstatic     #76                 // Field org/jboss/as/domain/management/audit/PeriodicRotatingFileAuditLogHandlerResourceDefinition.SUFFIX:Lorg/jboss/as/controller/SimpleAttributeDefinition;
     237: aload         8
     239: aload         5
     241: aload_1
     242: invokevirtual #45                 // Method org/jboss/as/controller/SimpleAttributeDefinition.parseAndSetParameter:(Ljava/lang/String;Lorg/jboss/dmr/ModelNode;Ljavax/xml/stream/XMLStreamReader;)V
     245: goto          255
     248: aload_1
     249: iload         7
     251: invokestatic  #38                 // Method org/jboss/as/controller/parsing/ParseUtils.unexpectedAttribute:(Lorg/jboss/staxmapper/XMLExtendedStreamReader;I)Ljavax/xml/stream/XMLStreamException;
     254: athrow
     255: iinc          7, 1
     258: goto          26
     261: aload_1
     262: invokestatic  #51                 // Method org/jboss/as/controller/parsing/ParseUtils.requireNoContent:(Lorg/jboss/staxmapper/XMLExtendedStreamReader;)V
     265: return

  private void parseSyslogAuditLogHandlerAttributes(org.jboss.staxmapper.XMLExtendedStreamReader, org.jboss.dmr.ModelNode, org.jboss.dmr.ModelNode) throws javax.xml.stream.XMLStreamException;
    Code:
       0: aload_1
       1: invokeinterface #35,  1           // InterfaceMethod org/jboss/staxmapper/XMLExtendedStreamReader.getAttributeCount:()I
       6: istore        4
       8: iconst_0
       9: istore        5
      11: iload         5
      13: iload         4
      15: if_icmpge     285
      18: aload_1
      19: iload         5
      21: invokeinterface #36,  2           // InterfaceMethod org/jboss/staxmapper/XMLExtendedStreamReader.getAttributeValue:(I)Ljava/lang/String;
      26: astore        6
      28: aload_1
      29: iload         5
      31: invokestatic  #37                 // Method org/jboss/as/controller/parsing/ParseUtils.isNoNamespaceAttribute:(Lorg/jboss/staxmapper/XMLExtendedStreamReader;I)Z
      34: ifne          44
      37: aload_1
      38: iload         5
      40: invokestatic  #38                 // Method org/jboss/as/controller/parsing/ParseUtils.unexpectedAttribute:(Lorg/jboss/staxmapper/XMLExtendedStreamReader;I)Ljavax/xml/stream/XMLStreamException;
      43: athrow
      44: aload_1
      45: iload         5
      47: invokeinterface #39,  2           // InterfaceMethod org/jboss/staxmapper/XMLExtendedStreamReader.getAttributeLocalName:(I)Ljava/lang/String;
      52: invokestatic  #40                 // Method org/jboss/as/controller/parsing/Attribute.forName:(Ljava/lang/String;)Lorg/jboss/as/controller/parsing/Attribute;
      55: astore        7
      57: getstatic     #41                 // Field org/jboss/as/domain/management/parsing/AuditLogXml_4$1.$SwitchMap$org$jboss$as$controller$parsing$Attribute:[I
      60: aload         7
      62: invokevirtual #42                 // Method org/jboss/as/controller/parsing/Attribute.ordinal:()I
      65: iaload
      66: tableswitch   { // 1 to 20
                     1: 160
                     2: 272
                     3: 272
                     4: 272
                     5: 272
                     6: 272
                     7: 272
                     8: 272
                     9: 181
                    10: 194
                    11: 272
                    12: 272
                    13: 272
                    14: 272
                    15: 272
                    16: 207
                    17: 220
                    18: 233
                    19: 246
                    20: 259
               default: 272
          }
     160: aload_3
     161: ldc           #17                 // String address
     163: invokevirtual #14                 // Method org/jboss/dmr/ModelNode.get:(Ljava/lang/String;)Lorg/jboss/dmr/ModelNode;
     166: aload_2
     167: invokevirtual #18                 // Method org/jboss/dmr/ModelNode.set:(Lorg/jboss/dmr/ModelNode;)Lorg/jboss/dmr/ModelNode;
     170: ldc           #77                 // String syslog-handler
     172: aload         6
     174: invokevirtual #10                 // Method org/jboss/dmr/ModelNode.add:(Ljava/lang/String;Ljava/lang/String;)Lorg/jboss/dmr/ModelNode;
     177: pop
     178: goto          279
     181: getstatic     #78                 // Field org/jboss/as/domain/management/audit/SyslogAuditLogHandlerResourceDefinition.MAX_FAILURE_COUNT:Lorg/jboss/as/controller/SimpleAttributeDefinition;
     184: aload         6
     186: aload_3
     187: aload_1
     188: invokevirtual #45                 // Method org/jboss/as/controller/SimpleAttributeDefinition.parseAndSetParameter:(Ljava/lang/String;Lorg/jboss/dmr/ModelNode;Ljavax/xml/stream/XMLStreamReader;)V
     191: goto          279
     194: getstatic     #79                 // Field org/jboss/as/domain/management/audit/SyslogAuditLogHandlerResourceDefinition.FORMATTER:Lorg/jboss/as/controller/SimpleAttributeDefinition;
     197: aload         6
     199: aload_3
     200: aload_1
     201: invokevirtual #45                 // Method org/jboss/as/controller/SimpleAttributeDefinition.parseAndSetParameter:(Ljava/lang/String;Lorg/jboss/dmr/ModelNode;Ljavax/xml/stream/XMLStreamReader;)V
     204: goto          279
     207: getstatic     #80                 // Field org/jboss/as/domain/management/audit/SyslogAuditLogHandlerResourceDefinition.MAX_LENGTH:Lorg/jboss/as/controller/SimpleAttributeDefinition;
     210: aload         6
     212: aload_3
     213: aload_1
     214: invokevirtual #45                 // Method org/jboss/as/controller/SimpleAttributeDefinition.parseAndSetParameter:(Ljava/lang/String;Lorg/jboss/dmr/ModelNode;Ljavax/xml/stream/XMLStreamReader;)V
     217: goto          279
     220: getstatic     #81                 // Field org/jboss/as/domain/management/audit/SyslogAuditLogHandlerResourceDefinition.TRUNCATE:Lorg/jboss/as/controller/SimpleAttributeDefinition;
     223: aload         6
     225: aload_3
     226: aload_1
     227: invokevirtual #45                 // Method org/jboss/as/controller/SimpleAttributeDefinition.parseAndSetParameter:(Ljava/lang/String;Lorg/jboss/dmr/ModelNode;Ljavax/xml/stream/XMLStreamReader;)V
     230: goto          279
     233: getstatic     #82                 // Field org/jboss/as/domain/management/audit/SyslogAuditLogHandlerResourceDefinition.FACILITY:Lorg/jboss/as/controller/SimpleAttributeDefinition;
     236: aload         6
     238: aload_3
     239: aload_1
     240: invokevirtual #45                 // Method org/jboss/as/controller/SimpleAttributeDefinition.parseAndSetParameter:(Ljava/lang/String;Lorg/jboss/dmr/ModelNode;Ljavax/xml/stream/XMLStreamReader;)V
     243: goto          279
     246: getstatic     #83                 // Field org/jboss/as/domain/management/audit/SyslogAuditLogHandlerResourceDefinition.APP_NAME:Lorg/jboss/as/controller/SimpleAttributeDefinition;
     249: aload         6
     251: aload_3
     252: aload_1
     253: invokevirtual #45                 // Method org/jboss/as/controller/SimpleAttributeDefinition.parseAndSetParameter:(Ljava/lang/String;Lorg/jboss/dmr/ModelNode;Ljavax/xml/stream/XMLStreamReader;)V
     256: goto          279
     259: getstatic     #84                 // Field org/jboss/as/domain/management/audit/SyslogAuditLogHandlerResourceDefinition.SYSLOG_FORMAT:Lorg/jboss/as/controller/SimpleAttributeDefinition;
     262: aload         6
     264: aload_3
     265: aload_1
     266: invokevirtual #45                 // Method org/jboss/as/controller/SimpleAttributeDefinition.parseAndSetParameter:(Ljava/lang/String;Lorg/jboss/dmr/ModelNode;Ljavax/xml/stream/XMLStreamReader;)V
     269: goto          279
     272: aload_1
     273: iload         5
     275: invokestatic  #38                 // Method org/jboss/as/controller/parsing/ParseUtils.unexpectedAttribute:(Lorg/jboss/staxmapper/XMLExtendedStreamReader;I)Ljavax/xml/stream/XMLStreamException;
     278: athrow
     279: iinc          5, 1
     282: goto          11
     285: return

  private void parseSyslogAuditLogHandler(org.jboss.staxmapper.XMLExtendedStreamReader, org.jboss.dmr.ModelNode, org.jboss.as.controller.parsing.Namespace, java.util.List<org.jboss.dmr.ModelNode>) throws javax.xml.stream.XMLStreamException;
    Code:
       0: invokestatic  #34                 // Method org/jboss/as/controller/operations/common/Util.createAddOperation:()Lorg/jboss/dmr/ModelNode;
       3: astore        5
       5: aload         4
       7: aload         5
       9: invokeinterface #19,  2           // InterfaceMethod java/util/List.add:(Ljava/lang/Object;)Z
      14: pop
      15: aload_0
      16: aload_1
      17: aload_2
      18: aload         5
      20: invokespecial #85                 // Method parseSyslogAuditLogHandlerAttributes:(Lorg/jboss/staxmapper/XMLExtendedStreamReader;Lorg/jboss/dmr/ModelNode;Lorg/jboss/dmr/ModelNode;)V
      23: aload         5
      25: ldc           #17                 // String address
      27: invokevirtual #14                 // Method org/jboss/dmr/ModelNode.get:(Ljava/lang/String;)Lorg/jboss/dmr/ModelNode;
      30: invokevirtual #86                 // Method org/jboss/dmr/ModelNode.isDefined:()Z
      33: ifne          47
      36: aload_1
      37: getstatic     #87                 // Field org/jboss/as/controller/parsing/Attribute.NAME:Lorg/jboss/as/controller/parsing/Attribute;
      40: invokestatic  #88                 // Method java/util/Collections.singleton:(Ljava/lang/Object;)Ljava/util/Set;
      43: invokestatic  #89                 // Method org/jboss/as/controller/parsing/ParseUtils.missingRequired:(Lorg/jboss/staxmapper/XMLExtendedStreamReader;Ljava/util/Set;)Ljavax/xml/stream/XMLStreamException;
      46: athrow
      47: iconst_0
      48: istore        6
      50: aload_1
      51: invokeinterface #21,  1           // InterfaceMethod org/jboss/staxmapper/XMLExtendedStreamReader.hasNext:()Z
      56: ifeq          172
      59: aload_1
      60: invokeinterface #22,  1           // InterfaceMethod org/jboss/staxmapper/XMLExtendedStreamReader.nextTag:()I
      65: iconst_2
      66: if_icmpeq     172
      69: aload_1
      70: aload_3
      71: invokestatic  #5                  // Method org/jboss/as/controller/parsing/ParseUtils.requireNamespace:(Lorg/jboss/staxmapper/XMLExtendedStreamReader;Lorg/jboss/as/controller/parsing/Namespace;)V
      74: aload_1
      75: invokeinterface #23,  1           // InterfaceMethod org/jboss/staxmapper/XMLExtendedStreamReader.getLocalName:()Ljava/lang/String;
      80: invokestatic  #24                 // Method org/jboss/as/controller/parsing/Element.forName:(Ljava/lang/String;)Lorg/jboss/as/controller/parsing/Element;
      83: astore        7
      85: iload         6
      87: ifeq          105
      90: getstatic     #90                 // Field org/jboss/as/domain/management/logging/DomainManagementLogger.ROOT_LOGGER:Lorg/jboss/as/domain/management/logging/DomainManagementLogger;
      93: aload_1
      94: invokeinterface #91,  1           // InterfaceMethod org/jboss/staxmapper/XMLExtendedStreamReader.getLocation:()Ljavax/xml/stream/Location;
      99: invokeinterface #92,  2           // InterfaceMethod org/jboss/as/domain/management/logging/DomainManagementLogger.onlyOneSyslogHandlerProtocol:(Ljavax/xml/stream/Location;)Ljavax/xml/stream/XMLStreamException;
     104: athrow
     105: iconst_1
     106: istore        6
     108: getstatic     #25                 // Field org/jboss/as/domain/management/parsing/AuditLogXml_4$1.$SwitchMap$org$jboss$as$controller$parsing$Element:[I
     111: aload         7
     113: invokevirtual #26                 // Method org/jboss/as/controller/parsing/Element.ordinal:()I
     116: iaload
     117: tableswitch   { // 11 to 13
                    11: 144
                    12: 144
                    13: 144
               default: 164
          }
     144: aload_0
     145: aload_1
     146: aload         5
     148: ldc           #17                 // String address
     150: invokevirtual #14                 // Method org/jboss/dmr/ModelNode.get:(Ljava/lang/String;)Lorg/jboss/dmr/ModelNode;
     153: aload_3
     154: aload         4
     156: aload         7
     158: invokespecial #93                 // Method parseSyslogAuditLogHandlerProtocol:(Lorg/jboss/staxmapper/XMLExtendedStreamReader;Lorg/jboss/dmr/ModelNode;Lorg/jboss/as/controller/parsing/Namespace;Ljava/util/List;Lorg/jboss/as/controller/parsing/Element;)V
     161: goto          169
     164: aload_1
     165: invokestatic  #32                 // Method org/jboss/as/controller/parsing/ParseUtils.unexpectedElement:(Lorg/jboss/staxmapper/XMLExtendedStreamReader;)Ljavax/xml/stream/XMLStreamException;
     168: athrow
     169: goto          50
     172: return

  private void parseSyslogAuditLogHandlerProtocol(org.jboss.staxmapper.XMLExtendedStreamReader, org.jboss.dmr.ModelNode, org.jboss.as.controller.parsing.Namespace, java.util.List<org.jboss.dmr.ModelNode>, org.jboss.as.controller.parsing.Element) throws javax.xml.stream.XMLStreamException;
    Code:
       0: aload_2
       1: invokevirtual #6                  // Method org/jboss/dmr/ModelNode.clone:()Lorg/jboss/dmr/ModelNode;
       4: ldc           #94                 // String protocol
       6: aload         5
       8: invokevirtual #95                 // Method org/jboss/as/controller/parsing/Element.getLocalName:()Ljava/lang/String;
      11: invokevirtual #10                 // Method org/jboss/dmr/ModelNode.add:(Ljava/lang/String;Ljava/lang/String;)Lorg/jboss/dmr/ModelNode;
      14: invokestatic  #96                 // Method org/jboss/as/controller/PathAddress.pathAddress:(Lorg/jboss/dmr/ModelNode;)Lorg/jboss/as/controller/PathAddress;
      17: astore        6
      19: aload         6
      21: invokestatic  #97                 // Method org/jboss/as/controller/operations/common/Util.createAddOperation:(Lorg/jboss/as/controller/PathAddress;)Lorg/jboss/dmr/ModelNode;
      24: astore        7
      26: aload         4
      28: aload         7
      30: invokeinterface #19,  2           // InterfaceMethod java/util/List.add:(Ljava/lang/Object;)Z
      35: pop
      36: aload_1
      37: invokeinterface #35,  1           // InterfaceMethod org/jboss/staxmapper/XMLExtendedStreamReader.getAttributeCount:()I
      42: istore        8
      44: iconst_0
      45: istore        9
      47: iload         9
      49: iload         8
      51: if_icmpge     217
      54: aload_1
      55: iload         9
      57: invokeinterface #36,  2           // InterfaceMethod org/jboss/staxmapper/XMLExtendedStreamReader.getAttributeValue:(I)Ljava/lang/String;
      62: astore        10
      64: aload_1
      65: iload         9
      67: invokestatic  #37                 // Method org/jboss/as/controller/parsing/ParseUtils.isNoNamespaceAttribute:(Lorg/jboss/staxmapper/XMLExtendedStreamReader;I)Z
      70: ifne          80
      73: aload_1
      74: iload         9
      76: invokestatic  #38                 // Method org/jboss/as/controller/parsing/ParseUtils.unexpectedAttribute:(Lorg/jboss/staxmapper/XMLExtendedStreamReader;I)Ljavax/xml/stream/XMLStreamException;
      79: athrow
      80: aload_1
      81: iload         9
      83: invokeinterface #39,  2           // InterfaceMethod org/jboss/staxmapper/XMLExtendedStreamReader.getAttributeLocalName:(I)Ljava/lang/String;
      88: invokestatic  #40                 // Method org/jboss/as/controller/parsing/Attribute.forName:(Ljava/lang/String;)Lorg/jboss/as/controller/parsing/Attribute;
      91: astore        11
      93: getstatic     #41                 // Field org/jboss/as/domain/management/parsing/AuditLogXml_4$1.$SwitchMap$org$jboss$as$controller$parsing$Attribute:[I
      96: aload         11
      98: invokevirtual #42                 // Method org/jboss/as/controller/parsing/Attribute.ordinal:()I
     101: iaload
     102: tableswitch   { // 21 to 24
                    21: 132
                    22: 146
                    23: 160
                    24: 182
               default: 204
          }
     132: getstatic     #98                 // Field org/jboss/as/domain/management/audit/SyslogAuditLogProtocolResourceDefinition$Udp.HOST:Lorg/jboss/as/controller/SimpleAttributeDefinition;
     135: aload         10
     137: aload         7
     139: aload_1
     140: invokevirtual #45                 // Method org/jboss/as/controller/SimpleAttributeDefinition.parseAndSetParameter:(Ljava/lang/String;Lorg/jboss/dmr/ModelNode;Ljavax/xml/stream/XMLStreamReader;)V
     143: goto          211
     146: getstatic     #99                 // Field org/jboss/as/domain/management/audit/SyslogAuditLogProtocolResourceDefinition$Udp.PORT:Lorg/jboss/as/controller/SimpleAttributeDefinition;
     149: aload         10
     151: aload         7
     153: aload_1
     154: invokevirtual #45                 // Method org/jboss/as/controller/SimpleAttributeDefinition.parseAndSetParameter:(Ljava/lang/String;Lorg/jboss/dmr/ModelNode;Ljavax/xml/stream/XMLStreamReader;)V
     157: goto          211
     160: aload         5
     162: getstatic     #100                // Field org/jboss/as/controller/parsing/Element.UDP:Lorg/jboss/as/controller/parsing/Element;
     165: if_acmpeq     182
     168: getstatic     #101                // Field org/jboss/as/domain/management/audit/SyslogAuditLogProtocolResourceDefinition$Tcp.MESSAGE_TRANSFER:Lorg/jboss/as/controller/SimpleAttributeDefinition;
     171: aload         10
     173: aload         7
     175: aload_1
     176: invokevirtual #45                 // Method org/jboss/as/controller/SimpleAttributeDefinition.parseAndSetParameter:(Ljava/lang/String;Lorg/jboss/dmr/ModelNode;Ljavax/xml/stream/XMLStreamReader;)V
     179: goto          211
     182: aload         5
     184: getstatic     #100                // Field org/jboss/as/controller/parsing/Element.UDP:Lorg/jboss/as/controller/parsing/Element;
     187: if_acmpeq     204
     190: getstatic     #102                // Field org/jboss/as/domain/management/audit/SyslogAuditLogProtocolResourceDefinition$Tcp.RECONNECT_TIMEOUT:Lorg/jboss/as/controller/SimpleAttributeDefinition;
     193: aload         10
     195: aload         7
     197: aload_1
     198: invokevirtual #45                 // Method org/jboss/as/controller/SimpleAttributeDefinition.parseAndSetParameter:(Ljava/lang/String;Lorg/jboss/dmr/ModelNode;Ljavax/xml/stream/XMLStreamReader;)V
     201: goto          211
     204: aload_1
     205: iload         9
     207: invokestatic  #38                 // Method org/jboss/as/controller/parsing/ParseUtils.unexpectedAttribute:(Lorg/jboss/staxmapper/XMLExtendedStreamReader;I)Ljavax/xml/stream/XMLStreamException;
     210: athrow
     211: iinc          9, 1
     214: goto          47
     217: aload         5
     219: getstatic     #103                // Field org/jboss/as/controller/parsing/Element.TLS:Lorg/jboss/as/controller/parsing/Element;
     222: if_acmpeq     232
     225: aload_1
     226: invokestatic  #51                 // Method org/jboss/as/controller/parsing/ParseUtils.requireNoContent:(Lorg/jboss/staxmapper/XMLExtendedStreamReader;)V
     229: goto          388
     232: iconst_0
     233: istore        9
     235: iconst_0
     236: istore        10
     238: aload_1
     239: invokeinterface #21,  1           // InterfaceMethod org/jboss/staxmapper/XMLExtendedStreamReader.hasNext:()Z
     244: ifeq          388
     247: aload_1
     248: invokeinterface #22,  1           // InterfaceMethod org/jboss/staxmapper/XMLExtendedStreamReader.nextTag:()I
     253: iconst_2
     254: if_icmpeq     388
     257: aload_1
     258: aload_3
     259: invokestatic  #5                  // Method org/jboss/as/controller/parsing/ParseUtils.requireNamespace:(Lorg/jboss/staxmapper/XMLExtendedStreamReader;Lorg/jboss/as/controller/parsing/Namespace;)V
     262: aload_1
     263: invokeinterface #23,  1           // InterfaceMethod org/jboss/staxmapper/XMLExtendedStreamReader.getLocalName:()Ljava/lang/String;
     268: invokestatic  #24                 // Method org/jboss/as/controller/parsing/Element.forName:(Ljava/lang/String;)Lorg/jboss/as/controller/parsing/Element;
     271: astore        11
     273: getstatic     #25                 // Field org/jboss/as/domain/management/parsing/AuditLogXml_4$1.$SwitchMap$org$jboss$as$controller$parsing$Element:[I
     276: aload         11
     278: invokevirtual #26                 // Method org/jboss/as/controller/parsing/Element.ordinal:()I
     281: iaload
     282: lookupswitch  { // 2
                    14: 308
                    15: 344
               default: 380
          }
     308: iload         9
     310: ifeq          324
     313: aload_1
     314: getstatic     #104                // Field org/jboss/as/controller/parsing/Element.TRUSTSTORE:Lorg/jboss/as/controller/parsing/Element;
     317: invokevirtual #95                 // Method org/jboss/as/controller/parsing/Element.getLocalName:()Ljava/lang/String;
     320: invokestatic  #105                // Method org/jboss/as/controller/parsing/ParseUtils.duplicateNamedElement:(Lorg/jboss/staxmapper/XMLExtendedStreamReader;Ljava/lang/String;)Ljavax/xml/stream/XMLStreamException;
     323: athrow
     324: iconst_1
     325: istore        9
     327: aload_0
     328: aload_1
     329: aload         6
     331: aload_3
     332: aload         4
     334: getstatic     #106                // Field org/jboss/as/domain/management/audit/SyslogAuditLogProtocolResourceDefinition$TlsKeyStore.TRUSTSTORE_ELEMENT:Lorg/jboss/as/controller/PathElement;
     337: iconst_0
     338: invokespecial #107                // Method parseSyslogTlsKeystore:(Lorg/jboss/staxmapper/XMLExtendedStreamReader;Lorg/jboss/as/controller/PathAddress;Lorg/jboss/as/controller/parsing/Namespace;Ljava/util/List;Lorg/jboss/as/controller/PathElement;Z)V
     341: goto          385
     344: iload         10
     346: ifeq          360
     349: aload_1
     350: getstatic     #108                // Field org/jboss/as/controller/parsing/Element.CLIENT_CERT_STORE:Lorg/jboss/as/controller/parsing/Element;
     353: invokevirtual #95                 // Method org/jboss/as/controller/parsing/Element.getLocalName:()Ljava/lang/String;
     356: invokestatic  #105                // Method org/jboss/as/controller/parsing/ParseUtils.duplicateNamedElement:(Lorg/jboss/staxmapper/XMLExtendedStreamReader;Ljava/lang/String;)Ljavax/xml/stream/XMLStreamException;
     359: athrow
     360: iconst_1
     361: istore        10
     363: aload_0
     364: aload_1
     365: aload         6
     367: aload_3
     368: aload         4
     370: getstatic     #109                // Field org/jboss/as/domain/management/audit/SyslogAuditLogProtocolResourceDefinition$TlsKeyStore.CLIENT_CERT_ELEMENT:Lorg/jboss/as/controller/PathElement;
     373: iconst_1
     374: invokespecial #107                // Method parseSyslogTlsKeystore:(Lorg/jboss/staxmapper/XMLExtendedStreamReader;Lorg/jboss/as/controller/PathAddress;Lorg/jboss/as/controller/parsing/Namespace;Ljava/util/List;Lorg/jboss/as/controller/PathElement;Z)V
     377: goto          385
     380: aload_1
     381: invokestatic  #32                 // Method org/jboss/as/controller/parsing/ParseUtils.unexpectedElement:(Lorg/jboss/staxmapper/XMLExtendedStreamReader;)Ljavax/xml/stream/XMLStreamException;
     384: athrow
     385: goto          238
     388: return

  private void parseSyslogTlsKeystore(org.jboss.staxmapper.XMLExtendedStreamReader, org.jboss.as.controller.PathAddress, org.jboss.as.controller.parsing.Namespace, java.util.List<org.jboss.dmr.ModelNode>, org.jboss.as.controller.PathElement, boolean) throws javax.xml.stream.XMLStreamException;
    Code:
       0: aload_2
       1: iconst_1
       2: anewarray     #110                // class org/jboss/as/controller/PathElement
       5: dup
       6: iconst_0
       7: aload         5
       9: aastore
      10: invokevirtual #111                // Method org/jboss/as/controller/PathAddress.append:([Lorg/jboss/as/controller/PathElement;)Lorg/jboss/as/controller/PathAddress;
      13: invokestatic  #97                 // Method org/jboss/as/controller/operations/common/Util.createAddOperation:(Lorg/jboss/as/controller/PathAddress;)Lorg/jboss/dmr/ModelNode;
      16: astore        7
      18: aload         4
      20: aload         7
      22: invokeinterface #19,  2           // InterfaceMethod java/util/List.add:(Ljava/lang/Object;)Z
      27: pop
      28: aload_1
      29: invokeinterface #35,  1           // InterfaceMethod org/jboss/staxmapper/XMLExtendedStreamReader.getAttributeCount:()I
      34: istore        8
      36: iconst_0
      37: istore        9
      39: iload         9
      41: iload         8
      43: if_icmpge     210
      46: aload_1
      47: iload         9
      49: invokeinterface #36,  2           // InterfaceMethod org/jboss/staxmapper/XMLExtendedStreamReader.getAttributeValue:(I)Ljava/lang/String;
      54: astore        10
      56: aload_1
      57: iload         9
      59: invokestatic  #37                 // Method org/jboss/as/controller/parsing/ParseUtils.isNoNamespaceAttribute:(Lorg/jboss/staxmapper/XMLExtendedStreamReader;I)Z
      62: ifne          72
      65: aload_1
      66: iload         9
      68: invokestatic  #38                 // Method org/jboss/as/controller/parsing/ParseUtils.unexpectedAttribute:(Lorg/jboss/staxmapper/XMLExtendedStreamReader;I)Ljavax/xml/stream/XMLStreamException;
      71: athrow
      72: aload_1
      73: iload         9
      75: invokeinterface #39,  2           // InterfaceMethod org/jboss/staxmapper/XMLExtendedStreamReader.getAttributeLocalName:(I)Ljava/lang/String;
      80: invokestatic  #40                 // Method org/jboss/as/controller/parsing/Attribute.forName:(Ljava/lang/String;)Lorg/jboss/as/controller/parsing/Attribute;
      83: astore        11
      85: getstatic     #41                 // Field org/jboss/as/domain/management/parsing/AuditLogXml_4$1.$SwitchMap$org$jboss$as$controller$parsing$Attribute:[I
      88: aload         11
      90: invokevirtual #42                 // Method org/jboss/as/controller/parsing/Attribute.ordinal:()I
      93: iaload
      94: lookupswitch  { // 4
                    11: 150
                    12: 164
                    25: 136
                    26: 178
               default: 197
          }
     136: getstatic     #112                // Field org/jboss/as/domain/management/audit/SyslogAuditLogProtocolResourceDefinition$TlsKeyStore.KEYSTORE_PASSWORD:Lorg/jboss/as/controller/SimpleAttributeDefinition;
     139: aload         10
     141: aload         7
     143: aload_1
     144: invokevirtual #45                 // Method org/jboss/as/controller/SimpleAttributeDefinition.parseAndSetParameter:(Ljava/lang/String;Lorg/jboss/dmr/ModelNode;Ljavax/xml/stream/XMLStreamReader;)V
     147: goto          204
     150: getstatic     #113                // Field org/jboss/as/domain/management/audit/SyslogAuditLogProtocolResourceDefinition$TlsKeyStore.KEYSTORE_PATH:Lorg/jboss/as/controller/SimpleAttributeDefinition;
     153: aload         10
     155: aload         7
     157: aload_1
     158: invokevirtual #45                 // Method org/jboss/as/controller/SimpleAttributeDefinition.parseAndSetParameter:(Ljava/lang/String;Lorg/jboss/dmr/ModelNode;Ljavax/xml/stream/XMLStreamReader;)V
     161: goto          204
     164: getstatic     #114                // Field org/jboss/as/domain/management/audit/SyslogAuditLogProtocolResourceDefinition$TlsKeyStore.KEYSTORE_RELATIVE_TO:Lorg/jboss/as/controller/SimpleAttributeDefinition;
     167: aload         10
     169: aload         7
     171: aload_1
     172: invokevirtual #45                 // Method org/jboss/as/controller/SimpleAttributeDefinition.parseAndSetParameter:(Ljava/lang/String;Lorg/jboss/dmr/ModelNode;Ljavax/xml/stream/XMLStreamReader;)V
     175: goto          204
     178: iload         6
     180: ifeq          197
     183: getstatic     #115                // Field org/jboss/as/domain/management/audit/SyslogAuditLogProtocolResourceDefinition$TlsKeyStore.KEY_PASSWORD:Lorg/jboss/as/controller/SimpleAttributeDefinition;
     186: aload         10
     188: aload         7
     190: aload_1
     191: invokevirtual #45                 // Method org/jboss/as/controller/SimpleAttributeDefinition.parseAndSetParameter:(Ljava/lang/String;Lorg/jboss/dmr/ModelNode;Ljavax/xml/stream/XMLStreamReader;)V
     194: goto          204
     197: aload_1
     198: iload         9
     200: invokestatic  #38                 // Method org/jboss/as/controller/parsing/ParseUtils.unexpectedAttribute:(Lorg/jboss/staxmapper/XMLExtendedStreamReader;I)Ljavax/xml/stream/XMLStreamException;
     203: athrow
     204: iinc          9, 1
     207: goto          39
     210: aload_1
     211: invokestatic  #51                 // Method org/jboss/as/controller/parsing/ParseUtils.requireNoContent:(Lorg/jboss/staxmapper/XMLExtendedStreamReader;)V
     214: return

  private void parseAuditLogConfig(org.jboss.staxmapper.XMLExtendedStreamReader, org.jboss.dmr.ModelNode, org.jboss.as.controller.parsing.Namespace, org.jboss.as.controller.PathElement, java.util.List<org.jboss.dmr.ModelNode>) throws javax.xml.stream.XMLStreamException;
    Code:
       0: aload_1
       1: aload_3
       2: invokestatic  #5                  // Method org/jboss/as/controller/parsing/ParseUtils.requireNamespace:(Lorg/jboss/staxmapper/XMLExtendedStreamReader;Lorg/jboss/as/controller/parsing/Namespace;)V
       5: aload_2
       6: invokevirtual #6                  // Method org/jboss/dmr/ModelNode.clone:()Lorg/jboss/dmr/ModelNode;
       9: aload         4
      11: invokevirtual #8                  // Method org/jboss/as/controller/PathElement.getKey:()Ljava/lang/String;
      14: aload         4
      16: invokevirtual #9                  // Method org/jboss/as/controller/PathElement.getValue:()Ljava/lang/String;
      19: invokevirtual #10                 // Method org/jboss/dmr/ModelNode.add:(Ljava/lang/String;Ljava/lang/String;)Lorg/jboss/dmr/ModelNode;
      22: astore        6
      24: new           #11                 // class org/jboss/dmr/ModelNode
      27: dup
      28: invokespecial #12                 // Method org/jboss/dmr/ModelNode."<init>":()V
      31: astore        7
      33: aload         7
      35: ldc           #13                 // String operation
      37: invokevirtual #14                 // Method org/jboss/dmr/ModelNode.get:(Ljava/lang/String;)Lorg/jboss/dmr/ModelNode;
      40: ldc           #15                 // String add
      42: invokevirtual #16                 // Method org/jboss/dmr/ModelNode.set:(Ljava/lang/String;)Lorg/jboss/dmr/ModelNode;
      45: pop
      46: aload         7
      48: ldc           #17                 // String address
      50: invokevirtual #14                 // Method org/jboss/dmr/ModelNode.get:(Ljava/lang/String;)Lorg/jboss/dmr/ModelNode;
      53: aload         6
      55: invokevirtual #18                 // Method org/jboss/dmr/ModelNode.set:(Lorg/jboss/dmr/ModelNode;)Lorg/jboss/dmr/ModelNode;
      58: pop
      59: aload         5
      61: aload         7
      63: invokeinterface #19,  2           // InterfaceMethod java/util/List.add:(Ljava/lang/Object;)Z
      68: pop
      69: aload_1
      70: invokeinterface #35,  1           // InterfaceMethod org/jboss/staxmapper/XMLExtendedStreamReader.getAttributeCount:()I
      75: istore        8
      77: iconst_0
      78: istore        9
      80: iload         9
      82: iload         8
      84: if_icmpge     215
      87: aload_1
      88: iload         9
      90: invokeinterface #36,  2           // InterfaceMethod org/jboss/staxmapper/XMLExtendedStreamReader.getAttributeValue:(I)Ljava/lang/String;
      95: astore        10
      97: aload_1
      98: iload         9
     100: invokestatic  #37                 // Method org/jboss/as/controller/parsing/ParseUtils.isNoNamespaceAttribute:(Lorg/jboss/staxmapper/XMLExtendedStreamReader;I)Z
     103: ifne          113
     106: aload_1
     107: iload         9
     109: invokestatic  #38                 // Method org/jboss/as/controller/parsing/ParseUtils.unexpectedAttribute:(Lorg/jboss/staxmapper/XMLExtendedStreamReader;I)Ljavax/xml/stream/XMLStreamException;
     112: athrow
     113: aload_1
     114: iload         9
     116: invokeinterface #39,  2           // InterfaceMethod org/jboss/staxmapper/XMLExtendedStreamReader.getAttributeLocalName:(I)Ljava/lang/String;
     121: invokestatic  #40                 // Method org/jboss/as/controller/parsing/Attribute.forName:(Ljava/lang/String;)Lorg/jboss/as/controller/parsing/Attribute;
     124: astore        11
     126: getstatic     #41                 // Field org/jboss/as/domain/management/parsing/AuditLogXml_4$1.$SwitchMap$org$jboss$as$controller$parsing$Attribute:[I
     129: aload         11
     131: invokevirtual #42                 // Method org/jboss/as/controller/parsing/Attribute.ordinal:()I
     134: iaload
     135: tableswitch   { // 27 to 29
                    27: 160
                    28: 174
                    29: 188
               default: 202
          }
     160: getstatic     #116                // Field org/jboss/as/domain/management/audit/AuditLogLoggerResourceDefinition.LOG_READ_ONLY:Lorg/jboss/as/controller/SimpleAttributeDefinition;
     163: aload         10
     165: aload         7
     167: aload_1
     168: invokevirtual #45                 // Method org/jboss/as/controller/SimpleAttributeDefinition.parseAndSetParameter:(Ljava/lang/String;Lorg/jboss/dmr/ModelNode;Ljavax/xml/stream/XMLStreamReader;)V
     171: goto          209
     174: getstatic     #117                // Field org/jboss/as/domain/management/audit/AuditLogLoggerResourceDefinition.LOG_BOOT:Lorg/jboss/as/controller/SimpleAttributeDefinition;
     177: aload         10
     179: aload         7
     181: aload_1
     182: invokevirtual #45                 // Method org/jboss/as/controller/SimpleAttributeDefinition.parseAndSetParameter:(Ljava/lang/String;Lorg/jboss/dmr/ModelNode;Ljavax/xml/stream/XMLStreamReader;)V
     185: goto          209
     188: getstatic     #118                // Field org/jboss/as/domain/management/audit/AuditLogLoggerResourceDefinition.ENABLED:Lorg/jboss/as/controller/SimpleAttributeDefinition;
     191: aload         10
     193: aload         7
     195: aload_1
     196: invokevirtual #45                 // Method org/jboss/as/controller/SimpleAttributeDefinition.parseAndSetParameter:(Ljava/lang/String;Lorg/jboss/dmr/ModelNode;Ljavax/xml/stream/XMLStreamReader;)V
     199: goto          209
     202: aload_1
     203: iload         9
     205: invokestatic  #38                 // Method org/jboss/as/controller/parsing/ParseUtils.unexpectedAttribute:(Lorg/jboss/staxmapper/XMLExtendedStreamReader;I)Ljavax/xml/stream/XMLStreamException;
     208: athrow
     209: iinc          9, 1
     212: goto          80
     215: aload_1
     216: invokeinterface #21,  1           // InterfaceMethod org/jboss/staxmapper/XMLExtendedStreamReader.hasNext:()Z
     221: ifeq          297
     224: aload_1
     225: invokeinterface #22,  1           // InterfaceMethod org/jboss/staxmapper/XMLExtendedStreamReader.nextTag:()I
     230: iconst_2
     231: if_icmpeq     297
     234: aload_1
     235: aload_3
     236: invokestatic  #5                  // Method org/jboss/as/controller/parsing/ParseUtils.requireNamespace:(Lorg/jboss/staxmapper/XMLExtendedStreamReader;Lorg/jboss/as/controller/parsing/Namespace;)V
     239: aload_1
     240: invokeinterface #23,  1           // InterfaceMethod org/jboss/staxmapper/XMLExtendedStreamReader.getLocalName:()Ljava/lang/String;
     245: invokestatic  #24                 // Method org/jboss/as/controller/parsing/Element.forName:(Ljava/lang/String;)Lorg/jboss/as/controller/parsing/Element;
     248: astore        9
     250: getstatic     #25                 // Field org/jboss/as/domain/management/parsing/AuditLogXml_4$1.$SwitchMap$org$jboss$as$controller$parsing$Element:[I
     253: aload         9
     255: invokevirtual #26                 // Method org/jboss/as/controller/parsing/Element.ordinal:()I
     258: iaload
     259: lookupswitch  { // 1
                     2: 276
               default: 289
          }
     276: aload_0
     277: aload_1
     278: aload         6
     280: aload_3
     281: aload         5
     283: invokespecial #119                // Method parseAuditLogHandlersReference:(Lorg/jboss/staxmapper/XMLExtendedStreamReader;Lorg/jboss/dmr/ModelNode;Lorg/jboss/as/controller/parsing/Namespace;Ljava/util/List;)V
     286: goto          294
     289: aload_1
     290: invokestatic  #32                 // Method org/jboss/as/controller/parsing/ParseUtils.unexpectedElement:(Lorg/jboss/staxmapper/XMLExtendedStreamReader;)Ljavax/xml/stream/XMLStreamException;
     293: athrow
     294: goto          215
     297: return

  private void parseAuditLogHandlersReference(org.jboss.staxmapper.XMLExtendedStreamReader, org.jboss.dmr.ModelNode, org.jboss.as.controller.parsing.Namespace, java.util.List<org.jboss.dmr.ModelNode>) throws javax.xml.stream.XMLStreamException;
    Code:
       0: aload_1
       1: aload_3
       2: invokestatic  #5                  // Method org/jboss/as/controller/parsing/ParseUtils.requireNamespace:(Lorg/jboss/staxmapper/XMLExtendedStreamReader;Lorg/jboss/as/controller/parsing/Namespace;)V
       5: aload_1
       6: invokeinterface #21,  1           // InterfaceMethod org/jboss/staxmapper/XMLExtendedStreamReader.hasNext:()Z
      11: ifeq          238
      14: aload_1
      15: invokeinterface #22,  1           // InterfaceMethod org/jboss/staxmapper/XMLExtendedStreamReader.nextTag:()I
      20: iconst_2
      21: if_icmpeq     238
      24: aload_1
      25: aload_3
      26: invokestatic  #5                  // Method org/jboss/as/controller/parsing/ParseUtils.requireNamespace:(Lorg/jboss/staxmapper/XMLExtendedStreamReader;Lorg/jboss/as/controller/parsing/Namespace;)V
      29: aload_1
      30: invokeinterface #23,  1           // InterfaceMethod org/jboss/staxmapper/XMLExtendedStreamReader.getLocalName:()Ljava/lang/String;
      35: invokestatic  #24                 // Method org/jboss/as/controller/parsing/Element.forName:(Ljava/lang/String;)Lorg/jboss/as/controller/parsing/Element;
      38: astore        5
      40: getstatic     #25                 // Field org/jboss/as/domain/management/parsing/AuditLogXml_4$1.$SwitchMap$org$jboss$as$controller$parsing$Element:[I
      43: aload         5
      45: invokevirtual #26                 // Method org/jboss/as/controller/parsing/Element.ordinal:()I
      48: iaload
      49: lookupswitch  { // 1
                    16: 68
               default: 230
          }
      68: aload_1
      69: aload_3
      70: invokestatic  #5                  // Method org/jboss/as/controller/parsing/ParseUtils.requireNamespace:(Lorg/jboss/staxmapper/XMLExtendedStreamReader;Lorg/jboss/as/controller/parsing/Namespace;)V
      73: new           #11                 // class org/jboss/dmr/ModelNode
      76: dup
      77: invokespecial #12                 // Method org/jboss/dmr/ModelNode."<init>":()V
      80: astore        6
      82: aload         6
      84: ldc           #13                 // String operation
      86: invokevirtual #14                 // Method org/jboss/dmr/ModelNode.get:(Ljava/lang/String;)Lorg/jboss/dmr/ModelNode;
      89: ldc           #15                 // String add
      91: invokevirtual #16                 // Method org/jboss/dmr/ModelNode.set:(Ljava/lang/String;)Lorg/jboss/dmr/ModelNode;
      94: pop
      95: aload         4
      97: aload         6
      99: invokeinterface #19,  2           // InterfaceMethod java/util/List.add:(Ljava/lang/Object;)Z
     104: pop
     105: aload_1
     106: invokeinterface #35,  1           // InterfaceMethod org/jboss/staxmapper/XMLExtendedStreamReader.getAttributeCount:()I
     111: istore        7
     113: iconst_0
     114: istore        8
     116: iload         8
     118: iload         7
     120: if_icmpge     227
     123: aload_1
     124: iload         8
     126: invokeinterface #36,  2           // InterfaceMethod org/jboss/staxmapper/XMLExtendedStreamReader.getAttributeValue:(I)Ljava/lang/String;
     131: astore        9
     133: aload_1
     134: iload         8
     136: invokestatic  #37                 // Method org/jboss/as/controller/parsing/ParseUtils.isNoNamespaceAttribute:(Lorg/jboss/staxmapper/XMLExtendedStreamReader;I)Z
     139: ifne          149
     142: aload_1
     143: iload         8
     145: invokestatic  #38                 // Method org/jboss/as/controller/parsing/ParseUtils.unexpectedAttribute:(Lorg/jboss/staxmapper/XMLExtendedStreamReader;I)Ljavax/xml/stream/XMLStreamException;
     148: athrow
     149: aload_1
     150: iload         8
     152: invokeinterface #39,  2           // InterfaceMethod org/jboss/staxmapper/XMLExtendedStreamReader.getAttributeLocalName:(I)Ljava/lang/String;
     157: invokestatic  #40                 // Method org/jboss/as/controller/parsing/Attribute.forName:(Ljava/lang/String;)Lorg/jboss/as/controller/parsing/Attribute;
     160: astore        10
     162: getstatic     #41                 // Field org/jboss/as/domain/management/parsing/AuditLogXml_4$1.$SwitchMap$org$jboss$as$controller$parsing$Attribute:[I
     165: aload         10
     167: invokevirtual #42                 // Method org/jboss/as/controller/parsing/Attribute.ordinal:()I
     170: iaload
     171: lookupswitch  { // 1
                     1: 188
               default: 210
          }
     188: aload         6
     190: ldc           #17                 // String address
     192: invokevirtual #14                 // Method org/jboss/dmr/ModelNode.get:(Ljava/lang/String;)Lorg/jboss/dmr/ModelNode;
     195: aload_2
     196: invokevirtual #18                 // Method org/jboss/dmr/ModelNode.set:(Lorg/jboss/dmr/ModelNode;)Lorg/jboss/dmr/ModelNode;
     199: ldc           #120                // String handler
     201: aload         9
     203: invokevirtual #10                 // Method org/jboss/dmr/ModelNode.add:(Ljava/lang/String;Ljava/lang/String;)Lorg/jboss/dmr/ModelNode;
     206: pop
     207: goto          217
     210: aload_1
     211: iload         8
     213: invokestatic  #38                 // Method org/jboss/as/controller/parsing/ParseUtils.unexpectedAttribute:(Lorg/jboss/staxmapper/XMLExtendedStreamReader;I)Ljavax/xml/stream/XMLStreamException;
     216: athrow
     217: aload_1
     218: invokestatic  #51                 // Method org/jboss/as/controller/parsing/ParseUtils.requireNoContent:(Lorg/jboss/staxmapper/XMLExtendedStreamReader;)V
     221: iinc          8, 1
     224: goto          116
     227: goto          235
     230: aload_1
     231: invokestatic  #32                 // Method org/jboss/as/controller/parsing/ParseUtils.unexpectedElement:(Lorg/jboss/staxmapper/XMLExtendedStreamReader;)Ljavax/xml/stream/XMLStreamException;
     234: athrow
     235: goto          5
     238: return

  public void writeAuditLog(org.jboss.staxmapper.XMLExtendedStreamWriter, org.jboss.dmr.ModelNode) throws javax.xml.stream.XMLStreamException;
    Code:
       0: aload_1
       1: getstatic     #121                // Field org/jboss/as/controller/parsing/Element.AUDIT_LOG:Lorg/jboss/as/controller/parsing/Element;
       4: invokevirtual #95                 // Method org/jboss/as/controller/parsing/Element.getLocalName:()Ljava/lang/String;
       7: invokeinterface #122,  2          // InterfaceMethod org/jboss/staxmapper/XMLExtendedStreamWriter.writeStartElement:(Ljava/lang/String;)V
      12: aload_2
      13: ldc           #43                 // String json-formatter
      15: invokevirtual #123                // Method org/jboss/dmr/ModelNode.hasDefined:(Ljava/lang/String;)Z
      18: ifeq          201
      21: aload_2
      22: ldc           #43                 // String json-formatter
      24: invokevirtual #14                 // Method org/jboss/dmr/ModelNode.get:(Ljava/lang/String;)Lorg/jboss/dmr/ModelNode;
      27: invokevirtual #124                // Method org/jboss/dmr/ModelNode.keys:()Ljava/util/Set;
      30: invokeinterface #125,  1          // InterfaceMethod java/util/Set.size:()I
      35: ifle          201
      38: aload_1
      39: getstatic     #126                // Field org/jboss/as/controller/parsing/Element.FORMATTERS:Lorg/jboss/as/controller/parsing/Element;
      42: invokevirtual #95                 // Method org/jboss/as/controller/parsing/Element.getLocalName:()Ljava/lang/String;
      45: invokeinterface #122,  2          // InterfaceMethod org/jboss/staxmapper/XMLExtendedStreamWriter.writeStartElement:(Ljava/lang/String;)V
      50: aload_2
      51: ldc           #43                 // String json-formatter
      53: invokevirtual #14                 // Method org/jboss/dmr/ModelNode.get:(Ljava/lang/String;)Lorg/jboss/dmr/ModelNode;
      56: invokevirtual #127                // Method org/jboss/dmr/ModelNode.asPropertyList:()Ljava/util/List;
      59: invokeinterface #128,  1          // InterfaceMethod java/util/List.iterator:()Ljava/util/Iterator;
      64: astore_3
      65: aload_3
      66: invokeinterface #129,  1          // InterfaceMethod java/util/Iterator.hasNext:()Z
      71: ifeq          195
      74: aload_3
      75: invokeinterface #130,  1          // InterfaceMethod java/util/Iterator.next:()Ljava/lang/Object;
      80: checkcast     #131                // class org/jboss/dmr/Property
      83: astore        4
      85: aload_1
      86: getstatic     #132                // Field org/jboss/as/controller/parsing/Element.JSON_FORMATTER:Lorg/jboss/as/controller/parsing/Element;
      89: invokevirtual #95                 // Method org/jboss/as/controller/parsing/Element.getLocalName:()Ljava/lang/String;
      92: invokeinterface #122,  2          // InterfaceMethod org/jboss/staxmapper/XMLExtendedStreamWriter.writeStartElement:(Ljava/lang/String;)V
      97: aload_1
      98: getstatic     #87                 // Field org/jboss/as/controller/parsing/Attribute.NAME:Lorg/jboss/as/controller/parsing/Attribute;
     101: invokevirtual #133                // Method org/jboss/as/controller/parsing/Attribute.getLocalName:()Ljava/lang/String;
     104: aload         4
     106: invokevirtual #134                // Method org/jboss/dmr/Property.getName:()Ljava/lang/String;
     109: invokeinterface #135,  3          // InterfaceMethod org/jboss/staxmapper/XMLExtendedStreamWriter.writeAttribute:(Ljava/lang/String;Ljava/lang/String;)V
     114: getstatic     #44                 // Field org/jboss/as/domain/management/audit/JsonAuditLogFormatterResourceDefinition.COMPACT:Lorg/jboss/as/controller/SimpleAttributeDefinition;
     117: aload         4
     119: invokevirtual #136                // Method org/jboss/dmr/Property.getValue:()Lorg/jboss/dmr/ModelNode;
     122: aload_1
     123: invokevirtual #137                // Method org/jboss/as/controller/SimpleAttributeDefinition.marshallAsAttribute:(Lorg/jboss/dmr/ModelNode;Ljavax/xml/stream/XMLStreamWriter;)V
     126: getstatic     #46                 // Field org/jboss/as/domain/management/audit/JsonAuditLogFormatterResourceDefinition.DATE_FORMAT:Lorg/jboss/as/controller/SimpleAttributeDefinition;
     129: aload         4
     131: invokevirtual #136                // Method org/jboss/dmr/Property.getValue:()Lorg/jboss/dmr/ModelNode;
     134: aload_1
     135: invokevirtual #137                // Method org/jboss/as/controller/SimpleAttributeDefinition.marshallAsAttribute:(Lorg/jboss/dmr/ModelNode;Ljavax/xml/stream/XMLStreamWriter;)V
     138: getstatic     #47                 // Field org/jboss/as/domain/management/audit/JsonAuditLogFormatterResourceDefinition.DATE_SEPARATOR:Lorg/jboss/as/controller/SimpleAttributeDefinition;
     141: aload         4
     143: invokevirtual #136                // Method org/jboss/dmr/Property.getValue:()Lorg/jboss/dmr/ModelNode;
     146: aload_1
     147: invokevirtual #137                // Method org/jboss/as/controller/SimpleAttributeDefinition.marshallAsAttribute:(Lorg/jboss/dmr/ModelNode;Ljavax/xml/stream/XMLStreamWriter;)V
     150: getstatic     #48                 // Field org/jboss/as/domain/management/audit/JsonAuditLogFormatterResourceDefinition.ESCAPE_CONTROL_CHARACTERS:Lorg/jboss/as/controller/SimpleAttributeDefinition;
     153: aload         4
     155: invokevirtual #136                // Method org/jboss/dmr/Property.getValue:()Lorg/jboss/dmr/ModelNode;
     158: aload_1
     159: invokevirtual #137                // Method org/jboss/as/controller/SimpleAttributeDefinition.marshallAsAttribute:(Lorg/jboss/dmr/ModelNode;Ljavax/xml/stream/XMLStreamWriter;)V
     162: getstatic     #49                 // Field org/jboss/as/domain/management/audit/JsonAuditLogFormatterResourceDefinition.ESCAPE_NEW_LINE:Lorg/jboss/as/controller/SimpleAttributeDefinition;
     165: aload         4
     167: invokevirtual #136                // Method org/jboss/dmr/Property.getValue:()Lorg/jboss/dmr/ModelNode;
     170: aload_1
     171: invokevirtual #137                // Method org/jboss/as/controller/SimpleAttributeDefinition.marshallAsAttribute:(Lorg/jboss/dmr/ModelNode;Ljavax/xml/stream/XMLStreamWriter;)V
     174: getstatic     #50                 // Field org/jboss/as/domain/management/audit/JsonAuditLogFormatterResourceDefinition.INCLUDE_DATE:Lorg/jboss/as/controller/SimpleAttributeDefinition;
     177: aload         4
     179: invokevirtual #136                // Method org/jboss/dmr/Property.getValue:()Lorg/jboss/dmr/ModelNode;
     182: aload_1
     183: invokevirtual #137                // Method org/jboss/as/controller/SimpleAttributeDefinition.marshallAsAttribute:(Lorg/jboss/dmr/ModelNode;Ljavax/xml/stream/XMLStreamWriter;)V
     186: aload_1
     187: invokeinterface #138,  1          // InterfaceMethod org/jboss/staxmapper/XMLExtendedStreamWriter.writeEndElement:()V
     192: goto          65
     195: aload_1
     196: invokeinterface #138,  1          // InterfaceMethod org/jboss/staxmapper/XMLExtendedStreamWriter.writeEndElement:()V
     201: aload_2
     202: ldc           #59                 // String file-handler
     204: invokevirtual #123                // Method org/jboss/dmr/ModelNode.hasDefined:(Ljava/lang/String;)Z
     207: ifeq          227
     210: aload_2
     211: ldc           #59                 // String file-handler
     213: invokevirtual #14                 // Method org/jboss/dmr/ModelNode.get:(Ljava/lang/String;)Lorg/jboss/dmr/ModelNode;
     216: invokevirtual #124                // Method org/jboss/dmr/ModelNode.keys:()Ljava/util/Set;
     219: invokeinterface #125,  1          // InterfaceMethod java/util/Set.size:()I
     224: ifgt          331
     227: aload_2
     228: ldc           #77                 // String syslog-handler
     230: invokevirtual #123                // Method org/jboss/dmr/ModelNode.hasDefined:(Ljava/lang/String;)Z
     233: ifeq          253
     236: aload_2
     237: ldc           #77                 // String syslog-handler
     239: invokevirtual #14                 // Method org/jboss/dmr/ModelNode.get:(Ljava/lang/String;)Lorg/jboss/dmr/ModelNode;
     242: invokevirtual #124                // Method org/jboss/dmr/ModelNode.keys:()Ljava/util/Set;
     245: invokeinterface #125,  1          // InterfaceMethod java/util/Set.size:()I
     250: ifgt          331
     253: aload_2
     254: ldc           #64                 // String size-rotating-file-handler
     256: invokevirtual #123                // Method org/jboss/dmr/ModelNode.hasDefined:(Ljava/lang/String;)Z
     259: ifeq          279
     262: aload_2
     263: ldc           #64                 // String size-rotating-file-handler
     265: invokevirtual #14                 // Method org/jboss/dmr/ModelNode.get:(Ljava/lang/String;)Lorg/jboss/dmr/ModelNode;
     268: invokevirtual #124                // Method org/jboss/dmr/ModelNode.keys:()Ljava/util/Set;
     271: invokeinterface #125,  1          // InterfaceMethod java/util/Set.size:()I
     276: ifgt          331
     279: aload_2
     280: ldc           #71                 // String periodic-rotating-file-handler
     282: invokevirtual #123                // Method org/jboss/dmr/ModelNode.hasDefined:(Ljava/lang/String;)Z
     285: ifeq          305
     288: aload_2
     289: ldc           #71                 // String periodic-rotating-file-handler
     291: invokevirtual #14                 // Method org/jboss/dmr/ModelNode.get:(Ljava/lang/String;)Lorg/jboss/dmr/ModelNode;
     294: invokevirtual #124                // Method org/jboss/dmr/ModelNode.keys:()Ljava/util/Set;
     297: invokeinterface #125,  1          // InterfaceMethod java/util/Set.size:()I
     302: ifgt          331
     305: aload_2
     306: ldc           #57                 // String in-memory-handler
     308: invokevirtual #123                // Method org/jboss/dmr/ModelNode.hasDefined:(Ljava/lang/String;)Z
     311: ifeq          1073
     314: aload_2
     315: ldc           #57                 // String in-memory-handler
     317: invokevirtual #14                 // Method org/jboss/dmr/ModelNode.get:(Ljava/lang/String;)Lorg/jboss/dmr/ModelNode;
     320: invokevirtual #124                // Method org/jboss/dmr/ModelNode.keys:()Ljava/util/Set;
     323: invokeinterface #139,  1          // InterfaceMethod java/util/Set.isEmpty:()Z
     328: ifne          1073
     331: aload_1
     332: getstatic     #140                // Field org/jboss/as/controller/parsing/Element.HANDLERS:Lorg/jboss/as/controller/parsing/Element;
     335: invokevirtual #95                 // Method org/jboss/as/controller/parsing/Element.getLocalName:()Ljava/lang/String;
     338: invokeinterface #122,  2          // InterfaceMethod org/jboss/staxmapper/XMLExtendedStreamWriter.writeStartElement:(Ljava/lang/String;)V
     343: aload_2
     344: ldc           #59                 // String file-handler
     346: invokevirtual #123                // Method org/jboss/dmr/ModelNode.hasDefined:(Ljava/lang/String;)Z
     349: ifeq          478
     352: aload_2
     353: ldc           #59                 // String file-handler
     355: invokevirtual #14                 // Method org/jboss/dmr/ModelNode.get:(Ljava/lang/String;)Lorg/jboss/dmr/ModelNode;
     358: invokevirtual #124                // Method org/jboss/dmr/ModelNode.keys:()Ljava/util/Set;
     361: invokeinterface #141,  1          // InterfaceMethod java/util/Set.iterator:()Ljava/util/Iterator;
     366: astore_3
     367: aload_3
     368: invokeinterface #129,  1          // InterfaceMethod java/util/Iterator.hasNext:()Z
     373: ifeq          478
     376: aload_3
     377: invokeinterface #130,  1          // InterfaceMethod java/util/Iterator.next:()Ljava/lang/Object;
     382: checkcast     #142                // class java/lang/String
     385: astore        4
     387: aload_1
     388: getstatic     #143                // Field org/jboss/as/controller/parsing/Element.FILE_HANDLER:Lorg/jboss/as/controller/parsing/Element;
     391: invokevirtual #95                 // Method org/jboss/as/controller/parsing/Element.getLocalName:()Ljava/lang/String;
     394: invokeinterface #122,  2          // InterfaceMethod org/jboss/staxmapper/XMLExtendedStreamWriter.writeStartElement:(Ljava/lang/String;)V
     399: aload_1
     400: getstatic     #87                 // Field org/jboss/as/controller/parsing/Attribute.NAME:Lorg/jboss/as/controller/parsing/Attribute;
     403: invokevirtual #133                // Method org/jboss/as/controller/parsing/Attribute.getLocalName:()Ljava/lang/String;
     406: aload         4
     408: invokeinterface #135,  3          // InterfaceMethod org/jboss/staxmapper/XMLExtendedStreamWriter.writeAttribute:(Ljava/lang/String;Ljava/lang/String;)V
     413: aload_2
     414: iconst_2
     415: anewarray     #142                // class java/lang/String
     418: dup
     419: iconst_0
     420: ldc           #59                 // String file-handler
     422: aastore
     423: dup
     424: iconst_1
     425: aload         4
     427: aastore
     428: invokevirtual #144                // Method org/jboss/dmr/ModelNode.get:([Ljava/lang/String;)Lorg/jboss/dmr/ModelNode;
     431: astore        5
     433: getstatic     #61                 // Field org/jboss/as/domain/management/audit/FileAuditLogHandlerResourceDefinition.FORMATTER:Lorg/jboss/as/controller/SimpleAttributeDefinition;
     436: aload         5
     438: aload_1
     439: invokevirtual #137                // Method org/jboss/as/controller/SimpleAttributeDefinition.marshallAsAttribute:(Lorg/jboss/dmr/ModelNode;Ljavax/xml/stream/XMLStreamWriter;)V
     442: getstatic     #60                 // Field org/jboss/as/domain/management/audit/FileAuditLogHandlerResourceDefinition.MAX_FAILURE_COUNT:Lorg/jboss/as/controller/SimpleAttributeDefinition;
     445: aload         5
     447: aload_1
     448: invokevirtual #137                // Method org/jboss/as/controller/SimpleAttributeDefinition.marshallAsAttribute:(Lorg/jboss/dmr/ModelNode;Ljavax/xml/stream/XMLStreamWriter;)V
     451: getstatic     #62                 // Field org/jboss/as/domain/management/audit/FileAuditLogHandlerResourceDefinition.PATH:Lorg/jboss/as/controller/SimpleAttributeDefinition;
     454: aload         5
     456: aload_1
     457: invokevirtual #137                // Method org/jboss/as/controller/SimpleAttributeDefinition.marshallAsAttribute:(Lorg/jboss/dmr/ModelNode;Ljavax/xml/stream/XMLStreamWriter;)V
     460: getstatic     #63                 // Field org/jboss/as/domain/management/audit/FileAuditLogHandlerResourceDefinition.RELATIVE_TO:Lorg/jboss/as/controller/SimpleAttributeDefinition;
     463: aload         5
     465: aload_1
     466: invokevirtual #137                // Method org/jboss/as/controller/SimpleAttributeDefinition.marshallAsAttribute:(Lorg/jboss/dmr/ModelNode;Ljavax/xml/stream/XMLStreamWriter;)V
     469: aload_1
     470: invokeinterface #138,  1          // InterfaceMethod org/jboss/staxmapper/XMLExtendedStreamWriter.writeEndElement:()V
     475: goto          367
     478: aload_2
     479: ldc           #71                 // String periodic-rotating-file-handler
     481: invokevirtual #123                // Method org/jboss/dmr/ModelNode.hasDefined:(Ljava/lang/String;)Z
     484: ifeq          622
     487: aload_2
     488: ldc           #71                 // String periodic-rotating-file-handler
     490: invokevirtual #14                 // Method org/jboss/dmr/ModelNode.get:(Ljava/lang/String;)Lorg/jboss/dmr/ModelNode;
     493: invokevirtual #124                // Method org/jboss/dmr/ModelNode.keys:()Ljava/util/Set;
     496: invokeinterface #141,  1          // InterfaceMethod java/util/Set.iterator:()Ljava/util/Iterator;
     501: astore_3
     502: aload_3
     503: invokeinterface #129,  1          // InterfaceMethod java/util/Iterator.hasNext:()Z
     508: ifeq          622
     511: aload_3
     512: invokeinterface #130,  1          // InterfaceMethod java/util/Iterator.next:()Ljava/lang/Object;
     517: checkcast     #142                // class java/lang/String
     520: astore        4
     522: aload_1
     523: getstatic     #145                // Field org/jboss/as/controller/parsing/Element.PERIODIC_ROTATING_FILE_HANDLER:Lorg/jboss/as/controller/parsing/Element;
     526: invokevirtual #95                 // Method org/jboss/as/controller/parsing/Element.getLocalName:()Ljava/lang/String;
     529: invokeinterface #122,  2          // InterfaceMethod org/jboss/staxmapper/XMLExtendedStreamWriter.writeStartElement:(Ljava/lang/String;)V
     534: aload_1
     535: getstatic     #87                 // Field org/jboss/as/controller/parsing/Attribute.NAME:Lorg/jboss/as/controller/parsing/Attribute;
     538: invokevirtual #133                // Method org/jboss/as/controller/parsing/Attribute.getLocalName:()Ljava/lang/String;
     541: aload         4
     543: invokeinterface #135,  3          // InterfaceMethod org/jboss/staxmapper/XMLExtendedStreamWriter.writeAttribute:(Ljava/lang/String;Ljava/lang/String;)V
     548: aload_2
     549: iconst_2
     550: anewarray     #142                // class java/lang/String
     553: dup
     554: iconst_0
     555: ldc           #71                 // String periodic-rotating-file-handler
     557: aastore
     558: dup
     559: iconst_1
     560: aload         4
     562: aastore
     563: invokevirtual #144                // Method org/jboss/dmr/ModelNode.get:([Ljava/lang/String;)Lorg/jboss/dmr/ModelNode;
     566: astore        5
     568: getstatic     #73                 // Field org/jboss/as/domain/management/audit/PeriodicRotatingFileAuditLogHandlerResourceDefinition.FORMATTER:Lorg/jboss/as/controller/SimpleAttributeDefinition;
     571: aload         5
     573: aload_1
     574: invokevirtual #137                // Method org/jboss/as/controller/SimpleAttributeDefinition.marshallAsAttribute:(Lorg/jboss/dmr/ModelNode;Ljavax/xml/stream/XMLStreamWriter;)V
     577: getstatic     #72                 // Field org/jboss/as/domain/management/audit/PeriodicRotatingFileAuditLogHandlerResourceDefinition.MAX_FAILURE_COUNT:Lorg/jboss/as/controller/SimpleAttributeDefinition;
     580: aload         5
     582: aload_1
     583: invokevirtual #137                // Method org/jboss/as/controller/SimpleAttributeDefinition.marshallAsAttribute:(Lorg/jboss/dmr/ModelNode;Ljavax/xml/stream/XMLStreamWriter;)V
     586: getstatic     #74                 // Field org/jboss/as/domain/management/audit/PeriodicRotatingFileAuditLogHandlerResourceDefinition.PATH:Lorg/jboss/as/controller/SimpleAttributeDefinition;
     589: aload         5
     591: aload_1
     592: invokevirtual #137                // Method org/jboss/as/controller/SimpleAttributeDefinition.marshallAsAttribute:(Lorg/jboss/dmr/ModelNode;Ljavax/xml/stream/XMLStreamWriter;)V
     595: getstatic     #75                 // Field org/jboss/as/domain/management/audit/PeriodicRotatingFileAuditLogHandlerResourceDefinition.RELATIVE_TO:Lorg/jboss/as/controller/SimpleAttributeDefinition;
     598: aload         5
     600: aload_1
     601: invokevirtual #137                // Method org/jboss/as/controller/SimpleAttributeDefinition.marshallAsAttribute:(Lorg/jboss/dmr/ModelNode;Ljavax/xml/stream/XMLStreamWriter;)V
     604: getstatic     #76                 // Field org/jboss/as/domain/management/audit/PeriodicRotatingFileAuditLogHandlerResourceDefinition.SUFFIX:Lorg/jboss/as/controller/SimpleAttributeDefinition;
     607: aload         5
     609: aload_1
     610: invokevirtual #137                // Method org/jboss/as/controller/SimpleAttributeDefinition.marshallAsAttribute:(Lorg/jboss/dmr/ModelNode;Ljavax/xml/stream/XMLStreamWriter;)V
     613: aload_1
     614: invokeinterface #138,  1          // InterfaceMethod org/jboss/staxmapper/XMLExtendedStreamWriter.writeEndElement:()V
     619: goto          502
     622: aload_2
     623: ldc           #64                 // String size-rotating-file-handler
     625: invokevirtual #123                // Method org/jboss/dmr/ModelNode.hasDefined:(Ljava/lang/String;)Z
     628: ifeq          775
     631: aload_2
     632: ldc           #64                 // String size-rotating-file-handler
     634: invokevirtual #14                 // Method org/jboss/dmr/ModelNode.get:(Ljava/lang/String;)Lorg/jboss/dmr/ModelNode;
     637: invokevirtual #124                // Method org/jboss/dmr/ModelNode.keys:()Ljava/util/Set;
     640: invokeinterface #141,  1          // InterfaceMethod java/util/Set.iterator:()Ljava/util/Iterator;
     645: astore_3
     646: aload_3
     647: invokeinterface #129,  1          // InterfaceMethod java/util/Iterator.hasNext:()Z
     652: ifeq          775
     655: aload_3
     656: invokeinterface #130,  1          // InterfaceMethod java/util/Iterator.next:()Ljava/lang/Object;
     661: checkcast     #142                // class java/lang/String
     664: astore        4
     666: aload_1
     667: getstatic     #146                // Field org/jboss/as/controller/parsing/Element.SIZE_ROTATING_FILE_HANDLER:Lorg/jboss/as/controller/parsing/Element;
     670: invokevirtual #95                 // Method org/jboss/as/controller/parsing/Element.getLocalName:()Ljava/lang/String;
     673: invokeinterface #122,  2          // InterfaceMethod org/jboss/staxmapper/XMLExtendedStreamWriter.writeStartElement:(Ljava/lang/String;)V
     678: aload_1
     679: getstatic     #87                 // Field org/jboss/as/controller/parsing/Attribute.NAME:Lorg/jboss/as/controller/parsing/Attribute;
     682: invokevirtual #133                // Method org/jboss/as/controller/parsing/Attribute.getLocalName:()Ljava/lang/String;
     685: aload         4
     687: invokeinterface #135,  3          // InterfaceMethod org/jboss/staxmapper/XMLExtendedStreamWriter.writeAttribute:(Ljava/lang/String;Ljava/lang/String;)V
     692: aload_2
     693: iconst_2
     694: anewarray     #142                // class java/lang/String
     697: dup
     698: iconst_0
     699: ldc           #64                 // String size-rotating-file-handler
     701: aastore
     702: dup
     703: iconst_1
     704: aload         4
     706: aastore
     707: invokevirtual #144                // Method org/jboss/dmr/ModelNode.get:([Ljava/lang/String;)Lorg/jboss/dmr/ModelNode;
     710: astore        5
     712: getstatic     #66                 // Field org/jboss/as/domain/management/audit/SizeRotatingFileAuditLogHandlerResourceDefinition.FORMATTER:Lorg/jboss/as/controller/SimpleAttributeDefinition;
     715: aload         5
     717: aload_1
     718: invokevirtual #137                // Method org/jboss/as/controller/SimpleAttributeDefinition.marshallAsAttribute:(Lorg/jboss/dmr/ModelNode;Ljavax/xml/stream/XMLStreamWriter;)V
     721: getstatic     #65                 // Field org/jboss/as/domain/management/audit/SizeRotatingFileAuditLogHandlerResourceDefinition.MAX_FAILURE_COUNT:Lorg/jboss/as/controller/SimpleAttributeDefinition;
     724: aload         5
     726: aload_1
     727: invokevirtual #137                // Method org/jboss/as/controller/SimpleAttributeDefinition.marshallAsAttribute:(Lorg/jboss/dmr/ModelNode;Ljavax/xml/stream/XMLStreamWriter;)V
     730: getstatic     #67                 // Field org/jboss/as/domain/management/audit/SizeRotatingFileAuditLogHandlerResourceDefinition.PATH:Lorg/jboss/as/controller/SimpleAttributeDefinition;
     733: aload         5
     735: aload_1
     736: invokevirtual #137                // Method org/jboss/as/controller/SimpleAttributeDefinition.marshallAsAttribute:(Lorg/jboss/dmr/ModelNode;Ljavax/xml/stream/XMLStreamWriter;)V
     739: getstatic     #68                 // Field org/jboss/as/domain/management/audit/SizeRotatingFileAuditLogHandlerResourceDefinition.RELATIVE_TO:Lorg/jboss/as/controller/SimpleAttributeDefinition;
     742: aload         5
     744: aload_1
     745: invokevirtual #137                // Method org/jboss/as/controller/SimpleAttributeDefinition.marshallAsAttribute:(Lorg/jboss/dmr/ModelNode;Ljavax/xml/stream/XMLStreamWriter;)V
     748: getstatic     #69                 // Field org/jboss/as/domain/management/audit/SizeRotatingFileAuditLogHandlerResourceDefinition.ROTATE_SIZE:Lorg/jboss/as/controller/SimpleAttributeDefinition;
     751: aload         5
     753: aload_1
     754: invokevirtual #137                // Method org/jboss/as/controller/SimpleAttributeDefinition.marshallAsAttribute:(Lorg/jboss/dmr/ModelNode;Ljavax/xml/stream/XMLStreamWriter;)V
     757: getstatic     #70                 // Field org/jboss/as/domain/management/audit/SizeRotatingFileAuditLogHandlerResourceDefinition.MAX_BACKUP_INDEX:Lorg/jboss/as/controller/SimpleAttributeDefinition;
     760: aload         5
     762: aload_1
     763: invokevirtual #137                // Method org/jboss/as/controller/SimpleAttributeDefinition.marshallAsAttribute:(Lorg/jboss/dmr/ModelNode;Ljavax/xml/stream/XMLStreamWriter;)V
     766: aload_1
     767: invokeinterface #138,  1          // InterfaceMethod org/jboss/staxmapper/XMLExtendedStreamWriter.writeEndElement:()V
     772: goto          646
     775: aload_2
     776: ldc           #77                 // String syslog-handler
     778: invokevirtual #123                // Method org/jboss/dmr/ModelNode.hasDefined:(Ljava/lang/String;)Z
     781: ifeq          959
     784: aload_2
     785: ldc           #77                 // String syslog-handler
     787: invokevirtual #14                 // Method org/jboss/dmr/ModelNode.get:(Ljava/lang/String;)Lorg/jboss/dmr/ModelNode;
     790: invokevirtual #124                // Method org/jboss/dmr/ModelNode.keys:()Ljava/util/Set;
     793: invokeinterface #141,  1          // InterfaceMethod java/util/Set.iterator:()Ljava/util/Iterator;
     798: astore_3
     799: aload_3
     800: invokeinterface #129,  1          // InterfaceMethod java/util/Iterator.hasNext:()Z
     805: ifeq          959
     808: aload_3
     809: invokeinterface #130,  1          // InterfaceMethod java/util/Iterator.next:()Ljava/lang/Object;
     814: checkcast     #142                // class java/lang/String
     817: astore        4
     819: aload_1
     820: getstatic     #147                // Field org/jboss/as/controller/parsing/Element.SYSLOG_HANDLER:Lorg/jboss/as/controller/parsing/Element;
     823: invokevirtual #95                 // Method org/jboss/as/controller/parsing/Element.getLocalName:()Ljava/lang/String;
     826: invokeinterface #122,  2          // InterfaceMethod org/jboss/staxmapper/XMLExtendedStreamWriter.writeStartElement:(Ljava/lang/String;)V
     831: aload_1
     832: getstatic     #87                 // Field org/jboss/as/controller/parsing/Attribute.NAME:Lorg/jboss/as/controller/parsing/Attribute;
     835: invokevirtual #133                // Method org/jboss/as/controller/parsing/Attribute.getLocalName:()Ljava/lang/String;
     838: aload         4
     840: invokeinterface #135,  3          // InterfaceMethod org/jboss/staxmapper/XMLExtendedStreamWriter.writeAttribute:(Ljava/lang/String;Ljava/lang/String;)V
     845: aload_2
     846: iconst_2
     847: anewarray     #142                // class java/lang/String
     850: dup
     851: iconst_0
     852: ldc           #77                 // String syslog-handler
     854: aastore
     855: dup
     856: iconst_1
     857: aload         4
     859: aastore
     860: invokevirtual #144                // Method org/jboss/dmr/ModelNode.get:([Ljava/lang/String;)Lorg/jboss/dmr/ModelNode;
     863: astore        5
     865: getstatic     #79                 // Field org/jboss/as/domain/management/audit/SyslogAuditLogHandlerResourceDefinition.FORMATTER:Lorg/jboss/as/controller/SimpleAttributeDefinition;
     868: aload         5
     870: aload_1
     871: invokevirtual #137                // Method org/jboss/as/controller/SimpleAttributeDefinition.marshallAsAttribute:(Lorg/jboss/dmr/ModelNode;Ljavax/xml/stream/XMLStreamWriter;)V
     874: getstatic     #78                 // Field org/jboss/as/domain/management/audit/SyslogAuditLogHandlerResourceDefinition.MAX_FAILURE_COUNT:Lorg/jboss/as/controller/SimpleAttributeDefinition;
     877: aload         5
     879: aload_1
     880: invokevirtual #137                // Method org/jboss/as/controller/SimpleAttributeDefinition.marshallAsAttribute:(Lorg/jboss/dmr/ModelNode;Ljavax/xml/stream/XMLStreamWriter;)V
     883: getstatic     #84                 // Field org/jboss/as/domain/management/audit/SyslogAuditLogHandlerResourceDefinition.SYSLOG_FORMAT:Lorg/jboss/as/controller/SimpleAttributeDefinition;
     886: aload         5
     888: aload_1
     889: invokevirtual #137                // Method org/jboss/as/controller/SimpleAttributeDefinition.marshallAsAttribute:(Lorg/jboss/dmr/ModelNode;Ljavax/xml/stream/XMLStreamWriter;)V
     892: getstatic     #80                 // Field org/jboss/as/domain/management/audit/SyslogAuditLogHandlerResourceDefinition.MAX_LENGTH:Lorg/jboss/as/controller/SimpleAttributeDefinition;
     895: aload         5
     897: aload_1
     898: invokevirtual #137                // Method org/jboss/as/controller/SimpleAttributeDefinition.marshallAsAttribute:(Lorg/jboss/dmr/ModelNode;Ljavax/xml/stream/XMLStreamWriter;)V
     901: getstatic     #81                 // Field org/jboss/as/domain/management/audit/SyslogAuditLogHandlerResourceDefinition.TRUNCATE:Lorg/jboss/as/controller/SimpleAttributeDefinition;
     904: aload         5
     906: aload_1
     907: invokevirtual #137                // Method org/jboss/as/controller/SimpleAttributeDefinition.marshallAsAttribute:(Lorg/jboss/dmr/ModelNode;Ljavax/xml/stream/XMLStreamWriter;)V
     910: getstatic     #82                 // Field org/jboss/as/domain/management/audit/SyslogAuditLogHandlerResourceDefinition.FACILITY:Lorg/jboss/as/controller/SimpleAttributeDefinition;
     913: aload         5
     915: aload_1
     916: invokevirtual #137                // Method org/jboss/as/controller/SimpleAttributeDefinition.marshallAsAttribute:(Lorg/jboss/dmr/ModelNode;Ljavax/xml/stream/XMLStreamWriter;)V
     919: getstatic     #83                 // Field org/jboss/as/domain/management/audit/SyslogAuditLogHandlerResourceDefinition.APP_NAME:Lorg/jboss/as/controller/SimpleAttributeDefinition;
     922: aload         5
     924: aload_1
     925: invokevirtual #137                // Method org/jboss/as/controller/SimpleAttributeDefinition.marshallAsAttribute:(Lorg/jboss/dmr/ModelNode;Ljavax/xml/stream/XMLStreamWriter;)V
     928: aload         5
     930: ldc           #94                 // String protocol
     932: invokevirtual #123                // Method org/jboss/dmr/ModelNode.hasDefined:(Ljava/lang/String;)Z
     935: ifeq          950
     938: aload_0
     939: aload_1
     940: aload         5
     942: ldc           #94                 // String protocol
     944: invokevirtual #14                 // Method org/jboss/dmr/ModelNode.get:(Ljava/lang/String;)Lorg/jboss/dmr/ModelNode;
     947: invokespecial #148                // Method writeAuditLogSyslogProtocol:(Lorg/jboss/staxmapper/XMLExtendedStreamWriter;Lorg/jboss/dmr/ModelNode;)V
     950: aload_1
     951: invokeinterface #138,  1          // InterfaceMethod org/jboss/staxmapper/XMLExtendedStreamWriter.writeEndElement:()V
     956: goto          799
     959: aload_2
     960: ldc           #57                 // String in-memory-handler
     962: invokevirtual #123                // Method org/jboss/dmr/ModelNode.hasDefined:(Ljava/lang/String;)Z
     965: ifeq          1067
     968: aload_2
     969: ldc           #57                 // String in-memory-handler
     971: invokevirtual #14                 // Method org/jboss/dmr/ModelNode.get:(Ljava/lang/String;)Lorg/jboss/dmr/ModelNode;
     974: invokevirtual #124                // Method org/jboss/dmr/ModelNode.keys:()Ljava/util/Set;
     977: invokeinterface #141,  1          // InterfaceMethod java/util/Set.iterator:()Ljava/util/Iterator;
     982: astore_3
     983: aload_3
     984: invokeinterface #129,  1          // InterfaceMethod java/util/Iterator.hasNext:()Z
     989: ifeq          1067
     992: aload_3
     993: invokeinterface #130,  1          // InterfaceMethod java/util/Iterator.next:()Ljava/lang/Object;
     998: checkcast     #142                // class java/lang/String
    1001: astore        4
    1003: aload_1
    1004: getstatic     #149                // Field org/jboss/as/controller/parsing/Element.IN_MEMORY_HANDLER:Lorg/jboss/as/controller/parsing/Element;
    1007: invokevirtual #95                 // Method org/jboss/as/controller/parsing/Element.getLocalName:()Ljava/lang/String;
    1010: invokeinterface #122,  2          // InterfaceMethod org/jboss/staxmapper/XMLExtendedStreamWriter.writeStartElement:(Ljava/lang/String;)V
    1015: aload_1
    1016: getstatic     #87                 // Field org/jboss/as/controller/parsing/Attribute.NAME:Lorg/jboss/as/controller/parsing/Attribute;
    1019: invokevirtual #133                // Method org/jboss/as/controller/parsing/Attribute.getLocalName:()Ljava/lang/String;
    1022: aload         4
    1024: invokeinterface #135,  3          // InterfaceMethod org/jboss/staxmapper/XMLExtendedStreamWriter.writeAttribute:(Ljava/lang/String;Ljava/lang/String;)V
    1029: aload_2
    1030: iconst_2
    1031: anewarray     #142                // class java/lang/String
    1034: dup
    1035: iconst_0
    1036: ldc           #57                 // String in-memory-handler
    1038: aastore
    1039: dup
    1040: iconst_1
    1041: aload         4
    1043: aastore
    1044: invokevirtual #144                // Method org/jboss/dmr/ModelNode.get:([Ljava/lang/String;)Lorg/jboss/dmr/ModelNode;
    1047: astore        5
    1049: getstatic     #58                 // Field org/jboss/as/domain/management/audit/InMemoryAuditLogHandlerResourceDefinition.MAX_OPERATION_COUNT:Lorg/jboss/as/controller/SimpleAttributeDefinition;
    1052: aload         5
    1054: aload_1
    1055: invokevirtual #137                // Method org/jboss/as/controller/SimpleAttributeDefinition.marshallAsAttribute:(Lorg/jboss/dmr/ModelNode;Ljavax/xml/stream/XMLStreamWriter;)V
    1058: aload_1
    1059: invokeinterface #138,  1          // InterfaceMethod org/jboss/staxmapper/XMLExtendedStreamWriter.writeEndElement:()V
    1064: goto          983
    1067: aload_1
    1068: invokeinterface #138,  1          // InterfaceMethod org/jboss/staxmapper/XMLExtendedStreamWriter.writeEndElement:()V
    1073: aload_0
    1074: aload_1
    1075: aload_2
    1076: getstatic     #150                // Field org/jboss/as/controller/parsing/Element.LOGGER:Lorg/jboss/as/controller/parsing/Element;
    1079: invokevirtual #95                 // Method org/jboss/as/controller/parsing/Element.getLocalName:()Ljava/lang/String;
    1082: invokespecial #151                // Method writeAuditLogger:(Lorg/jboss/staxmapper/XMLExtendedStreamWriter;Lorg/jboss/dmr/ModelNode;Ljava/lang/String;)V
    1085: aload_0
    1086: aload_1
    1087: aload_2
    1088: getstatic     #152                // Field org/jboss/as/controller/parsing/Element.SERVER_LOGGER:Lorg/jboss/as/controller/parsing/Element;
    1091: invokevirtual #95                 // Method org/jboss/as/controller/parsing/Element.getLocalName:()Ljava/lang/String;
    1094: invokespecial #151                // Method writeAuditLogger:(Lorg/jboss/staxmapper/XMLExtendedStreamWriter;Lorg/jboss/dmr/ModelNode;Ljava/lang/String;)V
    1097: aload_1
    1098: invokeinterface #138,  1          // InterfaceMethod org/jboss/staxmapper/XMLExtendedStreamWriter.writeEndElement:()V
    1103: return

  private void writeAuditLogger(org.jboss.staxmapper.XMLExtendedStreamWriter, org.jboss.dmr.ModelNode, java.lang.String) throws javax.xml.stream.XMLStreamException;
    Code:
       0: aload_2
       1: aload_3
       2: invokevirtual #123                // Method org/jboss/dmr/ModelNode.hasDefined:(Ljava/lang/String;)Z
       5: ifeq          200
       8: aload_2
       9: aload_3
      10: invokevirtual #14                 // Method org/jboss/dmr/ModelNode.get:(Ljava/lang/String;)Lorg/jboss/dmr/ModelNode;
      13: ldc           #153                // String audit-log
      15: invokevirtual #123                // Method org/jboss/dmr/ModelNode.hasDefined:(Ljava/lang/String;)Z
      18: ifeq          200
      21: aload_2
      22: iconst_2
      23: anewarray     #142                // class java/lang/String
      26: dup
      27: iconst_0
      28: aload_3
      29: aastore
      30: dup
      31: iconst_1
      32: ldc           #153                // String audit-log
      34: aastore
      35: invokevirtual #144                // Method org/jboss/dmr/ModelNode.get:([Ljava/lang/String;)Lorg/jboss/dmr/ModelNode;
      38: astore        4
      40: aload_1
      41: aload_3
      42: invokeinterface #122,  2          // InterfaceMethod org/jboss/staxmapper/XMLExtendedStreamWriter.writeStartElement:(Ljava/lang/String;)V
      47: getstatic     #117                // Field org/jboss/as/domain/management/audit/AuditLogLoggerResourceDefinition.LOG_BOOT:Lorg/jboss/as/controller/SimpleAttributeDefinition;
      50: aload         4
      52: aload_1
      53: invokevirtual #137                // Method org/jboss/as/controller/SimpleAttributeDefinition.marshallAsAttribute:(Lorg/jboss/dmr/ModelNode;Ljavax/xml/stream/XMLStreamWriter;)V
      56: getstatic     #116                // Field org/jboss/as/domain/management/audit/AuditLogLoggerResourceDefinition.LOG_READ_ONLY:Lorg/jboss/as/controller/SimpleAttributeDefinition;
      59: aload         4
      61: aload_1
      62: invokevirtual #137                // Method org/jboss/as/controller/SimpleAttributeDefinition.marshallAsAttribute:(Lorg/jboss/dmr/ModelNode;Ljavax/xml/stream/XMLStreamWriter;)V
      65: getstatic     #118                // Field org/jboss/as/domain/management/audit/AuditLogLoggerResourceDefinition.ENABLED:Lorg/jboss/as/controller/SimpleAttributeDefinition;
      68: aload         4
      70: aload_1
      71: invokevirtual #137                // Method org/jboss/as/controller/SimpleAttributeDefinition.marshallAsAttribute:(Lorg/jboss/dmr/ModelNode;Ljavax/xml/stream/XMLStreamWriter;)V
      74: aload         4
      76: ldc           #120                // String handler
      78: invokevirtual #123                // Method org/jboss/dmr/ModelNode.hasDefined:(Ljava/lang/String;)Z
      81: ifeq          194
      84: aload         4
      86: ldc           #120                // String handler
      88: invokevirtual #14                 // Method org/jboss/dmr/ModelNode.get:(Ljava/lang/String;)Lorg/jboss/dmr/ModelNode;
      91: invokevirtual #124                // Method org/jboss/dmr/ModelNode.keys:()Ljava/util/Set;
      94: invokeinterface #125,  1          // InterfaceMethod java/util/Set.size:()I
      99: ifle          194
     102: aload_1
     103: getstatic     #140                // Field org/jboss/as/controller/parsing/Element.HANDLERS:Lorg/jboss/as/controller/parsing/Element;
     106: invokevirtual #95                 // Method org/jboss/as/controller/parsing/Element.getLocalName:()Ljava/lang/String;
     109: invokeinterface #122,  2          // InterfaceMethod org/jboss/staxmapper/XMLExtendedStreamWriter.writeStartElement:(Ljava/lang/String;)V
     114: aload         4
     116: ldc           #120                // String handler
     118: invokevirtual #14                 // Method org/jboss/dmr/ModelNode.get:(Ljava/lang/String;)Lorg/jboss/dmr/ModelNode;
     121: invokevirtual #124                // Method org/jboss/dmr/ModelNode.keys:()Ljava/util/Set;
     124: invokeinterface #141,  1          // InterfaceMethod java/util/Set.iterator:()Ljava/util/Iterator;
     129: astore        5
     131: aload         5
     133: invokeinterface #129,  1          // InterfaceMethod java/util/Iterator.hasNext:()Z
     138: ifeq          188
     141: aload         5
     143: invokeinterface #130,  1          // InterfaceMethod java/util/Iterator.next:()Ljava/lang/Object;
     148: checkcast     #142                // class java/lang/String
     151: astore        6
     153: aload_1
     154: getstatic     #154                // Field org/jboss/as/controller/parsing/Element.HANDLER:Lorg/jboss/as/controller/parsing/Element;
     157: invokevirtual #95                 // Method org/jboss/as/controller/parsing/Element.getLocalName:()Ljava/lang/String;
     160: invokeinterface #122,  2          // InterfaceMethod org/jboss/staxmapper/XMLExtendedStreamWriter.writeStartElement:(Ljava/lang/String;)V
     165: aload_1
     166: getstatic     #87                 // Field org/jboss/as/controller/parsing/Attribute.NAME:Lorg/jboss/as/controller/parsing/Attribute;
     169: invokevirtual #133                // Method org/jboss/as/controller/parsing/Attribute.getLocalName:()Ljava/lang/String;
     172: aload         6
     174: invokeinterface #135,  3          // InterfaceMethod org/jboss/staxmapper/XMLExtendedStreamWriter.writeAttribute:(Ljava/lang/String;Ljava/lang/String;)V
     179: aload_1
     180: invokeinterface #138,  1          // InterfaceMethod org/jboss/staxmapper/XMLExtendedStreamWriter.writeEndElement:()V
     185: goto          131
     188: aload_1
     189: invokeinterface #138,  1          // InterfaceMethod org/jboss/staxmapper/XMLExtendedStreamWriter.writeEndElement:()V
     194: aload_1
     195: invokeinterface #138,  1          // InterfaceMethod org/jboss/staxmapper/XMLExtendedStreamWriter.writeEndElement:()V
     200: return

  private void writeAuditLogSyslogProtocol(org.jboss.staxmapper.XMLExtendedStreamWriter, org.jboss.dmr.ModelNode) throws javax.xml.stream.XMLStreamException;
    Code:
       0: aload_2
       1: invokevirtual #124                // Method org/jboss/dmr/ModelNode.keys:()Ljava/util/Set;
       4: invokeinterface #141,  1          // InterfaceMethod java/util/Set.iterator:()Ljava/util/Iterator;
       9: invokeinterface #130,  1          // InterfaceMethod java/util/Iterator.next:()Ljava/lang/Object;
      14: checkcast     #142                // class java/lang/String
      17: astore_3
      18: aload_2
      19: aload_3
      20: invokevirtual #14                 // Method org/jboss/dmr/ModelNode.get:(Ljava/lang/String;)Lorg/jboss/dmr/ModelNode;
      23: astore        4
      25: aload_3
      26: ldc           #155                // String udp
      28: invokevirtual #156                // Method java/lang/String.equals:(Ljava/lang/Object;)Z
      31: ifeq          68
      34: aload_1
      35: aload_3
      36: invokeinterface #122,  2          // InterfaceMethod org/jboss/staxmapper/XMLExtendedStreamWriter.writeStartElement:(Ljava/lang/String;)V
      41: getstatic     #98                 // Field org/jboss/as/domain/management/audit/SyslogAuditLogProtocolResourceDefinition$Udp.HOST:Lorg/jboss/as/controller/SimpleAttributeDefinition;
      44: aload         4
      46: aload_1
      47: invokevirtual #137                // Method org/jboss/as/controller/SimpleAttributeDefinition.marshallAsAttribute:(Lorg/jboss/dmr/ModelNode;Ljavax/xml/stream/XMLStreamWriter;)V
      50: getstatic     #99                 // Field org/jboss/as/domain/management/audit/SyslogAuditLogProtocolResourceDefinition$Udp.PORT:Lorg/jboss/as/controller/SimpleAttributeDefinition;
      53: aload         4
      55: aload_1
      56: invokevirtual #137                // Method org/jboss/as/controller/SimpleAttributeDefinition.marshallAsAttribute:(Lorg/jboss/dmr/ModelNode;Ljavax/xml/stream/XMLStreamWriter;)V
      59: aload_1
      60: invokeinterface #138,  1          // InterfaceMethod org/jboss/staxmapper/XMLExtendedStreamWriter.writeEndElement:()V
      65: goto          225
      68: aload_3
      69: ldc           #157                // String tcp
      71: invokevirtual #156                // Method java/lang/String.equals:(Ljava/lang/Object;)Z
      74: ifeq          129
      77: aload_1
      78: aload_3
      79: invokeinterface #122,  2          // InterfaceMethod org/jboss/staxmapper/XMLExtendedStreamWriter.writeStartElement:(Ljava/lang/String;)V
      84: getstatic     #158                // Field org/jboss/as/domain/management/audit/SyslogAuditLogProtocolResourceDefinition$Tcp.HOST:Lorg/jboss/as/controller/SimpleAttributeDefinition;
      87: aload         4
      89: aload_1
      90: invokevirtual #137                // Method org/jboss/as/controller/SimpleAttributeDefinition.marshallAsAttribute:(Lorg/jboss/dmr/ModelNode;Ljavax/xml/stream/XMLStreamWriter;)V
      93: getstatic     #159                // Field org/jboss/as/domain/management/audit/SyslogAuditLogProtocolResourceDefinition$Tcp.PORT:Lorg/jboss/as/controller/SimpleAttributeDefinition;
      96: aload         4
      98: aload_1
      99: invokevirtual #137                // Method org/jboss/as/controller/SimpleAttributeDefinition.marshallAsAttribute:(Lorg/jboss/dmr/ModelNode;Ljavax/xml/stream/XMLStreamWriter;)V
     102: getstatic     #101                // Field org/jboss/as/domain/management/audit/SyslogAuditLogProtocolResourceDefinition$Tcp.MESSAGE_TRANSFER:Lorg/jboss/as/controller/SimpleAttributeDefinition;
     105: aload         4
     107: aload_1
     108: invokevirtual #137                // Method org/jboss/as/controller/SimpleAttributeDefinition.marshallAsAttribute:(Lorg/jboss/dmr/ModelNode;Ljavax/xml/stream/XMLStreamWriter;)V
     111: getstatic     #102                // Field org/jboss/as/domain/management/audit/SyslogAuditLogProtocolResourceDefinition$Tcp.RECONNECT_TIMEOUT:Lorg/jboss/as/controller/SimpleAttributeDefinition;
     114: aload         4
     116: aload_1
     117: invokevirtual #137                // Method org/jboss/as/controller/SimpleAttributeDefinition.marshallAsAttribute:(Lorg/jboss/dmr/ModelNode;Ljavax/xml/stream/XMLStreamWriter;)V
     120: aload_1
     121: invokeinterface #138,  1          // InterfaceMethod org/jboss/staxmapper/XMLExtendedStreamWriter.writeEndElement:()V
     126: goto          225
     129: aload_3
     130: ldc           #160                // String tls
     132: invokevirtual #156                // Method java/lang/String.equals:(Ljava/lang/Object;)Z
     135: ifeq          225
     138: aload_1
     139: aload_3
     140: invokeinterface #122,  2          // InterfaceMethod org/jboss/staxmapper/XMLExtendedStreamWriter.writeStartElement:(Ljava/lang/String;)V
     145: getstatic     #161                // Field org/jboss/as/domain/management/audit/SyslogAuditLogProtocolResourceDefinition$Tls.HOST:Lorg/jboss/as/controller/SimpleAttributeDefinition;
     148: aload         4
     150: aload_1
     151: invokevirtual #137                // Method org/jboss/as/controller/SimpleAttributeDefinition.marshallAsAttribute:(Lorg/jboss/dmr/ModelNode;Ljavax/xml/stream/XMLStreamWriter;)V
     154: getstatic     #162                // Field org/jboss/as/domain/management/audit/SyslogAuditLogProtocolResourceDefinition$Tls.PORT:Lorg/jboss/as/controller/SimpleAttributeDefinition;
     157: aload         4
     159: aload_1
     160: invokevirtual #137                // Method org/jboss/as/controller/SimpleAttributeDefinition.marshallAsAttribute:(Lorg/jboss/dmr/ModelNode;Ljavax/xml/stream/XMLStreamWriter;)V
     163: getstatic     #163                // Field org/jboss/as/domain/management/audit/SyslogAuditLogProtocolResourceDefinition$Tls.MESSAGE_TRANSFER:Lorg/jboss/as/controller/SimpleAttributeDefinition;
     166: aload         4
     168: aload_1
     169: invokevirtual #137                // Method org/jboss/as/controller/SimpleAttributeDefinition.marshallAsAttribute:(Lorg/jboss/dmr/ModelNode;Ljavax/xml/stream/XMLStreamWriter;)V
     172: getstatic     #102                // Field org/jboss/as/domain/management/audit/SyslogAuditLogProtocolResourceDefinition$Tcp.RECONNECT_TIMEOUT:Lorg/jboss/as/controller/SimpleAttributeDefinition;
     175: aload         4
     177: aload_1
     178: invokevirtual #137                // Method org/jboss/as/controller/SimpleAttributeDefinition.marshallAsAttribute:(Lorg/jboss/dmr/ModelNode;Ljavax/xml/stream/XMLStreamWriter;)V
     181: aload         4
     183: ldc           #164                // String authentication
     185: invokevirtual #123                // Method org/jboss/dmr/ModelNode.hasDefined:(Ljava/lang/String;)Z
     188: ifeq          219
     191: aload_0
     192: aload_1
     193: aload         4
     195: ldc           #164                // String authentication
     197: invokevirtual #14                 // Method org/jboss/dmr/ModelNode.get:(Ljava/lang/String;)Lorg/jboss/dmr/ModelNode;
     200: ldc           #165                // String truststore
     202: invokespecial #166                // Method writeAuditLogSyslogTlsProtocolKeyStore:(Lorg/jboss/staxmapper/XMLExtendedStreamWriter;Lorg/jboss/dmr/ModelNode;Ljava/lang/String;)V
     205: aload_0
     206: aload_1
     207: aload         4
     209: ldc           #164                // String authentication
     211: invokevirtual #14                 // Method org/jboss/dmr/ModelNode.get:(Ljava/lang/String;)Lorg/jboss/dmr/ModelNode;
     214: ldc           #167                // String client-certificate-store
     216: invokespecial #166                // Method writeAuditLogSyslogTlsProtocolKeyStore:(Lorg/jboss/staxmapper/XMLExtendedStreamWriter;Lorg/jboss/dmr/ModelNode;Ljava/lang/String;)V
     219: aload_1
     220: invokeinterface #138,  1          // InterfaceMethod org/jboss/staxmapper/XMLExtendedStreamWriter.writeEndElement:()V
     225: return

  private void writeAuditLogSyslogTlsProtocolKeyStore(org.jboss.staxmapper.XMLExtendedStreamWriter, org.jboss.dmr.ModelNode, java.lang.String) throws javax.xml.stream.XMLStreamException;
    Code:
       0: aload_2
       1: aload_3
       2: invokevirtual #123                // Method org/jboss/dmr/ModelNode.hasDefined:(Ljava/lang/String;)Z
       5: ifeq          64
       8: aload_2
       9: aload_3
      10: invokevirtual #14                 // Method org/jboss/dmr/ModelNode.get:(Ljava/lang/String;)Lorg/jboss/dmr/ModelNode;
      13: astore        4
      15: aload_1
      16: aload_3
      17: invokeinterface #122,  2          // InterfaceMethod org/jboss/staxmapper/XMLExtendedStreamWriter.writeStartElement:(Ljava/lang/String;)V
      22: getstatic     #113                // Field org/jboss/as/domain/management/audit/SyslogAuditLogProtocolResourceDefinition$TlsKeyStore.KEYSTORE_PATH:Lorg/jboss/as/controller/SimpleAttributeDefinition;
      25: aload         4
      27: aload_1
      28: invokevirtual #137                // Method org/jboss/as/controller/SimpleAttributeDefinition.marshallAsAttribute:(Lorg/jboss/dmr/ModelNode;Ljavax/xml/stream/XMLStreamWriter;)V
      31: getstatic     #114                // Field org/jboss/as/domain/management/audit/SyslogAuditLogProtocolResourceDefinition$TlsKeyStore.KEYSTORE_RELATIVE_TO:Lorg/jboss/as/controller/SimpleAttributeDefinition;
      34: aload         4
      36: aload_1
      37: invokevirtual #137                // Method org/jboss/as/controller/SimpleAttributeDefinition.marshallAsAttribute:(Lorg/jboss/dmr/ModelNode;Ljavax/xml/stream/XMLStreamWriter;)V
      40: getstatic     #112                // Field org/jboss/as/domain/management/audit/SyslogAuditLogProtocolResourceDefinition$TlsKeyStore.KEYSTORE_PASSWORD:Lorg/jboss/as/controller/SimpleAttributeDefinition;
      43: aload         4
      45: aload_1
      46: invokevirtual #137                // Method org/jboss/as/controller/SimpleAttributeDefinition.marshallAsAttribute:(Lorg/jboss/dmr/ModelNode;Ljavax/xml/stream/XMLStreamWriter;)V
      49: getstatic     #115                // Field org/jboss/as/domain/management/audit/SyslogAuditLogProtocolResourceDefinition$TlsKeyStore.KEY_PASSWORD:Lorg/jboss/as/controller/SimpleAttributeDefinition;
      52: aload         4
      54: aload_1
      55: invokevirtual #137                // Method org/jboss/as/controller/SimpleAttributeDefinition.marshallAsAttribute:(Lorg/jboss/dmr/ModelNode;Ljavax/xml/stream/XMLStreamWriter;)V
      58: aload_1
      59: invokeinterface #138,  1          // InterfaceMethod org/jboss/staxmapper/XMLExtendedStreamWriter.writeEndElement:()V
      64: return
}
