Compiled from "PageStore.java"
public class org.h2.store.PageStore implements org.h2.util.CacheWriter {
  public static final int PAGE_SIZE_MIN;

  public static final int PAGE_SIZE_MAX;

  public static final int LOG_MODE_OFF;

  public static final int LOG_MODE_SYNC;

  private static final int PAGE_ID_FREE_LIST_ROOT;

  private static final int PAGE_ID_META_ROOT;

  private static final int MIN_PAGE_COUNT;

  private static final int INCREMENT_KB;

  private static final int INCREMENT_PERCENT_MIN;

  private static final int READ_VERSION;

  private static final int WRITE_VERSION;

  private static final int META_TYPE_DATA_INDEX;

  private static final int META_TYPE_BTREE_INDEX;

  private static final int META_TABLE_ID;

  private static final int COMPACT_BLOCK_SIZE;

  private final org.h2.engine.Database database;

  private final org.h2.message.Trace trace;

  private final java.lang.String fileName;

  private org.h2.store.FileStore file;

  private java.lang.String accessMode;

  private int pageSize;

  private int pageSizeShift;

  private long writeCountBase;

  private long writeCount;

  private long readCount;

  private int logKey;

  private int logFirstTrunkPage;

  private int logFirstDataPage;

  private final org.h2.util.Cache cache;

  private int freeListPagesPerList;

  private boolean recoveryRunning;

  private boolean ignoreBigLog;

  private int firstFreeListIndex;

  private long fileLength;

  private int pageCount;

  private org.h2.store.PageLog log;

  private org.h2.schema.Schema metaSchema;

  private org.h2.table.RegularTable metaTable;

  private org.h2.index.PageDataIndex metaIndex;

  private final org.h2.util.IntIntHashMap metaRootPageId;

  private final java.util.HashMap<java.lang.Integer, org.h2.index.PageIndex> metaObjects;

  private java.util.HashMap<java.lang.Integer, org.h2.index.PageIndex> tempObjects;

  private java.util.HashMap<java.lang.Integer, java.lang.Integer> reservedPages;

  private boolean isNew;

  private long maxLogSize;

  private final org.h2.engine.Session pageStoreSession;

  private final org.h2.util.BitField freed;

  private final java.util.ArrayList<org.h2.store.PageFreeList> freeLists;

  private boolean recordPageReads;

  private java.util.ArrayList<java.lang.Integer> recordedPagesList;

  private org.h2.util.IntIntHashMap recordedPagesIndex;

  private long changeCount;

  private org.h2.store.Data emptyPage;

  private long logSizeBase;

  private java.util.HashMap<java.lang.String, java.lang.Integer> statistics;

  private int logMode;

  private boolean lockFile;

  private boolean readMode;

  private int backupLevel;

  public org.h2.store.PageStore(org.h2.engine.Database, java.lang.String, java.lang.String, int);
    Code:
       0: aload_0
       1: invokespecial #1                  // Method java/lang/Object."<init>":()V
       4: aload_0
       5: sipush        4096
       8: putfield      #2                  // Field pageSize:I
      11: aload_0
      12: new           #3                  // class org/h2/util/IntIntHashMap
      15: dup
      16: invokespecial #4                  // Method org/h2/util/IntIntHashMap."<init>":()V
      19: putfield      #5                  // Field metaRootPageId:Lorg/h2/util/IntIntHashMap;
      22: aload_0
      23: new           #6                  // class java/util/HashMap
      26: dup
      27: invokespecial #7                  // Method java/util/HashMap."<init>":()V
      30: putfield      #8                  // Field metaObjects:Ljava/util/HashMap;
      33: aload_0
      34: ldc2_w        #9                  // long 16777216l
      37: putfield      #11                 // Field maxLogSize:J
      40: aload_0
      41: new           #12                 // class org/h2/util/BitField
      44: dup
      45: invokespecial #13                 // Method org/h2/util/BitField."<init>":()V
      48: putfield      #14                 // Field freed:Lorg/h2/util/BitField;
      51: aload_0
      52: invokestatic  #15                 // Method org/h2/util/New.arrayList:()Ljava/util/ArrayList;
      55: putfield      #16                 // Field freeLists:Ljava/util/ArrayList;
      58: aload_0
      59: lconst_1
      60: putfield      #17                 // Field changeCount:J
      63: aload_0
      64: iconst_2
      65: putfield      #18                 // Field logMode:I
      68: aload_0
      69: aload_2
      70: putfield      #19                 // Field fileName:Ljava/lang/String;
      73: aload_0
      74: aload_3
      75: putfield      #20                 // Field accessMode:Ljava/lang/String;
      78: aload_0
      79: aload_1
      80: putfield      #21                 // Field database:Lorg/h2/engine/Database;
      83: aload_0
      84: aload_1
      85: bipush        14
      87: invokevirtual #22                 // Method org/h2/engine/Database.getTrace:(I)Lorg/h2/message/Trace;
      90: putfield      #23                 // Field trace:Lorg/h2/message/Trace;
      93: aload_1
      94: invokevirtual #24                 // Method org/h2/engine/Database.getCacheType:()Ljava/lang/String;
      97: astore        5
      99: aload_0
     100: aload_0
     101: aload         5
     103: iload         4
     105: invokestatic  #25                 // Method org/h2/util/CacheLRU.getCache:(Lorg/h2/util/CacheWriter;Ljava/lang/String;I)Lorg/h2/util/Cache;
     108: putfield      #26                 // Field cache:Lorg/h2/util/Cache;
     111: aload_0
     112: new           #27                 // class org/h2/engine/Session
     115: dup
     116: aload_1
     117: aconst_null
     118: iconst_0
     119: invokespecial #28                 // Method org/h2/engine/Session."<init>":(Lorg/h2/engine/Database;Lorg/h2/engine/User;I)V
     122: putfield      #29                 // Field pageStoreSession:Lorg/h2/engine/Session;
     125: return

  public void statisticsStart();
    Code:
       0: aload_0
       1: new           #6                  // class java/util/HashMap
       4: dup
       5: invokespecial #7                  // Method java/util/HashMap."<init>":()V
       8: putfield      #30                 // Field statistics:Ljava/util/HashMap;
      11: return

  public java.util.HashMap<java.lang.String, java.lang.Integer> statisticsEnd();
    Code:
       0: aload_0
       1: getfield      #30                 // Field statistics:Ljava/util/HashMap;
       4: astore_1
       5: aload_0
       6: aconst_null
       7: putfield      #30                 // Field statistics:Ljava/util/HashMap;
      10: aload_1
      11: areturn

  private void statisticsIncrement(java.lang.String);
    Code:
       0: aload_0
       1: getfield      #30                 // Field statistics:Ljava/util/HashMap;
       4: ifnull        45
       7: aload_0
       8: getfield      #30                 // Field statistics:Ljava/util/HashMap;
      11: aload_1
      12: invokevirtual #31                 // Method java/util/HashMap.get:(Ljava/lang/Object;)Ljava/lang/Object;
      15: checkcast     #32                 // class java/lang/Integer
      18: astore_2
      19: aload_0
      20: getfield      #30                 // Field statistics:Ljava/util/HashMap;
      23: aload_1
      24: aload_2
      25: ifnonnull     32
      28: iconst_1
      29: goto          38
      32: aload_2
      33: invokevirtual #33                 // Method java/lang/Integer.intValue:()I
      36: iconst_1
      37: iadd
      38: invokestatic  #34                 // Method java/lang/Integer.valueOf:(I)Ljava/lang/Integer;
      41: invokevirtual #35                 // Method java/util/HashMap.put:(Ljava/lang/Object;Ljava/lang/Object;)Ljava/lang/Object;
      44: pop
      45: return

  public synchronized int copyDirect(int, java.io.OutputStream) throws java.io.IOException;
    Code:
       0: aload_0
       1: getfield      #2                  // Field pageSize:I
       4: newarray       byte
       6: astore_3
       7: iload_1
       8: aload_0
       9: getfield      #36                 // Field pageCount:I
      12: if_icmplt     17
      15: iconst_m1
      16: ireturn
      17: aload_0
      18: getfield      #37                 // Field file:Lorg/h2/store/FileStore;
      21: iload_1
      22: i2l
      23: aload_0
      24: getfield      #38                 // Field pageSizeShift:I
      27: lshl
      28: invokevirtual #39                 // Method org/h2/store/FileStore.seek:(J)V
      31: aload_0
      32: getfield      #37                 // Field file:Lorg/h2/store/FileStore;
      35: aload_3
      36: iconst_0
      37: aload_0
      38: getfield      #2                  // Field pageSize:I
      41: invokevirtual #40                 // Method org/h2/store/FileStore.readFullyDirect:([BII)V
      44: aload_0
      45: dup
      46: getfield      #41                 // Field readCount:J
      49: lconst_1
      50: ladd
      51: putfield      #41                 // Field readCount:J
      54: aload_2
      55: aload_3
      56: iconst_0
      57: aload_0
      58: getfield      #2                  // Field pageSize:I
      61: invokevirtual #42                 // Method java/io/OutputStream.write:([BII)V
      64: iload_1
      65: iconst_1
      66: iadd
      67: ireturn

  public synchronized void open();
    Code:
       0: aload_0
       1: getfield      #5                  // Field metaRootPageId:Lorg/h2/util/IntIntHashMap;
       4: iconst_m1
       5: iconst_4
       6: invokevirtual #43                 // Method org/h2/util/IntIntHashMap.put:(II)V
       9: aload_0
      10: getfield      #19                 // Field fileName:Ljava/lang/String;
      13: invokestatic  #44                 // Method org/h2/store/fs/FileUtils.exists:(Ljava/lang/String;)Z
      16: ifeq          91
      19: aload_0
      20: getfield      #19                 // Field fileName:Ljava/lang/String;
      23: invokestatic  #45                 // Method org/h2/store/fs/FileUtils.size:(Ljava/lang/String;)J
      26: lstore_1
      27: lload_1
      28: ldc2_w        #46                 // long 320l
      31: lcmp
      32: ifge          84
      35: aload_0
      36: getfield      #21                 // Field database:Lorg/h2/engine/Database;
      39: invokevirtual #48                 // Method org/h2/engine/Database.isReadOnly:()Z
      42: ifeq          77
      45: ldc           #49                 // int 90030
      47: new           #50                 // class java/lang/StringBuilder
      50: dup
      51: invokespecial #51                 // Method java/lang/StringBuilder."<init>":()V
      54: aload_0
      55: getfield      #19                 // Field fileName:Ljava/lang/String;
      58: invokevirtual #52                 // Method java/lang/StringBuilder.append:(Ljava/lang/String;)Ljava/lang/StringBuilder;
      61: ldc           #53                 // String  length:
      63: invokevirtual #52                 // Method java/lang/StringBuilder.append:(Ljava/lang/String;)Ljava/lang/StringBuilder;
      66: lload_1
      67: invokevirtual #54                 // Method java/lang/StringBuilder.append:(J)Ljava/lang/StringBuilder;
      70: invokevirtual #55                 // Method java/lang/StringBuilder.toString:()Ljava/lang/String;
      73: invokestatic  #56                 // Method org/h2/message/DbException.get:(ILjava/lang/String;)Lorg/h2/message/DbException;
      76: athrow
      77: aload_0
      78: invokespecial #57                 // Method openNew:()V
      81: goto          88
      84: aload_0
      85: invokespecial #58                 // Method openExisting:()V
      88: goto          95
      91: aload_0
      92: invokespecial #57                 // Method openNew:()V
      95: goto          105
      98: astore_1
      99: aload_0
     100: invokevirtual #60                 // Method close:()V
     103: aload_1
     104: athrow
     105: return
    Exception table:
       from    to  target type
           0    95    98   Class org/h2/message/DbException

  private void openNew();
    Code:
       0: aload_0
       1: aload_0
       2: getfield      #2                  // Field pageSize:I
       5: invokevirtual #61                 // Method setPageSize:(I)V
       8: aload_0
       9: aload_0
      10: getfield      #2                  // Field pageSize:I
      13: invokestatic  #62                 // Method org/h2/store/PageFreeList.getPagesAddressed:(I)I
      16: putfield      #63                 // Field freeListPagesPerList:I
      19: aload_0
      20: aload_0
      21: getfield      #21                 // Field database:Lorg/h2/engine/Database;
      24: aload_0
      25: getfield      #19                 // Field fileName:Ljava/lang/String;
      28: aload_0
      29: getfield      #20                 // Field accessMode:Ljava/lang/String;
      32: iconst_0
      33: invokevirtual #64                 // Method org/h2/engine/Database.openFile:(Ljava/lang/String;Ljava/lang/String;Z)Lorg/h2/store/FileStore;
      36: putfield      #37                 // Field file:Lorg/h2/store/FileStore;
      39: aload_0
      40: invokespecial #65                 // Method lockFile:()V
      43: aload_0
      44: iconst_1
      45: putfield      #66                 // Field recoveryRunning:Z
      48: aload_0
      49: invokespecial #67                 // Method writeStaticHeader:()V
      52: aload_0
      53: invokespecial #68                 // Method writeVariableHeader:()V
      56: aload_0
      57: new           #69                 // class org/h2/store/PageLog
      60: dup
      61: aload_0
      62: invokespecial #70                 // Method org/h2/store/PageLog."<init>":(Lorg/h2/store/PageStore;)V
      65: putfield      #71                 // Field log:Lorg/h2/store/PageLog;
      68: aload_0
      69: iconst_5
      70: invokespecial #72                 // Method increaseFileSize:(I)V
      73: aload_0
      74: invokespecial #73                 // Method openMetaIndex:()V
      77: aload_0
      78: aload_0
      79: invokevirtual #74                 // Method allocatePage:()I
      82: putfield      #75                 // Field logFirstTrunkPage:I
      85: aload_0
      86: getfield      #71                 // Field log:Lorg/h2/store/PageLog;
      89: aload_0
      90: getfield      #75                 // Field logFirstTrunkPage:I
      93: iconst_0
      94: invokevirtual #76                 // Method org/h2/store/PageLog.openForWriting:(IZ)V
      97: aload_0
      98: iconst_1
      99: putfield      #77                 // Field isNew:Z
     102: aload_0
     103: iconst_0
     104: putfield      #66                 // Field recoveryRunning:Z
     107: aload_0
     108: invokespecial #78                 // Method increaseFileSize:()V
     111: return

  private void lockFile();
    Code:
       0: aload_0
       1: getfield      #79                 // Field lockFile:Z
       4: ifeq          27
       7: aload_0
       8: getfield      #37                 // Field file:Lorg/h2/store/FileStore;
      11: invokevirtual #80                 // Method org/h2/store/FileStore.tryLock:()Z
      14: ifne          27
      17: ldc           #81                 // int 90020
      19: aload_0
      20: getfield      #19                 // Field fileName:Ljava/lang/String;
      23: invokestatic  #56                 // Method org/h2/message/DbException.get:(ILjava/lang/String;)Lorg/h2/message/DbException;
      26: athrow
      27: return

  private void openExisting();
    Code:
       0: aload_0
       1: aload_0
       2: getfield      #21                 // Field database:Lorg/h2/engine/Database;
       5: aload_0
       6: getfield      #19                 // Field fileName:Ljava/lang/String;
       9: aload_0
      10: getfield      #20                 // Field accessMode:Ljava/lang/String;
      13: iconst_1
      14: invokevirtual #64                 // Method org/h2/engine/Database.openFile:(Ljava/lang/String;Ljava/lang/String;Z)Lorg/h2/store/FileStore;
      17: putfield      #37                 // Field file:Lorg/h2/store/FileStore;
      20: goto          65
      23: astore_1
      24: aload_1
      25: invokevirtual #82                 // Method org/h2/message/DbException.getErrorCode:()I
      28: ldc           #83                 // int 90031
      30: if_icmpne     63
      33: aload_1
      34: invokevirtual #84                 // Method org/h2/message/DbException.getMessage:()Ljava/lang/String;
      37: ldc           #85                 // String locked
      39: invokevirtual #86                 // Method java/lang/String.contains:(Ljava/lang/CharSequence;)Z
      42: ifeq          63
      45: ldc           #81                 // int 90020
      47: aload_1
      48: iconst_1
      49: anewarray     #87                 // class java/lang/String
      52: dup
      53: iconst_0
      54: aload_0
      55: getfield      #19                 // Field fileName:Ljava/lang/String;
      58: aastore
      59: invokestatic  #88                 // Method org/h2/message/DbException.get:(ILjava/lang/Throwable;[Ljava/lang/String;)Lorg/h2/message/DbException;
      62: athrow
      63: aload_1
      64: athrow
      65: aload_0
      66: invokespecial #65                 // Method lockFile:()V
      69: aload_0
      70: invokespecial #89                 // Method readStaticHeader:()V
      73: aload_0
      74: aload_0
      75: getfield      #2                  // Field pageSize:I
      78: invokestatic  #62                 // Method org/h2/store/PageFreeList.getPagesAddressed:(I)I
      81: putfield      #63                 // Field freeListPagesPerList:I
      84: aload_0
      85: aload_0
      86: getfield      #37                 // Field file:Lorg/h2/store/FileStore;
      89: invokevirtual #90                 // Method org/h2/store/FileStore.length:()J
      92: putfield      #91                 // Field fileLength:J
      95: aload_0
      96: aload_0
      97: getfield      #91                 // Field fileLength:J
     100: aload_0
     101: getfield      #2                  // Field pageSize:I
     104: i2l
     105: ldiv
     106: l2i
     107: putfield      #36                 // Field pageCount:I
     110: aload_0
     111: getfield      #36                 // Field pageCount:I
     114: iconst_5
     115: if_icmpge     189
     118: aload_0
     119: getfield      #21                 // Field database:Lorg/h2/engine/Database;
     122: invokevirtual #48                 // Method org/h2/engine/Database.isReadOnly:()Z
     125: ifeq          163
     128: ldc           #49                 // int 90030
     130: new           #50                 // class java/lang/StringBuilder
     133: dup
     134: invokespecial #51                 // Method java/lang/StringBuilder."<init>":()V
     137: aload_0
     138: getfield      #19                 // Field fileName:Ljava/lang/String;
     141: invokevirtual #52                 // Method java/lang/StringBuilder.append:(Ljava/lang/String;)Ljava/lang/StringBuilder;
     144: ldc           #92                 // String  pageCount:
     146: invokevirtual #52                 // Method java/lang/StringBuilder.append:(Ljava/lang/String;)Ljava/lang/StringBuilder;
     149: aload_0
     150: getfield      #36                 // Field pageCount:I
     153: invokevirtual #93                 // Method java/lang/StringBuilder.append:(I)Ljava/lang/StringBuilder;
     156: invokevirtual #55                 // Method java/lang/StringBuilder.toString:()Ljava/lang/String;
     159: invokestatic  #56                 // Method org/h2/message/DbException.get:(ILjava/lang/String;)Lorg/h2/message/DbException;
     162: athrow
     163: aload_0
     164: getfield      #37                 // Field file:Lorg/h2/store/FileStore;
     167: invokevirtual #94                 // Method org/h2/store/FileStore.releaseLock:()V
     170: aload_0
     171: getfield      #37                 // Field file:Lorg/h2/store/FileStore;
     174: invokevirtual #95                 // Method org/h2/store/FileStore.close:()V
     177: aload_0
     178: getfield      #19                 // Field fileName:Ljava/lang/String;
     181: invokestatic  #96                 // Method org/h2/store/fs/FileUtils.delete:(Ljava/lang/String;)V
     184: aload_0
     185: invokespecial #57                 // Method openNew:()V
     188: return
     189: aload_0
     190: invokespecial #97                 // Method readVariableHeader:()V
     193: aload_0
     194: new           #69                 // class org/h2/store/PageLog
     197: dup
     198: aload_0
     199: invokespecial #70                 // Method org/h2/store/PageLog."<init>":(Lorg/h2/store/PageStore;)V
     202: putfield      #71                 // Field log:Lorg/h2/store/PageLog;
     205: aload_0
     206: getfield      #71                 // Field log:Lorg/h2/store/PageLog;
     209: aload_0
     210: getfield      #98                 // Field logKey:I
     213: aload_0
     214: getfield      #75                 // Field logFirstTrunkPage:I
     217: aload_0
     218: getfield      #99                 // Field logFirstDataPage:I
     221: invokevirtual #100                // Method org/h2/store/PageLog.openForReading:(III)V
     224: aload_0
     225: getfield      #21                 // Field database:Lorg/h2/engine/Database;
     228: invokevirtual #101                // Method org/h2/engine/Database.isMultiVersion:()Z
     231: istore_1
     232: aload_0
     233: getfield      #21                 // Field database:Lorg/h2/engine/Database;
     236: iconst_0
     237: invokevirtual #102                // Method org/h2/engine/Database.setMultiVersion:(Z)V
     240: aload_0
     241: invokespecial #103                // Method recover:()Z
     244: istore_2
     245: aload_0
     246: getfield      #21                 // Field database:Lorg/h2/engine/Database;
     249: iload_1
     250: invokevirtual #102                // Method org/h2/engine/Database.setMultiVersion:(Z)V
     253: aload_0
     254: getfield      #21                 // Field database:Lorg/h2/engine/Database;
     257: invokevirtual #48                 // Method org/h2/engine/Database.isReadOnly:()Z
     260: ifne          293
     263: aload_0
     264: iconst_1
     265: putfield      #104                // Field readMode:Z
     268: iload_2
     269: ifeq          285
     272: getstatic     #105                // Field org/h2/engine/SysProperties.MODIFY_ON_WRITE:Z
     275: ifeq          285
     278: aload_0
     279: getfield      #106                // Field tempObjects:Ljava/util/HashMap;
     282: ifnull        293
     285: aload_0
     286: invokespecial #107                // Method openForWriting:()V
     289: aload_0
     290: invokespecial #108                // Method removeOldTempIndexes:()V
     293: return
    Exception table:
       from    to  target type
           0    20    23   Class org/h2/message/DbException

  private void openForWriting();
    Code:
       0: aload_0
       1: getfield      #104                // Field readMode:Z
       4: ifeq          17
       7: aload_0
       8: getfield      #21                 // Field database:Lorg/h2/engine/Database;
      11: invokevirtual #48                 // Method org/h2/engine/Database.isReadOnly:()Z
      14: ifeq          18
      17: return
      18: aload_0
      19: iconst_0
      20: putfield      #104                // Field readMode:Z
      23: aload_0
      24: iconst_1
      25: putfield      #66                 // Field recoveryRunning:Z
      28: aload_0
      29: getfield      #71                 // Field log:Lorg/h2/store/PageLog;
      32: invokevirtual #109                // Method org/h2/store/PageLog.free:()V
      35: aload_0
      36: aload_0
      37: invokevirtual #74                 // Method allocatePage:()I
      40: putfield      #75                 // Field logFirstTrunkPage:I
      43: aload_0
      44: getfield      #71                 // Field log:Lorg/h2/store/PageLog;
      47: aload_0
      48: getfield      #75                 // Field logFirstTrunkPage:I
      51: iconst_0
      52: invokevirtual #76                 // Method org/h2/store/PageLog.openForWriting:(IZ)V
      55: aload_0
      56: iconst_0
      57: putfield      #66                 // Field recoveryRunning:Z
      60: aload_0
      61: getfield      #14                 // Field freed:Lorg/h2/util/BitField;
      64: iconst_0
      65: aload_0
      66: getfield      #36                 // Field pageCount:I
      69: iconst_1
      70: invokevirtual #110                // Method org/h2/util/BitField.set:(IIZ)V
      73: aload_0
      74: invokevirtual #111                // Method checkpoint:()V
      77: return

  private void removeOldTempIndexes();
    Code:
       0: aload_0
       1: getfield      #106                // Field tempObjects:Ljava/util/HashMap;
       4: ifnull        92
       7: aload_0
       8: getfield      #8                  // Field metaObjects:Ljava/util/HashMap;
      11: aload_0
      12: getfield      #106                // Field tempObjects:Ljava/util/HashMap;
      15: invokevirtual #112                // Method java/util/HashMap.putAll:(Ljava/util/Map;)V
      18: aload_0
      19: getfield      #106                // Field tempObjects:Ljava/util/HashMap;
      22: invokevirtual #113                // Method java/util/HashMap.values:()Ljava/util/Collection;
      25: invokeinterface #114,  1          // InterfaceMethod java/util/Collection.iterator:()Ljava/util/Iterator;
      30: astore_1
      31: aload_1
      32: invokeinterface #115,  1          // InterfaceMethod java/util/Iterator.hasNext:()Z
      37: ifeq          79
      40: aload_1
      41: invokeinterface #116,  1          // InterfaceMethod java/util/Iterator.next:()Ljava/lang/Object;
      46: checkcast     #117                // class org/h2/index/PageIndex
      49: astore_2
      50: aload_2
      51: invokevirtual #118                // Method org/h2/index/PageIndex.getTable:()Lorg/h2/table/Table;
      54: invokevirtual #119                // Method org/h2/table/Table.isTemporary:()Z
      57: ifeq          76
      60: aload_2
      61: aload_0
      62: getfield      #29                 // Field pageStoreSession:Lorg/h2/engine/Session;
      65: invokevirtual #120                // Method org/h2/index/PageIndex.truncate:(Lorg/h2/engine/Session;)V
      68: aload_2
      69: aload_0
      70: getfield      #29                 // Field pageStoreSession:Lorg/h2/engine/Session;
      73: invokevirtual #121                // Method org/h2/index/PageIndex.remove:(Lorg/h2/engine/Session;)V
      76: goto          31
      79: aload_0
      80: getfield      #29                 // Field pageStoreSession:Lorg/h2/engine/Session;
      83: iconst_1
      84: invokevirtual #122                // Method org/h2/engine/Session.commit:(Z)V
      87: aload_0
      88: aconst_null
      89: putfield      #106                // Field tempObjects:Ljava/util/HashMap;
      92: aload_0
      93: getfield      #8                  // Field metaObjects:Ljava/util/HashMap;
      96: invokevirtual #123                // Method java/util/HashMap.clear:()V
      99: aload_0
     100: getfield      #8                  // Field metaObjects:Ljava/util/HashMap;
     103: iconst_m1
     104: invokestatic  #34                 // Method java/lang/Integer.valueOf:(I)Ljava/lang/Integer;
     107: aload_0
     108: getfield      #124                // Field metaIndex:Lorg/h2/index/PageDataIndex;
     111: invokevirtual #35                 // Method java/util/HashMap.put:(Ljava/lang/Object;Ljava/lang/Object;)Ljava/lang/Object;
     114: pop
     115: return

  private void writeIndexRowCounts();
    Code:
       0: aload_0
       1: getfield      #8                  // Field metaObjects:Ljava/util/HashMap;
       4: invokevirtual #113                // Method java/util/HashMap.values:()Ljava/util/Collection;
       7: invokeinterface #114,  1          // InterfaceMethod java/util/Collection.iterator:()Ljava/util/Iterator;
      12: astore_1
      13: aload_1
      14: invokeinterface #115,  1          // InterfaceMethod java/util/Iterator.hasNext:()Z
      19: ifeq          39
      22: aload_1
      23: invokeinterface #116,  1          // InterfaceMethod java/util/Iterator.next:()Ljava/lang/Object;
      28: checkcast     #117                // class org/h2/index/PageIndex
      31: astore_2
      32: aload_2
      33: invokevirtual #125                // Method org/h2/index/PageIndex.writeRowCount:()V
      36: goto          13
      39: return

  private void writeBack();
    Code:
       0: aload_0
       1: getfield      #26                 // Field cache:Lorg/h2/util/Cache;
       4: invokeinterface #126,  1          // InterfaceMethod org/h2/util/Cache.getAllChanged:()Ljava/util/ArrayList;
       9: astore_1
      10: aload_1
      11: invokestatic  #127                // Method java/util/Collections.sort:(Ljava/util/List;)V
      14: aload_1
      15: invokevirtual #128                // Method java/util/ArrayList.iterator:()Ljava/util/Iterator;
      18: astore_2
      19: aload_2
      20: invokeinterface #115,  1          // InterfaceMethod java/util/Iterator.hasNext:()Z
      25: ifeq          46
      28: aload_2
      29: invokeinterface #116,  1          // InterfaceMethod java/util/Iterator.next:()Ljava/lang/Object;
      34: checkcast     #129                // class org/h2/util/CacheObject
      37: astore_3
      38: aload_0
      39: aload_3
      40: invokevirtual #130                // Method writeBack:(Lorg/h2/util/CacheObject;)V
      43: goto          19
      46: return

  public synchronized void checkpoint();
    Code:
       0: aload_0
       1: getfield      #23                 // Field trace:Lorg/h2/message/Trace;
       4: ldc           #131                // String checkpoint
       6: invokevirtual #132                // Method org/h2/message/Trace.debug:(Ljava/lang/String;)V
       9: aload_0
      10: getfield      #71                 // Field log:Lorg/h2/store/PageLog;
      13: ifnull        40
      16: aload_0
      17: getfield      #104                // Field readMode:Z
      20: ifne          40
      23: aload_0
      24: getfield      #21                 // Field database:Lorg/h2/engine/Database;
      27: invokevirtual #48                 // Method org/h2/engine/Database.isReadOnly:()Z
      30: ifne          40
      33: aload_0
      34: getfield      #133                // Field backupLevel:I
      37: ifle          41
      40: return
      41: aload_0
      42: getfield      #21                 // Field database:Lorg/h2/engine/Database;
      45: invokevirtual #134                // Method org/h2/engine/Database.checkPowerOff:()V
      48: aload_0
      49: invokespecial #135                // Method writeIndexRowCounts:()V
      52: aload_0
      53: getfield      #71                 // Field log:Lorg/h2/store/PageLog;
      56: invokevirtual #136                // Method org/h2/store/PageLog.checkpoint:()V
      59: aload_0
      60: invokespecial #137                // Method writeBack:()V
      63: aload_0
      64: invokespecial #138                // Method getFirstUncommittedSection:()I
      67: istore_1
      68: aload_0
      69: getfield      #71                 // Field log:Lorg/h2/store/PageLog;
      72: iload_1
      73: invokevirtual #139                // Method org/h2/store/PageLog.removeUntil:(I)V
      76: aload_0
      77: invokespecial #137                // Method writeBack:()V
      80: aload_0
      81: getfield      #71                 // Field log:Lorg/h2/store/PageLog;
      84: invokevirtual #136                // Method org/h2/store/PageLog.checkpoint:()V
      87: aload_0
      88: getfield      #23                 // Field trace:Lorg/h2/message/Trace;
      91: invokevirtual #140                // Method org/h2/message/Trace.isDebugEnabled:()Z
      94: ifeq          106
      97: aload_0
      98: getfield      #23                 // Field trace:Lorg/h2/message/Trace;
     101: ldc           #141                // String writeFree
     103: invokevirtual #132                // Method org/h2/message/Trace.debug:(Ljava/lang/String;)V
     106: bipush        16
     108: newarray       byte
     110: astore_2
     111: aload_0
     112: getfield      #2                  // Field pageSize:I
     115: newarray       byte
     117: astore_3
     118: iconst_3
     119: istore        4
     121: iload         4
     123: aload_0
     124: getfield      #36                 // Field pageCount:I
     127: if_icmpge     285
     130: aload_0
     131: iload         4
     133: invokespecial #142                // Method isUsed:(I)Z
     136: ifeq          151
     139: aload_0
     140: getfield      #14                 // Field freed:Lorg/h2/util/BitField;
     143: iload         4
     145: invokevirtual #143                // Method org/h2/util/BitField.clear:(I)V
     148: goto          279
     151: aload_0
     152: getfield      #14                 // Field freed:Lorg/h2/util/BitField;
     155: iload         4
     157: invokevirtual #144                // Method org/h2/util/BitField.get:(I)Z
     160: ifne          279
     163: aload_0
     164: getfield      #23                 // Field trace:Lorg/h2/message/Trace;
     167: invokevirtual #140                // Method org/h2/message/Trace.isDebugEnabled:()Z
     170: ifeq          200
     173: aload_0
     174: getfield      #23                 // Field trace:Lorg/h2/message/Trace;
     177: new           #50                 // class java/lang/StringBuilder
     180: dup
     181: invokespecial #51                 // Method java/lang/StringBuilder."<init>":()V
     184: ldc           #145                // String free
     186: invokevirtual #52                 // Method java/lang/StringBuilder.append:(Ljava/lang/String;)Ljava/lang/StringBuilder;
     189: iload         4
     191: invokevirtual #93                 // Method java/lang/StringBuilder.append:(I)Ljava/lang/StringBuilder;
     194: invokevirtual #55                 // Method java/lang/StringBuilder.toString:()Ljava/lang/String;
     197: invokevirtual #132                // Method org/h2/message/Trace.debug:(Ljava/lang/String;)V
     200: aload_0
     201: getfield      #37                 // Field file:Lorg/h2/store/FileStore;
     204: iload         4
     206: i2l
     207: aload_0
     208: getfield      #38                 // Field pageSizeShift:I
     211: lshl
     212: invokevirtual #39                 // Method org/h2/store/FileStore.seek:(J)V
     215: aload_0
     216: getfield      #37                 // Field file:Lorg/h2/store/FileStore;
     219: aload_2
     220: iconst_0
     221: bipush        16
     223: invokevirtual #146                // Method org/h2/store/FileStore.readFully:([BII)V
     226: aload_2
     227: iconst_0
     228: baload
     229: ifeq          270
     232: aload_0
     233: getfield      #37                 // Field file:Lorg/h2/store/FileStore;
     236: iload         4
     238: i2l
     239: aload_0
     240: getfield      #38                 // Field pageSizeShift:I
     243: lshl
     244: invokevirtual #39                 // Method org/h2/store/FileStore.seek:(J)V
     247: aload_0
     248: getfield      #37                 // Field file:Lorg/h2/store/FileStore;
     251: aload_3
     252: iconst_0
     253: aload_0
     254: getfield      #2                  // Field pageSize:I
     257: invokevirtual #147                // Method org/h2/store/FileStore.write:([BII)V
     260: aload_0
     261: dup
     262: getfield      #148                // Field writeCount:J
     265: lconst_1
     266: ladd
     267: putfield      #148                // Field writeCount:J
     270: aload_0
     271: getfield      #14                 // Field freed:Lorg/h2/util/BitField;
     274: iload         4
     276: invokevirtual #149                // Method org/h2/util/BitField.set:(I)V
     279: iinc          4, 1
     282: goto          121
     285: return

  public synchronized void compact(int);
    Code:
       0: aload_0
       1: getfield      #21                 // Field database:Lorg/h2/engine/Database;
       4: invokevirtual #150                // Method org/h2/engine/Database.getSettings:()Lorg/h2/engine/DbSettings;
       7: getfield      #151                // Field org/h2/engine/DbSettings.pageStoreTrim:Z
      10: ifne          14
      13: return
      14: getstatic     #105                // Field org/h2/engine/SysProperties.MODIFY_ON_WRITE:Z
      17: ifeq          32
      20: aload_0
      21: getfield      #104                // Field readMode:Z
      24: ifeq          32
      27: iload_1
      28: ifne          32
      31: return
      32: aload_0
      33: invokespecial #107                // Method openForWriting:()V
      36: iconst_m1
      37: istore_2
      38: aload_0
      39: aload_0
      40: getfield      #36                 // Field pageCount:I
      43: invokespecial #152                // Method getFreeListId:(I)I
      46: istore_3
      47: iload_3
      48: iflt          74
      51: aload_0
      52: iload_3
      53: invokespecial #153                // Method getFreeList:(I)Lorg/h2/store/PageFreeList;
      56: invokevirtual #154                // Method org/h2/store/PageFreeList.getLastUsed:()I
      59: istore_2
      60: iload_2
      61: iconst_m1
      62: if_icmpeq     68
      65: goto          74
      68: iinc          3, -1
      71: goto          47
      74: aload_0
      75: invokespecial #137                // Method writeBack:()V
      78: aload_0
      79: getfield      #71                 // Field log:Lorg/h2/store/PageLog;
      82: invokevirtual #109                // Method org/h2/store/PageLog.free:()V
      85: aload_0
      86: iconst_1
      87: putfield      #66                 // Field recoveryRunning:Z
      90: aload_0
      91: iload_2
      92: iconst_1
      93: iadd
      94: putfield      #75                 // Field logFirstTrunkPage:I
      97: aload_0
      98: aload_0
      99: getfield      #75                 // Field logFirstTrunkPage:I
     102: invokevirtual #155                // Method allocatePage:(I)V
     105: aload_0
     106: getfield      #71                 // Field log:Lorg/h2/store/PageLog;
     109: aload_0
     110: getfield      #75                 // Field logFirstTrunkPage:I
     113: iconst_1
     114: invokevirtual #76                 // Method org/h2/store/PageLog.openForWriting:(IZ)V
     117: aload_0
     118: getfield      #71                 // Field log:Lorg/h2/store/PageLog;
     121: invokevirtual #136                // Method org/h2/store/PageLog.checkpoint:()V
     124: aload_0
     125: iconst_0
     126: putfield      #66                 // Field recoveryRunning:Z
     129: goto          142
     132: astore        4
     134: aload_0
     135: iconst_0
     136: putfield      #66                 // Field recoveryRunning:Z
     139: aload         4
     141: athrow
     142: invokestatic  #156                // Method java/lang/System.nanoTime:()J
     145: lstore_3
     146: iload_1
     147: bipush        82
     149: if_icmpne     156
     152: iconst_1
     153: goto          157
     156: iconst_0
     157: istore        5
     159: iload_1
     160: bipush        84
     162: if_icmpne     169
     165: iconst_1
     166: goto          170
     169: iconst_0
     170: istore        6
     172: aload_0
     173: getfield      #21                 // Field database:Lorg/h2/engine/Database;
     176: invokevirtual #150                // Method org/h2/engine/Database.getSettings:()Lorg/h2/engine/DbSettings;
     179: getfield      #157                // Field org/h2/engine/DbSettings.defragAlways:Z
     182: ifeq          191
     185: iconst_1
     186: dup
     187: istore        6
     189: istore        5
     191: aload_0
     192: getfield      #21                 // Field database:Lorg/h2/engine/Database;
     195: invokevirtual #150                // Method org/h2/engine/Database.getSettings:()Lorg/h2/engine/DbSettings;
     198: getfield      #158                // Field org/h2/engine/DbSettings.maxCompactTime:I
     201: istore        7
     203: aload_0
     204: getfield      #21                 // Field database:Lorg/h2/engine/Database;
     207: invokevirtual #150                // Method org/h2/engine/Database.getSettings:()Lorg/h2/engine/DbSettings;
     210: getfield      #159                // Field org/h2/engine/DbSettings.maxCompactCount:I
     213: istore        8
     215: iload         5
     217: ifne          225
     220: iload         6
     222: ifeq          233
     225: ldc           #160                // int 2147483647
     227: istore        7
     229: ldc           #160                // int 2147483647
     231: istore        8
     233: iload         5
     235: ifeq          244
     238: sipush        1536
     241: goto          245
     244: iconst_1
     245: istore        9
     247: iconst_5
     248: istore        10
     250: iload_2
     251: istore        11
     253: iconst_0
     254: istore        12
     256: iload         11
     258: iconst_5
     259: if_icmple     412
     262: iload         12
     264: iload         8
     266: if_icmpge     412
     269: iload         11
     271: iload         9
     273: isub
     274: iconst_1
     275: iadd
     276: istore        13
     278: iload         13
     280: iload         11
     282: if_icmpgt     402
     285: iload         13
     287: iconst_5
     288: if_icmple     396
     291: aload_0
     292: iload         13
     294: invokespecial #142                // Method isUsed:(I)Z
     297: ifeq          396
     300: aload_0
     301: dup
     302: astore        14
     304: monitorenter
     305: aload_0
     306: iload         10
     308: invokespecial #161                // Method getFirstFree:(I)I
     311: istore        10
     313: iload         10
     315: iconst_m1
     316: if_icmpeq     326
     319: iload         10
     321: iload         13
     323: if_icmplt     336
     326: iload         8
     328: istore        12
     330: aload         14
     332: monitorexit
     333: goto          402
     336: aload_0
     337: iload         13
     339: iload         10
     341: invokespecial #162                // Method compact:(II)Z
     344: ifeq          382
     347: iinc          12, 1
     350: invokestatic  #156                // Method java/lang/System.nanoTime:()J
     353: lstore        15
     355: lload         15
     357: lload_3
     358: getstatic     #163                // Field java/util/concurrent/TimeUnit.MILLISECONDS:Ljava/util/concurrent/TimeUnit;
     361: iload         7
     363: i2l
     364: invokevirtual #164                // Method java/util/concurrent/TimeUnit.toNanos:(J)J
     367: ladd
     368: lcmp
     369: ifle          382
     372: iload         8
     374: istore        12
     376: aload         14
     378: monitorexit
     379: goto          402
     382: aload         14
     384: monitorexit
     385: goto          396
     388: astore        17
     390: aload         14
     392: monitorexit
     393: aload         17
     395: athrow
     396: iinc          13, 1
     399: goto          278
     402: iload         11
     404: iload         9
     406: isub
     407: istore        11
     409: goto          256
     412: iload         6
     414: ifeq          892
     417: aload_0
     418: getfield      #71                 // Field log:Lorg/h2/store/PageLog;
     421: invokevirtual #136                // Method org/h2/store/PageLog.checkpoint:()V
     424: aload_0
     425: invokespecial #137                // Method writeBack:()V
     428: aload_0
     429: getfield      #26                 // Field cache:Lorg/h2/util/Cache;
     432: invokeinterface #165,  1          // InterfaceMethod org/h2/util/Cache.clear:()V
     437: aload_0
     438: getfield      #21                 // Field database:Lorg/h2/engine/Database;
     441: iconst_0
     442: invokevirtual #166                // Method org/h2/engine/Database.getAllTablesAndViews:(Z)Ljava/util/ArrayList;
     445: astore        11
     447: aload_0
     448: invokestatic  #15                 // Method org/h2/util/New.arrayList:()Ljava/util/ArrayList;
     451: putfield      #167                // Field recordedPagesList:Ljava/util/ArrayList;
     454: aload_0
     455: new           #3                  // class org/h2/util/IntIntHashMap
     458: dup
     459: invokespecial #4                  // Method org/h2/util/IntIntHashMap."<init>":()V
     462: putfield      #168                // Field recordedPagesIndex:Lorg/h2/util/IntIntHashMap;
     465: aload_0
     466: iconst_1
     467: putfield      #169                // Field recordPageReads:Z
     470: aload_0
     471: getfield      #21                 // Field database:Lorg/h2/engine/Database;
     474: invokevirtual #170                // Method org/h2/engine/Database.getSystemSession:()Lorg/h2/engine/Session;
     477: astore        12
     479: aload         11
     481: invokevirtual #128                // Method java/util/ArrayList.iterator:()Ljava/util/Iterator;
     484: astore        13
     486: aload         13
     488: invokeinterface #115,  1          // InterfaceMethod java/util/Iterator.hasNext:()Z
     493: ifeq          651
     496: aload         13
     498: invokeinterface #116,  1          // InterfaceMethod java/util/Iterator.next:()Ljava/lang/Object;
     503: checkcast     #171                // class org/h2/table/Table
     506: astore        14
     508: aload         14
     510: invokevirtual #119                // Method org/h2/table/Table.isTemporary:()Z
     513: ifne          648
     516: getstatic     #172                // Field org/h2/table/TableType.TABLE:Lorg/h2/table/TableType;
     519: aload         14
     521: invokevirtual #173                // Method org/h2/table/Table.getTableType:()Lorg/h2/table/TableType;
     524: if_acmpne     648
     527: aload         14
     529: aload         12
     531: invokevirtual #174                // Method org/h2/table/Table.getScanIndex:(Lorg/h2/engine/Session;)Lorg/h2/index/Index;
     534: astore        15
     536: aload         15
     538: aload         12
     540: aconst_null
     541: aconst_null
     542: invokeinterface #175,  4          // InterfaceMethod org/h2/index/Index.find:(Lorg/h2/engine/Session;Lorg/h2/result/SearchRow;Lorg/h2/result/SearchRow;)Lorg/h2/index/Cursor;
     547: astore        16
     549: aload         16
     551: invokeinterface #176,  1          // InterfaceMethod org/h2/index/Cursor.next:()Z
     556: ifeq          570
     559: aload         16
     561: invokeinterface #177,  1          // InterfaceMethod org/h2/index/Cursor.get:()Lorg/h2/result/Row;
     566: pop
     567: goto          549
     570: aload         14
     572: invokevirtual #178                // Method org/h2/table/Table.getIndexes:()Ljava/util/ArrayList;
     575: invokevirtual #128                // Method java/util/ArrayList.iterator:()Ljava/util/Iterator;
     578: astore        17
     580: aload         17
     582: invokeinterface #115,  1          // InterfaceMethod java/util/Iterator.hasNext:()Z
     587: ifeq          648
     590: aload         17
     592: invokeinterface #116,  1          // InterfaceMethod java/util/Iterator.next:()Ljava/lang/Object;
     597: checkcast     #179                // class org/h2/index/Index
     600: astore        18
     602: aload         18
     604: aload         15
     606: if_acmpeq     645
     609: aload         18
     611: invokeinterface #180,  1          // InterfaceMethod org/h2/index/Index.canScan:()Z
     616: ifeq          645
     619: aload         18
     621: aload         12
     623: aconst_null
     624: aconst_null
     625: invokeinterface #175,  4          // InterfaceMethod org/h2/index/Index.find:(Lorg/h2/engine/Session;Lorg/h2/result/SearchRow;Lorg/h2/result/SearchRow;)Lorg/h2/index/Cursor;
     630: astore        16
     632: aload         16
     634: invokeinterface #176,  1          // InterfaceMethod org/h2/index/Cursor.next:()Z
     639: ifeq          645
     642: goto          632
     645: goto          580
     648: goto          486
     651: aload_0
     652: iconst_0
     653: putfield      #169                // Field recordPageReads:Z
     656: iconst_4
     657: istore        13
     659: iconst_0
     660: istore        14
     662: iconst_0
     663: istore        15
     665: aload_0
     666: getfield      #167                // Field recordedPagesList:Ljava/util/ArrayList;
     669: invokevirtual #181                // Method java/util/ArrayList.size:()I
     672: istore        16
     674: iload         15
     676: iload         16
     678: if_icmpge     882
     681: aload_0
     682: getfield      #71                 // Field log:Lorg/h2/store/PageLog;
     685: invokevirtual #136                // Method org/h2/store/PageLog.checkpoint:()V
     688: aload_0
     689: invokespecial #137                // Method writeBack:()V
     692: aload_0
     693: getfield      #167                // Field recordedPagesList:Ljava/util/ArrayList;
     696: iload         15
     698: invokevirtual #182                // Method java/util/ArrayList.get:(I)Ljava/lang/Object;
     701: checkcast     #32                 // class java/lang/Integer
     704: invokevirtual #33                 // Method java/lang/Integer.intValue:()I
     707: istore        17
     709: aload_0
     710: iload         17
     712: invokevirtual #183                // Method getPage:(I)Lorg/h2/store/Page;
     715: astore        18
     717: aload         18
     719: invokevirtual #184                // Method org/h2/store/Page.canMove:()Z
     722: ifne          728
     725: goto          876
     728: aload_0
     729: iinc          13, 1
     732: iload         13
     734: invokevirtual #183                // Method getPage:(I)Lorg/h2/store/Page;
     737: astore        19
     739: aload         19
     741: ifnull        758
     744: aload         19
     746: invokevirtual #184                // Method org/h2/store/Page.canMove:()Z
     749: ifeq          755
     752: goto          758
     755: goto          728
     758: iload         13
     760: iload         17
     762: if_icmpne     768
     765: goto          876
     768: aload_0
     769: iload         14
     771: invokespecial #161                // Method getFirstFree:(I)I
     774: istore        14
     776: iload         14
     778: iconst_m1
     779: if_icmpne     788
     782: ldc           #185                // String no free page for defrag
     784: invokestatic  #186                // Method org/h2/message/DbException.throwInternalError:(Ljava/lang/String;)Ljava/lang/RuntimeException;
     787: pop
     788: aload_0
     789: getfield      #26                 // Field cache:Lorg/h2/util/Cache;
     792: invokeinterface #165,  1          // InterfaceMethod org/h2/util/Cache.clear:()V
     797: aload_0
     798: iload         17
     800: iload         13
     802: iload         14
     804: invokespecial #187                // Method swap:(III)V
     807: aload_0
     808: getfield      #168                // Field recordedPagesIndex:Lorg/h2/util/IntIntHashMap;
     811: iload         13
     813: invokevirtual #188                // Method org/h2/util/IntIntHashMap.get:(I)I
     816: istore        19
     818: iload         19
     820: iconst_m1
     821: if_icmpeq     850
     824: aload_0
     825: getfield      #167                // Field recordedPagesList:Ljava/util/ArrayList;
     828: iload         19
     830: iload         17
     832: invokestatic  #34                 // Method java/lang/Integer.valueOf:(I)Ljava/lang/Integer;
     835: invokevirtual #189                // Method java/util/ArrayList.set:(ILjava/lang/Object;)Ljava/lang/Object;
     838: pop
     839: aload_0
     840: getfield      #168                // Field recordedPagesIndex:Lorg/h2/util/IntIntHashMap;
     843: iload         17
     845: iload         19
     847: invokevirtual #43                 // Method org/h2/util/IntIntHashMap.put:(II)V
     850: aload_0
     851: getfield      #167                // Field recordedPagesList:Ljava/util/ArrayList;
     854: iload         15
     856: iload         13
     858: invokestatic  #34                 // Method java/lang/Integer.valueOf:(I)Ljava/lang/Integer;
     861: invokevirtual #189                // Method java/util/ArrayList.set:(ILjava/lang/Object;)Ljava/lang/Object;
     864: pop
     865: aload_0
     866: getfield      #168                // Field recordedPagesIndex:Lorg/h2/util/IntIntHashMap;
     869: iload         13
     871: iload         15
     873: invokevirtual #43                 // Method org/h2/util/IntIntHashMap.put:(II)V
     876: iinc          15, 1
     879: goto          674
     882: aload_0
     883: aconst_null
     884: putfield      #167                // Field recordedPagesList:Ljava/util/ArrayList;
     887: aload_0
     888: aconst_null
     889: putfield      #168                // Field recordedPagesIndex:Lorg/h2/util/IntIntHashMap;
     892: aload_0
     893: invokevirtual #111                // Method checkpoint:()V
     896: aload_0
     897: getfield      #71                 // Field log:Lorg/h2/store/PageLog;
     900: invokevirtual #136                // Method org/h2/store/PageLog.checkpoint:()V
     903: aload_0
     904: invokespecial #135                // Method writeIndexRowCounts:()V
     907: aload_0
     908: getfield      #71                 // Field log:Lorg/h2/store/PageLog;
     911: invokevirtual #136                // Method org/h2/store/PageLog.checkpoint:()V
     914: aload_0
     915: invokespecial #137                // Method writeBack:()V
     918: aload_0
     919: aload_0
     920: getfield      #29                 // Field pageStoreSession:Lorg/h2/engine/Session;
     923: invokevirtual #190                // Method commit:(Lorg/h2/engine/Session;)V
     926: aload_0
     927: invokespecial #137                // Method writeBack:()V
     930: aload_0
     931: getfield      #71                 // Field log:Lorg/h2/store/PageLog;
     934: invokevirtual #136                // Method org/h2/store/PageLog.checkpoint:()V
     937: aload_0
     938: getfield      #71                 // Field log:Lorg/h2/store/PageLog;
     941: invokevirtual #109                // Method org/h2/store/PageLog.free:()V
     944: aload_0
     945: iconst_1
     946: putfield      #66                 // Field recoveryRunning:Z
     949: aload_0
     950: aload_0
     951: dup
     952: getfield      #98                 // Field logKey:I
     955: iconst_1
     956: iadd
     957: dup_x1
     958: putfield      #98                 // Field logKey:I
     961: iconst_0
     962: iconst_0
     963: invokevirtual #191                // Method setLogFirstPage:(III)V
     966: aload_0
     967: iconst_0
     968: putfield      #66                 // Field recoveryRunning:Z
     971: goto          984
     974: astore        20
     976: aload_0
     977: iconst_0
     978: putfield      #66                 // Field recoveryRunning:Z
     981: aload         20
     983: athrow
     984: aload_0
     985: invokespecial #137                // Method writeBack:()V
     988: aload_0
     989: aload_0
     990: getfield      #36                 // Field pageCount:I
     993: invokespecial #152                // Method getFreeListId:(I)I
     996: istore        11
     998: iload         11
    1000: iflt          1027
    1003: aload_0
    1004: iload         11
    1006: invokespecial #153                // Method getFreeList:(I)Lorg/h2/store/PageFreeList;
    1009: invokevirtual #154                // Method org/h2/store/PageFreeList.getLastUsed:()I
    1012: istore_2
    1013: iload_2
    1014: iconst_m1
    1015: if_icmpeq     1021
    1018: goto          1027
    1021: iinc          11, -1
    1024: goto          998
    1027: iload_2
    1028: iconst_1
    1029: iadd
    1030: istore        11
    1032: iload         11
    1034: aload_0
    1035: getfield      #36                 // Field pageCount:I
    1038: if_icmpge     1055
    1041: aload_0
    1042: getfield      #14                 // Field freed:Lorg/h2/util/BitField;
    1045: iload         11
    1047: aload_0
    1048: getfield      #36                 // Field pageCount:I
    1051: iconst_0
    1052: invokevirtual #110                // Method org/h2/util/BitField.set:(IIZ)V
    1055: aload_0
    1056: iload         11
    1058: putfield      #36                 // Field pageCount:I
    1061: aload_0
    1062: getfield      #16                 // Field freeLists:Ljava/util/ArrayList;
    1065: invokevirtual #192                // Method java/util/ArrayList.clear:()V
    1068: aload_0
    1069: getfield      #23                 // Field trace:Lorg/h2/message/Trace;
    1072: new           #50                 // class java/lang/StringBuilder
    1075: dup
    1076: invokespecial #51                 // Method java/lang/StringBuilder."<init>":()V
    1079: ldc           #193                // String pageCount:
    1081: invokevirtual #52                 // Method java/lang/StringBuilder.append:(Ljava/lang/String;)Ljava/lang/StringBuilder;
    1084: aload_0
    1085: getfield      #36                 // Field pageCount:I
    1088: invokevirtual #93                 // Method java/lang/StringBuilder.append:(I)Ljava/lang/StringBuilder;
    1091: invokevirtual #55                 // Method java/lang/StringBuilder.toString:()Ljava/lang/String;
    1094: invokevirtual #132                // Method org/h2/message/Trace.debug:(Ljava/lang/String;)V
    1097: aload_0
    1098: getfield      #36                 // Field pageCount:I
    1101: i2l
    1102: aload_0
    1103: getfield      #38                 // Field pageSizeShift:I
    1106: lshl
    1107: lstore        12
    1109: aload_0
    1110: getfield      #37                 // Field file:Lorg/h2/store/FileStore;
    1113: invokevirtual #90                 // Method org/h2/store/FileStore.length:()J
    1116: lload         12
    1118: lcmp
    1119: ifeq          1141
    1122: aload_0
    1123: getfield      #37                 // Field file:Lorg/h2/store/FileStore;
    1126: lload         12
    1128: invokevirtual #194                // Method org/h2/store/FileStore.setLength:(J)V
    1131: aload_0
    1132: dup
    1133: getfield      #148                // Field writeCount:J
    1136: lconst_1
    1137: ladd
    1138: putfield      #148                // Field writeCount:J
    1141: return
    Exception table:
       from    to  target type
          90   124   132   any
         132   134   132   any
         305   333   388   any
         336   379   388   any
         382   385   388   any
         388   393   388   any
         949   966   974   any
         974   976   974   any

  private int getFirstFree(int);
    Code:
       0: iconst_m1
       1: istore_2
       2: aload_0
       3: iload_1
       4: invokespecial #152                // Method getFreeListId:(I)I
       7: istore_3
       8: iload_1
       9: aload_0
      10: getfield      #36                 // Field pageCount:I
      13: if_icmpge     40
      16: aload_0
      17: iload_3
      18: invokespecial #153                // Method getFreeList:(I)Lorg/h2/store/PageFreeList;
      21: iload_1
      22: invokevirtual #195                // Method org/h2/store/PageFreeList.getFirstFree:(I)I
      25: istore_2
      26: iload_2
      27: iconst_m1
      28: if_icmpeq     34
      31: goto          40
      34: iinc          3, 1
      37: goto          8
      40: iload_2
      41: ireturn

  private void swap(int, int, int);
    Code:
       0: iload_1
       1: iconst_5
       2: if_icmplt     10
       5: iload_2
       6: iconst_5
       7: if_icmpge     79
      10: getstatic     #196                // Field java/lang/System.out:Ljava/io/PrintStream;
      13: new           #50                 // class java/lang/StringBuilder
      16: dup
      17: invokespecial #51                 // Method java/lang/StringBuilder."<init>":()V
      20: aload_0
      21: iload_1
      22: invokespecial #142                // Method isUsed:(I)Z
      25: invokevirtual #197                // Method java/lang/StringBuilder.append:(Z)Ljava/lang/StringBuilder;
      28: ldc           #198                // String
      30: invokevirtual #52                 // Method java/lang/StringBuilder.append:(Ljava/lang/String;)Ljava/lang/StringBuilder;
      33: aload_0
      34: iload_2
      35: invokespecial #142                // Method isUsed:(I)Z
      38: invokevirtual #197                // Method java/lang/StringBuilder.append:(Z)Ljava/lang/StringBuilder;
      41: invokevirtual #55                 // Method java/lang/StringBuilder.toString:()Ljava/lang/String;
      44: invokevirtual #199                // Method java/io/PrintStream.println:(Ljava/lang/String;)V
      47: new           #50                 // class java/lang/StringBuilder
      50: dup
      51: invokespecial #51                 // Method java/lang/StringBuilder."<init>":()V
      54: ldc           #200                // String can\'t swap
      56: invokevirtual #52                 // Method java/lang/StringBuilder.append:(Ljava/lang/String;)Ljava/lang/StringBuilder;
      59: iload_1
      60: invokevirtual #93                 // Method java/lang/StringBuilder.append:(I)Ljava/lang/StringBuilder;
      63: ldc           #201                // String  and
      65: invokevirtual #52                 // Method java/lang/StringBuilder.append:(Ljava/lang/String;)Ljava/lang/StringBuilder;
      68: iload_2
      69: invokevirtual #93                 // Method java/lang/StringBuilder.append:(I)Ljava/lang/StringBuilder;
      72: invokevirtual #55                 // Method java/lang/StringBuilder.toString:()Ljava/lang/String;
      75: invokestatic  #186                // Method org/h2/message/DbException.throwInternalError:(Ljava/lang/String;)Ljava/lang/RuntimeException;
      78: pop
      79: aload_0
      80: getfield      #26                 // Field cache:Lorg/h2/util/Cache;
      83: iload_3
      84: invokeinterface #202,  2          // InterfaceMethod org/h2/util/Cache.get:(I)Lorg/h2/util/CacheObject;
      89: checkcast     #203                // class org/h2/store/Page
      92: astore        4
      94: aload         4
      96: ifnull        123
      99: new           #50                 // class java/lang/StringBuilder
     102: dup
     103: invokespecial #51                 // Method java/lang/StringBuilder."<init>":()V
     106: ldc           #204                // String not free:
     108: invokevirtual #52                 // Method java/lang/StringBuilder.append:(Ljava/lang/String;)Ljava/lang/StringBuilder;
     111: aload         4
     113: invokevirtual #205                // Method java/lang/StringBuilder.append:(Ljava/lang/Object;)Ljava/lang/StringBuilder;
     116: invokevirtual #55                 // Method java/lang/StringBuilder.toString:()Ljava/lang/String;
     119: invokestatic  #186                // Method org/h2/message/DbException.throwInternalError:(Ljava/lang/String;)Ljava/lang/RuntimeException;
     122: pop
     123: aload_0
     124: getfield      #23                 // Field trace:Lorg/h2/message/Trace;
     127: invokevirtual #140                // Method org/h2/message/Trace.isDebugEnabled:()Z
     130: ifeq          177
     133: aload_0
     134: getfield      #23                 // Field trace:Lorg/h2/message/Trace;
     137: new           #50                 // class java/lang/StringBuilder
     140: dup
     141: invokespecial #51                 // Method java/lang/StringBuilder."<init>":()V
     144: ldc           #206                // String swap
     146: invokevirtual #52                 // Method java/lang/StringBuilder.append:(Ljava/lang/String;)Ljava/lang/StringBuilder;
     149: iload_1
     150: invokevirtual #93                 // Method java/lang/StringBuilder.append:(I)Ljava/lang/StringBuilder;
     153: ldc           #201                // String  and
     155: invokevirtual #52                 // Method java/lang/StringBuilder.append:(Ljava/lang/String;)Ljava/lang/StringBuilder;
     158: iload_2
     159: invokevirtual #93                 // Method java/lang/StringBuilder.append:(I)Ljava/lang/StringBuilder;
     162: ldc           #207                // String  via
     164: invokevirtual #52                 // Method java/lang/StringBuilder.append:(Ljava/lang/String;)Ljava/lang/StringBuilder;
     167: iload_3
     168: invokevirtual #93                 // Method java/lang/StringBuilder.append:(I)Ljava/lang/StringBuilder;
     171: invokevirtual #55                 // Method java/lang/StringBuilder.toString:()Ljava/lang/String;
     174: invokevirtual #132                // Method org/h2/message/Trace.debug:(Ljava/lang/String;)V
     177: aconst_null
     178: astore        5
     180: aload_0
     181: iload_1
     182: invokespecial #142                // Method isUsed:(I)Z
     185: ifeq          215
     188: aload_0
     189: iload_1
     190: invokevirtual #183                // Method getPage:(I)Lorg/h2/store/Page;
     193: astore        5
     195: aload         5
     197: ifnull        210
     200: aload         5
     202: aload_0
     203: getfield      #29                 // Field pageStoreSession:Lorg/h2/engine/Session;
     206: iload_3
     207: invokevirtual #208                // Method org/h2/store/Page.moveTo:(Lorg/h2/engine/Session;I)V
     210: aload_0
     211: iload_1
     212: invokevirtual #209                // Method free:(I)V
     215: iload_3
     216: iload_2
     217: if_icmpeq     287
     220: aload_0
     221: iload_2
     222: invokespecial #142                // Method isUsed:(I)Z
     225: ifeq          255
     228: aload_0
     229: iload_2
     230: invokevirtual #183                // Method getPage:(I)Lorg/h2/store/Page;
     233: astore        6
     235: aload         6
     237: ifnull        250
     240: aload         6
     242: aload_0
     243: getfield      #29                 // Field pageStoreSession:Lorg/h2/engine/Session;
     246: iload_1
     247: invokevirtual #208                // Method org/h2/store/Page.moveTo:(Lorg/h2/engine/Session;I)V
     250: aload_0
     251: iload_2
     252: invokevirtual #209                // Method free:(I)V
     255: aload         5
     257: ifnull        287
     260: aload_0
     261: iload_3
     262: invokevirtual #183                // Method getPage:(I)Lorg/h2/store/Page;
     265: astore        4
     267: aload         4
     269: ifnull        282
     272: aload         4
     274: aload_0
     275: getfield      #29                 // Field pageStoreSession:Lorg/h2/engine/Session;
     278: iload_2
     279: invokevirtual #208                // Method org/h2/store/Page.moveTo:(Lorg/h2/engine/Session;I)V
     282: aload_0
     283: iload_3
     284: invokevirtual #209                // Method free:(I)V
     287: return

  private boolean compact(int, int);
    Code:
       0: iload_1
       1: iconst_5
       2: if_icmplt     23
       5: iload_2
       6: iconst_m1
       7: if_icmpeq     23
      10: iload_2
      11: iload_1
      12: if_icmpge     23
      15: aload_0
      16: iload_1
      17: invokespecial #142                // Method isUsed:(I)Z
      20: ifne          25
      23: iconst_0
      24: ireturn
      25: aload_0
      26: getfield      #26                 // Field cache:Lorg/h2/util/Cache;
      29: iload_2
      30: invokeinterface #202,  2          // InterfaceMethod org/h2/util/Cache.get:(I)Lorg/h2/util/CacheObject;
      35: checkcast     #203                // class org/h2/store/Page
      38: astore_3
      39: aload_3
      40: ifnull        66
      43: new           #50                 // class java/lang/StringBuilder
      46: dup
      47: invokespecial #51                 // Method java/lang/StringBuilder."<init>":()V
      50: ldc           #204                // String not free:
      52: invokevirtual #52                 // Method java/lang/StringBuilder.append:(Ljava/lang/String;)Ljava/lang/StringBuilder;
      55: aload_3
      56: invokevirtual #205                // Method java/lang/StringBuilder.append:(Ljava/lang/Object;)Ljava/lang/StringBuilder;
      59: invokevirtual #55                 // Method java/lang/StringBuilder.toString:()Ljava/lang/String;
      62: invokestatic  #186                // Method org/h2/message/DbException.throwInternalError:(Ljava/lang/String;)Ljava/lang/RuntimeException;
      65: pop
      66: aload_0
      67: iload_1
      68: invokevirtual #183                // Method getPage:(I)Lorg/h2/store/Page;
      71: astore        4
      73: aload         4
      75: ifnonnull     86
      78: aload_0
      79: iload_1
      80: invokespecial #210                // Method freePage:(I)V
      83: goto          251
      86: aload         4
      88: instanceof    #211                // class org/h2/store/PageStreamData
      91: ifne          102
      94: aload         4
      96: instanceof    #212                // class org/h2/store/PageStreamTrunk
      99: ifeq          125
     102: aload         4
     104: invokevirtual #213                // Method org/h2/store/Page.getPos:()I
     107: aload_0
     108: getfield      #71                 // Field log:Lorg/h2/store/PageLog;
     111: invokevirtual #214                // Method org/h2/store/PageLog.getMinPageId:()I
     114: if_icmpge     251
     117: aload_0
     118: iload_1
     119: invokespecial #210                // Method freePage:(I)V
     122: goto          251
     125: aload_0
     126: getfield      #23                 // Field trace:Lorg/h2/message/Trace;
     129: invokevirtual #140                // Method org/h2/message/Trace.isDebugEnabled:()Z
     132: ifeq          174
     135: aload_0
     136: getfield      #23                 // Field trace:Lorg/h2/message/Trace;
     139: new           #50                 // class java/lang/StringBuilder
     142: dup
     143: invokespecial #51                 // Method java/lang/StringBuilder."<init>":()V
     146: ldc           #215                // String move
     148: invokevirtual #52                 // Method java/lang/StringBuilder.append:(Ljava/lang/String;)Ljava/lang/StringBuilder;
     151: aload         4
     153: invokevirtual #213                // Method org/h2/store/Page.getPos:()I
     156: invokevirtual #93                 // Method java/lang/StringBuilder.append:(I)Ljava/lang/StringBuilder;
     159: ldc           #216                // String  to
     161: invokevirtual #52                 // Method java/lang/StringBuilder.append:(Ljava/lang/String;)Ljava/lang/StringBuilder;
     164: iload_2
     165: invokevirtual #93                 // Method java/lang/StringBuilder.append:(I)Ljava/lang/StringBuilder;
     168: invokevirtual #55                 // Method java/lang/StringBuilder.toString:()Ljava/lang/String;
     171: invokevirtual #132                // Method org/h2/message/Trace.debug:(Ljava/lang/String;)V
     174: aload         4
     176: aload_0
     177: getfield      #29                 // Field pageStoreSession:Lorg/h2/engine/Session;
     180: iload_2
     181: invokevirtual #208                // Method org/h2/store/Page.moveTo:(Lorg/h2/engine/Session;I)V
     184: aload_0
     185: dup
     186: getfield      #17                 // Field changeCount:J
     189: lconst_1
     190: ladd
     191: putfield      #17                 // Field changeCount:J
     194: getstatic     #217                // Field org/h2/engine/SysProperties.CHECK:Z
     197: ifeq          251
     200: aload_0
     201: getfield      #17                 // Field changeCount:J
     204: lconst_0
     205: lcmp
     206: ifge          251
     209: ldc           #218                // String changeCount has wrapped
     211: invokestatic  #186                // Method org/h2/message/DbException.throwInternalError:(Ljava/lang/String;)Ljava/lang/RuntimeException;
     214: athrow
     215: astore        5
     217: aload_0
     218: dup
     219: getfield      #17                 // Field changeCount:J
     222: lconst_1
     223: ladd
     224: putfield      #17                 // Field changeCount:J
     227: getstatic     #217                // Field org/h2/engine/SysProperties.CHECK:Z
     230: ifeq          248
     233: aload_0
     234: getfield      #17                 // Field changeCount:J
     237: lconst_0
     238: lcmp
     239: ifge          248
     242: ldc           #218                // String changeCount has wrapped
     244: invokestatic  #186                // Method org/h2/message/DbException.throwInternalError:(Ljava/lang/String;)Ljava/lang/RuntimeException;
     247: athrow
     248: aload         5
     250: athrow
     251: iconst_1
     252: ireturn
    Exception table:
       from    to  target type
         174   184   215   any
         215   217   215   any

  public synchronized org.h2.store.Page getPage(int);
    Code:
       0: aload_0
       1: getfield      #26                 // Field cache:Lorg/h2/util/Cache;
       4: iload_1
       5: invokeinterface #202,  2          // InterfaceMethod org/h2/util/Cache.get:(I)Lorg/h2/util/CacheObject;
      10: checkcast     #203                // class org/h2/store/Page
      13: astore_2
      14: aload_2
      15: ifnull        20
      18: aload_2
      19: areturn
      20: aload_0
      21: invokevirtual #219                // Method createData:()Lorg/h2/store/Data;
      24: astore_3
      25: aload_0
      26: iload_1
      27: aload_3
      28: invokevirtual #220                // Method readPage:(ILorg/h2/store/Data;)V
      31: aload_3
      32: invokevirtual #221                // Method org/h2/store/Data.readByte:()B
      35: istore        4
      37: iload         4
      39: ifne          44
      42: aconst_null
      43: areturn
      44: aload_3
      45: invokevirtual #222                // Method org/h2/store/Data.readShortInt:()S
      48: pop
      49: aload_3
      50: invokevirtual #223                // Method org/h2/store/Data.readInt:()I
      53: pop
      54: aload_3
      55: invokevirtual #224                // Method org/h2/store/Data.getBytes:()[B
      58: iload_1
      59: aload_0
      60: getfield      #2                  // Field pageSize:I
      63: invokestatic  #225                // Method checksumTest:([BII)Z
      66: ifne          77
      69: ldc           #49                 // int 90030
      71: ldc           #226                // String wrong checksum
      73: invokestatic  #56                 // Method org/h2/message/DbException.get:(ILjava/lang/String;)Lorg/h2/message/DbException;
      76: athrow
      77: iload         4
      79: bipush        -17
      81: iand
      82: tableswitch   { // 1 to 8
                     1: 138
                     2: 304
                     3: 470
                     4: 493
                     5: 659
                     6: 128
                     7: 825
                     8: 835
               default: 845
          }
     128: aload_0
     129: aload_3
     130: iload_1
     131: invokestatic  #227                // Method org/h2/store/PageFreeList.read:(Lorg/h2/store/PageStore;Lorg/h2/store/Data;I)Lorg/h2/store/PageFreeList;
     134: astore_2
     135: goto          880
     138: aload_3
     139: invokevirtual #228                // Method org/h2/store/Data.readVarInt:()I
     142: istore        5
     144: aload_0
     145: getfield      #8                  // Field metaObjects:Ljava/util/HashMap;
     148: iload         5
     150: invokestatic  #34                 // Method java/lang/Integer.valueOf:(I)Ljava/lang/Integer;
     153: invokevirtual #31                 // Method java/util/HashMap.get:(Ljava/lang/Object;)Ljava/lang/Object;
     156: checkcast     #117                // class org/h2/index/PageIndex
     159: astore        6
     161: aload         6
     163: ifnonnull     192
     166: ldc           #49                 // int 90030
     168: new           #50                 // class java/lang/StringBuilder
     171: dup
     172: invokespecial #51                 // Method java/lang/StringBuilder."<init>":()V
     175: ldc           #229                // String index not found
     177: invokevirtual #52                 // Method java/lang/StringBuilder.append:(Ljava/lang/String;)Ljava/lang/StringBuilder;
     180: iload         5
     182: invokevirtual #93                 // Method java/lang/StringBuilder.append:(I)Ljava/lang/StringBuilder;
     185: invokevirtual #55                 // Method java/lang/StringBuilder.toString:()Ljava/lang/String;
     188: invokestatic  #56                 // Method org/h2/message/DbException.get:(ILjava/lang/String;)Lorg/h2/message/DbException;
     191: athrow
     192: aload         6
     194: instanceof    #230                // class org/h2/index/PageDataIndex
     197: ifne          236
     200: ldc           #49                 // int 90030
     202: new           #50                 // class java/lang/StringBuilder
     205: dup
     206: invokespecial #51                 // Method java/lang/StringBuilder."<init>":()V
     209: ldc           #231                // String not a data index
     211: invokevirtual #52                 // Method java/lang/StringBuilder.append:(Ljava/lang/String;)Ljava/lang/StringBuilder;
     214: iload         5
     216: invokevirtual #93                 // Method java/lang/StringBuilder.append:(I)Ljava/lang/StringBuilder;
     219: ldc           #198                // String
     221: invokevirtual #52                 // Method java/lang/StringBuilder.append:(Ljava/lang/String;)Ljava/lang/StringBuilder;
     224: aload         6
     226: invokevirtual #205                // Method java/lang/StringBuilder.append:(Ljava/lang/Object;)Ljava/lang/StringBuilder;
     229: invokevirtual #55                 // Method java/lang/StringBuilder.toString:()Ljava/lang/String;
     232: invokestatic  #56                 // Method org/h2/message/DbException.get:(ILjava/lang/String;)Lorg/h2/message/DbException;
     235: athrow
     236: aload         6
     238: checkcast     #230                // class org/h2/index/PageDataIndex
     241: astore        7
     243: aload_0
     244: getfield      #30                 // Field statistics:Ljava/util/HashMap;
     247: ifnull        293
     250: aload_0
     251: new           #50                 // class java/lang/StringBuilder
     254: dup
     255: invokespecial #51                 // Method java/lang/StringBuilder."<init>":()V
     258: aload         7
     260: invokevirtual #232                // Method org/h2/index/PageDataIndex.getTable:()Lorg/h2/table/Table;
     263: invokevirtual #233                // Method org/h2/table/Table.getName:()Ljava/lang/String;
     266: invokevirtual #52                 // Method java/lang/StringBuilder.append:(Ljava/lang/String;)Ljava/lang/StringBuilder;
     269: ldc           #234                // String .
     271: invokevirtual #52                 // Method java/lang/StringBuilder.append:(Ljava/lang/String;)Ljava/lang/StringBuilder;
     274: aload         7
     276: invokevirtual #235                // Method org/h2/index/PageDataIndex.getName:()Ljava/lang/String;
     279: invokevirtual #52                 // Method java/lang/StringBuilder.append:(Ljava/lang/String;)Ljava/lang/StringBuilder;
     282: ldc           #236                // String  read
     284: invokevirtual #52                 // Method java/lang/StringBuilder.append:(Ljava/lang/String;)Ljava/lang/StringBuilder;
     287: invokevirtual #55                 // Method java/lang/StringBuilder.toString:()Ljava/lang/String;
     290: invokespecial #237                // Method statisticsIncrement:(Ljava/lang/String;)V
     293: aload         7
     295: aload_3
     296: iload_1
     297: invokestatic  #238                // Method org/h2/index/PageDataLeaf.read:(Lorg/h2/index/PageDataIndex;Lorg/h2/store/Data;I)Lorg/h2/store/Page;
     300: astore_2
     301: goto          880
     304: aload_3
     305: invokevirtual #228                // Method org/h2/store/Data.readVarInt:()I
     308: istore        5
     310: aload_0
     311: getfield      #8                  // Field metaObjects:Ljava/util/HashMap;
     314: iload         5
     316: invokestatic  #34                 // Method java/lang/Integer.valueOf:(I)Ljava/lang/Integer;
     319: invokevirtual #31                 // Method java/util/HashMap.get:(Ljava/lang/Object;)Ljava/lang/Object;
     322: checkcast     #117                // class org/h2/index/PageIndex
     325: astore        6
     327: aload         6
     329: ifnonnull     358
     332: ldc           #49                 // int 90030
     334: new           #50                 // class java/lang/StringBuilder
     337: dup
     338: invokespecial #51                 // Method java/lang/StringBuilder."<init>":()V
     341: ldc           #229                // String index not found
     343: invokevirtual #52                 // Method java/lang/StringBuilder.append:(Ljava/lang/String;)Ljava/lang/StringBuilder;
     346: iload         5
     348: invokevirtual #93                 // Method java/lang/StringBuilder.append:(I)Ljava/lang/StringBuilder;
     351: invokevirtual #55                 // Method java/lang/StringBuilder.toString:()Ljava/lang/String;
     354: invokestatic  #56                 // Method org/h2/message/DbException.get:(ILjava/lang/String;)Lorg/h2/message/DbException;
     357: athrow
     358: aload         6
     360: instanceof    #230                // class org/h2/index/PageDataIndex
     363: ifne          402
     366: ldc           #49                 // int 90030
     368: new           #50                 // class java/lang/StringBuilder
     371: dup
     372: invokespecial #51                 // Method java/lang/StringBuilder."<init>":()V
     375: ldc           #231                // String not a data index
     377: invokevirtual #52                 // Method java/lang/StringBuilder.append:(Ljava/lang/String;)Ljava/lang/StringBuilder;
     380: iload         5
     382: invokevirtual #93                 // Method java/lang/StringBuilder.append:(I)Ljava/lang/StringBuilder;
     385: ldc           #198                // String
     387: invokevirtual #52                 // Method java/lang/StringBuilder.append:(Ljava/lang/String;)Ljava/lang/StringBuilder;
     390: aload         6
     392: invokevirtual #205                // Method java/lang/StringBuilder.append:(Ljava/lang/Object;)Ljava/lang/StringBuilder;
     395: invokevirtual #55                 // Method java/lang/StringBuilder.toString:()Ljava/lang/String;
     398: invokestatic  #56                 // Method org/h2/message/DbException.get:(ILjava/lang/String;)Lorg/h2/message/DbException;
     401: athrow
     402: aload         6
     404: checkcast     #230                // class org/h2/index/PageDataIndex
     407: astore        7
     409: aload_0
     410: getfield      #30                 // Field statistics:Ljava/util/HashMap;
     413: ifnull        459
     416: aload_0
     417: new           #50                 // class java/lang/StringBuilder
     420: dup
     421: invokespecial #51                 // Method java/lang/StringBuilder."<init>":()V
     424: aload         7
     426: invokevirtual #232                // Method org/h2/index/PageDataIndex.getTable:()Lorg/h2/table/Table;
     429: invokevirtual #233                // Method org/h2/table/Table.getName:()Ljava/lang/String;
     432: invokevirtual #52                 // Method java/lang/StringBuilder.append:(Ljava/lang/String;)Ljava/lang/StringBuilder;
     435: ldc           #234                // String .
     437: invokevirtual #52                 // Method java/lang/StringBuilder.append:(Ljava/lang/String;)Ljava/lang/StringBuilder;
     440: aload         7
     442: invokevirtual #235                // Method org/h2/index/PageDataIndex.getName:()Ljava/lang/String;
     445: invokevirtual #52                 // Method java/lang/StringBuilder.append:(Ljava/lang/String;)Ljava/lang/StringBuilder;
     448: ldc           #236                // String  read
     450: invokevirtual #52                 // Method java/lang/StringBuilder.append:(Ljava/lang/String;)Ljava/lang/StringBuilder;
     453: invokevirtual #55                 // Method java/lang/StringBuilder.toString:()Ljava/lang/String;
     456: invokespecial #237                // Method statisticsIncrement:(Ljava/lang/String;)V
     459: aload         7
     461: aload_3
     462: iload_1
     463: invokestatic  #239                // Method org/h2/index/PageDataNode.read:(Lorg/h2/index/PageDataIndex;Lorg/h2/store/Data;I)Lorg/h2/store/Page;
     466: astore_2
     467: goto          880
     470: aload_0
     471: aload_3
     472: iload_1
     473: invokestatic  #240                // Method org/h2/index/PageDataOverflow.read:(Lorg/h2/store/PageStore;Lorg/h2/store/Data;I)Lorg/h2/store/Page;
     476: astore_2
     477: aload_0
     478: getfield      #30                 // Field statistics:Ljava/util/HashMap;
     481: ifnull        880
     484: aload_0
     485: ldc           #241                // String overflow read
     487: invokespecial #237                // Method statisticsIncrement:(Ljava/lang/String;)V
     490: goto          880
     493: aload_3
     494: invokevirtual #228                // Method org/h2/store/Data.readVarInt:()I
     497: istore        5
     499: aload_0
     500: getfield      #8                  // Field metaObjects:Ljava/util/HashMap;
     503: iload         5
     505: invokestatic  #34                 // Method java/lang/Integer.valueOf:(I)Ljava/lang/Integer;
     508: invokevirtual #31                 // Method java/util/HashMap.get:(Ljava/lang/Object;)Ljava/lang/Object;
     511: checkcast     #117                // class org/h2/index/PageIndex
     514: astore        6
     516: aload         6
     518: ifnonnull     547
     521: ldc           #49                 // int 90030
     523: new           #50                 // class java/lang/StringBuilder
     526: dup
     527: invokespecial #51                 // Method java/lang/StringBuilder."<init>":()V
     530: ldc           #229                // String index not found
     532: invokevirtual #52                 // Method java/lang/StringBuilder.append:(Ljava/lang/String;)Ljava/lang/StringBuilder;
     535: iload         5
     537: invokevirtual #93                 // Method java/lang/StringBuilder.append:(I)Ljava/lang/StringBuilder;
     540: invokevirtual #55                 // Method java/lang/StringBuilder.toString:()Ljava/lang/String;
     543: invokestatic  #56                 // Method org/h2/message/DbException.get:(ILjava/lang/String;)Lorg/h2/message/DbException;
     546: athrow
     547: aload         6
     549: instanceof    #242                // class org/h2/index/PageBtreeIndex
     552: ifne          591
     555: ldc           #49                 // int 90030
     557: new           #50                 // class java/lang/StringBuilder
     560: dup
     561: invokespecial #51                 // Method java/lang/StringBuilder."<init>":()V
     564: ldc           #243                // String not a btree index
     566: invokevirtual #52                 // Method java/lang/StringBuilder.append:(Ljava/lang/String;)Ljava/lang/StringBuilder;
     569: iload         5
     571: invokevirtual #93                 // Method java/lang/StringBuilder.append:(I)Ljava/lang/StringBuilder;
     574: ldc           #198                // String
     576: invokevirtual #52                 // Method java/lang/StringBuilder.append:(Ljava/lang/String;)Ljava/lang/StringBuilder;
     579: aload         6
     581: invokevirtual #205                // Method java/lang/StringBuilder.append:(Ljava/lang/Object;)Ljava/lang/StringBuilder;
     584: invokevirtual #55                 // Method java/lang/StringBuilder.toString:()Ljava/lang/String;
     587: invokestatic  #56                 // Method org/h2/message/DbException.get:(ILjava/lang/String;)Lorg/h2/message/DbException;
     590: athrow
     591: aload         6
     593: checkcast     #242                // class org/h2/index/PageBtreeIndex
     596: astore        7
     598: aload_0
     599: getfield      #30                 // Field statistics:Ljava/util/HashMap;
     602: ifnull        648
     605: aload_0
     606: new           #50                 // class java/lang/StringBuilder
     609: dup
     610: invokespecial #51                 // Method java/lang/StringBuilder."<init>":()V
     613: aload         7
     615: invokevirtual #244                // Method org/h2/index/PageBtreeIndex.getTable:()Lorg/h2/table/Table;
     618: invokevirtual #233                // Method org/h2/table/Table.getName:()Ljava/lang/String;
     621: invokevirtual #52                 // Method java/lang/StringBuilder.append:(Ljava/lang/String;)Ljava/lang/StringBuilder;
     624: ldc           #234                // String .
     626: invokevirtual #52                 // Method java/lang/StringBuilder.append:(Ljava/lang/String;)Ljava/lang/StringBuilder;
     629: aload         7
     631: invokevirtual #245                // Method org/h2/index/PageBtreeIndex.getName:()Ljava/lang/String;
     634: invokevirtual #52                 // Method java/lang/StringBuilder.append:(Ljava/lang/String;)Ljava/lang/StringBuilder;
     637: ldc           #236                // String  read
     639: invokevirtual #52                 // Method java/lang/StringBuilder.append:(Ljava/lang/String;)Ljava/lang/StringBuilder;
     642: invokevirtual #55                 // Method java/lang/StringBuilder.toString:()Ljava/lang/String;
     645: invokespecial #237                // Method statisticsIncrement:(Ljava/lang/String;)V
     648: aload         7
     650: aload_3
     651: iload_1
     652: invokestatic  #246                // Method org/h2/index/PageBtreeLeaf.read:(Lorg/h2/index/PageBtreeIndex;Lorg/h2/store/Data;I)Lorg/h2/store/Page;
     655: astore_2
     656: goto          880
     659: aload_3
     660: invokevirtual #228                // Method org/h2/store/Data.readVarInt:()I
     663: istore        5
     665: aload_0
     666: getfield      #8                  // Field metaObjects:Ljava/util/HashMap;
     669: iload         5
     671: invokestatic  #34                 // Method java/lang/Integer.valueOf:(I)Ljava/lang/Integer;
     674: invokevirtual #31                 // Method java/util/HashMap.get:(Ljava/lang/Object;)Ljava/lang/Object;
     677: checkcast     #117                // class org/h2/index/PageIndex
     680: astore        6
     682: aload         6
     684: ifnonnull     713
     687: ldc           #49                 // int 90030
     689: new           #50                 // class java/lang/StringBuilder
     692: dup
     693: invokespecial #51                 // Method java/lang/StringBuilder."<init>":()V
     696: ldc           #229                // String index not found
     698: invokevirtual #52                 // Method java/lang/StringBuilder.append:(Ljava/lang/String;)Ljava/lang/StringBuilder;
     701: iload         5
     703: invokevirtual #93                 // Method java/lang/StringBuilder.append:(I)Ljava/lang/StringBuilder;
     706: invokevirtual #55                 // Method java/lang/StringBuilder.toString:()Ljava/lang/String;
     709: invokestatic  #56                 // Method org/h2/message/DbException.get:(ILjava/lang/String;)Lorg/h2/message/DbException;
     712: athrow
     713: aload         6
     715: instanceof    #242                // class org/h2/index/PageBtreeIndex
     718: ifne          757
     721: ldc           #49                 // int 90030
     723: new           #50                 // class java/lang/StringBuilder
     726: dup
     727: invokespecial #51                 // Method java/lang/StringBuilder."<init>":()V
     730: ldc           #243                // String not a btree index
     732: invokevirtual #52                 // Method java/lang/StringBuilder.append:(Ljava/lang/String;)Ljava/lang/StringBuilder;
     735: iload         5
     737: invokevirtual #93                 // Method java/lang/StringBuilder.append:(I)Ljava/lang/StringBuilder;
     740: ldc           #198                // String
     742: invokevirtual #52                 // Method java/lang/StringBuilder.append:(Ljava/lang/String;)Ljava/lang/StringBuilder;
     745: aload         6
     747: invokevirtual #205                // Method java/lang/StringBuilder.append:(Ljava/lang/Object;)Ljava/lang/StringBuilder;
     750: invokevirtual #55                 // Method java/lang/StringBuilder.toString:()Ljava/lang/String;
     753: invokestatic  #56                 // Method org/h2/message/DbException.get:(ILjava/lang/String;)Lorg/h2/message/DbException;
     756: athrow
     757: aload         6
     759: checkcast     #242                // class org/h2/index/PageBtreeIndex
     762: astore        7
     764: aload_0
     765: getfield      #30                 // Field statistics:Ljava/util/HashMap;
     768: ifnull        814
     771: aload_0
     772: new           #50                 // class java/lang/StringBuilder
     775: dup
     776: invokespecial #51                 // Method java/lang/StringBuilder."<init>":()V
     779: aload         7
     781: invokevirtual #244                // Method org/h2/index/PageBtreeIndex.getTable:()Lorg/h2/table/Table;
     784: invokevirtual #233                // Method org/h2/table/Table.getName:()Ljava/lang/String;
     787: invokevirtual #52                 // Method java/lang/StringBuilder.append:(Ljava/lang/String;)Ljava/lang/StringBuilder;
     790: ldc           #234                // String .
     792: invokevirtual #52                 // Method java/lang/StringBuilder.append:(Ljava/lang/String;)Ljava/lang/StringBuilder;
     795: aload         7
     797: invokevirtual #245                // Method org/h2/index/PageBtreeIndex.getName:()Ljava/lang/String;
     800: invokevirtual #52                 // Method java/lang/StringBuilder.append:(Ljava/lang/String;)Ljava/lang/StringBuilder;
     803: ldc           #236                // String  read
     805: invokevirtual #52                 // Method java/lang/StringBuilder.append:(Ljava/lang/String;)Ljava/lang/StringBuilder;
     808: invokevirtual #55                 // Method java/lang/StringBuilder.toString:()Ljava/lang/String;
     811: invokespecial #237                // Method statisticsIncrement:(Ljava/lang/String;)V
     814: aload         7
     816: aload_3
     817: iload_1
     818: invokestatic  #247                // Method org/h2/index/PageBtreeNode.read:(Lorg/h2/index/PageBtreeIndex;Lorg/h2/store/Data;I)Lorg/h2/store/Page;
     821: astore_2
     822: goto          880
     825: aload_0
     826: aload_3
     827: iload_1
     828: invokestatic  #248                // Method org/h2/store/PageStreamTrunk.read:(Lorg/h2/store/PageStore;Lorg/h2/store/Data;I)Lorg/h2/store/PageStreamTrunk;
     831: astore_2
     832: goto          880
     835: aload_0
     836: aload_3
     837: iload_1
     838: invokestatic  #249                // Method org/h2/store/PageStreamData.read:(Lorg/h2/store/PageStore;Lorg/h2/store/Data;I)Lorg/h2/store/PageStreamData;
     841: astore_2
     842: goto          880
     845: ldc           #49                 // int 90030
     847: new           #50                 // class java/lang/StringBuilder
     850: dup
     851: invokespecial #51                 // Method java/lang/StringBuilder."<init>":()V
     854: ldc           #250                // String page=
     856: invokevirtual #52                 // Method java/lang/StringBuilder.append:(Ljava/lang/String;)Ljava/lang/StringBuilder;
     859: iload_1
     860: invokevirtual #93                 // Method java/lang/StringBuilder.append:(I)Ljava/lang/StringBuilder;
     863: ldc           #251                // String  type=
     865: invokevirtual #52                 // Method java/lang/StringBuilder.append:(Ljava/lang/String;)Ljava/lang/StringBuilder;
     868: iload         4
     870: invokevirtual #93                 // Method java/lang/StringBuilder.append:(I)Ljava/lang/StringBuilder;
     873: invokevirtual #55                 // Method java/lang/StringBuilder.toString:()Ljava/lang/String;
     876: invokestatic  #56                 // Method org/h2/message/DbException.get:(ILjava/lang/String;)Lorg/h2/message/DbException;
     879: athrow
     880: aload_0
     881: getfield      #26                 // Field cache:Lorg/h2/util/Cache;
     884: aload_2
     885: invokeinterface #252,  2          // InterfaceMethod org/h2/util/Cache.put:(Lorg/h2/util/CacheObject;)V
     890: aload_2
     891: areturn

  private int getFirstUncommittedSection();
    Code:
       0: aload_0
       1: getfield      #23                 // Field trace:Lorg/h2/message/Trace;
       4: ldc           #253                // String getFirstUncommittedSection
       6: invokevirtual #132                // Method org/h2/message/Trace.debug:(Ljava/lang/String;)V
       9: aload_0
      10: getfield      #21                 // Field database:Lorg/h2/engine/Database;
      13: iconst_1
      14: invokevirtual #254                // Method org/h2/engine/Database.getSessions:(Z)[Lorg/h2/engine/Session;
      17: astore_1
      18: aload_0
      19: getfield      #71                 // Field log:Lorg/h2/store/PageLog;
      22: invokevirtual #255                // Method org/h2/store/PageLog.getLogSectionId:()I
      25: istore_2
      26: aload_1
      27: astore_3
      28: aload_3
      29: arraylength
      30: istore        4
      32: iconst_0
      33: istore        5
      35: iload         5
      37: iload         4
      39: if_icmpge     76
      42: aload_3
      43: iload         5
      45: aaload
      46: astore        6
      48: aload         6
      50: invokevirtual #256                // Method org/h2/engine/Session.getFirstUncommittedLog:()I
      53: istore        7
      55: iload         7
      57: iconst_m1
      58: if_icmpeq     70
      61: iload         7
      63: iload_2
      64: if_icmpge     70
      67: iload         7
      69: istore_2
      70: iinc          5, 1
      73: goto          35
      76: iload_2
      77: ireturn

  private void readStaticHeader();
    Code:
       0: aload_0
       1: getfield      #37                 // Field file:Lorg/h2/store/FileStore;
       4: ldc2_w        #257                // long 48l
       7: invokevirtual #39                 // Method org/h2/store/FileStore.seek:(J)V
      10: aload_0
      11: getfield      #21                 // Field database:Lorg/h2/engine/Database;
      14: bipush        16
      16: newarray       byte
      18: invokestatic  #259                // Method org/h2/store/Data.create:(Lorg/h2/store/DataHandler;[B)Lorg/h2/store/Data;
      21: astore_1
      22: aload_0
      23: getfield      #37                 // Field file:Lorg/h2/store/FileStore;
      26: aload_1
      27: invokevirtual #224                // Method org/h2/store/Data.getBytes:()[B
      30: iconst_0
      31: bipush        16
      33: invokevirtual #146                // Method org/h2/store/FileStore.readFully:([BII)V
      36: aload_0
      37: dup
      38: getfield      #41                 // Field readCount:J
      41: lconst_1
      42: ladd
      43: putfield      #41                 // Field readCount:J
      46: aload_0
      47: aload_1
      48: invokevirtual #223                // Method org/h2/store/Data.readInt:()I
      51: invokevirtual #61                 // Method setPageSize:(I)V
      54: aload_1
      55: invokevirtual #221                // Method org/h2/store/Data.readByte:()B
      58: istore_2
      59: aload_1
      60: invokevirtual #221                // Method org/h2/store/Data.readByte:()B
      63: istore_3
      64: iload_3
      65: iconst_3
      66: if_icmple     80
      69: ldc_w         #260                // int 90048
      72: aload_0
      73: getfield      #19                 // Field fileName:Ljava/lang/String;
      76: invokestatic  #56                 // Method org/h2/message/DbException.get:(ILjava/lang/String;)Lorg/h2/message/DbException;
      79: athrow
      80: iload_2
      81: iconst_3
      82: if_icmple     124
      85: aload_0
      86: invokevirtual #60                 // Method close:()V
      89: aload_0
      90: getfield      #21                 // Field database:Lorg/h2/engine/Database;
      93: iconst_1
      94: invokevirtual #261                // Method org/h2/engine/Database.setReadOnly:(Z)V
      97: aload_0
      98: ldc_w         #262                // String r
     101: putfield      #20                 // Field accessMode:Ljava/lang/String;
     104: aload_0
     105: aload_0
     106: getfield      #21                 // Field database:Lorg/h2/engine/Database;
     109: aload_0
     110: getfield      #19                 // Field fileName:Ljava/lang/String;
     113: aload_0
     114: getfield      #20                 // Field accessMode:Ljava/lang/String;
     117: iconst_1
     118: invokevirtual #64                 // Method org/h2/engine/Database.openFile:(Ljava/lang/String;Ljava/lang/String;Z)Lorg/h2/store/FileStore;
     121: putfield      #37                 // Field file:Lorg/h2/store/FileStore;
     124: return

  private void readVariableHeader();
    Code:
       0: aload_0
       1: invokevirtual #219                // Method createData:()Lorg/h2/store/Data;
       4: astore_1
       5: iconst_1
       6: istore_2
       7: iload_2
       8: iconst_3
       9: if_icmpne     22
      12: ldc           #49                 // int 90030
      14: aload_0
      15: getfield      #19                 // Field fileName:Ljava/lang/String;
      18: invokestatic  #56                 // Method org/h2/message/DbException.get:(ILjava/lang/String;)Lorg/h2/message/DbException;
      21: athrow
      22: aload_1
      23: invokevirtual #263                // Method org/h2/store/Data.reset:()V
      26: aload_0
      27: iload_2
      28: aload_1
      29: invokevirtual #220                // Method readPage:(ILorg/h2/store/Data;)V
      32: new           #264                // class java/util/zip/CRC32
      35: dup
      36: invokespecial #265                // Method java/util/zip/CRC32."<init>":()V
      39: astore_3
      40: aload_3
      41: aload_1
      42: invokevirtual #224                // Method org/h2/store/Data.getBytes:()[B
      45: iconst_4
      46: aload_0
      47: getfield      #2                  // Field pageSize:I
      50: iconst_4
      51: isub
      52: invokevirtual #266                // Method java/util/zip/CRC32.update:([BII)V
      55: aload_3
      56: invokevirtual #267                // Method java/util/zip/CRC32.getValue:()J
      59: l2i
      60: istore        4
      62: aload_1
      63: invokevirtual #223                // Method org/h2/store/Data.readInt:()I
      66: istore        5
      68: iload         4
      70: iload         5
      72: if_icmpne     110
      75: aload_0
      76: aload_1
      77: invokevirtual #268                // Method org/h2/store/Data.readLong:()J
      80: putfield      #269                // Field writeCountBase:J
      83: aload_0
      84: aload_1
      85: invokevirtual #223                // Method org/h2/store/Data.readInt:()I
      88: putfield      #98                 // Field logKey:I
      91: aload_0
      92: aload_1
      93: invokevirtual #223                // Method org/h2/store/Data.readInt:()I
      96: putfield      #75                 // Field logFirstTrunkPage:I
      99: aload_0
     100: aload_1
     101: invokevirtual #223                // Method org/h2/store/Data.readInt:()I
     104: putfield      #99                 // Field logFirstDataPage:I
     107: goto          116
     110: iinc          2, 1
     113: goto          7
     116: return

  public void setPageSize(int);
    Code:
       0: iload_1
       1: bipush        64
       3: if_icmplt     13
       6: iload_1
       7: ldc_w         #270                // int 32768
      10: if_icmple     46
      13: ldc           #49                 // int 90030
      15: new           #50                 // class java/lang/StringBuilder
      18: dup
      19: invokespecial #51                 // Method java/lang/StringBuilder."<init>":()V
      22: aload_0
      23: getfield      #19                 // Field fileName:Ljava/lang/String;
      26: invokevirtual #52                 // Method java/lang/StringBuilder.append:(Ljava/lang/String;)Ljava/lang/StringBuilder;
      29: ldc_w         #271                // String  pageSize:
      32: invokevirtual #52                 // Method java/lang/StringBuilder.append:(Ljava/lang/String;)Ljava/lang/StringBuilder;
      35: iload_1
      36: invokevirtual #93                 // Method java/lang/StringBuilder.append:(I)Ljava/lang/StringBuilder;
      39: invokevirtual #55                 // Method java/lang/StringBuilder.toString:()Ljava/lang/String;
      42: invokestatic  #56                 // Method org/h2/message/DbException.get:(ILjava/lang/String;)Lorg/h2/message/DbException;
      45: athrow
      46: iconst_0
      47: istore_2
      48: iconst_0
      49: istore_3
      50: iconst_1
      51: istore        4
      53: iload         4
      55: iload_1
      56: if_icmpgt     83
      59: iload_1
      60: iload         4
      62: if_icmpne     70
      65: iconst_1
      66: istore_2
      67: goto          83
      70: iinc          3, 1
      73: iload         4
      75: iload         4
      77: iadd
      78: istore        4
      80: goto          53
      83: iload_2
      84: ifne          97
      87: ldc           #49                 // int 90030
      89: aload_0
      90: getfield      #19                 // Field fileName:Ljava/lang/String;
      93: invokestatic  #56                 // Method org/h2/message/DbException.get:(ILjava/lang/String;)Lorg/h2/message/DbException;
      96: athrow
      97: aload_0
      98: iload_1
      99: putfield      #2                  // Field pageSize:I
     102: aload_0
     103: aload_0
     104: invokevirtual #219                // Method createData:()Lorg/h2/store/Data;
     107: putfield      #272                // Field emptyPage:Lorg/h2/store/Data;
     110: aload_0
     111: iload_3
     112: putfield      #38                 // Field pageSizeShift:I
     115: return

  private void writeStaticHeader();
    Code:
       0: aload_0
       1: getfield      #21                 // Field database:Lorg/h2/engine/Database;
       4: aload_0
       5: getfield      #2                  // Field pageSize:I
       8: bipush        48
      10: isub
      11: newarray       byte
      13: invokestatic  #259                // Method org/h2/store/Data.create:(Lorg/h2/store/DataHandler;[B)Lorg/h2/store/Data;
      16: astore_1
      17: aload_1
      18: aload_0
      19: getfield      #2                  // Field pageSize:I
      22: invokevirtual #273                // Method org/h2/store/Data.writeInt:(I)V
      25: aload_1
      26: iconst_3
      27: invokevirtual #274                // Method org/h2/store/Data.writeByte:(B)V
      30: aload_1
      31: iconst_3
      32: invokevirtual #274                // Method org/h2/store/Data.writeByte:(B)V
      35: aload_0
      36: getfield      #37                 // Field file:Lorg/h2/store/FileStore;
      39: ldc2_w        #257                // long 48l
      42: invokevirtual #39                 // Method org/h2/store/FileStore.seek:(J)V
      45: aload_0
      46: getfield      #37                 // Field file:Lorg/h2/store/FileStore;
      49: aload_1
      50: invokevirtual #224                // Method org/h2/store/Data.getBytes:()[B
      53: iconst_0
      54: aload_0
      55: getfield      #2                  // Field pageSize:I
      58: bipush        48
      60: isub
      61: invokevirtual #147                // Method org/h2/store/FileStore.write:([BII)V
      64: aload_0
      65: dup
      66: getfield      #148                // Field writeCount:J
      69: lconst_1
      70: ladd
      71: putfield      #148                // Field writeCount:J
      74: return

  void setLogFirstPage(int, int, int);
    Code:
       0: aload_0
       1: getfield      #23                 // Field trace:Lorg/h2/message/Trace;
       4: invokevirtual #140                // Method org/h2/message/Trace.isDebugEnabled:()Z
       7: ifeq          57
      10: aload_0
      11: getfield      #23                 // Field trace:Lorg/h2/message/Trace;
      14: new           #50                 // class java/lang/StringBuilder
      17: dup
      18: invokespecial #51                 // Method java/lang/StringBuilder."<init>":()V
      21: ldc_w         #275                // String setLogFirstPage key:
      24: invokevirtual #52                 // Method java/lang/StringBuilder.append:(Ljava/lang/String;)Ljava/lang/StringBuilder;
      27: iload_1
      28: invokevirtual #93                 // Method java/lang/StringBuilder.append:(I)Ljava/lang/StringBuilder;
      31: ldc_w         #276                // String  trunk:
      34: invokevirtual #52                 // Method java/lang/StringBuilder.append:(Ljava/lang/String;)Ljava/lang/StringBuilder;
      37: iload_2
      38: invokevirtual #93                 // Method java/lang/StringBuilder.append:(I)Ljava/lang/StringBuilder;
      41: ldc_w         #277                // String  data:
      44: invokevirtual #52                 // Method java/lang/StringBuilder.append:(Ljava/lang/String;)Ljava/lang/StringBuilder;
      47: iload_3
      48: invokevirtual #93                 // Method java/lang/StringBuilder.append:(I)Ljava/lang/StringBuilder;
      51: invokevirtual #55                 // Method java/lang/StringBuilder.toString:()Ljava/lang/String;
      54: invokevirtual #132                // Method org/h2/message/Trace.debug:(Ljava/lang/String;)V
      57: aload_0
      58: iload_1
      59: putfield      #98                 // Field logKey:I
      62: aload_0
      63: iload_2
      64: putfield      #75                 // Field logFirstTrunkPage:I
      67: aload_0
      68: iload_3
      69: putfield      #99                 // Field logFirstDataPage:I
      72: aload_0
      73: invokespecial #68                 // Method writeVariableHeader:()V
      76: return

  private void writeVariableHeader();
    Code:
       0: aload_0
       1: getfield      #23                 // Field trace:Lorg/h2/message/Trace;
       4: ldc_w         #278                // String writeVariableHeader
       7: invokevirtual #132                // Method org/h2/message/Trace.debug:(Ljava/lang/String;)V
      10: aload_0
      11: getfield      #18                 // Field logMode:I
      14: iconst_2
      15: if_icmpne     25
      18: aload_0
      19: getfield      #37                 // Field file:Lorg/h2/store/FileStore;
      22: invokevirtual #279                // Method org/h2/store/FileStore.sync:()V
      25: aload_0
      26: invokevirtual #219                // Method createData:()Lorg/h2/store/Data;
      29: astore_1
      30: aload_1
      31: iconst_0
      32: invokevirtual #273                // Method org/h2/store/Data.writeInt:(I)V
      35: aload_1
      36: aload_0
      37: invokevirtual #280                // Method getWriteCountTotal:()J
      40: invokevirtual #281                // Method org/h2/store/Data.writeLong:(J)V
      43: aload_1
      44: aload_0
      45: getfield      #98                 // Field logKey:I
      48: invokevirtual #273                // Method org/h2/store/Data.writeInt:(I)V
      51: aload_1
      52: aload_0
      53: getfield      #75                 // Field logFirstTrunkPage:I
      56: invokevirtual #273                // Method org/h2/store/Data.writeInt:(I)V
      59: aload_1
      60: aload_0
      61: getfield      #99                 // Field logFirstDataPage:I
      64: invokevirtual #273                // Method org/h2/store/Data.writeInt:(I)V
      67: new           #264                // class java/util/zip/CRC32
      70: dup
      71: invokespecial #265                // Method java/util/zip/CRC32."<init>":()V
      74: astore_2
      75: aload_2
      76: aload_1
      77: invokevirtual #224                // Method org/h2/store/Data.getBytes:()[B
      80: iconst_4
      81: aload_0
      82: getfield      #2                  // Field pageSize:I
      85: iconst_4
      86: isub
      87: invokevirtual #266                // Method java/util/zip/CRC32.update:([BII)V
      90: aload_1
      91: iconst_0
      92: aload_2
      93: invokevirtual #267                // Method java/util/zip/CRC32.getValue:()J
      96: l2i
      97: invokevirtual #282                // Method org/h2/store/Data.setInt:(II)V
     100: aload_0
     101: getfield      #37                 // Field file:Lorg/h2/store/FileStore;
     104: aload_0
     105: getfield      #2                  // Field pageSize:I
     108: i2l
     109: invokevirtual #39                 // Method org/h2/store/FileStore.seek:(J)V
     112: aload_0
     113: getfield      #37                 // Field file:Lorg/h2/store/FileStore;
     116: aload_1
     117: invokevirtual #224                // Method org/h2/store/Data.getBytes:()[B
     120: iconst_0
     121: aload_0
     122: getfield      #2                  // Field pageSize:I
     125: invokevirtual #147                // Method org/h2/store/FileStore.write:([BII)V
     128: aload_0
     129: getfield      #37                 // Field file:Lorg/h2/store/FileStore;
     132: aload_0
     133: getfield      #2                  // Field pageSize:I
     136: aload_0
     137: getfield      #2                  // Field pageSize:I
     140: iadd
     141: i2l
     142: invokevirtual #39                 // Method org/h2/store/FileStore.seek:(J)V
     145: aload_0
     146: getfield      #37                 // Field file:Lorg/h2/store/FileStore;
     149: aload_1
     150: invokevirtual #224                // Method org/h2/store/Data.getBytes:()[B
     153: iconst_0
     154: aload_0
     155: getfield      #2                  // Field pageSize:I
     158: invokevirtual #147                // Method org/h2/store/FileStore.write:([BII)V
     161: return

  public synchronized void close();
    Code:
       0: aload_0
       1: getfield      #23                 // Field trace:Lorg/h2/message/Trace;
       4: ldc_w         #283                // String close
       7: invokevirtual #132                // Method org/h2/message/Trace.debug:(Ljava/lang/String;)V
      10: aload_0
      11: getfield      #71                 // Field log:Lorg/h2/store/PageLog;
      14: ifnull        29
      17: aload_0
      18: getfield      #71                 // Field log:Lorg/h2/store/PageLog;
      21: invokevirtual #284                // Method org/h2/store/PageLog.close:()V
      24: aload_0
      25: aconst_null
      26: putfield      #71                 // Field log:Lorg/h2/store/PageLog;
      29: aload_0
      30: getfield      #37                 // Field file:Lorg/h2/store/FileStore;
      33: ifnull        66
      36: aload_0
      37: getfield      #37                 // Field file:Lorg/h2/store/FileStore;
      40: invokevirtual #94                 // Method org/h2/store/FileStore.releaseLock:()V
      43: aload_0
      44: getfield      #37                 // Field file:Lorg/h2/store/FileStore;
      47: invokevirtual #95                 // Method org/h2/store/FileStore.close:()V
      50: aload_0
      51: aconst_null
      52: putfield      #37                 // Field file:Lorg/h2/store/FileStore;
      55: goto          66
      58: astore_1
      59: aload_0
      60: aconst_null
      61: putfield      #37                 // Field file:Lorg/h2/store/FileStore;
      64: aload_1
      65: athrow
      66: return
    Exception table:
       from    to  target type
          36    50    58   any
          58    59    58   any

  public synchronized void flushLog();
    Code:
       0: aload_0
       1: getfield      #37                 // Field file:Lorg/h2/store/FileStore;
       4: ifnull        14
       7: aload_0
       8: getfield      #71                 // Field log:Lorg/h2/store/PageLog;
      11: invokevirtual #285                // Method org/h2/store/PageLog.flush:()V
      14: return

  public synchronized void sync();
    Code:
       0: aload_0
       1: getfield      #37                 // Field file:Lorg/h2/store/FileStore;
       4: ifnull        21
       7: aload_0
       8: getfield      #71                 // Field log:Lorg/h2/store/PageLog;
      11: invokevirtual #285                // Method org/h2/store/PageLog.flush:()V
      14: aload_0
      15: getfield      #37                 // Field file:Lorg/h2/store/FileStore;
      18: invokevirtual #279                // Method org/h2/store/FileStore.sync:()V
      21: return

  public org.h2.message.Trace getTrace();
    Code:
       0: aload_0
       1: getfield      #23                 // Field trace:Lorg/h2/message/Trace;
       4: areturn

  public synchronized void writeBack(org.h2.util.CacheObject);
    Code:
       0: aload_1
       1: checkcast     #203                // class org/h2/store/Page
       4: astore_2
       5: aload_0
       6: getfield      #23                 // Field trace:Lorg/h2/message/Trace;
       9: invokevirtual #140                // Method org/h2/message/Trace.isDebugEnabled:()Z
      12: ifeq          42
      15: aload_0
      16: getfield      #23                 // Field trace:Lorg/h2/message/Trace;
      19: new           #50                 // class java/lang/StringBuilder
      22: dup
      23: invokespecial #51                 // Method java/lang/StringBuilder."<init>":()V
      26: ldc_w         #286                // String writeBack
      29: invokevirtual #52                 // Method java/lang/StringBuilder.append:(Ljava/lang/String;)Ljava/lang/StringBuilder;
      32: aload_2
      33: invokevirtual #205                // Method java/lang/StringBuilder.append:(Ljava/lang/Object;)Ljava/lang/StringBuilder;
      36: invokevirtual #55                 // Method java/lang/StringBuilder.toString:()Ljava/lang/String;
      39: invokevirtual #132                // Method org/h2/message/Trace.debug:(Ljava/lang/String;)V
      42: aload_2
      43: invokevirtual #287                // Method org/h2/store/Page.write:()V
      46: aload_2
      47: iconst_0
      48: invokevirtual #288                // Method org/h2/store/Page.setChanged:(Z)V
      51: return

  public synchronized void logUndo(org.h2.store.Page, org.h2.store.Data);
    Code:
       0: aload_0
       1: getfield      #18                 // Field logMode:I
       4: ifne          8
       7: return
       8: aload_0
       9: invokespecial #289                // Method checkOpen:()V
      12: aload_0
      13: getfield      #21                 // Field database:Lorg/h2/engine/Database;
      16: invokevirtual #290                // Method org/h2/engine/Database.checkWritingAllowed:()V
      19: aload_0
      20: getfield      #66                 // Field recoveryRunning:Z
      23: ifne          65
      26: aload_1
      27: invokevirtual #213                // Method org/h2/store/Page.getPos:()I
      30: istore_3
      31: aload_0
      32: getfield      #71                 // Field log:Lorg/h2/store/PageLog;
      35: iload_3
      36: invokevirtual #291                // Method org/h2/store/PageLog.getUndo:(I)Z
      39: ifne          65
      42: aload_2
      43: ifnonnull     52
      46: aload_0
      47: iload_3
      48: invokevirtual #292                // Method readPage:(I)Lorg/h2/store/Data;
      51: astore_2
      52: aload_0
      53: invokespecial #107                // Method openForWriting:()V
      56: aload_0
      57: getfield      #71                 // Field log:Lorg/h2/store/PageLog;
      60: iload_3
      61: aload_2
      62: invokevirtual #293                // Method org/h2/store/PageLog.addUndo:(ILorg/h2/store/Data;)V
      65: return

  public synchronized void update(org.h2.store.Page);
    Code:
       0: aload_0
       1: getfield      #23                 // Field trace:Lorg/h2/message/Trace;
       4: invokevirtual #140                // Method org/h2/message/Trace.isDebugEnabled:()Z
       7: ifeq          47
      10: aload_1
      11: invokevirtual #294                // Method org/h2/store/Page.isChanged:()Z
      14: ifne          47
      17: aload_0
      18: getfield      #23                 // Field trace:Lorg/h2/message/Trace;
      21: new           #50                 // class java/lang/StringBuilder
      24: dup
      25: invokespecial #51                 // Method java/lang/StringBuilder."<init>":()V
      28: ldc_w         #295                // String updateRecord
      31: invokevirtual #52                 // Method java/lang/StringBuilder.append:(Ljava/lang/String;)Ljava/lang/StringBuilder;
      34: aload_1
      35: invokevirtual #296                // Method java/lang/Object.toString:()Ljava/lang/String;
      38: invokevirtual #52                 // Method java/lang/StringBuilder.append:(Ljava/lang/String;)Ljava/lang/StringBuilder;
      41: invokevirtual #55                 // Method java/lang/StringBuilder.toString:()Ljava/lang/String;
      44: invokevirtual #132                // Method org/h2/message/Trace.debug:(Ljava/lang/String;)V
      47: aload_0
      48: invokespecial #289                // Method checkOpen:()V
      51: aload_0
      52: getfield      #21                 // Field database:Lorg/h2/engine/Database;
      55: invokevirtual #290                // Method org/h2/engine/Database.checkWritingAllowed:()V
      58: aload_1
      59: iconst_1
      60: invokevirtual #288                // Method org/h2/store/Page.setChanged:(Z)V
      63: aload_1
      64: invokevirtual #213                // Method org/h2/store/Page.getPos:()I
      67: istore_2
      68: getstatic     #217                // Field org/h2/engine/SysProperties.CHECK:Z
      71: ifeq          97
      74: aload_0
      75: getfield      #66                 // Field recoveryRunning:Z
      78: ifne          97
      81: aload_0
      82: getfield      #18                 // Field logMode:I
      85: ifeq          97
      88: aload_0
      89: getfield      #71                 // Field log:Lorg/h2/store/PageLog;
      92: iload_2
      93: aconst_null
      94: invokevirtual #293                // Method org/h2/store/PageLog.addUndo:(ILorg/h2/store/Data;)V
      97: aload_0
      98: iload_2
      99: invokevirtual #155                // Method allocatePage:(I)V
     102: aload_0
     103: getfield      #26                 // Field cache:Lorg/h2/util/Cache;
     106: iload_2
     107: aload_1
     108: invokeinterface #297,  3          // InterfaceMethod org/h2/util/Cache.update:(ILorg/h2/util/CacheObject;)Lorg/h2/util/CacheObject;
     113: pop
     114: return

  private int getFreeListId(int);
    Code:
       0: iload_1
       1: iconst_3
       2: isub
       3: aload_0
       4: getfield      #63                 // Field freeListPagesPerList:I
       7: idiv
       8: ireturn

  private org.h2.store.PageFreeList getFreeListForPage(int);
    Code:
       0: aload_0
       1: aload_0
       2: iload_1
       3: invokespecial #152                // Method getFreeListId:(I)I
       6: invokespecial #153                // Method getFreeList:(I)Lorg/h2/store/PageFreeList;
       9: areturn

  private org.h2.store.PageFreeList getFreeList(int);
    Code:
       0: aconst_null
       1: astore_2
       2: iload_1
       3: aload_0
       4: getfield      #16                 // Field freeLists:Ljava/util/ArrayList;
       7: invokevirtual #181                // Method java/util/ArrayList.size:()I
      10: if_icmpge     31
      13: aload_0
      14: getfield      #16                 // Field freeLists:Ljava/util/ArrayList;
      17: iload_1
      18: invokevirtual #182                // Method java/util/ArrayList.get:(I)Ljava/lang/Object;
      21: checkcast     #298                // class org/h2/store/PageFreeList
      24: astore_2
      25: aload_2
      26: ifnull        31
      29: aload_2
      30: areturn
      31: iconst_3
      32: iload_1
      33: aload_0
      34: getfield      #63                 // Field freeListPagesPerList:I
      37: imul
      38: iadd
      39: istore_3
      40: iload_3
      41: aload_0
      42: getfield      #36                 // Field pageCount:I
      45: if_icmplt     55
      48: aload_0
      49: invokespecial #78                 // Method increaseFileSize:()V
      52: goto          40
      55: iload_3
      56: aload_0
      57: getfield      #36                 // Field pageCount:I
      60: if_icmpge     72
      63: aload_0
      64: iload_3
      65: invokevirtual #183                // Method getPage:(I)Lorg/h2/store/Page;
      68: checkcast     #298                // class org/h2/store/PageFreeList
      71: astore_2
      72: aload_2
      73: ifnonnull     92
      76: aload_0
      77: iload_3
      78: invokestatic  #299                // Method org/h2/store/PageFreeList.create:(Lorg/h2/store/PageStore;I)Lorg/h2/store/PageFreeList;
      81: astore_2
      82: aload_0
      83: getfield      #26                 // Field cache:Lorg/h2/util/Cache;
      86: aload_2
      87: invokeinterface #252,  2          // InterfaceMethod org/h2/util/Cache.put:(Lorg/h2/util/CacheObject;)V
      92: aload_0
      93: getfield      #16                 // Field freeLists:Ljava/util/ArrayList;
      96: invokevirtual #181                // Method java/util/ArrayList.size:()I
      99: iload_1
     100: if_icmpgt     115
     103: aload_0
     104: getfield      #16                 // Field freeLists:Ljava/util/ArrayList;
     107: aconst_null
     108: invokevirtual #300                // Method java/util/ArrayList.add:(Ljava/lang/Object;)Z
     111: pop
     112: goto          92
     115: aload_0
     116: getfield      #16                 // Field freeLists:Ljava/util/ArrayList;
     119: iload_1
     120: aload_2
     121: invokevirtual #189                // Method java/util/ArrayList.set:(ILjava/lang/Object;)Ljava/lang/Object;
     124: pop
     125: aload_2
     126: areturn

  private void freePage(int);
    Code:
       0: aload_0
       1: iload_1
       2: invokespecial #152                // Method getFreeListId:(I)I
       5: istore_2
       6: aload_0
       7: iload_2
       8: invokespecial #153                // Method getFreeList:(I)Lorg/h2/store/PageFreeList;
      11: astore_3
      12: aload_0
      13: iload_2
      14: aload_0
      15: getfield      #301                // Field firstFreeListIndex:I
      18: invokestatic  #302                // Method java/lang/Math.min:(II)I
      21: putfield      #301                // Field firstFreeListIndex:I
      24: aload_3
      25: iload_1
      26: invokevirtual #303                // Method org/h2/store/PageFreeList.free:(I)V
      29: return

  void allocatePage(int);
    Code:
       0: aload_0
       1: iload_1
       2: invokespecial #304                // Method getFreeListForPage:(I)Lorg/h2/store/PageFreeList;
       5: astore_2
       6: aload_2
       7: iload_1
       8: invokevirtual #305                // Method org/h2/store/PageFreeList.allocate:(I)V
      11: return

  private boolean isUsed(int);
    Code:
       0: aload_0
       1: iload_1
       2: invokespecial #304                // Method getFreeListForPage:(I)Lorg/h2/store/PageFreeList;
       5: iload_1
       6: invokevirtual #306                // Method org/h2/store/PageFreeList.isUsed:(I)Z
       9: ireturn

  void allocatePages(org.h2.util.IntArray, int, org.h2.util.BitField, int);
    Code:
       0: aload_1
       1: aload_1
       2: invokevirtual #307                // Method org/h2/util/IntArray.size:()I
       5: iload_2
       6: iadd
       7: invokevirtual #308                // Method org/h2/util/IntArray.ensureCapacity:(I)V
      10: iconst_0
      11: istore        5
      13: iload         5
      15: iload_2
      16: if_icmpge     44
      19: aload_0
      20: aload_3
      21: iload         4
      23: invokespecial #309                // Method allocatePage:(Lorg/h2/util/BitField;I)I
      26: istore        6
      28: iload         6
      30: istore        4
      32: aload_1
      33: iload         6
      35: invokevirtual #310                // Method org/h2/util/IntArray.add:(I)V
      38: iinc          5, 1
      41: goto          13
      44: return

  public synchronized int allocatePage();
    Code:
       0: aload_0
       1: invokespecial #107                // Method openForWriting:()V
       4: aload_0
       5: aconst_null
       6: iconst_0
       7: invokespecial #309                // Method allocatePage:(Lorg/h2/util/BitField;I)I
      10: istore_1
      11: aload_0
      12: getfield      #66                 // Field recoveryRunning:Z
      15: ifne          37
      18: aload_0
      19: getfield      #18                 // Field logMode:I
      22: ifeq          37
      25: aload_0
      26: getfield      #71                 // Field log:Lorg/h2/store/PageLog;
      29: iload_1
      30: aload_0
      31: getfield      #272                // Field emptyPage:Lorg/h2/store/Data;
      34: invokevirtual #293                // Method org/h2/store/PageLog.addUndo:(ILorg/h2/store/Data;)V
      37: iload_1
      38: ireturn

  private int allocatePage(org.h2.util.BitField, int);
    Code:
       0: aload_0
       1: getfield      #301                // Field firstFreeListIndex:I
       4: istore        4
       6: aload_0
       7: iload         4
       9: invokespecial #153                // Method getFreeList:(I)Lorg/h2/store/PageFreeList;
      12: astore        5
      14: aload         5
      16: aload_1
      17: iload_2
      18: invokevirtual #311                // Method org/h2/store/PageFreeList.allocate:(Lorg/h2/util/BitField;I)I
      21: istore_3
      22: iload_3
      23: iflt          35
      26: aload_0
      27: iload         4
      29: putfield      #301                // Field firstFreeListIndex:I
      32: goto          41
      35: iinc          4, 1
      38: goto          6
      41: iload_3
      42: aload_0
      43: getfield      #36                 // Field pageCount:I
      46: if_icmplt     56
      49: aload_0
      50: invokespecial #78                 // Method increaseFileSize:()V
      53: goto          41
      56: aload_0
      57: getfield      #23                 // Field trace:Lorg/h2/message/Trace;
      60: invokevirtual #140                // Method org/h2/message/Trace.isDebugEnabled:()Z
      63: ifeq          66
      66: iload_3
      67: ireturn

  private void increaseFileSize();
    Code:
       0: ldc_w         #312                // int 1048576
       3: aload_0
       4: getfield      #2                  // Field pageSize:I
       7: idiv
       8: istore_1
       9: aload_0
      10: getfield      #36                 // Field pageCount:I
      13: bipush        35
      15: imul
      16: bipush        100
      18: idiv
      19: istore_2
      20: iload_1
      21: iload_2
      22: if_icmpge     33
      25: iconst_1
      26: iload_2
      27: iload_1
      28: idiv
      29: iadd
      30: iload_1
      31: imul
      32: istore_1
      33: aload_0
      34: getfield      #21                 // Field database:Lorg/h2/engine/Database;
      37: invokevirtual #150                // Method org/h2/engine/Database.getSettings:()Lorg/h2/engine/DbSettings;
      40: getfield      #313                // Field org/h2/engine/DbSettings.pageStoreMaxGrowth:I
      43: istore_3
      44: iload_3
      45: iload_1
      46: if_icmpge     51
      49: iload_3
      50: istore_1
      51: aload_0
      52: iload_1
      53: invokespecial #72                 // Method increaseFileSize:(I)V
      56: return

  private void increaseFileSize(int);
    Code:
       0: aload_0
       1: getfield      #36                 // Field pageCount:I
       4: istore_2
       5: iload_2
       6: aload_0
       7: getfield      #36                 // Field pageCount:I
      10: iload_1
      11: iadd
      12: if_icmpge     29
      15: aload_0
      16: getfield      #14                 // Field freed:Lorg/h2/util/BitField;
      19: iload_2
      20: invokevirtual #149                // Method org/h2/util/BitField.set:(I)V
      23: iinc          2, 1
      26: goto          5
      29: aload_0
      30: dup
      31: getfield      #36                 // Field pageCount:I
      34: iload_1
      35: iadd
      36: putfield      #36                 // Field pageCount:I
      39: aload_0
      40: getfield      #36                 // Field pageCount:I
      43: i2l
      44: aload_0
      45: getfield      #38                 // Field pageSizeShift:I
      48: lshl
      49: lstore_2
      50: aload_0
      51: getfield      #37                 // Field file:Lorg/h2/store/FileStore;
      54: lload_2
      55: invokevirtual #194                // Method org/h2/store/FileStore.setLength:(J)V
      58: aload_0
      59: dup
      60: getfield      #148                // Field writeCount:J
      63: lconst_1
      64: ladd
      65: putfield      #148                // Field writeCount:J
      68: aload_0
      69: lload_2
      70: putfield      #91                 // Field fileLength:J
      73: return

  public synchronized void free(int);
    Code:
       0: aload_0
       1: iload_1
       2: iconst_1
       3: invokevirtual #314                // Method free:(IZ)V
       6: return

  void free(int, boolean);
    Code:
       0: aload_0
       1: getfield      #23                 // Field trace:Lorg/h2/message/Trace;
       4: invokevirtual #140                // Method org/h2/message/Trace.isDebugEnabled:()Z
       7: ifeq          10
      10: aload_0
      11: getfield      #26                 // Field cache:Lorg/h2/util/Cache;
      14: iload_1
      15: invokeinterface #315,  2          // InterfaceMethod org/h2/util/Cache.remove:(I)Z
      20: pop
      21: getstatic     #217                // Field org/h2/engine/SysProperties.CHECK:Z
      24: ifeq          54
      27: aload_0
      28: getfield      #66                 // Field recoveryRunning:Z
      31: ifne          54
      34: iload_2
      35: ifeq          54
      38: aload_0
      39: getfield      #18                 // Field logMode:I
      42: ifeq          54
      45: aload_0
      46: getfield      #71                 // Field log:Lorg/h2/store/PageLog;
      49: iload_1
      50: aconst_null
      51: invokevirtual #293                // Method org/h2/store/PageLog.addUndo:(ILorg/h2/store/Data;)V
      54: aload_0
      55: iload_1
      56: invokespecial #210                // Method freePage:(I)V
      59: aload_0
      60: getfield      #66                 // Field recoveryRunning:Z
      63: ifeq          130
      66: aload_0
      67: iload_1
      68: aload_0
      69: invokevirtual #219                // Method createData:()Lorg/h2/store/Data;
      72: invokevirtual #316                // Method writePage:(ILorg/h2/store/Data;)V
      75: aload_0
      76: getfield      #317                // Field reservedPages:Ljava/util/HashMap;
      79: ifnull        130
      82: aload_0
      83: getfield      #317                // Field reservedPages:Ljava/util/HashMap;
      86: iload_1
      87: invokestatic  #34                 // Method java/lang/Integer.valueOf:(I)Ljava/lang/Integer;
      90: invokevirtual #318                // Method java/util/HashMap.containsKey:(Ljava/lang/Object;)Z
      93: ifeq          130
      96: aload_0
      97: getfield      #317                // Field reservedPages:Ljava/util/HashMap;
     100: iload_1
     101: invokestatic  #34                 // Method java/lang/Integer.valueOf:(I)Ljava/lang/Integer;
     104: invokevirtual #31                 // Method java/util/HashMap.get:(Ljava/lang/Object;)Ljava/lang/Object;
     107: checkcast     #32                 // class java/lang/Integer
     110: invokevirtual #33                 // Method java/lang/Integer.intValue:()I
     113: istore_3
     114: iload_3
     115: aload_0
     116: getfield      #71                 // Field log:Lorg/h2/store/PageLog;
     119: invokevirtual #319                // Method org/h2/store/PageLog.getLogPos:()I
     122: if_icmple     130
     125: aload_0
     126: iload_1
     127: invokevirtual #155                // Method allocatePage:(I)V
     130: return

  void freeUnused(int);
    Code:
       0: aload_0
       1: getfield      #23                 // Field trace:Lorg/h2/message/Trace;
       4: invokevirtual #140                // Method org/h2/message/Trace.isDebugEnabled:()Z
       7: ifeq          37
      10: aload_0
      11: getfield      #23                 // Field trace:Lorg/h2/message/Trace;
      14: new           #50                 // class java/lang/StringBuilder
      17: dup
      18: invokespecial #51                 // Method java/lang/StringBuilder."<init>":()V
      21: ldc_w         #320                // String freeUnused
      24: invokevirtual #52                 // Method java/lang/StringBuilder.append:(Ljava/lang/String;)Ljava/lang/StringBuilder;
      27: iload_1
      28: invokevirtual #93                 // Method java/lang/StringBuilder.append:(I)Ljava/lang/StringBuilder;
      31: invokevirtual #55                 // Method java/lang/StringBuilder.toString:()Ljava/lang/String;
      34: invokevirtual #132                // Method org/h2/message/Trace.debug:(Ljava/lang/String;)V
      37: aload_0
      38: getfield      #26                 // Field cache:Lorg/h2/util/Cache;
      41: iload_1
      42: invokeinterface #315,  2          // InterfaceMethod org/h2/util/Cache.remove:(I)Z
      47: pop
      48: aload_0
      49: iload_1
      50: invokespecial #210                // Method freePage:(I)V
      53: aload_0
      54: getfield      #14                 // Field freed:Lorg/h2/util/BitField;
      57: iload_1
      58: invokevirtual #149                // Method org/h2/util/BitField.set:(I)V
      61: return

  public org.h2.store.Data createData();
    Code:
       0: aload_0
       1: getfield      #21                 // Field database:Lorg/h2/engine/Database;
       4: aload_0
       5: getfield      #2                  // Field pageSize:I
       8: newarray       byte
      10: invokestatic  #259                // Method org/h2/store/Data.create:(Lorg/h2/store/DataHandler;[B)Lorg/h2/store/Data;
      13: areturn

  public synchronized org.h2.store.Data readPage(int);
    Code:
       0: aload_0
       1: invokevirtual #219                // Method createData:()Lorg/h2/store/Data;
       4: astore_2
       5: aload_0
       6: iload_1
       7: aload_2
       8: invokevirtual #220                // Method readPage:(ILorg/h2/store/Data;)V
      11: aload_2
      12: areturn

  void readPage(int, org.h2.store.Data);
    Code:
       0: aload_0
       1: getfield      #169                // Field recordPageReads:Z
       4: ifeq          51
       7: iload_1
       8: iconst_5
       9: if_icmplt     51
      12: aload_0
      13: getfield      #168                // Field recordedPagesIndex:Lorg/h2/util/IntIntHashMap;
      16: iload_1
      17: invokevirtual #188                // Method org/h2/util/IntIntHashMap.get:(I)I
      20: iconst_m1
      21: if_icmpne     51
      24: aload_0
      25: getfield      #168                // Field recordedPagesIndex:Lorg/h2/util/IntIntHashMap;
      28: iload_1
      29: aload_0
      30: getfield      #167                // Field recordedPagesList:Ljava/util/ArrayList;
      33: invokevirtual #181                // Method java/util/ArrayList.size:()I
      36: invokevirtual #43                 // Method org/h2/util/IntIntHashMap.put:(II)V
      39: aload_0
      40: getfield      #167                // Field recordedPagesList:Ljava/util/ArrayList;
      43: iload_1
      44: invokestatic  #34                 // Method java/lang/Integer.valueOf:(I)Ljava/lang/Integer;
      47: invokevirtual #300                // Method java/util/ArrayList.add:(Ljava/lang/Object;)Z
      50: pop
      51: iload_1
      52: iflt          63
      55: iload_1
      56: aload_0
      57: getfield      #36                 // Field pageCount:I
      60: if_icmplt     96
      63: ldc           #49                 // int 90030
      65: new           #50                 // class java/lang/StringBuilder
      68: dup
      69: invokespecial #51                 // Method java/lang/StringBuilder."<init>":()V
      72: iload_1
      73: invokevirtual #93                 // Method java/lang/StringBuilder.append:(I)Ljava/lang/StringBuilder;
      76: ldc_w         #321                // String  of
      79: invokevirtual #52                 // Method java/lang/StringBuilder.append:(Ljava/lang/String;)Ljava/lang/StringBuilder;
      82: aload_0
      83: getfield      #36                 // Field pageCount:I
      86: invokevirtual #93                 // Method java/lang/StringBuilder.append:(I)Ljava/lang/StringBuilder;
      89: invokevirtual #55                 // Method java/lang/StringBuilder.toString:()Ljava/lang/String;
      92: invokestatic  #56                 // Method org/h2/message/DbException.get:(ILjava/lang/String;)Lorg/h2/message/DbException;
      95: athrow
      96: aload_0
      97: getfield      #37                 // Field file:Lorg/h2/store/FileStore;
     100: iload_1
     101: i2l
     102: aload_0
     103: getfield      #38                 // Field pageSizeShift:I
     106: lshl
     107: invokevirtual #39                 // Method org/h2/store/FileStore.seek:(J)V
     110: aload_0
     111: getfield      #37                 // Field file:Lorg/h2/store/FileStore;
     114: aload_2
     115: invokevirtual #224                // Method org/h2/store/Data.getBytes:()[B
     118: iconst_0
     119: aload_0
     120: getfield      #2                  // Field pageSize:I
     123: invokevirtual #146                // Method org/h2/store/FileStore.readFully:([BII)V
     126: aload_0
     127: dup
     128: getfield      #41                 // Field readCount:J
     131: lconst_1
     132: ladd
     133: putfield      #41                 // Field readCount:J
     136: return

  public int getPageSize();
    Code:
       0: aload_0
       1: getfield      #2                  // Field pageSize:I
       4: ireturn

  public int getPageCount();
    Code:
       0: aload_0
       1: getfield      #36                 // Field pageCount:I
       4: ireturn

  public synchronized void writePage(int, org.h2.store.Data);
    Code:
       0: iload_1
       1: ifgt          28
       4: new           #50                 // class java/lang/StringBuilder
       7: dup
       8: invokespecial #51                 // Method java/lang/StringBuilder."<init>":()V
      11: ldc_w         #322                // String write to page
      14: invokevirtual #52                 // Method java/lang/StringBuilder.append:(Ljava/lang/String;)Ljava/lang/StringBuilder;
      17: iload_1
      18: invokevirtual #93                 // Method java/lang/StringBuilder.append:(I)Ljava/lang/StringBuilder;
      21: invokevirtual #55                 // Method java/lang/StringBuilder.toString:()Ljava/lang/String;
      24: invokestatic  #186                // Method org/h2/message/DbException.throwInternalError:(Ljava/lang/String;)Ljava/lang/RuntimeException;
      27: pop
      28: aload_2
      29: invokevirtual #224                // Method org/h2/store/Data.getBytes:()[B
      32: astore_3
      33: getstatic     #217                // Field org/h2/engine/SysProperties.CHECK:Z
      36: ifeq          89
      39: iload_1
      40: iconst_3
      41: isub
      42: aload_0
      43: getfield      #63                 // Field freeListPagesPerList:I
      46: irem
      47: ifne          54
      50: iconst_1
      51: goto          55
      54: iconst_0
      55: istore        4
      57: aload_3
      58: iconst_0
      59: baload
      60: bipush        6
      62: if_icmpne     69
      65: iconst_1
      66: goto          70
      69: iconst_0
      70: istore        5
      72: aload_3
      73: iconst_0
      74: baload
      75: ifeq          89
      78: iload         4
      80: iload         5
      82: if_icmpeq     89
      85: invokestatic  #323                // Method org/h2/message/DbException.throwInternalError:()Ljava/lang/RuntimeException;
      88: athrow
      89: aload_0
      90: aload_3
      91: iload_1
      92: invokespecial #324                // Method checksumSet:([BI)V
      95: aload_0
      96: getfield      #37                 // Field file:Lorg/h2/store/FileStore;
      99: iload_1
     100: i2l
     101: aload_0
     102: getfield      #38                 // Field pageSizeShift:I
     105: lshl
     106: invokevirtual #39                 // Method org/h2/store/FileStore.seek:(J)V
     109: aload_0
     110: getfield      #37                 // Field file:Lorg/h2/store/FileStore;
     113: aload_3
     114: iconst_0
     115: aload_0
     116: getfield      #2                  // Field pageSize:I
     119: invokevirtual #147                // Method org/h2/store/FileStore.write:([BII)V
     122: aload_0
     123: dup
     124: getfield      #148                // Field writeCount:J
     127: lconst_1
     128: ladd
     129: putfield      #148                // Field writeCount:J
     132: return

  public synchronized void removeFromCache(int);
    Code:
       0: aload_0
       1: getfield      #26                 // Field cache:Lorg/h2/util/Cache;
       4: iload_1
       5: invokeinterface #315,  2          // InterfaceMethod org/h2/util/Cache.remove:(I)Z
      10: pop
      11: return

  org.h2.engine.Database getDatabase();
    Code:
       0: aload_0
       1: getfield      #21                 // Field database:Lorg/h2/engine/Database;
       4: areturn

  private boolean recover();
    Code:
       0: aload_0
       1: getfield      #23                 // Field trace:Lorg/h2/message/Trace;
       4: ldc_w         #325                // String log recover
       7: invokevirtual #132                // Method org/h2/message/Trace.debug:(Ljava/lang/String;)V
      10: aload_0
      11: iconst_1
      12: putfield      #66                 // Field recoveryRunning:Z
      15: iconst_1
      16: istore_1
      17: iload_1
      18: aload_0
      19: getfield      #71                 // Field log:Lorg/h2/store/PageLog;
      22: iconst_0
      23: invokevirtual #326                // Method org/h2/store/PageLog.recover:(I)Z
      26: iand
      27: istore_1
      28: aload_0
      29: getfield      #317                // Field reservedPages:Ljava/util/HashMap;
      32: ifnull        115
      35: aload_0
      36: getfield      #317                // Field reservedPages:Ljava/util/HashMap;
      39: invokevirtual #327                // Method java/util/HashMap.keySet:()Ljava/util/Set;
      42: invokeinterface #328,  1          // InterfaceMethod java/util/Set.iterator:()Ljava/util/Iterator;
      47: astore_2
      48: aload_2
      49: invokeinterface #115,  1          // InterfaceMethod java/util/Iterator.hasNext:()Z
      54: ifeq          115
      57: aload_2
      58: invokeinterface #116,  1          // InterfaceMethod java/util/Iterator.next:()Ljava/lang/Object;
      63: checkcast     #32                 // class java/lang/Integer
      66: invokevirtual #33                 // Method java/lang/Integer.intValue:()I
      69: istore_3
      70: aload_0
      71: getfield      #23                 // Field trace:Lorg/h2/message/Trace;
      74: invokevirtual #140                // Method org/h2/message/Trace.isDebugEnabled:()Z
      77: ifeq          107
      80: aload_0
      81: getfield      #23                 // Field trace:Lorg/h2/message/Trace;
      84: new           #50                 // class java/lang/StringBuilder
      87: dup
      88: invokespecial #51                 // Method java/lang/StringBuilder."<init>":()V
      91: ldc_w         #329                // String reserve
      94: invokevirtual #52                 // Method java/lang/StringBuilder.append:(Ljava/lang/String;)Ljava/lang/StringBuilder;
      97: iload_3
      98: invokevirtual #93                 // Method java/lang/StringBuilder.append:(I)Ljava/lang/StringBuilder;
     101: invokevirtual #55                 // Method java/lang/StringBuilder.toString:()Ljava/lang/String;
     104: invokevirtual #132                // Method org/h2/message/Trace.debug:(Ljava/lang/String;)V
     107: aload_0
     108: iload_3
     109: invokevirtual #155                // Method allocatePage:(I)V
     112: goto          48
     115: iload_1
     116: aload_0
     117: getfield      #71                 // Field log:Lorg/h2/store/PageLog;
     120: iconst_1
     121: invokevirtual #326                // Method org/h2/store/PageLog.recover:(I)Z
     124: iand
     125: istore_1
     126: aload_0
     127: invokespecial #73                 // Method openMetaIndex:()V
     130: aload_0
     131: invokespecial #330                // Method readMetaData:()V
     134: iload_1
     135: aload_0
     136: getfield      #71                 // Field log:Lorg/h2/store/PageLog;
     139: iconst_2
     140: invokevirtual #326                // Method org/h2/store/PageLog.recover:(I)Z
     143: iand
     144: istore_1
     145: iconst_0
     146: istore_2
     147: aload_0
     148: getfield      #21                 // Field database:Lorg/h2/engine/Database;
     151: invokevirtual #48                 // Method org/h2/engine/Database.isReadOnly:()Z
     154: ifne          195
     157: aload_0
     158: getfield      #71                 // Field log:Lorg/h2/store/PageLog;
     161: invokevirtual #331                // Method org/h2/store/PageLog.getInDoubtTransactions:()Ljava/util/ArrayList;
     164: invokevirtual #332                // Method java/util/ArrayList.isEmpty:()Z
     167: ifeq          193
     170: aload_0
     171: getfield      #71                 // Field log:Lorg/h2/store/PageLog;
     174: invokevirtual #333                // Method org/h2/store/PageLog.recoverEnd:()V
     177: aload_0
     178: invokespecial #138                // Method getFirstUncommittedSection:()I
     181: istore_3
     182: aload_0
     183: getfield      #71                 // Field log:Lorg/h2/store/PageLog;
     186: iload_3
     187: invokevirtual #139                // Method org/h2/store/PageLog.removeUntil:(I)V
     190: goto          195
     193: iconst_1
     194: istore_2
     195: aload_0
     196: getfield      #8                  // Field metaObjects:Ljava/util/HashMap;
     199: iconst_0
     200: invokestatic  #34                 // Method java/lang/Integer.valueOf:(I)Ljava/lang/Integer;
     203: invokevirtual #31                 // Method java/util/HashMap.get:(Ljava/lang/Object;)Ljava/lang/Object;
     206: checkcast     #230                // class org/h2/index/PageDataIndex
     209: astore_3
     210: aload_0
     211: aload_3
     212: ifnonnull     219
     215: iconst_1
     216: goto          220
     219: iconst_0
     220: putfield      #77                 // Field isNew:Z
     223: aload_0
     224: getfield      #8                  // Field metaObjects:Ljava/util/HashMap;
     227: invokevirtual #113                // Method java/util/HashMap.values:()Ljava/util/Collection;
     230: invokeinterface #114,  1          // InterfaceMethod java/util/Collection.iterator:()Ljava/util/Iterator;
     235: astore        4
     237: aload         4
     239: invokeinterface #115,  1          // InterfaceMethod java/util/Iterator.hasNext:()Z
     244: ifeq          321
     247: aload         4
     249: invokeinterface #116,  1          // InterfaceMethod java/util/Iterator.next:()Ljava/lang/Object;
     254: checkcast     #117                // class org/h2/index/PageIndex
     257: astore        5
     259: aload         5
     261: invokevirtual #118                // Method org/h2/index/PageIndex.getTable:()Lorg/h2/table/Table;
     264: invokevirtual #119                // Method org/h2/table/Table.isTemporary:()Z
     267: ifeq          309
     270: aload_0
     271: getfield      #106                // Field tempObjects:Ljava/util/HashMap;
     274: ifnonnull     288
     277: aload_0
     278: new           #6                  // class java/util/HashMap
     281: dup
     282: invokespecial #7                  // Method java/util/HashMap."<init>":()V
     285: putfield      #106                // Field tempObjects:Ljava/util/HashMap;
     288: aload_0
     289: getfield      #106                // Field tempObjects:Ljava/util/HashMap;
     292: aload         5
     294: invokevirtual #334                // Method org/h2/index/PageIndex.getId:()I
     297: invokestatic  #34                 // Method java/lang/Integer.valueOf:(I)Ljava/lang/Integer;
     300: aload         5
     302: invokevirtual #35                 // Method java/util/HashMap.put:(Ljava/lang/Object;Ljava/lang/Object;)Ljava/lang/Object;
     305: pop
     306: goto          318
     309: aload         5
     311: aload_0
     312: getfield      #29                 // Field pageStoreSession:Lorg/h2/engine/Session;
     315: invokevirtual #335                // Method org/h2/index/PageIndex.close:(Lorg/h2/engine/Session;)V
     318: goto          237
     321: aload_0
     322: iconst_4
     323: invokevirtual #155                // Method allocatePage:(I)V
     326: aload_0
     327: invokespecial #135                // Method writeIndexRowCounts:()V
     330: aload_0
     331: iconst_0
     332: putfield      #66                 // Field recoveryRunning:Z
     335: aload_0
     336: aconst_null
     337: putfield      #317                // Field reservedPages:Ljava/util/HashMap;
     340: aload_0
     341: invokespecial #137                // Method writeBack:()V
     344: aload_0
     345: getfield      #26                 // Field cache:Lorg/h2/util/Cache;
     348: invokeinterface #165,  1          // InterfaceMethod org/h2/util/Cache.clear:()V
     353: aload_0
     354: getfield      #16                 // Field freeLists:Ljava/util/ArrayList;
     357: invokevirtual #192                // Method java/util/ArrayList.clear:()V
     360: aload_0
     361: getfield      #8                  // Field metaObjects:Ljava/util/HashMap;
     364: invokevirtual #123                // Method java/util/HashMap.clear:()V
     367: aload_0
     368: getfield      #8                  // Field metaObjects:Ljava/util/HashMap;
     371: iconst_m1
     372: invokestatic  #34                 // Method java/lang/Integer.valueOf:(I)Ljava/lang/Integer;
     375: aload_0
     376: getfield      #124                // Field metaIndex:Lorg/h2/index/PageDataIndex;
     379: invokevirtual #35                 // Method java/util/HashMap.put:(Ljava/lang/Object;Ljava/lang/Object;)Ljava/lang/Object;
     382: pop
     383: iload_2
     384: ifeq          395
     387: aload_0
     388: getfield      #21                 // Field database:Lorg/h2/engine/Database;
     391: iconst_1
     392: invokevirtual #261                // Method org/h2/engine/Database.setReadOnly:(Z)V
     395: aload_0
     396: getfield      #23                 // Field trace:Lorg/h2/message/Trace;
     399: ldc_w         #336                // String log recover done
     402: invokevirtual #132                // Method org/h2/message/Trace.debug:(Ljava/lang/String;)V
     405: iload_1
     406: ireturn

  public synchronized void logAddOrRemoveRow(org.h2.engine.Session, int, org.h2.result.Row, boolean);
    Code:
       0: aload_0
       1: getfield      #18                 // Field logMode:I
       4: ifeq          26
       7: aload_0
       8: getfield      #66                 // Field recoveryRunning:Z
      11: ifne          26
      14: aload_0
      15: getfield      #71                 // Field log:Lorg/h2/store/PageLog;
      18: aload_1
      19: iload_2
      20: aload_3
      21: iload         4
      23: invokevirtual #337                // Method org/h2/store/PageLog.logAddOrRemoveRow:(Lorg/h2/engine/Session;ILorg/h2/result/Row;Z)V
      26: return

  public synchronized void commit(org.h2.engine.Session);
    Code:
       0: aload_0
       1: invokespecial #289                // Method checkOpen:()V
       4: aload_0
       5: invokespecial #107                // Method openForWriting:()V
       8: aload_0
       9: getfield      #71                 // Field log:Lorg/h2/store/PageLog;
      12: aload_1
      13: invokevirtual #338                // Method org/h2/engine/Session.getId:()I
      16: invokevirtual #339                // Method org/h2/store/PageLog.commit:(I)V
      19: aload_0
      20: getfield      #71                 // Field log:Lorg/h2/store/PageLog;
      23: invokevirtual #340                // Method org/h2/store/PageLog.getSize:()J
      26: lstore_2
      27: lload_2
      28: aload_0
      29: getfield      #341                // Field logSizeBase:J
      32: lsub
      33: aload_0
      34: getfield      #11                 // Field maxLogSize:J
      37: ldc2_w        #342                // long 2l
      40: ldiv
      41: lcmp
      42: ifle          174
      45: aload_0
      46: getfield      #71                 // Field log:Lorg/h2/store/PageLog;
      49: invokevirtual #344                // Method org/h2/store/PageLog.getLogFirstSectionId:()I
      52: istore        4
      54: aload_0
      55: invokevirtual #111                // Method checkpoint:()V
      58: aload_0
      59: getfield      #71                 // Field log:Lorg/h2/store/PageLog;
      62: invokevirtual #255                // Method org/h2/store/PageLog.getLogSectionId:()I
      65: istore        5
      67: iload         5
      69: iload         4
      71: isub
      72: iconst_2
      73: if_icmpgt     77
      76: return
      77: aload_0
      78: getfield      #71                 // Field log:Lorg/h2/store/PageLog;
      81: invokevirtual #340                // Method org/h2/store/PageLog.getSize:()J
      84: lstore        6
      86: lload         6
      88: lload_2
      89: lcmp
      90: iflt          102
      93: lload_2
      94: aload_0
      95: getfield      #11                 // Field maxLogSize:J
      98: lcmp
      99: ifge          108
     102: aload_0
     103: iconst_0
     104: putfield      #345                // Field ignoreBigLog:Z
     107: return
     108: aload_0
     109: getfield      #345                // Field ignoreBigLog:Z
     112: ifne          163
     115: aload_0
     116: iconst_1
     117: putfield      #345                // Field ignoreBigLog:Z
     120: aload_0
     121: getfield      #23                 // Field trace:Lorg/h2/message/Trace;
     124: aconst_null
     125: new           #50                 // class java/lang/StringBuilder
     128: dup
     129: invokespecial #51                 // Method java/lang/StringBuilder."<init>":()V
     132: ldc_w         #346                // String Transaction log could not be truncated; size:
     135: invokevirtual #52                 // Method java/lang/StringBuilder.append:(Ljava/lang/String;)Ljava/lang/StringBuilder;
     138: lload         6
     140: ldc2_w        #347                // long 1024l
     143: ldiv
     144: ldc2_w        #347                // long 1024l
     147: ldiv
     148: invokevirtual #54                 // Method java/lang/StringBuilder.append:(J)Ljava/lang/StringBuilder;
     151: ldc_w         #349                // String  MB
     154: invokevirtual #52                 // Method java/lang/StringBuilder.append:(Ljava/lang/String;)Ljava/lang/StringBuilder;
     157: invokevirtual #55                 // Method java/lang/StringBuilder.toString:()Ljava/lang/String;
     160: invokevirtual #350                // Method org/h2/message/Trace.error:(Ljava/lang/Throwable;Ljava/lang/String;)V
     163: aload_0
     164: aload_0
     165: getfield      #71                 // Field log:Lorg/h2/store/PageLog;
     168: invokevirtual #340                // Method org/h2/store/PageLog.getSize:()J
     171: putfield      #341                // Field logSizeBase:J
     174: return

  public synchronized void prepareCommit(org.h2.engine.Session, java.lang.String);
    Code:
       0: aload_0
       1: getfield      #71                 // Field log:Lorg/h2/store/PageLog;
       4: aload_1
       5: aload_2
       6: invokevirtual #351                // Method org/h2/store/PageLog.prepareCommit:(Lorg/h2/engine/Session;Ljava/lang/String;)V
       9: return

  public boolean isNew();
    Code:
       0: aload_0
       1: getfield      #77                 // Field isNew:Z
       4: ireturn

  void allocateIfIndexRoot(int, int, org.h2.result.Row);
    Code:
       0: iload_2
       1: iconst_m1
       2: if_icmpne     52
       5: aload_3
       6: iconst_3
       7: invokeinterface #352,  2          // InterfaceMethod org/h2/result/Row.getValue:(I)Lorg/h2/value/Value;
      12: invokevirtual #353                // Method org/h2/value/Value.getInt:()I
      15: istore        4
      17: aload_0
      18: getfield      #317                // Field reservedPages:Ljava/util/HashMap;
      21: ifnonnull     35
      24: aload_0
      25: new           #6                  // class java/util/HashMap
      28: dup
      29: invokespecial #7                  // Method java/util/HashMap."<init>":()V
      32: putfield      #317                // Field reservedPages:Ljava/util/HashMap;
      35: aload_0
      36: getfield      #317                // Field reservedPages:Ljava/util/HashMap;
      39: iload         4
      41: invokestatic  #34                 // Method java/lang/Integer.valueOf:(I)Ljava/lang/Integer;
      44: iload_1
      45: invokestatic  #34                 // Method java/lang/Integer.valueOf:(I)Ljava/lang/Integer;
      48: invokevirtual #35                 // Method java/util/HashMap.put:(Ljava/lang/Object;Ljava/lang/Object;)Ljava/lang/Object;
      51: pop
      52: return

  void redoDelete(int, long);
    Code:
       0: aload_0
       1: getfield      #8                  // Field metaObjects:Ljava/util/HashMap;
       4: iload_1
       5: invokestatic  #34                 // Method java/lang/Integer.valueOf:(I)Ljava/lang/Integer;
       8: invokevirtual #31                 // Method java/util/HashMap.get:(Ljava/lang/Object;)Ljava/lang/Object;
      11: checkcast     #179                // class org/h2/index/Index
      14: astore        4
      16: aload         4
      18: checkcast     #230                // class org/h2/index/PageDataIndex
      21: astore        5
      23: aload         5
      25: lload_2
      26: invokevirtual #354                // Method org/h2/index/PageDataIndex.getRowWithKey:(J)Lorg/h2/result/Row;
      29: astore        6
      31: aload         6
      33: ifnull        48
      36: aload         6
      38: invokeinterface #355,  1          // InterfaceMethod org/h2/result/Row.getKey:()J
      43: lload_2
      44: lcmp
      45: ifeq          94
      48: aload_0
      49: getfield      #23                 // Field trace:Lorg/h2/message/Trace;
      52: aconst_null
      53: new           #50                 // class java/lang/StringBuilder
      56: dup
      57: invokespecial #51                 // Method java/lang/StringBuilder."<init>":()V
      60: ldc_w         #356                // String Entry not found:
      63: invokevirtual #52                 // Method java/lang/StringBuilder.append:(Ljava/lang/String;)Ljava/lang/StringBuilder;
      66: lload_2
      67: invokevirtual #54                 // Method java/lang/StringBuilder.append:(J)Ljava/lang/StringBuilder;
      70: ldc_w         #357                // String  found instead:
      73: invokevirtual #52                 // Method java/lang/StringBuilder.append:(Ljava/lang/String;)Ljava/lang/StringBuilder;
      76: aload         6
      78: invokevirtual #205                // Method java/lang/StringBuilder.append:(Ljava/lang/Object;)Ljava/lang/StringBuilder;
      81: ldc_w         #358                // String  - ignoring
      84: invokevirtual #52                 // Method java/lang/StringBuilder.append:(Ljava/lang/String;)Ljava/lang/StringBuilder;
      87: invokevirtual #55                 // Method java/lang/StringBuilder.toString:()Ljava/lang/String;
      90: invokevirtual #350                // Method org/h2/message/Trace.error:(Ljava/lang/Throwable;Ljava/lang/String;)V
      93: return
      94: aload_0
      95: iload_1
      96: aload         6
      98: iconst_0
      99: invokevirtual #359                // Method redo:(ILorg/h2/result/Row;Z)V
     102: return

  void redo(int, org.h2.result.Row, boolean);
    Code:
       0: iload_1
       1: iconst_m1
       2: if_icmpne     27
       5: iload_3
       6: ifeq          22
       9: aload_0
      10: aload_2
      11: aload_0
      12: getfield      #29                 // Field pageStoreSession:Lorg/h2/engine/Session;
      15: iconst_1
      16: invokespecial #360                // Method addMeta:(Lorg/h2/result/Row;Lorg/h2/engine/Session;Z)V
      19: goto          27
      22: aload_0
      23: aload_2
      24: invokespecial #361                // Method removeMeta:(Lorg/h2/result/Row;)V
      27: aload_0
      28: getfield      #8                  // Field metaObjects:Ljava/util/HashMap;
      31: iload_1
      32: invokestatic  #34                 // Method java/lang/Integer.valueOf:(I)Ljava/lang/Integer;
      35: invokevirtual #31                 // Method java/util/HashMap.get:(Ljava/lang/Object;)Ljava/lang/Object;
      38: checkcast     #179                // class org/h2/index/Index
      41: astore        4
      43: aload         4
      45: ifnonnull     90
      48: new           #50                 // class java/lang/StringBuilder
      51: dup
      52: invokespecial #51                 // Method java/lang/StringBuilder."<init>":()V
      55: ldc_w         #362                // String Table not found:
      58: invokevirtual #52                 // Method java/lang/StringBuilder.append:(Ljava/lang/String;)Ljava/lang/StringBuilder;
      61: iload_1
      62: invokevirtual #93                 // Method java/lang/StringBuilder.append:(I)Ljava/lang/StringBuilder;
      65: ldc           #198                // String
      67: invokevirtual #52                 // Method java/lang/StringBuilder.append:(Ljava/lang/String;)Ljava/lang/StringBuilder;
      70: aload_2
      71: invokevirtual #205                // Method java/lang/StringBuilder.append:(Ljava/lang/Object;)Ljava/lang/StringBuilder;
      74: ldc           #198                // String
      76: invokevirtual #52                 // Method java/lang/StringBuilder.append:(Ljava/lang/String;)Ljava/lang/StringBuilder;
      79: iload_3
      80: invokevirtual #197                // Method java/lang/StringBuilder.append:(Z)Ljava/lang/StringBuilder;
      83: invokevirtual #55                 // Method java/lang/StringBuilder.toString:()Ljava/lang/String;
      86: invokestatic  #186                // Method org/h2/message/DbException.throwInternalError:(Ljava/lang/String;)Ljava/lang/RuntimeException;
      89: athrow
      90: aload         4
      92: invokeinterface #363,  1          // InterfaceMethod org/h2/index/Index.getTable:()Lorg/h2/table/Table;
      97: astore        5
      99: iload_3
     100: ifeq          116
     103: aload         5
     105: aload_0
     106: getfield      #29                 // Field pageStoreSession:Lorg/h2/engine/Session;
     109: aload_2
     110: invokevirtual #364                // Method org/h2/table/Table.addRow:(Lorg/h2/engine/Session;Lorg/h2/result/Row;)V
     113: goto          126
     116: aload         5
     118: aload_0
     119: getfield      #29                 // Field pageStoreSession:Lorg/h2/engine/Session;
     122: aload_2
     123: invokevirtual #365                // Method org/h2/table/Table.removeRow:(Lorg/h2/engine/Session;Lorg/h2/result/Row;)V
     126: return

  void redoTruncate(int);
    Code:
       0: aload_0
       1: getfield      #8                  // Field metaObjects:Ljava/util/HashMap;
       4: iload_1
       5: invokestatic  #34                 // Method java/lang/Integer.valueOf:(I)Ljava/lang/Integer;
       8: invokevirtual #31                 // Method java/util/HashMap.get:(Ljava/lang/Object;)Ljava/lang/Object;
      11: checkcast     #179                // class org/h2/index/Index
      14: astore_2
      15: aload_2
      16: invokeinterface #363,  1          // InterfaceMethod org/h2/index/Index.getTable:()Lorg/h2/table/Table;
      21: astore_3
      22: aload_3
      23: aload_0
      24: getfield      #29                 // Field pageStoreSession:Lorg/h2/engine/Session;
      27: invokevirtual #366                // Method org/h2/table/Table.truncate:(Lorg/h2/engine/Session;)V
      30: return

  private void openMetaIndex();
    Code:
       0: new           #367                // class org/h2/command/ddl/CreateTableData
       3: dup
       4: invokespecial #368                // Method org/h2/command/ddl/CreateTableData."<init>":()V
       7: astore_1
       8: aload_1
       9: getfield      #369                // Field org/h2/command/ddl/CreateTableData.columns:Ljava/util/ArrayList;
      12: astore_2
      13: aload_2
      14: new           #370                // class org/h2/table/Column
      17: dup
      18: ldc_w         #371                // String ID
      21: iconst_4
      22: invokespecial #372                // Method org/h2/table/Column."<init>":(Ljava/lang/String;I)V
      25: invokevirtual #300                // Method java/util/ArrayList.add:(Ljava/lang/Object;)Z
      28: pop
      29: aload_2
      30: new           #370                // class org/h2/table/Column
      33: dup
      34: ldc_w         #373                // String TYPE
      37: iconst_4
      38: invokespecial #372                // Method org/h2/table/Column."<init>":(Ljava/lang/String;I)V
      41: invokevirtual #300                // Method java/util/ArrayList.add:(Ljava/lang/Object;)Z
      44: pop
      45: aload_2
      46: new           #370                // class org/h2/table/Column
      49: dup
      50: ldc_w         #374                // String PARENT
      53: iconst_4
      54: invokespecial #372                // Method org/h2/table/Column."<init>":(Ljava/lang/String;I)V
      57: invokevirtual #300                // Method java/util/ArrayList.add:(Ljava/lang/Object;)Z
      60: pop
      61: aload_2
      62: new           #370                // class org/h2/table/Column
      65: dup
      66: ldc_w         #375                // String HEAD
      69: iconst_4
      70: invokespecial #372                // Method org/h2/table/Column."<init>":(Ljava/lang/String;I)V
      73: invokevirtual #300                // Method java/util/ArrayList.add:(Ljava/lang/Object;)Z
      76: pop
      77: aload_2
      78: new           #370                // class org/h2/table/Column
      81: dup
      82: ldc_w         #376                // String OPTIONS
      85: bipush        13
      87: invokespecial #372                // Method org/h2/table/Column."<init>":(Ljava/lang/String;I)V
      90: invokevirtual #300                // Method java/util/ArrayList.add:(Ljava/lang/Object;)Z
      93: pop
      94: aload_2
      95: new           #370                // class org/h2/table/Column
      98: dup
      99: ldc_w         #377                // String COLUMNS
     102: bipush        13
     104: invokespecial #372                // Method org/h2/table/Column."<init>":(Ljava/lang/String;I)V
     107: invokevirtual #300                // Method java/util/ArrayList.add:(Ljava/lang/Object;)Z
     110: pop
     111: aload_0
     112: new           #378                // class org/h2/schema/Schema
     115: dup
     116: aload_0
     117: getfield      #21                 // Field database:Lorg/h2/engine/Database;
     120: iconst_0
     121: ldc_w         #379                // String
     124: aconst_null
     125: iconst_1
     126: invokespecial #380                // Method org/h2/schema/Schema."<init>":(Lorg/h2/engine/Database;ILjava/lang/String;Lorg/h2/engine/User;Z)V
     129: putfield      #381                // Field metaSchema:Lorg/h2/schema/Schema;
     132: aload_1
     133: aload_0
     134: getfield      #381                // Field metaSchema:Lorg/h2/schema/Schema;
     137: putfield      #382                // Field org/h2/command/ddl/CreateTableData.schema:Lorg/h2/schema/Schema;
     140: aload_1
     141: ldc_w         #383                // String PAGE_INDEX
     144: putfield      #384                // Field org/h2/command/ddl/CreateTableData.tableName:Ljava/lang/String;
     147: aload_1
     148: iconst_m1
     149: putfield      #385                // Field org/h2/command/ddl/CreateTableData.id:I
     152: aload_1
     153: iconst_0
     154: putfield      #386                // Field org/h2/command/ddl/CreateTableData.temporary:Z
     157: aload_1
     158: iconst_1
     159: putfield      #387                // Field org/h2/command/ddl/CreateTableData.persistData:Z
     162: aload_1
     163: iconst_1
     164: putfield      #388                // Field org/h2/command/ddl/CreateTableData.persistIndexes:Z
     167: aload_1
     168: iconst_0
     169: putfield      #389                // Field org/h2/command/ddl/CreateTableData.create:Z
     172: aload_1
     173: aload_0
     174: getfield      #29                 // Field pageStoreSession:Lorg/h2/engine/Session;
     177: putfield      #390                // Field org/h2/command/ddl/CreateTableData.session:Lorg/h2/engine/Session;
     180: aload_0
     181: new           #391                // class org/h2/table/RegularTable
     184: dup
     185: aload_1
     186: invokespecial #392                // Method org/h2/table/RegularTable."<init>":(Lorg/h2/command/ddl/CreateTableData;)V
     189: putfield      #393                // Field metaTable:Lorg/h2/table/RegularTable;
     192: aload_0
     193: aload_0
     194: getfield      #393                // Field metaTable:Lorg/h2/table/RegularTable;
     197: aload_0
     198: getfield      #29                 // Field pageStoreSession:Lorg/h2/engine/Session;
     201: invokevirtual #394                // Method org/h2/table/RegularTable.getScanIndex:(Lorg/h2/engine/Session;)Lorg/h2/index/Index;
     204: checkcast     #230                // class org/h2/index/PageDataIndex
     207: putfield      #124                // Field metaIndex:Lorg/h2/index/PageDataIndex;
     210: aload_0
     211: getfield      #8                  // Field metaObjects:Ljava/util/HashMap;
     214: invokevirtual #123                // Method java/util/HashMap.clear:()V
     217: aload_0
     218: getfield      #8                  // Field metaObjects:Ljava/util/HashMap;
     221: iconst_m1
     222: invokestatic  #34                 // Method java/lang/Integer.valueOf:(I)Ljava/lang/Integer;
     225: aload_0
     226: getfield      #124                // Field metaIndex:Lorg/h2/index/PageDataIndex;
     229: invokevirtual #35                 // Method java/util/HashMap.put:(Ljava/lang/Object;Ljava/lang/Object;)Ljava/lang/Object;
     232: pop
     233: return

  private void readMetaData();
    Code:
       0: aload_0
       1: getfield      #124                // Field metaIndex:Lorg/h2/index/PageDataIndex;
       4: aload_0
       5: getfield      #29                 // Field pageStoreSession:Lorg/h2/engine/Session;
       8: aconst_null
       9: aconst_null
      10: invokevirtual #395                // Method org/h2/index/PageDataIndex.find:(Lorg/h2/engine/Session;Lorg/h2/result/SearchRow;Lorg/h2/result/SearchRow;)Lorg/h2/index/Cursor;
      13: astore_1
      14: aload_1
      15: invokeinterface #176,  1          // InterfaceMethod org/h2/index/Cursor.next:()Z
      20: ifeq          58
      23: aload_1
      24: invokeinterface #177,  1          // InterfaceMethod org/h2/index/Cursor.get:()Lorg/h2/result/Row;
      29: astore_2
      30: aload_2
      31: iconst_1
      32: invokeinterface #352,  2          // InterfaceMethod org/h2/result/Row.getValue:(I)Lorg/h2/value/Value;
      37: invokevirtual #353                // Method org/h2/value/Value.getInt:()I
      40: istore_3
      41: iload_3
      42: ifne          55
      45: aload_0
      46: aload_2
      47: aload_0
      48: getfield      #29                 // Field pageStoreSession:Lorg/h2/engine/Session;
      51: iconst_0
      52: invokespecial #360                // Method addMeta:(Lorg/h2/result/Row;Lorg/h2/engine/Session;Z)V
      55: goto          14
      58: aload_0
      59: getfield      #124                // Field metaIndex:Lorg/h2/index/PageDataIndex;
      62: aload_0
      63: getfield      #29                 // Field pageStoreSession:Lorg/h2/engine/Session;
      66: aconst_null
      67: aconst_null
      68: invokevirtual #395                // Method org/h2/index/PageDataIndex.find:(Lorg/h2/engine/Session;Lorg/h2/result/SearchRow;Lorg/h2/result/SearchRow;)Lorg/h2/index/Cursor;
      71: astore_1
      72: aload_1
      73: invokeinterface #176,  1          // InterfaceMethod org/h2/index/Cursor.next:()Z
      78: ifeq          116
      81: aload_1
      82: invokeinterface #177,  1          // InterfaceMethod org/h2/index/Cursor.get:()Lorg/h2/result/Row;
      87: astore_2
      88: aload_2
      89: iconst_1
      90: invokeinterface #352,  2          // InterfaceMethod org/h2/result/Row.getValue:(I)Lorg/h2/value/Value;
      95: invokevirtual #353                // Method org/h2/value/Value.getInt:()I
      98: istore_3
      99: iload_3
     100: ifeq          113
     103: aload_0
     104: aload_2
     105: aload_0
     106: getfield      #29                 // Field pageStoreSession:Lorg/h2/engine/Session;
     109: iconst_0
     110: invokespecial #360                // Method addMeta:(Lorg/h2/result/Row;Lorg/h2/engine/Session;Z)V
     113: goto          72
     116: return

  private void removeMeta(org.h2.result.Row);
    Code:
       0: aload_1
       1: iconst_0
       2: invokeinterface #352,  2          // InterfaceMethod org/h2/result/Row.getValue:(I)Lorg/h2/value/Value;
       7: invokevirtual #353                // Method org/h2/value/Value.getInt:()I
      10: istore_2
      11: aload_0
      12: getfield      #8                  // Field metaObjects:Ljava/util/HashMap;
      15: iload_2
      16: invokestatic  #34                 // Method java/lang/Integer.valueOf:(I)Ljava/lang/Integer;
      19: invokevirtual #31                 // Method java/util/HashMap.get:(Ljava/lang/Object;)Ljava/lang/Object;
      22: checkcast     #117                // class org/h2/index/PageIndex
      25: astore_3
      26: aload_3
      27: invokevirtual #118                // Method org/h2/index/PageIndex.getTable:()Lorg/h2/table/Table;
      30: aload_3
      31: invokevirtual #396                // Method org/h2/table/Table.removeIndex:(Lorg/h2/index/Index;)V
      34: aload_3
      35: instanceof    #242                // class org/h2/index/PageBtreeIndex
      38: ifne          48
      41: aload_3
      42: instanceof    #397                // class org/h2/index/PageDelegateIndex
      45: ifeq          74
      48: aload_3
      49: invokevirtual #398                // Method org/h2/index/PageIndex.isTemporary:()Z
      52: ifeq          66
      55: aload_0
      56: getfield      #29                 // Field pageStoreSession:Lorg/h2/engine/Session;
      59: aload_3
      60: invokevirtual #399                // Method org/h2/engine/Session.removeLocalTempTableIndex:(Lorg/h2/index/Index;)V
      63: goto          74
      66: aload_3
      67: invokevirtual #400                // Method org/h2/index/PageIndex.getSchema:()Lorg/h2/schema/Schema;
      70: aload_3
      71: invokevirtual #401                // Method org/h2/schema/Schema.remove:(Lorg/h2/schema/SchemaObject;)V
      74: aload_3
      75: aload_0
      76: getfield      #29                 // Field pageStoreSession:Lorg/h2/engine/Session;
      79: invokevirtual #121                // Method org/h2/index/PageIndex.remove:(Lorg/h2/engine/Session;)V
      82: aload_0
      83: getfield      #8                  // Field metaObjects:Ljava/util/HashMap;
      86: iload_2
      87: invokestatic  #34                 // Method java/lang/Integer.valueOf:(I)Ljava/lang/Integer;
      90: invokevirtual #402                // Method java/util/HashMap.remove:(Ljava/lang/Object;)Ljava/lang/Object;
      93: pop
      94: return

  private void addMeta(org.h2.result.Row, org.h2.engine.Session, boolean);
    Code:
       0: aload_1
       1: iconst_0
       2: invokeinterface #352,  2          // InterfaceMethod org/h2/result/Row.getValue:(I)Lorg/h2/value/Value;
       7: invokevirtual #353                // Method org/h2/value/Value.getInt:()I
      10: istore        4
      12: aload_1
      13: iconst_1
      14: invokeinterface #352,  2          // InterfaceMethod org/h2/result/Row.getValue:(I)Lorg/h2/value/Value;
      19: invokevirtual #353                // Method org/h2/value/Value.getInt:()I
      22: istore        5
      24: aload_1
      25: iconst_2
      26: invokeinterface #352,  2          // InterfaceMethod org/h2/result/Row.getValue:(I)Lorg/h2/value/Value;
      31: invokevirtual #353                // Method org/h2/value/Value.getInt:()I
      34: istore        6
      36: aload_1
      37: iconst_3
      38: invokeinterface #352,  2          // InterfaceMethod org/h2/result/Row.getValue:(I)Lorg/h2/value/Value;
      43: invokevirtual #353                // Method org/h2/value/Value.getInt:()I
      46: istore        7
      48: aload_1
      49: iconst_4
      50: invokeinterface #352,  2          // InterfaceMethod org/h2/result/Row.getValue:(I)Lorg/h2/value/Value;
      55: invokevirtual #403                // Method org/h2/value/Value.getString:()Ljava/lang/String;
      58: bipush        44
      60: iconst_0
      61: invokestatic  #404                // Method org/h2/util/StringUtils.arraySplit:(Ljava/lang/String;CZ)[Ljava/lang/String;
      64: astore        8
      66: aload_1
      67: iconst_5
      68: invokeinterface #352,  2          // InterfaceMethod org/h2/result/Row.getValue:(I)Lorg/h2/value/Value;
      73: invokevirtual #403                // Method org/h2/value/Value.getString:()Ljava/lang/String;
      76: astore        9
      78: aload         9
      80: bipush        44
      82: iconst_0
      83: invokestatic  #404                // Method org/h2/util/StringUtils.arraySplit:(Ljava/lang/String;CZ)[Ljava/lang/String;
      86: astore        10
      88: aload_0
      89: getfield      #23                 // Field trace:Lorg/h2/message/Trace;
      92: invokevirtual #140                // Method org/h2/message/Trace.isDebugEnabled:()Z
      95: ifeq          169
      98: aload_0
      99: getfield      #23                 // Field trace:Lorg/h2/message/Trace;
     102: new           #50                 // class java/lang/StringBuilder
     105: dup
     106: invokespecial #51                 // Method java/lang/StringBuilder."<init>":()V
     109: ldc_w         #405                // String addMeta id=
     112: invokevirtual #52                 // Method java/lang/StringBuilder.append:(Ljava/lang/String;)Ljava/lang/StringBuilder;
     115: iload         4
     117: invokevirtual #93                 // Method java/lang/StringBuilder.append:(I)Ljava/lang/StringBuilder;
     120: ldc           #251                // String  type=
     122: invokevirtual #52                 // Method java/lang/StringBuilder.append:(Ljava/lang/String;)Ljava/lang/StringBuilder;
     125: iload         5
     127: invokevirtual #93                 // Method java/lang/StringBuilder.append:(I)Ljava/lang/StringBuilder;
     130: ldc_w         #406                // String  root=
     133: invokevirtual #52                 // Method java/lang/StringBuilder.append:(Ljava/lang/String;)Ljava/lang/StringBuilder;
     136: iload         7
     138: invokevirtual #93                 // Method java/lang/StringBuilder.append:(I)Ljava/lang/StringBuilder;
     141: ldc_w         #407                // String  parent=
     144: invokevirtual #52                 // Method java/lang/StringBuilder.append:(Ljava/lang/String;)Ljava/lang/StringBuilder;
     147: iload         6
     149: invokevirtual #93                 // Method java/lang/StringBuilder.append:(I)Ljava/lang/StringBuilder;
     152: ldc_w         #408                // String  columns=
     155: invokevirtual #52                 // Method java/lang/StringBuilder.append:(Ljava/lang/String;)Ljava/lang/StringBuilder;
     158: aload         9
     160: invokevirtual #52                 // Method java/lang/StringBuilder.append:(Ljava/lang/String;)Ljava/lang/StringBuilder;
     163: invokevirtual #55                 // Method java/lang/StringBuilder.toString:()Ljava/lang/String;
     166: invokevirtual #132                // Method org/h2/message/Trace.debug:(Ljava/lang/String;)V
     169: iload_3
     170: ifeq          194
     173: iload         7
     175: ifeq          194
     178: aload_0
     179: iload         7
     181: aload_0
     182: invokevirtual #219                // Method createData:()Lorg/h2/store/Data;
     185: invokevirtual #316                // Method writePage:(ILorg/h2/store/Data;)V
     188: aload_0
     189: iload         7
     191: invokevirtual #155                // Method allocatePage:(I)V
     194: aload_0
     195: getfield      #5                  // Field metaRootPageId:Lorg/h2/util/IntIntHashMap;
     198: iload         4
     200: iload         7
     202: invokevirtual #43                 // Method org/h2/util/IntIntHashMap.put:(II)V
     205: iload         5
     207: ifne          450
     210: new           #367                // class org/h2/command/ddl/CreateTableData
     213: dup
     214: invokespecial #368                // Method org/h2/command/ddl/CreateTableData."<init>":()V
     217: astore        12
     219: getstatic     #217                // Field org/h2/engine/SysProperties.CHECK:Z
     222: ifeq          238
     225: aload         10
     227: ifnonnull     238
     230: aload_1
     231: invokevirtual #296                // Method java/lang/Object.toString:()Ljava/lang/String;
     234: invokestatic  #186                // Method org/h2/message/DbException.throwInternalError:(Ljava/lang/String;)Ljava/lang/RuntimeException;
     237: athrow
     238: iconst_0
     239: istore        13
     241: aload         10
     243: arraylength
     244: istore        14
     246: iload         13
     248: iload         14
     250: if_icmpge     301
     253: new           #370                // class org/h2/table/Column
     256: dup
     257: new           #50                 // class java/lang/StringBuilder
     260: dup
     261: invokespecial #51                 // Method java/lang/StringBuilder."<init>":()V
     264: ldc_w         #409                // String C
     267: invokevirtual #52                 // Method java/lang/StringBuilder.append:(Ljava/lang/String;)Ljava/lang/StringBuilder;
     270: iload         13
     272: invokevirtual #93                 // Method java/lang/StringBuilder.append:(I)Ljava/lang/StringBuilder;
     275: invokevirtual #55                 // Method java/lang/StringBuilder.toString:()Ljava/lang/String;
     278: iconst_4
     279: invokespecial #372                // Method org/h2/table/Column."<init>":(Ljava/lang/String;I)V
     282: astore        15
     284: aload         12
     286: getfield      #369                // Field org/h2/command/ddl/CreateTableData.columns:Ljava/util/ArrayList;
     289: aload         15
     291: invokevirtual #300                // Method java/util/ArrayList.add:(Ljava/lang/Object;)Z
     294: pop
     295: iinc          13, 1
     298: goto          246
     301: aload         12
     303: aload_0
     304: getfield      #381                // Field metaSchema:Lorg/h2/schema/Schema;
     307: putfield      #382                // Field org/h2/command/ddl/CreateTableData.schema:Lorg/h2/schema/Schema;
     310: aload         12
     312: new           #50                 // class java/lang/StringBuilder
     315: dup
     316: invokespecial #51                 // Method java/lang/StringBuilder."<init>":()V
     319: ldc_w         #410                // String T
     322: invokevirtual #52                 // Method java/lang/StringBuilder.append:(Ljava/lang/String;)Ljava/lang/StringBuilder;
     325: iload         4
     327: invokevirtual #93                 // Method java/lang/StringBuilder.append:(I)Ljava/lang/StringBuilder;
     330: invokevirtual #55                 // Method java/lang/StringBuilder.toString:()Ljava/lang/String;
     333: putfield      #384                // Field org/h2/command/ddl/CreateTableData.tableName:Ljava/lang/String;
     336: aload         12
     338: iload         4
     340: putfield      #385                // Field org/h2/command/ddl/CreateTableData.id:I
     343: aload         12
     345: aload         8
     347: iconst_2
     348: aaload
     349: ldc_w         #411                // String temp
     352: invokevirtual #412                // Method java/lang/String.equals:(Ljava/lang/Object;)Z
     355: putfield      #386                // Field org/h2/command/ddl/CreateTableData.temporary:Z
     358: aload         12
     360: iconst_1
     361: putfield      #387                // Field org/h2/command/ddl/CreateTableData.persistData:Z
     364: aload         12
     366: iconst_1
     367: putfield      #388                // Field org/h2/command/ddl/CreateTableData.persistIndexes:Z
     370: aload         12
     372: iconst_0
     373: putfield      #389                // Field org/h2/command/ddl/CreateTableData.create:Z
     376: aload         12
     378: aload_2
     379: putfield      #390                // Field org/h2/command/ddl/CreateTableData.session:Lorg/h2/engine/Session;
     382: new           #391                // class org/h2/table/RegularTable
     385: dup
     386: aload         12
     388: invokespecial #392                // Method org/h2/table/RegularTable."<init>":(Lorg/h2/command/ddl/CreateTableData;)V
     391: astore        13
     393: getstatic     #413                // Field org/h2/engine/SysProperties.SORT_BINARY_UNSIGNED:Z
     396: istore        14
     398: aload         8
     400: arraylength
     401: iconst_3
     402: if_icmple     414
     405: aload         8
     407: iconst_3
     408: aaload
     409: invokestatic  #414                // Method java/lang/Boolean.parseBoolean:(Ljava/lang/String;)Z
     412: istore        14
     414: aload         8
     416: iconst_0
     417: aaload
     418: aload         8
     420: iconst_1
     421: aaload
     422: invokestatic  #415                // Method java/lang/Integer.parseInt:(Ljava/lang/String;)I
     425: iload         14
     427: invokestatic  #416                // Method org/h2/value/CompareMode.getInstance:(Ljava/lang/String;IZ)Lorg/h2/value/CompareMode;
     430: astore        15
     432: aload         13
     434: aload         15
     436: invokevirtual #417                // Method org/h2/table/RegularTable.setCompareMode:(Lorg/h2/value/CompareMode;)V
     439: aload         13
     441: aload_2
     442: invokevirtual #394                // Method org/h2/table/RegularTable.getScanIndex:(Lorg/h2/engine/Session;)Lorg/h2/index/Index;
     445: astore        11
     447: goto          770
     450: aload_0
     451: getfield      #8                  // Field metaObjects:Ljava/util/HashMap;
     454: iload         6
     456: invokestatic  #34                 // Method java/lang/Integer.valueOf:(I)Ljava/lang/Integer;
     459: invokevirtual #31                 // Method java/util/HashMap.get:(Ljava/lang/Object;)Ljava/lang/Object;
     462: checkcast     #179                // class org/h2/index/Index
     465: astore        12
     467: aload         12
     469: ifnonnull     522
     472: ldc           #49                 // int 90030
     474: new           #50                 // class java/lang/StringBuilder
     477: dup
     478: invokespecial #51                 // Method java/lang/StringBuilder."<init>":()V
     481: ldc_w         #418                // String Table not found:
     484: invokevirtual #52                 // Method java/lang/StringBuilder.append:(Ljava/lang/String;)Ljava/lang/StringBuilder;
     487: iload         6
     489: invokevirtual #93                 // Method java/lang/StringBuilder.append:(I)Ljava/lang/StringBuilder;
     492: ldc_w         #419                // String  for
     495: invokevirtual #52                 // Method java/lang/StringBuilder.append:(Ljava/lang/String;)Ljava/lang/StringBuilder;
     498: aload_1
     499: invokevirtual #205                // Method java/lang/StringBuilder.append:(Ljava/lang/Object;)Ljava/lang/StringBuilder;
     502: ldc_w         #420                // String  meta:
     505: invokevirtual #52                 // Method java/lang/StringBuilder.append:(Ljava/lang/String;)Ljava/lang/StringBuilder;
     508: aload_0
     509: getfield      #8                  // Field metaObjects:Ljava/util/HashMap;
     512: invokevirtual #205                // Method java/lang/StringBuilder.append:(Ljava/lang/Object;)Ljava/lang/StringBuilder;
     515: invokevirtual #55                 // Method java/lang/StringBuilder.toString:()Ljava/lang/String;
     518: invokestatic  #56                 // Method org/h2/message/DbException.get:(ILjava/lang/String;)Lorg/h2/message/DbException;
     521: athrow
     522: aload         12
     524: invokeinterface #363,  1          // InterfaceMethod org/h2/index/Index.getTable:()Lorg/h2/table/Table;
     529: checkcast     #391                // class org/h2/table/RegularTable
     532: astore        13
     534: aload         13
     536: invokevirtual #421                // Method org/h2/table/RegularTable.getColumns:()[Lorg/h2/table/Column;
     539: astore        14
     541: aload         10
     543: arraylength
     544: istore        15
     546: iload         15
     548: anewarray     #422                // class org/h2/table/IndexColumn
     551: astore        16
     553: iconst_0
     554: istore        17
     556: iload         17
     558: iload         15
     560: if_icmpge     650
     563: aload         10
     565: iload         17
     567: aaload
     568: astore        18
     570: new           #422                // class org/h2/table/IndexColumn
     573: dup
     574: invokespecial #423                // Method org/h2/table/IndexColumn."<init>":()V
     577: astore        19
     579: aload         18
     581: bipush        47
     583: invokevirtual #424                // Method java/lang/String.indexOf:(I)I
     586: istore        20
     588: iload         20
     590: iflt          624
     593: aload         18
     595: iload         20
     597: iconst_1
     598: iadd
     599: invokevirtual #425                // Method java/lang/String.substring:(I)Ljava/lang/String;
     602: astore        21
     604: aload         19
     606: aload         21
     608: invokestatic  #415                // Method java/lang/Integer.parseInt:(Ljava/lang/String;)I
     611: putfield      #426                // Field org/h2/table/IndexColumn.sortType:I
     614: aload         18
     616: iconst_0
     617: iload         20
     619: invokevirtual #427                // Method java/lang/String.substring:(II)Ljava/lang/String;
     622: astore        18
     624: aload         19
     626: aload         14
     628: aload         18
     630: invokestatic  #415                // Method java/lang/Integer.parseInt:(Ljava/lang/String;)I
     633: aaload
     634: putfield      #428                // Field org/h2/table/IndexColumn.column:Lorg/h2/table/Column;
     637: aload         16
     639: iload         17
     641: aload         19
     643: aastore
     644: iinc          17, 1
     647: goto          556
     650: aload         8
     652: iconst_3
     653: aaload
     654: ldc_w         #429                // String d
     657: invokevirtual #412                // Method java/lang/String.equals:(Ljava/lang/Object;)Z
     660: ifeq          727
     663: iconst_1
     664: iconst_0
     665: invokestatic  #430                // Method org/h2/index/IndexType.createPrimaryKey:(ZZ)Lorg/h2/index/IndexType;
     668: astore        17
     670: aload         13
     672: invokevirtual #421                // Method org/h2/table/RegularTable.getColumns:()[Lorg/h2/table/Column;
     675: astore        18
     677: aload         16
     679: astore        19
     681: aload         19
     683: arraylength
     684: istore        20
     686: iconst_0
     687: istore        21
     689: iload         21
     691: iload         20
     693: if_icmpge     724
     696: aload         19
     698: iload         21
     700: aaload
     701: astore        22
     703: aload         18
     705: aload         22
     707: getfield      #428                // Field org/h2/table/IndexColumn.column:Lorg/h2/table/Column;
     710: invokevirtual #431                // Method org/h2/table/Column.getColumnId:()I
     713: aaload
     714: iconst_0
     715: invokevirtual #432                // Method org/h2/table/Column.setNullable:(Z)V
     718: iinc          21, 1
     721: goto          689
     724: goto          733
     727: iconst_1
     728: invokestatic  #433                // Method org/h2/index/IndexType.createNonUnique:(Z)Lorg/h2/index/IndexType;
     731: astore        17
     733: aload         13
     735: aload_2
     736: new           #50                 // class java/lang/StringBuilder
     739: dup
     740: invokespecial #51                 // Method java/lang/StringBuilder."<init>":()V
     743: ldc_w         #434                // String I
     746: invokevirtual #52                 // Method java/lang/StringBuilder.append:(Ljava/lang/String;)Ljava/lang/StringBuilder;
     749: iload         4
     751: invokevirtual #93                 // Method java/lang/StringBuilder.append:(I)Ljava/lang/StringBuilder;
     754: invokevirtual #55                 // Method java/lang/StringBuilder.toString:()Ljava/lang/String;
     757: iload         4
     759: aload         16
     761: aload         17
     763: iconst_0
     764: aconst_null
     765: invokevirtual #435                // Method org/h2/table/RegularTable.addIndex:(Lorg/h2/engine/Session;Ljava/lang/String;I[Lorg/h2/table/IndexColumn;Lorg/h2/index/IndexType;ZLjava/lang/String;)Lorg/h2/index/Index;
     768: astore        11
     770: aload         11
     772: instanceof    #436                // class org/h2/index/MultiVersionIndex
     775: ifeq          794
     778: aload         11
     780: checkcast     #436                // class org/h2/index/MultiVersionIndex
     783: invokevirtual #437                // Method org/h2/index/MultiVersionIndex.getBaseIndex:()Lorg/h2/index/Index;
     786: checkcast     #117                // class org/h2/index/PageIndex
     789: astore        12
     791: goto          801
     794: aload         11
     796: checkcast     #117                // class org/h2/index/PageIndex
     799: astore        12
     801: aload_0
     802: getfield      #8                  // Field metaObjects:Ljava/util/HashMap;
     805: iload         4
     807: invokestatic  #34                 // Method java/lang/Integer.valueOf:(I)Ljava/lang/Integer;
     810: aload         12
     812: invokevirtual #35                 // Method java/util/HashMap.put:(Ljava/lang/Object;Ljava/lang/Object;)Ljava/lang/Object;
     815: pop
     816: return

  public synchronized void addIndex(org.h2.index.PageIndex);
    Code:
       0: aload_0
       1: getfield      #8                  // Field metaObjects:Ljava/util/HashMap;
       4: aload_1
       5: invokevirtual #334                // Method org/h2/index/PageIndex.getId:()I
       8: invokestatic  #34                 // Method java/lang/Integer.valueOf:(I)Ljava/lang/Integer;
      11: aload_1
      12: invokevirtual #35                 // Method java/util/HashMap.put:(Ljava/lang/Object;Ljava/lang/Object;)Ljava/lang/Object;
      15: pop
      16: return

  public void addMeta(org.h2.index.PageIndex, org.h2.engine.Session);
    Code:
       0: aload_1
       1: invokevirtual #118                // Method org/h2/index/PageIndex.getTable:()Lorg/h2/table/Table;
       4: astore_3
       5: getstatic     #217                // Field org/h2/engine/SysProperties.CHECK:Z
       8: ifeq          67
      11: aload_3
      12: invokevirtual #119                // Method org/h2/table/Table.isTemporary:()Z
      15: ifne          67
      18: aload_0
      19: getfield      #21                 // Field database:Lorg/h2/engine/Database;
      22: dup
      23: astore        4
      25: monitorenter
      26: aload_0
      27: dup
      28: astore        5
      30: monitorenter
      31: aload_0
      32: getfield      #21                 // Field database:Lorg/h2/engine/Database;
      35: aload_2
      36: invokevirtual #438                // Method org/h2/engine/Database.verifyMetaLocked:(Lorg/h2/engine/Session;)V
      39: aload         5
      41: monitorexit
      42: goto          53
      45: astore        6
      47: aload         5
      49: monitorexit
      50: aload         6
      52: athrow
      53: aload         4
      55: monitorexit
      56: goto          67
      59: astore        7
      61: aload         4
      63: monitorexit
      64: aload         7
      66: athrow
      67: aload_0
      68: dup
      69: astore        4
      71: monitorenter
      72: aload_1
      73: instanceof    #230                // class org/h2/index/PageDataIndex
      76: ifeq          83
      79: iconst_0
      80: goto          84
      83: iconst_1
      84: istore        5
      86: aload_1
      87: invokevirtual #439                // Method org/h2/index/PageIndex.getIndexColumns:()[Lorg/h2/table/IndexColumn;
      90: astore        6
      92: new           #440                // class org/h2/util/StatementBuilder
      95: dup
      96: invokespecial #441                // Method org/h2/util/StatementBuilder."<init>":()V
      99: astore        7
     101: aload         6
     103: astore        8
     105: aload         8
     107: arraylength
     108: istore        9
     110: iconst_0
     111: istore        10
     113: iload         10
     115: iload         9
     117: if_icmpge     189
     120: aload         8
     122: iload         10
     124: aaload
     125: astore        11
     127: aload         7
     129: ldc_w         #442                // String ,
     132: invokevirtual #443                // Method org/h2/util/StatementBuilder.appendExceptFirst:(Ljava/lang/String;)V
     135: aload         11
     137: getfield      #428                // Field org/h2/table/IndexColumn.column:Lorg/h2/table/Column;
     140: invokevirtual #431                // Method org/h2/table/Column.getColumnId:()I
     143: istore        12
     145: aload         7
     147: iload         12
     149: i2l
     150: invokevirtual #444                // Method org/h2/util/StatementBuilder.append:(J)Lorg/h2/util/StatementBuilder;
     153: pop
     154: aload         11
     156: getfield      #426                // Field org/h2/table/IndexColumn.sortType:I
     159: istore        13
     161: iload         13
     163: ifeq          183
     166: aload         7
     168: bipush        47
     170: invokevirtual #445                // Method org/h2/util/StatementBuilder.append:(C)Lorg/h2/util/StatementBuilder;
     173: pop
     174: aload         7
     176: iload         13
     178: i2l
     179: invokevirtual #444                // Method org/h2/util/StatementBuilder.append:(J)Lorg/h2/util/StatementBuilder;
     182: pop
     183: iinc          10, 1
     186: goto          113
     189: aload         7
     191: invokevirtual #446                // Method org/h2/util/StatementBuilder.toString:()Ljava/lang/String;
     194: astore        8
     196: aload_3
     197: invokevirtual #447                // Method org/h2/table/Table.getCompareMode:()Lorg/h2/value/CompareMode;
     200: astore        9
     202: new           #50                 // class java/lang/StringBuilder
     205: dup
     206: invokespecial #51                 // Method java/lang/StringBuilder."<init>":()V
     209: aload         9
     211: invokevirtual #448                // Method org/h2/value/CompareMode.getName:()Ljava/lang/String;
     214: invokevirtual #52                 // Method java/lang/StringBuilder.append:(Ljava/lang/String;)Ljava/lang/StringBuilder;
     217: ldc_w         #442                // String ,
     220: invokevirtual #52                 // Method java/lang/StringBuilder.append:(Ljava/lang/String;)Ljava/lang/StringBuilder;
     223: aload         9
     225: invokevirtual #449                // Method org/h2/value/CompareMode.getStrength:()I
     228: invokevirtual #93                 // Method java/lang/StringBuilder.append:(I)Ljava/lang/StringBuilder;
     231: ldc_w         #442                // String ,
     234: invokevirtual #52                 // Method java/lang/StringBuilder.append:(Ljava/lang/String;)Ljava/lang/StringBuilder;
     237: invokevirtual #55                 // Method java/lang/StringBuilder.toString:()Ljava/lang/String;
     240: astore        10
     242: aload_3
     243: invokevirtual #119                // Method org/h2/table/Table.isTemporary:()Z
     246: ifeq          272
     249: new           #50                 // class java/lang/StringBuilder
     252: dup
     253: invokespecial #51                 // Method java/lang/StringBuilder."<init>":()V
     256: aload         10
     258: invokevirtual #52                 // Method java/lang/StringBuilder.append:(Ljava/lang/String;)Ljava/lang/StringBuilder;
     261: ldc_w         #411                // String temp
     264: invokevirtual #52                 // Method java/lang/StringBuilder.append:(Ljava/lang/String;)Ljava/lang/StringBuilder;
     267: invokevirtual #55                 // Method java/lang/StringBuilder.toString:()Ljava/lang/String;
     270: astore        10
     272: new           #50                 // class java/lang/StringBuilder
     275: dup
     276: invokespecial #51                 // Method java/lang/StringBuilder."<init>":()V
     279: aload         10
     281: invokevirtual #52                 // Method java/lang/StringBuilder.append:(Ljava/lang/String;)Ljava/lang/StringBuilder;
     284: ldc_w         #442                // String ,
     287: invokevirtual #52                 // Method java/lang/StringBuilder.append:(Ljava/lang/String;)Ljava/lang/StringBuilder;
     290: invokevirtual #55                 // Method java/lang/StringBuilder.toString:()Ljava/lang/String;
     293: astore        10
     295: aload_1
     296: instanceof    #397                // class org/h2/index/PageDelegateIndex
     299: ifeq          325
     302: new           #50                 // class java/lang/StringBuilder
     305: dup
     306: invokespecial #51                 // Method java/lang/StringBuilder."<init>":()V
     309: aload         10
     311: invokevirtual #52                 // Method java/lang/StringBuilder.append:(Ljava/lang/String;)Ljava/lang/StringBuilder;
     314: ldc_w         #429                // String d
     317: invokevirtual #52                 // Method java/lang/StringBuilder.append:(Ljava/lang/String;)Ljava/lang/StringBuilder;
     320: invokevirtual #55                 // Method java/lang/StringBuilder.toString:()Ljava/lang/String;
     323: astore        10
     325: new           #50                 // class java/lang/StringBuilder
     328: dup
     329: invokespecial #51                 // Method java/lang/StringBuilder."<init>":()V
     332: aload         10
     334: invokevirtual #52                 // Method java/lang/StringBuilder.append:(Ljava/lang/String;)Ljava/lang/StringBuilder;
     337: ldc_w         #442                // String ,
     340: invokevirtual #52                 // Method java/lang/StringBuilder.append:(Ljava/lang/String;)Ljava/lang/StringBuilder;
     343: aload         9
     345: invokevirtual #450                // Method org/h2/value/CompareMode.isBinaryUnsigned:()Z
     348: invokevirtual #197                // Method java/lang/StringBuilder.append:(Z)Ljava/lang/StringBuilder;
     351: invokevirtual #55                 // Method java/lang/StringBuilder.toString:()Ljava/lang/String;
     354: astore        10
     356: aload_0
     357: getfield      #393                // Field metaTable:Lorg/h2/table/RegularTable;
     360: invokevirtual #451                // Method org/h2/table/RegularTable.getTemplateRow:()Lorg/h2/result/Row;
     363: astore        11
     365: aload         11
     367: iconst_0
     368: aload_1
     369: invokevirtual #334                // Method org/h2/index/PageIndex.getId:()I
     372: invokestatic  #452                // Method org/h2/value/ValueInt.get:(I)Lorg/h2/value/ValueInt;
     375: invokeinterface #453,  3          // InterfaceMethod org/h2/result/Row.setValue:(ILorg/h2/value/Value;)V
     380: aload         11
     382: iconst_1
     383: iload         5
     385: invokestatic  #452                // Method org/h2/value/ValueInt.get:(I)Lorg/h2/value/ValueInt;
     388: invokeinterface #453,  3          // InterfaceMethod org/h2/result/Row.setValue:(ILorg/h2/value/Value;)V
     393: aload         11
     395: iconst_2
     396: aload_3
     397: invokevirtual #454                // Method org/h2/table/Table.getId:()I
     400: invokestatic  #452                // Method org/h2/value/ValueInt.get:(I)Lorg/h2/value/ValueInt;
     403: invokeinterface #453,  3          // InterfaceMethod org/h2/result/Row.setValue:(ILorg/h2/value/Value;)V
     408: aload         11
     410: iconst_3
     411: aload_1
     412: invokevirtual #455                // Method org/h2/index/PageIndex.getRootPageId:()I
     415: invokestatic  #452                // Method org/h2/value/ValueInt.get:(I)Lorg/h2/value/ValueInt;
     418: invokeinterface #453,  3          // InterfaceMethod org/h2/result/Row.setValue:(ILorg/h2/value/Value;)V
     423: aload         11
     425: iconst_4
     426: aload         10
     428: invokestatic  #456                // Method org/h2/value/ValueString.get:(Ljava/lang/String;)Lorg/h2/value/Value;
     431: invokeinterface #453,  3          // InterfaceMethod org/h2/result/Row.setValue:(ILorg/h2/value/Value;)V
     436: aload         11
     438: iconst_5
     439: aload         8
     441: invokestatic  #456                // Method org/h2/value/ValueString.get:(Ljava/lang/String;)Lorg/h2/value/Value;
     444: invokeinterface #453,  3          // InterfaceMethod org/h2/result/Row.setValue:(ILorg/h2/value/Value;)V
     449: aload         11
     451: aload_1
     452: invokevirtual #334                // Method org/h2/index/PageIndex.getId:()I
     455: iconst_1
     456: iadd
     457: i2l
     458: invokeinterface #457,  3          // InterfaceMethod org/h2/result/Row.setKey:(J)V
     463: aload_0
     464: getfield      #124                // Field metaIndex:Lorg/h2/index/PageDataIndex;
     467: aload_2
     468: aload         11
     470: invokevirtual #458                // Method org/h2/index/PageDataIndex.add:(Lorg/h2/engine/Session;Lorg/h2/result/Row;)V
     473: aload         4
     475: monitorexit
     476: goto          487
     479: astore        14
     481: aload         4
     483: monitorexit
     484: aload         14
     486: athrow
     487: return
    Exception table:
       from    to  target type
          31    42    45   any
          45    50    45   any
          26    56    59   any
          59    64    59   any
          72   476   479   any
         479   484   479   any

  public void removeMeta(org.h2.index.Index, org.h2.engine.Session);
    Code:
       0: getstatic     #217                // Field org/h2/engine/SysProperties.CHECK:Z
       3: ifeq          64
       6: aload_1
       7: invokeinterface #363,  1          // InterfaceMethod org/h2/index/Index.getTable:()Lorg/h2/table/Table;
      12: invokevirtual #119                // Method org/h2/table/Table.isTemporary:()Z
      15: ifne          64
      18: aload_0
      19: getfield      #21                 // Field database:Lorg/h2/engine/Database;
      22: dup
      23: astore_3
      24: monitorenter
      25: aload_0
      26: dup
      27: astore        4
      29: monitorenter
      30: aload_0
      31: getfield      #21                 // Field database:Lorg/h2/engine/Database;
      34: aload_2
      35: invokevirtual #438                // Method org/h2/engine/Database.verifyMetaLocked:(Lorg/h2/engine/Session;)V
      38: aload         4
      40: monitorexit
      41: goto          52
      44: astore        5
      46: aload         4
      48: monitorexit
      49: aload         5
      51: athrow
      52: aload_3
      53: monitorexit
      54: goto          64
      57: astore        6
      59: aload_3
      60: monitorexit
      61: aload         6
      63: athrow
      64: aload_0
      65: dup
      66: astore_3
      67: monitorenter
      68: aload_0
      69: getfield      #66                 // Field recoveryRunning:Z
      72: ifne          98
      75: aload_0
      76: aload_1
      77: aload_2
      78: invokespecial #459                // Method removeMetaIndex:(Lorg/h2/index/Index;Lorg/h2/engine/Session;)V
      81: aload_0
      82: getfield      #8                  // Field metaObjects:Ljava/util/HashMap;
      85: aload_1
      86: invokeinterface #460,  1          // InterfaceMethod org/h2/index/Index.getId:()I
      91: invokestatic  #34                 // Method java/lang/Integer.valueOf:(I)Ljava/lang/Integer;
      94: invokevirtual #402                // Method java/util/HashMap.remove:(Ljava/lang/Object;)Ljava/lang/Object;
      97: pop
      98: aload_3
      99: monitorexit
     100: goto          110
     103: astore        7
     105: aload_3
     106: monitorexit
     107: aload         7
     109: athrow
     110: return
    Exception table:
       from    to  target type
          30    41    44   any
          44    49    44   any
          25    54    57   any
          57    61    57   any
          68   100   103   any
         103   107   103   any

  private void removeMetaIndex(org.h2.index.Index, org.h2.engine.Session);
    Code:
       0: aload_1
       1: invokeinterface #460,  1          // InterfaceMethod org/h2/index/Index.getId:()I
       6: iconst_1
       7: iadd
       8: istore_3
       9: aload_0
      10: getfield      #124                // Field metaIndex:Lorg/h2/index/PageDataIndex;
      13: aload_2
      14: iload_3
      15: i2l
      16: invokevirtual #461                // Method org/h2/index/PageDataIndex.getRow:(Lorg/h2/engine/Session;J)Lorg/h2/result/Row;
      19: astore        4
      21: aload         4
      23: invokeinterface #355,  1          // InterfaceMethod org/h2/result/Row.getKey:()J
      28: iload_3
      29: i2l
      30: lcmp
      31: ifeq          96
      34: ldc           #49                 // int 90030
      36: new           #50                 // class java/lang/StringBuilder
      39: dup
      40: invokespecial #51                 // Method java/lang/StringBuilder."<init>":()V
      43: ldc_w         #462                // String key:
      46: invokevirtual #52                 // Method java/lang/StringBuilder.append:(Ljava/lang/String;)Ljava/lang/StringBuilder;
      49: iload_3
      50: invokevirtual #93                 // Method java/lang/StringBuilder.append:(I)Ljava/lang/StringBuilder;
      53: ldc_w         #463                // String  index:
      56: invokevirtual #52                 // Method java/lang/StringBuilder.append:(Ljava/lang/String;)Ljava/lang/StringBuilder;
      59: aload_1
      60: invokevirtual #205                // Method java/lang/StringBuilder.append:(Ljava/lang/Object;)Ljava/lang/StringBuilder;
      63: ldc_w         #464                // String  table:
      66: invokevirtual #52                 // Method java/lang/StringBuilder.append:(Ljava/lang/String;)Ljava/lang/StringBuilder;
      69: aload_1
      70: invokeinterface #363,  1          // InterfaceMethod org/h2/index/Index.getTable:()Lorg/h2/table/Table;
      75: invokevirtual #205                // Method java/lang/StringBuilder.append:(Ljava/lang/Object;)Ljava/lang/StringBuilder;
      78: ldc_w         #465                // String  row:
      81: invokevirtual #52                 // Method java/lang/StringBuilder.append:(Ljava/lang/String;)Ljava/lang/StringBuilder;
      84: aload         4
      86: invokevirtual #205                // Method java/lang/StringBuilder.append:(Ljava/lang/Object;)Ljava/lang/StringBuilder;
      89: invokevirtual #55                 // Method java/lang/StringBuilder.toString:()Ljava/lang/String;
      92: invokestatic  #56                 // Method org/h2/message/DbException.get:(ILjava/lang/String;)Lorg/h2/message/DbException;
      95: athrow
      96: aload_0
      97: getfield      #124                // Field metaIndex:Lorg/h2/index/PageDataIndex;
     100: aload_2
     101: aload         4
     103: invokevirtual #466                // Method org/h2/index/PageDataIndex.remove:(Lorg/h2/engine/Session;Lorg/h2/result/Row;)V
     106: return

  public void setMaxLogSize(long);
    Code:
       0: aload_0
       1: lload_1
       2: putfield      #11                 // Field maxLogSize:J
       5: return

  public synchronized void setInDoubtTransactionState(int, int, boolean);
    Code:
       0: aload_0
       1: getfield      #21                 // Field database:Lorg/h2/engine/Database;
       4: invokevirtual #48                 // Method org/h2/engine/Database.isReadOnly:()Z
       7: istore        4
       9: aload_0
      10: getfield      #21                 // Field database:Lorg/h2/engine/Database;
      13: iconst_0
      14: invokevirtual #261                // Method org/h2/engine/Database.setReadOnly:(Z)V
      17: aload_0
      18: getfield      #71                 // Field log:Lorg/h2/store/PageLog;
      21: iload_1
      22: iload_2
      23: iload_3
      24: invokevirtual #467                // Method org/h2/store/PageLog.setInDoubtTransactionState:(IIZ)V
      27: aload_0
      28: getfield      #21                 // Field database:Lorg/h2/engine/Database;
      31: iload         4
      33: invokevirtual #261                // Method org/h2/engine/Database.setReadOnly:(Z)V
      36: goto          53
      39: astore        5
      41: aload_0
      42: getfield      #21                 // Field database:Lorg/h2/engine/Database;
      45: iload         4
      47: invokevirtual #261                // Method org/h2/engine/Database.setReadOnly:(Z)V
      50: aload         5
      52: athrow
      53: return
    Exception table:
       from    to  target type
           9    27    39   any
          39    41    39   any

  public java.util.ArrayList<org.h2.store.InDoubtTransaction> getInDoubtTransactions();
    Code:
       0: aload_0
       1: getfield      #71                 // Field log:Lorg/h2/store/PageLog;
       4: invokevirtual #331                // Method org/h2/store/PageLog.getInDoubtTransactions:()Ljava/util/ArrayList;
       7: areturn

  public boolean isRecoveryRunning();
    Code:
       0: aload_0
       1: getfield      #66                 // Field recoveryRunning:Z
       4: ireturn

  private void checkOpen();
    Code:
       0: aload_0
       1: getfield      #37                 // Field file:Lorg/h2/store/FileStore;
       4: ifnonnull     14
       7: ldc_w         #468                // int 90098
      10: invokestatic  #469                // Method org/h2/message/DbException.get:(I)Lorg/h2/message/DbException;
      13: athrow
      14: return

  public long getWriteCountTotal();
    Code:
       0: aload_0
       1: getfield      #148                // Field writeCount:J
       4: aload_0
       5: getfield      #269                // Field writeCountBase:J
       8: ladd
       9: lreturn

  public long getWriteCount();
    Code:
       0: aload_0
       1: getfield      #148                // Field writeCount:J
       4: lreturn

  public long getReadCount();
    Code:
       0: aload_0
       1: getfield      #41                 // Field readCount:J
       4: lreturn

  public synchronized void logTruncate(org.h2.engine.Session, int);
    Code:
       0: aload_0
       1: getfield      #66                 // Field recoveryRunning:Z
       4: ifne          20
       7: aload_0
       8: invokespecial #107                // Method openForWriting:()V
      11: aload_0
      12: getfield      #71                 // Field log:Lorg/h2/store/PageLog;
      15: aload_1
      16: iload_2
      17: invokevirtual #470                // Method org/h2/store/PageLog.logTruncate:(Lorg/h2/engine/Session;I)V
      20: return

  public int getRootPageId(int);
    Code:
       0: aload_0
       1: getfield      #5                  // Field metaRootPageId:Lorg/h2/util/IntIntHashMap;
       4: iload_1
       5: invokevirtual #188                // Method org/h2/util/IntIntHashMap.get:(I)I
       8: ireturn

  public org.h2.util.Cache getCache();
    Code:
       0: aload_0
       1: getfield      #26                 // Field cache:Lorg/h2/util/Cache;
       4: areturn

  private void checksumSet(byte[], int);
    Code:
       0: aload_0
       1: getfield      #2                  // Field pageSize:I
       4: istore_3
       5: aload_1
       6: iconst_0
       7: baload
       8: istore        4
      10: iload         4
      12: ifne          16
      15: return
      16: sipush        255
      19: iload         4
      21: sipush        255
      24: iand
      25: iadd
      26: istore        5
      28: sipush        255
      31: iload         5
      33: iadd
      34: istore        6
      36: iload         6
      38: iload         5
      40: aload_1
      41: bipush        6
      43: baload
      44: sipush        255
      47: iand
      48: iadd
      49: dup
      50: istore        5
      52: iadd
      53: istore        6
      55: iload         6
      57: iload         5
      59: aload_1
      60: iload_3
      61: iconst_1
      62: ishr
      63: iconst_1
      64: isub
      65: baload
      66: sipush        255
      69: iand
      70: iadd
      71: dup
      72: istore        5
      74: iadd
      75: istore        6
      77: iload         6
      79: iload         5
      81: aload_1
      82: iload_3
      83: iconst_1
      84: ishr
      85: baload
      86: sipush        255
      89: iand
      90: iadd
      91: dup
      92: istore        5
      94: iadd
      95: istore        6
      97: iload         6
      99: iload         5
     101: aload_1
     102: iload_3
     103: iconst_2
     104: isub
     105: baload
     106: sipush        255
     109: iand
     110: iadd
     111: dup
     112: istore        5
     114: iadd
     115: istore        6
     117: iload         6
     119: iload         5
     121: aload_1
     122: iload_3
     123: iconst_1
     124: isub
     125: baload
     126: sipush        255
     129: iand
     130: iadd
     131: dup
     132: istore        5
     134: iadd
     135: istore        6
     137: aload_1
     138: iconst_1
     139: iload         5
     141: sipush        255
     144: iand
     145: iload         5
     147: bipush        8
     149: ishr
     150: iadd
     151: iload_2
     152: ixor
     153: i2b
     154: bastore
     155: aload_1
     156: iconst_2
     157: iload         6
     159: sipush        255
     162: iand
     163: iload         6
     165: bipush        8
     167: ishr
     168: iadd
     169: iload_2
     170: bipush        8
     172: ishr
     173: ixor
     174: i2b
     175: bastore
     176: return

  public static boolean checksumTest(byte[], int, int);
    Code:
       0: sipush        255
       3: aload_0
       4: iconst_0
       5: baload
       6: sipush        255
       9: iand
      10: iadd
      11: istore_3
      12: sipush        255
      15: iload_3
      16: iadd
      17: istore        4
      19: iload         4
      21: iload_3
      22: aload_0
      23: bipush        6
      25: baload
      26: sipush        255
      29: iand
      30: iadd
      31: dup
      32: istore_3
      33: iadd
      34: istore        4
      36: iload         4
      38: iload_3
      39: aload_0
      40: iload_2
      41: iconst_1
      42: ishr
      43: iconst_1
      44: isub
      45: baload
      46: sipush        255
      49: iand
      50: iadd
      51: dup
      52: istore_3
      53: iadd
      54: istore        4
      56: iload         4
      58: iload_3
      59: aload_0
      60: iload_2
      61: iconst_1
      62: ishr
      63: baload
      64: sipush        255
      67: iand
      68: iadd
      69: dup
      70: istore_3
      71: iadd
      72: istore        4
      74: iload         4
      76: iload_3
      77: aload_0
      78: iload_2
      79: iconst_2
      80: isub
      81: baload
      82: sipush        255
      85: iand
      86: iadd
      87: dup
      88: istore_3
      89: iadd
      90: istore        4
      92: iload         4
      94: iload_3
      95: aload_0
      96: iload_2
      97: iconst_1
      98: isub
      99: baload
     100: sipush        255
     103: iand
     104: iadd
     105: dup
     106: istore_3
     107: iadd
     108: istore        4
     110: aload_0
     111: iconst_1
     112: baload
     113: iload_3
     114: sipush        255
     117: iand
     118: iload_3
     119: bipush        8
     121: ishr
     122: iadd
     123: iload_1
     124: ixor
     125: i2b
     126: if_icmpne     157
     129: aload_0
     130: iconst_2
     131: baload
     132: iload         4
     134: sipush        255
     137: iand
     138: iload         4
     140: bipush        8
     142: ishr
     143: iadd
     144: iload_1
     145: bipush        8
     147: ishr
     148: ixor
     149: i2b
     150: if_icmpne     157
     153: iconst_1
     154: goto          158
     157: iconst_0
     158: ireturn

  public void incrementChangeCount();
    Code:
       0: aload_0
       1: dup
       2: getfield      #17                 // Field changeCount:J
       5: lconst_1
       6: ladd
       7: putfield      #17                 // Field changeCount:J
      10: getstatic     #217                // Field org/h2/engine/SysProperties.CHECK:Z
      13: ifeq          31
      16: aload_0
      17: getfield      #17                 // Field changeCount:J
      20: lconst_0
      21: lcmp
      22: ifge          31
      25: ldc           #218                // String changeCount has wrapped
      27: invokestatic  #186                // Method org/h2/message/DbException.throwInternalError:(Ljava/lang/String;)Ljava/lang/RuntimeException;
      30: athrow
      31: return

  public long getChangeCount();
    Code:
       0: aload_0
       1: getfield      #17                 // Field changeCount:J
       4: lreturn

  public void setLogMode(int);
    Code:
       0: aload_0
       1: iload_1
       2: putfield      #18                 // Field logMode:I
       5: return

  public int getLogMode();
    Code:
       0: aload_0
       1: getfield      #18                 // Field logMode:I
       4: ireturn

  public void setLockFile(boolean);
    Code:
       0: aload_0
       1: iload_1
       2: putfield      #79                 // Field lockFile:Z
       5: return

  public org.h2.util.BitField getObjectIds();
    Code:
       0: new           #12                 // class org/h2/util/BitField
       3: dup
       4: invokespecial #13                 // Method org/h2/util/BitField."<init>":()V
       7: astore_1
       8: aload_0
       9: getfield      #124                // Field metaIndex:Lorg/h2/index/PageDataIndex;
      12: aload_0
      13: getfield      #29                 // Field pageStoreSession:Lorg/h2/engine/Session;
      16: aconst_null
      17: aconst_null
      18: invokevirtual #395                // Method org/h2/index/PageDataIndex.find:(Lorg/h2/engine/Session;Lorg/h2/result/SearchRow;Lorg/h2/result/SearchRow;)Lorg/h2/index/Cursor;
      21: astore_2
      22: aload_2
      23: invokeinterface #176,  1          // InterfaceMethod org/h2/index/Cursor.next:()Z
      28: ifeq          64
      31: aload_2
      32: invokeinterface #177,  1          // InterfaceMethod org/h2/index/Cursor.get:()Lorg/h2/result/Row;
      37: astore_3
      38: aload_3
      39: iconst_0
      40: invokeinterface #352,  2          // InterfaceMethod org/h2/result/Row.getValue:(I)Lorg/h2/value/Value;
      45: invokevirtual #353                // Method org/h2/value/Value.getInt:()I
      48: istore        4
      50: iload         4
      52: ifle          61
      55: aload_1
      56: iload         4
      58: invokevirtual #149                // Method org/h2/util/BitField.set:(I)V
      61: goto          22
      64: aload_1
      65: areturn

  public org.h2.engine.Session getPageStoreSession();
    Code:
       0: aload_0
       1: getfield      #29                 // Field pageStoreSession:Lorg/h2/engine/Session;
       4: areturn

  public synchronized void setBackup(boolean);
    Code:
       0: aload_0
       1: dup
       2: getfield      #133                // Field backupLevel:I
       5: iload_1
       6: ifeq          13
       9: iconst_1
      10: goto          14
      13: iconst_m1
      14: iadd
      15: putfield      #133                // Field backupLevel:I
      18: return
}
