Compiled from "MVStore.java"
class org.h2.mvstore.MVStore$2 implements java.util.Comparator<org.h2.mvstore.Chunk> {
  final org.h2.mvstore.MVStore this$0;

  org.h2.mvstore.MVStore$2(org.h2.mvstore.MVStore);
    Code:
       0: aload_0
       1: aload_1
       2: putfield      #1                  // Field this$0:Lorg/h2/mvstore/MVStore;
       5: aload_0
       6: invokespecial #2                  // Method java/lang/Object."<init>":()V
       9: return

  public int compare(org.h2.mvstore.Chunk, org.h2.mvstore.Chunk);
    Code:
       0: aload_1
       1: getfield      #3                  // Field org/h2/mvstore/Chunk.collectPriority:I
       4: aload_2
       5: getfield      #3                  // Field org/h2/mvstore/Chunk.collectPriority:I
       8: invokestatic  #4                  // Method java/lang/Integer.compare:(II)I
      11: istore_3
      12: iload_3
      13: ifne          28
      16: aload_1
      17: getfield      #5                  // Field org/h2/mvstore/Chunk.maxLenLive:J
      20: aload_2
      21: getfield      #5                  // Field org/h2/mvstore/Chunk.maxLenLive:J
      24: invokestatic  #6                  // Method java/lang/Long.compare:(JJ)I
      27: istore_3
      28: iload_3
      29: ireturn

  public int compare(java.lang.Object, java.lang.Object);
    Code:
       0: aload_0
       1: aload_1
       2: checkcast     #7                  // class org/h2/mvstore/Chunk
       5: aload_2
       6: checkcast     #7                  // class org/h2/mvstore/Chunk
       9: invokevirtual #8                  // Method compare:(Lorg/h2/mvstore/Chunk;Lorg/h2/mvstore/Chunk;)I
      12: ireturn
}
