Compiled from "AbstractSpringFunctionAdapterInitializer.java"
class org.springframework.cloud.function.context.AbstractSpringFunctionAdapterInitializer$1 implements org.springframework.context.ApplicationContextInitializer<org.springframework.context.ConfigurableApplicationContext> {
  final java.lang.Object val$targetContext;

  final org.springframework.cloud.function.context.AbstractSpringFunctionAdapterInitializer this$0;

  org.springframework.cloud.function.context.AbstractSpringFunctionAdapterInitializer$1(org.springframework.cloud.function.context.AbstractSpringFunctionAdapterInitializer, java.lang.Object);
    Code:
       0: aload_0
       1: aload_1
       2: putfield      #2                  // Field this$0:Lorg/springframework/cloud/function/context/AbstractSpringFunctionAdapterInitializer;
       5: aload_0
       6: aload_2
       7: putfield      #3                  // Field val$targetContext:Ljava/lang/Object;
      10: aload_0
      11: invokespecial #4                  // Method java/lang/Object."<init>":()V
      14: return

  public void initialize(org.springframework.context.ConfigurableApplicationContext);
    Code:
       0: aload_1
       1: checkcast     #5                  // class org/springframework/context/support/GenericApplicationContext
       4: ldc           #6                  // String targetExecutionContext
       6: aload_0
       7: getfield      #3                  // Field val$targetContext:Ljava/lang/Object;
      10: invokevirtual #7                  // Method java/lang/Object.getClass:()Ljava/lang/Class;
      13: aload_0
      14: getfield      #3                  // Field val$targetContext:Ljava/lang/Object;
      17: invokedynamic #8,  0              // InvokeDynamic #0:get:(Ljava/lang/Object;)Ljava/util/function/Supplier;
      22: iconst_0
      23: anewarray     #9                  // class org/springframework/beans/factory/config/BeanDefinitionCustomizer
      26: invokevirtual #10                 // Method org/springframework/context/support/GenericApplicationContext.registerBean:(Ljava/lang/String;Ljava/lang/Class;Ljava/util/function/Supplier;[Lorg/springframework/beans/factory/config/BeanDefinitionCustomizer;)V
      29: return

  private static java.lang.Object lambda$initialize$0(java.lang.Object);
    Code:
       0: aload_0
       1: areturn
}
