Compiled from "HttpUpgradeConnectionProviderFactory.java"
public final class org.jboss.remoting3.remote.HttpUpgradeConnectionProviderFactory implements org.jboss.remoting3.spi.ConnectionProviderFactory {
  public org.jboss.remoting3.remote.HttpUpgradeConnectionProviderFactory();
    Code:
       0: aload_0
       1: invokespecial #1                  // Method java/lang/Object."<init>":()V
       4: return

  public org.jboss.remoting3.spi.ConnectionProvider createInstance(org.jboss.remoting3.spi.ConnectionProviderContext, org.xnio.OptionMap) throws java.io.IOException;
    Code:
       0: new           #2                  // class org/jboss/remoting3/remote/HttpUpgradeConnectionProvider
       3: dup
       4: aload_2
       5: aload_1
       6: invokespecial #3                  // Method org/jboss/remoting3/remote/HttpUpgradeConnectionProvider."<init>":(Lorg/xnio/OptionMap;Lorg/jboss/remoting3/spi/ConnectionProviderContext;)V
       9: areturn
}
