Compiled from "InlineState.java"
public class org.xwiki.rendering.wikimodel.impl.InlineState {
  public static final int BEGIN;

  public static final int BEGIN_FORMAT;

  public static final int ESCAPE;

  public static final int EXTENSION;

  private static int fCounter;

  public static final int IMAGE;

  public static final int LINE_BREAK;

  public static final int MACRO;

  public static final int NEW_LINE;

  public static final int REFERENCE;

  public static final int SPACE;

  public static final int SPECIAL_SYMBOL;

  public static final int VERBATIM;

  public static final int WORD;

  private int fState;

  public org.xwiki.rendering.wikimodel.impl.InlineState();
    Code:
       0: aload_0
       1: invokespecial #1                  // Method java/lang/Object."<init>":()V
       4: aload_0
       5: getstatic     #2                  // Field BEGIN_FORMAT:I
       8: putfield      #3                  // Field fState:I
      11: return

  private static int inc();
    Code:
       0: getstatic     #4                  // Field fCounter:I
       3: iconst_1
       4: iadd
       5: putstatic     #4                  // Field fCounter:I
       8: iconst_1
       9: getstatic     #4                  // Field fCounter:I
      12: ishl
      13: ireturn

  public boolean check(int);
    Code:
       0: aload_0
       1: getfield      #3                  // Field fState:I
       4: iload_1
       5: iand
       6: iload_1
       7: if_icmpne     14
      10: iconst_1
      11: goto          15
      14: iconst_0
      15: ireturn

  public int get();
    Code:
       0: aload_0
       1: getfield      #3                  // Field fState:I
       4: ireturn

  public void set(int);
    Code:
       0: aload_0
       1: iload_1
       2: putfield      #3                  // Field fState:I
       5: return

  static {};
    Code:
       0: invokestatic  #5                  // Method inc:()I
       3: putstatic     #6                  // Field BEGIN:I
       6: invokestatic  #5                  // Method inc:()I
       9: putstatic     #2                  // Field BEGIN_FORMAT:I
      12: invokestatic  #5                  // Method inc:()I
      15: putstatic     #7                  // Field ESCAPE:I
      18: invokestatic  #5                  // Method inc:()I
      21: putstatic     #8                  // Field EXTENSION:I
      24: invokestatic  #5                  // Method inc:()I
      27: putstatic     #9                  // Field IMAGE:I
      30: invokestatic  #5                  // Method inc:()I
      33: putstatic     #10                 // Field LINE_BREAK:I
      36: invokestatic  #5                  // Method inc:()I
      39: putstatic     #11                 // Field MACRO:I
      42: invokestatic  #5                  // Method inc:()I
      45: putstatic     #12                 // Field NEW_LINE:I
      48: invokestatic  #5                  // Method inc:()I
      51: putstatic     #13                 // Field REFERENCE:I
      54: invokestatic  #5                  // Method inc:()I
      57: putstatic     #14                 // Field SPACE:I
      60: invokestatic  #5                  // Method inc:()I
      63: putstatic     #15                 // Field SPECIAL_SYMBOL:I
      66: invokestatic  #5                  // Method inc:()I
      69: putstatic     #16                 // Field VERBATIM:I
      72: invokestatic  #5                  // Method inc:()I
      75: putstatic     #17                 // Field WORD:I
      78: return
}
