Compiled from "BeansWriter.java"
public class net.minidev.json.reader.BeansWriter implements net.minidev.json.reader.JsonWriterI<java.lang.Object> {
  public net.minidev.json.reader.BeansWriter();
    Code:
       0: aload_0
       1: invokespecial #1                  // Method java/lang/Object."<init>":()V
       4: return

  public <E> void writeJSONString(E, java.lang.Appendable, net.minidev.json.JSONStyle) throws java.io.IOException;
    Code:
       0: aload_1
       1: invokevirtual #2                  // Method java/lang/Object.getClass:()Ljava/lang/Class;
       4: astore        4
       6: iconst_0
       7: istore        5
       9: aload_3
      10: aload_2
      11: invokevirtual #3                  // Method net/minidev/json/JSONStyle.objectStart:(Ljava/lang/Appendable;)V
      14: aload         4
      16: ldc           #4                  // class java/lang/Object
      18: if_acmpeq     258
      21: aload         4
      23: invokevirtual #5                  // Method java/lang/Class.getDeclaredFields:()[Ljava/lang/reflect/Field;
      26: astore        6
      28: aload         6
      30: astore        7
      32: aload         7
      34: arraylength
      35: istore        8
      37: iconst_0
      38: istore        9
      40: iload         9
      42: iload         8
      44: if_icmpge     248
      47: aload         7
      49: iload         9
      51: aaload
      52: astore        10
      54: aload         10
      56: invokevirtual #6                  // Method java/lang/reflect/Field.getModifiers:()I
      59: istore        11
      61: iload         11
      63: sipush        152
      66: iand
      67: ifle          73
      70: goto          242
      73: aconst_null
      74: astore        12
      76: iload         11
      78: iconst_1
      79: iand
      80: ifle          94
      83: aload         10
      85: aload_1
      86: invokevirtual #8                  // Method java/lang/reflect/Field.get:(Ljava/lang/Object;)Ljava/lang/Object;
      89: astore        12
      91: goto          195
      94: aload         10
      96: invokevirtual #9                  // Method java/lang/reflect/Field.getName:()Ljava/lang/String;
      99: invokestatic  #10                 // Method net/minidev/json/JSONUtil.getGetterName:(Ljava/lang/String;)Ljava/lang/String;
     102: astore        13
     104: aconst_null
     105: astore        14
     107: aload         4
     109: aload         13
     111: iconst_0
     112: anewarray     #11                 // class java/lang/Class
     115: invokevirtual #12                 // Method java/lang/Class.getDeclaredMethod:(Ljava/lang/String;[Ljava/lang/Class;)Ljava/lang/reflect/Method;
     118: astore        14
     120: goto          125
     123: astore        15
     125: aload         14
     127: ifnonnull     175
     130: aload         10
     132: invokevirtual #14                 // Method java/lang/reflect/Field.getType:()Ljava/lang/Class;
     135: astore        15
     137: aload         15
     139: getstatic     #15                 // Field java/lang/Boolean.TYPE:Ljava/lang/Class;
     142: if_acmpeq     152
     145: aload         15
     147: ldc           #16                 // class java/lang/Boolean
     149: if_acmpne     175
     152: aload         10
     154: invokevirtual #9                  // Method java/lang/reflect/Field.getName:()Ljava/lang/String;
     157: invokestatic  #17                 // Method net/minidev/json/JSONUtil.getIsName:(Ljava/lang/String;)Ljava/lang/String;
     160: astore        13
     162: aload         4
     164: aload         13
     166: iconst_0
     167: anewarray     #11                 // class java/lang/Class
     170: invokevirtual #12                 // Method java/lang/Class.getDeclaredMethod:(Ljava/lang/String;[Ljava/lang/Class;)Ljava/lang/reflect/Method;
     173: astore        14
     175: aload         14
     177: ifnonnull     183
     180: goto          242
     183: aload         14
     185: aload_1
     186: iconst_0
     187: anewarray     #4                  // class java/lang/Object
     190: invokevirtual #18                 // Method java/lang/reflect/Method.invoke:(Ljava/lang/Object;[Ljava/lang/Object;)Ljava/lang/Object;
     193: astore        12
     195: aload         12
     197: ifnonnull     210
     200: aload_3
     201: invokevirtual #19                 // Method net/minidev/json/JSONStyle.ignoreNull:()Z
     204: ifeq          210
     207: goto          242
     210: iload         5
     212: ifeq          223
     215: aload_3
     216: aload_2
     217: invokevirtual #20                 // Method net/minidev/json/JSONStyle.objectNext:(Ljava/lang/Appendable;)V
     220: goto          226
     223: iconst_1
     224: istore        5
     226: aload         10
     228: invokevirtual #9                  // Method java/lang/reflect/Field.getName:()Ljava/lang/String;
     231: astore        13
     233: aload         13
     235: aload         12
     237: aload_2
     238: aload_3
     239: invokestatic  #21                 // Method net/minidev/json/reader/JsonWriter.writeJSONKV:(Ljava/lang/String;Ljava/lang/Object;Ljava/lang/Appendable;Lnet/minidev/json/JSONStyle;)V
     242: iinc          9, 1
     245: goto          40
     248: aload         4
     250: invokevirtual #22                 // Method java/lang/Class.getSuperclass:()Ljava/lang/Class;
     253: astore        4
     255: goto          14
     258: aload_3
     259: aload_2
     260: invokevirtual #23                 // Method net/minidev/json/JSONStyle.objectStop:(Ljava/lang/Appendable;)V
     263: goto          278
     266: astore        4
     268: new           #24                 // class java/lang/RuntimeException
     271: dup
     272: aload         4
     274: invokespecial #25                 // Method java/lang/RuntimeException."<init>":(Ljava/lang/Throwable;)V
     277: athrow
     278: return
    Exception table:
       from    to  target type
         107   120   123   Class java/lang/Exception
           0   263   266   Class java/lang/Exception
}
