Compiled from "BCodec.java"
public class io.dekorate.deps.commons.codec.net.BCodec extends io.dekorate.deps.commons.codec.net.RFC1522Codec implements io.dekorate.deps.commons.codec.StringEncoder,io.dekorate.deps.commons.codec.StringDecoder {
  private final java.nio.charset.Charset charset;

  public io.dekorate.deps.commons.codec.net.BCodec();
    Code:
       0: aload_0
       1: getstatic     #18                 // Field io/dekorate/deps/commons/codec/Charsets.UTF_8:Ljava/nio/charset/Charset;
       4: invokespecial #21                 // Method "<init>":(Ljava/nio/charset/Charset;)V
       7: return

  public io.dekorate.deps.commons.codec.net.BCodec(java.nio.charset.Charset);
    Code:
       0: aload_0
       1: invokespecial #25                 // Method io/dekorate/deps/commons/codec/net/RFC1522Codec."<init>":()V
       4: aload_0
       5: aload_1
       6: putfield      #27                 // Field charset:Ljava/nio/charset/Charset;
       9: return

  public io.dekorate.deps.commons.codec.net.BCodec(java.lang.String);
    Code:
       0: aload_0
       1: aload_1
       2: invokestatic  #34                 // Method java/nio/charset/Charset.forName:(Ljava/lang/String;)Ljava/nio/charset/Charset;
       5: invokespecial #21                 // Method "<init>":(Ljava/nio/charset/Charset;)V
       8: return

  protected java.lang.String getEncoding();
    Code:
       0: ldc           #40                 // String B
       2: areturn

  protected byte[] doEncoding(byte[]);
    Code:
       0: aload_1
       1: ifnonnull     6
       4: aconst_null
       5: areturn
       6: aload_1
       7: invokestatic  #47                 // Method io/dekorate/deps/commons/codec/binary/Base64.encodeBase64:([B)[B
      10: areturn

  protected byte[] doDecoding(byte[]);
    Code:
       0: aload_1
       1: ifnonnull     6
       4: aconst_null
       5: areturn
       6: aload_1
       7: invokestatic  #53                 // Method io/dekorate/deps/commons/codec/binary/Base64.decodeBase64:([B)[B
      10: areturn

  public java.lang.String encode(java.lang.String, java.nio.charset.Charset) throws io.dekorate.deps.commons.codec.EncoderException;
    Code:
       0: aload_1
       1: ifnonnull     6
       4: aconst_null
       5: areturn
       6: aload_0
       7: aload_1
       8: aload_2
       9: invokevirtual #60                 // Method encodeText:(Ljava/lang/String;Ljava/nio/charset/Charset;)Ljava/lang/String;
      12: areturn

  public java.lang.String encode(java.lang.String, java.lang.String) throws io.dekorate.deps.commons.codec.EncoderException;
    Code:
       0: aload_1
       1: ifnonnull     6
       4: aconst_null
       5: areturn
       6: aload_0
       7: aload_1
       8: aload_2
       9: invokevirtual #66                 // Method encodeText:(Ljava/lang/String;Ljava/lang/String;)Ljava/lang/String;
      12: areturn
      13: astore_3
      14: new           #57                 // class io/dekorate/deps/commons/codec/EncoderException
      17: dup
      18: aload_3
      19: invokevirtual #69                 // Method java/io/UnsupportedEncodingException.getMessage:()Ljava/lang/String;
      22: aload_3
      23: invokespecial #72                 // Method io/dekorate/deps/commons/codec/EncoderException."<init>":(Ljava/lang/String;Ljava/lang/Throwable;)V
      26: athrow
    Exception table:
       from    to  target type
           6    12    13   Class java/io/UnsupportedEncodingException

  public java.lang.String encode(java.lang.String) throws io.dekorate.deps.commons.codec.EncoderException;
    Code:
       0: aload_1
       1: ifnonnull     6
       4: aconst_null
       5: areturn
       6: aload_0
       7: aload_1
       8: aload_0
       9: invokevirtual #79                 // Method getCharset:()Ljava/nio/charset/Charset;
      12: invokevirtual #81                 // Method encode:(Ljava/lang/String;Ljava/nio/charset/Charset;)Ljava/lang/String;
      15: areturn

  public java.lang.String decode(java.lang.String) throws io.dekorate.deps.commons.codec.DecoderException;
    Code:
       0: aload_1
       1: ifnonnull     6
       4: aconst_null
       5: areturn
       6: aload_0
       7: aload_1
       8: invokevirtual #87                 // Method decodeText:(Ljava/lang/String;)Ljava/lang/String;
      11: areturn
      12: astore_2
      13: new           #84                 // class io/dekorate/deps/commons/codec/DecoderException
      16: dup
      17: aload_2
      18: invokevirtual #69                 // Method java/io/UnsupportedEncodingException.getMessage:()Ljava/lang/String;
      21: aload_2
      22: invokespecial #88                 // Method io/dekorate/deps/commons/codec/DecoderException."<init>":(Ljava/lang/String;Ljava/lang/Throwable;)V
      25: athrow
    Exception table:
       from    to  target type
           6    11    12   Class java/io/UnsupportedEncodingException

  public java.lang.Object encode(java.lang.Object) throws io.dekorate.deps.commons.codec.EncoderException;
    Code:
       0: aload_1
       1: ifnonnull     6
       4: aconst_null
       5: areturn
       6: aload_1
       7: instanceof    #91                 // class java/lang/String
      10: ifeq          22
      13: aload_0
      14: aload_1
      15: checkcast     #91                 // class java/lang/String
      18: invokevirtual #93                 // Method encode:(Ljava/lang/String;)Ljava/lang/String;
      21: areturn
      22: new           #57                 // class io/dekorate/deps/commons/codec/EncoderException
      25: dup
      26: new           #95                 // class java/lang/StringBuilder
      29: dup
      30: invokespecial #96                 // Method java/lang/StringBuilder."<init>":()V
      33: ldc           #98                 // String Objects of type
      35: invokevirtual #102                // Method java/lang/StringBuilder.append:(Ljava/lang/String;)Ljava/lang/StringBuilder;
      38: aload_1
      39: invokevirtual #108                // Method java/lang/Object.getClass:()Ljava/lang/Class;
      42: invokevirtual #113                // Method java/lang/Class.getName:()Ljava/lang/String;
      45: invokevirtual #102                // Method java/lang/StringBuilder.append:(Ljava/lang/String;)Ljava/lang/StringBuilder;
      48: ldc           #115                // String  cannot be encoded using BCodec
      50: invokevirtual #102                // Method java/lang/StringBuilder.append:(Ljava/lang/String;)Ljava/lang/StringBuilder;
      53: invokevirtual #118                // Method java/lang/StringBuilder.toString:()Ljava/lang/String;
      56: invokespecial #120                // Method io/dekorate/deps/commons/codec/EncoderException."<init>":(Ljava/lang/String;)V
      59: athrow

  public java.lang.Object decode(java.lang.Object) throws io.dekorate.deps.commons.codec.DecoderException;
    Code:
       0: aload_1
       1: ifnonnull     6
       4: aconst_null
       5: areturn
       6: aload_1
       7: instanceof    #91                 // class java/lang/String
      10: ifeq          22
      13: aload_0
      14: aload_1
      15: checkcast     #91                 // class java/lang/String
      18: invokevirtual #123                // Method decode:(Ljava/lang/String;)Ljava/lang/String;
      21: areturn
      22: new           #84                 // class io/dekorate/deps/commons/codec/DecoderException
      25: dup
      26: new           #95                 // class java/lang/StringBuilder
      29: dup
      30: invokespecial #96                 // Method java/lang/StringBuilder."<init>":()V
      33: ldc           #98                 // String Objects of type
      35: invokevirtual #102                // Method java/lang/StringBuilder.append:(Ljava/lang/String;)Ljava/lang/StringBuilder;
      38: aload_1
      39: invokevirtual #108                // Method java/lang/Object.getClass:()Ljava/lang/Class;
      42: invokevirtual #113                // Method java/lang/Class.getName:()Ljava/lang/String;
      45: invokevirtual #102                // Method java/lang/StringBuilder.append:(Ljava/lang/String;)Ljava/lang/StringBuilder;
      48: ldc           #125                // String  cannot be decoded using BCodec
      50: invokevirtual #102                // Method java/lang/StringBuilder.append:(Ljava/lang/String;)Ljava/lang/StringBuilder;
      53: invokevirtual #118                // Method java/lang/StringBuilder.toString:()Ljava/lang/String;
      56: invokespecial #126                // Method io/dekorate/deps/commons/codec/DecoderException."<init>":(Ljava/lang/String;)V
      59: athrow

  public java.nio.charset.Charset getCharset();
    Code:
       0: aload_0
       1: getfield      #27                 // Field charset:Ljava/nio/charset/Charset;
       4: areturn

  public java.lang.String getDefaultCharset();
    Code:
       0: aload_0
       1: getfield      #27                 // Field charset:Ljava/nio/charset/Charset;
       4: invokevirtual #130                // Method java/nio/charset/Charset.name:()Ljava/lang/String;
       7: areturn
}
