Compiled from "OperationCancellationException.java"
public class org.jboss.as.controller._private.OperationCancellationException extends java.util.concurrent.CancellationException implements org.jboss.as.controller.OperationClientException {
  private static final long serialVersionUID;

  static final boolean $assertionsDisabled;

  public org.jboss.as.controller._private.OperationCancellationException(java.lang.String);
    Code:
       0: aload_0
       1: aload_1
       2: invokespecial #1                  // Method java/util/concurrent/CancellationException."<init>":(Ljava/lang/String;)V
       5: getstatic     #2                  // Field $assertionsDisabled:Z
       8: ifne          25
      11: aload_1
      12: ifnonnull     25
      15: new           #3                  // class java/lang/AssertionError
      18: dup
      19: ldc           #4                  // String message is null
      21: invokespecial #5                  // Method java/lang/AssertionError."<init>":(Ljava/lang/Object;)V
      24: athrow
      25: return

  public org.jboss.dmr.ModelNode getFailureDescription();
    Code:
       0: new           #6                  // class org/jboss/dmr/ModelNode
       3: dup
       4: aload_0
       5: invokevirtual #7                  // Method getMessage:()Ljava/lang/String;
       8: invokespecial #8                  // Method org/jboss/dmr/ModelNode."<init>":(Ljava/lang/String;)V
      11: areturn

  static {};
    Code:
       0: ldc           #9                  // class org/jboss/as/controller/_private/OperationCancellationException
       2: invokevirtual #10                 // Method java/lang/Class.desiredAssertionStatus:()Z
       5: ifne          12
       8: iconst_1
       9: goto          13
      12: iconst_0
      13: putstatic     #2                  // Field $assertionsDisabled:Z
      16: return
}
