Compiled from "GeneratorConfig.java"
public class io.dekorate.option.config.GeneratorConfig extends io.dekorate.kubernetes.config.Configuration {
  private java.lang.String inputPath;

  private java.lang.String outputPath;

  public io.dekorate.option.config.GeneratorConfig();
    Code:
       0: aload_0
       1: invokespecial #1                  // Method io/dekorate/kubernetes/config/Configuration."<init>":()V
       4: aload_0
       5: ldc           #2                  // String
       7: putfield      #3                  // Field inputPath:Ljava/lang/String;
      10: aload_0
      11: ldc           #2                  // String
      13: putfield      #4                  // Field outputPath:Ljava/lang/String;
      16: return

  public io.dekorate.option.config.GeneratorConfig(io.dekorate.project.Project, java.util.Map<io.dekorate.kubernetes.config.ConfigKey, java.lang.Object>, java.lang.String, java.lang.String);
    Code:
       0: aload_0
       1: aload_1
       2: aload_2
       3: invokespecial #5                  // Method io/dekorate/kubernetes/config/Configuration."<init>":(Lio/dekorate/project/Project;Ljava/util/Map;)V
       6: aload_0
       7: ldc           #2                  // String
       9: putfield      #3                  // Field inputPath:Ljava/lang/String;
      12: aload_0
      13: ldc           #2                  // String
      15: putfield      #4                  // Field outputPath:Ljava/lang/String;
      18: aload_0
      19: aload_3
      20: ifnull        27
      23: aload_3
      24: goto          29
      27: ldc           #2                  // String
      29: putfield      #3                  // Field inputPath:Ljava/lang/String;
      32: aload_0
      33: aload         4
      35: ifnull        43
      38: aload         4
      40: goto          45
      43: ldc           #2                  // String
      45: putfield      #4                  // Field outputPath:Ljava/lang/String;
      48: return

  public java.lang.String getInputPath();
    Code:
       0: aload_0
       1: getfield      #3                  // Field inputPath:Ljava/lang/String;
       4: areturn

  public java.lang.String getOutputPath();
    Code:
       0: aload_0
       1: getfield      #4                  // Field outputPath:Ljava/lang/String;
       4: areturn
}
