Compiled from "UID.java"
public final class org.apache.cxf.aegis.util.UID {
  private static int counter;

  private static java.util.Random random;

  private org.apache.cxf.aegis.util.UID();
    Code:
       0: aload_0
       1: invokespecial #1                  // Method java/lang/Object."<init>":()V
       4: return

  public static java.lang.String generate();
    Code:
       0: new           #2                  // class java/lang/StringBuilder
       3: dup
       4: invokespecial #3                  // Method java/lang/StringBuilder."<init>":()V
       7: invokestatic  #4                  // Method java/lang/System.currentTimeMillis:()J
      10: invokestatic  #5                  // Method java/lang/String.valueOf:(J)Ljava/lang/String;
      13: invokevirtual #6                  // Method java/lang/StringBuilder.append:(Ljava/lang/String;)Ljava/lang/StringBuilder;
      16: getstatic     #7                  // Field counter:I
      19: dup
      20: iconst_1
      21: iadd
      22: putstatic     #7                  // Field counter:I
      25: invokevirtual #8                  // Method java/lang/StringBuilder.append:(I)Ljava/lang/StringBuilder;
      28: getstatic     #9                  // Field random:Ljava/util/Random;
      31: invokevirtual #10                 // Method java/util/Random.nextInt:()I
      34: invokevirtual #8                  // Method java/lang/StringBuilder.append:(I)Ljava/lang/StringBuilder;
      37: invokevirtual #11                 // Method java/lang/StringBuilder.toString:()Ljava/lang/String;
      40: areturn

  static {};
    Code:
       0: new           #12                 // class java/util/Random
       3: dup
       4: invokestatic  #4                  // Method java/lang/System.currentTimeMillis:()J
       7: invokespecial #13                 // Method java/util/Random."<init>":(J)V
      10: putstatic     #9                  // Field random:Ljava/util/Random;
      13: return
}
