Compiled from "ResourcesSetCssAdapter.java"
public class org.primefaces.extensions.optimizerplugin.util.ResourcesSetCssAdapter extends org.primefaces.extensions.optimizerplugin.util.ResourcesSetAdapter {
  private final org.primefaces.extensions.optimizerplugin.replacer.DataUriTokenResolver dataUriTokenResolver;

  public org.primefaces.extensions.optimizerplugin.util.ResourcesSetCssAdapter(java.io.File, java.util.Set<java.io.File>, org.primefaces.extensions.optimizerplugin.replacer.DataUriTokenResolver, org.primefaces.extensions.optimizerplugin.model.Aggregation, java.lang.String, boolean, java.lang.String);
    Code:
       0: aload_0
       1: aload_1
       2: aload_2
       3: aload         4
       5: aload         5
       7: iload         6
       9: aload         7
      11: invokespecial #1                  // Method org/primefaces/extensions/optimizerplugin/util/ResourcesSetAdapter."<init>":(Ljava/io/File;Ljava/util/Set;Lorg/primefaces/extensions/optimizerplugin/model/Aggregation;Ljava/lang/String;ZLjava/lang/String;)V
      14: aload_0
      15: aload_3
      16: putfield      #7                  // Field dataUriTokenResolver:Lorg/primefaces/extensions/optimizerplugin/replacer/DataUriTokenResolver;
      19: return

  public org.primefaces.extensions.optimizerplugin.replacer.DataUriTokenResolver getDataUriTokenResolver();
    Code:
       0: aload_0
       1: getfield      #7                  // Field dataUriTokenResolver:Lorg/primefaces/extensions/optimizerplugin/replacer/DataUriTokenResolver;
       4: areturn
}
