Compiled from "DiffMatchPatch.java"
class name.fraser.neil.plaintext.DiffMatchPatch$1 {
  static final int[] $SwitchMap$name$fraser$neil$plaintext$DiffMatchPatch$Operation;

  static {};
    Code:
       0: invokestatic  #1                  // Method name/fraser/neil/plaintext/DiffMatchPatch$Operation.values:()[Lname/fraser/neil/plaintext/DiffMatchPatch$Operation;
       3: arraylength
       4: newarray       int
       6: putstatic     #2                  // Field $SwitchMap$name$fraser$neil$plaintext$DiffMatchPatch$Operation:[I
       9: getstatic     #2                  // Field $SwitchMap$name$fraser$neil$plaintext$DiffMatchPatch$Operation:[I
      12: getstatic     #3                  // Field name/fraser/neil/plaintext/DiffMatchPatch$Operation.INSERT:Lname/fraser/neil/plaintext/DiffMatchPatch$Operation;
      15: invokevirtual #4                  // Method name/fraser/neil/plaintext/DiffMatchPatch$Operation.ordinal:()I
      18: iconst_1
      19: iastore
      20: goto          24
      23: astore_0
      24: getstatic     #2                  // Field $SwitchMap$name$fraser$neil$plaintext$DiffMatchPatch$Operation:[I
      27: getstatic     #6                  // Field name/fraser/neil/plaintext/DiffMatchPatch$Operation.DELETE:Lname/fraser/neil/plaintext/DiffMatchPatch$Operation;
      30: invokevirtual #4                  // Method name/fraser/neil/plaintext/DiffMatchPatch$Operation.ordinal:()I
      33: iconst_2
      34: iastore
      35: goto          39
      38: astore_0
      39: getstatic     #2                  // Field $SwitchMap$name$fraser$neil$plaintext$DiffMatchPatch$Operation:[I
      42: getstatic     #7                  // Field name/fraser/neil/plaintext/DiffMatchPatch$Operation.EQUAL:Lname/fraser/neil/plaintext/DiffMatchPatch$Operation;
      45: invokevirtual #4                  // Method name/fraser/neil/plaintext/DiffMatchPatch$Operation.ordinal:()I
      48: iconst_3
      49: iastore
      50: goto          54
      53: astore_0
      54: return
    Exception table:
       from    to  target type
           9    20    23   Class java/lang/NoSuchFieldError
          24    35    38   Class java/lang/NoSuchFieldError
          39    50    53   Class java/lang/NoSuchFieldError
}
