Compiled from "AnyType.java"
public final class org.hibernate.type.AnyType$ObjectTypeCacheEntry implements java.io.Serializable {
  final java.lang.String entityName;

  final java.io.Serializable id;

  org.hibernate.type.AnyType$ObjectTypeCacheEntry(java.lang.String, java.io.Serializable);
    Code:
       0: aload_0
       1: invokespecial #1                  // Method java/lang/Object."<init>":()V
       4: aload_0
       5: aload_1
       6: putfield      #2                  // Field entityName:Ljava/lang/String;
       9: aload_0
      10: aload_2
      11: putfield      #3                  // Field id:Ljava/io/Serializable;
      14: return
}
