Compiled from "MapType.java"
public class org.hibernate.type.MapType extends org.hibernate.type.CollectionType {
  public org.hibernate.type.MapType(org.hibernate.type.TypeFactory$TypeScope, java.lang.String, java.lang.String);
    Code:
       0: aload_0
       1: aload_1
       2: aload_2
       3: aload_3
       4: invokespecial #1                  // Method org/hibernate/type/CollectionType."<init>":(Lorg/hibernate/type/TypeFactory$TypeScope;Ljava/lang/String;Ljava/lang/String;)V
       7: return

  public org.hibernate.collection.spi.PersistentCollection instantiate(org.hibernate.engine.spi.SharedSessionContractImplementor, org.hibernate.persister.collection.CollectionPersister, java.io.Serializable);
    Code:
       0: new           #2                  // class org/hibernate/collection/internal/PersistentMap
       3: dup
       4: aload_1
       5: invokespecial #3                  // Method org/hibernate/collection/internal/PersistentMap."<init>":(Lorg/hibernate/engine/spi/SharedSessionContractImplementor;)V
       8: areturn

  public java.lang.Class getReturnedClass();
    Code:
       0: ldc           #4                  // class java/util/Map
       2: areturn

  public java.util.Iterator getElementsIterator(java.lang.Object);
    Code:
       0: aload_1
       1: checkcast     #4                  // class java/util/Map
       4: invokeinterface #5,  1            // InterfaceMethod java/util/Map.values:()Ljava/util/Collection;
       9: invokeinterface #6,  1            // InterfaceMethod java/util/Collection.iterator:()Ljava/util/Iterator;
      14: areturn

  public org.hibernate.collection.spi.PersistentCollection wrap(org.hibernate.engine.spi.SharedSessionContractImplementor, java.lang.Object);
    Code:
       0: new           #2                  // class org/hibernate/collection/internal/PersistentMap
       3: dup
       4: aload_1
       5: aload_2
       6: checkcast     #4                  // class java/util/Map
       9: invokespecial #7                  // Method org/hibernate/collection/internal/PersistentMap."<init>":(Lorg/hibernate/engine/spi/SharedSessionContractImplementor;Ljava/util/Map;)V
      12: areturn

  public java.lang.Object instantiate(int);
    Code:
       0: iload_1
       1: ifgt          14
       4: new           #8                  // class java/util/HashMap
       7: dup
       8: invokespecial #9                  // Method java/util/HashMap."<init>":()V
      11: goto          31
      14: new           #8                  // class java/util/HashMap
      17: dup
      18: iload_1
      19: iload_1
      20: i2f
      21: ldc           #10                 // float 0.75f
      23: fmul
      24: f2i
      25: iadd
      26: ldc           #10                 // float 0.75f
      28: invokespecial #11                 // Method java/util/HashMap."<init>":(IF)V
      31: areturn

  public java.lang.Object replaceElements(java.lang.Object, java.lang.Object, java.lang.Object, java.util.Map, org.hibernate.engine.spi.SharedSessionContractImplementor) throws org.hibernate.HibernateException;
    Code:
       0: aload         5
       2: invokeinterface #12,  1           // InterfaceMethod org/hibernate/engine/spi/SharedSessionContractImplementor.getFactory:()Lorg/hibernate/engine/spi/SessionFactoryImplementor;
       7: invokeinterface #13,  1           // InterfaceMethod org/hibernate/engine/spi/SessionFactoryImplementor.getMetamodel:()Lorg/hibernate/metamodel/spi/MetamodelImplementor;
      12: aload_0
      13: invokevirtual #14                 // Method getRole:()Ljava/lang/String;
      16: invokeinterface #15,  2           // InterfaceMethod org/hibernate/metamodel/spi/MetamodelImplementor.collectionPersister:(Ljava/lang/String;)Lorg/hibernate/persister/collection/CollectionPersister;
      21: astore        6
      23: aload_2
      24: checkcast     #4                  // class java/util/Map
      27: astore        7
      29: aload         7
      31: invokeinterface #16,  1           // InterfaceMethod java/util/Map.clear:()V
      36: aload_1
      37: checkcast     #4                  // class java/util/Map
      40: invokeinterface #17,  1           // InterfaceMethod java/util/Map.entrySet:()Ljava/util/Set;
      45: invokeinterface #18,  1           // InterfaceMethod java/util/Set.iterator:()Ljava/util/Iterator;
      50: astore        8
      52: aload         8
      54: invokeinterface #19,  1           // InterfaceMethod java/util/Iterator.hasNext:()Z
      59: ifeq          147
      62: aload         8
      64: invokeinterface #20,  1           // InterfaceMethod java/util/Iterator.next:()Ljava/lang/Object;
      69: astore        9
      71: aload         9
      73: checkcast     #21                 // class java/util/Map$Entry
      76: astore        10
      78: aload         6
      80: invokeinterface #22,  1           // InterfaceMethod org/hibernate/persister/collection/CollectionPersister.getIndexType:()Lorg/hibernate/type/Type;
      85: aload         10
      87: invokeinterface #23,  1           // InterfaceMethod java/util/Map$Entry.getKey:()Ljava/lang/Object;
      92: aconst_null
      93: aload         5
      95: aload_3
      96: aload         4
      98: invokeinterface #24,  6           // InterfaceMethod org/hibernate/type/Type.replace:(Ljava/lang/Object;Ljava/lang/Object;Lorg/hibernate/engine/spi/SharedSessionContractImplementor;Ljava/lang/Object;Ljava/util/Map;)Ljava/lang/Object;
     103: astore        11
     105: aload         6
     107: invokeinterface #25,  1           // InterfaceMethod org/hibernate/persister/collection/CollectionPersister.getElementType:()Lorg/hibernate/type/Type;
     112: aload         10
     114: invokeinterface #26,  1           // InterfaceMethod java/util/Map$Entry.getValue:()Ljava/lang/Object;
     119: aconst_null
     120: aload         5
     122: aload_3
     123: aload         4
     125: invokeinterface #24,  6           // InterfaceMethod org/hibernate/type/Type.replace:(Ljava/lang/Object;Ljava/lang/Object;Lorg/hibernate/engine/spi/SharedSessionContractImplementor;Ljava/lang/Object;Ljava/util/Map;)Ljava/lang/Object;
     130: astore        12
     132: aload         7
     134: aload         11
     136: aload         12
     138: invokeinterface #27,  3           // InterfaceMethod java/util/Map.put:(Ljava/lang/Object;Ljava/lang/Object;)Ljava/lang/Object;
     143: pop
     144: goto          52
     147: aload         7
     149: areturn

  public java.lang.Object indexOf(java.lang.Object, java.lang.Object);
    Code:
       0: aload_1
       1: checkcast     #4                  // class java/util/Map
       4: invokeinterface #17,  1           // InterfaceMethod java/util/Map.entrySet:()Ljava/util/Set;
       9: invokeinterface #18,  1           // InterfaceMethod java/util/Set.iterator:()Ljava/util/Iterator;
      14: astore_3
      15: aload_3
      16: invokeinterface #19,  1           // InterfaceMethod java/util/Iterator.hasNext:()Z
      21: ifeq          61
      24: aload_3
      25: invokeinterface #20,  1           // InterfaceMethod java/util/Iterator.next:()Ljava/lang/Object;
      30: astore        4
      32: aload         4
      34: checkcast     #21                 // class java/util/Map$Entry
      37: astore        5
      39: aload         5
      41: invokeinterface #26,  1           // InterfaceMethod java/util/Map$Entry.getValue:()Ljava/lang/Object;
      46: aload_2
      47: if_acmpne     58
      50: aload         5
      52: invokeinterface #23,  1           // InterfaceMethod java/util/Map$Entry.getKey:()Ljava/lang/Object;
      57: areturn
      58: goto          15
      61: aconst_null
      62: areturn
}
