Compiled from "KerberosContext.java"
public class org.apache.wss4j.common.kerberos.KerberosContext {
  private static final org.slf4j.Logger LOG;

  private boolean disposed;

  private org.ietf.jgss.GSSContext gssContext;

  private byte[] kerberosToken;

  private java.security.Key secretKey;

  public org.apache.wss4j.common.kerberos.KerberosContext();
    Code:
       0: aload_0
       1: invokespecial #1                  // Method java/lang/Object."<init>":()V
       4: return

  public byte[] getKerberosToken();
    Code:
       0: aload_0
       1: getfield      #2                  // Field disposed:Z
       4: ifeq          17
       7: new           #3                  // class java/lang/IllegalStateException
      10: dup
      11: ldc           #4                  // String Kerberos context is disposed.
      13: invokespecial #5                  // Method java/lang/IllegalStateException."<init>":(Ljava/lang/String;)V
      16: athrow
      17: aload_0
      18: getfield      #6                  // Field kerberosToken:[B
      21: areturn

  public void setKerberosToken(byte[]);
    Code:
       0: aload_0
       1: aload_1
       2: putfield      #6                  // Field kerberosToken:[B
       5: return

  public java.security.Key getSecretKey();
    Code:
       0: aload_0
       1: getfield      #2                  // Field disposed:Z
       4: ifeq          17
       7: new           #3                  // class java/lang/IllegalStateException
      10: dup
      11: ldc           #4                  // String Kerberos context is disposed.
      13: invokespecial #5                  // Method java/lang/IllegalStateException."<init>":(Ljava/lang/String;)V
      16: athrow
      17: aload_0
      18: getfield      #7                  // Field secretKey:Ljava/security/Key;
      21: areturn

  public void setSecretKey(java.security.Key);
    Code:
       0: aload_0
       1: aload_1
       2: putfield      #7                  // Field secretKey:Ljava/security/Key;
       5: return

  public org.ietf.jgss.GSSContext getGssContext();
    Code:
       0: aload_0
       1: getfield      #2                  // Field disposed:Z
       4: ifeq          17
       7: new           #3                  // class java/lang/IllegalStateException
      10: dup
      11: ldc           #4                  // String Kerberos context is disposed.
      13: invokespecial #5                  // Method java/lang/IllegalStateException."<init>":(Ljava/lang/String;)V
      16: athrow
      17: aload_0
      18: getfield      #8                  // Field gssContext:Lorg/ietf/jgss/GSSContext;
      21: areturn

  public void setGssContext(org.ietf.jgss.GSSContext);
    Code:
       0: aload_0
       1: aload_1
       2: putfield      #8                  // Field gssContext:Lorg/ietf/jgss/GSSContext;
       5: return

  public void dispose();
    Code:
       0: aload_0
       1: getfield      #2                  // Field disposed:Z
       4: ifne          79
       7: aload_0
       8: getfield      #6                  // Field kerberosToken:[B
      11: ifnull        38
      14: iconst_0
      15: istore_1
      16: iload_1
      17: aload_0
      18: getfield      #6                  // Field kerberosToken:[B
      21: arraylength
      22: if_icmpge     38
      25: aload_0
      26: getfield      #6                  // Field kerberosToken:[B
      29: iload_1
      30: iconst_0
      31: bastore
      32: iinc          1, 1
      35: goto          16
      38: aload_0
      39: aconst_null
      40: putfield      #7                  // Field secretKey:Ljava/security/Key;
      43: aload_0
      44: getfield      #8                  // Field gssContext:Lorg/ietf/jgss/GSSContext;
      47: ifnull        74
      50: aload_0
      51: getfield      #8                  // Field gssContext:Lorg/ietf/jgss/GSSContext;
      54: invokeinterface #9,  1            // InterfaceMethod org/ietf/jgss/GSSContext.dispose:()V
      59: goto          74
      62: astore_1
      63: getstatic     #11                 // Field LOG:Lorg/slf4j/Logger;
      66: ldc           #12                 // String Error disposing of the GSSContext
      68: aload_1
      69: invokeinterface #13,  3           // InterfaceMethod org/slf4j/Logger.error:(Ljava/lang/String;Ljava/lang/Throwable;)V
      74: aload_0
      75: iconst_1
      76: putfield      #2                  // Field disposed:Z
      79: return
    Exception table:
       from    to  target type
          50    59    62   Class org/ietf/jgss/GSSException

  public boolean isDisposed();
    Code:
       0: aload_0
       1: getfield      #2                  // Field disposed:Z
       4: ireturn

  static {};
    Code:
       0: ldc_w         #14                 // class org/apache/wss4j/common/kerberos/KerberosContext
       3: invokestatic  #15                 // Method org/slf4j/LoggerFactory.getLogger:(Ljava/lang/Class;)Lorg/slf4j/Logger;
       6: putstatic     #11                 // Field LOG:Lorg/slf4j/Logger;
       9: return
}
