Compiled from "EndpointCache.java"
class org.jboss.naming.remote.client.EndpointCache$EndpointWrapper implements org.jboss.remoting3.Endpoint {
  private final org.jboss.naming.remote.client.EndpointCache$CacheKey endpointHash;

  private final org.jboss.remoting3.Endpoint endpoint;

  final org.jboss.naming.remote.client.EndpointCache this$0;

  private org.jboss.naming.remote.client.EndpointCache$EndpointWrapper(org.jboss.naming.remote.client.EndpointCache, org.jboss.naming.remote.client.EndpointCache$CacheKey, org.jboss.remoting3.Endpoint);
    Code:
       0: aload_0
       1: aload_1
       2: putfield      #2                  // Field this$0:Lorg/jboss/naming/remote/client/EndpointCache;
       5: aload_0
       6: invokespecial #3                  // Method java/lang/Object."<init>":()V
       9: aload_0
      10: aload_2
      11: putfield      #4                  // Field endpointHash:Lorg/jboss/naming/remote/client/EndpointCache$CacheKey;
      14: aload_0
      15: aload_3
      16: putfield      #5                  // Field endpoint:Lorg/jboss/remoting3/Endpoint;
      19: return

  public java.lang.String getName();
    Code:
       0: aload_0
       1: getfield      #5                  // Field endpoint:Lorg/jboss/remoting3/Endpoint;
       4: invokeinterface #6,  1            // InterfaceMethod org/jboss/remoting3/Endpoint.getName:()Ljava/lang/String;
       9: areturn

  public org.jboss.remoting3.Registration registerService(java.lang.String, org.jboss.remoting3.OpenListener, org.xnio.OptionMap) throws org.jboss.remoting3.ServiceRegistrationException;
    Code:
       0: aload_0
       1: getfield      #5                  // Field endpoint:Lorg/jboss/remoting3/Endpoint;
       4: aload_1
       5: aload_2
       6: aload_3
       7: invokeinterface #7,  4            // InterfaceMethod org/jboss/remoting3/Endpoint.registerService:(Ljava/lang/String;Lorg/jboss/remoting3/OpenListener;Lorg/xnio/OptionMap;)Lorg/jboss/remoting3/Registration;
      12: areturn

  public org.xnio.IoFuture<org.jboss.remoting3.Connection> connect(java.net.URI) throws java.io.IOException;
    Code:
       0: aload_0
       1: getfield      #5                  // Field endpoint:Lorg/jboss/remoting3/Endpoint;
       4: aload_1
       5: invokeinterface #8,  2            // InterfaceMethod org/jboss/remoting3/Endpoint.connect:(Ljava/net/URI;)Lorg/xnio/IoFuture;
      10: areturn

  public org.xnio.IoFuture<org.jboss.remoting3.Connection> connect(java.net.URI, org.xnio.OptionMap) throws java.io.IOException;
    Code:
       0: aload_0
       1: getfield      #5                  // Field endpoint:Lorg/jboss/remoting3/Endpoint;
       4: aload_1
       5: aload_2
       6: invokeinterface #9,  3            // InterfaceMethod org/jboss/remoting3/Endpoint.connect:(Ljava/net/URI;Lorg/xnio/OptionMap;)Lorg/xnio/IoFuture;
      11: areturn

  public org.xnio.IoFuture<org.jboss.remoting3.Connection> connect(java.net.URI, org.xnio.OptionMap, javax.security.auth.callback.CallbackHandler) throws java.io.IOException;
    Code:
       0: aload_0
       1: getfield      #5                  // Field endpoint:Lorg/jboss/remoting3/Endpoint;
       4: aload_1
       5: aload_2
       6: aload_3
       7: invokeinterface #10,  4           // InterfaceMethod org/jboss/remoting3/Endpoint.connect:(Ljava/net/URI;Lorg/xnio/OptionMap;Ljavax/security/auth/callback/CallbackHandler;)Lorg/xnio/IoFuture;
      12: areturn

  public org.xnio.IoFuture<org.jboss.remoting3.Connection> connect(java.net.URI, org.xnio.OptionMap, javax.security.auth.callback.CallbackHandler, javax.net.ssl.SSLContext) throws java.io.IOException;
    Code:
       0: aload_0
       1: getfield      #5                  // Field endpoint:Lorg/jboss/remoting3/Endpoint;
       4: aload_1
       5: aload_2
       6: aload_3
       7: aload         4
       9: invokeinterface #11,  5           // InterfaceMethod org/jboss/remoting3/Endpoint.connect:(Ljava/net/URI;Lorg/xnio/OptionMap;Ljavax/security/auth/callback/CallbackHandler;Ljavax/net/ssl/SSLContext;)Lorg/xnio/IoFuture;
      14: areturn

  public org.xnio.IoFuture<org.jboss.remoting3.Connection> connect(java.net.URI, org.xnio.OptionMap, javax.security.auth.callback.CallbackHandler, org.xnio.ssl.XnioSsl) throws java.io.IOException;
    Code:
       0: aload_0
       1: getfield      #5                  // Field endpoint:Lorg/jboss/remoting3/Endpoint;
       4: aload_1
       5: aload_2
       6: aload_3
       7: aload         4
       9: invokeinterface #12,  5           // InterfaceMethod org/jboss/remoting3/Endpoint.connect:(Ljava/net/URI;Lorg/xnio/OptionMap;Ljavax/security/auth/callback/CallbackHandler;Lorg/xnio/ssl/XnioSsl;)Lorg/xnio/IoFuture;
      14: areturn

  public org.xnio.IoFuture<org.jboss.remoting3.Connection> connect(java.net.URI, org.xnio.OptionMap, java.lang.String, java.lang.String, char[]) throws java.io.IOException;
    Code:
       0: aload_0
       1: getfield      #5                  // Field endpoint:Lorg/jboss/remoting3/Endpoint;
       4: aload_1
       5: aload_2
       6: aload_3
       7: aload         4
       9: aload         5
      11: invokeinterface #13,  6           // InterfaceMethod org/jboss/remoting3/Endpoint.connect:(Ljava/net/URI;Lorg/xnio/OptionMap;Ljava/lang/String;Ljava/lang/String;[C)Lorg/xnio/IoFuture;
      16: areturn

  public org.xnio.IoFuture<org.jboss.remoting3.Connection> connect(java.net.URI, org.xnio.OptionMap, java.lang.String, java.lang.String, char[], javax.net.ssl.SSLContext) throws java.io.IOException;
    Code:
       0: aload_0
       1: getfield      #5                  // Field endpoint:Lorg/jboss/remoting3/Endpoint;
       4: aload_1
       5: aload_2
       6: aload_3
       7: aload         4
       9: aload         5
      11: aload         6
      13: invokeinterface #14,  7           // InterfaceMethod org/jboss/remoting3/Endpoint.connect:(Ljava/net/URI;Lorg/xnio/OptionMap;Ljava/lang/String;Ljava/lang/String;[CLjavax/net/ssl/SSLContext;)Lorg/xnio/IoFuture;
      18: areturn

  public org.xnio.IoFuture<org.jboss.remoting3.Connection> connect(java.net.URI, org.xnio.OptionMap, java.lang.String, java.lang.String, char[], org.xnio.ssl.XnioSsl) throws java.io.IOException;
    Code:
       0: aload_0
       1: getfield      #5                  // Field endpoint:Lorg/jboss/remoting3/Endpoint;
       4: aload_1
       5: aload_2
       6: aload_3
       7: aload         4
       9: aload         5
      11: aload         6
      13: invokeinterface #15,  7           // InterfaceMethod org/jboss/remoting3/Endpoint.connect:(Ljava/net/URI;Lorg/xnio/OptionMap;Ljava/lang/String;Ljava/lang/String;[CLorg/xnio/ssl/XnioSsl;)Lorg/xnio/IoFuture;
      18: areturn

  public org.xnio.IoFuture<org.jboss.remoting3.Connection> connect(java.lang.String, java.net.SocketAddress, java.net.SocketAddress) throws java.io.IOException;
    Code:
       0: aload_0
       1: getfield      #5                  // Field endpoint:Lorg/jboss/remoting3/Endpoint;
       4: aload_1
       5: aload_2
       6: aload_3
       7: invokeinterface #16,  4           // InterfaceMethod org/jboss/remoting3/Endpoint.connect:(Ljava/lang/String;Ljava/net/SocketAddress;Ljava/net/SocketAddress;)Lorg/xnio/IoFuture;
      12: areturn

  public org.xnio.IoFuture<org.jboss.remoting3.Connection> connect(java.lang.String, java.net.SocketAddress, java.net.SocketAddress, org.xnio.OptionMap) throws java.io.IOException;
    Code:
       0: aload_0
       1: getfield      #5                  // Field endpoint:Lorg/jboss/remoting3/Endpoint;
       4: aload_1
       5: aload_2
       6: aload_3
       7: aload         4
       9: invokeinterface #17,  5           // InterfaceMethod org/jboss/remoting3/Endpoint.connect:(Ljava/lang/String;Ljava/net/SocketAddress;Ljava/net/SocketAddress;Lorg/xnio/OptionMap;)Lorg/xnio/IoFuture;
      14: areturn

  public org.xnio.IoFuture<org.jboss.remoting3.Connection> connect(java.lang.String, java.net.SocketAddress, java.net.SocketAddress, org.xnio.OptionMap, javax.security.auth.callback.CallbackHandler) throws java.io.IOException;
    Code:
       0: aload_0
       1: getfield      #5                  // Field endpoint:Lorg/jboss/remoting3/Endpoint;
       4: aload_1
       5: aload_2
       6: aload_3
       7: aload         4
       9: aload         5
      11: invokeinterface #18,  6           // InterfaceMethod org/jboss/remoting3/Endpoint.connect:(Ljava/lang/String;Ljava/net/SocketAddress;Ljava/net/SocketAddress;Lorg/xnio/OptionMap;Ljavax/security/auth/callback/CallbackHandler;)Lorg/xnio/IoFuture;
      16: areturn

  public org.xnio.IoFuture<org.jboss.remoting3.Connection> connect(java.lang.String, java.net.SocketAddress, java.net.SocketAddress, org.xnio.OptionMap, javax.security.auth.callback.CallbackHandler, javax.net.ssl.SSLContext) throws java.io.IOException;
    Code:
       0: aload_0
       1: getfield      #5                  // Field endpoint:Lorg/jboss/remoting3/Endpoint;
       4: aload_1
       5: aload_2
       6: aload_3
       7: aload         4
       9: aload         5
      11: aload         6
      13: invokeinterface #19,  7           // InterfaceMethod org/jboss/remoting3/Endpoint.connect:(Ljava/lang/String;Ljava/net/SocketAddress;Ljava/net/SocketAddress;Lorg/xnio/OptionMap;Ljavax/security/auth/callback/CallbackHandler;Ljavax/net/ssl/SSLContext;)Lorg/xnio/IoFuture;
      18: areturn

  public org.xnio.IoFuture<org.jboss.remoting3.Connection> connect(java.lang.String, java.net.SocketAddress, java.net.SocketAddress, org.xnio.OptionMap, javax.security.auth.callback.CallbackHandler, org.xnio.ssl.XnioSsl) throws java.io.IOException;
    Code:
       0: aload_0
       1: getfield      #5                  // Field endpoint:Lorg/jboss/remoting3/Endpoint;
       4: aload_1
       5: aload_2
       6: aload_3
       7: aload         4
       9: aload         5
      11: aload         6
      13: invokeinterface #20,  7           // InterfaceMethod org/jboss/remoting3/Endpoint.connect:(Ljava/lang/String;Ljava/net/SocketAddress;Ljava/net/SocketAddress;Lorg/xnio/OptionMap;Ljavax/security/auth/callback/CallbackHandler;Lorg/xnio/ssl/XnioSsl;)Lorg/xnio/IoFuture;
      18: areturn

  public org.xnio.IoFuture<org.jboss.remoting3.Connection> connect(java.lang.String, java.net.SocketAddress, java.net.SocketAddress, org.xnio.OptionMap, java.lang.String, java.lang.String, char[]) throws java.io.IOException;
    Code:
       0: aload_0
       1: getfield      #5                  // Field endpoint:Lorg/jboss/remoting3/Endpoint;
       4: aload_1
       5: aload_2
       6: aload_3
       7: aload         4
       9: aload         5
      11: aload         6
      13: aload         7
      15: invokeinterface #21,  8           // InterfaceMethod org/jboss/remoting3/Endpoint.connect:(Ljava/lang/String;Ljava/net/SocketAddress;Ljava/net/SocketAddress;Lorg/xnio/OptionMap;Ljava/lang/String;Ljava/lang/String;[C)Lorg/xnio/IoFuture;
      20: areturn

  public org.xnio.IoFuture<org.jboss.remoting3.Connection> connect(java.lang.String, java.net.SocketAddress, java.net.SocketAddress, org.xnio.OptionMap, java.lang.String, java.lang.String, char[], javax.net.ssl.SSLContext) throws java.io.IOException;
    Code:
       0: aload_0
       1: getfield      #5                  // Field endpoint:Lorg/jboss/remoting3/Endpoint;
       4: aload_1
       5: aload_2
       6: aload_3
       7: aload         4
       9: aload         5
      11: aload         6
      13: aload         7
      15: aload         8
      17: invokeinterface #22,  9           // InterfaceMethod org/jboss/remoting3/Endpoint.connect:(Ljava/lang/String;Ljava/net/SocketAddress;Ljava/net/SocketAddress;Lorg/xnio/OptionMap;Ljava/lang/String;Ljava/lang/String;[CLjavax/net/ssl/SSLContext;)Lorg/xnio/IoFuture;
      22: areturn

  public org.xnio.IoFuture<org.jboss.remoting3.Connection> connect(java.lang.String, java.net.SocketAddress, java.net.SocketAddress, org.xnio.OptionMap, java.lang.String, java.lang.String, char[], org.xnio.ssl.XnioSsl) throws java.io.IOException;
    Code:
       0: aload_0
       1: getfield      #5                  // Field endpoint:Lorg/jboss/remoting3/Endpoint;
       4: aload_1
       5: aload_2
       6: aload_3
       7: aload         4
       9: aload         5
      11: aload         6
      13: aload         7
      15: aload         8
      17: invokeinterface #23,  9           // InterfaceMethod org/jboss/remoting3/Endpoint.connect:(Ljava/lang/String;Ljava/net/SocketAddress;Ljava/net/SocketAddress;Lorg/xnio/OptionMap;Ljava/lang/String;Ljava/lang/String;[CLorg/xnio/ssl/XnioSsl;)Lorg/xnio/IoFuture;
      22: areturn

  public org.jboss.remoting3.Registration addConnectionProvider(java.lang.String, org.jboss.remoting3.spi.ConnectionProviderFactory, org.xnio.OptionMap) throws org.jboss.remoting3.DuplicateRegistrationException, java.io.IOException;
    Code:
       0: aload_0
       1: getfield      #5                  // Field endpoint:Lorg/jboss/remoting3/Endpoint;
       4: aload_1
       5: aload_2
       6: aload_3
       7: invokeinterface #24,  4           // InterfaceMethod org/jboss/remoting3/Endpoint.addConnectionProvider:(Ljava/lang/String;Lorg/jboss/remoting3/spi/ConnectionProviderFactory;Lorg/xnio/OptionMap;)Lorg/jboss/remoting3/Registration;
      12: areturn

  public <T> T getConnectionProviderInterface(java.lang.String, java.lang.Class<T>) throws org.jboss.remoting3.UnknownURISchemeException, java.lang.ClassCastException;
    Code:
       0: aload_0
       1: getfield      #5                  // Field endpoint:Lorg/jboss/remoting3/Endpoint;
       4: aload_1
       5: aload_2
       6: invokeinterface #25,  3           // InterfaceMethod org/jboss/remoting3/Endpoint.getConnectionProviderInterface:(Ljava/lang/String;Ljava/lang/Class;)Ljava/lang/Object;
      11: areturn

  public boolean isValidUriScheme(java.lang.String);
    Code:
       0: aload_0
       1: getfield      #5                  // Field endpoint:Lorg/jboss/remoting3/Endpoint;
       4: aload_1
       5: invokeinterface #26,  2           // InterfaceMethod org/jboss/remoting3/Endpoint.isValidUriScheme:(Ljava/lang/String;)Z
      10: ireturn

  public org.xnio.XnioWorker getXnioWorker();
    Code:
       0: aload_0
       1: getfield      #5                  // Field endpoint:Lorg/jboss/remoting3/Endpoint;
       4: invokeinterface #27,  1           // InterfaceMethod org/jboss/remoting3/Endpoint.getXnioWorker:()Lorg/xnio/XnioWorker;
       9: areturn

  public void close() throws java.io.IOException;
    Code:
       0: aload_0
       1: getfield      #2                  // Field this$0:Lorg/jboss/naming/remote/client/EndpointCache;
       4: aload_0
       5: getfield      #4                  // Field endpointHash:Lorg/jboss/naming/remote/client/EndpointCache$CacheKey;
       8: iconst_0
       9: invokevirtual #28                 // Method org/jboss/naming/remote/client/EndpointCache.release:(Lorg/jboss/naming/remote/client/EndpointCache$CacheKey;Z)V
      12: return

  public void awaitClosed() throws java.lang.InterruptedException;
    Code:
       0: aload_0
       1: getfield      #5                  // Field endpoint:Lorg/jboss/remoting3/Endpoint;
       4: invokeinterface #29,  1           // InterfaceMethod org/jboss/remoting3/Endpoint.awaitClosed:()V
       9: return

  public void awaitClosedUninterruptibly();
    Code:
       0: aload_0
       1: getfield      #5                  // Field endpoint:Lorg/jboss/remoting3/Endpoint;
       4: invokeinterface #30,  1           // InterfaceMethod org/jboss/remoting3/Endpoint.awaitClosedUninterruptibly:()V
       9: return

  public void closeAsync();
    Code:
       0: aload_0
       1: getfield      #2                  // Field this$0:Lorg/jboss/naming/remote/client/EndpointCache;
       4: aload_0
       5: getfield      #4                  // Field endpointHash:Lorg/jboss/naming/remote/client/EndpointCache$CacheKey;
       8: iconst_1
       9: invokevirtual #28                 // Method org/jboss/naming/remote/client/EndpointCache.release:(Lorg/jboss/naming/remote/client/EndpointCache$CacheKey;Z)V
      12: return

  public org.jboss.remoting3.HandleableCloseable$Key addCloseHandler(org.jboss.remoting3.CloseHandler<? super org.jboss.remoting3.Endpoint>);
    Code:
       0: aload_0
       1: getfield      #5                  // Field endpoint:Lorg/jboss/remoting3/Endpoint;
       4: aload_1
       5: invokeinterface #31,  2           // InterfaceMethod org/jboss/remoting3/Endpoint.addCloseHandler:(Lorg/jboss/remoting3/CloseHandler;)Lorg/jboss/remoting3/HandleableCloseable$Key;
      10: areturn

  public org.jboss.remoting3.Attachments getAttachments();
    Code:
       0: aload_0
       1: getfield      #5                  // Field endpoint:Lorg/jboss/remoting3/Endpoint;
       4: invokeinterface #32,  1           // InterfaceMethod org/jboss/remoting3/Endpoint.getAttachments:()Lorg/jboss/remoting3/Attachments;
       9: areturn

  org.jboss.naming.remote.client.EndpointCache$EndpointWrapper(org.jboss.naming.remote.client.EndpointCache, org.jboss.naming.remote.client.EndpointCache$CacheKey, org.jboss.remoting3.Endpoint, org.jboss.naming.remote.client.EndpointCache$1);
    Code:
       0: aload_0
       1: aload_1
       2: aload_2
       3: aload_3
       4: invokespecial #1                  // Method "<init>":(Lorg/jboss/naming/remote/client/EndpointCache;Lorg/jboss/naming/remote/client/EndpointCache$CacheKey;Lorg/jboss/remoting3/Endpoint;)V
       7: return
}
