Compiled from "DefaultMetricCollectorFactory.java"
public class com.amazonaws.metrics.internal.cloudwatch.DefaultMetricCollectorFactory implements com.amazonaws.metrics.MetricCollector$Factory {
  public com.amazonaws.metrics.internal.cloudwatch.DefaultMetricCollectorFactory();
    Code:
       0: aload_0
       1: invokespecial #1                  // Method java/lang/Object."<init>":()V
       4: return

  public com.amazonaws.metrics.MetricCollector getInstance();
    Code:
       0: invokestatic  #2                  // Method com/amazonaws/metrics/AwsSdkMetrics.getCredentialProvider:()Lcom/amazonaws/auth/AWSCredentialsProvider;
       3: astore_1
       4: invokestatic  #3                  // Method com/amazonaws/metrics/AwsSdkMetrics.getRegion:()Lcom/amazonaws/regions/Regions;
       7: astore_2
       8: invokestatic  #4                  // Method com/amazonaws/metrics/AwsSdkMetrics.getMetricQueueSize:()Ljava/lang/Integer;
      11: astore_3
      12: invokestatic  #5                  // Method com/amazonaws/metrics/AwsSdkMetrics.getQueuePollTimeoutMilli:()Ljava/lang/Long;
      15: astore        4
      17: new           #6                  // class com/amazonaws/metrics/internal/cloudwatch/CloudWatchMetricConfig
      20: dup
      21: invokespecial #7                  // Method com/amazonaws/metrics/internal/cloudwatch/CloudWatchMetricConfig."<init>":()V
      24: astore        5
      26: new           #8                  // class com/amazonaws/ClientConfiguration
      29: dup
      30: invokespecial #9                  // Method com/amazonaws/ClientConfiguration."<init>":()V
      33: astore        6
      35: aload_1
      36: ifnull        45
      39: aload         5
      41: aload_1
      42: invokevirtual #10                 // Method com/amazonaws/metrics/internal/cloudwatch/CloudWatchMetricConfig.setCredentialsProvider:(Lcom/amazonaws/auth/AWSCredentialsProvider;)V
      45: aload_2
      46: ifnull        85
      49: new           #11                 // class java/lang/StringBuilder
      52: dup
      53: invokespecial #12                 // Method java/lang/StringBuilder."<init>":()V
      56: ldc           #13                 // String monitoring.
      58: invokevirtual #14                 // Method java/lang/StringBuilder.append:(Ljava/lang/String;)Ljava/lang/StringBuilder;
      61: aload_2
      62: invokevirtual #15                 // Method com/amazonaws/regions/Regions.getName:()Ljava/lang/String;
      65: invokevirtual #14                 // Method java/lang/StringBuilder.append:(Ljava/lang/String;)Ljava/lang/StringBuilder;
      68: ldc           #16                 // String .amazonaws.com
      70: invokevirtual #14                 // Method java/lang/StringBuilder.append:(Ljava/lang/String;)Ljava/lang/StringBuilder;
      73: invokevirtual #17                 // Method java/lang/StringBuilder.toString:()Ljava/lang/String;
      76: astore        7
      78: aload         5
      80: aload         7
      82: invokevirtual #18                 // Method com/amazonaws/metrics/internal/cloudwatch/CloudWatchMetricConfig.setCloudWatchEndPoint:(Ljava/lang/String;)V
      85: aload_3
      86: ifnull        98
      89: aload         5
      91: aload_3
      92: invokevirtual #19                 // Method java/lang/Integer.intValue:()I
      95: invokevirtual #20                 // Method com/amazonaws/metrics/internal/cloudwatch/CloudWatchMetricConfig.setMetricQueueSize:(I)V
      98: aload         4
     100: ifnull        113
     103: aload         5
     105: aload         4
     107: invokevirtual #21                 // Method java/lang/Long.longValue:()J
     110: invokevirtual #22                 // Method com/amazonaws/metrics/internal/cloudwatch/CloudWatchMetricConfig.setQueuePollTimeoutMilli:(J)V
     113: aload         5
     115: aload         6
     117: invokevirtual #23                 // Method com/amazonaws/metrics/internal/cloudwatch/CloudWatchMetricConfig.setClientConfiguration:(Lcom/amazonaws/ClientConfiguration;)V
     120: aload         5
     122: invokestatic  #24                 // Method com/amazonaws/metrics/internal/cloudwatch/MetricCollectorSupport.startSingleton:(Lcom/amazonaws/metrics/internal/cloudwatch/CloudWatchMetricConfig;)Z
     125: pop
     126: invokestatic  #25                 // Method com/amazonaws/metrics/internal/cloudwatch/MetricCollectorSupport.getInstance:()Lcom/amazonaws/metrics/internal/cloudwatch/MetricCollectorSupport;
     129: areturn
}
