Compiled from "DescribeMLModelsPublisher.java"
class software.amazon.awssdk.services.machinelearning.paginators.DescribeMLModelsPublisher$DescribeMlModelsResponseFetcher implements software.amazon.awssdk.core.pagination.async.AsyncPageFetcher<software.amazon.awssdk.services.machinelearning.model.DescribeMlModelsResponse> {
  final software.amazon.awssdk.services.machinelearning.paginators.DescribeMLModelsPublisher this$0;

  private software.amazon.awssdk.services.machinelearning.paginators.DescribeMLModelsPublisher$DescribeMlModelsResponseFetcher(software.amazon.awssdk.services.machinelearning.paginators.DescribeMLModelsPublisher);
    Code:
       0: aload_0
       1: aload_1
       2: putfield      #2                  // Field this$0:Lsoftware/amazon/awssdk/services/machinelearning/paginators/DescribeMLModelsPublisher;
       5: aload_0
       6: invokespecial #3                  // Method java/lang/Object."<init>":()V
       9: return

  public boolean hasNextPage(software.amazon.awssdk.services.machinelearning.model.DescribeMlModelsResponse);
    Code:
       0: aload_1
       1: invokevirtual #4                  // Method software/amazon/awssdk/services/machinelearning/model/DescribeMlModelsResponse.nextToken:()Ljava/lang/String;
       4: invokestatic  #5                  // Method software/amazon/awssdk/core/util/PaginatorUtils.isOutputTokenAvailable:(Ljava/lang/Object;)Z
       7: ireturn

  public java.util.concurrent.CompletableFuture<software.amazon.awssdk.services.machinelearning.model.DescribeMlModelsResponse> nextPage(software.amazon.awssdk.services.machinelearning.model.DescribeMlModelsResponse);
    Code:
       0: aload_1
       1: ifnonnull     24
       4: aload_0
       5: getfield      #2                  // Field this$0:Lsoftware/amazon/awssdk/services/machinelearning/paginators/DescribeMLModelsPublisher;
       8: invokestatic  #6                  // Method software/amazon/awssdk/services/machinelearning/paginators/DescribeMLModelsPublisher.access$200:(Lsoftware/amazon/awssdk/services/machinelearning/paginators/DescribeMLModelsPublisher;)Lsoftware/amazon/awssdk/services/machinelearning/MachineLearningAsyncClient;
      11: aload_0
      12: getfield      #2                  // Field this$0:Lsoftware/amazon/awssdk/services/machinelearning/paginators/DescribeMLModelsPublisher;
      15: invokestatic  #7                  // Method software/amazon/awssdk/services/machinelearning/paginators/DescribeMLModelsPublisher.access$100:(Lsoftware/amazon/awssdk/services/machinelearning/paginators/DescribeMLModelsPublisher;)Lsoftware/amazon/awssdk/services/machinelearning/model/DescribeMlModelsRequest;
      18: invokeinterface #8,  2            // InterfaceMethod software/amazon/awssdk/services/machinelearning/MachineLearningAsyncClient.describeMLModels:(Lsoftware/amazon/awssdk/services/machinelearning/model/DescribeMlModelsRequest;)Ljava/util/concurrent/CompletableFuture;
      23: areturn
      24: aload_0
      25: getfield      #2                  // Field this$0:Lsoftware/amazon/awssdk/services/machinelearning/paginators/DescribeMLModelsPublisher;
      28: invokestatic  #6                  // Method software/amazon/awssdk/services/machinelearning/paginators/DescribeMLModelsPublisher.access$200:(Lsoftware/amazon/awssdk/services/machinelearning/paginators/DescribeMLModelsPublisher;)Lsoftware/amazon/awssdk/services/machinelearning/MachineLearningAsyncClient;
      31: aload_0
      32: getfield      #2                  // Field this$0:Lsoftware/amazon/awssdk/services/machinelearning/paginators/DescribeMLModelsPublisher;
      35: invokestatic  #7                  // Method software/amazon/awssdk/services/machinelearning/paginators/DescribeMLModelsPublisher.access$100:(Lsoftware/amazon/awssdk/services/machinelearning/paginators/DescribeMLModelsPublisher;)Lsoftware/amazon/awssdk/services/machinelearning/model/DescribeMlModelsRequest;
      38: invokevirtual #9                  // Method software/amazon/awssdk/services/machinelearning/model/DescribeMlModelsRequest.toBuilder:()Lsoftware/amazon/awssdk/services/machinelearning/model/DescribeMlModelsRequest$Builder;
      41: aload_1
      42: invokevirtual #4                  // Method software/amazon/awssdk/services/machinelearning/model/DescribeMlModelsResponse.nextToken:()Ljava/lang/String;
      45: invokeinterface #10,  2           // InterfaceMethod software/amazon/awssdk/services/machinelearning/model/DescribeMlModelsRequest$Builder.nextToken:(Ljava/lang/String;)Lsoftware/amazon/awssdk/services/machinelearning/model/DescribeMlModelsRequest$Builder;
      50: invokeinterface #11,  1           // InterfaceMethod software/amazon/awssdk/services/machinelearning/model/DescribeMlModelsRequest$Builder.build:()Ljava/lang/Object;
      55: checkcast     #12                 // class software/amazon/awssdk/services/machinelearning/model/DescribeMlModelsRequest
      58: invokeinterface #8,  2            // InterfaceMethod software/amazon/awssdk/services/machinelearning/MachineLearningAsyncClient.describeMLModels:(Lsoftware/amazon/awssdk/services/machinelearning/model/DescribeMlModelsRequest;)Ljava/util/concurrent/CompletableFuture;
      63: areturn

  public java.util.concurrent.CompletableFuture nextPage(java.lang.Object);
    Code:
       0: aload_0
       1: aload_1
       2: checkcast     #13                 // class software/amazon/awssdk/services/machinelearning/model/DescribeMlModelsResponse
       5: invokevirtual #14                 // Method nextPage:(Lsoftware/amazon/awssdk/services/machinelearning/model/DescribeMlModelsResponse;)Ljava/util/concurrent/CompletableFuture;
       8: areturn

  public boolean hasNextPage(java.lang.Object);
    Code:
       0: aload_0
       1: aload_1
       2: checkcast     #13                 // class software/amazon/awssdk/services/machinelearning/model/DescribeMlModelsResponse
       5: invokevirtual #15                 // Method hasNextPage:(Lsoftware/amazon/awssdk/services/machinelearning/model/DescribeMlModelsResponse;)Z
       8: ireturn

  software.amazon.awssdk.services.machinelearning.paginators.DescribeMLModelsPublisher$DescribeMlModelsResponseFetcher(software.amazon.awssdk.services.machinelearning.paginators.DescribeMLModelsPublisher, software.amazon.awssdk.services.machinelearning.paginators.DescribeMLModelsPublisher$1);
    Code:
       0: aload_0
       1: aload_1
       2: invokespecial #1                  // Method "<init>":(Lsoftware/amazon/awssdk/services/machinelearning/paginators/DescribeMLModelsPublisher;)V
       5: return
}
