Compiled from "ForecastqueryClient.java"
public interface software.amazon.awssdk.services.forecastquery.ForecastqueryClient extends software.amazon.awssdk.core.SdkClient {
  public static final java.lang.String SERVICE_NAME;

  public static final java.lang.String SERVICE_METADATA_ID;

  public static software.amazon.awssdk.services.forecastquery.ForecastqueryClient create();
    Code:
       0: invokestatic  #1                  // InterfaceMethod builder:()Lsoftware/amazon/awssdk/services/forecastquery/ForecastqueryClientBuilder;
       3: invokeinterface #2,  1            // InterfaceMethod software/amazon/awssdk/services/forecastquery/ForecastqueryClientBuilder.build:()Ljava/lang/Object;
       8: checkcast     #3                  // class software/amazon/awssdk/services/forecastquery/ForecastqueryClient
      11: areturn

  public static software.amazon.awssdk.services.forecastquery.ForecastqueryClientBuilder builder();
    Code:
       0: new           #4                  // class software/amazon/awssdk/services/forecastquery/DefaultForecastqueryClientBuilder
       3: dup
       4: invokespecial #5                  // Method software/amazon/awssdk/services/forecastquery/DefaultForecastqueryClientBuilder."<init>":()V
       7: areturn

  public default software.amazon.awssdk.services.forecastquery.model.QueryForecastResponse queryForecast(software.amazon.awssdk.services.forecastquery.model.QueryForecastRequest) throws software.amazon.awssdk.services.forecastquery.model.ResourceNotFoundException, software.amazon.awssdk.services.forecastquery.model.ResourceInUseException, software.amazon.awssdk.services.forecastquery.model.InvalidInputException, software.amazon.awssdk.services.forecastquery.model.LimitExceededException, software.amazon.awssdk.services.forecastquery.model.InvalidNextTokenException, software.amazon.awssdk.awscore.exception.AwsServiceException, software.amazon.awssdk.core.exception.SdkClientException, software.amazon.awssdk.services.forecastquery.model.ForecastqueryException;
    Code:
       0: new           #6                  // class java/lang/UnsupportedOperationException
       3: dup
       4: invokespecial #7                  // Method java/lang/UnsupportedOperationException."<init>":()V
       7: athrow

  public default software.amazon.awssdk.services.forecastquery.model.QueryForecastResponse queryForecast(java.util.function.Consumer<software.amazon.awssdk.services.forecastquery.model.QueryForecastRequest$Builder>) throws software.amazon.awssdk.services.forecastquery.model.ResourceNotFoundException, software.amazon.awssdk.services.forecastquery.model.ResourceInUseException, software.amazon.awssdk.services.forecastquery.model.InvalidInputException, software.amazon.awssdk.services.forecastquery.model.LimitExceededException, software.amazon.awssdk.services.forecastquery.model.InvalidNextTokenException, software.amazon.awssdk.awscore.exception.AwsServiceException, software.amazon.awssdk.core.exception.SdkClientException, software.amazon.awssdk.services.forecastquery.model.ForecastqueryException;
    Code:
       0: aload_0
       1: invokestatic  #8                  // Method software/amazon/awssdk/services/forecastquery/model/QueryForecastRequest.builder:()Lsoftware/amazon/awssdk/services/forecastquery/model/QueryForecastRequest$Builder;
       4: aload_1
       5: invokeinterface #9,  2            // InterfaceMethod software/amazon/awssdk/services/forecastquery/model/QueryForecastRequest$Builder.applyMutation:(Ljava/util/function/Consumer;)Lsoftware/amazon/awssdk/utils/builder/SdkBuilder;
      10: checkcast     #10                 // class software/amazon/awssdk/services/forecastquery/model/QueryForecastRequest$Builder
      13: invokeinterface #11,  1           // InterfaceMethod software/amazon/awssdk/services/forecastquery/model/QueryForecastRequest$Builder.build:()Ljava/lang/Object;
      18: checkcast     #12                 // class software/amazon/awssdk/services/forecastquery/model/QueryForecastRequest
      21: invokeinterface #13,  2           // InterfaceMethod queryForecast:(Lsoftware/amazon/awssdk/services/forecastquery/model/QueryForecastRequest;)Lsoftware/amazon/awssdk/services/forecastquery/model/QueryForecastResponse;
      26: areturn

  public default software.amazon.awssdk.services.forecastquery.model.QueryWhatIfForecastResponse queryWhatIfForecast(software.amazon.awssdk.services.forecastquery.model.QueryWhatIfForecastRequest) throws software.amazon.awssdk.services.forecastquery.model.ResourceNotFoundException, software.amazon.awssdk.services.forecastquery.model.ResourceInUseException, software.amazon.awssdk.services.forecastquery.model.InvalidInputException, software.amazon.awssdk.services.forecastquery.model.LimitExceededException, software.amazon.awssdk.services.forecastquery.model.InvalidNextTokenException, software.amazon.awssdk.awscore.exception.AwsServiceException, software.amazon.awssdk.core.exception.SdkClientException, software.amazon.awssdk.services.forecastquery.model.ForecastqueryException;
    Code:
       0: new           #6                  // class java/lang/UnsupportedOperationException
       3: dup
       4: invokespecial #7                  // Method java/lang/UnsupportedOperationException."<init>":()V
       7: athrow

  public default software.amazon.awssdk.services.forecastquery.model.QueryWhatIfForecastResponse queryWhatIfForecast(java.util.function.Consumer<software.amazon.awssdk.services.forecastquery.model.QueryWhatIfForecastRequest$Builder>) throws software.amazon.awssdk.services.forecastquery.model.ResourceNotFoundException, software.amazon.awssdk.services.forecastquery.model.ResourceInUseException, software.amazon.awssdk.services.forecastquery.model.InvalidInputException, software.amazon.awssdk.services.forecastquery.model.LimitExceededException, software.amazon.awssdk.services.forecastquery.model.InvalidNextTokenException, software.amazon.awssdk.awscore.exception.AwsServiceException, software.amazon.awssdk.core.exception.SdkClientException, software.amazon.awssdk.services.forecastquery.model.ForecastqueryException;
    Code:
       0: aload_0
       1: invokestatic  #14                 // Method software/amazon/awssdk/services/forecastquery/model/QueryWhatIfForecastRequest.builder:()Lsoftware/amazon/awssdk/services/forecastquery/model/QueryWhatIfForecastRequest$Builder;
       4: aload_1
       5: invokeinterface #15,  2           // InterfaceMethod software/amazon/awssdk/services/forecastquery/model/QueryWhatIfForecastRequest$Builder.applyMutation:(Ljava/util/function/Consumer;)Lsoftware/amazon/awssdk/utils/builder/SdkBuilder;
      10: checkcast     #16                 // class software/amazon/awssdk/services/forecastquery/model/QueryWhatIfForecastRequest$Builder
      13: invokeinterface #17,  1           // InterfaceMethod software/amazon/awssdk/services/forecastquery/model/QueryWhatIfForecastRequest$Builder.build:()Ljava/lang/Object;
      18: checkcast     #18                 // class software/amazon/awssdk/services/forecastquery/model/QueryWhatIfForecastRequest
      21: invokeinterface #19,  2           // InterfaceMethod queryWhatIfForecast:(Lsoftware/amazon/awssdk/services/forecastquery/model/QueryWhatIfForecastRequest;)Lsoftware/amazon/awssdk/services/forecastquery/model/QueryWhatIfForecastResponse;
      26: areturn

  public static software.amazon.awssdk.regions.ServiceMetadata serviceMetadata();
    Code:
       0: ldc           #20                 // String forecastquery
       2: invokestatic  #21                 // InterfaceMethod software/amazon/awssdk/regions/ServiceMetadata.of:(Ljava/lang/String;)Lsoftware/amazon/awssdk/regions/ServiceMetadata;
       5: areturn
}
