Compiled from "QuickAccessContents.java"
class org.eclipse.ui.internal.quickaccess.QuickAccessContents$2 extends org.eclipse.core.runtime.jobs.JobChangeAdapter {
  final org.eclipse.ui.internal.quickaccess.QuickAccessContents this$0;

  private final org.eclipse.ui.progress.UIJob val$computingFeedbackJob;

  private final org.eclipse.core.runtime.jobs.Job val$currentComputeEntriesJob;

  private final org.eclipse.swt.widgets.Display val$display;

  private final org.eclipse.ui.quickaccess.QuickAccessElement val$perfectMatch;

  private final java.util.concurrent.atomic.AtomicReference val$entries;

  private final java.lang.String val$filter;

  org.eclipse.ui.internal.quickaccess.QuickAccessContents$2(org.eclipse.ui.internal.quickaccess.QuickAccessContents, org.eclipse.ui.progress.UIJob, org.eclipse.core.runtime.jobs.Job, org.eclipse.swt.widgets.Display, org.eclipse.ui.quickaccess.QuickAccessElement, java.util.concurrent.atomic.AtomicReference, java.lang.String);
    Code:
       0: aload_0
       1: aload_1
       2: putfield      #99                 // Field this$0:Lorg/eclipse/ui/internal/quickaccess/QuickAccessContents;
       5: aload_0
       6: aload_2
       7: putfield      #100                // Field val$computingFeedbackJob:Lorg/eclipse/ui/progress/UIJob;
      10: aload_0
      11: aload_3
      12: putfield      #97                 // Field val$currentComputeEntriesJob:Lorg/eclipse/core/runtime/jobs/Job;
      15: aload_0
      16: aload         4
      18: putfield      #98                 // Field val$display:Lorg/eclipse/swt/widgets/Display;
      21: aload_0
      22: aload         5
      24: putfield      #101                // Field val$perfectMatch:Lorg/eclipse/ui/quickaccess/QuickAccessElement;
      27: aload_0
      28: aload         6
      30: putfield      #96                 // Field val$entries:Ljava/util/concurrent/atomic/AtomicReference;
      33: aload_0
      34: aload         7
      36: putfield      #95                 // Field val$filter:Ljava/lang/String;
      39: aload_0
      40: invokespecial #104                // Method org/eclipse/core/runtime/jobs/JobChangeAdapter."<init>":()V
      43: return

  public void done(org.eclipse.core.runtime.jobs.IJobChangeEvent);
    Code:
       0: aload_0
       1: getfield      #100                // Field val$computingFeedbackJob:Lorg/eclipse/ui/progress/UIJob;
       4: invokevirtual #109                // Method org/eclipse/ui/progress/UIJob.cancel:()Z
       7: pop
       8: aload_0
       9: getfield      #99                 // Field this$0:Lorg/eclipse/ui/internal/quickaccess/QuickAccessContents;
      12: getfield      #93                 // Field org/eclipse/ui/internal/quickaccess/QuickAccessContents.computeProposalsJob:Lorg/eclipse/core/runtime/jobs/Job;
      15: aload_0
      16: getfield      #97                 // Field val$currentComputeEntriesJob:Lorg/eclipse/core/runtime/jobs/Job;
      19: if_acmpne     78
      22: aload_1
      23: invokeinterface #111,  1          // InterfaceMethod org/eclipse/core/runtime/jobs/IJobChangeEvent.getResult:()Lorg/eclipse/core/runtime/IStatus;
      28: invokeinterface #110,  1          // InterfaceMethod org/eclipse/core/runtime/IStatus.isOK:()Z
      33: ifeq          78
      36: aload_0
      37: getfield      #99                 // Field this$0:Lorg/eclipse/ui/internal/quickaccess/QuickAccessContents;
      40: getfield      #94                 // Field org/eclipse/ui/internal/quickaccess/QuickAccessContents.table:Lorg/eclipse/swt/widgets/Table;
      43: invokevirtual #106                // Method org/eclipse/swt/widgets/Table.isDisposed:()Z
      46: ifne          78
      49: aload_0
      50: getfield      #98                 // Field val$display:Lorg/eclipse/swt/widgets/Display;
      53: aload_0
      54: aload_0
      55: getfield      #100                // Field val$computingFeedbackJob:Lorg/eclipse/ui/progress/UIJob;
      58: aload_0
      59: getfield      #101                // Field val$perfectMatch:Lorg/eclipse/ui/quickaccess/QuickAccessElement;
      62: aload_0
      63: getfield      #96                 // Field val$entries:Ljava/util/concurrent/atomic/AtomicReference;
      66: aload_0
      67: getfield      #95                 // Field val$filter:Ljava/lang/String;
      70: invokedynamic #115,  0            // InvokeDynamic #0:run:(Lorg/eclipse/ui/internal/quickaccess/QuickAccessContents$2;Lorg/eclipse/ui/progress/UIJob;Lorg/eclipse/ui/quickaccess/QuickAccessElement;Ljava/util/concurrent/atomic/AtomicReference;Ljava/lang/String;)Ljava/lang/Runnable;
      75: invokevirtual #105                // Method org/eclipse/swt/widgets/Display.asyncExec:(Ljava/lang/Runnable;)V
      78: return

  private void lambda$0(org.eclipse.ui.progress.UIJob, org.eclipse.ui.quickaccess.QuickAccessElement, java.util.concurrent.atomic.AtomicReference, java.lang.String);
    Code:
       0: aload_1
       1: invokevirtual #109                // Method org/eclipse/ui/progress/UIJob.cancel:()Z
       4: pop
       5: aload_0
       6: getfield      #99                 // Field this$0:Lorg/eclipse/ui/internal/quickaccess/QuickAccessContents;
       9: aload_2
      10: aload_3
      11: invokevirtual #103                // Method java/util/concurrent/atomic/AtomicReference.get:()Ljava/lang/Object;
      14: checkcast     #40                 // class "[Ljava/util/List;"
      17: aload         4
      19: invokevirtual #107                // Method org/eclipse/ui/internal/quickaccess/QuickAccessContents.refreshTable:(Lorg/eclipse/ui/quickaccess/QuickAccessElement;[Ljava/util/List;Ljava/lang/String;)V
      22: return
}
