Compiled from "AbstractNamedValueMethodArgumentResolver.java"
public abstract class org.springframework.web.method.annotation.AbstractNamedValueMethodArgumentResolver implements org.springframework.web.method.support.HandlerMethodArgumentResolver {
  private final org.springframework.beans.factory.config.ConfigurableBeanFactory configurableBeanFactory;

  private final org.springframework.beans.factory.config.BeanExpressionContext expressionContext;

  private final java.util.Map<org.springframework.core.MethodParameter, org.springframework.web.method.annotation.AbstractNamedValueMethodArgumentResolver$NamedValueInfo> namedValueInfoCache;

  public org.springframework.web.method.annotation.AbstractNamedValueMethodArgumentResolver();
    Code:
       0: aload_0
       1: invokespecial #1                  // Method java/lang/Object."<init>":()V
       4: aload_0
       5: new           #2                  // class java/util/concurrent/ConcurrentHashMap
       8: dup
       9: sipush        256
      12: invokespecial #3                  // Method java/util/concurrent/ConcurrentHashMap."<init>":(I)V
      15: putfield      #4                  // Field namedValueInfoCache:Ljava/util/Map;
      18: aload_0
      19: aconst_null
      20: putfield      #5                  // Field configurableBeanFactory:Lorg/springframework/beans/factory/config/ConfigurableBeanFactory;
      23: aload_0
      24: aconst_null
      25: putfield      #6                  // Field expressionContext:Lorg/springframework/beans/factory/config/BeanExpressionContext;
      28: return

  public org.springframework.web.method.annotation.AbstractNamedValueMethodArgumentResolver(org.springframework.beans.factory.config.ConfigurableBeanFactory);
    Code:
       0: aload_0
       1: invokespecial #1                  // Method java/lang/Object."<init>":()V
       4: aload_0
       5: new           #2                  // class java/util/concurrent/ConcurrentHashMap
       8: dup
       9: sipush        256
      12: invokespecial #3                  // Method java/util/concurrent/ConcurrentHashMap."<init>":(I)V
      15: putfield      #4                  // Field namedValueInfoCache:Ljava/util/Map;
      18: aload_0
      19: aload_1
      20: putfield      #5                  // Field configurableBeanFactory:Lorg/springframework/beans/factory/config/ConfigurableBeanFactory;
      23: aload_0
      24: aload_1
      25: ifnull        46
      28: new           #7                  // class org/springframework/beans/factory/config/BeanExpressionContext
      31: dup
      32: aload_1
      33: new           #8                  // class org/springframework/web/context/request/RequestScope
      36: dup
      37: invokespecial #9                  // Method org/springframework/web/context/request/RequestScope."<init>":()V
      40: invokespecial #10                 // Method org/springframework/beans/factory/config/BeanExpressionContext."<init>":(Lorg/springframework/beans/factory/config/ConfigurableBeanFactory;Lorg/springframework/beans/factory/config/Scope;)V
      43: goto          47
      46: aconst_null
      47: putfield      #6                  // Field expressionContext:Lorg/springframework/beans/factory/config/BeanExpressionContext;
      50: return

  public final java.lang.Object resolveArgument(org.springframework.core.MethodParameter, org.springframework.web.method.support.ModelAndViewContainer, org.springframework.web.context.request.NativeWebRequest, org.springframework.web.bind.support.WebDataBinderFactory) throws java.lang.Exception;
    Code:
       0: aload_0
       1: aload_1
       2: invokespecial #11                 // Method getNamedValueInfo:(Lorg/springframework/core/MethodParameter;)Lorg/springframework/web/method/annotation/AbstractNamedValueMethodArgumentResolver$NamedValueInfo;
       5: astore        5
       7: aload_1
       8: invokevirtual #12                 // Method org/springframework/core/MethodParameter.nestedIfOptional:()Lorg/springframework/core/MethodParameter;
      11: astore        6
      13: aload_0
      14: aload         5
      16: invokestatic  #13                 // Method org/springframework/web/method/annotation/AbstractNamedValueMethodArgumentResolver$NamedValueInfo.access$000:(Lorg/springframework/web/method/annotation/AbstractNamedValueMethodArgumentResolver$NamedValueInfo;)Ljava/lang/String;
      19: invokespecial #14                 // Method resolveStringValue:(Ljava/lang/String;)Ljava/lang/Object;
      22: astore        7
      24: aload         7
      26: ifnonnull     65
      29: new           #15                 // class java/lang/IllegalArgumentException
      32: dup
      33: new           #16                 // class java/lang/StringBuilder
      36: dup
      37: invokespecial #17                 // Method java/lang/StringBuilder."<init>":()V
      40: ldc           #18                 // String Specified name must not resolve to null: [
      42: invokevirtual #19                 // Method java/lang/StringBuilder.append:(Ljava/lang/String;)Ljava/lang/StringBuilder;
      45: aload         5
      47: invokestatic  #13                 // Method org/springframework/web/method/annotation/AbstractNamedValueMethodArgumentResolver$NamedValueInfo.access$000:(Lorg/springframework/web/method/annotation/AbstractNamedValueMethodArgumentResolver$NamedValueInfo;)Ljava/lang/String;
      50: invokevirtual #19                 // Method java/lang/StringBuilder.append:(Ljava/lang/String;)Ljava/lang/StringBuilder;
      53: ldc           #20                 // String ]
      55: invokevirtual #19                 // Method java/lang/StringBuilder.append:(Ljava/lang/String;)Ljava/lang/StringBuilder;
      58: invokevirtual #21                 // Method java/lang/StringBuilder.toString:()Ljava/lang/String;
      61: invokespecial #22                 // Method java/lang/IllegalArgumentException."<init>":(Ljava/lang/String;)V
      64: athrow
      65: aload_0
      66: aload         7
      68: invokevirtual #23                 // Method java/lang/Object.toString:()Ljava/lang/String;
      71: aload         6
      73: aload_3
      74: invokevirtual #24                 // Method resolveName:(Ljava/lang/String;Lorg/springframework/core/MethodParameter;Lorg/springframework/web/context/request/NativeWebRequest;)Ljava/lang/Object;
      77: astore        8
      79: aload         8
      81: ifnonnull     155
      84: aload         5
      86: invokestatic  #25                 // Method org/springframework/web/method/annotation/AbstractNamedValueMethodArgumentResolver$NamedValueInfo.access$100:(Lorg/springframework/web/method/annotation/AbstractNamedValueMethodArgumentResolver$NamedValueInfo;)Ljava/lang/String;
      89: ifnull        106
      92: aload_0
      93: aload         5
      95: invokestatic  #25                 // Method org/springframework/web/method/annotation/AbstractNamedValueMethodArgumentResolver$NamedValueInfo.access$100:(Lorg/springframework/web/method/annotation/AbstractNamedValueMethodArgumentResolver$NamedValueInfo;)Ljava/lang/String;
      98: invokespecial #14                 // Method resolveStringValue:(Ljava/lang/String;)Ljava/lang/Object;
     101: astore        8
     103: goto          134
     106: aload         5
     108: invokestatic  #26                 // Method org/springframework/web/method/annotation/AbstractNamedValueMethodArgumentResolver$NamedValueInfo.access$200:(Lorg/springframework/web/method/annotation/AbstractNamedValueMethodArgumentResolver$NamedValueInfo;)Z
     111: ifeq          134
     114: aload         6
     116: invokevirtual #27                 // Method org/springframework/core/MethodParameter.isOptional:()Z
     119: ifne          134
     122: aload_0
     123: aload         5
     125: invokestatic  #13                 // Method org/springframework/web/method/annotation/AbstractNamedValueMethodArgumentResolver$NamedValueInfo.access$000:(Lorg/springframework/web/method/annotation/AbstractNamedValueMethodArgumentResolver$NamedValueInfo;)Ljava/lang/String;
     128: aload         6
     130: aload_3
     131: invokevirtual #28                 // Method handleMissingValue:(Ljava/lang/String;Lorg/springframework/core/MethodParameter;Lorg/springframework/web/context/request/NativeWebRequest;)V
     134: aload_0
     135: aload         5
     137: invokestatic  #13                 // Method org/springframework/web/method/annotation/AbstractNamedValueMethodArgumentResolver$NamedValueInfo.access$000:(Lorg/springframework/web/method/annotation/AbstractNamedValueMethodArgumentResolver$NamedValueInfo;)Ljava/lang/String;
     140: aload         8
     142: aload         6
     144: invokevirtual #29                 // Method org/springframework/core/MethodParameter.getNestedParameterType:()Ljava/lang/Class;
     147: invokespecial #30                 // Method handleNullValue:(Ljava/lang/String;Ljava/lang/Object;Ljava/lang/Class;)Ljava/lang/Object;
     150: astore        8
     152: goto          184
     155: ldc           #31                 // String
     157: aload         8
     159: invokevirtual #32                 // Method java/lang/String.equals:(Ljava/lang/Object;)Z
     162: ifeq          184
     165: aload         5
     167: invokestatic  #25                 // Method org/springframework/web/method/annotation/AbstractNamedValueMethodArgumentResolver$NamedValueInfo.access$100:(Lorg/springframework/web/method/annotation/AbstractNamedValueMethodArgumentResolver$NamedValueInfo;)Ljava/lang/String;
     170: ifnull        184
     173: aload_0
     174: aload         5
     176: invokestatic  #25                 // Method org/springframework/web/method/annotation/AbstractNamedValueMethodArgumentResolver$NamedValueInfo.access$100:(Lorg/springframework/web/method/annotation/AbstractNamedValueMethodArgumentResolver$NamedValueInfo;)Ljava/lang/String;
     179: invokespecial #14                 // Method resolveStringValue:(Ljava/lang/String;)Ljava/lang/Object;
     182: astore        8
     184: aload         4
     186: ifnull        278
     189: aload         4
     191: aload_3
     192: aconst_null
     193: aload         5
     195: invokestatic  #13                 // Method org/springframework/web/method/annotation/AbstractNamedValueMethodArgumentResolver$NamedValueInfo.access$000:(Lorg/springframework/web/method/annotation/AbstractNamedValueMethodArgumentResolver$NamedValueInfo;)Ljava/lang/String;
     198: invokeinterface #33,  4           // InterfaceMethod org/springframework/web/bind/support/WebDataBinderFactory.createBinder:(Lorg/springframework/web/context/request/NativeWebRequest;Ljava/lang/Object;Ljava/lang/String;)Lorg/springframework/web/bind/WebDataBinder;
     203: astore        9
     205: aload         9
     207: aload         8
     209: aload_1
     210: invokevirtual #34                 // Method org/springframework/core/MethodParameter.getParameterType:()Ljava/lang/Class;
     213: aload_1
     214: invokevirtual #35                 // Method org/springframework/web/bind/WebDataBinder.convertIfNecessary:(Ljava/lang/Object;Ljava/lang/Class;Lorg/springframework/core/MethodParameter;)Ljava/lang/Object;
     217: astore        8
     219: goto          278
     222: astore        10
     224: new           #37                 // class org/springframework/web/method/annotation/MethodArgumentConversionNotSupportedException
     227: dup
     228: aload         8
     230: aload         10
     232: invokevirtual #38                 // Method org/springframework/beans/ConversionNotSupportedException.getRequiredType:()Ljava/lang/Class;
     235: aload         5
     237: invokestatic  #13                 // Method org/springframework/web/method/annotation/AbstractNamedValueMethodArgumentResolver$NamedValueInfo.access$000:(Lorg/springframework/web/method/annotation/AbstractNamedValueMethodArgumentResolver$NamedValueInfo;)Ljava/lang/String;
     240: aload_1
     241: aload         10
     243: invokevirtual #39                 // Method org/springframework/beans/ConversionNotSupportedException.getCause:()Ljava/lang/Throwable;
     246: invokespecial #40                 // Method org/springframework/web/method/annotation/MethodArgumentConversionNotSupportedException."<init>":(Ljava/lang/Object;Ljava/lang/Class;Ljava/lang/String;Lorg/springframework/core/MethodParameter;Ljava/lang/Throwable;)V
     249: athrow
     250: astore        10
     252: new           #42                 // class org/springframework/web/method/annotation/MethodArgumentTypeMismatchException
     255: dup
     256: aload         8
     258: aload         10
     260: invokevirtual #43                 // Method org/springframework/beans/TypeMismatchException.getRequiredType:()Ljava/lang/Class;
     263: aload         5
     265: invokestatic  #13                 // Method org/springframework/web/method/annotation/AbstractNamedValueMethodArgumentResolver$NamedValueInfo.access$000:(Lorg/springframework/web/method/annotation/AbstractNamedValueMethodArgumentResolver$NamedValueInfo;)Ljava/lang/String;
     268: aload_1
     269: aload         10
     271: invokevirtual #44                 // Method org/springframework/beans/TypeMismatchException.getCause:()Ljava/lang/Throwable;
     274: invokespecial #45                 // Method org/springframework/web/method/annotation/MethodArgumentTypeMismatchException."<init>":(Ljava/lang/Object;Ljava/lang/Class;Ljava/lang/String;Lorg/springframework/core/MethodParameter;Ljava/lang/Throwable;)V
     277: athrow
     278: aload_0
     279: aload         8
     281: aload         5
     283: invokestatic  #13                 // Method org/springframework/web/method/annotation/AbstractNamedValueMethodArgumentResolver$NamedValueInfo.access$000:(Lorg/springframework/web/method/annotation/AbstractNamedValueMethodArgumentResolver$NamedValueInfo;)Ljava/lang/String;
     286: aload_1
     287: aload_2
     288: aload_3
     289: invokevirtual #46                 // Method handleResolvedValue:(Ljava/lang/Object;Ljava/lang/String;Lorg/springframework/core/MethodParameter;Lorg/springframework/web/method/support/ModelAndViewContainer;Lorg/springframework/web/context/request/NativeWebRequest;)V
     292: aload         8
     294: areturn
    Exception table:
       from    to  target type
         205   219   222   Class org/springframework/beans/ConversionNotSupportedException
         205   219   250   Class org/springframework/beans/TypeMismatchException

  private org.springframework.web.method.annotation.AbstractNamedValueMethodArgumentResolver$NamedValueInfo getNamedValueInfo(org.springframework.core.MethodParameter);
    Code:
       0: aload_0
       1: getfield      #4                  // Field namedValueInfoCache:Ljava/util/Map;
       4: aload_1
       5: invokeinterface #47,  2           // InterfaceMethod java/util/Map.get:(Ljava/lang/Object;)Ljava/lang/Object;
      10: checkcast     #48                 // class org/springframework/web/method/annotation/AbstractNamedValueMethodArgumentResolver$NamedValueInfo
      13: astore_2
      14: aload_2
      15: ifnonnull     43
      18: aload_0
      19: aload_1
      20: invokevirtual #49                 // Method createNamedValueInfo:(Lorg/springframework/core/MethodParameter;)Lorg/springframework/web/method/annotation/AbstractNamedValueMethodArgumentResolver$NamedValueInfo;
      23: astore_2
      24: aload_0
      25: aload_1
      26: aload_2
      27: invokespecial #50                 // Method updateNamedValueInfo:(Lorg/springframework/core/MethodParameter;Lorg/springframework/web/method/annotation/AbstractNamedValueMethodArgumentResolver$NamedValueInfo;)Lorg/springframework/web/method/annotation/AbstractNamedValueMethodArgumentResolver$NamedValueInfo;
      30: astore_2
      31: aload_0
      32: getfield      #4                  // Field namedValueInfoCache:Ljava/util/Map;
      35: aload_1
      36: aload_2
      37: invokeinterface #51,  3           // InterfaceMethod java/util/Map.put:(Ljava/lang/Object;Ljava/lang/Object;)Ljava/lang/Object;
      42: pop
      43: aload_2
      44: areturn

  protected abstract org.springframework.web.method.annotation.AbstractNamedValueMethodArgumentResolver$NamedValueInfo createNamedValueInfo(org.springframework.core.MethodParameter);

  private org.springframework.web.method.annotation.AbstractNamedValueMethodArgumentResolver$NamedValueInfo updateNamedValueInfo(org.springframework.core.MethodParameter, org.springframework.web.method.annotation.AbstractNamedValueMethodArgumentResolver$NamedValueInfo);
    Code:
       0: aload_2
       1: invokestatic  #13                 // Method org/springframework/web/method/annotation/AbstractNamedValueMethodArgumentResolver$NamedValueInfo.access$000:(Lorg/springframework/web/method/annotation/AbstractNamedValueMethodArgumentResolver$NamedValueInfo;)Ljava/lang/String;
       4: astore_3
       5: aload_2
       6: invokestatic  #13                 // Method org/springframework/web/method/annotation/AbstractNamedValueMethodArgumentResolver$NamedValueInfo.access$000:(Lorg/springframework/web/method/annotation/AbstractNamedValueMethodArgumentResolver$NamedValueInfo;)Ljava/lang/String;
       9: invokevirtual #52                 // Method java/lang/String.isEmpty:()Z
      12: ifeq          62
      15: aload_1
      16: invokevirtual #53                 // Method org/springframework/core/MethodParameter.getParameterName:()Ljava/lang/String;
      19: astore_3
      20: aload_3
      21: ifnonnull     62
      24: new           #15                 // class java/lang/IllegalArgumentException
      27: dup
      28: new           #16                 // class java/lang/StringBuilder
      31: dup
      32: invokespecial #17                 // Method java/lang/StringBuilder."<init>":()V
      35: ldc           #54                 // String Name for argument type [
      37: invokevirtual #19                 // Method java/lang/StringBuilder.append:(Ljava/lang/String;)Ljava/lang/StringBuilder;
      40: aload_1
      41: invokevirtual #29                 // Method org/springframework/core/MethodParameter.getNestedParameterType:()Ljava/lang/Class;
      44: invokevirtual #55                 // Method java/lang/Class.getName:()Ljava/lang/String;
      47: invokevirtual #19                 // Method java/lang/StringBuilder.append:(Ljava/lang/String;)Ljava/lang/StringBuilder;
      50: ldc           #56                 // String ] not available, and parameter name information not found in class file either.
      52: invokevirtual #19                 // Method java/lang/StringBuilder.append:(Ljava/lang/String;)Ljava/lang/StringBuilder;
      55: invokevirtual #21                 // Method java/lang/StringBuilder.toString:()Ljava/lang/String;
      58: invokespecial #22                 // Method java/lang/IllegalArgumentException."<init>":(Ljava/lang/String;)V
      61: athrow
      62: ldc           #58                 // String \n\t\t\n\t\t\n\n\t\t\t\t\n
      64: aload_2
      65: invokestatic  #25                 // Method org/springframework/web/method/annotation/AbstractNamedValueMethodArgumentResolver$NamedValueInfo.access$100:(Lorg/springframework/web/method/annotation/AbstractNamedValueMethodArgumentResolver$NamedValueInfo;)Ljava/lang/String;
      68: invokevirtual #32                 // Method java/lang/String.equals:(Ljava/lang/Object;)Z
      71: ifeq          78
      74: aconst_null
      75: goto          82
      78: aload_2
      79: invokestatic  #25                 // Method org/springframework/web/method/annotation/AbstractNamedValueMethodArgumentResolver$NamedValueInfo.access$100:(Lorg/springframework/web/method/annotation/AbstractNamedValueMethodArgumentResolver$NamedValueInfo;)Ljava/lang/String;
      82: astore        4
      84: new           #48                 // class org/springframework/web/method/annotation/AbstractNamedValueMethodArgumentResolver$NamedValueInfo
      87: dup
      88: aload_3
      89: aload_2
      90: invokestatic  #26                 // Method org/springframework/web/method/annotation/AbstractNamedValueMethodArgumentResolver$NamedValueInfo.access$200:(Lorg/springframework/web/method/annotation/AbstractNamedValueMethodArgumentResolver$NamedValueInfo;)Z
      93: aload         4
      95: invokespecial #59                 // Method org/springframework/web/method/annotation/AbstractNamedValueMethodArgumentResolver$NamedValueInfo."<init>":(Ljava/lang/String;ZLjava/lang/String;)V
      98: areturn

  private java.lang.Object resolveStringValue(java.lang.String);
    Code:
       0: aload_0
       1: getfield      #5                  // Field configurableBeanFactory:Lorg/springframework/beans/factory/config/ConfigurableBeanFactory;
       4: ifnonnull     9
       7: aload_1
       8: areturn
       9: aload_0
      10: getfield      #5                  // Field configurableBeanFactory:Lorg/springframework/beans/factory/config/ConfigurableBeanFactory;
      13: aload_1
      14: invokeinterface #60,  2           // InterfaceMethod org/springframework/beans/factory/config/ConfigurableBeanFactory.resolveEmbeddedValue:(Ljava/lang/String;)Ljava/lang/String;
      19: astore_2
      20: aload_0
      21: getfield      #5                  // Field configurableBeanFactory:Lorg/springframework/beans/factory/config/ConfigurableBeanFactory;
      24: invokeinterface #61,  1           // InterfaceMethod org/springframework/beans/factory/config/ConfigurableBeanFactory.getBeanExpressionResolver:()Lorg/springframework/beans/factory/config/BeanExpressionResolver;
      29: astore_3
      30: aload_3
      31: ifnonnull     36
      34: aload_1
      35: areturn
      36: aload_3
      37: aload_2
      38: aload_0
      39: getfield      #6                  // Field expressionContext:Lorg/springframework/beans/factory/config/BeanExpressionContext;
      42: invokeinterface #62,  3           // InterfaceMethod org/springframework/beans/factory/config/BeanExpressionResolver.evaluate:(Ljava/lang/String;Lorg/springframework/beans/factory/config/BeanExpressionContext;)Ljava/lang/Object;
      47: areturn

  protected abstract java.lang.Object resolveName(java.lang.String, org.springframework.core.MethodParameter, org.springframework.web.context.request.NativeWebRequest) throws java.lang.Exception;

  protected void handleMissingValue(java.lang.String, org.springframework.core.MethodParameter, org.springframework.web.context.request.NativeWebRequest) throws java.lang.Exception;
    Code:
       0: aload_0
       1: aload_1
       2: aload_2
       3: invokevirtual #63                 // Method handleMissingValue:(Ljava/lang/String;Lorg/springframework/core/MethodParameter;)V
       6: return

  protected void handleMissingValue(java.lang.String, org.springframework.core.MethodParameter) throws javax.servlet.ServletException;
    Code:
       0: new           #64                 // class org/springframework/web/bind/ServletRequestBindingException
       3: dup
       4: new           #16                 // class java/lang/StringBuilder
       7: dup
       8: invokespecial #17                 // Method java/lang/StringBuilder."<init>":()V
      11: ldc           #65                 // String Missing argument \'
      13: invokevirtual #19                 // Method java/lang/StringBuilder.append:(Ljava/lang/String;)Ljava/lang/StringBuilder;
      16: aload_1
      17: invokevirtual #19                 // Method java/lang/StringBuilder.append:(Ljava/lang/String;)Ljava/lang/StringBuilder;
      20: ldc           #66                 // String \' for method parameter of type
      22: invokevirtual #19                 // Method java/lang/StringBuilder.append:(Ljava/lang/String;)Ljava/lang/StringBuilder;
      25: aload_2
      26: invokevirtual #29                 // Method org/springframework/core/MethodParameter.getNestedParameterType:()Ljava/lang/Class;
      29: invokevirtual #67                 // Method java/lang/Class.getSimpleName:()Ljava/lang/String;
      32: invokevirtual #19                 // Method java/lang/StringBuilder.append:(Ljava/lang/String;)Ljava/lang/StringBuilder;
      35: invokevirtual #21                 // Method java/lang/StringBuilder.toString:()Ljava/lang/String;
      38: invokespecial #68                 // Method org/springframework/web/bind/ServletRequestBindingException."<init>":(Ljava/lang/String;)V
      41: athrow

  private java.lang.Object handleNullValue(java.lang.String, java.lang.Object, java.lang.Class<?>);
    Code:
       0: aload_2
       1: ifnonnull     69
       4: getstatic     #69                 // Field java/lang/Boolean.TYPE:Ljava/lang/Class;
       7: aload_3
       8: invokevirtual #70                 // Method java/lang/Object.equals:(Ljava/lang/Object;)Z
      11: ifeq          18
      14: getstatic     #71                 // Field java/lang/Boolean.FALSE:Ljava/lang/Boolean;
      17: areturn
      18: aload_3
      19: invokevirtual #72                 // Method java/lang/Class.isPrimitive:()Z
      22: ifeq          69
      25: new           #73                 // class java/lang/IllegalStateException
      28: dup
      29: new           #16                 // class java/lang/StringBuilder
      32: dup
      33: invokespecial #17                 // Method java/lang/StringBuilder."<init>":()V
      36: ldc           #74                 // String Optional
      38: invokevirtual #19                 // Method java/lang/StringBuilder.append:(Ljava/lang/String;)Ljava/lang/StringBuilder;
      41: aload_3
      42: invokevirtual #67                 // Method java/lang/Class.getSimpleName:()Ljava/lang/String;
      45: invokevirtual #19                 // Method java/lang/StringBuilder.append:(Ljava/lang/String;)Ljava/lang/StringBuilder;
      48: ldc           #75                 // String  parameter \'
      50: invokevirtual #19                 // Method java/lang/StringBuilder.append:(Ljava/lang/String;)Ljava/lang/StringBuilder;
      53: aload_1
      54: invokevirtual #19                 // Method java/lang/StringBuilder.append:(Ljava/lang/String;)Ljava/lang/StringBuilder;
      57: ldc           #76                 // String \' is present but cannot be translated into a null value due to being declared as a primitive type. Consider declaring it as object wrapper for the corresponding primitive type.
      59: invokevirtual #19                 // Method java/lang/StringBuilder.append:(Ljava/lang/String;)Ljava/lang/StringBuilder;
      62: invokevirtual #21                 // Method java/lang/StringBuilder.toString:()Ljava/lang/String;
      65: invokespecial #77                 // Method java/lang/IllegalStateException."<init>":(Ljava/lang/String;)V
      68: athrow
      69: aload_2
      70: areturn

  protected void handleResolvedValue(java.lang.Object, java.lang.String, org.springframework.core.MethodParameter, org.springframework.web.method.support.ModelAndViewContainer, org.springframework.web.context.request.NativeWebRequest);
    Code:
       0: return
}
