Compiled from "DefaultShieldClient.java"
final class software.amazon.awssdk.services.shield.DefaultShieldClient implements software.amazon.awssdk.services.shield.ShieldClient {
  private final software.amazon.awssdk.core.client.handler.SyncClientHandler clientHandler;

  private final software.amazon.awssdk.protocols.json.AwsJsonProtocolFactory protocolFactory;

  private final software.amazon.awssdk.core.client.config.SdkClientConfiguration clientConfiguration;

  protected software.amazon.awssdk.services.shield.DefaultShieldClient(software.amazon.awssdk.core.client.config.SdkClientConfiguration);
    Code:
       0: aload_0
       1: invokespecial #1                  // Method java/lang/Object."<init>":()V
       4: aload_0
       5: new           #2                  // class software/amazon/awssdk/awscore/client/handler/AwsSyncClientHandler
       8: dup
       9: aload_1
      10: invokespecial #3                  // Method software/amazon/awssdk/awscore/client/handler/AwsSyncClientHandler."<init>":(Lsoftware/amazon/awssdk/core/client/config/SdkClientConfiguration;)V
      13: putfield      #4                  // Field clientHandler:Lsoftware/amazon/awssdk/core/client/handler/SyncClientHandler;
      16: aload_0
      17: aload_1
      18: putfield      #5                  // Field clientConfiguration:Lsoftware/amazon/awssdk/core/client/config/SdkClientConfiguration;
      21: aload_0
      22: aload_0
      23: invokestatic  #6                  // Method software/amazon/awssdk/protocols/json/AwsJsonProtocolFactory.builder:()Lsoftware/amazon/awssdk/protocols/json/AwsJsonProtocolFactory$Builder;
      26: invokespecial #7                  // Method init:(Lsoftware/amazon/awssdk/protocols/json/BaseAwsJsonProtocolFactory$Builder;)Lsoftware/amazon/awssdk/protocols/json/BaseAwsJsonProtocolFactory$Builder;
      29: checkcast     #8                  // class software/amazon/awssdk/protocols/json/AwsJsonProtocolFactory$Builder
      32: invokevirtual #9                  // Method software/amazon/awssdk/protocols/json/AwsJsonProtocolFactory$Builder.build:()Lsoftware/amazon/awssdk/protocols/json/AwsJsonProtocolFactory;
      35: putfield      #10                 // Field protocolFactory:Lsoftware/amazon/awssdk/protocols/json/AwsJsonProtocolFactory;
      38: return

  public final java.lang.String serviceName();
    Code:
       0: ldc           #12                 // String shield
       2: areturn

  public software.amazon.awssdk.services.shield.model.AssociateDrtLogBucketResponse associateDRTLogBucket(software.amazon.awssdk.services.shield.model.AssociateDrtLogBucketRequest) throws software.amazon.awssdk.services.shield.model.InternalErrorException, software.amazon.awssdk.services.shield.model.InvalidOperationException, software.amazon.awssdk.services.shield.model.NoAssociatedRoleException, software.amazon.awssdk.services.shield.model.LimitsExceededException, software.amazon.awssdk.services.shield.model.InvalidParameterException, software.amazon.awssdk.services.shield.model.AccessDeniedForDependencyException, software.amazon.awssdk.services.shield.model.OptimisticLockException, software.amazon.awssdk.services.shield.model.ResourceNotFoundException, software.amazon.awssdk.awscore.exception.AwsServiceException, software.amazon.awssdk.core.exception.SdkClientException, software.amazon.awssdk.services.shield.model.ShieldException;
    Code:
       0: invokestatic  #13                 // Method software/amazon/awssdk/protocols/json/JsonOperationMetadata.builder:()Lsoftware/amazon/awssdk/protocols/json/JsonOperationMetadata$Builder;
       3: iconst_0
       4: invokevirtual #14                 // Method software/amazon/awssdk/protocols/json/JsonOperationMetadata$Builder.hasStreamingSuccessResponse:(Z)Lsoftware/amazon/awssdk/protocols/json/JsonOperationMetadata$Builder;
       7: iconst_1
       8: invokevirtual #15                 // Method software/amazon/awssdk/protocols/json/JsonOperationMetadata$Builder.isPayloadJson:(Z)Lsoftware/amazon/awssdk/protocols/json/JsonOperationMetadata$Builder;
      11: invokevirtual #16                 // Method software/amazon/awssdk/protocols/json/JsonOperationMetadata$Builder.build:()Lsoftware/amazon/awssdk/protocols/json/JsonOperationMetadata;
      14: astore_2
      15: aload_0
      16: getfield      #10                 // Field protocolFactory:Lsoftware/amazon/awssdk/protocols/json/AwsJsonProtocolFactory;
      19: aload_2
      20: invokedynamic #17,  0             // InvokeDynamic #0:get:()Ljava/util/function/Supplier;
      25: invokevirtual #18                 // Method software/amazon/awssdk/protocols/json/AwsJsonProtocolFactory.createResponseHandler:(Lsoftware/amazon/awssdk/protocols/json/JsonOperationMetadata;Ljava/util/function/Supplier;)Lsoftware/amazon/awssdk/core/http/HttpResponseHandler;
      28: astore_3
      29: aload_0
      30: aload_0
      31: getfield      #10                 // Field protocolFactory:Lsoftware/amazon/awssdk/protocols/json/AwsJsonProtocolFactory;
      34: aload_2
      35: invokespecial #19                 // Method createErrorResponseHandler:(Lsoftware/amazon/awssdk/protocols/json/BaseAwsJsonProtocolFactory;Lsoftware/amazon/awssdk/protocols/json/JsonOperationMetadata;)Lsoftware/amazon/awssdk/core/http/HttpResponseHandler;
      38: astore        4
      40: aload_0
      41: getfield      #4                  // Field clientHandler:Lsoftware/amazon/awssdk/core/client/handler/SyncClientHandler;
      44: new           #20                 // class software/amazon/awssdk/core/client/handler/ClientExecutionParams
      47: dup
      48: invokespecial #21                 // Method software/amazon/awssdk/core/client/handler/ClientExecutionParams."<init>":()V
      51: ldc           #22                 // String AssociateDRTLogBucket
      53: invokevirtual #23                 // Method software/amazon/awssdk/core/client/handler/ClientExecutionParams.withOperationName:(Ljava/lang/String;)Lsoftware/amazon/awssdk/core/client/handler/ClientExecutionParams;
      56: aload_3
      57: invokevirtual #24                 // Method software/amazon/awssdk/core/client/handler/ClientExecutionParams.withResponseHandler:(Lsoftware/amazon/awssdk/core/http/HttpResponseHandler;)Lsoftware/amazon/awssdk/core/client/handler/ClientExecutionParams;
      60: aload         4
      62: invokevirtual #25                 // Method software/amazon/awssdk/core/client/handler/ClientExecutionParams.withErrorResponseHandler:(Lsoftware/amazon/awssdk/core/http/HttpResponseHandler;)Lsoftware/amazon/awssdk/core/client/handler/ClientExecutionParams;
      65: aload_1
      66: invokevirtual #26                 // Method software/amazon/awssdk/core/client/handler/ClientExecutionParams.withInput:(Lsoftware/amazon/awssdk/core/SdkRequest;)Lsoftware/amazon/awssdk/core/client/handler/ClientExecutionParams;
      69: new           #27                 // class software/amazon/awssdk/services/shield/transform/AssociateDrtLogBucketRequestMarshaller
      72: dup
      73: aload_0
      74: getfield      #10                 // Field protocolFactory:Lsoftware/amazon/awssdk/protocols/json/AwsJsonProtocolFactory;
      77: invokespecial #28                 // Method software/amazon/awssdk/services/shield/transform/AssociateDrtLogBucketRequestMarshaller."<init>":(Lsoftware/amazon/awssdk/protocols/json/BaseAwsJsonProtocolFactory;)V
      80: invokevirtual #29                 // Method software/amazon/awssdk/core/client/handler/ClientExecutionParams.withMarshaller:(Lsoftware/amazon/awssdk/core/runtime/transform/Marshaller;)Lsoftware/amazon/awssdk/core/client/handler/ClientExecutionParams;
      83: invokeinterface #30,  2           // InterfaceMethod software/amazon/awssdk/core/client/handler/SyncClientHandler.execute:(Lsoftware/amazon/awssdk/core/client/handler/ClientExecutionParams;)Lsoftware/amazon/awssdk/core/SdkResponse;
      88: checkcast     #31                 // class software/amazon/awssdk/services/shield/model/AssociateDrtLogBucketResponse
      91: areturn

  public software.amazon.awssdk.services.shield.model.AssociateDrtRoleResponse associateDRTRole(software.amazon.awssdk.services.shield.model.AssociateDrtRoleRequest) throws software.amazon.awssdk.services.shield.model.InternalErrorException, software.amazon.awssdk.services.shield.model.InvalidOperationException, software.amazon.awssdk.services.shield.model.InvalidParameterException, software.amazon.awssdk.services.shield.model.AccessDeniedForDependencyException, software.amazon.awssdk.services.shield.model.OptimisticLockException, software.amazon.awssdk.services.shield.model.ResourceNotFoundException, software.amazon.awssdk.awscore.exception.AwsServiceException, software.amazon.awssdk.core.exception.SdkClientException, software.amazon.awssdk.services.shield.model.ShieldException;
    Code:
       0: invokestatic  #13                 // Method software/amazon/awssdk/protocols/json/JsonOperationMetadata.builder:()Lsoftware/amazon/awssdk/protocols/json/JsonOperationMetadata$Builder;
       3: iconst_0
       4: invokevirtual #14                 // Method software/amazon/awssdk/protocols/json/JsonOperationMetadata$Builder.hasStreamingSuccessResponse:(Z)Lsoftware/amazon/awssdk/protocols/json/JsonOperationMetadata$Builder;
       7: iconst_1
       8: invokevirtual #15                 // Method software/amazon/awssdk/protocols/json/JsonOperationMetadata$Builder.isPayloadJson:(Z)Lsoftware/amazon/awssdk/protocols/json/JsonOperationMetadata$Builder;
      11: invokevirtual #16                 // Method software/amazon/awssdk/protocols/json/JsonOperationMetadata$Builder.build:()Lsoftware/amazon/awssdk/protocols/json/JsonOperationMetadata;
      14: astore_2
      15: aload_0
      16: getfield      #10                 // Field protocolFactory:Lsoftware/amazon/awssdk/protocols/json/AwsJsonProtocolFactory;
      19: aload_2
      20: invokedynamic #32,  0             // InvokeDynamic #1:get:()Ljava/util/function/Supplier;
      25: invokevirtual #18                 // Method software/amazon/awssdk/protocols/json/AwsJsonProtocolFactory.createResponseHandler:(Lsoftware/amazon/awssdk/protocols/json/JsonOperationMetadata;Ljava/util/function/Supplier;)Lsoftware/amazon/awssdk/core/http/HttpResponseHandler;
      28: astore_3
      29: aload_0
      30: aload_0
      31: getfield      #10                 // Field protocolFactory:Lsoftware/amazon/awssdk/protocols/json/AwsJsonProtocolFactory;
      34: aload_2
      35: invokespecial #19                 // Method createErrorResponseHandler:(Lsoftware/amazon/awssdk/protocols/json/BaseAwsJsonProtocolFactory;Lsoftware/amazon/awssdk/protocols/json/JsonOperationMetadata;)Lsoftware/amazon/awssdk/core/http/HttpResponseHandler;
      38: astore        4
      40: aload_0
      41: getfield      #4                  // Field clientHandler:Lsoftware/amazon/awssdk/core/client/handler/SyncClientHandler;
      44: new           #20                 // class software/amazon/awssdk/core/client/handler/ClientExecutionParams
      47: dup
      48: invokespecial #21                 // Method software/amazon/awssdk/core/client/handler/ClientExecutionParams."<init>":()V
      51: ldc           #33                 // String AssociateDRTRole
      53: invokevirtual #23                 // Method software/amazon/awssdk/core/client/handler/ClientExecutionParams.withOperationName:(Ljava/lang/String;)Lsoftware/amazon/awssdk/core/client/handler/ClientExecutionParams;
      56: aload_3
      57: invokevirtual #24                 // Method software/amazon/awssdk/core/client/handler/ClientExecutionParams.withResponseHandler:(Lsoftware/amazon/awssdk/core/http/HttpResponseHandler;)Lsoftware/amazon/awssdk/core/client/handler/ClientExecutionParams;
      60: aload         4
      62: invokevirtual #25                 // Method software/amazon/awssdk/core/client/handler/ClientExecutionParams.withErrorResponseHandler:(Lsoftware/amazon/awssdk/core/http/HttpResponseHandler;)Lsoftware/amazon/awssdk/core/client/handler/ClientExecutionParams;
      65: aload_1
      66: invokevirtual #26                 // Method software/amazon/awssdk/core/client/handler/ClientExecutionParams.withInput:(Lsoftware/amazon/awssdk/core/SdkRequest;)Lsoftware/amazon/awssdk/core/client/handler/ClientExecutionParams;
      69: new           #34                 // class software/amazon/awssdk/services/shield/transform/AssociateDrtRoleRequestMarshaller
      72: dup
      73: aload_0
      74: getfield      #10                 // Field protocolFactory:Lsoftware/amazon/awssdk/protocols/json/AwsJsonProtocolFactory;
      77: invokespecial #35                 // Method software/amazon/awssdk/services/shield/transform/AssociateDrtRoleRequestMarshaller."<init>":(Lsoftware/amazon/awssdk/protocols/json/BaseAwsJsonProtocolFactory;)V
      80: invokevirtual #29                 // Method software/amazon/awssdk/core/client/handler/ClientExecutionParams.withMarshaller:(Lsoftware/amazon/awssdk/core/runtime/transform/Marshaller;)Lsoftware/amazon/awssdk/core/client/handler/ClientExecutionParams;
      83: invokeinterface #30,  2           // InterfaceMethod software/amazon/awssdk/core/client/handler/SyncClientHandler.execute:(Lsoftware/amazon/awssdk/core/client/handler/ClientExecutionParams;)Lsoftware/amazon/awssdk/core/SdkResponse;
      88: checkcast     #36                 // class software/amazon/awssdk/services/shield/model/AssociateDrtRoleResponse
      91: areturn

  public software.amazon.awssdk.services.shield.model.AssociateHealthCheckResponse associateHealthCheck(software.amazon.awssdk.services.shield.model.AssociateHealthCheckRequest) throws software.amazon.awssdk.services.shield.model.InternalErrorException, software.amazon.awssdk.services.shield.model.LimitsExceededException, software.amazon.awssdk.services.shield.model.ResourceNotFoundException, software.amazon.awssdk.services.shield.model.InvalidParameterException, software.amazon.awssdk.services.shield.model.OptimisticLockException, software.amazon.awssdk.awscore.exception.AwsServiceException, software.amazon.awssdk.core.exception.SdkClientException, software.amazon.awssdk.services.shield.model.ShieldException;
    Code:
       0: invokestatic  #13                 // Method software/amazon/awssdk/protocols/json/JsonOperationMetadata.builder:()Lsoftware/amazon/awssdk/protocols/json/JsonOperationMetadata$Builder;
       3: iconst_0
       4: invokevirtual #14                 // Method software/amazon/awssdk/protocols/json/JsonOperationMetadata$Builder.hasStreamingSuccessResponse:(Z)Lsoftware/amazon/awssdk/protocols/json/JsonOperationMetadata$Builder;
       7: iconst_1
       8: invokevirtual #15                 // Method software/amazon/awssdk/protocols/json/JsonOperationMetadata$Builder.isPayloadJson:(Z)Lsoftware/amazon/awssdk/protocols/json/JsonOperationMetadata$Builder;
      11: invokevirtual #16                 // Method software/amazon/awssdk/protocols/json/JsonOperationMetadata$Builder.build:()Lsoftware/amazon/awssdk/protocols/json/JsonOperationMetadata;
      14: astore_2
      15: aload_0
      16: getfield      #10                 // Field protocolFactory:Lsoftware/amazon/awssdk/protocols/json/AwsJsonProtocolFactory;
      19: aload_2
      20: invokedynamic #37,  0             // InvokeDynamic #2:get:()Ljava/util/function/Supplier;
      25: invokevirtual #18                 // Method software/amazon/awssdk/protocols/json/AwsJsonProtocolFactory.createResponseHandler:(Lsoftware/amazon/awssdk/protocols/json/JsonOperationMetadata;Ljava/util/function/Supplier;)Lsoftware/amazon/awssdk/core/http/HttpResponseHandler;
      28: astore_3
      29: aload_0
      30: aload_0
      31: getfield      #10                 // Field protocolFactory:Lsoftware/amazon/awssdk/protocols/json/AwsJsonProtocolFactory;
      34: aload_2
      35: invokespecial #19                 // Method createErrorResponseHandler:(Lsoftware/amazon/awssdk/protocols/json/BaseAwsJsonProtocolFactory;Lsoftware/amazon/awssdk/protocols/json/JsonOperationMetadata;)Lsoftware/amazon/awssdk/core/http/HttpResponseHandler;
      38: astore        4
      40: aload_0
      41: getfield      #4                  // Field clientHandler:Lsoftware/amazon/awssdk/core/client/handler/SyncClientHandler;
      44: new           #20                 // class software/amazon/awssdk/core/client/handler/ClientExecutionParams
      47: dup
      48: invokespecial #21                 // Method software/amazon/awssdk/core/client/handler/ClientExecutionParams."<init>":()V
      51: ldc           #38                 // String AssociateHealthCheck
      53: invokevirtual #23                 // Method software/amazon/awssdk/core/client/handler/ClientExecutionParams.withOperationName:(Ljava/lang/String;)Lsoftware/amazon/awssdk/core/client/handler/ClientExecutionParams;
      56: aload_3
      57: invokevirtual #24                 // Method software/amazon/awssdk/core/client/handler/ClientExecutionParams.withResponseHandler:(Lsoftware/amazon/awssdk/core/http/HttpResponseHandler;)Lsoftware/amazon/awssdk/core/client/handler/ClientExecutionParams;
      60: aload         4
      62: invokevirtual #25                 // Method software/amazon/awssdk/core/client/handler/ClientExecutionParams.withErrorResponseHandler:(Lsoftware/amazon/awssdk/core/http/HttpResponseHandler;)Lsoftware/amazon/awssdk/core/client/handler/ClientExecutionParams;
      65: aload_1
      66: invokevirtual #26                 // Method software/amazon/awssdk/core/client/handler/ClientExecutionParams.withInput:(Lsoftware/amazon/awssdk/core/SdkRequest;)Lsoftware/amazon/awssdk/core/client/handler/ClientExecutionParams;
      69: new           #39                 // class software/amazon/awssdk/services/shield/transform/AssociateHealthCheckRequestMarshaller
      72: dup
      73: aload_0
      74: getfield      #10                 // Field protocolFactory:Lsoftware/amazon/awssdk/protocols/json/AwsJsonProtocolFactory;
      77: invokespecial #40                 // Method software/amazon/awssdk/services/shield/transform/AssociateHealthCheckRequestMarshaller."<init>":(Lsoftware/amazon/awssdk/protocols/json/BaseAwsJsonProtocolFactory;)V
      80: invokevirtual #29                 // Method software/amazon/awssdk/core/client/handler/ClientExecutionParams.withMarshaller:(Lsoftware/amazon/awssdk/core/runtime/transform/Marshaller;)Lsoftware/amazon/awssdk/core/client/handler/ClientExecutionParams;
      83: invokeinterface #30,  2           // InterfaceMethod software/amazon/awssdk/core/client/handler/SyncClientHandler.execute:(Lsoftware/amazon/awssdk/core/client/handler/ClientExecutionParams;)Lsoftware/amazon/awssdk/core/SdkResponse;
      88: checkcast     #41                 // class software/amazon/awssdk/services/shield/model/AssociateHealthCheckResponse
      91: areturn

  public software.amazon.awssdk.services.shield.model.CreateProtectionResponse createProtection(software.amazon.awssdk.services.shield.model.CreateProtectionRequest) throws software.amazon.awssdk.services.shield.model.InternalErrorException, software.amazon.awssdk.services.shield.model.InvalidResourceException, software.amazon.awssdk.services.shield.model.InvalidOperationException, software.amazon.awssdk.services.shield.model.LimitsExceededException, software.amazon.awssdk.services.shield.model.ResourceAlreadyExistsException, software.amazon.awssdk.services.shield.model.OptimisticLockException, software.amazon.awssdk.services.shield.model.ResourceNotFoundException, software.amazon.awssdk.awscore.exception.AwsServiceException, software.amazon.awssdk.core.exception.SdkClientException, software.amazon.awssdk.services.shield.model.ShieldException;
    Code:
       0: invokestatic  #13                 // Method software/amazon/awssdk/protocols/json/JsonOperationMetadata.builder:()Lsoftware/amazon/awssdk/protocols/json/JsonOperationMetadata$Builder;
       3: iconst_0
       4: invokevirtual #14                 // Method software/amazon/awssdk/protocols/json/JsonOperationMetadata$Builder.hasStreamingSuccessResponse:(Z)Lsoftware/amazon/awssdk/protocols/json/JsonOperationMetadata$Builder;
       7: iconst_1
       8: invokevirtual #15                 // Method software/amazon/awssdk/protocols/json/JsonOperationMetadata$Builder.isPayloadJson:(Z)Lsoftware/amazon/awssdk/protocols/json/JsonOperationMetadata$Builder;
      11: invokevirtual #16                 // Method software/amazon/awssdk/protocols/json/JsonOperationMetadata$Builder.build:()Lsoftware/amazon/awssdk/protocols/json/JsonOperationMetadata;
      14: astore_2
      15: aload_0
      16: getfield      #10                 // Field protocolFactory:Lsoftware/amazon/awssdk/protocols/json/AwsJsonProtocolFactory;
      19: aload_2
      20: invokedynamic #42,  0             // InvokeDynamic #3:get:()Ljava/util/function/Supplier;
      25: invokevirtual #18                 // Method software/amazon/awssdk/protocols/json/AwsJsonProtocolFactory.createResponseHandler:(Lsoftware/amazon/awssdk/protocols/json/JsonOperationMetadata;Ljava/util/function/Supplier;)Lsoftware/amazon/awssdk/core/http/HttpResponseHandler;
      28: astore_3
      29: aload_0
      30: aload_0
      31: getfield      #10                 // Field protocolFactory:Lsoftware/amazon/awssdk/protocols/json/AwsJsonProtocolFactory;
      34: aload_2
      35: invokespecial #19                 // Method createErrorResponseHandler:(Lsoftware/amazon/awssdk/protocols/json/BaseAwsJsonProtocolFactory;Lsoftware/amazon/awssdk/protocols/json/JsonOperationMetadata;)Lsoftware/amazon/awssdk/core/http/HttpResponseHandler;
      38: astore        4
      40: aload_0
      41: getfield      #4                  // Field clientHandler:Lsoftware/amazon/awssdk/core/client/handler/SyncClientHandler;
      44: new           #20                 // class software/amazon/awssdk/core/client/handler/ClientExecutionParams
      47: dup
      48: invokespecial #21                 // Method software/amazon/awssdk/core/client/handler/ClientExecutionParams."<init>":()V
      51: ldc           #43                 // String CreateProtection
      53: invokevirtual #23                 // Method software/amazon/awssdk/core/client/handler/ClientExecutionParams.withOperationName:(Ljava/lang/String;)Lsoftware/amazon/awssdk/core/client/handler/ClientExecutionParams;
      56: aload_3
      57: invokevirtual #24                 // Method software/amazon/awssdk/core/client/handler/ClientExecutionParams.withResponseHandler:(Lsoftware/amazon/awssdk/core/http/HttpResponseHandler;)Lsoftware/amazon/awssdk/core/client/handler/ClientExecutionParams;
      60: aload         4
      62: invokevirtual #25                 // Method software/amazon/awssdk/core/client/handler/ClientExecutionParams.withErrorResponseHandler:(Lsoftware/amazon/awssdk/core/http/HttpResponseHandler;)Lsoftware/amazon/awssdk/core/client/handler/ClientExecutionParams;
      65: aload_1
      66: invokevirtual #26                 // Method software/amazon/awssdk/core/client/handler/ClientExecutionParams.withInput:(Lsoftware/amazon/awssdk/core/SdkRequest;)Lsoftware/amazon/awssdk/core/client/handler/ClientExecutionParams;
      69: new           #44                 // class software/amazon/awssdk/services/shield/transform/CreateProtectionRequestMarshaller
      72: dup
      73: aload_0
      74: getfield      #10                 // Field protocolFactory:Lsoftware/amazon/awssdk/protocols/json/AwsJsonProtocolFactory;
      77: invokespecial #45                 // Method software/amazon/awssdk/services/shield/transform/CreateProtectionRequestMarshaller."<init>":(Lsoftware/amazon/awssdk/protocols/json/BaseAwsJsonProtocolFactory;)V
      80: invokevirtual #29                 // Method software/amazon/awssdk/core/client/handler/ClientExecutionParams.withMarshaller:(Lsoftware/amazon/awssdk/core/runtime/transform/Marshaller;)Lsoftware/amazon/awssdk/core/client/handler/ClientExecutionParams;
      83: invokeinterface #30,  2           // InterfaceMethod software/amazon/awssdk/core/client/handler/SyncClientHandler.execute:(Lsoftware/amazon/awssdk/core/client/handler/ClientExecutionParams;)Lsoftware/amazon/awssdk/core/SdkResponse;
      88: checkcast     #46                 // class software/amazon/awssdk/services/shield/model/CreateProtectionResponse
      91: areturn

  public software.amazon.awssdk.services.shield.model.CreateSubscriptionResponse createSubscription(software.amazon.awssdk.services.shield.model.CreateSubscriptionRequest) throws software.amazon.awssdk.services.shield.model.InternalErrorException, software.amazon.awssdk.services.shield.model.ResourceAlreadyExistsException, software.amazon.awssdk.awscore.exception.AwsServiceException, software.amazon.awssdk.core.exception.SdkClientException, software.amazon.awssdk.services.shield.model.ShieldException;
    Code:
       0: invokestatic  #13                 // Method software/amazon/awssdk/protocols/json/JsonOperationMetadata.builder:()Lsoftware/amazon/awssdk/protocols/json/JsonOperationMetadata$Builder;
       3: iconst_0
       4: invokevirtual #14                 // Method software/amazon/awssdk/protocols/json/JsonOperationMetadata$Builder.hasStreamingSuccessResponse:(Z)Lsoftware/amazon/awssdk/protocols/json/JsonOperationMetadata$Builder;
       7: iconst_1
       8: invokevirtual #15                 // Method software/amazon/awssdk/protocols/json/JsonOperationMetadata$Builder.isPayloadJson:(Z)Lsoftware/amazon/awssdk/protocols/json/JsonOperationMetadata$Builder;
      11: invokevirtual #16                 // Method software/amazon/awssdk/protocols/json/JsonOperationMetadata$Builder.build:()Lsoftware/amazon/awssdk/protocols/json/JsonOperationMetadata;
      14: astore_2
      15: aload_0
      16: getfield      #10                 // Field protocolFactory:Lsoftware/amazon/awssdk/protocols/json/AwsJsonProtocolFactory;
      19: aload_2
      20: invokedynamic #47,  0             // InvokeDynamic #4:get:()Ljava/util/function/Supplier;
      25: invokevirtual #18                 // Method software/amazon/awssdk/protocols/json/AwsJsonProtocolFactory.createResponseHandler:(Lsoftware/amazon/awssdk/protocols/json/JsonOperationMetadata;Ljava/util/function/Supplier;)Lsoftware/amazon/awssdk/core/http/HttpResponseHandler;
      28: astore_3
      29: aload_0
      30: aload_0
      31: getfield      #10                 // Field protocolFactory:Lsoftware/amazon/awssdk/protocols/json/AwsJsonProtocolFactory;
      34: aload_2
      35: invokespecial #19                 // Method createErrorResponseHandler:(Lsoftware/amazon/awssdk/protocols/json/BaseAwsJsonProtocolFactory;Lsoftware/amazon/awssdk/protocols/json/JsonOperationMetadata;)Lsoftware/amazon/awssdk/core/http/HttpResponseHandler;
      38: astore        4
      40: aload_0
      41: getfield      #4                  // Field clientHandler:Lsoftware/amazon/awssdk/core/client/handler/SyncClientHandler;
      44: new           #20                 // class software/amazon/awssdk/core/client/handler/ClientExecutionParams
      47: dup
      48: invokespecial #21                 // Method software/amazon/awssdk/core/client/handler/ClientExecutionParams."<init>":()V
      51: ldc           #48                 // String CreateSubscription
      53: invokevirtual #23                 // Method software/amazon/awssdk/core/client/handler/ClientExecutionParams.withOperationName:(Ljava/lang/String;)Lsoftware/amazon/awssdk/core/client/handler/ClientExecutionParams;
      56: aload_3
      57: invokevirtual #24                 // Method software/amazon/awssdk/core/client/handler/ClientExecutionParams.withResponseHandler:(Lsoftware/amazon/awssdk/core/http/HttpResponseHandler;)Lsoftware/amazon/awssdk/core/client/handler/ClientExecutionParams;
      60: aload         4
      62: invokevirtual #25                 // Method software/amazon/awssdk/core/client/handler/ClientExecutionParams.withErrorResponseHandler:(Lsoftware/amazon/awssdk/core/http/HttpResponseHandler;)Lsoftware/amazon/awssdk/core/client/handler/ClientExecutionParams;
      65: aload_1
      66: invokevirtual #26                 // Method software/amazon/awssdk/core/client/handler/ClientExecutionParams.withInput:(Lsoftware/amazon/awssdk/core/SdkRequest;)Lsoftware/amazon/awssdk/core/client/handler/ClientExecutionParams;
      69: new           #49                 // class software/amazon/awssdk/services/shield/transform/CreateSubscriptionRequestMarshaller
      72: dup
      73: aload_0
      74: getfield      #10                 // Field protocolFactory:Lsoftware/amazon/awssdk/protocols/json/AwsJsonProtocolFactory;
      77: invokespecial #50                 // Method software/amazon/awssdk/services/shield/transform/CreateSubscriptionRequestMarshaller."<init>":(Lsoftware/amazon/awssdk/protocols/json/BaseAwsJsonProtocolFactory;)V
      80: invokevirtual #29                 // Method software/amazon/awssdk/core/client/handler/ClientExecutionParams.withMarshaller:(Lsoftware/amazon/awssdk/core/runtime/transform/Marshaller;)Lsoftware/amazon/awssdk/core/client/handler/ClientExecutionParams;
      83: invokeinterface #30,  2           // InterfaceMethod software/amazon/awssdk/core/client/handler/SyncClientHandler.execute:(Lsoftware/amazon/awssdk/core/client/handler/ClientExecutionParams;)Lsoftware/amazon/awssdk/core/SdkResponse;
      88: checkcast     #51                 // class software/amazon/awssdk/services/shield/model/CreateSubscriptionResponse
      91: areturn

  public software.amazon.awssdk.services.shield.model.DeleteProtectionResponse deleteProtection(software.amazon.awssdk.services.shield.model.DeleteProtectionRequest) throws software.amazon.awssdk.services.shield.model.InternalErrorException, software.amazon.awssdk.services.shield.model.ResourceNotFoundException, software.amazon.awssdk.services.shield.model.OptimisticLockException, software.amazon.awssdk.awscore.exception.AwsServiceException, software.amazon.awssdk.core.exception.SdkClientException, software.amazon.awssdk.services.shield.model.ShieldException;
    Code:
       0: invokestatic  #13                 // Method software/amazon/awssdk/protocols/json/JsonOperationMetadata.builder:()Lsoftware/amazon/awssdk/protocols/json/JsonOperationMetadata$Builder;
       3: iconst_0
       4: invokevirtual #14                 // Method software/amazon/awssdk/protocols/json/JsonOperationMetadata$Builder.hasStreamingSuccessResponse:(Z)Lsoftware/amazon/awssdk/protocols/json/JsonOperationMetadata$Builder;
       7: iconst_1
       8: invokevirtual #15                 // Method software/amazon/awssdk/protocols/json/JsonOperationMetadata$Builder.isPayloadJson:(Z)Lsoftware/amazon/awssdk/protocols/json/JsonOperationMetadata$Builder;
      11: invokevirtual #16                 // Method software/amazon/awssdk/protocols/json/JsonOperationMetadata$Builder.build:()Lsoftware/amazon/awssdk/protocols/json/JsonOperationMetadata;
      14: astore_2
      15: aload_0
      16: getfield      #10                 // Field protocolFactory:Lsoftware/amazon/awssdk/protocols/json/AwsJsonProtocolFactory;
      19: aload_2
      20: invokedynamic #52,  0             // InvokeDynamic #5:get:()Ljava/util/function/Supplier;
      25: invokevirtual #18                 // Method software/amazon/awssdk/protocols/json/AwsJsonProtocolFactory.createResponseHandler:(Lsoftware/amazon/awssdk/protocols/json/JsonOperationMetadata;Ljava/util/function/Supplier;)Lsoftware/amazon/awssdk/core/http/HttpResponseHandler;
      28: astore_3
      29: aload_0
      30: aload_0
      31: getfield      #10                 // Field protocolFactory:Lsoftware/amazon/awssdk/protocols/json/AwsJsonProtocolFactory;
      34: aload_2
      35: invokespecial #19                 // Method createErrorResponseHandler:(Lsoftware/amazon/awssdk/protocols/json/BaseAwsJsonProtocolFactory;Lsoftware/amazon/awssdk/protocols/json/JsonOperationMetadata;)Lsoftware/amazon/awssdk/core/http/HttpResponseHandler;
      38: astore        4
      40: aload_0
      41: getfield      #4                  // Field clientHandler:Lsoftware/amazon/awssdk/core/client/handler/SyncClientHandler;
      44: new           #20                 // class software/amazon/awssdk/core/client/handler/ClientExecutionParams
      47: dup
      48: invokespecial #21                 // Method software/amazon/awssdk/core/client/handler/ClientExecutionParams."<init>":()V
      51: ldc           #53                 // String DeleteProtection
      53: invokevirtual #23                 // Method software/amazon/awssdk/core/client/handler/ClientExecutionParams.withOperationName:(Ljava/lang/String;)Lsoftware/amazon/awssdk/core/client/handler/ClientExecutionParams;
      56: aload_3
      57: invokevirtual #24                 // Method software/amazon/awssdk/core/client/handler/ClientExecutionParams.withResponseHandler:(Lsoftware/amazon/awssdk/core/http/HttpResponseHandler;)Lsoftware/amazon/awssdk/core/client/handler/ClientExecutionParams;
      60: aload         4
      62: invokevirtual #25                 // Method software/amazon/awssdk/core/client/handler/ClientExecutionParams.withErrorResponseHandler:(Lsoftware/amazon/awssdk/core/http/HttpResponseHandler;)Lsoftware/amazon/awssdk/core/client/handler/ClientExecutionParams;
      65: aload_1
      66: invokevirtual #26                 // Method software/amazon/awssdk/core/client/handler/ClientExecutionParams.withInput:(Lsoftware/amazon/awssdk/core/SdkRequest;)Lsoftware/amazon/awssdk/core/client/handler/ClientExecutionParams;
      69: new           #54                 // class software/amazon/awssdk/services/shield/transform/DeleteProtectionRequestMarshaller
      72: dup
      73: aload_0
      74: getfield      #10                 // Field protocolFactory:Lsoftware/amazon/awssdk/protocols/json/AwsJsonProtocolFactory;
      77: invokespecial #55                 // Method software/amazon/awssdk/services/shield/transform/DeleteProtectionRequestMarshaller."<init>":(Lsoftware/amazon/awssdk/protocols/json/BaseAwsJsonProtocolFactory;)V
      80: invokevirtual #29                 // Method software/amazon/awssdk/core/client/handler/ClientExecutionParams.withMarshaller:(Lsoftware/amazon/awssdk/core/runtime/transform/Marshaller;)Lsoftware/amazon/awssdk/core/client/handler/ClientExecutionParams;
      83: invokeinterface #30,  2           // InterfaceMethod software/amazon/awssdk/core/client/handler/SyncClientHandler.execute:(Lsoftware/amazon/awssdk/core/client/handler/ClientExecutionParams;)Lsoftware/amazon/awssdk/core/SdkResponse;
      88: checkcast     #56                 // class software/amazon/awssdk/services/shield/model/DeleteProtectionResponse
      91: areturn

  public software.amazon.awssdk.services.shield.model.DescribeAttackResponse describeAttack(software.amazon.awssdk.services.shield.model.DescribeAttackRequest) throws software.amazon.awssdk.services.shield.model.InternalErrorException, software.amazon.awssdk.services.shield.model.AccessDeniedException, software.amazon.awssdk.awscore.exception.AwsServiceException, software.amazon.awssdk.core.exception.SdkClientException, software.amazon.awssdk.services.shield.model.ShieldException;
    Code:
       0: invokestatic  #13                 // Method software/amazon/awssdk/protocols/json/JsonOperationMetadata.builder:()Lsoftware/amazon/awssdk/protocols/json/JsonOperationMetadata$Builder;
       3: iconst_0
       4: invokevirtual #14                 // Method software/amazon/awssdk/protocols/json/JsonOperationMetadata$Builder.hasStreamingSuccessResponse:(Z)Lsoftware/amazon/awssdk/protocols/json/JsonOperationMetadata$Builder;
       7: iconst_1
       8: invokevirtual #15                 // Method software/amazon/awssdk/protocols/json/JsonOperationMetadata$Builder.isPayloadJson:(Z)Lsoftware/amazon/awssdk/protocols/json/JsonOperationMetadata$Builder;
      11: invokevirtual #16                 // Method software/amazon/awssdk/protocols/json/JsonOperationMetadata$Builder.build:()Lsoftware/amazon/awssdk/protocols/json/JsonOperationMetadata;
      14: astore_2
      15: aload_0
      16: getfield      #10                 // Field protocolFactory:Lsoftware/amazon/awssdk/protocols/json/AwsJsonProtocolFactory;
      19: aload_2
      20: invokedynamic #57,  0             // InvokeDynamic #6:get:()Ljava/util/function/Supplier;
      25: invokevirtual #18                 // Method software/amazon/awssdk/protocols/json/AwsJsonProtocolFactory.createResponseHandler:(Lsoftware/amazon/awssdk/protocols/json/JsonOperationMetadata;Ljava/util/function/Supplier;)Lsoftware/amazon/awssdk/core/http/HttpResponseHandler;
      28: astore_3
      29: aload_0
      30: aload_0
      31: getfield      #10                 // Field protocolFactory:Lsoftware/amazon/awssdk/protocols/json/AwsJsonProtocolFactory;
      34: aload_2
      35: invokespecial #19                 // Method createErrorResponseHandler:(Lsoftware/amazon/awssdk/protocols/json/BaseAwsJsonProtocolFactory;Lsoftware/amazon/awssdk/protocols/json/JsonOperationMetadata;)Lsoftware/amazon/awssdk/core/http/HttpResponseHandler;
      38: astore        4
      40: aload_0
      41: getfield      #4                  // Field clientHandler:Lsoftware/amazon/awssdk/core/client/handler/SyncClientHandler;
      44: new           #20                 // class software/amazon/awssdk/core/client/handler/ClientExecutionParams
      47: dup
      48: invokespecial #21                 // Method software/amazon/awssdk/core/client/handler/ClientExecutionParams."<init>":()V
      51: ldc           #58                 // String DescribeAttack
      53: invokevirtual #23                 // Method software/amazon/awssdk/core/client/handler/ClientExecutionParams.withOperationName:(Ljava/lang/String;)Lsoftware/amazon/awssdk/core/client/handler/ClientExecutionParams;
      56: aload_3
      57: invokevirtual #24                 // Method software/amazon/awssdk/core/client/handler/ClientExecutionParams.withResponseHandler:(Lsoftware/amazon/awssdk/core/http/HttpResponseHandler;)Lsoftware/amazon/awssdk/core/client/handler/ClientExecutionParams;
      60: aload         4
      62: invokevirtual #25                 // Method software/amazon/awssdk/core/client/handler/ClientExecutionParams.withErrorResponseHandler:(Lsoftware/amazon/awssdk/core/http/HttpResponseHandler;)Lsoftware/amazon/awssdk/core/client/handler/ClientExecutionParams;
      65: aload_1
      66: invokevirtual #26                 // Method software/amazon/awssdk/core/client/handler/ClientExecutionParams.withInput:(Lsoftware/amazon/awssdk/core/SdkRequest;)Lsoftware/amazon/awssdk/core/client/handler/ClientExecutionParams;
      69: new           #59                 // class software/amazon/awssdk/services/shield/transform/DescribeAttackRequestMarshaller
      72: dup
      73: aload_0
      74: getfield      #10                 // Field protocolFactory:Lsoftware/amazon/awssdk/protocols/json/AwsJsonProtocolFactory;
      77: invokespecial #60                 // Method software/amazon/awssdk/services/shield/transform/DescribeAttackRequestMarshaller."<init>":(Lsoftware/amazon/awssdk/protocols/json/BaseAwsJsonProtocolFactory;)V
      80: invokevirtual #29                 // Method software/amazon/awssdk/core/client/handler/ClientExecutionParams.withMarshaller:(Lsoftware/amazon/awssdk/core/runtime/transform/Marshaller;)Lsoftware/amazon/awssdk/core/client/handler/ClientExecutionParams;
      83: invokeinterface #30,  2           // InterfaceMethod software/amazon/awssdk/core/client/handler/SyncClientHandler.execute:(Lsoftware/amazon/awssdk/core/client/handler/ClientExecutionParams;)Lsoftware/amazon/awssdk/core/SdkResponse;
      88: checkcast     #61                 // class software/amazon/awssdk/services/shield/model/DescribeAttackResponse
      91: areturn

  public software.amazon.awssdk.services.shield.model.DescribeDrtAccessResponse describeDRTAccess(software.amazon.awssdk.services.shield.model.DescribeDrtAccessRequest) throws software.amazon.awssdk.services.shield.model.InternalErrorException, software.amazon.awssdk.services.shield.model.ResourceNotFoundException, software.amazon.awssdk.awscore.exception.AwsServiceException, software.amazon.awssdk.core.exception.SdkClientException, software.amazon.awssdk.services.shield.model.ShieldException;
    Code:
       0: invokestatic  #13                 // Method software/amazon/awssdk/protocols/json/JsonOperationMetadata.builder:()Lsoftware/amazon/awssdk/protocols/json/JsonOperationMetadata$Builder;
       3: iconst_0
       4: invokevirtual #14                 // Method software/amazon/awssdk/protocols/json/JsonOperationMetadata$Builder.hasStreamingSuccessResponse:(Z)Lsoftware/amazon/awssdk/protocols/json/JsonOperationMetadata$Builder;
       7: iconst_1
       8: invokevirtual #15                 // Method software/amazon/awssdk/protocols/json/JsonOperationMetadata$Builder.isPayloadJson:(Z)Lsoftware/amazon/awssdk/protocols/json/JsonOperationMetadata$Builder;
      11: invokevirtual #16                 // Method software/amazon/awssdk/protocols/json/JsonOperationMetadata$Builder.build:()Lsoftware/amazon/awssdk/protocols/json/JsonOperationMetadata;
      14: astore_2
      15: aload_0
      16: getfield      #10                 // Field protocolFactory:Lsoftware/amazon/awssdk/protocols/json/AwsJsonProtocolFactory;
      19: aload_2
      20: invokedynamic #62,  0             // InvokeDynamic #7:get:()Ljava/util/function/Supplier;
      25: invokevirtual #18                 // Method software/amazon/awssdk/protocols/json/AwsJsonProtocolFactory.createResponseHandler:(Lsoftware/amazon/awssdk/protocols/json/JsonOperationMetadata;Ljava/util/function/Supplier;)Lsoftware/amazon/awssdk/core/http/HttpResponseHandler;
      28: astore_3
      29: aload_0
      30: aload_0
      31: getfield      #10                 // Field protocolFactory:Lsoftware/amazon/awssdk/protocols/json/AwsJsonProtocolFactory;
      34: aload_2
      35: invokespecial #19                 // Method createErrorResponseHandler:(Lsoftware/amazon/awssdk/protocols/json/BaseAwsJsonProtocolFactory;Lsoftware/amazon/awssdk/protocols/json/JsonOperationMetadata;)Lsoftware/amazon/awssdk/core/http/HttpResponseHandler;
      38: astore        4
      40: aload_0
      41: getfield      #4                  // Field clientHandler:Lsoftware/amazon/awssdk/core/client/handler/SyncClientHandler;
      44: new           #20                 // class software/amazon/awssdk/core/client/handler/ClientExecutionParams
      47: dup
      48: invokespecial #21                 // Method software/amazon/awssdk/core/client/handler/ClientExecutionParams."<init>":()V
      51: ldc           #63                 // String DescribeDRTAccess
      53: invokevirtual #23                 // Method software/amazon/awssdk/core/client/handler/ClientExecutionParams.withOperationName:(Ljava/lang/String;)Lsoftware/amazon/awssdk/core/client/handler/ClientExecutionParams;
      56: aload_3
      57: invokevirtual #24                 // Method software/amazon/awssdk/core/client/handler/ClientExecutionParams.withResponseHandler:(Lsoftware/amazon/awssdk/core/http/HttpResponseHandler;)Lsoftware/amazon/awssdk/core/client/handler/ClientExecutionParams;
      60: aload         4
      62: invokevirtual #25                 // Method software/amazon/awssdk/core/client/handler/ClientExecutionParams.withErrorResponseHandler:(Lsoftware/amazon/awssdk/core/http/HttpResponseHandler;)Lsoftware/amazon/awssdk/core/client/handler/ClientExecutionParams;
      65: aload_1
      66: invokevirtual #26                 // Method software/amazon/awssdk/core/client/handler/ClientExecutionParams.withInput:(Lsoftware/amazon/awssdk/core/SdkRequest;)Lsoftware/amazon/awssdk/core/client/handler/ClientExecutionParams;
      69: new           #64                 // class software/amazon/awssdk/services/shield/transform/DescribeDrtAccessRequestMarshaller
      72: dup
      73: aload_0
      74: getfield      #10                 // Field protocolFactory:Lsoftware/amazon/awssdk/protocols/json/AwsJsonProtocolFactory;
      77: invokespecial #65                 // Method software/amazon/awssdk/services/shield/transform/DescribeDrtAccessRequestMarshaller."<init>":(Lsoftware/amazon/awssdk/protocols/json/BaseAwsJsonProtocolFactory;)V
      80: invokevirtual #29                 // Method software/amazon/awssdk/core/client/handler/ClientExecutionParams.withMarshaller:(Lsoftware/amazon/awssdk/core/runtime/transform/Marshaller;)Lsoftware/amazon/awssdk/core/client/handler/ClientExecutionParams;
      83: invokeinterface #30,  2           // InterfaceMethod software/amazon/awssdk/core/client/handler/SyncClientHandler.execute:(Lsoftware/amazon/awssdk/core/client/handler/ClientExecutionParams;)Lsoftware/amazon/awssdk/core/SdkResponse;
      88: checkcast     #66                 // class software/amazon/awssdk/services/shield/model/DescribeDrtAccessResponse
      91: areturn

  public software.amazon.awssdk.services.shield.model.DescribeEmergencyContactSettingsResponse describeEmergencyContactSettings(software.amazon.awssdk.services.shield.model.DescribeEmergencyContactSettingsRequest) throws software.amazon.awssdk.services.shield.model.InternalErrorException, software.amazon.awssdk.services.shield.model.ResourceNotFoundException, software.amazon.awssdk.awscore.exception.AwsServiceException, software.amazon.awssdk.core.exception.SdkClientException, software.amazon.awssdk.services.shield.model.ShieldException;
    Code:
       0: invokestatic  #13                 // Method software/amazon/awssdk/protocols/json/JsonOperationMetadata.builder:()Lsoftware/amazon/awssdk/protocols/json/JsonOperationMetadata$Builder;
       3: iconst_0
       4: invokevirtual #14                 // Method software/amazon/awssdk/protocols/json/JsonOperationMetadata$Builder.hasStreamingSuccessResponse:(Z)Lsoftware/amazon/awssdk/protocols/json/JsonOperationMetadata$Builder;
       7: iconst_1
       8: invokevirtual #15                 // Method software/amazon/awssdk/protocols/json/JsonOperationMetadata$Builder.isPayloadJson:(Z)Lsoftware/amazon/awssdk/protocols/json/JsonOperationMetadata$Builder;
      11: invokevirtual #16                 // Method software/amazon/awssdk/protocols/json/JsonOperationMetadata$Builder.build:()Lsoftware/amazon/awssdk/protocols/json/JsonOperationMetadata;
      14: astore_2
      15: aload_0
      16: getfield      #10                 // Field protocolFactory:Lsoftware/amazon/awssdk/protocols/json/AwsJsonProtocolFactory;
      19: aload_2
      20: invokedynamic #67,  0             // InvokeDynamic #8:get:()Ljava/util/function/Supplier;
      25: invokevirtual #18                 // Method software/amazon/awssdk/protocols/json/AwsJsonProtocolFactory.createResponseHandler:(Lsoftware/amazon/awssdk/protocols/json/JsonOperationMetadata;Ljava/util/function/Supplier;)Lsoftware/amazon/awssdk/core/http/HttpResponseHandler;
      28: astore_3
      29: aload_0
      30: aload_0
      31: getfield      #10                 // Field protocolFactory:Lsoftware/amazon/awssdk/protocols/json/AwsJsonProtocolFactory;
      34: aload_2
      35: invokespecial #19                 // Method createErrorResponseHandler:(Lsoftware/amazon/awssdk/protocols/json/BaseAwsJsonProtocolFactory;Lsoftware/amazon/awssdk/protocols/json/JsonOperationMetadata;)Lsoftware/amazon/awssdk/core/http/HttpResponseHandler;
      38: astore        4
      40: aload_0
      41: getfield      #4                  // Field clientHandler:Lsoftware/amazon/awssdk/core/client/handler/SyncClientHandler;
      44: new           #20                 // class software/amazon/awssdk/core/client/handler/ClientExecutionParams
      47: dup
      48: invokespecial #21                 // Method software/amazon/awssdk/core/client/handler/ClientExecutionParams."<init>":()V
      51: ldc           #68                 // String DescribeEmergencyContactSettings
      53: invokevirtual #23                 // Method software/amazon/awssdk/core/client/handler/ClientExecutionParams.withOperationName:(Ljava/lang/String;)Lsoftware/amazon/awssdk/core/client/handler/ClientExecutionParams;
      56: aload_3
      57: invokevirtual #24                 // Method software/amazon/awssdk/core/client/handler/ClientExecutionParams.withResponseHandler:(Lsoftware/amazon/awssdk/core/http/HttpResponseHandler;)Lsoftware/amazon/awssdk/core/client/handler/ClientExecutionParams;
      60: aload         4
      62: invokevirtual #25                 // Method software/amazon/awssdk/core/client/handler/ClientExecutionParams.withErrorResponseHandler:(Lsoftware/amazon/awssdk/core/http/HttpResponseHandler;)Lsoftware/amazon/awssdk/core/client/handler/ClientExecutionParams;
      65: aload_1
      66: invokevirtual #26                 // Method software/amazon/awssdk/core/client/handler/ClientExecutionParams.withInput:(Lsoftware/amazon/awssdk/core/SdkRequest;)Lsoftware/amazon/awssdk/core/client/handler/ClientExecutionParams;
      69: new           #69                 // class software/amazon/awssdk/services/shield/transform/DescribeEmergencyContactSettingsRequestMarshaller
      72: dup
      73: aload_0
      74: getfield      #10                 // Field protocolFactory:Lsoftware/amazon/awssdk/protocols/json/AwsJsonProtocolFactory;
      77: invokespecial #70                 // Method software/amazon/awssdk/services/shield/transform/DescribeEmergencyContactSettingsRequestMarshaller."<init>":(Lsoftware/amazon/awssdk/protocols/json/BaseAwsJsonProtocolFactory;)V
      80: invokevirtual #29                 // Method software/amazon/awssdk/core/client/handler/ClientExecutionParams.withMarshaller:(Lsoftware/amazon/awssdk/core/runtime/transform/Marshaller;)Lsoftware/amazon/awssdk/core/client/handler/ClientExecutionParams;
      83: invokeinterface #30,  2           // InterfaceMethod software/amazon/awssdk/core/client/handler/SyncClientHandler.execute:(Lsoftware/amazon/awssdk/core/client/handler/ClientExecutionParams;)Lsoftware/amazon/awssdk/core/SdkResponse;
      88: checkcast     #71                 // class software/amazon/awssdk/services/shield/model/DescribeEmergencyContactSettingsResponse
      91: areturn

  public software.amazon.awssdk.services.shield.model.DescribeProtectionResponse describeProtection(software.amazon.awssdk.services.shield.model.DescribeProtectionRequest) throws software.amazon.awssdk.services.shield.model.InternalErrorException, software.amazon.awssdk.services.shield.model.InvalidParameterException, software.amazon.awssdk.services.shield.model.ResourceNotFoundException, software.amazon.awssdk.awscore.exception.AwsServiceException, software.amazon.awssdk.core.exception.SdkClientException, software.amazon.awssdk.services.shield.model.ShieldException;
    Code:
       0: invokestatic  #13                 // Method software/amazon/awssdk/protocols/json/JsonOperationMetadata.builder:()Lsoftware/amazon/awssdk/protocols/json/JsonOperationMetadata$Builder;
       3: iconst_0
       4: invokevirtual #14                 // Method software/amazon/awssdk/protocols/json/JsonOperationMetadata$Builder.hasStreamingSuccessResponse:(Z)Lsoftware/amazon/awssdk/protocols/json/JsonOperationMetadata$Builder;
       7: iconst_1
       8: invokevirtual #15                 // Method software/amazon/awssdk/protocols/json/JsonOperationMetadata$Builder.isPayloadJson:(Z)Lsoftware/amazon/awssdk/protocols/json/JsonOperationMetadata$Builder;
      11: invokevirtual #16                 // Method software/amazon/awssdk/protocols/json/JsonOperationMetadata$Builder.build:()Lsoftware/amazon/awssdk/protocols/json/JsonOperationMetadata;
      14: astore_2
      15: aload_0
      16: getfield      #10                 // Field protocolFactory:Lsoftware/amazon/awssdk/protocols/json/AwsJsonProtocolFactory;
      19: aload_2
      20: invokedynamic #72,  0             // InvokeDynamic #9:get:()Ljava/util/function/Supplier;
      25: invokevirtual #18                 // Method software/amazon/awssdk/protocols/json/AwsJsonProtocolFactory.createResponseHandler:(Lsoftware/amazon/awssdk/protocols/json/JsonOperationMetadata;Ljava/util/function/Supplier;)Lsoftware/amazon/awssdk/core/http/HttpResponseHandler;
      28: astore_3
      29: aload_0
      30: aload_0
      31: getfield      #10                 // Field protocolFactory:Lsoftware/amazon/awssdk/protocols/json/AwsJsonProtocolFactory;
      34: aload_2
      35: invokespecial #19                 // Method createErrorResponseHandler:(Lsoftware/amazon/awssdk/protocols/json/BaseAwsJsonProtocolFactory;Lsoftware/amazon/awssdk/protocols/json/JsonOperationMetadata;)Lsoftware/amazon/awssdk/core/http/HttpResponseHandler;
      38: astore        4
      40: aload_0
      41: getfield      #4                  // Field clientHandler:Lsoftware/amazon/awssdk/core/client/handler/SyncClientHandler;
      44: new           #20                 // class software/amazon/awssdk/core/client/handler/ClientExecutionParams
      47: dup
      48: invokespecial #21                 // Method software/amazon/awssdk/core/client/handler/ClientExecutionParams."<init>":()V
      51: ldc           #73                 // String DescribeProtection
      53: invokevirtual #23                 // Method software/amazon/awssdk/core/client/handler/ClientExecutionParams.withOperationName:(Ljava/lang/String;)Lsoftware/amazon/awssdk/core/client/handler/ClientExecutionParams;
      56: aload_3
      57: invokevirtual #24                 // Method software/amazon/awssdk/core/client/handler/ClientExecutionParams.withResponseHandler:(Lsoftware/amazon/awssdk/core/http/HttpResponseHandler;)Lsoftware/amazon/awssdk/core/client/handler/ClientExecutionParams;
      60: aload         4
      62: invokevirtual #25                 // Method software/amazon/awssdk/core/client/handler/ClientExecutionParams.withErrorResponseHandler:(Lsoftware/amazon/awssdk/core/http/HttpResponseHandler;)Lsoftware/amazon/awssdk/core/client/handler/ClientExecutionParams;
      65: aload_1
      66: invokevirtual #26                 // Method software/amazon/awssdk/core/client/handler/ClientExecutionParams.withInput:(Lsoftware/amazon/awssdk/core/SdkRequest;)Lsoftware/amazon/awssdk/core/client/handler/ClientExecutionParams;
      69: new           #74                 // class software/amazon/awssdk/services/shield/transform/DescribeProtectionRequestMarshaller
      72: dup
      73: aload_0
      74: getfield      #10                 // Field protocolFactory:Lsoftware/amazon/awssdk/protocols/json/AwsJsonProtocolFactory;
      77: invokespecial #75                 // Method software/amazon/awssdk/services/shield/transform/DescribeProtectionRequestMarshaller."<init>":(Lsoftware/amazon/awssdk/protocols/json/BaseAwsJsonProtocolFactory;)V
      80: invokevirtual #29                 // Method software/amazon/awssdk/core/client/handler/ClientExecutionParams.withMarshaller:(Lsoftware/amazon/awssdk/core/runtime/transform/Marshaller;)Lsoftware/amazon/awssdk/core/client/handler/ClientExecutionParams;
      83: invokeinterface #30,  2           // InterfaceMethod software/amazon/awssdk/core/client/handler/SyncClientHandler.execute:(Lsoftware/amazon/awssdk/core/client/handler/ClientExecutionParams;)Lsoftware/amazon/awssdk/core/SdkResponse;
      88: checkcast     #76                 // class software/amazon/awssdk/services/shield/model/DescribeProtectionResponse
      91: areturn

  public software.amazon.awssdk.services.shield.model.DescribeSubscriptionResponse describeSubscription(software.amazon.awssdk.services.shield.model.DescribeSubscriptionRequest) throws software.amazon.awssdk.services.shield.model.InternalErrorException, software.amazon.awssdk.services.shield.model.ResourceNotFoundException, software.amazon.awssdk.awscore.exception.AwsServiceException, software.amazon.awssdk.core.exception.SdkClientException, software.amazon.awssdk.services.shield.model.ShieldException;
    Code:
       0: invokestatic  #13                 // Method software/amazon/awssdk/protocols/json/JsonOperationMetadata.builder:()Lsoftware/amazon/awssdk/protocols/json/JsonOperationMetadata$Builder;
       3: iconst_0
       4: invokevirtual #14                 // Method software/amazon/awssdk/protocols/json/JsonOperationMetadata$Builder.hasStreamingSuccessResponse:(Z)Lsoftware/amazon/awssdk/protocols/json/JsonOperationMetadata$Builder;
       7: iconst_1
       8: invokevirtual #15                 // Method software/amazon/awssdk/protocols/json/JsonOperationMetadata$Builder.isPayloadJson:(Z)Lsoftware/amazon/awssdk/protocols/json/JsonOperationMetadata$Builder;
      11: invokevirtual #16                 // Method software/amazon/awssdk/protocols/json/JsonOperationMetadata$Builder.build:()Lsoftware/amazon/awssdk/protocols/json/JsonOperationMetadata;
      14: astore_2
      15: aload_0
      16: getfield      #10                 // Field protocolFactory:Lsoftware/amazon/awssdk/protocols/json/AwsJsonProtocolFactory;
      19: aload_2
      20: invokedynamic #77,  0             // InvokeDynamic #10:get:()Ljava/util/function/Supplier;
      25: invokevirtual #18                 // Method software/amazon/awssdk/protocols/json/AwsJsonProtocolFactory.createResponseHandler:(Lsoftware/amazon/awssdk/protocols/json/JsonOperationMetadata;Ljava/util/function/Supplier;)Lsoftware/amazon/awssdk/core/http/HttpResponseHandler;
      28: astore_3
      29: aload_0
      30: aload_0
      31: getfield      #10                 // Field protocolFactory:Lsoftware/amazon/awssdk/protocols/json/AwsJsonProtocolFactory;
      34: aload_2
      35: invokespecial #19                 // Method createErrorResponseHandler:(Lsoftware/amazon/awssdk/protocols/json/BaseAwsJsonProtocolFactory;Lsoftware/amazon/awssdk/protocols/json/JsonOperationMetadata;)Lsoftware/amazon/awssdk/core/http/HttpResponseHandler;
      38: astore        4
      40: aload_0
      41: getfield      #4                  // Field clientHandler:Lsoftware/amazon/awssdk/core/client/handler/SyncClientHandler;
      44: new           #20                 // class software/amazon/awssdk/core/client/handler/ClientExecutionParams
      47: dup
      48: invokespecial #21                 // Method software/amazon/awssdk/core/client/handler/ClientExecutionParams."<init>":()V
      51: ldc           #78                 // String DescribeSubscription
      53: invokevirtual #23                 // Method software/amazon/awssdk/core/client/handler/ClientExecutionParams.withOperationName:(Ljava/lang/String;)Lsoftware/amazon/awssdk/core/client/handler/ClientExecutionParams;
      56: aload_3
      57: invokevirtual #24                 // Method software/amazon/awssdk/core/client/handler/ClientExecutionParams.withResponseHandler:(Lsoftware/amazon/awssdk/core/http/HttpResponseHandler;)Lsoftware/amazon/awssdk/core/client/handler/ClientExecutionParams;
      60: aload         4
      62: invokevirtual #25                 // Method software/amazon/awssdk/core/client/handler/ClientExecutionParams.withErrorResponseHandler:(Lsoftware/amazon/awssdk/core/http/HttpResponseHandler;)Lsoftware/amazon/awssdk/core/client/handler/ClientExecutionParams;
      65: aload_1
      66: invokevirtual #26                 // Method software/amazon/awssdk/core/client/handler/ClientExecutionParams.withInput:(Lsoftware/amazon/awssdk/core/SdkRequest;)Lsoftware/amazon/awssdk/core/client/handler/ClientExecutionParams;
      69: new           #79                 // class software/amazon/awssdk/services/shield/transform/DescribeSubscriptionRequestMarshaller
      72: dup
      73: aload_0
      74: getfield      #10                 // Field protocolFactory:Lsoftware/amazon/awssdk/protocols/json/AwsJsonProtocolFactory;
      77: invokespecial #80                 // Method software/amazon/awssdk/services/shield/transform/DescribeSubscriptionRequestMarshaller."<init>":(Lsoftware/amazon/awssdk/protocols/json/BaseAwsJsonProtocolFactory;)V
      80: invokevirtual #29                 // Method software/amazon/awssdk/core/client/handler/ClientExecutionParams.withMarshaller:(Lsoftware/amazon/awssdk/core/runtime/transform/Marshaller;)Lsoftware/amazon/awssdk/core/client/handler/ClientExecutionParams;
      83: invokeinterface #30,  2           // InterfaceMethod software/amazon/awssdk/core/client/handler/SyncClientHandler.execute:(Lsoftware/amazon/awssdk/core/client/handler/ClientExecutionParams;)Lsoftware/amazon/awssdk/core/SdkResponse;
      88: checkcast     #81                 // class software/amazon/awssdk/services/shield/model/DescribeSubscriptionResponse
      91: areturn

  public software.amazon.awssdk.services.shield.model.DisassociateDrtLogBucketResponse disassociateDRTLogBucket(software.amazon.awssdk.services.shield.model.DisassociateDrtLogBucketRequest) throws software.amazon.awssdk.services.shield.model.InternalErrorException, software.amazon.awssdk.services.shield.model.InvalidOperationException, software.amazon.awssdk.services.shield.model.NoAssociatedRoleException, software.amazon.awssdk.services.shield.model.AccessDeniedForDependencyException, software.amazon.awssdk.services.shield.model.OptimisticLockException, software.amazon.awssdk.services.shield.model.ResourceNotFoundException, software.amazon.awssdk.awscore.exception.AwsServiceException, software.amazon.awssdk.core.exception.SdkClientException, software.amazon.awssdk.services.shield.model.ShieldException;
    Code:
       0: invokestatic  #13                 // Method software/amazon/awssdk/protocols/json/JsonOperationMetadata.builder:()Lsoftware/amazon/awssdk/protocols/json/JsonOperationMetadata$Builder;
       3: iconst_0
       4: invokevirtual #14                 // Method software/amazon/awssdk/protocols/json/JsonOperationMetadata$Builder.hasStreamingSuccessResponse:(Z)Lsoftware/amazon/awssdk/protocols/json/JsonOperationMetadata$Builder;
       7: iconst_1
       8: invokevirtual #15                 // Method software/amazon/awssdk/protocols/json/JsonOperationMetadata$Builder.isPayloadJson:(Z)Lsoftware/amazon/awssdk/protocols/json/JsonOperationMetadata$Builder;
      11: invokevirtual #16                 // Method software/amazon/awssdk/protocols/json/JsonOperationMetadata$Builder.build:()Lsoftware/amazon/awssdk/protocols/json/JsonOperationMetadata;
      14: astore_2
      15: aload_0
      16: getfield      #10                 // Field protocolFactory:Lsoftware/amazon/awssdk/protocols/json/AwsJsonProtocolFactory;
      19: aload_2
      20: invokedynamic #82,  0             // InvokeDynamic #11:get:()Ljava/util/function/Supplier;
      25: invokevirtual #18                 // Method software/amazon/awssdk/protocols/json/AwsJsonProtocolFactory.createResponseHandler:(Lsoftware/amazon/awssdk/protocols/json/JsonOperationMetadata;Ljava/util/function/Supplier;)Lsoftware/amazon/awssdk/core/http/HttpResponseHandler;
      28: astore_3
      29: aload_0
      30: aload_0
      31: getfield      #10                 // Field protocolFactory:Lsoftware/amazon/awssdk/protocols/json/AwsJsonProtocolFactory;
      34: aload_2
      35: invokespecial #19                 // Method createErrorResponseHandler:(Lsoftware/amazon/awssdk/protocols/json/BaseAwsJsonProtocolFactory;Lsoftware/amazon/awssdk/protocols/json/JsonOperationMetadata;)Lsoftware/amazon/awssdk/core/http/HttpResponseHandler;
      38: astore        4
      40: aload_0
      41: getfield      #4                  // Field clientHandler:Lsoftware/amazon/awssdk/core/client/handler/SyncClientHandler;
      44: new           #20                 // class software/amazon/awssdk/core/client/handler/ClientExecutionParams
      47: dup
      48: invokespecial #21                 // Method software/amazon/awssdk/core/client/handler/ClientExecutionParams."<init>":()V
      51: ldc           #83                 // String DisassociateDRTLogBucket
      53: invokevirtual #23                 // Method software/amazon/awssdk/core/client/handler/ClientExecutionParams.withOperationName:(Ljava/lang/String;)Lsoftware/amazon/awssdk/core/client/handler/ClientExecutionParams;
      56: aload_3
      57: invokevirtual #24                 // Method software/amazon/awssdk/core/client/handler/ClientExecutionParams.withResponseHandler:(Lsoftware/amazon/awssdk/core/http/HttpResponseHandler;)Lsoftware/amazon/awssdk/core/client/handler/ClientExecutionParams;
      60: aload         4
      62: invokevirtual #25                 // Method software/amazon/awssdk/core/client/handler/ClientExecutionParams.withErrorResponseHandler:(Lsoftware/amazon/awssdk/core/http/HttpResponseHandler;)Lsoftware/amazon/awssdk/core/client/handler/ClientExecutionParams;
      65: aload_1
      66: invokevirtual #26                 // Method software/amazon/awssdk/core/client/handler/ClientExecutionParams.withInput:(Lsoftware/amazon/awssdk/core/SdkRequest;)Lsoftware/amazon/awssdk/core/client/handler/ClientExecutionParams;
      69: new           #84                 // class software/amazon/awssdk/services/shield/transform/DisassociateDrtLogBucketRequestMarshaller
      72: dup
      73: aload_0
      74: getfield      #10                 // Field protocolFactory:Lsoftware/amazon/awssdk/protocols/json/AwsJsonProtocolFactory;
      77: invokespecial #85                 // Method software/amazon/awssdk/services/shield/transform/DisassociateDrtLogBucketRequestMarshaller."<init>":(Lsoftware/amazon/awssdk/protocols/json/BaseAwsJsonProtocolFactory;)V
      80: invokevirtual #29                 // Method software/amazon/awssdk/core/client/handler/ClientExecutionParams.withMarshaller:(Lsoftware/amazon/awssdk/core/runtime/transform/Marshaller;)Lsoftware/amazon/awssdk/core/client/handler/ClientExecutionParams;
      83: invokeinterface #30,  2           // InterfaceMethod software/amazon/awssdk/core/client/handler/SyncClientHandler.execute:(Lsoftware/amazon/awssdk/core/client/handler/ClientExecutionParams;)Lsoftware/amazon/awssdk/core/SdkResponse;
      88: checkcast     #86                 // class software/amazon/awssdk/services/shield/model/DisassociateDrtLogBucketResponse
      91: areturn

  public software.amazon.awssdk.services.shield.model.DisassociateDrtRoleResponse disassociateDRTRole(software.amazon.awssdk.services.shield.model.DisassociateDrtRoleRequest) throws software.amazon.awssdk.services.shield.model.InternalErrorException, software.amazon.awssdk.services.shield.model.InvalidOperationException, software.amazon.awssdk.services.shield.model.OptimisticLockException, software.amazon.awssdk.services.shield.model.ResourceNotFoundException, software.amazon.awssdk.awscore.exception.AwsServiceException, software.amazon.awssdk.core.exception.SdkClientException, software.amazon.awssdk.services.shield.model.ShieldException;
    Code:
       0: invokestatic  #13                 // Method software/amazon/awssdk/protocols/json/JsonOperationMetadata.builder:()Lsoftware/amazon/awssdk/protocols/json/JsonOperationMetadata$Builder;
       3: iconst_0
       4: invokevirtual #14                 // Method software/amazon/awssdk/protocols/json/JsonOperationMetadata$Builder.hasStreamingSuccessResponse:(Z)Lsoftware/amazon/awssdk/protocols/json/JsonOperationMetadata$Builder;
       7: iconst_1
       8: invokevirtual #15                 // Method software/amazon/awssdk/protocols/json/JsonOperationMetadata$Builder.isPayloadJson:(Z)Lsoftware/amazon/awssdk/protocols/json/JsonOperationMetadata$Builder;
      11: invokevirtual #16                 // Method software/amazon/awssdk/protocols/json/JsonOperationMetadata$Builder.build:()Lsoftware/amazon/awssdk/protocols/json/JsonOperationMetadata;
      14: astore_2
      15: aload_0
      16: getfield      #10                 // Field protocolFactory:Lsoftware/amazon/awssdk/protocols/json/AwsJsonProtocolFactory;
      19: aload_2
      20: invokedynamic #87,  0             // InvokeDynamic #12:get:()Ljava/util/function/Supplier;
      25: invokevirtual #18                 // Method software/amazon/awssdk/protocols/json/AwsJsonProtocolFactory.createResponseHandler:(Lsoftware/amazon/awssdk/protocols/json/JsonOperationMetadata;Ljava/util/function/Supplier;)Lsoftware/amazon/awssdk/core/http/HttpResponseHandler;
      28: astore_3
      29: aload_0
      30: aload_0
      31: getfield      #10                 // Field protocolFactory:Lsoftware/amazon/awssdk/protocols/json/AwsJsonProtocolFactory;
      34: aload_2
      35: invokespecial #19                 // Method createErrorResponseHandler:(Lsoftware/amazon/awssdk/protocols/json/BaseAwsJsonProtocolFactory;Lsoftware/amazon/awssdk/protocols/json/JsonOperationMetadata;)Lsoftware/amazon/awssdk/core/http/HttpResponseHandler;
      38: astore        4
      40: aload_0
      41: getfield      #4                  // Field clientHandler:Lsoftware/amazon/awssdk/core/client/handler/SyncClientHandler;
      44: new           #20                 // class software/amazon/awssdk/core/client/handler/ClientExecutionParams
      47: dup
      48: invokespecial #21                 // Method software/amazon/awssdk/core/client/handler/ClientExecutionParams."<init>":()V
      51: ldc           #88                 // String DisassociateDRTRole
      53: invokevirtual #23                 // Method software/amazon/awssdk/core/client/handler/ClientExecutionParams.withOperationName:(Ljava/lang/String;)Lsoftware/amazon/awssdk/core/client/handler/ClientExecutionParams;
      56: aload_3
      57: invokevirtual #24                 // Method software/amazon/awssdk/core/client/handler/ClientExecutionParams.withResponseHandler:(Lsoftware/amazon/awssdk/core/http/HttpResponseHandler;)Lsoftware/amazon/awssdk/core/client/handler/ClientExecutionParams;
      60: aload         4
      62: invokevirtual #25                 // Method software/amazon/awssdk/core/client/handler/ClientExecutionParams.withErrorResponseHandler:(Lsoftware/amazon/awssdk/core/http/HttpResponseHandler;)Lsoftware/amazon/awssdk/core/client/handler/ClientExecutionParams;
      65: aload_1
      66: invokevirtual #26                 // Method software/amazon/awssdk/core/client/handler/ClientExecutionParams.withInput:(Lsoftware/amazon/awssdk/core/SdkRequest;)Lsoftware/amazon/awssdk/core/client/handler/ClientExecutionParams;
      69: new           #89                 // class software/amazon/awssdk/services/shield/transform/DisassociateDrtRoleRequestMarshaller
      72: dup
      73: aload_0
      74: getfield      #10                 // Field protocolFactory:Lsoftware/amazon/awssdk/protocols/json/AwsJsonProtocolFactory;
      77: invokespecial #90                 // Method software/amazon/awssdk/services/shield/transform/DisassociateDrtRoleRequestMarshaller."<init>":(Lsoftware/amazon/awssdk/protocols/json/BaseAwsJsonProtocolFactory;)V
      80: invokevirtual #29                 // Method software/amazon/awssdk/core/client/handler/ClientExecutionParams.withMarshaller:(Lsoftware/amazon/awssdk/core/runtime/transform/Marshaller;)Lsoftware/amazon/awssdk/core/client/handler/ClientExecutionParams;
      83: invokeinterface #30,  2           // InterfaceMethod software/amazon/awssdk/core/client/handler/SyncClientHandler.execute:(Lsoftware/amazon/awssdk/core/client/handler/ClientExecutionParams;)Lsoftware/amazon/awssdk/core/SdkResponse;
      88: checkcast     #91                 // class software/amazon/awssdk/services/shield/model/DisassociateDrtRoleResponse
      91: areturn

  public software.amazon.awssdk.services.shield.model.DisassociateHealthCheckResponse disassociateHealthCheck(software.amazon.awssdk.services.shield.model.DisassociateHealthCheckRequest) throws software.amazon.awssdk.services.shield.model.InternalErrorException, software.amazon.awssdk.services.shield.model.InvalidParameterException, software.amazon.awssdk.services.shield.model.ResourceNotFoundException, software.amazon.awssdk.services.shield.model.OptimisticLockException, software.amazon.awssdk.awscore.exception.AwsServiceException, software.amazon.awssdk.core.exception.SdkClientException, software.amazon.awssdk.services.shield.model.ShieldException;
    Code:
       0: invokestatic  #13                 // Method software/amazon/awssdk/protocols/json/JsonOperationMetadata.builder:()Lsoftware/amazon/awssdk/protocols/json/JsonOperationMetadata$Builder;
       3: iconst_0
       4: invokevirtual #14                 // Method software/amazon/awssdk/protocols/json/JsonOperationMetadata$Builder.hasStreamingSuccessResponse:(Z)Lsoftware/amazon/awssdk/protocols/json/JsonOperationMetadata$Builder;
       7: iconst_1
       8: invokevirtual #15                 // Method software/amazon/awssdk/protocols/json/JsonOperationMetadata$Builder.isPayloadJson:(Z)Lsoftware/amazon/awssdk/protocols/json/JsonOperationMetadata$Builder;
      11: invokevirtual #16                 // Method software/amazon/awssdk/protocols/json/JsonOperationMetadata$Builder.build:()Lsoftware/amazon/awssdk/protocols/json/JsonOperationMetadata;
      14: astore_2
      15: aload_0
      16: getfield      #10                 // Field protocolFactory:Lsoftware/amazon/awssdk/protocols/json/AwsJsonProtocolFactory;
      19: aload_2
      20: invokedynamic #92,  0             // InvokeDynamic #13:get:()Ljava/util/function/Supplier;
      25: invokevirtual #18                 // Method software/amazon/awssdk/protocols/json/AwsJsonProtocolFactory.createResponseHandler:(Lsoftware/amazon/awssdk/protocols/json/JsonOperationMetadata;Ljava/util/function/Supplier;)Lsoftware/amazon/awssdk/core/http/HttpResponseHandler;
      28: astore_3
      29: aload_0
      30: aload_0
      31: getfield      #10                 // Field protocolFactory:Lsoftware/amazon/awssdk/protocols/json/AwsJsonProtocolFactory;
      34: aload_2
      35: invokespecial #19                 // Method createErrorResponseHandler:(Lsoftware/amazon/awssdk/protocols/json/BaseAwsJsonProtocolFactory;Lsoftware/amazon/awssdk/protocols/json/JsonOperationMetadata;)Lsoftware/amazon/awssdk/core/http/HttpResponseHandler;
      38: astore        4
      40: aload_0
      41: getfield      #4                  // Field clientHandler:Lsoftware/amazon/awssdk/core/client/handler/SyncClientHandler;
      44: new           #20                 // class software/amazon/awssdk/core/client/handler/ClientExecutionParams
      47: dup
      48: invokespecial #21                 // Method software/amazon/awssdk/core/client/handler/ClientExecutionParams."<init>":()V
      51: ldc           #93                 // String DisassociateHealthCheck
      53: invokevirtual #23                 // Method software/amazon/awssdk/core/client/handler/ClientExecutionParams.withOperationName:(Ljava/lang/String;)Lsoftware/amazon/awssdk/core/client/handler/ClientExecutionParams;
      56: aload_3
      57: invokevirtual #24                 // Method software/amazon/awssdk/core/client/handler/ClientExecutionParams.withResponseHandler:(Lsoftware/amazon/awssdk/core/http/HttpResponseHandler;)Lsoftware/amazon/awssdk/core/client/handler/ClientExecutionParams;
      60: aload         4
      62: invokevirtual #25                 // Method software/amazon/awssdk/core/client/handler/ClientExecutionParams.withErrorResponseHandler:(Lsoftware/amazon/awssdk/core/http/HttpResponseHandler;)Lsoftware/amazon/awssdk/core/client/handler/ClientExecutionParams;
      65: aload_1
      66: invokevirtual #26                 // Method software/amazon/awssdk/core/client/handler/ClientExecutionParams.withInput:(Lsoftware/amazon/awssdk/core/SdkRequest;)Lsoftware/amazon/awssdk/core/client/handler/ClientExecutionParams;
      69: new           #94                 // class software/amazon/awssdk/services/shield/transform/DisassociateHealthCheckRequestMarshaller
      72: dup
      73: aload_0
      74: getfield      #10                 // Field protocolFactory:Lsoftware/amazon/awssdk/protocols/json/AwsJsonProtocolFactory;
      77: invokespecial #95                 // Method software/amazon/awssdk/services/shield/transform/DisassociateHealthCheckRequestMarshaller."<init>":(Lsoftware/amazon/awssdk/protocols/json/BaseAwsJsonProtocolFactory;)V
      80: invokevirtual #29                 // Method software/amazon/awssdk/core/client/handler/ClientExecutionParams.withMarshaller:(Lsoftware/amazon/awssdk/core/runtime/transform/Marshaller;)Lsoftware/amazon/awssdk/core/client/handler/ClientExecutionParams;
      83: invokeinterface #30,  2           // InterfaceMethod software/amazon/awssdk/core/client/handler/SyncClientHandler.execute:(Lsoftware/amazon/awssdk/core/client/handler/ClientExecutionParams;)Lsoftware/amazon/awssdk/core/SdkResponse;
      88: checkcast     #96                 // class software/amazon/awssdk/services/shield/model/DisassociateHealthCheckResponse
      91: areturn

  public software.amazon.awssdk.services.shield.model.GetSubscriptionStateResponse getSubscriptionState(software.amazon.awssdk.services.shield.model.GetSubscriptionStateRequest) throws software.amazon.awssdk.services.shield.model.InternalErrorException, software.amazon.awssdk.awscore.exception.AwsServiceException, software.amazon.awssdk.core.exception.SdkClientException, software.amazon.awssdk.services.shield.model.ShieldException;
    Code:
       0: invokestatic  #13                 // Method software/amazon/awssdk/protocols/json/JsonOperationMetadata.builder:()Lsoftware/amazon/awssdk/protocols/json/JsonOperationMetadata$Builder;
       3: iconst_0
       4: invokevirtual #14                 // Method software/amazon/awssdk/protocols/json/JsonOperationMetadata$Builder.hasStreamingSuccessResponse:(Z)Lsoftware/amazon/awssdk/protocols/json/JsonOperationMetadata$Builder;
       7: iconst_1
       8: invokevirtual #15                 // Method software/amazon/awssdk/protocols/json/JsonOperationMetadata$Builder.isPayloadJson:(Z)Lsoftware/amazon/awssdk/protocols/json/JsonOperationMetadata$Builder;
      11: invokevirtual #16                 // Method software/amazon/awssdk/protocols/json/JsonOperationMetadata$Builder.build:()Lsoftware/amazon/awssdk/protocols/json/JsonOperationMetadata;
      14: astore_2
      15: aload_0
      16: getfield      #10                 // Field protocolFactory:Lsoftware/amazon/awssdk/protocols/json/AwsJsonProtocolFactory;
      19: aload_2
      20: invokedynamic #97,  0             // InvokeDynamic #14:get:()Ljava/util/function/Supplier;
      25: invokevirtual #18                 // Method software/amazon/awssdk/protocols/json/AwsJsonProtocolFactory.createResponseHandler:(Lsoftware/amazon/awssdk/protocols/json/JsonOperationMetadata;Ljava/util/function/Supplier;)Lsoftware/amazon/awssdk/core/http/HttpResponseHandler;
      28: astore_3
      29: aload_0
      30: aload_0
      31: getfield      #10                 // Field protocolFactory:Lsoftware/amazon/awssdk/protocols/json/AwsJsonProtocolFactory;
      34: aload_2
      35: invokespecial #19                 // Method createErrorResponseHandler:(Lsoftware/amazon/awssdk/protocols/json/BaseAwsJsonProtocolFactory;Lsoftware/amazon/awssdk/protocols/json/JsonOperationMetadata;)Lsoftware/amazon/awssdk/core/http/HttpResponseHandler;
      38: astore        4
      40: aload_0
      41: getfield      #4                  // Field clientHandler:Lsoftware/amazon/awssdk/core/client/handler/SyncClientHandler;
      44: new           #20                 // class software/amazon/awssdk/core/client/handler/ClientExecutionParams
      47: dup
      48: invokespecial #21                 // Method software/amazon/awssdk/core/client/handler/ClientExecutionParams."<init>":()V
      51: ldc           #98                 // String GetSubscriptionState
      53: invokevirtual #23                 // Method software/amazon/awssdk/core/client/handler/ClientExecutionParams.withOperationName:(Ljava/lang/String;)Lsoftware/amazon/awssdk/core/client/handler/ClientExecutionParams;
      56: aload_3
      57: invokevirtual #24                 // Method software/amazon/awssdk/core/client/handler/ClientExecutionParams.withResponseHandler:(Lsoftware/amazon/awssdk/core/http/HttpResponseHandler;)Lsoftware/amazon/awssdk/core/client/handler/ClientExecutionParams;
      60: aload         4
      62: invokevirtual #25                 // Method software/amazon/awssdk/core/client/handler/ClientExecutionParams.withErrorResponseHandler:(Lsoftware/amazon/awssdk/core/http/HttpResponseHandler;)Lsoftware/amazon/awssdk/core/client/handler/ClientExecutionParams;
      65: aload_1
      66: invokevirtual #26                 // Method software/amazon/awssdk/core/client/handler/ClientExecutionParams.withInput:(Lsoftware/amazon/awssdk/core/SdkRequest;)Lsoftware/amazon/awssdk/core/client/handler/ClientExecutionParams;
      69: new           #99                 // class software/amazon/awssdk/services/shield/transform/GetSubscriptionStateRequestMarshaller
      72: dup
      73: aload_0
      74: getfield      #10                 // Field protocolFactory:Lsoftware/amazon/awssdk/protocols/json/AwsJsonProtocolFactory;
      77: invokespecial #100                // Method software/amazon/awssdk/services/shield/transform/GetSubscriptionStateRequestMarshaller."<init>":(Lsoftware/amazon/awssdk/protocols/json/BaseAwsJsonProtocolFactory;)V
      80: invokevirtual #29                 // Method software/amazon/awssdk/core/client/handler/ClientExecutionParams.withMarshaller:(Lsoftware/amazon/awssdk/core/runtime/transform/Marshaller;)Lsoftware/amazon/awssdk/core/client/handler/ClientExecutionParams;
      83: invokeinterface #30,  2           // InterfaceMethod software/amazon/awssdk/core/client/handler/SyncClientHandler.execute:(Lsoftware/amazon/awssdk/core/client/handler/ClientExecutionParams;)Lsoftware/amazon/awssdk/core/SdkResponse;
      88: checkcast     #101                // class software/amazon/awssdk/services/shield/model/GetSubscriptionStateResponse
      91: areturn

  public software.amazon.awssdk.services.shield.model.ListAttacksResponse listAttacks(software.amazon.awssdk.services.shield.model.ListAttacksRequest) throws software.amazon.awssdk.services.shield.model.InternalErrorException, software.amazon.awssdk.services.shield.model.InvalidParameterException, software.amazon.awssdk.services.shield.model.InvalidOperationException, software.amazon.awssdk.awscore.exception.AwsServiceException, software.amazon.awssdk.core.exception.SdkClientException, software.amazon.awssdk.services.shield.model.ShieldException;
    Code:
       0: invokestatic  #13                 // Method software/amazon/awssdk/protocols/json/JsonOperationMetadata.builder:()Lsoftware/amazon/awssdk/protocols/json/JsonOperationMetadata$Builder;
       3: iconst_0
       4: invokevirtual #14                 // Method software/amazon/awssdk/protocols/json/JsonOperationMetadata$Builder.hasStreamingSuccessResponse:(Z)Lsoftware/amazon/awssdk/protocols/json/JsonOperationMetadata$Builder;
       7: iconst_1
       8: invokevirtual #15                 // Method software/amazon/awssdk/protocols/json/JsonOperationMetadata$Builder.isPayloadJson:(Z)Lsoftware/amazon/awssdk/protocols/json/JsonOperationMetadata$Builder;
      11: invokevirtual #16                 // Method software/amazon/awssdk/protocols/json/JsonOperationMetadata$Builder.build:()Lsoftware/amazon/awssdk/protocols/json/JsonOperationMetadata;
      14: astore_2
      15: aload_0
      16: getfield      #10                 // Field protocolFactory:Lsoftware/amazon/awssdk/protocols/json/AwsJsonProtocolFactory;
      19: aload_2
      20: invokedynamic #102,  0            // InvokeDynamic #15:get:()Ljava/util/function/Supplier;
      25: invokevirtual #18                 // Method software/amazon/awssdk/protocols/json/AwsJsonProtocolFactory.createResponseHandler:(Lsoftware/amazon/awssdk/protocols/json/JsonOperationMetadata;Ljava/util/function/Supplier;)Lsoftware/amazon/awssdk/core/http/HttpResponseHandler;
      28: astore_3
      29: aload_0
      30: aload_0
      31: getfield      #10                 // Field protocolFactory:Lsoftware/amazon/awssdk/protocols/json/AwsJsonProtocolFactory;
      34: aload_2
      35: invokespecial #19                 // Method createErrorResponseHandler:(Lsoftware/amazon/awssdk/protocols/json/BaseAwsJsonProtocolFactory;Lsoftware/amazon/awssdk/protocols/json/JsonOperationMetadata;)Lsoftware/amazon/awssdk/core/http/HttpResponseHandler;
      38: astore        4
      40: aload_0
      41: getfield      #4                  // Field clientHandler:Lsoftware/amazon/awssdk/core/client/handler/SyncClientHandler;
      44: new           #20                 // class software/amazon/awssdk/core/client/handler/ClientExecutionParams
      47: dup
      48: invokespecial #21                 // Method software/amazon/awssdk/core/client/handler/ClientExecutionParams."<init>":()V
      51: ldc           #103                // String ListAttacks
      53: invokevirtual #23                 // Method software/amazon/awssdk/core/client/handler/ClientExecutionParams.withOperationName:(Ljava/lang/String;)Lsoftware/amazon/awssdk/core/client/handler/ClientExecutionParams;
      56: aload_3
      57: invokevirtual #24                 // Method software/amazon/awssdk/core/client/handler/ClientExecutionParams.withResponseHandler:(Lsoftware/amazon/awssdk/core/http/HttpResponseHandler;)Lsoftware/amazon/awssdk/core/client/handler/ClientExecutionParams;
      60: aload         4
      62: invokevirtual #25                 // Method software/amazon/awssdk/core/client/handler/ClientExecutionParams.withErrorResponseHandler:(Lsoftware/amazon/awssdk/core/http/HttpResponseHandler;)Lsoftware/amazon/awssdk/core/client/handler/ClientExecutionParams;
      65: aload_1
      66: invokevirtual #26                 // Method software/amazon/awssdk/core/client/handler/ClientExecutionParams.withInput:(Lsoftware/amazon/awssdk/core/SdkRequest;)Lsoftware/amazon/awssdk/core/client/handler/ClientExecutionParams;
      69: new           #104                // class software/amazon/awssdk/services/shield/transform/ListAttacksRequestMarshaller
      72: dup
      73: aload_0
      74: getfield      #10                 // Field protocolFactory:Lsoftware/amazon/awssdk/protocols/json/AwsJsonProtocolFactory;
      77: invokespecial #105                // Method software/amazon/awssdk/services/shield/transform/ListAttacksRequestMarshaller."<init>":(Lsoftware/amazon/awssdk/protocols/json/BaseAwsJsonProtocolFactory;)V
      80: invokevirtual #29                 // Method software/amazon/awssdk/core/client/handler/ClientExecutionParams.withMarshaller:(Lsoftware/amazon/awssdk/core/runtime/transform/Marshaller;)Lsoftware/amazon/awssdk/core/client/handler/ClientExecutionParams;
      83: invokeinterface #30,  2           // InterfaceMethod software/amazon/awssdk/core/client/handler/SyncClientHandler.execute:(Lsoftware/amazon/awssdk/core/client/handler/ClientExecutionParams;)Lsoftware/amazon/awssdk/core/SdkResponse;
      88: checkcast     #106                // class software/amazon/awssdk/services/shield/model/ListAttacksResponse
      91: areturn

  public software.amazon.awssdk.services.shield.model.ListProtectionsResponse listProtections(software.amazon.awssdk.services.shield.model.ListProtectionsRequest) throws software.amazon.awssdk.services.shield.model.InternalErrorException, software.amazon.awssdk.services.shield.model.ResourceNotFoundException, software.amazon.awssdk.services.shield.model.InvalidPaginationTokenException, software.amazon.awssdk.awscore.exception.AwsServiceException, software.amazon.awssdk.core.exception.SdkClientException, software.amazon.awssdk.services.shield.model.ShieldException;
    Code:
       0: invokestatic  #13                 // Method software/amazon/awssdk/protocols/json/JsonOperationMetadata.builder:()Lsoftware/amazon/awssdk/protocols/json/JsonOperationMetadata$Builder;
       3: iconst_0
       4: invokevirtual #14                 // Method software/amazon/awssdk/protocols/json/JsonOperationMetadata$Builder.hasStreamingSuccessResponse:(Z)Lsoftware/amazon/awssdk/protocols/json/JsonOperationMetadata$Builder;
       7: iconst_1
       8: invokevirtual #15                 // Method software/amazon/awssdk/protocols/json/JsonOperationMetadata$Builder.isPayloadJson:(Z)Lsoftware/amazon/awssdk/protocols/json/JsonOperationMetadata$Builder;
      11: invokevirtual #16                 // Method software/amazon/awssdk/protocols/json/JsonOperationMetadata$Builder.build:()Lsoftware/amazon/awssdk/protocols/json/JsonOperationMetadata;
      14: astore_2
      15: aload_0
      16: getfield      #10                 // Field protocolFactory:Lsoftware/amazon/awssdk/protocols/json/AwsJsonProtocolFactory;
      19: aload_2
      20: invokedynamic #107,  0            // InvokeDynamic #16:get:()Ljava/util/function/Supplier;
      25: invokevirtual #18                 // Method software/amazon/awssdk/protocols/json/AwsJsonProtocolFactory.createResponseHandler:(Lsoftware/amazon/awssdk/protocols/json/JsonOperationMetadata;Ljava/util/function/Supplier;)Lsoftware/amazon/awssdk/core/http/HttpResponseHandler;
      28: astore_3
      29: aload_0
      30: aload_0
      31: getfield      #10                 // Field protocolFactory:Lsoftware/amazon/awssdk/protocols/json/AwsJsonProtocolFactory;
      34: aload_2
      35: invokespecial #19                 // Method createErrorResponseHandler:(Lsoftware/amazon/awssdk/protocols/json/BaseAwsJsonProtocolFactory;Lsoftware/amazon/awssdk/protocols/json/JsonOperationMetadata;)Lsoftware/amazon/awssdk/core/http/HttpResponseHandler;
      38: astore        4
      40: aload_0
      41: getfield      #4                  // Field clientHandler:Lsoftware/amazon/awssdk/core/client/handler/SyncClientHandler;
      44: new           #20                 // class software/amazon/awssdk/core/client/handler/ClientExecutionParams
      47: dup
      48: invokespecial #21                 // Method software/amazon/awssdk/core/client/handler/ClientExecutionParams."<init>":()V
      51: ldc           #108                // String ListProtections
      53: invokevirtual #23                 // Method software/amazon/awssdk/core/client/handler/ClientExecutionParams.withOperationName:(Ljava/lang/String;)Lsoftware/amazon/awssdk/core/client/handler/ClientExecutionParams;
      56: aload_3
      57: invokevirtual #24                 // Method software/amazon/awssdk/core/client/handler/ClientExecutionParams.withResponseHandler:(Lsoftware/amazon/awssdk/core/http/HttpResponseHandler;)Lsoftware/amazon/awssdk/core/client/handler/ClientExecutionParams;
      60: aload         4
      62: invokevirtual #25                 // Method software/amazon/awssdk/core/client/handler/ClientExecutionParams.withErrorResponseHandler:(Lsoftware/amazon/awssdk/core/http/HttpResponseHandler;)Lsoftware/amazon/awssdk/core/client/handler/ClientExecutionParams;
      65: aload_1
      66: invokevirtual #26                 // Method software/amazon/awssdk/core/client/handler/ClientExecutionParams.withInput:(Lsoftware/amazon/awssdk/core/SdkRequest;)Lsoftware/amazon/awssdk/core/client/handler/ClientExecutionParams;
      69: new           #109                // class software/amazon/awssdk/services/shield/transform/ListProtectionsRequestMarshaller
      72: dup
      73: aload_0
      74: getfield      #10                 // Field protocolFactory:Lsoftware/amazon/awssdk/protocols/json/AwsJsonProtocolFactory;
      77: invokespecial #110                // Method software/amazon/awssdk/services/shield/transform/ListProtectionsRequestMarshaller."<init>":(Lsoftware/amazon/awssdk/protocols/json/BaseAwsJsonProtocolFactory;)V
      80: invokevirtual #29                 // Method software/amazon/awssdk/core/client/handler/ClientExecutionParams.withMarshaller:(Lsoftware/amazon/awssdk/core/runtime/transform/Marshaller;)Lsoftware/amazon/awssdk/core/client/handler/ClientExecutionParams;
      83: invokeinterface #30,  2           // InterfaceMethod software/amazon/awssdk/core/client/handler/SyncClientHandler.execute:(Lsoftware/amazon/awssdk/core/client/handler/ClientExecutionParams;)Lsoftware/amazon/awssdk/core/SdkResponse;
      88: checkcast     #111                // class software/amazon/awssdk/services/shield/model/ListProtectionsResponse
      91: areturn

  public software.amazon.awssdk.services.shield.model.UpdateEmergencyContactSettingsResponse updateEmergencyContactSettings(software.amazon.awssdk.services.shield.model.UpdateEmergencyContactSettingsRequest) throws software.amazon.awssdk.services.shield.model.InternalErrorException, software.amazon.awssdk.services.shield.model.InvalidParameterException, software.amazon.awssdk.services.shield.model.OptimisticLockException, software.amazon.awssdk.services.shield.model.ResourceNotFoundException, software.amazon.awssdk.awscore.exception.AwsServiceException, software.amazon.awssdk.core.exception.SdkClientException, software.amazon.awssdk.services.shield.model.ShieldException;
    Code:
       0: invokestatic  #13                 // Method software/amazon/awssdk/protocols/json/JsonOperationMetadata.builder:()Lsoftware/amazon/awssdk/protocols/json/JsonOperationMetadata$Builder;
       3: iconst_0
       4: invokevirtual #14                 // Method software/amazon/awssdk/protocols/json/JsonOperationMetadata$Builder.hasStreamingSuccessResponse:(Z)Lsoftware/amazon/awssdk/protocols/json/JsonOperationMetadata$Builder;
       7: iconst_1
       8: invokevirtual #15                 // Method software/amazon/awssdk/protocols/json/JsonOperationMetadata$Builder.isPayloadJson:(Z)Lsoftware/amazon/awssdk/protocols/json/JsonOperationMetadata$Builder;
      11: invokevirtual #16                 // Method software/amazon/awssdk/protocols/json/JsonOperationMetadata$Builder.build:()Lsoftware/amazon/awssdk/protocols/json/JsonOperationMetadata;
      14: astore_2
      15: aload_0
      16: getfield      #10                 // Field protocolFactory:Lsoftware/amazon/awssdk/protocols/json/AwsJsonProtocolFactory;
      19: aload_2
      20: invokedynamic #112,  0            // InvokeDynamic #17:get:()Ljava/util/function/Supplier;
      25: invokevirtual #18                 // Method software/amazon/awssdk/protocols/json/AwsJsonProtocolFactory.createResponseHandler:(Lsoftware/amazon/awssdk/protocols/json/JsonOperationMetadata;Ljava/util/function/Supplier;)Lsoftware/amazon/awssdk/core/http/HttpResponseHandler;
      28: astore_3
      29: aload_0
      30: aload_0
      31: getfield      #10                 // Field protocolFactory:Lsoftware/amazon/awssdk/protocols/json/AwsJsonProtocolFactory;
      34: aload_2
      35: invokespecial #19                 // Method createErrorResponseHandler:(Lsoftware/amazon/awssdk/protocols/json/BaseAwsJsonProtocolFactory;Lsoftware/amazon/awssdk/protocols/json/JsonOperationMetadata;)Lsoftware/amazon/awssdk/core/http/HttpResponseHandler;
      38: astore        4
      40: aload_0
      41: getfield      #4                  // Field clientHandler:Lsoftware/amazon/awssdk/core/client/handler/SyncClientHandler;
      44: new           #20                 // class software/amazon/awssdk/core/client/handler/ClientExecutionParams
      47: dup
      48: invokespecial #21                 // Method software/amazon/awssdk/core/client/handler/ClientExecutionParams."<init>":()V
      51: ldc           #113                // String UpdateEmergencyContactSettings
      53: invokevirtual #23                 // Method software/amazon/awssdk/core/client/handler/ClientExecutionParams.withOperationName:(Ljava/lang/String;)Lsoftware/amazon/awssdk/core/client/handler/ClientExecutionParams;
      56: aload_3
      57: invokevirtual #24                 // Method software/amazon/awssdk/core/client/handler/ClientExecutionParams.withResponseHandler:(Lsoftware/amazon/awssdk/core/http/HttpResponseHandler;)Lsoftware/amazon/awssdk/core/client/handler/ClientExecutionParams;
      60: aload         4
      62: invokevirtual #25                 // Method software/amazon/awssdk/core/client/handler/ClientExecutionParams.withErrorResponseHandler:(Lsoftware/amazon/awssdk/core/http/HttpResponseHandler;)Lsoftware/amazon/awssdk/core/client/handler/ClientExecutionParams;
      65: aload_1
      66: invokevirtual #26                 // Method software/amazon/awssdk/core/client/handler/ClientExecutionParams.withInput:(Lsoftware/amazon/awssdk/core/SdkRequest;)Lsoftware/amazon/awssdk/core/client/handler/ClientExecutionParams;
      69: new           #114                // class software/amazon/awssdk/services/shield/transform/UpdateEmergencyContactSettingsRequestMarshaller
      72: dup
      73: aload_0
      74: getfield      #10                 // Field protocolFactory:Lsoftware/amazon/awssdk/protocols/json/AwsJsonProtocolFactory;
      77: invokespecial #115                // Method software/amazon/awssdk/services/shield/transform/UpdateEmergencyContactSettingsRequestMarshaller."<init>":(Lsoftware/amazon/awssdk/protocols/json/BaseAwsJsonProtocolFactory;)V
      80: invokevirtual #29                 // Method software/amazon/awssdk/core/client/handler/ClientExecutionParams.withMarshaller:(Lsoftware/amazon/awssdk/core/runtime/transform/Marshaller;)Lsoftware/amazon/awssdk/core/client/handler/ClientExecutionParams;
      83: invokeinterface #30,  2           // InterfaceMethod software/amazon/awssdk/core/client/handler/SyncClientHandler.execute:(Lsoftware/amazon/awssdk/core/client/handler/ClientExecutionParams;)Lsoftware/amazon/awssdk/core/SdkResponse;
      88: checkcast     #116                // class software/amazon/awssdk/services/shield/model/UpdateEmergencyContactSettingsResponse
      91: areturn

  public software.amazon.awssdk.services.shield.model.UpdateSubscriptionResponse updateSubscription(software.amazon.awssdk.services.shield.model.UpdateSubscriptionRequest) throws software.amazon.awssdk.services.shield.model.InternalErrorException, software.amazon.awssdk.services.shield.model.LockedSubscriptionException, software.amazon.awssdk.services.shield.model.ResourceNotFoundException, software.amazon.awssdk.services.shield.model.InvalidParameterException, software.amazon.awssdk.services.shield.model.OptimisticLockException, software.amazon.awssdk.awscore.exception.AwsServiceException, software.amazon.awssdk.core.exception.SdkClientException, software.amazon.awssdk.services.shield.model.ShieldException;
    Code:
       0: invokestatic  #13                 // Method software/amazon/awssdk/protocols/json/JsonOperationMetadata.builder:()Lsoftware/amazon/awssdk/protocols/json/JsonOperationMetadata$Builder;
       3: iconst_0
       4: invokevirtual #14                 // Method software/amazon/awssdk/protocols/json/JsonOperationMetadata$Builder.hasStreamingSuccessResponse:(Z)Lsoftware/amazon/awssdk/protocols/json/JsonOperationMetadata$Builder;
       7: iconst_1
       8: invokevirtual #15                 // Method software/amazon/awssdk/protocols/json/JsonOperationMetadata$Builder.isPayloadJson:(Z)Lsoftware/amazon/awssdk/protocols/json/JsonOperationMetadata$Builder;
      11: invokevirtual #16                 // Method software/amazon/awssdk/protocols/json/JsonOperationMetadata$Builder.build:()Lsoftware/amazon/awssdk/protocols/json/JsonOperationMetadata;
      14: astore_2
      15: aload_0
      16: getfield      #10                 // Field protocolFactory:Lsoftware/amazon/awssdk/protocols/json/AwsJsonProtocolFactory;
      19: aload_2
      20: invokedynamic #117,  0            // InvokeDynamic #18:get:()Ljava/util/function/Supplier;
      25: invokevirtual #18                 // Method software/amazon/awssdk/protocols/json/AwsJsonProtocolFactory.createResponseHandler:(Lsoftware/amazon/awssdk/protocols/json/JsonOperationMetadata;Ljava/util/function/Supplier;)Lsoftware/amazon/awssdk/core/http/HttpResponseHandler;
      28: astore_3
      29: aload_0
      30: aload_0
      31: getfield      #10                 // Field protocolFactory:Lsoftware/amazon/awssdk/protocols/json/AwsJsonProtocolFactory;
      34: aload_2
      35: invokespecial #19                 // Method createErrorResponseHandler:(Lsoftware/amazon/awssdk/protocols/json/BaseAwsJsonProtocolFactory;Lsoftware/amazon/awssdk/protocols/json/JsonOperationMetadata;)Lsoftware/amazon/awssdk/core/http/HttpResponseHandler;
      38: astore        4
      40: aload_0
      41: getfield      #4                  // Field clientHandler:Lsoftware/amazon/awssdk/core/client/handler/SyncClientHandler;
      44: new           #20                 // class software/amazon/awssdk/core/client/handler/ClientExecutionParams
      47: dup
      48: invokespecial #21                 // Method software/amazon/awssdk/core/client/handler/ClientExecutionParams."<init>":()V
      51: ldc           #118                // String UpdateSubscription
      53: invokevirtual #23                 // Method software/amazon/awssdk/core/client/handler/ClientExecutionParams.withOperationName:(Ljava/lang/String;)Lsoftware/amazon/awssdk/core/client/handler/ClientExecutionParams;
      56: aload_3
      57: invokevirtual #24                 // Method software/amazon/awssdk/core/client/handler/ClientExecutionParams.withResponseHandler:(Lsoftware/amazon/awssdk/core/http/HttpResponseHandler;)Lsoftware/amazon/awssdk/core/client/handler/ClientExecutionParams;
      60: aload         4
      62: invokevirtual #25                 // Method software/amazon/awssdk/core/client/handler/ClientExecutionParams.withErrorResponseHandler:(Lsoftware/amazon/awssdk/core/http/HttpResponseHandler;)Lsoftware/amazon/awssdk/core/client/handler/ClientExecutionParams;
      65: aload_1
      66: invokevirtual #26                 // Method software/amazon/awssdk/core/client/handler/ClientExecutionParams.withInput:(Lsoftware/amazon/awssdk/core/SdkRequest;)Lsoftware/amazon/awssdk/core/client/handler/ClientExecutionParams;
      69: new           #119                // class software/amazon/awssdk/services/shield/transform/UpdateSubscriptionRequestMarshaller
      72: dup
      73: aload_0
      74: getfield      #10                 // Field protocolFactory:Lsoftware/amazon/awssdk/protocols/json/AwsJsonProtocolFactory;
      77: invokespecial #120                // Method software/amazon/awssdk/services/shield/transform/UpdateSubscriptionRequestMarshaller."<init>":(Lsoftware/amazon/awssdk/protocols/json/BaseAwsJsonProtocolFactory;)V
      80: invokevirtual #29                 // Method software/amazon/awssdk/core/client/handler/ClientExecutionParams.withMarshaller:(Lsoftware/amazon/awssdk/core/runtime/transform/Marshaller;)Lsoftware/amazon/awssdk/core/client/handler/ClientExecutionParams;
      83: invokeinterface #30,  2           // InterfaceMethod software/amazon/awssdk/core/client/handler/SyncClientHandler.execute:(Lsoftware/amazon/awssdk/core/client/handler/ClientExecutionParams;)Lsoftware/amazon/awssdk/core/SdkResponse;
      88: checkcast     #121                // class software/amazon/awssdk/services/shield/model/UpdateSubscriptionResponse
      91: areturn

  private software.amazon.awssdk.core.http.HttpResponseHandler<software.amazon.awssdk.awscore.exception.AwsServiceException> createErrorResponseHandler(software.amazon.awssdk.protocols.json.BaseAwsJsonProtocolFactory, software.amazon.awssdk.protocols.json.JsonOperationMetadata);
    Code:
       0: aload_1
       1: aload_2
       2: invokevirtual #122                // Method software/amazon/awssdk/protocols/json/BaseAwsJsonProtocolFactory.createErrorResponseHandler:(Lsoftware/amazon/awssdk/protocols/json/JsonOperationMetadata;)Lsoftware/amazon/awssdk/core/http/HttpResponseHandler;
       5: areturn

  private <T extends software.amazon.awssdk.protocols.json.BaseAwsJsonProtocolFactory$Builder<T>> T init(T);
    Code:
       0: aload_1
       1: aload_0
       2: getfield      #5                  // Field clientConfiguration:Lsoftware/amazon/awssdk/core/client/config/SdkClientConfiguration;
       5: invokevirtual #123                // Method software/amazon/awssdk/protocols/json/BaseAwsJsonProtocolFactory$Builder.clientConfiguration:(Lsoftware/amazon/awssdk/core/client/config/SdkClientConfiguration;)Lsoftware/amazon/awssdk/protocols/json/BaseAwsJsonProtocolFactory$Builder;
       8: invokedynamic #124,  0            // InvokeDynamic #19:get:()Ljava/util/function/Supplier;
      13: invokevirtual #125                // Method software/amazon/awssdk/protocols/json/BaseAwsJsonProtocolFactory$Builder.defaultServiceExceptionSupplier:(Ljava/util/function/Supplier;)Lsoftware/amazon/awssdk/protocols/json/BaseAwsJsonProtocolFactory$Builder;
      16: getstatic     #126                // Field software/amazon/awssdk/protocols/json/AwsJsonProtocol.AWS_JSON:Lsoftware/amazon/awssdk/protocols/json/AwsJsonProtocol;
      19: invokevirtual #127                // Method software/amazon/awssdk/protocols/json/BaseAwsJsonProtocolFactory$Builder.protocol:(Lsoftware/amazon/awssdk/protocols/json/AwsJsonProtocol;)Lsoftware/amazon/awssdk/protocols/json/BaseAwsJsonProtocolFactory$Builder;
      22: ldc           #128                // String 1.1
      24: invokevirtual #129                // Method software/amazon/awssdk/protocols/json/BaseAwsJsonProtocolFactory$Builder.protocolVersion:(Ljava/lang/String;)Lsoftware/amazon/awssdk/protocols/json/BaseAwsJsonProtocolFactory$Builder;
      27: invokestatic  #130                // Method software/amazon/awssdk/protocols/core/ExceptionMetadata.builder:()Lsoftware/amazon/awssdk/protocols/core/ExceptionMetadata$Builder;
      30: ldc           #131                // String AccessDeniedException
      32: invokevirtual #132                // Method software/amazon/awssdk/protocols/core/ExceptionMetadata$Builder.errorCode:(Ljava/lang/String;)Lsoftware/amazon/awssdk/protocols/core/ExceptionMetadata$Builder;
      35: invokedynamic #133,  0            // InvokeDynamic #20:get:()Ljava/util/function/Supplier;
      40: invokevirtual #134                // Method software/amazon/awssdk/protocols/core/ExceptionMetadata$Builder.exceptionBuilderSupplier:(Ljava/util/function/Supplier;)Lsoftware/amazon/awssdk/protocols/core/ExceptionMetadata$Builder;
      43: invokevirtual #135                // Method software/amazon/awssdk/protocols/core/ExceptionMetadata$Builder.build:()Lsoftware/amazon/awssdk/protocols/core/ExceptionMetadata;
      46: invokevirtual #136                // Method software/amazon/awssdk/protocols/json/BaseAwsJsonProtocolFactory$Builder.registerModeledException:(Lsoftware/amazon/awssdk/protocols/core/ExceptionMetadata;)Lsoftware/amazon/awssdk/protocols/json/BaseAwsJsonProtocolFactory$Builder;
      49: invokestatic  #130                // Method software/amazon/awssdk/protocols/core/ExceptionMetadata.builder:()Lsoftware/amazon/awssdk/protocols/core/ExceptionMetadata$Builder;
      52: ldc           #137                // String OptimisticLockException
      54: invokevirtual #132                // Method software/amazon/awssdk/protocols/core/ExceptionMetadata$Builder.errorCode:(Ljava/lang/String;)Lsoftware/amazon/awssdk/protocols/core/ExceptionMetadata$Builder;
      57: invokedynamic #138,  0            // InvokeDynamic #21:get:()Ljava/util/function/Supplier;
      62: invokevirtual #134                // Method software/amazon/awssdk/protocols/core/ExceptionMetadata$Builder.exceptionBuilderSupplier:(Ljava/util/function/Supplier;)Lsoftware/amazon/awssdk/protocols/core/ExceptionMetadata$Builder;
      65: invokevirtual #135                // Method software/amazon/awssdk/protocols/core/ExceptionMetadata$Builder.build:()Lsoftware/amazon/awssdk/protocols/core/ExceptionMetadata;
      68: invokevirtual #136                // Method software/amazon/awssdk/protocols/json/BaseAwsJsonProtocolFactory$Builder.registerModeledException:(Lsoftware/amazon/awssdk/protocols/core/ExceptionMetadata;)Lsoftware/amazon/awssdk/protocols/json/BaseAwsJsonProtocolFactory$Builder;
      71: invokestatic  #130                // Method software/amazon/awssdk/protocols/core/ExceptionMetadata.builder:()Lsoftware/amazon/awssdk/protocols/core/ExceptionMetadata$Builder;
      74: ldc           #139                // String LockedSubscriptionException
      76: invokevirtual #132                // Method software/amazon/awssdk/protocols/core/ExceptionMetadata$Builder.errorCode:(Ljava/lang/String;)Lsoftware/amazon/awssdk/protocols/core/ExceptionMetadata$Builder;
      79: invokedynamic #140,  0            // InvokeDynamic #22:get:()Ljava/util/function/Supplier;
      84: invokevirtual #134                // Method software/amazon/awssdk/protocols/core/ExceptionMetadata$Builder.exceptionBuilderSupplier:(Ljava/util/function/Supplier;)Lsoftware/amazon/awssdk/protocols/core/ExceptionMetadata$Builder;
      87: invokevirtual #135                // Method software/amazon/awssdk/protocols/core/ExceptionMetadata$Builder.build:()Lsoftware/amazon/awssdk/protocols/core/ExceptionMetadata;
      90: invokevirtual #136                // Method software/amazon/awssdk/protocols/json/BaseAwsJsonProtocolFactory$Builder.registerModeledException:(Lsoftware/amazon/awssdk/protocols/core/ExceptionMetadata;)Lsoftware/amazon/awssdk/protocols/json/BaseAwsJsonProtocolFactory$Builder;
      93: invokestatic  #130                // Method software/amazon/awssdk/protocols/core/ExceptionMetadata.builder:()Lsoftware/amazon/awssdk/protocols/core/ExceptionMetadata$Builder;
      96: ldc           #141                // String InvalidResourceException
      98: invokevirtual #132                // Method software/amazon/awssdk/protocols/core/ExceptionMetadata$Builder.errorCode:(Ljava/lang/String;)Lsoftware/amazon/awssdk/protocols/core/ExceptionMetadata$Builder;
     101: invokedynamic #142,  0            // InvokeDynamic #23:get:()Ljava/util/function/Supplier;
     106: invokevirtual #134                // Method software/amazon/awssdk/protocols/core/ExceptionMetadata$Builder.exceptionBuilderSupplier:(Ljava/util/function/Supplier;)Lsoftware/amazon/awssdk/protocols/core/ExceptionMetadata$Builder;
     109: invokevirtual #135                // Method software/amazon/awssdk/protocols/core/ExceptionMetadata$Builder.build:()Lsoftware/amazon/awssdk/protocols/core/ExceptionMetadata;
     112: invokevirtual #136                // Method software/amazon/awssdk/protocols/json/BaseAwsJsonProtocolFactory$Builder.registerModeledException:(Lsoftware/amazon/awssdk/protocols/core/ExceptionMetadata;)Lsoftware/amazon/awssdk/protocols/json/BaseAwsJsonProtocolFactory$Builder;
     115: invokestatic  #130                // Method software/amazon/awssdk/protocols/core/ExceptionMetadata.builder:()Lsoftware/amazon/awssdk/protocols/core/ExceptionMetadata$Builder;
     118: ldc           #143                // String InvalidParameterException
     120: invokevirtual #132                // Method software/amazon/awssdk/protocols/core/ExceptionMetadata$Builder.errorCode:(Ljava/lang/String;)Lsoftware/amazon/awssdk/protocols/core/ExceptionMetadata$Builder;
     123: invokedynamic #144,  0            // InvokeDynamic #24:get:()Ljava/util/function/Supplier;
     128: invokevirtual #134                // Method software/amazon/awssdk/protocols/core/ExceptionMetadata$Builder.exceptionBuilderSupplier:(Ljava/util/function/Supplier;)Lsoftware/amazon/awssdk/protocols/core/ExceptionMetadata$Builder;
     131: invokevirtual #135                // Method software/amazon/awssdk/protocols/core/ExceptionMetadata$Builder.build:()Lsoftware/amazon/awssdk/protocols/core/ExceptionMetadata;
     134: invokevirtual #136                // Method software/amazon/awssdk/protocols/json/BaseAwsJsonProtocolFactory$Builder.registerModeledException:(Lsoftware/amazon/awssdk/protocols/core/ExceptionMetadata;)Lsoftware/amazon/awssdk/protocols/json/BaseAwsJsonProtocolFactory$Builder;
     137: invokestatic  #130                // Method software/amazon/awssdk/protocols/core/ExceptionMetadata.builder:()Lsoftware/amazon/awssdk/protocols/core/ExceptionMetadata$Builder;
     140: ldc           #145                // String InvalidOperationException
     142: invokevirtual #132                // Method software/amazon/awssdk/protocols/core/ExceptionMetadata$Builder.errorCode:(Ljava/lang/String;)Lsoftware/amazon/awssdk/protocols/core/ExceptionMetadata$Builder;
     145: invokedynamic #146,  0            // InvokeDynamic #25:get:()Ljava/util/function/Supplier;
     150: invokevirtual #134                // Method software/amazon/awssdk/protocols/core/ExceptionMetadata$Builder.exceptionBuilderSupplier:(Ljava/util/function/Supplier;)Lsoftware/amazon/awssdk/protocols/core/ExceptionMetadata$Builder;
     153: invokevirtual #135                // Method software/amazon/awssdk/protocols/core/ExceptionMetadata$Builder.build:()Lsoftware/amazon/awssdk/protocols/core/ExceptionMetadata;
     156: invokevirtual #136                // Method software/amazon/awssdk/protocols/json/BaseAwsJsonProtocolFactory$Builder.registerModeledException:(Lsoftware/amazon/awssdk/protocols/core/ExceptionMetadata;)Lsoftware/amazon/awssdk/protocols/json/BaseAwsJsonProtocolFactory$Builder;
     159: invokestatic  #130                // Method software/amazon/awssdk/protocols/core/ExceptionMetadata.builder:()Lsoftware/amazon/awssdk/protocols/core/ExceptionMetadata$Builder;
     162: ldc           #147                // String ResourceNotFoundException
     164: invokevirtual #132                // Method software/amazon/awssdk/protocols/core/ExceptionMetadata$Builder.errorCode:(Ljava/lang/String;)Lsoftware/amazon/awssdk/protocols/core/ExceptionMetadata$Builder;
     167: invokedynamic #148,  0            // InvokeDynamic #26:get:()Ljava/util/function/Supplier;
     172: invokevirtual #134                // Method software/amazon/awssdk/protocols/core/ExceptionMetadata$Builder.exceptionBuilderSupplier:(Ljava/util/function/Supplier;)Lsoftware/amazon/awssdk/protocols/core/ExceptionMetadata$Builder;
     175: invokevirtual #135                // Method software/amazon/awssdk/protocols/core/ExceptionMetadata$Builder.build:()Lsoftware/amazon/awssdk/protocols/core/ExceptionMetadata;
     178: invokevirtual #136                // Method software/amazon/awssdk/protocols/json/BaseAwsJsonProtocolFactory$Builder.registerModeledException:(Lsoftware/amazon/awssdk/protocols/core/ExceptionMetadata;)Lsoftware/amazon/awssdk/protocols/json/BaseAwsJsonProtocolFactory$Builder;
     181: invokestatic  #130                // Method software/amazon/awssdk/protocols/core/ExceptionMetadata.builder:()Lsoftware/amazon/awssdk/protocols/core/ExceptionMetadata$Builder;
     184: ldc           #149                // String ResourceAlreadyExistsException
     186: invokevirtual #132                // Method software/amazon/awssdk/protocols/core/ExceptionMetadata$Builder.errorCode:(Ljava/lang/String;)Lsoftware/amazon/awssdk/protocols/core/ExceptionMetadata$Builder;
     189: invokedynamic #150,  0            // InvokeDynamic #27:get:()Ljava/util/function/Supplier;
     194: invokevirtual #134                // Method software/amazon/awssdk/protocols/core/ExceptionMetadata$Builder.exceptionBuilderSupplier:(Ljava/util/function/Supplier;)Lsoftware/amazon/awssdk/protocols/core/ExceptionMetadata$Builder;
     197: invokevirtual #135                // Method software/amazon/awssdk/protocols/core/ExceptionMetadata$Builder.build:()Lsoftware/amazon/awssdk/protocols/core/ExceptionMetadata;
     200: invokevirtual #136                // Method software/amazon/awssdk/protocols/json/BaseAwsJsonProtocolFactory$Builder.registerModeledException:(Lsoftware/amazon/awssdk/protocols/core/ExceptionMetadata;)Lsoftware/amazon/awssdk/protocols/json/BaseAwsJsonProtocolFactory$Builder;
     203: invokestatic  #130                // Method software/amazon/awssdk/protocols/core/ExceptionMetadata.builder:()Lsoftware/amazon/awssdk/protocols/core/ExceptionMetadata$Builder;
     206: ldc           #151                // String InternalErrorException
     208: invokevirtual #132                // Method software/amazon/awssdk/protocols/core/ExceptionMetadata$Builder.errorCode:(Ljava/lang/String;)Lsoftware/amazon/awssdk/protocols/core/ExceptionMetadata$Builder;
     211: invokedynamic #152,  0            // InvokeDynamic #28:get:()Ljava/util/function/Supplier;
     216: invokevirtual #134                // Method software/amazon/awssdk/protocols/core/ExceptionMetadata$Builder.exceptionBuilderSupplier:(Ljava/util/function/Supplier;)Lsoftware/amazon/awssdk/protocols/core/ExceptionMetadata$Builder;
     219: invokevirtual #135                // Method software/amazon/awssdk/protocols/core/ExceptionMetadata$Builder.build:()Lsoftware/amazon/awssdk/protocols/core/ExceptionMetadata;
     222: invokevirtual #136                // Method software/amazon/awssdk/protocols/json/BaseAwsJsonProtocolFactory$Builder.registerModeledException:(Lsoftware/amazon/awssdk/protocols/core/ExceptionMetadata;)Lsoftware/amazon/awssdk/protocols/json/BaseAwsJsonProtocolFactory$Builder;
     225: invokestatic  #130                // Method software/amazon/awssdk/protocols/core/ExceptionMetadata.builder:()Lsoftware/amazon/awssdk/protocols/core/ExceptionMetadata$Builder;
     228: ldc           #153                // String InvalidPaginationTokenException
     230: invokevirtual #132                // Method software/amazon/awssdk/protocols/core/ExceptionMetadata$Builder.errorCode:(Ljava/lang/String;)Lsoftware/amazon/awssdk/protocols/core/ExceptionMetadata$Builder;
     233: invokedynamic #154,  0            // InvokeDynamic #29:get:()Ljava/util/function/Supplier;
     238: invokevirtual #134                // Method software/amazon/awssdk/protocols/core/ExceptionMetadata$Builder.exceptionBuilderSupplier:(Ljava/util/function/Supplier;)Lsoftware/amazon/awssdk/protocols/core/ExceptionMetadata$Builder;
     241: invokevirtual #135                // Method software/amazon/awssdk/protocols/core/ExceptionMetadata$Builder.build:()Lsoftware/amazon/awssdk/protocols/core/ExceptionMetadata;
     244: invokevirtual #136                // Method software/amazon/awssdk/protocols/json/BaseAwsJsonProtocolFactory$Builder.registerModeledException:(Lsoftware/amazon/awssdk/protocols/core/ExceptionMetadata;)Lsoftware/amazon/awssdk/protocols/json/BaseAwsJsonProtocolFactory$Builder;
     247: invokestatic  #130                // Method software/amazon/awssdk/protocols/core/ExceptionMetadata.builder:()Lsoftware/amazon/awssdk/protocols/core/ExceptionMetadata$Builder;
     250: ldc           #155                // String LimitsExceededException
     252: invokevirtual #132                // Method software/amazon/awssdk/protocols/core/ExceptionMetadata$Builder.errorCode:(Ljava/lang/String;)Lsoftware/amazon/awssdk/protocols/core/ExceptionMetadata$Builder;
     255: invokedynamic #156,  0            // InvokeDynamic #30:get:()Ljava/util/function/Supplier;
     260: invokevirtual #134                // Method software/amazon/awssdk/protocols/core/ExceptionMetadata$Builder.exceptionBuilderSupplier:(Ljava/util/function/Supplier;)Lsoftware/amazon/awssdk/protocols/core/ExceptionMetadata$Builder;
     263: invokevirtual #135                // Method software/amazon/awssdk/protocols/core/ExceptionMetadata$Builder.build:()Lsoftware/amazon/awssdk/protocols/core/ExceptionMetadata;
     266: invokevirtual #136                // Method software/amazon/awssdk/protocols/json/BaseAwsJsonProtocolFactory$Builder.registerModeledException:(Lsoftware/amazon/awssdk/protocols/core/ExceptionMetadata;)Lsoftware/amazon/awssdk/protocols/json/BaseAwsJsonProtocolFactory$Builder;
     269: invokestatic  #130                // Method software/amazon/awssdk/protocols/core/ExceptionMetadata.builder:()Lsoftware/amazon/awssdk/protocols/core/ExceptionMetadata$Builder;
     272: ldc           #157                // String NoAssociatedRoleException
     274: invokevirtual #132                // Method software/amazon/awssdk/protocols/core/ExceptionMetadata$Builder.errorCode:(Ljava/lang/String;)Lsoftware/amazon/awssdk/protocols/core/ExceptionMetadata$Builder;
     277: invokedynamic #158,  0            // InvokeDynamic #31:get:()Ljava/util/function/Supplier;
     282: invokevirtual #134                // Method software/amazon/awssdk/protocols/core/ExceptionMetadata$Builder.exceptionBuilderSupplier:(Ljava/util/function/Supplier;)Lsoftware/amazon/awssdk/protocols/core/ExceptionMetadata$Builder;
     285: invokevirtual #135                // Method software/amazon/awssdk/protocols/core/ExceptionMetadata$Builder.build:()Lsoftware/amazon/awssdk/protocols/core/ExceptionMetadata;
     288: invokevirtual #136                // Method software/amazon/awssdk/protocols/json/BaseAwsJsonProtocolFactory$Builder.registerModeledException:(Lsoftware/amazon/awssdk/protocols/core/ExceptionMetadata;)Lsoftware/amazon/awssdk/protocols/json/BaseAwsJsonProtocolFactory$Builder;
     291: invokestatic  #130                // Method software/amazon/awssdk/protocols/core/ExceptionMetadata.builder:()Lsoftware/amazon/awssdk/protocols/core/ExceptionMetadata$Builder;
     294: ldc           #159                // String AccessDeniedForDependencyException
     296: invokevirtual #132                // Method software/amazon/awssdk/protocols/core/ExceptionMetadata$Builder.errorCode:(Ljava/lang/String;)Lsoftware/amazon/awssdk/protocols/core/ExceptionMetadata$Builder;
     299: invokedynamic #160,  0            // InvokeDynamic #32:get:()Ljava/util/function/Supplier;
     304: invokevirtual #134                // Method software/amazon/awssdk/protocols/core/ExceptionMetadata$Builder.exceptionBuilderSupplier:(Ljava/util/function/Supplier;)Lsoftware/amazon/awssdk/protocols/core/ExceptionMetadata$Builder;
     307: invokevirtual #135                // Method software/amazon/awssdk/protocols/core/ExceptionMetadata$Builder.build:()Lsoftware/amazon/awssdk/protocols/core/ExceptionMetadata;
     310: invokevirtual #136                // Method software/amazon/awssdk/protocols/json/BaseAwsJsonProtocolFactory$Builder.registerModeledException:(Lsoftware/amazon/awssdk/protocols/core/ExceptionMetadata;)Lsoftware/amazon/awssdk/protocols/json/BaseAwsJsonProtocolFactory$Builder;
     313: areturn

  public void close();
    Code:
       0: aload_0
       1: getfield      #4                  // Field clientHandler:Lsoftware/amazon/awssdk/core/client/handler/SyncClientHandler;
       4: invokeinterface #161,  1          // InterfaceMethod software/amazon/awssdk/core/client/handler/SyncClientHandler.close:()V
       9: return
}
