Compiled from "ShieldClient.java"
public interface software.amazon.awssdk.services.shield.ShieldClient extends software.amazon.awssdk.core.SdkClient {
  public static final java.lang.String SERVICE_NAME;

  public static software.amazon.awssdk.services.shield.ShieldClient create();
    Code:
       0: invokestatic  #1                  // InterfaceMethod builder:()Lsoftware/amazon/awssdk/services/shield/ShieldClientBuilder;
       3: invokeinterface #2,  1            // InterfaceMethod software/amazon/awssdk/services/shield/ShieldClientBuilder.build:()Ljava/lang/Object;
       8: checkcast     #3                  // class software/amazon/awssdk/services/shield/ShieldClient
      11: areturn

  public static software.amazon.awssdk.services.shield.ShieldClientBuilder builder();
    Code:
       0: new           #4                  // class software/amazon/awssdk/services/shield/DefaultShieldClientBuilder
       3: dup
       4: invokespecial #5                  // Method software/amazon/awssdk/services/shield/DefaultShieldClientBuilder."<init>":()V
       7: areturn

  public default software.amazon.awssdk.services.shield.model.AssociateDrtLogBucketResponse associateDRTLogBucket(software.amazon.awssdk.services.shield.model.AssociateDrtLogBucketRequest) throws software.amazon.awssdk.services.shield.model.InternalErrorException, software.amazon.awssdk.services.shield.model.InvalidOperationException, software.amazon.awssdk.services.shield.model.NoAssociatedRoleException, software.amazon.awssdk.services.shield.model.LimitsExceededException, software.amazon.awssdk.services.shield.model.InvalidParameterException, software.amazon.awssdk.services.shield.model.AccessDeniedForDependencyException, software.amazon.awssdk.services.shield.model.OptimisticLockException, software.amazon.awssdk.services.shield.model.ResourceNotFoundException, software.amazon.awssdk.awscore.exception.AwsServiceException, software.amazon.awssdk.core.exception.SdkClientException, software.amazon.awssdk.services.shield.model.ShieldException;
    Code:
       0: new           #6                  // class java/lang/UnsupportedOperationException
       3: dup
       4: invokespecial #7                  // Method java/lang/UnsupportedOperationException."<init>":()V
       7: athrow

  public default software.amazon.awssdk.services.shield.model.AssociateDrtLogBucketResponse associateDRTLogBucket(java.util.function.Consumer<software.amazon.awssdk.services.shield.model.AssociateDrtLogBucketRequest$Builder>) throws software.amazon.awssdk.services.shield.model.InternalErrorException, software.amazon.awssdk.services.shield.model.InvalidOperationException, software.amazon.awssdk.services.shield.model.NoAssociatedRoleException, software.amazon.awssdk.services.shield.model.LimitsExceededException, software.amazon.awssdk.services.shield.model.InvalidParameterException, software.amazon.awssdk.services.shield.model.AccessDeniedForDependencyException, software.amazon.awssdk.services.shield.model.OptimisticLockException, software.amazon.awssdk.services.shield.model.ResourceNotFoundException, software.amazon.awssdk.awscore.exception.AwsServiceException, software.amazon.awssdk.core.exception.SdkClientException, software.amazon.awssdk.services.shield.model.ShieldException;
    Code:
       0: aload_0
       1: invokestatic  #8                  // Method software/amazon/awssdk/services/shield/model/AssociateDrtLogBucketRequest.builder:()Lsoftware/amazon/awssdk/services/shield/model/AssociateDrtLogBucketRequest$Builder;
       4: aload_1
       5: invokeinterface #9,  2            // InterfaceMethod software/amazon/awssdk/services/shield/model/AssociateDrtLogBucketRequest$Builder.applyMutation:(Ljava/util/function/Consumer;)Lsoftware/amazon/awssdk/utils/builder/SdkBuilder;
      10: checkcast     #10                 // class software/amazon/awssdk/services/shield/model/AssociateDrtLogBucketRequest$Builder
      13: invokeinterface #11,  1           // InterfaceMethod software/amazon/awssdk/services/shield/model/AssociateDrtLogBucketRequest$Builder.build:()Ljava/lang/Object;
      18: checkcast     #12                 // class software/amazon/awssdk/services/shield/model/AssociateDrtLogBucketRequest
      21: invokeinterface #13,  2           // InterfaceMethod associateDRTLogBucket:(Lsoftware/amazon/awssdk/services/shield/model/AssociateDrtLogBucketRequest;)Lsoftware/amazon/awssdk/services/shield/model/AssociateDrtLogBucketResponse;
      26: areturn

  public default software.amazon.awssdk.services.shield.model.AssociateDrtRoleResponse associateDRTRole(software.amazon.awssdk.services.shield.model.AssociateDrtRoleRequest) throws software.amazon.awssdk.services.shield.model.InternalErrorException, software.amazon.awssdk.services.shield.model.InvalidOperationException, software.amazon.awssdk.services.shield.model.InvalidParameterException, software.amazon.awssdk.services.shield.model.AccessDeniedForDependencyException, software.amazon.awssdk.services.shield.model.OptimisticLockException, software.amazon.awssdk.services.shield.model.ResourceNotFoundException, software.amazon.awssdk.awscore.exception.AwsServiceException, software.amazon.awssdk.core.exception.SdkClientException, software.amazon.awssdk.services.shield.model.ShieldException;
    Code:
       0: new           #6                  // class java/lang/UnsupportedOperationException
       3: dup
       4: invokespecial #7                  // Method java/lang/UnsupportedOperationException."<init>":()V
       7: athrow

  public default software.amazon.awssdk.services.shield.model.AssociateDrtRoleResponse associateDRTRole(java.util.function.Consumer<software.amazon.awssdk.services.shield.model.AssociateDrtRoleRequest$Builder>) throws software.amazon.awssdk.services.shield.model.InternalErrorException, software.amazon.awssdk.services.shield.model.InvalidOperationException, software.amazon.awssdk.services.shield.model.InvalidParameterException, software.amazon.awssdk.services.shield.model.AccessDeniedForDependencyException, software.amazon.awssdk.services.shield.model.OptimisticLockException, software.amazon.awssdk.services.shield.model.ResourceNotFoundException, software.amazon.awssdk.awscore.exception.AwsServiceException, software.amazon.awssdk.core.exception.SdkClientException, software.amazon.awssdk.services.shield.model.ShieldException;
    Code:
       0: aload_0
       1: invokestatic  #14                 // Method software/amazon/awssdk/services/shield/model/AssociateDrtRoleRequest.builder:()Lsoftware/amazon/awssdk/services/shield/model/AssociateDrtRoleRequest$Builder;
       4: aload_1
       5: invokeinterface #15,  2           // InterfaceMethod software/amazon/awssdk/services/shield/model/AssociateDrtRoleRequest$Builder.applyMutation:(Ljava/util/function/Consumer;)Lsoftware/amazon/awssdk/utils/builder/SdkBuilder;
      10: checkcast     #16                 // class software/amazon/awssdk/services/shield/model/AssociateDrtRoleRequest$Builder
      13: invokeinterface #17,  1           // InterfaceMethod software/amazon/awssdk/services/shield/model/AssociateDrtRoleRequest$Builder.build:()Ljava/lang/Object;
      18: checkcast     #18                 // class software/amazon/awssdk/services/shield/model/AssociateDrtRoleRequest
      21: invokeinterface #19,  2           // InterfaceMethod associateDRTRole:(Lsoftware/amazon/awssdk/services/shield/model/AssociateDrtRoleRequest;)Lsoftware/amazon/awssdk/services/shield/model/AssociateDrtRoleResponse;
      26: areturn

  public default software.amazon.awssdk.services.shield.model.AssociateHealthCheckResponse associateHealthCheck(software.amazon.awssdk.services.shield.model.AssociateHealthCheckRequest) throws software.amazon.awssdk.services.shield.model.InternalErrorException, software.amazon.awssdk.services.shield.model.LimitsExceededException, software.amazon.awssdk.services.shield.model.ResourceNotFoundException, software.amazon.awssdk.services.shield.model.InvalidParameterException, software.amazon.awssdk.services.shield.model.OptimisticLockException, software.amazon.awssdk.awscore.exception.AwsServiceException, software.amazon.awssdk.core.exception.SdkClientException, software.amazon.awssdk.services.shield.model.ShieldException;
    Code:
       0: new           #6                  // class java/lang/UnsupportedOperationException
       3: dup
       4: invokespecial #7                  // Method java/lang/UnsupportedOperationException."<init>":()V
       7: athrow

  public default software.amazon.awssdk.services.shield.model.AssociateHealthCheckResponse associateHealthCheck(java.util.function.Consumer<software.amazon.awssdk.services.shield.model.AssociateHealthCheckRequest$Builder>) throws software.amazon.awssdk.services.shield.model.InternalErrorException, software.amazon.awssdk.services.shield.model.LimitsExceededException, software.amazon.awssdk.services.shield.model.ResourceNotFoundException, software.amazon.awssdk.services.shield.model.InvalidParameterException, software.amazon.awssdk.services.shield.model.OptimisticLockException, software.amazon.awssdk.awscore.exception.AwsServiceException, software.amazon.awssdk.core.exception.SdkClientException, software.amazon.awssdk.services.shield.model.ShieldException;
    Code:
       0: aload_0
       1: invokestatic  #20                 // Method software/amazon/awssdk/services/shield/model/AssociateHealthCheckRequest.builder:()Lsoftware/amazon/awssdk/services/shield/model/AssociateHealthCheckRequest$Builder;
       4: aload_1
       5: invokeinterface #21,  2           // InterfaceMethod software/amazon/awssdk/services/shield/model/AssociateHealthCheckRequest$Builder.applyMutation:(Ljava/util/function/Consumer;)Lsoftware/amazon/awssdk/utils/builder/SdkBuilder;
      10: checkcast     #22                 // class software/amazon/awssdk/services/shield/model/AssociateHealthCheckRequest$Builder
      13: invokeinterface #23,  1           // InterfaceMethod software/amazon/awssdk/services/shield/model/AssociateHealthCheckRequest$Builder.build:()Ljava/lang/Object;
      18: checkcast     #24                 // class software/amazon/awssdk/services/shield/model/AssociateHealthCheckRequest
      21: invokeinterface #25,  2           // InterfaceMethod associateHealthCheck:(Lsoftware/amazon/awssdk/services/shield/model/AssociateHealthCheckRequest;)Lsoftware/amazon/awssdk/services/shield/model/AssociateHealthCheckResponse;
      26: areturn

  public default software.amazon.awssdk.services.shield.model.CreateProtectionResponse createProtection(software.amazon.awssdk.services.shield.model.CreateProtectionRequest) throws software.amazon.awssdk.services.shield.model.InternalErrorException, software.amazon.awssdk.services.shield.model.InvalidResourceException, software.amazon.awssdk.services.shield.model.InvalidOperationException, software.amazon.awssdk.services.shield.model.LimitsExceededException, software.amazon.awssdk.services.shield.model.ResourceAlreadyExistsException, software.amazon.awssdk.services.shield.model.OptimisticLockException, software.amazon.awssdk.services.shield.model.ResourceNotFoundException, software.amazon.awssdk.awscore.exception.AwsServiceException, software.amazon.awssdk.core.exception.SdkClientException, software.amazon.awssdk.services.shield.model.ShieldException;
    Code:
       0: new           #6                  // class java/lang/UnsupportedOperationException
       3: dup
       4: invokespecial #7                  // Method java/lang/UnsupportedOperationException."<init>":()V
       7: athrow

  public default software.amazon.awssdk.services.shield.model.CreateProtectionResponse createProtection(java.util.function.Consumer<software.amazon.awssdk.services.shield.model.CreateProtectionRequest$Builder>) throws software.amazon.awssdk.services.shield.model.InternalErrorException, software.amazon.awssdk.services.shield.model.InvalidResourceException, software.amazon.awssdk.services.shield.model.InvalidOperationException, software.amazon.awssdk.services.shield.model.LimitsExceededException, software.amazon.awssdk.services.shield.model.ResourceAlreadyExistsException, software.amazon.awssdk.services.shield.model.OptimisticLockException, software.amazon.awssdk.services.shield.model.ResourceNotFoundException, software.amazon.awssdk.awscore.exception.AwsServiceException, software.amazon.awssdk.core.exception.SdkClientException, software.amazon.awssdk.services.shield.model.ShieldException;
    Code:
       0: aload_0
       1: invokestatic  #26                 // Method software/amazon/awssdk/services/shield/model/CreateProtectionRequest.builder:()Lsoftware/amazon/awssdk/services/shield/model/CreateProtectionRequest$Builder;
       4: aload_1
       5: invokeinterface #27,  2           // InterfaceMethod software/amazon/awssdk/services/shield/model/CreateProtectionRequest$Builder.applyMutation:(Ljava/util/function/Consumer;)Lsoftware/amazon/awssdk/utils/builder/SdkBuilder;
      10: checkcast     #28                 // class software/amazon/awssdk/services/shield/model/CreateProtectionRequest$Builder
      13: invokeinterface #29,  1           // InterfaceMethod software/amazon/awssdk/services/shield/model/CreateProtectionRequest$Builder.build:()Ljava/lang/Object;
      18: checkcast     #30                 // class software/amazon/awssdk/services/shield/model/CreateProtectionRequest
      21: invokeinterface #31,  2           // InterfaceMethod createProtection:(Lsoftware/amazon/awssdk/services/shield/model/CreateProtectionRequest;)Lsoftware/amazon/awssdk/services/shield/model/CreateProtectionResponse;
      26: areturn

  public default software.amazon.awssdk.services.shield.model.CreateSubscriptionResponse createSubscription() throws software.amazon.awssdk.services.shield.model.InternalErrorException, software.amazon.awssdk.services.shield.model.ResourceAlreadyExistsException, software.amazon.awssdk.awscore.exception.AwsServiceException, software.amazon.awssdk.core.exception.SdkClientException, software.amazon.awssdk.services.shield.model.ShieldException;
    Code:
       0: aload_0
       1: invokestatic  #32                 // Method software/amazon/awssdk/services/shield/model/CreateSubscriptionRequest.builder:()Lsoftware/amazon/awssdk/services/shield/model/CreateSubscriptionRequest$Builder;
       4: invokeinterface #33,  1           // InterfaceMethod software/amazon/awssdk/services/shield/model/CreateSubscriptionRequest$Builder.build:()Ljava/lang/Object;
       9: checkcast     #34                 // class software/amazon/awssdk/services/shield/model/CreateSubscriptionRequest
      12: invokeinterface #35,  2           // InterfaceMethod createSubscription:(Lsoftware/amazon/awssdk/services/shield/model/CreateSubscriptionRequest;)Lsoftware/amazon/awssdk/services/shield/model/CreateSubscriptionResponse;
      17: areturn

  public default software.amazon.awssdk.services.shield.model.CreateSubscriptionResponse createSubscription(software.amazon.awssdk.services.shield.model.CreateSubscriptionRequest) throws software.amazon.awssdk.services.shield.model.InternalErrorException, software.amazon.awssdk.services.shield.model.ResourceAlreadyExistsException, software.amazon.awssdk.awscore.exception.AwsServiceException, software.amazon.awssdk.core.exception.SdkClientException, software.amazon.awssdk.services.shield.model.ShieldException;
    Code:
       0: new           #6                  // class java/lang/UnsupportedOperationException
       3: dup
       4: invokespecial #7                  // Method java/lang/UnsupportedOperationException."<init>":()V
       7: athrow

  public default software.amazon.awssdk.services.shield.model.CreateSubscriptionResponse createSubscription(java.util.function.Consumer<software.amazon.awssdk.services.shield.model.CreateSubscriptionRequest$Builder>) throws software.amazon.awssdk.services.shield.model.InternalErrorException, software.amazon.awssdk.services.shield.model.ResourceAlreadyExistsException, software.amazon.awssdk.awscore.exception.AwsServiceException, software.amazon.awssdk.core.exception.SdkClientException, software.amazon.awssdk.services.shield.model.ShieldException;
    Code:
       0: aload_0
       1: invokestatic  #32                 // Method software/amazon/awssdk/services/shield/model/CreateSubscriptionRequest.builder:()Lsoftware/amazon/awssdk/services/shield/model/CreateSubscriptionRequest$Builder;
       4: aload_1
       5: invokeinterface #36,  2           // InterfaceMethod software/amazon/awssdk/services/shield/model/CreateSubscriptionRequest$Builder.applyMutation:(Ljava/util/function/Consumer;)Lsoftware/amazon/awssdk/utils/builder/SdkBuilder;
      10: checkcast     #37                 // class software/amazon/awssdk/services/shield/model/CreateSubscriptionRequest$Builder
      13: invokeinterface #33,  1           // InterfaceMethod software/amazon/awssdk/services/shield/model/CreateSubscriptionRequest$Builder.build:()Ljava/lang/Object;
      18: checkcast     #34                 // class software/amazon/awssdk/services/shield/model/CreateSubscriptionRequest
      21: invokeinterface #35,  2           // InterfaceMethod createSubscription:(Lsoftware/amazon/awssdk/services/shield/model/CreateSubscriptionRequest;)Lsoftware/amazon/awssdk/services/shield/model/CreateSubscriptionResponse;
      26: areturn

  public default software.amazon.awssdk.services.shield.model.DeleteProtectionResponse deleteProtection(software.amazon.awssdk.services.shield.model.DeleteProtectionRequest) throws software.amazon.awssdk.services.shield.model.InternalErrorException, software.amazon.awssdk.services.shield.model.ResourceNotFoundException, software.amazon.awssdk.services.shield.model.OptimisticLockException, software.amazon.awssdk.awscore.exception.AwsServiceException, software.amazon.awssdk.core.exception.SdkClientException, software.amazon.awssdk.services.shield.model.ShieldException;
    Code:
       0: new           #6                  // class java/lang/UnsupportedOperationException
       3: dup
       4: invokespecial #7                  // Method java/lang/UnsupportedOperationException."<init>":()V
       7: athrow

  public default software.amazon.awssdk.services.shield.model.DeleteProtectionResponse deleteProtection(java.util.function.Consumer<software.amazon.awssdk.services.shield.model.DeleteProtectionRequest$Builder>) throws software.amazon.awssdk.services.shield.model.InternalErrorException, software.amazon.awssdk.services.shield.model.ResourceNotFoundException, software.amazon.awssdk.services.shield.model.OptimisticLockException, software.amazon.awssdk.awscore.exception.AwsServiceException, software.amazon.awssdk.core.exception.SdkClientException, software.amazon.awssdk.services.shield.model.ShieldException;
    Code:
       0: aload_0
       1: invokestatic  #38                 // Method software/amazon/awssdk/services/shield/model/DeleteProtectionRequest.builder:()Lsoftware/amazon/awssdk/services/shield/model/DeleteProtectionRequest$Builder;
       4: aload_1
       5: invokeinterface #39,  2           // InterfaceMethod software/amazon/awssdk/services/shield/model/DeleteProtectionRequest$Builder.applyMutation:(Ljava/util/function/Consumer;)Lsoftware/amazon/awssdk/utils/builder/SdkBuilder;
      10: checkcast     #40                 // class software/amazon/awssdk/services/shield/model/DeleteProtectionRequest$Builder
      13: invokeinterface #41,  1           // InterfaceMethod software/amazon/awssdk/services/shield/model/DeleteProtectionRequest$Builder.build:()Ljava/lang/Object;
      18: checkcast     #42                 // class software/amazon/awssdk/services/shield/model/DeleteProtectionRequest
      21: invokeinterface #43,  2           // InterfaceMethod deleteProtection:(Lsoftware/amazon/awssdk/services/shield/model/DeleteProtectionRequest;)Lsoftware/amazon/awssdk/services/shield/model/DeleteProtectionResponse;
      26: areturn

  public default software.amazon.awssdk.services.shield.model.DescribeAttackResponse describeAttack(software.amazon.awssdk.services.shield.model.DescribeAttackRequest) throws software.amazon.awssdk.services.shield.model.InternalErrorException, software.amazon.awssdk.services.shield.model.AccessDeniedException, software.amazon.awssdk.awscore.exception.AwsServiceException, software.amazon.awssdk.core.exception.SdkClientException, software.amazon.awssdk.services.shield.model.ShieldException;
    Code:
       0: new           #6                  // class java/lang/UnsupportedOperationException
       3: dup
       4: invokespecial #7                  // Method java/lang/UnsupportedOperationException."<init>":()V
       7: athrow

  public default software.amazon.awssdk.services.shield.model.DescribeAttackResponse describeAttack(java.util.function.Consumer<software.amazon.awssdk.services.shield.model.DescribeAttackRequest$Builder>) throws software.amazon.awssdk.services.shield.model.InternalErrorException, software.amazon.awssdk.services.shield.model.AccessDeniedException, software.amazon.awssdk.awscore.exception.AwsServiceException, software.amazon.awssdk.core.exception.SdkClientException, software.amazon.awssdk.services.shield.model.ShieldException;
    Code:
       0: aload_0
       1: invokestatic  #44                 // Method software/amazon/awssdk/services/shield/model/DescribeAttackRequest.builder:()Lsoftware/amazon/awssdk/services/shield/model/DescribeAttackRequest$Builder;
       4: aload_1
       5: invokeinterface #45,  2           // InterfaceMethod software/amazon/awssdk/services/shield/model/DescribeAttackRequest$Builder.applyMutation:(Ljava/util/function/Consumer;)Lsoftware/amazon/awssdk/utils/builder/SdkBuilder;
      10: checkcast     #46                 // class software/amazon/awssdk/services/shield/model/DescribeAttackRequest$Builder
      13: invokeinterface #47,  1           // InterfaceMethod software/amazon/awssdk/services/shield/model/DescribeAttackRequest$Builder.build:()Ljava/lang/Object;
      18: checkcast     #48                 // class software/amazon/awssdk/services/shield/model/DescribeAttackRequest
      21: invokeinterface #49,  2           // InterfaceMethod describeAttack:(Lsoftware/amazon/awssdk/services/shield/model/DescribeAttackRequest;)Lsoftware/amazon/awssdk/services/shield/model/DescribeAttackResponse;
      26: areturn

  public default software.amazon.awssdk.services.shield.model.DescribeDrtAccessResponse describeDRTAccess(software.amazon.awssdk.services.shield.model.DescribeDrtAccessRequest) throws software.amazon.awssdk.services.shield.model.InternalErrorException, software.amazon.awssdk.services.shield.model.ResourceNotFoundException, software.amazon.awssdk.awscore.exception.AwsServiceException, software.amazon.awssdk.core.exception.SdkClientException, software.amazon.awssdk.services.shield.model.ShieldException;
    Code:
       0: new           #6                  // class java/lang/UnsupportedOperationException
       3: dup
       4: invokespecial #7                  // Method java/lang/UnsupportedOperationException."<init>":()V
       7: athrow

  public default software.amazon.awssdk.services.shield.model.DescribeDrtAccessResponse describeDRTAccess(java.util.function.Consumer<software.amazon.awssdk.services.shield.model.DescribeDrtAccessRequest$Builder>) throws software.amazon.awssdk.services.shield.model.InternalErrorException, software.amazon.awssdk.services.shield.model.ResourceNotFoundException, software.amazon.awssdk.awscore.exception.AwsServiceException, software.amazon.awssdk.core.exception.SdkClientException, software.amazon.awssdk.services.shield.model.ShieldException;
    Code:
       0: aload_0
       1: invokestatic  #50                 // Method software/amazon/awssdk/services/shield/model/DescribeDrtAccessRequest.builder:()Lsoftware/amazon/awssdk/services/shield/model/DescribeDrtAccessRequest$Builder;
       4: aload_1
       5: invokeinterface #51,  2           // InterfaceMethod software/amazon/awssdk/services/shield/model/DescribeDrtAccessRequest$Builder.applyMutation:(Ljava/util/function/Consumer;)Lsoftware/amazon/awssdk/utils/builder/SdkBuilder;
      10: checkcast     #52                 // class software/amazon/awssdk/services/shield/model/DescribeDrtAccessRequest$Builder
      13: invokeinterface #53,  1           // InterfaceMethod software/amazon/awssdk/services/shield/model/DescribeDrtAccessRequest$Builder.build:()Ljava/lang/Object;
      18: checkcast     #54                 // class software/amazon/awssdk/services/shield/model/DescribeDrtAccessRequest
      21: invokeinterface #55,  2           // InterfaceMethod describeDRTAccess:(Lsoftware/amazon/awssdk/services/shield/model/DescribeDrtAccessRequest;)Lsoftware/amazon/awssdk/services/shield/model/DescribeDrtAccessResponse;
      26: areturn

  public default software.amazon.awssdk.services.shield.model.DescribeEmergencyContactSettingsResponse describeEmergencyContactSettings(software.amazon.awssdk.services.shield.model.DescribeEmergencyContactSettingsRequest) throws software.amazon.awssdk.services.shield.model.InternalErrorException, software.amazon.awssdk.services.shield.model.ResourceNotFoundException, software.amazon.awssdk.awscore.exception.AwsServiceException, software.amazon.awssdk.core.exception.SdkClientException, software.amazon.awssdk.services.shield.model.ShieldException;
    Code:
       0: new           #6                  // class java/lang/UnsupportedOperationException
       3: dup
       4: invokespecial #7                  // Method java/lang/UnsupportedOperationException."<init>":()V
       7: athrow

  public default software.amazon.awssdk.services.shield.model.DescribeEmergencyContactSettingsResponse describeEmergencyContactSettings(java.util.function.Consumer<software.amazon.awssdk.services.shield.model.DescribeEmergencyContactSettingsRequest$Builder>) throws software.amazon.awssdk.services.shield.model.InternalErrorException, software.amazon.awssdk.services.shield.model.ResourceNotFoundException, software.amazon.awssdk.awscore.exception.AwsServiceException, software.amazon.awssdk.core.exception.SdkClientException, software.amazon.awssdk.services.shield.model.ShieldException;
    Code:
       0: aload_0
       1: invokestatic  #56                 // Method software/amazon/awssdk/services/shield/model/DescribeEmergencyContactSettingsRequest.builder:()Lsoftware/amazon/awssdk/services/shield/model/DescribeEmergencyContactSettingsRequest$Builder;
       4: aload_1
       5: invokeinterface #57,  2           // InterfaceMethod software/amazon/awssdk/services/shield/model/DescribeEmergencyContactSettingsRequest$Builder.applyMutation:(Ljava/util/function/Consumer;)Lsoftware/amazon/awssdk/utils/builder/SdkBuilder;
      10: checkcast     #58                 // class software/amazon/awssdk/services/shield/model/DescribeEmergencyContactSettingsRequest$Builder
      13: invokeinterface #59,  1           // InterfaceMethod software/amazon/awssdk/services/shield/model/DescribeEmergencyContactSettingsRequest$Builder.build:()Ljava/lang/Object;
      18: checkcast     #60                 // class software/amazon/awssdk/services/shield/model/DescribeEmergencyContactSettingsRequest
      21: invokeinterface #61,  2           // InterfaceMethod describeEmergencyContactSettings:(Lsoftware/amazon/awssdk/services/shield/model/DescribeEmergencyContactSettingsRequest;)Lsoftware/amazon/awssdk/services/shield/model/DescribeEmergencyContactSettingsResponse;
      26: areturn

  public default software.amazon.awssdk.services.shield.model.DescribeProtectionResponse describeProtection(software.amazon.awssdk.services.shield.model.DescribeProtectionRequest) throws software.amazon.awssdk.services.shield.model.InternalErrorException, software.amazon.awssdk.services.shield.model.InvalidParameterException, software.amazon.awssdk.services.shield.model.ResourceNotFoundException, software.amazon.awssdk.awscore.exception.AwsServiceException, software.amazon.awssdk.core.exception.SdkClientException, software.amazon.awssdk.services.shield.model.ShieldException;
    Code:
       0: new           #6                  // class java/lang/UnsupportedOperationException
       3: dup
       4: invokespecial #7                  // Method java/lang/UnsupportedOperationException."<init>":()V
       7: athrow

  public default software.amazon.awssdk.services.shield.model.DescribeProtectionResponse describeProtection(java.util.function.Consumer<software.amazon.awssdk.services.shield.model.DescribeProtectionRequest$Builder>) throws software.amazon.awssdk.services.shield.model.InternalErrorException, software.amazon.awssdk.services.shield.model.InvalidParameterException, software.amazon.awssdk.services.shield.model.ResourceNotFoundException, software.amazon.awssdk.awscore.exception.AwsServiceException, software.amazon.awssdk.core.exception.SdkClientException, software.amazon.awssdk.services.shield.model.ShieldException;
    Code:
       0: aload_0
       1: invokestatic  #62                 // Method software/amazon/awssdk/services/shield/model/DescribeProtectionRequest.builder:()Lsoftware/amazon/awssdk/services/shield/model/DescribeProtectionRequest$Builder;
       4: aload_1
       5: invokeinterface #63,  2           // InterfaceMethod software/amazon/awssdk/services/shield/model/DescribeProtectionRequest$Builder.applyMutation:(Ljava/util/function/Consumer;)Lsoftware/amazon/awssdk/utils/builder/SdkBuilder;
      10: checkcast     #64                 // class software/amazon/awssdk/services/shield/model/DescribeProtectionRequest$Builder
      13: invokeinterface #65,  1           // InterfaceMethod software/amazon/awssdk/services/shield/model/DescribeProtectionRequest$Builder.build:()Ljava/lang/Object;
      18: checkcast     #66                 // class software/amazon/awssdk/services/shield/model/DescribeProtectionRequest
      21: invokeinterface #67,  2           // InterfaceMethod describeProtection:(Lsoftware/amazon/awssdk/services/shield/model/DescribeProtectionRequest;)Lsoftware/amazon/awssdk/services/shield/model/DescribeProtectionResponse;
      26: areturn

  public default software.amazon.awssdk.services.shield.model.DescribeSubscriptionResponse describeSubscription() throws software.amazon.awssdk.services.shield.model.InternalErrorException, software.amazon.awssdk.services.shield.model.ResourceNotFoundException, software.amazon.awssdk.awscore.exception.AwsServiceException, software.amazon.awssdk.core.exception.SdkClientException, software.amazon.awssdk.services.shield.model.ShieldException;
    Code:
       0: aload_0
       1: invokestatic  #68                 // Method software/amazon/awssdk/services/shield/model/DescribeSubscriptionRequest.builder:()Lsoftware/amazon/awssdk/services/shield/model/DescribeSubscriptionRequest$Builder;
       4: invokeinterface #69,  1           // InterfaceMethod software/amazon/awssdk/services/shield/model/DescribeSubscriptionRequest$Builder.build:()Ljava/lang/Object;
       9: checkcast     #70                 // class software/amazon/awssdk/services/shield/model/DescribeSubscriptionRequest
      12: invokeinterface #71,  2           // InterfaceMethod describeSubscription:(Lsoftware/amazon/awssdk/services/shield/model/DescribeSubscriptionRequest;)Lsoftware/amazon/awssdk/services/shield/model/DescribeSubscriptionResponse;
      17: areturn

  public default software.amazon.awssdk.services.shield.model.DescribeSubscriptionResponse describeSubscription(software.amazon.awssdk.services.shield.model.DescribeSubscriptionRequest) throws software.amazon.awssdk.services.shield.model.InternalErrorException, software.amazon.awssdk.services.shield.model.ResourceNotFoundException, software.amazon.awssdk.awscore.exception.AwsServiceException, software.amazon.awssdk.core.exception.SdkClientException, software.amazon.awssdk.services.shield.model.ShieldException;
    Code:
       0: new           #6                  // class java/lang/UnsupportedOperationException
       3: dup
       4: invokespecial #7                  // Method java/lang/UnsupportedOperationException."<init>":()V
       7: athrow

  public default software.amazon.awssdk.services.shield.model.DescribeSubscriptionResponse describeSubscription(java.util.function.Consumer<software.amazon.awssdk.services.shield.model.DescribeSubscriptionRequest$Builder>) throws software.amazon.awssdk.services.shield.model.InternalErrorException, software.amazon.awssdk.services.shield.model.ResourceNotFoundException, software.amazon.awssdk.awscore.exception.AwsServiceException, software.amazon.awssdk.core.exception.SdkClientException, software.amazon.awssdk.services.shield.model.ShieldException;
    Code:
       0: aload_0
       1: invokestatic  #68                 // Method software/amazon/awssdk/services/shield/model/DescribeSubscriptionRequest.builder:()Lsoftware/amazon/awssdk/services/shield/model/DescribeSubscriptionRequest$Builder;
       4: aload_1
       5: invokeinterface #72,  2           // InterfaceMethod software/amazon/awssdk/services/shield/model/DescribeSubscriptionRequest$Builder.applyMutation:(Ljava/util/function/Consumer;)Lsoftware/amazon/awssdk/utils/builder/SdkBuilder;
      10: checkcast     #73                 // class software/amazon/awssdk/services/shield/model/DescribeSubscriptionRequest$Builder
      13: invokeinterface #69,  1           // InterfaceMethod software/amazon/awssdk/services/shield/model/DescribeSubscriptionRequest$Builder.build:()Ljava/lang/Object;
      18: checkcast     #70                 // class software/amazon/awssdk/services/shield/model/DescribeSubscriptionRequest
      21: invokeinterface #71,  2           // InterfaceMethod describeSubscription:(Lsoftware/amazon/awssdk/services/shield/model/DescribeSubscriptionRequest;)Lsoftware/amazon/awssdk/services/shield/model/DescribeSubscriptionResponse;
      26: areturn

  public default software.amazon.awssdk.services.shield.model.DisassociateDrtLogBucketResponse disassociateDRTLogBucket(software.amazon.awssdk.services.shield.model.DisassociateDrtLogBucketRequest) throws software.amazon.awssdk.services.shield.model.InternalErrorException, software.amazon.awssdk.services.shield.model.InvalidOperationException, software.amazon.awssdk.services.shield.model.NoAssociatedRoleException, software.amazon.awssdk.services.shield.model.AccessDeniedForDependencyException, software.amazon.awssdk.services.shield.model.OptimisticLockException, software.amazon.awssdk.services.shield.model.ResourceNotFoundException, software.amazon.awssdk.awscore.exception.AwsServiceException, software.amazon.awssdk.core.exception.SdkClientException, software.amazon.awssdk.services.shield.model.ShieldException;
    Code:
       0: new           #6                  // class java/lang/UnsupportedOperationException
       3: dup
       4: invokespecial #7                  // Method java/lang/UnsupportedOperationException."<init>":()V
       7: athrow

  public default software.amazon.awssdk.services.shield.model.DisassociateDrtLogBucketResponse disassociateDRTLogBucket(java.util.function.Consumer<software.amazon.awssdk.services.shield.model.DisassociateDrtLogBucketRequest$Builder>) throws software.amazon.awssdk.services.shield.model.InternalErrorException, software.amazon.awssdk.services.shield.model.InvalidOperationException, software.amazon.awssdk.services.shield.model.NoAssociatedRoleException, software.amazon.awssdk.services.shield.model.AccessDeniedForDependencyException, software.amazon.awssdk.services.shield.model.OptimisticLockException, software.amazon.awssdk.services.shield.model.ResourceNotFoundException, software.amazon.awssdk.awscore.exception.AwsServiceException, software.amazon.awssdk.core.exception.SdkClientException, software.amazon.awssdk.services.shield.model.ShieldException;
    Code:
       0: aload_0
       1: invokestatic  #74                 // Method software/amazon/awssdk/services/shield/model/DisassociateDrtLogBucketRequest.builder:()Lsoftware/amazon/awssdk/services/shield/model/DisassociateDrtLogBucketRequest$Builder;
       4: aload_1
       5: invokeinterface #75,  2           // InterfaceMethod software/amazon/awssdk/services/shield/model/DisassociateDrtLogBucketRequest$Builder.applyMutation:(Ljava/util/function/Consumer;)Lsoftware/amazon/awssdk/utils/builder/SdkBuilder;
      10: checkcast     #76                 // class software/amazon/awssdk/services/shield/model/DisassociateDrtLogBucketRequest$Builder
      13: invokeinterface #77,  1           // InterfaceMethod software/amazon/awssdk/services/shield/model/DisassociateDrtLogBucketRequest$Builder.build:()Ljava/lang/Object;
      18: checkcast     #78                 // class software/amazon/awssdk/services/shield/model/DisassociateDrtLogBucketRequest
      21: invokeinterface #79,  2           // InterfaceMethod disassociateDRTLogBucket:(Lsoftware/amazon/awssdk/services/shield/model/DisassociateDrtLogBucketRequest;)Lsoftware/amazon/awssdk/services/shield/model/DisassociateDrtLogBucketResponse;
      26: areturn

  public default software.amazon.awssdk.services.shield.model.DisassociateDrtRoleResponse disassociateDRTRole() throws software.amazon.awssdk.services.shield.model.InternalErrorException, software.amazon.awssdk.services.shield.model.InvalidOperationException, software.amazon.awssdk.services.shield.model.OptimisticLockException, software.amazon.awssdk.services.shield.model.ResourceNotFoundException, software.amazon.awssdk.awscore.exception.AwsServiceException, software.amazon.awssdk.core.exception.SdkClientException, software.amazon.awssdk.services.shield.model.ShieldException;
    Code:
       0: aload_0
       1: invokestatic  #80                 // Method software/amazon/awssdk/services/shield/model/DisassociateDrtRoleRequest.builder:()Lsoftware/amazon/awssdk/services/shield/model/DisassociateDrtRoleRequest$Builder;
       4: invokeinterface #81,  1           // InterfaceMethod software/amazon/awssdk/services/shield/model/DisassociateDrtRoleRequest$Builder.build:()Ljava/lang/Object;
       9: checkcast     #82                 // class software/amazon/awssdk/services/shield/model/DisassociateDrtRoleRequest
      12: invokeinterface #83,  2           // InterfaceMethod disassociateDRTRole:(Lsoftware/amazon/awssdk/services/shield/model/DisassociateDrtRoleRequest;)Lsoftware/amazon/awssdk/services/shield/model/DisassociateDrtRoleResponse;
      17: areturn

  public default software.amazon.awssdk.services.shield.model.DisassociateDrtRoleResponse disassociateDRTRole(software.amazon.awssdk.services.shield.model.DisassociateDrtRoleRequest) throws software.amazon.awssdk.services.shield.model.InternalErrorException, software.amazon.awssdk.services.shield.model.InvalidOperationException, software.amazon.awssdk.services.shield.model.OptimisticLockException, software.amazon.awssdk.services.shield.model.ResourceNotFoundException, software.amazon.awssdk.awscore.exception.AwsServiceException, software.amazon.awssdk.core.exception.SdkClientException, software.amazon.awssdk.services.shield.model.ShieldException;
    Code:
       0: new           #6                  // class java/lang/UnsupportedOperationException
       3: dup
       4: invokespecial #7                  // Method java/lang/UnsupportedOperationException."<init>":()V
       7: athrow

  public default software.amazon.awssdk.services.shield.model.DisassociateDrtRoleResponse disassociateDRTRole(java.util.function.Consumer<software.amazon.awssdk.services.shield.model.DisassociateDrtRoleRequest$Builder>) throws software.amazon.awssdk.services.shield.model.InternalErrorException, software.amazon.awssdk.services.shield.model.InvalidOperationException, software.amazon.awssdk.services.shield.model.OptimisticLockException, software.amazon.awssdk.services.shield.model.ResourceNotFoundException, software.amazon.awssdk.awscore.exception.AwsServiceException, software.amazon.awssdk.core.exception.SdkClientException, software.amazon.awssdk.services.shield.model.ShieldException;
    Code:
       0: aload_0
       1: invokestatic  #80                 // Method software/amazon/awssdk/services/shield/model/DisassociateDrtRoleRequest.builder:()Lsoftware/amazon/awssdk/services/shield/model/DisassociateDrtRoleRequest$Builder;
       4: aload_1
       5: invokeinterface #84,  2           // InterfaceMethod software/amazon/awssdk/services/shield/model/DisassociateDrtRoleRequest$Builder.applyMutation:(Ljava/util/function/Consumer;)Lsoftware/amazon/awssdk/utils/builder/SdkBuilder;
      10: checkcast     #85                 // class software/amazon/awssdk/services/shield/model/DisassociateDrtRoleRequest$Builder
      13: invokeinterface #81,  1           // InterfaceMethod software/amazon/awssdk/services/shield/model/DisassociateDrtRoleRequest$Builder.build:()Ljava/lang/Object;
      18: checkcast     #82                 // class software/amazon/awssdk/services/shield/model/DisassociateDrtRoleRequest
      21: invokeinterface #83,  2           // InterfaceMethod disassociateDRTRole:(Lsoftware/amazon/awssdk/services/shield/model/DisassociateDrtRoleRequest;)Lsoftware/amazon/awssdk/services/shield/model/DisassociateDrtRoleResponse;
      26: areturn

  public default software.amazon.awssdk.services.shield.model.DisassociateHealthCheckResponse disassociateHealthCheck(software.amazon.awssdk.services.shield.model.DisassociateHealthCheckRequest) throws software.amazon.awssdk.services.shield.model.InternalErrorException, software.amazon.awssdk.services.shield.model.InvalidParameterException, software.amazon.awssdk.services.shield.model.ResourceNotFoundException, software.amazon.awssdk.services.shield.model.OptimisticLockException, software.amazon.awssdk.awscore.exception.AwsServiceException, software.amazon.awssdk.core.exception.SdkClientException, software.amazon.awssdk.services.shield.model.ShieldException;
    Code:
       0: new           #6                  // class java/lang/UnsupportedOperationException
       3: dup
       4: invokespecial #7                  // Method java/lang/UnsupportedOperationException."<init>":()V
       7: athrow

  public default software.amazon.awssdk.services.shield.model.DisassociateHealthCheckResponse disassociateHealthCheck(java.util.function.Consumer<software.amazon.awssdk.services.shield.model.DisassociateHealthCheckRequest$Builder>) throws software.amazon.awssdk.services.shield.model.InternalErrorException, software.amazon.awssdk.services.shield.model.InvalidParameterException, software.amazon.awssdk.services.shield.model.ResourceNotFoundException, software.amazon.awssdk.services.shield.model.OptimisticLockException, software.amazon.awssdk.awscore.exception.AwsServiceException, software.amazon.awssdk.core.exception.SdkClientException, software.amazon.awssdk.services.shield.model.ShieldException;
    Code:
       0: aload_0
       1: invokestatic  #86                 // Method software/amazon/awssdk/services/shield/model/DisassociateHealthCheckRequest.builder:()Lsoftware/amazon/awssdk/services/shield/model/DisassociateHealthCheckRequest$Builder;
       4: aload_1
       5: invokeinterface #87,  2           // InterfaceMethod software/amazon/awssdk/services/shield/model/DisassociateHealthCheckRequest$Builder.applyMutation:(Ljava/util/function/Consumer;)Lsoftware/amazon/awssdk/utils/builder/SdkBuilder;
      10: checkcast     #88                 // class software/amazon/awssdk/services/shield/model/DisassociateHealthCheckRequest$Builder
      13: invokeinterface #89,  1           // InterfaceMethod software/amazon/awssdk/services/shield/model/DisassociateHealthCheckRequest$Builder.build:()Ljava/lang/Object;
      18: checkcast     #90                 // class software/amazon/awssdk/services/shield/model/DisassociateHealthCheckRequest
      21: invokeinterface #91,  2           // InterfaceMethod disassociateHealthCheck:(Lsoftware/amazon/awssdk/services/shield/model/DisassociateHealthCheckRequest;)Lsoftware/amazon/awssdk/services/shield/model/DisassociateHealthCheckResponse;
      26: areturn

  public default software.amazon.awssdk.services.shield.model.GetSubscriptionStateResponse getSubscriptionState() throws software.amazon.awssdk.services.shield.model.InternalErrorException, software.amazon.awssdk.awscore.exception.AwsServiceException, software.amazon.awssdk.core.exception.SdkClientException, software.amazon.awssdk.services.shield.model.ShieldException;
    Code:
       0: aload_0
       1: invokestatic  #92                 // Method software/amazon/awssdk/services/shield/model/GetSubscriptionStateRequest.builder:()Lsoftware/amazon/awssdk/services/shield/model/GetSubscriptionStateRequest$Builder;
       4: invokeinterface #93,  1           // InterfaceMethod software/amazon/awssdk/services/shield/model/GetSubscriptionStateRequest$Builder.build:()Ljava/lang/Object;
       9: checkcast     #94                 // class software/amazon/awssdk/services/shield/model/GetSubscriptionStateRequest
      12: invokeinterface #95,  2           // InterfaceMethod getSubscriptionState:(Lsoftware/amazon/awssdk/services/shield/model/GetSubscriptionStateRequest;)Lsoftware/amazon/awssdk/services/shield/model/GetSubscriptionStateResponse;
      17: areturn

  public default software.amazon.awssdk.services.shield.model.GetSubscriptionStateResponse getSubscriptionState(software.amazon.awssdk.services.shield.model.GetSubscriptionStateRequest) throws software.amazon.awssdk.services.shield.model.InternalErrorException, software.amazon.awssdk.awscore.exception.AwsServiceException, software.amazon.awssdk.core.exception.SdkClientException, software.amazon.awssdk.services.shield.model.ShieldException;
    Code:
       0: new           #6                  // class java/lang/UnsupportedOperationException
       3: dup
       4: invokespecial #7                  // Method java/lang/UnsupportedOperationException."<init>":()V
       7: athrow

  public default software.amazon.awssdk.services.shield.model.GetSubscriptionStateResponse getSubscriptionState(java.util.function.Consumer<software.amazon.awssdk.services.shield.model.GetSubscriptionStateRequest$Builder>) throws software.amazon.awssdk.services.shield.model.InternalErrorException, software.amazon.awssdk.awscore.exception.AwsServiceException, software.amazon.awssdk.core.exception.SdkClientException, software.amazon.awssdk.services.shield.model.ShieldException;
    Code:
       0: aload_0
       1: invokestatic  #92                 // Method software/amazon/awssdk/services/shield/model/GetSubscriptionStateRequest.builder:()Lsoftware/amazon/awssdk/services/shield/model/GetSubscriptionStateRequest$Builder;
       4: aload_1
       5: invokeinterface #96,  2           // InterfaceMethod software/amazon/awssdk/services/shield/model/GetSubscriptionStateRequest$Builder.applyMutation:(Ljava/util/function/Consumer;)Lsoftware/amazon/awssdk/utils/builder/SdkBuilder;
      10: checkcast     #97                 // class software/amazon/awssdk/services/shield/model/GetSubscriptionStateRequest$Builder
      13: invokeinterface #93,  1           // InterfaceMethod software/amazon/awssdk/services/shield/model/GetSubscriptionStateRequest$Builder.build:()Ljava/lang/Object;
      18: checkcast     #94                 // class software/amazon/awssdk/services/shield/model/GetSubscriptionStateRequest
      21: invokeinterface #95,  2           // InterfaceMethod getSubscriptionState:(Lsoftware/amazon/awssdk/services/shield/model/GetSubscriptionStateRequest;)Lsoftware/amazon/awssdk/services/shield/model/GetSubscriptionStateResponse;
      26: areturn

  public default software.amazon.awssdk.services.shield.model.ListAttacksResponse listAttacks() throws software.amazon.awssdk.services.shield.model.InternalErrorException, software.amazon.awssdk.services.shield.model.InvalidParameterException, software.amazon.awssdk.services.shield.model.InvalidOperationException, software.amazon.awssdk.awscore.exception.AwsServiceException, software.amazon.awssdk.core.exception.SdkClientException, software.amazon.awssdk.services.shield.model.ShieldException;
    Code:
       0: aload_0
       1: invokestatic  #98                 // Method software/amazon/awssdk/services/shield/model/ListAttacksRequest.builder:()Lsoftware/amazon/awssdk/services/shield/model/ListAttacksRequest$Builder;
       4: invokeinterface #99,  1           // InterfaceMethod software/amazon/awssdk/services/shield/model/ListAttacksRequest$Builder.build:()Ljava/lang/Object;
       9: checkcast     #100                // class software/amazon/awssdk/services/shield/model/ListAttacksRequest
      12: invokeinterface #101,  2          // InterfaceMethod listAttacks:(Lsoftware/amazon/awssdk/services/shield/model/ListAttacksRequest;)Lsoftware/amazon/awssdk/services/shield/model/ListAttacksResponse;
      17: areturn

  public default software.amazon.awssdk.services.shield.model.ListAttacksResponse listAttacks(software.amazon.awssdk.services.shield.model.ListAttacksRequest) throws software.amazon.awssdk.services.shield.model.InternalErrorException, software.amazon.awssdk.services.shield.model.InvalidParameterException, software.amazon.awssdk.services.shield.model.InvalidOperationException, software.amazon.awssdk.awscore.exception.AwsServiceException, software.amazon.awssdk.core.exception.SdkClientException, software.amazon.awssdk.services.shield.model.ShieldException;
    Code:
       0: new           #6                  // class java/lang/UnsupportedOperationException
       3: dup
       4: invokespecial #7                  // Method java/lang/UnsupportedOperationException."<init>":()V
       7: athrow

  public default software.amazon.awssdk.services.shield.model.ListAttacksResponse listAttacks(java.util.function.Consumer<software.amazon.awssdk.services.shield.model.ListAttacksRequest$Builder>) throws software.amazon.awssdk.services.shield.model.InternalErrorException, software.amazon.awssdk.services.shield.model.InvalidParameterException, software.amazon.awssdk.services.shield.model.InvalidOperationException, software.amazon.awssdk.awscore.exception.AwsServiceException, software.amazon.awssdk.core.exception.SdkClientException, software.amazon.awssdk.services.shield.model.ShieldException;
    Code:
       0: aload_0
       1: invokestatic  #98                 // Method software/amazon/awssdk/services/shield/model/ListAttacksRequest.builder:()Lsoftware/amazon/awssdk/services/shield/model/ListAttacksRequest$Builder;
       4: aload_1
       5: invokeinterface #102,  2          // InterfaceMethod software/amazon/awssdk/services/shield/model/ListAttacksRequest$Builder.applyMutation:(Ljava/util/function/Consumer;)Lsoftware/amazon/awssdk/utils/builder/SdkBuilder;
      10: checkcast     #103                // class software/amazon/awssdk/services/shield/model/ListAttacksRequest$Builder
      13: invokeinterface #99,  1           // InterfaceMethod software/amazon/awssdk/services/shield/model/ListAttacksRequest$Builder.build:()Ljava/lang/Object;
      18: checkcast     #100                // class software/amazon/awssdk/services/shield/model/ListAttacksRequest
      21: invokeinterface #101,  2          // InterfaceMethod listAttacks:(Lsoftware/amazon/awssdk/services/shield/model/ListAttacksRequest;)Lsoftware/amazon/awssdk/services/shield/model/ListAttacksResponse;
      26: areturn

  public default software.amazon.awssdk.services.shield.model.ListProtectionsResponse listProtections() throws software.amazon.awssdk.services.shield.model.InternalErrorException, software.amazon.awssdk.services.shield.model.ResourceNotFoundException, software.amazon.awssdk.services.shield.model.InvalidPaginationTokenException, software.amazon.awssdk.awscore.exception.AwsServiceException, software.amazon.awssdk.core.exception.SdkClientException, software.amazon.awssdk.services.shield.model.ShieldException;
    Code:
       0: aload_0
       1: invokestatic  #104                // Method software/amazon/awssdk/services/shield/model/ListProtectionsRequest.builder:()Lsoftware/amazon/awssdk/services/shield/model/ListProtectionsRequest$Builder;
       4: invokeinterface #105,  1          // InterfaceMethod software/amazon/awssdk/services/shield/model/ListProtectionsRequest$Builder.build:()Ljava/lang/Object;
       9: checkcast     #106                // class software/amazon/awssdk/services/shield/model/ListProtectionsRequest
      12: invokeinterface #107,  2          // InterfaceMethod listProtections:(Lsoftware/amazon/awssdk/services/shield/model/ListProtectionsRequest;)Lsoftware/amazon/awssdk/services/shield/model/ListProtectionsResponse;
      17: areturn

  public default software.amazon.awssdk.services.shield.model.ListProtectionsResponse listProtections(software.amazon.awssdk.services.shield.model.ListProtectionsRequest) throws software.amazon.awssdk.services.shield.model.InternalErrorException, software.amazon.awssdk.services.shield.model.ResourceNotFoundException, software.amazon.awssdk.services.shield.model.InvalidPaginationTokenException, software.amazon.awssdk.awscore.exception.AwsServiceException, software.amazon.awssdk.core.exception.SdkClientException, software.amazon.awssdk.services.shield.model.ShieldException;
    Code:
       0: new           #6                  // class java/lang/UnsupportedOperationException
       3: dup
       4: invokespecial #7                  // Method java/lang/UnsupportedOperationException."<init>":()V
       7: athrow

  public default software.amazon.awssdk.services.shield.model.ListProtectionsResponse listProtections(java.util.function.Consumer<software.amazon.awssdk.services.shield.model.ListProtectionsRequest$Builder>) throws software.amazon.awssdk.services.shield.model.InternalErrorException, software.amazon.awssdk.services.shield.model.ResourceNotFoundException, software.amazon.awssdk.services.shield.model.InvalidPaginationTokenException, software.amazon.awssdk.awscore.exception.AwsServiceException, software.amazon.awssdk.core.exception.SdkClientException, software.amazon.awssdk.services.shield.model.ShieldException;
    Code:
       0: aload_0
       1: invokestatic  #104                // Method software/amazon/awssdk/services/shield/model/ListProtectionsRequest.builder:()Lsoftware/amazon/awssdk/services/shield/model/ListProtectionsRequest$Builder;
       4: aload_1
       5: invokeinterface #108,  2          // InterfaceMethod software/amazon/awssdk/services/shield/model/ListProtectionsRequest$Builder.applyMutation:(Ljava/util/function/Consumer;)Lsoftware/amazon/awssdk/utils/builder/SdkBuilder;
      10: checkcast     #109                // class software/amazon/awssdk/services/shield/model/ListProtectionsRequest$Builder
      13: invokeinterface #105,  1          // InterfaceMethod software/amazon/awssdk/services/shield/model/ListProtectionsRequest$Builder.build:()Ljava/lang/Object;
      18: checkcast     #106                // class software/amazon/awssdk/services/shield/model/ListProtectionsRequest
      21: invokeinterface #107,  2          // InterfaceMethod listProtections:(Lsoftware/amazon/awssdk/services/shield/model/ListProtectionsRequest;)Lsoftware/amazon/awssdk/services/shield/model/ListProtectionsResponse;
      26: areturn

  public default software.amazon.awssdk.services.shield.model.UpdateEmergencyContactSettingsResponse updateEmergencyContactSettings(software.amazon.awssdk.services.shield.model.UpdateEmergencyContactSettingsRequest) throws software.amazon.awssdk.services.shield.model.InternalErrorException, software.amazon.awssdk.services.shield.model.InvalidParameterException, software.amazon.awssdk.services.shield.model.OptimisticLockException, software.amazon.awssdk.services.shield.model.ResourceNotFoundException, software.amazon.awssdk.awscore.exception.AwsServiceException, software.amazon.awssdk.core.exception.SdkClientException, software.amazon.awssdk.services.shield.model.ShieldException;
    Code:
       0: new           #6                  // class java/lang/UnsupportedOperationException
       3: dup
       4: invokespecial #7                  // Method java/lang/UnsupportedOperationException."<init>":()V
       7: athrow

  public default software.amazon.awssdk.services.shield.model.UpdateEmergencyContactSettingsResponse updateEmergencyContactSettings(java.util.function.Consumer<software.amazon.awssdk.services.shield.model.UpdateEmergencyContactSettingsRequest$Builder>) throws software.amazon.awssdk.services.shield.model.InternalErrorException, software.amazon.awssdk.services.shield.model.InvalidParameterException, software.amazon.awssdk.services.shield.model.OptimisticLockException, software.amazon.awssdk.services.shield.model.ResourceNotFoundException, software.amazon.awssdk.awscore.exception.AwsServiceException, software.amazon.awssdk.core.exception.SdkClientException, software.amazon.awssdk.services.shield.model.ShieldException;
    Code:
       0: aload_0
       1: invokestatic  #110                // Method software/amazon/awssdk/services/shield/model/UpdateEmergencyContactSettingsRequest.builder:()Lsoftware/amazon/awssdk/services/shield/model/UpdateEmergencyContactSettingsRequest$Builder;
       4: aload_1
       5: invokeinterface #111,  2          // InterfaceMethod software/amazon/awssdk/services/shield/model/UpdateEmergencyContactSettingsRequest$Builder.applyMutation:(Ljava/util/function/Consumer;)Lsoftware/amazon/awssdk/utils/builder/SdkBuilder;
      10: checkcast     #112                // class software/amazon/awssdk/services/shield/model/UpdateEmergencyContactSettingsRequest$Builder
      13: invokeinterface #113,  1          // InterfaceMethod software/amazon/awssdk/services/shield/model/UpdateEmergencyContactSettingsRequest$Builder.build:()Ljava/lang/Object;
      18: checkcast     #114                // class software/amazon/awssdk/services/shield/model/UpdateEmergencyContactSettingsRequest
      21: invokeinterface #115,  2          // InterfaceMethod updateEmergencyContactSettings:(Lsoftware/amazon/awssdk/services/shield/model/UpdateEmergencyContactSettingsRequest;)Lsoftware/amazon/awssdk/services/shield/model/UpdateEmergencyContactSettingsResponse;
      26: areturn

  public default software.amazon.awssdk.services.shield.model.UpdateSubscriptionResponse updateSubscription(software.amazon.awssdk.services.shield.model.UpdateSubscriptionRequest) throws software.amazon.awssdk.services.shield.model.InternalErrorException, software.amazon.awssdk.services.shield.model.LockedSubscriptionException, software.amazon.awssdk.services.shield.model.ResourceNotFoundException, software.amazon.awssdk.services.shield.model.InvalidParameterException, software.amazon.awssdk.services.shield.model.OptimisticLockException, software.amazon.awssdk.awscore.exception.AwsServiceException, software.amazon.awssdk.core.exception.SdkClientException, software.amazon.awssdk.services.shield.model.ShieldException;
    Code:
       0: new           #6                  // class java/lang/UnsupportedOperationException
       3: dup
       4: invokespecial #7                  // Method java/lang/UnsupportedOperationException."<init>":()V
       7: athrow

  public default software.amazon.awssdk.services.shield.model.UpdateSubscriptionResponse updateSubscription(java.util.function.Consumer<software.amazon.awssdk.services.shield.model.UpdateSubscriptionRequest$Builder>) throws software.amazon.awssdk.services.shield.model.InternalErrorException, software.amazon.awssdk.services.shield.model.LockedSubscriptionException, software.amazon.awssdk.services.shield.model.ResourceNotFoundException, software.amazon.awssdk.services.shield.model.InvalidParameterException, software.amazon.awssdk.services.shield.model.OptimisticLockException, software.amazon.awssdk.awscore.exception.AwsServiceException, software.amazon.awssdk.core.exception.SdkClientException, software.amazon.awssdk.services.shield.model.ShieldException;
    Code:
       0: aload_0
       1: invokestatic  #116                // Method software/amazon/awssdk/services/shield/model/UpdateSubscriptionRequest.builder:()Lsoftware/amazon/awssdk/services/shield/model/UpdateSubscriptionRequest$Builder;
       4: aload_1
       5: invokeinterface #117,  2          // InterfaceMethod software/amazon/awssdk/services/shield/model/UpdateSubscriptionRequest$Builder.applyMutation:(Ljava/util/function/Consumer;)Lsoftware/amazon/awssdk/utils/builder/SdkBuilder;
      10: checkcast     #118                // class software/amazon/awssdk/services/shield/model/UpdateSubscriptionRequest$Builder
      13: invokeinterface #119,  1          // InterfaceMethod software/amazon/awssdk/services/shield/model/UpdateSubscriptionRequest$Builder.build:()Ljava/lang/Object;
      18: checkcast     #120                // class software/amazon/awssdk/services/shield/model/UpdateSubscriptionRequest
      21: invokeinterface #121,  2          // InterfaceMethod updateSubscription:(Lsoftware/amazon/awssdk/services/shield/model/UpdateSubscriptionRequest;)Lsoftware/amazon/awssdk/services/shield/model/UpdateSubscriptionResponse;
      26: areturn

  public static software.amazon.awssdk.regions.ServiceMetadata serviceMetadata();
    Code:
       0: ldc           #122                // String shield
       2: invokestatic  #123                // InterfaceMethod software/amazon/awssdk/regions/ServiceMetadata.of:(Ljava/lang/String;)Lsoftware/amazon/awssdk/regions/ServiceMetadata;
       5: areturn
}
