Compiled from "JCacheCacheStatisticsProvider.java"
public class org.springframework.boot.actuate.cache.JCacheCacheStatisticsProvider extends org.springframework.boot.actuate.cache.AbstractJmxCacheStatisticsProvider<org.springframework.cache.jcache.JCacheCache> {
  public org.springframework.boot.actuate.cache.JCacheCacheStatisticsProvider();
    Code:
       0: aload_0
       1: invokespecial #1                  // Method org/springframework/boot/actuate/cache/AbstractJmxCacheStatisticsProvider."<init>":()V
       4: return

  protected javax.management.ObjectName getObjectName(org.springframework.cache.jcache.JCacheCache) throws javax.management.MalformedObjectNameException;
    Code:
       0: new           #2                  // class javax/management/ObjectName
       3: dup
       4: new           #3                  // class java/lang/StringBuilder
       7: dup
       8: invokespecial #4                  // Method java/lang/StringBuilder."<init>":()V
      11: ldc           #5                  // String javax.cache:type=CacheStatistics,Cache=
      13: invokevirtual #6                  // Method java/lang/StringBuilder.append:(Ljava/lang/String;)Ljava/lang/StringBuilder;
      16: aload_1
      17: invokevirtual #7                  // Method org/springframework/cache/jcache/JCacheCache.getName:()Ljava/lang/String;
      20: invokevirtual #6                  // Method java/lang/StringBuilder.append:(Ljava/lang/String;)Ljava/lang/StringBuilder;
      23: ldc           #8                  // String ,*
      25: invokevirtual #6                  // Method java/lang/StringBuilder.append:(Ljava/lang/String;)Ljava/lang/StringBuilder;
      28: invokevirtual #9                  // Method java/lang/StringBuilder.toString:()Ljava/lang/String;
      31: invokespecial #10                 // Method javax/management/ObjectName."<init>":(Ljava/lang/String;)V
      34: astore_2
      35: aload_0
      36: invokevirtual #11                 // Method getMBeanServer:()Ljavax/management/MBeanServer;
      39: aload_2
      40: aconst_null
      41: invokeinterface #12,  3           // InterfaceMethod javax/management/MBeanServer.queryMBeans:(Ljavax/management/ObjectName;Ljavax/management/QueryExp;)Ljava/util/Set;
      46: astore_3
      47: aload_3
      48: invokeinterface #13,  1           // InterfaceMethod java/util/Set.size:()I
      53: iconst_1
      54: if_icmpne     75
      57: aload_3
      58: invokeinterface #14,  1           // InterfaceMethod java/util/Set.iterator:()Ljava/util/Iterator;
      63: invokeinterface #15,  1           // InterfaceMethod java/util/Iterator.next:()Ljava/lang/Object;
      68: checkcast     #16                 // class javax/management/ObjectInstance
      71: invokevirtual #17                 // Method javax/management/ObjectInstance.getObjectName:()Ljavax/management/ObjectName;
      74: areturn
      75: aconst_null
      76: areturn

  protected org.springframework.boot.actuate.cache.CacheStatistics getCacheStatistics(javax.management.ObjectName);
    Code:
       0: new           #18                 // class org/springframework/boot/actuate/cache/DefaultCacheStatistics
       3: dup
       4: invokespecial #19                 // Method org/springframework/boot/actuate/cache/DefaultCacheStatistics."<init>":()V
       7: astore_2
       8: aload_0
       9: aload_1
      10: ldc           #20                 // String CacheHitPercentage
      12: ldc           #21                 // class java/lang/Float
      14: invokevirtual #22                 // Method getAttribute:(Ljavax/management/ObjectName;Ljava/lang/String;Ljava/lang/Class;)Ljava/lang/Object;
      17: checkcast     #21                 // class java/lang/Float
      20: astore_3
      21: aload_0
      22: aload_1
      23: ldc           #23                 // String CacheMissPercentage
      25: ldc           #21                 // class java/lang/Float
      27: invokevirtual #22                 // Method getAttribute:(Ljavax/management/ObjectName;Ljava/lang/String;Ljava/lang/Class;)Ljava/lang/Object;
      30: checkcast     #21                 // class java/lang/Float
      33: astore        4
      35: aload_3
      36: ifnull        96
      39: aload         4
      41: ifnull        96
      44: aload_3
      45: invokevirtual #24                 // Method java/lang/Float.floatValue:()F
      48: fconst_0
      49: fcmpl
      50: ifgt          63
      53: aload         4
      55: invokevirtual #24                 // Method java/lang/Float.floatValue:()F
      58: fconst_0
      59: fcmpl
      60: ifle          96
      63: aload_2
      64: aload_3
      65: invokevirtual #24                 // Method java/lang/Float.floatValue:()F
      68: f2d
      69: ldc2_w        #25                 // double 100.0d
      72: ddiv
      73: invokestatic  #27                 // Method java/lang/Double.valueOf:(D)Ljava/lang/Double;
      76: invokevirtual #28                 // Method org/springframework/boot/actuate/cache/DefaultCacheStatistics.setHitRatio:(Ljava/lang/Double;)V
      79: aload_2
      80: aload         4
      82: invokevirtual #24                 // Method java/lang/Float.floatValue:()F
      85: f2d
      86: ldc2_w        #25                 // double 100.0d
      89: ddiv
      90: invokestatic  #27                 // Method java/lang/Double.valueOf:(D)Ljava/lang/Double;
      93: invokevirtual #29                 // Method org/springframework/boot/actuate/cache/DefaultCacheStatistics.setMissRatio:(Ljava/lang/Double;)V
      96: aload_2
      97: areturn

  protected javax.management.ObjectName getObjectName(org.springframework.cache.Cache) throws javax.management.MalformedObjectNameException;
    Code:
       0: aload_0
       1: aload_1
       2: checkcast     #30                 // class org/springframework/cache/jcache/JCacheCache
       5: invokevirtual #31                 // Method getObjectName:(Lorg/springframework/cache/jcache/JCacheCache;)Ljavax/management/ObjectName;
       8: areturn
}
