Compiled from "JandexAnnotationsInfo.java"
public final class org.jboss.as.webservices.deployers.deployment.JandexAnnotationsInfo implements org.jboss.wsf.spi.deployment.AnnotationsInfo {
  private final java.util.List<org.jboss.as.server.deployment.module.ResourceRoot> resourceRoots;

  public org.jboss.as.webservices.deployers.deployment.JandexAnnotationsInfo(org.jboss.as.server.deployment.DeploymentUnit);
    Code:
       0: aload_0
       1: invokespecial #1                  // Method java/lang/Object."<init>":()V
       4: aload_0
       5: aload_1
       6: invokestatic  #2                  // Method org/jboss/as/webservices/util/ASHelper.getResourceRoots:(Lorg/jboss/as/server/deployment/DeploymentUnit;)Ljava/util/List;
       9: putfield      #3                  // Field resourceRoots:Ljava/util/List;
      12: return

  public boolean hasAnnotatedClasses(java.lang.String...);
    Code:
       0: aload_1
       1: ifnonnull     12
       4: new           #4                  // class java/lang/IllegalArgumentException
       7: dup
       8: invokespecial #5                  // Method java/lang/IllegalArgumentException."<init>":()V
      11: athrow
      12: aload_0
      13: getfield      #3                  // Field resourceRoots:Ljava/util/List;
      16: ifnull        129
      19: aconst_null
      20: astore_2
      21: aload_0
      22: getfield      #3                  // Field resourceRoots:Ljava/util/List;
      25: invokeinterface #6,  1            // InterfaceMethod java/util/List.iterator:()Ljava/util/Iterator;
      30: astore_3
      31: aload_3
      32: invokeinterface #7,  1            // InterfaceMethod java/util/Iterator.hasNext:()Z
      37: ifeq          129
      40: aload_3
      41: invokeinterface #8,  1            // InterfaceMethod java/util/Iterator.next:()Ljava/lang/Object;
      46: checkcast     #9                  // class org/jboss/as/server/deployment/module/ResourceRoot
      49: astore        4
      51: aload         4
      53: getstatic     #10                 // Field org/jboss/as/server/deployment/Attachments.ANNOTATION_INDEX:Lorg/jboss/as/server/deployment/AttachmentKey;
      56: invokevirtual #11                 // Method org/jboss/as/server/deployment/module/ResourceRoot.getAttachment:(Lorg/jboss/as/server/deployment/AttachmentKey;)Ljava/lang/Object;
      59: checkcast     #12                 // class org/jboss/jandex/Index
      62: astore_2
      63: aload_2
      64: ifnull        126
      67: aload_1
      68: astore        5
      70: aload         5
      72: arraylength
      73: istore        6
      75: iconst_0
      76: istore        7
      78: iload         7
      80: iload         6
      82: if_icmpge     126
      85: aload         5
      87: iload         7
      89: aaload
      90: astore        8
      92: aload_2
      93: aload         8
      95: invokestatic  #13                 // Method org/jboss/jandex/DotName.createSimple:(Ljava/lang/String;)Lorg/jboss/jandex/DotName;
      98: invokevirtual #14                 // Method org/jboss/jandex/Index.getAnnotations:(Lorg/jboss/jandex/DotName;)Ljava/util/List;
     101: astore        9
     103: aload         9
     105: ifnull        120
     108: aload         9
     110: invokeinterface #15,  1           // InterfaceMethod java/util/List.isEmpty:()Z
     115: ifne          120
     118: iconst_1
     119: ireturn
     120: iinc          7, 1
     123: goto          78
     126: goto          31
     129: iconst_0
     130: ireturn
}
