Compiled from "PropertyBuilder.java"
public class com.fasterxml.jackson.databind.ser.PropertyBuilder {
  protected final com.fasterxml.jackson.databind.SerializationConfig _config;

  protected final com.fasterxml.jackson.databind.BeanDescription _beanDesc;

  protected final com.fasterxml.jackson.annotation.JsonInclude$Include _defaultInclusion;

  protected final com.fasterxml.jackson.databind.AnnotationIntrospector _annotationIntrospector;

  protected java.lang.Object _defaultBean;

  public com.fasterxml.jackson.databind.ser.PropertyBuilder(com.fasterxml.jackson.databind.SerializationConfig, com.fasterxml.jackson.databind.BeanDescription);
    Code:
       0: aload_0
       1: invokespecial #1                  // Method java/lang/Object."<init>":()V
       4: aload_0
       5: aload_1
       6: putfield      #2                  // Field _config:Lcom/fasterxml/jackson/databind/SerializationConfig;
       9: aload_0
      10: aload_2
      11: putfield      #3                  // Field _beanDesc:Lcom/fasterxml/jackson/databind/BeanDescription;
      14: aload_0
      15: aload_2
      16: aload_1
      17: invokevirtual #4                  // Method com/fasterxml/jackson/databind/SerializationConfig.getSerializationInclusion:()Lcom/fasterxml/jackson/annotation/JsonInclude$Include;
      20: invokevirtual #5                  // Method com/fasterxml/jackson/databind/BeanDescription.findSerializationInclusion:(Lcom/fasterxml/jackson/annotation/JsonInclude$Include;)Lcom/fasterxml/jackson/annotation/JsonInclude$Include;
      23: putfield      #6                  // Field _defaultInclusion:Lcom/fasterxml/jackson/annotation/JsonInclude$Include;
      26: aload_0
      27: aload_0
      28: getfield      #2                  // Field _config:Lcom/fasterxml/jackson/databind/SerializationConfig;
      31: invokevirtual #7                  // Method com/fasterxml/jackson/databind/SerializationConfig.getAnnotationIntrospector:()Lcom/fasterxml/jackson/databind/AnnotationIntrospector;
      34: putfield      #8                  // Field _annotationIntrospector:Lcom/fasterxml/jackson/databind/AnnotationIntrospector;
      37: return

  public com.fasterxml.jackson.databind.util.Annotations getClassAnnotations();
    Code:
       0: aload_0
       1: getfield      #3                  // Field _beanDesc:Lcom/fasterxml/jackson/databind/BeanDescription;
       4: invokevirtual #9                  // Method com/fasterxml/jackson/databind/BeanDescription.getClassAnnotations:()Lcom/fasterxml/jackson/databind/util/Annotations;
       7: areturn

  protected com.fasterxml.jackson.databind.ser.BeanPropertyWriter buildWriter(com.fasterxml.jackson.databind.SerializerProvider, com.fasterxml.jackson.databind.introspect.BeanPropertyDefinition, com.fasterxml.jackson.databind.JavaType, com.fasterxml.jackson.databind.JsonSerializer<?>, com.fasterxml.jackson.databind.jsontype.TypeSerializer, com.fasterxml.jackson.databind.jsontype.TypeSerializer, com.fasterxml.jackson.databind.introspect.AnnotatedMember, boolean) throws com.fasterxml.jackson.databind.JsonMappingException;
    Code:
       0: aload_0
       1: aload         7
       3: iload         8
       5: aload_3
       6: invokevirtual #10                 // Method findSerializationType:(Lcom/fasterxml/jackson/databind/introspect/Annotated;ZLcom/fasterxml/jackson/databind/JavaType;)Lcom/fasterxml/jackson/databind/JavaType;
       9: astore        9
      11: aload         6
      13: ifnull        112
      16: aload         9
      18: ifnonnull     24
      21: aload_3
      22: astore        9
      24: aload         9
      26: invokevirtual #11                 // Method com/fasterxml/jackson/databind/JavaType.getContentType:()Lcom/fasterxml/jackson/databind/JavaType;
      29: astore        10
      31: aload         10
      33: ifnonnull     96
      36: new           #12                 // class java/lang/IllegalStateException
      39: dup
      40: new           #13                 // class java/lang/StringBuilder
      43: dup
      44: invokespecial #14                 // Method java/lang/StringBuilder."<init>":()V
      47: ldc           #15                 // String Problem trying to create BeanPropertyWriter for property \'
      49: invokevirtual #16                 // Method java/lang/StringBuilder.append:(Ljava/lang/String;)Ljava/lang/StringBuilder;
      52: aload_2
      53: invokevirtual #17                 // Method com/fasterxml/jackson/databind/introspect/BeanPropertyDefinition.getName:()Ljava/lang/String;
      56: invokevirtual #16                 // Method java/lang/StringBuilder.append:(Ljava/lang/String;)Ljava/lang/StringBuilder;
      59: ldc           #18                 // String \' (of type
      61: invokevirtual #16                 // Method java/lang/StringBuilder.append:(Ljava/lang/String;)Ljava/lang/StringBuilder;
      64: aload_0
      65: getfield      #3                  // Field _beanDesc:Lcom/fasterxml/jackson/databind/BeanDescription;
      68: invokevirtual #19                 // Method com/fasterxml/jackson/databind/BeanDescription.getType:()Lcom/fasterxml/jackson/databind/JavaType;
      71: invokevirtual #20                 // Method java/lang/StringBuilder.append:(Ljava/lang/Object;)Ljava/lang/StringBuilder;
      74: ldc           #21                 // String ); serialization type
      76: invokevirtual #16                 // Method java/lang/StringBuilder.append:(Ljava/lang/String;)Ljava/lang/StringBuilder;
      79: aload         9
      81: invokevirtual #20                 // Method java/lang/StringBuilder.append:(Ljava/lang/Object;)Ljava/lang/StringBuilder;
      84: ldc           #22                 // String  has no content
      86: invokevirtual #16                 // Method java/lang/StringBuilder.append:(Ljava/lang/String;)Ljava/lang/StringBuilder;
      89: invokevirtual #23                 // Method java/lang/StringBuilder.toString:()Ljava/lang/String;
      92: invokespecial #24                 // Method java/lang/IllegalStateException."<init>":(Ljava/lang/String;)V
      95: athrow
      96: aload         9
      98: aload         6
     100: invokevirtual #25                 // Method com/fasterxml/jackson/databind/JavaType.withContentTypeHandler:(Ljava/lang/Object;)Lcom/fasterxml/jackson/databind/JavaType;
     103: astore        9
     105: aload         9
     107: invokevirtual #11                 // Method com/fasterxml/jackson/databind/JavaType.getContentType:()Lcom/fasterxml/jackson/databind/JavaType;
     110: astore        10
     112: aconst_null
     113: astore        10
     115: iconst_0
     116: istore        11
     118: aload_2
     119: invokevirtual #26                 // Method com/fasterxml/jackson/databind/introspect/BeanPropertyDefinition.findInclusion:()Lcom/fasterxml/jackson/annotation/JsonInclude$Include;
     122: astore        12
     124: aload         12
     126: ifnonnull     135
     129: aload_0
     130: getfield      #6                  // Field _defaultInclusion:Lcom/fasterxml/jackson/annotation/JsonInclude$Include;
     133: astore        12
     135: aload         12
     137: ifnull        263
     140: getstatic     #27                 // Field com/fasterxml/jackson/databind/ser/PropertyBuilder$1.$SwitchMap$com$fasterxml$jackson$annotation$JsonInclude$Include:[I
     143: aload         12
     145: invokevirtual #28                 // Method com/fasterxml/jackson/annotation/JsonInclude$Include.ordinal:()I
     148: iaload
     149: tableswitch   { // 1 to 4
                     1: 180
                     2: 224
                     3: 235
                     4: 238
               default: 263
          }
     180: aload_0
     181: aload_2
     182: invokevirtual #17                 // Method com/fasterxml/jackson/databind/introspect/BeanPropertyDefinition.getName:()Ljava/lang/String;
     185: aload         7
     187: invokevirtual #29                 // Method getDefaultValue:(Ljava/lang/String;Lcom/fasterxml/jackson/databind/introspect/AnnotatedMember;)Ljava/lang/Object;
     190: astore        10
     192: aload         10
     194: ifnonnull     203
     197: iconst_1
     198: istore        11
     200: goto          263
     203: aload         10
     205: invokevirtual #30                 // Method java/lang/Object.getClass:()Ljava/lang/Class;
     208: invokevirtual #31                 // Method java/lang/Class.isArray:()Z
     211: ifeq          263
     214: aload         10
     216: invokestatic  #32                 // Method com/fasterxml/jackson/databind/util/ArrayBuilders.getArrayComparator:(Ljava/lang/Object;)Ljava/lang/Object;
     219: astore        10
     221: goto          263
     224: iconst_1
     225: istore        11
     227: getstatic     #33                 // Field com/fasterxml/jackson/databind/ser/BeanPropertyWriter.MARKER_FOR_EMPTY:Ljava/lang/Object;
     230: astore        10
     232: goto          263
     235: iconst_1
     236: istore        11
     238: aload_3
     239: invokevirtual #34                 // Method com/fasterxml/jackson/databind/JavaType.isContainerType:()Z
     242: ifeq          263
     245: aload_0
     246: getfield      #2                  // Field _config:Lcom/fasterxml/jackson/databind/SerializationConfig;
     249: getstatic     #35                 // Field com/fasterxml/jackson/databind/SerializationFeature.WRITE_EMPTY_JSON_ARRAYS:Lcom/fasterxml/jackson/databind/SerializationFeature;
     252: invokevirtual #36                 // Method com/fasterxml/jackson/databind/SerializationConfig.isEnabled:(Lcom/fasterxml/jackson/databind/SerializationFeature;)Z
     255: ifne          263
     258: getstatic     #33                 // Field com/fasterxml/jackson/databind/ser/BeanPropertyWriter.MARKER_FOR_EMPTY:Ljava/lang/Object;
     261: astore        10
     263: new           #37                 // class com/fasterxml/jackson/databind/ser/BeanPropertyWriter
     266: dup
     267: aload_2
     268: aload         7
     270: aload_0
     271: getfield      #3                  // Field _beanDesc:Lcom/fasterxml/jackson/databind/BeanDescription;
     274: invokevirtual #9                  // Method com/fasterxml/jackson/databind/BeanDescription.getClassAnnotations:()Lcom/fasterxml/jackson/databind/util/Annotations;
     277: aload_3
     278: aload         4
     280: aload         5
     282: aload         9
     284: iload         11
     286: aload         10
     288: invokespecial #38                 // Method com/fasterxml/jackson/databind/ser/BeanPropertyWriter."<init>":(Lcom/fasterxml/jackson/databind/introspect/BeanPropertyDefinition;Lcom/fasterxml/jackson/databind/introspect/AnnotatedMember;Lcom/fasterxml/jackson/databind/util/Annotations;Lcom/fasterxml/jackson/databind/JavaType;Lcom/fasterxml/jackson/databind/JsonSerializer;Lcom/fasterxml/jackson/databind/jsontype/TypeSerializer;Lcom/fasterxml/jackson/databind/JavaType;ZLjava/lang/Object;)V
     291: astore        13
     293: aload_0
     294: getfield      #8                  // Field _annotationIntrospector:Lcom/fasterxml/jackson/databind/AnnotationIntrospector;
     297: aload         7
     299: invokevirtual #39                 // Method com/fasterxml/jackson/databind/AnnotationIntrospector.findNullSerializer:(Lcom/fasterxml/jackson/databind/introspect/Annotated;)Ljava/lang/Object;
     302: astore        14
     304: aload         14
     306: ifnull        322
     309: aload         13
     311: aload_1
     312: aload         7
     314: aload         14
     316: invokevirtual #40                 // Method com/fasterxml/jackson/databind/SerializerProvider.serializerInstance:(Lcom/fasterxml/jackson/databind/introspect/Annotated;Ljava/lang/Object;)Lcom/fasterxml/jackson/databind/JsonSerializer;
     319: invokevirtual #41                 // Method com/fasterxml/jackson/databind/ser/BeanPropertyWriter.assignNullSerializer:(Lcom/fasterxml/jackson/databind/JsonSerializer;)V
     322: aload_0
     323: getfield      #8                  // Field _annotationIntrospector:Lcom/fasterxml/jackson/databind/AnnotationIntrospector;
     326: aload         7
     328: invokevirtual #42                 // Method com/fasterxml/jackson/databind/AnnotationIntrospector.findUnwrappingNameTransformer:(Lcom/fasterxml/jackson/databind/introspect/AnnotatedMember;)Lcom/fasterxml/jackson/databind/util/NameTransformer;
     331: astore        15
     333: aload         15
     335: ifnull        347
     338: aload         13
     340: aload         15
     342: invokevirtual #43                 // Method com/fasterxml/jackson/databind/ser/BeanPropertyWriter.unwrappingWriter:(Lcom/fasterxml/jackson/databind/util/NameTransformer;)Lcom/fasterxml/jackson/databind/ser/BeanPropertyWriter;
     345: astore        13
     347: aload         13
     349: areturn

  protected com.fasterxml.jackson.databind.JavaType findSerializationType(com.fasterxml.jackson.databind.introspect.Annotated, boolean, com.fasterxml.jackson.databind.JavaType);
    Code:
       0: aload_0
       1: getfield      #8                  // Field _annotationIntrospector:Lcom/fasterxml/jackson/databind/AnnotationIntrospector;
       4: aload_1
       5: invokevirtual #44                 // Method com/fasterxml/jackson/databind/AnnotationIntrospector.findSerializationType:(Lcom/fasterxml/jackson/databind/introspect/Annotated;)Ljava/lang/Class;
       8: astore        4
      10: aload         4
      12: ifnull        120
      15: aload_3
      16: invokevirtual #45                 // Method com/fasterxml/jackson/databind/JavaType.getRawClass:()Ljava/lang/Class;
      19: astore        5
      21: aload         4
      23: aload         5
      25: invokevirtual #46                 // Method java/lang/Class.isAssignableFrom:(Ljava/lang/Class;)Z
      28: ifeq          41
      31: aload_3
      32: aload         4
      34: invokevirtual #47                 // Method com/fasterxml/jackson/databind/JavaType.widenBy:(Ljava/lang/Class;)Lcom/fasterxml/jackson/databind/JavaType;
      37: astore_3
      38: goto          118
      41: aload         5
      43: aload         4
      45: invokevirtual #46                 // Method java/lang/Class.isAssignableFrom:(Ljava/lang/Class;)Z
      48: ifne          107
      51: new           #48                 // class java/lang/IllegalArgumentException
      54: dup
      55: new           #13                 // class java/lang/StringBuilder
      58: dup
      59: invokespecial #14                 // Method java/lang/StringBuilder."<init>":()V
      62: ldc           #49                 // String Illegal concrete-type annotation for method \'
      64: invokevirtual #16                 // Method java/lang/StringBuilder.append:(Ljava/lang/String;)Ljava/lang/StringBuilder;
      67: aload_1
      68: invokevirtual #50                 // Method com/fasterxml/jackson/databind/introspect/Annotated.getName:()Ljava/lang/String;
      71: invokevirtual #16                 // Method java/lang/StringBuilder.append:(Ljava/lang/String;)Ljava/lang/StringBuilder;
      74: ldc           #51                 // String \': class
      76: invokevirtual #16                 // Method java/lang/StringBuilder.append:(Ljava/lang/String;)Ljava/lang/StringBuilder;
      79: aload         4
      81: invokevirtual #52                 // Method java/lang/Class.getName:()Ljava/lang/String;
      84: invokevirtual #16                 // Method java/lang/StringBuilder.append:(Ljava/lang/String;)Ljava/lang/StringBuilder;
      87: ldc           #53                 // String  not a super-type of (declared) class
      89: invokevirtual #16                 // Method java/lang/StringBuilder.append:(Ljava/lang/String;)Ljava/lang/StringBuilder;
      92: aload         5
      94: invokevirtual #52                 // Method java/lang/Class.getName:()Ljava/lang/String;
      97: invokevirtual #16                 // Method java/lang/StringBuilder.append:(Ljava/lang/String;)Ljava/lang/StringBuilder;
     100: invokevirtual #23                 // Method java/lang/StringBuilder.toString:()Ljava/lang/String;
     103: invokespecial #54                 // Method java/lang/IllegalArgumentException."<init>":(Ljava/lang/String;)V
     106: athrow
     107: aload_0
     108: getfield      #2                  // Field _config:Lcom/fasterxml/jackson/databind/SerializationConfig;
     111: aload_3
     112: aload         4
     114: invokevirtual #55                 // Method com/fasterxml/jackson/databind/SerializationConfig.constructSpecializedType:(Lcom/fasterxml/jackson/databind/JavaType;Ljava/lang/Class;)Lcom/fasterxml/jackson/databind/JavaType;
     117: astore_3
     118: iconst_1
     119: istore_2
     120: aload_0
     121: getfield      #2                  // Field _config:Lcom/fasterxml/jackson/databind/SerializationConfig;
     124: aload_1
     125: aload_3
     126: invokestatic  #56                 // Method com/fasterxml/jackson/databind/ser/BasicSerializerFactory.modifySecondaryTypesByAnnotation:(Lcom/fasterxml/jackson/databind/SerializationConfig;Lcom/fasterxml/jackson/databind/introspect/Annotated;Lcom/fasterxml/jackson/databind/JavaType;)Lcom/fasterxml/jackson/databind/JavaType;
     129: astore        5
     131: aload         5
     133: aload_3
     134: if_acmpeq     142
     137: iconst_1
     138: istore_2
     139: aload         5
     141: astore_3
     142: aload_0
     143: getfield      #8                  // Field _annotationIntrospector:Lcom/fasterxml/jackson/databind/AnnotationIntrospector;
     146: aload_1
     147: invokevirtual #57                 // Method com/fasterxml/jackson/databind/AnnotationIntrospector.findSerializationTyping:(Lcom/fasterxml/jackson/databind/introspect/Annotated;)Lcom/fasterxml/jackson/databind/annotation/JsonSerialize$Typing;
     150: astore        6
     152: aload         6
     154: ifnull        179
     157: aload         6
     159: getstatic     #58                 // Field com/fasterxml/jackson/databind/annotation/JsonSerialize$Typing.DEFAULT_TYPING:Lcom/fasterxml/jackson/databind/annotation/JsonSerialize$Typing;
     162: if_acmpeq     179
     165: aload         6
     167: getstatic     #59                 // Field com/fasterxml/jackson/databind/annotation/JsonSerialize$Typing.STATIC:Lcom/fasterxml/jackson/databind/annotation/JsonSerialize$Typing;
     170: if_acmpne     177
     173: iconst_1
     174: goto          178
     177: iconst_0
     178: istore_2
     179: iload_2
     180: ifeq          187
     183: aload_3
     184: goto          188
     187: aconst_null
     188: areturn

  protected java.lang.Object getDefaultBean();
    Code:
       0: aload_0
       1: getfield      #60                 // Field _defaultBean:Ljava/lang/Object;
       4: ifnonnull     78
       7: aload_0
       8: aload_0
       9: getfield      #3                  // Field _beanDesc:Lcom/fasterxml/jackson/databind/BeanDescription;
      12: aload_0
      13: getfield      #2                  // Field _config:Lcom/fasterxml/jackson/databind/SerializationConfig;
      16: invokevirtual #61                 // Method com/fasterxml/jackson/databind/SerializationConfig.canOverrideAccessModifiers:()Z
      19: invokevirtual #62                 // Method com/fasterxml/jackson/databind/BeanDescription.instantiateBean:(Z)Ljava/lang/Object;
      22: putfield      #60                 // Field _defaultBean:Ljava/lang/Object;
      25: aload_0
      26: getfield      #60                 // Field _defaultBean:Ljava/lang/Object;
      29: ifnonnull     78
      32: aload_0
      33: getfield      #3                  // Field _beanDesc:Lcom/fasterxml/jackson/databind/BeanDescription;
      36: invokevirtual #63                 // Method com/fasterxml/jackson/databind/BeanDescription.getClassInfo:()Lcom/fasterxml/jackson/databind/introspect/AnnotatedClass;
      39: invokevirtual #64                 // Method com/fasterxml/jackson/databind/introspect/AnnotatedClass.getAnnotated:()Ljava/lang/Class;
      42: astore_1
      43: new           #48                 // class java/lang/IllegalArgumentException
      46: dup
      47: new           #13                 // class java/lang/StringBuilder
      50: dup
      51: invokespecial #14                 // Method java/lang/StringBuilder."<init>":()V
      54: ldc           #65                 // String Class
      56: invokevirtual #16                 // Method java/lang/StringBuilder.append:(Ljava/lang/String;)Ljava/lang/StringBuilder;
      59: aload_1
      60: invokevirtual #52                 // Method java/lang/Class.getName:()Ljava/lang/String;
      63: invokevirtual #16                 // Method java/lang/StringBuilder.append:(Ljava/lang/String;)Ljava/lang/StringBuilder;
      66: ldc           #66                 // String  has no default constructor; can not instantiate default bean value to support \'properties=JsonSerialize.Inclusion.NON_DEFAULT\' annotation
      68: invokevirtual #16                 // Method java/lang/StringBuilder.append:(Ljava/lang/String;)Ljava/lang/StringBuilder;
      71: invokevirtual #23                 // Method java/lang/StringBuilder.toString:()Ljava/lang/String;
      74: invokespecial #54                 // Method java/lang/IllegalArgumentException."<init>":(Ljava/lang/String;)V
      77: athrow
      78: aload_0
      79: getfield      #60                 // Field _defaultBean:Ljava/lang/Object;
      82: areturn

  protected java.lang.Object getDefaultValue(java.lang.String, com.fasterxml.jackson.databind.introspect.AnnotatedMember);
    Code:
       0: aload_0
       1: invokevirtual #67                 // Method getDefaultBean:()Ljava/lang/Object;
       4: astore_3
       5: aload_2
       6: aload_3
       7: invokevirtual #68                 // Method com/fasterxml/jackson/databind/introspect/AnnotatedMember.getValue:(Ljava/lang/Object;)Ljava/lang/Object;
      10: areturn
      11: astore        4
      13: aload_0
      14: aload         4
      16: aload_1
      17: aload_3
      18: invokevirtual #70                 // Method _throwWrapped:(Ljava/lang/Exception;Ljava/lang/String;Ljava/lang/Object;)Ljava/lang/Object;
      21: areturn
    Exception table:
       from    to  target type
           5    10    11   Class java/lang/Exception

  protected java.lang.Object _throwWrapped(java.lang.Exception, java.lang.String, java.lang.Object);
    Code:
       0: aload_1
       1: astore        4
       3: aload         4
       5: invokevirtual #71                 // Method java/lang/Throwable.getCause:()Ljava/lang/Throwable;
       8: ifnull        21
      11: aload         4
      13: invokevirtual #71                 // Method java/lang/Throwable.getCause:()Ljava/lang/Throwable;
      16: astore        4
      18: goto          3
      21: aload         4
      23: instanceof    #72                 // class java/lang/Error
      26: ifeq          35
      29: aload         4
      31: checkcast     #72                 // class java/lang/Error
      34: athrow
      35: aload         4
      37: instanceof    #73                 // class java/lang/RuntimeException
      40: ifeq          49
      43: aload         4
      45: checkcast     #73                 // class java/lang/RuntimeException
      48: athrow
      49: new           #48                 // class java/lang/IllegalArgumentException
      52: dup
      53: new           #13                 // class java/lang/StringBuilder
      56: dup
      57: invokespecial #14                 // Method java/lang/StringBuilder."<init>":()V
      60: ldc           #74                 // String Failed to get property \'
      62: invokevirtual #16                 // Method java/lang/StringBuilder.append:(Ljava/lang/String;)Ljava/lang/StringBuilder;
      65: aload_2
      66: invokevirtual #16                 // Method java/lang/StringBuilder.append:(Ljava/lang/String;)Ljava/lang/StringBuilder;
      69: ldc           #75                 // String \' of default
      71: invokevirtual #16                 // Method java/lang/StringBuilder.append:(Ljava/lang/String;)Ljava/lang/StringBuilder;
      74: aload_3
      75: invokevirtual #30                 // Method java/lang/Object.getClass:()Ljava/lang/Class;
      78: invokevirtual #52                 // Method java/lang/Class.getName:()Ljava/lang/String;
      81: invokevirtual #16                 // Method java/lang/StringBuilder.append:(Ljava/lang/String;)Ljava/lang/StringBuilder;
      84: ldc           #76                 // String  instance
      86: invokevirtual #16                 // Method java/lang/StringBuilder.append:(Ljava/lang/String;)Ljava/lang/StringBuilder;
      89: invokevirtual #23                 // Method java/lang/StringBuilder.toString:()Ljava/lang/String;
      92: invokespecial #54                 // Method java/lang/IllegalArgumentException."<init>":(Ljava/lang/String;)V
      95: athrow
}
