Compiled from "GuildMemberEvents.kt"
public final class love.forte.simbot.kaiheila.event.system.guild.member.GuildMemberOfflineEvent extends love.forte.simbot.kaiheila.event.system.SystemEventParserDefinition<love.forte.simbot.kaiheila.event.system.guild.member.GuildMemberOfflineEventBody> {
  public static final love.forte.simbot.kaiheila.event.system.guild.member.GuildMemberOfflineEvent INSTANCE;

  private love.forte.simbot.kaiheila.event.system.guild.member.GuildMemberOfflineEvent();
    Code:
       0: aload_0
       1: invokespecial #9                  // Method love/forte/simbot/kaiheila/event/system/SystemEventParserDefinition."<init>":()V
       4: return

  public love.forte.simbot.kaiheila.event.SysEventParser<love.forte.simbot.kaiheila.event.system.guild.member.GuildMemberOfflineEventBody> getParser();
    Code:
       0: getstatic     #21                 // Field love/forte/simbot/kaiheila/event/system/guild/member/GuildMemberEvents.INSTANCE:Llove/forte/simbot/kaiheila/event/system/guild/member/GuildMemberEvents;
       3: invokevirtual #24                 // Method love/forte/simbot/kaiheila/event/system/guild/member/GuildMemberEvents.getGuildMemberOfflineEventParser:()Llove/forte/simbot/kaiheila/event/SysEventParser;
       6: areturn

  public love.forte.simbot.kaiheila.event.EventParser getParser();
    Code:
       0: aload_0
       1: invokevirtual #27                 // Method getParser:()Llove/forte/simbot/kaiheila/event/SysEventParser;
       4: checkcast     #29                 // class love/forte/simbot/kaiheila/event/EventParser
       7: areturn

  static {};
    Code:
       0: new           #2                  // class love/forte/simbot/kaiheila/event/system/guild/member/GuildMemberOfflineEvent
       3: dup
       4: invokespecial #31                 // Method "<init>":()V
       7: putstatic     #33                 // Field INSTANCE:Llove/forte/simbot/kaiheila/event/system/guild/member/GuildMemberOfflineEvent;
      10: return
}
