Compiled from "FacebookRestApi.scala"
public final class net.liftweb.ext_api.facebook.RsvpAttending {
  public static final scala.collection.Iterator productElements();
    Code:
       0: getstatic     #11                 // Field net/liftweb/ext_api/facebook/RsvpAttending$.MODULE$:Lnet/liftweb/ext_api/facebook/RsvpAttending$;
       3: invokevirtual #13                 // Method net/liftweb/ext_api/facebook/RsvpAttending$.productElements:()Lscala/collection/Iterator;
       6: areturn

  public static final scala.collection.Iterator productIterator();
    Code:
       0: getstatic     #11                 // Field net/liftweb/ext_api/facebook/RsvpAttending$.MODULE$:Lnet/liftweb/ext_api/facebook/RsvpAttending$;
       3: invokevirtual #17                 // Method net/liftweb/ext_api/facebook/RsvpAttending$.productIterator:()Lscala/collection/Iterator;
       6: areturn

  public static final boolean canEqual(java.lang.Object);
    Code:
       0: getstatic     #11                 // Field net/liftweb/ext_api/facebook/RsvpAttending$.MODULE$:Lnet/liftweb/ext_api/facebook/RsvpAttending$;
       3: aload_0
       4: invokevirtual #21                 // Method net/liftweb/ext_api/facebook/RsvpAttending$.canEqual:(Ljava/lang/Object;)Z
       7: ireturn

  public static final java.lang.Object productElement(int);
    Code:
       0: getstatic     #11                 // Field net/liftweb/ext_api/facebook/RsvpAttending$.MODULE$:Lnet/liftweb/ext_api/facebook/RsvpAttending$;
       3: iload_0
       4: invokevirtual #25                 // Method net/liftweb/ext_api/facebook/RsvpAttending$.productElement:(I)Ljava/lang/Object;
       7: areturn

  public static final int productArity();
    Code:
       0: getstatic     #11                 // Field net/liftweb/ext_api/facebook/RsvpAttending$.MODULE$:Lnet/liftweb/ext_api/facebook/RsvpAttending$;
       3: invokevirtual #29                 // Method net/liftweb/ext_api/facebook/RsvpAttending$.productArity:()I
       6: ireturn

  public static final java.lang.String productPrefix();
    Code:
       0: getstatic     #11                 // Field net/liftweb/ext_api/facebook/RsvpAttending$.MODULE$:Lnet/liftweb/ext_api/facebook/RsvpAttending$;
       3: invokevirtual #33                 // Method net/liftweb/ext_api/facebook/RsvpAttending$.productPrefix:()Ljava/lang/String;
       6: areturn

  public static final java.lang.Object value();
    Code:
       0: getstatic     #11                 // Field net/liftweb/ext_api/facebook/RsvpAttending$.MODULE$:Lnet/liftweb/ext_api/facebook/RsvpAttending$;
       3: invokevirtual #37                 // Method net/liftweb/ext_api/facebook/RsvpAttending$.value:()Ljava/lang/Object;
       6: areturn

  public static final java.lang.String key();
    Code:
       0: getstatic     #11                 // Field net/liftweb/ext_api/facebook/RsvpAttending$.MODULE$:Lnet/liftweb/ext_api/facebook/RsvpAttending$;
       3: invokevirtual #40                 // Method net/liftweb/ext_api/facebook/RsvpAttending$.key:()Ljava/lang/String;
       6: areturn
}
