Compiled from "ResourceLoader.java"
public abstract class io.sundr.shaded.org.apache.velocity.runtime.resource.loader.ResourceLoader {
  protected boolean isCachingOn;

  protected long modificationCheckInterval;

  protected java.lang.String className;

  protected io.sundr.shaded.org.apache.velocity.runtime.RuntimeServices rsvc;

  protected io.sundr.shaded.org.apache.velocity.runtime.log.Log log;

  static java.lang.Class class$org$apache$velocity$runtime$resource$ResourceCacheImpl;

  public io.sundr.shaded.org.apache.velocity.runtime.resource.loader.ResourceLoader();
    Code:
       0: aload_0
       1: invokespecial #21                 // Method java/lang/Object."<init>":()V
       4: aload_0
       5: iconst_0
       6: putfield      #23                 // Field isCachingOn:Z
       9: aload_0
      10: ldc2_w        #24                 // long 2l
      13: putfield      #27                 // Field modificationCheckInterval:J
      16: aload_0
      17: aconst_null
      18: putfield      #29                 // Field className:Ljava/lang/String;
      21: aload_0
      22: aconst_null
      23: putfield      #31                 // Field rsvc:Lio/sundr/shaded/org/apache/velocity/runtime/RuntimeServices;
      26: aload_0
      27: aconst_null
      28: putfield      #33                 // Field log:Lio/sundr/shaded/org/apache/velocity/runtime/log/Log;
      31: return

  public void commonInit(io.sundr.shaded.org.apache.velocity.runtime.RuntimeServices, org.apache.commons.collections.ExtendedProperties);
    Code:
       0: aload_0
       1: aload_1
       2: putfield      #31                 // Field rsvc:Lio/sundr/shaded/org/apache/velocity/runtime/RuntimeServices;
       5: aload_0
       6: aload_0
       7: getfield      #31                 // Field rsvc:Lio/sundr/shaded/org/apache/velocity/runtime/RuntimeServices;
      10: invokeinterface #45,  1           // InterfaceMethod io/sundr/shaded/org/apache/velocity/runtime/RuntimeServices.getLog:()Lio/sundr/shaded/org/apache/velocity/runtime/log/Log;
      15: putfield      #33                 // Field log:Lio/sundr/shaded/org/apache/velocity/runtime/log/Log;
      18: aload_0
      19: aload_2
      20: ldc           #47                 // String cache
      22: iconst_0
      23: invokevirtual #53                 // Method org/apache/commons/collections/ExtendedProperties.getBoolean:(Ljava/lang/String;Z)Z
      26: putfield      #23                 // Field isCachingOn:Z
      29: goto          85
      32: astore_3
      33: aload_0
      34: iconst_0
      35: putfield      #23                 // Field isCachingOn:Z
      38: new           #55                 // class java/lang/StringBuffer
      41: dup
      42: invokespecial #56                 // Method java/lang/StringBuffer."<init>":()V
      45: ldc           #58                 // String Exception parsing cache setting:
      47: invokevirtual #62                 // Method java/lang/StringBuffer.append:(Ljava/lang/String;)Ljava/lang/StringBuffer;
      50: aload_2
      51: ldc           #47                 // String cache
      53: invokevirtual #66                 // Method org/apache/commons/collections/ExtendedProperties.getString:(Ljava/lang/String;)Ljava/lang/String;
      56: invokevirtual #62                 // Method java/lang/StringBuffer.append:(Ljava/lang/String;)Ljava/lang/StringBuffer;
      59: invokevirtual #70                 // Method java/lang/StringBuffer.toString:()Ljava/lang/String;
      62: astore        4
      64: aload_0
      65: getfield      #33                 // Field log:Lio/sundr/shaded/org/apache/velocity/runtime/log/Log;
      68: aload         4
      70: aload_3
      71: invokevirtual #76                 // Method io/sundr/shaded/org/apache/velocity/runtime/log/Log.error:(Ljava/lang/Object;Ljava/lang/Throwable;)V
      74: new           #78                 // class io/sundr/shaded/org/apache/velocity/exception/VelocityException
      77: dup
      78: aload         4
      80: aload_3
      81: invokespecial #81                 // Method io/sundr/shaded/org/apache/velocity/exception/VelocityException."<init>":(Ljava/lang/String;Ljava/lang/Throwable;)V
      84: athrow
      85: aload_0
      86: aload_2
      87: ldc           #82                 // String modificationCheckInterval
      89: lconst_0
      90: invokevirtual #86                 // Method org/apache/commons/collections/ExtendedProperties.getLong:(Ljava/lang/String;J)J
      93: putfield      #27                 // Field modificationCheckInterval:J
      96: goto          152
      99: astore_3
     100: aload_0
     101: lconst_0
     102: putfield      #27                 // Field modificationCheckInterval:J
     105: new           #55                 // class java/lang/StringBuffer
     108: dup
     109: invokespecial #56                 // Method java/lang/StringBuffer."<init>":()V
     112: ldc           #88                 // String Exception parsing modificationCheckInterval setting:
     114: invokevirtual #62                 // Method java/lang/StringBuffer.append:(Ljava/lang/String;)Ljava/lang/StringBuffer;
     117: aload_2
     118: ldc           #82                 // String modificationCheckInterval
     120: invokevirtual #66                 // Method org/apache/commons/collections/ExtendedProperties.getString:(Ljava/lang/String;)Ljava/lang/String;
     123: invokevirtual #62                 // Method java/lang/StringBuffer.append:(Ljava/lang/String;)Ljava/lang/StringBuffer;
     126: invokevirtual #70                 // Method java/lang/StringBuffer.toString:()Ljava/lang/String;
     129: astore        4
     131: aload_0
     132: getfield      #33                 // Field log:Lio/sundr/shaded/org/apache/velocity/runtime/log/Log;
     135: aload         4
     137: aload_3
     138: invokevirtual #76                 // Method io/sundr/shaded/org/apache/velocity/runtime/log/Log.error:(Ljava/lang/Object;Ljava/lang/Throwable;)V
     141: new           #78                 // class io/sundr/shaded/org/apache/velocity/exception/VelocityException
     144: dup
     145: aload         4
     147: aload_3
     148: invokespecial #81                 // Method io/sundr/shaded/org/apache/velocity/exception/VelocityException."<init>":(Ljava/lang/String;Ljava/lang/Throwable;)V
     151: athrow
     152: aload_0
     153: getstatic     #90                 // Field class$org$apache$velocity$runtime$resource$ResourceCacheImpl:Ljava/lang/Class;
     156: ifnonnull     171
     159: ldc           #92                 // String io.sundr.shaded.org.apache.velocity.runtime.resource.ResourceCacheImpl
     161: invokestatic  #96                 // Method class$:(Ljava/lang/String;)Ljava/lang/Class;
     164: dup
     165: putstatic     #90                 // Field class$org$apache$velocity$runtime$resource$ResourceCacheImpl:Ljava/lang/Class;
     168: goto          174
     171: getstatic     #90                 // Field class$org$apache$velocity$runtime$resource$ResourceCacheImpl:Ljava/lang/Class;
     174: invokevirtual #101                // Method java/lang/Class.getName:()Ljava/lang/String;
     177: putfield      #29                 // Field className:Ljava/lang/String;
     180: aload_0
     181: aload_2
     182: ldc           #103                // String class
     184: aload_0
     185: getfield      #29                 // Field className:Ljava/lang/String;
     188: invokevirtual #106                // Method org/apache/commons/collections/ExtendedProperties.getString:(Ljava/lang/String;Ljava/lang/String;)Ljava/lang/String;
     191: putfield      #29                 // Field className:Ljava/lang/String;
     194: goto          223
     197: astore_3
     198: ldc           #108                // String Exception retrieving resource cache class name
     200: astore        4
     202: aload_0
     203: getfield      #33                 // Field log:Lio/sundr/shaded/org/apache/velocity/runtime/log/Log;
     206: aload         4
     208: aload_3
     209: invokevirtual #76                 // Method io/sundr/shaded/org/apache/velocity/runtime/log/Log.error:(Ljava/lang/Object;Ljava/lang/Throwable;)V
     212: new           #78                 // class io/sundr/shaded/org/apache/velocity/exception/VelocityException
     215: dup
     216: aload         4
     218: aload_3
     219: invokespecial #81                 // Method io/sundr/shaded/org/apache/velocity/exception/VelocityException."<init>":(Ljava/lang/String;Ljava/lang/Throwable;)V
     222: athrow
     223: return
    Exception table:
       from    to  target type
          18    29    32   Class java/lang/Exception
          85    96    99   Class java/lang/Exception
         180   194   197   Class java/lang/Exception

  public abstract void init(org.apache.commons.collections.ExtendedProperties);

  public abstract java.io.InputStream getResourceStream(java.lang.String) throws io.sundr.shaded.org.apache.velocity.exception.ResourceNotFoundException;

  public abstract boolean isSourceModified(io.sundr.shaded.org.apache.velocity.runtime.resource.Resource);

  public abstract long getLastModified(io.sundr.shaded.org.apache.velocity.runtime.resource.Resource);

  public java.lang.String getClassName();
    Code:
       0: aload_0
       1: getfield      #29                 // Field className:Ljava/lang/String;
       4: areturn

  public void setCachingOn(boolean);
    Code:
       0: aload_0
       1: iload_1
       2: putfield      #23                 // Field isCachingOn:Z
       5: return

  public boolean isCachingOn();
    Code:
       0: aload_0
       1: getfield      #23                 // Field isCachingOn:Z
       4: ireturn

  public void setModificationCheckInterval(long);
    Code:
       0: aload_0
       1: lload_1
       2: putfield      #27                 // Field modificationCheckInterval:J
       5: return

  public long getModificationCheckInterval();
    Code:
       0: aload_0
       1: getfield      #27                 // Field modificationCheckInterval:J
       4: lreturn

  public boolean resourceExists(java.lang.String);
    Code:
       0: aconst_null
       1: astore_2
       2: aload_0
       3: aload_1
       4: invokevirtual #137                // Method getResourceStream:(Ljava/lang/String;)Ljava/io/InputStream;
       7: astore_2
       8: jsr           92
      11: goto          178
      14: astore_3
      15: aload_0
      16: getfield      #33                 // Field log:Lio/sundr/shaded/org/apache/velocity/runtime/log/Log;
      19: invokevirtual #140                // Method io/sundr/shaded/org/apache/velocity/runtime/log/Log.isDebugEnabled:()Z
      22: ifeq          78
      25: aload_0
      26: getfield      #33                 // Field log:Lio/sundr/shaded/org/apache/velocity/runtime/log/Log;
      29: new           #55                 // class java/lang/StringBuffer
      32: dup
      33: invokespecial #56                 // Method java/lang/StringBuffer."<init>":()V
      36: ldc           #142                // String Could not load resource \'
      38: invokevirtual #62                 // Method java/lang/StringBuffer.append:(Ljava/lang/String;)Ljava/lang/StringBuffer;
      41: aload_1
      42: invokevirtual #62                 // Method java/lang/StringBuffer.append:(Ljava/lang/String;)Ljava/lang/StringBuffer;
      45: ldc           #144                // String \' from ResourceLoader
      47: invokevirtual #62                 // Method java/lang/StringBuffer.append:(Ljava/lang/String;)Ljava/lang/StringBuffer;
      50: aload_0
      51: invokevirtual #148                // Method java/lang/Object.getClass:()Ljava/lang/Class;
      54: invokevirtual #101                // Method java/lang/Class.getName:()Ljava/lang/String;
      57: invokevirtual #62                 // Method java/lang/StringBuffer.append:(Ljava/lang/String;)Ljava/lang/StringBuffer;
      60: ldc           #150                // String :
      62: invokevirtual #62                 // Method java/lang/StringBuffer.append:(Ljava/lang/String;)Ljava/lang/StringBuffer;
      65: aload_3
      66: invokevirtual #153                // Method io/sundr/shaded/org/apache/velocity/exception/ResourceNotFoundException.getMessage:()Ljava/lang/String;
      69: invokevirtual #62                 // Method java/lang/StringBuffer.append:(Ljava/lang/String;)Ljava/lang/StringBuffer;
      72: invokevirtual #70                 // Method java/lang/StringBuffer.toString:()Ljava/lang/String;
      75: invokevirtual #157                // Method io/sundr/shaded/org/apache/velocity/runtime/log/Log.debug:(Ljava/lang/Object;)V
      78: jsr           92
      81: goto          178
      84: astore        4
      86: jsr           92
      89: aload         4
      91: athrow
      92: astore        5
      94: aload_2
      95: ifnull        102
      98: aload_2
      99: invokevirtual #162                // Method java/io/InputStream.close:()V
     102: goto          176
     105: astore        6
     107: aload_0
     108: getfield      #33                 // Field log:Lio/sundr/shaded/org/apache/velocity/runtime/log/Log;
     111: invokevirtual #165                // Method io/sundr/shaded/org/apache/velocity/runtime/log/Log.isErrorEnabled:()Z
     114: ifeq          176
     117: new           #55                 // class java/lang/StringBuffer
     120: dup
     121: invokespecial #56                 // Method java/lang/StringBuffer."<init>":()V
     124: ldc           #167                // String While closing InputStream for resource \'
     126: invokevirtual #62                 // Method java/lang/StringBuffer.append:(Ljava/lang/String;)Ljava/lang/StringBuffer;
     129: aload_1
     130: invokevirtual #62                 // Method java/lang/StringBuffer.append:(Ljava/lang/String;)Ljava/lang/StringBuffer;
     133: ldc           #144                // String \' from ResourceLoader
     135: invokevirtual #62                 // Method java/lang/StringBuffer.append:(Ljava/lang/String;)Ljava/lang/StringBuffer;
     138: aload_0
     139: invokevirtual #148                // Method java/lang/Object.getClass:()Ljava/lang/Class;
     142: invokevirtual #101                // Method java/lang/Class.getName:()Ljava/lang/String;
     145: invokevirtual #62                 // Method java/lang/StringBuffer.append:(Ljava/lang/String;)Ljava/lang/StringBuffer;
     148: invokevirtual #70                 // Method java/lang/StringBuffer.toString:()Ljava/lang/String;
     151: astore        7
     153: aload_0
     154: getfield      #33                 // Field log:Lio/sundr/shaded/org/apache/velocity/runtime/log/Log;
     157: aload         7
     159: aload         6
     161: invokevirtual #76                 // Method io/sundr/shaded/org/apache/velocity/runtime/log/Log.error:(Ljava/lang/Object;Ljava/lang/Throwable;)V
     164: new           #78                 // class io/sundr/shaded/org/apache/velocity/exception/VelocityException
     167: dup
     168: aload         7
     170: aload         6
     172: invokespecial #81                 // Method io/sundr/shaded/org/apache/velocity/exception/VelocityException."<init>":(Ljava/lang/String;Ljava/lang/Throwable;)V
     175: athrow
     176: ret           5
     178: aload_2
     179: ifnull        186
     182: iconst_1
     183: goto          187
     186: iconst_0
     187: ireturn
    Exception table:
       from    to  target type
           2     8    14   Class io/sundr/shaded/org/apache/velocity/exception/ResourceNotFoundException
           2    11    84   any
          14    81    84   any
          84    89    84   any
          94   102   105   Class java/lang/Exception

  static java.lang.Class class$(java.lang.String);
    Code:
       0: aload_0
       1: invokestatic  #176                // Method java/lang/Class.forName:(Ljava/lang/String;)Ljava/lang/Class;
       4: areturn
       5: astore_1
       6: new           #178                // class java/lang/NoClassDefFoundError
       9: dup
      10: invokespecial #179                // Method java/lang/NoClassDefFoundError."<init>":()V
      13: aload_1
      14: invokevirtual #183                // Method java/lang/NoClassDefFoundError.initCause:(Ljava/lang/Throwable;)Ljava/lang/Throwable;
      17: athrow
    Exception table:
       from    to  target type
           0     4     5   Class java/lang/ClassNotFoundException
}
