Compiled from "AbstractAsmLibraryInterface.java"
public abstract class jnr.ffi.provider.jffi.AbstractAsmLibraryInterface implements jnr.ffi.provider.LoadedLibrary {
  public static final com.kenai.jffi.Invoker ffi;

  protected final jnr.ffi.Runtime runtime;

  protected final jnr.ffi.provider.jffi.NativeLibrary library;

  public jnr.ffi.provider.jffi.AbstractAsmLibraryInterface(jnr.ffi.Runtime, jnr.ffi.provider.jffi.NativeLibrary);
    Code:
       0: aload_0
       1: invokespecial #1                  // Method java/lang/Object."<init>":()V
       4: aload_0
       5: aload_1
       6: putfield      #2                  // Field runtime:Ljnr/ffi/Runtime;
       9: aload_0
      10: aload_2
      11: putfield      #3                  // Field library:Ljnr/ffi/provider/jffi/NativeLibrary;
      14: return

  public final jnr.ffi.Runtime getRuntime();
    Code:
       0: aload_0
       1: getfield      #2                  // Field runtime:Ljnr/ffi/Runtime;
       4: areturn

  final jnr.ffi.provider.jffi.NativeLibrary getLibrary();
    Code:
       0: aload_0
       1: getfield      #3                  // Field library:Ljnr/ffi/provider/jffi/NativeLibrary;
       4: areturn

  static {};
    Code:
       0: invokestatic  #4                  // Method com/kenai/jffi/Invoker.getInstance:()Lcom/kenai/jffi/Invoker;
       3: putstatic     #5                  // Field ffi:Lcom/kenai/jffi/Invoker;
       6: return
}
