Compiled from "FastLongMethodGenerator.java"
public class jnr.ffi.provider.jffi.FastLongMethodGenerator extends jnr.ffi.provider.jffi.AbstractFastNumericMethodGenerator {
  private static final boolean ENABLED;

  private static final int MAX_PARAMETERS;

  private static final java.lang.String[] signatures;

  private static final java.lang.String[] methodNames;

  public jnr.ffi.provider.jffi.FastLongMethodGenerator();
    Code:
       0: aload_0
       1: invokespecial #1                  // Method jnr/ffi/provider/jffi/AbstractFastNumericMethodGenerator."<init>":()V
       4: return

  java.lang.String getInvokerMethodName(jnr.ffi.provider.ResultType, jnr.ffi.provider.ParameterType[], boolean);
    Code:
       0: aload_2
       1: arraylength
       2: istore        4
       4: iload         4
       6: getstatic     #2                  // Field MAX_PARAMETERS:I
       9: if_icmpgt     28
      12: iload         4
      14: getstatic     #3                  // Field methodNames:[Ljava/lang/String;
      17: arraylength
      18: if_icmpgt     28
      21: getstatic     #3                  // Field methodNames:[Ljava/lang/String;
      24: iload         4
      26: aaload
      27: areturn
      28: new           #4                  // class java/lang/IllegalArgumentException
      31: dup
      32: new           #5                  // class java/lang/StringBuilder
      35: dup
      36: invokespecial #6                  // Method java/lang/StringBuilder."<init>":()V
      39: ldc           #7                  // String invalid fast-int parameter count:
      41: invokevirtual #8                  // Method java/lang/StringBuilder.append:(Ljava/lang/String;)Ljava/lang/StringBuilder;
      44: iload         4
      46: invokevirtual #9                  // Method java/lang/StringBuilder.append:(I)Ljava/lang/StringBuilder;
      49: invokevirtual #10                 // Method java/lang/StringBuilder.toString:()Ljava/lang/String;
      52: invokespecial #11                 // Method java/lang/IllegalArgumentException."<init>":(Ljava/lang/String;)V
      55: athrow

  java.lang.String getInvokerSignature(int, java.lang.Class);
    Code:
       0: iload_1
       1: getstatic     #2                  // Field MAX_PARAMETERS:I
       4: if_icmpgt     21
       7: iload_1
       8: getstatic     #12                 // Field signatures:[Ljava/lang/String;
      11: arraylength
      12: if_icmpgt     21
      15: getstatic     #12                 // Field signatures:[Ljava/lang/String;
      18: iload_1
      19: aaload
      20: areturn
      21: new           #4                  // class java/lang/IllegalArgumentException
      24: dup
      25: new           #5                  // class java/lang/StringBuilder
      28: dup
      29: invokespecial #6                  // Method java/lang/StringBuilder."<init>":()V
      32: ldc           #7                  // String invalid fast-int parameter count:
      34: invokevirtual #8                  // Method java/lang/StringBuilder.append:(Ljava/lang/String;)Ljava/lang/StringBuilder;
      37: iload_1
      38: invokevirtual #9                  // Method java/lang/StringBuilder.append:(I)Ljava/lang/StringBuilder;
      41: invokevirtual #10                 // Method java/lang/StringBuilder.toString:()Ljava/lang/String;
      44: invokespecial #11                 // Method java/lang/IllegalArgumentException."<init>":(Ljava/lang/String;)V
      47: athrow

  java.lang.Class getInvokerType();
    Code:
       0: getstatic     #13                 // Field java/lang/Long.TYPE:Ljava/lang/Class;
       3: areturn

  public boolean isSupported(jnr.ffi.provider.ResultType, jnr.ffi.provider.ParameterType[], jnr.ffi.CallingConvention);
    Code:
       0: aload_2
       1: arraylength
       2: istore        4
       4: getstatic     #14                 // Field ENABLED:Z
       7: ifne          12
      10: iconst_0
      11: ireturn
      12: aload_3
      13: getstatic     #15                 // Field jnr/ffi/CallingConvention.DEFAULT:Ljnr/ffi/CallingConvention;
      16: if_acmpne     27
      19: iload         4
      21: getstatic     #2                  // Field MAX_PARAMETERS:I
      24: if_icmple     29
      27: iconst_0
      28: ireturn
      29: invokestatic  #16                 // Method com/kenai/jffi/Platform.getPlatform:()Lcom/kenai/jffi/Platform;
      32: astore        5
      34: aload         5
      36: invokevirtual #17                 // Method com/kenai/jffi/Platform.getCPU:()Lcom/kenai/jffi/Platform$CPU;
      39: getstatic     #18                 // Field com/kenai/jffi/Platform$CPU.X86_64:Lcom/kenai/jffi/Platform$CPU;
      42: if_acmpeq     47
      45: iconst_0
      46: ireturn
      47: aload         5
      49: invokevirtual #19                 // Method com/kenai/jffi/Platform.getOS:()Lcom/kenai/jffi/Platform$OS;
      52: getstatic     #20                 // Field com/kenai/jffi/Platform$OS.WINDOWS:Lcom/kenai/jffi/Platform$OS;
      55: invokevirtual #21                 // Method com/kenai/jffi/Platform$OS.equals:(Ljava/lang/Object;)Z
      58: ifeq          63
      61: iconst_0
      62: ireturn
      63: aload_2
      64: astore        6
      66: aload         6
      68: arraylength
      69: istore        7
      71: iconst_0
      72: istore        8
      74: iload         8
      76: iload         7
      78: if_icmpge     106
      81: aload         6
      83: iload         8
      85: aaload
      86: astore        9
      88: aload         5
      90: aload         9
      92: invokestatic  #22                 // Method isFastLongParameter:(Lcom/kenai/jffi/Platform;Ljnr/ffi/provider/ParameterType;)Z
      95: ifne          100
      98: iconst_0
      99: ireturn
     100: iinc          8, 1
     103: goto          74
     106: aload         5
     108: aload_1
     109: invokestatic  #23                 // Method isFastLongResult:(Lcom/kenai/jffi/Platform;Ljnr/ffi/provider/ResultType;)Z
     112: ireturn

  static int getMaximumFastLongParameters();
    Code:
       0: ldc           #24                 // class com/kenai/jffi/Invoker
       2: ldc           #25                 // String invokeL6
       4: bipush        8
       6: anewarray     #26                 // class java/lang/Class
       9: dup
      10: iconst_0
      11: ldc           #27                 // class com/kenai/jffi/CallContext
      13: aastore
      14: dup
      15: iconst_1
      16: getstatic     #13                 // Field java/lang/Long.TYPE:Ljava/lang/Class;
      19: aastore
      20: dup
      21: iconst_2
      22: getstatic     #13                 // Field java/lang/Long.TYPE:Ljava/lang/Class;
      25: aastore
      26: dup
      27: iconst_3
      28: getstatic     #13                 // Field java/lang/Long.TYPE:Ljava/lang/Class;
      31: aastore
      32: dup
      33: iconst_4
      34: getstatic     #13                 // Field java/lang/Long.TYPE:Ljava/lang/Class;
      37: aastore
      38: dup
      39: iconst_5
      40: getstatic     #13                 // Field java/lang/Long.TYPE:Ljava/lang/Class;
      43: aastore
      44: dup
      45: bipush        6
      47: getstatic     #13                 // Field java/lang/Long.TYPE:Ljava/lang/Class;
      50: aastore
      51: dup
      52: bipush        7
      54: getstatic     #13                 // Field java/lang/Long.TYPE:Ljava/lang/Class;
      57: aastore
      58: invokevirtual #28                 // Method java/lang/Class.getDeclaredMethod:(Ljava/lang/String;[Ljava/lang/Class;)Ljava/lang/reflect/Method;
      61: pop
      62: bipush        6
      64: ireturn
      65: astore_0
      66: iconst_0
      67: ireturn
    Exception table:
       from    to  target type
           0    64    65   Class java/lang/Throwable

  private static boolean isFastLongType(com.kenai.jffi.Platform, jnr.ffi.provider.SigType);
    Code:
       0: aload_0
       1: aload_1
       2: invokestatic  #30                 // Method jnr/ffi/provider/jffi/FastIntMethodGenerator.isFastIntType:(Lcom/kenai/jffi/Platform;Ljnr/ffi/provider/SigType;)Z
       5: ifne          69
       8: aload_1
       9: invokevirtual #31                 // Method jnr/ffi/provider/SigType.getNativeType:()Ljnr/ffi/NativeType;
      12: getstatic     #32                 // Field jnr/ffi/NativeType.ADDRESS:Ljnr/ffi/NativeType;
      15: if_acmpne     29
      18: getstatic     #32                 // Field jnr/ffi/NativeType.ADDRESS:Ljnr/ffi/NativeType;
      21: invokestatic  #33                 // Method jnr/ffi/provider/jffi/NumberUtil.sizeof:(Ljnr/ffi/NativeType;)I
      24: bipush        8
      26: if_icmpeq     69
      29: aload_1
      30: invokevirtual #31                 // Method jnr/ffi/provider/SigType.getNativeType:()Ljnr/ffi/NativeType;
      33: getstatic     #34                 // Field jnr/ffi/NativeType.SLONG:Ljnr/ffi/NativeType;
      36: if_acmpeq     69
      39: aload_1
      40: invokevirtual #31                 // Method jnr/ffi/provider/SigType.getNativeType:()Ljnr/ffi/NativeType;
      43: getstatic     #35                 // Field jnr/ffi/NativeType.ULONG:Ljnr/ffi/NativeType;
      46: if_acmpeq     69
      49: aload_1
      50: invokevirtual #31                 // Method jnr/ffi/provider/SigType.getNativeType:()Ljnr/ffi/NativeType;
      53: getstatic     #36                 // Field jnr/ffi/NativeType.SLONGLONG:Ljnr/ffi/NativeType;
      56: if_acmpeq     69
      59: aload_1
      60: invokevirtual #31                 // Method jnr/ffi/provider/SigType.getNativeType:()Ljnr/ffi/NativeType;
      63: getstatic     #37                 // Field jnr/ffi/NativeType.ULONGLONG:Ljnr/ffi/NativeType;
      66: if_acmpne     73
      69: iconst_1
      70: goto          74
      73: iconst_0
      74: ireturn

  static boolean isFastLongResult(com.kenai.jffi.Platform, jnr.ffi.provider.ResultType);
    Code:
       0: aload_0
       1: aload_1
       2: invokestatic  #38                 // Method isFastLongType:(Lcom/kenai/jffi/Platform;Ljnr/ffi/provider/SigType;)Z
       5: ifne          39
       8: aload_1
       9: invokevirtual #39                 // Method jnr/ffi/provider/ResultType.getNativeType:()Ljnr/ffi/NativeType;
      12: getstatic     #40                 // Field jnr/ffi/NativeType.VOID:Ljnr/ffi/NativeType;
      15: if_acmpeq     39
      18: aload_1
      19: invokevirtual #39                 // Method jnr/ffi/provider/ResultType.getNativeType:()Ljnr/ffi/NativeType;
      22: getstatic     #32                 // Field jnr/ffi/NativeType.ADDRESS:Ljnr/ffi/NativeType;
      25: if_acmpne     43
      28: getstatic     #32                 // Field jnr/ffi/NativeType.ADDRESS:Ljnr/ffi/NativeType;
      31: invokestatic  #33                 // Method jnr/ffi/provider/jffi/NumberUtil.sizeof:(Ljnr/ffi/NativeType;)I
      34: bipush        8
      36: if_icmpne     43
      39: iconst_1
      40: goto          44
      43: iconst_0
      44: ireturn

  static boolean isFastLongParameter(com.kenai.jffi.Platform, jnr.ffi.provider.ParameterType);
    Code:
       0: aload_0
       1: aload_1
       2: invokestatic  #38                 // Method isFastLongType:(Lcom/kenai/jffi/Platform;Ljnr/ffi/provider/SigType;)Z
       5: ireturn

  public void generate(jnr.ffi.provider.jffi.AsmBuilder, jnr.ffi.provider.jffi.SkinnyMethodAdapter, jnr.ffi.provider.jffi.LocalVariableAllocator, com.kenai.jffi.CallContext, jnr.ffi.provider.ResultType, jnr.ffi.provider.ParameterType[], boolean);
    Code:
       0: aload_0
       1: aload_1
       2: aload_2
       3: aload_3
       4: aload         4
       6: aload         5
       8: aload         6
      10: iload         7
      12: invokespecial #41                 // Method jnr/ffi/provider/jffi/AbstractFastNumericMethodGenerator.generate:(Ljnr/ffi/provider/jffi/AsmBuilder;Ljnr/ffi/provider/jffi/SkinnyMethodAdapter;Ljnr/ffi/provider/jffi/LocalVariableAllocator;Lcom/kenai/jffi/CallContext;Ljnr/ffi/provider/ResultType;[Ljnr/ffi/provider/ParameterType;Z)V
      15: return

  public void generate(jnr.ffi.provider.jffi.AsmBuilder, java.lang.String, com.kenai.jffi.Function, jnr.ffi.provider.ResultType, jnr.ffi.provider.ParameterType[], boolean);
    Code:
       0: aload_0
       1: aload_1
       2: aload_2
       3: aload_3
       4: aload         4
       6: aload         5
       8: iload         6
      10: invokespecial #42                 // Method jnr/ffi/provider/jffi/AbstractFastNumericMethodGenerator.generate:(Ljnr/ffi/provider/jffi/AsmBuilder;Ljava/lang/String;Lcom/kenai/jffi/Function;Ljnr/ffi/provider/ResultType;[Ljnr/ffi/provider/ParameterType;Z)V
      13: return

  static {};
    Code:
       0: ldc           #43                 // String jnr.ffi.fast-long.enabled
       2: iconst_1
       3: invokestatic  #44                 // Method jnr/ffi/provider/jffi/Util.getBooleanProperty:(Ljava/lang/String;Z)Z
       6: putstatic     #14                 // Field ENABLED:Z
       9: invokestatic  #45                 // Method getMaximumFastLongParameters:()I
      12: putstatic     #2                  // Field MAX_PARAMETERS:I
      15: bipush        7
      17: anewarray     #46                 // class java/lang/String
      20: dup
      21: iconst_0
      22: ldc           #47                 // String invokeL0
      24: aastore
      25: dup
      26: iconst_1
      27: ldc           #48                 // String invokeL1
      29: aastore
      30: dup
      31: iconst_2
      32: ldc           #49                 // String invokeL2
      34: aastore
      35: dup
      36: iconst_3
      37: ldc           #50                 // String invokeL3
      39: aastore
      40: dup
      41: iconst_4
      42: ldc           #51                 // String invokeL4
      44: aastore
      45: dup
      46: iconst_5
      47: ldc           #52                 // String invokeL5
      49: aastore
      50: dup
      51: bipush        6
      53: ldc           #25                 // String invokeL6
      55: aastore
      56: putstatic     #3                  // Field methodNames:[Ljava/lang/String;
      59: getstatic     #2                  // Field MAX_PARAMETERS:I
      62: iconst_1
      63: iadd
      64: anewarray     #46                 // class java/lang/String
      67: putstatic     #12                 // Field signatures:[Ljava/lang/String;
      70: iconst_0
      71: istore_0
      72: iload_0
      73: getstatic     #2                  // Field MAX_PARAMETERS:I
      76: if_icmpgt     151
      79: new           #5                  // class java/lang/StringBuilder
      82: dup
      83: invokespecial #6                  // Method java/lang/StringBuilder."<init>":()V
      86: astore_1
      87: aload_1
      88: bipush        40
      90: invokevirtual #53                 // Method java/lang/StringBuilder.append:(C)Ljava/lang/StringBuilder;
      93: ldc           #27                 // class com/kenai/jffi/CallContext
      95: invokestatic  #54                 // Method jnr/ffi/provider/jffi/CodegenUtils.ci:(Ljava/lang/Class;)Ljava/lang/String;
      98: invokevirtual #8                  // Method java/lang/StringBuilder.append:(Ljava/lang/String;)Ljava/lang/StringBuilder;
     101: getstatic     #13                 // Field java/lang/Long.TYPE:Ljava/lang/Class;
     104: invokestatic  #54                 // Method jnr/ffi/provider/jffi/CodegenUtils.ci:(Ljava/lang/Class;)Ljava/lang/String;
     107: invokevirtual #8                  // Method java/lang/StringBuilder.append:(Ljava/lang/String;)Ljava/lang/StringBuilder;
     110: pop
     111: iconst_0
     112: istore_2
     113: iload_2
     114: iload_0
     115: if_icmpge     131
     118: aload_1
     119: bipush        74
     121: invokevirtual #53                 // Method java/lang/StringBuilder.append:(C)Ljava/lang/StringBuilder;
     124: pop
     125: iinc          2, 1
     128: goto          113
     131: getstatic     #12                 // Field signatures:[Ljava/lang/String;
     134: iload_0
     135: aload_1
     136: ldc           #55                 // String )J
     138: invokevirtual #8                  // Method java/lang/StringBuilder.append:(Ljava/lang/String;)Ljava/lang/StringBuilder;
     141: invokevirtual #10                 // Method java/lang/StringBuilder.toString:()Ljava/lang/String;
     144: aastore
     145: iinc          0, 1
     148: goto          72
     151: return
}
