Compiled from "NotImplMethodGenerator.java"
class jnr.ffi.provider.jffi.NotImplMethodGenerator implements jnr.ffi.provider.jffi.MethodGenerator {
  jnr.ffi.provider.jffi.NotImplMethodGenerator();
    Code:
       0: aload_0
       1: invokespecial #1                  // Method java/lang/Object."<init>":()V
       4: return

  public boolean isSupported(jnr.ffi.provider.ResultType, jnr.ffi.provider.ParameterType[], jnr.ffi.CallingConvention);
    Code:
       0: iconst_0
       1: ireturn

  public void generate(jnr.ffi.provider.jffi.AsmBuilder, java.lang.String, com.kenai.jffi.Function, jnr.ffi.provider.ResultType, jnr.ffi.provider.ParameterType[], boolean);
    Code:
       0: new           #2                  // class java/lang/UnsupportedOperationException
       3: dup
       4: ldc           #3                  // String not supported
       6: invokespecial #4                  // Method java/lang/UnsupportedOperationException."<init>":(Ljava/lang/String;)V
       9: athrow
}
