Compiled from "NullObjectParameterStrategy.java"
public final class jnr.ffi.provider.jffi.NullObjectParameterStrategy extends jnr.ffi.provider.jffi.ParameterStrategy {
  public static final jnr.ffi.provider.jffi.ParameterStrategy NULL;

  public jnr.ffi.provider.jffi.NullObjectParameterStrategy();
    Code:
       0: aload_0
       1: getstatic     #1                  // Field DIRECT:Lcom/kenai/jffi/ObjectParameterStrategy$StrategyType;
       4: invokespecial #2                  // Method jnr/ffi/provider/jffi/ParameterStrategy."<init>":(Lcom/kenai/jffi/ObjectParameterStrategy$StrategyType;)V
       7: return

  public long address(java.lang.Object);
    Code:
       0: lconst_0
       1: lreturn

  public java.lang.Object object(java.lang.Object);
    Code:
       0: new           #3                  // class java/lang/NullPointerException
       3: dup
       4: ldc           #4                  // String null reference
       6: invokespecial #5                  // Method java/lang/NullPointerException."<init>":(Ljava/lang/String;)V
       9: athrow

  public int offset(java.lang.Object);
    Code:
       0: new           #3                  // class java/lang/NullPointerException
       3: dup
       4: ldc           #4                  // String null reference
       6: invokespecial #5                  // Method java/lang/NullPointerException."<init>":(Ljava/lang/String;)V
       9: athrow

  public int length(java.lang.Object);
    Code:
       0: new           #3                  // class java/lang/NullPointerException
       3: dup
       4: ldc           #4                  // String null reference
       6: invokespecial #5                  // Method java/lang/NullPointerException."<init>":(Ljava/lang/String;)V
       9: athrow

  static {};
    Code:
       0: new           #6                  // class jnr/ffi/provider/jffi/NullObjectParameterStrategy
       3: dup
       4: invokespecial #7                  // Method "<init>":()V
       7: putstatic     #8                  // Field NULL:Ljnr/ffi/provider/jffi/ParameterStrategy;
      10: return
}
