Compiled from "ReflectionLibraryLoader.java"
final class jnr.ffi.provider.jffi.ReflectionLibraryLoader$LazyLoader$VariableAcccessorInvoker implements jnr.ffi.provider.Invoker {
  private final jnr.ffi.Variable variable;

  private jnr.ffi.provider.jffi.ReflectionLibraryLoader$LazyLoader$VariableAcccessorInvoker(jnr.ffi.Variable);
    Code:
       0: aload_0
       1: invokespecial #2                  // Method java/lang/Object."<init>":()V
       4: aload_0
       5: aload_1
       6: putfield      #3                  // Field variable:Ljnr/ffi/Variable;
       9: return

  public java.lang.Object invoke(java.lang.Object, java.lang.Object[]);
    Code:
       0: aload_0
       1: getfield      #3                  // Field variable:Ljnr/ffi/Variable;
       4: areturn

  jnr.ffi.provider.jffi.ReflectionLibraryLoader$LazyLoader$VariableAcccessorInvoker(jnr.ffi.Variable, jnr.ffi.provider.jffi.ReflectionLibraryLoader$1);
    Code:
       0: aload_0
       1: aload_1
       2: invokespecial #1                  // Method "<init>":(Ljnr/ffi/Variable;)V
       5: return
}
