Compiled from "AlarmState.java"
final class software.amazon.awssdk.services.ioteventsdata.model.AlarmState$BuilderImpl implements software.amazon.awssdk.services.ioteventsdata.model.AlarmState$Builder {
  private java.lang.String stateName;

  private software.amazon.awssdk.services.ioteventsdata.model.RuleEvaluation ruleEvaluation;

  private software.amazon.awssdk.services.ioteventsdata.model.CustomerAction customerAction;

  private software.amazon.awssdk.services.ioteventsdata.model.SystemEvent systemEvent;

  private software.amazon.awssdk.services.ioteventsdata.model.AlarmState$BuilderImpl();
    Code:
       0: aload_0
       1: invokespecial #7                  // Method java/lang/Object."<init>":()V
       4: return

  private software.amazon.awssdk.services.ioteventsdata.model.AlarmState$BuilderImpl(software.amazon.awssdk.services.ioteventsdata.model.AlarmState);
    Code:
       0: aload_0
       1: invokespecial #7                  // Method java/lang/Object."<init>":()V
       4: aload_0
       5: aload_1
       6: invokestatic  #8                  // Method software/amazon/awssdk/services/ioteventsdata/model/AlarmState.access$600:(Lsoftware/amazon/awssdk/services/ioteventsdata/model/AlarmState;)Ljava/lang/String;
       9: invokevirtual #9                  // Method stateName:(Ljava/lang/String;)Lsoftware/amazon/awssdk/services/ioteventsdata/model/AlarmState$Builder;
      12: pop
      13: aload_0
      14: aload_1
      15: invokestatic  #10                 // Method software/amazon/awssdk/services/ioteventsdata/model/AlarmState.access$700:(Lsoftware/amazon/awssdk/services/ioteventsdata/model/AlarmState;)Lsoftware/amazon/awssdk/services/ioteventsdata/model/RuleEvaluation;
      18: invokevirtual #11                 // Method ruleEvaluation:(Lsoftware/amazon/awssdk/services/ioteventsdata/model/RuleEvaluation;)Lsoftware/amazon/awssdk/services/ioteventsdata/model/AlarmState$Builder;
      21: pop
      22: aload_0
      23: aload_1
      24: invokestatic  #12                 // Method software/amazon/awssdk/services/ioteventsdata/model/AlarmState.access$800:(Lsoftware/amazon/awssdk/services/ioteventsdata/model/AlarmState;)Lsoftware/amazon/awssdk/services/ioteventsdata/model/CustomerAction;
      27: invokevirtual #13                 // Method customerAction:(Lsoftware/amazon/awssdk/services/ioteventsdata/model/CustomerAction;)Lsoftware/amazon/awssdk/services/ioteventsdata/model/AlarmState$Builder;
      30: pop
      31: aload_0
      32: aload_1
      33: invokestatic  #14                 // Method software/amazon/awssdk/services/ioteventsdata/model/AlarmState.access$900:(Lsoftware/amazon/awssdk/services/ioteventsdata/model/AlarmState;)Lsoftware/amazon/awssdk/services/ioteventsdata/model/SystemEvent;
      36: invokevirtual #15                 // Method systemEvent:(Lsoftware/amazon/awssdk/services/ioteventsdata/model/SystemEvent;)Lsoftware/amazon/awssdk/services/ioteventsdata/model/AlarmState$Builder;
      39: pop
      40: return

  public final java.lang.String getStateName();
    Code:
       0: aload_0
       1: getfield      #6                  // Field stateName:Ljava/lang/String;
       4: areturn

  public final void setStateName(java.lang.String);
    Code:
       0: aload_0
       1: aload_1
       2: putfield      #6                  // Field stateName:Ljava/lang/String;
       5: return

  public final software.amazon.awssdk.services.ioteventsdata.model.AlarmState$Builder stateName(java.lang.String);
    Code:
       0: aload_0
       1: aload_1
       2: putfield      #6                  // Field stateName:Ljava/lang/String;
       5: aload_0
       6: areturn

  public final software.amazon.awssdk.services.ioteventsdata.model.AlarmState$Builder stateName(software.amazon.awssdk.services.ioteventsdata.model.AlarmStateName);
    Code:
       0: aload_0
       1: aload_1
       2: ifnonnull     9
       5: aconst_null
       6: goto          13
       9: aload_1
      10: invokevirtual #16                 // Method software/amazon/awssdk/services/ioteventsdata/model/AlarmStateName.toString:()Ljava/lang/String;
      13: invokevirtual #9                  // Method stateName:(Ljava/lang/String;)Lsoftware/amazon/awssdk/services/ioteventsdata/model/AlarmState$Builder;
      16: pop
      17: aload_0
      18: areturn

  public final software.amazon.awssdk.services.ioteventsdata.model.RuleEvaluation$Builder getRuleEvaluation();
    Code:
       0: aload_0
       1: getfield      #5                  // Field ruleEvaluation:Lsoftware/amazon/awssdk/services/ioteventsdata/model/RuleEvaluation;
       4: ifnull        17
       7: aload_0
       8: getfield      #5                  // Field ruleEvaluation:Lsoftware/amazon/awssdk/services/ioteventsdata/model/RuleEvaluation;
      11: invokevirtual #17                 // Method software/amazon/awssdk/services/ioteventsdata/model/RuleEvaluation.toBuilder:()Lsoftware/amazon/awssdk/services/ioteventsdata/model/RuleEvaluation$Builder;
      14: goto          18
      17: aconst_null
      18: areturn

  public final void setRuleEvaluation(software.amazon.awssdk.services.ioteventsdata.model.RuleEvaluation$BuilderImpl);
    Code:
       0: aload_0
       1: aload_1
       2: ifnull        12
       5: aload_1
       6: invokevirtual #18                 // Method software/amazon/awssdk/services/ioteventsdata/model/RuleEvaluation$BuilderImpl.build:()Lsoftware/amazon/awssdk/services/ioteventsdata/model/RuleEvaluation;
       9: goto          13
      12: aconst_null
      13: putfield      #5                  // Field ruleEvaluation:Lsoftware/amazon/awssdk/services/ioteventsdata/model/RuleEvaluation;
      16: return

  public final software.amazon.awssdk.services.ioteventsdata.model.AlarmState$Builder ruleEvaluation(software.amazon.awssdk.services.ioteventsdata.model.RuleEvaluation);
    Code:
       0: aload_0
       1: aload_1
       2: putfield      #5                  // Field ruleEvaluation:Lsoftware/amazon/awssdk/services/ioteventsdata/model/RuleEvaluation;
       5: aload_0
       6: areturn

  public final software.amazon.awssdk.services.ioteventsdata.model.CustomerAction$Builder getCustomerAction();
    Code:
       0: aload_0
       1: getfield      #4                  // Field customerAction:Lsoftware/amazon/awssdk/services/ioteventsdata/model/CustomerAction;
       4: ifnull        17
       7: aload_0
       8: getfield      #4                  // Field customerAction:Lsoftware/amazon/awssdk/services/ioteventsdata/model/CustomerAction;
      11: invokevirtual #19                 // Method software/amazon/awssdk/services/ioteventsdata/model/CustomerAction.toBuilder:()Lsoftware/amazon/awssdk/services/ioteventsdata/model/CustomerAction$Builder;
      14: goto          18
      17: aconst_null
      18: areturn

  public final void setCustomerAction(software.amazon.awssdk.services.ioteventsdata.model.CustomerAction$BuilderImpl);
    Code:
       0: aload_0
       1: aload_1
       2: ifnull        12
       5: aload_1
       6: invokevirtual #20                 // Method software/amazon/awssdk/services/ioteventsdata/model/CustomerAction$BuilderImpl.build:()Lsoftware/amazon/awssdk/services/ioteventsdata/model/CustomerAction;
       9: goto          13
      12: aconst_null
      13: putfield      #4                  // Field customerAction:Lsoftware/amazon/awssdk/services/ioteventsdata/model/CustomerAction;
      16: return

  public final software.amazon.awssdk.services.ioteventsdata.model.AlarmState$Builder customerAction(software.amazon.awssdk.services.ioteventsdata.model.CustomerAction);
    Code:
       0: aload_0
       1: aload_1
       2: putfield      #4                  // Field customerAction:Lsoftware/amazon/awssdk/services/ioteventsdata/model/CustomerAction;
       5: aload_0
       6: areturn

  public final software.amazon.awssdk.services.ioteventsdata.model.SystemEvent$Builder getSystemEvent();
    Code:
       0: aload_0
       1: getfield      #3                  // Field systemEvent:Lsoftware/amazon/awssdk/services/ioteventsdata/model/SystemEvent;
       4: ifnull        17
       7: aload_0
       8: getfield      #3                  // Field systemEvent:Lsoftware/amazon/awssdk/services/ioteventsdata/model/SystemEvent;
      11: invokevirtual #21                 // Method software/amazon/awssdk/services/ioteventsdata/model/SystemEvent.toBuilder:()Lsoftware/amazon/awssdk/services/ioteventsdata/model/SystemEvent$Builder;
      14: goto          18
      17: aconst_null
      18: areturn

  public final void setSystemEvent(software.amazon.awssdk.services.ioteventsdata.model.SystemEvent$BuilderImpl);
    Code:
       0: aload_0
       1: aload_1
       2: ifnull        12
       5: aload_1
       6: invokevirtual #22                 // Method software/amazon/awssdk/services/ioteventsdata/model/SystemEvent$BuilderImpl.build:()Lsoftware/amazon/awssdk/services/ioteventsdata/model/SystemEvent;
       9: goto          13
      12: aconst_null
      13: putfield      #3                  // Field systemEvent:Lsoftware/amazon/awssdk/services/ioteventsdata/model/SystemEvent;
      16: return

  public final software.amazon.awssdk.services.ioteventsdata.model.AlarmState$Builder systemEvent(software.amazon.awssdk.services.ioteventsdata.model.SystemEvent);
    Code:
       0: aload_0
       1: aload_1
       2: putfield      #3                  // Field systemEvent:Lsoftware/amazon/awssdk/services/ioteventsdata/model/SystemEvent;
       5: aload_0
       6: areturn

  public software.amazon.awssdk.services.ioteventsdata.model.AlarmState build();
    Code:
       0: new           #23                 // class software/amazon/awssdk/services/ioteventsdata/model/AlarmState
       3: dup
       4: aload_0
       5: aconst_null
       6: invokespecial #24                 // Method software/amazon/awssdk/services/ioteventsdata/model/AlarmState."<init>":(Lsoftware/amazon/awssdk/services/ioteventsdata/model/AlarmState$BuilderImpl;Lsoftware/amazon/awssdk/services/ioteventsdata/model/AlarmState$1;)V
       9: areturn

  public java.util.List<software.amazon.awssdk.core.SdkField<?>> sdkFields();
    Code:
       0: invokestatic  #25                 // Method software/amazon/awssdk/services/ioteventsdata/model/AlarmState.access$1100:()Ljava/util/List;
       3: areturn

  public java.lang.Object build();
    Code:
       0: aload_0
       1: invokevirtual #26                 // Method build:()Lsoftware/amazon/awssdk/services/ioteventsdata/model/AlarmState;
       4: areturn

  static java.lang.String access$000(software.amazon.awssdk.services.ioteventsdata.model.AlarmState$BuilderImpl);
    Code:
       0: aload_0
       1: getfield      #6                  // Field stateName:Ljava/lang/String;
       4: areturn

  static software.amazon.awssdk.services.ioteventsdata.model.RuleEvaluation access$100(software.amazon.awssdk.services.ioteventsdata.model.AlarmState$BuilderImpl);
    Code:
       0: aload_0
       1: getfield      #5                  // Field ruleEvaluation:Lsoftware/amazon/awssdk/services/ioteventsdata/model/RuleEvaluation;
       4: areturn

  static software.amazon.awssdk.services.ioteventsdata.model.CustomerAction access$200(software.amazon.awssdk.services.ioteventsdata.model.AlarmState$BuilderImpl);
    Code:
       0: aload_0
       1: getfield      #4                  // Field customerAction:Lsoftware/amazon/awssdk/services/ioteventsdata/model/CustomerAction;
       4: areturn

  static software.amazon.awssdk.services.ioteventsdata.model.SystemEvent access$300(software.amazon.awssdk.services.ioteventsdata.model.AlarmState$BuilderImpl);
    Code:
       0: aload_0
       1: getfield      #3                  // Field systemEvent:Lsoftware/amazon/awssdk/services/ioteventsdata/model/SystemEvent;
       4: areturn

  software.amazon.awssdk.services.ioteventsdata.model.AlarmState$BuilderImpl(software.amazon.awssdk.services.ioteventsdata.model.AlarmState, software.amazon.awssdk.services.ioteventsdata.model.AlarmState$1);
    Code:
       0: aload_0
       1: aload_1
       2: invokespecial #2                  // Method "<init>":(Lsoftware/amazon/awssdk/services/ioteventsdata/model/AlarmState;)V
       5: return

  software.amazon.awssdk.services.ioteventsdata.model.AlarmState$BuilderImpl(software.amazon.awssdk.services.ioteventsdata.model.AlarmState$1);
    Code:
       0: aload_0
       1: invokespecial #1                  // Method "<init>":()V
       4: return
}
