Compiled from "ArrayUtils.java"
public final class com.mchange.lang.ArrayUtils {
  public static int indexOf(java.lang.Object[], java.lang.Object);
    Code:
       0: iconst_0
       1: istore_2
       2: aload_0
       3: arraylength
       4: istore_3
       5: iload_2
       6: iload_3
       7: if_icmpge     28
      10: aload_1
      11: aload_0
      12: iload_2
      13: aaload
      14: invokevirtual #1                  // Method java/lang/Object.equals:(Ljava/lang/Object;)Z
      17: ifeq          22
      20: iload_2
      21: ireturn
      22: iinc          2, 1
      25: goto          5
      28: iconst_m1
      29: ireturn

  public static int identityIndexOf(java.lang.Object[], java.lang.Object);
    Code:
       0: iconst_0
       1: istore_2
       2: aload_0
       3: arraylength
       4: istore_3
       5: iload_2
       6: iload_3
       7: if_icmpge     25
      10: aload_1
      11: aload_0
      12: iload_2
      13: aaload
      14: if_acmpne     19
      17: iload_2
      18: ireturn
      19: iinc          2, 1
      22: goto          5
      25: iconst_m1
      26: ireturn

  public static int hashAll(java.lang.Object[]);
    Code:
       0: iconst_0
       1: istore_1
       2: iconst_0
       3: istore_2
       4: aload_0
       5: arraylength
       6: istore_3
       7: iload_2
       8: iload_3
       9: if_icmpge     36
      12: aload_0
      13: iload_2
      14: aaload
      15: astore        4
      17: aload         4
      19: ifnull        30
      22: iload_1
      23: aload         4
      25: invokevirtual #2                  // Method java/lang/Object.hashCode:()I
      28: ixor
      29: istore_1
      30: iinc          2, 1
      33: goto          7
      36: iload_1
      37: ireturn

  public static int hashAll(int[]);
    Code:
       0: iconst_0
       1: istore_1
       2: iconst_0
       3: istore_2
       4: aload_0
       5: arraylength
       6: istore_3
       7: iload_2
       8: iload_3
       9: if_icmpge     24
      12: iload_1
      13: aload_0
      14: iload_2
      15: iaload
      16: ixor
      17: istore_1
      18: iinc          2, 1
      21: goto          7
      24: iload_1
      25: ireturn

  public static boolean startsWith(byte[], byte[]);
    Code:
       0: aload_0
       1: arraylength
       2: istore_2
       3: aload_1
       4: arraylength
       5: istore_3
       6: iload_2
       7: iload_3
       8: if_icmpge     13
      11: iconst_0
      12: ireturn
      13: iconst_0
      14: istore        4
      16: iload         4
      18: iload_3
      19: if_icmpge     41
      22: aload_0
      23: iload         4
      25: baload
      26: aload_1
      27: iload         4
      29: baload
      30: if_icmpeq     35
      33: iconst_0
      34: ireturn
      35: iinc          4, 1
      38: goto          16
      41: iconst_1
      42: ireturn

  private com.mchange.lang.ArrayUtils();
    Code:
       0: aload_0
       1: invokespecial #3                  // Method java/lang/Object."<init>":()V
       4: return
}
