Compiled from "AbstractPersistentCollection.java"
public abstract class org.grails.datastore.mapping.collection.AbstractPersistentCollection implements org.grails.datastore.mapping.collection.PersistentCollection {
  private boolean initialized;

  private java.io.Serializable associationKey;

  private org.grails.datastore.mapping.core.Session session;

  private org.grails.datastore.mapping.engine.AssociationIndexer indexer;

  private java.util.Collection keys;

  private java.lang.Class childType;

  private boolean dirty;

  protected final java.util.Collection collection;

  protected org.grails.datastore.mapping.collection.AbstractPersistentCollection(java.lang.Class, org.grails.datastore.mapping.core.Session, java.util.Collection);
    Code:
       0: aload_0
       1: invokespecial #1                  // Method java/lang/Object."<init>":()V
       4: aload_0
       5: iconst_0
       6: putfield      #2                  // Field dirty:Z
       9: aload_0
      10: aload_1
      11: putfield      #3                  // Field childType:Ljava/lang/Class;
      14: aload_0
      15: aload_3
      16: putfield      #4                  // Field collection:Ljava/util/Collection;
      19: aload_0
      20: aload_2
      21: putfield      #5                  // Field session:Lorg/grails/datastore/mapping/core/Session;
      24: return

  protected org.grails.datastore.mapping.collection.AbstractPersistentCollection(java.util.Collection, java.lang.Class, org.grails.datastore.mapping.core.Session, java.util.Collection);
    Code:
       0: aload_0
       1: invokespecial #1                  // Method java/lang/Object."<init>":()V
       4: aload_0
       5: iconst_0
       6: putfield      #2                  // Field dirty:Z
       9: aload_0
      10: aload_3
      11: putfield      #5                  // Field session:Lorg/grails/datastore/mapping/core/Session;
      14: aload_0
      15: aload_1
      16: putfield      #6                  // Field keys:Ljava/util/Collection;
      19: aload_0
      20: aload_2
      21: putfield      #3                  // Field childType:Ljava/lang/Class;
      24: aload_0
      25: aload         4
      27: putfield      #4                  // Field collection:Ljava/util/Collection;
      30: return

  protected org.grails.datastore.mapping.collection.AbstractPersistentCollection(java.io.Serializable, org.grails.datastore.mapping.core.Session, org.grails.datastore.mapping.engine.AssociationIndexer, java.util.Collection);
    Code:
       0: aload_0
       1: invokespecial #1                  // Method java/lang/Object."<init>":()V
       4: aload_0
       5: iconst_0
       6: putfield      #2                  // Field dirty:Z
       9: aload_0
      10: aload_2
      11: putfield      #5                  // Field session:Lorg/grails/datastore/mapping/core/Session;
      14: aload_0
      15: aload_1
      16: putfield      #7                  // Field associationKey:Ljava/io/Serializable;
      19: aload_0
      20: aload_3
      21: putfield      #8                  // Field indexer:Lorg/grails/datastore/mapping/engine/AssociationIndexer;
      24: aload_0
      25: aload         4
      27: putfield      #4                  // Field collection:Ljava/util/Collection;
      30: return

  public java.util.Iterator iterator();
    Code:
       0: aload_0
       1: invokevirtual #9                  // Method initialize:()V
       4: aload_0
       5: getfield      #4                  // Field collection:Ljava/util/Collection;
       8: invokeinterface #10,  1           // InterfaceMethod java/util/Collection.iterator:()Ljava/util/Iterator;
      13: astore_1
      14: new           #11                 // class org/grails/datastore/mapping/collection/AbstractPersistentCollection$1
      17: dup
      18: aload_0
      19: aload_1
      20: invokespecial #12                 // Method org/grails/datastore/mapping/collection/AbstractPersistentCollection$1."<init>":(Lorg/grails/datastore/mapping/collection/AbstractPersistentCollection;Ljava/util/Iterator;)V
      23: areturn

  public int size();
    Code:
       0: aload_0
       1: invokevirtual #9                  // Method initialize:()V
       4: aload_0
       5: getfield      #4                  // Field collection:Ljava/util/Collection;
       8: invokeinterface #13,  1           // InterfaceMethod java/util/Collection.size:()I
      13: ireturn

  public boolean isEmpty();
    Code:
       0: aload_0
       1: invokevirtual #9                  // Method initialize:()V
       4: aload_0
       5: getfield      #4                  // Field collection:Ljava/util/Collection;
       8: invokeinterface #14,  1           // InterfaceMethod java/util/Collection.isEmpty:()Z
      13: ireturn

  public boolean contains(java.lang.Object);
    Code:
       0: aload_0
       1: invokevirtual #9                  // Method initialize:()V
       4: aload_0
       5: getfield      #4                  // Field collection:Ljava/util/Collection;
       8: aload_1
       9: invokeinterface #15,  2           // InterfaceMethod java/util/Collection.contains:(Ljava/lang/Object;)Z
      14: ireturn

  public boolean add(java.lang.Object);
    Code:
       0: aload_0
       1: invokevirtual #9                  // Method initialize:()V
       4: aload_0
       5: getfield      #4                  // Field collection:Ljava/util/Collection;
       8: aload_1
       9: invokeinterface #16,  2           // InterfaceMethod java/util/Collection.add:(Ljava/lang/Object;)Z
      14: istore_2
      15: iload_2
      16: ifeq          23
      19: aload_0
      20: invokevirtual #17                 // Method markDirty:()V
      23: iload_2
      24: ireturn

  public boolean remove(java.lang.Object);
    Code:
       0: aload_0
       1: invokevirtual #9                  // Method initialize:()V
       4: aload_0
       5: getfield      #4                  // Field collection:Ljava/util/Collection;
       8: aload_1
       9: invokeinterface #18,  2           // InterfaceMethod java/util/Collection.remove:(Ljava/lang/Object;)Z
      14: istore_2
      15: iload_2
      16: ifeq          23
      19: aload_0
      20: invokevirtual #17                 // Method markDirty:()V
      23: iload_2
      24: ireturn

  public void clear();
    Code:
       0: aload_0
       1: invokevirtual #9                  // Method initialize:()V
       4: aload_0
       5: getfield      #4                  // Field collection:Ljava/util/Collection;
       8: invokeinterface #19,  1           // InterfaceMethod java/util/Collection.clear:()V
      13: aload_0
      14: invokevirtual #17                 // Method markDirty:()V
      17: return

  public boolean equals(java.lang.Object);
    Code:
       0: aload_0
       1: invokevirtual #9                  // Method initialize:()V
       4: aload_0
       5: getfield      #4                  // Field collection:Ljava/util/Collection;
       8: aload_1
       9: invokeinterface #20,  2           // InterfaceMethod java/util/Collection.equals:(Ljava/lang/Object;)Z
      14: ireturn

  public int hashCode();
    Code:
       0: aload_0
       1: invokevirtual #9                  // Method initialize:()V
       4: aload_0
       5: getfield      #4                  // Field collection:Ljava/util/Collection;
       8: invokeinterface #21,  1           // InterfaceMethod java/util/Collection.hashCode:()I
      13: ireturn

  public java.lang.String toString();
    Code:
       0: aload_0
       1: invokevirtual #9                  // Method initialize:()V
       4: aload_0
       5: getfield      #4                  // Field collection:Ljava/util/Collection;
       8: invokevirtual #22                 // Method java/lang/Object.toString:()Ljava/lang/String;
      11: areturn

  public boolean removeAll(java.util.Collection);
    Code:
       0: aload_0
       1: invokevirtual #9                  // Method initialize:()V
       4: aload_0
       5: getfield      #4                  // Field collection:Ljava/util/Collection;
       8: aload_1
       9: invokeinterface #23,  2           // InterfaceMethod java/util/Collection.removeAll:(Ljava/util/Collection;)Z
      14: istore_2
      15: iload_2
      16: ifeq          23
      19: aload_0
      20: invokevirtual #17                 // Method markDirty:()V
      23: iload_2
      24: ireturn

  public java.lang.Object[] toArray();
    Code:
       0: aload_0
       1: invokevirtual #9                  // Method initialize:()V
       4: aload_0
       5: getfield      #4                  // Field collection:Ljava/util/Collection;
       8: invokeinterface #24,  1           // InterfaceMethod java/util/Collection.toArray:()[Ljava/lang/Object;
      13: areturn

  public java.lang.Object[] toArray(java.lang.Object[]);
    Code:
       0: aload_0
       1: invokevirtual #9                  // Method initialize:()V
       4: aload_0
       5: getfield      #4                  // Field collection:Ljava/util/Collection;
       8: aload_1
       9: invokeinterface #25,  2           // InterfaceMethod java/util/Collection.toArray:([Ljava/lang/Object;)[Ljava/lang/Object;
      14: areturn

  public boolean containsAll(java.util.Collection);
    Code:
       0: aload_0
       1: invokevirtual #9                  // Method initialize:()V
       4: aload_0
       5: getfield      #4                  // Field collection:Ljava/util/Collection;
       8: aload_1
       9: invokeinterface #26,  2           // InterfaceMethod java/util/Collection.containsAll:(Ljava/util/Collection;)Z
      14: ireturn

  public boolean addAll(java.util.Collection);
    Code:
       0: aload_0
       1: invokevirtual #9                  // Method initialize:()V
       4: aload_0
       5: getfield      #4                  // Field collection:Ljava/util/Collection;
       8: aload_1
       9: invokeinterface #27,  2           // InterfaceMethod java/util/Collection.addAll:(Ljava/util/Collection;)Z
      14: istore_2
      15: iload_2
      16: ifeq          23
      19: aload_0
      20: invokevirtual #17                 // Method markDirty:()V
      23: iload_2
      24: ireturn

  public boolean retainAll(java.util.Collection);
    Code:
       0: aload_0
       1: invokevirtual #9                  // Method initialize:()V
       4: aload_0
       5: getfield      #4                  // Field collection:Ljava/util/Collection;
       8: aload_1
       9: invokeinterface #28,  2           // InterfaceMethod java/util/Collection.retainAll:(Ljava/util/Collection;)Z
      14: istore_2
      15: iload_2
      16: ifeq          23
      19: aload_0
      20: invokevirtual #17                 // Method markDirty:()V
      23: iload_2
      24: ireturn

  public boolean isInitialized();
    Code:
       0: aload_0
       1: getfield      #29                 // Field initialized:Z
       4: ireturn

  public void initialize();
    Code:
       0: aload_0
       1: getfield      #29                 // Field initialized:Z
       4: ifeq          8
       7: return
       8: aload_0
       9: iconst_1
      10: putfield      #29                 // Field initialized:Z
      13: aload_0
      14: getfield      #7                  // Field associationKey:Ljava/io/Serializable;
      17: ifnonnull     52
      20: aload_0
      21: getfield      #6                  // Field keys:Ljava/util/Collection;
      24: ifnull        101
      27: aload_0
      28: aload_0
      29: getfield      #5                  // Field session:Lorg/grails/datastore/mapping/core/Session;
      32: aload_0
      33: getfield      #3                  // Field childType:Ljava/lang/Class;
      36: aload_0
      37: getfield      #6                  // Field keys:Ljava/util/Collection;
      40: invokeinterface #30,  3           // InterfaceMethod org/grails/datastore/mapping/core/Session.retrieveAll:(Ljava/lang/Class;Ljava/lang/Iterable;)Ljava/util/List;
      45: invokevirtual #31                 // Method addAll:(Ljava/util/Collection;)Z
      48: pop
      49: goto          101
      52: aload_0
      53: getfield      #8                  // Field indexer:Lorg/grails/datastore/mapping/engine/AssociationIndexer;
      56: aload_0
      57: getfield      #7                  // Field associationKey:Ljava/io/Serializable;
      60: invokeinterface #32,  2           // InterfaceMethod org/grails/datastore/mapping/engine/AssociationIndexer.query:(Ljava/lang/Object;)Ljava/util/List;
      65: astore_1
      66: aload_0
      67: getfield      #8                  // Field indexer:Lorg/grails/datastore/mapping/engine/AssociationIndexer;
      70: invokeinterface #33,  1           // InterfaceMethod org/grails/datastore/mapping/engine/AssociationIndexer.getIndexedEntity:()Lorg/grails/datastore/mapping/model/PersistentEntity;
      75: astore_2
      76: aload_2
      77: ifnull        101
      80: aload_0
      81: aload_0
      82: getfield      #5                  // Field session:Lorg/grails/datastore/mapping/core/Session;
      85: aload_2
      86: invokeinterface #34,  1           // InterfaceMethod org/grails/datastore/mapping/model/PersistentEntity.getJavaClass:()Ljava/lang/Class;
      91: aload_1
      92: invokeinterface #30,  3           // InterfaceMethod org/grails/datastore/mapping/core/Session.retrieveAll:(Ljava/lang/Class;Ljava/lang/Iterable;)Ljava/util/List;
      97: invokevirtual #31                 // Method addAll:(Ljava/util/Collection;)Z
     100: pop
     101: return

  public boolean isDirty();
    Code:
       0: aload_0
       1: getfield      #2                  // Field dirty:Z
       4: ireturn

  public void resetDirty();
    Code:
       0: aload_0
       1: iconst_0
       2: putfield      #2                  // Field dirty:Z
       5: return

  public void markDirty();
    Code:
       0: aload_0
       1: iconst_1
       2: putfield      #2                  // Field dirty:Z
       5: return
}
