Compiled from "PersistentSortedSet.java"
public class org.grails.datastore.mapping.collection.PersistentSortedSet extends org.grails.datastore.mapping.collection.AbstractPersistentCollection implements java.util.SortedSet {
  public org.grails.datastore.mapping.collection.PersistentSortedSet(java.lang.Class, org.grails.datastore.mapping.core.Session, java.util.SortedSet);
    Code:
       0: aload_0
       1: aload_1
       2: aload_2
       3: aload_3
       4: invokespecial #1                  // Method org/grails/datastore/mapping/collection/AbstractPersistentCollection."<init>":(Ljava/lang/Class;Lorg/grails/datastore/mapping/core/Session;Ljava/util/Collection;)V
       7: return

  public org.grails.datastore.mapping.collection.PersistentSortedSet(java.util.Collection, java.lang.Class, org.grails.datastore.mapping.core.Session);
    Code:
       0: aload_0
       1: aload_1
       2: aload_2
       3: aload_3
       4: new           #2                  // class java/util/TreeSet
       7: dup
       8: invokespecial #3                  // Method java/util/TreeSet."<init>":()V
      11: invokespecial #4                  // Method org/grails/datastore/mapping/collection/AbstractPersistentCollection."<init>":(Ljava/util/Collection;Ljava/lang/Class;Lorg/grails/datastore/mapping/core/Session;Ljava/util/Collection;)V
      14: return

  public org.grails.datastore.mapping.collection.PersistentSortedSet(java.io.Serializable, org.grails.datastore.mapping.core.Session, org.grails.datastore.mapping.engine.AssociationIndexer);
    Code:
       0: aload_0
       1: aload_1
       2: aload_2
       3: aload_3
       4: new           #2                  // class java/util/TreeSet
       7: dup
       8: invokespecial #3                  // Method java/util/TreeSet."<init>":()V
      11: invokespecial #5                  // Method org/grails/datastore/mapping/collection/AbstractPersistentCollection."<init>":(Ljava/io/Serializable;Lorg/grails/datastore/mapping/core/Session;Lorg/grails/datastore/mapping/engine/AssociationIndexer;Ljava/util/Collection;)V
      14: return

  public java.util.Comparator comparator();
    Code:
       0: aload_0
       1: invokespecial #6                  // Method getSortedSet:()Ljava/util/SortedSet;
       4: invokeinterface #7,  1            // InterfaceMethod java/util/SortedSet.comparator:()Ljava/util/Comparator;
       9: areturn

  private java.util.SortedSet getSortedSet();
    Code:
       0: aload_0
       1: invokevirtual #8                  // Method initialize:()V
       4: aload_0
       5: getfield      #9                  // Field collection:Ljava/util/Collection;
       8: checkcast     #10                 // class java/util/SortedSet
      11: areturn

  public java.util.SortedSet subSet(java.lang.Object, java.lang.Object);
    Code:
       0: aload_0
       1: invokespecial #6                  // Method getSortedSet:()Ljava/util/SortedSet;
       4: aload_1
       5: aload_2
       6: invokeinterface #11,  3           // InterfaceMethod java/util/SortedSet.subSet:(Ljava/lang/Object;Ljava/lang/Object;)Ljava/util/SortedSet;
      11: areturn

  public java.util.SortedSet headSet(java.lang.Object);
    Code:
       0: aload_0
       1: invokespecial #6                  // Method getSortedSet:()Ljava/util/SortedSet;
       4: aload_1
       5: invokeinterface #12,  2           // InterfaceMethod java/util/SortedSet.headSet:(Ljava/lang/Object;)Ljava/util/SortedSet;
      10: areturn

  public java.util.SortedSet tailSet(java.lang.Object);
    Code:
       0: aload_0
       1: invokespecial #6                  // Method getSortedSet:()Ljava/util/SortedSet;
       4: aload_1
       5: invokeinterface #13,  2           // InterfaceMethod java/util/SortedSet.tailSet:(Ljava/lang/Object;)Ljava/util/SortedSet;
      10: areturn

  public java.lang.Object first();
    Code:
       0: aload_0
       1: invokespecial #6                  // Method getSortedSet:()Ljava/util/SortedSet;
       4: invokeinterface #14,  1           // InterfaceMethod java/util/SortedSet.first:()Ljava/lang/Object;
       9: areturn

  public java.lang.Object last();
    Code:
       0: aload_0
       1: invokespecial #6                  // Method getSortedSet:()Ljava/util/SortedSet;
       4: invokeinterface #15,  1           // InterfaceMethod java/util/SortedSet.last:()Ljava/lang/Object;
       9: areturn
}
