Compiled from "JaxbHbmCompositeIndexType.java"
public class org.hibernate.boot.jaxb.hbm.spi.JaxbHbmCompositeIndexType implements java.io.Serializable {
  protected java.util.List<org.hibernate.boot.jaxb.hbm.spi.JaxbHbmToolingHintContainer> attributes;

  protected java.lang.String clazz;

  public org.hibernate.boot.jaxb.hbm.spi.JaxbHbmCompositeIndexType();
    Code:
       0: aload_0
       1: invokespecial #1                  // Method java/lang/Object."<init>":()V
       4: return

  public java.util.List<org.hibernate.boot.jaxb.hbm.spi.JaxbHbmToolingHintContainer> getAttributes();
    Code:
       0: aload_0
       1: getfield      #2                  // Field attributes:Ljava/util/List;
       4: ifnonnull     18
       7: aload_0
       8: new           #3                  // class java/util/ArrayList
      11: dup
      12: invokespecial #4                  // Method java/util/ArrayList."<init>":()V
      15: putfield      #2                  // Field attributes:Ljava/util/List;
      18: aload_0
      19: getfield      #2                  // Field attributes:Ljava/util/List;
      22: areturn

  public java.lang.String getClazz();
    Code:
       0: aload_0
       1: getfield      #5                  // Field clazz:Ljava/lang/String;
       4: areturn

  public void setClazz(java.lang.String);
    Code:
       0: aload_0
       1: aload_1
       2: putfield      #5                  // Field clazz:Ljava/lang/String;
       5: return
}
