Compiled from "PluralAttributeInfoPrimitiveArrayAdapter.java"
public abstract class org.hibernate.boot.jaxb.hbm.spi.PluralAttributeInfoPrimitiveArrayAdapter extends org.hibernate.boot.jaxb.hbm.spi.JaxbHbmToolingHintContainer implements org.hibernate.boot.jaxb.hbm.spi.PluralAttributeInfo {
  public org.hibernate.boot.jaxb.hbm.spi.PluralAttributeInfoPrimitiveArrayAdapter();
    Code:
       0: aload_0
       1: invokespecial #1                  // Method org/hibernate/boot/jaxb/hbm/spi/JaxbHbmToolingHintContainer."<init>":()V
       4: return

  public boolean isInverse();
    Code:
       0: iconst_0
       1: ireturn

  public org.hibernate.boot.jaxb.hbm.spi.JaxbHbmLazyWithExtraEnum getLazy();
    Code:
       0: getstatic     #2                  // Field org/hibernate/boot/jaxb/hbm/spi/JaxbHbmLazyWithExtraEnum.FALSE:Lorg/hibernate/boot/jaxb/hbm/spi/JaxbHbmLazyWithExtraEnum;
       3: areturn

  public org.hibernate.boot.jaxb.hbm.spi.JaxbHbmOneToManyCollectionElementType getOneToMany();
    Code:
       0: aconst_null
       1: areturn

  public org.hibernate.boot.jaxb.hbm.spi.JaxbHbmCompositeCollectionElementType getCompositeElement();
    Code:
       0: aconst_null
       1: areturn

  public org.hibernate.boot.jaxb.hbm.spi.JaxbHbmManyToManyCollectionElementType getManyToMany();
    Code:
       0: aconst_null
       1: areturn

  public org.hibernate.boot.jaxb.hbm.spi.JaxbHbmManyToAnyCollectionElementType getManyToAny();
    Code:
       0: aconst_null
       1: areturn

  public java.util.List<org.hibernate.boot.jaxb.hbm.spi.JaxbHbmFilterType> getFilter();
    Code:
       0: invokestatic  #3                  // Method java/util/Collections.emptyList:()Ljava/util/List;
       3: areturn

  public java.lang.String getCascade();
    Code:
       0: aconst_null
       1: areturn
}
