Compiled from "ArrayBuilders.java"
public final class org.apache.htrace.shaded.fasterxml.jackson.databind.util.ArrayBuilders$FloatBuilder extends org.apache.htrace.shaded.fasterxml.jackson.databind.util.PrimitiveArrayBuilder<float[]> {
  public org.apache.htrace.shaded.fasterxml.jackson.databind.util.ArrayBuilders$FloatBuilder();
    Code:
       0: aload_0
       1: invokespecial #13                 // Method org/apache/htrace/shaded/fasterxml/jackson/databind/util/PrimitiveArrayBuilder."<init>":()V
       4: return

  public final float[] _constructArray(int);
    Code:
       0: iload_1
       1: newarray       float
       3: areturn

  public java.lang.Object _constructArray(int);
    Code:
       0: aload_0
       1: iload_1
       2: invokevirtual #22                 // Method _constructArray:(I)[F
       5: areturn
}
