Compiled from "ByteBufferBackedOutputStream.java"
public class org.apache.htrace.shaded.fasterxml.jackson.databind.util.ByteBufferBackedOutputStream extends java.io.OutputStream {
  protected final java.nio.ByteBuffer _b;

  public org.apache.htrace.shaded.fasterxml.jackson.databind.util.ByteBufferBackedOutputStream(java.nio.ByteBuffer);
    Code:
       0: aload_0
       1: invokespecial #12                 // Method java/io/OutputStream."<init>":()V
       4: aload_0
       5: aload_1
       6: putfield      #14                 // Field _b:Ljava/nio/ByteBuffer;
       9: return

  public void write(int) throws java.io.IOException;
    Code:
       0: aload_0
       1: getfield      #14                 // Field _b:Ljava/nio/ByteBuffer;
       4: iload_1
       5: i2b
       6: invokevirtual #27                 // Method java/nio/ByteBuffer.put:(B)Ljava/nio/ByteBuffer;
       9: pop
      10: return

  public void write(byte[], int, int) throws java.io.IOException;
    Code:
       0: aload_0
       1: getfield      #14                 // Field _b:Ljava/nio/ByteBuffer;
       4: aload_1
       5: iload_2
       6: iload_3
       7: invokevirtual #33                 // Method java/nio/ByteBuffer.put:([BII)Ljava/nio/ByteBuffer;
      10: pop
      11: return
}
