Compiled from "WrappedFailoverProxyProvider.java"
public class org.apache.hadoop.hdfs.server.namenode.ha.WrappedFailoverProxyProvider<T> extends org.apache.hadoop.hdfs.server.namenode.ha.AbstractNNFailoverProxyProvider<T> {
  private final org.apache.hadoop.io.retry.FailoverProxyProvider<T> proxyProvider;

  public org.apache.hadoop.hdfs.server.namenode.ha.WrappedFailoverProxyProvider(org.apache.hadoop.io.retry.FailoverProxyProvider<T>);
    Code:
       0: aload_0
       1: invokespecial #1                  // Method org/apache/hadoop/hdfs/server/namenode/ha/AbstractNNFailoverProxyProvider."<init>":()V
       4: aload_0
       5: aload_1
       6: putfield      #2                  // Field proxyProvider:Lorg/apache/hadoop/io/retry/FailoverProxyProvider;
       9: return

  public java.lang.Class<T> getInterface();
    Code:
       0: aload_0
       1: getfield      #2                  // Field proxyProvider:Lorg/apache/hadoop/io/retry/FailoverProxyProvider;
       4: invokeinterface #3,  1            // InterfaceMethod org/apache/hadoop/io/retry/FailoverProxyProvider.getInterface:()Ljava/lang/Class;
       9: areturn

  public synchronized org.apache.hadoop.io.retry.FailoverProxyProvider$ProxyInfo<T> getProxy();
    Code:
       0: aload_0
       1: getfield      #2                  // Field proxyProvider:Lorg/apache/hadoop/io/retry/FailoverProxyProvider;
       4: invokeinterface #4,  1            // InterfaceMethod org/apache/hadoop/io/retry/FailoverProxyProvider.getProxy:()Lorg/apache/hadoop/io/retry/FailoverProxyProvider$ProxyInfo;
       9: areturn

  public void performFailover(T);
    Code:
       0: aload_0
       1: getfield      #2                  // Field proxyProvider:Lorg/apache/hadoop/io/retry/FailoverProxyProvider;
       4: aload_1
       5: invokeinterface #5,  2            // InterfaceMethod org/apache/hadoop/io/retry/FailoverProxyProvider.performFailover:(Ljava/lang/Object;)V
      10: return

  public synchronized void close() throws java.io.IOException;
    Code:
       0: aload_0
       1: getfield      #2                  // Field proxyProvider:Lorg/apache/hadoop/io/retry/FailoverProxyProvider;
       4: invokeinterface #6,  1            // InterfaceMethod org/apache/hadoop/io/retry/FailoverProxyProvider.close:()V
       9: return

  public boolean useLogicalURI();
    Code:
       0: iconst_1
       1: ireturn
}
