Compiled from "TimeDefinitions.java"
public class org.apache.kafka.streams.kstream.internals.suppress.TimeDefinitions$WindowEndTimeDefinition<K extends org.apache.kafka.streams.kstream.Windowed> implements org.apache.kafka.streams.kstream.internals.suppress.TimeDefinitions$TimeDefinition<K> {
  private static final org.apache.kafka.streams.kstream.internals.suppress.TimeDefinitions$WindowEndTimeDefinition INSTANCE;

  private org.apache.kafka.streams.kstream.internals.suppress.TimeDefinitions$WindowEndTimeDefinition();
    Code:
       0: aload_0
       1: invokespecial #1                  // Method java/lang/Object."<init>":()V
       4: return

  public static <K extends org.apache.kafka.streams.kstream.Windowed> org.apache.kafka.streams.kstream.internals.suppress.TimeDefinitions$WindowEndTimeDefinition<K> instance();
    Code:
       0: getstatic     #2                  // Field INSTANCE:Lorg/apache/kafka/streams/kstream/internals/suppress/TimeDefinitions$WindowEndTimeDefinition;
       3: areturn

  public long time(org.apache.kafka.streams.processor.ProcessorContext, K);
    Code:
       0: aload_2
       1: invokevirtual #3                  // Method org/apache/kafka/streams/kstream/Windowed.window:()Lorg/apache/kafka/streams/kstream/Window;
       4: invokevirtual #4                  // Method org/apache/kafka/streams/kstream/Window.end:()J
       7: lreturn

  public org.apache.kafka.streams.kstream.internals.suppress.TimeDefinitions$TimeDefinitionType type();
    Code:
       0: getstatic     #5                  // Field org/apache/kafka/streams/kstream/internals/suppress/TimeDefinitions$TimeDefinitionType.WINDOW_END_TIME:Lorg/apache/kafka/streams/kstream/internals/suppress/TimeDefinitions$TimeDefinitionType;
       3: areturn

  public long time(org.apache.kafka.streams.processor.ProcessorContext, java.lang.Object);
    Code:
       0: aload_0
       1: aload_1
       2: aload_2
       3: checkcast     #6                  // class org/apache/kafka/streams/kstream/Windowed
       6: invokevirtual #7                  // Method time:(Lorg/apache/kafka/streams/processor/ProcessorContext;Lorg/apache/kafka/streams/kstream/Windowed;)J
       9: lreturn

  static {};
    Code:
       0: new           #8                  // class org/apache/kafka/streams/kstream/internals/suppress/TimeDefinitions$WindowEndTimeDefinition
       3: dup
       4: invokespecial #9                  // Method "<init>":()V
       7: putstatic     #2                  // Field INSTANCE:Lorg/apache/kafka/streams/kstream/internals/suppress/TimeDefinitions$WindowEndTimeDefinition;
      10: return
}
