Compiled from "PathVariableMethodArgumentResolver.java"
class org.springframework.web.servlet.mvc.method.annotation.PathVariableMethodArgumentResolver$PathVariableNamedValueInfo extends org.springframework.web.method.annotation.AbstractNamedValueMethodArgumentResolver$NamedValueInfo {
  public org.springframework.web.servlet.mvc.method.annotation.PathVariableMethodArgumentResolver$PathVariableNamedValueInfo(org.springframework.web.bind.annotation.PathVariable);
    Code:
       0: aload_0
       1: aload_1
       2: invokeinterface #1,  1            // InterfaceMethod org/springframework/web/bind/annotation/PathVariable.name:()Ljava/lang/String;
       7: aload_1
       8: invokeinterface #2,  1            // InterfaceMethod org/springframework/web/bind/annotation/PathVariable.required:()Z
      13: ldc           #4                  // String \n\t\t\n\t\t\n\n\t\t\t\t\n
      15: invokespecial #5                  // Method org/springframework/web/method/annotation/AbstractNamedValueMethodArgumentResolver$NamedValueInfo."<init>":(Ljava/lang/String;ZLjava/lang/String;)V
      18: return
}
