Compiled from "LongForm.java"
public class org.apache.commons.compress.harmony.unpack200.bytecode.forms.LongForm extends org.apache.commons.compress.harmony.unpack200.bytecode.forms.ReferenceForm {
  public org.apache.commons.compress.harmony.unpack200.bytecode.forms.LongForm(int, java.lang.String, int[]);
    Code:
       0: aload_0
       1: iload_1
       2: aload_2
       3: aload_3
       4: invokespecial #1                  // Method org/apache/commons/compress/harmony/unpack200/bytecode/forms/ReferenceForm."<init>":(ILjava/lang/String;[I)V
       7: return

  protected int getOffset(org.apache.commons.compress.harmony.unpack200.bytecode.OperandManager);
    Code:
       0: aload_1
       1: invokevirtual #2                  // Method org/apache/commons/compress/harmony/unpack200/bytecode/OperandManager.nextLongRef:()I
       4: ireturn

  protected int getPoolID();
    Code:
       0: iconst_4
       1: ireturn
}
