Compiled from "DefaultSecurityManager.java"
public class org.apache.shiro.mgt.DefaultSecurityManager extends org.apache.shiro.mgt.SessionsSecurityManager {
  private static final org.slf4j.Logger log;

  protected org.apache.shiro.mgt.RememberMeManager rememberMeManager;

  protected org.apache.shiro.mgt.SubjectDAO subjectDAO;

  protected org.apache.shiro.mgt.SubjectFactory subjectFactory;

  public org.apache.shiro.mgt.DefaultSecurityManager();
    Code:
       0: aload_0
       1: invokespecial #1                  // Method org/apache/shiro/mgt/SessionsSecurityManager."<init>":()V
       4: aload_0
       5: new           #2                  // class org/apache/shiro/mgt/DefaultSubjectFactory
       8: dup
       9: invokespecial #3                  // Method org/apache/shiro/mgt/DefaultSubjectFactory."<init>":()V
      12: putfield      #4                  // Field subjectFactory:Lorg/apache/shiro/mgt/SubjectFactory;
      15: aload_0
      16: new           #5                  // class org/apache/shiro/mgt/DefaultSubjectDAO
      19: dup
      20: invokespecial #6                  // Method org/apache/shiro/mgt/DefaultSubjectDAO."<init>":()V
      23: putfield      #7                  // Field subjectDAO:Lorg/apache/shiro/mgt/SubjectDAO;
      26: return

  public org.apache.shiro.mgt.DefaultSecurityManager(org.apache.shiro.realm.Realm);
    Code:
       0: aload_0
       1: invokespecial #8                  // Method "<init>":()V
       4: aload_0
       5: aload_1
       6: invokevirtual #9                  // Method setRealm:(Lorg/apache/shiro/realm/Realm;)V
       9: return

  public org.apache.shiro.mgt.DefaultSecurityManager(java.util.Collection<org.apache.shiro.realm.Realm>);
    Code:
       0: aload_0
       1: invokespecial #8                  // Method "<init>":()V
       4: aload_0
       5: aload_1
       6: invokevirtual #10                 // Method setRealms:(Ljava/util/Collection;)V
       9: return

  public org.apache.shiro.mgt.SubjectFactory getSubjectFactory();
    Code:
       0: aload_0
       1: getfield      #4                  // Field subjectFactory:Lorg/apache/shiro/mgt/SubjectFactory;
       4: areturn

  public void setSubjectFactory(org.apache.shiro.mgt.SubjectFactory);
    Code:
       0: aload_0
       1: aload_1
       2: putfield      #4                  // Field subjectFactory:Lorg/apache/shiro/mgt/SubjectFactory;
       5: return

  public org.apache.shiro.mgt.SubjectDAO getSubjectDAO();
    Code:
       0: aload_0
       1: getfield      #7                  // Field subjectDAO:Lorg/apache/shiro/mgt/SubjectDAO;
       4: areturn

  public void setSubjectDAO(org.apache.shiro.mgt.SubjectDAO);
    Code:
       0: aload_0
       1: aload_1
       2: putfield      #7                  // Field subjectDAO:Lorg/apache/shiro/mgt/SubjectDAO;
       5: return

  public org.apache.shiro.mgt.RememberMeManager getRememberMeManager();
    Code:
       0: aload_0
       1: getfield      #11                 // Field rememberMeManager:Lorg/apache/shiro/mgt/RememberMeManager;
       4: areturn

  public void setRememberMeManager(org.apache.shiro.mgt.RememberMeManager);
    Code:
       0: aload_0
       1: aload_1
       2: putfield      #11                 // Field rememberMeManager:Lorg/apache/shiro/mgt/RememberMeManager;
       5: return

  protected org.apache.shiro.subject.SubjectContext createSubjectContext();
    Code:
       0: new           #12                 // class org/apache/shiro/subject/support/DefaultSubjectContext
       3: dup
       4: invokespecial #13                 // Method org/apache/shiro/subject/support/DefaultSubjectContext."<init>":()V
       7: areturn

  protected org.apache.shiro.subject.Subject createSubject(org.apache.shiro.authc.AuthenticationToken, org.apache.shiro.authc.AuthenticationInfo, org.apache.shiro.subject.Subject);
    Code:
       0: aload_0
       1: invokevirtual #14                 // Method createSubjectContext:()Lorg/apache/shiro/subject/SubjectContext;
       4: astore        4
       6: aload         4
       8: iconst_1
       9: invokeinterface #15,  2           // InterfaceMethod org/apache/shiro/subject/SubjectContext.setAuthenticated:(Z)V
      14: aload         4
      16: aload_1
      17: invokeinterface #16,  2           // InterfaceMethod org/apache/shiro/subject/SubjectContext.setAuthenticationToken:(Lorg/apache/shiro/authc/AuthenticationToken;)V
      22: aload         4
      24: aload_2
      25: invokeinterface #17,  2           // InterfaceMethod org/apache/shiro/subject/SubjectContext.setAuthenticationInfo:(Lorg/apache/shiro/authc/AuthenticationInfo;)V
      30: aload_3
      31: ifnull        42
      34: aload         4
      36: aload_3
      37: invokeinterface #18,  2           // InterfaceMethod org/apache/shiro/subject/SubjectContext.setSubject:(Lorg/apache/shiro/subject/Subject;)V
      42: aload_0
      43: aload         4
      45: invokevirtual #19                 // Method createSubject:(Lorg/apache/shiro/subject/SubjectContext;)Lorg/apache/shiro/subject/Subject;
      48: areturn

  protected void bind(org.apache.shiro.subject.Subject);
    Code:
       0: aload_0
       1: aload_1
       2: invokevirtual #20                 // Method save:(Lorg/apache/shiro/subject/Subject;)V
       5: return

  protected void rememberMeSuccessfulLogin(org.apache.shiro.authc.AuthenticationToken, org.apache.shiro.authc.AuthenticationInfo, org.apache.shiro.subject.Subject);
    Code:
       0: aload_0
       1: invokevirtual #21                 // Method getRememberMeManager:()Lorg/apache/shiro/mgt/RememberMeManager;
       4: astore        4
       6: aload         4
       8: ifnull        99
      11: aload         4
      13: aload_3
      14: aload_1
      15: aload_2
      16: invokeinterface #22,  4           // InterfaceMethod org/apache/shiro/mgt/RememberMeManager.onSuccessfulLogin:(Lorg/apache/shiro/subject/Subject;Lorg/apache/shiro/authc/AuthenticationToken;Lorg/apache/shiro/authc/AuthenticationInfo;)V
      21: goto          181
      24: astore        5
      26: getstatic     #24                 // Field log:Lorg/slf4j/Logger;
      29: invokeinterface #25,  1           // InterfaceMethod org/slf4j/Logger.isWarnEnabled:()Z
      34: ifeq          96
      37: new           #26                 // class java/lang/StringBuilder
      40: dup
      41: invokespecial #27                 // Method java/lang/StringBuilder."<init>":()V
      44: ldc           #28                 // String Delegate RememberMeManager instance of type [
      46: invokevirtual #29                 // Method java/lang/StringBuilder.append:(Ljava/lang/String;)Ljava/lang/StringBuilder;
      49: aload         4
      51: invokevirtual #30                 // Method java/lang/Object.getClass:()Ljava/lang/Class;
      54: invokevirtual #31                 // Method java/lang/Class.getName:()Ljava/lang/String;
      57: invokevirtual #29                 // Method java/lang/StringBuilder.append:(Ljava/lang/String;)Ljava/lang/StringBuilder;
      60: ldc           #32                 // String ] threw an exception during onSuccessfulLogin.  RememberMe services will not be
      62: invokevirtual #29                 // Method java/lang/StringBuilder.append:(Ljava/lang/String;)Ljava/lang/StringBuilder;
      65: ldc           #33                 // String performed for account [
      67: invokevirtual #29                 // Method java/lang/StringBuilder.append:(Ljava/lang/String;)Ljava/lang/StringBuilder;
      70: aload_2
      71: invokevirtual #34                 // Method java/lang/StringBuilder.append:(Ljava/lang/Object;)Ljava/lang/StringBuilder;
      74: ldc           #35                 // String ].
      76: invokevirtual #29                 // Method java/lang/StringBuilder.append:(Ljava/lang/String;)Ljava/lang/StringBuilder;
      79: invokevirtual #36                 // Method java/lang/StringBuilder.toString:()Ljava/lang/String;
      82: astore        6
      84: getstatic     #24                 // Field log:Lorg/slf4j/Logger;
      87: aload         6
      89: aload         5
      91: invokeinterface #37,  3           // InterfaceMethod org/slf4j/Logger.warn:(Ljava/lang/String;Ljava/lang/Throwable;)V
      96: goto          181
      99: getstatic     #24                 // Field log:Lorg/slf4j/Logger;
     102: invokeinterface #38,  1           // InterfaceMethod org/slf4j/Logger.isTraceEnabled:()Z
     107: ifeq          181
     110: getstatic     #24                 // Field log:Lorg/slf4j/Logger;
     113: new           #26                 // class java/lang/StringBuilder
     116: dup
     117: invokespecial #27                 // Method java/lang/StringBuilder."<init>":()V
     120: ldc           #39                 // String This
     122: invokevirtual #29                 // Method java/lang/StringBuilder.append:(Ljava/lang/String;)Ljava/lang/StringBuilder;
     125: aload_0
     126: invokevirtual #30                 // Method java/lang/Object.getClass:()Ljava/lang/Class;
     129: invokevirtual #31                 // Method java/lang/Class.getName:()Ljava/lang/String;
     132: invokevirtual #29                 // Method java/lang/StringBuilder.append:(Ljava/lang/String;)Ljava/lang/StringBuilder;
     135: ldc           #40                 // String  instance does not have a
     137: invokevirtual #29                 // Method java/lang/StringBuilder.append:(Ljava/lang/String;)Ljava/lang/StringBuilder;
     140: ldc           #41                 // String [
     142: invokevirtual #29                 // Method java/lang/StringBuilder.append:(Ljava/lang/String;)Ljava/lang/StringBuilder;
     145: ldc_w         #42                 // class org/apache/shiro/mgt/RememberMeManager
     148: invokevirtual #31                 // Method java/lang/Class.getName:()Ljava/lang/String;
     151: invokevirtual #29                 // Method java/lang/StringBuilder.append:(Ljava/lang/String;)Ljava/lang/StringBuilder;
     154: ldc           #43                 // String ] instance configured.  RememberMe services
     156: invokevirtual #29                 // Method java/lang/StringBuilder.append:(Ljava/lang/String;)Ljava/lang/StringBuilder;
     159: ldc           #44                 // String will not be performed for account [
     161: invokevirtual #29                 // Method java/lang/StringBuilder.append:(Ljava/lang/String;)Ljava/lang/StringBuilder;
     164: aload_2
     165: invokevirtual #34                 // Method java/lang/StringBuilder.append:(Ljava/lang/Object;)Ljava/lang/StringBuilder;
     168: ldc           #35                 // String ].
     170: invokevirtual #29                 // Method java/lang/StringBuilder.append:(Ljava/lang/String;)Ljava/lang/StringBuilder;
     173: invokevirtual #36                 // Method java/lang/StringBuilder.toString:()Ljava/lang/String;
     176: invokeinterface #45,  2           // InterfaceMethod org/slf4j/Logger.trace:(Ljava/lang/String;)V
     181: return
    Exception table:
       from    to  target type
          11    21    24   Class java/lang/Exception

  protected void rememberMeFailedLogin(org.apache.shiro.authc.AuthenticationToken, org.apache.shiro.authc.AuthenticationException, org.apache.shiro.subject.Subject);
    Code:
       0: aload_0
       1: invokevirtual #21                 // Method getRememberMeManager:()Lorg/apache/shiro/mgt/RememberMeManager;
       4: astore        4
       6: aload         4
       8: ifnull        91
      11: aload         4
      13: aload_3
      14: aload_1
      15: aload_2
      16: invokeinterface #46,  4           // InterfaceMethod org/apache/shiro/mgt/RememberMeManager.onFailedLogin:(Lorg/apache/shiro/subject/Subject;Lorg/apache/shiro/authc/AuthenticationToken;Lorg/apache/shiro/authc/AuthenticationException;)V
      21: goto          91
      24: astore        5
      26: getstatic     #24                 // Field log:Lorg/slf4j/Logger;
      29: invokeinterface #25,  1           // InterfaceMethod org/slf4j/Logger.isWarnEnabled:()Z
      34: ifeq          91
      37: new           #26                 // class java/lang/StringBuilder
      40: dup
      41: invokespecial #27                 // Method java/lang/StringBuilder."<init>":()V
      44: ldc           #28                 // String Delegate RememberMeManager instance of type [
      46: invokevirtual #29                 // Method java/lang/StringBuilder.append:(Ljava/lang/String;)Ljava/lang/StringBuilder;
      49: aload         4
      51: invokevirtual #30                 // Method java/lang/Object.getClass:()Ljava/lang/Class;
      54: invokevirtual #31                 // Method java/lang/Class.getName:()Ljava/lang/String;
      57: invokevirtual #29                 // Method java/lang/StringBuilder.append:(Ljava/lang/String;)Ljava/lang/StringBuilder;
      60: ldc           #47                 // String ] threw an exception during onFailedLogin for AuthenticationToken [
      62: invokevirtual #29                 // Method java/lang/StringBuilder.append:(Ljava/lang/String;)Ljava/lang/StringBuilder;
      65: aload_1
      66: invokevirtual #34                 // Method java/lang/StringBuilder.append:(Ljava/lang/Object;)Ljava/lang/StringBuilder;
      69: ldc           #35                 // String ].
      71: invokevirtual #29                 // Method java/lang/StringBuilder.append:(Ljava/lang/String;)Ljava/lang/StringBuilder;
      74: invokevirtual #36                 // Method java/lang/StringBuilder.toString:()Ljava/lang/String;
      77: astore        6
      79: getstatic     #24                 // Field log:Lorg/slf4j/Logger;
      82: aload         6
      84: aload         5
      86: invokeinterface #37,  3           // InterfaceMethod org/slf4j/Logger.warn:(Ljava/lang/String;Ljava/lang/Throwable;)V
      91: return
    Exception table:
       from    to  target type
          11    21    24   Class java/lang/Exception

  protected void rememberMeLogout(org.apache.shiro.subject.Subject);
    Code:
       0: aload_0
       1: invokevirtual #21                 // Method getRememberMeManager:()Lorg/apache/shiro/mgt/RememberMeManager;
       4: astore_2
       5: aload_2
       6: ifnull        96
       9: aload_2
      10: aload_1
      11: invokeinterface #48,  2           // InterfaceMethod org/apache/shiro/mgt/RememberMeManager.onLogout:(Lorg/apache/shiro/subject/Subject;)V
      16: goto          96
      19: astore_3
      20: getstatic     #24                 // Field log:Lorg/slf4j/Logger;
      23: invokeinterface #25,  1           // InterfaceMethod org/slf4j/Logger.isWarnEnabled:()Z
      28: ifeq          96
      31: new           #26                 // class java/lang/StringBuilder
      34: dup
      35: invokespecial #27                 // Method java/lang/StringBuilder."<init>":()V
      38: ldc           #28                 // String Delegate RememberMeManager instance of type [
      40: invokevirtual #29                 // Method java/lang/StringBuilder.append:(Ljava/lang/String;)Ljava/lang/StringBuilder;
      43: aload_2
      44: invokevirtual #30                 // Method java/lang/Object.getClass:()Ljava/lang/Class;
      47: invokevirtual #31                 // Method java/lang/Class.getName:()Ljava/lang/String;
      50: invokevirtual #29                 // Method java/lang/StringBuilder.append:(Ljava/lang/String;)Ljava/lang/StringBuilder;
      53: ldc           #49                 // String ] threw an exception during onLogout for subject with principals [
      55: invokevirtual #29                 // Method java/lang/StringBuilder.append:(Ljava/lang/String;)Ljava/lang/StringBuilder;
      58: aload_1
      59: ifnull        71
      62: aload_1
      63: invokeinterface #50,  1           // InterfaceMethod org/apache/shiro/subject/Subject.getPrincipals:()Lorg/apache/shiro/subject/PrincipalCollection;
      68: goto          72
      71: aconst_null
      72: invokevirtual #34                 // Method java/lang/StringBuilder.append:(Ljava/lang/Object;)Ljava/lang/StringBuilder;
      75: ldc           #51                 // String ]
      77: invokevirtual #29                 // Method java/lang/StringBuilder.append:(Ljava/lang/String;)Ljava/lang/StringBuilder;
      80: invokevirtual #36                 // Method java/lang/StringBuilder.toString:()Ljava/lang/String;
      83: astore        4
      85: getstatic     #24                 // Field log:Lorg/slf4j/Logger;
      88: aload         4
      90: aload_3
      91: invokeinterface #37,  3           // InterfaceMethod org/slf4j/Logger.warn:(Ljava/lang/String;Ljava/lang/Throwable;)V
      96: return
    Exception table:
       from    to  target type
           9    16    19   Class java/lang/Exception

  public org.apache.shiro.subject.Subject login(org.apache.shiro.subject.Subject, org.apache.shiro.authc.AuthenticationToken) throws org.apache.shiro.authc.AuthenticationException;
    Code:
       0: aload_0
       1: aload_2
       2: invokevirtual #52                 // Method authenticate:(Lorg/apache/shiro/authc/AuthenticationToken;)Lorg/apache/shiro/authc/AuthenticationInfo;
       5: astore_3
       6: goto          50
       9: astore        4
      11: aload_0
      12: aload_2
      13: aload         4
      15: aload_1
      16: invokevirtual #54                 // Method onFailedLogin:(Lorg/apache/shiro/authc/AuthenticationToken;Lorg/apache/shiro/authc/AuthenticationException;Lorg/apache/shiro/subject/Subject;)V
      19: goto          47
      22: astore        5
      24: getstatic     #24                 // Field log:Lorg/slf4j/Logger;
      27: invokeinterface #55,  1           // InterfaceMethod org/slf4j/Logger.isInfoEnabled:()Z
      32: ifeq          47
      35: getstatic     #24                 // Field log:Lorg/slf4j/Logger;
      38: ldc           #56                 // String onFailedLogin method threw an exception.  Logging and propagating original AuthenticationException.
      40: aload         5
      42: invokeinterface #57,  3           // InterfaceMethod org/slf4j/Logger.info:(Ljava/lang/String;Ljava/lang/Throwable;)V
      47: aload         4
      49: athrow
      50: aload_0
      51: aload_2
      52: aload_3
      53: aload_1
      54: invokevirtual #58                 // Method createSubject:(Lorg/apache/shiro/authc/AuthenticationToken;Lorg/apache/shiro/authc/AuthenticationInfo;Lorg/apache/shiro/subject/Subject;)Lorg/apache/shiro/subject/Subject;
      57: astore        4
      59: aload_0
      60: aload_2
      61: aload_3
      62: aload         4
      64: invokevirtual #59                 // Method onSuccessfulLogin:(Lorg/apache/shiro/authc/AuthenticationToken;Lorg/apache/shiro/authc/AuthenticationInfo;Lorg/apache/shiro/subject/Subject;)V
      67: aload         4
      69: areturn
    Exception table:
       from    to  target type
           0     6     9   Class org/apache/shiro/authc/AuthenticationException
          11    19    22   Class java/lang/Exception

  protected void onSuccessfulLogin(org.apache.shiro.authc.AuthenticationToken, org.apache.shiro.authc.AuthenticationInfo, org.apache.shiro.subject.Subject);
    Code:
       0: aload_0
       1: aload_1
       2: aload_2
       3: aload_3
       4: invokevirtual #60                 // Method rememberMeSuccessfulLogin:(Lorg/apache/shiro/authc/AuthenticationToken;Lorg/apache/shiro/authc/AuthenticationInfo;Lorg/apache/shiro/subject/Subject;)V
       7: return

  protected void onFailedLogin(org.apache.shiro.authc.AuthenticationToken, org.apache.shiro.authc.AuthenticationException, org.apache.shiro.subject.Subject);
    Code:
       0: aload_0
       1: aload_1
       2: aload_2
       3: aload_3
       4: invokevirtual #61                 // Method rememberMeFailedLogin:(Lorg/apache/shiro/authc/AuthenticationToken;Lorg/apache/shiro/authc/AuthenticationException;Lorg/apache/shiro/subject/Subject;)V
       7: return

  protected void beforeLogout(org.apache.shiro.subject.Subject);
    Code:
       0: aload_0
       1: aload_1
       2: invokevirtual #62                 // Method rememberMeLogout:(Lorg/apache/shiro/subject/Subject;)V
       5: return

  protected org.apache.shiro.subject.SubjectContext copy(org.apache.shiro.subject.SubjectContext);
    Code:
       0: new           #12                 // class org/apache/shiro/subject/support/DefaultSubjectContext
       3: dup
       4: aload_1
       5: invokespecial #63                 // Method org/apache/shiro/subject/support/DefaultSubjectContext."<init>":(Lorg/apache/shiro/subject/SubjectContext;)V
       8: areturn

  public org.apache.shiro.subject.Subject createSubject(org.apache.shiro.subject.SubjectContext);
    Code:
       0: aload_0
       1: aload_1
       2: invokevirtual #64                 // Method copy:(Lorg/apache/shiro/subject/SubjectContext;)Lorg/apache/shiro/subject/SubjectContext;
       5: astore_2
       6: aload_0
       7: aload_2
       8: invokevirtual #65                 // Method ensureSecurityManager:(Lorg/apache/shiro/subject/SubjectContext;)Lorg/apache/shiro/subject/SubjectContext;
      11: astore_2
      12: aload_0
      13: aload_2
      14: invokevirtual #66                 // Method resolveSession:(Lorg/apache/shiro/subject/SubjectContext;)Lorg/apache/shiro/subject/SubjectContext;
      17: astore_2
      18: aload_0
      19: aload_2
      20: invokevirtual #67                 // Method resolvePrincipals:(Lorg/apache/shiro/subject/SubjectContext;)Lorg/apache/shiro/subject/SubjectContext;
      23: astore_2
      24: aload_0
      25: aload_2
      26: invokevirtual #68                 // Method doCreateSubject:(Lorg/apache/shiro/subject/SubjectContext;)Lorg/apache/shiro/subject/Subject;
      29: astore_3
      30: aload_0
      31: aload_3
      32: invokevirtual #20                 // Method save:(Lorg/apache/shiro/subject/Subject;)V
      35: aload_3
      36: areturn

  protected org.apache.shiro.subject.Subject doCreateSubject(org.apache.shiro.subject.SubjectContext);
    Code:
       0: aload_0
       1: invokevirtual #69                 // Method getSubjectFactory:()Lorg/apache/shiro/mgt/SubjectFactory;
       4: aload_1
       5: invokeinterface #70,  2           // InterfaceMethod org/apache/shiro/mgt/SubjectFactory.createSubject:(Lorg/apache/shiro/subject/SubjectContext;)Lorg/apache/shiro/subject/Subject;
      10: areturn

  protected void save(org.apache.shiro.subject.Subject);
    Code:
       0: aload_0
       1: getfield      #7                  // Field subjectDAO:Lorg/apache/shiro/mgt/SubjectDAO;
       4: aload_1
       5: invokeinterface #71,  2           // InterfaceMethod org/apache/shiro/mgt/SubjectDAO.save:(Lorg/apache/shiro/subject/Subject;)Lorg/apache/shiro/subject/Subject;
      10: pop
      11: return

  protected void delete(org.apache.shiro.subject.Subject);
    Code:
       0: aload_0
       1: getfield      #7                  // Field subjectDAO:Lorg/apache/shiro/mgt/SubjectDAO;
       4: aload_1
       5: invokeinterface #72,  2           // InterfaceMethod org/apache/shiro/mgt/SubjectDAO.delete:(Lorg/apache/shiro/subject/Subject;)V
      10: return

  protected org.apache.shiro.subject.SubjectContext ensureSecurityManager(org.apache.shiro.subject.SubjectContext);
    Code:
       0: aload_1
       1: invokeinterface #73,  1           // InterfaceMethod org/apache/shiro/subject/SubjectContext.resolveSecurityManager:()Lorg/apache/shiro/mgt/SecurityManager;
       6: ifnull        21
       9: getstatic     #24                 // Field log:Lorg/slf4j/Logger;
      12: ldc           #74                 // String Context already contains a SecurityManager instance.  Returning.
      14: invokeinterface #45,  2           // InterfaceMethod org/slf4j/Logger.trace:(Ljava/lang/String;)V
      19: aload_1
      20: areturn
      21: getstatic     #24                 // Field log:Lorg/slf4j/Logger;
      24: ldc           #75                 // String No SecurityManager found in context.  Adding self reference.
      26: invokeinterface #45,  2           // InterfaceMethod org/slf4j/Logger.trace:(Ljava/lang/String;)V
      31: aload_1
      32: aload_0
      33: invokeinterface #76,  2           // InterfaceMethod org/apache/shiro/subject/SubjectContext.setSecurityManager:(Lorg/apache/shiro/mgt/SecurityManager;)V
      38: aload_1
      39: areturn

  protected org.apache.shiro.subject.SubjectContext resolveSession(org.apache.shiro.subject.SubjectContext);
    Code:
       0: aload_1
       1: invokeinterface #77,  1           // InterfaceMethod org/apache/shiro/subject/SubjectContext.resolveSession:()Lorg/apache/shiro/session/Session;
       6: ifnull        21
       9: getstatic     #24                 // Field log:Lorg/slf4j/Logger;
      12: ldc           #78                 // String Context already contains a session.  Returning.
      14: invokeinterface #79,  2           // InterfaceMethod org/slf4j/Logger.debug:(Ljava/lang/String;)V
      19: aload_1
      20: areturn
      21: aload_0
      22: aload_1
      23: invokevirtual #80                 // Method resolveContextSession:(Lorg/apache/shiro/subject/SubjectContext;)Lorg/apache/shiro/session/Session;
      26: astore_2
      27: aload_2
      28: ifnull        38
      31: aload_1
      32: aload_2
      33: invokeinterface #81,  2           // InterfaceMethod org/apache/shiro/subject/SubjectContext.setSession:(Lorg/apache/shiro/session/Session;)V
      38: goto          53
      41: astore_2
      42: getstatic     #24                 // Field log:Lorg/slf4j/Logger;
      45: ldc           #83                 // String Resolved SubjectContext context session is invalid.  Ignoring and creating an anonymous (session-less) Subject instance.
      47: aload_2
      48: invokeinterface #84,  3           // InterfaceMethod org/slf4j/Logger.debug:(Ljava/lang/String;Ljava/lang/Throwable;)V
      53: aload_1
      54: areturn
    Exception table:
       from    to  target type
          21    38    41   Class org/apache/shiro/session/InvalidSessionException

  protected org.apache.shiro.session.Session resolveContextSession(org.apache.shiro.subject.SubjectContext) throws org.apache.shiro.session.InvalidSessionException;
    Code:
       0: aload_0
       1: aload_1
       2: invokevirtual #85                 // Method getSessionKey:(Lorg/apache/shiro/subject/SubjectContext;)Lorg/apache/shiro/session/mgt/SessionKey;
       5: astore_2
       6: aload_2
       7: ifnull        16
      10: aload_0
      11: aload_2
      12: invokevirtual #86                 // Method getSession:(Lorg/apache/shiro/session/mgt/SessionKey;)Lorg/apache/shiro/session/Session;
      15: areturn
      16: aconst_null
      17: areturn

  protected org.apache.shiro.session.mgt.SessionKey getSessionKey(org.apache.shiro.subject.SubjectContext);
    Code:
       0: aload_1
       1: invokeinterface #87,  1           // InterfaceMethod org/apache/shiro/subject/SubjectContext.getSessionId:()Ljava/io/Serializable;
       6: astore_2
       7: aload_2
       8: ifnull        20
      11: new           #88                 // class org/apache/shiro/session/mgt/DefaultSessionKey
      14: dup
      15: aload_2
      16: invokespecial #89                 // Method org/apache/shiro/session/mgt/DefaultSessionKey."<init>":(Ljava/io/Serializable;)V
      19: areturn
      20: aconst_null
      21: areturn

  protected org.apache.shiro.subject.SubjectContext resolvePrincipals(org.apache.shiro.subject.SubjectContext);
    Code:
       0: aload_1
       1: invokeinterface #90,  1           // InterfaceMethod org/apache/shiro/subject/SubjectContext.resolvePrincipals:()Lorg/apache/shiro/subject/PrincipalCollection;
       6: astore_2
       7: aload_2
       8: invokestatic  #91                 // Method org/apache/shiro/util/CollectionUtils.isEmpty:(Lorg/apache/shiro/subject/PrincipalCollection;)Z
      11: ifeq          67
      14: getstatic     #24                 // Field log:Lorg/slf4j/Logger;
      17: ldc           #92                 // String No identity (PrincipalCollection) found in the context.  Looking for a remembered identity.
      19: invokeinterface #45,  2           // InterfaceMethod org/slf4j/Logger.trace:(Ljava/lang/String;)V
      24: aload_0
      25: aload_1
      26: invokevirtual #93                 // Method getRememberedIdentity:(Lorg/apache/shiro/subject/SubjectContext;)Lorg/apache/shiro/subject/PrincipalCollection;
      29: astore_2
      30: aload_2
      31: invokestatic  #91                 // Method org/apache/shiro/util/CollectionUtils.isEmpty:(Lorg/apache/shiro/subject/PrincipalCollection;)Z
      34: ifne          57
      37: getstatic     #24                 // Field log:Lorg/slf4j/Logger;
      40: ldc           #94                 // String Found remembered PrincipalCollection.  Adding to the context to be used for subject construction by the SubjectFactory.
      42: invokeinterface #79,  2           // InterfaceMethod org/slf4j/Logger.debug:(Ljava/lang/String;)V
      47: aload_1
      48: aload_2
      49: invokeinterface #95,  2           // InterfaceMethod org/apache/shiro/subject/SubjectContext.setPrincipals:(Lorg/apache/shiro/subject/PrincipalCollection;)V
      54: goto          67
      57: getstatic     #24                 // Field log:Lorg/slf4j/Logger;
      60: ldc           #96                 // String No remembered identity found.  Returning original context.
      62: invokeinterface #45,  2           // InterfaceMethod org/slf4j/Logger.trace:(Ljava/lang/String;)V
      67: aload_1
      68: areturn

  protected org.apache.shiro.session.mgt.SessionContext createSessionContext(org.apache.shiro.subject.SubjectContext);
    Code:
       0: new           #97                 // class org/apache/shiro/session/mgt/DefaultSessionContext
       3: dup
       4: invokespecial #98                 // Method org/apache/shiro/session/mgt/DefaultSessionContext."<init>":()V
       7: astore_2
       8: aload_1
       9: invokestatic  #99                 // Method org/apache/shiro/util/CollectionUtils.isEmpty:(Ljava/util/Map;)Z
      12: ifne          20
      15: aload_2
      16: aload_1
      17: invokevirtual #100                // Method org/apache/shiro/session/mgt/DefaultSessionContext.putAll:(Ljava/util/Map;)V
      20: aload_1
      21: invokeinterface #87,  1           // InterfaceMethod org/apache/shiro/subject/SubjectContext.getSessionId:()Ljava/io/Serializable;
      26: astore_3
      27: aload_3
      28: ifnull        36
      31: aload_2
      32: aload_3
      33: invokevirtual #101                // Method org/apache/shiro/session/mgt/DefaultSessionContext.setSessionId:(Ljava/io/Serializable;)V
      36: aload_1
      37: invokeinterface #102,  1          // InterfaceMethod org/apache/shiro/subject/SubjectContext.resolveHost:()Ljava/lang/String;
      42: astore        4
      44: aload         4
      46: ifnull        55
      49: aload_2
      50: aload         4
      52: invokevirtual #103                // Method org/apache/shiro/session/mgt/DefaultSessionContext.setHost:(Ljava/lang/String;)V
      55: aload_2
      56: areturn

  public void logout(org.apache.shiro.subject.Subject);
    Code:
       0: aload_1
       1: ifnonnull     14
       4: new           #104                // class java/lang/IllegalArgumentException
       7: dup
       8: ldc           #105                // String Subject method argument cannot be null.
      10: invokespecial #106                // Method java/lang/IllegalArgumentException."<init>":(Ljava/lang/String;)V
      13: athrow
      14: aload_0
      15: aload_1
      16: invokevirtual #107                // Method beforeLogout:(Lorg/apache/shiro/subject/Subject;)V
      19: aload_1
      20: invokeinterface #50,  1           // InterfaceMethod org/apache/shiro/subject/Subject.getPrincipals:()Lorg/apache/shiro/subject/PrincipalCollection;
      25: astore_2
      26: aload_2
      27: ifnull        88
      30: aload_2
      31: invokeinterface #108,  1          // InterfaceMethod org/apache/shiro/subject/PrincipalCollection.isEmpty:()Z
      36: ifne          88
      39: getstatic     #24                 // Field log:Lorg/slf4j/Logger;
      42: invokeinterface #109,  1          // InterfaceMethod org/slf4j/Logger.isDebugEnabled:()Z
      47: ifeq          66
      50: getstatic     #24                 // Field log:Lorg/slf4j/Logger;
      53: ldc           #110                // String Logging out subject with primary principal {}
      55: aload_2
      56: invokeinterface #111,  1          // InterfaceMethod org/apache/shiro/subject/PrincipalCollection.getPrimaryPrincipal:()Ljava/lang/Object;
      61: invokeinterface #112,  3          // InterfaceMethod org/slf4j/Logger.debug:(Ljava/lang/String;Ljava/lang/Object;)V
      66: aload_0
      67: invokevirtual #113                // Method getAuthenticator:()Lorg/apache/shiro/authc/Authenticator;
      70: astore_3
      71: aload_3
      72: instanceof    #114                // class org/apache/shiro/authc/LogoutAware
      75: ifeq          88
      78: aload_3
      79: checkcast     #114                // class org/apache/shiro/authc/LogoutAware
      82: aload_2
      83: invokeinterface #115,  2          // InterfaceMethod org/apache/shiro/authc/LogoutAware.onLogout:(Lorg/apache/shiro/subject/PrincipalCollection;)V
      88: aload_0
      89: aload_1
      90: invokevirtual #116                // Method delete:(Lorg/apache/shiro/subject/Subject;)V
      93: aload_0
      94: aload_1
      95: invokevirtual #117                // Method stopSession:(Lorg/apache/shiro/subject/Subject;)V
      98: goto          334
     101: astore_3
     102: getstatic     #24                 // Field log:Lorg/slf4j/Logger;
     105: invokeinterface #109,  1          // InterfaceMethod org/slf4j/Logger.isDebugEnabled:()Z
     110: ifeq          160
     113: new           #26                 // class java/lang/StringBuilder
     116: dup
     117: invokespecial #27                 // Method java/lang/StringBuilder."<init>":()V
     120: ldc           #118                // String Unable to cleanly stop Session for Subject [
     122: invokevirtual #29                 // Method java/lang/StringBuilder.append:(Ljava/lang/String;)Ljava/lang/StringBuilder;
     125: aload_1
     126: invokeinterface #119,  1          // InterfaceMethod org/apache/shiro/subject/Subject.getPrincipal:()Ljava/lang/Object;
     131: invokevirtual #34                 // Method java/lang/StringBuilder.append:(Ljava/lang/Object;)Ljava/lang/StringBuilder;
     134: ldc           #120                // String ]
     136: invokevirtual #29                 // Method java/lang/StringBuilder.append:(Ljava/lang/String;)Ljava/lang/StringBuilder;
     139: ldc           #121                // String Ignoring (logging out).
     141: invokevirtual #29                 // Method java/lang/StringBuilder.append:(Ljava/lang/String;)Ljava/lang/StringBuilder;
     144: invokevirtual #36                 // Method java/lang/StringBuilder.toString:()Ljava/lang/String;
     147: astore        4
     149: getstatic     #24                 // Field log:Lorg/slf4j/Logger;
     152: aload         4
     154: aload_3
     155: invokeinterface #84,  3           // InterfaceMethod org/slf4j/Logger.debug:(Ljava/lang/String;Ljava/lang/Throwable;)V
     160: goto          334
     163: astore_3
     164: getstatic     #24                 // Field log:Lorg/slf4j/Logger;
     167: invokeinterface #109,  1          // InterfaceMethod org/slf4j/Logger.isDebugEnabled:()Z
     172: ifeq          190
     175: ldc           #122                // String Unable to cleanly unbind Subject.  Ignoring (logging out).
     177: astore        4
     179: getstatic     #24                 // Field log:Lorg/slf4j/Logger;
     182: aload         4
     184: aload_3
     185: invokeinterface #84,  3           // InterfaceMethod org/slf4j/Logger.debug:(Ljava/lang/String;Ljava/lang/Throwable;)V
     190: aload_0
     191: aload_1
     192: invokevirtual #117                // Method stopSession:(Lorg/apache/shiro/subject/Subject;)V
     195: goto          334
     198: astore_3
     199: getstatic     #24                 // Field log:Lorg/slf4j/Logger;
     202: invokeinterface #109,  1          // InterfaceMethod org/slf4j/Logger.isDebugEnabled:()Z
     207: ifeq          257
     210: new           #26                 // class java/lang/StringBuilder
     213: dup
     214: invokespecial #27                 // Method java/lang/StringBuilder."<init>":()V
     217: ldc           #118                // String Unable to cleanly stop Session for Subject [
     219: invokevirtual #29                 // Method java/lang/StringBuilder.append:(Ljava/lang/String;)Ljava/lang/StringBuilder;
     222: aload_1
     223: invokeinterface #119,  1          // InterfaceMethod org/apache/shiro/subject/Subject.getPrincipal:()Ljava/lang/Object;
     228: invokevirtual #34                 // Method java/lang/StringBuilder.append:(Ljava/lang/Object;)Ljava/lang/StringBuilder;
     231: ldc           #120                // String ]
     233: invokevirtual #29                 // Method java/lang/StringBuilder.append:(Ljava/lang/String;)Ljava/lang/StringBuilder;
     236: ldc           #121                // String Ignoring (logging out).
     238: invokevirtual #29                 // Method java/lang/StringBuilder.append:(Ljava/lang/String;)Ljava/lang/StringBuilder;
     241: invokevirtual #36                 // Method java/lang/StringBuilder.toString:()Ljava/lang/String;
     244: astore        4
     246: getstatic     #24                 // Field log:Lorg/slf4j/Logger;
     249: aload         4
     251: aload_3
     252: invokeinterface #84,  3           // InterfaceMethod org/slf4j/Logger.debug:(Ljava/lang/String;Ljava/lang/Throwable;)V
     257: goto          334
     260: astore        5
     262: aload_0
     263: aload_1
     264: invokevirtual #117                // Method stopSession:(Lorg/apache/shiro/subject/Subject;)V
     267: goto          331
     270: astore        6
     272: getstatic     #24                 // Field log:Lorg/slf4j/Logger;
     275: invokeinterface #109,  1          // InterfaceMethod org/slf4j/Logger.isDebugEnabled:()Z
     280: ifeq          331
     283: new           #26                 // class java/lang/StringBuilder
     286: dup
     287: invokespecial #27                 // Method java/lang/StringBuilder."<init>":()V
     290: ldc           #118                // String Unable to cleanly stop Session for Subject [
     292: invokevirtual #29                 // Method java/lang/StringBuilder.append:(Ljava/lang/String;)Ljava/lang/StringBuilder;
     295: aload_1
     296: invokeinterface #119,  1          // InterfaceMethod org/apache/shiro/subject/Subject.getPrincipal:()Ljava/lang/Object;
     301: invokevirtual #34                 // Method java/lang/StringBuilder.append:(Ljava/lang/Object;)Ljava/lang/StringBuilder;
     304: ldc           #120                // String ]
     306: invokevirtual #29                 // Method java/lang/StringBuilder.append:(Ljava/lang/String;)Ljava/lang/StringBuilder;
     309: ldc           #121                // String Ignoring (logging out).
     311: invokevirtual #29                 // Method java/lang/StringBuilder.append:(Ljava/lang/String;)Ljava/lang/StringBuilder;
     314: invokevirtual #36                 // Method java/lang/StringBuilder.toString:()Ljava/lang/String;
     317: astore        7
     319: getstatic     #24                 // Field log:Lorg/slf4j/Logger;
     322: aload         7
     324: aload         6
     326: invokeinterface #84,  3           // InterfaceMethod org/slf4j/Logger.debug:(Ljava/lang/String;Ljava/lang/Throwable;)V
     331: aload         5
     333: athrow
     334: return
    Exception table:
       from    to  target type
          93    98   101   Class java/lang/Exception
          88    93   163   Class java/lang/Exception
         190   195   198   Class java/lang/Exception
          88    93   260   any
         163   190   260   any
         262   267   270   Class java/lang/Exception
         260   262   260   any

  protected void stopSession(org.apache.shiro.subject.Subject);
    Code:
       0: aload_1
       1: iconst_0
       2: invokeinterface #123,  2          // InterfaceMethod org/apache/shiro/subject/Subject.getSession:(Z)Lorg/apache/shiro/session/Session;
       7: astore_2
       8: aload_2
       9: ifnull        18
      12: aload_2
      13: invokeinterface #124,  1          // InterfaceMethod org/apache/shiro/session/Session.stop:()V
      18: return

  protected void unbind(org.apache.shiro.subject.Subject);
    Code:
       0: aload_0
       1: aload_1
       2: invokevirtual #116                // Method delete:(Lorg/apache/shiro/subject/Subject;)V
       5: return

  protected org.apache.shiro.subject.PrincipalCollection getRememberedIdentity(org.apache.shiro.subject.SubjectContext);
    Code:
       0: aload_0
       1: invokevirtual #21                 // Method getRememberMeManager:()Lorg/apache/shiro/mgt/RememberMeManager;
       4: astore_2
       5: aload_2
       6: ifnull        72
       9: aload_2
      10: aload_1
      11: invokeinterface #125,  2          // InterfaceMethod org/apache/shiro/mgt/RememberMeManager.getRememberedPrincipals:(Lorg/apache/shiro/subject/SubjectContext;)Lorg/apache/shiro/subject/PrincipalCollection;
      16: areturn
      17: astore_3
      18: getstatic     #24                 // Field log:Lorg/slf4j/Logger;
      21: invokeinterface #25,  1           // InterfaceMethod org/slf4j/Logger.isWarnEnabled:()Z
      26: ifeq          72
      29: new           #26                 // class java/lang/StringBuilder
      32: dup
      33: invokespecial #27                 // Method java/lang/StringBuilder."<init>":()V
      36: ldc           #28                 // String Delegate RememberMeManager instance of type [
      38: invokevirtual #29                 // Method java/lang/StringBuilder.append:(Ljava/lang/String;)Ljava/lang/StringBuilder;
      41: aload_2
      42: invokevirtual #30                 // Method java/lang/Object.getClass:()Ljava/lang/Class;
      45: invokevirtual #31                 // Method java/lang/Class.getName:()Ljava/lang/String;
      48: invokevirtual #29                 // Method java/lang/StringBuilder.append:(Ljava/lang/String;)Ljava/lang/StringBuilder;
      51: ldc           #126                // String ] threw an exception during getRememberedPrincipals().
      53: invokevirtual #29                 // Method java/lang/StringBuilder.append:(Ljava/lang/String;)Ljava/lang/StringBuilder;
      56: invokevirtual #36                 // Method java/lang/StringBuilder.toString:()Ljava/lang/String;
      59: astore        4
      61: getstatic     #24                 // Field log:Lorg/slf4j/Logger;
      64: aload         4
      66: aload_3
      67: invokeinterface #37,  3           // InterfaceMethod org/slf4j/Logger.warn:(Ljava/lang/String;Ljava/lang/Throwable;)V
      72: aconst_null
      73: areturn
    Exception table:
       from    to  target type
           9    16    17   Class java/lang/Exception

  static {};
    Code:
       0: ldc_w         #127                // class org/apache/shiro/mgt/DefaultSecurityManager
       3: invokestatic  #128                // Method org/slf4j/LoggerFactory.getLogger:(Ljava/lang/Class;)Lorg/slf4j/Logger;
       6: putstatic     #24                 // Field log:Lorg/slf4j/Logger;
       9: return
}
