Compiled from "ExecutableMetaData.java"
public class org.hibernate.validator.internal.metadata.aggregated.ExecutableMetaData$Builder extends org.hibernate.validator.internal.metadata.aggregated.MetaDataBuilder {
  private final java.util.Set<org.hibernate.validator.internal.properties.Signature> signatures;

  private final org.hibernate.validator.internal.metadata.raw.ConstrainedElement$ConstrainedElementKind kind;

  private final java.util.Set<org.hibernate.validator.internal.metadata.raw.ConstrainedExecutable> constrainedExecutables;

  private org.hibernate.validator.internal.properties.Callable callable;

  private final java.util.Set<org.hibernate.validator.internal.metadata.core.MetaConstraint<?>> crossParameterConstraints;

  private final java.util.Set<org.hibernate.validator.internal.metadata.aggregated.rule.MethodConfigurationRule> rules;

  private boolean isConstrained;

  private org.hibernate.validator.internal.metadata.aggregated.CascadingMetaDataBuilder cascadingMetaDataBuilder;

  private final java.util.Map<java.lang.Class<?>, org.hibernate.validator.internal.metadata.raw.ConstrainedExecutable> executablesByDeclaringType;

  private final org.hibernate.validator.internal.util.ExecutableHelper executableHelper;

  private final org.hibernate.validator.internal.util.ExecutableParameterNameProvider parameterNameProvider;

  public org.hibernate.validator.internal.metadata.aggregated.ExecutableMetaData$Builder(java.lang.Class<?>, org.hibernate.validator.internal.metadata.raw.ConstrainedExecutable, org.hibernate.validator.internal.engine.ConstraintCreationContext, org.hibernate.validator.internal.util.ExecutableHelper, org.hibernate.validator.internal.util.ExecutableParameterNameProvider, org.hibernate.validator.internal.engine.MethodValidationConfiguration);
    Code:
       0: aload_0
       1: aload_1
       2: aload_3
       3: invokespecial #1                  // Method org/hibernate/validator/internal/metadata/aggregated/MetaDataBuilder."<init>":(Ljava/lang/Class;Lorg/hibernate/validator/internal/engine/ConstraintCreationContext;)V
       6: aload_0
       7: invokestatic  #7                  // Method org/hibernate/validator/internal/util/CollectionHelper.newHashSet:()Ljava/util/HashSet;
      10: putfield      #13                 // Field signatures:Ljava/util/Set;
      13: aload_0
      14: invokestatic  #7                  // Method org/hibernate/validator/internal/util/CollectionHelper.newHashSet:()Ljava/util/HashSet;
      17: putfield      #19                 // Field constrainedExecutables:Ljava/util/Set;
      20: aload_0
      21: invokestatic  #7                  // Method org/hibernate/validator/internal/util/CollectionHelper.newHashSet:()Ljava/util/HashSet;
      24: putfield      #22                 // Field crossParameterConstraints:Ljava/util/Set;
      27: aload_0
      28: iconst_0
      29: putfield      #25                 // Field isConstrained:Z
      32: aload_0
      33: invokestatic  #29                 // Method org/hibernate/validator/internal/util/CollectionHelper.newHashMap:()Ljava/util/HashMap;
      36: putfield      #33                 // Field executablesByDeclaringType:Ljava/util/Map;
      39: aload_0
      40: aload         4
      42: putfield      #37                 // Field executableHelper:Lorg/hibernate/validator/internal/util/ExecutableHelper;
      45: aload_0
      46: aload         5
      48: putfield      #41                 // Field parameterNameProvider:Lorg/hibernate/validator/internal/util/ExecutableParameterNameProvider;
      51: aload_0
      52: aload_2
      53: invokevirtual #45                 // Method org/hibernate/validator/internal/metadata/raw/ConstrainedExecutable.getKind:()Lorg/hibernate/validator/internal/metadata/raw/ConstrainedElement$ConstrainedElementKind;
      56: putfield      #51                 // Field kind:Lorg/hibernate/validator/internal/metadata/raw/ConstrainedElement$ConstrainedElementKind;
      59: aload_0
      60: aload_2
      61: invokevirtual #55                 // Method org/hibernate/validator/internal/metadata/raw/ConstrainedExecutable.getCallable:()Lorg/hibernate/validator/internal/properties/Callable;
      64: putfield      #59                 // Field callable:Lorg/hibernate/validator/internal/properties/Callable;
      67: aload_0
      68: aload         6
      70: invokevirtual #63                 // Method org/hibernate/validator/internal/engine/MethodValidationConfiguration.getConfiguredRuleSet:()Ljava/util/Set;
      73: putfield      #69                 // Field rules:Ljava/util/Set;
      76: aload_0
      77: aload_2
      78: invokevirtual #72                 // Method add:(Lorg/hibernate/validator/internal/metadata/raw/ConstrainedElement;)V
      81: return

  public boolean accepts(org.hibernate.validator.internal.metadata.raw.ConstrainedElement);
    Code:
       0: aload_0
       1: getfield      #51                 // Field kind:Lorg/hibernate/validator/internal/metadata/raw/ConstrainedElement$ConstrainedElementKind;
       4: aload_1
       5: invokeinterface #76,  1           // InterfaceMethod org/hibernate/validator/internal/metadata/raw/ConstrainedElement.getKind:()Lorg/hibernate/validator/internal/metadata/raw/ConstrainedElement$ConstrainedElementKind;
      10: if_acmpeq     15
      13: iconst_0
      14: ireturn
      15: aload_1
      16: checkcast     #46                 // class org/hibernate/validator/internal/metadata/raw/ConstrainedExecutable
      19: invokevirtual #55                 // Method org/hibernate/validator/internal/metadata/raw/ConstrainedExecutable.getCallable:()Lorg/hibernate/validator/internal/properties/Callable;
      22: astore_2
      23: aload_0
      24: aload_0
      25: getfield      #59                 // Field callable:Lorg/hibernate/validator/internal/properties/Callable;
      28: aload_2
      29: invokevirtual #79                 // Method isResolvedToSameMethodInHierarchy:(Lorg/hibernate/validator/internal/properties/Callable;Lorg/hibernate/validator/internal/properties/Callable;)Z
      32: ireturn

  private boolean isResolvedToSameMethodInHierarchy(org.hibernate.validator.internal.properties.Callable, org.hibernate.validator.internal.properties.Callable);
    Code:
       0: aload_0
       1: aload_1
       2: invokevirtual #83                 // Method isConstructor:(Lorg/hibernate/validator/internal/properties/Callable;)Z
       5: ifne          16
       8: aload_0
       9: aload_2
      10: invokevirtual #83                 // Method isConstructor:(Lorg/hibernate/validator/internal/properties/Callable;)Z
      13: ifeq          22
      16: aload_1
      17: aload_2
      18: invokevirtual #87                 // Method java/lang/Object.equals:(Ljava/lang/Object;)Z
      21: ireturn
      22: aload_1
      23: aload_0
      24: getfield      #37                 // Field executableHelper:Lorg/hibernate/validator/internal/util/ExecutableHelper;
      27: aload_0
      28: invokevirtual #93                 // Method getBeanClass:()Ljava/lang/Class;
      31: aload_2
      32: invokeinterface #97,  4           // InterfaceMethod org/hibernate/validator/internal/properties/Callable.isResolvedToSameMethodInHierarchy:(Lorg/hibernate/validator/internal/util/ExecutableHelper;Ljava/lang/Class;Lorg/hibernate/validator/internal/properties/Callable;)Z
      37: ireturn

  private boolean overrides(org.hibernate.validator.internal.properties.Callable, org.hibernate.validator.internal.properties.Callable);
    Code:
       0: aload_0
       1: aload_1
       2: invokevirtual #83                 // Method isConstructor:(Lorg/hibernate/validator/internal/properties/Callable;)Z
       5: ifne          16
       8: aload_0
       9: aload_2
      10: invokevirtual #83                 // Method isConstructor:(Lorg/hibernate/validator/internal/properties/Callable;)Z
      13: ifeq          18
      16: iconst_0
      17: ireturn
      18: aload_0
      19: getfield      #37                 // Field executableHelper:Lorg/hibernate/validator/internal/util/ExecutableHelper;
      22: aload_1
      23: aload_2
      24: invokevirtual #102                // Method org/hibernate/validator/internal/util/ExecutableHelper.overrides:(Lorg/hibernate/validator/internal/properties/Callable;Lorg/hibernate/validator/internal/properties/Callable;)Z
      27: ireturn

  private boolean isConstructor(org.hibernate.validator.internal.properties.Callable);
    Code:
       0: aload_1
       1: invokeinterface #107,  1          // InterfaceMethod org/hibernate/validator/internal/properties/Callable.getConstrainedElementKind:()Lorg/hibernate/validator/internal/metadata/raw/ConstrainedElement$ConstrainedElementKind;
       6: getstatic     #110                // Field org/hibernate/validator/internal/metadata/raw/ConstrainedElement$ConstrainedElementKind.CONSTRUCTOR:Lorg/hibernate/validator/internal/metadata/raw/ConstrainedElement$ConstrainedElementKind;
       9: if_acmpne     16
      12: iconst_1
      13: goto          17
      16: iconst_0
      17: ireturn

  public final void add(org.hibernate.validator.internal.metadata.raw.ConstrainedElement);
    Code:
       0: aload_0
       1: aload_1
       2: invokespecial #115                // Method org/hibernate/validator/internal/metadata/aggregated/MetaDataBuilder.add:(Lorg/hibernate/validator/internal/metadata/raw/ConstrainedElement;)V
       5: aload_1
       6: checkcast     #46                 // class org/hibernate/validator/internal/metadata/raw/ConstrainedExecutable
       9: astore_2
      10: aload_0
      11: getfield      #13                 // Field signatures:Ljava/util/Set;
      14: aload_2
      15: invokevirtual #55                 // Method org/hibernate/validator/internal/metadata/raw/ConstrainedExecutable.getCallable:()Lorg/hibernate/validator/internal/properties/Callable;
      18: invokeinterface #116,  1          // InterfaceMethod org/hibernate/validator/internal/properties/Callable.getSignature:()Lorg/hibernate/validator/internal/properties/Signature;
      23: invokeinterface #120,  2          // InterfaceMethod java/util/Set.add:(Ljava/lang/Object;)Z
      28: pop
      29: aload_0
      30: getfield      #19                 // Field constrainedExecutables:Ljava/util/Set;
      33: aload_2
      34: invokeinterface #120,  2          // InterfaceMethod java/util/Set.add:(Ljava/lang/Object;)Z
      39: pop
      40: aload_0
      41: aload_0
      42: getfield      #25                 // Field isConstrained:Z
      45: ifne          55
      48: aload_2
      49: invokevirtual #124                // Method org/hibernate/validator/internal/metadata/raw/ConstrainedExecutable.isConstrained:()Z
      52: ifeq          59
      55: iconst_1
      56: goto          60
      59: iconst_0
      60: putfield      #25                 // Field isConstrained:Z
      63: aload_0
      64: getfield      #22                 // Field crossParameterConstraints:Ljava/util/Set;
      67: aload_2
      68: invokevirtual #127                // Method org/hibernate/validator/internal/metadata/raw/ConstrainedExecutable.getCrossParameterConstraints:()Ljava/util/Set;
      71: invokeinterface #130,  2          // InterfaceMethod java/util/Set.addAll:(Ljava/util/Collection;)Z
      76: pop
      77: aload_0
      78: getfield      #134                // Field cascadingMetaDataBuilder:Lorg/hibernate/validator/internal/metadata/aggregated/CascadingMetaDataBuilder;
      81: ifnonnull     95
      84: aload_0
      85: aload_2
      86: invokevirtual #138                // Method org/hibernate/validator/internal/metadata/raw/ConstrainedExecutable.getCascadingMetaDataBuilder:()Lorg/hibernate/validator/internal/metadata/aggregated/CascadingMetaDataBuilder;
      89: putfield      #134                // Field cascadingMetaDataBuilder:Lorg/hibernate/validator/internal/metadata/aggregated/CascadingMetaDataBuilder;
      92: goto          110
      95: aload_0
      96: aload_0
      97: getfield      #134                // Field cascadingMetaDataBuilder:Lorg/hibernate/validator/internal/metadata/aggregated/CascadingMetaDataBuilder;
     100: aload_2
     101: invokevirtual #138                // Method org/hibernate/validator/internal/metadata/raw/ConstrainedExecutable.getCascadingMetaDataBuilder:()Lorg/hibernate/validator/internal/metadata/aggregated/CascadingMetaDataBuilder;
     104: invokevirtual #142                // Method org/hibernate/validator/internal/metadata/aggregated/CascadingMetaDataBuilder.merge:(Lorg/hibernate/validator/internal/metadata/aggregated/CascadingMetaDataBuilder;)Lorg/hibernate/validator/internal/metadata/aggregated/CascadingMetaDataBuilder;
     107: putfield      #134                // Field cascadingMetaDataBuilder:Lorg/hibernate/validator/internal/metadata/aggregated/CascadingMetaDataBuilder;
     110: aload_0
     111: aload_2
     112: invokevirtual #148                // Method addToExecutablesByDeclaringType:(Lorg/hibernate/validator/internal/metadata/raw/ConstrainedExecutable;)V
     115: aload_0
     116: getfield      #59                 // Field callable:Lorg/hibernate/validator/internal/properties/Callable;
     119: ifnull        145
     122: aload_0
     123: aload_2
     124: invokevirtual #55                 // Method org/hibernate/validator/internal/metadata/raw/ConstrainedExecutable.getCallable:()Lorg/hibernate/validator/internal/properties/Callable;
     127: aload_0
     128: getfield      #59                 // Field callable:Lorg/hibernate/validator/internal/properties/Callable;
     131: invokevirtual #152                // Method overrides:(Lorg/hibernate/validator/internal/properties/Callable;Lorg/hibernate/validator/internal/properties/Callable;)Z
     134: ifeq          145
     137: aload_0
     138: aload_2
     139: invokevirtual #55                 // Method org/hibernate/validator/internal/metadata/raw/ConstrainedExecutable.getCallable:()Lorg/hibernate/validator/internal/properties/Callable;
     142: putfield      #59                 // Field callable:Lorg/hibernate/validator/internal/properties/Callable;
     145: return

  private void addToExecutablesByDeclaringType(org.hibernate.validator.internal.metadata.raw.ConstrainedExecutable);
    Code:
       0: aload_1
       1: invokevirtual #55                 // Method org/hibernate/validator/internal/metadata/raw/ConstrainedExecutable.getCallable:()Lorg/hibernate/validator/internal/properties/Callable;
       4: invokeinterface #153,  1          // InterfaceMethod org/hibernate/validator/internal/properties/Callable.getDeclaringClass:()Ljava/lang/Class;
       9: astore_2
      10: aload_0
      11: getfield      #33                 // Field executablesByDeclaringType:Ljava/util/Map;
      14: aload_2
      15: invokeinterface #156,  2          // InterfaceMethod java/util/Map.get:(Ljava/lang/Object;)Ljava/lang/Object;
      20: checkcast     #46                 // class org/hibernate/validator/internal/metadata/raw/ConstrainedExecutable
      23: astore_3
      24: aload_3
      25: ifnull        37
      28: aload_3
      29: aload_1
      30: invokevirtual #162                // Method org/hibernate/validator/internal/metadata/raw/ConstrainedExecutable.merge:(Lorg/hibernate/validator/internal/metadata/raw/ConstrainedExecutable;)Lorg/hibernate/validator/internal/metadata/raw/ConstrainedExecutable;
      33: astore_3
      34: goto          39
      37: aload_1
      38: astore_3
      39: aload_0
      40: getfield      #33                 // Field executablesByDeclaringType:Ljava/util/Map;
      43: aload_2
      44: aload_3
      45: invokeinterface #165,  3          // InterfaceMethod java/util/Map.put:(Ljava/lang/Object;Ljava/lang/Object;)Ljava/lang/Object;
      50: pop
      51: return

  public org.hibernate.validator.internal.metadata.aggregated.ExecutableMetaData build();
    Code:
       0: aload_0
       1: invokevirtual #169                // Method assertCorrectnessOfConfiguration:()V
       4: new           #173                // class org/hibernate/validator/internal/metadata/aggregated/ExecutableMetaData
       7: dup
       8: aload_0
       9: getfield      #59                 // Field callable:Lorg/hibernate/validator/internal/properties/Callable;
      12: invokeinterface #175,  1          // InterfaceMethod org/hibernate/validator/internal/properties/Callable.getName:()Ljava/lang/String;
      17: aload_0
      18: getfield      #59                 // Field callable:Lorg/hibernate/validator/internal/properties/Callable;
      21: invokeinterface #179,  1          // InterfaceMethod org/hibernate/validator/internal/properties/Callable.getType:()Ljava/lang/reflect/Type;
      26: aload_0
      27: getfield      #59                 // Field callable:Lorg/hibernate/validator/internal/properties/Callable;
      30: invokeinterface #183,  1          // InterfaceMethod org/hibernate/validator/internal/properties/Callable.getParameterTypes:()[Ljava/lang/Class;
      35: aload_0
      36: getfield      #51                 // Field kind:Lorg/hibernate/validator/internal/metadata/raw/ConstrainedElement$ConstrainedElementKind;
      39: getstatic     #110                // Field org/hibernate/validator/internal/metadata/raw/ConstrainedElement$ConstrainedElementKind.CONSTRUCTOR:Lorg/hibernate/validator/internal/metadata/raw/ConstrainedElement$ConstrainedElementKind;
      42: if_acmpne     51
      45: getstatic     #187                // Field jakarta/validation/ElementKind.CONSTRUCTOR:Ljakarta/validation/ElementKind;
      48: goto          54
      51: getstatic     #192                // Field jakarta/validation/ElementKind.METHOD:Ljakarta/validation/ElementKind;
      54: aload_0
      55: getfield      #51                 // Field kind:Lorg/hibernate/validator/internal/metadata/raw/ConstrainedElement$ConstrainedElementKind;
      58: getstatic     #110                // Field org/hibernate/validator/internal/metadata/raw/ConstrainedElement$ConstrainedElementKind.CONSTRUCTOR:Lorg/hibernate/validator/internal/metadata/raw/ConstrainedElement$ConstrainedElementKind;
      61: if_acmpne     79
      64: aload_0
      65: getfield      #59                 // Field callable:Lorg/hibernate/validator/internal/properties/Callable;
      68: invokeinterface #116,  1          // InterfaceMethod org/hibernate/validator/internal/properties/Callable.getSignature:()Lorg/hibernate/validator/internal/properties/Signature;
      73: invokestatic  #195                // Method java/util/Collections.singleton:(Ljava/lang/Object;)Ljava/util/Set;
      76: goto          86
      79: aload_0
      80: getfield      #13                 // Field signatures:Ljava/util/Set;
      83: invokestatic  #201                // Method org/hibernate/validator/internal/util/CollectionHelper.toImmutableSet:(Ljava/util/Set;)Ljava/util/Set;
      86: aload_0
      87: aload_0
      88: invokevirtual #205                // Method getDirectConstraints:()Ljava/util/Set;
      91: invokevirtual #208                // Method adaptOriginsAndImplicitGroups:(Ljava/util/Set;)Ljava/util/Set;
      94: aload_0
      95: aload_0
      96: invokevirtual #211                // Method getContainerElementConstraints:()Ljava/util/Set;
      99: invokevirtual #208                // Method adaptOriginsAndImplicitGroups:(Ljava/util/Set;)Ljava/util/Set;
     102: aload_0
     103: invokevirtual #214                // Method findParameterMetaData:()Ljava/util/List;
     106: aload_0
     107: aload_0
     108: getfield      #22                 // Field crossParameterConstraints:Ljava/util/Set;
     111: invokevirtual #208                // Method adaptOriginsAndImplicitGroups:(Ljava/util/Set;)Ljava/util/Set;
     114: aload_0
     115: getfield      #134                // Field cascadingMetaDataBuilder:Lorg/hibernate/validator/internal/metadata/aggregated/CascadingMetaDataBuilder;
     118: aload_0
     119: getfield      #218                // Field constraintCreationContext:Lorg/hibernate/validator/internal/engine/ConstraintCreationContext;
     122: invokevirtual #222                // Method org/hibernate/validator/internal/engine/ConstraintCreationContext.getValueExtractorManager:()Lorg/hibernate/validator/internal/engine/valueextraction/ValueExtractorManager;
     125: aload_0
     126: getfield      #59                 // Field callable:Lorg/hibernate/validator/internal/properties/Callable;
     129: invokevirtual #228                // Method org/hibernate/validator/internal/metadata/aggregated/CascadingMetaDataBuilder.build:(Lorg/hibernate/validator/internal/engine/valueextraction/ValueExtractorManager;Ljava/lang/Object;)Lorg/hibernate/validator/internal/metadata/aggregated/CascadingMetaData;
     132: aload_0
     133: getfield      #25                 // Field isConstrained:Z
     136: aload_0
     137: getfield      #51                 // Field kind:Lorg/hibernate/validator/internal/metadata/raw/ConstrainedElement$ConstrainedElementKind;
     140: getstatic     #232                // Field org/hibernate/validator/internal/metadata/raw/ConstrainedElement$ConstrainedElementKind.GETTER:Lorg/hibernate/validator/internal/metadata/raw/ConstrainedElement$ConstrainedElementKind;
     143: if_acmpne     150
     146: iconst_1
     147: goto          151
     150: iconst_0
     151: invokespecial #235                // Method org/hibernate/validator/internal/metadata/aggregated/ExecutableMetaData."<init>":(Ljava/lang/String;Ljava/lang/reflect/Type;[Ljava/lang/Class;Ljakarta/validation/ElementKind;Ljava/util/Set;Ljava/util/Set;Ljava/util/Set;Ljava/util/List;Ljava/util/Set;Lorg/hibernate/validator/internal/metadata/aggregated/CascadingMetaData;ZZ)V
     154: areturn

  private java.util.List<org.hibernate.validator.internal.metadata.aggregated.ParameterMetaData> findParameterMetaData();
    Code:
       0: aconst_null
       1: astore_1
       2: aload_0
       3: getfield      #19                 // Field constrainedExecutables:Ljava/util/Set;
       6: invokeinterface #238,  1          // InterfaceMethod java/util/Set.iterator:()Ljava/util/Iterator;
      11: astore_2
      12: aload_2
      13: invokeinterface #242,  1          // InterfaceMethod java/util/Iterator.hasNext:()Z
      18: ifeq          172
      21: aload_2
      22: invokeinterface #247,  1          // InterfaceMethod java/util/Iterator.next:()Ljava/lang/Object;
      27: checkcast     #46                 // class org/hibernate/validator/internal/metadata/raw/ConstrainedExecutable
      30: astore_3
      31: aload_1
      32: ifnonnull     111
      35: invokestatic  #251                // Method org/hibernate/validator/internal/util/CollectionHelper.newArrayList:()Ljava/util/ArrayList;
      38: astore_1
      39: aload_3
      40: invokevirtual #255                // Method org/hibernate/validator/internal/metadata/raw/ConstrainedExecutable.getAllParameterMetaData:()Ljava/util/List;
      43: invokeinterface #258,  1          // InterfaceMethod java/util/List.iterator:()Ljava/util/Iterator;
      48: astore        4
      50: aload         4
      52: invokeinterface #242,  1          // InterfaceMethod java/util/Iterator.hasNext:()Z
      57: ifeq          108
      60: aload         4
      62: invokeinterface #247,  1          // InterfaceMethod java/util/Iterator.next:()Ljava/lang/Object;
      67: checkcast     #261                // class org/hibernate/validator/internal/metadata/raw/ConstrainedParameter
      70: astore        5
      72: aload_1
      73: new           #263                // class org/hibernate/validator/internal/metadata/aggregated/ParameterMetaData$Builder
      76: dup
      77: aload_0
      78: getfield      #59                 // Field callable:Lorg/hibernate/validator/internal/properties/Callable;
      81: invokeinterface #153,  1          // InterfaceMethod org/hibernate/validator/internal/properties/Callable.getDeclaringClass:()Ljava/lang/Class;
      86: aload         5
      88: aload_0
      89: getfield      #218                // Field constraintCreationContext:Lorg/hibernate/validator/internal/engine/ConstraintCreationContext;
      92: aload_0
      93: getfield      #41                 // Field parameterNameProvider:Lorg/hibernate/validator/internal/util/ExecutableParameterNameProvider;
      96: invokespecial #265                // Method org/hibernate/validator/internal/metadata/aggregated/ParameterMetaData$Builder."<init>":(Ljava/lang/Class;Lorg/hibernate/validator/internal/metadata/raw/ConstrainedParameter;Lorg/hibernate/validator/internal/engine/ConstraintCreationContext;Lorg/hibernate/validator/internal/util/ExecutableParameterNameProvider;)V
      99: invokeinterface #268,  2          // InterfaceMethod java/util/List.add:(Ljava/lang/Object;)Z
     104: pop
     105: goto          50
     108: goto          169
     111: iconst_0
     112: istore        4
     114: aload_3
     115: invokevirtual #255                // Method org/hibernate/validator/internal/metadata/raw/ConstrainedExecutable.getAllParameterMetaData:()Ljava/util/List;
     118: invokeinterface #258,  1          // InterfaceMethod java/util/List.iterator:()Ljava/util/Iterator;
     123: astore        5
     125: aload         5
     127: invokeinterface #242,  1          // InterfaceMethod java/util/Iterator.hasNext:()Z
     132: ifeq          169
     135: aload         5
     137: invokeinterface #247,  1          // InterfaceMethod java/util/Iterator.next:()Ljava/lang/Object;
     142: checkcast     #261                // class org/hibernate/validator/internal/metadata/raw/ConstrainedParameter
     145: astore        6
     147: aload_1
     148: iload         4
     150: invokeinterface #269,  2          // InterfaceMethod java/util/List.get:(I)Ljava/lang/Object;
     155: checkcast     #263                // class org/hibernate/validator/internal/metadata/aggregated/ParameterMetaData$Builder
     158: aload         6
     160: invokevirtual #272                // Method org/hibernate/validator/internal/metadata/aggregated/ParameterMetaData$Builder.add:(Lorg/hibernate/validator/internal/metadata/raw/ConstrainedElement;)V
     163: iinc          4, 1
     166: goto          125
     169: goto          12
     172: invokestatic  #251                // Method org/hibernate/validator/internal/util/CollectionHelper.newArrayList:()Ljava/util/ArrayList;
     175: astore_2
     176: aload_1
     177: invokeinterface #258,  1          // InterfaceMethod java/util/List.iterator:()Ljava/util/Iterator;
     182: astore_3
     183: aload_3
     184: invokeinterface #242,  1          // InterfaceMethod java/util/Iterator.hasNext:()Z
     189: ifeq          218
     192: aload_3
     193: invokeinterface #247,  1          // InterfaceMethod java/util/Iterator.next:()Ljava/lang/Object;
     198: checkcast     #263                // class org/hibernate/validator/internal/metadata/aggregated/ParameterMetaData$Builder
     201: astore        4
     203: aload_2
     204: aload         4
     206: invokevirtual #273                // Method org/hibernate/validator/internal/metadata/aggregated/ParameterMetaData$Builder.build:()Lorg/hibernate/validator/internal/metadata/aggregated/ParameterMetaData;
     209: invokeinterface #268,  2          // InterfaceMethod java/util/List.add:(Ljava/lang/Object;)Z
     214: pop
     215: goto          183
     218: aload_2
     219: areturn

  private void assertCorrectnessOfConfiguration();
    Code:
       0: aload_0
       1: getfield      #33                 // Field executablesByDeclaringType:Ljava/util/Map;
       4: invokeinterface #276,  1          // InterfaceMethod java/util/Map.entrySet:()Ljava/util/Set;
       9: invokeinterface #238,  1          // InterfaceMethod java/util/Set.iterator:()Ljava/util/Iterator;
      14: astore_1
      15: aload_1
      16: invokeinterface #242,  1          // InterfaceMethod java/util/Iterator.hasNext:()Z
      21: ifeq          135
      24: aload_1
      25: invokeinterface #247,  1          // InterfaceMethod java/util/Iterator.next:()Ljava/lang/Object;
      30: checkcast     #279                // class java/util/Map$Entry
      33: astore_2
      34: aload_0
      35: getfield      #33                 // Field executablesByDeclaringType:Ljava/util/Map;
      38: invokeinterface #276,  1          // InterfaceMethod java/util/Map.entrySet:()Ljava/util/Set;
      43: invokeinterface #238,  1          // InterfaceMethod java/util/Set.iterator:()Ljava/util/Iterator;
      48: astore_3
      49: aload_3
      50: invokeinterface #242,  1          // InterfaceMethod java/util/Iterator.hasNext:()Z
      55: ifeq          132
      58: aload_3
      59: invokeinterface #247,  1          // InterfaceMethod java/util/Iterator.next:()Ljava/lang/Object;
      64: checkcast     #279                // class java/util/Map$Entry
      67: astore        4
      69: aload_0
      70: getfield      #69                 // Field rules:Ljava/util/Set;
      73: invokeinterface #238,  1          // InterfaceMethod java/util/Set.iterator:()Ljava/util/Iterator;
      78: astore        5
      80: aload         5
      82: invokeinterface #242,  1          // InterfaceMethod java/util/Iterator.hasNext:()Z
      87: ifeq          129
      90: aload         5
      92: invokeinterface #247,  1          // InterfaceMethod java/util/Iterator.next:()Ljava/lang/Object;
      97: checkcast     #281                // class org/hibernate/validator/internal/metadata/aggregated/rule/MethodConfigurationRule
     100: astore        6
     102: aload         6
     104: aload_2
     105: invokeinterface #283,  1          // InterfaceMethod java/util/Map$Entry.getValue:()Ljava/lang/Object;
     110: checkcast     #46                 // class org/hibernate/validator/internal/metadata/raw/ConstrainedExecutable
     113: aload         4
     115: invokeinterface #283,  1          // InterfaceMethod java/util/Map$Entry.getValue:()Ljava/lang/Object;
     120: checkcast     #46                 // class org/hibernate/validator/internal/metadata/raw/ConstrainedExecutable
     123: invokevirtual #286                // Method org/hibernate/validator/internal/metadata/aggregated/rule/MethodConfigurationRule.apply:(Lorg/hibernate/validator/internal/metadata/raw/ConstrainedExecutable;Lorg/hibernate/validator/internal/metadata/raw/ConstrainedExecutable;)V
     126: goto          80
     129: goto          49
     132: goto          15
     135: return

  public org.hibernate.validator.internal.metadata.aggregated.ConstraintMetaData build();
    Code:
       0: aload_0
       1: invokevirtual #290                // Method build:()Lorg/hibernate/validator/internal/metadata/aggregated/ExecutableMetaData;
       4: areturn
}
