Compiled from "StreamRuleMatcherFactory.java"
public class org.graylog2.streams.StreamRuleMatcherFactory {
  public org.graylog2.streams.StreamRuleMatcherFactory();
    Code:
       0: aload_0
       1: invokespecial #1                  // Method java/lang/Object."<init>":()V
       4: return

  public static org.graylog2.streams.matchers.StreamRuleMatcher build(org.graylog2.plugin.streams.StreamRuleType) throws org.graylog2.streams.InvalidStreamRuleTypeException;
    Code:
       0: getstatic     #2                  // Field org/graylog2/streams/StreamRuleMatcherFactory$1.$SwitchMap$org$graylog2$plugin$streams$StreamRuleType:[I
       3: aload_0
       4: invokevirtual #3                  // Method org/graylog2/plugin/streams/StreamRuleType.ordinal:()I
       7: iaload
       8: tableswitch   { // 1 to 7
                     1: 52
                     2: 60
                     3: 68
                     4: 76
                     5: 84
                     6: 92
                     7: 100
               default: 108
          }
      52: new           #4                  // class org/graylog2/streams/matchers/ExactMatcher
      55: dup
      56: invokespecial #5                  // Method org/graylog2/streams/matchers/ExactMatcher."<init>":()V
      59: areturn
      60: new           #6                  // class org/graylog2/streams/matchers/RegexMatcher
      63: dup
      64: invokespecial #7                  // Method org/graylog2/streams/matchers/RegexMatcher."<init>":()V
      67: areturn
      68: new           #8                  // class org/graylog2/streams/matchers/GreaterMatcher
      71: dup
      72: invokespecial #9                  // Method org/graylog2/streams/matchers/GreaterMatcher."<init>":()V
      75: areturn
      76: new           #10                 // class org/graylog2/streams/matchers/SmallerMatcher
      79: dup
      80: invokespecial #11                 // Method org/graylog2/streams/matchers/SmallerMatcher."<init>":()V
      83: areturn
      84: new           #12                 // class org/graylog2/streams/matchers/FieldPresenceMatcher
      87: dup
      88: invokespecial #13                 // Method org/graylog2/streams/matchers/FieldPresenceMatcher."<init>":()V
      91: areturn
      92: new           #14                 // class org/graylog2/streams/matchers/ContainsMatcher
      95: dup
      96: invokespecial #15                 // Method org/graylog2/streams/matchers/ContainsMatcher."<init>":()V
      99: areturn
     100: new           #16                 // class org/graylog2/streams/matchers/AlwaysMatcher
     103: dup
     104: invokespecial #17                 // Method org/graylog2/streams/matchers/AlwaysMatcher."<init>":()V
     107: areturn
     108: new           #18                 // class org/graylog2/streams/InvalidStreamRuleTypeException
     111: dup
     112: invokespecial #19                 // Method org/graylog2/streams/InvalidStreamRuleTypeException."<init>":()V
     115: athrow
}
