Compiled from "StreamRuleServiceImpl.java"
public class org.graylog2.streams.StreamRuleServiceImpl extends org.graylog2.database.PersistedServiceImpl implements org.graylog2.streams.StreamRuleService {
  private final org.graylog2.events.ClusterEventBus clusterEventBus;

  public org.graylog2.streams.StreamRuleServiceImpl(org.graylog2.database.MongoConnection, org.graylog2.events.ClusterEventBus);
    Code:
       0: aload_0
       1: aload_1
       2: invokespecial #1                  // Method org/graylog2/database/PersistedServiceImpl."<init>":(Lorg/graylog2/database/MongoConnection;)V
       5: aload_0
       6: ldc           #2                  // class org/graylog2/streams/StreamRuleImpl
       8: invokevirtual #3                  // Method collection:(Ljava/lang/Class;)Lcom/mongodb/DBCollection;
      11: ldc           #4                  // String stream_id
      13: invokevirtual #5                  // Method com/mongodb/DBCollection.createIndex:(Ljava/lang/String;)V
      16: aload_0
      17: aload_2
      18: putfield      #6                  // Field clusterEventBus:Lorg/graylog2/events/ClusterEventBus;
      21: return

  public org.graylog2.plugin.streams.StreamRule load(java.lang.String) throws org.graylog2.database.NotFoundException;
    Code:
       0: aload_0
       1: ldc           #2                  // class org/graylog2/streams/StreamRuleImpl
       3: new           #7                  // class org/bson/types/ObjectId
       6: dup
       7: aload_1
       8: invokespecial #8                  // Method org/bson/types/ObjectId."<init>":(Ljava/lang/String;)V
      11: invokevirtual #9                  // Method get:(Ljava/lang/Class;Lorg/bson/types/ObjectId;)Lcom/mongodb/DBObject;
      14: checkcast     #10                 // class com/mongodb/BasicDBObject
      17: astore_2
      18: aload_2
      19: ifnonnull     49
      22: new           #11                 // class org/graylog2/database/NotFoundException
      25: dup
      26: new           #12                 // class java/lang/StringBuilder
      29: dup
      30: invokespecial #13                 // Method java/lang/StringBuilder."<init>":()V
      33: ldc           #14                 // String Couldn\'t find stream rule with ID
      35: invokevirtual #15                 // Method java/lang/StringBuilder.append:(Ljava/lang/String;)Ljava/lang/StringBuilder;
      38: aload_1
      39: invokevirtual #15                 // Method java/lang/StringBuilder.append:(Ljava/lang/String;)Ljava/lang/StringBuilder;
      42: invokevirtual #16                 // Method java/lang/StringBuilder.toString:()Ljava/lang/String;
      45: invokespecial #17                 // Method org/graylog2/database/NotFoundException."<init>":(Ljava/lang/String;)V
      48: athrow
      49: new           #2                  // class org/graylog2/streams/StreamRuleImpl
      52: dup
      53: aload_2
      54: ldc           #18                 // String _id
      56: invokevirtual #19                 // Method com/mongodb/BasicDBObject.get:(Ljava/lang/String;)Ljava/lang/Object;
      59: checkcast     #7                  // class org/bson/types/ObjectId
      62: aload_2
      63: invokevirtual #20                 // Method com/mongodb/BasicDBObject.toMap:()Ljava/util/Map;
      66: invokespecial #21                 // Method org/graylog2/streams/StreamRuleImpl."<init>":(Lorg/bson/types/ObjectId;Ljava/util/Map;)V
      69: areturn

  public java.util.List<org.graylog2.plugin.streams.StreamRule> loadForStream(org.graylog2.plugin.streams.Stream);
    Code:
       0: aload_0
       1: aload_1
       2: invokeinterface #22,  1           // InterfaceMethod org/graylog2/plugin/streams/Stream.getId:()Ljava/lang/String;
       7: invokevirtual #23                 // Method loadForStreamId:(Ljava/lang/String;)Ljava/util/List;
      10: areturn

  public org.graylog2.plugin.streams.StreamRule create(java.util.Map<java.lang.String, java.lang.Object>);
    Code:
       0: new           #2                  // class org/graylog2/streams/StreamRuleImpl
       3: dup
       4: aload_1
       5: invokespecial #24                 // Method org/graylog2/streams/StreamRuleImpl."<init>":(Ljava/util/Map;)V
       8: areturn

  public org.graylog2.plugin.streams.StreamRule create(java.lang.String, org.graylog2.rest.resources.streams.rules.requests.CreateStreamRuleRequest);
    Code:
       0: invokestatic  #25                 // Method com/google/common/collect/Maps.newHashMap:()Ljava/util/HashMap;
       3: astore_3
       4: aload_3
       5: ldc           #26                 // String type
       7: aload_2
       8: invokevirtual #27                 // Method org/graylog2/rest/resources/streams/rules/requests/CreateStreamRuleRequest.type:()I
      11: invokestatic  #28                 // Method java/lang/Integer.valueOf:(I)Ljava/lang/Integer;
      14: invokeinterface #29,  3           // InterfaceMethod java/util/Map.put:(Ljava/lang/Object;Ljava/lang/Object;)Ljava/lang/Object;
      19: pop
      20: aload_3
      21: ldc           #30                 // String value
      23: aload_2
      24: invokevirtual #31                 // Method org/graylog2/rest/resources/streams/rules/requests/CreateStreamRuleRequest.value:()Ljava/lang/String;
      27: invokeinterface #29,  3           // InterfaceMethod java/util/Map.put:(Ljava/lang/Object;Ljava/lang/Object;)Ljava/lang/Object;
      32: pop
      33: aload_3
      34: ldc           #32                 // String field
      36: aload_2
      37: invokevirtual #33                 // Method org/graylog2/rest/resources/streams/rules/requests/CreateStreamRuleRequest.field:()Ljava/lang/String;
      40: invokeinterface #29,  3           // InterfaceMethod java/util/Map.put:(Ljava/lang/Object;Ljava/lang/Object;)Ljava/lang/Object;
      45: pop
      46: aload_3
      47: ldc           #34                 // String inverted
      49: aload_2
      50: invokevirtual #35                 // Method org/graylog2/rest/resources/streams/rules/requests/CreateStreamRuleRequest.inverted:()Z
      53: invokestatic  #36                 // Method java/lang/Boolean.valueOf:(Z)Ljava/lang/Boolean;
      56: invokeinterface #29,  3           // InterfaceMethod java/util/Map.put:(Ljava/lang/Object;Ljava/lang/Object;)Ljava/lang/Object;
      61: pop
      62: aload_3
      63: ldc           #37                 // String description
      65: aload_2
      66: invokevirtual #38                 // Method org/graylog2/rest/resources/streams/rules/requests/CreateStreamRuleRequest.description:()Ljava/lang/String;
      69: invokeinterface #29,  3           // InterfaceMethod java/util/Map.put:(Ljava/lang/Object;Ljava/lang/Object;)Ljava/lang/Object;
      74: pop
      75: aload_1
      76: ifnull        96
      79: aload_3
      80: ldc           #4                  // String stream_id
      82: new           #7                  // class org/bson/types/ObjectId
      85: dup
      86: aload_1
      87: invokespecial #8                  // Method org/bson/types/ObjectId."<init>":(Ljava/lang/String;)V
      90: invokeinterface #29,  3           // InterfaceMethod java/util/Map.put:(Ljava/lang/Object;Ljava/lang/Object;)Ljava/lang/Object;
      95: pop
      96: new           #2                  // class org/graylog2/streams/StreamRuleImpl
      99: dup
     100: aload_3
     101: invokespecial #24                 // Method org/graylog2/streams/StreamRuleImpl."<init>":(Ljava/util/Map;)V
     104: areturn

  public org.graylog2.plugin.streams.StreamRule copy(java.lang.String, org.graylog2.plugin.streams.StreamRule);
    Code:
       0: invokestatic  #25                 // Method com/google/common/collect/Maps.newHashMap:()Ljava/util/HashMap;
       3: astore_3
       4: aload_3
       5: ldc           #26                 // String type
       7: aload_2
       8: invokeinterface #39,  1           // InterfaceMethod org/graylog2/plugin/streams/StreamRule.getType:()Lorg/graylog2/plugin/streams/StreamRuleType;
      13: invokevirtual #40                 // Method org/graylog2/plugin/streams/StreamRuleType.toInteger:()I
      16: invokestatic  #28                 // Method java/lang/Integer.valueOf:(I)Ljava/lang/Integer;
      19: invokeinterface #29,  3           // InterfaceMethod java/util/Map.put:(Ljava/lang/Object;Ljava/lang/Object;)Ljava/lang/Object;
      24: pop
      25: aload_3
      26: ldc           #30                 // String value
      28: aload_2
      29: invokeinterface #41,  1           // InterfaceMethod org/graylog2/plugin/streams/StreamRule.getValue:()Ljava/lang/String;
      34: invokeinterface #29,  3           // InterfaceMethod java/util/Map.put:(Ljava/lang/Object;Ljava/lang/Object;)Ljava/lang/Object;
      39: pop
      40: aload_3
      41: ldc           #32                 // String field
      43: aload_2
      44: invokeinterface #42,  1           // InterfaceMethod org/graylog2/plugin/streams/StreamRule.getField:()Ljava/lang/String;
      49: invokeinterface #29,  3           // InterfaceMethod java/util/Map.put:(Ljava/lang/Object;Ljava/lang/Object;)Ljava/lang/Object;
      54: pop
      55: aload_3
      56: ldc           #34                 // String inverted
      58: aload_2
      59: invokeinterface #43,  1           // InterfaceMethod org/graylog2/plugin/streams/StreamRule.getInverted:()Ljava/lang/Boolean;
      64: invokeinterface #29,  3           // InterfaceMethod java/util/Map.put:(Ljava/lang/Object;Ljava/lang/Object;)Ljava/lang/Object;
      69: pop
      70: aload_3
      71: ldc           #37                 // String description
      73: aload_2
      74: invokeinterface #44,  1           // InterfaceMethod org/graylog2/plugin/streams/StreamRule.getDescription:()Ljava/lang/String;
      79: invokeinterface #29,  3           // InterfaceMethod java/util/Map.put:(Ljava/lang/Object;Ljava/lang/Object;)Ljava/lang/Object;
      84: pop
      85: aload_1
      86: ifnull        106
      89: aload_3
      90: ldc           #4                  // String stream_id
      92: new           #7                  // class org/bson/types/ObjectId
      95: dup
      96: aload_1
      97: invokespecial #8                  // Method org/bson/types/ObjectId."<init>":(Ljava/lang/String;)V
     100: invokeinterface #29,  3           // InterfaceMethod java/util/Map.put:(Ljava/lang/Object;Ljava/lang/Object;)Ljava/lang/Object;
     105: pop
     106: new           #2                  // class org/graylog2/streams/StreamRuleImpl
     109: dup
     110: aload_3
     111: invokespecial #24                 // Method org/graylog2/streams/StreamRuleImpl."<init>":(Ljava/util/Map;)V
     114: areturn

  public java.lang.String save(org.graylog2.plugin.streams.StreamRule) throws org.graylog2.plugin.database.ValidationException;
    Code:
       0: aload_1
       1: invokeinterface #45,  1           // InterfaceMethod org/graylog2/plugin/streams/StreamRule.getStreamId:()Ljava/lang/String;
       6: astore_2
       7: aload_0
       8: aload_1
       9: invokespecial #46                 // Method org/graylog2/database/PersistedServiceImpl.save:(Lorg/graylog2/plugin/database/Persisted;)Ljava/lang/String;
      12: astore_3
      13: aload_0
      14: getfield      #6                  // Field clusterEventBus:Lorg/graylog2/events/ClusterEventBus;
      17: aload_2
      18: invokestatic  #47                 // Method org/graylog2/streams/events/StreamsChangedEvent.create:(Ljava/lang/String;)Lorg/graylog2/streams/events/StreamsChangedEvent;
      21: invokevirtual #48                 // Method org/graylog2/events/ClusterEventBus.post:(Ljava/lang/Object;)V
      24: aload_3
      25: areturn

  public java.util.Set<java.lang.String> save(java.util.Collection<org.graylog2.plugin.streams.StreamRule>) throws org.graylog2.plugin.database.ValidationException;
    Code:
       0: invokestatic  #49                 // Method com/google/common/collect/ImmutableSet.builder:()Lcom/google/common/collect/ImmutableSet$Builder;
       3: astore_2
       4: invokestatic  #49                 // Method com/google/common/collect/ImmutableSet.builder:()Lcom/google/common/collect/ImmutableSet$Builder;
       7: astore_3
       8: aload_1
       9: invokeinterface #50,  1           // InterfaceMethod java/util/Collection.iterator:()Ljava/util/Iterator;
      14: astore        4
      16: aload         4
      18: invokeinterface #51,  1           // InterfaceMethod java/util/Iterator.hasNext:()Z
      23: ifeq          72
      26: aload         4
      28: invokeinterface #52,  1           // InterfaceMethod java/util/Iterator.next:()Ljava/lang/Object;
      33: checkcast     #53                 // class org/graylog2/plugin/streams/StreamRule
      36: astore        5
      38: aload         5
      40: invokeinterface #45,  1           // InterfaceMethod org/graylog2/plugin/streams/StreamRule.getStreamId:()Ljava/lang/String;
      45: astore        6
      47: aload_0
      48: aload         5
      50: invokespecial #46                 // Method org/graylog2/database/PersistedServiceImpl.save:(Lorg/graylog2/plugin/database/Persisted;)Ljava/lang/String;
      53: astore        7
      55: aload_2
      56: aload         6
      58: invokevirtual #54                 // Method com/google/common/collect/ImmutableSet$Builder.add:(Ljava/lang/Object;)Lcom/google/common/collect/ImmutableSet$Builder;
      61: pop
      62: aload_3
      63: aload         7
      65: invokevirtual #54                 // Method com/google/common/collect/ImmutableSet$Builder.add:(Ljava/lang/Object;)Lcom/google/common/collect/ImmutableSet$Builder;
      68: pop
      69: goto          16
      72: aload_0
      73: getfield      #6                  // Field clusterEventBus:Lorg/graylog2/events/ClusterEventBus;
      76: aload_2
      77: invokevirtual #55                 // Method com/google/common/collect/ImmutableSet$Builder.build:()Lcom/google/common/collect/ImmutableSet;
      80: invokestatic  #56                 // Method org/graylog2/streams/events/StreamsChangedEvent.create:(Lcom/google/common/collect/ImmutableSet;)Lorg/graylog2/streams/events/StreamsChangedEvent;
      83: invokevirtual #48                 // Method org/graylog2/events/ClusterEventBus.post:(Ljava/lang/Object;)V
      86: aload_3
      87: invokevirtual #55                 // Method com/google/common/collect/ImmutableSet$Builder.build:()Lcom/google/common/collect/ImmutableSet;
      90: areturn

  public int destroy(org.graylog2.plugin.streams.StreamRule);
    Code:
       0: aload_1
       1: invokeinterface #45,  1           // InterfaceMethod org/graylog2/plugin/streams/StreamRule.getStreamId:()Ljava/lang/String;
       6: astore_2
       7: aload_0
       8: aload_1
       9: invokespecial #57                 // Method org/graylog2/database/PersistedServiceImpl.destroy:(Lorg/graylog2/plugin/database/Persisted;)I
      12: istore_3
      13: aload_0
      14: getfield      #6                  // Field clusterEventBus:Lorg/graylog2/events/ClusterEventBus;
      17: aload_2
      18: invokestatic  #47                 // Method org/graylog2/streams/events/StreamsChangedEvent.create:(Ljava/lang/String;)Lorg/graylog2/streams/events/StreamsChangedEvent;
      21: invokevirtual #48                 // Method org/graylog2/events/ClusterEventBus.post:(Ljava/lang/Object;)V
      24: iload_3
      25: ireturn

  public java.util.List<org.graylog2.plugin.streams.StreamRule> loadForStreamId(java.lang.String);
    Code:
       0: new           #7                  // class org/bson/types/ObjectId
       3: dup
       4: aload_1
       5: invokespecial #8                  // Method org/bson/types/ObjectId."<init>":(Ljava/lang/String;)V
       8: astore_2
       9: new           #58                 // class java/util/ArrayList
      12: dup
      13: invokespecial #59                 // Method java/util/ArrayList."<init>":()V
      16: astore_3
      17: aload_0
      18: ldc           #2                  // class org/graylog2/streams/StreamRuleImpl
      20: new           #10                 // class com/mongodb/BasicDBObject
      23: dup
      24: ldc           #4                  // String stream_id
      26: aload_2
      27: invokespecial #60                 // Method com/mongodb/BasicDBObject."<init>":(Ljava/lang/String;Ljava/lang/Object;)V
      30: invokevirtual #61                 // Method query:(Ljava/lang/Class;Lcom/mongodb/DBObject;)Ljava/util/List;
      33: astore        4
      35: aload         4
      37: invokeinterface #62,  1           // InterfaceMethod java/util/List.iterator:()Ljava/util/Iterator;
      42: astore        5
      44: aload         5
      46: invokeinterface #51,  1           // InterfaceMethod java/util/Iterator.hasNext:()Z
      51: ifeq          82
      54: aload         5
      56: invokeinterface #52,  1           // InterfaceMethod java/util/Iterator.next:()Ljava/lang/Object;
      61: checkcast     #63                 // class com/mongodb/DBObject
      64: astore        6
      66: aload_3
      67: aload_0
      68: aload         6
      70: invokespecial #64                 // Method toStreamRule:(Lcom/mongodb/DBObject;)Lorg/graylog2/plugin/streams/StreamRule;
      73: invokeinterface #65,  2           // InterfaceMethod java/util/List.add:(Ljava/lang/Object;)Z
      78: pop
      79: goto          44
      82: aload_3
      83: areturn

  public java.util.Map<java.lang.String, java.util.List<org.graylog2.plugin.streams.StreamRule>> loadForStreamIds(java.util.Collection<java.lang.String>);
    Code:
       0: aload_1
       1: invokeinterface #66,  1           // InterfaceMethod java/util/Collection.stream:()Ljava/util/stream/Stream;
       6: invokedynamic #67,  0             // InvokeDynamic #0:apply:()Ljava/util/function/Function;
      11: invokeinterface #68,  2           // InterfaceMethod java/util/stream/Stream.map:(Ljava/util/function/Function;)Ljava/util/stream/Stream;
      16: invokestatic  #69                 // Method java/util/stream/Collectors.toList:()Ljava/util/stream/Collector;
      19: invokeinterface #70,  2           // InterfaceMethod java/util/stream/Stream.collect:(Ljava/util/stream/Collector;)Ljava/lang/Object;
      24: checkcast     #71                 // class java/util/List
      27: astore_2
      28: aload_0
      29: ldc           #2                  // class org/graylog2/streams/StreamRuleImpl
      31: new           #10                 // class com/mongodb/BasicDBObject
      34: dup
      35: ldc           #4                  // String stream_id
      37: new           #10                 // class com/mongodb/BasicDBObject
      40: dup
      41: ldc           #72                 // String $in
      43: aload_2
      44: invokespecial #60                 // Method com/mongodb/BasicDBObject."<init>":(Ljava/lang/String;Ljava/lang/Object;)V
      47: invokespecial #60                 // Method com/mongodb/BasicDBObject."<init>":(Ljava/lang/String;Ljava/lang/Object;)V
      50: invokevirtual #61                 // Method query:(Ljava/lang/Class;Lcom/mongodb/DBObject;)Ljava/util/List;
      53: astore_3
      54: aload_3
      55: invokeinterface #73,  1           // InterfaceMethod java/util/List.stream:()Ljava/util/stream/Stream;
      60: aload_0
      61: invokedynamic #74,  0             // InvokeDynamic #1:apply:(Lorg/graylog2/streams/StreamRuleServiceImpl;)Ljava/util/function/Function;
      66: invokeinterface #68,  2           // InterfaceMethod java/util/stream/Stream.map:(Ljava/util/function/Function;)Ljava/util/stream/Stream;
      71: invokedynamic #75,  0             // InvokeDynamic #2:apply:()Ljava/util/function/Function;
      76: invokestatic  #76                 // Method java/util/stream/Collectors.groupingBy:(Ljava/util/function/Function;)Ljava/util/stream/Collector;
      79: invokeinterface #70,  2           // InterfaceMethod java/util/stream/Stream.collect:(Ljava/util/stream/Collector;)Ljava/lang/Object;
      84: checkcast     #77                 // class java/util/Map
      87: areturn

  public long totalStreamRuleCount();
    Code:
       0: aload_0
       1: ldc           #2                  // class org/graylog2/streams/StreamRuleImpl
       3: invokevirtual #78                 // Method totalCount:(Ljava/lang/Class;)J
       6: lreturn

  public long streamRuleCount(java.lang.String);
    Code:
       0: aload_0
       1: new           #7                  // class org/bson/types/ObjectId
       4: dup
       5: aload_1
       6: invokespecial #8                  // Method org/bson/types/ObjectId."<init>":(Ljava/lang/String;)V
       9: invokespecial #79                 // Method streamRuleCount:(Lorg/bson/types/ObjectId;)J
      12: lreturn

  private long streamRuleCount(org.bson.types.ObjectId);
    Code:
       0: aload_0
       1: ldc           #2                  // class org/graylog2/streams/StreamRuleImpl
       3: new           #10                 // class com/mongodb/BasicDBObject
       6: dup
       7: ldc           #4                  // String stream_id
       9: aload_1
      10: invokespecial #60                 // Method com/mongodb/BasicDBObject."<init>":(Ljava/lang/String;Ljava/lang/Object;)V
      13: invokevirtual #80                 // Method count:(Ljava/lang/Class;Lcom/mongodb/DBObject;)J
      16: lreturn

  public java.util.Map<java.lang.String, java.lang.Long> streamRuleCountByStream();
    Code:
       0: invokestatic  #81                 // Method com/google/common/collect/ImmutableMap.builder:()Lcom/google/common/collect/ImmutableMap$Builder;
       3: astore_1
       4: aload_0
       5: ldc           #82                 // class org/graylog2/streams/StreamImpl
       7: invokevirtual #3                  // Method collection:(Ljava/lang/Class;)Lcom/mongodb/DBCollection;
      10: new           #10                 // class com/mongodb/BasicDBObject
      13: dup
      14: invokespecial #83                 // Method com/mongodb/BasicDBObject."<init>":()V
      17: new           #10                 // class com/mongodb/BasicDBObject
      20: dup
      21: ldc           #18                 // String _id
      23: iconst_1
      24: invokestatic  #28                 // Method java/lang/Integer.valueOf:(I)Ljava/lang/Integer;
      27: invokespecial #60                 // Method com/mongodb/BasicDBObject."<init>":(Ljava/lang/String;Ljava/lang/Object;)V
      30: invokevirtual #84                 // Method com/mongodb/DBCollection.find:(Lcom/mongodb/DBObject;Lcom/mongodb/DBObject;)Lcom/mongodb/DBCursor;
      33: astore_2
      34: aconst_null
      35: astore_3
      36: aload_2
      37: invokevirtual #85                 // Method com/mongodb/DBCursor.iterator:()Ljava/util/Iterator;
      40: astore        4
      42: aload         4
      44: invokeinterface #51,  1           // InterfaceMethod java/util/Iterator.hasNext:()Z
      49: ifeq          100
      52: aload         4
      54: invokeinterface #52,  1           // InterfaceMethod java/util/Iterator.next:()Ljava/lang/Object;
      59: checkcast     #63                 // class com/mongodb/DBObject
      62: astore        5
      64: aload         5
      66: ldc           #18                 // String _id
      68: invokeinterface #86,  2           // InterfaceMethod com/mongodb/DBObject.get:(Ljava/lang/String;)Ljava/lang/Object;
      73: checkcast     #7                  // class org/bson/types/ObjectId
      76: astore        6
      78: aload_1
      79: aload         6
      81: invokevirtual #87                 // Method org/bson/types/ObjectId.toHexString:()Ljava/lang/String;
      84: aload_0
      85: aload         6
      87: invokespecial #79                 // Method streamRuleCount:(Lorg/bson/types/ObjectId;)J
      90: invokestatic  #88                 // Method java/lang/Long.valueOf:(J)Ljava/lang/Long;
      93: invokevirtual #89                 // Method com/google/common/collect/ImmutableMap$Builder.put:(Ljava/lang/Object;Ljava/lang/Object;)Lcom/google/common/collect/ImmutableMap$Builder;
      96: pop
      97: goto          42
     100: aload_2
     101: ifnull        176
     104: aload_3
     105: ifnull        126
     108: aload_2
     109: invokevirtual #90                 // Method com/mongodb/DBCursor.close:()V
     112: goto          176
     115: astore        4
     117: aload_3
     118: aload         4
     120: invokevirtual #92                 // Method java/lang/Throwable.addSuppressed:(Ljava/lang/Throwable;)V
     123: goto          176
     126: aload_2
     127: invokevirtual #90                 // Method com/mongodb/DBCursor.close:()V
     130: goto          176
     133: astore        4
     135: aload         4
     137: astore_3
     138: aload         4
     140: athrow
     141: astore        7
     143: aload_2
     144: ifnull        173
     147: aload_3
     148: ifnull        169
     151: aload_2
     152: invokevirtual #90                 // Method com/mongodb/DBCursor.close:()V
     155: goto          173
     158: astore        8
     160: aload_3
     161: aload         8
     163: invokevirtual #92                 // Method java/lang/Throwable.addSuppressed:(Ljava/lang/Throwable;)V
     166: goto          173
     169: aload_2
     170: invokevirtual #90                 // Method com/mongodb/DBCursor.close:()V
     173: aload         7
     175: athrow
     176: aload_1
     177: invokevirtual #93                 // Method com/google/common/collect/ImmutableMap$Builder.build:()Lcom/google/common/collect/ImmutableMap;
     180: areturn
    Exception table:
       from    to  target type
         108   112   115   Class java/lang/Throwable
          36   100   133   Class java/lang/Throwable
          36   100   141   any
         151   155   158   Class java/lang/Throwable
         133   143   141   any

  private org.graylog2.plugin.streams.StreamRule toStreamRule(com.mongodb.DBObject);
    Code:
       0: aload_1
       1: invokeinterface #94,  1           // InterfaceMethod com/mongodb/DBObject.toMap:()Ljava/util/Map;
       6: astore_2
       7: new           #2                  // class org/graylog2/streams/StreamRuleImpl
      10: dup
      11: aload_1
      12: ldc           #18                 // String _id
      14: invokeinterface #86,  2           // InterfaceMethod com/mongodb/DBObject.get:(Ljava/lang/String;)Ljava/lang/Object;
      19: checkcast     #7                  // class org/bson/types/ObjectId
      22: aload_2
      23: invokespecial #21                 // Method org/graylog2/streams/StreamRuleImpl."<init>":(Lorg/bson/types/ObjectId;Ljava/util/Map;)V
      26: areturn
}
