Compiled from "DefaultTransactionDefinition.java"
public class org.springframework.transaction.support.DefaultTransactionDefinition implements org.springframework.transaction.TransactionDefinition,java.io.Serializable {
  public static final java.lang.String PREFIX_PROPAGATION;

  public static final java.lang.String PREFIX_ISOLATION;

  public static final java.lang.String PREFIX_TIMEOUT;

  public static final java.lang.String READ_ONLY_MARKER;

  static final org.springframework.core.Constants constants;

  private int propagationBehavior;

  private int isolationLevel;

  private int timeout;

  private boolean readOnly;

  private java.lang.String name;

  public org.springframework.transaction.support.DefaultTransactionDefinition();
    Code:
       0: aload_0
       1: invokespecial #1                  // Method java/lang/Object."<init>":()V
       4: aload_0
       5: iconst_0
       6: putfield      #3                  // Field propagationBehavior:I
       9: aload_0
      10: iconst_m1
      11: putfield      #4                  // Field isolationLevel:I
      14: aload_0
      15: iconst_m1
      16: putfield      #5                  // Field timeout:I
      19: aload_0
      20: iconst_0
      21: putfield      #6                  // Field readOnly:Z
      24: return

  public org.springframework.transaction.support.DefaultTransactionDefinition(org.springframework.transaction.TransactionDefinition);
    Code:
       0: aload_0
       1: invokespecial #1                  // Method java/lang/Object."<init>":()V
       4: aload_0
       5: iconst_0
       6: putfield      #3                  // Field propagationBehavior:I
       9: aload_0
      10: iconst_m1
      11: putfield      #4                  // Field isolationLevel:I
      14: aload_0
      15: iconst_m1
      16: putfield      #5                  // Field timeout:I
      19: aload_0
      20: iconst_0
      21: putfield      #6                  // Field readOnly:Z
      24: aload_0
      25: aload_1
      26: invokeinterface #7,  1            // InterfaceMethod org/springframework/transaction/TransactionDefinition.getPropagationBehavior:()I
      31: putfield      #3                  // Field propagationBehavior:I
      34: aload_0
      35: aload_1
      36: invokeinterface #8,  1            // InterfaceMethod org/springframework/transaction/TransactionDefinition.getIsolationLevel:()I
      41: putfield      #4                  // Field isolationLevel:I
      44: aload_0
      45: aload_1
      46: invokeinterface #9,  1            // InterfaceMethod org/springframework/transaction/TransactionDefinition.getTimeout:()I
      51: putfield      #5                  // Field timeout:I
      54: aload_0
      55: aload_1
      56: invokeinterface #10,  1           // InterfaceMethod org/springframework/transaction/TransactionDefinition.isReadOnly:()Z
      61: putfield      #6                  // Field readOnly:Z
      64: aload_0
      65: aload_1
      66: invokeinterface #11,  1           // InterfaceMethod org/springframework/transaction/TransactionDefinition.getName:()Ljava/lang/String;
      71: putfield      #12                 // Field name:Ljava/lang/String;
      74: return

  public org.springframework.transaction.support.DefaultTransactionDefinition(int);
    Code:
       0: aload_0
       1: invokespecial #1                  // Method java/lang/Object."<init>":()V
       4: aload_0
       5: iconst_0
       6: putfield      #3                  // Field propagationBehavior:I
       9: aload_0
      10: iconst_m1
      11: putfield      #4                  // Field isolationLevel:I
      14: aload_0
      15: iconst_m1
      16: putfield      #5                  // Field timeout:I
      19: aload_0
      20: iconst_0
      21: putfield      #6                  // Field readOnly:Z
      24: aload_0
      25: iload_1
      26: putfield      #3                  // Field propagationBehavior:I
      29: return

  public final void setPropagationBehaviorName(java.lang.String) throws java.lang.IllegalArgumentException;
    Code:
       0: aload_1
       1: ldc           #14                 // String PROPAGATION_
       3: invokevirtual #15                 // Method java/lang/String.startsWith:(Ljava/lang/String;)Z
       6: ifne          19
       9: new           #16                 // class java/lang/IllegalArgumentException
      12: dup
      13: ldc           #17                 // String Only propagation constants allowed
      15: invokespecial #18                 // Method java/lang/IllegalArgumentException."<init>":(Ljava/lang/String;)V
      18: athrow
      19: aload_0
      20: getstatic     #19                 // Field constants:Lorg/springframework/core/Constants;
      23: aload_1
      24: invokevirtual #20                 // Method org/springframework/core/Constants.asNumber:(Ljava/lang/String;)Ljava/lang/Number;
      27: invokevirtual #21                 // Method java/lang/Number.intValue:()I
      30: invokevirtual #22                 // Method setPropagationBehavior:(I)V
      33: return

  public final void setPropagationBehavior(int);
    Code:
       0: getstatic     #19                 // Field constants:Lorg/springframework/core/Constants;
       3: ldc           #14                 // String PROPAGATION_
       5: invokevirtual #23                 // Method org/springframework/core/Constants.getValues:(Ljava/lang/String;)Ljava/util/Set;
       8: iload_1
       9: invokestatic  #24                 // Method java/lang/Integer.valueOf:(I)Ljava/lang/Integer;
      12: invokeinterface #25,  2           // InterfaceMethod java/util/Set.contains:(Ljava/lang/Object;)Z
      17: ifne          30
      20: new           #16                 // class java/lang/IllegalArgumentException
      23: dup
      24: ldc           #26                 // String Only values of propagation constants allowed
      26: invokespecial #18                 // Method java/lang/IllegalArgumentException."<init>":(Ljava/lang/String;)V
      29: athrow
      30: aload_0
      31: iload_1
      32: putfield      #3                  // Field propagationBehavior:I
      35: return

  public final int getPropagationBehavior();
    Code:
       0: aload_0
       1: getfield      #3                  // Field propagationBehavior:I
       4: ireturn

  public final void setIsolationLevelName(java.lang.String) throws java.lang.IllegalArgumentException;
    Code:
       0: aload_1
       1: ldc           #27                 // String ISOLATION_
       3: invokevirtual #15                 // Method java/lang/String.startsWith:(Ljava/lang/String;)Z
       6: ifne          19
       9: new           #16                 // class java/lang/IllegalArgumentException
      12: dup
      13: ldc           #28                 // String Only isolation constants allowed
      15: invokespecial #18                 // Method java/lang/IllegalArgumentException."<init>":(Ljava/lang/String;)V
      18: athrow
      19: aload_0
      20: getstatic     #19                 // Field constants:Lorg/springframework/core/Constants;
      23: aload_1
      24: invokevirtual #20                 // Method org/springframework/core/Constants.asNumber:(Ljava/lang/String;)Ljava/lang/Number;
      27: invokevirtual #21                 // Method java/lang/Number.intValue:()I
      30: invokevirtual #29                 // Method setIsolationLevel:(I)V
      33: return

  public final void setIsolationLevel(int);
    Code:
       0: getstatic     #19                 // Field constants:Lorg/springframework/core/Constants;
       3: ldc           #27                 // String ISOLATION_
       5: invokevirtual #23                 // Method org/springframework/core/Constants.getValues:(Ljava/lang/String;)Ljava/util/Set;
       8: iload_1
       9: invokestatic  #24                 // Method java/lang/Integer.valueOf:(I)Ljava/lang/Integer;
      12: invokeinterface #25,  2           // InterfaceMethod java/util/Set.contains:(Ljava/lang/Object;)Z
      17: ifne          30
      20: new           #16                 // class java/lang/IllegalArgumentException
      23: dup
      24: ldc           #30                 // String Only values of isolation constants allowed
      26: invokespecial #18                 // Method java/lang/IllegalArgumentException."<init>":(Ljava/lang/String;)V
      29: athrow
      30: aload_0
      31: iload_1
      32: putfield      #4                  // Field isolationLevel:I
      35: return

  public final int getIsolationLevel();
    Code:
       0: aload_0
       1: getfield      #4                  // Field isolationLevel:I
       4: ireturn

  public final void setTimeout(int);
    Code:
       0: iload_1
       1: iconst_m1
       2: if_icmpge     15
       5: new           #16                 // class java/lang/IllegalArgumentException
       8: dup
       9: ldc           #31                 // String Timeout must be a positive integer or TIMEOUT_DEFAULT
      11: invokespecial #18                 // Method java/lang/IllegalArgumentException."<init>":(Ljava/lang/String;)V
      14: athrow
      15: aload_0
      16: iload_1
      17: putfield      #5                  // Field timeout:I
      20: return

  public final int getTimeout();
    Code:
       0: aload_0
       1: getfield      #5                  // Field timeout:I
       4: ireturn

  public final void setReadOnly(boolean);
    Code:
       0: aload_0
       1: iload_1
       2: putfield      #6                  // Field readOnly:Z
       5: return

  public final boolean isReadOnly();
    Code:
       0: aload_0
       1: getfield      #6                  // Field readOnly:Z
       4: ireturn

  public final void setName(java.lang.String);
    Code:
       0: aload_0
       1: aload_1
       2: putfield      #12                 // Field name:Ljava/lang/String;
       5: return

  public final java.lang.String getName();
    Code:
       0: aload_0
       1: getfield      #12                 // Field name:Ljava/lang/String;
       4: areturn

  public boolean equals(java.lang.Object);
    Code:
       0: aload_0
       1: aload_1
       2: if_acmpeq     26
       5: aload_1
       6: instanceof    #2                  // class org/springframework/transaction/TransactionDefinition
       9: ifeq          30
      12: aload_0
      13: invokevirtual #32                 // Method toString:()Ljava/lang/String;
      16: aload_1
      17: invokevirtual #33                 // Method java/lang/Object.toString:()Ljava/lang/String;
      20: invokevirtual #34                 // Method java/lang/String.equals:(Ljava/lang/Object;)Z
      23: ifeq          30
      26: iconst_1
      27: goto          31
      30: iconst_0
      31: ireturn

  public int hashCode();
    Code:
       0: aload_0
       1: invokevirtual #32                 // Method toString:()Ljava/lang/String;
       4: invokevirtual #35                 // Method java/lang/String.hashCode:()I
       7: ireturn

  public java.lang.String toString();
    Code:
       0: aload_0
       1: invokevirtual #36                 // Method getDefinitionDescription:()Ljava/lang/StringBuilder;
       4: invokevirtual #37                 // Method java/lang/StringBuilder.toString:()Ljava/lang/String;
       7: areturn

  protected final java.lang.StringBuilder getDefinitionDescription();
    Code:
       0: new           #38                 // class java/lang/StringBuilder
       3: dup
       4: invokespecial #39                 // Method java/lang/StringBuilder."<init>":()V
       7: astore_1
       8: aload_1
       9: getstatic     #19                 // Field constants:Lorg/springframework/core/Constants;
      12: aload_0
      13: getfield      #3                  // Field propagationBehavior:I
      16: invokestatic  #24                 // Method java/lang/Integer.valueOf:(I)Ljava/lang/Integer;
      19: ldc           #14                 // String PROPAGATION_
      21: invokevirtual #40                 // Method org/springframework/core/Constants.toCode:(Ljava/lang/Object;Ljava/lang/String;)Ljava/lang/String;
      24: invokevirtual #41                 // Method java/lang/StringBuilder.append:(Ljava/lang/String;)Ljava/lang/StringBuilder;
      27: pop
      28: aload_1
      29: bipush        44
      31: invokevirtual #42                 // Method java/lang/StringBuilder.append:(C)Ljava/lang/StringBuilder;
      34: pop
      35: aload_1
      36: getstatic     #19                 // Field constants:Lorg/springframework/core/Constants;
      39: aload_0
      40: getfield      #4                  // Field isolationLevel:I
      43: invokestatic  #24                 // Method java/lang/Integer.valueOf:(I)Ljava/lang/Integer;
      46: ldc           #27                 // String ISOLATION_
      48: invokevirtual #40                 // Method org/springframework/core/Constants.toCode:(Ljava/lang/Object;Ljava/lang/String;)Ljava/lang/String;
      51: invokevirtual #41                 // Method java/lang/StringBuilder.append:(Ljava/lang/String;)Ljava/lang/StringBuilder;
      54: pop
      55: aload_0
      56: getfield      #5                  // Field timeout:I
      59: iconst_m1
      60: if_icmpeq     84
      63: aload_1
      64: bipush        44
      66: invokevirtual #42                 // Method java/lang/StringBuilder.append:(C)Ljava/lang/StringBuilder;
      69: pop
      70: aload_1
      71: ldc           #43                 // String timeout_
      73: invokevirtual #41                 // Method java/lang/StringBuilder.append:(Ljava/lang/String;)Ljava/lang/StringBuilder;
      76: aload_0
      77: getfield      #5                  // Field timeout:I
      80: invokevirtual #44                 // Method java/lang/StringBuilder.append:(I)Ljava/lang/StringBuilder;
      83: pop
      84: aload_0
      85: getfield      #6                  // Field readOnly:Z
      88: ifeq          105
      91: aload_1
      92: bipush        44
      94: invokevirtual #42                 // Method java/lang/StringBuilder.append:(C)Ljava/lang/StringBuilder;
      97: pop
      98: aload_1
      99: ldc           #45                 // String readOnly
     101: invokevirtual #41                 // Method java/lang/StringBuilder.append:(Ljava/lang/String;)Ljava/lang/StringBuilder;
     104: pop
     105: aload_1
     106: areturn

  static {};
    Code:
       0: new           #46                 // class org/springframework/core/Constants
       3: dup
       4: ldc           #2                  // class org/springframework/transaction/TransactionDefinition
       6: invokespecial #47                 // Method org/springframework/core/Constants."<init>":(Ljava/lang/Class;)V
       9: putstatic     #19                 // Field constants:Lorg/springframework/core/Constants;
      12: return
}
