abstract class org.bouncycastle.crypto.digests.Kangaroo$KangarooBase implements org.bouncycastle.crypto.ExtendedDigest,org.bouncycastle.crypto.Xof {
  private static final int BLKSIZE;

  private static final byte[] SINGLE;

  private static final byte[] INTERMEDIATE;

  private static final byte[] FINAL;

  private static final byte[] FIRST;

  private final byte[] singleByte;

  private final org.bouncycastle.crypto.digests.Kangaroo$KangarooSponge theTree;

  private final org.bouncycastle.crypto.digests.Kangaroo$KangarooSponge theLeaf;

  private final int theChainLen;

  private byte[] thePersonal;

  private long theXofLen;

  private long theXofRemaining;

  private boolean squeezing;

  private int theCurrNode;

  private int theProcessed;

  org.bouncycastle.crypto.digests.Kangaroo$KangarooBase(int, int, int);
    Code:
       0: aload_0
       1: invokespecial #163                // Method java/lang/Object."<init>":()V
       4: aload_0
       5: iconst_1
       6: newarray       byte
       8: putfield      #156                // Field singleByte:[B
      11: aload_0
      12: new           #98                 // class org/bouncycastle/crypto/digests/Kangaroo$KangarooSponge
      15: dup
      16: iload_1
      17: iload_2
      18: invokespecial #179                // Method org/bouncycastle/crypto/digests/Kangaroo$KangarooSponge."<init>":(II)V
      21: putfield      #159                // Field theTree:Lorg/bouncycastle/crypto/digests/Kangaroo$KangarooSponge;
      24: aload_0
      25: new           #98                 // class org/bouncycastle/crypto/digests/Kangaroo$KangarooSponge
      28: dup
      29: iload_1
      30: iload_2
      31: invokespecial #179                // Method org/bouncycastle/crypto/digests/Kangaroo$KangarooSponge."<init>":(II)V
      34: putfield      #158                // Field theLeaf:Lorg/bouncycastle/crypto/digests/Kangaroo$KangarooSponge;
      37: aload_0
      38: iload_1
      39: iconst_2
      40: ishr
      41: putfield      #146                // Field theChainLen:I
      44: aload_0
      45: iload_3
      46: i2l
      47: putfield      #149                // Field theXofLen:J
      50: aload_0
      51: ldc2_w        #86                 // long -1l
      54: putfield      #150                // Field theXofRemaining:J
      57: aload_0
      58: aconst_null
      59: invokespecial #172                // Method buildPersonal:([B)V
      62: return

  private void buildPersonal(byte[]);
    Code:
       0: aload_1
       1: ifnonnull     8
       4: iconst_0
       5: goto          10
       8: aload_1
       9: arraylength
      10: istore_2
      11: iload_2
      12: i2l
      13: invokestatic  #170                // Method lengthEncode:(J)[B
      16: astore_3
      17: aload_0
      18: aload_1
      19: ifnonnull     31
      22: iload_2
      23: aload_3
      24: arraylength
      25: iadd
      26: newarray       byte
      28: goto          39
      31: aload_1
      32: iload_2
      33: aload_3
      34: arraylength
      35: iadd
      36: invokestatic  #185                // Method org/bouncycastle/util/Arrays.copyOf:([BI)[B
      39: putfield      #157                // Field thePersonal:[B
      42: aload_3
      43: iconst_0
      44: aload_0
      45: getfield      #157                // Field thePersonal:[B
      48: iload_2
      49: aload_3
      50: arraylength
      51: invokestatic  #164                // Method java/lang/System.arraycopy:(Ljava/lang/Object;ILjava/lang/Object;II)V
      54: return

  public int getByteLength();
    Code:
       0: aload_0
       1: getfield      #159                // Field theTree:Lorg/bouncycastle/crypto/digests/Kangaroo$KangarooSponge;
       4: invokestatic  #180                // Method org/bouncycastle/crypto/digests/Kangaroo$KangarooSponge.access$200:(Lorg/bouncycastle/crypto/digests/Kangaroo$KangarooSponge;)I
       7: ireturn

  public int getDigestSize();
    Code:
       0: aload_0
       1: getfield      #149                // Field theXofLen:J
       4: lconst_0
       5: lcmp
       6: ifne          18
       9: aload_0
      10: getfield      #146                // Field theChainLen:I
      13: iconst_1
      14: ishr
      15: goto          23
      18: aload_0
      19: getfield      #149                // Field theXofLen:J
      22: l2i
      23: ireturn

  public void init(org.bouncycastle.crypto.digests.Kangaroo$KangarooParameters);
    Code:
       0: aload_0
       1: aload_1
       2: invokevirtual #178                // Method org/bouncycastle/crypto/digests/Kangaroo$KangarooParameters.getPersonalisation:()[B
       5: invokespecial #172                // Method buildPersonal:([B)V
       8: aload_1
       9: invokevirtual #177                // Method org/bouncycastle/crypto/digests/Kangaroo$KangarooParameters.getMaxOutputLength:()J
      12: lstore_2
      13: lload_2
      14: ldc2_w        #86                 // long -1l
      17: lcmp
      18: ifge          31
      21: new           #88                 // class java/lang/IllegalArgumentException
      24: dup
      25: ldc           #3                  // String Invalid output length
      27: invokespecial #160                // Method java/lang/IllegalArgumentException."<init>":(Ljava/lang/String;)V
      30: athrow
      31: aload_0
      32: lload_2
      33: putfield      #149                // Field theXofLen:J
      36: aload_0
      37: invokevirtual #166                // Method reset:()V
      40: return

  public void update(byte);
    Code:
       0: aload_0
       1: getfield      #156                // Field singleByte:[B
       4: iconst_0
       5: iload_1
       6: bastore
       7: aload_0
       8: aload_0
       9: getfield      #156                // Field singleByte:[B
      12: iconst_0
      13: iconst_1
      14: invokevirtual #176                // Method update:([BII)V
      17: return

  public void update(byte[], int, int);
    Code:
       0: aload_0
       1: aload_1
       2: iload_2
       3: iload_3
       4: invokespecial #175                // Method processData:([BII)V
       7: return

  public int doFinal(byte[], int);
    Code:
       0: aload_0
       1: invokevirtual #165                // Method getDigestSize:()I
       4: iconst_m1
       5: if_icmpne     18
       8: new           #89                 // class java/lang/IllegalStateException
      11: dup
      12: ldc           #4                  // String No defined output length
      14: invokespecial #161                // Method java/lang/IllegalStateException."<init>":(Ljava/lang/String;)V
      17: athrow
      18: aload_0
      19: aload_1
      20: iload_2
      21: aload_0
      22: invokevirtual #165                // Method getDigestSize:()I
      25: invokevirtual #173                // Method doFinal:([BII)I
      28: ireturn

  public int doFinal(byte[], int, int);
    Code:
       0: aload_0
       1: getfield      #151                // Field squeezing:Z
       4: ifeq          17
       7: new           #89                 // class java/lang/IllegalStateException
      10: dup
      11: ldc           #1                  // String Already outputting
      13: invokespecial #161                // Method java/lang/IllegalStateException."<init>":(Ljava/lang/String;)V
      16: athrow
      17: aload_0
      18: aload_1
      19: iload_2
      20: iload_3
      21: invokevirtual #174                // Method doOutput:([BII)I
      24: istore        4
      26: aload_0
      27: invokevirtual #166                // Method reset:()V
      30: iload         4
      32: ireturn

  public int doOutput(byte[], int, int);
    Code:
       0: aload_0
       1: getfield      #151                // Field squeezing:Z
       4: ifne          11
       7: aload_0
       8: invokespecial #169                // Method switchToSqueezing:()V
      11: iload_3
      12: iflt          34
      15: aload_0
      16: getfield      #150                // Field theXofRemaining:J
      19: lconst_0
      20: lcmp
      21: ifle          44
      24: iload_3
      25: i2l
      26: aload_0
      27: getfield      #150                // Field theXofRemaining:J
      30: lcmp
      31: ifle          44
      34: new           #88                 // class java/lang/IllegalArgumentException
      37: dup
      38: ldc           #2                  // String Insufficient bytes remaining
      40: invokespecial #160                // Method java/lang/IllegalArgumentException."<init>":(Ljava/lang/String;)V
      43: athrow
      44: aload_0
      45: getfield      #159                // Field theTree:Lorg/bouncycastle/crypto/digests/Kangaroo$KangarooSponge;
      48: aload_1
      49: iload_2
      50: iload_3
      51: invokestatic  #183                // Method org/bouncycastle/crypto/digests/Kangaroo$KangarooSponge.access$300:(Lorg/bouncycastle/crypto/digests/Kangaroo$KangarooSponge;[BII)V
      54: iload_3
      55: ireturn

  private void processData(byte[], int, int);
    Code:
       0: aload_0
       1: getfield      #151                // Field squeezing:Z
       4: ifeq          17
       7: new           #89                 // class java/lang/IllegalStateException
      10: dup
      11: ldc           #5                  // String attempt to absorb while squeezing
      13: invokespecial #161                // Method java/lang/IllegalStateException."<init>":(Ljava/lang/String;)V
      16: athrow
      17: aload_0
      18: getfield      #147                // Field theCurrNode:I
      21: ifne          31
      24: aload_0
      25: getfield      #159                // Field theTree:Lorg/bouncycastle/crypto/digests/Kangaroo$KangarooSponge;
      28: goto          35
      31: aload_0
      32: getfield      #158                // Field theLeaf:Lorg/bouncycastle/crypto/digests/Kangaroo$KangarooSponge;
      35: astore        4
      37: sipush        8192
      40: aload_0
      41: getfield      #148                // Field theProcessed:I
      44: isub
      45: istore        5
      47: iload         5
      49: iload_3
      50: if_icmplt     72
      53: aload         4
      55: aload_1
      56: iload_2
      57: iload_3
      58: invokestatic  #184                // Method org/bouncycastle/crypto/digests/Kangaroo$KangarooSponge.access$400:(Lorg/bouncycastle/crypto/digests/Kangaroo$KangarooSponge;[BII)V
      61: aload_0
      62: dup
      63: getfield      #148                // Field theProcessed:I
      66: iload_3
      67: iadd
      68: putfield      #148                // Field theProcessed:I
      71: return
      72: iload         5
      74: ifle          97
      77: aload         4
      79: aload_1
      80: iload_2
      81: iload         5
      83: invokestatic  #184                // Method org/bouncycastle/crypto/digests/Kangaroo$KangarooSponge.access$400:(Lorg/bouncycastle/crypto/digests/Kangaroo$KangarooSponge;[BII)V
      86: aload_0
      87: dup
      88: getfield      #148                // Field theProcessed:I
      91: iload         5
      93: iadd
      94: putfield      #148                // Field theProcessed:I
      97: iload         5
      99: istore        6
     101: iload         6
     103: iload_3
     104: if_icmpge     169
     107: aload_0
     108: getfield      #148                // Field theProcessed:I
     111: sipush        8192
     114: if_icmpne     122
     117: aload_0
     118: iconst_1
     119: invokespecial #171                // Method switchLeaf:(Z)V
     122: iload_3
     123: iload         6
     125: isub
     126: sipush        8192
     129: invokestatic  #162                // Method java/lang/Math.min:(II)I
     132: istore        7
     134: aload_0
     135: getfield      #158                // Field theLeaf:Lorg/bouncycastle/crypto/digests/Kangaroo$KangarooSponge;
     138: aload_1
     139: iload_2
     140: iload         6
     142: iadd
     143: iload         7
     145: invokestatic  #184                // Method org/bouncycastle/crypto/digests/Kangaroo$KangarooSponge.access$400:(Lorg/bouncycastle/crypto/digests/Kangaroo$KangarooSponge;[BII)V
     148: aload_0
     149: dup
     150: getfield      #148                // Field theProcessed:I
     153: iload         7
     155: iadd
     156: putfield      #148                // Field theProcessed:I
     159: iload         6
     161: iload         7
     163: iadd
     164: istore        6
     166: goto          101
     169: return

  public void reset();
    Code:
       0: aload_0
       1: getfield      #159                // Field theTree:Lorg/bouncycastle/crypto/digests/Kangaroo$KangarooSponge;
       4: invokestatic  #181                // Method org/bouncycastle/crypto/digests/Kangaroo$KangarooSponge.access$500:(Lorg/bouncycastle/crypto/digests/Kangaroo$KangarooSponge;)V
       7: aload_0
       8: getfield      #158                // Field theLeaf:Lorg/bouncycastle/crypto/digests/Kangaroo$KangarooSponge;
      11: invokestatic  #181                // Method org/bouncycastle/crypto/digests/Kangaroo$KangarooSponge.access$500:(Lorg/bouncycastle/crypto/digests/Kangaroo$KangarooSponge;)V
      14: aload_0
      15: iconst_0
      16: putfield      #147                // Field theCurrNode:I
      19: aload_0
      20: iconst_0
      21: putfield      #148                // Field theProcessed:I
      24: aload_0
      25: ldc2_w        #86                 // long -1l
      28: putfield      #150                // Field theXofRemaining:J
      31: aload_0
      32: iconst_0
      33: putfield      #151                // Field squeezing:Z
      36: return

  private void switchLeaf(boolean);
    Code:
       0: aload_0
       1: getfield      #147                // Field theCurrNode:I
       4: ifne          25
       7: aload_0
       8: getfield      #159                // Field theTree:Lorg/bouncycastle/crypto/digests/Kangaroo$KangarooSponge;
      11: getstatic     #153                // Field FIRST:[B
      14: iconst_0
      15: getstatic     #153                // Field FIRST:[B
      18: arraylength
      19: invokestatic  #184                // Method org/bouncycastle/crypto/digests/Kangaroo$KangarooSponge.access$400:(Lorg/bouncycastle/crypto/digests/Kangaroo$KangarooSponge;[BII)V
      22: goto          80
      25: aload_0
      26: getfield      #158                // Field theLeaf:Lorg/bouncycastle/crypto/digests/Kangaroo$KangarooSponge;
      29: getstatic     #154                // Field INTERMEDIATE:[B
      32: iconst_0
      33: getstatic     #154                // Field INTERMEDIATE:[B
      36: arraylength
      37: invokestatic  #184                // Method org/bouncycastle/crypto/digests/Kangaroo$KangarooSponge.access$400:(Lorg/bouncycastle/crypto/digests/Kangaroo$KangarooSponge;[BII)V
      40: aload_0
      41: getfield      #146                // Field theChainLen:I
      44: newarray       byte
      46: astore_2
      47: aload_0
      48: getfield      #158                // Field theLeaf:Lorg/bouncycastle/crypto/digests/Kangaroo$KangarooSponge;
      51: aload_2
      52: iconst_0
      53: aload_0
      54: getfield      #146                // Field theChainLen:I
      57: invokestatic  #183                // Method org/bouncycastle/crypto/digests/Kangaroo$KangarooSponge.access$300:(Lorg/bouncycastle/crypto/digests/Kangaroo$KangarooSponge;[BII)V
      60: aload_0
      61: getfield      #159                // Field theTree:Lorg/bouncycastle/crypto/digests/Kangaroo$KangarooSponge;
      64: aload_2
      65: iconst_0
      66: aload_0
      67: getfield      #146                // Field theChainLen:I
      70: invokestatic  #184                // Method org/bouncycastle/crypto/digests/Kangaroo$KangarooSponge.access$400:(Lorg/bouncycastle/crypto/digests/Kangaroo$KangarooSponge;[BII)V
      73: aload_0
      74: getfield      #158                // Field theLeaf:Lorg/bouncycastle/crypto/digests/Kangaroo$KangarooSponge;
      77: invokestatic  #181                // Method org/bouncycastle/crypto/digests/Kangaroo$KangarooSponge.access$500:(Lorg/bouncycastle/crypto/digests/Kangaroo$KangarooSponge;)V
      80: iload_1
      81: ifeq          94
      84: aload_0
      85: dup
      86: getfield      #147                // Field theCurrNode:I
      89: iconst_1
      90: iadd
      91: putfield      #147                // Field theCurrNode:I
      94: aload_0
      95: iconst_0
      96: putfield      #148                // Field theProcessed:I
      99: return

  private void switchToSqueezing();
    Code:
       0: aload_0
       1: aload_0
       2: getfield      #157                // Field thePersonal:[B
       5: iconst_0
       6: aload_0
       7: getfield      #157                // Field thePersonal:[B
      10: arraylength
      11: invokespecial #175                // Method processData:([BII)V
      14: aload_0
      15: getfield      #147                // Field theCurrNode:I
      18: ifne          28
      21: aload_0
      22: invokespecial #168                // Method switchSingle:()V
      25: goto          32
      28: aload_0
      29: invokespecial #167                // Method switchFinal:()V
      32: aload_0
      33: getfield      #149                // Field theXofLen:J
      36: lconst_0
      37: lcmp
      38: ifne          53
      41: aload_0
      42: aload_0
      43: invokevirtual #165                // Method getDigestSize:()I
      46: i2l
      47: putfield      #150                // Field theXofRemaining:J
      50: goto          78
      53: aload_0
      54: aload_0
      55: getfield      #149                // Field theXofLen:J
      58: ldc2_w        #86                 // long -1l
      61: lcmp
      62: ifne          71
      65: ldc2_w        #84                 // long -2l
      68: goto          75
      71: aload_0
      72: getfield      #149                // Field theXofLen:J
      75: putfield      #150                // Field theXofRemaining:J
      78: return

  private void switchSingle();
    Code:
       0: aload_0
       1: getfield      #159                // Field theTree:Lorg/bouncycastle/crypto/digests/Kangaroo$KangarooSponge;
       4: getstatic     #155                // Field SINGLE:[B
       7: iconst_0
       8: iconst_1
       9: invokestatic  #184                // Method org/bouncycastle/crypto/digests/Kangaroo$KangarooSponge.access$400:(Lorg/bouncycastle/crypto/digests/Kangaroo$KangarooSponge;[BII)V
      12: aload_0
      13: getfield      #159                // Field theTree:Lorg/bouncycastle/crypto/digests/Kangaroo$KangarooSponge;
      16: invokestatic  #182                // Method org/bouncycastle/crypto/digests/Kangaroo$KangarooSponge.access$600:(Lorg/bouncycastle/crypto/digests/Kangaroo$KangarooSponge;)V
      19: return

  private void switchFinal();
    Code:
       0: aload_0
       1: iconst_0
       2: invokespecial #171                // Method switchLeaf:(Z)V
       5: aload_0
       6: getfield      #147                // Field theCurrNode:I
       9: i2l
      10: invokestatic  #170                // Method lengthEncode:(J)[B
      13: astore_1
      14: aload_0
      15: getfield      #159                // Field theTree:Lorg/bouncycastle/crypto/digests/Kangaroo$KangarooSponge;
      18: aload_1
      19: iconst_0
      20: aload_1
      21: arraylength
      22: invokestatic  #184                // Method org/bouncycastle/crypto/digests/Kangaroo$KangarooSponge.access$400:(Lorg/bouncycastle/crypto/digests/Kangaroo$KangarooSponge;[BII)V
      25: aload_0
      26: getfield      #159                // Field theTree:Lorg/bouncycastle/crypto/digests/Kangaroo$KangarooSponge;
      29: getstatic     #152                // Field FINAL:[B
      32: iconst_0
      33: getstatic     #152                // Field FINAL:[B
      36: arraylength
      37: invokestatic  #184                // Method org/bouncycastle/crypto/digests/Kangaroo$KangarooSponge.access$400:(Lorg/bouncycastle/crypto/digests/Kangaroo$KangarooSponge;[BII)V
      40: aload_0
      41: getfield      #159                // Field theTree:Lorg/bouncycastle/crypto/digests/Kangaroo$KangarooSponge;
      44: invokestatic  #182                // Method org/bouncycastle/crypto/digests/Kangaroo$KangarooSponge.access$600:(Lorg/bouncycastle/crypto/digests/Kangaroo$KangarooSponge;)V
      47: return

  private static byte[] lengthEncode(long);
    Code:
       0: iconst_0
       1: istore_2
       2: lload_0
       3: lstore_3
       4: lload_3
       5: lconst_0
       6: lcmp
       7: ifeq          31
      10: iconst_1
      11: istore_2
      12: lload_3
      13: bipush        8
      15: lshr
      16: dup2
      17: lstore_3
      18: lconst_0
      19: lcmp
      20: ifeq          31
      23: iload_2
      24: iconst_1
      25: iadd
      26: i2b
      27: istore_2
      28: goto          12
      31: iload_2
      32: iconst_1
      33: iadd
      34: newarray       byte
      36: astore        5
      38: aload         5
      40: iload_2
      41: iload_2
      42: bastore
      43: iconst_0
      44: istore        6
      46: iload         6
      48: iload_2
      49: if_icmpge     76
      52: aload         5
      54: iload         6
      56: lload_0
      57: bipush        8
      59: iload_2
      60: iload         6
      62: isub
      63: iconst_1
      64: isub
      65: imul
      66: lshr
      67: l2i
      68: i2b
      69: bastore
      70: iinc          6, 1
      73: goto          46
      76: aload         5
      78: areturn

  static {};
    Code:
       0: iconst_1
       1: newarray       byte
       3: dup
       4: iconst_0
       5: bipush        7
       7: bastore
       8: putstatic     #155                // Field SINGLE:[B
      11: iconst_1
      12: newarray       byte
      14: dup
      15: iconst_0
      16: bipush        11
      18: bastore
      19: putstatic     #154                // Field INTERMEDIATE:[B
      22: iconst_3
      23: newarray       byte
      25: dup
      26: iconst_0
      27: iconst_m1
      28: bastore
      29: dup
      30: iconst_1
      31: iconst_m1
      32: bastore
      33: dup
      34: iconst_2
      35: bipush        6
      37: bastore
      38: putstatic     #152                // Field FINAL:[B
      41: bipush        8
      43: newarray       byte
      45: dup
      46: iconst_0
      47: iconst_3
      48: bastore
      49: dup
      50: iconst_1
      51: iconst_0
      52: bastore
      53: dup
      54: iconst_2
      55: iconst_0
      56: bastore
      57: dup
      58: iconst_3
      59: iconst_0
      60: bastore
      61: dup
      62: iconst_4
      63: iconst_0
      64: bastore
      65: dup
      66: iconst_5
      67: iconst_0
      68: bastore
      69: dup
      70: bipush        6
      72: iconst_0
      73: bastore
      74: dup
      75: bipush        7
      77: iconst_0
      78: bastore
      79: putstatic     #153                // Field FIRST:[B
      82: return
}
