Compiled from "JsonValueSerializer.java"
public final class org.elasticsearch.hadoop.thirdparty.codehaus.jackson.map.ser.JsonValueSerializer extends org.elasticsearch.hadoop.thirdparty.codehaus.jackson.map.ser.SerializerBase<java.lang.Object> implements org.elasticsearch.hadoop.thirdparty.codehaus.jackson.map.ResolvableSerializer, org.elasticsearch.hadoop.thirdparty.codehaus.jackson.schema.SchemaAware {
  protected final java.lang.reflect.Method _accessorMethod;

  protected org.elasticsearch.hadoop.thirdparty.codehaus.jackson.map.JsonSerializer<java.lang.Object> _valueSerializer;

  protected final org.elasticsearch.hadoop.thirdparty.codehaus.jackson.map.BeanProperty _property;

  protected boolean _forceTypeInformation;

  public org.elasticsearch.hadoop.thirdparty.codehaus.jackson.map.ser.JsonValueSerializer(java.lang.reflect.Method, org.elasticsearch.hadoop.thirdparty.codehaus.jackson.map.JsonSerializer<java.lang.Object>, org.elasticsearch.hadoop.thirdparty.codehaus.jackson.map.BeanProperty);
    Code:
       0: aload_0
       1: ldc           #30                 // class java/lang/Object
       3: invokespecial #33                 // Method org/elasticsearch/hadoop/thirdparty/codehaus/jackson/map/ser/SerializerBase."<init>":(Ljava/lang/Class;)V
       6: aload_0
       7: aload_1
       8: putfield      #35                 // Field _accessorMethod:Ljava/lang/reflect/Method;
      11: aload_0
      12: aload_2
      13: putfield      #37                 // Field _valueSerializer:Lorg/elasticsearch/hadoop/thirdparty/codehaus/jackson/map/JsonSerializer;
      16: aload_0
      17: aload_3
      18: putfield      #39                 // Field _property:Lorg/elasticsearch/hadoop/thirdparty/codehaus/jackson/map/BeanProperty;
      21: return

  public void serialize(java.lang.Object, org.elasticsearch.hadoop.thirdparty.codehaus.jackson.JsonGenerator, org.elasticsearch.hadoop.thirdparty.codehaus.jackson.map.SerializerProvider) throws java.io.IOException, org.elasticsearch.hadoop.thirdparty.codehaus.jackson.JsonGenerationException;
    Code:
       0: aload_0
       1: getfield      #35                 // Field _accessorMethod:Ljava/lang/reflect/Method;
       4: aload_1
       5: iconst_0
       6: anewarray     #30                 // class java/lang/Object
       9: invokevirtual #58                 // Method java/lang/reflect/Method.invoke:(Ljava/lang/Object;[Ljava/lang/Object;)Ljava/lang/Object;
      12: astore        4
      14: aload         4
      16: ifnonnull     25
      19: aload_3
      20: aload_2
      21: invokevirtual #64                 // Method org/elasticsearch/hadoop/thirdparty/codehaus/jackson/map/SerializerProvider.defaultSerializeNull:(Lorg/elasticsearch/hadoop/thirdparty/codehaus/jackson/JsonGenerator;)V
      24: return
      25: aload_0
      26: getfield      #37                 // Field _valueSerializer:Lorg/elasticsearch/hadoop/thirdparty/codehaus/jackson/map/JsonSerializer;
      29: astore        5
      31: aload         5
      33: ifnonnull     56
      36: aload         4
      38: invokevirtual #68                 // Method java/lang/Object.getClass:()Ljava/lang/Class;
      41: astore        6
      43: aload_3
      44: aload         6
      46: iconst_1
      47: aload_0
      48: getfield      #39                 // Field _property:Lorg/elasticsearch/hadoop/thirdparty/codehaus/jackson/map/BeanProperty;
      51: invokevirtual #72                 // Method org/elasticsearch/hadoop/thirdparty/codehaus/jackson/map/SerializerProvider.findTypedValueSerializer:(Ljava/lang/Class;ZLorg/elasticsearch/hadoop/thirdparty/codehaus/jackson/map/BeanProperty;)Lorg/elasticsearch/hadoop/thirdparty/codehaus/jackson/map/JsonSerializer;
      54: astore        5
      56: aload         5
      58: aload         4
      60: aload_2
      61: aload_3
      62: invokevirtual #76                 // Method org/elasticsearch/hadoop/thirdparty/codehaus/jackson/map/JsonSerializer.serialize:(Ljava/lang/Object;Lorg/elasticsearch/hadoop/thirdparty/codehaus/jackson/JsonGenerator;Lorg/elasticsearch/hadoop/thirdparty/codehaus/jackson/map/SerializerProvider;)V
      65: goto          151
      68: astore        4
      70: aload         4
      72: athrow
      73: astore        4
      75: aload         4
      77: astore        5
      79: aload         5
      81: instanceof    #78                 // class java/lang/reflect/InvocationTargetException
      84: ifeq          105
      87: aload         5
      89: invokevirtual #84                 // Method java/lang/Throwable.getCause:()Ljava/lang/Throwable;
      92: ifnull        105
      95: aload         5
      97: invokevirtual #84                 // Method java/lang/Throwable.getCause:()Ljava/lang/Throwable;
     100: astore        5
     102: goto          79
     105: aload         5
     107: instanceof    #86                 // class java/lang/Error
     110: ifeq          119
     113: aload         5
     115: checkcast     #86                 // class java/lang/Error
     118: athrow
     119: aload         5
     121: aload_1
     122: new           #88                 // class java/lang/StringBuilder
     125: dup
     126: invokespecial #91                 // Method java/lang/StringBuilder."<init>":()V
     129: aload_0
     130: getfield      #35                 // Field _accessorMethod:Ljava/lang/reflect/Method;
     133: invokevirtual #95                 // Method java/lang/reflect/Method.getName:()Ljava/lang/String;
     136: invokevirtual #99                 // Method java/lang/StringBuilder.append:(Ljava/lang/String;)Ljava/lang/StringBuilder;
     139: ldc           #101                // String ()
     141: invokevirtual #99                 // Method java/lang/StringBuilder.append:(Ljava/lang/String;)Ljava/lang/StringBuilder;
     144: invokevirtual #104                // Method java/lang/StringBuilder.toString:()Ljava/lang/String;
     147: invokestatic  #110                // Method org/elasticsearch/hadoop/thirdparty/codehaus/jackson/map/JsonMappingException.wrapWithPath:(Ljava/lang/Throwable;Ljava/lang/Object;Ljava/lang/String;)Lorg/elasticsearch/hadoop/thirdparty/codehaus/jackson/map/JsonMappingException;
     150: athrow
     151: return
    Exception table:
       from    to  target type
           0    24    68   Class java/io/IOException
          25    65    68   Class java/io/IOException
           0    24    73   Class java/lang/Exception
          25    65    73   Class java/lang/Exception

  public void serializeWithType(java.lang.Object, org.elasticsearch.hadoop.thirdparty.codehaus.jackson.JsonGenerator, org.elasticsearch.hadoop.thirdparty.codehaus.jackson.map.SerializerProvider, org.elasticsearch.hadoop.thirdparty.codehaus.jackson.map.TypeSerializer) throws java.io.IOException, org.elasticsearch.hadoop.thirdparty.codehaus.jackson.JsonProcessingException;
    Code:
       0: aconst_null
       1: astore        5
       3: aload_0
       4: getfield      #35                 // Field _accessorMethod:Ljava/lang/reflect/Method;
       7: aload_1
       8: iconst_0
       9: anewarray     #30                 // class java/lang/Object
      12: invokevirtual #58                 // Method java/lang/reflect/Method.invoke:(Ljava/lang/Object;[Ljava/lang/Object;)Ljava/lang/Object;
      15: astore        5
      17: aload         5
      19: ifnonnull     28
      22: aload_3
      23: aload_2
      24: invokevirtual #64                 // Method org/elasticsearch/hadoop/thirdparty/codehaus/jackson/map/SerializerProvider.defaultSerializeNull:(Lorg/elasticsearch/hadoop/thirdparty/codehaus/jackson/JsonGenerator;)V
      27: return
      28: aload_0
      29: getfield      #37                 // Field _valueSerializer:Lorg/elasticsearch/hadoop/thirdparty/codehaus/jackson/map/JsonSerializer;
      32: astore        6
      34: aload         6
      36: ifnull        79
      39: aload_0
      40: getfield      #132                // Field _forceTypeInformation:Z
      43: ifeq          53
      46: aload         4
      48: aload_1
      49: aload_2
      50: invokevirtual #138                // Method org/elasticsearch/hadoop/thirdparty/codehaus/jackson/map/TypeSerializer.writeTypePrefixForScalar:(Ljava/lang/Object;Lorg/elasticsearch/hadoop/thirdparty/codehaus/jackson/JsonGenerator;)V
      53: aload         6
      55: aload         5
      57: aload_2
      58: aload_3
      59: aload         4
      61: invokevirtual #140                // Method org/elasticsearch/hadoop/thirdparty/codehaus/jackson/map/JsonSerializer.serializeWithType:(Ljava/lang/Object;Lorg/elasticsearch/hadoop/thirdparty/codehaus/jackson/JsonGenerator;Lorg/elasticsearch/hadoop/thirdparty/codehaus/jackson/map/SerializerProvider;Lorg/elasticsearch/hadoop/thirdparty/codehaus/jackson/map/TypeSerializer;)V
      64: aload_0
      65: getfield      #132                // Field _forceTypeInformation:Z
      68: ifeq          78
      71: aload         4
      73: aload_1
      74: aload_2
      75: invokevirtual #143                // Method org/elasticsearch/hadoop/thirdparty/codehaus/jackson/map/TypeSerializer.writeTypeSuffixForScalar:(Ljava/lang/Object;Lorg/elasticsearch/hadoop/thirdparty/codehaus/jackson/JsonGenerator;)V
      78: return
      79: aload         5
      81: invokevirtual #68                 // Method java/lang/Object.getClass:()Ljava/lang/Class;
      84: astore        7
      86: aload_3
      87: aload         7
      89: iconst_1
      90: aload_0
      91: getfield      #39                 // Field _property:Lorg/elasticsearch/hadoop/thirdparty/codehaus/jackson/map/BeanProperty;
      94: invokevirtual #72                 // Method org/elasticsearch/hadoop/thirdparty/codehaus/jackson/map/SerializerProvider.findTypedValueSerializer:(Ljava/lang/Class;ZLorg/elasticsearch/hadoop/thirdparty/codehaus/jackson/map/BeanProperty;)Lorg/elasticsearch/hadoop/thirdparty/codehaus/jackson/map/JsonSerializer;
      97: astore        6
      99: aload         6
     101: aload         5
     103: aload_2
     104: aload_3
     105: invokevirtual #76                 // Method org/elasticsearch/hadoop/thirdparty/codehaus/jackson/map/JsonSerializer.serialize:(Ljava/lang/Object;Lorg/elasticsearch/hadoop/thirdparty/codehaus/jackson/JsonGenerator;Lorg/elasticsearch/hadoop/thirdparty/codehaus/jackson/map/SerializerProvider;)V
     108: goto          194
     111: astore        6
     113: aload         6
     115: athrow
     116: astore        6
     118: aload         6
     120: astore        7
     122: aload         7
     124: instanceof    #78                 // class java/lang/reflect/InvocationTargetException
     127: ifeq          148
     130: aload         7
     132: invokevirtual #84                 // Method java/lang/Throwable.getCause:()Ljava/lang/Throwable;
     135: ifnull        148
     138: aload         7
     140: invokevirtual #84                 // Method java/lang/Throwable.getCause:()Ljava/lang/Throwable;
     143: astore        7
     145: goto          122
     148: aload         7
     150: instanceof    #86                 // class java/lang/Error
     153: ifeq          162
     156: aload         7
     158: checkcast     #86                 // class java/lang/Error
     161: athrow
     162: aload         7
     164: aload_1
     165: new           #88                 // class java/lang/StringBuilder
     168: dup
     169: invokespecial #91                 // Method java/lang/StringBuilder."<init>":()V
     172: aload_0
     173: getfield      #35                 // Field _accessorMethod:Ljava/lang/reflect/Method;
     176: invokevirtual #95                 // Method java/lang/reflect/Method.getName:()Ljava/lang/String;
     179: invokevirtual #99                 // Method java/lang/StringBuilder.append:(Ljava/lang/String;)Ljava/lang/StringBuilder;
     182: ldc           #101                // String ()
     184: invokevirtual #99                 // Method java/lang/StringBuilder.append:(Ljava/lang/String;)Ljava/lang/StringBuilder;
     187: invokevirtual #104                // Method java/lang/StringBuilder.toString:()Ljava/lang/String;
     190: invokestatic  #110                // Method org/elasticsearch/hadoop/thirdparty/codehaus/jackson/map/JsonMappingException.wrapWithPath:(Ljava/lang/Throwable;Ljava/lang/Object;Ljava/lang/String;)Lorg/elasticsearch/hadoop/thirdparty/codehaus/jackson/map/JsonMappingException;
     193: athrow
     194: return
    Exception table:
       from    to  target type
           3    27   111   Class java/io/IOException
          28    78   111   Class java/io/IOException
          79   108   111   Class java/io/IOException
           3    27   116   Class java/lang/Exception
          28    78   116   Class java/lang/Exception
          79   108   116   Class java/lang/Exception

  public org.elasticsearch.hadoop.thirdparty.codehaus.jackson.JsonNode getSchema(org.elasticsearch.hadoop.thirdparty.codehaus.jackson.map.SerializerProvider, java.lang.reflect.Type) throws org.elasticsearch.hadoop.thirdparty.codehaus.jackson.map.JsonMappingException;
    Code:
       0: aload_0
       1: getfield      #37                 // Field _valueSerializer:Lorg/elasticsearch/hadoop/thirdparty/codehaus/jackson/map/JsonSerializer;
       4: instanceof    #9                  // class org/elasticsearch/hadoop/thirdparty/codehaus/jackson/schema/SchemaAware
       7: ifeq          27
      10: aload_0
      11: getfield      #37                 // Field _valueSerializer:Lorg/elasticsearch/hadoop/thirdparty/codehaus/jackson/map/JsonSerializer;
      14: checkcast     #9                  // class org/elasticsearch/hadoop/thirdparty/codehaus/jackson/schema/SchemaAware
      17: aload_1
      18: aconst_null
      19: invokeinterface #150,  3          // InterfaceMethod org/elasticsearch/hadoop/thirdparty/codehaus/jackson/schema/SchemaAware.getSchema:(Lorg/elasticsearch/hadoop/thirdparty/codehaus/jackson/map/SerializerProvider;Ljava/lang/reflect/Type;)Lorg/elasticsearch/hadoop/thirdparty/codehaus/jackson/JsonNode;
      24: goto          30
      27: invokestatic  #156                // Method org/elasticsearch/hadoop/thirdparty/codehaus/jackson/schema/JsonSchema.getDefaultSchemaNode:()Lorg/elasticsearch/hadoop/thirdparty/codehaus/jackson/JsonNode;
      30: areturn

  public void resolve(org.elasticsearch.hadoop.thirdparty.codehaus.jackson.map.SerializerProvider) throws org.elasticsearch.hadoop.thirdparty.codehaus.jackson.map.JsonMappingException;
    Code:
       0: aload_0
       1: getfield      #37                 // Field _valueSerializer:Lorg/elasticsearch/hadoop/thirdparty/codehaus/jackson/map/JsonSerializer;
       4: ifnonnull     72
       7: aload_1
       8: getstatic     #164                // Field org/elasticsearch/hadoop/thirdparty/codehaus/jackson/map/SerializationConfig$Feature.USE_STATIC_TYPING:Lorg/elasticsearch/hadoop/thirdparty/codehaus/jackson/map/SerializationConfig$Feature;
      11: invokevirtual #168                // Method org/elasticsearch/hadoop/thirdparty/codehaus/jackson/map/SerializerProvider.isEnabled:(Lorg/elasticsearch/hadoop/thirdparty/codehaus/jackson/map/SerializationConfig$Feature;)Z
      14: ifne          33
      17: aload_0
      18: getfield      #35                 // Field _accessorMethod:Ljava/lang/reflect/Method;
      21: invokevirtual #171                // Method java/lang/reflect/Method.getReturnType:()Ljava/lang/Class;
      24: invokevirtual #177                // Method java/lang/Class.getModifiers:()I
      27: invokestatic  #183                // Method java/lang/reflect/Modifier.isFinal:(I)Z
      30: ifeq          72
      33: aload_1
      34: aload_0
      35: getfield      #35                 // Field _accessorMethod:Ljava/lang/reflect/Method;
      38: invokevirtual #187                // Method java/lang/reflect/Method.getGenericReturnType:()Ljava/lang/reflect/Type;
      41: invokevirtual #191                // Method org/elasticsearch/hadoop/thirdparty/codehaus/jackson/map/SerializerProvider.constructType:(Ljava/lang/reflect/Type;)Lorg/elasticsearch/hadoop/thirdparty/codehaus/jackson/type/JavaType;
      44: astore_2
      45: aload_0
      46: aload_1
      47: aload_2
      48: iconst_0
      49: aload_0
      50: getfield      #39                 // Field _property:Lorg/elasticsearch/hadoop/thirdparty/codehaus/jackson/map/BeanProperty;
      53: invokevirtual #194                // Method org/elasticsearch/hadoop/thirdparty/codehaus/jackson/map/SerializerProvider.findTypedValueSerializer:(Lorg/elasticsearch/hadoop/thirdparty/codehaus/jackson/type/JavaType;ZLorg/elasticsearch/hadoop/thirdparty/codehaus/jackson/map/BeanProperty;)Lorg/elasticsearch/hadoop/thirdparty/codehaus/jackson/map/JsonSerializer;
      56: putfield      #37                 // Field _valueSerializer:Lorg/elasticsearch/hadoop/thirdparty/codehaus/jackson/map/JsonSerializer;
      59: aload_0
      60: aload_0
      61: aload_2
      62: aload_0
      63: getfield      #37                 // Field _valueSerializer:Lorg/elasticsearch/hadoop/thirdparty/codehaus/jackson/map/JsonSerializer;
      66: invokevirtual #198                // Method isNaturalTypeWithStdHandling:(Lorg/elasticsearch/hadoop/thirdparty/codehaus/jackson/type/JavaType;Lorg/elasticsearch/hadoop/thirdparty/codehaus/jackson/map/JsonSerializer;)Z
      69: putfield      #132                // Field _forceTypeInformation:Z
      72: return

  protected boolean isNaturalTypeWithStdHandling(org.elasticsearch.hadoop.thirdparty.codehaus.jackson.type.JavaType, org.elasticsearch.hadoop.thirdparty.codehaus.jackson.map.JsonSerializer<?>);
    Code:
       0: aload_1
       1: invokevirtual #205                // Method org/elasticsearch/hadoop/thirdparty/codehaus/jackson/type/JavaType.getRawClass:()Ljava/lang/Class;
       4: astore_3
       5: aload_1
       6: invokevirtual #209                // Method org/elasticsearch/hadoop/thirdparty/codehaus/jackson/type/JavaType.isPrimitive:()Z
       9: ifeq          35
      12: aload_3
      13: getstatic     #214                // Field java/lang/Integer.TYPE:Ljava/lang/Class;
      16: if_acmpeq     61
      19: aload_3
      20: getstatic     #217                // Field java/lang/Boolean.TYPE:Ljava/lang/Class;
      23: if_acmpeq     61
      26: aload_3
      27: getstatic     #220                // Field java/lang/Double.TYPE:Ljava/lang/Class;
      30: if_acmpeq     61
      33: iconst_0
      34: ireturn
      35: aload_3
      36: ldc           #222                // class java/lang/String
      38: if_acmpeq     61
      41: aload_3
      42: ldc           #211                // class java/lang/Integer
      44: if_acmpeq     61
      47: aload_3
      48: ldc           #216                // class java/lang/Boolean
      50: if_acmpeq     61
      53: aload_3
      54: ldc           #219                // class java/lang/Double
      56: if_acmpeq     61
      59: iconst_0
      60: ireturn
      61: aload_2
      62: invokevirtual #68                 // Method java/lang/Object.getClass:()Ljava/lang/Class;
      65: ldc           #224                // class org/elasticsearch/hadoop/thirdparty/codehaus/jackson/map/annotate/JacksonStdImpl
      67: invokevirtual #228                // Method java/lang/Class.getAnnotation:(Ljava/lang/Class;)Ljava/lang/annotation/Annotation;
      70: ifnull        77
      73: iconst_1
      74: goto          78
      77: iconst_0
      78: ireturn

  public java.lang.String toString();
    Code:
       0: new           #88                 // class java/lang/StringBuilder
       3: dup
       4: invokespecial #91                 // Method java/lang/StringBuilder."<init>":()V
       7: ldc           #233                // String (@JsonValue serializer for method
       9: invokevirtual #99                 // Method java/lang/StringBuilder.append:(Ljava/lang/String;)Ljava/lang/StringBuilder;
      12: aload_0
      13: getfield      #35                 // Field _accessorMethod:Ljava/lang/reflect/Method;
      16: invokevirtual #236                // Method java/lang/reflect/Method.getDeclaringClass:()Ljava/lang/Class;
      19: invokevirtual #239                // Method java/lang/StringBuilder.append:(Ljava/lang/Object;)Ljava/lang/StringBuilder;
      22: ldc           #241                // String #
      24: invokevirtual #99                 // Method java/lang/StringBuilder.append:(Ljava/lang/String;)Ljava/lang/StringBuilder;
      27: aload_0
      28: getfield      #35                 // Field _accessorMethod:Ljava/lang/reflect/Method;
      31: invokevirtual #95                 // Method java/lang/reflect/Method.getName:()Ljava/lang/String;
      34: invokevirtual #99                 // Method java/lang/StringBuilder.append:(Ljava/lang/String;)Ljava/lang/StringBuilder;
      37: ldc           #243                // String )
      39: invokevirtual #99                 // Method java/lang/StringBuilder.append:(Ljava/lang/String;)Ljava/lang/StringBuilder;
      42: invokevirtual #104                // Method java/lang/StringBuilder.toString:()Ljava/lang/String;
      45: areturn
}
