Compiled from "WeakFastHashMap.java"
class org.apache.commons.beanutils.WeakFastHashMap$EntrySet extends org.apache.commons.beanutils.WeakFastHashMap<K, V>.CollectionView<java.util.Map$Entry<K, V>> implements java.util.Set<java.util.Map$Entry<K, V>> {
  final org.apache.commons.beanutils.WeakFastHashMap this$0;

  private org.apache.commons.beanutils.WeakFastHashMap$EntrySet(org.apache.commons.beanutils.WeakFastHashMap);
    Code:
       0: aload_0
       1: aload_1
       2: putfield      #2                  // Field this$0:Lorg/apache/commons/beanutils/WeakFastHashMap;
       5: aload_0
       6: aload_1
       7: invokespecial #3                  // Method org/apache/commons/beanutils/WeakFastHashMap$CollectionView."<init>":(Lorg/apache/commons/beanutils/WeakFastHashMap;)V
      10: return

  protected java.util.Collection<java.util.Map$Entry<K, V>> get(java.util.Map<K, V>);
    Code:
       0: aload_1
       1: invokeinterface #4,  1            // InterfaceMethod java/util/Map.entrySet:()Ljava/util/Set;
       6: areturn

  protected java.util.Map$Entry<K, V> iteratorNext(java.util.Map$Entry<K, V>);
    Code:
       0: aload_1
       1: areturn

  protected java.lang.Object iteratorNext(java.util.Map$Entry);
    Code:
       0: aload_0
       1: aload_1
       2: invokevirtual #5                  // Method iteratorNext:(Ljava/util/Map$Entry;)Ljava/util/Map$Entry;
       5: areturn

  org.apache.commons.beanutils.WeakFastHashMap$EntrySet(org.apache.commons.beanutils.WeakFastHashMap, org.apache.commons.beanutils.WeakFastHashMap$1);
    Code:
       0: aload_0
       1: aload_1
       2: invokespecial #1                  // Method "<init>":(Lorg/apache/commons/beanutils/WeakFastHashMap;)V
       5: return
}
