Compiled from "DefaultListeningIOReactor.java"
class org.apache.hc.core5.reactor.DefaultListeningIOReactor$1 implements org.apache.hc.core5.function.Callback<org.apache.hc.core5.reactor.ChannelEntry> {
  final org.apache.hc.core5.reactor.DefaultListeningIOReactor this$0;

  org.apache.hc.core5.reactor.DefaultListeningIOReactor$1(org.apache.hc.core5.reactor.DefaultListeningIOReactor);
    Code:
       0: aload_0
       1: aload_1
       2: putfield      #1                  // Field this$0:Lorg/apache/hc/core5/reactor/DefaultListeningIOReactor;
       5: aload_0
       6: invokespecial #2                  // Method java/lang/Object."<init>":()V
       9: return

  public void execute(org.apache.hc.core5.reactor.ChannelEntry);
    Code:
       0: aload_0
       1: getfield      #1                  // Field this$0:Lorg/apache/hc/core5/reactor/DefaultListeningIOReactor;
       4: aload_1
       5: invokestatic  #3                  // Method org/apache/hc/core5/reactor/DefaultListeningIOReactor.access$000:(Lorg/apache/hc/core5/reactor/DefaultListeningIOReactor;Lorg/apache/hc/core5/reactor/ChannelEntry;)V
       8: return

  public void execute(java.lang.Object);
    Code:
       0: aload_0
       1: aload_1
       2: checkcast     #4                  // class org/apache/hc/core5/reactor/ChannelEntry
       5: invokevirtual #5                  // Method execute:(Lorg/apache/hc/core5/reactor/ChannelEntry;)V
       8: return
}
