Compiled from "ConsumeContext.java"
public class org.joyqueue.client.internal.consumer.interceptor.ConsumeContext {
  private java.lang.String topic;

  private java.lang.String app;

  private org.joyqueue.client.internal.nameserver.NameServerConfig nameserver;

  private java.util.List<org.joyqueue.client.internal.consumer.domain.ConsumeMessage> messages;

  private java.util.Map<java.lang.Object, java.lang.Object> attributes;

  private java.util.Set<org.joyqueue.client.internal.consumer.domain.ConsumeMessage> messageFilter;

  public org.joyqueue.client.internal.consumer.interceptor.ConsumeContext(java.lang.String, java.lang.String, org.joyqueue.client.internal.nameserver.NameServerConfig, java.util.List<org.joyqueue.client.internal.consumer.domain.ConsumeMessage>);
    Code:
       0: aload_0
       1: invokespecial #1                  // Method java/lang/Object."<init>":()V
       4: aload_0
       5: aload_1
       6: putfield      #2                  // Field topic:Ljava/lang/String;
       9: aload_0
      10: aload_2
      11: putfield      #3                  // Field app:Ljava/lang/String;
      14: aload_0
      15: aload_3
      16: putfield      #4                  // Field nameserver:Lorg/joyqueue/client/internal/nameserver/NameServerConfig;
      19: aload_0
      20: aload         4
      22: putfield      #5                  // Field messages:Ljava/util/List;
      25: return

  public java.lang.String getTopic();
    Code:
       0: aload_0
       1: getfield      #2                  // Field topic:Ljava/lang/String;
       4: areturn

  public java.lang.String getApp();
    Code:
       0: aload_0
       1: getfield      #3                  // Field app:Ljava/lang/String;
       4: areturn

  public org.joyqueue.client.internal.nameserver.NameServerConfig getNameserver();
    Code:
       0: aload_0
       1: getfield      #4                  // Field nameserver:Lorg/joyqueue/client/internal/nameserver/NameServerConfig;
       4: areturn

  public java.util.List<org.joyqueue.client.internal.consumer.domain.ConsumeMessage> getMessages();
    Code:
       0: aload_0
       1: getfield      #5                  // Field messages:Ljava/util/List;
       4: areturn

  public java.util.Set<org.joyqueue.client.internal.consumer.domain.ConsumeMessage> getMessageFilter();
    Code:
       0: aload_0
       1: getfield      #6                  // Field messageFilter:Ljava/util/Set;
       4: areturn

  public void filterMessage(org.joyqueue.client.internal.consumer.domain.ConsumeMessage);
    Code:
       0: aload_0
       1: getfield      #6                  // Field messageFilter:Ljava/util/Set;
       4: ifnonnull     14
       7: aload_0
       8: invokestatic  #7                  // Method com/google/common/collect/Sets.newHashSet:()Ljava/util/HashSet;
      11: putfield      #6                  // Field messageFilter:Ljava/util/Set;
      14: aload_0
      15: getfield      #6                  // Field messageFilter:Ljava/util/Set;
      18: aload_1
      19: invokeinterface #8,  2            // InterfaceMethod java/util/Set.add:(Ljava/lang/Object;)Z
      24: pop
      25: return

  public boolean isFilteredMessage(org.joyqueue.client.internal.consumer.domain.ConsumeMessage);
    Code:
       0: aload_0
       1: getfield      #6                  // Field messageFilter:Ljava/util/Set;
       4: ifnonnull     9
       7: iconst_0
       8: ireturn
       9: aload_0
      10: getfield      #6                  // Field messageFilter:Ljava/util/Set;
      13: aload_1
      14: invokeinterface #9,  2            // InterfaceMethod java/util/Set.contains:(Ljava/lang/Object;)Z
      19: ireturn

  public java.util.List<org.joyqueue.client.internal.consumer.domain.ConsumeMessage> getFilteredMessages();
    Code:
       0: aload_0
       1: getfield      #6                  // Field messageFilter:Ljava/util/Set;
       4: ifnonnull     12
       7: aload_0
       8: getfield      #5                  // Field messages:Ljava/util/List;
      11: areturn
      12: aload_0
      13: getfield      #5                  // Field messages:Ljava/util/List;
      16: invokestatic  #10                 // Method com/google/common/collect/Sets.newHashSet:(Ljava/lang/Iterable;)Ljava/util/HashSet;
      19: astore_1
      20: aload_0
      21: getfield      #6                  // Field messageFilter:Ljava/util/Set;
      24: invokeinterface #11,  1           // InterfaceMethod java/util/Set.iterator:()Ljava/util/Iterator;
      29: astore_2
      30: aload_2
      31: invokeinterface #12,  1           // InterfaceMethod java/util/Iterator.hasNext:()Z
      36: ifeq          60
      39: aload_2
      40: invokeinterface #13,  1           // InterfaceMethod java/util/Iterator.next:()Ljava/lang/Object;
      45: checkcast     #14                 // class org/joyqueue/client/internal/consumer/domain/ConsumeMessage
      48: astore_3
      49: aload_1
      50: aload_3
      51: invokeinterface #15,  2           // InterfaceMethod java/util/Set.remove:(Ljava/lang/Object;)Z
      56: pop
      57: goto          30
      60: aload_1
      61: invokestatic  #16                 // Method com/google/common/collect/Lists.newArrayList:(Ljava/lang/Iterable;)Ljava/util/ArrayList;
      64: areturn

  public <T> T getAttribute(java.lang.Object);
    Code:
       0: aload_0
       1: getfield      #17                 // Field attributes:Ljava/util/Map;
       4: ifnonnull     9
       7: aconst_null
       8: areturn
       9: aload_0
      10: getfield      #17                 // Field attributes:Ljava/util/Map;
      13: aload_1
      14: invokeinterface #18,  2           // InterfaceMethod java/util/Map.get:(Ljava/lang/Object;)Ljava/lang/Object;
      19: areturn

  public boolean removeAttribute(java.lang.Object);
    Code:
       0: aload_0
       1: getfield      #17                 // Field attributes:Ljava/util/Map;
       4: ifnonnull     9
       7: iconst_0
       8: ireturn
       9: aload_0
      10: getfield      #17                 // Field attributes:Ljava/util/Map;
      13: aload_1
      14: invokeinterface #19,  2           // InterfaceMethod java/util/Map.remove:(Ljava/lang/Object;)Ljava/lang/Object;
      19: ifnull        26
      22: iconst_1
      23: goto          27
      26: iconst_0
      27: ireturn

  public boolean putAttribute(java.lang.Object, java.lang.Object);
    Code:
       0: aload_0
       1: getfield      #17                 // Field attributes:Ljava/util/Map;
       4: ifnonnull     14
       7: aload_0
       8: invokestatic  #20                 // Method com/google/common/collect/Maps.newLinkedHashMap:()Ljava/util/LinkedHashMap;
      11: putfield      #17                 // Field attributes:Ljava/util/Map;
      14: aload_0
      15: getfield      #17                 // Field attributes:Ljava/util/Map;
      18: aload_1
      19: aload_2
      20: invokeinterface #21,  3           // InterfaceMethod java/util/Map.put:(Ljava/lang/Object;Ljava/lang/Object;)Ljava/lang/Object;
      25: ifnonnull     32
      28: iconst_1
      29: goto          33
      32: iconst_0
      33: ireturn

  public boolean containsAttribute(java.lang.Object);
    Code:
       0: aload_0
       1: getfield      #17                 // Field attributes:Ljava/util/Map;
       4: ifnonnull     9
       7: iconst_0
       8: ireturn
       9: aload_0
      10: getfield      #17                 // Field attributes:Ljava/util/Map;
      13: aload_1
      14: invokeinterface #22,  2           // InterfaceMethod java/util/Map.containsKey:(Ljava/lang/Object;)Z
      19: ireturn

  public java.util.Map<java.lang.Object, java.lang.Object> getAttributes();
    Code:
       0: aload_0
       1: getfield      #17                 // Field attributes:Ljava/util/Map;
       4: areturn
}
