Compiled from "CommandFailedEvent.java"
public final class com.mongodb.event.CommandFailedEvent extends com.mongodb.event.CommandEvent {
  private final long elapsedTimeNanos;

  private final java.lang.Throwable throwable;

  public com.mongodb.event.CommandFailedEvent(int, com.mongodb.connection.ConnectionDescription, java.lang.String, long, java.lang.Throwable);
    Code:
       0: aload_0
       1: iload_1
       2: aload_2
       3: aload_3
       4: invokespecial #1                  // Method com/mongodb/event/CommandEvent."<init>":(ILcom/mongodb/connection/ConnectionDescription;Ljava/lang/String;)V
       7: ldc           #2                  // String elapsed time is not negative
       9: lload         4
      11: lconst_0
      12: lcmp
      13: iflt          20
      16: iconst_1
      17: goto          21
      20: iconst_0
      21: invokestatic  #3                  // Method com/mongodb/assertions/Assertions.isTrueArgument:(Ljava/lang/String;Z)V
      24: aload_0
      25: lload         4
      27: putfield      #4                  // Field elapsedTimeNanos:J
      30: aload_0
      31: aload         6
      33: putfield      #5                  // Field throwable:Ljava/lang/Throwable;
      36: return

  public long getElapsedTime(java.util.concurrent.TimeUnit);
    Code:
       0: aload_1
       1: aload_0
       2: getfield      #4                  // Field elapsedTimeNanos:J
       5: getstatic     #6                  // Field java/util/concurrent/TimeUnit.NANOSECONDS:Ljava/util/concurrent/TimeUnit;
       8: invokevirtual #7                  // Method java/util/concurrent/TimeUnit.convert:(JLjava/util/concurrent/TimeUnit;)J
      11: lreturn

  public java.lang.Throwable getThrowable();
    Code:
       0: aload_0
       1: getfield      #5                  // Field throwable:Ljava/lang/Throwable;
       4: areturn
}
