Compiled from "JBossLoadTimeWeaver.java"
public class org.springframework.instrument.classloading.jboss.JBossLoadTimeWeaver implements org.springframework.instrument.classloading.LoadTimeWeaver {
  private static final java.lang.String DELEGATING_TRANSFORMER_CLASS_NAME;

  private static final java.lang.String WRAPPER_TRANSFORMER_CLASS_NAME;

  private final java.lang.ClassLoader classLoader;

  private final java.lang.Object delegatingTransformer;

  private final java.lang.reflect.Method addTransformer;

  public org.springframework.instrument.classloading.jboss.JBossLoadTimeWeaver();
    Code:
       0: aload_0
       1: invokestatic  #1                  // Method org/springframework/util/ClassUtils.getDefaultClassLoader:()Ljava/lang/ClassLoader;
       4: invokespecial #2                  // Method "<init>":(Ljava/lang/ClassLoader;)V
       7: return

  public org.springframework.instrument.classloading.jboss.JBossLoadTimeWeaver(java.lang.ClassLoader);
    Code:
       0: aload_0
       1: invokespecial #3                  // Method java/lang/Object."<init>":()V
       4: aload_1
       5: ldc           #4                  // String ClassLoader must not be null
       7: invokestatic  #5                  // Method org/springframework/util/Assert.notNull:(Ljava/lang/Object;Ljava/lang/String;)V
      10: aload_0
      11: aload_1
      12: putfield      #6                  // Field classLoader:Ljava/lang/ClassLoader;
      15: aload_1
      16: invokevirtual #7                  // Method java/lang/Object.getClass:()Ljava/lang/Class;
      19: ldc           #8                  // String transformer
      21: invokestatic  #9                  // Method org/springframework/util/ReflectionUtils.findField:(Ljava/lang/Class;Ljava/lang/String;)Ljava/lang/reflect/Field;
      24: astore_2
      25: aload_2
      26: ifnonnull     62
      29: new           #10                 // class java/lang/IllegalArgumentException
      32: dup
      33: new           #11                 // class java/lang/StringBuilder
      36: dup
      37: invokespecial #12                 // Method java/lang/StringBuilder."<init>":()V
      40: ldc           #13                 // String Could not find \'transformer\' field on JBoss ClassLoader:
      42: invokevirtual #14                 // Method java/lang/StringBuilder.append:(Ljava/lang/String;)Ljava/lang/StringBuilder;
      45: aload_1
      46: invokevirtual #7                  // Method java/lang/Object.getClass:()Ljava/lang/Class;
      49: invokevirtual #15                 // Method java/lang/Class.getName:()Ljava/lang/String;
      52: invokevirtual #14                 // Method java/lang/StringBuilder.append:(Ljava/lang/String;)Ljava/lang/StringBuilder;
      55: invokevirtual #16                 // Method java/lang/StringBuilder.toString:()Ljava/lang/String;
      58: invokespecial #17                 // Method java/lang/IllegalArgumentException."<init>":(Ljava/lang/String;)V
      61: athrow
      62: aload_2
      63: iconst_1
      64: invokevirtual #18                 // Method java/lang/reflect/Field.setAccessible:(Z)V
      67: aload_2
      68: aload_1
      69: invokevirtual #19                 // Method java/lang/reflect/Field.get:(Ljava/lang/Object;)Ljava/lang/Object;
      72: astore_3
      73: aload_3
      74: invokevirtual #7                  // Method java/lang/Object.getClass:()Ljava/lang/Class;
      77: invokevirtual #15                 // Method java/lang/Class.getName:()Ljava/lang/String;
      80: ldc           #21                 // String org.jboss.modules.JLIClassTransformer
      82: invokevirtual #22                 // Method java/lang/String.equals:(Ljava/lang/Object;)Z
      85: ifeq          150
      88: aload_3
      89: invokevirtual #7                  // Method java/lang/Object.getClass:()Ljava/lang/Class;
      92: ldc           #8                  // String transformer
      94: invokestatic  #9                  // Method org/springframework/util/ReflectionUtils.findField:(Ljava/lang/Class;Ljava/lang/String;)Ljava/lang/reflect/Field;
      97: astore        4
      99: aload         4
     101: ifnonnull     137
     104: new           #10                 // class java/lang/IllegalArgumentException
     107: dup
     108: new           #11                 // class java/lang/StringBuilder
     111: dup
     112: invokespecial #12                 // Method java/lang/StringBuilder."<init>":()V
     115: ldc           #23                 // String Could not find \'transformer\' field on JBoss JLIClassTransformer:
     117: invokevirtual #14                 // Method java/lang/StringBuilder.append:(Ljava/lang/String;)Ljava/lang/StringBuilder;
     120: aload_3
     121: invokevirtual #7                  // Method java/lang/Object.getClass:()Ljava/lang/Class;
     124: invokevirtual #15                 // Method java/lang/Class.getName:()Ljava/lang/String;
     127: invokevirtual #14                 // Method java/lang/StringBuilder.append:(Ljava/lang/String;)Ljava/lang/StringBuilder;
     130: invokevirtual #16                 // Method java/lang/StringBuilder.toString:()Ljava/lang/String;
     133: invokespecial #17                 // Method java/lang/IllegalArgumentException."<init>":(Ljava/lang/String;)V
     136: athrow
     137: aload         4
     139: iconst_1
     140: invokevirtual #18                 // Method java/lang/reflect/Field.setAccessible:(Z)V
     143: aload         4
     145: aload_3
     146: invokevirtual #19                 // Method java/lang/reflect/Field.get:(Ljava/lang/Object;)Ljava/lang/Object;
     149: astore_3
     150: aload_3
     151: invokevirtual #7                  // Method java/lang/Object.getClass:()Ljava/lang/Class;
     154: invokevirtual #15                 // Method java/lang/Class.getName:()Ljava/lang/String;
     157: ldc           #24                 // String org.jboss.as.server.deployment.module.DelegatingClassFileTransformer
     159: invokevirtual #22                 // Method java/lang/String.equals:(Ljava/lang/Object;)Z
     162: ifne          198
     165: new           #25                 // class java/lang/IllegalStateException
     168: dup
     169: new           #11                 // class java/lang/StringBuilder
     172: dup
     173: invokespecial #12                 // Method java/lang/StringBuilder."<init>":()V
     176: ldc           #26                 // String Transformer not of the expected type DelegatingClassFileTransformer:
     178: invokevirtual #14                 // Method java/lang/StringBuilder.append:(Ljava/lang/String;)Ljava/lang/StringBuilder;
     181: aload_3
     182: invokevirtual #7                  // Method java/lang/Object.getClass:()Ljava/lang/Class;
     185: invokevirtual #15                 // Method java/lang/Class.getName:()Ljava/lang/String;
     188: invokevirtual #14                 // Method java/lang/StringBuilder.append:(Ljava/lang/String;)Ljava/lang/StringBuilder;
     191: invokevirtual #16                 // Method java/lang/StringBuilder.toString:()Ljava/lang/String;
     194: invokespecial #27                 // Method java/lang/IllegalStateException."<init>":(Ljava/lang/String;)V
     197: athrow
     198: aload_0
     199: aload_3
     200: putfield      #28                 // Field delegatingTransformer:Ljava/lang/Object;
     203: aload_0
     204: getfield      #28                 // Field delegatingTransformer:Ljava/lang/Object;
     207: invokevirtual #7                  // Method java/lang/Object.getClass:()Ljava/lang/Class;
     210: ldc           #29                 // String addTransformer
     212: iconst_1
     213: anewarray     #30                 // class java/lang/Class
     216: dup
     217: iconst_0
     218: ldc           #31                 // class java/lang/instrument/ClassFileTransformer
     220: aastore
     221: invokestatic  #32                 // Method org/springframework/util/ReflectionUtils.findMethod:(Ljava/lang/Class;Ljava/lang/String;[Ljava/lang/Class;)Ljava/lang/reflect/Method;
     224: astore        4
     226: aload         4
     228: ifnonnull     267
     231: new           #10                 // class java/lang/IllegalArgumentException
     234: dup
     235: new           #11                 // class java/lang/StringBuilder
     238: dup
     239: invokespecial #12                 // Method java/lang/StringBuilder."<init>":()V
     242: ldc           #33                 // String Could not find \'addTransformer\' method on JBoss DelegatingClassFileTransformer:
     244: invokevirtual #14                 // Method java/lang/StringBuilder.append:(Ljava/lang/String;)Ljava/lang/StringBuilder;
     247: aload_0
     248: getfield      #28                 // Field delegatingTransformer:Ljava/lang/Object;
     251: invokevirtual #7                  // Method java/lang/Object.getClass:()Ljava/lang/Class;
     254: invokevirtual #15                 // Method java/lang/Class.getName:()Ljava/lang/String;
     257: invokevirtual #14                 // Method java/lang/StringBuilder.append:(Ljava/lang/String;)Ljava/lang/StringBuilder;
     260: invokevirtual #16                 // Method java/lang/StringBuilder.toString:()Ljava/lang/String;
     263: invokespecial #17                 // Method java/lang/IllegalArgumentException."<init>":(Ljava/lang/String;)V
     266: athrow
     267: aload         4
     269: iconst_1
     270: invokevirtual #34                 // Method java/lang/reflect/Method.setAccessible:(Z)V
     273: aload_0
     274: aload         4
     276: putfield      #35                 // Field addTransformer:Ljava/lang/reflect/Method;
     279: goto          294
     282: astore_2
     283: new           #25                 // class java/lang/IllegalStateException
     286: dup
     287: ldc           #37                 // String Could not initialize JBoss LoadTimeWeaver
     289: aload_2
     290: invokespecial #38                 // Method java/lang/IllegalStateException."<init>":(Ljava/lang/String;Ljava/lang/Throwable;)V
     293: athrow
     294: return
    Exception table:
       from    to  target type
          15   279   282   Class java/lang/Throwable

  public void addTransformer(java.lang.instrument.ClassFileTransformer);
    Code:
       0: aload_0
       1: getfield      #35                 // Field addTransformer:Ljava/lang/reflect/Method;
       4: aload_0
       5: getfield      #28                 // Field delegatingTransformer:Ljava/lang/Object;
       8: iconst_1
       9: anewarray     #39                 // class java/lang/Object
      12: dup
      13: iconst_0
      14: aload_1
      15: aastore
      16: invokevirtual #40                 // Method java/lang/reflect/Method.invoke:(Ljava/lang/Object;[Ljava/lang/Object;)Ljava/lang/Object;
      19: pop
      20: goto          55
      23: astore_2
      24: new           #25                 // class java/lang/IllegalStateException
      27: dup
      28: new           #11                 // class java/lang/StringBuilder
      31: dup
      32: invokespecial #12                 // Method java/lang/StringBuilder."<init>":()V
      35: ldc           #41                 // String Could not add transformer on JBoss ClassLoader:
      37: invokevirtual #14                 // Method java/lang/StringBuilder.append:(Ljava/lang/String;)Ljava/lang/StringBuilder;
      40: aload_0
      41: getfield      #6                  // Field classLoader:Ljava/lang/ClassLoader;
      44: invokevirtual #42                 // Method java/lang/StringBuilder.append:(Ljava/lang/Object;)Ljava/lang/StringBuilder;
      47: invokevirtual #16                 // Method java/lang/StringBuilder.toString:()Ljava/lang/String;
      50: aload_2
      51: invokespecial #38                 // Method java/lang/IllegalStateException."<init>":(Ljava/lang/String;Ljava/lang/Throwable;)V
      54: athrow
      55: return
    Exception table:
       from    to  target type
           0    20    23   Class java/lang/Throwable

  public java.lang.ClassLoader getInstrumentableClassLoader();
    Code:
       0: aload_0
       1: getfield      #6                  // Field classLoader:Ljava/lang/ClassLoader;
       4: areturn

  public java.lang.ClassLoader getThrowawayClassLoader();
    Code:
       0: new           #43                 // class org/springframework/instrument/classloading/SimpleThrowawayClassLoader
       3: dup
       4: aload_0
       5: invokevirtual #44                 // Method getInstrumentableClassLoader:()Ljava/lang/ClassLoader;
       8: invokespecial #45                 // Method org/springframework/instrument/classloading/SimpleThrowawayClassLoader."<init>":(Ljava/lang/ClassLoader;)V
      11: areturn
}
