Compiled from "DataFormatDetector.java"
public class org.elasticsearch.hadoop.thirdparty.codehaus.jackson.format.DataFormatDetector {
  public static final int DEFAULT_MAX_INPUT_LOOKAHEAD;

  protected final org.elasticsearch.hadoop.thirdparty.codehaus.jackson.JsonFactory[] _detectors;

  protected final org.elasticsearch.hadoop.thirdparty.codehaus.jackson.format.MatchStrength _optimalMatch;

  protected final org.elasticsearch.hadoop.thirdparty.codehaus.jackson.format.MatchStrength _minimalMatch;

  protected final int _maxInputLookahead;

  public org.elasticsearch.hadoop.thirdparty.codehaus.jackson.format.DataFormatDetector(org.elasticsearch.hadoop.thirdparty.codehaus.jackson.JsonFactory...);
    Code:
       0: aload_0
       1: aload_1
       2: getstatic     #26                 // Field org/elasticsearch/hadoop/thirdparty/codehaus/jackson/format/MatchStrength.SOLID_MATCH:Lorg/elasticsearch/hadoop/thirdparty/codehaus/jackson/format/MatchStrength;
       5: getstatic     #29                 // Field org/elasticsearch/hadoop/thirdparty/codehaus/jackson/format/MatchStrength.WEAK_MATCH:Lorg/elasticsearch/hadoop/thirdparty/codehaus/jackson/format/MatchStrength;
       8: bipush        64
      10: invokespecial #32                 // Method "<init>":([Lorg/elasticsearch/hadoop/thirdparty/codehaus/jackson/JsonFactory;Lorg/elasticsearch/hadoop/thirdparty/codehaus/jackson/format/MatchStrength;Lorg/elasticsearch/hadoop/thirdparty/codehaus/jackson/format/MatchStrength;I)V
      13: return

  public org.elasticsearch.hadoop.thirdparty.codehaus.jackson.format.DataFormatDetector(java.util.Collection<org.elasticsearch.hadoop.thirdparty.codehaus.jackson.JsonFactory>);
    Code:
       0: aload_0
       1: aload_1
       2: aload_1
       3: invokeinterface #43,  1           // InterfaceMethod java/util/Collection.size:()I
       8: anewarray     #45                 // class org/elasticsearch/hadoop/thirdparty/codehaus/jackson/JsonFactory
      11: invokeinterface #49,  2           // InterfaceMethod java/util/Collection.toArray:([Ljava/lang/Object;)[Ljava/lang/Object;
      16: checkcast     #50                 // class "[Lorg/elasticsearch/hadoop/thirdparty/codehaus/jackson/JsonFactory;"
      19: invokespecial #52                 // Method "<init>":([Lorg/elasticsearch/hadoop/thirdparty/codehaus/jackson/JsonFactory;)V
      22: return

  public org.elasticsearch.hadoop.thirdparty.codehaus.jackson.format.DataFormatDetector withOptimalMatch(org.elasticsearch.hadoop.thirdparty.codehaus.jackson.format.MatchStrength);
    Code:
       0: aload_1
       1: aload_0
       2: getfield      #58                 // Field _optimalMatch:Lorg/elasticsearch/hadoop/thirdparty/codehaus/jackson/format/MatchStrength;
       5: if_acmpne     10
       8: aload_0
       9: areturn
      10: new           #2                  // class org/elasticsearch/hadoop/thirdparty/codehaus/jackson/format/DataFormatDetector
      13: dup
      14: aload_0
      15: getfield      #60                 // Field _detectors:[Lorg/elasticsearch/hadoop/thirdparty/codehaus/jackson/JsonFactory;
      18: aload_1
      19: aload_0
      20: getfield      #62                 // Field _minimalMatch:Lorg/elasticsearch/hadoop/thirdparty/codehaus/jackson/format/MatchStrength;
      23: aload_0
      24: getfield      #64                 // Field _maxInputLookahead:I
      27: invokespecial #32                 // Method "<init>":([Lorg/elasticsearch/hadoop/thirdparty/codehaus/jackson/JsonFactory;Lorg/elasticsearch/hadoop/thirdparty/codehaus/jackson/format/MatchStrength;Lorg/elasticsearch/hadoop/thirdparty/codehaus/jackson/format/MatchStrength;I)V
      30: areturn

  public org.elasticsearch.hadoop.thirdparty.codehaus.jackson.format.DataFormatDetector withMinimalMatch(org.elasticsearch.hadoop.thirdparty.codehaus.jackson.format.MatchStrength);
    Code:
       0: aload_1
       1: aload_0
       2: getfield      #62                 // Field _minimalMatch:Lorg/elasticsearch/hadoop/thirdparty/codehaus/jackson/format/MatchStrength;
       5: if_acmpne     10
       8: aload_0
       9: areturn
      10: new           #2                  // class org/elasticsearch/hadoop/thirdparty/codehaus/jackson/format/DataFormatDetector
      13: dup
      14: aload_0
      15: getfield      #60                 // Field _detectors:[Lorg/elasticsearch/hadoop/thirdparty/codehaus/jackson/JsonFactory;
      18: aload_0
      19: getfield      #58                 // Field _optimalMatch:Lorg/elasticsearch/hadoop/thirdparty/codehaus/jackson/format/MatchStrength;
      22: aload_1
      23: aload_0
      24: getfield      #64                 // Field _maxInputLookahead:I
      27: invokespecial #32                 // Method "<init>":([Lorg/elasticsearch/hadoop/thirdparty/codehaus/jackson/JsonFactory;Lorg/elasticsearch/hadoop/thirdparty/codehaus/jackson/format/MatchStrength;Lorg/elasticsearch/hadoop/thirdparty/codehaus/jackson/format/MatchStrength;I)V
      30: areturn

  public org.elasticsearch.hadoop.thirdparty.codehaus.jackson.format.DataFormatDetector withMaxInputLookahead(int);
    Code:
       0: iload_1
       1: aload_0
       2: getfield      #64                 // Field _maxInputLookahead:I
       5: if_icmpne     10
       8: aload_0
       9: areturn
      10: new           #2                  // class org/elasticsearch/hadoop/thirdparty/codehaus/jackson/format/DataFormatDetector
      13: dup
      14: aload_0
      15: getfield      #60                 // Field _detectors:[Lorg/elasticsearch/hadoop/thirdparty/codehaus/jackson/JsonFactory;
      18: aload_0
      19: getfield      #58                 // Field _optimalMatch:Lorg/elasticsearch/hadoop/thirdparty/codehaus/jackson/format/MatchStrength;
      22: aload_0
      23: getfield      #62                 // Field _minimalMatch:Lorg/elasticsearch/hadoop/thirdparty/codehaus/jackson/format/MatchStrength;
      26: iload_1
      27: invokespecial #32                 // Method "<init>":([Lorg/elasticsearch/hadoop/thirdparty/codehaus/jackson/JsonFactory;Lorg/elasticsearch/hadoop/thirdparty/codehaus/jackson/format/MatchStrength;Lorg/elasticsearch/hadoop/thirdparty/codehaus/jackson/format/MatchStrength;I)V
      30: areturn

  private org.elasticsearch.hadoop.thirdparty.codehaus.jackson.format.DataFormatDetector(org.elasticsearch.hadoop.thirdparty.codehaus.jackson.JsonFactory[], org.elasticsearch.hadoop.thirdparty.codehaus.jackson.format.MatchStrength, org.elasticsearch.hadoop.thirdparty.codehaus.jackson.format.MatchStrength, int);
    Code:
       0: aload_0
       1: invokespecial #73                 // Method java/lang/Object."<init>":()V
       4: aload_0
       5: aload_1
       6: putfield      #60                 // Field _detectors:[Lorg/elasticsearch/hadoop/thirdparty/codehaus/jackson/JsonFactory;
       9: aload_0
      10: aload_2
      11: putfield      #58                 // Field _optimalMatch:Lorg/elasticsearch/hadoop/thirdparty/codehaus/jackson/format/MatchStrength;
      14: aload_0
      15: aload_3
      16: putfield      #62                 // Field _minimalMatch:Lorg/elasticsearch/hadoop/thirdparty/codehaus/jackson/format/MatchStrength;
      19: aload_0
      20: iload         4
      22: putfield      #64                 // Field _maxInputLookahead:I
      25: return

  public org.elasticsearch.hadoop.thirdparty.codehaus.jackson.format.DataFormatMatcher findFormat(java.io.InputStream) throws java.io.IOException;
    Code:
       0: aload_0
       1: new           #7                  // class org/elasticsearch/hadoop/thirdparty/codehaus/jackson/format/InputAccessor$Std
       4: dup
       5: aload_1
       6: aload_0
       7: getfield      #64                 // Field _maxInputLookahead:I
      10: newarray       byte
      12: invokespecial #81                 // Method org/elasticsearch/hadoop/thirdparty/codehaus/jackson/format/InputAccessor$Std."<init>":(Ljava/io/InputStream;[B)V
      15: invokespecial #85                 // Method _findFormat:(Lorg/elasticsearch/hadoop/thirdparty/codehaus/jackson/format/InputAccessor$Std;)Lorg/elasticsearch/hadoop/thirdparty/codehaus/jackson/format/DataFormatMatcher;
      18: areturn

  public org.elasticsearch.hadoop.thirdparty.codehaus.jackson.format.DataFormatMatcher findFormat(byte[]) throws java.io.IOException;
    Code:
       0: aload_0
       1: new           #7                  // class org/elasticsearch/hadoop/thirdparty/codehaus/jackson/format/InputAccessor$Std
       4: dup
       5: aload_1
       6: invokespecial #91                 // Method org/elasticsearch/hadoop/thirdparty/codehaus/jackson/format/InputAccessor$Std."<init>":([B)V
       9: invokespecial #85                 // Method _findFormat:(Lorg/elasticsearch/hadoop/thirdparty/codehaus/jackson/format/InputAccessor$Std;)Lorg/elasticsearch/hadoop/thirdparty/codehaus/jackson/format/DataFormatMatcher;
      12: areturn

  private org.elasticsearch.hadoop.thirdparty.codehaus.jackson.format.DataFormatMatcher _findFormat(org.elasticsearch.hadoop.thirdparty.codehaus.jackson.format.InputAccessor$Std) throws java.io.IOException;
    Code:
       0: aconst_null
       1: astore_2
       2: aconst_null
       3: astore_3
       4: aload_0
       5: getfield      #60                 // Field _detectors:[Lorg/elasticsearch/hadoop/thirdparty/codehaus/jackson/JsonFactory;
       8: astore        4
      10: aload         4
      12: arraylength
      13: istore        5
      15: iconst_0
      16: istore        6
      18: iload         6
      20: iload         5
      22: if_icmpge     116
      25: aload         4
      27: iload         6
      29: aaload
      30: astore        7
      32: aload_1
      33: invokevirtual #96                 // Method org/elasticsearch/hadoop/thirdparty/codehaus/jackson/format/InputAccessor$Std.reset:()V
      36: aload         7
      38: aload_1
      39: invokevirtual #100                // Method org/elasticsearch/hadoop/thirdparty/codehaus/jackson/JsonFactory.hasFormat:(Lorg/elasticsearch/hadoop/thirdparty/codehaus/jackson/format/InputAccessor;)Lorg/elasticsearch/hadoop/thirdparty/codehaus/jackson/format/MatchStrength;
      42: astore        8
      44: aload         8
      46: ifnull        110
      49: aload         8
      51: invokevirtual #103                // Method org/elasticsearch/hadoop/thirdparty/codehaus/jackson/format/MatchStrength.ordinal:()I
      54: aload_0
      55: getfield      #62                 // Field _minimalMatch:Lorg/elasticsearch/hadoop/thirdparty/codehaus/jackson/format/MatchStrength;
      58: invokevirtual #103                // Method org/elasticsearch/hadoop/thirdparty/codehaus/jackson/format/MatchStrength.ordinal:()I
      61: if_icmpge     67
      64: goto          110
      67: aload_2
      68: ifnull        86
      71: aload_3
      72: invokevirtual #103                // Method org/elasticsearch/hadoop/thirdparty/codehaus/jackson/format/MatchStrength.ordinal:()I
      75: aload         8
      77: invokevirtual #103                // Method org/elasticsearch/hadoop/thirdparty/codehaus/jackson/format/MatchStrength.ordinal:()I
      80: if_icmplt     86
      83: goto          110
      86: aload         7
      88: astore_2
      89: aload         8
      91: astore_3
      92: aload         8
      94: invokevirtual #103                // Method org/elasticsearch/hadoop/thirdparty/codehaus/jackson/format/MatchStrength.ordinal:()I
      97: aload_0
      98: getfield      #58                 // Field _optimalMatch:Lorg/elasticsearch/hadoop/thirdparty/codehaus/jackson/format/MatchStrength;
     101: invokevirtual #103                // Method org/elasticsearch/hadoop/thirdparty/codehaus/jackson/format/MatchStrength.ordinal:()I
     104: if_icmplt     110
     107: goto          116
     110: iinc          6, 1
     113: goto          18
     116: aload_1
     117: aload_2
     118: aload_3
     119: invokevirtual #107                // Method org/elasticsearch/hadoop/thirdparty/codehaus/jackson/format/InputAccessor$Std.createMatcher:(Lorg/elasticsearch/hadoop/thirdparty/codehaus/jackson/JsonFactory;Lorg/elasticsearch/hadoop/thirdparty/codehaus/jackson/format/MatchStrength;)Lorg/elasticsearch/hadoop/thirdparty/codehaus/jackson/format/DataFormatMatcher;
     122: areturn
}
