Compiled from "$AutoValue_AuthenticationConfig.java"
final class org.graylog2.security.$AutoValue_AuthenticationConfig$Builder extends org.graylog2.security.AuthenticationConfig$Builder {
  private java.util.List<java.lang.String> realmOrder;

  private java.util.Set<java.lang.String> disabledRealms;

  org.graylog2.security.$AutoValue_AuthenticationConfig$Builder();
    Code:
       0: aload_0
       1: invokespecial #2                  // Method org/graylog2/security/AuthenticationConfig$Builder."<init>":()V
       4: return

  private org.graylog2.security.$AutoValue_AuthenticationConfig$Builder(org.graylog2.security.AuthenticationConfig);
    Code:
       0: aload_0
       1: invokespecial #2                  // Method org/graylog2/security/AuthenticationConfig$Builder."<init>":()V
       4: aload_0
       5: aload_1
       6: invokevirtual #3                  // Method org/graylog2/security/AuthenticationConfig.realmOrder:()Ljava/util/List;
       9: putfield      #4                  // Field realmOrder:Ljava/util/List;
      12: aload_0
      13: aload_1
      14: invokevirtual #5                  // Method org/graylog2/security/AuthenticationConfig.disabledRealms:()Ljava/util/Set;
      17: putfield      #6                  // Field disabledRealms:Ljava/util/Set;
      20: return

  public org.graylog2.security.AuthenticationConfig$Builder realmOrder(java.util.List<java.lang.String>);
    Code:
       0: aload_1
       1: ifnonnull     14
       4: new           #7                  // class java/lang/NullPointerException
       7: dup
       8: ldc           #8                  // String Null realmOrder
      10: invokespecial #9                  // Method java/lang/NullPointerException."<init>":(Ljava/lang/String;)V
      13: athrow
      14: aload_0
      15: aload_1
      16: putfield      #4                  // Field realmOrder:Ljava/util/List;
      19: aload_0
      20: areturn

  public org.graylog2.security.AuthenticationConfig$Builder disabledRealms(java.util.Set<java.lang.String>);
    Code:
       0: aload_1
       1: ifnonnull     14
       4: new           #7                  // class java/lang/NullPointerException
       7: dup
       8: ldc           #10                 // String Null disabledRealms
      10: invokespecial #9                  // Method java/lang/NullPointerException."<init>":(Ljava/lang/String;)V
      13: athrow
      14: aload_0
      15: aload_1
      16: putfield      #6                  // Field disabledRealms:Ljava/util/Set;
      19: aload_0
      20: areturn

  public org.graylog2.security.AuthenticationConfig build();
    Code:
       0: ldc           #11                 // String
       2: astore_1
       3: aload_0
       4: getfield      #4                  // Field realmOrder:Ljava/util/List;
       7: ifnonnull     30
      10: new           #12                 // class java/lang/StringBuilder
      13: dup
      14: invokespecial #13                 // Method java/lang/StringBuilder."<init>":()V
      17: aload_1
      18: invokevirtual #14                 // Method java/lang/StringBuilder.append:(Ljava/lang/String;)Ljava/lang/StringBuilder;
      21: ldc           #15                 // String  realmOrder
      23: invokevirtual #14                 // Method java/lang/StringBuilder.append:(Ljava/lang/String;)Ljava/lang/StringBuilder;
      26: invokevirtual #16                 // Method java/lang/StringBuilder.toString:()Ljava/lang/String;
      29: astore_1
      30: aload_0
      31: getfield      #6                  // Field disabledRealms:Ljava/util/Set;
      34: ifnonnull     57
      37: new           #12                 // class java/lang/StringBuilder
      40: dup
      41: invokespecial #13                 // Method java/lang/StringBuilder."<init>":()V
      44: aload_1
      45: invokevirtual #14                 // Method java/lang/StringBuilder.append:(Ljava/lang/String;)Ljava/lang/StringBuilder;
      48: ldc           #17                 // String  disabledRealms
      50: invokevirtual #14                 // Method java/lang/StringBuilder.append:(Ljava/lang/String;)Ljava/lang/StringBuilder;
      53: invokevirtual #16                 // Method java/lang/StringBuilder.toString:()Ljava/lang/String;
      56: astore_1
      57: aload_1
      58: invokevirtual #18                 // Method java/lang/String.isEmpty:()Z
      61: ifne          91
      64: new           #19                 // class java/lang/IllegalStateException
      67: dup
      68: new           #12                 // class java/lang/StringBuilder
      71: dup
      72: invokespecial #13                 // Method java/lang/StringBuilder."<init>":()V
      75: ldc           #20                 // String Missing required properties:
      77: invokevirtual #14                 // Method java/lang/StringBuilder.append:(Ljava/lang/String;)Ljava/lang/StringBuilder;
      80: aload_1
      81: invokevirtual #14                 // Method java/lang/StringBuilder.append:(Ljava/lang/String;)Ljava/lang/StringBuilder;
      84: invokevirtual #16                 // Method java/lang/StringBuilder.toString:()Ljava/lang/String;
      87: invokespecial #21                 // Method java/lang/IllegalStateException."<init>":(Ljava/lang/String;)V
      90: athrow
      91: new           #22                 // class org/graylog2/security/AutoValue_AuthenticationConfig
      94: dup
      95: aload_0
      96: getfield      #4                  // Field realmOrder:Ljava/util/List;
      99: aload_0
     100: getfield      #6                  // Field disabledRealms:Ljava/util/Set;
     103: invokespecial #23                 // Method org/graylog2/security/AutoValue_AuthenticationConfig."<init>":(Ljava/util/List;Ljava/util/Set;)V
     106: areturn

  org.graylog2.security.$AutoValue_AuthenticationConfig$Builder(org.graylog2.security.AuthenticationConfig, org.graylog2.security.$AutoValue_AuthenticationConfig$1);
    Code:
       0: aload_0
       1: aload_1
       2: invokespecial #1                  // Method "<init>":(Lorg/graylog2/security/AuthenticationConfig;)V
       5: return
}
