Compiled from "TransformParser.scala"
public class edu.psu.sagnik.research.inkscapesvgprocessing.transformparser.impl.TransformParser implements scala.util.parsing.combinator.RegexParsers {
  private final scala.util.matching.Regex whiteSpace;

  private final scala.util.DynamicVariable<scala.Option<scala.util.parsing.combinator.Parsers$NoSuccess>> scala$util$parsing$combinator$Parsers$$lastNoSuccessVar;

  private volatile scala.util.parsing.combinator.Parsers$Success$ Success$module;

  private volatile boolean bitmap$0;

  private volatile scala.util.parsing.combinator.Parsers$NoSuccess$ NoSuccess$module;

  private volatile scala.util.parsing.combinator.Parsers$Failure$ Failure$module;

  private volatile scala.util.parsing.combinator.Parsers$Error$ Error$module;

  private volatile scala.util.parsing.combinator.Parsers$$tilde$ $tilde$module;

  public static scala.collection.Seq<edu.psu.sagnik.research.inkscapesvgprocessing.transformparser.model.TransformCommand> apply(java.lang.String);
    Code:
       0: getstatic     #18                 // Field edu/psu/sagnik/research/inkscapesvgprocessing/transformparser/impl/TransformParser$.MODULE$:Ledu/psu/sagnik/research/inkscapesvgprocessing/transformparser/impl/TransformParser$;
       3: aload_0
       4: invokevirtual #20                 // Method edu/psu/sagnik/research/inkscapesvgprocessing/transformparser/impl/TransformParser$.apply:(Ljava/lang/String;)Lscala/collection/Seq;
       7: areturn

  public scala.util.matching.Regex whiteSpace();
    Code:
       0: aload_0
       1: getfield      #40                 // Field whiteSpace:Lscala/util/matching/Regex;
       4: areturn

  public scala.util.parsing.combinator.Parsers$Parser scala$util$parsing$combinator$RegexParsers$$super$positioned(scala.Function0);
    Code:
       0: aload_0
       1: aload_1
       2: invokestatic  #50                 // Method scala/util/parsing/combinator/Parsers$class.positioned:(Lscala/util/parsing/combinator/Parsers;Lscala/Function0;)Lscala/util/parsing/combinator/Parsers$Parser;
       5: areturn

  public scala.util.parsing.combinator.Parsers$Parser scala$util$parsing$combinator$RegexParsers$$super$phrase(scala.util.parsing.combinator.Parsers$Parser);
    Code:
       0: aload_0
       1: aload_1
       2: invokestatic  #58                 // Method scala/util/parsing/combinator/Parsers$class.phrase:(Lscala/util/parsing/combinator/Parsers;Lscala/util/parsing/combinator/Parsers$Parser;)Lscala/util/parsing/combinator/Parsers$Parser;
       5: areturn

  public void scala$util$parsing$combinator$RegexParsers$_setter_$whiteSpace_$eq(scala.util.matching.Regex);
    Code:
       0: aload_0
       1: aload_1
       2: putfield      #40                 // Field whiteSpace:Lscala/util/matching/Regex;
       5: return

  public int handleWhiteSpace(java.lang.CharSequence, int);
    Code:
       0: aload_0
       1: aload_1
       2: iload_2
       3: invokestatic  #69                 // Method scala/util/parsing/combinator/RegexParsers$class.handleWhiteSpace:(Lscala/util/parsing/combinator/RegexParsers;Ljava/lang/CharSequence;I)I
       6: ireturn

  public scala.util.parsing.combinator.Parsers$Parser<java.lang.String> literal(java.lang.String);
    Code:
       0: aload_0
       1: aload_1
       2: invokestatic  #78                 // Method scala/util/parsing/combinator/RegexParsers$class.literal:(Lscala/util/parsing/combinator/RegexParsers;Ljava/lang/String;)Lscala/util/parsing/combinator/Parsers$Parser;
       5: areturn

  public scala.util.parsing.combinator.Parsers$Parser<java.lang.String> regex(scala.util.matching.Regex);
    Code:
       0: aload_0
       1: aload_1
       2: invokestatic  #85                 // Method scala/util/parsing/combinator/RegexParsers$class.regex:(Lscala/util/parsing/combinator/RegexParsers;Lscala/util/matching/Regex;)Lscala/util/parsing/combinator/Parsers$Parser;
       5: areturn

  public <T extends scala.util.parsing.input.Positional> scala.util.parsing.combinator.Parsers$Parser<T> positioned(scala.Function0<scala.util.parsing.combinator.Parsers$Parser<T>>);
    Code:
       0: aload_0
       1: aload_1
       2: invokestatic  #89                 // Method scala/util/parsing/combinator/RegexParsers$class.positioned:(Lscala/util/parsing/combinator/RegexParsers;Lscala/Function0;)Lscala/util/parsing/combinator/Parsers$Parser;
       5: areturn

  public <T> scala.util.parsing.combinator.Parsers$Parser<T> phrase(scala.util.parsing.combinator.Parsers$Parser<T>);
    Code:
       0: aload_0
       1: aload_1
       2: invokestatic  #92                 // Method scala/util/parsing/combinator/RegexParsers$class.phrase:(Lscala/util/parsing/combinator/RegexParsers;Lscala/util/parsing/combinator/Parsers$Parser;)Lscala/util/parsing/combinator/Parsers$Parser;
       5: areturn

  public <T> scala.util.parsing.combinator.Parsers$ParseResult<T> parse(scala.util.parsing.combinator.Parsers$Parser<T>, scala.util.parsing.input.Reader<java.lang.Object>);
    Code:
       0: aload_0
       1: aload_1
       2: aload_2
       3: invokestatic  #97                 // Method scala/util/parsing/combinator/RegexParsers$class.parse:(Lscala/util/parsing/combinator/RegexParsers;Lscala/util/parsing/combinator/Parsers$Parser;Lscala/util/parsing/input/Reader;)Lscala/util/parsing/combinator/Parsers$ParseResult;
       6: areturn

  public <T> scala.util.parsing.combinator.Parsers$ParseResult<T> parse(scala.util.parsing.combinator.Parsers$Parser<T>, java.lang.CharSequence);
    Code:
       0: aload_0
       1: aload_1
       2: aload_2
       3: invokestatic  #103                // Method scala/util/parsing/combinator/RegexParsers$class.parse:(Lscala/util/parsing/combinator/RegexParsers;Lscala/util/parsing/combinator/Parsers$Parser;Ljava/lang/CharSequence;)Lscala/util/parsing/combinator/Parsers$ParseResult;
       6: areturn

  public <T> scala.util.parsing.combinator.Parsers$ParseResult<T> parse(scala.util.parsing.combinator.Parsers$Parser<T>, java.io.Reader);
    Code:
       0: aload_0
       1: aload_1
       2: aload_2
       3: invokestatic  #107                // Method scala/util/parsing/combinator/RegexParsers$class.parse:(Lscala/util/parsing/combinator/RegexParsers;Lscala/util/parsing/combinator/Parsers$Parser;Ljava/io/Reader;)Lscala/util/parsing/combinator/Parsers$ParseResult;
       6: areturn

  public <T> scala.util.parsing.combinator.Parsers$ParseResult<T> parseAll(scala.util.parsing.combinator.Parsers$Parser<T>, scala.util.parsing.input.Reader<java.lang.Object>);
    Code:
       0: aload_0
       1: aload_1
       2: aload_2
       3: invokestatic  #111                // Method scala/util/parsing/combinator/RegexParsers$class.parseAll:(Lscala/util/parsing/combinator/RegexParsers;Lscala/util/parsing/combinator/Parsers$Parser;Lscala/util/parsing/input/Reader;)Lscala/util/parsing/combinator/Parsers$ParseResult;
       6: areturn

  public <T> scala.util.parsing.combinator.Parsers$ParseResult<T> parseAll(scala.util.parsing.combinator.Parsers$Parser<T>, java.io.Reader);
    Code:
       0: aload_0
       1: aload_1
       2: aload_2
       3: invokestatic  #113                // Method scala/util/parsing/combinator/RegexParsers$class.parseAll:(Lscala/util/parsing/combinator/RegexParsers;Lscala/util/parsing/combinator/Parsers$Parser;Ljava/io/Reader;)Lscala/util/parsing/combinator/Parsers$ParseResult;
       6: areturn

  public <T> scala.util.parsing.combinator.Parsers$ParseResult<T> parseAll(scala.util.parsing.combinator.Parsers$Parser<T>, java.lang.CharSequence);
    Code:
       0: aload_0
       1: aload_1
       2: aload_2
       3: invokestatic  #115                // Method scala/util/parsing/combinator/RegexParsers$class.parseAll:(Lscala/util/parsing/combinator/RegexParsers;Lscala/util/parsing/combinator/Parsers$Parser;Ljava/lang/CharSequence;)Lscala/util/parsing/combinator/Parsers$ParseResult;
       6: areturn

  private scala.util.parsing.combinator.Parsers$Success$ Success$lzycompute();
    Code:
       0: aload_0
       1: dup
       2: astore_1
       3: monitorenter
       4: aload_0
       5: getfield      #119                // Field Success$module:Lscala/util/parsing/combinator/Parsers$Success$;
       8: ifnonnull     23
      11: aload_0
      12: new           #121                // class scala/util/parsing/combinator/Parsers$Success$
      15: dup
      16: aload_0
      17: invokespecial #125                // Method scala/util/parsing/combinator/Parsers$Success$."<init>":(Lscala/util/parsing/combinator/Parsers;)V
      20: putfield      #119                // Field Success$module:Lscala/util/parsing/combinator/Parsers$Success$;
      23: getstatic     #131                // Field scala/runtime/BoxedUnit.UNIT:Lscala/runtime/BoxedUnit;
      26: pop
      27: aload_1
      28: monitorexit
      29: aconst_null
      30: pop
      31: aload_0
      32: getfield      #119                // Field Success$module:Lscala/util/parsing/combinator/Parsers$Success$;
      35: areturn
      36: aload_1
      37: monitorexit
      38: athrow
    Exception table:
       from    to  target type
           4    29    36   any

  public scala.util.parsing.combinator.Parsers$Success$ Success();
    Code:
       0: aload_0
       1: getfield      #119                // Field Success$module:Lscala/util/parsing/combinator/Parsers$Success$;
       4: ifnonnull     14
       7: aload_0
       8: invokespecial #136                // Method Success$lzycompute:()Lscala/util/parsing/combinator/Parsers$Success$;
      11: goto          18
      14: aload_0
      15: getfield      #119                // Field Success$module:Lscala/util/parsing/combinator/Parsers$Success$;
      18: areturn

  private scala.util.DynamicVariable scala$util$parsing$combinator$Parsers$$lastNoSuccessVar$lzycompute();
    Code:
       0: aload_0
       1: dup
       2: astore_1
       3: monitorenter
       4: aload_0
       5: getfield      #140                // Field bitmap$0:Z
       8: ifne          24
      11: aload_0
      12: aload_0
      13: invokestatic  #143                // Method scala/util/parsing/combinator/Parsers$class.scala$util$parsing$combinator$Parsers$$lastNoSuccessVar:(Lscala/util/parsing/combinator/Parsers;)Lscala/util/DynamicVariable;
      16: putfield      #145                // Field scala$util$parsing$combinator$Parsers$$lastNoSuccessVar:Lscala/util/DynamicVariable;
      19: aload_0
      20: iconst_1
      21: putfield      #140                // Field bitmap$0:Z
      24: getstatic     #131                // Field scala/runtime/BoxedUnit.UNIT:Lscala/runtime/BoxedUnit;
      27: pop
      28: aload_1
      29: monitorexit
      30: aload_0
      31: getfield      #145                // Field scala$util$parsing$combinator$Parsers$$lastNoSuccessVar:Lscala/util/DynamicVariable;
      34: areturn
      35: aload_1
      36: monitorexit
      37: athrow
    Exception table:
       from    to  target type
           4    30    35   any

  public scala.util.DynamicVariable<scala.Option<scala.util.parsing.combinator.Parsers$NoSuccess>> scala$util$parsing$combinator$Parsers$$lastNoSuccessVar();
    Code:
       0: aload_0
       1: getfield      #140                // Field bitmap$0:Z
       4: ifeq          14
       7: aload_0
       8: getfield      #145                // Field scala$util$parsing$combinator$Parsers$$lastNoSuccessVar:Lscala/util/DynamicVariable;
      11: goto          18
      14: aload_0
      15: invokespecial #147                // Method scala$util$parsing$combinator$Parsers$$lastNoSuccessVar$lzycompute:()Lscala/util/DynamicVariable;
      18: areturn

  private scala.util.parsing.combinator.Parsers$NoSuccess$ NoSuccess$lzycompute();
    Code:
       0: aload_0
       1: dup
       2: astore_1
       3: monitorenter
       4: aload_0
       5: getfield      #153                // Field NoSuccess$module:Lscala/util/parsing/combinator/Parsers$NoSuccess$;
       8: ifnonnull     23
      11: aload_0
      12: new           #155                // class scala/util/parsing/combinator/Parsers$NoSuccess$
      15: dup
      16: aload_0
      17: invokespecial #156                // Method scala/util/parsing/combinator/Parsers$NoSuccess$."<init>":(Lscala/util/parsing/combinator/Parsers;)V
      20: putfield      #153                // Field NoSuccess$module:Lscala/util/parsing/combinator/Parsers$NoSuccess$;
      23: getstatic     #131                // Field scala/runtime/BoxedUnit.UNIT:Lscala/runtime/BoxedUnit;
      26: pop
      27: aload_1
      28: monitorexit
      29: aconst_null
      30: pop
      31: aload_0
      32: getfield      #153                // Field NoSuccess$module:Lscala/util/parsing/combinator/Parsers$NoSuccess$;
      35: areturn
      36: aload_1
      37: monitorexit
      38: athrow
    Exception table:
       from    to  target type
           4    29    36   any

  public scala.util.parsing.combinator.Parsers$NoSuccess$ NoSuccess();
    Code:
       0: aload_0
       1: getfield      #153                // Field NoSuccess$module:Lscala/util/parsing/combinator/Parsers$NoSuccess$;
       4: ifnonnull     14
       7: aload_0
       8: invokespecial #159                // Method NoSuccess$lzycompute:()Lscala/util/parsing/combinator/Parsers$NoSuccess$;
      11: goto          18
      14: aload_0
      15: getfield      #153                // Field NoSuccess$module:Lscala/util/parsing/combinator/Parsers$NoSuccess$;
      18: areturn

  private scala.util.parsing.combinator.Parsers$Failure$ Failure$lzycompute();
    Code:
       0: aload_0
       1: dup
       2: astore_1
       3: monitorenter
       4: aload_0
       5: getfield      #163                // Field Failure$module:Lscala/util/parsing/combinator/Parsers$Failure$;
       8: ifnonnull     23
      11: aload_0
      12: new           #165                // class scala/util/parsing/combinator/Parsers$Failure$
      15: dup
      16: aload_0
      17: invokespecial #166                // Method scala/util/parsing/combinator/Parsers$Failure$."<init>":(Lscala/util/parsing/combinator/Parsers;)V
      20: putfield      #163                // Field Failure$module:Lscala/util/parsing/combinator/Parsers$Failure$;
      23: getstatic     #131                // Field scala/runtime/BoxedUnit.UNIT:Lscala/runtime/BoxedUnit;
      26: pop
      27: aload_1
      28: monitorexit
      29: aconst_null
      30: pop
      31: aload_0
      32: getfield      #163                // Field Failure$module:Lscala/util/parsing/combinator/Parsers$Failure$;
      35: areturn
      36: aload_1
      37: monitorexit
      38: athrow
    Exception table:
       from    to  target type
           4    29    36   any

  public scala.util.parsing.combinator.Parsers$Failure$ Failure();
    Code:
       0: aload_0
       1: getfield      #163                // Field Failure$module:Lscala/util/parsing/combinator/Parsers$Failure$;
       4: ifnonnull     14
       7: aload_0
       8: invokespecial #169                // Method Failure$lzycompute:()Lscala/util/parsing/combinator/Parsers$Failure$;
      11: goto          18
      14: aload_0
      15: getfield      #163                // Field Failure$module:Lscala/util/parsing/combinator/Parsers$Failure$;
      18: areturn

  private scala.util.parsing.combinator.Parsers$Error$ Error$lzycompute();
    Code:
       0: aload_0
       1: dup
       2: astore_1
       3: monitorenter
       4: aload_0
       5: getfield      #173                // Field Error$module:Lscala/util/parsing/combinator/Parsers$Error$;
       8: ifnonnull     23
      11: aload_0
      12: new           #175                // class scala/util/parsing/combinator/Parsers$Error$
      15: dup
      16: aload_0
      17: invokespecial #176                // Method scala/util/parsing/combinator/Parsers$Error$."<init>":(Lscala/util/parsing/combinator/Parsers;)V
      20: putfield      #173                // Field Error$module:Lscala/util/parsing/combinator/Parsers$Error$;
      23: getstatic     #131                // Field scala/runtime/BoxedUnit.UNIT:Lscala/runtime/BoxedUnit;
      26: pop
      27: aload_1
      28: monitorexit
      29: aconst_null
      30: pop
      31: aload_0
      32: getfield      #173                // Field Error$module:Lscala/util/parsing/combinator/Parsers$Error$;
      35: areturn
      36: aload_1
      37: monitorexit
      38: athrow
    Exception table:
       from    to  target type
           4    29    36   any

  public scala.util.parsing.combinator.Parsers$Error$ Error();
    Code:
       0: aload_0
       1: getfield      #173                // Field Error$module:Lscala/util/parsing/combinator/Parsers$Error$;
       4: ifnonnull     14
       7: aload_0
       8: invokespecial #179                // Method Error$lzycompute:()Lscala/util/parsing/combinator/Parsers$Error$;
      11: goto          18
      14: aload_0
      15: getfield      #173                // Field Error$module:Lscala/util/parsing/combinator/Parsers$Error$;
      18: areturn

  private scala.util.parsing.combinator.Parsers$$tilde$ $tilde$lzycompute();
    Code:
       0: aload_0
       1: dup
       2: astore_1
       3: monitorenter
       4: aload_0
       5: getfield      #183                // Field $tilde$module:Lscala/util/parsing/combinator/Parsers$$tilde$;
       8: ifnonnull     23
      11: aload_0
      12: new           #185                // class scala/util/parsing/combinator/Parsers$$tilde$
      15: dup
      16: aload_0
      17: invokespecial #186                // Method scala/util/parsing/combinator/Parsers$$tilde$."<init>":(Lscala/util/parsing/combinator/Parsers;)V
      20: putfield      #183                // Field $tilde$module:Lscala/util/parsing/combinator/Parsers$$tilde$;
      23: getstatic     #131                // Field scala/runtime/BoxedUnit.UNIT:Lscala/runtime/BoxedUnit;
      26: pop
      27: aload_1
      28: monitorexit
      29: aconst_null
      30: pop
      31: aload_0
      32: getfield      #183                // Field $tilde$module:Lscala/util/parsing/combinator/Parsers$$tilde$;
      35: areturn
      36: aload_1
      37: monitorexit
      38: athrow
    Exception table:
       from    to  target type
           4    29    36   any

  public scala.util.parsing.combinator.Parsers$$tilde$ $tilde();
    Code:
       0: aload_0
       1: getfield      #183                // Field $tilde$module:Lscala/util/parsing/combinator/Parsers$$tilde$;
       4: ifnonnull     14
       7: aload_0
       8: invokespecial #189                // Method $tilde$lzycompute:()Lscala/util/parsing/combinator/Parsers$$tilde$;
      11: goto          18
      14: aload_0
      15: getfield      #183                // Field $tilde$module:Lscala/util/parsing/combinator/Parsers$$tilde$;
      18: areturn

  public <T> scala.util.parsing.combinator.Parsers$Parser<T> Parser(scala.Function1<scala.util.parsing.input.Reader<java.lang.Object>, scala.util.parsing.combinator.Parsers$ParseResult<T>>);
    Code:
       0: aload_0
       1: aload_1
       2: invokestatic  #194                // Method scala/util/parsing/combinator/Parsers$class.Parser:(Lscala/util/parsing/combinator/Parsers;Lscala/Function1;)Lscala/util/parsing/combinator/Parsers$Parser;
       5: areturn

  public <T> scala.util.parsing.combinator.Parsers$Parser<T> OnceParser(scala.Function1<scala.util.parsing.input.Reader<java.lang.Object>, scala.util.parsing.combinator.Parsers$ParseResult<T>>);
    Code:
       0: aload_0
       1: aload_1
       2: invokestatic  #201                // Method scala/util/parsing/combinator/Parsers$class.OnceParser:(Lscala/util/parsing/combinator/Parsers;Lscala/Function1;)Lscala/util/parsing/combinator/Parsers$OnceParser;
       5: areturn

  public <T> scala.util.parsing.combinator.Parsers$Parser<T> commit(scala.Function0<scala.util.parsing.combinator.Parsers$Parser<T>>);
    Code:
       0: aload_0
       1: aload_1
       2: invokestatic  #204                // Method scala/util/parsing/combinator/Parsers$class.commit:(Lscala/util/parsing/combinator/Parsers;Lscala/Function0;)Lscala/util/parsing/combinator/Parsers$Parser;
       5: areturn

  public scala.util.parsing.combinator.Parsers$Parser<java.lang.Object> elem(java.lang.String, scala.Function1<java.lang.Object, java.lang.Object>);
    Code:
       0: aload_0
       1: aload_1
       2: aload_2
       3: invokestatic  #209                // Method scala/util/parsing/combinator/Parsers$class.elem:(Lscala/util/parsing/combinator/Parsers;Ljava/lang/String;Lscala/Function1;)Lscala/util/parsing/combinator/Parsers$Parser;
       6: areturn

  public scala.util.parsing.combinator.Parsers$Parser<java.lang.Object> elem(java.lang.Object);
    Code:
       0: aload_0
       1: aload_1
       2: invokestatic  #214                // Method scala/util/parsing/combinator/Parsers$class.elem:(Lscala/util/parsing/combinator/Parsers;Ljava/lang/Object;)Lscala/util/parsing/combinator/Parsers$Parser;
       5: areturn

  public scala.util.parsing.combinator.Parsers$Parser<java.lang.Object> accept(java.lang.Object);
    Code:
       0: aload_0
       1: aload_1
       2: invokestatic  #219                // Method scala/util/parsing/combinator/Parsers$class.accept:(Lscala/util/parsing/combinator/Parsers;Ljava/lang/Object;)Lscala/util/parsing/combinator/Parsers$Parser;
       5: areturn

  public <ES> scala.util.parsing.combinator.Parsers$Parser<scala.collection.immutable.List<java.lang.Object>> accept(ES, scala.Function1<ES, scala.collection.immutable.List<java.lang.Object>>);
    Code:
       0: aload_0
       1: aload_1
       2: aload_2
       3: invokestatic  #223                // Method scala/util/parsing/combinator/Parsers$class.accept:(Lscala/util/parsing/combinator/Parsers;Ljava/lang/Object;Lscala/Function1;)Lscala/util/parsing/combinator/Parsers$Parser;
       6: areturn

  public <U> scala.util.parsing.combinator.Parsers$Parser<U> accept(java.lang.String, scala.PartialFunction<java.lang.Object, U>);
    Code:
       0: aload_0
       1: aload_1
       2: aload_2
       3: invokestatic  #229                // Method scala/util/parsing/combinator/Parsers$class.accept:(Lscala/util/parsing/combinator/Parsers;Ljava/lang/String;Lscala/PartialFunction;)Lscala/util/parsing/combinator/Parsers$Parser;
       6: areturn

  public scala.util.parsing.combinator.Parsers$Parser<java.lang.Object> acceptIf(scala.Function1<java.lang.Object, java.lang.Object>, scala.Function1<java.lang.Object, java.lang.String>);
    Code:
       0: aload_0
       1: aload_1
       2: aload_2
       3: invokestatic  #236                // Method scala/util/parsing/combinator/Parsers$class.acceptIf:(Lscala/util/parsing/combinator/Parsers;Lscala/Function1;Lscala/Function1;)Lscala/util/parsing/combinator/Parsers$Parser;
       6: areturn

  public <U> scala.util.parsing.combinator.Parsers$Parser<U> acceptMatch(java.lang.String, scala.PartialFunction<java.lang.Object, U>);
    Code:
       0: aload_0
       1: aload_1
       2: aload_2
       3: invokestatic  #240                // Method scala/util/parsing/combinator/Parsers$class.acceptMatch:(Lscala/util/parsing/combinator/Parsers;Ljava/lang/String;Lscala/PartialFunction;)Lscala/util/parsing/combinator/Parsers$Parser;
       6: areturn

  public <ES> scala.util.parsing.combinator.Parsers$Parser<scala.collection.immutable.List<java.lang.Object>> acceptSeq(ES, scala.Function1<ES, scala.collection.Iterable<java.lang.Object>>);
    Code:
       0: aload_0
       1: aload_1
       2: aload_2
       3: invokestatic  #243                // Method scala/util/parsing/combinator/Parsers$class.acceptSeq:(Lscala/util/parsing/combinator/Parsers;Ljava/lang/Object;Lscala/Function1;)Lscala/util/parsing/combinator/Parsers$Parser;
       6: areturn

  public scala.util.parsing.combinator.Parsers$Parser<scala.runtime.Nothing$> failure(java.lang.String);
    Code:
       0: aload_0
       1: aload_1
       2: invokestatic  #248                // Method scala/util/parsing/combinator/Parsers$class.failure:(Lscala/util/parsing/combinator/Parsers;Ljava/lang/String;)Lscala/util/parsing/combinator/Parsers$Parser;
       5: areturn

  public scala.util.parsing.combinator.Parsers$Parser<scala.runtime.Nothing$> err(java.lang.String);
    Code:
       0: aload_0
       1: aload_1
       2: invokestatic  #251                // Method scala/util/parsing/combinator/Parsers$class.err:(Lscala/util/parsing/combinator/Parsers;Ljava/lang/String;)Lscala/util/parsing/combinator/Parsers$Parser;
       5: areturn

  public <T> scala.util.parsing.combinator.Parsers$Parser<T> success(T);
    Code:
       0: aload_0
       1: aload_1
       2: invokestatic  #254                // Method scala/util/parsing/combinator/Parsers$class.success:(Lscala/util/parsing/combinator/Parsers;Ljava/lang/Object;)Lscala/util/parsing/combinator/Parsers$Parser;
       5: areturn

  public <T> scala.util.parsing.combinator.Parsers$Parser<T> log(scala.Function0<scala.util.parsing.combinator.Parsers$Parser<T>>, java.lang.String);
    Code:
       0: aload_0
       1: aload_1
       2: aload_2
       3: invokestatic  #260                // Method scala/util/parsing/combinator/Parsers$class.log:(Lscala/util/parsing/combinator/Parsers;Lscala/Function0;Ljava/lang/String;)Lscala/util/parsing/combinator/Parsers$Parser;
       6: areturn

  public <T> scala.util.parsing.combinator.Parsers$Parser<scala.collection.immutable.List<T>> rep(scala.Function0<scala.util.parsing.combinator.Parsers$Parser<T>>);
    Code:
       0: aload_0
       1: aload_1
       2: invokestatic  #264                // Method scala/util/parsing/combinator/Parsers$class.rep:(Lscala/util/parsing/combinator/Parsers;Lscala/Function0;)Lscala/util/parsing/combinator/Parsers$Parser;
       5: areturn

  public <T> scala.util.parsing.combinator.Parsers$Parser<scala.collection.immutable.List<T>> repsep(scala.Function0<scala.util.parsing.combinator.Parsers$Parser<T>>, scala.Function0<scala.util.parsing.combinator.Parsers$Parser<java.lang.Object>>);
    Code:
       0: aload_0
       1: aload_1
       2: aload_2
       3: invokestatic  #269                // Method scala/util/parsing/combinator/Parsers$class.repsep:(Lscala/util/parsing/combinator/Parsers;Lscala/Function0;Lscala/Function0;)Lscala/util/parsing/combinator/Parsers$Parser;
       6: areturn

  public <T> scala.util.parsing.combinator.Parsers$Parser<scala.collection.immutable.List<T>> rep1(scala.Function0<scala.util.parsing.combinator.Parsers$Parser<T>>);
    Code:
       0: aload_0
       1: aload_1
       2: invokestatic  #273                // Method scala/util/parsing/combinator/Parsers$class.rep1:(Lscala/util/parsing/combinator/Parsers;Lscala/Function0;)Lscala/util/parsing/combinator/Parsers$Parser;
       5: areturn

  public <T> scala.util.parsing.combinator.Parsers$Parser<scala.collection.immutable.List<T>> rep1(scala.Function0<scala.util.parsing.combinator.Parsers$Parser<T>>, scala.Function0<scala.util.parsing.combinator.Parsers$Parser<T>>);
    Code:
       0: aload_0
       1: aload_1
       2: aload_2
       3: invokestatic  #275                // Method scala/util/parsing/combinator/Parsers$class.rep1:(Lscala/util/parsing/combinator/Parsers;Lscala/Function0;Lscala/Function0;)Lscala/util/parsing/combinator/Parsers$Parser;
       6: areturn

  public <T> scala.util.parsing.combinator.Parsers$Parser<scala.collection.immutable.List<T>> repN(int, scala.Function0<scala.util.parsing.combinator.Parsers$Parser<T>>);
    Code:
       0: aload_0
       1: iload_1
       2: aload_2
       3: invokestatic  #282                // Method scala/util/parsing/combinator/Parsers$class.repN:(Lscala/util/parsing/combinator/Parsers;ILscala/Function0;)Lscala/util/parsing/combinator/Parsers$Parser;
       6: areturn

  public <T> scala.util.parsing.combinator.Parsers$Parser<scala.collection.immutable.List<T>> rep1sep(scala.Function0<scala.util.parsing.combinator.Parsers$Parser<T>>, scala.Function0<scala.util.parsing.combinator.Parsers$Parser<java.lang.Object>>);
    Code:
       0: aload_0
       1: aload_1
       2: aload_2
       3: invokestatic  #286                // Method scala/util/parsing/combinator/Parsers$class.rep1sep:(Lscala/util/parsing/combinator/Parsers;Lscala/Function0;Lscala/Function0;)Lscala/util/parsing/combinator/Parsers$Parser;
       6: areturn

  public <T> scala.util.parsing.combinator.Parsers$Parser<T> chainl1(scala.Function0<scala.util.parsing.combinator.Parsers$Parser<T>>, scala.Function0<scala.util.parsing.combinator.Parsers$Parser<scala.Function2<T, T, T>>>);
    Code:
       0: aload_0
       1: aload_1
       2: aload_2
       3: invokestatic  #289                // Method scala/util/parsing/combinator/Parsers$class.chainl1:(Lscala/util/parsing/combinator/Parsers;Lscala/Function0;Lscala/Function0;)Lscala/util/parsing/combinator/Parsers$Parser;
       6: areturn

  public <T, U> scala.util.parsing.combinator.Parsers$Parser<T> chainl1(scala.Function0<scala.util.parsing.combinator.Parsers$Parser<T>>, scala.Function0<scala.util.parsing.combinator.Parsers$Parser<U>>, scala.Function0<scala.util.parsing.combinator.Parsers$Parser<scala.Function2<T, U, T>>>);
    Code:
       0: aload_0
       1: aload_1
       2: aload_2
       3: aload_3
       4: invokestatic  #293                // Method scala/util/parsing/combinator/Parsers$class.chainl1:(Lscala/util/parsing/combinator/Parsers;Lscala/Function0;Lscala/Function0;Lscala/Function0;)Lscala/util/parsing/combinator/Parsers$Parser;
       7: areturn

  public <T, U> scala.util.parsing.combinator.Parsers$Parser<U> chainr1(scala.Function0<scala.util.parsing.combinator.Parsers$Parser<T>>, scala.Function0<scala.util.parsing.combinator.Parsers$Parser<scala.Function2<T, U, U>>>, scala.Function2<T, U, U>, U);
    Code:
       0: aload_0
       1: aload_1
       2: aload_2
       3: aload_3
       4: aload         4
       6: invokestatic  #298                // Method scala/util/parsing/combinator/Parsers$class.chainr1:(Lscala/util/parsing/combinator/Parsers;Lscala/Function0;Lscala/Function0;Lscala/Function2;Ljava/lang/Object;)Lscala/util/parsing/combinator/Parsers$Parser;
       9: areturn

  public <T> scala.util.parsing.combinator.Parsers$Parser<scala.Option<T>> opt(scala.Function0<scala.util.parsing.combinator.Parsers$Parser<T>>);
    Code:
       0: aload_0
       1: aload_1
       2: invokestatic  #303                // Method scala/util/parsing/combinator/Parsers$class.opt:(Lscala/util/parsing/combinator/Parsers;Lscala/Function0;)Lscala/util/parsing/combinator/Parsers$Parser;
       5: areturn

  public <T> scala.util.parsing.combinator.Parsers$Parser<scala.runtime.BoxedUnit> not(scala.Function0<scala.util.parsing.combinator.Parsers$Parser<T>>);
    Code:
       0: aload_0
       1: aload_1
       2: invokestatic  #306                // Method scala/util/parsing/combinator/Parsers$class.not:(Lscala/util/parsing/combinator/Parsers;Lscala/Function0;)Lscala/util/parsing/combinator/Parsers$Parser;
       5: areturn

  public <T> scala.util.parsing.combinator.Parsers$Parser<T> guard(scala.Function0<scala.util.parsing.combinator.Parsers$Parser<T>>);
    Code:
       0: aload_0
       1: aload_1
       2: invokestatic  #309                // Method scala/util/parsing/combinator/Parsers$class.guard:(Lscala/util/parsing/combinator/Parsers;Lscala/Function0;)Lscala/util/parsing/combinator/Parsers$Parser;
       5: areturn

  public <T> scala.Function1<scala.util.parsing.combinator.Parsers$$tilde<T, scala.collection.immutable.List<T>>, scala.collection.immutable.List<T>> mkList();
    Code:
       0: aload_0
       1: invokestatic  #314                // Method scala/util/parsing/combinator/Parsers$class.mkList:(Lscala/util/parsing/combinator/Parsers;)Lscala/Function1;
       4: areturn

  public boolean skipWhitespace();
    Code:
       0: iconst_0
       1: ireturn

  public scala.util.parsing.combinator.Parsers$Parser<java.lang.String> wsp();
    Code:
       0: aload_0
       1: new           #320                // class scala/collection/immutable/StringOps
       4: dup
       5: getstatic     #325                // Field scala/Predef$.MODULE$:Lscala/Predef$;
       8: ldc_w         #327                // String \\s|\\n
      11: invokevirtual #331                // Method scala/Predef$.augmentString:(Ljava/lang/String;)Ljava/lang/String;
      14: invokespecial #334                // Method scala/collection/immutable/StringOps."<init>":(Ljava/lang/String;)V
      17: invokevirtual #336                // Method scala/collection/immutable/StringOps.r:()Lscala/util/matching/Regex;
      20: invokevirtual #338                // Method regex:(Lscala/util/matching/Regex;)Lscala/util/parsing/combinator/Parsers$Parser;
      23: new           #340                // class edu/psu/sagnik/research/inkscapesvgprocessing/transformparser/impl/TransformParser$$anonfun$wsp$1
      26: dup
      27: aload_0
      28: invokespecial #343                // Method edu/psu/sagnik/research/inkscapesvgprocessing/transformparser/impl/TransformParser$$anonfun$wsp$1."<init>":(Ledu/psu/sagnik/research/inkscapesvgprocessing/transformparser/impl/TransformParser;)V
      31: invokevirtual #348                // Method scala/util/parsing/combinator/Parsers$Parser.$up$up:(Lscala/Function1;)Lscala/util/parsing/combinator/Parsers$Parser;
      34: areturn

  public scala.util.parsing.combinator.Parsers$Parser<java.lang.String> digit();
    Code:
       0: aload_0
       1: new           #320                // class scala/collection/immutable/StringOps
       4: dup
       5: getstatic     #325                // Field scala/Predef$.MODULE$:Lscala/Predef$;
       8: ldc_w         #351                // String 0|1|2|3|4|5|6|7|8|9
      11: invokevirtual #331                // Method scala/Predef$.augmentString:(Ljava/lang/String;)Ljava/lang/String;
      14: invokespecial #334                // Method scala/collection/immutable/StringOps."<init>":(Ljava/lang/String;)V
      17: invokevirtual #336                // Method scala/collection/immutable/StringOps.r:()Lscala/util/matching/Regex;
      20: invokevirtual #338                // Method regex:(Lscala/util/matching/Regex;)Lscala/util/parsing/combinator/Parsers$Parser;
      23: new           #353                // class edu/psu/sagnik/research/inkscapesvgprocessing/transformparser/impl/TransformParser$$anonfun$digit$1
      26: dup
      27: aload_0
      28: invokespecial #354                // Method edu/psu/sagnik/research/inkscapesvgprocessing/transformparser/impl/TransformParser$$anonfun$digit$1."<init>":(Ledu/psu/sagnik/research/inkscapesvgprocessing/transformparser/impl/TransformParser;)V
      31: invokevirtual #348                // Method scala/util/parsing/combinator/Parsers$Parser.$up$up:(Lscala/Function1;)Lscala/util/parsing/combinator/Parsers$Parser;
      34: areturn

  public scala.util.parsing.combinator.Parsers$Parser<java.lang.String> digit_sequence();
    Code:
       0: aload_0
       1: invokevirtual #357                // Method digit:()Lscala/util/parsing/combinator/Parsers$Parser;
       4: new           #359                // class edu/psu/sagnik/research/inkscapesvgprocessing/transformparser/impl/TransformParser$$anonfun$digit_sequence$1
       7: dup
       8: aload_0
       9: invokespecial #360                // Method edu/psu/sagnik/research/inkscapesvgprocessing/transformparser/impl/TransformParser$$anonfun$digit_sequence$1."<init>":(Ledu/psu/sagnik/research/inkscapesvgprocessing/transformparser/impl/TransformParser;)V
      12: invokevirtual #362                // Method scala/util/parsing/combinator/Parsers$Parser.$tilde:(Lscala/Function0;)Lscala/util/parsing/combinator/Parsers$Parser;
      15: new           #364                // class edu/psu/sagnik/research/inkscapesvgprocessing/transformparser/impl/TransformParser$$anonfun$digit_sequence$2
      18: dup
      19: aload_0
      20: invokespecial #365                // Method edu/psu/sagnik/research/inkscapesvgprocessing/transformparser/impl/TransformParser$$anonfun$digit_sequence$2."<init>":(Ledu/psu/sagnik/research/inkscapesvgprocessing/transformparser/impl/TransformParser;)V
      23: invokevirtual #348                // Method scala/util/parsing/combinator/Parsers$Parser.$up$up:(Lscala/Function1;)Lscala/util/parsing/combinator/Parsers$Parser;
      26: areturn

  public scala.util.parsing.combinator.Parsers$Parser<java.lang.String> sign();
    Code:
       0: aload_0
       1: new           #320                // class scala/collection/immutable/StringOps
       4: dup
       5: getstatic     #325                // Field scala/Predef$.MODULE$:Lscala/Predef$;
       8: ldc_w         #368                // String \\+|\\-
      11: invokevirtual #331                // Method scala/Predef$.augmentString:(Ljava/lang/String;)Ljava/lang/String;
      14: invokespecial #334                // Method scala/collection/immutable/StringOps."<init>":(Ljava/lang/String;)V
      17: invokevirtual #336                // Method scala/collection/immutable/StringOps.r:()Lscala/util/matching/Regex;
      20: invokevirtual #338                // Method regex:(Lscala/util/matching/Regex;)Lscala/util/parsing/combinator/Parsers$Parser;
      23: new           #370                // class edu/psu/sagnik/research/inkscapesvgprocessing/transformparser/impl/TransformParser$$anonfun$sign$1
      26: dup
      27: aload_0
      28: invokespecial #371                // Method edu/psu/sagnik/research/inkscapesvgprocessing/transformparser/impl/TransformParser$$anonfun$sign$1."<init>":(Ledu/psu/sagnik/research/inkscapesvgprocessing/transformparser/impl/TransformParser;)V
      31: invokevirtual #348                // Method scala/util/parsing/combinator/Parsers$Parser.$up$up:(Lscala/Function1;)Lscala/util/parsing/combinator/Parsers$Parser;
      34: areturn

  public scala.util.parsing.combinator.Parsers$Parser<java.lang.Object> exponent();
    Code:
       0: aload_0
       1: new           #320                // class scala/collection/immutable/StringOps
       4: dup
       5: getstatic     #325                // Field scala/Predef$.MODULE$:Lscala/Predef$;
       8: ldc_w         #374                // String e|E
      11: invokevirtual #331                // Method scala/Predef$.augmentString:(Ljava/lang/String;)Ljava/lang/String;
      14: invokespecial #334                // Method scala/collection/immutable/StringOps."<init>":(Ljava/lang/String;)V
      17: invokevirtual #336                // Method scala/collection/immutable/StringOps.r:()Lscala/util/matching/Regex;
      20: invokevirtual #338                // Method regex:(Lscala/util/matching/Regex;)Lscala/util/parsing/combinator/Parsers$Parser;
      23: new           #376                // class edu/psu/sagnik/research/inkscapesvgprocessing/transformparser/impl/TransformParser$$anonfun$exponent$1
      26: dup
      27: aload_0
      28: invokespecial #377                // Method edu/psu/sagnik/research/inkscapesvgprocessing/transformparser/impl/TransformParser$$anonfun$exponent$1."<init>":(Ledu/psu/sagnik/research/inkscapesvgprocessing/transformparser/impl/TransformParser;)V
      31: invokevirtual #362                // Method scala/util/parsing/combinator/Parsers$Parser.$tilde:(Lscala/Function0;)Lscala/util/parsing/combinator/Parsers$Parser;
      34: new           #379                // class edu/psu/sagnik/research/inkscapesvgprocessing/transformparser/impl/TransformParser$$anonfun$exponent$2
      37: dup
      38: aload_0
      39: invokespecial #380                // Method edu/psu/sagnik/research/inkscapesvgprocessing/transformparser/impl/TransformParser$$anonfun$exponent$2."<init>":(Ledu/psu/sagnik/research/inkscapesvgprocessing/transformparser/impl/TransformParser;)V
      42: invokevirtual #362                // Method scala/util/parsing/combinator/Parsers$Parser.$tilde:(Lscala/Function0;)Lscala/util/parsing/combinator/Parsers$Parser;
      45: new           #382                // class edu/psu/sagnik/research/inkscapesvgprocessing/transformparser/impl/TransformParser$$anonfun$exponent$3
      48: dup
      49: aload_0
      50: invokespecial #383                // Method edu/psu/sagnik/research/inkscapesvgprocessing/transformparser/impl/TransformParser$$anonfun$exponent$3."<init>":(Ledu/psu/sagnik/research/inkscapesvgprocessing/transformparser/impl/TransformParser;)V
      53: invokevirtual #348                // Method scala/util/parsing/combinator/Parsers$Parser.$up$up:(Lscala/Function1;)Lscala/util/parsing/combinator/Parsers$Parser;
      56: areturn

  public scala.util.parsing.combinator.Parsers$Parser<java.lang.String> fractional_constant();
    Code:
       0: aload_0
       1: new           #386                // class edu/psu/sagnik/research/inkscapesvgprocessing/transformparser/impl/TransformParser$$anonfun$fractional_constant$1
       4: dup
       5: aload_0
       6: invokespecial #387                // Method edu/psu/sagnik/research/inkscapesvgprocessing/transformparser/impl/TransformParser$$anonfun$fractional_constant$1."<init>":(Ledu/psu/sagnik/research/inkscapesvgprocessing/transformparser/impl/TransformParser;)V
       9: invokevirtual #389                // Method opt:(Lscala/Function0;)Lscala/util/parsing/combinator/Parsers$Parser;
      12: new           #391                // class edu/psu/sagnik/research/inkscapesvgprocessing/transformparser/impl/TransformParser$$anonfun$fractional_constant$2
      15: dup
      16: aload_0
      17: invokespecial #392                // Method edu/psu/sagnik/research/inkscapesvgprocessing/transformparser/impl/TransformParser$$anonfun$fractional_constant$2."<init>":(Ledu/psu/sagnik/research/inkscapesvgprocessing/transformparser/impl/TransformParser;)V
      20: invokevirtual #362                // Method scala/util/parsing/combinator/Parsers$Parser.$tilde:(Lscala/Function0;)Lscala/util/parsing/combinator/Parsers$Parser;
      23: new           #394                // class edu/psu/sagnik/research/inkscapesvgprocessing/transformparser/impl/TransformParser$$anonfun$fractional_constant$3
      26: dup
      27: aload_0
      28: invokespecial #395                // Method edu/psu/sagnik/research/inkscapesvgprocessing/transformparser/impl/TransformParser$$anonfun$fractional_constant$3."<init>":(Ledu/psu/sagnik/research/inkscapesvgprocessing/transformparser/impl/TransformParser;)V
      31: invokevirtual #362                // Method scala/util/parsing/combinator/Parsers$Parser.$tilde:(Lscala/Function0;)Lscala/util/parsing/combinator/Parsers$Parser;
      34: new           #397                // class edu/psu/sagnik/research/inkscapesvgprocessing/transformparser/impl/TransformParser$$anonfun$fractional_constant$4
      37: dup
      38: aload_0
      39: invokespecial #398                // Method edu/psu/sagnik/research/inkscapesvgprocessing/transformparser/impl/TransformParser$$anonfun$fractional_constant$4."<init>":(Ledu/psu/sagnik/research/inkscapesvgprocessing/transformparser/impl/TransformParser;)V
      42: invokevirtual #348                // Method scala/util/parsing/combinator/Parsers$Parser.$up$up:(Lscala/Function1;)Lscala/util/parsing/combinator/Parsers$Parser;
      45: new           #400                // class edu/psu/sagnik/research/inkscapesvgprocessing/transformparser/impl/TransformParser$$anonfun$fractional_constant$5
      48: dup
      49: aload_0
      50: invokespecial #401                // Method edu/psu/sagnik/research/inkscapesvgprocessing/transformparser/impl/TransformParser$$anonfun$fractional_constant$5."<init>":(Ledu/psu/sagnik/research/inkscapesvgprocessing/transformparser/impl/TransformParser;)V
      53: invokevirtual #404                // Method scala/util/parsing/combinator/Parsers$Parser.$bar:(Lscala/Function0;)Lscala/util/parsing/combinator/Parsers$Parser;
      56: areturn

  public scala.util.parsing.combinator.Parsers$Parser<java.lang.String> floating_point_constant();
    Code:
       0: aload_0
       1: invokevirtual #407                // Method fractional_constant:()Lscala/util/parsing/combinator/Parsers$Parser;
       4: new           #409                // class edu/psu/sagnik/research/inkscapesvgprocessing/transformparser/impl/TransformParser$$anonfun$floating_point_constant$1
       7: dup
       8: aload_0
       9: invokespecial #410                // Method edu/psu/sagnik/research/inkscapesvgprocessing/transformparser/impl/TransformParser$$anonfun$floating_point_constant$1."<init>":(Ledu/psu/sagnik/research/inkscapesvgprocessing/transformparser/impl/TransformParser;)V
      12: invokevirtual #362                // Method scala/util/parsing/combinator/Parsers$Parser.$tilde:(Lscala/Function0;)Lscala/util/parsing/combinator/Parsers$Parser;
      15: new           #412                // class edu/psu/sagnik/research/inkscapesvgprocessing/transformparser/impl/TransformParser$$anonfun$floating_point_constant$2
      18: dup
      19: aload_0
      20: invokespecial #413                // Method edu/psu/sagnik/research/inkscapesvgprocessing/transformparser/impl/TransformParser$$anonfun$floating_point_constant$2."<init>":(Ledu/psu/sagnik/research/inkscapesvgprocessing/transformparser/impl/TransformParser;)V
      23: invokevirtual #348                // Method scala/util/parsing/combinator/Parsers$Parser.$up$up:(Lscala/Function1;)Lscala/util/parsing/combinator/Parsers$Parser;
      26: new           #415                // class edu/psu/sagnik/research/inkscapesvgprocessing/transformparser/impl/TransformParser$$anonfun$floating_point_constant$3
      29: dup
      30: aload_0
      31: invokespecial #416                // Method edu/psu/sagnik/research/inkscapesvgprocessing/transformparser/impl/TransformParser$$anonfun$floating_point_constant$3."<init>":(Ledu/psu/sagnik/research/inkscapesvgprocessing/transformparser/impl/TransformParser;)V
      34: invokevirtual #404                // Method scala/util/parsing/combinator/Parsers$Parser.$bar:(Lscala/Function0;)Lscala/util/parsing/combinator/Parsers$Parser;
      37: areturn

  public scala.util.parsing.combinator.Parsers$Parser<java.lang.String> integer_constant();
    Code:
       0: aload_0
       1: invokevirtual #419                // Method digit_sequence:()Lscala/util/parsing/combinator/Parsers$Parser;
       4: new           #421                // class edu/psu/sagnik/research/inkscapesvgprocessing/transformparser/impl/TransformParser$$anonfun$integer_constant$1
       7: dup
       8: aload_0
       9: invokespecial #422                // Method edu/psu/sagnik/research/inkscapesvgprocessing/transformparser/impl/TransformParser$$anonfun$integer_constant$1."<init>":(Ledu/psu/sagnik/research/inkscapesvgprocessing/transformparser/impl/TransformParser;)V
      12: invokevirtual #348                // Method scala/util/parsing/combinator/Parsers$Parser.$up$up:(Lscala/Function1;)Lscala/util/parsing/combinator/Parsers$Parser;
      15: areturn

  public scala.util.parsing.combinator.Parsers$Parser<java.lang.String> comma();
    Code:
       0: aload_0
       1: new           #320                // class scala/collection/immutable/StringOps
       4: dup
       5: getstatic     #325                // Field scala/Predef$.MODULE$:Lscala/Predef$;
       8: ldc_w         #425                // String ,
      11: invokevirtual #331                // Method scala/Predef$.augmentString:(Ljava/lang/String;)Ljava/lang/String;
      14: invokespecial #334                // Method scala/collection/immutable/StringOps."<init>":(Ljava/lang/String;)V
      17: invokevirtual #336                // Method scala/collection/immutable/StringOps.r:()Lscala/util/matching/Regex;
      20: invokevirtual #338                // Method regex:(Lscala/util/matching/Regex;)Lscala/util/parsing/combinator/Parsers$Parser;
      23: new           #427                // class edu/psu/sagnik/research/inkscapesvgprocessing/transformparser/impl/TransformParser$$anonfun$comma$1
      26: dup
      27: aload_0
      28: invokespecial #428                // Method edu/psu/sagnik/research/inkscapesvgprocessing/transformparser/impl/TransformParser$$anonfun$comma$1."<init>":(Ledu/psu/sagnik/research/inkscapesvgprocessing/transformparser/impl/TransformParser;)V
      31: invokevirtual #348                // Method scala/util/parsing/combinator/Parsers$Parser.$up$up:(Lscala/Function1;)Lscala/util/parsing/combinator/Parsers$Parser;
      34: areturn

  public scala.util.parsing.combinator.Parsers$Parser<java.lang.String> comma_wsp();
    Code:
       0: aload_0
       1: invokevirtual #431                // Method wsp:()Lscala/util/parsing/combinator/Parsers$Parser;
       4: new           #433                // class edu/psu/sagnik/research/inkscapesvgprocessing/transformparser/impl/TransformParser$$anonfun$comma_wsp$1
       7: dup
       8: aload_0
       9: invokespecial #434                // Method edu/psu/sagnik/research/inkscapesvgprocessing/transformparser/impl/TransformParser$$anonfun$comma_wsp$1."<init>":(Ledu/psu/sagnik/research/inkscapesvgprocessing/transformparser/impl/TransformParser;)V
      12: invokevirtual #362                // Method scala/util/parsing/combinator/Parsers$Parser.$tilde:(Lscala/Function0;)Lscala/util/parsing/combinator/Parsers$Parser;
      15: new           #436                // class edu/psu/sagnik/research/inkscapesvgprocessing/transformparser/impl/TransformParser$$anonfun$comma_wsp$2
      18: dup
      19: aload_0
      20: invokespecial #437                // Method edu/psu/sagnik/research/inkscapesvgprocessing/transformparser/impl/TransformParser$$anonfun$comma_wsp$2."<init>":(Ledu/psu/sagnik/research/inkscapesvgprocessing/transformparser/impl/TransformParser;)V
      23: invokevirtual #362                // Method scala/util/parsing/combinator/Parsers$Parser.$tilde:(Lscala/Function0;)Lscala/util/parsing/combinator/Parsers$Parser;
      26: new           #439                // class edu/psu/sagnik/research/inkscapesvgprocessing/transformparser/impl/TransformParser$$anonfun$comma_wsp$3
      29: dup
      30: aload_0
      31: invokespecial #440                // Method edu/psu/sagnik/research/inkscapesvgprocessing/transformparser/impl/TransformParser$$anonfun$comma_wsp$3."<init>":(Ledu/psu/sagnik/research/inkscapesvgprocessing/transformparser/impl/TransformParser;)V
      34: invokevirtual #362                // Method scala/util/parsing/combinator/Parsers$Parser.$tilde:(Lscala/Function0;)Lscala/util/parsing/combinator/Parsers$Parser;
      37: new           #442                // class edu/psu/sagnik/research/inkscapesvgprocessing/transformparser/impl/TransformParser$$anonfun$comma_wsp$4
      40: dup
      41: aload_0
      42: invokespecial #443                // Method edu/psu/sagnik/research/inkscapesvgprocessing/transformparser/impl/TransformParser$$anonfun$comma_wsp$4."<init>":(Ledu/psu/sagnik/research/inkscapesvgprocessing/transformparser/impl/TransformParser;)V
      45: invokevirtual #348                // Method scala/util/parsing/combinator/Parsers$Parser.$up$up:(Lscala/Function1;)Lscala/util/parsing/combinator/Parsers$Parser;
      48: new           #445                // class edu/psu/sagnik/research/inkscapesvgprocessing/transformparser/impl/TransformParser$$anonfun$comma_wsp$5
      51: dup
      52: aload_0
      53: invokespecial #446                // Method edu/psu/sagnik/research/inkscapesvgprocessing/transformparser/impl/TransformParser$$anonfun$comma_wsp$5."<init>":(Ledu/psu/sagnik/research/inkscapesvgprocessing/transformparser/impl/TransformParser;)V
      56: invokevirtual #404                // Method scala/util/parsing/combinator/Parsers$Parser.$bar:(Lscala/Function0;)Lscala/util/parsing/combinator/Parsers$Parser;
      59: areturn

  public scala.util.parsing.combinator.Parsers$Parser<java.lang.Object> flag();
    Code:
       0: aload_0
       1: new           #320                // class scala/collection/immutable/StringOps
       4: dup
       5: getstatic     #325                // Field scala/Predef$.MODULE$:Lscala/Predef$;
       8: ldc_w         #449                // String 0|1
      11: invokevirtual #331                // Method scala/Predef$.augmentString:(Ljava/lang/String;)Ljava/lang/String;
      14: invokespecial #334                // Method scala/collection/immutable/StringOps."<init>":(Ljava/lang/String;)V
      17: invokevirtual #336                // Method scala/collection/immutable/StringOps.r:()Lscala/util/matching/Regex;
      20: invokevirtual #338                // Method regex:(Lscala/util/matching/Regex;)Lscala/util/parsing/combinator/Parsers$Parser;
      23: new           #451                // class edu/psu/sagnik/research/inkscapesvgprocessing/transformparser/impl/TransformParser$$anonfun$flag$1
      26: dup
      27: aload_0
      28: invokespecial #452                // Method edu/psu/sagnik/research/inkscapesvgprocessing/transformparser/impl/TransformParser$$anonfun$flag$1."<init>":(Ledu/psu/sagnik/research/inkscapesvgprocessing/transformparser/impl/TransformParser;)V
      31: invokevirtual #348                // Method scala/util/parsing/combinator/Parsers$Parser.$up$up:(Lscala/Function1;)Lscala/util/parsing/combinator/Parsers$Parser;
      34: areturn

  public scala.util.parsing.combinator.Parsers$Parser<java.lang.Object> number();
    Code:
       0: aload_0
       1: new           #455                // class edu/psu/sagnik/research/inkscapesvgprocessing/transformparser/impl/TransformParser$$anonfun$number$1
       4: dup
       5: aload_0
       6: invokespecial #456                // Method edu/psu/sagnik/research/inkscapesvgprocessing/transformparser/impl/TransformParser$$anonfun$number$1."<init>":(Ledu/psu/sagnik/research/inkscapesvgprocessing/transformparser/impl/TransformParser;)V
       9: invokevirtual #389                // Method opt:(Lscala/Function0;)Lscala/util/parsing/combinator/Parsers$Parser;
      12: new           #458                // class edu/psu/sagnik/research/inkscapesvgprocessing/transformparser/impl/TransformParser$$anonfun$number$2
      15: dup
      16: aload_0
      17: invokespecial #459                // Method edu/psu/sagnik/research/inkscapesvgprocessing/transformparser/impl/TransformParser$$anonfun$number$2."<init>":(Ledu/psu/sagnik/research/inkscapesvgprocessing/transformparser/impl/TransformParser;)V
      20: invokevirtual #362                // Method scala/util/parsing/combinator/Parsers$Parser.$tilde:(Lscala/Function0;)Lscala/util/parsing/combinator/Parsers$Parser;
      23: new           #461                // class edu/psu/sagnik/research/inkscapesvgprocessing/transformparser/impl/TransformParser$$anonfun$number$3
      26: dup
      27: aload_0
      28: invokespecial #462                // Method edu/psu/sagnik/research/inkscapesvgprocessing/transformparser/impl/TransformParser$$anonfun$number$3."<init>":(Ledu/psu/sagnik/research/inkscapesvgprocessing/transformparser/impl/TransformParser;)V
      31: invokevirtual #348                // Method scala/util/parsing/combinator/Parsers$Parser.$up$up:(Lscala/Function1;)Lscala/util/parsing/combinator/Parsers$Parser;
      34: new           #464                // class edu/psu/sagnik/research/inkscapesvgprocessing/transformparser/impl/TransformParser$$anonfun$number$4
      37: dup
      38: aload_0
      39: invokespecial #465                // Method edu/psu/sagnik/research/inkscapesvgprocessing/transformparser/impl/TransformParser$$anonfun$number$4."<init>":(Ledu/psu/sagnik/research/inkscapesvgprocessing/transformparser/impl/TransformParser;)V
      42: invokevirtual #404                // Method scala/util/parsing/combinator/Parsers$Parser.$bar:(Lscala/Function0;)Lscala/util/parsing/combinator/Parsers$Parser;
      45: areturn

  public scala.util.parsing.combinator.Parsers$Parser<edu.psu.sagnik.research.inkscapesvgprocessing.transformparser.model.SkewYOp> skewY();
    Code:
       0: aload_0
       1: new           #320                // class scala/collection/immutable/StringOps
       4: dup
       5: getstatic     #325                // Field scala/Predef$.MODULE$:Lscala/Predef$;
       8: ldc_w         #467                // String skewY
      11: invokevirtual #331                // Method scala/Predef$.augmentString:(Ljava/lang/String;)Ljava/lang/String;
      14: invokespecial #334                // Method scala/collection/immutable/StringOps."<init>":(Ljava/lang/String;)V
      17: invokevirtual #336                // Method scala/collection/immutable/StringOps.r:()Lscala/util/matching/Regex;
      20: invokevirtual #338                // Method regex:(Lscala/util/matching/Regex;)Lscala/util/parsing/combinator/Parsers$Parser;
      23: new           #469                // class edu/psu/sagnik/research/inkscapesvgprocessing/transformparser/impl/TransformParser$$anonfun$skewY$1
      26: dup
      27: aload_0
      28: invokespecial #470                // Method edu/psu/sagnik/research/inkscapesvgprocessing/transformparser/impl/TransformParser$$anonfun$skewY$1."<init>":(Ledu/psu/sagnik/research/inkscapesvgprocessing/transformparser/impl/TransformParser;)V
      31: invokevirtual #362                // Method scala/util/parsing/combinator/Parsers$Parser.$tilde:(Lscala/Function0;)Lscala/util/parsing/combinator/Parsers$Parser;
      34: new           #472                // class edu/psu/sagnik/research/inkscapesvgprocessing/transformparser/impl/TransformParser$$anonfun$skewY$2
      37: dup
      38: aload_0
      39: invokespecial #473                // Method edu/psu/sagnik/research/inkscapesvgprocessing/transformparser/impl/TransformParser$$anonfun$skewY$2."<init>":(Ledu/psu/sagnik/research/inkscapesvgprocessing/transformparser/impl/TransformParser;)V
      42: invokevirtual #362                // Method scala/util/parsing/combinator/Parsers$Parser.$tilde:(Lscala/Function0;)Lscala/util/parsing/combinator/Parsers$Parser;
      45: new           #475                // class edu/psu/sagnik/research/inkscapesvgprocessing/transformparser/impl/TransformParser$$anonfun$skewY$3
      48: dup
      49: aload_0
      50: invokespecial #476                // Method edu/psu/sagnik/research/inkscapesvgprocessing/transformparser/impl/TransformParser$$anonfun$skewY$3."<init>":(Ledu/psu/sagnik/research/inkscapesvgprocessing/transformparser/impl/TransformParser;)V
      53: invokevirtual #362                // Method scala/util/parsing/combinator/Parsers$Parser.$tilde:(Lscala/Function0;)Lscala/util/parsing/combinator/Parsers$Parser;
      56: new           #478                // class edu/psu/sagnik/research/inkscapesvgprocessing/transformparser/impl/TransformParser$$anonfun$skewY$4
      59: dup
      60: aload_0
      61: invokespecial #479                // Method edu/psu/sagnik/research/inkscapesvgprocessing/transformparser/impl/TransformParser$$anonfun$skewY$4."<init>":(Ledu/psu/sagnik/research/inkscapesvgprocessing/transformparser/impl/TransformParser;)V
      64: invokevirtual #362                // Method scala/util/parsing/combinator/Parsers$Parser.$tilde:(Lscala/Function0;)Lscala/util/parsing/combinator/Parsers$Parser;
      67: new           #481                // class edu/psu/sagnik/research/inkscapesvgprocessing/transformparser/impl/TransformParser$$anonfun$skewY$5
      70: dup
      71: aload_0
      72: invokespecial #482                // Method edu/psu/sagnik/research/inkscapesvgprocessing/transformparser/impl/TransformParser$$anonfun$skewY$5."<init>":(Ledu/psu/sagnik/research/inkscapesvgprocessing/transformparser/impl/TransformParser;)V
      75: invokevirtual #362                // Method scala/util/parsing/combinator/Parsers$Parser.$tilde:(Lscala/Function0;)Lscala/util/parsing/combinator/Parsers$Parser;
      78: new           #484                // class edu/psu/sagnik/research/inkscapesvgprocessing/transformparser/impl/TransformParser$$anonfun$skewY$6
      81: dup
      82: aload_0
      83: invokespecial #485                // Method edu/psu/sagnik/research/inkscapesvgprocessing/transformparser/impl/TransformParser$$anonfun$skewY$6."<init>":(Ledu/psu/sagnik/research/inkscapesvgprocessing/transformparser/impl/TransformParser;)V
      86: invokevirtual #362                // Method scala/util/parsing/combinator/Parsers$Parser.$tilde:(Lscala/Function0;)Lscala/util/parsing/combinator/Parsers$Parser;
      89: new           #487                // class edu/psu/sagnik/research/inkscapesvgprocessing/transformparser/impl/TransformParser$$anonfun$skewY$7
      92: dup
      93: aload_0
      94: invokespecial #488                // Method edu/psu/sagnik/research/inkscapesvgprocessing/transformparser/impl/TransformParser$$anonfun$skewY$7."<init>":(Ledu/psu/sagnik/research/inkscapesvgprocessing/transformparser/impl/TransformParser;)V
      97: invokevirtual #348                // Method scala/util/parsing/combinator/Parsers$Parser.$up$up:(Lscala/Function1;)Lscala/util/parsing/combinator/Parsers$Parser;
     100: areturn

  public scala.util.parsing.combinator.Parsers$Parser<edu.psu.sagnik.research.inkscapesvgprocessing.transformparser.model.SkewXOp> skewX();
    Code:
       0: aload_0
       1: new           #320                // class scala/collection/immutable/StringOps
       4: dup
       5: getstatic     #325                // Field scala/Predef$.MODULE$:Lscala/Predef$;
       8: ldc_w         #490                // String skewX
      11: invokevirtual #331                // Method scala/Predef$.augmentString:(Ljava/lang/String;)Ljava/lang/String;
      14: invokespecial #334                // Method scala/collection/immutable/StringOps."<init>":(Ljava/lang/String;)V
      17: invokevirtual #336                // Method scala/collection/immutable/StringOps.r:()Lscala/util/matching/Regex;
      20: invokevirtual #338                // Method regex:(Lscala/util/matching/Regex;)Lscala/util/parsing/combinator/Parsers$Parser;
      23: new           #492                // class edu/psu/sagnik/research/inkscapesvgprocessing/transformparser/impl/TransformParser$$anonfun$skewX$1
      26: dup
      27: aload_0
      28: invokespecial #493                // Method edu/psu/sagnik/research/inkscapesvgprocessing/transformparser/impl/TransformParser$$anonfun$skewX$1."<init>":(Ledu/psu/sagnik/research/inkscapesvgprocessing/transformparser/impl/TransformParser;)V
      31: invokevirtual #362                // Method scala/util/parsing/combinator/Parsers$Parser.$tilde:(Lscala/Function0;)Lscala/util/parsing/combinator/Parsers$Parser;
      34: new           #495                // class edu/psu/sagnik/research/inkscapesvgprocessing/transformparser/impl/TransformParser$$anonfun$skewX$2
      37: dup
      38: aload_0
      39: invokespecial #496                // Method edu/psu/sagnik/research/inkscapesvgprocessing/transformparser/impl/TransformParser$$anonfun$skewX$2."<init>":(Ledu/psu/sagnik/research/inkscapesvgprocessing/transformparser/impl/TransformParser;)V
      42: invokevirtual #362                // Method scala/util/parsing/combinator/Parsers$Parser.$tilde:(Lscala/Function0;)Lscala/util/parsing/combinator/Parsers$Parser;
      45: new           #498                // class edu/psu/sagnik/research/inkscapesvgprocessing/transformparser/impl/TransformParser$$anonfun$skewX$3
      48: dup
      49: aload_0
      50: invokespecial #499                // Method edu/psu/sagnik/research/inkscapesvgprocessing/transformparser/impl/TransformParser$$anonfun$skewX$3."<init>":(Ledu/psu/sagnik/research/inkscapesvgprocessing/transformparser/impl/TransformParser;)V
      53: invokevirtual #362                // Method scala/util/parsing/combinator/Parsers$Parser.$tilde:(Lscala/Function0;)Lscala/util/parsing/combinator/Parsers$Parser;
      56: new           #501                // class edu/psu/sagnik/research/inkscapesvgprocessing/transformparser/impl/TransformParser$$anonfun$skewX$4
      59: dup
      60: aload_0
      61: invokespecial #502                // Method edu/psu/sagnik/research/inkscapesvgprocessing/transformparser/impl/TransformParser$$anonfun$skewX$4."<init>":(Ledu/psu/sagnik/research/inkscapesvgprocessing/transformparser/impl/TransformParser;)V
      64: invokevirtual #362                // Method scala/util/parsing/combinator/Parsers$Parser.$tilde:(Lscala/Function0;)Lscala/util/parsing/combinator/Parsers$Parser;
      67: new           #504                // class edu/psu/sagnik/research/inkscapesvgprocessing/transformparser/impl/TransformParser$$anonfun$skewX$5
      70: dup
      71: aload_0
      72: invokespecial #505                // Method edu/psu/sagnik/research/inkscapesvgprocessing/transformparser/impl/TransformParser$$anonfun$skewX$5."<init>":(Ledu/psu/sagnik/research/inkscapesvgprocessing/transformparser/impl/TransformParser;)V
      75: invokevirtual #362                // Method scala/util/parsing/combinator/Parsers$Parser.$tilde:(Lscala/Function0;)Lscala/util/parsing/combinator/Parsers$Parser;
      78: new           #507                // class edu/psu/sagnik/research/inkscapesvgprocessing/transformparser/impl/TransformParser$$anonfun$skewX$6
      81: dup
      82: aload_0
      83: invokespecial #508                // Method edu/psu/sagnik/research/inkscapesvgprocessing/transformparser/impl/TransformParser$$anonfun$skewX$6."<init>":(Ledu/psu/sagnik/research/inkscapesvgprocessing/transformparser/impl/TransformParser;)V
      86: invokevirtual #362                // Method scala/util/parsing/combinator/Parsers$Parser.$tilde:(Lscala/Function0;)Lscala/util/parsing/combinator/Parsers$Parser;
      89: new           #510                // class edu/psu/sagnik/research/inkscapesvgprocessing/transformparser/impl/TransformParser$$anonfun$skewX$7
      92: dup
      93: aload_0
      94: invokespecial #511                // Method edu/psu/sagnik/research/inkscapesvgprocessing/transformparser/impl/TransformParser$$anonfun$skewX$7."<init>":(Ledu/psu/sagnik/research/inkscapesvgprocessing/transformparser/impl/TransformParser;)V
      97: invokevirtual #348                // Method scala/util/parsing/combinator/Parsers$Parser.$up$up:(Lscala/Function1;)Lscala/util/parsing/combinator/Parsers$Parser;
     100: areturn

  public scala.util.parsing.combinator.Parsers$Parser<edu.psu.sagnik.research.inkscapesvgprocessing.transformparser.model.RotateOp> rotate();
    Code:
       0: aload_0
       1: new           #320                // class scala/collection/immutable/StringOps
       4: dup
       5: getstatic     #325                // Field scala/Predef$.MODULE$:Lscala/Predef$;
       8: ldc_w         #513                // String rotate
      11: invokevirtual #331                // Method scala/Predef$.augmentString:(Ljava/lang/String;)Ljava/lang/String;
      14: invokespecial #334                // Method scala/collection/immutable/StringOps."<init>":(Ljava/lang/String;)V
      17: invokevirtual #336                // Method scala/collection/immutable/StringOps.r:()Lscala/util/matching/Regex;
      20: invokevirtual #338                // Method regex:(Lscala/util/matching/Regex;)Lscala/util/parsing/combinator/Parsers$Parser;
      23: new           #515                // class edu/psu/sagnik/research/inkscapesvgprocessing/transformparser/impl/TransformParser$$anonfun$rotate$1
      26: dup
      27: aload_0
      28: invokespecial #516                // Method edu/psu/sagnik/research/inkscapesvgprocessing/transformparser/impl/TransformParser$$anonfun$rotate$1."<init>":(Ledu/psu/sagnik/research/inkscapesvgprocessing/transformparser/impl/TransformParser;)V
      31: invokevirtual #362                // Method scala/util/parsing/combinator/Parsers$Parser.$tilde:(Lscala/Function0;)Lscala/util/parsing/combinator/Parsers$Parser;
      34: new           #518                // class edu/psu/sagnik/research/inkscapesvgprocessing/transformparser/impl/TransformParser$$anonfun$rotate$2
      37: dup
      38: aload_0
      39: invokespecial #519                // Method edu/psu/sagnik/research/inkscapesvgprocessing/transformparser/impl/TransformParser$$anonfun$rotate$2."<init>":(Ledu/psu/sagnik/research/inkscapesvgprocessing/transformparser/impl/TransformParser;)V
      42: invokevirtual #362                // Method scala/util/parsing/combinator/Parsers$Parser.$tilde:(Lscala/Function0;)Lscala/util/parsing/combinator/Parsers$Parser;
      45: new           #521                // class edu/psu/sagnik/research/inkscapesvgprocessing/transformparser/impl/TransformParser$$anonfun$rotate$3
      48: dup
      49: aload_0
      50: invokespecial #522                // Method edu/psu/sagnik/research/inkscapesvgprocessing/transformparser/impl/TransformParser$$anonfun$rotate$3."<init>":(Ledu/psu/sagnik/research/inkscapesvgprocessing/transformparser/impl/TransformParser;)V
      53: invokevirtual #362                // Method scala/util/parsing/combinator/Parsers$Parser.$tilde:(Lscala/Function0;)Lscala/util/parsing/combinator/Parsers$Parser;
      56: new           #524                // class edu/psu/sagnik/research/inkscapesvgprocessing/transformparser/impl/TransformParser$$anonfun$rotate$4
      59: dup
      60: aload_0
      61: invokespecial #525                // Method edu/psu/sagnik/research/inkscapesvgprocessing/transformparser/impl/TransformParser$$anonfun$rotate$4."<init>":(Ledu/psu/sagnik/research/inkscapesvgprocessing/transformparser/impl/TransformParser;)V
      64: invokevirtual #362                // Method scala/util/parsing/combinator/Parsers$Parser.$tilde:(Lscala/Function0;)Lscala/util/parsing/combinator/Parsers$Parser;
      67: new           #527                // class edu/psu/sagnik/research/inkscapesvgprocessing/transformparser/impl/TransformParser$$anonfun$rotate$5
      70: dup
      71: aload_0
      72: invokespecial #528                // Method edu/psu/sagnik/research/inkscapesvgprocessing/transformparser/impl/TransformParser$$anonfun$rotate$5."<init>":(Ledu/psu/sagnik/research/inkscapesvgprocessing/transformparser/impl/TransformParser;)V
      75: invokevirtual #362                // Method scala/util/parsing/combinator/Parsers$Parser.$tilde:(Lscala/Function0;)Lscala/util/parsing/combinator/Parsers$Parser;
      78: new           #530                // class edu/psu/sagnik/research/inkscapesvgprocessing/transformparser/impl/TransformParser$$anonfun$rotate$6
      81: dup
      82: aload_0
      83: invokespecial #531                // Method edu/psu/sagnik/research/inkscapesvgprocessing/transformparser/impl/TransformParser$$anonfun$rotate$6."<init>":(Ledu/psu/sagnik/research/inkscapesvgprocessing/transformparser/impl/TransformParser;)V
      86: invokevirtual #362                // Method scala/util/parsing/combinator/Parsers$Parser.$tilde:(Lscala/Function0;)Lscala/util/parsing/combinator/Parsers$Parser;
      89: new           #533                // class edu/psu/sagnik/research/inkscapesvgprocessing/transformparser/impl/TransformParser$$anonfun$rotate$7
      92: dup
      93: aload_0
      94: invokespecial #534                // Method edu/psu/sagnik/research/inkscapesvgprocessing/transformparser/impl/TransformParser$$anonfun$rotate$7."<init>":(Ledu/psu/sagnik/research/inkscapesvgprocessing/transformparser/impl/TransformParser;)V
      97: invokevirtual #362                // Method scala/util/parsing/combinator/Parsers$Parser.$tilde:(Lscala/Function0;)Lscala/util/parsing/combinator/Parsers$Parser;
     100: new           #536                // class edu/psu/sagnik/research/inkscapesvgprocessing/transformparser/impl/TransformParser$$anonfun$rotate$8
     103: dup
     104: aload_0
     105: invokespecial #537                // Method edu/psu/sagnik/research/inkscapesvgprocessing/transformparser/impl/TransformParser$$anonfun$rotate$8."<init>":(Ledu/psu/sagnik/research/inkscapesvgprocessing/transformparser/impl/TransformParser;)V
     108: invokevirtual #348                // Method scala/util/parsing/combinator/Parsers$Parser.$up$up:(Lscala/Function1;)Lscala/util/parsing/combinator/Parsers$Parser;
     111: areturn

  public scala.util.parsing.combinator.Parsers$Parser<edu.psu.sagnik.research.inkscapesvgprocessing.transformparser.model.ScaleOp> scale();
    Code:
       0: aload_0
       1: new           #320                // class scala/collection/immutable/StringOps
       4: dup
       5: getstatic     #325                // Field scala/Predef$.MODULE$:Lscala/Predef$;
       8: ldc_w         #539                // String scale
      11: invokevirtual #331                // Method scala/Predef$.augmentString:(Ljava/lang/String;)Ljava/lang/String;
      14: invokespecial #334                // Method scala/collection/immutable/StringOps."<init>":(Ljava/lang/String;)V
      17: invokevirtual #336                // Method scala/collection/immutable/StringOps.r:()Lscala/util/matching/Regex;
      20: invokevirtual #338                // Method regex:(Lscala/util/matching/Regex;)Lscala/util/parsing/combinator/Parsers$Parser;
      23: new           #541                // class edu/psu/sagnik/research/inkscapesvgprocessing/transformparser/impl/TransformParser$$anonfun$scale$1
      26: dup
      27: aload_0
      28: invokespecial #542                // Method edu/psu/sagnik/research/inkscapesvgprocessing/transformparser/impl/TransformParser$$anonfun$scale$1."<init>":(Ledu/psu/sagnik/research/inkscapesvgprocessing/transformparser/impl/TransformParser;)V
      31: invokevirtual #362                // Method scala/util/parsing/combinator/Parsers$Parser.$tilde:(Lscala/Function0;)Lscala/util/parsing/combinator/Parsers$Parser;
      34: new           #544                // class edu/psu/sagnik/research/inkscapesvgprocessing/transformparser/impl/TransformParser$$anonfun$scale$2
      37: dup
      38: aload_0
      39: invokespecial #545                // Method edu/psu/sagnik/research/inkscapesvgprocessing/transformparser/impl/TransformParser$$anonfun$scale$2."<init>":(Ledu/psu/sagnik/research/inkscapesvgprocessing/transformparser/impl/TransformParser;)V
      42: invokevirtual #362                // Method scala/util/parsing/combinator/Parsers$Parser.$tilde:(Lscala/Function0;)Lscala/util/parsing/combinator/Parsers$Parser;
      45: new           #547                // class edu/psu/sagnik/research/inkscapesvgprocessing/transformparser/impl/TransformParser$$anonfun$scale$3
      48: dup
      49: aload_0
      50: invokespecial #548                // Method edu/psu/sagnik/research/inkscapesvgprocessing/transformparser/impl/TransformParser$$anonfun$scale$3."<init>":(Ledu/psu/sagnik/research/inkscapesvgprocessing/transformparser/impl/TransformParser;)V
      53: invokevirtual #362                // Method scala/util/parsing/combinator/Parsers$Parser.$tilde:(Lscala/Function0;)Lscala/util/parsing/combinator/Parsers$Parser;
      56: new           #550                // class edu/psu/sagnik/research/inkscapesvgprocessing/transformparser/impl/TransformParser$$anonfun$scale$4
      59: dup
      60: aload_0
      61: invokespecial #551                // Method edu/psu/sagnik/research/inkscapesvgprocessing/transformparser/impl/TransformParser$$anonfun$scale$4."<init>":(Ledu/psu/sagnik/research/inkscapesvgprocessing/transformparser/impl/TransformParser;)V
      64: invokevirtual #362                // Method scala/util/parsing/combinator/Parsers$Parser.$tilde:(Lscala/Function0;)Lscala/util/parsing/combinator/Parsers$Parser;
      67: new           #553                // class edu/psu/sagnik/research/inkscapesvgprocessing/transformparser/impl/TransformParser$$anonfun$scale$5
      70: dup
      71: aload_0
      72: invokespecial #554                // Method edu/psu/sagnik/research/inkscapesvgprocessing/transformparser/impl/TransformParser$$anonfun$scale$5."<init>":(Ledu/psu/sagnik/research/inkscapesvgprocessing/transformparser/impl/TransformParser;)V
      75: invokevirtual #362                // Method scala/util/parsing/combinator/Parsers$Parser.$tilde:(Lscala/Function0;)Lscala/util/parsing/combinator/Parsers$Parser;
      78: new           #556                // class edu/psu/sagnik/research/inkscapesvgprocessing/transformparser/impl/TransformParser$$anonfun$scale$6
      81: dup
      82: aload_0
      83: invokespecial #557                // Method edu/psu/sagnik/research/inkscapesvgprocessing/transformparser/impl/TransformParser$$anonfun$scale$6."<init>":(Ledu/psu/sagnik/research/inkscapesvgprocessing/transformparser/impl/TransformParser;)V
      86: invokevirtual #362                // Method scala/util/parsing/combinator/Parsers$Parser.$tilde:(Lscala/Function0;)Lscala/util/parsing/combinator/Parsers$Parser;
      89: new           #559                // class edu/psu/sagnik/research/inkscapesvgprocessing/transformparser/impl/TransformParser$$anonfun$scale$7
      92: dup
      93: aload_0
      94: invokespecial #560                // Method edu/psu/sagnik/research/inkscapesvgprocessing/transformparser/impl/TransformParser$$anonfun$scale$7."<init>":(Ledu/psu/sagnik/research/inkscapesvgprocessing/transformparser/impl/TransformParser;)V
      97: invokevirtual #362                // Method scala/util/parsing/combinator/Parsers$Parser.$tilde:(Lscala/Function0;)Lscala/util/parsing/combinator/Parsers$Parser;
     100: new           #562                // class edu/psu/sagnik/research/inkscapesvgprocessing/transformparser/impl/TransformParser$$anonfun$scale$8
     103: dup
     104: aload_0
     105: invokespecial #563                // Method edu/psu/sagnik/research/inkscapesvgprocessing/transformparser/impl/TransformParser$$anonfun$scale$8."<init>":(Ledu/psu/sagnik/research/inkscapesvgprocessing/transformparser/impl/TransformParser;)V
     108: invokevirtual #348                // Method scala/util/parsing/combinator/Parsers$Parser.$up$up:(Lscala/Function1;)Lscala/util/parsing/combinator/Parsers$Parser;
     111: areturn

  public scala.util.parsing.combinator.Parsers$Parser<edu.psu.sagnik.research.inkscapesvgprocessing.transformparser.model.TranslateOp> translate();
    Code:
       0: aload_0
       1: new           #320                // class scala/collection/immutable/StringOps
       4: dup
       5: getstatic     #325                // Field scala/Predef$.MODULE$:Lscala/Predef$;
       8: ldc_w         #565                // String translate
      11: invokevirtual #331                // Method scala/Predef$.augmentString:(Ljava/lang/String;)Ljava/lang/String;
      14: invokespecial #334                // Method scala/collection/immutable/StringOps."<init>":(Ljava/lang/String;)V
      17: invokevirtual #336                // Method scala/collection/immutable/StringOps.r:()Lscala/util/matching/Regex;
      20: invokevirtual #338                // Method regex:(Lscala/util/matching/Regex;)Lscala/util/parsing/combinator/Parsers$Parser;
      23: new           #567                // class edu/psu/sagnik/research/inkscapesvgprocessing/transformparser/impl/TransformParser$$anonfun$translate$1
      26: dup
      27: aload_0
      28: invokespecial #568                // Method edu/psu/sagnik/research/inkscapesvgprocessing/transformparser/impl/TransformParser$$anonfun$translate$1."<init>":(Ledu/psu/sagnik/research/inkscapesvgprocessing/transformparser/impl/TransformParser;)V
      31: invokevirtual #362                // Method scala/util/parsing/combinator/Parsers$Parser.$tilde:(Lscala/Function0;)Lscala/util/parsing/combinator/Parsers$Parser;
      34: new           #570                // class edu/psu/sagnik/research/inkscapesvgprocessing/transformparser/impl/TransformParser$$anonfun$translate$2
      37: dup
      38: aload_0
      39: invokespecial #571                // Method edu/psu/sagnik/research/inkscapesvgprocessing/transformparser/impl/TransformParser$$anonfun$translate$2."<init>":(Ledu/psu/sagnik/research/inkscapesvgprocessing/transformparser/impl/TransformParser;)V
      42: invokevirtual #362                // Method scala/util/parsing/combinator/Parsers$Parser.$tilde:(Lscala/Function0;)Lscala/util/parsing/combinator/Parsers$Parser;
      45: new           #573                // class edu/psu/sagnik/research/inkscapesvgprocessing/transformparser/impl/TransformParser$$anonfun$translate$3
      48: dup
      49: aload_0
      50: invokespecial #574                // Method edu/psu/sagnik/research/inkscapesvgprocessing/transformparser/impl/TransformParser$$anonfun$translate$3."<init>":(Ledu/psu/sagnik/research/inkscapesvgprocessing/transformparser/impl/TransformParser;)V
      53: invokevirtual #362                // Method scala/util/parsing/combinator/Parsers$Parser.$tilde:(Lscala/Function0;)Lscala/util/parsing/combinator/Parsers$Parser;
      56: new           #576                // class edu/psu/sagnik/research/inkscapesvgprocessing/transformparser/impl/TransformParser$$anonfun$translate$4
      59: dup
      60: aload_0
      61: invokespecial #577                // Method edu/psu/sagnik/research/inkscapesvgprocessing/transformparser/impl/TransformParser$$anonfun$translate$4."<init>":(Ledu/psu/sagnik/research/inkscapesvgprocessing/transformparser/impl/TransformParser;)V
      64: invokevirtual #362                // Method scala/util/parsing/combinator/Parsers$Parser.$tilde:(Lscala/Function0;)Lscala/util/parsing/combinator/Parsers$Parser;
      67: new           #579                // class edu/psu/sagnik/research/inkscapesvgprocessing/transformparser/impl/TransformParser$$anonfun$translate$5
      70: dup
      71: aload_0
      72: invokespecial #580                // Method edu/psu/sagnik/research/inkscapesvgprocessing/transformparser/impl/TransformParser$$anonfun$translate$5."<init>":(Ledu/psu/sagnik/research/inkscapesvgprocessing/transformparser/impl/TransformParser;)V
      75: invokevirtual #362                // Method scala/util/parsing/combinator/Parsers$Parser.$tilde:(Lscala/Function0;)Lscala/util/parsing/combinator/Parsers$Parser;
      78: new           #582                // class edu/psu/sagnik/research/inkscapesvgprocessing/transformparser/impl/TransformParser$$anonfun$translate$6
      81: dup
      82: aload_0
      83: invokespecial #583                // Method edu/psu/sagnik/research/inkscapesvgprocessing/transformparser/impl/TransformParser$$anonfun$translate$6."<init>":(Ledu/psu/sagnik/research/inkscapesvgprocessing/transformparser/impl/TransformParser;)V
      86: invokevirtual #362                // Method scala/util/parsing/combinator/Parsers$Parser.$tilde:(Lscala/Function0;)Lscala/util/parsing/combinator/Parsers$Parser;
      89: new           #585                // class edu/psu/sagnik/research/inkscapesvgprocessing/transformparser/impl/TransformParser$$anonfun$translate$7
      92: dup
      93: aload_0
      94: invokespecial #586                // Method edu/psu/sagnik/research/inkscapesvgprocessing/transformparser/impl/TransformParser$$anonfun$translate$7."<init>":(Ledu/psu/sagnik/research/inkscapesvgprocessing/transformparser/impl/TransformParser;)V
      97: invokevirtual #362                // Method scala/util/parsing/combinator/Parsers$Parser.$tilde:(Lscala/Function0;)Lscala/util/parsing/combinator/Parsers$Parser;
     100: new           #588                // class edu/psu/sagnik/research/inkscapesvgprocessing/transformparser/impl/TransformParser$$anonfun$translate$8
     103: dup
     104: aload_0
     105: invokespecial #589                // Method edu/psu/sagnik/research/inkscapesvgprocessing/transformparser/impl/TransformParser$$anonfun$translate$8."<init>":(Ledu/psu/sagnik/research/inkscapesvgprocessing/transformparser/impl/TransformParser;)V
     108: invokevirtual #348                // Method scala/util/parsing/combinator/Parsers$Parser.$up$up:(Lscala/Function1;)Lscala/util/parsing/combinator/Parsers$Parser;
     111: areturn

  public scala.util.parsing.combinator.Parsers$Parser<edu.psu.sagnik.research.inkscapesvgprocessing.transformparser.model.MatrixOp> matrix();
    Code:
       0: aload_0
       1: new           #320                // class scala/collection/immutable/StringOps
       4: dup
       5: getstatic     #325                // Field scala/Predef$.MODULE$:Lscala/Predef$;
       8: ldc_w         #591                // String matrix
      11: invokevirtual #331                // Method scala/Predef$.augmentString:(Ljava/lang/String;)Ljava/lang/String;
      14: invokespecial #334                // Method scala/collection/immutable/StringOps."<init>":(Ljava/lang/String;)V
      17: invokevirtual #336                // Method scala/collection/immutable/StringOps.r:()Lscala/util/matching/Regex;
      20: invokevirtual #338                // Method regex:(Lscala/util/matching/Regex;)Lscala/util/parsing/combinator/Parsers$Parser;
      23: new           #593                // class edu/psu/sagnik/research/inkscapesvgprocessing/transformparser/impl/TransformParser$$anonfun$matrix$1
      26: dup
      27: aload_0
      28: invokespecial #594                // Method edu/psu/sagnik/research/inkscapesvgprocessing/transformparser/impl/TransformParser$$anonfun$matrix$1."<init>":(Ledu/psu/sagnik/research/inkscapesvgprocessing/transformparser/impl/TransformParser;)V
      31: invokevirtual #362                // Method scala/util/parsing/combinator/Parsers$Parser.$tilde:(Lscala/Function0;)Lscala/util/parsing/combinator/Parsers$Parser;
      34: new           #596                // class edu/psu/sagnik/research/inkscapesvgprocessing/transformparser/impl/TransformParser$$anonfun$matrix$2
      37: dup
      38: aload_0
      39: invokespecial #597                // Method edu/psu/sagnik/research/inkscapesvgprocessing/transformparser/impl/TransformParser$$anonfun$matrix$2."<init>":(Ledu/psu/sagnik/research/inkscapesvgprocessing/transformparser/impl/TransformParser;)V
      42: invokevirtual #362                // Method scala/util/parsing/combinator/Parsers$Parser.$tilde:(Lscala/Function0;)Lscala/util/parsing/combinator/Parsers$Parser;
      45: new           #599                // class edu/psu/sagnik/research/inkscapesvgprocessing/transformparser/impl/TransformParser$$anonfun$matrix$3
      48: dup
      49: aload_0
      50: invokespecial #600                // Method edu/psu/sagnik/research/inkscapesvgprocessing/transformparser/impl/TransformParser$$anonfun$matrix$3."<init>":(Ledu/psu/sagnik/research/inkscapesvgprocessing/transformparser/impl/TransformParser;)V
      53: invokevirtual #362                // Method scala/util/parsing/combinator/Parsers$Parser.$tilde:(Lscala/Function0;)Lscala/util/parsing/combinator/Parsers$Parser;
      56: new           #602                // class edu/psu/sagnik/research/inkscapesvgprocessing/transformparser/impl/TransformParser$$anonfun$matrix$4
      59: dup
      60: aload_0
      61: invokespecial #603                // Method edu/psu/sagnik/research/inkscapesvgprocessing/transformparser/impl/TransformParser$$anonfun$matrix$4."<init>":(Ledu/psu/sagnik/research/inkscapesvgprocessing/transformparser/impl/TransformParser;)V
      64: invokevirtual #362                // Method scala/util/parsing/combinator/Parsers$Parser.$tilde:(Lscala/Function0;)Lscala/util/parsing/combinator/Parsers$Parser;
      67: new           #605                // class edu/psu/sagnik/research/inkscapesvgprocessing/transformparser/impl/TransformParser$$anonfun$matrix$5
      70: dup
      71: aload_0
      72: invokespecial #606                // Method edu/psu/sagnik/research/inkscapesvgprocessing/transformparser/impl/TransformParser$$anonfun$matrix$5."<init>":(Ledu/psu/sagnik/research/inkscapesvgprocessing/transformparser/impl/TransformParser;)V
      75: invokevirtual #362                // Method scala/util/parsing/combinator/Parsers$Parser.$tilde:(Lscala/Function0;)Lscala/util/parsing/combinator/Parsers$Parser;
      78: new           #608                // class edu/psu/sagnik/research/inkscapesvgprocessing/transformparser/impl/TransformParser$$anonfun$matrix$6
      81: dup
      82: aload_0
      83: invokespecial #609                // Method edu/psu/sagnik/research/inkscapesvgprocessing/transformparser/impl/TransformParser$$anonfun$matrix$6."<init>":(Ledu/psu/sagnik/research/inkscapesvgprocessing/transformparser/impl/TransformParser;)V
      86: invokevirtual #362                // Method scala/util/parsing/combinator/Parsers$Parser.$tilde:(Lscala/Function0;)Lscala/util/parsing/combinator/Parsers$Parser;
      89: new           #611                // class edu/psu/sagnik/research/inkscapesvgprocessing/transformparser/impl/TransformParser$$anonfun$matrix$7
      92: dup
      93: aload_0
      94: invokespecial #612                // Method edu/psu/sagnik/research/inkscapesvgprocessing/transformparser/impl/TransformParser$$anonfun$matrix$7."<init>":(Ledu/psu/sagnik/research/inkscapesvgprocessing/transformparser/impl/TransformParser;)V
      97: invokevirtual #362                // Method scala/util/parsing/combinator/Parsers$Parser.$tilde:(Lscala/Function0;)Lscala/util/parsing/combinator/Parsers$Parser;
     100: new           #614                // class edu/psu/sagnik/research/inkscapesvgprocessing/transformparser/impl/TransformParser$$anonfun$matrix$8
     103: dup
     104: aload_0
     105: invokespecial #615                // Method edu/psu/sagnik/research/inkscapesvgprocessing/transformparser/impl/TransformParser$$anonfun$matrix$8."<init>":(Ledu/psu/sagnik/research/inkscapesvgprocessing/transformparser/impl/TransformParser;)V
     108: invokevirtual #362                // Method scala/util/parsing/combinator/Parsers$Parser.$tilde:(Lscala/Function0;)Lscala/util/parsing/combinator/Parsers$Parser;
     111: new           #617                // class edu/psu/sagnik/research/inkscapesvgprocessing/transformparser/impl/TransformParser$$anonfun$matrix$9
     114: dup
     115: aload_0
     116: invokespecial #618                // Method edu/psu/sagnik/research/inkscapesvgprocessing/transformparser/impl/TransformParser$$anonfun$matrix$9."<init>":(Ledu/psu/sagnik/research/inkscapesvgprocessing/transformparser/impl/TransformParser;)V
     119: invokevirtual #362                // Method scala/util/parsing/combinator/Parsers$Parser.$tilde:(Lscala/Function0;)Lscala/util/parsing/combinator/Parsers$Parser;
     122: new           #620                // class edu/psu/sagnik/research/inkscapesvgprocessing/transformparser/impl/TransformParser$$anonfun$matrix$10
     125: dup
     126: aload_0
     127: invokespecial #621                // Method edu/psu/sagnik/research/inkscapesvgprocessing/transformparser/impl/TransformParser$$anonfun$matrix$10."<init>":(Ledu/psu/sagnik/research/inkscapesvgprocessing/transformparser/impl/TransformParser;)V
     130: invokevirtual #362                // Method scala/util/parsing/combinator/Parsers$Parser.$tilde:(Lscala/Function0;)Lscala/util/parsing/combinator/Parsers$Parser;
     133: new           #623                // class edu/psu/sagnik/research/inkscapesvgprocessing/transformparser/impl/TransformParser$$anonfun$matrix$11
     136: dup
     137: aload_0
     138: invokespecial #624                // Method edu/psu/sagnik/research/inkscapesvgprocessing/transformparser/impl/TransformParser$$anonfun$matrix$11."<init>":(Ledu/psu/sagnik/research/inkscapesvgprocessing/transformparser/impl/TransformParser;)V
     141: invokevirtual #362                // Method scala/util/parsing/combinator/Parsers$Parser.$tilde:(Lscala/Function0;)Lscala/util/parsing/combinator/Parsers$Parser;
     144: new           #626                // class edu/psu/sagnik/research/inkscapesvgprocessing/transformparser/impl/TransformParser$$anonfun$matrix$12
     147: dup
     148: aload_0
     149: invokespecial #627                // Method edu/psu/sagnik/research/inkscapesvgprocessing/transformparser/impl/TransformParser$$anonfun$matrix$12."<init>":(Ledu/psu/sagnik/research/inkscapesvgprocessing/transformparser/impl/TransformParser;)V
     152: invokevirtual #362                // Method scala/util/parsing/combinator/Parsers$Parser.$tilde:(Lscala/Function0;)Lscala/util/parsing/combinator/Parsers$Parser;
     155: new           #629                // class edu/psu/sagnik/research/inkscapesvgprocessing/transformparser/impl/TransformParser$$anonfun$matrix$13
     158: dup
     159: aload_0
     160: invokespecial #630                // Method edu/psu/sagnik/research/inkscapesvgprocessing/transformparser/impl/TransformParser$$anonfun$matrix$13."<init>":(Ledu/psu/sagnik/research/inkscapesvgprocessing/transformparser/impl/TransformParser;)V
     163: invokevirtual #362                // Method scala/util/parsing/combinator/Parsers$Parser.$tilde:(Lscala/Function0;)Lscala/util/parsing/combinator/Parsers$Parser;
     166: new           #632                // class edu/psu/sagnik/research/inkscapesvgprocessing/transformparser/impl/TransformParser$$anonfun$matrix$14
     169: dup
     170: aload_0
     171: invokespecial #633                // Method edu/psu/sagnik/research/inkscapesvgprocessing/transformparser/impl/TransformParser$$anonfun$matrix$14."<init>":(Ledu/psu/sagnik/research/inkscapesvgprocessing/transformparser/impl/TransformParser;)V
     174: invokevirtual #362                // Method scala/util/parsing/combinator/Parsers$Parser.$tilde:(Lscala/Function0;)Lscala/util/parsing/combinator/Parsers$Parser;
     177: new           #635                // class edu/psu/sagnik/research/inkscapesvgprocessing/transformparser/impl/TransformParser$$anonfun$matrix$15
     180: dup
     181: aload_0
     182: invokespecial #636                // Method edu/psu/sagnik/research/inkscapesvgprocessing/transformparser/impl/TransformParser$$anonfun$matrix$15."<init>":(Ledu/psu/sagnik/research/inkscapesvgprocessing/transformparser/impl/TransformParser;)V
     185: invokevirtual #362                // Method scala/util/parsing/combinator/Parsers$Parser.$tilde:(Lscala/Function0;)Lscala/util/parsing/combinator/Parsers$Parser;
     188: new           #638                // class edu/psu/sagnik/research/inkscapesvgprocessing/transformparser/impl/TransformParser$$anonfun$matrix$16
     191: dup
     192: aload_0
     193: invokespecial #639                // Method edu/psu/sagnik/research/inkscapesvgprocessing/transformparser/impl/TransformParser$$anonfun$matrix$16."<init>":(Ledu/psu/sagnik/research/inkscapesvgprocessing/transformparser/impl/TransformParser;)V
     196: invokevirtual #362                // Method scala/util/parsing/combinator/Parsers$Parser.$tilde:(Lscala/Function0;)Lscala/util/parsing/combinator/Parsers$Parser;
     199: new           #641                // class edu/psu/sagnik/research/inkscapesvgprocessing/transformparser/impl/TransformParser$$anonfun$matrix$17
     202: dup
     203: aload_0
     204: invokespecial #642                // Method edu/psu/sagnik/research/inkscapesvgprocessing/transformparser/impl/TransformParser$$anonfun$matrix$17."<init>":(Ledu/psu/sagnik/research/inkscapesvgprocessing/transformparser/impl/TransformParser;)V
     207: invokevirtual #348                // Method scala/util/parsing/combinator/Parsers$Parser.$up$up:(Lscala/Function1;)Lscala/util/parsing/combinator/Parsers$Parser;
     210: areturn

  public scala.util.parsing.combinator.Parsers$Parser<edu.psu.sagnik.research.inkscapesvgprocessing.transformparser.model.TransformCommand> transform();
    Code:
       0: aload_0
       1: invokevirtual #645                // Method matrix:()Lscala/util/parsing/combinator/Parsers$Parser;
       4: new           #647                // class edu/psu/sagnik/research/inkscapesvgprocessing/transformparser/impl/TransformParser$$anonfun$transform$1
       7: dup
       8: aload_0
       9: invokespecial #648                // Method edu/psu/sagnik/research/inkscapesvgprocessing/transformparser/impl/TransformParser$$anonfun$transform$1."<init>":(Ledu/psu/sagnik/research/inkscapesvgprocessing/transformparser/impl/TransformParser;)V
      12: invokevirtual #348                // Method scala/util/parsing/combinator/Parsers$Parser.$up$up:(Lscala/Function1;)Lscala/util/parsing/combinator/Parsers$Parser;
      15: new           #650                // class edu/psu/sagnik/research/inkscapesvgprocessing/transformparser/impl/TransformParser$$anonfun$transform$2
      18: dup
      19: aload_0
      20: invokespecial #651                // Method edu/psu/sagnik/research/inkscapesvgprocessing/transformparser/impl/TransformParser$$anonfun$transform$2."<init>":(Ledu/psu/sagnik/research/inkscapesvgprocessing/transformparser/impl/TransformParser;)V
      23: invokevirtual #404                // Method scala/util/parsing/combinator/Parsers$Parser.$bar:(Lscala/Function0;)Lscala/util/parsing/combinator/Parsers$Parser;
      26: new           #653                // class edu/psu/sagnik/research/inkscapesvgprocessing/transformparser/impl/TransformParser$$anonfun$transform$3
      29: dup
      30: aload_0
      31: invokespecial #654                // Method edu/psu/sagnik/research/inkscapesvgprocessing/transformparser/impl/TransformParser$$anonfun$transform$3."<init>":(Ledu/psu/sagnik/research/inkscapesvgprocessing/transformparser/impl/TransformParser;)V
      34: invokevirtual #404                // Method scala/util/parsing/combinator/Parsers$Parser.$bar:(Lscala/Function0;)Lscala/util/parsing/combinator/Parsers$Parser;
      37: new           #656                // class edu/psu/sagnik/research/inkscapesvgprocessing/transformparser/impl/TransformParser$$anonfun$transform$4
      40: dup
      41: aload_0
      42: invokespecial #657                // Method edu/psu/sagnik/research/inkscapesvgprocessing/transformparser/impl/TransformParser$$anonfun$transform$4."<init>":(Ledu/psu/sagnik/research/inkscapesvgprocessing/transformparser/impl/TransformParser;)V
      45: invokevirtual #404                // Method scala/util/parsing/combinator/Parsers$Parser.$bar:(Lscala/Function0;)Lscala/util/parsing/combinator/Parsers$Parser;
      48: new           #659                // class edu/psu/sagnik/research/inkscapesvgprocessing/transformparser/impl/TransformParser$$anonfun$transform$5
      51: dup
      52: aload_0
      53: invokespecial #660                // Method edu/psu/sagnik/research/inkscapesvgprocessing/transformparser/impl/TransformParser$$anonfun$transform$5."<init>":(Ledu/psu/sagnik/research/inkscapesvgprocessing/transformparser/impl/TransformParser;)V
      56: invokevirtual #404                // Method scala/util/parsing/combinator/Parsers$Parser.$bar:(Lscala/Function0;)Lscala/util/parsing/combinator/Parsers$Parser;
      59: new           #662                // class edu/psu/sagnik/research/inkscapesvgprocessing/transformparser/impl/TransformParser$$anonfun$transform$6
      62: dup
      63: aload_0
      64: invokespecial #663                // Method edu/psu/sagnik/research/inkscapesvgprocessing/transformparser/impl/TransformParser$$anonfun$transform$6."<init>":(Ledu/psu/sagnik/research/inkscapesvgprocessing/transformparser/impl/TransformParser;)V
      67: invokevirtual #404                // Method scala/util/parsing/combinator/Parsers$Parser.$bar:(Lscala/Function0;)Lscala/util/parsing/combinator/Parsers$Parser;
      70: areturn

  public scala.util.parsing.combinator.Parsers$Parser<scala.collection.Seq<edu.psu.sagnik.research.inkscapesvgprocessing.transformparser.model.TransformCommand>> transforms();
    Code:
       0: aload_0
       1: invokevirtual #666                // Method transform:()Lscala/util/parsing/combinator/Parsers$Parser;
       4: new           #668                // class edu/psu/sagnik/research/inkscapesvgprocessing/transformparser/impl/TransformParser$$anonfun$transforms$1
       7: dup
       8: aload_0
       9: invokespecial #669                // Method edu/psu/sagnik/research/inkscapesvgprocessing/transformparser/impl/TransformParser$$anonfun$transforms$1."<init>":(Ledu/psu/sagnik/research/inkscapesvgprocessing/transformparser/impl/TransformParser;)V
      12: invokevirtual #362                // Method scala/util/parsing/combinator/Parsers$Parser.$tilde:(Lscala/Function0;)Lscala/util/parsing/combinator/Parsers$Parser;
      15: new           #671                // class edu/psu/sagnik/research/inkscapesvgprocessing/transformparser/impl/TransformParser$$anonfun$transforms$2
      18: dup
      19: aload_0
      20: invokespecial #672                // Method edu/psu/sagnik/research/inkscapesvgprocessing/transformparser/impl/TransformParser$$anonfun$transforms$2."<init>":(Ledu/psu/sagnik/research/inkscapesvgprocessing/transformparser/impl/TransformParser;)V
      23: invokevirtual #362                // Method scala/util/parsing/combinator/Parsers$Parser.$tilde:(Lscala/Function0;)Lscala/util/parsing/combinator/Parsers$Parser;
      26: new           #674                // class edu/psu/sagnik/research/inkscapesvgprocessing/transformparser/impl/TransformParser$$anonfun$transforms$3
      29: dup
      30: aload_0
      31: invokespecial #675                // Method edu/psu/sagnik/research/inkscapesvgprocessing/transformparser/impl/TransformParser$$anonfun$transforms$3."<init>":(Ledu/psu/sagnik/research/inkscapesvgprocessing/transformparser/impl/TransformParser;)V
      34: invokevirtual #362                // Method scala/util/parsing/combinator/Parsers$Parser.$tilde:(Lscala/Function0;)Lscala/util/parsing/combinator/Parsers$Parser;
      37: new           #677                // class edu/psu/sagnik/research/inkscapesvgprocessing/transformparser/impl/TransformParser$$anonfun$transforms$4
      40: dup
      41: aload_0
      42: invokespecial #678                // Method edu/psu/sagnik/research/inkscapesvgprocessing/transformparser/impl/TransformParser$$anonfun$transforms$4."<init>":(Ledu/psu/sagnik/research/inkscapesvgprocessing/transformparser/impl/TransformParser;)V
      45: invokevirtual #348                // Method scala/util/parsing/combinator/Parsers$Parser.$up$up:(Lscala/Function1;)Lscala/util/parsing/combinator/Parsers$Parser;
      48: new           #680                // class edu/psu/sagnik/research/inkscapesvgprocessing/transformparser/impl/TransformParser$$anonfun$transforms$5
      51: dup
      52: aload_0
      53: invokespecial #681                // Method edu/psu/sagnik/research/inkscapesvgprocessing/transformparser/impl/TransformParser$$anonfun$transforms$5."<init>":(Ledu/psu/sagnik/research/inkscapesvgprocessing/transformparser/impl/TransformParser;)V
      56: invokevirtual #404                // Method scala/util/parsing/combinator/Parsers$Parser.$bar:(Lscala/Function0;)Lscala/util/parsing/combinator/Parsers$Parser;
      59: areturn

  public scala.util.parsing.combinator.Parsers$Parser<scala.Option<scala.collection.Seq<edu.psu.sagnik.research.inkscapesvgprocessing.transformparser.model.TransformCommand>>> transform_list();
    Code:
       0: aload_0
       1: new           #684                // class edu/psu/sagnik/research/inkscapesvgprocessing/transformparser/impl/TransformParser$$anonfun$transform_list$1
       4: dup
       5: aload_0
       6: invokespecial #685                // Method edu/psu/sagnik/research/inkscapesvgprocessing/transformparser/impl/TransformParser$$anonfun$transform_list$1."<init>":(Ledu/psu/sagnik/research/inkscapesvgprocessing/transformparser/impl/TransformParser;)V
       9: invokevirtual #687                // Method rep:(Lscala/Function0;)Lscala/util/parsing/combinator/Parsers$Parser;
      12: new           #689                // class edu/psu/sagnik/research/inkscapesvgprocessing/transformparser/impl/TransformParser$$anonfun$transform_list$2
      15: dup
      16: aload_0
      17: invokespecial #690                // Method edu/psu/sagnik/research/inkscapesvgprocessing/transformparser/impl/TransformParser$$anonfun$transform_list$2."<init>":(Ledu/psu/sagnik/research/inkscapesvgprocessing/transformparser/impl/TransformParser;)V
      20: invokevirtual #362                // Method scala/util/parsing/combinator/Parsers$Parser.$tilde:(Lscala/Function0;)Lscala/util/parsing/combinator/Parsers$Parser;
      23: new           #692                // class edu/psu/sagnik/research/inkscapesvgprocessing/transformparser/impl/TransformParser$$anonfun$transform_list$3
      26: dup
      27: aload_0
      28: invokespecial #693                // Method edu/psu/sagnik/research/inkscapesvgprocessing/transformparser/impl/TransformParser$$anonfun$transform_list$3."<init>":(Ledu/psu/sagnik/research/inkscapesvgprocessing/transformparser/impl/TransformParser;)V
      31: invokevirtual #362                // Method scala/util/parsing/combinator/Parsers$Parser.$tilde:(Lscala/Function0;)Lscala/util/parsing/combinator/Parsers$Parser;
      34: new           #695                // class edu/psu/sagnik/research/inkscapesvgprocessing/transformparser/impl/TransformParser$$anonfun$transform_list$4
      37: dup
      38: aload_0
      39: invokespecial #696                // Method edu/psu/sagnik/research/inkscapesvgprocessing/transformparser/impl/TransformParser$$anonfun$transform_list$4."<init>":(Ledu/psu/sagnik/research/inkscapesvgprocessing/transformparser/impl/TransformParser;)V
      42: invokevirtual #348                // Method scala/util/parsing/combinator/Parsers$Parser.$up$up:(Lscala/Function1;)Lscala/util/parsing/combinator/Parsers$Parser;
      45: areturn

  public double digitReduce(double);
    Code:
       0: getstatic     #703                // Field scala/package$.MODULE$:Lscala/package$;
       3: invokevirtual #707                // Method scala/package$.BigDecimal:()Lscala/math/BigDecimal$;
       6: dload_1
       7: invokevirtual #712                // Method scala/math/BigDecimal$.apply:(D)Lscala/math/BigDecimal;
      10: iconst_2
      11: getstatic     #717                // Field scala/math/BigDecimal$RoundingMode$.MODULE$:Lscala/math/BigDecimal$RoundingMode$;
      14: invokevirtual #721                // Method scala/math/BigDecimal$RoundingMode$.HALF_UP:()Lscala/Enumeration$Value;
      17: invokevirtual #727                // Method scala/math/BigDecimal.setScale:(ILscala/Enumeration$Value;)Lscala/math/BigDecimal;
      20: invokevirtual #731                // Method scala/math/BigDecimal.toDouble:()D
      23: dreturn

  public double D2R(double);
    Code:
       0: dload_1
       1: ldc2_w        #735                // double 0.017453292519943295d
       4: dmul
       5: dreturn

  public double R2D(double);
    Code:
       0: dload_1
       1: ldc2_w        #735                // double 0.017453292519943295d
       4: ddiv
       5: dreturn

  public double cosine(double);
    Code:
       0: aload_0
       1: getstatic     #744                // Field scala/math/package$.MODULE$:Lscala/math/package$;
       4: aload_0
       5: dload_1
       6: invokevirtual #746                // Method D2R:(D)D
       9: invokevirtual #749                // Method scala/math/package$.cos:(D)D
      12: invokevirtual #751                // Method digitReduce:(D)D
      15: dreturn

  public double sine(double);
    Code:
       0: aload_0
       1: getstatic     #744                // Field scala/math/package$.MODULE$:Lscala/math/package$;
       4: aload_0
       5: dload_1
       6: invokevirtual #746                // Method D2R:(D)D
       9: invokevirtual #755                // Method scala/math/package$.sin:(D)D
      12: invokevirtual #751                // Method digitReduce:(D)D
      15: dreturn

  public double tan(double);
    Code:
       0: aload_0
       1: getstatic     #744                // Field scala/math/package$.MODULE$:Lscala/math/package$;
       4: aload_0
       5: dload_1
       6: invokevirtual #746                // Method D2R:(D)D
       9: invokevirtual #758                // Method scala/math/package$.tan:(D)D
      12: invokevirtual #751                // Method digitReduce:(D)D
      15: dreturn

  public <A> breeze.linalg.DenseMatrix<java.lang.Object> getMatrix(A);
    Code:
       0: aload_1
       1: astore_2
       2: aload_2
       3: instanceof    #762                // class edu/psu/sagnik/research/inkscapesvgprocessing/transformparser/model/MatrixOp
       6: ifeq          126
       9: aload_2
      10: checkcast     #762                // class edu/psu/sagnik/research/inkscapesvgprocessing/transformparser/model/MatrixOp
      13: astore_3
      14: aload_3
      15: invokevirtual #766                // Method edu/psu/sagnik/research/inkscapesvgprocessing/transformparser/model/MatrixOp.args:()Ledu/psu/sagnik/research/inkscapesvgprocessing/transformparser/model/MatrixOpArg;
      18: astore        5
      20: getstatic     #771                // Field scala/Array$.MODULE$:Lscala/Array$;
      23: getstatic     #325                // Field scala/Predef$.MODULE$:Lscala/Predef$;
      26: bipush        9
      28: newarray       float
      30: dup
      31: iconst_0
      32: aload         5
      34: invokevirtual #777                // Method edu/psu/sagnik/research/inkscapesvgprocessing/transformparser/model/MatrixOpArg.a:()F
      37: fastore
      38: dup
      39: iconst_1
      40: aload         5
      42: invokevirtual #780                // Method edu/psu/sagnik/research/inkscapesvgprocessing/transformparser/model/MatrixOpArg.b:()F
      45: fastore
      46: dup
      47: iconst_2
      48: fconst_0
      49: fastore
      50: dup
      51: iconst_3
      52: aload         5
      54: invokevirtual #783                // Method edu/psu/sagnik/research/inkscapesvgprocessing/transformparser/model/MatrixOpArg.c:()F
      57: fastore
      58: dup
      59: iconst_4
      60: aload         5
      62: invokevirtual #785                // Method edu/psu/sagnik/research/inkscapesvgprocessing/transformparser/model/MatrixOpArg.d:()F
      65: fastore
      66: dup
      67: iconst_5
      68: fconst_0
      69: fastore
      70: dup
      71: bipush        6
      73: aload         5
      75: invokevirtual #787                // Method edu/psu/sagnik/research/inkscapesvgprocessing/transformparser/model/MatrixOpArg.e:()F
      78: fastore
      79: dup
      80: bipush        7
      82: aload         5
      84: invokevirtual #789                // Method edu/psu/sagnik/research/inkscapesvgprocessing/transformparser/model/MatrixOpArg.f:()F
      87: fastore
      88: dup
      89: bipush        8
      91: fconst_1
      92: fastore
      93: invokevirtual #793                // Method scala/Predef$.wrapFloatArray:([F)Lscala/collection/mutable/WrappedArray;
      96: getstatic     #798                // Field scala/reflect/ClassTag$.MODULE$:Lscala/reflect/ClassTag$;
      99: invokevirtual #802                // Method scala/reflect/ClassTag$.Float:()Lscala/reflect/ClassTag;
     102: invokevirtual #805                // Method scala/Array$.apply:(Lscala/collection/Seq;Lscala/reflect/ClassTag;)Ljava/lang/Object;
     105: checkcast     #807                // class "[F"
     108: astore        6
     110: new           #809                // class breeze/linalg/DenseMatrix$mcF$sp
     113: dup
     114: iconst_3
     115: iconst_3
     116: aload         6
     118: invokespecial #812                // Method breeze/linalg/DenseMatrix$mcF$sp."<init>":(II[F)V
     121: astore        4
     123: goto          1148
     126: aload_2
     127: instanceof    #814                // class edu/psu/sagnik/research/inkscapesvgprocessing/transformparser/model/TranslateOp
     130: ifeq          279
     133: aload_2
     134: checkcast     #814                // class edu/psu/sagnik/research/inkscapesvgprocessing/transformparser/model/TranslateOp
     137: astore        7
     139: aload         7
     141: invokevirtual #817                // Method edu/psu/sagnik/research/inkscapesvgprocessing/transformparser/model/TranslateOp.args:()Ledu/psu/sagnik/research/inkscapesvgprocessing/transformparser/model/TranslateOpArg;
     144: astore        8
     146: aload         8
     148: invokevirtual #823                // Method edu/psu/sagnik/research/inkscapesvgprocessing/transformparser/model/TranslateOpArg.tY:()Lscala/Option;
     151: astore        10
     153: aload         10
     155: instanceof    #825                // class scala/Some
     158: ifeq          185
     161: aload         10
     163: checkcast     #825                // class scala/Some
     166: astore        11
     168: aload         11
     170: invokevirtual #829                // Method scala/Some.x:()Ljava/lang/Object;
     173: invokestatic  #835                // Method scala/runtime/BoxesRunTime.unboxToFloat:(Ljava/lang/Object;)F
     176: fstore        12
     178: fload         12
     180: fstore        13
     182: goto          188
     185: fconst_0
     186: fstore        13
     188: fload         13
     190: fstore        9
     192: getstatic     #771                // Field scala/Array$.MODULE$:Lscala/Array$;
     195: getstatic     #325                // Field scala/Predef$.MODULE$:Lscala/Predef$;
     198: bipush        9
     200: newarray       float
     202: dup
     203: iconst_0
     204: fconst_1
     205: fastore
     206: dup
     207: iconst_1
     208: fconst_0
     209: fastore
     210: dup
     211: iconst_2
     212: fconst_0
     213: fastore
     214: dup
     215: iconst_3
     216: fconst_0
     217: fastore
     218: dup
     219: iconst_4
     220: fconst_1
     221: fastore
     222: dup
     223: iconst_5
     224: fconst_0
     225: fastore
     226: dup
     227: bipush        6
     229: aload         8
     231: invokevirtual #838                // Method edu/psu/sagnik/research/inkscapesvgprocessing/transformparser/model/TranslateOpArg.tX:()F
     234: fastore
     235: dup
     236: bipush        7
     238: fload         9
     240: fastore
     241: dup
     242: bipush        8
     244: fconst_1
     245: fastore
     246: invokevirtual #793                // Method scala/Predef$.wrapFloatArray:([F)Lscala/collection/mutable/WrappedArray;
     249: getstatic     #798                // Field scala/reflect/ClassTag$.MODULE$:Lscala/reflect/ClassTag$;
     252: invokevirtual #802                // Method scala/reflect/ClassTag$.Float:()Lscala/reflect/ClassTag;
     255: invokevirtual #805                // Method scala/Array$.apply:(Lscala/collection/Seq;Lscala/reflect/ClassTag;)Ljava/lang/Object;
     258: checkcast     #807                // class "[F"
     261: astore        14
     263: new           #809                // class breeze/linalg/DenseMatrix$mcF$sp
     266: dup
     267: iconst_3
     268: iconst_3
     269: aload         14
     271: invokespecial #812                // Method breeze/linalg/DenseMatrix$mcF$sp."<init>":(II[F)V
     274: astore        4
     276: goto          1148
     279: aload_2
     280: instanceof    #840                // class edu/psu/sagnik/research/inkscapesvgprocessing/transformparser/model/ScaleOp
     283: ifeq          436
     286: aload_2
     287: checkcast     #840                // class edu/psu/sagnik/research/inkscapesvgprocessing/transformparser/model/ScaleOp
     290: astore        15
     292: aload         15
     294: invokevirtual #843                // Method edu/psu/sagnik/research/inkscapesvgprocessing/transformparser/model/ScaleOp.args:()Ledu/psu/sagnik/research/inkscapesvgprocessing/transformparser/model/ScaleOpArg;
     297: astore        16
     299: aload         16
     301: invokevirtual #848                // Method edu/psu/sagnik/research/inkscapesvgprocessing/transformparser/model/ScaleOpArg.sY:()Lscala/Option;
     304: astore        18
     306: aload         18
     308: instanceof    #825                // class scala/Some
     311: ifeq          338
     314: aload         18
     316: checkcast     #825                // class scala/Some
     319: astore        19
     321: aload         19
     323: invokevirtual #829                // Method scala/Some.x:()Ljava/lang/Object;
     326: invokestatic  #835                // Method scala/runtime/BoxesRunTime.unboxToFloat:(Ljava/lang/Object;)F
     329: fstore        20
     331: fload         20
     333: fstore        21
     335: goto          345
     338: aload         16
     340: invokevirtual #851                // Method edu/psu/sagnik/research/inkscapesvgprocessing/transformparser/model/ScaleOpArg.sX:()F
     343: fstore        21
     345: fload         21
     347: fstore        17
     349: getstatic     #771                // Field scala/Array$.MODULE$:Lscala/Array$;
     352: getstatic     #325                // Field scala/Predef$.MODULE$:Lscala/Predef$;
     355: bipush        9
     357: newarray       float
     359: dup
     360: iconst_0
     361: aload         16
     363: invokevirtual #851                // Method edu/psu/sagnik/research/inkscapesvgprocessing/transformparser/model/ScaleOpArg.sX:()F
     366: fastore
     367: dup
     368: iconst_1
     369: fconst_0
     370: fastore
     371: dup
     372: iconst_2
     373: fconst_0
     374: fastore
     375: dup
     376: iconst_3
     377: fconst_0
     378: fastore
     379: dup
     380: iconst_4
     381: fload         17
     383: fastore
     384: dup
     385: iconst_5
     386: fconst_0
     387: fastore
     388: dup
     389: bipush        6
     391: fconst_0
     392: fastore
     393: dup
     394: bipush        7
     396: fconst_0
     397: fastore
     398: dup
     399: bipush        8
     401: fconst_1
     402: fastore
     403: invokevirtual #793                // Method scala/Predef$.wrapFloatArray:([F)Lscala/collection/mutable/WrappedArray;
     406: getstatic     #798                // Field scala/reflect/ClassTag$.MODULE$:Lscala/reflect/ClassTag$;
     409: invokevirtual #802                // Method scala/reflect/ClassTag$.Float:()Lscala/reflect/ClassTag;
     412: invokevirtual #805                // Method scala/Array$.apply:(Lscala/collection/Seq;Lscala/reflect/ClassTag;)Ljava/lang/Object;
     415: checkcast     #807                // class "[F"
     418: astore        22
     420: new           #809                // class breeze/linalg/DenseMatrix$mcF$sp
     423: dup
     424: iconst_3
     425: iconst_3
     426: aload         22
     428: invokespecial #812                // Method breeze/linalg/DenseMatrix$mcF$sp."<init>":(II[F)V
     431: astore        4
     433: goto          1148
     436: aload_2
     437: instanceof    #853                // class edu/psu/sagnik/research/inkscapesvgprocessing/transformparser/model/RotateOp
     440: ifeq          927
     443: aload_2
     444: checkcast     #853                // class edu/psu/sagnik/research/inkscapesvgprocessing/transformparser/model/RotateOp
     447: astore        23
     449: aload         23
     451: invokevirtual #856                // Method edu/psu/sagnik/research/inkscapesvgprocessing/transformparser/model/RotateOp.args:()Ledu/psu/sagnik/research/inkscapesvgprocessing/transformparser/model/RotateOpArg;
     454: astore        24
     456: aload         24
     458: invokevirtual #861                // Method edu/psu/sagnik/research/inkscapesvgprocessing/transformparser/model/RotateOpArg.translateArg:()Lscala/Option;
     461: astore        26
     463: aload         26
     465: instanceof    #825                // class scala/Some
     468: ifeq          535
     471: aload         26
     473: checkcast     #825                // class scala/Some
     476: astore        27
     478: aload         27
     480: invokevirtual #829                // Method scala/Some.x:()Ljava/lang/Object;
     483: checkcast     #863                // class scala/Tuple2
     486: astore        28
     488: aload         28
     490: ifnull        535
     493: aload         28
     495: invokevirtual #866                // Method scala/Tuple2._1:()Ljava/lang/Object;
     498: invokestatic  #835                // Method scala/runtime/BoxesRunTime.unboxToFloat:(Ljava/lang/Object;)F
     501: fstore        29
     503: aload         28
     505: invokevirtual #869                // Method scala/Tuple2._2:()Ljava/lang/Object;
     508: invokestatic  #835                // Method scala/runtime/BoxesRunTime.unboxToFloat:(Ljava/lang/Object;)F
     511: fstore        30
     513: new           #863                // class scala/Tuple2
     516: dup
     517: fload         29
     519: invokestatic  #873                // Method scala/runtime/BoxesRunTime.boxToFloat:(F)Ljava/lang/Float;
     522: fload         30
     524: invokestatic  #873                // Method scala/runtime/BoxesRunTime.boxToFloat:(F)Ljava/lang/Float;
     527: invokespecial #876                // Method scala/Tuple2."<init>":(Ljava/lang/Object;Ljava/lang/Object;)V
     530: astore        31
     532: goto          552
     535: new           #863                // class scala/Tuple2
     538: dup
     539: fconst_0
     540: invokestatic  #873                // Method scala/runtime/BoxesRunTime.boxToFloat:(F)Ljava/lang/Float;
     543: fconst_0
     544: invokestatic  #873                // Method scala/runtime/BoxesRunTime.boxToFloat:(F)Ljava/lang/Float;
     547: invokespecial #876                // Method scala/Tuple2."<init>":(Ljava/lang/Object;Ljava/lang/Object;)V
     550: astore        31
     552: aload         31
     554: astore        25
     556: getstatic     #771                // Field scala/Array$.MODULE$:Lscala/Array$;
     559: getstatic     #325                // Field scala/Predef$.MODULE$:Lscala/Predef$;
     562: bipush        9
     564: newarray       float
     566: dup
     567: iconst_0
     568: aload_0
     569: aload         24
     571: invokevirtual #879                // Method edu/psu/sagnik/research/inkscapesvgprocessing/transformparser/model/RotateOpArg.rAngle:()F
     574: f2d
     575: invokevirtual #881                // Method cosine:(D)D
     578: d2f
     579: fastore
     580: dup
     581: iconst_1
     582: aload_0
     583: aload         24
     585: invokevirtual #879                // Method edu/psu/sagnik/research/inkscapesvgprocessing/transformparser/model/RotateOpArg.rAngle:()F
     588: f2d
     589: invokevirtual #883                // Method sine:(D)D
     592: d2f
     593: fastore
     594: dup
     595: iconst_2
     596: fconst_0
     597: fastore
     598: dup
     599: iconst_3
     600: aload_0
     601: aload         24
     603: invokevirtual #879                // Method edu/psu/sagnik/research/inkscapesvgprocessing/transformparser/model/RotateOpArg.rAngle:()F
     606: f2d
     607: invokevirtual #883                // Method sine:(D)D
     610: d2f
     611: fneg
     612: fastore
     613: dup
     614: iconst_4
     615: aload_0
     616: aload         24
     618: invokevirtual #879                // Method edu/psu/sagnik/research/inkscapesvgprocessing/transformparser/model/RotateOpArg.rAngle:()F
     621: f2d
     622: invokevirtual #881                // Method cosine:(D)D
     625: d2f
     626: fastore
     627: dup
     628: iconst_5
     629: fconst_0
     630: fastore
     631: dup
     632: bipush        6
     634: fconst_0
     635: fastore
     636: dup
     637: bipush        7
     639: fconst_0
     640: fastore
     641: dup
     642: bipush        8
     644: fconst_1
     645: fastore
     646: invokevirtual #793                // Method scala/Predef$.wrapFloatArray:([F)Lscala/collection/mutable/WrappedArray;
     649: getstatic     #798                // Field scala/reflect/ClassTag$.MODULE$:Lscala/reflect/ClassTag$;
     652: invokevirtual #802                // Method scala/reflect/ClassTag$.Float:()Lscala/reflect/ClassTag;
     655: invokevirtual #805                // Method scala/Array$.apply:(Lscala/collection/Seq;Lscala/reflect/ClassTag;)Ljava/lang/Object;
     658: checkcast     #807                // class "[F"
     661: astore        32
     663: aload         25
     665: invokevirtual #866                // Method scala/Tuple2._1:()Ljava/lang/Object;
     668: invokestatic  #835                // Method scala/runtime/BoxesRunTime.unboxToFloat:(Ljava/lang/Object;)F
     671: iconst_0
     672: i2f
     673: fcmpl
     674: ifne          705
     677: aload         25
     679: invokevirtual #869                // Method scala/Tuple2._2:()Ljava/lang/Object;
     682: invokestatic  #835                // Method scala/runtime/BoxesRunTime.unboxToFloat:(Ljava/lang/Object;)F
     685: iconst_0
     686: i2f
     687: fcmpl
     688: ifne          705
     691: new           #809                // class breeze/linalg/DenseMatrix$mcF$sp
     694: dup
     695: iconst_3
     696: iconst_3
     697: aload         32
     699: invokespecial #812                // Method breeze/linalg/DenseMatrix$mcF$sp."<init>":(II[F)V
     702: goto          922
     705: aload         25
     707: invokevirtual #866                // Method scala/Tuple2._1:()Ljava/lang/Object;
     710: invokestatic  #835                // Method scala/runtime/BoxesRunTime.unboxToFloat:(Ljava/lang/Object;)F
     713: fstore        33
     715: aload         25
     717: invokevirtual #869                // Method scala/Tuple2._2:()Ljava/lang/Object;
     720: invokestatic  #835                // Method scala/runtime/BoxesRunTime.unboxToFloat:(Ljava/lang/Object;)F
     723: fstore        34
     725: getstatic     #771                // Field scala/Array$.MODULE$:Lscala/Array$;
     728: getstatic     #325                // Field scala/Predef$.MODULE$:Lscala/Predef$;
     731: bipush        9
     733: newarray       float
     735: dup
     736: iconst_0
     737: fconst_1
     738: fastore
     739: dup
     740: iconst_1
     741: fconst_0
     742: fastore
     743: dup
     744: iconst_2
     745: fconst_0
     746: fastore
     747: dup
     748: iconst_3
     749: fconst_0
     750: fastore
     751: dup
     752: iconst_4
     753: fconst_1
     754: fastore
     755: dup
     756: iconst_5
     757: fconst_0
     758: fastore
     759: dup
     760: bipush        6
     762: fload         33
     764: fastore
     765: dup
     766: bipush        7
     768: fload         34
     770: fastore
     771: dup
     772: bipush        8
     774: fconst_1
     775: fastore
     776: invokevirtual #793                // Method scala/Predef$.wrapFloatArray:([F)Lscala/collection/mutable/WrappedArray;
     779: getstatic     #798                // Field scala/reflect/ClassTag$.MODULE$:Lscala/reflect/ClassTag$;
     782: invokevirtual #802                // Method scala/reflect/ClassTag$.Float:()Lscala/reflect/ClassTag;
     785: invokevirtual #805                // Method scala/Array$.apply:(Lscala/collection/Seq;Lscala/reflect/ClassTag;)Ljava/lang/Object;
     788: checkcast     #807                // class "[F"
     791: astore        35
     793: getstatic     #771                // Field scala/Array$.MODULE$:Lscala/Array$;
     796: getstatic     #325                // Field scala/Predef$.MODULE$:Lscala/Predef$;
     799: bipush        9
     801: newarray       float
     803: dup
     804: iconst_0
     805: fconst_1
     806: fastore
     807: dup
     808: iconst_1
     809: fconst_0
     810: fastore
     811: dup
     812: iconst_2
     813: fconst_0
     814: fastore
     815: dup
     816: iconst_3
     817: fconst_0
     818: fastore
     819: dup
     820: iconst_4
     821: fconst_1
     822: fastore
     823: dup
     824: iconst_5
     825: fconst_0
     826: fastore
     827: dup
     828: bipush        6
     830: fload         33
     832: fneg
     833: fastore
     834: dup
     835: bipush        7
     837: fload         34
     839: fneg
     840: fastore
     841: dup
     842: bipush        8
     844: fconst_1
     845: fastore
     846: invokevirtual #793                // Method scala/Predef$.wrapFloatArray:([F)Lscala/collection/mutable/WrappedArray;
     849: getstatic     #798                // Field scala/reflect/ClassTag$.MODULE$:Lscala/reflect/ClassTag$;
     852: invokevirtual #802                // Method scala/reflect/ClassTag$.Float:()Lscala/reflect/ClassTag;
     855: invokevirtual #805                // Method scala/Array$.apply:(Lscala/collection/Seq;Lscala/reflect/ClassTag;)Ljava/lang/Object;
     858: checkcast     #807                // class "[F"
     861: astore        36
     863: new           #809                // class breeze/linalg/DenseMatrix$mcF$sp
     866: dup
     867: iconst_3
     868: iconst_3
     869: aload         35
     871: invokespecial #812                // Method breeze/linalg/DenseMatrix$mcF$sp."<init>":(II[F)V
     874: new           #809                // class breeze/linalg/DenseMatrix$mcF$sp
     877: dup
     878: iconst_3
     879: iconst_3
     880: aload         32
     882: invokespecial #812                // Method breeze/linalg/DenseMatrix$mcF$sp."<init>":(II[F)V
     885: getstatic     #888                // Field breeze/linalg/DenseMatrix$.MODULE$:Lbreeze/linalg/DenseMatrix$;
     888: invokevirtual #892                // Method breeze/linalg/DenseMatrix$.implOpMulMatrix_DMF_DMF_eq_DMF:()Lbreeze/linalg/operators/DenseMatrixFloatMultiplyStuff$implOpMulMatrix_DMF_DMF_eq_DMF$;
     891: invokevirtual #896                // Method breeze/linalg/DenseMatrix$mcF$sp.$times:(Ljava/lang/Object;Lbreeze/generic/UFunc$UImpl2;)Ljava/lang/Object;
     894: checkcast     #898                // class breeze/linalg/ImmutableNumericOps
     897: new           #809                // class breeze/linalg/DenseMatrix$mcF$sp
     900: dup
     901: iconst_3
     902: iconst_3
     903: aload         36
     905: invokespecial #812                // Method breeze/linalg/DenseMatrix$mcF$sp."<init>":(II[F)V
     908: getstatic     #888                // Field breeze/linalg/DenseMatrix$.MODULE$:Lbreeze/linalg/DenseMatrix$;
     911: invokevirtual #892                // Method breeze/linalg/DenseMatrix$.implOpMulMatrix_DMF_DMF_eq_DMF:()Lbreeze/linalg/operators/DenseMatrixFloatMultiplyStuff$implOpMulMatrix_DMF_DMF_eq_DMF$;
     914: invokeinterface #899,  3          // InterfaceMethod breeze/linalg/ImmutableNumericOps.$times:(Ljava/lang/Object;Lbreeze/generic/UFunc$UImpl2;)Ljava/lang/Object;
     919: checkcast     #901                // class breeze/linalg/DenseMatrix
     922: astore        4
     924: goto          1148
     927: aload_2
     928: instanceof    #903                // class edu/psu/sagnik/research/inkscapesvgprocessing/transformparser/model/SkewXOp
     931: ifeq          1039
     934: aload_2
     935: checkcast     #903                // class edu/psu/sagnik/research/inkscapesvgprocessing/transformparser/model/SkewXOp
     938: astore        37
     940: aload         37
     942: invokevirtual #906                // Method edu/psu/sagnik/research/inkscapesvgprocessing/transformparser/model/SkewXOp.args:()Ledu/psu/sagnik/research/inkscapesvgprocessing/transformparser/model/SkewXOpArg;
     945: astore        38
     947: getstatic     #771                // Field scala/Array$.MODULE$:Lscala/Array$;
     950: getstatic     #325                // Field scala/Predef$.MODULE$:Lscala/Predef$;
     953: bipush        9
     955: newarray       float
     957: dup
     958: iconst_0
     959: fconst_1
     960: fastore
     961: dup
     962: iconst_1
     963: fconst_0
     964: fastore
     965: dup
     966: iconst_2
     967: fconst_0
     968: fastore
     969: dup
     970: iconst_3
     971: aload_0
     972: aload         38
     974: invokevirtual #911                // Method edu/psu/sagnik/research/inkscapesvgprocessing/transformparser/model/SkewXOpArg.skAngle:()F
     977: f2d
     978: invokevirtual #912                // Method tan:(D)D
     981: d2f
     982: fastore
     983: dup
     984: iconst_4
     985: fconst_1
     986: fastore
     987: dup
     988: iconst_5
     989: fconst_0
     990: fastore
     991: dup
     992: bipush        6
     994: fconst_0
     995: fastore
     996: dup
     997: bipush        7
     999: fconst_0
    1000: fastore
    1001: dup
    1002: bipush        8
    1004: fconst_1
    1005: fastore
    1006: invokevirtual #793                // Method scala/Predef$.wrapFloatArray:([F)Lscala/collection/mutable/WrappedArray;
    1009: getstatic     #798                // Field scala/reflect/ClassTag$.MODULE$:Lscala/reflect/ClassTag$;
    1012: invokevirtual #802                // Method scala/reflect/ClassTag$.Float:()Lscala/reflect/ClassTag;
    1015: invokevirtual #805                // Method scala/Array$.apply:(Lscala/collection/Seq;Lscala/reflect/ClassTag;)Ljava/lang/Object;
    1018: checkcast     #807                // class "[F"
    1021: astore        39
    1023: new           #809                // class breeze/linalg/DenseMatrix$mcF$sp
    1026: dup
    1027: iconst_3
    1028: iconst_3
    1029: aload         39
    1031: invokespecial #812                // Method breeze/linalg/DenseMatrix$mcF$sp."<init>":(II[F)V
    1034: astore        4
    1036: goto          1148
    1039: aload_2
    1040: instanceof    #914                // class edu/psu/sagnik/research/inkscapesvgprocessing/transformparser/model/SkewYOp
    1043: ifeq          1151
    1046: aload_2
    1047: checkcast     #914                // class edu/psu/sagnik/research/inkscapesvgprocessing/transformparser/model/SkewYOp
    1050: astore        40
    1052: aload         40
    1054: invokevirtual #917                // Method edu/psu/sagnik/research/inkscapesvgprocessing/transformparser/model/SkewYOp.args:()Ledu/psu/sagnik/research/inkscapesvgprocessing/transformparser/model/SkewYOpArg;
    1057: astore        41
    1059: getstatic     #771                // Field scala/Array$.MODULE$:Lscala/Array$;
    1062: getstatic     #325                // Field scala/Predef$.MODULE$:Lscala/Predef$;
    1065: bipush        9
    1067: newarray       float
    1069: dup
    1070: iconst_0
    1071: fconst_1
    1072: fastore
    1073: dup
    1074: iconst_1
    1075: aload_0
    1076: aload         41
    1078: invokevirtual #920                // Method edu/psu/sagnik/research/inkscapesvgprocessing/transformparser/model/SkewYOpArg.skAngle:()F
    1081: f2d
    1082: invokevirtual #912                // Method tan:(D)D
    1085: d2f
    1086: fastore
    1087: dup
    1088: iconst_2
    1089: fconst_0
    1090: fastore
    1091: dup
    1092: iconst_3
    1093: fconst_0
    1094: fastore
    1095: dup
    1096: iconst_4
    1097: fconst_1
    1098: fastore
    1099: dup
    1100: iconst_5
    1101: fconst_0
    1102: fastore
    1103: dup
    1104: bipush        6
    1106: fconst_0
    1107: fastore
    1108: dup
    1109: bipush        7
    1111: fconst_0
    1112: fastore
    1113: dup
    1114: bipush        8
    1116: fconst_1
    1117: fastore
    1118: invokevirtual #793                // Method scala/Predef$.wrapFloatArray:([F)Lscala/collection/mutable/WrappedArray;
    1121: getstatic     #798                // Field scala/reflect/ClassTag$.MODULE$:Lscala/reflect/ClassTag$;
    1124: invokevirtual #802                // Method scala/reflect/ClassTag$.Float:()Lscala/reflect/ClassTag;
    1127: invokevirtual #805                // Method scala/Array$.apply:(Lscala/collection/Seq;Lscala/reflect/ClassTag;)Ljava/lang/Object;
    1130: checkcast     #807                // class "[F"
    1133: astore        42
    1135: new           #809                // class breeze/linalg/DenseMatrix$mcF$sp
    1138: dup
    1139: iconst_3
    1140: iconst_3
    1141: aload         42
    1143: invokespecial #812                // Method breeze/linalg/DenseMatrix$mcF$sp."<init>":(II[F)V
    1146: astore        4
    1148: aload         4
    1150: areturn
    1151: new           #922                // class scala/MatchError
    1154: dup
    1155: aload_2
    1156: invokespecial #925                // Method scala/MatchError."<init>":(Ljava/lang/Object;)V
    1159: athrow

  public edu.psu.sagnik.research.inkscapesvgprocessing.transformparser.impl.TransformParser();
    Code:
       0: aload_0
       1: invokespecial #945                // Method java/lang/Object."<init>":()V
       4: aload_0
       5: invokestatic  #948                // Method scala/util/parsing/combinator/Parsers$class.$init$:(Lscala/util/parsing/combinator/Parsers;)V
       8: aload_0
       9: invokestatic  #951                // Method scala/util/parsing/combinator/RegexParsers$class.$init$:(Lscala/util/parsing/combinator/RegexParsers;)V
      12: return
}
