Compiled from "CapabilitiesPacketHandler.java"
public class de.ovgu.dke.glue.xmpp.transport.capabilities.CapabilitiesPacketHandler implements de.ovgu.dke.glue.api.transport.PacketHandler,de.ovgu.dke.glue.api.reporting.Reporter {
  private final de.ovgu.dke.glue.api.reporting.ReportListenerSupport reporting;

  public de.ovgu.dke.glue.xmpp.transport.capabilities.CapabilitiesPacketHandler();
    Code:
       0: aload_0
       1: invokespecial #1                  // Method java/lang/Object."<init>":()V
       4: aload_0
       5: new           #2                  // class de/ovgu/dke/glue/api/reporting/ReportListenerSupport
       8: dup
       9: aload_0
      10: invokespecial #3                  // Method de/ovgu/dke/glue/api/reporting/ReportListenerSupport."<init>":(Lde/ovgu/dke/glue/api/reporting/Reporter;)V
      13: putfield      #4                  // Field reporting:Lde/ovgu/dke/glue/api/reporting/ReportListenerSupport;
      16: return

  public void handle(de.ovgu.dke.glue.api.transport.PacketThread, de.ovgu.dke.glue.api.transport.Packet);
    Code:
       0: aload_2
       1: invokeinterface #5,  1            // InterfaceMethod de/ovgu/dke/glue/api/transport/Packet.getPayload:()Ljava/lang/Object;
       6: astore_3
       7: aload_3
       8: ifnonnull     25
      11: aload_0
      12: getfield      #4                  // Field reporting:Lde/ovgu/dke/glue/api/reporting/ReportListenerSupport;
      15: ldc           #6                  // String Got capabilities packet without payload, ignoring.
      17: aconst_null
      18: getstatic     #7                  // Field de/ovgu/dke/glue/api/reporting/Reporter$Level.WARN:Lde/ovgu/dke/glue/api/reporting/Reporter$Level;
      21: invokevirtual #8                  // Method de/ovgu/dke/glue/api/reporting/ReportListenerSupport.fireReport:(Ljava/lang/String;Ljava/lang/Throwable;Lde/ovgu/dke/glue/api/reporting/Reporter$Level;)V
      24: return
      25: aload_3
      26: instanceof    #9                  // class java/util/List
      29: ifne          46
      32: aload_0
      33: getfield      #4                  // Field reporting:Lde/ovgu/dke/glue/api/reporting/ReportListenerSupport;
      36: ldc           #10                 // String Capabilities payload is not of type List<?>, ignoring.
      38: aconst_null
      39: getstatic     #11                 // Field de/ovgu/dke/glue/api/reporting/Reporter$Level.ERROR:Lde/ovgu/dke/glue/api/reporting/Reporter$Level;
      42: invokevirtual #8                  // Method de/ovgu/dke/glue/api/reporting/ReportListenerSupport.fireReport:(Ljava/lang/String;Ljava/lang/Throwable;Lde/ovgu/dke/glue/api/reporting/Reporter$Level;)V
      45: return
      46: aload_3
      47: checkcast     #9                  // class java/util/List
      50: astore        4
      52: aload         4
      54: invokeinterface #12,  1           // InterfaceMethod java/util/List.iterator:()Ljava/util/Iterator;
      59: astore        5
      61: aload         5
      63: invokeinterface #13,  1           // InterfaceMethod java/util/Iterator.hasNext:()Z
      68: ifeq          123
      71: aload         5
      73: invokeinterface #14,  1           // InterfaceMethod java/util/Iterator.next:()Ljava/lang/Object;
      78: checkcast     #15                 // class de/ovgu/dke/glue/xmpp/transport/capabilities/SerializationCapability
      81: astore        6
      83: getstatic     #16                 // Field java/lang/System.out:Ljava/io/PrintStream;
      86: new           #17                 // class java/lang/StringBuilder
      89: dup
      90: invokespecial #18                 // Method java/lang/StringBuilder."<init>":()V
      93: aload         6
      95: invokevirtual #19                 // Method de/ovgu/dke/glue/xmpp/transport/capabilities/SerializationCapability.getFormat:()Ljava/lang/String;
      98: invokevirtual #20                 // Method java/lang/StringBuilder.append:(Ljava/lang/String;)Ljava/lang/StringBuilder;
     101: ldc           #21                 // String  -
     103: invokevirtual #20                 // Method java/lang/StringBuilder.append:(Ljava/lang/String;)Ljava/lang/StringBuilder;
     106: aload         6
     108: invokevirtual #22                 // Method de/ovgu/dke/glue/xmpp/transport/capabilities/SerializationCapability.getSchema:()Ljava/lang/String;
     111: invokevirtual #20                 // Method java/lang/StringBuilder.append:(Ljava/lang/String;)Ljava/lang/StringBuilder;
     114: invokevirtual #23                 // Method java/lang/StringBuilder.toString:()Ljava/lang/String;
     117: invokevirtual #24                 // Method java/io/PrintStream.println:(Ljava/lang/String;)V
     120: goto          61
     123: return

  public void addReportListener(de.ovgu.dke.glue.api.reporting.ReportListener);
    Code:
       0: aload_0
       1: getfield      #4                  // Field reporting:Lde/ovgu/dke/glue/api/reporting/ReportListenerSupport;
       4: aload_1
       5: invokevirtual #25                 // Method de/ovgu/dke/glue/api/reporting/ReportListenerSupport.addReportListener:(Lde/ovgu/dke/glue/api/reporting/ReportListener;)V
       8: return

  public void removeReportListener(de.ovgu.dke.glue.api.reporting.ReportListener);
    Code:
       0: aload_0
       1: getfield      #4                  // Field reporting:Lde/ovgu/dke/glue/api/reporting/ReportListenerSupport;
       4: aload_1
       5: invokevirtual #26                 // Method de/ovgu/dke/glue/api/reporting/ReportListenerSupport.removeReportListener:(Lde/ovgu/dke/glue/api/reporting/ReportListener;)V
       8: return
}
