Compiled from "package.scala"
public final class scala.reflect.package$ {
  public static final scala.reflect.package$ MODULE$;

  private final scala.reflect.ClassManifestFactory$ ClassManifest;

  private final scala.reflect.ManifestFactory$ Manifest;

  public static {};
    Code:
       0: new           #2                  // class scala/reflect/package$
       3: invokespecial #12                 // Method "<init>":()V
       6: return

  public scala.reflect.ClassManifestFactory$ ClassManifest();
    Code:
       0: aload_0
       1: getfield      #19                 // Field ClassManifest:Lscala/reflect/ClassManifestFactory$;
       4: areturn

  public scala.reflect.ManifestFactory$ Manifest();
    Code:
       0: aload_0
       1: getfield      #23                 // Field Manifest:Lscala/reflect/ManifestFactory$;
       4: areturn

  public <T> scala.reflect.ClassTag<T> classTag(scala.reflect.ClassTag<T>);
    Code:
       0: aload_1
       1: areturn

  public <T extends java.lang.reflect.AccessibleObject> T ensureAccessible(T);
    Code:
       0: aload_1
       1: invokevirtual #37                 // Method java/lang/reflect/AccessibleObject.isAccessible:()Z
       4: ifne          16
       7: aload_1
       8: iconst_1
       9: invokevirtual #41                 // Method java/lang/reflect/AccessibleObject.setAccessible:(Z)V
      12: goto          16
      15: pop
      16: aload_1
      17: areturn
    Exception table:
       from    to  target type
           7    15    15   Class java/lang/SecurityException

  private scala.reflect.package$();
    Code:
       0: aload_0
       1: invokespecial #44                 // Method java/lang/Object."<init>":()V
       4: aload_0
       5: putstatic     #46                 // Field MODULE$:Lscala/reflect/package$;
       8: aload_0
       9: getstatic     #50                 // Field scala/reflect/ClassManifestFactory$.MODULE$:Lscala/reflect/ClassManifestFactory$;
      12: putfield      #19                 // Field ClassManifest:Lscala/reflect/ClassManifestFactory$;
      15: aload_0
      16: getstatic     #54                 // Field scala/reflect/ManifestFactory$.MODULE$:Lscala/reflect/ManifestFactory$;
      19: putfield      #23                 // Field Manifest:Lscala/reflect/ManifestFactory$;
      22: return
}
