Compiled from "ConditionKeyMap.java"
class io.minio.policy.ConditionKeyMap extends java.util.Hashtable<java.lang.String, java.util.Set<java.lang.String>> {
  public io.minio.policy.ConditionKeyMap();
    Code:
       0: aload_0
       1: invokespecial #1                  // Method java/util/Hashtable."<init>":()V
       4: return

  public io.minio.policy.ConditionKeyMap(io.minio.policy.ConditionKeyMap);
    Code:
       0: aload_0
       1: aload_1
       2: invokespecial #2                  // Method java/util/Hashtable."<init>":(Ljava/util/Map;)V
       5: return

  public io.minio.policy.ConditionKeyMap(java.lang.String, java.lang.String);
    Code:
       0: aload_0
       1: invokespecial #1                  // Method java/util/Hashtable."<init>":()V
       4: aload_0
       5: aload_1
       6: aload_2
       7: invokevirtual #3                  // Method put:(Ljava/lang/String;Ljava/lang/String;)Ljava/util/Set;
      10: pop
      11: return

  public java.util.Set<java.lang.String> put(java.lang.String, java.util.Set<java.lang.String>);
    Code:
       0: aload_0
       1: aload_1
       2: invokespecial #4                  // Method java/util/Hashtable.get:(Ljava/lang/Object;)Ljava/lang/Object;
       5: checkcast     #5                  // class java/util/Set
       8: astore_3
       9: aload_3
      10: ifnonnull     25
      13: new           #6                  // class java/util/HashSet
      16: dup
      17: aload_2
      18: invokespecial #7                  // Method java/util/HashSet."<init>":(Ljava/util/Collection;)V
      21: astore_3
      22: goto          33
      25: aload_3
      26: aload_2
      27: invokeinterface #8,  2            // InterfaceMethod java/util/Set.addAll:(Ljava/util/Collection;)Z
      32: pop
      33: aload_0
      34: aload_1
      35: aload_3
      36: invokespecial #9                  // Method java/util/Hashtable.put:(Ljava/lang/Object;Ljava/lang/Object;)Ljava/lang/Object;
      39: checkcast     #5                  // class java/util/Set
      42: areturn

  public java.util.Set<java.lang.String> put(java.lang.String, java.lang.String);
    Code:
       0: new           #6                  // class java/util/HashSet
       3: dup
       4: invokespecial #10                 // Method java/util/HashSet."<init>":()V
       7: astore_3
       8: aload_3
       9: aload_2
      10: invokeinterface #11,  2           // InterfaceMethod java/util/Set.add:(Ljava/lang/Object;)Z
      15: pop
      16: aload_0
      17: aload_1
      18: aload_3
      19: invokevirtual #12                 // Method put:(Ljava/lang/String;Ljava/util/Set;)Ljava/util/Set;
      22: areturn

  public java.util.Set<java.lang.String> remove(java.lang.String, java.util.Set<java.lang.String>);
    Code:
       0: aload_0
       1: aload_1
       2: invokespecial #4                  // Method java/util/Hashtable.get:(Ljava/lang/Object;)Ljava/lang/Object;
       5: checkcast     #5                  // class java/util/Set
       8: astore_3
       9: aload_3
      10: ifnonnull     15
      13: aconst_null
      14: areturn
      15: aload_3
      16: aload_2
      17: invokeinterface #13,  2           // InterfaceMethod java/util/Set.removeAll:(Ljava/util/Collection;)Z
      22: pop
      23: aload_3
      24: invokeinterface #14,  1           // InterfaceMethod java/util/Set.isEmpty:()Z
      29: ifeq          41
      32: aload_0
      33: aload_1
      34: invokespecial #15                 // Method java/util/Hashtable.remove:(Ljava/lang/Object;)Ljava/lang/Object;
      37: checkcast     #5                  // class java/util/Set
      40: areturn
      41: aload_0
      42: aload_1
      43: aload_3
      44: invokespecial #9                  // Method java/util/Hashtable.put:(Ljava/lang/Object;Ljava/lang/Object;)Ljava/lang/Object;
      47: checkcast     #5                  // class java/util/Set
      50: areturn

  public java.lang.Object put(java.lang.Object, java.lang.Object);
    Code:
       0: aload_0
       1: aload_1
       2: checkcast     #16                 // class java/lang/String
       5: aload_2
       6: checkcast     #5                  // class java/util/Set
       9: invokevirtual #12                 // Method put:(Ljava/lang/String;Ljava/util/Set;)Ljava/util/Set;
      12: areturn
}
