Compiled from "FSNodeStoreLogOp.java"
public abstract class org.apache.hadoop.yarn.nodelabels.store.op.FSNodeStoreLogOp<M> implements org.apache.hadoop.yarn.nodelabels.store.StoreOp<java.io.OutputStream, java.io.InputStream, M> {
  public org.apache.hadoop.yarn.nodelabels.store.op.FSNodeStoreLogOp();
    Code:
       0: aload_0
       1: invokespecial #1                  // Method java/lang/Object."<init>":()V
       4: return

  public abstract int getOpCode();

  protected java.util.Map<java.lang.String, java.util.Set<org.apache.hadoop.yarn.api.records.NodeAttribute>> getNodeToAttributesMap(org.apache.hadoop.yarn.server.api.protocolrecords.NodesToAttributesMappingRequest);
    Code:
       0: aload_1
       1: invokevirtual #2                  // Method org/apache/hadoop/yarn/server/api/protocolrecords/NodesToAttributesMappingRequest.getNodesToAttributes:()Ljava/util/List;
       4: astore_2
       5: new           #3                  // class java/util/HashMap
       8: dup
       9: invokespecial #4                  // Method java/util/HashMap."<init>":()V
      12: astore_3
      13: aload_2
      14: aload_3
      15: invokedynamic #5,  0              // InvokeDynamic #0:accept:(Ljava/util/Map;)Ljava/util/function/Consumer;
      20: invokeinterface #6,  2            // InterfaceMethod java/util/List.forEach:(Ljava/util/function/Consumer;)V
      25: aload_3
      26: areturn

  private static void lambda$getNodeToAttributesMap$0(java.util.Map, org.apache.hadoop.yarn.server.api.protocolrecords.NodeToAttributes);
    Code:
       0: aload_0
       1: aload_1
       2: invokevirtual #7                  // Method org/apache/hadoop/yarn/server/api/protocolrecords/NodeToAttributes.getNode:()Ljava/lang/String;
       5: new           #8                  // class java/util/HashSet
       8: dup
       9: aload_1
      10: invokevirtual #9                  // Method org/apache/hadoop/yarn/server/api/protocolrecords/NodeToAttributes.getNodeAttributes:()Ljava/util/List;
      13: invokespecial #10                 // Method java/util/HashSet."<init>":(Ljava/util/Collection;)V
      16: invokeinterface #11,  3           // InterfaceMethod java/util/Map.put:(Ljava/lang/Object;Ljava/lang/Object;)Ljava/lang/Object;
      21: checkcast     #12                 // class java/util/Set
      24: pop
      25: return
}
