Compiled from "JCToolsBlockingQueueFactory.java"
public class org.apache.logging.log4j.core.async.JCToolsBlockingQueueFactory<E> implements org.apache.logging.log4j.core.async.BlockingQueueFactory<E> {
  private final org.apache.logging.log4j.core.async.JCToolsBlockingQueueFactory$WaitStrategy waitStrategy;

  private org.apache.logging.log4j.core.async.JCToolsBlockingQueueFactory(org.apache.logging.log4j.core.async.JCToolsBlockingQueueFactory$WaitStrategy);
    Code:
       0: aload_0
       1: invokespecial #1                  // Method java/lang/Object."<init>":()V
       4: aload_0
       5: aload_1
       6: putfield      #2                  // Field waitStrategy:Lorg/apache/logging/log4j/core/async/JCToolsBlockingQueueFactory$WaitStrategy;
       9: return

  public java.util.concurrent.BlockingQueue<E> create(int);
    Code:
       0: new           #3                  // class org/apache/logging/log4j/core/async/JCToolsBlockingQueueFactory$MpscBlockingQueue
       3: dup
       4: iload_1
       5: aload_0
       6: getfield      #2                  // Field waitStrategy:Lorg/apache/logging/log4j/core/async/JCToolsBlockingQueueFactory$WaitStrategy;
       9: invokespecial #4                  // Method org/apache/logging/log4j/core/async/JCToolsBlockingQueueFactory$MpscBlockingQueue."<init>":(ILorg/apache/logging/log4j/core/async/JCToolsBlockingQueueFactory$WaitStrategy;)V
      12: areturn

  public static <E> org.apache.logging.log4j.core.async.JCToolsBlockingQueueFactory<E> createFactory(org.apache.logging.log4j.core.async.JCToolsBlockingQueueFactory$WaitStrategy);
    Code:
       0: new           #5                  // class org/apache/logging/log4j/core/async/JCToolsBlockingQueueFactory
       3: dup
       4: aload_0
       5: invokespecial #6                  // Method "<init>":(Lorg/apache/logging/log4j/core/async/JCToolsBlockingQueueFactory$WaitStrategy;)V
       8: areturn
}
