Compiled from "BasicKeystoreKeyStrategyTool.java"
public class net.shibboleth.utilities.java.support.security.BasicKeystoreKeyStrategyTool {
  private org.slf4j.Logger log;

  private final net.shibboleth.utilities.java.support.security.BasicKeystoreKeyStrategyTool$CommandLineArgs args;

  public net.shibboleth.utilities.java.support.security.BasicKeystoreKeyStrategyTool();
    Code:
       0: aload_0
       1: invokespecial #1                  // Method java/lang/Object."<init>":()V
       4: aload_0
       5: ldc_w         #2                  // class net/shibboleth/utilities/java/support/security/BasicKeystoreKeyStrategyTool
       8: invokestatic  #3                  // Method org/slf4j/LoggerFactory.getLogger:(Ljava/lang/Class;)Lorg/slf4j/Logger;
      11: putfield      #4                  // Field log:Lorg/slf4j/Logger;
      14: aload_0
      15: new           #5                  // class net/shibboleth/utilities/java/support/security/BasicKeystoreKeyStrategyTool$CommandLineArgs
      18: dup
      19: aconst_null
      20: invokespecial #6                  // Method net/shibboleth/utilities/java/support/security/BasicKeystoreKeyStrategyTool$CommandLineArgs."<init>":(Lnet/shibboleth/utilities/java/support/security/BasicKeystoreKeyStrategyTool$1;)V
      23: putfield      #7                  // Field args:Lnet/shibboleth/utilities/java/support/security/BasicKeystoreKeyStrategyTool$CommandLineArgs;
      26: return

  public void setKeyType(java.lang.String);
    Code:
       0: aload_0
       1: getfield      #7                  // Field args:Lnet/shibboleth/utilities/java/support/security/BasicKeystoreKeyStrategyTool$CommandLineArgs;
       4: aload_1
       5: invokestatic  #8                  // Method net/shibboleth/utilities/java/support/primitive/StringSupport.trimOrNull:(Ljava/lang/String;)Ljava/lang/String;
       8: ldc           #9                  // String Key type cannot be null or empty
      10: invokestatic  #10                 // Method net/shibboleth/utilities/java/support/logic/Constraint.isNotNull:(Ljava/lang/Object;Ljava/lang/String;)Ljava/lang/Object;
      13: checkcast     #11                 // class java/lang/String
      16: invokestatic  #12                 // Method net/shibboleth/utilities/java/support/security/BasicKeystoreKeyStrategyTool$CommandLineArgs.access$102:(Lnet/shibboleth/utilities/java/support/security/BasicKeystoreKeyStrategyTool$CommandLineArgs;Ljava/lang/String;)Ljava/lang/String;
      19: pop
      20: return

  public void setKeySize(int);
    Code:
       0: lconst_0
       1: iload_1
       2: i2l
       3: ldc           #13                 // String Key size must be greater than 0
       5: invokestatic  #14                 // Method net/shibboleth/utilities/java/support/logic/Constraint.isGreaterThan:(JJLjava/lang/String;)J
       8: pop2
       9: aload_0
      10: getfield      #7                  // Field args:Lnet/shibboleth/utilities/java/support/security/BasicKeystoreKeyStrategyTool$CommandLineArgs;
      13: iload_1
      14: invokestatic  #15                 // Method net/shibboleth/utilities/java/support/security/BasicKeystoreKeyStrategyTool$CommandLineArgs.access$202:(Lnet/shibboleth/utilities/java/support/security/BasicKeystoreKeyStrategyTool$CommandLineArgs;I)I
      17: pop
      18: return

  public void setKeyAlias(java.lang.String);
    Code:
       0: aload_0
       1: getfield      #7                  // Field args:Lnet/shibboleth/utilities/java/support/security/BasicKeystoreKeyStrategyTool$CommandLineArgs;
       4: aload_1
       5: invokestatic  #8                  // Method net/shibboleth/utilities/java/support/primitive/StringSupport.trimOrNull:(Ljava/lang/String;)Ljava/lang/String;
       8: ldc           #16                 // String Key alias base cannot be null or empty
      10: invokestatic  #10                 // Method net/shibboleth/utilities/java/support/logic/Constraint.isNotNull:(Ljava/lang/Object;Ljava/lang/String;)Ljava/lang/Object;
      13: checkcast     #11                 // class java/lang/String
      16: invokestatic  #17                 // Method net/shibboleth/utilities/java/support/security/BasicKeystoreKeyStrategyTool$CommandLineArgs.access$302:(Lnet/shibboleth/utilities/java/support/security/BasicKeystoreKeyStrategyTool$CommandLineArgs;Ljava/lang/String;)Ljava/lang/String;
      19: pop
      20: return

  public void setKeyCount(int);
    Code:
       0: lconst_0
       1: iload_1
       2: i2l
       3: ldc           #18                 // String Key count must be greater than 0
       5: invokestatic  #14                 // Method net/shibboleth/utilities/java/support/logic/Constraint.isGreaterThan:(JJLjava/lang/String;)J
       8: pop2
       9: aload_0
      10: getfield      #7                  // Field args:Lnet/shibboleth/utilities/java/support/security/BasicKeystoreKeyStrategyTool$CommandLineArgs;
      13: iload_1
      14: invokestatic  #19                 // Method net/shibboleth/utilities/java/support/security/BasicKeystoreKeyStrategyTool$CommandLineArgs.access$402:(Lnet/shibboleth/utilities/java/support/security/BasicKeystoreKeyStrategyTool$CommandLineArgs;I)I
      17: pop
      18: return

  public void setKeystoreType(java.lang.String);
    Code:
       0: aload_0
       1: getfield      #7                  // Field args:Lnet/shibboleth/utilities/java/support/security/BasicKeystoreKeyStrategyTool$CommandLineArgs;
       4: aload_1
       5: invokestatic  #8                  // Method net/shibboleth/utilities/java/support/primitive/StringSupport.trimOrNull:(Ljava/lang/String;)Ljava/lang/String;
       8: ldc           #20                 // String Keystore type cannot be null or empty
      10: invokestatic  #10                 // Method net/shibboleth/utilities/java/support/logic/Constraint.isNotNull:(Ljava/lang/Object;Ljava/lang/String;)Ljava/lang/Object;
      13: checkcast     #11                 // class java/lang/String
      16: invokestatic  #21                 // Method net/shibboleth/utilities/java/support/security/BasicKeystoreKeyStrategyTool$CommandLineArgs.access$502:(Lnet/shibboleth/utilities/java/support/security/BasicKeystoreKeyStrategyTool$CommandLineArgs;Ljava/lang/String;)Ljava/lang/String;
      19: pop
      20: return

  public void setKeystoreFile(java.io.File);
    Code:
       0: aload_0
       1: getfield      #7                  // Field args:Lnet/shibboleth/utilities/java/support/security/BasicKeystoreKeyStrategyTool$CommandLineArgs;
       4: aload_1
       5: ldc           #22                 // String Keystore file cannot be null
       7: invokestatic  #10                 // Method net/shibboleth/utilities/java/support/logic/Constraint.isNotNull:(Ljava/lang/Object;Ljava/lang/String;)Ljava/lang/Object;
      10: checkcast     #23                 // class java/io/File
      13: invokestatic  #24                 // Method net/shibboleth/utilities/java/support/security/BasicKeystoreKeyStrategyTool$CommandLineArgs.access$602:(Lnet/shibboleth/utilities/java/support/security/BasicKeystoreKeyStrategyTool$CommandLineArgs;Ljava/io/File;)Ljava/io/File;
      16: pop
      17: return

  public void setKeystorePassword(java.lang.String);
    Code:
       0: aload_0
       1: getfield      #7                  // Field args:Lnet/shibboleth/utilities/java/support/security/BasicKeystoreKeyStrategyTool$CommandLineArgs;
       4: aload_1
       5: invokestatic  #25                 // Method net/shibboleth/utilities/java/support/security/BasicKeystoreKeyStrategyTool$CommandLineArgs.access$702:(Lnet/shibboleth/utilities/java/support/security/BasicKeystoreKeyStrategyTool$CommandLineArgs;Ljava/lang/String;)Ljava/lang/String;
       8: pop
       9: return

  public void setVersionFile(java.io.File);
    Code:
       0: aload_0
       1: getfield      #7                  // Field args:Lnet/shibboleth/utilities/java/support/security/BasicKeystoreKeyStrategyTool$CommandLineArgs;
       4: aload_1
       5: ldc           #26                 // String Key versioning file cannot be null
       7: invokestatic  #10                 // Method net/shibboleth/utilities/java/support/logic/Constraint.isNotNull:(Ljava/lang/Object;Ljava/lang/String;)Ljava/lang/Object;
      10: checkcast     #23                 // class java/io/File
      13: invokestatic  #27                 // Method net/shibboleth/utilities/java/support/security/BasicKeystoreKeyStrategyTool$CommandLineArgs.access$802:(Lnet/shibboleth/utilities/java/support/security/BasicKeystoreKeyStrategyTool$CommandLineArgs;Ljava/io/File;)Ljava/io/File;
      16: pop
      17: return

  public void changeKey() throws java.lang.Exception;
    Code:
       0: aload_0
       1: getfield      #7                  // Field args:Lnet/shibboleth/utilities/java/support/security/BasicKeystoreKeyStrategyTool$CommandLineArgs;
       4: invokestatic  #28                 // Method net/shibboleth/utilities/java/support/security/BasicKeystoreKeyStrategyTool$CommandLineArgs.access$500:(Lnet/shibboleth/utilities/java/support/security/BasicKeystoreKeyStrategyTool$CommandLineArgs;)Ljava/lang/String;
       7: invokestatic  #29                 // Method java/security/KeyStore.getInstance:(Ljava/lang/String;)Ljava/security/KeyStore;
      10: astore_1
      11: aload_0
      12: getfield      #7                  // Field args:Lnet/shibboleth/utilities/java/support/security/BasicKeystoreKeyStrategyTool$CommandLineArgs;
      15: invokestatic  #30                 // Method net/shibboleth/utilities/java/support/security/BasicKeystoreKeyStrategyTool$CommandLineArgs.access$600:(Lnet/shibboleth/utilities/java/support/security/BasicKeystoreKeyStrategyTool$CommandLineArgs;)Ljava/io/File;
      18: invokevirtual #31                 // Method java/io/File.exists:()Z
      21: ifeq          41
      24: new           #32                 // class java/io/FileInputStream
      27: dup
      28: aload_0
      29: getfield      #7                  // Field args:Lnet/shibboleth/utilities/java/support/security/BasicKeystoreKeyStrategyTool$CommandLineArgs;
      32: invokestatic  #30                 // Method net/shibboleth/utilities/java/support/security/BasicKeystoreKeyStrategyTool$CommandLineArgs.access$600:(Lnet/shibboleth/utilities/java/support/security/BasicKeystoreKeyStrategyTool$CommandLineArgs;)Ljava/io/File;
      35: invokespecial #33                 // Method java/io/FileInputStream."<init>":(Ljava/io/File;)V
      38: goto          42
      41: aconst_null
      42: astore_2
      43: aconst_null
      44: astore_3
      45: aload_1
      46: aload_2
      47: aload_0
      48: getfield      #7                  // Field args:Lnet/shibboleth/utilities/java/support/security/BasicKeystoreKeyStrategyTool$CommandLineArgs;
      51: invokestatic  #34                 // Method net/shibboleth/utilities/java/support/security/BasicKeystoreKeyStrategyTool$CommandLineArgs.access$700:(Lnet/shibboleth/utilities/java/support/security/BasicKeystoreKeyStrategyTool$CommandLineArgs;)Ljava/lang/String;
      54: invokevirtual #35                 // Method java/lang/String.toCharArray:()[C
      57: invokevirtual #36                 // Method java/security/KeyStore.load:(Ljava/io/InputStream;[C)V
      60: aload_2
      61: ifnull        136
      64: aload_3
      65: ifnull        86
      68: aload_2
      69: invokevirtual #37                 // Method java/io/FileInputStream.close:()V
      72: goto          136
      75: astore        4
      77: aload_3
      78: aload         4
      80: invokevirtual #39                 // Method java/lang/Throwable.addSuppressed:(Ljava/lang/Throwable;)V
      83: goto          136
      86: aload_2
      87: invokevirtual #37                 // Method java/io/FileInputStream.close:()V
      90: goto          136
      93: astore        4
      95: aload         4
      97: astore_3
      98: aload         4
     100: athrow
     101: astore        5
     103: aload_2
     104: ifnull        133
     107: aload_3
     108: ifnull        129
     111: aload_2
     112: invokevirtual #37                 // Method java/io/FileInputStream.close:()V
     115: goto          133
     118: astore        6
     120: aload_3
     121: aload         6
     123: invokevirtual #39                 // Method java/lang/Throwable.addSuppressed:(Ljava/lang/Throwable;)V
     126: goto          133
     129: aload_2
     130: invokevirtual #37                 // Method java/io/FileInputStream.close:()V
     133: aload         5
     135: athrow
     136: new           #40                 // class java/util/Properties
     139: dup
     140: invokespecial #41                 // Method java/util/Properties."<init>":()V
     143: astore_2
     144: aload_0
     145: getfield      #7                  // Field args:Lnet/shibboleth/utilities/java/support/security/BasicKeystoreKeyStrategyTool$CommandLineArgs;
     148: invokestatic  #42                 // Method net/shibboleth/utilities/java/support/security/BasicKeystoreKeyStrategyTool$CommandLineArgs.access$800:(Lnet/shibboleth/utilities/java/support/security/BasicKeystoreKeyStrategyTool$CommandLineArgs;)Ljava/io/File;
     151: invokevirtual #31                 // Method java/io/File.exists:()Z
     154: ifeq          261
     157: new           #32                 // class java/io/FileInputStream
     160: dup
     161: aload_0
     162: getfield      #7                  // Field args:Lnet/shibboleth/utilities/java/support/security/BasicKeystoreKeyStrategyTool$CommandLineArgs;
     165: invokestatic  #42                 // Method net/shibboleth/utilities/java/support/security/BasicKeystoreKeyStrategyTool$CommandLineArgs.access$800:(Lnet/shibboleth/utilities/java/support/security/BasicKeystoreKeyStrategyTool$CommandLineArgs;)Ljava/io/File;
     168: invokespecial #33                 // Method java/io/FileInputStream."<init>":(Ljava/io/File;)V
     171: astore_3
     172: aconst_null
     173: astore        4
     175: aload_2
     176: aload_3
     177: invokevirtual #43                 // Method java/util/Properties.load:(Ljava/io/InputStream;)V
     180: aload_3
     181: ifnull        261
     184: aload         4
     186: ifnull        208
     189: aload_3
     190: invokevirtual #37                 // Method java/io/FileInputStream.close:()V
     193: goto          261
     196: astore        5
     198: aload         4
     200: aload         5
     202: invokevirtual #39                 // Method java/lang/Throwable.addSuppressed:(Ljava/lang/Throwable;)V
     205: goto          261
     208: aload_3
     209: invokevirtual #37                 // Method java/io/FileInputStream.close:()V
     212: goto          261
     215: astore        5
     217: aload         5
     219: astore        4
     221: aload         5
     223: athrow
     224: astore        7
     226: aload_3
     227: ifnull        258
     230: aload         4
     232: ifnull        254
     235: aload_3
     236: invokevirtual #37                 // Method java/io/FileInputStream.close:()V
     239: goto          258
     242: astore        8
     244: aload         4
     246: aload         8
     248: invokevirtual #39                 // Method java/lang/Throwable.addSuppressed:(Ljava/lang/Throwable;)V
     251: goto          258
     254: aload_3
     255: invokevirtual #37                 // Method java/io/FileInputStream.close:()V
     258: aload         7
     260: athrow
     261: aload_2
     262: ldc           #44                 // String CurrentVersion
     264: ldc           #45                 // String 0
     266: invokevirtual #46                 // Method java/util/Properties.getProperty:(Ljava/lang/String;Ljava/lang/String;)Ljava/lang/String;
     269: invokestatic  #47                 // Method java/lang/Integer.parseInt:(Ljava/lang/String;)I
     272: istore_3
     273: iload_3
     274: ifne          291
     277: aload_0
     278: getfield      #4                  // Field log:Lorg/slf4j/Logger;
     281: ldc           #48                 // String No existing versioning property, initializing...
     283: invokeinterface #49,  2           // InterfaceMethod org/slf4j/Logger.info:(Ljava/lang/String;)V
     288: goto          312
     291: aload_0
     292: getfield      #4                  // Field log:Lorg/slf4j/Logger;
     295: ldc           #50                 // String Incrementing key version from {} to {}
     297: iload_3
     298: invokestatic  #51                 // Method java/lang/Integer.valueOf:(I)Ljava/lang/Integer;
     301: iload_3
     302: iconst_1
     303: iadd
     304: invokestatic  #51                 // Method java/lang/Integer.valueOf:(I)Ljava/lang/Integer;
     307: invokeinterface #52,  4           // InterfaceMethod org/slf4j/Logger.info:(Ljava/lang/String;Ljava/lang/Object;Ljava/lang/Object;)V
     312: iinc          3, 1
     315: new           #53                 // class java/lang/StringBuilder
     318: dup
     319: invokespecial #54                 // Method java/lang/StringBuilder."<init>":()V
     322: aload_0
     323: getfield      #7                  // Field args:Lnet/shibboleth/utilities/java/support/security/BasicKeystoreKeyStrategyTool$CommandLineArgs;
     326: invokestatic  #55                 // Method net/shibboleth/utilities/java/support/security/BasicKeystoreKeyStrategyTool$CommandLineArgs.access$300:(Lnet/shibboleth/utilities/java/support/security/BasicKeystoreKeyStrategyTool$CommandLineArgs;)Ljava/lang/String;
     329: invokevirtual #56                 // Method java/lang/StringBuilder.append:(Ljava/lang/String;)Ljava/lang/StringBuilder;
     332: iload_3
     333: invokestatic  #57                 // Method java/lang/Integer.toString:(I)Ljava/lang/String;
     336: invokevirtual #56                 // Method java/lang/StringBuilder.append:(Ljava/lang/String;)Ljava/lang/StringBuilder;
     339: invokevirtual #58                 // Method java/lang/StringBuilder.toString:()Ljava/lang/String;
     342: astore        4
     344: aload_1
     345: aload         4
     347: invokevirtual #59                 // Method java/security/KeyStore.containsAlias:(Ljava/lang/String;)Z
     350: ifeq          376
     353: aload_0
     354: getfield      #4                  // Field log:Lorg/slf4j/Logger;
     357: ldc           #60                 // String Keystore already contains an entry named {}, exiting
     359: aload         4
     361: invokeinterface #61,  3           // InterfaceMethod org/slf4j/Logger.error:(Ljava/lang/String;Ljava/lang/Object;)V
     366: new           #62                 // class java/security/KeyException
     369: dup
     370: ldc           #63                 // String Entry for new key already exists
     372: invokespecial #64                 // Method java/security/KeyException."<init>":(Ljava/lang/String;)V
     375: athrow
     376: aload_0
     377: getfield      #7                  // Field args:Lnet/shibboleth/utilities/java/support/security/BasicKeystoreKeyStrategyTool$CommandLineArgs;
     380: invokestatic  #65                 // Method net/shibboleth/utilities/java/support/security/BasicKeystoreKeyStrategyTool$CommandLineArgs.access$100:(Lnet/shibboleth/utilities/java/support/security/BasicKeystoreKeyStrategyTool$CommandLineArgs;)Ljava/lang/String;
     383: invokestatic  #66                 // Method javax/crypto/KeyGenerator.getInstance:(Ljava/lang/String;)Ljavax/crypto/KeyGenerator;
     386: astore        5
     388: aload         5
     390: aload_0
     391: getfield      #7                  // Field args:Lnet/shibboleth/utilities/java/support/security/BasicKeystoreKeyStrategyTool$CommandLineArgs;
     394: invokestatic  #67                 // Method net/shibboleth/utilities/java/support/security/BasicKeystoreKeyStrategyTool$CommandLineArgs.access$200:(Lnet/shibboleth/utilities/java/support/security/BasicKeystoreKeyStrategyTool$CommandLineArgs;)I
     397: invokevirtual #68                 // Method javax/crypto/KeyGenerator.init:(I)V
     400: aload         5
     402: invokevirtual #69                 // Method javax/crypto/KeyGenerator.generateKey:()Ljavax/crypto/SecretKey;
     405: astore        6
     407: aload_1
     408: aload         4
     410: aload         6
     412: aload_0
     413: getfield      #7                  // Field args:Lnet/shibboleth/utilities/java/support/security/BasicKeystoreKeyStrategyTool$CommandLineArgs;
     416: invokestatic  #34                 // Method net/shibboleth/utilities/java/support/security/BasicKeystoreKeyStrategyTool$CommandLineArgs.access$700:(Lnet/shibboleth/utilities/java/support/security/BasicKeystoreKeyStrategyTool$CommandLineArgs;)Ljava/lang/String;
     419: invokevirtual #35                 // Method java/lang/String.toCharArray:()[C
     422: aconst_null
     423: invokevirtual #70                 // Method java/security/KeyStore.setKeyEntry:(Ljava/lang/String;Ljava/security/Key;[C[Ljava/security/cert/Certificate;)V
     426: iload_3
     427: aload_0
     428: getfield      #7                  // Field args:Lnet/shibboleth/utilities/java/support/security/BasicKeystoreKeyStrategyTool$CommandLineArgs;
     431: invokestatic  #71                 // Method net/shibboleth/utilities/java/support/security/BasicKeystoreKeyStrategyTool$CommandLineArgs.access$400:(Lnet/shibboleth/utilities/java/support/security/BasicKeystoreKeyStrategyTool$CommandLineArgs;)I
     434: isub
     435: istore        7
     437: iload         7
     439: ifle          506
     442: new           #53                 // class java/lang/StringBuilder
     445: dup
     446: invokespecial #54                 // Method java/lang/StringBuilder."<init>":()V
     449: aload_0
     450: getfield      #7                  // Field args:Lnet/shibboleth/utilities/java/support/security/BasicKeystoreKeyStrategyTool$CommandLineArgs;
     453: invokestatic  #55                 // Method net/shibboleth/utilities/java/support/security/BasicKeystoreKeyStrategyTool$CommandLineArgs.access$300:(Lnet/shibboleth/utilities/java/support/security/BasicKeystoreKeyStrategyTool$CommandLineArgs;)Ljava/lang/String;
     456: invokevirtual #56                 // Method java/lang/StringBuilder.append:(Ljava/lang/String;)Ljava/lang/StringBuilder;
     459: iload         7
     461: invokestatic  #57                 // Method java/lang/Integer.toString:(I)Ljava/lang/String;
     464: invokevirtual #56                 // Method java/lang/StringBuilder.append:(Ljava/lang/String;)Ljava/lang/StringBuilder;
     467: invokevirtual #58                 // Method java/lang/StringBuilder.toString:()Ljava/lang/String;
     470: astore        8
     472: aload_1
     473: aload         8
     475: invokevirtual #59                 // Method java/security/KeyStore.containsAlias:(Ljava/lang/String;)Z
     478: ifeq          506
     481: aload_0
     482: getfield      #4                  // Field log:Lorg/slf4j/Logger;
     485: ldc           #72                 // String Deleting old key: {}
     487: aload         8
     489: invokeinterface #73,  3           // InterfaceMethod org/slf4j/Logger.info:(Ljava/lang/String;Ljava/lang/Object;)V
     494: aload_1
     495: aload         8
     497: invokevirtual #74                 // Method java/security/KeyStore.deleteEntry:(Ljava/lang/String;)V
     500: iinc          7, -1
     503: goto          437
     506: new           #75                 // class java/io/FileOutputStream
     509: dup
     510: aload_0
     511: getfield      #7                  // Field args:Lnet/shibboleth/utilities/java/support/security/BasicKeystoreKeyStrategyTool$CommandLineArgs;
     514: invokestatic  #30                 // Method net/shibboleth/utilities/java/support/security/BasicKeystoreKeyStrategyTool$CommandLineArgs.access$600:(Lnet/shibboleth/utilities/java/support/security/BasicKeystoreKeyStrategyTool$CommandLineArgs;)Ljava/io/File;
     517: invokespecial #76                 // Method java/io/FileOutputStream."<init>":(Ljava/io/File;)V
     520: astore        8
     522: aconst_null
     523: astore        9
     525: aload_1
     526: aload         8
     528: aload_0
     529: getfield      #7                  // Field args:Lnet/shibboleth/utilities/java/support/security/BasicKeystoreKeyStrategyTool$CommandLineArgs;
     532: invokestatic  #34                 // Method net/shibboleth/utilities/java/support/security/BasicKeystoreKeyStrategyTool$CommandLineArgs.access$700:(Lnet/shibboleth/utilities/java/support/security/BasicKeystoreKeyStrategyTool$CommandLineArgs;)Ljava/lang/String;
     535: invokevirtual #35                 // Method java/lang/String.toCharArray:()[C
     538: invokevirtual #77                 // Method java/security/KeyStore.store:(Ljava/io/OutputStream;[C)V
     541: aload         8
     543: ifnull        628
     546: aload         9
     548: ifnull        571
     551: aload         8
     553: invokevirtual #78                 // Method java/io/FileOutputStream.close:()V
     556: goto          628
     559: astore        10
     561: aload         9
     563: aload         10
     565: invokevirtual #39                 // Method java/lang/Throwable.addSuppressed:(Ljava/lang/Throwable;)V
     568: goto          628
     571: aload         8
     573: invokevirtual #78                 // Method java/io/FileOutputStream.close:()V
     576: goto          628
     579: astore        10
     581: aload         10
     583: astore        9
     585: aload         10
     587: athrow
     588: astore        11
     590: aload         8
     592: ifnull        625
     595: aload         9
     597: ifnull        620
     600: aload         8
     602: invokevirtual #78                 // Method java/io/FileOutputStream.close:()V
     605: goto          625
     608: astore        12
     610: aload         9
     612: aload         12
     614: invokevirtual #39                 // Method java/lang/Throwable.addSuppressed:(Ljava/lang/Throwable;)V
     617: goto          625
     620: aload         8
     622: invokevirtual #78                 // Method java/io/FileOutputStream.close:()V
     625: aload         11
     627: athrow
     628: new           #75                 // class java/io/FileOutputStream
     631: dup
     632: aload_0
     633: getfield      #7                  // Field args:Lnet/shibboleth/utilities/java/support/security/BasicKeystoreKeyStrategyTool$CommandLineArgs;
     636: invokestatic  #42                 // Method net/shibboleth/utilities/java/support/security/BasicKeystoreKeyStrategyTool$CommandLineArgs.access$800:(Lnet/shibboleth/utilities/java/support/security/BasicKeystoreKeyStrategyTool$CommandLineArgs;)Ljava/io/File;
     639: invokespecial #76                 // Method java/io/FileOutputStream."<init>":(Ljava/io/File;)V
     642: astore        8
     644: aconst_null
     645: astore        9
     647: aload_2
     648: ldc           #44                 // String CurrentVersion
     650: iload_3
     651: invokestatic  #57                 // Method java/lang/Integer.toString:(I)Ljava/lang/String;
     654: invokevirtual #79                 // Method java/util/Properties.setProperty:(Ljava/lang/String;Ljava/lang/String;)Ljava/lang/Object;
     657: pop
     658: aload_2
     659: aload         8
     661: aconst_null
     662: invokevirtual #80                 // Method java/util/Properties.store:(Ljava/io/OutputStream;Ljava/lang/String;)V
     665: aload         8
     667: ifnull        752
     670: aload         9
     672: ifnull        695
     675: aload         8
     677: invokevirtual #78                 // Method java/io/FileOutputStream.close:()V
     680: goto          752
     683: astore        10
     685: aload         9
     687: aload         10
     689: invokevirtual #39                 // Method java/lang/Throwable.addSuppressed:(Ljava/lang/Throwable;)V
     692: goto          752
     695: aload         8
     697: invokevirtual #78                 // Method java/io/FileOutputStream.close:()V
     700: goto          752
     703: astore        10
     705: aload         10
     707: astore        9
     709: aload         10
     711: athrow
     712: astore        13
     714: aload         8
     716: ifnull        749
     719: aload         9
     721: ifnull        744
     724: aload         8
     726: invokevirtual #78                 // Method java/io/FileOutputStream.close:()V
     729: goto          749
     732: astore        14
     734: aload         9
     736: aload         14
     738: invokevirtual #39                 // Method java/lang/Throwable.addSuppressed:(Ljava/lang/Throwable;)V
     741: goto          749
     744: aload         8
     746: invokevirtual #78                 // Method java/io/FileOutputStream.close:()V
     749: aload         13
     751: athrow
     752: return
    Exception table:
       from    to  target type
          68    72    75   Class java/lang/Throwable
          45    60    93   Class java/lang/Throwable
          45    60   101   any
         111   115   118   Class java/lang/Throwable
          93   103   101   any
         189   193   196   Class java/lang/Throwable
         175   180   215   Class java/lang/Throwable
         175   180   224   any
         235   239   242   Class java/lang/Throwable
         215   226   224   any
         551   556   559   Class java/lang/Throwable
         525   541   579   Class java/lang/Throwable
         525   541   588   any
         600   605   608   Class java/lang/Throwable
         579   590   588   any
         675   680   683   Class java/lang/Throwable
         647   665   703   Class java/lang/Throwable
         647   665   712   any
         724   729   732   Class java/lang/Throwable
         703   714   712   any

  public static void main(java.lang.String[]) throws java.lang.Exception;
    Code:
       0: new           #2                  // class net/shibboleth/utilities/java/support/security/BasicKeystoreKeyStrategyTool
       3: dup
       4: invokespecial #81                 // Method "<init>":()V
       7: astore_1
       8: new           #82                 // class com/beust/jcommander/JCommander
      11: dup
      12: aload_1
      13: getfield      #7                  // Field args:Lnet/shibboleth/utilities/java/support/security/BasicKeystoreKeyStrategyTool$CommandLineArgs;
      16: aload_0
      17: invokespecial #83                 // Method com/beust/jcommander/JCommander."<init>":(Ljava/lang/Object;[Ljava/lang/String;)V
      20: astore_2
      21: aload_1
      22: getfield      #7                  // Field args:Lnet/shibboleth/utilities/java/support/security/BasicKeystoreKeyStrategyTool$CommandLineArgs;
      25: invokestatic  #84                 // Method net/shibboleth/utilities/java/support/security/BasicKeystoreKeyStrategyTool$CommandLineArgs.access$900:(Lnet/shibboleth/utilities/java/support/security/BasicKeystoreKeyStrategyTool$CommandLineArgs;)Z
      28: ifeq          42
      31: aload_2
      32: ldc           #85                 // String BasicKeystoreKeyStrategyTool
      34: invokevirtual #86                 // Method com/beust/jcommander/JCommander.setProgramName:(Ljava/lang/String;)V
      37: aload_2
      38: invokevirtual #87                 // Method com/beust/jcommander/JCommander.usage:()V
      41: return
      42: aload_1
      43: invokevirtual #88                 // Method changeKey:()V
      46: return
}
