Compiled from "Graph.java"
public class org.hpccsystems.ws.client.platform.Graph extends org.hpccsystems.ws.client.utils.DataSingleton {
  private static java.util.Map<java.lang.Integer, org.hpccsystems.ws.client.platform.Graph> Graphs;

  private org.hpccsystems.ws.client.platform.Workunit workunit;

  private org.hpccsystems.ws.client.gen.axis2.wsworkunits.v1_81.ECLGraph info;

  public static synchronized org.hpccsystems.ws.client.platform.Graph get(org.hpccsystems.ws.client.platform.Workunit, java.lang.String);
    Code:
       0: new           #1                  // class org/hpccsystems/ws/client/platform/Graph
       3: dup
       4: aload_0
       5: aload_1
       6: invokespecial #2                  // Method "<init>":(Lorg/hpccsystems/ws/client/platform/Workunit;Ljava/lang/String;)V
       9: astore_2
      10: getstatic     #3                  // Field Graphs:Ljava/util/Map;
      13: aload_2
      14: invokevirtual #4                  // Method hashCode:()I
      17: invokestatic  #5                  // Method java/lang/Integer.valueOf:(I)Ljava/lang/Integer;
      20: invokeinterface #6,  2            // InterfaceMethod java/util/Map.containsKey:(Ljava/lang/Object;)Z
      25: ifeq          47
      28: getstatic     #3                  // Field Graphs:Ljava/util/Map;
      31: aload_2
      32: invokevirtual #4                  // Method hashCode:()I
      35: invokestatic  #5                  // Method java/lang/Integer.valueOf:(I)Ljava/lang/Integer;
      38: invokeinterface #7,  2            // InterfaceMethod java/util/Map.get:(Ljava/lang/Object;)Ljava/lang/Object;
      43: checkcast     #1                  // class org/hpccsystems/ws/client/platform/Graph
      46: areturn
      47: getstatic     #3                  // Field Graphs:Ljava/util/Map;
      50: aload_2
      51: invokevirtual #4                  // Method hashCode:()I
      54: invokestatic  #5                  // Method java/lang/Integer.valueOf:(I)Ljava/lang/Integer;
      57: aload_2
      58: invokeinterface #8,  3            // InterfaceMethod java/util/Map.put:(Ljava/lang/Object;Ljava/lang/Object;)Ljava/lang/Object;
      63: pop
      64: aload_2
      65: areturn

  private org.hpccsystems.ws.client.platform.Graph(org.hpccsystems.ws.client.platform.Workunit, java.lang.String);
    Code:
       0: aload_0
       1: invokespecial #9                  // Method org/hpccsystems/ws/client/utils/DataSingleton."<init>":()V
       4: aload_0
       5: aload_1
       6: putfield      #10                 // Field workunit:Lorg/hpccsystems/ws/client/platform/Workunit;
       9: aload_0
      10: new           #11                 // class org/hpccsystems/ws/client/gen/axis2/wsworkunits/v1_81/ECLGraph
      13: dup
      14: invokespecial #12                 // Method org/hpccsystems/ws/client/gen/axis2/wsworkunits/v1_81/ECLGraph."<init>":()V
      17: putfield      #13                 // Field info:Lorg/hpccsystems/ws/client/gen/axis2/wsworkunits/v1_81/ECLGraph;
      20: aload_0
      21: getfield      #13                 // Field info:Lorg/hpccsystems/ws/client/gen/axis2/wsworkunits/v1_81/ECLGraph;
      24: aload_2
      25: invokevirtual #14                 // Method org/hpccsystems/ws/client/gen/axis2/wsworkunits/v1_81/ECLGraph.setName:(Ljava/lang/String;)V
      28: return

  public org.hpccsystems.ws.client.platform.Workunit getWorkunit();
    Code:
       0: aload_0
       1: getfield      #10                 // Field workunit:Lorg/hpccsystems/ws/client/platform/Workunit;
       4: areturn

  public java.lang.String getWuid();
    Code:
       0: aload_0
       1: getfield      #10                 // Field workunit:Lorg/hpccsystems/ws/client/platform/Workunit;
       4: invokevirtual #15                 // Method org/hpccsystems/ws/client/platform/Workunit.getWuid:()Ljava/lang/String;
       7: areturn

  public java.lang.String getName();
    Code:
       0: aload_0
       1: getfield      #13                 // Field info:Lorg/hpccsystems/ws/client/gen/axis2/wsworkunits/v1_81/ECLGraph;
       4: invokevirtual #16                 // Method org/hpccsystems/ws/client/gen/axis2/wsworkunits/v1_81/ECLGraph.getName:()Ljava/lang/String;
       7: areturn

  public org.hpccsystems.ws.client.wrappers.WUState getStateID();
    Code:
       0: aload_0
       1: getfield      #13                 // Field info:Lorg/hpccsystems/ws/client/gen/axis2/wsworkunits/v1_81/ECLGraph;
       4: invokevirtual #17                 // Method org/hpccsystems/ws/client/gen/axis2/wsworkunits/v1_81/ECLGraph.getRunning:()Z
       7: ifeq          14
      10: getstatic     #18                 // Field org/hpccsystems/ws/client/wrappers/WUState.RUNNING:Lorg/hpccsystems/ws/client/wrappers/WUState;
      13: areturn
      14: aload_0
      15: getfield      #13                 // Field info:Lorg/hpccsystems/ws/client/gen/axis2/wsworkunits/v1_81/ECLGraph;
      18: invokevirtual #19                 // Method org/hpccsystems/ws/client/gen/axis2/wsworkunits/v1_81/ECLGraph.getComplete:()Z
      21: ifeq          28
      24: getstatic     #20                 // Field org/hpccsystems/ws/client/wrappers/WUState.COMPLETED:Lorg/hpccsystems/ws/client/wrappers/WUState;
      27: areturn
      28: aload_0
      29: getfield      #13                 // Field info:Lorg/hpccsystems/ws/client/gen/axis2/wsworkunits/v1_81/ECLGraph;
      32: invokevirtual #21                 // Method org/hpccsystems/ws/client/gen/axis2/wsworkunits/v1_81/ECLGraph.getFailed:()Z
      35: ifeq          42
      38: getstatic     #22                 // Field org/hpccsystems/ws/client/wrappers/WUState.FAILED:Lorg/hpccsystems/ws/client/wrappers/WUState;
      41: areturn
      42: getstatic     #23                 // Field org/hpccsystems/ws/client/wrappers/WUState.UNKNOWN:Lorg/hpccsystems/ws/client/wrappers/WUState;
      45: areturn

  public boolean isComplete();
    Code:
       0: aload_0
       1: invokevirtual #24                 // Method getStateID:()Lorg/hpccsystems/ws/client/wrappers/WUState;
       4: invokestatic  #25                 // Method org/hpccsystems/ws/client/HPCCWsWorkUnitsClient.isWorkunitComplete:(Lorg/hpccsystems/ws/client/wrappers/WUState;)Z
       7: ifne          20
      10: aload_0
      11: getfield      #10                 // Field workunit:Lorg/hpccsystems/ws/client/platform/Workunit;
      14: invokevirtual #26                 // Method org/hpccsystems/ws/client/platform/Workunit.isComplete:()Z
      17: ifeq          24
      20: iconst_1
      21: goto          25
      24: iconst_0
      25: ireturn

  protected void fastRefresh();
    Code:
       0: aload_0
       1: invokevirtual #27                 // Method fullRefresh:()V
       4: return

  protected void fullRefresh();
    Code:
       0: aload_0
       1: getfield      #10                 // Field workunit:Lorg/hpccsystems/ws/client/platform/Workunit;
       4: invokevirtual #28                 // Method org/hpccsystems/ws/client/platform/Workunit.getGraphs:()[Lorg/hpccsystems/ws/client/platform/Graph;
       7: pop
       8: return

  boolean update(org.hpccsystems.ws.client.gen.axis2.wsworkunits.v1_81.ECLGraph);
    Code:
       0: iconst_0
       1: istore_2
       2: aload_1
       3: ifnull        51
       6: aload_0
       7: getfield      #13                 // Field info:Lorg/hpccsystems/ws/client/gen/axis2/wsworkunits/v1_81/ECLGraph;
      10: invokevirtual #16                 // Method org/hpccsystems/ws/client/gen/axis2/wsworkunits/v1_81/ECLGraph.getName:()Ljava/lang/String;
      13: aload_1
      14: invokevirtual #16                 // Method org/hpccsystems/ws/client/gen/axis2/wsworkunits/v1_81/ECLGraph.getName:()Ljava/lang/String;
      17: invokevirtual #29                 // Method java/lang/String.equals:(Ljava/lang/Object;)Z
      20: ifeq          51
      23: aload_0
      24: getfield      #13                 // Field info:Lorg/hpccsystems/ws/client/gen/axis2/wsworkunits/v1_81/ECLGraph;
      27: aload_1
      28: invokevirtual #30                 // Method java/lang/Object.equals:(Ljava/lang/Object;)Z
      31: ifne          51
      34: aload_0
      35: aload_1
      36: invokevirtual #31                 // Method UpdateState:(Lorg/hpccsystems/ws/client/gen/axis2/wsworkunits/v1_81/ECLGraph;)Z
      39: ifeq          51
      42: iconst_1
      43: istore_2
      44: aload_0
      45: getstatic     #32                 // Field org/hpccsystems/ws/client/platform/Graph$Notification.GRAPH:Lorg/hpccsystems/ws/client/platform/Graph$Notification;
      48: invokevirtual #33                 // Method notifyObservers:(Ljava/lang/Object;)V
      51: aload_0
      52: invokevirtual #34                 // Method monitor:()V
      55: iload_2
      56: ireturn

  boolean UpdateState(org.hpccsystems.ws.client.gen.axis2.wsworkunits.v1_81.ECLGraph);
    Code:
       0: aload_0
       1: getfield      #13                 // Field info:Lorg/hpccsystems/ws/client/gen/axis2/wsworkunits/v1_81/ECLGraph;
       4: invokevirtual #16                 // Method org/hpccsystems/ws/client/gen/axis2/wsworkunits/v1_81/ECLGraph.getName:()Ljava/lang/String;
       7: aload_1
       8: invokevirtual #16                 // Method org/hpccsystems/ws/client/gen/axis2/wsworkunits/v1_81/ECLGraph.getName:()Ljava/lang/String;
      11: invokevirtual #29                 // Method java/lang/String.equals:(Ljava/lang/Object;)Z
      14: ifeq          39
      17: aload_0
      18: getfield      #13                 // Field info:Lorg/hpccsystems/ws/client/gen/axis2/wsworkunits/v1_81/ECLGraph;
      21: aload_1
      22: invokestatic  #35                 // Method org/hpccsystems/ws/client/utils/EqualsUtil.hasChanged:(Ljava/lang/Object;Ljava/lang/Object;)Z
      25: ifeq          39
      28: aload_0
      29: aload_1
      30: putfield      #13                 // Field info:Lorg/hpccsystems/ws/client/gen/axis2/wsworkunits/v1_81/ECLGraph;
      33: aload_0
      34: invokevirtual #36                 // Method setChanged:()V
      37: iconst_1
      38: ireturn
      39: iconst_0
      40: ireturn

  public boolean equals(java.lang.Object);
    Code:
       0: aload_0
       1: aload_1
       2: if_acmpne     7
       5: iconst_1
       6: ireturn
       7: aload_1
       8: instanceof    #1                  // class org/hpccsystems/ws/client/platform/Graph
      11: ifne          16
      14: iconst_0
      15: ireturn
      16: aload_1
      17: checkcast     #1                  // class org/hpccsystems/ws/client/platform/Graph
      20: astore_2
      21: aload_0
      22: getfield      #10                 // Field workunit:Lorg/hpccsystems/ws/client/platform/Workunit;
      25: aload_2
      26: getfield      #10                 // Field workunit:Lorg/hpccsystems/ws/client/platform/Workunit;
      29: invokestatic  #37                 // Method org/hpccsystems/ws/client/utils/EqualsUtil.areEqual:(Ljava/lang/Object;Ljava/lang/Object;)Z
      32: ifeq          59
      35: aload_0
      36: getfield      #13                 // Field info:Lorg/hpccsystems/ws/client/gen/axis2/wsworkunits/v1_81/ECLGraph;
      39: invokevirtual #16                 // Method org/hpccsystems/ws/client/gen/axis2/wsworkunits/v1_81/ECLGraph.getName:()Ljava/lang/String;
      42: aload_2
      43: getfield      #13                 // Field info:Lorg/hpccsystems/ws/client/gen/axis2/wsworkunits/v1_81/ECLGraph;
      46: invokevirtual #16                 // Method org/hpccsystems/ws/client/gen/axis2/wsworkunits/v1_81/ECLGraph.getName:()Ljava/lang/String;
      49: invokestatic  #37                 // Method org/hpccsystems/ws/client/utils/EqualsUtil.areEqual:(Ljava/lang/Object;Ljava/lang/Object;)Z
      52: ifeq          59
      55: iconst_1
      56: goto          60
      59: iconst_0
      60: ireturn

  public int hashCode();
    Code:
       0: bipush        23
       2: istore_1
       3: iload_1
       4: aload_0
       5: getfield      #10                 // Field workunit:Lorg/hpccsystems/ws/client/platform/Workunit;
       8: invokestatic  #39                 // Method org/hpccsystems/ws/client/utils/HashCodeUtil.hash:(ILjava/lang/Object;)I
      11: istore_1
      12: iload_1
      13: aload_0
      14: getfield      #13                 // Field info:Lorg/hpccsystems/ws/client/gen/axis2/wsworkunits/v1_81/ECLGraph;
      17: invokevirtual #16                 // Method org/hpccsystems/ws/client/gen/axis2/wsworkunits/v1_81/ECLGraph.getName:()Ljava/lang/String;
      20: invokestatic  #39                 // Method org/hpccsystems/ws/client/utils/HashCodeUtil.hash:(ILjava/lang/Object;)I
      23: istore_1
      24: iload_1
      25: ireturn

  static {};
    Code:
       0: new           #40                 // class java/util/HashMap
       3: dup
       4: invokespecial #41                 // Method java/util/HashMap."<init>":()V
       7: putstatic     #3                  // Field Graphs:Ljava/util/Map;
      10: return
}
