Compiled from "PhysicalFile.java"
public final class org.hpccsystems.ws.client.platform.PhysicalFile$Notification extends java.lang.Enum<org.hpccsystems.ws.client.platform.PhysicalFile$Notification> {
  public static final org.hpccsystems.ws.client.platform.PhysicalFile$Notification PHYSICALFILE;

  private static final org.hpccsystems.ws.client.platform.PhysicalFile$Notification[] $VALUES;

  public static org.hpccsystems.ws.client.platform.PhysicalFile$Notification[] values();
    Code:
       0: getstatic     #1                  // Field $VALUES:[Lorg/hpccsystems/ws/client/platform/PhysicalFile$Notification;
       3: invokevirtual #2                  // Method "[Lorg/hpccsystems/ws/client/platform/PhysicalFile$Notification;".clone:()Ljava/lang/Object;
       6: checkcast     #3                  // class "[Lorg/hpccsystems/ws/client/platform/PhysicalFile$Notification;"
       9: areturn

  public static org.hpccsystems.ws.client.platform.PhysicalFile$Notification valueOf(java.lang.String);
    Code:
       0: ldc           #4                  // class org/hpccsystems/ws/client/platform/PhysicalFile$Notification
       2: aload_0
       3: invokestatic  #5                  // Method java/lang/Enum.valueOf:(Ljava/lang/Class;Ljava/lang/String;)Ljava/lang/Enum;
       6: checkcast     #4                  // class org/hpccsystems/ws/client/platform/PhysicalFile$Notification
       9: areturn

  private org.hpccsystems.ws.client.platform.PhysicalFile$Notification();
    Code:
       0: aload_0
       1: aload_1
       2: iload_2
       3: invokespecial #6                  // Method java/lang/Enum."<init>":(Ljava/lang/String;I)V
       6: return

  static {};
    Code:
       0: new           #4                  // class org/hpccsystems/ws/client/platform/PhysicalFile$Notification
       3: dup
       4: ldc           #7                  // String PHYSICALFILE
       6: iconst_0
       7: invokespecial #8                  // Method "<init>":(Ljava/lang/String;I)V
      10: putstatic     #9                  // Field PHYSICALFILE:Lorg/hpccsystems/ws/client/platform/PhysicalFile$Notification;
      13: iconst_1
      14: anewarray     #4                  // class org/hpccsystems/ws/client/platform/PhysicalFile$Notification
      17: dup
      18: iconst_0
      19: getstatic     #9                  // Field PHYSICALFILE:Lorg/hpccsystems/ws/client/platform/PhysicalFile$Notification;
      22: aastore
      23: putstatic     #1                  // Field $VALUES:[Lorg/hpccsystems/ws/client/platform/PhysicalFile$Notification;
      26: return
}
