Compiled from "GenericSuccessResponse.java"
public class org.hawkular.cmdgw.api.GenericSuccessResponse extends org.hawkular.cmdgw.api.AuthMessage {
  private java.lang.String message;

  public org.hawkular.cmdgw.api.GenericSuccessResponse();
    Code:
       0: aload_0
       1: invokespecial #1                  // Method org/hawkular/cmdgw/api/AuthMessage."<init>":()V
       4: return

  public java.lang.String getMessage();
    Code:
       0: aload_0
       1: getfield      #2                  // Field message:Ljava/lang/String;
       4: areturn

  public void setMessage(java.lang.String);
    Code:
       0: aload_0
       1: aload_1
       2: putfield      #2                  // Field message:Ljava/lang/String;
       5: return
}
