Compiled from "UpdateCollectionIntervalsRequest.java"
public class org.hawkular.cmdgw.api.UpdateCollectionIntervalsRequest extends org.hawkular.cmdgw.api.ResourcePathRequest implements org.hawkular.cmdgw.api.ResourcePathDestination {
  private java.util.Map<java.lang.String, java.lang.String> metricTypes;

  private java.util.Map<java.lang.String, java.lang.String> availTypes;

  public org.hawkular.cmdgw.api.UpdateCollectionIntervalsRequest();
    Code:
       0: aload_0
       1: invokespecial #1                  // Method org/hawkular/cmdgw/api/ResourcePathRequest."<init>":()V
       4: return

  public java.util.Map<java.lang.String, java.lang.String> getMetricTypes();
    Code:
       0: aload_0
       1: getfield      #2                  // Field metricTypes:Ljava/util/Map;
       4: areturn

  public void setMetricTypes(java.util.Map<java.lang.String, java.lang.String>);
    Code:
       0: aload_0
       1: aload_1
       2: putfield      #2                  // Field metricTypes:Ljava/util/Map;
       5: return

  public java.util.Map<java.lang.String, java.lang.String> getAvailTypes();
    Code:
       0: aload_0
       1: getfield      #3                  // Field availTypes:Ljava/util/Map;
       4: areturn

  public void setAvailTypes(java.util.Map<java.lang.String, java.lang.String>);
    Code:
       0: aload_0
       1: aload_1
       2: putfield      #3                  // Field availTypes:Ljava/util/Map;
       5: return
}
