Compiled from "AnnotationValue.java"
final class net.bytebuddy.description.annotation.AnnotationValue$ForConstant$PropertyDelegate$ForNonArrayType$1 extends net.bytebuddy.description.annotation.AnnotationValue$ForConstant$PropertyDelegate$ForNonArrayType {
  net.bytebuddy.description.annotation.AnnotationValue$ForConstant$PropertyDelegate$ForNonArrayType$1(java.lang.String, int);
    Code:
       0: aload_0
       1: aload_1
       2: iload_2
       3: aconst_null
       4: invokespecial #24                 // Method net/bytebuddy/description/annotation/AnnotationValue$ForConstant$PropertyDelegate$ForNonArrayType."<init>":(Ljava/lang/String;ILnet/bytebuddy/description/annotation/AnnotationValue$1;)V
       7: return

  public java.lang.String toString(java.lang.Object);
    Code:
       0: getstatic     #32                 // Field net/bytebuddy/description/annotation/AnnotationValue$RenderingDispatcher.CURRENT:Lnet/bytebuddy/description/annotation/AnnotationValue$RenderingDispatcher;
       3: aload_1
       4: checkcast     #34                 // class java/lang/Boolean
       7: invokevirtual #38                 // Method java/lang/Boolean.booleanValue:()Z
      10: invokevirtual #42                 // Method net/bytebuddy/description/annotation/AnnotationValue$RenderingDispatcher.toSourceString:(Z)Ljava/lang/String;
      13: areturn
}
