Compiled from "RoleResourceHandler.java"
public class org.sonatype.nexus.rest.roles.RoleResourceHandler extends org.sonatype.nexus.rest.roles.AbstractRoleResourceHandler {
  private java.lang.String roleId;

  public org.sonatype.nexus.rest.roles.RoleResourceHandler(org.restlet.Context, org.restlet.data.Request, org.restlet.data.Response);
    Code:
       0: aload_0
       1: aload_1
       2: aload_2
       3: aload_3
       4: invokespecial #1                  // Method org/sonatype/nexus/rest/roles/AbstractRoleResourceHandler."<init>":(Lorg/restlet/Context;Lorg/restlet/data/Request;Lorg/restlet/data/Response;)V
       7: aload_0
       8: aload_0
       9: invokevirtual #2                  // Method getRequest:()Lorg/restlet/data/Request;
      12: invokevirtual #3                  // Method org/restlet/data/Request.getAttributes:()Ljava/util/Map;
      15: ldc           #4                  // String roleId
      17: invokeinterface #5,  2            // InterfaceMethod java/util/Map.get:(Ljava/lang/Object;)Ljava/lang/Object;
      22: invokevirtual #6                  // Method java/lang/Object.toString:()Ljava/lang/String;
      25: putfield      #7                  // Field roleId:Ljava/lang/String;
      28: return

  protected java.lang.String getRoleId();
    Code:
       0: aload_0
       1: getfield      #7                  // Field roleId:Ljava/lang/String;
       4: areturn

  public boolean allowGet();
    Code:
       0: iconst_1
       1: ireturn

  public org.restlet.resource.Representation getRepresentationHandler(org.restlet.resource.Variant);
    Code:
       0: new           #8                  // class org/sonatype/nexus/rest/model/RoleResourceResponse
       3: dup
       4: invokespecial #9                  // Method org/sonatype/nexus/rest/model/RoleResourceResponse."<init>":()V
       7: astore_2
       8: aload_2
       9: aload_0
      10: aload_0
      11: invokevirtual #10                 // Method getNexusSecurityConfiguration:()Lorg/sonatype/nexus/configuration/security/NexusSecurityConfiguration;
      14: aload_0
      15: invokevirtual #11                 // Method getRoleId:()Ljava/lang/String;
      18: invokeinterface #12,  2           // InterfaceMethod org/sonatype/nexus/configuration/security/NexusSecurityConfiguration.readRole:(Ljava/lang/String;)Lorg/sonatype/nexus/configuration/security/model/CRole;
      23: invokevirtual #13                 // Method nexusToRestModel:(Lorg/sonatype/nexus/configuration/security/model/CRole;)Lorg/sonatype/nexus/rest/model/RoleResource;
      26: invokevirtual #14                 // Method org/sonatype/nexus/rest/model/RoleResourceResponse.setData:(Lorg/sonatype/nexus/rest/model/RoleResource;)V
      29: aload_0
      30: aload_1
      31: aload_2
      32: invokevirtual #15                 // Method serialize:(Lorg/restlet/resource/Variant;Ljava/lang/Object;)Lorg/restlet/resource/Representation;
      35: areturn
      36: astore_3
      37: aload_0
      38: invokevirtual #17                 // Method getResponse:()Lorg/restlet/data/Response;
      41: getstatic     #18                 // Field org/restlet/data/Status.CLIENT_ERROR_NOT_FOUND:Lorg/restlet/data/Status;
      44: aload_3
      45: invokevirtual #19                 // Method org/sonatype/nexus/configuration/security/NoSuchRoleException.getMessage:()Ljava/lang/String;
      48: invokevirtual #20                 // Method org/restlet/data/Response.setStatus:(Lorg/restlet/data/Status;Ljava/lang/String;)V
      51: aconst_null
      52: areturn
    Exception table:
       from    to  target type
           8    35    36   Class org/sonatype/nexus/configuration/security/NoSuchRoleException

  public boolean allowPut();
    Code:
       0: iconst_1
       1: ireturn

  public void put(org.restlet.resource.Representation);
    Code:
       0: aload_0
       1: new           #21                 // class org/sonatype/nexus/rest/model/RoleResourceRequest
       4: dup
       5: invokespecial #22                 // Method org/sonatype/nexus/rest/model/RoleResourceRequest."<init>":()V
       8: invokevirtual #23                 // Method deserialize:(Ljava/lang/Object;)Ljava/lang/Object;
      11: checkcast     #21                 // class org/sonatype/nexus/rest/model/RoleResourceRequest
      14: astore_2
      15: aload_2
      16: ifnonnull     20
      19: return
      20: aload_2
      21: invokevirtual #24                 // Method org/sonatype/nexus/rest/model/RoleResourceRequest.getData:()Lorg/sonatype/nexus/rest/model/RoleResource;
      24: astore_3
      25: aload_0
      26: aload_0
      27: invokevirtual #10                 // Method getNexusSecurityConfiguration:()Lorg/sonatype/nexus/configuration/security/NexusSecurityConfiguration;
      30: aload_3
      31: invokevirtual #25                 // Method org/sonatype/nexus/rest/model/RoleResource.getId:()Ljava/lang/String;
      34: invokeinterface #12,  2           // InterfaceMethod org/sonatype/nexus/configuration/security/NexusSecurityConfiguration.readRole:(Ljava/lang/String;)Lorg/sonatype/nexus/configuration/security/model/CRole;
      39: aload_3
      40: invokevirtual #26                 // Method restToNexusModel:(Lorg/sonatype/nexus/configuration/security/model/CRole;Lorg/sonatype/nexus/rest/model/RoleResource;)Lorg/sonatype/nexus/configuration/security/model/CRole;
      43: astore        4
      45: aload_0
      46: invokevirtual #10                 // Method getNexusSecurityConfiguration:()Lorg/sonatype/nexus/configuration/security/NexusSecurityConfiguration;
      49: aload         4
      51: invokeinterface #27,  2           // InterfaceMethod org/sonatype/nexus/configuration/security/NexusSecurityConfiguration.updateRole:(Lorg/sonatype/nexus/configuration/security/model/CRole;)V
      56: new           #8                  // class org/sonatype/nexus/rest/model/RoleResourceResponse
      59: dup
      60: invokespecial #9                  // Method org/sonatype/nexus/rest/model/RoleResourceResponse."<init>":()V
      63: astore        5
      65: aload         5
      67: aload_2
      68: invokevirtual #24                 // Method org/sonatype/nexus/rest/model/RoleResourceRequest.getData:()Lorg/sonatype/nexus/rest/model/RoleResource;
      71: invokevirtual #14                 // Method org/sonatype/nexus/rest/model/RoleResourceResponse.setData:(Lorg/sonatype/nexus/rest/model/RoleResource;)V
      74: aload         5
      76: invokevirtual #28                 // Method org/sonatype/nexus/rest/model/RoleResourceResponse.getData:()Lorg/sonatype/nexus/rest/model/RoleResource;
      79: aload_0
      80: aload_3
      81: invokevirtual #25                 // Method org/sonatype/nexus/rest/model/RoleResource.getId:()Ljava/lang/String;
      84: invokevirtual #29                 // Method calculateSubReference:(Ljava/lang/String;)Lorg/restlet/data/Reference;
      87: invokevirtual #30                 // Method org/restlet/data/Reference.toString:()Ljava/lang/String;
      90: invokevirtual #31                 // Method org/sonatype/nexus/rest/model/RoleResource.setResourceURI:(Ljava/lang/String;)V
      93: aload_0
      94: invokevirtual #17                 // Method getResponse:()Lorg/restlet/data/Response;
      97: aload_0
      98: aload_1
      99: aload         5
     101: invokevirtual #15                 // Method serialize:(Lorg/restlet/resource/Variant;Ljava/lang/Object;)Lorg/restlet/resource/Representation;
     104: invokevirtual #32                 // Method org/restlet/data/Response.setEntity:(Lorg/restlet/resource/Representation;)V
     107: goto          168
     110: astore        4
     112: aload_0
     113: invokevirtual #17                 // Method getResponse:()Lorg/restlet/data/Response;
     116: getstatic     #18                 // Field org/restlet/data/Status.CLIENT_ERROR_NOT_FOUND:Lorg/restlet/data/Status;
     119: aload         4
     121: invokevirtual #19                 // Method org/sonatype/nexus/configuration/security/NoSuchRoleException.getMessage:()Ljava/lang/String;
     124: invokevirtual #20                 // Method org/restlet/data/Response.setStatus:(Lorg/restlet/data/Status;Ljava/lang/String;)V
     127: goto          168
     130: astore        4
     132: aload_0
     133: aload         4
     135: aload_1
     136: invokevirtual #34                 // Method handleConfigurationException:(Lorg/sonatype/nexus/configuration/ConfigurationException;Lorg/restlet/resource/Representation;)V
     139: goto          168
     142: astore        4
     144: aload_0
     145: invokevirtual #17                 // Method getResponse:()Lorg/restlet/data/Response;
     148: getstatic     #36                 // Field org/restlet/data/Status.SERVER_ERROR_INTERNAL:Lorg/restlet/data/Status;
     151: invokevirtual #37                 // Method org/restlet/data/Response.setStatus:(Lorg/restlet/data/Status;)V
     154: aload_0
     155: invokevirtual #38                 // Method getLogger:()Ljava/util/logging/Logger;
     158: getstatic     #39                 // Field java/util/logging/Level.SEVERE:Ljava/util/logging/Level;
     161: ldc           #40                 // String Got IO Exception!
     163: aload         4
     165: invokevirtual #41                 // Method java/util/logging/Logger.log:(Ljava/util/logging/Level;Ljava/lang/String;Ljava/lang/Throwable;)V
     168: return
    Exception table:
       from    to  target type
          25   107   110   Class org/sonatype/nexus/configuration/security/NoSuchRoleException
          25   107   130   Class org/sonatype/nexus/configuration/ConfigurationException
          25   107   142   Class java/io/IOException

  public boolean allowDelete();
    Code:
       0: iconst_1
       1: ireturn

  public void delete();
    Code:
       0: aload_0
       1: invokevirtual #10                 // Method getNexusSecurityConfiguration:()Lorg/sonatype/nexus/configuration/security/NexusSecurityConfiguration;
       4: aload_0
       5: invokevirtual #11                 // Method getRoleId:()Ljava/lang/String;
       8: invokeinterface #42,  2           // InterfaceMethod org/sonatype/nexus/configuration/security/NexusSecurityConfiguration.deleteRole:(Ljava/lang/String;)V
      13: aload_0
      14: invokevirtual #17                 // Method getResponse:()Lorg/restlet/data/Response;
      17: getstatic     #43                 // Field org/restlet/data/Status.SUCCESS_NO_CONTENT:Lorg/restlet/data/Status;
      20: invokevirtual #37                 // Method org/restlet/data/Response.setStatus:(Lorg/restlet/data/Status;)V
      23: goto          68
      26: astore_1
      27: aload_0
      28: invokevirtual #17                 // Method getResponse:()Lorg/restlet/data/Response;
      31: getstatic     #18                 // Field org/restlet/data/Status.CLIENT_ERROR_NOT_FOUND:Lorg/restlet/data/Status;
      34: aload_1
      35: invokevirtual #19                 // Method org/sonatype/nexus/configuration/security/NoSuchRoleException.getMessage:()Ljava/lang/String;
      38: invokevirtual #20                 // Method org/restlet/data/Response.setStatus:(Lorg/restlet/data/Status;Ljava/lang/String;)V
      41: goto          68
      44: astore_1
      45: aload_0
      46: invokevirtual #17                 // Method getResponse:()Lorg/restlet/data/Response;
      49: getstatic     #36                 // Field org/restlet/data/Status.SERVER_ERROR_INTERNAL:Lorg/restlet/data/Status;
      52: invokevirtual #37                 // Method org/restlet/data/Response.setStatus:(Lorg/restlet/data/Status;)V
      55: aload_0
      56: invokevirtual #38                 // Method getLogger:()Ljava/util/logging/Logger;
      59: getstatic     #39                 // Field java/util/logging/Level.SEVERE:Ljava/util/logging/Level;
      62: ldc           #40                 // String Got IO Exception!
      64: aload_1
      65: invokevirtual #41                 // Method java/util/logging/Logger.log:(Ljava/util/logging/Level;Ljava/lang/String;Ljava/lang/Throwable;)V
      68: return
    Exception table:
       from    to  target type
           0    23    26   Class org/sonatype/nexus/configuration/security/NoSuchRoleException
           0    23    44   Class java/io/IOException
}
