Compiled from "SimpleSocketServer.java"
public class ch.qos.logback.classic.net.SimpleSocketServer extends java.lang.Thread {
  org.slf4j.Logger logger;

  private final int port;

  private final ch.qos.logback.classic.LoggerContext lc;

  private boolean closed;

  private java.net.ServerSocket serverSocket;

  private java.util.List<ch.qos.logback.classic.net.SocketNode> socketNodeList;

  private java.util.concurrent.CountDownLatch latch;

  public static void main(java.lang.String[]) throws java.lang.Exception;
    Code:
       0: ldc_w         #1                  // class ch/qos/logback/classic/net/SimpleSocketServer
       3: aload_0
       4: invokestatic  #2                  // Method doMain:(Ljava/lang/Class;[Ljava/lang/String;)V
       7: return

  protected static void doMain(java.lang.Class<? extends ch.qos.logback.classic.net.SimpleSocketServer>, java.lang.String[]) throws java.lang.Exception;
    Code:
       0: iconst_m1
       1: istore_2
       2: aload_1
       3: arraylength
       4: iconst_2
       5: if_icmpne     18
       8: aload_1
       9: iconst_0
      10: aaload
      11: invokestatic  #3                  // Method parsePortNumber:(Ljava/lang/String;)I
      14: istore_2
      15: goto          23
      18: ldc           #4                  // String Wrong number of arguments.
      20: invokestatic  #5                  // Method usage:(Ljava/lang/String;)V
      23: aload_1
      24: iconst_1
      25: aaload
      26: astore_3
      27: invokestatic  #6                  // Method org/slf4j/LoggerFactory.getILoggerFactory:()Lorg/slf4j/ILoggerFactory;
      30: checkcast     #7                  // class ch/qos/logback/classic/LoggerContext
      33: astore        4
      35: aload         4
      37: aload_3
      38: invokestatic  #8                  // Method configureLC:(Lch/qos/logback/classic/LoggerContext;Ljava/lang/String;)V
      41: new           #1                  // class ch/qos/logback/classic/net/SimpleSocketServer
      44: dup
      45: aload         4
      47: iload_2
      48: invokespecial #9                  // Method "<init>":(Lch/qos/logback/classic/LoggerContext;I)V
      51: astore        5
      53: aload         5
      55: invokevirtual #10                 // Method start:()V
      58: return

  public ch.qos.logback.classic.net.SimpleSocketServer(ch.qos.logback.classic.LoggerContext, int);
    Code:
       0: aload_0
       1: invokespecial #11                 // Method java/lang/Thread."<init>":()V
       4: aload_0
       5: ldc_w         #1                  // class ch/qos/logback/classic/net/SimpleSocketServer
       8: invokestatic  #12                 // Method org/slf4j/LoggerFactory.getLogger:(Ljava/lang/Class;)Lorg/slf4j/Logger;
      11: putfield      #13                 // Field logger:Lorg/slf4j/Logger;
      14: aload_0
      15: iconst_0
      16: putfield      #14                 // Field closed:Z
      19: aload_0
      20: new           #15                 // class java/util/ArrayList
      23: dup
      24: invokespecial #16                 // Method java/util/ArrayList."<init>":()V
      27: putfield      #17                 // Field socketNodeList:Ljava/util/List;
      30: aload_0
      31: aload_1
      32: putfield      #18                 // Field lc:Lch/qos/logback/classic/LoggerContext;
      35: aload_0
      36: iload_2
      37: putfield      #19                 // Field port:I
      40: return

  public void run();
    Code:
       0: invokestatic  #20                 // Method java/lang/Thread.currentThread:()Ljava/lang/Thread;
       3: invokevirtual #21                 // Method java/lang/Thread.getName:()Ljava/lang/String;
       6: astore_1
       7: aload_0
       8: invokevirtual #22                 // Method getServerThreadName:()Ljava/lang/String;
      11: astore_2
      12: invokestatic  #20                 // Method java/lang/Thread.currentThread:()Ljava/lang/Thread;
      15: aload_2
      16: invokevirtual #23                 // Method java/lang/Thread.setName:(Ljava/lang/String;)V
      19: aload_0
      20: getfield      #13                 // Field logger:Lorg/slf4j/Logger;
      23: new           #24                 // class java/lang/StringBuilder
      26: dup
      27: invokespecial #25                 // Method java/lang/StringBuilder."<init>":()V
      30: ldc           #26                 // String Listening on port
      32: invokevirtual #27                 // Method java/lang/StringBuilder.append:(Ljava/lang/String;)Ljava/lang/StringBuilder;
      35: aload_0
      36: getfield      #19                 // Field port:I
      39: invokevirtual #28                 // Method java/lang/StringBuilder.append:(I)Ljava/lang/StringBuilder;
      42: invokevirtual #29                 // Method java/lang/StringBuilder.toString:()Ljava/lang/String;
      45: invokeinterface #30,  2           // InterfaceMethod org/slf4j/Logger.info:(Ljava/lang/String;)V
      50: aload_0
      51: aload_0
      52: invokevirtual #31                 // Method getServerSocketFactory:()Ljavax/net/ServerSocketFactory;
      55: aload_0
      56: getfield      #19                 // Field port:I
      59: invokevirtual #32                 // Method javax/net/ServerSocketFactory.createServerSocket:(I)Ljava/net/ServerSocket;
      62: putfield      #33                 // Field serverSocket:Ljava/net/ServerSocket;
      65: aload_0
      66: getfield      #14                 // Field closed:Z
      69: ifne          210
      72: aload_0
      73: getfield      #13                 // Field logger:Lorg/slf4j/Logger;
      76: ldc           #34                 // String Waiting to accept a new client.
      78: invokeinterface #30,  2           // InterfaceMethod org/slf4j/Logger.info:(Ljava/lang/String;)V
      83: aload_0
      84: invokevirtual #35                 // Method signalAlmostReadiness:()V
      87: aload_0
      88: getfield      #33                 // Field serverSocket:Ljava/net/ServerSocket;
      91: invokevirtual #36                 // Method java/net/ServerSocket.accept:()Ljava/net/Socket;
      94: astore_3
      95: aload_0
      96: getfield      #13                 // Field logger:Lorg/slf4j/Logger;
      99: new           #24                 // class java/lang/StringBuilder
     102: dup
     103: invokespecial #25                 // Method java/lang/StringBuilder."<init>":()V
     106: ldc           #37                 // String Connected to client at
     108: invokevirtual #27                 // Method java/lang/StringBuilder.append:(Ljava/lang/String;)Ljava/lang/StringBuilder;
     111: aload_3
     112: invokevirtual #38                 // Method java/net/Socket.getInetAddress:()Ljava/net/InetAddress;
     115: invokevirtual #39                 // Method java/lang/StringBuilder.append:(Ljava/lang/Object;)Ljava/lang/StringBuilder;
     118: invokevirtual #29                 // Method java/lang/StringBuilder.toString:()Ljava/lang/String;
     121: invokeinterface #30,  2           // InterfaceMethod org/slf4j/Logger.info:(Ljava/lang/String;)V
     126: aload_0
     127: getfield      #13                 // Field logger:Lorg/slf4j/Logger;
     130: ldc           #40                 // String Starting new socket node.
     132: invokeinterface #30,  2           // InterfaceMethod org/slf4j/Logger.info:(Ljava/lang/String;)V
     137: new           #41                 // class ch/qos/logback/classic/net/SocketNode
     140: dup
     141: aload_0
     142: aload_3
     143: aload_0
     144: getfield      #18                 // Field lc:Lch/qos/logback/classic/LoggerContext;
     147: invokespecial #42                 // Method ch/qos/logback/classic/net/SocketNode."<init>":(Lch/qos/logback/classic/net/SimpleSocketServer;Ljava/net/Socket;Lch/qos/logback/classic/LoggerContext;)V
     150: astore        4
     152: aload_0
     153: getfield      #17                 // Field socketNodeList:Ljava/util/List;
     156: dup
     157: astore        5
     159: monitorenter
     160: aload_0
     161: getfield      #17                 // Field socketNodeList:Ljava/util/List;
     164: aload         4
     166: invokeinterface #43,  2           // InterfaceMethod java/util/List.add:(Ljava/lang/Object;)Z
     171: pop
     172: aload         5
     174: monitorexit
     175: goto          186
     178: astore        6
     180: aload         5
     182: monitorexit
     183: aload         6
     185: athrow
     186: aload_0
     187: aload_3
     188: invokevirtual #44                 // Method getClientThreadName:(Ljava/net/Socket;)Ljava/lang/String;
     191: astore        5
     193: new           #45                 // class java/lang/Thread
     196: dup
     197: aload         4
     199: aload         5
     201: invokespecial #46                 // Method java/lang/Thread."<init>":(Ljava/lang/Runnable;Ljava/lang/String;)V
     204: invokevirtual #47                 // Method java/lang/Thread.start:()V
     207: goto          65
     210: invokestatic  #20                 // Method java/lang/Thread.currentThread:()Ljava/lang/Thread;
     213: aload_1
     214: invokevirtual #23                 // Method java/lang/Thread.setName:(Ljava/lang/String;)V
     217: goto          276
     220: astore_2
     221: aload_0
     222: getfield      #14                 // Field closed:Z
     225: ifeq          242
     228: aload_0
     229: getfield      #13                 // Field logger:Lorg/slf4j/Logger;
     232: ldc           #49                 // String Exception in run method for a closed server. This is normal.
     234: invokeinterface #30,  2           // InterfaceMethod org/slf4j/Logger.info:(Ljava/lang/String;)V
     239: goto          254
     242: aload_0
     243: getfield      #13                 // Field logger:Lorg/slf4j/Logger;
     246: ldc           #50                 // String Unexpected failure in run method
     248: aload_2
     249: invokeinterface #51,  3           // InterfaceMethod org/slf4j/Logger.error:(Ljava/lang/String;Ljava/lang/Throwable;)V
     254: invokestatic  #20                 // Method java/lang/Thread.currentThread:()Ljava/lang/Thread;
     257: aload_1
     258: invokevirtual #23                 // Method java/lang/Thread.setName:(Ljava/lang/String;)V
     261: goto          276
     264: astore        7
     266: invokestatic  #20                 // Method java/lang/Thread.currentThread:()Ljava/lang/Thread;
     269: aload_1
     270: invokevirtual #23                 // Method java/lang/Thread.setName:(Ljava/lang/String;)V
     273: aload         7
     275: athrow
     276: return
    Exception table:
       from    to  target type
         160   175   178   any
         178   183   178   any
           7   210   220   Class java/lang/Exception
           7   210   264   any
         220   254   264   any
         264   266   264   any

  protected java.lang.String getServerThreadName();
    Code:
       0: ldc           #52                 // String Logback %s (port %d)
       2: iconst_2
       3: anewarray     #53                 // class java/lang/Object
       6: dup
       7: iconst_0
       8: aload_0
       9: invokevirtual #54                 // Method java/lang/Object.getClass:()Ljava/lang/Class;
      12: invokevirtual #55                 // Method java/lang/Class.getSimpleName:()Ljava/lang/String;
      15: aastore
      16: dup
      17: iconst_1
      18: aload_0
      19: getfield      #19                 // Field port:I
      22: invokestatic  #56                 // Method java/lang/Integer.valueOf:(I)Ljava/lang/Integer;
      25: aastore
      26: invokestatic  #57                 // Method java/lang/String.format:(Ljava/lang/String;[Ljava/lang/Object;)Ljava/lang/String;
      29: areturn

  protected java.lang.String getClientThreadName(java.net.Socket);
    Code:
       0: ldc           #58                 // String Logback SocketNode (client: %s)
       2: iconst_1
       3: anewarray     #53                 // class java/lang/Object
       6: dup
       7: iconst_0
       8: aload_1
       9: invokevirtual #59                 // Method java/net/Socket.getRemoteSocketAddress:()Ljava/net/SocketAddress;
      12: aastore
      13: invokestatic  #57                 // Method java/lang/String.format:(Ljava/lang/String;[Ljava/lang/Object;)Ljava/lang/String;
      16: areturn

  protected javax.net.ServerSocketFactory getServerSocketFactory();
    Code:
       0: invokestatic  #60                 // Method javax/net/ServerSocketFactory.getDefault:()Ljavax/net/ServerSocketFactory;
       3: areturn

  void signalAlmostReadiness();
    Code:
       0: aload_0
       1: getfield      #61                 // Field latch:Ljava/util/concurrent/CountDownLatch;
       4: ifnull        26
       7: aload_0
       8: getfield      #61                 // Field latch:Ljava/util/concurrent/CountDownLatch;
      11: invokevirtual #62                 // Method java/util/concurrent/CountDownLatch.getCount:()J
      14: lconst_0
      15: lcmp
      16: ifeq          26
      19: aload_0
      20: getfield      #61                 // Field latch:Ljava/util/concurrent/CountDownLatch;
      23: invokevirtual #63                 // Method java/util/concurrent/CountDownLatch.countDown:()V
      26: return

  void setLatch(java.util.concurrent.CountDownLatch);
    Code:
       0: aload_0
       1: aload_1
       2: putfield      #61                 // Field latch:Ljava/util/concurrent/CountDownLatch;
       5: return

  public java.util.concurrent.CountDownLatch getLatch();
    Code:
       0: aload_0
       1: getfield      #61                 // Field latch:Ljava/util/concurrent/CountDownLatch;
       4: areturn

  public boolean isClosed();
    Code:
       0: aload_0
       1: getfield      #14                 // Field closed:Z
       4: ireturn

  public void close();
    Code:
       0: aload_0
       1: iconst_1
       2: putfield      #14                 // Field closed:Z
       5: aload_0
       6: getfield      #33                 // Field serverSocket:Ljava/net/ServerSocket;
       9: ifnull        56
      12: aload_0
      13: getfield      #33                 // Field serverSocket:Ljava/net/ServerSocket;
      16: invokevirtual #64                 // Method java/net/ServerSocket.close:()V
      19: aload_0
      20: aconst_null
      21: putfield      #33                 // Field serverSocket:Ljava/net/ServerSocket;
      24: goto          56
      27: astore_1
      28: aload_0
      29: getfield      #13                 // Field logger:Lorg/slf4j/Logger;
      32: ldc           #66                 // String Failed to close serverSocket
      34: aload_1
      35: invokeinterface #51,  3           // InterfaceMethod org/slf4j/Logger.error:(Ljava/lang/String;Ljava/lang/Throwable;)V
      40: aload_0
      41: aconst_null
      42: putfield      #33                 // Field serverSocket:Ljava/net/ServerSocket;
      45: goto          56
      48: astore_2
      49: aload_0
      50: aconst_null
      51: putfield      #33                 // Field serverSocket:Ljava/net/ServerSocket;
      54: aload_2
      55: athrow
      56: aload_0
      57: getfield      #13                 // Field logger:Lorg/slf4j/Logger;
      60: ldc           #67                 // String closing this server
      62: invokeinterface #30,  2           // InterfaceMethod org/slf4j/Logger.info:(Ljava/lang/String;)V
      67: aload_0
      68: getfield      #17                 // Field socketNodeList:Ljava/util/List;
      71: dup
      72: astore_1
      73: monitorenter
      74: aload_0
      75: getfield      #17                 // Field socketNodeList:Ljava/util/List;
      78: invokeinterface #68,  1           // InterfaceMethod java/util/List.iterator:()Ljava/util/Iterator;
      83: astore_2
      84: aload_2
      85: invokeinterface #69,  1           // InterfaceMethod java/util/Iterator.hasNext:()Z
      90: ifeq          110
      93: aload_2
      94: invokeinterface #70,  1           // InterfaceMethod java/util/Iterator.next:()Ljava/lang/Object;
      99: checkcast     #41                 // class ch/qos/logback/classic/net/SocketNode
     102: astore_3
     103: aload_3
     104: invokevirtual #71                 // Method ch/qos/logback/classic/net/SocketNode.close:()V
     107: goto          84
     110: aload_1
     111: monitorexit
     112: goto          122
     115: astore        4
     117: aload_1
     118: monitorexit
     119: aload         4
     121: athrow
     122: aload_0
     123: getfield      #17                 // Field socketNodeList:Ljava/util/List;
     126: invokeinterface #72,  1           // InterfaceMethod java/util/List.size:()I
     131: ifeq          145
     134: aload_0
     135: getfield      #13                 // Field logger:Lorg/slf4j/Logger;
     138: ldc           #73                 // String Was expecting a 0-sized socketNodeList after server shutdown
     140: invokeinterface #74,  2           // InterfaceMethod org/slf4j/Logger.warn:(Ljava/lang/String;)V
     145: return
    Exception table:
       from    to  target type
          12    19    27   Class java/io/IOException
          12    19    48   any
          27    40    48   any
          48    49    48   any
          74   112   115   any
         115   119   115   any

  public void socketNodeClosing(ch.qos.logback.classic.net.SocketNode);
    Code:
       0: aload_0
       1: getfield      #13                 // Field logger:Lorg/slf4j/Logger;
       4: ldc           #75                 // String Removing {}
       6: aload_1
       7: invokeinterface #76,  3           // InterfaceMethod org/slf4j/Logger.debug:(Ljava/lang/String;Ljava/lang/Object;)V
      12: aload_0
      13: getfield      #17                 // Field socketNodeList:Ljava/util/List;
      16: dup
      17: astore_2
      18: monitorenter
      19: aload_0
      20: getfield      #17                 // Field socketNodeList:Ljava/util/List;
      23: aload_1
      24: invokeinterface #77,  2           // InterfaceMethod java/util/List.remove:(Ljava/lang/Object;)Z
      29: pop
      30: aload_2
      31: monitorexit
      32: goto          40
      35: astore_3
      36: aload_2
      37: monitorexit
      38: aload_3
      39: athrow
      40: return
    Exception table:
       from    to  target type
          19    32    35   any
          35    38    35   any

  static void usage(java.lang.String);
    Code:
       0: getstatic     #78                 // Field java/lang/System.err:Ljava/io/PrintStream;
       3: aload_0
       4: invokevirtual #79                 // Method java/io/PrintStream.println:(Ljava/lang/String;)V
       7: getstatic     #78                 // Field java/lang/System.err:Ljava/io/PrintStream;
      10: new           #24                 // class java/lang/StringBuilder
      13: dup
      14: invokespecial #25                 // Method java/lang/StringBuilder."<init>":()V
      17: ldc           #80                 // String Usage: java
      19: invokevirtual #27                 // Method java/lang/StringBuilder.append:(Ljava/lang/String;)Ljava/lang/StringBuilder;
      22: ldc_w         #1                  // class ch/qos/logback/classic/net/SimpleSocketServer
      25: invokevirtual #81                 // Method java/lang/Class.getName:()Ljava/lang/String;
      28: invokevirtual #27                 // Method java/lang/StringBuilder.append:(Ljava/lang/String;)Ljava/lang/StringBuilder;
      31: ldc           #82                 // String  port configFile
      33: invokevirtual #27                 // Method java/lang/StringBuilder.append:(Ljava/lang/String;)Ljava/lang/StringBuilder;
      36: invokevirtual #29                 // Method java/lang/StringBuilder.toString:()Ljava/lang/String;
      39: invokevirtual #79                 // Method java/io/PrintStream.println:(Ljava/lang/String;)V
      42: iconst_1
      43: invokestatic  #83                 // Method java/lang/System.exit:(I)V
      46: return

  static int parsePortNumber(java.lang.String);
    Code:
       0: aload_0
       1: invokestatic  #84                 // Method java/lang/Integer.parseInt:(Ljava/lang/String;)I
       4: ireturn
       5: astore_1
       6: aload_1
       7: invokevirtual #86                 // Method java/lang/NumberFormatException.printStackTrace:()V
      10: new           #24                 // class java/lang/StringBuilder
      13: dup
      14: invokespecial #25                 // Method java/lang/StringBuilder."<init>":()V
      17: ldc           #87                 // String Could not interpret port number [
      19: invokevirtual #27                 // Method java/lang/StringBuilder.append:(Ljava/lang/String;)Ljava/lang/StringBuilder;
      22: aload_0
      23: invokevirtual #27                 // Method java/lang/StringBuilder.append:(Ljava/lang/String;)Ljava/lang/StringBuilder;
      26: ldc           #88                 // String ].
      28: invokevirtual #27                 // Method java/lang/StringBuilder.append:(Ljava/lang/String;)Ljava/lang/StringBuilder;
      31: invokevirtual #29                 // Method java/lang/StringBuilder.toString:()Ljava/lang/String;
      34: invokestatic  #5                  // Method usage:(Ljava/lang/String;)V
      37: iconst_m1
      38: ireturn
    Exception table:
       from    to  target type
           0     4     5   Class java/lang/NumberFormatException

  public static void configureLC(ch.qos.logback.classic.LoggerContext, java.lang.String) throws ch.qos.logback.core.joran.spi.JoranException;
    Code:
       0: new           #89                 // class ch/qos/logback/classic/joran/JoranConfigurator
       3: dup
       4: invokespecial #90                 // Method ch/qos/logback/classic/joran/JoranConfigurator."<init>":()V
       7: astore_2
       8: aload_0
       9: invokevirtual #91                 // Method ch/qos/logback/classic/LoggerContext.reset:()V
      12: aload_2
      13: aload_0
      14: invokevirtual #92                 // Method ch/qos/logback/classic/joran/JoranConfigurator.setContext:(Lch/qos/logback/core/Context;)V
      17: aload_2
      18: aload_1
      19: invokevirtual #93                 // Method ch/qos/logback/classic/joran/JoranConfigurator.doConfigure:(Ljava/lang/String;)V
      22: return
}
