Compiled from "AxiomAnnotationButton.java"
public class org.protege.editor.owl.ui.framelist.AxiomAnnotationButton extends org.protege.editor.core.ui.list.MListButton {
  public static final java.awt.Color ROLL_OVER_COLOR;

  private static final java.lang.String ANNOTATE_STRING;

  private boolean annotationPresent;

  public org.protege.editor.owl.ui.framelist.AxiomAnnotationButton(java.awt.event.ActionListener);
    Code:
       0: aload_0
       1: ldc           #1                  // String Annotations
       3: getstatic     #2                  // Field ROLL_OVER_COLOR:Ljava/awt/Color;
       6: aload_1
       7: invokespecial #3                  // Method org/protege/editor/core/ui/list/MListButton."<init>":(Ljava/lang/String;Ljava/awt/Color;Ljava/awt/event/ActionListener;)V
      10: aload_0
      11: iconst_0
      12: putfield      #4                  // Field annotationPresent:Z
      15: return

  public java.awt.Color getBackground();
    Code:
       0: aload_0
       1: getfield      #4                  // Field annotationPresent:Z
       4: ifeq          11
       7: getstatic     #5                  // Field java/awt/Color.ORANGE:Ljava/awt/Color;
      10: areturn
      11: aload_0
      12: invokespecial #6                  // Method org/protege/editor/core/ui/list/MListButton.getBackground:()Ljava/awt/Color;
      15: areturn

  public void paintButtonContent(java.awt.Graphics2D);
    Code:
       0: aload_0
       1: invokevirtual #7                  // Method getBounds:()Ljava/awt/Rectangle;
       4: getfield      #8                  // Field java/awt/Rectangle.width:I
       7: istore_2
       8: aload_0
       9: invokevirtual #7                  // Method getBounds:()Ljava/awt/Rectangle;
      12: getfield      #9                  // Field java/awt/Rectangle.height:I
      15: istore_3
      16: aload_0
      17: invokevirtual #7                  // Method getBounds:()Ljava/awt/Rectangle;
      20: getfield      #10                 // Field java/awt/Rectangle.x:I
      23: istore        4
      25: aload_0
      26: invokevirtual #7                  // Method getBounds:()Ljava/awt/Rectangle;
      29: getfield      #11                 // Field java/awt/Rectangle.y:I
      32: istore        5
      34: aload_1
      35: invokevirtual #12                 // Method java/awt/Graphics2D.getFont:()Ljava/awt/Font;
      38: iconst_1
      39: invokestatic  #14                 // Method org/protege/editor/owl/ui/renderer/OWLRendererPreferences.getInstance:()Lorg/protege/editor/owl/ui/renderer/OWLRendererPreferences;
      42: invokevirtual #15                 // Method org/protege/editor/owl/ui/renderer/OWLRendererPreferences.getFontSize:()I
      45: i2f
      46: invokevirtual #16                 // Method java/awt/Font.deriveFont:(IF)Ljava/awt/Font;
      49: astore        6
      51: aload_1
      52: aload         6
      54: invokevirtual #17                 // Method java/awt/Graphics2D.setFont:(Ljava/awt/Font;)V
      57: aload_1
      58: aload         6
      60: invokevirtual #18                 // Method java/awt/Graphics2D.getFontMetrics:(Ljava/awt/Font;)Ljava/awt/FontMetrics;
      63: astore        7
      65: aload         7
      67: ldc           #20                 // String @
      69: aload_1
      70: invokevirtual #21                 // Method java/awt/FontMetrics.getStringBounds:(Ljava/lang/String;Ljava/awt/Graphics;)Ljava/awt/geom/Rectangle2D;
      73: invokevirtual #22                 // Method java/awt/geom/Rectangle2D.getBounds:()Ljava/awt/Rectangle;
      76: astore        8
      78: aload         7
      80: invokevirtual #23                 // Method java/awt/FontMetrics.getLeading:()I
      83: aload         7
      85: invokevirtual #24                 // Method java/awt/FontMetrics.getAscent:()I
      88: iadd
      89: istore        9
      91: aload_1
      92: ldc           #20                 // String @
      94: iload         4
      96: iload_2
      97: iconst_2
      98: idiv
      99: iadd
     100: aload         8
     102: getfield      #8                  // Field java/awt/Rectangle.width:I
     105: iconst_2
     106: idiv
     107: isub
     108: iload         5
     110: iload_3
     111: aload         8
     113: getfield      #9                  // Field java/awt/Rectangle.height:I
     116: isub
     117: iconst_2
     118: idiv
     119: iadd
     120: iload         9
     122: iadd
     123: invokevirtual #25                 // Method java/awt/Graphics2D.drawString:(Ljava/lang/String;II)V
     126: aload_1
     127: aload         6
     129: invokevirtual #17                 // Method java/awt/Graphics2D.setFont:(Ljava/awt/Font;)V
     132: return

  public void setAnnotationPresent(boolean);
    Code:
       0: aload_0
       1: iload_1
       2: putfield      #4                  // Field annotationPresent:Z
       5: return

  static {};
    Code:
       0: new           #26                 // class java/awt/Color
       3: dup
       4: iconst_0
       5: iconst_0
       6: iconst_0
       7: invokespecial #27                 // Method java/awt/Color."<init>":(III)V
      10: putstatic     #2                  // Field ROLL_OVER_COLOR:Ljava/awt/Color;
      13: return
}
