Compiled from "BulkWriteOptions.kt"
public final class io.vertx.kotlin.ext.mongo.BulkWriteOptionsKt {
  public static final io.vertx.ext.mongo.BulkWriteOptions bulkWriteOptionsOf(java.lang.Boolean, io.vertx.ext.mongo.WriteOption);
    Code:
       0: new           #10                 // class io/vertx/ext/mongo/BulkWriteOptions
       3: dup
       4: invokespecial #14                 // Method io/vertx/ext/mongo/BulkWriteOptions."<init>":()V
       7: astore_2
       8: iconst_0
       9: istore_3
      10: iconst_0
      11: istore        4
      13: aload_2
      14: astore        5
      16: iconst_0
      17: istore        6
      19: aload_0
      20: ifnull        33
      23: aload         5
      25: aload_0
      26: invokevirtual #20                 // Method java/lang/Boolean.booleanValue:()Z
      29: invokevirtual #24                 // Method io/vertx/ext/mongo/BulkWriteOptions.setOrdered:(Z)Lio/vertx/ext/mongo/BulkWriteOptions;
      32: pop
      33: aload_1
      34: ifnull        44
      37: aload         5
      39: aload_1
      40: invokevirtual #28                 // Method io/vertx/ext/mongo/BulkWriteOptions.setWriteOption:(Lio/vertx/ext/mongo/WriteOption;)Lio/vertx/ext/mongo/BulkWriteOptions;
      43: pop
      44: nop
      45: aload_2
      46: areturn

  public static io.vertx.ext.mongo.BulkWriteOptions bulkWriteOptionsOf$default(java.lang.Boolean, io.vertx.ext.mongo.WriteOption, int, java.lang.Object);
    Code:
       0: iload_2
       1: iconst_1
       2: iand
       3: ifeq          11
       6: aconst_null
       7: checkcast     #16                 // class java/lang/Boolean
      10: astore_0
      11: iload_2
      12: iconst_2
      13: iand
      14: ifeq          22
      17: aconst_null
      18: checkcast     #38                 // class io/vertx/ext/mongo/WriteOption
      21: astore_1
      22: aload_0
      23: aload_1
      24: invokestatic  #42                 // Method bulkWriteOptionsOf:(Ljava/lang/Boolean;Lio/vertx/ext/mongo/WriteOption;)Lio/vertx/ext/mongo/BulkWriteOptions;
      27: areturn

  public static final io.vertx.ext.mongo.BulkWriteOptions BulkWriteOptions(java.lang.Boolean, io.vertx.ext.mongo.WriteOption);
    Code:
       0: new           #10                 // class io/vertx/ext/mongo/BulkWriteOptions
       3: dup
       4: invokespecial #14                 // Method io/vertx/ext/mongo/BulkWriteOptions."<init>":()V
       7: astore_2
       8: iconst_0
       9: istore_3
      10: iconst_0
      11: istore        4
      13: aload_2
      14: astore        5
      16: iconst_0
      17: istore        6
      19: aload_0
      20: ifnull        33
      23: aload         5
      25: aload_0
      26: invokevirtual #20                 // Method java/lang/Boolean.booleanValue:()Z
      29: invokevirtual #24                 // Method io/vertx/ext/mongo/BulkWriteOptions.setOrdered:(Z)Lio/vertx/ext/mongo/BulkWriteOptions;
      32: pop
      33: aload_1
      34: ifnull        44
      37: aload         5
      39: aload_1
      40: invokevirtual #28                 // Method io/vertx/ext/mongo/BulkWriteOptions.setWriteOption:(Lio/vertx/ext/mongo/WriteOption;)Lio/vertx/ext/mongo/BulkWriteOptions;
      43: pop
      44: nop
      45: aload_2
      46: areturn

  public static io.vertx.ext.mongo.BulkWriteOptions BulkWriteOptions$default(java.lang.Boolean, io.vertx.ext.mongo.WriteOption, int, java.lang.Object);
    Code:
       0: iload_2
       1: iconst_1
       2: iand
       3: ifeq          11
       6: aconst_null
       7: checkcast     #16                 // class java/lang/Boolean
      10: astore_0
      11: iload_2
      12: iconst_2
      13: iand
      14: ifeq          22
      17: aconst_null
      18: checkcast     #38                 // class io/vertx/ext/mongo/WriteOption
      21: astore_1
      22: aload_0
      23: aload_1
      24: invokestatic  #55                 // Method BulkWriteOptions:(Ljava/lang/Boolean;Lio/vertx/ext/mongo/WriteOption;)Lio/vertx/ext/mongo/BulkWriteOptions;
      27: areturn
}
