Compiled from "BasicHttpCache.java"
class org.apache.http.impl.client.cache.BasicHttpCache$2 implements org.apache.http.client.cache.HttpCacheUpdateCallback {
  final org.apache.http.HttpRequest val$req;

  final org.apache.http.client.cache.HttpCacheEntry val$entry;

  final java.lang.String val$variantKey;

  final java.lang.String val$variantCacheKey;

  final org.apache.http.impl.client.cache.BasicHttpCache this$0;

  org.apache.http.impl.client.cache.BasicHttpCache$2(org.apache.http.impl.client.cache.BasicHttpCache, org.apache.http.HttpRequest, org.apache.http.client.cache.HttpCacheEntry, java.lang.String, java.lang.String);
    Code:
       0: aload_0
       1: aload_1
       2: putfield      #1                  // Field this$0:Lorg/apache/http/impl/client/cache/BasicHttpCache;
       5: aload_0
       6: aload_2
       7: putfield      #2                  // Field val$req:Lorg/apache/http/HttpRequest;
      10: aload_0
      11: aload_3
      12: putfield      #3                  // Field val$entry:Lorg/apache/http/client/cache/HttpCacheEntry;
      15: aload_0
      16: aload         4
      18: putfield      #4                  // Field val$variantKey:Ljava/lang/String;
      21: aload_0
      22: aload         5
      24: putfield      #5                  // Field val$variantCacheKey:Ljava/lang/String;
      27: aload_0
      28: invokespecial #6                  // Method java/lang/Object."<init>":()V
      31: return

  public org.apache.http.client.cache.HttpCacheEntry update(org.apache.http.client.cache.HttpCacheEntry) throws java.io.IOException;
    Code:
       0: aload_0
       1: getfield      #1                  // Field this$0:Lorg/apache/http/impl/client/cache/BasicHttpCache;
       4: aload_0
       5: getfield      #2                  // Field val$req:Lorg/apache/http/HttpRequest;
       8: invokeinterface #7,  1            // InterfaceMethod org/apache/http/HttpRequest.getRequestLine:()Lorg/apache/http/RequestLine;
      13: invokeinterface #8,  1            // InterfaceMethod org/apache/http/RequestLine.getUri:()Ljava/lang/String;
      18: aload_1
      19: aload_0
      20: getfield      #3                  // Field val$entry:Lorg/apache/http/client/cache/HttpCacheEntry;
      23: aload_0
      24: getfield      #4                  // Field val$variantKey:Ljava/lang/String;
      27: aload_0
      28: getfield      #5                  // Field val$variantCacheKey:Ljava/lang/String;
      31: invokevirtual #9                  // Method org/apache/http/impl/client/cache/BasicHttpCache.doGetUpdatedParentEntry:(Ljava/lang/String;Lorg/apache/http/client/cache/HttpCacheEntry;Lorg/apache/http/client/cache/HttpCacheEntry;Ljava/lang/String;Ljava/lang/String;)Lorg/apache/http/client/cache/HttpCacheEntry;
      34: areturn
}
