Compiled from "CachingHttpClientBuilder.java"
public class org.apache.http.impl.client.cache.CachingHttpClientBuilder extends org.apache.http.impl.client.HttpClientBuilder {
  private org.apache.http.client.cache.ResourceFactory resourceFactory;

  private org.apache.http.client.cache.HttpCacheStorage storage;

  private java.io.File cacheDir;

  private org.apache.http.impl.client.cache.CacheConfig cacheConfig;

  private org.apache.http.impl.client.cache.SchedulingStrategy schedulingStrategy;

  private org.apache.http.client.cache.HttpCacheInvalidator httpCacheInvalidator;

  private boolean deleteCache;

  public static org.apache.http.impl.client.cache.CachingHttpClientBuilder create();
    Code:
       0: new           #1                  // class org/apache/http/impl/client/cache/CachingHttpClientBuilder
       3: dup
       4: invokespecial #2                  // Method "<init>":()V
       7: areturn

  protected org.apache.http.impl.client.cache.CachingHttpClientBuilder();
    Code:
       0: aload_0
       1: invokespecial #3                  // Method org/apache/http/impl/client/HttpClientBuilder."<init>":()V
       4: aload_0
       5: iconst_1
       6: putfield      #4                  // Field deleteCache:Z
       9: return

  public final org.apache.http.impl.client.cache.CachingHttpClientBuilder setResourceFactory(org.apache.http.client.cache.ResourceFactory);
    Code:
       0: aload_0
       1: aload_1
       2: putfield      #5                  // Field resourceFactory:Lorg/apache/http/client/cache/ResourceFactory;
       5: aload_0
       6: areturn

  public final org.apache.http.impl.client.cache.CachingHttpClientBuilder setHttpCacheStorage(org.apache.http.client.cache.HttpCacheStorage);
    Code:
       0: aload_0
       1: aload_1
       2: putfield      #6                  // Field storage:Lorg/apache/http/client/cache/HttpCacheStorage;
       5: aload_0
       6: areturn

  public final org.apache.http.impl.client.cache.CachingHttpClientBuilder setCacheDir(java.io.File);
    Code:
       0: aload_0
       1: aload_1
       2: putfield      #7                  // Field cacheDir:Ljava/io/File;
       5: aload_0
       6: areturn

  public final org.apache.http.impl.client.cache.CachingHttpClientBuilder setCacheConfig(org.apache.http.impl.client.cache.CacheConfig);
    Code:
       0: aload_0
       1: aload_1
       2: putfield      #8                  // Field cacheConfig:Lorg/apache/http/impl/client/cache/CacheConfig;
       5: aload_0
       6: areturn

  public final org.apache.http.impl.client.cache.CachingHttpClientBuilder setSchedulingStrategy(org.apache.http.impl.client.cache.SchedulingStrategy);
    Code:
       0: aload_0
       1: aload_1
       2: putfield      #9                  // Field schedulingStrategy:Lorg/apache/http/impl/client/cache/SchedulingStrategy;
       5: aload_0
       6: areturn

  public final org.apache.http.impl.client.cache.CachingHttpClientBuilder setHttpCacheInvalidator(org.apache.http.client.cache.HttpCacheInvalidator);
    Code:
       0: aload_0
       1: aload_1
       2: putfield      #10                 // Field httpCacheInvalidator:Lorg/apache/http/client/cache/HttpCacheInvalidator;
       5: aload_0
       6: areturn

  public org.apache.http.impl.client.cache.CachingHttpClientBuilder setDeleteCache(boolean);
    Code:
       0: aload_0
       1: iload_1
       2: putfield      #4                  // Field deleteCache:Z
       5: aload_0
       6: areturn

  protected org.apache.http.impl.execchain.ClientExecChain decorateMainExec(org.apache.http.impl.execchain.ClientExecChain);
    Code:
       0: aload_0
       1: getfield      #8                  // Field cacheConfig:Lorg/apache/http/impl/client/cache/CacheConfig;
       4: ifnull        14
       7: aload_0
       8: getfield      #8                  // Field cacheConfig:Lorg/apache/http/impl/client/cache/CacheConfig;
      11: goto          17
      14: getstatic     #11                 // Field org/apache/http/impl/client/cache/CacheConfig.DEFAULT:Lorg/apache/http/impl/client/cache/CacheConfig;
      17: astore_2
      18: aload_0
      19: getfield      #5                  // Field resourceFactory:Lorg/apache/http/client/cache/ResourceFactory;
      22: astore_3
      23: aload_3
      24: ifnonnull     57
      27: aload_0
      28: getfield      #7                  // Field cacheDir:Ljava/io/File;
      31: ifnonnull     45
      34: new           #12                 // class org/apache/http/impl/client/cache/HeapResourceFactory
      37: dup
      38: invokespecial #13                 // Method org/apache/http/impl/client/cache/HeapResourceFactory."<init>":()V
      41: astore_3
      42: goto          57
      45: new           #14                 // class org/apache/http/impl/client/cache/FileResourceFactory
      48: dup
      49: aload_0
      50: getfield      #7                  // Field cacheDir:Ljava/io/File;
      53: invokespecial #15                 // Method org/apache/http/impl/client/cache/FileResourceFactory."<init>":(Ljava/io/File;)V
      56: astore_3
      57: aload_0
      58: getfield      #6                  // Field storage:Lorg/apache/http/client/cache/HttpCacheStorage;
      61: astore        4
      63: aload         4
      65: ifnonnull     132
      68: aload_0
      69: getfield      #7                  // Field cacheDir:Ljava/io/File;
      72: ifnonnull     88
      75: new           #16                 // class org/apache/http/impl/client/cache/BasicHttpCacheStorage
      78: dup
      79: aload_2
      80: invokespecial #17                 // Method org/apache/http/impl/client/cache/BasicHttpCacheStorage."<init>":(Lorg/apache/http/impl/client/cache/CacheConfig;)V
      83: astore        4
      85: goto          132
      88: new           #18                 // class org/apache/http/impl/client/cache/ManagedHttpCacheStorage
      91: dup
      92: aload_2
      93: invokespecial #19                 // Method org/apache/http/impl/client/cache/ManagedHttpCacheStorage."<init>":(Lorg/apache/http/impl/client/cache/CacheConfig;)V
      96: astore        5
      98: aload_0
      99: getfield      #4                  // Field deleteCache:Z
     102: ifeq          122
     105: aload_0
     106: new           #20                 // class org/apache/http/impl/client/cache/CachingHttpClientBuilder$1
     109: dup
     110: aload_0
     111: aload         5
     113: invokespecial #21                 // Method org/apache/http/impl/client/cache/CachingHttpClientBuilder$1."<init>":(Lorg/apache/http/impl/client/cache/CachingHttpClientBuilder;Lorg/apache/http/impl/client/cache/ManagedHttpCacheStorage;)V
     116: invokevirtual #22                 // Method addCloseable:(Ljava/io/Closeable;)V
     119: goto          128
     122: aload_0
     123: aload         5
     125: invokevirtual #22                 // Method addCloseable:(Ljava/io/Closeable;)V
     128: aload         5
     130: astore        4
     132: aload_0
     133: aload_2
     134: invokespecial #23                 // Method createAsynchronousRevalidator:(Lorg/apache/http/impl/client/cache/CacheConfig;)Lorg/apache/http/impl/client/cache/AsynchronousValidator;
     137: astore        5
     139: new           #24                 // class org/apache/http/impl/client/cache/CacheKeyGenerator
     142: dup
     143: invokespecial #25                 // Method org/apache/http/impl/client/cache/CacheKeyGenerator."<init>":()V
     146: astore        6
     148: aload_0
     149: getfield      #10                 // Field httpCacheInvalidator:Lorg/apache/http/client/cache/HttpCacheInvalidator;
     152: astore        7
     154: aload         7
     156: ifnonnull     172
     159: new           #26                 // class org/apache/http/impl/client/cache/CacheInvalidator
     162: dup
     163: aload         6
     165: aload         4
     167: invokespecial #27                 // Method org/apache/http/impl/client/cache/CacheInvalidator."<init>":(Lorg/apache/http/impl/client/cache/CacheKeyGenerator;Lorg/apache/http/client/cache/HttpCacheStorage;)V
     170: astore        7
     172: new           #28                 // class org/apache/http/impl/client/cache/CachingExec
     175: dup
     176: aload_1
     177: new           #29                 // class org/apache/http/impl/client/cache/BasicHttpCache
     180: dup
     181: aload_3
     182: aload         4
     184: aload_2
     185: aload         6
     187: aload         7
     189: invokespecial #30                 // Method org/apache/http/impl/client/cache/BasicHttpCache."<init>":(Lorg/apache/http/client/cache/ResourceFactory;Lorg/apache/http/client/cache/HttpCacheStorage;Lorg/apache/http/impl/client/cache/CacheConfig;Lorg/apache/http/impl/client/cache/CacheKeyGenerator;Lorg/apache/http/client/cache/HttpCacheInvalidator;)V
     192: aload_2
     193: aload         5
     195: invokespecial #31                 // Method org/apache/http/impl/client/cache/CachingExec."<init>":(Lorg/apache/http/impl/execchain/ClientExecChain;Lorg/apache/http/impl/client/cache/HttpCache;Lorg/apache/http/impl/client/cache/CacheConfig;Lorg/apache/http/impl/client/cache/AsynchronousValidator;)V
     198: areturn

  private org.apache.http.impl.client.cache.AsynchronousValidator createAsynchronousRevalidator(org.apache.http.impl.client.cache.CacheConfig);
    Code:
       0: aload_1
       1: invokevirtual #32                 // Method org/apache/http/impl/client/cache/CacheConfig.getAsynchronousWorkersMax:()I
       4: ifle          29
       7: aload_0
       8: aload_1
       9: invokespecial #33                 // Method createSchedulingStrategy:(Lorg/apache/http/impl/client/cache/CacheConfig;)Lorg/apache/http/impl/client/cache/SchedulingStrategy;
      12: astore_2
      13: new           #34                 // class org/apache/http/impl/client/cache/AsynchronousValidator
      16: dup
      17: aload_2
      18: invokespecial #35                 // Method org/apache/http/impl/client/cache/AsynchronousValidator."<init>":(Lorg/apache/http/impl/client/cache/SchedulingStrategy;)V
      21: astore_3
      22: aload_0
      23: aload_3
      24: invokevirtual #22                 // Method addCloseable:(Ljava/io/Closeable;)V
      27: aload_3
      28: areturn
      29: aconst_null
      30: areturn

  private org.apache.http.impl.client.cache.SchedulingStrategy createSchedulingStrategy(org.apache.http.impl.client.cache.CacheConfig);
    Code:
       0: aload_0
       1: getfield      #9                  // Field schedulingStrategy:Lorg/apache/http/impl/client/cache/SchedulingStrategy;
       4: ifnull        14
       7: aload_0
       8: getfield      #9                  // Field schedulingStrategy:Lorg/apache/http/impl/client/cache/SchedulingStrategy;
      11: goto          22
      14: new           #36                 // class org/apache/http/impl/client/cache/ImmediateSchedulingStrategy
      17: dup
      18: aload_1
      19: invokespecial #37                 // Method org/apache/http/impl/client/cache/ImmediateSchedulingStrategy."<init>":(Lorg/apache/http/impl/client/cache/CacheConfig;)V
      22: areturn
}
