Compiled from "NMClientAsyncImpl.java"
public class org.apache.hadoop.yarn.client.api.async.impl.NMClientAsyncImpl$ContainerEventProcessor implements java.lang.Runnable {
  protected org.apache.hadoop.yarn.client.api.async.impl.NMClientAsyncImpl$ContainerEvent event;

  final org.apache.hadoop.yarn.client.api.async.impl.NMClientAsyncImpl this$0;

  public org.apache.hadoop.yarn.client.api.async.impl.NMClientAsyncImpl$ContainerEventProcessor(org.apache.hadoop.yarn.client.api.async.impl.NMClientAsyncImpl, org.apache.hadoop.yarn.client.api.async.impl.NMClientAsyncImpl$ContainerEvent);
    Code:
       0: aload_0
       1: aload_1
       2: putfield      #1                  // Field this$0:Lorg/apache/hadoop/yarn/client/api/async/impl/NMClientAsyncImpl;
       5: aload_0
       6: invokespecial #2                  // Method java/lang/Object."<init>":()V
       9: aload_0
      10: aload_2
      11: putfield      #3                  // Field event:Lorg/apache/hadoop/yarn/client/api/async/impl/NMClientAsyncImpl$ContainerEvent;
      14: return

  public void run();
    Code:
       0: aload_0
       1: getfield      #3                  // Field event:Lorg/apache/hadoop/yarn/client/api/async/impl/NMClientAsyncImpl$ContainerEvent;
       4: invokevirtual #4                  // Method org/apache/hadoop/yarn/client/api/async/impl/NMClientAsyncImpl$ContainerEvent.getContainerId:()Lorg/apache/hadoop/yarn/api/records/ContainerId;
       7: astore_1
       8: invokestatic  #5                  // Method org/apache/hadoop/yarn/client/api/async/impl/NMClientAsyncImpl.access$000:()Lorg/slf4j/Logger;
      11: new           #6                  // class java/lang/StringBuilder
      14: dup
      15: invokespecial #7                  // Method java/lang/StringBuilder."<init>":()V
      18: ldc           #8                  // String Processing Event
      20: invokevirtual #9                  // Method java/lang/StringBuilder.append:(Ljava/lang/String;)Ljava/lang/StringBuilder;
      23: aload_0
      24: getfield      #3                  // Field event:Lorg/apache/hadoop/yarn/client/api/async/impl/NMClientAsyncImpl$ContainerEvent;
      27: invokevirtual #10                 // Method java/lang/StringBuilder.append:(Ljava/lang/Object;)Ljava/lang/StringBuilder;
      30: ldc           #11                 // String  for Container
      32: invokevirtual #9                  // Method java/lang/StringBuilder.append:(Ljava/lang/String;)Ljava/lang/StringBuilder;
      35: aload_1
      36: invokevirtual #10                 // Method java/lang/StringBuilder.append:(Ljava/lang/Object;)Ljava/lang/StringBuilder;
      39: invokevirtual #12                 // Method java/lang/StringBuilder.toString:()Ljava/lang/String;
      42: invokeinterface #13,  2           // InterfaceMethod org/slf4j/Logger.info:(Ljava/lang/String;)V
      47: aload_0
      48: getfield      #3                  // Field event:Lorg/apache/hadoop/yarn/client/api/async/impl/NMClientAsyncImpl$ContainerEvent;
      51: invokevirtual #14                 // Method org/apache/hadoop/yarn/client/api/async/impl/NMClientAsyncImpl$ContainerEvent.getType:()Ljava/lang/Enum;
      54: getstatic     #15                 // Field org/apache/hadoop/yarn/client/api/async/impl/NMClientAsyncImpl$ContainerEventType.QUERY_CONTAINER:Lorg/apache/hadoop/yarn/client/api/async/impl/NMClientAsyncImpl$ContainerEventType;
      57: if_acmpne     164
      60: aload_0
      61: getfield      #1                  // Field this$0:Lorg/apache/hadoop/yarn/client/api/async/impl/NMClientAsyncImpl;
      64: invokestatic  #16                 // Method org/apache/hadoop/yarn/client/api/async/impl/NMClientAsyncImpl.access$300:(Lorg/apache/hadoop/yarn/client/api/async/impl/NMClientAsyncImpl;)Lorg/apache/hadoop/yarn/client/api/NMClient;
      67: aload_1
      68: aload_0
      69: getfield      #3                  // Field event:Lorg/apache/hadoop/yarn/client/api/async/impl/NMClientAsyncImpl$ContainerEvent;
      72: invokevirtual #17                 // Method org/apache/hadoop/yarn/client/api/async/impl/NMClientAsyncImpl$ContainerEvent.getNodeId:()Lorg/apache/hadoop/yarn/api/records/NodeId;
      75: invokevirtual #18                 // Method org/apache/hadoop/yarn/client/api/NMClient.getContainerStatus:(Lorg/apache/hadoop/yarn/api/records/ContainerId;Lorg/apache/hadoop/yarn/api/records/NodeId;)Lorg/apache/hadoop/yarn/api/records/ContainerStatus;
      78: astore_2
      79: aload_0
      80: getfield      #1                  // Field this$0:Lorg/apache/hadoop/yarn/client/api/async/impl/NMClientAsyncImpl;
      83: invokestatic  #19                 // Method org/apache/hadoop/yarn/client/api/async/impl/NMClientAsyncImpl.access$400:(Lorg/apache/hadoop/yarn/client/api/async/impl/NMClientAsyncImpl;)Lorg/apache/hadoop/yarn/client/api/async/NMClientAsync$CallbackHandler;
      86: aload_1
      87: aload_2
      88: invokeinterface #20,  3           // InterfaceMethod org/apache/hadoop/yarn/client/api/async/NMClientAsync$CallbackHandler.onContainerStatusReceived:(Lorg/apache/hadoop/yarn/api/records/ContainerId;Lorg/apache/hadoop/yarn/api/records/ContainerStatus;)V
      93: goto          131
      96: astore_3
      97: invokestatic  #5                  // Method org/apache/hadoop/yarn/client/api/async/impl/NMClientAsyncImpl.access$000:()Lorg/slf4j/Logger;
     100: new           #6                  // class java/lang/StringBuilder
     103: dup
     104: invokespecial #7                  // Method java/lang/StringBuilder."<init>":()V
     107: ldc           #22                 // String Unchecked exception is thrown from onContainerStatusReceived for Container
     109: invokevirtual #9                  // Method java/lang/StringBuilder.append:(Ljava/lang/String;)Ljava/lang/StringBuilder;
     112: aload_0
     113: getfield      #3                  // Field event:Lorg/apache/hadoop/yarn/client/api/async/impl/NMClientAsyncImpl$ContainerEvent;
     116: invokevirtual #4                  // Method org/apache/hadoop/yarn/client/api/async/impl/NMClientAsyncImpl$ContainerEvent.getContainerId:()Lorg/apache/hadoop/yarn/api/records/ContainerId;
     119: invokevirtual #10                 // Method java/lang/StringBuilder.append:(Ljava/lang/Object;)Ljava/lang/StringBuilder;
     122: invokevirtual #12                 // Method java/lang/StringBuilder.toString:()Ljava/lang/String;
     125: aload_3
     126: invokeinterface #23,  3           // InterfaceMethod org/slf4j/Logger.info:(Ljava/lang/String;Ljava/lang/Throwable;)V
     131: goto          253
     134: astore_2
     135: aload_0
     136: aload_1
     137: aload_2
     138: invokespecial #25                 // Method onExceptionRaised:(Lorg/apache/hadoop/yarn/api/records/ContainerId;Ljava/lang/Throwable;)V
     141: goto          253
     144: astore_2
     145: aload_0
     146: aload_1
     147: aload_2
     148: invokespecial #25                 // Method onExceptionRaised:(Lorg/apache/hadoop/yarn/api/records/ContainerId;Ljava/lang/Throwable;)V
     151: goto          253
     154: astore_2
     155: aload_0
     156: aload_1
     157: aload_2
     158: invokespecial #25                 // Method onExceptionRaised:(Lorg/apache/hadoop/yarn/api/records/ContainerId;Ljava/lang/Throwable;)V
     161: goto          253
     164: aload_0
     165: getfield      #1                  // Field this$0:Lorg/apache/hadoop/yarn/client/api/async/impl/NMClientAsyncImpl;
     168: getfield      #27                 // Field org/apache/hadoop/yarn/client/api/async/impl/NMClientAsyncImpl.containers:Ljava/util/concurrent/ConcurrentMap;
     171: aload_1
     172: invokeinterface #28,  2           // InterfaceMethod java/util/concurrent/ConcurrentMap.get:(Ljava/lang/Object;)Ljava/lang/Object;
     177: checkcast     #29                 // class org/apache/hadoop/yarn/client/api/async/impl/NMClientAsyncImpl$StatefulContainer
     180: astore_2
     181: aload_2
     182: ifnonnull     220
     185: invokestatic  #5                  // Method org/apache/hadoop/yarn/client/api/async/impl/NMClientAsyncImpl.access$000:()Lorg/slf4j/Logger;
     188: new           #6                  // class java/lang/StringBuilder
     191: dup
     192: invokespecial #7                  // Method java/lang/StringBuilder."<init>":()V
     195: ldc           #30                 // String Container
     197: invokevirtual #9                  // Method java/lang/StringBuilder.append:(Ljava/lang/String;)Ljava/lang/StringBuilder;
     200: aload_1
     201: invokevirtual #10                 // Method java/lang/StringBuilder.append:(Ljava/lang/Object;)Ljava/lang/StringBuilder;
     204: ldc           #31                 // String  is already stopped or failed
     206: invokevirtual #9                  // Method java/lang/StringBuilder.append:(Ljava/lang/String;)Ljava/lang/StringBuilder;
     209: invokevirtual #12                 // Method java/lang/StringBuilder.toString:()Ljava/lang/String;
     212: invokeinterface #13,  2           // InterfaceMethod org/slf4j/Logger.info:(Ljava/lang/String;)V
     217: goto          253
     220: aload_2
     221: aload_0
     222: getfield      #3                  // Field event:Lorg/apache/hadoop/yarn/client/api/async/impl/NMClientAsyncImpl$ContainerEvent;
     225: invokevirtual #32                 // Method org/apache/hadoop/yarn/client/api/async/impl/NMClientAsyncImpl$StatefulContainer.handle:(Lorg/apache/hadoop/yarn/client/api/async/impl/NMClientAsyncImpl$ContainerEvent;)V
     228: aload_0
     229: getfield      #1                  // Field this$0:Lorg/apache/hadoop/yarn/client/api/async/impl/NMClientAsyncImpl;
     232: aload_2
     233: invokevirtual #33                 // Method org/apache/hadoop/yarn/client/api/async/impl/NMClientAsyncImpl.isCompletelyDone:(Lorg/apache/hadoop/yarn/client/api/async/impl/NMClientAsyncImpl$StatefulContainer;)Z
     236: ifeq          253
     239: aload_0
     240: getfield      #1                  // Field this$0:Lorg/apache/hadoop/yarn/client/api/async/impl/NMClientAsyncImpl;
     243: getfield      #27                 // Field org/apache/hadoop/yarn/client/api/async/impl/NMClientAsyncImpl.containers:Ljava/util/concurrent/ConcurrentMap;
     246: aload_1
     247: invokeinterface #34,  2           // InterfaceMethod java/util/concurrent/ConcurrentMap.remove:(Ljava/lang/Object;)Ljava/lang/Object;
     252: pop
     253: return
    Exception table:
       from    to  target type
          79    93    96   Class java/lang/Throwable
          60   131   134   Class org/apache/hadoop/yarn/exceptions/YarnException
          60   131   144   Class java/io/IOException
          60   131   154   Class java/lang/Throwable

  private void onExceptionRaised(org.apache.hadoop.yarn.api.records.ContainerId, java.lang.Throwable);
    Code:
       0: aload_0
       1: getfield      #1                  // Field this$0:Lorg/apache/hadoop/yarn/client/api/async/impl/NMClientAsyncImpl;
       4: invokestatic  #35                 // Method org/apache/hadoop/yarn/client/api/async/impl/NMClientAsyncImpl.access$500:(Lorg/apache/hadoop/yarn/client/api/async/impl/NMClientAsyncImpl;)Lorg/apache/hadoop/yarn/client/api/async/NMClientAsync$CallbackHandler;
       7: aload_1
       8: aload_2
       9: invokeinterface #36,  3           // InterfaceMethod org/apache/hadoop/yarn/client/api/async/NMClientAsync$CallbackHandler.onGetContainerStatusError:(Lorg/apache/hadoop/yarn/api/records/ContainerId;Ljava/lang/Throwable;)V
      14: goto          46
      17: astore_3
      18: invokestatic  #5                  // Method org/apache/hadoop/yarn/client/api/async/impl/NMClientAsyncImpl.access$000:()Lorg/slf4j/Logger;
      21: new           #6                  // class java/lang/StringBuilder
      24: dup
      25: invokespecial #7                  // Method java/lang/StringBuilder."<init>":()V
      28: ldc           #37                 // String Unchecked exception is thrown from onGetContainerStatusError for Container
      30: invokevirtual #9                  // Method java/lang/StringBuilder.append:(Ljava/lang/String;)Ljava/lang/StringBuilder;
      33: aload_1
      34: invokevirtual #10                 // Method java/lang/StringBuilder.append:(Ljava/lang/Object;)Ljava/lang/StringBuilder;
      37: invokevirtual #12                 // Method java/lang/StringBuilder.toString:()Ljava/lang/String;
      40: aload_3
      41: invokeinterface #23,  3           // InterfaceMethod org/slf4j/Logger.info:(Ljava/lang/String;Ljava/lang/Throwable;)V
      46: return
    Exception table:
       from    to  target type
           0    14    17   Class java/lang/Throwable
}
