Compiled from "SimpleScriptField.java"
class io.manbang.ebatis.core.domain.SimpleScriptField implements io.manbang.ebatis.core.domain.ScriptField {
  private final java.lang.String name;

  private final io.manbang.ebatis.core.domain.Script script;

  private boolean ignoreFailure;

  io.manbang.ebatis.core.domain.SimpleScriptField(java.lang.String, io.manbang.ebatis.core.domain.Script);
    Code:
       0: aload_0
       1: invokespecial #1                  // Method java/lang/Object."<init>":()V
       4: aload_0
       5: aload_1
       6: putfield      #2                  // Field name:Ljava/lang/String;
       9: aload_0
      10: aload_2
      11: putfield      #3                  // Field script:Lio/manbang/ebatis/core/domain/Script;
      14: return

  public java.lang.String getName();
    Code:
       0: aload_0
       1: getfield      #2                  // Field name:Ljava/lang/String;
       4: areturn

  public io.manbang.ebatis.core.domain.Script getScript();
    Code:
       0: aload_0
       1: getfield      #3                  // Field script:Lio/manbang/ebatis/core/domain/Script;
       4: areturn

  public boolean isIgnoreFailure();
    Code:
       0: aload_0
       1: getfield      #4                  // Field ignoreFailure:Z
       4: ireturn

  public void setIgnoreFailure(boolean);
    Code:
       0: aload_0
       1: iload_1
       2: putfield      #4                  // Field ignoreFailure:Z
       5: return
}
