Compiled from "CallReferenceNumberImpl.java"
public class org.mobicents.protocols.ss7.map.service.callhandling.CallReferenceNumberImpl extends org.mobicents.protocols.ss7.map.primitives.OctetStringBase implements org.mobicents.protocols.ss7.map.api.service.callhandling.CallReferenceNumber {
  private static final java.lang.String DATA_XML;

  protected static final javolution.xml.XMLFormat<org.mobicents.protocols.ss7.map.service.callhandling.CallReferenceNumberImpl> CALL_REFERENCE_NUMBER_XML;

  public org.mobicents.protocols.ss7.map.service.callhandling.CallReferenceNumberImpl();
    Code:
       0: aload_0
       1: iconst_1
       2: bipush        8
       4: ldc           #2                  // String CallReferenceNumber
       6: invokespecial #3                  // Method org/mobicents/protocols/ss7/map/primitives/OctetStringBase."<init>":(IILjava/lang/String;)V
       9: return

  public org.mobicents.protocols.ss7.map.service.callhandling.CallReferenceNumberImpl(byte[]);
    Code:
       0: aload_0
       1: iconst_1
       2: bipush        8
       4: ldc           #2                  // String CallReferenceNumber
       6: aload_1
       7: invokespecial #4                  // Method org/mobicents/protocols/ss7/map/primitives/OctetStringBase."<init>":(IILjava/lang/String;[B)V
      10: return

  public byte[] getData();
    Code:
       0: aload_0
       1: getfield      #1                  // Field data:[B
       4: areturn

  static byte[] access$002(org.mobicents.protocols.ss7.map.service.callhandling.CallReferenceNumberImpl, byte[]);
    Code:
       0: aload_0
       1: aload_1
       2: dup_x1
       3: putfield      #1                  // Field data:[B
       6: areturn

  static byte[] access$100(org.mobicents.protocols.ss7.map.service.callhandling.CallReferenceNumberImpl);
    Code:
       0: aload_0
       1: getfield      #1                  // Field data:[B
       4: areturn

  static byte[] access$200(org.mobicents.protocols.ss7.map.service.callhandling.CallReferenceNumberImpl);
    Code:
       0: aload_0
       1: getfield      #1                  // Field data:[B
       4: areturn

  static byte[] access$300(org.mobicents.protocols.ss7.map.service.callhandling.CallReferenceNumberImpl);
    Code:
       0: aload_0
       1: getfield      #1                  // Field data:[B
       4: areturn

  static {};
    Code:
       0: new           #5                  // class org/mobicents/protocols/ss7/map/service/callhandling/CallReferenceNumberImpl$1
       3: dup
       4: ldc_w         #6                  // class org/mobicents/protocols/ss7/map/service/callhandling/CallReferenceNumberImpl
       7: invokespecial #7                  // Method org/mobicents/protocols/ss7/map/service/callhandling/CallReferenceNumberImpl$1."<init>":(Ljava/lang/Class;)V
      10: putstatic     #8                  // Field CALL_REFERENCE_NUMBER_XML:Ljavolution/xml/XMLFormat;
      13: return
}
