Compiled from "UsernameTokenAction.java"
public class org.apache.wss4j.dom.action.UsernameTokenAction implements org.apache.wss4j.dom.action.Action {
  public org.apache.wss4j.dom.action.UsernameTokenAction();
    Code:
       0: aload_0
       1: invokespecial #1                  // Method java/lang/Object."<init>":()V
       4: return

  public void execute(org.apache.wss4j.dom.handler.WSHandler, org.apache.wss4j.common.SecurityActionToken, org.w3c.dom.Document, org.apache.wss4j.dom.handler.RequestData) throws org.apache.wss4j.common.ext.WSSecurityException;
    Code:
       0: aload         4
       2: invokevirtual #2                  // Method org/apache/wss4j/dom/handler/RequestData.getUsername:()Ljava/lang/String;
       5: astore        5
       7: aconst_null
       8: astore        6
      10: aload         4
      12: invokevirtual #3                  // Method org/apache/wss4j/dom/handler/RequestData.getPwType:()Ljava/lang/String;
      15: ifnull        56
      18: aload_1
      19: aload         4
      21: invokevirtual #4                  // Method org/apache/wss4j/dom/handler/WSHandler.getPasswordCallbackHandler:(Lorg/apache/wss4j/dom/handler/RequestData;)Ljavax/security/auth/callback/CallbackHandler;
      24: astore        7
      26: aload_1
      27: aload         4
      29: invokevirtual #2                  // Method org/apache/wss4j/dom/handler/RequestData.getUsername:()Ljava/lang/String;
      32: iconst_1
      33: aload         7
      35: aload         4
      37: invokevirtual #5                  // Method org/apache/wss4j/dom/handler/WSHandler.getPasswordCB:(Ljava/lang/String;ILjavax/security/auth/callback/CallbackHandler;Lorg/apache/wss4j/dom/handler/RequestData;)Lorg/apache/wss4j/common/ext/WSPasswordCallback;
      40: astore        8
      42: aload         8
      44: invokevirtual #6                  // Method org/apache/wss4j/common/ext/WSPasswordCallback.getIdentifier:()Ljava/lang/String;
      47: astore        5
      49: aload         8
      51: invokevirtual #7                  // Method org/apache/wss4j/common/ext/WSPasswordCallback.getPassword:()Ljava/lang/String;
      54: astore        6
      56: aload         5
      58: ifnonnull     74
      61: new           #8                  // class org/apache/wss4j/common/ext/WSSecurityException
      64: dup
      65: getstatic     #9                  // Field org/apache/wss4j/common/ext/WSSecurityException$ErrorCode.FAILURE:Lorg/apache/wss4j/common/ext/WSSecurityException$ErrorCode;
      68: ldc           #10                 // String noUser
      70: invokespecial #11                 // Method org/apache/wss4j/common/ext/WSSecurityException."<init>":(Lorg/apache/wss4j/common/ext/WSSecurityException$ErrorCode;Ljava/lang/String;)V
      73: athrow
      74: new           #12                 // class org/apache/wss4j/dom/message/WSSecUsernameToken
      77: dup
      78: invokespecial #13                 // Method org/apache/wss4j/dom/message/WSSecUsernameToken."<init>":()V
      81: astore        7
      83: aload         7
      85: aload         4
      87: invokevirtual #14                 // Method org/apache/wss4j/dom/handler/RequestData.getWssConfig:()Lorg/apache/wss4j/dom/engine/WSSConfig;
      90: invokevirtual #15                 // Method org/apache/wss4j/dom/engine/WSSConfig.getIdAllocator:()Lorg/apache/wss4j/dom/WsuIdAllocator;
      93: invokevirtual #16                 // Method org/apache/wss4j/dom/message/WSSecUsernameToken.setIdAllocator:(Lorg/apache/wss4j/dom/WsuIdAllocator;)V
      96: aload         7
      98: aload         4
     100: invokevirtual #17                 // Method org/apache/wss4j/dom/handler/RequestData.isPrecisionInMilliSeconds:()Z
     103: invokevirtual #18                 // Method org/apache/wss4j/dom/message/WSSecUsernameToken.setPrecisionInMilliSeconds:(Z)V
     106: aload         7
     108: aload         4
     110: invokevirtual #14                 // Method org/apache/wss4j/dom/handler/RequestData.getWssConfig:()Lorg/apache/wss4j/dom/engine/WSSConfig;
     113: invokevirtual #19                 // Method org/apache/wss4j/dom/engine/WSSConfig.getCurrentTime:()Lorg/apache/wss4j/common/util/WSTimeSource;
     116: invokevirtual #20                 // Method org/apache/wss4j/dom/message/WSSecUsernameToken.setWsTimeSource:(Lorg/apache/wss4j/common/util/WSTimeSource;)V
     119: aload         7
     121: aload         4
     123: invokevirtual #3                  // Method org/apache/wss4j/dom/handler/RequestData.getPwType:()Ljava/lang/String;
     126: invokevirtual #21                 // Method org/apache/wss4j/dom/message/WSSecUsernameToken.setPasswordType:(Ljava/lang/String;)V
     129: aload         7
     131: aload         4
     133: invokevirtual #22                 // Method org/apache/wss4j/dom/handler/RequestData.isEncodePasswords:()Z
     136: invokevirtual #23                 // Method org/apache/wss4j/dom/message/WSSecUsernameToken.setPasswordsAreEncoded:(Z)V
     139: aload         7
     141: aload         5
     143: aload         6
     145: invokevirtual #24                 // Method org/apache/wss4j/dom/message/WSSecUsernameToken.setUserInfo:(Ljava/lang/String;Ljava/lang/String;)V
     148: aload         4
     150: invokevirtual #25                 // Method org/apache/wss4j/dom/handler/RequestData.isAddUsernameTokenNonce:()Z
     153: ifeq          161
     156: aload         7
     158: invokevirtual #26                 // Method org/apache/wss4j/dom/message/WSSecUsernameToken.addNonce:()V
     161: aload         4
     163: invokevirtual #27                 // Method org/apache/wss4j/dom/handler/RequestData.isAddUsernameTokenCreated:()Z
     166: ifeq          174
     169: aload         7
     171: invokevirtual #28                 // Method org/apache/wss4j/dom/message/WSSecUsernameToken.addCreated:()V
     174: aload         7
     176: aload_3
     177: aload         4
     179: invokevirtual #29                 // Method org/apache/wss4j/dom/handler/RequestData.getSecHeader:()Lorg/apache/wss4j/dom/message/WSSecHeader;
     182: invokevirtual #30                 // Method org/apache/wss4j/dom/message/WSSecUsernameToken.build:(Lorg/w3c/dom/Document;Lorg/apache/wss4j/dom/message/WSSecHeader;)Lorg/w3c/dom/Document;
     185: pop
     186: return
}
