Compiled from "PrefixMappingAssembler.java"
public class org.apache.jena.assembler.assemblers.PrefixMappingAssembler extends org.apache.jena.assembler.assemblers.AssemblerBase implements org.apache.jena.assembler.Assembler {
  public org.apache.jena.assembler.assemblers.PrefixMappingAssembler();
    Code:
       0: aload_0
       1: invokespecial #1                  // Method org/apache/jena/assembler/assemblers/AssemblerBase."<init>":()V
       4: return

  public java.lang.Object open(org.apache.jena.assembler.Assembler, org.apache.jena.rdf.model.Resource, org.apache.jena.assembler.Mode);
    Code:
       0: aload_0
       1: aload_2
       2: getstatic     #2                  // Field org/apache/jena/assembler/JA.PrefixMapping:Lorg/apache/jena/rdf/model/Resource;
       5: invokevirtual #3                  // Method checkType:(Lorg/apache/jena/rdf/model/Resource;Lorg/apache/jena/rdf/model/Resource;)V
       8: aload_1
       9: aload_2
      10: invokestatic  #4                  // Method org/apache/jena/shared/PrefixMapping$Factory.create:()Lorg/apache/jena/shared/PrefixMapping;
      13: invokestatic  #5                  // Method getPrefixes:(Lorg/apache/jena/assembler/Assembler;Lorg/apache/jena/rdf/model/Resource;Lorg/apache/jena/shared/PrefixMapping;)Lorg/apache/jena/shared/PrefixMapping;
      16: areturn

  public static org.apache.jena.shared.PrefixMapping getPrefixes(org.apache.jena.assembler.Assembler, org.apache.jena.rdf.model.Resource, org.apache.jena.shared.PrefixMapping);
    Code:
       0: aload_1
       1: aload_2
       2: invokestatic  #6                  // Method setSimplePrefixes:(Lorg/apache/jena/rdf/model/Resource;Lorg/apache/jena/shared/PrefixMapping;)V
       5: aload_0
       6: aload_1
       7: aload_2
       8: getstatic     #7                  // Field org/apache/jena/assembler/JA.includes:Lorg/apache/jena/rdf/model/Property;
      11: invokestatic  #8                  // Method includePrefixesFor:(Lorg/apache/jena/assembler/Assembler;Lorg/apache/jena/rdf/model/Resource;Lorg/apache/jena/shared/PrefixMapping;Lorg/apache/jena/rdf/model/Property;)V
      14: aload_0
      15: aload_1
      16: aload_2
      17: getstatic     #9                  // Field org/apache/jena/assembler/JA.prefixMapping:Lorg/apache/jena/rdf/model/Property;
      20: invokestatic  #8                  // Method includePrefixesFor:(Lorg/apache/jena/assembler/Assembler;Lorg/apache/jena/rdf/model/Resource;Lorg/apache/jena/shared/PrefixMapping;Lorg/apache/jena/rdf/model/Property;)V
      23: aload_2
      24: areturn

  private static void includePrefixesFor(org.apache.jena.assembler.Assembler, org.apache.jena.rdf.model.Resource, org.apache.jena.shared.PrefixMapping, org.apache.jena.rdf.model.Property);
    Code:
       0: aload_1
       1: aload_3
       2: invokeinterface #10,  2           // InterfaceMethod org/apache/jena/rdf/model/Resource.listProperties:(Lorg/apache/jena/rdf/model/Property;)Lorg/apache/jena/rdf/model/StmtIterator;
       7: astore        4
       9: aload         4
      11: invokeinterface #11,  1           // InterfaceMethod org/apache/jena/rdf/model/StmtIterator.hasNext:()Z
      16: ifeq          56
      19: aload         4
      21: invokeinterface #12,  1           // InterfaceMethod org/apache/jena/rdf/model/StmtIterator.nextStatement:()Lorg/apache/jena/rdf/model/Statement;
      26: astore        5
      28: aload_0
      29: aload         5
      31: invokestatic  #13                 // Method getResource:(Lorg/apache/jena/rdf/model/Statement;)Lorg/apache/jena/rdf/model/Resource;
      34: invokeinterface #14,  2           // InterfaceMethod org/apache/jena/assembler/Assembler.open:(Lorg/apache/jena/rdf/model/Resource;)Ljava/lang/Object;
      39: checkcast     #15                 // class org/apache/jena/shared/PrefixMapping
      42: astore        6
      44: aload_2
      45: aload         6
      47: invokeinterface #16,  2           // InterfaceMethod org/apache/jena/shared/PrefixMapping.setNsPrefixes:(Lorg/apache/jena/shared/PrefixMapping;)Lorg/apache/jena/shared/PrefixMapping;
      52: pop
      53: goto          9
      56: return

  private static void setSimplePrefixes(org.apache.jena.rdf.model.Resource, org.apache.jena.shared.PrefixMapping);
    Code:
       0: aload_0
       1: getstatic     #17                 // Field org/apache/jena/assembler/JA.prefix:Lorg/apache/jena/rdf/model/Property;
       4: invokeinterface #18,  2           // InterfaceMethod org/apache/jena/rdf/model/Resource.hasProperty:(Lorg/apache/jena/rdf/model/Property;)Z
       9: ifeq          47
      12: aload_0
      13: getstatic     #17                 // Field org/apache/jena/assembler/JA.prefix:Lorg/apache/jena/rdf/model/Property;
      16: invokestatic  #19                 // Method getUniqueLiteral:(Lorg/apache/jena/rdf/model/Resource;Lorg/apache/jena/rdf/model/Property;)Lorg/apache/jena/rdf/model/Literal;
      19: astore_2
      20: aload_0
      21: getstatic     #20                 // Field org/apache/jena/assembler/JA.namespace:Lorg/apache/jena/rdf/model/Property;
      24: invokestatic  #19                 // Method getUniqueLiteral:(Lorg/apache/jena/rdf/model/Resource;Lorg/apache/jena/rdf/model/Property;)Lorg/apache/jena/rdf/model/Literal;
      27: astore_3
      28: aload_1
      29: aload_2
      30: invokeinterface #21,  1           // InterfaceMethod org/apache/jena/rdf/model/Literal.getLexicalForm:()Ljava/lang/String;
      35: aload_3
      36: invokeinterface #21,  1           // InterfaceMethod org/apache/jena/rdf/model/Literal.getLexicalForm:()Ljava/lang/String;
      41: invokeinterface #22,  3           // InterfaceMethod org/apache/jena/shared/PrefixMapping.setNsPrefix:(Ljava/lang/String;Ljava/lang/String;)Lorg/apache/jena/shared/PrefixMapping;
      46: pop
      47: return
}
