Compiled from "BagImpl.java"
public class org.apache.jena.rdf.model.impl.BagImpl extends org.apache.jena.rdf.model.impl.ContainerImpl implements org.apache.jena.rdf.model.Bag {
  public static final org.apache.jena.enhanced.Implementation factory;

  public org.apache.jena.rdf.model.impl.BagImpl(org.apache.jena.rdf.model.impl.ModelCom);
    Code:
       0: aload_0
       1: aload_1
       2: invokespecial #1                  // Method org/apache/jena/rdf/model/impl/ContainerImpl."<init>":(Lorg/apache/jena/rdf/model/impl/ModelCom;)V
       5: return

  public org.apache.jena.rdf.model.impl.BagImpl(java.lang.String, org.apache.jena.rdf.model.impl.ModelCom);
    Code:
       0: aload_0
       1: aload_1
       2: aload_2
       3: invokespecial #2                  // Method org/apache/jena/rdf/model/impl/ContainerImpl."<init>":(Ljava/lang/String;Lorg/apache/jena/rdf/model/impl/ModelCom;)V
       6: return

  public org.apache.jena.rdf.model.impl.BagImpl(org.apache.jena.rdf.model.Resource, org.apache.jena.rdf.model.impl.ModelCom);
    Code:
       0: aload_0
       1: aload_1
       2: aload_2
       3: invokespecial #3                  // Method org/apache/jena/rdf/model/impl/ContainerImpl."<init>":(Lorg/apache/jena/rdf/model/Resource;Lorg/apache/jena/rdf/model/impl/ModelCom;)V
       6: return

  public org.apache.jena.rdf.model.impl.BagImpl(org.apache.jena.graph.Node, org.apache.jena.enhanced.EnhGraph);
    Code:
       0: aload_0
       1: aload_1
       2: aload_2
       3: invokespecial #4                  // Method org/apache/jena/rdf/model/impl/ContainerImpl."<init>":(Lorg/apache/jena/graph/Node;Lorg/apache/jena/enhanced/EnhGraph;)V
       6: return

  static {};
    Code:
       0: new           #5                  // class org/apache/jena/rdf/model/impl/BagImpl$1
       3: dup
       4: invokespecial #6                  // Method org/apache/jena/rdf/model/impl/BagImpl$1."<init>":()V
       7: putstatic     #7                  // Field factory:Lorg/apache/jena/enhanced/Implementation;
      10: return
}
