Compiled from "LiteralImpl.java"
public class org.apache.jena.rdf.model.impl.LiteralImpl extends org.apache.jena.enhanced.EnhNode implements org.apache.jena.rdf.model.Literal {
  public static final org.apache.jena.enhanced.Implementation factory;

  public org.apache.jena.rdf.model.impl.LiteralImpl(org.apache.jena.graph.Node, org.apache.jena.rdf.model.impl.ModelCom);
    Code:
       0: aload_0
       1: aload_1
       2: aload_2
       3: invokespecial #1                  // Method org/apache/jena/enhanced/EnhNode."<init>":(Lorg/apache/jena/graph/Node;Lorg/apache/jena/enhanced/EnhGraph;)V
       6: return

  public org.apache.jena.rdf.model.impl.LiteralImpl(org.apache.jena.graph.Node, org.apache.jena.enhanced.EnhGraph);
    Code:
       0: aload_0
       1: aload_1
       2: aload_2
       3: invokespecial #1                  // Method org/apache/jena/enhanced/EnhNode."<init>":(Lorg/apache/jena/graph/Node;Lorg/apache/jena/enhanced/EnhGraph;)V
       6: return

  public java.lang.Object visitWith(org.apache.jena.rdf.model.RDFVisitor);
    Code:
       0: aload_1
       1: aload_0
       2: invokeinterface #2,  2            // InterfaceMethod org/apache/jena/rdf/model/RDFVisitor.visitLiteral:(Lorg/apache/jena/rdf/model/Literal;)Ljava/lang/Object;
       7: areturn

  public org.apache.jena.rdf.model.Literal inModel(org.apache.jena.rdf.model.Model);
    Code:
       0: aload_0
       1: invokevirtual #3                  // Method getModel:()Lorg/apache/jena/rdf/model/Model;
       4: aload_1
       5: if_acmpne     12
       8: aload_0
       9: goto          25
      12: aload_1
      13: aload_0
      14: invokevirtual #4                  // Method asNode:()Lorg/apache/jena/graph/Node;
      17: invokeinterface #5,  2            // InterfaceMethod org/apache/jena/rdf/model/Model.getRDFNode:(Lorg/apache/jena/graph/Node;)Lorg/apache/jena/rdf/model/RDFNode;
      22: checkcast     #6                  // class org/apache/jena/rdf/model/Literal
      25: areturn

  public org.apache.jena.rdf.model.Literal asLiteral();
    Code:
       0: aload_0
       1: areturn

  public org.apache.jena.rdf.model.Resource asResource();
    Code:
       0: new           #7                  // class org/apache/jena/rdf/model/ResourceRequiredException
       3: dup
       4: aload_0
       5: invokevirtual #4                  // Method asNode:()Lorg/apache/jena/graph/Node;
       8: invokespecial #8                  // Method org/apache/jena/rdf/model/ResourceRequiredException."<init>":(Lorg/apache/jena/graph/Node;)V
      11: athrow

  public org.apache.jena.rdf.model.Model getModel();
    Code:
       0: aload_0
       1: invokevirtual #9                  // Method getGraph:()Lorg/apache/jena/enhanced/EnhGraph;
       4: checkcast     #10                 // class org/apache/jena/rdf/model/impl/ModelCom
       7: areturn

  public java.lang.String toString();
    Code:
       0: aload_0
       1: invokevirtual #4                  // Method asNode:()Lorg/apache/jena/graph/Node;
       4: getstatic     #11                 // Field org/apache/jena/shared/PrefixMapping.Standard:Lorg/apache/jena/shared/PrefixMapping;
       7: iconst_0
       8: invokevirtual #12                 // Method org/apache/jena/graph/Node.toString:(Lorg/apache/jena/shared/PrefixMapping;Z)Ljava/lang/String;
      11: areturn

  public java.lang.Object getValue();
    Code:
       0: aload_0
       1: invokevirtual #4                  // Method asNode:()Lorg/apache/jena/graph/Node;
       4: invokevirtual #13                 // Method org/apache/jena/graph/Node.getLiteralValue:()Ljava/lang/Object;
       7: areturn

  public org.apache.jena.datatypes.RDFDatatype getDatatype();
    Code:
       0: aload_0
       1: invokevirtual #4                  // Method asNode:()Lorg/apache/jena/graph/Node;
       4: invokevirtual #14                 // Method org/apache/jena/graph/Node.getLiteralDatatype:()Lorg/apache/jena/datatypes/RDFDatatype;
       7: areturn

  public java.lang.String getDatatypeURI();
    Code:
       0: aload_0
       1: invokevirtual #4                  // Method asNode:()Lorg/apache/jena/graph/Node;
       4: invokevirtual #15                 // Method org/apache/jena/graph/Node.getLiteralDatatypeURI:()Ljava/lang/String;
       7: areturn

  private boolean isPlainLiteral();
    Code:
       0: getstatic     #16                 // Field org/apache/jena/JenaRuntime.isRDF11:Z
       3: ifeq          26
       6: aload_0
       7: invokestatic  #17                 // Method org/apache/jena/rdf/model/impl/Util.isLangString:(Lorg/apache/jena/rdf/model/Literal;)Z
      10: ifne          20
      13: aload_0
      14: invokestatic  #18                 // Method org/apache/jena/rdf/model/impl/Util.isSimpleString:(Lorg/apache/jena/rdf/model/Literal;)Z
      17: ifeq          24
      20: iconst_1
      21: goto          25
      24: iconst_0
      25: ireturn
      26: aload_0
      27: invokevirtual #4                  // Method asNode:()Lorg/apache/jena/graph/Node;
      30: invokevirtual #14                 // Method org/apache/jena/graph/Node.getLiteralDatatype:()Lorg/apache/jena/datatypes/RDFDatatype;
      33: ifnonnull     40
      36: iconst_1
      37: goto          41
      40: iconst_0
      41: ireturn

  public java.lang.String getLexicalForm();
    Code:
       0: aload_0
       1: invokevirtual #4                  // Method asNode:()Lorg/apache/jena/graph/Node;
       4: invokevirtual #19                 // Method org/apache/jena/graph/Node.getLiteralLexicalForm:()Ljava/lang/String;
       7: areturn

  public boolean getBoolean();
    Code:
       0: aload_0
       1: invokevirtual #4                  // Method asNode:()Lorg/apache/jena/graph/Node;
       4: invokevirtual #13                 // Method org/apache/jena/graph/Node.getLiteralValue:()Ljava/lang/Object;
       7: astore_1
       8: aload_0
       9: invokespecial #20                 // Method isPlainLiteral:()Z
      12: ifeq          49
      15: aload_1
      16: ldc           #21                 // String true
      18: invokevirtual #22                 // Method java/lang/Object.equals:(Ljava/lang/Object;)Z
      21: ifeq          26
      24: iconst_1
      25: ireturn
      26: aload_1
      27: ldc           #23                 // String false
      29: invokevirtual #22                 // Method java/lang/Object.equals:(Ljava/lang/Object;)Z
      32: ifeq          37
      35: iconst_0
      36: ireturn
      37: new           #24                 // class org/apache/jena/shared/BadBooleanException
      40: dup
      41: aload_1
      42: invokevirtual #25                 // Method java/lang/Object.toString:()Ljava/lang/String;
      45: invokespecial #26                 // Method org/apache/jena/shared/BadBooleanException."<init>":(Ljava/lang/String;)V
      48: athrow
      49: aload_1
      50: instanceof    #27                 // class java/lang/Boolean
      53: ifeq          64
      56: aload_1
      57: checkcast     #27                 // class java/lang/Boolean
      60: invokevirtual #28                 // Method java/lang/Boolean.booleanValue:()Z
      63: ireturn
      64: new           #29                 // class org/apache/jena/datatypes/DatatypeFormatException
      67: dup
      68: new           #30                 // class java/lang/StringBuilder
      71: dup
      72: invokespecial #31                 // Method java/lang/StringBuilder."<init>":()V
      75: aload_0
      76: invokevirtual #32                 // Method toString:()Ljava/lang/String;
      79: invokevirtual #33                 // Method java/lang/StringBuilder.append:(Ljava/lang/String;)Ljava/lang/StringBuilder;
      82: ldc           #34                 // String  is not a Boolean
      84: invokevirtual #33                 // Method java/lang/StringBuilder.append:(Ljava/lang/String;)Ljava/lang/StringBuilder;
      87: invokevirtual #35                 // Method java/lang/StringBuilder.toString:()Ljava/lang/String;
      90: invokespecial #36                 // Method org/apache/jena/datatypes/DatatypeFormatException."<init>":(Ljava/lang/String;)V
      93: athrow

  public byte getByte();
    Code:
       0: aload_0
       1: invokespecial #20                 // Method isPlainLiteral:()Z
       4: ifeq          15
       7: aload_0
       8: invokevirtual #37                 // Method getLexicalForm:()Ljava/lang/String;
      11: invokestatic  #38                 // Method java/lang/Byte.parseByte:(Ljava/lang/String;)B
      14: ireturn
      15: aload_0
      16: aload_0
      17: aload_0
      18: invokevirtual #39                 // Method getValue:()Ljava/lang/Object;
      21: invokespecial #40                 // Method asNumber:(Ljava/lang/Object;)Ljava/lang/Number;
      24: invokespecial #41                 // Method byteValue:(Ljava/lang/Number;)B
      27: ireturn

  public short getShort();
    Code:
       0: aload_0
       1: invokespecial #20                 // Method isPlainLiteral:()Z
       4: ifeq          15
       7: aload_0
       8: invokevirtual #37                 // Method getLexicalForm:()Ljava/lang/String;
      11: invokestatic  #42                 // Method java/lang/Short.parseShort:(Ljava/lang/String;)S
      14: ireturn
      15: aload_0
      16: aload_0
      17: aload_0
      18: invokevirtual #39                 // Method getValue:()Ljava/lang/Object;
      21: invokespecial #40                 // Method asNumber:(Ljava/lang/Object;)Ljava/lang/Number;
      24: invokespecial #43                 // Method shortValue:(Ljava/lang/Number;)S
      27: ireturn

  public int getInt();
    Code:
       0: aload_0
       1: invokespecial #20                 // Method isPlainLiteral:()Z
       4: ifeq          15
       7: aload_0
       8: invokevirtual #37                 // Method getLexicalForm:()Ljava/lang/String;
      11: invokestatic  #44                 // Method java/lang/Integer.parseInt:(Ljava/lang/String;)I
      14: ireturn
      15: aload_0
      16: aload_0
      17: aload_0
      18: invokevirtual #39                 // Method getValue:()Ljava/lang/Object;
      21: invokespecial #40                 // Method asNumber:(Ljava/lang/Object;)Ljava/lang/Number;
      24: invokespecial #45                 // Method intValue:(Ljava/lang/Number;)I
      27: ireturn

  public long getLong();
    Code:
       0: aload_0
       1: invokespecial #20                 // Method isPlainLiteral:()Z
       4: ifeq          15
       7: aload_0
       8: invokevirtual #37                 // Method getLexicalForm:()Ljava/lang/String;
      11: invokestatic  #46                 // Method java/lang/Long.parseLong:(Ljava/lang/String;)J
      14: lreturn
      15: aload_0
      16: aload_0
      17: invokevirtual #39                 // Method getValue:()Ljava/lang/Object;
      20: invokespecial #40                 // Method asNumber:(Ljava/lang/Object;)Ljava/lang/Number;
      23: invokevirtual #47                 // Method java/lang/Number.longValue:()J
      26: lreturn

  public char getChar();
    Code:
       0: aload_0
       1: invokespecial #20                 // Method isPlainLiteral:()Z
       4: ifeq          39
       7: aload_0
       8: invokevirtual #48                 // Method getString:()Ljava/lang/String;
      11: invokevirtual #49                 // Method java/lang/String.length:()I
      14: iconst_1
      15: if_icmpne     27
      18: aload_0
      19: invokevirtual #48                 // Method getString:()Ljava/lang/String;
      22: iconst_0
      23: invokevirtual #50                 // Method java/lang/String.charAt:(I)C
      26: ireturn
      27: new           #51                 // class org/apache/jena/shared/BadCharLiteralException
      30: dup
      31: aload_0
      32: invokevirtual #48                 // Method getString:()Ljava/lang/String;
      35: invokespecial #52                 // Method org/apache/jena/shared/BadCharLiteralException."<init>":(Ljava/lang/String;)V
      38: athrow
      39: aload_0
      40: invokevirtual #39                 // Method getValue:()Ljava/lang/Object;
      43: astore_1
      44: aload_1
      45: instanceof    #53                 // class java/lang/Character
      48: ifeq          59
      51: aload_1
      52: checkcast     #53                 // class java/lang/Character
      55: invokevirtual #54                 // Method java/lang/Character.charValue:()C
      58: ireturn
      59: new           #29                 // class org/apache/jena/datatypes/DatatypeFormatException
      62: dup
      63: new           #30                 // class java/lang/StringBuilder
      66: dup
      67: invokespecial #31                 // Method java/lang/StringBuilder."<init>":()V
      70: aload_1
      71: invokevirtual #25                 // Method java/lang/Object.toString:()Ljava/lang/String;
      74: invokevirtual #33                 // Method java/lang/StringBuilder.append:(Ljava/lang/String;)Ljava/lang/StringBuilder;
      77: ldc           #55                 // String  is not a Character
      79: invokevirtual #33                 // Method java/lang/StringBuilder.append:(Ljava/lang/String;)Ljava/lang/StringBuilder;
      82: invokevirtual #35                 // Method java/lang/StringBuilder.toString:()Ljava/lang/String;
      85: invokespecial #36                 // Method org/apache/jena/datatypes/DatatypeFormatException."<init>":(Ljava/lang/String;)V
      88: athrow

  public float getFloat();
    Code:
       0: aload_0
       1: invokespecial #20                 // Method isPlainLiteral:()Z
       4: ifeq          15
       7: aload_0
       8: invokevirtual #37                 // Method getLexicalForm:()Ljava/lang/String;
      11: invokestatic  #56                 // Method java/lang/Float.parseFloat:(Ljava/lang/String;)F
      14: freturn
      15: aload_0
      16: aload_0
      17: invokevirtual #39                 // Method getValue:()Ljava/lang/Object;
      20: invokespecial #40                 // Method asNumber:(Ljava/lang/Object;)Ljava/lang/Number;
      23: invokevirtual #57                 // Method java/lang/Number.floatValue:()F
      26: freturn

  public double getDouble();
    Code:
       0: aload_0
       1: invokespecial #20                 // Method isPlainLiteral:()Z
       4: ifeq          15
       7: aload_0
       8: invokevirtual #37                 // Method getLexicalForm:()Ljava/lang/String;
      11: invokestatic  #58                 // Method java/lang/Double.parseDouble:(Ljava/lang/String;)D
      14: dreturn
      15: aload_0
      16: aload_0
      17: invokevirtual #39                 // Method getValue:()Ljava/lang/Object;
      20: invokespecial #40                 // Method asNumber:(Ljava/lang/Object;)Ljava/lang/Number;
      23: invokevirtual #59                 // Method java/lang/Number.doubleValue:()D
      26: dreturn

  public java.lang.String getString();
    Code:
       0: aload_0
       1: invokevirtual #4                  // Method asNode:()Lorg/apache/jena/graph/Node;
       4: invokevirtual #19                 // Method org/apache/jena/graph/Node.getLiteralLexicalForm:()Ljava/lang/String;
       7: areturn

  public java.lang.String getLanguage();
    Code:
       0: aload_0
       1: invokevirtual #4                  // Method asNode:()Lorg/apache/jena/graph/Node;
       4: invokevirtual #60                 // Method org/apache/jena/graph/Node.getLiteralLanguage:()Ljava/lang/String;
       7: areturn

  public boolean isWellFormedXML();
    Code:
       0: aload_0
       1: invokevirtual #4                  // Method asNode:()Lorg/apache/jena/graph/Node;
       4: invokevirtual #61                 // Method org/apache/jena/graph/Node.getLiteralIsXML:()Z
       7: ireturn

  public boolean sameValueAs(org.apache.jena.rdf.model.Literal);
    Code:
       0: aload_0
       1: invokevirtual #4                  // Method asNode:()Lorg/apache/jena/graph/Node;
       4: aload_1
       5: invokeinterface #62,  1           // InterfaceMethod org/apache/jena/rdf/model/Literal.asNode:()Lorg/apache/jena/graph/Node;
      10: invokevirtual #63                 // Method org/apache/jena/graph/Node.sameValueAs:(Ljava/lang/Object;)Z
      13: ireturn

  private java.lang.Number asNumber(java.lang.Object);
    Code:
       0: aload_1
       1: instanceof    #64                 // class java/lang/Number
       4: ifeq          12
       7: aload_1
       8: checkcast     #64                 // class java/lang/Number
      11: areturn
      12: ldc           #65                 // String Error converting typed value to a number. \n
      14: astore_2
      15: new           #30                 // class java/lang/StringBuilder
      18: dup
      19: invokespecial #31                 // Method java/lang/StringBuilder."<init>":()V
      22: aload_2
      23: invokevirtual #33                 // Method java/lang/StringBuilder.append:(Ljava/lang/String;)Ljava/lang/StringBuilder;
      26: ldc           #66                 // String Datatype is:
      28: invokevirtual #33                 // Method java/lang/StringBuilder.append:(Ljava/lang/String;)Ljava/lang/StringBuilder;
      31: aload_0
      32: invokevirtual #67                 // Method getDatatypeURI:()Ljava/lang/String;
      35: invokevirtual #33                 // Method java/lang/StringBuilder.append:(Ljava/lang/String;)Ljava/lang/StringBuilder;
      38: invokevirtual #35                 // Method java/lang/StringBuilder.toString:()Ljava/lang/String;
      41: astore_2
      42: aload_0
      43: invokevirtual #67                 // Method getDatatypeURI:()Ljava/lang/String;
      46: ifnull        61
      49: aload_0
      50: invokevirtual #67                 // Method getDatatypeURI:()Ljava/lang/String;
      53: ldc           #69                 // String http://www.w3.org/2001/XMLSchema
      55: invokevirtual #70                 // Method java/lang/String.startsWith:(Ljava/lang/String;)Z
      58: ifne          81
      61: new           #30                 // class java/lang/StringBuilder
      64: dup
      65: invokespecial #31                 // Method java/lang/StringBuilder."<init>":()V
      68: aload_2
      69: invokevirtual #33                 // Method java/lang/StringBuilder.append:(Ljava/lang/String;)Ljava/lang/StringBuilder;
      72: ldc           #71                 // String  which is not an xsd type.
      74: invokevirtual #33                 // Method java/lang/StringBuilder.append:(Ljava/lang/String;)Ljava/lang/StringBuilder;
      77: invokevirtual #35                 // Method java/lang/StringBuilder.toString:()Ljava/lang/String;
      80: astore_2
      81: new           #30                 // class java/lang/StringBuilder
      84: dup
      85: invokespecial #31                 // Method java/lang/StringBuilder."<init>":()V
      88: aload_2
      89: invokevirtual #33                 // Method java/lang/StringBuilder.append:(Ljava/lang/String;)Ljava/lang/StringBuilder;
      92: ldc           #72                 // String  \n
      94: invokevirtual #33                 // Method java/lang/StringBuilder.append:(Ljava/lang/String;)Ljava/lang/StringBuilder;
      97: invokevirtual #35                 // Method java/lang/StringBuilder.toString:()Ljava/lang/String;
     100: astore_2
     101: new           #30                 // class java/lang/StringBuilder
     104: dup
     105: invokespecial #31                 // Method java/lang/StringBuilder."<init>":()V
     108: aload_2
     109: invokevirtual #33                 // Method java/lang/StringBuilder.append:(Ljava/lang/String;)Ljava/lang/StringBuilder;
     112: ldc           #73                 // String Java representation type is
     114: invokevirtual #33                 // Method java/lang/StringBuilder.append:(Ljava/lang/String;)Ljava/lang/StringBuilder;
     117: aload_1
     118: ifnonnull     126
     121: ldc           #74                 // String null
     123: goto          133
     126: aload_1
     127: invokevirtual #75                 // Method java/lang/Object.getClass:()Ljava/lang/Class;
     130: invokevirtual #76                 // Method java/lang/Class.toString:()Ljava/lang/String;
     133: invokevirtual #33                 // Method java/lang/StringBuilder.append:(Ljava/lang/String;)Ljava/lang/StringBuilder;
     136: invokevirtual #35                 // Method java/lang/StringBuilder.toString:()Ljava/lang/String;
     139: dup
     140: astore_2
     141: astore_3
     142: new           #29                 // class org/apache/jena/datatypes/DatatypeFormatException
     145: dup
     146: aload_2
     147: invokespecial #36                 // Method org/apache/jena/datatypes/DatatypeFormatException."<init>":(Ljava/lang/String;)V
     150: athrow

  private byte byteValue(java.lang.Number);
    Code:
       0: aload_0
       1: ldc2_w        #78                 // long -128l
       4: aload_1
       5: ldc2_w        #80                 // long 127l
       8: invokespecial #82                 // Method getIntegralValueInRange:(JLjava/lang/Number;J)J
      11: l2i
      12: i2b
      13: ireturn

  private short shortValue(java.lang.Number);
    Code:
       0: aload_0
       1: ldc2_w        #84                 // long -32768l
       4: aload_1
       5: ldc2_w        #86                 // long 32767l
       8: invokespecial #82                 // Method getIntegralValueInRange:(JLjava/lang/Number;J)J
      11: l2i
      12: i2s
      13: ireturn

  private int intValue(java.lang.Number);
    Code:
       0: aload_0
       1: ldc2_w        #89                 // long -2147483648l
       4: aload_1
       5: ldc2_w        #91                 // long 2147483647l
       8: invokespecial #82                 // Method getIntegralValueInRange:(JLjava/lang/Number;J)J
      11: l2i
      12: ireturn

  private long getIntegralValueInRange(long, java.lang.Number, long);
    Code:
       0: aload_3
       1: invokevirtual #47                 // Method java/lang/Number.longValue:()J
       4: lstore        6
       6: lload_1
       7: lload         6
       9: lcmp
      10: ifgt          24
      13: lload         6
      15: lload         4
      17: lcmp
      18: ifgt          24
      21: lload         6
      23: lreturn
      24: new           #93                 // class java/lang/IllegalArgumentException
      27: dup
      28: new           #30                 // class java/lang/StringBuilder
      31: dup
      32: invokespecial #31                 // Method java/lang/StringBuilder."<init>":()V
      35: ldc           #94                 // String byte value required:
      37: invokevirtual #33                 // Method java/lang/StringBuilder.append:(Ljava/lang/String;)Ljava/lang/StringBuilder;
      40: lload         6
      42: invokevirtual #95                 // Method java/lang/StringBuilder.append:(J)Ljava/lang/StringBuilder;
      45: invokevirtual #35                 // Method java/lang/StringBuilder.toString:()Ljava/lang/String;
      48: invokespecial #96                 // Method java/lang/IllegalArgumentException."<init>":(Ljava/lang/String;)V
      51: athrow

  public org.apache.jena.rdf.model.RDFNode inModel(org.apache.jena.rdf.model.Model);
    Code:
       0: aload_0
       1: aload_1
       2: invokevirtual #97                 // Method inModel:(Lorg/apache/jena/rdf/model/Model;)Lorg/apache/jena/rdf/model/Literal;
       5: areturn

  static {};
    Code:
       0: new           #98                 // class org/apache/jena/rdf/model/impl/LiteralImpl$1
       3: dup
       4: invokespecial #99                 // Method org/apache/jena/rdf/model/impl/LiteralImpl$1."<init>":()V
       7: putstatic     #100                // Field factory:Lorg/apache/jena/enhanced/Implementation;
      10: return
}
