Compiled from "SeqImpl.java"
public class org.apache.jena.rdf.model.impl.SeqImpl extends org.apache.jena.rdf.model.impl.ContainerImpl implements org.apache.jena.rdf.model.Seq {
  public static final org.apache.jena.enhanced.Implementation factory;

  static org.apache.jena.rdf.model.impl.NodeIteratorFactory seqIteratorFactory;

  public org.apache.jena.rdf.model.impl.SeqImpl(org.apache.jena.rdf.model.impl.ModelCom);
    Code:
       0: aload_0
       1: aload_1
       2: invokespecial #1                  // Method org/apache/jena/rdf/model/impl/ContainerImpl."<init>":(Lorg/apache/jena/rdf/model/impl/ModelCom;)V
       5: return

  public org.apache.jena.rdf.model.impl.SeqImpl(java.lang.String, org.apache.jena.rdf.model.impl.ModelCom);
    Code:
       0: aload_0
       1: aload_1
       2: aload_2
       3: invokespecial #2                  // Method org/apache/jena/rdf/model/impl/ContainerImpl."<init>":(Ljava/lang/String;Lorg/apache/jena/rdf/model/impl/ModelCom;)V
       6: return

  public org.apache.jena.rdf.model.impl.SeqImpl(org.apache.jena.rdf.model.Resource, org.apache.jena.rdf.model.impl.ModelCom);
    Code:
       0: aload_0
       1: aload_1
       2: aload_2
       3: invokespecial #3                  // Method org/apache/jena/rdf/model/impl/ContainerImpl."<init>":(Lorg/apache/jena/rdf/model/Resource;Lorg/apache/jena/rdf/model/impl/ModelCom;)V
       6: return

  public org.apache.jena.rdf.model.impl.SeqImpl(org.apache.jena.graph.Node, org.apache.jena.enhanced.EnhGraph);
    Code:
       0: aload_0
       1: aload_1
       2: aload_2
       3: invokespecial #4                  // Method org/apache/jena/rdf/model/impl/ContainerImpl."<init>":(Lorg/apache/jena/graph/Node;Lorg/apache/jena/enhanced/EnhGraph;)V
       6: return

  public org.apache.jena.rdf.model.Resource getResource(int);
    Code:
       0: aload_0
       1: iload_1
       2: invokestatic  #5                  // Method org/apache/jena/vocabulary/RDF.li:(I)Lorg/apache/jena/rdf/model/Property;
       5: invokevirtual #6                  // Method getRequiredProperty:(Lorg/apache/jena/rdf/model/Property;)Lorg/apache/jena/rdf/model/Statement;
       8: invokeinterface #7,  1            // InterfaceMethod org/apache/jena/rdf/model/Statement.getResource:()Lorg/apache/jena/rdf/model/Resource;
      13: areturn

  public org.apache.jena.rdf.model.Literal getLiteral(int);
    Code:
       0: aload_0
       1: iload_1
       2: invokestatic  #5                  // Method org/apache/jena/vocabulary/RDF.li:(I)Lorg/apache/jena/rdf/model/Property;
       5: invokevirtual #6                  // Method getRequiredProperty:(Lorg/apache/jena/rdf/model/Property;)Lorg/apache/jena/rdf/model/Statement;
       8: invokeinterface #8,  1            // InterfaceMethod org/apache/jena/rdf/model/Statement.getLiteral:()Lorg/apache/jena/rdf/model/Literal;
      13: areturn

  public org.apache.jena.rdf.model.RDFNode getObject(int);
    Code:
       0: aload_0
       1: iload_1
       2: invokestatic  #5                  // Method org/apache/jena/vocabulary/RDF.li:(I)Lorg/apache/jena/rdf/model/Property;
       5: invokevirtual #6                  // Method getRequiredProperty:(Lorg/apache/jena/rdf/model/Property;)Lorg/apache/jena/rdf/model/Statement;
       8: invokeinterface #9,  1            // InterfaceMethod org/apache/jena/rdf/model/Statement.getObject:()Lorg/apache/jena/rdf/model/RDFNode;
      13: areturn

  public boolean getBoolean(int);
    Code:
       0: aload_0
       1: iload_1
       2: invokevirtual #10                 // Method checkIndex:(I)V
       5: aload_0
       6: iload_1
       7: invokestatic  #5                  // Method org/apache/jena/vocabulary/RDF.li:(I)Lorg/apache/jena/rdf/model/Property;
      10: invokevirtual #6                  // Method getRequiredProperty:(Lorg/apache/jena/rdf/model/Property;)Lorg/apache/jena/rdf/model/Statement;
      13: invokeinterface #11,  1           // InterfaceMethod org/apache/jena/rdf/model/Statement.getBoolean:()Z
      18: ireturn

  public byte getByte(int);
    Code:
       0: aload_0
       1: iload_1
       2: invokevirtual #10                 // Method checkIndex:(I)V
       5: aload_0
       6: iload_1
       7: invokestatic  #5                  // Method org/apache/jena/vocabulary/RDF.li:(I)Lorg/apache/jena/rdf/model/Property;
      10: invokevirtual #6                  // Method getRequiredProperty:(Lorg/apache/jena/rdf/model/Property;)Lorg/apache/jena/rdf/model/Statement;
      13: invokeinterface #12,  1           // InterfaceMethod org/apache/jena/rdf/model/Statement.getByte:()B
      18: ireturn

  public short getShort(int);
    Code:
       0: aload_0
       1: iload_1
       2: invokevirtual #10                 // Method checkIndex:(I)V
       5: aload_0
       6: iload_1
       7: invokestatic  #5                  // Method org/apache/jena/vocabulary/RDF.li:(I)Lorg/apache/jena/rdf/model/Property;
      10: invokevirtual #6                  // Method getRequiredProperty:(Lorg/apache/jena/rdf/model/Property;)Lorg/apache/jena/rdf/model/Statement;
      13: invokeinterface #13,  1           // InterfaceMethod org/apache/jena/rdf/model/Statement.getShort:()S
      18: ireturn

  public int getInt(int);
    Code:
       0: aload_0
       1: iload_1
       2: invokevirtual #10                 // Method checkIndex:(I)V
       5: aload_0
       6: iload_1
       7: invokestatic  #5                  // Method org/apache/jena/vocabulary/RDF.li:(I)Lorg/apache/jena/rdf/model/Property;
      10: invokevirtual #6                  // Method getRequiredProperty:(Lorg/apache/jena/rdf/model/Property;)Lorg/apache/jena/rdf/model/Statement;
      13: invokeinterface #14,  1           // InterfaceMethod org/apache/jena/rdf/model/Statement.getInt:()I
      18: ireturn

  public long getLong(int);
    Code:
       0: aload_0
       1: iload_1
       2: invokevirtual #10                 // Method checkIndex:(I)V
       5: aload_0
       6: iload_1
       7: invokestatic  #5                  // Method org/apache/jena/vocabulary/RDF.li:(I)Lorg/apache/jena/rdf/model/Property;
      10: invokevirtual #6                  // Method getRequiredProperty:(Lorg/apache/jena/rdf/model/Property;)Lorg/apache/jena/rdf/model/Statement;
      13: invokeinterface #15,  1           // InterfaceMethod org/apache/jena/rdf/model/Statement.getLong:()J
      18: lreturn

  public char getChar(int);
    Code:
       0: aload_0
       1: iload_1
       2: invokevirtual #10                 // Method checkIndex:(I)V
       5: aload_0
       6: iload_1
       7: invokestatic  #5                  // Method org/apache/jena/vocabulary/RDF.li:(I)Lorg/apache/jena/rdf/model/Property;
      10: invokevirtual #6                  // Method getRequiredProperty:(Lorg/apache/jena/rdf/model/Property;)Lorg/apache/jena/rdf/model/Statement;
      13: invokeinterface #16,  1           // InterfaceMethod org/apache/jena/rdf/model/Statement.getChar:()C
      18: ireturn

  public float getFloat(int);
    Code:
       0: aload_0
       1: iload_1
       2: invokevirtual #10                 // Method checkIndex:(I)V
       5: aload_0
       6: iload_1
       7: invokestatic  #5                  // Method org/apache/jena/vocabulary/RDF.li:(I)Lorg/apache/jena/rdf/model/Property;
      10: invokevirtual #6                  // Method getRequiredProperty:(Lorg/apache/jena/rdf/model/Property;)Lorg/apache/jena/rdf/model/Statement;
      13: invokeinterface #17,  1           // InterfaceMethod org/apache/jena/rdf/model/Statement.getFloat:()F
      18: freturn

  public double getDouble(int);
    Code:
       0: aload_0
       1: iload_1
       2: invokevirtual #10                 // Method checkIndex:(I)V
       5: aload_0
       6: iload_1
       7: invokestatic  #5                  // Method org/apache/jena/vocabulary/RDF.li:(I)Lorg/apache/jena/rdf/model/Property;
      10: invokevirtual #6                  // Method getRequiredProperty:(Lorg/apache/jena/rdf/model/Property;)Lorg/apache/jena/rdf/model/Statement;
      13: invokeinterface #18,  1           // InterfaceMethod org/apache/jena/rdf/model/Statement.getDouble:()D
      18: dreturn

  public java.lang.String getString(int);
    Code:
       0: aload_0
       1: iload_1
       2: invokevirtual #10                 // Method checkIndex:(I)V
       5: aload_0
       6: iload_1
       7: invokestatic  #5                  // Method org/apache/jena/vocabulary/RDF.li:(I)Lorg/apache/jena/rdf/model/Property;
      10: invokevirtual #6                  // Method getRequiredProperty:(Lorg/apache/jena/rdf/model/Property;)Lorg/apache/jena/rdf/model/Statement;
      13: invokeinterface #19,  1           // InterfaceMethod org/apache/jena/rdf/model/Statement.getString:()Ljava/lang/String;
      18: areturn

  public java.lang.String getLanguage(int);
    Code:
       0: aload_0
       1: iload_1
       2: invokevirtual #10                 // Method checkIndex:(I)V
       5: aload_0
       6: iload_1
       7: invokestatic  #5                  // Method org/apache/jena/vocabulary/RDF.li:(I)Lorg/apache/jena/rdf/model/Property;
      10: invokevirtual #6                  // Method getRequiredProperty:(Lorg/apache/jena/rdf/model/Property;)Lorg/apache/jena/rdf/model/Statement;
      13: invokeinterface #20,  1           // InterfaceMethod org/apache/jena/rdf/model/Statement.getLanguage:()Ljava/lang/String;
      18: areturn

  public org.apache.jena.rdf.model.Resource getResource(int, org.apache.jena.rdf.model.ResourceF);
    Code:
       0: aload_0
       1: iload_1
       2: invokestatic  #5                  // Method org/apache/jena/vocabulary/RDF.li:(I)Lorg/apache/jena/rdf/model/Property;
       5: invokevirtual #6                  // Method getRequiredProperty:(Lorg/apache/jena/rdf/model/Property;)Lorg/apache/jena/rdf/model/Statement;
       8: aload_2
       9: invokeinterface #21,  2           // InterfaceMethod org/apache/jena/rdf/model/Statement.getResource:(Lorg/apache/jena/rdf/model/ResourceF;)Lorg/apache/jena/rdf/model/Resource;
      14: areturn

  public org.apache.jena.rdf.model.Bag getBag(int);
    Code:
       0: aload_0
       1: iload_1
       2: invokevirtual #10                 // Method checkIndex:(I)V
       5: aload_0
       6: iload_1
       7: invokestatic  #5                  // Method org/apache/jena/vocabulary/RDF.li:(I)Lorg/apache/jena/rdf/model/Property;
      10: invokevirtual #6                  // Method getRequiredProperty:(Lorg/apache/jena/rdf/model/Property;)Lorg/apache/jena/rdf/model/Statement;
      13: invokeinterface #22,  1           // InterfaceMethod org/apache/jena/rdf/model/Statement.getBag:()Lorg/apache/jena/rdf/model/Bag;
      18: areturn

  public org.apache.jena.rdf.model.Alt getAlt(int);
    Code:
       0: aload_0
       1: iload_1
       2: invokevirtual #10                 // Method checkIndex:(I)V
       5: aload_0
       6: iload_1
       7: invokestatic  #5                  // Method org/apache/jena/vocabulary/RDF.li:(I)Lorg/apache/jena/rdf/model/Property;
      10: invokevirtual #6                  // Method getRequiredProperty:(Lorg/apache/jena/rdf/model/Property;)Lorg/apache/jena/rdf/model/Statement;
      13: invokeinterface #23,  1           // InterfaceMethod org/apache/jena/rdf/model/Statement.getAlt:()Lorg/apache/jena/rdf/model/Alt;
      18: areturn

  public org.apache.jena.rdf.model.Seq getSeq(int);
    Code:
       0: aload_0
       1: iload_1
       2: invokevirtual #10                 // Method checkIndex:(I)V
       5: aload_0
       6: iload_1
       7: invokestatic  #5                  // Method org/apache/jena/vocabulary/RDF.li:(I)Lorg/apache/jena/rdf/model/Property;
      10: invokevirtual #6                  // Method getRequiredProperty:(Lorg/apache/jena/rdf/model/Property;)Lorg/apache/jena/rdf/model/Statement;
      13: invokeinterface #24,  1           // InterfaceMethod org/apache/jena/rdf/model/Statement.getSeq:()Lorg/apache/jena/rdf/model/Seq;
      18: areturn

  public org.apache.jena.rdf.model.Seq set(int, org.apache.jena.rdf.model.RDFNode);
    Code:
       0: aload_0
       1: iload_1
       2: invokevirtual #10                 // Method checkIndex:(I)V
       5: aload_0
       6: iload_1
       7: invokestatic  #5                  // Method org/apache/jena/vocabulary/RDF.li:(I)Lorg/apache/jena/rdf/model/Property;
      10: invokevirtual #6                  // Method getRequiredProperty:(Lorg/apache/jena/rdf/model/Property;)Lorg/apache/jena/rdf/model/Statement;
      13: aload_2
      14: invokeinterface #25,  2           // InterfaceMethod org/apache/jena/rdf/model/Statement.changeObject:(Lorg/apache/jena/rdf/model/RDFNode;)Lorg/apache/jena/rdf/model/Statement;
      19: pop
      20: aload_0
      21: areturn

  public org.apache.jena.rdf.model.Seq set(int, boolean);
    Code:
       0: aload_0
       1: iload_1
       2: invokevirtual #10                 // Method checkIndex:(I)V
       5: aload_0
       6: iload_1
       7: invokestatic  #5                  // Method org/apache/jena/vocabulary/RDF.li:(I)Lorg/apache/jena/rdf/model/Property;
      10: invokevirtual #6                  // Method getRequiredProperty:(Lorg/apache/jena/rdf/model/Property;)Lorg/apache/jena/rdf/model/Statement;
      13: iload_2
      14: invokeinterface #26,  2           // InterfaceMethod org/apache/jena/rdf/model/Statement.changeLiteralObject:(Z)Lorg/apache/jena/rdf/model/Statement;
      19: pop
      20: aload_0
      21: areturn

  public org.apache.jena.rdf.model.Seq set(int, long);
    Code:
       0: aload_0
       1: iload_1
       2: invokevirtual #10                 // Method checkIndex:(I)V
       5: aload_0
       6: iload_1
       7: invokestatic  #5                  // Method org/apache/jena/vocabulary/RDF.li:(I)Lorg/apache/jena/rdf/model/Property;
      10: invokevirtual #6                  // Method getRequiredProperty:(Lorg/apache/jena/rdf/model/Property;)Lorg/apache/jena/rdf/model/Statement;
      13: lload_2
      14: invokeinterface #27,  3           // InterfaceMethod org/apache/jena/rdf/model/Statement.changeLiteralObject:(J)Lorg/apache/jena/rdf/model/Statement;
      19: pop
      20: aload_0
      21: areturn

  public org.apache.jena.rdf.model.Seq set(int, float);
    Code:
       0: aload_0
       1: iload_1
       2: invokevirtual #10                 // Method checkIndex:(I)V
       5: aload_0
       6: iload_1
       7: invokestatic  #5                  // Method org/apache/jena/vocabulary/RDF.li:(I)Lorg/apache/jena/rdf/model/Property;
      10: invokevirtual #6                  // Method getRequiredProperty:(Lorg/apache/jena/rdf/model/Property;)Lorg/apache/jena/rdf/model/Statement;
      13: fload_2
      14: invokeinterface #28,  2           // InterfaceMethod org/apache/jena/rdf/model/Statement.changeLiteralObject:(F)Lorg/apache/jena/rdf/model/Statement;
      19: pop
      20: aload_0
      21: areturn

  public org.apache.jena.rdf.model.Seq set(int, double);
    Code:
       0: aload_0
       1: iload_1
       2: invokevirtual #10                 // Method checkIndex:(I)V
       5: aload_0
       6: iload_1
       7: invokestatic  #5                  // Method org/apache/jena/vocabulary/RDF.li:(I)Lorg/apache/jena/rdf/model/Property;
      10: invokevirtual #6                  // Method getRequiredProperty:(Lorg/apache/jena/rdf/model/Property;)Lorg/apache/jena/rdf/model/Statement;
      13: dload_2
      14: invokeinterface #29,  3           // InterfaceMethod org/apache/jena/rdf/model/Statement.changeLiteralObject:(D)Lorg/apache/jena/rdf/model/Statement;
      19: pop
      20: aload_0
      21: areturn

  public org.apache.jena.rdf.model.Seq set(int, char);
    Code:
       0: aload_0
       1: iload_1
       2: invokevirtual #10                 // Method checkIndex:(I)V
       5: aload_0
       6: iload_1
       7: invokestatic  #5                  // Method org/apache/jena/vocabulary/RDF.li:(I)Lorg/apache/jena/rdf/model/Property;
      10: invokevirtual #6                  // Method getRequiredProperty:(Lorg/apache/jena/rdf/model/Property;)Lorg/apache/jena/rdf/model/Statement;
      13: iload_2
      14: invokeinterface #30,  2           // InterfaceMethod org/apache/jena/rdf/model/Statement.changeLiteralObject:(C)Lorg/apache/jena/rdf/model/Statement;
      19: pop
      20: aload_0
      21: areturn

  public org.apache.jena.rdf.model.Seq set(int, java.lang.String);
    Code:
       0: aload_0
       1: iload_1
       2: invokevirtual #10                 // Method checkIndex:(I)V
       5: aload_0
       6: iload_1
       7: invokestatic  #5                  // Method org/apache/jena/vocabulary/RDF.li:(I)Lorg/apache/jena/rdf/model/Property;
      10: invokevirtual #6                  // Method getRequiredProperty:(Lorg/apache/jena/rdf/model/Property;)Lorg/apache/jena/rdf/model/Statement;
      13: aload_2
      14: invokeinterface #31,  2           // InterfaceMethod org/apache/jena/rdf/model/Statement.changeObject:(Ljava/lang/String;)Lorg/apache/jena/rdf/model/Statement;
      19: pop
      20: aload_0
      21: areturn

  public org.apache.jena.rdf.model.Seq set(int, java.lang.String, java.lang.String);
    Code:
       0: aload_0
       1: iload_1
       2: invokevirtual #10                 // Method checkIndex:(I)V
       5: aload_0
       6: iload_1
       7: invokestatic  #5                  // Method org/apache/jena/vocabulary/RDF.li:(I)Lorg/apache/jena/rdf/model/Property;
      10: invokevirtual #6                  // Method getRequiredProperty:(Lorg/apache/jena/rdf/model/Property;)Lorg/apache/jena/rdf/model/Statement;
      13: aload_2
      14: aload_3
      15: invokeinterface #32,  3           // InterfaceMethod org/apache/jena/rdf/model/Statement.changeObject:(Ljava/lang/String;Ljava/lang/String;)Lorg/apache/jena/rdf/model/Statement;
      20: pop
      21: aload_0
      22: areturn

  public org.apache.jena.rdf.model.Seq set(int, java.lang.Object);
    Code:
       0: aload_0
       1: iload_1
       2: invokevirtual #10                 // Method checkIndex:(I)V
       5: aload_0
       6: iload_1
       7: invokestatic  #5                  // Method org/apache/jena/vocabulary/RDF.li:(I)Lorg/apache/jena/rdf/model/Property;
      10: invokevirtual #6                  // Method getRequiredProperty:(Lorg/apache/jena/rdf/model/Property;)Lorg/apache/jena/rdf/model/Statement;
      13: astore_3
      14: aload_3
      15: invokeinterface #33,  1           // InterfaceMethod org/apache/jena/rdf/model/Statement.getModel:()Lorg/apache/jena/rdf/model/Model;
      20: astore        4
      22: aload         4
      24: aload_3
      25: invokeinterface #34,  1           // InterfaceMethod org/apache/jena/rdf/model/Statement.getSubject:()Lorg/apache/jena/rdf/model/Resource;
      30: aload_3
      31: invokeinterface #35,  1           // InterfaceMethod org/apache/jena/rdf/model/Statement.getPredicate:()Lorg/apache/jena/rdf/model/Property;
      36: aload_2
      37: invokeinterface #36,  4           // InterfaceMethod org/apache/jena/rdf/model/Model.createLiteralStatement:(Lorg/apache/jena/rdf/model/Resource;Lorg/apache/jena/rdf/model/Property;Ljava/lang/Object;)Lorg/apache/jena/rdf/model/Statement;
      42: astore        5
      44: aload_3
      45: invokeinterface #33,  1           // InterfaceMethod org/apache/jena/rdf/model/Statement.getModel:()Lorg/apache/jena/rdf/model/Model;
      50: aload_3
      51: invokeinterface #37,  2           // InterfaceMethod org/apache/jena/rdf/model/Model.remove:(Lorg/apache/jena/rdf/model/Statement;)Lorg/apache/jena/rdf/model/Model;
      56: pop
      57: aload_3
      58: invokeinterface #33,  1           // InterfaceMethod org/apache/jena/rdf/model/Statement.getModel:()Lorg/apache/jena/rdf/model/Model;
      63: aload         5
      65: invokeinterface #38,  2           // InterfaceMethod org/apache/jena/rdf/model/Model.add:(Lorg/apache/jena/rdf/model/Statement;)Lorg/apache/jena/rdf/model/Model;
      70: pop
      71: aload_0
      72: areturn

  public org.apache.jena.rdf.model.Seq add(int, boolean);
    Code:
       0: aload_0
       1: iload_1
       2: iload_2
       3: invokestatic  #39                 // Method java/lang/String.valueOf:(Z)Ljava/lang/String;
       6: invokevirtual #40                 // Method add:(ILjava/lang/String;)Lorg/apache/jena/rdf/model/Seq;
       9: areturn

  public org.apache.jena.rdf.model.Seq add(int, long);
    Code:
       0: aload_0
       1: iload_1
       2: lload_2
       3: invokestatic  #41                 // Method java/lang/String.valueOf:(J)Ljava/lang/String;
       6: invokevirtual #40                 // Method add:(ILjava/lang/String;)Lorg/apache/jena/rdf/model/Seq;
       9: areturn

  public org.apache.jena.rdf.model.Seq add(int, char);
    Code:
       0: aload_0
       1: iload_1
       2: iload_2
       3: invokestatic  #42                 // Method java/lang/String.valueOf:(C)Ljava/lang/String;
       6: invokevirtual #40                 // Method add:(ILjava/lang/String;)Lorg/apache/jena/rdf/model/Seq;
       9: areturn

  public org.apache.jena.rdf.model.Seq add(int, float);
    Code:
       0: aload_0
       1: iload_1
       2: fload_2
       3: invokestatic  #43                 // Method java/lang/String.valueOf:(F)Ljava/lang/String;
       6: invokevirtual #40                 // Method add:(ILjava/lang/String;)Lorg/apache/jena/rdf/model/Seq;
       9: areturn

  public org.apache.jena.rdf.model.Seq add(int, double);
    Code:
       0: aload_0
       1: iload_1
       2: dload_2
       3: invokestatic  #44                 // Method java/lang/String.valueOf:(D)Ljava/lang/String;
       6: invokevirtual #40                 // Method add:(ILjava/lang/String;)Lorg/apache/jena/rdf/model/Seq;
       9: areturn

  public org.apache.jena.rdf.model.Seq add(int, java.lang.Object);
    Code:
       0: aload_0
       1: iload_1
       2: aload_2
       3: invokestatic  #45                 // Method java/lang/String.valueOf:(Ljava/lang/Object;)Ljava/lang/String;
       6: invokevirtual #40                 // Method add:(ILjava/lang/String;)Lorg/apache/jena/rdf/model/Seq;
       9: areturn

  public org.apache.jena.rdf.model.Seq add(int, java.lang.String);
    Code:
       0: aload_0
       1: iload_1
       2: aload_2
       3: ldc           #46                 // String
       5: invokevirtual #47                 // Method add:(ILjava/lang/String;Ljava/lang/String;)Lorg/apache/jena/rdf/model/Seq;
       8: areturn

  public org.apache.jena.rdf.model.Seq add(int, java.lang.String, java.lang.String);
    Code:
       0: aload_0
       1: iload_1
       2: aload_0
       3: aload_2
       4: aload_3
       5: invokespecial #48                 // Method literal:(Ljava/lang/String;Ljava/lang/String;)Lorg/apache/jena/rdf/model/Literal;
       8: invokevirtual #49                 // Method add:(ILorg/apache/jena/rdf/model/RDFNode;)Lorg/apache/jena/rdf/model/Seq;
      11: areturn

  public org.apache.jena.rdf.model.Seq add(int, org.apache.jena.rdf.model.RDFNode);
    Code:
       0: aload_0
       1: invokevirtual #50                 // Method size:()I
       4: istore_3
       5: aload_0
       6: iload_1
       7: iload_3
       8: iconst_1
       9: iadd
      10: invokevirtual #51                 // Method checkIndex:(II)V
      13: aload_0
      14: iload_1
      15: iload_3
      16: invokevirtual #52                 // Method shiftUp:(II)V
      19: aload_0
      20: iload_1
      21: invokestatic  #5                  // Method org/apache/jena/vocabulary/RDF.li:(I)Lorg/apache/jena/rdf/model/Property;
      24: aload_2
      25: invokevirtual #53                 // Method addProperty:(Lorg/apache/jena/rdf/model/Property;Lorg/apache/jena/rdf/model/RDFNode;)Lorg/apache/jena/rdf/model/Resource;
      28: pop
      29: aload_0
      30: areturn

  public org.apache.jena.rdf.model.NodeIterator iterator();
    Code:
       0: aload_0
       1: getstatic     #54                 // Field seqIteratorFactory:Lorg/apache/jena/rdf/model/impl/NodeIteratorFactory;
       4: invokevirtual #55                 // Method listContainerMembers:(Lorg/apache/jena/rdf/model/impl/NodeIteratorFactory;)Lorg/apache/jena/rdf/model/NodeIterator;
       7: areturn

  public org.apache.jena.rdf.model.Container remove(org.apache.jena.rdf.model.Statement);
    Code:
       0: aload_0
       1: invokevirtual #56                 // Method getModel:()Lorg/apache/jena/rdf/model/Model;
       4: aload_1
       5: invokeinterface #37,  2           // InterfaceMethod org/apache/jena/rdf/model/Model.remove:(Lorg/apache/jena/rdf/model/Statement;)Lorg/apache/jena/rdf/model/Model;
      10: pop
      11: aload_0
      12: aload_1
      13: invokeinterface #35,  1           // InterfaceMethod org/apache/jena/rdf/model/Statement.getPredicate:()Lorg/apache/jena/rdf/model/Property;
      18: invokeinterface #57,  1           // InterfaceMethod org/apache/jena/rdf/model/Property.getOrdinal:()I
      23: iconst_1
      24: iadd
      25: aload_0
      26: invokevirtual #50                 // Method size:()I
      29: iconst_1
      30: iadd
      31: invokevirtual #58                 // Method shiftDown:(II)V
      34: aload_0
      35: areturn

  public org.apache.jena.rdf.model.Seq remove(int);
    Code:
       0: aload_0
       1: iload_1
       2: invokestatic  #5                  // Method org/apache/jena/vocabulary/RDF.li:(I)Lorg/apache/jena/rdf/model/Property;
       5: invokevirtual #6                  // Method getRequiredProperty:(Lorg/apache/jena/rdf/model/Property;)Lorg/apache/jena/rdf/model/Statement;
       8: invokeinterface #59,  1           // InterfaceMethod org/apache/jena/rdf/model/Statement.remove:()Lorg/apache/jena/rdf/model/Statement;
      13: pop
      14: aload_0
      15: iload_1
      16: iconst_1
      17: iadd
      18: aload_0
      19: invokevirtual #50                 // Method size:()I
      22: iconst_1
      23: iadd
      24: invokevirtual #58                 // Method shiftDown:(II)V
      27: aload_0
      28: areturn

  public org.apache.jena.rdf.model.Container remove(int, org.apache.jena.rdf.model.RDFNode);
    Code:
       0: aload_0
       1: aload_0
       2: invokevirtual #56                 // Method getModel:()Lorg/apache/jena/rdf/model/Model;
       5: aload_0
       6: iload_1
       7: invokestatic  #5                  // Method org/apache/jena/vocabulary/RDF.li:(I)Lorg/apache/jena/rdf/model/Property;
      10: aload_2
      11: invokeinterface #60,  4           // InterfaceMethod org/apache/jena/rdf/model/Model.createStatement:(Lorg/apache/jena/rdf/model/Resource;Lorg/apache/jena/rdf/model/Property;Lorg/apache/jena/rdf/model/RDFNode;)Lorg/apache/jena/rdf/model/Statement;
      16: invokeinterface #59,  1           // InterfaceMethod org/apache/jena/rdf/model/Statement.remove:()Lorg/apache/jena/rdf/model/Statement;
      21: invokevirtual #61                 // Method remove:(Lorg/apache/jena/rdf/model/Statement;)Lorg/apache/jena/rdf/model/Container;
      24: areturn

  public int indexOf(org.apache.jena.rdf.model.RDFNode);
    Code:
       0: aload_0
       1: aload_1
       2: invokevirtual #62                 // Method containerIndexOf:(Lorg/apache/jena/rdf/model/RDFNode;)I
       5: ireturn

  public int indexOf(boolean);
    Code:
       0: aload_0
       1: iload_1
       2: invokestatic  #39                 // Method java/lang/String.valueOf:(Z)Ljava/lang/String;
       5: invokevirtual #63                 // Method indexOf:(Ljava/lang/String;)I
       8: ireturn

  public int indexOf(long);
    Code:
       0: aload_0
       1: lload_1
       2: invokestatic  #41                 // Method java/lang/String.valueOf:(J)Ljava/lang/String;
       5: invokevirtual #63                 // Method indexOf:(Ljava/lang/String;)I
       8: ireturn

  public int indexOf(char);
    Code:
       0: aload_0
       1: iload_1
       2: invokestatic  #42                 // Method java/lang/String.valueOf:(C)Ljava/lang/String;
       5: invokevirtual #63                 // Method indexOf:(Ljava/lang/String;)I
       8: ireturn

  public int indexOf(float);
    Code:
       0: aload_0
       1: fload_1
       2: invokestatic  #43                 // Method java/lang/String.valueOf:(F)Ljava/lang/String;
       5: invokevirtual #63                 // Method indexOf:(Ljava/lang/String;)I
       8: ireturn

  public int indexOf(double);
    Code:
       0: aload_0
       1: dload_1
       2: invokestatic  #44                 // Method java/lang/String.valueOf:(D)Ljava/lang/String;
       5: invokevirtual #63                 // Method indexOf:(Ljava/lang/String;)I
       8: ireturn

  public int indexOf(java.lang.Object);
    Code:
       0: aload_0
       1: aload_1
       2: invokestatic  #45                 // Method java/lang/String.valueOf:(Ljava/lang/Object;)Ljava/lang/String;
       5: invokevirtual #63                 // Method indexOf:(Ljava/lang/String;)I
       8: ireturn

  public int indexOf(java.lang.String);
    Code:
       0: aload_0
       1: aload_1
       2: ldc           #46                 // String
       4: invokevirtual #64                 // Method indexOf:(Ljava/lang/String;Ljava/lang/String;)I
       7: ireturn

  public int indexOf(java.lang.String, java.lang.String);
    Code:
       0: aload_0
       1: aload_0
       2: aload_1
       3: aload_2
       4: invokespecial #48                 // Method literal:(Ljava/lang/String;Ljava/lang/String;)Lorg/apache/jena/rdf/model/Literal;
       7: invokevirtual #65                 // Method indexOf:(Lorg/apache/jena/rdf/model/RDFNode;)I
      10: ireturn

  private org.apache.jena.rdf.model.Literal literal(java.lang.String, java.lang.String);
    Code:
       0: new           #66                 // class org/apache/jena/rdf/model/impl/LiteralImpl
       3: dup
       4: aload_1
       5: aload_2
       6: invokestatic  #67                 // Method org/apache/jena/graph/NodeFactory.createLiteral:(Ljava/lang/String;Ljava/lang/String;)Lorg/apache/jena/graph/Node;
       9: aload_0
      10: invokevirtual #68                 // Method getModelCom:()Lorg/apache/jena/rdf/model/impl/ModelCom;
      13: invokespecial #69                 // Method org/apache/jena/rdf/model/impl/LiteralImpl."<init>":(Lorg/apache/jena/graph/Node;Lorg/apache/jena/rdf/model/impl/ModelCom;)V
      16: areturn

  protected void shiftUp(int, int);
    Code:
       0: aconst_null
       1: astore_3
       2: iload_2
       3: istore        4
       5: iload         4
       7: iload_1
       8: if_icmplt     56
      11: aload_0
      12: iload         4
      14: invokestatic  #5                  // Method org/apache/jena/vocabulary/RDF.li:(I)Lorg/apache/jena/rdf/model/Property;
      17: invokevirtual #6                  // Method getRequiredProperty:(Lorg/apache/jena/rdf/model/Property;)Lorg/apache/jena/rdf/model/Statement;
      20: astore_3
      21: aload_0
      22: invokevirtual #56                 // Method getModel:()Lorg/apache/jena/rdf/model/Model;
      25: aload_3
      26: invokeinterface #37,  2           // InterfaceMethod org/apache/jena/rdf/model/Model.remove:(Lorg/apache/jena/rdf/model/Statement;)Lorg/apache/jena/rdf/model/Model;
      31: pop
      32: aload_0
      33: iload         4
      35: iconst_1
      36: iadd
      37: invokestatic  #5                  // Method org/apache/jena/vocabulary/RDF.li:(I)Lorg/apache/jena/rdf/model/Property;
      40: aload_3
      41: invokeinterface #9,  1            // InterfaceMethod org/apache/jena/rdf/model/Statement.getObject:()Lorg/apache/jena/rdf/model/RDFNode;
      46: invokevirtual #53                 // Method addProperty:(Lorg/apache/jena/rdf/model/Property;Lorg/apache/jena/rdf/model/RDFNode;)Lorg/apache/jena/rdf/model/Resource;
      49: pop
      50: iinc          4, -1
      53: goto          5
      56: return

  protected void shiftDown(int, int);
    Code:
       0: iload_1
       1: istore_3
       2: iload_3
       3: iload_2
       4: if_icmpgt     49
       7: aload_0
       8: iload_3
       9: invokestatic  #5                  // Method org/apache/jena/vocabulary/RDF.li:(I)Lorg/apache/jena/rdf/model/Property;
      12: invokevirtual #6                  // Method getRequiredProperty:(Lorg/apache/jena/rdf/model/Property;)Lorg/apache/jena/rdf/model/Statement;
      15: astore        4
      17: aload         4
      19: invokeinterface #59,  1           // InterfaceMethod org/apache/jena/rdf/model/Statement.remove:()Lorg/apache/jena/rdf/model/Statement;
      24: pop
      25: aload_0
      26: iload_3
      27: iconst_1
      28: isub
      29: invokestatic  #5                  // Method org/apache/jena/vocabulary/RDF.li:(I)Lorg/apache/jena/rdf/model/Property;
      32: aload         4
      34: invokeinterface #9,  1            // InterfaceMethod org/apache/jena/rdf/model/Statement.getObject:()Lorg/apache/jena/rdf/model/RDFNode;
      39: invokevirtual #53                 // Method addProperty:(Lorg/apache/jena/rdf/model/Property;Lorg/apache/jena/rdf/model/RDFNode;)Lorg/apache/jena/rdf/model/Resource;
      42: pop
      43: iinc          3, 1
      46: goto          2
      49: return

  protected void checkIndex(int);
    Code:
       0: aload_0
       1: iload_1
       2: aload_0
       3: invokevirtual #50                 // Method size:()I
       6: invokevirtual #51                 // Method checkIndex:(II)V
       9: return

  protected void checkIndex(int, int);
    Code:
       0: iconst_1
       1: iload_1
       2: if_icmpgt     10
       5: iload_1
       6: iload_2
       7: if_icmple     20
      10: new           #70                 // class org/apache/jena/rdf/model/SeqIndexBoundsException
      13: dup
      14: iload_2
      15: iload_1
      16: invokespecial #71                 // Method org/apache/jena/rdf/model/SeqIndexBoundsException."<init>":(II)V
      19: athrow
      20: return

  static {};
    Code:
       0: new           #72                 // class org/apache/jena/rdf/model/impl/SeqImpl$1
       3: dup
       4: invokespecial #73                 // Method org/apache/jena/rdf/model/impl/SeqImpl$1."<init>":()V
       7: putstatic     #74                 // Field factory:Lorg/apache/jena/enhanced/Implementation;
      10: new           #75                 // class org/apache/jena/rdf/model/impl/SeqNodeIteratorFactoryImpl
      13: dup
      14: invokespecial #76                 // Method org/apache/jena/rdf/model/impl/SeqNodeIteratorFactoryImpl."<init>":()V
      17: putstatic     #54                 // Field seqIteratorFactory:Lorg/apache/jena/rdf/model/impl/NodeIteratorFactory;
      20: return
}
