Compiled from "StmtIteratorImpl.java"
public class org.apache.jena.rdf.model.impl.StmtIteratorImpl extends org.apache.jena.util.iterator.WrappedIterator<org.apache.jena.rdf.model.Statement> implements org.apache.jena.rdf.model.StmtIterator {
  private org.apache.jena.rdf.model.Statement current;

  public org.apache.jena.rdf.model.impl.StmtIteratorImpl(java.util.Iterator<org.apache.jena.rdf.model.Statement>);
    Code:
       0: aload_0
       1: aload_1
       2: invokespecial #1                  // Method org/apache/jena/util/iterator/WrappedIterator."<init>":(Ljava/util/Iterator;)V
       5: return

  public org.apache.jena.rdf.model.Statement next();
    Code:
       0: aload_0
       1: aload_0
       2: invokespecial #2                  // Method org/apache/jena/util/iterator/WrappedIterator.next:()Ljava/lang/Object;
       5: checkcast     #3                  // class org/apache/jena/rdf/model/Statement
       8: dup_x1
       9: putfield      #4                  // Field current:Lorg/apache/jena/rdf/model/Statement;
      12: areturn

  public void remove();
    Code:
       0: aload_0
       1: invokespecial #5                  // Method org/apache/jena/util/iterator/WrappedIterator.remove:()V
       4: aload_0
       5: getfield      #4                  // Field current:Lorg/apache/jena/rdf/model/Statement;
       8: invokeinterface #6,  1            // InterfaceMethod org/apache/jena/rdf/model/Statement.remove:()Lorg/apache/jena/rdf/model/Statement;
      13: pop
      14: return

  public org.apache.jena.rdf.model.Statement nextStatement();
    Code:
       0: aload_0
       1: invokevirtual #7                  // Method next:()Lorg/apache/jena/rdf/model/Statement;
       4: areturn

  public java.lang.Object next();
    Code:
       0: aload_0
       1: invokevirtual #7                  // Method next:()Lorg/apache/jena/rdf/model/Statement;
       4: areturn
}
