Compiled from "MarshallableFunctions.java"
final class org.infinispan.commons.marshall.MarshallableFunctions$SetValue<V> extends org.infinispan.commons.marshall.MarshallableFunctions$AbstractSetValue<V> {
  private static final org.infinispan.commons.marshall.MarshallableFunctions$SetValue INSTANCE;

  protected org.infinispan.commons.marshall.MarshallableFunctions$SetValue(org.infinispan.commons.api.functional.MetaParam$Writable[]);
    Code:
       0: aload_0
       1: aload_1
       2: invokespecial #2                  // Method org/infinispan/commons/marshall/MarshallableFunctions$AbstractSetValue."<init>":([Lorg/infinispan/commons/api/functional/MetaParam$Writable;)V
       5: return

  private static <K, V> java.util.function.BiConsumer<V, org.infinispan.commons.api.functional.EntryView$WriteEntryView<V>> getInstance();
    Code:
       0: getstatic     #3                  // Field INSTANCE:Lorg/infinispan/commons/marshall/MarshallableFunctions$SetValue;
       3: areturn

  static java.util.function.BiConsumer access$900();
    Code:
       0: invokestatic  #1                  // Method getInstance:()Ljava/util/function/BiConsumer;
       3: areturn

  static {};
    Code:
       0: new           #4                  // class org/infinispan/commons/marshall/MarshallableFunctions$SetValue
       3: dup
       4: iconst_0
       5: anewarray     #5                  // class org/infinispan/commons/api/functional/MetaParam$Writable
       8: invokespecial #6                  // Method "<init>":([Lorg/infinispan/commons/api/functional/MetaParam$Writable;)V
      11: putstatic     #3                  // Field INSTANCE:Lorg/infinispan/commons/marshall/MarshallableFunctions$SetValue;
      14: return
}
