Compiled from "MAPErrorMessageSMDeliveryFailureImpl.java"
public class org.mobicents.protocols.ss7.map.errors.MAPErrorMessageSMDeliveryFailureImpl extends org.mobicents.protocols.ss7.map.errors.MAPErrorMessageImpl implements org.mobicents.protocols.ss7.map.api.errors.MAPErrorMessageSMDeliveryFailure {
  private static final java.lang.String MAP_PROTOCOL_VERSION;

  private static final java.lang.String SM_ENUMERATE_DEL_FAIL_CAUSE;

  private static final java.lang.String SIGNAL_INFO;

  private static final java.lang.String MAP_EXTENSION_CONTAINER;

  private long mapProtocolVersion;

  private org.mobicents.protocols.ss7.map.api.errors.SMEnumeratedDeliveryFailureCause sMEnumeratedDeliveryFailureCause;

  private byte[] signalInfo;

  private org.mobicents.protocols.ss7.map.api.primitives.MAPExtensionContainer extensionContainer;

  protected static final javolution.xml.XMLFormat<org.mobicents.protocols.ss7.map.errors.MAPErrorMessageSMDeliveryFailureImpl> MAP_ERROR_MESSAGE_SM_DEL_FAILURE_XML;

  public org.mobicents.protocols.ss7.map.errors.MAPErrorMessageSMDeliveryFailureImpl(long, org.mobicents.protocols.ss7.map.api.errors.SMEnumeratedDeliveryFailureCause, byte[], org.mobicents.protocols.ss7.map.api.primitives.MAPExtensionContainer);
    Code:
       0: aload_0
       1: ldc2_w        #5                  // long 32l
       4: invokestatic  #7                  // Method java/lang/Long.valueOf:(J)Ljava/lang/Long;
       7: invokespecial #8                  // Method org/mobicents/protocols/ss7/map/errors/MAPErrorMessageImpl."<init>":(Ljava/lang/Long;)V
      10: aload_0
      11: lload_1
      12: putfield      #4                  // Field mapProtocolVersion:J
      15: aload_0
      16: aload_3
      17: putfield      #3                  // Field sMEnumeratedDeliveryFailureCause:Lorg/mobicents/protocols/ss7/map/api/errors/SMEnumeratedDeliveryFailureCause;
      20: aload_0
      21: aload         4
      23: putfield      #2                  // Field signalInfo:[B
      26: aload_0
      27: aload         5
      29: putfield      #1                  // Field extensionContainer:Lorg/mobicents/protocols/ss7/map/api/primitives/MAPExtensionContainer;
      32: return

  public org.mobicents.protocols.ss7.map.errors.MAPErrorMessageSMDeliveryFailureImpl();
    Code:
       0: aload_0
       1: ldc2_w        #5                  // long 32l
       4: invokestatic  #7                  // Method java/lang/Long.valueOf:(J)Ljava/lang/Long;
       7: invokespecial #8                  // Method org/mobicents/protocols/ss7/map/errors/MAPErrorMessageImpl."<init>":(Ljava/lang/Long;)V
      10: return

  public org.mobicents.protocols.ss7.map.api.errors.SMEnumeratedDeliveryFailureCause getSMEnumeratedDeliveryFailureCause();
    Code:
       0: aload_0
       1: getfield      #3                  // Field sMEnumeratedDeliveryFailureCause:Lorg/mobicents/protocols/ss7/map/api/errors/SMEnumeratedDeliveryFailureCause;
       4: areturn

  public byte[] getSignalInfo();
    Code:
       0: aload_0
       1: getfield      #2                  // Field signalInfo:[B
       4: areturn

  public long getMapProtocolVersion();
    Code:
       0: aload_0
       1: getfield      #4                  // Field mapProtocolVersion:J
       4: lreturn

  public org.mobicents.protocols.ss7.map.api.primitives.MAPExtensionContainer getExtensionContainer();
    Code:
       0: aload_0
       1: getfield      #1                  // Field extensionContainer:Lorg/mobicents/protocols/ss7/map/api/primitives/MAPExtensionContainer;
       4: areturn

  public void setSMEnumeratedDeliveryFailureCause(org.mobicents.protocols.ss7.map.api.errors.SMEnumeratedDeliveryFailureCause);
    Code:
       0: aload_0
       1: aload_1
       2: putfield      #3                  // Field sMEnumeratedDeliveryFailureCause:Lorg/mobicents/protocols/ss7/map/api/errors/SMEnumeratedDeliveryFailureCause;
       5: return

  public void setSignalInfo(byte[]);
    Code:
       0: aload_0
       1: aload_1
       2: putfield      #2                  // Field signalInfo:[B
       5: return

  public void setExtensionContainer(org.mobicents.protocols.ss7.map.api.primitives.MAPExtensionContainer);
    Code:
       0: aload_0
       1: aload_1
       2: putfield      #1                  // Field extensionContainer:Lorg/mobicents/protocols/ss7/map/api/primitives/MAPExtensionContainer;
       5: return

  public void setMapProtocolVersion(long);
    Code:
       0: aload_0
       1: lload_1
       2: putfield      #4                  // Field mapProtocolVersion:J
       5: return

  public boolean isEmSMDeliveryFailure();
    Code:
       0: iconst_1
       1: ireturn

  public org.mobicents.protocols.ss7.map.api.errors.MAPErrorMessageSMDeliveryFailure getEmSMDeliveryFailure();
    Code:
       0: aload_0
       1: areturn

  public int getTag() throws org.mobicents.protocols.ss7.map.api.MAPException;
    Code:
       0: aload_0
       1: getfield      #4                  // Field mapProtocolVersion:J
       4: lconst_1
       5: lcmp
       6: ifne          12
       9: bipush        10
      11: ireturn
      12: bipush        16
      14: ireturn

  public int getTagClass();
    Code:
       0: iconst_0
       1: ireturn

  public boolean getIsPrimitive();
    Code:
       0: aload_0
       1: getfield      #4                  // Field mapProtocolVersion:J
       4: lconst_1
       5: lcmp
       6: ifne          11
       9: iconst_1
      10: ireturn
      11: iconst_0
      12: ireturn

  public void decodeAll(org.mobicents.protocols.asn.AsnInputStream) throws org.mobicents.protocols.ss7.map.api.MAPParsingComponentException;
    Code:
       0: aload_1
       1: invokevirtual #9                  // Method org/mobicents/protocols/asn/AsnInputStream.readLength:()I
       4: istore_2
       5: aload_0
       6: aload_1
       7: iload_2
       8: invokespecial #10                 // Method _decode:(Lorg/mobicents/protocols/asn/AsnInputStream;I)V
      11: goto          84
      14: astore_2
      15: new           #12                 // class org/mobicents/protocols/ss7/map/api/MAPParsingComponentException
      18: dup
      19: new           #13                 // class java/lang/StringBuilder
      22: dup
      23: invokespecial #14                 // Method java/lang/StringBuilder."<init>":()V
      26: ldc           #15                 // String IOException when decoding MAPErrorMessageSMDeliveryFailure:
      28: invokevirtual #16                 // Method java/lang/StringBuilder.append:(Ljava/lang/String;)Ljava/lang/StringBuilder;
      31: aload_2
      32: invokevirtual #17                 // Method java/io/IOException.getMessage:()Ljava/lang/String;
      35: invokevirtual #16                 // Method java/lang/StringBuilder.append:(Ljava/lang/String;)Ljava/lang/StringBuilder;
      38: invokevirtual #18                 // Method java/lang/StringBuilder.toString:()Ljava/lang/String;
      41: aload_2
      42: getstatic     #19                 // Field org/mobicents/protocols/ss7/map/api/MAPParsingComponentExceptionReason.MistypedParameter:Lorg/mobicents/protocols/ss7/map/api/MAPParsingComponentExceptionReason;
      45: invokespecial #20                 // Method org/mobicents/protocols/ss7/map/api/MAPParsingComponentException."<init>":(Ljava/lang/String;Ljava/lang/Throwable;Lorg/mobicents/protocols/ss7/map/api/MAPParsingComponentExceptionReason;)V
      48: athrow
      49: astore_2
      50: new           #12                 // class org/mobicents/protocols/ss7/map/api/MAPParsingComponentException
      53: dup
      54: new           #13                 // class java/lang/StringBuilder
      57: dup
      58: invokespecial #14                 // Method java/lang/StringBuilder."<init>":()V
      61: ldc           #22                 // String AsnException when decoding MAPErrorMessageSMDeliveryFailure:
      63: invokevirtual #16                 // Method java/lang/StringBuilder.append:(Ljava/lang/String;)Ljava/lang/StringBuilder;
      66: aload_2
      67: invokevirtual #23                 // Method org/mobicents/protocols/asn/AsnException.getMessage:()Ljava/lang/String;
      70: invokevirtual #16                 // Method java/lang/StringBuilder.append:(Ljava/lang/String;)Ljava/lang/StringBuilder;
      73: invokevirtual #18                 // Method java/lang/StringBuilder.toString:()Ljava/lang/String;
      76: aload_2
      77: getstatic     #19                 // Field org/mobicents/protocols/ss7/map/api/MAPParsingComponentExceptionReason.MistypedParameter:Lorg/mobicents/protocols/ss7/map/api/MAPParsingComponentExceptionReason;
      80: invokespecial #20                 // Method org/mobicents/protocols/ss7/map/api/MAPParsingComponentException."<init>":(Ljava/lang/String;Ljava/lang/Throwable;Lorg/mobicents/protocols/ss7/map/api/MAPParsingComponentExceptionReason;)V
      83: athrow
      84: return
    Exception table:
       from    to  target type
           0    11    14   Class java/io/IOException
           0    11    49   Class org/mobicents/protocols/asn/AsnException

  public void decodeData(org.mobicents.protocols.asn.AsnInputStream, int) throws org.mobicents.protocols.ss7.map.api.MAPParsingComponentException;
    Code:
       0: aload_0
       1: aload_1
       2: iload_2
       3: invokespecial #10                 // Method _decode:(Lorg/mobicents/protocols/asn/AsnInputStream;I)V
       6: goto          79
       9: astore_3
      10: new           #12                 // class org/mobicents/protocols/ss7/map/api/MAPParsingComponentException
      13: dup
      14: new           #13                 // class java/lang/StringBuilder
      17: dup
      18: invokespecial #14                 // Method java/lang/StringBuilder."<init>":()V
      21: ldc           #15                 // String IOException when decoding MAPErrorMessageSMDeliveryFailure:
      23: invokevirtual #16                 // Method java/lang/StringBuilder.append:(Ljava/lang/String;)Ljava/lang/StringBuilder;
      26: aload_3
      27: invokevirtual #17                 // Method java/io/IOException.getMessage:()Ljava/lang/String;
      30: invokevirtual #16                 // Method java/lang/StringBuilder.append:(Ljava/lang/String;)Ljava/lang/StringBuilder;
      33: invokevirtual #18                 // Method java/lang/StringBuilder.toString:()Ljava/lang/String;
      36: aload_3
      37: getstatic     #19                 // Field org/mobicents/protocols/ss7/map/api/MAPParsingComponentExceptionReason.MistypedParameter:Lorg/mobicents/protocols/ss7/map/api/MAPParsingComponentExceptionReason;
      40: invokespecial #20                 // Method org/mobicents/protocols/ss7/map/api/MAPParsingComponentException."<init>":(Ljava/lang/String;Ljava/lang/Throwable;Lorg/mobicents/protocols/ss7/map/api/MAPParsingComponentExceptionReason;)V
      43: athrow
      44: astore_3
      45: new           #12                 // class org/mobicents/protocols/ss7/map/api/MAPParsingComponentException
      48: dup
      49: new           #13                 // class java/lang/StringBuilder
      52: dup
      53: invokespecial #14                 // Method java/lang/StringBuilder."<init>":()V
      56: ldc           #22                 // String AsnException when decoding MAPErrorMessageSMDeliveryFailure:
      58: invokevirtual #16                 // Method java/lang/StringBuilder.append:(Ljava/lang/String;)Ljava/lang/StringBuilder;
      61: aload_3
      62: invokevirtual #23                 // Method org/mobicents/protocols/asn/AsnException.getMessage:()Ljava/lang/String;
      65: invokevirtual #16                 // Method java/lang/StringBuilder.append:(Ljava/lang/String;)Ljava/lang/StringBuilder;
      68: invokevirtual #18                 // Method java/lang/StringBuilder.toString:()Ljava/lang/String;
      71: aload_3
      72: getstatic     #19                 // Field org/mobicents/protocols/ss7/map/api/MAPParsingComponentExceptionReason.MistypedParameter:Lorg/mobicents/protocols/ss7/map/api/MAPParsingComponentExceptionReason;
      75: invokespecial #20                 // Method org/mobicents/protocols/ss7/map/api/MAPParsingComponentException."<init>":(Ljava/lang/String;Ljava/lang/Throwable;Lorg/mobicents/protocols/ss7/map/api/MAPParsingComponentExceptionReason;)V
      78: athrow
      79: return
    Exception table:
       from    to  target type
           0     6     9   Class java/io/IOException
           0     6    44   Class org/mobicents/protocols/asn/AsnException

  private void _decode(org.mobicents.protocols.asn.AsnInputStream, int) throws org.mobicents.protocols.ss7.map.api.MAPParsingComponentException, java.io.IOException, org.mobicents.protocols.asn.AsnException;
    Code:
       0: aload_0
       1: aconst_null
       2: putfield      #3                  // Field sMEnumeratedDeliveryFailureCause:Lorg/mobicents/protocols/ss7/map/api/errors/SMEnumeratedDeliveryFailureCause;
       5: aload_0
       6: aconst_null
       7: putfield      #2                  // Field signalInfo:[B
      10: aload_0
      11: aconst_null
      12: putfield      #1                  // Field extensionContainer:Lorg/mobicents/protocols/ss7/map/api/primitives/MAPExtensionContainer;
      15: aload_1
      16: invokevirtual #24                 // Method org/mobicents/protocols/asn/AsnInputStream.getTagClass:()I
      19: ifeq          35
      22: new           #12                 // class org/mobicents/protocols/ss7/map/api/MAPParsingComponentException
      25: dup
      26: ldc           #25                 // String Error decoding MAPErrorMessageSMDeliveryFailure: bad tag class
      28: getstatic     #19                 // Field org/mobicents/protocols/ss7/map/api/MAPParsingComponentExceptionReason.MistypedParameter:Lorg/mobicents/protocols/ss7/map/api/MAPParsingComponentExceptionReason;
      31: invokespecial #26                 // Method org/mobicents/protocols/ss7/map/api/MAPParsingComponentException."<init>":(Ljava/lang/String;Lorg/mobicents/protocols/ss7/map/api/MAPParsingComponentExceptionReason;)V
      34: athrow
      35: aload_1
      36: invokevirtual #27                 // Method org/mobicents/protocols/asn/AsnInputStream.getTag:()I
      39: lookupswitch  { // 2
                    10: 64
                    16: 127
               default: 353
          }
      64: aload_1
      65: invokevirtual #28                 // Method org/mobicents/protocols/asn/AsnInputStream.isTagPrimitive:()Z
      68: ifne          84
      71: new           #12                 // class org/mobicents/protocols/ss7/map/api/MAPParsingComponentException
      74: dup
      75: ldc           #29                 // String Error decoding MAPErrorMessageSMDeliveryFailure: ENUMERATED tag but data is not primitive
      77: getstatic     #19                 // Field org/mobicents/protocols/ss7/map/api/MAPParsingComponentExceptionReason.MistypedParameter:Lorg/mobicents/protocols/ss7/map/api/MAPParsingComponentExceptionReason;
      80: invokespecial #26                 // Method org/mobicents/protocols/ss7/map/api/MAPParsingComponentException."<init>":(Ljava/lang/String;Lorg/mobicents/protocols/ss7/map/api/MAPParsingComponentExceptionReason;)V
      83: athrow
      84: aload_1
      85: iload_2
      86: invokevirtual #30                 // Method org/mobicents/protocols/asn/AsnInputStream.readIntegerData:(I)J
      89: l2i
      90: istore_3
      91: aload_0
      92: iload_3
      93: invokestatic  #31                 // Method org/mobicents/protocols/ss7/map/api/errors/SMEnumeratedDeliveryFailureCause.getInstance:(I)Lorg/mobicents/protocols/ss7/map/api/errors/SMEnumeratedDeliveryFailureCause;
      96: putfield      #3                  // Field sMEnumeratedDeliveryFailureCause:Lorg/mobicents/protocols/ss7/map/api/errors/SMEnumeratedDeliveryFailureCause;
      99: aload_0
     100: getfield      #3                  // Field sMEnumeratedDeliveryFailureCause:Lorg/mobicents/protocols/ss7/map/api/errors/SMEnumeratedDeliveryFailureCause;
     103: ifnonnull     119
     106: new           #12                 // class org/mobicents/protocols/ss7/map/api/MAPParsingComponentException
     109: dup
     110: ldc           #32                 // String Error decoding MAPErrorMessageSMDeliveryFailure.sMEnumeratedDeliveryFailureCause: bad code value
     112: getstatic     #19                 // Field org/mobicents/protocols/ss7/map/api/MAPParsingComponentExceptionReason.MistypedParameter:Lorg/mobicents/protocols/ss7/map/api/MAPParsingComponentExceptionReason;
     115: invokespecial #26                 // Method org/mobicents/protocols/ss7/map/api/MAPParsingComponentException."<init>":(Ljava/lang/String;Lorg/mobicents/protocols/ss7/map/api/MAPParsingComponentExceptionReason;)V
     118: athrow
     119: aload_0
     120: lconst_1
     121: putfield      #4                  // Field mapProtocolVersion:J
     124: goto          353
     127: aload_1
     128: invokevirtual #28                 // Method org/mobicents/protocols/asn/AsnInputStream.isTagPrimitive:()Z
     131: ifeq          147
     134: new           #12                 // class org/mobicents/protocols/ss7/map/api/MAPParsingComponentException
     137: dup
     138: ldc           #33                 // String Error decoding MAPErrorMessageCallBarred: SEQUENCE tag but data is primitive
     140: getstatic     #19                 // Field org/mobicents/protocols/ss7/map/api/MAPParsingComponentExceptionReason.MistypedParameter:Lorg/mobicents/protocols/ss7/map/api/MAPParsingComponentExceptionReason;
     143: invokespecial #26                 // Method org/mobicents/protocols/ss7/map/api/MAPParsingComponentException."<init>":(Ljava/lang/String;Lorg/mobicents/protocols/ss7/map/api/MAPParsingComponentExceptionReason;)V
     146: athrow
     147: aload_1
     148: iload_2
     149: invokevirtual #34                 // Method org/mobicents/protocols/asn/AsnInputStream.readSequenceStreamData:(I)Lorg/mobicents/protocols/asn/AsnInputStream;
     152: astore        4
     154: aload         4
     156: invokevirtual #35                 // Method org/mobicents/protocols/asn/AsnInputStream.readTag:()I
     159: istore        5
     161: aload         4
     163: invokevirtual #24                 // Method org/mobicents/protocols/asn/AsnInputStream.getTagClass:()I
     166: ifne          176
     169: iload         5
     171: bipush        10
     173: if_icmpeq     189
     176: new           #12                 // class org/mobicents/protocols/ss7/map/api/MAPParsingComponentException
     179: dup
     180: ldc           #36                 // String Error decoding MAPErrorMessageSMDeliveryFailure.sMEnumeratedDeliveryFailureCause: bad tag class or tag
     182: getstatic     #19                 // Field org/mobicents/protocols/ss7/map/api/MAPParsingComponentExceptionReason.MistypedParameter:Lorg/mobicents/protocols/ss7/map/api/MAPParsingComponentExceptionReason;
     185: invokespecial #26                 // Method org/mobicents/protocols/ss7/map/api/MAPParsingComponentException."<init>":(Ljava/lang/String;Lorg/mobicents/protocols/ss7/map/api/MAPParsingComponentExceptionReason;)V
     188: athrow
     189: aload         4
     191: invokevirtual #37                 // Method org/mobicents/protocols/asn/AsnInputStream.readInteger:()J
     194: l2i
     195: istore_3
     196: aload_0
     197: iload_3
     198: invokestatic  #31                 // Method org/mobicents/protocols/ss7/map/api/errors/SMEnumeratedDeliveryFailureCause.getInstance:(I)Lorg/mobicents/protocols/ss7/map/api/errors/SMEnumeratedDeliveryFailureCause;
     201: putfield      #3                  // Field sMEnumeratedDeliveryFailureCause:Lorg/mobicents/protocols/ss7/map/api/errors/SMEnumeratedDeliveryFailureCause;
     204: aload_0
     205: getfield      #3                  // Field sMEnumeratedDeliveryFailureCause:Lorg/mobicents/protocols/ss7/map/api/errors/SMEnumeratedDeliveryFailureCause;
     208: ifnonnull     224
     211: new           #12                 // class org/mobicents/protocols/ss7/map/api/MAPParsingComponentException
     214: dup
     215: ldc           #38                 // String Error decoding MAPErrorMessageSMDeliveryFailure.sMEnumeratedDeliveryFailureCause: bad value
     217: getstatic     #19                 // Field org/mobicents/protocols/ss7/map/api/MAPParsingComponentExceptionReason.MistypedParameter:Lorg/mobicents/protocols/ss7/map/api/MAPParsingComponentExceptionReason;
     220: invokespecial #26                 // Method org/mobicents/protocols/ss7/map/api/MAPParsingComponentException."<init>":(Ljava/lang/String;Lorg/mobicents/protocols/ss7/map/api/MAPParsingComponentExceptionReason;)V
     223: athrow
     224: aload         4
     226: invokevirtual #39                 // Method org/mobicents/protocols/asn/AsnInputStream.available:()I
     229: ifne          235
     232: goto          346
     235: aload         4
     237: invokevirtual #35                 // Method org/mobicents/protocols/asn/AsnInputStream.readTag:()I
     240: istore        5
     242: aload         4
     244: invokevirtual #24                 // Method org/mobicents/protocols/asn/AsnInputStream.getTagClass:()I
     247: lookupswitch  { // 1
                     0: 264
               default: 338
          }
     264: iload         5
     266: lookupswitch  { // 2
                     4: 292
                    16: 304
               default: 330
          }
     292: aload_0
     293: aload         4
     295: invokevirtual #40                 // Method org/mobicents/protocols/asn/AsnInputStream.readOctetString:()[B
     298: putfield      #2                  // Field signalInfo:[B
     301: goto          224
     304: aload_0
     305: new           #41                 // class org/mobicents/protocols/ss7/map/primitives/MAPExtensionContainerImpl
     308: dup
     309: invokespecial #42                 // Method org/mobicents/protocols/ss7/map/primitives/MAPExtensionContainerImpl."<init>":()V
     312: putfield      #1                  // Field extensionContainer:Lorg/mobicents/protocols/ss7/map/api/primitives/MAPExtensionContainer;
     315: aload_0
     316: getfield      #1                  // Field extensionContainer:Lorg/mobicents/protocols/ss7/map/api/primitives/MAPExtensionContainer;
     319: checkcast     #41                 // class org/mobicents/protocols/ss7/map/primitives/MAPExtensionContainerImpl
     322: aload         4
     324: invokevirtual #43                 // Method org/mobicents/protocols/ss7/map/primitives/MAPExtensionContainerImpl.decodeAll:(Lorg/mobicents/protocols/asn/AsnInputStream;)V
     327: goto          224
     330: aload         4
     332: invokevirtual #44                 // Method org/mobicents/protocols/asn/AsnInputStream.advanceElement:()V
     335: goto          224
     338: aload         4
     340: invokevirtual #44                 // Method org/mobicents/protocols/asn/AsnInputStream.advanceElement:()V
     343: goto          224
     346: aload_0
     347: ldc2_w        #45                 // long 3l
     350: putfield      #4                  // Field mapProtocolVersion:J
     353: return

  public void encodeAll(org.mobicents.protocols.asn.AsnOutputStream) throws org.mobicents.protocols.ss7.map.api.MAPException;
    Code:
       0: aload_0
       1: aload_1
       2: iconst_0
       3: bipush        16
       5: invokevirtual #47                 // Method encodeAll:(Lorg/mobicents/protocols/asn/AsnOutputStream;II)V
       8: return

  public void encodeAll(org.mobicents.protocols.asn.AsnOutputStream, int, int) throws org.mobicents.protocols.ss7.map.api.MAPException;
    Code:
       0: aload_1
       1: iload_2
       2: aload_0
       3: invokevirtual #48                 // Method getIsPrimitive:()Z
       6: iload_3
       7: invokevirtual #49                 // Method org/mobicents/protocols/asn/AsnOutputStream.writeTag:(IZI)V
      10: aload_1
      11: invokevirtual #50                 // Method org/mobicents/protocols/asn/AsnOutputStream.StartContentDefiniteLength:()I
      14: istore        4
      16: aload_0
      17: aload_1
      18: invokevirtual #51                 // Method encodeData:(Lorg/mobicents/protocols/asn/AsnOutputStream;)V
      21: aload_1
      22: iload         4
      24: invokevirtual #52                 // Method org/mobicents/protocols/asn/AsnOutputStream.FinalizeContent:(I)V
      27: goto          65
      30: astore        4
      32: new           #53                 // class org/mobicents/protocols/ss7/map/api/MAPException
      35: dup
      36: new           #13                 // class java/lang/StringBuilder
      39: dup
      40: invokespecial #14                 // Method java/lang/StringBuilder."<init>":()V
      43: ldc           #54                 // String AsnException when encoding MAPErrorMessageSMDeliveryFailure:
      45: invokevirtual #16                 // Method java/lang/StringBuilder.append:(Ljava/lang/String;)Ljava/lang/StringBuilder;
      48: aload         4
      50: invokevirtual #23                 // Method org/mobicents/protocols/asn/AsnException.getMessage:()Ljava/lang/String;
      53: invokevirtual #16                 // Method java/lang/StringBuilder.append:(Ljava/lang/String;)Ljava/lang/StringBuilder;
      56: invokevirtual #18                 // Method java/lang/StringBuilder.toString:()Ljava/lang/String;
      59: aload         4
      61: invokespecial #55                 // Method org/mobicents/protocols/ss7/map/api/MAPException."<init>":(Ljava/lang/String;Ljava/lang/Throwable;)V
      64: athrow
      65: return
    Exception table:
       from    to  target type
           0    27    30   Class org/mobicents/protocols/asn/AsnException

  public void encodeData(org.mobicents.protocols.asn.AsnOutputStream) throws org.mobicents.protocols.ss7.map.api.MAPException;
    Code:
       0: aload_0
       1: getfield      #3                  // Field sMEnumeratedDeliveryFailureCause:Lorg/mobicents/protocols/ss7/map/api/errors/SMEnumeratedDeliveryFailureCause;
       4: ifnonnull     17
       7: new           #53                 // class org/mobicents/protocols/ss7/map/api/MAPException
      10: dup
      11: ldc           #56                 // String Error encoding MAPErrorMessageSMDeliveryFailure: parameter sMEnumeratedDeliveryFailureCause must not be null
      13: invokespecial #57                 // Method org/mobicents/protocols/ss7/map/api/MAPException."<init>":(Ljava/lang/String;)V
      16: athrow
      17: aload_0
      18: getfield      #4                  // Field mapProtocolVersion:J
      21: ldc2_w        #45                 // long 3l
      24: lcmp
      25: ifge          44
      28: aload_1
      29: aload_0
      30: getfield      #3                  // Field sMEnumeratedDeliveryFailureCause:Lorg/mobicents/protocols/ss7/map/api/errors/SMEnumeratedDeliveryFailureCause;
      33: invokevirtual #58                 // Method org/mobicents/protocols/ss7/map/api/errors/SMEnumeratedDeliveryFailureCause.getCode:()I
      36: i2l
      37: invokevirtual #59                 // Method org/mobicents/protocols/asn/AsnOutputStream.writeIntegerData:(J)I
      40: pop
      41: goto          94
      44: aload_1
      45: iconst_0
      46: bipush        10
      48: aload_0
      49: getfield      #3                  // Field sMEnumeratedDeliveryFailureCause:Lorg/mobicents/protocols/ss7/map/api/errors/SMEnumeratedDeliveryFailureCause;
      52: invokevirtual #58                 // Method org/mobicents/protocols/ss7/map/api/errors/SMEnumeratedDeliveryFailureCause.getCode:()I
      55: i2l
      56: invokevirtual #60                 // Method org/mobicents/protocols/asn/AsnOutputStream.writeInteger:(IIJ)V
      59: aload_0
      60: getfield      #2                  // Field signalInfo:[B
      63: ifnull        76
      66: aload_1
      67: iconst_0
      68: iconst_4
      69: aload_0
      70: getfield      #2                  // Field signalInfo:[B
      73: invokevirtual #61                 // Method org/mobicents/protocols/asn/AsnOutputStream.writeOctetString:(II[B)V
      76: aload_0
      77: getfield      #1                  // Field extensionContainer:Lorg/mobicents/protocols/ss7/map/api/primitives/MAPExtensionContainer;
      80: ifnull        94
      83: aload_0
      84: getfield      #1                  // Field extensionContainer:Lorg/mobicents/protocols/ss7/map/api/primitives/MAPExtensionContainer;
      87: checkcast     #41                 // class org/mobicents/protocols/ss7/map/primitives/MAPExtensionContainerImpl
      90: aload_1
      91: invokevirtual #62                 // Method org/mobicents/protocols/ss7/map/primitives/MAPExtensionContainerImpl.encodeAll:(Lorg/mobicents/protocols/asn/AsnOutputStream;)V
      94: goto          161
      97: astore_2
      98: new           #53                 // class org/mobicents/protocols/ss7/map/api/MAPException
     101: dup
     102: new           #13                 // class java/lang/StringBuilder
     105: dup
     106: invokespecial #14                 // Method java/lang/StringBuilder."<init>":()V
     109: ldc           #63                 // String IOException when encoding MAPErrorMessageSMDeliveryFailure:
     111: invokevirtual #16                 // Method java/lang/StringBuilder.append:(Ljava/lang/String;)Ljava/lang/StringBuilder;
     114: aload_2
     115: invokevirtual #17                 // Method java/io/IOException.getMessage:()Ljava/lang/String;
     118: invokevirtual #16                 // Method java/lang/StringBuilder.append:(Ljava/lang/String;)Ljava/lang/StringBuilder;
     121: invokevirtual #18                 // Method java/lang/StringBuilder.toString:()Ljava/lang/String;
     124: aload_2
     125: invokespecial #55                 // Method org/mobicents/protocols/ss7/map/api/MAPException."<init>":(Ljava/lang/String;Ljava/lang/Throwable;)V
     128: athrow
     129: astore_2
     130: new           #53                 // class org/mobicents/protocols/ss7/map/api/MAPException
     133: dup
     134: new           #13                 // class java/lang/StringBuilder
     137: dup
     138: invokespecial #14                 // Method java/lang/StringBuilder."<init>":()V
     141: ldc           #54                 // String AsnException when encoding MAPErrorMessageSMDeliveryFailure:
     143: invokevirtual #16                 // Method java/lang/StringBuilder.append:(Ljava/lang/String;)Ljava/lang/StringBuilder;
     146: aload_2
     147: invokevirtual #23                 // Method org/mobicents/protocols/asn/AsnException.getMessage:()Ljava/lang/String;
     150: invokevirtual #16                 // Method java/lang/StringBuilder.append:(Ljava/lang/String;)Ljava/lang/StringBuilder;
     153: invokevirtual #18                 // Method java/lang/StringBuilder.toString:()Ljava/lang/String;
     156: aload_2
     157: invokespecial #55                 // Method org/mobicents/protocols/ss7/map/api/MAPException."<init>":(Ljava/lang/String;Ljava/lang/Throwable;)V
     160: athrow
     161: return
    Exception table:
       from    to  target type
          17    94    97   Class java/io/IOException
          17    94   129   Class org/mobicents/protocols/asn/AsnException

  public java.lang.String toString();
    Code:
       0: new           #13                 // class java/lang/StringBuilder
       3: dup
       4: invokespecial #14                 // Method java/lang/StringBuilder."<init>":()V
       7: astore_1
       8: aload_1
       9: ldc           #64                 // String MAPErrorMessageSMDeliveryFailure [
      11: invokevirtual #16                 // Method java/lang/StringBuilder.append:(Ljava/lang/String;)Ljava/lang/StringBuilder;
      14: pop
      15: aload_0
      16: getfield      #3                  // Field sMEnumeratedDeliveryFailureCause:Lorg/mobicents/protocols/ss7/map/api/errors/SMEnumeratedDeliveryFailureCause;
      19: ifnull        52
      22: aload_1
      23: new           #13                 // class java/lang/StringBuilder
      26: dup
      27: invokespecial #14                 // Method java/lang/StringBuilder."<init>":()V
      30: ldc           #65                 // String sMEnumeratedDeliveryFailureCause=
      32: invokevirtual #16                 // Method java/lang/StringBuilder.append:(Ljava/lang/String;)Ljava/lang/StringBuilder;
      35: aload_0
      36: getfield      #3                  // Field sMEnumeratedDeliveryFailureCause:Lorg/mobicents/protocols/ss7/map/api/errors/SMEnumeratedDeliveryFailureCause;
      39: invokevirtual #66                 // Method org/mobicents/protocols/ss7/map/api/errors/SMEnumeratedDeliveryFailureCause.toString:()Ljava/lang/String;
      42: invokevirtual #16                 // Method java/lang/StringBuilder.append:(Ljava/lang/String;)Ljava/lang/StringBuilder;
      45: invokevirtual #18                 // Method java/lang/StringBuilder.toString:()Ljava/lang/String;
      48: invokevirtual #16                 // Method java/lang/StringBuilder.append:(Ljava/lang/String;)Ljava/lang/StringBuilder;
      51: pop
      52: aload_0
      53: getfield      #2                  // Field signalInfo:[B
      56: ifnull        90
      59: aload_1
      60: new           #13                 // class java/lang/StringBuilder
      63: dup
      64: invokespecial #14                 // Method java/lang/StringBuilder."<init>":()V
      67: ldc           #67                 // String , signalInfo=
      69: invokevirtual #16                 // Method java/lang/StringBuilder.append:(Ljava/lang/String;)Ljava/lang/StringBuilder;
      72: aload_0
      73: aload_0
      74: getfield      #2                  // Field signalInfo:[B
      77: invokespecial #68                 // Method printDataArr:([B)Ljava/lang/String;
      80: invokevirtual #16                 // Method java/lang/StringBuilder.append:(Ljava/lang/String;)Ljava/lang/StringBuilder;
      83: invokevirtual #18                 // Method java/lang/StringBuilder.toString:()Ljava/lang/String;
      86: invokevirtual #16                 // Method java/lang/StringBuilder.append:(Ljava/lang/String;)Ljava/lang/StringBuilder;
      89: pop
      90: aload_0
      91: getfield      #1                  // Field extensionContainer:Lorg/mobicents/protocols/ss7/map/api/primitives/MAPExtensionContainer;
      94: ifnull        127
      97: aload_1
      98: new           #13                 // class java/lang/StringBuilder
     101: dup
     102: invokespecial #14                 // Method java/lang/StringBuilder."<init>":()V
     105: ldc           #69                 // String , extensionContainer=
     107: invokevirtual #16                 // Method java/lang/StringBuilder.append:(Ljava/lang/String;)Ljava/lang/StringBuilder;
     110: aload_0
     111: getfield      #1                  // Field extensionContainer:Lorg/mobicents/protocols/ss7/map/api/primitives/MAPExtensionContainer;
     114: invokevirtual #70                 // Method java/lang/Object.toString:()Ljava/lang/String;
     117: invokevirtual #16                 // Method java/lang/StringBuilder.append:(Ljava/lang/String;)Ljava/lang/StringBuilder;
     120: invokevirtual #18                 // Method java/lang/StringBuilder.toString:()Ljava/lang/String;
     123: invokevirtual #16                 // Method java/lang/StringBuilder.append:(Ljava/lang/String;)Ljava/lang/StringBuilder;
     126: pop
     127: aload_1
     128: ldc           #71                 // String ]
     130: invokevirtual #16                 // Method java/lang/StringBuilder.append:(Ljava/lang/String;)Ljava/lang/StringBuilder;
     133: pop
     134: aload_1
     135: invokevirtual #18                 // Method java/lang/StringBuilder.toString:()Ljava/lang/String;
     138: areturn

  private java.lang.String printDataArr(byte[]);
    Code:
       0: new           #13                 // class java/lang/StringBuilder
       3: dup
       4: invokespecial #14                 // Method java/lang/StringBuilder."<init>":()V
       7: astore_2
       8: aload_1
       9: ifnull        54
      12: aload_1
      13: astore_3
      14: aload_3
      15: arraylength
      16: istore        4
      18: iconst_0
      19: istore        5
      21: iload         5
      23: iload         4
      25: if_icmpge     54
      28: aload_3
      29: iload         5
      31: baload
      32: istore        6
      34: aload_2
      35: iload         6
      37: invokevirtual #72                 // Method java/lang/StringBuilder.append:(I)Ljava/lang/StringBuilder;
      40: pop
      41: aload_2
      42: ldc           #73                 // String ,
      44: invokevirtual #16                 // Method java/lang/StringBuilder.append:(Ljava/lang/String;)Ljava/lang/StringBuilder;
      47: pop
      48: iinc          5, 1
      51: goto          21
      54: aload_2
      55: invokevirtual #18                 // Method java/lang/StringBuilder.toString:()Ljava/lang/String;
      58: areturn

  static long access$002(org.mobicents.protocols.ss7.map.errors.MAPErrorMessageSMDeliveryFailureImpl, long);
    Code:
       0: aload_0
       1: lload_1
       2: dup2_x1
       3: putfield      #4                  // Field mapProtocolVersion:J
       6: lreturn

  static org.mobicents.protocols.ss7.map.api.errors.SMEnumeratedDeliveryFailureCause access$102(org.mobicents.protocols.ss7.map.errors.MAPErrorMessageSMDeliveryFailureImpl, org.mobicents.protocols.ss7.map.api.errors.SMEnumeratedDeliveryFailureCause);
    Code:
       0: aload_0
       1: aload_1
       2: dup_x1
       3: putfield      #3                  // Field sMEnumeratedDeliveryFailureCause:Lorg/mobicents/protocols/ss7/map/api/errors/SMEnumeratedDeliveryFailureCause;
       6: areturn

  static byte[] access$202(org.mobicents.protocols.ss7.map.errors.MAPErrorMessageSMDeliveryFailureImpl, byte[]);
    Code:
       0: aload_0
       1: aload_1
       2: dup_x1
       3: putfield      #2                  // Field signalInfo:[B
       6: areturn

  static org.mobicents.protocols.ss7.map.api.primitives.MAPExtensionContainer access$302(org.mobicents.protocols.ss7.map.errors.MAPErrorMessageSMDeliveryFailureImpl, org.mobicents.protocols.ss7.map.api.primitives.MAPExtensionContainer);
    Code:
       0: aload_0
       1: aload_1
       2: dup_x1
       3: putfield      #1                  // Field extensionContainer:Lorg/mobicents/protocols/ss7/map/api/primitives/MAPExtensionContainer;
       6: areturn

  static byte[] access$200(org.mobicents.protocols.ss7.map.errors.MAPErrorMessageSMDeliveryFailureImpl);
    Code:
       0: aload_0
       1: getfield      #2                  // Field signalInfo:[B
       4: areturn

  static org.mobicents.protocols.ss7.map.api.primitives.MAPExtensionContainer access$300(org.mobicents.protocols.ss7.map.errors.MAPErrorMessageSMDeliveryFailureImpl);
    Code:
       0: aload_0
       1: getfield      #1                  // Field extensionContainer:Lorg/mobicents/protocols/ss7/map/api/primitives/MAPExtensionContainer;
       4: areturn

  static {};
    Code:
       0: new           #74                 // class org/mobicents/protocols/ss7/map/errors/MAPErrorMessageSMDeliveryFailureImpl$1
       3: dup
       4: ldc_w         #75                 // class org/mobicents/protocols/ss7/map/errors/MAPErrorMessageSMDeliveryFailureImpl
       7: invokespecial #76                 // Method org/mobicents/protocols/ss7/map/errors/MAPErrorMessageSMDeliveryFailureImpl$1."<init>":(Ljava/lang/Class;)V
      10: putstatic     #77                 // Field MAP_ERROR_MESSAGE_SM_DEL_FAILURE_XML:Ljavolution/xml/XMLFormat;
      13: return
}
