Compiled from "CharSource.java"
final class org.apache.curator.shaded.com.google.common.io.CharSource$ConcatenatedCharSource extends org.apache.curator.shaded.com.google.common.io.CharSource {
  private final java.lang.Iterable<? extends org.apache.curator.shaded.com.google.common.io.CharSource> sources;

  org.apache.curator.shaded.com.google.common.io.CharSource$ConcatenatedCharSource(java.lang.Iterable<? extends org.apache.curator.shaded.com.google.common.io.CharSource>);
    Code:
       0: aload_0
       1: invokespecial #14                 // Method org/apache/curator/shaded/com/google/common/io/CharSource."<init>":()V
       4: aload_0
       5: aload_1
       6: invokestatic  #20                 // Method org/apache/curator/shaded/com/google/common/base/Preconditions.checkNotNull:(Ljava/lang/Object;)Ljava/lang/Object;
       9: checkcast     #22                 // class java/lang/Iterable
      12: putfield      #24                 // Field sources:Ljava/lang/Iterable;
      15: return

  public java.io.Reader openStream() throws java.io.IOException;
    Code:
       0: new           #32                 // class org/apache/curator/shaded/com/google/common/io/MultiReader
       3: dup
       4: aload_0
       5: getfield      #24                 // Field sources:Ljava/lang/Iterable;
       8: invokeinterface #36,  1           // InterfaceMethod java/lang/Iterable.iterator:()Ljava/util/Iterator;
      13: invokespecial #39                 // Method org/apache/curator/shaded/com/google/common/io/MultiReader."<init>":(Ljava/util/Iterator;)V
      16: areturn

  public boolean isEmpty() throws java.io.IOException;
    Code:
       0: aload_0
       1: getfield      #24                 // Field sources:Ljava/lang/Iterable;
       4: invokeinterface #36,  1           // InterfaceMethod java/lang/Iterable.iterator:()Ljava/util/Iterator;
       9: astore_1
      10: aload_1
      11: invokeinterface #46,  1           // InterfaceMethod java/util/Iterator.hasNext:()Z
      16: ifeq          41
      19: aload_1
      20: invokeinterface #50,  1           // InterfaceMethod java/util/Iterator.next:()Ljava/lang/Object;
      25: checkcast     #4                  // class org/apache/curator/shaded/com/google/common/io/CharSource
      28: astore_2
      29: aload_2
      30: invokevirtual #52                 // Method org/apache/curator/shaded/com/google/common/io/CharSource.isEmpty:()Z
      33: ifne          38
      36: iconst_0
      37: ireturn
      38: goto          10
      41: iconst_1
      42: ireturn

  public java.lang.String toString();
    Code:
       0: new           #60                 // class java/lang/StringBuilder
       3: dup
       4: invokespecial #61                 // Method java/lang/StringBuilder."<init>":()V
       7: ldc           #63                 // String CharSource.concat(
       9: invokevirtual #67                 // Method java/lang/StringBuilder.append:(Ljava/lang/String;)Ljava/lang/StringBuilder;
      12: aload_0
      13: getfield      #24                 // Field sources:Ljava/lang/Iterable;
      16: invokevirtual #70                 // Method java/lang/StringBuilder.append:(Ljava/lang/Object;)Ljava/lang/StringBuilder;
      19: ldc           #72                 // String )
      21: invokevirtual #67                 // Method java/lang/StringBuilder.append:(Ljava/lang/String;)Ljava/lang/StringBuilder;
      24: invokevirtual #74                 // Method java/lang/StringBuilder.toString:()Ljava/lang/String;
      27: areturn

  public java.lang.Object getInput() throws java.io.IOException;
    Code:
       0: aload_0
       1: invokespecial #77                 // Method org/apache/curator/shaded/com/google/common/io/CharSource.getInput:()Ljava/io/Reader;
       4: areturn
}
