class org.bouncycastle.jce.provider.RFC3280CertPathUtilities {
  private static final org.bouncycastle.jce.provider.PKIXCRLUtil CRL_UTIL;

  public static final java.lang.String CERTIFICATE_POLICIES;

  public static final java.lang.String POLICY_MAPPINGS;

  public static final java.lang.String INHIBIT_ANY_POLICY;

  public static final java.lang.String ISSUING_DISTRIBUTION_POINT;

  public static final java.lang.String FRESHEST_CRL;

  public static final java.lang.String DELTA_CRL_INDICATOR;

  public static final java.lang.String POLICY_CONSTRAINTS;

  public static final java.lang.String BASIC_CONSTRAINTS;

  public static final java.lang.String CRL_DISTRIBUTION_POINTS;

  public static final java.lang.String SUBJECT_ALTERNATIVE_NAME;

  public static final java.lang.String NAME_CONSTRAINTS;

  public static final java.lang.String AUTHORITY_KEY_IDENTIFIER;

  public static final java.lang.String KEY_USAGE;

  public static final java.lang.String CRL_NUMBER;

  public static final java.lang.String ANY_POLICY;

  protected static final int KEY_CERT_SIGN;

  protected static final int CRL_SIGN;

  protected static final java.lang.String[] crlReasons;

  org.bouncycastle.jce.provider.RFC3280CertPathUtilities();
    Code:
       0: aload_0
       1: invokespecial #951                // Method java/lang/Object."<init>":()V
       4: return

  protected static void processCRLB2(org.bouncycastle.asn1.x509.DistributionPoint, java.lang.Object, java.security.cert.X509CRL) throws org.bouncycastle.jce.provider.AnnotatedException;
    Code:
       0: aconst_null
       1: astore_3
       2: aload_2
       3: getstatic     #940                // Field ISSUING_DISTRIBUTION_POINT:Ljava/lang/String;
       6: invokestatic  #1086               // Method org/bouncycastle/jce/provider/CertPathValidatorUtilities.getExtensionValue:(Ljava/security/cert/X509Extension;Ljava/lang/String;)Lorg/bouncycastle/asn1/ASN1Primitive;
       9: invokestatic  #1041               // Method org/bouncycastle/asn1/x509/IssuingDistributionPoint.getInstance:(Ljava/lang/Object;)Lorg/bouncycastle/asn1/x509/IssuingDistributionPoint;
      12: astore_3
      13: goto          30
      16: astore        4
      18: new           #565                // class org/bouncycastle/jce/provider/AnnotatedException
      21: dup
      22: ldc           #35                 // String Issuing distribution point extension could not be decoded.
      24: aload         4
      26: invokespecial #1075               // Method org/bouncycastle/jce/provider/AnnotatedException."<init>":(Ljava/lang/String;Ljava/lang/Throwable;)V
      29: athrow
      30: aload_3
      31: ifnull        702
      34: aload_3
      35: invokevirtual #1039               // Method org/bouncycastle/asn1/x509/IssuingDistributionPoint.getDistributionPoint:()Lorg/bouncycastle/asn1/x509/DistributionPointName;
      38: ifnull        583
      41: aload_3
      42: invokestatic  #1041               // Method org/bouncycastle/asn1/x509/IssuingDistributionPoint.getInstance:(Ljava/lang/Object;)Lorg/bouncycastle/asn1/x509/IssuingDistributionPoint;
      45: invokevirtual #1039               // Method org/bouncycastle/asn1/x509/IssuingDistributionPoint.getDistributionPoint:()Lorg/bouncycastle/asn1/x509/DistributionPointName;
      48: astore        4
      50: new           #521                // class java/util/ArrayList
      53: dup
      54: invokespecial #984                // Method java/util/ArrayList."<init>":()V
      57: astore        5
      59: aload         4
      61: invokevirtual #1023               // Method org/bouncycastle/asn1/x509/DistributionPointName.getType:()I
      64: ifne          110
      67: aload         4
      69: invokevirtual #1024               // Method org/bouncycastle/asn1/x509/DistributionPointName.getName:()Lorg/bouncycastle/asn1/ASN1Encodable;
      72: invokestatic  #1033               // Method org/bouncycastle/asn1/x509/GeneralNames.getInstance:(Ljava/lang/Object;)Lorg/bouncycastle/asn1/x509/GeneralNames;
      75: invokevirtual #1031               // Method org/bouncycastle/asn1/x509/GeneralNames.getNames:()[Lorg/bouncycastle/asn1/x509/GeneralName;
      78: astore        6
      80: iconst_0
      81: istore        7
      83: iload         7
      85: aload         6
      87: arraylength
      88: if_icmpge     110
      91: aload         5
      93: aload         6
      95: iload         7
      97: aaload
      98: invokeinterface #1146,  2         // InterfaceMethod java/util/List.add:(Ljava/lang/Object;)Z
     103: pop
     104: iinc          7, 1
     107: goto          83
     110: aload         4
     112: invokevirtual #1023               // Method org/bouncycastle/asn1/x509/DistributionPointName.getType:()I
     115: iconst_1
     116: if_icmpne     222
     119: new           #533                // class org/bouncycastle/asn1/ASN1EncodableVector
     122: dup
     123: invokespecial #991                // Method org/bouncycastle/asn1/ASN1EncodableVector."<init>":()V
     126: astore        6
     128: aload_2
     129: invokestatic  #1115               // Method org/bouncycastle/jce/provider/PrincipalUtils.getIssuerPrincipal:(Ljava/security/cert/X509CRL;)Lorg/bouncycastle/asn1/x500/X500Name;
     132: invokestatic  #1003               // Method org/bouncycastle/asn1/ASN1Sequence.getInstance:(Ljava/lang/Object;)Lorg/bouncycastle/asn1/ASN1Sequence;
     135: invokevirtual #1001               // Method org/bouncycastle/asn1/ASN1Sequence.getObjects:()Ljava/util/Enumeration;
     138: astore        7
     140: aload         7
     142: invokeinterface #1139,  1         // InterfaceMethod java/util/Enumeration.hasMoreElements:()Z
     147: ifeq          168
     150: aload         6
     152: aload         7
     154: invokeinterface #1140,  1         // InterfaceMethod java/util/Enumeration.nextElement:()Ljava/lang/Object;
     159: checkcast     #532                // class org/bouncycastle/asn1/ASN1Encodable
     162: invokevirtual #992                // Method org/bouncycastle/asn1/ASN1EncodableVector.add:(Lorg/bouncycastle/asn1/ASN1Encodable;)V
     165: goto          140
     168: goto          185
     171: astore        7
     173: new           #565                // class org/bouncycastle/jce/provider/AnnotatedException
     176: dup
     177: ldc           #17                 // String Could not read CRL issuer.
     179: aload         7
     181: invokespecial #1075               // Method org/bouncycastle/jce/provider/AnnotatedException."<init>":(Ljava/lang/String;Ljava/lang/Throwable;)V
     184: athrow
     185: aload         6
     187: aload         4
     189: invokevirtual #1024               // Method org/bouncycastle/asn1/x509/DistributionPointName.getName:()Lorg/bouncycastle/asn1/ASN1Encodable;
     192: invokevirtual #992                // Method org/bouncycastle/asn1/ASN1EncodableVector.add:(Lorg/bouncycastle/asn1/ASN1Encodable;)V
     195: aload         5
     197: new           #550                // class org/bouncycastle/asn1/x509/GeneralName
     200: dup
     201: new           #540                // class org/bouncycastle/asn1/DERSequence
     204: dup
     205: aload         6
     207: invokespecial #1006               // Method org/bouncycastle/asn1/DERSequence."<init>":(Lorg/bouncycastle/asn1/ASN1EncodableVector;)V
     210: invokestatic  #1013               // Method org/bouncycastle/asn1/x500/X500Name.getInstance:(Ljava/lang/Object;)Lorg/bouncycastle/asn1/x500/X500Name;
     213: invokespecial #1030               // Method org/bouncycastle/asn1/x509/GeneralName."<init>":(Lorg/bouncycastle/asn1/x500/X500Name;)V
     216: invokeinterface #1146,  2         // InterfaceMethod java/util/List.add:(Ljava/lang/Object;)Z
     221: pop
     222: iconst_0
     223: istore        6
     225: aload_0
     226: invokevirtual #1019               // Method org/bouncycastle/asn1/x509/DistributionPoint.getDistributionPoint:()Lorg/bouncycastle/asn1/x509/DistributionPointName;
     229: ifnull        504
     232: aload_0
     233: invokevirtual #1019               // Method org/bouncycastle/asn1/x509/DistributionPoint.getDistributionPoint:()Lorg/bouncycastle/asn1/x509/DistributionPointName;
     236: astore        4
     238: aconst_null
     239: astore        7
     241: aload         4
     243: invokevirtual #1023               // Method org/bouncycastle/asn1/x509/DistributionPointName.getType:()I
     246: ifne          262
     249: aload         4
     251: invokevirtual #1024               // Method org/bouncycastle/asn1/x509/DistributionPointName.getName:()Lorg/bouncycastle/asn1/ASN1Encodable;
     254: invokestatic  #1033               // Method org/bouncycastle/asn1/x509/GeneralNames.getInstance:(Ljava/lang/Object;)Lorg/bouncycastle/asn1/x509/GeneralNames;
     257: invokevirtual #1031               // Method org/bouncycastle/asn1/x509/GeneralNames.getNames:()[Lorg/bouncycastle/asn1/x509/GeneralName;
     260: astore        7
     262: aload         4
     264: invokevirtual #1023               // Method org/bouncycastle/asn1/x509/DistributionPointName.getType:()I
     267: iconst_1
     268: if_icmpne     443
     271: aload_0
     272: invokevirtual #1020               // Method org/bouncycastle/asn1/x509/DistributionPoint.getCRLIssuer:()Lorg/bouncycastle/asn1/x509/GeneralNames;
     275: ifnull        290
     278: aload_0
     279: invokevirtual #1020               // Method org/bouncycastle/asn1/x509/DistributionPoint.getCRLIssuer:()Lorg/bouncycastle/asn1/x509/GeneralNames;
     282: invokevirtual #1031               // Method org/bouncycastle/asn1/x509/GeneralNames.getNames:()[Lorg/bouncycastle/asn1/x509/GeneralName;
     285: astore        7
     287: goto          334
     290: iconst_1
     291: anewarray     #550                // class org/bouncycastle/asn1/x509/GeneralName
     294: astore        7
     296: aload         7
     298: iconst_0
     299: new           #550                // class org/bouncycastle/asn1/x509/GeneralName
     302: dup
     303: aload_1
     304: invokestatic  #1114               // Method org/bouncycastle/jce/provider/PrincipalUtils.getEncodedIssuerPrincipal:(Ljava/lang/Object;)Lorg/bouncycastle/asn1/x500/X500Name;
     307: invokevirtual #1010               // Method org/bouncycastle/asn1/x500/X500Name.getEncoded:()[B
     310: invokestatic  #1013               // Method org/bouncycastle/asn1/x500/X500Name.getInstance:(Ljava/lang/Object;)Lorg/bouncycastle/asn1/x500/X500Name;
     313: invokespecial #1030               // Method org/bouncycastle/asn1/x509/GeneralName."<init>":(Lorg/bouncycastle/asn1/x500/X500Name;)V
     316: aastore
     317: goto          334
     320: astore        8
     322: new           #565                // class org/bouncycastle/jce/provider/AnnotatedException
     325: dup
     326: ldc           #18                 // String Could not read certificate issuer.
     328: aload         8
     330: invokespecial #1075               // Method org/bouncycastle/jce/provider/AnnotatedException."<init>":(Ljava/lang/String;Ljava/lang/Throwable;)V
     333: athrow
     334: iconst_0
     335: istore        8
     337: iload         8
     339: aload         7
     341: arraylength
     342: if_icmpge     443
     345: aload         7
     347: iload         8
     349: aaload
     350: invokevirtual #1028               // Method org/bouncycastle/asn1/x509/GeneralName.getName:()Lorg/bouncycastle/asn1/ASN1Encodable;
     353: invokeinterface #1160,  1         // InterfaceMethod org/bouncycastle/asn1/ASN1Encodable.toASN1Primitive:()Lorg/bouncycastle/asn1/ASN1Primitive;
     358: invokestatic  #1003               // Method org/bouncycastle/asn1/ASN1Sequence.getInstance:(Ljava/lang/Object;)Lorg/bouncycastle/asn1/ASN1Sequence;
     361: invokevirtual #1001               // Method org/bouncycastle/asn1/ASN1Sequence.getObjects:()Ljava/util/Enumeration;
     364: astore        9
     366: new           #533                // class org/bouncycastle/asn1/ASN1EncodableVector
     369: dup
     370: invokespecial #991                // Method org/bouncycastle/asn1/ASN1EncodableVector."<init>":()V
     373: astore        10
     375: aload         9
     377: invokeinterface #1139,  1         // InterfaceMethod java/util/Enumeration.hasMoreElements:()Z
     382: ifeq          403
     385: aload         10
     387: aload         9
     389: invokeinterface #1140,  1         // InterfaceMethod java/util/Enumeration.nextElement:()Ljava/lang/Object;
     394: checkcast     #532                // class org/bouncycastle/asn1/ASN1Encodable
     397: invokevirtual #992                // Method org/bouncycastle/asn1/ASN1EncodableVector.add:(Lorg/bouncycastle/asn1/ASN1Encodable;)V
     400: goto          375
     403: aload         10
     405: aload         4
     407: invokevirtual #1024               // Method org/bouncycastle/asn1/x509/DistributionPointName.getName:()Lorg/bouncycastle/asn1/ASN1Encodable;
     410: invokevirtual #992                // Method org/bouncycastle/asn1/ASN1EncodableVector.add:(Lorg/bouncycastle/asn1/ASN1Encodable;)V
     413: aload         7
     415: iload         8
     417: new           #550                // class org/bouncycastle/asn1/x509/GeneralName
     420: dup
     421: new           #540                // class org/bouncycastle/asn1/DERSequence
     424: dup
     425: aload         10
     427: invokespecial #1006               // Method org/bouncycastle/asn1/DERSequence."<init>":(Lorg/bouncycastle/asn1/ASN1EncodableVector;)V
     430: invokestatic  #1013               // Method org/bouncycastle/asn1/x500/X500Name.getInstance:(Ljava/lang/Object;)Lorg/bouncycastle/asn1/x500/X500Name;
     433: invokespecial #1030               // Method org/bouncycastle/asn1/x509/GeneralName."<init>":(Lorg/bouncycastle/asn1/x500/X500Name;)V
     436: aastore
     437: iinc          8, 1
     440: goto          337
     443: aload         7
     445: ifnull        486
     448: iconst_0
     449: istore        8
     451: iload         8
     453: aload         7
     455: arraylength
     456: if_icmpge     486
     459: aload         5
     461: aload         7
     463: iload         8
     465: aaload
     466: invokeinterface #1147,  2         // InterfaceMethod java/util/List.contains:(Ljava/lang/Object;)Z
     471: ifeq          480
     474: iconst_1
     475: istore        6
     477: goto          486
     480: iinc          8, 1
     483: goto          451
     486: iload         6
     488: ifne          501
     491: new           #565                // class org/bouncycastle/jce/provider/AnnotatedException
     494: dup
     495: ldc           #38                 // String No match for certificate CRL issuing distribution point name to cRLIssuer CRL distribution point.
     497: invokespecial #1073               // Method org/bouncycastle/jce/provider/AnnotatedException."<init>":(Ljava/lang/String;)V
     500: athrow
     501: goto          583
     504: aload_0
     505: invokevirtual #1020               // Method org/bouncycastle/asn1/x509/DistributionPoint.getCRLIssuer:()Lorg/bouncycastle/asn1/x509/GeneralNames;
     508: ifnonnull     521
     511: new           #565                // class org/bouncycastle/jce/provider/AnnotatedException
     514: dup
     515: ldc           #25                 // String Either the cRLIssuer or the distributionPoint field must be contained in DistributionPoint.
     517: invokespecial #1073               // Method org/bouncycastle/jce/provider/AnnotatedException."<init>":(Ljava/lang/String;)V
     520: athrow
     521: aload_0
     522: invokevirtual #1020               // Method org/bouncycastle/asn1/x509/DistributionPoint.getCRLIssuer:()Lorg/bouncycastle/asn1/x509/GeneralNames;
     525: invokevirtual #1031               // Method org/bouncycastle/asn1/x509/GeneralNames.getNames:()[Lorg/bouncycastle/asn1/x509/GeneralName;
     528: astore        7
     530: iconst_0
     531: istore        8
     533: iload         8
     535: aload         7
     537: arraylength
     538: if_icmpge     568
     541: aload         5
     543: aload         7
     545: iload         8
     547: aaload
     548: invokeinterface #1147,  2         // InterfaceMethod java/util/List.contains:(Ljava/lang/Object;)Z
     553: ifeq          562
     556: iconst_1
     557: istore        6
     559: goto          568
     562: iinc          8, 1
     565: goto          533
     568: iload         6
     570: ifne          583
     573: new           #565                // class org/bouncycastle/jce/provider/AnnotatedException
     576: dup
     577: ldc           #38                 // String No match for certificate CRL issuing distribution point name to cRLIssuer CRL distribution point.
     579: invokespecial #1073               // Method org/bouncycastle/jce/provider/AnnotatedException."<init>":(Ljava/lang/String;)V
     582: athrow
     583: aconst_null
     584: astore        4
     586: aload_1
     587: checkcast     #519                // class java/security/cert/X509Extension
     590: getstatic     #933                // Field BASIC_CONSTRAINTS:Ljava/lang/String;
     593: invokestatic  #1086               // Method org/bouncycastle/jce/provider/CertPathValidatorUtilities.getExtensionValue:(Ljava/security/cert/X509Extension;Ljava/lang/String;)Lorg/bouncycastle/asn1/ASN1Primitive;
     596: invokestatic  #1016               // Method org/bouncycastle/asn1/x509/BasicConstraints.getInstance:(Ljava/lang/Object;)Lorg/bouncycastle/asn1/x509/BasicConstraints;
     599: astore        4
     601: goto          618
     604: astore        5
     606: new           #565                // class org/bouncycastle/jce/provider/AnnotatedException
     609: dup
     610: ldc           #4                  // String Basic constraints extension could not be decoded.
     612: aload         5
     614: invokespecial #1075               // Method org/bouncycastle/jce/provider/AnnotatedException."<init>":(Ljava/lang/String;Ljava/lang/Throwable;)V
     617: athrow
     618: aload_1
     619: instanceof    #518                // class java/security/cert/X509Certificate
     622: ifeq          685
     625: aload_3
     626: invokevirtual #1037               // Method org/bouncycastle/asn1/x509/IssuingDistributionPoint.onlyContainsUserCerts:()Z
     629: ifeq          655
     632: aload         4
     634: ifnull        655
     637: aload         4
     639: invokevirtual #1014               // Method org/bouncycastle/asn1/x509/BasicConstraints.isCA:()Z
     642: ifeq          655
     645: new           #565                // class org/bouncycastle/jce/provider/AnnotatedException
     648: dup
     649: ldc           #5                  // String CA Cert CRL only contains user certificates.
     651: invokespecial #1073               // Method org/bouncycastle/jce/provider/AnnotatedException."<init>":(Ljava/lang/String;)V
     654: athrow
     655: aload_3
     656: invokevirtual #1036               // Method org/bouncycastle/asn1/x509/IssuingDistributionPoint.onlyContainsCACerts:()Z
     659: ifeq          685
     662: aload         4
     664: ifnull        675
     667: aload         4
     669: invokevirtual #1014               // Method org/bouncycastle/asn1/x509/BasicConstraints.isCA:()Z
     672: ifne          685
     675: new           #565                // class org/bouncycastle/jce/provider/AnnotatedException
     678: dup
     679: ldc           #26                 // String End CRL only contains CA certificates.
     681: invokespecial #1073               // Method org/bouncycastle/jce/provider/AnnotatedException."<init>":(Ljava/lang/String;)V
     684: athrow
     685: aload_3
     686: invokevirtual #1035               // Method org/bouncycastle/asn1/x509/IssuingDistributionPoint.onlyContainsAttributeCerts:()Z
     689: ifeq          702
     692: new           #565                // class org/bouncycastle/jce/provider/AnnotatedException
     695: dup
     696: ldc           #55                 // String onlyContainsAttributeCerts boolean is asserted.
     698: invokespecial #1073               // Method org/bouncycastle/jce/provider/AnnotatedException."<init>":(Ljava/lang/String;)V
     701: athrow
     702: return
    Exception table:
       from    to  target type
           2    13    16   Class java/lang/Exception
         128   168   171   Class java/lang/Exception
         296   317   320   Class java/lang/Exception
         586   601   604   Class java/lang/Exception

  protected static void processCRLB1(org.bouncycastle.asn1.x509.DistributionPoint, java.lang.Object, java.security.cert.X509CRL) throws org.bouncycastle.jce.provider.AnnotatedException;
    Code:
       0: aload_2
       1: getstatic     #940                // Field ISSUING_DISTRIBUTION_POINT:Ljava/lang/String;
       4: invokestatic  #1086               // Method org/bouncycastle/jce/provider/CertPathValidatorUtilities.getExtensionValue:(Ljava/security/cert/X509Extension;Ljava/lang/String;)Lorg/bouncycastle/asn1/ASN1Primitive;
       7: astore_3
       8: iconst_0
       9: istore        4
      11: aload_3
      12: ifnull        28
      15: aload_3
      16: invokestatic  #1041               // Method org/bouncycastle/asn1/x509/IssuingDistributionPoint.getInstance:(Ljava/lang/Object;)Lorg/bouncycastle/asn1/x509/IssuingDistributionPoint;
      19: invokevirtual #1034               // Method org/bouncycastle/asn1/x509/IssuingDistributionPoint.isIndirectCRL:()Z
      22: ifeq          28
      25: iconst_1
      26: istore        4
      28: aload_2
      29: invokestatic  #1115               // Method org/bouncycastle/jce/provider/PrincipalUtils.getIssuerPrincipal:(Ljava/security/cert/X509CRL;)Lorg/bouncycastle/asn1/x500/X500Name;
      32: invokevirtual #1010               // Method org/bouncycastle/asn1/x500/X500Name.getEncoded:()[B
      35: astore        5
      37: goto          75
      40: astore        6
      42: new           #565                // class org/bouncycastle/jce/provider/AnnotatedException
      45: dup
      46: new           #503                // class java/lang/StringBuilder
      49: dup
      50: invokespecial #953                // Method java/lang/StringBuilder."<init>":()V
      53: ldc           #27                 // String Exception encoding CRL issuer:
      55: invokevirtual #956                // Method java/lang/StringBuilder.append:(Ljava/lang/String;)Ljava/lang/StringBuilder;
      58: aload         6
      60: invokevirtual #949                // Method java/io/IOException.getMessage:()Ljava/lang/String;
      63: invokevirtual #956                // Method java/lang/StringBuilder.append:(Ljava/lang/String;)Ljava/lang/StringBuilder;
      66: invokevirtual #954                // Method java/lang/StringBuilder.toString:()Ljava/lang/String;
      69: aload         6
      71: invokespecial #1075               // Method org/bouncycastle/jce/provider/AnnotatedException."<init>":(Ljava/lang/String;Ljava/lang/Throwable;)V
      74: athrow
      75: iconst_0
      76: istore        6
      78: aload_0
      79: invokevirtual #1020               // Method org/bouncycastle/asn1/x509/DistributionPoint.getCRLIssuer:()Lorg/bouncycastle/asn1/x509/GeneralNames;
      82: ifnull        205
      85: aload_0
      86: invokevirtual #1020               // Method org/bouncycastle/asn1/x509/DistributionPoint.getCRLIssuer:()Lorg/bouncycastle/asn1/x509/GeneralNames;
      89: invokevirtual #1031               // Method org/bouncycastle/asn1/x509/GeneralNames.getNames:()[Lorg/bouncycastle/asn1/x509/GeneralName;
      92: astore        7
      94: iconst_0
      95: istore        8
      97: iload         8
      99: aload         7
     101: arraylength
     102: if_icmpge     167
     105: aload         7
     107: iload         8
     109: aaload
     110: invokevirtual #1026               // Method org/bouncycastle/asn1/x509/GeneralName.getTagNo:()I
     113: iconst_4
     114: if_icmpne     161
     117: aload         7
     119: iload         8
     121: aaload
     122: invokevirtual #1028               // Method org/bouncycastle/asn1/x509/GeneralName.getName:()Lorg/bouncycastle/asn1/ASN1Encodable;
     125: invokeinterface #1160,  1         // InterfaceMethod org/bouncycastle/asn1/ASN1Encodable.toASN1Primitive:()Lorg/bouncycastle/asn1/ASN1Primitive;
     130: invokevirtual #998                // Method org/bouncycastle/asn1/ASN1Primitive.getEncoded:()[B
     133: aload         5
     135: invokestatic  #1134               // Method org/bouncycastle/util/Arrays.areEqual:([B[B)Z
     138: ifeq          144
     141: iconst_1
     142: istore        6
     144: goto          161
     147: astore        9
     149: new           #565                // class org/bouncycastle/jce/provider/AnnotatedException
     152: dup
     153: ldc           #7                  // String CRL issuer information from distribution point cannot be decoded.
     155: aload         9
     157: invokespecial #1075               // Method org/bouncycastle/jce/provider/AnnotatedException."<init>":(Ljava/lang/String;Ljava/lang/Throwable;)V
     160: athrow
     161: iinc          8, 1
     164: goto          97
     167: iload         6
     169: ifeq          187
     172: iload         4
     174: ifne          187
     177: new           #565                // class org/bouncycastle/jce/provider/AnnotatedException
     180: dup
     181: ldc           #24                 // String Distribution point contains cRLIssuer field but CRL is not indirect.
     183: invokespecial #1073               // Method org/bouncycastle/jce/provider/AnnotatedException."<init>":(Ljava/lang/String;)V
     186: athrow
     187: iload         6
     189: ifne          202
     192: new           #565                // class org/bouncycastle/jce/provider/AnnotatedException
     195: dup
     196: ldc           #8                  // String CRL issuer of CRL does not match CRL issuer of distribution point.
     198: invokespecial #1073               // Method org/bouncycastle/jce/provider/AnnotatedException."<init>":(Ljava/lang/String;)V
     201: athrow
     202: goto          222
     205: aload_2
     206: invokestatic  #1115               // Method org/bouncycastle/jce/provider/PrincipalUtils.getIssuerPrincipal:(Ljava/security/cert/X509CRL;)Lorg/bouncycastle/asn1/x500/X500Name;
     209: aload_1
     210: invokestatic  #1114               // Method org/bouncycastle/jce/provider/PrincipalUtils.getEncodedIssuerPrincipal:(Ljava/lang/Object;)Lorg/bouncycastle/asn1/x500/X500Name;
     213: invokevirtual #1011               // Method org/bouncycastle/asn1/x500/X500Name.equals:(Ljava/lang/Object;)Z
     216: ifeq          222
     219: iconst_1
     220: istore        6
     222: iload         6
     224: ifne          237
     227: new           #565                // class org/bouncycastle/jce/provider/AnnotatedException
     230: dup
     231: ldc           #11                 // String Cannot find matching CRL issuer for certificate.
     233: invokespecial #1073               // Method org/bouncycastle/jce/provider/AnnotatedException."<init>":(Ljava/lang/String;)V
     236: athrow
     237: return
    Exception table:
       from    to  target type
          28    37    40   Class java/io/IOException
         117   144   147   Class java/io/IOException

  protected static org.bouncycastle.jce.provider.ReasonsMask processCRLD(java.security.cert.X509CRL, org.bouncycastle.asn1.x509.DistributionPoint) throws org.bouncycastle.jce.provider.AnnotatedException;
    Code:
       0: aconst_null
       1: astore_2
       2: aload_0
       3: getstatic     #940                // Field ISSUING_DISTRIBUTION_POINT:Ljava/lang/String;
       6: invokestatic  #1086               // Method org/bouncycastle/jce/provider/CertPathValidatorUtilities.getExtensionValue:(Ljava/security/cert/X509Extension;Ljava/lang/String;)Lorg/bouncycastle/asn1/ASN1Primitive;
       9: invokestatic  #1041               // Method org/bouncycastle/asn1/x509/IssuingDistributionPoint.getInstance:(Ljava/lang/Object;)Lorg/bouncycastle/asn1/x509/IssuingDistributionPoint;
      12: astore_2
      13: goto          28
      16: astore_3
      17: new           #565                // class org/bouncycastle/jce/provider/AnnotatedException
      20: dup
      21: ldc           #35                 // String Issuing distribution point extension could not be decoded.
      23: aload_3
      24: invokespecial #1075               // Method org/bouncycastle/jce/provider/AnnotatedException."<init>":(Ljava/lang/String;Ljava/lang/Throwable;)V
      27: athrow
      28: aload_2
      29: ifnull        72
      32: aload_2
      33: invokevirtual #1040               // Method org/bouncycastle/asn1/x509/IssuingDistributionPoint.getOnlySomeReasons:()Lorg/bouncycastle/asn1/x509/ReasonFlags;
      36: ifnull        72
      39: aload_1
      40: invokevirtual #1021               // Method org/bouncycastle/asn1/x509/DistributionPoint.getReasons:()Lorg/bouncycastle/asn1/x509/ReasonFlags;
      43: ifnull        72
      46: new           #575                // class org/bouncycastle/jce/provider/ReasonsMask
      49: dup
      50: aload_1
      51: invokevirtual #1021               // Method org/bouncycastle/asn1/x509/DistributionPoint.getReasons:()Lorg/bouncycastle/asn1/x509/ReasonFlags;
      54: invokespecial #1130               // Method org/bouncycastle/jce/provider/ReasonsMask."<init>":(Lorg/bouncycastle/asn1/x509/ReasonFlags;)V
      57: new           #575                // class org/bouncycastle/jce/provider/ReasonsMask
      60: dup
      61: aload_2
      62: invokevirtual #1040               // Method org/bouncycastle/asn1/x509/IssuingDistributionPoint.getOnlySomeReasons:()Lorg/bouncycastle/asn1/x509/ReasonFlags;
      65: invokespecial #1130               // Method org/bouncycastle/jce/provider/ReasonsMask."<init>":(Lorg/bouncycastle/asn1/x509/ReasonFlags;)V
      68: invokevirtual #1133               // Method org/bouncycastle/jce/provider/ReasonsMask.intersect:(Lorg/bouncycastle/jce/provider/ReasonsMask;)Lorg/bouncycastle/jce/provider/ReasonsMask;
      71: areturn
      72: aload_2
      73: ifnull        83
      76: aload_2
      77: invokevirtual #1040               // Method org/bouncycastle/asn1/x509/IssuingDistributionPoint.getOnlySomeReasons:()Lorg/bouncycastle/asn1/x509/ReasonFlags;
      80: ifnonnull     94
      83: aload_1
      84: invokevirtual #1021               // Method org/bouncycastle/asn1/x509/DistributionPoint.getReasons:()Lorg/bouncycastle/asn1/x509/ReasonFlags;
      87: ifnonnull     94
      90: getstatic     #948                // Field org/bouncycastle/jce/provider/ReasonsMask.allReasons:Lorg/bouncycastle/jce/provider/ReasonsMask;
      93: areturn
      94: aload_1
      95: invokevirtual #1021               // Method org/bouncycastle/asn1/x509/DistributionPoint.getReasons:()Lorg/bouncycastle/asn1/x509/ReasonFlags;
      98: ifnonnull     107
     101: getstatic     #948                // Field org/bouncycastle/jce/provider/ReasonsMask.allReasons:Lorg/bouncycastle/jce/provider/ReasonsMask;
     104: goto          118
     107: new           #575                // class org/bouncycastle/jce/provider/ReasonsMask
     110: dup
     111: aload_1
     112: invokevirtual #1021               // Method org/bouncycastle/asn1/x509/DistributionPoint.getReasons:()Lorg/bouncycastle/asn1/x509/ReasonFlags;
     115: invokespecial #1130               // Method org/bouncycastle/jce/provider/ReasonsMask."<init>":(Lorg/bouncycastle/asn1/x509/ReasonFlags;)V
     118: aload_2
     119: ifnonnull     128
     122: getstatic     #948                // Field org/bouncycastle/jce/provider/ReasonsMask.allReasons:Lorg/bouncycastle/jce/provider/ReasonsMask;
     125: goto          139
     128: new           #575                // class org/bouncycastle/jce/provider/ReasonsMask
     131: dup
     132: aload_2
     133: invokevirtual #1040               // Method org/bouncycastle/asn1/x509/IssuingDistributionPoint.getOnlySomeReasons:()Lorg/bouncycastle/asn1/x509/ReasonFlags;
     136: invokespecial #1130               // Method org/bouncycastle/jce/provider/ReasonsMask."<init>":(Lorg/bouncycastle/asn1/x509/ReasonFlags;)V
     139: invokevirtual #1133               // Method org/bouncycastle/jce/provider/ReasonsMask.intersect:(Lorg/bouncycastle/jce/provider/ReasonsMask;)Lorg/bouncycastle/jce/provider/ReasonsMask;
     142: areturn
    Exception table:
       from    to  target type
           2    13    16   Class java/lang/Exception

  protected static java.util.Set processCRLF(java.security.cert.X509CRL, java.lang.Object, java.security.cert.X509Certificate, java.security.PublicKey, org.bouncycastle.jcajce.PKIXExtendedParameters, java.util.List, org.bouncycastle.jcajce.util.JcaJceHelper) throws org.bouncycastle.jce.provider.AnnotatedException;
    Code:
       0: new           #517                // class java/security/cert/X509CertSelector
       3: dup
       4: invokespecial #973                // Method java/security/cert/X509CertSelector."<init>":()V
       7: astore        7
       9: aload_0
      10: invokestatic  #1115               // Method org/bouncycastle/jce/provider/PrincipalUtils.getIssuerPrincipal:(Ljava/security/cert/X509CRL;)Lorg/bouncycastle/asn1/x500/X500Name;
      13: invokevirtual #1010               // Method org/bouncycastle/asn1/x500/X500Name.getEncoded:()[B
      16: astore        8
      18: aload         7
      20: aload         8
      22: invokevirtual #974                // Method java/security/cert/X509CertSelector.setSubject:([B)V
      25: goto          42
      28: astore        8
      30: new           #565                // class org/bouncycastle/jce/provider/AnnotatedException
      33: dup
      34: ldc           #49                 // String Subject criteria for certificate selector to find issuer certificate for CRL could not be set.
      36: aload         8
      38: invokespecial #1075               // Method org/bouncycastle/jce/provider/AnnotatedException."<init>":(Ljava/lang/String;Ljava/lang/Throwable;)V
      41: athrow
      42: new           #559                // class org/bouncycastle/jcajce/PKIXCertStoreSelector$Builder
      45: dup
      46: aload         7
      48: invokespecial #1051               // Method org/bouncycastle/jcajce/PKIXCertStoreSelector$Builder."<init>":(Ljava/security/cert/CertSelector;)V
      51: invokevirtual #1052               // Method org/bouncycastle/jcajce/PKIXCertStoreSelector$Builder.build:()Lorg/bouncycastle/jcajce/PKIXCertStoreSelector;
      54: astore        8
      56: aload         8
      58: aload         4
      60: invokevirtual #1064               // Method org/bouncycastle/jcajce/PKIXExtendedParameters.getCertificateStores:()Ljava/util/List;
      63: invokestatic  #1081               // Method org/bouncycastle/jce/provider/CertPathValidatorUtilities.findCertificates:(Lorg/bouncycastle/jcajce/PKIXCertStoreSelector;Ljava/util/List;)Ljava/util/Collection;
      66: astore        9
      68: aload         9
      70: aload         8
      72: aload         4
      74: invokevirtual #1063               // Method org/bouncycastle/jcajce/PKIXExtendedParameters.getCertStores:()Ljava/util/List;
      77: invokestatic  #1081               // Method org/bouncycastle/jce/provider/CertPathValidatorUtilities.findCertificates:(Lorg/bouncycastle/jcajce/PKIXCertStoreSelector;Ljava/util/List;)Ljava/util/Collection;
      80: invokeinterface #1137,  2         // InterfaceMethod java/util/Collection.addAll:(Ljava/util/Collection;)Z
      85: pop
      86: goto          103
      89: astore        10
      91: new           #565                // class org/bouncycastle/jce/provider/AnnotatedException
      94: dup
      95: ldc           #32                 // String Issuer certificate for CRL cannot be searched.
      97: aload         10
      99: invokespecial #1075               // Method org/bouncycastle/jce/provider/AnnotatedException."<init>":(Ljava/lang/String;Ljava/lang/Throwable;)V
     102: athrow
     103: aload         9
     105: aload_2
     106: invokeinterface #1136,  2         // InterfaceMethod java/util/Collection.add:(Ljava/lang/Object;)Z
     111: pop
     112: aload         9
     114: invokeinterface #1138,  1         // InterfaceMethod java/util/Collection.iterator:()Ljava/util/Iterator;
     119: astore        10
     121: new           #521                // class java/util/ArrayList
     124: dup
     125: invokespecial #984                // Method java/util/ArrayList."<init>":()V
     128: astore        11
     130: new           #521                // class java/util/ArrayList
     133: dup
     134: invokespecial #984                // Method java/util/ArrayList."<init>":()V
     137: astore        12
     139: aload         10
     141: invokeinterface #1142,  1         // InterfaceMethod java/util/Iterator.hasNext:()Z
     146: ifeq          380
     149: aload         10
     151: invokeinterface #1143,  1         // InterfaceMethod java/util/Iterator.next:()Ljava/lang/Object;
     156: checkcast     #518                // class java/security/cert/X509Certificate
     159: astore        13
     161: aload         13
     163: aload_2
     164: invokevirtual #977                // Method java/security/cert/X509Certificate.equals:(Ljava/lang/Object;)Z
     167: ifeq          192
     170: aload         11
     172: aload         13
     174: invokeinterface #1146,  2         // InterfaceMethod java/util/List.add:(Ljava/lang/Object;)Z
     179: pop
     180: aload         12
     182: aload_3
     183: invokeinterface #1146,  2         // InterfaceMethod java/util/List.add:(Ljava/lang/Object;)Z
     188: pop
     189: goto          139
     192: new           #569                // class org/bouncycastle/jce/provider/PKIXCertPathBuilderSpi
     195: dup
     196: iconst_1
     197: invokespecial #1097               // Method org/bouncycastle/jce/provider/PKIXCertPathBuilderSpi."<init>":(Z)V
     200: astore        14
     202: new           #517                // class java/security/cert/X509CertSelector
     205: dup
     206: invokespecial #973                // Method java/security/cert/X509CertSelector."<init>":()V
     209: astore        15
     211: aload         15
     213: aload         13
     215: invokevirtual #975                // Method java/security/cert/X509CertSelector.setCertificate:(Ljava/security/cert/X509Certificate;)V
     218: new           #563                // class org/bouncycastle/jcajce/PKIXExtendedParameters$Builder
     221: dup
     222: aload         4
     224: invokespecial #1068               // Method org/bouncycastle/jcajce/PKIXExtendedParameters$Builder."<init>":(Lorg/bouncycastle/jcajce/PKIXExtendedParameters;)V
     227: new           #559                // class org/bouncycastle/jcajce/PKIXCertStoreSelector$Builder
     230: dup
     231: aload         15
     233: invokespecial #1051               // Method org/bouncycastle/jcajce/PKIXCertStoreSelector$Builder."<init>":(Ljava/security/cert/CertSelector;)V
     236: invokevirtual #1052               // Method org/bouncycastle/jcajce/PKIXCertStoreSelector$Builder.build:()Lorg/bouncycastle/jcajce/PKIXCertStoreSelector;
     239: invokevirtual #1070               // Method org/bouncycastle/jcajce/PKIXExtendedParameters$Builder.setTargetConstraints:(Lorg/bouncycastle/jcajce/PKIXCertStoreSelector;)Lorg/bouncycastle/jcajce/PKIXExtendedParameters$Builder;
     242: astore        16
     244: aload         5
     246: aload         13
     248: invokeinterface #1147,  2         // InterfaceMethod java/util/List.contains:(Ljava/lang/Object;)Z
     253: ifeq          265
     256: aload         16
     258: iconst_0
     259: invokevirtual #1066               // Method org/bouncycastle/jcajce/PKIXExtendedParameters$Builder.setRevocationEnabled:(Z)V
     262: goto          271
     265: aload         16
     267: iconst_1
     268: invokevirtual #1066               // Method org/bouncycastle/jcajce/PKIXExtendedParameters$Builder.setRevocationEnabled:(Z)V
     271: new           #561                // class org/bouncycastle/jcajce/PKIXExtendedBuilderParameters$Builder
     274: dup
     275: aload         16
     277: invokevirtual #1067               // Method org/bouncycastle/jcajce/PKIXExtendedParameters$Builder.build:()Lorg/bouncycastle/jcajce/PKIXExtendedParameters;
     280: invokespecial #1054               // Method org/bouncycastle/jcajce/PKIXExtendedBuilderParameters$Builder."<init>":(Lorg/bouncycastle/jcajce/PKIXExtendedParameters;)V
     283: invokevirtual #1053               // Method org/bouncycastle/jcajce/PKIXExtendedBuilderParameters$Builder.build:()Lorg/bouncycastle/jcajce/PKIXExtendedBuilderParameters;
     286: astore        17
     288: aload         14
     290: aload         17
     292: invokevirtual #1098               // Method org/bouncycastle/jce/provider/PKIXCertPathBuilderSpi.engineBuild:(Ljava/security/cert/CertPathParameters;)Ljava/security/cert/CertPathBuilderResult;
     295: invokeinterface #1135,  1         // InterfaceMethod java/security/cert/CertPathBuilderResult.getCertPath:()Ljava/security/cert/CertPath;
     300: invokevirtual #959                // Method java/security/cert/CertPath.getCertificates:()Ljava/util/List;
     303: astore        18
     305: aload         11
     307: aload         13
     309: invokeinterface #1146,  2         // InterfaceMethod java/util/List.add:(Ljava/lang/Object;)Z
     314: pop
     315: aload         12
     317: aload         18
     319: iconst_0
     320: aload         6
     322: invokestatic  #1080               // Method org/bouncycastle/jce/provider/CertPathValidatorUtilities.getNextWorkingKey:(Ljava/util/List;ILorg/bouncycastle/jcajce/util/JcaJceHelper;)Ljava/security/PublicKey;
     325: invokeinterface #1146,  2         // InterfaceMethod java/util/List.add:(Ljava/lang/Object;)Z
     330: pop
     331: goto          377
     334: astore        14
     336: new           #565                // class org/bouncycastle/jce/provider/AnnotatedException
     339: dup
     340: ldc           #14                 // String CertPath for CRL signer failed to validate.
     342: aload         14
     344: invokespecial #1075               // Method org/bouncycastle/jce/provider/AnnotatedException."<init>":(Ljava/lang/String;Ljava/lang/Throwable;)V
     347: athrow
     348: astore        14
     350: new           #565                // class org/bouncycastle/jce/provider/AnnotatedException
     353: dup
     354: ldc           #46                 // String Public key of issuer certificate of CRL could not be retrieved.
     356: aload         14
     358: invokespecial #1075               // Method org/bouncycastle/jce/provider/AnnotatedException."<init>":(Ljava/lang/String;Ljava/lang/Throwable;)V
     361: athrow
     362: astore        14
     364: new           #565                // class org/bouncycastle/jce/provider/AnnotatedException
     367: dup
     368: aload         14
     370: invokevirtual #950                // Method java/lang/Exception.getMessage:()Ljava/lang/String;
     373: invokespecial #1073               // Method org/bouncycastle/jce/provider/AnnotatedException."<init>":(Ljava/lang/String;)V
     376: athrow
     377: goto          139
     380: new           #526                // class java/util/HashSet
     383: dup
     384: invokespecial #988                // Method java/util/HashSet."<init>":()V
     387: astore        13
     389: aconst_null
     390: astore        14
     392: iconst_0
     393: istore        15
     395: iload         15
     397: aload         11
     399: invokeinterface #1144,  1         // InterfaceMethod java/util/List.size:()I
     404: if_icmpge     486
     407: aload         11
     409: iload         15
     411: invokeinterface #1145,  2         // InterfaceMethod java/util/List.get:(I)Ljava/lang/Object;
     416: checkcast     #518                // class java/security/cert/X509Certificate
     419: astore        16
     421: aload         16
     423: invokevirtual #976                // Method java/security/cert/X509Certificate.getKeyUsage:()[Z
     426: astore        17
     428: aload         17
     430: ifnull        463
     433: aload         17
     435: arraylength
     436: bipush        7
     438: if_icmplt     449
     441: aload         17
     443: bipush        6
     445: baload
     446: ifne          463
     449: new           #565                // class org/bouncycastle/jce/provider/AnnotatedException
     452: dup
     453: ldc           #33                 // String Issuer certificate key usage extension does not permit CRL signing.
     455: invokespecial #1073               // Method org/bouncycastle/jce/provider/AnnotatedException."<init>":(Ljava/lang/String;)V
     458: astore        14
     460: goto          480
     463: aload         13
     465: aload         12
     467: iload         15
     469: invokeinterface #1145,  2         // InterfaceMethod java/util/List.get:(I)Ljava/lang/Object;
     474: invokeinterface #1155,  2         // InterfaceMethod java/util/Set.add:(Ljava/lang/Object;)Z
     479: pop
     480: iinc          15, 1
     483: goto          395
     486: aload         13
     488: invokeinterface #1154,  1         // InterfaceMethod java/util/Set.isEmpty:()Z
     493: ifeq          511
     496: aload         14
     498: ifnonnull     511
     501: new           #565                // class org/bouncycastle/jce/provider/AnnotatedException
     504: dup
     505: ldc           #10                 // String Cannot find a valid issuer certificate.
     507: invokespecial #1073               // Method org/bouncycastle/jce/provider/AnnotatedException."<init>":(Ljava/lang/String;)V
     510: athrow
     511: aload         13
     513: invokeinterface #1154,  1         // InterfaceMethod java/util/Set.isEmpty:()Z
     518: ifeq          529
     521: aload         14
     523: ifnull        529
     526: aload         14
     528: athrow
     529: aload         13
     531: areturn
    Exception table:
       from    to  target type
           9    25    28   Class java/io/IOException
          56    86    89   Class org/bouncycastle/jce/provider/AnnotatedException
         192   331   334   Class java/security/cert/CertPathBuilderException
         192   331   348   Class java/security/cert/CertPathValidatorException
         192   331   362   Class java/lang/Exception

  protected static java.security.PublicKey processCRLG(java.security.cert.X509CRL, java.util.Set) throws org.bouncycastle.jce.provider.AnnotatedException;
    Code:
       0: aconst_null
       1: astore_2
       2: aload_1
       3: invokeinterface #1159,  1         // InterfaceMethod java/util/Set.iterator:()Ljava/util/Iterator;
       8: astore_3
       9: aload_3
      10: invokeinterface #1142,  1         // InterfaceMethod java/util/Iterator.hasNext:()Z
      15: ifeq          46
      18: aload_3
      19: invokeinterface #1143,  1         // InterfaceMethod java/util/Iterator.next:()Ljava/lang/Object;
      24: checkcast     #507                // class java/security/PublicKey
      27: astore        4
      29: aload_0
      30: aload         4
      32: invokevirtual #967                // Method java/security/cert/X509CRL.verify:(Ljava/security/PublicKey;)V
      35: aload         4
      37: areturn
      38: astore        5
      40: aload         5
      42: astore_2
      43: goto          9
      46: new           #565                // class org/bouncycastle/jce/provider/AnnotatedException
      49: dup
      50: ldc           #12                 // String Cannot verify CRL.
      52: aload_2
      53: invokespecial #1075               // Method org/bouncycastle/jce/provider/AnnotatedException."<init>":(Ljava/lang/String;Ljava/lang/Throwable;)V
      56: athrow
    Exception table:
       from    to  target type
          29    37    38   Class java/lang/Exception

  protected static java.security.cert.X509CRL processCRLH(java.util.Set, java.security.PublicKey) throws org.bouncycastle.jce.provider.AnnotatedException;
    Code:
       0: aconst_null
       1: astore_2
       2: aload_0
       3: invokeinterface #1159,  1         // InterfaceMethod java/util/Set.iterator:()Ljava/util/Iterator;
       8: astore_3
       9: aload_3
      10: invokeinterface #1142,  1         // InterfaceMethod java/util/Iterator.hasNext:()Z
      15: ifeq          46
      18: aload_3
      19: invokeinterface #1143,  1         // InterfaceMethod java/util/Iterator.next:()Ljava/lang/Object;
      24: checkcast     #515                // class java/security/cert/X509CRL
      27: astore        4
      29: aload         4
      31: aload_1
      32: invokevirtual #967                // Method java/security/cert/X509CRL.verify:(Ljava/security/PublicKey;)V
      35: aload         4
      37: areturn
      38: astore        5
      40: aload         5
      42: astore_2
      43: goto          9
      46: aload_2
      47: ifnull        61
      50: new           #565                // class org/bouncycastle/jce/provider/AnnotatedException
      53: dup
      54: ldc           #13                 // String Cannot verify delta CRL.
      56: aload_2
      57: invokespecial #1075               // Method org/bouncycastle/jce/provider/AnnotatedException."<init>":(Ljava/lang/String;Ljava/lang/Throwable;)V
      60: athrow
      61: aconst_null
      62: areturn
    Exception table:
       from    to  target type
          29    37    38   Class java/lang/Exception

  protected static java.util.Set processCRLA1i(java.util.Date, org.bouncycastle.jcajce.PKIXExtendedParameters, java.security.cert.X509Certificate, java.security.cert.X509CRL) throws org.bouncycastle.jce.provider.AnnotatedException;
    Code:
       0: new           #526                // class java/util/HashSet
       3: dup
       4: invokespecial #988                // Method java/util/HashSet."<init>":()V
       7: astore        4
       9: aload_1
      10: invokevirtual #1058               // Method org/bouncycastle/jcajce/PKIXExtendedParameters.isUseDeltasEnabled:()Z
      13: ifeq          178
      16: aconst_null
      17: astore        5
      19: aload_2
      20: getstatic     #938                // Field FRESHEST_CRL:Ljava/lang/String;
      23: invokestatic  #1086               // Method org/bouncycastle/jce/provider/CertPathValidatorUtilities.getExtensionValue:(Ljava/security/cert/X509Extension;Ljava/lang/String;)Lorg/bouncycastle/asn1/ASN1Primitive;
      26: invokestatic  #1018               // Method org/bouncycastle/asn1/x509/CRLDistPoint.getInstance:(Ljava/lang/Object;)Lorg/bouncycastle/asn1/x509/CRLDistPoint;
      29: astore        5
      31: goto          48
      34: astore        6
      36: new           #565                // class org/bouncycastle/jce/provider/AnnotatedException
      39: dup
      40: ldc           #31                 // String Freshest CRL extension could not be decoded from certificate.
      42: aload         6
      44: invokespecial #1075               // Method org/bouncycastle/jce/provider/AnnotatedException."<init>":(Ljava/lang/String;Ljava/lang/Throwable;)V
      47: athrow
      48: aload         5
      50: ifnonnull     82
      53: aload_3
      54: getstatic     #938                // Field FRESHEST_CRL:Ljava/lang/String;
      57: invokestatic  #1086               // Method org/bouncycastle/jce/provider/CertPathValidatorUtilities.getExtensionValue:(Ljava/security/cert/X509Extension;Ljava/lang/String;)Lorg/bouncycastle/asn1/ASN1Primitive;
      60: invokestatic  #1018               // Method org/bouncycastle/asn1/x509/CRLDistPoint.getInstance:(Ljava/lang/Object;)Lorg/bouncycastle/asn1/x509/CRLDistPoint;
      63: astore        5
      65: goto          82
      68: astore        6
      70: new           #565                // class org/bouncycastle/jce/provider/AnnotatedException
      73: dup
      74: ldc           #30                 // String Freshest CRL extension could not be decoded from CRL.
      76: aload         6
      78: invokespecial #1075               // Method org/bouncycastle/jce/provider/AnnotatedException."<init>":(Ljava/lang/String;Ljava/lang/Throwable;)V
      81: athrow
      82: aload         5
      84: ifnull        178
      87: new           #521                // class java/util/ArrayList
      90: dup
      91: invokespecial #984                // Method java/util/ArrayList."<init>":()V
      94: astore        6
      96: aload         6
      98: aload_1
      99: invokevirtual #1062               // Method org/bouncycastle/jcajce/PKIXExtendedParameters.getCRLStores:()Ljava/util/List;
     102: invokeinterface #1148,  2         // InterfaceMethod java/util/List.addAll:(Ljava/util/Collection;)Z
     107: pop
     108: aload         6
     110: aload         5
     112: aload_1
     113: invokevirtual #1065               // Method org/bouncycastle/jcajce/PKIXExtendedParameters.getNamedCRLStoreMap:()Ljava/util/Map;
     116: invokestatic  #1083               // Method org/bouncycastle/jce/provider/CertPathValidatorUtilities.getAdditionalStoresFromCRLDistributionPoint:(Lorg/bouncycastle/asn1/x509/CRLDistPoint;Ljava/util/Map;)Ljava/util/List;
     119: invokeinterface #1148,  2         // InterfaceMethod java/util/List.addAll:(Ljava/util/Collection;)Z
     124: pop
     125: goto          142
     128: astore        7
     130: new           #565                // class org/bouncycastle/jce/provider/AnnotatedException
     133: dup
     134: ldc           #39                 // String No new delta CRL locations could be added from Freshest CRL extension.
     136: aload         7
     138: invokespecial #1075               // Method org/bouncycastle/jce/provider/AnnotatedException."<init>":(Ljava/lang/String;Ljava/lang/Throwable;)V
     141: athrow
     142: aload         4
     144: aload_0
     145: aload_3
     146: aload_1
     147: invokevirtual #1063               // Method org/bouncycastle/jcajce/PKIXExtendedParameters.getCertStores:()Ljava/util/List;
     150: aload         6
     152: invokestatic  #1089               // Method org/bouncycastle/jce/provider/CertPathValidatorUtilities.getDeltaCRLs:(Ljava/util/Date;Ljava/security/cert/X509CRL;Ljava/util/List;Ljava/util/List;)Ljava/util/Set;
     155: invokeinterface #1158,  2         // InterfaceMethod java/util/Set.addAll:(Ljava/util/Collection;)Z
     160: pop
     161: goto          178
     164: astore        7
     166: new           #565                // class org/bouncycastle/jce/provider/AnnotatedException
     169: dup
     170: ldc           #29                 // String Exception obtaining delta CRLs.
     172: aload         7
     174: invokespecial #1075               // Method org/bouncycastle/jce/provider/AnnotatedException."<init>":(Ljava/lang/String;Ljava/lang/Throwable;)V
     177: athrow
     178: aload         4
     180: areturn
    Exception table:
       from    to  target type
          19    31    34   Class org/bouncycastle/jce/provider/AnnotatedException
          53    65    68   Class org/bouncycastle/jce/provider/AnnotatedException
         108   125   128   Class org/bouncycastle/jce/provider/AnnotatedException
         142   161   164   Class org/bouncycastle/jce/provider/AnnotatedException

  protected static java.util.Set[] processCRLA1ii(java.util.Date, org.bouncycastle.jcajce.PKIXExtendedParameters, java.security.cert.X509Certificate, java.security.cert.X509CRL) throws org.bouncycastle.jce.provider.AnnotatedException;
    Code:
       0: new           #526                // class java/util/HashSet
       3: dup
       4: invokespecial #988                // Method java/util/HashSet."<init>":()V
       7: astore        4
       9: new           #516                // class java/security/cert/X509CRLSelector
      12: dup
      13: invokespecial #970                // Method java/security/cert/X509CRLSelector."<init>":()V
      16: astore        5
      18: aload         5
      20: aload_2
      21: invokevirtual #972                // Method java/security/cert/X509CRLSelector.setCertificateChecking:(Ljava/security/cert/X509Certificate;)V
      24: aload         5
      26: aload_3
      27: invokestatic  #1115               // Method org/bouncycastle/jce/provider/PrincipalUtils.getIssuerPrincipal:(Ljava/security/cert/X509CRL;)Lorg/bouncycastle/asn1/x500/X500Name;
      30: invokevirtual #1010               // Method org/bouncycastle/asn1/x500/X500Name.getEncoded:()[B
      33: invokevirtual #971                // Method java/security/cert/X509CRLSelector.addIssuerName:([B)V
      36: goto          71
      39: astore        6
      41: new           #565                // class org/bouncycastle/jce/provider/AnnotatedException
      44: dup
      45: new           #503                // class java/lang/StringBuilder
      48: dup
      49: invokespecial #953                // Method java/lang/StringBuilder."<init>":()V
      52: ldc           #9                  // String Cannot extract issuer from CRL.
      54: invokevirtual #956                // Method java/lang/StringBuilder.append:(Ljava/lang/String;)Ljava/lang/StringBuilder;
      57: aload         6
      59: invokevirtual #955                // Method java/lang/StringBuilder.append:(Ljava/lang/Object;)Ljava/lang/StringBuilder;
      62: invokevirtual #954                // Method java/lang/StringBuilder.toString:()Ljava/lang/String;
      65: aload         6
      67: invokespecial #1075               // Method org/bouncycastle/jce/provider/AnnotatedException."<init>":(Ljava/lang/String;Ljava/lang/Throwable;)V
      70: athrow
      71: new           #557                // class org/bouncycastle/jcajce/PKIXCRLStoreSelector$Builder
      74: dup
      75: aload         5
      77: invokespecial #1048               // Method org/bouncycastle/jcajce/PKIXCRLStoreSelector$Builder."<init>":(Ljava/security/cert/CRLSelector;)V
      80: iconst_1
      81: invokevirtual #1050               // Method org/bouncycastle/jcajce/PKIXCRLStoreSelector$Builder.setCompleteCRLEnabled:(Z)Lorg/bouncycastle/jcajce/PKIXCRLStoreSelector$Builder;
      84: invokevirtual #1049               // Method org/bouncycastle/jcajce/PKIXCRLStoreSelector$Builder.build:()Lorg/bouncycastle/jcajce/PKIXCRLStoreSelector;
      87: astore        6
      89: aload_0
      90: astore        7
      92: aload_1
      93: invokevirtual #1061               // Method org/bouncycastle/jcajce/PKIXExtendedParameters.getDate:()Ljava/util/Date;
      96: ifnull        105
      99: aload_1
     100: invokevirtual #1061               // Method org/bouncycastle/jcajce/PKIXExtendedParameters.getDate:()Ljava/util/Date;
     103: astore        7
     105: getstatic     #947                // Field CRL_UTIL:Lorg/bouncycastle/jce/provider/PKIXCRLUtil;
     108: aload         6
     110: aload         7
     112: aload_1
     113: invokevirtual #1063               // Method org/bouncycastle/jcajce/PKIXExtendedParameters.getCertStores:()Ljava/util/List;
     116: aload_1
     117: invokevirtual #1062               // Method org/bouncycastle/jcajce/PKIXExtendedParameters.getCRLStores:()Ljava/util/List;
     120: invokevirtual #1096               // Method org/bouncycastle/jce/provider/PKIXCRLUtil.findCRLs:(Lorg/bouncycastle/jcajce/PKIXCRLStoreSelector;Ljava/util/Date;Ljava/util/List;Ljava/util/List;)Ljava/util/Set;
     123: astore        8
     125: aload_1
     126: invokevirtual #1058               // Method org/bouncycastle/jcajce/PKIXExtendedParameters.isUseDeltasEnabled:()Z
     129: ifeq          171
     132: aload         4
     134: aload         7
     136: aload_3
     137: aload_1
     138: invokevirtual #1063               // Method org/bouncycastle/jcajce/PKIXExtendedParameters.getCertStores:()Ljava/util/List;
     141: aload_1
     142: invokevirtual #1062               // Method org/bouncycastle/jcajce/PKIXExtendedParameters.getCRLStores:()Ljava/util/List;
     145: invokestatic  #1089               // Method org/bouncycastle/jce/provider/CertPathValidatorUtilities.getDeltaCRLs:(Ljava/util/Date;Ljava/security/cert/X509CRL;Ljava/util/List;Ljava/util/List;)Ljava/util/Set;
     148: invokeinterface #1158,  2         // InterfaceMethod java/util/Set.addAll:(Ljava/util/Collection;)Z
     153: pop
     154: goto          171
     157: astore        9
     159: new           #565                // class org/bouncycastle/jce/provider/AnnotatedException
     162: dup
     163: ldc           #29                 // String Exception obtaining delta CRLs.
     165: aload         9
     167: invokespecial #1075               // Method org/bouncycastle/jce/provider/AnnotatedException."<init>":(Ljava/lang/String;Ljava/lang/Throwable;)V
     170: athrow
     171: iconst_2
     172: anewarray     #530                // class java/util/Set
     175: dup
     176: iconst_0
     177: aload         8
     179: aastore
     180: dup
     181: iconst_1
     182: aload         4
     184: aastore
     185: areturn
    Exception table:
       from    to  target type
          24    36    39   Class java/lang/Exception
         132   154   157   Class org/bouncycastle/jce/provider/AnnotatedException

  protected static void processCRLC(java.security.cert.X509CRL, java.security.cert.X509CRL, org.bouncycastle.jcajce.PKIXExtendedParameters) throws org.bouncycastle.jce.provider.AnnotatedException;
    Code:
       0: aload_0
       1: ifnonnull     5
       4: return
       5: aload_0
       6: invokevirtual #966                // Method java/security/cert/X509CRL.hasUnsupportedCriticalExtension:()Z
       9: ifeq          22
      12: new           #565                // class org/bouncycastle/jce/provider/AnnotatedException
      15: dup
      16: ldc           #54                 // String delta CRL has unsupported critical extensions
      18: invokespecial #1073               // Method org/bouncycastle/jce/provider/AnnotatedException."<init>":(Ljava/lang/String;)V
      21: athrow
      22: aconst_null
      23: astore_3
      24: aload_1
      25: getstatic     #940                // Field ISSUING_DISTRIBUTION_POINT:Ljava/lang/String;
      28: invokestatic  #1086               // Method org/bouncycastle/jce/provider/CertPathValidatorUtilities.getExtensionValue:(Ljava/security/cert/X509Extension;Ljava/lang/String;)Lorg/bouncycastle/asn1/ASN1Primitive;
      31: invokestatic  #1041               // Method org/bouncycastle/asn1/x509/IssuingDistributionPoint.getInstance:(Ljava/lang/Object;)Lorg/bouncycastle/asn1/x509/IssuingDistributionPoint;
      34: astore_3
      35: goto          52
      38: astore        4
      40: new           #565                // class org/bouncycastle/jce/provider/AnnotatedException
      43: dup
      44: ldc           #35                 // String Issuing distribution point extension could not be decoded.
      46: aload         4
      48: invokespecial #1075               // Method org/bouncycastle/jce/provider/AnnotatedException."<init>":(Ljava/lang/String;Ljava/lang/Throwable;)V
      51: athrow
      52: aload_2
      53: invokevirtual #1058               // Method org/bouncycastle/jcajce/PKIXExtendedParameters.isUseDeltasEnabled:()Z
      56: ifeq          268
      59: aload_0
      60: invokestatic  #1115               // Method org/bouncycastle/jce/provider/PrincipalUtils.getIssuerPrincipal:(Ljava/security/cert/X509CRL;)Lorg/bouncycastle/asn1/x500/X500Name;
      63: aload_1
      64: invokestatic  #1115               // Method org/bouncycastle/jce/provider/PrincipalUtils.getIssuerPrincipal:(Ljava/security/cert/X509CRL;)Lorg/bouncycastle/asn1/x500/X500Name;
      67: invokevirtual #1011               // Method org/bouncycastle/asn1/x500/X500Name.equals:(Ljava/lang/Object;)Z
      70: ifne          83
      73: new           #565                // class org/bouncycastle/jce/provider/AnnotatedException
      76: dup
      77: ldc           #16                 // String Complete CRL issuer does not match delta CRL issuer.
      79: invokespecial #1073               // Method org/bouncycastle/jce/provider/AnnotatedException."<init>":(Ljava/lang/String;)V
      82: athrow
      83: aconst_null
      84: astore        4
      86: aload_0
      87: getstatic     #940                // Field ISSUING_DISTRIBUTION_POINT:Ljava/lang/String;
      90: invokestatic  #1086               // Method org/bouncycastle/jce/provider/CertPathValidatorUtilities.getExtensionValue:(Ljava/security/cert/X509Extension;Ljava/lang/String;)Lorg/bouncycastle/asn1/ASN1Primitive;
      93: invokestatic  #1041               // Method org/bouncycastle/asn1/x509/IssuingDistributionPoint.getInstance:(Ljava/lang/Object;)Lorg/bouncycastle/asn1/x509/IssuingDistributionPoint;
      96: astore        4
      98: goto          115
     101: astore        5
     103: new           #565                // class org/bouncycastle/jce/provider/AnnotatedException
     106: dup
     107: ldc           #37                 // String Issuing distribution point extension from delta CRL could not be decoded.
     109: aload         5
     111: invokespecial #1075               // Method org/bouncycastle/jce/provider/AnnotatedException."<init>":(Ljava/lang/String;Ljava/lang/Throwable;)V
     114: athrow
     115: iconst_0
     116: istore        5
     118: aload_3
     119: ifnonnull     133
     122: aload         4
     124: ifnonnull     145
     127: iconst_1
     128: istore        5
     130: goto          145
     133: aload_3
     134: aload         4
     136: invokevirtual #1038               // Method org/bouncycastle/asn1/x509/IssuingDistributionPoint.equals:(Ljava/lang/Object;)Z
     139: ifeq          145
     142: iconst_1
     143: istore        5
     145: iload         5
     147: ifne          160
     150: new           #565                // class org/bouncycastle/jce/provider/AnnotatedException
     153: dup
     154: ldc           #36                 // String Issuing distribution point extension from delta CRL and complete CRL does not match.
     156: invokespecial #1073               // Method org/bouncycastle/jce/provider/AnnotatedException."<init>":(Ljava/lang/String;)V
     159: athrow
     160: aconst_null
     161: astore        6
     163: aload_1
     164: getstatic     #932                // Field AUTHORITY_KEY_IDENTIFIER:Ljava/lang/String;
     167: invokestatic  #1086               // Method org/bouncycastle/jce/provider/CertPathValidatorUtilities.getExtensionValue:(Ljava/security/cert/X509Extension;Ljava/lang/String;)Lorg/bouncycastle/asn1/ASN1Primitive;
     170: astore        6
     172: goto          189
     175: astore        7
     177: new           #565                // class org/bouncycastle/jce/provider/AnnotatedException
     180: dup
     181: ldc           #2                  // String Authority key identifier extension could not be extracted from complete CRL.
     183: aload         7
     185: invokespecial #1075               // Method org/bouncycastle/jce/provider/AnnotatedException."<init>":(Ljava/lang/String;Ljava/lang/Throwable;)V
     188: athrow
     189: aconst_null
     190: astore        7
     192: aload_0
     193: getstatic     #932                // Field AUTHORITY_KEY_IDENTIFIER:Ljava/lang/String;
     196: invokestatic  #1086               // Method org/bouncycastle/jce/provider/CertPathValidatorUtilities.getExtensionValue:(Ljava/security/cert/X509Extension;Ljava/lang/String;)Lorg/bouncycastle/asn1/ASN1Primitive;
     199: astore        7
     201: goto          218
     204: astore        8
     206: new           #565                // class org/bouncycastle/jce/provider/AnnotatedException
     209: dup
     210: ldc           #3                  // String Authority key identifier extension could not be extracted from delta CRL.
     212: aload         8
     214: invokespecial #1075               // Method org/bouncycastle/jce/provider/AnnotatedException."<init>":(Ljava/lang/String;Ljava/lang/Throwable;)V
     217: athrow
     218: aload         6
     220: ifnonnull     233
     223: new           #565                // class org/bouncycastle/jce/provider/AnnotatedException
     226: dup
     227: ldc           #6                  // String CRL authority key identifier is null.
     229: invokespecial #1073               // Method org/bouncycastle/jce/provider/AnnotatedException."<init>":(Ljava/lang/String;)V
     232: athrow
     233: aload         7
     235: ifnonnull     248
     238: new           #565                // class org/bouncycastle/jce/provider/AnnotatedException
     241: dup
     242: ldc           #23                 // String Delta CRL authority key identifier is null.
     244: invokespecial #1073               // Method org/bouncycastle/jce/provider/AnnotatedException."<init>":(Ljava/lang/String;)V
     247: athrow
     248: aload         6
     250: aload         7
     252: invokevirtual #999                // Method org/bouncycastle/asn1/ASN1Primitive.equals:(Lorg/bouncycastle/asn1/ASN1Primitive;)Z
     255: ifne          268
     258: new           #565                // class org/bouncycastle/jce/provider/AnnotatedException
     261: dup
     262: ldc           #22                 // String Delta CRL authority key identifier does not match complete CRL authority key identifier.
     264: invokespecial #1073               // Method org/bouncycastle/jce/provider/AnnotatedException."<init>":(Ljava/lang/String;)V
     267: athrow
     268: return
    Exception table:
       from    to  target type
          24    35    38   Class java/lang/Exception
          86    98   101   Class java/lang/Exception
         163   172   175   Class org/bouncycastle/jce/provider/AnnotatedException
         192   201   204   Class org/bouncycastle/jce/provider/AnnotatedException

  protected static void processCRLI(java.util.Date, java.security.cert.X509CRL, java.lang.Object, org.bouncycastle.jce.provider.CertStatus, org.bouncycastle.jcajce.PKIXExtendedParameters) throws org.bouncycastle.jce.provider.AnnotatedException;
    Code:
       0: aload         4
       2: invokevirtual #1058               // Method org/bouncycastle/jcajce/PKIXExtendedParameters.isUseDeltasEnabled:()Z
       5: ifeq          19
       8: aload_1
       9: ifnull        19
      12: aload_0
      13: aload_1
      14: aload_2
      15: aload_3
      16: invokestatic  #1087               // Method org/bouncycastle/jce/provider/CertPathValidatorUtilities.getCertStatus:(Ljava/util/Date;Ljava/security/cert/X509CRL;Ljava/lang/Object;Lorg/bouncycastle/jce/provider/CertStatus;)V
      19: return

  protected static void processCRLJ(java.util.Date, java.security.cert.X509CRL, java.lang.Object, org.bouncycastle.jce.provider.CertStatus) throws org.bouncycastle.jce.provider.AnnotatedException;
    Code:
       0: aload_3
       1: invokevirtual #1091               // Method org/bouncycastle/jce/provider/CertStatus.getCertStatus:()I
       4: bipush        11
       6: if_icmpne     16
       9: aload_0
      10: aload_1
      11: aload_2
      12: aload_3
      13: invokestatic  #1087               // Method org/bouncycastle/jce/provider/CertPathValidatorUtilities.getCertStatus:(Ljava/util/Date;Ljava/security/cert/X509CRL;Ljava/lang/Object;Lorg/bouncycastle/jce/provider/CertStatus;)V
      16: return

  protected static org.bouncycastle.jce.provider.PKIXPolicyNode prepareCertB(java.security.cert.CertPath, int, java.util.List[], org.bouncycastle.jce.provider.PKIXPolicyNode, int) throws java.security.cert.CertPathValidatorException;
    Code:
       0: aload_0
       1: invokevirtual #959                // Method java/security/cert/CertPath.getCertificates:()Ljava/util/List;
       4: astore        5
       6: aload         5
       8: iload_1
       9: invokeinterface #1145,  2         // InterfaceMethod java/util/List.get:(I)Ljava/lang/Object;
      14: checkcast     #518                // class java/security/cert/X509Certificate
      17: astore        6
      19: aload         5
      21: invokeinterface #1144,  1         // InterfaceMethod java/util/List.size:()I
      26: istore        7
      28: iload         7
      30: iload_1
      31: isub
      32: istore        8
      34: aconst_null
      35: astore        9
      37: aload         6
      39: getstatic     #944                // Field POLICY_MAPPINGS:Ljava/lang/String;
      42: invokestatic  #1086               // Method org/bouncycastle/jce/provider/CertPathValidatorUtilities.getExtensionValue:(Ljava/security/cert/X509Extension;Ljava/lang/String;)Lorg/bouncycastle/asn1/ASN1Primitive;
      45: invokestatic  #1007               // Method org/bouncycastle/asn1/DERSequence.getInstance:(Ljava/lang/Object;)Lorg/bouncycastle/asn1/ASN1Sequence;
      48: astore        9
      50: goto          69
      53: astore        10
      55: new           #564                // class org/bouncycastle/jce/exception/ExtCertPathValidatorException
      58: dup
      59: ldc           #43                 // String Policy mappings extension could not be decoded.
      61: aload         10
      63: aload_0
      64: iload_1
      65: invokespecial #1071               // Method org/bouncycastle/jce/exception/ExtCertPathValidatorException."<init>":(Ljava/lang/String;Ljava/lang/Throwable;Ljava/security/cert/CertPath;I)V
      68: athrow
      69: aload_3
      70: astore        10
      72: aload         9
      74: ifnull        817
      77: aload         9
      79: astore        11
      81: new           #525                // class java/util/HashMap
      84: dup
      85: invokespecial #987                // Method java/util/HashMap."<init>":()V
      88: astore        12
      90: new           #526                // class java/util/HashSet
      93: dup
      94: invokespecial #988                // Method java/util/HashSet."<init>":()V
      97: astore        13
      99: iconst_0
     100: istore        14
     102: iload         14
     104: aload         11
     106: invokevirtual #1000               // Method org/bouncycastle/asn1/ASN1Sequence.size:()I
     109: if_icmpge     238
     112: aload         11
     114: iload         14
     116: invokevirtual #1002               // Method org/bouncycastle/asn1/ASN1Sequence.getObjectAt:(I)Lorg/bouncycastle/asn1/ASN1Encodable;
     119: checkcast     #537                // class org/bouncycastle/asn1/ASN1Sequence
     122: astore        15
     124: aload         15
     126: iconst_0
     127: invokevirtual #1002               // Method org/bouncycastle/asn1/ASN1Sequence.getObjectAt:(I)Lorg/bouncycastle/asn1/ASN1Encodable;
     130: checkcast     #535                // class org/bouncycastle/asn1/ASN1ObjectIdentifier
     133: invokevirtual #996                // Method org/bouncycastle/asn1/ASN1ObjectIdentifier.getId:()Ljava/lang/String;
     136: astore        16
     138: aload         15
     140: iconst_1
     141: invokevirtual #1002               // Method org/bouncycastle/asn1/ASN1Sequence.getObjectAt:(I)Lorg/bouncycastle/asn1/ASN1Encodable;
     144: checkcast     #535                // class org/bouncycastle/asn1/ASN1ObjectIdentifier
     147: invokevirtual #996                // Method org/bouncycastle/asn1/ASN1ObjectIdentifier.getId:()Ljava/lang/String;
     150: astore        17
     152: aload         12
     154: aload         16
     156: invokeinterface #1150,  2         // InterfaceMethod java/util/Map.containsKey:(Ljava/lang/Object;)Z
     161: ifne          208
     164: new           #526                // class java/util/HashSet
     167: dup
     168: invokespecial #988                // Method java/util/HashSet."<init>":()V
     171: astore        18
     173: aload         18
     175: aload         17
     177: invokeinterface #1155,  2         // InterfaceMethod java/util/Set.add:(Ljava/lang/Object;)Z
     182: pop
     183: aload         12
     185: aload         16
     187: aload         18
     189: invokeinterface #1152,  3         // InterfaceMethod java/util/Map.put:(Ljava/lang/Object;Ljava/lang/Object;)Ljava/lang/Object;
     194: pop
     195: aload         13
     197: aload         16
     199: invokeinterface #1155,  2         // InterfaceMethod java/util/Set.add:(Ljava/lang/Object;)Z
     204: pop
     205: goto          232
     208: aload         12
     210: aload         16
     212: invokeinterface #1151,  2         // InterfaceMethod java/util/Map.get:(Ljava/lang/Object;)Ljava/lang/Object;
     217: checkcast     #530                // class java/util/Set
     220: astore        18
     222: aload         18
     224: aload         17
     226: invokeinterface #1155,  2         // InterfaceMethod java/util/Set.add:(Ljava/lang/Object;)Z
     231: pop
     232: iinc          14, 1
     235: goto          102
     238: aload         13
     240: invokeinterface #1159,  1         // InterfaceMethod java/util/Set.iterator:()Ljava/util/Iterator;
     245: astore        14
     247: aload         14
     249: invokeinterface #1142,  1         // InterfaceMethod java/util/Iterator.hasNext:()Z
     254: ifeq          817
     257: aload         14
     259: invokeinterface #1143,  1         // InterfaceMethod java/util/Iterator.next:()Ljava/lang/Object;
     264: checkcast     #502                // class java/lang/String
     267: astore        15
     269: iload         4
     271: ifle          652
     274: iconst_0
     275: istore        16
     277: aload_2
     278: iload         8
     280: aaload
     281: invokeinterface #1149,  1         // InterfaceMethod java/util/List.iterator:()Ljava/util/Iterator;
     286: astore        17
     288: aload         17
     290: invokeinterface #1142,  1         // InterfaceMethod java/util/Iterator.hasNext:()Z
     295: ifeq          349
     298: aload         17
     300: invokeinterface #1143,  1         // InterfaceMethod java/util/Iterator.next:()Ljava/lang/Object;
     305: checkcast     #572                // class org/bouncycastle/jce/provider/PKIXPolicyNode
     308: astore        18
     310: aload         18
     312: invokevirtual #1107               // Method org/bouncycastle/jce/provider/PKIXPolicyNode.getValidPolicy:()Ljava/lang/String;
     315: aload         15
     317: invokevirtual #952                // Method java/lang/String.equals:(Ljava/lang/Object;)Z
     320: ifeq          346
     323: iconst_1
     324: istore        16
     326: aload         18
     328: aload         12
     330: aload         15
     332: invokeinterface #1151,  2         // InterfaceMethod java/util/Map.get:(Ljava/lang/Object;)Ljava/lang/Object;
     337: checkcast     #530                // class java/util/Set
     340: putfield      #931                // Field org/bouncycastle/jce/provider/PKIXPolicyNode.expectedPolicies:Ljava/util/Set;
     343: goto          349
     346: goto          288
     349: iload         16
     351: ifne          649
     354: aload_2
     355: iload         8
     357: aaload
     358: invokeinterface #1149,  1         // InterfaceMethod java/util/List.iterator:()Ljava/util/Iterator;
     363: astore        17
     365: aload         17
     367: invokeinterface #1142,  1         // InterfaceMethod java/util/Iterator.hasNext:()Z
     372: ifeq          649
     375: aload         17
     377: invokeinterface #1143,  1         // InterfaceMethod java/util/Iterator.next:()Ljava/lang/Object;
     382: checkcast     #572                // class org/bouncycastle/jce/provider/PKIXPolicyNode
     385: astore        18
     387: ldc           #1                  // String 2.5.29.32.0
     389: aload         18
     391: invokevirtual #1107               // Method org/bouncycastle/jce/provider/PKIXPolicyNode.getValidPolicy:()Ljava/lang/String;
     394: invokevirtual #952                // Method java/lang/String.equals:(Ljava/lang/Object;)Z
     397: ifeq          646
     400: aconst_null
     401: astore        19
     403: aconst_null
     404: astore        20
     406: aload         6
     408: getstatic     #934                // Field CERTIFICATE_POLICIES:Ljava/lang/String;
     411: invokestatic  #1086               // Method org/bouncycastle/jce/provider/CertPathValidatorUtilities.getExtensionValue:(Ljava/security/cert/X509Extension;Ljava/lang/String;)Lorg/bouncycastle/asn1/ASN1Primitive;
     414: checkcast     #537                // class org/bouncycastle/asn1/ASN1Sequence
     417: astore        20
     419: goto          438
     422: astore        21
     424: new           #564                // class org/bouncycastle/jce/exception/ExtCertPathValidatorException
     427: dup
     428: ldc           #15                 // String Certificate policies extension could not be decoded.
     430: aload         21
     432: aload_0
     433: iload_1
     434: invokespecial #1071               // Method org/bouncycastle/jce/exception/ExtCertPathValidatorException."<init>":(Ljava/lang/String;Ljava/lang/Throwable;Ljava/security/cert/CertPath;I)V
     437: athrow
     438: aload         20
     440: invokevirtual #1001               // Method org/bouncycastle/asn1/ASN1Sequence.getObjects:()Ljava/util/Enumeration;
     443: astore        21
     445: aload         21
     447: invokeinterface #1139,  1         // InterfaceMethod java/util/Enumeration.hasMoreElements:()Z
     452: ifeq          537
     455: aconst_null
     456: astore        22
     458: aload         21
     460: invokeinterface #1140,  1         // InterfaceMethod java/util/Enumeration.nextElement:()Ljava/lang/Object;
     465: invokestatic  #1047               // Method org/bouncycastle/asn1/x509/PolicyInformation.getInstance:(Ljava/lang/Object;)Lorg/bouncycastle/asn1/x509/PolicyInformation;
     468: astore        22
     470: goto          489
     473: astore        23
     475: new           #511                // class java/security/cert/CertPathValidatorException
     478: dup
     479: ldc           #41                 // String Policy information could not be decoded.
     481: aload         23
     483: aload_0
     484: iload_1
     485: invokespecial #962                // Method java/security/cert/CertPathValidatorException."<init>":(Ljava/lang/String;Ljava/lang/Throwable;Ljava/security/cert/CertPath;I)V
     488: athrow
     489: ldc           #1                  // String 2.5.29.32.0
     491: aload         22
     493: invokevirtual #1045               // Method org/bouncycastle/asn1/x509/PolicyInformation.getPolicyIdentifier:()Lorg/bouncycastle/asn1/ASN1ObjectIdentifier;
     496: invokevirtual #996                // Method org/bouncycastle/asn1/ASN1ObjectIdentifier.getId:()Ljava/lang/String;
     499: invokevirtual #952                // Method java/lang/String.equals:(Ljava/lang/Object;)Z
     502: ifeq          534
     505: aload         22
     507: invokevirtual #1046               // Method org/bouncycastle/asn1/x509/PolicyInformation.getPolicyQualifiers:()Lorg/bouncycastle/asn1/ASN1Sequence;
     510: invokestatic  #1078               // Method org/bouncycastle/jce/provider/CertPathValidatorUtilities.getQualifierSet:(Lorg/bouncycastle/asn1/ASN1Sequence;)Ljava/util/Set;
     513: astore        19
     515: goto          537
     518: astore        23
     520: new           #564                // class org/bouncycastle/jce/exception/ExtCertPathValidatorException
     523: dup
     524: ldc           #45                 // String Policy qualifier info set could not be decoded.
     526: aload         23
     528: aload_0
     529: iload_1
     530: invokespecial #1071               // Method org/bouncycastle/jce/exception/ExtCertPathValidatorException."<init>":(Ljava/lang/String;Ljava/lang/Throwable;Ljava/security/cert/CertPath;I)V
     533: athrow
     534: goto          445
     537: iconst_0
     538: istore        22
     540: aload         6
     542: invokevirtual #980                // Method java/security/cert/X509Certificate.getCriticalExtensionOIDs:()Ljava/util/Set;
     545: ifnull        563
     548: aload         6
     550: invokevirtual #980                // Method java/security/cert/X509Certificate.getCriticalExtensionOIDs:()Ljava/util/Set;
     553: getstatic     #934                // Field CERTIFICATE_POLICIES:Ljava/lang/String;
     556: invokeinterface #1156,  2         // InterfaceMethod java/util/Set.contains:(Ljava/lang/Object;)Z
     561: istore        22
     563: aload         18
     565: invokevirtual #1108               // Method org/bouncycastle/jce/provider/PKIXPolicyNode.getParent:()Ljava/security/cert/PolicyNode;
     568: checkcast     #572                // class org/bouncycastle/jce/provider/PKIXPolicyNode
     571: astore        23
     573: ldc           #1                  // String 2.5.29.32.0
     575: aload         23
     577: invokevirtual #1107               // Method org/bouncycastle/jce/provider/PKIXPolicyNode.getValidPolicy:()Ljava/lang/String;
     580: invokevirtual #952                // Method java/lang/String.equals:(Ljava/lang/Object;)Z
     583: ifeq          649
     586: new           #572                // class org/bouncycastle/jce/provider/PKIXPolicyNode
     589: dup
     590: new           #521                // class java/util/ArrayList
     593: dup
     594: invokespecial #984                // Method java/util/ArrayList."<init>":()V
     597: iload         8
     599: aload         12
     601: aload         15
     603: invokeinterface #1151,  2         // InterfaceMethod java/util/Map.get:(Ljava/lang/Object;)Ljava/lang/Object;
     608: checkcast     #530                // class java/util/Set
     611: aload         23
     613: aload         19
     615: aload         15
     617: iload         22
     619: invokespecial #1113               // Method org/bouncycastle/jce/provider/PKIXPolicyNode."<init>":(Ljava/util/List;ILjava/util/Set;Ljava/security/cert/PolicyNode;Ljava/util/Set;Ljava/lang/String;Z)V
     622: astore        24
     624: aload         23
     626: aload         24
     628: invokevirtual #1111               // Method org/bouncycastle/jce/provider/PKIXPolicyNode.addChild:(Lorg/bouncycastle/jce/provider/PKIXPolicyNode;)V
     631: aload_2
     632: iload         8
     634: aaload
     635: aload         24
     637: invokeinterface #1146,  2         // InterfaceMethod java/util/List.add:(Ljava/lang/Object;)Z
     642: pop
     643: goto          649
     646: goto          365
     649: goto          814
     652: iload         4
     654: ifgt          814
     657: aload_2
     658: iload         8
     660: aaload
     661: invokeinterface #1149,  1         // InterfaceMethod java/util/List.iterator:()Ljava/util/Iterator;
     666: astore        16
     668: aload         16
     670: invokeinterface #1142,  1         // InterfaceMethod java/util/Iterator.hasNext:()Z
     675: ifeq          814
     678: aload         16
     680: invokeinterface #1143,  1         // InterfaceMethod java/util/Iterator.next:()Ljava/lang/Object;
     685: checkcast     #572                // class org/bouncycastle/jce/provider/PKIXPolicyNode
     688: astore        17
     690: aload         17
     692: invokevirtual #1107               // Method org/bouncycastle/jce/provider/PKIXPolicyNode.getValidPolicy:()Ljava/lang/String;
     695: aload         15
     697: invokevirtual #952                // Method java/lang/String.equals:(Ljava/lang/Object;)Z
     700: ifeq          811
     703: aload         17
     705: invokevirtual #1108               // Method org/bouncycastle/jce/provider/PKIXPolicyNode.getParent:()Ljava/security/cert/PolicyNode;
     708: checkcast     #572                // class org/bouncycastle/jce/provider/PKIXPolicyNode
     711: astore        18
     713: aload         18
     715: aload         17
     717: invokevirtual #1112               // Method org/bouncycastle/jce/provider/PKIXPolicyNode.removeChild:(Lorg/bouncycastle/jce/provider/PKIXPolicyNode;)V
     720: aload         16
     722: invokeinterface #1141,  1         // InterfaceMethod java/util/Iterator.remove:()V
     727: iload         8
     729: iconst_1
     730: isub
     731: istore        19
     733: iload         19
     735: iflt          811
     738: aload_2
     739: iload         19
     741: aaload
     742: astore        20
     744: iconst_0
     745: istore        21
     747: iload         21
     749: aload         20
     751: invokeinterface #1144,  1         // InterfaceMethod java/util/List.size:()I
     756: if_icmpge     805
     759: aload         20
     761: iload         21
     763: invokeinterface #1145,  2         // InterfaceMethod java/util/List.get:(I)Ljava/lang/Object;
     768: checkcast     #572                // class org/bouncycastle/jce/provider/PKIXPolicyNode
     771: astore        22
     773: aload         22
     775: invokevirtual #1105               // Method org/bouncycastle/jce/provider/PKIXPolicyNode.hasChildren:()Z
     778: ifne          799
     781: aload         10
     783: aload_2
     784: aload         22
     786: invokestatic  #1088               // Method org/bouncycastle/jce/provider/CertPathValidatorUtilities.removePolicyNode:(Lorg/bouncycastle/jce/provider/PKIXPolicyNode;[Ljava/util/List;Lorg/bouncycastle/jce/provider/PKIXPolicyNode;)Lorg/bouncycastle/jce/provider/PKIXPolicyNode;
     789: astore        10
     791: aload         10
     793: ifnonnull     799
     796: goto          805
     799: iinc          21, 1
     802: goto          747
     805: iinc          19, -1
     808: goto          733
     811: goto          668
     814: goto          247
     817: aload         10
     819: areturn
    Exception table:
       from    to  target type
          37    50    53   Class org/bouncycastle/jce/provider/AnnotatedException
         406   419   422   Class org/bouncycastle/jce/provider/AnnotatedException
         458   470   473   Class java/lang/Exception
         505   515   518   Class java/security/cert/CertPathValidatorException

  protected static void prepareNextCertA(java.security.cert.CertPath, int) throws java.security.cert.CertPathValidatorException;
    Code:
       0: aload_0
       1: invokevirtual #959                // Method java/security/cert/CertPath.getCertificates:()Ljava/util/List;
       4: astore_2
       5: aload_2
       6: iload_1
       7: invokeinterface #1145,  2         // InterfaceMethod java/util/List.get:(I)Ljava/lang/Object;
      12: checkcast     #518                // class java/security/cert/X509Certificate
      15: astore_3
      16: aconst_null
      17: astore        4
      19: aload_3
      20: getstatic     #944                // Field POLICY_MAPPINGS:Ljava/lang/String;
      23: invokestatic  #1086               // Method org/bouncycastle/jce/provider/CertPathValidatorUtilities.getExtensionValue:(Ljava/security/cert/X509Extension;Ljava/lang/String;)Lorg/bouncycastle/asn1/ASN1Primitive;
      26: invokestatic  #1007               // Method org/bouncycastle/asn1/DERSequence.getInstance:(Ljava/lang/Object;)Lorg/bouncycastle/asn1/ASN1Sequence;
      29: astore        4
      31: goto          50
      34: astore        5
      36: new           #564                // class org/bouncycastle/jce/exception/ExtCertPathValidatorException
      39: dup
      40: ldc           #43                 // String Policy mappings extension could not be decoded.
      42: aload         5
      44: aload_0
      45: iload_1
      46: invokespecial #1071               // Method org/bouncycastle/jce/exception/ExtCertPathValidatorException."<init>":(Ljava/lang/String;Ljava/lang/Throwable;Ljava/security/cert/CertPath;I)V
      49: athrow
      50: aload         4
      52: ifnull        189
      55: aload         4
      57: astore        5
      59: iconst_0
      60: istore        6
      62: iload         6
      64: aload         5
      66: invokevirtual #1000               // Method org/bouncycastle/asn1/ASN1Sequence.size:()I
      69: if_icmpge     189
      72: aconst_null
      73: astore        7
      75: aconst_null
      76: astore        8
      78: aload         5
      80: iload         6
      82: invokevirtual #1002               // Method org/bouncycastle/asn1/ASN1Sequence.getObjectAt:(I)Lorg/bouncycastle/asn1/ASN1Encodable;
      85: invokestatic  #1007               // Method org/bouncycastle/asn1/DERSequence.getInstance:(Ljava/lang/Object;)Lorg/bouncycastle/asn1/ASN1Sequence;
      88: astore        9
      90: aload         9
      92: iconst_0
      93: invokevirtual #1002               // Method org/bouncycastle/asn1/ASN1Sequence.getObjectAt:(I)Lorg/bouncycastle/asn1/ASN1Encodable;
      96: invokestatic  #997                // Method org/bouncycastle/asn1/ASN1ObjectIdentifier.getInstance:(Ljava/lang/Object;)Lorg/bouncycastle/asn1/ASN1ObjectIdentifier;
      99: astore        7
     101: aload         9
     103: iconst_1
     104: invokevirtual #1002               // Method org/bouncycastle/asn1/ASN1Sequence.getObjectAt:(I)Lorg/bouncycastle/asn1/ASN1Encodable;
     107: invokestatic  #997                // Method org/bouncycastle/asn1/ASN1ObjectIdentifier.getInstance:(Ljava/lang/Object;)Lorg/bouncycastle/asn1/ASN1ObjectIdentifier;
     110: astore        8
     112: goto          131
     115: astore        9
     117: new           #564                // class org/bouncycastle/jce/exception/ExtCertPathValidatorException
     120: dup
     121: ldc           #42                 // String Policy mappings extension contents could not be decoded.
     123: aload         9
     125: aload_0
     126: iload_1
     127: invokespecial #1071               // Method org/bouncycastle/jce/exception/ExtCertPathValidatorException."<init>":(Ljava/lang/String;Ljava/lang/Throwable;Ljava/security/cert/CertPath;I)V
     130: athrow
     131: ldc           #1                  // String 2.5.29.32.0
     133: aload         7
     135: invokevirtual #996                // Method org/bouncycastle/asn1/ASN1ObjectIdentifier.getId:()Ljava/lang/String;
     138: invokevirtual #952                // Method java/lang/String.equals:(Ljava/lang/Object;)Z
     141: ifeq          157
     144: new           #511                // class java/security/cert/CertPathValidatorException
     147: dup
     148: ldc           #34                 // String IssuerDomainPolicy is anyPolicy
     150: aconst_null
     151: aload_0
     152: iload_1
     153: invokespecial #962                // Method java/security/cert/CertPathValidatorException."<init>":(Ljava/lang/String;Ljava/lang/Throwable;Ljava/security/cert/CertPath;I)V
     156: athrow
     157: ldc           #1                  // String 2.5.29.32.0
     159: aload         8
     161: invokevirtual #996                // Method org/bouncycastle/asn1/ASN1ObjectIdentifier.getId:()Ljava/lang/String;
     164: invokevirtual #952                // Method java/lang/String.equals:(Ljava/lang/Object;)Z
     167: ifeq          183
     170: new           #511                // class java/security/cert/CertPathValidatorException
     173: dup
     174: ldc           #50                 // String SubjectDomainPolicy is anyPolicy
     176: aconst_null
     177: aload_0
     178: iload_1
     179: invokespecial #962                // Method java/security/cert/CertPathValidatorException."<init>":(Ljava/lang/String;Ljava/lang/Throwable;Ljava/security/cert/CertPath;I)V
     182: athrow
     183: iinc          6, 1
     186: goto          62
     189: return
    Exception table:
       from    to  target type
          19    31    34   Class org/bouncycastle/jce/provider/AnnotatedException
          78   112   115   Class java/lang/Exception

  protected static void processCertF(java.security.cert.CertPath, int, org.bouncycastle.jce.provider.PKIXPolicyNode, int) throws java.security.cert.CertPathValidatorException;
    Code:
       0: iload_3
       1: ifgt          21
       4: aload_2
       5: ifnonnull     21
       8: new           #564                // class org/bouncycastle/jce/exception/ExtCertPathValidatorException
      11: dup
      12: ldc           #40                 // String No valid policy tree found when one expected.
      14: aconst_null
      15: aload_0
      16: iload_1
      17: invokespecial #1071               // Method org/bouncycastle/jce/exception/ExtCertPathValidatorException."<init>":(Ljava/lang/String;Ljava/lang/Throwable;Ljava/security/cert/CertPath;I)V
      20: athrow
      21: return

  protected static org.bouncycastle.jce.provider.PKIXPolicyNode processCertE(java.security.cert.CertPath, int, org.bouncycastle.jce.provider.PKIXPolicyNode) throws java.security.cert.CertPathValidatorException;
    Code:
       0: aload_0
       1: invokevirtual #959                // Method java/security/cert/CertPath.getCertificates:()Ljava/util/List;
       4: astore_3
       5: aload_3
       6: iload_1
       7: invokeinterface #1145,  2         // InterfaceMethod java/util/List.get:(I)Ljava/lang/Object;
      12: checkcast     #518                // class java/security/cert/X509Certificate
      15: astore        4
      17: aconst_null
      18: astore        5
      20: aload         4
      22: getstatic     #934                // Field CERTIFICATE_POLICIES:Ljava/lang/String;
      25: invokestatic  #1086               // Method org/bouncycastle/jce/provider/CertPathValidatorUtilities.getExtensionValue:(Ljava/security/cert/X509Extension;Ljava/lang/String;)Lorg/bouncycastle/asn1/ASN1Primitive;
      28: invokestatic  #1007               // Method org/bouncycastle/asn1/DERSequence.getInstance:(Ljava/lang/Object;)Lorg/bouncycastle/asn1/ASN1Sequence;
      31: astore        5
      33: goto          52
      36: astore        6
      38: new           #564                // class org/bouncycastle/jce/exception/ExtCertPathValidatorException
      41: dup
      42: ldc           #19                 // String Could not read certificate policies extension from certificate.
      44: aload         6
      46: aload_0
      47: iload_1
      48: invokespecial #1071               // Method org/bouncycastle/jce/exception/ExtCertPathValidatorException."<init>":(Ljava/lang/String;Ljava/lang/Throwable;Ljava/security/cert/CertPath;I)V
      51: athrow
      52: aload         5
      54: ifnonnull     59
      57: aconst_null
      58: astore_2
      59: aload_2
      60: areturn
    Exception table:
       from    to  target type
          20    33    36   Class org/bouncycastle/jce/provider/AnnotatedException

  protected static void processCertBC(java.security.cert.CertPath, int, org.bouncycastle.jce.provider.PKIXNameConstraintValidator, boolean) throws java.security.cert.CertPathValidatorException;
    Code:
       0: aload_0
       1: invokevirtual #959                // Method java/security/cert/CertPath.getCertificates:()Ljava/util/List;
       4: astore        4
       6: aload         4
       8: iload_1
       9: invokeinterface #1145,  2         // InterfaceMethod java/util/List.get:(I)Ljava/lang/Object;
      14: checkcast     #518                // class java/security/cert/X509Certificate
      17: astore        5
      19: aload         4
      21: invokeinterface #1144,  1         // InterfaceMethod java/util/List.size:()I
      26: istore        6
      28: iload         6
      30: iload_1
      31: isub
      32: istore        7
      34: aload         5
      36: invokestatic  #1076               // Method org/bouncycastle/jce/provider/CertPathValidatorUtilities.isSelfIssued:(Ljava/security/cert/X509Certificate;)Z
      39: ifeq          53
      42: iload         7
      44: iload         6
      46: if_icmplt     337
      49: iload_3
      50: ifne          337
      53: aload         5
      55: invokestatic  #1116               // Method org/bouncycastle/jce/provider/PrincipalUtils.getSubjectPrincipal:(Ljava/security/cert/X509Certificate;)Lorg/bouncycastle/asn1/x500/X500Name;
      58: astore        8
      60: aload         8
      62: invokevirtual #1010               // Method org/bouncycastle/asn1/x500/X500Name.getEncoded:()[B
      65: invokestatic  #1007               // Method org/bouncycastle/asn1/DERSequence.getInstance:(Ljava/lang/Object;)Lorg/bouncycastle/asn1/ASN1Sequence;
      68: astore        9
      70: goto          89
      73: astore        10
      75: new           #511                // class java/security/cert/CertPathValidatorException
      78: dup
      79: ldc           #28                 // String Exception extracting subject name when checking subtrees.
      81: aload         10
      83: aload_0
      84: iload_1
      85: invokespecial #962                // Method java/security/cert/CertPathValidatorException."<init>":(Ljava/lang/String;Ljava/lang/Throwable;Ljava/security/cert/CertPath;I)V
      88: athrow
      89: aload_2
      90: aload         9
      92: invokevirtual #1100               // Method org/bouncycastle/jce/provider/PKIXNameConstraintValidator.checkPermittedDN:(Lorg/bouncycastle/asn1/ASN1Sequence;)V
      95: aload_2
      96: aload         9
      98: invokevirtual #1099               // Method org/bouncycastle/jce/provider/PKIXNameConstraintValidator.checkExcludedDN:(Lorg/bouncycastle/asn1/ASN1Sequence;)V
     101: goto          120
     104: astore        10
     106: new           #511                // class java/security/cert/CertPathValidatorException
     109: dup
     110: ldc           #53                 // String Subtree check for certificate subject failed.
     112: aload         10
     114: aload_0
     115: iload_1
     116: invokespecial #962                // Method java/security/cert/CertPathValidatorException."<init>":(Ljava/lang/String;Ljava/lang/Throwable;Ljava/security/cert/CertPath;I)V
     119: athrow
     120: aconst_null
     121: astore        10
     123: aload         5
     125: getstatic     #945                // Field SUBJECT_ALTERNATIVE_NAME:Ljava/lang/String;
     128: invokestatic  #1086               // Method org/bouncycastle/jce/provider/CertPathValidatorUtilities.getExtensionValue:(Ljava/security/cert/X509Extension;Ljava/lang/String;)Lorg/bouncycastle/asn1/ASN1Primitive;
     131: invokestatic  #1033               // Method org/bouncycastle/asn1/x509/GeneralNames.getInstance:(Ljava/lang/Object;)Lorg/bouncycastle/asn1/x509/GeneralNames;
     134: astore        10
     136: goto          155
     139: astore        11
     141: new           #511                // class java/security/cert/CertPathValidatorException
     144: dup
     145: ldc           #48                 // String Subject alternative name extension could not be decoded.
     147: aload         11
     149: aload_0
     150: iload_1
     151: invokespecial #962                // Method java/security/cert/CertPathValidatorException."<init>":(Ljava/lang/String;Ljava/lang/Throwable;Ljava/security/cert/CertPath;I)V
     154: athrow
     155: aload         9
     157: invokestatic  #1013               // Method org/bouncycastle/asn1/x500/X500Name.getInstance:(Ljava/lang/Object;)Lorg/bouncycastle/asn1/x500/X500Name;
     160: getstatic     #916                // Field org/bouncycastle/asn1/x500/style/BCStyle.EmailAddress:Lorg/bouncycastle/asn1/ASN1ObjectIdentifier;
     163: invokevirtual #1012               // Method org/bouncycastle/asn1/x500/X500Name.getRDNs:(Lorg/bouncycastle/asn1/ASN1ObjectIdentifier;)[Lorg/bouncycastle/asn1/x500/RDN;
     166: astore        11
     168: iconst_0
     169: istore        12
     171: iload         12
     173: aload         11
     175: arraylength
     176: if_icmpeq     249
     179: aload         11
     181: iload         12
     183: aaload
     184: invokevirtual #1009               // Method org/bouncycastle/asn1/x500/RDN.getFirst:()Lorg/bouncycastle/asn1/x500/AttributeTypeAndValue;
     187: invokevirtual #1008               // Method org/bouncycastle/asn1/x500/AttributeTypeAndValue.getValue:()Lorg/bouncycastle/asn1/ASN1Encodable;
     190: checkcast     #538                // class org/bouncycastle/asn1/ASN1String
     193: invokeinterface #1161,  1         // InterfaceMethod org/bouncycastle/asn1/ASN1String.getString:()Ljava/lang/String;
     198: astore        13
     200: new           #550                // class org/bouncycastle/asn1/x509/GeneralName
     203: dup
     204: iconst_1
     205: aload         13
     207: invokespecial #1027               // Method org/bouncycastle/asn1/x509/GeneralName."<init>":(ILjava/lang/String;)V
     210: astore        14
     212: aload_2
     213: aload         14
     215: invokevirtual #1102               // Method org/bouncycastle/jce/provider/PKIXNameConstraintValidator.checkPermitted:(Lorg/bouncycastle/asn1/x509/GeneralName;)V
     218: aload_2
     219: aload         14
     221: invokevirtual #1101               // Method org/bouncycastle/jce/provider/PKIXNameConstraintValidator.checkExcluded:(Lorg/bouncycastle/asn1/x509/GeneralName;)V
     224: goto          243
     227: astore        15
     229: new           #511                // class java/security/cert/CertPathValidatorException
     232: dup
     233: ldc           #51                 // String Subtree check for certificate subject alternative email failed.
     235: aload         15
     237: aload_0
     238: iload_1
     239: invokespecial #962                // Method java/security/cert/CertPathValidatorException."<init>":(Ljava/lang/String;Ljava/lang/Throwable;Ljava/security/cert/CertPath;I)V
     242: athrow
     243: iinc          12, 1
     246: goto          171
     249: aload         10
     251: ifnull        337
     254: aconst_null
     255: astore        12
     257: aload         10
     259: invokevirtual #1031               // Method org/bouncycastle/asn1/x509/GeneralNames.getNames:()[Lorg/bouncycastle/asn1/x509/GeneralName;
     262: astore        12
     264: goto          283
     267: astore        13
     269: new           #511                // class java/security/cert/CertPathValidatorException
     272: dup
     273: ldc           #47                 // String Subject alternative name contents could not be decoded.
     275: aload         13
     277: aload_0
     278: iload_1
     279: invokespecial #962                // Method java/security/cert/CertPathValidatorException."<init>":(Ljava/lang/String;Ljava/lang/Throwable;Ljava/security/cert/CertPath;I)V
     282: athrow
     283: iconst_0
     284: istore        13
     286: iload         13
     288: aload         12
     290: arraylength
     291: if_icmpge     337
     294: aload_2
     295: aload         12
     297: iload         13
     299: aaload
     300: invokevirtual #1102               // Method org/bouncycastle/jce/provider/PKIXNameConstraintValidator.checkPermitted:(Lorg/bouncycastle/asn1/x509/GeneralName;)V
     303: aload_2
     304: aload         12
     306: iload         13
     308: aaload
     309: invokevirtual #1101               // Method org/bouncycastle/jce/provider/PKIXNameConstraintValidator.checkExcluded:(Lorg/bouncycastle/asn1/x509/GeneralName;)V
     312: goto          331
     315: astore        14
     317: new           #511                // class java/security/cert/CertPathValidatorException
     320: dup
     321: ldc           #52                 // String Subtree check for certificate subject alternative name failed.
     323: aload         14
     325: aload_0
     326: iload_1
     327: invokespecial #962                // Method java/security/cert/CertPathValidatorException."<init>":(Ljava/lang/String;Ljava/lang/Throwable;Ljava/security/cert/CertPath;I)V
     330: athrow
     331: iinc          13, 1
     334: goto          286
     337: return
    Exception table:
       from    to  target type
          60    70    73   Class java/lang/Exception
          89   101   104   Class org/bouncycastle/jce/provider/PKIXNameConstraintValidatorException
         123   136   139   Class java/lang/Exception
         212   224   227   Class org/bouncycastle/jce/provider/PKIXNameConstraintValidatorException
         257   264   267   Class java/lang/Exception
         294   312   315   Class org/bouncycastle/jce/provider/PKIXNameConstraintValidatorException

  protected static org.bouncycastle.jce.provider.PKIXPolicyNode processCertD(java.security.cert.CertPath, int, java.util.Set, org.bouncycastle.jce.provider.PKIXPolicyNode, java.util.List[], int, boolean) throws java.security.cert.CertPathValidatorException;
    Code:
       0: aload_0
       1: invokevirtual #959                // Method java/security/cert/CertPath.getCertificates:()Ljava/util/List;
       4: astore        7
       6: aload         7
       8: iload_1
       9: invokeinterface #1145,  2         // InterfaceMethod java/util/List.get:(I)Ljava/lang/Object;
      14: checkcast     #518                // class java/security/cert/X509Certificate
      17: astore        8
      19: aload         7
      21: invokeinterface #1144,  1         // InterfaceMethod java/util/List.size:()I
      26: istore        9
      28: iload         9
      30: iload_1
      31: isub
      32: istore        10
      34: aconst_null
      35: astore        11
      37: aload         8
      39: getstatic     #934                // Field CERTIFICATE_POLICIES:Ljava/lang/String;
      42: invokestatic  #1086               // Method org/bouncycastle/jce/provider/CertPathValidatorUtilities.getExtensionValue:(Ljava/security/cert/X509Extension;Ljava/lang/String;)Lorg/bouncycastle/asn1/ASN1Primitive;
      45: invokestatic  #1007               // Method org/bouncycastle/asn1/DERSequence.getInstance:(Ljava/lang/Object;)Lorg/bouncycastle/asn1/ASN1Sequence;
      48: astore        11
      50: goto          69
      53: astore        12
      55: new           #564                // class org/bouncycastle/jce/exception/ExtCertPathValidatorException
      58: dup
      59: ldc           #19                 // String Could not read certificate policies extension from certificate.
      61: aload         12
      63: aload_0
      64: iload_1
      65: invokespecial #1071               // Method org/bouncycastle/jce/exception/ExtCertPathValidatorException."<init>":(Ljava/lang/String;Ljava/lang/Throwable;Ljava/security/cert/CertPath;I)V
      68: athrow
      69: aload         11
      71: ifnull        814
      74: aload_3
      75: ifnull        814
      78: aload         11
      80: invokevirtual #1001               // Method org/bouncycastle/asn1/ASN1Sequence.getObjects:()Ljava/util/Enumeration;
      83: astore        12
      85: new           #526                // class java/util/HashSet
      88: dup
      89: invokespecial #988                // Method java/util/HashSet."<init>":()V
      92: astore        13
      94: aload         12
      96: invokeinterface #1139,  1         // InterfaceMethod java/util/Enumeration.hasMoreElements:()Z
     101: ifeq          213
     104: aload         12
     106: invokeinterface #1140,  1         // InterfaceMethod java/util/Enumeration.nextElement:()Ljava/lang/Object;
     111: invokestatic  #1047               // Method org/bouncycastle/asn1/x509/PolicyInformation.getInstance:(Ljava/lang/Object;)Lorg/bouncycastle/asn1/x509/PolicyInformation;
     114: astore        14
     116: aload         14
     118: invokevirtual #1045               // Method org/bouncycastle/asn1/x509/PolicyInformation.getPolicyIdentifier:()Lorg/bouncycastle/asn1/ASN1ObjectIdentifier;
     121: astore        15
     123: aload         13
     125: aload         15
     127: invokevirtual #996                // Method org/bouncycastle/asn1/ASN1ObjectIdentifier.getId:()Ljava/lang/String;
     130: invokeinterface #1155,  2         // InterfaceMethod java/util/Set.add:(Ljava/lang/Object;)Z
     135: pop
     136: ldc           #1                  // String 2.5.29.32.0
     138: aload         15
     140: invokevirtual #996                // Method org/bouncycastle/asn1/ASN1ObjectIdentifier.getId:()Ljava/lang/String;
     143: invokevirtual #952                // Method java/lang/String.equals:(Ljava/lang/Object;)Z
     146: ifne          210
     149: aconst_null
     150: astore        16
     152: aload         14
     154: invokevirtual #1046               // Method org/bouncycastle/asn1/x509/PolicyInformation.getPolicyQualifiers:()Lorg/bouncycastle/asn1/ASN1Sequence;
     157: invokestatic  #1078               // Method org/bouncycastle/jce/provider/CertPathValidatorUtilities.getQualifierSet:(Lorg/bouncycastle/asn1/ASN1Sequence;)Ljava/util/Set;
     160: astore        16
     162: goto          181
     165: astore        17
     167: new           #564                // class org/bouncycastle/jce/exception/ExtCertPathValidatorException
     170: dup
     171: ldc           #44                 // String Policy qualifier info set could not be build.
     173: aload         17
     175: aload_0
     176: iload_1
     177: invokespecial #1071               // Method org/bouncycastle/jce/exception/ExtCertPathValidatorException."<init>":(Ljava/lang/String;Ljava/lang/Throwable;Ljava/security/cert/CertPath;I)V
     180: athrow
     181: iload         10
     183: aload         4
     185: aload         15
     187: aload         16
     189: invokestatic  #1085               // Method org/bouncycastle/jce/provider/CertPathValidatorUtilities.processCertD1i:(I[Ljava/util/List;Lorg/bouncycastle/asn1/ASN1ObjectIdentifier;Ljava/util/Set;)Z
     192: istore        17
     194: iload         17
     196: ifne          210
     199: iload         10
     201: aload         4
     203: aload         15
     205: aload         16
     207: invokestatic  #1084               // Method org/bouncycastle/jce/provider/CertPathValidatorUtilities.processCertD1ii:(I[Ljava/util/List;Lorg/bouncycastle/asn1/ASN1ObjectIdentifier;Ljava/util/Set;)V
     210: goto          94
     213: aload_2
     214: invokeinterface #1154,  1         // InterfaceMethod java/util/Set.isEmpty:()Z
     219: ifne          233
     222: aload_2
     223: ldc           #1                  // String 2.5.29.32.0
     225: invokeinterface #1156,  2         // InterfaceMethod java/util/Set.contains:(Ljava/lang/Object;)Z
     230: ifeq          251
     233: aload_2
     234: invokeinterface #1153,  1         // InterfaceMethod java/util/Set.clear:()V
     239: aload_2
     240: aload         13
     242: invokeinterface #1158,  2         // InterfaceMethod java/util/Set.addAll:(Ljava/util/Collection;)Z
     247: pop
     248: goto          327
     251: aload_2
     252: invokeinterface #1159,  1         // InterfaceMethod java/util/Set.iterator:()Ljava/util/Iterator;
     257: astore        14
     259: new           #526                // class java/util/HashSet
     262: dup
     263: invokespecial #988                // Method java/util/HashSet."<init>":()V
     266: astore        15
     268: aload         14
     270: invokeinterface #1142,  1         // InterfaceMethod java/util/Iterator.hasNext:()Z
     275: ifeq          312
     278: aload         14
     280: invokeinterface #1143,  1         // InterfaceMethod java/util/Iterator.next:()Ljava/lang/Object;
     285: astore        16
     287: aload         13
     289: aload         16
     291: invokeinterface #1156,  2         // InterfaceMethod java/util/Set.contains:(Ljava/lang/Object;)Z
     296: ifeq          309
     299: aload         15
     301: aload         16
     303: invokeinterface #1155,  2         // InterfaceMethod java/util/Set.add:(Ljava/lang/Object;)Z
     308: pop
     309: goto          268
     312: aload_2
     313: invokeinterface #1153,  1         // InterfaceMethod java/util/Set.clear:()V
     318: aload_2
     319: aload         15
     321: invokeinterface #1158,  2         // InterfaceMethod java/util/Set.addAll:(Ljava/util/Collection;)Z
     326: pop
     327: iload         5
     329: ifgt          352
     332: iload         10
     334: iload         9
     336: if_icmplt     344
     339: iload         6
     341: ifeq          649
     344: aload         8
     346: invokestatic  #1076               // Method org/bouncycastle/jce/provider/CertPathValidatorUtilities.isSelfIssued:(Ljava/security/cert/X509Certificate;)Z
     349: ifeq          649
     352: aload         11
     354: invokevirtual #1001               // Method org/bouncycastle/asn1/ASN1Sequence.getObjects:()Ljava/util/Enumeration;
     357: astore        12
     359: aload         12
     361: invokeinterface #1139,  1         // InterfaceMethod java/util/Enumeration.hasMoreElements:()Z
     366: ifeq          649
     369: aload         12
     371: invokeinterface #1140,  1         // InterfaceMethod java/util/Enumeration.nextElement:()Ljava/lang/Object;
     376: invokestatic  #1047               // Method org/bouncycastle/asn1/x509/PolicyInformation.getInstance:(Ljava/lang/Object;)Lorg/bouncycastle/asn1/x509/PolicyInformation;
     379: astore        14
     381: ldc           #1                  // String 2.5.29.32.0
     383: aload         14
     385: invokevirtual #1045               // Method org/bouncycastle/asn1/x509/PolicyInformation.getPolicyIdentifier:()Lorg/bouncycastle/asn1/ASN1ObjectIdentifier;
     388: invokevirtual #996                // Method org/bouncycastle/asn1/ASN1ObjectIdentifier.getId:()Ljava/lang/String;
     391: invokevirtual #952                // Method java/lang/String.equals:(Ljava/lang/Object;)Z
     394: ifeq          646
     397: aload         14
     399: invokevirtual #1046               // Method org/bouncycastle/asn1/x509/PolicyInformation.getPolicyQualifiers:()Lorg/bouncycastle/asn1/ASN1Sequence;
     402: invokestatic  #1078               // Method org/bouncycastle/jce/provider/CertPathValidatorUtilities.getQualifierSet:(Lorg/bouncycastle/asn1/ASN1Sequence;)Ljava/util/Set;
     405: astore        15
     407: aload         4
     409: iload         10
     411: iconst_1
     412: isub
     413: aaload
     414: astore        16
     416: iconst_0
     417: istore        17
     419: iload         17
     421: aload         16
     423: invokeinterface #1144,  1         // InterfaceMethod java/util/List.size:()I
     428: if_icmpge     643
     431: aload         16
     433: iload         17
     435: invokeinterface #1145,  2         // InterfaceMethod java/util/List.get:(I)Ljava/lang/Object;
     440: checkcast     #572                // class org/bouncycastle/jce/provider/PKIXPolicyNode
     443: astore        18
     445: aload         18
     447: invokevirtual #1110               // Method org/bouncycastle/jce/provider/PKIXPolicyNode.getExpectedPolicies:()Ljava/util/Set;
     450: invokeinterface #1159,  1         // InterfaceMethod java/util/Set.iterator:()Ljava/util/Iterator;
     455: astore        19
     457: aload         19
     459: invokeinterface #1142,  1         // InterfaceMethod java/util/Iterator.hasNext:()Z
     464: ifeq          637
     467: aload         19
     469: invokeinterface #1143,  1         // InterfaceMethod java/util/Iterator.next:()Ljava/lang/Object;
     474: astore        20
     476: aload         20
     478: instanceof    #502                // class java/lang/String
     481: ifeq          494
     484: aload         20
     486: checkcast     #502                // class java/lang/String
     489: astore        21
     491: goto          512
     494: aload         20
     496: instanceof    #535                // class org/bouncycastle/asn1/ASN1ObjectIdentifier
     499: ifeq          457
     502: aload         20
     504: checkcast     #535                // class org/bouncycastle/asn1/ASN1ObjectIdentifier
     507: invokevirtual #996                // Method org/bouncycastle/asn1/ASN1ObjectIdentifier.getId:()Ljava/lang/String;
     510: astore        21
     512: iconst_0
     513: istore        22
     515: aload         18
     517: invokevirtual #1109               // Method org/bouncycastle/jce/provider/PKIXPolicyNode.getChildren:()Ljava/util/Iterator;
     520: astore        23
     522: aload         23
     524: invokeinterface #1142,  1         // InterfaceMethod java/util/Iterator.hasNext:()Z
     529: ifeq          563
     532: aload         23
     534: invokeinterface #1143,  1         // InterfaceMethod java/util/Iterator.next:()Ljava/lang/Object;
     539: checkcast     #572                // class org/bouncycastle/jce/provider/PKIXPolicyNode
     542: astore        24
     544: aload         21
     546: aload         24
     548: invokevirtual #1107               // Method org/bouncycastle/jce/provider/PKIXPolicyNode.getValidPolicy:()Ljava/lang/String;
     551: invokevirtual #952                // Method java/lang/String.equals:(Ljava/lang/Object;)Z
     554: ifeq          560
     557: iconst_1
     558: istore        22
     560: goto          522
     563: iload         22
     565: ifne          634
     568: new           #526                // class java/util/HashSet
     571: dup
     572: invokespecial #988                // Method java/util/HashSet."<init>":()V
     575: astore        24
     577: aload         24
     579: aload         21
     581: invokeinterface #1155,  2         // InterfaceMethod java/util/Set.add:(Ljava/lang/Object;)Z
     586: pop
     587: new           #572                // class org/bouncycastle/jce/provider/PKIXPolicyNode
     590: dup
     591: new           #521                // class java/util/ArrayList
     594: dup
     595: invokespecial #984                // Method java/util/ArrayList."<init>":()V
     598: iload         10
     600: aload         24
     602: aload         18
     604: aload         15
     606: aload         21
     608: iconst_0
     609: invokespecial #1113               // Method org/bouncycastle/jce/provider/PKIXPolicyNode."<init>":(Ljava/util/List;ILjava/util/Set;Ljava/security/cert/PolicyNode;Ljava/util/Set;Ljava/lang/String;Z)V
     612: astore        25
     614: aload         18
     616: aload         25
     618: invokevirtual #1111               // Method org/bouncycastle/jce/provider/PKIXPolicyNode.addChild:(Lorg/bouncycastle/jce/provider/PKIXPolicyNode;)V
     621: aload         4
     623: iload         10
     625: aaload
     626: aload         25
     628: invokeinterface #1146,  2         // InterfaceMethod java/util/List.add:(Ljava/lang/Object;)Z
     633: pop
     634: goto          457
     637: iinc          17, 1
     640: goto          419
     643: goto          649
     646: goto          359
     649: aload_3
     650: astore        14
     652: iload         10
     654: iconst_1
     655: isub
     656: istore        15
     658: iload         15
     660: iflt          738
     663: aload         4
     665: iload         15
     667: aaload
     668: astore        16
     670: iconst_0
     671: istore        17
     673: iload         17
     675: aload         16
     677: invokeinterface #1144,  1         // InterfaceMethod java/util/List.size:()I
     682: if_icmpge     732
     685: aload         16
     687: iload         17
     689: invokeinterface #1145,  2         // InterfaceMethod java/util/List.get:(I)Ljava/lang/Object;
     694: checkcast     #572                // class org/bouncycastle/jce/provider/PKIXPolicyNode
     697: astore        18
     699: aload         18
     701: invokevirtual #1105               // Method org/bouncycastle/jce/provider/PKIXPolicyNode.hasChildren:()Z
     704: ifne          726
     707: aload         14
     709: aload         4
     711: aload         18
     713: invokestatic  #1088               // Method org/bouncycastle/jce/provider/CertPathValidatorUtilities.removePolicyNode:(Lorg/bouncycastle/jce/provider/PKIXPolicyNode;[Ljava/util/List;Lorg/bouncycastle/jce/provider/PKIXPolicyNode;)Lorg/bouncycastle/jce/provider/PKIXPolicyNode;
     716: astore        14
     718: aload         14
     720: ifnonnull     726
     723: goto          732
     726: iinc          17, 1
     729: goto          673
     732: iinc          15, -1
     735: goto          658
     738: aload         8
     740: invokevirtual #980                // Method java/security/cert/X509Certificate.getCriticalExtensionOIDs:()Ljava/util/Set;
     743: astore        15
     745: aload         15
     747: ifnull        811
     750: aload         15
     752: getstatic     #934                // Field CERTIFICATE_POLICIES:Ljava/lang/String;
     755: invokeinterface #1156,  2         // InterfaceMethod java/util/Set.contains:(Ljava/lang/Object;)Z
     760: istore        16
     762: aload         4
     764: iload         10
     766: aaload
     767: astore        17
     769: iconst_0
     770: istore        18
     772: iload         18
     774: aload         17
     776: invokeinterface #1144,  1         // InterfaceMethod java/util/List.size:()I
     781: if_icmpge     811
     784: aload         17
     786: iload         18
     788: invokeinterface #1145,  2         // InterfaceMethod java/util/List.get:(I)Ljava/lang/Object;
     793: checkcast     #572                // class org/bouncycastle/jce/provider/PKIXPolicyNode
     796: astore        19
     798: aload         19
     800: iload         16
     802: invokevirtual #1106               // Method org/bouncycastle/jce/provider/PKIXPolicyNode.setCritical:(Z)V
     805: iinc          18, 1
     808: goto          772
     811: aload         14
     813: areturn
     814: aconst_null
     815: areturn
    Exception table:
       from    to  target type
          37    50    53   Class org/bouncycastle/jce/provider/AnnotatedException
         152   162   165   Class java/security/cert/CertPathValidatorException

  protected static void processCertA(java.security.cert.CertPath, org.bouncycastle.jcajce.PKIXExtendedParameters, int, java.security.PublicKey, boolean, org.bouncycastle.asn1.x500.X500Name, java.security.cert.X509Certificate, org.bouncycastle.jcajce.util.JcaJceHelper) throws org.bouncycastle.jce.exception.ExtCertPathValidatorException;
    Code:
       0: aload_0
       1: invokevirtual #959                // Method java/security/cert/CertPath.getCertificates:()Ljava/util/List;
       4: astore        8
       6: aload         8
       8: iload_2
       9: invokeinterface #1145,  2         // InterfaceMethod java/util/List.get:(I)Ljava/lang/Object;
      14: checkcast     #518                // class java/security/cert/X509Certificate
      17: astore        9
      19: iload         4
      21: ifne          53
      24: aload         9
      26: aload_3
      27: aload_1
      28: invokevirtual #1060               // Method org/bouncycastle/jcajce/PKIXExtendedParameters.getSigProvider:()Ljava/lang/String;
      31: invokestatic  #1079               // Method org/bouncycastle/jce/provider/CertPathValidatorUtilities.verifyX509Certificate:(Ljava/security/cert/X509Certificate;Ljava/security/PublicKey;Ljava/lang/String;)V
      34: goto          53
      37: astore        10
      39: new           #564                // class org/bouncycastle/jce/exception/ExtCertPathValidatorException
      42: dup
      43: ldc           #20                 // String Could not validate certificate signature.
      45: aload         10
      47: aload_0
      48: iload_2
      49: invokespecial #1071               // Method org/bouncycastle/jce/exception/ExtCertPathValidatorException."<init>":(Ljava/lang/String;Ljava/lang/Throwable;Ljava/security/cert/CertPath;I)V
      52: athrow
      53: aload         9
      55: aload_1
      56: aload_0
      57: iload_2
      58: invokestatic  #1082               // Method org/bouncycastle/jce/provider/CertPathValidatorUtilities.getValidCertDateFromValidityModel:(Lorg/bouncycastle/jcajce/PKIXExtendedParameters;Ljava/security/cert/CertPath;I)Ljava/util/Date;
      61: invokevirtual #979                // Method java/security/cert/X509Certificate.checkValidity:(Ljava/util/Date;)V
      64: goto          158
      67: astore        10
      69: new           #564                // class org/bouncycastle/jce/exception/ExtCertPathValidatorException
      72: dup
      73: new           #503                // class java/lang/StringBuilder
      76: dup
      77: invokespecial #953                // Method java/lang/StringBuilder."<init>":()V
      80: ldc           #21                 // String Could not validate certificate:
      82: invokevirtual #956                // Method java/lang/StringBuilder.append:(Ljava/lang/String;)Ljava/lang/StringBuilder;
      85: aload         10
      87: invokevirtual #963                // Method java/security/cert/CertificateExpiredException.getMessage:()Ljava/lang/String;
      90: invokevirtual #956                // Method java/lang/StringBuilder.append:(Ljava/lang/String;)Ljava/lang/StringBuilder;
      93: invokevirtual #954                // Method java/lang/StringBuilder.toString:()Ljava/lang/String;
      96: aload         10
      98: aload_0
      99: iload_2
     100: invokespecial #1071               // Method org/bouncycastle/jce/exception/ExtCertPathValidatorException."<init>":(Ljava/lang/String;Ljava/lang/Throwable;Ljava/security/cert/CertPath;I)V
     103: athrow
     104: astore        10
     106: new           #564                // class org/bouncycastle/jce/exception/ExtCertPathValidatorException
     109: dup
     110: new           #503                // class java/lang/StringBuilder
     113: dup
     114: invokespecial #953                // Method java/lang/StringBuilder."<init>":()V
     117: ldc           #21                 // String Could not validate certificate:
     119: invokevirtual #956                // Method java/lang/StringBuilder.append:(Ljava/lang/String;)Ljava/lang/StringBuilder;
     122: aload         10
     124: invokevirtual #964                // Method java/security/cert/CertificateNotYetValidException.getMessage:()Ljava/lang/String;
     127: invokevirtual #956                // Method java/lang/StringBuilder.append:(Ljava/lang/String;)Ljava/lang/StringBuilder;
     130: invokevirtual #954                // Method java/lang/StringBuilder.toString:()Ljava/lang/String;
     133: aload         10
     135: aload_0
     136: iload_2
     137: invokespecial #1071               // Method org/bouncycastle/jce/exception/ExtCertPathValidatorException."<init>":(Ljava/lang/String;Ljava/lang/Throwable;Ljava/security/cert/CertPath;I)V
     140: athrow
     141: astore        10
     143: new           #564                // class org/bouncycastle/jce/exception/ExtCertPathValidatorException
     146: dup
     147: ldc_w         #462                // String Could not validate time of certificate.
     150: aload         10
     152: aload_0
     153: iload_2
     154: invokespecial #1071               // Method org/bouncycastle/jce/exception/ExtCertPathValidatorException."<init>":(Ljava/lang/String;Ljava/lang/Throwable;Ljava/security/cert/CertPath;I)V
     157: athrow
     158: aload_1
     159: invokevirtual #1057               // Method org/bouncycastle/jcajce/PKIXExtendedParameters.isRevocationEnabled:()Z
     162: ifeq          226
     165: aload_1
     166: aload         9
     168: aload_1
     169: aload_0
     170: iload_2
     171: invokestatic  #1082               // Method org/bouncycastle/jce/provider/CertPathValidatorUtilities.getValidCertDateFromValidityModel:(Lorg/bouncycastle/jcajce/PKIXExtendedParameters;Ljava/security/cert/CertPath;I)Ljava/util/Date;
     174: aload         6
     176: aload_3
     177: aload         8
     179: aload         7
     181: invokestatic  #1125               // Method checkCRLs:(Lorg/bouncycastle/jcajce/PKIXExtendedParameters;Ljava/security/cert/X509Certificate;Ljava/util/Date;Ljava/security/cert/X509Certificate;Ljava/security/PublicKey;Ljava/util/List;Lorg/bouncycastle/jcajce/util/JcaJceHelper;)V
     184: goto          226
     187: astore        10
     189: aload         10
     191: astore        11
     193: aconst_null
     194: aload         10
     196: invokevirtual #1074               // Method org/bouncycastle/jce/provider/AnnotatedException.getCause:()Ljava/lang/Throwable;
     199: if_acmpeq     209
     202: aload         10
     204: invokevirtual #1074               // Method org/bouncycastle/jce/provider/AnnotatedException.getCause:()Ljava/lang/Throwable;
     207: astore        11
     209: new           #564                // class org/bouncycastle/jce/exception/ExtCertPathValidatorException
     212: dup
     213: aload         10
     215: invokevirtual #1072               // Method org/bouncycastle/jce/provider/AnnotatedException.getMessage:()Ljava/lang/String;
     218: aload         11
     220: aload_0
     221: iload_2
     222: invokespecial #1071               // Method org/bouncycastle/jce/exception/ExtCertPathValidatorException."<init>":(Ljava/lang/String;Ljava/lang/Throwable;Ljava/security/cert/CertPath;I)V
     225: athrow
     226: aload         9
     228: invokestatic  #1114               // Method org/bouncycastle/jce/provider/PrincipalUtils.getEncodedIssuerPrincipal:(Ljava/lang/Object;)Lorg/bouncycastle/asn1/x500/X500Name;
     231: aload         5
     233: invokevirtual #1011               // Method org/bouncycastle/asn1/x500/X500Name.equals:(Ljava/lang/Object;)Z
     236: ifne          291
     239: new           #564                // class org/bouncycastle/jce/exception/ExtCertPathValidatorException
     242: dup
     243: new           #503                // class java/lang/StringBuilder
     246: dup
     247: invokespecial #953                // Method java/lang/StringBuilder."<init>":()V
     250: ldc_w         #471                // String IssuerName(
     253: invokevirtual #956                // Method java/lang/StringBuilder.append:(Ljava/lang/String;)Ljava/lang/StringBuilder;
     256: aload         9
     258: invokestatic  #1114               // Method org/bouncycastle/jce/provider/PrincipalUtils.getEncodedIssuerPrincipal:(Ljava/lang/Object;)Lorg/bouncycastle/asn1/x500/X500Name;
     261: invokevirtual #955                // Method java/lang/StringBuilder.append:(Ljava/lang/Object;)Ljava/lang/StringBuilder;
     264: ldc_w         #452                // String ) does not match SubjectName(
     267: invokevirtual #956                // Method java/lang/StringBuilder.append:(Ljava/lang/String;)Ljava/lang/StringBuilder;
     270: aload         5
     272: invokevirtual #955                // Method java/lang/StringBuilder.append:(Ljava/lang/Object;)Ljava/lang/StringBuilder;
     275: ldc_w         #453                // String ) of signing certificate.
     278: invokevirtual #956                // Method java/lang/StringBuilder.append:(Ljava/lang/String;)Ljava/lang/StringBuilder;
     281: invokevirtual #954                // Method java/lang/StringBuilder.toString:()Ljava/lang/String;
     284: aconst_null
     285: aload_0
     286: iload_2
     287: invokespecial #1071               // Method org/bouncycastle/jce/exception/ExtCertPathValidatorException."<init>":(Ljava/lang/String;Ljava/lang/Throwable;Ljava/security/cert/CertPath;I)V
     290: athrow
     291: return
    Exception table:
       from    to  target type
          24    34    37   Class java/security/GeneralSecurityException
          53    64    67   Class java/security/cert/CertificateExpiredException
          53    64   104   Class java/security/cert/CertificateNotYetValidException
          53    64   141   Class org/bouncycastle/jce/provider/AnnotatedException
         165   184   187   Class org/bouncycastle/jce/provider/AnnotatedException

  protected static int prepareNextCertI1(java.security.cert.CertPath, int, int) throws java.security.cert.CertPathValidatorException;
    Code:
       0: aload_0
       1: invokevirtual #959                // Method java/security/cert/CertPath.getCertificates:()Ljava/util/List;
       4: astore_3
       5: aload_3
       6: iload_1
       7: invokeinterface #1145,  2         // InterfaceMethod java/util/List.get:(I)Ljava/lang/Object;
      12: checkcast     #518                // class java/security/cert/X509Certificate
      15: astore        4
      17: aconst_null
      18: astore        5
      20: aload         4
      22: getstatic     #943                // Field POLICY_CONSTRAINTS:Ljava/lang/String;
      25: invokestatic  #1086               // Method org/bouncycastle/jce/provider/CertPathValidatorUtilities.getExtensionValue:(Ljava/security/cert/X509Extension;Ljava/lang/String;)Lorg/bouncycastle/asn1/ASN1Primitive;
      28: invokestatic  #1007               // Method org/bouncycastle/asn1/DERSequence.getInstance:(Ljava/lang/Object;)Lorg/bouncycastle/asn1/ASN1Sequence;
      31: astore        5
      33: goto          53
      36: astore        6
      38: new           #564                // class org/bouncycastle/jce/exception/ExtCertPathValidatorException
      41: dup
      42: ldc_w         #480                // String Policy constraints extension cannot be decoded.
      45: aload         6
      47: aload_0
      48: iload_1
      49: invokespecial #1071               // Method org/bouncycastle/jce/exception/ExtCertPathValidatorException."<init>":(Ljava/lang/String;Ljava/lang/Throwable;Ljava/security/cert/CertPath;I)V
      52: athrow
      53: aload         5
      55: ifnull        138
      58: aload         5
      60: invokevirtual #1001               // Method org/bouncycastle/asn1/ASN1Sequence.getObjects:()Ljava/util/Enumeration;
      63: astore        7
      65: aload         7
      67: invokeinterface #1139,  1         // InterfaceMethod java/util/Enumeration.hasMoreElements:()Z
      72: ifeq          138
      75: aload         7
      77: invokeinterface #1140,  1         // InterfaceMethod java/util/Enumeration.nextElement:()Ljava/lang/Object;
      82: invokestatic  #1005               // Method org/bouncycastle/asn1/ASN1TaggedObject.getInstance:(Ljava/lang/Object;)Lorg/bouncycastle/asn1/ASN1TaggedObject;
      85: astore        8
      87: aload         8
      89: invokevirtual #1004               // Method org/bouncycastle/asn1/ASN1TaggedObject.getTagNo:()I
      92: ifne          118
      95: aload         8
      97: iconst_0
      98: invokestatic  #995                // Method org/bouncycastle/asn1/ASN1Integer.getInstance:(Lorg/bouncycastle/asn1/ASN1TaggedObject;Z)Lorg/bouncycastle/asn1/ASN1Integer;
     101: invokevirtual #993                // Method org/bouncycastle/asn1/ASN1Integer.intValueExact:()I
     104: istore        6
     106: iload         6
     108: iload_2
     109: if_icmpge     115
     112: iload         6
     114: ireturn
     115: goto          138
     118: goto          65
     121: astore        8
     123: new           #564                // class org/bouncycastle/jce/exception/ExtCertPathValidatorException
     126: dup
     127: ldc_w         #481                // String Policy constraints extension contents cannot be decoded.
     130: aload         8
     132: aload_0
     133: iload_1
     134: invokespecial #1071               // Method org/bouncycastle/jce/exception/ExtCertPathValidatorException."<init>":(Ljava/lang/String;Ljava/lang/Throwable;Ljava/security/cert/CertPath;I)V
     137: athrow
     138: iload_2
     139: ireturn
    Exception table:
       from    to  target type
          20    33    36   Class java/lang/Exception
          75   114   121   Class java/lang/IllegalArgumentException

  protected static int prepareNextCertI2(java.security.cert.CertPath, int, int) throws java.security.cert.CertPathValidatorException;
    Code:
       0: aload_0
       1: invokevirtual #959                // Method java/security/cert/CertPath.getCertificates:()Ljava/util/List;
       4: astore_3
       5: aload_3
       6: iload_1
       7: invokeinterface #1145,  2         // InterfaceMethod java/util/List.get:(I)Ljava/lang/Object;
      12: checkcast     #518                // class java/security/cert/X509Certificate
      15: astore        4
      17: aconst_null
      18: astore        5
      20: aload         4
      22: getstatic     #943                // Field POLICY_CONSTRAINTS:Ljava/lang/String;
      25: invokestatic  #1086               // Method org/bouncycastle/jce/provider/CertPathValidatorUtilities.getExtensionValue:(Ljava/security/cert/X509Extension;Ljava/lang/String;)Lorg/bouncycastle/asn1/ASN1Primitive;
      28: invokestatic  #1007               // Method org/bouncycastle/asn1/DERSequence.getInstance:(Ljava/lang/Object;)Lorg/bouncycastle/asn1/ASN1Sequence;
      31: astore        5
      33: goto          53
      36: astore        6
      38: new           #564                // class org/bouncycastle/jce/exception/ExtCertPathValidatorException
      41: dup
      42: ldc_w         #480                // String Policy constraints extension cannot be decoded.
      45: aload         6
      47: aload_0
      48: iload_1
      49: invokespecial #1071               // Method org/bouncycastle/jce/exception/ExtCertPathValidatorException."<init>":(Ljava/lang/String;Ljava/lang/Throwable;Ljava/security/cert/CertPath;I)V
      52: athrow
      53: aload         5
      55: ifnull        139
      58: aload         5
      60: invokevirtual #1001               // Method org/bouncycastle/asn1/ASN1Sequence.getObjects:()Ljava/util/Enumeration;
      63: astore        7
      65: aload         7
      67: invokeinterface #1139,  1         // InterfaceMethod java/util/Enumeration.hasMoreElements:()Z
      72: ifeq          139
      75: aload         7
      77: invokeinterface #1140,  1         // InterfaceMethod java/util/Enumeration.nextElement:()Ljava/lang/Object;
      82: invokestatic  #1005               // Method org/bouncycastle/asn1/ASN1TaggedObject.getInstance:(Ljava/lang/Object;)Lorg/bouncycastle/asn1/ASN1TaggedObject;
      85: astore        8
      87: aload         8
      89: invokevirtual #1004               // Method org/bouncycastle/asn1/ASN1TaggedObject.getTagNo:()I
      92: iconst_1
      93: if_icmpne     119
      96: aload         8
      98: iconst_0
      99: invokestatic  #995                // Method org/bouncycastle/asn1/ASN1Integer.getInstance:(Lorg/bouncycastle/asn1/ASN1TaggedObject;Z)Lorg/bouncycastle/asn1/ASN1Integer;
     102: invokevirtual #993                // Method org/bouncycastle/asn1/ASN1Integer.intValueExact:()I
     105: istore        6
     107: iload         6
     109: iload_2
     110: if_icmpge     116
     113: iload         6
     115: ireturn
     116: goto          139
     119: goto          65
     122: astore        8
     124: new           #564                // class org/bouncycastle/jce/exception/ExtCertPathValidatorException
     127: dup
     128: ldc_w         #481                // String Policy constraints extension contents cannot be decoded.
     131: aload         8
     133: aload_0
     134: iload_1
     135: invokespecial #1071               // Method org/bouncycastle/jce/exception/ExtCertPathValidatorException."<init>":(Ljava/lang/String;Ljava/lang/Throwable;Ljava/security/cert/CertPath;I)V
     138: athrow
     139: iload_2
     140: ireturn
    Exception table:
       from    to  target type
          20    33    36   Class java/lang/Exception
          75   115   122   Class java/lang/IllegalArgumentException

  protected static void prepareNextCertG(java.security.cert.CertPath, int, org.bouncycastle.jce.provider.PKIXNameConstraintValidator) throws java.security.cert.CertPathValidatorException;
    Code:
       0: aload_0
       1: invokevirtual #959                // Method java/security/cert/CertPath.getCertificates:()Ljava/util/List;
       4: astore_3
       5: aload_3
       6: iload_1
       7: invokeinterface #1145,  2         // InterfaceMethod java/util/List.get:(I)Ljava/lang/Object;
      12: checkcast     #518                // class java/security/cert/X509Certificate
      15: astore        4
      17: aconst_null
      18: astore        5
      20: aload         4
      22: getstatic     #942                // Field NAME_CONSTRAINTS:Ljava/lang/String;
      25: invokestatic  #1086               // Method org/bouncycastle/jce/provider/CertPathValidatorUtilities.getExtensionValue:(Ljava/security/cert/X509Extension;Ljava/lang/String;)Lorg/bouncycastle/asn1/ASN1Primitive;
      28: invokestatic  #1007               // Method org/bouncycastle/asn1/DERSequence.getInstance:(Ljava/lang/Object;)Lorg/bouncycastle/asn1/ASN1Sequence;
      31: astore        6
      33: aload         6
      35: ifnull        45
      38: aload         6
      40: invokestatic  #1044               // Method org/bouncycastle/asn1/x509/NameConstraints.getInstance:(Ljava/lang/Object;)Lorg/bouncycastle/asn1/x509/NameConstraints;
      43: astore        5
      45: goto          65
      48: astore        6
      50: new           #564                // class org/bouncycastle/jce/exception/ExtCertPathValidatorException
      53: dup
      54: ldc_w         #473                // String Name constraints extension could not be decoded.
      57: aload         6
      59: aload_0
      60: iload_1
      61: invokespecial #1071               // Method org/bouncycastle/jce/exception/ExtCertPathValidatorException."<init>":(Ljava/lang/String;Ljava/lang/Throwable;Ljava/security/cert/CertPath;I)V
      64: athrow
      65: aload         5
      67: ifnull        166
      70: aload         5
      72: invokevirtual #1043               // Method org/bouncycastle/asn1/x509/NameConstraints.getPermittedSubtrees:()[Lorg/bouncycastle/asn1/x509/GeneralSubtree;
      75: astore        6
      77: aload         6
      79: ifnull        108
      82: aload_2
      83: aload         6
      85: invokevirtual #1104               // Method org/bouncycastle/jce/provider/PKIXNameConstraintValidator.intersectPermittedSubtree:([Lorg/bouncycastle/asn1/x509/GeneralSubtree;)V
      88: goto          108
      91: astore        7
      93: new           #564                // class org/bouncycastle/jce/exception/ExtCertPathValidatorException
      96: dup
      97: ldc_w         #478                // String Permitted subtrees cannot be build from name constraints extension.
     100: aload         7
     102: aload_0
     103: iload_1
     104: invokespecial #1071               // Method org/bouncycastle/jce/exception/ExtCertPathValidatorException."<init>":(Ljava/lang/String;Ljava/lang/Throwable;Ljava/security/cert/CertPath;I)V
     107: athrow
     108: aload         5
     110: invokevirtual #1042               // Method org/bouncycastle/asn1/x509/NameConstraints.getExcludedSubtrees:()[Lorg/bouncycastle/asn1/x509/GeneralSubtree;
     113: astore        7
     115: aload         7
     117: ifnull        166
     120: iconst_0
     121: istore        8
     123: iload         8
     125: aload         7
     127: arraylength
     128: if_icmpeq     166
     131: aload_2
     132: aload         7
     134: iload         8
     136: aaload
     137: invokevirtual #1103               // Method org/bouncycastle/jce/provider/PKIXNameConstraintValidator.addExcludedSubtree:(Lorg/bouncycastle/asn1/x509/GeneralSubtree;)V
     140: goto          160
     143: astore        9
     145: new           #564                // class org/bouncycastle/jce/exception/ExtCertPathValidatorException
     148: dup
     149: ldc_w         #465                // String Excluded subtrees cannot be build from name constraints extension.
     152: aload         9
     154: aload_0
     155: iload_1
     156: invokespecial #1071               // Method org/bouncycastle/jce/exception/ExtCertPathValidatorException."<init>":(Ljava/lang/String;Ljava/lang/Throwable;Ljava/security/cert/CertPath;I)V
     159: athrow
     160: iinc          8, 1
     163: goto          123
     166: return
    Exception table:
       from    to  target type
          20    45    48   Class java/lang/Exception
          82    88    91   Class java/lang/Exception
         131   140   143   Class java/lang/Exception

  private static void checkCRL(org.bouncycastle.asn1.x509.DistributionPoint, org.bouncycastle.jcajce.PKIXExtendedParameters, java.security.cert.X509Certificate, java.util.Date, java.security.cert.X509Certificate, java.security.PublicKey, org.bouncycastle.jce.provider.CertStatus, org.bouncycastle.jce.provider.ReasonsMask, java.util.List, org.bouncycastle.jcajce.util.JcaJceHelper) throws org.bouncycastle.jce.provider.AnnotatedException;
    Code:
       0: new           #523                // class java/util/Date
       3: dup
       4: invokestatic  #957                // Method java/lang/System.currentTimeMillis:()J
       7: invokespecial #986                // Method java/util/Date."<init>":(J)V
      10: astore        10
      12: aload_3
      13: invokevirtual #985                // Method java/util/Date.getTime:()J
      16: aload         10
      18: invokevirtual #985                // Method java/util/Date.getTime:()J
      21: lcmp
      22: ifle          36
      25: new           #565                // class org/bouncycastle/jce/provider/AnnotatedException
      28: dup
      29: ldc_w         #484                // String Validation time is in future.
      32: invokespecial #1073               // Method org/bouncycastle/jce/provider/AnnotatedException."<init>":(Ljava/lang/String;)V
      35: athrow
      36: aload_0
      37: aload_2
      38: aload         10
      40: aload_1
      41: invokestatic  #1090               // Method org/bouncycastle/jce/provider/CertPathValidatorUtilities.getCompleteCRLs:(Lorg/bouncycastle/asn1/x509/DistributionPoint;Ljava/lang/Object;Ljava/util/Date;Lorg/bouncycastle/jcajce/PKIXExtendedParameters;)Ljava/util/Set;
      44: astore        11
      46: iconst_0
      47: istore        12
      49: aconst_null
      50: astore        13
      52: aload         11
      54: invokeinterface #1159,  1         // InterfaceMethod java/util/Set.iterator:()Ljava/util/Iterator;
      59: astore        14
      61: aload         14
      63: invokeinterface #1142,  1         // InterfaceMethod java/util/Iterator.hasNext:()Z
      68: ifeq          468
      71: aload         6
      73: invokevirtual #1091               // Method org/bouncycastle/jce/provider/CertStatus.getCertStatus:()I
      76: bipush        11
      78: if_icmpne     468
      81: aload         7
      83: invokevirtual #1129               // Method org/bouncycastle/jce/provider/ReasonsMask.isAllReasons:()Z
      86: ifne          468
      89: aload         14
      91: invokeinterface #1143,  1         // InterfaceMethod java/util/Iterator.next:()Ljava/lang/Object;
      96: checkcast     #515                // class java/security/cert/X509CRL
      99: astore        15
     101: aload         15
     103: aload_0
     104: invokestatic  #1122               // Method processCRLD:(Ljava/security/cert/X509CRL;Lorg/bouncycastle/asn1/x509/DistributionPoint;)Lorg/bouncycastle/jce/provider/ReasonsMask;
     107: astore        16
     109: aload         16
     111: aload         7
     113: invokevirtual #1132               // Method org/bouncycastle/jce/provider/ReasonsMask.hasNewReasons:(Lorg/bouncycastle/jce/provider/ReasonsMask;)Z
     116: ifne          122
     119: goto          61
     122: aload         15
     124: aload_2
     125: aload         4
     127: aload         5
     129: aload_1
     130: aload         8
     132: aload         9
     134: invokestatic  #1126               // Method processCRLF:(Ljava/security/cert/X509CRL;Ljava/lang/Object;Ljava/security/cert/X509Certificate;Ljava/security/PublicKey;Lorg/bouncycastle/jcajce/PKIXExtendedParameters;Ljava/util/List;Lorg/bouncycastle/jcajce/util/JcaJceHelper;)Ljava/util/Set;
     137: astore        17
     139: aload         15
     141: aload         17
     143: invokestatic  #1117               // Method processCRLG:(Ljava/security/cert/X509CRL;Ljava/util/Set;)Ljava/security/PublicKey;
     146: astore        18
     148: aconst_null
     149: astore        19
     151: aload         10
     153: astore        20
     155: aload_1
     156: invokevirtual #1061               // Method org/bouncycastle/jcajce/PKIXExtendedParameters.getDate:()Ljava/util/Date;
     159: ifnull        168
     162: aload_1
     163: invokevirtual #1061               // Method org/bouncycastle/jcajce/PKIXExtendedParameters.getDate:()Ljava/util/Date;
     166: astore        20
     168: aload_1
     169: invokevirtual #1058               // Method org/bouncycastle/jcajce/PKIXExtendedParameters.isUseDeltasEnabled:()Z
     172: ifeq          201
     175: aload         20
     177: aload         15
     179: aload_1
     180: invokevirtual #1063               // Method org/bouncycastle/jcajce/PKIXExtendedParameters.getCertStores:()Ljava/util/List;
     183: aload_1
     184: invokevirtual #1062               // Method org/bouncycastle/jcajce/PKIXExtendedParameters.getCRLStores:()Ljava/util/List;
     187: invokestatic  #1089               // Method org/bouncycastle/jce/provider/CertPathValidatorUtilities.getDeltaCRLs:(Ljava/util/Date;Ljava/security/cert/X509CRL;Ljava/util/List;Ljava/util/List;)Ljava/util/Set;
     190: astore        21
     192: aload         21
     194: aload         18
     196: invokestatic  #1120               // Method processCRLH:(Ljava/util/Set;Ljava/security/PublicKey;)Ljava/security/cert/X509CRL;
     199: astore        19
     201: aload_1
     202: invokevirtual #1055               // Method org/bouncycastle/jcajce/PKIXExtendedParameters.getValidityModel:()I
     205: iconst_1
     206: if_icmpeq     239
     209: aload_2
     210: invokevirtual #978                // Method java/security/cert/X509Certificate.getNotAfter:()Ljava/util/Date;
     213: invokevirtual #985                // Method java/util/Date.getTime:()J
     216: aload         15
     218: invokevirtual #968                // Method java/security/cert/X509CRL.getThisUpdate:()Ljava/util/Date;
     221: invokevirtual #985                // Method java/util/Date.getTime:()J
     224: lcmp
     225: ifge          239
     228: new           #565                // class org/bouncycastle/jce/provider/AnnotatedException
     231: dup
     232: ldc_w         #475                // String No valid CRL for current time found.
     235: invokespecial #1073               // Method org/bouncycastle/jce/provider/AnnotatedException."<init>":(Ljava/lang/String;)V
     238: athrow
     239: aload_0
     240: aload_2
     241: aload         15
     243: invokestatic  #1118               // Method processCRLB1:(Lorg/bouncycastle/asn1/x509/DistributionPoint;Ljava/lang/Object;Ljava/security/cert/X509CRL;)V
     246: aload_0
     247: aload_2
     248: aload         15
     250: invokestatic  #1119               // Method processCRLB2:(Lorg/bouncycastle/asn1/x509/DistributionPoint;Ljava/lang/Object;Ljava/security/cert/X509CRL;)V
     253: aload         19
     255: aload         15
     257: aload_1
     258: invokestatic  #1121               // Method processCRLC:(Ljava/security/cert/X509CRL;Ljava/security/cert/X509CRL;Lorg/bouncycastle/jcajce/PKIXExtendedParameters;)V
     261: aload_3
     262: aload         19
     264: aload_2
     265: aload         6
     267: aload_1
     268: invokestatic  #1124               // Method processCRLI:(Ljava/util/Date;Ljava/security/cert/X509CRL;Ljava/lang/Object;Lorg/bouncycastle/jce/provider/CertStatus;Lorg/bouncycastle/jcajce/PKIXExtendedParameters;)V
     271: aload_3
     272: aload         15
     274: aload_2
     275: aload         6
     277: invokestatic  #1123               // Method processCRLJ:(Ljava/util/Date;Ljava/security/cert/X509CRL;Ljava/lang/Object;Lorg/bouncycastle/jce/provider/CertStatus;)V
     280: aload         6
     282: invokevirtual #1091               // Method org/bouncycastle/jce/provider/CertStatus.getCertStatus:()I
     285: bipush        8
     287: if_icmpne     297
     290: aload         6
     292: bipush        11
     294: invokevirtual #1093               // Method org/bouncycastle/jce/provider/CertStatus.setCertStatus:(I)V
     297: aload         7
     299: aload         16
     301: invokevirtual #1131               // Method org/bouncycastle/jce/provider/ReasonsMask.addReasons:(Lorg/bouncycastle/jce/provider/ReasonsMask;)V
     304: aload         15
     306: invokevirtual #969                // Method java/security/cert/X509CRL.getCriticalExtensionOIDs:()Ljava/util/Set;
     309: astore        21
     311: aload         21
     313: ifnull        376
     316: new           #526                // class java/util/HashSet
     319: dup
     320: aload         21
     322: invokespecial #989                // Method java/util/HashSet."<init>":(Ljava/util/Collection;)V
     325: astore        21
     327: aload         21
     329: getstatic     #925                // Field org/bouncycastle/asn1/x509/Extension.issuingDistributionPoint:Lorg/bouncycastle/asn1/ASN1ObjectIdentifier;
     332: invokevirtual #996                // Method org/bouncycastle/asn1/ASN1ObjectIdentifier.getId:()Ljava/lang/String;
     335: invokeinterface #1157,  2         // InterfaceMethod java/util/Set.remove:(Ljava/lang/Object;)Z
     340: pop
     341: aload         21
     343: getstatic     #922                // Field org/bouncycastle/asn1/x509/Extension.deltaCRLIndicator:Lorg/bouncycastle/asn1/ASN1ObjectIdentifier;
     346: invokevirtual #996                // Method org/bouncycastle/asn1/ASN1ObjectIdentifier.getId:()Ljava/lang/String;
     349: invokeinterface #1157,  2         // InterfaceMethod java/util/Set.remove:(Ljava/lang/Object;)Z
     354: pop
     355: aload         21
     357: invokeinterface #1154,  1         // InterfaceMethod java/util/Set.isEmpty:()Z
     362: ifne          376
     365: new           #565                // class org/bouncycastle/jce/provider/AnnotatedException
     368: dup
     369: ldc_w         #457                // String CRL contains unsupported critical extensions.
     372: invokespecial #1073               // Method org/bouncycastle/jce/provider/AnnotatedException."<init>":(Ljava/lang/String;)V
     375: athrow
     376: aload         19
     378: ifnull        453
     381: aload         19
     383: invokevirtual #969                // Method java/security/cert/X509CRL.getCriticalExtensionOIDs:()Ljava/util/Set;
     386: astore        21
     388: aload         21
     390: ifnull        453
     393: new           #526                // class java/util/HashSet
     396: dup
     397: aload         21
     399: invokespecial #989                // Method java/util/HashSet."<init>":(Ljava/util/Collection;)V
     402: astore        21
     404: aload         21
     406: getstatic     #925                // Field org/bouncycastle/asn1/x509/Extension.issuingDistributionPoint:Lorg/bouncycastle/asn1/ASN1ObjectIdentifier;
     409: invokevirtual #996                // Method org/bouncycastle/asn1/ASN1ObjectIdentifier.getId:()Ljava/lang/String;
     412: invokeinterface #1157,  2         // InterfaceMethod java/util/Set.remove:(Ljava/lang/Object;)Z
     417: pop
     418: aload         21
     420: getstatic     #922                // Field org/bouncycastle/asn1/x509/Extension.deltaCRLIndicator:Lorg/bouncycastle/asn1/ASN1ObjectIdentifier;
     423: invokevirtual #996                // Method org/bouncycastle/asn1/ASN1ObjectIdentifier.getId:()Ljava/lang/String;
     426: invokeinterface #1157,  2         // InterfaceMethod java/util/Set.remove:(Ljava/lang/Object;)Z
     431: pop
     432: aload         21
     434: invokeinterface #1154,  1         // InterfaceMethod java/util/Set.isEmpty:()Z
     439: ifne          453
     442: new           #565                // class org/bouncycastle/jce/provider/AnnotatedException
     445: dup
     446: ldc_w         #463                // String Delta CRL contains unsupported critical extension.
     449: invokespecial #1073               // Method org/bouncycastle/jce/provider/AnnotatedException."<init>":(Ljava/lang/String;)V
     452: athrow
     453: iconst_1
     454: istore        12
     456: goto          61
     459: astore        15
     461: aload         15
     463: astore        13
     465: goto          61
     468: iload         12
     470: ifne          476
     473: aload         13
     475: athrow
     476: return
    Exception table:
       from    to  target type
          89   119   459   Class org/bouncycastle/jce/provider/AnnotatedException
         122   456   459   Class org/bouncycastle/jce/provider/AnnotatedException

  protected static void checkCRLs(org.bouncycastle.jcajce.PKIXExtendedParameters, java.security.cert.X509Certificate, java.util.Date, java.security.cert.X509Certificate, java.security.PublicKey, java.util.List, org.bouncycastle.jcajce.util.JcaJceHelper) throws org.bouncycastle.jce.provider.AnnotatedException;
    Code:
       0: aconst_null
       1: astore        7
       3: aconst_null
       4: astore        8
       6: aload_1
       7: getstatic     #935                // Field CRL_DISTRIBUTION_POINTS:Ljava/lang/String;
      10: invokestatic  #1086               // Method org/bouncycastle/jce/provider/CertPathValidatorUtilities.getExtensionValue:(Ljava/security/cert/X509Extension;Ljava/lang/String;)Lorg/bouncycastle/asn1/ASN1Primitive;
      13: invokestatic  #1018               // Method org/bouncycastle/asn1/x509/CRLDistPoint.getInstance:(Ljava/lang/Object;)Lorg/bouncycastle/asn1/x509/CRLDistPoint;
      16: astore        8
      18: goto          36
      21: astore        9
      23: new           #565                // class org/bouncycastle/jce/provider/AnnotatedException
      26: dup
      27: ldc_w         #458                // String CRL distribution point extension could not be read.
      30: aload         9
      32: invokespecial #1075               // Method org/bouncycastle/jce/provider/AnnotatedException."<init>":(Ljava/lang/String;Ljava/lang/Throwable;)V
      35: athrow
      36: new           #563                // class org/bouncycastle/jcajce/PKIXExtendedParameters$Builder
      39: dup
      40: aload_0
      41: invokespecial #1068               // Method org/bouncycastle/jcajce/PKIXExtendedParameters$Builder."<init>":(Lorg/bouncycastle/jcajce/PKIXExtendedParameters;)V
      44: astore        9
      46: aload         8
      48: aload_0
      49: invokevirtual #1065               // Method org/bouncycastle/jcajce/PKIXExtendedParameters.getNamedCRLStoreMap:()Ljava/util/Map;
      52: invokestatic  #1083               // Method org/bouncycastle/jce/provider/CertPathValidatorUtilities.getAdditionalStoresFromCRLDistributionPoint:(Lorg/bouncycastle/asn1/x509/CRLDistPoint;Ljava/util/Map;)Ljava/util/List;
      55: astore        10
      57: aload         10
      59: invokeinterface #1149,  1         // InterfaceMethod java/util/List.iterator:()Ljava/util/Iterator;
      64: astore        11
      66: aload         11
      68: invokeinterface #1142,  1         // InterfaceMethod java/util/Iterator.hasNext:()Z
      73: ifeq          95
      76: aload         9
      78: aload         11
      80: invokeinterface #1143,  1         // InterfaceMethod java/util/Iterator.next:()Ljava/lang/Object;
      85: checkcast     #555                // class org/bouncycastle/jcajce/PKIXCRLStore
      88: invokevirtual #1069               // Method org/bouncycastle/jcajce/PKIXExtendedParameters$Builder.addCRLStore:(Lorg/bouncycastle/jcajce/PKIXCRLStore;)Lorg/bouncycastle/jcajce/PKIXExtendedParameters$Builder;
      91: pop
      92: goto          66
      95: goto          113
      98: astore        10
     100: new           #565                // class org/bouncycastle/jce/provider/AnnotatedException
     103: dup
     104: ldc_w         #474                // String No additional CRL locations could be decoded from CRL distribution point extension.
     107: aload         10
     109: invokespecial #1075               // Method org/bouncycastle/jce/provider/AnnotatedException."<init>":(Ljava/lang/String;Ljava/lang/Throwable;)V
     112: athrow
     113: new           #567                // class org/bouncycastle/jce/provider/CertStatus
     116: dup
     117: invokespecial #1092               // Method org/bouncycastle/jce/provider/CertStatus."<init>":()V
     120: astore        10
     122: new           #575                // class org/bouncycastle/jce/provider/ReasonsMask
     125: dup
     126: invokespecial #1128               // Method org/bouncycastle/jce/provider/ReasonsMask."<init>":()V
     129: astore        11
     131: aload         9
     133: invokevirtual #1067               // Method org/bouncycastle/jcajce/PKIXExtendedParameters$Builder.build:()Lorg/bouncycastle/jcajce/PKIXExtendedParameters;
     136: astore        12
     138: iconst_0
     139: istore        13
     141: aload         8
     143: ifnull        249
     146: aconst_null
     147: astore        14
     149: aload         8
     151: invokevirtual #1017               // Method org/bouncycastle/asn1/x509/CRLDistPoint.getDistributionPoints:()[Lorg/bouncycastle/asn1/x509/DistributionPoint;
     154: astore        14
     156: goto          174
     159: astore        15
     161: new           #565                // class org/bouncycastle/jce/provider/AnnotatedException
     164: dup
     165: ldc_w         #464                // String Distribution points could not be read.
     168: aload         15
     170: invokespecial #1075               // Method org/bouncycastle/jce/provider/AnnotatedException."<init>":(Ljava/lang/String;Ljava/lang/Throwable;)V
     173: athrow
     174: aload         14
     176: ifnull        249
     179: iconst_0
     180: istore        15
     182: iload         15
     184: aload         14
     186: arraylength
     187: if_icmpge     249
     190: aload         10
     192: invokevirtual #1091               // Method org/bouncycastle/jce/provider/CertStatus.getCertStatus:()I
     195: bipush        11
     197: if_icmpne     249
     200: aload         11
     202: invokevirtual #1129               // Method org/bouncycastle/jce/provider/ReasonsMask.isAllReasons:()Z
     205: ifne          249
     208: aload         14
     210: iload         15
     212: aaload
     213: aload         12
     215: aload_1
     216: aload_2
     217: aload_3
     218: aload         4
     220: aload         10
     222: aload         11
     224: aload         5
     226: aload         6
     228: invokestatic  #1127               // Method checkCRL:(Lorg/bouncycastle/asn1/x509/DistributionPoint;Lorg/bouncycastle/jcajce/PKIXExtendedParameters;Ljava/security/cert/X509Certificate;Ljava/util/Date;Ljava/security/cert/X509Certificate;Ljava/security/PublicKey;Lorg/bouncycastle/jce/provider/CertStatus;Lorg/bouncycastle/jce/provider/ReasonsMask;Ljava/util/List;Lorg/bouncycastle/jcajce/util/JcaJceHelper;)V
     231: iconst_1
     232: istore        13
     234: goto          243
     237: astore        16
     239: aload         16
     241: astore        7
     243: iinc          15, 1
     246: goto          182
     249: aload         10
     251: invokevirtual #1091               // Method org/bouncycastle/jce/provider/CertStatus.getCertStatus:()I
     254: bipush        11
     256: if_icmpne     368
     259: aload         11
     261: invokevirtual #1129               // Method org/bouncycastle/jce/provider/ReasonsMask.isAllReasons:()Z
     264: ifne          368
     267: aload_1
     268: invokestatic  #1114               // Method org/bouncycastle/jce/provider/PrincipalUtils.getEncodedIssuerPrincipal:(Ljava/lang/Object;)Lorg/bouncycastle/asn1/x500/X500Name;
     271: astore        14
     273: goto          291
     276: astore        15
     278: new           #565                // class org/bouncycastle/jce/provider/AnnotatedException
     281: dup
     282: ldc_w         #470                // String Issuer from certificate for CRL could not be reencoded.
     285: aload         15
     287: invokespecial #1075               // Method org/bouncycastle/jce/provider/AnnotatedException."<init>":(Ljava/lang/String;Ljava/lang/Throwable;)V
     290: athrow
     291: new           #547                // class org/bouncycastle/asn1/x509/DistributionPoint
     294: dup
     295: new           #548                // class org/bouncycastle/asn1/x509/DistributionPointName
     298: dup
     299: iconst_0
     300: new           #551                // class org/bouncycastle/asn1/x509/GeneralNames
     303: dup
     304: new           #550                // class org/bouncycastle/asn1/x509/GeneralName
     307: dup
     308: iconst_4
     309: aload         14
     311: invokespecial #1029               // Method org/bouncycastle/asn1/x509/GeneralName."<init>":(ILorg/bouncycastle/asn1/ASN1Encodable;)V
     314: invokespecial #1032               // Method org/bouncycastle/asn1/x509/GeneralNames."<init>":(Lorg/bouncycastle/asn1/x509/GeneralName;)V
     317: invokespecial #1025               // Method org/bouncycastle/asn1/x509/DistributionPointName."<init>":(ILorg/bouncycastle/asn1/ASN1Encodable;)V
     320: aconst_null
     321: aconst_null
     322: invokespecial #1022               // Method org/bouncycastle/asn1/x509/DistributionPoint."<init>":(Lorg/bouncycastle/asn1/x509/DistributionPointName;Lorg/bouncycastle/asn1/x509/ReasonFlags;Lorg/bouncycastle/asn1/x509/GeneralNames;)V
     325: astore        15
     327: aload_0
     328: invokevirtual #1059               // Method org/bouncycastle/jcajce/PKIXExtendedParameters.clone:()Ljava/lang/Object;
     331: checkcast     #562                // class org/bouncycastle/jcajce/PKIXExtendedParameters
     334: astore        16
     336: aload         15
     338: aload         16
     340: aload_1
     341: aload_2
     342: aload_3
     343: aload         4
     345: aload         10
     347: aload         11
     349: aload         5
     351: aload         6
     353: invokestatic  #1127               // Method checkCRL:(Lorg/bouncycastle/asn1/x509/DistributionPoint;Lorg/bouncycastle/jcajce/PKIXExtendedParameters;Ljava/security/cert/X509Certificate;Ljava/util/Date;Ljava/security/cert/X509Certificate;Ljava/security/PublicKey;Lorg/bouncycastle/jce/provider/CertStatus;Lorg/bouncycastle/jce/provider/ReasonsMask;Ljava/util/List;Lorg/bouncycastle/jcajce/util/JcaJceHelper;)V
     356: iconst_1
     357: istore        13
     359: goto          368
     362: astore        14
     364: aload         14
     366: astore        7
     368: iload         13
     370: ifne          397
     373: aload         7
     375: instanceof    #565                // class org/bouncycastle/jce/provider/AnnotatedException
     378: ifeq          384
     381: aload         7
     383: athrow
     384: new           #565                // class org/bouncycastle/jce/provider/AnnotatedException
     387: dup
     388: ldc_w         #476                // String No valid CRL found.
     391: aload         7
     393: invokespecial #1075               // Method org/bouncycastle/jce/provider/AnnotatedException."<init>":(Ljava/lang/String;Ljava/lang/Throwable;)V
     396: athrow
     397: aload         10
     399: invokevirtual #1091               // Method org/bouncycastle/jce/provider/CertStatus.getCertStatus:()I
     402: bipush        11
     404: if_icmpeq     506
     407: new           #520                // class java/text/SimpleDateFormat
     410: dup
     411: ldc_w         #496                // String yyyy-MM-dd HH:mm:ss Z
     414: invokespecial #981                // Method java/text/SimpleDateFormat."<init>":(Ljava/lang/String;)V
     417: astore        14
     419: aload         14
     421: ldc_w         #483                // String UTC
     424: invokestatic  #990                // Method java/util/TimeZone.getTimeZone:(Ljava/lang/String;)Ljava/util/TimeZone;
     427: invokevirtual #982                // Method java/text/SimpleDateFormat.setTimeZone:(Ljava/util/TimeZone;)V
     430: new           #503                // class java/lang/StringBuilder
     433: dup
     434: invokespecial #953                // Method java/lang/StringBuilder."<init>":()V
     437: ldc_w         #460                // String Certificate revocation after
     440: invokevirtual #956                // Method java/lang/StringBuilder.append:(Ljava/lang/String;)Ljava/lang/StringBuilder;
     443: aload         14
     445: aload         10
     447: invokevirtual #1094               // Method org/bouncycastle/jce/provider/CertStatus.getRevocationDate:()Ljava/util/Date;
     450: invokevirtual #983                // Method java/text/SimpleDateFormat.format:(Ljava/util/Date;)Ljava/lang/String;
     453: invokevirtual #956                // Method java/lang/StringBuilder.append:(Ljava/lang/String;)Ljava/lang/StringBuilder;
     456: invokevirtual #954                // Method java/lang/StringBuilder.toString:()Ljava/lang/String;
     459: astore        15
     461: new           #503                // class java/lang/StringBuilder
     464: dup
     465: invokespecial #953                // Method java/lang/StringBuilder."<init>":()V
     468: aload         15
     470: invokevirtual #956                // Method java/lang/StringBuilder.append:(Ljava/lang/String;)Ljava/lang/StringBuilder;
     473: ldc_w         #454                // String , reason:
     476: invokevirtual #956                // Method java/lang/StringBuilder.append:(Ljava/lang/String;)Ljava/lang/StringBuilder;
     479: getstatic     #946                // Field crlReasons:[Ljava/lang/String;
     482: aload         10
     484: invokevirtual #1091               // Method org/bouncycastle/jce/provider/CertStatus.getCertStatus:()I
     487: aaload
     488: invokevirtual #956                // Method java/lang/StringBuilder.append:(Ljava/lang/String;)Ljava/lang/StringBuilder;
     491: invokevirtual #954                // Method java/lang/StringBuilder.toString:()Ljava/lang/String;
     494: astore        15
     496: new           #565                // class org/bouncycastle/jce/provider/AnnotatedException
     499: dup
     500: aload         15
     502: invokespecial #1073               // Method org/bouncycastle/jce/provider/AnnotatedException."<init>":(Ljava/lang/String;)V
     505: athrow
     506: aload         11
     508: invokevirtual #1129               // Method org/bouncycastle/jce/provider/ReasonsMask.isAllReasons:()Z
     511: ifne          531
     514: aload         10
     516: invokevirtual #1091               // Method org/bouncycastle/jce/provider/CertStatus.getCertStatus:()I
     519: bipush        11
     521: if_icmpne     531
     524: aload         10
     526: bipush        12
     528: invokevirtual #1093               // Method org/bouncycastle/jce/provider/CertStatus.setCertStatus:(I)V
     531: aload         10
     533: invokevirtual #1091               // Method org/bouncycastle/jce/provider/CertStatus.getCertStatus:()I
     536: bipush        12
     538: if_icmpne     552
     541: new           #565                // class org/bouncycastle/jce/provider/AnnotatedException
     544: dup
     545: ldc_w         #461                // String Certificate status could not be determined.
     548: invokespecial #1073               // Method org/bouncycastle/jce/provider/AnnotatedException."<init>":(Ljava/lang/String;)V
     551: athrow
     552: return
    Exception table:
       from    to  target type
           6    18    21   Class java/lang/Exception
          46    95    98   Class org/bouncycastle/jce/provider/AnnotatedException
         149   156   159   Class java/lang/Exception
         208   234   237   Class org/bouncycastle/jce/provider/AnnotatedException
         267   273   276   Class java/lang/RuntimeException
         267   359   362   Class org/bouncycastle/jce/provider/AnnotatedException

  protected static int prepareNextCertJ(java.security.cert.CertPath, int, int) throws java.security.cert.CertPathValidatorException;
    Code:
       0: aload_0
       1: invokevirtual #959                // Method java/security/cert/CertPath.getCertificates:()Ljava/util/List;
       4: astore_3
       5: aload_3
       6: iload_1
       7: invokeinterface #1145,  2         // InterfaceMethod java/util/List.get:(I)Ljava/lang/Object;
      12: checkcast     #518                // class java/security/cert/X509Certificate
      15: astore        4
      17: aconst_null
      18: astore        5
      20: aload         4
      22: getstatic     #939                // Field INHIBIT_ANY_POLICY:Ljava/lang/String;
      25: invokestatic  #1086               // Method org/bouncycastle/jce/provider/CertPathValidatorUtilities.getExtensionValue:(Ljava/security/cert/X509Extension;Ljava/lang/String;)Lorg/bouncycastle/asn1/ASN1Primitive;
      28: invokestatic  #994                // Method org/bouncycastle/asn1/ASN1Integer.getInstance:(Ljava/lang/Object;)Lorg/bouncycastle/asn1/ASN1Integer;
      31: astore        5
      33: goto          53
      36: astore        6
      38: new           #564                // class org/bouncycastle/jce/exception/ExtCertPathValidatorException
      41: dup
      42: ldc_w         #467                // String Inhibit any-policy extension cannot be decoded.
      45: aload         6
      47: aload_0
      48: iload_1
      49: invokespecial #1071               // Method org/bouncycastle/jce/exception/ExtCertPathValidatorException."<init>":(Ljava/lang/String;Ljava/lang/Throwable;Ljava/security/cert/CertPath;I)V
      52: athrow
      53: aload         5
      55: ifnull        74
      58: aload         5
      60: invokevirtual #993                // Method org/bouncycastle/asn1/ASN1Integer.intValueExact:()I
      63: istore        6
      65: iload         6
      67: iload_2
      68: if_icmpge     74
      71: iload         6
      73: ireturn
      74: iload_2
      75: ireturn
    Exception table:
       from    to  target type
          20    33    36   Class java/lang/Exception

  protected static void prepareNextCertK(java.security.cert.CertPath, int) throws java.security.cert.CertPathValidatorException;
    Code:
       0: aload_0
       1: invokevirtual #959                // Method java/security/cert/CertPath.getCertificates:()Ljava/util/List;
       4: astore_2
       5: aload_2
       6: iload_1
       7: invokeinterface #1145,  2         // InterfaceMethod java/util/List.get:(I)Ljava/lang/Object;
      12: checkcast     #518                // class java/security/cert/X509Certificate
      15: astore_3
      16: aconst_null
      17: astore        4
      19: aload_3
      20: getstatic     #933                // Field BASIC_CONSTRAINTS:Ljava/lang/String;
      23: invokestatic  #1086               // Method org/bouncycastle/jce/provider/CertPathValidatorUtilities.getExtensionValue:(Ljava/security/cert/X509Extension;Ljava/lang/String;)Lorg/bouncycastle/asn1/ASN1Primitive;
      26: invokestatic  #1016               // Method org/bouncycastle/asn1/x509/BasicConstraints.getInstance:(Ljava/lang/Object;)Lorg/bouncycastle/asn1/x509/BasicConstraints;
      29: astore        4
      31: goto          51
      34: astore        5
      36: new           #564                // class org/bouncycastle/jce/exception/ExtCertPathValidatorException
      39: dup
      40: ldc_w         #456                // String Basic constraints extension cannot be decoded.
      43: aload         5
      45: aload_0
      46: iload_1
      47: invokespecial #1071               // Method org/bouncycastle/jce/exception/ExtCertPathValidatorException."<init>":(Ljava/lang/String;Ljava/lang/Throwable;Ljava/security/cert/CertPath;I)V
      50: athrow
      51: aload         4
      53: ifnull        78
      56: aload         4
      58: invokevirtual #1014               // Method org/bouncycastle/asn1/x509/BasicConstraints.isCA:()Z
      61: ifne          92
      64: new           #511                // class java/security/cert/CertPathValidatorException
      67: dup
      68: ldc_w         #477                // String Not a CA certificate
      71: aconst_null
      72: aload_0
      73: iload_1
      74: invokespecial #962                // Method java/security/cert/CertPathValidatorException."<init>":(Ljava/lang/String;Ljava/lang/Throwable;Ljava/security/cert/CertPath;I)V
      77: athrow
      78: new           #511                // class java/security/cert/CertPathValidatorException
      81: dup
      82: ldc_w         #468                // String Intermediate certificate lacks BasicConstraints
      85: aconst_null
      86: aload_0
      87: iload_1
      88: invokespecial #962                // Method java/security/cert/CertPathValidatorException."<init>":(Ljava/lang/String;Ljava/lang/Throwable;Ljava/security/cert/CertPath;I)V
      91: athrow
      92: return
    Exception table:
       from    to  target type
          19    31    34   Class java/lang/Exception

  protected static int prepareNextCertL(java.security.cert.CertPath, int, int) throws java.security.cert.CertPathValidatorException;
    Code:
       0: aload_0
       1: invokevirtual #959                // Method java/security/cert/CertPath.getCertificates:()Ljava/util/List;
       4: astore_3
       5: aload_3
       6: iload_1
       7: invokeinterface #1145,  2         // InterfaceMethod java/util/List.get:(I)Ljava/lang/Object;
      12: checkcast     #518                // class java/security/cert/X509Certificate
      15: astore        4
      17: aload         4
      19: invokestatic  #1076               // Method org/bouncycastle/jce/provider/CertPathValidatorUtilities.isSelfIssued:(Ljava/security/cert/X509Certificate;)Z
      22: ifne          47
      25: iload_2
      26: ifgt          43
      29: new           #564                // class org/bouncycastle/jce/exception/ExtCertPathValidatorException
      32: dup
      33: ldc_w         #472                // String Max path length not greater than zero
      36: aconst_null
      37: aload_0
      38: iload_1
      39: invokespecial #1071               // Method org/bouncycastle/jce/exception/ExtCertPathValidatorException."<init>":(Ljava/lang/String;Ljava/lang/Throwable;Ljava/security/cert/CertPath;I)V
      42: athrow
      43: iload_2
      44: iconst_1
      45: isub
      46: ireturn
      47: iload_2
      48: ireturn

  protected static int prepareNextCertM(java.security.cert.CertPath, int, int) throws java.security.cert.CertPathValidatorException;
    Code:
       0: aload_0
       1: invokevirtual #959                // Method java/security/cert/CertPath.getCertificates:()Ljava/util/List;
       4: astore_3
       5: aload_3
       6: iload_1
       7: invokeinterface #1145,  2         // InterfaceMethod java/util/List.get:(I)Ljava/lang/Object;
      12: checkcast     #518                // class java/security/cert/X509Certificate
      15: astore        4
      17: aconst_null
      18: astore        5
      20: aload         4
      22: getstatic     #933                // Field BASIC_CONSTRAINTS:Ljava/lang/String;
      25: invokestatic  #1086               // Method org/bouncycastle/jce/provider/CertPathValidatorUtilities.getExtensionValue:(Ljava/security/cert/X509Extension;Ljava/lang/String;)Lorg/bouncycastle/asn1/ASN1Primitive;
      28: invokestatic  #1016               // Method org/bouncycastle/asn1/x509/BasicConstraints.getInstance:(Ljava/lang/Object;)Lorg/bouncycastle/asn1/x509/BasicConstraints;
      31: astore        5
      33: goto          53
      36: astore        6
      38: new           #564                // class org/bouncycastle/jce/exception/ExtCertPathValidatorException
      41: dup
      42: ldc_w         #456                // String Basic constraints extension cannot be decoded.
      45: aload         6
      47: aload_0
      48: iload_1
      49: invokespecial #1071               // Method org/bouncycastle/jce/exception/ExtCertPathValidatorException."<init>":(Ljava/lang/String;Ljava/lang/Throwable;Ljava/security/cert/CertPath;I)V
      52: athrow
      53: aload         5
      55: ifnull        86
      58: aload         5
      60: invokevirtual #1015               // Method org/bouncycastle/asn1/x509/BasicConstraints.getPathLenConstraint:()Ljava/math/BigInteger;
      63: astore        6
      65: aload         6
      67: ifnull        86
      70: aload         6
      72: invokevirtual #958                // Method java/math/BigInteger.intValue:()I
      75: istore        7
      77: iload         7
      79: iload_2
      80: if_icmpge     86
      83: iload         7
      85: ireturn
      86: iload_2
      87: ireturn
    Exception table:
       from    to  target type
          20    33    36   Class java/lang/Exception

  protected static void prepareNextCertN(java.security.cert.CertPath, int) throws java.security.cert.CertPathValidatorException;
    Code:
       0: aload_0
       1: invokevirtual #959                // Method java/security/cert/CertPath.getCertificates:()Ljava/util/List;
       4: astore_2
       5: aload_2
       6: iload_1
       7: invokeinterface #1145,  2         // InterfaceMethod java/util/List.get:(I)Ljava/lang/Object;
      12: checkcast     #518                // class java/security/cert/X509Certificate
      15: astore_3
      16: aload_3
      17: invokevirtual #976                // Method java/security/cert/X509Certificate.getKeyUsage:()[Z
      20: astore        4
      22: aload         4
      24: ifnull        48
      27: aload         4
      29: iconst_5
      30: baload
      31: ifne          48
      34: new           #564                // class org/bouncycastle/jce/exception/ExtCertPathValidatorException
      37: dup
      38: ldc_w         #469                // String Issuer certificate keyusage extension is critical and does not permit key signing.
      41: aconst_null
      42: aload_0
      43: iload_1
      44: invokespecial #1071               // Method org/bouncycastle/jce/exception/ExtCertPathValidatorException."<init>":(Ljava/lang/String;Ljava/lang/Throwable;Ljava/security/cert/CertPath;I)V
      47: athrow
      48: return

  protected static void prepareNextCertO(java.security.cert.CertPath, int, java.util.Set, java.util.List) throws java.security.cert.CertPathValidatorException;
    Code:
       0: aload_0
       1: invokevirtual #959                // Method java/security/cert/CertPath.getCertificates:()Ljava/util/List;
       4: astore        4
       6: aload         4
       8: iload_1
       9: invokeinterface #1145,  2         // InterfaceMethod java/util/List.get:(I)Ljava/lang/Object;
      14: checkcast     #518                // class java/security/cert/X509Certificate
      17: astore        5
      19: aload_3
      20: invokeinterface #1149,  1         // InterfaceMethod java/util/List.iterator:()Ljava/util/Iterator;
      25: astore        6
      27: aload         6
      29: invokeinterface #1142,  1         // InterfaceMethod java/util/Iterator.hasNext:()Z
      34: ifeq          78
      37: aload         6
      39: invokeinterface #1143,  1         // InterfaceMethod java/util/Iterator.next:()Ljava/lang/Object;
      44: checkcast     #514                // class java/security/cert/PKIXCertPathChecker
      47: aload         5
      49: aload_2
      50: invokevirtual #965                // Method java/security/cert/PKIXCertPathChecker.check:(Ljava/security/cert/Certificate;Ljava/util/Collection;)V
      53: goto          27
      56: astore        7
      58: new           #511                // class java/security/cert/CertPathValidatorException
      61: dup
      62: aload         7
      64: invokevirtual #960                // Method java/security/cert/CertPathValidatorException.getMessage:()Ljava/lang/String;
      67: aload         7
      69: invokevirtual #961                // Method java/security/cert/CertPathValidatorException.getCause:()Ljava/lang/Throwable;
      72: aload_0
      73: iload_1
      74: invokespecial #962                // Method java/security/cert/CertPathValidatorException."<init>":(Ljava/lang/String;Ljava/lang/Throwable;Ljava/security/cert/CertPath;I)V
      77: athrow
      78: aload_2
      79: invokeinterface #1154,  1         // InterfaceMethod java/util/Set.isEmpty:()Z
      84: ifne          118
      87: new           #564                // class org/bouncycastle/jce/exception/ExtCertPathValidatorException
      90: dup
      91: new           #503                // class java/lang/StringBuilder
      94: dup
      95: invokespecial #953                // Method java/lang/StringBuilder."<init>":()V
      98: ldc_w         #459                // String Certificate has unsupported critical extension:
     101: invokevirtual #956                // Method java/lang/StringBuilder.append:(Ljava/lang/String;)Ljava/lang/StringBuilder;
     104: aload_2
     105: invokevirtual #955                // Method java/lang/StringBuilder.append:(Ljava/lang/Object;)Ljava/lang/StringBuilder;
     108: invokevirtual #954                // Method java/lang/StringBuilder.toString:()Ljava/lang/String;
     111: aconst_null
     112: aload_0
     113: iload_1
     114: invokespecial #1071               // Method org/bouncycastle/jce/exception/ExtCertPathValidatorException."<init>":(Ljava/lang/String;Ljava/lang/Throwable;Ljava/security/cert/CertPath;I)V
     117: athrow
     118: return
    Exception table:
       from    to  target type
          37    53    56   Class java/security/cert/CertPathValidatorException

  protected static int prepareNextCertH1(java.security.cert.CertPath, int, int);
    Code:
       0: aload_0
       1: invokevirtual #959                // Method java/security/cert/CertPath.getCertificates:()Ljava/util/List;
       4: astore_3
       5: aload_3
       6: iload_1
       7: invokeinterface #1145,  2         // InterfaceMethod java/util/List.get:(I)Ljava/lang/Object;
      12: checkcast     #518                // class java/security/cert/X509Certificate
      15: astore        4
      17: aload         4
      19: invokestatic  #1076               // Method org/bouncycastle/jce/provider/CertPathValidatorUtilities.isSelfIssued:(Ljava/security/cert/X509Certificate;)Z
      22: ifne          33
      25: iload_2
      26: ifeq          33
      29: iload_2
      30: iconst_1
      31: isub
      32: ireturn
      33: iload_2
      34: ireturn

  protected static int prepareNextCertH2(java.security.cert.CertPath, int, int);
    Code:
       0: aload_0
       1: invokevirtual #959                // Method java/security/cert/CertPath.getCertificates:()Ljava/util/List;
       4: astore_3
       5: aload_3
       6: iload_1
       7: invokeinterface #1145,  2         // InterfaceMethod java/util/List.get:(I)Ljava/lang/Object;
      12: checkcast     #518                // class java/security/cert/X509Certificate
      15: astore        4
      17: aload         4
      19: invokestatic  #1076               // Method org/bouncycastle/jce/provider/CertPathValidatorUtilities.isSelfIssued:(Ljava/security/cert/X509Certificate;)Z
      22: ifne          33
      25: iload_2
      26: ifeq          33
      29: iload_2
      30: iconst_1
      31: isub
      32: ireturn
      33: iload_2
      34: ireturn

  protected static int prepareNextCertH3(java.security.cert.CertPath, int, int);
    Code:
       0: aload_0
       1: invokevirtual #959                // Method java/security/cert/CertPath.getCertificates:()Ljava/util/List;
       4: astore_3
       5: aload_3
       6: iload_1
       7: invokeinterface #1145,  2         // InterfaceMethod java/util/List.get:(I)Ljava/lang/Object;
      12: checkcast     #518                // class java/security/cert/X509Certificate
      15: astore        4
      17: aload         4
      19: invokestatic  #1076               // Method org/bouncycastle/jce/provider/CertPathValidatorUtilities.isSelfIssued:(Ljava/security/cert/X509Certificate;)Z
      22: ifne          33
      25: iload_2
      26: ifeq          33
      29: iload_2
      30: iconst_1
      31: isub
      32: ireturn
      33: iload_2
      34: ireturn

  protected static int wrapupCertA(int, java.security.cert.X509Certificate);
    Code:
       0: aload_1
       1: invokestatic  #1076               // Method org/bouncycastle/jce/provider/CertPathValidatorUtilities.isSelfIssued:(Ljava/security/cert/X509Certificate;)Z
       4: ifne          14
       7: iload_0
       8: ifeq          14
      11: iinc          0, -1
      14: iload_0
      15: ireturn

  protected static int wrapupCertB(java.security.cert.CertPath, int, int) throws java.security.cert.CertPathValidatorException;
    Code:
       0: aload_0
       1: invokevirtual #959                // Method java/security/cert/CertPath.getCertificates:()Ljava/util/List;
       4: astore_3
       5: aload_3
       6: iload_1
       7: invokeinterface #1145,  2         // InterfaceMethod java/util/List.get:(I)Ljava/lang/Object;
      12: checkcast     #518                // class java/security/cert/X509Certificate
      15: astore        4
      17: aconst_null
      18: astore        6
      20: aload         4
      22: getstatic     #943                // Field POLICY_CONSTRAINTS:Ljava/lang/String;
      25: invokestatic  #1086               // Method org/bouncycastle/jce/provider/CertPathValidatorUtilities.getExtensionValue:(Ljava/security/cert/X509Extension;Ljava/lang/String;)Lorg/bouncycastle/asn1/ASN1Primitive;
      28: invokestatic  #1007               // Method org/bouncycastle/asn1/DERSequence.getInstance:(Ljava/lang/Object;)Lorg/bouncycastle/asn1/ASN1Sequence;
      31: astore        6
      33: goto          53
      36: astore        7
      38: new           #564                // class org/bouncycastle/jce/exception/ExtCertPathValidatorException
      41: dup
      42: ldc_w         #479                // String Policy constraints could not be decoded.
      45: aload         7
      47: aload_0
      48: iload_1
      49: invokespecial #1071               // Method org/bouncycastle/jce/exception/ExtCertPathValidatorException."<init>":(Ljava/lang/String;Ljava/lang/Throwable;Ljava/security/cert/CertPath;I)V
      52: athrow
      53: aload         6
      55: ifnull        153
      58: aload         6
      60: invokevirtual #1001               // Method org/bouncycastle/asn1/ASN1Sequence.getObjects:()Ljava/util/Enumeration;
      63: astore        7
      65: aload         7
      67: invokeinterface #1139,  1         // InterfaceMethod java/util/Enumeration.hasMoreElements:()Z
      72: ifeq          153
      75: aload         7
      77: invokeinterface #1140,  1         // InterfaceMethod java/util/Enumeration.nextElement:()Ljava/lang/Object;
      82: checkcast     #539                // class org/bouncycastle/asn1/ASN1TaggedObject
      85: astore        8
      87: aload         8
      89: invokevirtual #1004               // Method org/bouncycastle/asn1/ASN1TaggedObject.getTagNo:()I
      92: lookupswitch  { // 1
                     0: 112
               default: 150
          }
     112: aload         8
     114: iconst_0
     115: invokestatic  #995                // Method org/bouncycastle/asn1/ASN1Integer.getInstance:(Lorg/bouncycastle/asn1/ASN1TaggedObject;Z)Lorg/bouncycastle/asn1/ASN1Integer;
     118: invokevirtual #993                // Method org/bouncycastle/asn1/ASN1Integer.intValueExact:()I
     121: istore        5
     123: goto          143
     126: astore        9
     128: new           #564                // class org/bouncycastle/jce/exception/ExtCertPathValidatorException
     131: dup
     132: ldc_w         #482                // String Policy constraints requireExplicitPolicy field could not be decoded.
     135: aload         9
     137: aload_0
     138: iload_1
     139: invokespecial #1071               // Method org/bouncycastle/jce/exception/ExtCertPathValidatorException."<init>":(Ljava/lang/String;Ljava/lang/Throwable;Ljava/security/cert/CertPath;I)V
     142: athrow
     143: iload         5
     145: ifne          150
     148: iconst_0
     149: ireturn
     150: goto          65
     153: iload_2
     154: ireturn
    Exception table:
       from    to  target type
          20    33    36   Class org/bouncycastle/jce/provider/AnnotatedException
         112   123   126   Class java/lang/Exception

  protected static void wrapupCertF(java.security.cert.CertPath, int, java.util.List, java.util.Set) throws java.security.cert.CertPathValidatorException;
    Code:
       0: aload_0
       1: invokevirtual #959                // Method java/security/cert/CertPath.getCertificates:()Ljava/util/List;
       4: astore        4
       6: aload         4
       8: iload_1
       9: invokeinterface #1145,  2         // InterfaceMethod java/util/List.get:(I)Ljava/lang/Object;
      14: checkcast     #518                // class java/security/cert/X509Certificate
      17: astore        5
      19: aload_2
      20: invokeinterface #1149,  1         // InterfaceMethod java/util/List.iterator:()Ljava/util/Iterator;
      25: astore        6
      27: aload         6
      29: invokeinterface #1142,  1         // InterfaceMethod java/util/Iterator.hasNext:()Z
      34: ifeq          92
      37: aload         6
      39: invokeinterface #1143,  1         // InterfaceMethod java/util/Iterator.next:()Ljava/lang/Object;
      44: checkcast     #514                // class java/security/cert/PKIXCertPathChecker
      47: aload         5
      49: aload_3
      50: invokevirtual #965                // Method java/security/cert/PKIXCertPathChecker.check:(Ljava/security/cert/Certificate;Ljava/util/Collection;)V
      53: goto          27
      56: astore        7
      58: new           #564                // class org/bouncycastle/jce/exception/ExtCertPathValidatorException
      61: dup
      62: aload         7
      64: invokevirtual #960                // Method java/security/cert/CertPathValidatorException.getMessage:()Ljava/lang/String;
      67: aload         7
      69: aload_0
      70: iload_1
      71: invokespecial #1071               // Method org/bouncycastle/jce/exception/ExtCertPathValidatorException."<init>":(Ljava/lang/String;Ljava/lang/Throwable;Ljava/security/cert/CertPath;I)V
      74: athrow
      75: astore        7
      77: new           #511                // class java/security/cert/CertPathValidatorException
      80: dup
      81: ldc_w         #455                // String Additional certificate path checker failed.
      84: aload         7
      86: aload_0
      87: iload_1
      88: invokespecial #962                // Method java/security/cert/CertPathValidatorException."<init>":(Ljava/lang/String;Ljava/lang/Throwable;Ljava/security/cert/CertPath;I)V
      91: athrow
      92: aload_3
      93: invokeinterface #1154,  1         // InterfaceMethod java/util/Set.isEmpty:()Z
      98: ifne          132
     101: new           #564                // class org/bouncycastle/jce/exception/ExtCertPathValidatorException
     104: dup
     105: new           #503                // class java/lang/StringBuilder
     108: dup
     109: invokespecial #953                // Method java/lang/StringBuilder."<init>":()V
     112: ldc_w         #459                // String Certificate has unsupported critical extension:
     115: invokevirtual #956                // Method java/lang/StringBuilder.append:(Ljava/lang/String;)Ljava/lang/StringBuilder;
     118: aload_3
     119: invokevirtual #955                // Method java/lang/StringBuilder.append:(Ljava/lang/Object;)Ljava/lang/StringBuilder;
     122: invokevirtual #954                // Method java/lang/StringBuilder.toString:()Ljava/lang/String;
     125: aconst_null
     126: aload_0
     127: iload_1
     128: invokespecial #1071               // Method org/bouncycastle/jce/exception/ExtCertPathValidatorException."<init>":(Ljava/lang/String;Ljava/lang/Throwable;Ljava/security/cert/CertPath;I)V
     131: athrow
     132: return
    Exception table:
       from    to  target type
          37    53    56   Class java/security/cert/CertPathValidatorException
          37    53    75   Class java/lang/Exception

  protected static org.bouncycastle.jce.provider.PKIXPolicyNode wrapupCertG(java.security.cert.CertPath, org.bouncycastle.jcajce.PKIXExtendedParameters, java.util.Set, int, java.util.List[], org.bouncycastle.jce.provider.PKIXPolicyNode, java.util.Set) throws java.security.cert.CertPathValidatorException;
    Code:
       0: aload_0
       1: invokevirtual #959                // Method java/security/cert/CertPath.getCertificates:()Ljava/util/List;
       4: invokeinterface #1144,  1         // InterfaceMethod java/util/List.size:()I
       9: istore        7
      11: aload         5
      13: ifnonnull     43
      16: aload_1
      17: invokevirtual #1056               // Method org/bouncycastle/jcajce/PKIXExtendedParameters.isExplicitPolicyRequired:()Z
      20: ifeq          37
      23: new           #564                // class org/bouncycastle/jce/exception/ExtCertPathValidatorException
      26: dup
      27: ldc_w         #466                // String Explicit policy requested but none available.
      30: aconst_null
      31: aload_0
      32: iload_3
      33: invokespecial #1071               // Method org/bouncycastle/jce/exception/ExtCertPathValidatorException."<init>":(Ljava/lang/String;Ljava/lang/Throwable;Ljava/security/cert/CertPath;I)V
      36: athrow
      37: aconst_null
      38: astore        8
      40: goto          626
      43: aload_2
      44: invokestatic  #1077               // Method org/bouncycastle/jce/provider/CertPathValidatorUtilities.isAnyPolicy:(Ljava/util/Set;)Z
      47: ifeq          340
      50: aload_1
      51: invokevirtual #1056               // Method org/bouncycastle/jcajce/PKIXExtendedParameters.isExplicitPolicyRequired:()Z
      54: ifeq          333
      57: aload         6
      59: invokeinterface #1154,  1         // InterfaceMethod java/util/Set.isEmpty:()Z
      64: ifeq          81
      67: new           #564                // class org/bouncycastle/jce/exception/ExtCertPathValidatorException
      70: dup
      71: ldc_w         #466                // String Explicit policy requested but none available.
      74: aconst_null
      75: aload_0
      76: iload_3
      77: invokespecial #1071               // Method org/bouncycastle/jce/exception/ExtCertPathValidatorException."<init>":(Ljava/lang/String;Ljava/lang/Throwable;Ljava/security/cert/CertPath;I)V
      80: athrow
      81: new           #526                // class java/util/HashSet
      84: dup
      85: invokespecial #988                // Method java/util/HashSet."<init>":()V
      88: astore        9
      90: iconst_0
      91: istore        10
      93: iload         10
      95: aload         4
      97: arraylength
      98: if_icmpge     197
     101: aload         4
     103: iload         10
     105: aaload
     106: astore        11
     108: iconst_0
     109: istore        12
     111: iload         12
     113: aload         11
     115: invokeinterface #1144,  1         // InterfaceMethod java/util/List.size:()I
     120: if_icmpge     191
     123: aload         11
     125: iload         12
     127: invokeinterface #1145,  2         // InterfaceMethod java/util/List.get:(I)Ljava/lang/Object;
     132: checkcast     #572                // class org/bouncycastle/jce/provider/PKIXPolicyNode
     135: astore        13
     137: ldc           #1                  // String 2.5.29.32.0
     139: aload         13
     141: invokevirtual #1107               // Method org/bouncycastle/jce/provider/PKIXPolicyNode.getValidPolicy:()Ljava/lang/String;
     144: invokevirtual #952                // Method java/lang/String.equals:(Ljava/lang/Object;)Z
     147: ifeq          185
     150: aload         13
     152: invokevirtual #1109               // Method org/bouncycastle/jce/provider/PKIXPolicyNode.getChildren:()Ljava/util/Iterator;
     155: astore        14
     157: aload         14
     159: invokeinterface #1142,  1         // InterfaceMethod java/util/Iterator.hasNext:()Z
     164: ifeq          185
     167: aload         9
     169: aload         14
     171: invokeinterface #1143,  1         // InterfaceMethod java/util/Iterator.next:()Ljava/lang/Object;
     176: invokeinterface #1155,  2         // InterfaceMethod java/util/Set.add:(Ljava/lang/Object;)Z
     181: pop
     182: goto          157
     185: iinc          12, 1
     188: goto          111
     191: iinc          10, 1
     194: goto          93
     197: aload         9
     199: invokeinterface #1159,  1         // InterfaceMethod java/util/Set.iterator:()Ljava/util/Iterator;
     204: astore        10
     206: aload         10
     208: invokeinterface #1142,  1         // InterfaceMethod java/util/Iterator.hasNext:()Z
     213: ifeq          250
     216: aload         10
     218: invokeinterface #1143,  1         // InterfaceMethod java/util/Iterator.next:()Ljava/lang/Object;
     223: checkcast     #572                // class org/bouncycastle/jce/provider/PKIXPolicyNode
     226: astore        11
     228: aload         11
     230: invokevirtual #1107               // Method org/bouncycastle/jce/provider/PKIXPolicyNode.getValidPolicy:()Ljava/lang/String;
     233: astore        12
     235: aload         6
     237: aload         12
     239: invokeinterface #1156,  2         // InterfaceMethod java/util/Set.contains:(Ljava/lang/Object;)Z
     244: ifne          247
     247: goto          206
     250: aload         5
     252: ifnull        333
     255: iload         7
     257: iconst_1
     258: isub
     259: istore        11
     261: iload         11
     263: iflt          333
     266: aload         4
     268: iload         11
     270: aaload
     271: astore        12
     273: iconst_0
     274: istore        13
     276: iload         13
     278: aload         12
     280: invokeinterface #1144,  1         // InterfaceMethod java/util/List.size:()I
     285: if_icmpge     327
     288: aload         12
     290: iload         13
     292: invokeinterface #1145,  2         // InterfaceMethod java/util/List.get:(I)Ljava/lang/Object;
     297: checkcast     #572                // class org/bouncycastle/jce/provider/PKIXPolicyNode
     300: astore        14
     302: aload         14
     304: invokevirtual #1105               // Method org/bouncycastle/jce/provider/PKIXPolicyNode.hasChildren:()Z
     307: ifne          321
     310: aload         5
     312: aload         4
     314: aload         14
     316: invokestatic  #1088               // Method org/bouncycastle/jce/provider/CertPathValidatorUtilities.removePolicyNode:(Lorg/bouncycastle/jce/provider/PKIXPolicyNode;[Ljava/util/List;Lorg/bouncycastle/jce/provider/PKIXPolicyNode;)Lorg/bouncycastle/jce/provider/PKIXPolicyNode;
     319: astore        5
     321: iinc          13, 1
     324: goto          276
     327: iinc          11, -1
     330: goto          261
     333: aload         5
     335: astore        8
     337: goto          626
     340: new           #526                // class java/util/HashSet
     343: dup
     344: invokespecial #988                // Method java/util/HashSet."<init>":()V
     347: astore        9
     349: iconst_0
     350: istore        10
     352: iload         10
     354: aload         4
     356: arraylength
     357: if_icmpge     476
     360: aload         4
     362: iload         10
     364: aaload
     365: astore        11
     367: iconst_0
     368: istore        12
     370: iload         12
     372: aload         11
     374: invokeinterface #1144,  1         // InterfaceMethod java/util/List.size:()I
     379: if_icmpge     470
     382: aload         11
     384: iload         12
     386: invokeinterface #1145,  2         // InterfaceMethod java/util/List.get:(I)Ljava/lang/Object;
     391: checkcast     #572                // class org/bouncycastle/jce/provider/PKIXPolicyNode
     394: astore        13
     396: ldc           #1                  // String 2.5.29.32.0
     398: aload         13
     400: invokevirtual #1107               // Method org/bouncycastle/jce/provider/PKIXPolicyNode.getValidPolicy:()Ljava/lang/String;
     403: invokevirtual #952                // Method java/lang/String.equals:(Ljava/lang/Object;)Z
     406: ifeq          464
     409: aload         13
     411: invokevirtual #1109               // Method org/bouncycastle/jce/provider/PKIXPolicyNode.getChildren:()Ljava/util/Iterator;
     414: astore        14
     416: aload         14
     418: invokeinterface #1142,  1         // InterfaceMethod java/util/Iterator.hasNext:()Z
     423: ifeq          464
     426: aload         14
     428: invokeinterface #1143,  1         // InterfaceMethod java/util/Iterator.next:()Ljava/lang/Object;
     433: checkcast     #572                // class org/bouncycastle/jce/provider/PKIXPolicyNode
     436: astore        15
     438: ldc           #1                  // String 2.5.29.32.0
     440: aload         15
     442: invokevirtual #1107               // Method org/bouncycastle/jce/provider/PKIXPolicyNode.getValidPolicy:()Ljava/lang/String;
     445: invokevirtual #952                // Method java/lang/String.equals:(Ljava/lang/Object;)Z
     448: ifne          461
     451: aload         9
     453: aload         15
     455: invokeinterface #1155,  2         // InterfaceMethod java/util/Set.add:(Ljava/lang/Object;)Z
     460: pop
     461: goto          416
     464: iinc          12, 1
     467: goto          370
     470: iinc          10, 1
     473: goto          352
     476: aload         9
     478: invokeinterface #1159,  1         // InterfaceMethod java/util/Set.iterator:()Ljava/util/Iterator;
     483: astore        10
     485: aload         10
     487: invokeinterface #1142,  1         // InterfaceMethod java/util/Iterator.hasNext:()Z
     492: ifeq          539
     495: aload         10
     497: invokeinterface #1143,  1         // InterfaceMethod java/util/Iterator.next:()Ljava/lang/Object;
     502: checkcast     #572                // class org/bouncycastle/jce/provider/PKIXPolicyNode
     505: astore        11
     507: aload         11
     509: invokevirtual #1107               // Method org/bouncycastle/jce/provider/PKIXPolicyNode.getValidPolicy:()Ljava/lang/String;
     512: astore        12
     514: aload_2
     515: aload         12
     517: invokeinterface #1156,  2         // InterfaceMethod java/util/Set.contains:(Ljava/lang/Object;)Z
     522: ifne          536
     525: aload         5
     527: aload         4
     529: aload         11
     531: invokestatic  #1088               // Method org/bouncycastle/jce/provider/CertPathValidatorUtilities.removePolicyNode:(Lorg/bouncycastle/jce/provider/PKIXPolicyNode;[Ljava/util/List;Lorg/bouncycastle/jce/provider/PKIXPolicyNode;)Lorg/bouncycastle/jce/provider/PKIXPolicyNode;
     534: astore        5
     536: goto          485
     539: aload         5
     541: ifnull        622
     544: iload         7
     546: iconst_1
     547: isub
     548: istore        11
     550: iload         11
     552: iflt          622
     555: aload         4
     557: iload         11
     559: aaload
     560: astore        12
     562: iconst_0
     563: istore        13
     565: iload         13
     567: aload         12
     569: invokeinterface #1144,  1         // InterfaceMethod java/util/List.size:()I
     574: if_icmpge     616
     577: aload         12
     579: iload         13
     581: invokeinterface #1145,  2         // InterfaceMethod java/util/List.get:(I)Ljava/lang/Object;
     586: checkcast     #572                // class org/bouncycastle/jce/provider/PKIXPolicyNode
     589: astore        14
     591: aload         14
     593: invokevirtual #1105               // Method org/bouncycastle/jce/provider/PKIXPolicyNode.hasChildren:()Z
     596: ifne          610
     599: aload         5
     601: aload         4
     603: aload         14
     605: invokestatic  #1088               // Method org/bouncycastle/jce/provider/CertPathValidatorUtilities.removePolicyNode:(Lorg/bouncycastle/jce/provider/PKIXPolicyNode;[Ljava/util/List;Lorg/bouncycastle/jce/provider/PKIXPolicyNode;)Lorg/bouncycastle/jce/provider/PKIXPolicyNode;
     608: astore        5
     610: iinc          13, 1
     613: goto          565
     616: iinc          11, -1
     619: goto          550
     622: aload         5
     624: astore        8
     626: aload         8
     628: areturn

  static {};
    Code:
       0: new           #568                // class org/bouncycastle/jce/provider/PKIXCRLUtil
       3: dup
       4: invokespecial #1095               // Method org/bouncycastle/jce/provider/PKIXCRLUtil."<init>":()V
       7: putstatic     #947                // Field CRL_UTIL:Lorg/bouncycastle/jce/provider/PKIXCRLUtil;
      10: getstatic     #921                // Field org/bouncycastle/asn1/x509/Extension.certificatePolicies:Lorg/bouncycastle/asn1/ASN1ObjectIdentifier;
      13: invokevirtual #996                // Method org/bouncycastle/asn1/ASN1ObjectIdentifier.getId:()Ljava/lang/String;
      16: putstatic     #934                // Field CERTIFICATE_POLICIES:Ljava/lang/String;
      19: getstatic     #929                // Field org/bouncycastle/asn1/x509/Extension.policyMappings:Lorg/bouncycastle/asn1/ASN1ObjectIdentifier;
      22: invokevirtual #996                // Method org/bouncycastle/asn1/ASN1ObjectIdentifier.getId:()Ljava/lang/String;
      25: putstatic     #944                // Field POLICY_MAPPINGS:Ljava/lang/String;
      28: getstatic     #924                // Field org/bouncycastle/asn1/x509/Extension.inhibitAnyPolicy:Lorg/bouncycastle/asn1/ASN1ObjectIdentifier;
      31: invokevirtual #996                // Method org/bouncycastle/asn1/ASN1ObjectIdentifier.getId:()Ljava/lang/String;
      34: putstatic     #939                // Field INHIBIT_ANY_POLICY:Ljava/lang/String;
      37: getstatic     #925                // Field org/bouncycastle/asn1/x509/Extension.issuingDistributionPoint:Lorg/bouncycastle/asn1/ASN1ObjectIdentifier;
      40: invokevirtual #996                // Method org/bouncycastle/asn1/ASN1ObjectIdentifier.getId:()Ljava/lang/String;
      43: putstatic     #940                // Field ISSUING_DISTRIBUTION_POINT:Ljava/lang/String;
      46: getstatic     #923                // Field org/bouncycastle/asn1/x509/Extension.freshestCRL:Lorg/bouncycastle/asn1/ASN1ObjectIdentifier;
      49: invokevirtual #996                // Method org/bouncycastle/asn1/ASN1ObjectIdentifier.getId:()Ljava/lang/String;
      52: putstatic     #938                // Field FRESHEST_CRL:Ljava/lang/String;
      55: getstatic     #922                // Field org/bouncycastle/asn1/x509/Extension.deltaCRLIndicator:Lorg/bouncycastle/asn1/ASN1ObjectIdentifier;
      58: invokevirtual #996                // Method org/bouncycastle/asn1/ASN1ObjectIdentifier.getId:()Ljava/lang/String;
      61: putstatic     #937                // Field DELTA_CRL_INDICATOR:Ljava/lang/String;
      64: getstatic     #928                // Field org/bouncycastle/asn1/x509/Extension.policyConstraints:Lorg/bouncycastle/asn1/ASN1ObjectIdentifier;
      67: invokevirtual #996                // Method org/bouncycastle/asn1/ASN1ObjectIdentifier.getId:()Ljava/lang/String;
      70: putstatic     #943                // Field POLICY_CONSTRAINTS:Ljava/lang/String;
      73: getstatic     #918                // Field org/bouncycastle/asn1/x509/Extension.basicConstraints:Lorg/bouncycastle/asn1/ASN1ObjectIdentifier;
      76: invokevirtual #996                // Method org/bouncycastle/asn1/ASN1ObjectIdentifier.getId:()Ljava/lang/String;
      79: putstatic     #933                // Field BASIC_CONSTRAINTS:Ljava/lang/String;
      82: getstatic     #919                // Field org/bouncycastle/asn1/x509/Extension.cRLDistributionPoints:Lorg/bouncycastle/asn1/ASN1ObjectIdentifier;
      85: invokevirtual #996                // Method org/bouncycastle/asn1/ASN1ObjectIdentifier.getId:()Ljava/lang/String;
      88: putstatic     #935                // Field CRL_DISTRIBUTION_POINTS:Ljava/lang/String;
      91: getstatic     #930                // Field org/bouncycastle/asn1/x509/Extension.subjectAlternativeName:Lorg/bouncycastle/asn1/ASN1ObjectIdentifier;
      94: invokevirtual #996                // Method org/bouncycastle/asn1/ASN1ObjectIdentifier.getId:()Ljava/lang/String;
      97: putstatic     #945                // Field SUBJECT_ALTERNATIVE_NAME:Ljava/lang/String;
     100: getstatic     #927                // Field org/bouncycastle/asn1/x509/Extension.nameConstraints:Lorg/bouncycastle/asn1/ASN1ObjectIdentifier;
     103: invokevirtual #996                // Method org/bouncycastle/asn1/ASN1ObjectIdentifier.getId:()Ljava/lang/String;
     106: putstatic     #942                // Field NAME_CONSTRAINTS:Ljava/lang/String;
     109: getstatic     #917                // Field org/bouncycastle/asn1/x509/Extension.authorityKeyIdentifier:Lorg/bouncycastle/asn1/ASN1ObjectIdentifier;
     112: invokevirtual #996                // Method org/bouncycastle/asn1/ASN1ObjectIdentifier.getId:()Ljava/lang/String;
     115: putstatic     #932                // Field AUTHORITY_KEY_IDENTIFIER:Ljava/lang/String;
     118: getstatic     #926                // Field org/bouncycastle/asn1/x509/Extension.keyUsage:Lorg/bouncycastle/asn1/ASN1ObjectIdentifier;
     121: invokevirtual #996                // Method org/bouncycastle/asn1/ASN1ObjectIdentifier.getId:()Ljava/lang/String;
     124: putstatic     #941                // Field KEY_USAGE:Ljava/lang/String;
     127: getstatic     #920                // Field org/bouncycastle/asn1/x509/Extension.cRLNumber:Lorg/bouncycastle/asn1/ASN1ObjectIdentifier;
     130: invokevirtual #996                // Method org/bouncycastle/asn1/ASN1ObjectIdentifier.getId:()Ljava/lang/String;
     133: putstatic     #936                // Field CRL_NUMBER:Ljava/lang/String;
     136: bipush        11
     138: anewarray     #502                // class java/lang/String
     141: dup
     142: iconst_0
     143: ldc_w         #495                // String unspecified
     146: aastore
     147: dup
     148: iconst_1
     149: ldc_w         #490                // String keyCompromise
     152: aastore
     153: dup
     154: iconst_2
     155: ldc_w         #487                // String cACompromise
     158: aastore
     159: dup
     160: iconst_3
     161: ldc_w         #486                // String affiliationChanged
     164: aastore
     165: dup
     166: iconst_4
     167: ldc_w         #493                // String superseded
     170: aastore
     171: dup
     172: iconst_5
     173: ldc_w         #489                // String cessationOfOperation
     176: aastore
     177: dup
     178: bipush        6
     180: ldc_w         #488                // String certificateHold
     183: aastore
     184: dup
     185: bipush        7
     187: ldc_w         #494                // String unknown
     190: aastore
     191: dup
     192: bipush        8
     194: ldc_w         #492                // String removeFromCRL
     197: aastore
     198: dup
     199: bipush        9
     201: ldc_w         #491                // String privilegeWithdrawn
     204: aastore
     205: dup
     206: bipush        10
     208: ldc_w         #485                // String aACompromise
     211: aastore
     212: putstatic     #946                // Field crlReasons:[Ljava/lang/String;
     215: return
}
