Compiled from "InvalidTestClassError.java"
public class org.junit.runners.model.InvalidTestClassError extends org.junit.runners.model.InitializationError {
  private static final long serialVersionUID;

  private final java.lang.String message;

  public org.junit.runners.model.InvalidTestClassError(java.lang.Class<?>, java.util.List<java.lang.Throwable>);
    Code:
       0: aload_0
       1: aload_2
       2: invokespecial #1                  // Method org/junit/runners/model/InitializationError."<init>":(Ljava/util/List;)V
       5: aload_0
       6: aload_1
       7: aload_2
       8: invokestatic  #2                  // Method createMessage:(Ljava/lang/Class;Ljava/util/List;)Ljava/lang/String;
      11: putfield      #3                  // Field message:Ljava/lang/String;
      14: return

  private static java.lang.String createMessage(java.lang.Class<?>, java.util.List<java.lang.Throwable>);
    Code:
       0: new           #4                  // class java/lang/StringBuilder
       3: dup
       4: invokespecial #5                  // Method java/lang/StringBuilder."<init>":()V
       7: astore_2
       8: aload_2
       9: ldc           #6                  // String Invalid test class \'%s\':
      11: iconst_1
      12: anewarray     #7                  // class java/lang/Object
      15: dup
      16: iconst_0
      17: aload_0
      18: invokevirtual #8                  // Method java/lang/Class.getName:()Ljava/lang/String;
      21: aastore
      22: invokestatic  #9                  // Method java/lang/String.format:(Ljava/lang/String;[Ljava/lang/Object;)Ljava/lang/String;
      25: invokevirtual #10                 // Method java/lang/StringBuilder.append:(Ljava/lang/String;)Ljava/lang/StringBuilder;
      28: pop
      29: iconst_1
      30: istore_3
      31: aload_1
      32: invokeinterface #11,  1           // InterfaceMethod java/util/List.iterator:()Ljava/util/Iterator;
      37: astore        4
      39: aload         4
      41: invokeinterface #12,  1           // InterfaceMethod java/util/Iterator.hasNext:()Z
      46: ifeq          104
      49: aload         4
      51: invokeinterface #13,  1           // InterfaceMethod java/util/Iterator.next:()Ljava/lang/Object;
      56: checkcast     #14                 // class java/lang/Throwable
      59: astore        5
      61: aload_2
      62: new           #4                  // class java/lang/StringBuilder
      65: dup
      66: invokespecial #5                  // Method java/lang/StringBuilder."<init>":()V
      69: ldc           #15                 // String \n
      71: invokevirtual #10                 // Method java/lang/StringBuilder.append:(Ljava/lang/String;)Ljava/lang/StringBuilder;
      74: iload_3
      75: iinc          3, 1
      78: invokevirtual #16                 // Method java/lang/StringBuilder.append:(I)Ljava/lang/StringBuilder;
      81: ldc           #17                 // String .
      83: invokevirtual #10                 // Method java/lang/StringBuilder.append:(Ljava/lang/String;)Ljava/lang/StringBuilder;
      86: aload         5
      88: invokevirtual #18                 // Method java/lang/Throwable.getMessage:()Ljava/lang/String;
      91: invokevirtual #10                 // Method java/lang/StringBuilder.append:(Ljava/lang/String;)Ljava/lang/StringBuilder;
      94: invokevirtual #19                 // Method java/lang/StringBuilder.toString:()Ljava/lang/String;
      97: invokevirtual #10                 // Method java/lang/StringBuilder.append:(Ljava/lang/String;)Ljava/lang/StringBuilder;
     100: pop
     101: goto          39
     104: aload_2
     105: invokevirtual #19                 // Method java/lang/StringBuilder.toString:()Ljava/lang/String;
     108: areturn

  public java.lang.String getMessage();
    Code:
       0: aload_0
       1: getfield      #3                  // Field message:Ljava/lang/String;
       4: areturn
}
