Compiled from "EmptyDataSource.java"
public class org.apache.axiom.util.activation.EmptyDataSource implements org.apache.axiom.ext.activation.SizeAwareDataSource {
  public static final org.apache.axiom.util.activation.EmptyDataSource INSTANCE;

  private static final java.io.InputStream emptyInputStream;

  private final java.lang.String contentType;

  public org.apache.axiom.util.activation.EmptyDataSource(java.lang.String);
    Code:
       0: aload_0
       1: invokespecial #1                  // Method java/lang/Object."<init>":()V
       4: aload_0
       5: aload_1
       6: putfield      #2                  // Field contentType:Ljava/lang/String;
       9: return

  public java.lang.String getContentType();
    Code:
       0: aload_0
       1: getfield      #2                  // Field contentType:Ljava/lang/String;
       4: areturn

  public java.lang.String getName();
    Code:
       0: aconst_null
       1: areturn

  public long getSize();
    Code:
       0: lconst_0
       1: lreturn

  public java.io.InputStream getInputStream() throws java.io.IOException;
    Code:
       0: getstatic     #3                  // Field emptyInputStream:Ljava/io/InputStream;
       3: areturn

  public java.io.OutputStream getOutputStream() throws java.io.IOException;
    Code:
       0: new           #4                  // class java/lang/UnsupportedOperationException
       3: dup
       4: invokespecial #5                  // Method java/lang/UnsupportedOperationException."<init>":()V
       7: athrow

  static {};
    Code:
       0: new           #6                  // class org/apache/axiom/util/activation/EmptyDataSource
       3: dup
       4: ldc           #7                  // String application/octet-stream
       6: invokespecial #8                  // Method "<init>":(Ljava/lang/String;)V
       9: putstatic     #9                  // Field INSTANCE:Lorg/apache/axiom/util/activation/EmptyDataSource;
      12: new           #10                 // class org/apache/axiom/util/activation/EmptyDataSource$1
      15: dup
      16: invokespecial #11                 // Method org/apache/axiom/util/activation/EmptyDataSource$1."<init>":()V
      19: putstatic     #3                  // Field emptyInputStream:Ljava/io/InputStream;
      22: return
}
