Compiled from "KeytabInputStream.java"
public class org.apache.kerby.kerberos.kerb.keytab.KeytabInputStream extends org.apache.kerby.kerberos.kerb.KrbInputStream {
  public org.apache.kerby.kerberos.kerb.keytab.KeytabInputStream(java.io.InputStream);
    Code:
       0: aload_0
       1: aload_1
       2: invokespecial #1                  // Method org/apache/kerby/kerberos/kerb/KrbInputStream."<init>":(Ljava/io/InputStream;)V
       5: return

  public org.apache.kerby.kerberos.kerb.type.KerberosTime readTime() throws java.io.IOException;
    Code:
       0: aload_0
       1: invokevirtual #2                  // Method readInt:()I
       4: i2l
       5: lstore_1
       6: new           #3                  // class org/apache/kerby/kerberos/kerb/type/KerberosTime
       9: dup
      10: lload_1
      11: ldc2_w        #4                  // long 1000l
      14: lmul
      15: invokespecial #6                  // Method org/apache/kerby/kerberos/kerb/type/KerberosTime."<init>":(J)V
      18: astore_3
      19: aload_3
      20: areturn

  public org.apache.kerby.kerberos.kerb.type.base.PrincipalName readPrincipal(int) throws java.io.IOException;
    Code:
       0: aload_0
       1: invokevirtual #7                  // Method readShort:()S
       4: istore_2
       5: iload_1
       6: sipush        1281
       9: if_icmpne     15
      12: iinc          2, -1
      15: aload_0
      16: invokevirtual #8                  // Method readCountedString:()Ljava/lang/String;
      19: astore_3
      20: new           #9                  // class java/util/ArrayList
      23: dup
      24: invokespecial #10                 // Method java/util/ArrayList."<init>":()V
      27: astore        4
      29: iconst_0
      30: istore        5
      32: iload         5
      34: iload_2
      35: if_icmpge     60
      38: aload_0
      39: invokevirtual #8                  // Method readCountedString:()Ljava/lang/String;
      42: astore        6
      44: aload         4
      46: aload         6
      48: invokeinterface #11,  2           // InterfaceMethod java/util/List.add:(Ljava/lang/Object;)Z
      53: pop
      54: iinc          5, 1
      57: goto          32
      60: aload_0
      61: invokevirtual #2                  // Method readInt:()I
      64: istore        5
      66: iload         5
      68: invokestatic  #12                 // Method java/lang/Integer.valueOf:(I)Ljava/lang/Integer;
      71: invokestatic  #13                 // Method org/apache/kerby/kerberos/kerb/type/base/NameType.fromValue:(Ljava/lang/Integer;)Lorg/apache/kerby/kerberos/kerb/type/base/NameType;
      74: astore        6
      76: new           #14                 // class org/apache/kerby/kerberos/kerb/type/base/PrincipalName
      79: dup
      80: aload         4
      82: aload         6
      84: invokespecial #15                 // Method org/apache/kerby/kerberos/kerb/type/base/PrincipalName."<init>":(Ljava/util/List;Lorg/apache/kerby/kerberos/kerb/type/base/NameType;)V
      87: astore        7
      89: aload         7
      91: aload_3
      92: invokevirtual #16                 // Method org/apache/kerby/kerberos/kerb/type/base/PrincipalName.setRealm:(Ljava/lang/String;)V
      95: aload         7
      97: areturn

  public int readOctetsCount() throws java.io.IOException;
    Code:
       0: aload_0
       1: invokevirtual #7                  // Method readShort:()S
       4: ireturn
}
