Compiled from "MaxRequestSizeTestCase.java"
final class io.undertow.server.MaxRequestSizeTestCase$1 implements io.undertow.server.HttpHandler {
  io.undertow.server.MaxRequestSizeTestCase$1();
    Code:
       0: aload_0
       1: invokespecial #2                  // Method java/lang/Object."<init>":()V
       4: return

  public void handleRequest(io.undertow.server.HttpServerExchange) throws java.lang.Exception;
    Code:
       0: aload_1
       1: invokevirtual #3                  // Method io/undertow/server/HttpServerExchange.getOutputStream:()Ljava/io/OutputStream;
       4: astore_2
       5: aload_1
       6: invokevirtual #4                  // Method io/undertow/server/HttpServerExchange.getInputStream:()Ljava/io/InputStream;
       9: astore_3
      10: aload_3
      11: invokestatic  #5                  // Method io/undertow/testutils/HttpClientUtils.readResponse:(Ljava/io/InputStream;)Ljava/lang/String;
      14: astore        4
      16: ldc           #6                  // String A message
      18: aload         4
      20: invokestatic  #7                  // Method org/junit/Assert.assertEquals:(Ljava/lang/Object;Ljava/lang/Object;)V
      23: aload_3
      24: invokevirtual #8                  // Method java/io/InputStream.close:()V
      27: aload_2
      28: invokevirtual #9                  // Method java/io/OutputStream.close:()V
      31: return
}
