Compiled from "NewlineInHeadersTestCase.java"
class io.undertow.server.NewlineInHeadersTestCase$1$1 implements io.undertow.io.Receiver$FullStringCallback {
  final io.undertow.server.NewlineInHeadersTestCase$1 this$1;

  io.undertow.server.NewlineInHeadersTestCase$1$1(io.undertow.server.NewlineInHeadersTestCase$1);
    Code:
       0: aload_0
       1: aload_1
       2: putfield      #2                  // Field this$1:Lio/undertow/server/NewlineInHeadersTestCase$1;
       5: aload_0
       6: invokespecial #3                  // Method java/lang/Object."<init>":()V
       9: return

  public void handle(io.undertow.server.HttpServerExchange, java.lang.String);
    Code:
       0: aload_1
       1: invokevirtual #4                  // Method io/undertow/server/HttpServerExchange.getResponseHeaders:()Lio/undertow/util/HeaderMap;
       4: ldc           #5                  // String echo
       6: invokestatic  #6                  // Method io/undertow/util/HttpString.tryFromString:(Ljava/lang/String;)Lio/undertow/util/HttpString;
       9: aload_2
      10: invokevirtual #7                  // Method io/undertow/util/HeaderMap.put:(Lio/undertow/util/HttpString;Ljava/lang/String;)Lio/undertow/util/HeaderMap;
      13: pop
      14: aload_1
      15: invokevirtual #8                  // Method io/undertow/server/HttpServerExchange.getResponseSender:()Lio/undertow/io/Sender;
      18: ldc           #9                  // String response
      20: invokeinterface #10,  2           // InterfaceMethod io/undertow/io/Sender.send:(Ljava/lang/String;)V
      25: return
}
