Compiled from "XmlServletWebServerApplicationContext.java"
public class org.springframework.boot.web.servlet.context.XmlServletWebServerApplicationContext extends org.springframework.boot.web.servlet.context.ServletWebServerApplicationContext {
  private final org.springframework.beans.factory.xml.XmlBeanDefinitionReader reader;

  public org.springframework.boot.web.servlet.context.XmlServletWebServerApplicationContext();
    Code:
       0: aload_0
       1: invokespecial #1                  // Method org/springframework/boot/web/servlet/context/ServletWebServerApplicationContext."<init>":()V
       4: aload_0
       5: new           #2                  // class org/springframework/beans/factory/xml/XmlBeanDefinitionReader
       8: dup
       9: aload_0
      10: invokespecial #3                  // Method org/springframework/beans/factory/xml/XmlBeanDefinitionReader."<init>":(Lorg/springframework/beans/factory/support/BeanDefinitionRegistry;)V
      13: putfield      #4                  // Field reader:Lorg/springframework/beans/factory/xml/XmlBeanDefinitionReader;
      16: aload_0
      17: getfield      #4                  // Field reader:Lorg/springframework/beans/factory/xml/XmlBeanDefinitionReader;
      20: aload_0
      21: invokevirtual #5                  // Method getEnvironment:()Lorg/springframework/core/env/ConfigurableEnvironment;
      24: invokevirtual #6                  // Method org/springframework/beans/factory/xml/XmlBeanDefinitionReader.setEnvironment:(Lorg/springframework/core/env/Environment;)V
      27: return

  public org.springframework.boot.web.servlet.context.XmlServletWebServerApplicationContext(org.springframework.core.io.Resource...);
    Code:
       0: aload_0
       1: invokespecial #1                  // Method org/springframework/boot/web/servlet/context/ServletWebServerApplicationContext."<init>":()V
       4: aload_0
       5: new           #2                  // class org/springframework/beans/factory/xml/XmlBeanDefinitionReader
       8: dup
       9: aload_0
      10: invokespecial #3                  // Method org/springframework/beans/factory/xml/XmlBeanDefinitionReader."<init>":(Lorg/springframework/beans/factory/support/BeanDefinitionRegistry;)V
      13: putfield      #4                  // Field reader:Lorg/springframework/beans/factory/xml/XmlBeanDefinitionReader;
      16: aload_0
      17: aload_1
      18: invokevirtual #7                  // Method load:([Lorg/springframework/core/io/Resource;)V
      21: aload_0
      22: invokevirtual #8                  // Method refresh:()V
      25: return

  public org.springframework.boot.web.servlet.context.XmlServletWebServerApplicationContext(java.lang.String...);
    Code:
       0: aload_0
       1: invokespecial #1                  // Method org/springframework/boot/web/servlet/context/ServletWebServerApplicationContext."<init>":()V
       4: aload_0
       5: new           #2                  // class org/springframework/beans/factory/xml/XmlBeanDefinitionReader
       8: dup
       9: aload_0
      10: invokespecial #3                  // Method org/springframework/beans/factory/xml/XmlBeanDefinitionReader."<init>":(Lorg/springframework/beans/factory/support/BeanDefinitionRegistry;)V
      13: putfield      #4                  // Field reader:Lorg/springframework/beans/factory/xml/XmlBeanDefinitionReader;
      16: aload_0
      17: aload_1
      18: invokevirtual #9                  // Method load:([Ljava/lang/String;)V
      21: aload_0
      22: invokevirtual #8                  // Method refresh:()V
      25: return

  public org.springframework.boot.web.servlet.context.XmlServletWebServerApplicationContext(java.lang.Class<?>, java.lang.String...);
    Code:
       0: aload_0
       1: invokespecial #1                  // Method org/springframework/boot/web/servlet/context/ServletWebServerApplicationContext."<init>":()V
       4: aload_0
       5: new           #2                  // class org/springframework/beans/factory/xml/XmlBeanDefinitionReader
       8: dup
       9: aload_0
      10: invokespecial #3                  // Method org/springframework/beans/factory/xml/XmlBeanDefinitionReader."<init>":(Lorg/springframework/beans/factory/support/BeanDefinitionRegistry;)V
      13: putfield      #4                  // Field reader:Lorg/springframework/beans/factory/xml/XmlBeanDefinitionReader;
      16: aload_0
      17: aload_1
      18: aload_2
      19: invokevirtual #10                 // Method load:(Ljava/lang/Class;[Ljava/lang/String;)V
      22: aload_0
      23: invokevirtual #8                  // Method refresh:()V
      26: return

  public void setValidating(boolean);
    Code:
       0: aload_0
       1: getfield      #4                  // Field reader:Lorg/springframework/beans/factory/xml/XmlBeanDefinitionReader;
       4: iload_1
       5: invokevirtual #11                 // Method org/springframework/beans/factory/xml/XmlBeanDefinitionReader.setValidating:(Z)V
       8: return

  public void setEnvironment(org.springframework.core.env.ConfigurableEnvironment);
    Code:
       0: aload_0
       1: aload_1
       2: invokespecial #12                 // Method org/springframework/boot/web/servlet/context/ServletWebServerApplicationContext.setEnvironment:(Lorg/springframework/core/env/ConfigurableEnvironment;)V
       5: aload_0
       6: getfield      #4                  // Field reader:Lorg/springframework/beans/factory/xml/XmlBeanDefinitionReader;
       9: aload_0
      10: invokevirtual #5                  // Method getEnvironment:()Lorg/springframework/core/env/ConfigurableEnvironment;
      13: invokevirtual #6                  // Method org/springframework/beans/factory/xml/XmlBeanDefinitionReader.setEnvironment:(Lorg/springframework/core/env/Environment;)V
      16: return

  public final void load(org.springframework.core.io.Resource...);
    Code:
       0: aload_0
       1: getfield      #4                  // Field reader:Lorg/springframework/beans/factory/xml/XmlBeanDefinitionReader;
       4: aload_1
       5: invokevirtual #13                 // Method org/springframework/beans/factory/xml/XmlBeanDefinitionReader.loadBeanDefinitions:([Lorg/springframework/core/io/Resource;)I
       8: pop
       9: return

  public final void load(java.lang.String...);
    Code:
       0: aload_0
       1: getfield      #4                  // Field reader:Lorg/springframework/beans/factory/xml/XmlBeanDefinitionReader;
       4: aload_1
       5: invokevirtual #14                 // Method org/springframework/beans/factory/xml/XmlBeanDefinitionReader.loadBeanDefinitions:([Ljava/lang/String;)I
       8: pop
       9: return

  public final void load(java.lang.Class<?>, java.lang.String...);
    Code:
       0: aload_2
       1: arraylength
       2: anewarray     #15                 // class org/springframework/core/io/Resource
       5: astore_3
       6: iconst_0
       7: istore        4
       9: iload         4
      11: aload_2
      12: arraylength
      13: if_icmpge     38
      16: aload_3
      17: iload         4
      19: new           #16                 // class org/springframework/core/io/ClassPathResource
      22: dup
      23: aload_2
      24: iload         4
      26: aaload
      27: aload_1
      28: invokespecial #17                 // Method org/springframework/core/io/ClassPathResource."<init>":(Ljava/lang/String;Ljava/lang/Class;)V
      31: aastore
      32: iinc          4, 1
      35: goto          9
      38: aload_0
      39: getfield      #4                  // Field reader:Lorg/springframework/beans/factory/xml/XmlBeanDefinitionReader;
      42: aload_3
      43: invokevirtual #13                 // Method org/springframework/beans/factory/xml/XmlBeanDefinitionReader.loadBeanDefinitions:([Lorg/springframework/core/io/Resource;)I
      46: pop
      47: return
}
