Compiled from "ServletUpgradeListener.java"
class io.undertow.servlet.core.ServletUpgradeListener$1 implements org.xnio.ChannelListener<org.xnio.StreamConnection> {
  final io.undertow.servlet.core.ServletUpgradeListener this$0;

  io.undertow.servlet.core.ServletUpgradeListener$1(io.undertow.servlet.core.ServletUpgradeListener);
    Code:
       0: aload_0
       1: aload_1
       2: putfield      #1                  // Field this$0:Lio/undertow/servlet/core/ServletUpgradeListener;
       5: aload_0
       6: invokespecial #2                  // Method java/lang/Object."<init>":()V
       9: return

  public void handleEvent(org.xnio.StreamConnection);
    Code:
       0: aload_0
       1: getfield      #1                  // Field this$0:Lio/undertow/servlet/core/ServletUpgradeListener;
       4: invokestatic  #3                  // Method io/undertow/servlet/core/ServletUpgradeListener.access$100:(Lio/undertow/servlet/core/ServletUpgradeListener;)Lio/undertow/servlet/api/ThreadSetupAction;
       7: aload_0
       8: getfield      #1                  // Field this$0:Lio/undertow/servlet/core/ServletUpgradeListener;
      11: invokestatic  #4                  // Method io/undertow/servlet/core/ServletUpgradeListener.access$000:(Lio/undertow/servlet/core/ServletUpgradeListener;)Lio/undertow/server/HttpServerExchange;
      14: invokeinterface #5,  2            // InterfaceMethod io/undertow/servlet/api/ThreadSetupAction.setup:(Lio/undertow/server/HttpServerExchange;)Lio/undertow/servlet/api/ThreadSetupAction$Handle;
      19: astore_2
      20: aload_0
      21: getfield      #1                  // Field this$0:Lio/undertow/servlet/core/ServletUpgradeListener;
      24: invokestatic  #6                  // Method io/undertow/servlet/core/ServletUpgradeListener.access$200:(Lio/undertow/servlet/core/ServletUpgradeListener;)Lio/undertow/servlet/api/InstanceHandle;
      27: invokeinterface #7,  1            // InterfaceMethod io/undertow/servlet/api/InstanceHandle.getInstance:()Ljava/lang/Object;
      32: checkcast     #8                  // class javax/servlet/http/HttpUpgradeHandler
      35: invokeinterface #9,  1            // InterfaceMethod javax/servlet/http/HttpUpgradeHandler.destroy:()V
      40: aload_2
      41: invokeinterface #10,  1           // InterfaceMethod io/undertow/servlet/api/ThreadSetupAction$Handle.tearDown:()V
      46: aload_0
      47: getfield      #1                  // Field this$0:Lio/undertow/servlet/core/ServletUpgradeListener;
      50: invokestatic  #6                  // Method io/undertow/servlet/core/ServletUpgradeListener.access$200:(Lio/undertow/servlet/core/ServletUpgradeListener;)Lio/undertow/servlet/api/InstanceHandle;
      53: invokeinterface #11,  1           // InterfaceMethod io/undertow/servlet/api/InstanceHandle.release:()V
      58: goto          76
      61: astore_3
      62: aload_0
      63: getfield      #1                  // Field this$0:Lio/undertow/servlet/core/ServletUpgradeListener;
      66: invokestatic  #6                  // Method io/undertow/servlet/core/ServletUpgradeListener.access$200:(Lio/undertow/servlet/core/ServletUpgradeListener;)Lio/undertow/servlet/api/InstanceHandle;
      69: invokeinterface #11,  1           // InterfaceMethod io/undertow/servlet/api/InstanceHandle.release:()V
      74: aload_3
      75: athrow
      76: goto          122
      79: astore        4
      81: aload_2
      82: invokeinterface #10,  1           // InterfaceMethod io/undertow/servlet/api/ThreadSetupAction$Handle.tearDown:()V
      87: aload_0
      88: getfield      #1                  // Field this$0:Lio/undertow/servlet/core/ServletUpgradeListener;
      91: invokestatic  #6                  // Method io/undertow/servlet/core/ServletUpgradeListener.access$200:(Lio/undertow/servlet/core/ServletUpgradeListener;)Lio/undertow/servlet/api/InstanceHandle;
      94: invokeinterface #11,  1           // InterfaceMethod io/undertow/servlet/api/InstanceHandle.release:()V
      99: goto          119
     102: astore        5
     104: aload_0
     105: getfield      #1                  // Field this$0:Lio/undertow/servlet/core/ServletUpgradeListener;
     108: invokestatic  #6                  // Method io/undertow/servlet/core/ServletUpgradeListener.access$200:(Lio/undertow/servlet/core/ServletUpgradeListener;)Lio/undertow/servlet/api/InstanceHandle;
     111: invokeinterface #11,  1           // InterfaceMethod io/undertow/servlet/api/InstanceHandle.release:()V
     116: aload         5
     118: athrow
     119: aload         4
     121: athrow
     122: return
    Exception table:
       from    to  target type
          40    46    61   any
          20    40    79   any
          81    87   102   any
         102   104   102   any
          79    81    79   any

  public void handleEvent(java.nio.channels.Channel);
    Code:
       0: aload_0
       1: aload_1
       2: checkcast     #12                 // class org/xnio/StreamConnection
       5: invokevirtual #13                 // Method handleEvent:(Lorg/xnio/StreamConnection;)V
       8: return
}
