Compiled from "ProtoBuf.java"
public final class kotlin.reflect.jvm.internal.impl.metadata.ProtoBuf$Function extends kotlin.reflect.jvm.internal.impl.protobuf.GeneratedMessageLite$ExtendableMessage<kotlin.reflect.jvm.internal.impl.metadata.ProtoBuf$Function> implements kotlin.reflect.jvm.internal.impl.metadata.ProtoBuf$FunctionOrBuilder {
  private static final kotlin.reflect.jvm.internal.impl.metadata.ProtoBuf$Function defaultInstance;

  private final kotlin.reflect.jvm.internal.impl.protobuf.ByteString unknownFields;

  public static kotlin.reflect.jvm.internal.impl.protobuf.Parser<kotlin.reflect.jvm.internal.impl.metadata.ProtoBuf$Function> PARSER;

  private int bitField0_;

  private int flags_;

  private int oldFlags_;

  private int name_;

  private kotlin.reflect.jvm.internal.impl.metadata.ProtoBuf$Type returnType_;

  private int returnTypeId_;

  private java.util.List<kotlin.reflect.jvm.internal.impl.metadata.ProtoBuf$TypeParameter> typeParameter_;

  private kotlin.reflect.jvm.internal.impl.metadata.ProtoBuf$Type receiverType_;

  private int receiverTypeId_;

  private java.util.List<kotlin.reflect.jvm.internal.impl.metadata.ProtoBuf$Type> contextReceiverType_;

  private java.util.List<java.lang.Integer> contextReceiverTypeId_;

  private int contextReceiverTypeIdMemoizedSerializedSize;

  private java.util.List<kotlin.reflect.jvm.internal.impl.metadata.ProtoBuf$ValueParameter> valueParameter_;

  private kotlin.reflect.jvm.internal.impl.metadata.ProtoBuf$TypeTable typeTable_;

  private java.util.List<java.lang.Integer> versionRequirement_;

  private kotlin.reflect.jvm.internal.impl.metadata.ProtoBuf$Contract contract_;

  private byte memoizedIsInitialized;

  private int memoizedSerializedSize;

  private kotlin.reflect.jvm.internal.impl.metadata.ProtoBuf$Function(kotlin.reflect.jvm.internal.impl.protobuf.GeneratedMessageLite$ExtendableBuilder<kotlin.reflect.jvm.internal.impl.metadata.ProtoBuf$Function, ?>);
    Code:
       0: aload_0
       1: aload_1
       2: invokespecial #141                // Method kotlin/reflect/jvm/internal/impl/protobuf/GeneratedMessageLite$ExtendableMessage."<init>":(Lkotlin/reflect/jvm/internal/impl/protobuf/GeneratedMessageLite$ExtendableBuilder;)V
       5: aload_0
       6: iconst_m1
       7: putfield      #37                 // Field contextReceiverTypeIdMemoizedSerializedSize:I
      10: aload_0
      11: iconst_m1
      12: putfield      #43                 // Field memoizedIsInitialized:B
      15: aload_0
      16: iconst_m1
      17: putfield      #44                 // Field memoizedSerializedSize:I
      20: aload_0
      21: aload_1
      22: invokevirtual #139                // Method kotlin/reflect/jvm/internal/impl/protobuf/GeneratedMessageLite$ExtendableBuilder.getUnknownFields:()Lkotlin/reflect/jvm/internal/impl/protobuf/ByteString;
      25: putfield      #53                 // Field unknownFields:Lkotlin/reflect/jvm/internal/impl/protobuf/ByteString;
      28: return

  private kotlin.reflect.jvm.internal.impl.metadata.ProtoBuf$Function(boolean);
    Code:
       0: aload_0
       1: invokespecial #140                // Method kotlin/reflect/jvm/internal/impl/protobuf/GeneratedMessageLite$ExtendableMessage."<init>":()V
       4: aload_0
       5: iconst_m1
       6: putfield      #37                 // Field contextReceiverTypeIdMemoizedSerializedSize:I
       9: aload_0
      10: iconst_m1
      11: putfield      #43                 // Field memoizedIsInitialized:B
      14: aload_0
      15: iconst_m1
      16: putfield      #44                 // Field memoizedSerializedSize:I
      19: aload_0
      20: getstatic     #60                 // Field kotlin/reflect/jvm/internal/impl/protobuf/ByteString.EMPTY:Lkotlin/reflect/jvm/internal/impl/protobuf/ByteString;
      23: putfield      #53                 // Field unknownFields:Lkotlin/reflect/jvm/internal/impl/protobuf/ByteString;
      26: return

  public static kotlin.reflect.jvm.internal.impl.metadata.ProtoBuf$Function getDefaultInstance();
    Code:
       0: getstatic     #41                 // Field defaultInstance:Lkotlin/reflect/jvm/internal/impl/metadata/ProtoBuf$Function;
       3: areturn

  public kotlin.reflect.jvm.internal.impl.metadata.ProtoBuf$Function getDefaultInstanceForType();
    Code:
       0: getstatic     #41                 // Field defaultInstance:Lkotlin/reflect/jvm/internal/impl/metadata/ProtoBuf$Function;
       3: areturn

  private kotlin.reflect.jvm.internal.impl.metadata.ProtoBuf$Function(kotlin.reflect.jvm.internal.impl.protobuf.CodedInputStream, kotlin.reflect.jvm.internal.impl.protobuf.ExtensionRegistryLite) throws kotlin.reflect.jvm.internal.impl.protobuf.InvalidProtocolBufferException;
    Code:
       0: aload_0
       1: invokespecial #140                // Method kotlin/reflect/jvm/internal/impl/protobuf/GeneratedMessageLite$ExtendableMessage."<init>":()V
       4: aload_0
       5: iconst_m1
       6: putfield      #37                 // Field contextReceiverTypeIdMemoizedSerializedSize:I
       9: aload_0
      10: iconst_m1
      11: putfield      #43                 // Field memoizedIsInitialized:B
      14: aload_0
      15: iconst_m1
      16: putfield      #44                 // Field memoizedSerializedSize:I
      19: aload_0
      20: invokespecial #96                 // Method initFields:()V
      23: iconst_0
      24: istore_3
      25: invokestatic  #119                // Method kotlin/reflect/jvm/internal/impl/protobuf/ByteString.newOutput:()Lkotlin/reflect/jvm/internal/impl/protobuf/ByteString$Output;
      28: astore        4
      30: aload         4
      32: iconst_1
      33: invokestatic  #133                // Method kotlin/reflect/jvm/internal/impl/protobuf/CodedOutputStream.newInstance:(Ljava/io/OutputStream;I)Lkotlin/reflect/jvm/internal/impl/protobuf/CodedOutputStream;
      36: astore        5
      38: iconst_0
      39: istore        6
      41: iload         6
      43: ifne          1059
      46: aload_1
      47: invokevirtual #128                // Method kotlin/reflect/jvm/internal/impl/protobuf/CodedInputStream.readTag:()I
      50: istore        7
      52: iload         7
      54: lookupswitch  { // 17
                     0: 200
                     8: 225
                    16: 246
                    26: 267
                    34: 344
                    42: 390
                    50: 467
                    56: 516
                    64: 538
                    72: 560
                    82: 581
                    88: 630
                    90: 678
                   242: 763
                   248: 843
                   250: 891
                   258: 976
               default: 206
          }
     200: iconst_1
     201: istore        6
     203: goto          1056
     206: aload_0
     207: aload_1
     208: aload         5
     210: aload_2
     211: iload         7
     213: invokevirtual #102                // Method parseUnknownField:(Lkotlin/reflect/jvm/internal/impl/protobuf/CodedInputStream;Lkotlin/reflect/jvm/internal/impl/protobuf/CodedOutputStream;Lkotlin/reflect/jvm/internal/impl/protobuf/ExtensionRegistryLite;I)Z
     216: ifne          1056
     219: iconst_1
     220: istore        6
     222: goto          1056
     225: aload_0
     226: dup
     227: getfield      #36                 // Field bitField0_:I
     230: iconst_2
     231: ior
     232: putfield      #36                 // Field bitField0_:I
     235: aload_0
     236: aload_1
     237: invokevirtual #125                // Method kotlin/reflect/jvm/internal/impl/protobuf/CodedInputStream.readInt32:()I
     240: putfield      #46                 // Field oldFlags_:I
     243: goto          1056
     246: aload_0
     247: dup
     248: getfield      #36                 // Field bitField0_:I
     251: iconst_4
     252: ior
     253: putfield      #36                 // Field bitField0_:I
     256: aload_0
     257: aload_1
     258: invokevirtual #125                // Method kotlin/reflect/jvm/internal/impl/protobuf/CodedInputStream.readInt32:()I
     261: putfield      #45                 // Field name_:I
     264: goto          1056
     267: aconst_null
     268: astore        8
     270: aload_0
     271: getfield      #36                 // Field bitField0_:I
     274: bipush        8
     276: iand
     277: bipush        8
     279: if_icmpne     291
     282: aload_0
     283: getfield      #50                 // Field returnType_:Lkotlin/reflect/jvm/internal/impl/metadata/ProtoBuf$Type;
     286: invokevirtual #109                // Method kotlin/reflect/jvm/internal/impl/metadata/ProtoBuf$Type.toBuilder:()Lkotlin/reflect/jvm/internal/impl/metadata/ProtoBuf$Type$Builder;
     289: astore        8
     291: aload_0
     292: aload_1
     293: getstatic     #56                 // Field kotlin/reflect/jvm/internal/impl/metadata/ProtoBuf$Type.PARSER:Lkotlin/reflect/jvm/internal/impl/protobuf/Parser;
     296: aload_2
     297: invokevirtual #126                // Method kotlin/reflect/jvm/internal/impl/protobuf/CodedInputStream.readMessage:(Lkotlin/reflect/jvm/internal/impl/protobuf/Parser;Lkotlin/reflect/jvm/internal/impl/protobuf/ExtensionRegistryLite;)Lkotlin/reflect/jvm/internal/impl/protobuf/MessageLite;
     300: checkcast     #15                 // class kotlin/reflect/jvm/internal/impl/metadata/ProtoBuf$Type
     303: putfield      #50                 // Field returnType_:Lkotlin/reflect/jvm/internal/impl/metadata/ProtoBuf$Type;
     306: aload         8
     308: ifnull        330
     311: aload         8
     313: aload_0
     314: getfield      #50                 // Field returnType_:Lkotlin/reflect/jvm/internal/impl/metadata/ProtoBuf$Type;
     317: invokevirtual #111                // Method kotlin/reflect/jvm/internal/impl/metadata/ProtoBuf$Type$Builder.mergeFrom:(Lkotlin/reflect/jvm/internal/impl/metadata/ProtoBuf$Type;)Lkotlin/reflect/jvm/internal/impl/metadata/ProtoBuf$Type$Builder;
     320: pop
     321: aload_0
     322: aload         8
     324: invokevirtual #110                // Method kotlin/reflect/jvm/internal/impl/metadata/ProtoBuf$Type$Builder.buildPartial:()Lkotlin/reflect/jvm/internal/impl/metadata/ProtoBuf$Type;
     327: putfield      #50                 // Field returnType_:Lkotlin/reflect/jvm/internal/impl/metadata/ProtoBuf$Type;
     330: aload_0
     331: dup
     332: getfield      #36                 // Field bitField0_:I
     335: bipush        8
     337: ior
     338: putfield      #36                 // Field bitField0_:I
     341: goto          1056
     344: iload_3
     345: bipush        32
     347: iand
     348: bipush        32
     350: if_icmpeq     369
     353: aload_0
     354: new           #4                  // class java/util/ArrayList
     357: dup
     358: invokespecial #64                 // Method java/util/ArrayList."<init>":()V
     361: putfield      #51                 // Field typeParameter_:Ljava/util/List;
     364: iload_3
     365: bipush        32
     367: ior
     368: istore_3
     369: aload_0
     370: getfield      #51                 // Field typeParameter_:Ljava/util/List;
     373: aload_1
     374: getstatic     #57                 // Field kotlin/reflect/jvm/internal/impl/metadata/ProtoBuf$TypeParameter.PARSER:Lkotlin/reflect/jvm/internal/impl/protobuf/Parser;
     377: aload_2
     378: invokevirtual #126                // Method kotlin/reflect/jvm/internal/impl/protobuf/CodedInputStream.readMessage:(Lkotlin/reflect/jvm/internal/impl/protobuf/Parser;Lkotlin/reflect/jvm/internal/impl/protobuf/ExtensionRegistryLite;)Lkotlin/reflect/jvm/internal/impl/protobuf/MessageLite;
     381: invokeinterface #145,  2          // InterfaceMethod java/util/List.add:(Ljava/lang/Object;)Z
     386: pop
     387: goto          1056
     390: aconst_null
     391: astore        8
     393: aload_0
     394: getfield      #36                 // Field bitField0_:I
     397: bipush        32
     399: iand
     400: bipush        32
     402: if_icmpne     414
     405: aload_0
     406: getfield      #48                 // Field receiverType_:Lkotlin/reflect/jvm/internal/impl/metadata/ProtoBuf$Type;
     409: invokevirtual #109                // Method kotlin/reflect/jvm/internal/impl/metadata/ProtoBuf$Type.toBuilder:()Lkotlin/reflect/jvm/internal/impl/metadata/ProtoBuf$Type$Builder;
     412: astore        8
     414: aload_0
     415: aload_1
     416: getstatic     #56                 // Field kotlin/reflect/jvm/internal/impl/metadata/ProtoBuf$Type.PARSER:Lkotlin/reflect/jvm/internal/impl/protobuf/Parser;
     419: aload_2
     420: invokevirtual #126                // Method kotlin/reflect/jvm/internal/impl/protobuf/CodedInputStream.readMessage:(Lkotlin/reflect/jvm/internal/impl/protobuf/Parser;Lkotlin/reflect/jvm/internal/impl/protobuf/ExtensionRegistryLite;)Lkotlin/reflect/jvm/internal/impl/protobuf/MessageLite;
     423: checkcast     #15                 // class kotlin/reflect/jvm/internal/impl/metadata/ProtoBuf$Type
     426: putfield      #48                 // Field receiverType_:Lkotlin/reflect/jvm/internal/impl/metadata/ProtoBuf$Type;
     429: aload         8
     431: ifnull        453
     434: aload         8
     436: aload_0
     437: getfield      #48                 // Field receiverType_:Lkotlin/reflect/jvm/internal/impl/metadata/ProtoBuf$Type;
     440: invokevirtual #111                // Method kotlin/reflect/jvm/internal/impl/metadata/ProtoBuf$Type$Builder.mergeFrom:(Lkotlin/reflect/jvm/internal/impl/metadata/ProtoBuf$Type;)Lkotlin/reflect/jvm/internal/impl/metadata/ProtoBuf$Type$Builder;
     443: pop
     444: aload_0
     445: aload         8
     447: invokevirtual #110                // Method kotlin/reflect/jvm/internal/impl/metadata/ProtoBuf$Type$Builder.buildPartial:()Lkotlin/reflect/jvm/internal/impl/metadata/ProtoBuf$Type;
     450: putfield      #48                 // Field receiverType_:Lkotlin/reflect/jvm/internal/impl/metadata/ProtoBuf$Type;
     453: aload_0
     454: dup
     455: getfield      #36                 // Field bitField0_:I
     458: bipush        32
     460: ior
     461: putfield      #36                 // Field bitField0_:I
     464: goto          1056
     467: iload_3
     468: sipush        1024
     471: iand
     472: sipush        1024
     475: if_icmpeq     495
     478: aload_0
     479: new           #4                  // class java/util/ArrayList
     482: dup
     483: invokespecial #64                 // Method java/util/ArrayList."<init>":()V
     486: putfield      #54                 // Field valueParameter_:Ljava/util/List;
     489: iload_3
     490: sipush        1024
     493: ior
     494: istore_3
     495: aload_0
     496: getfield      #54                 // Field valueParameter_:Ljava/util/List;
     499: aload_1
     500: getstatic     #59                 // Field kotlin/reflect/jvm/internal/impl/metadata/ProtoBuf$ValueParameter.PARSER:Lkotlin/reflect/jvm/internal/impl/protobuf/Parser;
     503: aload_2
     504: invokevirtual #126                // Method kotlin/reflect/jvm/internal/impl/protobuf/CodedInputStream.readMessage:(Lkotlin/reflect/jvm/internal/impl/protobuf/Parser;Lkotlin/reflect/jvm/internal/impl/protobuf/ExtensionRegistryLite;)Lkotlin/reflect/jvm/internal/impl/protobuf/MessageLite;
     507: invokeinterface #145,  2          // InterfaceMethod java/util/List.add:(Ljava/lang/Object;)Z
     512: pop
     513: goto          1056
     516: aload_0
     517: dup
     518: getfield      #36                 // Field bitField0_:I
     521: bipush        16
     523: ior
     524: putfield      #36                 // Field bitField0_:I
     527: aload_0
     528: aload_1
     529: invokevirtual #125                // Method kotlin/reflect/jvm/internal/impl/protobuf/CodedInputStream.readInt32:()I
     532: putfield      #49                 // Field returnTypeId_:I
     535: goto          1056
     538: aload_0
     539: dup
     540: getfield      #36                 // Field bitField0_:I
     543: bipush        64
     545: ior
     546: putfield      #36                 // Field bitField0_:I
     549: aload_0
     550: aload_1
     551: invokevirtual #125                // Method kotlin/reflect/jvm/internal/impl/protobuf/CodedInputStream.readInt32:()I
     554: putfield      #47                 // Field receiverTypeId_:I
     557: goto          1056
     560: aload_0
     561: dup
     562: getfield      #36                 // Field bitField0_:I
     565: iconst_1
     566: ior
     567: putfield      #36                 // Field bitField0_:I
     570: aload_0
     571: aload_1
     572: invokevirtual #125                // Method kotlin/reflect/jvm/internal/impl/protobuf/CodedInputStream.readInt32:()I
     575: putfield      #42                 // Field flags_:I
     578: goto          1056
     581: iload_3
     582: sipush        256
     585: iand
     586: sipush        256
     589: if_icmpeq     609
     592: aload_0
     593: new           #4                  // class java/util/ArrayList
     596: dup
     597: invokespecial #64                 // Method java/util/ArrayList."<init>":()V
     600: putfield      #39                 // Field contextReceiverType_:Ljava/util/List;
     603: iload_3
     604: sipush        256
     607: ior
     608: istore_3
     609: aload_0
     610: getfield      #39                 // Field contextReceiverType_:Ljava/util/List;
     613: aload_1
     614: getstatic     #56                 // Field kotlin/reflect/jvm/internal/impl/metadata/ProtoBuf$Type.PARSER:Lkotlin/reflect/jvm/internal/impl/protobuf/Parser;
     617: aload_2
     618: invokevirtual #126                // Method kotlin/reflect/jvm/internal/impl/protobuf/CodedInputStream.readMessage:(Lkotlin/reflect/jvm/internal/impl/protobuf/Parser;Lkotlin/reflect/jvm/internal/impl/protobuf/ExtensionRegistryLite;)Lkotlin/reflect/jvm/internal/impl/protobuf/MessageLite;
     621: invokeinterface #145,  2          // InterfaceMethod java/util/List.add:(Ljava/lang/Object;)Z
     626: pop
     627: goto          1056
     630: iload_3
     631: sipush        512
     634: iand
     635: sipush        512
     638: if_icmpeq     658
     641: aload_0
     642: new           #4                  // class java/util/ArrayList
     645: dup
     646: invokespecial #64                 // Method java/util/ArrayList."<init>":()V
     649: putfield      #38                 // Field contextReceiverTypeId_:Ljava/util/List;
     652: iload_3
     653: sipush        512
     656: ior
     657: istore_3
     658: aload_0
     659: getfield      #38                 // Field contextReceiverTypeId_:Ljava/util/List;
     662: aload_1
     663: invokevirtual #125                // Method kotlin/reflect/jvm/internal/impl/protobuf/CodedInputStream.readInt32:()I
     666: invokestatic  #63                 // Method java/lang/Integer.valueOf:(I)Ljava/lang/Integer;
     669: invokeinterface #145,  2          // InterfaceMethod java/util/List.add:(Ljava/lang/Object;)Z
     674: pop
     675: goto          1056
     678: aload_1
     679: invokevirtual #127                // Method kotlin/reflect/jvm/internal/impl/protobuf/CodedInputStream.readRawVarint32:()I
     682: istore        8
     684: aload_1
     685: iload         8
     687: invokevirtual #124                // Method kotlin/reflect/jvm/internal/impl/protobuf/CodedInputStream.pushLimit:(I)I
     690: istore        9
     692: iload_3
     693: sipush        512
     696: iand
     697: sipush        512
     700: if_icmpeq     727
     703: aload_1
     704: invokevirtual #122                // Method kotlin/reflect/jvm/internal/impl/protobuf/CodedInputStream.getBytesUntilLimit:()I
     707: ifle          727
     710: aload_0
     711: new           #4                  // class java/util/ArrayList
     714: dup
     715: invokespecial #64                 // Method java/util/ArrayList."<init>":()V
     718: putfield      #38                 // Field contextReceiverTypeId_:Ljava/util/List;
     721: iload_3
     722: sipush        512
     725: ior
     726: istore_3
     727: aload_1
     728: invokevirtual #122                // Method kotlin/reflect/jvm/internal/impl/protobuf/CodedInputStream.getBytesUntilLimit:()I
     731: ifle          754
     734: aload_0
     735: getfield      #38                 // Field contextReceiverTypeId_:Ljava/util/List;
     738: aload_1
     739: invokevirtual #125                // Method kotlin/reflect/jvm/internal/impl/protobuf/CodedInputStream.readInt32:()I
     742: invokestatic  #63                 // Method java/lang/Integer.valueOf:(I)Ljava/lang/Integer;
     745: invokeinterface #145,  2          // InterfaceMethod java/util/List.add:(Ljava/lang/Object;)Z
     750: pop
     751: goto          727
     754: aload_1
     755: iload         9
     757: invokevirtual #123                // Method kotlin/reflect/jvm/internal/impl/protobuf/CodedInputStream.popLimit:(I)V
     760: goto          1056
     763: aconst_null
     764: astore        8
     766: aload_0
     767: getfield      #36                 // Field bitField0_:I
     770: sipush        128
     773: iand
     774: sipush        128
     777: if_icmpne     789
     780: aload_0
     781: getfield      #52                 // Field typeTable_:Lkotlin/reflect/jvm/internal/impl/metadata/ProtoBuf$TypeTable;
     784: invokevirtual #115                // Method kotlin/reflect/jvm/internal/impl/metadata/ProtoBuf$TypeTable.toBuilder:()Lkotlin/reflect/jvm/internal/impl/metadata/ProtoBuf$TypeTable$Builder;
     787: astore        8
     789: aload_0
     790: aload_1
     791: getstatic     #58                 // Field kotlin/reflect/jvm/internal/impl/metadata/ProtoBuf$TypeTable.PARSER:Lkotlin/reflect/jvm/internal/impl/protobuf/Parser;
     794: aload_2
     795: invokevirtual #126                // Method kotlin/reflect/jvm/internal/impl/protobuf/CodedInputStream.readMessage:(Lkotlin/reflect/jvm/internal/impl/protobuf/Parser;Lkotlin/reflect/jvm/internal/impl/protobuf/ExtensionRegistryLite;)Lkotlin/reflect/jvm/internal/impl/protobuf/MessageLite;
     798: checkcast     #18                 // class kotlin/reflect/jvm/internal/impl/metadata/ProtoBuf$TypeTable
     801: putfield      #52                 // Field typeTable_:Lkotlin/reflect/jvm/internal/impl/metadata/ProtoBuf$TypeTable;
     804: aload         8
     806: ifnull        828
     809: aload         8
     811: aload_0
     812: getfield      #52                 // Field typeTable_:Lkotlin/reflect/jvm/internal/impl/metadata/ProtoBuf$TypeTable;
     815: invokevirtual #117                // Method kotlin/reflect/jvm/internal/impl/metadata/ProtoBuf$TypeTable$Builder.mergeFrom:(Lkotlin/reflect/jvm/internal/impl/metadata/ProtoBuf$TypeTable;)Lkotlin/reflect/jvm/internal/impl/metadata/ProtoBuf$TypeTable$Builder;
     818: pop
     819: aload_0
     820: aload         8
     822: invokevirtual #116                // Method kotlin/reflect/jvm/internal/impl/metadata/ProtoBuf$TypeTable$Builder.buildPartial:()Lkotlin/reflect/jvm/internal/impl/metadata/ProtoBuf$TypeTable;
     825: putfield      #52                 // Field typeTable_:Lkotlin/reflect/jvm/internal/impl/metadata/ProtoBuf$TypeTable;
     828: aload_0
     829: dup
     830: getfield      #36                 // Field bitField0_:I
     833: sipush        128
     836: ior
     837: putfield      #36                 // Field bitField0_:I
     840: goto          1056
     843: iload_3
     844: sipush        4096
     847: iand
     848: sipush        4096
     851: if_icmpeq     871
     854: aload_0
     855: new           #4                  // class java/util/ArrayList
     858: dup
     859: invokespecial #64                 // Method java/util/ArrayList."<init>":()V
     862: putfield      #55                 // Field versionRequirement_:Ljava/util/List;
     865: iload_3
     866: sipush        4096
     869: ior
     870: istore_3
     871: aload_0
     872: getfield      #55                 // Field versionRequirement_:Ljava/util/List;
     875: aload_1
     876: invokevirtual #125                // Method kotlin/reflect/jvm/internal/impl/protobuf/CodedInputStream.readInt32:()I
     879: invokestatic  #63                 // Method java/lang/Integer.valueOf:(I)Ljava/lang/Integer;
     882: invokeinterface #145,  2          // InterfaceMethod java/util/List.add:(Ljava/lang/Object;)Z
     887: pop
     888: goto          1056
     891: aload_1
     892: invokevirtual #127                // Method kotlin/reflect/jvm/internal/impl/protobuf/CodedInputStream.readRawVarint32:()I
     895: istore        8
     897: aload_1
     898: iload         8
     900: invokevirtual #124                // Method kotlin/reflect/jvm/internal/impl/protobuf/CodedInputStream.pushLimit:(I)I
     903: istore        9
     905: iload_3
     906: sipush        4096
     909: iand
     910: sipush        4096
     913: if_icmpeq     940
     916: aload_1
     917: invokevirtual #122                // Method kotlin/reflect/jvm/internal/impl/protobuf/CodedInputStream.getBytesUntilLimit:()I
     920: ifle          940
     923: aload_0
     924: new           #4                  // class java/util/ArrayList
     927: dup
     928: invokespecial #64                 // Method java/util/ArrayList."<init>":()V
     931: putfield      #55                 // Field versionRequirement_:Ljava/util/List;
     934: iload_3
     935: sipush        4096
     938: ior
     939: istore_3
     940: aload_1
     941: invokevirtual #122                // Method kotlin/reflect/jvm/internal/impl/protobuf/CodedInputStream.getBytesUntilLimit:()I
     944: ifle          967
     947: aload_0
     948: getfield      #55                 // Field versionRequirement_:Ljava/util/List;
     951: aload_1
     952: invokevirtual #125                // Method kotlin/reflect/jvm/internal/impl/protobuf/CodedInputStream.readInt32:()I
     955: invokestatic  #63                 // Method java/lang/Integer.valueOf:(I)Ljava/lang/Integer;
     958: invokeinterface #145,  2          // InterfaceMethod java/util/List.add:(Ljava/lang/Object;)Z
     963: pop
     964: goto          940
     967: aload_1
     968: iload         9
     970: invokevirtual #123                // Method kotlin/reflect/jvm/internal/impl/protobuf/CodedInputStream.popLimit:(I)V
     973: goto          1056
     976: aconst_null
     977: astore        8
     979: aload_0
     980: getfield      #36                 // Field bitField0_:I
     983: sipush        256
     986: iand
     987: sipush        256
     990: if_icmpne     1002
     993: aload_0
     994: getfield      #40                 // Field contract_:Lkotlin/reflect/jvm/internal/impl/metadata/ProtoBuf$Contract;
     997: invokevirtual #69                 // Method kotlin/reflect/jvm/internal/impl/metadata/ProtoBuf$Contract.toBuilder:()Lkotlin/reflect/jvm/internal/impl/metadata/ProtoBuf$Contract$Builder;
    1000: astore        8
    1002: aload_0
    1003: aload_1
    1004: getstatic     #34                 // Field kotlin/reflect/jvm/internal/impl/metadata/ProtoBuf$Contract.PARSER:Lkotlin/reflect/jvm/internal/impl/protobuf/Parser;
    1007: aload_2
    1008: invokevirtual #126                // Method kotlin/reflect/jvm/internal/impl/protobuf/CodedInputStream.readMessage:(Lkotlin/reflect/jvm/internal/impl/protobuf/Parser;Lkotlin/reflect/jvm/internal/impl/protobuf/ExtensionRegistryLite;)Lkotlin/reflect/jvm/internal/impl/protobuf/MessageLite;
    1011: checkcast     #9                  // class kotlin/reflect/jvm/internal/impl/metadata/ProtoBuf$Contract
    1014: putfield      #40                 // Field contract_:Lkotlin/reflect/jvm/internal/impl/metadata/ProtoBuf$Contract;
    1017: aload         8
    1019: ifnull        1041
    1022: aload         8
    1024: aload_0
    1025: getfield      #40                 // Field contract_:Lkotlin/reflect/jvm/internal/impl/metadata/ProtoBuf$Contract;
    1028: invokevirtual #71                 // Method kotlin/reflect/jvm/internal/impl/metadata/ProtoBuf$Contract$Builder.mergeFrom:(Lkotlin/reflect/jvm/internal/impl/metadata/ProtoBuf$Contract;)Lkotlin/reflect/jvm/internal/impl/metadata/ProtoBuf$Contract$Builder;
    1031: pop
    1032: aload_0
    1033: aload         8
    1035: invokevirtual #70                 // Method kotlin/reflect/jvm/internal/impl/metadata/ProtoBuf$Contract$Builder.buildPartial:()Lkotlin/reflect/jvm/internal/impl/metadata/ProtoBuf$Contract;
    1038: putfield      #40                 // Field contract_:Lkotlin/reflect/jvm/internal/impl/metadata/ProtoBuf$Contract;
    1041: aload_0
    1042: dup
    1043: getfield      #36                 // Field bitField0_:I
    1046: sipush        256
    1049: ior
    1050: putfield      #36                 // Field bitField0_:I
    1053: goto          1056
    1056: goto          41
    1059: iload_3
    1060: bipush        32
    1062: iand
    1063: bipush        32
    1065: if_icmpne     1079
    1068: aload_0
    1069: aload_0
    1070: getfield      #51                 // Field typeParameter_:Ljava/util/List;
    1073: invokestatic  #66                 // Method java/util/Collections.unmodifiableList:(Ljava/util/List;)Ljava/util/List;
    1076: putfield      #51                 // Field typeParameter_:Ljava/util/List;
    1079: iload_3
    1080: sipush        1024
    1083: iand
    1084: sipush        1024
    1087: if_icmpne     1101
    1090: aload_0
    1091: aload_0
    1092: getfield      #54                 // Field valueParameter_:Ljava/util/List;
    1095: invokestatic  #66                 // Method java/util/Collections.unmodifiableList:(Ljava/util/List;)Ljava/util/List;
    1098: putfield      #54                 // Field valueParameter_:Ljava/util/List;
    1101: iload_3
    1102: sipush        256
    1105: iand
    1106: sipush        256
    1109: if_icmpne     1123
    1112: aload_0
    1113: aload_0
    1114: getfield      #39                 // Field contextReceiverType_:Ljava/util/List;
    1117: invokestatic  #66                 // Method java/util/Collections.unmodifiableList:(Ljava/util/List;)Ljava/util/List;
    1120: putfield      #39                 // Field contextReceiverType_:Ljava/util/List;
    1123: iload_3
    1124: sipush        512
    1127: iand
    1128: sipush        512
    1131: if_icmpne     1145
    1134: aload_0
    1135: aload_0
    1136: getfield      #38                 // Field contextReceiverTypeId_:Ljava/util/List;
    1139: invokestatic  #66                 // Method java/util/Collections.unmodifiableList:(Ljava/util/List;)Ljava/util/List;
    1142: putfield      #38                 // Field contextReceiverTypeId_:Ljava/util/List;
    1145: iload_3
    1146: sipush        4096
    1149: iand
    1150: sipush        4096
    1153: if_icmpne     1167
    1156: aload_0
    1157: aload_0
    1158: getfield      #55                 // Field versionRequirement_:Ljava/util/List;
    1161: invokestatic  #66                 // Method java/util/Collections.unmodifiableList:(Ljava/util/List;)Ljava/util/List;
    1164: putfield      #55                 // Field versionRequirement_:Ljava/util/List;
    1167: aload         5
    1169: invokevirtual #132                // Method kotlin/reflect/jvm/internal/impl/protobuf/CodedOutputStream.flush:()V
    1172: aload_0
    1173: aload         4
    1175: invokevirtual #121                // Method kotlin/reflect/jvm/internal/impl/protobuf/ByteString$Output.toByteString:()Lkotlin/reflect/jvm/internal/impl/protobuf/ByteString;
    1178: putfield      #53                 // Field unknownFields:Lkotlin/reflect/jvm/internal/impl/protobuf/ByteString;
    1181: goto          1212
    1184: astore        6
    1186: aload_0
    1187: aload         4
    1189: invokevirtual #121                // Method kotlin/reflect/jvm/internal/impl/protobuf/ByteString$Output.toByteString:()Lkotlin/reflect/jvm/internal/impl/protobuf/ByteString;
    1192: putfield      #53                 // Field unknownFields:Lkotlin/reflect/jvm/internal/impl/protobuf/ByteString;
    1195: goto          1212
    1198: astore        10
    1200: aload_0
    1201: aload         4
    1203: invokevirtual #121                // Method kotlin/reflect/jvm/internal/impl/protobuf/ByteString$Output.toByteString:()Lkotlin/reflect/jvm/internal/impl/protobuf/ByteString;
    1206: putfield      #53                 // Field unknownFields:Lkotlin/reflect/jvm/internal/impl/protobuf/ByteString;
    1209: aload         10
    1211: athrow
    1212: aload_0
    1213: invokevirtual #97                 // Method makeExtensionsImmutable:()V
    1216: goto          1409
    1219: astore        6
    1221: aload         6
    1223: aload_0
    1224: invokevirtual #144                // Method kotlin/reflect/jvm/internal/impl/protobuf/InvalidProtocolBufferException.setUnfinishedMessage:(Lkotlin/reflect/jvm/internal/impl/protobuf/MessageLite;)Lkotlin/reflect/jvm/internal/impl/protobuf/InvalidProtocolBufferException;
    1227: athrow
    1228: astore        6
    1230: new           #30                 // class kotlin/reflect/jvm/internal/impl/protobuf/InvalidProtocolBufferException
    1233: dup
    1234: aload         6
    1236: invokevirtual #61                 // Method java/io/IOException.getMessage:()Ljava/lang/String;
    1239: invokespecial #143                // Method kotlin/reflect/jvm/internal/impl/protobuf/InvalidProtocolBufferException."<init>":(Ljava/lang/String;)V
    1242: aload_0
    1243: invokevirtual #144                // Method kotlin/reflect/jvm/internal/impl/protobuf/InvalidProtocolBufferException.setUnfinishedMessage:(Lkotlin/reflect/jvm/internal/impl/protobuf/MessageLite;)Lkotlin/reflect/jvm/internal/impl/protobuf/InvalidProtocolBufferException;
    1246: athrow
    1247: astore        11
    1249: iload_3
    1250: bipush        32
    1252: iand
    1253: bipush        32
    1255: if_icmpne     1269
    1258: aload_0
    1259: aload_0
    1260: getfield      #51                 // Field typeParameter_:Ljava/util/List;
    1263: invokestatic  #66                 // Method java/util/Collections.unmodifiableList:(Ljava/util/List;)Ljava/util/List;
    1266: putfield      #51                 // Field typeParameter_:Ljava/util/List;
    1269: iload_3
    1270: sipush        1024
    1273: iand
    1274: sipush        1024
    1277: if_icmpne     1291
    1280: aload_0
    1281: aload_0
    1282: getfield      #54                 // Field valueParameter_:Ljava/util/List;
    1285: invokestatic  #66                 // Method java/util/Collections.unmodifiableList:(Ljava/util/List;)Ljava/util/List;
    1288: putfield      #54                 // Field valueParameter_:Ljava/util/List;
    1291: iload_3
    1292: sipush        256
    1295: iand
    1296: sipush        256
    1299: if_icmpne     1313
    1302: aload_0
    1303: aload_0
    1304: getfield      #39                 // Field contextReceiverType_:Ljava/util/List;
    1307: invokestatic  #66                 // Method java/util/Collections.unmodifiableList:(Ljava/util/List;)Ljava/util/List;
    1310: putfield      #39                 // Field contextReceiverType_:Ljava/util/List;
    1313: iload_3
    1314: sipush        512
    1317: iand
    1318: sipush        512
    1321: if_icmpne     1335
    1324: aload_0
    1325: aload_0
    1326: getfield      #38                 // Field contextReceiverTypeId_:Ljava/util/List;
    1329: invokestatic  #66                 // Method java/util/Collections.unmodifiableList:(Ljava/util/List;)Ljava/util/List;
    1332: putfield      #38                 // Field contextReceiverTypeId_:Ljava/util/List;
    1335: iload_3
    1336: sipush        4096
    1339: iand
    1340: sipush        4096
    1343: if_icmpne     1357
    1346: aload_0
    1347: aload_0
    1348: getfield      #55                 // Field versionRequirement_:Ljava/util/List;
    1351: invokestatic  #66                 // Method java/util/Collections.unmodifiableList:(Ljava/util/List;)Ljava/util/List;
    1354: putfield      #55                 // Field versionRequirement_:Ljava/util/List;
    1357: aload         5
    1359: invokevirtual #132                // Method kotlin/reflect/jvm/internal/impl/protobuf/CodedOutputStream.flush:()V
    1362: aload_0
    1363: aload         4
    1365: invokevirtual #121                // Method kotlin/reflect/jvm/internal/impl/protobuf/ByteString$Output.toByteString:()Lkotlin/reflect/jvm/internal/impl/protobuf/ByteString;
    1368: putfield      #53                 // Field unknownFields:Lkotlin/reflect/jvm/internal/impl/protobuf/ByteString;
    1371: goto          1402
    1374: astore        12
    1376: aload_0
    1377: aload         4
    1379: invokevirtual #121                // Method kotlin/reflect/jvm/internal/impl/protobuf/ByteString$Output.toByteString:()Lkotlin/reflect/jvm/internal/impl/protobuf/ByteString;
    1382: putfield      #53                 // Field unknownFields:Lkotlin/reflect/jvm/internal/impl/protobuf/ByteString;
    1385: goto          1402
    1388: astore        13
    1390: aload_0
    1391: aload         4
    1393: invokevirtual #121                // Method kotlin/reflect/jvm/internal/impl/protobuf/ByteString$Output.toByteString:()Lkotlin/reflect/jvm/internal/impl/protobuf/ByteString;
    1396: putfield      #53                 // Field unknownFields:Lkotlin/reflect/jvm/internal/impl/protobuf/ByteString;
    1399: aload         13
    1401: athrow
    1402: aload_0
    1403: invokevirtual #97                 // Method makeExtensionsImmutable:()V
    1406: aload         11
    1408: athrow
    1409: return
    Exception table:
       from    to  target type
        1167  1172  1184   Class java/io/IOException
        1167  1172  1198   any
        1184  1186  1198   any
        1198  1200  1198   any
          38  1059  1219   Class kotlin/reflect/jvm/internal/impl/protobuf/InvalidProtocolBufferException
          38  1059  1228   Class java/io/IOException
          38  1059  1247   any
        1357  1362  1374   Class java/io/IOException
        1357  1362  1388   any
        1374  1376  1388   any
        1388  1390  1388   any
        1219  1249  1247   any

  public kotlin.reflect.jvm.internal.impl.protobuf.Parser<kotlin.reflect.jvm.internal.impl.metadata.ProtoBuf$Function> getParserForType();
    Code:
       0: getstatic     #35                 // Field PARSER:Lkotlin/reflect/jvm/internal/impl/protobuf/Parser;
       3: areturn

  public boolean hasFlags();
    Code:
       0: aload_0
       1: getfield      #36                 // Field bitField0_:I
       4: iconst_1
       5: iand
       6: iconst_1
       7: if_icmpne     14
      10: iconst_1
      11: goto          15
      14: iconst_0
      15: ireturn

  public int getFlags();
    Code:
       0: aload_0
       1: getfield      #42                 // Field flags_:I
       4: ireturn

  public boolean hasOldFlags();
    Code:
       0: aload_0
       1: getfield      #36                 // Field bitField0_:I
       4: iconst_2
       5: iand
       6: iconst_2
       7: if_icmpne     14
      10: iconst_1
      11: goto          15
      14: iconst_0
      15: ireturn

  public int getOldFlags();
    Code:
       0: aload_0
       1: getfield      #46                 // Field oldFlags_:I
       4: ireturn

  public boolean hasName();
    Code:
       0: aload_0
       1: getfield      #36                 // Field bitField0_:I
       4: iconst_4
       5: iand
       6: iconst_4
       7: if_icmpne     14
      10: iconst_1
      11: goto          15
      14: iconst_0
      15: ireturn

  public int getName();
    Code:
       0: aload_0
       1: getfield      #45                 // Field name_:I
       4: ireturn

  public boolean hasReturnType();
    Code:
       0: aload_0
       1: getfield      #36                 // Field bitField0_:I
       4: bipush        8
       6: iand
       7: bipush        8
       9: if_icmpne     16
      12: iconst_1
      13: goto          17
      16: iconst_0
      17: ireturn

  public kotlin.reflect.jvm.internal.impl.metadata.ProtoBuf$Type getReturnType();
    Code:
       0: aload_0
       1: getfield      #50                 // Field returnType_:Lkotlin/reflect/jvm/internal/impl/metadata/ProtoBuf$Type;
       4: areturn

  public boolean hasReturnTypeId();
    Code:
       0: aload_0
       1: getfield      #36                 // Field bitField0_:I
       4: bipush        16
       6: iand
       7: bipush        16
       9: if_icmpne     16
      12: iconst_1
      13: goto          17
      16: iconst_0
      17: ireturn

  public int getReturnTypeId();
    Code:
       0: aload_0
       1: getfield      #49                 // Field returnTypeId_:I
       4: ireturn

  public java.util.List<kotlin.reflect.jvm.internal.impl.metadata.ProtoBuf$TypeParameter> getTypeParameterList();
    Code:
       0: aload_0
       1: getfield      #51                 // Field typeParameter_:Ljava/util/List;
       4: areturn

  public int getTypeParameterCount();
    Code:
       0: aload_0
       1: getfield      #51                 // Field typeParameter_:Ljava/util/List;
       4: invokeinterface #148,  1          // InterfaceMethod java/util/List.size:()I
       9: ireturn

  public kotlin.reflect.jvm.internal.impl.metadata.ProtoBuf$TypeParameter getTypeParameter(int);
    Code:
       0: aload_0
       1: getfield      #51                 // Field typeParameter_:Ljava/util/List;
       4: iload_1
       5: invokeinterface #146,  2          // InterfaceMethod java/util/List.get:(I)Ljava/lang/Object;
      10: checkcast     #17                 // class kotlin/reflect/jvm/internal/impl/metadata/ProtoBuf$TypeParameter
      13: areturn

  public boolean hasReceiverType();
    Code:
       0: aload_0
       1: getfield      #36                 // Field bitField0_:I
       4: bipush        32
       6: iand
       7: bipush        32
       9: if_icmpne     16
      12: iconst_1
      13: goto          17
      16: iconst_0
      17: ireturn

  public kotlin.reflect.jvm.internal.impl.metadata.ProtoBuf$Type getReceiverType();
    Code:
       0: aload_0
       1: getfield      #48                 // Field receiverType_:Lkotlin/reflect/jvm/internal/impl/metadata/ProtoBuf$Type;
       4: areturn

  public boolean hasReceiverTypeId();
    Code:
       0: aload_0
       1: getfield      #36                 // Field bitField0_:I
       4: bipush        64
       6: iand
       7: bipush        64
       9: if_icmpne     16
      12: iconst_1
      13: goto          17
      16: iconst_0
      17: ireturn

  public int getReceiverTypeId();
    Code:
       0: aload_0
       1: getfield      #47                 // Field receiverTypeId_:I
       4: ireturn

  public java.util.List<kotlin.reflect.jvm.internal.impl.metadata.ProtoBuf$Type> getContextReceiverTypeList();
    Code:
       0: aload_0
       1: getfield      #39                 // Field contextReceiverType_:Ljava/util/List;
       4: areturn

  public int getContextReceiverTypeCount();
    Code:
       0: aload_0
       1: getfield      #39                 // Field contextReceiverType_:Ljava/util/List;
       4: invokeinterface #148,  1          // InterfaceMethod java/util/List.size:()I
       9: ireturn

  public kotlin.reflect.jvm.internal.impl.metadata.ProtoBuf$Type getContextReceiverType(int);
    Code:
       0: aload_0
       1: getfield      #39                 // Field contextReceiverType_:Ljava/util/List;
       4: iload_1
       5: invokeinterface #146,  2          // InterfaceMethod java/util/List.get:(I)Ljava/lang/Object;
      10: checkcast     #15                 // class kotlin/reflect/jvm/internal/impl/metadata/ProtoBuf$Type
      13: areturn

  public java.util.List<java.lang.Integer> getContextReceiverTypeIdList();
    Code:
       0: aload_0
       1: getfield      #38                 // Field contextReceiverTypeId_:Ljava/util/List;
       4: areturn

  public java.util.List<kotlin.reflect.jvm.internal.impl.metadata.ProtoBuf$ValueParameter> getValueParameterList();
    Code:
       0: aload_0
       1: getfield      #54                 // Field valueParameter_:Ljava/util/List;
       4: areturn

  public int getValueParameterCount();
    Code:
       0: aload_0
       1: getfield      #54                 // Field valueParameter_:Ljava/util/List;
       4: invokeinterface #148,  1          // InterfaceMethod java/util/List.size:()I
       9: ireturn

  public kotlin.reflect.jvm.internal.impl.metadata.ProtoBuf$ValueParameter getValueParameter(int);
    Code:
       0: aload_0
       1: getfield      #54                 // Field valueParameter_:Ljava/util/List;
       4: iload_1
       5: invokeinterface #146,  2          // InterfaceMethod java/util/List.get:(I)Ljava/lang/Object;
      10: checkcast     #20                 // class kotlin/reflect/jvm/internal/impl/metadata/ProtoBuf$ValueParameter
      13: areturn

  public boolean hasTypeTable();
    Code:
       0: aload_0
       1: getfield      #36                 // Field bitField0_:I
       4: sipush        128
       7: iand
       8: sipush        128
      11: if_icmpne     18
      14: iconst_1
      15: goto          19
      18: iconst_0
      19: ireturn

  public kotlin.reflect.jvm.internal.impl.metadata.ProtoBuf$TypeTable getTypeTable();
    Code:
       0: aload_0
       1: getfield      #52                 // Field typeTable_:Lkotlin/reflect/jvm/internal/impl/metadata/ProtoBuf$TypeTable;
       4: areturn

  public java.util.List<java.lang.Integer> getVersionRequirementList();
    Code:
       0: aload_0
       1: getfield      #55                 // Field versionRequirement_:Ljava/util/List;
       4: areturn

  public boolean hasContract();
    Code:
       0: aload_0
       1: getfield      #36                 // Field bitField0_:I
       4: sipush        256
       7: iand
       8: sipush        256
      11: if_icmpne     18
      14: iconst_1
      15: goto          19
      18: iconst_0
      19: ireturn

  public kotlin.reflect.jvm.internal.impl.metadata.ProtoBuf$Contract getContract();
    Code:
       0: aload_0
       1: getfield      #40                 // Field contract_:Lkotlin/reflect/jvm/internal/impl/metadata/ProtoBuf$Contract;
       4: areturn

  private void initFields();
    Code:
       0: aload_0
       1: bipush        6
       3: putfield      #42                 // Field flags_:I
       6: aload_0
       7: bipush        6
       9: putfield      #46                 // Field oldFlags_:I
      12: aload_0
      13: iconst_0
      14: putfield      #45                 // Field name_:I
      17: aload_0
      18: invokestatic  #107                // Method kotlin/reflect/jvm/internal/impl/metadata/ProtoBuf$Type.getDefaultInstance:()Lkotlin/reflect/jvm/internal/impl/metadata/ProtoBuf$Type;
      21: putfield      #50                 // Field returnType_:Lkotlin/reflect/jvm/internal/impl/metadata/ProtoBuf$Type;
      24: aload_0
      25: iconst_0
      26: putfield      #49                 // Field returnTypeId_:I
      29: aload_0
      30: invokestatic  #65                 // Method java/util/Collections.emptyList:()Ljava/util/List;
      33: putfield      #51                 // Field typeParameter_:Ljava/util/List;
      36: aload_0
      37: invokestatic  #107                // Method kotlin/reflect/jvm/internal/impl/metadata/ProtoBuf$Type.getDefaultInstance:()Lkotlin/reflect/jvm/internal/impl/metadata/ProtoBuf$Type;
      40: putfield      #48                 // Field receiverType_:Lkotlin/reflect/jvm/internal/impl/metadata/ProtoBuf$Type;
      43: aload_0
      44: iconst_0
      45: putfield      #47                 // Field receiverTypeId_:I
      48: aload_0
      49: invokestatic  #65                 // Method java/util/Collections.emptyList:()Ljava/util/List;
      52: putfield      #39                 // Field contextReceiverType_:Ljava/util/List;
      55: aload_0
      56: invokestatic  #65                 // Method java/util/Collections.emptyList:()Ljava/util/List;
      59: putfield      #38                 // Field contextReceiverTypeId_:Ljava/util/List;
      62: aload_0
      63: invokestatic  #65                 // Method java/util/Collections.emptyList:()Ljava/util/List;
      66: putfield      #54                 // Field valueParameter_:Ljava/util/List;
      69: aload_0
      70: invokestatic  #113                // Method kotlin/reflect/jvm/internal/impl/metadata/ProtoBuf$TypeTable.getDefaultInstance:()Lkotlin/reflect/jvm/internal/impl/metadata/ProtoBuf$TypeTable;
      73: putfield      #52                 // Field typeTable_:Lkotlin/reflect/jvm/internal/impl/metadata/ProtoBuf$TypeTable;
      76: aload_0
      77: invokestatic  #65                 // Method java/util/Collections.emptyList:()Ljava/util/List;
      80: putfield      #55                 // Field versionRequirement_:Ljava/util/List;
      83: aload_0
      84: invokestatic  #67                 // Method kotlin/reflect/jvm/internal/impl/metadata/ProtoBuf$Contract.getDefaultInstance:()Lkotlin/reflect/jvm/internal/impl/metadata/ProtoBuf$Contract;
      87: putfield      #40                 // Field contract_:Lkotlin/reflect/jvm/internal/impl/metadata/ProtoBuf$Contract;
      90: return

  public final boolean isInitialized();
    Code:
       0: aload_0
       1: getfield      #43                 // Field memoizedIsInitialized:B
       4: istore_1
       5: iload_1
       6: iconst_1
       7: if_icmpne     12
      10: iconst_1
      11: ireturn
      12: iload_1
      13: ifne          18
      16: iconst_0
      17: ireturn
      18: aload_0
      19: invokevirtual #92                 // Method hasName:()Z
      22: ifne          32
      25: aload_0
      26: iconst_0
      27: putfield      #43                 // Field memoizedIsInitialized:B
      30: iconst_0
      31: ireturn
      32: aload_0
      33: invokevirtual #94                 // Method hasReturnType:()Z
      36: ifeq          56
      39: aload_0
      40: invokevirtual #83                 // Method getReturnType:()Lkotlin/reflect/jvm/internal/impl/metadata/ProtoBuf$Type;
      43: invokevirtual #108                // Method kotlin/reflect/jvm/internal/impl/metadata/ProtoBuf$Type.isInitialized:()Z
      46: ifne          56
      49: aload_0
      50: iconst_0
      51: putfield      #43                 // Field memoizedIsInitialized:B
      54: iconst_0
      55: ireturn
      56: iconst_0
      57: istore_2
      58: iload_2
      59: aload_0
      60: invokevirtual #86                 // Method getTypeParameterCount:()I
      63: if_icmpge     90
      66: aload_0
      67: iload_2
      68: invokevirtual #85                 // Method getTypeParameter:(I)Lkotlin/reflect/jvm/internal/impl/metadata/ProtoBuf$TypeParameter;
      71: invokevirtual #112                // Method kotlin/reflect/jvm/internal/impl/metadata/ProtoBuf$TypeParameter.isInitialized:()Z
      74: ifne          84
      77: aload_0
      78: iconst_0
      79: putfield      #43                 // Field memoizedIsInitialized:B
      82: iconst_0
      83: ireturn
      84: iinc          2, 1
      87: goto          58
      90: aload_0
      91: invokevirtual #93                 // Method hasReceiverType:()Z
      94: ifeq          114
      97: aload_0
      98: invokevirtual #82                 // Method getReceiverType:()Lkotlin/reflect/jvm/internal/impl/metadata/ProtoBuf$Type;
     101: invokevirtual #108                // Method kotlin/reflect/jvm/internal/impl/metadata/ProtoBuf$Type.isInitialized:()Z
     104: ifne          114
     107: aload_0
     108: iconst_0
     109: putfield      #43                 // Field memoizedIsInitialized:B
     112: iconst_0
     113: ireturn
     114: iconst_0
     115: istore_2
     116: iload_2
     117: aload_0
     118: invokevirtual #78                 // Method getContextReceiverTypeCount:()I
     121: if_icmpge     148
     124: aload_0
     125: iload_2
     126: invokevirtual #77                 // Method getContextReceiverType:(I)Lkotlin/reflect/jvm/internal/impl/metadata/ProtoBuf$Type;
     129: invokevirtual #108                // Method kotlin/reflect/jvm/internal/impl/metadata/ProtoBuf$Type.isInitialized:()Z
     132: ifne          142
     135: aload_0
     136: iconst_0
     137: putfield      #43                 // Field memoizedIsInitialized:B
     140: iconst_0
     141: ireturn
     142: iinc          2, 1
     145: goto          116
     148: iconst_0
     149: istore_2
     150: iload_2
     151: aload_0
     152: invokevirtual #89                 // Method getValueParameterCount:()I
     155: if_icmpge     182
     158: aload_0
     159: iload_2
     160: invokevirtual #88                 // Method getValueParameter:(I)Lkotlin/reflect/jvm/internal/impl/metadata/ProtoBuf$ValueParameter;
     163: invokevirtual #118                // Method kotlin/reflect/jvm/internal/impl/metadata/ProtoBuf$ValueParameter.isInitialized:()Z
     166: ifne          176
     169: aload_0
     170: iconst_0
     171: putfield      #43                 // Field memoizedIsInitialized:B
     174: iconst_0
     175: ireturn
     176: iinc          2, 1
     179: goto          150
     182: aload_0
     183: invokevirtual #95                 // Method hasTypeTable:()Z
     186: ifeq          206
     189: aload_0
     190: invokevirtual #87                 // Method getTypeTable:()Lkotlin/reflect/jvm/internal/impl/metadata/ProtoBuf$TypeTable;
     193: invokevirtual #114                // Method kotlin/reflect/jvm/internal/impl/metadata/ProtoBuf$TypeTable.isInitialized:()Z
     196: ifne          206
     199: aload_0
     200: iconst_0
     201: putfield      #43                 // Field memoizedIsInitialized:B
     204: iconst_0
     205: ireturn
     206: aload_0
     207: invokevirtual #91                 // Method hasContract:()Z
     210: ifeq          230
     213: aload_0
     214: invokevirtual #80                 // Method getContract:()Lkotlin/reflect/jvm/internal/impl/metadata/ProtoBuf$Contract;
     217: invokevirtual #68                 // Method kotlin/reflect/jvm/internal/impl/metadata/ProtoBuf$Contract.isInitialized:()Z
     220: ifne          230
     223: aload_0
     224: iconst_0
     225: putfield      #43                 // Field memoizedIsInitialized:B
     228: iconst_0
     229: ireturn
     230: aload_0
     231: invokevirtual #75                 // Method extensionsAreInitialized:()Z
     234: ifne          244
     237: aload_0
     238: iconst_0
     239: putfield      #43                 // Field memoizedIsInitialized:B
     242: iconst_0
     243: ireturn
     244: aload_0
     245: iconst_1
     246: putfield      #43                 // Field memoizedIsInitialized:B
     249: iconst_1
     250: ireturn

  public void writeTo(kotlin.reflect.jvm.internal.impl.protobuf.CodedOutputStream) throws java.io.IOException;
    Code:
       0: aload_0
       1: invokevirtual #84                 // Method getSerializedSize:()I
       4: pop
       5: aload_0
       6: invokevirtual #101                // Method newExtensionWriter:()Lkotlin/reflect/jvm/internal/impl/protobuf/GeneratedMessageLite$ExtendableMessage$ExtensionWriter;
       9: astore_2
      10: aload_0
      11: getfield      #36                 // Field bitField0_:I
      14: iconst_2
      15: iand
      16: iconst_2
      17: if_icmpne     29
      20: aload_1
      21: iconst_1
      22: aload_0
      23: getfield      #46                 // Field oldFlags_:I
      26: invokevirtual #134                // Method kotlin/reflect/jvm/internal/impl/protobuf/CodedOutputStream.writeInt32:(II)V
      29: aload_0
      30: getfield      #36                 // Field bitField0_:I
      33: iconst_4
      34: iand
      35: iconst_4
      36: if_icmpne     48
      39: aload_1
      40: iconst_2
      41: aload_0
      42: getfield      #45                 // Field name_:I
      45: invokevirtual #134                // Method kotlin/reflect/jvm/internal/impl/protobuf/CodedOutputStream.writeInt32:(II)V
      48: aload_0
      49: getfield      #36                 // Field bitField0_:I
      52: bipush        8
      54: iand
      55: bipush        8
      57: if_icmpne     69
      60: aload_1
      61: iconst_3
      62: aload_0
      63: getfield      #50                 // Field returnType_:Lkotlin/reflect/jvm/internal/impl/metadata/ProtoBuf$Type;
      66: invokevirtual #136                // Method kotlin/reflect/jvm/internal/impl/protobuf/CodedOutputStream.writeMessage:(ILkotlin/reflect/jvm/internal/impl/protobuf/MessageLite;)V
      69: iconst_0
      70: istore_3
      71: iload_3
      72: aload_0
      73: getfield      #51                 // Field typeParameter_:Ljava/util/List;
      76: invokeinterface #148,  1          // InterfaceMethod java/util/List.size:()I
      81: if_icmpge     108
      84: aload_1
      85: iconst_4
      86: aload_0
      87: getfield      #51                 // Field typeParameter_:Ljava/util/List;
      90: iload_3
      91: invokeinterface #146,  2          // InterfaceMethod java/util/List.get:(I)Ljava/lang/Object;
      96: checkcast     #31                 // class kotlin/reflect/jvm/internal/impl/protobuf/MessageLite
      99: invokevirtual #136                // Method kotlin/reflect/jvm/internal/impl/protobuf/CodedOutputStream.writeMessage:(ILkotlin/reflect/jvm/internal/impl/protobuf/MessageLite;)V
     102: iinc          3, 1
     105: goto          71
     108: aload_0
     109: getfield      #36                 // Field bitField0_:I
     112: bipush        32
     114: iand
     115: bipush        32
     117: if_icmpne     129
     120: aload_1
     121: iconst_5
     122: aload_0
     123: getfield      #48                 // Field receiverType_:Lkotlin/reflect/jvm/internal/impl/metadata/ProtoBuf$Type;
     126: invokevirtual #136                // Method kotlin/reflect/jvm/internal/impl/protobuf/CodedOutputStream.writeMessage:(ILkotlin/reflect/jvm/internal/impl/protobuf/MessageLite;)V
     129: iconst_0
     130: istore_3
     131: iload_3
     132: aload_0
     133: getfield      #54                 // Field valueParameter_:Ljava/util/List;
     136: invokeinterface #148,  1          // InterfaceMethod java/util/List.size:()I
     141: if_icmpge     169
     144: aload_1
     145: bipush        6
     147: aload_0
     148: getfield      #54                 // Field valueParameter_:Ljava/util/List;
     151: iload_3
     152: invokeinterface #146,  2          // InterfaceMethod java/util/List.get:(I)Ljava/lang/Object;
     157: checkcast     #31                 // class kotlin/reflect/jvm/internal/impl/protobuf/MessageLite
     160: invokevirtual #136                // Method kotlin/reflect/jvm/internal/impl/protobuf/CodedOutputStream.writeMessage:(ILkotlin/reflect/jvm/internal/impl/protobuf/MessageLite;)V
     163: iinc          3, 1
     166: goto          131
     169: aload_0
     170: getfield      #36                 // Field bitField0_:I
     173: bipush        16
     175: iand
     176: bipush        16
     178: if_icmpne     191
     181: aload_1
     182: bipush        7
     184: aload_0
     185: getfield      #49                 // Field returnTypeId_:I
     188: invokevirtual #134                // Method kotlin/reflect/jvm/internal/impl/protobuf/CodedOutputStream.writeInt32:(II)V
     191: aload_0
     192: getfield      #36                 // Field bitField0_:I
     195: bipush        64
     197: iand
     198: bipush        64
     200: if_icmpne     213
     203: aload_1
     204: bipush        8
     206: aload_0
     207: getfield      #47                 // Field receiverTypeId_:I
     210: invokevirtual #134                // Method kotlin/reflect/jvm/internal/impl/protobuf/CodedOutputStream.writeInt32:(II)V
     213: aload_0
     214: getfield      #36                 // Field bitField0_:I
     217: iconst_1
     218: iand
     219: iconst_1
     220: if_icmpne     233
     223: aload_1
     224: bipush        9
     226: aload_0
     227: getfield      #42                 // Field flags_:I
     230: invokevirtual #134                // Method kotlin/reflect/jvm/internal/impl/protobuf/CodedOutputStream.writeInt32:(II)V
     233: iconst_0
     234: istore_3
     235: iload_3
     236: aload_0
     237: getfield      #39                 // Field contextReceiverType_:Ljava/util/List;
     240: invokeinterface #148,  1          // InterfaceMethod java/util/List.size:()I
     245: if_icmpge     273
     248: aload_1
     249: bipush        10
     251: aload_0
     252: getfield      #39                 // Field contextReceiverType_:Ljava/util/List;
     255: iload_3
     256: invokeinterface #146,  2          // InterfaceMethod java/util/List.get:(I)Ljava/lang/Object;
     261: checkcast     #31                 // class kotlin/reflect/jvm/internal/impl/protobuf/MessageLite
     264: invokevirtual #136                // Method kotlin/reflect/jvm/internal/impl/protobuf/CodedOutputStream.writeMessage:(ILkotlin/reflect/jvm/internal/impl/protobuf/MessageLite;)V
     267: iinc          3, 1
     270: goto          235
     273: aload_0
     274: invokevirtual #79                 // Method getContextReceiverTypeIdList:()Ljava/util/List;
     277: invokeinterface #148,  1          // InterfaceMethod java/util/List.size:()I
     282: ifle          299
     285: aload_1
     286: bipush        90
     288: invokevirtual #138                // Method kotlin/reflect/jvm/internal/impl/protobuf/CodedOutputStream.writeRawVarint32:(I)V
     291: aload_1
     292: aload_0
     293: getfield      #37                 // Field contextReceiverTypeIdMemoizedSerializedSize:I
     296: invokevirtual #138                // Method kotlin/reflect/jvm/internal/impl/protobuf/CodedOutputStream.writeRawVarint32:(I)V
     299: iconst_0
     300: istore_3
     301: iload_3
     302: aload_0
     303: getfield      #38                 // Field contextReceiverTypeId_:Ljava/util/List;
     306: invokeinterface #148,  1          // InterfaceMethod java/util/List.size:()I
     311: if_icmpge     340
     314: aload_1
     315: aload_0
     316: getfield      #38                 // Field contextReceiverTypeId_:Ljava/util/List;
     319: iload_3
     320: invokeinterface #146,  2          // InterfaceMethod java/util/List.get:(I)Ljava/lang/Object;
     325: checkcast     #2                  // class java/lang/Integer
     328: invokevirtual #62                 // Method java/lang/Integer.intValue:()I
     331: invokevirtual #135                // Method kotlin/reflect/jvm/internal/impl/protobuf/CodedOutputStream.writeInt32NoTag:(I)V
     334: iinc          3, 1
     337: goto          301
     340: aload_0
     341: getfield      #36                 // Field bitField0_:I
     344: sipush        128
     347: iand
     348: sipush        128
     351: if_icmpne     364
     354: aload_1
     355: bipush        30
     357: aload_0
     358: getfield      #52                 // Field typeTable_:Lkotlin/reflect/jvm/internal/impl/metadata/ProtoBuf$TypeTable;
     361: invokevirtual #136                // Method kotlin/reflect/jvm/internal/impl/protobuf/CodedOutputStream.writeMessage:(ILkotlin/reflect/jvm/internal/impl/protobuf/MessageLite;)V
     364: iconst_0
     365: istore_3
     366: iload_3
     367: aload_0
     368: getfield      #55                 // Field versionRequirement_:Ljava/util/List;
     371: invokeinterface #148,  1          // InterfaceMethod java/util/List.size:()I
     376: if_icmpge     407
     379: aload_1
     380: bipush        31
     382: aload_0
     383: getfield      #55                 // Field versionRequirement_:Ljava/util/List;
     386: iload_3
     387: invokeinterface #146,  2          // InterfaceMethod java/util/List.get:(I)Ljava/lang/Object;
     392: checkcast     #2                  // class java/lang/Integer
     395: invokevirtual #62                 // Method java/lang/Integer.intValue:()I
     398: invokevirtual #134                // Method kotlin/reflect/jvm/internal/impl/protobuf/CodedOutputStream.writeInt32:(II)V
     401: iinc          3, 1
     404: goto          366
     407: aload_0
     408: getfield      #36                 // Field bitField0_:I
     411: sipush        256
     414: iand
     415: sipush        256
     418: if_icmpne     431
     421: aload_1
     422: bipush        32
     424: aload_0
     425: getfield      #40                 // Field contract_:Lkotlin/reflect/jvm/internal/impl/metadata/ProtoBuf$Contract;
     428: invokevirtual #136                // Method kotlin/reflect/jvm/internal/impl/protobuf/CodedOutputStream.writeMessage:(ILkotlin/reflect/jvm/internal/impl/protobuf/MessageLite;)V
     431: aload_2
     432: sipush        19000
     435: aload_1
     436: invokevirtual #142                // Method kotlin/reflect/jvm/internal/impl/protobuf/GeneratedMessageLite$ExtendableMessage$ExtensionWriter.writeUntil:(ILkotlin/reflect/jvm/internal/impl/protobuf/CodedOutputStream;)V
     439: aload_1
     440: aload_0
     441: getfield      #53                 // Field unknownFields:Lkotlin/reflect/jvm/internal/impl/protobuf/ByteString;
     444: invokevirtual #137                // Method kotlin/reflect/jvm/internal/impl/protobuf/CodedOutputStream.writeRawBytes:(Lkotlin/reflect/jvm/internal/impl/protobuf/ByteString;)V
     447: return

  public int getSerializedSize();
    Code:
       0: aload_0
       1: getfield      #44                 // Field memoizedSerializedSize:I
       4: istore_1
       5: iload_1
       6: iconst_m1
       7: if_icmpeq     12
      10: iload_1
      11: ireturn
      12: iconst_0
      13: istore_1
      14: aload_0
      15: getfield      #36                 // Field bitField0_:I
      18: iconst_2
      19: iand
      20: iconst_2
      21: if_icmpne     35
      24: iload_1
      25: iconst_1
      26: aload_0
      27: getfield      #46                 // Field oldFlags_:I
      30: invokestatic  #129                // Method kotlin/reflect/jvm/internal/impl/protobuf/CodedOutputStream.computeInt32Size:(II)I
      33: iadd
      34: istore_1
      35: aload_0
      36: getfield      #36                 // Field bitField0_:I
      39: iconst_4
      40: iand
      41: iconst_4
      42: if_icmpne     56
      45: iload_1
      46: iconst_2
      47: aload_0
      48: getfield      #45                 // Field name_:I
      51: invokestatic  #129                // Method kotlin/reflect/jvm/internal/impl/protobuf/CodedOutputStream.computeInt32Size:(II)I
      54: iadd
      55: istore_1
      56: aload_0
      57: getfield      #36                 // Field bitField0_:I
      60: bipush        8
      62: iand
      63: bipush        8
      65: if_icmpne     79
      68: iload_1
      69: iconst_3
      70: aload_0
      71: getfield      #50                 // Field returnType_:Lkotlin/reflect/jvm/internal/impl/metadata/ProtoBuf$Type;
      74: invokestatic  #131                // Method kotlin/reflect/jvm/internal/impl/protobuf/CodedOutputStream.computeMessageSize:(ILkotlin/reflect/jvm/internal/impl/protobuf/MessageLite;)I
      77: iadd
      78: istore_1
      79: iconst_0
      80: istore_2
      81: iload_2
      82: aload_0
      83: getfield      #51                 // Field typeParameter_:Ljava/util/List;
      86: invokeinterface #148,  1          // InterfaceMethod java/util/List.size:()I
      91: if_icmpge     120
      94: iload_1
      95: iconst_4
      96: aload_0
      97: getfield      #51                 // Field typeParameter_:Ljava/util/List;
     100: iload_2
     101: invokeinterface #146,  2          // InterfaceMethod java/util/List.get:(I)Ljava/lang/Object;
     106: checkcast     #31                 // class kotlin/reflect/jvm/internal/impl/protobuf/MessageLite
     109: invokestatic  #131                // Method kotlin/reflect/jvm/internal/impl/protobuf/CodedOutputStream.computeMessageSize:(ILkotlin/reflect/jvm/internal/impl/protobuf/MessageLite;)I
     112: iadd
     113: istore_1
     114: iinc          2, 1
     117: goto          81
     120: aload_0
     121: getfield      #36                 // Field bitField0_:I
     124: bipush        32
     126: iand
     127: bipush        32
     129: if_icmpne     143
     132: iload_1
     133: iconst_5
     134: aload_0
     135: getfield      #48                 // Field receiverType_:Lkotlin/reflect/jvm/internal/impl/metadata/ProtoBuf$Type;
     138: invokestatic  #131                // Method kotlin/reflect/jvm/internal/impl/protobuf/CodedOutputStream.computeMessageSize:(ILkotlin/reflect/jvm/internal/impl/protobuf/MessageLite;)I
     141: iadd
     142: istore_1
     143: iconst_0
     144: istore_2
     145: iload_2
     146: aload_0
     147: getfield      #54                 // Field valueParameter_:Ljava/util/List;
     150: invokeinterface #148,  1          // InterfaceMethod java/util/List.size:()I
     155: if_icmpge     185
     158: iload_1
     159: bipush        6
     161: aload_0
     162: getfield      #54                 // Field valueParameter_:Ljava/util/List;
     165: iload_2
     166: invokeinterface #146,  2          // InterfaceMethod java/util/List.get:(I)Ljava/lang/Object;
     171: checkcast     #31                 // class kotlin/reflect/jvm/internal/impl/protobuf/MessageLite
     174: invokestatic  #131                // Method kotlin/reflect/jvm/internal/impl/protobuf/CodedOutputStream.computeMessageSize:(ILkotlin/reflect/jvm/internal/impl/protobuf/MessageLite;)I
     177: iadd
     178: istore_1
     179: iinc          2, 1
     182: goto          145
     185: aload_0
     186: getfield      #36                 // Field bitField0_:I
     189: bipush        16
     191: iand
     192: bipush        16
     194: if_icmpne     209
     197: iload_1
     198: bipush        7
     200: aload_0
     201: getfield      #49                 // Field returnTypeId_:I
     204: invokestatic  #129                // Method kotlin/reflect/jvm/internal/impl/protobuf/CodedOutputStream.computeInt32Size:(II)I
     207: iadd
     208: istore_1
     209: aload_0
     210: getfield      #36                 // Field bitField0_:I
     213: bipush        64
     215: iand
     216: bipush        64
     218: if_icmpne     233
     221: iload_1
     222: bipush        8
     224: aload_0
     225: getfield      #47                 // Field receiverTypeId_:I
     228: invokestatic  #129                // Method kotlin/reflect/jvm/internal/impl/protobuf/CodedOutputStream.computeInt32Size:(II)I
     231: iadd
     232: istore_1
     233: aload_0
     234: getfield      #36                 // Field bitField0_:I
     237: iconst_1
     238: iand
     239: iconst_1
     240: if_icmpne     255
     243: iload_1
     244: bipush        9
     246: aload_0
     247: getfield      #42                 // Field flags_:I
     250: invokestatic  #129                // Method kotlin/reflect/jvm/internal/impl/protobuf/CodedOutputStream.computeInt32Size:(II)I
     253: iadd
     254: istore_1
     255: iconst_0
     256: istore_2
     257: iload_2
     258: aload_0
     259: getfield      #39                 // Field contextReceiverType_:Ljava/util/List;
     262: invokeinterface #148,  1          // InterfaceMethod java/util/List.size:()I
     267: if_icmpge     297
     270: iload_1
     271: bipush        10
     273: aload_0
     274: getfield      #39                 // Field contextReceiverType_:Ljava/util/List;
     277: iload_2
     278: invokeinterface #146,  2          // InterfaceMethod java/util/List.get:(I)Ljava/lang/Object;
     283: checkcast     #31                 // class kotlin/reflect/jvm/internal/impl/protobuf/MessageLite
     286: invokestatic  #131                // Method kotlin/reflect/jvm/internal/impl/protobuf/CodedOutputStream.computeMessageSize:(ILkotlin/reflect/jvm/internal/impl/protobuf/MessageLite;)I
     289: iadd
     290: istore_1
     291: iinc          2, 1
     294: goto          257
     297: iconst_0
     298: istore_2
     299: iconst_0
     300: istore_3
     301: iload_3
     302: aload_0
     303: getfield      #38                 // Field contextReceiverTypeId_:Ljava/util/List;
     306: invokeinterface #148,  1          // InterfaceMethod java/util/List.size:()I
     311: if_icmpge     342
     314: iload_2
     315: aload_0
     316: getfield      #38                 // Field contextReceiverTypeId_:Ljava/util/List;
     319: iload_3
     320: invokeinterface #146,  2          // InterfaceMethod java/util/List.get:(I)Ljava/lang/Object;
     325: checkcast     #2                  // class java/lang/Integer
     328: invokevirtual #62                 // Method java/lang/Integer.intValue:()I
     331: invokestatic  #130                // Method kotlin/reflect/jvm/internal/impl/protobuf/CodedOutputStream.computeInt32SizeNoTag:(I)I
     334: iadd
     335: istore_2
     336: iinc          3, 1
     339: goto          301
     342: iload_1
     343: iload_2
     344: iadd
     345: istore_1
     346: aload_0
     347: invokevirtual #79                 // Method getContextReceiverTypeIdList:()Ljava/util/List;
     350: invokeinterface #147,  1          // InterfaceMethod java/util/List.isEmpty:()Z
     355: ifne          368
     358: iinc          1, 1
     361: iload_1
     362: iload_2
     363: invokestatic  #130                // Method kotlin/reflect/jvm/internal/impl/protobuf/CodedOutputStream.computeInt32SizeNoTag:(I)I
     366: iadd
     367: istore_1
     368: aload_0
     369: iload_2
     370: putfield      #37                 // Field contextReceiverTypeIdMemoizedSerializedSize:I
     373: aload_0
     374: getfield      #36                 // Field bitField0_:I
     377: sipush        128
     380: iand
     381: sipush        128
     384: if_icmpne     399
     387: iload_1
     388: bipush        30
     390: aload_0
     391: getfield      #52                 // Field typeTable_:Lkotlin/reflect/jvm/internal/impl/metadata/ProtoBuf$TypeTable;
     394: invokestatic  #131                // Method kotlin/reflect/jvm/internal/impl/protobuf/CodedOutputStream.computeMessageSize:(ILkotlin/reflect/jvm/internal/impl/protobuf/MessageLite;)I
     397: iadd
     398: istore_1
     399: iconst_0
     400: istore_2
     401: iconst_0
     402: istore_3
     403: iload_3
     404: aload_0
     405: getfield      #55                 // Field versionRequirement_:Ljava/util/List;
     408: invokeinterface #148,  1          // InterfaceMethod java/util/List.size:()I
     413: if_icmpge     444
     416: iload_2
     417: aload_0
     418: getfield      #55                 // Field versionRequirement_:Ljava/util/List;
     421: iload_3
     422: invokeinterface #146,  2          // InterfaceMethod java/util/List.get:(I)Ljava/lang/Object;
     427: checkcast     #2                  // class java/lang/Integer
     430: invokevirtual #62                 // Method java/lang/Integer.intValue:()I
     433: invokestatic  #130                // Method kotlin/reflect/jvm/internal/impl/protobuf/CodedOutputStream.computeInt32SizeNoTag:(I)I
     436: iadd
     437: istore_2
     438: iinc          3, 1
     441: goto          403
     444: iload_1
     445: iload_2
     446: iadd
     447: istore_1
     448: iload_1
     449: iconst_2
     450: aload_0
     451: invokevirtual #90                 // Method getVersionRequirementList:()Ljava/util/List;
     454: invokeinterface #148,  1          // InterfaceMethod java/util/List.size:()I
     459: imul
     460: iadd
     461: istore_1
     462: aload_0
     463: getfield      #36                 // Field bitField0_:I
     466: sipush        256
     469: iand
     470: sipush        256
     473: if_icmpne     488
     476: iload_1
     477: bipush        32
     479: aload_0
     480: getfield      #40                 // Field contract_:Lkotlin/reflect/jvm/internal/impl/metadata/ProtoBuf$Contract;
     483: invokestatic  #131                // Method kotlin/reflect/jvm/internal/impl/protobuf/CodedOutputStream.computeMessageSize:(ILkotlin/reflect/jvm/internal/impl/protobuf/MessageLite;)I
     486: iadd
     487: istore_1
     488: iload_1
     489: aload_0
     490: invokevirtual #76                 // Method extensionsSerializedSize:()I
     493: iadd
     494: istore_1
     495: iload_1
     496: aload_0
     497: getfield      #53                 // Field unknownFields:Lkotlin/reflect/jvm/internal/impl/protobuf/ByteString;
     500: invokevirtual #120                // Method kotlin/reflect/jvm/internal/impl/protobuf/ByteString.size:()I
     503: iadd
     504: istore_1
     505: aload_0
     506: iload_1
     507: putfield      #44                 // Field memoizedSerializedSize:I
     510: iload_1
     511: ireturn

  public static kotlin.reflect.jvm.internal.impl.metadata.ProtoBuf$Function parseFrom(java.io.InputStream, kotlin.reflect.jvm.internal.impl.protobuf.ExtensionRegistryLite) throws java.io.IOException;
    Code:
       0: getstatic     #35                 // Field PARSER:Lkotlin/reflect/jvm/internal/impl/protobuf/Parser;
       3: aload_0
       4: aload_1
       5: invokeinterface #149,  3          // InterfaceMethod kotlin/reflect/jvm/internal/impl/protobuf/Parser.parseFrom:(Ljava/io/InputStream;Lkotlin/reflect/jvm/internal/impl/protobuf/ExtensionRegistryLite;)Ljava/lang/Object;
      10: checkcast     #11                 // class kotlin/reflect/jvm/internal/impl/metadata/ProtoBuf$Function
      13: areturn

  public static kotlin.reflect.jvm.internal.impl.metadata.ProtoBuf$Function$Builder newBuilder();
    Code:
       0: invokestatic  #105                // Method kotlin/reflect/jvm/internal/impl/metadata/ProtoBuf$Function$Builder.access$14100:()Lkotlin/reflect/jvm/internal/impl/metadata/ProtoBuf$Function$Builder;
       3: areturn

  public kotlin.reflect.jvm.internal.impl.metadata.ProtoBuf$Function$Builder newBuilderForType();
    Code:
       0: invokestatic  #98                 // Method newBuilder:()Lkotlin/reflect/jvm/internal/impl/metadata/ProtoBuf$Function$Builder;
       3: areturn

  public static kotlin.reflect.jvm.internal.impl.metadata.ProtoBuf$Function$Builder newBuilder(kotlin.reflect.jvm.internal.impl.metadata.ProtoBuf$Function);
    Code:
       0: invokestatic  #98                 // Method newBuilder:()Lkotlin/reflect/jvm/internal/impl/metadata/ProtoBuf$Function$Builder;
       3: aload_0
       4: invokevirtual #106                // Method kotlin/reflect/jvm/internal/impl/metadata/ProtoBuf$Function$Builder.mergeFrom:(Lkotlin/reflect/jvm/internal/impl/metadata/ProtoBuf$Function;)Lkotlin/reflect/jvm/internal/impl/metadata/ProtoBuf$Function$Builder;
       7: areturn

  public kotlin.reflect.jvm.internal.impl.metadata.ProtoBuf$Function$Builder toBuilder();
    Code:
       0: aload_0
       1: invokestatic  #99                 // Method newBuilder:(Lkotlin/reflect/jvm/internal/impl/metadata/ProtoBuf$Function;)Lkotlin/reflect/jvm/internal/impl/metadata/ProtoBuf$Function$Builder;
       4: areturn

  public kotlin.reflect.jvm.internal.impl.protobuf.MessageLite getDefaultInstanceForType();
    Code:
       0: aload_0
       1: invokevirtual #81                 // Method getDefaultInstanceForType:()Lkotlin/reflect/jvm/internal/impl/metadata/ProtoBuf$Function;
       4: areturn

  public kotlin.reflect.jvm.internal.impl.protobuf.MessageLite$Builder toBuilder();
    Code:
       0: aload_0
       1: invokevirtual #103                // Method toBuilder:()Lkotlin/reflect/jvm/internal/impl/metadata/ProtoBuf$Function$Builder;
       4: areturn

  public kotlin.reflect.jvm.internal.impl.protobuf.MessageLite$Builder newBuilderForType();
    Code:
       0: aload_0
       1: invokevirtual #100                // Method newBuilderForType:()Lkotlin/reflect/jvm/internal/impl/metadata/ProtoBuf$Function$Builder;
       4: areturn

  kotlin.reflect.jvm.internal.impl.metadata.ProtoBuf$Function(kotlin.reflect.jvm.internal.impl.protobuf.CodedInputStream, kotlin.reflect.jvm.internal.impl.protobuf.ExtensionRegistryLite, kotlin.reflect.jvm.internal.impl.metadata.ProtoBuf$1) throws kotlin.reflect.jvm.internal.impl.protobuf.InvalidProtocolBufferException;
    Code:
       0: aload_0
       1: aload_1
       2: aload_2
       3: invokespecial #72                 // Method "<init>":(Lkotlin/reflect/jvm/internal/impl/protobuf/CodedInputStream;Lkotlin/reflect/jvm/internal/impl/protobuf/ExtensionRegistryLite;)V
       6: return

  kotlin.reflect.jvm.internal.impl.metadata.ProtoBuf$Function(kotlin.reflect.jvm.internal.impl.protobuf.GeneratedMessageLite$ExtendableBuilder, kotlin.reflect.jvm.internal.impl.metadata.ProtoBuf$1);
    Code:
       0: aload_0
       1: aload_1
       2: invokespecial #73                 // Method "<init>":(Lkotlin/reflect/jvm/internal/impl/protobuf/GeneratedMessageLite$ExtendableBuilder;)V
       5: return

  static int access$14302(kotlin.reflect.jvm.internal.impl.metadata.ProtoBuf$Function, int);
    Code:
       0: aload_0
       1: iload_1
       2: dup_x1
       3: putfield      #42                 // Field flags_:I
       6: ireturn

  static int access$14402(kotlin.reflect.jvm.internal.impl.metadata.ProtoBuf$Function, int);
    Code:
       0: aload_0
       1: iload_1
       2: dup_x1
       3: putfield      #46                 // Field oldFlags_:I
       6: ireturn

  static int access$14502(kotlin.reflect.jvm.internal.impl.metadata.ProtoBuf$Function, int);
    Code:
       0: aload_0
       1: iload_1
       2: dup_x1
       3: putfield      #45                 // Field name_:I
       6: ireturn

  static kotlin.reflect.jvm.internal.impl.metadata.ProtoBuf$Type access$14602(kotlin.reflect.jvm.internal.impl.metadata.ProtoBuf$Function, kotlin.reflect.jvm.internal.impl.metadata.ProtoBuf$Type);
    Code:
       0: aload_0
       1: aload_1
       2: dup_x1
       3: putfield      #50                 // Field returnType_:Lkotlin/reflect/jvm/internal/impl/metadata/ProtoBuf$Type;
       6: areturn

  static int access$14702(kotlin.reflect.jvm.internal.impl.metadata.ProtoBuf$Function, int);
    Code:
       0: aload_0
       1: iload_1
       2: dup_x1
       3: putfield      #49                 // Field returnTypeId_:I
       6: ireturn

  static java.util.List access$14802(kotlin.reflect.jvm.internal.impl.metadata.ProtoBuf$Function, java.util.List);
    Code:
       0: aload_0
       1: aload_1
       2: dup_x1
       3: putfield      #51                 // Field typeParameter_:Ljava/util/List;
       6: areturn

  static kotlin.reflect.jvm.internal.impl.metadata.ProtoBuf$Type access$14902(kotlin.reflect.jvm.internal.impl.metadata.ProtoBuf$Function, kotlin.reflect.jvm.internal.impl.metadata.ProtoBuf$Type);
    Code:
       0: aload_0
       1: aload_1
       2: dup_x1
       3: putfield      #48                 // Field receiverType_:Lkotlin/reflect/jvm/internal/impl/metadata/ProtoBuf$Type;
       6: areturn

  static int access$15002(kotlin.reflect.jvm.internal.impl.metadata.ProtoBuf$Function, int);
    Code:
       0: aload_0
       1: iload_1
       2: dup_x1
       3: putfield      #47                 // Field receiverTypeId_:I
       6: ireturn

  static java.util.List access$15102(kotlin.reflect.jvm.internal.impl.metadata.ProtoBuf$Function, java.util.List);
    Code:
       0: aload_0
       1: aload_1
       2: dup_x1
       3: putfield      #39                 // Field contextReceiverType_:Ljava/util/List;
       6: areturn

  static java.util.List access$15202(kotlin.reflect.jvm.internal.impl.metadata.ProtoBuf$Function, java.util.List);
    Code:
       0: aload_0
       1: aload_1
       2: dup_x1
       3: putfield      #38                 // Field contextReceiverTypeId_:Ljava/util/List;
       6: areturn

  static java.util.List access$15302(kotlin.reflect.jvm.internal.impl.metadata.ProtoBuf$Function, java.util.List);
    Code:
       0: aload_0
       1: aload_1
       2: dup_x1
       3: putfield      #54                 // Field valueParameter_:Ljava/util/List;
       6: areturn

  static kotlin.reflect.jvm.internal.impl.metadata.ProtoBuf$TypeTable access$15402(kotlin.reflect.jvm.internal.impl.metadata.ProtoBuf$Function, kotlin.reflect.jvm.internal.impl.metadata.ProtoBuf$TypeTable);
    Code:
       0: aload_0
       1: aload_1
       2: dup_x1
       3: putfield      #52                 // Field typeTable_:Lkotlin/reflect/jvm/internal/impl/metadata/ProtoBuf$TypeTable;
       6: areturn

  static java.util.List access$15502(kotlin.reflect.jvm.internal.impl.metadata.ProtoBuf$Function, java.util.List);
    Code:
       0: aload_0
       1: aload_1
       2: dup_x1
       3: putfield      #55                 // Field versionRequirement_:Ljava/util/List;
       6: areturn

  static kotlin.reflect.jvm.internal.impl.metadata.ProtoBuf$Contract access$15602(kotlin.reflect.jvm.internal.impl.metadata.ProtoBuf$Function, kotlin.reflect.jvm.internal.impl.metadata.ProtoBuf$Contract);
    Code:
       0: aload_0
       1: aload_1
       2: dup_x1
       3: putfield      #40                 // Field contract_:Lkotlin/reflect/jvm/internal/impl/metadata/ProtoBuf$Contract;
       6: areturn

  static int access$15702(kotlin.reflect.jvm.internal.impl.metadata.ProtoBuf$Function, int);
    Code:
       0: aload_0
       1: iload_1
       2: dup_x1
       3: putfield      #36                 // Field bitField0_:I
       6: ireturn

  static java.util.List access$14800(kotlin.reflect.jvm.internal.impl.metadata.ProtoBuf$Function);
    Code:
       0: aload_0
       1: getfield      #51                 // Field typeParameter_:Ljava/util/List;
       4: areturn

  static java.util.List access$15100(kotlin.reflect.jvm.internal.impl.metadata.ProtoBuf$Function);
    Code:
       0: aload_0
       1: getfield      #39                 // Field contextReceiverType_:Ljava/util/List;
       4: areturn

  static java.util.List access$15200(kotlin.reflect.jvm.internal.impl.metadata.ProtoBuf$Function);
    Code:
       0: aload_0
       1: getfield      #38                 // Field contextReceiverTypeId_:Ljava/util/List;
       4: areturn

  static java.util.List access$15300(kotlin.reflect.jvm.internal.impl.metadata.ProtoBuf$Function);
    Code:
       0: aload_0
       1: getfield      #54                 // Field valueParameter_:Ljava/util/List;
       4: areturn

  static java.util.List access$15500(kotlin.reflect.jvm.internal.impl.metadata.ProtoBuf$Function);
    Code:
       0: aload_0
       1: getfield      #55                 // Field versionRequirement_:Ljava/util/List;
       4: areturn

  static kotlin.reflect.jvm.internal.impl.protobuf.ByteString access$15800(kotlin.reflect.jvm.internal.impl.metadata.ProtoBuf$Function);
    Code:
       0: aload_0
       1: getfield      #53                 // Field unknownFields:Lkotlin/reflect/jvm/internal/impl/protobuf/ByteString;
       4: areturn

  static {};
    Code:
       0: new           #12                 // class kotlin/reflect/jvm/internal/impl/metadata/ProtoBuf$Function$1
       3: dup
       4: invokespecial #104                // Method kotlin/reflect/jvm/internal/impl/metadata/ProtoBuf$Function$1."<init>":()V
       7: putstatic     #35                 // Field PARSER:Lkotlin/reflect/jvm/internal/impl/protobuf/Parser;
      10: new           #11                 // class kotlin/reflect/jvm/internal/impl/metadata/ProtoBuf$Function
      13: dup
      14: iconst_1
      15: invokespecial #74                 // Method "<init>":(Z)V
      18: putstatic     #41                 // Field defaultInstance:Lkotlin/reflect/jvm/internal/impl/metadata/ProtoBuf$Function;
      21: getstatic     #41                 // Field defaultInstance:Lkotlin/reflect/jvm/internal/impl/metadata/ProtoBuf$Function;
      24: invokespecial #96                 // Method initFields:()V
      27: return
}
