Compiled from "UnresolvableModelException.java"
public class org.apache.maven.model.resolution.UnresolvableModelException extends java.lang.Exception {
  private final java.lang.String groupId;

  private final java.lang.String artifactId;

  private final java.lang.String version;

  public org.apache.maven.model.resolution.UnresolvableModelException(java.lang.String, java.lang.String, java.lang.String, java.lang.String, java.lang.Throwable);
    Code:
       0: aload_0
       1: aload_1
       2: aload         5
       4: invokespecial #1                  // Method java/lang/Exception."<init>":(Ljava/lang/String;Ljava/lang/Throwable;)V
       7: aload_0
       8: aload_2
       9: ifnull        16
      12: aload_2
      13: goto          18
      16: ldc           #2                  // String
      18: putfield      #3                  // Field groupId:Ljava/lang/String;
      21: aload_0
      22: aload_3
      23: ifnull        30
      26: aload_3
      27: goto          32
      30: ldc           #2                  // String
      32: putfield      #4                  // Field artifactId:Ljava/lang/String;
      35: aload_0
      36: aload         4
      38: ifnull        46
      41: aload         4
      43: goto          48
      46: ldc           #2                  // String
      48: putfield      #5                  // Field version:Ljava/lang/String;
      51: return

  public org.apache.maven.model.resolution.UnresolvableModelException(java.lang.String, java.lang.String, java.lang.String, java.lang.String);
    Code:
       0: aload_0
       1: aload_1
       2: invokespecial #6                  // Method java/lang/Exception."<init>":(Ljava/lang/String;)V
       5: aload_0
       6: aload_2
       7: ifnull        14
      10: aload_2
      11: goto          16
      14: ldc           #2                  // String
      16: putfield      #3                  // Field groupId:Ljava/lang/String;
      19: aload_0
      20: aload_3
      21: ifnull        28
      24: aload_3
      25: goto          30
      28: ldc           #2                  // String
      30: putfield      #4                  // Field artifactId:Ljava/lang/String;
      33: aload_0
      34: aload         4
      36: ifnull        44
      39: aload         4
      41: goto          46
      44: ldc           #2                  // String
      46: putfield      #5                  // Field version:Ljava/lang/String;
      49: return

  public java.lang.String getGroupId();
    Code:
       0: aload_0
       1: getfield      #3                  // Field groupId:Ljava/lang/String;
       4: areturn

  public java.lang.String getArtifactId();
    Code:
       0: aload_0
       1: getfield      #4                  // Field artifactId:Ljava/lang/String;
       4: areturn

  public java.lang.String getVersion();
    Code:
       0: aload_0
       1: getfield      #5                  // Field version:Ljava/lang/String;
       4: areturn
}
