Compiled from "ManagedMetric.java"
public class org.springframework.jmx.export.metadata.ManagedMetric extends org.springframework.jmx.export.metadata.AbstractJmxAttribute {
  private java.lang.String category;

  private java.lang.String displayName;

  private org.springframework.jmx.support.MetricType metricType;

  private int persistPeriod;

  private java.lang.String persistPolicy;

  private java.lang.String unit;

  public org.springframework.jmx.export.metadata.ManagedMetric();
    Code:
       0: aload_0
       1: invokespecial #1                  // Method org/springframework/jmx/export/metadata/AbstractJmxAttribute."<init>":()V
       4: aload_0
       5: ldc           #2                  // String
       7: putfield      #3                  // Field category:Ljava/lang/String;
      10: aload_0
      11: ldc           #2                  // String
      13: putfield      #4                  // Field displayName:Ljava/lang/String;
      16: aload_0
      17: getstatic     #5                  // Field org/springframework/jmx/support/MetricType.GAUGE:Lorg/springframework/jmx/support/MetricType;
      20: putfield      #6                  // Field metricType:Lorg/springframework/jmx/support/MetricType;
      23: aload_0
      24: iconst_m1
      25: putfield      #7                  // Field persistPeriod:I
      28: aload_0
      29: ldc           #2                  // String
      31: putfield      #8                  // Field persistPolicy:Ljava/lang/String;
      34: aload_0
      35: ldc           #2                  // String
      37: putfield      #9                  // Field unit:Ljava/lang/String;
      40: return

  public void setCategory(java.lang.String);
    Code:
       0: aload_0
       1: aload_1
       2: putfield      #3                  // Field category:Ljava/lang/String;
       5: return

  public java.lang.String getCategory();
    Code:
       0: aload_0
       1: getfield      #3                  // Field category:Ljava/lang/String;
       4: areturn

  public void setDisplayName(java.lang.String);
    Code:
       0: aload_0
       1: aload_1
       2: putfield      #4                  // Field displayName:Ljava/lang/String;
       5: return

  public java.lang.String getDisplayName();
    Code:
       0: aload_0
       1: getfield      #4                  // Field displayName:Ljava/lang/String;
       4: areturn

  public void setMetricType(org.springframework.jmx.support.MetricType);
    Code:
       0: aload_0
       1: aload_1
       2: putfield      #6                  // Field metricType:Lorg/springframework/jmx/support/MetricType;
       5: return

  public org.springframework.jmx.support.MetricType getMetricType();
    Code:
       0: aload_0
       1: getfield      #6                  // Field metricType:Lorg/springframework/jmx/support/MetricType;
       4: areturn

  public void setPersistPeriod(int);
    Code:
       0: aload_0
       1: iload_1
       2: putfield      #7                  // Field persistPeriod:I
       5: return

  public int getPersistPeriod();
    Code:
       0: aload_0
       1: getfield      #7                  // Field persistPeriod:I
       4: ireturn

  public void setPersistPolicy(java.lang.String);
    Code:
       0: aload_0
       1: aload_1
       2: putfield      #8                  // Field persistPolicy:Ljava/lang/String;
       5: return

  public java.lang.String getPersistPolicy();
    Code:
       0: aload_0
       1: getfield      #8                  // Field persistPolicy:Ljava/lang/String;
       4: areturn

  public void setUnit(java.lang.String);
    Code:
       0: aload_0
       1: aload_1
       2: putfield      #9                  // Field unit:Ljava/lang/String;
       5: return

  public java.lang.String getUnit();
    Code:
       0: aload_0
       1: getfield      #9                  // Field unit:Ljava/lang/String;
       4: areturn
}
