Compiled from "OWLEntityFindPanel.java"
public class org.protege.editor.owl.ui.find.OWLEntityFindPanel extends javax.swing.JPanel {
  private org.protege.editor.owl.OWLEditorKit owlEditorKit;

  private org.protege.editor.owl.ui.view.Findable<?> findable;

  private final javax.swing.JTextField textField;

  private javax.swing.JList<org.semanticweb.owlapi.model.OWLEntity> resultsList;

  javax.swing.Timer findTimer;

  public org.protege.editor.owl.ui.find.OWLEntityFindPanel(org.protege.editor.owl.OWLEditorKit, org.protege.editor.owl.ui.view.Findable<?>);
    Code:
       0: aload_0
       1: invokespecial #4                  // Method javax/swing/JPanel."<init>":()V
       4: aload_0
       5: new           #5                  // class org/protege/editor/core/ui/util/AugmentedJTextField
       8: dup
       9: ldc           #6                  // String Enter search text
      11: invokespecial #7                  // Method org/protege/editor/core/ui/util/AugmentedJTextField."<init>":(Ljava/lang/String;)V
      14: putfield      #8                  // Field textField:Ljavax/swing/JTextField;
      17: aload_0
      18: aload_1
      19: putfield      #9                  // Field owlEditorKit:Lorg/protege/editor/owl/OWLEditorKit;
      22: aload_0
      23: aload_2
      24: putfield      #10                 // Field findable:Lorg/protege/editor/owl/ui/view/Findable;
      27: aload_0
      28: invokespecial #11                 // Method createUI:()V
      31: aload_0
      32: new           #12                 // class javax/swing/Timer
      35: dup
      36: sipush        300
      39: new           #13                 // class org/protege/editor/owl/ui/find/OWLEntityFindPanel$1
      42: dup
      43: aload_0
      44: invokespecial #14                 // Method org/protege/editor/owl/ui/find/OWLEntityFindPanel$1."<init>":(Lorg/protege/editor/owl/ui/find/OWLEntityFindPanel;)V
      47: invokespecial #15                 // Method javax/swing/Timer."<init>":(ILjava/awt/event/ActionListener;)V
      50: putfield      #16                 // Field findTimer:Ljavax/swing/Timer;
      53: aload_0
      54: getfield      #16                 // Field findTimer:Ljavax/swing/Timer;
      57: iconst_0
      58: invokevirtual #17                 // Method javax/swing/Timer.setRepeats:(Z)V
      61: return

  public org.semanticweb.owlapi.model.OWLEntity getSelectedEntity();
    Code:
       0: aload_0
       1: getfield      #18                 // Field resultsList:Ljavax/swing/JList;
       4: invokevirtual #19                 // Method javax/swing/JList.getSelectedValue:()Ljava/lang/Object;
       7: checkcast     #20                 // class org/semanticweb/owlapi/model/OWLEntity
      10: areturn

  private void createUI();
    Code:
       0: aload_0
       1: new           #21                 // class java/awt/BorderLayout
       4: dup
       5: bipush        7
       7: bipush        7
       9: invokespecial #22                 // Method java/awt/BorderLayout."<init>":(II)V
      12: invokevirtual #23                 // Method setLayout:(Ljava/awt/LayoutManager;)V
      15: new           #24                 // class javax/swing/JPanel
      18: dup
      19: new           #21                 // class java/awt/BorderLayout
      22: dup
      23: invokespecial #25                 // Method java/awt/BorderLayout."<init>":()V
      26: invokespecial #26                 // Method javax/swing/JPanel."<init>":(Ljava/awt/LayoutManager;)V
      29: astore_1
      30: aload_1
      31: aload_0
      32: getfield      #8                  // Field textField:Ljavax/swing/JTextField;
      35: invokevirtual #27                 // Method javax/swing/JPanel.add:(Ljava/awt/Component;)Ljava/awt/Component;
      38: pop
      39: aload_0
      40: aload_1
      41: ldc           #28                 // String North
      43: invokevirtual #29                 // Method add:(Ljava/awt/Component;Ljava/lang/Object;)V
      46: aload_0
      47: new           #30                 // class org/protege/editor/owl/ui/list/OWLObjectList
      50: dup
      51: aload_0
      52: getfield      #9                  // Field owlEditorKit:Lorg/protege/editor/owl/OWLEditorKit;
      55: invokespecial #31                 // Method org/protege/editor/owl/ui/list/OWLObjectList."<init>":(Lorg/protege/editor/owl/OWLEditorKit;)V
      58: putfield      #18                 // Field resultsList:Ljavax/swing/JList;
      61: new           #24                 // class javax/swing/JPanel
      64: dup
      65: new           #21                 // class java/awt/BorderLayout
      68: dup
      69: invokespecial #25                 // Method java/awt/BorderLayout."<init>":()V
      72: invokespecial #26                 // Method javax/swing/JPanel."<init>":(Ljava/awt/LayoutManager;)V
      75: astore_2
      76: aload_2
      77: aload_0
      78: getfield      #18                 // Field resultsList:Ljavax/swing/JList;
      81: invokestatic  #32                 // Method org/protege/editor/core/ui/util/ComponentFactory.createScrollPane:(Ljavax/swing/JComponent;)Ljavax/swing/JScrollPane;
      84: invokevirtual #27                 // Method javax/swing/JPanel.add:(Ljava/awt/Component;)Ljava/awt/Component;
      87: pop
      88: aload_0
      89: aload_2
      90: ldc           #33                 // String Center
      92: invokevirtual #29                 // Method add:(Ljava/awt/Component;Ljava/lang/Object;)V
      95: aload_0
      96: getfield      #8                  // Field textField:Ljavax/swing/JTextField;
      99: invokevirtual #34                 // Method javax/swing/JTextField.getDocument:()Ljavax/swing/text/Document;
     102: new           #35                 // class org/protege/editor/owl/ui/find/OWLEntityFindPanel$2
     105: dup
     106: aload_0
     107: invokespecial #36                 // Method org/protege/editor/owl/ui/find/OWLEntityFindPanel$2."<init>":(Lorg/protege/editor/owl/ui/find/OWLEntityFindPanel;)V
     110: invokeinterface #37,  2           // InterfaceMethod javax/swing/text/Document.addDocumentListener:(Ljavax/swing/event/DocumentListener;)V
     115: aload_0
     116: getfield      #8                  // Field textField:Ljavax/swing/JTextField;
     119: new           #38                 // class org/protege/editor/owl/ui/find/OWLEntityFindPanel$3
     122: dup
     123: aload_0
     124: invokespecial #39                 // Method org/protege/editor/owl/ui/find/OWLEntityFindPanel$3."<init>":(Lorg/protege/editor/owl/ui/find/OWLEntityFindPanel;)V
     127: invokevirtual #40                 // Method javax/swing/JTextField.addKeyListener:(Ljava/awt/event/KeyListener;)V
     130: return

  private void handleKeyPressed(java.awt.event.KeyEvent);
    Code:
       0: aload_1
       1: invokevirtual #41                 // Method java/awt/event/KeyEvent.getKeyCode:()I
       4: bipush        38
       6: if_icmpne     16
       9: aload_0
      10: invokespecial #43                 // Method navUp:()V
      13: goto          29
      16: aload_1
      17: invokevirtual #41                 // Method java/awt/event/KeyEvent.getKeyCode:()I
      20: bipush        40
      22: if_icmpne     29
      25: aload_0
      26: invokespecial #44                 // Method navDown:()V
      29: return

  private void navUp();
    Code:
       0: aload_0
       1: getfield      #18                 // Field resultsList:Ljavax/swing/JList;
       4: invokevirtual #45                 // Method javax/swing/JList.getSelectedIndex:()I
       7: istore_1
       8: iload_1
       9: iconst_m1
      10: if_icmpne     14
      13: return
      14: iinc          1, -1
      17: iload_1
      18: ifge          36
      21: aload_0
      22: getfield      #18                 // Field resultsList:Ljavax/swing/JList;
      25: invokevirtual #46                 // Method javax/swing/JList.getModel:()Ljavax/swing/ListModel;
      28: invokeinterface #47,  1           // InterfaceMethod javax/swing/ListModel.getSize:()I
      33: iconst_1
      34: isub
      35: istore_1
      36: aload_0
      37: getfield      #18                 // Field resultsList:Ljavax/swing/JList;
      40: iload_1
      41: invokevirtual #48                 // Method javax/swing/JList.setSelectedIndex:(I)V
      44: return

  private void navDown();
    Code:
       0: aload_0
       1: getfield      #18                 // Field resultsList:Ljavax/swing/JList;
       4: invokevirtual #45                 // Method javax/swing/JList.getSelectedIndex:()I
       7: istore_1
       8: iload_1
       9: iconst_m1
      10: if_icmpne     14
      13: return
      14: iinc          1, 1
      17: iload_1
      18: aload_0
      19: getfield      #18                 // Field resultsList:Ljavax/swing/JList;
      22: invokevirtual #46                 // Method javax/swing/JList.getModel:()Ljavax/swing/ListModel;
      25: invokeinterface #47,  1           // InterfaceMethod javax/swing/ListModel.getSize:()I
      30: iconst_1
      31: isub
      32: if_icmple     37
      35: iconst_0
      36: istore_1
      37: aload_0
      38: getfield      #18                 // Field resultsList:Ljavax/swing/JList;
      41: iload_1
      42: invokevirtual #48                 // Method javax/swing/JList.setSelectedIndex:(I)V
      45: return

  private void update();
    Code:
       0: aload_0
       1: getfield      #16                 // Field findTimer:Ljavax/swing/Timer;
       4: invokevirtual #49                 // Method javax/swing/Timer.restart:()V
       7: return

  private void doUpdate();
    Code:
       0: aload_0
       1: getfield      #8                  // Field textField:Ljavax/swing/JTextField;
       4: invokevirtual #50                 // Method javax/swing/JTextField.getText:()Ljava/lang/String;
       7: invokevirtual #51                 // Method java/lang/String.trim:()Ljava/lang/String;
      10: astore_1
      11: aload_1
      12: invokevirtual #52                 // Method java/lang/String.length:()I
      15: ifne          30
      18: aload_0
      19: getfield      #18                 // Field resultsList:Ljavax/swing/JList;
      22: iconst_0
      23: anewarray     #20                 // class org/semanticweb/owlapi/model/OWLEntity
      26: invokevirtual #53                 // Method javax/swing/JList.setListData:([Ljava/lang/Object;)V
      29: return
      30: aload_0
      31: getfield      #10                 // Field findable:Lorg/protege/editor/owl/ui/view/Findable;
      34: aload_1
      35: invokeinterface #54,  2           // InterfaceMethod org/protege/editor/owl/ui/view/Findable.find:(Ljava/lang/String;)Ljava/util/List;
      40: astore_2
      41: aload_0
      42: getfield      #18                 // Field resultsList:Ljavax/swing/JList;
      45: aload_2
      46: aload_2
      47: invokeinterface #55,  1           // InterfaceMethod java/util/List.size:()I
      52: anewarray     #20                 // class org/semanticweb/owlapi/model/OWLEntity
      55: invokeinterface #56,  2           // InterfaceMethod java/util/List.toArray:([Ljava/lang/Object;)[Ljava/lang/Object;
      60: checkcast     #57                 // class "[Lorg/semanticweb/owlapi/model/OWLEntity;"
      63: invokevirtual #53                 // Method javax/swing/JList.setListData:([Ljava/lang/Object;)V
      66: aload_2
      67: invokeinterface #58,  1           // InterfaceMethod java/util/List.isEmpty:()Z
      72: ifne          83
      75: aload_0
      76: getfield      #18                 // Field resultsList:Ljavax/swing/JList;
      79: iconst_0
      80: invokevirtual #48                 // Method javax/swing/JList.setSelectedIndex:(I)V
      83: return

  public java.awt.Dimension getPreferredSize();
    Code:
       0: new           #59                 // class java/awt/Dimension
       3: dup
       4: sipush        250
       7: sipush        400
      10: invokespecial #60                 // Method java/awt/Dimension."<init>":(II)V
      13: areturn

  public static org.semanticweb.owlapi.model.OWLEntity showDialog(java.awt.Component, org.protege.editor.owl.OWLEditorKit, org.protege.editor.owl.ui.view.Findable<? extends org.semanticweb.owlapi.model.OWLEntity>);
    Code:
       0: new           #61                 // class org/protege/editor/owl/ui/find/OWLEntityFindPanel
       3: dup
       4: aload_1
       5: aload_2
       6: invokespecial #62                 // Method "<init>":(Lorg/protege/editor/owl/OWLEditorKit;Lorg/protege/editor/owl/ui/view/Findable;)V
       9: astore_3
      10: aload_0
      11: ldc           #63                 // String Find
      13: aload_3
      14: iconst_m1
      15: iconst_2
      16: aload_3
      17: getfield      #8                  // Field textField:Ljavax/swing/JTextField;
      20: invokestatic  #65                 // Method org/protege/editor/core/ui/util/JOptionPaneEx.showConfirmDialog:(Ljava/awt/Component;Ljava/lang/String;Ljavax/swing/JComponent;IILjavax/swing/JComponent;)I
      23: istore        4
      25: iload         4
      27: ifne          35
      30: aload_3
      31: invokevirtual #66                 // Method getSelectedEntity:()Lorg/semanticweb/owlapi/model/OWLEntity;
      34: areturn
      35: aconst_null
      36: areturn

  static void access$000(org.protege.editor.owl.ui.find.OWLEntityFindPanel);
    Code:
       0: aload_0
       1: invokespecial #3                  // Method doUpdate:()V
       4: return

  static void access$100(org.protege.editor.owl.ui.find.OWLEntityFindPanel);
    Code:
       0: aload_0
       1: invokespecial #2                  // Method update:()V
       4: return

  static void access$200(org.protege.editor.owl.ui.find.OWLEntityFindPanel, java.awt.event.KeyEvent);
    Code:
       0: aload_0
       1: aload_1
       2: invokespecial #1                  // Method handleKeyPressed:(Ljava/awt/event/KeyEvent;)V
       5: return
}
