Compiled from "Type.java"
public final class org.springframework.hateoas.alps.Type extends java.lang.Enum<org.springframework.hateoas.alps.Type> {
  public static final org.springframework.hateoas.alps.Type SEMANTIC;

  public static final org.springframework.hateoas.alps.Type SAFE;

  public static final org.springframework.hateoas.alps.Type IDEMPOTENT;

  public static final org.springframework.hateoas.alps.Type UNSAFE;

  private static final org.springframework.hateoas.alps.Type[] $VALUES;

  public static org.springframework.hateoas.alps.Type[] values();
    Code:
       0: getstatic     #1                  // Field $VALUES:[Lorg/springframework/hateoas/alps/Type;
       3: invokevirtual #2                  // Method "[Lorg/springframework/hateoas/alps/Type;".clone:()Ljava/lang/Object;
       6: checkcast     #3                  // class "[Lorg/springframework/hateoas/alps/Type;"
       9: areturn

  public static org.springframework.hateoas.alps.Type valueOf(java.lang.String);
    Code:
       0: ldc           #4                  // class org/springframework/hateoas/alps/Type
       2: aload_0
       3: invokestatic  #5                  // Method java/lang/Enum.valueOf:(Ljava/lang/Class;Ljava/lang/String;)Ljava/lang/Enum;
       6: checkcast     #4                  // class org/springframework/hateoas/alps/Type
       9: areturn

  private org.springframework.hateoas.alps.Type();
    Code:
       0: aload_0
       1: aload_1
       2: iload_2
       3: invokespecial #6                  // Method java/lang/Enum."<init>":(Ljava/lang/String;I)V
       6: return

  public java.lang.String toString();
    Code:
       0: aload_0
       1: invokevirtual #7                  // Method name:()Ljava/lang/String;
       4: getstatic     #8                  // Field java/util/Locale.US:Ljava/util/Locale;
       7: invokevirtual #9                  // Method java/lang/String.toLowerCase:(Ljava/util/Locale;)Ljava/lang/String;
      10: areturn

  static {};
    Code:
       0: new           #4                  // class org/springframework/hateoas/alps/Type
       3: dup
       4: ldc           #10                 // String SEMANTIC
       6: iconst_0
       7: invokespecial #11                 // Method "<init>":(Ljava/lang/String;I)V
      10: putstatic     #12                 // Field SEMANTIC:Lorg/springframework/hateoas/alps/Type;
      13: new           #4                  // class org/springframework/hateoas/alps/Type
      16: dup
      17: ldc           #13                 // String SAFE
      19: iconst_1
      20: invokespecial #11                 // Method "<init>":(Ljava/lang/String;I)V
      23: putstatic     #14                 // Field SAFE:Lorg/springframework/hateoas/alps/Type;
      26: new           #4                  // class org/springframework/hateoas/alps/Type
      29: dup
      30: ldc           #15                 // String IDEMPOTENT
      32: iconst_2
      33: invokespecial #11                 // Method "<init>":(Ljava/lang/String;I)V
      36: putstatic     #16                 // Field IDEMPOTENT:Lorg/springframework/hateoas/alps/Type;
      39: new           #4                  // class org/springframework/hateoas/alps/Type
      42: dup
      43: ldc           #17                 // String UNSAFE
      45: iconst_3
      46: invokespecial #11                 // Method "<init>":(Ljava/lang/String;I)V
      49: putstatic     #18                 // Field UNSAFE:Lorg/springframework/hateoas/alps/Type;
      52: iconst_4
      53: anewarray     #4                  // class org/springframework/hateoas/alps/Type
      56: dup
      57: iconst_0
      58: getstatic     #12                 // Field SEMANTIC:Lorg/springframework/hateoas/alps/Type;
      61: aastore
      62: dup
      63: iconst_1
      64: getstatic     #14                 // Field SAFE:Lorg/springframework/hateoas/alps/Type;
      67: aastore
      68: dup
      69: iconst_2
      70: getstatic     #16                 // Field IDEMPOTENT:Lorg/springframework/hateoas/alps/Type;
      73: aastore
      74: dup
      75: iconst_3
      76: getstatic     #18                 // Field UNSAFE:Lorg/springframework/hateoas/alps/Type;
      79: aastore
      80: putstatic     #1                  // Field $VALUES:[Lorg/springframework/hateoas/alps/Type;
      83: return
}
