Compiled from "PropertyListConfiguration.java"
class org.apache.commons.configuration.plist.PropertyListConfiguration$DateTimeZoneParser extends org.apache.commons.configuration.plist.PropertyListConfiguration$DateComponentParser {
  private org.apache.commons.configuration.plist.PropertyListConfiguration$DateTimeZoneParser();
    Code:
       0: aload_0
       1: aconst_null
       2: invokespecial #2                  // Method org/apache/commons/configuration/plist/PropertyListConfiguration$DateComponentParser."<init>":(Lorg/apache/commons/configuration/plist/PropertyListConfiguration$1;)V
       5: return

  public void formatComponent(java.lang.StringBuilder, java.util.Calendar);
    Code:
       0: aload_2
       1: invokevirtual #3                  // Method java/util/Calendar.getTimeZone:()Ljava/util/TimeZone;
       4: astore_3
       5: aload_3
       6: invokevirtual #4                  // Method java/util/TimeZone.getRawOffset:()I
       9: ldc           #5                  // int 60000
      11: idiv
      12: istore        4
      14: iload         4
      16: ifge          34
      19: aload_1
      20: bipush        45
      22: invokevirtual #6                  // Method java/lang/StringBuilder.append:(C)Ljava/lang/StringBuilder;
      25: pop
      26: iload         4
      28: ineg
      29: istore        4
      31: goto          41
      34: aload_1
      35: bipush        43
      37: invokevirtual #6                  // Method java/lang/StringBuilder.append:(C)Ljava/lang/StringBuilder;
      40: pop
      41: iload         4
      43: bipush        60
      45: idiv
      46: istore        5
      48: iload         4
      50: bipush        60
      52: irem
      53: istore        6
      55: aload_0
      56: aload_1
      57: iload         5
      59: iconst_2
      60: invokevirtual #7                  // Method padNum:(Ljava/lang/StringBuilder;II)V
      63: aload_0
      64: aload_1
      65: iload         6
      67: iconst_2
      68: invokevirtual #7                  // Method padNum:(Ljava/lang/StringBuilder;II)V
      71: return

  public int parseComponent(java.lang.String, int, java.util.Calendar) throws org.apache.commons.configuration.plist.ParseException;
    Code:
       0: aload_0
       1: aload_1
       2: iload_2
       3: iconst_5
       4: invokevirtual #8                  // Method checkLength:(Ljava/lang/String;II)V
       7: new           #9                  // class java/lang/StringBuilder
      10: dup
      11: invokespecial #10                 // Method java/lang/StringBuilder."<init>":()V
      14: ldc           #11                 // String GMT
      16: invokevirtual #12                 // Method java/lang/StringBuilder.append:(Ljava/lang/String;)Ljava/lang/StringBuilder;
      19: aload_1
      20: iload_2
      21: iload_2
      22: iconst_5
      23: iadd
      24: invokevirtual #13                 // Method java/lang/String.substring:(II)Ljava/lang/String;
      27: invokevirtual #12                 // Method java/lang/StringBuilder.append:(Ljava/lang/String;)Ljava/lang/StringBuilder;
      30: invokevirtual #14                 // Method java/lang/StringBuilder.toString:()Ljava/lang/String;
      33: invokestatic  #15                 // Method java/util/TimeZone.getTimeZone:(Ljava/lang/String;)Ljava/util/TimeZone;
      36: astore        4
      38: aload_3
      39: aload         4
      41: invokevirtual #16                 // Method java/util/Calendar.setTimeZone:(Ljava/util/TimeZone;)V
      44: iconst_5
      45: ireturn

  org.apache.commons.configuration.plist.PropertyListConfiguration$DateTimeZoneParser(org.apache.commons.configuration.plist.PropertyListConfiguration$1);
    Code:
       0: aload_0
       1: invokespecial #1                  // Method "<init>":()V
       4: return
}
