Compiled from "DeserializedPackageMemberScope.kt"
public class kotlin.reflect.jvm.internal.impl.serialization.deserialization.descriptors.DeserializedPackageMemberScope extends kotlin.reflect.jvm.internal.impl.serialization.deserialization.descriptors.DeserializedMemberScope {
  private final kotlin.reflect.jvm.internal.impl.descriptors.PackageFragmentDescriptor packageDescriptor;

  private final java.lang.String debugName;

  private final kotlin.reflect.jvm.internal.impl.name.FqName packageFqName;

  public kotlin.reflect.jvm.internal.impl.serialization.deserialization.descriptors.DeserializedPackageMemberScope(kotlin.reflect.jvm.internal.impl.descriptors.PackageFragmentDescriptor, kotlin.reflect.jvm.internal.impl.metadata.ProtoBuf$Package, kotlin.reflect.jvm.internal.impl.metadata.deserialization.NameResolver, kotlin.reflect.jvm.internal.impl.metadata.deserialization.BinaryVersion, kotlin.reflect.jvm.internal.impl.serialization.deserialization.descriptors.DeserializedContainerSource, kotlin.reflect.jvm.internal.impl.serialization.deserialization.DeserializationComponents, java.lang.String, kotlin.jvm.functions.Function0<? extends java.util.Collection<kotlin.reflect.jvm.internal.impl.name.Name>>);
    Code:
       0: aload_1
       1: ldc           #10                 // String packageDescriptor
       3: invokestatic  #56                 // Method kotlin/jvm/internal/Intrinsics.checkNotNullParameter:(Ljava/lang/Object;Ljava/lang/String;)V
       6: aload_2
       7: ldc           #11                 // String proto
       9: invokestatic  #56                 // Method kotlin/jvm/internal/Intrinsics.checkNotNullParameter:(Ljava/lang/Object;Ljava/lang/String;)V
      12: aload_3
      13: ldc           #9                  // String nameResolver
      15: invokestatic  #56                 // Method kotlin/jvm/internal/Intrinsics.checkNotNullParameter:(Ljava/lang/Object;Ljava/lang/String;)V
      18: aload         4
      20: ldc           #6                  // String metadataVersion
      22: invokestatic  #56                 // Method kotlin/jvm/internal/Intrinsics.checkNotNullParameter:(Ljava/lang/Object;Ljava/lang/String;)V
      25: aload         6
      27: ldc           #2                  // String components
      29: invokestatic  #56                 // Method kotlin/jvm/internal/Intrinsics.checkNotNullParameter:(Ljava/lang/Object;Ljava/lang/String;)V
      32: aload         7
      34: ldc           #3                  // String debugName
      36: invokestatic  #56                 // Method kotlin/jvm/internal/Intrinsics.checkNotNullParameter:(Ljava/lang/Object;Ljava/lang/String;)V
      39: aload         8
      41: ldc           #1                  // String classNames
      43: invokestatic  #56                 // Method kotlin/jvm/internal/Intrinsics.checkNotNullParameter:(Ljava/lang/Object;Ljava/lang/String;)V
      46: aload_0
      47: aload         6
      49: aload_1
      50: aload_3
      51: new           #36                 // class kotlin/reflect/jvm/internal/impl/metadata/deserialization/TypeTable
      54: dup
      55: aload_2
      56: invokevirtual #61                 // Method kotlin/reflect/jvm/internal/impl/metadata/ProtoBuf$Package.getTypeTable:()Lkotlin/reflect/jvm/internal/impl/metadata/ProtoBuf$TypeTable;
      59: dup
      60: ldc           #15                 // String proto.typeTable
      62: invokestatic  #55                 // Method kotlin/jvm/internal/Intrinsics.checkNotNullExpressionValue:(Ljava/lang/Object;Ljava/lang/String;)V
      65: invokespecial #63                 // Method kotlin/reflect/jvm/internal/impl/metadata/deserialization/TypeTable."<init>":(Lkotlin/reflect/jvm/internal/impl/metadata/ProtoBuf$TypeTable;)V
      68: getstatic     #47                 // Field kotlin/reflect/jvm/internal/impl/metadata/deserialization/VersionRequirementTable.Companion:Lkotlin/reflect/jvm/internal/impl/metadata/deserialization/VersionRequirementTable$Companion;
      71: aload_2
      72: invokevirtual #62                 // Method kotlin/reflect/jvm/internal/impl/metadata/ProtoBuf$Package.getVersionRequirementTable:()Lkotlin/reflect/jvm/internal/impl/metadata/ProtoBuf$VersionRequirementTable;
      75: dup
      76: ldc           #16                 // String proto.versionRequirementTable
      78: invokestatic  #55                 // Method kotlin/jvm/internal/Intrinsics.checkNotNullExpressionValue:(Ljava/lang/Object;Ljava/lang/String;)V
      81: invokevirtual #64                 // Method kotlin/reflect/jvm/internal/impl/metadata/deserialization/VersionRequirementTable$Companion.create:(Lkotlin/reflect/jvm/internal/impl/metadata/ProtoBuf$VersionRequirementTable;)Lkotlin/reflect/jvm/internal/impl/metadata/deserialization/VersionRequirementTable;
      84: aload         4
      86: aload         5
      88: invokevirtual #66                 // Method kotlin/reflect/jvm/internal/impl/serialization/deserialization/DeserializationComponents.createContext:(Lkotlin/reflect/jvm/internal/impl/descriptors/PackageFragmentDescriptor;Lkotlin/reflect/jvm/internal/impl/metadata/deserialization/NameResolver;Lkotlin/reflect/jvm/internal/impl/metadata/deserialization/TypeTable;Lkotlin/reflect/jvm/internal/impl/metadata/deserialization/VersionRequirementTable;Lkotlin/reflect/jvm/internal/impl/metadata/deserialization/BinaryVersion;Lkotlin/reflect/jvm/internal/impl/serialization/deserialization/descriptors/DeserializedContainerSource;)Lkotlin/reflect/jvm/internal/impl/serialization/deserialization/DeserializationContext;
      91: aload_2
      92: invokevirtual #58                 // Method kotlin/reflect/jvm/internal/impl/metadata/ProtoBuf$Package.getFunctionList:()Ljava/util/List;
      95: dup
      96: ldc           #12                 // String proto.functionList
      98: invokestatic  #55                 // Method kotlin/jvm/internal/Intrinsics.checkNotNullExpressionValue:(Ljava/lang/Object;Ljava/lang/String;)V
     101: aload_2
     102: invokevirtual #59                 // Method kotlin/reflect/jvm/internal/impl/metadata/ProtoBuf$Package.getPropertyList:()Ljava/util/List;
     105: dup
     106: ldc           #13                 // String proto.propertyList
     108: invokestatic  #55                 // Method kotlin/jvm/internal/Intrinsics.checkNotNullExpressionValue:(Ljava/lang/Object;Ljava/lang/String;)V
     111: aload_2
     112: invokevirtual #60                 // Method kotlin/reflect/jvm/internal/impl/metadata/ProtoBuf$Package.getTypeAliasList:()Ljava/util/List;
     115: dup
     116: ldc           #14                 // String proto.typeAliasList
     118: invokestatic  #55                 // Method kotlin/jvm/internal/Intrinsics.checkNotNullExpressionValue:(Ljava/lang/Object;Ljava/lang/String;)V
     121: aload         8
     123: invokespecial #70                 // Method kotlin/reflect/jvm/internal/impl/serialization/deserialization/descriptors/DeserializedMemberScope."<init>":(Lkotlin/reflect/jvm/internal/impl/serialization/deserialization/DeserializationContext;Ljava/util/List;Ljava/util/List;Ljava/util/List;Lkotlin/jvm/functions/Function0;)V
     126: aload_0
     127: aload_1
     128: putfield      #49                 // Field packageDescriptor:Lkotlin/reflect/jvm/internal/impl/descriptors/PackageFragmentDescriptor;
     131: aload_0
     132: aload         7
     134: putfield      #48                 // Field debugName:Ljava/lang/String;
     137: aload_0
     138: aload_0
     139: getfield      #49                 // Field packageDescriptor:Lkotlin/reflect/jvm/internal/impl/descriptors/PackageFragmentDescriptor;
     142: invokeinterface #81,  1           // InterfaceMethod kotlin/reflect/jvm/internal/impl/descriptors/PackageFragmentDescriptor.getFqName:()Lkotlin/reflect/jvm/internal/impl/name/FqName;
     147: putfield      #50                 // Field packageFqName:Lkotlin/reflect/jvm/internal/impl/name/FqName;
     150: return

  public java.util.List<kotlin.reflect.jvm.internal.impl.descriptors.DeclarationDescriptor> getContributedDescriptors(kotlin.reflect.jvm.internal.impl.resolve.scopes.DescriptorKindFilter, kotlin.jvm.functions.Function1<? super kotlin.reflect.jvm.internal.impl.name.Name, java.lang.Boolean>);
    Code:
       0: aload_1
       1: ldc           #4                  // String kindFilter
       3: invokestatic  #56                 // Method kotlin/jvm/internal/Intrinsics.checkNotNullParameter:(Ljava/lang/Object;Ljava/lang/String;)V
       6: aload_2
       7: ldc           #8                  // String nameFilter
       9: invokestatic  #56                 // Method kotlin/jvm/internal/Intrinsics.checkNotNullParameter:(Ljava/lang/Object;Ljava/lang/String;)V
      12: aload_0
      13: aload_1
      14: aload_2
      15: getstatic     #46                 // Field kotlin/reflect/jvm/internal/impl/incremental/components/NoLookupLocation.WHEN_GET_ALL_DESCRIPTORS:Lkotlin/reflect/jvm/internal/impl/incremental/components/NoLookupLocation;
      18: checkcast     #30                 // class kotlin/reflect/jvm/internal/impl/incremental/components/LookupLocation
      21: invokevirtual #73                 // Method computeDescriptors:(Lkotlin/reflect/jvm/internal/impl/resolve/scopes/DescriptorKindFilter;Lkotlin/jvm/functions/Function1;Lkotlin/reflect/jvm/internal/impl/incremental/components/LookupLocation;)Ljava/util/Collection;
      24: aload_0
      25: invokevirtual #74                 // Method getC:()Lkotlin/reflect/jvm/internal/impl/serialization/deserialization/DeserializationContext;
      28: invokevirtual #69                 // Method kotlin/reflect/jvm/internal/impl/serialization/deserialization/DeserializationContext.getComponents:()Lkotlin/reflect/jvm/internal/impl/serialization/deserialization/DeserializationComponents;
      31: invokevirtual #67                 // Method kotlin/reflect/jvm/internal/impl/serialization/deserialization/DeserializationComponents.getFictitiousClassDescriptorFactories:()Ljava/lang/Iterable;
      34: astore_3
      35: astore        12
      37: iconst_0
      38: istore        4
      40: aload_3
      41: astore        5
      43: new           #19                 // class java/util/ArrayList
      46: dup
      47: invokespecial #51                 // Method java/util/ArrayList."<init>":()V
      50: checkcast     #20                 // class java/util/Collection
      53: astore        6
      55: iconst_0
      56: istore        7
      58: aload         5
      60: invokeinterface #77,  1           // InterfaceMethod java/lang/Iterable.iterator:()Ljava/util/Iterator;
      65: astore        8
      67: aload         8
      69: invokeinterface #79,  1           // InterfaceMethod java/util/Iterator.hasNext:()Z
      74: ifeq          123
      77: aload         8
      79: invokeinterface #80,  1           // InterfaceMethod java/util/Iterator.next:()Ljava/lang/Object;
      84: astore        9
      86: aload         9
      88: checkcast     #28                 // class kotlin/reflect/jvm/internal/impl/descriptors/deserialization/ClassDescriptorFactory
      91: astore        10
      93: iconst_0
      94: istore        11
      96: aload         10
      98: aload_0
      99: getfield      #50                 // Field packageFqName:Lkotlin/reflect/jvm/internal/impl/name/FqName;
     102: invokeinterface #82,  2           // InterfaceMethod kotlin/reflect/jvm/internal/impl/descriptors/deserialization/ClassDescriptorFactory.getAllContributedClassesIfPossible:(Lkotlin/reflect/jvm/internal/impl/name/FqName;)Ljava/util/Collection;
     107: checkcast     #18                 // class java/lang/Iterable
     110: astore        10
     112: aload         6
     114: aload         10
     116: invokestatic  #52                 // Method kotlin/collections/CollectionsKt.addAll:(Ljava/util/Collection;Ljava/lang/Iterable;)Z
     119: pop
     120: goto          67
     123: aload         6
     125: checkcast     #22                 // class java/util/List
     128: nop
     129: aload         12
     131: swap
     132: checkcast     #18                 // class java/lang/Iterable
     135: invokestatic  #53                 // Method kotlin/collections/CollectionsKt.plus:(Ljava/util/Collection;Ljava/lang/Iterable;)Ljava/util/List;
     138: areturn

  protected boolean hasClass(kotlin.reflect.jvm.internal.impl.name.Name);
    Code:
       0: aload_1
       1: ldc           #7                  // String name
       3: invokestatic  #56                 // Method kotlin/jvm/internal/Intrinsics.checkNotNullParameter:(Ljava/lang/Object;Ljava/lang/String;)V
       6: aload_0
       7: aload_1
       8: invokespecial #72                 // Method kotlin/reflect/jvm/internal/impl/serialization/deserialization/descriptors/DeserializedMemberScope.hasClass:(Lkotlin/reflect/jvm/internal/impl/name/Name;)Z
      11: ifne          110
      14: aload_0
      15: invokevirtual #74                 // Method getC:()Lkotlin/reflect/jvm/internal/impl/serialization/deserialization/DeserializationContext;
      18: invokevirtual #69                 // Method kotlin/reflect/jvm/internal/impl/serialization/deserialization/DeserializationContext.getComponents:()Lkotlin/reflect/jvm/internal/impl/serialization/deserialization/DeserializationComponents;
      21: invokevirtual #67                 // Method kotlin/reflect/jvm/internal/impl/serialization/deserialization/DeserializationComponents.getFictitiousClassDescriptorFactories:()Ljava/lang/Iterable;
      24: astore_2
      25: iconst_0
      26: istore_3
      27: aload_2
      28: instanceof    #20                 // class java/util/Collection
      31: ifeq          50
      34: aload_2
      35: checkcast     #20                 // class java/util/Collection
      38: invokeinterface #78,  1           // InterfaceMethod java/util/Collection.isEmpty:()Z
      43: ifeq          50
      46: iconst_0
      47: goto          107
      50: aload_2
      51: invokeinterface #77,  1           // InterfaceMethod java/lang/Iterable.iterator:()Ljava/util/Iterator;
      56: astore        4
      58: aload         4
      60: invokeinterface #79,  1           // InterfaceMethod java/util/Iterator.hasNext:()Z
      65: ifeq          106
      68: aload         4
      70: invokeinterface #80,  1           // InterfaceMethod java/util/Iterator.next:()Ljava/lang/Object;
      75: astore        5
      77: aload         5
      79: checkcast     #28                 // class kotlin/reflect/jvm/internal/impl/descriptors/deserialization/ClassDescriptorFactory
      82: astore        6
      84: iconst_0
      85: istore        7
      87: aload         6
      89: aload_0
      90: getfield      #50                 // Field packageFqName:Lkotlin/reflect/jvm/internal/impl/name/FqName;
      93: aload_1
      94: invokeinterface #83,  3           // InterfaceMethod kotlin/reflect/jvm/internal/impl/descriptors/deserialization/ClassDescriptorFactory.shouldCreateClass:(Lkotlin/reflect/jvm/internal/impl/name/FqName;Lkotlin/reflect/jvm/internal/impl/name/Name;)Z
      99: ifeq          58
     102: iconst_1
     103: goto          107
     106: iconst_0
     107: ifeq          114
     110: iconst_1
     111: goto          115
     114: iconst_0
     115: ireturn

  protected kotlin.reflect.jvm.internal.impl.name.ClassId createClassId(kotlin.reflect.jvm.internal.impl.name.Name);
    Code:
       0: aload_1
       1: ldc           #7                  // String name
       3: invokestatic  #56                 // Method kotlin/jvm/internal/Intrinsics.checkNotNullParameter:(Ljava/lang/Object;Ljava/lang/String;)V
       6: new           #39                 // class kotlin/reflect/jvm/internal/impl/name/ClassId
       9: dup
      10: aload_0
      11: getfield      #50                 // Field packageFqName:Lkotlin/reflect/jvm/internal/impl/name/FqName;
      14: aload_1
      15: invokespecial #65                 // Method kotlin/reflect/jvm/internal/impl/name/ClassId."<init>":(Lkotlin/reflect/jvm/internal/impl/name/FqName;Lkotlin/reflect/jvm/internal/impl/name/Name;)V
      18: areturn

  public kotlin.reflect.jvm.internal.impl.descriptors.ClassifierDescriptor getContributedClassifier(kotlin.reflect.jvm.internal.impl.name.Name, kotlin.reflect.jvm.internal.impl.incremental.components.LookupLocation);
    Code:
       0: aload_1
       1: ldc           #7                  // String name
       3: invokestatic  #56                 // Method kotlin/jvm/internal/Intrinsics.checkNotNullParameter:(Ljava/lang/Object;Ljava/lang/String;)V
       6: aload_2
       7: ldc           #5                  // String location
       9: invokestatic  #56                 // Method kotlin/jvm/internal/Intrinsics.checkNotNullParameter:(Ljava/lang/Object;Ljava/lang/String;)V
      12: aload_0
      13: aload_1
      14: aload_2
      15: invokevirtual #76                 // Method recordLookup:(Lkotlin/reflect/jvm/internal/impl/name/Name;Lkotlin/reflect/jvm/internal/impl/incremental/components/LookupLocation;)V
      18: aload_0
      19: aload_1
      20: aload_2
      21: invokespecial #71                 // Method kotlin/reflect/jvm/internal/impl/serialization/deserialization/descriptors/DeserializedMemberScope.getContributedClassifier:(Lkotlin/reflect/jvm/internal/impl/name/Name;Lkotlin/reflect/jvm/internal/impl/incremental/components/LookupLocation;)Lkotlin/reflect/jvm/internal/impl/descriptors/ClassifierDescriptor;
      24: areturn

  public void recordLookup(kotlin.reflect.jvm.internal.impl.name.Name, kotlin.reflect.jvm.internal.impl.incremental.components.LookupLocation);
    Code:
       0: aload_1
       1: ldc           #7                  // String name
       3: invokestatic  #56                 // Method kotlin/jvm/internal/Intrinsics.checkNotNullParameter:(Ljava/lang/Object;Ljava/lang/String;)V
       6: aload_2
       7: ldc           #5                  // String location
       9: invokestatic  #56                 // Method kotlin/jvm/internal/Intrinsics.checkNotNullParameter:(Ljava/lang/Object;Ljava/lang/String;)V
      12: aload_0
      13: invokevirtual #74                 // Method getC:()Lkotlin/reflect/jvm/internal/impl/serialization/deserialization/DeserializationContext;
      16: invokevirtual #69                 // Method kotlin/reflect/jvm/internal/impl/serialization/deserialization/DeserializationContext.getComponents:()Lkotlin/reflect/jvm/internal/impl/serialization/deserialization/DeserializationComponents;
      19: invokevirtual #68                 // Method kotlin/reflect/jvm/internal/impl/serialization/deserialization/DeserializationComponents.getLookupTracker:()Lkotlin/reflect/jvm/internal/impl/incremental/components/LookupTracker;
      22: aload_2
      23: aload_0
      24: getfield      #49                 // Field packageDescriptor:Lkotlin/reflect/jvm/internal/impl/descriptors/PackageFragmentDescriptor;
      27: aload_1
      28: invokestatic  #57                 // Method kotlin/reflect/jvm/internal/impl/incremental/UtilsKt.record:(Lkotlin/reflect/jvm/internal/impl/incremental/components/LookupTracker;Lkotlin/reflect/jvm/internal/impl/incremental/components/LookupLocation;Lkotlin/reflect/jvm/internal/impl/descriptors/PackageFragmentDescriptor;Lkotlin/reflect/jvm/internal/impl/name/Name;)V
      31: return

  protected java.util.Set<kotlin.reflect.jvm.internal.impl.name.Name> getNonDeclaredFunctionNames();
    Code:
       0: invokestatic  #54                 // Method kotlin/collections/SetsKt.emptySet:()Ljava/util/Set;
       3: areturn

  protected java.util.Set<kotlin.reflect.jvm.internal.impl.name.Name> getNonDeclaredVariableNames();
    Code:
       0: invokestatic  #54                 // Method kotlin/collections/SetsKt.emptySet:()Ljava/util/Set;
       3: areturn

  protected java.util.Set<kotlin.reflect.jvm.internal.impl.name.Name> getNonDeclaredClassifierNames();
    Code:
       0: invokestatic  #54                 // Method kotlin/collections/SetsKt.emptySet:()Ljava/util/Set;
       3: areturn

  protected void addEnumEntryDescriptors(java.util.Collection<kotlin.reflect.jvm.internal.impl.descriptors.DeclarationDescriptor>, kotlin.jvm.functions.Function1<? super kotlin.reflect.jvm.internal.impl.name.Name, java.lang.Boolean>);
    Code:
       0: aload_1
       1: ldc           #17                 // String result
       3: invokestatic  #56                 // Method kotlin/jvm/internal/Intrinsics.checkNotNullParameter:(Ljava/lang/Object;Ljava/lang/String;)V
       6: aload_2
       7: ldc           #8                  // String nameFilter
       9: invokestatic  #56                 // Method kotlin/jvm/internal/Intrinsics.checkNotNullParameter:(Ljava/lang/Object;Ljava/lang/String;)V
      12: return

  public java.lang.String toString();
    Code:
       0: aload_0
       1: getfield      #48                 // Field debugName:Ljava/lang/String;
       4: areturn

  public java.util.Collection getContributedDescriptors(kotlin.reflect.jvm.internal.impl.resolve.scopes.DescriptorKindFilter, kotlin.jvm.functions.Function1);
    Code:
       0: aload_0
       1: aload_1
       2: aload_2
       3: invokevirtual #75                 // Method getContributedDescriptors:(Lkotlin/reflect/jvm/internal/impl/resolve/scopes/DescriptorKindFilter;Lkotlin/jvm/functions/Function1;)Ljava/util/List;
       6: checkcast     #20                 // class java/util/Collection
       9: areturn
}
