Compiled from "MixinEmitter.java"
class org.springframework.cglib.proxy.MixinEmitter extends org.springframework.cglib.core.ClassEmitter {
  private static final java.lang.String FIELD_NAME;

  private static final org.springframework.cglib.core.Signature CSTRUCT_OBJECT_ARRAY;

  private static final org.springframework.asm.Type MIXIN;

  private static final org.springframework.cglib.core.Signature NEW_INSTANCE;

  public org.springframework.cglib.proxy.MixinEmitter(org.springframework.asm.ClassVisitor, java.lang.String, java.lang.Class[], int[]);
    Code:
       0: aload_0
       1: aload_1
       2: invokespecial #19                 // Method org/springframework/cglib/core/ClassEmitter."<init>":(Lorg/springframework/asm/ClassVisitor;)V
       5: aload_0
       6: bipush        46
       8: iconst_1
       9: aload_2
      10: getstatic     #21                 // Field MIXIN:Lorg/springframework/asm/Type;
      13: aload_0
      14: aload_3
      15: invokevirtual #25                 // Method getInterfaces:([Ljava/lang/Class;)[Ljava/lang/Class;
      18: invokestatic  #31                 // Method org/springframework/cglib/core/TypeUtils.getTypes:([Ljava/lang/Class;)[Lorg/springframework/asm/Type;
      21: ldc           #33                 // String <generated>
      23: invokevirtual #37                 // Method begin_class:(IILjava/lang/String;Lorg/springframework/asm/Type;[Lorg/springframework/asm/Type;Ljava/lang/String;)V
      26: aload_0
      27: invokestatic  #43                 // Method org/springframework/cglib/core/EmitUtils.null_constructor:(Lorg/springframework/cglib/core/ClassEmitter;)V
      30: aload_0
      31: getstatic     #45                 // Field NEW_INSTANCE:Lorg/springframework/cglib/core/Signature;
      34: invokestatic  #49                 // Method org/springframework/cglib/core/EmitUtils.factory_method:(Lorg/springframework/cglib/core/ClassEmitter;Lorg/springframework/cglib/core/Signature;)V
      37: aload_0
      38: iconst_2
      39: ldc           #9                  // String CGLIB$DELEGATES
      41: getstatic     #54                 // Field org/springframework/cglib/core/Constants.TYPE_OBJECT_ARRAY:Lorg/springframework/asm/Type;
      44: aconst_null
      45: invokevirtual #58                 // Method declare_field:(ILjava/lang/String;Lorg/springframework/asm/Type;Ljava/lang/Object;)V
      48: aload_0
      49: iconst_1
      50: getstatic     #60                 // Field CSTRUCT_OBJECT_ARRAY:Lorg/springframework/cglib/core/Signature;
      53: aconst_null
      54: invokevirtual #64                 // Method begin_method:(ILorg/springframework/cglib/core/Signature;[Lorg/springframework/asm/Type;)Lorg/springframework/cglib/core/CodeEmitter;
      57: astore        5
      59: aload         5
      61: invokevirtual #70                 // Method org/springframework/cglib/core/CodeEmitter.load_this:()V
      64: aload         5
      66: invokevirtual #73                 // Method org/springframework/cglib/core/CodeEmitter.super_invoke_constructor:()V
      69: aload         5
      71: invokevirtual #70                 // Method org/springframework/cglib/core/CodeEmitter.load_this:()V
      74: aload         5
      76: iconst_0
      77: invokevirtual #77                 // Method org/springframework/cglib/core/CodeEmitter.load_arg:(I)V
      80: aload         5
      82: ldc           #9                  // String CGLIB$DELEGATES
      84: invokevirtual #81                 // Method org/springframework/cglib/core/CodeEmitter.putfield:(Ljava/lang/String;)V
      87: aload         5
      89: invokevirtual #84                 // Method org/springframework/cglib/core/CodeEmitter.return_value:()V
      92: aload         5
      94: invokevirtual #87                 // Method org/springframework/cglib/core/CodeEmitter.end_method:()V
      97: new           #89                 // class java/util/HashSet
     100: dup
     101: invokespecial #91                 // Method java/util/HashSet."<init>":()V
     104: astore        6
     106: iconst_0
     107: istore        7
     109: iload         7
     111: aload_3
     112: arraylength
     113: if_icmpge     280
     116: aload_0
     117: aload_3
     118: iload         7
     120: aaload
     121: invokevirtual #95                 // Method getMethods:(Ljava/lang/Class;)[Ljava/lang/reflect/Method;
     124: astore        8
     126: iconst_0
     127: istore        9
     129: iload         9
     131: aload         8
     133: arraylength
     134: if_icmpge     274
     137: aload         6
     139: aload         8
     141: iload         9
     143: aaload
     144: invokestatic  #101                // Method org/springframework/cglib/core/MethodWrapper.create:(Ljava/lang/reflect/Method;)Ljava/lang/Object;
     147: invokeinterface #107,  2          // InterfaceMethod java/util/Set.add:(Ljava/lang/Object;)Z
     152: ifeq          268
     155: aload         8
     157: iload         9
     159: aaload
     160: invokestatic  #113                // Method org/springframework/cglib/core/ReflectUtils.getMethodInfo:(Ljava/lang/reflect/Member;)Lorg/springframework/cglib/core/MethodInfo;
     163: astore        10
     165: iconst_1
     166: istore        11
     168: aload         10
     170: invokevirtual #119                // Method org/springframework/cglib/core/MethodInfo.getModifiers:()I
     173: sipush        128
     176: iand
     177: sipush        128
     180: if_icmpne     191
     183: iload         11
     185: sipush        128
     188: ior
     189: istore        11
     191: aload_0
     192: aload         10
     194: iload         11
     196: invokestatic  #122                // Method org/springframework/cglib/core/EmitUtils.begin_method:(Lorg/springframework/cglib/core/ClassEmitter;Lorg/springframework/cglib/core/MethodInfo;I)Lorg/springframework/cglib/core/CodeEmitter;
     199: astore        5
     201: aload         5
     203: invokevirtual #70                 // Method org/springframework/cglib/core/CodeEmitter.load_this:()V
     206: aload         5
     208: ldc           #9                  // String CGLIB$DELEGATES
     210: invokevirtual #125                // Method org/springframework/cglib/core/CodeEmitter.getfield:(Ljava/lang/String;)V
     213: aload         5
     215: aload         4
     217: ifnull        228
     220: aload         4
     222: iload         7
     224: iaload
     225: goto          230
     228: iload         7
     230: invokevirtual #128                // Method org/springframework/cglib/core/CodeEmitter.aaload:(I)V
     233: aload         5
     235: aload         10
     237: invokevirtual #132                // Method org/springframework/cglib/core/MethodInfo.getClassInfo:()Lorg/springframework/cglib/core/ClassInfo;
     240: invokevirtual #138                // Method org/springframework/cglib/core/ClassInfo.getType:()Lorg/springframework/asm/Type;
     243: invokevirtual #142                // Method org/springframework/cglib/core/CodeEmitter.checkcast:(Lorg/springframework/asm/Type;)V
     246: aload         5
     248: invokevirtual #145                // Method org/springframework/cglib/core/CodeEmitter.load_args:()V
     251: aload         5
     253: aload         10
     255: invokevirtual #149                // Method org/springframework/cglib/core/CodeEmitter.invoke:(Lorg/springframework/cglib/core/MethodInfo;)V
     258: aload         5
     260: invokevirtual #84                 // Method org/springframework/cglib/core/CodeEmitter.return_value:()V
     263: aload         5
     265: invokevirtual #87                 // Method org/springframework/cglib/core/CodeEmitter.end_method:()V
     268: iinc          9, 1
     271: goto          129
     274: iinc          7, 1
     277: goto          109
     280: aload_0
     281: invokevirtual #152                // Method end_class:()V
     284: return

  protected java.lang.Class[] getInterfaces(java.lang.Class[]);
    Code:
       0: aload_1
       1: areturn

  protected java.lang.reflect.Method[] getMethods(java.lang.Class);
    Code:
       0: aload_1
       1: invokevirtual #178                // Method java/lang/Class.getMethods:()[Ljava/lang/reflect/Method;
       4: areturn

  static {};
    Code:
       0: ldc           #183                // String Object[]
       2: invokestatic  #187                // Method org/springframework/cglib/core/TypeUtils.parseConstructor:(Ljava/lang/String;)Lorg/springframework/cglib/core/Signature;
       5: putstatic     #60                 // Field CSTRUCT_OBJECT_ARRAY:Lorg/springframework/cglib/core/Signature;
       8: ldc           #189                // String org.springframework.cglib.proxy.Mixin
      10: invokestatic  #193                // Method org/springframework/cglib/core/TypeUtils.parseType:(Ljava/lang/String;)Lorg/springframework/asm/Type;
      13: putstatic     #21                 // Field MIXIN:Lorg/springframework/asm/Type;
      16: new           #195                // class org/springframework/cglib/core/Signature
      19: dup
      20: ldc           #197                // String newInstance
      22: getstatic     #21                 // Field MIXIN:Lorg/springframework/asm/Type;
      25: iconst_1
      26: anewarray     #199                // class org/springframework/asm/Type
      29: dup
      30: iconst_0
      31: getstatic     #54                 // Field org/springframework/cglib/core/Constants.TYPE_OBJECT_ARRAY:Lorg/springframework/asm/Type;
      34: aastore
      35: invokespecial #202                // Method org/springframework/cglib/core/Signature."<init>":(Ljava/lang/String;Lorg/springframework/asm/Type;[Lorg/springframework/asm/Type;)V
      38: putstatic     #45                 // Field NEW_INSTANCE:Lorg/springframework/cglib/core/Signature;
      41: return
}
