Compiled from "InterceptedInvocation.java"
class org.mockito.internal.creation.bytebuddy.InterceptedInvocation implements org.mockito.invocation.Invocation,org.mockito.internal.exceptions.VerificationAwareInvocation {
  private static final long serialVersionUID;

  private final java.lang.Object mock;

  private final org.mockito.internal.invocation.MockitoMethod mockitoMethod;

  private final java.lang.Object[] arguments;

  private final java.lang.Object[] rawArguments;

  private final org.mockito.internal.creation.bytebuddy.InterceptedInvocation$SuperMethod superMethod;

  private final int sequenceNumber;

  private final org.mockito.invocation.Location location;

  private boolean verified;

  private boolean isIgnoredForVerification;

  private org.mockito.invocation.StubInfo stubInfo;

  public org.mockito.internal.creation.bytebuddy.InterceptedInvocation(java.lang.Object, org.mockito.internal.invocation.MockitoMethod, java.lang.Object[], org.mockito.internal.creation.bytebuddy.InterceptedInvocation$SuperMethod, int);
    Code:
       0: aload_0
       1: invokespecial #1                  // Method java/lang/Object."<init>":()V
       4: aload_0
       5: aload_1
       6: putfield      #2                  // Field mock:Ljava/lang/Object;
       9: aload_0
      10: aload_2
      11: putfield      #3                  // Field mockitoMethod:Lorg/mockito/internal/invocation/MockitoMethod;
      14: aload_0
      15: aload_2
      16: invokeinterface #4,  1            // InterfaceMethod org/mockito/internal/invocation/MockitoMethod.isVarArgs:()Z
      21: aload_3
      22: invokestatic  #5                  // Method org/mockito/internal/invocation/ArgumentsProcessor.expandVarArgs:(Z[Ljava/lang/Object;)[Ljava/lang/Object;
      25: putfield      #6                  // Field arguments:[Ljava/lang/Object;
      28: aload_0
      29: aload_3
      30: putfield      #7                  // Field rawArguments:[Ljava/lang/Object;
      33: aload_0
      34: aload         4
      36: putfield      #8                  // Field superMethod:Lorg/mockito/internal/creation/bytebuddy/InterceptedInvocation$SuperMethod;
      39: aload_0
      40: iload         5
      42: putfield      #9                  // Field sequenceNumber:I
      45: aload_0
      46: new           #10                 // class org/mockito/internal/debugging/LocationImpl
      49: dup
      50: invokespecial #11                 // Method org/mockito/internal/debugging/LocationImpl."<init>":()V
      53: putfield      #12                 // Field location:Lorg/mockito/invocation/Location;
      56: return

  public boolean isVerified();
    Code:
       0: aload_0
       1: getfield      #13                 // Field verified:Z
       4: ifne          14
       7: aload_0
       8: getfield      #14                 // Field isIgnoredForVerification:Z
      11: ifeq          18
      14: iconst_1
      15: goto          19
      18: iconst_0
      19: ireturn

  public int getSequenceNumber();
    Code:
       0: aload_0
       1: getfield      #9                  // Field sequenceNumber:I
       4: ireturn

  public org.mockito.invocation.Location getLocation();
    Code:
       0: aload_0
       1: getfield      #12                 // Field location:Lorg/mockito/invocation/Location;
       4: areturn

  public java.lang.Object[] getRawArguments();
    Code:
       0: aload_0
       1: getfield      #7                  // Field rawArguments:[Ljava/lang/Object;
       4: areturn

  public java.lang.Class<?> getRawReturnType();
    Code:
       0: aload_0
       1: getfield      #3                  // Field mockitoMethod:Lorg/mockito/internal/invocation/MockitoMethod;
       4: invokeinterface #15,  1           // InterfaceMethod org/mockito/internal/invocation/MockitoMethod.getReturnType:()Ljava/lang/Class;
       9: areturn

  public void markVerified();
    Code:
       0: aload_0
       1: iconst_1
       2: putfield      #13                 // Field verified:Z
       5: return

  public org.mockito.invocation.StubInfo stubInfo();
    Code:
       0: aload_0
       1: getfield      #16                 // Field stubInfo:Lorg/mockito/invocation/StubInfo;
       4: areturn

  public void markStubbed(org.mockito.invocation.StubInfo);
    Code:
       0: aload_0
       1: aload_1
       2: putfield      #16                 // Field stubInfo:Lorg/mockito/invocation/StubInfo;
       5: return

  public boolean isIgnoredForVerification();
    Code:
       0: aload_0
       1: getfield      #14                 // Field isIgnoredForVerification:Z
       4: ireturn

  public void ignoreForVerification();
    Code:
       0: aload_0
       1: iconst_1
       2: putfield      #14                 // Field isIgnoredForVerification:Z
       5: return

  public java.lang.Object getMock();
    Code:
       0: aload_0
       1: getfield      #2                  // Field mock:Ljava/lang/Object;
       4: areturn

  public java.lang.reflect.Method getMethod();
    Code:
       0: aload_0
       1: getfield      #3                  // Field mockitoMethod:Lorg/mockito/internal/invocation/MockitoMethod;
       4: invokeinterface #17,  1           // InterfaceMethod org/mockito/internal/invocation/MockitoMethod.getJavaMethod:()Ljava/lang/reflect/Method;
       9: areturn

  public java.lang.Object[] getArguments();
    Code:
       0: aload_0
       1: getfield      #6                  // Field arguments:[Ljava/lang/Object;
       4: areturn

  public <T> T getArgument(int);
    Code:
       0: aload_0
       1: getfield      #6                  // Field arguments:[Ljava/lang/Object;
       4: iload_1
       5: aaload
       6: areturn

  public java.lang.Object callRealMethod() throws java.lang.Throwable;
    Code:
       0: aload_0
       1: getfield      #8                  // Field superMethod:Lorg/mockito/internal/creation/bytebuddy/InterceptedInvocation$SuperMethod;
       4: invokeinterface #18,  1           // InterfaceMethod org/mockito/internal/creation/bytebuddy/InterceptedInvocation$SuperMethod.isInvokable:()Z
       9: ifne          16
      12: invokestatic  #19                 // Method org/mockito/internal/exceptions/Reporter.cannotCallAbstractRealMethod:()Lorg/mockito/exceptions/base/MockitoException;
      15: athrow
      16: aload_0
      17: getfield      #8                  // Field superMethod:Lorg/mockito/internal/creation/bytebuddy/InterceptedInvocation$SuperMethod;
      20: invokeinterface #20,  1           // InterfaceMethod org/mockito/internal/creation/bytebuddy/InterceptedInvocation$SuperMethod.invoke:()Ljava/lang/Object;
      25: areturn

  public int hashCode();
    Code:
       0: iconst_1
       1: ireturn

  public boolean equals(java.lang.Object);
    Code:
       0: aload_1
       1: ifnull        18
       4: aload_1
       5: invokevirtual #21                 // Method java/lang/Object.getClass:()Ljava/lang/Class;
       8: aload_0
       9: invokevirtual #21                 // Method java/lang/Object.getClass:()Ljava/lang/Class;
      12: invokevirtual #22                 // Method java/lang/Object.equals:(Ljava/lang/Object;)Z
      15: ifne          20
      18: iconst_0
      19: ireturn
      20: aload_1
      21: checkcast     #23                 // class org/mockito/internal/creation/bytebuddy/InterceptedInvocation
      24: astore_2
      25: aload_0
      26: getfield      #2                  // Field mock:Ljava/lang/Object;
      29: aload_2
      30: getfield      #2                  // Field mock:Ljava/lang/Object;
      33: invokevirtual #22                 // Method java/lang/Object.equals:(Ljava/lang/Object;)Z
      36: ifeq          68
      39: aload_0
      40: getfield      #3                  // Field mockitoMethod:Lorg/mockito/internal/invocation/MockitoMethod;
      43: aload_2
      44: getfield      #3                  // Field mockitoMethod:Lorg/mockito/internal/invocation/MockitoMethod;
      47: invokevirtual #22                 // Method java/lang/Object.equals:(Ljava/lang/Object;)Z
      50: ifeq          68
      53: aload_0
      54: aload_2
      55: getfield      #6                  // Field arguments:[Ljava/lang/Object;
      58: invokespecial #24                 // Method equalArguments:([Ljava/lang/Object;)Z
      61: ifeq          68
      64: iconst_1
      65: goto          69
      68: iconst_0
      69: ireturn

  private boolean equalArguments(java.lang.Object[]);
    Code:
       0: aload_1
       1: aload_0
       2: getfield      #6                  // Field arguments:[Ljava/lang/Object;
       5: invokestatic  #25                 // Method java/util/Arrays.equals:([Ljava/lang/Object;[Ljava/lang/Object;)Z
       8: ireturn

  public java.lang.String toString();
    Code:
       0: new           #26                 // class org/mockito/internal/reporting/PrintSettings
       3: dup
       4: invokespecial #27                 // Method org/mockito/internal/reporting/PrintSettings."<init>":()V
       7: aload_0
       8: invokevirtual #28                 // Method getArguments:()[Ljava/lang/Object;
      11: invokestatic  #29                 // Method org/mockito/internal/invocation/ArgumentsProcessor.argumentsToMatchers:([Ljava/lang/Object;)Ljava/util/List;
      14: aload_0
      15: invokevirtual #30                 // Method org/mockito/internal/reporting/PrintSettings.print:(Ljava/util/List;Lorg/mockito/invocation/Invocation;)Ljava/lang/String;
      18: areturn
}
