Compiled from "AbstractMapBasedMultimap.java"
class com.google.common.collect.AbstractMapBasedMultimap$1 extends com.google.common.collect.AbstractMapBasedMultimap<K, V>.Itr<V> {
  final com.google.common.collect.AbstractMapBasedMultimap this$0;

  com.google.common.collect.AbstractMapBasedMultimap$1(com.google.common.collect.AbstractMapBasedMultimap);
    Code:
       0: aload_0
       1: aload_1
       2: putfield      #1                  // Field this$0:Lcom/google/common/collect/AbstractMapBasedMultimap;
       5: aload_0
       6: aload_1
       7: invokespecial #2                  // Method com/google/common/collect/AbstractMapBasedMultimap$Itr."<init>":(Lcom/google/common/collect/AbstractMapBasedMultimap;)V
      10: return

  V output(K, V);
    Code:
       0: aload_2
       1: areturn
}
