Compiled from "GuildRoleRevokeRequest.kt"
public final class love.forte.simbot.kaiheila.api.guild.role.GuildRoleRevokeRequest extends love.forte.simbot.kaiheila.api.KaiheilaPostRequest<love.forte.simbot.kaiheila.api.guild.role.UserRoleOperated> {
  public static final love.forte.simbot.kaiheila.api.guild.role.GuildRoleRevokeRequest$Key Key;

  private final love.forte.simbot.ID guildId;

  private final love.forte.simbot.ID roleId;

  private final love.forte.simbot.ID userId;

  public love.forte.simbot.kaiheila.api.guild.role.GuildRoleRevokeRequest(love.forte.simbot.ID, love.forte.simbot.ID, love.forte.simbot.ID);
    Code:
       0: aload_1
       1: ldc           #12                 // String guildId
       3: invokestatic  #18                 // Method kotlin/jvm/internal/Intrinsics.checkNotNullParameter:(Ljava/lang/Object;Ljava/lang/String;)V
       6: aload_2
       7: ldc           #19                 // String roleId
       9: invokestatic  #18                 // Method kotlin/jvm/internal/Intrinsics.checkNotNullParameter:(Ljava/lang/Object;Ljava/lang/String;)V
      12: aload_3
      13: ldc           #20                 // String userId
      15: invokestatic  #18                 // Method kotlin/jvm/internal/Intrinsics.checkNotNullParameter:(Ljava/lang/Object;Ljava/lang/String;)V
      18: aload_0
      19: iconst_0
      20: iconst_1
      21: aconst_null
      22: invokespecial #23                 // Method love/forte/simbot/kaiheila/api/KaiheilaPostRequest."<init>":(ZILkotlin/jvm/internal/DefaultConstructorMarker;)V
      25: aload_0
      26: aload_1
      27: putfield      #26                 // Field guildId:Llove/forte/simbot/ID;
      30: aload_0
      31: aload_2
      32: putfield      #28                 // Field roleId:Llove/forte/simbot/ID;
      35: aload_0
      36: aload_3
      37: putfield      #30                 // Field userId:Llove/forte/simbot/ID;
      40: return

  public kotlinx.serialization.DeserializationStrategy<? extends love.forte.simbot.kaiheila.api.guild.role.UserRoleOperated> getResultDeserializer();
    Code:
       0: getstatic     #41                 // Field love/forte/simbot/kaiheila/api/guild/role/UserRoleOperated.Companion:Llove/forte/simbot/kaiheila/api/guild/role/UserRoleOperated$Companion;
       3: invokevirtual #47                 // Method love/forte/simbot/kaiheila/api/guild/role/UserRoleOperated$Companion.serializer:()Lkotlinx/serialization/KSerializer;
       6: checkcast     #49                 // class kotlinx/serialization/DeserializationStrategy
       9: areturn

  protected java.util.List<java.lang.String> getApiPaths();
    Code:
       0: getstatic     #56                 // Field Key:Llove/forte/simbot/kaiheila/api/guild/role/GuildRoleRevokeRequest$Key;
       3: invokevirtual #61                 // Method love/forte/simbot/kaiheila/api/guild/role/GuildRoleRevokeRequest$Key.getApiPathList:()Ljava/util/List;
       6: areturn

  protected java.lang.Object createBody();
    Code:
       0: new           #65                 // class love/forte/simbot/kaiheila/api/guild/role/GuildRoleRevokeRequest$Body
       3: dup
       4: aload_0
       5: getfield      #26                 // Field guildId:Llove/forte/simbot/ID;
       8: aload_0
       9: getfield      #28                 // Field roleId:Llove/forte/simbot/ID;
      12: aload_0
      13: getfield      #30                 // Field userId:Llove/forte/simbot/ID;
      16: invokespecial #67                 // Method love/forte/simbot/kaiheila/api/guild/role/GuildRoleRevokeRequest$Body."<init>":(Llove/forte/simbot/ID;Llove/forte/simbot/ID;Llove/forte/simbot/ID;)V
      19: areturn

  static {};
    Code:
       0: new           #58                 // class love/forte/simbot/kaiheila/api/guild/role/GuildRoleRevokeRequest$Key
       3: dup
       4: aconst_null
       5: invokespecial #72                 // Method love/forte/simbot/kaiheila/api/guild/role/GuildRoleRevokeRequest$Key."<init>":(Lkotlin/jvm/internal/DefaultConstructorMarker;)V
       8: putstatic     #56                 // Field Key:Llove/forte/simbot/kaiheila/api/guild/role/GuildRoleRevokeRequest$Key;
      11: return
}
