Compiled from "ApiManHttpGatewayHandler.java"
class io.fabric8.gateway.apiman.ApiManHttpGatewayHandler$2 implements io.apiman.gateway.engine.async.IAsyncHandler<io.apiman.gateway.engine.io.ISignalWriteStream> {
  final org.vertx.java.core.http.HttpServerRequest val$request;

  final io.fabric8.gateway.apiman.ApiManHttpGatewayHandler this$0;

  io.fabric8.gateway.apiman.ApiManHttpGatewayHandler$2(io.fabric8.gateway.apiman.ApiManHttpGatewayHandler, org.vertx.java.core.http.HttpServerRequest);
    Code:
       0: aload_0
       1: aload_1
       2: putfield      #1                  // Field this$0:Lio/fabric8/gateway/apiman/ApiManHttpGatewayHandler;
       5: aload_0
       6: aload_2
       7: putfield      #2                  // Field val$request:Lorg/vertx/java/core/http/HttpServerRequest;
      10: aload_0
      11: invokespecial #3                  // Method java/lang/Object."<init>":()V
      14: return

  public void handle(io.apiman.gateway.engine.io.ISignalWriteStream);
    Code:
       0: aload_0
       1: getfield      #2                  // Field val$request:Lorg/vertx/java/core/http/HttpServerRequest;
       4: new           #4                  // class io/fabric8/gateway/apiman/ApiManHttpGatewayHandler$2$1
       7: dup
       8: aload_0
       9: aload_1
      10: invokespecial #5                  // Method io/fabric8/gateway/apiman/ApiManHttpGatewayHandler$2$1."<init>":(Lio/fabric8/gateway/apiman/ApiManHttpGatewayHandler$2;Lio/apiman/gateway/engine/io/ISignalWriteStream;)V
      13: invokeinterface #6,  2            // InterfaceMethod org/vertx/java/core/http/HttpServerRequest.dataHandler:(Lorg/vertx/java/core/Handler;)Ljava/lang/Object;
      18: pop
      19: aload_1
      20: invokeinterface #7,  1            // InterfaceMethod io/apiman/gateway/engine/io/ISignalWriteStream.end:()V
      25: return

  public void handle(java.lang.Object);
    Code:
       0: aload_0
       1: aload_1
       2: checkcast     #8                  // class io/apiman/gateway/engine/io/ISignalWriteStream
       5: invokevirtual #9                  // Method handle:(Lio/apiman/gateway/engine/io/ISignalWriteStream;)V
       8: return
}
