Compiled from "ESServiceMappingStorage.java"
public class io.fabric8.gateway.apiman.ESServiceMappingStorage implements io.fabric8.gateway.apiman.ServiceMappingStorage {
  private java.util.Map<java.lang.String, java.lang.String> config;

  private io.searchbox.client.JestClient esClient;

  public io.fabric8.gateway.apiman.ESServiceMappingStorage(java.util.Map<java.lang.String, java.lang.String>);
    Code:
       0: aload_0
       1: invokespecial #1                  // Method java/lang/Object."<init>":()V
       4: aload_0
       5: aload_1
       6: putfield      #2                  // Field config:Ljava/util/Map;
       9: return

  public synchronized io.searchbox.client.JestClient getClient();
    Code:
       0: aload_0
       1: getfield      #3                  // Field esClient:Lio/searchbox/client/JestClient;
       4: ifnonnull     18
       7: aload_0
       8: aload_0
       9: getfield      #2                  // Field config:Ljava/util/Map;
      12: invokestatic  #4                  // Method io/apiman/gateway/engine/es/ESClientFactory.createClient:(Ljava/util/Map;)Lio/searchbox/client/JestClient;
      15: putfield      #3                  // Field esClient:Lio/searchbox/client/JestClient;
      18: aload_0
      19: getfield      #3                  // Field esClient:Lio/searchbox/client/JestClient;
      22: areturn

  public void put(java.lang.String, io.fabric8.gateway.api.apimanager.ServiceMapping, io.apiman.gateway.engine.async.IAsyncResultHandler<java.lang.Void>);
    Code:
       0: aload_0
       1: aload_1
       2: invokespecial #5                  // Method idFromPath:(Ljava/lang/String;)Ljava/lang/String;
       5: astore        4
       7: new           #6                  // class io/searchbox/core/Index$Builder
      10: dup
      11: aload_2
      12: invokespecial #7                  // Method io/searchbox/core/Index$Builder."<init>":(Ljava/lang/Object;)V
      15: iconst_0
      16: invokevirtual #8                  // Method io/searchbox/core/Index$Builder.refresh:(Z)Ljava/lang/Object;
      19: checkcast     #6                  // class io/searchbox/core/Index$Builder
      22: ldc           #9                  // String apiman_gateway
      24: invokevirtual #10                 // Method io/searchbox/core/Index$Builder.index:(Ljava/lang/String;)Ljava/lang/Object;
      27: checkcast     #6                  // class io/searchbox/core/Index$Builder
      30: ldc           #11                 // String f8_service_mapping
      32: invokevirtual #12                 // Method io/searchbox/core/Index$Builder.type:(Ljava/lang/String;)Ljava/lang/Object;
      35: checkcast     #6                  // class io/searchbox/core/Index$Builder
      38: aload         4
      40: invokevirtual #13                 // Method io/searchbox/core/Index$Builder.id:(Ljava/lang/String;)Ljava/lang/Object;
      43: checkcast     #6                  // class io/searchbox/core/Index$Builder
      46: invokevirtual #14                 // Method io/searchbox/core/Index$Builder.build:()Lio/searchbox/core/Index;
      49: astore        5
      51: aload_0
      52: invokevirtual #15                 // Method getClient:()Lio/searchbox/client/JestClient;
      55: aload         5
      57: new           #16                 // class io/fabric8/gateway/apiman/ESServiceMappingStorage$1
      60: dup
      61: aload_0
      62: aload_3
      63: aload_1
      64: invokespecial #17                 // Method io/fabric8/gateway/apiman/ESServiceMappingStorage$1."<init>":(Lio/fabric8/gateway/apiman/ESServiceMappingStorage;Lio/apiman/gateway/engine/async/IAsyncResultHandler;Ljava/lang/String;)V
      67: invokeinterface #18,  3           // InterfaceMethod io/searchbox/client/JestClient.executeAsync:(Lio/searchbox/action/Action;Lio/searchbox/client/JestResultHandler;)V
      72: goto          117
      75: astore        6
      77: aload_3
      78: new           #22                 // class java/lang/Exception
      81: dup
      82: new           #23                 // class java/lang/StringBuilder
      85: dup
      86: invokespecial #24                 // Method java/lang/StringBuilder."<init>":()V
      89: ldc           #25                 // String Error storing service mapping for path:
      91: invokevirtual #26                 // Method java/lang/StringBuilder.append:(Ljava/lang/String;)Ljava/lang/StringBuilder;
      94: aload_1
      95: invokevirtual #26                 // Method java/lang/StringBuilder.append:(Ljava/lang/String;)Ljava/lang/StringBuilder;
      98: invokevirtual #27                 // Method java/lang/StringBuilder.toString:()Ljava/lang/String;
     101: aload         6
     103: invokespecial #28                 // Method java/lang/Exception."<init>":(Ljava/lang/String;Ljava/lang/Throwable;)V
     106: ldc_w         #29                 // class java/lang/Void
     109: invokestatic  #30                 // Method io/apiman/gateway/engine/async/AsyncResultImpl.create:(Ljava/lang/Throwable;Ljava/lang/Class;)Lio/apiman/gateway/engine/async/AsyncResultImpl;
     112: invokeinterface #31,  2           // InterfaceMethod io/apiman/gateway/engine/async/IAsyncResultHandler.handle:(Ljava/lang/Object;)V
     117: return
    Exception table:
       from    to  target type
          51    72    75   Class java/util/concurrent/ExecutionException
          51    72    75   Class java/lang/InterruptedException
          51    72    75   Class java/io/IOException

  private java.lang.String idFromPath(java.lang.String);
    Code:
       0: aload_1
       1: invokevirtual #32                 // Method java/lang/String.getBytes:()[B
       4: invokestatic  #33                 // Method org/apache/commons/codec/binary/Base64.encodeBase64String:([B)Ljava/lang/String;
       7: areturn

  public io.fabric8.gateway.api.apimanager.ServiceMapping get(java.lang.String);
    Code:
       0: aload_0
       1: aload_1
       2: invokespecial #5                  // Method idFromPath:(Ljava/lang/String;)Ljava/lang/String;
       5: astore_2
       6: new           #34                 // class io/searchbox/core/Get$Builder
       9: dup
      10: ldc           #9                  // String apiman_gateway
      12: aload_2
      13: invokespecial #35                 // Method io/searchbox/core/Get$Builder."<init>":(Ljava/lang/String;Ljava/lang/String;)V
      16: ldc           #11                 // String f8_service_mapping
      18: invokevirtual #36                 // Method io/searchbox/core/Get$Builder.type:(Ljava/lang/String;)Ljava/lang/Object;
      21: checkcast     #34                 // class io/searchbox/core/Get$Builder
      24: invokevirtual #37                 // Method io/searchbox/core/Get$Builder.build:()Lio/searchbox/core/Get;
      27: astore_3
      28: aload_0
      29: invokevirtual #15                 // Method getClient:()Lio/searchbox/client/JestClient;
      32: aload_3
      33: invokeinterface #38,  2           // InterfaceMethod io/searchbox/client/JestClient.execute:(Lio/searchbox/action/Action;)Lio/searchbox/client/JestResult;
      38: astore        4
      40: aload         4
      42: invokevirtual #39                 // Method io/searchbox/client/JestResult.isSucceeded:()Z
      45: ifeq          60
      48: aload         4
      50: ldc_w         #40                 // class io/fabric8/gateway/api/apimanager/ServiceMapping
      53: invokevirtual #41                 // Method io/searchbox/client/JestResult.getSourceAsObject:(Ljava/lang/Class;)Ljava/lang/Object;
      56: checkcast     #40                 // class io/fabric8/gateway/api/apimanager/ServiceMapping
      59: areturn
      60: aconst_null
      61: areturn
      62: astore        4
      64: aconst_null
      65: areturn
    Exception table:
       from    to  target type
          28    59    62   Class java/lang/Exception
          60    61    62   Class java/lang/Exception

  public void remove(java.lang.String, io.apiman.gateway.engine.async.IAsyncResultHandler<java.lang.Void>);
    Code:
       0: aload_0
       1: aload_1
       2: invokespecial #5                  // Method idFromPath:(Ljava/lang/String;)Ljava/lang/String;
       5: astore_3
       6: new           #42                 // class io/searchbox/core/Delete$Builder
       9: dup
      10: aload_3
      11: invokespecial #43                 // Method io/searchbox/core/Delete$Builder."<init>":(Ljava/lang/String;)V
      14: ldc           #9                  // String apiman_gateway
      16: invokevirtual #44                 // Method io/searchbox/core/Delete$Builder.index:(Ljava/lang/String;)Ljava/lang/Object;
      19: checkcast     #42                 // class io/searchbox/core/Delete$Builder
      22: ldc           #11                 // String f8_service_mapping
      24: invokevirtual #45                 // Method io/searchbox/core/Delete$Builder.type:(Ljava/lang/String;)Ljava/lang/Object;
      27: checkcast     #42                 // class io/searchbox/core/Delete$Builder
      30: invokevirtual #46                 // Method io/searchbox/core/Delete$Builder.build:()Lio/searchbox/core/Delete;
      33: astore        4
      35: aload_0
      36: invokevirtual #15                 // Method getClient:()Lio/searchbox/client/JestClient;
      39: aload         4
      41: new           #47                 // class io/fabric8/gateway/apiman/ESServiceMappingStorage$2
      44: dup
      45: aload_0
      46: aload_2
      47: aload_1
      48: invokespecial #48                 // Method io/fabric8/gateway/apiman/ESServiceMappingStorage$2."<init>":(Lio/fabric8/gateway/apiman/ESServiceMappingStorage;Lio/apiman/gateway/engine/async/IAsyncResultHandler;Ljava/lang/String;)V
      51: invokeinterface #18,  3           // InterfaceMethod io/searchbox/client/JestClient.executeAsync:(Lio/searchbox/action/Action;Lio/searchbox/client/JestResultHandler;)V
      56: goto          101
      59: astore        5
      61: aload_2
      62: new           #22                 // class java/lang/Exception
      65: dup
      66: new           #23                 // class java/lang/StringBuilder
      69: dup
      70: invokespecial #24                 // Method java/lang/StringBuilder."<init>":()V
      73: ldc           #49                 // String Error removing mapping at path:
      75: invokevirtual #26                 // Method java/lang/StringBuilder.append:(Ljava/lang/String;)Ljava/lang/StringBuilder;
      78: aload_1
      79: invokevirtual #26                 // Method java/lang/StringBuilder.append:(Ljava/lang/String;)Ljava/lang/StringBuilder;
      82: invokevirtual #27                 // Method java/lang/StringBuilder.toString:()Ljava/lang/String;
      85: aload         5
      87: invokespecial #28                 // Method java/lang/Exception."<init>":(Ljava/lang/String;Ljava/lang/Throwable;)V
      90: ldc_w         #29                 // class java/lang/Void
      93: invokestatic  #30                 // Method io/apiman/gateway/engine/async/AsyncResultImpl.create:(Ljava/lang/Throwable;Ljava/lang/Class;)Lio/apiman/gateway/engine/async/AsyncResultImpl;
      96: invokeinterface #31,  2           // InterfaceMethod io/apiman/gateway/engine/async/IAsyncResultHandler.handle:(Ljava/lang/Object;)V
     101: return
    Exception table:
       from    to  target type
          35    56    59   Class java/util/concurrent/ExecutionException
          35    56    59   Class java/lang/InterruptedException
          35    56    59   Class java/io/IOException
}
