Compiled from "Pages.java"
public class net.thucydides.core.pages.Pages implements java.io.Serializable {
  private static final long serialVersionUID;

  private transient org.openqa.selenium.WebDriver driver;

  private static final org.slf4j.Logger LOGGER;

  private java.lang.String defaultBaseUrl;

  private final net.thucydides.core.webdriver.Configuration configuration;

  private net.thucydides.core.webdriver.WebdriverProxyFactory proxyFactory;

  private transient boolean usePreviousPage;

  net.serenitybdd.core.pages.PageObject currentPage;

  public net.thucydides.core.pages.Pages(net.thucydides.core.webdriver.Configuration);
    Code:
       0: aload_0
       1: invokespecial #1                  // Method java/lang/Object."<init>":()V
       4: aload_0
       5: iconst_0
       6: putfield      #2                  // Field usePreviousPage:Z
       9: aload_0
      10: aconst_null
      11: putfield      #3                  // Field currentPage:Lnet/serenitybdd/core/pages/PageObject;
      14: aload_0
      15: aload_1
      16: putfield      #4                  // Field configuration:Lnet/thucydides/core/webdriver/Configuration;
      19: aload_0
      20: invokestatic  #5                  // Method net/thucydides/core/webdriver/WebdriverProxyFactory.getFactory:()Lnet/thucydides/core/webdriver/WebdriverProxyFactory;
      23: putfield      #6                  // Field proxyFactory:Lnet/thucydides/core/webdriver/WebdriverProxyFactory;
      26: return

  public net.thucydides.core.pages.Pages();
    Code:
       0: aload_0
       1: invokestatic  #7                  // Method net/serenitybdd/core/environment/ConfiguredEnvironment.getConfiguration:()Lnet/thucydides/core/webdriver/Configuration;
       4: invokespecial #8                  // Method "<init>":(Lnet/thucydides/core/webdriver/Configuration;)V
       7: return

  public net.thucydides.core.pages.Pages(org.openqa.selenium.WebDriver);
    Code:
       0: aload_0
       1: invokestatic  #7                  // Method net/serenitybdd/core/environment/ConfiguredEnvironment.getConfiguration:()Lnet/thucydides/core/webdriver/Configuration;
       4: invokespecial #8                  // Method "<init>":(Lnet/thucydides/core/webdriver/Configuration;)V
       7: aload_0
       8: aload_1
       9: putfield      #9                  // Field driver:Lorg/openqa/selenium/WebDriver;
      12: return

  public net.thucydides.core.pages.Pages(org.openqa.selenium.WebDriver, net.thucydides.core.webdriver.Configuration);
    Code:
       0: aload_0
       1: aload_2
       2: invokespecial #8                  // Method "<init>":(Lnet/thucydides/core/webdriver/Configuration;)V
       5: aload_0
       6: aload_1
       7: putfield      #9                  // Field driver:Lorg/openqa/selenium/WebDriver;
      10: return

  public void setDriver(org.openqa.selenium.WebDriver);
    Code:
       0: aload_0
       1: aload_1
       2: putfield      #9                  // Field driver:Lorg/openqa/selenium/WebDriver;
       5: return

  public org.openqa.selenium.WebDriver getDriver();
    Code:
       0: aload_0
       1: getfield      #9                  // Field driver:Lorg/openqa/selenium/WebDriver;
       4: areturn

  protected net.thucydides.core.webdriver.WebdriverProxyFactory getProxyFactory();
    Code:
       0: aload_0
       1: getfield      #6                  // Field proxyFactory:Lnet/thucydides/core/webdriver/WebdriverProxyFactory;
       4: areturn

  public net.thucydides.core.webdriver.Configuration getConfiguration();
    Code:
       0: aload_0
       1: getfield      #4                  // Field configuration:Lnet/thucydides/core/webdriver/Configuration;
       4: areturn

  public <T extends net.serenitybdd.core.pages.PageObject> T getAt(java.lang.Class<T>);
    Code:
       0: aload_0
       1: aload_1
       2: invokevirtual #10                 // Method getPage:(Ljava/lang/Class;)Lnet/serenitybdd/core/pages/PageObject;
       5: areturn

  public <T extends net.serenitybdd.core.pages.PageObject> T getPage(java.lang.Class<T>);
    Code:
       0: aload_0
       1: aload_1
       2: invokespecial #11                 // Method getCurrentPageOfType:(Ljava/lang/Class;)Lnet/serenitybdd/core/pages/PageObject;
       5: astore_2
       6: aload_2
       7: aload_0
       8: invokevirtual #12                 // Method getDefaultBaseUrl:()Ljava/lang/String;
      11: invokevirtual #13                 // Method net/serenitybdd/core/pages/PageObject.setDefaultBaseUrl:(Ljava/lang/String;)V
      14: aload_2
      15: areturn

  public <T extends net.serenitybdd.core.pages.PageObject> T get(java.lang.Class<T>);
    Code:
       0: aload_0
       1: aload_1
       2: invokespecial #14                 // Method shouldUsePreviousPage:(Ljava/lang/Class;)Z
       5: ifeq          16
       8: aload_0
       9: getfield      #3                  // Field currentPage:Lnet/serenitybdd/core/pages/PageObject;
      12: astore_2
      13: goto          37
      16: aload_0
      17: aload_1
      18: invokespecial #11                 // Method getCurrentPageOfType:(Ljava/lang/Class;)Lnet/serenitybdd/core/pages/PageObject;
      21: astore_3
      22: aload_3
      23: aload_0
      24: invokevirtual #12                 // Method getDefaultBaseUrl:()Ljava/lang/String;
      27: invokevirtual #13                 // Method net/serenitybdd/core/pages/PageObject.setDefaultBaseUrl:(Ljava/lang/String;)V
      30: aload_0
      31: aload_3
      32: invokespecial #15                 // Method cacheCurrentPage:(Lnet/serenitybdd/core/pages/PageObject;)V
      35: aload_3
      36: astore_2
      37: aload_0
      38: iconst_0
      39: putfield      #2                  // Field usePreviousPage:Z
      42: aload_2
      43: areturn

  public <T extends net.serenitybdd.core.pages.PageObject> T currentPageAt(java.lang.Class<T>);
    Code:
       0: aload_0
       1: aload_1
       2: invokespecial #14                 // Method shouldUsePreviousPage:(Ljava/lang/Class;)Z
       5: ifeq          16
       8: aload_0
       9: getfield      #3                  // Field currentPage:Lnet/serenitybdd/core/pages/PageObject;
      12: astore_2
      13: goto          52
      16: aload_0
      17: aload_1
      18: invokespecial #11                 // Method getCurrentPageOfType:(Ljava/lang/Class;)Lnet/serenitybdd/core/pages/PageObject;
      21: astore_3
      22: aload_3
      23: aload_0
      24: invokevirtual #12                 // Method getDefaultBaseUrl:()Ljava/lang/String;
      27: invokevirtual #13                 // Method net/serenitybdd/core/pages/PageObject.setDefaultBaseUrl:(Ljava/lang/String;)V
      30: aload_0
      31: aload_3
      32: invokespecial #16                 // Method openBrowserIfRequiredFor:(Lnet/serenitybdd/core/pages/PageObject;)V
      35: aload_0
      36: aload_1
      37: aload_3
      38: invokespecial #17                 // Method checkUrlPatterns:(Ljava/lang/Class;Lnet/serenitybdd/core/pages/PageObject;)V
      41: aload_0
      42: aload_3
      43: invokespecial #15                 // Method cacheCurrentPage:(Lnet/serenitybdd/core/pages/PageObject;)V
      46: aload_3
      47: astore_2
      48: aload_2
      49: invokevirtual #18                 // Method net/serenitybdd/core/pages/PageObject.addJQuerySupport:()V
      52: aload_0
      53: iconst_0
      54: putfield      #2                  // Field usePreviousPage:Z
      57: aload_2
      58: areturn

  private <T extends net.serenitybdd.core.pages.PageObject> void openBrowserIfRequiredFor(T);
    Code:
       0: aload_0
       1: invokespecial #19                 // Method browserNotOpen:()Z
       4: ifeq          15
       7: aload_0
       8: invokespecial #20                 // Method openHeadlessDriverIfNotOpen:()V
      11: aload_1
      12: invokevirtual #21                 // Method net/serenitybdd/core/pages/PageObject.open:()V
      15: return

  private void openHeadlessDriverIfNotOpen();
    Code:
       0: aload_0
       1: invokespecial #22                 // Method browserIsHeadless:()Z
       4: ifeq          18
       7: aload_0
       8: getfield      #9                  // Field driver:Lorg/openqa/selenium/WebDriver;
      11: ldc           #23                 // String about:blank
      13: invokeinterface #24,  2           // InterfaceMethod org/openqa/selenium/WebDriver.get:(Ljava/lang/String;)V
      18: return

  private boolean browserNotOpen();
    Code:
       0: aload_0
       1: invokevirtual #25                 // Method getDriver:()Lorg/openqa/selenium/WebDriver;
       4: instanceof    #26                 // class net/thucydides/core/webdriver/WebDriverFacade
       7: ifeq          29
      10: aload_0
      11: invokevirtual #25                 // Method getDriver:()Lorg/openqa/selenium/WebDriver;
      14: checkcast     #26                 // class net/thucydides/core/webdriver/WebDriverFacade
      17: invokevirtual #27                 // Method net/thucydides/core/webdriver/WebDriverFacade.isInstantiated:()Z
      20: ifne          27
      23: iconst_1
      24: goto          28
      27: iconst_0
      28: ireturn
      29: aload_0
      30: invokevirtual #25                 // Method getDriver:()Lorg/openqa/selenium/WebDriver;
      33: invokeinterface #28,  1           // InterfaceMethod org/openqa/selenium/WebDriver.getCurrentUrl:()Ljava/lang/String;
      38: invokestatic  #29                 // Method org/apache/commons/lang3/StringUtils.isEmpty:(Ljava/lang/CharSequence;)Z
      41: ireturn

  private boolean browserIsHeadless();
    Code:
       0: aload_0
       1: invokevirtual #25                 // Method getDriver:()Lorg/openqa/selenium/WebDriver;
       4: instanceof    #26                 // class net/thucydides/core/webdriver/WebDriverFacade
       7: ifeq          24
      10: aload_0
      11: invokevirtual #25                 // Method getDriver:()Lorg/openqa/selenium/WebDriver;
      14: checkcast     #26                 // class net/thucydides/core/webdriver/WebDriverFacade
      17: invokevirtual #30                 // Method net/thucydides/core/webdriver/WebDriverFacade.getProxiedDriver:()Lorg/openqa/selenium/WebDriver;
      20: instanceof    #31                 // class org/openqa/selenium/htmlunit/HtmlUnitDriver
      23: ireturn
      24: aload_0
      25: invokevirtual #25                 // Method getDriver:()Lorg/openqa/selenium/WebDriver;
      28: instanceof    #31                 // class org/openqa/selenium/htmlunit/HtmlUnitDriver
      31: ireturn

  private <T extends net.serenitybdd.core.pages.PageObject> void checkUrlPatterns(java.lang.Class<T>, T);
    Code:
       0: aload_2
       1: invokevirtual #32                 // Method net/serenitybdd/core/pages/PageObject.matchesAnyUrl:()Z
       4: ifne          30
       7: aload_0
       8: invokevirtual #25                 // Method getDriver:()Lorg/openqa/selenium/WebDriver;
      11: invokeinterface #28,  1           // InterfaceMethod org/openqa/selenium/WebDriver.getCurrentUrl:()Ljava/lang/String;
      16: astore_3
      17: aload_2
      18: aload_3
      19: invokevirtual #33                 // Method net/serenitybdd/core/pages/PageObject.compatibleWithUrl:(Ljava/lang/String;)Z
      22: ifne          30
      25: aload_0
      26: aload_1
      27: invokespecial #34                 // Method thisIsNotThePageYourLookingFor:(Ljava/lang/Class;)V
      30: return

  private <T extends net.serenitybdd.core.pages.PageObject> boolean shouldUsePreviousPage(java.lang.Class<T>);
    Code:
       0: aload_0
       1: getfield      #2                  // Field usePreviousPage:Z
       4: ifne          9
       7: iconst_0
       8: ireturn
       9: aload_0
      10: aload_1
      11: invokespecial #35                 // Method currentPageIsSameTypeAs:(Ljava/lang/Class;)Z
      14: ireturn

  private void cacheCurrentPage(net.serenitybdd.core.pages.PageObject);
    Code:
       0: aload_0
       1: aload_1
       2: putfield      #3                  // Field currentPage:Lnet/serenitybdd/core/pages/PageObject;
       5: return

  private <T extends net.serenitybdd.core.pages.PageObject> boolean currentPageIsSameTypeAs(java.lang.Class<T>);
    Code:
       0: aload_0
       1: getfield      #3                  // Field currentPage:Lnet/serenitybdd/core/pages/PageObject;
       4: ifnull        25
       7: aload_0
       8: getfield      #3                  // Field currentPage:Lnet/serenitybdd/core/pages/PageObject;
      11: invokevirtual #36                 // Method java/lang/Object.getClass:()Ljava/lang/Class;
      14: aload_1
      15: invokevirtual #37                 // Method java/lang/Object.equals:(Ljava/lang/Object;)Z
      18: ifeq          25
      21: iconst_1
      22: goto          26
      25: iconst_0
      26: ireturn

  public boolean isCurrentPageAt(java.lang.Class<? extends net.serenitybdd.core.pages.PageObject>);
    Code:
       0: aload_0
       1: aload_1
       2: invokespecial #11                 // Method getCurrentPageOfType:(Ljava/lang/Class;)Lnet/serenitybdd/core/pages/PageObject;
       5: astore_2
       6: aload_0
       7: invokevirtual #25                 // Method getDriver:()Lorg/openqa/selenium/WebDriver;
      10: invokeinterface #28,  1           // InterfaceMethod org/openqa/selenium/WebDriver.getCurrentUrl:()Ljava/lang/String;
      15: astore_3
      16: aload_2
      17: aload_3
      18: invokevirtual #33                 // Method net/serenitybdd/core/pages/PageObject.compatibleWithUrl:(Ljava/lang/String;)Z
      21: ireturn
      22: astore_2
      23: iconst_0
      24: ireturn
    Exception table:
       from    to  target type
           0    21    22   Class net/thucydides/core/pages/WrongPageError

  private <T extends net.serenitybdd.core.pages.PageObject> T getCurrentPageOfType(java.lang.Class<T>);
    Code:
       0: aconst_null
       1: astore_2
       2: aload_0
       3: aload_1
       4: invokespecial #39                 // Method createFromSimpleConstructor:(Ljava/lang/Class;)Lnet/serenitybdd/core/pages/PageObject;
       7: astore_2
       8: aload_2
       9: ifnonnull     18
      12: aload_0
      13: aload_1
      14: invokespecial #40                 // Method createFromConstructorWithWebdriver:(Ljava/lang/Class;)Lnet/serenitybdd/core/pages/PageObject;
      17: astore_2
      18: aload_0
      19: aload_2
      20: invokespecial #41                 // Method hasPageFactoryProperty:(Ljava/lang/Object;)Z
      23: ifeq          31
      26: aload_0
      27: aload_2
      28: invokespecial #42                 // Method setPageFactory:(Ljava/lang/Object;)V
      31: goto          153
      34: astore_3
      35: getstatic     #44                 // Field LOGGER:Lorg/slf4j/Logger;
      38: ldc           #45                 // String This page object does not appear have a constructor that takes a WebDriver parameter: {} ({})
      40: aload_1
      41: aload_3
      42: invokevirtual #46                 // Method java/lang/NoSuchMethodException.getMessage:()Ljava/lang/String;
      45: invokeinterface #47,  4           // InterfaceMethod org/slf4j/Logger.warn:(Ljava/lang/String;Ljava/lang/Object;Ljava/lang/Object;)V
      50: aload_0
      51: aload_1
      52: ldc           #48                 // String This page object does not appear have a constructor that takes a WebDriver parameter
      54: invokespecial #49                 // Method thisPageObjectLooksDodgy:(Ljava/lang/Class;Ljava/lang/String;)V
      57: goto          153
      60: astore_3
      61: getstatic     #44                 // Field LOGGER:Lorg/slf4j/Logger;
      64: ldc           #51                 // String Failed to instantiate page of type {} ({})
      66: aload_1
      67: aload_3
      68: invokevirtual #52                 // Method java/lang/reflect/InvocationTargetException.getTargetException:()Ljava/lang/Throwable;
      71: invokeinterface #47,  4           // InterfaceMethod org/slf4j/Logger.warn:(Ljava/lang/String;Ljava/lang/Object;Ljava/lang/Object;)V
      76: aload_0
      77: aload_1
      78: new           #53                 // class java/lang/StringBuilder
      81: dup
      82: invokespecial #54                 // Method java/lang/StringBuilder."<init>":()V
      85: ldc           #55                 // String Failed to instantiate page (
      87: invokevirtual #56                 // Method java/lang/StringBuilder.append:(Ljava/lang/String;)Ljava/lang/StringBuilder;
      90: aload_3
      91: invokevirtual #52                 // Method java/lang/reflect/InvocationTargetException.getTargetException:()Ljava/lang/Throwable;
      94: invokevirtual #57                 // Method java/lang/StringBuilder.append:(Ljava/lang/Object;)Ljava/lang/StringBuilder;
      97: ldc           #58                 // String )
      99: invokevirtual #56                 // Method java/lang/StringBuilder.append:(Ljava/lang/String;)Ljava/lang/StringBuilder;
     102: invokevirtual #59                 // Method java/lang/StringBuilder.toString:()Ljava/lang/String;
     105: invokespecial #49                 // Method thisPageObjectLooksDodgy:(Ljava/lang/Class;Ljava/lang/String;)V
     108: goto          153
     111: astore_3
     112: getstatic     #44                 // Field LOGGER:Lorg/slf4j/Logger;
     115: ldc           #51                 // String Failed to instantiate page of type {} ({})
     117: aload_1
     118: aload_3
     119: invokeinterface #47,  4           // InterfaceMethod org/slf4j/Logger.warn:(Ljava/lang/String;Ljava/lang/Object;Ljava/lang/Object;)V
     124: aload_0
     125: aload_1
     126: new           #53                 // class java/lang/StringBuilder
     129: dup
     130: invokespecial #54                 // Method java/lang/StringBuilder."<init>":()V
     133: ldc           #55                 // String Failed to instantiate page (
     135: invokevirtual #56                 // Method java/lang/StringBuilder.append:(Ljava/lang/String;)Ljava/lang/StringBuilder;
     138: aload_3
     139: invokevirtual #57                 // Method java/lang/StringBuilder.append:(Ljava/lang/Object;)Ljava/lang/StringBuilder;
     142: ldc           #58                 // String )
     144: invokevirtual #56                 // Method java/lang/StringBuilder.append:(Ljava/lang/String;)Ljava/lang/StringBuilder;
     147: invokevirtual #59                 // Method java/lang/StringBuilder.toString:()Ljava/lang/String;
     150: invokespecial #49                 // Method thisPageObjectLooksDodgy:(Ljava/lang/Class;Ljava/lang/String;)V
     153: aload_2
     154: areturn
    Exception table:
       from    to  target type
           2    31    34   Class java/lang/NoSuchMethodException
           2    31    60   Class java/lang/reflect/InvocationTargetException
           2    31   111   Class java/lang/Exception

  private <T extends net.serenitybdd.core.pages.PageObject> T createFromSimpleConstructor(java.lang.Class<T>) throws java.lang.IllegalAccessException, java.lang.reflect.InvocationTargetException, java.lang.InstantiationException, java.lang.NoSuchFieldException;
    Code:
       0: aconst_null
       1: astore_2
       2: aload_0
       3: aload_1
       4: invokespecial #61                 // Method hasDefaultConstructor:(Ljava/lang/Class;)Z
       7: ifeq          47
      10: iconst_0
      11: anewarray     #62                 // class java/lang/Class
      14: astore_3
      15: aload_1
      16: aload_3
      17: invokevirtual #63                 // Method java/lang/Class.getConstructor:([Ljava/lang/Class;)Ljava/lang/reflect/Constructor;
      20: astore        4
      22: aload         4
      24: iconst_0
      25: anewarray     #64                 // class java/lang/Object
      28: invokevirtual #65                 // Method java/lang/reflect/Constructor.newInstance:([Ljava/lang/Object;)Ljava/lang/Object;
      31: checkcast     #66                 // class net/serenitybdd/core/pages/PageObject
      34: astore_2
      35: aload_2
      36: aload_0
      37: getfield      #9                  // Field driver:Lorg/openqa/selenium/WebDriver;
      40: invokevirtual #67                 // Method net/serenitybdd/core/pages/PageObject.setDriver:(Lorg/openqa/selenium/WebDriver;)Lnet/serenitybdd/core/pages/PageObject;
      43: pop
      44: goto          102
      47: aload_0
      48: aload_1
      49: invokespecial #68                 // Method hasOuterClassConstructor:(Ljava/lang/Class;)Z
      52: ifeq          102
      55: aload_1
      56: iconst_1
      57: anewarray     #62                 // class java/lang/Class
      60: dup
      61: iconst_0
      62: aload_1
      63: invokevirtual #69                 // Method java/lang/Class.getEnclosingClass:()Ljava/lang/Class;
      66: aastore
      67: invokevirtual #63                 // Method java/lang/Class.getConstructor:([Ljava/lang/Class;)Ljava/lang/reflect/Constructor;
      70: astore_3
      71: aload_3
      72: iconst_1
      73: anewarray     #64                 // class java/lang/Object
      76: dup
      77: iconst_0
      78: aload_1
      79: invokestatic  #70                 // Method net/thucydides/core/steps/EnclosingClass.of:(Ljava/lang/Class;)Lnet/thucydides/core/steps/EnclosingClass;
      82: invokevirtual #71                 // Method net/thucydides/core/steps/EnclosingClass.newInstance:()Ljava/lang/Object;
      85: aastore
      86: invokevirtual #65                 // Method java/lang/reflect/Constructor.newInstance:([Ljava/lang/Object;)Ljava/lang/Object;
      89: checkcast     #66                 // class net/serenitybdd/core/pages/PageObject
      92: astore_2
      93: aload_2
      94: aload_0
      95: getfield      #9                  // Field driver:Lorg/openqa/selenium/WebDriver;
      98: invokevirtual #67                 // Method net/serenitybdd/core/pages/PageObject.setDriver:(Lorg/openqa/selenium/WebDriver;)Lnet/serenitybdd/core/pages/PageObject;
     101: pop
     102: goto          106
     105: astore_3
     106: aload_2
     107: areturn
    Exception table:
       from    to  target type
           2   102   105   Class java/lang/NoSuchMethodException

  private <T extends net.serenitybdd.core.pages.PageObject> boolean hasDefaultConstructor(java.lang.Class<T>);
    Code:
       0: aload_1
       1: invokevirtual #72                 // Method java/lang/Class.getConstructors:()[Ljava/lang/reflect/Constructor;
       4: invokestatic  #73                 // Method java/util/Arrays.stream:([Ljava/lang/Object;)Ljava/util/stream/Stream;
       7: invokedynamic #74,  0             // InvokeDynamic #0:test:()Ljava/util/function/Predicate;
      12: invokeinterface #75,  2           // InterfaceMethod java/util/stream/Stream.anyMatch:(Ljava/util/function/Predicate;)Z
      17: ireturn

  private <T extends net.serenitybdd.core.pages.PageObject> boolean hasOuterClassConstructor(java.lang.Class<T>);
    Code:
       0: aload_1
       1: invokevirtual #72                 // Method java/lang/Class.getConstructors:()[Ljava/lang/reflect/Constructor;
       4: invokestatic  #73                 // Method java/util/Arrays.stream:([Ljava/lang/Object;)Ljava/util/stream/Stream;
       7: aload_1
       8: invokedynamic #76,  0             // InvokeDynamic #1:test:(Ljava/lang/Class;)Ljava/util/function/Predicate;
      13: invokeinterface #75,  2           // InterfaceMethod java/util/stream/Stream.anyMatch:(Ljava/util/function/Predicate;)Z
      18: ireturn

  private <T extends net.serenitybdd.core.pages.PageObject> T createFromConstructorWithWebdriver(java.lang.Class<T>) throws java.lang.NoSuchMethodException, java.lang.IllegalAccessException, java.lang.reflect.InvocationTargetException, java.lang.InstantiationException;
    Code:
       0: iconst_1
       1: anewarray     #62                 // class java/lang/Class
       4: astore_2
       5: aload_2
       6: iconst_0
       7: ldc           #77                 // class org/openqa/selenium/WebDriver
       9: aastore
      10: aload_1
      11: aload_2
      12: invokevirtual #63                 // Method java/lang/Class.getConstructor:([Ljava/lang/Class;)Ljava/lang/reflect/Constructor;
      15: astore_3
      16: aload_3
      17: iconst_1
      18: anewarray     #64                 // class java/lang/Object
      21: dup
      22: iconst_0
      23: aload_0
      24: getfield      #9                  // Field driver:Lorg/openqa/selenium/WebDriver;
      27: aastore
      28: invokevirtual #65                 // Method java/lang/reflect/Constructor.newInstance:([Ljava/lang/Object;)Ljava/lang/Object;
      31: checkcast     #66                 // class net/serenitybdd/core/pages/PageObject
      34: areturn

  private boolean hasPageFactoryProperty(java.lang.Object);
    Code:
       0: aload_1
       1: invokevirtual #36                 // Method java/lang/Object.getClass:()Ljava/lang/Class;
       4: invokestatic  #78                 // Method net/thucydides/core/annotations/Fields.of:(Ljava/lang/Class;)Lnet/thucydides/core/annotations/Fields;
       7: ldc           #79                 // String pages
       9: invokevirtual #80                 // Method net/thucydides/core/annotations/Fields.withName:(Ljava/lang/String;)Ljava/util/Optional;
      12: astore_2
      13: aload_2
      14: invokevirtual #81                 // Method java/util/Optional.isPresent:()Z
      17: ifeq          39
      20: aload_2
      21: invokevirtual #82                 // Method java/util/Optional.get:()Ljava/lang/Object;
      24: checkcast     #83                 // class java/lang/reflect/Field
      27: invokevirtual #84                 // Method java/lang/reflect/Field.getType:()Ljava/lang/Class;
      30: ldc           #85                 // class net/thucydides/core/pages/Pages
      32: if_acmpne     39
      35: iconst_1
      36: goto          40
      39: iconst_0
      40: ireturn

  private void setPageFactory(java.lang.Object) throws java.lang.IllegalAccessException;
    Code:
       0: aload_1
       1: invokevirtual #36                 // Method java/lang/Object.getClass:()Ljava/lang/Class;
       4: invokestatic  #78                 // Method net/thucydides/core/annotations/Fields.of:(Ljava/lang/Class;)Lnet/thucydides/core/annotations/Fields;
       7: ldc           #79                 // String pages
       9: invokevirtual #80                 // Method net/thucydides/core/annotations/Fields.withName:(Ljava/lang/String;)Ljava/util/Optional;
      12: aload_0
      13: aload_1
      14: invokedynamic #86,  0             // InvokeDynamic #2:accept:(Lnet/thucydides/core/pages/Pages;Ljava/lang/Object;)Ljava/util/function/Consumer;
      19: invokevirtual #87                 // Method java/util/Optional.ifPresent:(Ljava/util/function/Consumer;)V
      22: return

  private void assignTo(java.lang.reflect.Field, java.lang.Object);
    Code:
       0: aload_1
       1: iconst_1
       2: invokevirtual #88                 // Method java/lang/reflect/Field.setAccessible:(Z)V
       5: aload_1
       6: aload_2
       7: aload_0
       8: invokevirtual #89                 // Method java/lang/reflect/Field.set:(Ljava/lang/Object;Ljava/lang/Object;)V
      11: goto          26
      14: astore_3
      15: getstatic     #44                 // Field LOGGER:Lorg/slf4j/Logger;
      18: ldc           #91                 // String Failed to assign page object field:
      20: aload_3
      21: invokeinterface #92,  3           // InterfaceMethod org/slf4j/Logger.warn:(Ljava/lang/String;Ljava/lang/Throwable;)V
      26: return
    Exception table:
       from    to  target type
           0    11    14   Class java/lang/IllegalAccessException

  private void thisPageObjectLooksDodgy(java.lang.Class<? extends net.serenitybdd.core.pages.PageObject>, java.lang.String);
    Code:
       0: new           #53                 // class java/lang/StringBuilder
       3: dup
       4: invokespecial #54                 // Method java/lang/StringBuilder."<init>":()V
       7: ldc           #93                 // String The page object
       9: invokevirtual #56                 // Method java/lang/StringBuilder.append:(Ljava/lang/String;)Ljava/lang/StringBuilder;
      12: aload_1
      13: invokevirtual #57                 // Method java/lang/StringBuilder.append:(Ljava/lang/Object;)Ljava/lang/StringBuilder;
      16: ldc           #94                 // String  looks dodgy:\n
      18: invokevirtual #56                 // Method java/lang/StringBuilder.append:(Ljava/lang/String;)Ljava/lang/StringBuilder;
      21: aload_2
      22: invokevirtual #56                 // Method java/lang/StringBuilder.append:(Ljava/lang/String;)Ljava/lang/StringBuilder;
      25: invokevirtual #59                 // Method java/lang/StringBuilder.toString:()Ljava/lang/String;
      28: astore_3
      29: new           #38                 // class net/thucydides/core/pages/WrongPageError
      32: dup
      33: aload_3
      34: invokespecial #95                 // Method net/thucydides/core/pages/WrongPageError."<init>":(Ljava/lang/String;)V
      37: athrow

  private void thisIsNotThePageYourLookingFor(java.lang.Class<? extends net.serenitybdd.core.pages.PageObject>);
    Code:
       0: new           #53                 // class java/lang/StringBuilder
       3: dup
       4: invokespecial #54                 // Method java/lang/StringBuilder."<init>":()V
       7: ldc           #96                 // String This is not the page you\'re looking for: I was looking for a page compatible with
       9: invokevirtual #56                 // Method java/lang/StringBuilder.append:(Ljava/lang/String;)Ljava/lang/StringBuilder;
      12: aload_1
      13: invokevirtual #57                 // Method java/lang/StringBuilder.append:(Ljava/lang/Object;)Ljava/lang/StringBuilder;
      16: ldc           #97                 // String  but I was at the URL
      18: invokevirtual #56                 // Method java/lang/StringBuilder.append:(Ljava/lang/String;)Ljava/lang/StringBuilder;
      21: aload_0
      22: invokevirtual #25                 // Method getDriver:()Lorg/openqa/selenium/WebDriver;
      25: invokeinterface #28,  1           // InterfaceMethod org/openqa/selenium/WebDriver.getCurrentUrl:()Ljava/lang/String;
      30: invokevirtual #56                 // Method java/lang/StringBuilder.append:(Ljava/lang/String;)Ljava/lang/StringBuilder;
      33: invokevirtual #59                 // Method java/lang/StringBuilder.toString:()Ljava/lang/String;
      36: astore_2
      37: new           #38                 // class net/thucydides/core/pages/WrongPageError
      40: dup
      41: aload_2
      42: invokespecial #95                 // Method net/thucydides/core/pages/WrongPageError."<init>":(Ljava/lang/String;)V
      45: athrow

  public java.lang.String getDefaultBaseUrl();
    Code:
       0: aload_0
       1: getfield      #98                 // Field defaultBaseUrl:Ljava/lang/String;
       4: astore_1
       5: aload_0
       6: invokevirtual #99                 // Method getConfiguration:()Lnet/thucydides/core/webdriver/Configuration;
       9: invokeinterface #100,  1          // InterfaceMethod net/thucydides/core/webdriver/Configuration.getBaseUrl:()Ljava/lang/String;
      14: invokestatic  #101                // Method org/apache/commons/lang3/StringUtils.isNotEmpty:(Ljava/lang/CharSequence;)Z
      17: ifeq          30
      20: aload_0
      21: invokevirtual #99                 // Method getConfiguration:()Lnet/thucydides/core/webdriver/Configuration;
      24: invokeinterface #100,  1          // InterfaceMethod net/thucydides/core/webdriver/Configuration.getBaseUrl:()Ljava/lang/String;
      29: astore_1
      30: aload_1
      31: areturn

  public void setDefaultBaseUrl(java.lang.String);
    Code:
       0: aload_0
       1: aload_1
       2: putfield      #98                 // Field defaultBaseUrl:Ljava/lang/String;
       5: return

  public net.thucydides.core.pages.Pages onSamePage();
    Code:
       0: aload_0
       1: iconst_1
       2: putfield      #2                  // Field usePreviousPage:Z
       5: aload_0
       6: areturn

  public static <T extends net.serenitybdd.core.pages.PageObject> T instrumentedPageObjectUsing(java.lang.Class<T>, org.openqa.selenium.WebDriver);
    Code:
       0: aload_1
       1: invokestatic  #102                // Method net/serenitybdd/core/pages/PageObjects.usingDriver:(Lorg/openqa/selenium/WebDriver;)Lnet/serenitybdd/core/pages/PageObjects;
       4: aload_0
       5: invokevirtual #103                // Method net/serenitybdd/core/pages/PageObjects.ofType:(Ljava/lang/Class;)Lnet/serenitybdd/core/pages/PageObject;
       8: areturn

  private void lambda$setPageFactory$2(java.lang.Object, java.lang.reflect.Field);
    Code:
       0: aload_0
       1: aload_2
       2: aload_1
       3: invokespecial #104                // Method assignTo:(Ljava/lang/reflect/Field;Ljava/lang/Object;)V
       6: return

  private static boolean lambda$hasOuterClassConstructor$1(java.lang.Class, java.lang.reflect.Constructor);
    Code:
       0: aload_1
       1: invokevirtual #105                // Method java/lang/reflect/Constructor.getParameters:()[Ljava/lang/reflect/Parameter;
       4: arraylength
       5: iconst_1
       6: if_icmpne     29
       9: aload_1
      10: invokevirtual #105                // Method java/lang/reflect/Constructor.getParameters:()[Ljava/lang/reflect/Parameter;
      13: iconst_0
      14: aaload
      15: invokevirtual #106                // Method java/lang/reflect/Parameter.getType:()Ljava/lang/Class;
      18: aload_0
      19: invokevirtual #69                 // Method java/lang/Class.getEnclosingClass:()Ljava/lang/Class;
      22: if_acmpne     29
      25: iconst_1
      26: goto          30
      29: iconst_0
      30: ireturn

  private static boolean lambda$hasDefaultConstructor$0(java.lang.reflect.Constructor);
    Code:
       0: aload_0
       1: invokevirtual #105                // Method java/lang/reflect/Constructor.getParameters:()[Ljava/lang/reflect/Parameter;
       4: arraylength
       5: ifne          12
       8: iconst_1
       9: goto          13
      12: iconst_0
      13: ireturn

  static {};
    Code:
       0: ldc           #85                 // class net/thucydides/core/pages/Pages
       2: invokestatic  #107                // Method org/slf4j/LoggerFactory.getLogger:(Ljava/lang/Class;)Lorg/slf4j/Logger;
       5: putstatic     #44                 // Field LOGGER:Lorg/slf4j/Logger;
       8: return
}
