Compiled from "C3P0BenchmarkApp.java"
class com.mchange.v2.c3p0.test.C3P0BenchmarkApp$DataBaseMetaDataListNonexistentTablesTest extends com.mchange.v2.c3p0.test.C3P0BenchmarkApp$Test {
  com.mchange.v2.c3p0.test.C3P0BenchmarkApp$DataBaseMetaDataListNonexistentTablesTest();
    Code:
       0: aload_0
       1: ldc           #1                  // String DataBaseMetaDataListNonexistentTablesTest
       3: invokespecial #2                  // Method com/mchange/v2/c3p0/test/C3P0BenchmarkApp$Test."<init>":(Ljava/lang/String;)V
       6: return

  protected long test(javax.sql.DataSource, int) throws java.sql.SQLException;
    Code:
       0: aconst_null
       1: astore_3
       2: aconst_null
       3: astore        4
       5: aload_1
       6: invokeinterface #3,  1            // InterfaceMethod javax/sql/DataSource.getConnection:()Ljava/sql/Connection;
      11: astore_3
      12: aload_0
      13: aload_3
      14: iload_2
      15: invokevirtual #4                  // Method test:(Ljava/sql/Connection;I)J
      18: lstore        5
      20: aload         4
      22: invokestatic  #5                  // Method com/mchange/v1/db/sql/StatementUtils.attemptClose:(Ljava/sql/Statement;)Z
      25: pop
      26: aload_3
      27: invokestatic  #6                  // Method com/mchange/v1/db/sql/ConnectionUtils.attemptClose:(Ljava/sql/Connection;)Z
      30: pop
      31: lload         5
      33: lreturn
      34: astore        7
      36: aload         4
      38: invokestatic  #5                  // Method com/mchange/v1/db/sql/StatementUtils.attemptClose:(Ljava/sql/Statement;)Z
      41: pop
      42: aload_3
      43: invokestatic  #6                  // Method com/mchange/v1/db/sql/ConnectionUtils.attemptClose:(Ljava/sql/Connection;)Z
      46: pop
      47: aload         7
      49: athrow
    Exception table:
       from    to  target type
           5    20    34   any
          34    36    34   any

  long test(java.sql.Connection, int) throws java.sql.SQLException;
    Code:
       0: aconst_null
       1: astore_3
       2: invokestatic  #7                  // Method java/lang/System.currentTimeMillis:()J
       5: lstore        4
       7: iconst_0
       8: istore        8
      10: iload         8
      12: iload_2
      13: if_icmpge     47
      16: aload_1
      17: invokeinterface #8,  1            // InterfaceMethod java/sql/Connection.getMetaData:()Ljava/sql/DatabaseMetaData;
      22: aconst_null
      23: aconst_null
      24: ldc           #9                  // String PROBABLYNOT
      26: iconst_1
      27: anewarray     #10                 // class java/lang/String
      30: dup
      31: iconst_0
      32: ldc           #11                 // String TABLE
      34: aastore
      35: invokeinterface #12,  5           // InterfaceMethod java/sql/DatabaseMetaData.getTables:(Ljava/lang/String;Ljava/lang/String;Ljava/lang/String;[Ljava/lang/String;)Ljava/sql/ResultSet;
      40: astore_3
      41: iinc          8, 1
      44: goto          10
      47: invokestatic  #7                  // Method java/lang/System.currentTimeMillis:()J
      50: lstore        6
      52: lload         6
      54: lload         4
      56: lsub
      57: lstore        8
      59: aload_3
      60: invokestatic  #13                 // Method com/mchange/v1/db/sql/ResultSetUtils.attemptClose:(Ljava/sql/ResultSet;)Z
      63: pop
      64: lload         8
      66: lreturn
      67: astore        10
      69: aload_3
      70: invokestatic  #13                 // Method com/mchange/v1/db/sql/ResultSetUtils.attemptClose:(Ljava/sql/ResultSet;)Z
      73: pop
      74: aload         10
      76: athrow
    Exception table:
       from    to  target type
           2    59    67   any
          67    69    67   any
}
