Compiled from "C3P0BenchmarkApp.java"
class com.mchange.v2.c3p0.test.C3P0BenchmarkApp$ResultSetReadTest extends com.mchange.v2.c3p0.test.C3P0BenchmarkApp$Test {
  com.mchange.v2.c3p0.test.C3P0BenchmarkApp$ResultSetReadTest();
    Code:
       0: aload_0
       1: ldc           #2                  // String Reading one row / one entry from a result set
       3: invokespecial #3                  // Method com/mchange/v2/c3p0/test/C3P0BenchmarkApp$Test."<init>":(Ljava/lang/String;)V
       6: return

  protected long test(javax.sql.DataSource, int) throws java.sql.SQLException;
    Code:
       0: iload_2
       1: sipush        10000
       4: if_icmple     17
       7: new           #4                  // class java/lang/IllegalArgumentException
      10: dup
      11: ldc           #5                  // String 10K max.
      13: invokespecial #6                  // Method java/lang/IllegalArgumentException."<init>":(Ljava/lang/String;)V
      16: athrow
      17: aconst_null
      18: astore        7
      20: aconst_null
      21: astore        8
      23: aconst_null
      24: astore        9
      26: aload_1
      27: invokeinterface #7,  1            // InterfaceMethod javax/sql/DataSource.getConnection:()Ljava/sql/Connection;
      32: astore        7
      34: aload         7
      36: ldc           #8                  // String SELECT * FROM n_entryyukyuk
      38: invokeinterface #9,  2            // InterfaceMethod java/sql/Connection.prepareStatement:(Ljava/lang/String;)Ljava/sql/PreparedStatement;
      43: astore        8
      45: aload         8
      47: invokeinterface #10,  1           // InterfaceMethod java/sql/PreparedStatement.executeQuery:()Ljava/sql/ResultSet;
      52: astore        9
      54: invokestatic  #11                 // Method java/lang/System.currentTimeMillis:()J
      57: lstore_3
      58: iconst_0
      59: istore        10
      61: iload         10
      63: iload_2
      64: if_icmpge     100
      67: aload         9
      69: invokeinterface #12,  1           // InterfaceMethod java/sql/ResultSet.next:()Z
      74: ifne          85
      77: getstatic     #13                 // Field java/lang/System.err:Ljava/io/PrintStream;
      80: ldc           #14                 // String huh?
      82: invokevirtual #15                 // Method java/io/PrintStream.println:(Ljava/lang/String;)V
      85: aload         9
      87: iconst_1
      88: invokeinterface #16,  2           // InterfaceMethod java/sql/ResultSet.getInt:(I)I
      93: pop
      94: iinc          10, 1
      97: goto          61
     100: invokestatic  #11                 // Method java/lang/System.currentTimeMillis:()J
     103: lstore        5
     105: lload         5
     107: lload_3
     108: lsub
     109: lstore        10
     111: aload         9
     113: invokestatic  #17                 // Method com/mchange/v1/db/sql/ResultSetUtils.attemptClose:(Ljava/sql/ResultSet;)Z
     116: pop
     117: aload         8
     119: invokestatic  #18                 // Method com/mchange/v1/db/sql/StatementUtils.attemptClose:(Ljava/sql/Statement;)Z
     122: pop
     123: aload         7
     125: invokestatic  #19                 // Method com/mchange/v1/db/sql/ConnectionUtils.attemptClose:(Ljava/sql/Connection;)Z
     128: pop
     129: lload         10
     131: lreturn
     132: astore        12
     134: aload         9
     136: invokestatic  #17                 // Method com/mchange/v1/db/sql/ResultSetUtils.attemptClose:(Ljava/sql/ResultSet;)Z
     139: pop
     140: aload         8
     142: invokestatic  #18                 // Method com/mchange/v1/db/sql/StatementUtils.attemptClose:(Ljava/sql/Statement;)Z
     145: pop
     146: aload         7
     148: invokestatic  #19                 // Method com/mchange/v1/db/sql/ConnectionUtils.attemptClose:(Ljava/sql/Connection;)Z
     151: pop
     152: aload         12
     154: athrow
    Exception table:
       from    to  target type
          26   111   132   any
         132   134   132   any
}
