Compiled from "InterruptedBatchTest.java"
public final class com.mchange.v2.c3p0.test.InterruptedBatchTest {
  static javax.sql.DataSource ds_unpooled;

  static javax.sql.DataSource ds_pooled;

  public com.mchange.v2.c3p0.test.InterruptedBatchTest();
    Code:
       0: aload_0
       1: invokespecial #1                  // Method java/lang/Object."<init>":()V
       4: return

  public static void main(java.lang.String[]);
    Code:
       0: aload_0
       1: arraylength
       2: ifle          35
       5: getstatic     #2                  // Field java/lang/System.err:Ljava/io/PrintStream;
       8: new           #3                  // class java/lang/StringBuilder
      11: dup
      12: invokespecial #4                  // Method java/lang/StringBuilder."<init>":()V
      15: ldc           #5                  // class com/mchange/v2/c3p0/test/C3P0BenchmarkApp
      17: invokevirtual #6                  // Method java/lang/Class.getName:()Ljava/lang/String;
      20: invokevirtual #7                  // Method java/lang/StringBuilder.append:(Ljava/lang/String;)Ljava/lang/StringBuilder;
      23: ldc           #8                  // String  now requires no args. Please set everything in standard c3p0 config files.
      25: invokevirtual #7                  // Method java/lang/StringBuilder.append:(Ljava/lang/String;)Ljava/lang/StringBuilder;
      28: invokevirtual #9                  // Method java/lang/StringBuilder.toString:()Ljava/lang/String;
      31: invokevirtual #10                 // Method java/io/PrintStream.println:(Ljava/lang/String;)V
      34: return
      35: new           #11                 // class com/mchange/v2/c3p0/DriverManagerDataSource
      38: dup
      39: invokespecial #12                 // Method com/mchange/v2/c3p0/DriverManagerDataSource."<init>":()V
      42: putstatic     #13                 // Field ds_unpooled:Ljavax/sql/DataSource;
      45: new           #14                 // class com/mchange/v2/c3p0/ComboPooledDataSource
      48: dup
      49: invokespecial #15                 // Method com/mchange/v2/c3p0/ComboPooledDataSource."<init>":()V
      52: astore_1
      53: aload_1
      54: putstatic     #16                 // Field ds_pooled:Ljavax/sql/DataSource;
      57: invokestatic  #17                 // Method attemptSetupTable:()V
      60: iconst_1
      61: invokestatic  #18                 // Method performTransaction:(Z)V
      64: iconst_0
      65: invokestatic  #18                 // Method performTransaction:(Z)V
      68: invokestatic  #19                 // Method checkCount:()V
      71: getstatic     #16                 // Field ds_pooled:Ljavax/sql/DataSource;
      74: invokestatic  #20                 // Method com/mchange/v2/c3p0/DataSources.destroy:(Ljavax/sql/DataSource;)V
      77: goto          85
      80: astore_1
      81: aload_1
      82: invokevirtual #22                 // Method java/lang/Exception.printStackTrace:()V
      85: getstatic     #13                 // Field ds_unpooled:Ljavax/sql/DataSource;
      88: invokestatic  #20                 // Method com/mchange/v2/c3p0/DataSources.destroy:(Ljavax/sql/DataSource;)V
      91: goto          189
      94: astore_1
      95: aload_1
      96: invokevirtual #22                 // Method java/lang/Exception.printStackTrace:()V
      99: goto          189
     102: astore_1
     103: getstatic     #2                  // Field java/lang/System.err:Ljava/io/PrintStream;
     106: ldc           #24                 // String Aborting tests on Throwable --
     108: invokevirtual #25                 // Method java/io/PrintStream.print:(Ljava/lang/String;)V
     111: aload_1
     112: invokevirtual #26                 // Method java/lang/Throwable.printStackTrace:()V
     115: aload_1
     116: instanceof    #27                 // class java/lang/Error
     119: ifeq          127
     122: aload_1
     123: checkcast     #27                 // class java/lang/Error
     126: athrow
     127: getstatic     #16                 // Field ds_pooled:Ljavax/sql/DataSource;
     130: invokestatic  #20                 // Method com/mchange/v2/c3p0/DataSources.destroy:(Ljavax/sql/DataSource;)V
     133: goto          141
     136: astore_1
     137: aload_1
     138: invokevirtual #22                 // Method java/lang/Exception.printStackTrace:()V
     141: getstatic     #13                 // Field ds_unpooled:Ljavax/sql/DataSource;
     144: invokestatic  #20                 // Method com/mchange/v2/c3p0/DataSources.destroy:(Ljavax/sql/DataSource;)V
     147: goto          189
     150: astore_1
     151: aload_1
     152: invokevirtual #22                 // Method java/lang/Exception.printStackTrace:()V
     155: goto          189
     158: astore_2
     159: getstatic     #16                 // Field ds_pooled:Ljavax/sql/DataSource;
     162: invokestatic  #20                 // Method com/mchange/v2/c3p0/DataSources.destroy:(Ljavax/sql/DataSource;)V
     165: goto          173
     168: astore_3
     169: aload_3
     170: invokevirtual #22                 // Method java/lang/Exception.printStackTrace:()V
     173: getstatic     #13                 // Field ds_unpooled:Ljavax/sql/DataSource;
     176: invokestatic  #20                 // Method com/mchange/v2/c3p0/DataSources.destroy:(Ljavax/sql/DataSource;)V
     179: goto          187
     182: astore_3
     183: aload_3
     184: invokevirtual #22                 // Method java/lang/Exception.printStackTrace:()V
     187: aload_2
     188: athrow
     189: return
    Exception table:
       from    to  target type
          71    77    80   Class java/lang/Exception
          85    91    94   Class java/lang/Exception
          35    71   102   Class java/lang/Throwable
         127   133   136   Class java/lang/Exception
         141   147   150   Class java/lang/Exception
          35    71   158   any
         102   127   158   any
         159   165   168   Class java/lang/Exception
         173   179   182   Class java/lang/Exception

  public static void performTransaction(boolean) throws java.sql.SQLException;
    Code:
       0: aconst_null
       1: astore_1
       2: aconst_null
       3: astore_2
       4: getstatic     #16                 // Field ds_pooled:Ljavax/sql/DataSource;
       7: invokeinterface #28,  1           // InterfaceMethod javax/sql/DataSource.getConnection:()Ljava/sql/Connection;
      12: astore_1
      13: aload_1
      14: iconst_0
      15: invokeinterface #29,  2           // InterfaceMethod java/sql/Connection.setAutoCommit:(Z)V
      20: aload_1
      21: ldc           #30                 // String INSERT INTO CG_TAROPT_LOG(CO_ID, ENTDATE, CS_SEQNO, DESCRIPTION) VALUES (?,?,?,?)
      23: invokeinterface #31,  2           // InterfaceMethod java/sql/Connection.prepareStatement:(Ljava/lang/String;)Ljava/sql/PreparedStatement;
      28: astore_2
      29: aload_2
      30: iconst_1
      31: ldc2_w        #32                 // long -665l
      34: invokeinterface #34,  4           // InterfaceMethod java/sql/PreparedStatement.setLong:(IJ)V
      39: aload_2
      40: iconst_2
      41: new           #35                 // class java/sql/Timestamp
      44: dup
      45: invokestatic  #36                 // Method java/lang/System.currentTimeMillis:()J
      48: invokespecial #37                 // Method java/sql/Timestamp."<init>":(J)V
      51: invokeinterface #38,  3           // InterfaceMethod java/sql/PreparedStatement.setTimestamp:(ILjava/sql/Timestamp;)V
      56: aload_2
      57: iconst_3
      58: iconst_1
      59: invokeinterface #39,  3           // InterfaceMethod java/sql/PreparedStatement.setInt:(II)V
      64: aload_2
      65: iconst_4
      66: new           #3                  // class java/lang/StringBuilder
      69: dup
      70: invokespecial #4                  // Method java/lang/StringBuilder."<init>":()V
      73: ldc           #40                 // String time:
      75: invokevirtual #7                  // Method java/lang/StringBuilder.append:(Ljava/lang/String;)Ljava/lang/StringBuilder;
      78: invokestatic  #36                 // Method java/lang/System.currentTimeMillis:()J
      81: invokevirtual #41                 // Method java/lang/StringBuilder.append:(J)Ljava/lang/StringBuilder;
      84: invokevirtual #9                  // Method java/lang/StringBuilder.toString:()Ljava/lang/String;
      87: invokeinterface #42,  3           // InterfaceMethod java/sql/PreparedStatement.setString:(ILjava/lang/String;)V
      92: aload_2
      93: invokeinterface #43,  1           // InterfaceMethod java/sql/PreparedStatement.addBatch:()V
      98: iload_0
      99: ifeq          112
     102: new           #44                 // class java/lang/NullPointerException
     105: dup
     106: ldc           #45                 // String my exception
     108: invokespecial #46                 // Method java/lang/NullPointerException."<init>":(Ljava/lang/String;)V
     111: athrow
     112: aload_2
     113: invokeinterface #47,  1           // InterfaceMethod java/sql/PreparedStatement.executeBatch:()[I
     118: pop
     119: aload_1
     120: invokeinterface #48,  1           // InterfaceMethod java/sql/Connection.commit:()V
     125: aload_2
     126: ifnull        135
     129: aload_2
     130: invokeinterface #49,  1           // InterfaceMethod java/sql/PreparedStatement.close:()V
     135: goto          143
     138: astore_3
     139: aload_3
     140: invokevirtual #22                 // Method java/lang/Exception.printStackTrace:()V
     143: aload_1
     144: invokeinterface #50,  1           // InterfaceMethod java/sql/Connection.close:()V
     149: goto          249
     152: astore_3
     153: aload_3
     154: invokevirtual #22                 // Method java/lang/Exception.printStackTrace:()V
     157: goto          249
     160: astore_3
     161: getstatic     #51                 // Field java/lang/System.out:Ljava/io/PrintStream;
     164: ldc           #52                 // String exception caught (NPE expected):
     166: invokevirtual #10                 // Method java/io/PrintStream.println:(Ljava/lang/String;)V
     169: aload_3
     170: invokevirtual #22                 // Method java/lang/Exception.printStackTrace:()V
     173: aload_2
     174: ifnull        183
     177: aload_2
     178: invokeinterface #49,  1           // InterfaceMethod java/sql/PreparedStatement.close:()V
     183: goto          191
     186: astore_3
     187: aload_3
     188: invokevirtual #22                 // Method java/lang/Exception.printStackTrace:()V
     191: aload_1
     192: invokeinterface #50,  1           // InterfaceMethod java/sql/Connection.close:()V
     197: goto          249
     200: astore_3
     201: aload_3
     202: invokevirtual #22                 // Method java/lang/Exception.printStackTrace:()V
     205: goto          249
     208: astore        4
     210: aload_2
     211: ifnull        220
     214: aload_2
     215: invokeinterface #49,  1           // InterfaceMethod java/sql/PreparedStatement.close:()V
     220: goto          230
     223: astore        5
     225: aload         5
     227: invokevirtual #22                 // Method java/lang/Exception.printStackTrace:()V
     230: aload_1
     231: invokeinterface #50,  1           // InterfaceMethod java/sql/Connection.close:()V
     236: goto          246
     239: astore        5
     241: aload         5
     243: invokevirtual #22                 // Method java/lang/Exception.printStackTrace:()V
     246: aload         4
     248: athrow
     249: return
    Exception table:
       from    to  target type
         125   135   138   Class java/lang/Exception
         143   149   152   Class java/lang/Exception
           4   125   160   Class java/lang/Exception
         173   183   186   Class java/lang/Exception
         191   197   200   Class java/lang/Exception
           4   125   208   any
         160   173   208   any
         210   220   223   Class java/lang/Exception
         230   236   239   Class java/lang/Exception
         208   210   208   any

  private static void attemptSetupTable() throws java.lang.Exception;
    Code:
       0: aconst_null
       1: astore_0
       2: aconst_null
       3: astore_1
       4: getstatic     #16                 // Field ds_pooled:Ljavax/sql/DataSource;
       7: invokeinterface #28,  1           // InterfaceMethod javax/sql/DataSource.getConnection:()Ljava/sql/Connection;
      12: astore_0
      13: aload_0
      14: invokeinterface #53,  1           // InterfaceMethod java/sql/Connection.createStatement:()Ljava/sql/Statement;
      19: astore_1
      20: aload_1
      21: ldc           #54                 // String CREATE TABLE CG_TAROPT_LOG ( CO_ID INTEGER, ENTDATE TIMESTAMP, CS_SEQNO INTEGER, DESCRIPTION VARCHAR(32) )
      23: invokeinterface #55,  2           // InterfaceMethod java/sql/Statement.executeUpdate:(Ljava/lang/String;)I
      28: pop
      29: goto          45
      32: astore_2
      33: getstatic     #2                  // Field java/lang/System.err:Ljava/io/PrintStream;
      36: ldc           #57                 // String Table already constructed?
      38: invokevirtual #10                 // Method java/io/PrintStream.println:(Ljava/lang/String;)V
      41: aload_2
      42: invokevirtual #58                 // Method java/sql/SQLException.printStackTrace:()V
      45: aload_1
      46: ldc           #59                 // String DELETE FROM CG_TAROPT_LOG
      48: invokeinterface #55,  2           // InterfaceMethod java/sql/Statement.executeUpdate:(Ljava/lang/String;)I
      53: pop
      54: aload_1
      55: invokeinterface #60,  1           // InterfaceMethod java/sql/Statement.close:()V
      60: goto          68
      63: astore_2
      64: aload_2
      65: invokevirtual #58                 // Method java/sql/SQLException.printStackTrace:()V
      68: aload_0
      69: invokeinterface #50,  1           // InterfaceMethod java/sql/Connection.close:()V
      74: goto          120
      77: astore_2
      78: aload_2
      79: invokevirtual #58                 // Method java/sql/SQLException.printStackTrace:()V
      82: goto          120
      85: astore_3
      86: aload_1
      87: invokeinterface #60,  1           // InterfaceMethod java/sql/Statement.close:()V
      92: goto          102
      95: astore        4
      97: aload         4
      99: invokevirtual #58                 // Method java/sql/SQLException.printStackTrace:()V
     102: aload_0
     103: invokeinterface #50,  1           // InterfaceMethod java/sql/Connection.close:()V
     108: goto          118
     111: astore        4
     113: aload         4
     115: invokevirtual #58                 // Method java/sql/SQLException.printStackTrace:()V
     118: aload_3
     119: athrow
     120: return
    Exception table:
       from    to  target type
          20    29    32   Class java/sql/SQLException
          54    60    63   Class java/sql/SQLException
          68    74    77   Class java/sql/SQLException
           4    54    85   any
          86    92    95   Class java/sql/SQLException
         102   108   111   Class java/sql/SQLException

  private static void checkCount() throws java.lang.Exception;
    Code:
       0: aconst_null
       1: astore_0
       2: aconst_null
       3: astore_1
       4: aconst_null
       5: astore_2
       6: getstatic     #16                 // Field ds_pooled:Ljavax/sql/DataSource;
       9: invokeinterface #28,  1           // InterfaceMethod javax/sql/DataSource.getConnection:()Ljava/sql/Connection;
      14: astore_0
      15: aload_0
      16: invokeinterface #53,  1           // InterfaceMethod java/sql/Connection.createStatement:()Ljava/sql/Statement;
      21: astore_1
      22: aload_1
      23: ldc           #61                 // String SELECT COUNT(*) FROM CG_TAROPT_LOG
      25: invokeinterface #62,  2           // InterfaceMethod java/sql/Statement.executeQuery:(Ljava/lang/String;)Ljava/sql/ResultSet;
      30: astore_2
      31: aload_2
      32: invokeinterface #63,  1           // InterfaceMethod java/sql/ResultSet.next:()Z
      37: pop
      38: getstatic     #51                 // Field java/lang/System.out:Ljava/io/PrintStream;
      41: new           #3                  // class java/lang/StringBuilder
      44: dup
      45: invokespecial #4                  // Method java/lang/StringBuilder."<init>":()V
      48: aload_2
      49: iconst_1
      50: invokeinterface #64,  2           // InterfaceMethod java/sql/ResultSet.getInt:(I)I
      55: invokevirtual #65                 // Method java/lang/StringBuilder.append:(I)Ljava/lang/StringBuilder;
      58: ldc           #66                 // String  rows found. (one row expected.)
      60: invokevirtual #7                  // Method java/lang/StringBuilder.append:(Ljava/lang/String;)Ljava/lang/StringBuilder;
      63: invokevirtual #9                  // Method java/lang/StringBuilder.toString:()Ljava/lang/String;
      66: invokevirtual #10                 // Method java/io/PrintStream.println:(Ljava/lang/String;)V
      69: aload_1
      70: invokeinterface #60,  1           // InterfaceMethod java/sql/Statement.close:()V
      75: goto          83
      78: astore_3
      79: aload_3
      80: invokevirtual #58                 // Method java/sql/SQLException.printStackTrace:()V
      83: aload_0
      84: invokeinterface #50,  1           // InterfaceMethod java/sql/Connection.close:()V
      89: goto          137
      92: astore_3
      93: aload_3
      94: invokevirtual #58                 // Method java/sql/SQLException.printStackTrace:()V
      97: goto          137
     100: astore        4
     102: aload_1
     103: invokeinterface #60,  1           // InterfaceMethod java/sql/Statement.close:()V
     108: goto          118
     111: astore        5
     113: aload         5
     115: invokevirtual #58                 // Method java/sql/SQLException.printStackTrace:()V
     118: aload_0
     119: invokeinterface #50,  1           // InterfaceMethod java/sql/Connection.close:()V
     124: goto          134
     127: astore        5
     129: aload         5
     131: invokevirtual #58                 // Method java/sql/SQLException.printStackTrace:()V
     134: aload         4
     136: athrow
     137: return
    Exception table:
       from    to  target type
          69    75    78   Class java/sql/SQLException
          83    89    92   Class java/sql/SQLException
           6    69   100   any
         102   108   111   Class java/sql/SQLException
         118   124   127   Class java/sql/SQLException
         100   102   100   any

  static {};
    Code:
       0: aconst_null
       1: putstatic     #13                 // Field ds_unpooled:Ljavax/sql/DataSource;
       4: aconst_null
       5: putstatic     #16                 // Field ds_pooled:Ljavax/sql/DataSource;
       8: return
}
