Compiled from "AddressingConstants.java"
public final class org.jboss.ws.api.addressing.AddressingConstants$Core$Attributes {
  public static final java.lang.String RELATIONSHIPTYPE;

  public static final javax.xml.namespace.QName RELATIONSHIPTYPE_QNAME;

  public static final java.lang.String ISREFERENCEPARAMETER;

  public static final javax.xml.namespace.QName ISREFERENCEPARAMETER_QNAME;

  private org.jboss.ws.api.addressing.AddressingConstants$Core$Attributes();
    Code:
       0: aload_0
       1: invokespecial #1                  // Method java/lang/Object."<init>":()V
       4: return

  static {};
    Code:
       0: new           #2                  // class javax/xml/namespace/QName
       3: dup
       4: ldc           #3                  // String http://www.w3.org/2005/08/addressing
       6: ldc           #4                  // String RelationshipType
       8: ldc           #5                  // String wsa
      10: invokespecial #6                  // Method javax/xml/namespace/QName."<init>":(Ljava/lang/String;Ljava/lang/String;Ljava/lang/String;)V
      13: putstatic     #7                  // Field RELATIONSHIPTYPE_QNAME:Ljavax/xml/namespace/QName;
      16: new           #2                  // class javax/xml/namespace/QName
      19: dup
      20: ldc           #3                  // String http://www.w3.org/2005/08/addressing
      22: ldc           #8                  // String IsReferenceParameter
      24: ldc           #5                  // String wsa
      26: invokespecial #6                  // Method javax/xml/namespace/QName."<init>":(Ljava/lang/String;Ljava/lang/String;Ljava/lang/String;)V
      29: putstatic     #9                  // Field ISREFERENCEPARAMETER_QNAME:Ljavax/xml/namespace/QName;
      32: return
}
