Compiled from "SocksAuthScheme.java"
public final class io.netty.handler.codec.socks.SocksAuthScheme extends java.lang.Enum<io.netty.handler.codec.socks.SocksAuthScheme> {
  public static final io.netty.handler.codec.socks.SocksAuthScheme NO_AUTH;

  public static final io.netty.handler.codec.socks.SocksAuthScheme AUTH_GSSAPI;

  public static final io.netty.handler.codec.socks.SocksAuthScheme AUTH_PASSWORD;

  public static final io.netty.handler.codec.socks.SocksAuthScheme UNKNOWN;

  private final byte b;

  private static final io.netty.handler.codec.socks.SocksAuthScheme[] $VALUES;

  public static io.netty.handler.codec.socks.SocksAuthScheme[] values();
    Code:
       0: getstatic     #1                  // Field $VALUES:[Lio/netty/handler/codec/socks/SocksAuthScheme;
       3: invokevirtual #2                  // Method "[Lio/netty/handler/codec/socks/SocksAuthScheme;".clone:()Ljava/lang/Object;
       6: checkcast     #3                  // class "[Lio/netty/handler/codec/socks/SocksAuthScheme;"
       9: areturn

  public static io.netty.handler.codec.socks.SocksAuthScheme valueOf(java.lang.String);
    Code:
       0: ldc           #4                  // class io/netty/handler/codec/socks/SocksAuthScheme
       2: aload_0
       3: invokestatic  #5                  // Method java/lang/Enum.valueOf:(Ljava/lang/Class;Ljava/lang/String;)Ljava/lang/Enum;
       6: checkcast     #4                  // class io/netty/handler/codec/socks/SocksAuthScheme
       9: areturn

  private io.netty.handler.codec.socks.SocksAuthScheme(byte);
    Code:
       0: aload_0
       1: aload_1
       2: iload_2
       3: invokespecial #6                  // Method java/lang/Enum."<init>":(Ljava/lang/String;I)V
       6: aload_0
       7: iload_3
       8: putfield      #7                  // Field b:B
      11: return

  public static io.netty.handler.codec.socks.SocksAuthScheme fromByte(byte);
    Code:
       0: iload_0
       1: invokestatic  #8                  // Method valueOf:(B)Lio/netty/handler/codec/socks/SocksAuthScheme;
       4: areturn

  public static io.netty.handler.codec.socks.SocksAuthScheme valueOf(byte);
    Code:
       0: invokestatic  #9                  // Method values:()[Lio/netty/handler/codec/socks/SocksAuthScheme;
       3: astore_1
       4: aload_1
       5: arraylength
       6: istore_2
       7: iconst_0
       8: istore_3
       9: iload_3
      10: iload_2
      11: if_icmpge     37
      14: aload_1
      15: iload_3
      16: aaload
      17: astore        4
      19: aload         4
      21: getfield      #7                  // Field b:B
      24: iload_0
      25: if_icmpne     31
      28: aload         4
      30: areturn
      31: iinc          3, 1
      34: goto          9
      37: getstatic     #10                 // Field UNKNOWN:Lio/netty/handler/codec/socks/SocksAuthScheme;
      40: areturn

  public byte byteValue();
    Code:
       0: aload_0
       1: getfield      #7                  // Field b:B
       4: ireturn

  static {};
    Code:
       0: new           #4                  // class io/netty/handler/codec/socks/SocksAuthScheme
       3: dup
       4: ldc           #11                 // String NO_AUTH
       6: iconst_0
       7: iconst_0
       8: invokespecial #12                 // Method "<init>":(Ljava/lang/String;IB)V
      11: putstatic     #13                 // Field NO_AUTH:Lio/netty/handler/codec/socks/SocksAuthScheme;
      14: new           #4                  // class io/netty/handler/codec/socks/SocksAuthScheme
      17: dup
      18: ldc           #14                 // String AUTH_GSSAPI
      20: iconst_1
      21: iconst_1
      22: invokespecial #12                 // Method "<init>":(Ljava/lang/String;IB)V
      25: putstatic     #15                 // Field AUTH_GSSAPI:Lio/netty/handler/codec/socks/SocksAuthScheme;
      28: new           #4                  // class io/netty/handler/codec/socks/SocksAuthScheme
      31: dup
      32: ldc           #16                 // String AUTH_PASSWORD
      34: iconst_2
      35: iconst_2
      36: invokespecial #12                 // Method "<init>":(Ljava/lang/String;IB)V
      39: putstatic     #17                 // Field AUTH_PASSWORD:Lio/netty/handler/codec/socks/SocksAuthScheme;
      42: new           #4                  // class io/netty/handler/codec/socks/SocksAuthScheme
      45: dup
      46: ldc           #18                 // String UNKNOWN
      48: iconst_3
      49: iconst_m1
      50: invokespecial #12                 // Method "<init>":(Ljava/lang/String;IB)V
      53: putstatic     #10                 // Field UNKNOWN:Lio/netty/handler/codec/socks/SocksAuthScheme;
      56: iconst_4
      57: anewarray     #4                  // class io/netty/handler/codec/socks/SocksAuthScheme
      60: dup
      61: iconst_0
      62: getstatic     #13                 // Field NO_AUTH:Lio/netty/handler/codec/socks/SocksAuthScheme;
      65: aastore
      66: dup
      67: iconst_1
      68: getstatic     #15                 // Field AUTH_GSSAPI:Lio/netty/handler/codec/socks/SocksAuthScheme;
      71: aastore
      72: dup
      73: iconst_2
      74: getstatic     #17                 // Field AUTH_PASSWORD:Lio/netty/handler/codec/socks/SocksAuthScheme;
      77: aastore
      78: dup
      79: iconst_3
      80: getstatic     #10                 // Field UNKNOWN:Lio/netty/handler/codec/socks/SocksAuthScheme;
      83: aastore
      84: putstatic     #1                  // Field $VALUES:[Lio/netty/handler/codec/socks/SocksAuthScheme;
      87: return
}
