Compiled from "FilterBuilder.java"
public abstract class org.reflections.util.FilterBuilder$Matcher implements com.google.common.base.Predicate<java.lang.String> {
  final java.util.regex.Pattern pattern;

  public org.reflections.util.FilterBuilder$Matcher(java.lang.String);
    Code:
       0: aload_0
       1: invokespecial #1                  // Method java/lang/Object."<init>":()V
       4: aload_0
       5: aload_1
       6: invokestatic  #2                  // Method java/util/regex/Pattern.compile:(Ljava/lang/String;)Ljava/util/regex/Pattern;
       9: putfield      #3                  // Field pattern:Ljava/util/regex/Pattern;
      12: return

  public abstract boolean apply(java.lang.String);

  public java.lang.String toString();
    Code:
       0: aload_0
       1: getfield      #3                  // Field pattern:Ljava/util/regex/Pattern;
       4: invokevirtual #4                  // Method java/util/regex/Pattern.pattern:()Ljava/lang/String;
       7: areturn

  public boolean apply(java.lang.Object);
    Code:
       0: aload_0
       1: aload_1
       2: checkcast     #5                  // class java/lang/String
       5: invokevirtual #6                  // Method apply:(Ljava/lang/String;)Z
       8: ireturn
}
