Compiled from "KDiag.java"
public class org.apache.hadoop.security.KDiag extends org.apache.hadoop.conf.Configured implements org.apache.hadoop.util.Tool,java.io.Closeable {
  private static final org.slf4j.Logger LOG;

  public static final java.lang.String KRB5_CCNAME;

  public static final java.lang.String KRB5_CONFIG;

  public static final java.lang.String JAVA_SECURITY_KRB5_CONF;

  public static final java.lang.String JAVA_SECURITY_KRB5_REALM;

  public static final java.lang.String JAVA_SECURITY_KRB5_KDC_ADDRESS;

  public static final java.lang.String SUN_SECURITY_KRB5_DEBUG;

  public static final java.lang.String SUN_SECURITY_SPNEGO_DEBUG;

  public static final java.lang.String SUN_SECURITY_JAAS_FILE;

  public static final java.lang.String KERBEROS_KINIT_COMMAND;

  public static final java.lang.String HADOOP_AUTHENTICATION_IS_DISABLED;

  public static final java.lang.String UNSET;

  public static final java.lang.String NO_DEFAULT_REALM;

  public static final int KDIAG_FAILURE;

  public static final java.lang.String DFS_DATA_TRANSFER_SASLPROPERTIES_RESOLVER_CLASS;

  public static final java.lang.String DFS_DATA_TRANSFER_PROTECTION;

  public static final java.lang.String ETC_KRB5_CONF;

  public static final java.lang.String ETC_NTP;

  public static final java.lang.String HADOOP_JAAS_DEBUG;

  private java.io.PrintWriter out;

  private java.io.File keytab;

  private java.lang.String principal;

  private long minKeyLength;

  private boolean securityRequired;

  private boolean nofail;

  private boolean nologin;

  private boolean jaas;

  private boolean checkShortName;

  private static final java.util.regex.Pattern nonSimplePattern;

  private boolean probeHasFailed;

  public static final java.lang.String CAT_CONFIG;

  public static final java.lang.String CAT_JAAS;

  public static final java.lang.String CAT_JVM;

  public static final java.lang.String CAT_KERBEROS;

  public static final java.lang.String CAT_LOGIN;

  public static final java.lang.String CAT_OS;

  public static final java.lang.String CAT_SASL;

  public static final java.lang.String CAT_UGI;

  public static final java.lang.String CAT_TOKEN;

  public static final java.lang.String ARG_KEYLEN;

  public static final java.lang.String ARG_KEYTAB;

  public static final java.lang.String ARG_JAAS;

  public static final java.lang.String ARG_NOFAIL;

  public static final java.lang.String ARG_NOLOGIN;

  public static final java.lang.String ARG_OUTPUT;

  public static final java.lang.String ARG_PRINCIPAL;

  public static final java.lang.String ARG_RESOURCE;

  public static final java.lang.String ARG_SECURE;

  public static final java.lang.String ARG_VERIFYSHORTNAME;

  public org.apache.hadoop.security.KDiag(org.apache.hadoop.conf.Configuration, java.io.PrintWriter, java.io.File, java.lang.String, long, boolean);
    Code:
       0: aload_0
       1: aload_1
       2: invokespecial #3                  // Method org/apache/hadoop/conf/Configured."<init>":(Lorg/apache/hadoop/conf/Configuration;)V
       5: aload_0
       6: ldc2_w        #4                  // long 256l
       9: putfield      #6                  // Field minKeyLength:J
      12: aload_0
      13: iconst_0
      14: putfield      #7                  // Field nofail:Z
      17: aload_0
      18: iconst_0
      19: putfield      #8                  // Field nologin:Z
      22: aload_0
      23: iconst_0
      24: putfield      #9                  // Field jaas:Z
      27: aload_0
      28: iconst_0
      29: putfield      #10                 // Field checkShortName:Z
      32: aload_0
      33: iconst_0
      34: putfield      #11                 // Field probeHasFailed:Z
      37: aload_0
      38: aload_3
      39: putfield      #12                 // Field keytab:Ljava/io/File;
      42: aload_0
      43: aload         4
      45: putfield      #13                 // Field principal:Ljava/lang/String;
      48: aload_0
      49: aload_2
      50: putfield      #14                 // Field out:Ljava/io/PrintWriter;
      53: aload_0
      54: lload         5
      56: putfield      #6                  // Field minKeyLength:J
      59: aload_0
      60: iload         7
      62: putfield      #15                 // Field securityRequired:Z
      65: return

  public org.apache.hadoop.security.KDiag();
    Code:
       0: aload_0
       1: invokespecial #16                 // Method org/apache/hadoop/conf/Configured."<init>":()V
       4: aload_0
       5: ldc2_w        #4                  // long 256l
       8: putfield      #6                  // Field minKeyLength:J
      11: aload_0
      12: iconst_0
      13: putfield      #7                  // Field nofail:Z
      16: aload_0
      17: iconst_0
      18: putfield      #8                  // Field nologin:Z
      21: aload_0
      22: iconst_0
      23: putfield      #9                  // Field jaas:Z
      26: aload_0
      27: iconst_0
      28: putfield      #10                 // Field checkShortName:Z
      31: aload_0
      32: iconst_0
      33: putfield      #11                 // Field probeHasFailed:Z
      36: return

  public void close() throws java.io.IOException;
    Code:
       0: aload_0
       1: invokespecial #17                 // Method flush:()V
       4: aload_0
       5: getfield      #14                 // Field out:Ljava/io/PrintWriter;
       8: ifnull        18
      11: aload_0
      12: getfield      #14                 // Field out:Ljava/io/PrintWriter;
      15: invokevirtual #18                 // Method java/io/PrintWriter.close:()V
      18: return

  public int run(java.lang.String[]) throws java.lang.Exception;
    Code:
       0: new           #19                 // class java/util/LinkedList
       3: dup
       4: aload_1
       5: invokestatic  #20                 // Method java/util/Arrays.asList:([Ljava/lang/Object;)Ljava/util/List;
       8: invokespecial #21                 // Method java/util/LinkedList."<init>":(Ljava/util/Collection;)V
      11: astore_2
      12: ldc           #23                 // String --keytab
      14: aload_2
      15: invokestatic  #24                 // Method org/apache/hadoop/util/StringUtils.popOptionWithArgument:(Ljava/lang/String;Ljava/util/List;)Ljava/lang/String;
      18: astore_3
      19: aload_3
      20: ifnull        35
      23: aload_0
      24: new           #25                 // class java/io/File
      27: dup
      28: aload_3
      29: invokespecial #26                 // Method java/io/File."<init>":(Ljava/lang/String;)V
      32: putfield      #12                 // Field keytab:Ljava/io/File;
      35: aload_0
      36: ldc           #27                 // String --principal
      38: aload_2
      39: invokestatic  #24                 // Method org/apache/hadoop/util/StringUtils.popOptionWithArgument:(Ljava/lang/String;Ljava/util/List;)Ljava/lang/String;
      42: putfield      #13                 // Field principal:Ljava/lang/String;
      45: ldc           #28                 // String --out
      47: aload_2
      48: invokestatic  #24                 // Method org/apache/hadoop/util/StringUtils.popOptionWithArgument:(Ljava/lang/String;Ljava/util/List;)Ljava/lang/String;
      51: astore        4
      53: ldc           #29                 // String --keylen
      55: aload_2
      56: invokestatic  #24                 // Method org/apache/hadoop/util/StringUtils.popOptionWithArgument:(Ljava/lang/String;Ljava/util/List;)Ljava/lang/String;
      59: astore        5
      61: aload         5
      63: ifnull        76
      66: aload_0
      67: aload         5
      69: invokestatic  #30                 // Method java/lang/Integer.parseInt:(Ljava/lang/String;)I
      72: i2l
      73: putfield      #6                  // Field minKeyLength:J
      76: aload_0
      77: ldc           #31                 // String --secure
      79: aload_2
      80: invokestatic  #32                 // Method org/apache/hadoop/util/StringUtils.popOption:(Ljava/lang/String;Ljava/util/List;)Z
      83: putfield      #15                 // Field securityRequired:Z
      86: aload_0
      87: ldc           #33                 // String --nofail
      89: aload_2
      90: invokestatic  #32                 // Method org/apache/hadoop/util/StringUtils.popOption:(Ljava/lang/String;Ljava/util/List;)Z
      93: putfield      #7                  // Field nofail:Z
      96: aload_0
      97: ldc           #34                 // String --jaas
      99: aload_2
     100: invokestatic  #32                 // Method org/apache/hadoop/util/StringUtils.popOption:(Ljava/lang/String;Ljava/util/List;)Z
     103: putfield      #9                  // Field jaas:Z
     106: aload_0
     107: ldc           #35                 // String --nologin
     109: aload_2
     110: invokestatic  #32                 // Method org/apache/hadoop/util/StringUtils.popOption:(Ljava/lang/String;Ljava/util/List;)Z
     113: putfield      #8                  // Field nologin:Z
     116: aload_0
     117: ldc           #36                 // String --verifyshortname
     119: aload_2
     120: invokestatic  #32                 // Method org/apache/hadoop/util/StringUtils.popOption:(Ljava/lang/String;Ljava/util/List;)Z
     123: putfield      #10                 // Field checkShortName:Z
     126: aconst_null
     127: ldc           #37                 // String --resource
     129: aload_2
     130: invokestatic  #24                 // Method org/apache/hadoop/util/StringUtils.popOptionWithArgument:(Ljava/lang/String;Ljava/util/List;)Ljava/lang/String;
     133: dup
     134: astore        6
     136: if_acmpeq     293
     139: getstatic     #38                 // Field LOG:Lorg/slf4j/Logger;
     142: ldc           #39                 // String Loading resource {}
     144: aload         6
     146: invokeinterface #40,  3           // InterfaceMethod org/slf4j/Logger.info:(Ljava/lang/String;Ljava/lang/Object;)V
     151: aload_0
     152: invokevirtual #41                 // Method java/lang/Object.getClass:()Ljava/lang/Class;
     155: invokevirtual #42                 // Method java/lang/Class.getClassLoader:()Ljava/lang/ClassLoader;
     158: aload         6
     160: invokevirtual #43                 // Method java/lang/ClassLoader.getResourceAsStream:(Ljava/lang/String;)Ljava/io/InputStream;
     163: astore        7
     165: aconst_null
     166: astore        8
     168: aload_0
     169: aload         7
     171: ifnull        178
     174: iconst_1
     175: goto          179
     178: iconst_0
     179: ldc           #44                 // String CONFIG
     181: ldc           #45                 // String No resource %s
     183: iconst_1
     184: anewarray     #46                 // class java/lang/Object
     187: dup
     188: iconst_0
     189: aload         6
     191: aastore
     192: invokespecial #47                 // Method verify:(ZLjava/lang/String;Ljava/lang/String;[Ljava/lang/Object;)Z
     195: ifeq          203
     198: aload         6
     200: invokestatic  #48                 // Method org/apache/hadoop/conf/Configuration.addDefaultResource:(Ljava/lang/String;)V
     203: aload         7
     205: ifnull        290
     208: aload         8
     210: ifnull        233
     213: aload         7
     215: invokevirtual #49                 // Method java/io/InputStream.close:()V
     218: goto          290
     221: astore        9
     223: aload         8
     225: aload         9
     227: invokevirtual #51                 // Method java/lang/Throwable.addSuppressed:(Ljava/lang/Throwable;)V
     230: goto          290
     233: aload         7
     235: invokevirtual #49                 // Method java/io/InputStream.close:()V
     238: goto          290
     241: astore        9
     243: aload         9
     245: astore        8
     247: aload         9
     249: athrow
     250: astore        10
     252: aload         7
     254: ifnull        287
     257: aload         8
     259: ifnull        282
     262: aload         7
     264: invokevirtual #49                 // Method java/io/InputStream.close:()V
     267: goto          287
     270: astore        11
     272: aload         8
     274: aload         11
     276: invokevirtual #51                 // Method java/lang/Throwable.addSuppressed:(Ljava/lang/Throwable;)V
     279: goto          287
     282: aload         7
     284: invokevirtual #49                 // Method java/io/InputStream.close:()V
     287: aload         10
     289: athrow
     290: goto          126
     293: aload_2
     294: invokeinterface #52,  1           // InterfaceMethod java/util/List.isEmpty:()Z
     299: ifne          378
     302: aload_0
     303: ldc           #53                 // String Unknown arguments in command:
     305: iconst_0
     306: anewarray     #46                 // class java/lang/Object
     309: invokespecial #54                 // Method println:(Ljava/lang/String;[Ljava/lang/Object;)V
     312: aload_2
     313: invokeinterface #55,  1           // InterfaceMethod java/util/List.iterator:()Ljava/util/Iterator;
     318: astore        7
     320: aload         7
     322: invokeinterface #56,  1           // InterfaceMethod java/util/Iterator.hasNext:()Z
     327: ifeq          360
     330: aload         7
     332: invokeinterface #57,  1           // InterfaceMethod java/util/Iterator.next:()Ljava/lang/Object;
     337: checkcast     #58                 // class java/lang/String
     340: astore        8
     342: aload_0
     343: ldc           #59                 // String   \"%s\"
     345: iconst_1
     346: anewarray     #46                 // class java/lang/Object
     349: dup
     350: iconst_0
     351: aload         8
     353: aastore
     354: invokespecial #54                 // Method println:(Ljava/lang/String;[Ljava/lang/Object;)V
     357: goto          320
     360: aload_0
     361: invokespecial #60                 // Method println:()V
     364: aload_0
     365: aload_0
     366: invokespecial #61                 // Method usage:()Ljava/lang/String;
     369: iconst_0
     370: anewarray     #46                 // class java/lang/Object
     373: invokespecial #54                 // Method println:(Ljava/lang/String;[Ljava/lang/Object;)V
     376: iconst_m1
     377: ireturn
     378: aload         4
     380: ifnull        420
     383: aload_0
     384: ldc           #62                 // String Printing output to %s
     386: iconst_1
     387: anewarray     #46                 // class java/lang/Object
     390: dup
     391: iconst_0
     392: aload         4
     394: aastore
     395: invokespecial #54                 // Method println:(Ljava/lang/String;[Ljava/lang/Object;)V
     398: aload_0
     399: new           #63                 // class java/io/PrintWriter
     402: dup
     403: new           #25                 // class java/io/File
     406: dup
     407: aload         4
     409: invokespecial #26                 // Method java/io/File."<init>":(Ljava/lang/String;)V
     412: ldc           #64                 // String UTF-8
     414: invokespecial #65                 // Method java/io/PrintWriter."<init>":(Ljava/io/File;Ljava/lang/String;)V
     417: putfield      #14                 // Field out:Ljava/io/PrintWriter;
     420: aload_0
     421: invokevirtual #66                 // Method execute:()Z
     424: pop
     425: aload_0
     426: getfield      #11                 // Field probeHasFailed:Z
     429: ifeq          437
     432: bipush        41
     434: goto          438
     437: iconst_0
     438: ireturn
    Exception table:
       from    to  target type
         213   218   221   Class java/lang/Throwable
         168   203   241   Class java/lang/Throwable
         168   203   250   any
         262   267   270   Class java/lang/Throwable
         241   252   250   any

  private java.lang.String usage();
    Code:
       0: new           #67                 // class java/lang/StringBuilder
       3: dup
       4: invokespecial #68                 // Method java/lang/StringBuilder."<init>":()V
       7: ldc           #69                 // String KDiag: Diagnose Kerberos Problems\n
       9: invokevirtual #70                 // Method java/lang/StringBuilder.append:(Ljava/lang/String;)Ljava/lang/StringBuilder;
      12: aload_0
      13: ldc           #71                 // String -D
      15: ldc           #72                 // String key=value
      17: ldc           #73                 // String Define a configuration option
      19: invokespecial #74                 // Method arg:(Ljava/lang/String;Ljava/lang/String;Ljava/lang/String;)Ljava/lang/String;
      22: invokevirtual #70                 // Method java/lang/StringBuilder.append:(Ljava/lang/String;)Ljava/lang/StringBuilder;
      25: aload_0
      26: ldc           #34                 // String --jaas
      28: ldc           #75                 // String
      30: ldc           #76                 // String Require a JAAS file to be defined in java.security.auth.login.config
      32: invokespecial #74                 // Method arg:(Ljava/lang/String;Ljava/lang/String;Ljava/lang/String;)Ljava/lang/String;
      35: invokevirtual #70                 // Method java/lang/StringBuilder.append:(Ljava/lang/String;)Ljava/lang/StringBuilder;
      38: aload_0
      39: ldc           #29                 // String --keylen
      41: ldc           #77                 // String <keylen>
      43: new           #67                 // class java/lang/StringBuilder
      46: dup
      47: invokespecial #68                 // Method java/lang/StringBuilder."<init>":()V
      50: ldc           #78                 // String Require a minimum size for encryption keys supported by the JVM. Default value :
      52: invokevirtual #70                 // Method java/lang/StringBuilder.append:(Ljava/lang/String;)Ljava/lang/StringBuilder;
      55: aload_0
      56: getfield      #6                  // Field minKeyLength:J
      59: invokevirtual #79                 // Method java/lang/StringBuilder.append:(J)Ljava/lang/StringBuilder;
      62: invokevirtual #80                 // Method java/lang/StringBuilder.toString:()Ljava/lang/String;
      65: invokespecial #74                 // Method arg:(Ljava/lang/String;Ljava/lang/String;Ljava/lang/String;)Ljava/lang/String;
      68: invokevirtual #70                 // Method java/lang/StringBuilder.append:(Ljava/lang/String;)Ljava/lang/StringBuilder;
      71: aload_0
      72: ldc           #23                 // String --keytab
      74: ldc           #81                 // String <keytab> --principal <principal>
      76: ldc           #82                 // String Login from a keytab as a specific principal
      78: invokespecial #74                 // Method arg:(Ljava/lang/String;Ljava/lang/String;Ljava/lang/String;)Ljava/lang/String;
      81: invokevirtual #70                 // Method java/lang/StringBuilder.append:(Ljava/lang/String;)Ljava/lang/StringBuilder;
      84: aload_0
      85: ldc           #33                 // String --nofail
      87: ldc           #75                 // String
      89: ldc           #83                 // String Do not fail on the first problem
      91: invokespecial #74                 // Method arg:(Ljava/lang/String;Ljava/lang/String;Ljava/lang/String;)Ljava/lang/String;
      94: invokevirtual #70                 // Method java/lang/StringBuilder.append:(Ljava/lang/String;)Ljava/lang/StringBuilder;
      97: aload_0
      98: ldc           #35                 // String --nologin
     100: ldc           #75                 // String
     102: ldc           #84                 // String Do not attempt to log in
     104: invokespecial #74                 // Method arg:(Ljava/lang/String;Ljava/lang/String;Ljava/lang/String;)Ljava/lang/String;
     107: invokevirtual #70                 // Method java/lang/StringBuilder.append:(Ljava/lang/String;)Ljava/lang/StringBuilder;
     110: aload_0
     111: ldc           #28                 // String --out
     113: ldc           #85                 // String <file>
     115: ldc           #86                 // String Write output to a file
     117: invokespecial #74                 // Method arg:(Ljava/lang/String;Ljava/lang/String;Ljava/lang/String;)Ljava/lang/String;
     120: invokevirtual #70                 // Method java/lang/StringBuilder.append:(Ljava/lang/String;)Ljava/lang/StringBuilder;
     123: aload_0
     124: ldc           #37                 // String --resource
     126: ldc           #87                 // String <resource>
     128: ldc           #88                 // String Load an XML configuration resource
     130: invokespecial #74                 // Method arg:(Ljava/lang/String;Ljava/lang/String;Ljava/lang/String;)Ljava/lang/String;
     133: invokevirtual #70                 // Method java/lang/StringBuilder.append:(Ljava/lang/String;)Ljava/lang/StringBuilder;
     136: aload_0
     137: ldc           #31                 // String --secure
     139: ldc           #75                 // String
     141: ldc           #89                 // String Require the hadoop configuration to be secure
     143: invokespecial #74                 // Method arg:(Ljava/lang/String;Ljava/lang/String;Ljava/lang/String;)Ljava/lang/String;
     146: invokevirtual #70                 // Method java/lang/StringBuilder.append:(Ljava/lang/String;)Ljava/lang/StringBuilder;
     149: aload_0
     150: ldc           #36                 // String --verifyshortname
     152: ldc           #90                 // String --principal <principal>
     154: ldc           #91                 // String Verify the short name of the specific principal does not contain \'@\' or \'/\'
     156: invokespecial #74                 // Method arg:(Ljava/lang/String;Ljava/lang/String;Ljava/lang/String;)Ljava/lang/String;
     159: invokevirtual #70                 // Method java/lang/StringBuilder.append:(Ljava/lang/String;)Ljava/lang/StringBuilder;
     162: invokevirtual #80                 // Method java/lang/StringBuilder.toString:()Ljava/lang/String;
     165: areturn

  private java.lang.String arg(java.lang.String, java.lang.String, java.lang.String);
    Code:
       0: new           #67                 // class java/lang/StringBuilder
       3: dup
       4: invokespecial #68                 // Method java/lang/StringBuilder."<init>":()V
       7: ldc           #92                 // String   [%s%s%s] : %s
       9: iconst_4
      10: anewarray     #46                 // class java/lang/Object
      13: dup
      14: iconst_0
      15: aload_1
      16: aastore
      17: dup
      18: iconst_1
      19: aload_2
      20: invokevirtual #93                 // Method java/lang/String.isEmpty:()Z
      23: ifne          31
      26: ldc           #94                 // String
      28: goto          33
      31: ldc           #75                 // String
      33: aastore
      34: dup
      35: iconst_2
      36: aload_2
      37: aastore
      38: dup
      39: iconst_3
      40: aload_3
      41: aastore
      42: invokestatic  #95                 // Method java/lang/String.format:(Ljava/lang/String;[Ljava/lang/Object;)Ljava/lang/String;
      45: invokevirtual #70                 // Method java/lang/StringBuilder.append:(Ljava/lang/String;)Ljava/lang/StringBuilder;
      48: ldc           #96                 // String .\n
      50: invokevirtual #70                 // Method java/lang/StringBuilder.append:(Ljava/lang/String;)Ljava/lang/StringBuilder;
      53: invokevirtual #80                 // Method java/lang/StringBuilder.toString:()Ljava/lang/String;
      56: areturn

  public boolean execute() throws java.lang.Exception;
    Code:
       0: aload_0
       1: ldc           #97                 // String Kerberos Diagnostics scan at %s
       3: iconst_1
       4: anewarray     #46                 // class java/lang/Object
       7: dup
       8: iconst_0
       9: new           #98                 // class java/util/Date
      12: dup
      13: invokestatic  #99                 // Method java/lang/System.currentTimeMillis:()J
      16: invokespecial #100                // Method java/util/Date."<init>":(J)V
      19: aastore
      20: invokespecial #101                // Method title:(Ljava/lang/String;[Ljava/lang/Object;)V
      23: aload_0
      24: ldc           #102                // String Hostname = %s
      26: iconst_1
      27: anewarray     #46                 // class java/lang/Object
      30: dup
      31: iconst_0
      32: invokestatic  #103                // Method java/net/InetAddress.getLocalHost:()Ljava/net/InetAddress;
      35: invokevirtual #104                // Method java/net/InetAddress.getCanonicalHostName:()Ljava/lang/String;
      38: aastore
      39: invokespecial #54                 // Method println:(Ljava/lang/String;[Ljava/lang/Object;)V
      42: aload_0
      43: ldc           #105                // String %s = %d
      45: iconst_2
      46: anewarray     #46                 // class java/lang/Object
      49: dup
      50: iconst_0
      51: ldc           #29                 // String --keylen
      53: aastore
      54: dup
      55: iconst_1
      56: aload_0
      57: getfield      #6                  // Field minKeyLength:J
      60: invokestatic  #106                // Method java/lang/Long.valueOf:(J)Ljava/lang/Long;
      63: aastore
      64: invokespecial #54                 // Method println:(Ljava/lang/String;[Ljava/lang/Object;)V
      67: aload_0
      68: ldc           #107                // String %s = %s
      70: iconst_2
      71: anewarray     #46                 // class java/lang/Object
      74: dup
      75: iconst_0
      76: ldc           #23                 // String --keytab
      78: aastore
      79: dup
      80: iconst_1
      81: aload_0
      82: getfield      #12                 // Field keytab:Ljava/io/File;
      85: aastore
      86: invokespecial #54                 // Method println:(Ljava/lang/String;[Ljava/lang/Object;)V
      89: aload_0
      90: ldc           #107                // String %s = %s
      92: iconst_2
      93: anewarray     #46                 // class java/lang/Object
      96: dup
      97: iconst_0
      98: ldc           #27                 // String --principal
     100: aastore
     101: dup
     102: iconst_1
     103: aload_0
     104: getfield      #13                 // Field principal:Ljava/lang/String;
     107: aastore
     108: invokespecial #54                 // Method println:(Ljava/lang/String;[Ljava/lang/Object;)V
     111: aload_0
     112: ldc           #107                // String %s = %s
     114: iconst_2
     115: anewarray     #46                 // class java/lang/Object
     118: dup
     119: iconst_0
     120: ldc           #36                 // String --verifyshortname
     122: aastore
     123: dup
     124: iconst_1
     125: aload_0
     126: getfield      #10                 // Field checkShortName:Z
     129: invokestatic  #108                // Method java/lang/Boolean.valueOf:(Z)Ljava/lang/Boolean;
     132: aastore
     133: invokespecial #54                 // Method println:(Ljava/lang/String;[Ljava/lang/Object;)V
     136: aload_0
     137: invokevirtual #109                // Method validateKeyLength:()V
     140: aload_0
     141: ldc           #110                // String JVM Kerberos Login Module = %s
     143: iconst_1
     144: anewarray     #46                 // class java/lang/Object
     147: dup
     148: iconst_0
     149: invokestatic  #111                // Method org/apache/hadoop/security/authentication/util/KerberosUtil.getKrb5LoginModuleName:()Ljava/lang/String;
     152: aastore
     153: invokespecial #54                 // Method println:(Ljava/lang/String;[Ljava/lang/Object;)V
     156: aload_0
     157: ldc           #112                // String Core System Properties
     159: iconst_0
     160: anewarray     #46                 // class java/lang/Object
     163: invokespecial #101                // Method title:(Ljava/lang/String;[Ljava/lang/Object;)V
     166: bipush        9
     168: anewarray     #58                 // class java/lang/String
     171: dup
     172: iconst_0
     173: ldc           #113                // String user.name
     175: aastore
     176: dup
     177: iconst_1
     178: ldc           #114                // String java.version
     180: aastore
     181: dup
     182: iconst_2
     183: ldc           #115                // String java.vendor
     185: aastore
     186: dup
     187: iconst_3
     188: ldc           #116                // String java.security.krb5.conf
     190: aastore
     191: dup
     192: iconst_4
     193: ldc           #117                // String java.security.krb5.realm
     195: aastore
     196: dup
     197: iconst_5
     198: ldc           #118                // String java.security.krb5.kdc
     200: aastore
     201: dup
     202: bipush        6
     204: ldc           #119                // String sun.security.krb5.debug
     206: aastore
     207: dup
     208: bipush        7
     210: ldc           #120                // String sun.security.spnego.debug
     212: aastore
     213: dup
     214: bipush        8
     216: ldc           #121                // String java.security.auth.login.config
     218: aastore
     219: astore_1
     220: aload_1
     221: arraylength
     222: istore_2
     223: iconst_0
     224: istore_3
     225: iload_3
     226: iload_2
     227: if_icmpge     247
     230: aload_1
     231: iload_3
     232: aaload
     233: astore        4
     235: aload_0
     236: aload         4
     238: invokespecial #122                // Method printSysprop:(Ljava/lang/String;)V
     241: iinc          3, 1
     244: goto          225
     247: aload_0
     248: invokespecial #123                // Method endln:()V
     251: aload_0
     252: ldc           #124                // String All System Properties
     254: iconst_0
     255: anewarray     #46                 // class java/lang/Object
     258: invokespecial #101                // Method title:(Ljava/lang/String;[Ljava/lang/Object;)V
     261: new           #125                // class java/util/ArrayList
     264: dup
     265: invokestatic  #126                // Method java/lang/System.getProperties:()Ljava/util/Properties;
     268: invokevirtual #127                // Method java/util/Properties.stringPropertyNames:()Ljava/util/Set;
     271: invokespecial #128                // Method java/util/ArrayList."<init>":(Ljava/util/Collection;)V
     274: astore_1
     275: aload_1
     276: getstatic     #129                // Field java/lang/String.CASE_INSENSITIVE_ORDER:Ljava/util/Comparator;
     279: invokestatic  #130                // Method java/util/Collections.sort:(Ljava/util/List;Ljava/util/Comparator;)V
     282: aload_1
     283: invokevirtual #131                // Method java/util/ArrayList.iterator:()Ljava/util/Iterator;
     286: astore_2
     287: aload_2
     288: invokeinterface #56,  1           // InterfaceMethod java/util/Iterator.hasNext:()Z
     293: ifeq          314
     296: aload_2
     297: invokeinterface #57,  1           // InterfaceMethod java/util/Iterator.next:()Ljava/lang/Object;
     302: checkcast     #58                 // class java/lang/String
     305: astore_3
     306: aload_0
     307: aload_3
     308: invokespecial #122                // Method printSysprop:(Ljava/lang/String;)V
     311: goto          287
     314: aload_0
     315: invokespecial #123                // Method endln:()V
     318: aload_0
     319: ldc           #132                // String Environment Variables
     321: iconst_0
     322: anewarray     #46                 // class java/lang/Object
     325: invokespecial #101                // Method title:(Ljava/lang/String;[Ljava/lang/Object;)V
     328: bipush        9
     330: anewarray     #58                 // class java/lang/String
     333: dup
     334: iconst_0
     335: ldc           #133                // String HADOOP_JAAS_DEBUG
     337: aastore
     338: dup
     339: iconst_1
     340: ldc           #134                // String KRB5CCNAME
     342: aastore
     343: dup
     344: iconst_2
     345: ldc           #135                // String KRB5_CONFIG
     347: aastore
     348: dup
     349: iconst_3
     350: ldc           #136                // String HADOOP_USER_NAME
     352: aastore
     353: dup
     354: iconst_4
     355: ldc           #137                // String HADOOP_PROXY_USER
     357: aastore
     358: dup
     359: iconst_5
     360: ldc           #138                // String HADOOP_TOKEN_FILE_LOCATION
     362: aastore
     363: dup
     364: bipush        6
     366: ldc           #139                // String HADOOP_SECURE_LOG
     368: aastore
     369: dup
     370: bipush        7
     372: ldc           #140                // String HADOOP_OPTS
     374: aastore
     375: dup
     376: bipush        8
     378: ldc           #141                // String HADOOP_CLIENT_OPTS
     380: aastore
     381: astore_2
     382: aload_2
     383: arraylength
     384: istore_3
     385: iconst_0
     386: istore        4
     388: iload         4
     390: iload_3
     391: if_icmpge     412
     394: aload_2
     395: iload         4
     397: aaload
     398: astore        5
     400: aload_0
     401: aload         5
     403: invokespecial #142                // Method printEnv:(Ljava/lang/String;)V
     406: iinc          4, 1
     409: goto          388
     412: aload_0
     413: invokespecial #123                // Method endln:()V
     416: aload_0
     417: ldc           #143                // String Configuration Options
     419: iconst_0
     420: anewarray     #46                 // class java/lang/Object
     423: invokespecial #101                // Method title:(Ljava/lang/String;[Ljava/lang/Object;)V
     426: bipush        13
     428: anewarray     #58                 // class java/lang/String
     431: dup
     432: iconst_0
     433: ldc           #144                // String hadoop.kerberos.kinit.command
     435: aastore
     436: dup
     437: iconst_1
     438: ldc           #145                // String hadoop.security.authentication
     440: aastore
     441: dup
     442: iconst_2
     443: ldc           #146                // String hadoop.security.authorization
     445: aastore
     446: dup
     447: iconst_3
     448: ldc           #147                // String hadoop.kerberos.min.seconds.before.relogin
     450: aastore
     451: dup
     452: iconst_4
     453: ldc           #148                // String hadoop.security.dns.interface
     455: aastore
     456: dup
     457: iconst_5
     458: ldc           #149                // String hadoop.security.dns.nameserver
     460: aastore
     461: dup
     462: bipush        6
     464: ldc           #150                // String hadoop.rpc.protection
     466: aastore
     467: dup
     468: bipush        7
     470: ldc           #151                // String hadoop.security.saslproperties.resolver.class
     472: aastore
     473: dup
     474: bipush        8
     476: ldc           #152                // String hadoop.security.crypto.codec.classes
     478: aastore
     479: dup
     480: bipush        9
     482: ldc           #153                // String hadoop.security.group.mapping
     484: aastore
     485: dup
     486: bipush        10
     488: ldc           #154                // String hadoop.security.impersonation.provider.class
     490: aastore
     491: dup
     492: bipush        11
     494: ldc           #155                // String dfs.data.transfer.protection
     496: aastore
     497: dup
     498: bipush        12
     500: ldc           #156                // String dfs.data.transfer.saslproperties.resolver.class
     502: aastore
     503: astore_2
     504: aload_2
     505: arraylength
     506: istore_3
     507: iconst_0
     508: istore        4
     510: iload         4
     512: iload_3
     513: if_icmpge     534
     516: aload_2
     517: iload         4
     519: aaload
     520: astore        5
     522: aload_0
     523: aload         5
     525: invokespecial #157                // Method printConfOpt:(Ljava/lang/String;)V
     528: iinc          4, 1
     531: goto          510
     534: aload_0
     535: invokevirtual #158                // Method getConf:()Lorg/apache/hadoop/conf/Configuration;
     538: astore_2
     539: aload_0
     540: aload_2
     541: invokevirtual #159                // Method isSimpleAuthentication:(Lorg/apache/hadoop/conf/Configuration;)Z
     544: ifeq          586
     547: aload_0
     548: ldc           #160                // String Hadoop authentication is disabled
     550: iconst_0
     551: anewarray     #46                 // class java/lang/Object
     554: invokespecial #54                 // Method println:(Ljava/lang/String;[Ljava/lang/Object;)V
     557: aload_0
     558: aload_0
     559: getfield      #15                 // Field securityRequired:Z
     562: ldc           #44                 // String CONFIG
     564: ldc           #160                // String Hadoop authentication is disabled
     566: iconst_0
     567: anewarray     #46                 // class java/lang/Object
     570: invokespecial #161                // Method failif:(ZLjava/lang/String;Ljava/lang/String;[Ljava/lang/Object;)V
     573: getstatic     #38                 // Field LOG:Lorg/slf4j/Logger;
     576: ldc           #162                // String Security is not enabled for the Hadoop cluster
     578: invokeinterface #163,  2          // InterfaceMethod org/slf4j/Logger.warn:(Ljava/lang/String;)V
     583: goto          626
     586: aload_0
     587: new           #164                // class org/apache/hadoop/conf/Configuration
     590: dup
     591: invokespecial #165                // Method org/apache/hadoop/conf/Configuration."<init>":()V
     594: invokevirtual #159                // Method isSimpleAuthentication:(Lorg/apache/hadoop/conf/Configuration;)Z
     597: ifeq          626
     600: getstatic     #38                 // Field LOG:Lorg/slf4j/Logger;
     603: ldc           #166                // String The default cluster security is insecure
     605: invokeinterface #163,  2          // InterfaceMethod org/slf4j/Logger.warn:(Ljava/lang/String;)V
     610: aload_0
     611: aload_0
     612: getfield      #15                 // Field securityRequired:Z
     615: ldc           #44                 // String CONFIG
     617: ldc           #160                // String Hadoop authentication is disabled
     619: iconst_0
     620: anewarray     #46                 // class java/lang/Object
     623: invokespecial #161                // Method failif:(ZLjava/lang/String;Ljava/lang/String;[Ljava/lang/Object;)V
     626: aload_0
     627: ldc           #119                // String sun.security.krb5.debug
     629: invokespecial #167                // Method getAndSet:(Ljava/lang/String;)Z
     632: istore_3
     633: aload_0
     634: ldc           #120                // String sun.security.spnego.debug
     636: invokespecial #167                // Method getAndSet:(Ljava/lang/String;)Z
     639: istore        4
     641: aload_2
     642: invokestatic  #168                // Method org/apache/hadoop/security/UserGroupInformation.setConfiguration:(Lorg/apache/hadoop/conf/Configuration;)V
     645: aload_0
     646: aload_2
     647: invokespecial #169                // Method validateHadoopTokenFiles:(Lorg/apache/hadoop/conf/Configuration;)V
     650: aload_0
     651: invokespecial #170                // Method validateKrb5File:()V
     654: aload_0
     655: invokevirtual #171                // Method printDefaultRealm:()V
     658: aload_0
     659: ldc           #151                // String hadoop.security.saslproperties.resolver.class
     661: invokespecial #172                // Method validateSasl:(Ljava/lang/String;)V
     664: aload_2
     665: ldc           #156                // String dfs.data.transfer.saslproperties.resolver.class
     667: invokevirtual #173                // Method org/apache/hadoop/conf/Configuration.get:(Ljava/lang/String;)Ljava/lang/String;
     670: ifnull        679
     673: aload_0
     674: ldc           #156                // String dfs.data.transfer.saslproperties.resolver.class
     676: invokespecial #172                // Method validateSasl:(Ljava/lang/String;)V
     679: aload_0
     680: invokespecial #174                // Method validateKinitExecutable:()V
     683: aload_0
     684: aload_0
     685: getfield      #9                  // Field jaas:Z
     688: invokespecial #175                // Method validateJAAS:(Z)V
     691: aload_0
     692: invokespecial #176                // Method validateNTPConf:()V
     695: aload_0
     696: getfield      #10                 // Field checkShortName:Z
     699: ifeq          706
     702: aload_0
     703: invokevirtual #177                // Method validateShortName:()V
     706: aload_0
     707: getfield      #8                  // Field nologin:Z
     710: ifne          804
     713: aload_0
     714: ldc           #178                // String Logging in
     716: iconst_0
     717: anewarray     #46                 // class java/lang/Object
     720: invokespecial #101                // Method title:(Ljava/lang/String;[Ljava/lang/Object;)V
     723: aload_0
     724: getfield      #12                 // Field keytab:Ljava/io/File;
     727: ifnull        745
     730: aload_0
     731: aload_0
     732: getfield      #12                 // Field keytab:Ljava/io/File;
     735: invokespecial #179                // Method dumpKeytab:(Ljava/io/File;)V
     738: aload_0
     739: invokespecial #180                // Method loginFromKeytab:()V
     742: goto          804
     745: invokestatic  #181                // Method org/apache/hadoop/security/UserGroupInformation.getLoginUser:()Lorg/apache/hadoop/security/UserGroupInformation;
     748: astore        5
     750: aload_0
     751: ldc           #182                // String Log in user
     753: aload         5
     755: invokespecial #183                // Method dumpUGI:(Ljava/lang/String;Lorg/apache/hadoop/security/UserGroupInformation;)V
     758: aload_0
     759: ldc           #184                // String Login user
     761: aload         5
     763: invokespecial #185                // Method validateUGI:(Ljava/lang/String;Lorg/apache/hadoop/security/UserGroupInformation;)V
     766: aload_0
     767: ldc           #186                // String Ticket based login: %b
     769: iconst_1
     770: anewarray     #46                 // class java/lang/Object
     773: dup
     774: iconst_0
     775: invokestatic  #187                // Method org/apache/hadoop/security/UserGroupInformation.isLoginTicketBased:()Z
     778: invokestatic  #108                // Method java/lang/Boolean.valueOf:(Z)Ljava/lang/Boolean;
     781: aastore
     782: invokespecial #54                 // Method println:(Ljava/lang/String;[Ljava/lang/Object;)V
     785: aload_0
     786: ldc           #188                // String Keytab based login: %b
     788: iconst_1
     789: anewarray     #46                 // class java/lang/Object
     792: dup
     793: iconst_0
     794: invokestatic  #189                // Method org/apache/hadoop/security/UserGroupInformation.isLoginKeytabBased:()Z
     797: invokestatic  #108                // Method java/lang/Boolean.valueOf:(Z)Ljava/lang/Boolean;
     800: aastore
     801: invokespecial #54                 // Method println:(Ljava/lang/String;[Ljava/lang/Object;)V
     804: iconst_1
     805: istore        5
     807: ldc           #119                // String sun.security.krb5.debug
     809: iload_3
     810: invokestatic  #190                // Method java/lang/Boolean.toString:(Z)Ljava/lang/String;
     813: invokestatic  #191                // Method java/lang/System.setProperty:(Ljava/lang/String;Ljava/lang/String;)Ljava/lang/String;
     816: pop
     817: ldc           #120                // String sun.security.spnego.debug
     819: iload         4
     821: invokestatic  #190                // Method java/lang/Boolean.toString:(Z)Ljava/lang/String;
     824: invokestatic  #191                // Method java/lang/System.setProperty:(Ljava/lang/String;Ljava/lang/String;)Ljava/lang/String;
     827: pop
     828: iload         5
     830: ireturn
     831: astore        6
     833: ldc           #119                // String sun.security.krb5.debug
     835: iload_3
     836: invokestatic  #190                // Method java/lang/Boolean.toString:(Z)Ljava/lang/String;
     839: invokestatic  #191                // Method java/lang/System.setProperty:(Ljava/lang/String;Ljava/lang/String;)Ljava/lang/String;
     842: pop
     843: ldc           #120                // String sun.security.spnego.debug
     845: iload         4
     847: invokestatic  #190                // Method java/lang/Boolean.toString:(Z)Ljava/lang/String;
     850: invokestatic  #191                // Method java/lang/System.setProperty:(Ljava/lang/String;Ljava/lang/String;)Ljava/lang/String;
     853: pop
     854: aload         6
     856: athrow
    Exception table:
       from    to  target type
         641   807   831   any
         831   833   831   any

  protected boolean isSimpleAuthentication(org.apache.hadoop.conf.Configuration);
    Code:
       0: aload_1
       1: invokestatic  #192                // Method org/apache/hadoop/security/SecurityUtil.getAuthenticationMethod:(Lorg/apache/hadoop/conf/Configuration;)Lorg/apache/hadoop/security/UserGroupInformation$AuthenticationMethod;
       4: getstatic     #193                // Field org/apache/hadoop/security/UserGroupInformation$AuthenticationMethod.SIMPLE:Lorg/apache/hadoop/security/UserGroupInformation$AuthenticationMethod;
       7: invokevirtual #194                // Method org/apache/hadoop/security/UserGroupInformation$AuthenticationMethod.equals:(Ljava/lang/Object;)Z
      10: ireturn

  protected void validateKeyLength() throws java.security.NoSuchAlgorithmException;
    Code:
       0: ldc           #195                // String AES
       2: invokestatic  #196                // Method javax/crypto/Cipher.getMaxAllowedKeyLength:(Ljava/lang/String;)I
       5: istore_1
       6: aload_0
       7: ldc           #197                // String Maximum AES encryption key length %d bits
       9: iconst_1
      10: anewarray     #46                 // class java/lang/Object
      13: dup
      14: iconst_0
      15: iload_1
      16: invokestatic  #198                // Method java/lang/Integer.valueOf:(I)Ljava/lang/Integer;
      19: aastore
      20: invokespecial #54                 // Method println:(Ljava/lang/String;[Ljava/lang/Object;)V
      23: aload_0
      24: aload_0
      25: getfield      #6                  // Field minKeyLength:J
      28: iload_1
      29: i2l
      30: lcmp
      31: ifgt          38
      34: iconst_1
      35: goto          39
      38: iconst_0
      39: ldc           #199                // String JVM
      41: ldc           #200                // String Java Cryptography Extensions are not installed on this JVM. Maximum supported key length %s - minimum required %d
      43: iconst_2
      44: anewarray     #46                 // class java/lang/Object
      47: dup
      48: iconst_0
      49: iload_1
      50: invokestatic  #198                // Method java/lang/Integer.valueOf:(I)Ljava/lang/Integer;
      53: aastore
      54: dup
      55: iconst_1
      56: aload_0
      57: getfield      #6                  // Field minKeyLength:J
      60: invokestatic  #106                // Method java/lang/Long.valueOf:(J)Ljava/lang/Long;
      63: aastore
      64: invokespecial #47                 // Method verify:(ZLjava/lang/String;Ljava/lang/String;[Ljava/lang/Object;)Z
      67: pop
      68: return

  protected void validateShortName();
    Code:
       0: aload_0
       1: aload_0
       2: getfield      #13                 // Field principal:Ljava/lang/String;
       5: ifnonnull     12
       8: iconst_1
       9: goto          13
      12: iconst_0
      13: ldc           #201                // String KERBEROS
      15: ldc           #202                // String No principal defined
      17: iconst_0
      18: anewarray     #46                 // class java/lang/Object
      21: invokespecial #161                // Method failif:(ZLjava/lang/String;Ljava/lang/String;[Ljava/lang/Object;)V
      24: new           #203                // class org/apache/hadoop/security/authentication/util/KerberosName
      27: dup
      28: aload_0
      29: getfield      #13                 // Field principal:Ljava/lang/String;
      32: invokespecial #204                // Method org/apache/hadoop/security/authentication/util/KerberosName."<init>":(Ljava/lang/String;)V
      35: astore_1
      36: aload_1
      37: invokevirtual #205                // Method org/apache/hadoop/security/authentication/util/KerberosName.getShortName:()Ljava/lang/String;
      40: astore_2
      41: getstatic     #206                // Field nonSimplePattern:Ljava/util/regex/Pattern;
      44: aload_2
      45: invokevirtual #207                // Method java/util/regex/Pattern.matcher:(Ljava/lang/CharSequence;)Ljava/util/regex/Matcher;
      48: invokevirtual #208                // Method java/util/regex/Matcher.find:()Z
      51: ifeq          95
      54: aload_0
      55: ldc           #201                // String KERBEROS
      57: new           #67                 // class java/lang/StringBuilder
      60: dup
      61: invokespecial #68                 // Method java/lang/StringBuilder."<init>":()V
      64: aload_0
      65: getfield      #13                 // Field principal:Ljava/lang/String;
      68: invokevirtual #70                 // Method java/lang/StringBuilder.append:(Ljava/lang/String;)Ljava/lang/StringBuilder;
      71: ldc           #209                // String  short name:
      73: invokevirtual #70                 // Method java/lang/StringBuilder.append:(Ljava/lang/String;)Ljava/lang/StringBuilder;
      76: aload_2
      77: invokevirtual #70                 // Method java/lang/StringBuilder.append:(Ljava/lang/String;)Ljava/lang/StringBuilder;
      80: ldc           #210                // String  still contains @ or /
      82: invokevirtual #70                 // Method java/lang/StringBuilder.append:(Ljava/lang/String;)Ljava/lang/StringBuilder;
      85: invokevirtual #80                 // Method java/lang/StringBuilder.toString:()Ljava/lang/String;
      88: iconst_0
      89: anewarray     #46                 // class java/lang/Object
      92: invokespecial #211                // Method warn:(Ljava/lang/String;Ljava/lang/String;[Ljava/lang/Object;)V
      95: goto          189
      98: astore_1
      99: new           #213                // class org/apache/hadoop/security/KDiag$KerberosDiagsFailure
     102: dup
     103: ldc           #201                // String KERBEROS
     105: aload_1
     106: new           #67                 // class java/lang/StringBuilder
     109: dup
     110: invokespecial #68                 // Method java/lang/StringBuilder."<init>":()V
     113: ldc           #214                // String Failed to get short name for
     115: invokevirtual #70                 // Method java/lang/StringBuilder.append:(Ljava/lang/String;)Ljava/lang/StringBuilder;
     118: aload_0
     119: getfield      #13                 // Field principal:Ljava/lang/String;
     122: invokevirtual #70                 // Method java/lang/StringBuilder.append:(Ljava/lang/String;)Ljava/lang/StringBuilder;
     125: invokevirtual #80                 // Method java/lang/StringBuilder.toString:()Ljava/lang/String;
     128: iconst_1
     129: anewarray     #46                 // class java/lang/Object
     132: dup
     133: iconst_0
     134: aload_1
     135: aastore
     136: invokespecial #215                // Method org/apache/hadoop/security/KDiag$KerberosDiagsFailure."<init>":(Ljava/lang/String;Ljava/lang/Throwable;Ljava/lang/String;[Ljava/lang/Object;)V
     139: athrow
     140: astore_1
     141: aload_0
     142: ldc           #201                // String KERBEROS
     144: new           #67                 // class java/lang/StringBuilder
     147: dup
     148: invokespecial #68                 // Method java/lang/StringBuilder."<init>":()V
     151: ldc           #217                // String KerberosName(
     153: invokevirtual #70                 // Method java/lang/StringBuilder.append:(Ljava/lang/String;)Ljava/lang/StringBuilder;
     156: aload_0
     157: getfield      #13                 // Field principal:Ljava/lang/String;
     160: invokevirtual #70                 // Method java/lang/StringBuilder.append:(Ljava/lang/String;)Ljava/lang/StringBuilder;
     163: ldc           #218                // String ) failed: %s\n%s
     165: invokevirtual #70                 // Method java/lang/StringBuilder.append:(Ljava/lang/String;)Ljava/lang/StringBuilder;
     168: invokevirtual #80                 // Method java/lang/StringBuilder.toString:()Ljava/lang/String;
     171: iconst_2
     172: anewarray     #46                 // class java/lang/Object
     175: dup
     176: iconst_0
     177: aload_1
     178: aastore
     179: dup
     180: iconst_1
     181: aload_1
     182: invokestatic  #219                // Method org/apache/hadoop/util/StringUtils.stringifyException:(Ljava/lang/Throwable;)Ljava/lang/String;
     185: aastore
     186: invokespecial #220                // Method error:(Ljava/lang/String;Ljava/lang/String;[Ljava/lang/Object;)V
     189: return
    Exception table:
       from    to  target type
          24    95    98   Class java/io/IOException
          24    95   140   Class java/lang/IllegalArgumentException

  protected void printDefaultRealm();
    Code:
       0: invokestatic  #221                // Method org/apache/hadoop/security/authentication/util/KerberosUtil.getDefaultRealm:()Ljava/lang/String;
       3: astore_1
       4: aload_0
       5: ldc           #222                // String Default Realm = %s
       7: iconst_1
       8: anewarray     #46                 // class java/lang/Object
      11: dup
      12: iconst_0
      13: aload_1
      14: aastore
      15: invokespecial #54                 // Method println:(Ljava/lang/String;[Ljava/lang/Object;)V
      18: aload_1
      19: ifnonnull     34
      22: aload_0
      23: ldc           #201                // String KERBEROS
      25: ldc           #223                // String Host has no default realm
      27: iconst_0
      28: anewarray     #46                 // class java/lang/Object
      31: invokespecial #211                // Method warn:(Ljava/lang/String;Ljava/lang/String;[Ljava/lang/Object;)V
      34: goto          156
      37: astore_1
      38: new           #213                // class org/apache/hadoop/security/KDiag$KerberosDiagsFailure
      41: dup
      42: ldc           #199                // String JVM
      44: aload_1
      45: new           #67                 // class java/lang/StringBuilder
      48: dup
      49: invokespecial #68                 // Method java/lang/StringBuilder."<init>":()V
      52: ldc           #227                // String Failed to invoke krb5.Config.getDefaultRealm: %s:
      54: invokevirtual #70                 // Method java/lang/StringBuilder.append:(Ljava/lang/String;)Ljava/lang/StringBuilder;
      57: aload_1
      58: invokevirtual #228                // Method java/lang/StringBuilder.append:(Ljava/lang/Object;)Ljava/lang/StringBuilder;
      61: invokevirtual #80                 // Method java/lang/StringBuilder.toString:()Ljava/lang/String;
      64: iconst_1
      65: anewarray     #46                 // class java/lang/Object
      68: dup
      69: iconst_0
      70: aload_1
      71: aastore
      72: invokespecial #215                // Method org/apache/hadoop/security/KDiag$KerberosDiagsFailure."<init>":(Ljava/lang/String;Ljava/lang/Throwable;Ljava/lang/String;[Ljava/lang/Object;)V
      75: athrow
      76: astore_1
      77: aload_1
      78: invokevirtual #230                // Method java/lang/reflect/InvocationTargetException.getCause:()Ljava/lang/Throwable;
      81: ifnull        91
      84: aload_1
      85: invokevirtual #230                // Method java/lang/reflect/InvocationTargetException.getCause:()Ljava/lang/Throwable;
      88: goto          92
      91: aload_1
      92: astore_2
      93: aload_2
      94: invokevirtual #231                // Method java/lang/Throwable.toString:()Ljava/lang/String;
      97: ldc           #232                // String Cannot locate default realm
      99: invokevirtual #233                // Method java/lang/String.contains:(Ljava/lang/CharSequence;)Z
     102: ifeq          133
     105: aload_0
     106: ldc           #201                // String KERBEROS
     108: ldc           #223                // String Host has no default realm
     110: iconst_0
     111: anewarray     #46                 // class java/lang/Object
     114: invokespecial #211                // Method warn:(Ljava/lang/String;Ljava/lang/String;[Ljava/lang/Object;)V
     117: getstatic     #38                 // Field LOG:Lorg/slf4j/Logger;
     120: aload_2
     121: invokevirtual #231                // Method java/lang/Throwable.toString:()Ljava/lang/String;
     124: aload_2
     125: invokeinterface #234,  3          // InterfaceMethod org/slf4j/Logger.debug:(Ljava/lang/String;Ljava/lang/Throwable;)V
     130: goto          156
     133: aload_0
     134: ldc           #201                // String KERBEROS
     136: ldc           #235                // String Kerberos.getDefaultRealm() failed: %s\n%s
     138: iconst_2
     139: anewarray     #46                 // class java/lang/Object
     142: dup
     143: iconst_0
     144: aload_2
     145: aastore
     146: dup
     147: iconst_1
     148: aload_2
     149: invokestatic  #219                // Method org/apache/hadoop/util/StringUtils.stringifyException:(Ljava/lang/Throwable;)Ljava/lang/String;
     152: aastore
     153: invokespecial #220                // Method error:(Ljava/lang/String;Ljava/lang/String;[Ljava/lang/Object;)V
     156: return
    Exception table:
       from    to  target type
           0    34    37   Class java/lang/ClassNotFoundException
           0    34    37   Class java/lang/IllegalAccessException
           0    34    37   Class java/lang/NoSuchMethodException
           0    34    76   Class java/lang/reflect/InvocationTargetException

  private void validateHadoopTokenFiles(org.apache.hadoop.conf.Configuration) throws java.lang.ClassNotFoundException, org.apache.hadoop.security.KDiag$KerberosDiagsFailure, java.lang.NoSuchMethodException, java.lang.SecurityException;
    Code:
       0: aload_0
       1: ldc           #236                // String Locating Hadoop token files
       3: iconst_0
       4: anewarray     #46                 // class java/lang/Object
       7: invokespecial #101                // Method title:(Ljava/lang/String;[Ljava/lang/Object;)V
      10: ldc           #237                // String hadoop.token.files
      12: invokestatic  #238                // Method java/lang/System.getProperty:(Ljava/lang/String;)Ljava/lang/String;
      15: astore_2
      16: aload_2
      17: ifnull        47
      20: aload_0
      21: new           #67                 // class java/lang/StringBuilder
      24: dup
      25: invokespecial #68                 // Method java/lang/StringBuilder."<init>":()V
      28: ldc           #239                // String Found hadoop.token.files in system properties :
      30: invokevirtual #70                 // Method java/lang/StringBuilder.append:(Ljava/lang/String;)Ljava/lang/StringBuilder;
      33: aload_2
      34: invokevirtual #70                 // Method java/lang/StringBuilder.append:(Ljava/lang/String;)Ljava/lang/StringBuilder;
      37: invokevirtual #80                 // Method java/lang/StringBuilder.toString:()Ljava/lang/String;
      40: iconst_0
      41: anewarray     #46                 // class java/lang/Object
      44: invokespecial #54                 // Method println:(Ljava/lang/String;[Ljava/lang/Object;)V
      47: aload_1
      48: ldc           #237                // String hadoop.token.files
      50: invokevirtual #173                // Method org/apache/hadoop/conf/Configuration.get:(Ljava/lang/String;)Ljava/lang/String;
      53: ifnull        116
      56: aload_0
      57: new           #67                 // class java/lang/StringBuilder
      60: dup
      61: invokespecial #68                 // Method java/lang/StringBuilder."<init>":()V
      64: ldc           #240                // String Found hadoop.token.files in hadoop configuration :
      66: invokevirtual #70                 // Method java/lang/StringBuilder.append:(Ljava/lang/String;)Ljava/lang/StringBuilder;
      69: aload_1
      70: ldc           #237                // String hadoop.token.files
      72: invokevirtual #173                // Method org/apache/hadoop/conf/Configuration.get:(Ljava/lang/String;)Ljava/lang/String;
      75: invokevirtual #70                 // Method java/lang/StringBuilder.append:(Ljava/lang/String;)Ljava/lang/StringBuilder;
      78: invokevirtual #80                 // Method java/lang/StringBuilder.toString:()Ljava/lang/String;
      81: iconst_0
      82: anewarray     #46                 // class java/lang/Object
      85: invokespecial #54                 // Method println:(Ljava/lang/String;[Ljava/lang/Object;)V
      88: ldc           #237                // String hadoop.token.files
      90: invokestatic  #238                // Method java/lang/System.getProperty:(Ljava/lang/String;)Ljava/lang/String;
      93: ifnull        109
      96: aload_0
      97: ldc           #241                // String hadoop.token.files in the system properties overrides the one specified in hadoop configuration
      99: iconst_0
     100: anewarray     #46                 // class java/lang/Object
     103: invokespecial #54                 // Method println:(Ljava/lang/String;[Ljava/lang/Object;)V
     106: goto          116
     109: aload_1
     110: ldc           #237                // String hadoop.token.files
     112: invokevirtual #173                // Method org/apache/hadoop/conf/Configuration.get:(Ljava/lang/String;)Ljava/lang/String;
     115: astore_2
     116: aload_2
     117: ifnull        193
     120: aload_2
     121: invokestatic  #242                // Method org/apache/hadoop/util/StringUtils.getTrimmedStrings:(Ljava/lang/String;)[Ljava/lang/String;
     124: astore_3
     125: aload_3
     126: arraylength
     127: istore        4
     129: iconst_0
     130: istore        5
     132: iload         5
     134: iload         4
     136: if_icmpge     193
     139: aload_3
     140: iload         5
     142: aaload
     143: astore        6
     145: aload         6
     147: invokevirtual #243                // Method java/lang/String.length:()I
     150: ifle          187
     153: new           #25                 // class java/io/File
     156: dup
     157: aload         6
     159: invokespecial #26                 // Method java/io/File."<init>":(Ljava/lang/String;)V
     162: astore        7
     164: aload_0
     165: aload         7
     167: ldc           #244                // String TOKEN
     169: ldc           #245                // String token
     171: invokespecial #246                // Method verifyFileIsValid:(Ljava/io/File;Ljava/lang/String;Ljava/lang/String;)Z
     174: pop
     175: aload_0
     176: aload         7
     178: aload_1
     179: ldc           #244                // String TOKEN
     181: ldc           #245                // String token
     183: invokespecial #247                // Method verify:(Ljava/io/File;Lorg/apache/hadoop/conf/Configuration;Ljava/lang/String;Ljava/lang/String;)Z
     186: pop
     187: iinc          5, 1
     190: goto          132
     193: return

  private void validateKrb5File() throws java.io.IOException;
    Code:
       0: getstatic     #248                // Field org/apache/hadoop/util/Shell.WINDOWS:Z
       3: ifne          152
       6: aload_0
       7: ldc           #249                // String Locating Kerberos configuration file
       9: iconst_0
      10: anewarray     #46                 // class java/lang/Object
      13: invokespecial #101                // Method title:(Ljava/lang/String;[Ljava/lang/Object;)V
      16: ldc           #250                // String /etc/krb5.conf
      18: astore_1
      19: ldc           #116                // String java.security.krb5.conf
      21: invokestatic  #238                // Method java/lang/System.getProperty:(Ljava/lang/String;)Ljava/lang/String;
      24: astore_2
      25: aload_2
      26: ifnull        57
      29: aload_2
      30: invokevirtual #93                 // Method java/lang/String.isEmpty:()Z
      33: ifne          57
      36: aload_0
      37: ldc           #251                // String Setting kerberos path from sysprop %s: \"%s\"
      39: iconst_2
      40: anewarray     #46                 // class java/lang/Object
      43: dup
      44: iconst_0
      45: ldc           #116                // String java.security.krb5.conf
      47: aastore
      48: dup
      49: iconst_1
      50: aload_2
      51: aastore
      52: invokespecial #54                 // Method println:(Ljava/lang/String;[Ljava/lang/Object;)V
      55: aload_2
      56: astore_1
      57: ldc           #135                // String KRB5_CONFIG
      59: invokestatic  #252                // Method java/lang/System.getenv:(Ljava/lang/String;)Ljava/lang/String;
      62: astore_3
      63: aload_3
      64: ifnull        117
      67: aload_0
      68: ldc           #253                // String Setting kerberos path from environment variable %s: \"%s\"
      70: iconst_2
      71: anewarray     #46                 // class java/lang/Object
      74: dup
      75: iconst_0
      76: ldc           #135                // String KRB5_CONFIG
      78: aastore
      79: dup
      80: iconst_1
      81: aload_3
      82: aastore
      83: invokespecial #54                 // Method println:(Ljava/lang/String;[Ljava/lang/Object;)V
      86: aload_3
      87: astore_1
      88: aload_2
      89: ifnull        117
      92: aload_0
      93: ldc           #254                // String Warning - both %s and %s were set - %s takes priority
      95: iconst_3
      96: anewarray     #46                 // class java/lang/Object
      99: dup
     100: iconst_0
     101: ldc           #116                // String java.security.krb5.conf
     103: aastore
     104: dup
     105: iconst_1
     106: ldc           #135                // String KRB5_CONFIG
     108: aastore
     109: dup
     110: iconst_2
     111: ldc           #135                // String KRB5_CONFIG
     113: aastore
     114: invokespecial #54                 // Method println:(Ljava/lang/String;[Ljava/lang/Object;)V
     117: new           #25                 // class java/io/File
     120: dup
     121: aload_1
     122: invokespecial #26                 // Method java/io/File."<init>":(Ljava/lang/String;)V
     125: astore        4
     127: aload_0
     128: ldc           #255                // String Kerberos configuration file = %s
     130: iconst_1
     131: anewarray     #46                 // class java/lang/Object
     134: dup
     135: iconst_0
     136: aload         4
     138: aastore
     139: invokespecial #54                 // Method println:(Ljava/lang/String;[Ljava/lang/Object;)V
     142: aload_0
     143: aload         4
     145: invokespecial #256                // Method dump:(Ljava/io/File;)V
     148: aload_0
     149: invokespecial #123                // Method endln:()V
     152: return

  private void dumpKeytab(java.io.File) throws java.io.IOException;
    Code:
       0: aload_0
       1: ldc_w         #257                // String Examining keytab %s
       4: iconst_1
       5: anewarray     #46                 // class java/lang/Object
       8: dup
       9: iconst_0
      10: aload_1
      11: aastore
      12: invokespecial #101                // Method title:(Ljava/lang/String;[Ljava/lang/Object;)V
      15: aload_1
      16: invokevirtual #258                // Method java/io/File.getCanonicalFile:()Ljava/io/File;
      19: astore_2
      20: aload_0
      21: aload_2
      22: ldc           #201                // String KERBEROS
      24: ldc_w         #259                // String keytab
      27: invokespecial #246                // Method verifyFileIsValid:(Ljava/io/File;Ljava/lang/String;Ljava/lang/String;)Z
      30: pop
      31: aload_2
      32: invokestatic  #260                // Method org/apache/kerby/kerberos/kerb/keytab/Keytab.loadKeytab:(Ljava/io/File;)Lorg/apache/kerby/kerberos/kerb/keytab/Keytab;
      35: astore_3
      36: aload_3
      37: invokevirtual #261                // Method org/apache/kerby/kerberos/kerb/keytab/Keytab.getPrincipals:()Ljava/util/List;
      40: astore        4
      42: aload_0
      43: ldc_w         #262                // String keytab principal count: %d
      46: iconst_1
      47: anewarray     #46                 // class java/lang/Object
      50: dup
      51: iconst_0
      52: aload         4
      54: invokeinterface #263,  1          // InterfaceMethod java/util/List.size:()I
      59: invokestatic  #198                // Method java/lang/Integer.valueOf:(I)Ljava/lang/Integer;
      62: aastore
      63: invokespecial #54                 // Method println:(Ljava/lang/String;[Ljava/lang/Object;)V
      66: iconst_0
      67: istore        5
      69: aload         4
      71: invokeinterface #55,  1           // InterfaceMethod java/util/List.iterator:()Ljava/util/Iterator;
      76: astore        6
      78: aload         6
      80: invokeinterface #56,  1           // InterfaceMethod java/util/Iterator.hasNext:()Z
      85: ifeq          210
      88: aload         6
      90: invokeinterface #57,  1           // InterfaceMethod java/util/Iterator.next:()Ljava/lang/Object;
      95: checkcast     #264                // class org/apache/kerby/kerberos/kerb/type/base/PrincipalName
      98: astore        7
     100: aload_3
     101: aload         7
     103: invokevirtual #265                // Method org/apache/kerby/kerberos/kerb/keytab/Keytab.getKeytabEntries:(Lorg/apache/kerby/kerberos/kerb/type/base/PrincipalName;)Ljava/util/List;
     106: astore        8
     108: iload         5
     110: aload         8
     112: invokeinterface #263,  1          // InterfaceMethod java/util/List.size:()I
     117: iadd
     118: istore        5
     120: aload         8
     122: invokeinterface #55,  1           // InterfaceMethod java/util/List.iterator:()Ljava/util/Iterator;
     127: astore        9
     129: aload         9
     131: invokeinterface #56,  1           // InterfaceMethod java/util/Iterator.hasNext:()Z
     136: ifeq          207
     139: aload         9
     141: invokeinterface #57,  1           // InterfaceMethod java/util/Iterator.next:()Ljava/lang/Object;
     146: checkcast     #266                // class org/apache/kerby/kerberos/kerb/keytab/KeytabEntry
     149: astore        10
     151: aload         10
     153: invokevirtual #267                // Method org/apache/kerby/kerberos/kerb/keytab/KeytabEntry.getKey:()Lorg/apache/kerby/kerberos/kerb/type/base/EncryptionKey;
     156: astore        11
     158: aload_0
     159: ldc_w         #268                // String  %s: version=%d expires=%s encryption=%s
     162: iconst_4
     163: anewarray     #46                 // class java/lang/Object
     166: dup
     167: iconst_0
     168: aload         10
     170: invokevirtual #269                // Method org/apache/kerby/kerberos/kerb/keytab/KeytabEntry.getPrincipal:()Lorg/apache/kerby/kerberos/kerb/type/base/PrincipalName;
     173: aastore
     174: dup
     175: iconst_1
     176: aload         10
     178: invokevirtual #270                // Method org/apache/kerby/kerberos/kerb/keytab/KeytabEntry.getKvno:()I
     181: invokestatic  #198                // Method java/lang/Integer.valueOf:(I)Ljava/lang/Integer;
     184: aastore
     185: dup
     186: iconst_2
     187: aload         10
     189: invokevirtual #271                // Method org/apache/kerby/kerberos/kerb/keytab/KeytabEntry.getTimestamp:()Lorg/apache/kerby/kerberos/kerb/type/KerberosTime;
     192: aastore
     193: dup
     194: iconst_3
     195: aload         11
     197: invokevirtual #272                // Method org/apache/kerby/kerberos/kerb/type/base/EncryptionKey.getKeyType:()Lorg/apache/kerby/kerberos/kerb/type/base/EncryptionType;
     200: aastore
     201: invokespecial #54                 // Method println:(Ljava/lang/String;[Ljava/lang/Object;)V
     204: goto          129
     207: goto          78
     210: aload_0
     211: ldc_w         #273                // String keytab entry count: %d
     214: iconst_1
     215: anewarray     #46                 // class java/lang/Object
     218: dup
     219: iconst_0
     220: iload         5
     222: invokestatic  #198                // Method java/lang/Integer.valueOf:(I)Ljava/lang/Integer;
     225: aastore
     226: invokespecial #54                 // Method println:(Ljava/lang/String;[Ljava/lang/Object;)V
     229: aload_0
     230: invokespecial #123                // Method endln:()V
     233: return

  private void loginFromKeytab() throws java.io.IOException;
    Code:
       0: aload_0
       1: getfield      #12                 // Field keytab:Ljava/io/File;
       4: ifnull        149
       7: aload_0
       8: getfield      #12                 // Field keytab:Ljava/io/File;
      11: invokevirtual #258                // Method java/io/File.getCanonicalFile:()Ljava/io/File;
      14: astore_3
      15: aload_0
      16: ldc_w         #274                // String Using keytab %s principal %s
      19: iconst_2
      20: anewarray     #46                 // class java/lang/Object
      23: dup
      24: iconst_0
      25: aload_3
      26: aastore
      27: dup
      28: iconst_1
      29: aload_0
      30: getfield      #13                 // Field principal:Ljava/lang/String;
      33: aastore
      34: invokespecial #54                 // Method println:(Ljava/lang/String;[Ljava/lang/Object;)V
      37: aload_0
      38: getfield      #13                 // Field principal:Ljava/lang/String;
      41: astore_2
      42: aload_0
      43: aload_0
      44: getfield      #13                 // Field principal:Ljava/lang/String;
      47: ifnonnull     54
      50: iconst_1
      51: goto          55
      54: iconst_0
      55: ldc           #201                // String KERBEROS
      57: ldc           #202                // String No principal defined
      59: iconst_0
      60: anewarray     #46                 // class java/lang/Object
      63: invokespecial #161                // Method failif:(ZLjava/lang/String;Ljava/lang/String;[Ljava/lang/Object;)V
      66: aload_0
      67: getfield      #13                 // Field principal:Ljava/lang/String;
      70: aload_3
      71: invokevirtual #275                // Method java/io/File.getPath:()Ljava/lang/String;
      74: invokestatic  #276                // Method org/apache/hadoop/security/UserGroupInformation.loginUserFromKeytabAndReturnUGI:(Ljava/lang/String;Ljava/lang/String;)Lorg/apache/hadoop/security/UserGroupInformation;
      77: astore_1
      78: aload_0
      79: aload_2
      80: aload_1
      81: invokespecial #183                // Method dumpUGI:(Ljava/lang/String;Lorg/apache/hadoop/security/UserGroupInformation;)V
      84: aload_0
      85: aload_0
      86: getfield      #13                 // Field principal:Ljava/lang/String;
      89: aload_1
      90: invokespecial #185                // Method validateUGI:(Ljava/lang/String;Lorg/apache/hadoop/security/UserGroupInformation;)V
      93: aload_0
      94: ldc_w         #277                // String Attempting to relogin
      97: iconst_0
      98: anewarray     #46                 // class java/lang/Object
     101: invokespecial #101                // Method title:(Ljava/lang/String;[Ljava/lang/Object;)V
     104: iconst_1
     105: invokestatic  #278                // Method org/apache/hadoop/security/UserGroupInformation.setShouldRenewImmediatelyForTests:(Z)V
     108: aload_1
     109: invokevirtual #279                // Method org/apache/hadoop/security/UserGroupInformation.reloginFromKeytab:()V
     112: goto          146
     115: astore        4
     117: aload_0
     118: ldc_w         #281                // String UGI
     121: ldc_w         #282                // String Failed to reset UGI -and so could not try to relogin
     124: iconst_0
     125: anewarray     #46                 // class java/lang/Object
     128: invokespecial #211                // Method warn:(Ljava/lang/String;Ljava/lang/String;[Ljava/lang/Object;)V
     131: getstatic     #38                 // Field LOG:Lorg/slf4j/Logger;
     134: ldc_w         #283                // String Failed to reset UGI: {}
     137: aload         4
     139: aload         4
     141: invokeinterface #284,  4          // InterfaceMethod org/slf4j/Logger.debug:(Ljava/lang/String;Ljava/lang/Object;Ljava/lang/Object;)V
     146: goto          160
     149: aload_0
     150: ldc_w         #285                // String No keytab: attempting to log in is as current user
     153: iconst_0
     154: anewarray     #46                 // class java/lang/Object
     157: invokespecial #54                 // Method println:(Ljava/lang/String;[Ljava/lang/Object;)V
     160: return
    Exception table:
       from    to  target type
         104   112   115   Class java/lang/IllegalAccessError

  private void dumpUGI(java.lang.String, org.apache.hadoop.security.UserGroupInformation) throws java.io.IOException;
    Code:
       0: aload_0
       1: aload_1
       2: iconst_0
       3: anewarray     #46                 // class java/lang/Object
       6: invokespecial #101                // Method title:(Ljava/lang/String;[Ljava/lang/Object;)V
       9: aload_0
      10: ldc_w         #286                // String UGI instance = %s
      13: iconst_1
      14: anewarray     #46                 // class java/lang/Object
      17: dup
      18: iconst_0
      19: aload_2
      20: aastore
      21: invokespecial #54                 // Method println:(Ljava/lang/String;[Ljava/lang/Object;)V
      24: aload_0
      25: ldc_w         #287                // String Has kerberos credentials: %b
      28: iconst_1
      29: anewarray     #46                 // class java/lang/Object
      32: dup
      33: iconst_0
      34: aload_2
      35: invokevirtual #288                // Method org/apache/hadoop/security/UserGroupInformation.hasKerberosCredentials:()Z
      38: invokestatic  #108                // Method java/lang/Boolean.valueOf:(Z)Ljava/lang/Boolean;
      41: aastore
      42: invokespecial #54                 // Method println:(Ljava/lang/String;[Ljava/lang/Object;)V
      45: aload_0
      46: ldc_w         #289                // String Authentication method: %s
      49: iconst_1
      50: anewarray     #46                 // class java/lang/Object
      53: dup
      54: iconst_0
      55: aload_2
      56: invokevirtual #290                // Method org/apache/hadoop/security/UserGroupInformation.getAuthenticationMethod:()Lorg/apache/hadoop/security/UserGroupInformation$AuthenticationMethod;
      59: aastore
      60: invokespecial #54                 // Method println:(Ljava/lang/String;[Ljava/lang/Object;)V
      63: aload_0
      64: ldc_w         #291                // String Real Authentication method: %s
      67: iconst_1
      68: anewarray     #46                 // class java/lang/Object
      71: dup
      72: iconst_0
      73: aload_2
      74: invokevirtual #292                // Method org/apache/hadoop/security/UserGroupInformation.getRealAuthenticationMethod:()Lorg/apache/hadoop/security/UserGroupInformation$AuthenticationMethod;
      77: aastore
      78: invokespecial #54                 // Method println:(Ljava/lang/String;[Ljava/lang/Object;)V
      81: aload_0
      82: ldc_w         #293                // String Group names
      85: iconst_0
      86: anewarray     #46                 // class java/lang/Object
      89: invokespecial #101                // Method title:(Ljava/lang/String;[Ljava/lang/Object;)V
      92: aload_2
      93: invokevirtual #294                // Method org/apache/hadoop/security/UserGroupInformation.getGroupNames:()[Ljava/lang/String;
      96: astore_3
      97: aload_3
      98: arraylength
      99: istore        4
     101: iconst_0
     102: istore        5
     104: iload         5
     106: iload         4
     108: if_icmpge     133
     111: aload_3
     112: iload         5
     114: aaload
     115: astore        6
     117: aload_0
     118: aload         6
     120: iconst_0
     121: anewarray     #46                 // class java/lang/Object
     124: invokespecial #54                 // Method println:(Ljava/lang/String;[Ljava/lang/Object;)V
     127: iinc          5, 1
     130: goto          104
     133: aload_0
     134: ldc_w         #295                // String Credentials
     137: iconst_0
     138: anewarray     #46                 // class java/lang/Object
     141: invokespecial #101                // Method title:(Ljava/lang/String;[Ljava/lang/Object;)V
     144: aload_2
     145: invokevirtual #296                // Method org/apache/hadoop/security/UserGroupInformation.getCredentials:()Lorg/apache/hadoop/security/Credentials;
     148: invokevirtual #297                // Method org/apache/hadoop/security/Credentials.getAllSecretKeys:()Ljava/util/List;
     151: astore_3
     152: aload_0
     153: ldc_w         #298                // String Secret keys
     156: iconst_0
     157: anewarray     #46                 // class java/lang/Object
     160: invokespecial #101                // Method title:(Ljava/lang/String;[Ljava/lang/Object;)V
     163: aload_3
     164: invokeinterface #52,  1           // InterfaceMethod java/util/List.isEmpty:()Z
     169: ifne          224
     172: aload_3
     173: invokeinterface #55,  1           // InterfaceMethod java/util/List.iterator:()Ljava/util/Iterator;
     178: astore        4
     180: aload         4
     182: invokeinterface #56,  1           // InterfaceMethod java/util/Iterator.hasNext:()Z
     187: ifeq          221
     190: aload         4
     192: invokeinterface #57,  1           // InterfaceMethod java/util/Iterator.next:()Ljava/lang/Object;
     197: checkcast     #299                // class org/apache/hadoop/io/Text
     200: astore        5
     202: aload_0
     203: ldc_w         #300                // String %s
     206: iconst_1
     207: anewarray     #46                 // class java/lang/Object
     210: dup
     211: iconst_0
     212: aload         5
     214: aastore
     215: invokespecial #54                 // Method println:(Ljava/lang/String;[Ljava/lang/Object;)V
     218: goto          180
     221: goto          235
     224: aload_0
     225: ldc_w         #301                // String (none)
     228: iconst_0
     229: anewarray     #46                 // class java/lang/Object
     232: invokespecial #54                 // Method println:(Ljava/lang/String;[Ljava/lang/Object;)V
     235: aload_0
     236: aload_2
     237: invokevirtual #302                // Method dumpTokens:(Lorg/apache/hadoop/security/UserGroupInformation;)V
     240: return

  private void validateUGI(java.lang.String, org.apache.hadoop.security.UserGroupInformation);
    Code:
       0: aload_0
       1: aload_2
       2: invokevirtual #290                // Method org/apache/hadoop/security/UserGroupInformation.getAuthenticationMethod:()Lorg/apache/hadoop/security/UserGroupInformation$AuthenticationMethod;
       5: getstatic     #303                // Field org/apache/hadoop/security/UserGroupInformation$AuthenticationMethod.KERBEROS:Lorg/apache/hadoop/security/UserGroupInformation$AuthenticationMethod;
       8: if_acmpne     15
      11: iconst_1
      12: goto          16
      15: iconst_0
      16: ldc_w         #304                // String LOGIN
      19: ldc_w         #305                // String User %s is not authenticated by Kerberos
      22: iconst_1
      23: anewarray     #46                 // class java/lang/Object
      26: dup
      27: iconst_0
      28: aload_2
      29: aastore
      30: invokespecial #47                 // Method verify:(ZLjava/lang/String;Ljava/lang/String;[Ljava/lang/Object;)Z
      33: ifeq          98
      36: aload_0
      37: aload_2
      38: invokevirtual #288                // Method org/apache/hadoop/security/UserGroupInformation.hasKerberosCredentials:()Z
      41: ldc_w         #304                // String LOGIN
      44: ldc_w         #306                // String %s: No kerberos credentials for %s
      47: iconst_2
      48: anewarray     #46                 // class java/lang/Object
      51: dup
      52: iconst_0
      53: aload_1
      54: aastore
      55: dup
      56: iconst_1
      57: aload_2
      58: aastore
      59: invokespecial #47                 // Method verify:(ZLjava/lang/String;Ljava/lang/String;[Ljava/lang/Object;)Z
      62: pop
      63: aload_0
      64: aload_2
      65: invokevirtual #290                // Method org/apache/hadoop/security/UserGroupInformation.getAuthenticationMethod:()Lorg/apache/hadoop/security/UserGroupInformation$AuthenticationMethod;
      68: ifnull        75
      71: iconst_1
      72: goto          76
      75: iconst_0
      76: ldc_w         #304                // String LOGIN
      79: ldc_w         #307                // String %s: Null AuthenticationMethod for %s
      82: iconst_2
      83: anewarray     #46                 // class java/lang/Object
      86: dup
      87: iconst_0
      88: aload_1
      89: aastore
      90: dup
      91: iconst_1
      92: aload_2
      93: aastore
      94: invokespecial #47                 // Method verify:(ZLjava/lang/String;Ljava/lang/String;[Ljava/lang/Object;)Z
      97: pop
      98: return

  private void validateKinitExecutable();
    Code:
       0: aload_0
       1: invokevirtual #158                // Method getConf:()Lorg/apache/hadoop/conf/Configuration;
       4: ldc           #144                // String hadoop.kerberos.kinit.command
       6: ldc           #75                 // String
       8: invokevirtual #308                // Method org/apache/hadoop/conf/Configuration.getTrimmed:(Ljava/lang/String;Ljava/lang/String;)Ljava/lang/String;
      11: astore_1
      12: aload_1
      13: invokevirtual #93                 // Method java/lang/String.isEmpty:()Z
      16: ifne          89
      19: new           #25                 // class java/io/File
      22: dup
      23: aload_1
      24: invokespecial #26                 // Method java/io/File."<init>":(Ljava/lang/String;)V
      27: astore_2
      28: aload_0
      29: ldc           #107                // String %s = %s
      31: iconst_2
      32: anewarray     #46                 // class java/lang/Object
      35: dup
      36: iconst_0
      37: ldc           #144                // String hadoop.kerberos.kinit.command
      39: aastore
      40: dup
      41: iconst_1
      42: aload_2
      43: aastore
      44: invokespecial #54                 // Method println:(Ljava/lang/String;[Ljava/lang/Object;)V
      47: aload_2
      48: invokevirtual #309                // Method java/io/File.isAbsolute:()Z
      51: ifeq          67
      54: aload_0
      55: aload_2
      56: ldc           #201                // String KERBEROS
      58: ldc           #144                // String hadoop.kerberos.kinit.command
      60: invokespecial #246                // Method verifyFileIsValid:(Ljava/io/File;Ljava/lang/String;Ljava/lang/String;)Z
      63: pop
      64: goto          89
      67: aload_0
      68: ldc_w         #310                // String Executable %s is relative -must be on the PATH
      71: iconst_1
      72: anewarray     #46                 // class java/lang/Object
      75: dup
      76: iconst_0
      77: aload_1
      78: aastore
      79: invokespecial #54                 // Method println:(Ljava/lang/String;[Ljava/lang/Object;)V
      82: aload_0
      83: ldc_w         #311                // String PATH
      86: invokespecial #142                // Method printEnv:(Ljava/lang/String;)V
      89: return

  private void validateSasl(java.lang.String);
    Code:
       0: aload_0
       1: ldc_w         #312                // String Resolving SASL property %s
       4: iconst_1
       5: anewarray     #46                 // class java/lang/Object
       8: dup
       9: iconst_0
      10: aload_1
      11: aastore
      12: invokespecial #101                // Method title:(Ljava/lang/String;[Ljava/lang/Object;)V
      15: aload_0
      16: invokevirtual #158                // Method getConf:()Lorg/apache/hadoop/conf/Configuration;
      19: aload_1
      20: invokevirtual #313                // Method org/apache/hadoop/conf/Configuration.getTrimmed:(Ljava/lang/String;)Ljava/lang/String;
      23: astore_2
      24: aload_0
      25: invokevirtual #158                // Method getConf:()Lorg/apache/hadoop/conf/Configuration;
      28: aload_1
      29: ldc_w         #314                // class org/apache/hadoop/security/SaslPropertiesResolver
      32: ldc_w         #314                // class org/apache/hadoop/security/SaslPropertiesResolver
      35: invokevirtual #315                // Method org/apache/hadoop/conf/Configuration.getClass:(Ljava/lang/String;Ljava/lang/Class;Ljava/lang/Class;)Ljava/lang/Class;
      38: astore_3
      39: aload_0
      40: ldc_w         #316                // String Resolver is %s
      43: iconst_1
      44: anewarray     #46                 // class java/lang/Object
      47: dup
      48: iconst_0
      49: aload_3
      50: aastore
      51: invokespecial #54                 // Method println:(Ljava/lang/String;[Ljava/lang/Object;)V
      54: goto          85
      57: astore_3
      58: new           #213                // class org/apache/hadoop/security/KDiag$KerberosDiagsFailure
      61: dup
      62: ldc_w         #318                // String SASL
      65: aload_3
      66: ldc_w         #319                // String Failed to load %s class %s
      69: iconst_2
      70: anewarray     #46                 // class java/lang/Object
      73: dup
      74: iconst_0
      75: aload_1
      76: aastore
      77: dup
      78: iconst_1
      79: aload_2
      80: aastore
      81: invokespecial #215                // Method org/apache/hadoop/security/KDiag$KerberosDiagsFailure."<init>":(Ljava/lang/String;Ljava/lang/Throwable;Ljava/lang/String;[Ljava/lang/Object;)V
      84: athrow
      85: return
    Exception table:
       from    to  target type
          24    54    57   Class java/lang/RuntimeException

  private void validateJAAS(boolean) throws java.io.IOException;
    Code:
       0: ldc           #121                // String java.security.auth.login.config
       2: invokestatic  #238                // Method java/lang/System.getProperty:(Ljava/lang/String;)Ljava/lang/String;
       5: astore_2
       6: iload_1
       7: ifeq          34
      10: aload_0
      11: aload_2
      12: ifnull        19
      15: iconst_1
      16: goto          20
      19: iconst_0
      20: ldc_w         #320                // String JAAS
      23: ldc_w         #321                // String No JAAS file specified in java.security.auth.login.config
      26: iconst_0
      27: anewarray     #46                 // class java/lang/Object
      30: invokespecial #47                 // Method verify:(ZLjava/lang/String;Ljava/lang/String;[Ljava/lang/Object;)Z
      33: pop
      34: aload_2
      35: ifnull        99
      38: aload_0
      39: ldc_w         #320                // String JAAS
      42: iconst_0
      43: anewarray     #46                 // class java/lang/Object
      46: invokespecial #101                // Method title:(Ljava/lang/String;[Ljava/lang/Object;)V
      49: new           #25                 // class java/io/File
      52: dup
      53: aload_2
      54: invokespecial #26                 // Method java/io/File."<init>":(Ljava/lang/String;)V
      57: astore_3
      58: aload_0
      59: ldc_w         #322                // String JAAS file is defined in %s: %s
      62: iconst_2
      63: anewarray     #46                 // class java/lang/Object
      66: dup
      67: iconst_0
      68: ldc           #121                // String java.security.auth.login.config
      70: aastore
      71: dup
      72: iconst_1
      73: aload_3
      74: aastore
      75: invokespecial #54                 // Method println:(Ljava/lang/String;[Ljava/lang/Object;)V
      78: aload_0
      79: aload_3
      80: ldc_w         #320                // String JAAS
      83: ldc_w         #323                // String JAAS file defined in java.security.auth.login.config
      86: invokespecial #246                // Method verifyFileIsValid:(Ljava/io/File;Ljava/lang/String;Ljava/lang/String;)Z
      89: pop
      90: aload_0
      91: aload_3
      92: invokespecial #256                // Method dump:(Ljava/io/File;)V
      95: aload_0
      96: invokespecial #123                // Method endln:()V
      99: return

  private void validateNTPConf() throws java.io.IOException;
    Code:
       0: getstatic     #248                // Field org/apache/hadoop/util/Shell.WINDOWS:Z
       3: ifne          75
       6: new           #25                 // class java/io/File
       9: dup
      10: ldc_w         #324                // String /etc/ntp.conf
      13: invokespecial #26                 // Method java/io/File."<init>":(Ljava/lang/String;)V
      16: astore_1
      17: aload_1
      18: invokevirtual #325                // Method java/io/File.exists:()Z
      21: ifeq          75
      24: aload_0
      25: aload_1
      26: ldc_w         #320                // String JAAS
      29: new           #67                 // class java/lang/StringBuilder
      32: dup
      33: invokespecial #68                 // Method java/lang/StringBuilder."<init>":()V
      36: ldc_w         #326                // String NTP file:
      39: invokevirtual #70                 // Method java/lang/StringBuilder.append:(Ljava/lang/String;)Ljava/lang/StringBuilder;
      42: aload_1
      43: invokevirtual #228                // Method java/lang/StringBuilder.append:(Ljava/lang/Object;)Ljava/lang/StringBuilder;
      46: invokevirtual #80                 // Method java/lang/StringBuilder.toString:()Ljava/lang/String;
      49: invokespecial #246                // Method verifyFileIsValid:(Ljava/io/File;Ljava/lang/String;Ljava/lang/String;)Z
      52: ifeq          75
      55: aload_0
      56: ldc_w         #327                // String NTP
      59: iconst_0
      60: anewarray     #46                 // class java/lang/Object
      63: invokespecial #101                // Method title:(Ljava/lang/String;[Ljava/lang/Object;)V
      66: aload_0
      67: aload_1
      68: invokespecial #256                // Method dump:(Ljava/io/File;)V
      71: aload_0
      72: invokespecial #123                // Method endln:()V
      75: return

  private boolean verifyFileIsValid(java.io.File, java.lang.String, java.lang.String);
    Code:
       0: aload_0
       1: aload_1
       2: invokevirtual #325                // Method java/io/File.exists:()Z
       5: aload_2
       6: ldc_w         #328                // String %s file does not exist: %s
       9: iconst_2
      10: anewarray     #46                 // class java/lang/Object
      13: dup
      14: iconst_0
      15: aload_3
      16: aastore
      17: dup
      18: iconst_1
      19: aload_1
      20: aastore
      21: invokespecial #47                 // Method verify:(ZLjava/lang/String;Ljava/lang/String;[Ljava/lang/Object;)Z
      24: ifeq          122
      27: aload_0
      28: aload_1
      29: invokevirtual #329                // Method java/io/File.isFile:()Z
      32: aload_2
      33: ldc_w         #330                // String %s path does not refer to a file: %s
      36: iconst_2
      37: anewarray     #46                 // class java/lang/Object
      40: dup
      41: iconst_0
      42: aload_3
      43: aastore
      44: dup
      45: iconst_1
      46: aload_1
      47: aastore
      48: invokespecial #47                 // Method verify:(ZLjava/lang/String;Ljava/lang/String;[Ljava/lang/Object;)Z
      51: ifeq          122
      54: aload_0
      55: aload_1
      56: invokevirtual #331                // Method java/io/File.length:()J
      59: lconst_0
      60: lcmp
      61: ifeq          68
      64: iconst_1
      65: goto          69
      68: iconst_0
      69: aload_2
      70: ldc_w         #332                // String %s file is empty: %s
      73: iconst_2
      74: anewarray     #46                 // class java/lang/Object
      77: dup
      78: iconst_0
      79: aload_3
      80: aastore
      81: dup
      82: iconst_1
      83: aload_1
      84: aastore
      85: invokespecial #47                 // Method verify:(ZLjava/lang/String;Ljava/lang/String;[Ljava/lang/Object;)Z
      88: ifeq          122
      91: aload_0
      92: aload_1
      93: invokevirtual #333                // Method java/io/File.canRead:()Z
      96: aload_2
      97: ldc_w         #334                // String %s file is not readable: %s
     100: iconst_2
     101: anewarray     #46                 // class java/lang/Object
     104: dup
     105: iconst_0
     106: aload_3
     107: aastore
     108: dup
     109: iconst_1
     110: aload_1
     111: aastore
     112: invokespecial #47                 // Method verify:(ZLjava/lang/String;Ljava/lang/String;[Ljava/lang/Object;)Z
     115: ifeq          122
     118: iconst_1
     119: goto          123
     122: iconst_0
     123: ireturn

  public void dumpTokens(org.apache.hadoop.security.UserGroupInformation);
    Code:
       0: aload_1
       1: invokevirtual #296                // Method org/apache/hadoop/security/UserGroupInformation.getCredentials:()Lorg/apache/hadoop/security/Credentials;
       4: invokevirtual #335                // Method org/apache/hadoop/security/Credentials.getAllTokens:()Ljava/util/Collection;
       7: astore_2
       8: aload_0
       9: ldc_w         #336                // String Token Count: %d
      12: iconst_1
      13: anewarray     #46                 // class java/lang/Object
      16: dup
      17: iconst_0
      18: aload_2
      19: invokeinterface #337,  1          // InterfaceMethod java/util/Collection.size:()I
      24: invokestatic  #198                // Method java/lang/Integer.valueOf:(I)Ljava/lang/Integer;
      27: aastore
      28: invokespecial #101                // Method title:(Ljava/lang/String;[Ljava/lang/Object;)V
      31: aload_2
      32: invokeinterface #338,  1          // InterfaceMethod java/util/Collection.iterator:()Ljava/util/Iterator;
      37: astore_3
      38: aload_3
      39: invokeinterface #56,  1           // InterfaceMethod java/util/Iterator.hasNext:()Z
      44: ifeq          80
      47: aload_3
      48: invokeinterface #57,  1           // InterfaceMethod java/util/Iterator.next:()Ljava/lang/Object;
      53: checkcast     #339                // class org/apache/hadoop/security/token/Token
      56: astore        4
      58: aload_0
      59: ldc_w         #340                // String Token %s
      62: iconst_1
      63: anewarray     #46                 // class java/lang/Object
      66: dup
      67: iconst_0
      68: aload         4
      70: invokevirtual #341                // Method org/apache/hadoop/security/token/Token.getKind:()Lorg/apache/hadoop/io/Text;
      73: aastore
      74: invokespecial #54                 // Method println:(Ljava/lang/String;[Ljava/lang/Object;)V
      77: goto          38
      80: aload_0
      81: invokespecial #123                // Method endln:()V
      84: return

  private boolean getAndSet(java.lang.String);
    Code:
       0: aload_1
       1: invokestatic  #342                // Method java/lang/Boolean.getBoolean:(Ljava/lang/String;)Z
       4: istore_2
       5: aload_1
       6: ldc_w         #343                // String true
       9: invokestatic  #191                // Method java/lang/System.setProperty:(Ljava/lang/String;Ljava/lang/String;)Ljava/lang/String;
      12: pop
      13: iload_2
      14: ireturn

  private void flush();
    Code:
       0: aload_0
       1: getfield      #14                 // Field out:Ljava/io/PrintWriter;
       4: ifnull        17
       7: aload_0
       8: getfield      #14                 // Field out:Ljava/io/PrintWriter;
      11: invokevirtual #344                // Method java/io/PrintWriter.flush:()V
      14: goto          23
      17: getstatic     #345                // Field java/lang/System.out:Ljava/io/PrintStream;
      20: invokevirtual #346                // Method java/io/PrintStream.flush:()V
      23: getstatic     #347                // Field java/lang/System.err:Ljava/io/PrintStream;
      26: invokevirtual #346                // Method java/io/PrintStream.flush:()V
      29: return

  private void println(java.lang.String, java.lang.Object...);
    Code:
       0: aload_0
       1: invokespecial #17                 // Method flush:()V
       4: aload_1
       5: aload_2
       6: invokestatic  #95                 // Method java/lang/String.format:(Ljava/lang/String;[Ljava/lang/Object;)Ljava/lang/String;
       9: astore_3
      10: aload_0
      11: getfield      #14                 // Field out:Ljava/io/PrintWriter;
      14: ifnull        28
      17: aload_0
      18: getfield      #14                 // Field out:Ljava/io/PrintWriter;
      21: aload_3
      22: invokevirtual #348                // Method java/io/PrintWriter.println:(Ljava/lang/String;)V
      25: goto          35
      28: getstatic     #345                // Field java/lang/System.out:Ljava/io/PrintStream;
      31: aload_3
      32: invokevirtual #349                // Method java/io/PrintStream.println:(Ljava/lang/String;)V
      35: aload_0
      36: invokespecial #17                 // Method flush:()V
      39: return

  private void println();
    Code:
       0: aload_0
       1: ldc           #75                 // String
       3: iconst_0
       4: anewarray     #46                 // class java/lang/Object
       7: invokespecial #54                 // Method println:(Ljava/lang/String;[Ljava/lang/Object;)V
      10: return

  private void endln();
    Code:
       0: aload_0
       1: invokespecial #60                 // Method println:()V
       4: aload_0
       5: ldc_w         #350                // String -----
       8: iconst_0
       9: anewarray     #46                 // class java/lang/Object
      12: invokespecial #54                 // Method println:(Ljava/lang/String;[Ljava/lang/Object;)V
      15: return

  private void title(java.lang.String, java.lang.Object...);
    Code:
       0: aload_0
       1: invokespecial #60                 // Method println:()V
       4: aload_0
       5: invokespecial #60                 // Method println:()V
       8: aload_0
       9: new           #67                 // class java/lang/StringBuilder
      12: dup
      13: invokespecial #68                 // Method java/lang/StringBuilder."<init>":()V
      16: ldc_w         #351                // String ==
      19: invokevirtual #70                 // Method java/lang/StringBuilder.append:(Ljava/lang/String;)Ljava/lang/StringBuilder;
      22: aload_1
      23: aload_2
      24: invokestatic  #95                 // Method java/lang/String.format:(Ljava/lang/String;[Ljava/lang/Object;)Ljava/lang/String;
      27: invokevirtual #70                 // Method java/lang/StringBuilder.append:(Ljava/lang/String;)Ljava/lang/StringBuilder;
      30: ldc_w         #352                // String  ==
      33: invokevirtual #70                 // Method java/lang/StringBuilder.append:(Ljava/lang/String;)Ljava/lang/StringBuilder;
      36: invokevirtual #80                 // Method java/lang/StringBuilder.toString:()Ljava/lang/String;
      39: iconst_0
      40: anewarray     #46                 // class java/lang/Object
      43: invokespecial #54                 // Method println:(Ljava/lang/String;[Ljava/lang/Object;)V
      46: aload_0
      47: invokespecial #60                 // Method println:()V
      50: return

  private void printSysprop(java.lang.String);
    Code:
       0: aload_0
       1: ldc_w         #353                // String %s = \"%s\"
       4: iconst_2
       5: anewarray     #46                 // class java/lang/Object
       8: dup
       9: iconst_0
      10: aload_1
      11: aastore
      12: dup
      13: iconst_1
      14: aload_1
      15: ldc_w         #354                // String (unset)
      18: invokestatic  #355                // Method java/lang/System.getProperty:(Ljava/lang/String;Ljava/lang/String;)Ljava/lang/String;
      21: aastore
      22: invokespecial #54                 // Method println:(Ljava/lang/String;[Ljava/lang/Object;)V
      25: return

  private void printConfOpt(java.lang.String);
    Code:
       0: aload_0
       1: ldc_w         #353                // String %s = \"%s\"
       4: iconst_2
       5: anewarray     #46                 // class java/lang/Object
       8: dup
       9: iconst_0
      10: aload_1
      11: aastore
      12: dup
      13: iconst_1
      14: aload_0
      15: invokevirtual #158                // Method getConf:()Lorg/apache/hadoop/conf/Configuration;
      18: aload_1
      19: ldc_w         #354                // String (unset)
      22: invokevirtual #356                // Method org/apache/hadoop/conf/Configuration.get:(Ljava/lang/String;Ljava/lang/String;)Ljava/lang/String;
      25: aastore
      26: invokespecial #54                 // Method println:(Ljava/lang/String;[Ljava/lang/Object;)V
      29: return

  private void printEnv(java.lang.String);
    Code:
       0: aload_1
       1: invokestatic  #252                // Method java/lang/System.getenv:(Ljava/lang/String;)Ljava/lang/String;
       4: astore_2
       5: aload_0
       6: ldc_w         #353                // String %s = \"%s\"
       9: iconst_2
      10: anewarray     #46                 // class java/lang/Object
      13: dup
      14: iconst_0
      15: aload_1
      16: aastore
      17: dup
      18: iconst_1
      19: aload_2
      20: ifnull        27
      23: aload_2
      24: goto          30
      27: ldc_w         #354                // String (unset)
      30: aastore
      31: invokespecial #54                 // Method println:(Ljava/lang/String;[Ljava/lang/Object;)V
      34: return

  private void dump(java.io.File) throws java.io.IOException;
    Code:
       0: new           #357                // class java/io/FileInputStream
       3: dup
       4: aload_1
       5: invokespecial #358                // Method java/io/FileInputStream."<init>":(Ljava/io/File;)V
       8: astore_2
       9: aconst_null
      10: astore_3
      11: aload_2
      12: invokestatic  #359                // Method org/apache/commons/io/IOUtils.readLines:(Ljava/io/InputStream;)Ljava/util/List;
      15: invokeinterface #55,  1           // InterfaceMethod java/util/List.iterator:()Ljava/util/Iterator;
      20: astore        4
      22: aload         4
      24: invokeinterface #56,  1           // InterfaceMethod java/util/Iterator.hasNext:()Z
      29: ifeq          63
      32: aload         4
      34: invokeinterface #57,  1           // InterfaceMethod java/util/Iterator.next:()Ljava/lang/Object;
      39: checkcast     #58                 // class java/lang/String
      42: astore        5
      44: aload_0
      45: ldc_w         #300                // String %s
      48: iconst_1
      49: anewarray     #46                 // class java/lang/Object
      52: dup
      53: iconst_0
      54: aload         5
      56: aastore
      57: invokespecial #54                 // Method println:(Ljava/lang/String;[Ljava/lang/Object;)V
      60: goto          22
      63: aload_2
      64: ifnull        139
      67: aload_3
      68: ifnull        89
      71: aload_2
      72: invokevirtual #360                // Method java/io/FileInputStream.close:()V
      75: goto          139
      78: astore        4
      80: aload_3
      81: aload         4
      83: invokevirtual #51                 // Method java/lang/Throwable.addSuppressed:(Ljava/lang/Throwable;)V
      86: goto          139
      89: aload_2
      90: invokevirtual #360                // Method java/io/FileInputStream.close:()V
      93: goto          139
      96: astore        4
      98: aload         4
     100: astore_3
     101: aload         4
     103: athrow
     104: astore        6
     106: aload_2
     107: ifnull        136
     110: aload_3
     111: ifnull        132
     114: aload_2
     115: invokevirtual #360                // Method java/io/FileInputStream.close:()V
     118: goto          136
     121: astore        7
     123: aload_3
     124: aload         7
     126: invokevirtual #51                 // Method java/lang/Throwable.addSuppressed:(Ljava/lang/Throwable;)V
     129: goto          136
     132: aload_2
     133: invokevirtual #360                // Method java/io/FileInputStream.close:()V
     136: aload         6
     138: athrow
     139: return
    Exception table:
       from    to  target type
          71    75    78   Class java/lang/Throwable
          11    63    96   Class java/lang/Throwable
          11    63   104   any
         114   118   121   Class java/lang/Throwable
          96   106   104   any

  private void fail(java.lang.String, java.lang.String, java.lang.Object...) throws org.apache.hadoop.security.KDiag$KerberosDiagsFailure;
    Code:
       0: aload_0
       1: aload_1
       2: aload_2
       3: aload_3
       4: invokespecial #220                // Method error:(Ljava/lang/String;Ljava/lang/String;[Ljava/lang/Object;)V
       7: new           #213                // class org/apache/hadoop/security/KDiag$KerberosDiagsFailure
      10: dup
      11: aload_1
      12: aload_2
      13: aload_3
      14: invokespecial #361                // Method org/apache/hadoop/security/KDiag$KerberosDiagsFailure."<init>":(Ljava/lang/String;Ljava/lang/String;[Ljava/lang/Object;)V
      17: athrow

  private boolean verify(boolean, java.lang.String, java.lang.String, java.lang.Object...) throws org.apache.hadoop.security.KDiag$KerberosDiagsFailure;
    Code:
       0: iload_1
       1: ifne          37
       4: aload_0
       5: iconst_1
       6: putfield      #11                 // Field probeHasFailed:Z
       9: aload_0
      10: getfield      #7                  // Field nofail:Z
      13: ifne          27
      16: aload_0
      17: aload_2
      18: aload_3
      19: aload         4
      21: invokespecial #362                // Method fail:(Ljava/lang/String;Ljava/lang/String;[Ljava/lang/Object;)V
      24: goto          35
      27: aload_0
      28: aload_2
      29: aload_3
      30: aload         4
      32: invokespecial #220                // Method error:(Ljava/lang/String;Ljava/lang/String;[Ljava/lang/Object;)V
      35: iconst_0
      36: ireturn
      37: iconst_1
      38: ireturn

  private boolean verify(java.io.File, org.apache.hadoop.conf.Configuration, java.lang.String, java.lang.String) throws org.apache.hadoop.security.KDiag$KerberosDiagsFailure;
    Code:
       0: aload_1
       1: aload_2
       2: invokestatic  #363                // Method org/apache/hadoop/security/Credentials.readTokenStorageFile:(Ljava/io/File;Lorg/apache/hadoop/conf/Configuration;)Lorg/apache/hadoop/security/Credentials;
       5: pop
       6: goto          45
       9: astore        5
      11: aload_0
      12: getfield      #7                  // Field nofail:Z
      15: ifne          32
      18: aload_0
      19: aload_3
      20: aload         4
      22: iconst_0
      23: anewarray     #46                 // class java/lang/Object
      26: invokespecial #362                // Method fail:(Ljava/lang/String;Ljava/lang/String;[Ljava/lang/Object;)V
      29: goto          43
      32: aload_0
      33: aload_3
      34: aload         4
      36: iconst_0
      37: anewarray     #46                 // class java/lang/Object
      40: invokespecial #220                // Method error:(Ljava/lang/String;Ljava/lang/String;[Ljava/lang/Object;)V
      43: iconst_0
      44: ireturn
      45: iconst_1
      46: ireturn
    Exception table:
       from    to  target type
           0     6     9   Class java/lang/Exception

  private void error(java.lang.String, java.lang.String, java.lang.Object...);
    Code:
       0: aload_0
       1: ldc_w         #365                // String ERROR: %s: %s
       4: iconst_2
       5: anewarray     #46                 // class java/lang/Object
       8: dup
       9: iconst_0
      10: aload_1
      11: aastore
      12: dup
      13: iconst_1
      14: aload_2
      15: aload_3
      16: invokestatic  #95                 // Method java/lang/String.format:(Ljava/lang/String;[Ljava/lang/Object;)Ljava/lang/String;
      19: aastore
      20: invokespecial #54                 // Method println:(Ljava/lang/String;[Ljava/lang/Object;)V
      23: return

  private void warn(java.lang.String, java.lang.String, java.lang.Object...);
    Code:
       0: aload_0
       1: ldc_w         #366                // String WARNING: %s: %s
       4: iconst_2
       5: anewarray     #46                 // class java/lang/Object
       8: dup
       9: iconst_0
      10: aload_1
      11: aastore
      12: dup
      13: iconst_1
      14: aload_2
      15: aload_3
      16: invokestatic  #95                 // Method java/lang/String.format:(Ljava/lang/String;[Ljava/lang/Object;)Ljava/lang/String;
      19: aastore
      20: invokespecial #54                 // Method println:(Ljava/lang/String;[Ljava/lang/Object;)V
      23: return

  private void failif(boolean, java.lang.String, java.lang.String, java.lang.Object...) throws org.apache.hadoop.security.KDiag$KerberosDiagsFailure;
    Code:
       0: iload_1
       1: ifeq          12
       4: aload_0
       5: aload_2
       6: aload_3
       7: aload         4
       9: invokespecial #362                // Method fail:(Ljava/lang/String;Ljava/lang/String;[Ljava/lang/Object;)V
      12: return

  public static int exec(org.apache.hadoop.conf.Configuration, java.lang.String...) throws java.lang.Exception;
    Code:
       0: new           #22                 // class org/apache/hadoop/security/KDiag
       3: dup
       4: invokespecial #367                // Method "<init>":()V
       7: astore_2
       8: aconst_null
       9: astore_3
      10: aload_0
      11: aload_2
      12: aload_1
      13: invokestatic  #368                // Method org/apache/hadoop/util/ToolRunner.run:(Lorg/apache/hadoop/conf/Configuration;Lorg/apache/hadoop/util/Tool;[Ljava/lang/String;)I
      16: istore        4
      18: aload_2
      19: ifnull        48
      22: aload_3
      23: ifnull        44
      26: aload_2
      27: invokevirtual #369                // Method close:()V
      30: goto          48
      33: astore        5
      35: aload_3
      36: aload         5
      38: invokevirtual #51                 // Method java/lang/Throwable.addSuppressed:(Ljava/lang/Throwable;)V
      41: goto          48
      44: aload_2
      45: invokevirtual #369                // Method close:()V
      48: iload         4
      50: ireturn
      51: astore        4
      53: aload         4
      55: astore_3
      56: aload         4
      58: athrow
      59: astore        6
      61: aload_2
      62: ifnull        91
      65: aload_3
      66: ifnull        87
      69: aload_2
      70: invokevirtual #369                // Method close:()V
      73: goto          91
      76: astore        7
      78: aload_3
      79: aload         7
      81: invokevirtual #51                 // Method java/lang/Throwable.addSuppressed:(Ljava/lang/Throwable;)V
      84: goto          91
      87: aload_2
      88: invokevirtual #369                // Method close:()V
      91: aload         6
      93: athrow
    Exception table:
       from    to  target type
          26    30    33   Class java/lang/Throwable
          10    18    51   Class java/lang/Throwable
          10    18    59   any
          69    73    76   Class java/lang/Throwable
          51    61    59   any

  public static void main(java.lang.String[]);
    Code:
       0: new           #164                // class org/apache/hadoop/conf/Configuration
       3: dup
       4: invokespecial #165                // Method org/apache/hadoop/conf/Configuration."<init>":()V
       7: aload_0
       8: invokestatic  #370                // Method exec:(Lorg/apache/hadoop/conf/Configuration;[Ljava/lang/String;)I
      11: invokestatic  #371                // Method org/apache/hadoop/util/ExitUtil.terminate:(I)V
      14: goto          59
      17: astore_1
      18: getstatic     #38                 // Field LOG:Lorg/slf4j/Logger;
      21: aload_1
      22: invokevirtual #373                // Method org/apache/hadoop/util/ExitUtil$ExitException.toString:()Ljava/lang/String;
      25: invokeinterface #374,  2          // InterfaceMethod org/slf4j/Logger.error:(Ljava/lang/String;)V
      30: aload_1
      31: getfield      #375                // Field org/apache/hadoop/util/ExitUtil$ExitException.status:I
      34: invokestatic  #376                // Method java/lang/System.exit:(I)V
      37: goto          59
      40: astore_1
      41: getstatic     #38                 // Field LOG:Lorg/slf4j/Logger;
      44: aload_1
      45: invokevirtual #377                // Method java/lang/Exception.toString:()Ljava/lang/String;
      48: aload_1
      49: invokeinterface #378,  3          // InterfaceMethod org/slf4j/Logger.error:(Ljava/lang/String;Ljava/lang/Throwable;)V
      54: iconst_m1
      55: aload_1
      56: invokestatic  #379                // Method org/apache/hadoop/util/ExitUtil.halt:(ILjava/lang/Throwable;)V
      59: return
    Exception table:
       from    to  target type
           0    14    17   Class org/apache/hadoop/util/ExitUtil$ExitException
           0    14    40   Class java/lang/Exception

  static {};
    Code:
       0: ldc           #22                 // class org/apache/hadoop/security/KDiag
       2: invokestatic  #380                // Method org/slf4j/LoggerFactory.getLogger:(Ljava/lang/Class;)Lorg/slf4j/Logger;
       5: putstatic     #38                 // Field LOG:Lorg/slf4j/Logger;
       8: ldc_w         #381                // String [/@]
      11: invokestatic  #382                // Method java/util/regex/Pattern.compile:(Ljava/lang/String;)Ljava/util/regex/Pattern;
      14: putstatic     #206                // Field nonSimplePattern:Ljava/util/regex/Pattern;
      17: return
}
