Compiled from "ServiceBuilderImpl.java"
final class org.jboss.msc.service.ServiceBuilderImpl$Dependency {
  private final org.jboss.msc.service.ServiceName name;

  private org.jboss.msc.service.ServiceBuilder$DependencyType dependencyType;

  private java.util.List<org.jboss.msc.inject.Injector<java.lang.Object>> injectorList;

  org.jboss.msc.service.ServiceBuilderImpl$Dependency(org.jboss.msc.service.ServiceName, org.jboss.msc.service.ServiceBuilder$DependencyType);
    Code:
       0: aload_0
       1: invokespecial #1                  // Method java/lang/Object."<init>":()V
       4: aload_0
       5: new           #2                  // class java/util/ArrayList
       8: dup
       9: iconst_0
      10: invokespecial #3                  // Method java/util/ArrayList."<init>":(I)V
      13: putfield      #4                  // Field injectorList:Ljava/util/List;
      16: aload_0
      17: aload_1
      18: putfield      #5                  // Field name:Lorg/jboss/msc/service/ServiceName;
      21: aload_0
      22: aload_2
      23: putfield      #6                  // Field dependencyType:Lorg/jboss/msc/service/ServiceBuilder$DependencyType;
      26: return

  org.jboss.msc.service.ServiceName getName();
    Code:
       0: aload_0
       1: getfield      #5                  // Field name:Lorg/jboss/msc/service/ServiceName;
       4: areturn

  java.util.List<org.jboss.msc.inject.Injector<java.lang.Object>> getInjectorList();
    Code:
       0: aload_0
       1: getfield      #4                  // Field injectorList:Ljava/util/List;
       4: areturn

  org.jboss.msc.service.ServiceBuilder$DependencyType getDependencyType();
    Code:
       0: aload_0
       1: getfield      #6                  // Field dependencyType:Lorg/jboss/msc/service/ServiceBuilder$DependencyType;
       4: areturn

  void setDependencyType(org.jboss.msc.service.ServiceBuilder$DependencyType);
    Code:
       0: aload_0
       1: aload_1
       2: putfield      #6                  // Field dependencyType:Lorg/jboss/msc/service/ServiceBuilder$DependencyType;
       5: return
}
