Compiled from "HttpServerExchange.java"
class io.undertow.server.HttpServerExchange$2 implements org.xnio.ChannelListener<org.xnio.channels.StreamSourceChannel> {
  final int val$state;

  final io.undertow.server.HttpServerExchange this$0;

  io.undertow.server.HttpServerExchange$2(io.undertow.server.HttpServerExchange, int);
    Code:
       0: aload_0
       1: aload_1
       2: putfield      #2                  // Field this$0:Lio/undertow/server/HttpServerExchange;
       5: aload_0
       6: iload_2
       7: putfield      #3                  // Field val$state:I
      10: aload_0
      11: invokespecial #4                  // Method java/lang/Object."<init>":()V
      14: return

  public void handleEvent(org.xnio.channels.StreamSourceChannel);
    Code:
       0: aload_0
       1: getfield      #3                  // Field val$state:I
       4: sipush        2048
       7: invokestatic  #5                  // Method org/xnio/Bits.anyAreClear:(II)Z
      10: ifeq          20
      13: aload_0
      14: getfield      #2                  // Field this$0:Lio/undertow/server/HttpServerExchange;
      17: invokevirtual #6                  // Method io/undertow/server/HttpServerExchange.closeAndFlushResponse:()V
      20: return

  public void handleEvent(java.nio.channels.Channel);
    Code:
       0: aload_0
       1: aload_1
       2: checkcast     #7                  // class org/xnio/channels/StreamSourceChannel
       5: invokevirtual #8                  // Method handleEvent:(Lorg/xnio/channels/StreamSourceChannel;)V
       8: return
}
