Compiled from "ListenerRegistry.java"
public final class io.undertow.server.ListenerRegistry$Listener {
  private final java.lang.String protocol;

  private final java.lang.String name;

  private final java.lang.String serverName;

  private final java.net.InetSocketAddress bindAddress;

  private final java.util.Map<java.lang.String, java.lang.Object> contextInformation;

  private final java.util.Set<io.undertow.server.ListenerRegistry$HttpUpgradeMetadata> httpUpgradeMetadata;

  public io.undertow.server.ListenerRegistry$Listener(java.lang.String, java.lang.String, java.lang.String, java.net.InetSocketAddress);
    Code:
       0: aload_0
       1: invokespecial #1                  // Method java/lang/Object."<init>":()V
       4: aload_0
       5: new           #2                  // class io/undertow/util/CopyOnWriteMap
       8: dup
       9: invokespecial #3                  // Method io/undertow/util/CopyOnWriteMap."<init>":()V
      12: putfield      #4                  // Field contextInformation:Ljava/util/Map;
      15: aload_0
      16: new           #5                  // class java/util/concurrent/CopyOnWriteArraySet
      19: dup
      20: invokespecial #6                  // Method java/util/concurrent/CopyOnWriteArraySet."<init>":()V
      23: putfield      #7                  // Field httpUpgradeMetadata:Ljava/util/Set;
      26: aload_0
      27: aload_1
      28: putfield      #8                  // Field protocol:Ljava/lang/String;
      31: aload_0
      32: aload_2
      33: putfield      #9                  // Field name:Ljava/lang/String;
      36: aload_0
      37: aload_3
      38: putfield      #10                 // Field serverName:Ljava/lang/String;
      41: aload_0
      42: aload         4
      44: putfield      #11                 // Field bindAddress:Ljava/net/InetSocketAddress;
      47: return

  public java.lang.String getProtocol();
    Code:
       0: aload_0
       1: getfield      #8                  // Field protocol:Ljava/lang/String;
       4: areturn

  public java.lang.String getName();
    Code:
       0: aload_0
       1: getfield      #9                  // Field name:Ljava/lang/String;
       4: areturn

  public java.lang.String getServerName();
    Code:
       0: aload_0
       1: getfield      #10                 // Field serverName:Ljava/lang/String;
       4: areturn

  public java.net.InetSocketAddress getBindAddress();
    Code:
       0: aload_0
       1: getfield      #11                 // Field bindAddress:Ljava/net/InetSocketAddress;
       4: areturn

  public java.util.Collection<java.lang.String> getContextKeys();
    Code:
       0: aload_0
       1: getfield      #4                  // Field contextInformation:Ljava/util/Map;
       4: invokeinterface #12,  1           // InterfaceMethod java/util/Map.keySet:()Ljava/util/Set;
       9: areturn

  public java.lang.Object removeContextInformation(java.lang.String);
    Code:
       0: aload_0
       1: getfield      #4                  // Field contextInformation:Ljava/util/Map;
       4: aload_1
       5: invokeinterface #13,  2           // InterfaceMethod java/util/Map.remove:(Ljava/lang/Object;)Ljava/lang/Object;
      10: areturn

  public java.lang.Object setContextInformation(java.lang.String, java.lang.Object);
    Code:
       0: aload_0
       1: getfield      #4                  // Field contextInformation:Ljava/util/Map;
       4: aload_1
       5: aload_2
       6: invokeinterface #14,  3           // InterfaceMethod java/util/Map.put:(Ljava/lang/Object;Ljava/lang/Object;)Ljava/lang/Object;
      11: areturn

  public java.lang.Object getContextInformation(java.lang.String);
    Code:
       0: aload_0
       1: getfield      #4                  // Field contextInformation:Ljava/util/Map;
       4: aload_1
       5: invokeinterface #15,  2           // InterfaceMethod java/util/Map.get:(Ljava/lang/Object;)Ljava/lang/Object;
      10: areturn

  public void addHttpUpgradeMetadata(io.undertow.server.ListenerRegistry$HttpUpgradeMetadata);
    Code:
       0: aload_0
       1: getfield      #7                  // Field httpUpgradeMetadata:Ljava/util/Set;
       4: aload_1
       5: invokeinterface #16,  2           // InterfaceMethod java/util/Set.add:(Ljava/lang/Object;)Z
      10: pop
      11: return

  public void removeHttpUpgradeMetadata(io.undertow.server.ListenerRegistry$HttpUpgradeMetadata);
    Code:
       0: aload_0
       1: getfield      #7                  // Field httpUpgradeMetadata:Ljava/util/Set;
       4: aload_1
       5: invokeinterface #17,  2           // InterfaceMethod java/util/Set.remove:(Ljava/lang/Object;)Z
      10: pop
      11: return

  public java.util.Set<io.undertow.server.ListenerRegistry$HttpUpgradeMetadata> getHttpUpgradeMetadata();
    Code:
       0: aload_0
       1: getfield      #7                  // Field httpUpgradeMetadata:Ljava/util/Set;
       4: invokestatic  #18                 // Method java/util/Collections.unmodifiableSet:(Ljava/util/Set;)Ljava/util/Set;
       7: areturn
}
