Compiled from "IntArrayUnionFind.java"
public class de.tum.in.naturals.unionfind.IntArrayUnionFind implements de.tum.in.naturals.unionfind.IntUnionFind {
  private int componentCount;

  private int[] parent;

  private int[] size;

  static final boolean $assertionsDisabled;

  public de.tum.in.naturals.unionfind.IntArrayUnionFind(int);
    Code:
       0: aload_0
       1: invokespecial #1                  // Method java/lang/Object."<init>":()V
       4: aload_0
       5: iload_1
       6: newarray       int
       8: putfield      #2                  // Field parent:[I
      11: aload_0
      12: iload_1
      13: newarray       int
      15: putfield      #3                  // Field size:[I
      18: aload_0
      19: iload_1
      20: putfield      #4                  // Field componentCount:I
      23: iconst_0
      24: istore_2
      25: iload_2
      26: iload_1
      27: if_icmpge     43
      30: aload_0
      31: getfield      #2                  // Field parent:[I
      34: iload_2
      35: iload_2
      36: iastore
      37: iinc          2, 1
      40: goto          25
      43: aload_0
      44: getfield      #3                  // Field size:[I
      47: iconst_1
      48: invokestatic  #5                  // Method java/util/Arrays.fill:([II)V
      51: return

  public void add(int);
    Code:
       0: aload_0
       1: dup
       2: getfield      #4                  // Field componentCount:I
       5: iload_1
       6: iadd
       7: putfield      #4                  // Field componentCount:I
      10: aload_0
      11: getfield      #2                  // Field parent:[I
      14: arraylength
      15: istore_2
      16: iload_2
      17: iload_1
      18: iadd
      19: istore_3
      20: aload_0
      21: aload_0
      22: getfield      #2                  // Field parent:[I
      25: iload_3
      26: invokestatic  #6                  // Method java/util/Arrays.copyOf:([II)[I
      29: putfield      #2                  // Field parent:[I
      32: aload_0
      33: aload_0
      34: getfield      #2                  // Field parent:[I
      37: iload_3
      38: invokestatic  #6                  // Method java/util/Arrays.copyOf:([II)[I
      41: putfield      #3                  // Field size:[I
      44: iload_2
      45: istore        4
      47: iload         4
      49: iload_3
      50: if_icmpge     76
      53: aload_0
      54: getfield      #2                  // Field parent:[I
      57: iload         4
      59: iload         4
      61: iastore
      62: aload_0
      63: getfield      #3                  // Field size:[I
      66: iload         4
      68: iconst_1
      69: iastore
      70: iinc          4, 1
      73: goto          47
      76: return

  public int componentCount();
    Code:
       0: aload_0
       1: getfield      #4                  // Field componentCount:I
       4: ireturn

  public int find(int);
    Code:
       0: getstatic     #7                  // Field $assertionsDisabled:Z
       3: ifne          22
       6: aload_0
       7: iload_1
       8: invokespecial #8                  // Method isValid:(I)Z
      11: ifne          22
      14: new           #9                  // class java/lang/AssertionError
      17: dup
      18: invokespecial #10                 // Method java/lang/AssertionError."<init>":()V
      21: athrow
      22: iload_1
      23: istore_2
      24: iload_2
      25: aload_0
      26: getfield      #2                  // Field parent:[I
      29: iload_2
      30: iaload
      31: if_icmpeq     44
      34: aload_0
      35: getfield      #2                  // Field parent:[I
      38: iload_2
      39: iaload
      40: istore_2
      41: goto          24
      44: iload_1
      45: istore_3
      46: iload_3
      47: iload_2
      48: if_icmpeq     72
      51: aload_0
      52: getfield      #2                  // Field parent:[I
      55: iload_3
      56: iaload
      57: istore        4
      59: aload_0
      60: getfield      #2                  // Field parent:[I
      63: iload_3
      64: iload_2
      65: iastore
      66: iload         4
      68: istore_3
      69: goto          46
      72: iload_2
      73: ireturn

  private boolean isValid(int);
    Code:
       0: iconst_0
       1: iload_1
       2: if_icmpgt     17
       5: iload_1
       6: aload_0
       7: invokevirtual #11                 // Method size:()I
      10: if_icmpge     17
      13: iconst_1
      14: goto          18
      17: iconst_0
      18: ireturn

  public int size();
    Code:
       0: aload_0
       1: getfield      #2                  // Field parent:[I
       4: arraylength
       5: ireturn

  public void union(int, int);
    Code:
       0: aload_0
       1: iload_1
       2: invokevirtual #12                 // Method find:(I)I
       5: istore_3
       6: aload_0
       7: iload_2
       8: invokevirtual #12                 // Method find:(I)I
      11: istore        4
      13: iload_3
      14: iload         4
      16: if_icmpne     20
      19: return
      20: aload_0
      21: getfield      #3                  // Field size:[I
      24: iload_3
      25: iaload
      26: istore        5
      28: aload_0
      29: getfield      #3                  // Field size:[I
      32: iload         4
      34: iaload
      35: istore        6
      37: iload         5
      39: iload         6
      41: if_icmpge     67
      44: aload_0
      45: getfield      #2                  // Field parent:[I
      48: iload_3
      49: iload         4
      51: iastore
      52: aload_0
      53: getfield      #3                  // Field size:[I
      56: iload         4
      58: iload         5
      60: iload         6
      62: iadd
      63: iastore
      64: goto          86
      67: aload_0
      68: getfield      #2                  // Field parent:[I
      71: iload         4
      73: iload_3
      74: iastore
      75: aload_0
      76: getfield      #3                  // Field size:[I
      79: iload_3
      80: iload         5
      82: iload         6
      84: iadd
      85: iastore
      86: aload_0
      87: dup
      88: getfield      #4                  // Field componentCount:I
      91: iconst_1
      92: isub
      93: putfield      #4                  // Field componentCount:I
      96: return

  static {};
    Code:
       0: ldc           #13                 // class de/tum/in/naturals/unionfind/IntArrayUnionFind
       2: invokevirtual #14                 // Method java/lang/Class.desiredAssertionStatus:()Z
       5: ifne          12
       8: iconst_1
       9: goto          13
      12: iconst_0
      13: putstatic     #7                  // Field $assertionsDisabled:Z
      16: return
}
