Compiled from "DateTimeFormatterBuilder.java"
class org.joda.time.format.DateTimeFormatterBuilder$Composite implements org.joda.time.format.DateTimePrinter,org.joda.time.format.DateTimeParser {
  private final org.joda.time.format.DateTimePrinter[] iPrinters;

  private final org.joda.time.format.DateTimeParser[] iParsers;

  private final int iPrintedLengthEstimate;

  private final int iParsedLengthEstimate;

  org.joda.time.format.DateTimeFormatterBuilder$Composite(java.util.List<java.lang.Object>);
    Code:
       0: aload_0
       1: invokespecial #1                  // Method java/lang/Object."<init>":()V
       4: new           #2                  // class java/util/ArrayList
       7: dup
       8: invokespecial #3                  // Method java/util/ArrayList."<init>":()V
      11: astore_2
      12: new           #2                  // class java/util/ArrayList
      15: dup
      16: invokespecial #3                  // Method java/util/ArrayList."<init>":()V
      19: astore_3
      20: aload_0
      21: aload_1
      22: aload_2
      23: aload_3
      24: invokespecial #4                  // Method decompose:(Ljava/util/List;Ljava/util/List;Ljava/util/List;)V
      27: aload_2
      28: aconst_null
      29: invokeinterface #5,  2            // InterfaceMethod java/util/List.contains:(Ljava/lang/Object;)Z
      34: ifne          46
      37: aload_2
      38: invokeinterface #6,  1            // InterfaceMethod java/util/List.isEmpty:()Z
      43: ifeq          59
      46: aload_0
      47: aconst_null
      48: putfield      #7                  // Field iPrinters:[Lorg/joda/time/format/DateTimePrinter;
      51: aload_0
      52: iconst_0
      53: putfield      #8                  // Field iPrintedLengthEstimate:I
      56: goto          135
      59: aload_2
      60: invokeinterface #9,  1            // InterfaceMethod java/util/List.size:()I
      65: istore        4
      67: aload_0
      68: iload         4
      70: anewarray     #10                 // class org/joda/time/format/DateTimePrinter
      73: putfield      #7                  // Field iPrinters:[Lorg/joda/time/format/DateTimePrinter;
      76: iconst_0
      77: istore        5
      79: iconst_0
      80: istore        6
      82: iload         6
      84: iload         4
      86: if_icmpge     129
      89: aload_2
      90: iload         6
      92: invokeinterface #11,  2           // InterfaceMethod java/util/List.get:(I)Ljava/lang/Object;
      97: checkcast     #10                 // class org/joda/time/format/DateTimePrinter
     100: astore        7
     102: iload         5
     104: aload         7
     106: invokeinterface #12,  1           // InterfaceMethod org/joda/time/format/DateTimePrinter.estimatePrintedLength:()I
     111: iadd
     112: istore        5
     114: aload_0
     115: getfield      #7                  // Field iPrinters:[Lorg/joda/time/format/DateTimePrinter;
     118: iload         6
     120: aload         7
     122: aastore
     123: iinc          6, 1
     126: goto          82
     129: aload_0
     130: iload         5
     132: putfield      #8                  // Field iPrintedLengthEstimate:I
     135: aload_3
     136: aconst_null
     137: invokeinterface #5,  2            // InterfaceMethod java/util/List.contains:(Ljava/lang/Object;)Z
     142: ifne          154
     145: aload_3
     146: invokeinterface #6,  1            // InterfaceMethod java/util/List.isEmpty:()Z
     151: ifeq          167
     154: aload_0
     155: aconst_null
     156: putfield      #13                 // Field iParsers:[Lorg/joda/time/format/DateTimeParser;
     159: aload_0
     160: iconst_0
     161: putfield      #14                 // Field iParsedLengthEstimate:I
     164: goto          243
     167: aload_3
     168: invokeinterface #9,  1            // InterfaceMethod java/util/List.size:()I
     173: istore        4
     175: aload_0
     176: iload         4
     178: anewarray     #15                 // class org/joda/time/format/DateTimeParser
     181: putfield      #13                 // Field iParsers:[Lorg/joda/time/format/DateTimeParser;
     184: iconst_0
     185: istore        5
     187: iconst_0
     188: istore        6
     190: iload         6
     192: iload         4
     194: if_icmpge     237
     197: aload_3
     198: iload         6
     200: invokeinterface #11,  2           // InterfaceMethod java/util/List.get:(I)Ljava/lang/Object;
     205: checkcast     #15                 // class org/joda/time/format/DateTimeParser
     208: astore        7
     210: iload         5
     212: aload         7
     214: invokeinterface #16,  1           // InterfaceMethod org/joda/time/format/DateTimeParser.estimateParsedLength:()I
     219: iadd
     220: istore        5
     222: aload_0
     223: getfield      #13                 // Field iParsers:[Lorg/joda/time/format/DateTimeParser;
     226: iload         6
     228: aload         7
     230: aastore
     231: iinc          6, 1
     234: goto          190
     237: aload_0
     238: iload         5
     240: putfield      #14                 // Field iParsedLengthEstimate:I
     243: return

  public int estimatePrintedLength();
    Code:
       0: aload_0
       1: getfield      #8                  // Field iPrintedLengthEstimate:I
       4: ireturn

  public void printTo(java.lang.StringBuffer, long, org.joda.time.Chronology, int, org.joda.time.DateTimeZone, java.util.Locale);
    Code:
       0: aload_0
       1: getfield      #7                  // Field iPrinters:[Lorg/joda/time/format/DateTimePrinter;
       4: astore        8
       6: aload         8
       8: ifnonnull     19
      11: new           #17                 // class java/lang/UnsupportedOperationException
      14: dup
      15: invokespecial #18                 // Method java/lang/UnsupportedOperationException."<init>":()V
      18: athrow
      19: aload         7
      21: ifnonnull     29
      24: invokestatic  #19                 // Method java/util/Locale.getDefault:()Ljava/util/Locale;
      27: astore        7
      29: aload         8
      31: arraylength
      32: istore        9
      34: iconst_0
      35: istore        10
      37: iload         10
      39: iload         9
      41: if_icmpge     70
      44: aload         8
      46: iload         10
      48: aaload
      49: aload_1
      50: lload_2
      51: aload         4
      53: iload         5
      55: aload         6
      57: aload         7
      59: invokeinterface #20,  8           // InterfaceMethod org/joda/time/format/DateTimePrinter.printTo:(Ljava/lang/StringBuffer;JLorg/joda/time/Chronology;ILorg/joda/time/DateTimeZone;Ljava/util/Locale;)V
      64: iinc          10, 1
      67: goto          37
      70: return

  public void printTo(java.io.Writer, long, org.joda.time.Chronology, int, org.joda.time.DateTimeZone, java.util.Locale) throws java.io.IOException;
    Code:
       0: aload_0
       1: getfield      #7                  // Field iPrinters:[Lorg/joda/time/format/DateTimePrinter;
       4: astore        8
       6: aload         8
       8: ifnonnull     19
      11: new           #17                 // class java/lang/UnsupportedOperationException
      14: dup
      15: invokespecial #18                 // Method java/lang/UnsupportedOperationException."<init>":()V
      18: athrow
      19: aload         7
      21: ifnonnull     29
      24: invokestatic  #19                 // Method java/util/Locale.getDefault:()Ljava/util/Locale;
      27: astore        7
      29: aload         8
      31: arraylength
      32: istore        9
      34: iconst_0
      35: istore        10
      37: iload         10
      39: iload         9
      41: if_icmpge     70
      44: aload         8
      46: iload         10
      48: aaload
      49: aload_1
      50: lload_2
      51: aload         4
      53: iload         5
      55: aload         6
      57: aload         7
      59: invokeinterface #21,  8           // InterfaceMethod org/joda/time/format/DateTimePrinter.printTo:(Ljava/io/Writer;JLorg/joda/time/Chronology;ILorg/joda/time/DateTimeZone;Ljava/util/Locale;)V
      64: iinc          10, 1
      67: goto          37
      70: return

  public void printTo(java.lang.StringBuffer, org.joda.time.ReadablePartial, java.util.Locale);
    Code:
       0: aload_0
       1: getfield      #7                  // Field iPrinters:[Lorg/joda/time/format/DateTimePrinter;
       4: astore        4
       6: aload         4
       8: ifnonnull     19
      11: new           #17                 // class java/lang/UnsupportedOperationException
      14: dup
      15: invokespecial #18                 // Method java/lang/UnsupportedOperationException."<init>":()V
      18: athrow
      19: aload_3
      20: ifnonnull     27
      23: invokestatic  #19                 // Method java/util/Locale.getDefault:()Ljava/util/Locale;
      26: astore_3
      27: aload         4
      29: arraylength
      30: istore        5
      32: iconst_0
      33: istore        6
      35: iload         6
      37: iload         5
      39: if_icmpge     61
      42: aload         4
      44: iload         6
      46: aaload
      47: aload_1
      48: aload_2
      49: aload_3
      50: invokeinterface #22,  4           // InterfaceMethod org/joda/time/format/DateTimePrinter.printTo:(Ljava/lang/StringBuffer;Lorg/joda/time/ReadablePartial;Ljava/util/Locale;)V
      55: iinc          6, 1
      58: goto          35
      61: return

  public void printTo(java.io.Writer, org.joda.time.ReadablePartial, java.util.Locale) throws java.io.IOException;
    Code:
       0: aload_0
       1: getfield      #7                  // Field iPrinters:[Lorg/joda/time/format/DateTimePrinter;
       4: astore        4
       6: aload         4
       8: ifnonnull     19
      11: new           #17                 // class java/lang/UnsupportedOperationException
      14: dup
      15: invokespecial #18                 // Method java/lang/UnsupportedOperationException."<init>":()V
      18: athrow
      19: aload_3
      20: ifnonnull     27
      23: invokestatic  #19                 // Method java/util/Locale.getDefault:()Ljava/util/Locale;
      26: astore_3
      27: aload         4
      29: arraylength
      30: istore        5
      32: iconst_0
      33: istore        6
      35: iload         6
      37: iload         5
      39: if_icmpge     61
      42: aload         4
      44: iload         6
      46: aaload
      47: aload_1
      48: aload_2
      49: aload_3
      50: invokeinterface #23,  4           // InterfaceMethod org/joda/time/format/DateTimePrinter.printTo:(Ljava/io/Writer;Lorg/joda/time/ReadablePartial;Ljava/util/Locale;)V
      55: iinc          6, 1
      58: goto          35
      61: return

  public int estimateParsedLength();
    Code:
       0: aload_0
       1: getfield      #14                 // Field iParsedLengthEstimate:I
       4: ireturn

  public int parseInto(org.joda.time.format.DateTimeParserBucket, java.lang.String, int);
    Code:
       0: aload_0
       1: getfield      #13                 // Field iParsers:[Lorg/joda/time/format/DateTimeParser;
       4: astore        4
       6: aload         4
       8: ifnonnull     19
      11: new           #17                 // class java/lang/UnsupportedOperationException
      14: dup
      15: invokespecial #18                 // Method java/lang/UnsupportedOperationException."<init>":()V
      18: athrow
      19: aload         4
      21: arraylength
      22: istore        5
      24: iconst_0
      25: istore        6
      27: iload         6
      29: iload         5
      31: if_icmpge     58
      34: iload_3
      35: iflt          58
      38: aload         4
      40: iload         6
      42: aaload
      43: aload_1
      44: aload_2
      45: iload_3
      46: invokeinterface #24,  4           // InterfaceMethod org/joda/time/format/DateTimeParser.parseInto:(Lorg/joda/time/format/DateTimeParserBucket;Ljava/lang/String;I)I
      51: istore_3
      52: iinc          6, 1
      55: goto          27
      58: iload_3
      59: ireturn

  boolean isPrinter();
    Code:
       0: aload_0
       1: getfield      #7                  // Field iPrinters:[Lorg/joda/time/format/DateTimePrinter;
       4: ifnull        11
       7: iconst_1
       8: goto          12
      11: iconst_0
      12: ireturn

  boolean isParser();
    Code:
       0: aload_0
       1: getfield      #13                 // Field iParsers:[Lorg/joda/time/format/DateTimeParser;
       4: ifnull        11
       7: iconst_1
       8: goto          12
      11: iconst_0
      12: ireturn

  private void decompose(java.util.List<java.lang.Object>, java.util.List<java.lang.Object>, java.util.List<java.lang.Object>);
    Code:
       0: aload_1
       1: invokeinterface #9,  1            // InterfaceMethod java/util/List.size:()I
       6: istore        4
       8: iconst_0
       9: istore        5
      11: iload         5
      13: iload         4
      15: if_icmpge     112
      18: aload_1
      19: iload         5
      21: invokeinterface #11,  2           // InterfaceMethod java/util/List.get:(I)Ljava/lang/Object;
      26: astore        6
      28: aload         6
      30: instanceof    #25                 // class org/joda/time/format/DateTimeFormatterBuilder$Composite
      33: ifeq          52
      36: aload_0
      37: aload_2
      38: aload         6
      40: checkcast     #25                 // class org/joda/time/format/DateTimeFormatterBuilder$Composite
      43: getfield      #7                  // Field iPrinters:[Lorg/joda/time/format/DateTimePrinter;
      46: invokespecial #26                 // Method addArrayToList:(Ljava/util/List;[Ljava/lang/Object;)V
      49: goto          61
      52: aload_2
      53: aload         6
      55: invokeinterface #27,  2           // InterfaceMethod java/util/List.add:(Ljava/lang/Object;)Z
      60: pop
      61: aload_1
      62: iload         5
      64: iconst_1
      65: iadd
      66: invokeinterface #11,  2           // InterfaceMethod java/util/List.get:(I)Ljava/lang/Object;
      71: astore        6
      73: aload         6
      75: instanceof    #25                 // class org/joda/time/format/DateTimeFormatterBuilder$Composite
      78: ifeq          97
      81: aload_0
      82: aload_3
      83: aload         6
      85: checkcast     #25                 // class org/joda/time/format/DateTimeFormatterBuilder$Composite
      88: getfield      #13                 // Field iParsers:[Lorg/joda/time/format/DateTimeParser;
      91: invokespecial #26                 // Method addArrayToList:(Ljava/util/List;[Ljava/lang/Object;)V
      94: goto          106
      97: aload_3
      98: aload         6
     100: invokeinterface #27,  2           // InterfaceMethod java/util/List.add:(Ljava/lang/Object;)Z
     105: pop
     106: iinc          5, 2
     109: goto          11
     112: return

  private void addArrayToList(java.util.List<java.lang.Object>, java.lang.Object[]);
    Code:
       0: aload_2
       1: ifnull        28
       4: iconst_0
       5: istore_3
       6: iload_3
       7: aload_2
       8: arraylength
       9: if_icmpge     28
      12: aload_1
      13: aload_2
      14: iload_3
      15: aaload
      16: invokeinterface #27,  2           // InterfaceMethod java/util/List.add:(Ljava/lang/Object;)Z
      21: pop
      22: iinc          3, 1
      25: goto          6
      28: return
}
