Compiled from "WebServiceTemplateBuilder.java"
final class org.springframework.boot.webservices.client.WebServiceTemplateBuilder$WebServiceMessageSenders {
  private final boolean onlyAdditional;

  private java.util.Set<org.springframework.ws.transport.WebServiceMessageSender> messageSenders;

  private org.springframework.boot.webservices.client.WebServiceTemplateBuilder$WebServiceMessageSenders();
    Code:
       0: aload_0
       1: iconst_1
       2: invokestatic  #2                  // Method java/util/Collections.emptySet:()Ljava/util/Set;
       5: invokespecial #3                  // Method "<init>":(ZLjava/util/Set;)V
       8: return

  private org.springframework.boot.webservices.client.WebServiceTemplateBuilder$WebServiceMessageSenders(boolean, java.util.Set<org.springframework.ws.transport.WebServiceMessageSender>);
    Code:
       0: aload_0
       1: invokespecial #4                  // Method java/lang/Object."<init>":()V
       4: aload_0
       5: iload_1
       6: putfield      #5                  // Field onlyAdditional:Z
       9: aload_0
      10: aload_2
      11: putfield      #6                  // Field messageSenders:Ljava/util/Set;
      14: return

  boolean isOnlyAdditional();
    Code:
       0: aload_0
       1: getfield      #5                  // Field onlyAdditional:Z
       4: ireturn

  java.util.Set<org.springframework.ws.transport.WebServiceMessageSender> getMessageSenders();
    Code:
       0: aload_0
       1: getfield      #6                  // Field messageSenders:Ljava/util/Set;
       4: areturn

  org.springframework.boot.webservices.client.WebServiceTemplateBuilder$WebServiceMessageSenders set(java.util.Collection<? extends org.springframework.ws.transport.WebServiceMessageSender>);
    Code:
       0: new           #7                  // class org/springframework/boot/webservices/client/WebServiceTemplateBuilder$WebServiceMessageSenders
       3: dup
       4: iconst_0
       5: new           #8                  // class java/util/LinkedHashSet
       8: dup
       9: aload_1
      10: invokespecial #9                  // Method java/util/LinkedHashSet."<init>":(Ljava/util/Collection;)V
      13: invokespecial #3                  // Method "<init>":(ZLjava/util/Set;)V
      16: areturn

  org.springframework.boot.webservices.client.WebServiceTemplateBuilder$WebServiceMessageSenders add(java.util.Collection<? extends org.springframework.ws.transport.WebServiceMessageSender>);
    Code:
       0: new           #7                  // class org/springframework/boot/webservices/client/WebServiceTemplateBuilder$WebServiceMessageSenders
       3: dup
       4: aload_0
       5: getfield      #5                  // Field onlyAdditional:Z
       8: aload_0
       9: getfield      #6                  // Field messageSenders:Ljava/util/Set;
      12: aload_1
      13: invokestatic  #10                 // Method org/springframework/boot/webservices/client/WebServiceTemplateBuilder.access$400:(Ljava/util/Set;Ljava/util/Collection;)Ljava/util/Set;
      16: invokespecial #3                  // Method "<init>":(ZLjava/util/Set;)V
      19: areturn

  org.springframework.boot.webservices.client.WebServiceTemplateBuilder$WebServiceMessageSenders(org.springframework.boot.webservices.client.WebServiceTemplateBuilder$1);
    Code:
       0: aload_0
       1: invokespecial #1                  // Method "<init>":()V
       4: return
}
