Compiled from "CookieRememberMeManager.java"
public class org.apache.shiro.web.mgt.CookieRememberMeManager extends org.apache.shiro.mgt.AbstractRememberMeManager {
  private static final transient org.slf4j.Logger log;

  public static final java.lang.String DEFAULT_REMEMBER_ME_COOKIE_NAME;

  private org.apache.shiro.web.servlet.Cookie cookie;

  public org.apache.shiro.web.mgt.CookieRememberMeManager();
    Code:
       0: aload_0
       1: invokespecial #1                  // Method org/apache/shiro/mgt/AbstractRememberMeManager."<init>":()V
       4: new           #2                  // class org/apache/shiro/web/servlet/SimpleCookie
       7: dup
       8: ldc           #3                  // String rememberMe
      10: invokespecial #4                  // Method org/apache/shiro/web/servlet/SimpleCookie."<init>":(Ljava/lang/String;)V
      13: astore_1
      14: aload_1
      15: iconst_1
      16: invokeinterface #5,  2            // InterfaceMethod org/apache/shiro/web/servlet/Cookie.setHttpOnly:(Z)V
      21: aload_1
      22: ldc           #6                  // int 31536000
      24: invokeinterface #7,  2            // InterfaceMethod org/apache/shiro/web/servlet/Cookie.setMaxAge:(I)V
      29: aload_0
      30: aload_1
      31: putfield      #8                  // Field cookie:Lorg/apache/shiro/web/servlet/Cookie;
      34: return

  public org.apache.shiro.web.servlet.Cookie getCookie();
    Code:
       0: aload_0
       1: getfield      #8                  // Field cookie:Lorg/apache/shiro/web/servlet/Cookie;
       4: areturn

  public void setCookie(org.apache.shiro.web.servlet.Cookie);
    Code:
       0: aload_0
       1: aload_1
       2: putfield      #8                  // Field cookie:Lorg/apache/shiro/web/servlet/Cookie;
       5: return

  protected void rememberSerializedIdentity(org.apache.shiro.subject.Subject, byte[]);
    Code:
       0: aload_1
       1: invokestatic  #9                  // Method org/apache/shiro/web/util/WebUtils.isHttp:(Ljava/lang/Object;)Z
       4: ifne          31
       7: getstatic     #10                 // Field log:Lorg/slf4j/Logger;
      10: invokeinterface #11,  1           // InterfaceMethod org/slf4j/Logger.isDebugEnabled:()Z
      15: ifeq          30
      18: ldc           #12                 // String Subject argument is not an HTTP-aware instance.  This is required to obtain a servlet request and response in order to set the rememberMe cookie. Returning immediately and ignoring rememberMe operation.
      20: astore_3
      21: getstatic     #10                 // Field log:Lorg/slf4j/Logger;
      24: aload_3
      25: invokeinterface #13,  2           // InterfaceMethod org/slf4j/Logger.debug:(Ljava/lang/String;)V
      30: return
      31: aload_1
      32: invokestatic  #14                 // Method org/apache/shiro/web/util/WebUtils.getHttpRequest:(Ljava/lang/Object;)Ljavax/servlet/http/HttpServletRequest;
      35: astore_3
      36: aload_1
      37: invokestatic  #15                 // Method org/apache/shiro/web/util/WebUtils.getHttpResponse:(Ljava/lang/Object;)Ljavax/servlet/http/HttpServletResponse;
      40: astore        4
      42: aload_2
      43: invokestatic  #16                 // Method org/apache/shiro/codec/Base64.encodeToString:([B)Ljava/lang/String;
      46: astore        5
      48: aload_0
      49: invokevirtual #17                 // Method getCookie:()Lorg/apache/shiro/web/servlet/Cookie;
      52: astore        6
      54: new           #2                  // class org/apache/shiro/web/servlet/SimpleCookie
      57: dup
      58: aload         6
      60: invokespecial #18                 // Method org/apache/shiro/web/servlet/SimpleCookie."<init>":(Lorg/apache/shiro/web/servlet/Cookie;)V
      63: astore        7
      65: aload         7
      67: aload         5
      69: invokeinterface #19,  2           // InterfaceMethod org/apache/shiro/web/servlet/Cookie.setValue:(Ljava/lang/String;)V
      74: aload         7
      76: aload_3
      77: aload         4
      79: invokeinterface #20,  3           // InterfaceMethod org/apache/shiro/web/servlet/Cookie.saveTo:(Ljavax/servlet/http/HttpServletRequest;Ljavax/servlet/http/HttpServletResponse;)V
      84: return

  private boolean isIdentityRemoved(org.apache.shiro.web.subject.WebSubjectContext);
    Code:
       0: aload_1
       1: invokeinterface #21,  1           // InterfaceMethod org/apache/shiro/web/subject/WebSubjectContext.resolveServletRequest:()Ljavax/servlet/ServletRequest;
       6: astore_2
       7: aload_2
       8: ifnull        41
      11: aload_2
      12: getstatic     #22                 // Field org/apache/shiro/web/servlet/ShiroHttpServletRequest.IDENTITY_REMOVED_KEY:Ljava/lang/String;
      15: invokeinterface #23,  2           // InterfaceMethod javax/servlet/ServletRequest.getAttribute:(Ljava/lang/String;)Ljava/lang/Object;
      20: checkcast     #24                 // class java/lang/Boolean
      23: astore_3
      24: aload_3
      25: ifnull        39
      28: aload_3
      29: invokevirtual #25                 // Method java/lang/Boolean.booleanValue:()Z
      32: ifeq          39
      35: iconst_1
      36: goto          40
      39: iconst_0
      40: ireturn
      41: iconst_0
      42: ireturn

  protected byte[] getRememberedSerializedIdentity(org.apache.shiro.subject.SubjectContext);
    Code:
       0: aload_1
       1: invokestatic  #9                  // Method org/apache/shiro/web/util/WebUtils.isHttp:(Ljava/lang/Object;)Z
       4: ifne          32
       7: getstatic     #10                 // Field log:Lorg/slf4j/Logger;
      10: invokeinterface #11,  1           // InterfaceMethod org/slf4j/Logger.isDebugEnabled:()Z
      15: ifeq          30
      18: ldc           #26                 // String SubjectContext argument is not an HTTP-aware instance.  This is required to obtain a servlet request and response in order to retrieve the rememberMe cookie. Returning immediately and ignoring rememberMe operation.
      20: astore_2
      21: getstatic     #10                 // Field log:Lorg/slf4j/Logger;
      24: aload_2
      25: invokeinterface #13,  2           // InterfaceMethod org/slf4j/Logger.debug:(Ljava/lang/String;)V
      30: aconst_null
      31: areturn
      32: aload_1
      33: checkcast     #27                 // class org/apache/shiro/web/subject/WebSubjectContext
      36: astore_2
      37: aload_0
      38: aload_2
      39: invokespecial #28                 // Method isIdentityRemoved:(Lorg/apache/shiro/web/subject/WebSubjectContext;)Z
      42: ifeq          47
      45: aconst_null
      46: areturn
      47: aload_2
      48: invokestatic  #14                 // Method org/apache/shiro/web/util/WebUtils.getHttpRequest:(Ljava/lang/Object;)Ljavax/servlet/http/HttpServletRequest;
      51: astore_3
      52: aload_2
      53: invokestatic  #15                 // Method org/apache/shiro/web/util/WebUtils.getHttpResponse:(Ljava/lang/Object;)Ljavax/servlet/http/HttpServletResponse;
      56: astore        4
      58: aload_0
      59: invokevirtual #17                 // Method getCookie:()Lorg/apache/shiro/web/servlet/Cookie;
      62: aload_3
      63: aload         4
      65: invokeinterface #29,  3           // InterfaceMethod org/apache/shiro/web/servlet/Cookie.readValue:(Ljavax/servlet/http/HttpServletRequest;Ljavax/servlet/http/HttpServletResponse;)Ljava/lang/String;
      70: astore        5
      72: ldc           #30                 // String deleteMe
      74: aload         5
      76: invokevirtual #31                 // Method java/lang/String.equals:(Ljava/lang/Object;)Z
      79: ifeq          84
      82: aconst_null
      83: areturn
      84: aload         5
      86: ifnull        205
      89: aload_0
      90: aload         5
      92: invokespecial #32                 // Method ensurePadding:(Ljava/lang/String;)Ljava/lang/String;
      95: astore        5
      97: getstatic     #10                 // Field log:Lorg/slf4j/Logger;
     100: invokeinterface #33,  1           // InterfaceMethod org/slf4j/Logger.isTraceEnabled:()Z
     105: ifeq          141
     108: getstatic     #10                 // Field log:Lorg/slf4j/Logger;
     111: new           #34                 // class java/lang/StringBuilder
     114: dup
     115: invokespecial #35                 // Method java/lang/StringBuilder."<init>":()V
     118: ldc           #36                 // String Acquired Base64 encoded identity [
     120: invokevirtual #37                 // Method java/lang/StringBuilder.append:(Ljava/lang/String;)Ljava/lang/StringBuilder;
     123: aload         5
     125: invokevirtual #37                 // Method java/lang/StringBuilder.append:(Ljava/lang/String;)Ljava/lang/StringBuilder;
     128: ldc           #38                 // String ]
     130: invokevirtual #37                 // Method java/lang/StringBuilder.append:(Ljava/lang/String;)Ljava/lang/StringBuilder;
     133: invokevirtual #39                 // Method java/lang/StringBuilder.toString:()Ljava/lang/String;
     136: invokeinterface #40,  2           // InterfaceMethod org/slf4j/Logger.trace:(Ljava/lang/String;)V
     141: aload         5
     143: invokestatic  #41                 // Method org/apache/shiro/codec/Base64.decode:(Ljava/lang/String;)[B
     146: astore        6
     148: getstatic     #10                 // Field log:Lorg/slf4j/Logger;
     151: invokeinterface #33,  1           // InterfaceMethod org/slf4j/Logger.isTraceEnabled:()Z
     156: ifeq          202
     159: getstatic     #10                 // Field log:Lorg/slf4j/Logger;
     162: new           #34                 // class java/lang/StringBuilder
     165: dup
     166: invokespecial #35                 // Method java/lang/StringBuilder."<init>":()V
     169: ldc           #42                 // String Base64 decoded byte array length:
     171: invokevirtual #37                 // Method java/lang/StringBuilder.append:(Ljava/lang/String;)Ljava/lang/StringBuilder;
     174: aload         6
     176: ifnull        185
     179: aload         6
     181: arraylength
     182: goto          186
     185: iconst_0
     186: invokevirtual #43                 // Method java/lang/StringBuilder.append:(I)Ljava/lang/StringBuilder;
     189: ldc           #44                 // String  bytes.
     191: invokevirtual #37                 // Method java/lang/StringBuilder.append:(Ljava/lang/String;)Ljava/lang/StringBuilder;
     194: invokevirtual #39                 // Method java/lang/StringBuilder.toString:()Ljava/lang/String;
     197: invokeinterface #40,  2           // InterfaceMethod org/slf4j/Logger.trace:(Ljava/lang/String;)V
     202: aload         6
     204: areturn
     205: aconst_null
     206: areturn

  private java.lang.String ensurePadding(java.lang.String);
    Code:
       0: aload_1
       1: invokevirtual #45                 // Method java/lang/String.length:()I
       4: istore_2
       5: iload_2
       6: iconst_4
       7: irem
       8: ifeq          49
      11: new           #34                 // class java/lang/StringBuilder
      14: dup
      15: aload_1
      16: invokespecial #46                 // Method java/lang/StringBuilder."<init>":(Ljava/lang/String;)V
      19: astore_3
      20: iconst_0
      21: istore        4
      23: iload         4
      25: iload_2
      26: iconst_4
      27: irem
      28: if_icmpge     44
      31: aload_3
      32: bipush        61
      34: invokevirtual #47                 // Method java/lang/StringBuilder.append:(C)Ljava/lang/StringBuilder;
      37: pop
      38: iinc          4, 1
      41: goto          23
      44: aload_3
      45: invokevirtual #39                 // Method java/lang/StringBuilder.toString:()Ljava/lang/String;
      48: astore_1
      49: aload_1
      50: areturn

  protected void forgetIdentity(org.apache.shiro.subject.Subject);
    Code:
       0: aload_1
       1: invokestatic  #9                  // Method org/apache/shiro/web/util/WebUtils.isHttp:(Ljava/lang/Object;)Z
       4: ifeq          23
       7: aload_1
       8: invokestatic  #14                 // Method org/apache/shiro/web/util/WebUtils.getHttpRequest:(Ljava/lang/Object;)Ljavax/servlet/http/HttpServletRequest;
      11: astore_2
      12: aload_1
      13: invokestatic  #15                 // Method org/apache/shiro/web/util/WebUtils.getHttpResponse:(Ljava/lang/Object;)Ljavax/servlet/http/HttpServletResponse;
      16: astore_3
      17: aload_0
      18: aload_2
      19: aload_3
      20: invokespecial #48                 // Method forgetIdentity:(Ljavax/servlet/http/HttpServletRequest;Ljavax/servlet/http/HttpServletResponse;)V
      23: return

  public void forgetIdentity(org.apache.shiro.subject.SubjectContext);
    Code:
       0: aload_1
       1: invokestatic  #9                  // Method org/apache/shiro/web/util/WebUtils.isHttp:(Ljava/lang/Object;)Z
       4: ifeq          23
       7: aload_1
       8: invokestatic  #14                 // Method org/apache/shiro/web/util/WebUtils.getHttpRequest:(Ljava/lang/Object;)Ljavax/servlet/http/HttpServletRequest;
      11: astore_2
      12: aload_1
      13: invokestatic  #15                 // Method org/apache/shiro/web/util/WebUtils.getHttpResponse:(Ljava/lang/Object;)Ljavax/servlet/http/HttpServletResponse;
      16: astore_3
      17: aload_0
      18: aload_2
      19: aload_3
      20: invokespecial #48                 // Method forgetIdentity:(Ljavax/servlet/http/HttpServletRequest;Ljavax/servlet/http/HttpServletResponse;)V
      23: return

  private void forgetIdentity(javax.servlet.http.HttpServletRequest, javax.servlet.http.HttpServletResponse);
    Code:
       0: aload_0
       1: invokevirtual #17                 // Method getCookie:()Lorg/apache/shiro/web/servlet/Cookie;
       4: aload_1
       5: aload_2
       6: invokeinterface #49,  3           // InterfaceMethod org/apache/shiro/web/servlet/Cookie.removeFrom:(Ljavax/servlet/http/HttpServletRequest;Ljavax/servlet/http/HttpServletResponse;)V
      11: return

  static {};
    Code:
       0: ldc_w         #50                 // class org/apache/shiro/web/mgt/CookieRememberMeManager
       3: invokestatic  #51                 // Method org/slf4j/LoggerFactory.getLogger:(Ljava/lang/Class;)Lorg/slf4j/Logger;
       6: putstatic     #10                 // Field log:Lorg/slf4j/Logger;
       9: return
}
