Compiled from "ModuleContainer.java"
public class org.sonarsource.sonarlint.core.analysis.container.module.ModuleContainer extends org.sonarsource.sonarlint.core.plugin.commons.pico.ComponentContainer {
  private final boolean isTransient;

  public org.sonarsource.sonarlint.core.analysis.container.module.ModuleContainer(org.sonarsource.sonarlint.core.plugin.commons.pico.ComponentContainer, boolean);
    Code:
       0: aload_0
       1: aload_1
       2: invokespecial #17                 // Method org/sonarsource/sonarlint/core/plugin/commons/pico/ComponentContainer."<init>":(Lorg/sonarsource/sonarlint/core/plugin/commons/pico/ComponentContainer;)V
       5: aload_0
       6: iload_2
       7: putfield      #19                 // Field isTransient:Z
      10: return

  protected void doBeforeStart();
    Code:
       0: aload_0
       1: iconst_5
       2: anewarray     #27                 // class java/lang/Object
       5: dup
       6: iconst_0
       7: ldc           #29                 // class org/sonarsource/sonarlint/core/analysis/sonarapi/SonarLintModuleFileSystem
       9: aastore
      10: dup
      11: iconst_1
      12: ldc           #31                 // class org/sonarsource/sonarlint/core/analysis/container/module/ModuleInputFileBuilder
      14: aastore
      15: dup
      16: iconst_2
      17: ldc           #33                 // class org/sonarsource/sonarlint/core/analysis/container/analysis/filesystem/FileMetadata
      19: aastore
      20: dup
      21: iconst_3
      22: ldc           #35                 // class org/sonarsource/sonarlint/core/analysis/container/analysis/filesystem/LanguageDetection
      24: aastore
      25: dup
      26: iconst_4
      27: ldc           #37                 // class org/sonarsource/sonarlint/core/analysis/container/module/ModuleFileEventNotifier
      29: aastore
      30: invokevirtual #41                 // Method add:([Ljava/lang/Object;)Lorg/sonarsource/sonarlint/core/plugin/commons/pico/ComponentContainer;
      33: pop
      34: aload_0
      35: ldc           #43                 // class org/sonarsource/sonarlint/core/analysis/container/global/AnalysisExtensionInstaller
      37: invokevirtual #47                 // Method getComponentByType:(Ljava/lang/Class;)Ljava/lang/Object;
      40: checkcast     #43                 // class org/sonarsource/sonarlint/core/analysis/container/global/AnalysisExtensionInstaller
      43: aload_0
      44: getstatic     #53                 // Field org/sonarsource/sonarlint/core/analysis/container/ContainerLifespan.MODULE:Lorg/sonarsource/sonarlint/core/analysis/container/ContainerLifespan;
      47: invokevirtual #57                 // Method org/sonarsource/sonarlint/core/analysis/container/global/AnalysisExtensionInstaller.install:(Lorg/sonarsource/sonarlint/core/plugin/commons/pico/ComponentContainer;Lorg/sonarsource/sonarlint/core/analysis/container/ContainerLifespan;)Lorg/sonarsource/sonarlint/core/analysis/container/global/AnalysisExtensionInstaller;
      50: pop
      51: return

  public boolean isTransient();
    Code:
       0: aload_0
       1: getfield      #19                 // Field isTransient:Z
       4: ireturn

  public org.sonarsource.sonarlint.core.analysis.api.AnalysisResults analyze(org.sonarsource.sonarlint.core.analysis.api.AnalysisConfiguration, java.util.function.Consumer<org.sonarsource.sonarlint.core.analysis.api.Issue>, org.sonarsource.sonarlint.core.commons.progress.ProgressMonitor);
    Code:
       0: new           #63                 // class org/sonarsource/sonarlint/core/analysis/container/analysis/AnalysisContainer
       3: dup
       4: aload_0
       5: aload_3
       6: invokespecial #66                 // Method org/sonarsource/sonarlint/core/analysis/container/analysis/AnalysisContainer."<init>":(Lorg/sonarsource/sonarlint/core/plugin/commons/pico/ComponentContainer;Lorg/sonarsource/sonarlint/core/commons/progress/ProgressMonitor;)V
       9: astore        4
      11: aload         4
      13: iconst_1
      14: anewarray     #27                 // class java/lang/Object
      17: dup
      18: iconst_0
      19: aload_1
      20: aastore
      21: invokevirtual #67                 // Method org/sonarsource/sonarlint/core/analysis/container/analysis/AnalysisContainer.add:([Ljava/lang/Object;)Lorg/sonarsource/sonarlint/core/plugin/commons/pico/ComponentContainer;
      24: pop
      25: aload         4
      27: iconst_1
      28: anewarray     #27                 // class java/lang/Object
      31: dup
      32: iconst_0
      33: new           #69                 // class org/sonarsource/sonarlint/core/analysis/container/analysis/IssueListenerHolder
      36: dup
      37: aload_2
      38: invokespecial #72                 // Method org/sonarsource/sonarlint/core/analysis/container/analysis/IssueListenerHolder."<init>":(Ljava/util/function/Consumer;)V
      41: aastore
      42: invokevirtual #67                 // Method org/sonarsource/sonarlint/core/analysis/container/analysis/AnalysisContainer.add:([Ljava/lang/Object;)Lorg/sonarsource/sonarlint/core/plugin/commons/pico/ComponentContainer;
      45: pop
      46: aload         4
      48: iconst_1
      49: anewarray     #27                 // class java/lang/Object
      52: dup
      53: iconst_0
      54: new           #74                 // class org/sonarsource/sonarlint/core/analysis/sonarapi/ActiveRulesAdapter
      57: dup
      58: aload_1
      59: invokevirtual #80                 // Method org/sonarsource/sonarlint/core/analysis/api/AnalysisConfiguration.activeRules:()Ljava/util/Collection;
      62: invokeinterface #86,  1           // InterfaceMethod java/util/Collection.stream:()Ljava/util/stream/Stream;
      67: invokedynamic #107,  0            // InvokeDynamic #0:apply:()Ljava/util/function/Function;
      72: invokeinterface #113,  2          // InterfaceMethod java/util/stream/Stream.map:(Ljava/util/function/Function;)Ljava/util/stream/Stream;
      77: invokestatic  #119                // Method java/util/stream/Collectors.toList:()Ljava/util/stream/Collector;
      80: invokeinterface #123,  2          // InterfaceMethod java/util/stream/Stream.collect:(Ljava/util/stream/Collector;)Ljava/lang/Object;
      85: checkcast     #82                 // class java/util/Collection
      88: invokespecial #126                // Method org/sonarsource/sonarlint/core/analysis/sonarapi/ActiveRulesAdapter."<init>":(Ljava/util/Collection;)V
      91: aastore
      92: invokevirtual #67                 // Method org/sonarsource/sonarlint/core/analysis/container/analysis/AnalysisContainer.add:([Ljava/lang/Object;)Lorg/sonarsource/sonarlint/core/plugin/commons/pico/ComponentContainer;
      95: pop
      96: new           #128                // class org/sonarsource/sonarlint/core/analysis/api/AnalysisResults
      99: dup
     100: invokespecial #130                // Method org/sonarsource/sonarlint/core/analysis/api/AnalysisResults."<init>":()V
     103: astore        5
     105: aload         4
     107: iconst_1
     108: anewarray     #27                 // class java/lang/Object
     111: dup
     112: iconst_0
     113: aload         5
     115: aastore
     116: invokevirtual #67                 // Method org/sonarsource/sonarlint/core/analysis/container/analysis/AnalysisContainer.add:([Ljava/lang/Object;)Lorg/sonarsource/sonarlint/core/plugin/commons/pico/ComponentContainer;
     119: pop
     120: aload         4
     122: invokevirtual #133                // Method org/sonarsource/sonarlint/core/analysis/container/analysis/AnalysisContainer.execute:()V
     125: aload         5
     127: areturn
}
