Compiled from "InfinispanRegionFactory.java"
public class org.hibernate.cache.infinispan.InfinispanRegionFactory implements org.hibernate.cache.spi.RegionFactory {
  private static final org.infinispan.util.logging.Log log;

  private static final java.lang.String PREFIX;

  private static final java.lang.String CONFIG_SUFFIX;

  private static final java.lang.String STRATEGY_SUFFIX;

  private static final java.lang.String WAKE_UP_INTERVAL_SUFFIX;

  private static final java.lang.String MAX_ENTRIES_SUFFIX;

  private static final java.lang.String LIFESPAN_SUFFIX;

  private static final java.lang.String MAX_IDLE_SUFFIX;

  public static final java.lang.String INFINISPAN_CONFIG_RESOURCE_PROP;

  public static final java.lang.String INFINISPAN_GLOBAL_STATISTICS_PROP;

  public static final java.lang.String INFINISPAN_USE_SYNCHRONIZATION_PROP;

  private static final java.lang.String NATURAL_ID_KEY;

  public static final java.lang.String NATURAL_ID_CACHE_RESOURCE_PROP;

  private static final java.lang.String ENTITY_KEY;

  public static final java.lang.String ENTITY_CACHE_RESOURCE_PROP;

  private static final java.lang.String IMMUTABLE_ENTITY_KEY;

  public static final java.lang.String IMMUTABLE_ENTITY_CACHE_RESOURCE_PROP;

  private static final java.lang.String COLLECTION_KEY;

  public static final java.lang.String COLLECTION_CACHE_RESOURCE_PROP;

  private static final java.lang.String TIMESTAMPS_KEY;

  public static final java.lang.String TIMESTAMPS_CACHE_RESOURCE_PROP;

  private static final java.lang.String QUERY_KEY;

  public static final java.lang.String QUERY_CACHE_RESOURCE_PROP;

  public static final java.lang.String DEF_INFINISPAN_CONFIG_RESOURCE;

  public static final java.lang.String DEF_ENTITY_RESOURCE;

  public static final java.lang.String DEF_IMMUTABLE_ENTITY_RESOURCE;

  public static final java.lang.String DEF_TIMESTAMPS_RESOURCE;

  public static final java.lang.String DEF_QUERY_RESOURCE;

  public static final boolean DEF_USE_SYNCHRONIZATION;

  public static final java.lang.String PENDING_PUTS_CACHE_NAME;

  public static final org.infinispan.configuration.cache.Configuration DEFAULT_PENDING_PUTS_CACHE_CONFIGURATION;

  private org.infinispan.configuration.cache.Configuration pendingPutsCacheConfiguration;

  private org.infinispan.manager.EmbeddedCacheManager manager;

  private final java.util.Map<java.lang.String, org.hibernate.cache.infinispan.TypeOverrides> typeOverrides;

  private final java.util.Set<java.lang.String> definedConfigurations;

  private org.infinispan.transaction.lookup.TransactionManagerLookup transactionManagerlookup;

  private javax.transaction.TransactionManager transactionManager;

  private java.util.List<java.lang.String> regionNames;

  private org.hibernate.boot.spi.SessionFactoryOptions settings;

  public org.hibernate.cache.infinispan.InfinispanRegionFactory();
    Code:
       0: aload_0
       1: invokespecial #3                  // Method java/lang/Object."<init>":()V
       4: aload_0
       5: new           #4                  // class java/util/HashMap
       8: dup
       9: invokespecial #5                  // Method java/util/HashMap."<init>":()V
      12: putfield      #6                  // Field typeOverrides:Ljava/util/Map;
      15: aload_0
      16: new           #7                  // class java/util/HashSet
      19: dup
      20: invokespecial #8                  // Method java/util/HashSet."<init>":()V
      23: putfield      #9                  // Field definedConfigurations:Ljava/util/Set;
      26: aload_0
      27: new           #10                 // class java/util/ArrayList
      30: dup
      31: invokespecial #11                 // Method java/util/ArrayList."<init>":()V
      34: putfield      #12                 // Field regionNames:Ljava/util/List;
      37: return

  public org.hibernate.cache.infinispan.InfinispanRegionFactory(java.util.Properties);
    Code:
       0: aload_0
       1: invokespecial #3                  // Method java/lang/Object."<init>":()V
       4: aload_0
       5: new           #4                  // class java/util/HashMap
       8: dup
       9: invokespecial #5                  // Method java/util/HashMap."<init>":()V
      12: putfield      #6                  // Field typeOverrides:Ljava/util/Map;
      15: aload_0
      16: new           #7                  // class java/util/HashSet
      19: dup
      20: invokespecial #8                  // Method java/util/HashSet."<init>":()V
      23: putfield      #9                  // Field definedConfigurations:Ljava/util/Set;
      26: aload_0
      27: new           #10                 // class java/util/ArrayList
      30: dup
      31: invokespecial #11                 // Method java/util/ArrayList."<init>":()V
      34: putfield      #12                 // Field regionNames:Ljava/util/List;
      37: return

  public org.hibernate.cache.spi.CollectionRegion buildCollectionRegion(java.lang.String, java.util.Properties, org.hibernate.cache.spi.CacheDataDescription) throws org.hibernate.cache.CacheException;
    Code:
       0: getstatic     #13                 // Field log:Lorg/infinispan/util/logging/Log;
       3: invokeinterface #14,  1           // InterfaceMethod org/infinispan/util/logging/Log.isDebugEnabled:()Z
       8: ifeq          43
      11: getstatic     #13                 // Field log:Lorg/infinispan/util/logging/Log;
      14: new           #15                 // class java/lang/StringBuilder
      17: dup
      18: invokespecial #16                 // Method java/lang/StringBuilder."<init>":()V
      21: ldc           #17                 // String Building collection cache region [
      23: invokevirtual #18                 // Method java/lang/StringBuilder.append:(Ljava/lang/String;)Ljava/lang/StringBuilder;
      26: aload_1
      27: invokevirtual #18                 // Method java/lang/StringBuilder.append:(Ljava/lang/String;)Ljava/lang/StringBuilder;
      30: ldc           #19                 // String ]
      32: invokevirtual #18                 // Method java/lang/StringBuilder.append:(Ljava/lang/String;)Ljava/lang/StringBuilder;
      35: invokevirtual #20                 // Method java/lang/StringBuilder.toString:()Ljava/lang/String;
      38: invokeinterface #21,  2           // InterfaceMethod org/infinispan/util/logging/Log.debug:(Ljava/lang/Object;)V
      43: aload_0
      44: aload_1
      45: ldc           #23                 // String collection
      47: aload_2
      48: aload_3
      49: invokevirtual #24                 // Method getCache:(Ljava/lang/String;Ljava/lang/String;Ljava/util/Properties;Lorg/hibernate/cache/spi/CacheDataDescription;)Lorg/infinispan/AdvancedCache;
      52: astore        4
      54: new           #25                 // class org/hibernate/cache/infinispan/collection/CollectionRegionImpl
      57: dup
      58: aload         4
      60: aload_1
      61: aload_0
      62: getfield      #26                 // Field transactionManager:Ljavax/transaction/TransactionManager;
      65: aload_3
      66: aload_0
      67: aload_0
      68: invokespecial #27                 // Method buildCacheKeysFactory:()Lorg/hibernate/cache/spi/CacheKeysFactory;
      71: invokespecial #28                 // Method org/hibernate/cache/infinispan/collection/CollectionRegionImpl."<init>":(Lorg/infinispan/AdvancedCache;Ljava/lang/String;Ljavax/transaction/TransactionManager;Lorg/hibernate/cache/spi/CacheDataDescription;Lorg/hibernate/cache/infinispan/InfinispanRegionFactory;Lorg/hibernate/cache/spi/CacheKeysFactory;)V
      74: astore        5
      76: aload_0
      77: aload         5
      79: aload_1
      80: invokespecial #29                 // Method startRegion:(Lorg/hibernate/cache/infinispan/impl/BaseRegion;Ljava/lang/String;)V
      83: aload         5
      85: areturn

  public org.hibernate.cache.spi.EntityRegion buildEntityRegion(java.lang.String, java.util.Properties, org.hibernate.cache.spi.CacheDataDescription) throws org.hibernate.cache.CacheException;
    Code:
       0: getstatic     #13                 // Field log:Lorg/infinispan/util/logging/Log;
       3: invokeinterface #14,  1           // InterfaceMethod org/infinispan/util/logging/Log.isDebugEnabled:()Z
       8: ifeq          40
      11: getstatic     #13                 // Field log:Lorg/infinispan/util/logging/Log;
      14: ldc           #30                 // String Building entity cache region [%s] (mutable=%s, versioned=%s)
      16: aload_1
      17: aload_3
      18: invokeinterface #31,  1           // InterfaceMethod org/hibernate/cache/spi/CacheDataDescription.isMutable:()Z
      23: invokestatic  #32                 // Method java/lang/Boolean.valueOf:(Z)Ljava/lang/Boolean;
      26: aload_3
      27: invokeinterface #33,  1           // InterfaceMethod org/hibernate/cache/spi/CacheDataDescription.isVersioned:()Z
      32: invokestatic  #32                 // Method java/lang/Boolean.valueOf:(Z)Ljava/lang/Boolean;
      35: invokeinterface #34,  5           // InterfaceMethod org/infinispan/util/logging/Log.debugf:(Ljava/lang/String;Ljava/lang/Object;Ljava/lang/Object;Ljava/lang/Object;)V
      40: aload_0
      41: aload_1
      42: aload_3
      43: invokeinterface #31,  1           // InterfaceMethod org/hibernate/cache/spi/CacheDataDescription.isMutable:()Z
      48: ifeq          56
      51: ldc           #35                 // String entity
      53: goto          58
      56: ldc           #36                 // String immutable-entity
      58: aload_2
      59: aload_3
      60: invokevirtual #24                 // Method getCache:(Ljava/lang/String;Ljava/lang/String;Ljava/util/Properties;Lorg/hibernate/cache/spi/CacheDataDescription;)Lorg/infinispan/AdvancedCache;
      63: astore        4
      65: new           #37                 // class org/hibernate/cache/infinispan/entity/EntityRegionImpl
      68: dup
      69: aload         4
      71: aload_1
      72: aload_0
      73: getfield      #26                 // Field transactionManager:Ljavax/transaction/TransactionManager;
      76: aload_3
      77: aload_0
      78: aload_0
      79: invokespecial #27                 // Method buildCacheKeysFactory:()Lorg/hibernate/cache/spi/CacheKeysFactory;
      82: invokespecial #38                 // Method org/hibernate/cache/infinispan/entity/EntityRegionImpl."<init>":(Lorg/infinispan/AdvancedCache;Ljava/lang/String;Ljavax/transaction/TransactionManager;Lorg/hibernate/cache/spi/CacheDataDescription;Lorg/hibernate/cache/infinispan/InfinispanRegionFactory;Lorg/hibernate/cache/spi/CacheKeysFactory;)V
      85: astore        5
      87: aload_0
      88: aload         5
      90: aload_1
      91: invokespecial #29                 // Method startRegion:(Lorg/hibernate/cache/infinispan/impl/BaseRegion;Ljava/lang/String;)V
      94: aload         5
      96: areturn

  public org.hibernate.cache.spi.NaturalIdRegion buildNaturalIdRegion(java.lang.String, java.util.Properties, org.hibernate.cache.spi.CacheDataDescription) throws org.hibernate.cache.CacheException;
    Code:
       0: getstatic     #13                 // Field log:Lorg/infinispan/util/logging/Log;
       3: invokeinterface #14,  1           // InterfaceMethod org/infinispan/util/logging/Log.isDebugEnabled:()Z
       8: ifeq          43
      11: getstatic     #13                 // Field log:Lorg/infinispan/util/logging/Log;
      14: new           #15                 // class java/lang/StringBuilder
      17: dup
      18: invokespecial #16                 // Method java/lang/StringBuilder."<init>":()V
      21: ldc           #39                 // String Building natural id cache region [
      23: invokevirtual #18                 // Method java/lang/StringBuilder.append:(Ljava/lang/String;)Ljava/lang/StringBuilder;
      26: aload_1
      27: invokevirtual #18                 // Method java/lang/StringBuilder.append:(Ljava/lang/String;)Ljava/lang/StringBuilder;
      30: ldc           #19                 // String ]
      32: invokevirtual #18                 // Method java/lang/StringBuilder.append:(Ljava/lang/String;)Ljava/lang/StringBuilder;
      35: invokevirtual #20                 // Method java/lang/StringBuilder.toString:()Ljava/lang/String;
      38: invokeinterface #21,  2           // InterfaceMethod org/infinispan/util/logging/Log.debug:(Ljava/lang/Object;)V
      43: aload_0
      44: aload_1
      45: ldc           #40                 // String naturalid
      47: aload_2
      48: aload_3
      49: invokevirtual #24                 // Method getCache:(Ljava/lang/String;Ljava/lang/String;Ljava/util/Properties;Lorg/hibernate/cache/spi/CacheDataDescription;)Lorg/infinispan/AdvancedCache;
      52: astore        4
      54: new           #41                 // class org/hibernate/cache/infinispan/naturalid/NaturalIdRegionImpl
      57: dup
      58: aload         4
      60: aload_1
      61: aload_0
      62: getfield      #26                 // Field transactionManager:Ljavax/transaction/TransactionManager;
      65: aload_3
      66: aload_0
      67: aload_0
      68: invokespecial #27                 // Method buildCacheKeysFactory:()Lorg/hibernate/cache/spi/CacheKeysFactory;
      71: invokespecial #42                 // Method org/hibernate/cache/infinispan/naturalid/NaturalIdRegionImpl."<init>":(Lorg/infinispan/AdvancedCache;Ljava/lang/String;Ljavax/transaction/TransactionManager;Lorg/hibernate/cache/spi/CacheDataDescription;Lorg/hibernate/cache/infinispan/InfinispanRegionFactory;Lorg/hibernate/cache/spi/CacheKeysFactory;)V
      74: astore        5
      76: aload_0
      77: aload         5
      79: aload_1
      80: invokespecial #29                 // Method startRegion:(Lorg/hibernate/cache/infinispan/impl/BaseRegion;Ljava/lang/String;)V
      83: aload         5
      85: areturn

  public org.hibernate.cache.spi.QueryResultsRegion buildQueryResultsRegion(java.lang.String, java.util.Properties) throws org.hibernate.cache.CacheException;
    Code:
       0: getstatic     #13                 // Field log:Lorg/infinispan/util/logging/Log;
       3: invokeinterface #14,  1           // InterfaceMethod org/infinispan/util/logging/Log.isDebugEnabled:()Z
       8: ifeq          43
      11: getstatic     #13                 // Field log:Lorg/infinispan/util/logging/Log;
      14: new           #15                 // class java/lang/StringBuilder
      17: dup
      18: invokespecial #16                 // Method java/lang/StringBuilder."<init>":()V
      21: ldc           #43                 // String Building query results cache region [
      23: invokevirtual #18                 // Method java/lang/StringBuilder.append:(Ljava/lang/String;)Ljava/lang/StringBuilder;
      26: aload_1
      27: invokevirtual #18                 // Method java/lang/StringBuilder.append:(Ljava/lang/String;)Ljava/lang/StringBuilder;
      30: ldc           #19                 // String ]
      32: invokevirtual #18                 // Method java/lang/StringBuilder.append:(Ljava/lang/String;)Ljava/lang/StringBuilder;
      35: invokevirtual #20                 // Method java/lang/StringBuilder.toString:()Ljava/lang/String;
      38: invokeinterface #21,  2           // InterfaceMethod org/infinispan/util/logging/Log.debug:(Ljava/lang/Object;)V
      43: aload_0
      44: getfield      #6                  // Field typeOverrides:Ljava/util/Map;
      47: ldc           #44                 // String query
      49: invokeinterface #45,  2           // InterfaceMethod java/util/Map.get:(Ljava/lang/Object;)Ljava/lang/Object;
      54: checkcast     #46                 // class org/hibernate/cache/infinispan/TypeOverrides
      57: invokevirtual #47                 // Method org/hibernate/cache/infinispan/TypeOverrides.getCacheName:()Ljava/lang/String;
      60: astore_3
      61: aload_1
      62: ldc           #48                 // String org.hibernate.cache.internal.StandardQueryCache
      64: invokevirtual #49                 // Method java/lang/String.equals:(Ljava/lang/Object;)Z
      67: ifne          72
      70: aload_1
      71: astore_3
      72: aload_0
      73: aload_3
      74: ldc           #44                 // String query
      76: aload_2
      77: aconst_null
      78: invokevirtual #24                 // Method getCache:(Ljava/lang/String;Ljava/lang/String;Ljava/util/Properties;Lorg/hibernate/cache/spi/CacheDataDescription;)Lorg/infinispan/AdvancedCache;
      81: astore        4
      83: new           #50                 // class org/hibernate/cache/infinispan/query/QueryResultsRegionImpl
      86: dup
      87: aload         4
      89: aload_1
      90: aload_0
      91: getfield      #26                 // Field transactionManager:Ljavax/transaction/TransactionManager;
      94: aload_0
      95: invokespecial #51                 // Method org/hibernate/cache/infinispan/query/QueryResultsRegionImpl."<init>":(Lorg/infinispan/AdvancedCache;Ljava/lang/String;Ljavax/transaction/TransactionManager;Lorg/hibernate/cache/infinispan/InfinispanRegionFactory;)V
      98: astore        5
     100: aload_0
     101: aload         5
     103: aload_1
     104: invokespecial #29                 // Method startRegion:(Lorg/hibernate/cache/infinispan/impl/BaseRegion;Ljava/lang/String;)V
     107: aload         5
     109: areturn

  public org.hibernate.cache.spi.TimestampsRegion buildTimestampsRegion(java.lang.String, java.util.Properties) throws org.hibernate.cache.CacheException;
    Code:
       0: getstatic     #13                 // Field log:Lorg/infinispan/util/logging/Log;
       3: invokeinterface #14,  1           // InterfaceMethod org/infinispan/util/logging/Log.isDebugEnabled:()Z
       8: ifeq          43
      11: getstatic     #13                 // Field log:Lorg/infinispan/util/logging/Log;
      14: new           #15                 // class java/lang/StringBuilder
      17: dup
      18: invokespecial #16                 // Method java/lang/StringBuilder."<init>":()V
      21: ldc           #52                 // String Building timestamps cache region [
      23: invokevirtual #18                 // Method java/lang/StringBuilder.append:(Ljava/lang/String;)Ljava/lang/StringBuilder;
      26: aload_1
      27: invokevirtual #18                 // Method java/lang/StringBuilder.append:(Ljava/lang/String;)Ljava/lang/StringBuilder;
      30: ldc           #19                 // String ]
      32: invokevirtual #18                 // Method java/lang/StringBuilder.append:(Ljava/lang/String;)Ljava/lang/StringBuilder;
      35: invokevirtual #20                 // Method java/lang/StringBuilder.toString:()Ljava/lang/String;
      38: invokeinterface #21,  2           // InterfaceMethod org/infinispan/util/logging/Log.debug:(Ljava/lang/Object;)V
      43: aload_0
      44: aload_1
      45: ldc           #53                 // String timestamps
      47: aload_2
      48: aconst_null
      49: invokevirtual #24                 // Method getCache:(Ljava/lang/String;Ljava/lang/String;Ljava/util/Properties;Lorg/hibernate/cache/spi/CacheDataDescription;)Lorg/infinispan/AdvancedCache;
      52: astore_3
      53: aload_0
      54: aload_3
      55: aload_1
      56: invokevirtual #54                 // Method createTimestampsRegion:(Lorg/infinispan/AdvancedCache;Ljava/lang/String;)Lorg/hibernate/cache/infinispan/timestamp/TimestampsRegionImpl;
      59: astore        4
      61: aload_0
      62: aload         4
      64: aload_1
      65: invokespecial #29                 // Method startRegion:(Lorg/hibernate/cache/infinispan/impl/BaseRegion;Ljava/lang/String;)V
      68: aload         4
      70: areturn

  protected org.hibernate.cache.infinispan.timestamp.TimestampsRegionImpl createTimestampsRegion(org.infinispan.AdvancedCache, java.lang.String);
    Code:
       0: aload_1
       1: invokestatic  #55                 // Method org/hibernate/cache/infinispan/util/Caches.isClustered:(Lorg/infinispan/AdvancedCache;)Z
       4: ifeq          18
       7: new           #56                 // class org/hibernate/cache/infinispan/timestamp/ClusteredTimestampsRegionImpl
      10: dup
      11: aload_1
      12: aload_2
      13: aload_0
      14: invokespecial #57                 // Method org/hibernate/cache/infinispan/timestamp/ClusteredTimestampsRegionImpl."<init>":(Lorg/infinispan/AdvancedCache;Ljava/lang/String;Lorg/hibernate/cache/infinispan/InfinispanRegionFactory;)V
      17: areturn
      18: new           #58                 // class org/hibernate/cache/infinispan/timestamp/TimestampsRegionImpl
      21: dup
      22: aload_1
      23: aload_2
      24: aload_0
      25: invokespecial #59                 // Method org/hibernate/cache/infinispan/timestamp/TimestampsRegionImpl."<init>":(Lorg/infinispan/AdvancedCache;Ljava/lang/String;Lorg/hibernate/cache/infinispan/InfinispanRegionFactory;)V
      28: areturn

  private org.hibernate.cache.spi.CacheKeysFactory buildCacheKeysFactory();
    Code:
       0: aload_0
       1: getfield      #60                 // Field settings:Lorg/hibernate/boot/spi/SessionFactoryOptions;
       4: invokeinterface #61,  1           // InterfaceMethod org/hibernate/boot/spi/SessionFactoryOptions.getMultiTenancyStrategy:()Lorg/hibernate/MultiTenancyStrategy;
       9: getstatic     #62                 // Field org/hibernate/MultiTenancyStrategy.NONE:Lorg/hibernate/MultiTenancyStrategy;
      12: if_acmpeq     19
      15: getstatic     #63                 // Field org/hibernate/cache/internal/DefaultCacheKeysFactory.INSTANCE:Lorg/hibernate/cache/spi/CacheKeysFactory;
      18: areturn
      19: getstatic     #64                 // Field org/hibernate/cache/internal/SimpleCacheKeysFactory.INSTANCE:Lorg/hibernate/cache/spi/CacheKeysFactory;
      22: areturn

  public boolean isMinimalPutsEnabledByDefault();
    Code:
       0: iconst_1
       1: ireturn

  public org.hibernate.cache.spi.access.AccessType getDefaultAccessType();
    Code:
       0: getstatic     #65                 // Field org/hibernate/cache/spi/access/AccessType.TRANSACTIONAL:Lorg/hibernate/cache/spi/access/AccessType;
       3: areturn

  public long nextTimestamp();
    Code:
       0: invokestatic  #66                 // Method java/lang/System.currentTimeMillis:()J
       3: lreturn

  public void setCacheManager(org.infinispan.manager.EmbeddedCacheManager);
    Code:
       0: aload_0
       1: aload_1
       2: putfield      #67                 // Field manager:Lorg/infinispan/manager/EmbeddedCacheManager;
       5: return

  public org.infinispan.manager.EmbeddedCacheManager getCacheManager();
    Code:
       0: aload_0
       1: getfield      #67                 // Field manager:Lorg/infinispan/manager/EmbeddedCacheManager;
       4: areturn

  public void start(org.hibernate.boot.spi.SessionFactoryOptions, java.util.Properties) throws org.hibernate.cache.CacheException;
    Code:
       0: getstatic     #13                 // Field log:Lorg/infinispan/util/logging/Log;
       3: ldc           #68                 // String Starting Infinispan region factory
       5: invokeinterface #21,  2           // InterfaceMethod org/infinispan/util/logging/Log.debug:(Ljava/lang/Object;)V
      10: aload_0
      11: aload_0
      12: aload_1
      13: aload_2
      14: invokevirtual #69                 // Method createTransactionManagerLookup:(Lorg/hibernate/boot/spi/SessionFactoryOptions;Ljava/util/Properties;)Lorg/infinispan/transaction/lookup/TransactionManagerLookup;
      17: putfield      #70                 // Field transactionManagerlookup:Lorg/infinispan/transaction/lookup/TransactionManagerLookup;
      20: aload_0
      21: aload_0
      22: getfield      #70                 // Field transactionManagerlookup:Lorg/infinispan/transaction/lookup/TransactionManagerLookup;
      25: invokeinterface #71,  1           // InterfaceMethod org/infinispan/transaction/lookup/TransactionManagerLookup.getTransactionManager:()Ljavax/transaction/TransactionManager;
      30: putfield      #26                 // Field transactionManager:Ljavax/transaction/TransactionManager;
      33: aload_0
      34: aload_0
      35: aload_2
      36: aload_1
      37: invokeinterface #72,  1           // InterfaceMethod org/hibernate/boot/spi/SessionFactoryOptions.getServiceRegistry:()Lorg/hibernate/boot/registry/StandardServiceRegistry;
      42: invokevirtual #73                 // Method createCacheManager:(Ljava/util/Properties;Lorg/hibernate/service/ServiceRegistry;)Lorg/infinispan/manager/EmbeddedCacheManager;
      45: putfield      #67                 // Field manager:Lorg/infinispan/manager/EmbeddedCacheManager;
      48: aload_0
      49: aload_1
      50: putfield      #60                 // Field settings:Lorg/hibernate/boot/spi/SessionFactoryOptions;
      53: aload_0
      54: invokespecial #74                 // Method initGenericDataTypeOverrides:()Ljava/util/Map;
      57: pop
      58: aload_2
      59: invokevirtual #75                 // Method java/util/Properties.propertyNames:()Ljava/util/Enumeration;
      62: astore_3
      63: aload_3
      64: invokeinterface #76,  1           // InterfaceMethod java/util/Enumeration.hasMoreElements:()Z
      69: ifeq          109
      72: aload_3
      73: invokeinterface #77,  1           // InterfaceMethod java/util/Enumeration.nextElement:()Ljava/lang/Object;
      78: checkcast     #78                 // class java/lang/String
      81: astore        4
      83: aload         4
      85: ldc           #79                 // String hibernate.cache.infinispan.
      87: invokevirtual #80                 // Method java/lang/String.indexOf:(Ljava/lang/String;)I
      90: dup
      91: istore        5
      93: iconst_m1
      94: if_icmpeq     106
      97: aload_0
      98: iload         5
     100: aload         4
     102: aload_2
     103: invokespecial #81                 // Method dissectProperty:(ILjava/lang/String;Ljava/util/Properties;)V
     106: goto          63
     109: aload_0
     110: aload_2
     111: invokespecial #82                 // Method defineGenericDataTypeCacheConfigurations:(Ljava/util/Properties;)V
     114: aload_0
     115: aload_0
     116: getfield      #67                 // Field manager:Lorg/infinispan/manager/EmbeddedCacheManager;
     119: ldc           #83                 // String pending-puts
     121: invokeinterface #84,  2           // InterfaceMethod org/infinispan/manager/EmbeddedCacheManager.getCacheConfiguration:(Ljava/lang/String;)Lorg/infinispan/configuration/cache/Configuration;
     126: putfield      #85                 // Field pendingPutsCacheConfiguration:Lorg/infinispan/configuration/cache/Configuration;
     129: aload_0
     130: getfield      #85                 // Field pendingPutsCacheConfiguration:Lorg/infinispan/configuration/cache/Configuration;
     133: ifnonnull     162
     136: aload_0
     137: getstatic     #86                 // Field DEFAULT_PENDING_PUTS_CACHE_CONFIGURATION:Lorg/infinispan/configuration/cache/Configuration;
     140: putfield      #85                 // Field pendingPutsCacheConfiguration:Lorg/infinispan/configuration/cache/Configuration;
     143: aload_0
     144: getfield      #67                 // Field manager:Lorg/infinispan/manager/EmbeddedCacheManager;
     147: ldc           #83                 // String pending-puts
     149: aload_0
     150: getfield      #85                 // Field pendingPutsCacheConfiguration:Lorg/infinispan/configuration/cache/Configuration;
     153: invokeinterface #87,  3           // InterfaceMethod org/infinispan/manager/EmbeddedCacheManager.defineConfiguration:(Ljava/lang/String;Lorg/infinispan/configuration/cache/Configuration;)Lorg/infinispan/configuration/cache/Configuration;
     158: pop
     159: goto          253
     162: aload_0
     163: getfield      #85                 // Field pendingPutsCacheConfiguration:Lorg/infinispan/configuration/cache/Configuration;
     166: invokevirtual #88                 // Method org/infinispan/configuration/cache/Configuration.clustering:()Lorg/infinispan/configuration/cache/ClusteringConfiguration;
     169: invokevirtual #89                 // Method org/infinispan/configuration/cache/ClusteringConfiguration.cacheMode:()Lorg/infinispan/configuration/cache/CacheMode;
     172: invokevirtual #90                 // Method org/infinispan/configuration/cache/CacheMode.isClustered:()Z
     175: ifeq          188
     178: new           #91                 // class java/lang/IllegalStateException
     181: dup
     182: ldc           #92                 // String Pending-puts cache must not be clustered!
     184: invokespecial #93                 // Method java/lang/IllegalStateException."<init>":(Ljava/lang/String;)V
     187: athrow
     188: aload_0
     189: getfield      #85                 // Field pendingPutsCacheConfiguration:Lorg/infinispan/configuration/cache/Configuration;
     192: invokevirtual #94                 // Method org/infinispan/configuration/cache/Configuration.transaction:()Lorg/infinispan/configuration/cache/TransactionConfiguration;
     195: invokevirtual #95                 // Method org/infinispan/configuration/cache/TransactionConfiguration.transactionMode:()Lorg/infinispan/transaction/TransactionMode;
     198: invokevirtual #96                 // Method org/infinispan/transaction/TransactionMode.isTransactional:()Z
     201: ifeq          214
     204: new           #91                 // class java/lang/IllegalStateException
     207: dup
     208: ldc           #97                 // String Pending-puts cache must not be transactional!
     210: invokespecial #93                 // Method java/lang/IllegalStateException."<init>":(Ljava/lang/String;)V
     213: athrow
     214: aload_0
     215: getfield      #85                 // Field pendingPutsCacheConfiguration:Lorg/infinispan/configuration/cache/Configuration;
     218: invokevirtual #98                 // Method org/infinispan/configuration/cache/Configuration.expiration:()Lorg/infinispan/configuration/cache/ExpirationConfiguration;
     221: astore        4
     223: aload         4
     225: invokevirtual #99                 // Method org/infinispan/configuration/cache/ExpirationConfiguration.maxIdle:()J
     228: lconst_0
     229: lcmp
     230: ifgt          253
     233: aload         4
     235: invokevirtual #100                // Method org/infinispan/configuration/cache/ExpirationConfiguration.lifespan:()J
     238: lconst_0
     239: lcmp
     240: ifgt          253
     243: getstatic     #13                 // Field log:Lorg/infinispan/util/logging/Log;
     246: ldc           #101                // String Pending-puts cache should expire old entries
     248: invokeinterface #102,  2          // InterfaceMethod org/infinispan/util/logging/Log.warn:(Ljava/lang/Object;)V
     253: goto          271
     256: astore_3
     257: aload_3
     258: athrow
     259: astore_3
     260: new           #103                // class org/hibernate/cache/CacheException
     263: dup
     264: ldc           #105                // String Unable to start region factory
     266: aload_3
     267: invokespecial #106                // Method org/hibernate/cache/CacheException."<init>":(Ljava/lang/String;Ljava/lang/Throwable;)V
     270: athrow
     271: return
    Exception table:
       from    to  target type
          10   253   256   Class org/hibernate/cache/CacheException
          10   253   259   Class java/lang/Throwable

  protected org.infinispan.transaction.lookup.TransactionManagerLookup createTransactionManagerLookup(org.hibernate.boot.spi.SessionFactoryOptions, java.util.Properties);
    Code:
       0: new           #107                // class org/hibernate/cache/infinispan/tm/HibernateTransactionManagerLookup
       3: dup
       4: aload_1
       5: aload_2
       6: invokespecial #108                // Method org/hibernate/cache/infinispan/tm/HibernateTransactionManagerLookup."<init>":(Lorg/hibernate/boot/spi/SessionFactoryOptions;Ljava/util/Properties;)V
       9: areturn

  public void stop();
    Code:
       0: getstatic     #13                 // Field log:Lorg/infinispan/util/logging/Log;
       3: ldc           #109                // String Stop region factory
       5: invokeinterface #21,  2           // InterfaceMethod org/infinispan/util/logging/Log.debug:(Ljava/lang/Object;)V
      10: aload_0
      11: invokevirtual #110                // Method stopCacheRegions:()V
      14: aload_0
      15: invokevirtual #111                // Method stopCacheManager:()V
      18: return

  protected void stopCacheRegions();
    Code:
       0: getstatic     #13                 // Field log:Lorg/infinispan/util/logging/Log;
       3: ldc           #112                // String Clear region references
       5: invokeinterface #21,  2           // InterfaceMethod org/infinispan/util/logging/Log.debug:(Ljava/lang/Object;)V
      10: aload_0
      11: aload_0
      12: getfield      #67                 // Field manager:Lorg/infinispan/manager/EmbeddedCacheManager;
      15: invokeinterface #113,  1          // InterfaceMethod org/infinispan/manager/EmbeddedCacheManager.getCache:()Lorg/infinispan/Cache;
      20: invokeinterface #114,  1          // InterfaceMethod org/infinispan/Cache.getAdvancedCache:()Lorg/infinispan/AdvancedCache;
      25: invokespecial #115                // Method getCacheCommandFactory:(Lorg/infinispan/AdvancedCache;)Lorg/hibernate/cache/infinispan/util/CacheCommandFactory;
      28: aload_0
      29: getfield      #12                 // Field regionNames:Ljava/util/List;
      32: invokevirtual #116                // Method org/hibernate/cache/infinispan/util/CacheCommandFactory.clearRegions:(Ljava/util/List;)V
      35: aload_0
      36: getfield      #12                 // Field regionNames:Ljava/util/List;
      39: invokeinterface #117,  1          // InterfaceMethod java/util/List.clear:()V
      44: return

  protected void stopCacheManager();
    Code:
       0: getstatic     #13                 // Field log:Lorg/infinispan/util/logging/Log;
       3: ldc           #118                // String Stop cache manager
       5: invokeinterface #21,  2           // InterfaceMethod org/infinispan/util/logging/Log.debug:(Ljava/lang/Object;)V
      10: aload_0
      11: getfield      #67                 // Field manager:Lorg/infinispan/manager/EmbeddedCacheManager;
      14: invokeinterface #119,  1          // InterfaceMethod org/infinispan/manager/EmbeddedCacheManager.stop:()V
      19: return

  public java.util.Map<java.lang.String, org.hibernate.cache.infinispan.TypeOverrides> getTypeOverrides();
    Code:
       0: aload_0
       1: getfield      #6                  // Field typeOverrides:Ljava/util/Map;
       4: invokestatic  #120                // Method java/util/Collections.unmodifiableMap:(Ljava/util/Map;)Ljava/util/Map;
       7: areturn

  public java.util.Set<java.lang.String> getDefinedConfigurations();
    Code:
       0: aload_0
       1: getfield      #9                  // Field definedConfigurations:Ljava/util/Set;
       4: invokestatic  #121                // Method java/util/Collections.unmodifiableSet:(Ljava/util/Set;)Ljava/util/Set;
       7: areturn

  protected org.infinispan.manager.EmbeddedCacheManager createCacheManager(java.util.Properties, org.hibernate.service.ServiceRegistry) throws org.hibernate.cache.CacheException;
    Code:
       0: ldc           #122                // String hibernate.cache.infinispan.cfg
       2: aload_1
       3: ldc           #123                // String org/hibernate/cache/infinispan/builder/infinispan-configs.xml
       5: invokestatic  #124                // Method org/hibernate/internal/util/config/ConfigurationHelper.getString:(Ljava/lang/String;Ljava/util/Map;Ljava/lang/String;)Ljava/lang/String;
       8: astore_3
       9: invokestatic  #125                // Method org/infinispan/commons/util/FileLookupFactory.newInstance:()Lorg/infinispan/commons/util/FileLookup;
      12: astore        4
      14: ldc           #22                 // class org/hibernate/cache/infinispan/InfinispanRegionFactory
      16: invokevirtual #126                // Method java/lang/Class.getClassLoader:()Ljava/lang/ClassLoader;
      19: astore        5
      21: aload_2
      22: ldc           #127                // class org/hibernate/boot/registry/classloading/spi/ClassLoaderService
      24: invokeinterface #128,  2          // InterfaceMethod org/hibernate/service/ServiceRegistry.getService:(Ljava/lang/Class;)Lorg/hibernate/service/Service;
      29: checkcast     #127                // class org/hibernate/boot/registry/classloading/spi/ClassLoaderService
      32: new           #129                // class org/hibernate/cache/infinispan/InfinispanRegionFactory$1
      35: dup
      36: aload_0
      37: aload         4
      39: aload_3
      40: aload         5
      42: aload_1
      43: invokespecial #130                // Method org/hibernate/cache/infinispan/InfinispanRegionFactory$1."<init>":(Lorg/hibernate/cache/infinispan/InfinispanRegionFactory;Lorg/infinispan/commons/util/FileLookup;Ljava/lang/String;Ljava/lang/ClassLoader;Ljava/util/Properties;)V
      46: invokeinterface #131,  2          // InterfaceMethod org/hibernate/boot/registry/classloading/spi/ClassLoaderService.workWithClassLoader:(Lorg/hibernate/boot/registry/classloading/spi/ClassLoaderService$Work;)Ljava/lang/Object;
      51: checkcast     #132                // class org/infinispan/manager/EmbeddedCacheManager
      54: areturn

  private static org.infinispan.configuration.parsing.ConfigurationBuilderHolder parseWithOverridenClassLoader(org.infinispan.configuration.parsing.ParserRegistry, java.io.InputStream, java.lang.ClassLoader);
    Code:
       0: invokestatic  #133                // Method java/lang/Thread.currentThread:()Ljava/lang/Thread;
       3: astore_3
       4: aload_3
       5: invokevirtual #134                // Method java/lang/Thread.getContextClassLoader:()Ljava/lang/ClassLoader;
       8: astore        4
      10: aload_3
      11: aload_2
      12: invokevirtual #135                // Method java/lang/Thread.setContextClassLoader:(Ljava/lang/ClassLoader;)V
      15: aload_0
      16: aload_1
      17: invokevirtual #136                // Method org/infinispan/configuration/parsing/ParserRegistry.parse:(Ljava/io/InputStream;)Lorg/infinispan/configuration/parsing/ConfigurationBuilderHolder;
      20: astore        5
      22: aload         5
      24: invokevirtual #137                // Method org/infinispan/configuration/parsing/ConfigurationBuilderHolder.getGlobalConfigurationBuilder:()Lorg/infinispan/configuration/global/GlobalConfigurationBuilder;
      27: aload_2
      28: invokevirtual #138                // Method org/infinispan/configuration/global/GlobalConfigurationBuilder.classLoader:(Ljava/lang/ClassLoader;)Lorg/infinispan/configuration/global/GlobalConfigurationBuilder;
      31: pop
      32: aload         5
      34: astore        6
      36: aload_3
      37: aload         4
      39: invokevirtual #135                // Method java/lang/Thread.setContextClassLoader:(Ljava/lang/ClassLoader;)V
      42: aload         6
      44: areturn
      45: astore        7
      47: aload_3
      48: aload         4
      50: invokevirtual #135                // Method java/lang/Thread.setContextClassLoader:(Ljava/lang/ClassLoader;)V
      53: aload         7
      55: athrow
    Exception table:
       from    to  target type
          10    36    45   any
          45    47    45   any

  protected org.infinispan.manager.EmbeddedCacheManager createCacheManager(org.infinispan.configuration.parsing.ConfigurationBuilderHolder);
    Code:
       0: new           #139                // class org/infinispan/manager/DefaultCacheManager
       3: dup
       4: aload_1
       5: iconst_1
       6: invokespecial #140                // Method org/infinispan/manager/DefaultCacheManager."<init>":(Lorg/infinispan/configuration/parsing/ConfigurationBuilderHolder;Z)V
       9: areturn

  private void startRegion(org.hibernate.cache.infinispan.impl.BaseRegion, java.lang.String);
    Code:
       0: aload_0
       1: getfield      #12                 // Field regionNames:Ljava/util/List;
       4: aload_2
       5: invokeinterface #141,  2          // InterfaceMethod java/util/List.add:(Ljava/lang/Object;)Z
      10: pop
      11: aload_0
      12: aload_1
      13: invokevirtual #142                // Method org/hibernate/cache/infinispan/impl/BaseRegion.getCache:()Lorg/infinispan/AdvancedCache;
      16: invokespecial #115                // Method getCacheCommandFactory:(Lorg/infinispan/AdvancedCache;)Lorg/hibernate/cache/infinispan/util/CacheCommandFactory;
      19: aload_2
      20: aload_1
      21: invokevirtual #143                // Method org/hibernate/cache/infinispan/util/CacheCommandFactory.addRegion:(Ljava/lang/String;Lorg/hibernate/cache/infinispan/impl/BaseRegion;)V
      24: return

  private java.util.Map<java.lang.String, org.hibernate.cache.infinispan.TypeOverrides> initGenericDataTypeOverrides();
    Code:
       0: new           #46                 // class org/hibernate/cache/infinispan/TypeOverrides
       3: dup
       4: invokespecial #144                // Method org/hibernate/cache/infinispan/TypeOverrides."<init>":()V
       7: astore_1
       8: aload_1
       9: ldc           #35                 // String entity
      11: invokevirtual #145                // Method org/hibernate/cache/infinispan/TypeOverrides.setCacheName:(Ljava/lang/String;)V
      14: aload_0
      15: getfield      #6                  // Field typeOverrides:Ljava/util/Map;
      18: ldc           #35                 // String entity
      20: aload_1
      21: invokeinterface #146,  3          // InterfaceMethod java/util/Map.put:(Ljava/lang/Object;Ljava/lang/Object;)Ljava/lang/Object;
      26: pop
      27: new           #46                 // class org/hibernate/cache/infinispan/TypeOverrides
      30: dup
      31: invokespecial #144                // Method org/hibernate/cache/infinispan/TypeOverrides."<init>":()V
      34: astore_2
      35: aload_2
      36: ldc           #35                 // String entity
      38: invokevirtual #145                // Method org/hibernate/cache/infinispan/TypeOverrides.setCacheName:(Ljava/lang/String;)V
      41: aload_0
      42: getfield      #6                  // Field typeOverrides:Ljava/util/Map;
      45: ldc           #36                 // String immutable-entity
      47: aload_2
      48: invokeinterface #146,  3          // InterfaceMethod java/util/Map.put:(Ljava/lang/Object;Ljava/lang/Object;)Ljava/lang/Object;
      53: pop
      54: new           #46                 // class org/hibernate/cache/infinispan/TypeOverrides
      57: dup
      58: invokespecial #144                // Method org/hibernate/cache/infinispan/TypeOverrides."<init>":()V
      61: astore_3
      62: aload_3
      63: ldc           #35                 // String entity
      65: invokevirtual #145                // Method org/hibernate/cache/infinispan/TypeOverrides.setCacheName:(Ljava/lang/String;)V
      68: aload_0
      69: getfield      #6                  // Field typeOverrides:Ljava/util/Map;
      72: ldc           #23                 // String collection
      74: aload_3
      75: invokeinterface #146,  3          // InterfaceMethod java/util/Map.put:(Ljava/lang/Object;Ljava/lang/Object;)Ljava/lang/Object;
      80: pop
      81: new           #46                 // class org/hibernate/cache/infinispan/TypeOverrides
      84: dup
      85: invokespecial #144                // Method org/hibernate/cache/infinispan/TypeOverrides."<init>":()V
      88: astore        4
      90: aload         4
      92: ldc           #35                 // String entity
      94: invokevirtual #145                // Method org/hibernate/cache/infinispan/TypeOverrides.setCacheName:(Ljava/lang/String;)V
      97: aload_0
      98: getfield      #6                  // Field typeOverrides:Ljava/util/Map;
     101: ldc           #40                 // String naturalid
     103: aload         4
     105: invokeinterface #146,  3          // InterfaceMethod java/util/Map.put:(Ljava/lang/Object;Ljava/lang/Object;)Ljava/lang/Object;
     110: pop
     111: new           #147                // class org/hibernate/cache/infinispan/timestamp/TimestampTypeOverrides
     114: dup
     115: invokespecial #148                // Method org/hibernate/cache/infinispan/timestamp/TimestampTypeOverrides."<init>":()V
     118: astore        5
     120: aload         5
     122: ldc           #53                 // String timestamps
     124: invokevirtual #145                // Method org/hibernate/cache/infinispan/TypeOverrides.setCacheName:(Ljava/lang/String;)V
     127: aload_0
     128: getfield      #6                  // Field typeOverrides:Ljava/util/Map;
     131: ldc           #53                 // String timestamps
     133: aload         5
     135: invokeinterface #146,  3          // InterfaceMethod java/util/Map.put:(Ljava/lang/Object;Ljava/lang/Object;)Ljava/lang/Object;
     140: pop
     141: new           #46                 // class org/hibernate/cache/infinispan/TypeOverrides
     144: dup
     145: invokespecial #144                // Method org/hibernate/cache/infinispan/TypeOverrides."<init>":()V
     148: astore        6
     150: aload         6
     152: ldc           #149                // String local-query
     154: invokevirtual #145                // Method org/hibernate/cache/infinispan/TypeOverrides.setCacheName:(Ljava/lang/String;)V
     157: aload_0
     158: getfield      #6                  // Field typeOverrides:Ljava/util/Map;
     161: ldc           #44                 // String query
     163: aload         6
     165: invokeinterface #146,  3          // InterfaceMethod java/util/Map.put:(Ljava/lang/Object;Ljava/lang/Object;)Ljava/lang/Object;
     170: pop
     171: aload_0
     172: getfield      #6                  // Field typeOverrides:Ljava/util/Map;
     175: areturn

  private void dissectProperty(int, java.lang.String, java.util.Properties);
    Code:
       0: aload_2
       1: ldc           #122                // String hibernate.cache.infinispan.cfg
       3: invokevirtual #49                 // Method java/lang/String.equals:(Ljava/lang/Object;)Z
       6: ifne          46
       9: aload_2
      10: ldc           #150                // String .cfg
      12: invokevirtual #80                 // Method java/lang/String.indexOf:(Ljava/lang/String;)I
      15: dup
      16: istore        5
      18: iconst_m1
      19: if_icmpeq     46
      22: aload_0
      23: iload_1
      24: aload_2
      25: iload         5
      27: invokespecial #151                // Method getOrCreateConfig:(ILjava/lang/String;I)Lorg/hibernate/cache/infinispan/TypeOverrides;
      30: astore        4
      32: aload         4
      34: aload_0
      35: aload_2
      36: aload_3
      37: invokespecial #1                  // Method extractProperty:(Ljava/lang/String;Ljava/util/Properties;)Ljava/lang/String;
      40: invokevirtual #145                // Method org/hibernate/cache/infinispan/TypeOverrides.setCacheName:(Ljava/lang/String;)V
      43: goto          240
      46: aload_2
      47: ldc           #152                // String .eviction.strategy
      49: invokevirtual #80                 // Method java/lang/String.indexOf:(Ljava/lang/String;)I
      52: dup
      53: istore        5
      55: iconst_m1
      56: if_icmpeq     83
      59: aload_0
      60: iload_1
      61: aload_2
      62: iload         5
      64: invokespecial #151                // Method getOrCreateConfig:(ILjava/lang/String;I)Lorg/hibernate/cache/infinispan/TypeOverrides;
      67: astore        4
      69: aload         4
      71: aload_0
      72: aload_2
      73: aload_3
      74: invokespecial #1                  // Method extractProperty:(Ljava/lang/String;Ljava/util/Properties;)Ljava/lang/String;
      77: invokevirtual #153                // Method org/hibernate/cache/infinispan/TypeOverrides.setEvictionStrategy:(Ljava/lang/String;)V
      80: goto          240
      83: aload_2
      84: ldc           #154                // String .eviction.wake_up_interval
      86: invokevirtual #80                 // Method java/lang/String.indexOf:(Ljava/lang/String;)I
      89: dup
      90: istore        5
      92: iconst_m1
      93: if_icmpeq     123
      96: aload_0
      97: iload_1
      98: aload_2
      99: iload         5
     101: invokespecial #151                // Method getOrCreateConfig:(ILjava/lang/String;I)Lorg/hibernate/cache/infinispan/TypeOverrides;
     104: astore        4
     106: aload         4
     108: aload_0
     109: aload_2
     110: aload_3
     111: invokespecial #1                  // Method extractProperty:(Ljava/lang/String;Ljava/util/Properties;)Ljava/lang/String;
     114: invokestatic  #155                // Method java/lang/Long.parseLong:(Ljava/lang/String;)J
     117: invokevirtual #156                // Method org/hibernate/cache/infinispan/TypeOverrides.setEvictionWakeUpInterval:(J)V
     120: goto          240
     123: aload_2
     124: ldc           #157                // String .eviction.max_entries
     126: invokevirtual #80                 // Method java/lang/String.indexOf:(Ljava/lang/String;)I
     129: dup
     130: istore        5
     132: iconst_m1
     133: if_icmpeq     163
     136: aload_0
     137: iload_1
     138: aload_2
     139: iload         5
     141: invokespecial #151                // Method getOrCreateConfig:(ILjava/lang/String;I)Lorg/hibernate/cache/infinispan/TypeOverrides;
     144: astore        4
     146: aload         4
     148: aload_0
     149: aload_2
     150: aload_3
     151: invokespecial #1                  // Method extractProperty:(Ljava/lang/String;Ljava/util/Properties;)Ljava/lang/String;
     154: invokestatic  #158                // Method java/lang/Integer.parseInt:(Ljava/lang/String;)I
     157: invokevirtual #159                // Method org/hibernate/cache/infinispan/TypeOverrides.setEvictionMaxEntries:(I)V
     160: goto          240
     163: aload_2
     164: ldc           #160                // String .expiration.lifespan
     166: invokevirtual #80                 // Method java/lang/String.indexOf:(Ljava/lang/String;)I
     169: dup
     170: istore        5
     172: iconst_m1
     173: if_icmpeq     203
     176: aload_0
     177: iload_1
     178: aload_2
     179: iload         5
     181: invokespecial #151                // Method getOrCreateConfig:(ILjava/lang/String;I)Lorg/hibernate/cache/infinispan/TypeOverrides;
     184: astore        4
     186: aload         4
     188: aload_0
     189: aload_2
     190: aload_3
     191: invokespecial #1                  // Method extractProperty:(Ljava/lang/String;Ljava/util/Properties;)Ljava/lang/String;
     194: invokestatic  #155                // Method java/lang/Long.parseLong:(Ljava/lang/String;)J
     197: invokevirtual #161                // Method org/hibernate/cache/infinispan/TypeOverrides.setExpirationLifespan:(J)V
     200: goto          240
     203: aload_2
     204: ldc           #162                // String .expiration.max_idle
     206: invokevirtual #80                 // Method java/lang/String.indexOf:(Ljava/lang/String;)I
     209: dup
     210: istore        5
     212: iconst_m1
     213: if_icmpeq     240
     216: aload_0
     217: iload_1
     218: aload_2
     219: iload         5
     221: invokespecial #151                // Method getOrCreateConfig:(ILjava/lang/String;I)Lorg/hibernate/cache/infinispan/TypeOverrides;
     224: astore        4
     226: aload         4
     228: aload_0
     229: aload_2
     230: aload_3
     231: invokespecial #1                  // Method extractProperty:(Ljava/lang/String;Ljava/util/Properties;)Ljava/lang/String;
     234: invokestatic  #155                // Method java/lang/Long.parseLong:(Ljava/lang/String;)J
     237: invokevirtual #163                // Method org/hibernate/cache/infinispan/TypeOverrides.setExpirationMaxIdle:(J)V
     240: return

  private java.lang.String extractProperty(java.lang.String, java.util.Properties);
    Code:
       0: aload_1
       1: aload_2
       2: invokestatic  #164                // Method org/hibernate/internal/util/config/ConfigurationHelper.extractPropertyValue:(Ljava/lang/String;Ljava/util/Properties;)Ljava/lang/String;
       5: astore_3
       6: getstatic     #13                 // Field log:Lorg/infinispan/util/logging/Log;
       9: ldc           #165                // String Configuration override via property %s: %s
      11: aload_1
      12: aload_3
      13: invokeinterface #166,  4          // InterfaceMethod org/infinispan/util/logging/Log.debugf:(Ljava/lang/String;Ljava/lang/Object;Ljava/lang/Object;)V
      18: aload_3
      19: areturn

  private org.hibernate.cache.infinispan.TypeOverrides getOrCreateConfig(int, java.lang.String, int);
    Code:
       0: aload_2
       1: iload_1
       2: ldc           #79                 // String hibernate.cache.infinispan.
       4: invokevirtual #167                // Method java/lang/String.length:()I
       7: iadd
       8: iload_3
       9: invokevirtual #168                // Method java/lang/String.substring:(II)Ljava/lang/String;
      12: astore        4
      14: aload_0
      15: getfield      #6                  // Field typeOverrides:Ljava/util/Map;
      18: aload         4
      20: invokeinterface #45,  2           // InterfaceMethod java/util/Map.get:(Ljava/lang/Object;)Ljava/lang/Object;
      25: checkcast     #46                 // class org/hibernate/cache/infinispan/TypeOverrides
      28: astore        5
      30: aload         5
      32: ifnonnull     58
      35: new           #46                 // class org/hibernate/cache/infinispan/TypeOverrides
      38: dup
      39: invokespecial #144                // Method org/hibernate/cache/infinispan/TypeOverrides."<init>":()V
      42: astore        5
      44: aload_0
      45: getfield      #6                  // Field typeOverrides:Ljava/util/Map;
      48: aload         4
      50: aload         5
      52: invokeinterface #146,  3          // InterfaceMethod java/util/Map.put:(Ljava/lang/Object;Ljava/lang/Object;)Ljava/lang/Object;
      57: pop
      58: aload         5
      60: areturn

  private void defineGenericDataTypeCacheConfigurations(java.util.Properties);
    Code:
       0: iconst_5
       1: anewarray     #78                 // class java/lang/String
       4: dup
       5: iconst_0
       6: ldc           #35                 // String entity
       8: aastore
       9: dup
      10: iconst_1
      11: ldc           #36                 // String immutable-entity
      13: aastore
      14: dup
      15: iconst_2
      16: ldc           #23                 // String collection
      18: aastore
      19: dup
      20: iconst_3
      21: ldc           #53                 // String timestamps
      23: aastore
      24: dup
      25: iconst_4
      26: ldc           #44                 // String query
      28: aastore
      29: astore_2
      30: aload_2
      31: astore_3
      32: aload_3
      33: arraylength
      34: istore        4
      36: iconst_0
      37: istore        5
      39: iload         5
      41: iload         4
      43: if_icmpge     159
      46: aload_3
      47: iload         5
      49: aaload
      50: astore        6
      52: aload_0
      53: aload_0
      54: getfield      #6                  // Field typeOverrides:Ljava/util/Map;
      57: aload         6
      59: invokeinterface #45,  2           // InterfaceMethod java/util/Map.get:(Ljava/lang/Object;)Ljava/lang/Object;
      64: checkcast     #46                 // class org/hibernate/cache/infinispan/TypeOverrides
      67: aload_1
      68: invokespecial #169                // Method overrideStatisticsIfPresent:(Lorg/hibernate/cache/infinispan/TypeOverrides;Ljava/util/Properties;)Lorg/hibernate/cache/infinispan/TypeOverrides;
      71: astore        7
      73: aload         7
      75: invokevirtual #47                 // Method org/hibernate/cache/infinispan/TypeOverrides.getCacheName:()Ljava/lang/String;
      78: astore        8
      80: new           #170                // class org/infinispan/configuration/cache/ConfigurationBuilder
      83: dup
      84: invokespecial #171                // Method org/infinispan/configuration/cache/ConfigurationBuilder."<init>":()V
      87: astore        9
      89: aload_0
      90: aload         8
      92: aload         9
      94: invokespecial #172                // Method applyConfiguration:(Ljava/lang/String;Lorg/infinispan/configuration/cache/ConfigurationBuilder;)V
      97: aload         7
      99: aload         9
     101: invokevirtual #173                // Method org/hibernate/cache/infinispan/TypeOverrides.applyTo:(Lorg/infinispan/configuration/cache/ConfigurationBuilder;)V
     104: aload_0
     105: aload         9
     107: aload         8
     109: aload_1
     110: invokespecial #174                // Method configureTransactionManager:(Lorg/infinispan/configuration/cache/ConfigurationBuilder;Ljava/lang/String;Ljava/util/Properties;)V
     113: aload         9
     115: invokevirtual #175                // Method org/infinispan/configuration/cache/ConfigurationBuilder.build:()Lorg/infinispan/configuration/cache/Configuration;
     118: astore        10
     120: aload         7
     122: aload         10
     124: invokevirtual #176                // Method org/hibernate/cache/infinispan/TypeOverrides.validateInfinispanConfiguration:(Lorg/infinispan/configuration/cache/Configuration;)V
     127: aload_0
     128: getfield      #67                 // Field manager:Lorg/infinispan/manager/EmbeddedCacheManager;
     131: aload         8
     133: aload         10
     135: invokeinterface #87,  3           // InterfaceMethod org/infinispan/manager/EmbeddedCacheManager.defineConfiguration:(Ljava/lang/String;Lorg/infinispan/configuration/cache/Configuration;)Lorg/infinispan/configuration/cache/Configuration;
     140: pop
     141: aload_0
     142: getfield      #9                  // Field definedConfigurations:Ljava/util/Set;
     145: aload         8
     147: invokeinterface #177,  2          // InterfaceMethod java/util/Set.add:(Ljava/lang/Object;)Z
     152: pop
     153: iinc          5, 1
     156: goto          39
     159: return

  protected org.infinispan.AdvancedCache getCache(java.lang.String, java.lang.String, java.util.Properties, org.hibernate.cache.spi.CacheDataDescription);
    Code:
       0: aload_0
       1: getfield      #6                  // Field typeOverrides:Ljava/util/Map;
       4: aload_1
       5: invokeinterface #45,  2           // InterfaceMethod java/util/Map.get:(Ljava/lang/Object;)Ljava/lang/Object;
      10: checkcast     #46                 // class org/hibernate/cache/infinispan/TypeOverrides
      13: astore        5
      15: aload_0
      16: getfield      #9                  // Field definedConfigurations:Ljava/util/Set;
      19: aload_1
      20: invokeinterface #178,  2          // InterfaceMethod java/util/Set.contains:(Ljava/lang/Object;)Z
      25: ifne          287
      28: new           #170                // class org/infinispan/configuration/cache/ConfigurationBuilder
      31: dup
      32: invokespecial #171                // Method org/infinispan/configuration/cache/ConfigurationBuilder."<init>":()V
      35: astore        7
      37: aload         5
      39: ifnull        145
      42: getstatic     #13                 // Field log:Lorg/infinispan/util/logging/Log;
      45: invokeinterface #14,  1           // InterfaceMethod org/infinispan/util/logging/Log.isDebugEnabled:()Z
      50: ifeq          81
      53: getstatic     #13                 // Field log:Lorg/infinispan/util/logging/Log;
      56: new           #15                 // class java/lang/StringBuilder
      59: dup
      60: invokespecial #16                 // Method java/lang/StringBuilder."<init>":()V
      63: ldc           #179                // String Cache region specific configuration exists:
      65: invokevirtual #18                 // Method java/lang/StringBuilder.append:(Ljava/lang/String;)Ljava/lang/StringBuilder;
      68: aload         5
      70: invokevirtual #180                // Method java/lang/StringBuilder.append:(Ljava/lang/Object;)Ljava/lang/StringBuilder;
      73: invokevirtual #20                 // Method java/lang/StringBuilder.toString:()Ljava/lang/String;
      76: invokeinterface #21,  2           // InterfaceMethod org/infinispan/util/logging/Log.debug:(Ljava/lang/Object;)V
      81: aload         5
      83: invokevirtual #47                 // Method org/hibernate/cache/infinispan/TypeOverrides.getCacheName:()Ljava/lang/String;
      86: astore        8
      88: aload         8
      90: ifnull        100
      93: aload         8
      95: astore        6
      97: goto          118
     100: aload_0
     101: getfield      #6                  // Field typeOverrides:Ljava/util/Map;
     104: aload_2
     105: invokeinterface #45,  2           // InterfaceMethod java/util/Map.get:(Ljava/lang/Object;)Ljava/lang/Object;
     110: checkcast     #46                 // class org/hibernate/cache/infinispan/TypeOverrides
     113: invokevirtual #47                 // Method org/hibernate/cache/infinispan/TypeOverrides.getCacheName:()Ljava/lang/String;
     116: astore        6
     118: aload_0
     119: aload         6
     121: aload         7
     123: invokespecial #172                // Method applyConfiguration:(Ljava/lang/String;Lorg/infinispan/configuration/cache/ConfigurationBuilder;)V
     126: aload_0
     127: aload         5
     129: aload_3
     130: invokespecial #169                // Method overrideStatisticsIfPresent:(Lorg/hibernate/cache/infinispan/TypeOverrides;Ljava/util/Properties;)Lorg/hibernate/cache/infinispan/TypeOverrides;
     133: astore        5
     135: aload         5
     137: aload         7
     139: invokevirtual #173                // Method org/hibernate/cache/infinispan/TypeOverrides.applyTo:(Lorg/infinispan/configuration/cache/ConfigurationBuilder;)V
     142: goto          198
     145: aload_0
     146: getfield      #6                  // Field typeOverrides:Ljava/util/Map;
     149: aload_2
     150: invokeinterface #45,  2           // InterfaceMethod java/util/Map.get:(Ljava/lang/Object;)Ljava/lang/Object;
     155: checkcast     #46                 // class org/hibernate/cache/infinispan/TypeOverrides
     158: invokevirtual #47                 // Method org/hibernate/cache/infinispan/TypeOverrides.getCacheName:()Ljava/lang/String;
     161: astore        6
     163: aload         7
     165: aload_0
     166: getfield      #67                 // Field manager:Lorg/infinispan/manager/EmbeddedCacheManager;
     169: aload         6
     171: invokeinterface #84,  2           // InterfaceMethod org/infinispan/manager/EmbeddedCacheManager.getCacheConfiguration:(Ljava/lang/String;)Lorg/infinispan/configuration/cache/Configuration;
     176: invokevirtual #181                // Method org/infinispan/configuration/cache/ConfigurationBuilder.read:(Lorg/infinispan/configuration/cache/Configuration;)Lorg/infinispan/configuration/cache/ConfigurationBuilder;
     179: pop
     180: aload_0
     181: getfield      #6                  // Field typeOverrides:Ljava/util/Map;
     184: aload_2
     185: invokeinterface #45,  2           // InterfaceMethod java/util/Map.get:(Ljava/lang/Object;)Ljava/lang/Object;
     190: checkcast     #46                 // class org/hibernate/cache/infinispan/TypeOverrides
     193: aload         7
     195: invokevirtual #173                // Method org/hibernate/cache/infinispan/TypeOverrides.applyTo:(Lorg/infinispan/configuration/cache/ConfigurationBuilder;)V
     198: aload_0
     199: getfield      #60                 // Field settings:Lorg/hibernate/boot/spi/SessionFactoryOptions;
     202: invokeinterface #61,  1           // InterfaceMethod org/hibernate/boot/spi/SessionFactoryOptions.getMultiTenancyStrategy:()Lorg/hibernate/MultiTenancyStrategy;
     207: getstatic     #62                 // Field org/hibernate/MultiTenancyStrategy.NONE:Lorg/hibernate/MultiTenancyStrategy;
     210: if_acmpne     251
     213: aload         4
     215: ifnull        251
     218: aload         4
     220: invokeinterface #182,  1          // InterfaceMethod org/hibernate/cache/spi/CacheDataDescription.getKeyType:()Lorg/hibernate/type/Type;
     225: ifnull        251
     228: aload         7
     230: invokevirtual #183                // Method org/infinispan/configuration/cache/ConfigurationBuilder.dataContainer:()Lorg/infinispan/configuration/cache/DataContainerConfigurationBuilder;
     233: new           #184                // class org/hibernate/cache/infinispan/TypeEquivalance
     236: dup
     237: aload         4
     239: invokeinterface #182,  1          // InterfaceMethod org/hibernate/cache/spi/CacheDataDescription.getKeyType:()Lorg/hibernate/type/Type;
     244: invokespecial #185                // Method org/hibernate/cache/infinispan/TypeEquivalance."<init>":(Lorg/hibernate/type/Type;)V
     247: invokevirtual #186                // Method org/infinispan/configuration/cache/DataContainerConfigurationBuilder.keyEquivalence:(Lorg/infinispan/commons/equivalence/Equivalence;)Lorg/infinispan/configuration/cache/DataContainerConfigurationBuilder;
     250: pop
     251: aload_0
     252: aload         7
     254: aload         6
     256: aload_3
     257: invokespecial #174                // Method configureTransactionManager:(Lorg/infinispan/configuration/cache/ConfigurationBuilder;Ljava/lang/String;Ljava/util/Properties;)V
     260: aload_0
     261: getfield      #67                 // Field manager:Lorg/infinispan/manager/EmbeddedCacheManager;
     264: aload_1
     265: aload         7
     267: invokevirtual #175                // Method org/infinispan/configuration/cache/ConfigurationBuilder.build:()Lorg/infinispan/configuration/cache/Configuration;
     270: invokeinterface #87,  3           // InterfaceMethod org/infinispan/manager/EmbeddedCacheManager.defineConfiguration:(Ljava/lang/String;Lorg/infinispan/configuration/cache/Configuration;)Lorg/infinispan/configuration/cache/Configuration;
     275: pop
     276: aload_0
     277: getfield      #9                  // Field definedConfigurations:Ljava/util/Set;
     280: aload_1
     281: invokeinterface #177,  2          // InterfaceMethod java/util/Set.add:(Ljava/lang/Object;)Z
     286: pop
     287: aload_0
     288: getfield      #67                 // Field manager:Lorg/infinispan/manager/EmbeddedCacheManager;
     291: aload_1
     292: invokeinterface #187,  2          // InterfaceMethod org/infinispan/manager/EmbeddedCacheManager.getCache:(Ljava/lang/String;)Lorg/infinispan/Cache;
     297: invokeinterface #114,  1          // InterfaceMethod org/infinispan/Cache.getAdvancedCache:()Lorg/infinispan/AdvancedCache;
     302: astore        6
     304: aload         6
     306: invokeinterface #188,  1          // InterfaceMethod org/infinispan/AdvancedCache.getStatus:()Lorg/infinispan/lifecycle/ComponentStatus;
     311: invokevirtual #189                // Method org/infinispan/lifecycle/ComponentStatus.allowInvocations:()Z
     314: ifne          324
     317: aload         6
     319: invokeinterface #190,  1          // InterfaceMethod org/infinispan/AdvancedCache.start:()V
     324: aload_0
     325: aload         6
     327: invokevirtual #191                // Method createCacheWrapper:(Lorg/infinispan/AdvancedCache;)Lorg/infinispan/AdvancedCache;
     330: areturn

  private void applyConfiguration(java.lang.String, org.infinispan.configuration.cache.ConfigurationBuilder);
    Code:
       0: aload_0
       1: getfield      #67                 // Field manager:Lorg/infinispan/manager/EmbeddedCacheManager;
       4: aload_1
       5: invokeinterface #84,  2           // InterfaceMethod org/infinispan/manager/EmbeddedCacheManager.getCacheConfiguration:(Ljava/lang/String;)Lorg/infinispan/configuration/cache/Configuration;
      10: astore_3
      11: aload_3
      12: ifnull        21
      15: aload_2
      16: aload_3
      17: invokevirtual #181                // Method org/infinispan/configuration/cache/ConfigurationBuilder.read:(Lorg/infinispan/configuration/cache/Configuration;)Lorg/infinispan/configuration/cache/ConfigurationBuilder;
      20: pop
      21: return

  private org.hibernate.cache.infinispan.util.CacheCommandFactory getCacheCommandFactory(org.infinispan.AdvancedCache);
    Code:
       0: aload_1
       1: invokeinterface #192,  1          // InterfaceMethod org/infinispan/AdvancedCache.getComponentRegistry:()Lorg/infinispan/factories/ComponentRegistry;
       6: invokevirtual #193                // Method org/infinispan/factories/ComponentRegistry.getGlobalComponentRegistry:()Lorg/infinispan/factories/GlobalComponentRegistry;
       9: astore_2
      10: aload_2
      11: ldc           #194                // String org.infinispan.modules.command.factories
      13: invokevirtual #195                // Method org/infinispan/factories/GlobalComponentRegistry.getComponent:(Ljava/lang/String;)Ljava/lang/Object;
      16: checkcast     #196                // class java/util/Map
      19: astore_3
      20: aload_3
      21: invokeinterface #197,  1          // InterfaceMethod java/util/Map.values:()Ljava/util/Collection;
      26: invokeinterface #198,  1          // InterfaceMethod java/util/Collection.iterator:()Ljava/util/Iterator;
      31: astore        4
      33: aload         4
      35: invokeinterface #199,  1          // InterfaceMethod java/util/Iterator.hasNext:()Z
      40: ifeq          72
      43: aload         4
      45: invokeinterface #200,  1          // InterfaceMethod java/util/Iterator.next:()Ljava/lang/Object;
      50: checkcast     #201                // class org/infinispan/commands/module/ModuleCommandFactory
      53: astore        5
      55: aload         5
      57: instanceof    #202                // class org/hibernate/cache/infinispan/util/CacheCommandFactory
      60: ifeq          69
      63: aload         5
      65: checkcast     #202                // class org/hibernate/cache/infinispan/util/CacheCommandFactory
      68: areturn
      69: goto          33
      72: new           #103                // class org/hibernate/cache/CacheException
      75: dup
      76: ldc           #203                // String Infinispan custom cache command factory not installed (possibly because the classloader where Infinispan lives couldn\'t find the Hibernate Infinispan cache provider)
      78: invokespecial #204                // Method org/hibernate/cache/CacheException."<init>":(Ljava/lang/String;)V
      81: athrow

  protected org.infinispan.AdvancedCache createCacheWrapper(org.infinispan.AdvancedCache);
    Code:
       0: aload_1
       1: areturn

  private void configureTransactionManager(org.infinispan.configuration.cache.ConfigurationBuilder, java.lang.String, java.util.Properties);
    Code:
       0: aload_0
       1: getfield      #67                 // Field manager:Lorg/infinispan/manager/EmbeddedCacheManager;
       4: aload_2
       5: invokeinterface #84,  2           // InterfaceMethod org/infinispan/manager/EmbeddedCacheManager.getCacheConfiguration:(Ljava/lang/String;)Lorg/infinispan/configuration/cache/Configuration;
      10: astore        4
      12: aload         4
      14: ifnull        205
      17: aload         4
      19: invokevirtual #94                 // Method org/infinispan/configuration/cache/Configuration.transaction:()Lorg/infinispan/configuration/cache/TransactionConfiguration;
      22: invokevirtual #95                 // Method org/infinispan/configuration/cache/TransactionConfiguration.transactionMode:()Lorg/infinispan/transaction/TransactionMode;
      25: invokevirtual #96                 // Method org/infinispan/transaction/TransactionMode.isTransactional:()Z
      28: ifeq          205
      31: aload         4
      33: invokevirtual #94                 // Method org/infinispan/configuration/cache/Configuration.transaction:()Lorg/infinispan/configuration/cache/TransactionConfiguration;
      36: invokevirtual #205                // Method org/infinispan/configuration/cache/TransactionConfiguration.transactionManagerLookup:()Lorg/infinispan/transaction/lookup/TransactionManagerLookup;
      39: invokevirtual #206                // Method java/lang/Object.getClass:()Ljava/lang/Class;
      42: invokevirtual #207                // Method java/lang/Class.getName:()Ljava/lang/String;
      45: astore        5
      47: ldc           #107                // class org/hibernate/cache/infinispan/tm/HibernateTransactionManagerLookup
      49: invokevirtual #207                // Method java/lang/Class.getName:()Ljava/lang/String;
      52: astore        6
      54: ldc           #208                // class org/infinispan/transaction/lookup/GenericTransactionManagerLookup
      56: invokevirtual #207                // Method java/lang/Class.getName:()Ljava/lang/String;
      59: aload         5
      61: invokevirtual #49                 // Method java/lang/String.equals:(Ljava/lang/Object;)Z
      64: ifeq          92
      67: getstatic     #13                 // Field log:Lorg/infinispan/util/logging/Log;
      70: ldc           #209                // String Using default Infinispan transaction manager lookup instance (GenericTransactionManagerLookup), overriding it with Hibernate transaction manager lookup
      72: invokeinterface #21,  2           // InterfaceMethod org/infinispan/util/logging/Log.debug:(Ljava/lang/Object;)V
      77: aload_1
      78: invokevirtual #210                // Method org/infinispan/configuration/cache/ConfigurationBuilder.transaction:()Lorg/infinispan/configuration/cache/TransactionConfigurationBuilder;
      81: aload_0
      82: getfield      #70                 // Field transactionManagerlookup:Lorg/infinispan/transaction/lookup/TransactionManagerLookup;
      85: invokevirtual #211                // Method org/infinispan/configuration/cache/TransactionConfigurationBuilder.transactionManagerLookup:(Lorg/infinispan/transaction/lookup/TransactionManagerLookup;)Lorg/infinispan/configuration/cache/TransactionConfigurationBuilder;
      88: pop
      89: goto          170
      92: aload         5
      94: ifnull        158
      97: aload         5
      99: aload         6
     101: invokevirtual #49                 // Method java/lang/String.equals:(Ljava/lang/Object;)Z
     104: ifne          158
     107: getstatic     #13                 // Field log:Lorg/infinispan/util/logging/Log;
     110: new           #15                 // class java/lang/StringBuilder
     113: dup
     114: invokespecial #16                 // Method java/lang/StringBuilder."<init>":()V
     117: ldc           #212                // String Infinispan is configured [
     119: invokevirtual #18                 // Method java/lang/StringBuilder.append:(Ljava/lang/String;)Ljava/lang/StringBuilder;
     122: aload         5
     124: invokevirtual #18                 // Method java/lang/StringBuilder.append:(Ljava/lang/String;)Ljava/lang/StringBuilder;
     127: ldc           #213                // String ] with a different transaction manager lookup
     129: invokevirtual #18                 // Method java/lang/StringBuilder.append:(Ljava/lang/String;)Ljava/lang/StringBuilder;
     132: ldc           #214                // String class than Hibernate [
     134: invokevirtual #18                 // Method java/lang/StringBuilder.append:(Ljava/lang/String;)Ljava/lang/StringBuilder;
     137: aload         6
     139: invokevirtual #18                 // Method java/lang/StringBuilder.append:(Ljava/lang/String;)Ljava/lang/StringBuilder;
     142: ldc           #19                 // String ]
     144: invokevirtual #18                 // Method java/lang/StringBuilder.append:(Ljava/lang/String;)Ljava/lang/StringBuilder;
     147: invokevirtual #20                 // Method java/lang/StringBuilder.toString:()Ljava/lang/String;
     150: invokeinterface #21,  2           // InterfaceMethod org/infinispan/util/logging/Log.debug:(Ljava/lang/Object;)V
     155: goto          170
     158: aload_1
     159: invokevirtual #210                // Method org/infinispan/configuration/cache/ConfigurationBuilder.transaction:()Lorg/infinispan/configuration/cache/TransactionConfigurationBuilder;
     162: aload_0
     163: getfield      #70                 // Field transactionManagerlookup:Lorg/infinispan/transaction/lookup/TransactionManagerLookup;
     166: invokevirtual #211                // Method org/infinispan/configuration/cache/TransactionConfigurationBuilder.transactionManagerLookup:(Lorg/infinispan/transaction/lookup/TransactionManagerLookup;)Lorg/infinispan/configuration/cache/TransactionConfigurationBuilder;
     169: pop
     170: aload_0
     171: ldc           #215                // String hibernate.cache.infinispan.use_synchronization
     173: aload_3
     174: invokespecial #1                  // Method extractProperty:(Ljava/lang/String;Ljava/util/Properties;)Ljava/lang/String;
     177: astore        7
     179: aload         7
     181: ifnonnull     188
     184: iconst_1
     185: goto          193
     188: aload         7
     190: invokestatic  #216                // Method java/lang/Boolean.parseBoolean:(Ljava/lang/String;)Z
     193: istore        8
     195: aload_1
     196: invokevirtual #210                // Method org/infinispan/configuration/cache/ConfigurationBuilder.transaction:()Lorg/infinispan/configuration/cache/TransactionConfigurationBuilder;
     199: iload         8
     201: invokevirtual #217                // Method org/infinispan/configuration/cache/TransactionConfigurationBuilder.useSynchronization:(Z)Lorg/infinispan/configuration/cache/TransactionConfigurationBuilder;
     204: pop
     205: return

  private org.hibernate.cache.infinispan.TypeOverrides overrideStatisticsIfPresent(org.hibernate.cache.infinispan.TypeOverrides, java.util.Properties);
    Code:
       0: aload_0
       1: ldc           #218                // String hibernate.cache.infinispan.statistics
       3: aload_2
       4: invokespecial #1                  // Method extractProperty:(Ljava/lang/String;Ljava/util/Properties;)Ljava/lang/String;
       7: astore_3
       8: aload_3
       9: ifnull        20
      12: aload_1
      13: aload_3
      14: invokestatic  #216                // Method java/lang/Boolean.parseBoolean:(Ljava/lang/String;)Z
      17: invokevirtual #219                // Method org/hibernate/cache/infinispan/TypeOverrides.setExposeStatistics:(Z)V
      20: aload_1
      21: areturn

  public org.infinispan.configuration.cache.Configuration getPendingPutsCacheConfiguration();
    Code:
       0: aload_0
       1: getfield      #85                 // Field pendingPutsCacheConfiguration:Lorg/infinispan/configuration/cache/Configuration;
       4: areturn

  static org.infinispan.configuration.parsing.ConfigurationBuilderHolder access$000(org.infinispan.configuration.parsing.ParserRegistry, java.io.InputStream, java.lang.ClassLoader);
    Code:
       0: aload_0
       1: aload_1
       2: aload_2
       3: invokestatic  #2                  // Method parseWithOverridenClassLoader:(Lorg/infinispan/configuration/parsing/ParserRegistry;Ljava/io/InputStream;Ljava/lang/ClassLoader;)Lorg/infinispan/configuration/parsing/ConfigurationBuilderHolder;
       6: areturn

  static java.lang.String access$100(org.hibernate.cache.infinispan.InfinispanRegionFactory, java.lang.String, java.util.Properties);
    Code:
       0: aload_0
       1: aload_1
       2: aload_2
       3: invokespecial #1                  // Method extractProperty:(Ljava/lang/String;Ljava/util/Properties;)Ljava/lang/String;
       6: areturn

  static {};
    Code:
       0: ldc           #22                 // class org/hibernate/cache/infinispan/InfinispanRegionFactory
       2: invokestatic  #220                // Method org/infinispan/util/logging/LogFactory.getLog:(Ljava/lang/Class;)Lorg/infinispan/util/logging/Log;
       5: putstatic     #13                 // Field log:Lorg/infinispan/util/logging/Log;
       8: new           #170                // class org/infinispan/configuration/cache/ConfigurationBuilder
      11: dup
      12: invokespecial #171                // Method org/infinispan/configuration/cache/ConfigurationBuilder."<init>":()V
      15: invokevirtual #221                // Method org/infinispan/configuration/cache/ConfigurationBuilder.clustering:()Lorg/infinispan/configuration/cache/ClusteringConfigurationBuilder;
      18: getstatic     #222                // Field org/infinispan/configuration/cache/CacheMode.LOCAL:Lorg/infinispan/configuration/cache/CacheMode;
      21: invokevirtual #223                // Method org/infinispan/configuration/cache/ClusteringConfigurationBuilder.cacheMode:(Lorg/infinispan/configuration/cache/CacheMode;)Lorg/infinispan/configuration/cache/ClusteringConfigurationBuilder;
      24: invokevirtual #224                // Method org/infinispan/configuration/cache/ClusteringConfigurationBuilder.transaction:()Lorg/infinispan/configuration/cache/TransactionConfigurationBuilder;
      27: getstatic     #225                // Field org/infinispan/transaction/TransactionMode.NON_TRANSACTIONAL:Lorg/infinispan/transaction/TransactionMode;
      30: invokevirtual #226                // Method org/infinispan/configuration/cache/TransactionConfigurationBuilder.transactionMode:(Lorg/infinispan/transaction/TransactionMode;)Lorg/infinispan/configuration/cache/TransactionConfigurationBuilder;
      33: invokevirtual #227                // Method org/infinispan/configuration/cache/TransactionConfigurationBuilder.expiration:()Lorg/infinispan/configuration/cache/ExpirationConfigurationBuilder;
      36: getstatic     #228                // Field java/util/concurrent/TimeUnit.SECONDS:Ljava/util/concurrent/TimeUnit;
      39: ldc2_w        #229                // long 60l
      42: invokevirtual #231                // Method java/util/concurrent/TimeUnit.toMillis:(J)J
      45: invokevirtual #232                // Method org/infinispan/configuration/cache/ExpirationConfigurationBuilder.maxIdle:(J)Lorg/infinispan/configuration/cache/ExpirationConfigurationBuilder;
      48: invokevirtual #233                // Method org/infinispan/configuration/cache/ExpirationConfigurationBuilder.jmxStatistics:()Lorg/infinispan/configuration/cache/JMXStatisticsConfigurationBuilder;
      51: invokevirtual #234                // Method org/infinispan/configuration/cache/JMXStatisticsConfigurationBuilder.disable:()Lorg/infinispan/configuration/cache/JMXStatisticsConfigurationBuilder;
      54: invokevirtual #235                // Method org/infinispan/configuration/cache/JMXStatisticsConfigurationBuilder.build:()Lorg/infinispan/configuration/cache/Configuration;
      57: putstatic     #86                 // Field DEFAULT_PENDING_PUTS_CACHE_CONFIGURATION:Lorg/infinispan/configuration/cache/Configuration;
      60: return
}
