Compiled from "TypeOverrides.java"
public class org.hibernate.cache.infinispan.TypeOverrides implements java.io.Serializable {
  private final java.util.Set<java.lang.String> overridden;

  private java.lang.String cacheName;

  private org.infinispan.eviction.EvictionStrategy evictionStrategy;

  private long evictionWakeUpInterval;

  private int evictionMaxEntries;

  private long expirationLifespan;

  private long expirationMaxIdle;

  private boolean isExposeStatistics;

  public org.hibernate.cache.infinispan.TypeOverrides();
    Code:
       0: aload_0
       1: invokespecial #1                  // Method java/lang/Object."<init>":()V
       4: aload_0
       5: new           #2                  // class java/util/HashSet
       8: dup
       9: invokespecial #3                  // Method java/util/HashSet."<init>":()V
      12: putfield      #4                  // Field overridden:Ljava/util/Set;
      15: return

  public java.lang.String getCacheName();
    Code:
       0: aload_0
       1: getfield      #5                  // Field cacheName:Ljava/lang/String;
       4: areturn

  public void setCacheName(java.lang.String);
    Code:
       0: aload_0
       1: aload_1
       2: putfield      #5                  // Field cacheName:Ljava/lang/String;
       5: return

  public org.infinispan.eviction.EvictionStrategy getEvictionStrategy();
    Code:
       0: aload_0
       1: getfield      #6                  // Field evictionStrategy:Lorg/infinispan/eviction/EvictionStrategy;
       4: areturn

  public void setEvictionStrategy(java.lang.String);
    Code:
       0: aload_0
       1: ldc           #7                  // String evictionStrategy
       3: invokespecial #8                  // Method markAsOverriden:(Ljava/lang/String;)V
       6: aload_0
       7: aload_0
       8: aload_1
       9: invokespecial #9                  // Method uc:(Ljava/lang/String;)Ljava/lang/String;
      12: invokestatic  #10                 // Method org/infinispan/eviction/EvictionStrategy.valueOf:(Ljava/lang/String;)Lorg/infinispan/eviction/EvictionStrategy;
      15: putfield      #6                  // Field evictionStrategy:Lorg/infinispan/eviction/EvictionStrategy;
      18: return

  public long getEvictionWakeUpInterval();
    Code:
       0: aload_0
       1: getfield      #11                 // Field evictionWakeUpInterval:J
       4: lreturn

  public void setEvictionWakeUpInterval(long);
    Code:
       0: aload_0
       1: ldc           #12                 // String evictionWakeUpInterval
       3: invokespecial #8                  // Method markAsOverriden:(Ljava/lang/String;)V
       6: aload_0
       7: lload_1
       8: putfield      #11                 // Field evictionWakeUpInterval:J
      11: return

  public int getEvictionMaxEntries();
    Code:
       0: aload_0
       1: getfield      #13                 // Field evictionMaxEntries:I
       4: ireturn

  public void setEvictionMaxEntries(int);
    Code:
       0: aload_0
       1: ldc           #14                 // String evictionMaxEntries
       3: invokespecial #8                  // Method markAsOverriden:(Ljava/lang/String;)V
       6: aload_0
       7: iload_1
       8: putfield      #13                 // Field evictionMaxEntries:I
      11: return

  public long getExpirationLifespan();
    Code:
       0: aload_0
       1: getfield      #15                 // Field expirationLifespan:J
       4: lreturn

  public void setExpirationLifespan(long);
    Code:
       0: aload_0
       1: ldc           #16                 // String expirationLifespan
       3: invokespecial #8                  // Method markAsOverriden:(Ljava/lang/String;)V
       6: aload_0
       7: lload_1
       8: putfield      #15                 // Field expirationLifespan:J
      11: return

  public long getExpirationMaxIdle();
    Code:
       0: aload_0
       1: getfield      #17                 // Field expirationMaxIdle:J
       4: lreturn

  public void setExpirationMaxIdle(long);
    Code:
       0: aload_0
       1: ldc           #18                 // String expirationMaxIdle
       3: invokespecial #8                  // Method markAsOverriden:(Ljava/lang/String;)V
       6: aload_0
       7: lload_1
       8: putfield      #17                 // Field expirationMaxIdle:J
      11: return

  public boolean isExposeStatistics();
    Code:
       0: aload_0
       1: getfield      #19                 // Field isExposeStatistics:Z
       4: ireturn

  public void setExposeStatistics(boolean);
    Code:
       0: aload_0
       1: ldc           #20                 // String isExposeStatistics
       3: invokespecial #8                  // Method markAsOverriden:(Ljava/lang/String;)V
       6: aload_0
       7: iload_1
       8: putfield      #19                 // Field isExposeStatistics:Z
      11: return

  public void applyTo(org.infinispan.configuration.cache.ConfigurationBuilder);
    Code:
       0: aload_0
       1: getfield      #4                  // Field overridden:Ljava/util/Set;
       4: ldc           #7                  // String evictionStrategy
       6: invokeinterface #21,  2           // InterfaceMethod java/util/Set.contains:(Ljava/lang/Object;)Z
      11: ifeq          26
      14: aload_1
      15: invokevirtual #22                 // Method org/infinispan/configuration/cache/ConfigurationBuilder.eviction:()Lorg/infinispan/configuration/cache/EvictionConfigurationBuilder;
      18: aload_0
      19: getfield      #6                  // Field evictionStrategy:Lorg/infinispan/eviction/EvictionStrategy;
      22: invokevirtual #23                 // Method org/infinispan/configuration/cache/EvictionConfigurationBuilder.strategy:(Lorg/infinispan/eviction/EvictionStrategy;)Lorg/infinispan/configuration/cache/EvictionConfigurationBuilder;
      25: pop
      26: aload_0
      27: getfield      #4                  // Field overridden:Ljava/util/Set;
      30: ldc           #12                 // String evictionWakeUpInterval
      32: invokeinterface #21,  2           // InterfaceMethod java/util/Set.contains:(Ljava/lang/Object;)Z
      37: ifeq          52
      40: aload_1
      41: invokevirtual #24                 // Method org/infinispan/configuration/cache/ConfigurationBuilder.expiration:()Lorg/infinispan/configuration/cache/ExpirationConfigurationBuilder;
      44: aload_0
      45: getfield      #11                 // Field evictionWakeUpInterval:J
      48: invokevirtual #25                 // Method org/infinispan/configuration/cache/ExpirationConfigurationBuilder.wakeUpInterval:(J)Lorg/infinispan/configuration/cache/ExpirationConfigurationBuilder;
      51: pop
      52: aload_0
      53: getfield      #4                  // Field overridden:Ljava/util/Set;
      56: ldc           #14                 // String evictionMaxEntries
      58: invokeinterface #21,  2           // InterfaceMethod java/util/Set.contains:(Ljava/lang/Object;)Z
      63: ifeq          78
      66: aload_1
      67: invokevirtual #22                 // Method org/infinispan/configuration/cache/ConfigurationBuilder.eviction:()Lorg/infinispan/configuration/cache/EvictionConfigurationBuilder;
      70: aload_0
      71: getfield      #13                 // Field evictionMaxEntries:I
      74: invokevirtual #26                 // Method org/infinispan/configuration/cache/EvictionConfigurationBuilder.maxEntries:(I)Lorg/infinispan/configuration/cache/EvictionConfigurationBuilder;
      77: pop
      78: aload_0
      79: getfield      #4                  // Field overridden:Ljava/util/Set;
      82: ldc           #16                 // String expirationLifespan
      84: invokeinterface #21,  2           // InterfaceMethod java/util/Set.contains:(Ljava/lang/Object;)Z
      89: ifeq          104
      92: aload_1
      93: invokevirtual #24                 // Method org/infinispan/configuration/cache/ConfigurationBuilder.expiration:()Lorg/infinispan/configuration/cache/ExpirationConfigurationBuilder;
      96: aload_0
      97: getfield      #15                 // Field expirationLifespan:J
     100: invokevirtual #27                 // Method org/infinispan/configuration/cache/ExpirationConfigurationBuilder.lifespan:(J)Lorg/infinispan/configuration/cache/ExpirationConfigurationBuilder;
     103: pop
     104: aload_0
     105: getfield      #4                  // Field overridden:Ljava/util/Set;
     108: ldc           #18                 // String expirationMaxIdle
     110: invokeinterface #21,  2           // InterfaceMethod java/util/Set.contains:(Ljava/lang/Object;)Z
     115: ifeq          130
     118: aload_1
     119: invokevirtual #24                 // Method org/infinispan/configuration/cache/ConfigurationBuilder.expiration:()Lorg/infinispan/configuration/cache/ExpirationConfigurationBuilder;
     122: aload_0
     123: getfield      #17                 // Field expirationMaxIdle:J
     126: invokevirtual #28                 // Method org/infinispan/configuration/cache/ExpirationConfigurationBuilder.maxIdle:(J)Lorg/infinispan/configuration/cache/ExpirationConfigurationBuilder;
     129: pop
     130: aload_0
     131: getfield      #4                  // Field overridden:Ljava/util/Set;
     134: ldc           #20                 // String isExposeStatistics
     136: invokeinterface #21,  2           // InterfaceMethod java/util/Set.contains:(Ljava/lang/Object;)Z
     141: ifeq          159
     144: aload_0
     145: getfield      #19                 // Field isExposeStatistics:Z
     148: ifeq          159
     151: aload_1
     152: invokevirtual #29                 // Method org/infinispan/configuration/cache/ConfigurationBuilder.jmxStatistics:()Lorg/infinispan/configuration/cache/JMXStatisticsConfigurationBuilder;
     155: invokevirtual #30                 // Method org/infinispan/configuration/cache/JMXStatisticsConfigurationBuilder.enable:()Lorg/infinispan/configuration/cache/JMXStatisticsConfigurationBuilder;
     158: pop
     159: return

  public void validateInfinispanConfiguration(org.infinispan.configuration.cache.Configuration) throws org.hibernate.cache.CacheException;
    Code:
       0: return

  public java.lang.String toString();
    Code:
       0: new           #31                 // class java/lang/StringBuilder
       3: dup
       4: invokespecial #32                 // Method java/lang/StringBuilder."<init>":()V
       7: aload_0
       8: invokevirtual #33                 // Method java/lang/Object.getClass:()Ljava/lang/Class;
      11: invokevirtual #34                 // Method java/lang/Class.getSimpleName:()Ljava/lang/String;
      14: invokevirtual #35                 // Method java/lang/StringBuilder.append:(Ljava/lang/String;)Ljava/lang/StringBuilder;
      17: bipush        123
      19: invokevirtual #36                 // Method java/lang/StringBuilder.append:(C)Ljava/lang/StringBuilder;
      22: ldc           #37                 // String cache=
      24: invokevirtual #35                 // Method java/lang/StringBuilder.append:(Ljava/lang/String;)Ljava/lang/StringBuilder;
      27: aload_0
      28: getfield      #5                  // Field cacheName:Ljava/lang/String;
      31: invokevirtual #35                 // Method java/lang/StringBuilder.append:(Ljava/lang/String;)Ljava/lang/StringBuilder;
      34: ldc           #38                 // String , strategy=
      36: invokevirtual #35                 // Method java/lang/StringBuilder.append:(Ljava/lang/String;)Ljava/lang/StringBuilder;
      39: aload_0
      40: getfield      #6                  // Field evictionStrategy:Lorg/infinispan/eviction/EvictionStrategy;
      43: invokevirtual #39                 // Method java/lang/StringBuilder.append:(Ljava/lang/Object;)Ljava/lang/StringBuilder;
      46: ldc           #40                 // String , wakeUpInterval=
      48: invokevirtual #35                 // Method java/lang/StringBuilder.append:(Ljava/lang/String;)Ljava/lang/StringBuilder;
      51: aload_0
      52: getfield      #11                 // Field evictionWakeUpInterval:J
      55: invokevirtual #41                 // Method java/lang/StringBuilder.append:(J)Ljava/lang/StringBuilder;
      58: ldc           #42                 // String , maxEntries=
      60: invokevirtual #35                 // Method java/lang/StringBuilder.append:(Ljava/lang/String;)Ljava/lang/StringBuilder;
      63: aload_0
      64: getfield      #13                 // Field evictionMaxEntries:I
      67: invokevirtual #43                 // Method java/lang/StringBuilder.append:(I)Ljava/lang/StringBuilder;
      70: ldc           #44                 // String , lifespan=
      72: invokevirtual #35                 // Method java/lang/StringBuilder.append:(Ljava/lang/String;)Ljava/lang/StringBuilder;
      75: aload_0
      76: getfield      #15                 // Field expirationLifespan:J
      79: invokevirtual #41                 // Method java/lang/StringBuilder.append:(J)Ljava/lang/StringBuilder;
      82: ldc           #45                 // String , maxIdle=
      84: invokevirtual #35                 // Method java/lang/StringBuilder.append:(Ljava/lang/String;)Ljava/lang/StringBuilder;
      87: aload_0
      88: getfield      #17                 // Field expirationMaxIdle:J
      91: invokevirtual #41                 // Method java/lang/StringBuilder.append:(J)Ljava/lang/StringBuilder;
      94: bipush        125
      96: invokevirtual #36                 // Method java/lang/StringBuilder.append:(C)Ljava/lang/StringBuilder;
      99: invokevirtual #46                 // Method java/lang/StringBuilder.toString:()Ljava/lang/String;
     102: areturn

  private java.lang.String uc(java.lang.String);
    Code:
       0: aload_1
       1: ifnonnull     8
       4: aconst_null
       5: goto          15
       8: aload_1
       9: getstatic     #47                 // Field java/util/Locale.ENGLISH:Ljava/util/Locale;
      12: invokevirtual #48                 // Method java/lang/String.toUpperCase:(Ljava/util/Locale;)Ljava/lang/String;
      15: areturn

  private void markAsOverriden(java.lang.String);
    Code:
       0: aload_0
       1: getfield      #4                  // Field overridden:Ljava/util/Set;
       4: aload_1
       5: invokeinterface #49,  2           // InterfaceMethod java/util/Set.add:(Ljava/lang/Object;)Z
      10: pop
      11: return
}
