Compiled from "FluxDoFinallyFuseable.java"
final class reactor.core.publisher.FluxDoFinallyFuseable<T> extends reactor.core.publisher.FluxOperator<T, T> implements reactor.core.Fuseable {
  final java.util.function.Consumer<reactor.core.publisher.SignalType> onFinally;

  reactor.core.publisher.FluxDoFinallyFuseable(reactor.core.publisher.Flux<? extends T>, java.util.function.Consumer<reactor.core.publisher.SignalType>);
    Code:
       0: aload_0
       1: aload_1
       2: invokespecial #1                  // Method reactor/core/publisher/FluxOperator."<init>":(Lreactor/core/publisher/Flux;)V
       5: aload_0
       6: aload_2
       7: putfield      #2                  // Field onFinally:Ljava/util/function/Consumer;
      10: return

  public void subscribe(reactor.core.CoreSubscriber<? super T>);
    Code:
       0: aload_0
       1: getfield      #3                  // Field source:Lreactor/core/publisher/Flux;
       4: aload_1
       5: aload_0
       6: getfield      #2                  // Field onFinally:Ljava/util/function/Consumer;
       9: iconst_1
      10: invokestatic  #4                  // Method reactor/core/publisher/FluxDoFinally.createSubscriber:(Lreactor/core/CoreSubscriber;Ljava/util/function/Consumer;Z)Lreactor/core/CoreSubscriber;
      13: invokevirtual #5                  // Method reactor/core/publisher/Flux.subscribe:(Lreactor/core/CoreSubscriber;)V
      16: return
}
