Compiled from "RingBuffer.java"
final class reactor.core.publisher.UnsafeSequence extends reactor.core.publisher.RhsPadding implements reactor.core.publisher.RingBuffer$Sequence,java.util.function.LongSupplier {
  private static final sun.misc.Unsafe UNSAFE;

  private static final long VALUE_OFFSET;

  reactor.core.publisher.UnsafeSequence(long);
    Code:
       0: aload_0
       1: invokespecial #1                  // Method reactor/core/publisher/RhsPadding."<init>":()V
       4: getstatic     #2                  // Field UNSAFE:Lsun/misc/Unsafe;
       7: aload_0
       8: getstatic     #3                  // Field VALUE_OFFSET:J
      11: lload_1
      12: invokevirtual #4                  // Method sun/misc/Unsafe.putOrderedLong:(Ljava/lang/Object;JJ)V
      15: return

  public long getAsLong();
    Code:
       0: aload_0
       1: getfield      #5                  // Field value:J
       4: lreturn

  public void set(long);
    Code:
       0: getstatic     #2                  // Field UNSAFE:Lsun/misc/Unsafe;
       3: aload_0
       4: getstatic     #3                  // Field VALUE_OFFSET:J
       7: lload_1
       8: invokevirtual #4                  // Method sun/misc/Unsafe.putOrderedLong:(Ljava/lang/Object;JJ)V
      11: return

  public boolean compareAndSet(long, long);
    Code:
       0: getstatic     #2                  // Field UNSAFE:Lsun/misc/Unsafe;
       3: aload_0
       4: getstatic     #3                  // Field VALUE_OFFSET:J
       7: lload_1
       8: lload_3
       9: invokevirtual #6                  // Method sun/misc/Unsafe.compareAndSwapLong:(Ljava/lang/Object;JJJ)Z
      12: ireturn

  static {};
    Code:
       0: invokestatic  #7                  // Method reactor/core/publisher/RingBuffer.getUnsafe:()Ljava/lang/Object;
       3: checkcast     #8                  // class sun/misc/Unsafe
       6: putstatic     #2                  // Field UNSAFE:Lsun/misc/Unsafe;
       9: getstatic     #2                  // Field UNSAFE:Lsun/misc/Unsafe;
      12: ldc           #9                  // class reactor/core/publisher/Value
      14: ldc           #10                 // String value
      16: invokevirtual #11                 // Method java/lang/Class.getDeclaredField:(Ljava/lang/String;)Ljava/lang/reflect/Field;
      19: invokevirtual #12                 // Method sun/misc/Unsafe.objectFieldOffset:(Ljava/lang/reflect/Field;)J
      22: putstatic     #3                  // Field VALUE_OFFSET:J
      25: goto          38
      28: astore_0
      29: new           #14                 // class java/lang/RuntimeException
      32: dup
      33: aload_0
      34: invokespecial #15                 // Method java/lang/RuntimeException."<init>":(Ljava/lang/Throwable;)V
      37: athrow
      38: return
    Exception table:
       from    to  target type
           9    25    28   Class java/lang/Exception
}
