Compiled from "WorkQueueProcessor.java"
class reactor.core.publisher.WorkQueueProcessor$WorkQueueInner$1 implements java.lang.Runnable {
  final reactor.core.publisher.WorkQueueProcessor$WorkQueueInner this$0;

  reactor.core.publisher.WorkQueueProcessor$WorkQueueInner$1(reactor.core.publisher.WorkQueueProcessor$WorkQueueInner);
    Code:
       0: aload_0
       1: aload_1
       2: putfield      #1                  // Field this$0:Lreactor/core/publisher/WorkQueueProcessor$WorkQueueInner;
       5: aload_0
       6: invokespecial #2                  // Method java/lang/Object."<init>":()V
       9: return

  public void run();
    Code:
       0: aload_0
       1: getfield      #1                  // Field this$0:Lreactor/core/publisher/WorkQueueProcessor$WorkQueueInner;
       4: getfield      #3                  // Field reactor/core/publisher/WorkQueueProcessor$WorkQueueInner.barrier:Lreactor/core/publisher/RingBuffer$Reader;
       7: invokevirtual #4                  // Method reactor/core/publisher/RingBuffer$Reader.isAlerted:()Z
      10: ifne          57
      13: aload_0
      14: getfield      #1                  // Field this$0:Lreactor/core/publisher/WorkQueueProcessor$WorkQueueInner;
      17: invokevirtual #5                  // Method reactor/core/publisher/WorkQueueProcessor$WorkQueueInner.isRunning:()Z
      20: ifeq          57
      23: aload_0
      24: getfield      #1                  // Field this$0:Lreactor/core/publisher/WorkQueueProcessor$WorkQueueInner;
      27: aload_0
      28: getfield      #1                  // Field this$0:Lreactor/core/publisher/WorkQueueProcessor$WorkQueueInner;
      31: getfield      #6                  // Field reactor/core/publisher/WorkQueueProcessor$WorkQueueInner.pendingRequest:Lreactor/core/publisher/RingBuffer$Sequence;
      34: invokeinterface #7,  1            // InterfaceMethod reactor/core/publisher/RingBuffer$Sequence.getAsLong:()J
      39: ldc2_w        #9                  // long 9223372036854775807l
      42: lcmp
      43: ifne          50
      46: iconst_1
      47: goto          51
      50: iconst_0
      51: invokevirtual #11                 // Method reactor/core/publisher/WorkQueueProcessor$WorkQueueInner.replay:(Z)Z
      54: ifeq          60
      57: invokestatic  #12                 // Method reactor/util/concurrent/WaitStrategy.alert:()V
      60: return
}
