Compiled from "NativeQueryTupleTransformer.java"
public class org.hibernate.jpa.spi.NativeQueryTupleTransformer extends org.hibernate.transform.BasicTransformerAdapter {
  public org.hibernate.jpa.spi.NativeQueryTupleTransformer();
    Code:
       0: aload_0
       1: invokespecial #1                  // Method org/hibernate/transform/BasicTransformerAdapter."<init>":()V
       4: return

  public java.lang.Object transformTuple(java.lang.Object[], java.lang.String[]);
    Code:
       0: new           #2                  // class org/hibernate/jpa/spi/NativeQueryTupleTransformer$NativeTupleImpl
       3: dup
       4: aload_1
       5: aload_2
       6: invokespecial #3                  // Method org/hibernate/jpa/spi/NativeQueryTupleTransformer$NativeTupleImpl."<init>":([Ljava/lang/Object;[Ljava/lang/String;)V
       9: areturn
}
