Compiled from "ActiveMQFrameDecoder2.java"
public class org.apache.activemq.artemis.core.remoting.impl.netty.ActiveMQFrameDecoder2 extends io.netty.handler.codec.LengthFieldBasedFrameDecoder {
  public org.apache.activemq.artemis.core.remoting.impl.netty.ActiveMQFrameDecoder2();
    Code:
       0: aload_0
       1: ldc           #2                  // int 2147483647
       3: iconst_0
       4: iconst_4
       5: invokespecial #4                  // Method io/netty/handler/codec/LengthFieldBasedFrameDecoder."<init>":(III)V
       8: return

  protected io.netty.buffer.ByteBuf extractFrame(io.netty.channel.ChannelHandlerContext, io.netty.buffer.ByteBuf, int, int);
    Code:
       0: aload_1
       1: invokeinterface #5,  1            // InterfaceMethod io/netty/channel/ChannelHandlerContext.alloc:()Lio/netty/buffer/ByteBufAllocator;
       6: iload         4
       8: invokeinterface #6,  2            // InterfaceMethod io/netty/buffer/ByteBufAllocator.buffer:(I)Lio/netty/buffer/ByteBuf;
      13: astore        5
      15: aload         5
      17: aload_2
      18: iload_3
      19: iload         4
      21: invokevirtual #7                  // Method io/netty/buffer/ByteBuf.writeBytes:(Lio/netty/buffer/ByteBuf;II)Lio/netty/buffer/ByteBuf;
      24: pop
      25: aload         5
      27: iconst_4
      28: invokevirtual #8                  // Method io/netty/buffer/ByteBuf.skipBytes:(I)Lio/netty/buffer/ByteBuf;
      31: areturn
}
