Compiled from "SharedNioEventLoopGroup.java"
class org.apache.activemq.artemis.core.remoting.impl.netty.SharedNioEventLoopGroup$2 implements java.lang.Runnable {
  final long val$l;

  final long val$l2;

  final java.util.concurrent.TimeUnit val$timeUnit;

  final org.apache.activemq.artemis.core.remoting.impl.netty.SharedNioEventLoopGroup this$0;

  org.apache.activemq.artemis.core.remoting.impl.netty.SharedNioEventLoopGroup$2(org.apache.activemq.artemis.core.remoting.impl.netty.SharedNioEventLoopGroup, long, long, java.util.concurrent.TimeUnit);
    Code:
       0: aload_0
       1: aload_1
       2: putfield      #1                  // Field this$0:Lorg/apache/activemq/artemis/core/remoting/impl/netty/SharedNioEventLoopGroup;
       5: aload_0
       6: lload_2
       7: putfield      #2                  // Field val$l:J
      10: aload_0
      11: lload         4
      13: putfield      #3                  // Field val$l2:J
      16: aload_0
      17: aload         6
      19: putfield      #4                  // Field val$timeUnit:Ljava/util/concurrent/TimeUnit;
      22: aload_0
      23: invokespecial #5                  // Method java/lang/Object."<init>":()V
      26: return

  public void run();
    Code:
       0: ldc           #6                  // class org/apache/activemq/artemis/core/remoting/impl/netty/SharedNioEventLoopGroup
       2: dup
       3: astore_1
       4: monitorenter
       5: aload_0
       6: getfield      #1                  // Field this$0:Lorg/apache/activemq/artemis/core/remoting/impl/netty/SharedNioEventLoopGroup;
       9: invokestatic  #7                  // Method org/apache/activemq/artemis/core/remoting/impl/netty/SharedNioEventLoopGroup.access$000:(Lorg/apache/activemq/artemis/core/remoting/impl/netty/SharedNioEventLoopGroup;)Ljava/util/concurrent/atomic/AtomicReference;
      12: invokevirtual #8                  // Method java/util/concurrent/atomic/AtomicReference.get:()Ljava/lang/Object;
      15: ifnull        58
      18: aload_0
      19: getfield      #1                  // Field this$0:Lorg/apache/activemq/artemis/core/remoting/impl/netty/SharedNioEventLoopGroup;
      22: aload_0
      23: getfield      #2                  // Field val$l:J
      26: aload_0
      27: getfield      #3                  // Field val$l2:J
      30: aload_0
      31: getfield      #4                  // Field val$timeUnit:Ljava/util/concurrent/TimeUnit;
      34: invokestatic  #9                  // Method org/apache/activemq/artemis/core/remoting/impl/netty/SharedNioEventLoopGroup.access$101:(Lorg/apache/activemq/artemis/core/remoting/impl/netty/SharedNioEventLoopGroup;JJLjava/util/concurrent/TimeUnit;)Lio/netty/util/concurrent/Future;
      37: astore_2
      38: aload_2
      39: new           #10                 // class org/apache/activemq/artemis/core/remoting/impl/netty/SharedNioEventLoopGroup$2$1
      42: dup
      43: aload_0
      44: invokespecial #11                 // Method org/apache/activemq/artemis/core/remoting/impl/netty/SharedNioEventLoopGroup$2$1."<init>":(Lorg/apache/activemq/artemis/core/remoting/impl/netty/SharedNioEventLoopGroup$2;)V
      47: invokeinterface #12,  2           // InterfaceMethod io/netty/util/concurrent/Future.addListener:(Lio/netty/util/concurrent/GenericFutureListener;)Lio/netty/util/concurrent/Future;
      52: pop
      53: aconst_null
      54: invokestatic  #13                 // Method org/apache/activemq/artemis/core/remoting/impl/netty/SharedNioEventLoopGroup.access$302:(Lorg/apache/activemq/artemis/core/remoting/impl/netty/SharedNioEventLoopGroup;)Lorg/apache/activemq/artemis/core/remoting/impl/netty/SharedNioEventLoopGroup;
      57: pop
      58: aload_1
      59: monitorexit
      60: goto          68
      63: astore_3
      64: aload_1
      65: monitorexit
      66: aload_3
      67: athrow
      68: return
    Exception table:
       from    to  target type
           5    60    63   any
          63    66    63   any
}
