Compiled from "OpVars.java"
class org.apache.jena.sparql.algebra.OpVars$OpVarsPattern extends org.apache.jena.sparql.algebra.OpVisitorBase {
  protected java.util.Set<org.apache.jena.sparql.core.Var> acc;

  final boolean visibleOnly;

  org.apache.jena.sparql.algebra.OpVars$OpVarsPattern(java.util.Set<org.apache.jena.sparql.core.Var>, boolean);
    Code:
       0: aload_0
       1: invokespecial #1                  // Method org/apache/jena/sparql/algebra/OpVisitorBase."<init>":()V
       4: aload_0
       5: aload_1
       6: putfield      #2                  // Field acc:Ljava/util/Set;
       9: aload_0
      10: iload_2
      11: putfield      #3                  // Field visibleOnly:Z
      14: return

  public void visit(org.apache.jena.sparql.algebra.op.OpBGP);
    Code:
       0: aload_0
       1: getfield      #2                  // Field acc:Ljava/util/Set;
       4: aload_1
       5: invokevirtual #4                  // Method org/apache/jena/sparql/algebra/op/OpBGP.getPattern:()Lorg/apache/jena/sparql/core/BasicPattern;
       8: invokestatic  #5                  // Method org/apache/jena/sparql/util/VarUtils.addVars:(Ljava/util/Collection;Lorg/apache/jena/sparql/core/BasicPattern;)V
      11: return

  public void visit(org.apache.jena.sparql.algebra.op.OpPath);
    Code:
       0: aload_0
       1: getfield      #2                  // Field acc:Ljava/util/Set;
       4: aload_1
       5: invokevirtual #6                  // Method org/apache/jena/sparql/algebra/op/OpPath.getTriplePath:()Lorg/apache/jena/sparql/core/TriplePath;
       8: invokevirtual #7                  // Method org/apache/jena/sparql/core/TriplePath.getSubject:()Lorg/apache/jena/graph/Node;
      11: invokestatic  #8                  // Method org/apache/jena/sparql/core/Vars.addVar:(Ljava/util/Collection;Lorg/apache/jena/graph/Node;)V
      14: aload_0
      15: getfield      #2                  // Field acc:Ljava/util/Set;
      18: aload_1
      19: invokevirtual #6                  // Method org/apache/jena/sparql/algebra/op/OpPath.getTriplePath:()Lorg/apache/jena/sparql/core/TriplePath;
      22: invokevirtual #9                  // Method org/apache/jena/sparql/core/TriplePath.getObject:()Lorg/apache/jena/graph/Node;
      25: invokestatic  #8                  // Method org/apache/jena/sparql/core/Vars.addVar:(Ljava/util/Collection;Lorg/apache/jena/graph/Node;)V
      28: return

  public void visit(org.apache.jena.sparql.algebra.op.OpQuadPattern);
    Code:
       0: aload_0
       1: getfield      #2                  // Field acc:Ljava/util/Set;
       4: aload_1
       5: invokevirtual #10                 // Method org/apache/jena/sparql/algebra/op/OpQuadPattern.getGraphNode:()Lorg/apache/jena/graph/Node;
       8: invokestatic  #8                  // Method org/apache/jena/sparql/core/Vars.addVar:(Ljava/util/Collection;Lorg/apache/jena/graph/Node;)V
      11: aload_0
      12: getfield      #2                  // Field acc:Ljava/util/Set;
      15: aload_1
      16: invokevirtual #11                 // Method org/apache/jena/sparql/algebra/op/OpQuadPattern.getBasicPattern:()Lorg/apache/jena/sparql/core/BasicPattern;
      19: invokestatic  #5                  // Method org/apache/jena/sparql/util/VarUtils.addVars:(Ljava/util/Collection;Lorg/apache/jena/sparql/core/BasicPattern;)V
      22: return

  public void visit(org.apache.jena.sparql.algebra.op.OpGraph);
    Code:
       0: aload_0
       1: getfield      #2                  // Field acc:Ljava/util/Set;
       4: aload_1
       5: invokevirtual #12                 // Method org/apache/jena/sparql/algebra/op/OpGraph.getNode:()Lorg/apache/jena/graph/Node;
       8: invokestatic  #8                  // Method org/apache/jena/sparql/core/Vars.addVar:(Ljava/util/Collection;Lorg/apache/jena/graph/Node;)V
      11: return

  public void visit(org.apache.jena.sparql.algebra.op.OpDatasetNames);
    Code:
       0: aload_0
       1: getfield      #2                  // Field acc:Ljava/util/Set;
       4: aload_1
       5: invokevirtual #13                 // Method org/apache/jena/sparql/algebra/op/OpDatasetNames.getGraphNode:()Lorg/apache/jena/graph/Node;
       8: invokestatic  #8                  // Method org/apache/jena/sparql/core/Vars.addVar:(Ljava/util/Collection;Lorg/apache/jena/graph/Node;)V
      11: return

  public void visit(org.apache.jena.sparql.algebra.op.OpTable);
    Code:
       0: aload_1
       1: invokevirtual #14                 // Method org/apache/jena/sparql/algebra/op/OpTable.getTable:()Lorg/apache/jena/sparql/algebra/Table;
       4: astore_2
       5: aload_0
       6: getfield      #2                  // Field acc:Ljava/util/Set;
       9: aload_2
      10: invokeinterface #15,  1           // InterfaceMethod org/apache/jena/sparql/algebra/Table.getVars:()Ljava/util/List;
      15: invokeinterface #16,  2           // InterfaceMethod java/util/Set.addAll:(Ljava/util/Collection;)Z
      20: pop
      21: return

  public void visit(org.apache.jena.sparql.algebra.op.OpProject);
    Code:
       0: aload_0
       1: getfield      #3                  // Field visibleOnly:Z
       4: ifeq          16
       7: aload_0
       8: getfield      #2                  // Field acc:Ljava/util/Set;
      11: invokeinterface #17,  1           // InterfaceMethod java/util/Set.clear:()V
      16: aload_0
      17: getfield      #2                  // Field acc:Ljava/util/Set;
      20: aload_1
      21: invokevirtual #18                 // Method org/apache/jena/sparql/algebra/op/OpProject.getVars:()Ljava/util/List;
      24: invokeinterface #16,  2           // InterfaceMethod java/util/Set.addAll:(Ljava/util/Collection;)Z
      29: pop
      30: return

  public void visit(org.apache.jena.sparql.algebra.op.OpAssign);
    Code:
       0: aload_0
       1: getfield      #2                  // Field acc:Ljava/util/Set;
       4: aload_1
       5: invokevirtual #19                 // Method org/apache/jena/sparql/algebra/op/OpAssign.getVarExprList:()Lorg/apache/jena/sparql/core/VarExprList;
       8: invokevirtual #20                 // Method org/apache/jena/sparql/core/VarExprList.getVars:()Ljava/util/List;
      11: invokeinterface #16,  2           // InterfaceMethod java/util/Set.addAll:(Ljava/util/Collection;)Z
      16: pop
      17: return

  public void visit(org.apache.jena.sparql.algebra.op.OpExtend);
    Code:
       0: aload_0
       1: getfield      #2                  // Field acc:Ljava/util/Set;
       4: aload_1
       5: invokevirtual #21                 // Method org/apache/jena/sparql/algebra/op/OpExtend.getVarExprList:()Lorg/apache/jena/sparql/core/VarExprList;
       8: invokevirtual #20                 // Method org/apache/jena/sparql/core/VarExprList.getVars:()Ljava/util/List;
      11: invokeinterface #16,  2           // InterfaceMethod java/util/Set.addAll:(Ljava/util/Collection;)Z
      16: pop
      17: return

  public void visit(org.apache.jena.sparql.algebra.op.OpPropFunc);
    Code:
       0: aload_0
       1: getfield      #2                  // Field acc:Ljava/util/Set;
       4: aload_1
       5: invokevirtual #22                 // Method org/apache/jena/sparql/algebra/op/OpPropFunc.getSubjectArgs:()Lorg/apache/jena/sparql/pfunction/PropFuncArg;
       8: invokestatic  #23                 // Method org/apache/jena/sparql/pfunction/PropFuncArg.addVars:(Ljava/util/Collection;Lorg/apache/jena/sparql/pfunction/PropFuncArg;)V
      11: aload_0
      12: getfield      #2                  // Field acc:Ljava/util/Set;
      15: aload_1
      16: invokevirtual #24                 // Method org/apache/jena/sparql/algebra/op/OpPropFunc.getObjectArgs:()Lorg/apache/jena/sparql/pfunction/PropFuncArg;
      19: invokestatic  #23                 // Method org/apache/jena/sparql/pfunction/PropFuncArg.addVars:(Ljava/util/Collection;Lorg/apache/jena/sparql/pfunction/PropFuncArg;)V
      22: return

  public void visit(org.apache.jena.sparql.algebra.op.OpProcedure);
    Code:
       0: aload_0
       1: getfield      #2                  // Field acc:Ljava/util/Set;
       4: aload_1
       5: invokevirtual #25                 // Method org/apache/jena/sparql/algebra/op/OpProcedure.getArgs:()Lorg/apache/jena/sparql/expr/ExprList;
       8: invokestatic  #26                 // Method org/apache/jena/sparql/expr/ExprVars.varsMentioned:(Ljava/util/Collection;Lorg/apache/jena/sparql/expr/ExprList;)V
      11: return
}
