Compiled from "TransformCopy.java"
public class org.apache.jena.sparql.algebra.TransformCopy implements org.apache.jena.sparql.algebra.Transform {
  public static final boolean COPY_ALWAYS;

  public static final boolean COPY_ONLY_ON_CHANGE;

  private boolean alwaysCopy;

  public org.apache.jena.sparql.algebra.TransformCopy();
    Code:
       0: aload_0
       1: iconst_0
       2: invokespecial #2                  // Method "<init>":(Z)V
       5: return

  public org.apache.jena.sparql.algebra.TransformCopy(boolean);
    Code:
       0: aload_0
       1: invokespecial #3                  // Method java/lang/Object."<init>":()V
       4: aload_0
       5: iconst_0
       6: putfield      #4                  // Field alwaysCopy:Z
       9: aload_0
      10: iload_1
      11: putfield      #4                  // Field alwaysCopy:Z
      14: return

  public org.apache.jena.sparql.algebra.Op transform(org.apache.jena.sparql.algebra.op.OpTable);
    Code:
       0: aload_0
       1: aload_1
       2: invokespecial #5                  // Method xform:(Lorg/apache/jena/sparql/algebra/op/Op0;)Lorg/apache/jena/sparql/algebra/Op;
       5: areturn

  public org.apache.jena.sparql.algebra.Op transform(org.apache.jena.sparql.algebra.op.OpBGP);
    Code:
       0: aload_0
       1: aload_1
       2: invokespecial #5                  // Method xform:(Lorg/apache/jena/sparql/algebra/op/Op0;)Lorg/apache/jena/sparql/algebra/Op;
       5: areturn

  public org.apache.jena.sparql.algebra.Op transform(org.apache.jena.sparql.algebra.op.OpQuadPattern);
    Code:
       0: aload_0
       1: aload_1
       2: invokespecial #5                  // Method xform:(Lorg/apache/jena/sparql/algebra/op/Op0;)Lorg/apache/jena/sparql/algebra/Op;
       5: areturn

  public org.apache.jena.sparql.algebra.Op transform(org.apache.jena.sparql.algebra.op.OpQuadBlock);
    Code:
       0: aload_0
       1: aload_1
       2: invokespecial #5                  // Method xform:(Lorg/apache/jena/sparql/algebra/op/Op0;)Lorg/apache/jena/sparql/algebra/Op;
       5: areturn

  public org.apache.jena.sparql.algebra.Op transform(org.apache.jena.sparql.algebra.op.OpTriple);
    Code:
       0: aload_0
       1: aload_1
       2: invokespecial #5                  // Method xform:(Lorg/apache/jena/sparql/algebra/op/Op0;)Lorg/apache/jena/sparql/algebra/Op;
       5: areturn

  public org.apache.jena.sparql.algebra.Op transform(org.apache.jena.sparql.algebra.op.OpQuad);
    Code:
       0: aload_0
       1: aload_1
       2: invokespecial #5                  // Method xform:(Lorg/apache/jena/sparql/algebra/op/Op0;)Lorg/apache/jena/sparql/algebra/Op;
       5: areturn

  public org.apache.jena.sparql.algebra.Op transform(org.apache.jena.sparql.algebra.op.OpPath);
    Code:
       0: aload_0
       1: aload_1
       2: invokespecial #5                  // Method xform:(Lorg/apache/jena/sparql/algebra/op/Op0;)Lorg/apache/jena/sparql/algebra/Op;
       5: areturn

  public org.apache.jena.sparql.algebra.Op transform(org.apache.jena.sparql.algebra.op.OpProcedure, org.apache.jena.sparql.algebra.Op);
    Code:
       0: aload_0
       1: aload_1
       2: aload_2
       3: invokespecial #6                  // Method xform:(Lorg/apache/jena/sparql/algebra/op/Op1;Lorg/apache/jena/sparql/algebra/Op;)Lorg/apache/jena/sparql/algebra/Op;
       6: areturn

  public org.apache.jena.sparql.algebra.Op transform(org.apache.jena.sparql.algebra.op.OpPropFunc, org.apache.jena.sparql.algebra.Op);
    Code:
       0: aload_0
       1: aload_1
       2: aload_2
       3: invokespecial #6                  // Method xform:(Lorg/apache/jena/sparql/algebra/op/Op1;Lorg/apache/jena/sparql/algebra/Op;)Lorg/apache/jena/sparql/algebra/Op;
       6: areturn

  public org.apache.jena.sparql.algebra.Op transform(org.apache.jena.sparql.algebra.op.OpDatasetNames);
    Code:
       0: aload_0
       1: aload_1
       2: invokespecial #5                  // Method xform:(Lorg/apache/jena/sparql/algebra/op/Op0;)Lorg/apache/jena/sparql/algebra/Op;
       5: areturn

  public org.apache.jena.sparql.algebra.Op transform(org.apache.jena.sparql.algebra.op.OpFilter, org.apache.jena.sparql.algebra.Op);
    Code:
       0: aload_0
       1: aload_1
       2: aload_2
       3: invokespecial #6                  // Method xform:(Lorg/apache/jena/sparql/algebra/op/Op1;Lorg/apache/jena/sparql/algebra/Op;)Lorg/apache/jena/sparql/algebra/Op;
       6: areturn

  public org.apache.jena.sparql.algebra.Op transform(org.apache.jena.sparql.algebra.op.OpGraph, org.apache.jena.sparql.algebra.Op);
    Code:
       0: aload_0
       1: aload_1
       2: aload_2
       3: invokespecial #6                  // Method xform:(Lorg/apache/jena/sparql/algebra/op/Op1;Lorg/apache/jena/sparql/algebra/Op;)Lorg/apache/jena/sparql/algebra/Op;
       6: areturn

  public org.apache.jena.sparql.algebra.Op transform(org.apache.jena.sparql.algebra.op.OpService, org.apache.jena.sparql.algebra.Op);
    Code:
       0: aload_0
       1: aload_1
       2: aload_2
       3: invokespecial #6                  // Method xform:(Lorg/apache/jena/sparql/algebra/op/Op1;Lorg/apache/jena/sparql/algebra/Op;)Lorg/apache/jena/sparql/algebra/Op;
       6: areturn

  public org.apache.jena.sparql.algebra.Op transform(org.apache.jena.sparql.algebra.op.OpAssign, org.apache.jena.sparql.algebra.Op);
    Code:
       0: aload_0
       1: aload_1
       2: aload_2
       3: invokespecial #6                  // Method xform:(Lorg/apache/jena/sparql/algebra/op/Op1;Lorg/apache/jena/sparql/algebra/Op;)Lorg/apache/jena/sparql/algebra/Op;
       6: areturn

  public org.apache.jena.sparql.algebra.Op transform(org.apache.jena.sparql.algebra.op.OpExtend, org.apache.jena.sparql.algebra.Op);
    Code:
       0: aload_0
       1: aload_1
       2: aload_2
       3: invokespecial #6                  // Method xform:(Lorg/apache/jena/sparql/algebra/op/Op1;Lorg/apache/jena/sparql/algebra/Op;)Lorg/apache/jena/sparql/algebra/Op;
       6: areturn

  public org.apache.jena.sparql.algebra.Op transform(org.apache.jena.sparql.algebra.op.OpJoin, org.apache.jena.sparql.algebra.Op, org.apache.jena.sparql.algebra.Op);
    Code:
       0: aload_0
       1: aload_1
       2: aload_2
       3: aload_3
       4: invokespecial #7                  // Method xform:(Lorg/apache/jena/sparql/algebra/op/Op2;Lorg/apache/jena/sparql/algebra/Op;Lorg/apache/jena/sparql/algebra/Op;)Lorg/apache/jena/sparql/algebra/Op;
       7: areturn

  public org.apache.jena.sparql.algebra.Op transform(org.apache.jena.sparql.algebra.op.OpLeftJoin, org.apache.jena.sparql.algebra.Op, org.apache.jena.sparql.algebra.Op);
    Code:
       0: aload_0
       1: aload_1
       2: aload_2
       3: aload_3
       4: invokespecial #7                  // Method xform:(Lorg/apache/jena/sparql/algebra/op/Op2;Lorg/apache/jena/sparql/algebra/Op;Lorg/apache/jena/sparql/algebra/Op;)Lorg/apache/jena/sparql/algebra/Op;
       7: areturn

  public org.apache.jena.sparql.algebra.Op transform(org.apache.jena.sparql.algebra.op.OpDiff, org.apache.jena.sparql.algebra.Op, org.apache.jena.sparql.algebra.Op);
    Code:
       0: aload_0
       1: aload_1
       2: aload_2
       3: aload_3
       4: invokespecial #7                  // Method xform:(Lorg/apache/jena/sparql/algebra/op/Op2;Lorg/apache/jena/sparql/algebra/Op;Lorg/apache/jena/sparql/algebra/Op;)Lorg/apache/jena/sparql/algebra/Op;
       7: areturn

  public org.apache.jena.sparql.algebra.Op transform(org.apache.jena.sparql.algebra.op.OpMinus, org.apache.jena.sparql.algebra.Op, org.apache.jena.sparql.algebra.Op);
    Code:
       0: aload_0
       1: aload_1
       2: aload_2
       3: aload_3
       4: invokespecial #7                  // Method xform:(Lorg/apache/jena/sparql/algebra/op/Op2;Lorg/apache/jena/sparql/algebra/Op;Lorg/apache/jena/sparql/algebra/Op;)Lorg/apache/jena/sparql/algebra/Op;
       7: areturn

  public org.apache.jena.sparql.algebra.Op transform(org.apache.jena.sparql.algebra.op.OpUnion, org.apache.jena.sparql.algebra.Op, org.apache.jena.sparql.algebra.Op);
    Code:
       0: aload_0
       1: aload_1
       2: aload_2
       3: aload_3
       4: invokespecial #7                  // Method xform:(Lorg/apache/jena/sparql/algebra/op/Op2;Lorg/apache/jena/sparql/algebra/Op;Lorg/apache/jena/sparql/algebra/Op;)Lorg/apache/jena/sparql/algebra/Op;
       7: areturn

  public org.apache.jena.sparql.algebra.Op transform(org.apache.jena.sparql.algebra.op.OpConditional, org.apache.jena.sparql.algebra.Op, org.apache.jena.sparql.algebra.Op);
    Code:
       0: aload_0
       1: aload_1
       2: aload_2
       3: aload_3
       4: invokespecial #7                  // Method xform:(Lorg/apache/jena/sparql/algebra/op/Op2;Lorg/apache/jena/sparql/algebra/Op;Lorg/apache/jena/sparql/algebra/Op;)Lorg/apache/jena/sparql/algebra/Op;
       7: areturn

  public org.apache.jena.sparql.algebra.Op transform(org.apache.jena.sparql.algebra.op.OpSequence, java.util.List<org.apache.jena.sparql.algebra.Op>);
    Code:
       0: aload_0
       1: aload_1
       2: aload_2
       3: invokespecial #8                  // Method xform:(Lorg/apache/jena/sparql/algebra/op/OpN;Ljava/util/List;)Lorg/apache/jena/sparql/algebra/Op;
       6: areturn

  public org.apache.jena.sparql.algebra.Op transform(org.apache.jena.sparql.algebra.op.OpDisjunction, java.util.List<org.apache.jena.sparql.algebra.Op>);
    Code:
       0: aload_0
       1: aload_1
       2: aload_2
       3: invokespecial #8                  // Method xform:(Lorg/apache/jena/sparql/algebra/op/OpN;Ljava/util/List;)Lorg/apache/jena/sparql/algebra/Op;
       6: areturn

  public org.apache.jena.sparql.algebra.Op transform(org.apache.jena.sparql.algebra.op.OpExt);
    Code:
       0: aload_0
       1: aload_1
       2: invokespecial #9                  // Method xform:(Lorg/apache/jena/sparql/algebra/op/OpExt;)Lorg/apache/jena/sparql/algebra/Op;
       5: areturn

  public org.apache.jena.sparql.algebra.Op transform(org.apache.jena.sparql.algebra.op.OpNull);
    Code:
       0: aload_1
       1: invokevirtual #10                 // Method org/apache/jena/sparql/algebra/op/OpNull.copy:()Lorg/apache/jena/sparql/algebra/op/Op0;
       4: areturn

  public org.apache.jena.sparql.algebra.Op transform(org.apache.jena.sparql.algebra.op.OpLabel, org.apache.jena.sparql.algebra.Op);
    Code:
       0: aload_0
       1: aload_1
       2: aload_2
       3: invokespecial #6                  // Method xform:(Lorg/apache/jena/sparql/algebra/op/Op1;Lorg/apache/jena/sparql/algebra/Op;)Lorg/apache/jena/sparql/algebra/Op;
       6: areturn

  public org.apache.jena.sparql.algebra.Op transform(org.apache.jena.sparql.algebra.op.OpList, org.apache.jena.sparql.algebra.Op);
    Code:
       0: aload_0
       1: aload_1
       2: aload_2
       3: invokespecial #6                  // Method xform:(Lorg/apache/jena/sparql/algebra/op/Op1;Lorg/apache/jena/sparql/algebra/Op;)Lorg/apache/jena/sparql/algebra/Op;
       6: areturn

  public org.apache.jena.sparql.algebra.Op transform(org.apache.jena.sparql.algebra.op.OpOrder, org.apache.jena.sparql.algebra.Op);
    Code:
       0: aload_0
       1: aload_1
       2: aload_2
       3: invokespecial #6                  // Method xform:(Lorg/apache/jena/sparql/algebra/op/Op1;Lorg/apache/jena/sparql/algebra/Op;)Lorg/apache/jena/sparql/algebra/Op;
       6: areturn

  public org.apache.jena.sparql.algebra.Op transform(org.apache.jena.sparql.algebra.op.OpTopN, org.apache.jena.sparql.algebra.Op);
    Code:
       0: aload_0
       1: aload_1
       2: aload_2
       3: invokespecial #6                  // Method xform:(Lorg/apache/jena/sparql/algebra/op/Op1;Lorg/apache/jena/sparql/algebra/Op;)Lorg/apache/jena/sparql/algebra/Op;
       6: areturn

  public org.apache.jena.sparql.algebra.Op transform(org.apache.jena.sparql.algebra.op.OpProject, org.apache.jena.sparql.algebra.Op);
    Code:
       0: aload_0
       1: aload_1
       2: aload_2
       3: invokespecial #6                  // Method xform:(Lorg/apache/jena/sparql/algebra/op/Op1;Lorg/apache/jena/sparql/algebra/Op;)Lorg/apache/jena/sparql/algebra/Op;
       6: areturn

  public org.apache.jena.sparql.algebra.Op transform(org.apache.jena.sparql.algebra.op.OpDistinct, org.apache.jena.sparql.algebra.Op);
    Code:
       0: aload_0
       1: aload_1
       2: aload_2
       3: invokespecial #6                  // Method xform:(Lorg/apache/jena/sparql/algebra/op/Op1;Lorg/apache/jena/sparql/algebra/Op;)Lorg/apache/jena/sparql/algebra/Op;
       6: areturn

  public org.apache.jena.sparql.algebra.Op transform(org.apache.jena.sparql.algebra.op.OpReduced, org.apache.jena.sparql.algebra.Op);
    Code:
       0: aload_0
       1: aload_1
       2: aload_2
       3: invokespecial #6                  // Method xform:(Lorg/apache/jena/sparql/algebra/op/Op1;Lorg/apache/jena/sparql/algebra/Op;)Lorg/apache/jena/sparql/algebra/Op;
       6: areturn

  public org.apache.jena.sparql.algebra.Op transform(org.apache.jena.sparql.algebra.op.OpSlice, org.apache.jena.sparql.algebra.Op);
    Code:
       0: aload_0
       1: aload_1
       2: aload_2
       3: invokespecial #6                  // Method xform:(Lorg/apache/jena/sparql/algebra/op/Op1;Lorg/apache/jena/sparql/algebra/Op;)Lorg/apache/jena/sparql/algebra/Op;
       6: areturn

  public org.apache.jena.sparql.algebra.Op transform(org.apache.jena.sparql.algebra.op.OpGroup, org.apache.jena.sparql.algebra.Op);
    Code:
       0: aload_0
       1: aload_1
       2: aload_2
       3: invokespecial #6                  // Method xform:(Lorg/apache/jena/sparql/algebra/op/Op1;Lorg/apache/jena/sparql/algebra/Op;)Lorg/apache/jena/sparql/algebra/Op;
       6: areturn

  private org.apache.jena.sparql.algebra.Op xform(org.apache.jena.sparql.algebra.op.Op0);
    Code:
       0: aload_0
       1: getfield      #4                  // Field alwaysCopy:Z
       4: ifne          9
       7: aload_1
       8: areturn
       9: aload_1
      10: invokevirtual #11                 // Method org/apache/jena/sparql/algebra/op/Op0.copy:()Lorg/apache/jena/sparql/algebra/op/Op0;
      13: areturn

  private org.apache.jena.sparql.algebra.Op xform(org.apache.jena.sparql.algebra.op.Op1, org.apache.jena.sparql.algebra.Op);
    Code:
       0: aload_0
       1: getfield      #4                  // Field alwaysCopy:Z
       4: ifne          17
       7: aload_1
       8: invokevirtual #12                 // Method org/apache/jena/sparql/algebra/op/Op1.getSubOp:()Lorg/apache/jena/sparql/algebra/Op;
      11: aload_2
      12: if_acmpne     17
      15: aload_1
      16: areturn
      17: aload_1
      18: aload_2
      19: invokevirtual #13                 // Method org/apache/jena/sparql/algebra/op/Op1.copy:(Lorg/apache/jena/sparql/algebra/Op;)Lorg/apache/jena/sparql/algebra/op/Op1;
      22: areturn

  private org.apache.jena.sparql.algebra.Op xform(org.apache.jena.sparql.algebra.op.Op2, org.apache.jena.sparql.algebra.Op, org.apache.jena.sparql.algebra.Op);
    Code:
       0: aload_0
       1: getfield      #4                  // Field alwaysCopy:Z
       4: ifne          25
       7: aload_1
       8: invokevirtual #14                 // Method org/apache/jena/sparql/algebra/op/Op2.getLeft:()Lorg/apache/jena/sparql/algebra/Op;
      11: aload_2
      12: if_acmpne     25
      15: aload_1
      16: invokevirtual #15                 // Method org/apache/jena/sparql/algebra/op/Op2.getRight:()Lorg/apache/jena/sparql/algebra/Op;
      19: aload_3
      20: if_acmpne     25
      23: aload_1
      24: areturn
      25: aload_1
      26: aload_2
      27: aload_3
      28: invokevirtual #16                 // Method org/apache/jena/sparql/algebra/op/Op2.copy:(Lorg/apache/jena/sparql/algebra/Op;Lorg/apache/jena/sparql/algebra/Op;)Lorg/apache/jena/sparql/algebra/op/Op2;
      31: areturn

  private org.apache.jena.sparql.algebra.Op xform(org.apache.jena.sparql.algebra.op.OpN, java.util.List<org.apache.jena.sparql.algebra.Op>);
    Code:
       0: aload_0
       1: getfield      #4                  // Field alwaysCopy:Z
       4: ifne          21
       7: aload_0
       8: aload_2
       9: aload_1
      10: invokevirtual #17                 // Method org/apache/jena/sparql/algebra/op/OpN.getElements:()Ljava/util/List;
      13: invokespecial #18                 // Method equals1:(Ljava/util/List;Ljava/util/List;)Z
      16: ifeq          21
      19: aload_1
      20: areturn
      21: aload_1
      22: aload_2
      23: invokevirtual #19                 // Method org/apache/jena/sparql/algebra/op/OpN.copy:(Ljava/util/List;)Lorg/apache/jena/sparql/algebra/op/OpN;
      26: areturn

  private org.apache.jena.sparql.algebra.Op xform(org.apache.jena.sparql.algebra.op.OpExt);
    Code:
       0: aload_1
       1: aload_0
       2: invokevirtual #20                 // Method org/apache/jena/sparql/algebra/op/OpExt.apply:(Lorg/apache/jena/sparql/algebra/Transform;)Lorg/apache/jena/sparql/algebra/Op;
       5: areturn
       6: astore_2
       7: aload_1
       8: areturn
    Exception table:
       from    to  target type
           0     5     6   Class java/lang/Exception

  private boolean equals1(java.util.List<org.apache.jena.sparql.algebra.Op>, java.util.List<org.apache.jena.sparql.algebra.Op>);
    Code:
       0: aload_1
       1: invokeinterface #22,  1           // InterfaceMethod java/util/List.size:()I
       6: aload_2
       7: invokeinterface #22,  1           // InterfaceMethod java/util/List.size:()I
      12: if_icmpeq     17
      15: iconst_0
      16: ireturn
      17: iconst_0
      18: istore_3
      19: iload_3
      20: aload_1
      21: invokeinterface #22,  1           // InterfaceMethod java/util/List.size:()I
      26: if_icmpge     54
      29: aload_1
      30: iload_3
      31: invokeinterface #23,  2           // InterfaceMethod java/util/List.get:(I)Ljava/lang/Object;
      36: aload_2
      37: iload_3
      38: invokeinterface #23,  2           // InterfaceMethod java/util/List.get:(I)Ljava/lang/Object;
      43: if_acmpeq     48
      46: iconst_0
      47: ireturn
      48: iinc          3, 1
      51: goto          19
      54: iconst_1
      55: ireturn
}
