Compiled from "AbstractConstraintMetaData.java"
class org.hibernate.validator.internal.metadata.aggregated.AbstractConstraintMetaData$ContainerElementMetaDataTree {
  private final java.util.Map<java.lang.reflect.TypeVariable<?>, org.hibernate.validator.internal.metadata.aggregated.AbstractConstraintMetaData$ContainerElementMetaDataTree> nodes;

  private java.lang.reflect.Type elementType;

  private java.lang.Class<?> containerClass;

  private final java.util.Set<org.hibernate.validator.internal.metadata.core.MetaConstraint<?>> constraints;

  private boolean cascading;

  private java.util.Set<javax.validation.metadata.GroupConversionDescriptor> groupConversionDescriptors;

  private org.hibernate.validator.internal.metadata.aggregated.AbstractConstraintMetaData$ContainerElementMetaDataTree();
    Code:
       0: aload_0
       1: invokespecial #8                  // Method java/lang/Object."<init>":()V
       4: aload_0
       5: new           #9                  // class java/util/HashMap
       8: dup
       9: invokespecial #10                 // Method java/util/HashMap."<init>":()V
      12: putfield      #6                  // Field nodes:Ljava/util/Map;
      15: aload_0
      16: aconst_null
      17: putfield      #5                  // Field elementType:Ljava/lang/reflect/Type;
      20: aload_0
      21: new           #11                 // class java/util/HashSet
      24: dup
      25: invokespecial #12                 // Method java/util/HashSet."<init>":()V
      28: putfield      #3                  // Field constraints:Ljava/util/Set;
      31: aload_0
      32: iconst_0
      33: putfield      #2                  // Field cascading:Z
      36: aload_0
      37: new           #11                 // class java/util/HashSet
      40: dup
      41: invokespecial #12                 // Method java/util/HashSet."<init>":()V
      44: putfield      #1                  // Field groupConversionDescriptors:Ljava/util/Set;
      47: return

  private static org.hibernate.validator.internal.metadata.aggregated.AbstractConstraintMetaData$ContainerElementMetaDataTree of(org.hibernate.validator.internal.metadata.aggregated.CascadingMetaData, java.util.Set<org.hibernate.validator.internal.metadata.core.MetaConstraint<?>>);
    Code:
       0: new           #13                 // class org/hibernate/validator/internal/metadata/aggregated/AbstractConstraintMetaData$ContainerElementMetaDataTree
       3: dup
       4: invokespecial #14                 // Method "<init>":()V
       7: astore_2
       8: aload_1
       9: invokeinterface #15,  1           // InterfaceMethod java/util/Set.iterator:()Ljava/util/Iterator;
      14: astore_3
      15: aload_3
      16: invokeinterface #16,  1           // InterfaceMethod java/util/Iterator.hasNext:()Z
      21: ifeq          105
      24: aload_3
      25: invokeinterface #17,  1           // InterfaceMethod java/util/Iterator.next:()Ljava/lang/Object;
      30: checkcast     #18                 // class org/hibernate/validator/internal/metadata/core/MetaConstraint
      33: astore        4
      35: aload         4
      37: invokevirtual #19                 // Method org/hibernate/validator/internal/metadata/core/MetaConstraint.getLocation:()Lorg/hibernate/validator/internal/metadata/location/ConstraintLocation;
      40: astore        5
      42: new           #20                 // class java/util/ArrayList
      45: dup
      46: invokespecial #21                 // Method java/util/ArrayList."<init>":()V
      49: astore        6
      51: aload         5
      53: instanceof    #22                 // class org/hibernate/validator/internal/metadata/location/TypeArgumentConstraintLocation
      56: ifeq          89
      59: aload         5
      61: checkcast     #22                 // class org/hibernate/validator/internal/metadata/location/TypeArgumentConstraintLocation
      64: astore        7
      66: aload         6
      68: aload         7
      70: invokevirtual #23                 // Method org/hibernate/validator/internal/metadata/location/TypeArgumentConstraintLocation.getTypeParameter:()Ljava/lang/reflect/TypeVariable;
      73: invokeinterface #24,  2           // InterfaceMethod java/util/List.add:(Ljava/lang/Object;)Z
      78: pop
      79: aload         7
      81: invokevirtual #25                 // Method org/hibernate/validator/internal/metadata/location/TypeArgumentConstraintLocation.getDelegate:()Lorg/hibernate/validator/internal/metadata/location/ConstraintLocation;
      84: astore        5
      86: goto          51
      89: aload         6
      91: invokestatic  #26                 // Method java/util/Collections.reverse:(Ljava/util/List;)V
      94: aload_2
      95: aload         6
      97: aload         4
      99: invokespecial #27                 // Method addConstraint:(Ljava/util/List;Lorg/hibernate/validator/internal/metadata/core/MetaConstraint;)V
     102: goto          15
     105: aload_0
     106: ifnull        149
     109: aload_0
     110: invokeinterface #28,  1           // InterfaceMethod org/hibernate/validator/internal/metadata/aggregated/CascadingMetaData.isContainer:()Z
     115: ifeq          149
     118: aload_0
     119: invokeinterface #29,  1           // InterfaceMethod org/hibernate/validator/internal/metadata/aggregated/CascadingMetaData.isMarkedForCascadingOnAnnotatedObjectOrContainerElements:()Z
     124: ifeq          149
     127: aload_2
     128: new           #20                 // class java/util/ArrayList
     131: dup
     132: invokespecial #21                 // Method java/util/ArrayList."<init>":()V
     135: aload_0
     136: ldc           #30                 // class org/hibernate/validator/internal/metadata/aggregated/ContainerCascadingMetaData
     138: invokeinterface #31,  2           // InterfaceMethod org/hibernate/validator/internal/metadata/aggregated/CascadingMetaData.as:(Ljava/lang/Class;)Lorg/hibernate/validator/internal/metadata/aggregated/CascadingMetaData;
     143: checkcast     #30                 // class org/hibernate/validator/internal/metadata/aggregated/ContainerCascadingMetaData
     146: invokespecial #32                 // Method addCascadingMetaData:(Ljava/util/List;Lorg/hibernate/validator/internal/metadata/aggregated/ContainerCascadingMetaData;)V
     149: aload_2
     150: areturn

  private void addConstraint(java.util.List<java.lang.reflect.TypeVariable<?>>, org.hibernate.validator.internal.metadata.core.MetaConstraint<?>);
    Code:
       0: aload_0
       1: astore_3
       2: aload_1
       3: invokeinterface #33,  1           // InterfaceMethod java/util/List.iterator:()Ljava/util/Iterator;
       8: astore        4
      10: aload         4
      12: invokeinterface #16,  1           // InterfaceMethod java/util/Iterator.hasNext:()Z
      17: ifeq          55
      20: aload         4
      22: invokeinterface #17,  1           // InterfaceMethod java/util/Iterator.next:()Ljava/lang/Object;
      27: checkcast     #34                 // class java/lang/reflect/TypeVariable
      30: astore        5
      32: aload_3
      33: getfield      #6                  // Field nodes:Ljava/util/Map;
      36: aload         5
      38: invokedynamic #35,  0             // InvokeDynamic #0:apply:()Ljava/util/function/Function;
      43: invokeinterface #36,  3           // InterfaceMethod java/util/Map.computeIfAbsent:(Ljava/lang/Object;Ljava/util/function/Function;)Ljava/lang/Object;
      48: checkcast     #13                 // class org/hibernate/validator/internal/metadata/aggregated/AbstractConstraintMetaData$ContainerElementMetaDataTree
      51: astore_3
      52: goto          10
      55: aload_2
      56: invokevirtual #19                 // Method org/hibernate/validator/internal/metadata/core/MetaConstraint.getLocation:()Lorg/hibernate/validator/internal/metadata/location/ConstraintLocation;
      59: checkcast     #22                 // class org/hibernate/validator/internal/metadata/location/TypeArgumentConstraintLocation
      62: astore        4
      64: aload_3
      65: aload         4
      67: invokevirtual #37                 // Method org/hibernate/validator/internal/metadata/location/TypeArgumentConstraintLocation.getTypeForValidatorResolution:()Ljava/lang/reflect/Type;
      70: putfield      #5                  // Field elementType:Ljava/lang/reflect/Type;
      73: aload_3
      74: aload_2
      75: invokevirtual #19                 // Method org/hibernate/validator/internal/metadata/core/MetaConstraint.getLocation:()Lorg/hibernate/validator/internal/metadata/location/ConstraintLocation;
      78: checkcast     #22                 // class org/hibernate/validator/internal/metadata/location/TypeArgumentConstraintLocation
      81: invokevirtual #38                 // Method org/hibernate/validator/internal/metadata/location/TypeArgumentConstraintLocation.getContainerClass:()Ljava/lang/Class;
      84: putfield      #4                  // Field containerClass:Ljava/lang/Class;
      87: aload_3
      88: getfield      #3                  // Field constraints:Ljava/util/Set;
      91: aload_2
      92: invokeinterface #39,  2           // InterfaceMethod java/util/Set.add:(Ljava/lang/Object;)Z
      97: pop
      98: return

  private void addCascadingMetaData(java.util.List<java.lang.reflect.TypeVariable<?>>, org.hibernate.validator.internal.metadata.aggregated.ContainerCascadingMetaData);
    Code:
       0: aload_2
       1: invokevirtual #40                 // Method org/hibernate/validator/internal/metadata/aggregated/ContainerCascadingMetaData.getContainerElementTypesCascadingMetaData:()Ljava/util/List;
       4: invokeinterface #33,  1           // InterfaceMethod java/util/List.iterator:()Ljava/util/Iterator;
       9: astore_3
      10: aload_3
      11: invokeinterface #16,  1           // InterfaceMethod java/util/Iterator.hasNext:()Z
      16: ifeq          179
      19: aload_3
      20: invokeinterface #17,  1           // InterfaceMethod java/util/Iterator.next:()Ljava/lang/Object;
      25: checkcast     #30                 // class org/hibernate/validator/internal/metadata/aggregated/ContainerCascadingMetaData
      28: astore        4
      30: new           #20                 // class java/util/ArrayList
      33: dup
      34: aload_1
      35: invokespecial #41                 // Method java/util/ArrayList."<init>":(Ljava/util/Collection;)V
      38: astore        5
      40: aload         5
      42: aload         4
      44: invokevirtual #42                 // Method org/hibernate/validator/internal/metadata/aggregated/ContainerCascadingMetaData.getTypeParameter:()Ljava/lang/reflect/TypeVariable;
      47: invokeinterface #24,  2           // InterfaceMethod java/util/List.add:(Ljava/lang/Object;)Z
      52: pop
      53: aload_0
      54: astore        6
      56: aload         5
      58: invokeinterface #33,  1           // InterfaceMethod java/util/List.iterator:()Ljava/util/Iterator;
      63: astore        7
      65: aload         7
      67: invokeinterface #16,  1           // InterfaceMethod java/util/Iterator.hasNext:()Z
      72: ifeq          112
      75: aload         7
      77: invokeinterface #17,  1           // InterfaceMethod java/util/Iterator.next:()Ljava/lang/Object;
      82: checkcast     #34                 // class java/lang/reflect/TypeVariable
      85: astore        8
      87: aload         6
      89: getfield      #6                  // Field nodes:Ljava/util/Map;
      92: aload         8
      94: invokedynamic #43,  0             // InvokeDynamic #1:apply:()Ljava/util/function/Function;
      99: invokeinterface #36,  3           // InterfaceMethod java/util/Map.computeIfAbsent:(Ljava/lang/Object;Ljava/util/function/Function;)Ljava/lang/Object;
     104: checkcast     #13                 // class org/hibernate/validator/internal/metadata/aggregated/AbstractConstraintMetaData$ContainerElementMetaDataTree
     107: astore        6
     109: goto          65
     112: aload         6
     114: aload         4
     116: invokevirtual #44                 // Method org/hibernate/validator/internal/metadata/aggregated/ContainerCascadingMetaData.getEnclosingType:()Ljava/lang/reflect/Type;
     119: aload         4
     121: invokevirtual #42                 // Method org/hibernate/validator/internal/metadata/aggregated/ContainerCascadingMetaData.getTypeParameter:()Ljava/lang/reflect/TypeVariable;
     124: invokestatic  #45                 // Method org/hibernate/validator/internal/util/TypeVariables.getContainerElementType:(Ljava/lang/reflect/Type;Ljava/lang/reflect/TypeVariable;)Ljava/lang/reflect/Type;
     127: putfield      #5                  // Field elementType:Ljava/lang/reflect/Type;
     130: aload         6
     132: aload         4
     134: invokevirtual #46                 // Method org/hibernate/validator/internal/metadata/aggregated/ContainerCascadingMetaData.getDeclaredContainerClass:()Ljava/lang/Class;
     137: putfield      #4                  // Field containerClass:Ljava/lang/Class;
     140: aload         6
     142: aload         4
     144: invokevirtual #47                 // Method org/hibernate/validator/internal/metadata/aggregated/ContainerCascadingMetaData.isCascading:()Z
     147: putfield      #2                  // Field cascading:Z
     150: aload         6
     152: aload         4
     154: invokevirtual #48                 // Method org/hibernate/validator/internal/metadata/aggregated/ContainerCascadingMetaData.getGroupConversionDescriptors:()Ljava/util/Set;
     157: putfield      #1                  // Field groupConversionDescriptors:Ljava/util/Set;
     160: aload         4
     162: invokevirtual #49                 // Method org/hibernate/validator/internal/metadata/aggregated/ContainerCascadingMetaData.isMarkedForCascadingOnAnnotatedObjectOrContainerElements:()Z
     165: ifeq          176
     168: aload_0
     169: aload         5
     171: aload         4
     173: invokespecial #32                 // Method addCascadingMetaData:(Ljava/util/List;Lorg/hibernate/validator/internal/metadata/aggregated/ContainerCascadingMetaData;)V
     176: goto          10
     179: return

  private static org.hibernate.validator.internal.metadata.aggregated.AbstractConstraintMetaData$ContainerElementMetaDataTree lambda$addCascadingMetaData$1(java.lang.reflect.TypeVariable);
    Code:
       0: new           #13                 // class org/hibernate/validator/internal/metadata/aggregated/AbstractConstraintMetaData$ContainerElementMetaDataTree
       3: dup
       4: invokespecial #14                 // Method "<init>":()V
       7: areturn

  private static org.hibernate.validator.internal.metadata.aggregated.AbstractConstraintMetaData$ContainerElementMetaDataTree lambda$addConstraint$0(java.lang.reflect.TypeVariable);
    Code:
       0: new           #13                 // class org/hibernate/validator/internal/metadata/aggregated/AbstractConstraintMetaData$ContainerElementMetaDataTree
       3: dup
       4: invokespecial #14                 // Method "<init>":()V
       7: areturn

  static org.hibernate.validator.internal.metadata.aggregated.AbstractConstraintMetaData$ContainerElementMetaDataTree access$000(org.hibernate.validator.internal.metadata.aggregated.CascadingMetaData, java.util.Set);
    Code:
       0: aload_0
       1: aload_1
       2: invokestatic  #7                  // Method of:(Lorg/hibernate/validator/internal/metadata/aggregated/CascadingMetaData;Ljava/util/Set;)Lorg/hibernate/validator/internal/metadata/aggregated/AbstractConstraintMetaData$ContainerElementMetaDataTree;
       5: areturn

  static java.util.Map access$100(org.hibernate.validator.internal.metadata.aggregated.AbstractConstraintMetaData$ContainerElementMetaDataTree);
    Code:
       0: aload_0
       1: getfield      #6                  // Field nodes:Ljava/util/Map;
       4: areturn

  static java.lang.reflect.Type access$200(org.hibernate.validator.internal.metadata.aggregated.AbstractConstraintMetaData$ContainerElementMetaDataTree);
    Code:
       0: aload_0
       1: getfield      #5                  // Field elementType:Ljava/lang/reflect/Type;
       4: areturn

  static java.lang.Class access$300(org.hibernate.validator.internal.metadata.aggregated.AbstractConstraintMetaData$ContainerElementMetaDataTree);
    Code:
       0: aload_0
       1: getfield      #4                  // Field containerClass:Ljava/lang/Class;
       4: areturn

  static java.util.Set access$400(org.hibernate.validator.internal.metadata.aggregated.AbstractConstraintMetaData$ContainerElementMetaDataTree);
    Code:
       0: aload_0
       1: getfield      #3                  // Field constraints:Ljava/util/Set;
       4: areturn

  static boolean access$500(org.hibernate.validator.internal.metadata.aggregated.AbstractConstraintMetaData$ContainerElementMetaDataTree);
    Code:
       0: aload_0
       1: getfield      #2                  // Field cascading:Z
       4: ireturn

  static java.util.Set access$600(org.hibernate.validator.internal.metadata.aggregated.AbstractConstraintMetaData$ContainerElementMetaDataTree);
    Code:
       0: aload_0
       1: getfield      #1                  // Field groupConversionDescriptors:Ljava/util/Set;
       4: areturn
}
