Compiled from "IdleConnectionEvictor.java"
class org.apache.http.impl.client.IdleConnectionEvictor$1 implements java.lang.Runnable {
  final org.apache.http.conn.HttpClientConnectionManager val$connectionManager;

  final org.apache.http.impl.client.IdleConnectionEvictor this$0;

  org.apache.http.impl.client.IdleConnectionEvictor$1(org.apache.http.impl.client.IdleConnectionEvictor, org.apache.http.conn.HttpClientConnectionManager);
    Code:
       0: aload_0
       1: aload_1
       2: putfield      #1                  // Field this$0:Lorg/apache/http/impl/client/IdleConnectionEvictor;
       5: aload_0
       6: aload_2
       7: putfield      #2                  // Field val$connectionManager:Lorg/apache/http/conn/HttpClientConnectionManager;
      10: aload_0
      11: invokespecial #3                  // Method java/lang/Object."<init>":()V
      14: return

  public void run();
    Code:
       0: invokestatic  #4                  // Method java/lang/Thread.currentThread:()Ljava/lang/Thread;
       3: invokevirtual #5                  // Method java/lang/Thread.isInterrupted:()Z
       6: ifne          62
       9: aload_0
      10: getfield      #1                  // Field this$0:Lorg/apache/http/impl/client/IdleConnectionEvictor;
      13: invokestatic  #6                  // Method org/apache/http/impl/client/IdleConnectionEvictor.access$000:(Lorg/apache/http/impl/client/IdleConnectionEvictor;)J
      16: invokestatic  #7                  // Method java/lang/Thread.sleep:(J)V
      19: aload_0
      20: getfield      #2                  // Field val$connectionManager:Lorg/apache/http/conn/HttpClientConnectionManager;
      23: invokeinterface #8,  1            // InterfaceMethod org/apache/http/conn/HttpClientConnectionManager.closeExpiredConnections:()V
      28: aload_0
      29: getfield      #1                  // Field this$0:Lorg/apache/http/impl/client/IdleConnectionEvictor;
      32: invokestatic  #9                  // Method org/apache/http/impl/client/IdleConnectionEvictor.access$100:(Lorg/apache/http/impl/client/IdleConnectionEvictor;)J
      35: lconst_0
      36: lcmp
      37: ifle          0
      40: aload_0
      41: getfield      #2                  // Field val$connectionManager:Lorg/apache/http/conn/HttpClientConnectionManager;
      44: aload_0
      45: getfield      #1                  // Field this$0:Lorg/apache/http/impl/client/IdleConnectionEvictor;
      48: invokestatic  #9                  // Method org/apache/http/impl/client/IdleConnectionEvictor.access$100:(Lorg/apache/http/impl/client/IdleConnectionEvictor;)J
      51: getstatic     #10                 // Field java/util/concurrent/TimeUnit.MILLISECONDS:Ljava/util/concurrent/TimeUnit;
      54: invokeinterface #11,  4           // InterfaceMethod org/apache/http/conn/HttpClientConnectionManager.closeIdleConnections:(JLjava/util/concurrent/TimeUnit;)V
      59: goto          0
      62: goto          75
      65: astore_1
      66: aload_0
      67: getfield      #1                  // Field this$0:Lorg/apache/http/impl/client/IdleConnectionEvictor;
      70: aload_1
      71: invokestatic  #13                 // Method org/apache/http/impl/client/IdleConnectionEvictor.access$202:(Lorg/apache/http/impl/client/IdleConnectionEvictor;Ljava/lang/Exception;)Ljava/lang/Exception;
      74: pop
      75: return
    Exception table:
       from    to  target type
           0    62    65   Class java/lang/Exception
}
