Compiled from "ClassNode.java"
public class org.jboss.resteasy.core.registry.ClassNode {
  protected java.lang.String segment;

  protected java.util.Map<java.lang.String, org.jboss.resteasy.core.registry.ClassNode> children;

  protected java.util.List<org.jboss.resteasy.core.registry.ClassExpression> targets;

  public org.jboss.resteasy.core.registry.ClassNode(java.lang.String);
    Code:
       0: aload_0
       1: invokespecial #1                  // Method java/lang/Object."<init>":()V
       4: aload_0
       5: new           #2                  // class java/util/HashMap
       8: dup
       9: invokespecial #3                  // Method java/util/HashMap."<init>":()V
      12: putfield      #4                  // Field children:Ljava/util/Map;
      15: aload_0
      16: new           #5                  // class java/util/ArrayList
      19: dup
      20: invokespecial #6                  // Method java/util/ArrayList."<init>":()V
      23: putfield      #7                  // Field targets:Ljava/util/List;
      26: aload_0
      27: aload_1
      28: putfield      #8                  // Field segment:Ljava/lang/String;
      31: return

  public org.jboss.resteasy.core.registry.RootNode match(org.jboss.resteasy.spi.HttpRequest, int);
    Code:
       0: aload_1
       1: invokeinterface #9,  1            // InterfaceMethod org/jboss/resteasy/spi/HttpRequest.getUri:()Lorg/jboss/resteasy/spi/ResteasyUriInfo;
       6: invokevirtual #10                 // Method org/jboss/resteasy/spi/ResteasyUriInfo.getMatchingPath:()Ljava/lang/String;
       9: astore_3
      10: iload_2
      11: aload_3
      12: invokevirtual #11                 // Method java/lang/String.length:()I
      15: if_icmpge     31
      18: aload_3
      19: iload_2
      20: invokevirtual #12                 // Method java/lang/String.charAt:(I)C
      23: bipush        47
      25: if_icmpne     31
      28: iinc          2, 1
      31: new           #5                  // class java/util/ArrayList
      34: dup
      35: invokespecial #6                  // Method java/util/ArrayList."<init>":()V
      38: astore        4
      40: aload_0
      41: aload_3
      42: iload_2
      43: aload         4
      45: invokevirtual #13                 // Method potentials:(Ljava/lang/String;ILjava/util/List;)V
      48: aload         4
      50: invokestatic  #14                 // Method java/util/Collections.sort:(Ljava/util/List;)V
      53: aload         4
      55: invokeinterface #15,  1           // InterfaceMethod java/util/List.iterator:()Ljava/util/Iterator;
      60: astore        5
      62: aload         5
      64: invokeinterface #16,  1           // InterfaceMethod java/util/Iterator.hasNext:()Z
      69: ifeq          180
      72: aload         5
      74: invokeinterface #17,  1           // InterfaceMethod java/util/Iterator.next:()Ljava/lang/Object;
      79: checkcast     #18                 // class org/jboss/resteasy/core/registry/ClassExpression
      82: astore        6
      84: aload         6
      86: invokevirtual #19                 // Method org/jboss/resteasy/core/registry/ClassExpression.getPattern:()Ljava/util/regex/Pattern;
      89: astore        7
      91: aload         7
      93: aload_3
      94: invokevirtual #20                 // Method java/util/regex/Pattern.matcher:(Ljava/lang/CharSequence;)Ljava/util/regex/Matcher;
      97: astore        8
      99: aload         8
     101: iload_2
     102: aload_3
     103: invokevirtual #11                 // Method java/lang/String.length:()I
     106: invokevirtual #21                 // Method java/util/regex/Matcher.region:(II)Ljava/util/regex/Matcher;
     109: pop
     110: aload         8
     112: invokevirtual #22                 // Method java/util/regex/Matcher.matches:()Z
     115: ifeq          177
     118: aload_1
     119: invokeinterface #9,  1            // InterfaceMethod org/jboss/resteasy/spi/HttpRequest.getUri:()Lorg/jboss/resteasy/spi/ResteasyUriInfo;
     124: astore        9
     126: aload         8
     128: aload         6
     130: invokevirtual #23                 // Method org/jboss/resteasy/core/registry/ClassExpression.getNumGroups:()I
     133: iconst_1
     134: iadd
     135: invokevirtual #24                 // Method java/util/regex/Matcher.start:(I)I
     138: istore        10
     140: iload         10
     142: iconst_m1
     143: if_icmpne     155
     146: aload         9
     148: aload_3
     149: invokevirtual #25                 // Method org/jboss/resteasy/spi/ResteasyUriInfo.pushMatchedURI:(Ljava/lang/String;)V
     152: goto          171
     155: aload_3
     156: iconst_0
     157: iload         10
     159: invokevirtual #26                 // Method java/lang/String.substring:(II)Ljava/lang/String;
     162: astore        11
     164: aload         9
     166: aload         11
     168: invokevirtual #25                 // Method org/jboss/resteasy/spi/ResteasyUriInfo.pushMatchedURI:(Ljava/lang/String;)V
     171: aload         6
     173: invokevirtual #27                 // Method org/jboss/resteasy/core/registry/ClassExpression.getRoot:()Lorg/jboss/resteasy/core/registry/RootNode;
     176: areturn
     177: goto          62
     180: new           #28                 // class javax/ws/rs/NotFoundException
     183: dup
     184: getstatic     #29                 // Field org/jboss/resteasy/resteasy_jaxrs/i18n/Messages.MESSAGES:Lorg/jboss/resteasy/resteasy_jaxrs/i18n/Messages;
     187: aload_1
     188: invokeinterface #9,  1            // InterfaceMethod org/jboss/resteasy/spi/HttpRequest.getUri:()Lorg/jboss/resteasy/spi/ResteasyUriInfo;
     193: invokevirtual #30                 // Method org/jboss/resteasy/spi/ResteasyUriInfo.getRequestUri:()Ljava/net/URI;
     196: invokeinterface #31,  2           // InterfaceMethod org/jboss/resteasy/resteasy_jaxrs/i18n/Messages.couldNotFindResourceForFullPath:(Ljava/net/URI;)Ljava/lang/String;
     201: invokespecial #32                 // Method javax/ws/rs/NotFoundException."<init>":(Ljava/lang/String;)V
     204: athrow

  public void potentials(java.lang.String, int, java.util.List<org.jboss.resteasy.core.registry.ClassExpression>);
    Code:
       0: iload_2
       1: aload_1
       2: invokevirtual #11                 // Method java/lang/String.length:()I
       5: if_icmpne     20
       8: aload_3
       9: aload_0
      10: getfield      #7                  // Field targets:Ljava/util/List;
      13: invokeinterface #33,  2           // InterfaceMethod java/util/List.addAll:(Ljava/util/Collection;)Z
      18: pop
      19: return
      20: iload_2
      21: aload_1
      22: invokevirtual #11                 // Method java/lang/String.length:()I
      25: if_icmpge     113
      28: aconst_null
      29: astore        4
      31: aload_1
      32: bipush        47
      34: iload_2
      35: invokevirtual #34                 // Method java/lang/String.indexOf:(II)I
      38: istore        5
      40: iload         5
      42: iconst_m1
      43: if_icmple     58
      46: aload_1
      47: iload_2
      48: iload         5
      50: invokevirtual #26                 // Method java/lang/String.substring:(II)Ljava/lang/String;
      53: astore        4
      55: goto          65
      58: aload_1
      59: iload_2
      60: invokevirtual #35                 // Method java/lang/String.substring:(I)Ljava/lang/String;
      63: astore        4
      65: aload_0
      66: getfield      #4                  // Field children:Ljava/util/Map;
      69: aload         4
      71: invokeinterface #36,  2           // InterfaceMethod java/util/Map.get:(Ljava/lang/Object;)Ljava/lang/Object;
      76: checkcast     #37                 // class org/jboss/resteasy/core/registry/ClassNode
      79: astore        6
      81: aload         6
      83: ifnull        113
      86: iload_2
      87: aload         4
      89: invokevirtual #11                 // Method java/lang/String.length:()I
      92: iadd
      93: istore        7
      95: iload         5
      97: iconst_m1
      98: if_icmple     104
     101: iinc          7, 1
     104: aload         6
     106: aload_1
     107: iload         7
     109: aload_3
     110: invokevirtual #13                 // Method potentials:(Ljava/lang/String;ILjava/util/List;)V
     113: aload_0
     114: getfield      #7                  // Field targets:Ljava/util/List;
     117: invokeinterface #15,  1           // InterfaceMethod java/util/List.iterator:()Ljava/util/Iterator;
     122: astore        4
     124: aload         4
     126: invokeinterface #16,  1           // InterfaceMethod java/util/Iterator.hasNext:()Z
     131: ifeq          158
     134: aload         4
     136: invokeinterface #17,  1           // InterfaceMethod java/util/Iterator.next:()Ljava/lang/Object;
     141: checkcast     #18                 // class org/jboss/resteasy/core/registry/ClassExpression
     144: astore        5
     146: aload_3
     147: aload         5
     149: invokeinterface #38,  2           // InterfaceMethod java/util/List.add:(Ljava/lang/Object;)Z
     154: pop
     155: goto          124
     158: return
}
