Compiled from "SegmentNode.java"
public class org.jboss.resteasy.core.registry.SegmentNode$Match {
  org.jboss.resteasy.core.registry.MethodExpression expression;

  java.util.regex.Matcher matcher;

  public org.jboss.resteasy.core.registry.SegmentNode$Match(org.jboss.resteasy.core.registry.MethodExpression, java.util.regex.Matcher);
    Code:
       0: aload_0
       1: invokespecial #1                  // Method java/lang/Object."<init>":()V
       4: aload_0
       5: aload_1
       6: putfield      #2                  // Field expression:Lorg/jboss/resteasy/core/registry/MethodExpression;
       9: aload_0
      10: aload_2
      11: putfield      #3                  // Field matcher:Ljava/util/regex/Matcher;
      14: return
}
