Compiled from "SegmentNode.java"
public class org.jboss.resteasy.core.registry.SegmentNode {
  public static final java.lang.String RESTEASY_CHOSEN_ACCEPT;

  public static final javax.ws.rs.core.MediaType[] WILDCARD_ARRAY;

  public static final java.util.List<javax.ws.rs.core.MediaType> DEFAULT_ACCEPTS;

  protected java.lang.String segment;

  protected java.util.Map<java.lang.String, org.jboss.resteasy.core.registry.SegmentNode> children;

  protected java.util.List<org.jboss.resteasy.core.registry.MethodExpression> targets;

  public org.jboss.resteasy.core.registry.SegmentNode(java.lang.String);
    Code:
       0: aload_0
       1: invokespecial #1                  // Method java/lang/Object."<init>":()V
       4: aload_0
       5: new           #2                  // class java/util/HashMap
       8: dup
       9: invokespecial #3                  // Method java/util/HashMap."<init>":()V
      12: putfield      #4                  // Field children:Ljava/util/Map;
      15: aload_0
      16: new           #5                  // class java/util/ArrayList
      19: dup
      20: invokespecial #6                  // Method java/util/ArrayList."<init>":()V
      23: putfield      #7                  // Field targets:Ljava/util/List;
      26: aload_0
      27: aload_1
      28: putfield      #8                  // Field segment:Ljava/lang/String;
      31: return

  public org.jboss.resteasy.core.ResourceInvoker match(org.jboss.resteasy.spi.HttpRequest, int);
    Code:
       0: aload_1
       1: invokeinterface #9,  1            // InterfaceMethod org/jboss/resteasy/spi/HttpRequest.getUri:()Lorg/jboss/resteasy/spi/ResteasyUriInfo;
       6: invokevirtual #10                 // Method org/jboss/resteasy/spi/ResteasyUriInfo.getMatchingPath:()Ljava/lang/String;
       9: astore_3
      10: iload_2
      11: aload_3
      12: invokevirtual #11                 // Method java/lang/String.length:()I
      15: if_icmpge     31
      18: aload_3
      19: iload_2
      20: invokevirtual #12                 // Method java/lang/String.charAt:(I)C
      23: bipush        47
      25: if_icmpne     31
      28: iinc          2, 1
      31: new           #5                  // class java/util/ArrayList
      34: dup
      35: invokespecial #6                  // Method java/util/ArrayList."<init>":()V
      38: astore        4
      40: aload_0
      41: aload_3
      42: iload_2
      43: aload         4
      45: invokevirtual #13                 // Method potentials:(Ljava/lang/String;ILjava/util/List;)V
      48: aload         4
      50: invokestatic  #14                 // Method java/util/Collections.sort:(Ljava/util/List;)V
      53: iconst_0
      54: istore        5
      56: new           #5                  // class java/util/ArrayList
      59: dup
      60: invokespecial #6                  // Method java/util/ArrayList."<init>":()V
      63: astore        6
      65: aload         4
      67: invokeinterface #15,  1           // InterfaceMethod java/util/List.iterator:()Ljava/util/Iterator;
      72: astore        7
      74: aload         7
      76: invokeinterface #16,  1           // InterfaceMethod java/util/Iterator.hasNext:()Z
      81: ifeq          264
      84: aload         7
      86: invokeinterface #17,  1           // InterfaceMethod java/util/Iterator.next:()Ljava/lang/Object;
      91: checkcast     #18                 // class org/jboss/resteasy/core/registry/MethodExpression
      94: astore        8
      96: iload         5
      98: ifeq          112
     101: aload         8
     103: invokevirtual #19                 // Method org/jboss/resteasy/core/registry/MethodExpression.isLocator:()Z
     106: ifeq          112
     109: goto          74
     112: aload         8
     114: invokevirtual #20                 // Method org/jboss/resteasy/core/registry/MethodExpression.getPattern:()Ljava/util/regex/Pattern;
     117: astore        9
     119: aload         9
     121: aload_3
     122: invokevirtual #21                 // Method java/util/regex/Pattern.matcher:(Ljava/lang/CharSequence;)Ljava/util/regex/Matcher;
     125: astore        10
     127: aload         10
     129: iload_2
     130: aload_3
     131: invokevirtual #11                 // Method java/lang/String.length:()I
     134: invokevirtual #22                 // Method java/util/regex/Matcher.region:(II)Ljava/util/regex/Matcher;
     137: pop
     138: aload         10
     140: invokevirtual #23                 // Method java/util/regex/Matcher.matches:()Z
     143: ifeq          261
     146: iconst_1
     147: istore        5
     149: aload         8
     151: invokevirtual #24                 // Method org/jboss/resteasy/core/registry/MethodExpression.getInvoker:()Lorg/jboss/resteasy/core/ResourceInvoker;
     154: astore        11
     156: aload         11
     158: instanceof    #25                 // class org/jboss/resteasy/core/ResourceLocatorInvoker
     161: ifeq          242
     164: aload_1
     165: invokeinterface #9,  1            // InterfaceMethod org/jboss/resteasy/spi/HttpRequest.getUri:()Lorg/jboss/resteasy/spi/ResteasyUriInfo;
     170: astore        12
     172: aload         10
     174: aload         8
     176: invokevirtual #26                 // Method org/jboss/resteasy/core/registry/MethodExpression.getNumGroups:()I
     179: iconst_1
     180: iadd
     181: invokevirtual #27                 // Method java/util/regex/Matcher.start:(I)I
     184: istore        13
     186: iload         13
     188: iconst_m1
     189: if_icmpne     207
     192: aload         12
     194: aload_3
     195: invokevirtual #28                 // Method org/jboss/resteasy/spi/ResteasyUriInfo.pushMatchedPath:(Ljava/lang/String;)V
     198: aload         12
     200: aload_3
     201: invokevirtual #29                 // Method org/jboss/resteasy/spi/ResteasyUriInfo.pushMatchedURI:(Ljava/lang/String;)V
     204: goto          230
     207: aload_3
     208: iconst_0
     209: iload         13
     211: invokevirtual #30                 // Method java/lang/String.substring:(II)Ljava/lang/String;
     214: astore        14
     216: aload         12
     218: aload         14
     220: invokevirtual #28                 // Method org/jboss/resteasy/spi/ResteasyUriInfo.pushMatchedPath:(Ljava/lang/String;)V
     223: aload         12
     225: aload         14
     227: invokevirtual #29                 // Method org/jboss/resteasy/spi/ResteasyUriInfo.pushMatchedURI:(Ljava/lang/String;)V
     230: aload         8
     232: aload_1
     233: aload         10
     235: aload_3
     236: invokevirtual #31                 // Method org/jboss/resteasy/core/registry/MethodExpression.populatePathParams:(Lorg/jboss/resteasy/spi/HttpRequest;Ljava/util/regex/Matcher;Ljava/lang/String;)V
     239: aload         11
     241: areturn
     242: aload         6
     244: new           #32                 // class org/jboss/resteasy/core/registry/SegmentNode$Match
     247: dup
     248: aload         8
     250: aload         10
     252: invokespecial #33                 // Method org/jboss/resteasy/core/registry/SegmentNode$Match."<init>":(Lorg/jboss/resteasy/core/registry/MethodExpression;Ljava/util/regex/Matcher;)V
     255: invokeinterface #34,  2           // InterfaceMethod java/util/List.add:(Ljava/lang/Object;)Z
     260: pop
     261: goto          74
     264: aload         6
     266: invokeinterface #35,  1           // InterfaceMethod java/util/List.size:()I
     271: ifne          299
     274: new           #36                 // class javax/ws/rs/NotFoundException
     277: dup
     278: getstatic     #37                 // Field org/jboss/resteasy/resteasy_jaxrs/i18n/Messages.MESSAGES:Lorg/jboss/resteasy/resteasy_jaxrs/i18n/Messages;
     281: aload_1
     282: invokeinterface #9,  1            // InterfaceMethod org/jboss/resteasy/spi/HttpRequest.getUri:()Lorg/jboss/resteasy/spi/ResteasyUriInfo;
     287: invokevirtual #38                 // Method org/jboss/resteasy/spi/ResteasyUriInfo.getRequestUri:()Ljava/net/URI;
     290: invokeinterface #39,  2           // InterfaceMethod org/jboss/resteasy/resteasy_jaxrs/i18n/Messages.couldNotFindResourceForFullPath:(Ljava/net/URI;)Ljava/lang/String;
     295: invokespecial #40                 // Method javax/ws/rs/NotFoundException."<init>":(Ljava/lang/String;)V
     298: athrow
     299: aload_0
     300: aload         6
     302: aload_1
     303: invokeinterface #41,  1           // InterfaceMethod org/jboss/resteasy/spi/HttpRequest.getHttpMethod:()Ljava/lang/String;
     308: aload_1
     309: invokevirtual #42                 // Method match:(Ljava/util/List;Ljava/lang/String;Lorg/jboss/resteasy/spi/HttpRequest;)Lorg/jboss/resteasy/core/registry/SegmentNode$Match;
     312: astore        7
     314: aload         7
     316: getfield      #43                 // Field org/jboss/resteasy/core/registry/SegmentNode$Match.expression:Lorg/jboss/resteasy/core/registry/MethodExpression;
     319: aload_1
     320: aload         7
     322: getfield      #44                 // Field org/jboss/resteasy/core/registry/SegmentNode$Match.matcher:Ljava/util/regex/Matcher;
     325: aload_3
     326: invokevirtual #31                 // Method org/jboss/resteasy/core/registry/MethodExpression.populatePathParams:(Lorg/jboss/resteasy/spi/HttpRequest;Ljava/util/regex/Matcher;Ljava/lang/String;)V
     329: aload         7
     331: getfield      #43                 // Field org/jboss/resteasy/core/registry/SegmentNode$Match.expression:Lorg/jboss/resteasy/core/registry/MethodExpression;
     334: invokevirtual #24                 // Method org/jboss/resteasy/core/registry/MethodExpression.getInvoker:()Lorg/jboss/resteasy/core/ResourceInvoker;
     337: areturn

  public void potentials(java.lang.String, int, java.util.List<org.jboss.resteasy.core.registry.MethodExpression>);
    Code:
       0: iload_2
       1: aload_1
       2: invokevirtual #11                 // Method java/lang/String.length:()I
       5: if_icmpne     20
       8: aload_3
       9: aload_0
      10: getfield      #7                  // Field targets:Ljava/util/List;
      13: invokeinterface #45,  2           // InterfaceMethod java/util/List.addAll:(Ljava/util/Collection;)Z
      18: pop
      19: return
      20: iload_2
      21: aload_1
      22: invokevirtual #11                 // Method java/lang/String.length:()I
      25: if_icmpge     113
      28: aconst_null
      29: astore        4
      31: aload_1
      32: bipush        47
      34: iload_2
      35: invokevirtual #46                 // Method java/lang/String.indexOf:(II)I
      38: istore        5
      40: iload         5
      42: iconst_m1
      43: if_icmple     58
      46: aload_1
      47: iload_2
      48: iload         5
      50: invokevirtual #30                 // Method java/lang/String.substring:(II)Ljava/lang/String;
      53: astore        4
      55: goto          65
      58: aload_1
      59: iload_2
      60: invokevirtual #47                 // Method java/lang/String.substring:(I)Ljava/lang/String;
      63: astore        4
      65: aload_0
      66: getfield      #4                  // Field children:Ljava/util/Map;
      69: aload         4
      71: invokeinterface #48,  2           // InterfaceMethod java/util/Map.get:(Ljava/lang/Object;)Ljava/lang/Object;
      76: checkcast     #49                 // class org/jboss/resteasy/core/registry/SegmentNode
      79: astore        6
      81: aload         6
      83: ifnull        113
      86: iload_2
      87: aload         4
      89: invokevirtual #11                 // Method java/lang/String.length:()I
      92: iadd
      93: istore        7
      95: iload         5
      97: iconst_m1
      98: if_icmple     104
     101: iinc          7, 1
     104: aload         6
     106: aload_1
     107: iload         7
     109: aload_3
     110: invokevirtual #13                 // Method potentials:(Ljava/lang/String;ILjava/util/List;)V
     113: aload_0
     114: getfield      #7                  // Field targets:Ljava/util/List;
     117: invokeinterface #15,  1           // InterfaceMethod java/util/List.iterator:()Ljava/util/Iterator;
     122: astore        4
     124: aload         4
     126: invokeinterface #16,  1           // InterfaceMethod java/util/Iterator.hasNext:()Z
     131: ifeq          177
     134: aload         4
     136: invokeinterface #17,  1           // InterfaceMethod java/util/Iterator.next:()Ljava/lang/Object;
     141: checkcast     #18                 // class org/jboss/resteasy/core/registry/MethodExpression
     144: astore        5
     146: aload         5
     148: invokevirtual #26                 // Method org/jboss/resteasy/core/registry/MethodExpression.getNumGroups:()I
     151: ifgt          165
     154: aload         5
     156: invokevirtual #24                 // Method org/jboss/resteasy/core/registry/MethodExpression.getInvoker:()Lorg/jboss/resteasy/core/ResourceInvoker;
     159: instanceof    #25                 // class org/jboss/resteasy/core/ResourceLocatorInvoker
     162: ifeq          174
     165: aload_3
     166: aload         5
     168: invokeinterface #34,  2           // InterfaceMethod java/util/List.add:(Ljava/lang/Object;)Z
     173: pop
     174: goto          124
     177: return

  public static org.jboss.resteasy.core.registry.SegmentNode$SortFactor createSortFactor(javax.ws.rs.core.MediaType, javax.ws.rs.core.MediaType);
    Code:
       0: new           #50                 // class org/jboss/resteasy/core/registry/SegmentNode$SortFactor
       3: dup
       4: invokespecial #51                 // Method org/jboss/resteasy/core/registry/SegmentNode$SortFactor."<init>":()V
       7: astore_2
       8: aload_0
       9: invokevirtual #52                 // Method javax/ws/rs/core/MediaType.isWildcardType:()Z
      12: aload_1
      13: invokevirtual #52                 // Method javax/ws/rs/core/MediaType.isWildcardType:()Z
      16: if_icmpeq     54
      19: aload_2
      20: aload_0
      21: invokevirtual #52                 // Method javax/ws/rs/core/MediaType.isWildcardType:()Z
      24: ifeq          34
      27: aload_1
      28: invokevirtual #53                 // Method javax/ws/rs/core/MediaType.getType:()Ljava/lang/String;
      31: goto          38
      34: aload_0
      35: invokevirtual #53                 // Method javax/ws/rs/core/MediaType.getType:()Ljava/lang/String;
      38: putfield      #54                 // Field org/jboss/resteasy/core/registry/SegmentNode$SortFactor.type:Ljava/lang/String;
      41: aload_2
      42: dup
      43: getfield      #55                 // Field org/jboss/resteasy/core/registry/SegmentNode$SortFactor.d:I
      46: iconst_1
      47: iadd
      48: putfield      #55                 // Field org/jboss/resteasy/core/registry/SegmentNode$SortFactor.d:I
      51: goto          62
      54: aload_2
      55: aload_0
      56: invokevirtual #53                 // Method javax/ws/rs/core/MediaType.getType:()Ljava/lang/String;
      59: putfield      #54                 // Field org/jboss/resteasy/core/registry/SegmentNode$SortFactor.type:Ljava/lang/String;
      62: aload_0
      63: invokevirtual #56                 // Method javax/ws/rs/core/MediaType.isWildcardSubtype:()Z
      66: aload_1
      67: invokevirtual #56                 // Method javax/ws/rs/core/MediaType.isWildcardSubtype:()Z
      70: if_icmpeq     108
      73: aload_2
      74: aload_0
      75: invokevirtual #56                 // Method javax/ws/rs/core/MediaType.isWildcardSubtype:()Z
      78: ifeq          88
      81: aload_1
      82: invokevirtual #57                 // Method javax/ws/rs/core/MediaType.getSubtype:()Ljava/lang/String;
      85: goto          92
      88: aload_0
      89: invokevirtual #57                 // Method javax/ws/rs/core/MediaType.getSubtype:()Ljava/lang/String;
      92: putfield      #58                 // Field org/jboss/resteasy/core/registry/SegmentNode$SortFactor.subtype:Ljava/lang/String;
      95: aload_2
      96: dup
      97: getfield      #55                 // Field org/jboss/resteasy/core/registry/SegmentNode$SortFactor.d:I
     100: iconst_1
     101: iadd
     102: putfield      #55                 // Field org/jboss/resteasy/core/registry/SegmentNode$SortFactor.d:I
     105: goto          116
     108: aload_2
     109: aload_0
     110: invokevirtual #57                 // Method javax/ws/rs/core/MediaType.getSubtype:()Ljava/lang/String;
     113: putfield      #58                 // Field org/jboss/resteasy/core/registry/SegmentNode$SortFactor.subtype:Ljava/lang/String;
     116: aload_0
     117: invokevirtual #59                 // Method javax/ws/rs/core/MediaType.getParameters:()Ljava/util/Map;
     120: ldc           #60                 // String q
     122: invokeinterface #48,  2           // InterfaceMethod java/util/Map.get:(Ljava/lang/Object;)Ljava/lang/Object;
     127: checkcast     #61                 // class java/lang/String
     130: astore_3
     131: aload_3
     132: ifnull        143
     135: aload_2
     136: aload_3
     137: invokestatic  #62                 // Method java/lang/Float.parseFloat:(Ljava/lang/String;)F
     140: putfield      #63                 // Field org/jboss/resteasy/core/registry/SegmentNode$SortFactor.q:F
     143: aload_1
     144: invokevirtual #59                 // Method javax/ws/rs/core/MediaType.getParameters:()Ljava/util/Map;
     147: ldc           #64                 // String qs
     149: invokeinterface #48,  2           // InterfaceMethod java/util/Map.get:(Ljava/lang/Object;)Ljava/lang/Object;
     154: checkcast     #61                 // class java/lang/String
     157: astore        4
     159: aload         4
     161: ifnull        173
     164: aload_2
     165: aload         4
     167: invokestatic  #62                 // Method java/lang/Float.parseFloat:(Ljava/lang/String;)F
     170: putfield      #65                 // Field org/jboss/resteasy/core/registry/SegmentNode$SortFactor.qs:F
     173: aload_2
     174: iconst_0
     175: putfield      #66                 // Field org/jboss/resteasy/core/registry/SegmentNode$SortFactor.dm:I
     178: aload_0
     179: invokevirtual #59                 // Method javax/ws/rs/core/MediaType.getParameters:()Ljava/util/Map;
     182: invokeinterface #67,  1           // InterfaceMethod java/util/Map.entrySet:()Ljava/util/Set;
     187: invokeinterface #68,  1           // InterfaceMethod java/util/Set.iterator:()Ljava/util/Iterator;
     192: astore        5
     194: aload         5
     196: invokeinterface #16,  1           // InterfaceMethod java/util/Iterator.hasNext:()Z
     201: ifeq          316
     204: aload         5
     206: invokeinterface #17,  1           // InterfaceMethod java/util/Iterator.next:()Ljava/lang/Object;
     211: checkcast     #69                 // class java/util/Map$Entry
     214: astore        6
     216: aload         6
     218: invokeinterface #70,  1           // InterfaceMethod java/util/Map$Entry.getKey:()Ljava/lang/Object;
     223: checkcast     #61                 // class java/lang/String
     226: astore        7
     228: ldc           #60                 // String q
     230: aload         7
     232: invokevirtual #71                 // Method java/lang/String.equals:(Ljava/lang/Object;)Z
     235: ifne          194
     238: ldc           #64                 // String qs
     240: aload         7
     242: invokevirtual #71                 // Method java/lang/String.equals:(Ljava/lang/Object;)Z
     245: ifeq          251
     248: goto          194
     251: aload_1
     252: invokevirtual #59                 // Method javax/ws/rs/core/MediaType.getParameters:()Ljava/util/Map;
     255: aload         7
     257: invokeinterface #48,  2           // InterfaceMethod java/util/Map.get:(Ljava/lang/Object;)Ljava/lang/Object;
     262: checkcast     #61                 // class java/lang/String
     265: astore        8
     267: aload         8
     269: ifnonnull     285
     272: aload_2
     273: dup
     274: getfield      #66                 // Field org/jboss/resteasy/core/registry/SegmentNode$SortFactor.dm:I
     277: iconst_1
     278: iadd
     279: putfield      #66                 // Field org/jboss/resteasy/core/registry/SegmentNode$SortFactor.dm:I
     282: goto          194
     285: aload         8
     287: aload         6
     289: invokeinterface #72,  1           // InterfaceMethod java/util/Map$Entry.getValue:()Ljava/lang/Object;
     294: invokevirtual #71                 // Method java/lang/String.equals:(Ljava/lang/Object;)Z
     297: ifne          313
     300: aload_2
     301: dup
     302: getfield      #66                 // Field org/jboss/resteasy/core/registry/SegmentNode$SortFactor.dm:I
     305: iconst_1
     306: iadd
     307: putfield      #66                 // Field org/jboss/resteasy/core/registry/SegmentNode$SortFactor.dm:I
     310: goto          194
     313: goto          194
     316: aload_1
     317: invokevirtual #59                 // Method javax/ws/rs/core/MediaType.getParameters:()Ljava/util/Map;
     320: invokeinterface #67,  1           // InterfaceMethod java/util/Map.entrySet:()Ljava/util/Set;
     325: invokeinterface #68,  1           // InterfaceMethod java/util/Set.iterator:()Ljava/util/Iterator;
     330: astore        5
     332: aload         5
     334: invokeinterface #16,  1           // InterfaceMethod java/util/Iterator.hasNext:()Z
     339: ifeq          454
     342: aload         5
     344: invokeinterface #17,  1           // InterfaceMethod java/util/Iterator.next:()Ljava/lang/Object;
     349: checkcast     #69                 // class java/util/Map$Entry
     352: astore        6
     354: aload         6
     356: invokeinterface #70,  1           // InterfaceMethod java/util/Map$Entry.getKey:()Ljava/lang/Object;
     361: checkcast     #61                 // class java/lang/String
     364: astore        7
     366: ldc           #60                 // String q
     368: aload         7
     370: invokevirtual #71                 // Method java/lang/String.equals:(Ljava/lang/Object;)Z
     373: ifne          332
     376: ldc           #64                 // String qs
     378: aload         7
     380: invokevirtual #71                 // Method java/lang/String.equals:(Ljava/lang/Object;)Z
     383: ifeq          389
     386: goto          332
     389: aload_0
     390: invokevirtual #59                 // Method javax/ws/rs/core/MediaType.getParameters:()Ljava/util/Map;
     393: aload         7
     395: invokeinterface #48,  2           // InterfaceMethod java/util/Map.get:(Ljava/lang/Object;)Ljava/lang/Object;
     400: checkcast     #61                 // class java/lang/String
     403: astore        8
     405: aload         8
     407: ifnonnull     423
     410: aload_2
     411: dup
     412: getfield      #66                 // Field org/jboss/resteasy/core/registry/SegmentNode$SortFactor.dm:I
     415: iconst_1
     416: iadd
     417: putfield      #66                 // Field org/jboss/resteasy/core/registry/SegmentNode$SortFactor.dm:I
     420: goto          332
     423: aload         8
     425: aload         6
     427: invokeinterface #72,  1           // InterfaceMethod java/util/Map$Entry.getValue:()Ljava/lang/Object;
     432: invokevirtual #71                 // Method java/lang/String.equals:(Ljava/lang/Object;)Z
     435: ifne          451
     438: aload_2
     439: dup
     440: getfield      #66                 // Field org/jboss/resteasy/core/registry/SegmentNode$SortFactor.dm:I
     443: iconst_1
     444: iadd
     445: putfield      #66                 // Field org/jboss/resteasy/core/registry/SegmentNode$SortFactor.dm:I
     448: goto          332
     451: goto          332
     454: aload_2
     455: areturn

  public org.jboss.resteasy.core.registry.SegmentNode$Match match(java.util.List<org.jboss.resteasy.core.registry.SegmentNode$Match>, java.lang.String, org.jboss.resteasy.spi.HttpRequest);
    Code:
       0: aload_3
       1: invokeinterface #73,  1           // InterfaceMethod org/jboss/resteasy/spi/HttpRequest.getHttpHeaders:()Ljavax/ws/rs/core/HttpHeaders;
       6: invokeinterface #74,  1           // InterfaceMethod javax/ws/rs/core/HttpHeaders.getMediaType:()Ljavax/ws/rs/core/MediaType;
      11: astore        4
      13: aload_3
      14: invokeinterface #73,  1           // InterfaceMethod org/jboss/resteasy/spi/HttpRequest.getHttpHeaders:()Ljavax/ws/rs/core/HttpHeaders;
      19: invokeinterface #75,  1           // InterfaceMethod javax/ws/rs/core/HttpHeaders.getAcceptableMediaTypes:()Ljava/util/List;
      24: astore        5
      26: new           #5                  // class java/util/ArrayList
      29: dup
      30: invokespecial #6                  // Method java/util/ArrayList."<init>":()V
      33: astore        6
      35: aload         5
      37: invokeinterface #15,  1           // InterfaceMethod java/util/List.iterator:()Ljava/util/Iterator;
      42: astore        7
      44: aload         7
      46: invokeinterface #16,  1           // InterfaceMethod java/util/Iterator.hasNext:()Z
      51: ifeq          82
      54: aload         7
      56: invokeinterface #17,  1           // InterfaceMethod java/util/Iterator.next:()Ljava/lang/Object;
      61: checkcast     #76                 // class javax/ws/rs/core/MediaType
      64: astore        8
      66: aload         6
      68: aload         8
      70: invokestatic  #77                 // Method org/jboss/resteasy/util/WeightedMediaType.parse:(Ljavax/ws/rs/core/MediaType;)Lorg/jboss/resteasy/util/WeightedMediaType;
      73: invokeinterface #34,  2           // InterfaceMethod java/util/List.add:(Ljava/lang/Object;)Z
      78: pop
      79: goto          44
      82: new           #5                  // class java/util/ArrayList
      85: dup
      86: invokespecial #6                  // Method java/util/ArrayList."<init>":()V
      89: astore        7
      91: iconst_0
      92: istore        8
      94: iconst_0
      95: istore        9
      97: aload_1
      98: invokeinterface #15,  1           // InterfaceMethod java/util/List.iterator:()Ljava/util/Iterator;
     103: astore        10
     105: aload         10
     107: invokeinterface #16,  1           // InterfaceMethod java/util/Iterator.hasNext:()Z
     112: ifeq          196
     115: aload         10
     117: invokeinterface #17,  1           // InterfaceMethod java/util/Iterator.next:()Ljava/lang/Object;
     122: checkcast     #32                 // class org/jboss/resteasy/core/registry/SegmentNode$Match
     125: astore        11
     127: aload         11
     129: getfield      #43                 // Field org/jboss/resteasy/core/registry/SegmentNode$Match.expression:Lorg/jboss/resteasy/core/registry/MethodExpression;
     132: invokevirtual #24                 // Method org/jboss/resteasy/core/registry/MethodExpression.getInvoker:()Lorg/jboss/resteasy/core/ResourceInvoker;
     135: checkcast     #78                 // class org/jboss/resteasy/core/ResourceMethodInvoker
     138: astore        12
     140: aload         12
     142: invokevirtual #79                 // Method org/jboss/resteasy/core/ResourceMethodInvoker.getHttpMethods:()Ljava/util/Set;
     145: aload_2
     146: invokevirtual #80                 // Method java/lang/String.toUpperCase:()Ljava/lang/String;
     149: invokeinterface #81,  2           // InterfaceMethod java/util/Set.contains:(Ljava/lang/Object;)Z
     154: ifeq          193
     157: iconst_1
     158: istore        8
     160: aload         12
     162: aload         4
     164: invokevirtual #82                 // Method org/jboss/resteasy/core/ResourceMethodInvoker.doesConsume:(Ljavax/ws/rs/core/MediaType;)Z
     167: ifeq          193
     170: iconst_1
     171: istore        9
     173: aload         12
     175: aload         6
     177: invokevirtual #83                 // Method org/jboss/resteasy/core/ResourceMethodInvoker.doesProduce:(Ljava/util/List;)Z
     180: ifeq          193
     183: aload         7
     185: aload         11
     187: invokeinterface #34,  2           // InterfaceMethod java/util/List.add:(Ljava/lang/Object;)Z
     192: pop
     193: goto          105
     196: aload         7
     198: invokeinterface #35,  1           // InterfaceMethod java/util/List.size:()I
     203: ifne          542
     206: iload         8
     208: ifne          505
     211: new           #84                 // class java/util/HashSet
     214: dup
     215: invokespecial #85                 // Method java/util/HashSet."<init>":()V
     218: astore        10
     220: aload_1
     221: invokeinterface #15,  1           // InterfaceMethod java/util/List.iterator:()Ljava/util/Iterator;
     226: astore        11
     228: aload         11
     230: invokeinterface #16,  1           // InterfaceMethod java/util/Iterator.hasNext:()Z
     235: ifeq          273
     238: aload         11
     240: invokeinterface #17,  1           // InterfaceMethod java/util/Iterator.next:()Ljava/lang/Object;
     245: checkcast     #32                 // class org/jboss/resteasy/core/registry/SegmentNode$Match
     248: astore        12
     250: aload         10
     252: aload         12
     254: getfield      #43                 // Field org/jboss/resteasy/core/registry/SegmentNode$Match.expression:Lorg/jboss/resteasy/core/registry/MethodExpression;
     257: invokevirtual #24                 // Method org/jboss/resteasy/core/registry/MethodExpression.getInvoker:()Lorg/jboss/resteasy/core/ResourceInvoker;
     260: checkcast     #78                 // class org/jboss/resteasy/core/ResourceMethodInvoker
     263: invokevirtual #79                 // Method org/jboss/resteasy/core/ResourceMethodInvoker.getHttpMethods:()Ljava/util/Set;
     266: invokevirtual #86                 // Method java/util/HashSet.addAll:(Ljava/util/Collection;)Z
     269: pop
     270: goto          228
     273: aload_2
     274: ldc           #87                 // String HEAD
     276: invokevirtual #88                 // Method java/lang/String.equalsIgnoreCase:(Ljava/lang/String;)Z
     279: ifeq          301
     282: aload         10
     284: ldc           #89                 // String GET
     286: invokevirtual #90                 // Method java/util/HashSet.contains:(Ljava/lang/Object;)Z
     289: ifeq          301
     292: aload_0
     293: aload_1
     294: ldc           #89                 // String GET
     296: aload_3
     297: invokevirtual #42                 // Method match:(Ljava/util/List;Ljava/lang/String;Lorg/jboss/resteasy/spi/HttpRequest;)Lorg/jboss/resteasy/core/registry/SegmentNode$Match;
     300: areturn
     301: aload         10
     303: ldc           #89                 // String GET
     305: invokevirtual #90                 // Method java/util/HashSet.contains:(Ljava/lang/Object;)Z
     308: ifeq          319
     311: aload         10
     313: ldc           #87                 // String HEAD
     315: invokevirtual #91                 // Method java/util/HashSet.add:(Ljava/lang/Object;)Z
     318: pop
     319: aload         10
     321: ldc           #92                 // String OPTIONS
     323: invokevirtual #91                 // Method java/util/HashSet.add:(Ljava/lang/Object;)Z
     326: pop
     327: ldc           #93                 // String
     329: astore        11
     331: iconst_1
     332: istore        12
     334: aload         10
     336: invokevirtual #94                 // Method java/util/HashSet.iterator:()Ljava/util/Iterator;
     339: astore        13
     341: aload         13
     343: invokeinterface #16,  1           // InterfaceMethod java/util/Iterator.hasNext:()Z
     348: ifeq          421
     351: aload         13
     353: invokeinterface #17,  1           // InterfaceMethod java/util/Iterator.next:()Ljava/lang/Object;
     358: checkcast     #61                 // class java/lang/String
     361: astore        14
     363: iload         12
     365: ifeq          374
     368: iconst_0
     369: istore        12
     371: goto          396
     374: new           #95                 // class java/lang/StringBuilder
     377: dup
     378: invokespecial #96                 // Method java/lang/StringBuilder."<init>":()V
     381: aload         11
     383: invokevirtual #97                 // Method java/lang/StringBuilder.append:(Ljava/lang/String;)Ljava/lang/StringBuilder;
     386: ldc           #98                 // String ,
     388: invokevirtual #97                 // Method java/lang/StringBuilder.append:(Ljava/lang/String;)Ljava/lang/StringBuilder;
     391: invokevirtual #99                 // Method java/lang/StringBuilder.toString:()Ljava/lang/String;
     394: astore        11
     396: new           #95                 // class java/lang/StringBuilder
     399: dup
     400: invokespecial #96                 // Method java/lang/StringBuilder."<init>":()V
     403: aload         11
     405: invokevirtual #97                 // Method java/lang/StringBuilder.append:(Ljava/lang/String;)Ljava/lang/StringBuilder;
     408: aload         14
     410: invokevirtual #97                 // Method java/lang/StringBuilder.append:(Ljava/lang/String;)Ljava/lang/StringBuilder;
     413: invokevirtual #99                 // Method java/lang/StringBuilder.toString:()Ljava/lang/String;
     416: astore        11
     418: goto          341
     421: aload_2
     422: ldc           #92                 // String OPTIONS
     424: invokevirtual #71                 // Method java/lang/String.equals:(Ljava/lang/Object;)Z
     427: ifeq          468
     430: aload         11
     432: getstatic     #100                // Field javax/ws/rs/core/MediaType.TEXT_PLAIN_TYPE:Ljavax/ws/rs/core/MediaType;
     435: invokestatic  #101                // Method javax/ws/rs/core/Response.ok:(Ljava/lang/Object;Ljavax/ws/rs/core/MediaType;)Ljavax/ws/rs/core/Response$ResponseBuilder;
     438: ldc           #103                // String Allow
     440: aload         11
     442: invokevirtual #104                // Method javax/ws/rs/core/Response$ResponseBuilder.header:(Ljava/lang/String;Ljava/lang/Object;)Ljavax/ws/rs/core/Response$ResponseBuilder;
     445: invokevirtual #105                // Method javax/ws/rs/core/Response$ResponseBuilder.build:()Ljavax/ws/rs/core/Response;
     448: astore        13
     450: new           #106                // class org/jboss/resteasy/spi/DefaultOptionsMethodException
     453: dup
     454: getstatic     #37                 // Field org/jboss/resteasy/resteasy_jaxrs/i18n/Messages.MESSAGES:Lorg/jboss/resteasy/resteasy_jaxrs/i18n/Messages;
     457: invokeinterface #107,  1          // InterfaceMethod org/jboss/resteasy/resteasy_jaxrs/i18n/Messages.noResourceMethodFoundForOptions:()Ljava/lang/String;
     462: aload         13
     464: invokespecial #108                // Method org/jboss/resteasy/spi/DefaultOptionsMethodException."<init>":(Ljava/lang/String;Ljavax/ws/rs/core/Response;)V
     467: athrow
     468: sipush        405
     471: invokestatic  #110                // Method javax/ws/rs/core/Response.status:(I)Ljavax/ws/rs/core/Response$ResponseBuilder;
     474: ldc           #103                // String Allow
     476: aload         11
     478: invokevirtual #104                // Method javax/ws/rs/core/Response$ResponseBuilder.header:(Ljava/lang/String;Ljava/lang/Object;)Ljavax/ws/rs/core/Response$ResponseBuilder;
     481: invokevirtual #105                // Method javax/ws/rs/core/Response$ResponseBuilder.build:()Ljavax/ws/rs/core/Response;
     484: astore        13
     486: new           #111                // class javax/ws/rs/NotAllowedException
     489: dup
     490: getstatic     #37                 // Field org/jboss/resteasy/resteasy_jaxrs/i18n/Messages.MESSAGES:Lorg/jboss/resteasy/resteasy_jaxrs/i18n/Messages;
     493: aload_2
     494: invokeinterface #112,  2          // InterfaceMethod org/jboss/resteasy/resteasy_jaxrs/i18n/Messages.noResourceMethodFoundForHttpMethod:(Ljava/lang/String;)Ljava/lang/String;
     499: aload         13
     501: invokespecial #113                // Method javax/ws/rs/NotAllowedException."<init>":(Ljava/lang/String;Ljavax/ws/rs/core/Response;)V
     504: athrow
     505: iload         9
     507: ifne          526
     510: new           #114                // class javax/ws/rs/NotSupportedException
     513: dup
     514: getstatic     #37                 // Field org/jboss/resteasy/resteasy_jaxrs/i18n/Messages.MESSAGES:Lorg/jboss/resteasy/resteasy_jaxrs/i18n/Messages;
     517: invokeinterface #115,  1          // InterfaceMethod org/jboss/resteasy/resteasy_jaxrs/i18n/Messages.cannotConsumeContentType:()Ljava/lang/String;
     522: invokespecial #116                // Method javax/ws/rs/NotSupportedException."<init>":(Ljava/lang/String;)V
     525: athrow
     526: new           #117                // class javax/ws/rs/NotAcceptableException
     529: dup
     530: getstatic     #37                 // Field org/jboss/resteasy/resteasy_jaxrs/i18n/Messages.MESSAGES:Lorg/jboss/resteasy/resteasy_jaxrs/i18n/Messages;
     533: invokeinterface #118,  1          // InterfaceMethod org/jboss/resteasy/resteasy_jaxrs/i18n/Messages.noMatchForAcceptHeader:()Ljava/lang/String;
     538: invokespecial #119                // Method javax/ws/rs/NotAcceptableException."<init>":(Ljava/lang/String;)V
     541: athrow
     542: new           #5                  // class java/util/ArrayList
     545: dup
     546: invokespecial #6                  // Method java/util/ArrayList."<init>":()V
     549: astore        10
     551: aload         7
     553: invokeinterface #15,  1           // InterfaceMethod java/util/List.iterator:()Ljava/util/Iterator;
     558: astore        11
     560: aload         11
     562: invokeinterface #16,  1           // InterfaceMethod java/util/Iterator.hasNext:()Z
     567: ifeq          862
     570: aload         11
     572: invokeinterface #17,  1           // InterfaceMethod java/util/Iterator.next:()Ljava/lang/Object;
     577: checkcast     #32                 // class org/jboss/resteasy/core/registry/SegmentNode$Match
     580: astore        12
     582: aload         12
     584: getfield      #43                 // Field org/jboss/resteasy/core/registry/SegmentNode$Match.expression:Lorg/jboss/resteasy/core/registry/MethodExpression;
     587: invokevirtual #24                 // Method org/jboss/resteasy/core/registry/MethodExpression.getInvoker:()Lorg/jboss/resteasy/core/ResourceInvoker;
     590: checkcast     #78                 // class org/jboss/resteasy/core/ResourceMethodInvoker
     593: astore        13
     595: aload         4
     597: ifnonnull     605
     600: getstatic     #120                // Field javax/ws/rs/core/MediaType.WILDCARD_TYPE:Ljavax/ws/rs/core/MediaType;
     603: astore        4
     605: aload         13
     607: invokevirtual #121                // Method org/jboss/resteasy/core/ResourceMethodInvoker.getConsumes:()[Ljavax/ws/rs/core/MediaType;
     610: astore        14
     612: aload         14
     614: arraylength
     615: ifne          623
     618: getstatic     #122                // Field WILDCARD_ARRAY:[Ljavax/ws/rs/core/MediaType;
     621: astore        14
     623: aload         13
     625: invokevirtual #123                // Method org/jboss/resteasy/core/ResourceMethodInvoker.getProduces:()[Ljavax/ws/rs/core/MediaType;
     628: astore        15
     630: aload         15
     632: arraylength
     633: ifne          641
     636: getstatic     #122                // Field WILDCARD_ARRAY:[Ljavax/ws/rs/core/MediaType;
     639: astore        15
     641: new           #5                  // class java/util/ArrayList
     644: dup
     645: invokespecial #6                  // Method java/util/ArrayList."<init>":()V
     648: astore        16
     650: aload         14
     652: astore        17
     654: aload         17
     656: arraylength
     657: istore        18
     659: iconst_0
     660: istore        19
     662: iload         19
     664: iload         18
     666: if_icmpge     697
     669: aload         17
     671: iload         19
     673: aaload
     674: astore        20
     676: aload         16
     678: aload         4
     680: aload         20
     682: invokestatic  #124                // Method createSortFactor:(Ljavax/ws/rs/core/MediaType;Ljavax/ws/rs/core/MediaType;)Lorg/jboss/resteasy/core/registry/SegmentNode$SortFactor;
     685: invokeinterface #34,  2           // InterfaceMethod java/util/List.add:(Ljava/lang/Object;)Z
     690: pop
     691: iinc          19, 1
     694: goto          662
     697: aload         15
     699: astore        17
     701: aload         17
     703: arraylength
     704: istore        18
     706: iconst_0
     707: istore        19
     709: iload         19
     711: iload         18
     713: if_icmpge     859
     716: aload         17
     718: iload         19
     720: aaload
     721: astore        20
     723: aload         5
     725: astore        21
     727: aload         21
     729: invokeinterface #35,  1           // InterfaceMethod java/util/List.size:()I
     734: ifne          742
     737: getstatic     #125                // Field DEFAULT_ACCEPTS:Ljava/util/List;
     740: astore        21
     742: aload         21
     744: invokeinterface #15,  1           // InterfaceMethod java/util/List.iterator:()Ljava/util/Iterator;
     749: astore        22
     751: aload         22
     753: invokeinterface #16,  1           // InterfaceMethod java/util/Iterator.hasNext:()Z
     758: ifeq          853
     761: aload         22
     763: invokeinterface #17,  1           // InterfaceMethod java/util/Iterator.next:()Ljava/lang/Object;
     768: checkcast     #76                 // class javax/ws/rs/core/MediaType
     771: astore        23
     773: aload         23
     775: aload         20
     777: invokevirtual #126                // Method javax/ws/rs/core/MediaType.isCompatible:(Ljavax/ws/rs/core/MediaType;)Z
     780: ifeq          850
     783: aload         23
     785: aload         20
     787: invokestatic  #124                // Method createSortFactor:(Ljavax/ws/rs/core/MediaType;Ljavax/ws/rs/core/MediaType;)Lorg/jboss/resteasy/core/registry/SegmentNode$SortFactor;
     790: astore        24
     792: aload         16
     794: invokeinterface #15,  1           // InterfaceMethod java/util/List.iterator:()Ljava/util/Iterator;
     799: astore        25
     801: aload         25
     803: invokeinterface #16,  1           // InterfaceMethod java/util/Iterator.hasNext:()Z
     808: ifeq          850
     811: aload         25
     813: invokeinterface #17,  1           // InterfaceMethod java/util/Iterator.next:()Ljava/lang/Object;
     818: checkcast     #50                 // class org/jboss/resteasy/core/registry/SegmentNode$SortFactor
     821: astore        26
     823: aload         10
     825: new           #127                // class org/jboss/resteasy/core/registry/SegmentNode$SortEntry
     828: dup
     829: aload_0
     830: aload         12
     832: aload         26
     834: aload         24
     836: aload         20
     838: invokespecial #128                // Method org/jboss/resteasy/core/registry/SegmentNode$SortEntry."<init>":(Lorg/jboss/resteasy/core/registry/SegmentNode;Lorg/jboss/resteasy/core/registry/SegmentNode$Match;Lorg/jboss/resteasy/core/registry/SegmentNode$SortFactor;Lorg/jboss/resteasy/core/registry/SegmentNode$SortFactor;Ljavax/ws/rs/core/MediaType;)V
     841: invokeinterface #34,  2           // InterfaceMethod java/util/List.add:(Ljava/lang/Object;)Z
     846: pop
     847: goto          801
     850: goto          751
     853: iinc          19, 1
     856: goto          709
     859: goto          560
     862: aload         10
     864: invokestatic  #14                 // Method java/util/Collections.sort:(Ljava/util/List;)V
     867: aload         10
     869: iconst_0
     870: invokeinterface #129,  2          // InterfaceMethod java/util/List.get:(I)Ljava/lang/Object;
     875: checkcast     #127                // class org/jboss/resteasy/core/registry/SegmentNode$SortEntry
     878: astore        11
     880: aload_3
     881: ldc           #130                // String RESTEASY_CHOSEN_ACCEPT
     883: aload         11
     885: invokevirtual #131                // Method org/jboss/resteasy/core/registry/SegmentNode$SortEntry.getAcceptType:()Ljavax/ws/rs/core/MediaType;
     888: invokeinterface #132,  3          // InterfaceMethod org/jboss/resteasy/spi/HttpRequest.setAttribute:(Ljava/lang/String;Ljava/lang/Object;)V
     893: aload         11
     895: getfield      #133                // Field org/jboss/resteasy/core/registry/SegmentNode$SortEntry.match:Lorg/jboss/resteasy/core/registry/SegmentNode$Match;
     898: areturn

  protected void addExpression(org.jboss.resteasy.core.registry.MethodExpression);
    Code:
       0: aload_0
       1: getfield      #7                  // Field targets:Ljava/util/List;
       4: aload_1
       5: invokeinterface #34,  2           // InterfaceMethod java/util/List.add:(Ljava/lang/Object;)Z
      10: pop
      11: aload_0
      12: getfield      #7                  // Field targets:Ljava/util/List;
      15: invokestatic  #14                 // Method java/util/Collections.sort:(Ljava/util/List;)V
      18: return

  static {};
    Code:
       0: iconst_1
       1: anewarray     #76                 // class javax/ws/rs/core/MediaType
       4: dup
       5: iconst_0
       6: getstatic     #120                // Field javax/ws/rs/core/MediaType.WILDCARD_TYPE:Ljavax/ws/rs/core/MediaType;
       9: aastore
      10: putstatic     #122                // Field WILDCARD_ARRAY:[Ljavax/ws/rs/core/MediaType;
      13: new           #5                  // class java/util/ArrayList
      16: dup
      17: invokespecial #6                  // Method java/util/ArrayList."<init>":()V
      20: putstatic     #125                // Field DEFAULT_ACCEPTS:Ljava/util/List;
      23: getstatic     #125                // Field DEFAULT_ACCEPTS:Ljava/util/List;
      26: getstatic     #120                // Field javax/ws/rs/core/MediaType.WILDCARD_TYPE:Ljavax/ws/rs/core/MediaType;
      29: invokeinterface #34,  2           // InterfaceMethod java/util/List.add:(Ljava/lang/Object;)Z
      34: pop
      35: return
}
