Compiled from "HttpBPHandler.java"
public class org.apache.cxf.transport.http.blueprint.HttpBPHandler implements org.apache.aries.blueprint.NamespaceHandler {
  public org.apache.cxf.transport.http.blueprint.HttpBPHandler();
    Code:
       0: aload_0
       1: invokespecial #1                  // Method java/lang/Object."<init>":()V
       4: return

  public java.net.URL getSchemaLocation(java.lang.String);
    Code:
       0: ldc           #2                  // String http://cxf.apache.org/transports/http/configuration
       2: aload_1
       3: invokevirtual #3                  // Method java/lang/String.equals:(Ljava/lang/Object;)Z
       6: ifeq          22
       9: aload_0
      10: invokevirtual #4                  // Method java/lang/Object.getClass:()Ljava/lang/Class;
      13: invokevirtual #5                  // Method java/lang/Class.getClassLoader:()Ljava/lang/ClassLoader;
      16: ldc           #6                  // String schemas/configuration/http-conf.xsd
      18: invokevirtual #7                  // Method java/lang/ClassLoader.getResource:(Ljava/lang/String;)Ljava/net/URL;
      21: areturn
      22: aconst_null
      23: areturn

  public org.osgi.service.blueprint.reflect.Metadata parse(org.w3c.dom.Element, org.apache.aries.blueprint.ParserContext);
    Code:
       0: aload_1
       1: invokeinterface #8,  1            // InterfaceMethod org/w3c/dom/Element.getLocalName:()Ljava/lang/String;
       6: astore_3
       7: ldc           #9                  // String conduit
       9: aload_3
      10: invokevirtual #3                  // Method java/lang/String.equals:(Ljava/lang/Object;)Z
      13: ifeq          29
      16: new           #10                 // class org/apache/cxf/transport/http/blueprint/HttpConduitBPBeanDefinitionParser
      19: dup
      20: invokespecial #11                 // Method org/apache/cxf/transport/http/blueprint/HttpConduitBPBeanDefinitionParser."<init>":()V
      23: aload_1
      24: aload_2
      25: invokevirtual #12                 // Method org/apache/cxf/transport/http/blueprint/HttpConduitBPBeanDefinitionParser.parse:(Lorg/w3c/dom/Element;Lorg/apache/aries/blueprint/ParserContext;)Lorg/osgi/service/blueprint/reflect/Metadata;
      28: areturn
      29: ldc           #13                 // String destination
      31: aload_3
      32: invokevirtual #3                  // Method java/lang/String.equals:(Ljava/lang/Object;)Z
      35: ifeq          51
      38: new           #14                 // class org/apache/cxf/transport/http/blueprint/HttpDestinationBPBeanDefinitionParser
      41: dup
      42: invokespecial #15                 // Method org/apache/cxf/transport/http/blueprint/HttpDestinationBPBeanDefinitionParser."<init>":()V
      45: aload_1
      46: aload_2
      47: invokevirtual #16                 // Method org/apache/cxf/transport/http/blueprint/HttpDestinationBPBeanDefinitionParser.parse:(Lorg/w3c/dom/Element;Lorg/apache/aries/blueprint/ParserContext;)Lorg/osgi/service/blueprint/reflect/Metadata;
      50: areturn
      51: aconst_null
      52: areturn

  public java.util.Set<java.lang.Class> getManagedClasses();
    Code:
       0: aconst_null
       1: areturn

  public org.osgi.service.blueprint.reflect.ComponentMetadata decorate(org.w3c.dom.Node, org.osgi.service.blueprint.reflect.ComponentMetadata, org.apache.aries.blueprint.ParserContext);
    Code:
       0: aconst_null
       1: areturn
}
