Compiled from "Stage.java"
public final class com.google.inject.Stage extends java.lang.Enum<com.google.inject.Stage> {
  public static final com.google.inject.Stage TOOL;

  public static final com.google.inject.Stage DEVELOPMENT;

  public static final com.google.inject.Stage PRODUCTION;

  private static final com.google.inject.Stage[] $VALUES;

  public static com.google.inject.Stage[] values();
    Code:
       0: getstatic     #16                 // Field $VALUES:[Lcom/google/inject/Stage;
       3: invokevirtual #21                 // Method "[Lcom/google/inject/Stage;".clone:()Ljava/lang/Object;
       6: checkcast     #17                 // class "[Lcom/google/inject/Stage;"
       9: areturn

  public static com.google.inject.Stage valueOf(java.lang.String);
    Code:
       0: ldc           #2                  // class com/google/inject/Stage
       2: aload_0
       3: invokestatic  #26                 // Method java/lang/Enum.valueOf:(Ljava/lang/Class;Ljava/lang/String;)Ljava/lang/Enum;
       6: checkcast     #2                  // class com/google/inject/Stage
       9: areturn

  private com.google.inject.Stage();
    Code:
       0: aload_0
       1: aload_1
       2: iload_2
       3: invokespecial #32                 // Method java/lang/Enum."<init>":(Ljava/lang/String;I)V
       6: return

  static {};
    Code:
       0: new           #2                  // class com/google/inject/Stage
       3: dup
       4: ldc           #36                 // String TOOL
       6: iconst_0
       7: invokespecial #37                 // Method "<init>":(Ljava/lang/String;I)V
      10: putstatic     #39                 // Field TOOL:Lcom/google/inject/Stage;
      13: new           #2                  // class com/google/inject/Stage
      16: dup
      17: ldc           #40                 // String DEVELOPMENT
      19: iconst_1
      20: invokespecial #37                 // Method "<init>":(Ljava/lang/String;I)V
      23: putstatic     #42                 // Field DEVELOPMENT:Lcom/google/inject/Stage;
      26: new           #2                  // class com/google/inject/Stage
      29: dup
      30: ldc           #43                 // String PRODUCTION
      32: iconst_2
      33: invokespecial #37                 // Method "<init>":(Ljava/lang/String;I)V
      36: putstatic     #45                 // Field PRODUCTION:Lcom/google/inject/Stage;
      39: iconst_3
      40: anewarray     #2                  // class com/google/inject/Stage
      43: dup
      44: iconst_0
      45: getstatic     #39                 // Field TOOL:Lcom/google/inject/Stage;
      48: aastore
      49: dup
      50: iconst_1
      51: getstatic     #42                 // Field DEVELOPMENT:Lcom/google/inject/Stage;
      54: aastore
      55: dup
      56: iconst_2
      57: getstatic     #45                 // Field PRODUCTION:Lcom/google/inject/Stage;
      60: aastore
      61: putstatic     #16                 // Field $VALUES:[Lcom/google/inject/Stage;
      64: return
}
