Compiled from "EmailValidator.java"
public class org.apache.commons.validator.EmailValidator {
  private static final java.lang.String SPECIAL_CHARS;

  private static final java.lang.String VALID_CHARS;

  private static final java.lang.String QUOTED_USER;

  private static final java.lang.String ATOM;

  private static final java.lang.String WORD;

  private static final java.util.regex.Pattern IP_DOMAIN_PATTERN;

  private static final java.util.regex.Pattern TLD_PATTERN;

  private static final java.util.regex.Pattern USER_PATTERN;

  private static final java.util.regex.Pattern DOMAIN_PATTERN;

  private static final java.util.regex.Pattern ATOM_PATTERN;

  private static final org.apache.commons.validator.EmailValidator EMAIL_VALIDATOR;

  public static org.apache.commons.validator.EmailValidator getInstance();
    Code:
       0: getstatic     #1                  // Field EMAIL_VALIDATOR:Lorg/apache/commons/validator/EmailValidator;
       3: areturn

  protected org.apache.commons.validator.EmailValidator();
    Code:
       0: aload_0
       1: invokespecial #2                  // Method java/lang/Object."<init>":()V
       4: return

  public boolean isValid(java.lang.String);
    Code:
       0: invokestatic  #3                  // Method org/apache/commons/validator/routines/EmailValidator.getInstance:()Lorg/apache/commons/validator/routines/EmailValidator;
       3: aload_1
       4: invokevirtual #4                  // Method org/apache/commons/validator/routines/EmailValidator.isValid:(Ljava/lang/String;)Z
       7: ireturn

  protected boolean isValidDomain(java.lang.String);
    Code:
       0: iconst_0
       1: istore_2
       2: getstatic     #5                  // Field IP_DOMAIN_PATTERN:Ljava/util/regex/Pattern;
       5: aload_1
       6: invokevirtual #6                  // Method java/util/regex/Pattern.matcher:(Ljava/lang/CharSequence;)Ljava/util/regex/Matcher;
       9: astore_3
      10: aload_3
      11: invokevirtual #7                  // Method java/util/regex/Matcher.matches:()Z
      14: ifeq          40
      17: invokestatic  #8                  // Method org/apache/commons/validator/routines/InetAddressValidator.getInstance:()Lorg/apache/commons/validator/routines/InetAddressValidator;
      20: astore        4
      22: aload         4
      24: aload_3
      25: iconst_1
      26: invokevirtual #9                  // Method java/util/regex/Matcher.group:(I)Ljava/lang/String;
      29: invokevirtual #10                 // Method org/apache/commons/validator/routines/InetAddressValidator.isValid:(Ljava/lang/String;)Z
      32: ifeq          37
      35: iconst_1
      36: ireturn
      37: goto          51
      40: getstatic     #11                 // Field DOMAIN_PATTERN:Ljava/util/regex/Pattern;
      43: aload_1
      44: invokevirtual #6                  // Method java/util/regex/Pattern.matcher:(Ljava/lang/CharSequence;)Ljava/util/regex/Matcher;
      47: invokevirtual #7                  // Method java/util/regex/Matcher.matches:()Z
      50: istore_2
      51: iload_2
      52: ifeq          65
      55: aload_0
      56: aload_1
      57: invokevirtual #12                 // Method isValidSymbolicDomain:(Ljava/lang/String;)Z
      60: ifne          67
      63: iconst_0
      64: ireturn
      65: iconst_0
      66: ireturn
      67: iconst_1
      68: ireturn

  protected boolean isValidUser(java.lang.String);
    Code:
       0: getstatic     #13                 // Field USER_PATTERN:Ljava/util/regex/Pattern;
       3: aload_1
       4: invokevirtual #6                  // Method java/util/regex/Pattern.matcher:(Ljava/lang/CharSequence;)Ljava/util/regex/Matcher;
       7: invokevirtual #7                  // Method java/util/regex/Matcher.matches:()Z
      10: ireturn

  protected boolean isValidIpAddress(java.lang.String);
    Code:
       0: getstatic     #5                  // Field IP_DOMAIN_PATTERN:Ljava/util/regex/Pattern;
       3: aload_1
       4: invokevirtual #6                  // Method java/util/regex/Pattern.matcher:(Ljava/lang/CharSequence;)Ljava/util/regex/Matcher;
       7: astore_2
       8: iconst_1
       9: istore_3
      10: iload_3
      11: iconst_4
      12: if_icmpgt     70
      15: aload_2
      16: iload_3
      17: invokevirtual #9                  // Method java/util/regex/Matcher.group:(I)Ljava/lang/String;
      20: astore        4
      22: aload         4
      24: ifnull        35
      27: aload         4
      29: invokevirtual #14                 // Method java/lang/String.length:()I
      32: ifgt          37
      35: iconst_0
      36: ireturn
      37: iconst_0
      38: istore        5
      40: aload         4
      42: invokestatic  #15                 // Method java/lang/Integer.parseInt:(Ljava/lang/String;)I
      45: istore        5
      47: goto          54
      50: astore        6
      52: iconst_0
      53: ireturn
      54: iload         5
      56: sipush        255
      59: if_icmple     64
      62: iconst_0
      63: ireturn
      64: iinc          3, 1
      67: goto          10
      70: iconst_1
      71: ireturn
    Exception table:
       from    to  target type
          40    47    50   Class java/lang/NumberFormatException

  protected boolean isValidSymbolicDomain(java.lang.String);
    Code:
       0: bipush        10
       2: anewarray     #17                 // class java/lang/String
       5: astore_2
       6: iconst_1
       7: istore_3
       8: iconst_0
       9: istore        4
      11: getstatic     #18                 // Field ATOM_PATTERN:Ljava/util/regex/Pattern;
      14: aload_1
      15: invokevirtual #6                  // Method java/util/regex/Pattern.matcher:(Ljava/lang/CharSequence;)Ljava/util/regex/Matcher;
      18: astore        5
      20: iload_3
      21: ifeq          82
      24: aload         5
      26: invokevirtual #7                  // Method java/util/regex/Matcher.matches:()Z
      29: istore_3
      30: iload_3
      31: ifeq          20
      34: aload_2
      35: iload         4
      37: aload         5
      39: iconst_1
      40: invokevirtual #9                  // Method java/util/regex/Matcher.group:(I)Ljava/lang/String;
      43: aastore
      44: aload_2
      45: iload         4
      47: aaload
      48: invokevirtual #14                 // Method java/lang/String.length:()I
      51: iconst_1
      52: iadd
      53: istore        6
      55: iload         6
      57: aload_1
      58: invokevirtual #14                 // Method java/lang/String.length:()I
      61: if_icmplt     69
      64: ldc           #19                 // String
      66: goto          75
      69: aload_1
      70: iload         6
      72: invokevirtual #20                 // Method java/lang/String.substring:(I)Ljava/lang/String;
      75: astore_1
      76: iinc          4, 1
      79: goto          20
      82: iload         4
      84: istore        6
      86: iload         6
      88: iconst_2
      89: if_icmpge     94
      92: iconst_0
      93: ireturn
      94: aload_2
      95: iload         6
      97: iconst_1
      98: isub
      99: aaload
     100: astore        7
     102: aload         7
     104: invokevirtual #14                 // Method java/lang/String.length:()I
     107: iconst_1
     108: if_icmple     127
     111: getstatic     #21                 // Field TLD_PATTERN:Ljava/util/regex/Pattern;
     114: aload         7
     116: invokevirtual #6                  // Method java/util/regex/Pattern.matcher:(Ljava/lang/CharSequence;)Ljava/util/regex/Matcher;
     119: invokevirtual #7                  // Method java/util/regex/Matcher.matches:()Z
     122: ifne          129
     125: iconst_0
     126: ireturn
     127: iconst_0
     128: ireturn
     129: iconst_1
     130: ireturn

  protected java.lang.String stripComments(java.lang.String);
    Code:
       0: aload_1
       1: astore_2
       2: ldc           #22                 // String ^((?:[^\"\\\\]|\\\\.)*(?:\"(?:[^\"\\\\]|\\\\.)*\"(?:[^\"\\\\]|I111\\\\.)*)*)\\((?:[^()\\\\]|\\\\.)*\\)/
       4: astore_3
       5: aload_3
       6: invokestatic  #23                 // Method java/util/regex/Pattern.compile:(Ljava/lang/String;)Ljava/util/regex/Pattern;
       9: astore        4
      11: aload         4
      13: aload_2
      14: invokevirtual #6                  // Method java/util/regex/Pattern.matcher:(Ljava/lang/CharSequence;)Ljava/util/regex/Matcher;
      17: invokevirtual #7                  // Method java/util/regex/Matcher.matches:()Z
      20: ifeq          34
      23: aload_2
      24: aload_3
      25: ldc           #24                 // String \u0001
      27: invokevirtual #25                 // Method java/lang/String.replaceFirst:(Ljava/lang/String;Ljava/lang/String;)Ljava/lang/String;
      30: astore_2
      31: goto          11
      34: aload_2
      35: areturn

  static {};
    Code:
       0: ldc           #26                 // String ^\\[(.*)\\]$
       2: invokestatic  #23                 // Method java/util/regex/Pattern.compile:(Ljava/lang/String;)Ljava/util/regex/Pattern;
       5: putstatic     #5                  // Field IP_DOMAIN_PATTERN:Ljava/util/regex/Pattern;
       8: ldc           #27                 // String ^([a-zA-Z]+)$
      10: invokestatic  #23                 // Method java/util/regex/Pattern.compile:(Ljava/lang/String;)Ljava/util/regex/Pattern;
      13: putstatic     #21                 // Field TLD_PATTERN:Ljava/util/regex/Pattern;
      16: ldc           #28                 // String ^\\s*(([^\\s\\p{Cntrl}\\(\\)<>@,;:\'\\\\\\\"\\.\\[\\]]|\')+|(\"[^\"]*\"))(\\.(([^\\s\\p{Cntrl}\\(\\)<>@,;:\'\\\\\\\"\\.\\[\\]]|\')+|(\"[^\"]*\")))*$
      18: invokestatic  #23                 // Method java/util/regex/Pattern.compile:(Ljava/lang/String;)Ljava/util/regex/Pattern;
      21: putstatic     #13                 // Field USER_PATTERN:Ljava/util/regex/Pattern;
      24: ldc           #29                 // String ^[^\\s\\p{Cntrl}\\(\\)<>@,;:\'\\\\\\\"\\.\\[\\]]+(\\.[^\\s\\p{Cntrl}\\(\\)<>@,;:\'\\\\\\\"\\.\\[\\]]+)*\\s*$
      26: invokestatic  #23                 // Method java/util/regex/Pattern.compile:(Ljava/lang/String;)Ljava/util/regex/Pattern;
      29: putstatic     #11                 // Field DOMAIN_PATTERN:Ljava/util/regex/Pattern;
      32: ldc           #30                 // String ([^\\s\\p{Cntrl}\\(\\)<>@,;:\'\\\\\\\"\\.\\[\\]]+)
      34: invokestatic  #23                 // Method java/util/regex/Pattern.compile:(Ljava/lang/String;)Ljava/util/regex/Pattern;
      37: putstatic     #18                 // Field ATOM_PATTERN:Ljava/util/regex/Pattern;
      40: new           #31                 // class org/apache/commons/validator/EmailValidator
      43: dup
      44: invokespecial #32                 // Method "<init>":()V
      47: putstatic     #1                  // Field EMAIL_VALIDATOR:Lorg/apache/commons/validator/EmailValidator;
      50: return
}
