Compiled from "Form.java"
public class org.apache.commons.validator.Form implements java.io.Serializable {
  private static final long serialVersionUID;

  protected java.lang.String name;

  protected java.util.List<org.apache.commons.validator.Field> lFields;

  protected org.apache.commons.collections.FastHashMap hFields;

  protected java.lang.String inherit;

  private boolean processed;

  public org.apache.commons.validator.Form();
    Code:
       0: aload_0
       1: invokespecial #1                  // Method java/lang/Object."<init>":()V
       4: aload_0
       5: aconst_null
       6: putfield      #2                  // Field name:Ljava/lang/String;
       9: aload_0
      10: new           #3                  // class java/util/ArrayList
      13: dup
      14: invokespecial #4                  // Method java/util/ArrayList."<init>":()V
      17: putfield      #5                  // Field lFields:Ljava/util/List;
      20: aload_0
      21: new           #6                  // class org/apache/commons/collections/FastHashMap
      24: dup
      25: invokespecial #7                  // Method org/apache/commons/collections/FastHashMap."<init>":()V
      28: putfield      #8                  // Field hFields:Lorg/apache/commons/collections/FastHashMap;
      31: aload_0
      32: aconst_null
      33: putfield      #9                  // Field inherit:Ljava/lang/String;
      36: aload_0
      37: iconst_0
      38: putfield      #10                 // Field processed:Z
      41: return

  public java.lang.String getName();
    Code:
       0: aload_0
       1: getfield      #2                  // Field name:Ljava/lang/String;
       4: areturn

  public void setName(java.lang.String);
    Code:
       0: aload_0
       1: aload_1
       2: putfield      #2                  // Field name:Ljava/lang/String;
       5: return

  public void addField(org.apache.commons.validator.Field);
    Code:
       0: aload_0
       1: getfield      #5                  // Field lFields:Ljava/util/List;
       4: aload_1
       5: invokeinterface #11,  2           // InterfaceMethod java/util/List.add:(Ljava/lang/Object;)Z
      10: pop
      11: aload_0
      12: invokevirtual #12                 // Method getFieldMap:()Ljava/util/Map;
      15: aload_1
      16: invokevirtual #13                 // Method org/apache/commons/validator/Field.getKey:()Ljava/lang/String;
      19: aload_1
      20: invokeinterface #14,  3           // InterfaceMethod java/util/Map.put:(Ljava/lang/Object;Ljava/lang/Object;)Ljava/lang/Object;
      25: pop
      26: return

  public java.util.List<org.apache.commons.validator.Field> getFields();
    Code:
       0: aload_0
       1: getfield      #5                  // Field lFields:Ljava/util/List;
       4: invokestatic  #15                 // Method java/util/Collections.unmodifiableList:(Ljava/util/List;)Ljava/util/List;
       7: areturn

  public org.apache.commons.validator.Field getField(java.lang.String);
    Code:
       0: aload_0
       1: invokevirtual #12                 // Method getFieldMap:()Ljava/util/Map;
       4: aload_1
       5: invokeinterface #16,  2           // InterfaceMethod java/util/Map.get:(Ljava/lang/Object;)Ljava/lang/Object;
      10: checkcast     #17                 // class org/apache/commons/validator/Field
      13: areturn

  public boolean containsField(java.lang.String);
    Code:
       0: aload_0
       1: invokevirtual #12                 // Method getFieldMap:()Ljava/util/Map;
       4: aload_1
       5: invokeinterface #18,  2           // InterfaceMethod java/util/Map.containsKey:(Ljava/lang/Object;)Z
      10: ireturn

  protected void merge(org.apache.commons.validator.Form);
    Code:
       0: new           #3                  // class java/util/ArrayList
       3: dup
       4: invokespecial #4                  // Method java/util/ArrayList."<init>":()V
       7: astore_2
       8: new           #6                  // class org/apache/commons/collections/FastHashMap
      11: dup
      12: invokespecial #7                  // Method org/apache/commons/collections/FastHashMap."<init>":()V
      15: astore_3
      16: aload_1
      17: invokevirtual #19                 // Method getFields:()Ljava/util/List;
      20: invokeinterface #20,  1           // InterfaceMethod java/util/List.iterator:()Ljava/util/Iterator;
      25: astore        4
      27: aload         4
      29: invokeinterface #21,  1           // InterfaceMethod java/util/Iterator.hasNext:()Z
      34: ifeq          148
      37: aload         4
      39: invokeinterface #22,  1           // InterfaceMethod java/util/Iterator.next:()Ljava/lang/Object;
      44: checkcast     #17                 // class org/apache/commons/validator/Field
      47: astore        5
      49: aload         5
      51: ifnull        145
      54: aload         5
      56: invokevirtual #13                 // Method org/apache/commons/validator/Field.getKey:()Ljava/lang/String;
      59: astore        6
      61: aload_0
      62: aload         6
      64: invokevirtual #23                 // Method containsField:(Ljava/lang/String;)Z
      67: ifne          93
      70: aload_2
      71: aload         5
      73: invokeinterface #11,  2           // InterfaceMethod java/util/List.add:(Ljava/lang/Object;)Z
      78: pop
      79: aload_3
      80: aload         6
      82: aload         5
      84: invokeinterface #14,  3           // InterfaceMethod java/util/Map.put:(Ljava/lang/Object;Ljava/lang/Object;)Ljava/lang/Object;
      89: pop
      90: goto          145
      93: aload_0
      94: aload         6
      96: invokevirtual #24                 // Method getField:(Ljava/lang/String;)Lorg/apache/commons/validator/Field;
      99: astore        7
     101: aload_0
     102: invokevirtual #12                 // Method getFieldMap:()Ljava/util/Map;
     105: aload         6
     107: invokeinterface #25,  2           // InterfaceMethod java/util/Map.remove:(Ljava/lang/Object;)Ljava/lang/Object;
     112: pop
     113: aload_0
     114: getfield      #5                  // Field lFields:Ljava/util/List;
     117: aload         7
     119: invokeinterface #26,  2           // InterfaceMethod java/util/List.remove:(Ljava/lang/Object;)Z
     124: pop
     125: aload_2
     126: aload         7
     128: invokeinterface #11,  2           // InterfaceMethod java/util/List.add:(Ljava/lang/Object;)Z
     133: pop
     134: aload_3
     135: aload         6
     137: aload         7
     139: invokeinterface #14,  3           // InterfaceMethod java/util/Map.put:(Ljava/lang/Object;Ljava/lang/Object;)Ljava/lang/Object;
     144: pop
     145: goto          27
     148: aload_0
     149: getfield      #5                  // Field lFields:Ljava/util/List;
     152: iconst_0
     153: aload_2
     154: invokeinterface #27,  3           // InterfaceMethod java/util/List.addAll:(ILjava/util/Collection;)Z
     159: pop
     160: aload_0
     161: invokevirtual #12                 // Method getFieldMap:()Ljava/util/Map;
     164: aload_3
     165: invokeinterface #28,  2           // InterfaceMethod java/util/Map.putAll:(Ljava/util/Map;)V
     170: return

  protected void process(java.util.Map<java.lang.String, java.lang.String>, java.util.Map<java.lang.String, java.lang.String>, java.util.Map<java.lang.String, org.apache.commons.validator.Form>);
    Code:
       0: aload_0
       1: invokevirtual #29                 // Method isProcessed:()Z
       4: ifeq          8
       7: return
       8: iconst_0
       9: istore        4
      11: aload_0
      12: invokevirtual #30                 // Method isExtending:()Z
      15: ifeq          141
      18: aload_3
      19: aload_0
      20: getfield      #9                  // Field inherit:Ljava/lang/String;
      23: invokeinterface #16,  2           // InterfaceMethod java/util/Map.get:(Ljava/lang/Object;)Ljava/lang/Object;
      28: checkcast     #31                 // class org/apache/commons/validator/Form
      31: astore        5
      33: aload         5
      35: ifnull        141
      38: aload         5
      40: invokevirtual #29                 // Method isProcessed:()Z
      43: ifne          54
      46: aload         5
      48: aload_2
      49: aload_1
      50: aload_3
      51: invokevirtual #32                 // Method process:(Ljava/util/Map;Ljava/util/Map;Ljava/util/Map;)V
      54: aload         5
      56: invokevirtual #19                 // Method getFields:()Ljava/util/List;
      59: invokeinterface #20,  1           // InterfaceMethod java/util/List.iterator:()Ljava/util/Iterator;
      64: astore        6
      66: aload         6
      68: invokeinterface #21,  1           // InterfaceMethod java/util/Iterator.hasNext:()Z
      73: ifeq          141
      76: aload         6
      78: invokeinterface #22,  1           // InterfaceMethod java/util/Iterator.next:()Ljava/lang/Object;
      83: checkcast     #17                 // class org/apache/commons/validator/Field
      86: astore        7
      88: aload_0
      89: invokevirtual #12                 // Method getFieldMap:()Ljava/util/Map;
      92: aload         7
      94: invokevirtual #13                 // Method org/apache/commons/validator/Field.getKey:()Ljava/lang/String;
      97: invokeinterface #16,  2           // InterfaceMethod java/util/Map.get:(Ljava/lang/Object;)Ljava/lang/Object;
     102: ifnonnull     138
     105: aload_0
     106: getfield      #5                  // Field lFields:Ljava/util/List;
     109: iload         4
     111: aload         7
     113: invokeinterface #33,  3           // InterfaceMethod java/util/List.add:(ILjava/lang/Object;)V
     118: aload_0
     119: invokevirtual #12                 // Method getFieldMap:()Ljava/util/Map;
     122: aload         7
     124: invokevirtual #13                 // Method org/apache/commons/validator/Field.getKey:()Ljava/lang/String;
     127: aload         7
     129: invokeinterface #14,  3           // InterfaceMethod java/util/Map.put:(Ljava/lang/Object;Ljava/lang/Object;)Ljava/lang/Object;
     134: pop
     135: iinc          4, 1
     138: goto          66
     141: aload_0
     142: getfield      #8                  // Field hFields:Lorg/apache/commons/collections/FastHashMap;
     145: iconst_1
     146: invokevirtual #34                 // Method org/apache/commons/collections/FastHashMap.setFast:(Z)V
     149: aload_0
     150: getfield      #5                  // Field lFields:Ljava/util/List;
     153: iload         4
     155: invokeinterface #35,  2           // InterfaceMethod java/util/List.listIterator:(I)Ljava/util/ListIterator;
     160: astore        5
     162: aload         5
     164: invokeinterface #21,  1           // InterfaceMethod java/util/Iterator.hasNext:()Z
     169: ifeq          194
     172: aload         5
     174: invokeinterface #22,  1           // InterfaceMethod java/util/Iterator.next:()Ljava/lang/Object;
     179: checkcast     #17                 // class org/apache/commons/validator/Field
     182: astore        6
     184: aload         6
     186: aload_1
     187: aload_2
     188: invokevirtual #36                 // Method org/apache/commons/validator/Field.process:(Ljava/util/Map;Ljava/util/Map;)V
     191: goto          162
     194: aload_0
     195: iconst_1
     196: putfield      #10                 // Field processed:Z
     199: return

  public java.lang.String toString();
    Code:
       0: new           #37                 // class java/lang/StringBuilder
       3: dup
       4: invokespecial #38                 // Method java/lang/StringBuilder."<init>":()V
       7: astore_1
       8: aload_1
       9: ldc           #39                 // String Form:
      11: invokevirtual #40                 // Method java/lang/StringBuilder.append:(Ljava/lang/String;)Ljava/lang/StringBuilder;
      14: pop
      15: aload_1
      16: aload_0
      17: getfield      #2                  // Field name:Ljava/lang/String;
      20: invokevirtual #40                 // Method java/lang/StringBuilder.append:(Ljava/lang/String;)Ljava/lang/StringBuilder;
      23: pop
      24: aload_1
      25: ldc           #41                 // String \n
      27: invokevirtual #40                 // Method java/lang/StringBuilder.append:(Ljava/lang/String;)Ljava/lang/StringBuilder;
      30: pop
      31: aload_0
      32: getfield      #5                  // Field lFields:Ljava/util/List;
      35: invokeinterface #20,  1           // InterfaceMethod java/util/List.iterator:()Ljava/util/Iterator;
      40: astore_2
      41: aload_2
      42: invokeinterface #21,  1           // InterfaceMethod java/util/Iterator.hasNext:()Z
      47: ifeq          78
      50: aload_1
      51: ldc           #42                 // String \tField: \n
      53: invokevirtual #40                 // Method java/lang/StringBuilder.append:(Ljava/lang/String;)Ljava/lang/StringBuilder;
      56: pop
      57: aload_1
      58: aload_2
      59: invokeinterface #22,  1           // InterfaceMethod java/util/Iterator.next:()Ljava/lang/Object;
      64: invokevirtual #43                 // Method java/lang/StringBuilder.append:(Ljava/lang/Object;)Ljava/lang/StringBuilder;
      67: pop
      68: aload_1
      69: ldc           #41                 // String \n
      71: invokevirtual #40                 // Method java/lang/StringBuilder.append:(Ljava/lang/String;)Ljava/lang/StringBuilder;
      74: pop
      75: goto          41
      78: aload_1
      79: invokevirtual #44                 // Method java/lang/StringBuilder.toString:()Ljava/lang/String;
      82: areturn

  org.apache.commons.validator.ValidatorResults validate(java.util.Map<java.lang.String, java.lang.Object>, java.util.Map<java.lang.String, org.apache.commons.validator.ValidatorAction>, int) throws org.apache.commons.validator.ValidatorException;
    Code:
       0: aload_0
       1: aload_1
       2: aload_2
       3: iload_3
       4: aconst_null
       5: invokevirtual #45                 // Method validate:(Ljava/util/Map;Ljava/util/Map;ILjava/lang/String;)Lorg/apache/commons/validator/ValidatorResults;
       8: areturn

  org.apache.commons.validator.ValidatorResults validate(java.util.Map<java.lang.String, java.lang.Object>, java.util.Map<java.lang.String, org.apache.commons.validator.ValidatorAction>, int, java.lang.String) throws org.apache.commons.validator.ValidatorException;
    Code:
       0: new           #46                 // class org/apache/commons/validator/ValidatorResults
       3: dup
       4: invokespecial #47                 // Method org/apache/commons/validator/ValidatorResults."<init>":()V
       7: astore        5
       9: aload_1
      10: ldc           #48                 // String org.apache.commons.validator.ValidatorResults
      12: aload         5
      14: invokeinterface #14,  3           // InterfaceMethod java/util/Map.put:(Ljava/lang/Object;Ljava/lang/Object;)Ljava/lang/Object;
      19: pop
      20: aload         4
      22: ifnull        121
      25: aload_0
      26: invokevirtual #12                 // Method getFieldMap:()Ljava/util/Map;
      29: aload         4
      31: invokeinterface #16,  2           // InterfaceMethod java/util/Map.get:(Ljava/lang/Object;)Ljava/lang/Object;
      36: checkcast     #17                 // class org/apache/commons/validator/Field
      39: astore        6
      41: aload         6
      43: ifnonnull     86
      46: new           #49                 // class org/apache/commons/validator/ValidatorException
      49: dup
      50: new           #37                 // class java/lang/StringBuilder
      53: dup
      54: invokespecial #38                 // Method java/lang/StringBuilder."<init>":()V
      57: ldc           #50                 // String Unknown field
      59: invokevirtual #40                 // Method java/lang/StringBuilder.append:(Ljava/lang/String;)Ljava/lang/StringBuilder;
      62: aload         4
      64: invokevirtual #40                 // Method java/lang/StringBuilder.append:(Ljava/lang/String;)Ljava/lang/StringBuilder;
      67: ldc           #51                 // String  in form
      69: invokevirtual #40                 // Method java/lang/StringBuilder.append:(Ljava/lang/String;)Ljava/lang/StringBuilder;
      72: aload_0
      73: invokevirtual #52                 // Method getName:()Ljava/lang/String;
      76: invokevirtual #40                 // Method java/lang/StringBuilder.append:(Ljava/lang/String;)Ljava/lang/StringBuilder;
      79: invokevirtual #44                 // Method java/lang/StringBuilder.toString:()Ljava/lang/String;
      82: invokespecial #53                 // Method org/apache/commons/validator/ValidatorException."<init>":(Ljava/lang/String;)V
      85: athrow
      86: aload_1
      87: ldc           #54                 // String org.apache.commons.validator.Field
      89: aload         6
      91: invokeinterface #14,  3           // InterfaceMethod java/util/Map.put:(Ljava/lang/Object;Ljava/lang/Object;)Ljava/lang/Object;
      96: pop
      97: aload         6
      99: invokevirtual #55                 // Method org/apache/commons/validator/Field.getPage:()I
     102: iload_3
     103: if_icmpgt     118
     106: aload         5
     108: aload         6
     110: aload_1
     111: aload_2
     112: invokevirtual #56                 // Method org/apache/commons/validator/Field.validate:(Ljava/util/Map;Ljava/util/Map;)Lorg/apache/commons/validator/ValidatorResults;
     115: invokevirtual #57                 // Method org/apache/commons/validator/ValidatorResults.merge:(Lorg/apache/commons/validator/ValidatorResults;)V
     118: goto          189
     121: aload_0
     122: getfield      #5                  // Field lFields:Ljava/util/List;
     125: invokeinterface #20,  1           // InterfaceMethod java/util/List.iterator:()Ljava/util/Iterator;
     130: astore        6
     132: aload         6
     134: invokeinterface #21,  1           // InterfaceMethod java/util/Iterator.hasNext:()Z
     139: ifeq          189
     142: aload         6
     144: invokeinterface #22,  1           // InterfaceMethod java/util/Iterator.next:()Ljava/lang/Object;
     149: checkcast     #17                 // class org/apache/commons/validator/Field
     152: astore        7
     154: aload_1
     155: ldc           #54                 // String org.apache.commons.validator.Field
     157: aload         7
     159: invokeinterface #14,  3           // InterfaceMethod java/util/Map.put:(Ljava/lang/Object;Ljava/lang/Object;)Ljava/lang/Object;
     164: pop
     165: aload         7
     167: invokevirtual #55                 // Method org/apache/commons/validator/Field.getPage:()I
     170: iload_3
     171: if_icmpgt     186
     174: aload         5
     176: aload         7
     178: aload_1
     179: aload_2
     180: invokevirtual #56                 // Method org/apache/commons/validator/Field.validate:(Ljava/util/Map;Ljava/util/Map;)Lorg/apache/commons/validator/ValidatorResults;
     183: invokevirtual #57                 // Method org/apache/commons/validator/ValidatorResults.merge:(Lorg/apache/commons/validator/ValidatorResults;)V
     186: goto          132
     189: aload         5
     191: areturn

  public boolean isProcessed();
    Code:
       0: aload_0
       1: getfield      #10                 // Field processed:Z
       4: ireturn

  public java.lang.String getExtends();
    Code:
       0: aload_0
       1: getfield      #9                  // Field inherit:Ljava/lang/String;
       4: areturn

  public void setExtends(java.lang.String);
    Code:
       0: aload_0
       1: aload_1
       2: putfield      #9                  // Field inherit:Ljava/lang/String;
       5: return

  public boolean isExtending();
    Code:
       0: aload_0
       1: getfield      #9                  // Field inherit:Ljava/lang/String;
       4: ifnull        11
       7: iconst_1
       8: goto          12
      11: iconst_0
      12: ireturn

  protected java.util.Map<java.lang.String, org.apache.commons.validator.Field> getFieldMap();
    Code:
       0: aload_0
       1: getfield      #8                  // Field hFields:Lorg/apache/commons/collections/FastHashMap;
       4: areturn
}
