Compiled from "typeCodecs.scala"
public interface morphir.ir.codec.typeCodecs$TypeCodec {
  public static upickle.core.Types$ReadWriter readWriter$(morphir.ir.codec.typeCodecs$TypeCodec, upickle.core.Types$ReadWriter);
    Code:
       0: aload_0
       1: aload_1
       2: invokespecial #98                 // InterfaceMethod readWriter:(Lupickle/core/Types$ReadWriter;)Lupickle/core/Types$ReadWriter;
       5: areturn

  public default <A> upickle.core.Types$ReadWriter<morphir.ir.Type<A>> readWriter(upickle.core.Types$ReadWriter<A>);
    Code:
       0: getstatic     #107                // Field upickle/default$.MODULE$:Lupickle/default$;
       3: getstatic     #107                // Field upickle/default$.MODULE$:Lupickle/default$;
       6: invokevirtual #110                // Method upickle/default$.ReadWriter:()Lupickle/core/Types$ReadWriter$;
       9: getstatic     #107                // Field upickle/default$.MODULE$:Lupickle/default$;
      12: invokevirtual #114                // Method upickle/default$.JsValueR:()Lupickle/core/Types$Reader;
      15: getstatic     #107                // Field upickle/default$.MODULE$:Lupickle/default$;
      18: invokevirtual #118                // Method upickle/default$.JsValueW:()Lupickle/core/Types$Writer;
      21: invokevirtual #122                // Method upickle/core/Types$ReadWriter$.join:(Lupickle/core/Types$Reader;Lupickle/core/Types$Writer;)Lupickle/core/Types$ReadWriter;
      24: invokevirtual #125                // Method upickle/default$.readwriter:(Lupickle/core/Types$ReadWriter;)Lupickle/core/Types$ReadWriter;
      27: aload_1
      28: invokedynamic #147,  0            // InvokeDynamic #0:apply:(Lupickle/core/Types$ReadWriter;)Lscala/Function1;
      33: aload_1
      34: invokedynamic #155,  0            // InvokeDynamic #1:apply:(Lupickle/core/Types$ReadWriter;)Lscala/Function1;
      39: invokeinterface #159,  3          // InterfaceMethod upickle/core/Types$ReadWriter.bimap:(Lscala/Function1;Lscala/Function1;)Lupickle/core/Types$ReadWriter;
      44: areturn

  public static ujson.Value $anonfun$readWriter$1(upickle.core.Types$ReadWriter, morphir.ir.Type);
    Code:
       0: aload_1
       1: astore_3
       2: aload_3
       3: instanceof    #50                 // class morphir/ir/Type$Variable
       6: ifeq          34
       9: aload_3
      10: checkcast     #50                 // class morphir/ir/Type$Variable
      13: astore        4
      15: getstatic     #107                // Field upickle/default$.MODULE$:Lupickle/default$;
      18: aload         4
      20: getstatic     #165                // Field morphir/ir/Type$Variable$.MODULE$:Lmorphir/ir/Type$Variable$;
      23: aload_0
      24: invokevirtual #166                // Method morphir/ir/Type$Variable$.readWriter:(Lupickle/core/Types$ReadWriter;)Lupickle/core/Types$ReadWriter;
      27: invokevirtual #170                // Method upickle/default$.writeJs:(Ljava/lang/Object;Lupickle/core/Types$Writer;)Lujson/Value;
      30: astore_2
      31: goto          256
      34: goto          37
      37: aload_3
      38: instanceof    #32                 // class morphir/ir/Type$Reference
      41: ifeq          69
      44: aload_3
      45: checkcast     #32                 // class morphir/ir/Type$Reference
      48: astore        5
      50: getstatic     #107                // Field upickle/default$.MODULE$:Lupickle/default$;
      53: aload         5
      55: getstatic     #173                // Field morphir/ir/Type$Reference$.MODULE$:Lmorphir/ir/Type$Reference$;
      58: aload_0
      59: invokevirtual #174                // Method morphir/ir/Type$Reference$.readWriter:(Lupickle/core/Types$ReadWriter;)Lupickle/core/Types$ReadWriter;
      62: invokevirtual #170                // Method upickle/default$.writeJs:(Ljava/lang/Object;Lupickle/core/Types$Writer;)Lujson/Value;
      65: astore_2
      66: goto          256
      69: goto          72
      72: aload_3
      73: instanceof    #38                 // class morphir/ir/Type$Tuple
      76: ifeq          104
      79: aload_3
      80: checkcast     #38                 // class morphir/ir/Type$Tuple
      83: astore        6
      85: getstatic     #107                // Field upickle/default$.MODULE$:Lupickle/default$;
      88: aload         6
      90: getstatic     #177                // Field morphir/ir/Type$Tuple$.MODULE$:Lmorphir/ir/Type$Tuple$;
      93: aload_0
      94: invokevirtual #178                // Method morphir/ir/Type$Tuple$.readWriter:(Lupickle/core/Types$ReadWriter;)Lupickle/core/Types$ReadWriter;
      97: invokevirtual #170                // Method upickle/default$.writeJs:(Ljava/lang/Object;Lupickle/core/Types$Writer;)Lujson/Value;
     100: astore_2
     101: goto          256
     104: goto          107
     107: aload_3
     108: instanceof    #26                 // class morphir/ir/Type$Record
     111: ifeq          139
     114: aload_3
     115: checkcast     #26                 // class morphir/ir/Type$Record
     118: astore        7
     120: getstatic     #107                // Field upickle/default$.MODULE$:Lupickle/default$;
     123: aload         7
     125: getstatic     #181                // Field morphir/ir/Type$Record$.MODULE$:Lmorphir/ir/Type$Record$;
     128: aload_0
     129: invokevirtual #182                // Method morphir/ir/Type$Record$.readWriter:(Lupickle/core/Types$ReadWriter;)Lupickle/core/Types$ReadWriter;
     132: invokevirtual #170                // Method upickle/default$.writeJs:(Ljava/lang/Object;Lupickle/core/Types$Writer;)Lujson/Value;
     135: astore_2
     136: goto          256
     139: goto          142
     142: aload_3
     143: instanceof    #12                 // class morphir/ir/Type$ExtensibleRecord
     146: ifeq          174
     149: aload_3
     150: checkcast     #12                 // class morphir/ir/Type$ExtensibleRecord
     153: astore        8
     155: getstatic     #107                // Field upickle/default$.MODULE$:Lupickle/default$;
     158: aload         8
     160: getstatic     #185                // Field morphir/ir/Type$ExtensibleRecord$.MODULE$:Lmorphir/ir/Type$ExtensibleRecord$;
     163: aload_0
     164: invokevirtual #186                // Method morphir/ir/Type$ExtensibleRecord$.readWriter:(Lupickle/core/Types$ReadWriter;)Lupickle/core/Types$ReadWriter;
     167: invokevirtual #170                // Method upickle/default$.writeJs:(Ljava/lang/Object;Lupickle/core/Types$Writer;)Lujson/Value;
     170: astore_2
     171: goto          256
     174: goto          177
     177: aload_3
     178: instanceof    #20                 // class morphir/ir/Type$Function
     181: ifeq          209
     184: aload_3
     185: checkcast     #20                 // class morphir/ir/Type$Function
     188: astore        9
     190: getstatic     #107                // Field upickle/default$.MODULE$:Lupickle/default$;
     193: aload         9
     195: getstatic     #189                // Field morphir/ir/Type$Function$.MODULE$:Lmorphir/ir/Type$Function$;
     198: aload_0
     199: invokevirtual #190                // Method morphir/ir/Type$Function$.readWriter:(Lupickle/core/Types$ReadWriter;)Lupickle/core/Types$ReadWriter;
     202: invokevirtual #170                // Method upickle/default$.writeJs:(Ljava/lang/Object;Lupickle/core/Types$Writer;)Lujson/Value;
     205: astore_2
     206: goto          256
     209: goto          212
     212: aload_3
     213: instanceof    #44                 // class morphir/ir/Type$Unit
     216: ifeq          244
     219: aload_3
     220: checkcast     #44                 // class morphir/ir/Type$Unit
     223: astore        10
     225: getstatic     #107                // Field upickle/default$.MODULE$:Lupickle/default$;
     228: aload         10
     230: getstatic     #193                // Field morphir/ir/Type$Unit$.MODULE$:Lmorphir/ir/Type$Unit$;
     233: aload_0
     234: invokevirtual #194                // Method morphir/ir/Type$Unit$.readWriter:(Lupickle/core/Types$ReadWriter;)Lupickle/core/Types$ReadWriter;
     237: invokevirtual #170                // Method upickle/default$.writeJs:(Ljava/lang/Object;Lupickle/core/Types$Writer;)Lujson/Value;
     240: astore_2
     241: goto          256
     244: goto          247
     247: new           #196                // class scala/MatchError
     250: dup
     251: aload_3
     252: invokespecial #200                // Method scala/MatchError."<init>":(Ljava/lang/Object;)V
     255: athrow
     256: aload_2
     257: areturn

  public static morphir.ir.Type $anonfun$readWriter$2(upickle.core.Types$ReadWriter, ujson.Value);
    Code:
       0: aload_1
       1: getstatic     #205                // Field ujson/Value$Selector$.MODULE$:Lujson/Value$Selector$;
       4: iconst_0
       5: invokevirtual #208                // Method ujson/Value$Selector$.IntSelector:(I)Lujson/Value$Selector$IntSelector;
       8: invokeinterface #211,  2          // InterfaceMethod ujson/Value.apply:(Lujson/Value$Selector;)Lujson/Value;
      13: invokeinterface #215,  1          // InterfaceMethod ujson/Value.str:()Ljava/lang/String;
      18: astore_3
      19: aload_3
      20: astore        4
      22: aload         4
      24: ifnonnull     31
      27: iconst_0
      28: goto          36
      31: aload         4
      33: invokevirtual #221                // Method java/lang/String.hashCode:()I
      36: lookupswitch  { // 0
               default: 48
          }
      48: goto          51
      51: aload         4
      53: getstatic     #165                // Field morphir/ir/Type$Variable$.MODULE$:Lmorphir/ir/Type$Variable$;
      56: invokevirtual #224                // Method morphir/ir/Type$Variable$.Tag:()Ljava/lang/String;
      59: astore        5
      61: dup
      62: ifnonnull     74
      65: pop
      66: aload         5
      68: ifnull        82
      71: goto          102
      74: aload         5
      76: invokevirtual #228                // Method java/lang/Object.equals:(Ljava/lang/Object;)Z
      79: ifeq          102
      82: getstatic     #107                // Field upickle/default$.MODULE$:Lupickle/default$;
      85: aload_1
      86: getstatic     #165                // Field morphir/ir/Type$Variable$.MODULE$:Lmorphir/ir/Type$Variable$;
      89: aload_0
      90: invokevirtual #166                // Method morphir/ir/Type$Variable$.readWriter:(Lupickle/core/Types$ReadWriter;)Lupickle/core/Types$ReadWriter;
      93: invokevirtual #232                // Method upickle/default$.read:(Lujson/Readable;Lupickle/core/Types$Reader;)Ljava/lang/Object;
      96: checkcast     #14                 // class morphir/ir/Type
      99: goto          491
     102: aload         4
     104: getstatic     #173                // Field morphir/ir/Type$Reference$.MODULE$:Lmorphir/ir/Type$Reference$;
     107: invokevirtual #233                // Method morphir/ir/Type$Reference$.Tag:()Ljava/lang/String;
     110: astore        6
     112: dup
     113: ifnonnull     125
     116: pop
     117: aload         6
     119: ifnull        133
     122: goto          153
     125: aload         6
     127: invokevirtual #228                // Method java/lang/Object.equals:(Ljava/lang/Object;)Z
     130: ifeq          153
     133: getstatic     #107                // Field upickle/default$.MODULE$:Lupickle/default$;
     136: aload_1
     137: getstatic     #173                // Field morphir/ir/Type$Reference$.MODULE$:Lmorphir/ir/Type$Reference$;
     140: aload_0
     141: invokevirtual #174                // Method morphir/ir/Type$Reference$.readWriter:(Lupickle/core/Types$ReadWriter;)Lupickle/core/Types$ReadWriter;
     144: invokevirtual #232                // Method upickle/default$.read:(Lujson/Readable;Lupickle/core/Types$Reader;)Ljava/lang/Object;
     147: checkcast     #14                 // class morphir/ir/Type
     150: goto          491
     153: aload         4
     155: getstatic     #177                // Field morphir/ir/Type$Tuple$.MODULE$:Lmorphir/ir/Type$Tuple$;
     158: invokevirtual #234                // Method morphir/ir/Type$Tuple$.Tag:()Ljava/lang/String;
     161: astore        7
     163: dup
     164: ifnonnull     176
     167: pop
     168: aload         7
     170: ifnull        184
     173: goto          204
     176: aload         7
     178: invokevirtual #228                // Method java/lang/Object.equals:(Ljava/lang/Object;)Z
     181: ifeq          204
     184: getstatic     #107                // Field upickle/default$.MODULE$:Lupickle/default$;
     187: aload_1
     188: getstatic     #177                // Field morphir/ir/Type$Tuple$.MODULE$:Lmorphir/ir/Type$Tuple$;
     191: aload_0
     192: invokevirtual #178                // Method morphir/ir/Type$Tuple$.readWriter:(Lupickle/core/Types$ReadWriter;)Lupickle/core/Types$ReadWriter;
     195: invokevirtual #232                // Method upickle/default$.read:(Lujson/Readable;Lupickle/core/Types$Reader;)Ljava/lang/Object;
     198: checkcast     #14                 // class morphir/ir/Type
     201: goto          491
     204: aload         4
     206: getstatic     #181                // Field morphir/ir/Type$Record$.MODULE$:Lmorphir/ir/Type$Record$;
     209: invokevirtual #235                // Method morphir/ir/Type$Record$.Tag:()Ljava/lang/String;
     212: astore        8
     214: dup
     215: ifnonnull     227
     218: pop
     219: aload         8
     221: ifnull        235
     224: goto          255
     227: aload         8
     229: invokevirtual #228                // Method java/lang/Object.equals:(Ljava/lang/Object;)Z
     232: ifeq          255
     235: getstatic     #107                // Field upickle/default$.MODULE$:Lupickle/default$;
     238: aload_1
     239: getstatic     #181                // Field morphir/ir/Type$Record$.MODULE$:Lmorphir/ir/Type$Record$;
     242: aload_0
     243: invokevirtual #182                // Method morphir/ir/Type$Record$.readWriter:(Lupickle/core/Types$ReadWriter;)Lupickle/core/Types$ReadWriter;
     246: invokevirtual #232                // Method upickle/default$.read:(Lujson/Readable;Lupickle/core/Types$Reader;)Ljava/lang/Object;
     249: checkcast     #14                 // class morphir/ir/Type
     252: goto          491
     255: aload         4
     257: getstatic     #185                // Field morphir/ir/Type$ExtensibleRecord$.MODULE$:Lmorphir/ir/Type$ExtensibleRecord$;
     260: invokevirtual #236                // Method morphir/ir/Type$ExtensibleRecord$.Tag:()Ljava/lang/String;
     263: astore        9
     265: dup
     266: ifnonnull     278
     269: pop
     270: aload         9
     272: ifnull        286
     275: goto          306
     278: aload         9
     280: invokevirtual #228                // Method java/lang/Object.equals:(Ljava/lang/Object;)Z
     283: ifeq          306
     286: getstatic     #107                // Field upickle/default$.MODULE$:Lupickle/default$;
     289: aload_1
     290: getstatic     #185                // Field morphir/ir/Type$ExtensibleRecord$.MODULE$:Lmorphir/ir/Type$ExtensibleRecord$;
     293: aload_0
     294: invokevirtual #186                // Method morphir/ir/Type$ExtensibleRecord$.readWriter:(Lupickle/core/Types$ReadWriter;)Lupickle/core/Types$ReadWriter;
     297: invokevirtual #232                // Method upickle/default$.read:(Lujson/Readable;Lupickle/core/Types$Reader;)Ljava/lang/Object;
     300: checkcast     #14                 // class morphir/ir/Type
     303: goto          491
     306: aload         4
     308: getstatic     #189                // Field morphir/ir/Type$Function$.MODULE$:Lmorphir/ir/Type$Function$;
     311: invokevirtual #237                // Method morphir/ir/Type$Function$.Tag:()Ljava/lang/String;
     314: astore        10
     316: dup
     317: ifnonnull     329
     320: pop
     321: aload         10
     323: ifnull        337
     326: goto          357
     329: aload         10
     331: invokevirtual #228                // Method java/lang/Object.equals:(Ljava/lang/Object;)Z
     334: ifeq          357
     337: getstatic     #107                // Field upickle/default$.MODULE$:Lupickle/default$;
     340: aload_1
     341: getstatic     #189                // Field morphir/ir/Type$Function$.MODULE$:Lmorphir/ir/Type$Function$;
     344: aload_0
     345: invokevirtual #190                // Method morphir/ir/Type$Function$.readWriter:(Lupickle/core/Types$ReadWriter;)Lupickle/core/Types$ReadWriter;
     348: invokevirtual #232                // Method upickle/default$.read:(Lujson/Readable;Lupickle/core/Types$Reader;)Ljava/lang/Object;
     351: checkcast     #14                 // class morphir/ir/Type
     354: goto          491
     357: aload         4
     359: getstatic     #193                // Field morphir/ir/Type$Unit$.MODULE$:Lmorphir/ir/Type$Unit$;
     362: invokevirtual #238                // Method morphir/ir/Type$Unit$.Tag:()Ljava/lang/String;
     365: astore        11
     367: dup
     368: ifnonnull     380
     371: pop
     372: aload         11
     374: ifnull        388
     377: goto          408
     380: aload         11
     382: invokevirtual #228                // Method java/lang/Object.equals:(Ljava/lang/Object;)Z
     385: ifeq          408
     388: getstatic     #107                // Field upickle/default$.MODULE$:Lupickle/default$;
     391: aload_1
     392: getstatic     #193                // Field morphir/ir/Type$Unit$.MODULE$:Lmorphir/ir/Type$Unit$;
     395: aload_0
     396: invokevirtual #194                // Method morphir/ir/Type$Unit$.readWriter:(Lupickle/core/Types$ReadWriter;)Lupickle/core/Types$ReadWriter;
     399: invokevirtual #232                // Method upickle/default$.read:(Lujson/Readable;Lupickle/core/Types$Reader;)Ljava/lang/Object;
     402: checkcast     #14                 // class morphir/ir/Type
     405: goto          491
     408: getstatic     #241                // Field morphir/ir/json/Decode$DecodeError$.MODULE$:Lmorphir/ir/json/Decode$DecodeError$;
     411: aload         4
     413: getstatic     #165                // Field morphir/ir/Type$Variable$.MODULE$:Lmorphir/ir/Type$Variable$;
     416: invokevirtual #224                // Method morphir/ir/Type$Variable$.Tag:()Ljava/lang/String;
     419: getstatic     #246                // Field scala/runtime/ScalaRunTime$.MODULE$:Lscala/runtime/ScalaRunTime$;
     422: bipush        6
     424: anewarray     #217                // class java/lang/String
     427: dup
     428: iconst_0
     429: getstatic     #173                // Field morphir/ir/Type$Reference$.MODULE$:Lmorphir/ir/Type$Reference$;
     432: invokevirtual #233                // Method morphir/ir/Type$Reference$.Tag:()Ljava/lang/String;
     435: aastore
     436: dup
     437: iconst_1
     438: getstatic     #177                // Field morphir/ir/Type$Tuple$.MODULE$:Lmorphir/ir/Type$Tuple$;
     441: invokevirtual #234                // Method morphir/ir/Type$Tuple$.Tag:()Ljava/lang/String;
     444: aastore
     445: dup
     446: iconst_2
     447: getstatic     #181                // Field morphir/ir/Type$Record$.MODULE$:Lmorphir/ir/Type$Record$;
     450: invokevirtual #235                // Method morphir/ir/Type$Record$.Tag:()Ljava/lang/String;
     453: aastore
     454: dup
     455: iconst_3
     456: getstatic     #185                // Field morphir/ir/Type$ExtensibleRecord$.MODULE$:Lmorphir/ir/Type$ExtensibleRecord$;
     459: invokevirtual #236                // Method morphir/ir/Type$ExtensibleRecord$.Tag:()Ljava/lang/String;
     462: aastore
     463: dup
     464: iconst_4
     465: getstatic     #189                // Field morphir/ir/Type$Function$.MODULE$:Lmorphir/ir/Type$Function$;
     468: invokevirtual #237                // Method morphir/ir/Type$Function$.Tag:()Ljava/lang/String;
     471: aastore
     472: dup
     473: iconst_5
     474: getstatic     #193                // Field morphir/ir/Type$Unit$.MODULE$:Lmorphir/ir/Type$Unit$;
     477: invokevirtual #238                // Method morphir/ir/Type$Unit$.Tag:()Ljava/lang/String;
     480: aastore
     481: checkcast     #248                // class "[Ljava/lang/Object;"
     484: invokevirtual #252                // Method scala/runtime/ScalaRunTime$.wrapRefArray:([Ljava/lang/Object;)Lscala/collection/immutable/ArraySeq;
     487: invokevirtual #256                // Method morphir/ir/json/Decode$DecodeError$.unexpectedTag:(Ljava/lang/String;Ljava/lang/String;Lscala/collection/immutable/Seq;)Lmorphir/ir/json/Decode$DecodeError$UnexpectedTag;
     490: athrow
     491: astore_2
     492: goto          495
     495: aload_2
     496: areturn

  public static void $init$(morphir.ir.codec.typeCodecs$TypeCodec);
    Code:
       0: return

  private static java.lang.Object $deserializeLambda$(java.lang.invoke.SerializedLambda);
    Code:
       0: aload_0
       1: invokedynamic #273,  0            // InvokeDynamic #2:lambdaDeserialize:(Ljava/lang/invoke/SerializedLambda;)Ljava/lang/Object;
       6: areturn
}
