Compiled from "typeCodecs.scala"
public interface morphir.ir.codec.typeCodecs$FieldCodec {
  public static upickle.core.Types$ReadWriter readWriter$(morphir.ir.codec.typeCodecs$FieldCodec, upickle.core.Types$ReadWriter);
    Code:
       0: aload_0
       1: aload_1
       2: invokespecial #54                 // InterfaceMethod readWriter:(Lupickle/core/Types$ReadWriter;)Lupickle/core/Types$ReadWriter;
       5: areturn

  public default <A> upickle.core.Types$ReadWriter<morphir.ir.Type$Field<A>> readWriter(upickle.core.Types$ReadWriter<A>);
    Code:
       0: getstatic     #63                 // Field upickle/default$.MODULE$:Lupickle/default$;
       3: getstatic     #63                 // Field upickle/default$.MODULE$:Lupickle/default$;
       6: invokevirtual #66                 // Method upickle/default$.ReadWriter:()Lupickle/core/Types$ReadWriter$;
       9: getstatic     #63                 // Field upickle/default$.MODULE$:Lupickle/default$;
      12: getstatic     #69                 // Field morphir/ir/name$Name$.MODULE$:Lmorphir/ir/name$Name$;
      15: invokevirtual #73                 // Method morphir/ir/name$Name$.nameReadWriter:()Lupickle/core/Types$ReadWriter;
      18: getstatic     #78                 // Field morphir/ir/Type$.MODULE$:Lmorphir/ir/Type$;
      21: aload_1
      22: invokevirtual #79                 // Method morphir/ir/Type$.readWriter:(Lupickle/core/Types$ReadWriter;)Lupickle/core/Types$ReadWriter;
      25: invokevirtual #83                 // Method upickle/default$.Tuple2Reader:(Lupickle/core/Types$Reader;Lupickle/core/Types$Reader;)Lupickle/core/Types$TupleNReader;
      28: getstatic     #63                 // Field upickle/default$.MODULE$:Lupickle/default$;
      31: getstatic     #69                 // Field morphir/ir/name$Name$.MODULE$:Lmorphir/ir/name$Name$;
      34: invokevirtual #73                 // Method morphir/ir/name$Name$.nameReadWriter:()Lupickle/core/Types$ReadWriter;
      37: getstatic     #78                 // Field morphir/ir/Type$.MODULE$:Lmorphir/ir/Type$;
      40: aload_1
      41: invokevirtual #79                 // Method morphir/ir/Type$.readWriter:(Lupickle/core/Types$ReadWriter;)Lupickle/core/Types$ReadWriter;
      44: invokevirtual #87                 // Method upickle/default$.Tuple2Writer:(Lupickle/core/Types$Writer;Lupickle/core/Types$Writer;)Lupickle/core/Types$TupleNWriter;
      47: invokevirtual #91                 // Method upickle/core/Types$ReadWriter$.join:(Lupickle/core/Types$Reader;Lupickle/core/Types$Writer;)Lupickle/core/Types$ReadWriter;
      50: invokevirtual #94                 // Method upickle/default$.readwriter:(Lupickle/core/Types$ReadWriter;)Lupickle/core/Types$ReadWriter;
      53: invokedynamic #115,  0            // InvokeDynamic #0:apply:()Lscala/Function1;
      58: invokedynamic #122,  0            // InvokeDynamic #1:apply:()Lscala/Function1;
      63: invokeinterface #126,  3          // InterfaceMethod upickle/core/Types$ReadWriter.bimap:(Lscala/Function1;Lscala/Function1;)Lupickle/core/Types$ReadWriter;
      68: areturn

  public static scala.Tuple2 $anonfun$readWriter$23(morphir.ir.Type$Field);
    Code:
       0: new           #130                // class scala/Tuple2
       3: dup
       4: new           #20                 // class morphir/ir/name$Name
       7: dup
       8: aload_0
       9: invokevirtual #134                // Method morphir/ir/Type$Field.name:()Lscala/collection/immutable/List;
      12: invokespecial #138                // Method morphir/ir/name$Name."<init>":(Lscala/collection/immutable/List;)V
      15: aload_0
      16: invokevirtual #142                // Method morphir/ir/Type$Field.fieldType:()Lmorphir/ir/Type;
      19: invokespecial #145                // Method scala/Tuple2."<init>":(Ljava/lang/Object;Ljava/lang/Object;)V
      22: areturn

  public static morphir.ir.Type$Field $anonfun$readWriter$24(scala.Tuple2);
    Code:
       0: aload_0
       1: astore_2
       2: aload_2
       3: ifnull        40
       6: aload_2
       7: invokevirtual #151                // Method scala/Tuple2._1:()Ljava/lang/Object;
      10: checkcast     #20                 // class morphir/ir/name$Name
      13: invokevirtual #154                // Method morphir/ir/name$Name.value:()Lscala/collection/immutable/List;
      16: astore_3
      17: aload_2
      18: invokevirtual #157                // Method scala/Tuple2._2:()Ljava/lang/Object;
      21: checkcast     #14                 // class morphir/ir/Type
      24: astore        4
      26: new           #12                 // class morphir/ir/Type$Field
      29: dup
      30: aload_3
      31: aload         4
      33: invokespecial #160                // Method morphir/ir/Type$Field."<init>":(Lscala/collection/immutable/List;Lmorphir/ir/Type;)V
      36: astore_1
      37: goto          52
      40: goto          43
      43: new           #162                // class scala/MatchError
      46: dup
      47: aload_2
      48: invokespecial #165                // Method scala/MatchError."<init>":(Ljava/lang/Object;)V
      51: athrow
      52: aload_1
      53: areturn

  public static void $init$(morphir.ir.codec.typeCodecs$FieldCodec);
    Code:
       0: return

  private static java.lang.Object $deserializeLambda$(java.lang.invoke.SerializedLambda);
    Code:
       0: aload_0
       1: invokedynamic #184,  0            // InvokeDynamic #2:lambdaDeserialize:(Ljava/lang/invoke/SerializedLambda;)Ljava/lang/Object;
       6: areturn
}
