Compiled from "XPathExpression.java"
final class org.apache.activemq.artemis.selector.filter.XPathExpression$1 implements org.apache.activemq.artemis.selector.filter.XPathExpression$XPathEvaluatorFactory {
  org.apache.activemq.artemis.selector.filter.XPathExpression$1();
    Code:
       0: aload_0
       1: invokespecial #1                  // Method java/lang/Object."<init>":()V
       4: return

  public org.apache.activemq.artemis.selector.filter.XPathExpression$XPathEvaluator create(java.lang.String);
    Code:
       0: new           #2                  // class org/apache/activemq/artemis/selector/filter/XalanXPathEvaluator
       3: dup
       4: aload_1
       5: invokespecial #3                  // Method org/apache/activemq/artemis/selector/filter/XalanXPathEvaluator."<init>":(Ljava/lang/String;)V
       8: areturn
}
