Compiled from "ElementKind.java"
public final class io.dekorate.deps.javax.validation.ElementKind extends java.lang.Enum<io.dekorate.deps.javax.validation.ElementKind> {
  public static final io.dekorate.deps.javax.validation.ElementKind BEAN;

  public static final io.dekorate.deps.javax.validation.ElementKind PROPERTY;

  public static final io.dekorate.deps.javax.validation.ElementKind METHOD;

  public static final io.dekorate.deps.javax.validation.ElementKind CONSTRUCTOR;

  public static final io.dekorate.deps.javax.validation.ElementKind PARAMETER;

  public static final io.dekorate.deps.javax.validation.ElementKind CROSS_PARAMETER;

  public static final io.dekorate.deps.javax.validation.ElementKind RETURN_VALUE;

  private static final io.dekorate.deps.javax.validation.ElementKind[] $VALUES;

  public static io.dekorate.deps.javax.validation.ElementKind[] values();
    Code:
       0: getstatic     #20                 // Field $VALUES:[Lio/dekorate/deps/javax/validation/ElementKind;
       3: invokevirtual #25                 // Method "[Lio/dekorate/deps/javax/validation/ElementKind;".clone:()Ljava/lang/Object;
       6: checkcast     #21                 // class "[Lio/dekorate/deps/javax/validation/ElementKind;"
       9: areturn

  public static io.dekorate.deps.javax.validation.ElementKind valueOf(java.lang.String);
    Code:
       0: ldc           #2                  // class io/dekorate/deps/javax/validation/ElementKind
       2: aload_0
       3: invokestatic  #30                 // Method java/lang/Enum.valueOf:(Ljava/lang/Class;Ljava/lang/String;)Ljava/lang/Enum;
       6: checkcast     #2                  // class io/dekorate/deps/javax/validation/ElementKind
       9: areturn

  private io.dekorate.deps.javax.validation.ElementKind();
    Code:
       0: aload_0
       1: aload_1
       2: iload_2
       3: invokespecial #37                 // Method java/lang/Enum."<init>":(Ljava/lang/String;I)V
       6: return

  static {};
    Code:
       0: new           #2                  // class io/dekorate/deps/javax/validation/ElementKind
       3: dup
       4: ldc           #40                 // String BEAN
       6: iconst_0
       7: invokespecial #41                 // Method "<init>":(Ljava/lang/String;I)V
      10: putstatic     #43                 // Field BEAN:Lio/dekorate/deps/javax/validation/ElementKind;
      13: new           #2                  // class io/dekorate/deps/javax/validation/ElementKind
      16: dup
      17: ldc           #44                 // String PROPERTY
      19: iconst_1
      20: invokespecial #41                 // Method "<init>":(Ljava/lang/String;I)V
      23: putstatic     #46                 // Field PROPERTY:Lio/dekorate/deps/javax/validation/ElementKind;
      26: new           #2                  // class io/dekorate/deps/javax/validation/ElementKind
      29: dup
      30: ldc           #47                 // String METHOD
      32: iconst_2
      33: invokespecial #41                 // Method "<init>":(Ljava/lang/String;I)V
      36: putstatic     #49                 // Field METHOD:Lio/dekorate/deps/javax/validation/ElementKind;
      39: new           #2                  // class io/dekorate/deps/javax/validation/ElementKind
      42: dup
      43: ldc           #50                 // String CONSTRUCTOR
      45: iconst_3
      46: invokespecial #41                 // Method "<init>":(Ljava/lang/String;I)V
      49: putstatic     #52                 // Field CONSTRUCTOR:Lio/dekorate/deps/javax/validation/ElementKind;
      52: new           #2                  // class io/dekorate/deps/javax/validation/ElementKind
      55: dup
      56: ldc           #53                 // String PARAMETER
      58: iconst_4
      59: invokespecial #41                 // Method "<init>":(Ljava/lang/String;I)V
      62: putstatic     #55                 // Field PARAMETER:Lio/dekorate/deps/javax/validation/ElementKind;
      65: new           #2                  // class io/dekorate/deps/javax/validation/ElementKind
      68: dup
      69: ldc           #56                 // String CROSS_PARAMETER
      71: iconst_5
      72: invokespecial #41                 // Method "<init>":(Ljava/lang/String;I)V
      75: putstatic     #58                 // Field CROSS_PARAMETER:Lio/dekorate/deps/javax/validation/ElementKind;
      78: new           #2                  // class io/dekorate/deps/javax/validation/ElementKind
      81: dup
      82: ldc           #59                 // String RETURN_VALUE
      84: bipush        6
      86: invokespecial #41                 // Method "<init>":(Ljava/lang/String;I)V
      89: putstatic     #61                 // Field RETURN_VALUE:Lio/dekorate/deps/javax/validation/ElementKind;
      92: bipush        7
      94: anewarray     #2                  // class io/dekorate/deps/javax/validation/ElementKind
      97: dup
      98: iconst_0
      99: getstatic     #43                 // Field BEAN:Lio/dekorate/deps/javax/validation/ElementKind;
     102: aastore
     103: dup
     104: iconst_1
     105: getstatic     #46                 // Field PROPERTY:Lio/dekorate/deps/javax/validation/ElementKind;
     108: aastore
     109: dup
     110: iconst_2
     111: getstatic     #49                 // Field METHOD:Lio/dekorate/deps/javax/validation/ElementKind;
     114: aastore
     115: dup
     116: iconst_3
     117: getstatic     #52                 // Field CONSTRUCTOR:Lio/dekorate/deps/javax/validation/ElementKind;
     120: aastore
     121: dup
     122: iconst_4
     123: getstatic     #55                 // Field PARAMETER:Lio/dekorate/deps/javax/validation/ElementKind;
     126: aastore
     127: dup
     128: iconst_5
     129: getstatic     #58                 // Field CROSS_PARAMETER:Lio/dekorate/deps/javax/validation/ElementKind;
     132: aastore
     133: dup
     134: bipush        6
     136: getstatic     #61                 // Field RETURN_VALUE:Lio/dekorate/deps/javax/validation/ElementKind;
     139: aastore
     140: putstatic     #20                 // Field $VALUES:[Lio/dekorate/deps/javax/validation/ElementKind;
     143: return
}
