Compiled from "ValidationException.java"
public class io.dekorate.deps.javax.validation.ValidationException extends java.lang.RuntimeException {
  public io.dekorate.deps.javax.validation.ValidationException(java.lang.String);
    Code:
       0: aload_0
       1: aload_1
       2: invokespecial #9                  // Method java/lang/RuntimeException."<init>":(Ljava/lang/String;)V
       5: return

  public io.dekorate.deps.javax.validation.ValidationException();
    Code:
       0: aload_0
       1: invokespecial #16                 // Method java/lang/RuntimeException."<init>":()V
       4: return

  public io.dekorate.deps.javax.validation.ValidationException(java.lang.String, java.lang.Throwable);
    Code:
       0: aload_0
       1: aload_1
       2: aload_2
       3: invokespecial #19                 // Method java/lang/RuntimeException."<init>":(Ljava/lang/String;Ljava/lang/Throwable;)V
       6: return

  public io.dekorate.deps.javax.validation.ValidationException(java.lang.Throwable);
    Code:
       0: aload_0
       1: aload_1
       2: invokespecial #24                 // Method java/lang/RuntimeException."<init>":(Ljava/lang/Throwable;)V
       5: return
}
