Compiled from "NordsieckStepInterpolator.java"
public class org.apache.commons.math3.ode.sampling.NordsieckStepInterpolator extends org.apache.commons.math3.ode.sampling.AbstractStepInterpolator {
  private static final long serialVersionUID;

  protected double[] stateVariation;

  private double scalingH;

  private double referenceTime;

  private double[] scaled;

  private org.apache.commons.math3.linear.Array2DRowRealMatrix nordsieck;

  public org.apache.commons.math3.ode.sampling.NordsieckStepInterpolator();
    Code:
       0: aload_0
       1: invokespecial #1                  // Method org/apache/commons/math3/ode/sampling/AbstractStepInterpolator."<init>":()V
       4: return

  public org.apache.commons.math3.ode.sampling.NordsieckStepInterpolator(org.apache.commons.math3.ode.sampling.NordsieckStepInterpolator);
    Code:
       0: aload_0
       1: aload_1
       2: invokespecial #2                  // Method org/apache/commons/math3/ode/sampling/AbstractStepInterpolator."<init>":(Lorg/apache/commons/math3/ode/sampling/AbstractStepInterpolator;)V
       5: aload_0
       6: aload_1
       7: getfield      #3                  // Field scalingH:D
      10: putfield      #3                  // Field scalingH:D
      13: aload_0
      14: aload_1
      15: getfield      #4                  // Field referenceTime:D
      18: putfield      #4                  // Field referenceTime:D
      21: aload_1
      22: getfield      #5                  // Field scaled:[D
      25: ifnull        42
      28: aload_0
      29: aload_1
      30: getfield      #5                  // Field scaled:[D
      33: invokevirtual #6                  // Method "[D".clone:()Ljava/lang/Object;
      36: checkcast     #7                  // class "[D"
      39: putfield      #5                  // Field scaled:[D
      42: aload_1
      43: getfield      #8                  // Field nordsieck:Lorg/apache/commons/math3/linear/Array2DRowRealMatrix;
      46: ifnull        68
      49: aload_0
      50: new           #9                  // class org/apache/commons/math3/linear/Array2DRowRealMatrix
      53: dup
      54: aload_1
      55: getfield      #8                  // Field nordsieck:Lorg/apache/commons/math3/linear/Array2DRowRealMatrix;
      58: invokevirtual #10                 // Method org/apache/commons/math3/linear/Array2DRowRealMatrix.getDataRef:()[[D
      61: iconst_1
      62: invokespecial #11                 // Method org/apache/commons/math3/linear/Array2DRowRealMatrix."<init>":([[DZ)V
      65: putfield      #8                  // Field nordsieck:Lorg/apache/commons/math3/linear/Array2DRowRealMatrix;
      68: aload_1
      69: getfield      #12                 // Field stateVariation:[D
      72: ifnull        89
      75: aload_0
      76: aload_1
      77: getfield      #12                 // Field stateVariation:[D
      80: invokevirtual #13                 // Method "[D".clone:()Ljava/lang/Object;
      83: checkcast     #7                  // class "[D"
      86: putfield      #12                 // Field stateVariation:[D
      89: return

  protected org.apache.commons.math3.ode.sampling.StepInterpolator doCopy();
    Code:
       0: new           #14                 // class org/apache/commons/math3/ode/sampling/NordsieckStepInterpolator
       3: dup
       4: aload_0
       5: invokespecial #15                 // Method "<init>":(Lorg/apache/commons/math3/ode/sampling/NordsieckStepInterpolator;)V
       8: areturn

  public void reinitialize(double[], boolean, org.apache.commons.math3.ode.EquationsMapper, org.apache.commons.math3.ode.EquationsMapper[]);
    Code:
       0: aload_0
       1: aload_1
       2: iload_2
       3: aload_3
       4: aload         4
       6: invokespecial #16                 // Method org/apache/commons/math3/ode/sampling/AbstractStepInterpolator.reinitialize:([DZLorg/apache/commons/math3/ode/EquationsMapper;[Lorg/apache/commons/math3/ode/EquationsMapper;)V
       9: aload_0
      10: aload_1
      11: arraylength
      12: newarray       double
      14: putfield      #12                 // Field stateVariation:[D
      17: return

  public void reinitialize(double, double, double[], org.apache.commons.math3.linear.Array2DRowRealMatrix);
    Code:
       0: aload_0
       1: dload_1
       2: putfield      #4                  // Field referenceTime:D
       5: aload_0
       6: dload_3
       7: putfield      #3                  // Field scalingH:D
      10: aload_0
      11: aload         5
      13: putfield      #5                  // Field scaled:[D
      16: aload_0
      17: aload         6
      19: putfield      #8                  // Field nordsieck:Lorg/apache/commons/math3/linear/Array2DRowRealMatrix;
      22: aload_0
      23: aload_0
      24: invokevirtual #17                 // Method getInterpolatedTime:()D
      27: invokevirtual #18                 // Method setInterpolatedTime:(D)V
      30: return

  public void rescale(double);
    Code:
       0: dload_1
       1: aload_0
       2: getfield      #3                  // Field scalingH:D
       5: ddiv
       6: dstore_3
       7: iconst_0
       8: istore        5
      10: iload         5
      12: aload_0
      13: getfield      #5                  // Field scaled:[D
      16: arraylength
      17: if_icmpge     37
      20: aload_0
      21: getfield      #5                  // Field scaled:[D
      24: iload         5
      26: dup2
      27: daload
      28: dload_3
      29: dmul
      30: dastore
      31: iinc          5, 1
      34: goto          10
      37: aload_0
      38: getfield      #8                  // Field nordsieck:Lorg/apache/commons/math3/linear/Array2DRowRealMatrix;
      41: invokevirtual #10                 // Method org/apache/commons/math3/linear/Array2DRowRealMatrix.getDataRef:()[[D
      44: astore        5
      46: dload_3
      47: dstore        6
      49: iconst_0
      50: istore        8
      52: iload         8
      54: aload         5
      56: arraylength
      57: if_icmpge     106
      60: dload         6
      62: dload_3
      63: dmul
      64: dstore        6
      66: aload         5
      68: iload         8
      70: aaload
      71: astore        9
      73: iconst_0
      74: istore        10
      76: iload         10
      78: aload         9
      80: arraylength
      81: if_icmpge     100
      84: aload         9
      86: iload         10
      88: dup2
      89: daload
      90: dload         6
      92: dmul
      93: dastore
      94: iinc          10, 1
      97: goto          76
     100: iinc          8, 1
     103: goto          52
     106: aload_0
     107: dload_1
     108: putfield      #3                  // Field scalingH:D
     111: return

  public double[] getInterpolatedStateVariation() throws org.apache.commons.math3.exception.MaxCountExceededException;
    Code:
       0: aload_0
       1: invokevirtual #19                 // Method getInterpolatedState:()[D
       4: pop
       5: aload_0
       6: getfield      #12                 // Field stateVariation:[D
       9: areturn

  protected void computeInterpolatedStateAndDerivatives(double, double);
    Code:
       0: aload_0
       1: getfield      #20                 // Field interpolatedTime:D
       4: aload_0
       5: getfield      #4                  // Field referenceTime:D
       8: dsub
       9: dstore        5
      11: dload         5
      13: aload_0
      14: getfield      #3                  // Field scalingH:D
      17: ddiv
      18: dstore        7
      20: aload_0
      21: getfield      #12                 // Field stateVariation:[D
      24: dconst_0
      25: invokestatic  #21                 // Method java/util/Arrays.fill:([DD)V
      28: aload_0
      29: getfield      #22                 // Field interpolatedDerivatives:[D
      32: dconst_0
      33: invokestatic  #21                 // Method java/util/Arrays.fill:([DD)V
      36: aload_0
      37: getfield      #8                  // Field nordsieck:Lorg/apache/commons/math3/linear/Array2DRowRealMatrix;
      40: invokevirtual #10                 // Method org/apache/commons/math3/linear/Array2DRowRealMatrix.getDataRef:()[[D
      43: astore        9
      45: aload         9
      47: arraylength
      48: iconst_1
      49: isub
      50: istore        10
      52: iload         10
      54: iflt          140
      57: iload         10
      59: iconst_2
      60: iadd
      61: istore        11
      63: aload         9
      65: iload         10
      67: aaload
      68: astore        12
      70: dload         7
      72: iload         11
      74: invokestatic  #23                 // Method org/apache/commons/math3/util/FastMath.pow:(DI)D
      77: dstore        13
      79: iconst_0
      80: istore        15
      82: iload         15
      84: aload         12
      86: arraylength
      87: if_icmpge     134
      90: aload         12
      92: iload         15
      94: daload
      95: dload         13
      97: dmul
      98: dstore        16
     100: aload_0
     101: getfield      #12                 // Field stateVariation:[D
     104: iload         15
     106: dup2
     107: daload
     108: dload         16
     110: dadd
     111: dastore
     112: aload_0
     113: getfield      #22                 // Field interpolatedDerivatives:[D
     116: iload         15
     118: dup2
     119: daload
     120: iload         11
     122: i2d
     123: dload         16
     125: dmul
     126: dadd
     127: dastore
     128: iinc          15, 1
     131: goto          82
     134: iinc          10, -1
     137: goto          52
     140: iconst_0
     141: istore        10
     143: iload         10
     145: aload_0
     146: getfield      #24                 // Field currentState:[D
     149: arraylength
     150: if_icmpge     229
     153: aload_0
     154: getfield      #12                 // Field stateVariation:[D
     157: iload         10
     159: dup2
     160: daload
     161: aload_0
     162: getfield      #5                  // Field scaled:[D
     165: iload         10
     167: daload
     168: dload         7
     170: dmul
     171: dadd
     172: dastore
     173: aload_0
     174: getfield      #25                 // Field interpolatedState:[D
     177: iload         10
     179: aload_0
     180: getfield      #24                 // Field currentState:[D
     183: iload         10
     185: daload
     186: aload_0
     187: getfield      #12                 // Field stateVariation:[D
     190: iload         10
     192: daload
     193: dadd
     194: dastore
     195: aload_0
     196: getfield      #22                 // Field interpolatedDerivatives:[D
     199: iload         10
     201: aload_0
     202: getfield      #22                 // Field interpolatedDerivatives:[D
     205: iload         10
     207: daload
     208: aload_0
     209: getfield      #5                  // Field scaled:[D
     212: iload         10
     214: daload
     215: dload         7
     217: dmul
     218: dadd
     219: dload         5
     221: ddiv
     222: dastore
     223: iinc          10, 1
     226: goto          143
     229: return

  public void writeExternal(java.io.ObjectOutput) throws java.io.IOException;
    Code:
       0: aload_0
       1: aload_1
       2: invokevirtual #26                 // Method writeBaseExternal:(Ljava/io/ObjectOutput;)V
       5: aload_1
       6: aload_0
       7: getfield      #3                  // Field scalingH:D
      10: invokeinterface #27,  3           // InterfaceMethod java/io/ObjectOutput.writeDouble:(D)V
      15: aload_1
      16: aload_0
      17: getfield      #4                  // Field referenceTime:D
      20: invokeinterface #27,  3           // InterfaceMethod java/io/ObjectOutput.writeDouble:(D)V
      25: aload_0
      26: getfield      #24                 // Field currentState:[D
      29: ifnonnull     36
      32: iconst_m1
      33: goto          41
      36: aload_0
      37: getfield      #24                 // Field currentState:[D
      40: arraylength
      41: istore_2
      42: aload_0
      43: getfield      #5                  // Field scaled:[D
      46: ifnonnull     59
      49: aload_1
      50: iconst_0
      51: invokeinterface #28,  2           // InterfaceMethod java/io/ObjectOutput.writeBoolean:(Z)V
      56: goto          91
      59: aload_1
      60: iconst_1
      61: invokeinterface #28,  2           // InterfaceMethod java/io/ObjectOutput.writeBoolean:(Z)V
      66: iconst_0
      67: istore_3
      68: iload_3
      69: iload_2
      70: if_icmpge     91
      73: aload_1
      74: aload_0
      75: getfield      #5                  // Field scaled:[D
      78: iload_3
      79: daload
      80: invokeinterface #27,  3           // InterfaceMethod java/io/ObjectOutput.writeDouble:(D)V
      85: iinc          3, 1
      88: goto          68
      91: aload_0
      92: getfield      #8                  // Field nordsieck:Lorg/apache/commons/math3/linear/Array2DRowRealMatrix;
      95: ifnonnull     108
      98: aload_1
      99: iconst_0
     100: invokeinterface #28,  2           // InterfaceMethod java/io/ObjectOutput.writeBoolean:(Z)V
     105: goto          125
     108: aload_1
     109: iconst_1
     110: invokeinterface #28,  2           // InterfaceMethod java/io/ObjectOutput.writeBoolean:(Z)V
     115: aload_1
     116: aload_0
     117: getfield      #8                  // Field nordsieck:Lorg/apache/commons/math3/linear/Array2DRowRealMatrix;
     120: invokeinterface #29,  2           // InterfaceMethod java/io/ObjectOutput.writeObject:(Ljava/lang/Object;)V
     125: return

  public void readExternal(java.io.ObjectInput) throws java.io.IOException, java.lang.ClassNotFoundException;
    Code:
       0: aload_0
       1: aload_1
       2: invokevirtual #30                 // Method readBaseExternal:(Ljava/io/ObjectInput;)D
       5: dstore_2
       6: aload_0
       7: aload_1
       8: invokeinterface #31,  1           // InterfaceMethod java/io/ObjectInput.readDouble:()D
      13: putfield      #3                  // Field scalingH:D
      16: aload_0
      17: aload_1
      18: invokeinterface #31,  1           // InterfaceMethod java/io/ObjectInput.readDouble:()D
      23: putfield      #4                  // Field referenceTime:D
      26: aload_0
      27: getfield      #24                 // Field currentState:[D
      30: ifnonnull     37
      33: iconst_m1
      34: goto          42
      37: aload_0
      38: getfield      #24                 // Field currentState:[D
      41: arraylength
      42: istore        4
      44: aload_1
      45: invokeinterface #32,  1           // InterfaceMethod java/io/ObjectInput.readBoolean:()Z
      50: istore        5
      52: iload         5
      54: ifeq          97
      57: aload_0
      58: iload         4
      60: newarray       double
      62: putfield      #5                  // Field scaled:[D
      65: iconst_0
      66: istore        6
      68: iload         6
      70: iload         4
      72: if_icmpge     94
      75: aload_0
      76: getfield      #5                  // Field scaled:[D
      79: iload         6
      81: aload_1
      82: invokeinterface #31,  1           // InterfaceMethod java/io/ObjectInput.readDouble:()D
      87: dastore
      88: iinc          6, 1
      91: goto          68
      94: goto          102
      97: aload_0
      98: aconst_null
      99: putfield      #5                  // Field scaled:[D
     102: aload_1
     103: invokeinterface #32,  1           // InterfaceMethod java/io/ObjectInput.readBoolean:()Z
     108: istore        6
     110: iload         6
     112: ifeq          131
     115: aload_0
     116: aload_1
     117: invokeinterface #33,  1           // InterfaceMethod java/io/ObjectInput.readObject:()Ljava/lang/Object;
     122: checkcast     #9                  // class org/apache/commons/math3/linear/Array2DRowRealMatrix
     125: putfield      #8                  // Field nordsieck:Lorg/apache/commons/math3/linear/Array2DRowRealMatrix;
     128: goto          136
     131: aload_0
     132: aconst_null
     133: putfield      #8                  // Field nordsieck:Lorg/apache/commons/math3/linear/Array2DRowRealMatrix;
     136: iload         5
     138: ifeq          162
     141: iload         6
     143: ifeq          162
     146: aload_0
     147: iload         4
     149: newarray       double
     151: putfield      #12                 // Field stateVariation:[D
     154: aload_0
     155: dload_2
     156: invokevirtual #18                 // Method setInterpolatedTime:(D)V
     159: goto          167
     162: aload_0
     163: aconst_null
     164: putfield      #12                 // Field stateVariation:[D
     167: return
}
