Compiled from "JDBCAuthOptions.kt"
public final class io.vertx.kotlin.ext.auth.jdbc.JDBCAuthOptionsKt {
  public static final io.vertx.ext.auth.jdbc.JDBCAuthOptions jdbcAuthOptionsOf(java.lang.String, io.vertx.core.json.JsonObject, java.lang.String, java.lang.String, java.lang.String, java.lang.String, java.lang.Boolean);
    Code:
       0: new           #10                 // class io/vertx/ext/auth/jdbc/JDBCAuthOptions
       3: dup
       4: invokespecial #14                 // Method io/vertx/ext/auth/jdbc/JDBCAuthOptions."<init>":()V
       7: astore        7
       9: iconst_0
      10: istore        8
      12: iconst_0
      13: istore        9
      15: aload         7
      17: astore        10
      19: iconst_0
      20: istore        11
      22: aload_0
      23: ifnull        33
      26: aload         10
      28: aload_0
      29: invokevirtual #18                 // Method io/vertx/ext/auth/jdbc/JDBCAuthOptions.setAuthenticationQuery:(Ljava/lang/String;)Lio/vertx/ext/auth/jdbc/JDBCAuthOptions;
      32: pop
      33: aload_1
      34: ifnull        44
      37: aload         10
      39: aload_1
      40: invokevirtual #22                 // Method io/vertx/ext/auth/jdbc/JDBCAuthOptions.setConfig:(Lio/vertx/core/json/JsonObject;)Lio/vertx/ext/auth/jdbc/JDBCAuthOptions;
      43: pop
      44: aload_2
      45: ifnull        55
      48: aload         10
      50: aload_2
      51: invokevirtual #25                 // Method io/vertx/ext/auth/jdbc/JDBCAuthOptions.setDatasourceName:(Ljava/lang/String;)Lio/vertx/ext/auth/jdbc/JDBCAuthOptions;
      54: pop
      55: aload_3
      56: ifnull        66
      59: aload         10
      61: aload_3
      62: invokevirtual #28                 // Method io/vertx/ext/auth/jdbc/JDBCAuthOptions.setPermissionsQuery:(Ljava/lang/String;)Lio/vertx/ext/auth/jdbc/JDBCAuthOptions;
      65: pop
      66: aload         4
      68: ifnull        79
      71: aload         10
      73: aload         4
      75: invokevirtual #31                 // Method io/vertx/ext/auth/jdbc/JDBCAuthOptions.setRolesPrefix:(Ljava/lang/String;)Lio/vertx/ext/auth/jdbc/JDBCAuthOptions;
      78: pop
      79: aload         5
      81: ifnull        92
      84: aload         10
      86: aload         5
      88: invokevirtual #34                 // Method io/vertx/ext/auth/jdbc/JDBCAuthOptions.setRolesQuery:(Ljava/lang/String;)Lio/vertx/ext/auth/jdbc/JDBCAuthOptions;
      91: pop
      92: aload         6
      94: ifnull        108
      97: aload         10
      99: aload         6
     101: invokevirtual #40                 // Method java/lang/Boolean.booleanValue:()Z
     104: invokevirtual #44                 // Method io/vertx/ext/auth/jdbc/JDBCAuthOptions.setShared:(Z)Lio/vertx/ext/auth/jdbc/JDBCAuthOptions;
     107: pop
     108: nop
     109: aload         7
     111: areturn

  public static io.vertx.ext.auth.jdbc.JDBCAuthOptions jdbcAuthOptionsOf$default(java.lang.String, io.vertx.core.json.JsonObject, java.lang.String, java.lang.String, java.lang.String, java.lang.String, java.lang.Boolean, int, java.lang.Object);
    Code:
       0: iload         7
       2: iconst_1
       3: iand
       4: ifeq          12
       7: aconst_null
       8: checkcast     #60                 // class java/lang/String
      11: astore_0
      12: iload         7
      14: iconst_2
      15: iand
      16: ifeq          24
      19: aconst_null
      20: checkcast     #62                 // class io/vertx/core/json/JsonObject
      23: astore_1
      24: iload         7
      26: iconst_4
      27: iand
      28: ifeq          36
      31: aconst_null
      32: checkcast     #60                 // class java/lang/String
      35: astore_2
      36: iload         7
      38: bipush        8
      40: iand
      41: ifeq          49
      44: aconst_null
      45: checkcast     #60                 // class java/lang/String
      48: astore_3
      49: iload         7
      51: bipush        16
      53: iand
      54: ifeq          63
      57: aconst_null
      58: checkcast     #60                 // class java/lang/String
      61: astore        4
      63: iload         7
      65: bipush        32
      67: iand
      68: ifeq          77
      71: aconst_null
      72: checkcast     #60                 // class java/lang/String
      75: astore        5
      77: iload         7
      79: bipush        64
      81: iand
      82: ifeq          91
      85: aconst_null
      86: checkcast     #36                 // class java/lang/Boolean
      89: astore        6
      91: aload_0
      92: aload_1
      93: aload_2
      94: aload_3
      95: aload         4
      97: aload         5
      99: aload         6
     101: invokestatic  #66                 // Method jdbcAuthOptionsOf:(Ljava/lang/String;Lio/vertx/core/json/JsonObject;Ljava/lang/String;Ljava/lang/String;Ljava/lang/String;Ljava/lang/String;Ljava/lang/Boolean;)Lio/vertx/ext/auth/jdbc/JDBCAuthOptions;
     104: areturn

  public static final io.vertx.ext.auth.jdbc.JDBCAuthOptions JDBCAuthOptions(java.lang.String, io.vertx.core.json.JsonObject, java.lang.String, java.lang.String, java.lang.String, java.lang.String, java.lang.Boolean);
    Code:
       0: new           #10                 // class io/vertx/ext/auth/jdbc/JDBCAuthOptions
       3: dup
       4: invokespecial #14                 // Method io/vertx/ext/auth/jdbc/JDBCAuthOptions."<init>":()V
       7: astore        7
       9: iconst_0
      10: istore        8
      12: iconst_0
      13: istore        9
      15: aload         7
      17: astore        10
      19: iconst_0
      20: istore        11
      22: aload_0
      23: ifnull        33
      26: aload         10
      28: aload_0
      29: invokevirtual #18                 // Method io/vertx/ext/auth/jdbc/JDBCAuthOptions.setAuthenticationQuery:(Ljava/lang/String;)Lio/vertx/ext/auth/jdbc/JDBCAuthOptions;
      32: pop
      33: aload_1
      34: ifnull        44
      37: aload         10
      39: aload_1
      40: invokevirtual #22                 // Method io/vertx/ext/auth/jdbc/JDBCAuthOptions.setConfig:(Lio/vertx/core/json/JsonObject;)Lio/vertx/ext/auth/jdbc/JDBCAuthOptions;
      43: pop
      44: aload_2
      45: ifnull        55
      48: aload         10
      50: aload_2
      51: invokevirtual #25                 // Method io/vertx/ext/auth/jdbc/JDBCAuthOptions.setDatasourceName:(Ljava/lang/String;)Lio/vertx/ext/auth/jdbc/JDBCAuthOptions;
      54: pop
      55: aload_3
      56: ifnull        66
      59: aload         10
      61: aload_3
      62: invokevirtual #28                 // Method io/vertx/ext/auth/jdbc/JDBCAuthOptions.setPermissionsQuery:(Ljava/lang/String;)Lio/vertx/ext/auth/jdbc/JDBCAuthOptions;
      65: pop
      66: aload         4
      68: ifnull        79
      71: aload         10
      73: aload         4
      75: invokevirtual #31                 // Method io/vertx/ext/auth/jdbc/JDBCAuthOptions.setRolesPrefix:(Ljava/lang/String;)Lio/vertx/ext/auth/jdbc/JDBCAuthOptions;
      78: pop
      79: aload         5
      81: ifnull        92
      84: aload         10
      86: aload         5
      88: invokevirtual #34                 // Method io/vertx/ext/auth/jdbc/JDBCAuthOptions.setRolesQuery:(Ljava/lang/String;)Lio/vertx/ext/auth/jdbc/JDBCAuthOptions;
      91: pop
      92: aload         6
      94: ifnull        108
      97: aload         10
      99: aload         6
     101: invokevirtual #40                 // Method java/lang/Boolean.booleanValue:()Z
     104: invokevirtual #44                 // Method io/vertx/ext/auth/jdbc/JDBCAuthOptions.setShared:(Z)Lio/vertx/ext/auth/jdbc/JDBCAuthOptions;
     107: pop
     108: nop
     109: aload         7
     111: areturn

  public static io.vertx.ext.auth.jdbc.JDBCAuthOptions JDBCAuthOptions$default(java.lang.String, io.vertx.core.json.JsonObject, java.lang.String, java.lang.String, java.lang.String, java.lang.String, java.lang.Boolean, int, java.lang.Object);
    Code:
       0: iload         7
       2: iconst_1
       3: iand
       4: ifeq          12
       7: aconst_null
       8: checkcast     #60                 // class java/lang/String
      11: astore_0
      12: iload         7
      14: iconst_2
      15: iand
      16: ifeq          24
      19: aconst_null
      20: checkcast     #62                 // class io/vertx/core/json/JsonObject
      23: astore_1
      24: iload         7
      26: iconst_4
      27: iand
      28: ifeq          36
      31: aconst_null
      32: checkcast     #60                 // class java/lang/String
      35: astore_2
      36: iload         7
      38: bipush        8
      40: iand
      41: ifeq          49
      44: aconst_null
      45: checkcast     #60                 // class java/lang/String
      48: astore_3
      49: iload         7
      51: bipush        16
      53: iand
      54: ifeq          63
      57: aconst_null
      58: checkcast     #60                 // class java/lang/String
      61: astore        4
      63: iload         7
      65: bipush        32
      67: iand
      68: ifeq          77
      71: aconst_null
      72: checkcast     #60                 // class java/lang/String
      75: astore        5
      77: iload         7
      79: bipush        64
      81: iand
      82: ifeq          91
      85: aconst_null
      86: checkcast     #36                 // class java/lang/Boolean
      89: astore        6
      91: aload_0
      92: aload_1
      93: aload_2
      94: aload_3
      95: aload         4
      97: aload         5
      99: aload         6
     101: invokestatic  #79                 // Method JDBCAuthOptions:(Ljava/lang/String;Lio/vertx/core/json/JsonObject;Ljava/lang/String;Ljava/lang/String;Ljava/lang/String;Ljava/lang/String;Ljava/lang/Boolean;)Lio/vertx/ext/auth/jdbc/JDBCAuthOptions;
     104: areturn
}
