Compiled from "ActiveContext.java"
final class software.amazon.awssdk.services.lexruntimev2.model.ActiveContext$BuilderImpl implements software.amazon.awssdk.services.lexruntimev2.model.ActiveContext$Builder {
  private java.lang.String name;

  private software.amazon.awssdk.services.lexruntimev2.model.ActiveContextTimeToLive timeToLive;

  private java.util.Map<java.lang.String, java.lang.String> contextAttributes;

  private software.amazon.awssdk.services.lexruntimev2.model.ActiveContext$BuilderImpl();
    Code:
       0: aload_0
       1: invokespecial #6                  // Method java/lang/Object."<init>":()V
       4: aload_0
       5: invokestatic  #7                  // Method software/amazon/awssdk/core/util/DefaultSdkAutoConstructMap.getInstance:()Lsoftware/amazon/awssdk/core/util/DefaultSdkAutoConstructMap;
       8: putfield      #3                  // Field contextAttributes:Ljava/util/Map;
      11: return

  private software.amazon.awssdk.services.lexruntimev2.model.ActiveContext$BuilderImpl(software.amazon.awssdk.services.lexruntimev2.model.ActiveContext);
    Code:
       0: aload_0
       1: invokespecial #6                  // Method java/lang/Object."<init>":()V
       4: aload_0
       5: invokestatic  #7                  // Method software/amazon/awssdk/core/util/DefaultSdkAutoConstructMap.getInstance:()Lsoftware/amazon/awssdk/core/util/DefaultSdkAutoConstructMap;
       8: putfield      #3                  // Field contextAttributes:Ljava/util/Map;
      11: aload_0
      12: aload_1
      13: invokestatic  #8                  // Method software/amazon/awssdk/services/lexruntimev2/model/ActiveContext.access$500:(Lsoftware/amazon/awssdk/services/lexruntimev2/model/ActiveContext;)Ljava/lang/String;
      16: invokevirtual #9                  // Method name:(Ljava/lang/String;)Lsoftware/amazon/awssdk/services/lexruntimev2/model/ActiveContext$Builder;
      19: pop
      20: aload_0
      21: aload_1
      22: invokestatic  #10                 // Method software/amazon/awssdk/services/lexruntimev2/model/ActiveContext.access$600:(Lsoftware/amazon/awssdk/services/lexruntimev2/model/ActiveContext;)Lsoftware/amazon/awssdk/services/lexruntimev2/model/ActiveContextTimeToLive;
      25: invokevirtual #11                 // Method timeToLive:(Lsoftware/amazon/awssdk/services/lexruntimev2/model/ActiveContextTimeToLive;)Lsoftware/amazon/awssdk/services/lexruntimev2/model/ActiveContext$Builder;
      28: pop
      29: aload_0
      30: aload_1
      31: invokestatic  #12                 // Method software/amazon/awssdk/services/lexruntimev2/model/ActiveContext.access$700:(Lsoftware/amazon/awssdk/services/lexruntimev2/model/ActiveContext;)Ljava/util/Map;
      34: invokevirtual #13                 // Method contextAttributes:(Ljava/util/Map;)Lsoftware/amazon/awssdk/services/lexruntimev2/model/ActiveContext$Builder;
      37: pop
      38: return

  public final java.lang.String getName();
    Code:
       0: aload_0
       1: getfield      #5                  // Field name:Ljava/lang/String;
       4: areturn

  public final void setName(java.lang.String);
    Code:
       0: aload_0
       1: aload_1
       2: putfield      #5                  // Field name:Ljava/lang/String;
       5: return

  public final software.amazon.awssdk.services.lexruntimev2.model.ActiveContext$Builder name(java.lang.String);
    Code:
       0: aload_0
       1: aload_1
       2: putfield      #5                  // Field name:Ljava/lang/String;
       5: aload_0
       6: areturn

  public final software.amazon.awssdk.services.lexruntimev2.model.ActiveContextTimeToLive$Builder getTimeToLive();
    Code:
       0: aload_0
       1: getfield      #4                  // Field timeToLive:Lsoftware/amazon/awssdk/services/lexruntimev2/model/ActiveContextTimeToLive;
       4: ifnull        17
       7: aload_0
       8: getfield      #4                  // Field timeToLive:Lsoftware/amazon/awssdk/services/lexruntimev2/model/ActiveContextTimeToLive;
      11: invokevirtual #14                 // Method software/amazon/awssdk/services/lexruntimev2/model/ActiveContextTimeToLive.toBuilder:()Lsoftware/amazon/awssdk/services/lexruntimev2/model/ActiveContextTimeToLive$Builder;
      14: goto          18
      17: aconst_null
      18: areturn

  public final void setTimeToLive(software.amazon.awssdk.services.lexruntimev2.model.ActiveContextTimeToLive$BuilderImpl);
    Code:
       0: aload_0
       1: aload_1
       2: ifnull        12
       5: aload_1
       6: invokevirtual #15                 // Method software/amazon/awssdk/services/lexruntimev2/model/ActiveContextTimeToLive$BuilderImpl.build:()Lsoftware/amazon/awssdk/services/lexruntimev2/model/ActiveContextTimeToLive;
       9: goto          13
      12: aconst_null
      13: putfield      #4                  // Field timeToLive:Lsoftware/amazon/awssdk/services/lexruntimev2/model/ActiveContextTimeToLive;
      16: return

  public final software.amazon.awssdk.services.lexruntimev2.model.ActiveContext$Builder timeToLive(software.amazon.awssdk.services.lexruntimev2.model.ActiveContextTimeToLive);
    Code:
       0: aload_0
       1: aload_1
       2: putfield      #4                  // Field timeToLive:Lsoftware/amazon/awssdk/services/lexruntimev2/model/ActiveContextTimeToLive;
       5: aload_0
       6: areturn

  public final java.util.Map<java.lang.String, java.lang.String> getContextAttributes();
    Code:
       0: aload_0
       1: getfield      #3                  // Field contextAttributes:Ljava/util/Map;
       4: instanceof    #16                 // class software/amazon/awssdk/core/util/SdkAutoConstructMap
       7: ifeq          12
      10: aconst_null
      11: areturn
      12: aload_0
      13: getfield      #3                  // Field contextAttributes:Ljava/util/Map;
      16: areturn

  public final void setContextAttributes(java.util.Map<java.lang.String, java.lang.String>);
    Code:
       0: aload_0
       1: aload_1
       2: invokestatic  #17                 // Method software/amazon/awssdk/services/lexruntimev2/model/ActiveContextParametersMapCopier.copy:(Ljava/util/Map;)Ljava/util/Map;
       5: putfield      #3                  // Field contextAttributes:Ljava/util/Map;
       8: return

  public final software.amazon.awssdk.services.lexruntimev2.model.ActiveContext$Builder contextAttributes(java.util.Map<java.lang.String, java.lang.String>);
    Code:
       0: aload_0
       1: aload_1
       2: invokestatic  #17                 // Method software/amazon/awssdk/services/lexruntimev2/model/ActiveContextParametersMapCopier.copy:(Ljava/util/Map;)Ljava/util/Map;
       5: putfield      #3                  // Field contextAttributes:Ljava/util/Map;
       8: aload_0
       9: areturn

  public software.amazon.awssdk.services.lexruntimev2.model.ActiveContext build();
    Code:
       0: new           #18                 // class software/amazon/awssdk/services/lexruntimev2/model/ActiveContext
       3: dup
       4: aload_0
       5: aconst_null
       6: invokespecial #19                 // Method software/amazon/awssdk/services/lexruntimev2/model/ActiveContext."<init>":(Lsoftware/amazon/awssdk/services/lexruntimev2/model/ActiveContext$BuilderImpl;Lsoftware/amazon/awssdk/services/lexruntimev2/model/ActiveContext$1;)V
       9: areturn

  public java.util.List<software.amazon.awssdk.core.SdkField<?>> sdkFields();
    Code:
       0: invokestatic  #20                 // Method software/amazon/awssdk/services/lexruntimev2/model/ActiveContext.access$900:()Ljava/util/List;
       3: areturn

  public java.lang.Object build();
    Code:
       0: aload_0
       1: invokevirtual #21                 // Method build:()Lsoftware/amazon/awssdk/services/lexruntimev2/model/ActiveContext;
       4: areturn

  static java.lang.String access$000(software.amazon.awssdk.services.lexruntimev2.model.ActiveContext$BuilderImpl);
    Code:
       0: aload_0
       1: getfield      #5                  // Field name:Ljava/lang/String;
       4: areturn

  static software.amazon.awssdk.services.lexruntimev2.model.ActiveContextTimeToLive access$100(software.amazon.awssdk.services.lexruntimev2.model.ActiveContext$BuilderImpl);
    Code:
       0: aload_0
       1: getfield      #4                  // Field timeToLive:Lsoftware/amazon/awssdk/services/lexruntimev2/model/ActiveContextTimeToLive;
       4: areturn

  static java.util.Map access$200(software.amazon.awssdk.services.lexruntimev2.model.ActiveContext$BuilderImpl);
    Code:
       0: aload_0
       1: getfield      #3                  // Field contextAttributes:Ljava/util/Map;
       4: areturn

  software.amazon.awssdk.services.lexruntimev2.model.ActiveContext$BuilderImpl(software.amazon.awssdk.services.lexruntimev2.model.ActiveContext, software.amazon.awssdk.services.lexruntimev2.model.ActiveContext$1);
    Code:
       0: aload_0
       1: aload_1
       2: invokespecial #2                  // Method "<init>":(Lsoftware/amazon/awssdk/services/lexruntimev2/model/ActiveContext;)V
       5: return

  software.amazon.awssdk.services.lexruntimev2.model.ActiveContext$BuilderImpl(software.amazon.awssdk.services.lexruntimev2.model.ActiveContext$1);
    Code:
       0: aload_0
       1: invokespecial #1                  // Method "<init>":()V
       4: return
}
