Compiled from "RecognizeUtteranceRequest.java"
public interface software.amazon.awssdk.services.lexruntimev2.model.RecognizeUtteranceRequest$Builder extends software.amazon.awssdk.services.lexruntimev2.model.LexRuntimeV2Request$Builder, software.amazon.awssdk.core.SdkPojo, software.amazon.awssdk.utils.builder.CopyableBuilder<software.amazon.awssdk.services.lexruntimev2.model.RecognizeUtteranceRequest$Builder, software.amazon.awssdk.services.lexruntimev2.model.RecognizeUtteranceRequest> {
  public abstract software.amazon.awssdk.services.lexruntimev2.model.RecognizeUtteranceRequest$Builder botId(java.lang.String);

  public abstract software.amazon.awssdk.services.lexruntimev2.model.RecognizeUtteranceRequest$Builder botAliasId(java.lang.String);

  public abstract software.amazon.awssdk.services.lexruntimev2.model.RecognizeUtteranceRequest$Builder localeId(java.lang.String);

  public abstract software.amazon.awssdk.services.lexruntimev2.model.RecognizeUtteranceRequest$Builder sessionId(java.lang.String);

  public abstract software.amazon.awssdk.services.lexruntimev2.model.RecognizeUtteranceRequest$Builder sessionState(java.lang.String);

  public abstract software.amazon.awssdk.services.lexruntimev2.model.RecognizeUtteranceRequest$Builder requestAttributes(java.lang.String);

  public abstract software.amazon.awssdk.services.lexruntimev2.model.RecognizeUtteranceRequest$Builder requestContentType(java.lang.String);

  public abstract software.amazon.awssdk.services.lexruntimev2.model.RecognizeUtteranceRequest$Builder responseContentType(java.lang.String);

  public abstract software.amazon.awssdk.services.lexruntimev2.model.RecognizeUtteranceRequest$Builder overrideConfiguration(software.amazon.awssdk.awscore.AwsRequestOverrideConfiguration);

  public abstract software.amazon.awssdk.services.lexruntimev2.model.RecognizeUtteranceRequest$Builder overrideConfiguration(java.util.function.Consumer<software.amazon.awssdk.awscore.AwsRequestOverrideConfiguration$Builder>);

  public default software.amazon.awssdk.awscore.AwsRequest$Builder overrideConfiguration(java.util.function.Consumer);
    Code:
       0: aload_0
       1: aload_1
       2: invokeinterface #1,  2            // InterfaceMethod overrideConfiguration:(Ljava/util/function/Consumer;)Lsoftware/amazon/awssdk/services/lexruntimev2/model/RecognizeUtteranceRequest$Builder;
       7: areturn

  public default software.amazon.awssdk.awscore.AwsRequest$Builder overrideConfiguration(software.amazon.awssdk.awscore.AwsRequestOverrideConfiguration);
    Code:
       0: aload_0
       1: aload_1
       2: invokeinterface #2,  2            // InterfaceMethod overrideConfiguration:(Lsoftware/amazon/awssdk/awscore/AwsRequestOverrideConfiguration;)Lsoftware/amazon/awssdk/services/lexruntimev2/model/RecognizeUtteranceRequest$Builder;
       7: areturn
}
