Compiled from "NullConduitSelector.java"
public class org.apache.cxf.endpoint.NullConduitSelector implements org.apache.cxf.endpoint.ConduitSelector {
  private org.apache.cxf.endpoint.Endpoint endpoint;

  public org.apache.cxf.endpoint.NullConduitSelector();
    Code:
       0: aload_0
       1: invokespecial #1                  // Method java/lang/Object."<init>":()V
       4: return

  public void prepare(org.apache.cxf.message.Message);
    Code:
       0: return

  public org.apache.cxf.transport.Conduit selectConduit(org.apache.cxf.message.Message);
    Code:
       0: aconst_null
       1: areturn

  public void complete(org.apache.cxf.message.Exchange);
    Code:
       0: return

  public org.apache.cxf.endpoint.Endpoint getEndpoint();
    Code:
       0: aload_0
       1: getfield      #2                  // Field endpoint:Lorg/apache/cxf/endpoint/Endpoint;
       4: areturn

  public void setEndpoint(org.apache.cxf.endpoint.Endpoint);
    Code:
       0: aload_0
       1: aload_1
       2: putfield      #2                  // Field endpoint:Lorg/apache/cxf/endpoint/Endpoint;
       5: return
}
