Compiled from "LazyId.java"
class io.fluxcapacitor.javaclient.common.LazyId$CustomDeserializer extends com.fasterxml.jackson.databind.deser.std.StdScalarDeserializer<io.fluxcapacitor.javaclient.common.LazyId> {
  protected io.fluxcapacitor.javaclient.common.LazyId$CustomDeserializer();
    Code:
       0: aload_0
       1: ldc           #1                  // class io/fluxcapacitor/javaclient/common/LazyId
       3: invokespecial #3                  // Method com/fasterxml/jackson/databind/deser/std/StdScalarDeserializer."<init>":(Ljava/lang/Class;)V
       6: return

  public io.fluxcapacitor.javaclient.common.LazyId getNullValue(com.fasterxml.jackson.databind.DeserializationContext);
    Code:
       0: new           #1                  // class io/fluxcapacitor/javaclient/common/LazyId
       3: dup
       4: aconst_null
       5: invokespecial #9                  // Method io/fluxcapacitor/javaclient/common/LazyId."<init>":(Ljava/lang/Object;)V
       8: areturn

  public io.fluxcapacitor.javaclient.common.LazyId deserialize(com.fasterxml.jackson.core.JsonParser, com.fasterxml.jackson.databind.DeserializationContext) throws java.io.IOException;
    Code:
       0: new           #1                  // class io/fluxcapacitor/javaclient/common/LazyId
       3: dup
       4: aload_1
       5: invokevirtual #12                 // Method com/fasterxml/jackson/core/JsonParser.getText:()Ljava/lang/String;
       8: invokespecial #9                  // Method io/fluxcapacitor/javaclient/common/LazyId."<init>":(Ljava/lang/Object;)V
      11: areturn

  public java.lang.Object getNullValue(com.fasterxml.jackson.databind.DeserializationContext) throws com.fasterxml.jackson.databind.JsonMappingException;
    Code:
       0: aload_0
       1: aload_1
       2: invokevirtual #18                 // Method getNullValue:(Lcom/fasterxml/jackson/databind/DeserializationContext;)Lio/fluxcapacitor/javaclient/common/LazyId;
       5: areturn

  public java.lang.Object deserialize(com.fasterxml.jackson.core.JsonParser, com.fasterxml.jackson.databind.DeserializationContext) throws java.io.IOException, com.fasterxml.jackson.core.JacksonException;
    Code:
       0: aload_0
       1: aload_1
       2: aload_2
       3: invokevirtual #24                 // Method deserialize:(Lcom/fasterxml/jackson/core/JsonParser;Lcom/fasterxml/jackson/databind/DeserializationContext;)Lio/fluxcapacitor/javaclient/common/LazyId;
       6: areturn
}
