Compiled from "LazyId.java"
class io.fluxcapacitor.javaclient.common.LazyId$CustomSerializer extends com.fasterxml.jackson.databind.ser.std.StdScalarSerializer<io.fluxcapacitor.javaclient.common.LazyId> {
  protected io.fluxcapacitor.javaclient.common.LazyId$CustomSerializer();
    Code:
       0: aload_0
       1: ldc           #1                  // class io/fluxcapacitor/javaclient/common/LazyId
       3: invokespecial #3                  // Method com/fasterxml/jackson/databind/ser/std/StdScalarSerializer."<init>":(Ljava/lang/Class;)V
       6: return

  public void serialize(io.fluxcapacitor.javaclient.common.LazyId, com.fasterxml.jackson.core.JsonGenerator, com.fasterxml.jackson.databind.SerializerProvider) throws java.io.IOException;
    Code:
       0: aload_1
       1: ifnonnull     8
       4: aconst_null
       5: goto          12
       8: aload_1
       9: invokevirtual #9                  // Method io/fluxcapacitor/javaclient/common/LazyId.getId:()Ljava/lang/String;
      12: astore        4
      14: aload         4
      16: ifnonnull     26
      19: aload_2
      20: invokevirtual #13                 // Method com/fasterxml/jackson/core/JsonGenerator.writeNull:()V
      23: goto          32
      26: aload_2
      27: aload         4
      29: invokevirtual #19                 // Method com/fasterxml/jackson/core/JsonGenerator.writeString:(Ljava/lang/String;)V
      32: return

  public void serialize(java.lang.Object, com.fasterxml.jackson.core.JsonGenerator, com.fasterxml.jackson.databind.SerializerProvider) throws java.io.IOException;
    Code:
       0: aload_0
       1: aload_1
       2: checkcast     #1                  // class io/fluxcapacitor/javaclient/common/LazyId
       5: aload_2
       6: aload_3
       7: invokevirtual #23                 // Method serialize:(Lio/fluxcapacitor/javaclient/common/LazyId;Lcom/fasterxml/jackson/core/JsonGenerator;Lcom/fasterxml/jackson/databind/SerializerProvider;)V
      10: return
}
