Compiled from "ServiceMonitorHandler.java"
public class io.dekorate.prometheus.handler.ServiceMonitorHandler implements io.dekorate.Handler<io.dekorate.prometheus.config.ServiceMonitorConfig> {
  private final io.dekorate.Resources resources;

  public io.dekorate.prometheus.handler.ServiceMonitorHandler(io.dekorate.Resources);
    Code:
       0: aload_0
       1: invokespecial #1                  // Method java/lang/Object."<init>":()V
       4: aload_0
       5: aload_1
       6: putfield      #2                  // Field resources:Lio/dekorate/Resources;
       9: return

  public int order();
    Code:
       0: sipush        450
       3: ireturn

  public void handle(io.dekorate.prometheus.config.ServiceMonitorConfig);
    Code:
       0: aload_0
       1: getfield      #2                  // Field resources:Lio/dekorate/Resources;
       4: new           #3                  // class io/dekorate/prometheus/decorator/AddServiceMonitorResourceDecorator
       7: dup
       8: aload_1
       9: invokespecial #4                  // Method io/dekorate/prometheus/decorator/AddServiceMonitorResourceDecorator."<init>":(Lio/dekorate/prometheus/config/ServiceMonitorConfig;)V
      12: invokevirtual #5                  // Method io/dekorate/Resources.decorate:(Lio/dekorate/kubernetes/decorator/Decorator;)V
      15: return

  public boolean canHandle(java.lang.Class<? extends io.dekorate.kubernetes.config.Configuration>);
    Code:
       0: aload_1
       1: ldc           #6                  // class io/dekorate/prometheus/config/ServiceMonitorConfig
       3: invokevirtual #7                  // Method java/lang/Object.equals:(Ljava/lang/Object;)Z
       6: ifne          18
       9: aload_1
      10: ldc           #8                  // class io/dekorate/prometheus/config/EditableServiceMonitorConfig
      12: invokevirtual #7                  // Method java/lang/Object.equals:(Ljava/lang/Object;)Z
      15: ifeq          22
      18: iconst_1
      19: goto          23
      22: iconst_0
      23: ireturn

  public void handle(io.dekorate.kubernetes.config.Configuration);
    Code:
       0: aload_0
       1: aload_1
       2: checkcast     #6                  // class io/dekorate/prometheus/config/ServiceMonitorConfig
       5: invokevirtual #9                  // Method handle:(Lio/dekorate/prometheus/config/ServiceMonitorConfig;)V
       8: return
}
