Compiled from "BasicDeserializerFactory.java"
public class com.fasterxml.jackson.databind.deser.BasicDeserializerFactory$CreatorCollectionState {
  public final com.fasterxml.jackson.databind.DeserializationContext context;

  public final com.fasterxml.jackson.databind.BeanDescription beanDesc;

  public final com.fasterxml.jackson.databind.introspect.VisibilityChecker<?> vchecker;

  public final com.fasterxml.jackson.databind.deser.impl.CreatorCollector creators;

  public final java.util.Map<com.fasterxml.jackson.databind.introspect.AnnotatedWithParams, com.fasterxml.jackson.databind.introspect.BeanPropertyDefinition[]> creatorParams;

  private java.util.List<com.fasterxml.jackson.databind.deser.impl.CreatorCandidate> _implicitFactoryCandidates;

  private int _explicitFactoryCount;

  private java.util.List<com.fasterxml.jackson.databind.deser.impl.CreatorCandidate> _implicitConstructorCandidates;

  private int _explicitConstructorCount;

  public com.fasterxml.jackson.databind.deser.BasicDeserializerFactory$CreatorCollectionState(com.fasterxml.jackson.databind.DeserializationContext, com.fasterxml.jackson.databind.BeanDescription, com.fasterxml.jackson.databind.introspect.VisibilityChecker<?>, com.fasterxml.jackson.databind.deser.impl.CreatorCollector, java.util.Map<com.fasterxml.jackson.databind.introspect.AnnotatedWithParams, com.fasterxml.jackson.databind.introspect.BeanPropertyDefinition[]>);
    Code:
       0: aload_0
       1: invokespecial #1                  // Method java/lang/Object."<init>":()V
       4: aload_0
       5: aload_1
       6: putfield      #2                  // Field context:Lcom/fasterxml/jackson/databind/DeserializationContext;
       9: aload_0
      10: aload_2
      11: putfield      #3                  // Field beanDesc:Lcom/fasterxml/jackson/databind/BeanDescription;
      14: aload_0
      15: aload_3
      16: putfield      #4                  // Field vchecker:Lcom/fasterxml/jackson/databind/introspect/VisibilityChecker;
      19: aload_0
      20: aload         4
      22: putfield      #5                  // Field creators:Lcom/fasterxml/jackson/databind/deser/impl/CreatorCollector;
      25: aload_0
      26: aload         5
      28: putfield      #6                  // Field creatorParams:Ljava/util/Map;
      31: return

  public com.fasterxml.jackson.databind.AnnotationIntrospector annotationIntrospector();
    Code:
       0: aload_0
       1: getfield      #2                  // Field context:Lcom/fasterxml/jackson/databind/DeserializationContext;
       4: invokevirtual #7                  // Method com/fasterxml/jackson/databind/DeserializationContext.getAnnotationIntrospector:()Lcom/fasterxml/jackson/databind/AnnotationIntrospector;
       7: areturn

  public void addImplicitFactoryCandidate(com.fasterxml.jackson.databind.deser.impl.CreatorCandidate);
    Code:
       0: aload_0
       1: getfield      #8                  // Field _implicitFactoryCandidates:Ljava/util/List;
       4: ifnonnull     18
       7: aload_0
       8: new           #9                  // class java/util/LinkedList
      11: dup
      12: invokespecial #10                 // Method java/util/LinkedList."<init>":()V
      15: putfield      #8                  // Field _implicitFactoryCandidates:Ljava/util/List;
      18: aload_0
      19: getfield      #8                  // Field _implicitFactoryCandidates:Ljava/util/List;
      22: aload_1
      23: invokeinterface #11,  2           // InterfaceMethod java/util/List.add:(Ljava/lang/Object;)Z
      28: pop
      29: return

  public void increaseExplicitFactoryCount();
    Code:
       0: aload_0
       1: dup
       2: getfield      #12                 // Field _explicitFactoryCount:I
       5: iconst_1
       6: iadd
       7: putfield      #12                 // Field _explicitFactoryCount:I
      10: return

  public boolean hasExplicitFactories();
    Code:
       0: aload_0
       1: getfield      #12                 // Field _explicitFactoryCount:I
       4: ifle          11
       7: iconst_1
       8: goto          12
      11: iconst_0
      12: ireturn

  public boolean hasImplicitFactoryCandidates();
    Code:
       0: aload_0
       1: getfield      #8                  // Field _implicitFactoryCandidates:Ljava/util/List;
       4: ifnull        11
       7: iconst_1
       8: goto          12
      11: iconst_0
      12: ireturn

  public java.util.List<com.fasterxml.jackson.databind.deser.impl.CreatorCandidate> implicitFactoryCandidates();
    Code:
       0: aload_0
       1: getfield      #8                  // Field _implicitFactoryCandidates:Ljava/util/List;
       4: areturn

  public void addImplicitConstructorCandidate(com.fasterxml.jackson.databind.deser.impl.CreatorCandidate);
    Code:
       0: aload_0
       1: getfield      #13                 // Field _implicitConstructorCandidates:Ljava/util/List;
       4: ifnonnull     18
       7: aload_0
       8: new           #9                  // class java/util/LinkedList
      11: dup
      12: invokespecial #10                 // Method java/util/LinkedList."<init>":()V
      15: putfield      #13                 // Field _implicitConstructorCandidates:Ljava/util/List;
      18: aload_0
      19: getfield      #13                 // Field _implicitConstructorCandidates:Ljava/util/List;
      22: aload_1
      23: invokeinterface #11,  2           // InterfaceMethod java/util/List.add:(Ljava/lang/Object;)Z
      28: pop
      29: return

  public void increaseExplicitConstructorCount();
    Code:
       0: aload_0
       1: dup
       2: getfield      #14                 // Field _explicitConstructorCount:I
       5: iconst_1
       6: iadd
       7: putfield      #14                 // Field _explicitConstructorCount:I
      10: return

  public boolean hasExplicitConstructors();
    Code:
       0: aload_0
       1: getfield      #14                 // Field _explicitConstructorCount:I
       4: ifle          11
       7: iconst_1
       8: goto          12
      11: iconst_0
      12: ireturn

  public boolean hasImplicitConstructorCandidates();
    Code:
       0: aload_0
       1: getfield      #13                 // Field _implicitConstructorCandidates:Ljava/util/List;
       4: ifnull        11
       7: iconst_1
       8: goto          12
      11: iconst_0
      12: ireturn

  public java.util.List<com.fasterxml.jackson.databind.deser.impl.CreatorCandidate> implicitConstructorCandidates();
    Code:
       0: aload_0
       1: getfield      #13                 // Field _implicitConstructorCandidates:Ljava/util/List;
       4: areturn
}
