Compiled from "RabbitProperties.java"
public class org.springframework.boot.autoconfigure.amqp.RabbitProperties$ListenerRetry extends org.springframework.boot.autoconfigure.amqp.RabbitProperties$Retry {
  private boolean stateless;

  public org.springframework.boot.autoconfigure.amqp.RabbitProperties$ListenerRetry();
    Code:
       0: aload_0
       1: invokespecial #1                  // Method org/springframework/boot/autoconfigure/amqp/RabbitProperties$Retry."<init>":()V
       4: aload_0
       5: iconst_1
       6: putfield      #2                  // Field stateless:Z
       9: return

  public boolean isStateless();
    Code:
       0: aload_0
       1: getfield      #2                  // Field stateless:Z
       4: ireturn

  public void setStateless(boolean);
    Code:
       0: aload_0
       1: iload_1
       2: putfield      #2                  // Field stateless:Z
       5: return
}
