Compiled from "NetUtils.java"
public class org.apache.bookkeeper.clients.utils.NetUtils {
  public org.apache.bookkeeper.clients.utils.NetUtils();
    Code:
       0: aload_0
       1: invokespecial #1                  // Method java/lang/Object."<init>":()V
       4: return

  public static java.net.InetSocketAddress of(org.apache.bookkeeper.stream.proto.common.Endpoint);
    Code:
       0: new           #2                  // class java/net/InetSocketAddress
       3: dup
       4: aload_0
       5: invokevirtual #3                  // Method org/apache/bookkeeper/stream/proto/common/Endpoint.getHostname:()Ljava/lang/String;
       8: aload_0
       9: invokevirtual #4                  // Method org/apache/bookkeeper/stream/proto/common/Endpoint.getPort:()I
      12: invokespecial #5                  // Method java/net/InetSocketAddress."<init>":(Ljava/lang/String;I)V
      15: areturn

  public static java.lang.String getLocalHostName(boolean);
    Code:
       0: iload_0
       1: ifeq          14
       4: invokestatic  #6                  // Method java/net/InetAddress.getLocalHost:()Ljava/net/InetAddress;
       7: invokevirtual #7                  // Method java/net/InetAddress.getHostName:()Ljava/lang/String;
      10: astore_1
      11: goto          21
      14: invokestatic  #6                  // Method java/net/InetAddress.getLocalHost:()Ljava/net/InetAddress;
      17: invokevirtual #8                  // Method java/net/InetAddress.getHostAddress:()Ljava/lang/String;
      20: astore_1
      21: goto          28
      24: astore_2
      25: ldc           #10                 // String Unknown-Host-Name
      27: astore_1
      28: aload_1
      29: areturn
    Exception table:
       from    to  target type
           0    21    24   Class java/net/UnknownHostException

  public static org.apache.bookkeeper.stream.proto.common.Endpoint getLocalEndpoint(int, boolean) throws java.net.UnknownHostException;
    Code:
       0: iload_1
       1: ifeq          14
       4: invokestatic  #6                  // Method java/net/InetAddress.getLocalHost:()Ljava/net/InetAddress;
       7: invokevirtual #7                  // Method java/net/InetAddress.getHostName:()Ljava/lang/String;
      10: astore_2
      11: goto          21
      14: invokestatic  #6                  // Method java/net/InetAddress.getLocalHost:()Ljava/net/InetAddress;
      17: invokevirtual #8                  // Method java/net/InetAddress.getHostAddress:()Ljava/lang/String;
      20: astore_2
      21: aload_2
      22: iload_0
      23: invokestatic  #11                 // Method createEndpoint:(Ljava/lang/String;I)Lorg/apache/bookkeeper/stream/proto/common/Endpoint;
      26: areturn

  public static java.util.List<org.apache.bookkeeper.stream.proto.common.Endpoint> parseEndpoints(java.lang.String);
    Code:
       0: aload_0
       1: bipush        44
       3: invokestatic  #12                 // Method org/apache/commons/lang/StringUtils.split:(Ljava/lang/String;C)[Ljava/lang/String;
       6: astore_1
       7: aload_1
       8: arraylength
       9: ifle          16
      12: iconst_1
      13: goto          17
      16: iconst_0
      17: ldc           #13                 // String Invalid endpoint strings %s
      19: aload_0
      20: invokestatic  #14                 // Method com/google/common/base/Preconditions.checkArgument:(ZLjava/lang/String;Ljava/lang/Object;)V
      23: aload_1
      24: arraylength
      25: invokestatic  #15                 // Method com/google/common/collect/Lists.newArrayListWithExpectedSize:(I)Ljava/util/ArrayList;
      28: astore_2
      29: aload_1
      30: astore_3
      31: aload_3
      32: arraylength
      33: istore        4
      35: iconst_0
      36: istore        5
      38: iload         5
      40: iload         4
      42: if_icmpge     69
      45: aload_3
      46: iload         5
      48: aaload
      49: astore        6
      51: aload_2
      52: aload         6
      54: invokestatic  #16                 // Method parseEndpoint:(Ljava/lang/String;)Lorg/apache/bookkeeper/stream/proto/common/Endpoint;
      57: invokeinterface #17,  2           // InterfaceMethod java/util/List.add:(Ljava/lang/Object;)Z
      62: pop
      63: iinc          5, 1
      66: goto          38
      69: aload_2
      70: areturn

  public static org.apache.bookkeeper.stream.proto.common.Endpoint parseEndpoint(java.lang.String);
    Code:
       0: aload_0
       1: bipush        58
       3: invokestatic  #12                 // Method org/apache/commons/lang/StringUtils.split:(Ljava/lang/String;C)[Ljava/lang/String;
       6: astore_1
       7: iconst_2
       8: aload_1
       9: arraylength
      10: if_icmpne     17
      13: iconst_1
      14: goto          18
      17: iconst_0
      18: ldc           #18                 // String Invalid endpoint string %s - It should be \'host:port\'.
      20: aload_0
      21: invokestatic  #14                 // Method com/google/common/base/Preconditions.checkArgument:(ZLjava/lang/String;Ljava/lang/Object;)V
      24: aload_1
      25: iconst_0
      26: aaload
      27: astore_2
      28: aload_1
      29: iconst_1
      30: aaload
      31: invokestatic  #19                 // Method java/lang/Integer.parseInt:(Ljava/lang/String;)I
      34: istore_3
      35: goto          69
      38: astore        4
      40: new           #21                 // class java/lang/IllegalArgumentException
      43: dup
      44: new           #22                 // class java/lang/StringBuilder
      47: dup
      48: invokespecial #23                 // Method java/lang/StringBuilder."<init>":()V
      51: ldc           #24                 // String Invalid port found in the endpoint string
      53: invokevirtual #25                 // Method java/lang/StringBuilder.append:(Ljava/lang/String;)Ljava/lang/StringBuilder;
      56: aload_0
      57: invokevirtual #25                 // Method java/lang/StringBuilder.append:(Ljava/lang/String;)Ljava/lang/StringBuilder;
      60: invokevirtual #26                 // Method java/lang/StringBuilder.toString:()Ljava/lang/String;
      63: aload         4
      65: invokespecial #27                 // Method java/lang/IllegalArgumentException."<init>":(Ljava/lang/String;Ljava/lang/Throwable;)V
      68: athrow
      69: aload_2
      70: iload_3
      71: invokestatic  #11                 // Method createEndpoint:(Ljava/lang/String;I)Lorg/apache/bookkeeper/stream/proto/common/Endpoint;
      74: areturn
    Exception table:
       from    to  target type
          28    35    38   Class java/lang/NumberFormatException

  public static org.apache.bookkeeper.stream.proto.common.Endpoint createEndpoint(java.lang.String, int);
    Code:
       0: invokestatic  #28                 // Method org/apache/bookkeeper/stream/proto/common/Endpoint.newBuilder:()Lorg/apache/bookkeeper/stream/proto/common/Endpoint$Builder;
       3: aload_0
       4: invokevirtual #29                 // Method org/apache/bookkeeper/stream/proto/common/Endpoint$Builder.setHostname:(Ljava/lang/String;)Lorg/apache/bookkeeper/stream/proto/common/Endpoint$Builder;
       7: iload_1
       8: invokevirtual #30                 // Method org/apache/bookkeeper/stream/proto/common/Endpoint$Builder.setPort:(I)Lorg/apache/bookkeeper/stream/proto/common/Endpoint$Builder;
      11: invokevirtual #31                 // Method org/apache/bookkeeper/stream/proto/common/Endpoint$Builder.build:()Lorg/apache/bookkeeper/stream/proto/common/Endpoint;
      14: areturn

  public static java.lang.String endpointToString(org.apache.bookkeeper.stream.proto.common.Endpoint);
    Code:
       0: new           #22                 // class java/lang/StringBuilder
       3: dup
       4: invokespecial #23                 // Method java/lang/StringBuilder."<init>":()V
       7: astore_1
       8: aload_1
       9: aload_0
      10: invokevirtual #3                  // Method org/apache/bookkeeper/stream/proto/common/Endpoint.getHostname:()Ljava/lang/String;
      13: invokevirtual #25                 // Method java/lang/StringBuilder.append:(Ljava/lang/String;)Ljava/lang/StringBuilder;
      16: ldc           #32                 // String :
      18: invokevirtual #25                 // Method java/lang/StringBuilder.append:(Ljava/lang/String;)Ljava/lang/StringBuilder;
      21: aload_0
      22: invokevirtual #4                  // Method org/apache/bookkeeper/stream/proto/common/Endpoint.getPort:()I
      25: invokevirtual #33                 // Method java/lang/StringBuilder.append:(I)Ljava/lang/StringBuilder;
      28: pop
      29: aload_1
      30: invokevirtual #26                 // Method java/lang/StringBuilder.toString:()Ljava/lang/String;
      33: areturn
}
