Compiled from "ElementTo.java"
final class io.sundr.codegen.functions.ElementTo$4 implements io.sundr.Function<javax.lang.model.type.TypeMirror, io.sundr.codegen.model.TypeRef> {
  io.sundr.codegen.functions.ElementTo$4();
    Code:
       0: aload_0
       1: invokespecial #14                 // Method java/lang/Object."<init>":()V
       4: return

  public io.sundr.codegen.model.TypeRef apply(javax.lang.model.type.TypeMirror);
    Code:
       0: aload_1
       1: new           #20                 // class io/sundr/codegen/converters/TypeRefTypeVisitor
       4: dup
       5: invokespecial #21                 // Method io/sundr/codegen/converters/TypeRefTypeVisitor."<init>":()V
       8: iconst_0
       9: invokestatic  #27                 // Method java/lang/Integer.valueOf:(I)Ljava/lang/Integer;
      12: invokeinterface #33,  3           // InterfaceMethod javax/lang/model/type/TypeMirror.accept:(Ljavax/lang/model/type/TypeVisitor;Ljava/lang/Object;)Ljava/lang/Object;
      17: checkcast     #35                 // class io/sundr/codegen/model/TypeRef
      20: areturn

  public java.lang.Object apply(java.lang.Object);
    Code:
       0: aload_0
       1: aload_1
       2: checkcast     #29                 // class javax/lang/model/type/TypeMirror
       5: invokevirtual #40                 // Method apply:(Ljavax/lang/model/type/TypeMirror;)Lio/sundr/codegen/model/TypeRef;
       8: areturn
}
