Compiled from "RouteLookupConfig.java"
public final class io.grpc.lookup.v1.RouteLookupConfig$Builder extends com.google.protobuf.GeneratedMessageV3$Builder<io.grpc.lookup.v1.RouteLookupConfig$Builder> implements io.grpc.lookup.v1.RouteLookupConfigOrBuilder {
  private int bitField0_;

  private java.util.List<io.grpc.lookup.v1.HttpKeyBuilder> httpKeybuilders_;

  private com.google.protobuf.RepeatedFieldBuilderV3<io.grpc.lookup.v1.HttpKeyBuilder, io.grpc.lookup.v1.HttpKeyBuilder$Builder, io.grpc.lookup.v1.HttpKeyBuilderOrBuilder> httpKeybuildersBuilder_;

  private java.util.List<io.grpc.lookup.v1.GrpcKeyBuilder> grpcKeybuilders_;

  private com.google.protobuf.RepeatedFieldBuilderV3<io.grpc.lookup.v1.GrpcKeyBuilder, io.grpc.lookup.v1.GrpcKeyBuilder$Builder, io.grpc.lookup.v1.GrpcKeyBuilderOrBuilder> grpcKeybuildersBuilder_;

  private java.lang.Object lookupService_;

  private com.google.protobuf.Duration lookupServiceTimeout_;

  private com.google.protobuf.SingleFieldBuilderV3<com.google.protobuf.Duration, com.google.protobuf.Duration$Builder, com.google.protobuf.DurationOrBuilder> lookupServiceTimeoutBuilder_;

  private com.google.protobuf.Duration maxAge_;

  private com.google.protobuf.SingleFieldBuilderV3<com.google.protobuf.Duration, com.google.protobuf.Duration$Builder, com.google.protobuf.DurationOrBuilder> maxAgeBuilder_;

  private com.google.protobuf.Duration staleAge_;

  private com.google.protobuf.SingleFieldBuilderV3<com.google.protobuf.Duration, com.google.protobuf.Duration$Builder, com.google.protobuf.DurationOrBuilder> staleAgeBuilder_;

  private long cacheSizeBytes_;

  private com.google.protobuf.LazyStringList validTargets_;

  private java.lang.Object defaultTarget_;

  public static final com.google.protobuf.Descriptors$Descriptor getDescriptor();
    Code:
       0: getstatic     #3                  // Field io/grpc/lookup/v1/RlsConfigProto.internal_static_grpc_lookup_v1_RouteLookupConfig_descriptor:Lcom/google/protobuf/Descriptors$Descriptor;
       3: areturn

  protected com.google.protobuf.GeneratedMessageV3$FieldAccessorTable internalGetFieldAccessorTable();
    Code:
       0: getstatic     #4                  // Field io/grpc/lookup/v1/RlsConfigProto.internal_static_grpc_lookup_v1_RouteLookupConfig_fieldAccessorTable:Lcom/google/protobuf/GeneratedMessageV3$FieldAccessorTable;
       3: ldc           #5                  // class io/grpc/lookup/v1/RouteLookupConfig
       5: ldc           #6                  // class io/grpc/lookup/v1/RouteLookupConfig$Builder
       7: invokevirtual #7                  // Method com/google/protobuf/GeneratedMessageV3$FieldAccessorTable.ensureFieldAccessorsInitialized:(Ljava/lang/Class;Ljava/lang/Class;)Lcom/google/protobuf/GeneratedMessageV3$FieldAccessorTable;
      10: areturn

  private io.grpc.lookup.v1.RouteLookupConfig$Builder();
    Code:
       0: aload_0
       1: invokespecial #8                  // Method com/google/protobuf/GeneratedMessageV3$Builder."<init>":()V
       4: aload_0
       5: invokestatic  #9                  // Method java/util/Collections.emptyList:()Ljava/util/List;
       8: putfield      #10                 // Field httpKeybuilders_:Ljava/util/List;
      11: aload_0
      12: invokestatic  #9                  // Method java/util/Collections.emptyList:()Ljava/util/List;
      15: putfield      #11                 // Field grpcKeybuilders_:Ljava/util/List;
      18: aload_0
      19: ldc           #12                 // String
      21: putfield      #13                 // Field lookupService_:Ljava/lang/Object;
      24: aload_0
      25: getstatic     #14                 // Field com/google/protobuf/LazyStringArrayList.EMPTY:Lcom/google/protobuf/LazyStringList;
      28: putfield      #15                 // Field validTargets_:Lcom/google/protobuf/LazyStringList;
      31: aload_0
      32: ldc           #12                 // String
      34: putfield      #16                 // Field defaultTarget_:Ljava/lang/Object;
      37: aload_0
      38: invokespecial #17                 // Method maybeForceBuilderInitialization:()V
      41: return

  private io.grpc.lookup.v1.RouteLookupConfig$Builder(com.google.protobuf.GeneratedMessageV3$BuilderParent);
    Code:
       0: aload_0
       1: aload_1
       2: invokespecial #18                 // Method com/google/protobuf/GeneratedMessageV3$Builder."<init>":(Lcom/google/protobuf/GeneratedMessageV3$BuilderParent;)V
       5: aload_0
       6: invokestatic  #9                  // Method java/util/Collections.emptyList:()Ljava/util/List;
       9: putfield      #10                 // Field httpKeybuilders_:Ljava/util/List;
      12: aload_0
      13: invokestatic  #9                  // Method java/util/Collections.emptyList:()Ljava/util/List;
      16: putfield      #11                 // Field grpcKeybuilders_:Ljava/util/List;
      19: aload_0
      20: ldc           #12                 // String
      22: putfield      #13                 // Field lookupService_:Ljava/lang/Object;
      25: aload_0
      26: getstatic     #14                 // Field com/google/protobuf/LazyStringArrayList.EMPTY:Lcom/google/protobuf/LazyStringList;
      29: putfield      #15                 // Field validTargets_:Lcom/google/protobuf/LazyStringList;
      32: aload_0
      33: ldc           #12                 // String
      35: putfield      #16                 // Field defaultTarget_:Ljava/lang/Object;
      38: aload_0
      39: invokespecial #17                 // Method maybeForceBuilderInitialization:()V
      42: return

  private void maybeForceBuilderInitialization();
    Code:
       0: invokestatic  #19                 // Method io/grpc/lookup/v1/RouteLookupConfig.access$200:()Z
       3: ifeq          16
       6: aload_0
       7: invokespecial #20                 // Method getHttpKeybuildersFieldBuilder:()Lcom/google/protobuf/RepeatedFieldBuilderV3;
      10: pop
      11: aload_0
      12: invokespecial #21                 // Method getGrpcKeybuildersFieldBuilder:()Lcom/google/protobuf/RepeatedFieldBuilderV3;
      15: pop
      16: return

  public io.grpc.lookup.v1.RouteLookupConfig$Builder clear();
    Code:
       0: aload_0
       1: invokespecial #22                 // Method com/google/protobuf/GeneratedMessageV3$Builder.clear:()Lcom/google/protobuf/GeneratedMessageV3$Builder;
       4: pop
       5: aload_0
       6: getfield      #23                 // Field httpKeybuildersBuilder_:Lcom/google/protobuf/RepeatedFieldBuilderV3;
       9: ifnonnull     33
      12: aload_0
      13: invokestatic  #9                  // Method java/util/Collections.emptyList:()Ljava/util/List;
      16: putfield      #10                 // Field httpKeybuilders_:Ljava/util/List;
      19: aload_0
      20: aload_0
      21: getfield      #24                 // Field bitField0_:I
      24: bipush        -2
      26: iand
      27: putfield      #24                 // Field bitField0_:I
      30: goto          40
      33: aload_0
      34: getfield      #23                 // Field httpKeybuildersBuilder_:Lcom/google/protobuf/RepeatedFieldBuilderV3;
      37: invokevirtual #25                 // Method com/google/protobuf/RepeatedFieldBuilderV3.clear:()V
      40: aload_0
      41: getfield      #26                 // Field grpcKeybuildersBuilder_:Lcom/google/protobuf/RepeatedFieldBuilderV3;
      44: ifnonnull     68
      47: aload_0
      48: invokestatic  #9                  // Method java/util/Collections.emptyList:()Ljava/util/List;
      51: putfield      #11                 // Field grpcKeybuilders_:Ljava/util/List;
      54: aload_0
      55: aload_0
      56: getfield      #24                 // Field bitField0_:I
      59: bipush        -3
      61: iand
      62: putfield      #24                 // Field bitField0_:I
      65: goto          75
      68: aload_0
      69: getfield      #26                 // Field grpcKeybuildersBuilder_:Lcom/google/protobuf/RepeatedFieldBuilderV3;
      72: invokevirtual #25                 // Method com/google/protobuf/RepeatedFieldBuilderV3.clear:()V
      75: aload_0
      76: ldc           #12                 // String
      78: putfield      #13                 // Field lookupService_:Ljava/lang/Object;
      81: aload_0
      82: getfield      #27                 // Field lookupServiceTimeoutBuilder_:Lcom/google/protobuf/SingleFieldBuilderV3;
      85: ifnonnull     96
      88: aload_0
      89: aconst_null
      90: putfield      #28                 // Field lookupServiceTimeout_:Lcom/google/protobuf/Duration;
      93: goto          106
      96: aload_0
      97: aconst_null
      98: putfield      #28                 // Field lookupServiceTimeout_:Lcom/google/protobuf/Duration;
     101: aload_0
     102: aconst_null
     103: putfield      #27                 // Field lookupServiceTimeoutBuilder_:Lcom/google/protobuf/SingleFieldBuilderV3;
     106: aload_0
     107: getfield      #29                 // Field maxAgeBuilder_:Lcom/google/protobuf/SingleFieldBuilderV3;
     110: ifnonnull     121
     113: aload_0
     114: aconst_null
     115: putfield      #30                 // Field maxAge_:Lcom/google/protobuf/Duration;
     118: goto          131
     121: aload_0
     122: aconst_null
     123: putfield      #30                 // Field maxAge_:Lcom/google/protobuf/Duration;
     126: aload_0
     127: aconst_null
     128: putfield      #29                 // Field maxAgeBuilder_:Lcom/google/protobuf/SingleFieldBuilderV3;
     131: aload_0
     132: getfield      #31                 // Field staleAgeBuilder_:Lcom/google/protobuf/SingleFieldBuilderV3;
     135: ifnonnull     146
     138: aload_0
     139: aconst_null
     140: putfield      #32                 // Field staleAge_:Lcom/google/protobuf/Duration;
     143: goto          156
     146: aload_0
     147: aconst_null
     148: putfield      #32                 // Field staleAge_:Lcom/google/protobuf/Duration;
     151: aload_0
     152: aconst_null
     153: putfield      #31                 // Field staleAgeBuilder_:Lcom/google/protobuf/SingleFieldBuilderV3;
     156: aload_0
     157: lconst_0
     158: putfield      #33                 // Field cacheSizeBytes_:J
     161: aload_0
     162: getstatic     #14                 // Field com/google/protobuf/LazyStringArrayList.EMPTY:Lcom/google/protobuf/LazyStringList;
     165: putfield      #15                 // Field validTargets_:Lcom/google/protobuf/LazyStringList;
     168: aload_0
     169: aload_0
     170: getfield      #24                 // Field bitField0_:I
     173: bipush        -5
     175: iand
     176: putfield      #24                 // Field bitField0_:I
     179: aload_0
     180: ldc           #12                 // String
     182: putfield      #16                 // Field defaultTarget_:Ljava/lang/Object;
     185: aload_0
     186: areturn

  public com.google.protobuf.Descriptors$Descriptor getDescriptorForType();
    Code:
       0: getstatic     #3                  // Field io/grpc/lookup/v1/RlsConfigProto.internal_static_grpc_lookup_v1_RouteLookupConfig_descriptor:Lcom/google/protobuf/Descriptors$Descriptor;
       3: areturn

  public io.grpc.lookup.v1.RouteLookupConfig getDefaultInstanceForType();
    Code:
       0: invokestatic  #34                 // Method io/grpc/lookup/v1/RouteLookupConfig.getDefaultInstance:()Lio/grpc/lookup/v1/RouteLookupConfig;
       3: areturn

  public io.grpc.lookup.v1.RouteLookupConfig build();
    Code:
       0: aload_0
       1: invokevirtual #35                 // Method buildPartial:()Lio/grpc/lookup/v1/RouteLookupConfig;
       4: astore_1
       5: aload_1
       6: invokevirtual #36                 // Method io/grpc/lookup/v1/RouteLookupConfig.isInitialized:()Z
       9: ifne          17
      12: aload_1
      13: invokestatic  #37                 // Method newUninitializedMessageException:(Lcom/google/protobuf/Message;)Lcom/google/protobuf/UninitializedMessageException;
      16: athrow
      17: aload_1
      18: areturn

  public io.grpc.lookup.v1.RouteLookupConfig buildPartial();
    Code:
       0: new           #5                  // class io/grpc/lookup/v1/RouteLookupConfig
       3: dup
       4: aload_0
       5: aconst_null
       6: invokespecial #38                 // Method io/grpc/lookup/v1/RouteLookupConfig."<init>":(Lcom/google/protobuf/GeneratedMessageV3$Builder;Lio/grpc/lookup/v1/RouteLookupConfig$1;)V
       9: astore_1
      10: aload_0
      11: getfield      #24                 // Field bitField0_:I
      14: istore_2
      15: aload_0
      16: getfield      #23                 // Field httpKeybuildersBuilder_:Lcom/google/protobuf/RepeatedFieldBuilderV3;
      19: ifnonnull     65
      22: aload_0
      23: getfield      #24                 // Field bitField0_:I
      26: iconst_1
      27: iand
      28: ifeq          53
      31: aload_0
      32: aload_0
      33: getfield      #10                 // Field httpKeybuilders_:Ljava/util/List;
      36: invokestatic  #39                 // Method java/util/Collections.unmodifiableList:(Ljava/util/List;)Ljava/util/List;
      39: putfield      #10                 // Field httpKeybuilders_:Ljava/util/List;
      42: aload_0
      43: aload_0
      44: getfield      #24                 // Field bitField0_:I
      47: bipush        -2
      49: iand
      50: putfield      #24                 // Field bitField0_:I
      53: aload_1
      54: aload_0
      55: getfield      #10                 // Field httpKeybuilders_:Ljava/util/List;
      58: invokestatic  #40                 // Method io/grpc/lookup/v1/RouteLookupConfig.access$402:(Lio/grpc/lookup/v1/RouteLookupConfig;Ljava/util/List;)Ljava/util/List;
      61: pop
      62: goto          77
      65: aload_1
      66: aload_0
      67: getfield      #23                 // Field httpKeybuildersBuilder_:Lcom/google/protobuf/RepeatedFieldBuilderV3;
      70: invokevirtual #41                 // Method com/google/protobuf/RepeatedFieldBuilderV3.build:()Ljava/util/List;
      73: invokestatic  #40                 // Method io/grpc/lookup/v1/RouteLookupConfig.access$402:(Lio/grpc/lookup/v1/RouteLookupConfig;Ljava/util/List;)Ljava/util/List;
      76: pop
      77: aload_0
      78: getfield      #26                 // Field grpcKeybuildersBuilder_:Lcom/google/protobuf/RepeatedFieldBuilderV3;
      81: ifnonnull     127
      84: aload_0
      85: getfield      #24                 // Field bitField0_:I
      88: iconst_2
      89: iand
      90: ifeq          115
      93: aload_0
      94: aload_0
      95: getfield      #11                 // Field grpcKeybuilders_:Ljava/util/List;
      98: invokestatic  #39                 // Method java/util/Collections.unmodifiableList:(Ljava/util/List;)Ljava/util/List;
     101: putfield      #11                 // Field grpcKeybuilders_:Ljava/util/List;
     104: aload_0
     105: aload_0
     106: getfield      #24                 // Field bitField0_:I
     109: bipush        -3
     111: iand
     112: putfield      #24                 // Field bitField0_:I
     115: aload_1
     116: aload_0
     117: getfield      #11                 // Field grpcKeybuilders_:Ljava/util/List;
     120: invokestatic  #42                 // Method io/grpc/lookup/v1/RouteLookupConfig.access$502:(Lio/grpc/lookup/v1/RouteLookupConfig;Ljava/util/List;)Ljava/util/List;
     123: pop
     124: goto          139
     127: aload_1
     128: aload_0
     129: getfield      #26                 // Field grpcKeybuildersBuilder_:Lcom/google/protobuf/RepeatedFieldBuilderV3;
     132: invokevirtual #41                 // Method com/google/protobuf/RepeatedFieldBuilderV3.build:()Ljava/util/List;
     135: invokestatic  #42                 // Method io/grpc/lookup/v1/RouteLookupConfig.access$502:(Lio/grpc/lookup/v1/RouteLookupConfig;Ljava/util/List;)Ljava/util/List;
     138: pop
     139: aload_1
     140: aload_0
     141: getfield      #13                 // Field lookupService_:Ljava/lang/Object;
     144: invokestatic  #43                 // Method io/grpc/lookup/v1/RouteLookupConfig.access$602:(Lio/grpc/lookup/v1/RouteLookupConfig;Ljava/lang/Object;)Ljava/lang/Object;
     147: pop
     148: aload_0
     149: getfield      #27                 // Field lookupServiceTimeoutBuilder_:Lcom/google/protobuf/SingleFieldBuilderV3;
     152: ifnonnull     167
     155: aload_1
     156: aload_0
     157: getfield      #28                 // Field lookupServiceTimeout_:Lcom/google/protobuf/Duration;
     160: invokestatic  #44                 // Method io/grpc/lookup/v1/RouteLookupConfig.access$702:(Lio/grpc/lookup/v1/RouteLookupConfig;Lcom/google/protobuf/Duration;)Lcom/google/protobuf/Duration;
     163: pop
     164: goto          182
     167: aload_1
     168: aload_0
     169: getfield      #27                 // Field lookupServiceTimeoutBuilder_:Lcom/google/protobuf/SingleFieldBuilderV3;
     172: invokevirtual #45                 // Method com/google/protobuf/SingleFieldBuilderV3.build:()Lcom/google/protobuf/AbstractMessage;
     175: checkcast     #46                 // class com/google/protobuf/Duration
     178: invokestatic  #44                 // Method io/grpc/lookup/v1/RouteLookupConfig.access$702:(Lio/grpc/lookup/v1/RouteLookupConfig;Lcom/google/protobuf/Duration;)Lcom/google/protobuf/Duration;
     181: pop
     182: aload_0
     183: getfield      #29                 // Field maxAgeBuilder_:Lcom/google/protobuf/SingleFieldBuilderV3;
     186: ifnonnull     201
     189: aload_1
     190: aload_0
     191: getfield      #30                 // Field maxAge_:Lcom/google/protobuf/Duration;
     194: invokestatic  #47                 // Method io/grpc/lookup/v1/RouteLookupConfig.access$802:(Lio/grpc/lookup/v1/RouteLookupConfig;Lcom/google/protobuf/Duration;)Lcom/google/protobuf/Duration;
     197: pop
     198: goto          216
     201: aload_1
     202: aload_0
     203: getfield      #29                 // Field maxAgeBuilder_:Lcom/google/protobuf/SingleFieldBuilderV3;
     206: invokevirtual #45                 // Method com/google/protobuf/SingleFieldBuilderV3.build:()Lcom/google/protobuf/AbstractMessage;
     209: checkcast     #46                 // class com/google/protobuf/Duration
     212: invokestatic  #47                 // Method io/grpc/lookup/v1/RouteLookupConfig.access$802:(Lio/grpc/lookup/v1/RouteLookupConfig;Lcom/google/protobuf/Duration;)Lcom/google/protobuf/Duration;
     215: pop
     216: aload_0
     217: getfield      #31                 // Field staleAgeBuilder_:Lcom/google/protobuf/SingleFieldBuilderV3;
     220: ifnonnull     235
     223: aload_1
     224: aload_0
     225: getfield      #32                 // Field staleAge_:Lcom/google/protobuf/Duration;
     228: invokestatic  #48                 // Method io/grpc/lookup/v1/RouteLookupConfig.access$902:(Lio/grpc/lookup/v1/RouteLookupConfig;Lcom/google/protobuf/Duration;)Lcom/google/protobuf/Duration;
     231: pop
     232: goto          250
     235: aload_1
     236: aload_0
     237: getfield      #31                 // Field staleAgeBuilder_:Lcom/google/protobuf/SingleFieldBuilderV3;
     240: invokevirtual #45                 // Method com/google/protobuf/SingleFieldBuilderV3.build:()Lcom/google/protobuf/AbstractMessage;
     243: checkcast     #46                 // class com/google/protobuf/Duration
     246: invokestatic  #48                 // Method io/grpc/lookup/v1/RouteLookupConfig.access$902:(Lio/grpc/lookup/v1/RouteLookupConfig;Lcom/google/protobuf/Duration;)Lcom/google/protobuf/Duration;
     249: pop
     250: aload_1
     251: aload_0
     252: getfield      #33                 // Field cacheSizeBytes_:J
     255: invokestatic  #49                 // Method io/grpc/lookup/v1/RouteLookupConfig.access$1002:(Lio/grpc/lookup/v1/RouteLookupConfig;J)J
     258: pop2
     259: aload_0
     260: getfield      #24                 // Field bitField0_:I
     263: iconst_4
     264: iand
     265: ifeq          292
     268: aload_0
     269: aload_0
     270: getfield      #15                 // Field validTargets_:Lcom/google/protobuf/LazyStringList;
     273: invokeinterface #50,  1           // InterfaceMethod com/google/protobuf/LazyStringList.getUnmodifiableView:()Lcom/google/protobuf/LazyStringList;
     278: putfield      #15                 // Field validTargets_:Lcom/google/protobuf/LazyStringList;
     281: aload_0
     282: aload_0
     283: getfield      #24                 // Field bitField0_:I
     286: bipush        -5
     288: iand
     289: putfield      #24                 // Field bitField0_:I
     292: aload_1
     293: aload_0
     294: getfield      #15                 // Field validTargets_:Lcom/google/protobuf/LazyStringList;
     297: invokestatic  #51                 // Method io/grpc/lookup/v1/RouteLookupConfig.access$1102:(Lio/grpc/lookup/v1/RouteLookupConfig;Lcom/google/protobuf/LazyStringList;)Lcom/google/protobuf/LazyStringList;
     300: pop
     301: aload_1
     302: aload_0
     303: getfield      #16                 // Field defaultTarget_:Ljava/lang/Object;
     306: invokestatic  #52                 // Method io/grpc/lookup/v1/RouteLookupConfig.access$1202:(Lio/grpc/lookup/v1/RouteLookupConfig;Ljava/lang/Object;)Ljava/lang/Object;
     309: pop
     310: aload_0
     311: invokevirtual #53                 // Method onBuilt:()V
     314: aload_1
     315: areturn

  public io.grpc.lookup.v1.RouteLookupConfig$Builder clone();
    Code:
       0: aload_0
       1: invokespecial #54                 // Method com/google/protobuf/GeneratedMessageV3$Builder.clone:()Lcom/google/protobuf/GeneratedMessageV3$Builder;
       4: checkcast     #6                  // class io/grpc/lookup/v1/RouteLookupConfig$Builder
       7: areturn

  public io.grpc.lookup.v1.RouteLookupConfig$Builder setField(com.google.protobuf.Descriptors$FieldDescriptor, java.lang.Object);
    Code:
       0: aload_0
       1: aload_1
       2: aload_2
       3: invokespecial #55                 // Method com/google/protobuf/GeneratedMessageV3$Builder.setField:(Lcom/google/protobuf/Descriptors$FieldDescriptor;Ljava/lang/Object;)Lcom/google/protobuf/GeneratedMessageV3$Builder;
       6: checkcast     #6                  // class io/grpc/lookup/v1/RouteLookupConfig$Builder
       9: areturn

  public io.grpc.lookup.v1.RouteLookupConfig$Builder clearField(com.google.protobuf.Descriptors$FieldDescriptor);
    Code:
       0: aload_0
       1: aload_1
       2: invokespecial #56                 // Method com/google/protobuf/GeneratedMessageV3$Builder.clearField:(Lcom/google/protobuf/Descriptors$FieldDescriptor;)Lcom/google/protobuf/GeneratedMessageV3$Builder;
       5: checkcast     #6                  // class io/grpc/lookup/v1/RouteLookupConfig$Builder
       8: areturn

  public io.grpc.lookup.v1.RouteLookupConfig$Builder clearOneof(com.google.protobuf.Descriptors$OneofDescriptor);
    Code:
       0: aload_0
       1: aload_1
       2: invokespecial #57                 // Method com/google/protobuf/GeneratedMessageV3$Builder.clearOneof:(Lcom/google/protobuf/Descriptors$OneofDescriptor;)Lcom/google/protobuf/GeneratedMessageV3$Builder;
       5: checkcast     #6                  // class io/grpc/lookup/v1/RouteLookupConfig$Builder
       8: areturn

  public io.grpc.lookup.v1.RouteLookupConfig$Builder setRepeatedField(com.google.protobuf.Descriptors$FieldDescriptor, int, java.lang.Object);
    Code:
       0: aload_0
       1: aload_1
       2: iload_2
       3: aload_3
       4: invokespecial #58                 // Method com/google/protobuf/GeneratedMessageV3$Builder.setRepeatedField:(Lcom/google/protobuf/Descriptors$FieldDescriptor;ILjava/lang/Object;)Lcom/google/protobuf/GeneratedMessageV3$Builder;
       7: checkcast     #6                  // class io/grpc/lookup/v1/RouteLookupConfig$Builder
      10: areturn

  public io.grpc.lookup.v1.RouteLookupConfig$Builder addRepeatedField(com.google.protobuf.Descriptors$FieldDescriptor, java.lang.Object);
    Code:
       0: aload_0
       1: aload_1
       2: aload_2
       3: invokespecial #59                 // Method com/google/protobuf/GeneratedMessageV3$Builder.addRepeatedField:(Lcom/google/protobuf/Descriptors$FieldDescriptor;Ljava/lang/Object;)Lcom/google/protobuf/GeneratedMessageV3$Builder;
       6: checkcast     #6                  // class io/grpc/lookup/v1/RouteLookupConfig$Builder
       9: areturn

  public io.grpc.lookup.v1.RouteLookupConfig$Builder mergeFrom(com.google.protobuf.Message);
    Code:
       0: aload_1
       1: instanceof    #5                  // class io/grpc/lookup/v1/RouteLookupConfig
       4: ifeq          16
       7: aload_0
       8: aload_1
       9: checkcast     #5                  // class io/grpc/lookup/v1/RouteLookupConfig
      12: invokevirtual #60                 // Method mergeFrom:(Lio/grpc/lookup/v1/RouteLookupConfig;)Lio/grpc/lookup/v1/RouteLookupConfig$Builder;
      15: areturn
      16: aload_0
      17: aload_1
      18: invokespecial #61                 // Method com/google/protobuf/GeneratedMessageV3$Builder.mergeFrom:(Lcom/google/protobuf/Message;)Lcom/google/protobuf/AbstractMessage$Builder;
      21: pop
      22: aload_0
      23: areturn

  public io.grpc.lookup.v1.RouteLookupConfig$Builder mergeFrom(io.grpc.lookup.v1.RouteLookupConfig);
    Code:
       0: aload_1
       1: invokestatic  #34                 // Method io/grpc/lookup/v1/RouteLookupConfig.getDefaultInstance:()Lio/grpc/lookup/v1/RouteLookupConfig;
       4: if_acmpne     9
       7: aload_0
       8: areturn
       9: aload_0
      10: getfield      #23                 // Field httpKeybuildersBuilder_:Lcom/google/protobuf/RepeatedFieldBuilderV3;
      13: ifnonnull     87
      16: aload_1
      17: invokestatic  #62                 // Method io/grpc/lookup/v1/RouteLookupConfig.access$400:(Lio/grpc/lookup/v1/RouteLookupConfig;)Ljava/util/List;
      20: invokeinterface #63,  1           // InterfaceMethod java/util/List.isEmpty:()Z
      25: ifne          173
      28: aload_0
      29: getfield      #10                 // Field httpKeybuilders_:Ljava/util/List;
      32: invokeinterface #63,  1           // InterfaceMethod java/util/List.isEmpty:()Z
      37: ifeq          62
      40: aload_0
      41: aload_1
      42: invokestatic  #62                 // Method io/grpc/lookup/v1/RouteLookupConfig.access$400:(Lio/grpc/lookup/v1/RouteLookupConfig;)Ljava/util/List;
      45: putfield      #10                 // Field httpKeybuilders_:Ljava/util/List;
      48: aload_0
      49: aload_0
      50: getfield      #24                 // Field bitField0_:I
      53: bipush        -2
      55: iand
      56: putfield      #24                 // Field bitField0_:I
      59: goto          80
      62: aload_0
      63: invokespecial #64                 // Method ensureHttpKeybuildersIsMutable:()V
      66: aload_0
      67: getfield      #10                 // Field httpKeybuilders_:Ljava/util/List;
      70: aload_1
      71: invokestatic  #62                 // Method io/grpc/lookup/v1/RouteLookupConfig.access$400:(Lio/grpc/lookup/v1/RouteLookupConfig;)Ljava/util/List;
      74: invokeinterface #65,  2           // InterfaceMethod java/util/List.addAll:(Ljava/util/Collection;)Z
      79: pop
      80: aload_0
      81: invokevirtual #66                 // Method onChanged:()V
      84: goto          173
      87: aload_1
      88: invokestatic  #62                 // Method io/grpc/lookup/v1/RouteLookupConfig.access$400:(Lio/grpc/lookup/v1/RouteLookupConfig;)Ljava/util/List;
      91: invokeinterface #63,  1           // InterfaceMethod java/util/List.isEmpty:()Z
      96: ifne          173
      99: aload_0
     100: getfield      #23                 // Field httpKeybuildersBuilder_:Lcom/google/protobuf/RepeatedFieldBuilderV3;
     103: invokevirtual #67                 // Method com/google/protobuf/RepeatedFieldBuilderV3.isEmpty:()Z
     106: ifeq          161
     109: aload_0
     110: getfield      #23                 // Field httpKeybuildersBuilder_:Lcom/google/protobuf/RepeatedFieldBuilderV3;
     113: invokevirtual #68                 // Method com/google/protobuf/RepeatedFieldBuilderV3.dispose:()V
     116: aload_0
     117: aconst_null
     118: putfield      #23                 // Field httpKeybuildersBuilder_:Lcom/google/protobuf/RepeatedFieldBuilderV3;
     121: aload_0
     122: aload_1
     123: invokestatic  #62                 // Method io/grpc/lookup/v1/RouteLookupConfig.access$400:(Lio/grpc/lookup/v1/RouteLookupConfig;)Ljava/util/List;
     126: putfield      #10                 // Field httpKeybuilders_:Ljava/util/List;
     129: aload_0
     130: aload_0
     131: getfield      #24                 // Field bitField0_:I
     134: bipush        -2
     136: iand
     137: putfield      #24                 // Field bitField0_:I
     140: aload_0
     141: invokestatic  #69                 // Method io/grpc/lookup/v1/RouteLookupConfig.access$1300:()Z
     144: ifeq          154
     147: aload_0
     148: invokespecial #20                 // Method getHttpKeybuildersFieldBuilder:()Lcom/google/protobuf/RepeatedFieldBuilderV3;
     151: goto          155
     154: aconst_null
     155: putfield      #23                 // Field httpKeybuildersBuilder_:Lcom/google/protobuf/RepeatedFieldBuilderV3;
     158: goto          173
     161: aload_0
     162: getfield      #23                 // Field httpKeybuildersBuilder_:Lcom/google/protobuf/RepeatedFieldBuilderV3;
     165: aload_1
     166: invokestatic  #62                 // Method io/grpc/lookup/v1/RouteLookupConfig.access$400:(Lio/grpc/lookup/v1/RouteLookupConfig;)Ljava/util/List;
     169: invokevirtual #70                 // Method com/google/protobuf/RepeatedFieldBuilderV3.addAllMessages:(Ljava/lang/Iterable;)Lcom/google/protobuf/RepeatedFieldBuilderV3;
     172: pop
     173: aload_0
     174: getfield      #26                 // Field grpcKeybuildersBuilder_:Lcom/google/protobuf/RepeatedFieldBuilderV3;
     177: ifnonnull     251
     180: aload_1
     181: invokestatic  #71                 // Method io/grpc/lookup/v1/RouteLookupConfig.access$500:(Lio/grpc/lookup/v1/RouteLookupConfig;)Ljava/util/List;
     184: invokeinterface #63,  1           // InterfaceMethod java/util/List.isEmpty:()Z
     189: ifne          337
     192: aload_0
     193: getfield      #11                 // Field grpcKeybuilders_:Ljava/util/List;
     196: invokeinterface #63,  1           // InterfaceMethod java/util/List.isEmpty:()Z
     201: ifeq          226
     204: aload_0
     205: aload_1
     206: invokestatic  #71                 // Method io/grpc/lookup/v1/RouteLookupConfig.access$500:(Lio/grpc/lookup/v1/RouteLookupConfig;)Ljava/util/List;
     209: putfield      #11                 // Field grpcKeybuilders_:Ljava/util/List;
     212: aload_0
     213: aload_0
     214: getfield      #24                 // Field bitField0_:I
     217: bipush        -3
     219: iand
     220: putfield      #24                 // Field bitField0_:I
     223: goto          244
     226: aload_0
     227: invokespecial #72                 // Method ensureGrpcKeybuildersIsMutable:()V
     230: aload_0
     231: getfield      #11                 // Field grpcKeybuilders_:Ljava/util/List;
     234: aload_1
     235: invokestatic  #71                 // Method io/grpc/lookup/v1/RouteLookupConfig.access$500:(Lio/grpc/lookup/v1/RouteLookupConfig;)Ljava/util/List;
     238: invokeinterface #65,  2           // InterfaceMethod java/util/List.addAll:(Ljava/util/Collection;)Z
     243: pop
     244: aload_0
     245: invokevirtual #66                 // Method onChanged:()V
     248: goto          337
     251: aload_1
     252: invokestatic  #71                 // Method io/grpc/lookup/v1/RouteLookupConfig.access$500:(Lio/grpc/lookup/v1/RouteLookupConfig;)Ljava/util/List;
     255: invokeinterface #63,  1           // InterfaceMethod java/util/List.isEmpty:()Z
     260: ifne          337
     263: aload_0
     264: getfield      #26                 // Field grpcKeybuildersBuilder_:Lcom/google/protobuf/RepeatedFieldBuilderV3;
     267: invokevirtual #67                 // Method com/google/protobuf/RepeatedFieldBuilderV3.isEmpty:()Z
     270: ifeq          325
     273: aload_0
     274: getfield      #26                 // Field grpcKeybuildersBuilder_:Lcom/google/protobuf/RepeatedFieldBuilderV3;
     277: invokevirtual #68                 // Method com/google/protobuf/RepeatedFieldBuilderV3.dispose:()V
     280: aload_0
     281: aconst_null
     282: putfield      #26                 // Field grpcKeybuildersBuilder_:Lcom/google/protobuf/RepeatedFieldBuilderV3;
     285: aload_0
     286: aload_1
     287: invokestatic  #71                 // Method io/grpc/lookup/v1/RouteLookupConfig.access$500:(Lio/grpc/lookup/v1/RouteLookupConfig;)Ljava/util/List;
     290: putfield      #11                 // Field grpcKeybuilders_:Ljava/util/List;
     293: aload_0
     294: aload_0
     295: getfield      #24                 // Field bitField0_:I
     298: bipush        -3
     300: iand
     301: putfield      #24                 // Field bitField0_:I
     304: aload_0
     305: invokestatic  #73                 // Method io/grpc/lookup/v1/RouteLookupConfig.access$1400:()Z
     308: ifeq          318
     311: aload_0
     312: invokespecial #21                 // Method getGrpcKeybuildersFieldBuilder:()Lcom/google/protobuf/RepeatedFieldBuilderV3;
     315: goto          319
     318: aconst_null
     319: putfield      #26                 // Field grpcKeybuildersBuilder_:Lcom/google/protobuf/RepeatedFieldBuilderV3;
     322: goto          337
     325: aload_0
     326: getfield      #26                 // Field grpcKeybuildersBuilder_:Lcom/google/protobuf/RepeatedFieldBuilderV3;
     329: aload_1
     330: invokestatic  #71                 // Method io/grpc/lookup/v1/RouteLookupConfig.access$500:(Lio/grpc/lookup/v1/RouteLookupConfig;)Ljava/util/List;
     333: invokevirtual #70                 // Method com/google/protobuf/RepeatedFieldBuilderV3.addAllMessages:(Ljava/lang/Iterable;)Lcom/google/protobuf/RepeatedFieldBuilderV3;
     336: pop
     337: aload_1
     338: invokevirtual #74                 // Method io/grpc/lookup/v1/RouteLookupConfig.getLookupService:()Ljava/lang/String;
     341: invokevirtual #75                 // Method java/lang/String.isEmpty:()Z
     344: ifne          359
     347: aload_0
     348: aload_1
     349: invokestatic  #76                 // Method io/grpc/lookup/v1/RouteLookupConfig.access$600:(Lio/grpc/lookup/v1/RouteLookupConfig;)Ljava/lang/Object;
     352: putfield      #13                 // Field lookupService_:Ljava/lang/Object;
     355: aload_0
     356: invokevirtual #66                 // Method onChanged:()V
     359: aload_1
     360: invokevirtual #77                 // Method io/grpc/lookup/v1/RouteLookupConfig.hasLookupServiceTimeout:()Z
     363: ifeq          375
     366: aload_0
     367: aload_1
     368: invokevirtual #78                 // Method io/grpc/lookup/v1/RouteLookupConfig.getLookupServiceTimeout:()Lcom/google/protobuf/Duration;
     371: invokevirtual #79                 // Method mergeLookupServiceTimeout:(Lcom/google/protobuf/Duration;)Lio/grpc/lookup/v1/RouteLookupConfig$Builder;
     374: pop
     375: aload_1
     376: invokevirtual #80                 // Method io/grpc/lookup/v1/RouteLookupConfig.hasMaxAge:()Z
     379: ifeq          391
     382: aload_0
     383: aload_1
     384: invokevirtual #81                 // Method io/grpc/lookup/v1/RouteLookupConfig.getMaxAge:()Lcom/google/protobuf/Duration;
     387: invokevirtual #82                 // Method mergeMaxAge:(Lcom/google/protobuf/Duration;)Lio/grpc/lookup/v1/RouteLookupConfig$Builder;
     390: pop
     391: aload_1
     392: invokevirtual #83                 // Method io/grpc/lookup/v1/RouteLookupConfig.hasStaleAge:()Z
     395: ifeq          407
     398: aload_0
     399: aload_1
     400: invokevirtual #84                 // Method io/grpc/lookup/v1/RouteLookupConfig.getStaleAge:()Lcom/google/protobuf/Duration;
     403: invokevirtual #85                 // Method mergeStaleAge:(Lcom/google/protobuf/Duration;)Lio/grpc/lookup/v1/RouteLookupConfig$Builder;
     406: pop
     407: aload_1
     408: invokevirtual #86                 // Method io/grpc/lookup/v1/RouteLookupConfig.getCacheSizeBytes:()J
     411: lconst_0
     412: lcmp
     413: ifeq          425
     416: aload_0
     417: aload_1
     418: invokevirtual #86                 // Method io/grpc/lookup/v1/RouteLookupConfig.getCacheSizeBytes:()J
     421: invokevirtual #87                 // Method setCacheSizeBytes:(J)Lio/grpc/lookup/v1/RouteLookupConfig$Builder;
     424: pop
     425: aload_1
     426: invokestatic  #88                 // Method io/grpc/lookup/v1/RouteLookupConfig.access$1100:(Lio/grpc/lookup/v1/RouteLookupConfig;)Lcom/google/protobuf/LazyStringList;
     429: invokeinterface #89,  1           // InterfaceMethod com/google/protobuf/LazyStringList.isEmpty:()Z
     434: ifne          493
     437: aload_0
     438: getfield      #15                 // Field validTargets_:Lcom/google/protobuf/LazyStringList;
     441: invokeinterface #89,  1           // InterfaceMethod com/google/protobuf/LazyStringList.isEmpty:()Z
     446: ifeq          471
     449: aload_0
     450: aload_1
     451: invokestatic  #88                 // Method io/grpc/lookup/v1/RouteLookupConfig.access$1100:(Lio/grpc/lookup/v1/RouteLookupConfig;)Lcom/google/protobuf/LazyStringList;
     454: putfield      #15                 // Field validTargets_:Lcom/google/protobuf/LazyStringList;
     457: aload_0
     458: aload_0
     459: getfield      #24                 // Field bitField0_:I
     462: bipush        -5
     464: iand
     465: putfield      #24                 // Field bitField0_:I
     468: goto          489
     471: aload_0
     472: invokespecial #90                 // Method ensureValidTargetsIsMutable:()V
     475: aload_0
     476: getfield      #15                 // Field validTargets_:Lcom/google/protobuf/LazyStringList;
     479: aload_1
     480: invokestatic  #88                 // Method io/grpc/lookup/v1/RouteLookupConfig.access$1100:(Lio/grpc/lookup/v1/RouteLookupConfig;)Lcom/google/protobuf/LazyStringList;
     483: invokeinterface #91,  2           // InterfaceMethod com/google/protobuf/LazyStringList.addAll:(Ljava/util/Collection;)Z
     488: pop
     489: aload_0
     490: invokevirtual #66                 // Method onChanged:()V
     493: aload_1
     494: invokevirtual #92                 // Method io/grpc/lookup/v1/RouteLookupConfig.getDefaultTarget:()Ljava/lang/String;
     497: invokevirtual #75                 // Method java/lang/String.isEmpty:()Z
     500: ifne          515
     503: aload_0
     504: aload_1
     505: invokestatic  #93                 // Method io/grpc/lookup/v1/RouteLookupConfig.access$1200:(Lio/grpc/lookup/v1/RouteLookupConfig;)Ljava/lang/Object;
     508: putfield      #16                 // Field defaultTarget_:Ljava/lang/Object;
     511: aload_0
     512: invokevirtual #66                 // Method onChanged:()V
     515: aload_0
     516: aload_1
     517: invokestatic  #94                 // Method io/grpc/lookup/v1/RouteLookupConfig.access$1500:(Lio/grpc/lookup/v1/RouteLookupConfig;)Lcom/google/protobuf/UnknownFieldSet;
     520: invokevirtual #95                 // Method mergeUnknownFields:(Lcom/google/protobuf/UnknownFieldSet;)Lio/grpc/lookup/v1/RouteLookupConfig$Builder;
     523: pop
     524: aload_0
     525: invokevirtual #66                 // Method onChanged:()V
     528: aload_0
     529: areturn

  public final boolean isInitialized();
    Code:
       0: iconst_1
       1: ireturn

  public io.grpc.lookup.v1.RouteLookupConfig$Builder mergeFrom(com.google.protobuf.CodedInputStream, com.google.protobuf.ExtensionRegistryLite) throws java.io.IOException;
    Code:
       0: aconst_null
       1: astore_3
       2: invokestatic  #96                 // Method io/grpc/lookup/v1/RouteLookupConfig.access$1600:()Lcom/google/protobuf/Parser;
       5: aload_1
       6: aload_2
       7: invokeinterface #97,  3           // InterfaceMethod com/google/protobuf/Parser.parsePartialFrom:(Lcom/google/protobuf/CodedInputStream;Lcom/google/protobuf/ExtensionRegistryLite;)Ljava/lang/Object;
      12: checkcast     #5                  // class io/grpc/lookup/v1/RouteLookupConfig
      15: astore_3
      16: aload_3
      17: ifnull        61
      20: aload_0
      21: aload_3
      22: invokevirtual #60                 // Method mergeFrom:(Lio/grpc/lookup/v1/RouteLookupConfig;)Lio/grpc/lookup/v1/RouteLookupConfig$Builder;
      25: pop
      26: goto          61
      29: astore        4
      31: aload         4
      33: invokevirtual #99                 // Method com/google/protobuf/InvalidProtocolBufferException.getUnfinishedMessage:()Lcom/google/protobuf/MessageLite;
      36: checkcast     #5                  // class io/grpc/lookup/v1/RouteLookupConfig
      39: astore_3
      40: aload         4
      42: invokevirtual #100                // Method com/google/protobuf/InvalidProtocolBufferException.unwrapIOException:()Ljava/io/IOException;
      45: athrow
      46: astore        5
      48: aload_3
      49: ifnull        58
      52: aload_0
      53: aload_3
      54: invokevirtual #60                 // Method mergeFrom:(Lio/grpc/lookup/v1/RouteLookupConfig;)Lio/grpc/lookup/v1/RouteLookupConfig$Builder;
      57: pop
      58: aload         5
      60: athrow
      61: aload_0
      62: areturn
    Exception table:
       from    to  target type
           2    16    29   Class com/google/protobuf/InvalidProtocolBufferException
           2    16    46   any
          29    48    46   any

  private void ensureHttpKeybuildersIsMutable();
    Code:
       0: aload_0
       1: getfield      #24                 // Field bitField0_:I
       4: iconst_1
       5: iand
       6: ifne          34
       9: aload_0
      10: new           #101                // class java/util/ArrayList
      13: dup
      14: aload_0
      15: getfield      #10                 // Field httpKeybuilders_:Ljava/util/List;
      18: invokespecial #102                // Method java/util/ArrayList."<init>":(Ljava/util/Collection;)V
      21: putfield      #10                 // Field httpKeybuilders_:Ljava/util/List;
      24: aload_0
      25: dup
      26: getfield      #24                 // Field bitField0_:I
      29: iconst_1
      30: ior
      31: putfield      #24                 // Field bitField0_:I
      34: return

  public java.util.List<io.grpc.lookup.v1.HttpKeyBuilder> getHttpKeybuildersList();
    Code:
       0: aload_0
       1: getfield      #23                 // Field httpKeybuildersBuilder_:Lcom/google/protobuf/RepeatedFieldBuilderV3;
       4: ifnonnull     15
       7: aload_0
       8: getfield      #10                 // Field httpKeybuilders_:Ljava/util/List;
      11: invokestatic  #39                 // Method java/util/Collections.unmodifiableList:(Ljava/util/List;)Ljava/util/List;
      14: areturn
      15: aload_0
      16: getfield      #23                 // Field httpKeybuildersBuilder_:Lcom/google/protobuf/RepeatedFieldBuilderV3;
      19: invokevirtual #103                // Method com/google/protobuf/RepeatedFieldBuilderV3.getMessageList:()Ljava/util/List;
      22: areturn

  public int getHttpKeybuildersCount();
    Code:
       0: aload_0
       1: getfield      #23                 // Field httpKeybuildersBuilder_:Lcom/google/protobuf/RepeatedFieldBuilderV3;
       4: ifnonnull     17
       7: aload_0
       8: getfield      #10                 // Field httpKeybuilders_:Ljava/util/List;
      11: invokeinterface #104,  1          // InterfaceMethod java/util/List.size:()I
      16: ireturn
      17: aload_0
      18: getfield      #23                 // Field httpKeybuildersBuilder_:Lcom/google/protobuf/RepeatedFieldBuilderV3;
      21: invokevirtual #105                // Method com/google/protobuf/RepeatedFieldBuilderV3.getCount:()I
      24: ireturn

  public io.grpc.lookup.v1.HttpKeyBuilder getHttpKeybuilders(int);
    Code:
       0: aload_0
       1: getfield      #23                 // Field httpKeybuildersBuilder_:Lcom/google/protobuf/RepeatedFieldBuilderV3;
       4: ifnonnull     21
       7: aload_0
       8: getfield      #10                 // Field httpKeybuilders_:Ljava/util/List;
      11: iload_1
      12: invokeinterface #106,  2          // InterfaceMethod java/util/List.get:(I)Ljava/lang/Object;
      17: checkcast     #107                // class io/grpc/lookup/v1/HttpKeyBuilder
      20: areturn
      21: aload_0
      22: getfield      #23                 // Field httpKeybuildersBuilder_:Lcom/google/protobuf/RepeatedFieldBuilderV3;
      25: iload_1
      26: invokevirtual #108                // Method com/google/protobuf/RepeatedFieldBuilderV3.getMessage:(I)Lcom/google/protobuf/AbstractMessage;
      29: checkcast     #107                // class io/grpc/lookup/v1/HttpKeyBuilder
      32: areturn

  public io.grpc.lookup.v1.RouteLookupConfig$Builder setHttpKeybuilders(int, io.grpc.lookup.v1.HttpKeyBuilder);
    Code:
       0: aload_0
       1: getfield      #23                 // Field httpKeybuildersBuilder_:Lcom/google/protobuf/RepeatedFieldBuilderV3;
       4: ifnonnull     42
       7: aload_2
       8: ifnonnull     19
      11: new           #109                // class java/lang/NullPointerException
      14: dup
      15: invokespecial #110                // Method java/lang/NullPointerException."<init>":()V
      18: athrow
      19: aload_0
      20: invokespecial #64                 // Method ensureHttpKeybuildersIsMutable:()V
      23: aload_0
      24: getfield      #10                 // Field httpKeybuilders_:Ljava/util/List;
      27: iload_1
      28: aload_2
      29: invokeinterface #111,  3          // InterfaceMethod java/util/List.set:(ILjava/lang/Object;)Ljava/lang/Object;
      34: pop
      35: aload_0
      36: invokevirtual #66                 // Method onChanged:()V
      39: goto          52
      42: aload_0
      43: getfield      #23                 // Field httpKeybuildersBuilder_:Lcom/google/protobuf/RepeatedFieldBuilderV3;
      46: iload_1
      47: aload_2
      48: invokevirtual #112                // Method com/google/protobuf/RepeatedFieldBuilderV3.setMessage:(ILcom/google/protobuf/AbstractMessage;)Lcom/google/protobuf/RepeatedFieldBuilderV3;
      51: pop
      52: aload_0
      53: areturn

  public io.grpc.lookup.v1.RouteLookupConfig$Builder setHttpKeybuilders(int, io.grpc.lookup.v1.HttpKeyBuilder$Builder);
    Code:
       0: aload_0
       1: getfield      #23                 // Field httpKeybuildersBuilder_:Lcom/google/protobuf/RepeatedFieldBuilderV3;
       4: ifnonnull     33
       7: aload_0
       8: invokespecial #64                 // Method ensureHttpKeybuildersIsMutable:()V
      11: aload_0
      12: getfield      #10                 // Field httpKeybuilders_:Ljava/util/List;
      15: iload_1
      16: aload_2
      17: invokevirtual #113                // Method io/grpc/lookup/v1/HttpKeyBuilder$Builder.build:()Lio/grpc/lookup/v1/HttpKeyBuilder;
      20: invokeinterface #111,  3          // InterfaceMethod java/util/List.set:(ILjava/lang/Object;)Ljava/lang/Object;
      25: pop
      26: aload_0
      27: invokevirtual #66                 // Method onChanged:()V
      30: goto          46
      33: aload_0
      34: getfield      #23                 // Field httpKeybuildersBuilder_:Lcom/google/protobuf/RepeatedFieldBuilderV3;
      37: iload_1
      38: aload_2
      39: invokevirtual #113                // Method io/grpc/lookup/v1/HttpKeyBuilder$Builder.build:()Lio/grpc/lookup/v1/HttpKeyBuilder;
      42: invokevirtual #112                // Method com/google/protobuf/RepeatedFieldBuilderV3.setMessage:(ILcom/google/protobuf/AbstractMessage;)Lcom/google/protobuf/RepeatedFieldBuilderV3;
      45: pop
      46: aload_0
      47: areturn

  public io.grpc.lookup.v1.RouteLookupConfig$Builder addHttpKeybuilders(io.grpc.lookup.v1.HttpKeyBuilder);
    Code:
       0: aload_0
       1: getfield      #23                 // Field httpKeybuildersBuilder_:Lcom/google/protobuf/RepeatedFieldBuilderV3;
       4: ifnonnull     41
       7: aload_1
       8: ifnonnull     19
      11: new           #109                // class java/lang/NullPointerException
      14: dup
      15: invokespecial #110                // Method java/lang/NullPointerException."<init>":()V
      18: athrow
      19: aload_0
      20: invokespecial #64                 // Method ensureHttpKeybuildersIsMutable:()V
      23: aload_0
      24: getfield      #10                 // Field httpKeybuilders_:Ljava/util/List;
      27: aload_1
      28: invokeinterface #114,  2          // InterfaceMethod java/util/List.add:(Ljava/lang/Object;)Z
      33: pop
      34: aload_0
      35: invokevirtual #66                 // Method onChanged:()V
      38: goto          50
      41: aload_0
      42: getfield      #23                 // Field httpKeybuildersBuilder_:Lcom/google/protobuf/RepeatedFieldBuilderV3;
      45: aload_1
      46: invokevirtual #115                // Method com/google/protobuf/RepeatedFieldBuilderV3.addMessage:(Lcom/google/protobuf/AbstractMessage;)Lcom/google/protobuf/RepeatedFieldBuilderV3;
      49: pop
      50: aload_0
      51: areturn

  public io.grpc.lookup.v1.RouteLookupConfig$Builder addHttpKeybuilders(int, io.grpc.lookup.v1.HttpKeyBuilder);
    Code:
       0: aload_0
       1: getfield      #23                 // Field httpKeybuildersBuilder_:Lcom/google/protobuf/RepeatedFieldBuilderV3;
       4: ifnonnull     41
       7: aload_2
       8: ifnonnull     19
      11: new           #109                // class java/lang/NullPointerException
      14: dup
      15: invokespecial #110                // Method java/lang/NullPointerException."<init>":()V
      18: athrow
      19: aload_0
      20: invokespecial #64                 // Method ensureHttpKeybuildersIsMutable:()V
      23: aload_0
      24: getfield      #10                 // Field httpKeybuilders_:Ljava/util/List;
      27: iload_1
      28: aload_2
      29: invokeinterface #116,  3          // InterfaceMethod java/util/List.add:(ILjava/lang/Object;)V
      34: aload_0
      35: invokevirtual #66                 // Method onChanged:()V
      38: goto          51
      41: aload_0
      42: getfield      #23                 // Field httpKeybuildersBuilder_:Lcom/google/protobuf/RepeatedFieldBuilderV3;
      45: iload_1
      46: aload_2
      47: invokevirtual #117                // Method com/google/protobuf/RepeatedFieldBuilderV3.addMessage:(ILcom/google/protobuf/AbstractMessage;)Lcom/google/protobuf/RepeatedFieldBuilderV3;
      50: pop
      51: aload_0
      52: areturn

  public io.grpc.lookup.v1.RouteLookupConfig$Builder addHttpKeybuilders(io.grpc.lookup.v1.HttpKeyBuilder$Builder);
    Code:
       0: aload_0
       1: getfield      #23                 // Field httpKeybuildersBuilder_:Lcom/google/protobuf/RepeatedFieldBuilderV3;
       4: ifnonnull     32
       7: aload_0
       8: invokespecial #64                 // Method ensureHttpKeybuildersIsMutable:()V
      11: aload_0
      12: getfield      #10                 // Field httpKeybuilders_:Ljava/util/List;
      15: aload_1
      16: invokevirtual #113                // Method io/grpc/lookup/v1/HttpKeyBuilder$Builder.build:()Lio/grpc/lookup/v1/HttpKeyBuilder;
      19: invokeinterface #114,  2          // InterfaceMethod java/util/List.add:(Ljava/lang/Object;)Z
      24: pop
      25: aload_0
      26: invokevirtual #66                 // Method onChanged:()V
      29: goto          44
      32: aload_0
      33: getfield      #23                 // Field httpKeybuildersBuilder_:Lcom/google/protobuf/RepeatedFieldBuilderV3;
      36: aload_1
      37: invokevirtual #113                // Method io/grpc/lookup/v1/HttpKeyBuilder$Builder.build:()Lio/grpc/lookup/v1/HttpKeyBuilder;
      40: invokevirtual #115                // Method com/google/protobuf/RepeatedFieldBuilderV3.addMessage:(Lcom/google/protobuf/AbstractMessage;)Lcom/google/protobuf/RepeatedFieldBuilderV3;
      43: pop
      44: aload_0
      45: areturn

  public io.grpc.lookup.v1.RouteLookupConfig$Builder addHttpKeybuilders(int, io.grpc.lookup.v1.HttpKeyBuilder$Builder);
    Code:
       0: aload_0
       1: getfield      #23                 // Field httpKeybuildersBuilder_:Lcom/google/protobuf/RepeatedFieldBuilderV3;
       4: ifnonnull     32
       7: aload_0
       8: invokespecial #64                 // Method ensureHttpKeybuildersIsMutable:()V
      11: aload_0
      12: getfield      #10                 // Field httpKeybuilders_:Ljava/util/List;
      15: iload_1
      16: aload_2
      17: invokevirtual #113                // Method io/grpc/lookup/v1/HttpKeyBuilder$Builder.build:()Lio/grpc/lookup/v1/HttpKeyBuilder;
      20: invokeinterface #116,  3          // InterfaceMethod java/util/List.add:(ILjava/lang/Object;)V
      25: aload_0
      26: invokevirtual #66                 // Method onChanged:()V
      29: goto          45
      32: aload_0
      33: getfield      #23                 // Field httpKeybuildersBuilder_:Lcom/google/protobuf/RepeatedFieldBuilderV3;
      36: iload_1
      37: aload_2
      38: invokevirtual #113                // Method io/grpc/lookup/v1/HttpKeyBuilder$Builder.build:()Lio/grpc/lookup/v1/HttpKeyBuilder;
      41: invokevirtual #117                // Method com/google/protobuf/RepeatedFieldBuilderV3.addMessage:(ILcom/google/protobuf/AbstractMessage;)Lcom/google/protobuf/RepeatedFieldBuilderV3;
      44: pop
      45: aload_0
      46: areturn

  public io.grpc.lookup.v1.RouteLookupConfig$Builder addAllHttpKeybuilders(java.lang.Iterable<? extends io.grpc.lookup.v1.HttpKeyBuilder>);
    Code:
       0: aload_0
       1: getfield      #23                 // Field httpKeybuildersBuilder_:Lcom/google/protobuf/RepeatedFieldBuilderV3;
       4: ifnonnull     26
       7: aload_0
       8: invokespecial #64                 // Method ensureHttpKeybuildersIsMutable:()V
      11: aload_1
      12: aload_0
      13: getfield      #10                 // Field httpKeybuilders_:Ljava/util/List;
      16: invokestatic  #118                // Method com/google/protobuf/AbstractMessageLite$Builder.addAll:(Ljava/lang/Iterable;Ljava/util/List;)V
      19: aload_0
      20: invokevirtual #66                 // Method onChanged:()V
      23: goto          35
      26: aload_0
      27: getfield      #23                 // Field httpKeybuildersBuilder_:Lcom/google/protobuf/RepeatedFieldBuilderV3;
      30: aload_1
      31: invokevirtual #70                 // Method com/google/protobuf/RepeatedFieldBuilderV3.addAllMessages:(Ljava/lang/Iterable;)Lcom/google/protobuf/RepeatedFieldBuilderV3;
      34: pop
      35: aload_0
      36: areturn

  public io.grpc.lookup.v1.RouteLookupConfig$Builder clearHttpKeybuilders();
    Code:
       0: aload_0
       1: getfield      #23                 // Field httpKeybuildersBuilder_:Lcom/google/protobuf/RepeatedFieldBuilderV3;
       4: ifnonnull     32
       7: aload_0
       8: invokestatic  #9                  // Method java/util/Collections.emptyList:()Ljava/util/List;
      11: putfield      #10                 // Field httpKeybuilders_:Ljava/util/List;
      14: aload_0
      15: aload_0
      16: getfield      #24                 // Field bitField0_:I
      19: bipush        -2
      21: iand
      22: putfield      #24                 // Field bitField0_:I
      25: aload_0
      26: invokevirtual #66                 // Method onChanged:()V
      29: goto          39
      32: aload_0
      33: getfield      #23                 // Field httpKeybuildersBuilder_:Lcom/google/protobuf/RepeatedFieldBuilderV3;
      36: invokevirtual #25                 // Method com/google/protobuf/RepeatedFieldBuilderV3.clear:()V
      39: aload_0
      40: areturn

  public io.grpc.lookup.v1.RouteLookupConfig$Builder removeHttpKeybuilders(int);
    Code:
       0: aload_0
       1: getfield      #23                 // Field httpKeybuildersBuilder_:Lcom/google/protobuf/RepeatedFieldBuilderV3;
       4: ifnonnull     29
       7: aload_0
       8: invokespecial #64                 // Method ensureHttpKeybuildersIsMutable:()V
      11: aload_0
      12: getfield      #10                 // Field httpKeybuilders_:Ljava/util/List;
      15: iload_1
      16: invokeinterface #119,  2          // InterfaceMethod java/util/List.remove:(I)Ljava/lang/Object;
      21: pop
      22: aload_0
      23: invokevirtual #66                 // Method onChanged:()V
      26: goto          37
      29: aload_0
      30: getfield      #23                 // Field httpKeybuildersBuilder_:Lcom/google/protobuf/RepeatedFieldBuilderV3;
      33: iload_1
      34: invokevirtual #120                // Method com/google/protobuf/RepeatedFieldBuilderV3.remove:(I)V
      37: aload_0
      38: areturn

  public io.grpc.lookup.v1.HttpKeyBuilder$Builder getHttpKeybuildersBuilder(int);
    Code:
       0: aload_0
       1: invokespecial #20                 // Method getHttpKeybuildersFieldBuilder:()Lcom/google/protobuf/RepeatedFieldBuilderV3;
       4: iload_1
       5: invokevirtual #121                // Method com/google/protobuf/RepeatedFieldBuilderV3.getBuilder:(I)Lcom/google/protobuf/AbstractMessage$Builder;
       8: checkcast     #122                // class io/grpc/lookup/v1/HttpKeyBuilder$Builder
      11: areturn

  public io.grpc.lookup.v1.HttpKeyBuilderOrBuilder getHttpKeybuildersOrBuilder(int);
    Code:
       0: aload_0
       1: getfield      #23                 // Field httpKeybuildersBuilder_:Lcom/google/protobuf/RepeatedFieldBuilderV3;
       4: ifnonnull     21
       7: aload_0
       8: getfield      #10                 // Field httpKeybuilders_:Ljava/util/List;
      11: iload_1
      12: invokeinterface #106,  2          // InterfaceMethod java/util/List.get:(I)Ljava/lang/Object;
      17: checkcast     #123                // class io/grpc/lookup/v1/HttpKeyBuilderOrBuilder
      20: areturn
      21: aload_0
      22: getfield      #23                 // Field httpKeybuildersBuilder_:Lcom/google/protobuf/RepeatedFieldBuilderV3;
      25: iload_1
      26: invokevirtual #124                // Method com/google/protobuf/RepeatedFieldBuilderV3.getMessageOrBuilder:(I)Lcom/google/protobuf/MessageOrBuilder;
      29: checkcast     #123                // class io/grpc/lookup/v1/HttpKeyBuilderOrBuilder
      32: areturn

  public java.util.List<? extends io.grpc.lookup.v1.HttpKeyBuilderOrBuilder> getHttpKeybuildersOrBuilderList();
    Code:
       0: aload_0
       1: getfield      #23                 // Field httpKeybuildersBuilder_:Lcom/google/protobuf/RepeatedFieldBuilderV3;
       4: ifnull        15
       7: aload_0
       8: getfield      #23                 // Field httpKeybuildersBuilder_:Lcom/google/protobuf/RepeatedFieldBuilderV3;
      11: invokevirtual #125                // Method com/google/protobuf/RepeatedFieldBuilderV3.getMessageOrBuilderList:()Ljava/util/List;
      14: areturn
      15: aload_0
      16: getfield      #10                 // Field httpKeybuilders_:Ljava/util/List;
      19: invokestatic  #39                 // Method java/util/Collections.unmodifiableList:(Ljava/util/List;)Ljava/util/List;
      22: areturn

  public io.grpc.lookup.v1.HttpKeyBuilder$Builder addHttpKeybuildersBuilder();
    Code:
       0: aload_0
       1: invokespecial #20                 // Method getHttpKeybuildersFieldBuilder:()Lcom/google/protobuf/RepeatedFieldBuilderV3;
       4: invokestatic  #126                // Method io/grpc/lookup/v1/HttpKeyBuilder.getDefaultInstance:()Lio/grpc/lookup/v1/HttpKeyBuilder;
       7: invokevirtual #127                // Method com/google/protobuf/RepeatedFieldBuilderV3.addBuilder:(Lcom/google/protobuf/AbstractMessage;)Lcom/google/protobuf/AbstractMessage$Builder;
      10: checkcast     #122                // class io/grpc/lookup/v1/HttpKeyBuilder$Builder
      13: areturn

  public io.grpc.lookup.v1.HttpKeyBuilder$Builder addHttpKeybuildersBuilder(int);
    Code:
       0: aload_0
       1: invokespecial #20                 // Method getHttpKeybuildersFieldBuilder:()Lcom/google/protobuf/RepeatedFieldBuilderV3;
       4: iload_1
       5: invokestatic  #126                // Method io/grpc/lookup/v1/HttpKeyBuilder.getDefaultInstance:()Lio/grpc/lookup/v1/HttpKeyBuilder;
       8: invokevirtual #128                // Method com/google/protobuf/RepeatedFieldBuilderV3.addBuilder:(ILcom/google/protobuf/AbstractMessage;)Lcom/google/protobuf/AbstractMessage$Builder;
      11: checkcast     #122                // class io/grpc/lookup/v1/HttpKeyBuilder$Builder
      14: areturn

  public java.util.List<io.grpc.lookup.v1.HttpKeyBuilder$Builder> getHttpKeybuildersBuilderList();
    Code:
       0: aload_0
       1: invokespecial #20                 // Method getHttpKeybuildersFieldBuilder:()Lcom/google/protobuf/RepeatedFieldBuilderV3;
       4: invokevirtual #129                // Method com/google/protobuf/RepeatedFieldBuilderV3.getBuilderList:()Ljava/util/List;
       7: areturn

  private com.google.protobuf.RepeatedFieldBuilderV3<io.grpc.lookup.v1.HttpKeyBuilder, io.grpc.lookup.v1.HttpKeyBuilder$Builder, io.grpc.lookup.v1.HttpKeyBuilderOrBuilder> getHttpKeybuildersFieldBuilder();
    Code:
       0: aload_0
       1: getfield      #23                 // Field httpKeybuildersBuilder_:Lcom/google/protobuf/RepeatedFieldBuilderV3;
       4: ifnonnull     49
       7: aload_0
       8: new           #130                // class com/google/protobuf/RepeatedFieldBuilderV3
      11: dup
      12: aload_0
      13: getfield      #10                 // Field httpKeybuilders_:Ljava/util/List;
      16: aload_0
      17: getfield      #24                 // Field bitField0_:I
      20: iconst_1
      21: iand
      22: ifeq          29
      25: iconst_1
      26: goto          30
      29: iconst_0
      30: aload_0
      31: invokevirtual #131                // Method getParentForChildren:()Lcom/google/protobuf/GeneratedMessageV3$BuilderParent;
      34: aload_0
      35: invokevirtual #132                // Method isClean:()Z
      38: invokespecial #133                // Method com/google/protobuf/RepeatedFieldBuilderV3."<init>":(Ljava/util/List;ZLcom/google/protobuf/AbstractMessage$BuilderParent;Z)V
      41: putfield      #23                 // Field httpKeybuildersBuilder_:Lcom/google/protobuf/RepeatedFieldBuilderV3;
      44: aload_0
      45: aconst_null
      46: putfield      #10                 // Field httpKeybuilders_:Ljava/util/List;
      49: aload_0
      50: getfield      #23                 // Field httpKeybuildersBuilder_:Lcom/google/protobuf/RepeatedFieldBuilderV3;
      53: areturn

  private void ensureGrpcKeybuildersIsMutable();
    Code:
       0: aload_0
       1: getfield      #24                 // Field bitField0_:I
       4: iconst_2
       5: iand
       6: ifne          34
       9: aload_0
      10: new           #101                // class java/util/ArrayList
      13: dup
      14: aload_0
      15: getfield      #11                 // Field grpcKeybuilders_:Ljava/util/List;
      18: invokespecial #102                // Method java/util/ArrayList."<init>":(Ljava/util/Collection;)V
      21: putfield      #11                 // Field grpcKeybuilders_:Ljava/util/List;
      24: aload_0
      25: dup
      26: getfield      #24                 // Field bitField0_:I
      29: iconst_2
      30: ior
      31: putfield      #24                 // Field bitField0_:I
      34: return

  public java.util.List<io.grpc.lookup.v1.GrpcKeyBuilder> getGrpcKeybuildersList();
    Code:
       0: aload_0
       1: getfield      #26                 // Field grpcKeybuildersBuilder_:Lcom/google/protobuf/RepeatedFieldBuilderV3;
       4: ifnonnull     15
       7: aload_0
       8: getfield      #11                 // Field grpcKeybuilders_:Ljava/util/List;
      11: invokestatic  #39                 // Method java/util/Collections.unmodifiableList:(Ljava/util/List;)Ljava/util/List;
      14: areturn
      15: aload_0
      16: getfield      #26                 // Field grpcKeybuildersBuilder_:Lcom/google/protobuf/RepeatedFieldBuilderV3;
      19: invokevirtual #103                // Method com/google/protobuf/RepeatedFieldBuilderV3.getMessageList:()Ljava/util/List;
      22: areturn

  public int getGrpcKeybuildersCount();
    Code:
       0: aload_0
       1: getfield      #26                 // Field grpcKeybuildersBuilder_:Lcom/google/protobuf/RepeatedFieldBuilderV3;
       4: ifnonnull     17
       7: aload_0
       8: getfield      #11                 // Field grpcKeybuilders_:Ljava/util/List;
      11: invokeinterface #104,  1          // InterfaceMethod java/util/List.size:()I
      16: ireturn
      17: aload_0
      18: getfield      #26                 // Field grpcKeybuildersBuilder_:Lcom/google/protobuf/RepeatedFieldBuilderV3;
      21: invokevirtual #105                // Method com/google/protobuf/RepeatedFieldBuilderV3.getCount:()I
      24: ireturn

  public io.grpc.lookup.v1.GrpcKeyBuilder getGrpcKeybuilders(int);
    Code:
       0: aload_0
       1: getfield      #26                 // Field grpcKeybuildersBuilder_:Lcom/google/protobuf/RepeatedFieldBuilderV3;
       4: ifnonnull     21
       7: aload_0
       8: getfield      #11                 // Field grpcKeybuilders_:Ljava/util/List;
      11: iload_1
      12: invokeinterface #106,  2          // InterfaceMethod java/util/List.get:(I)Ljava/lang/Object;
      17: checkcast     #134                // class io/grpc/lookup/v1/GrpcKeyBuilder
      20: areturn
      21: aload_0
      22: getfield      #26                 // Field grpcKeybuildersBuilder_:Lcom/google/protobuf/RepeatedFieldBuilderV3;
      25: iload_1
      26: invokevirtual #108                // Method com/google/protobuf/RepeatedFieldBuilderV3.getMessage:(I)Lcom/google/protobuf/AbstractMessage;
      29: checkcast     #134                // class io/grpc/lookup/v1/GrpcKeyBuilder
      32: areturn

  public io.grpc.lookup.v1.RouteLookupConfig$Builder setGrpcKeybuilders(int, io.grpc.lookup.v1.GrpcKeyBuilder);
    Code:
       0: aload_0
       1: getfield      #26                 // Field grpcKeybuildersBuilder_:Lcom/google/protobuf/RepeatedFieldBuilderV3;
       4: ifnonnull     42
       7: aload_2
       8: ifnonnull     19
      11: new           #109                // class java/lang/NullPointerException
      14: dup
      15: invokespecial #110                // Method java/lang/NullPointerException."<init>":()V
      18: athrow
      19: aload_0
      20: invokespecial #72                 // Method ensureGrpcKeybuildersIsMutable:()V
      23: aload_0
      24: getfield      #11                 // Field grpcKeybuilders_:Ljava/util/List;
      27: iload_1
      28: aload_2
      29: invokeinterface #111,  3          // InterfaceMethod java/util/List.set:(ILjava/lang/Object;)Ljava/lang/Object;
      34: pop
      35: aload_0
      36: invokevirtual #66                 // Method onChanged:()V
      39: goto          52
      42: aload_0
      43: getfield      #26                 // Field grpcKeybuildersBuilder_:Lcom/google/protobuf/RepeatedFieldBuilderV3;
      46: iload_1
      47: aload_2
      48: invokevirtual #112                // Method com/google/protobuf/RepeatedFieldBuilderV3.setMessage:(ILcom/google/protobuf/AbstractMessage;)Lcom/google/protobuf/RepeatedFieldBuilderV3;
      51: pop
      52: aload_0
      53: areturn

  public io.grpc.lookup.v1.RouteLookupConfig$Builder setGrpcKeybuilders(int, io.grpc.lookup.v1.GrpcKeyBuilder$Builder);
    Code:
       0: aload_0
       1: getfield      #26                 // Field grpcKeybuildersBuilder_:Lcom/google/protobuf/RepeatedFieldBuilderV3;
       4: ifnonnull     33
       7: aload_0
       8: invokespecial #72                 // Method ensureGrpcKeybuildersIsMutable:()V
      11: aload_0
      12: getfield      #11                 // Field grpcKeybuilders_:Ljava/util/List;
      15: iload_1
      16: aload_2
      17: invokevirtual #135                // Method io/grpc/lookup/v1/GrpcKeyBuilder$Builder.build:()Lio/grpc/lookup/v1/GrpcKeyBuilder;
      20: invokeinterface #111,  3          // InterfaceMethod java/util/List.set:(ILjava/lang/Object;)Ljava/lang/Object;
      25: pop
      26: aload_0
      27: invokevirtual #66                 // Method onChanged:()V
      30: goto          46
      33: aload_0
      34: getfield      #26                 // Field grpcKeybuildersBuilder_:Lcom/google/protobuf/RepeatedFieldBuilderV3;
      37: iload_1
      38: aload_2
      39: invokevirtual #135                // Method io/grpc/lookup/v1/GrpcKeyBuilder$Builder.build:()Lio/grpc/lookup/v1/GrpcKeyBuilder;
      42: invokevirtual #112                // Method com/google/protobuf/RepeatedFieldBuilderV3.setMessage:(ILcom/google/protobuf/AbstractMessage;)Lcom/google/protobuf/RepeatedFieldBuilderV3;
      45: pop
      46: aload_0
      47: areturn

  public io.grpc.lookup.v1.RouteLookupConfig$Builder addGrpcKeybuilders(io.grpc.lookup.v1.GrpcKeyBuilder);
    Code:
       0: aload_0
       1: getfield      #26                 // Field grpcKeybuildersBuilder_:Lcom/google/protobuf/RepeatedFieldBuilderV3;
       4: ifnonnull     41
       7: aload_1
       8: ifnonnull     19
      11: new           #109                // class java/lang/NullPointerException
      14: dup
      15: invokespecial #110                // Method java/lang/NullPointerException."<init>":()V
      18: athrow
      19: aload_0
      20: invokespecial #72                 // Method ensureGrpcKeybuildersIsMutable:()V
      23: aload_0
      24: getfield      #11                 // Field grpcKeybuilders_:Ljava/util/List;
      27: aload_1
      28: invokeinterface #114,  2          // InterfaceMethod java/util/List.add:(Ljava/lang/Object;)Z
      33: pop
      34: aload_0
      35: invokevirtual #66                 // Method onChanged:()V
      38: goto          50
      41: aload_0
      42: getfield      #26                 // Field grpcKeybuildersBuilder_:Lcom/google/protobuf/RepeatedFieldBuilderV3;
      45: aload_1
      46: invokevirtual #115                // Method com/google/protobuf/RepeatedFieldBuilderV3.addMessage:(Lcom/google/protobuf/AbstractMessage;)Lcom/google/protobuf/RepeatedFieldBuilderV3;
      49: pop
      50: aload_0
      51: areturn

  public io.grpc.lookup.v1.RouteLookupConfig$Builder addGrpcKeybuilders(int, io.grpc.lookup.v1.GrpcKeyBuilder);
    Code:
       0: aload_0
       1: getfield      #26                 // Field grpcKeybuildersBuilder_:Lcom/google/protobuf/RepeatedFieldBuilderV3;
       4: ifnonnull     41
       7: aload_2
       8: ifnonnull     19
      11: new           #109                // class java/lang/NullPointerException
      14: dup
      15: invokespecial #110                // Method java/lang/NullPointerException."<init>":()V
      18: athrow
      19: aload_0
      20: invokespecial #72                 // Method ensureGrpcKeybuildersIsMutable:()V
      23: aload_0
      24: getfield      #11                 // Field grpcKeybuilders_:Ljava/util/List;
      27: iload_1
      28: aload_2
      29: invokeinterface #116,  3          // InterfaceMethod java/util/List.add:(ILjava/lang/Object;)V
      34: aload_0
      35: invokevirtual #66                 // Method onChanged:()V
      38: goto          51
      41: aload_0
      42: getfield      #26                 // Field grpcKeybuildersBuilder_:Lcom/google/protobuf/RepeatedFieldBuilderV3;
      45: iload_1
      46: aload_2
      47: invokevirtual #117                // Method com/google/protobuf/RepeatedFieldBuilderV3.addMessage:(ILcom/google/protobuf/AbstractMessage;)Lcom/google/protobuf/RepeatedFieldBuilderV3;
      50: pop
      51: aload_0
      52: areturn

  public io.grpc.lookup.v1.RouteLookupConfig$Builder addGrpcKeybuilders(io.grpc.lookup.v1.GrpcKeyBuilder$Builder);
    Code:
       0: aload_0
       1: getfield      #26                 // Field grpcKeybuildersBuilder_:Lcom/google/protobuf/RepeatedFieldBuilderV3;
       4: ifnonnull     32
       7: aload_0
       8: invokespecial #72                 // Method ensureGrpcKeybuildersIsMutable:()V
      11: aload_0
      12: getfield      #11                 // Field grpcKeybuilders_:Ljava/util/List;
      15: aload_1
      16: invokevirtual #135                // Method io/grpc/lookup/v1/GrpcKeyBuilder$Builder.build:()Lio/grpc/lookup/v1/GrpcKeyBuilder;
      19: invokeinterface #114,  2          // InterfaceMethod java/util/List.add:(Ljava/lang/Object;)Z
      24: pop
      25: aload_0
      26: invokevirtual #66                 // Method onChanged:()V
      29: goto          44
      32: aload_0
      33: getfield      #26                 // Field grpcKeybuildersBuilder_:Lcom/google/protobuf/RepeatedFieldBuilderV3;
      36: aload_1
      37: invokevirtual #135                // Method io/grpc/lookup/v1/GrpcKeyBuilder$Builder.build:()Lio/grpc/lookup/v1/GrpcKeyBuilder;
      40: invokevirtual #115                // Method com/google/protobuf/RepeatedFieldBuilderV3.addMessage:(Lcom/google/protobuf/AbstractMessage;)Lcom/google/protobuf/RepeatedFieldBuilderV3;
      43: pop
      44: aload_0
      45: areturn

  public io.grpc.lookup.v1.RouteLookupConfig$Builder addGrpcKeybuilders(int, io.grpc.lookup.v1.GrpcKeyBuilder$Builder);
    Code:
       0: aload_0
       1: getfield      #26                 // Field grpcKeybuildersBuilder_:Lcom/google/protobuf/RepeatedFieldBuilderV3;
       4: ifnonnull     32
       7: aload_0
       8: invokespecial #72                 // Method ensureGrpcKeybuildersIsMutable:()V
      11: aload_0
      12: getfield      #11                 // Field grpcKeybuilders_:Ljava/util/List;
      15: iload_1
      16: aload_2
      17: invokevirtual #135                // Method io/grpc/lookup/v1/GrpcKeyBuilder$Builder.build:()Lio/grpc/lookup/v1/GrpcKeyBuilder;
      20: invokeinterface #116,  3          // InterfaceMethod java/util/List.add:(ILjava/lang/Object;)V
      25: aload_0
      26: invokevirtual #66                 // Method onChanged:()V
      29: goto          45
      32: aload_0
      33: getfield      #26                 // Field grpcKeybuildersBuilder_:Lcom/google/protobuf/RepeatedFieldBuilderV3;
      36: iload_1
      37: aload_2
      38: invokevirtual #135                // Method io/grpc/lookup/v1/GrpcKeyBuilder$Builder.build:()Lio/grpc/lookup/v1/GrpcKeyBuilder;
      41: invokevirtual #117                // Method com/google/protobuf/RepeatedFieldBuilderV3.addMessage:(ILcom/google/protobuf/AbstractMessage;)Lcom/google/protobuf/RepeatedFieldBuilderV3;
      44: pop
      45: aload_0
      46: areturn

  public io.grpc.lookup.v1.RouteLookupConfig$Builder addAllGrpcKeybuilders(java.lang.Iterable<? extends io.grpc.lookup.v1.GrpcKeyBuilder>);
    Code:
       0: aload_0
       1: getfield      #26                 // Field grpcKeybuildersBuilder_:Lcom/google/protobuf/RepeatedFieldBuilderV3;
       4: ifnonnull     26
       7: aload_0
       8: invokespecial #72                 // Method ensureGrpcKeybuildersIsMutable:()V
      11: aload_1
      12: aload_0
      13: getfield      #11                 // Field grpcKeybuilders_:Ljava/util/List;
      16: invokestatic  #118                // Method com/google/protobuf/AbstractMessageLite$Builder.addAll:(Ljava/lang/Iterable;Ljava/util/List;)V
      19: aload_0
      20: invokevirtual #66                 // Method onChanged:()V
      23: goto          35
      26: aload_0
      27: getfield      #26                 // Field grpcKeybuildersBuilder_:Lcom/google/protobuf/RepeatedFieldBuilderV3;
      30: aload_1
      31: invokevirtual #70                 // Method com/google/protobuf/RepeatedFieldBuilderV3.addAllMessages:(Ljava/lang/Iterable;)Lcom/google/protobuf/RepeatedFieldBuilderV3;
      34: pop
      35: aload_0
      36: areturn

  public io.grpc.lookup.v1.RouteLookupConfig$Builder clearGrpcKeybuilders();
    Code:
       0: aload_0
       1: getfield      #26                 // Field grpcKeybuildersBuilder_:Lcom/google/protobuf/RepeatedFieldBuilderV3;
       4: ifnonnull     32
       7: aload_0
       8: invokestatic  #9                  // Method java/util/Collections.emptyList:()Ljava/util/List;
      11: putfield      #11                 // Field grpcKeybuilders_:Ljava/util/List;
      14: aload_0
      15: aload_0
      16: getfield      #24                 // Field bitField0_:I
      19: bipush        -3
      21: iand
      22: putfield      #24                 // Field bitField0_:I
      25: aload_0
      26: invokevirtual #66                 // Method onChanged:()V
      29: goto          39
      32: aload_0
      33: getfield      #26                 // Field grpcKeybuildersBuilder_:Lcom/google/protobuf/RepeatedFieldBuilderV3;
      36: invokevirtual #25                 // Method com/google/protobuf/RepeatedFieldBuilderV3.clear:()V
      39: aload_0
      40: areturn

  public io.grpc.lookup.v1.RouteLookupConfig$Builder removeGrpcKeybuilders(int);
    Code:
       0: aload_0
       1: getfield      #26                 // Field grpcKeybuildersBuilder_:Lcom/google/protobuf/RepeatedFieldBuilderV3;
       4: ifnonnull     29
       7: aload_0
       8: invokespecial #72                 // Method ensureGrpcKeybuildersIsMutable:()V
      11: aload_0
      12: getfield      #11                 // Field grpcKeybuilders_:Ljava/util/List;
      15: iload_1
      16: invokeinterface #119,  2          // InterfaceMethod java/util/List.remove:(I)Ljava/lang/Object;
      21: pop
      22: aload_0
      23: invokevirtual #66                 // Method onChanged:()V
      26: goto          37
      29: aload_0
      30: getfield      #26                 // Field grpcKeybuildersBuilder_:Lcom/google/protobuf/RepeatedFieldBuilderV3;
      33: iload_1
      34: invokevirtual #120                // Method com/google/protobuf/RepeatedFieldBuilderV3.remove:(I)V
      37: aload_0
      38: areturn

  public io.grpc.lookup.v1.GrpcKeyBuilder$Builder getGrpcKeybuildersBuilder(int);
    Code:
       0: aload_0
       1: invokespecial #21                 // Method getGrpcKeybuildersFieldBuilder:()Lcom/google/protobuf/RepeatedFieldBuilderV3;
       4: iload_1
       5: invokevirtual #121                // Method com/google/protobuf/RepeatedFieldBuilderV3.getBuilder:(I)Lcom/google/protobuf/AbstractMessage$Builder;
       8: checkcast     #136                // class io/grpc/lookup/v1/GrpcKeyBuilder$Builder
      11: areturn

  public io.grpc.lookup.v1.GrpcKeyBuilderOrBuilder getGrpcKeybuildersOrBuilder(int);
    Code:
       0: aload_0
       1: getfield      #26                 // Field grpcKeybuildersBuilder_:Lcom/google/protobuf/RepeatedFieldBuilderV3;
       4: ifnonnull     21
       7: aload_0
       8: getfield      #11                 // Field grpcKeybuilders_:Ljava/util/List;
      11: iload_1
      12: invokeinterface #106,  2          // InterfaceMethod java/util/List.get:(I)Ljava/lang/Object;
      17: checkcast     #137                // class io/grpc/lookup/v1/GrpcKeyBuilderOrBuilder
      20: areturn
      21: aload_0
      22: getfield      #26                 // Field grpcKeybuildersBuilder_:Lcom/google/protobuf/RepeatedFieldBuilderV3;
      25: iload_1
      26: invokevirtual #124                // Method com/google/protobuf/RepeatedFieldBuilderV3.getMessageOrBuilder:(I)Lcom/google/protobuf/MessageOrBuilder;
      29: checkcast     #137                // class io/grpc/lookup/v1/GrpcKeyBuilderOrBuilder
      32: areturn

  public java.util.List<? extends io.grpc.lookup.v1.GrpcKeyBuilderOrBuilder> getGrpcKeybuildersOrBuilderList();
    Code:
       0: aload_0
       1: getfield      #26                 // Field grpcKeybuildersBuilder_:Lcom/google/protobuf/RepeatedFieldBuilderV3;
       4: ifnull        15
       7: aload_0
       8: getfield      #26                 // Field grpcKeybuildersBuilder_:Lcom/google/protobuf/RepeatedFieldBuilderV3;
      11: invokevirtual #125                // Method com/google/protobuf/RepeatedFieldBuilderV3.getMessageOrBuilderList:()Ljava/util/List;
      14: areturn
      15: aload_0
      16: getfield      #11                 // Field grpcKeybuilders_:Ljava/util/List;
      19: invokestatic  #39                 // Method java/util/Collections.unmodifiableList:(Ljava/util/List;)Ljava/util/List;
      22: areturn

  public io.grpc.lookup.v1.GrpcKeyBuilder$Builder addGrpcKeybuildersBuilder();
    Code:
       0: aload_0
       1: invokespecial #21                 // Method getGrpcKeybuildersFieldBuilder:()Lcom/google/protobuf/RepeatedFieldBuilderV3;
       4: invokestatic  #138                // Method io/grpc/lookup/v1/GrpcKeyBuilder.getDefaultInstance:()Lio/grpc/lookup/v1/GrpcKeyBuilder;
       7: invokevirtual #127                // Method com/google/protobuf/RepeatedFieldBuilderV3.addBuilder:(Lcom/google/protobuf/AbstractMessage;)Lcom/google/protobuf/AbstractMessage$Builder;
      10: checkcast     #136                // class io/grpc/lookup/v1/GrpcKeyBuilder$Builder
      13: areturn

  public io.grpc.lookup.v1.GrpcKeyBuilder$Builder addGrpcKeybuildersBuilder(int);
    Code:
       0: aload_0
       1: invokespecial #21                 // Method getGrpcKeybuildersFieldBuilder:()Lcom/google/protobuf/RepeatedFieldBuilderV3;
       4: iload_1
       5: invokestatic  #138                // Method io/grpc/lookup/v1/GrpcKeyBuilder.getDefaultInstance:()Lio/grpc/lookup/v1/GrpcKeyBuilder;
       8: invokevirtual #128                // Method com/google/protobuf/RepeatedFieldBuilderV3.addBuilder:(ILcom/google/protobuf/AbstractMessage;)Lcom/google/protobuf/AbstractMessage$Builder;
      11: checkcast     #136                // class io/grpc/lookup/v1/GrpcKeyBuilder$Builder
      14: areturn

  public java.util.List<io.grpc.lookup.v1.GrpcKeyBuilder$Builder> getGrpcKeybuildersBuilderList();
    Code:
       0: aload_0
       1: invokespecial #21                 // Method getGrpcKeybuildersFieldBuilder:()Lcom/google/protobuf/RepeatedFieldBuilderV3;
       4: invokevirtual #129                // Method com/google/protobuf/RepeatedFieldBuilderV3.getBuilderList:()Ljava/util/List;
       7: areturn

  private com.google.protobuf.RepeatedFieldBuilderV3<io.grpc.lookup.v1.GrpcKeyBuilder, io.grpc.lookup.v1.GrpcKeyBuilder$Builder, io.grpc.lookup.v1.GrpcKeyBuilderOrBuilder> getGrpcKeybuildersFieldBuilder();
    Code:
       0: aload_0
       1: getfield      #26                 // Field grpcKeybuildersBuilder_:Lcom/google/protobuf/RepeatedFieldBuilderV3;
       4: ifnonnull     49
       7: aload_0
       8: new           #130                // class com/google/protobuf/RepeatedFieldBuilderV3
      11: dup
      12: aload_0
      13: getfield      #11                 // Field grpcKeybuilders_:Ljava/util/List;
      16: aload_0
      17: getfield      #24                 // Field bitField0_:I
      20: iconst_2
      21: iand
      22: ifeq          29
      25: iconst_1
      26: goto          30
      29: iconst_0
      30: aload_0
      31: invokevirtual #131                // Method getParentForChildren:()Lcom/google/protobuf/GeneratedMessageV3$BuilderParent;
      34: aload_0
      35: invokevirtual #132                // Method isClean:()Z
      38: invokespecial #133                // Method com/google/protobuf/RepeatedFieldBuilderV3."<init>":(Ljava/util/List;ZLcom/google/protobuf/AbstractMessage$BuilderParent;Z)V
      41: putfield      #26                 // Field grpcKeybuildersBuilder_:Lcom/google/protobuf/RepeatedFieldBuilderV3;
      44: aload_0
      45: aconst_null
      46: putfield      #11                 // Field grpcKeybuilders_:Ljava/util/List;
      49: aload_0
      50: getfield      #26                 // Field grpcKeybuildersBuilder_:Lcom/google/protobuf/RepeatedFieldBuilderV3;
      53: areturn

  public java.lang.String getLookupService();
    Code:
       0: aload_0
       1: getfield      #13                 // Field lookupService_:Ljava/lang/Object;
       4: astore_1
       5: aload_1
       6: instanceof    #139                // class java/lang/String
       9: ifne          29
      12: aload_1
      13: checkcast     #140                // class com/google/protobuf/ByteString
      16: astore_2
      17: aload_2
      18: invokevirtual #141                // Method com/google/protobuf/ByteString.toStringUtf8:()Ljava/lang/String;
      21: astore_3
      22: aload_0
      23: aload_3
      24: putfield      #13                 // Field lookupService_:Ljava/lang/Object;
      27: aload_3
      28: areturn
      29: aload_1
      30: checkcast     #139                // class java/lang/String
      33: areturn

  public com.google.protobuf.ByteString getLookupServiceBytes();
    Code:
       0: aload_0
       1: getfield      #13                 // Field lookupService_:Ljava/lang/Object;
       4: astore_1
       5: aload_1
       6: instanceof    #139                // class java/lang/String
       9: ifeq          27
      12: aload_1
      13: checkcast     #139                // class java/lang/String
      16: invokestatic  #142                // Method com/google/protobuf/ByteString.copyFromUtf8:(Ljava/lang/String;)Lcom/google/protobuf/ByteString;
      19: astore_2
      20: aload_0
      21: aload_2
      22: putfield      #13                 // Field lookupService_:Ljava/lang/Object;
      25: aload_2
      26: areturn
      27: aload_1
      28: checkcast     #140                // class com/google/protobuf/ByteString
      31: areturn

  public io.grpc.lookup.v1.RouteLookupConfig$Builder setLookupService(java.lang.String);
    Code:
       0: aload_1
       1: ifnonnull     12
       4: new           #109                // class java/lang/NullPointerException
       7: dup
       8: invokespecial #110                // Method java/lang/NullPointerException."<init>":()V
      11: athrow
      12: aload_0
      13: aload_1
      14: putfield      #13                 // Field lookupService_:Ljava/lang/Object;
      17: aload_0
      18: invokevirtual #66                 // Method onChanged:()V
      21: aload_0
      22: areturn

  public io.grpc.lookup.v1.RouteLookupConfig$Builder clearLookupService();
    Code:
       0: aload_0
       1: invokestatic  #34                 // Method io/grpc/lookup/v1/RouteLookupConfig.getDefaultInstance:()Lio/grpc/lookup/v1/RouteLookupConfig;
       4: invokevirtual #74                 // Method io/grpc/lookup/v1/RouteLookupConfig.getLookupService:()Ljava/lang/String;
       7: putfield      #13                 // Field lookupService_:Ljava/lang/Object;
      10: aload_0
      11: invokevirtual #66                 // Method onChanged:()V
      14: aload_0
      15: areturn

  public io.grpc.lookup.v1.RouteLookupConfig$Builder setLookupServiceBytes(com.google.protobuf.ByteString);
    Code:
       0: aload_1
       1: ifnonnull     12
       4: new           #109                // class java/lang/NullPointerException
       7: dup
       8: invokespecial #110                // Method java/lang/NullPointerException."<init>":()V
      11: athrow
      12: aload_1
      13: invokestatic  #143                // Method io/grpc/lookup/v1/RouteLookupConfig.access$1700:(Lcom/google/protobuf/ByteString;)V
      16: aload_0
      17: aload_1
      18: putfield      #13                 // Field lookupService_:Ljava/lang/Object;
      21: aload_0
      22: invokevirtual #66                 // Method onChanged:()V
      25: aload_0
      26: areturn

  public boolean hasLookupServiceTimeout();
    Code:
       0: aload_0
       1: getfield      #27                 // Field lookupServiceTimeoutBuilder_:Lcom/google/protobuf/SingleFieldBuilderV3;
       4: ifnonnull     14
       7: aload_0
       8: getfield      #28                 // Field lookupServiceTimeout_:Lcom/google/protobuf/Duration;
      11: ifnull        18
      14: iconst_1
      15: goto          19
      18: iconst_0
      19: ireturn

  public com.google.protobuf.Duration getLookupServiceTimeout();
    Code:
       0: aload_0
       1: getfield      #27                 // Field lookupServiceTimeoutBuilder_:Lcom/google/protobuf/SingleFieldBuilderV3;
       4: ifnonnull     25
       7: aload_0
       8: getfield      #28                 // Field lookupServiceTimeout_:Lcom/google/protobuf/Duration;
      11: ifnonnull     20
      14: invokestatic  #144                // Method com/google/protobuf/Duration.getDefaultInstance:()Lcom/google/protobuf/Duration;
      17: goto          24
      20: aload_0
      21: getfield      #28                 // Field lookupServiceTimeout_:Lcom/google/protobuf/Duration;
      24: areturn
      25: aload_0
      26: getfield      #27                 // Field lookupServiceTimeoutBuilder_:Lcom/google/protobuf/SingleFieldBuilderV3;
      29: invokevirtual #145                // Method com/google/protobuf/SingleFieldBuilderV3.getMessage:()Lcom/google/protobuf/AbstractMessage;
      32: checkcast     #46                 // class com/google/protobuf/Duration
      35: areturn

  public io.grpc.lookup.v1.RouteLookupConfig$Builder setLookupServiceTimeout(com.google.protobuf.Duration);
    Code:
       0: aload_0
       1: getfield      #27                 // Field lookupServiceTimeoutBuilder_:Lcom/google/protobuf/SingleFieldBuilderV3;
       4: ifnonnull     31
       7: aload_1
       8: ifnonnull     19
      11: new           #109                // class java/lang/NullPointerException
      14: dup
      15: invokespecial #110                // Method java/lang/NullPointerException."<init>":()V
      18: athrow
      19: aload_0
      20: aload_1
      21: putfield      #28                 // Field lookupServiceTimeout_:Lcom/google/protobuf/Duration;
      24: aload_0
      25: invokevirtual #66                 // Method onChanged:()V
      28: goto          40
      31: aload_0
      32: getfield      #27                 // Field lookupServiceTimeoutBuilder_:Lcom/google/protobuf/SingleFieldBuilderV3;
      35: aload_1
      36: invokevirtual #146                // Method com/google/protobuf/SingleFieldBuilderV3.setMessage:(Lcom/google/protobuf/AbstractMessage;)Lcom/google/protobuf/SingleFieldBuilderV3;
      39: pop
      40: aload_0
      41: areturn

  public io.grpc.lookup.v1.RouteLookupConfig$Builder setLookupServiceTimeout(com.google.protobuf.Duration$Builder);
    Code:
       0: aload_0
       1: getfield      #27                 // Field lookupServiceTimeoutBuilder_:Lcom/google/protobuf/SingleFieldBuilderV3;
       4: ifnonnull     22
       7: aload_0
       8: aload_1
       9: invokevirtual #147                // Method com/google/protobuf/Duration$Builder.build:()Lcom/google/protobuf/Duration;
      12: putfield      #28                 // Field lookupServiceTimeout_:Lcom/google/protobuf/Duration;
      15: aload_0
      16: invokevirtual #66                 // Method onChanged:()V
      19: goto          34
      22: aload_0
      23: getfield      #27                 // Field lookupServiceTimeoutBuilder_:Lcom/google/protobuf/SingleFieldBuilderV3;
      26: aload_1
      27: invokevirtual #147                // Method com/google/protobuf/Duration$Builder.build:()Lcom/google/protobuf/Duration;
      30: invokevirtual #146                // Method com/google/protobuf/SingleFieldBuilderV3.setMessage:(Lcom/google/protobuf/AbstractMessage;)Lcom/google/protobuf/SingleFieldBuilderV3;
      33: pop
      34: aload_0
      35: areturn

  public io.grpc.lookup.v1.RouteLookupConfig$Builder mergeLookupServiceTimeout(com.google.protobuf.Duration);
    Code:
       0: aload_0
       1: getfield      #27                 // Field lookupServiceTimeoutBuilder_:Lcom/google/protobuf/SingleFieldBuilderV3;
       4: ifnonnull     47
       7: aload_0
       8: getfield      #28                 // Field lookupServiceTimeout_:Lcom/google/protobuf/Duration;
      11: ifnull        35
      14: aload_0
      15: aload_0
      16: getfield      #28                 // Field lookupServiceTimeout_:Lcom/google/protobuf/Duration;
      19: invokestatic  #148                // Method com/google/protobuf/Duration.newBuilder:(Lcom/google/protobuf/Duration;)Lcom/google/protobuf/Duration$Builder;
      22: aload_1
      23: invokevirtual #149                // Method com/google/protobuf/Duration$Builder.mergeFrom:(Lcom/google/protobuf/Duration;)Lcom/google/protobuf/Duration$Builder;
      26: invokevirtual #150                // Method com/google/protobuf/Duration$Builder.buildPartial:()Lcom/google/protobuf/Duration;
      29: putfield      #28                 // Field lookupServiceTimeout_:Lcom/google/protobuf/Duration;
      32: goto          40
      35: aload_0
      36: aload_1
      37: putfield      #28                 // Field lookupServiceTimeout_:Lcom/google/protobuf/Duration;
      40: aload_0
      41: invokevirtual #66                 // Method onChanged:()V
      44: goto          56
      47: aload_0
      48: getfield      #27                 // Field lookupServiceTimeoutBuilder_:Lcom/google/protobuf/SingleFieldBuilderV3;
      51: aload_1
      52: invokevirtual #151                // Method com/google/protobuf/SingleFieldBuilderV3.mergeFrom:(Lcom/google/protobuf/AbstractMessage;)Lcom/google/protobuf/SingleFieldBuilderV3;
      55: pop
      56: aload_0
      57: areturn

  public io.grpc.lookup.v1.RouteLookupConfig$Builder clearLookupServiceTimeout();
    Code:
       0: aload_0
       1: getfield      #27                 // Field lookupServiceTimeoutBuilder_:Lcom/google/protobuf/SingleFieldBuilderV3;
       4: ifnonnull     19
       7: aload_0
       8: aconst_null
       9: putfield      #28                 // Field lookupServiceTimeout_:Lcom/google/protobuf/Duration;
      12: aload_0
      13: invokevirtual #66                 // Method onChanged:()V
      16: goto          29
      19: aload_0
      20: aconst_null
      21: putfield      #28                 // Field lookupServiceTimeout_:Lcom/google/protobuf/Duration;
      24: aload_0
      25: aconst_null
      26: putfield      #27                 // Field lookupServiceTimeoutBuilder_:Lcom/google/protobuf/SingleFieldBuilderV3;
      29: aload_0
      30: areturn

  public com.google.protobuf.Duration$Builder getLookupServiceTimeoutBuilder();
    Code:
       0: aload_0
       1: invokevirtual #66                 // Method onChanged:()V
       4: aload_0
       5: invokespecial #152                // Method getLookupServiceTimeoutFieldBuilder:()Lcom/google/protobuf/SingleFieldBuilderV3;
       8: invokevirtual #153                // Method com/google/protobuf/SingleFieldBuilderV3.getBuilder:()Lcom/google/protobuf/AbstractMessage$Builder;
      11: checkcast     #154                // class com/google/protobuf/Duration$Builder
      14: areturn

  public com.google.protobuf.DurationOrBuilder getLookupServiceTimeoutOrBuilder();
    Code:
       0: aload_0
       1: getfield      #27                 // Field lookupServiceTimeoutBuilder_:Lcom/google/protobuf/SingleFieldBuilderV3;
       4: ifnull        18
       7: aload_0
       8: getfield      #27                 // Field lookupServiceTimeoutBuilder_:Lcom/google/protobuf/SingleFieldBuilderV3;
      11: invokevirtual #155                // Method com/google/protobuf/SingleFieldBuilderV3.getMessageOrBuilder:()Lcom/google/protobuf/MessageOrBuilder;
      14: checkcast     #156                // class com/google/protobuf/DurationOrBuilder
      17: areturn
      18: aload_0
      19: getfield      #28                 // Field lookupServiceTimeout_:Lcom/google/protobuf/Duration;
      22: ifnonnull     31
      25: invokestatic  #144                // Method com/google/protobuf/Duration.getDefaultInstance:()Lcom/google/protobuf/Duration;
      28: goto          35
      31: aload_0
      32: getfield      #28                 // Field lookupServiceTimeout_:Lcom/google/protobuf/Duration;
      35: areturn

  private com.google.protobuf.SingleFieldBuilderV3<com.google.protobuf.Duration, com.google.protobuf.Duration$Builder, com.google.protobuf.DurationOrBuilder> getLookupServiceTimeoutFieldBuilder();
    Code:
       0: aload_0
       1: getfield      #27                 // Field lookupServiceTimeoutBuilder_:Lcom/google/protobuf/SingleFieldBuilderV3;
       4: ifnonnull     35
       7: aload_0
       8: new           #157                // class com/google/protobuf/SingleFieldBuilderV3
      11: dup
      12: aload_0
      13: invokevirtual #158                // Method getLookupServiceTimeout:()Lcom/google/protobuf/Duration;
      16: aload_0
      17: invokevirtual #131                // Method getParentForChildren:()Lcom/google/protobuf/GeneratedMessageV3$BuilderParent;
      20: aload_0
      21: invokevirtual #132                // Method isClean:()Z
      24: invokespecial #159                // Method com/google/protobuf/SingleFieldBuilderV3."<init>":(Lcom/google/protobuf/AbstractMessage;Lcom/google/protobuf/AbstractMessage$BuilderParent;Z)V
      27: putfield      #27                 // Field lookupServiceTimeoutBuilder_:Lcom/google/protobuf/SingleFieldBuilderV3;
      30: aload_0
      31: aconst_null
      32: putfield      #28                 // Field lookupServiceTimeout_:Lcom/google/protobuf/Duration;
      35: aload_0
      36: getfield      #27                 // Field lookupServiceTimeoutBuilder_:Lcom/google/protobuf/SingleFieldBuilderV3;
      39: areturn

  public boolean hasMaxAge();
    Code:
       0: aload_0
       1: getfield      #29                 // Field maxAgeBuilder_:Lcom/google/protobuf/SingleFieldBuilderV3;
       4: ifnonnull     14
       7: aload_0
       8: getfield      #30                 // Field maxAge_:Lcom/google/protobuf/Duration;
      11: ifnull        18
      14: iconst_1
      15: goto          19
      18: iconst_0
      19: ireturn

  public com.google.protobuf.Duration getMaxAge();
    Code:
       0: aload_0
       1: getfield      #29                 // Field maxAgeBuilder_:Lcom/google/protobuf/SingleFieldBuilderV3;
       4: ifnonnull     25
       7: aload_0
       8: getfield      #30                 // Field maxAge_:Lcom/google/protobuf/Duration;
      11: ifnonnull     20
      14: invokestatic  #144                // Method com/google/protobuf/Duration.getDefaultInstance:()Lcom/google/protobuf/Duration;
      17: goto          24
      20: aload_0
      21: getfield      #30                 // Field maxAge_:Lcom/google/protobuf/Duration;
      24: areturn
      25: aload_0
      26: getfield      #29                 // Field maxAgeBuilder_:Lcom/google/protobuf/SingleFieldBuilderV3;
      29: invokevirtual #145                // Method com/google/protobuf/SingleFieldBuilderV3.getMessage:()Lcom/google/protobuf/AbstractMessage;
      32: checkcast     #46                 // class com/google/protobuf/Duration
      35: areturn

  public io.grpc.lookup.v1.RouteLookupConfig$Builder setMaxAge(com.google.protobuf.Duration);
    Code:
       0: aload_0
       1: getfield      #29                 // Field maxAgeBuilder_:Lcom/google/protobuf/SingleFieldBuilderV3;
       4: ifnonnull     31
       7: aload_1
       8: ifnonnull     19
      11: new           #109                // class java/lang/NullPointerException
      14: dup
      15: invokespecial #110                // Method java/lang/NullPointerException."<init>":()V
      18: athrow
      19: aload_0
      20: aload_1
      21: putfield      #30                 // Field maxAge_:Lcom/google/protobuf/Duration;
      24: aload_0
      25: invokevirtual #66                 // Method onChanged:()V
      28: goto          40
      31: aload_0
      32: getfield      #29                 // Field maxAgeBuilder_:Lcom/google/protobuf/SingleFieldBuilderV3;
      35: aload_1
      36: invokevirtual #146                // Method com/google/protobuf/SingleFieldBuilderV3.setMessage:(Lcom/google/protobuf/AbstractMessage;)Lcom/google/protobuf/SingleFieldBuilderV3;
      39: pop
      40: aload_0
      41: areturn

  public io.grpc.lookup.v1.RouteLookupConfig$Builder setMaxAge(com.google.protobuf.Duration$Builder);
    Code:
       0: aload_0
       1: getfield      #29                 // Field maxAgeBuilder_:Lcom/google/protobuf/SingleFieldBuilderV3;
       4: ifnonnull     22
       7: aload_0
       8: aload_1
       9: invokevirtual #147                // Method com/google/protobuf/Duration$Builder.build:()Lcom/google/protobuf/Duration;
      12: putfield      #30                 // Field maxAge_:Lcom/google/protobuf/Duration;
      15: aload_0
      16: invokevirtual #66                 // Method onChanged:()V
      19: goto          34
      22: aload_0
      23: getfield      #29                 // Field maxAgeBuilder_:Lcom/google/protobuf/SingleFieldBuilderV3;
      26: aload_1
      27: invokevirtual #147                // Method com/google/protobuf/Duration$Builder.build:()Lcom/google/protobuf/Duration;
      30: invokevirtual #146                // Method com/google/protobuf/SingleFieldBuilderV3.setMessage:(Lcom/google/protobuf/AbstractMessage;)Lcom/google/protobuf/SingleFieldBuilderV3;
      33: pop
      34: aload_0
      35: areturn

  public io.grpc.lookup.v1.RouteLookupConfig$Builder mergeMaxAge(com.google.protobuf.Duration);
    Code:
       0: aload_0
       1: getfield      #29                 // Field maxAgeBuilder_:Lcom/google/protobuf/SingleFieldBuilderV3;
       4: ifnonnull     47
       7: aload_0
       8: getfield      #30                 // Field maxAge_:Lcom/google/protobuf/Duration;
      11: ifnull        35
      14: aload_0
      15: aload_0
      16: getfield      #30                 // Field maxAge_:Lcom/google/protobuf/Duration;
      19: invokestatic  #148                // Method com/google/protobuf/Duration.newBuilder:(Lcom/google/protobuf/Duration;)Lcom/google/protobuf/Duration$Builder;
      22: aload_1
      23: invokevirtual #149                // Method com/google/protobuf/Duration$Builder.mergeFrom:(Lcom/google/protobuf/Duration;)Lcom/google/protobuf/Duration$Builder;
      26: invokevirtual #150                // Method com/google/protobuf/Duration$Builder.buildPartial:()Lcom/google/protobuf/Duration;
      29: putfield      #30                 // Field maxAge_:Lcom/google/protobuf/Duration;
      32: goto          40
      35: aload_0
      36: aload_1
      37: putfield      #30                 // Field maxAge_:Lcom/google/protobuf/Duration;
      40: aload_0
      41: invokevirtual #66                 // Method onChanged:()V
      44: goto          56
      47: aload_0
      48: getfield      #29                 // Field maxAgeBuilder_:Lcom/google/protobuf/SingleFieldBuilderV3;
      51: aload_1
      52: invokevirtual #151                // Method com/google/protobuf/SingleFieldBuilderV3.mergeFrom:(Lcom/google/protobuf/AbstractMessage;)Lcom/google/protobuf/SingleFieldBuilderV3;
      55: pop
      56: aload_0
      57: areturn

  public io.grpc.lookup.v1.RouteLookupConfig$Builder clearMaxAge();
    Code:
       0: aload_0
       1: getfield      #29                 // Field maxAgeBuilder_:Lcom/google/protobuf/SingleFieldBuilderV3;
       4: ifnonnull     19
       7: aload_0
       8: aconst_null
       9: putfield      #30                 // Field maxAge_:Lcom/google/protobuf/Duration;
      12: aload_0
      13: invokevirtual #66                 // Method onChanged:()V
      16: goto          29
      19: aload_0
      20: aconst_null
      21: putfield      #30                 // Field maxAge_:Lcom/google/protobuf/Duration;
      24: aload_0
      25: aconst_null
      26: putfield      #29                 // Field maxAgeBuilder_:Lcom/google/protobuf/SingleFieldBuilderV3;
      29: aload_0
      30: areturn

  public com.google.protobuf.Duration$Builder getMaxAgeBuilder();
    Code:
       0: aload_0
       1: invokevirtual #66                 // Method onChanged:()V
       4: aload_0
       5: invokespecial #160                // Method getMaxAgeFieldBuilder:()Lcom/google/protobuf/SingleFieldBuilderV3;
       8: invokevirtual #153                // Method com/google/protobuf/SingleFieldBuilderV3.getBuilder:()Lcom/google/protobuf/AbstractMessage$Builder;
      11: checkcast     #154                // class com/google/protobuf/Duration$Builder
      14: areturn

  public com.google.protobuf.DurationOrBuilder getMaxAgeOrBuilder();
    Code:
       0: aload_0
       1: getfield      #29                 // Field maxAgeBuilder_:Lcom/google/protobuf/SingleFieldBuilderV3;
       4: ifnull        18
       7: aload_0
       8: getfield      #29                 // Field maxAgeBuilder_:Lcom/google/protobuf/SingleFieldBuilderV3;
      11: invokevirtual #155                // Method com/google/protobuf/SingleFieldBuilderV3.getMessageOrBuilder:()Lcom/google/protobuf/MessageOrBuilder;
      14: checkcast     #156                // class com/google/protobuf/DurationOrBuilder
      17: areturn
      18: aload_0
      19: getfield      #30                 // Field maxAge_:Lcom/google/protobuf/Duration;
      22: ifnonnull     31
      25: invokestatic  #144                // Method com/google/protobuf/Duration.getDefaultInstance:()Lcom/google/protobuf/Duration;
      28: goto          35
      31: aload_0
      32: getfield      #30                 // Field maxAge_:Lcom/google/protobuf/Duration;
      35: areturn

  private com.google.protobuf.SingleFieldBuilderV3<com.google.protobuf.Duration, com.google.protobuf.Duration$Builder, com.google.protobuf.DurationOrBuilder> getMaxAgeFieldBuilder();
    Code:
       0: aload_0
       1: getfield      #29                 // Field maxAgeBuilder_:Lcom/google/protobuf/SingleFieldBuilderV3;
       4: ifnonnull     35
       7: aload_0
       8: new           #157                // class com/google/protobuf/SingleFieldBuilderV3
      11: dup
      12: aload_0
      13: invokevirtual #161                // Method getMaxAge:()Lcom/google/protobuf/Duration;
      16: aload_0
      17: invokevirtual #131                // Method getParentForChildren:()Lcom/google/protobuf/GeneratedMessageV3$BuilderParent;
      20: aload_0
      21: invokevirtual #132                // Method isClean:()Z
      24: invokespecial #159                // Method com/google/protobuf/SingleFieldBuilderV3."<init>":(Lcom/google/protobuf/AbstractMessage;Lcom/google/protobuf/AbstractMessage$BuilderParent;Z)V
      27: putfield      #29                 // Field maxAgeBuilder_:Lcom/google/protobuf/SingleFieldBuilderV3;
      30: aload_0
      31: aconst_null
      32: putfield      #30                 // Field maxAge_:Lcom/google/protobuf/Duration;
      35: aload_0
      36: getfield      #29                 // Field maxAgeBuilder_:Lcom/google/protobuf/SingleFieldBuilderV3;
      39: areturn

  public boolean hasStaleAge();
    Code:
       0: aload_0
       1: getfield      #31                 // Field staleAgeBuilder_:Lcom/google/protobuf/SingleFieldBuilderV3;
       4: ifnonnull     14
       7: aload_0
       8: getfield      #32                 // Field staleAge_:Lcom/google/protobuf/Duration;
      11: ifnull        18
      14: iconst_1
      15: goto          19
      18: iconst_0
      19: ireturn

  public com.google.protobuf.Duration getStaleAge();
    Code:
       0: aload_0
       1: getfield      #31                 // Field staleAgeBuilder_:Lcom/google/protobuf/SingleFieldBuilderV3;
       4: ifnonnull     25
       7: aload_0
       8: getfield      #32                 // Field staleAge_:Lcom/google/protobuf/Duration;
      11: ifnonnull     20
      14: invokestatic  #144                // Method com/google/protobuf/Duration.getDefaultInstance:()Lcom/google/protobuf/Duration;
      17: goto          24
      20: aload_0
      21: getfield      #32                 // Field staleAge_:Lcom/google/protobuf/Duration;
      24: areturn
      25: aload_0
      26: getfield      #31                 // Field staleAgeBuilder_:Lcom/google/protobuf/SingleFieldBuilderV3;
      29: invokevirtual #145                // Method com/google/protobuf/SingleFieldBuilderV3.getMessage:()Lcom/google/protobuf/AbstractMessage;
      32: checkcast     #46                 // class com/google/protobuf/Duration
      35: areturn

  public io.grpc.lookup.v1.RouteLookupConfig$Builder setStaleAge(com.google.protobuf.Duration);
    Code:
       0: aload_0
       1: getfield      #31                 // Field staleAgeBuilder_:Lcom/google/protobuf/SingleFieldBuilderV3;
       4: ifnonnull     31
       7: aload_1
       8: ifnonnull     19
      11: new           #109                // class java/lang/NullPointerException
      14: dup
      15: invokespecial #110                // Method java/lang/NullPointerException."<init>":()V
      18: athrow
      19: aload_0
      20: aload_1
      21: putfield      #32                 // Field staleAge_:Lcom/google/protobuf/Duration;
      24: aload_0
      25: invokevirtual #66                 // Method onChanged:()V
      28: goto          40
      31: aload_0
      32: getfield      #31                 // Field staleAgeBuilder_:Lcom/google/protobuf/SingleFieldBuilderV3;
      35: aload_1
      36: invokevirtual #146                // Method com/google/protobuf/SingleFieldBuilderV3.setMessage:(Lcom/google/protobuf/AbstractMessage;)Lcom/google/protobuf/SingleFieldBuilderV3;
      39: pop
      40: aload_0
      41: areturn

  public io.grpc.lookup.v1.RouteLookupConfig$Builder setStaleAge(com.google.protobuf.Duration$Builder);
    Code:
       0: aload_0
       1: getfield      #31                 // Field staleAgeBuilder_:Lcom/google/protobuf/SingleFieldBuilderV3;
       4: ifnonnull     22
       7: aload_0
       8: aload_1
       9: invokevirtual #147                // Method com/google/protobuf/Duration$Builder.build:()Lcom/google/protobuf/Duration;
      12: putfield      #32                 // Field staleAge_:Lcom/google/protobuf/Duration;
      15: aload_0
      16: invokevirtual #66                 // Method onChanged:()V
      19: goto          34
      22: aload_0
      23: getfield      #31                 // Field staleAgeBuilder_:Lcom/google/protobuf/SingleFieldBuilderV3;
      26: aload_1
      27: invokevirtual #147                // Method com/google/protobuf/Duration$Builder.build:()Lcom/google/protobuf/Duration;
      30: invokevirtual #146                // Method com/google/protobuf/SingleFieldBuilderV3.setMessage:(Lcom/google/protobuf/AbstractMessage;)Lcom/google/protobuf/SingleFieldBuilderV3;
      33: pop
      34: aload_0
      35: areturn

  public io.grpc.lookup.v1.RouteLookupConfig$Builder mergeStaleAge(com.google.protobuf.Duration);
    Code:
       0: aload_0
       1: getfield      #31                 // Field staleAgeBuilder_:Lcom/google/protobuf/SingleFieldBuilderV3;
       4: ifnonnull     47
       7: aload_0
       8: getfield      #32                 // Field staleAge_:Lcom/google/protobuf/Duration;
      11: ifnull        35
      14: aload_0
      15: aload_0
      16: getfield      #32                 // Field staleAge_:Lcom/google/protobuf/Duration;
      19: invokestatic  #148                // Method com/google/protobuf/Duration.newBuilder:(Lcom/google/protobuf/Duration;)Lcom/google/protobuf/Duration$Builder;
      22: aload_1
      23: invokevirtual #149                // Method com/google/protobuf/Duration$Builder.mergeFrom:(Lcom/google/protobuf/Duration;)Lcom/google/protobuf/Duration$Builder;
      26: invokevirtual #150                // Method com/google/protobuf/Duration$Builder.buildPartial:()Lcom/google/protobuf/Duration;
      29: putfield      #32                 // Field staleAge_:Lcom/google/protobuf/Duration;
      32: goto          40
      35: aload_0
      36: aload_1
      37: putfield      #32                 // Field staleAge_:Lcom/google/protobuf/Duration;
      40: aload_0
      41: invokevirtual #66                 // Method onChanged:()V
      44: goto          56
      47: aload_0
      48: getfield      #31                 // Field staleAgeBuilder_:Lcom/google/protobuf/SingleFieldBuilderV3;
      51: aload_1
      52: invokevirtual #151                // Method com/google/protobuf/SingleFieldBuilderV3.mergeFrom:(Lcom/google/protobuf/AbstractMessage;)Lcom/google/protobuf/SingleFieldBuilderV3;
      55: pop
      56: aload_0
      57: areturn

  public io.grpc.lookup.v1.RouteLookupConfig$Builder clearStaleAge();
    Code:
       0: aload_0
       1: getfield      #31                 // Field staleAgeBuilder_:Lcom/google/protobuf/SingleFieldBuilderV3;
       4: ifnonnull     19
       7: aload_0
       8: aconst_null
       9: putfield      #32                 // Field staleAge_:Lcom/google/protobuf/Duration;
      12: aload_0
      13: invokevirtual #66                 // Method onChanged:()V
      16: goto          29
      19: aload_0
      20: aconst_null
      21: putfield      #32                 // Field staleAge_:Lcom/google/protobuf/Duration;
      24: aload_0
      25: aconst_null
      26: putfield      #31                 // Field staleAgeBuilder_:Lcom/google/protobuf/SingleFieldBuilderV3;
      29: aload_0
      30: areturn

  public com.google.protobuf.Duration$Builder getStaleAgeBuilder();
    Code:
       0: aload_0
       1: invokevirtual #66                 // Method onChanged:()V
       4: aload_0
       5: invokespecial #162                // Method getStaleAgeFieldBuilder:()Lcom/google/protobuf/SingleFieldBuilderV3;
       8: invokevirtual #153                // Method com/google/protobuf/SingleFieldBuilderV3.getBuilder:()Lcom/google/protobuf/AbstractMessage$Builder;
      11: checkcast     #154                // class com/google/protobuf/Duration$Builder
      14: areturn

  public com.google.protobuf.DurationOrBuilder getStaleAgeOrBuilder();
    Code:
       0: aload_0
       1: getfield      #31                 // Field staleAgeBuilder_:Lcom/google/protobuf/SingleFieldBuilderV3;
       4: ifnull        18
       7: aload_0
       8: getfield      #31                 // Field staleAgeBuilder_:Lcom/google/protobuf/SingleFieldBuilderV3;
      11: invokevirtual #155                // Method com/google/protobuf/SingleFieldBuilderV3.getMessageOrBuilder:()Lcom/google/protobuf/MessageOrBuilder;
      14: checkcast     #156                // class com/google/protobuf/DurationOrBuilder
      17: areturn
      18: aload_0
      19: getfield      #32                 // Field staleAge_:Lcom/google/protobuf/Duration;
      22: ifnonnull     31
      25: invokestatic  #144                // Method com/google/protobuf/Duration.getDefaultInstance:()Lcom/google/protobuf/Duration;
      28: goto          35
      31: aload_0
      32: getfield      #32                 // Field staleAge_:Lcom/google/protobuf/Duration;
      35: areturn

  private com.google.protobuf.SingleFieldBuilderV3<com.google.protobuf.Duration, com.google.protobuf.Duration$Builder, com.google.protobuf.DurationOrBuilder> getStaleAgeFieldBuilder();
    Code:
       0: aload_0
       1: getfield      #31                 // Field staleAgeBuilder_:Lcom/google/protobuf/SingleFieldBuilderV3;
       4: ifnonnull     35
       7: aload_0
       8: new           #157                // class com/google/protobuf/SingleFieldBuilderV3
      11: dup
      12: aload_0
      13: invokevirtual #163                // Method getStaleAge:()Lcom/google/protobuf/Duration;
      16: aload_0
      17: invokevirtual #131                // Method getParentForChildren:()Lcom/google/protobuf/GeneratedMessageV3$BuilderParent;
      20: aload_0
      21: invokevirtual #132                // Method isClean:()Z
      24: invokespecial #159                // Method com/google/protobuf/SingleFieldBuilderV3."<init>":(Lcom/google/protobuf/AbstractMessage;Lcom/google/protobuf/AbstractMessage$BuilderParent;Z)V
      27: putfield      #31                 // Field staleAgeBuilder_:Lcom/google/protobuf/SingleFieldBuilderV3;
      30: aload_0
      31: aconst_null
      32: putfield      #32                 // Field staleAge_:Lcom/google/protobuf/Duration;
      35: aload_0
      36: getfield      #31                 // Field staleAgeBuilder_:Lcom/google/protobuf/SingleFieldBuilderV3;
      39: areturn

  public long getCacheSizeBytes();
    Code:
       0: aload_0
       1: getfield      #33                 // Field cacheSizeBytes_:J
       4: lreturn

  public io.grpc.lookup.v1.RouteLookupConfig$Builder setCacheSizeBytes(long);
    Code:
       0: aload_0
       1: lload_1
       2: putfield      #33                 // Field cacheSizeBytes_:J
       5: aload_0
       6: invokevirtual #66                 // Method onChanged:()V
       9: aload_0
      10: areturn

  public io.grpc.lookup.v1.RouteLookupConfig$Builder clearCacheSizeBytes();
    Code:
       0: aload_0
       1: lconst_0
       2: putfield      #33                 // Field cacheSizeBytes_:J
       5: aload_0
       6: invokevirtual #66                 // Method onChanged:()V
       9: aload_0
      10: areturn

  private void ensureValidTargetsIsMutable();
    Code:
       0: aload_0
       1: getfield      #24                 // Field bitField0_:I
       4: iconst_4
       5: iand
       6: ifne          34
       9: aload_0
      10: new           #164                // class com/google/protobuf/LazyStringArrayList
      13: dup
      14: aload_0
      15: getfield      #15                 // Field validTargets_:Lcom/google/protobuf/LazyStringList;
      18: invokespecial #165                // Method com/google/protobuf/LazyStringArrayList."<init>":(Lcom/google/protobuf/LazyStringList;)V
      21: putfield      #15                 // Field validTargets_:Lcom/google/protobuf/LazyStringList;
      24: aload_0
      25: dup
      26: getfield      #24                 // Field bitField0_:I
      29: iconst_4
      30: ior
      31: putfield      #24                 // Field bitField0_:I
      34: return

  public com.google.protobuf.ProtocolStringList getValidTargetsList();
    Code:
       0: aload_0
       1: getfield      #15                 // Field validTargets_:Lcom/google/protobuf/LazyStringList;
       4: invokeinterface #50,  1           // InterfaceMethod com/google/protobuf/LazyStringList.getUnmodifiableView:()Lcom/google/protobuf/LazyStringList;
       9: areturn

  public int getValidTargetsCount();
    Code:
       0: aload_0
       1: getfield      #15                 // Field validTargets_:Lcom/google/protobuf/LazyStringList;
       4: invokeinterface #166,  1          // InterfaceMethod com/google/protobuf/LazyStringList.size:()I
       9: ireturn

  public java.lang.String getValidTargets(int);
    Code:
       0: aload_0
       1: getfield      #15                 // Field validTargets_:Lcom/google/protobuf/LazyStringList;
       4: iload_1
       5: invokeinterface #167,  2          // InterfaceMethod com/google/protobuf/LazyStringList.get:(I)Ljava/lang/Object;
      10: checkcast     #139                // class java/lang/String
      13: areturn

  public com.google.protobuf.ByteString getValidTargetsBytes(int);
    Code:
       0: aload_0
       1: getfield      #15                 // Field validTargets_:Lcom/google/protobuf/LazyStringList;
       4: iload_1
       5: invokeinterface #168,  2          // InterfaceMethod com/google/protobuf/LazyStringList.getByteString:(I)Lcom/google/protobuf/ByteString;
      10: areturn

  public io.grpc.lookup.v1.RouteLookupConfig$Builder setValidTargets(int, java.lang.String);
    Code:
       0: aload_2
       1: ifnonnull     12
       4: new           #109                // class java/lang/NullPointerException
       7: dup
       8: invokespecial #110                // Method java/lang/NullPointerException."<init>":()V
      11: athrow
      12: aload_0
      13: invokespecial #90                 // Method ensureValidTargetsIsMutable:()V
      16: aload_0
      17: getfield      #15                 // Field validTargets_:Lcom/google/protobuf/LazyStringList;
      20: iload_1
      21: aload_2
      22: invokeinterface #169,  3          // InterfaceMethod com/google/protobuf/LazyStringList.set:(ILjava/lang/Object;)Ljava/lang/Object;
      27: pop
      28: aload_0
      29: invokevirtual #66                 // Method onChanged:()V
      32: aload_0
      33: areturn

  public io.grpc.lookup.v1.RouteLookupConfig$Builder addValidTargets(java.lang.String);
    Code:
       0: aload_1
       1: ifnonnull     12
       4: new           #109                // class java/lang/NullPointerException
       7: dup
       8: invokespecial #110                // Method java/lang/NullPointerException."<init>":()V
      11: athrow
      12: aload_0
      13: invokespecial #90                 // Method ensureValidTargetsIsMutable:()V
      16: aload_0
      17: getfield      #15                 // Field validTargets_:Lcom/google/protobuf/LazyStringList;
      20: aload_1
      21: invokeinterface #170,  2          // InterfaceMethod com/google/protobuf/LazyStringList.add:(Ljava/lang/Object;)Z
      26: pop
      27: aload_0
      28: invokevirtual #66                 // Method onChanged:()V
      31: aload_0
      32: areturn

  public io.grpc.lookup.v1.RouteLookupConfig$Builder addAllValidTargets(java.lang.Iterable<java.lang.String>);
    Code:
       0: aload_0
       1: invokespecial #90                 // Method ensureValidTargetsIsMutable:()V
       4: aload_1
       5: aload_0
       6: getfield      #15                 // Field validTargets_:Lcom/google/protobuf/LazyStringList;
       9: invokestatic  #118                // Method com/google/protobuf/AbstractMessageLite$Builder.addAll:(Ljava/lang/Iterable;Ljava/util/List;)V
      12: aload_0
      13: invokevirtual #66                 // Method onChanged:()V
      16: aload_0
      17: areturn

  public io.grpc.lookup.v1.RouteLookupConfig$Builder clearValidTargets();
    Code:
       0: aload_0
       1: getstatic     #14                 // Field com/google/protobuf/LazyStringArrayList.EMPTY:Lcom/google/protobuf/LazyStringList;
       4: putfield      #15                 // Field validTargets_:Lcom/google/protobuf/LazyStringList;
       7: aload_0
       8: aload_0
       9: getfield      #24                 // Field bitField0_:I
      12: bipush        -5
      14: iand
      15: putfield      #24                 // Field bitField0_:I
      18: aload_0
      19: invokevirtual #66                 // Method onChanged:()V
      22: aload_0
      23: areturn

  public io.grpc.lookup.v1.RouteLookupConfig$Builder addValidTargetsBytes(com.google.protobuf.ByteString);
    Code:
       0: aload_1
       1: ifnonnull     12
       4: new           #109                // class java/lang/NullPointerException
       7: dup
       8: invokespecial #110                // Method java/lang/NullPointerException."<init>":()V
      11: athrow
      12: aload_1
      13: invokestatic  #171                // Method io/grpc/lookup/v1/RouteLookupConfig.access$1800:(Lcom/google/protobuf/ByteString;)V
      16: aload_0
      17: invokespecial #90                 // Method ensureValidTargetsIsMutable:()V
      20: aload_0
      21: getfield      #15                 // Field validTargets_:Lcom/google/protobuf/LazyStringList;
      24: aload_1
      25: invokeinterface #172,  2          // InterfaceMethod com/google/protobuf/LazyStringList.add:(Lcom/google/protobuf/ByteString;)V
      30: aload_0
      31: invokevirtual #66                 // Method onChanged:()V
      34: aload_0
      35: areturn

  public java.lang.String getDefaultTarget();
    Code:
       0: aload_0
       1: getfield      #16                 // Field defaultTarget_:Ljava/lang/Object;
       4: astore_1
       5: aload_1
       6: instanceof    #139                // class java/lang/String
       9: ifne          29
      12: aload_1
      13: checkcast     #140                // class com/google/protobuf/ByteString
      16: astore_2
      17: aload_2
      18: invokevirtual #141                // Method com/google/protobuf/ByteString.toStringUtf8:()Ljava/lang/String;
      21: astore_3
      22: aload_0
      23: aload_3
      24: putfield      #16                 // Field defaultTarget_:Ljava/lang/Object;
      27: aload_3
      28: areturn
      29: aload_1
      30: checkcast     #139                // class java/lang/String
      33: areturn

  public com.google.protobuf.ByteString getDefaultTargetBytes();
    Code:
       0: aload_0
       1: getfield      #16                 // Field defaultTarget_:Ljava/lang/Object;
       4: astore_1
       5: aload_1
       6: instanceof    #139                // class java/lang/String
       9: ifeq          27
      12: aload_1
      13: checkcast     #139                // class java/lang/String
      16: invokestatic  #142                // Method com/google/protobuf/ByteString.copyFromUtf8:(Ljava/lang/String;)Lcom/google/protobuf/ByteString;
      19: astore_2
      20: aload_0
      21: aload_2
      22: putfield      #16                 // Field defaultTarget_:Ljava/lang/Object;
      25: aload_2
      26: areturn
      27: aload_1
      28: checkcast     #140                // class com/google/protobuf/ByteString
      31: areturn

  public io.grpc.lookup.v1.RouteLookupConfig$Builder setDefaultTarget(java.lang.String);
    Code:
       0: aload_1
       1: ifnonnull     12
       4: new           #109                // class java/lang/NullPointerException
       7: dup
       8: invokespecial #110                // Method java/lang/NullPointerException."<init>":()V
      11: athrow
      12: aload_0
      13: aload_1
      14: putfield      #16                 // Field defaultTarget_:Ljava/lang/Object;
      17: aload_0
      18: invokevirtual #66                 // Method onChanged:()V
      21: aload_0
      22: areturn

  public io.grpc.lookup.v1.RouteLookupConfig$Builder clearDefaultTarget();
    Code:
       0: aload_0
       1: invokestatic  #34                 // Method io/grpc/lookup/v1/RouteLookupConfig.getDefaultInstance:()Lio/grpc/lookup/v1/RouteLookupConfig;
       4: invokevirtual #92                 // Method io/grpc/lookup/v1/RouteLookupConfig.getDefaultTarget:()Ljava/lang/String;
       7: putfield      #16                 // Field defaultTarget_:Ljava/lang/Object;
      10: aload_0
      11: invokevirtual #66                 // Method onChanged:()V
      14: aload_0
      15: areturn

  public io.grpc.lookup.v1.RouteLookupConfig$Builder setDefaultTargetBytes(com.google.protobuf.ByteString);
    Code:
       0: aload_1
       1: ifnonnull     12
       4: new           #109                // class java/lang/NullPointerException
       7: dup
       8: invokespecial #110                // Method java/lang/NullPointerException."<init>":()V
      11: athrow
      12: aload_1
      13: invokestatic  #173                // Method io/grpc/lookup/v1/RouteLookupConfig.access$1900:(Lcom/google/protobuf/ByteString;)V
      16: aload_0
      17: aload_1
      18: putfield      #16                 // Field defaultTarget_:Ljava/lang/Object;
      21: aload_0
      22: invokevirtual #66                 // Method onChanged:()V
      25: aload_0
      26: areturn

  public final io.grpc.lookup.v1.RouteLookupConfig$Builder setUnknownFields(com.google.protobuf.UnknownFieldSet);
    Code:
       0: aload_0
       1: aload_1
       2: invokespecial #174                // Method com/google/protobuf/GeneratedMessageV3$Builder.setUnknownFields:(Lcom/google/protobuf/UnknownFieldSet;)Lcom/google/protobuf/GeneratedMessageV3$Builder;
       5: checkcast     #6                  // class io/grpc/lookup/v1/RouteLookupConfig$Builder
       8: areturn

  public final io.grpc.lookup.v1.RouteLookupConfig$Builder mergeUnknownFields(com.google.protobuf.UnknownFieldSet);
    Code:
       0: aload_0
       1: aload_1
       2: invokespecial #175                // Method com/google/protobuf/GeneratedMessageV3$Builder.mergeUnknownFields:(Lcom/google/protobuf/UnknownFieldSet;)Lcom/google/protobuf/GeneratedMessageV3$Builder;
       5: checkcast     #6                  // class io/grpc/lookup/v1/RouteLookupConfig$Builder
       8: areturn

  public com.google.protobuf.GeneratedMessageV3$Builder mergeUnknownFields(com.google.protobuf.UnknownFieldSet);
    Code:
       0: aload_0
       1: aload_1
       2: invokevirtual #95                 // Method mergeUnknownFields:(Lcom/google/protobuf/UnknownFieldSet;)Lio/grpc/lookup/v1/RouteLookupConfig$Builder;
       5: areturn

  public com.google.protobuf.GeneratedMessageV3$Builder setUnknownFields(com.google.protobuf.UnknownFieldSet);
    Code:
       0: aload_0
       1: aload_1
       2: invokevirtual #176                // Method setUnknownFields:(Lcom/google/protobuf/UnknownFieldSet;)Lio/grpc/lookup/v1/RouteLookupConfig$Builder;
       5: areturn

  public com.google.protobuf.GeneratedMessageV3$Builder addRepeatedField(com.google.protobuf.Descriptors$FieldDescriptor, java.lang.Object);
    Code:
       0: aload_0
       1: aload_1
       2: aload_2
       3: invokevirtual #177                // Method addRepeatedField:(Lcom/google/protobuf/Descriptors$FieldDescriptor;Ljava/lang/Object;)Lio/grpc/lookup/v1/RouteLookupConfig$Builder;
       6: areturn

  public com.google.protobuf.GeneratedMessageV3$Builder setRepeatedField(com.google.protobuf.Descriptors$FieldDescriptor, int, java.lang.Object);
    Code:
       0: aload_0
       1: aload_1
       2: iload_2
       3: aload_3
       4: invokevirtual #178                // Method setRepeatedField:(Lcom/google/protobuf/Descriptors$FieldDescriptor;ILjava/lang/Object;)Lio/grpc/lookup/v1/RouteLookupConfig$Builder;
       7: areturn

  public com.google.protobuf.GeneratedMessageV3$Builder clearOneof(com.google.protobuf.Descriptors$OneofDescriptor);
    Code:
       0: aload_0
       1: aload_1
       2: invokevirtual #179                // Method clearOneof:(Lcom/google/protobuf/Descriptors$OneofDescriptor;)Lio/grpc/lookup/v1/RouteLookupConfig$Builder;
       5: areturn

  public com.google.protobuf.GeneratedMessageV3$Builder clearField(com.google.protobuf.Descriptors$FieldDescriptor);
    Code:
       0: aload_0
       1: aload_1
       2: invokevirtual #180                // Method clearField:(Lcom/google/protobuf/Descriptors$FieldDescriptor;)Lio/grpc/lookup/v1/RouteLookupConfig$Builder;
       5: areturn

  public com.google.protobuf.GeneratedMessageV3$Builder setField(com.google.protobuf.Descriptors$FieldDescriptor, java.lang.Object);
    Code:
       0: aload_0
       1: aload_1
       2: aload_2
       3: invokevirtual #181                // Method setField:(Lcom/google/protobuf/Descriptors$FieldDescriptor;Ljava/lang/Object;)Lio/grpc/lookup/v1/RouteLookupConfig$Builder;
       6: areturn

  public com.google.protobuf.GeneratedMessageV3$Builder clear();
    Code:
       0: aload_0
       1: invokevirtual #182                // Method clear:()Lio/grpc/lookup/v1/RouteLookupConfig$Builder;
       4: areturn

  public com.google.protobuf.GeneratedMessageV3$Builder clone();
    Code:
       0: aload_0
       1: invokevirtual #183                // Method clone:()Lio/grpc/lookup/v1/RouteLookupConfig$Builder;
       4: areturn

  public com.google.protobuf.AbstractMessage$Builder mergeUnknownFields(com.google.protobuf.UnknownFieldSet);
    Code:
       0: aload_0
       1: aload_1
       2: invokevirtual #95                 // Method mergeUnknownFields:(Lcom/google/protobuf/UnknownFieldSet;)Lio/grpc/lookup/v1/RouteLookupConfig$Builder;
       5: areturn

  public com.google.protobuf.AbstractMessage$Builder mergeFrom(com.google.protobuf.CodedInputStream, com.google.protobuf.ExtensionRegistryLite) throws java.io.IOException;
    Code:
       0: aload_0
       1: aload_1
       2: aload_2
       3: invokevirtual #184                // Method mergeFrom:(Lcom/google/protobuf/CodedInputStream;Lcom/google/protobuf/ExtensionRegistryLite;)Lio/grpc/lookup/v1/RouteLookupConfig$Builder;
       6: areturn

  public com.google.protobuf.AbstractMessage$Builder mergeFrom(com.google.protobuf.Message);
    Code:
       0: aload_0
       1: aload_1
       2: invokevirtual #185                // Method mergeFrom:(Lcom/google/protobuf/Message;)Lio/grpc/lookup/v1/RouteLookupConfig$Builder;
       5: areturn

  public com.google.protobuf.AbstractMessage$Builder clear();
    Code:
       0: aload_0
       1: invokevirtual #182                // Method clear:()Lio/grpc/lookup/v1/RouteLookupConfig$Builder;
       4: areturn

  public com.google.protobuf.AbstractMessage$Builder clearOneof(com.google.protobuf.Descriptors$OneofDescriptor);
    Code:
       0: aload_0
       1: aload_1
       2: invokevirtual #179                // Method clearOneof:(Lcom/google/protobuf/Descriptors$OneofDescriptor;)Lio/grpc/lookup/v1/RouteLookupConfig$Builder;
       5: areturn

  public com.google.protobuf.AbstractMessage$Builder clone();
    Code:
       0: aload_0
       1: invokevirtual #183                // Method clone:()Lio/grpc/lookup/v1/RouteLookupConfig$Builder;
       4: areturn

  public com.google.protobuf.Message$Builder mergeUnknownFields(com.google.protobuf.UnknownFieldSet);
    Code:
       0: aload_0
       1: aload_1
       2: invokevirtual #95                 // Method mergeUnknownFields:(Lcom/google/protobuf/UnknownFieldSet;)Lio/grpc/lookup/v1/RouteLookupConfig$Builder;
       5: areturn

  public com.google.protobuf.Message$Builder setUnknownFields(com.google.protobuf.UnknownFieldSet);
    Code:
       0: aload_0
       1: aload_1
       2: invokevirtual #176                // Method setUnknownFields:(Lcom/google/protobuf/UnknownFieldSet;)Lio/grpc/lookup/v1/RouteLookupConfig$Builder;
       5: areturn

  public com.google.protobuf.Message$Builder addRepeatedField(com.google.protobuf.Descriptors$FieldDescriptor, java.lang.Object);
    Code:
       0: aload_0
       1: aload_1
       2: aload_2
       3: invokevirtual #177                // Method addRepeatedField:(Lcom/google/protobuf/Descriptors$FieldDescriptor;Ljava/lang/Object;)Lio/grpc/lookup/v1/RouteLookupConfig$Builder;
       6: areturn

  public com.google.protobuf.Message$Builder setRepeatedField(com.google.protobuf.Descriptors$FieldDescriptor, int, java.lang.Object);
    Code:
       0: aload_0
       1: aload_1
       2: iload_2
       3: aload_3
       4: invokevirtual #178                // Method setRepeatedField:(Lcom/google/protobuf/Descriptors$FieldDescriptor;ILjava/lang/Object;)Lio/grpc/lookup/v1/RouteLookupConfig$Builder;
       7: areturn

  public com.google.protobuf.Message$Builder clearOneof(com.google.protobuf.Descriptors$OneofDescriptor);
    Code:
       0: aload_0
       1: aload_1
       2: invokevirtual #179                // Method clearOneof:(Lcom/google/protobuf/Descriptors$OneofDescriptor;)Lio/grpc/lookup/v1/RouteLookupConfig$Builder;
       5: areturn

  public com.google.protobuf.Message$Builder clearField(com.google.protobuf.Descriptors$FieldDescriptor);
    Code:
       0: aload_0
       1: aload_1
       2: invokevirtual #180                // Method clearField:(Lcom/google/protobuf/Descriptors$FieldDescriptor;)Lio/grpc/lookup/v1/RouteLookupConfig$Builder;
       5: areturn

  public com.google.protobuf.Message$Builder setField(com.google.protobuf.Descriptors$FieldDescriptor, java.lang.Object);
    Code:
       0: aload_0
       1: aload_1
       2: aload_2
       3: invokevirtual #181                // Method setField:(Lcom/google/protobuf/Descriptors$FieldDescriptor;Ljava/lang/Object;)Lio/grpc/lookup/v1/RouteLookupConfig$Builder;
       6: areturn

  public com.google.protobuf.Message$Builder mergeFrom(com.google.protobuf.CodedInputStream, com.google.protobuf.ExtensionRegistryLite) throws java.io.IOException;
    Code:
       0: aload_0
       1: aload_1
       2: aload_2
       3: invokevirtual #184                // Method mergeFrom:(Lcom/google/protobuf/CodedInputStream;Lcom/google/protobuf/ExtensionRegistryLite;)Lio/grpc/lookup/v1/RouteLookupConfig$Builder;
       6: areturn

  public com.google.protobuf.Message$Builder clone();
    Code:
       0: aload_0
       1: invokevirtual #183                // Method clone:()Lio/grpc/lookup/v1/RouteLookupConfig$Builder;
       4: areturn

  public com.google.protobuf.Message buildPartial();
    Code:
       0: aload_0
       1: invokevirtual #35                 // Method buildPartial:()Lio/grpc/lookup/v1/RouteLookupConfig;
       4: areturn

  public com.google.protobuf.Message build();
    Code:
       0: aload_0
       1: invokevirtual #186                // Method build:()Lio/grpc/lookup/v1/RouteLookupConfig;
       4: areturn

  public com.google.protobuf.Message$Builder mergeFrom(com.google.protobuf.Message);
    Code:
       0: aload_0
       1: aload_1
       2: invokevirtual #185                // Method mergeFrom:(Lcom/google/protobuf/Message;)Lio/grpc/lookup/v1/RouteLookupConfig$Builder;
       5: areturn

  public com.google.protobuf.Message$Builder clear();
    Code:
       0: aload_0
       1: invokevirtual #182                // Method clear:()Lio/grpc/lookup/v1/RouteLookupConfig$Builder;
       4: areturn

  public com.google.protobuf.MessageLite$Builder mergeFrom(com.google.protobuf.CodedInputStream, com.google.protobuf.ExtensionRegistryLite) throws java.io.IOException;
    Code:
       0: aload_0
       1: aload_1
       2: aload_2
       3: invokevirtual #184                // Method mergeFrom:(Lcom/google/protobuf/CodedInputStream;Lcom/google/protobuf/ExtensionRegistryLite;)Lio/grpc/lookup/v1/RouteLookupConfig$Builder;
       6: areturn

  public com.google.protobuf.MessageLite$Builder clone();
    Code:
       0: aload_0
       1: invokevirtual #183                // Method clone:()Lio/grpc/lookup/v1/RouteLookupConfig$Builder;
       4: areturn

  public com.google.protobuf.MessageLite buildPartial();
    Code:
       0: aload_0
       1: invokevirtual #35                 // Method buildPartial:()Lio/grpc/lookup/v1/RouteLookupConfig;
       4: areturn

  public com.google.protobuf.MessageLite build();
    Code:
       0: aload_0
       1: invokevirtual #186                // Method build:()Lio/grpc/lookup/v1/RouteLookupConfig;
       4: areturn

  public com.google.protobuf.MessageLite$Builder clear();
    Code:
       0: aload_0
       1: invokevirtual #182                // Method clear:()Lio/grpc/lookup/v1/RouteLookupConfig$Builder;
       4: areturn

  public com.google.protobuf.MessageLite getDefaultInstanceForType();
    Code:
       0: aload_0
       1: invokevirtual #187                // Method getDefaultInstanceForType:()Lio/grpc/lookup/v1/RouteLookupConfig;
       4: areturn

  public com.google.protobuf.Message getDefaultInstanceForType();
    Code:
       0: aload_0
       1: invokevirtual #187                // Method getDefaultInstanceForType:()Lio/grpc/lookup/v1/RouteLookupConfig;
       4: areturn

  public com.google.protobuf.AbstractMessageLite$Builder mergeFrom(com.google.protobuf.CodedInputStream, com.google.protobuf.ExtensionRegistryLite) throws java.io.IOException;
    Code:
       0: aload_0
       1: aload_1
       2: aload_2
       3: invokevirtual #184                // Method mergeFrom:(Lcom/google/protobuf/CodedInputStream;Lcom/google/protobuf/ExtensionRegistryLite;)Lio/grpc/lookup/v1/RouteLookupConfig$Builder;
       6: areturn

  public com.google.protobuf.AbstractMessageLite$Builder clone();
    Code:
       0: aload_0
       1: invokevirtual #183                // Method clone:()Lio/grpc/lookup/v1/RouteLookupConfig$Builder;
       4: areturn

  public java.lang.Object clone() throws java.lang.CloneNotSupportedException;
    Code:
       0: aload_0
       1: invokevirtual #183                // Method clone:()Lio/grpc/lookup/v1/RouteLookupConfig$Builder;
       4: areturn

  public java.util.List getValidTargetsList();
    Code:
       0: aload_0
       1: invokevirtual #188                // Method getValidTargetsList:()Lcom/google/protobuf/ProtocolStringList;
       4: areturn

  io.grpc.lookup.v1.RouteLookupConfig$Builder(io.grpc.lookup.v1.RouteLookupConfig$1);
    Code:
       0: aload_0
       1: invokespecial #2                  // Method "<init>":()V
       4: return

  io.grpc.lookup.v1.RouteLookupConfig$Builder(com.google.protobuf.GeneratedMessageV3$BuilderParent, io.grpc.lookup.v1.RouteLookupConfig$1);
    Code:
       0: aload_0
       1: aload_1
       2: invokespecial #1                  // Method "<init>":(Lcom/google/protobuf/GeneratedMessageV3$BuilderParent;)V
       5: return
}
