Compiled from "SignatureDependentSelectionPreviewPanel.java"
class org.protege.editor.owl.ui.ontology.wizard.move.common.SignatureDependentSelectionPreviewPanel$1 implements org.protege.editor.core.ui.util.CheckList$CheckListListener {
  final org.protege.editor.owl.ui.ontology.wizard.move.common.SignatureDependentSelectionPreviewPanel this$0;

  org.protege.editor.owl.ui.ontology.wizard.move.common.SignatureDependentSelectionPreviewPanel$1(org.protege.editor.owl.ui.ontology.wizard.move.common.SignatureDependentSelectionPreviewPanel);
    Code:
       0: aload_0
       1: aload_1
       2: putfield      #1                  // Field this$0:Lorg/protege/editor/owl/ui/ontology/wizard/move/common/SignatureDependentSelectionPreviewPanel;
       5: aload_0
       6: invokespecial #2                  // Method java/lang/Object."<init>":()V
       9: return

  public void itemChecked(java.lang.Object);
    Code:
       0: aload_0
       1: getfield      #1                  // Field this$0:Lorg/protege/editor/owl/ui/ontology/wizard/move/common/SignatureDependentSelectionPreviewPanel;
       4: invokevirtual #3                  // Method org/protege/editor/owl/ui/ontology/wizard/move/common/SignatureDependentSelectionPreviewPanel.updatePreview:()V
       7: return

  public void itemUnchecked(java.lang.Object);
    Code:
       0: aload_0
       1: getfield      #1                  // Field this$0:Lorg/protege/editor/owl/ui/ontology/wizard/move/common/SignatureDependentSelectionPreviewPanel;
       4: invokevirtual #3                  // Method org/protege/editor/owl/ui/ontology/wizard/move/common/SignatureDependentSelectionPreviewPanel.updatePreview:()V
       7: return
}
