Compiled from "UnsupportedKeyTypeException.java"
public class org.infinispan.persistence.keymappers.UnsupportedKeyTypeException extends org.infinispan.persistence.spi.PersistenceException {
  private static final long serialVersionUID;

  public org.infinispan.persistence.keymappers.UnsupportedKeyTypeException(java.lang.Object);
    Code:
       0: aload_0
       1: new           #1                  // class java/lang/StringBuilder
       4: dup
       5: invokespecial #2                  // Method java/lang/StringBuilder."<init>":()V
       8: ldc           #3                  // String Unsupported key type: \'
      10: invokevirtual #4                  // Method java/lang/StringBuilder.append:(Ljava/lang/String;)Ljava/lang/StringBuilder;
      13: aload_1
      14: invokevirtual #5                  // Method java/lang/Object.getClass:()Ljava/lang/Class;
      17: invokevirtual #6                  // Method java/lang/Class.getName:()Ljava/lang/String;
      20: invokevirtual #4                  // Method java/lang/StringBuilder.append:(Ljava/lang/String;)Ljava/lang/StringBuilder;
      23: ldc           #7                  // String \' on key:
      25: invokevirtual #4                  // Method java/lang/StringBuilder.append:(Ljava/lang/String;)Ljava/lang/StringBuilder;
      28: aload_1
      29: invokevirtual #8                  // Method java/lang/StringBuilder.append:(Ljava/lang/Object;)Ljava/lang/StringBuilder;
      32: invokevirtual #9                  // Method java/lang/StringBuilder.toString:()Ljava/lang/String;
      35: invokespecial #10                 // Method "<init>":(Ljava/lang/String;)V
      38: return

  public org.infinispan.persistence.keymappers.UnsupportedKeyTypeException(java.lang.String);
    Code:
       0: aload_0
       1: aload_1
       2: invokespecial #11                 // Method org/infinispan/persistence/spi/PersistenceException."<init>":(Ljava/lang/String;)V
       5: return

  public org.infinispan.persistence.keymappers.UnsupportedKeyTypeException(java.lang.String, java.lang.Throwable);
    Code:
       0: aload_0
       1: aload_1
       2: aload_2
       3: invokespecial #12                 // Method org/infinispan/persistence/spi/PersistenceException."<init>":(Ljava/lang/String;Ljava/lang/Throwable;)V
       6: return

  public org.infinispan.persistence.keymappers.UnsupportedKeyTypeException(java.lang.Throwable);
    Code:
       0: aload_0
       1: aload_1
       2: invokespecial #13                 // Method org/infinispan/persistence/spi/PersistenceException."<init>":(Ljava/lang/Throwable;)V
       5: return
}
