Compiled from "JAXPDOMAdapter.java"
public class org.jdom.adapters.JAXPDOMAdapter extends org.jdom.adapters.AbstractDOMAdapter {
  private static final java.lang.String CVS_ID;

  static java.lang.Class class$org$xml$sax$ErrorHandler;

  static java.lang.Class class$java$io$InputStream;

  public org.jdom.adapters.JAXPDOMAdapter();
    Code:
       0: aload_0
       1: invokespecial #6                  // Method org/jdom/adapters/AbstractDOMAdapter."<init>":()V
       4: return

  public org.w3c.dom.Document getDocument(java.io.InputStream, boolean) throws java.io.IOException, org.jdom.JDOMException;
    Code:
       0: ldc           #7                  // String javax.xml.transform.Transformer
       2: invokestatic  #1                  // Method java/lang/Class.forName:(Ljava/lang/String;)Ljava/lang/Class;
       5: pop
       6: ldc           #8                  // String javax.xml.parsers.DocumentBuilderFactory
       8: invokestatic  #1                  // Method java/lang/Class.forName:(Ljava/lang/String;)Ljava/lang/Class;
      11: astore_3
      12: aload_3
      13: ldc           #9                  // String newInstance
      15: aconst_null
      16: invokevirtual #10                 // Method java/lang/Class.getMethod:(Ljava/lang/String;[Ljava/lang/Class;)Ljava/lang/reflect/Method;
      19: astore        4
      21: aload         4
      23: aconst_null
      24: aconst_null
      25: invokevirtual #11                 // Method java/lang/reflect/Method.invoke:(Ljava/lang/Object;[Ljava/lang/Object;)Ljava/lang/Object;
      28: astore        5
      30: aload_3
      31: ldc           #12                 // String setValidating
      33: iconst_1
      34: anewarray     #13                 // class java/lang/Class
      37: dup
      38: iconst_0
      39: getstatic     #14                 // Field java/lang/Boolean.TYPE:Ljava/lang/Class;
      42: aastore
      43: invokevirtual #10                 // Method java/lang/Class.getMethod:(Ljava/lang/String;[Ljava/lang/Class;)Ljava/lang/reflect/Method;
      46: astore        6
      48: aload         6
      50: aload         5
      52: iconst_1
      53: anewarray     #15                 // class java/lang/Object
      56: dup
      57: iconst_0
      58: new           #16                 // class java/lang/Boolean
      61: dup
      62: iload_2
      63: invokespecial #17                 // Method java/lang/Boolean."<init>":(Z)V
      66: aastore
      67: invokevirtual #11                 // Method java/lang/reflect/Method.invoke:(Ljava/lang/Object;[Ljava/lang/Object;)Ljava/lang/Object;
      70: pop
      71: aload_3
      72: ldc           #18                 // String setNamespaceAware
      74: iconst_1
      75: anewarray     #13                 // class java/lang/Class
      78: dup
      79: iconst_0
      80: getstatic     #14                 // Field java/lang/Boolean.TYPE:Ljava/lang/Class;
      83: aastore
      84: invokevirtual #10                 // Method java/lang/Class.getMethod:(Ljava/lang/String;[Ljava/lang/Class;)Ljava/lang/reflect/Method;
      87: astore        7
      89: aload         7
      91: aload         5
      93: iconst_1
      94: anewarray     #15                 // class java/lang/Object
      97: dup
      98: iconst_0
      99: getstatic     #19                 // Field java/lang/Boolean.TRUE:Ljava/lang/Boolean;
     102: aastore
     103: invokevirtual #11                 // Method java/lang/reflect/Method.invoke:(Ljava/lang/Object;[Ljava/lang/Object;)Ljava/lang/Object;
     106: pop
     107: aload_3
     108: ldc           #20                 // String newDocumentBuilder
     110: aconst_null
     111: invokevirtual #10                 // Method java/lang/Class.getMethod:(Ljava/lang/String;[Ljava/lang/Class;)Ljava/lang/reflect/Method;
     114: astore        8
     116: aload         8
     118: aload         5
     120: aconst_null
     121: invokevirtual #11                 // Method java/lang/reflect/Method.invoke:(Ljava/lang/Object;[Ljava/lang/Object;)Ljava/lang/Object;
     124: astore        9
     126: aload         9
     128: invokevirtual #21                 // Method java/lang/Object.getClass:()Ljava/lang/Class;
     131: astore        10
     133: aload         10
     135: ldc           #22                 // String setErrorHandler
     137: iconst_1
     138: anewarray     #13                 // class java/lang/Class
     141: dup
     142: iconst_0
     143: getstatic     #23                 // Field class$org$xml$sax$ErrorHandler:Ljava/lang/Class;
     146: ifnonnull     161
     149: ldc           #24                 // String org.xml.sax.ErrorHandler
     151: invokestatic  #25                 // Method class$:(Ljava/lang/String;)Ljava/lang/Class;
     154: dup
     155: putstatic     #23                 // Field class$org$xml$sax$ErrorHandler:Ljava/lang/Class;
     158: goto          164
     161: getstatic     #23                 // Field class$org$xml$sax$ErrorHandler:Ljava/lang/Class;
     164: aastore
     165: invokevirtual #10                 // Method java/lang/Class.getMethod:(Ljava/lang/String;[Ljava/lang/Class;)Ljava/lang/reflect/Method;
     168: astore        11
     170: aload         11
     172: aload         9
     174: iconst_1
     175: anewarray     #15                 // class java/lang/Object
     178: dup
     179: iconst_0
     180: new           #26                 // class org/jdom/input/BuilderErrorHandler
     183: dup
     184: invokespecial #27                 // Method org/jdom/input/BuilderErrorHandler."<init>":()V
     187: aastore
     188: invokevirtual #11                 // Method java/lang/reflect/Method.invoke:(Ljava/lang/Object;[Ljava/lang/Object;)Ljava/lang/Object;
     191: pop
     192: aload         10
     194: ldc           #28                 // String parse
     196: iconst_1
     197: anewarray     #13                 // class java/lang/Class
     200: dup
     201: iconst_0
     202: getstatic     #29                 // Field class$java$io$InputStream:Ljava/lang/Class;
     205: ifnonnull     220
     208: ldc           #30                 // String java.io.InputStream
     210: invokestatic  #25                 // Method class$:(Ljava/lang/String;)Ljava/lang/Class;
     213: dup
     214: putstatic     #29                 // Field class$java$io$InputStream:Ljava/lang/Class;
     217: goto          223
     220: getstatic     #29                 // Field class$java$io$InputStream:Ljava/lang/Class;
     223: aastore
     224: invokevirtual #10                 // Method java/lang/Class.getMethod:(Ljava/lang/String;[Ljava/lang/Class;)Ljava/lang/reflect/Method;
     227: astore        12
     229: aload         12
     231: aload         9
     233: iconst_1
     234: anewarray     #15                 // class java/lang/Object
     237: dup
     238: iconst_0
     239: aload_1
     240: aastore
     241: invokevirtual #11                 // Method java/lang/reflect/Method.invoke:(Ljava/lang/Object;[Ljava/lang/Object;)Ljava/lang/Object;
     244: checkcast     #31                 // class org/w3c/dom/Document
     247: astore        13
     249: aload         13
     251: areturn
     252: astore_3
     253: aload_3
     254: invokevirtual #33                 // Method java/lang/reflect/InvocationTargetException.getTargetException:()Ljava/lang/Throwable;
     257: astore        4
     259: aload         4
     261: instanceof    #34                 // class java/io/IOException
     264: ifeq          273
     267: aload         4
     269: checkcast     #34                 // class java/io/IOException
     272: athrow
     273: new           #35                 // class org/jdom/JDOMException
     276: dup
     277: aload         4
     279: invokevirtual #36                 // Method java/lang/Throwable.getMessage:()Ljava/lang/String;
     282: aload         4
     284: invokespecial #37                 // Method org/jdom/JDOMException."<init>":(Ljava/lang/String;Ljava/lang/Throwable;)V
     287: athrow
     288: astore_3
     289: new           #35                 // class org/jdom/JDOMException
     292: dup
     293: ldc           #39                 // String Reflection failed while parsing a document with JAXP
     295: aload_3
     296: invokespecial #37                 // Method org/jdom/JDOMException."<init>":(Ljava/lang/String;Ljava/lang/Throwable;)V
     299: athrow
    Exception table:
       from    to  target type
           0   251   252   Class java/lang/reflect/InvocationTargetException
           0   251   288   Class java/lang/Exception

  public org.w3c.dom.Document createDocument() throws org.jdom.JDOMException;
    Code:
       0: ldc           #7                  // String javax.xml.transform.Transformer
       2: invokestatic  #1                  // Method java/lang/Class.forName:(Ljava/lang/String;)Ljava/lang/Class;
       5: pop
       6: ldc           #8                  // String javax.xml.parsers.DocumentBuilderFactory
       8: invokestatic  #1                  // Method java/lang/Class.forName:(Ljava/lang/String;)Ljava/lang/Class;
      11: astore_1
      12: aload_1
      13: ldc           #9                  // String newInstance
      15: aconst_null
      16: invokevirtual #10                 // Method java/lang/Class.getMethod:(Ljava/lang/String;[Ljava/lang/Class;)Ljava/lang/reflect/Method;
      19: astore_2
      20: aload_2
      21: aconst_null
      22: aconst_null
      23: invokevirtual #11                 // Method java/lang/reflect/Method.invoke:(Ljava/lang/Object;[Ljava/lang/Object;)Ljava/lang/Object;
      26: astore_3
      27: aload_1
      28: ldc           #20                 // String newDocumentBuilder
      30: aconst_null
      31: invokevirtual #10                 // Method java/lang/Class.getMethod:(Ljava/lang/String;[Ljava/lang/Class;)Ljava/lang/reflect/Method;
      34: astore        4
      36: aload         4
      38: aload_3
      39: aconst_null
      40: invokevirtual #11                 // Method java/lang/reflect/Method.invoke:(Ljava/lang/Object;[Ljava/lang/Object;)Ljava/lang/Object;
      43: astore        5
      45: aload         5
      47: invokevirtual #21                 // Method java/lang/Object.getClass:()Ljava/lang/Class;
      50: astore        6
      52: aload         6
      54: ldc           #40                 // String newDocument
      56: aconst_null
      57: invokevirtual #10                 // Method java/lang/Class.getMethod:(Ljava/lang/String;[Ljava/lang/Class;)Ljava/lang/reflect/Method;
      60: astore        7
      62: aload         7
      64: aload         5
      66: aconst_null
      67: invokevirtual #11                 // Method java/lang/reflect/Method.invoke:(Ljava/lang/Object;[Ljava/lang/Object;)Ljava/lang/Object;
      70: checkcast     #31                 // class org/w3c/dom/Document
      73: astore        8
      75: aload         8
      77: areturn
      78: astore_1
      79: new           #35                 // class org/jdom/JDOMException
      82: dup
      83: ldc           #41                 // String Reflection failed while creating new JAXP document
      85: aload_1
      86: invokespecial #37                 // Method org/jdom/JDOMException."<init>":(Ljava/lang/String;Ljava/lang/Throwable;)V
      89: athrow
    Exception table:
       from    to  target type
           0    77    78   Class java/lang/Exception

  static java.lang.Class class$(java.lang.String);
    Code:
       0: aload_0
       1: invokestatic  #1                  // Method java/lang/Class.forName:(Ljava/lang/String;)Ljava/lang/Class;
       4: areturn
       5: astore_1
       6: new           #3                  // class java/lang/NoClassDefFoundError
       9: dup
      10: aload_1
      11: invokevirtual #4                  // Method java/lang/ClassNotFoundException.getMessage:()Ljava/lang/String;
      14: invokespecial #5                  // Method java/lang/NoClassDefFoundError."<init>":(Ljava/lang/String;)V
      17: athrow
    Exception table:
       from    to  target type
           0     4     5   Class java/lang/ClassNotFoundException
}
