Compiled from "DetectionRule.java"
public class org.elasticsearch.client.ml.job.config.DetectionRule$Builder {
  private java.util.EnumSet<org.elasticsearch.client.ml.job.config.RuleAction> actions;

  private org.elasticsearch.client.ml.job.config.RuleScope scope;

  private java.util.List<org.elasticsearch.client.ml.job.config.RuleCondition> conditions;

  public org.elasticsearch.client.ml.job.config.DetectionRule$Builder(org.elasticsearch.client.ml.job.config.RuleScope$Builder);
    Code:
       0: aload_0
       1: invokespecial #1                  // Method java/lang/Object."<init>":()V
       4: aload_0
       5: getstatic     #2                  // Field org/elasticsearch/client/ml/job/config/RuleAction.SKIP_RESULT:Lorg/elasticsearch/client/ml/job/config/RuleAction;
       8: invokestatic  #3                  // Method java/util/EnumSet.of:(Ljava/lang/Enum;)Ljava/util/EnumSet;
      11: putfield      #4                  // Field actions:Ljava/util/EnumSet;
      14: aload_0
      15: new           #5                  // class org/elasticsearch/client/ml/job/config/RuleScope
      18: dup
      19: invokespecial #6                  // Method org/elasticsearch/client/ml/job/config/RuleScope."<init>":()V
      22: putfield      #7                  // Field scope:Lorg/elasticsearch/client/ml/job/config/RuleScope;
      25: aload_0
      26: invokestatic  #8                  // Method java/util/Collections.emptyList:()Ljava/util/List;
      29: putfield      #9                  // Field conditions:Ljava/util/List;
      32: aload_0
      33: aload_1
      34: invokevirtual #10                 // Method org/elasticsearch/client/ml/job/config/RuleScope$Builder.build:()Lorg/elasticsearch/client/ml/job/config/RuleScope;
      37: putfield      #7                  // Field scope:Lorg/elasticsearch/client/ml/job/config/RuleScope;
      40: return

  public org.elasticsearch.client.ml.job.config.DetectionRule$Builder(java.util.List<org.elasticsearch.client.ml.job.config.RuleCondition>);
    Code:
       0: aload_0
       1: invokespecial #1                  // Method java/lang/Object."<init>":()V
       4: aload_0
       5: getstatic     #2                  // Field org/elasticsearch/client/ml/job/config/RuleAction.SKIP_RESULT:Lorg/elasticsearch/client/ml/job/config/RuleAction;
       8: invokestatic  #3                  // Method java/util/EnumSet.of:(Ljava/lang/Enum;)Ljava/util/EnumSet;
      11: putfield      #4                  // Field actions:Ljava/util/EnumSet;
      14: aload_0
      15: new           #5                  // class org/elasticsearch/client/ml/job/config/RuleScope
      18: dup
      19: invokespecial #6                  // Method org/elasticsearch/client/ml/job/config/RuleScope."<init>":()V
      22: putfield      #7                  // Field scope:Lorg/elasticsearch/client/ml/job/config/RuleScope;
      25: aload_0
      26: invokestatic  #8                  // Method java/util/Collections.emptyList:()Ljava/util/List;
      29: putfield      #9                  // Field conditions:Ljava/util/List;
      32: aload_0
      33: aload_1
      34: invokestatic  #11                 // Method java/util/Objects.requireNonNull:(Ljava/lang/Object;)Ljava/lang/Object;
      37: checkcast     #12                 // class java/util/List
      40: putfield      #9                  // Field conditions:Ljava/util/List;
      43: return

  org.elasticsearch.client.ml.job.config.DetectionRule$Builder();
    Code:
       0: aload_0
       1: invokespecial #1                  // Method java/lang/Object."<init>":()V
       4: aload_0
       5: getstatic     #2                  // Field org/elasticsearch/client/ml/job/config/RuleAction.SKIP_RESULT:Lorg/elasticsearch/client/ml/job/config/RuleAction;
       8: invokestatic  #3                  // Method java/util/EnumSet.of:(Ljava/lang/Enum;)Ljava/util/EnumSet;
      11: putfield      #4                  // Field actions:Ljava/util/EnumSet;
      14: aload_0
      15: new           #5                  // class org/elasticsearch/client/ml/job/config/RuleScope
      18: dup
      19: invokespecial #6                  // Method org/elasticsearch/client/ml/job/config/RuleScope."<init>":()V
      22: putfield      #7                  // Field scope:Lorg/elasticsearch/client/ml/job/config/RuleScope;
      25: aload_0
      26: invokestatic  #8                  // Method java/util/Collections.emptyList:()Ljava/util/List;
      29: putfield      #9                  // Field conditions:Ljava/util/List;
      32: return

  public org.elasticsearch.client.ml.job.config.DetectionRule$Builder setActions(java.util.List<java.lang.String>);
    Code:
       0: aload_0
       1: getfield      #4                  // Field actions:Ljava/util/EnumSet;
       4: invokevirtual #13                 // Method java/util/EnumSet.clear:()V
       7: aload_1
       8: invokeinterface #14,  1           // InterfaceMethod java/util/List.stream:()Ljava/util/stream/Stream;
      13: invokedynamic #15,  0             // InvokeDynamic #0:apply:()Ljava/util/function/Function;
      18: invokeinterface #16,  2           // InterfaceMethod java/util/stream/Stream.map:(Ljava/util/function/Function;)Ljava/util/stream/Stream;
      23: aload_0
      24: getfield      #4                  // Field actions:Ljava/util/EnumSet;
      27: dup
      28: invokestatic  #11                 // Method java/util/Objects.requireNonNull:(Ljava/lang/Object;)Ljava/lang/Object;
      31: pop
      32: invokedynamic #17,  0             // InvokeDynamic #1:accept:(Ljava/util/EnumSet;)Ljava/util/function/Consumer;
      37: invokeinterface #18,  2           // InterfaceMethod java/util/stream/Stream.forEach:(Ljava/util/function/Consumer;)V
      42: aload_0
      43: areturn

  public org.elasticsearch.client.ml.job.config.DetectionRule$Builder setActions(java.util.EnumSet<org.elasticsearch.client.ml.job.config.RuleAction>);
    Code:
       0: aload_0
       1: aload_1
       2: getstatic     #19                 // Field org/elasticsearch/client/ml/job/config/DetectionRule.ACTIONS_FIELD:Lorg/elasticsearch/common/ParseField;
       5: invokevirtual #20                 // Method org/elasticsearch/common/ParseField.getPreferredName:()Ljava/lang/String;
       8: invokestatic  #21                 // Method java/util/Objects.requireNonNull:(Ljava/lang/Object;Ljava/lang/String;)Ljava/lang/Object;
      11: checkcast     #22                 // class java/util/EnumSet
      14: putfield      #4                  // Field actions:Ljava/util/EnumSet;
      17: aload_0
      18: areturn

  public org.elasticsearch.client.ml.job.config.DetectionRule$Builder setActions(org.elasticsearch.client.ml.job.config.RuleAction...);
    Code:
       0: aload_0
       1: getfield      #4                  // Field actions:Ljava/util/EnumSet;
       4: invokevirtual #13                 // Method java/util/EnumSet.clear:()V
       7: aload_1
       8: invokestatic  #23                 // Method java/util/Arrays.stream:([Ljava/lang/Object;)Ljava/util/stream/Stream;
      11: aload_0
      12: getfield      #4                  // Field actions:Ljava/util/EnumSet;
      15: dup
      16: invokestatic  #11                 // Method java/util/Objects.requireNonNull:(Ljava/lang/Object;)Ljava/lang/Object;
      19: pop
      20: invokedynamic #17,  0             // InvokeDynamic #1:accept:(Ljava/util/EnumSet;)Ljava/util/function/Consumer;
      25: invokeinterface #18,  2           // InterfaceMethod java/util/stream/Stream.forEach:(Ljava/util/function/Consumer;)V
      30: aload_0
      31: areturn

  public org.elasticsearch.client.ml.job.config.DetectionRule$Builder setScope(org.elasticsearch.client.ml.job.config.RuleScope);
    Code:
       0: aload_0
       1: aload_1
       2: invokestatic  #11                 // Method java/util/Objects.requireNonNull:(Ljava/lang/Object;)Ljava/lang/Object;
       5: checkcast     #5                  // class org/elasticsearch/client/ml/job/config/RuleScope
       8: putfield      #7                  // Field scope:Lorg/elasticsearch/client/ml/job/config/RuleScope;
      11: aload_0
      12: areturn

  public org.elasticsearch.client.ml.job.config.DetectionRule$Builder setConditions(java.util.List<org.elasticsearch.client.ml.job.config.RuleCondition>);
    Code:
       0: aload_0
       1: aload_1
       2: invokestatic  #11                 // Method java/util/Objects.requireNonNull:(Ljava/lang/Object;)Ljava/lang/Object;
       5: checkcast     #12                 // class java/util/List
       8: putfield      #9                  // Field conditions:Ljava/util/List;
      11: aload_0
      12: areturn

  public org.elasticsearch.client.ml.job.config.DetectionRule build();
    Code:
       0: new           #24                 // class org/elasticsearch/client/ml/job/config/DetectionRule
       3: dup
       4: aload_0
       5: getfield      #4                  // Field actions:Ljava/util/EnumSet;
       8: aload_0
       9: getfield      #7                  // Field scope:Lorg/elasticsearch/client/ml/job/config/RuleScope;
      12: aload_0
      13: getfield      #9                  // Field conditions:Ljava/util/List;
      16: aconst_null
      17: invokespecial #25                 // Method org/elasticsearch/client/ml/job/config/DetectionRule."<init>":(Ljava/util/EnumSet;Lorg/elasticsearch/client/ml/job/config/RuleScope;Ljava/util/List;Lorg/elasticsearch/client/ml/job/config/DetectionRule$1;)V
      20: areturn
}
