Compiled from "RuleScope.java"
public class org.elasticsearch.client.ml.job.config.RuleScope implements org.elasticsearch.common.xcontent.ToXContentObject {
  private static final org.elasticsearch.common.xcontent.DeprecationHandler DEPRECATION_HANDLER;

  private final java.util.Map<java.lang.String, org.elasticsearch.client.ml.job.config.FilterRef> scope;

  public static org.elasticsearch.common.xcontent.ContextParser<java.lang.Void, org.elasticsearch.client.ml.job.config.RuleScope> parser();
    Code:
       0: invokedynamic #2,  0              // InvokeDynamic #0:parse:()Lorg/elasticsearch/common/xcontent/ContextParser;
       5: areturn

  public org.elasticsearch.client.ml.job.config.RuleScope();
    Code:
       0: aload_0
       1: invokespecial #3                  // Method java/lang/Object."<init>":()V
       4: aload_0
       5: invokestatic  #4                  // Method java/util/Collections.emptyMap:()Ljava/util/Map;
       8: putfield      #1                  // Field scope:Ljava/util/Map;
      11: return

  public org.elasticsearch.client.ml.job.config.RuleScope(java.util.Map<java.lang.String, org.elasticsearch.client.ml.job.config.FilterRef>);
    Code:
       0: aload_0
       1: invokespecial #3                  // Method java/lang/Object."<init>":()V
       4: aload_0
       5: aload_1
       6: invokestatic  #5                  // Method java/util/Collections.unmodifiableMap:(Ljava/util/Map;)Ljava/util/Map;
       9: putfield      #1                  // Field scope:Ljava/util/Map;
      12: return

  public org.elasticsearch.common.xcontent.XContentBuilder toXContent(org.elasticsearch.common.xcontent.XContentBuilder, org.elasticsearch.common.xcontent.ToXContent$Params) throws java.io.IOException;
    Code:
       0: aload_1
       1: aload_0
       2: getfield      #1                  // Field scope:Ljava/util/Map;
       5: invokevirtual #6                  // Method org/elasticsearch/common/xcontent/XContentBuilder.map:(Ljava/util/Map;)Lorg/elasticsearch/common/xcontent/XContentBuilder;
       8: areturn

  public boolean isEmpty();
    Code:
       0: aload_0
       1: getfield      #1                  // Field scope:Ljava/util/Map;
       4: invokeinterface #7,  1            // InterfaceMethod java/util/Map.isEmpty:()Z
       9: ireturn

  public java.util.Set<java.lang.String> getReferencedFilters();
    Code:
       0: aload_0
       1: getfield      #1                  // Field scope:Ljava/util/Map;
       4: invokeinterface #8,  1            // InterfaceMethod java/util/Map.values:()Ljava/util/Collection;
       9: invokeinterface #9,  1            // InterfaceMethod java/util/Collection.stream:()Ljava/util/stream/Stream;
      14: invokedynamic #10,  0             // InvokeDynamic #1:apply:()Ljava/util/function/Function;
      19: invokeinterface #11,  2           // InterfaceMethod java/util/stream/Stream.map:(Ljava/util/function/Function;)Ljava/util/stream/Stream;
      24: invokestatic  #12                 // Method java/util/stream/Collectors.toSet:()Ljava/util/stream/Collector;
      27: invokeinterface #13,  2           // InterfaceMethod java/util/stream/Stream.collect:(Ljava/util/stream/Collector;)Ljava/lang/Object;
      32: checkcast     #14                 // class java/util/Set
      35: areturn

  public boolean equals(java.lang.Object);
    Code:
       0: aload_0
       1: aload_1
       2: if_acmpne     7
       5: iconst_1
       6: ireturn
       7: aload_1
       8: instanceof    #15                 // class org/elasticsearch/client/ml/job/config/RuleScope
      11: ifne          16
      14: iconst_0
      15: ireturn
      16: aload_1
      17: checkcast     #15                 // class org/elasticsearch/client/ml/job/config/RuleScope
      20: astore_2
      21: aload_0
      22: getfield      #1                  // Field scope:Ljava/util/Map;
      25: aload_2
      26: getfield      #1                  // Field scope:Ljava/util/Map;
      29: invokestatic  #16                 // Method java/util/Objects.equals:(Ljava/lang/Object;Ljava/lang/Object;)Z
      32: ireturn

  public int hashCode();
    Code:
       0: iconst_1
       1: anewarray     #17                 // class java/lang/Object
       4: dup
       5: iconst_0
       6: aload_0
       7: getfield      #1                  // Field scope:Ljava/util/Map;
      10: aastore
      11: invokestatic  #18                 // Method java/util/Objects.hash:([Ljava/lang/Object;)I
      14: ireturn

  public static org.elasticsearch.client.ml.job.config.RuleScope$Builder builder();
    Code:
       0: new           #19                 // class org/elasticsearch/client/ml/job/config/RuleScope$Builder
       3: dup
       4: invokespecial #20                 // Method org/elasticsearch/client/ml/job/config/RuleScope$Builder."<init>":()V
       7: areturn

  private static org.elasticsearch.client.ml.job.config.RuleScope lambda$parser$0(org.elasticsearch.common.xcontent.XContentParser, java.lang.Void) throws java.io.IOException;
    Code:
       0: aload_0
       1: invokeinterface #21,  1           // InterfaceMethod org/elasticsearch/common/xcontent/XContentParser.map:()Ljava/util/Map;
       6: astore_2
       7: aload_2
       8: invokeinterface #7,  1            // InterfaceMethod java/util/Map.isEmpty:()Z
      13: ifeq          24
      16: new           #15                 // class org/elasticsearch/client/ml/job/config/RuleScope
      19: dup
      20: invokespecial #22                 // Method "<init>":()V
      23: areturn
      24: new           #23                 // class java/util/HashMap
      27: dup
      28: invokespecial #24                 // Method java/util/HashMap."<init>":()V
      31: astore_3
      32: aload_2
      33: invokeinterface #25,  1           // InterfaceMethod java/util/Map.entrySet:()Ljava/util/Set;
      38: invokeinterface #26,  1           // InterfaceMethod java/util/Set.iterator:()Ljava/util/Iterator;
      43: astore        4
      45: aload         4
      47: invokeinterface #27,  1           // InterfaceMethod java/util/Iterator.hasNext:()Z
      52: ifeq          234
      55: aload         4
      57: invokeinterface #28,  1           // InterfaceMethod java/util/Iterator.next:()Ljava/lang/Object;
      62: checkcast     #29                 // class java/util/Map$Entry
      65: astore        5
      67: invokestatic  #30                 // Method org/elasticsearch/common/xcontent/XContentFactory.jsonBuilder:()Lorg/elasticsearch/common/xcontent/XContentBuilder;
      70: astore        6
      72: aload         5
      74: invokeinterface #31,  1           // InterfaceMethod java/util/Map$Entry.getValue:()Ljava/lang/Object;
      79: checkcast     #32                 // class java/util/Map
      82: astore        7
      84: aload         6
      86: aload         7
      88: invokevirtual #6                  // Method org/elasticsearch/common/xcontent/XContentBuilder.map:(Ljava/util/Map;)Lorg/elasticsearch/common/xcontent/XContentBuilder;
      91: pop
      92: aload         6
      94: invokevirtual #33                 // Method org/elasticsearch/common/xcontent/XContentBuilder.contentType:()Lorg/elasticsearch/common/xcontent/XContentType;
      97: invokestatic  #34                 // Method org/elasticsearch/common/xcontent/XContentFactory.xContent:(Lorg/elasticsearch/common/xcontent/XContentType;)Lorg/elasticsearch/common/xcontent/XContent;
     100: getstatic     #35                 // Field org/elasticsearch/common/xcontent/NamedXContentRegistry.EMPTY:Lorg/elasticsearch/common/xcontent/NamedXContentRegistry;
     103: getstatic     #36                 // Field DEPRECATION_HANDLER:Lorg/elasticsearch/common/xcontent/DeprecationHandler;
     106: aload         6
     108: invokestatic  #37                 // Method org/elasticsearch/common/Strings.toString:(Lorg/elasticsearch/common/xcontent/XContentBuilder;)Ljava/lang/String;
     111: invokeinterface #38,  4           // InterfaceMethod org/elasticsearch/common/xcontent/XContent.createParser:(Lorg/elasticsearch/common/xcontent/NamedXContentRegistry;Lorg/elasticsearch/common/xcontent/DeprecationHandler;Ljava/lang/String;)Lorg/elasticsearch/common/xcontent/XContentParser;
     116: astore        8
     118: aload_3
     119: aload         5
     121: invokeinterface #39,  1           // InterfaceMethod java/util/Map$Entry.getKey:()Ljava/lang/Object;
     126: checkcast     #40                 // class java/lang/String
     129: getstatic     #41                 // Field org/elasticsearch/client/ml/job/config/FilterRef.PARSER:Lorg/elasticsearch/common/xcontent/ConstructingObjectParser;
     132: aload         8
     134: aconst_null
     135: invokevirtual #42                 // Method org/elasticsearch/common/xcontent/ConstructingObjectParser.parse:(Lorg/elasticsearch/common/xcontent/XContentParser;Ljava/lang/Object;)Ljava/lang/Object;
     138: checkcast     #43                 // class org/elasticsearch/client/ml/job/config/FilterRef
     141: invokeinterface #44,  3           // InterfaceMethod java/util/Map.put:(Ljava/lang/Object;Ljava/lang/Object;)Ljava/lang/Object;
     146: pop
     147: aload         8
     149: ifnull        191
     152: aload         8
     154: invokeinterface #45,  1           // InterfaceMethod org/elasticsearch/common/xcontent/XContentParser.close:()V
     159: goto          191
     162: astore        9
     164: aload         8
     166: ifnull        188
     169: aload         8
     171: invokeinterface #45,  1           // InterfaceMethod org/elasticsearch/common/xcontent/XContentParser.close:()V
     176: goto          188
     179: astore        10
     181: aload         9
     183: aload         10
     185: invokevirtual #47                 // Method java/lang/Throwable.addSuppressed:(Ljava/lang/Throwable;)V
     188: aload         9
     190: athrow
     191: aload         6
     193: ifnull        231
     196: aload         6
     198: invokevirtual #48                 // Method org/elasticsearch/common/xcontent/XContentBuilder.close:()V
     201: goto          231
     204: astore        7
     206: aload         6
     208: ifnull        228
     211: aload         6
     213: invokevirtual #48                 // Method org/elasticsearch/common/xcontent/XContentBuilder.close:()V
     216: goto          228
     219: astore        8
     221: aload         7
     223: aload         8
     225: invokevirtual #47                 // Method java/lang/Throwable.addSuppressed:(Ljava/lang/Throwable;)V
     228: aload         7
     230: athrow
     231: goto          45
     234: new           #15                 // class org/elasticsearch/client/ml/job/config/RuleScope
     237: dup
     238: aload_3
     239: invokespecial #49                 // Method "<init>":(Ljava/util/Map;)V
     242: areturn
    Exception table:
       from    to  target type
         118   147   162   Class java/lang/Throwable
         169   176   179   Class java/lang/Throwable
          72   191   204   Class java/lang/Throwable
         211   216   219   Class java/lang/Throwable

  static java.util.Map access$000(org.elasticsearch.client.ml.job.config.RuleScope);
    Code:
       0: aload_0
       1: getfield      #1                  // Field scope:Ljava/util/Map;
       4: areturn

  static {};
    Code:
       0: new           #50                 // class org/elasticsearch/client/ml/job/config/RuleScope$1
       3: dup
       4: invokespecial #51                 // Method org/elasticsearch/client/ml/job/config/RuleScope$1."<init>":()V
       7: putstatic     #36                 // Field DEPRECATION_HANDLER:Lorg/elasticsearch/common/xcontent/DeprecationHandler;
      10: return
}
