Compiled from "DeserializerFactoryConfig.java"
public class com.fasterxml.jackson.databind.cfg.DeserializerFactoryConfig implements java.io.Serializable {
  private static final long serialVersionUID;

  protected static final com.fasterxml.jackson.databind.deser.Deserializers[] NO_DESERIALIZERS;

  protected static final com.fasterxml.jackson.databind.deser.BeanDeserializerModifier[] NO_MODIFIERS;

  protected static final com.fasterxml.jackson.databind.AbstractTypeResolver[] NO_ABSTRACT_TYPE_RESOLVERS;

  protected static final com.fasterxml.jackson.databind.deser.ValueInstantiators[] NO_VALUE_INSTANTIATORS;

  protected static final com.fasterxml.jackson.databind.deser.KeyDeserializers[] DEFAULT_KEY_DESERIALIZERS;

  protected final com.fasterxml.jackson.databind.deser.Deserializers[] _additionalDeserializers;

  protected final com.fasterxml.jackson.databind.deser.KeyDeserializers[] _additionalKeyDeserializers;

  protected final com.fasterxml.jackson.databind.deser.BeanDeserializerModifier[] _modifiers;

  protected final com.fasterxml.jackson.databind.AbstractTypeResolver[] _abstractTypeResolvers;

  protected final com.fasterxml.jackson.databind.deser.ValueInstantiators[] _valueInstantiators;

  public com.fasterxml.jackson.databind.cfg.DeserializerFactoryConfig();
    Code:
       0: aload_0
       1: aconst_null
       2: aconst_null
       3: aconst_null
       4: aconst_null
       5: aconst_null
       6: invokespecial #1                  // Method "<init>":([Lcom/fasterxml/jackson/databind/deser/Deserializers;[Lcom/fasterxml/jackson/databind/deser/KeyDeserializers;[Lcom/fasterxml/jackson/databind/deser/BeanDeserializerModifier;[Lcom/fasterxml/jackson/databind/AbstractTypeResolver;[Lcom/fasterxml/jackson/databind/deser/ValueInstantiators;)V
       9: return

  protected com.fasterxml.jackson.databind.cfg.DeserializerFactoryConfig(com.fasterxml.jackson.databind.deser.Deserializers[], com.fasterxml.jackson.databind.deser.KeyDeserializers[], com.fasterxml.jackson.databind.deser.BeanDeserializerModifier[], com.fasterxml.jackson.databind.AbstractTypeResolver[], com.fasterxml.jackson.databind.deser.ValueInstantiators[]);
    Code:
       0: aload_0
       1: invokespecial #2                  // Method java/lang/Object."<init>":()V
       4: aload_0
       5: aload_1
       6: ifnonnull     15
       9: getstatic     #3                  // Field NO_DESERIALIZERS:[Lcom/fasterxml/jackson/databind/deser/Deserializers;
      12: goto          16
      15: aload_1
      16: putfield      #4                  // Field _additionalDeserializers:[Lcom/fasterxml/jackson/databind/deser/Deserializers;
      19: aload_0
      20: aload_2
      21: ifnonnull     30
      24: getstatic     #5                  // Field DEFAULT_KEY_DESERIALIZERS:[Lcom/fasterxml/jackson/databind/deser/KeyDeserializers;
      27: goto          31
      30: aload_2
      31: putfield      #6                  // Field _additionalKeyDeserializers:[Lcom/fasterxml/jackson/databind/deser/KeyDeserializers;
      34: aload_0
      35: aload_3
      36: ifnonnull     45
      39: getstatic     #7                  // Field NO_MODIFIERS:[Lcom/fasterxml/jackson/databind/deser/BeanDeserializerModifier;
      42: goto          46
      45: aload_3
      46: putfield      #8                  // Field _modifiers:[Lcom/fasterxml/jackson/databind/deser/BeanDeserializerModifier;
      49: aload_0
      50: aload         4
      52: ifnonnull     61
      55: getstatic     #9                  // Field NO_ABSTRACT_TYPE_RESOLVERS:[Lcom/fasterxml/jackson/databind/AbstractTypeResolver;
      58: goto          63
      61: aload         4
      63: putfield      #10                 // Field _abstractTypeResolvers:[Lcom/fasterxml/jackson/databind/AbstractTypeResolver;
      66: aload_0
      67: aload         5
      69: ifnonnull     78
      72: getstatic     #11                 // Field NO_VALUE_INSTANTIATORS:[Lcom/fasterxml/jackson/databind/deser/ValueInstantiators;
      75: goto          80
      78: aload         5
      80: putfield      #12                 // Field _valueInstantiators:[Lcom/fasterxml/jackson/databind/deser/ValueInstantiators;
      83: return

  public com.fasterxml.jackson.databind.cfg.DeserializerFactoryConfig withAdditionalDeserializers(com.fasterxml.jackson.databind.deser.Deserializers);
    Code:
       0: aload_1
       1: ifnonnull     14
       4: new           #13                 // class java/lang/IllegalArgumentException
       7: dup
       8: ldc           #14                 // String Can not pass null Deserializers
      10: invokespecial #15                 // Method java/lang/IllegalArgumentException."<init>":(Ljava/lang/String;)V
      13: athrow
      14: aload_0
      15: getfield      #4                  // Field _additionalDeserializers:[Lcom/fasterxml/jackson/databind/deser/Deserializers;
      18: aload_1
      19: invokestatic  #16                 // Method com/fasterxml/jackson/databind/util/ArrayBuilders.insertInListNoDup:([Ljava/lang/Object;Ljava/lang/Object;)[Ljava/lang/Object;
      22: checkcast     #17                 // class "[Lcom/fasterxml/jackson/databind/deser/Deserializers;"
      25: astore_2
      26: new           #18                 // class com/fasterxml/jackson/databind/cfg/DeserializerFactoryConfig
      29: dup
      30: aload_2
      31: aload_0
      32: getfield      #6                  // Field _additionalKeyDeserializers:[Lcom/fasterxml/jackson/databind/deser/KeyDeserializers;
      35: aload_0
      36: getfield      #8                  // Field _modifiers:[Lcom/fasterxml/jackson/databind/deser/BeanDeserializerModifier;
      39: aload_0
      40: getfield      #10                 // Field _abstractTypeResolvers:[Lcom/fasterxml/jackson/databind/AbstractTypeResolver;
      43: aload_0
      44: getfield      #12                 // Field _valueInstantiators:[Lcom/fasterxml/jackson/databind/deser/ValueInstantiators;
      47: invokespecial #1                  // Method "<init>":([Lcom/fasterxml/jackson/databind/deser/Deserializers;[Lcom/fasterxml/jackson/databind/deser/KeyDeserializers;[Lcom/fasterxml/jackson/databind/deser/BeanDeserializerModifier;[Lcom/fasterxml/jackson/databind/AbstractTypeResolver;[Lcom/fasterxml/jackson/databind/deser/ValueInstantiators;)V
      50: areturn

  public com.fasterxml.jackson.databind.cfg.DeserializerFactoryConfig withAdditionalKeyDeserializers(com.fasterxml.jackson.databind.deser.KeyDeserializers);
    Code:
       0: aload_1
       1: ifnonnull     14
       4: new           #13                 // class java/lang/IllegalArgumentException
       7: dup
       8: ldc           #19                 // String Can not pass null KeyDeserializers
      10: invokespecial #15                 // Method java/lang/IllegalArgumentException."<init>":(Ljava/lang/String;)V
      13: athrow
      14: aload_0
      15: getfield      #6                  // Field _additionalKeyDeserializers:[Lcom/fasterxml/jackson/databind/deser/KeyDeserializers;
      18: aload_1
      19: invokestatic  #16                 // Method com/fasterxml/jackson/databind/util/ArrayBuilders.insertInListNoDup:([Ljava/lang/Object;Ljava/lang/Object;)[Ljava/lang/Object;
      22: checkcast     #20                 // class "[Lcom/fasterxml/jackson/databind/deser/KeyDeserializers;"
      25: astore_2
      26: new           #18                 // class com/fasterxml/jackson/databind/cfg/DeserializerFactoryConfig
      29: dup
      30: aload_0
      31: getfield      #4                  // Field _additionalDeserializers:[Lcom/fasterxml/jackson/databind/deser/Deserializers;
      34: aload_2
      35: aload_0
      36: getfield      #8                  // Field _modifiers:[Lcom/fasterxml/jackson/databind/deser/BeanDeserializerModifier;
      39: aload_0
      40: getfield      #10                 // Field _abstractTypeResolvers:[Lcom/fasterxml/jackson/databind/AbstractTypeResolver;
      43: aload_0
      44: getfield      #12                 // Field _valueInstantiators:[Lcom/fasterxml/jackson/databind/deser/ValueInstantiators;
      47: invokespecial #1                  // Method "<init>":([Lcom/fasterxml/jackson/databind/deser/Deserializers;[Lcom/fasterxml/jackson/databind/deser/KeyDeserializers;[Lcom/fasterxml/jackson/databind/deser/BeanDeserializerModifier;[Lcom/fasterxml/jackson/databind/AbstractTypeResolver;[Lcom/fasterxml/jackson/databind/deser/ValueInstantiators;)V
      50: areturn

  public com.fasterxml.jackson.databind.cfg.DeserializerFactoryConfig withDeserializerModifier(com.fasterxml.jackson.databind.deser.BeanDeserializerModifier);
    Code:
       0: aload_1
       1: ifnonnull     14
       4: new           #13                 // class java/lang/IllegalArgumentException
       7: dup
       8: ldc           #21                 // String Can not pass null modifier
      10: invokespecial #15                 // Method java/lang/IllegalArgumentException."<init>":(Ljava/lang/String;)V
      13: athrow
      14: aload_0
      15: getfield      #8                  // Field _modifiers:[Lcom/fasterxml/jackson/databind/deser/BeanDeserializerModifier;
      18: aload_1
      19: invokestatic  #16                 // Method com/fasterxml/jackson/databind/util/ArrayBuilders.insertInListNoDup:([Ljava/lang/Object;Ljava/lang/Object;)[Ljava/lang/Object;
      22: checkcast     #22                 // class "[Lcom/fasterxml/jackson/databind/deser/BeanDeserializerModifier;"
      25: astore_2
      26: new           #18                 // class com/fasterxml/jackson/databind/cfg/DeserializerFactoryConfig
      29: dup
      30: aload_0
      31: getfield      #4                  // Field _additionalDeserializers:[Lcom/fasterxml/jackson/databind/deser/Deserializers;
      34: aload_0
      35: getfield      #6                  // Field _additionalKeyDeserializers:[Lcom/fasterxml/jackson/databind/deser/KeyDeserializers;
      38: aload_2
      39: aload_0
      40: getfield      #10                 // Field _abstractTypeResolvers:[Lcom/fasterxml/jackson/databind/AbstractTypeResolver;
      43: aload_0
      44: getfield      #12                 // Field _valueInstantiators:[Lcom/fasterxml/jackson/databind/deser/ValueInstantiators;
      47: invokespecial #1                  // Method "<init>":([Lcom/fasterxml/jackson/databind/deser/Deserializers;[Lcom/fasterxml/jackson/databind/deser/KeyDeserializers;[Lcom/fasterxml/jackson/databind/deser/BeanDeserializerModifier;[Lcom/fasterxml/jackson/databind/AbstractTypeResolver;[Lcom/fasterxml/jackson/databind/deser/ValueInstantiators;)V
      50: areturn

  public com.fasterxml.jackson.databind.cfg.DeserializerFactoryConfig withAbstractTypeResolver(com.fasterxml.jackson.databind.AbstractTypeResolver);
    Code:
       0: aload_1
       1: ifnonnull     14
       4: new           #13                 // class java/lang/IllegalArgumentException
       7: dup
       8: ldc           #23                 // String Can not pass null resolver
      10: invokespecial #15                 // Method java/lang/IllegalArgumentException."<init>":(Ljava/lang/String;)V
      13: athrow
      14: aload_0
      15: getfield      #10                 // Field _abstractTypeResolvers:[Lcom/fasterxml/jackson/databind/AbstractTypeResolver;
      18: aload_1
      19: invokestatic  #16                 // Method com/fasterxml/jackson/databind/util/ArrayBuilders.insertInListNoDup:([Ljava/lang/Object;Ljava/lang/Object;)[Ljava/lang/Object;
      22: checkcast     #24                 // class "[Lcom/fasterxml/jackson/databind/AbstractTypeResolver;"
      25: astore_2
      26: new           #18                 // class com/fasterxml/jackson/databind/cfg/DeserializerFactoryConfig
      29: dup
      30: aload_0
      31: getfield      #4                  // Field _additionalDeserializers:[Lcom/fasterxml/jackson/databind/deser/Deserializers;
      34: aload_0
      35: getfield      #6                  // Field _additionalKeyDeserializers:[Lcom/fasterxml/jackson/databind/deser/KeyDeserializers;
      38: aload_0
      39: getfield      #8                  // Field _modifiers:[Lcom/fasterxml/jackson/databind/deser/BeanDeserializerModifier;
      42: aload_2
      43: aload_0
      44: getfield      #12                 // Field _valueInstantiators:[Lcom/fasterxml/jackson/databind/deser/ValueInstantiators;
      47: invokespecial #1                  // Method "<init>":([Lcom/fasterxml/jackson/databind/deser/Deserializers;[Lcom/fasterxml/jackson/databind/deser/KeyDeserializers;[Lcom/fasterxml/jackson/databind/deser/BeanDeserializerModifier;[Lcom/fasterxml/jackson/databind/AbstractTypeResolver;[Lcom/fasterxml/jackson/databind/deser/ValueInstantiators;)V
      50: areturn

  public com.fasterxml.jackson.databind.cfg.DeserializerFactoryConfig withValueInstantiators(com.fasterxml.jackson.databind.deser.ValueInstantiators);
    Code:
       0: aload_1
       1: ifnonnull     14
       4: new           #13                 // class java/lang/IllegalArgumentException
       7: dup
       8: ldc           #23                 // String Can not pass null resolver
      10: invokespecial #15                 // Method java/lang/IllegalArgumentException."<init>":(Ljava/lang/String;)V
      13: athrow
      14: aload_0
      15: getfield      #12                 // Field _valueInstantiators:[Lcom/fasterxml/jackson/databind/deser/ValueInstantiators;
      18: aload_1
      19: invokestatic  #16                 // Method com/fasterxml/jackson/databind/util/ArrayBuilders.insertInListNoDup:([Ljava/lang/Object;Ljava/lang/Object;)[Ljava/lang/Object;
      22: checkcast     #25                 // class "[Lcom/fasterxml/jackson/databind/deser/ValueInstantiators;"
      25: astore_2
      26: new           #18                 // class com/fasterxml/jackson/databind/cfg/DeserializerFactoryConfig
      29: dup
      30: aload_0
      31: getfield      #4                  // Field _additionalDeserializers:[Lcom/fasterxml/jackson/databind/deser/Deserializers;
      34: aload_0
      35: getfield      #6                  // Field _additionalKeyDeserializers:[Lcom/fasterxml/jackson/databind/deser/KeyDeserializers;
      38: aload_0
      39: getfield      #8                  // Field _modifiers:[Lcom/fasterxml/jackson/databind/deser/BeanDeserializerModifier;
      42: aload_0
      43: getfield      #10                 // Field _abstractTypeResolvers:[Lcom/fasterxml/jackson/databind/AbstractTypeResolver;
      46: aload_2
      47: invokespecial #1                  // Method "<init>":([Lcom/fasterxml/jackson/databind/deser/Deserializers;[Lcom/fasterxml/jackson/databind/deser/KeyDeserializers;[Lcom/fasterxml/jackson/databind/deser/BeanDeserializerModifier;[Lcom/fasterxml/jackson/databind/AbstractTypeResolver;[Lcom/fasterxml/jackson/databind/deser/ValueInstantiators;)V
      50: areturn

  public boolean hasDeserializers();
    Code:
       0: aload_0
       1: getfield      #4                  // Field _additionalDeserializers:[Lcom/fasterxml/jackson/databind/deser/Deserializers;
       4: arraylength
       5: ifle          12
       8: iconst_1
       9: goto          13
      12: iconst_0
      13: ireturn

  public boolean hasKeyDeserializers();
    Code:
       0: aload_0
       1: getfield      #6                  // Field _additionalKeyDeserializers:[Lcom/fasterxml/jackson/databind/deser/KeyDeserializers;
       4: arraylength
       5: ifle          12
       8: iconst_1
       9: goto          13
      12: iconst_0
      13: ireturn

  public boolean hasDeserializerModifiers();
    Code:
       0: aload_0
       1: getfield      #8                  // Field _modifiers:[Lcom/fasterxml/jackson/databind/deser/BeanDeserializerModifier;
       4: arraylength
       5: ifle          12
       8: iconst_1
       9: goto          13
      12: iconst_0
      13: ireturn

  public boolean hasAbstractTypeResolvers();
    Code:
       0: aload_0
       1: getfield      #10                 // Field _abstractTypeResolvers:[Lcom/fasterxml/jackson/databind/AbstractTypeResolver;
       4: arraylength
       5: ifle          12
       8: iconst_1
       9: goto          13
      12: iconst_0
      13: ireturn

  public boolean hasValueInstantiators();
    Code:
       0: aload_0
       1: getfield      #12                 // Field _valueInstantiators:[Lcom/fasterxml/jackson/databind/deser/ValueInstantiators;
       4: arraylength
       5: ifle          12
       8: iconst_1
       9: goto          13
      12: iconst_0
      13: ireturn

  public java.lang.Iterable<com.fasterxml.jackson.databind.deser.Deserializers> deserializers();
    Code:
       0: new           #26                 // class com/fasterxml/jackson/databind/util/ArrayIterator
       3: dup
       4: aload_0
       5: getfield      #4                  // Field _additionalDeserializers:[Lcom/fasterxml/jackson/databind/deser/Deserializers;
       8: invokespecial #27                 // Method com/fasterxml/jackson/databind/util/ArrayIterator."<init>":([Ljava/lang/Object;)V
      11: areturn

  public java.lang.Iterable<com.fasterxml.jackson.databind.deser.KeyDeserializers> keyDeserializers();
    Code:
       0: new           #26                 // class com/fasterxml/jackson/databind/util/ArrayIterator
       3: dup
       4: aload_0
       5: getfield      #6                  // Field _additionalKeyDeserializers:[Lcom/fasterxml/jackson/databind/deser/KeyDeserializers;
       8: invokespecial #27                 // Method com/fasterxml/jackson/databind/util/ArrayIterator."<init>":([Ljava/lang/Object;)V
      11: areturn

  public java.lang.Iterable<com.fasterxml.jackson.databind.deser.BeanDeserializerModifier> deserializerModifiers();
    Code:
       0: new           #26                 // class com/fasterxml/jackson/databind/util/ArrayIterator
       3: dup
       4: aload_0
       5: getfield      #8                  // Field _modifiers:[Lcom/fasterxml/jackson/databind/deser/BeanDeserializerModifier;
       8: invokespecial #27                 // Method com/fasterxml/jackson/databind/util/ArrayIterator."<init>":([Ljava/lang/Object;)V
      11: areturn

  public java.lang.Iterable<com.fasterxml.jackson.databind.AbstractTypeResolver> abstractTypeResolvers();
    Code:
       0: new           #26                 // class com/fasterxml/jackson/databind/util/ArrayIterator
       3: dup
       4: aload_0
       5: getfield      #10                 // Field _abstractTypeResolvers:[Lcom/fasterxml/jackson/databind/AbstractTypeResolver;
       8: invokespecial #27                 // Method com/fasterxml/jackson/databind/util/ArrayIterator."<init>":([Ljava/lang/Object;)V
      11: areturn

  public java.lang.Iterable<com.fasterxml.jackson.databind.deser.ValueInstantiators> valueInstantiators();
    Code:
       0: new           #26                 // class com/fasterxml/jackson/databind/util/ArrayIterator
       3: dup
       4: aload_0
       5: getfield      #12                 // Field _valueInstantiators:[Lcom/fasterxml/jackson/databind/deser/ValueInstantiators;
       8: invokespecial #27                 // Method com/fasterxml/jackson/databind/util/ArrayIterator."<init>":([Ljava/lang/Object;)V
      11: areturn

  static {};
    Code:
       0: iconst_0
       1: anewarray     #28                 // class com/fasterxml/jackson/databind/deser/Deserializers
       4: putstatic     #3                  // Field NO_DESERIALIZERS:[Lcom/fasterxml/jackson/databind/deser/Deserializers;
       7: iconst_0
       8: anewarray     #29                 // class com/fasterxml/jackson/databind/deser/BeanDeserializerModifier
      11: putstatic     #7                  // Field NO_MODIFIERS:[Lcom/fasterxml/jackson/databind/deser/BeanDeserializerModifier;
      14: iconst_0
      15: anewarray     #30                 // class com/fasterxml/jackson/databind/AbstractTypeResolver
      18: putstatic     #9                  // Field NO_ABSTRACT_TYPE_RESOLVERS:[Lcom/fasterxml/jackson/databind/AbstractTypeResolver;
      21: iconst_0
      22: anewarray     #31                 // class com/fasterxml/jackson/databind/deser/ValueInstantiators
      25: putstatic     #11                 // Field NO_VALUE_INSTANTIATORS:[Lcom/fasterxml/jackson/databind/deser/ValueInstantiators;
      28: iconst_1
      29: anewarray     #32                 // class com/fasterxml/jackson/databind/deser/KeyDeserializers
      32: dup
      33: iconst_0
      34: new           #33                 // class com/fasterxml/jackson/databind/deser/std/StdKeyDeserializers
      37: dup
      38: invokespecial #34                 // Method com/fasterxml/jackson/databind/deser/std/StdKeyDeserializers."<init>":()V
      41: aastore
      42: putstatic     #5                  // Field DEFAULT_KEY_DESERIALIZERS:[Lcom/fasterxml/jackson/databind/deser/KeyDeserializers;
      45: return
}
