Compiled from "UrlXmlSource.java"
public class org.hibernate.boot.jaxb.internal.UrlXmlSource extends org.hibernate.boot.jaxb.spi.XmlSource {
  private final java.net.URL url;

  public org.hibernate.boot.jaxb.internal.UrlXmlSource(org.hibernate.boot.jaxb.Origin, java.net.URL);
    Code:
       0: aload_0
       1: aload_1
       2: invokespecial #1                  // Method org/hibernate/boot/jaxb/spi/XmlSource."<init>":(Lorg/hibernate/boot/jaxb/Origin;)V
       5: aload_0
       6: aload_2
       7: putfield      #2                  // Field url:Ljava/net/URL;
      10: return

  public org.hibernate.boot.jaxb.spi.Binding doBind(org.hibernate.boot.jaxb.spi.Binder);
    Code:
       0: aload_0
       1: getfield      #2                  // Field url:Ljava/net/URL;
       4: invokevirtual #3                  // Method java/net/URL.openStream:()Ljava/io/InputStream;
       7: astore_2
       8: aload_1
       9: aload_2
      10: aload_0
      11: invokevirtual #4                  // Method getOrigin:()Lorg/hibernate/boot/jaxb/Origin;
      14: iconst_1
      15: invokestatic  #5                  // Method org/hibernate/boot/jaxb/internal/InputStreamXmlSource.doBind:(Lorg/hibernate/boot/jaxb/spi/Binder;Ljava/io/InputStream;Lorg/hibernate/boot/jaxb/Origin;Z)Lorg/hibernate/boot/jaxb/spi/Binding;
      18: areturn
      19: astore_2
      20: new           #7                  // class org/hibernate/boot/MappingNotFoundException
      23: dup
      24: ldc           #8                  // String Invalid URL
      26: aload_2
      27: aload_0
      28: invokevirtual #4                  // Method getOrigin:()Lorg/hibernate/boot/jaxb/Origin;
      31: invokespecial #9                  // Method org/hibernate/boot/MappingNotFoundException."<init>":(Ljava/lang/String;Ljava/lang/Throwable;Lorg/hibernate/boot/jaxb/Origin;)V
      34: athrow
      35: astore_2
      36: new           #11                 // class org/hibernate/boot/MappingException
      39: dup
      40: ldc           #12                 // String Unable to open URL InputStream
      42: aload_2
      43: aload_0
      44: invokevirtual #4                  // Method getOrigin:()Lorg/hibernate/boot/jaxb/Origin;
      47: invokespecial #13                 // Method org/hibernate/boot/MappingException."<init>":(Ljava/lang/String;Ljava/lang/Throwable;Lorg/hibernate/boot/jaxb/Origin;)V
      50: athrow
    Exception table:
       from    to  target type
           0    18    19   Class java/net/UnknownHostException
           0    18    35   Class java/io/IOException
}
