Compiled from "InvocationPattern.java"
public final class org.apache.axis2.jaxws.core.controller.InvocationPattern extends java.lang.Enum<org.apache.axis2.jaxws.core.controller.InvocationPattern> {
  public static final org.apache.axis2.jaxws.core.controller.InvocationPattern SYNC;

  public static final org.apache.axis2.jaxws.core.controller.InvocationPattern ONEWAY;

  public static final org.apache.axis2.jaxws.core.controller.InvocationPattern ASYNC_CALLBACK;

  public static final org.apache.axis2.jaxws.core.controller.InvocationPattern ASYNC_POLLING;

  private static final org.apache.axis2.jaxws.core.controller.InvocationPattern[] $VALUES;

  public static org.apache.axis2.jaxws.core.controller.InvocationPattern[] values();
    Code:
       0: getstatic     #1                  // Field $VALUES:[Lorg/apache/axis2/jaxws/core/controller/InvocationPattern;
       3: invokevirtual #2                  // Method "[Lorg/apache/axis2/jaxws/core/controller/InvocationPattern;".clone:()Ljava/lang/Object;
       6: checkcast     #3                  // class "[Lorg/apache/axis2/jaxws/core/controller/InvocationPattern;"
       9: areturn

  public static org.apache.axis2.jaxws.core.controller.InvocationPattern valueOf(java.lang.String);
    Code:
       0: ldc           #4                  // class org/apache/axis2/jaxws/core/controller/InvocationPattern
       2: aload_0
       3: invokestatic  #5                  // Method java/lang/Enum.valueOf:(Ljava/lang/Class;Ljava/lang/String;)Ljava/lang/Enum;
       6: checkcast     #4                  // class org/apache/axis2/jaxws/core/controller/InvocationPattern
       9: areturn

  private org.apache.axis2.jaxws.core.controller.InvocationPattern();
    Code:
       0: aload_0
       1: aload_1
       2: iload_2
       3: invokespecial #6                  // Method java/lang/Enum."<init>":(Ljava/lang/String;I)V
       6: return

  static {};
    Code:
       0: new           #4                  // class org/apache/axis2/jaxws/core/controller/InvocationPattern
       3: dup
       4: ldc           #7                  // String SYNC
       6: iconst_0
       7: invokespecial #8                  // Method "<init>":(Ljava/lang/String;I)V
      10: putstatic     #9                  // Field SYNC:Lorg/apache/axis2/jaxws/core/controller/InvocationPattern;
      13: new           #4                  // class org/apache/axis2/jaxws/core/controller/InvocationPattern
      16: dup
      17: ldc           #10                 // String ONEWAY
      19: iconst_1
      20: invokespecial #8                  // Method "<init>":(Ljava/lang/String;I)V
      23: putstatic     #11                 // Field ONEWAY:Lorg/apache/axis2/jaxws/core/controller/InvocationPattern;
      26: new           #4                  // class org/apache/axis2/jaxws/core/controller/InvocationPattern
      29: dup
      30: ldc           #12                 // String ASYNC_CALLBACK
      32: iconst_2
      33: invokespecial #8                  // Method "<init>":(Ljava/lang/String;I)V
      36: putstatic     #13                 // Field ASYNC_CALLBACK:Lorg/apache/axis2/jaxws/core/controller/InvocationPattern;
      39: new           #4                  // class org/apache/axis2/jaxws/core/controller/InvocationPattern
      42: dup
      43: ldc           #14                 // String ASYNC_POLLING
      45: iconst_3
      46: invokespecial #8                  // Method "<init>":(Ljava/lang/String;I)V
      49: putstatic     #15                 // Field ASYNC_POLLING:Lorg/apache/axis2/jaxws/core/controller/InvocationPattern;
      52: iconst_4
      53: anewarray     #4                  // class org/apache/axis2/jaxws/core/controller/InvocationPattern
      56: dup
      57: iconst_0
      58: getstatic     #9                  // Field SYNC:Lorg/apache/axis2/jaxws/core/controller/InvocationPattern;
      61: aastore
      62: dup
      63: iconst_1
      64: getstatic     #11                 // Field ONEWAY:Lorg/apache/axis2/jaxws/core/controller/InvocationPattern;
      67: aastore
      68: dup
      69: iconst_2
      70: getstatic     #13                 // Field ASYNC_CALLBACK:Lorg/apache/axis2/jaxws/core/controller/InvocationPattern;
      73: aastore
      74: dup
      75: iconst_3
      76: getstatic     #15                 // Field ASYNC_POLLING:Lorg/apache/axis2/jaxws/core/controller/InvocationPattern;
      79: aastore
      80: putstatic     #1                  // Field $VALUES:[Lorg/apache/axis2/jaxws/core/controller/InvocationPattern;
      83: return
}
