Compiled from "WebSetupSteps.java"
public class ru.sbtqa.tag.pagefactory.web.junit.WebSetupSteps {
  static final java.lang.ThreadLocal<ru.sbtqa.tag.pagefactory.web.drivers.WebDriverService> storage;

  static {};
    Code:
       0: invokedynamic #12,  0             // InvokeDynamic #0:get:()Ljava/util/function/Supplier;
       5: invokestatic  #16                 // Method java/lang/ThreadLocal.withInitial:(Ljava/util/function/Supplier;)Ljava/lang/ThreadLocal;
       8: putstatic     #22                 // Field storage:Ljava/lang/ThreadLocal;
      11: return

  private ru.sbtqa.tag.pagefactory.web.junit.WebSetupSteps();
    Code:
       0: aload_0
       1: invokespecial #28                 // Method java/lang/Object."<init>":()V
       4: return

  public static synchronized void initWeb();
    Code:
       0: invokestatic  #33                 // Method ru/sbtqa/tag/pagefactory/PageManager.cachePages:()V
       3: invokestatic  #38                 // Method ru/sbtqa/tag/pagefactory/environment/Environment.isDriverEmpty:()Z
       6: ifne          18
       9: invokestatic  #44                 // Method ru/sbtqa/tag/pagefactory/environment/Environment.getDriverService:()Lru/sbtqa/tag/pagefactory/drivers/DriverService;
      12: instanceof    #48                 // class ru/sbtqa/tag/pagefactory/web/drivers/WebDriverService
      15: ifne          30
      18: getstatic     #22                 // Field storage:Ljava/lang/ThreadLocal;
      21: invokevirtual #50                 // Method java/lang/ThreadLocal.get:()Ljava/lang/Object;
      24: checkcast     #53                 // class ru/sbtqa/tag/pagefactory/drivers/DriverService
      27: invokestatic  #55                 // Method ru/sbtqa/tag/pagefactory/environment/Environment.setDriverService:(Lru/sbtqa/tag/pagefactory/drivers/DriverService;)V
      30: return

  public static synchronized void disposeWeb();
    Code:
       0: new           #61                 // class ru/sbtqa/tag/pagefactory/web/tasks/KillAlertTask
       3: dup
       4: invokespecial #63                 // Method ru/sbtqa/tag/pagefactory/web/tasks/KillAlertTask."<init>":()V
       7: invokestatic  #64                 // Method ru/sbtqa/tag/pagefactory/tasks/TaskHandler.addTask:(Lru/sbtqa/tag/pagefactory/tasks/Task;)V
      10: return
}
