Compiled from "ClassloadingUtility.java"
public class com.arjuna.common.internal.util.ClassloadingUtility {
  private static final char BREAKCHARACTER;

  public com.arjuna.common.internal.util.ClassloadingUtility();
    Code:
       0: aload_0
       1: invokespecial #1                  // Method java/lang/Object."<init>":()V
       4: return

  public static java.lang.Class loadClass(java.lang.String);
    Code:
       0: aload_0
       1: invokestatic  #2                  // Method java/lang/Class.forName:(Ljava/lang/String;)Ljava/lang/Class;
       4: astore_1
       5: goto          21
       8: astore_2
       9: getstatic     #4                  // Field com/arjuna/common/logging/commonLogger.i18NLogger:Lcom/arjuna/common/logging/commonI18NLogger;
      12: aload_0
      13: aload_2
      14: invokeinterface #5,  3            // InterfaceMethod com/arjuna/common/logging/commonI18NLogger.warn_common_ClassloadingUtility_2:(Ljava/lang/String;Ljava/lang/Throwable;)V
      19: aconst_null
      20: areturn
      21: aload_1
      22: areturn
    Exception table:
       from    to  target type
           0     5     8   Class java/lang/ClassNotFoundException

  public static <T> java.lang.Class<? extends T> loadClass(java.lang.Class<T>, java.lang.String);
    Code:
       0: getstatic     #6                  // Field com/arjuna/common/logging/commonLogger.logger:Lorg/jboss/logging/Logger;
       3: invokevirtual #7                  // Method org/jboss/logging/Logger.isTraceEnabled:()Z
       6: ifeq          34
       9: getstatic     #6                  // Field com/arjuna/common/logging/commonLogger.logger:Lorg/jboss/logging/Logger;
      12: new           #8                  // class java/lang/StringBuilder
      15: dup
      16: invokespecial #9                  // Method java/lang/StringBuilder."<init>":()V
      19: ldc           #10                 // String Loading class
      21: invokevirtual #11                 // Method java/lang/StringBuilder.append:(Ljava/lang/String;)Ljava/lang/StringBuilder;
      24: aload_1
      25: invokevirtual #11                 // Method java/lang/StringBuilder.append:(Ljava/lang/String;)Ljava/lang/StringBuilder;
      28: invokevirtual #12                 // Method java/lang/StringBuilder.toString:()Ljava/lang/String;
      31: invokevirtual #13                 // Method org/jboss/logging/Logger.trace:(Ljava/lang/Object;)V
      34: aload_1
      35: ifnonnull     48
      38: getstatic     #4                  // Field com/arjuna/common/logging/commonLogger.i18NLogger:Lcom/arjuna/common/logging/commonI18NLogger;
      41: invokeinterface #14,  1           // InterfaceMethod com/arjuna/common/logging/commonI18NLogger.warn_common_ClassloadingUtility_1:()V
      46: aconst_null
      47: areturn
      48: aload_1
      49: invokestatic  #15                 // Method loadClass:(Ljava/lang/String;)Ljava/lang/Class;
      52: astore_2
      53: aload_2
      54: ifnonnull     59
      57: aconst_null
      58: areturn
      59: aload_2
      60: aload_0
      61: invokevirtual #16                 // Method java/lang/Class.asSubclass:(Ljava/lang/Class;)Ljava/lang/Class;
      64: astore_3
      65: aload_3
      66: areturn
      67: astore_3
      68: getstatic     #4                  // Field com/arjuna/common/logging/commonLogger.i18NLogger:Lcom/arjuna/common/logging/commonI18NLogger;
      71: aload_1
      72: aload_0
      73: invokevirtual #18                 // Method java/lang/Class.getName:()Ljava/lang/String;
      76: aload_3
      77: invokeinterface #19,  4           // InterfaceMethod com/arjuna/common/logging/commonI18NLogger.warn_common_ClassloadingUtility_3:(Ljava/lang/String;Ljava/lang/String;Ljava/lang/Throwable;)V
      82: aconst_null
      83: areturn
    Exception table:
       from    to  target type
          59    66    67   Class java/lang/ClassCastException

  public static <T> T loadAndInstantiateClass(java.lang.Class<T>, java.lang.String, java.lang.String);
    Code:
       0: aconst_null
       1: astore_3
       2: aload_0
       3: aload_1
       4: invokestatic  #20                 // Method loadClass:(Ljava/lang/Class;Ljava/lang/String;)Ljava/lang/Class;
       7: astore        4
       9: aload         4
      11: ifnonnull     16
      14: aconst_null
      15: areturn
      16: aload         4
      18: invokevirtual #21                 // Method java/lang/Class.getConstructors:()[Ljava/lang/reflect/Constructor;
      21: astore        5
      23: aconst_null
      24: astore        6
      26: aload         5
      28: astore        7
      30: aload         7
      32: arraylength
      33: istore        8
      35: iconst_0
      36: istore        9
      38: iload         9
      40: iload         8
      42: if_icmpge     121
      45: aload         7
      47: iload         9
      49: aaload
      50: astore        10
      52: aload         10
      54: invokevirtual #22                 // Method java/lang/reflect/Constructor.getParameterTypes:()[Ljava/lang/Class;
      57: arraylength
      58: iconst_1
      59: if_icmpne     115
      62: aload         10
      64: invokevirtual #22                 // Method java/lang/reflect/Constructor.getParameterTypes:()[Ljava/lang/Class;
      67: iconst_0
      68: aaload
      69: invokevirtual #23                 // Method java/lang/Class.getCanonicalName:()Ljava/lang/String;
      72: ldc           #24                 // String EnvironmentBean
      74: invokevirtual #25                 // Method java/lang/String.endsWith:(Ljava/lang/String;)Z
      77: ifeq          115
      80: aload         10
      82: invokevirtual #22                 // Method java/lang/reflect/Constructor.getParameterTypes:()[Ljava/lang/Class;
      85: iconst_0
      86: aaload
      87: astore        6
      89: aload         6
      91: aload_2
      92: invokestatic  #26                 // Method com/arjuna/common/internal/util/propertyservice/BeanPopulator.getNamedInstance:(Ljava/lang/Class;Ljava/lang/String;)Ljava/lang/Object;
      95: astore        11
      97: aload         10
      99: iconst_1
     100: anewarray     #27                 // class java/lang/Object
     103: dup
     104: iconst_0
     105: aload         11
     107: aastore
     108: invokevirtual #28                 // Method java/lang/reflect/Constructor.newInstance:([Ljava/lang/Object;)Ljava/lang/Object;
     111: astore_3
     112: goto          121
     115: iinc          9, 1
     118: goto          38
     121: aload         6
     123: ifnonnull     136
     126: aload_2
     127: ifnonnull     136
     130: aload         4
     132: invokevirtual #29                 // Method java/lang/Class.newInstance:()Ljava/lang/Object;
     135: astore_3
     136: goto          184
     139: astore        4
     141: getstatic     #4                  // Field com/arjuna/common/logging/commonLogger.i18NLogger:Lcom/arjuna/common/logging/commonI18NLogger;
     144: aload_1
     145: aload         4
     147: invokeinterface #31,  3           // InterfaceMethod com/arjuna/common/logging/commonI18NLogger.warn_common_ClassloadingUtility_4:(Ljava/lang/String;Ljava/lang/Throwable;)V
     152: goto          184
     155: astore        4
     157: getstatic     #4                  // Field com/arjuna/common/logging/commonLogger.i18NLogger:Lcom/arjuna/common/logging/commonI18NLogger;
     160: aload_1
     161: aload         4
     163: invokeinterface #33,  3           // InterfaceMethod com/arjuna/common/logging/commonI18NLogger.warn_common_ClassloadingUtility_5:(Ljava/lang/String;Ljava/lang/Throwable;)V
     168: goto          184
     171: astore        4
     173: getstatic     #4                  // Field com/arjuna/common/logging/commonLogger.i18NLogger:Lcom/arjuna/common/logging/commonI18NLogger;
     176: aload_1
     177: aload         4
     179: invokeinterface #31,  3           // InterfaceMethod com/arjuna/common/logging/commonI18NLogger.warn_common_ClassloadingUtility_4:(Ljava/lang/String;Ljava/lang/Throwable;)V
     184: aload_3
     185: areturn
    Exception table:
       from    to  target type
           2    15   139   Class java/lang/InstantiationException
          16   136   139   Class java/lang/InstantiationException
           2    15   155   Class java/lang/IllegalAccessException
          16   136   155   Class java/lang/IllegalAccessException
           2    15   171   Class java/lang/reflect/InvocationTargetException
          16   136   171   Class java/lang/reflect/InvocationTargetException

  public static <T> java.util.List<T> loadAndInstantiateClasses(java.lang.Class<T>, java.util.List<java.lang.String>);
    Code:
       0: new           #35                 // class java/util/ArrayList
       3: dup
       4: invokespecial #36                 // Method java/util/ArrayList."<init>":()V
       7: astore_2
       8: aload_1
       9: ifnull        65
      12: aload_1
      13: invokeinterface #37,  1           // InterfaceMethod java/util/List.iterator:()Ljava/util/Iterator;
      18: astore_3
      19: aload_3
      20: invokeinterface #38,  1           // InterfaceMethod java/util/Iterator.hasNext:()Z
      25: ifeq          65
      28: aload_3
      29: invokeinterface #39,  1           // InterfaceMethod java/util/Iterator.next:()Ljava/lang/Object;
      34: checkcast     #40                 // class java/lang/String
      37: astore        4
      39: aload_0
      40: aload         4
      42: aconst_null
      43: invokestatic  #41                 // Method loadAndInstantiateClass:(Ljava/lang/Class;Ljava/lang/String;Ljava/lang/String;)Ljava/lang/Object;
      46: astore        5
      48: aload         5
      50: ifnull        62
      53: aload_2
      54: aload         5
      56: invokeinterface #42,  2           // InterfaceMethod java/util/List.add:(Ljava/lang/Object;)Z
      61: pop
      62: goto          19
      65: aload_2
      66: areturn

  public static <T> java.util.List<T> loadAndInstantiateClassesWithInit(java.lang.Class<T>, java.util.List<java.lang.String>);
    Code:
       0: new           #35                 // class java/util/ArrayList
       3: dup
       4: invokespecial #36                 // Method java/util/ArrayList."<init>":()V
       7: astore_2
       8: aload_1
       9: ifnull        182
      12: aload_1
      13: invokeinterface #37,  1           // InterfaceMethod java/util/List.iterator:()Ljava/util/Iterator;
      18: astore_3
      19: aload_3
      20: invokeinterface #38,  1           // InterfaceMethod java/util/Iterator.hasNext:()Z
      25: ifeq          182
      28: aload_3
      29: invokeinterface #39,  1           // InterfaceMethod java/util/Iterator.next:()Ljava/lang/Object;
      34: checkcast     #40                 // class java/lang/String
      37: astore        4
      39: aload         4
      41: bipush        59
      43: invokevirtual #44                 // Method java/lang/String.indexOf:(I)I
      46: istore        5
      48: aconst_null
      49: astore        6
      51: aconst_null
      52: astore        7
      54: iload         5
      56: iconst_m1
      57: if_icmpeq     84
      60: aload         4
      62: iconst_0
      63: iload         5
      65: invokevirtual #45                 // Method java/lang/String.substring:(II)Ljava/lang/String;
      68: astore        6
      70: aload         4
      72: iload         5
      74: iconst_1
      75: iadd
      76: invokevirtual #46                 // Method java/lang/String.substring:(I)Ljava/lang/String;
      79: astore        7
      81: goto          88
      84: aload         4
      86: astore        6
      88: aload_0
      89: aload         6
      91: aconst_null
      92: invokestatic  #41                 // Method loadAndInstantiateClass:(Ljava/lang/Class;Ljava/lang/String;Ljava/lang/String;)Ljava/lang/Object;
      95: astore        8
      97: aload         6
      99: ifnull        165
     102: aload         7
     104: ifnull        165
     107: aload         8
     109: invokevirtual #47                 // Method java/lang/Object.getClass:()Ljava/lang/Class;
     112: ldc           #48                 // String initialise
     114: iconst_1
     115: anewarray     #49                 // class java/lang/Class
     118: dup
     119: iconst_0
     120: ldc           #40                 // class java/lang/String
     122: aastore
     123: invokevirtual #50                 // Method java/lang/Class.getMethod:(Ljava/lang/String;[Ljava/lang/Class;)Ljava/lang/reflect/Method;
     126: astore        9
     128: aload         9
     130: aload         8
     132: iconst_1
     133: anewarray     #27                 // class java/lang/Object
     136: dup
     137: iconst_0
     138: aload         7
     140: aastore
     141: invokevirtual #51                 // Method java/lang/reflect/Method.invoke:(Ljava/lang/Object;[Ljava/lang/Object;)Ljava/lang/Object;
     144: pop
     145: goto          165
     148: astore        9
     150: getstatic     #4                  // Field com/arjuna/common/logging/commonLogger.i18NLogger:Lcom/arjuna/common/logging/commonI18NLogger;
     153: aload         4
     155: aload         9
     157: invokeinterface #53,  3           // InterfaceMethod com/arjuna/common/logging/commonI18NLogger.warn_common_ClassloadingUtility_6:(Ljava/lang/String;Ljava/lang/Throwable;)V
     162: goto          19
     165: aload         8
     167: ifnull        179
     170: aload_2
     171: aload         8
     173: invokeinterface #42,  2           // InterfaceMethod java/util/List.add:(Ljava/lang/Object;)Z
     178: pop
     179: goto          19
     182: aload_2
     183: areturn
    Exception table:
       from    to  target type
         107   145   148   Class java/lang/Exception

  public static java.lang.String getNameForClass(java.lang.Object);
    Code:
       0: aload_0
       1: ifnonnull     6
       4: aconst_null
       5: areturn
       6: aload_0
       7: invokevirtual #47                 // Method java/lang/Object.getClass:()Ljava/lang/Class;
      10: invokevirtual #18                 // Method java/lang/Class.getName:()Ljava/lang/String;
      13: areturn

  public static java.util.List<java.lang.String> getNamesForClasses(java.util.List<? extends java.lang.Object>);
    Code:
       0: new           #35                 // class java/util/ArrayList
       3: dup
       4: invokespecial #36                 // Method java/util/ArrayList."<init>":()V
       7: astore_1
       8: aload_0
       9: ifnull        58
      12: aload_0
      13: invokeinterface #37,  1           // InterfaceMethod java/util/List.iterator:()Ljava/util/Iterator;
      18: astore_2
      19: aload_2
      20: invokeinterface #38,  1           // InterfaceMethod java/util/Iterator.hasNext:()Z
      25: ifeq          58
      28: aload_2
      29: invokeinterface #39,  1           // InterfaceMethod java/util/Iterator.next:()Ljava/lang/Object;
      34: astore_3
      35: aload_3
      36: invokestatic  #54                 // Method getNameForClass:(Ljava/lang/Object;)Ljava/lang/String;
      39: astore        4
      41: aload         4
      43: ifnull        55
      46: aload_1
      47: aload         4
      49: invokeinterface #42,  2           // InterfaceMethod java/util/List.add:(Ljava/lang/Object;)Z
      54: pop
      55: goto          19
      58: aload_1
      59: areturn
}
