Compiled from "FixedByteArraySaltGenerator.java"
public class org.jasypt.salt.FixedByteArraySaltGenerator implements org.jasypt.salt.SaltGenerator {
  private byte[] salt;

  public org.jasypt.salt.FixedByteArraySaltGenerator();
    Code:
       0: aload_0
       1: invokespecial #1                  // Method java/lang/Object."<init>":()V
       4: aload_0
       5: aconst_null
       6: putfield      #2                  // Field salt:[B
       9: return

  public synchronized void setSalt(byte[]);
    Code:
       0: aload_1
       1: ldc           #3                  // String Salt cannot be set null
       3: invokestatic  #4                  // Method org/jasypt/commons/CommonUtils.validateNotNull:(Ljava/lang/Object;Ljava/lang/String;)V
       6: aload_0
       7: aload_1
       8: invokevirtual #5                  // Method java/lang/Object.clone:()Ljava/lang/Object;
      11: checkcast     #6                  // class "[B"
      14: checkcast     #6                  // class "[B"
      17: putfield      #2                  // Field salt:[B
      20: return

  public byte[] generateSalt(int);
    Code:
       0: aload_0
       1: getfield      #2                  // Field salt:[B
       4: ifnonnull     17
       7: new           #7                  // class org/jasypt/exceptions/EncryptionInitializationException
      10: dup
      11: ldc           #8                  // String Salt has not been set
      13: invokespecial #9                  // Method org/jasypt/exceptions/EncryptionInitializationException."<init>":(Ljava/lang/String;)V
      16: athrow
      17: aload_0
      18: getfield      #2                  // Field salt:[B
      21: arraylength
      22: iload_1
      23: if_icmpge     36
      26: new           #7                  // class org/jasypt/exceptions/EncryptionInitializationException
      29: dup
      30: ldc           #10                 // String Requested salt larger than set
      32: invokespecial #9                  // Method org/jasypt/exceptions/EncryptionInitializationException."<init>":(Ljava/lang/String;)V
      35: athrow
      36: iload_1
      37: newarray       byte
      39: astore_2
      40: aload_0
      41: getfield      #2                  // Field salt:[B
      44: iconst_0
      45: aload_2
      46: iconst_0
      47: iload_1
      48: invokestatic  #11                 // Method java/lang/System.arraycopy:(Ljava/lang/Object;ILjava/lang/Object;II)V
      51: aload_2
      52: areturn

  public boolean includePlainSaltInEncryptionResults();
    Code:
       0: iconst_0
       1: ireturn
}
