Compiled from "ReplicationHandler2.java"
public class net.openhft.chronicle.engine.server.internal.ReplicationHandler2<E> extends net.openhft.chronicle.engine.server.internal.AbstractHandler {
  private static final org.slf4j.Logger LOG;

  private final java.lang.StringBuilder eventName;

  private net.openhft.chronicle.engine.api.pubsub.Replication replication;

  private net.openhft.chronicle.network.connection.WireOutPublisher publisher;

  private net.openhft.chronicle.engine.tree.HostIdentifier hostId;

  private long tid;

  private boolean isAcceptor;

  private net.openhft.chronicle.core.threads.EventLoop eventLoop;

  private byte remoteIdentifier;

  private byte localIdentifier;

  private net.openhft.chronicle.engine.api.tree.RequestContext requestContext;

  private long cid;

  private final java.util.function.BiConsumer<net.openhft.chronicle.wire.WireIn, java.lang.Long> dataConsumer;

  public net.openhft.chronicle.engine.server.internal.ReplicationHandler2();
    Code:
       0: aload_0
       1: invokespecial #13                 // Method net/openhft/chronicle/engine/server/internal/AbstractHandler."<init>":()V
       4: aload_0
       5: new           #14                 // class java/lang/StringBuilder
       8: dup
       9: invokespecial #15                 // Method java/lang/StringBuilder."<init>":()V
      12: putfield      #12                 // Field eventName:Ljava/lang/StringBuilder;
      15: aload_0
      16: new           #16                 // class net/openhft/chronicle/engine/server/internal/ReplicationHandler2$1
      19: dup
      20: aload_0
      21: invokespecial #17                 // Method net/openhft/chronicle/engine/server/internal/ReplicationHandler2$1."<init>":(Lnet/openhft/chronicle/engine/server/internal/ReplicationHandler2;)V
      24: putfield      #18                 // Field dataConsumer:Ljava/util/function/BiConsumer;
      27: return

  void process(net.openhft.chronicle.wire.WireIn, net.openhft.chronicle.network.connection.WireOutPublisher, long, net.openhft.chronicle.wire.Wire, net.openhft.chronicle.engine.tree.HostIdentifier, net.openhft.chronicle.engine.api.pubsub.Replication, net.openhft.chronicle.core.threads.EventLoop, boolean, byte, net.openhft.chronicle.engine.api.tree.RequestContext, long, byte);
    Code:
       0: aload_0
       1: aload         8
       3: putfield      #7                  // Field eventLoop:Lnet/openhft/chronicle/core/threads/EventLoop;
       6: aload_0
       7: iload         9
       9: putfield      #8                  // Field isAcceptor:Z
      12: aload_0
      13: aload         5
      15: invokevirtual #19                 // Method setOutWire:(Lnet/openhft/chronicle/wire/WireOut;)V
      18: aload_0
      19: iload         14
      21: putfield      #6                  // Field localIdentifier:B
      24: aload_0
      25: aload         6
      27: putfield      #5                  // Field hostId:Lnet/openhft/chronicle/engine/tree/HostIdentifier;
      30: aload_0
      31: aload_2
      32: putfield      #1                  // Field publisher:Lnet/openhft/chronicle/network/connection/WireOutPublisher;
      35: aload_0
      36: aload         7
      38: putfield      #10                 // Field replication:Lnet/openhft/chronicle/engine/api/pubsub/Replication;
      41: aload_0
      42: lload_3
      43: putfield      #4                  // Field tid:J
      46: aload_0
      47: iload         10
      49: putfield      #9                  // Field remoteIdentifier:B
      52: aload_0
      53: aload         11
      55: putfield      #3                  // Field requestContext:Lnet/openhft/chronicle/engine/api/tree/RequestContext;
      58: aload_0
      59: lload         12
      61: putfield      #2                  // Field cid:J
      64: aload_0
      65: getfield      #18                 // Field dataConsumer:Ljava/util/function/BiConsumer;
      68: aload_1
      69: lload_3
      70: invokestatic  #20                 // Method java/lang/Long.valueOf:(J)Ljava/lang/Long;
      73: invokeinterface #21,  3           // InterfaceMethod java/util/function/BiConsumer.accept:(Ljava/lang/Object;Ljava/lang/Object;)V
      78: return

  static java.lang.StringBuilder access$000(net.openhft.chronicle.engine.server.internal.ReplicationHandler2);
    Code:
       0: aload_0
       1: getfield      #12                 // Field eventName:Ljava/lang/StringBuilder;
       4: areturn

  static org.slf4j.Logger access$100();
    Code:
       0: getstatic     #11                 // Field LOG:Lorg/slf4j/Logger;
       3: areturn

  static net.openhft.chronicle.engine.api.pubsub.Replication access$200(net.openhft.chronicle.engine.server.internal.ReplicationHandler2);
    Code:
       0: aload_0
       1: getfield      #10                 // Field replication:Lnet/openhft/chronicle/engine/api/pubsub/Replication;
       4: areturn

  static byte access$300(net.openhft.chronicle.engine.server.internal.ReplicationHandler2);
    Code:
       0: aload_0
       1: getfield      #9                  // Field remoteIdentifier:B
       4: ireturn

  static boolean access$400(net.openhft.chronicle.engine.server.internal.ReplicationHandler2);
    Code:
       0: aload_0
       1: getfield      #8                  // Field isAcceptor:Z
       4: ireturn

  static net.openhft.chronicle.core.threads.EventLoop access$500(net.openhft.chronicle.engine.server.internal.ReplicationHandler2);
    Code:
       0: aload_0
       1: getfield      #7                  // Field eventLoop:Lnet/openhft/chronicle/core/threads/EventLoop;
       4: areturn

  static byte access$600(net.openhft.chronicle.engine.server.internal.ReplicationHandler2);
    Code:
       0: aload_0
       1: getfield      #6                  // Field localIdentifier:B
       4: ireturn

  static net.openhft.chronicle.engine.tree.HostIdentifier access$700(net.openhft.chronicle.engine.server.internal.ReplicationHandler2);
    Code:
       0: aload_0
       1: getfield      #5                  // Field hostId:Lnet/openhft/chronicle/engine/tree/HostIdentifier;
       4: areturn

  static long access$800(net.openhft.chronicle.engine.server.internal.ReplicationHandler2);
    Code:
       0: aload_0
       1: getfield      #4                  // Field tid:J
       4: lreturn

  static net.openhft.chronicle.engine.api.tree.RequestContext access$900(net.openhft.chronicle.engine.server.internal.ReplicationHandler2);
    Code:
       0: aload_0
       1: getfield      #3                  // Field requestContext:Lnet/openhft/chronicle/engine/api/tree/RequestContext;
       4: areturn

  static long access$1000(net.openhft.chronicle.engine.server.internal.ReplicationHandler2);
    Code:
       0: aload_0
       1: getfield      #2                  // Field cid:J
       4: lreturn

  static net.openhft.chronicle.network.connection.WireOutPublisher access$1100(net.openhft.chronicle.engine.server.internal.ReplicationHandler2);
    Code:
       0: aload_0
       1: getfield      #1                  // Field publisher:Lnet/openhft/chronicle/network/connection/WireOutPublisher;
       4: areturn

  static {};
    Code:
       0: ldc           #22                 // class net/openhft/chronicle/engine/server/internal/ReplicationHandler2
       2: invokestatic  #23                 // Method org/slf4j/LoggerFactory.getLogger:(Ljava/lang/Class;)Lorg/slf4j/Logger;
       5: putstatic     #11                 // Field LOG:Lorg/slf4j/Logger;
       8: return
}
