Compiled from "ConfigurationCustomizer.java"
class org.sonatype.nexus.httpclient.config.ConfigurationCustomizer$1 implements com.google.common.base.Function<java.lang.String, java.lang.String> {
  org.sonatype.nexus.httpclient.config.ConfigurationCustomizer$1();
    Code:
       0: aload_0
       1: invokespecial #10                 // Method java/lang/Object."<init>":()V
       4: return

  public java.lang.String apply(java.lang.String);
    Code:
       0: new           #18                 // class java/lang/StringBuilder
       3: dup
       4: ldc           #20                 // String (
       6: invokespecial #22                 // Method java/lang/StringBuilder."<init>":(Ljava/lang/String;)V
       9: aload_1
      10: getstatic     #25                 // Field java/util/Locale.US:Ljava/util/Locale;
      13: invokevirtual #31                 // Method java/lang/String.toLowerCase:(Ljava/util/Locale;)Ljava/lang/String;
      16: ldc           #37                 // String \\.
      18: ldc           #39                 // String \\\\.
      20: invokevirtual #41                 // Method java/lang/String.replaceAll:(Ljava/lang/String;Ljava/lang/String;)Ljava/lang/String;
      23: ldc           #45                 // String \\*
      25: ldc           #47                 // String .*?
      27: invokevirtual #41                 // Method java/lang/String.replaceAll:(Ljava/lang/String;Ljava/lang/String;)Ljava/lang/String;
      30: ldc           #49                 // String \\[
      32: ldc           #51                 // String \\\\[
      34: invokevirtual #41                 // Method java/lang/String.replaceAll:(Ljava/lang/String;Ljava/lang/String;)Ljava/lang/String;
      37: ldc           #53                 // String \\]
      39: ldc           #55                 // String \\\\]
      41: invokevirtual #41                 // Method java/lang/String.replaceAll:(Ljava/lang/String;Ljava/lang/String;)Ljava/lang/String;
      44: invokevirtual #57                 // Method java/lang/StringBuilder.append:(Ljava/lang/String;)Ljava/lang/StringBuilder;
      47: ldc           #61                 // String )
      49: invokevirtual #57                 // Method java/lang/StringBuilder.append:(Ljava/lang/String;)Ljava/lang/StringBuilder;
      52: invokevirtual #63                 // Method java/lang/StringBuilder.toString:()Ljava/lang/String;
      55: areturn

  public java.lang.Object apply(java.lang.Object);
    Code:
       0: aload_0
       1: aload_1
       2: checkcast     #32                 // class java/lang/String
       5: invokevirtual #70                 // Method apply:(Ljava/lang/String;)Ljava/lang/String;
       8: areturn
}
