Compiled from "TargetMethodAnnotationDrivenBinder.java"
public class org.modelmapper.internal.bytebuddy.implementation.bind.annotation.TargetMethodAnnotationDrivenBinder$DelegationProcessor$Handler$Bound<T extends java.lang.annotation.Annotation> implements org.modelmapper.internal.bytebuddy.implementation.bind.annotation.TargetMethodAnnotationDrivenBinder$DelegationProcessor$Handler {
  private final org.modelmapper.internal.bytebuddy.description.method.ParameterDescription target;

  private final org.modelmapper.internal.bytebuddy.implementation.bind.annotation.TargetMethodAnnotationDrivenBinder$ParameterBinder<T> parameterBinder;

  private final org.modelmapper.internal.bytebuddy.description.annotation.AnnotationDescription$Loadable<T> annotation;

  private final org.modelmapper.internal.bytebuddy.implementation.bytecode.assign.Assigner$Typing typing;

  protected org.modelmapper.internal.bytebuddy.implementation.bind.annotation.TargetMethodAnnotationDrivenBinder$DelegationProcessor$Handler$Bound(org.modelmapper.internal.bytebuddy.description.method.ParameterDescription, org.modelmapper.internal.bytebuddy.implementation.bind.annotation.TargetMethodAnnotationDrivenBinder$ParameterBinder<T>, org.modelmapper.internal.bytebuddy.description.annotation.AnnotationDescription$Loadable<T>, org.modelmapper.internal.bytebuddy.implementation.bytecode.assign.Assigner$Typing);
    Code:
       0: aload_0
       1: invokespecial #59                 // Method java/lang/Object."<init>":()V
       4: aload_0
       5: aload_1
       6: putfield      #61                 // Field target:Lorg/modelmapper/internal/bytebuddy/description/method/ParameterDescription;
       9: aload_0
      10: aload_2
      11: putfield      #63                 // Field parameterBinder:Lorg/modelmapper/internal/bytebuddy/implementation/bind/annotation/TargetMethodAnnotationDrivenBinder$ParameterBinder;
      14: aload_0
      15: aload_3
      16: putfield      #65                 // Field annotation:Lorg/modelmapper/internal/bytebuddy/description/annotation/AnnotationDescription$Loadable;
      19: aload_0
      20: aload         4
      22: putfield      #67                 // Field typing:Lorg/modelmapper/internal/bytebuddy/implementation/bytecode/assign/Assigner$Typing;
      25: return

  protected static org.modelmapper.internal.bytebuddy.implementation.bind.annotation.TargetMethodAnnotationDrivenBinder$DelegationProcessor$Handler of(org.modelmapper.internal.bytebuddy.description.method.ParameterDescription, org.modelmapper.internal.bytebuddy.implementation.bind.annotation.TargetMethodAnnotationDrivenBinder$ParameterBinder<?>, org.modelmapper.internal.bytebuddy.description.annotation.AnnotationDescription, org.modelmapper.internal.bytebuddy.implementation.bytecode.assign.Assigner$Typing);
    Code:
       0: new           #2                  // class org/modelmapper/internal/bytebuddy/implementation/bind/annotation/TargetMethodAnnotationDrivenBinder$DelegationProcessor$Handler$Bound
       3: dup
       4: aload_0
       5: aload_1
       6: aload_2
       7: aload_1
       8: invokeinterface #76,  1           // InterfaceMethod org/modelmapper/internal/bytebuddy/implementation/bind/annotation/TargetMethodAnnotationDrivenBinder$ParameterBinder.getHandledType:()Ljava/lang/Class;
      13: invokeinterface #80,  2           // InterfaceMethod org/modelmapper/internal/bytebuddy/description/annotation/AnnotationDescription.prepare:(Ljava/lang/Class;)Lorg/modelmapper/internal/bytebuddy/description/annotation/AnnotationDescription$Loadable;
      18: aload_3
      19: invokespecial #82                 // Method "<init>":(Lorg/modelmapper/internal/bytebuddy/description/method/ParameterDescription;Lorg/modelmapper/internal/bytebuddy/implementation/bind/annotation/TargetMethodAnnotationDrivenBinder$ParameterBinder;Lorg/modelmapper/internal/bytebuddy/description/annotation/AnnotationDescription$Loadable;Lorg/modelmapper/internal/bytebuddy/implementation/bytecode/assign/Assigner$Typing;)V
      22: areturn

  public boolean isBound();
    Code:
       0: iconst_1
       1: ireturn

  public org.modelmapper.internal.bytebuddy.implementation.bind.MethodDelegationBinder$ParameterBinding<?> bind(org.modelmapper.internal.bytebuddy.description.method.MethodDescription, org.modelmapper.internal.bytebuddy.implementation.Implementation$Target, org.modelmapper.internal.bytebuddy.implementation.bytecode.assign.Assigner);
    Code:
       0: aload_0
       1: getfield      #63                 // Field parameterBinder:Lorg/modelmapper/internal/bytebuddy/implementation/bind/annotation/TargetMethodAnnotationDrivenBinder$ParameterBinder;
       4: aload_0
       5: getfield      #65                 // Field annotation:Lorg/modelmapper/internal/bytebuddy/description/annotation/AnnotationDescription$Loadable;
       8: aload_1
       9: aload_0
      10: getfield      #61                 // Field target:Lorg/modelmapper/internal/bytebuddy/description/method/ParameterDescription;
      13: aload_2
      14: aload_3
      15: aload_0
      16: getfield      #67                 // Field typing:Lorg/modelmapper/internal/bytebuddy/implementation/bytecode/assign/Assigner$Typing;
      19: invokeinterface #91,  7           // InterfaceMethod org/modelmapper/internal/bytebuddy/implementation/bind/annotation/TargetMethodAnnotationDrivenBinder$ParameterBinder.bind:(Lorg/modelmapper/internal/bytebuddy/description/annotation/AnnotationDescription$Loadable;Lorg/modelmapper/internal/bytebuddy/description/method/MethodDescription;Lorg/modelmapper/internal/bytebuddy/description/method/ParameterDescription;Lorg/modelmapper/internal/bytebuddy/implementation/Implementation$Target;Lorg/modelmapper/internal/bytebuddy/implementation/bytecode/assign/Assigner;Lorg/modelmapper/internal/bytebuddy/implementation/bytecode/assign/Assigner$Typing;)Lorg/modelmapper/internal/bytebuddy/implementation/bind/MethodDelegationBinder$ParameterBinding;
      24: areturn

  public boolean equals(java.lang.Object);
    Code:
       0: aload_0
       1: aload_1
       2: if_acmpne     7
       5: iconst_1
       6: ireturn
       7: aload_1
       8: ifnonnull     13
      11: iconst_0
      12: ireturn
      13: aload_0
      14: invokevirtual #102                // Method java/lang/Object.getClass:()Ljava/lang/Class;
      17: aload_1
      18: invokevirtual #102                // Method java/lang/Object.getClass:()Ljava/lang/Class;
      21: if_acmpeq     26
      24: iconst_0
      25: ireturn
      26: aload_0
      27: getfield      #61                 // Field target:Lorg/modelmapper/internal/bytebuddy/description/method/ParameterDescription;
      30: aload_1
      31: checkcast     #2                  // class org/modelmapper/internal/bytebuddy/implementation/bind/annotation/TargetMethodAnnotationDrivenBinder$DelegationProcessor$Handler$Bound
      34: getfield      #61                 // Field target:Lorg/modelmapper/internal/bytebuddy/description/method/ParameterDescription;
      37: invokeinterface #106,  2          // InterfaceMethod org/modelmapper/internal/bytebuddy/description/method/ParameterDescription.equals:(Ljava/lang/Object;)Z
      42: ifne          47
      45: iconst_0
      46: ireturn
      47: aload_0
      48: getfield      #63                 // Field parameterBinder:Lorg/modelmapper/internal/bytebuddy/implementation/bind/annotation/TargetMethodAnnotationDrivenBinder$ParameterBinder;
      51: aload_1
      52: checkcast     #2                  // class org/modelmapper/internal/bytebuddy/implementation/bind/annotation/TargetMethodAnnotationDrivenBinder$DelegationProcessor$Handler$Bound
      55: getfield      #63                 // Field parameterBinder:Lorg/modelmapper/internal/bytebuddy/implementation/bind/annotation/TargetMethodAnnotationDrivenBinder$ParameterBinder;
      58: invokeinterface #107,  2          // InterfaceMethod org/modelmapper/internal/bytebuddy/implementation/bind/annotation/TargetMethodAnnotationDrivenBinder$ParameterBinder.equals:(Ljava/lang/Object;)Z
      63: ifne          68
      66: iconst_0
      67: ireturn
      68: aload_0
      69: getfield      #65                 // Field annotation:Lorg/modelmapper/internal/bytebuddy/description/annotation/AnnotationDescription$Loadable;
      72: aload_1
      73: checkcast     #2                  // class org/modelmapper/internal/bytebuddy/implementation/bind/annotation/TargetMethodAnnotationDrivenBinder$DelegationProcessor$Handler$Bound
      76: getfield      #65                 // Field annotation:Lorg/modelmapper/internal/bytebuddy/description/annotation/AnnotationDescription$Loadable;
      79: invokeinterface #108,  2          // InterfaceMethod org/modelmapper/internal/bytebuddy/description/annotation/AnnotationDescription$Loadable.equals:(Ljava/lang/Object;)Z
      84: ifne          89
      87: iconst_0
      88: ireturn
      89: aload_0
      90: getfield      #67                 // Field typing:Lorg/modelmapper/internal/bytebuddy/implementation/bytecode/assign/Assigner$Typing;
      93: aload_1
      94: checkcast     #2                  // class org/modelmapper/internal/bytebuddy/implementation/bind/annotation/TargetMethodAnnotationDrivenBinder$DelegationProcessor$Handler$Bound
      97: getfield      #67                 // Field typing:Lorg/modelmapper/internal/bytebuddy/implementation/bytecode/assign/Assigner$Typing;
     100: invokevirtual #109                // Method org/modelmapper/internal/bytebuddy/implementation/bytecode/assign/Assigner$Typing.equals:(Ljava/lang/Object;)Z
     103: ifne          108
     106: iconst_0
     107: ireturn
     108: iconst_1
     109: ireturn

  public int hashCode();
    Code:
       0: bipush        17
       2: bipush        31
       4: imul
       5: aload_0
       6: getfield      #61                 // Field target:Lorg/modelmapper/internal/bytebuddy/description/method/ParameterDescription;
       9: invokeinterface #113,  1          // InterfaceMethod org/modelmapper/internal/bytebuddy/description/method/ParameterDescription.hashCode:()I
      14: iadd
      15: bipush        31
      17: imul
      18: aload_0
      19: getfield      #63                 // Field parameterBinder:Lorg/modelmapper/internal/bytebuddy/implementation/bind/annotation/TargetMethodAnnotationDrivenBinder$ParameterBinder;
      22: invokeinterface #114,  1          // InterfaceMethod org/modelmapper/internal/bytebuddy/implementation/bind/annotation/TargetMethodAnnotationDrivenBinder$ParameterBinder.hashCode:()I
      27: iadd
      28: bipush        31
      30: imul
      31: aload_0
      32: getfield      #65                 // Field annotation:Lorg/modelmapper/internal/bytebuddy/description/annotation/AnnotationDescription$Loadable;
      35: invokeinterface #115,  1          // InterfaceMethod org/modelmapper/internal/bytebuddy/description/annotation/AnnotationDescription$Loadable.hashCode:()I
      40: iadd
      41: bipush        31
      43: imul
      44: aload_0
      45: getfield      #67                 // Field typing:Lorg/modelmapper/internal/bytebuddy/implementation/bytecode/assign/Assigner$Typing;
      48: invokevirtual #116                // Method org/modelmapper/internal/bytebuddy/implementation/bytecode/assign/Assigner$Typing.hashCode:()I
      51: iadd
      52: ireturn
}
