Compiled from "AndroidLog.java"
public class org.flywaydb.core.internal.util.logging.android.AndroidLog implements org.flywaydb.core.internal.util.logging.Log {
  private static final java.lang.String TAG;

  public org.flywaydb.core.internal.util.logging.android.AndroidLog();
    Code:
       0: aload_0
       1: invokespecial #1                  // Method java/lang/Object."<init>":()V
       4: return

  public void debug(java.lang.String);
    Code:
       0: ldc           #3                  // String Flyway
       2: aload_1
       3: invokestatic  #4                  // Method android/util/Log.d:(Ljava/lang/String;Ljava/lang/String;)I
       6: pop
       7: return

  public void info(java.lang.String);
    Code:
       0: ldc           #3                  // String Flyway
       2: aload_1
       3: invokestatic  #5                  // Method android/util/Log.i:(Ljava/lang/String;Ljava/lang/String;)I
       6: pop
       7: return

  public void warn(java.lang.String);
    Code:
       0: ldc           #3                  // String Flyway
       2: aload_1
       3: invokestatic  #6                  // Method android/util/Log.w:(Ljava/lang/String;Ljava/lang/String;)I
       6: pop
       7: return

  public void error(java.lang.String);
    Code:
       0: ldc           #3                  // String Flyway
       2: aload_1
       3: invokestatic  #7                  // Method android/util/Log.e:(Ljava/lang/String;Ljava/lang/String;)I
       6: pop
       7: return

  public void error(java.lang.String, java.lang.Exception);
    Code:
       0: ldc           #3                  // String Flyway
       2: aload_1
       3: aload_2
       4: invokestatic  #8                  // Method android/util/Log.e:(Ljava/lang/String;Ljava/lang/String;Ljava/lang/Throwable;)I
       7: pop
       8: return
}
