Compiled from "AbstractObjectOutput.java"
public abstract class org.jboss.marshalling.AbstractObjectOutput extends org.jboss.marshalling.SimpleDataOutput implements java.io.ObjectOutput {
  protected org.jboss.marshalling.AbstractObjectOutput(int);
    Code:
       0: aload_0
       1: iload_1
       2: invokespecial #1                  // Method org/jboss/marshalling/SimpleDataOutput."<init>":(I)V
       5: return

  protected abstract void doWriteObject(java.lang.Object, boolean) throws java.io.IOException;

  public void writeObjectUnshared(java.lang.Object) throws java.io.IOException;
    Code:
       0: aload_0
       1: aload_1
       2: iconst_1
       3: invokevirtual #2                  // Method doWriteObject:(Ljava/lang/Object;Z)V
       6: return

  public void writeObject(java.lang.Object) throws java.io.IOException;
    Code:
       0: aload_0
       1: aload_1
       2: iconst_0
       3: invokevirtual #2                  // Method doWriteObject:(Ljava/lang/Object;Z)V
       6: return
}
