Compiled from "ObjectOutputStreamMarshaller.java"
public class org.jboss.marshalling.ObjectOutputStreamMarshaller implements org.jboss.marshalling.Marshaller {
  private final java.io.ObjectOutputStream oos;

  public org.jboss.marshalling.ObjectOutputStreamMarshaller(java.io.ObjectOutputStream);
    Code:
       0: aload_0
       1: invokespecial #1                  // Method java/lang/Object."<init>":()V
       4: aload_0
       5: aload_1
       6: putfield      #2                  // Field oos:Ljava/io/ObjectOutputStream;
       9: return

  public void writeObject(java.lang.Object) throws java.io.IOException;
    Code:
       0: aload_0
       1: getfield      #2                  // Field oos:Ljava/io/ObjectOutputStream;
       4: aload_1
       5: invokevirtual #3                  // Method java/io/ObjectOutputStream.writeObject:(Ljava/lang/Object;)V
       8: return

  public void write(int) throws java.io.IOException;
    Code:
       0: aload_0
       1: getfield      #2                  // Field oos:Ljava/io/ObjectOutputStream;
       4: iload_1
       5: invokevirtual #4                  // Method java/io/ObjectOutputStream.write:(I)V
       8: return

  public void write(byte[]) throws java.io.IOException;
    Code:
       0: aload_0
       1: getfield      #2                  // Field oos:Ljava/io/ObjectOutputStream;
       4: aload_1
       5: invokevirtual #5                  // Method java/io/ObjectOutputStream.write:([B)V
       8: return

  public void write(byte[], int, int) throws java.io.IOException;
    Code:
       0: aload_0
       1: getfield      #2                  // Field oos:Ljava/io/ObjectOutputStream;
       4: aload_1
       5: iload_2
       6: iload_3
       7: invokevirtual #6                  // Method java/io/ObjectOutputStream.write:([BII)V
      10: return

  public void flush() throws java.io.IOException;
    Code:
       0: aload_0
       1: getfield      #2                  // Field oos:Ljava/io/ObjectOutputStream;
       4: invokevirtual #7                  // Method java/io/ObjectOutputStream.flush:()V
       7: return

  public void close() throws java.io.IOException;
    Code:
       0: aload_0
       1: getfield      #2                  // Field oos:Ljava/io/ObjectOutputStream;
       4: invokevirtual #8                  // Method java/io/ObjectOutputStream.close:()V
       7: return

  public void writeBoolean(boolean) throws java.io.IOException;
    Code:
       0: aload_0
       1: getfield      #2                  // Field oos:Ljava/io/ObjectOutputStream;
       4: iload_1
       5: invokevirtual #9                  // Method java/io/ObjectOutputStream.writeBoolean:(Z)V
       8: return

  public void writeByte(int) throws java.io.IOException;
    Code:
       0: aload_0
       1: getfield      #2                  // Field oos:Ljava/io/ObjectOutputStream;
       4: iload_1
       5: invokevirtual #10                 // Method java/io/ObjectOutputStream.writeByte:(I)V
       8: return

  public void writeShort(int) throws java.io.IOException;
    Code:
       0: aload_0
       1: getfield      #2                  // Field oos:Ljava/io/ObjectOutputStream;
       4: iload_1
       5: invokevirtual #11                 // Method java/io/ObjectOutputStream.writeShort:(I)V
       8: return

  public void writeChar(int) throws java.io.IOException;
    Code:
       0: aload_0
       1: getfield      #2                  // Field oos:Ljava/io/ObjectOutputStream;
       4: iload_1
       5: invokevirtual #12                 // Method java/io/ObjectOutputStream.writeChar:(I)V
       8: return

  public void writeInt(int) throws java.io.IOException;
    Code:
       0: aload_0
       1: getfield      #2                  // Field oos:Ljava/io/ObjectOutputStream;
       4: iload_1
       5: invokevirtual #13                 // Method java/io/ObjectOutputStream.writeInt:(I)V
       8: return

  public void writeLong(long) throws java.io.IOException;
    Code:
       0: aload_0
       1: getfield      #2                  // Field oos:Ljava/io/ObjectOutputStream;
       4: lload_1
       5: invokevirtual #14                 // Method java/io/ObjectOutputStream.writeLong:(J)V
       8: return

  public void writeFloat(float) throws java.io.IOException;
    Code:
       0: aload_0
       1: getfield      #2                  // Field oos:Ljava/io/ObjectOutputStream;
       4: fload_1
       5: invokevirtual #15                 // Method java/io/ObjectOutputStream.writeFloat:(F)V
       8: return

  public void writeDouble(double) throws java.io.IOException;
    Code:
       0: aload_0
       1: getfield      #2                  // Field oos:Ljava/io/ObjectOutputStream;
       4: dload_1
       5: invokevirtual #16                 // Method java/io/ObjectOutputStream.writeDouble:(D)V
       8: return

  public void writeBytes(java.lang.String) throws java.io.IOException;
    Code:
       0: aload_0
       1: getfield      #2                  // Field oos:Ljava/io/ObjectOutputStream;
       4: aload_1
       5: invokevirtual #17                 // Method java/io/ObjectOutputStream.writeBytes:(Ljava/lang/String;)V
       8: return

  public void writeChars(java.lang.String) throws java.io.IOException;
    Code:
       0: aload_0
       1: getfield      #2                  // Field oos:Ljava/io/ObjectOutputStream;
       4: aload_1
       5: invokevirtual #18                 // Method java/io/ObjectOutputStream.writeChars:(Ljava/lang/String;)V
       8: return

  public void writeUTF(java.lang.String) throws java.io.IOException;
    Code:
       0: aload_0
       1: getfield      #2                  // Field oos:Ljava/io/ObjectOutputStream;
       4: aload_1
       5: invokevirtual #19                 // Method java/io/ObjectOutputStream.writeUTF:(Ljava/lang/String;)V
       8: return

  public void writeObjectUnshared(java.lang.Object) throws java.io.IOException;
    Code:
       0: aload_0
       1: getfield      #2                  // Field oos:Ljava/io/ObjectOutputStream;
       4: aload_1
       5: invokevirtual #20                 // Method java/io/ObjectOutputStream.writeUnshared:(Ljava/lang/Object;)V
       8: return

  public void start(org.jboss.marshalling.ByteOutput) throws java.io.IOException;
    Code:
       0: new           #21                 // class java/lang/UnsupportedOperationException
       3: dup
       4: invokespecial #22                 // Method java/lang/UnsupportedOperationException."<init>":()V
       7: athrow

  public void clearInstanceCache() throws java.io.IOException;
    Code:
       0: aload_0
       1: getfield      #2                  // Field oos:Ljava/io/ObjectOutputStream;
       4: invokevirtual #23                 // Method java/io/ObjectOutputStream.reset:()V
       7: return

  public void clearClassCache() throws java.io.IOException;
    Code:
       0: aload_0
       1: getfield      #2                  // Field oos:Ljava/io/ObjectOutputStream;
       4: invokevirtual #23                 // Method java/io/ObjectOutputStream.reset:()V
       7: return

  public void finish() throws java.io.IOException;
    Code:
       0: return
}
