Compiled from "AbstractEventExecutorGroup.java"
public abstract class io.netty.util.concurrent.AbstractEventExecutorGroup implements io.netty.util.concurrent.EventExecutorGroup {
  public io.netty.util.concurrent.AbstractEventExecutorGroup();
    Code:
       0: aload_0
       1: invokespecial #11                 // Method java/lang/Object."<init>":()V
       4: return

  public io.netty.util.concurrent.Future<?> submit(java.lang.Runnable);
    Code:
       0: aload_0
       1: invokevirtual #19                 // Method next:()Lio/netty/util/concurrent/EventExecutor;
       4: aload_1
       5: invokeinterface #23,  2           // InterfaceMethod io/netty/util/concurrent/EventExecutor.submit:(Ljava/lang/Runnable;)Lio/netty/util/concurrent/Future;
      10: areturn

  public <T> io.netty.util.concurrent.Future<T> submit(java.lang.Runnable, T);
    Code:
       0: aload_0
       1: invokevirtual #19                 // Method next:()Lio/netty/util/concurrent/EventExecutor;
       4: aload_1
       5: aload_2
       6: invokeinterface #28,  3           // InterfaceMethod io/netty/util/concurrent/EventExecutor.submit:(Ljava/lang/Runnable;Ljava/lang/Object;)Lio/netty/util/concurrent/Future;
      11: areturn

  public <T> io.netty.util.concurrent.Future<T> submit(java.util.concurrent.Callable<T>);
    Code:
       0: aload_0
       1: invokevirtual #19                 // Method next:()Lio/netty/util/concurrent/EventExecutor;
       4: aload_1
       5: invokeinterface #34,  2           // InterfaceMethod io/netty/util/concurrent/EventExecutor.submit:(Ljava/util/concurrent/Callable;)Lio/netty/util/concurrent/Future;
      10: areturn

  public io.netty.util.concurrent.ScheduledFuture<?> schedule(java.lang.Runnable, long, java.util.concurrent.TimeUnit);
    Code:
       0: aload_0
       1: invokevirtual #19                 // Method next:()Lio/netty/util/concurrent/EventExecutor;
       4: aload_1
       5: lload_2
       6: aload         4
       8: invokeinterface #40,  5           // InterfaceMethod io/netty/util/concurrent/EventExecutor.schedule:(Ljava/lang/Runnable;JLjava/util/concurrent/TimeUnit;)Lio/netty/util/concurrent/ScheduledFuture;
      13: areturn

  public <V> io.netty.util.concurrent.ScheduledFuture<V> schedule(java.util.concurrent.Callable<V>, long, java.util.concurrent.TimeUnit);
    Code:
       0: aload_0
       1: invokevirtual #19                 // Method next:()Lio/netty/util/concurrent/EventExecutor;
       4: aload_1
       5: lload_2
       6: aload         4
       8: invokeinterface #48,  5           // InterfaceMethod io/netty/util/concurrent/EventExecutor.schedule:(Ljava/util/concurrent/Callable;JLjava/util/concurrent/TimeUnit;)Lio/netty/util/concurrent/ScheduledFuture;
      13: areturn

  public io.netty.util.concurrent.ScheduledFuture<?> scheduleAtFixedRate(java.lang.Runnable, long, long, java.util.concurrent.TimeUnit);
    Code:
       0: aload_0
       1: invokevirtual #19                 // Method next:()Lio/netty/util/concurrent/EventExecutor;
       4: aload_1
       5: lload_2
       6: lload         4
       8: aload         6
      10: invokeinterface #54,  7           // InterfaceMethod io/netty/util/concurrent/EventExecutor.scheduleAtFixedRate:(Ljava/lang/Runnable;JJLjava/util/concurrent/TimeUnit;)Lio/netty/util/concurrent/ScheduledFuture;
      15: areturn

  public io.netty.util.concurrent.ScheduledFuture<?> scheduleWithFixedDelay(java.lang.Runnable, long, long, java.util.concurrent.TimeUnit);
    Code:
       0: aload_0
       1: invokevirtual #19                 // Method next:()Lio/netty/util/concurrent/EventExecutor;
       4: aload_1
       5: lload_2
       6: lload         4
       8: aload         6
      10: invokeinterface #59,  7           // InterfaceMethod io/netty/util/concurrent/EventExecutor.scheduleWithFixedDelay:(Ljava/lang/Runnable;JJLjava/util/concurrent/TimeUnit;)Lio/netty/util/concurrent/ScheduledFuture;
      15: areturn

  public io.netty.util.concurrent.Future<?> shutdownGracefully();
    Code:
       0: aload_0
       1: ldc2_w        #62                 // long 2l
       4: ldc2_w        #64                 // long 15l
       7: getstatic     #70                 // Field java/util/concurrent/TimeUnit.SECONDS:Ljava/util/concurrent/TimeUnit;
      10: invokevirtual #73                 // Method shutdownGracefully:(JJLjava/util/concurrent/TimeUnit;)Lio/netty/util/concurrent/Future;
      13: areturn

  public abstract void shutdown();

  public java.util.List<java.lang.Runnable> shutdownNow();
    Code:
       0: aload_0
       1: invokevirtual #79                 // Method shutdown:()V
       4: invokestatic  #84                 // Method java/util/Collections.emptyList:()Ljava/util/List;
       7: areturn

  public <T> java.util.List<java.util.concurrent.Future<T>> invokeAll(java.util.Collection<? extends java.util.concurrent.Callable<T>>) throws java.lang.InterruptedException;
    Code:
       0: aload_0
       1: invokevirtual #19                 // Method next:()Lio/netty/util/concurrent/EventExecutor;
       4: aload_1
       5: invokeinterface #90,  2           // InterfaceMethod io/netty/util/concurrent/EventExecutor.invokeAll:(Ljava/util/Collection;)Ljava/util/List;
      10: areturn

  public <T> java.util.List<java.util.concurrent.Future<T>> invokeAll(java.util.Collection<? extends java.util.concurrent.Callable<T>>, long, java.util.concurrent.TimeUnit) throws java.lang.InterruptedException;
    Code:
       0: aload_0
       1: invokevirtual #19                 // Method next:()Lio/netty/util/concurrent/EventExecutor;
       4: aload_1
       5: lload_2
       6: aload         4
       8: invokeinterface #96,  5           // InterfaceMethod io/netty/util/concurrent/EventExecutor.invokeAll:(Ljava/util/Collection;JLjava/util/concurrent/TimeUnit;)Ljava/util/List;
      13: areturn

  public <T> T invokeAny(java.util.Collection<? extends java.util.concurrent.Callable<T>>) throws java.lang.InterruptedException, java.util.concurrent.ExecutionException;
    Code:
       0: aload_0
       1: invokevirtual #19                 // Method next:()Lio/netty/util/concurrent/EventExecutor;
       4: aload_1
       5: invokeinterface #103,  2          // InterfaceMethod io/netty/util/concurrent/EventExecutor.invokeAny:(Ljava/util/Collection;)Ljava/lang/Object;
      10: areturn

  public <T> T invokeAny(java.util.Collection<? extends java.util.concurrent.Callable<T>>, long, java.util.concurrent.TimeUnit) throws java.lang.InterruptedException, java.util.concurrent.ExecutionException, java.util.concurrent.TimeoutException;
    Code:
       0: aload_0
       1: invokevirtual #19                 // Method next:()Lio/netty/util/concurrent/EventExecutor;
       4: aload_1
       5: lload_2
       6: aload         4
       8: invokeinterface #108,  5          // InterfaceMethod io/netty/util/concurrent/EventExecutor.invokeAny:(Ljava/util/Collection;JLjava/util/concurrent/TimeUnit;)Ljava/lang/Object;
      13: areturn

  public void execute(java.lang.Runnable);
    Code:
       0: aload_0
       1: invokevirtual #19                 // Method next:()Lio/netty/util/concurrent/EventExecutor;
       4: aload_1
       5: invokeinterface #112,  2          // InterfaceMethod io/netty/util/concurrent/EventExecutor.execute:(Ljava/lang/Runnable;)V
      10: return

  public java.util.concurrent.ScheduledFuture scheduleWithFixedDelay(java.lang.Runnable, long, long, java.util.concurrent.TimeUnit);
    Code:
       0: aload_0
       1: aload_1
       2: lload_2
       3: lload         4
       5: aload         6
       7: invokevirtual #114                // Method scheduleWithFixedDelay:(Ljava/lang/Runnable;JJLjava/util/concurrent/TimeUnit;)Lio/netty/util/concurrent/ScheduledFuture;
      10: areturn

  public java.util.concurrent.ScheduledFuture scheduleAtFixedRate(java.lang.Runnable, long, long, java.util.concurrent.TimeUnit);
    Code:
       0: aload_0
       1: aload_1
       2: lload_2
       3: lload         4
       5: aload         6
       7: invokevirtual #115                // Method scheduleAtFixedRate:(Ljava/lang/Runnable;JJLjava/util/concurrent/TimeUnit;)Lio/netty/util/concurrent/ScheduledFuture;
      10: areturn

  public java.util.concurrent.ScheduledFuture schedule(java.util.concurrent.Callable, long, java.util.concurrent.TimeUnit);
    Code:
       0: aload_0
       1: aload_1
       2: lload_2
       3: aload         4
       5: invokevirtual #117                // Method schedule:(Ljava/util/concurrent/Callable;JLjava/util/concurrent/TimeUnit;)Lio/netty/util/concurrent/ScheduledFuture;
       8: areturn

  public java.util.concurrent.ScheduledFuture schedule(java.lang.Runnable, long, java.util.concurrent.TimeUnit);
    Code:
       0: aload_0
       1: aload_1
       2: lload_2
       3: aload         4
       5: invokevirtual #119                // Method schedule:(Ljava/lang/Runnable;JLjava/util/concurrent/TimeUnit;)Lio/netty/util/concurrent/ScheduledFuture;
       8: areturn

  public java.util.concurrent.Future submit(java.lang.Runnable);
    Code:
       0: aload_0
       1: aload_1
       2: invokevirtual #121                // Method submit:(Ljava/lang/Runnable;)Lio/netty/util/concurrent/Future;
       5: areturn

  public java.util.concurrent.Future submit(java.lang.Runnable, java.lang.Object);
    Code:
       0: aload_0
       1: aload_1
       2: aload_2
       3: invokevirtual #123                // Method submit:(Ljava/lang/Runnable;Ljava/lang/Object;)Lio/netty/util/concurrent/Future;
       6: areturn

  public java.util.concurrent.Future submit(java.util.concurrent.Callable);
    Code:
       0: aload_0
       1: aload_1
       2: invokevirtual #125                // Method submit:(Ljava/util/concurrent/Callable;)Lio/netty/util/concurrent/Future;
       5: areturn
}
