Compiled from "HttpLogger.scala"
public interface wvlet.airframe.http.HttpLogger extends java.lang.AutoCloseable {
  public static scala.Function1<scala.collection.immutable.Map<java.lang.String, java.lang.Object>, java.lang.String> jsonFormatter();
    Code:
       0: getstatic     #25                 // Field wvlet/airframe/http/HttpLogger$.MODULE$:Lwvlet/airframe/http/HttpLogger$;
       3: invokevirtual #27                 // Method wvlet/airframe/http/HttpLogger$.jsonFormatter:()Lscala/Function1;
       6: areturn

  public static wvlet.airframe.http.HttpLogger emptyLogger(wvlet.airframe.http.HttpLoggerConfig);
    Code:
       0: getstatic     #25                 // Field wvlet/airframe/http/HttpLogger$.MODULE$:Lwvlet/airframe/http/HttpLogger$;
       3: aload_0
       4: invokevirtual #32                 // Method wvlet/airframe/http/HttpLogger$.emptyLogger:(Lwvlet/airframe/http/HttpLoggerConfig;)Lwvlet/airframe/http/HttpLogger;
       7: areturn

  public static scala.collection.immutable.Set<java.lang.String> defaultExcludeHeaders();
    Code:
       0: getstatic     #25                 // Field wvlet/airframe/http/HttpLogger$.MODULE$:Lwvlet/airframe/http/HttpLogger$;
       3: invokevirtual #38                 // Method wvlet/airframe/http/HttpLogger$.defaultExcludeHeaders:()Lscala/collection/immutable/Set;
       6: areturn

  public abstract wvlet.airframe.http.HttpLoggerConfig config();

  public static void write$(wvlet.airframe.http.HttpLogger, scala.collection.immutable.Map);
    Code:
       0: aload_0
       1: aload_1
       2: invokespecial #48                 // InterfaceMethod write:(Lscala/collection/immutable/Map;)V
       5: return

  public default void write(scala.collection.immutable.Map<java.lang.String, java.lang.Object>);
    Code:
       0: aload_0
       1: aload_0
       2: invokeinterface #53,  1           // InterfaceMethod config:()Lwvlet/airframe/http/HttpLoggerConfig;
       7: invokevirtual #58                 // Method wvlet/airframe/http/HttpLoggerConfig.logFilter:()Lscala/Function1;
      10: aload_0
      11: invokeinterface #53,  1           // InterfaceMethod config:()Lwvlet/airframe/http/HttpLoggerConfig;
      16: invokevirtual #62                 // Method wvlet/airframe/http/HttpLoggerConfig.extraTags:()Lscala/collection/immutable/Map;
      19: aload_1
      20: invokeinterface #68,  2           // InterfaceMethod scala/collection/immutable/Map.$plus$plus:(Lscala/collection/IterableOnce;)Lscala/collection/IterableOps;
      25: invokeinterface #74,  2           // InterfaceMethod scala/Function1.apply:(Ljava/lang/Object;)Ljava/lang/Object;
      30: checkcast     #64                 // class scala/collection/immutable/Map
      33: invokeinterface #77,  2           // InterfaceMethod writeInternal:(Lscala/collection/immutable/Map;)V
      38: return

  public abstract void writeInternal(scala.collection.immutable.Map<java.lang.String, java.lang.Object>);

  public static void $init$(wvlet.airframe.http.HttpLogger);
    Code:
       0: return
}
