Compiled from "HttpAccessLogWriter.scala"
public class wvlet.airframe.http.HttpAccessLogWriter$JSONHttpAccessLogWriter$ {
  public static final wvlet.airframe.http.HttpAccessLogWriter$JSONHttpAccessLogWriter$ MODULE$;

  public static {};
    Code:
       0: new           #2                  // class wvlet/airframe/http/HttpAccessLogWriter$JSONHttpAccessLogWriter$
       3: dup
       4: invokespecial #15                 // Method "<init>":()V
       7: putstatic     #17                 // Field MODULE$:Lwvlet/airframe/http/HttpAccessLogWriter$JSONHttpAccessLogWriter$;
      10: return

  public wvlet.airframe.http.HttpAccessLogConfig $lessinit$greater$default$1();
    Code:
       0: new           #21                 // class wvlet/airframe/http/HttpAccessLogConfig
       3: dup
       4: getstatic     #26                 // Field wvlet/airframe/http/HttpAccessLogConfig$.MODULE$:Lwvlet/airframe/http/HttpAccessLogConfig$;
       7: invokevirtual #30                 // Method wvlet/airframe/http/HttpAccessLogConfig$.apply$default$1:()Ljava/lang/String;
      10: getstatic     #26                 // Field wvlet/airframe/http/HttpAccessLogConfig$.MODULE$:Lwvlet/airframe/http/HttpAccessLogConfig$;
      13: invokevirtual #34                 // Method wvlet/airframe/http/HttpAccessLogConfig$.apply$default$2:()I
      16: getstatic     #26                 // Field wvlet/airframe/http/HttpAccessLogConfig$.MODULE$:Lwvlet/airframe/http/HttpAccessLogConfig$;
      19: invokevirtual #38                 // Method wvlet/airframe/http/HttpAccessLogConfig$.apply$default$3:()J
      22: invokespecial #41                 // Method wvlet/airframe/http/HttpAccessLogConfig."<init>":(Ljava/lang/String;IJ)V
      25: areturn

  public wvlet.airframe.http.HttpAccessLogWriter$JSONHttpAccessLogWriter$();
    Code:
       0: aload_0
       1: invokespecial #43                 // Method java/lang/Object."<init>":()V
       4: return
}
