Compiled from "CollectionSubject.java"
public class com.google.common.truth.CollectionSubject$Has<T, C extends java.util.Collection<T>> {
  final com.google.common.truth.CollectionSubject this$0;

  public com.google.common.truth.CollectionSubject$Has(com.google.common.truth.CollectionSubject);
    Code:
       0: aload_0
       1: aload_1
       2: putfield      #1                  // Field this$0:Lcom/google/common/truth/CollectionSubject;
       5: aload_0
       6: invokespecial #2                  // Method java/lang/Object."<init>":()V
       9: return

  public void item(T);
    Code:
       0: aload_0
       1: getfield      #1                  // Field this$0:Lcom/google/common/truth/CollectionSubject;
       4: aload_1
       5: invokevirtual #3                  // Method com/google/common/truth/CollectionSubject.contains:(Ljava/lang/Object;)V
       8: return

  public void anyOf(T);
    Code:
       0: aload_0
       1: getfield      #1                  // Field this$0:Lcom/google/common/truth/CollectionSubject;
       4: aload_1
       5: invokevirtual #3                  // Method com/google/common/truth/CollectionSubject.contains:(Ljava/lang/Object;)V
       8: return

  public void anyOf(T, T, T...);
    Code:
       0: aload_0
       1: getfield      #1                  // Field this$0:Lcom/google/common/truth/CollectionSubject;
       4: aload_1
       5: aload_2
       6: aload_3
       7: invokevirtual #4                  // Method com/google/common/truth/CollectionSubject.containsAnyOf:(Ljava/lang/Object;Ljava/lang/Object;[Ljava/lang/Object;)V
      10: return

  public void anyFrom(java.lang.Iterable<T>);
    Code:
       0: aload_0
       1: getfield      #1                  // Field this$0:Lcom/google/common/truth/CollectionSubject;
       4: aload_1
       5: invokevirtual #5                  // Method com/google/common/truth/CollectionSubject.containsAnyIn:(Ljava/lang/Iterable;)V
       8: return

  public com.google.common.truth.Ordered allOf(T);
    Code:
       0: aload_0
       1: aload_1
       2: invokestatic  #6                  // Method com/google/common/truth/SubjectUtils.accumulate:(Ljava/lang/Object;)Ljava/util/List;
       5: invokevirtual #7                  // Method allFrom:(Ljava/lang/Iterable;)Lcom/google/common/truth/Ordered;
       8: areturn

  public com.google.common.truth.Ordered allOf(T, T, T...);
    Code:
       0: aload_0
       1: getfield      #1                  // Field this$0:Lcom/google/common/truth/CollectionSubject;
       4: aload_1
       5: aload_2
       6: aload_3
       7: invokevirtual #8                  // Method com/google/common/truth/CollectionSubject.containsAllOf:(Ljava/lang/Object;Ljava/lang/Object;[Ljava/lang/Object;)Lcom/google/common/truth/Ordered;
      10: areturn

  public com.google.common.truth.Ordered allFrom(java.lang.Iterable<T>);
    Code:
       0: aload_0
       1: getfield      #1                  // Field this$0:Lcom/google/common/truth/CollectionSubject;
       4: aload_1
       5: invokevirtual #9                  // Method com/google/common/truth/CollectionSubject.containsAllIn:(Ljava/lang/Iterable;)Lcom/google/common/truth/Ordered;
       8: areturn

  public com.google.common.truth.Ordered exactly(T);
    Code:
       0: aload_0
       1: aload_1
       2: invokestatic  #6                  // Method com/google/common/truth/SubjectUtils.accumulate:(Ljava/lang/Object;)Ljava/util/List;
       5: invokevirtual #10                 // Method exactlyAs:(Ljava/lang/Iterable;)Lcom/google/common/truth/Ordered;
       8: areturn

  public com.google.common.truth.Ordered exactly(T, T, T...);
    Code:
       0: aload_0
       1: getfield      #1                  // Field this$0:Lcom/google/common/truth/CollectionSubject;
       4: aload_1
       5: aload_2
       6: aload_3
       7: invokevirtual #11                 // Method com/google/common/truth/CollectionSubject.containsOnlyElements:(Ljava/lang/Object;Ljava/lang/Object;[Ljava/lang/Object;)Lcom/google/common/truth/Ordered;
      10: areturn

  public com.google.common.truth.Ordered exactlyAs(java.lang.Iterable<T>);
    Code:
       0: aload_0
       1: getfield      #1                  // Field this$0:Lcom/google/common/truth/CollectionSubject;
       4: aload_1
       5: invokevirtual #12                 // Method com/google/common/truth/CollectionSubject.containsOnlyElementsIn:(Ljava/lang/Iterable;)Lcom/google/common/truth/Ordered;
       8: areturn

  public void noneOf(T);
    Code:
       0: aload_0
       1: getfield      #1                  // Field this$0:Lcom/google/common/truth/CollectionSubject;
       4: aload_1
       5: invokevirtual #13                 // Method com/google/common/truth/CollectionSubject.doesNotContain:(Ljava/lang/Object;)V
       8: return

  public void noneOf(T, T, T...);
    Code:
       0: aload_0
       1: getfield      #1                  // Field this$0:Lcom/google/common/truth/CollectionSubject;
       4: aload_1
       5: aload_2
       6: aload_3
       7: invokevirtual #14                 // Method com/google/common/truth/CollectionSubject.containsNoneOf:(Ljava/lang/Object;Ljava/lang/Object;[Ljava/lang/Object;)V
      10: return

  public void noneFrom(java.lang.Iterable<T>);
    Code:
       0: aload_0
       1: getfield      #1                  // Field this$0:Lcom/google/common/truth/CollectionSubject;
       4: aload_1
       5: invokevirtual #15                 // Method com/google/common/truth/CollectionSubject.containsNoneIn:(Ljava/lang/Iterable;)V
       8: return
}
