Compiled from "ServiceLauncher.java"
public class org.apache.hadoop.service.launcher.ServiceLauncher<S extends org.apache.hadoop.service.Service> implements org.apache.hadoop.service.launcher.LauncherExitCodes, org.apache.hadoop.service.launcher.LauncherArguments, java.lang.Thread$UncaughtExceptionHandler {
  private static final org.slf4j.Logger LOG;

  protected static final int SHUTDOWN_PRIORITY;

  public static final java.lang.String NAME;

  protected static final java.lang.String USAGE_NAME;

  protected static final java.lang.String USAGE_SERVICE_ARGUMENTS;

  public static final java.lang.String USAGE_MESSAGE;

  private static final int SHUTDOWN_TIME_ON_INTERRUPT;

  private volatile S service;

  private int serviceExitCode;

  private org.apache.hadoop.util.ExitUtil$ExitException serviceException;

  private org.apache.hadoop.service.launcher.InterruptEscalator interruptEscalator;

  private org.apache.hadoop.conf.Configuration configuration;

  private java.lang.String serviceName;

  private java.lang.String serviceClassName;

  protected static final java.lang.String[] DEFAULT_CONFIGS;

  private java.util.List<java.lang.String> confClassnames;

  private java.util.List<java.net.URL> confResourceUrls;

  private org.apache.commons.cli.Options commandOptions;

  public org.apache.hadoop.service.launcher.ServiceLauncher(java.lang.String);
    Code:
       0: aload_0
       1: aload_1
       2: aload_1
       3: invokespecial #3                  // Method "<init>":(Ljava/lang/String;Ljava/lang/String;)V
       6: return

  public org.apache.hadoop.service.launcher.ServiceLauncher(java.lang.String, java.lang.String);
    Code:
       0: aload_0
       1: invokespecial #4                  // Method java/lang/Object."<init>":()V
       4: aload_0
       5: ldc           #5                  // String
       7: putfield      #6                  // Field serviceClassName:Ljava/lang/String;
      10: aload_0
      11: new           #7                  // class java/util/ArrayList
      14: dup
      15: getstatic     #8                  // Field DEFAULT_CONFIGS:[Ljava/lang/String;
      18: arraylength
      19: invokespecial #9                  // Method java/util/ArrayList."<init>":(I)V
      22: putfield      #10                 // Field confClassnames:Ljava/util/List;
      25: aload_0
      26: new           #7                  // class java/util/ArrayList
      29: dup
      30: iconst_1
      31: invokespecial #9                  // Method java/util/ArrayList."<init>":(I)V
      34: putfield      #11                 // Field confResourceUrls:Ljava/util/List;
      37: aload_0
      38: aload_2
      39: putfield      #6                  // Field serviceClassName:Ljava/lang/String;
      42: aload_0
      43: aload_1
      44: putfield      #12                 // Field serviceName:Ljava/lang/String;
      47: aload_0
      48: getfield      #10                 // Field confClassnames:Ljava/util/List;
      51: getstatic     #8                  // Field DEFAULT_CONFIGS:[Ljava/lang/String;
      54: invokestatic  #13                 // Method java/util/Arrays.asList:([Ljava/lang/Object;)Ljava/util/List;
      57: invokeinterface #14,  2           // InterfaceMethod java/util/List.addAll:(Ljava/util/Collection;)Z
      62: pop
      63: return

  public final S getService();
    Code:
       0: aload_0
       1: getfield      #15                 // Field service:Lorg/apache/hadoop/service/Service;
       4: areturn

  protected void setService(S);
    Code:
       0: aload_0
       1: aload_1
       2: putfield      #15                 // Field service:Lorg/apache/hadoop/service/Service;
       5: return

  public final org.apache.hadoop.conf.Configuration getConfiguration();
    Code:
       0: aload_0
       1: getfield      #16                 // Field configuration:Lorg/apache/hadoop/conf/Configuration;
       4: areturn

  public final int getServiceExitCode();
    Code:
       0: aload_0
       1: getfield      #17                 // Field serviceExitCode:I
       4: ireturn

  public final org.apache.hadoop.util.ExitUtil$ExitException getServiceException();
    Code:
       0: aload_0
       1: getfield      #18                 // Field serviceException:Lorg/apache/hadoop/util/ExitUtil$ExitException;
       4: areturn

  private boolean isClassnameDefined();
    Code:
       0: aload_0
       1: getfield      #6                  // Field serviceClassName:Ljava/lang/String;
       4: ifnull        21
       7: aload_0
       8: getfield      #6                  // Field serviceClassName:Ljava/lang/String;
      11: invokevirtual #19                 // Method java/lang/String.isEmpty:()Z
      14: ifne          21
      17: iconst_1
      18: goto          22
      21: iconst_0
      22: ireturn

  public java.lang.String toString();
    Code:
       0: new           #20                 // class java/lang/StringBuilder
       3: dup
       4: ldc           #21                 // String \"ServiceLauncher for \"
       6: invokespecial #22                 // Method java/lang/StringBuilder."<init>":(Ljava/lang/String;)V
       9: astore_1
      10: aload_1
      11: aload_0
      12: getfield      #12                 // Field serviceName:Ljava/lang/String;
      15: invokevirtual #23                 // Method java/lang/StringBuilder.append:(Ljava/lang/String;)Ljava/lang/StringBuilder;
      18: pop
      19: aload_0
      20: invokespecial #24                 // Method isClassnameDefined:()Z
      23: ifeq          45
      26: aload_1
      27: ldc           #25                 // String , serviceClassName=\'
      29: invokevirtual #23                 // Method java/lang/StringBuilder.append:(Ljava/lang/String;)Ljava/lang/StringBuilder;
      32: aload_0
      33: getfield      #6                  // Field serviceClassName:Ljava/lang/String;
      36: invokevirtual #23                 // Method java/lang/StringBuilder.append:(Ljava/lang/String;)Ljava/lang/StringBuilder;
      39: bipush        39
      41: invokevirtual #26                 // Method java/lang/StringBuilder.append:(C)Ljava/lang/StringBuilder;
      44: pop
      45: aload_0
      46: getfield      #15                 // Field service:Lorg/apache/hadoop/service/Service;
      49: ifnull        66
      52: aload_1
      53: ldc           #27                 // String , service=
      55: invokevirtual #23                 // Method java/lang/StringBuilder.append:(Ljava/lang/String;)Ljava/lang/StringBuilder;
      58: aload_0
      59: getfield      #15                 // Field service:Lorg/apache/hadoop/service/Service;
      62: invokevirtual #28                 // Method java/lang/StringBuilder.append:(Ljava/lang/Object;)Ljava/lang/StringBuilder;
      65: pop
      66: aload_1
      67: invokevirtual #29                 // Method java/lang/StringBuilder.toString:()Ljava/lang/String;
      70: areturn

  public void launchServiceAndExit(java.util.List<java.lang.String>);
    Code:
       0: new           #20                 // class java/lang/StringBuilder
       3: dup
       4: invokespecial #30                 // Method java/lang/StringBuilder."<init>":()V
       7: astore_2
       8: aload_1
       9: invokeinterface #31,  1           // InterfaceMethod java/util/List.iterator:()Ljava/util/Iterator;
      14: astore_3
      15: aload_3
      16: invokeinterface #32,  1           // InterfaceMethod java/util/Iterator.hasNext:()Z
      21: ifeq          55
      24: aload_3
      25: invokeinterface #33,  1           // InterfaceMethod java/util/Iterator.next:()Ljava/lang/Object;
      30: checkcast     #34                 // class java/lang/String
      33: astore        4
      35: aload_2
      36: bipush        34
      38: invokevirtual #26                 // Method java/lang/StringBuilder.append:(C)Ljava/lang/StringBuilder;
      41: aload         4
      43: invokevirtual #23                 // Method java/lang/StringBuilder.append:(Ljava/lang/String;)Ljava/lang/StringBuilder;
      46: ldc           #35                 // String \"
      48: invokevirtual #23                 // Method java/lang/StringBuilder.append:(Ljava/lang/String;)Ljava/lang/StringBuilder;
      51: pop
      52: goto          15
      55: aload_2
      56: invokevirtual #29                 // Method java/lang/StringBuilder.toString:()Ljava/lang/String;
      59: astore_3
      60: getstatic     #36                 // Field LOG:Lorg/slf4j/Logger;
      63: invokeinterface #37,  1           // InterfaceMethod org/slf4j/Logger.isDebugEnabled:()Z
      68: ifeq          96
      71: getstatic     #36                 // Field LOG:Lorg/slf4j/Logger;
      74: aload_0
      75: getfield      #12                 // Field serviceName:Ljava/lang/String;
      78: aload_1
      79: invokestatic  #38                 // Method startupShutdownMessage:(Ljava/lang/String;Ljava/util/List;)Ljava/lang/String;
      82: invokeinterface #39,  2           // InterfaceMethod org/slf4j/Logger.debug:(Ljava/lang/String;)V
      87: getstatic     #36                 // Field LOG:Lorg/slf4j/Logger;
      90: aload_3
      91: invokeinterface #39,  2           // InterfaceMethod org/slf4j/Logger.debug:(Ljava/lang/String;)V
      96: aload_0
      97: invokevirtual #40                 // Method registerFailureHandling:()V
     100: aload_0
     101: invokevirtual #41                 // Method loadConfigurationClasses:()I
     104: pop
     105: aload_0
     106: invokevirtual #42                 // Method createConfiguration:()Lorg/apache/hadoop/conf/Configuration;
     109: astore        4
     111: aload_0
     112: getfield      #11                 // Field confResourceUrls:Ljava/util/List;
     115: invokeinterface #31,  1           // InterfaceMethod java/util/List.iterator:()Ljava/util/Iterator;
     120: astore        5
     122: aload         5
     124: invokeinterface #32,  1           // InterfaceMethod java/util/Iterator.hasNext:()Z
     129: ifeq          154
     132: aload         5
     134: invokeinterface #33,  1           // InterfaceMethod java/util/Iterator.next:()Ljava/lang/Object;
     139: checkcast     #43                 // class java/net/URL
     142: astore        6
     144: aload         4
     146: aload         6
     148: invokevirtual #44                 // Method org/apache/hadoop/conf/Configuration.addResource:(Ljava/net/URL;)V
     151: goto          122
     154: aload_0
     155: invokevirtual #45                 // Method bindCommandOptions:()V
     158: aload_0
     159: aload         4
     161: aload_1
     162: invokevirtual #46                 // Method extractCommandOptions:(Lorg/apache/hadoop/conf/Configuration;Ljava/util/List;)Ljava/util/List;
     165: astore        6
     167: aload_0
     168: aload         4
     170: aload         6
     172: iconst_1
     173: iconst_1
     174: invokevirtual #47                 // Method launchService:(Lorg/apache/hadoop/conf/Configuration;Ljava/util/List;ZZ)Lorg/apache/hadoop/util/ExitUtil$ExitException;
     177: astore        5
     179: goto          194
     182: astore        6
     184: aload         6
     186: astore        5
     188: aload_0
     189: aload         5
     191: invokevirtual #49                 // Method noteException:(Lorg/apache/hadoop/util/ExitUtil$ExitException;)V
     194: aload         5
     196: invokevirtual #50                 // Method org/apache/hadoop/util/ExitUtil$ExitException.getExitCode:()I
     199: ifeq          237
     202: getstatic     #51                 // Field java/lang/System.err:Ljava/io/PrintStream;
     205: aload_0
     206: invokevirtual #52                 // Method getUsageMessage:()Ljava/lang/String;
     209: invokevirtual #53                 // Method java/io/PrintStream.println:(Ljava/lang/String;)V
     212: getstatic     #51                 // Field java/lang/System.err:Ljava/io/PrintStream;
     215: new           #20                 // class java/lang/StringBuilder
     218: dup
     219: invokespecial #30                 // Method java/lang/StringBuilder."<init>":()V
     222: ldc           #54                 // String Command:
     224: invokevirtual #23                 // Method java/lang/StringBuilder.append:(Ljava/lang/String;)Ljava/lang/StringBuilder;
     227: aload_3
     228: invokevirtual #23                 // Method java/lang/StringBuilder.append:(Ljava/lang/String;)Ljava/lang/StringBuilder;
     231: invokevirtual #29                 // Method java/lang/StringBuilder.toString:()Ljava/lang/String;
     234: invokevirtual #53                 // Method java/io/PrintStream.println:(Ljava/lang/String;)V
     237: getstatic     #55                 // Field java/lang/System.out:Ljava/io/PrintStream;
     240: invokevirtual #56                 // Method java/io/PrintStream.flush:()V
     243: getstatic     #51                 // Field java/lang/System.err:Ljava/io/PrintStream;
     246: invokevirtual #56                 // Method java/io/PrintStream.flush:()V
     249: aload_0
     250: aload         5
     252: invokevirtual #57                 // Method exit:(Lorg/apache/hadoop/util/ExitUtil$ExitException;)V
     255: return
    Exception table:
       from    to  target type
         158   179   182   Class org/apache/hadoop/util/ExitUtil$ExitException

  protected void bindCommandOptions();
    Code:
       0: aload_0
       1: aload_0
       2: invokevirtual #58                 // Method createOptions:()Lorg/apache/commons/cli/Options;
       5: putfield      #59                 // Field commandOptions:Lorg/apache/commons/cli/Options;
       8: return

  void noteException(org.apache.hadoop.util.ExitUtil$ExitException);
    Code:
       0: getstatic     #36                 // Field LOG:Lorg/slf4j/Logger;
       3: ldc           #60                 // String Exception raised
       5: aload_1
       6: invokeinterface #61,  3           // InterfaceMethod org/slf4j/Logger.debug:(Ljava/lang/String;Ljava/lang/Throwable;)V
      11: aload_0
      12: aload_1
      13: invokevirtual #50                 // Method org/apache/hadoop/util/ExitUtil$ExitException.getExitCode:()I
      16: putfield      #17                 // Field serviceExitCode:I
      19: aload_0
      20: aload_1
      21: putfield      #18                 // Field serviceException:Lorg/apache/hadoop/util/ExitUtil$ExitException;
      24: return

  protected java.lang.String getUsageMessage();
    Code:
       0: ldc           #62                 // String Usage: ServiceLauncher [--conf <conf file>] [--hadoopconf <configuration classname>] service-classname <service arguments>
       2: astore_1
       3: aload_0
       4: getfield      #59                 // Field commandOptions:Lorg/apache/commons/cli/Options;
       7: ifnull        46
      10: new           #20                 // class java/lang/StringBuilder
      13: dup
      14: invokespecial #30                 // Method java/lang/StringBuilder."<init>":()V
      17: ldc           #63                 // String Usage: ServiceLauncher
      19: invokevirtual #23                 // Method java/lang/StringBuilder.append:(Ljava/lang/String;)Ljava/lang/StringBuilder;
      22: aload_0
      23: getfield      #59                 // Field commandOptions:Lorg/apache/commons/cli/Options;
      26: invokevirtual #64                 // Method org/apache/commons/cli/Options.toString:()Ljava/lang/String;
      29: invokevirtual #23                 // Method java/lang/StringBuilder.append:(Ljava/lang/String;)Ljava/lang/StringBuilder;
      32: ldc           #65                 // String
      34: invokevirtual #23                 // Method java/lang/StringBuilder.append:(Ljava/lang/String;)Ljava/lang/StringBuilder;
      37: ldc           #66                 // String service-classname <service arguments>
      39: invokevirtual #23                 // Method java/lang/StringBuilder.append:(Ljava/lang/String;)Ljava/lang/StringBuilder;
      42: invokevirtual #29                 // Method java/lang/StringBuilder.toString:()Ljava/lang/String;
      45: astore_1
      46: aload_1
      47: areturn

  protected org.apache.commons.cli.Options createOptions();
    Code:
       0: ldc           #67                 // class org/apache/commons/cli/OptionBuilder
       2: dup
       3: astore_1
       4: monitorenter
       5: new           #68                 // class org/apache/commons/cli/Options
       8: dup
       9: invokespecial #69                 // Method org/apache/commons/cli/Options."<init>":()V
      12: astore_2
      13: ldc           #70                 // String configuration file
      15: invokestatic  #71                 // Method org/apache/commons/cli/OptionBuilder.withArgName:(Ljava/lang/String;)Lorg/apache/commons/cli/OptionBuilder;
      18: pop
      19: invokestatic  #72                 // Method org/apache/commons/cli/OptionBuilder.hasArg:()Lorg/apache/commons/cli/OptionBuilder;
      22: pop
      23: ldc           #73                 // String specify an application configuration file
      25: invokestatic  #74                 // Method org/apache/commons/cli/OptionBuilder.withDescription:(Ljava/lang/String;)Lorg/apache/commons/cli/OptionBuilder;
      28: pop
      29: ldc           #75                 // String conf
      31: invokestatic  #76                 // Method org/apache/commons/cli/OptionBuilder.withLongOpt:(Ljava/lang/String;)Lorg/apache/commons/cli/OptionBuilder;
      34: pop
      35: ldc           #75                 // String conf
      37: invokestatic  #77                 // Method org/apache/commons/cli/OptionBuilder.create:(Ljava/lang/String;)Lorg/apache/commons/cli/Option;
      40: astore_3
      41: ldc           #78                 // String configuration classname
      43: invokestatic  #71                 // Method org/apache/commons/cli/OptionBuilder.withArgName:(Ljava/lang/String;)Lorg/apache/commons/cli/OptionBuilder;
      46: pop
      47: invokestatic  #72                 // Method org/apache/commons/cli/OptionBuilder.hasArg:()Lorg/apache/commons/cli/OptionBuilder;
      50: pop
      51: ldc           #79                 // String Classname of a Hadoop Configuration subclass to load
      53: invokestatic  #74                 // Method org/apache/commons/cli/OptionBuilder.withDescription:(Ljava/lang/String;)Lorg/apache/commons/cli/OptionBuilder;
      56: pop
      57: ldc           #80                 // String hadoopconf
      59: invokestatic  #76                 // Method org/apache/commons/cli/OptionBuilder.withLongOpt:(Ljava/lang/String;)Lorg/apache/commons/cli/OptionBuilder;
      62: pop
      63: ldc           #80                 // String hadoopconf
      65: invokestatic  #77                 // Method org/apache/commons/cli/OptionBuilder.create:(Ljava/lang/String;)Lorg/apache/commons/cli/Option;
      68: astore        4
      70: ldc           #81                 // String property=value
      72: invokestatic  #71                 // Method org/apache/commons/cli/OptionBuilder.withArgName:(Ljava/lang/String;)Lorg/apache/commons/cli/OptionBuilder;
      75: pop
      76: invokestatic  #72                 // Method org/apache/commons/cli/OptionBuilder.hasArg:()Lorg/apache/commons/cli/OptionBuilder;
      79: pop
      80: ldc           #82                 // String use value for given property
      82: invokestatic  #74                 // Method org/apache/commons/cli/OptionBuilder.withDescription:(Ljava/lang/String;)Lorg/apache/commons/cli/OptionBuilder;
      85: pop
      86: bipush        68
      88: invokestatic  #83                 // Method org/apache/commons/cli/OptionBuilder.create:(C)Lorg/apache/commons/cli/Option;
      91: astore        5
      93: aload_2
      94: aload_3
      95: invokevirtual #84                 // Method org/apache/commons/cli/Options.addOption:(Lorg/apache/commons/cli/Option;)Lorg/apache/commons/cli/Options;
      98: pop
      99: aload_2
     100: aload         5
     102: invokevirtual #84                 // Method org/apache/commons/cli/Options.addOption:(Lorg/apache/commons/cli/Option;)Lorg/apache/commons/cli/Options;
     105: pop
     106: aload_2
     107: aload         4
     109: invokevirtual #84                 // Method org/apache/commons/cli/Options.addOption:(Lorg/apache/commons/cli/Option;)Lorg/apache/commons/cli/Options;
     112: pop
     113: aload_2
     114: aload_1
     115: monitorexit
     116: areturn
     117: astore        6
     119: aload_1
     120: monitorexit
     121: aload         6
     123: athrow
    Exception table:
       from    to  target type
           5   116   117   any
         117   121   117   any

  protected org.apache.hadoop.conf.Configuration createConfiguration();
    Code:
       0: new           #85                 // class org/apache/hadoop/conf/Configuration
       3: dup
       4: invokespecial #86                 // Method org/apache/hadoop/conf/Configuration."<init>":()V
       7: areturn

  protected java.util.List<java.lang.String> getConfigurationsToCreate();
    Code:
       0: aload_0
       1: getfield      #10                 // Field confClassnames:Ljava/util/List;
       4: areturn

  public int loadConfigurationClasses();
    Code:
       0: aload_0
       1: invokevirtual #87                 // Method getConfigurationsToCreate:()Ljava/util/List;
       4: astore_1
       5: iconst_0
       6: istore_2
       7: aload_1
       8: invokeinterface #31,  1           // InterfaceMethod java/util/List.iterator:()Ljava/util/Iterator;
      13: astore_3
      14: aload_3
      15: invokeinterface #32,  1           // InterfaceMethod java/util/Iterator.hasNext:()Z
      20: ifeq          153
      23: aload_3
      24: invokeinterface #33,  1           // InterfaceMethod java/util/Iterator.next:()Ljava/lang/Object;
      29: checkcast     #34                 // class java/lang/String
      32: astore        4
      34: aload_0
      35: invokevirtual #88                 // Method getClassLoader:()Ljava/lang/ClassLoader;
      38: aload         4
      40: invokevirtual #89                 // Method java/lang/ClassLoader.loadClass:(Ljava/lang/String;)Ljava/lang/Class;
      43: astore        5
      45: aload         5
      47: iconst_0
      48: anewarray     #90                 // class java/lang/Class
      51: invokevirtual #91                 // Method java/lang/Class.getConstructor:([Ljava/lang/Class;)Ljava/lang/reflect/Constructor;
      54: iconst_0
      55: anewarray     #92                 // class java/lang/Object
      58: invokevirtual #93                 // Method java/lang/reflect/Constructor.newInstance:([Ljava/lang/Object;)Ljava/lang/Object;
      61: astore        6
      63: aload         6
      65: instanceof    #85                 // class org/apache/hadoop/conf/Configuration
      68: ifne          106
      71: new           #48                 // class org/apache/hadoop/util/ExitUtil$ExitException
      74: dup
      75: bipush        56
      77: new           #20                 // class java/lang/StringBuilder
      80: dup
      81: invokespecial #30                 // Method java/lang/StringBuilder."<init>":()V
      84: ldc           #95                 // String Could not create
      86: invokevirtual #23                 // Method java/lang/StringBuilder.append:(Ljava/lang/String;)Ljava/lang/StringBuilder;
      89: aload         4
      91: invokevirtual #23                 // Method java/lang/StringBuilder.append:(Ljava/lang/String;)Ljava/lang/StringBuilder;
      94: ldc           #96                 // String  because it is not a Configuration class/subclass
      96: invokevirtual #23                 // Method java/lang/StringBuilder.append:(Ljava/lang/String;)Ljava/lang/StringBuilder;
      99: invokevirtual #29                 // Method java/lang/StringBuilder.toString:()Ljava/lang/String;
     102: invokespecial #97                 // Method org/apache/hadoop/util/ExitUtil$ExitException."<init>":(ILjava/lang/String;)V
     105: athrow
     106: iinc          2, 1
     109: goto          150
     112: astore        5
     114: getstatic     #36                 // Field LOG:Lorg/slf4j/Logger;
     117: ldc           #99                 // String Failed to load {} because it is not on the classpath
     119: aload         4
     121: invokeinterface #100,  3          // InterfaceMethod org/slf4j/Logger.debug:(Ljava/lang/String;Ljava/lang/Object;)V
     126: goto          150
     129: astore        5
     131: aload         5
     133: athrow
     134: astore        5
     136: getstatic     #36                 // Field LOG:Lorg/slf4j/Logger;
     139: ldc           #102                // String Failed to create {}
     141: aload         4
     143: aload         5
     145: invokeinterface #103,  4          // InterfaceMethod org/slf4j/Logger.info:(Ljava/lang/String;Ljava/lang/Object;Ljava/lang/Object;)V
     150: goto          14
     153: iload_2
     154: ireturn
    Exception table:
       from    to  target type
          34   109   112   Class java/lang/ClassNotFoundException
          34   109   129   Class org/apache/hadoop/util/ExitUtil$ExitException
          34   109   134   Class java/lang/Exception

  public org.apache.hadoop.util.ExitUtil$ExitException launchService(org.apache.hadoop.conf.Configuration, java.util.List<java.lang.String>, boolean, boolean);
    Code:
       0: aload_0
       1: aload_1
       2: aload_2
       3: iload_3
       4: iload         4
       6: invokevirtual #104                // Method coreServiceLaunch:(Lorg/apache/hadoop/conf/Configuration;Ljava/util/List;ZZ)I
       9: istore        6
      11: aload_0
      12: getfield      #15                 // Field service:Lorg/apache/hadoop/service/Service;
      15: ifnull        73
      18: aload_0
      19: getfield      #15                 // Field service:Lorg/apache/hadoop/service/Service;
      22: invokeinterface #105,  1          // InterfaceMethod org/apache/hadoop/service/Service.getFailureCause:()Ljava/lang/Throwable;
      27: astore        7
      29: aload         7
      31: ifnull        73
      34: aload_0
      35: getfield      #15                 // Field service:Lorg/apache/hadoop/service/Service;
      38: invokeinterface #106,  1          // InterfaceMethod org/apache/hadoop/service/Service.getFailureState:()Lorg/apache/hadoop/service/Service$STATE;
      43: astore        8
      45: aload         8
      47: getstatic     #107                // Field org/apache/hadoop/service/Service$STATE.STOPPED:Lorg/apache/hadoop/service/Service$STATE;
      50: if_acmpne     70
      53: getstatic     #36                 // Field LOG:Lorg/slf4j/Logger;
      56: ldc           #108                // String Failure during shutdown: {}
      58: aload         7
      60: aload         7
      62: invokeinterface #109,  4          // InterfaceMethod org/slf4j/Logger.debug:(Ljava/lang/String;Ljava/lang/Object;Ljava/lang/Object;)V
      67: goto          73
      70: aload         7
      72: athrow
      73: aload_0
      74: invokevirtual #110                // Method getServiceName:()Ljava/lang/String;
      77: astore        7
      79: iload         6
      81: ifne          109
      84: new           #111                // class org/apache/hadoop/service/launcher/ServiceLaunchException
      87: dup
      88: iload         6
      90: ldc           #112                // String %s succeeded
      92: iconst_1
      93: anewarray     #92                 // class java/lang/Object
      96: dup
      97: iconst_0
      98: aload         7
     100: aastore
     101: invokespecial #113                // Method org/apache/hadoop/service/launcher/ServiceLaunchException."<init>":(ILjava/lang/String;[Ljava/lang/Object;)V
     104: astore        5
     106: goto          131
     109: new           #111                // class org/apache/hadoop/service/launcher/ServiceLaunchException
     112: dup
     113: iload         6
     115: ldc           #114                // String %s failed
     117: iconst_1
     118: anewarray     #92                 // class java/lang/Object
     121: dup
     122: iconst_0
     123: aload         7
     125: aastore
     126: invokespecial #113                // Method org/apache/hadoop/service/launcher/ServiceLaunchException."<init>":(ILjava/lang/String;[Ljava/lang/Object;)V
     129: astore        5
     131: goto          152
     134: astore        6
     136: aload         6
     138: astore        5
     140: goto          152
     143: astore        6
     145: aload         6
     147: invokestatic  #116                // Method convertToExitException:(Ljava/lang/Throwable;)Lorg/apache/hadoop/util/ExitUtil$ExitException;
     150: astore        5
     152: aload_0
     153: aload         5
     155: invokevirtual #49                 // Method noteException:(Lorg/apache/hadoop/util/ExitUtil$ExitException;)V
     158: aload         5
     160: areturn
    Exception table:
       from    to  target type
           0   131   134   Class org/apache/hadoop/util/ExitUtil$ExitException
           0   131   143   Class java/lang/Throwable

  protected int coreServiceLaunch(org.apache.hadoop.conf.Configuration, java.util.List<java.lang.String>, boolean, boolean) throws java.lang.Exception;
    Code:
       0: aload_0
       1: aload_1
       2: invokevirtual #117                // Method instantiateService:(Lorg/apache/hadoop/conf/Configuration;)Lorg/apache/hadoop/service/Service;
       5: pop
       6: aconst_null
       7: astore        5
       9: iload_3
      10: ifeq          33
      13: new           #118                // class org/apache/hadoop/service/launcher/ServiceShutdownHook
      16: dup
      17: aload_0
      18: getfield      #15                 // Field service:Lorg/apache/hadoop/service/Service;
      21: invokespecial #119                // Method org/apache/hadoop/service/launcher/ServiceShutdownHook."<init>":(Lorg/apache/hadoop/service/Service;)V
      24: astore        5
      26: aload         5
      28: bipush        30
      30: invokevirtual #120                // Method org/apache/hadoop/service/launcher/ServiceShutdownHook.register:(I)V
      33: aload_0
      34: invokevirtual #110                // Method getServiceName:()Ljava/lang/String;
      37: astore        6
      39: getstatic     #36                 // Field LOG:Lorg/slf4j/Logger;
      42: ldc           #121                // String Launched service {}
      44: aload         6
      46: invokeinterface #100,  3          // InterfaceMethod org/slf4j/Logger.debug:(Ljava/lang/String;Ljava/lang/Object;)V
      51: aconst_null
      52: astore        7
      54: aload_0
      55: getfield      #15                 // Field service:Lorg/apache/hadoop/service/Service;
      58: instanceof    #122                // class org/apache/hadoop/service/launcher/LaunchableService
      61: ifeq          135
      64: getstatic     #36                 // Field LOG:Lorg/slf4j/Logger;
      67: ldc           #123                // String Service {} implements LaunchableService
      69: aload         6
      71: invokeinterface #100,  3          // InterfaceMethod org/slf4j/Logger.debug:(Ljava/lang/String;Ljava/lang/Object;)V
      76: aload_0
      77: getfield      #15                 // Field service:Lorg/apache/hadoop/service/Service;
      80: checkcast     #122                // class org/apache/hadoop/service/launcher/LaunchableService
      83: astore        7
      85: aload         7
      87: getstatic     #124                // Field org/apache/hadoop/service/Service$STATE.INITED:Lorg/apache/hadoop/service/Service$STATE;
      90: invokeinterface #125,  2          // InterfaceMethod org/apache/hadoop/service/launcher/LaunchableService.isInState:(Lorg/apache/hadoop/service/Service$STATE;)Z
      95: ifeq          110
      98: getstatic     #36                 // Field LOG:Lorg/slf4j/Logger;
     101: ldc           #126                // String LaunchableService {} initialized in constructor before CLI arguments passed in
     103: aload         6
     105: invokeinterface #127,  3          // InterfaceMethod org/slf4j/Logger.warn:(Ljava/lang/String;Ljava/lang/Object;)V
     110: aload         7
     112: aload_0
     113: getfield      #16                 // Field configuration:Lorg/apache/hadoop/conf/Configuration;
     116: aload_2
     117: invokeinterface #128,  3          // InterfaceMethod org/apache/hadoop/service/launcher/LaunchableService.bindArgs:(Lorg/apache/hadoop/conf/Configuration;Ljava/util/List;)Lorg/apache/hadoop/conf/Configuration;
     122: astore        8
     124: aload         8
     126: ifnull        135
     129: aload_0
     130: aload         8
     132: putfield      #16                 // Field configuration:Lorg/apache/hadoop/conf/Configuration;
     135: aload_0
     136: getfield      #15                 // Field service:Lorg/apache/hadoop/service/Service;
     139: getstatic     #124                // Field org/apache/hadoop/service/Service$STATE.INITED:Lorg/apache/hadoop/service/Service$STATE;
     142: invokeinterface #129,  2          // InterfaceMethod org/apache/hadoop/service/Service.isInState:(Lorg/apache/hadoop/service/Service$STATE;)Z
     147: ifne          163
     150: aload_0
     151: getfield      #15                 // Field service:Lorg/apache/hadoop/service/Service;
     154: aload_0
     155: getfield      #16                 // Field configuration:Lorg/apache/hadoop/conf/Configuration;
     158: invokeinterface #130,  2          // InterfaceMethod org/apache/hadoop/service/Service.init:(Lorg/apache/hadoop/conf/Configuration;)V
     163: aload_0
     164: getfield      #15                 // Field service:Lorg/apache/hadoop/service/Service;
     167: invokeinterface #131,  1          // InterfaceMethod org/apache/hadoop/service/Service.start:()V
     172: iconst_0
     173: istore        8
     175: iload         4
     177: ifeq          276
     180: aload_0
     181: getfield      #15                 // Field service:Lorg/apache/hadoop/service/Service;
     184: getstatic     #132                // Field org/apache/hadoop/service/Service$STATE.STARTED:Lorg/apache/hadoop/service/Service$STATE;
     187: invokeinterface #129,  2          // InterfaceMethod org/apache/hadoop/service/Service.isInState:(Lorg/apache/hadoop/service/Service$STATE;)Z
     192: ifeq          276
     195: aload         7
     197: ifnull        255
     200: aload         7
     202: invokeinterface #133,  1          // InterfaceMethod org/apache/hadoop/service/launcher/LaunchableService.execute:()I
     207: istore        8
     209: getstatic     #36                 // Field LOG:Lorg/slf4j/Logger;
     212: ldc           #134                // String Service {} execution returned exit code {}
     214: aload         6
     216: iload         8
     218: invokestatic  #135                // Method java/lang/Integer.valueOf:(I)Ljava/lang/Integer;
     221: invokeinterface #109,  4          // InterfaceMethod org/slf4j/Logger.debug:(Ljava/lang/String;Ljava/lang/Object;Ljava/lang/Object;)V
     226: aload_0
     227: getfield      #15                 // Field service:Lorg/apache/hadoop/service/Service;
     230: invokeinterface #136,  1          // InterfaceMethod org/apache/hadoop/service/Service.stop:()V
     235: goto          252
     238: astore        9
     240: aload_0
     241: getfield      #15                 // Field service:Lorg/apache/hadoop/service/Service;
     244: invokeinterface #136,  1          // InterfaceMethod org/apache/hadoop/service/Service.stop:()V
     249: aload         9
     251: athrow
     252: goto          276
     255: getstatic     #36                 // Field LOG:Lorg/slf4j/Logger;
     258: ldc           #137                // String waiting for service threads to terminate
     260: invokeinterface #39,  2           // InterfaceMethod org/slf4j/Logger.debug:(Ljava/lang/String;)V
     265: aload_0
     266: getfield      #15                 // Field service:Lorg/apache/hadoop/service/Service;
     269: lconst_0
     270: invokeinterface #138,  3          // InterfaceMethod org/apache/hadoop/service/Service.waitForServiceToStop:(J)Z
     275: pop
     276: aload         5
     278: ifnull        304
     281: aload         5
     283: invokevirtual #139                // Method org/apache/hadoop/service/launcher/ServiceShutdownHook.unregister:()V
     286: goto          304
     289: astore        10
     291: aload         5
     293: ifnull        301
     296: aload         5
     298: invokevirtual #139                // Method org/apache/hadoop/service/launcher/ServiceShutdownHook.unregister:()V
     301: aload         10
     303: athrow
     304: iload         8
     306: ireturn
    Exception table:
       from    to  target type
         200   226   238   any
         238   240   238   any
         163   276   289   any
         289   291   289   any

  public org.apache.hadoop.service.Service instantiateService(org.apache.hadoop.conf.Configuration);
    Code:
       0: aload_1
       1: ifnull        8
       4: iconst_1
       5: goto          9
       8: iconst_0
       9: ldc           #140                // String null conf
      11: invokestatic  #141                // Method com/google/common/base/Preconditions.checkArgument:(ZLjava/lang/Object;)V
      14: aload_0
      15: getfield      #6                  // Field serviceClassName:Ljava/lang/String;
      18: ifnull        25
      21: iconst_1
      22: goto          26
      25: iconst_0
      26: ldc           #142                // String null service classname
      28: invokestatic  #141                // Method com/google/common/base/Preconditions.checkArgument:(ZLjava/lang/Object;)V
      31: aload_0
      32: getfield      #6                  // Field serviceClassName:Ljava/lang/String;
      35: invokevirtual #19                 // Method java/lang/String.isEmpty:()Z
      38: ifne          45
      41: iconst_1
      42: goto          46
      45: iconst_0
      46: ldc           #143                // String undefined service classname
      48: invokestatic  #141                // Method com/google/common/base/Preconditions.checkArgument:(ZLjava/lang/Object;)V
      51: aload_0
      52: aload_1
      53: putfield      #16                 // Field configuration:Lorg/apache/hadoop/conf/Configuration;
      56: aload_0
      57: invokevirtual #88                 // Method getClassLoader:()Ljava/lang/ClassLoader;
      60: aload_0
      61: getfield      #6                  // Field serviceClassName:Ljava/lang/String;
      64: invokevirtual #89                 // Method java/lang/ClassLoader.loadClass:(Ljava/lang/String;)Ljava/lang/Class;
      67: astore_3
      68: aload_3
      69: iconst_0
      70: anewarray     #90                 // class java/lang/Class
      73: invokevirtual #91                 // Method java/lang/Class.getConstructor:([Ljava/lang/Class;)Ljava/lang/reflect/Constructor;
      76: iconst_0
      77: anewarray     #92                 // class java/lang/Object
      80: invokevirtual #93                 // Method java/lang/reflect/Constructor.newInstance:([Ljava/lang/Object;)Ljava/lang/Object;
      83: astore_2
      84: goto          131
      87: astore        4
      89: getstatic     #36                 // Field LOG:Lorg/slf4j/Logger;
      92: ldc           #145                // String No empty constructor {}
      94: aload         4
      96: aload         4
      98: invokeinterface #109,  4          // InterfaceMethod org/slf4j/Logger.debug:(Ljava/lang/String;Ljava/lang/Object;Ljava/lang/Object;)V
     103: aload_3
     104: iconst_1
     105: anewarray     #90                 // class java/lang/Class
     108: dup
     109: iconst_0
     110: ldc           #34                 // class java/lang/String
     112: aastore
     113: invokevirtual #91                 // Method java/lang/Class.getConstructor:([Ljava/lang/Class;)Ljava/lang/reflect/Constructor;
     116: iconst_1
     117: anewarray     #92                 // class java/lang/Object
     120: dup
     121: iconst_0
     122: aload_0
     123: getfield      #6                  // Field serviceClassName:Ljava/lang/String;
     126: aastore
     127: invokevirtual #93                 // Method java/lang/reflect/Constructor.newInstance:([Ljava/lang/Object;)Ljava/lang/Object;
     130: astore_2
     131: goto          141
     134: astore_3
     135: aload_0
     136: aload_3
     137: invokevirtual #146                // Method serviceCreationFailure:(Ljava/lang/Exception;)Lorg/apache/hadoop/service/launcher/ServiceLaunchException;
     140: athrow
     141: aload_2
     142: instanceof    #147                // class org/apache/hadoop/service/Service
     145: ifne          171
     148: new           #111                // class org/apache/hadoop/service/launcher/ServiceLaunchException
     151: dup
     152: bipush        56
     154: ldc           #148                // String Not a service class: \"%s\"
     156: iconst_1
     157: anewarray     #92                 // class java/lang/Object
     160: dup
     161: iconst_0
     162: aload_0
     163: getfield      #6                  // Field serviceClassName:Ljava/lang/String;
     166: aastore
     167: invokespecial #113                // Method org/apache/hadoop/service/launcher/ServiceLaunchException."<init>":(ILjava/lang/String;[Ljava/lang/Object;)V
     170: athrow
     171: aload_0
     172: aload_2
     173: checkcast     #147                // class org/apache/hadoop/service/Service
     176: putfield      #15                 // Field service:Lorg/apache/hadoop/service/Service;
     179: aload_0
     180: getfield      #15                 // Field service:Lorg/apache/hadoop/service/Service;
     183: areturn
    Exception table:
       from    to  target type
          68    84    87   Class java/lang/NoSuchMethodException
          56   131   134   Class java/lang/Exception

  protected static org.apache.hadoop.util.ExitUtil$ExitException convertToExitException(java.lang.Throwable);
    Code:
       0: aload_0
       1: invokevirtual #149                // Method java/lang/Throwable.toString:()Ljava/lang/String;
       4: astore_2
       5: aload_0
       6: instanceof    #150                // class org/apache/hadoop/util/ExitCodeProvider
       9: ifeq          39
      12: aload_0
      13: checkcast     #150                // class org/apache/hadoop/util/ExitCodeProvider
      16: invokeinterface #151,  1          // InterfaceMethod org/apache/hadoop/util/ExitCodeProvider.getExitCode:()I
      21: istore_3
      22: aload_0
      23: invokevirtual #152                // Method java/lang/Throwable.getMessage:()Ljava/lang/String;
      26: astore_2
      27: aload_2
      28: ifnonnull     42
      31: aload_0
      32: invokevirtual #149                // Method java/lang/Throwable.toString:()Ljava/lang/String;
      35: astore_2
      36: goto          42
      39: bipush        50
      41: istore_3
      42: new           #111                // class org/apache/hadoop/service/launcher/ServiceLaunchException
      45: dup
      46: iload_3
      47: aload_2
      48: invokespecial #153                // Method org/apache/hadoop/service/launcher/ServiceLaunchException."<init>":(ILjava/lang/String;)V
      51: astore_1
      52: aload_1
      53: aload_0
      54: invokevirtual #154                // Method org/apache/hadoop/util/ExitUtil$ExitException.initCause:(Ljava/lang/Throwable;)Ljava/lang/Throwable;
      57: pop
      58: aload_1
      59: areturn

  protected org.apache.hadoop.service.launcher.ServiceLaunchException serviceCreationFailure(java.lang.Exception);
    Code:
       0: new           #111                // class org/apache/hadoop/service/launcher/ServiceLaunchException
       3: dup
       4: bipush        56
       6: aload_1
       7: invokespecial #155                // Method org/apache/hadoop/service/launcher/ServiceLaunchException."<init>":(ILjava/lang/Throwable;)V
      10: areturn

  protected void registerFailureHandling();
    Code:
       0: aload_0
       1: new           #156                // class org/apache/hadoop/service/launcher/InterruptEscalator
       4: dup
       5: aload_0
       6: sipush        30000
       9: invokespecial #157                // Method org/apache/hadoop/service/launcher/InterruptEscalator."<init>":(Lorg/apache/hadoop/service/launcher/ServiceLauncher;I)V
      12: putfield      #158                // Field interruptEscalator:Lorg/apache/hadoop/service/launcher/InterruptEscalator;
      15: aload_0
      16: getfield      #158                // Field interruptEscalator:Lorg/apache/hadoop/service/launcher/InterruptEscalator;
      19: ldc           #160                // String INT
      21: invokevirtual #161                // Method org/apache/hadoop/service/launcher/InterruptEscalator.register:(Ljava/lang/String;)V
      24: aload_0
      25: getfield      #158                // Field interruptEscalator:Lorg/apache/hadoop/service/launcher/InterruptEscalator;
      28: ldc           #162                // String TERM
      30: invokevirtual #161                // Method org/apache/hadoop/service/launcher/InterruptEscalator.register:(Ljava/lang/String;)V
      33: goto          49
      36: astore_1
      37: getstatic     #36                 // Field LOG:Lorg/slf4j/Logger;
      40: ldc           #164                // String {}
      42: aload_1
      43: aload_1
      44: invokeinterface #165,  4          // InterfaceMethod org/slf4j/Logger.warn:(Ljava/lang/String;Ljava/lang/Object;Ljava/lang/Object;)V
      49: new           #166                // class org/apache/hadoop/service/launcher/HadoopUncaughtExceptionHandler
      52: dup
      53: aload_0
      54: invokespecial #167                // Method org/apache/hadoop/service/launcher/HadoopUncaughtExceptionHandler."<init>":(Ljava/lang/Thread$UncaughtExceptionHandler;)V
      57: invokestatic  #168                // Method java/lang/Thread.setDefaultUncaughtExceptionHandler:(Ljava/lang/Thread$UncaughtExceptionHandler;)V
      60: return
    Exception table:
       from    to  target type
           0    33    36   Class java/lang/IllegalArgumentException

  public void uncaughtException(java.lang.Thread, java.lang.Throwable);
    Code:
       0: getstatic     #36                 // Field LOG:Lorg/slf4j/Logger;
       3: ldc           #169                // String Uncaught exception in thread {} -exiting
       5: aload_1
       6: aload_2
       7: invokeinterface #170,  4          // InterfaceMethod org/slf4j/Logger.error:(Ljava/lang/String;Ljava/lang/Object;Ljava/lang/Object;)V
      12: aload_0
      13: aload_2
      14: invokestatic  #116                // Method convertToExitException:(Ljava/lang/Throwable;)Lorg/apache/hadoop/util/ExitUtil$ExitException;
      17: invokevirtual #57                 // Method exit:(Lorg/apache/hadoop/util/ExitUtil$ExitException;)V
      20: return

  public java.lang.String getServiceName();
    Code:
       0: aload_0
       1: getfield      #15                 // Field service:Lorg/apache/hadoop/service/Service;
       4: astore_1
       5: aconst_null
       6: astore_2
       7: aload_1
       8: ifnull        22
      11: aload_1
      12: invokeinterface #171,  1          // InterfaceMethod org/apache/hadoop/service/Service.getName:()Ljava/lang/String;
      17: astore_2
      18: goto          22
      21: astore_3
      22: aload_2
      23: ifnull        46
      26: new           #20                 // class java/lang/StringBuilder
      29: dup
      30: invokespecial #30                 // Method java/lang/StringBuilder."<init>":()V
      33: ldc           #172                // String service
      35: invokevirtual #23                 // Method java/lang/StringBuilder.append:(Ljava/lang/String;)Ljava/lang/StringBuilder;
      38: aload_2
      39: invokevirtual #23                 // Method java/lang/StringBuilder.append:(Ljava/lang/String;)Ljava/lang/StringBuilder;
      42: invokevirtual #29                 // Method java/lang/StringBuilder.toString:()Ljava/lang/String;
      45: areturn
      46: new           #20                 // class java/lang/StringBuilder
      49: dup
      50: invokespecial #30                 // Method java/lang/StringBuilder."<init>":()V
      53: ldc           #172                // String service
      55: invokevirtual #23                 // Method java/lang/StringBuilder.append:(Ljava/lang/String;)Ljava/lang/StringBuilder;
      58: aload_0
      59: getfield      #12                 // Field serviceName:Ljava/lang/String;
      62: invokevirtual #23                 // Method java/lang/StringBuilder.append:(Ljava/lang/String;)Ljava/lang/StringBuilder;
      65: invokevirtual #29                 // Method java/lang/StringBuilder.toString:()Ljava/lang/String;
      68: areturn
    Exception table:
       from    to  target type
          11    18    21   Class java/lang/Exception

  protected void warn(java.lang.String);
    Code:
       0: getstatic     #36                 // Field LOG:Lorg/slf4j/Logger;
       3: invokeinterface #173,  1          // InterfaceMethod org/slf4j/Logger.isWarnEnabled:()Z
       8: ifeq          23
      11: getstatic     #36                 // Field LOG:Lorg/slf4j/Logger;
      14: aload_1
      15: invokeinterface #174,  2          // InterfaceMethod org/slf4j/Logger.warn:(Ljava/lang/String;)V
      20: goto          30
      23: getstatic     #51                 // Field java/lang/System.err:Ljava/io/PrintStream;
      26: aload_1
      27: invokevirtual #53                 // Method java/io/PrintStream.println:(Ljava/lang/String;)V
      30: return

  protected void error(java.lang.String, java.lang.Throwable);
    Code:
       0: new           #20                 // class java/lang/StringBuilder
       3: dup
       4: invokespecial #30                 // Method java/lang/StringBuilder."<init>":()V
       7: ldc           #175                // String Exception:
       9: invokevirtual #23                 // Method java/lang/StringBuilder.append:(Ljava/lang/String;)Ljava/lang/StringBuilder;
      12: aload_1
      13: invokevirtual #23                 // Method java/lang/StringBuilder.append:(Ljava/lang/String;)Ljava/lang/StringBuilder;
      16: invokevirtual #29                 // Method java/lang/StringBuilder.toString:()Ljava/lang/String;
      19: astore_3
      20: getstatic     #36                 // Field LOG:Lorg/slf4j/Logger;
      23: invokeinterface #176,  1          // InterfaceMethod org/slf4j/Logger.isErrorEnabled:()Z
      28: ifeq          44
      31: getstatic     #36                 // Field LOG:Lorg/slf4j/Logger;
      34: aload_3
      35: aload_2
      36: invokeinterface #177,  3          // InterfaceMethod org/slf4j/Logger.error:(Ljava/lang/String;Ljava/lang/Throwable;)V
      41: goto          65
      44: getstatic     #51                 // Field java/lang/System.err:Ljava/io/PrintStream;
      47: aload_3
      48: invokevirtual #53                 // Method java/io/PrintStream.println:(Ljava/lang/String;)V
      51: aload_2
      52: ifnull        65
      55: getstatic     #51                 // Field java/lang/System.err:Ljava/io/PrintStream;
      58: aload_2
      59: invokevirtual #149                // Method java/lang/Throwable.toString:()Ljava/lang/String;
      62: invokevirtual #53                 // Method java/io/PrintStream.println:(Ljava/lang/String;)V
      65: return

  protected void exit(int, java.lang.String);
    Code:
       0: iload_1
       1: aload_2
       2: invokestatic  #178                // Method org/apache/hadoop/util/ExitUtil.terminate:(ILjava/lang/String;)V
       5: return

  protected void exit(org.apache.hadoop.util.ExitUtil$ExitException);
    Code:
       0: aload_1
       1: invokestatic  #179                // Method org/apache/hadoop/util/ExitUtil.terminate:(Lorg/apache/hadoop/util/ExitUtil$ExitException;)V
       4: return

  protected java.lang.ClassLoader getClassLoader();
    Code:
       0: aload_0
       1: invokevirtual #180                // Method java/lang/Object.getClass:()Ljava/lang/Class;
       4: invokevirtual #181                // Method java/lang/Class.getClassLoader:()Ljava/lang/ClassLoader;
       7: areturn

  public java.util.List<java.lang.String> extractCommandOptions(org.apache.hadoop.conf.Configuration, java.util.List<java.lang.String>);
    Code:
       0: aload_2
       1: invokeinterface #182,  1          // InterfaceMethod java/util/List.size:()I
       6: istore_3
       7: iload_3
       8: iconst_1
       9: if_icmpgt     21
      12: new           #7                  // class java/util/ArrayList
      15: dup
      16: iconst_0
      17: invokespecial #9                  // Method java/util/ArrayList."<init>":(I)V
      20: areturn
      21: aload_2
      22: iconst_1
      23: iload_3
      24: invokeinterface #183,  3          // InterfaceMethod java/util/List.subList:(II)Ljava/util/List;
      29: astore        4
      31: aload_0
      32: aload_1
      33: aload         4
      35: invokevirtual #184                // Method parseCommandArgs:(Lorg/apache/hadoop/conf/Configuration;Ljava/util/List;)Ljava/util/List;
      38: areturn

  protected java.util.List<java.lang.String> parseCommandArgs(org.apache.hadoop.conf.Configuration, java.util.List<java.lang.String>);
    Code:
       0: aload_0
       1: getfield      #59                 // Field commandOptions:Lorg/apache/commons/cli/Options;
       4: ldc           #185                // String Command options have not been created
       6: invokestatic  #186                // Method com/google/common/base/Preconditions.checkNotNull:(Ljava/lang/Object;Ljava/lang/Object;)Ljava/lang/Object;
       9: pop
      10: new           #20                 // class java/lang/StringBuilder
      13: dup
      14: aload_2
      15: invokeinterface #182,  1          // InterfaceMethod java/util/List.size:()I
      20: bipush        32
      22: imul
      23: invokespecial #187                // Method java/lang/StringBuilder."<init>":(I)V
      26: astore_3
      27: aload_2
      28: invokeinterface #31,  1           // InterfaceMethod java/util/List.iterator:()Ljava/util/Iterator;
      33: astore        4
      35: aload         4
      37: invokeinterface #32,  1           // InterfaceMethod java/util/Iterator.hasNext:()Z
      42: ifeq          77
      45: aload         4
      47: invokeinterface #33,  1           // InterfaceMethod java/util/Iterator.next:()Ljava/lang/Object;
      52: checkcast     #34                 // class java/lang/String
      55: astore        5
      57: aload_3
      58: ldc           #188                // String \"
      60: invokevirtual #23                 // Method java/lang/StringBuilder.append:(Ljava/lang/String;)Ljava/lang/StringBuilder;
      63: aload         5
      65: invokevirtual #23                 // Method java/lang/StringBuilder.append:(Ljava/lang/String;)Ljava/lang/StringBuilder;
      68: ldc           #35                 // String \"
      70: invokevirtual #23                 // Method java/lang/StringBuilder.append:(Ljava/lang/String;)Ljava/lang/StringBuilder;
      73: pop
      74: goto          35
      77: getstatic     #36                 // Field LOG:Lorg/slf4j/Logger;
      80: ldc           #189                // String Command line: {}
      82: aload_3
      83: invokeinterface #100,  3          // InterfaceMethod org/slf4j/Logger.debug:(Ljava/lang/String;Ljava/lang/Object;)V
      88: aload_2
      89: aload_2
      90: invokeinterface #182,  1          // InterfaceMethod java/util/List.size:()I
      95: anewarray     #34                 // class java/lang/String
      98: invokeinterface #190,  2          // InterfaceMethod java/util/List.toArray:([Ljava/lang/Object;)[Ljava/lang/Object;
     103: checkcast     #191                // class "[Ljava/lang/String;"
     106: astore        4
     108: aload_0
     109: aload_1
     110: aload         4
     112: invokevirtual #192                // Method createGenericOptionsParser:(Lorg/apache/hadoop/conf/Configuration;[Ljava/lang/String;)Lorg/apache/hadoop/util/GenericOptionsParser;
     115: astore        5
     117: aload         5
     119: invokevirtual #193                // Method org/apache/hadoop/util/GenericOptionsParser.isParseSuccessful:()Z
     122: ifne          145
     125: new           #111                // class org/apache/hadoop/service/launcher/ServiceLaunchException
     128: dup
     129: bipush        40
     131: ldc           #194                // String Failed to parse:  %s
     133: iconst_1
     134: anewarray     #92                 // class java/lang/Object
     137: dup
     138: iconst_0
     139: aload_3
     140: aastore
     141: invokespecial #113                // Method org/apache/hadoop/service/launcher/ServiceLaunchException."<init>":(ILjava/lang/String;[Ljava/lang/Object;)V
     144: athrow
     145: aload         5
     147: invokevirtual #195                // Method org/apache/hadoop/util/GenericOptionsParser.getCommandLine:()Lorg/apache/commons/cli/CommandLine;
     150: astore        6
     152: aload         5
     154: invokevirtual #196                // Method org/apache/hadoop/util/GenericOptionsParser.getRemainingArgs:()[Ljava/lang/String;
     157: invokestatic  #13                 // Method java/util/Arrays.asList:([Ljava/lang/Object;)Ljava/util/List;
     160: astore        7
     162: getstatic     #36                 // Field LOG:Lorg/slf4j/Logger;
     165: ldc           #197                // String Remaining arguments {}
     167: aload         7
     169: invokeinterface #100,  3          // InterfaceMethod org/slf4j/Logger.debug:(Ljava/lang/String;Ljava/lang/Object;)V
     174: aload         6
     176: ldc           #75                 // String conf
     178: invokevirtual #198                // Method org/apache/commons/cli/CommandLine.hasOption:(Ljava/lang/String;)Z
     181: ifeq          272
     184: aload         6
     186: ldc           #75                 // String conf
     188: invokevirtual #199                // Method org/apache/commons/cli/CommandLine.getOptionValues:(Ljava/lang/String;)[Ljava/lang/String;
     191: astore        8
     193: aload_0
     194: aload         8
     196: invokevirtual #200                // Method verifyConfigurationFilesExist:([Ljava/lang/String;)V
     199: aload         8
     201: astore        9
     203: aload         9
     205: arraylength
     206: istore        10
     208: iconst_0
     209: istore        11
     211: iload         11
     213: iload         10
     215: if_icmpge     272
     218: aload         9
     220: iload         11
     222: aaload
     223: astore        12
     225: new           #201                // class java/io/File
     228: dup
     229: aload         12
     231: invokespecial #202                // Method java/io/File."<init>":(Ljava/lang/String;)V
     234: astore        13
     236: getstatic     #36                 // Field LOG:Lorg/slf4j/Logger;
     239: ldc           #203                // String Configuration files {}
     241: aload         13
     243: invokeinterface #100,  3          // InterfaceMethod org/slf4j/Logger.debug:(Ljava/lang/String;Ljava/lang/Object;)V
     248: aload_0
     249: getfield      #11                 // Field confResourceUrls:Ljava/util/List;
     252: aload         13
     254: invokevirtual #204                // Method java/io/File.toURI:()Ljava/net/URI;
     257: invokevirtual #205                // Method java/net/URI.toURL:()Ljava/net/URL;
     260: invokeinterface #206,  2          // InterfaceMethod java/util/List.add:(Ljava/lang/Object;)Z
     265: pop
     266: iinc          11, 1
     269: goto          211
     272: aload         6
     274: ldc           #80                 // String hadoopconf
     276: invokevirtual #198                // Method org/apache/commons/cli/CommandLine.hasOption:(Ljava/lang/String;)Z
     279: ifeq          318
     282: aload         6
     284: ldc           #80                 // String hadoopconf
     286: invokevirtual #199                // Method org/apache/commons/cli/CommandLine.getOptionValues:(Ljava/lang/String;)[Ljava/lang/String;
     289: invokestatic  #13                 // Method java/util/Arrays.asList:([Ljava/lang/Object;)Ljava/util/List;
     292: astore        8
     294: getstatic     #36                 // Field LOG:Lorg/slf4j/Logger;
     297: ldc           #207                // String Configuration classes {}
     299: aload         8
     301: invokeinterface #100,  3          // InterfaceMethod org/slf4j/Logger.debug:(Ljava/lang/String;Ljava/lang/Object;)V
     306: aload_0
     307: getfield      #10                 // Field confClassnames:Ljava/util/List;
     310: aload         8
     312: invokeinterface #14,  2           // InterfaceMethod java/util/List.addAll:(Ljava/util/Collection;)Z
     317: pop
     318: aload         7
     320: areturn
     321: astore        4
     323: new           #111                // class org/apache/hadoop/service/launcher/ServiceLaunchException
     326: dup
     327: bipush        40
     329: aload         4
     331: invokespecial #155                // Method org/apache/hadoop/service/launcher/ServiceLaunchException."<init>":(ILjava/lang/Throwable;)V
     334: athrow
     335: astore        4
     337: new           #111                // class org/apache/hadoop/service/launcher/ServiceLaunchException
     340: dup
     341: bipush        40
     343: ldc           #210                // String Failed to parse:  %s : %s
     345: iconst_2
     346: anewarray     #92                 // class java/lang/Object
     349: dup
     350: iconst_0
     351: aload_3
     352: aastore
     353: dup
     354: iconst_1
     355: aload         4
     357: aastore
     358: invokespecial #113                // Method org/apache/hadoop/service/launcher/ServiceLaunchException."<init>":(ILjava/lang/String;[Ljava/lang/Object;)V
     361: athrow
    Exception table:
       from    to  target type
          88   320   321   Class java/io/IOException
          88   320   335   Class java/lang/RuntimeException

  protected org.apache.hadoop.util.GenericOptionsParser createGenericOptionsParser(org.apache.hadoop.conf.Configuration, java.lang.String[]) throws java.io.IOException;
    Code:
       0: new           #211                // class org/apache/hadoop/service/launcher/ServiceLauncher$MinimalGenericOptionsParser
       3: dup
       4: aload_1
       5: aload_0
       6: getfield      #59                 // Field commandOptions:Lorg/apache/commons/cli/Options;
       9: aload_2
      10: invokespecial #212                // Method org/apache/hadoop/service/launcher/ServiceLauncher$MinimalGenericOptionsParser."<init>":(Lorg/apache/hadoop/conf/Configuration;Lorg/apache/commons/cli/Options;[Ljava/lang/String;)V
      13: areturn

  protected void verifyConfigurationFilesExist(java.lang.String[]);
    Code:
       0: aload_1
       1: ifnonnull     5
       4: return
       5: aload_1
       6: astore_2
       7: aload_2
       8: arraylength
       9: istore_3
      10: iconst_0
      11: istore        4
      13: iload         4
      15: iload_3
      16: if_icmpge     89
      19: aload_2
      20: iload         4
      22: aaload
      23: astore        5
      25: new           #201                // class java/io/File
      28: dup
      29: aload         5
      31: invokespecial #202                // Method java/io/File."<init>":(Ljava/lang/String;)V
      34: astore        6
      36: getstatic     #36                 // Field LOG:Lorg/slf4j/Logger;
      39: ldc           #213                // String Conf file {}
      41: aload         6
      43: invokevirtual #214                // Method java/io/File.getAbsolutePath:()Ljava/lang/String;
      46: invokeinterface #100,  3          // InterfaceMethod org/slf4j/Logger.debug:(Ljava/lang/String;Ljava/lang/Object;)V
      51: aload         6
      53: invokevirtual #215                // Method java/io/File.exists:()Z
      56: ifne          83
      59: new           #111                // class org/apache/hadoop/service/launcher/ServiceLaunchException
      62: dup
      63: bipush        44
      65: ldc           #216                // String --conf: configuration file not found: %s
      67: iconst_1
      68: anewarray     #92                 // class java/lang/Object
      71: dup
      72: iconst_0
      73: aload         6
      75: invokevirtual #214                // Method java/io/File.getAbsolutePath:()Ljava/lang/String;
      78: aastore
      79: invokespecial #113                // Method org/apache/hadoop/service/launcher/ServiceLaunchException."<init>":(ILjava/lang/String;[Ljava/lang/Object;)V
      82: athrow
      83: iinc          4, 1
      86: goto          13
      89: return

  protected static java.lang.String startupShutdownMessage(java.lang.String, java.util.List<java.lang.String>);
    Code:
       0: invokestatic  #217                // Method org/apache/hadoop/net/NetUtils.getHostname:()Ljava/lang/String;
       3: astore_2
       4: aload_0
       5: aload_2
       6: aload_1
       7: aload_1
       8: invokeinterface #182,  1          // InterfaceMethod java/util/List.size:()I
      13: anewarray     #34                 // class java/lang/String
      16: invokeinterface #190,  2          // InterfaceMethod java/util/List.toArray:([Ljava/lang/Object;)[Ljava/lang/Object;
      21: checkcast     #191                // class "[Ljava/lang/String;"
      24: invokestatic  #218                // Method org/apache/hadoop/util/StringUtils.createStartupShutdownMessage:(Ljava/lang/String;Ljava/lang/String;[Ljava/lang/String;)Ljava/lang/String;
      27: areturn

  protected static void exitWithMessage(int, java.lang.String);
    Code:
       0: new           #111                // class org/apache/hadoop/service/launcher/ServiceLaunchException
       3: dup
       4: iload_0
       5: aload_1
       6: invokespecial #153                // Method org/apache/hadoop/service/launcher/ServiceLaunchException."<init>":(ILjava/lang/String;)V
       9: invokestatic  #179                // Method org/apache/hadoop/util/ExitUtil.terminate:(Lorg/apache/hadoop/util/ExitUtil$ExitException;)V
      12: return

  protected static void exitWithUsageMessage();
    Code:
       0: bipush        42
       2: ldc           #62                 // String Usage: ServiceLauncher [--conf <conf file>] [--hadoopconf <configuration classname>] service-classname <service arguments>
       4: invokestatic  #219                // Method exitWithMessage:(ILjava/lang/String;)V
       7: return

  public static void main(java.lang.String[]);
    Code:
       0: aload_0
       1: invokestatic  #13                 // Method java/util/Arrays.asList:([Ljava/lang/Object;)Ljava/util/List;
       4: invokestatic  #220                // Method serviceMain:(Ljava/util/List;)V
       7: return

  public static void serviceMain(java.lang.String...);
    Code:
       0: aload_0
       1: invokestatic  #13                 // Method java/util/Arrays.asList:([Ljava/lang/Object;)Ljava/util/List;
       4: invokestatic  #220                // Method serviceMain:(Ljava/util/List;)V
       7: return

  public static void serviceMain(java.util.List<java.lang.String>);
    Code:
       0: aload_0
       1: invokeinterface #221,  1          // InterfaceMethod java/util/List.isEmpty:()Z
       6: ifeq          15
       9: invokestatic  #222                // Method exitWithUsageMessage:()V
      12: goto          38
      15: new           #1                  // class org/apache/hadoop/service/launcher/ServiceLauncher
      18: dup
      19: aload_0
      20: iconst_0
      21: invokeinterface #223,  2          // InterfaceMethod java/util/List.get:(I)Ljava/lang/Object;
      26: checkcast     #34                 // class java/lang/String
      29: invokespecial #224                // Method "<init>":(Ljava/lang/String;)V
      32: astore_1
      33: aload_1
      34: aload_0
      35: invokevirtual #225                // Method launchServiceAndExit:(Ljava/util/List;)V
      38: return

  static {};
    Code:
       0: ldc           #1                  // class org/apache/hadoop/service/launcher/ServiceLauncher
       2: invokestatic  #226                // Method org/slf4j/LoggerFactory.getLogger:(Ljava/lang/Class;)Lorg/slf4j/Logger;
       5: putstatic     #36                 // Field LOG:Lorg/slf4j/Logger;
       8: iconst_3
       9: anewarray     #34                 // class java/lang/String
      12: dup
      13: iconst_0
      14: ldc           #227                // String org.apache.hadoop.conf.Configuration
      16: aastore
      17: dup
      18: iconst_1
      19: ldc           #228                // String org.apache.hadoop.hdfs.HdfsConfiguration
      21: aastore
      22: dup
      23: iconst_2
      24: ldc           #229                // String org.apache.hadoop.yarn.conf.YarnConfiguration
      26: aastore
      27: putstatic     #8                  // Field DEFAULT_CONFIGS:[Ljava/lang/String;
      30: return
}
