Compiled from "CommitManager.java"
class org.infinispan.statetransfer.CommitManager$DiscardPolicy {
  private boolean discardST;

  private boolean discardXSiteST;

  private org.infinispan.statetransfer.CommitManager$DiscardPolicy(boolean, boolean);
    Code:
       0: aload_0
       1: invokespecial #2                  // Method java/lang/Object."<init>":()V
       4: aload_0
       5: iload_1
       6: putfield      #3                  // Field discardST:Z
       9: aload_0
      10: iload_2
      11: putfield      #4                  // Field discardXSiteST:Z
      14: return

  public final synchronized boolean ignore(org.infinispan.context.Flag);
    Code:
       0: aload_0
       1: getfield      #3                  // Field discardST:Z
       4: ifeq          14
       7: aload_1
       8: getstatic     #5                  // Field org/infinispan/context/Flag.PUT_FOR_STATE_TRANSFER:Lorg/infinispan/context/Flag;
      11: if_acmpeq     28
      14: aload_0
      15: getfield      #4                  // Field discardXSiteST:Z
      18: ifeq          32
      21: aload_1
      22: getstatic     #6                  // Field org/infinispan/context/Flag.PUT_FOR_X_SITE_STATE_TRANSFER:Lorg/infinispan/context/Flag;
      25: if_acmpne     32
      28: iconst_1
      29: goto          33
      32: iconst_0
      33: ireturn

  public synchronized boolean update(boolean, boolean);
    Code:
       0: aload_0
       1: iload_1
       2: putfield      #3                  // Field discardST:Z
       5: aload_0
       6: iload_2
       7: putfield      #4                  // Field discardXSiteST:Z
      10: aload_0
      11: getfield      #3                  // Field discardST:Z
      14: ifne          28
      17: aload_0
      18: getfield      #4                  // Field discardXSiteST:Z
      21: ifne          28
      24: iconst_1
      25: goto          29
      28: iconst_0
      29: ireturn

  public boolean equals(java.lang.Object);
    Code:
       0: aload_0
       1: aload_1
       2: if_acmpne     7
       5: iconst_1
       6: ireturn
       7: aload_1
       8: ifnull        22
      11: aload_0
      12: invokevirtual #7                  // Method java/lang/Object.getClass:()Ljava/lang/Class;
      15: aload_1
      16: invokevirtual #7                  // Method java/lang/Object.getClass:()Ljava/lang/Class;
      19: if_acmpeq     24
      22: iconst_0
      23: ireturn
      24: aload_1
      25: checkcast     #8                  // class org/infinispan/statetransfer/CommitManager$DiscardPolicy
      28: astore_2
      29: aload_0
      30: getfield      #3                  // Field discardST:Z
      33: aload_2
      34: getfield      #3                  // Field discardST:Z
      37: if_icmpne     55
      40: aload_0
      41: getfield      #4                  // Field discardXSiteST:Z
      44: aload_2
      45: getfield      #4                  // Field discardXSiteST:Z
      48: if_icmpne     55
      51: iconst_1
      52: goto          56
      55: iconst_0
      56: ireturn

  public int hashCode();
    Code:
       0: aload_0
       1: getfield      #3                  // Field discardST:Z
       4: ifeq          11
       7: iconst_1
       8: goto          12
      11: iconst_0
      12: istore_1
      13: bipush        31
      15: iload_1
      16: imul
      17: aload_0
      18: getfield      #4                  // Field discardXSiteST:Z
      21: ifeq          28
      24: iconst_1
      25: goto          29
      28: iconst_0
      29: iadd
      30: istore_1
      31: iload_1
      32: ireturn

  public java.lang.String toString();
    Code:
       0: new           #9                  // class java/lang/StringBuilder
       3: dup
       4: invokespecial #10                 // Method java/lang/StringBuilder."<init>":()V
       7: ldc           #11                 // String DiscardPolicy{discardStateTransfer=
       9: invokevirtual #12                 // Method java/lang/StringBuilder.append:(Ljava/lang/String;)Ljava/lang/StringBuilder;
      12: aload_0
      13: getfield      #3                  // Field discardST:Z
      16: invokevirtual #13                 // Method java/lang/StringBuilder.append:(Z)Ljava/lang/StringBuilder;
      19: ldc           #14                 // String , discardXSiteStateTransfer=
      21: invokevirtual #12                 // Method java/lang/StringBuilder.append:(Ljava/lang/String;)Ljava/lang/StringBuilder;
      24: aload_0
      25: getfield      #4                  // Field discardXSiteST:Z
      28: invokevirtual #13                 // Method java/lang/StringBuilder.append:(Z)Ljava/lang/StringBuilder;
      31: bipush        125
      33: invokevirtual #15                 // Method java/lang/StringBuilder.append:(C)Ljava/lang/StringBuilder;
      36: invokevirtual #16                 // Method java/lang/StringBuilder.toString:()Ljava/lang/String;
      39: areturn

  org.infinispan.statetransfer.CommitManager$DiscardPolicy(boolean, boolean, org.infinispan.statetransfer.CommitManager$1);
    Code:
       0: aload_0
       1: iload_1
       2: iload_2
       3: invokespecial #1                  // Method "<init>":(ZZ)V
       6: return
}
