Compiled from "OutboundTransferTask.java"
class org.infinispan.statetransfer.OutboundTransferTask$2 implements org.infinispan.persistence.spi.AdvancedCacheLoader$CacheLoaderTask {
  final org.infinispan.statetransfer.OutboundTransferTask this$0;

  org.infinispan.statetransfer.OutboundTransferTask$2(org.infinispan.statetransfer.OutboundTransferTask);
    Code:
       0: aload_0
       1: aload_1
       2: putfield      #1                  // Field this$0:Lorg/infinispan/statetransfer/OutboundTransferTask;
       5: aload_0
       6: invokespecial #2                  // Method java/lang/Object."<init>":()V
       9: return

  public void processEntry(org.infinispan.marshall.core.MarshalledEntry, org.infinispan.persistence.spi.AdvancedCacheLoader$TaskContext) throws java.lang.InterruptedException;
    Code:
       0: aload_0
       1: getfield      #1                  // Field this$0:Lorg/infinispan/statetransfer/OutboundTransferTask;
       4: invokestatic  #3                  // Method org/infinispan/statetransfer/OutboundTransferTask.access$100:(Lorg/infinispan/statetransfer/OutboundTransferTask;)Lorg/infinispan/distribution/ch/ConsistentHash;
       7: aload_1
       8: invokeinterface #4,  1            // InterfaceMethod org/infinispan/marshall/core/MarshalledEntry.getKey:()Ljava/lang/Object;
      13: invokeinterface #5,  2            // InterfaceMethod org/infinispan/distribution/ch/ConsistentHash.getSegment:(Ljava/lang/Object;)I
      18: istore_3
      19: aload_0
      20: getfield      #1                  // Field this$0:Lorg/infinispan/statetransfer/OutboundTransferTask;
      23: invokestatic  #6                  // Method org/infinispan/statetransfer/OutboundTransferTask.access$200:(Lorg/infinispan/statetransfer/OutboundTransferTask;)Ljava/util/Set;
      26: iload_3
      27: invokestatic  #7                  // Method java/lang/Integer.valueOf:(I)Ljava/lang/Integer;
      30: invokeinterface #8,  2            // InterfaceMethod java/util/Set.contains:(Ljava/lang/Object;)Z
      35: ifeq          101
      38: aload_0
      39: getfield      #1                  // Field this$0:Lorg/infinispan/statetransfer/OutboundTransferTask;
      42: invokestatic  #9                  // Method org/infinispan/statetransfer/OutboundTransferTask.access$300:(Lorg/infinispan/statetransfer/OutboundTransferTask;)Lorg/infinispan/container/InternalEntryFactory;
      45: aload_1
      46: invokeinterface #4,  1            // InterfaceMethod org/infinispan/marshall/core/MarshalledEntry.getKey:()Ljava/lang/Object;
      51: aload_1
      52: invokeinterface #10,  1           // InterfaceMethod org/infinispan/marshall/core/MarshalledEntry.getValue:()Ljava/lang/Object;
      57: aload_1
      58: invokeinterface #11,  1           // InterfaceMethod org/infinispan/marshall/core/MarshalledEntry.getMetadata:()Lorg/infinispan/metadata/InternalMetadata;
      63: invokeinterface #12,  4           // InterfaceMethod org/infinispan/container/InternalEntryFactory.create:(Ljava/lang/Object;Ljava/lang/Object;Lorg/infinispan/metadata/Metadata;)Lorg/infinispan/container/entries/InternalCacheEntry;
      68: astore        4
      70: aload_0
      71: getfield      #1                  // Field this$0:Lorg/infinispan/statetransfer/OutboundTransferTask;
      74: aload         4
      76: iload_3
      77: invokestatic  #13                 // Method org/infinispan/statetransfer/OutboundTransferTask.access$400:(Lorg/infinispan/statetransfer/OutboundTransferTask;Lorg/infinispan/container/entries/InternalCacheEntry;I)V
      80: goto          101
      83: astore        4
      85: invokestatic  #15                 // Method org/infinispan/statetransfer/OutboundTransferTask.access$500:()Lorg/infinispan/util/logging/Log;
      88: aload_1
      89: invokeinterface #4,  1            // InterfaceMethod org/infinispan/marshall/core/MarshalledEntry.getKey:()Ljava/lang/Object;
      94: aload         4
      96: invokeinterface #16,  3           // InterfaceMethod org/infinispan/util/logging/Log.failedLoadingValueFromCacheStore:(Ljava/lang/Object;Ljava/lang/Exception;)V
     101: return
    Exception table:
       from    to  target type
          38    80    83   Class org/infinispan/commons/CacheException
}
