Compiled from "TransactionInfo.java"
public class org.infinispan.statetransfer.TransactionInfo$Externalizer extends org.infinispan.commons.marshall.AbstractExternalizer<org.infinispan.statetransfer.TransactionInfo> {
  public org.infinispan.statetransfer.TransactionInfo$Externalizer();
    Code:
       0: aload_0
       1: invokespecial #1                  // Method org/infinispan/commons/marshall/AbstractExternalizer."<init>":()V
       4: return

  public java.lang.Integer getId();
    Code:
       0: bipush        84
       2: invokestatic  #3                  // Method java/lang/Integer.valueOf:(I)Ljava/lang/Integer;
       5: areturn

  public java.util.Set<java.lang.Class<? extends org.infinispan.statetransfer.TransactionInfo>> getTypeClasses();
    Code:
       0: ldc           #4                  // class org/infinispan/statetransfer/TransactionInfo
       2: invokestatic  #5                  // Method java/util/Collections.singleton:(Ljava/lang/Object;)Ljava/util/Set;
       5: areturn

  public void writeObject(java.io.ObjectOutput, org.infinispan.statetransfer.TransactionInfo) throws java.io.IOException;
    Code:
       0: aload_1
       1: aload_2
       2: invokestatic  #6                  // Method org/infinispan/statetransfer/TransactionInfo.access$000:(Lorg/infinispan/statetransfer/TransactionInfo;)Lorg/infinispan/transaction/xa/GlobalTransaction;
       5: invokeinterface #7,  2            // InterfaceMethod java/io/ObjectOutput.writeObject:(Ljava/lang/Object;)V
      10: aload_1
      11: aload_2
      12: invokestatic  #8                  // Method org/infinispan/statetransfer/TransactionInfo.access$100:(Lorg/infinispan/statetransfer/TransactionInfo;)I
      15: invokeinterface #9,  2            // InterfaceMethod java/io/ObjectOutput.writeInt:(I)V
      20: aload_1
      21: aload_2
      22: invokestatic  #10                 // Method org/infinispan/statetransfer/TransactionInfo.access$200:(Lorg/infinispan/statetransfer/TransactionInfo;)[Lorg/infinispan/commands/write/WriteCommand;
      25: invokeinterface #7,  2            // InterfaceMethod java/io/ObjectOutput.writeObject:(Ljava/lang/Object;)V
      30: aload_1
      31: aload_2
      32: invokestatic  #11                 // Method org/infinispan/statetransfer/TransactionInfo.access$300:(Lorg/infinispan/statetransfer/TransactionInfo;)Ljava/util/Set;
      35: invokeinterface #7,  2            // InterfaceMethod java/io/ObjectOutput.writeObject:(Ljava/lang/Object;)V
      40: return

  public org.infinispan.statetransfer.TransactionInfo readObject(java.io.ObjectInput) throws java.io.IOException, java.lang.ClassNotFoundException;
    Code:
       0: aload_1
       1: invokeinterface #12,  1           // InterfaceMethod java/io/ObjectInput.readObject:()Ljava/lang/Object;
       6: checkcast     #13                 // class org/infinispan/transaction/xa/GlobalTransaction
       9: astore_2
      10: aload_1
      11: invokeinterface #14,  1           // InterfaceMethod java/io/ObjectInput.readInt:()I
      16: istore_3
      17: aload_1
      18: invokeinterface #12,  1           // InterfaceMethod java/io/ObjectInput.readObject:()Ljava/lang/Object;
      23: checkcast     #15                 // class "[Lorg/infinispan/commands/write/WriteCommand;"
      26: checkcast     #15                 // class "[Lorg/infinispan/commands/write/WriteCommand;"
      29: astore        4
      31: aload_1
      32: invokeinterface #12,  1           // InterfaceMethod java/io/ObjectInput.readObject:()Ljava/lang/Object;
      37: checkcast     #16                 // class java/util/Set
      40: astore        5
      42: new           #4                  // class org/infinispan/statetransfer/TransactionInfo
      45: dup
      46: aload_2
      47: iload_3
      48: aload         4
      50: aload         5
      52: invokespecial #17                 // Method org/infinispan/statetransfer/TransactionInfo."<init>":(Lorg/infinispan/transaction/xa/GlobalTransaction;I[Lorg/infinispan/commands/write/WriteCommand;Ljava/util/Set;)V
      55: areturn

  public java.lang.Object readObject(java.io.ObjectInput) throws java.io.IOException, java.lang.ClassNotFoundException;
    Code:
       0: aload_0
       1: aload_1
       2: invokevirtual #18                 // Method readObject:(Ljava/io/ObjectInput;)Lorg/infinispan/statetransfer/TransactionInfo;
       5: areturn

  public void writeObject(java.io.ObjectOutput, java.lang.Object) throws java.io.IOException;
    Code:
       0: aload_0
       1: aload_1
       2: aload_2
       3: checkcast     #4                  // class org/infinispan/statetransfer/TransactionInfo
       6: invokevirtual #19                 // Method writeObject:(Ljava/io/ObjectOutput;Lorg/infinispan/statetransfer/TransactionInfo;)V
       9: return
}
