Compiled from "ConnectionTableNIO.java"
class org.jgroups.blocks.ConnectionTableNIO$2 implements java.util.concurrent.ThreadFactory {
  final org.jgroups.blocks.ConnectionTableNIO this$0;

  org.jgroups.blocks.ConnectionTableNIO$2(org.jgroups.blocks.ConnectionTableNIO);
    Code:
       0: aload_0
       1: aload_1
       2: putfield      #1                  // Field this$0:Lorg/jgroups/blocks/ConnectionTableNIO;
       5: aload_0
       6: invokespecial #2                  // Method java/lang/Object."<init>":()V
       9: return

  public java.lang.Thread newThread(java.lang.Runnable);
    Code:
       0: new           #3                  // class java/lang/Thread
       3: dup
       4: aload_1
       5: ldc           #4                  // String ConnectionTableNIO.Thread
       7: invokespecial #5                  // Method java/lang/Thread."<init>":(Ljava/lang/Runnable;Ljava/lang/String;)V
      10: astore_2
      11: aload_2
      12: iconst_1
      13: invokevirtual #6                  // Method java/lang/Thread.setDaemon:(Z)V
      16: aload_0
      17: getfield      #1                  // Field this$0:Lorg/jgroups/blocks/ConnectionTableNIO;
      20: invokestatic  #7                  // Method org/jgroups/blocks/ConnectionTableNIO.access$200:(Lorg/jgroups/blocks/ConnectionTableNIO;)Ljava/util/List;
      23: aload_2
      24: invokeinterface #8,  2            // InterfaceMethod java/util/List.add:(Ljava/lang/Object;)Z
      29: pop
      30: aload_2
      31: areturn
}
