Compiled from "package.scala"
public class scala.collection.parallel.immutable.Repetition$ParIterator$ {
  private final scala.collection.parallel.immutable.Repetition $outer;

  public int $lessinit$greater$default$1();
    Code:
       0: iconst_0
       1: ireturn

  public int $lessinit$greater$default$2();
    Code:
       0: aload_0
       1: getfield      #14                 // Field $outer:Lscala/collection/parallel/immutable/Repetition;
       4: invokevirtual #19                 // Method scala/collection/parallel/immutable/Repetition.length:()I
       7: ireturn

  public T $lessinit$greater$default$3();
    Code:
       0: aload_0
       1: getfield      #14                 // Field $outer:Lscala/collection/parallel/immutable/Repetition;
       4: getfield      #25                 // Field scala/collection/parallel/immutable/Repetition.scala$collection$parallel$immutable$Repetition$$elem:Ljava/lang/Object;
       7: areturn

  public scala.collection.parallel.immutable.Repetition$ParIterator$(scala.collection.parallel.immutable.Repetition<T>);
    Code:
       0: aload_1
       1: ifnonnull     6
       4: aconst_null
       5: athrow
       6: aload_0
       7: aload_1
       8: putfield      #14                 // Field $outer:Lscala/collection/parallel/immutable/Repetition;
      11: aload_0
      12: invokespecial #30                 // Method java/lang/Object."<init>":()V
      15: return
}
