Compiled from "ClusterAssignmentData.java"
final class org.apache.bookkeeper.stream.proto.cluster.ClusterAssignmentData$ServersDefaultEntryHolder {
  static final com.google.protobuf.MapEntry<java.lang.String, org.apache.bookkeeper.stream.proto.cluster.ServerAssignmentData> defaultEntry;

  private org.apache.bookkeeper.stream.proto.cluster.ClusterAssignmentData$ServersDefaultEntryHolder();
    Code:
       0: aload_0
       1: invokespecial #1                  // Method java/lang/Object."<init>":()V
       4: return

  static {};
    Code:
       0: getstatic     #2                  // Field org/apache/bookkeeper/stream/proto/cluster/Cluster.internal_static_bookkeeper_proto_cluster_ClusterAssignmentData_ServersEntry_descriptor:Lcom/google/protobuf/Descriptors$Descriptor;
       3: getstatic     #3                  // Field com/google/protobuf/WireFormat$FieldType.STRING:Lcom/google/protobuf/WireFormat$FieldType;
       6: ldc           #4                  // String
       8: getstatic     #5                  // Field com/google/protobuf/WireFormat$FieldType.MESSAGE:Lcom/google/protobuf/WireFormat$FieldType;
      11: invokestatic  #6                  // Method org/apache/bookkeeper/stream/proto/cluster/ServerAssignmentData.getDefaultInstance:()Lorg/apache/bookkeeper/stream/proto/cluster/ServerAssignmentData;
      14: invokestatic  #7                  // Method com/google/protobuf/MapEntry.newDefaultInstance:(Lcom/google/protobuf/Descriptors$Descriptor;Lcom/google/protobuf/WireFormat$FieldType;Ljava/lang/Object;Lcom/google/protobuf/WireFormat$FieldType;Ljava/lang/Object;)Lcom/google/protobuf/MapEntry;
      17: putstatic     #8                  // Field defaultEntry:Lcom/google/protobuf/MapEntry;
      20: return
}
