Compiled from "LanguageEndpoint.java"
public class org.apache.camel.component.language.LanguageEndpoint extends org.apache.camel.component.ResourceEndpoint {
  private org.apache.camel.spi.Language language;

  private org.apache.camel.Expression expression;

  private boolean contentResolvedFromResource;

  private java.lang.String languageName;

  private java.lang.String resourceUri;

  private java.lang.String script;

  private boolean transform;

  private boolean binary;

  private boolean cacheScript;

  public org.apache.camel.component.language.LanguageEndpoint();
    Code:
       0: aload_0
       1: invokespecial #43                 // Method org/apache/camel/component/ResourceEndpoint."<init>":()V
       4: aload_0
       5: iconst_1
       6: putfield      #45                 // Field transform:Z
       9: aload_0
      10: iconst_1
      11: invokevirtual #49                 // Method setContentCache:(Z)V
      14: return

  public org.apache.camel.component.language.LanguageEndpoint(java.lang.String, org.apache.camel.Component, org.apache.camel.spi.Language, org.apache.camel.Expression, java.lang.String);
    Code:
       0: aload_0
       1: aload_1
       2: aload_2
       3: aload         5
       5: invokespecial #55                 // Method org/apache/camel/component/ResourceEndpoint."<init>":(Ljava/lang/String;Lorg/apache/camel/Component;Ljava/lang/String;)V
       8: aload_0
       9: iconst_1
      10: putfield      #45                 // Field transform:Z
      13: aload_0
      14: aload_3
      15: putfield      #57                 // Field language:Lorg/apache/camel/spi/Language;
      18: aload_0
      19: aload         4
      21: putfield      #59                 // Field expression:Lorg/apache/camel/Expression;
      24: aload_0
      25: iconst_1
      26: invokevirtual #49                 // Method setContentCache:(Z)V
      29: return

  public org.apache.camel.Producer createProducer() throws java.lang.Exception;
    Code:
       0: aload_0
       1: invokevirtual #70                 // Method getCamelContext:()Lorg/apache/camel/CamelContext;
       4: ldc           #72                 // String CamelContext
       6: aload_0
       7: invokestatic  #78                 // Method org/apache/camel/util/ObjectHelper.notNull:(Ljava/lang/Object;Ljava/lang/String;Ljava/lang/Object;)Ljava/lang/Object;
      10: pop
      11: aload_0
      12: getfield      #57                 // Field language:Lorg/apache/camel/spi/Language;
      15: ifnonnull     42
      18: aload_0
      19: getfield      #80                 // Field languageName:Ljava/lang/String;
      22: ifnull        42
      25: aload_0
      26: aload_0
      27: invokevirtual #70                 // Method getCamelContext:()Lorg/apache/camel/CamelContext;
      30: aload_0
      31: getfield      #80                 // Field languageName:Ljava/lang/String;
      34: invokeinterface #86,  2           // InterfaceMethod org/apache/camel/CamelContext.resolveLanguage:(Ljava/lang/String;)Lorg/apache/camel/spi/Language;
      39: putfield      #57                 // Field language:Lorg/apache/camel/spi/Language;
      42: aload_0
      43: getfield      #57                 // Field language:Lorg/apache/camel/spi/Language;
      46: ldc           #87                 // String language
      48: aload_0
      49: invokestatic  #78                 // Method org/apache/camel/util/ObjectHelper.notNull:(Ljava/lang/Object;Ljava/lang/String;Ljava/lang/Object;)Ljava/lang/Object;
      52: pop
      53: aload_0
      54: getfield      #89                 // Field cacheScript:Z
      57: ifeq          103
      60: aload_0
      61: getfield      #59                 // Field expression:Lorg/apache/camel/Expression;
      64: ifnonnull     103
      67: aload_0
      68: getfield      #91                 // Field script:Ljava/lang/String;
      71: ifnull        103
      74: aload_0
      75: aload_0
      76: aload_0
      77: getfield      #91                 // Field script:Ljava/lang/String;
      80: invokevirtual #95                 // Method resolveScript:(Ljava/lang/String;)Ljava/lang/String;
      83: putfield      #91                 // Field script:Ljava/lang/String;
      86: aload_0
      87: aload_0
      88: getfield      #57                 // Field language:Lorg/apache/camel/spi/Language;
      91: aload_0
      92: getfield      #91                 // Field script:Ljava/lang/String;
      95: invokeinterface #101,  2          // InterfaceMethod org/apache/camel/spi/Language.createExpression:(Ljava/lang/String;)Lorg/apache/camel/Expression;
     100: putfield      #59                 // Field expression:Lorg/apache/camel/Expression;
     103: new           #103                // class org/apache/camel/component/language/LanguageProducer
     106: dup
     107: aload_0
     108: invokespecial #106                // Method org/apache/camel/component/language/LanguageProducer."<init>":(Lorg/apache/camel/component/language/LanguageEndpoint;)V
     111: areturn

  public org.apache.camel.Consumer createConsumer(org.apache.camel.Processor) throws java.lang.Exception;
    Code:
       0: new           #110                // class org/apache/camel/RuntimeCamelException
       3: dup
       4: new           #112                // class java/lang/StringBuilder
       7: dup
       8: invokespecial #113                // Method java/lang/StringBuilder."<init>":()V
      11: ldc           #115                // String Cannot consume to a LanguageEndpoint:
      13: invokevirtual #119                // Method java/lang/StringBuilder.append:(Ljava/lang/String;)Ljava/lang/StringBuilder;
      16: aload_0
      17: invokevirtual #123                // Method getEndpointUri:()Ljava/lang/String;
      20: invokevirtual #119                // Method java/lang/StringBuilder.append:(Ljava/lang/String;)Ljava/lang/StringBuilder;
      23: invokevirtual #126                // Method java/lang/StringBuilder.toString:()Ljava/lang/String;
      26: invokespecial #129                // Method org/apache/camel/RuntimeCamelException."<init>":(Ljava/lang/String;)V
      29: athrow

  protected java.lang.String resolveScript(java.lang.String) throws java.io.IOException;
    Code:
       0: aload_1
       1: invokestatic  #139                // Method org/apache/camel/util/ResourceHelper.hasScheme:(Ljava/lang/String;)Z
       4: ifeq          41
       7: aload_0
       8: aload_1
       9: invokevirtual #143                // Method loadResource:(Ljava/lang/String;)Ljava/io/InputStream;
      12: astore_2
      13: aload_0
      14: invokevirtual #70                 // Method getCamelContext:()Lorg/apache/camel/CamelContext;
      17: invokeinterface #147,  1          // InterfaceMethod org/apache/camel/CamelContext.getTypeConverter:()Lorg/apache/camel/TypeConverter;
      22: ldc           #149                // class java/lang/String
      24: aload_2
      25: invokeinterface #155,  3          // InterfaceMethod org/apache/camel/TypeConverter.convertTo:(Ljava/lang/Class;Ljava/lang/Object;)Ljava/lang/Object;
      30: checkcast     #149                // class java/lang/String
      33: astore_3
      34: aload_2
      35: invokestatic  #161                // Method org/apache/camel/util/IOHelper.close:(Ljava/io/Closeable;)V
      38: goto          43
      41: aload_1
      42: astore_3
      43: aload_3
      44: areturn

  public boolean isSingleton();
    Code:
       0: iconst_1
       1: ireturn

  protected java.lang.String createEndpointUri();
    Code:
       0: aload_0
       1: getfield      #91                 // Field script:Ljava/lang/String;
       4: astore_1
       5: aload_1
       6: ldc           #171                // String UTF-8
       8: invokestatic  #177                // Method java/net/URLEncoder.encode:(Ljava/lang/String;Ljava/lang/String;)Ljava/lang/String;
      11: astore_1
      12: goto          16
      15: astore_2
      16: new           #112                // class java/lang/StringBuilder
      19: dup
      20: invokespecial #113                // Method java/lang/StringBuilder."<init>":()V
      23: aload_0
      24: getfield      #80                 // Field languageName:Ljava/lang/String;
      27: invokevirtual #119                // Method java/lang/StringBuilder.append:(Ljava/lang/String;)Ljava/lang/StringBuilder;
      30: ldc           #179                // String :
      32: invokevirtual #119                // Method java/lang/StringBuilder.append:(Ljava/lang/String;)Ljava/lang/StringBuilder;
      35: aload_1
      36: invokevirtual #119                // Method java/lang/StringBuilder.append:(Ljava/lang/String;)Ljava/lang/StringBuilder;
      39: invokevirtual #126                // Method java/lang/StringBuilder.toString:()Ljava/lang/String;
      42: areturn
    Exception table:
       from    to  target type
           5    12    15   Class java/io/UnsupportedEncodingException

  public org.apache.camel.spi.Language getLanguage();
    Code:
       0: aload_0
       1: getfield      #57                 // Field language:Lorg/apache/camel/spi/Language;
       4: areturn

  public org.apache.camel.Expression getExpression();
    Code:
       0: aload_0
       1: invokevirtual #187                // Method isContentResolvedFromResource:()Z
       4: ifeq          16
       7: aload_0
       8: invokevirtual #190                // Method isContentCacheCleared:()Z
      11: ifeq          16
      14: aconst_null
      15: areturn
      16: aload_0
      17: getfield      #59                 // Field expression:Lorg/apache/camel/Expression;
      20: areturn

  public void setExpression(org.apache.camel.Expression);
    Code:
       0: aload_0
       1: aload_1
       2: putfield      #59                 // Field expression:Lorg/apache/camel/Expression;
       5: return

  public boolean isTransform();
    Code:
       0: aload_0
       1: getfield      #45                 // Field transform:Z
       4: ireturn

  public void setTransform(boolean);
    Code:
       0: aload_0
       1: iload_1
       2: putfield      #45                 // Field transform:Z
       5: return

  public boolean isBinary();
    Code:
       0: aload_0
       1: getfield      #197                // Field binary:Z
       4: ireturn

  public void setBinary(boolean);
    Code:
       0: aload_0
       1: iload_1
       2: putfield      #197                // Field binary:Z
       5: return

  public void setLanguageName(java.lang.String);
    Code:
       0: aload_0
       1: aload_1
       2: putfield      #80                 // Field languageName:Ljava/lang/String;
       5: return

  public void setResourceUri(java.lang.String);
    Code:
       0: aload_0
       1: aload_1
       2: invokespecial #202                // Method org/apache/camel/component/ResourceEndpoint.setResourceUri:(Ljava/lang/String;)V
       5: return

  public java.lang.String getResourceUri();
    Code:
       0: aload_0
       1: invokespecial #205                // Method org/apache/camel/component/ResourceEndpoint.getResourceUri:()Ljava/lang/String;
       4: areturn

  public void setScript(java.lang.String);
    Code:
       0: aload_0
       1: aload_1
       2: putfield      #91                 // Field script:Ljava/lang/String;
       5: return

  public java.lang.String getScript();
    Code:
       0: aload_0
       1: getfield      #91                 // Field script:Ljava/lang/String;
       4: areturn

  public boolean isContentResolvedFromResource();
    Code:
       0: aload_0
       1: getfield      #209                // Field contentResolvedFromResource:Z
       4: ireturn

  public void setContentResolvedFromResource(boolean);
    Code:
       0: aload_0
       1: iload_1
       2: putfield      #209                // Field contentResolvedFromResource:Z
       5: return

  public boolean isCacheScript();
    Code:
       0: aload_0
       1: getfield      #89                 // Field cacheScript:Z
       4: ireturn

  public void setCacheScript(boolean);
    Code:
       0: aload_0
       1: iload_1
       2: putfield      #89                 // Field cacheScript:Z
       5: return

  public void clearContentCache();
    Code:
       0: aload_0
       1: invokespecial #215                // Method org/apache/camel/component/ResourceEndpoint.clearContentCache:()V
       4: aload_0
       5: aconst_null
       6: putfield      #59                 // Field expression:Lorg/apache/camel/Expression;
       9: aload_0
      10: aconst_null
      11: putfield      #91                 // Field script:Ljava/lang/String;
      14: return
}
