Compiled from "ExtensionSchemas.java"
final class com.google.protobuf.ExtensionSchemas {
  private static final com.google.protobuf.ExtensionSchema<?> LITE_SCHEMA;

  private static final com.google.protobuf.ExtensionSchema<?> FULL_SCHEMA;

  com.google.protobuf.ExtensionSchemas();
    Code:
       0: aload_0
       1: invokespecial #13                 // Method java/lang/Object."<init>":()V
       4: return

  private static com.google.protobuf.ExtensionSchema<?> loadSchemaForFullRuntime();
    Code:
       0: ldc           #22                 // String com.google.protobuf.ExtensionSchemaFull
       2: invokestatic  #28                 // Method java/lang/Class.forName:(Ljava/lang/String;)Ljava/lang/Class;
       5: astore_0
       6: aload_0
       7: iconst_0
       8: anewarray     #24                 // class java/lang/Class
      11: invokevirtual #32                 // Method java/lang/Class.getDeclaredConstructor:([Ljava/lang/Class;)Ljava/lang/reflect/Constructor;
      14: iconst_0
      15: anewarray     #4                  // class java/lang/Object
      18: invokevirtual #38                 // Method java/lang/reflect/Constructor.newInstance:([Ljava/lang/Object;)Ljava/lang/Object;
      21: checkcast     #40                 // class com/google/protobuf/ExtensionSchema
      24: areturn
      25: astore_0
      26: aconst_null
      27: areturn
    Exception table:
       from    to  target type
           0    24    25   Class java/lang/Exception

  static com.google.protobuf.ExtensionSchema<?> lite();
    Code:
       0: getstatic     #48                 // Field LITE_SCHEMA:Lcom/google/protobuf/ExtensionSchema;
       3: areturn

  static com.google.protobuf.ExtensionSchema<?> full();
    Code:
       0: getstatic     #51                 // Field FULL_SCHEMA:Lcom/google/protobuf/ExtensionSchema;
       3: ifnonnull     16
       6: new           #53                 // class java/lang/IllegalStateException
       9: dup
      10: ldc           #55                 // String Protobuf runtime is not correctly loaded.
      12: invokespecial #58                 // Method java/lang/IllegalStateException."<init>":(Ljava/lang/String;)V
      15: athrow
      16: getstatic     #51                 // Field FULL_SCHEMA:Lcom/google/protobuf/ExtensionSchema;
      19: areturn

  static {};
    Code:
       0: new           #61                 // class com/google/protobuf/ExtensionSchemaLite
       3: dup
       4: invokespecial #62                 // Method com/google/protobuf/ExtensionSchemaLite."<init>":()V
       7: putstatic     #48                 // Field LITE_SCHEMA:Lcom/google/protobuf/ExtensionSchema;
      10: invokestatic  #64                 // Method loadSchemaForFullRuntime:()Lcom/google/protobuf/ExtensionSchema;
      13: putstatic     #51                 // Field FULL_SCHEMA:Lcom/google/protobuf/ExtensionSchema;
      16: return
}
