Compiled from "GeneratedMessageV3.java"
public abstract class com.google.protobuf.GeneratedMessageV3$ExtendableBuilder<MessageType extends com.google.protobuf.GeneratedMessageV3$ExtendableMessage, BuilderType extends com.google.protobuf.GeneratedMessageV3$ExtendableBuilder<MessageType, BuilderType>> extends com.google.protobuf.GeneratedMessageV3$Builder<BuilderType> implements com.google.protobuf.GeneratedMessageV3$ExtendableMessageOrBuilder<MessageType> {
  private com.google.protobuf.FieldSet$Builder<com.google.protobuf.Descriptors$FieldDescriptor> extensions;

  protected com.google.protobuf.GeneratedMessageV3$ExtendableBuilder();
    Code:
       0: aload_0
       1: invokespecial #65                 // Method com/google/protobuf/GeneratedMessageV3$Builder."<init>":()V
       4: return

  protected com.google.protobuf.GeneratedMessageV3$ExtendableBuilder(com.google.protobuf.GeneratedMessageV3$BuilderParent);
    Code:
       0: aload_0
       1: aload_1
       2: invokespecial #71                 // Method com/google/protobuf/GeneratedMessageV3$Builder."<init>":(Lcom/google/protobuf/GeneratedMessageV3$BuilderParent;)V
       5: return

  void internalSetExtensionSet(com.google.protobuf.FieldSet<com.google.protobuf.Descriptors$FieldDescriptor>);
    Code:
       0: aload_0
       1: aload_1
       2: invokestatic  #80                 // Method com/google/protobuf/FieldSet$Builder.fromFieldSet:(Lcom/google/protobuf/FieldSet;)Lcom/google/protobuf/FieldSet$Builder;
       5: putfield      #82                 // Field extensions:Lcom/google/protobuf/FieldSet$Builder;
       8: return

  public BuilderType clear();
    Code:
       0: aload_0
       1: aconst_null
       2: putfield      #82                 // Field extensions:Lcom/google/protobuf/FieldSet$Builder;
       5: aload_0
       6: invokespecial #90                 // Method com/google/protobuf/GeneratedMessageV3$Builder.clear:()Lcom/google/protobuf/GeneratedMessageV3$Builder;
       9: checkcast     #2                  // class com/google/protobuf/GeneratedMessageV3$ExtendableBuilder
      12: areturn

  private void ensureExtensionsIsMutable();
    Code:
       0: aload_0
       1: getfield      #82                 // Field extensions:Lcom/google/protobuf/FieldSet$Builder;
       4: ifnonnull     14
       7: aload_0
       8: invokestatic  #95                 // Method com/google/protobuf/FieldSet.newBuilder:()Lcom/google/protobuf/FieldSet$Builder;
      11: putfield      #82                 // Field extensions:Lcom/google/protobuf/FieldSet$Builder;
      14: return

  private void verifyExtensionContainingType(com.google.protobuf.Extension<MessageType, ?>);
    Code:
       0: aload_1
       1: invokevirtual #104                // Method com/google/protobuf/Extension.getDescriptor:()Lcom/google/protobuf/Descriptors$FieldDescriptor;
       4: invokevirtual #108                // Method com/google/protobuf/Descriptors$FieldDescriptor.getContainingType:()Lcom/google/protobuf/Descriptors$Descriptor;
       7: aload_0
       8: invokevirtual #111                // Method getDescriptorForType:()Lcom/google/protobuf/Descriptors$Descriptor;
      11: if_acmpeq     93
      14: new           #113                // class java/lang/IllegalArgumentException
      17: dup
      18: aload_1
      19: invokevirtual #104                // Method com/google/protobuf/Extension.getDescriptor:()Lcom/google/protobuf/Descriptors$FieldDescriptor;
      22: invokevirtual #108                // Method com/google/protobuf/Descriptors$FieldDescriptor.getContainingType:()Lcom/google/protobuf/Descriptors$Descriptor;
      25: invokevirtual #117                // Method com/google/protobuf/Descriptors$Descriptor.getFullName:()Ljava/lang/String;
      28: astore_2
      29: aload_0
      30: invokevirtual #111                // Method getDescriptorForType:()Lcom/google/protobuf/Descriptors$Descriptor;
      33: invokevirtual #117                // Method com/google/protobuf/Descriptors$Descriptor.getFullName:()Ljava/lang/String;
      36: astore_3
      37: bipush        62
      39: aload_2
      40: invokestatic  #123                // Method java/lang/String.valueOf:(Ljava/lang/Object;)Ljava/lang/String;
      43: invokevirtual #127                // Method java/lang/String.length:()I
      46: iadd
      47: aload_3
      48: invokestatic  #123                // Method java/lang/String.valueOf:(Ljava/lang/Object;)Ljava/lang/String;
      51: invokevirtual #127                // Method java/lang/String.length:()I
      54: iadd
      55: new           #129                // class java/lang/StringBuilder
      58: dup_x1
      59: swap
      60: invokespecial #132                // Method java/lang/StringBuilder."<init>":(I)V
      63: ldc           #134                // String Extension is for type \"
      65: invokevirtual #138                // Method java/lang/StringBuilder.append:(Ljava/lang/String;)Ljava/lang/StringBuilder;
      68: aload_2
      69: invokevirtual #138                // Method java/lang/StringBuilder.append:(Ljava/lang/String;)Ljava/lang/StringBuilder;
      72: ldc           #140                // String \" which does not match message type \"
      74: invokevirtual #138                // Method java/lang/StringBuilder.append:(Ljava/lang/String;)Ljava/lang/StringBuilder;
      77: aload_3
      78: invokevirtual #138                // Method java/lang/StringBuilder.append:(Ljava/lang/String;)Ljava/lang/StringBuilder;
      81: ldc           #142                // String \".
      83: invokevirtual #138                // Method java/lang/StringBuilder.append:(Ljava/lang/String;)Ljava/lang/StringBuilder;
      86: invokevirtual #145                // Method java/lang/StringBuilder.toString:()Ljava/lang/String;
      89: invokespecial #148                // Method java/lang/IllegalArgumentException."<init>":(Ljava/lang/String;)V
      92: athrow
      93: return

  public final <Type> boolean hasExtension(com.google.protobuf.ExtensionLite<MessageType, Type>);
    Code:
       0: aload_1
       1: invokestatic  #158                // Method com/google/protobuf/GeneratedMessageV3.access$500:(Lcom/google/protobuf/ExtensionLite;)Lcom/google/protobuf/Extension;
       4: astore_2
       5: aload_0
       6: aload_2
       7: invokespecial #160                // Method verifyExtensionContainingType:(Lcom/google/protobuf/Extension;)V
      10: aload_0
      11: getfield      #82                 // Field extensions:Lcom/google/protobuf/FieldSet$Builder;
      14: ifnonnull     21
      17: iconst_0
      18: goto          32
      21: aload_0
      22: getfield      #82                 // Field extensions:Lcom/google/protobuf/FieldSet$Builder;
      25: aload_2
      26: invokevirtual #104                // Method com/google/protobuf/Extension.getDescriptor:()Lcom/google/protobuf/Descriptors$FieldDescriptor;
      29: invokevirtual #164                // Method com/google/protobuf/FieldSet$Builder.hasField:(Lcom/google/protobuf/FieldSet$FieldDescriptorLite;)Z
      32: ireturn

  public final <Type> int getExtensionCount(com.google.protobuf.ExtensionLite<MessageType, java.util.List<Type>>);
    Code:
       0: aload_1
       1: invokestatic  #158                // Method com/google/protobuf/GeneratedMessageV3.access$500:(Lcom/google/protobuf/ExtensionLite;)Lcom/google/protobuf/Extension;
       4: astore_2
       5: aload_0
       6: aload_2
       7: invokespecial #160                // Method verifyExtensionContainingType:(Lcom/google/protobuf/Extension;)V
      10: aload_2
      11: invokevirtual #104                // Method com/google/protobuf/Extension.getDescriptor:()Lcom/google/protobuf/Descriptors$FieldDescriptor;
      14: astore_3
      15: aload_0
      16: getfield      #82                 // Field extensions:Lcom/google/protobuf/FieldSet$Builder;
      19: ifnonnull     26
      22: iconst_0
      23: goto          34
      26: aload_0
      27: getfield      #82                 // Field extensions:Lcom/google/protobuf/FieldSet$Builder;
      30: aload_3
      31: invokevirtual #175                // Method com/google/protobuf/FieldSet$Builder.getRepeatedFieldCount:(Lcom/google/protobuf/FieldSet$FieldDescriptorLite;)I
      34: ireturn

  public final <Type> Type getExtension(com.google.protobuf.ExtensionLite<MessageType, Type>);
    Code:
       0: aload_1
       1: invokestatic  #158                // Method com/google/protobuf/GeneratedMessageV3.access$500:(Lcom/google/protobuf/ExtensionLite;)Lcom/google/protobuf/Extension;
       4: astore_2
       5: aload_0
       6: aload_2
       7: invokespecial #160                // Method verifyExtensionContainingType:(Lcom/google/protobuf/Extension;)V
      10: aload_2
      11: invokevirtual #104                // Method com/google/protobuf/Extension.getDescriptor:()Lcom/google/protobuf/Descriptors$FieldDescriptor;
      14: astore_3
      15: aload_0
      16: getfield      #82                 // Field extensions:Lcom/google/protobuf/FieldSet$Builder;
      19: ifnonnull     26
      22: aconst_null
      23: goto          34
      26: aload_0
      27: getfield      #82                 // Field extensions:Lcom/google/protobuf/FieldSet$Builder;
      30: aload_3
      31: invokevirtual #186                // Method com/google/protobuf/FieldSet$Builder.getField:(Lcom/google/protobuf/FieldSet$FieldDescriptorLite;)Ljava/lang/Object;
      34: astore        4
      36: aload         4
      38: ifnonnull     76
      41: aload_3
      42: invokevirtual #192                // Method com/google/protobuf/Descriptors$FieldDescriptor.isRepeated:()Z
      45: ifeq          52
      48: invokestatic  #198                // Method java/util/Collections.emptyList:()Ljava/util/List;
      51: areturn
      52: aload_3
      53: invokevirtual #202                // Method com/google/protobuf/Descriptors$FieldDescriptor.getJavaType:()Lcom/google/protobuf/Descriptors$FieldDescriptor$JavaType;
      56: getstatic     #206                // Field com/google/protobuf/Descriptors$FieldDescriptor$JavaType.MESSAGE:Lcom/google/protobuf/Descriptors$FieldDescriptor$JavaType;
      59: if_acmpne     67
      62: aload_2
      63: invokevirtual #210                // Method com/google/protobuf/Extension.getMessageDefaultInstance:()Lcom/google/protobuf/Message;
      66: areturn
      67: aload_2
      68: aload_3
      69: invokevirtual #214                // Method com/google/protobuf/Descriptors$FieldDescriptor.getDefaultValue:()Ljava/lang/Object;
      72: invokevirtual #218                // Method com/google/protobuf/Extension.fromReflectionType:(Ljava/lang/Object;)Ljava/lang/Object;
      75: areturn
      76: aload_2
      77: aload         4
      79: invokevirtual #218                // Method com/google/protobuf/Extension.fromReflectionType:(Ljava/lang/Object;)Ljava/lang/Object;
      82: areturn

  public final <Type> Type getExtension(com.google.protobuf.ExtensionLite<MessageType, java.util.List<Type>>, int);
    Code:
       0: aload_1
       1: invokestatic  #158                // Method com/google/protobuf/GeneratedMessageV3.access$500:(Lcom/google/protobuf/ExtensionLite;)Lcom/google/protobuf/Extension;
       4: astore_3
       5: aload_0
       6: aload_3
       7: invokespecial #160                // Method verifyExtensionContainingType:(Lcom/google/protobuf/Extension;)V
      10: aload_3
      11: invokevirtual #104                // Method com/google/protobuf/Extension.getDescriptor:()Lcom/google/protobuf/Descriptors$FieldDescriptor;
      14: astore        4
      16: aload_0
      17: getfield      #82                 // Field extensions:Lcom/google/protobuf/FieldSet$Builder;
      20: ifnonnull     31
      23: new           #224                // class java/lang/IndexOutOfBoundsException
      26: dup
      27: invokespecial #225                // Method java/lang/IndexOutOfBoundsException."<init>":()V
      30: athrow
      31: aload_3
      32: aload_0
      33: getfield      #82                 // Field extensions:Lcom/google/protobuf/FieldSet$Builder;
      36: aload         4
      38: iload_2
      39: invokevirtual #229                // Method com/google/protobuf/FieldSet$Builder.getRepeatedField:(Lcom/google/protobuf/FieldSet$FieldDescriptorLite;I)Ljava/lang/Object;
      42: invokevirtual #232                // Method com/google/protobuf/Extension.singularFromReflectionType:(Ljava/lang/Object;)Ljava/lang/Object;
      45: areturn

  public final <Type> BuilderType setExtension(com.google.protobuf.ExtensionLite<MessageType, Type>, Type);
    Code:
       0: aload_1
       1: invokestatic  #158                // Method com/google/protobuf/GeneratedMessageV3.access$500:(Lcom/google/protobuf/ExtensionLite;)Lcom/google/protobuf/Extension;
       4: astore_3
       5: aload_0
       6: aload_3
       7: invokespecial #160                // Method verifyExtensionContainingType:(Lcom/google/protobuf/Extension;)V
      10: aload_0
      11: invokespecial #239                // Method ensureExtensionsIsMutable:()V
      14: aload_3
      15: invokevirtual #104                // Method com/google/protobuf/Extension.getDescriptor:()Lcom/google/protobuf/Descriptors$FieldDescriptor;
      18: astore        4
      20: aload_0
      21: getfield      #82                 // Field extensions:Lcom/google/protobuf/FieldSet$Builder;
      24: aload         4
      26: aload_3
      27: aload_2
      28: invokevirtual #242                // Method com/google/protobuf/Extension.toReflectionType:(Ljava/lang/Object;)Ljava/lang/Object;
      31: invokevirtual #246                // Method com/google/protobuf/FieldSet$Builder.setField:(Lcom/google/protobuf/FieldSet$FieldDescriptorLite;Ljava/lang/Object;)V
      34: aload_0
      35: invokevirtual #249                // Method onChanged:()V
      38: aload_0
      39: areturn

  public final <Type> BuilderType setExtension(com.google.protobuf.ExtensionLite<MessageType, java.util.List<Type>>, int, Type);
    Code:
       0: aload_1
       1: invokestatic  #158                // Method com/google/protobuf/GeneratedMessageV3.access$500:(Lcom/google/protobuf/ExtensionLite;)Lcom/google/protobuf/Extension;
       4: astore        4
       6: aload_0
       7: aload         4
       9: invokespecial #160                // Method verifyExtensionContainingType:(Lcom/google/protobuf/Extension;)V
      12: aload_0
      13: invokespecial #239                // Method ensureExtensionsIsMutable:()V
      16: aload         4
      18: invokevirtual #104                // Method com/google/protobuf/Extension.getDescriptor:()Lcom/google/protobuf/Descriptors$FieldDescriptor;
      21: astore        5
      23: aload_0
      24: getfield      #82                 // Field extensions:Lcom/google/protobuf/FieldSet$Builder;
      27: aload         5
      29: iload_2
      30: aload         4
      32: aload_3
      33: invokevirtual #255                // Method com/google/protobuf/Extension.singularToReflectionType:(Ljava/lang/Object;)Ljava/lang/Object;
      36: invokevirtual #259                // Method com/google/protobuf/FieldSet$Builder.setRepeatedField:(Lcom/google/protobuf/FieldSet$FieldDescriptorLite;ILjava/lang/Object;)V
      39: aload_0
      40: invokevirtual #249                // Method onChanged:()V
      43: aload_0
      44: areturn

  public final <Type> BuilderType addExtension(com.google.protobuf.ExtensionLite<MessageType, java.util.List<Type>>, Type);
    Code:
       0: aload_1
       1: invokestatic  #158                // Method com/google/protobuf/GeneratedMessageV3.access$500:(Lcom/google/protobuf/ExtensionLite;)Lcom/google/protobuf/Extension;
       4: astore_3
       5: aload_0
       6: aload_3
       7: invokespecial #160                // Method verifyExtensionContainingType:(Lcom/google/protobuf/Extension;)V
      10: aload_0
      11: invokespecial #239                // Method ensureExtensionsIsMutable:()V
      14: aload_3
      15: invokevirtual #104                // Method com/google/protobuf/Extension.getDescriptor:()Lcom/google/protobuf/Descriptors$FieldDescriptor;
      18: astore        4
      20: aload_0
      21: getfield      #82                 // Field extensions:Lcom/google/protobuf/FieldSet$Builder;
      24: aload         4
      26: aload_3
      27: aload_2
      28: invokevirtual #255                // Method com/google/protobuf/Extension.singularToReflectionType:(Ljava/lang/Object;)Ljava/lang/Object;
      31: invokevirtual #264                // Method com/google/protobuf/FieldSet$Builder.addRepeatedField:(Lcom/google/protobuf/FieldSet$FieldDescriptorLite;Ljava/lang/Object;)V
      34: aload_0
      35: invokevirtual #249                // Method onChanged:()V
      38: aload_0
      39: areturn

  public final BuilderType clearExtension(com.google.protobuf.ExtensionLite<MessageType, ?>);
    Code:
       0: aload_1
       1: invokestatic  #158                // Method com/google/protobuf/GeneratedMessageV3.access$500:(Lcom/google/protobuf/ExtensionLite;)Lcom/google/protobuf/Extension;
       4: astore_2
       5: aload_0
       6: aload_2
       7: invokespecial #160                // Method verifyExtensionContainingType:(Lcom/google/protobuf/Extension;)V
      10: aload_0
      11: invokespecial #239                // Method ensureExtensionsIsMutable:()V
      14: aload_0
      15: getfield      #82                 // Field extensions:Lcom/google/protobuf/FieldSet$Builder;
      18: aload_2
      19: invokevirtual #104                // Method com/google/protobuf/Extension.getDescriptor:()Lcom/google/protobuf/Descriptors$FieldDescriptor;
      22: invokevirtual #271                // Method com/google/protobuf/FieldSet$Builder.clearField:(Lcom/google/protobuf/FieldSet$FieldDescriptorLite;)V
      25: aload_0
      26: invokevirtual #249                // Method onChanged:()V
      29: aload_0
      30: areturn

  public final <Type> boolean hasExtension(com.google.protobuf.Extension<MessageType, Type>);
    Code:
       0: aload_0
       1: aload_1
       2: invokevirtual #276                // Method hasExtension:(Lcom/google/protobuf/ExtensionLite;)Z
       5: ireturn

  public final <Type> boolean hasExtension(com.google.protobuf.GeneratedMessage$GeneratedExtension<MessageType, Type>);
    Code:
       0: aload_0
       1: aload_1
       2: invokevirtual #276                // Method hasExtension:(Lcom/google/protobuf/ExtensionLite;)Z
       5: ireturn

  public final <Type> int getExtensionCount(com.google.protobuf.Extension<MessageType, java.util.List<Type>>);
    Code:
       0: aload_0
       1: aload_1
       2: invokevirtual #284                // Method getExtensionCount:(Lcom/google/protobuf/ExtensionLite;)I
       5: ireturn

  public final <Type> int getExtensionCount(com.google.protobuf.GeneratedMessage$GeneratedExtension<MessageType, java.util.List<Type>>);
    Code:
       0: aload_0
       1: aload_1
       2: invokevirtual #284                // Method getExtensionCount:(Lcom/google/protobuf/ExtensionLite;)I
       5: ireturn

  public final <Type> Type getExtension(com.google.protobuf.Extension<MessageType, Type>);
    Code:
       0: aload_0
       1: aload_1
       2: invokevirtual #291                // Method getExtension:(Lcom/google/protobuf/ExtensionLite;)Ljava/lang/Object;
       5: areturn

  public final <Type> Type getExtension(com.google.protobuf.GeneratedMessage$GeneratedExtension<MessageType, Type>);
    Code:
       0: aload_0
       1: aload_1
       2: invokevirtual #291                // Method getExtension:(Lcom/google/protobuf/ExtensionLite;)Ljava/lang/Object;
       5: areturn

  public final <Type> Type getExtension(com.google.protobuf.Extension<MessageType, java.util.List<Type>>, int);
    Code:
       0: aload_0
       1: aload_1
       2: iload_2
       3: invokevirtual #297                // Method getExtension:(Lcom/google/protobuf/ExtensionLite;I)Ljava/lang/Object;
       6: areturn

  public final <Type> Type getExtension(com.google.protobuf.GeneratedMessage$GeneratedExtension<MessageType, java.util.List<Type>>, int);
    Code:
       0: aload_0
       1: aload_1
       2: iload_2
       3: invokevirtual #297                // Method getExtension:(Lcom/google/protobuf/ExtensionLite;I)Ljava/lang/Object;
       6: areturn

  public final <Type> BuilderType setExtension(com.google.protobuf.Extension<MessageType, Type>, Type);
    Code:
       0: aload_0
       1: aload_1
       2: aload_2
       3: invokevirtual #303                // Method setExtension:(Lcom/google/protobuf/ExtensionLite;Ljava/lang/Object;)Lcom/google/protobuf/GeneratedMessageV3$ExtendableBuilder;
       6: areturn

  public <Type> BuilderType setExtension(com.google.protobuf.GeneratedMessage$GeneratedExtension<MessageType, Type>, Type);
    Code:
       0: aload_0
       1: aload_1
       2: aload_2
       3: invokevirtual #303                // Method setExtension:(Lcom/google/protobuf/ExtensionLite;Ljava/lang/Object;)Lcom/google/protobuf/GeneratedMessageV3$ExtendableBuilder;
       6: areturn

  public final <Type> BuilderType setExtension(com.google.protobuf.Extension<MessageType, java.util.List<Type>>, int, Type);
    Code:
       0: aload_0
       1: aload_1
       2: iload_2
       3: aload_3
       4: invokevirtual #309                // Method setExtension:(Lcom/google/protobuf/ExtensionLite;ILjava/lang/Object;)Lcom/google/protobuf/GeneratedMessageV3$ExtendableBuilder;
       7: areturn

  public <Type> BuilderType setExtension(com.google.protobuf.GeneratedMessage$GeneratedExtension<MessageType, java.util.List<Type>>, int, Type);
    Code:
       0: aload_0
       1: aload_1
       2: iload_2
       3: aload_3
       4: invokevirtual #309                // Method setExtension:(Lcom/google/protobuf/ExtensionLite;ILjava/lang/Object;)Lcom/google/protobuf/GeneratedMessageV3$ExtendableBuilder;
       7: areturn

  public final <Type> BuilderType addExtension(com.google.protobuf.Extension<MessageType, java.util.List<Type>>, Type);
    Code:
       0: aload_0
       1: aload_1
       2: aload_2
       3: invokevirtual #314                // Method addExtension:(Lcom/google/protobuf/ExtensionLite;Ljava/lang/Object;)Lcom/google/protobuf/GeneratedMessageV3$ExtendableBuilder;
       6: areturn

  public <Type> BuilderType addExtension(com.google.protobuf.GeneratedMessage$GeneratedExtension<MessageType, java.util.List<Type>>, Type);
    Code:
       0: aload_0
       1: aload_1
       2: aload_2
       3: invokevirtual #314                // Method addExtension:(Lcom/google/protobuf/ExtensionLite;Ljava/lang/Object;)Lcom/google/protobuf/GeneratedMessageV3$ExtendableBuilder;
       6: areturn

  public final <Type> BuilderType clearExtension(com.google.protobuf.Extension<MessageType, ?>);
    Code:
       0: aload_0
       1: aload_1
       2: invokevirtual #319                // Method clearExtension:(Lcom/google/protobuf/ExtensionLite;)Lcom/google/protobuf/GeneratedMessageV3$ExtendableBuilder;
       5: areturn

  public <Type> BuilderType clearExtension(com.google.protobuf.GeneratedMessage$GeneratedExtension<MessageType, ?>);
    Code:
       0: aload_0
       1: aload_1
       2: invokevirtual #319                // Method clearExtension:(Lcom/google/protobuf/ExtensionLite;)Lcom/google/protobuf/GeneratedMessageV3$ExtendableBuilder;
       5: areturn

  protected boolean extensionsAreInitialized();
    Code:
       0: aload_0
       1: getfield      #82                 // Field extensions:Lcom/google/protobuf/FieldSet$Builder;
       4: ifnonnull     11
       7: iconst_1
       8: goto          18
      11: aload_0
      12: getfield      #82                 // Field extensions:Lcom/google/protobuf/FieldSet$Builder;
      15: invokevirtual #326                // Method com/google/protobuf/FieldSet$Builder.isInitialized:()Z
      18: ireturn

  private com.google.protobuf.FieldSet<com.google.protobuf.Descriptors$FieldDescriptor> buildExtensions();
    Code:
       0: aload_0
       1: getfield      #82                 // Field extensions:Lcom/google/protobuf/FieldSet$Builder;
       4: ifnonnull     13
       7: invokestatic  #332                // Method com/google/protobuf/FieldSet.emptySet:()Lcom/google/protobuf/FieldSet;
      10: goto          20
      13: aload_0
      14: getfield      #82                 // Field extensions:Lcom/google/protobuf/FieldSet$Builder;
      17: invokevirtual #335                // Method com/google/protobuf/FieldSet$Builder.build:()Lcom/google/protobuf/FieldSet;
      20: areturn

  public boolean isInitialized();
    Code:
       0: aload_0
       1: invokespecial #336                // Method com/google/protobuf/GeneratedMessageV3$Builder.isInitialized:()Z
       4: ifeq          18
       7: aload_0
       8: invokevirtual #338                // Method extensionsAreInitialized:()Z
      11: ifeq          18
      14: iconst_1
      15: goto          19
      18: iconst_0
      19: ireturn

  public java.util.Map<com.google.protobuf.Descriptors$FieldDescriptor, java.lang.Object> getAllFields();
    Code:
       0: aload_0
       1: invokestatic  #345                // Method com/google/protobuf/GeneratedMessageV3$Builder.access$900:(Lcom/google/protobuf/GeneratedMessageV3$Builder;)Ljava/util/Map;
       4: astore_1
       5: aload_0
       6: getfield      #82                 // Field extensions:Lcom/google/protobuf/FieldSet$Builder;
       9: ifnull        25
      12: aload_1
      13: aload_0
      14: getfield      #82                 // Field extensions:Lcom/google/protobuf/FieldSet$Builder;
      17: invokevirtual #347                // Method com/google/protobuf/FieldSet$Builder.getAllFields:()Ljava/util/Map;
      20: invokeinterface #353,  2          // InterfaceMethod java/util/Map.putAll:(Ljava/util/Map;)V
      25: aload_1
      26: invokestatic  #357                // Method java/util/Collections.unmodifiableMap:(Ljava/util/Map;)Ljava/util/Map;
      29: areturn

  public java.lang.Object getField(com.google.protobuf.Descriptors$FieldDescriptor);
    Code:
       0: aload_1
       1: invokevirtual #364                // Method com/google/protobuf/Descriptors$FieldDescriptor.isExtension:()Z
       4: ifeq          61
       7: aload_0
       8: aload_1
       9: invokespecial #368                // Method verifyContainingType:(Lcom/google/protobuf/Descriptors$FieldDescriptor;)V
      12: aload_0
      13: getfield      #82                 // Field extensions:Lcom/google/protobuf/FieldSet$Builder;
      16: ifnonnull     23
      19: aconst_null
      20: goto          31
      23: aload_0
      24: getfield      #82                 // Field extensions:Lcom/google/protobuf/FieldSet$Builder;
      27: aload_1
      28: invokevirtual #186                // Method com/google/protobuf/FieldSet$Builder.getField:(Lcom/google/protobuf/FieldSet$FieldDescriptorLite;)Ljava/lang/Object;
      31: astore_2
      32: aload_2
      33: ifnonnull     59
      36: aload_1
      37: invokevirtual #202                // Method com/google/protobuf/Descriptors$FieldDescriptor.getJavaType:()Lcom/google/protobuf/Descriptors$FieldDescriptor$JavaType;
      40: getstatic     #206                // Field com/google/protobuf/Descriptors$FieldDescriptor$JavaType.MESSAGE:Lcom/google/protobuf/Descriptors$FieldDescriptor$JavaType;
      43: if_acmpne     54
      46: aload_1
      47: invokevirtual #371                // Method com/google/protobuf/Descriptors$FieldDescriptor.getMessageType:()Lcom/google/protobuf/Descriptors$Descriptor;
      50: invokestatic  #375                // Method com/google/protobuf/DynamicMessage.getDefaultInstance:(Lcom/google/protobuf/Descriptors$Descriptor;)Lcom/google/protobuf/DynamicMessage;
      53: areturn
      54: aload_1
      55: invokevirtual #214                // Method com/google/protobuf/Descriptors$FieldDescriptor.getDefaultValue:()Ljava/lang/Object;
      58: areturn
      59: aload_2
      60: areturn
      61: aload_0
      62: aload_1
      63: invokespecial #377                // Method com/google/protobuf/GeneratedMessageV3$Builder.getField:(Lcom/google/protobuf/Descriptors$FieldDescriptor;)Ljava/lang/Object;
      66: areturn

  public com.google.protobuf.Message$Builder getFieldBuilder(com.google.protobuf.Descriptors$FieldDescriptor);
    Code:
       0: aload_1
       1: invokevirtual #364                // Method com/google/protobuf/Descriptors$FieldDescriptor.isExtension:()Z
       4: ifeq          128
       7: aload_0
       8: aload_1
       9: invokespecial #368                // Method verifyContainingType:(Lcom/google/protobuf/Descriptors$FieldDescriptor;)V
      12: aload_1
      13: invokevirtual #202                // Method com/google/protobuf/Descriptors$FieldDescriptor.getJavaType:()Lcom/google/protobuf/Descriptors$FieldDescriptor$JavaType;
      16: getstatic     #206                // Field com/google/protobuf/Descriptors$FieldDescriptor$JavaType.MESSAGE:Lcom/google/protobuf/Descriptors$FieldDescriptor$JavaType;
      19: if_acmpeq     33
      22: new           #382                // class java/lang/UnsupportedOperationException
      25: dup
      26: ldc_w         #384                // String getFieldBuilder() called on a non-Message type.
      29: invokespecial #385                // Method java/lang/UnsupportedOperationException."<init>":(Ljava/lang/String;)V
      32: athrow
      33: aload_0
      34: invokespecial #239                // Method ensureExtensionsIsMutable:()V
      37: aload_0
      38: getfield      #82                 // Field extensions:Lcom/google/protobuf/FieldSet$Builder;
      41: aload_1
      42: invokevirtual #388                // Method com/google/protobuf/FieldSet$Builder.getFieldAllowBuilders:(Lcom/google/protobuf/FieldSet$FieldDescriptorLite;)Ljava/lang/Object;
      45: astore_2
      46: aload_2
      47: ifnonnull     73
      50: aload_1
      51: invokevirtual #371                // Method com/google/protobuf/Descriptors$FieldDescriptor.getMessageType:()Lcom/google/protobuf/Descriptors$Descriptor;
      54: invokestatic  #391                // Method com/google/protobuf/DynamicMessage.newBuilder:(Lcom/google/protobuf/Descriptors$Descriptor;)Lcom/google/protobuf/DynamicMessage$Builder;
      57: astore_3
      58: aload_0
      59: getfield      #82                 // Field extensions:Lcom/google/protobuf/FieldSet$Builder;
      62: aload_1
      63: aload_3
      64: invokevirtual #246                // Method com/google/protobuf/FieldSet$Builder.setField:(Lcom/google/protobuf/FieldSet$FieldDescriptorLite;Ljava/lang/Object;)V
      67: aload_0
      68: invokevirtual #249                // Method onChanged:()V
      71: aload_3
      72: areturn
      73: aload_2
      74: instanceof    #31                 // class com/google/protobuf/Message$Builder
      77: ifeq          85
      80: aload_2
      81: checkcast     #31                 // class com/google/protobuf/Message$Builder
      84: areturn
      85: aload_2
      86: instanceof    #33                 // class com/google/protobuf/Message
      89: ifeq          117
      92: aload_2
      93: checkcast     #33                 // class com/google/protobuf/Message
      96: invokeinterface #395,  1          // InterfaceMethod com/google/protobuf/Message.toBuilder:()Lcom/google/protobuf/Message$Builder;
     101: astore_3
     102: aload_0
     103: getfield      #82                 // Field extensions:Lcom/google/protobuf/FieldSet$Builder;
     106: aload_1
     107: aload_3
     108: invokevirtual #246                // Method com/google/protobuf/FieldSet$Builder.setField:(Lcom/google/protobuf/FieldSet$FieldDescriptorLite;Ljava/lang/Object;)V
     111: aload_0
     112: invokevirtual #249                // Method onChanged:()V
     115: aload_3
     116: areturn
     117: new           #382                // class java/lang/UnsupportedOperationException
     120: dup
     121: ldc_w         #397                // String getRepeatedFieldBuilder() called on a non-Message type.
     124: invokespecial #385                // Method java/lang/UnsupportedOperationException."<init>":(Ljava/lang/String;)V
     127: athrow
     128: aload_0
     129: aload_1
     130: invokespecial #399                // Method com/google/protobuf/GeneratedMessageV3$Builder.getFieldBuilder:(Lcom/google/protobuf/Descriptors$FieldDescriptor;)Lcom/google/protobuf/Message$Builder;
     133: areturn

  public int getRepeatedFieldCount(com.google.protobuf.Descriptors$FieldDescriptor);
    Code:
       0: aload_1
       1: invokevirtual #364                // Method com/google/protobuf/Descriptors$FieldDescriptor.isExtension:()Z
       4: ifeq          32
       7: aload_0
       8: aload_1
       9: invokespecial #368                // Method verifyContainingType:(Lcom/google/protobuf/Descriptors$FieldDescriptor;)V
      12: aload_0
      13: getfield      #82                 // Field extensions:Lcom/google/protobuf/FieldSet$Builder;
      16: ifnonnull     23
      19: iconst_0
      20: goto          31
      23: aload_0
      24: getfield      #82                 // Field extensions:Lcom/google/protobuf/FieldSet$Builder;
      27: aload_1
      28: invokevirtual #175                // Method com/google/protobuf/FieldSet$Builder.getRepeatedFieldCount:(Lcom/google/protobuf/FieldSet$FieldDescriptorLite;)I
      31: ireturn
      32: aload_0
      33: aload_1
      34: invokespecial #404                // Method com/google/protobuf/GeneratedMessageV3$Builder.getRepeatedFieldCount:(Lcom/google/protobuf/Descriptors$FieldDescriptor;)I
      37: ireturn

  public java.lang.Object getRepeatedField(com.google.protobuf.Descriptors$FieldDescriptor, int);
    Code:
       0: aload_1
       1: invokevirtual #364                // Method com/google/protobuf/Descriptors$FieldDescriptor.isExtension:()Z
       4: ifeq          37
       7: aload_0
       8: aload_1
       9: invokespecial #368                // Method verifyContainingType:(Lcom/google/protobuf/Descriptors$FieldDescriptor;)V
      12: aload_0
      13: getfield      #82                 // Field extensions:Lcom/google/protobuf/FieldSet$Builder;
      16: ifnonnull     27
      19: new           #224                // class java/lang/IndexOutOfBoundsException
      22: dup
      23: invokespecial #225                // Method java/lang/IndexOutOfBoundsException."<init>":()V
      26: athrow
      27: aload_0
      28: getfield      #82                 // Field extensions:Lcom/google/protobuf/FieldSet$Builder;
      31: aload_1
      32: iload_2
      33: invokevirtual #229                // Method com/google/protobuf/FieldSet$Builder.getRepeatedField:(Lcom/google/protobuf/FieldSet$FieldDescriptorLite;I)Ljava/lang/Object;
      36: areturn
      37: aload_0
      38: aload_1
      39: iload_2
      40: invokespecial #407                // Method com/google/protobuf/GeneratedMessageV3$Builder.getRepeatedField:(Lcom/google/protobuf/Descriptors$FieldDescriptor;I)Ljava/lang/Object;
      43: areturn

  public com.google.protobuf.Message$Builder getRepeatedFieldBuilder(com.google.protobuf.Descriptors$FieldDescriptor, int);
    Code:
       0: aload_1
       1: invokevirtual #364                // Method com/google/protobuf/Descriptors$FieldDescriptor.isExtension:()Z
       4: ifeq          106
       7: aload_0
       8: aload_1
       9: invokespecial #368                // Method verifyContainingType:(Lcom/google/protobuf/Descriptors$FieldDescriptor;)V
      12: aload_0
      13: invokespecial #239                // Method ensureExtensionsIsMutable:()V
      16: aload_1
      17: invokevirtual #202                // Method com/google/protobuf/Descriptors$FieldDescriptor.getJavaType:()Lcom/google/protobuf/Descriptors$FieldDescriptor$JavaType;
      20: getstatic     #206                // Field com/google/protobuf/Descriptors$FieldDescriptor$JavaType.MESSAGE:Lcom/google/protobuf/Descriptors$FieldDescriptor$JavaType;
      23: if_acmpeq     37
      26: new           #382                // class java/lang/UnsupportedOperationException
      29: dup
      30: ldc_w         #397                // String getRepeatedFieldBuilder() called on a non-Message type.
      33: invokespecial #385                // Method java/lang/UnsupportedOperationException."<init>":(Ljava/lang/String;)V
      36: athrow
      37: aload_0
      38: getfield      #82                 // Field extensions:Lcom/google/protobuf/FieldSet$Builder;
      41: aload_1
      42: iload_2
      43: invokevirtual #412                // Method com/google/protobuf/FieldSet$Builder.getRepeatedFieldAllowBuilders:(Lcom/google/protobuf/FieldSet$FieldDescriptorLite;I)Ljava/lang/Object;
      46: astore_3
      47: aload_3
      48: instanceof    #31                 // class com/google/protobuf/Message$Builder
      51: ifeq          59
      54: aload_3
      55: checkcast     #31                 // class com/google/protobuf/Message$Builder
      58: areturn
      59: aload_3
      60: instanceof    #33                 // class com/google/protobuf/Message
      63: ifeq          95
      66: aload_3
      67: checkcast     #33                 // class com/google/protobuf/Message
      70: invokeinterface #395,  1          // InterfaceMethod com/google/protobuf/Message.toBuilder:()Lcom/google/protobuf/Message$Builder;
      75: astore        4
      77: aload_0
      78: getfield      #82                 // Field extensions:Lcom/google/protobuf/FieldSet$Builder;
      81: aload_1
      82: iload_2
      83: aload         4
      85: invokevirtual #259                // Method com/google/protobuf/FieldSet$Builder.setRepeatedField:(Lcom/google/protobuf/FieldSet$FieldDescriptorLite;ILjava/lang/Object;)V
      88: aload_0
      89: invokevirtual #249                // Method onChanged:()V
      92: aload         4
      94: areturn
      95: new           #382                // class java/lang/UnsupportedOperationException
      98: dup
      99: ldc_w         #397                // String getRepeatedFieldBuilder() called on a non-Message type.
     102: invokespecial #385                // Method java/lang/UnsupportedOperationException."<init>":(Ljava/lang/String;)V
     105: athrow
     106: aload_0
     107: aload_1
     108: iload_2
     109: invokespecial #414                // Method com/google/protobuf/GeneratedMessageV3$Builder.getRepeatedFieldBuilder:(Lcom/google/protobuf/Descriptors$FieldDescriptor;I)Lcom/google/protobuf/Message$Builder;
     112: areturn

  public boolean hasField(com.google.protobuf.Descriptors$FieldDescriptor);
    Code:
       0: aload_1
       1: invokevirtual #364                // Method com/google/protobuf/Descriptors$FieldDescriptor.isExtension:()Z
       4: ifeq          32
       7: aload_0
       8: aload_1
       9: invokespecial #368                // Method verifyContainingType:(Lcom/google/protobuf/Descriptors$FieldDescriptor;)V
      12: aload_0
      13: getfield      #82                 // Field extensions:Lcom/google/protobuf/FieldSet$Builder;
      16: ifnonnull     23
      19: iconst_0
      20: goto          31
      23: aload_0
      24: getfield      #82                 // Field extensions:Lcom/google/protobuf/FieldSet$Builder;
      27: aload_1
      28: invokevirtual #164                // Method com/google/protobuf/FieldSet$Builder.hasField:(Lcom/google/protobuf/FieldSet$FieldDescriptorLite;)Z
      31: ireturn
      32: aload_0
      33: aload_1
      34: invokespecial #417                // Method com/google/protobuf/GeneratedMessageV3$Builder.hasField:(Lcom/google/protobuf/Descriptors$FieldDescriptor;)Z
      37: ireturn

  public BuilderType setField(com.google.protobuf.Descriptors$FieldDescriptor, java.lang.Object);
    Code:
       0: aload_1
       1: invokevirtual #364                // Method com/google/protobuf/Descriptors$FieldDescriptor.isExtension:()Z
       4: ifeq          31
       7: aload_0
       8: aload_1
       9: invokespecial #368                // Method verifyContainingType:(Lcom/google/protobuf/Descriptors$FieldDescriptor;)V
      12: aload_0
      13: invokespecial #239                // Method ensureExtensionsIsMutable:()V
      16: aload_0
      17: getfield      #82                 // Field extensions:Lcom/google/protobuf/FieldSet$Builder;
      20: aload_1
      21: aload_2
      22: invokevirtual #246                // Method com/google/protobuf/FieldSet$Builder.setField:(Lcom/google/protobuf/FieldSet$FieldDescriptorLite;Ljava/lang/Object;)V
      25: aload_0
      26: invokevirtual #249                // Method onChanged:()V
      29: aload_0
      30: areturn
      31: aload_0
      32: aload_1
      33: aload_2
      34: invokespecial #422                // Method com/google/protobuf/GeneratedMessageV3$Builder.setField:(Lcom/google/protobuf/Descriptors$FieldDescriptor;Ljava/lang/Object;)Lcom/google/protobuf/GeneratedMessageV3$Builder;
      37: checkcast     #2                  // class com/google/protobuf/GeneratedMessageV3$ExtendableBuilder
      40: areturn

  public BuilderType clearField(com.google.protobuf.Descriptors$FieldDescriptor);
    Code:
       0: aload_1
       1: invokevirtual #364                // Method com/google/protobuf/Descriptors$FieldDescriptor.isExtension:()Z
       4: ifeq          30
       7: aload_0
       8: aload_1
       9: invokespecial #368                // Method verifyContainingType:(Lcom/google/protobuf/Descriptors$FieldDescriptor;)V
      12: aload_0
      13: invokespecial #239                // Method ensureExtensionsIsMutable:()V
      16: aload_0
      17: getfield      #82                 // Field extensions:Lcom/google/protobuf/FieldSet$Builder;
      20: aload_1
      21: invokevirtual #271                // Method com/google/protobuf/FieldSet$Builder.clearField:(Lcom/google/protobuf/FieldSet$FieldDescriptorLite;)V
      24: aload_0
      25: invokevirtual #249                // Method onChanged:()V
      28: aload_0
      29: areturn
      30: aload_0
      31: aload_1
      32: invokespecial #427                // Method com/google/protobuf/GeneratedMessageV3$Builder.clearField:(Lcom/google/protobuf/Descriptors$FieldDescriptor;)Lcom/google/protobuf/GeneratedMessageV3$Builder;
      35: checkcast     #2                  // class com/google/protobuf/GeneratedMessageV3$ExtendableBuilder
      38: areturn

  public BuilderType setRepeatedField(com.google.protobuf.Descriptors$FieldDescriptor, int, java.lang.Object);
    Code:
       0: aload_1
       1: invokevirtual #364                // Method com/google/protobuf/Descriptors$FieldDescriptor.isExtension:()Z
       4: ifeq          32
       7: aload_0
       8: aload_1
       9: invokespecial #368                // Method verifyContainingType:(Lcom/google/protobuf/Descriptors$FieldDescriptor;)V
      12: aload_0
      13: invokespecial #239                // Method ensureExtensionsIsMutable:()V
      16: aload_0
      17: getfield      #82                 // Field extensions:Lcom/google/protobuf/FieldSet$Builder;
      20: aload_1
      21: iload_2
      22: aload_3
      23: invokevirtual #259                // Method com/google/protobuf/FieldSet$Builder.setRepeatedField:(Lcom/google/protobuf/FieldSet$FieldDescriptorLite;ILjava/lang/Object;)V
      26: aload_0
      27: invokevirtual #249                // Method onChanged:()V
      30: aload_0
      31: areturn
      32: aload_0
      33: aload_1
      34: iload_2
      35: aload_3
      36: invokespecial #432                // Method com/google/protobuf/GeneratedMessageV3$Builder.setRepeatedField:(Lcom/google/protobuf/Descriptors$FieldDescriptor;ILjava/lang/Object;)Lcom/google/protobuf/GeneratedMessageV3$Builder;
      39: checkcast     #2                  // class com/google/protobuf/GeneratedMessageV3$ExtendableBuilder
      42: areturn

  public BuilderType addRepeatedField(com.google.protobuf.Descriptors$FieldDescriptor, java.lang.Object);
    Code:
       0: aload_1
       1: invokevirtual #364                // Method com/google/protobuf/Descriptors$FieldDescriptor.isExtension:()Z
       4: ifeq          31
       7: aload_0
       8: aload_1
       9: invokespecial #368                // Method verifyContainingType:(Lcom/google/protobuf/Descriptors$FieldDescriptor;)V
      12: aload_0
      13: invokespecial #239                // Method ensureExtensionsIsMutable:()V
      16: aload_0
      17: getfield      #82                 // Field extensions:Lcom/google/protobuf/FieldSet$Builder;
      20: aload_1
      21: aload_2
      22: invokevirtual #264                // Method com/google/protobuf/FieldSet$Builder.addRepeatedField:(Lcom/google/protobuf/FieldSet$FieldDescriptorLite;Ljava/lang/Object;)V
      25: aload_0
      26: invokevirtual #249                // Method onChanged:()V
      29: aload_0
      30: areturn
      31: aload_0
      32: aload_1
      33: aload_2
      34: invokespecial #434                // Method com/google/protobuf/GeneratedMessageV3$Builder.addRepeatedField:(Lcom/google/protobuf/Descriptors$FieldDescriptor;Ljava/lang/Object;)Lcom/google/protobuf/GeneratedMessageV3$Builder;
      37: checkcast     #2                  // class com/google/protobuf/GeneratedMessageV3$ExtendableBuilder
      40: areturn

  public com.google.protobuf.Message$Builder newBuilderForField(com.google.protobuf.Descriptors$FieldDescriptor);
    Code:
       0: aload_1
       1: invokevirtual #364                // Method com/google/protobuf/Descriptors$FieldDescriptor.isExtension:()Z
       4: ifeq          15
       7: aload_1
       8: invokevirtual #371                // Method com/google/protobuf/Descriptors$FieldDescriptor.getMessageType:()Lcom/google/protobuf/Descriptors$Descriptor;
      11: invokestatic  #391                // Method com/google/protobuf/DynamicMessage.newBuilder:(Lcom/google/protobuf/Descriptors$Descriptor;)Lcom/google/protobuf/DynamicMessage$Builder;
      14: areturn
      15: aload_0
      16: aload_1
      17: invokespecial #437                // Method com/google/protobuf/GeneratedMessageV3$Builder.newBuilderForField:(Lcom/google/protobuf/Descriptors$FieldDescriptor;)Lcom/google/protobuf/Message$Builder;
      20: areturn

  protected final void mergeExtensionFields(com.google.protobuf.GeneratedMessageV3$ExtendableMessage);
    Code:
       0: aload_1
       1: invokestatic  #443                // Method com/google/protobuf/GeneratedMessageV3$ExtendableMessage.access$600:(Lcom/google/protobuf/GeneratedMessageV3$ExtendableMessage;)Lcom/google/protobuf/FieldSet;
       4: ifnull        26
       7: aload_0
       8: invokespecial #239                // Method ensureExtensionsIsMutable:()V
      11: aload_0
      12: getfield      #82                 // Field extensions:Lcom/google/protobuf/FieldSet$Builder;
      15: aload_1
      16: invokestatic  #443                // Method com/google/protobuf/GeneratedMessageV3$ExtendableMessage.access$600:(Lcom/google/protobuf/GeneratedMessageV3$ExtendableMessage;)Lcom/google/protobuf/FieldSet;
      19: invokevirtual #446                // Method com/google/protobuf/FieldSet$Builder.mergeFrom:(Lcom/google/protobuf/FieldSet;)V
      22: aload_0
      23: invokevirtual #249                // Method onChanged:()V
      26: return

  private void verifyContainingType(com.google.protobuf.Descriptors$FieldDescriptor);
    Code:
       0: aload_1
       1: invokevirtual #108                // Method com/google/protobuf/Descriptors$FieldDescriptor.getContainingType:()Lcom/google/protobuf/Descriptors$Descriptor;
       4: aload_0
       5: invokevirtual #111                // Method getDescriptorForType:()Lcom/google/protobuf/Descriptors$Descriptor;
       8: if_acmpeq     22
      11: new           #113                // class java/lang/IllegalArgumentException
      14: dup
      15: ldc_w         #450                // String FieldDescriptor does not match message type.
      18: invokespecial #148                // Method java/lang/IllegalArgumentException."<init>":(Ljava/lang/String;)V
      21: athrow
      22: return

  public com.google.protobuf.GeneratedMessageV3$Builder addRepeatedField(com.google.protobuf.Descriptors$FieldDescriptor, java.lang.Object);
    Code:
       0: aload_0
       1: aload_1
       2: aload_2
       3: invokevirtual #452                // Method addRepeatedField:(Lcom/google/protobuf/Descriptors$FieldDescriptor;Ljava/lang/Object;)Lcom/google/protobuf/GeneratedMessageV3$ExtendableBuilder;
       6: areturn

  public com.google.protobuf.GeneratedMessageV3$Builder setRepeatedField(com.google.protobuf.Descriptors$FieldDescriptor, int, java.lang.Object);
    Code:
       0: aload_0
       1: aload_1
       2: iload_2
       3: aload_3
       4: invokevirtual #454                // Method setRepeatedField:(Lcom/google/protobuf/Descriptors$FieldDescriptor;ILjava/lang/Object;)Lcom/google/protobuf/GeneratedMessageV3$ExtendableBuilder;
       7: areturn

  public com.google.protobuf.GeneratedMessageV3$Builder clearField(com.google.protobuf.Descriptors$FieldDescriptor);
    Code:
       0: aload_0
       1: aload_1
       2: invokevirtual #456                // Method clearField:(Lcom/google/protobuf/Descriptors$FieldDescriptor;)Lcom/google/protobuf/GeneratedMessageV3$ExtendableBuilder;
       5: areturn

  public com.google.protobuf.GeneratedMessageV3$Builder setField(com.google.protobuf.Descriptors$FieldDescriptor, java.lang.Object);
    Code:
       0: aload_0
       1: aload_1
       2: aload_2
       3: invokevirtual #458                // Method setField:(Lcom/google/protobuf/Descriptors$FieldDescriptor;Ljava/lang/Object;)Lcom/google/protobuf/GeneratedMessageV3$ExtendableBuilder;
       6: areturn

  public com.google.protobuf.GeneratedMessageV3$Builder clear();
    Code:
       0: aload_0
       1: invokevirtual #460                // Method clear:()Lcom/google/protobuf/GeneratedMessageV3$ExtendableBuilder;
       4: areturn

  public com.google.protobuf.AbstractMessage$Builder clear();
    Code:
       0: aload_0
       1: invokevirtual #460                // Method clear:()Lcom/google/protobuf/GeneratedMessageV3$ExtendableBuilder;
       4: areturn

  public com.google.protobuf.Message$Builder addRepeatedField(com.google.protobuf.Descriptors$FieldDescriptor, java.lang.Object);
    Code:
       0: aload_0
       1: aload_1
       2: aload_2
       3: invokevirtual #452                // Method addRepeatedField:(Lcom/google/protobuf/Descriptors$FieldDescriptor;Ljava/lang/Object;)Lcom/google/protobuf/GeneratedMessageV3$ExtendableBuilder;
       6: areturn

  public com.google.protobuf.Message$Builder setRepeatedField(com.google.protobuf.Descriptors$FieldDescriptor, int, java.lang.Object);
    Code:
       0: aload_0
       1: aload_1
       2: iload_2
       3: aload_3
       4: invokevirtual #454                // Method setRepeatedField:(Lcom/google/protobuf/Descriptors$FieldDescriptor;ILjava/lang/Object;)Lcom/google/protobuf/GeneratedMessageV3$ExtendableBuilder;
       7: areturn

  public com.google.protobuf.Message$Builder clearField(com.google.protobuf.Descriptors$FieldDescriptor);
    Code:
       0: aload_0
       1: aload_1
       2: invokevirtual #456                // Method clearField:(Lcom/google/protobuf/Descriptors$FieldDescriptor;)Lcom/google/protobuf/GeneratedMessageV3$ExtendableBuilder;
       5: areturn

  public com.google.protobuf.Message$Builder setField(com.google.protobuf.Descriptors$FieldDescriptor, java.lang.Object);
    Code:
       0: aload_0
       1: aload_1
       2: aload_2
       3: invokevirtual #458                // Method setField:(Lcom/google/protobuf/Descriptors$FieldDescriptor;Ljava/lang/Object;)Lcom/google/protobuf/GeneratedMessageV3$ExtendableBuilder;
       6: areturn

  public com.google.protobuf.Message$Builder clear();
    Code:
       0: aload_0
       1: invokevirtual #460                // Method clear:()Lcom/google/protobuf/GeneratedMessageV3$ExtendableBuilder;
       4: areturn

  public com.google.protobuf.MessageLite$Builder clear();
    Code:
       0: aload_0
       1: invokevirtual #460                // Method clear:()Lcom/google/protobuf/GeneratedMessageV3$ExtendableBuilder;
       4: areturn

  static com.google.protobuf.FieldSet access$400(com.google.protobuf.GeneratedMessageV3$ExtendableBuilder);
    Code:
       0: aload_0
       1: invokespecial #468                // Method buildExtensions:()Lcom/google/protobuf/FieldSet;
       4: areturn
}
