Compiled from "Double.scala"
public final class scala.Double$ implements scala.AnyValCompanion {
  public static final scala.Double$ MODULE$;

  private final double MinPositiveValue;

  private final double NaN;

  private final double PositiveInfinity;

  private final double NegativeInfinity;

  private final double MinValue;

  private final double MaxValue;

  public static {};
    Code:
       0: new           #2                  // class scala/Double$
       3: invokespecial #14                 // Method "<init>":()V
       6: return

  public final double MinPositiveValue();
    Code:
       0: ldc2_w        #23                 // double 4.9E-324d
       3: dreturn

  public final double NaN();
    Code:
       0: ldc2_w        #26                 // double NaNd
       3: dreturn

  public final double PositiveInfinity();
    Code:
       0: ldc2_w        #28                 // double Infinityd
       3: dreturn

  public final double NegativeInfinity();
    Code:
       0: ldc2_w        #30                 // double -Infinityd
       3: dreturn

  public final double MinValue();
    Code:
       0: aload_0
       1: getfield      #33                 // Field MinValue:D
       4: dreturn

  public final double MaxValue();
    Code:
       0: ldc2_w        #34                 // double 1.7976931348623157E308d
       3: dreturn

  public java.lang.Double box(double);
    Code:
       0: dload_1
       1: invokestatic  #42                 // Method java/lang/Double.valueOf:(D)Ljava/lang/Double;
       4: areturn

  public double unbox(java.lang.Object);
    Code:
       0: aload_1
       1: checkcast     #39                 // class java/lang/Double
       4: invokevirtual #48                 // Method java/lang/Double.doubleValue:()D
       7: dreturn

  public java.lang.String toString();
    Code:
       0: ldc           #53                 // String object scala.Double
       2: areturn

  private scala.Double$();
    Code:
       0: aload_0
       1: invokespecial #54                 // Method java/lang/Object."<init>":()V
       4: aload_0
       5: putstatic     #56                 // Field MODULE$:Lscala/Double$;
       8: aload_0
       9: ldc2_w        #34                 // double 1.7976931348623157E308d
      12: dneg
      13: putfield      #33                 // Field MinValue:D
      16: return
}
