Compiled from "Proxy.scala"
public abstract class scala.Proxy$class {
  public static int hashCode(scala.Proxy);
    Code:
       0: aload_0
       1: invokeinterface #13,  1           // InterfaceMethod scala/Proxy.self:()Ljava/lang/Object;
       6: invokevirtual #16                 // Method java/lang/Object.hashCode:()I
       9: ireturn

  public static boolean equals(scala.Proxy, java.lang.Object);
    Code:
       0: aload_1
       1: ifnonnull     9
       4: iconst_0
       5: istore_2
       6: goto          43
       9: aload_1
      10: aload_0
      11: if_acmpeq     37
      14: aload_1
      15: aload_0
      16: invokeinterface #13,  1           // InterfaceMethod scala/Proxy.self:()Ljava/lang/Object;
      21: if_acmpeq     37
      24: aload_1
      25: aload_0
      26: invokeinterface #13,  1           // InterfaceMethod scala/Proxy.self:()Ljava/lang/Object;
      31: invokevirtual #23                 // Method java/lang/Object.equals:(Ljava/lang/Object;)Z
      34: ifeq          41
      37: iconst_1
      38: goto          42
      41: iconst_0
      42: istore_2
      43: iload_2
      44: ireturn

  public static java.lang.String toString(scala.Proxy);
    Code:
       0: aload_0
       1: invokeinterface #13,  1           // InterfaceMethod scala/Proxy.self:()Ljava/lang/Object;
       6: invokestatic  #33                 // Method java/lang/String.valueOf:(Ljava/lang/Object;)Ljava/lang/String;
       9: areturn

  public static void $init$(scala.Proxy);
    Code:
       0: return
}
