Compiled from "SubscriptionType.java"
public final class org.apache.pulsar.client.api.SubscriptionType extends java.lang.Enum<org.apache.pulsar.client.api.SubscriptionType> {
  public static final org.apache.pulsar.client.api.SubscriptionType Exclusive;

  public static final org.apache.pulsar.client.api.SubscriptionType Shared;

  public static final org.apache.pulsar.client.api.SubscriptionType Failover;

  public static final org.apache.pulsar.client.api.SubscriptionType Key_Shared;

  private static final org.apache.pulsar.client.api.SubscriptionType[] $VALUES;

  public static org.apache.pulsar.client.api.SubscriptionType[] values();
    Code:
       0: getstatic     #1                  // Field $VALUES:[Lorg/apache/pulsar/client/api/SubscriptionType;
       3: invokevirtual #2                  // Method "[Lorg/apache/pulsar/client/api/SubscriptionType;".clone:()Ljava/lang/Object;
       6: checkcast     #3                  // class "[Lorg/apache/pulsar/client/api/SubscriptionType;"
       9: areturn

  public static org.apache.pulsar.client.api.SubscriptionType valueOf(java.lang.String);
    Code:
       0: ldc           #4                  // class org/apache/pulsar/client/api/SubscriptionType
       2: aload_0
       3: invokestatic  #5                  // Method java/lang/Enum.valueOf:(Ljava/lang/Class;Ljava/lang/String;)Ljava/lang/Enum;
       6: checkcast     #4                  // class org/apache/pulsar/client/api/SubscriptionType
       9: areturn

  private org.apache.pulsar.client.api.SubscriptionType();
    Code:
       0: aload_0
       1: aload_1
       2: iload_2
       3: invokespecial #6                  // Method java/lang/Enum."<init>":(Ljava/lang/String;I)V
       6: return

  static {};
    Code:
       0: new           #4                  // class org/apache/pulsar/client/api/SubscriptionType
       3: dup
       4: ldc           #7                  // String Exclusive
       6: iconst_0
       7: invokespecial #8                  // Method "<init>":(Ljava/lang/String;I)V
      10: putstatic     #9                  // Field Exclusive:Lorg/apache/pulsar/client/api/SubscriptionType;
      13: new           #4                  // class org/apache/pulsar/client/api/SubscriptionType
      16: dup
      17: ldc           #10                 // String Shared
      19: iconst_1
      20: invokespecial #8                  // Method "<init>":(Ljava/lang/String;I)V
      23: putstatic     #11                 // Field Shared:Lorg/apache/pulsar/client/api/SubscriptionType;
      26: new           #4                  // class org/apache/pulsar/client/api/SubscriptionType
      29: dup
      30: ldc           #12                 // String Failover
      32: iconst_2
      33: invokespecial #8                  // Method "<init>":(Ljava/lang/String;I)V
      36: putstatic     #13                 // Field Failover:Lorg/apache/pulsar/client/api/SubscriptionType;
      39: new           #4                  // class org/apache/pulsar/client/api/SubscriptionType
      42: dup
      43: ldc           #14                 // String Key_Shared
      45: iconst_3
      46: invokespecial #8                  // Method "<init>":(Ljava/lang/String;I)V
      49: putstatic     #15                 // Field Key_Shared:Lorg/apache/pulsar/client/api/SubscriptionType;
      52: iconst_4
      53: anewarray     #4                  // class org/apache/pulsar/client/api/SubscriptionType
      56: dup
      57: iconst_0
      58: getstatic     #9                  // Field Exclusive:Lorg/apache/pulsar/client/api/SubscriptionType;
      61: aastore
      62: dup
      63: iconst_1
      64: getstatic     #11                 // Field Shared:Lorg/apache/pulsar/client/api/SubscriptionType;
      67: aastore
      68: dup
      69: iconst_2
      70: getstatic     #13                 // Field Failover:Lorg/apache/pulsar/client/api/SubscriptionType;
      73: aastore
      74: dup
      75: iconst_3
      76: getstatic     #15                 // Field Key_Shared:Lorg/apache/pulsar/client/api/SubscriptionType;
      79: aastore
      80: putstatic     #1                  // Field $VALUES:[Lorg/apache/pulsar/client/api/SubscriptionType;
      83: return
}
