Compiled from "ServiceRefHandlerType.java"
public class org.apache.axis2.jaxws.description.xml.handler.ServiceRefHandlerType {
  protected java.util.List<org.apache.axis2.jaxws.description.xml.handler.DescriptionType> description;

  protected java.util.List<org.apache.axis2.jaxws.description.xml.handler.DisplayNameType> displayName;

  protected java.util.List<org.apache.axis2.jaxws.description.xml.handler.IconType> icon;

  protected org.apache.axis2.jaxws.description.xml.handler.String handlerName;

  protected org.apache.axis2.jaxws.description.xml.handler.FullyQualifiedClassType handlerClass;

  protected java.util.List<org.apache.axis2.jaxws.description.xml.handler.ParamValueType> initParam;

  protected java.util.List<org.apache.axis2.jaxws.description.xml.handler.XsdQNameType> soapHeader;

  protected java.util.List<org.apache.axis2.jaxws.description.xml.handler.String> soapRole;

  protected java.util.List<org.apache.axis2.jaxws.description.xml.handler.String> portName;

  protected java.lang.String id;

  public org.apache.axis2.jaxws.description.xml.handler.ServiceRefHandlerType();
    Code:
       0: aload_0
       1: invokespecial #1                  // Method java/lang/Object."<init>":()V
       4: return

  public java.util.List<org.apache.axis2.jaxws.description.xml.handler.DescriptionType> getDescription();
    Code:
       0: aload_0
       1: getfield      #2                  // Field description:Ljava/util/List;
       4: ifnonnull     18
       7: aload_0
       8: new           #3                  // class java/util/ArrayList
      11: dup
      12: invokespecial #4                  // Method java/util/ArrayList."<init>":()V
      15: putfield      #2                  // Field description:Ljava/util/List;
      18: aload_0
      19: getfield      #2                  // Field description:Ljava/util/List;
      22: areturn

  public java.util.List<org.apache.axis2.jaxws.description.xml.handler.DisplayNameType> getDisplayName();
    Code:
       0: aload_0
       1: getfield      #5                  // Field displayName:Ljava/util/List;
       4: ifnonnull     18
       7: aload_0
       8: new           #3                  // class java/util/ArrayList
      11: dup
      12: invokespecial #4                  // Method java/util/ArrayList."<init>":()V
      15: putfield      #5                  // Field displayName:Ljava/util/List;
      18: aload_0
      19: getfield      #5                  // Field displayName:Ljava/util/List;
      22: areturn

  public java.util.List<org.apache.axis2.jaxws.description.xml.handler.IconType> getIcon();
    Code:
       0: aload_0
       1: getfield      #6                  // Field icon:Ljava/util/List;
       4: ifnonnull     18
       7: aload_0
       8: new           #3                  // class java/util/ArrayList
      11: dup
      12: invokespecial #4                  // Method java/util/ArrayList."<init>":()V
      15: putfield      #6                  // Field icon:Ljava/util/List;
      18: aload_0
      19: getfield      #6                  // Field icon:Ljava/util/List;
      22: areturn

  public org.apache.axis2.jaxws.description.xml.handler.String getHandlerName();
    Code:
       0: aload_0
       1: getfield      #7                  // Field handlerName:Lorg/apache/axis2/jaxws/description/xml/handler/String;
       4: areturn

  public void setHandlerName(org.apache.axis2.jaxws.description.xml.handler.String);
    Code:
       0: aload_0
       1: aload_1
       2: putfield      #7                  // Field handlerName:Lorg/apache/axis2/jaxws/description/xml/handler/String;
       5: return

  public org.apache.axis2.jaxws.description.xml.handler.FullyQualifiedClassType getHandlerClass();
    Code:
       0: aload_0
       1: getfield      #8                  // Field handlerClass:Lorg/apache/axis2/jaxws/description/xml/handler/FullyQualifiedClassType;
       4: areturn

  public void setHandlerClass(org.apache.axis2.jaxws.description.xml.handler.FullyQualifiedClassType);
    Code:
       0: aload_0
       1: aload_1
       2: putfield      #8                  // Field handlerClass:Lorg/apache/axis2/jaxws/description/xml/handler/FullyQualifiedClassType;
       5: return

  public java.util.List<org.apache.axis2.jaxws.description.xml.handler.ParamValueType> getInitParam();
    Code:
       0: aload_0
       1: getfield      #9                  // Field initParam:Ljava/util/List;
       4: ifnonnull     18
       7: aload_0
       8: new           #3                  // class java/util/ArrayList
      11: dup
      12: invokespecial #4                  // Method java/util/ArrayList."<init>":()V
      15: putfield      #9                  // Field initParam:Ljava/util/List;
      18: aload_0
      19: getfield      #9                  // Field initParam:Ljava/util/List;
      22: areturn

  public java.util.List<org.apache.axis2.jaxws.description.xml.handler.XsdQNameType> getSoapHeader();
    Code:
       0: aload_0
       1: getfield      #10                 // Field soapHeader:Ljava/util/List;
       4: ifnonnull     18
       7: aload_0
       8: new           #3                  // class java/util/ArrayList
      11: dup
      12: invokespecial #4                  // Method java/util/ArrayList."<init>":()V
      15: putfield      #10                 // Field soapHeader:Ljava/util/List;
      18: aload_0
      19: getfield      #10                 // Field soapHeader:Ljava/util/List;
      22: areturn

  public java.util.List<org.apache.axis2.jaxws.description.xml.handler.String> getSoapRole();
    Code:
       0: aload_0
       1: getfield      #11                 // Field soapRole:Ljava/util/List;
       4: ifnonnull     18
       7: aload_0
       8: new           #3                  // class java/util/ArrayList
      11: dup
      12: invokespecial #4                  // Method java/util/ArrayList."<init>":()V
      15: putfield      #11                 // Field soapRole:Ljava/util/List;
      18: aload_0
      19: getfield      #11                 // Field soapRole:Ljava/util/List;
      22: areturn

  public java.util.List<org.apache.axis2.jaxws.description.xml.handler.String> getPortName();
    Code:
       0: aload_0
       1: getfield      #12                 // Field portName:Ljava/util/List;
       4: ifnonnull     18
       7: aload_0
       8: new           #3                  // class java/util/ArrayList
      11: dup
      12: invokespecial #4                  // Method java/util/ArrayList."<init>":()V
      15: putfield      #12                 // Field portName:Ljava/util/List;
      18: aload_0
      19: getfield      #12                 // Field portName:Ljava/util/List;
      22: areturn

  public java.lang.String getId();
    Code:
       0: aload_0
       1: getfield      #13                 // Field id:Ljava/lang/String;
       4: areturn

  public void setId(java.lang.String);
    Code:
       0: aload_0
       1: aload_1
       2: putfield      #13                 // Field id:Ljava/lang/String;
       5: return
}
