Compiled from "AuthorizationCodeHandler.kt"
final class no.nav.security.mock.oauth2.grant.AuthorizationCodeHandler$LoginOAuth2TokenCallback implements no.nav.security.mock.oauth2.token.OAuth2TokenCallback {
  private final no.nav.security.mock.oauth2.login.Login login;

  private final no.nav.security.mock.oauth2.token.OAuth2TokenCallback oAuth2TokenCallback;

  public no.nav.security.mock.oauth2.grant.AuthorizationCodeHandler$LoginOAuth2TokenCallback(no.nav.security.mock.oauth2.login.Login, no.nav.security.mock.oauth2.token.OAuth2TokenCallback);
    Code:
       0: aload_1
       1: ldc           #11                 // String login
       3: invokestatic  #17                 // Method kotlin/jvm/internal/Intrinsics.checkNotNullParameter:(Ljava/lang/Object;Ljava/lang/String;)V
       6: aload_2
       7: ldc           #19                 // String oAuth2TokenCallback
       9: invokestatic  #17                 // Method kotlin/jvm/internal/Intrinsics.checkNotNullParameter:(Ljava/lang/Object;Ljava/lang/String;)V
      12: aload_0
      13: invokespecial #22                 // Method java/lang/Object."<init>":()V
      16: aload_0
      17: aload_1
      18: putfield      #25                 // Field login:Lno/nav/security/mock/oauth2/login/Login;
      21: aload_0
      22: aload_2
      23: putfield      #28                 // Field oAuth2TokenCallback:Lno/nav/security/mock/oauth2/token/OAuth2TokenCallback;
      26: return

  public final no.nav.security.mock.oauth2.login.Login getLogin();
    Code:
       0: aload_0
       1: getfield      #25                 // Field login:Lno/nav/security/mock/oauth2/login/Login;
       4: areturn

  public final no.nav.security.mock.oauth2.token.OAuth2TokenCallback getOAuth2TokenCallback();
    Code:
       0: aload_0
       1: getfield      #28                 // Field oAuth2TokenCallback:Lno/nav/security/mock/oauth2/token/OAuth2TokenCallback;
       4: areturn

  public java.lang.String issuerId();
    Code:
       0: aload_0
       1: getfield      #28                 // Field oAuth2TokenCallback:Lno/nav/security/mock/oauth2/token/OAuth2TokenCallback;
       4: invokeinterface #38,  1           // InterfaceMethod no/nav/security/mock/oauth2/token/OAuth2TokenCallback.issuerId:()Ljava/lang/String;
       9: areturn

  public java.lang.String subject(com.nimbusds.oauth2.sdk.TokenRequest);
    Code:
       0: aload_1
       1: ldc           #42                 // String tokenRequest
       3: invokestatic  #17                 // Method kotlin/jvm/internal/Intrinsics.checkNotNullParameter:(Ljava/lang/Object;Ljava/lang/String;)V
       6: aload_0
       7: getfield      #25                 // Field login:Lno/nav/security/mock/oauth2/login/Login;
      10: invokevirtual #47                 // Method no/nav/security/mock/oauth2/login/Login.getUsername:()Ljava/lang/String;
      13: areturn

  public java.lang.String typeHeader(com.nimbusds.oauth2.sdk.TokenRequest);
    Code:
       0: aload_1
       1: ldc           #42                 // String tokenRequest
       3: invokestatic  #17                 // Method kotlin/jvm/internal/Intrinsics.checkNotNullParameter:(Ljava/lang/Object;Ljava/lang/String;)V
       6: aload_0
       7: getfield      #28                 // Field oAuth2TokenCallback:Lno/nav/security/mock/oauth2/token/OAuth2TokenCallback;
      10: aload_1
      11: invokeinterface #51,  2           // InterfaceMethod no/nav/security/mock/oauth2/token/OAuth2TokenCallback.typeHeader:(Lcom/nimbusds/oauth2/sdk/TokenRequest;)Ljava/lang/String;
      16: areturn

  public java.util.List<java.lang.String> audience(com.nimbusds.oauth2.sdk.TokenRequest);
    Code:
       0: aload_1
       1: ldc           #42                 // String tokenRequest
       3: invokestatic  #17                 // Method kotlin/jvm/internal/Intrinsics.checkNotNullParameter:(Ljava/lang/Object;Ljava/lang/String;)V
       6: aload_0
       7: getfield      #28                 // Field oAuth2TokenCallback:Lno/nav/security/mock/oauth2/token/OAuth2TokenCallback;
      10: aload_1
      11: invokeinterface #56,  2           // InterfaceMethod no/nav/security/mock/oauth2/token/OAuth2TokenCallback.audience:(Lcom/nimbusds/oauth2/sdk/TokenRequest;)Ljava/util/List;
      16: areturn

  public java.util.Map<java.lang.String, java.lang.Object> addClaims(com.nimbusds.oauth2.sdk.TokenRequest);
    Code:
       0: aload_1
       1: ldc           #42                 // String tokenRequest
       3: invokestatic  #17                 // Method kotlin/jvm/internal/Intrinsics.checkNotNullParameter:(Ljava/lang/Object;Ljava/lang/String;)V
       6: aload_0
       7: getfield      #28                 // Field oAuth2TokenCallback:Lno/nav/security/mock/oauth2/token/OAuth2TokenCallback;
      10: aload_1
      11: invokeinterface #63,  2           // InterfaceMethod no/nav/security/mock/oauth2/token/OAuth2TokenCallback.addClaims:(Lcom/nimbusds/oauth2/sdk/TokenRequest;)Ljava/util/Map;
      16: invokestatic  #69                 // Method kotlin/collections/MapsKt.toMutableMap:(Ljava/util/Map;)Ljava/util/Map;
      19: astore_2
      20: aload_2
      21: astore_3
      22: iconst_0
      23: istore        4
      25: aload_0
      26: getfield      #25                 // Field login:Lno/nav/security/mock/oauth2/login/Login;
      29: invokevirtual #72                 // Method no/nav/security/mock/oauth2/login/Login.getClaims:()Ljava/lang/String;
      32: dup
      33: ifnull        202
      36: astore        5
      38: iconst_0
      39: istore        6
      41: nop
      42: invokestatic  #78                 // Method no/nav/security/mock/oauth2/grant/AuthorizationCodeHandlerKt.access$getJsonMapper$p:()Lcom/fasterxml/jackson/databind/ObjectMapper;
      45: aload         5
      47: invokevirtual #84                 // Method com/fasterxml/jackson/databind/ObjectMapper.readTree:(Ljava/lang/String;)Lcom/fasterxml/jackson/databind/JsonNode;
      50: invokevirtual #90                 // Method com/fasterxml/jackson/databind/JsonNode.fields:()Ljava/util/Iterator;
      53: dup
      54: ldc           #92                 // String fields(...)
      56: invokestatic  #95                 // Method kotlin/jvm/internal/Intrinsics.checkNotNullExpressionValue:(Ljava/lang/Object;Ljava/lang/String;)V
      59: astore        7
      61: nop
      62: iconst_0
      63: istore        8
      65: aload         7
      67: astore        9
      69: aload         9
      71: invokeinterface #101,  1          // InterfaceMethod java/util/Iterator.hasNext:()Z
      76: ifeq          172
      79: aload         9
      81: invokeinterface #105,  1          // InterfaceMethod java/util/Iterator.next:()Ljava/lang/Object;
      86: astore        10
      88: aload         10
      90: checkcast     #107                // class java/util/Map$Entry
      93: astore        11
      95: iconst_0
      96: istore        12
      98: aload_3
      99: aload         11
     101: invokeinterface #110,  1          // InterfaceMethod java/util/Map$Entry.getKey:()Ljava/lang/Object;
     106: dup
     107: ldc           #112                // String <get-key>(...)
     109: invokestatic  #95                 // Method kotlin/jvm/internal/Intrinsics.checkNotNullExpressionValue:(Ljava/lang/Object;Ljava/lang/String;)V
     112: invokestatic  #78                 // Method no/nav/security/mock/oauth2/grant/AuthorizationCodeHandlerKt.access$getJsonMapper$p:()Lcom/fasterxml/jackson/databind/ObjectMapper;
     115: astore        13
     117: aload         11
     119: invokeinterface #115,  1          // InterfaceMethod java/util/Map$Entry.getValue:()Ljava/lang/Object;
     124: checkcast     #86                 // class com/fasterxml/jackson/databind/JsonNode
     127: invokevirtual #118                // Method com/fasterxml/jackson/databind/JsonNode.toString:()Ljava/lang/String;
     130: dup
     131: ldc           #120                // String toString(...)
     133: invokestatic  #95                 // Method kotlin/jvm/internal/Intrinsics.checkNotNullExpressionValue:(Ljava/lang/Object;Ljava/lang/String;)V
     136: astore        14
     138: iconst_0
     139: istore        15
     141: aload         13
     143: aload         14
     145: iconst_0
     146: istore        16
     148: new           #122                // class no/nav/security/mock/oauth2/grant/AuthorizationCodeHandler$LoginOAuth2TokenCallback$addClaims$lambda$2$lambda$1$lambda$0$$inlined$readValue$1
     151: dup
     152: invokespecial #123                // Method no/nav/security/mock/oauth2/grant/AuthorizationCodeHandler$LoginOAuth2TokenCallback$addClaims$lambda$2$lambda$1$lambda$0$$inlined$readValue$1."<init>":()V
     155: checkcast     #125                // class com/fasterxml/jackson/core/type/TypeReference
     158: invokevirtual #129                // Method com/fasterxml/jackson/databind/ObjectMapper.readValue:(Ljava/lang/String;Lcom/fasterxml/jackson/core/type/TypeReference;)Ljava/lang/Object;
     161: invokeinterface #135,  3          // InterfaceMethod java/util/Map.put:(Ljava/lang/Object;Ljava/lang/Object;)Ljava/lang/Object;
     166: pop
     167: nop
     168: nop
     169: goto          69
     172: nop
     173: goto          198
     176: astore        7
     178: invokestatic  #139                // Method no/nav/security/mock/oauth2/grant/AuthorizationCodeHandlerKt.access$getLog$p:()Lmu/KLogger;
     181: aload         5
     183: aload         7
     185: invokevirtual #142                // Method com/fasterxml/jackson/core/JsonProcessingException.getMessage:()Ljava/lang/String;
     188: invokedynamic #154,  0            // InvokeDynamic #0:makeConcatWithConstants:(Ljava/lang/String;Ljava/lang/String;)Ljava/lang/String;
     193: invokeinterface #160,  2          // InterfaceMethod mu/KLogger.warn:(Ljava/lang/String;)V
     198: nop
     199: goto          204
     202: pop
     203: nop
     204: nop
     205: aload_2
     206: areturn
    Exception table:
       from    to  target type
          41   173   176   Class com/fasterxml/jackson/core/JsonProcessingException

  public long tokenExpiry();
    Code:
       0: aload_0
       1: getfield      #28                 // Field oAuth2TokenCallback:Lno/nav/security/mock/oauth2/token/OAuth2TokenCallback;
       4: invokeinterface #190,  1          // InterfaceMethod no/nav/security/mock/oauth2/token/OAuth2TokenCallback.tokenExpiry:()J
       9: lreturn
}
