Compiled from "RefreshTokenManager.kt"
public final class no.nav.security.mock.oauth2.grant.RefreshTokenManager {
  private final java.util.Map<java.lang.String, no.nav.security.mock.oauth2.token.OAuth2TokenCallback> cache;

  public no.nav.security.mock.oauth2.grant.RefreshTokenManager(java.util.Map<java.lang.String, no.nav.security.mock.oauth2.token.OAuth2TokenCallback>);
    Code:
       0: aload_1
       1: ldc           #10                 // String cache
       3: invokestatic  #16                 // Method kotlin/jvm/internal/Intrinsics.checkNotNullParameter:(Ljava/lang/Object;Ljava/lang/String;)V
       6: aload_0
       7: invokespecial #19                 // Method java/lang/Object."<init>":()V
      10: aload_0
      11: aload_1
      12: putfield      #22                 // Field cache:Ljava/util/Map;
      15: return

  public no.nav.security.mock.oauth2.grant.RefreshTokenManager(java.util.Map, int, kotlin.jvm.internal.DefaultConstructorMarker);
    Code:
       0: iload_2
       1: iconst_1
       2: iand
       3: ifeq          17
       6: new           #27                 // class java/util/HashMap
       9: dup
      10: invokespecial #28                 // Method java/util/HashMap."<init>":()V
      13: checkcast     #30                 // class java/util/Map
      16: astore_1
      17: aload_0
      18: aload_1
      19: invokespecial #32                 // Method "<init>":(Ljava/util/Map;)V
      22: return

  public final no.nav.security.mock.oauth2.token.OAuth2TokenCallback get(java.lang.String);
    Code:
       0: aload_1
       1: ldc           #37                 // String refreshToken
       3: invokestatic  #16                 // Method kotlin/jvm/internal/Intrinsics.checkNotNullParameter:(Ljava/lang/Object;Ljava/lang/String;)V
       6: aload_0
       7: getfield      #22                 // Field cache:Ljava/util/Map;
      10: aload_1
      11: invokeinterface #40,  2           // InterfaceMethod java/util/Map.get:(Ljava/lang/Object;)Ljava/lang/Object;
      16: checkcast     #42                 // class no/nav/security/mock/oauth2/token/OAuth2TokenCallback
      19: areturn

  public final no.nav.security.mock.oauth2.token.OAuth2TokenCallback remove(java.lang.String);
    Code:
       0: aload_1
       1: ldc           #37                 // String refreshToken
       3: invokestatic  #16                 // Method kotlin/jvm/internal/Intrinsics.checkNotNullParameter:(Ljava/lang/Object;Ljava/lang/String;)V
       6: aload_0
       7: getfield      #22                 // Field cache:Ljava/util/Map;
      10: aload_1
      11: invokeinterface #46,  2           // InterfaceMethod java/util/Map.remove:(Ljava/lang/Object;)Ljava/lang/Object;
      16: checkcast     #42                 // class no/nav/security/mock/oauth2/token/OAuth2TokenCallback
      19: areturn

  public final java.lang.String refreshToken(no.nav.security.mock.oauth2.token.OAuth2TokenCallback, java.lang.String);
    Code:
       0: aload_1
       1: ldc           #49                 // String tokenCallback
       3: invokestatic  #16                 // Method kotlin/jvm/internal/Intrinsics.checkNotNullParameter:(Ljava/lang/Object;Ljava/lang/String;)V
       6: invokestatic  #55                 // Method java/util/UUID.randomUUID:()Ljava/util/UUID;
       9: invokevirtual #59                 // Method java/util/UUID.toString:()Ljava/lang/String;
      12: dup
      13: ldc           #61                 // String toString(...)
      15: invokestatic  #64                 // Method kotlin/jvm/internal/Intrinsics.checkNotNullExpressionValue:(Ljava/lang/Object;Ljava/lang/String;)V
      18: astore_3
      19: aload_2
      20: dup
      21: ifnull        40
      24: astore        5
      26: iconst_0
      27: istore        6
      29: aload_0
      30: aload_3
      31: aload_2
      32: invokespecial #68                 // Method plainJWT:(Ljava/lang/String;Ljava/lang/String;)Ljava/lang/String;
      35: nop
      36: dup
      37: ifnonnull     42
      40: pop
      41: aload_3
      42: astore        4
      44: aload_0
      45: getfield      #22                 // Field cache:Ljava/util/Map;
      48: aload         4
      50: aload_1
      51: invokeinterface #72,  3           // InterfaceMethod java/util/Map.put:(Ljava/lang/Object;Ljava/lang/Object;)Ljava/lang/Object;
      56: pop
      57: aload         4
      59: areturn

  private final java.lang.String plainJWT(java.lang.String, java.lang.String);
    Code:
       0: new           #82                 // class com/nimbusds/jwt/PlainJWT
       3: dup
       4: iconst_2
       5: anewarray     #84                 // class kotlin/Pair
       8: astore_3
       9: aload_3
      10: iconst_0
      11: ldc           #85                 // String jti
      13: aload_1
      14: invokestatic  #91                 // Method kotlin/TuplesKt.to:(Ljava/lang/Object;Ljava/lang/Object;)Lkotlin/Pair;
      17: aastore
      18: aload_3
      19: iconst_1
      20: ldc           #92                 // String nonce
      22: aload_2
      23: invokestatic  #91                 // Method kotlin/TuplesKt.to:(Ljava/lang/Object;Ljava/lang/Object;)Lkotlin/Pair;
      26: aastore
      27: aload_3
      28: invokestatic  #98                 // Method kotlin/collections/MapsKt.mapOf:([Lkotlin/Pair;)Ljava/util/Map;
      31: invokestatic  #104                // Method com/nimbusds/jwt/JWTClaimsSet.parse:(Ljava/util/Map;)Lcom/nimbusds/jwt/JWTClaimsSet;
      34: invokespecial #107                // Method com/nimbusds/jwt/PlainJWT."<init>":(Lcom/nimbusds/jwt/JWTClaimsSet;)V
      37: invokevirtual #110                // Method com/nimbusds/jwt/PlainJWT.serialize:()Ljava/lang/String;
      40: dup
      41: ldc           #112                // String serialize(...)
      43: invokestatic  #64                 // Method kotlin/jvm/internal/Intrinsics.checkNotNullExpressionValue:(Ljava/lang/Object;Ljava/lang/String;)V
      46: areturn

  private final java.util.Map<java.lang.String, no.nav.security.mock.oauth2.token.OAuth2TokenCallback> component1();
    Code:
       0: aload_0
       1: getfield      #22                 // Field cache:Ljava/util/Map;
       4: areturn

  public final no.nav.security.mock.oauth2.grant.RefreshTokenManager copy(java.util.Map<java.lang.String, no.nav.security.mock.oauth2.token.OAuth2TokenCallback>);
    Code:
       0: aload_1
       1: ldc           #10                 // String cache
       3: invokestatic  #16                 // Method kotlin/jvm/internal/Intrinsics.checkNotNullParameter:(Ljava/lang/Object;Ljava/lang/String;)V
       6: new           #2                  // class no/nav/security/mock/oauth2/grant/RefreshTokenManager
       9: dup
      10: aload_1
      11: invokespecial #32                 // Method "<init>":(Ljava/util/Map;)V
      14: areturn

  public static no.nav.security.mock.oauth2.grant.RefreshTokenManager copy$default(no.nav.security.mock.oauth2.grant.RefreshTokenManager, java.util.Map, int, java.lang.Object);
    Code:
       0: iload_2
       1: iconst_1
       2: iand
       3: ifeq          11
       6: aload_0
       7: getfield      #22                 // Field cache:Ljava/util/Map;
      10: astore_1
      11: aload_0
      12: aload_1
      13: invokevirtual #122                // Method copy:(Ljava/util/Map;)Lno/nav/security/mock/oauth2/grant/RefreshTokenManager;
      16: areturn

  public java.lang.String toString();
    Code:
       0: aload_0
       1: getfield      #22                 // Field cache:Ljava/util/Map;
       4: invokedynamic #134,  0            // InvokeDynamic #0:makeConcatWithConstants:(Ljava/util/Map;)Ljava/lang/String;
       9: areturn

  public int hashCode();
    Code:
       0: aload_0
       1: getfield      #22                 // Field cache:Ljava/util/Map;
       4: invokevirtual #138                // Method java/lang/Object.hashCode:()I
       7: ireturn

  public boolean equals(java.lang.Object);
    Code:
       0: aload_0
       1: aload_1
       2: if_acmpne     7
       5: iconst_1
       6: ireturn
       7: aload_1
       8: instanceof    #2                  // class no/nav/security/mock/oauth2/grant/RefreshTokenManager
      11: ifne          16
      14: iconst_0
      15: ireturn
      16: aload_1
      17: checkcast     #2                  // class no/nav/security/mock/oauth2/grant/RefreshTokenManager
      20: astore_2
      21: aload_0
      22: getfield      #22                 // Field cache:Ljava/util/Map;
      25: aload_2
      26: getfield      #22                 // Field cache:Ljava/util/Map;
      29: invokestatic  #144                // Method kotlin/jvm/internal/Intrinsics.areEqual:(Ljava/lang/Object;Ljava/lang/Object;)Z
      32: ifne          37
      35: iconst_0
      36: ireturn
      37: iconst_1
      38: ireturn

  public no.nav.security.mock.oauth2.grant.RefreshTokenManager();
    Code:
       0: aload_0
       1: aconst_null
       2: iconst_1
       3: aconst_null
       4: invokespecial #148                // Method "<init>":(Ljava/util/Map;ILkotlin/jvm/internal/DefaultConstructorMarker;)V
       7: return
}
