Compiled from "Document.java"
public final class io.fluxcapacitor.common.search.Document {
  public static java.util.function.Function<io.fluxcapacitor.common.search.Document, ?> identityFunction;

  private final java.lang.String id;

  private final java.lang.String type;

  private final int revision;

  private final java.lang.String collection;

  private final java.time.Instant timestamp;

  private final java.time.Instant end;

  private final java.util.Map<io.fluxcapacitor.common.search.Document$Entry, java.util.List<io.fluxcapacitor.common.search.Document$Path>> entries;

  private final java.util.concurrent.atomic.AtomicReference<java.lang.Object> summarize;

  private java.lang.String doSummarize();
    Code:
       0: iconst_2
       1: anewarray     #1                  // class java/lang/String
       4: dup
       5: iconst_0
       6: aload_0
       7: getfield      #3                  // Field type:Ljava/lang/String;
      10: aastore
      11: dup
      12: iconst_1
      13: aload_0
      14: getfield      #9                  // Field id:Ljava/lang/String;
      17: aastore
      18: invokestatic  #12                 // InterfaceMethod java/util/stream/Stream.of:([Ljava/lang/Object;)Ljava/util/stream/Stream;
      21: aload_0
      22: invokevirtual #18                 // Method getEntries:()Ljava/util/Map;
      25: invokeinterface #22,  1           // InterfaceMethod java/util/Map.keySet:()Ljava/util/Set;
      30: invokeinterface #28,  1           // InterfaceMethod java/util/Set.stream:()Ljava/util/stream/Stream;
      35: invokedynamic #34,  0             // InvokeDynamic #0:apply:()Ljava/util/function/Function;
      40: invokeinterface #38,  2           // InterfaceMethod java/util/stream/Stream.map:(Ljava/util/function/Function;)Ljava/util/stream/Stream;
      45: invokestatic  #42                 // InterfaceMethod java/util/stream/Stream.concat:(Ljava/util/stream/Stream;Ljava/util/stream/Stream;)Ljava/util/stream/Stream;
      48: ldc           #46                 // String
      50: invokestatic  #48                 // Method java/util/stream/Collectors.joining:(Ljava/lang/CharSequence;)Ljava/util/stream/Collector;
      53: invokeinterface #54,  2           // InterfaceMethod java/util/stream/Stream.collect:(Ljava/util/stream/Collector;)Ljava/lang/Object;
      58: checkcast     #1                  // class java/lang/String
      61: areturn

  public java.util.Optional<io.fluxcapacitor.common.search.Document$Entry> getEntryAtPath(java.lang.String);
    Code:
       0: aload_0
       1: aload_1
       2: invokestatic  #58                 // Method io/fluxcapacitor/common/search/Document$Path.pathPredicate:(Ljava/lang/String;)Ljava/util/function/Predicate;
       5: invokevirtual #64                 // Method getMatchingEntries:(Ljava/util/function/Predicate;)Ljava/util/stream/Stream;
       8: invokeinterface #68,  1           // InterfaceMethod java/util/stream/Stream.findFirst:()Ljava/util/Optional;
      13: areturn

  public java.util.stream.Stream<io.fluxcapacitor.common.search.Document$Entry> getMatchingEntries(java.util.function.Predicate<io.fluxcapacitor.common.search.Document$Path>);
    Code:
       0: aload_0
       1: getfield      #72                 // Field entries:Ljava/util/Map;
       4: invokeinterface #76,  1           // InterfaceMethod java/util/Map.entrySet:()Ljava/util/Set;
       9: invokeinterface #28,  1           // InterfaceMethod java/util/Set.stream:()Ljava/util/stream/Stream;
      14: aload_1
      15: invokedynamic #79,  0             // InvokeDynamic #1:test:(Ljava/util/function/Predicate;)Ljava/util/function/Predicate;
      20: invokeinterface #83,  2           // InterfaceMethod java/util/stream/Stream.filter:(Ljava/util/function/Predicate;)Ljava/util/stream/Stream;
      25: invokedynamic #86,  0             // InvokeDynamic #2:apply:()Ljava/util/function/Function;
      30: invokeinterface #38,  2           // InterfaceMethod java/util/stream/Stream.map:(Ljava/util/function/Function;)Ljava/util/stream/Stream;
      35: areturn

  public io.fluxcapacitor.common.search.Document filterPaths(java.util.function.Predicate<io.fluxcapacitor.common.search.Document$Path>);
    Code:
       0: aload_0
       1: getfield      #72                 // Field entries:Ljava/util/Map;
       4: invokeinterface #76,  1           // InterfaceMethod java/util/Map.entrySet:()Ljava/util/Set;
       9: invokeinterface #28,  1           // InterfaceMethod java/util/Set.stream:()Ljava/util/stream/Stream;
      14: aload_1
      15: invokedynamic #87,  0             // InvokeDynamic #3:apply:(Ljava/util/function/Predicate;)Ljava/util/function/Function;
      20: invokeinterface #90,  2           // InterfaceMethod java/util/stream/Stream.flatMap:(Ljava/util/function/Function;)Ljava/util/stream/Stream;
      25: invokedynamic #86,  0             // InvokeDynamic #2:apply:()Ljava/util/function/Function;
      30: invokedynamic #93,  0             // InvokeDynamic #4:apply:()Ljava/util/function/Function;
      35: invokestatic  #94                 // Method java/util/stream/Collectors.toMap:(Ljava/util/function/Function;Ljava/util/function/Function;)Ljava/util/stream/Collector;
      38: invokeinterface #54,  2           // InterfaceMethod java/util/stream/Stream.collect:(Ljava/util/stream/Collector;)Ljava/lang/Object;
      43: checkcast     #23                 // class java/util/Map
      46: astore_2
      47: aload_0
      48: invokevirtual #98                 // Method toBuilder:()Lio/fluxcapacitor/common/search/Document$DocumentBuilder;
      51: aload_2
      52: invokevirtual #102                // Method io/fluxcapacitor/common/search/Document$DocumentBuilder.entries:(Ljava/util/Map;)Lio/fluxcapacitor/common/search/Document$DocumentBuilder;
      55: invokevirtual #107                // Method io/fluxcapacitor/common/search/Document$DocumentBuilder.build:()Lio/fluxcapacitor/common/search/Document;
      58: areturn

  public java.time.Instant getEnd();
    Code:
       0: aload_0
       1: getfield      #111                // Field end:Ljava/time/Instant;
       4: ifnull        28
       7: aload_0
       8: getfield      #115                // Field timestamp:Ljava/time/Instant;
      11: ifnull        28
      14: aload_0
      15: getfield      #111                // Field end:Ljava/time/Instant;
      18: aload_0
      19: getfield      #115                // Field timestamp:Ljava/time/Instant;
      22: invokevirtual #118                // Method java/time/Instant.isAfter:(Ljava/time/Instant;)Z
      25: ifeq          35
      28: aload_0
      29: getfield      #111                // Field end:Ljava/time/Instant;
      32: goto          39
      35: aload_0
      36: getfield      #115                // Field timestamp:Ljava/time/Instant;
      39: areturn

  public static java.util.Comparator<io.fluxcapacitor.common.search.Document> createComparator(io.fluxcapacitor.common.api.search.SearchDocuments);
    Code:
       0: aload_0
       1: invokevirtual #124                // Method io/fluxcapacitor/common/api/search/SearchDocuments.getSorting:()Ljava/util/List;
       4: invokeinterface #130,  1          // InterfaceMethod java/util/List.stream:()Ljava/util/stream/Stream;
       9: invokedynamic #133,  0            // InvokeDynamic #5:apply:()Ljava/util/function/Function;
      14: invokeinterface #38,  2           // InterfaceMethod java/util/stream/Stream.map:(Ljava/util/function/Function;)Ljava/util/stream/Stream;
      19: invokedynamic #134,  0            // InvokeDynamic #6:apply:()Ljava/util/function/BinaryOperator;
      24: invokeinterface #137,  2          // InterfaceMethod java/util/stream/Stream.reduce:(Ljava/util/function/BinaryOperator;)Ljava/util/Optional;
      29: invokedynamic #141,  0            // InvokeDynamic #7:get:()Ljava/util/function/Supplier;
      34: invokevirtual #145                // Method java/util/Optional.orElseGet:(Ljava/util/function/Supplier;)Ljava/lang/Object;
      37: checkcast     #151                // class java/util/Comparator
      40: areturn

  public static io.fluxcapacitor.common.search.Document$DocumentBuilder builder();
    Code:
       0: new           #103                // class io/fluxcapacitor/common/search/Document$DocumentBuilder
       3: dup
       4: invokespecial #153                // Method io/fluxcapacitor/common/search/Document$DocumentBuilder."<init>":()V
       7: areturn

  public io.fluxcapacitor.common.search.Document$DocumentBuilder toBuilder();
    Code:
       0: new           #103                // class io/fluxcapacitor/common/search/Document$DocumentBuilder
       3: dup
       4: invokespecial #153                // Method io/fluxcapacitor/common/search/Document$DocumentBuilder."<init>":()V
       7: aload_0
       8: getfield      #9                  // Field id:Ljava/lang/String;
      11: invokevirtual #157                // Method io/fluxcapacitor/common/search/Document$DocumentBuilder.id:(Ljava/lang/String;)Lio/fluxcapacitor/common/search/Document$DocumentBuilder;
      14: aload_0
      15: getfield      #3                  // Field type:Ljava/lang/String;
      18: invokevirtual #160                // Method io/fluxcapacitor/common/search/Document$DocumentBuilder.type:(Ljava/lang/String;)Lio/fluxcapacitor/common/search/Document$DocumentBuilder;
      21: aload_0
      22: getfield      #162                // Field revision:I
      25: invokevirtual #166                // Method io/fluxcapacitor/common/search/Document$DocumentBuilder.revision:(I)Lio/fluxcapacitor/common/search/Document$DocumentBuilder;
      28: aload_0
      29: getfield      #169                // Field collection:Ljava/lang/String;
      32: invokevirtual #172                // Method io/fluxcapacitor/common/search/Document$DocumentBuilder.collection:(Ljava/lang/String;)Lio/fluxcapacitor/common/search/Document$DocumentBuilder;
      35: aload_0
      36: getfield      #115                // Field timestamp:Ljava/time/Instant;
      39: invokevirtual #174                // Method io/fluxcapacitor/common/search/Document$DocumentBuilder.timestamp:(Ljava/time/Instant;)Lio/fluxcapacitor/common/search/Document$DocumentBuilder;
      42: aload_0
      43: getfield      #111                // Field end:Ljava/time/Instant;
      46: invokevirtual #177                // Method io/fluxcapacitor/common/search/Document$DocumentBuilder.end:(Ljava/time/Instant;)Lio/fluxcapacitor/common/search/Document$DocumentBuilder;
      49: aload_0
      50: getfield      #72                 // Field entries:Ljava/util/Map;
      53: invokevirtual #102                // Method io/fluxcapacitor/common/search/Document$DocumentBuilder.entries:(Ljava/util/Map;)Lio/fluxcapacitor/common/search/Document$DocumentBuilder;
      56: areturn

  public java.lang.String getId();
    Code:
       0: aload_0
       1: getfield      #9                  // Field id:Ljava/lang/String;
       4: areturn

  public java.lang.String getType();
    Code:
       0: aload_0
       1: getfield      #3                  // Field type:Ljava/lang/String;
       4: areturn

  public int getRevision();
    Code:
       0: aload_0
       1: getfield      #162                // Field revision:I
       4: ireturn

  public java.lang.String getCollection();
    Code:
       0: aload_0
       1: getfield      #169                // Field collection:Ljava/lang/String;
       4: areturn

  public java.time.Instant getTimestamp();
    Code:
       0: aload_0
       1: getfield      #115                // Field timestamp:Ljava/time/Instant;
       4: areturn

  public java.util.Map<io.fluxcapacitor.common.search.Document$Entry, java.util.List<io.fluxcapacitor.common.search.Document$Path>> getEntries();
    Code:
       0: aload_0
       1: getfield      #72                 // Field entries:Ljava/util/Map;
       4: areturn

  public boolean equals(java.lang.Object);
    Code:
       0: aload_1
       1: aload_0
       2: if_acmpne     7
       5: iconst_1
       6: ireturn
       7: aload_1
       8: instanceof    #4                  // class io/fluxcapacitor/common/search/Document
      11: ifne          16
      14: iconst_0
      15: ireturn
      16: aload_1
      17: checkcast     #4                  // class io/fluxcapacitor/common/search/Document
      20: astore_2
      21: aload_0
      22: invokevirtual #179                // Method getRevision:()I
      25: aload_2
      26: invokevirtual #179                // Method getRevision:()I
      29: if_icmpeq     34
      32: iconst_0
      33: ireturn
      34: aload_0
      35: invokevirtual #183                // Method getId:()Ljava/lang/String;
      38: astore_3
      39: aload_2
      40: invokevirtual #183                // Method getId:()Ljava/lang/String;
      43: astore        4
      45: aload_3
      46: ifnonnull     57
      49: aload         4
      51: ifnull        68
      54: goto          66
      57: aload_3
      58: aload         4
      60: invokevirtual #187                // Method java/lang/Object.equals:(Ljava/lang/Object;)Z
      63: ifne          68
      66: iconst_0
      67: ireturn
      68: aload_0
      69: invokevirtual #193                // Method getType:()Ljava/lang/String;
      72: astore        5
      74: aload_2
      75: invokevirtual #193                // Method getType:()Ljava/lang/String;
      78: astore        6
      80: aload         5
      82: ifnonnull     93
      85: aload         6
      87: ifnull        105
      90: goto          103
      93: aload         5
      95: aload         6
      97: invokevirtual #187                // Method java/lang/Object.equals:(Ljava/lang/Object;)Z
     100: ifne          105
     103: iconst_0
     104: ireturn
     105: aload_0
     106: invokevirtual #196                // Method getCollection:()Ljava/lang/String;
     109: astore        7
     111: aload_2
     112: invokevirtual #196                // Method getCollection:()Ljava/lang/String;
     115: astore        8
     117: aload         7
     119: ifnonnull     130
     122: aload         8
     124: ifnull        142
     127: goto          140
     130: aload         7
     132: aload         8
     134: invokevirtual #187                // Method java/lang/Object.equals:(Ljava/lang/Object;)Z
     137: ifne          142
     140: iconst_0
     141: ireturn
     142: aload_0
     143: invokevirtual #199                // Method getTimestamp:()Ljava/time/Instant;
     146: astore        9
     148: aload_2
     149: invokevirtual #199                // Method getTimestamp:()Ljava/time/Instant;
     152: astore        10
     154: aload         9
     156: ifnonnull     167
     159: aload         10
     161: ifnull        179
     164: goto          177
     167: aload         9
     169: aload         10
     171: invokevirtual #187                // Method java/lang/Object.equals:(Ljava/lang/Object;)Z
     174: ifne          179
     177: iconst_0
     178: ireturn
     179: aload_0
     180: invokevirtual #203                // Method getEnd:()Ljava/time/Instant;
     183: astore        11
     185: aload_2
     186: invokevirtual #203                // Method getEnd:()Ljava/time/Instant;
     189: astore        12
     191: aload         11
     193: ifnonnull     204
     196: aload         12
     198: ifnull        216
     201: goto          214
     204: aload         11
     206: aload         12
     208: invokevirtual #187                // Method java/lang/Object.equals:(Ljava/lang/Object;)Z
     211: ifne          216
     214: iconst_0
     215: ireturn
     216: aload_0
     217: invokevirtual #18                 // Method getEntries:()Ljava/util/Map;
     220: astore        13
     222: aload_2
     223: invokevirtual #18                 // Method getEntries:()Ljava/util/Map;
     226: astore        14
     228: aload         13
     230: ifnonnull     241
     233: aload         14
     235: ifnull        253
     238: goto          251
     241: aload         13
     243: aload         14
     245: invokevirtual #187                // Method java/lang/Object.equals:(Ljava/lang/Object;)Z
     248: ifne          253
     251: iconst_0
     252: ireturn
     253: iconst_1
     254: ireturn

  public int hashCode();
    Code:
       0: bipush        59
       2: istore_1
       3: iconst_1
       4: istore_2
       5: iload_2
       6: bipush        59
       8: imul
       9: aload_0
      10: invokevirtual #179                // Method getRevision:()I
      13: iadd
      14: istore_2
      15: aload_0
      16: invokevirtual #183                // Method getId:()Ljava/lang/String;
      19: astore_3
      20: iload_2
      21: bipush        59
      23: imul
      24: aload_3
      25: ifnonnull     33
      28: bipush        43
      30: goto          37
      33: aload_3
      34: invokevirtual #206                // Method java/lang/Object.hashCode:()I
      37: iadd
      38: istore_2
      39: aload_0
      40: invokevirtual #193                // Method getType:()Ljava/lang/String;
      43: astore        4
      45: iload_2
      46: bipush        59
      48: imul
      49: aload         4
      51: ifnonnull     59
      54: bipush        43
      56: goto          64
      59: aload         4
      61: invokevirtual #206                // Method java/lang/Object.hashCode:()I
      64: iadd
      65: istore_2
      66: aload_0
      67: invokevirtual #196                // Method getCollection:()Ljava/lang/String;
      70: astore        5
      72: iload_2
      73: bipush        59
      75: imul
      76: aload         5
      78: ifnonnull     86
      81: bipush        43
      83: goto          91
      86: aload         5
      88: invokevirtual #206                // Method java/lang/Object.hashCode:()I
      91: iadd
      92: istore_2
      93: aload_0
      94: invokevirtual #199                // Method getTimestamp:()Ljava/time/Instant;
      97: astore        6
      99: iload_2
     100: bipush        59
     102: imul
     103: aload         6
     105: ifnonnull     113
     108: bipush        43
     110: goto          118
     113: aload         6
     115: invokevirtual #206                // Method java/lang/Object.hashCode:()I
     118: iadd
     119: istore_2
     120: aload_0
     121: invokevirtual #203                // Method getEnd:()Ljava/time/Instant;
     124: astore        7
     126: iload_2
     127: bipush        59
     129: imul
     130: aload         7
     132: ifnonnull     140
     135: bipush        43
     137: goto          145
     140: aload         7
     142: invokevirtual #206                // Method java/lang/Object.hashCode:()I
     145: iadd
     146: istore_2
     147: aload_0
     148: invokevirtual #18                 // Method getEntries:()Ljava/util/Map;
     151: astore        8
     153: iload_2
     154: bipush        59
     156: imul
     157: aload         8
     159: ifnonnull     167
     162: bipush        43
     164: goto          172
     167: aload         8
     169: invokevirtual #206                // Method java/lang/Object.hashCode:()I
     172: iadd
     173: istore_2
     174: iload_2
     175: ireturn

  public java.lang.String toString();
    Code:
       0: aload_0
       1: invokevirtual #183                // Method getId:()Ljava/lang/String;
       4: aload_0
       5: invokevirtual #193                // Method getType:()Ljava/lang/String;
       8: aload_0
       9: invokevirtual #179                // Method getRevision:()I
      12: aload_0
      13: invokevirtual #196                // Method getCollection:()Ljava/lang/String;
      16: aload_0
      17: invokevirtual #199                // Method getTimestamp:()Ljava/time/Instant;
      20: aload_0
      21: invokevirtual #203                // Method getEnd:()Ljava/time/Instant;
      24: aload_0
      25: invokevirtual #18                 // Method getEntries:()Ljava/util/Map;
      28: invokedynamic #209,  0            // InvokeDynamic #8:makeConcatWithConstants:(Ljava/lang/String;Ljava/lang/String;ILjava/lang/String;Ljava/time/Instant;Ljava/time/Instant;Ljava/util/Map;)Ljava/lang/String;
      33: areturn

  public io.fluxcapacitor.common.search.Document(java.lang.String, java.lang.String, int, java.lang.String, java.time.Instant, java.time.Instant, java.util.Map<io.fluxcapacitor.common.search.Document$Entry, java.util.List<io.fluxcapacitor.common.search.Document$Path>>);
    Code:
       0: aload_0
       1: invokespecial #213                // Method java/lang/Object."<init>":()V
       4: aload_0
       5: new           #214                // class java/util/concurrent/atomic/AtomicReference
       8: dup
       9: invokespecial #216                // Method java/util/concurrent/atomic/AtomicReference."<init>":()V
      12: putfield      #217                // Field summarize:Ljava/util/concurrent/atomic/AtomicReference;
      15: aload_1
      16: ifnonnull     29
      19: new           #221                // class java/lang/NullPointerException
      22: dup
      23: ldc           #223                // String id is marked non-null but is null
      25: invokespecial #225                // Method java/lang/NullPointerException."<init>":(Ljava/lang/String;)V
      28: athrow
      29: aload_0
      30: aload_1
      31: putfield      #9                  // Field id:Ljava/lang/String;
      34: aload_0
      35: aload_2
      36: putfield      #3                  // Field type:Ljava/lang/String;
      39: aload_0
      40: iload_3
      41: putfield      #162                // Field revision:I
      44: aload_0
      45: aload         4
      47: putfield      #169                // Field collection:Ljava/lang/String;
      50: aload_0
      51: aload         5
      53: putfield      #115                // Field timestamp:Ljava/time/Instant;
      56: aload_0
      57: aload         6
      59: putfield      #111                // Field end:Ljava/time/Instant;
      62: aload_0
      63: aload         7
      65: putfield      #72                 // Field entries:Ljava/util/Map;
      68: return

  public java.lang.String summarize();
    Code:
       0: aload_0
       1: getfield      #217                // Field summarize:Ljava/util/concurrent/atomic/AtomicReference;
       4: invokevirtual #228                // Method java/util/concurrent/atomic/AtomicReference.get:()Ljava/lang/Object;
       7: astore_1
       8: aload_1
       9: ifnonnull     69
      12: aload_0
      13: getfield      #217                // Field summarize:Ljava/util/concurrent/atomic/AtomicReference;
      16: dup
      17: astore_2
      18: monitorenter
      19: aload_0
      20: getfield      #217                // Field summarize:Ljava/util/concurrent/atomic/AtomicReference;
      23: invokevirtual #228                // Method java/util/concurrent/atomic/AtomicReference.get:()Ljava/lang/Object;
      26: astore_1
      27: aload_1
      28: ifnonnull     57
      31: aload_0
      32: invokevirtual #231                // Method doSummarize:()Ljava/lang/String;
      35: astore_3
      36: aload_3
      37: ifnonnull     47
      40: aload_0
      41: getfield      #217                // Field summarize:Ljava/util/concurrent/atomic/AtomicReference;
      44: goto          48
      47: aload_3
      48: astore_1
      49: aload_0
      50: getfield      #217                // Field summarize:Ljava/util/concurrent/atomic/AtomicReference;
      53: aload_1
      54: invokevirtual #234                // Method java/util/concurrent/atomic/AtomicReference.set:(Ljava/lang/Object;)V
      57: aload_2
      58: monitorexit
      59: goto          69
      62: astore        4
      64: aload_2
      65: monitorexit
      66: aload         4
      68: athrow
      69: aload_1
      70: aload_0
      71: getfield      #217                // Field summarize:Ljava/util/concurrent/atomic/AtomicReference;
      74: if_acmpne     81
      77: aconst_null
      78: goto          82
      81: aload_1
      82: checkcast     #1                  // class java/lang/String
      85: areturn
    Exception table:
       from    to  target type
          19    59    62   any
          62    66    62   any

  private static java.util.Comparator lambda$createComparator$5();
    Code:
       0: invokedynamic #238,  0            // InvokeDynamic #9:apply:()Ljava/util/function/Function;
       5: invokestatic  #239                // InterfaceMethod java/util/Comparator.naturalOrder:()Ljava/util/Comparator;
       8: invokestatic  #243                // InterfaceMethod java/util/Comparator.nullsLast:(Ljava/util/Comparator;)Ljava/util/Comparator;
      11: invokestatic  #247                // InterfaceMethod java/util/Comparator.comparing:(Ljava/util/function/Function;Ljava/util/Comparator;)Ljava/util/Comparator;
      14: invokeinterface #251,  1          // InterfaceMethod java/util/Comparator.reversed:()Ljava/util/Comparator;
      19: areturn

  private static java.util.Comparator lambda$createComparator$4(java.lang.String);
    Code:
       0: aload_0
       1: astore_1
       2: iconst_m1
       3: istore_2
       4: aload_1
       5: invokevirtual #254                // Method java/lang/String.hashCode:()I
       8: lookupswitch  { // 4
            -198046839: 52
                100571: 96
               1441166: 81
              55126294: 66
               default: 108
          }
      52: aload_1
      53: ldc           #255                // String -timestamp
      55: invokevirtual #257                // Method java/lang/String.equals:(Ljava/lang/Object;)Z
      58: ifeq          108
      61: iconst_0
      62: istore_2
      63: goto          108
      66: aload_1
      67: ldc_w         #258                // String timestamp
      70: invokevirtual #257                // Method java/lang/String.equals:(Ljava/lang/Object;)Z
      73: ifeq          108
      76: iconst_1
      77: istore_2
      78: goto          108
      81: aload_1
      82: ldc_w         #259                // String -end
      85: invokevirtual #257                // Method java/lang/String.equals:(Ljava/lang/Object;)Z
      88: ifeq          108
      91: iconst_2
      92: istore_2
      93: goto          108
      96: aload_1
      97: ldc_w         #261                // String end
     100: invokevirtual #257                // Method java/lang/String.equals:(Ljava/lang/Object;)Z
     103: ifeq          108
     106: iconst_3
     107: istore_2
     108: iload_2
     109: tableswitch   { // 0 to 3
                     0: 140
                     1: 160
                     2: 175
                     3: 195
               default: 210
          }
     140: invokedynamic #238,  0            // InvokeDynamic #9:apply:()Ljava/util/function/Function;
     145: invokestatic  #239                // InterfaceMethod java/util/Comparator.naturalOrder:()Ljava/util/Comparator;
     148: invokestatic  #262                // InterfaceMethod java/util/Comparator.nullsFirst:(Ljava/util/Comparator;)Ljava/util/Comparator;
     151: invokestatic  #247                // InterfaceMethod java/util/Comparator.comparing:(Ljava/util/function/Function;Ljava/util/Comparator;)Ljava/util/Comparator;
     154: invokeinterface #251,  1          // InterfaceMethod java/util/Comparator.reversed:()Ljava/util/Comparator;
     159: areturn
     160: invokedynamic #238,  0            // InvokeDynamic #9:apply:()Ljava/util/function/Function;
     165: invokestatic  #239                // InterfaceMethod java/util/Comparator.naturalOrder:()Ljava/util/Comparator;
     168: invokestatic  #262                // InterfaceMethod java/util/Comparator.nullsFirst:(Ljava/util/Comparator;)Ljava/util/Comparator;
     171: invokestatic  #247                // InterfaceMethod java/util/Comparator.comparing:(Ljava/util/function/Function;Ljava/util/Comparator;)Ljava/util/Comparator;
     174: areturn
     175: invokedynamic #265,  0            // InvokeDynamic #10:apply:()Ljava/util/function/Function;
     180: invokestatic  #239                // InterfaceMethod java/util/Comparator.naturalOrder:()Ljava/util/Comparator;
     183: invokestatic  #243                // InterfaceMethod java/util/Comparator.nullsLast:(Ljava/util/Comparator;)Ljava/util/Comparator;
     186: invokestatic  #247                // InterfaceMethod java/util/Comparator.comparing:(Ljava/util/function/Function;Ljava/util/Comparator;)Ljava/util/Comparator;
     189: invokeinterface #251,  1          // InterfaceMethod java/util/Comparator.reversed:()Ljava/util/Comparator;
     194: areturn
     195: invokedynamic #265,  0            // InvokeDynamic #10:apply:()Ljava/util/function/Function;
     200: invokestatic  #239                // InterfaceMethod java/util/Comparator.naturalOrder:()Ljava/util/Comparator;
     203: invokestatic  #243                // InterfaceMethod java/util/Comparator.nullsLast:(Ljava/util/Comparator;)Ljava/util/Comparator;
     206: invokestatic  #247                // InterfaceMethod java/util/Comparator.comparing:(Ljava/util/function/Function;Ljava/util/Comparator;)Ljava/util/Comparator;
     209: areturn
     210: aload_0
     211: ldc_w         #266                // String -
     214: invokevirtual #268                // Method java/lang/String.startsWith:(Ljava/lang/String;)Z
     217: istore_3
     218: iload_3
     219: ifeq          230
     222: aload_0
     223: iconst_1
     224: invokevirtual #272                // Method java/lang/String.substring:(I)Ljava/lang/String;
     227: goto          231
     230: aload_0
     231: astore        4
     233: aload         4
     235: invokestatic  #58                 // Method io/fluxcapacitor/common/search/Document$Path.pathPredicate:(Ljava/lang/String;)Ljava/util/function/Predicate;
     238: astore        5
     240: aload         5
     242: iload_3
     243: invokedynamic #276,  0            // InvokeDynamic #11:apply:(Ljava/util/function/Predicate;Z)Ljava/util/function/Function;
     248: invokestatic  #239                // InterfaceMethod java/util/Comparator.naturalOrder:()Ljava/util/Comparator;
     251: invokestatic  #243                // InterfaceMethod java/util/Comparator.nullsLast:(Ljava/util/Comparator;)Ljava/util/Comparator;
     254: invokestatic  #247                // InterfaceMethod java/util/Comparator.comparing:(Ljava/util/function/Function;Ljava/util/Comparator;)Ljava/util/Comparator;
     257: invokestatic  #243                // InterfaceMethod java/util/Comparator.nullsLast:(Ljava/util/Comparator;)Ljava/util/Comparator;
     260: astore        6
     262: iload_3
     263: ifeq          276
     266: aload         6
     268: invokeinterface #251,  1          // InterfaceMethod java/util/Comparator.reversed:()Ljava/util/Comparator;
     273: goto          278
     276: aload         6
     278: areturn

  private static io.fluxcapacitor.common.search.Document$Entry lambda$createComparator$3(java.util.function.Predicate, boolean, io.fluxcapacitor.common.search.Document);
    Code:
       0: aload_2
       1: aload_0
       2: invokevirtual #64                 // Method getMatchingEntries:(Ljava/util/function/Predicate;)Ljava/util/stream/Stream;
       5: astore_3
       6: iload_1
       7: ifeq          22
      10: aload_3
      11: invokestatic  #239                // InterfaceMethod java/util/Comparator.naturalOrder:()Ljava/util/Comparator;
      14: invokeinterface #279,  2          // InterfaceMethod java/util/stream/Stream.max:(Ljava/util/Comparator;)Ljava/util/Optional;
      19: goto          31
      22: aload_3
      23: invokestatic  #239                // InterfaceMethod java/util/Comparator.naturalOrder:()Ljava/util/Comparator;
      26: invokeinterface #283,  2          // InterfaceMethod java/util/stream/Stream.min:(Ljava/util/Comparator;)Ljava/util/Optional;
      31: aconst_null
      32: invokevirtual #286                // Method java/util/Optional.orElse:(Ljava/lang/Object;)Ljava/lang/Object;
      35: checkcast     #290                // class io/fluxcapacitor/common/search/Document$Entry
      38: areturn

  private static java.util.stream.Stream lambda$filterPaths$2(java.util.function.Predicate, java.util.Map$Entry);
    Code:
       0: aload_1
       1: invokeinterface #292,  1          // InterfaceMethod java/util/Map$Entry.getValue:()Ljava/lang/Object;
       6: checkcast     #131                // class java/util/List
       9: invokeinterface #130,  1          // InterfaceMethod java/util/List.stream:()Ljava/util/stream/Stream;
      14: aload_0
      15: invokeinterface #83,  2           // InterfaceMethod java/util/stream/Stream.filter:(Ljava/util/function/Predicate;)Ljava/util/stream/Stream;
      20: invokestatic  #297                // Method java/util/stream/Collectors.toList:()Ljava/util/stream/Collector;
      23: invokeinterface #54,  2           // InterfaceMethod java/util/stream/Stream.collect:(Ljava/util/stream/Collector;)Ljava/lang/Object;
      28: checkcast     #131                // class java/util/List
      31: astore_2
      32: aload_2
      33: invokeinterface #301,  1          // InterfaceMethod java/util/List.isEmpty:()Z
      38: ifeq          45
      41: invokestatic  #305                // InterfaceMethod java/util/stream/Stream.empty:()Ljava/util/stream/Stream;
      44: areturn
      45: aload_1
      46: invokeinterface #292,  1          // InterfaceMethod java/util/Map$Entry.getValue:()Ljava/lang/Object;
      51: checkcast     #131                // class java/util/List
      54: invokeinterface #308,  1          // InterfaceMethod java/util/List.size:()I
      59: aload_2
      60: invokeinterface #308,  1          // InterfaceMethod java/util/List.size:()I
      65: if_icmpne     72
      68: aload_1
      69: goto          89
      72: new           #311                // class java/util/AbstractMap$SimpleEntry
      75: dup
      76: aload_1
      77: invokeinterface #313,  1          // InterfaceMethod java/util/Map$Entry.getKey:()Ljava/lang/Object;
      82: checkcast     #290                // class io/fluxcapacitor/common/search/Document$Entry
      85: aload_2
      86: invokespecial #316                // Method java/util/AbstractMap$SimpleEntry."<init>":(Ljava/lang/Object;Ljava/lang/Object;)V
      89: invokestatic  #319                // InterfaceMethod java/util/stream/Stream.of:(Ljava/lang/Object;)Ljava/util/stream/Stream;
      92: areturn

  private static boolean lambda$getMatchingEntries$1(java.util.function.Predicate, java.util.Map$Entry);
    Code:
       0: aload_1
       1: invokeinterface #292,  1          // InterfaceMethod java/util/Map$Entry.getValue:()Ljava/lang/Object;
       6: checkcast     #131                // class java/util/List
       9: invokeinterface #130,  1          // InterfaceMethod java/util/List.stream:()Ljava/util/stream/Stream;
      14: aload_0
      15: invokeinterface #322,  2          // InterfaceMethod java/util/stream/Stream.anyMatch:(Ljava/util/function/Predicate;)Z
      20: ireturn

  private static java.lang.Object lambda$static$0(io.fluxcapacitor.common.search.Document);
    Code:
       0: ldc_w         #326                // String %s_%s
       3: iconst_2
       4: anewarray     #188                // class java/lang/Object
       7: dup
       8: iconst_0
       9: aload_0
      10: invokevirtual #196                // Method getCollection:()Ljava/lang/String;
      13: aastore
      14: dup
      15: iconst_1
      16: aload_0
      17: invokevirtual #183                // Method getId:()Ljava/lang/String;
      20: aastore
      21: invokestatic  #328                // Method java/lang/String.format:(Ljava/lang/String;[Ljava/lang/Object;)Ljava/lang/String;
      24: areturn

  static {};
    Code:
       0: invokedynamic #332,  0            // InvokeDynamic #12:apply:()Ljava/util/function/Function;
       5: putstatic     #333                // Field identityFunction:Ljava/util/function/Function;
       8: return
}
