Compiled from "Marshaller.java"
class org.wildfly.swarm.config.runtime.invocation.Marshaller$Subresource {
  public final java.lang.Class<?> type;

  public final java.lang.reflect.Method method;

  public org.wildfly.swarm.config.runtime.invocation.Marshaller$Subresource(java.lang.Class<?>, java.lang.reflect.Method);
    Code:
       0: aload_0
       1: invokespecial #1                  // Method java/lang/Object."<init>":()V
       4: aload_0
       5: aload_1
       6: putfield      #2                  // Field type:Ljava/lang/Class;
       9: aload_0
      10: aload_2
      11: putfield      #3                  // Field method:Ljava/lang/reflect/Method;
      14: return

  public java.lang.Object invoke(java.lang.Object) throws java.lang.reflect.InvocationTargetException, java.lang.IllegalAccessException;
    Code:
       0: aload_0
       1: getfield      #3                  // Field method:Ljava/lang/reflect/Method;
       4: aload_1
       5: iconst_0
       6: anewarray     #4                  // class java/lang/Object
       9: invokevirtual #5                  // Method java/lang/reflect/Method.invoke:(Ljava/lang/Object;[Ljava/lang/Object;)Ljava/lang/Object;
      12: areturn
}
