Compiled from "XMPPTransportFactory.java"
public class de.ovgu.dke.glue.xmpp.transport.XMPPTransportFactory implements de.ovgu.dke.glue.api.transport.TransportFactory {
  public static final java.lang.String DEFAULT_REGISTRY_KEY;

  private de.ovgu.dke.glue.xmpp.transport.XMPPClient client;

  public de.ovgu.dke.glue.xmpp.transport.XMPPTransportFactory();
    Code:
       0: aload_0
       1: invokespecial #1                  // Method java/lang/Object."<init>":()V
       4: return

  public void init(java.util.Properties) throws de.ovgu.dke.glue.api.transport.TransportException;
    Code:
       0: new           #2                  // class de/ovgu/dke/glue/xmpp/config/XMPPPropertiesConfigurationLoader
       3: dup
       4: invokespecial #3                  // Method de/ovgu/dke/glue/xmpp/config/XMPPPropertiesConfigurationLoader."<init>":()V
       7: astore_2
       8: aload_0
       9: new           #4                  // class de/ovgu/dke/glue/xmpp/transport/XMPPClient
      12: dup
      13: aload_2
      14: aload_1
      15: invokeinterface #5,  2            // InterfaceMethod de/ovgu/dke/glue/xmpp/config/XMPPConfigurationLoader.loadConfiguration:(Ljava/util/Properties;)Lde/ovgu/dke/glue/xmpp/config/XMPPConfiguration;
      20: invokespecial #6                  // Method de/ovgu/dke/glue/xmpp/transport/XMPPClient."<init>":(Lde/ovgu/dke/glue/xmpp/config/XMPPConfiguration;)V
      23: putfield      #7                  // Field client:Lde/ovgu/dke/glue/xmpp/transport/XMPPClient;
      26: aload_0
      27: getfield      #7                  // Field client:Lde/ovgu/dke/glue/xmpp/transport/XMPPClient;
      30: invokevirtual #8                  // Method de/ovgu/dke/glue/xmpp/transport/XMPPClient.startup:()V
      33: goto          100
      36: astore_2
      37: new           #10                 // class de/ovgu/dke/glue/api/transport/TransportException
      40: dup
      41: new           #11                 // class java/lang/StringBuilder
      44: dup
      45: invokespecial #12                 // Method java/lang/StringBuilder."<init>":()V
      48: ldc           #13                 // String Error loading the configuration:
      50: invokevirtual #14                 // Method java/lang/StringBuilder.append:(Ljava/lang/String;)Ljava/lang/StringBuilder;
      53: aload_2
      54: invokevirtual #15                 // Method org/apache/commons/configuration/ConfigurationException.getMessage:()Ljava/lang/String;
      57: invokevirtual #14                 // Method java/lang/StringBuilder.append:(Ljava/lang/String;)Ljava/lang/StringBuilder;
      60: invokevirtual #16                 // Method java/lang/StringBuilder.toString:()Ljava/lang/String;
      63: aload_2
      64: invokespecial #17                 // Method de/ovgu/dke/glue/api/transport/TransportException."<init>":(Ljava/lang/String;Ljava/lang/Throwable;)V
      67: athrow
      68: astore_2
      69: new           #10                 // class de/ovgu/dke/glue/api/transport/TransportException
      72: dup
      73: new           #11                 // class java/lang/StringBuilder
      76: dup
      77: invokespecial #12                 // Method java/lang/StringBuilder."<init>":()V
      80: ldc           #18                 // String Error during client initialization:
      82: invokevirtual #14                 // Method java/lang/StringBuilder.append:(Ljava/lang/String;)Ljava/lang/StringBuilder;
      85: aload_2
      86: invokevirtual #19                 // Method de/ovgu/dke/glue/api/transport/TransportException.getMessage:()Ljava/lang/String;
      89: invokevirtual #14                 // Method java/lang/StringBuilder.append:(Ljava/lang/String;)Ljava/lang/StringBuilder;
      92: invokevirtual #16                 // Method java/lang/StringBuilder.toString:()Ljava/lang/String;
      95: aload_2
      96: invokespecial #17                 // Method de/ovgu/dke/glue/api/transport/TransportException."<init>":(Ljava/lang/String;Ljava/lang/Throwable;)V
      99: athrow
     100: return
    Exception table:
       from    to  target type
           0    33    36   Class org/apache/commons/configuration/ConfigurationException
           0    33    68   Class de/ovgu/dke/glue/api/transport/TransportException

  public de.ovgu.dke.glue.api.transport.Transport createTransport(java.net.URI) throws de.ovgu.dke.glue.api.transport.TransportException;
    Code:
       0: aload_0
       1: getfield      #7                  // Field client:Lde/ovgu/dke/glue/xmpp/transport/XMPPClient;
       4: ifnonnull     11
       7: aconst_null
       8: goto          19
      11: aload_0
      12: getfield      #7                  // Field client:Lde/ovgu/dke/glue/xmpp/transport/XMPPClient;
      15: aload_1
      16: invokevirtual #20                 // Method de/ovgu/dke/glue/xmpp/transport/XMPPClient.createTransport:(Ljava/net/URI;)Lde/ovgu/dke/glue/api/transport/Transport;
      19: areturn

  public void dispose();
    Code:
       0: aload_0
       1: getfield      #7                  // Field client:Lde/ovgu/dke/glue/xmpp/transport/XMPPClient;
       4: ifnull        14
       7: aload_0
       8: getfield      #7                  // Field client:Lde/ovgu/dke/glue/xmpp/transport/XMPPClient;
      11: invokevirtual #21                 // Method de/ovgu/dke/glue/xmpp/transport/XMPPClient.teardown:()V
      14: return

  public java.lang.String getDefaultRegistryKey();
    Code:
       0: ldc           #22                 // String xmpp
       2: areturn

  public void addReportListener(de.ovgu.dke.glue.api.reporting.ReportListener);
    Code:
       0: aload_0
       1: getfield      #7                  // Field client:Lde/ovgu/dke/glue/xmpp/transport/XMPPClient;
       4: ifnull        15
       7: aload_0
       8: getfield      #7                  // Field client:Lde/ovgu/dke/glue/xmpp/transport/XMPPClient;
      11: aload_1
      12: invokevirtual #23                 // Method de/ovgu/dke/glue/xmpp/transport/XMPPClient.addReportListener:(Lde/ovgu/dke/glue/api/reporting/ReportListener;)V
      15: return

  public void removeReportListener(de.ovgu.dke.glue.api.reporting.ReportListener);
    Code:
       0: aload_0
       1: getfield      #7                  // Field client:Lde/ovgu/dke/glue/xmpp/transport/XMPPClient;
       4: ifnull        15
       7: aload_0
       8: getfield      #7                  // Field client:Lde/ovgu/dke/glue/xmpp/transport/XMPPClient;
      11: aload_1
      12: invokevirtual #24                 // Method de/ovgu/dke/glue/xmpp/transport/XMPPClient.removeReportListener:(Lde/ovgu/dke/glue/api/reporting/ReportListener;)V
      15: return

  public void addTransportLifecycleListener(de.ovgu.dke.glue.api.transport.TransportLifecycleListener);
    Code:
       0: aload_0
       1: getfield      #7                  // Field client:Lde/ovgu/dke/glue/xmpp/transport/XMPPClient;
       4: ifnull        15
       7: aload_0
       8: getfield      #7                  // Field client:Lde/ovgu/dke/glue/xmpp/transport/XMPPClient;
      11: aload_1
      12: invokevirtual #25                 // Method de/ovgu/dke/glue/xmpp/transport/XMPPClient.addLifecycleListener:(Lde/ovgu/dke/glue/api/transport/TransportLifecycleListener;)V
      15: return

  public void removeTransportLifecycleListener(de.ovgu.dke.glue.api.transport.TransportLifecycleListener);
    Code:
       0: aload_0
       1: getfield      #7                  // Field client:Lde/ovgu/dke/glue/xmpp/transport/XMPPClient;
       4: ifnull        15
       7: aload_0
       8: getfield      #7                  // Field client:Lde/ovgu/dke/glue/xmpp/transport/XMPPClient;
      11: aload_1
      12: invokevirtual #26                 // Method de/ovgu/dke/glue/xmpp/transport/XMPPClient.removeLifecycleListener:(Lde/ovgu/dke/glue/api/transport/TransportLifecycleListener;)V
      15: return
}
