Compiled from "RouteTracker.java"
public final class org.apache.hc.client5.http.RouteTracker implements org.apache.hc.client5.http.RouteInfo,java.lang.Cloneable {
  private final org.apache.hc.core5.http.HttpHost targetHost;

  private final java.net.InetAddress localAddress;

  private boolean connected;

  private org.apache.hc.core5.http.HttpHost[] proxyChain;

  private org.apache.hc.client5.http.RouteInfo$TunnelType tunnelled;

  private org.apache.hc.client5.http.RouteInfo$LayerType layered;

  private boolean secure;

  public org.apache.hc.client5.http.RouteTracker(org.apache.hc.core5.http.HttpHost, java.net.InetAddress);
    Code:
       0: aload_0
       1: invokespecial #1                  // Method java/lang/Object."<init>":()V
       4: aload_1
       5: ldc           #2                  // String Target host
       7: invokestatic  #3                  // Method org/apache/hc/core5/util/Args.notNull:(Ljava/lang/Object;Ljava/lang/String;)Ljava/lang/Object;
      10: pop
      11: aload_0
      12: aload_1
      13: putfield      #4                  // Field targetHost:Lorg/apache/hc/core5/http/HttpHost;
      16: aload_0
      17: aload_2
      18: putfield      #5                  // Field localAddress:Ljava/net/InetAddress;
      21: aload_0
      22: getstatic     #6                  // Field org/apache/hc/client5/http/RouteInfo$TunnelType.PLAIN:Lorg/apache/hc/client5/http/RouteInfo$TunnelType;
      25: putfield      #7                  // Field tunnelled:Lorg/apache/hc/client5/http/RouteInfo$TunnelType;
      28: aload_0
      29: getstatic     #8                  // Field org/apache/hc/client5/http/RouteInfo$LayerType.PLAIN:Lorg/apache/hc/client5/http/RouteInfo$LayerType;
      32: putfield      #9                  // Field layered:Lorg/apache/hc/client5/http/RouteInfo$LayerType;
      35: return

  public void reset();
    Code:
       0: aload_0
       1: iconst_0
       2: putfield      #10                 // Field connected:Z
       5: aload_0
       6: aconst_null
       7: putfield      #11                 // Field proxyChain:[Lorg/apache/hc/core5/http/HttpHost;
      10: aload_0
      11: getstatic     #6                  // Field org/apache/hc/client5/http/RouteInfo$TunnelType.PLAIN:Lorg/apache/hc/client5/http/RouteInfo$TunnelType;
      14: putfield      #7                  // Field tunnelled:Lorg/apache/hc/client5/http/RouteInfo$TunnelType;
      17: aload_0
      18: getstatic     #8                  // Field org/apache/hc/client5/http/RouteInfo$LayerType.PLAIN:Lorg/apache/hc/client5/http/RouteInfo$LayerType;
      21: putfield      #9                  // Field layered:Lorg/apache/hc/client5/http/RouteInfo$LayerType;
      24: aload_0
      25: iconst_0
      26: putfield      #12                 // Field secure:Z
      29: return

  public org.apache.hc.client5.http.RouteTracker(org.apache.hc.client5.http.HttpRoute);
    Code:
       0: aload_0
       1: aload_1
       2: invokevirtual #13                 // Method org/apache/hc/client5/http/HttpRoute.getTargetHost:()Lorg/apache/hc/core5/http/HttpHost;
       5: aload_1
       6: invokevirtual #14                 // Method org/apache/hc/client5/http/HttpRoute.getLocalAddress:()Ljava/net/InetAddress;
       9: invokespecial #15                 // Method "<init>":(Lorg/apache/hc/core5/http/HttpHost;Ljava/net/InetAddress;)V
      12: return

  public void connectTarget(boolean);
    Code:
       0: aload_0
       1: getfield      #10                 // Field connected:Z
       4: ifne          11
       7: iconst_1
       8: goto          12
      11: iconst_0
      12: ldc           #16                 // String Already connected
      14: invokestatic  #17                 // Method org/apache/hc/core5/util/Asserts.check:(ZLjava/lang/String;)V
      17: aload_0
      18: iconst_1
      19: putfield      #10                 // Field connected:Z
      22: aload_0
      23: iload_1
      24: putfield      #12                 // Field secure:Z
      27: return

  public void connectProxy(org.apache.hc.core5.http.HttpHost, boolean);
    Code:
       0: aload_1
       1: ldc           #18                 // String Proxy host
       3: invokestatic  #3                  // Method org/apache/hc/core5/util/Args.notNull:(Ljava/lang/Object;Ljava/lang/String;)Ljava/lang/Object;
       6: pop
       7: aload_0
       8: getfield      #10                 // Field connected:Z
      11: ifne          18
      14: iconst_1
      15: goto          19
      18: iconst_0
      19: ldc           #16                 // String Already connected
      21: invokestatic  #17                 // Method org/apache/hc/core5/util/Asserts.check:(ZLjava/lang/String;)V
      24: aload_0
      25: iconst_1
      26: putfield      #10                 // Field connected:Z
      29: aload_0
      30: iconst_1
      31: anewarray     #19                 // class org/apache/hc/core5/http/HttpHost
      34: dup
      35: iconst_0
      36: aload_1
      37: aastore
      38: putfield      #11                 // Field proxyChain:[Lorg/apache/hc/core5/http/HttpHost;
      41: aload_0
      42: iload_2
      43: putfield      #12                 // Field secure:Z
      46: return

  public void tunnelTarget(boolean);
    Code:
       0: aload_0
       1: getfield      #10                 // Field connected:Z
       4: ldc           #20                 // String No tunnel unless connected
       6: invokestatic  #17                 // Method org/apache/hc/core5/util/Asserts.check:(ZLjava/lang/String;)V
       9: aload_0
      10: getfield      #11                 // Field proxyChain:[Lorg/apache/hc/core5/http/HttpHost;
      13: ldc           #21                 // String No tunnel without proxy
      15: invokestatic  #22                 // Method org/apache/hc/core5/util/Asserts.notNull:(Ljava/lang/Object;Ljava/lang/String;)V
      18: aload_0
      19: getstatic     #23                 // Field org/apache/hc/client5/http/RouteInfo$TunnelType.TUNNELLED:Lorg/apache/hc/client5/http/RouteInfo$TunnelType;
      22: putfield      #7                  // Field tunnelled:Lorg/apache/hc/client5/http/RouteInfo$TunnelType;
      25: aload_0
      26: iload_1
      27: putfield      #12                 // Field secure:Z
      30: return

  public void tunnelProxy(org.apache.hc.core5.http.HttpHost, boolean);
    Code:
       0: aload_1
       1: ldc           #18                 // String Proxy host
       3: invokestatic  #3                  // Method org/apache/hc/core5/util/Args.notNull:(Ljava/lang/Object;Ljava/lang/String;)Ljava/lang/Object;
       6: pop
       7: aload_0
       8: getfield      #10                 // Field connected:Z
      11: ldc           #20                 // String No tunnel unless connected
      13: invokestatic  #17                 // Method org/apache/hc/core5/util/Asserts.check:(ZLjava/lang/String;)V
      16: aload_0
      17: getfield      #11                 // Field proxyChain:[Lorg/apache/hc/core5/http/HttpHost;
      20: ldc           #21                 // String No tunnel without proxy
      22: invokestatic  #22                 // Method org/apache/hc/core5/util/Asserts.notNull:(Ljava/lang/Object;Ljava/lang/String;)V
      25: aload_0
      26: getfield      #11                 // Field proxyChain:[Lorg/apache/hc/core5/http/HttpHost;
      29: arraylength
      30: iconst_1
      31: iadd
      32: anewarray     #19                 // class org/apache/hc/core5/http/HttpHost
      35: astore_3
      36: aload_0
      37: getfield      #11                 // Field proxyChain:[Lorg/apache/hc/core5/http/HttpHost;
      40: iconst_0
      41: aload_3
      42: iconst_0
      43: aload_0
      44: getfield      #11                 // Field proxyChain:[Lorg/apache/hc/core5/http/HttpHost;
      47: arraylength
      48: invokestatic  #24                 // Method java/lang/System.arraycopy:(Ljava/lang/Object;ILjava/lang/Object;II)V
      51: aload_3
      52: aload_3
      53: arraylength
      54: iconst_1
      55: isub
      56: aload_1
      57: aastore
      58: aload_0
      59: aload_3
      60: putfield      #11                 // Field proxyChain:[Lorg/apache/hc/core5/http/HttpHost;
      63: aload_0
      64: iload_2
      65: putfield      #12                 // Field secure:Z
      68: return

  public void layerProtocol(boolean);
    Code:
       0: aload_0
       1: getfield      #10                 // Field connected:Z
       4: ldc           #25                 // String No layered protocol unless connected
       6: invokestatic  #17                 // Method org/apache/hc/core5/util/Asserts.check:(ZLjava/lang/String;)V
       9: aload_0
      10: getstatic     #26                 // Field org/apache/hc/client5/http/RouteInfo$LayerType.LAYERED:Lorg/apache/hc/client5/http/RouteInfo$LayerType;
      13: putfield      #9                  // Field layered:Lorg/apache/hc/client5/http/RouteInfo$LayerType;
      16: aload_0
      17: iload_1
      18: putfield      #12                 // Field secure:Z
      21: return

  public org.apache.hc.core5.http.HttpHost getTargetHost();
    Code:
       0: aload_0
       1: getfield      #4                  // Field targetHost:Lorg/apache/hc/core5/http/HttpHost;
       4: areturn

  public java.net.InetAddress getLocalAddress();
    Code:
       0: aload_0
       1: getfield      #5                  // Field localAddress:Ljava/net/InetAddress;
       4: areturn

  public int getHopCount();
    Code:
       0: iconst_0
       1: istore_1
       2: aload_0
       3: getfield      #10                 // Field connected:Z
       6: ifeq          29
       9: aload_0
      10: getfield      #11                 // Field proxyChain:[Lorg/apache/hc/core5/http/HttpHost;
      13: ifnonnull     21
      16: iconst_1
      17: istore_1
      18: goto          29
      21: aload_0
      22: getfield      #11                 // Field proxyChain:[Lorg/apache/hc/core5/http/HttpHost;
      25: arraylength
      26: iconst_1
      27: iadd
      28: istore_1
      29: iload_1
      30: ireturn

  public org.apache.hc.core5.http.HttpHost getHopTarget(int);
    Code:
       0: iload_1
       1: ldc           #27                 // String Hop index
       3: invokestatic  #28                 // Method org/apache/hc/core5/util/Args.notNegative:(ILjava/lang/String;)I
       6: pop
       7: aload_0
       8: invokevirtual #29                 // Method getHopCount:()I
      11: istore_2
      12: iload_1
      13: iload_2
      14: if_icmpge     21
      17: iconst_1
      18: goto          22
      21: iconst_0
      22: ldc           #30                 // String Hop index exceeds tracked route length
      24: invokestatic  #31                 // Method org/apache/hc/core5/util/Args.check:(ZLjava/lang/String;)V
      27: aconst_null
      28: astore_3
      29: iload_1
      30: iload_2
      31: iconst_1
      32: isub
      33: if_icmpge     46
      36: aload_0
      37: getfield      #11                 // Field proxyChain:[Lorg/apache/hc/core5/http/HttpHost;
      40: iload_1
      41: aaload
      42: astore_3
      43: goto          51
      46: aload_0
      47: getfield      #4                  // Field targetHost:Lorg/apache/hc/core5/http/HttpHost;
      50: astore_3
      51: aload_3
      52: areturn

  public org.apache.hc.core5.http.HttpHost getProxyHost();
    Code:
       0: aload_0
       1: getfield      #11                 // Field proxyChain:[Lorg/apache/hc/core5/http/HttpHost;
       4: ifnonnull     11
       7: aconst_null
       8: goto          17
      11: aload_0
      12: getfield      #11                 // Field proxyChain:[Lorg/apache/hc/core5/http/HttpHost;
      15: iconst_0
      16: aaload
      17: areturn

  public boolean isConnected();
    Code:
       0: aload_0
       1: getfield      #10                 // Field connected:Z
       4: ireturn

  public org.apache.hc.client5.http.RouteInfo$TunnelType getTunnelType();
    Code:
       0: aload_0
       1: getfield      #7                  // Field tunnelled:Lorg/apache/hc/client5/http/RouteInfo$TunnelType;
       4: areturn

  public boolean isTunnelled();
    Code:
       0: aload_0
       1: getfield      #7                  // Field tunnelled:Lorg/apache/hc/client5/http/RouteInfo$TunnelType;
       4: getstatic     #23                 // Field org/apache/hc/client5/http/RouteInfo$TunnelType.TUNNELLED:Lorg/apache/hc/client5/http/RouteInfo$TunnelType;
       7: if_acmpne     14
      10: iconst_1
      11: goto          15
      14: iconst_0
      15: ireturn

  public org.apache.hc.client5.http.RouteInfo$LayerType getLayerType();
    Code:
       0: aload_0
       1: getfield      #9                  // Field layered:Lorg/apache/hc/client5/http/RouteInfo$LayerType;
       4: areturn

  public boolean isLayered();
    Code:
       0: aload_0
       1: getfield      #9                  // Field layered:Lorg/apache/hc/client5/http/RouteInfo$LayerType;
       4: getstatic     #26                 // Field org/apache/hc/client5/http/RouteInfo$LayerType.LAYERED:Lorg/apache/hc/client5/http/RouteInfo$LayerType;
       7: if_acmpne     14
      10: iconst_1
      11: goto          15
      14: iconst_0
      15: ireturn

  public boolean isSecure();
    Code:
       0: aload_0
       1: getfield      #12                 // Field secure:Z
       4: ireturn

  public org.apache.hc.client5.http.HttpRoute toRoute();
    Code:
       0: aload_0
       1: getfield      #10                 // Field connected:Z
       4: ifne          11
       7: aconst_null
       8: goto          42
      11: new           #32                 // class org/apache/hc/client5/http/HttpRoute
      14: dup
      15: aload_0
      16: getfield      #4                  // Field targetHost:Lorg/apache/hc/core5/http/HttpHost;
      19: aload_0
      20: getfield      #5                  // Field localAddress:Ljava/net/InetAddress;
      23: aload_0
      24: getfield      #11                 // Field proxyChain:[Lorg/apache/hc/core5/http/HttpHost;
      27: aload_0
      28: getfield      #12                 // Field secure:Z
      31: aload_0
      32: getfield      #7                  // Field tunnelled:Lorg/apache/hc/client5/http/RouteInfo$TunnelType;
      35: aload_0
      36: getfield      #9                  // Field layered:Lorg/apache/hc/client5/http/RouteInfo$LayerType;
      39: invokespecial #33                 // Method org/apache/hc/client5/http/HttpRoute."<init>":(Lorg/apache/hc/core5/http/HttpHost;Ljava/net/InetAddress;[Lorg/apache/hc/core5/http/HttpHost;ZLorg/apache/hc/client5/http/RouteInfo$TunnelType;Lorg/apache/hc/client5/http/RouteInfo$LayerType;)V
      42: areturn

  public boolean equals(java.lang.Object);
    Code:
       0: aload_1
       1: aload_0
       2: if_acmpne     7
       5: iconst_1
       6: ireturn
       7: aload_1
       8: instanceof    #34                 // class org/apache/hc/client5/http/RouteTracker
      11: ifne          16
      14: iconst_0
      15: ireturn
      16: aload_1
      17: checkcast     #34                 // class org/apache/hc/client5/http/RouteTracker
      20: astore_2
      21: aload_0
      22: getfield      #10                 // Field connected:Z
      25: aload_2
      26: getfield      #10                 // Field connected:Z
      29: if_icmpne     111
      32: aload_0
      33: getfield      #12                 // Field secure:Z
      36: aload_2
      37: getfield      #12                 // Field secure:Z
      40: if_icmpne     111
      43: aload_0
      44: getfield      #7                  // Field tunnelled:Lorg/apache/hc/client5/http/RouteInfo$TunnelType;
      47: aload_2
      48: getfield      #7                  // Field tunnelled:Lorg/apache/hc/client5/http/RouteInfo$TunnelType;
      51: if_acmpne     111
      54: aload_0
      55: getfield      #9                  // Field layered:Lorg/apache/hc/client5/http/RouteInfo$LayerType;
      58: aload_2
      59: getfield      #9                  // Field layered:Lorg/apache/hc/client5/http/RouteInfo$LayerType;
      62: if_acmpne     111
      65: aload_0
      66: getfield      #4                  // Field targetHost:Lorg/apache/hc/core5/http/HttpHost;
      69: aload_2
      70: getfield      #4                  // Field targetHost:Lorg/apache/hc/core5/http/HttpHost;
      73: invokestatic  #35                 // Method org/apache/hc/core5/util/LangUtils.equals:(Ljava/lang/Object;Ljava/lang/Object;)Z
      76: ifeq          111
      79: aload_0
      80: getfield      #5                  // Field localAddress:Ljava/net/InetAddress;
      83: aload_2
      84: getfield      #5                  // Field localAddress:Ljava/net/InetAddress;
      87: invokestatic  #35                 // Method org/apache/hc/core5/util/LangUtils.equals:(Ljava/lang/Object;Ljava/lang/Object;)Z
      90: ifeq          111
      93: aload_0
      94: getfield      #11                 // Field proxyChain:[Lorg/apache/hc/core5/http/HttpHost;
      97: aload_2
      98: getfield      #11                 // Field proxyChain:[Lorg/apache/hc/core5/http/HttpHost;
     101: invokestatic  #36                 // Method org/apache/hc/core5/util/LangUtils.equals:([Ljava/lang/Object;[Ljava/lang/Object;)Z
     104: ifeq          111
     107: iconst_1
     108: goto          112
     111: iconst_0
     112: ireturn

  public int hashCode();
    Code:
       0: bipush        17
       2: istore_1
       3: iload_1
       4: aload_0
       5: getfield      #4                  // Field targetHost:Lorg/apache/hc/core5/http/HttpHost;
       8: invokestatic  #37                 // Method org/apache/hc/core5/util/LangUtils.hashCode:(ILjava/lang/Object;)I
      11: istore_1
      12: iload_1
      13: aload_0
      14: getfield      #5                  // Field localAddress:Ljava/net/InetAddress;
      17: invokestatic  #37                 // Method org/apache/hc/core5/util/LangUtils.hashCode:(ILjava/lang/Object;)I
      20: istore_1
      21: aload_0
      22: getfield      #11                 // Field proxyChain:[Lorg/apache/hc/core5/http/HttpHost;
      25: ifnull        64
      28: aload_0
      29: getfield      #11                 // Field proxyChain:[Lorg/apache/hc/core5/http/HttpHost;
      32: astore_2
      33: aload_2
      34: arraylength
      35: istore_3
      36: iconst_0
      37: istore        4
      39: iload         4
      41: iload_3
      42: if_icmpge     64
      45: aload_2
      46: iload         4
      48: aaload
      49: astore        5
      51: iload_1
      52: aload         5
      54: invokestatic  #37                 // Method org/apache/hc/core5/util/LangUtils.hashCode:(ILjava/lang/Object;)I
      57: istore_1
      58: iinc          4, 1
      61: goto          39
      64: iload_1
      65: aload_0
      66: getfield      #10                 // Field connected:Z
      69: invokestatic  #38                 // Method org/apache/hc/core5/util/LangUtils.hashCode:(IZ)I
      72: istore_1
      73: iload_1
      74: aload_0
      75: getfield      #12                 // Field secure:Z
      78: invokestatic  #38                 // Method org/apache/hc/core5/util/LangUtils.hashCode:(IZ)I
      81: istore_1
      82: iload_1
      83: aload_0
      84: getfield      #7                  // Field tunnelled:Lorg/apache/hc/client5/http/RouteInfo$TunnelType;
      87: invokestatic  #37                 // Method org/apache/hc/core5/util/LangUtils.hashCode:(ILjava/lang/Object;)I
      90: istore_1
      91: iload_1
      92: aload_0
      93: getfield      #9                  // Field layered:Lorg/apache/hc/client5/http/RouteInfo$LayerType;
      96: invokestatic  #37                 // Method org/apache/hc/core5/util/LangUtils.hashCode:(ILjava/lang/Object;)I
      99: istore_1
     100: iload_1
     101: ireturn

  public java.lang.String toString();
    Code:
       0: new           #39                 // class java/lang/StringBuilder
       3: dup
       4: bipush        50
       6: aload_0
       7: invokevirtual #29                 // Method getHopCount:()I
      10: bipush        30
      12: imul
      13: iadd
      14: invokespecial #40                 // Method java/lang/StringBuilder."<init>":(I)V
      17: astore_1
      18: aload_1
      19: ldc           #41                 // String RouteTracker[
      21: invokevirtual #42                 // Method java/lang/StringBuilder.append:(Ljava/lang/String;)Ljava/lang/StringBuilder;
      24: pop
      25: aload_0
      26: getfield      #5                  // Field localAddress:Ljava/net/InetAddress;
      29: ifnull        48
      32: aload_1
      33: aload_0
      34: getfield      #5                  // Field localAddress:Ljava/net/InetAddress;
      37: invokevirtual #43                 // Method java/lang/StringBuilder.append:(Ljava/lang/Object;)Ljava/lang/StringBuilder;
      40: pop
      41: aload_1
      42: ldc           #44                 // String ->
      44: invokevirtual #42                 // Method java/lang/StringBuilder.append:(Ljava/lang/String;)Ljava/lang/StringBuilder;
      47: pop
      48: aload_1
      49: bipush        123
      51: invokevirtual #45                 // Method java/lang/StringBuilder.append:(C)Ljava/lang/StringBuilder;
      54: pop
      55: aload_0
      56: getfield      #10                 // Field connected:Z
      59: ifeq          69
      62: aload_1
      63: bipush        99
      65: invokevirtual #45                 // Method java/lang/StringBuilder.append:(C)Ljava/lang/StringBuilder;
      68: pop
      69: aload_0
      70: getfield      #7                  // Field tunnelled:Lorg/apache/hc/client5/http/RouteInfo$TunnelType;
      73: getstatic     #23                 // Field org/apache/hc/client5/http/RouteInfo$TunnelType.TUNNELLED:Lorg/apache/hc/client5/http/RouteInfo$TunnelType;
      76: if_acmpne     86
      79: aload_1
      80: bipush        116
      82: invokevirtual #45                 // Method java/lang/StringBuilder.append:(C)Ljava/lang/StringBuilder;
      85: pop
      86: aload_0
      87: getfield      #9                  // Field layered:Lorg/apache/hc/client5/http/RouteInfo$LayerType;
      90: getstatic     #26                 // Field org/apache/hc/client5/http/RouteInfo$LayerType.LAYERED:Lorg/apache/hc/client5/http/RouteInfo$LayerType;
      93: if_acmpne     103
      96: aload_1
      97: bipush        108
      99: invokevirtual #45                 // Method java/lang/StringBuilder.append:(C)Ljava/lang/StringBuilder;
     102: pop
     103: aload_0
     104: getfield      #12                 // Field secure:Z
     107: ifeq          117
     110: aload_1
     111: bipush        115
     113: invokevirtual #45                 // Method java/lang/StringBuilder.append:(C)Ljava/lang/StringBuilder;
     116: pop
     117: aload_1
     118: ldc           #46                 // String }->
     120: invokevirtual #42                 // Method java/lang/StringBuilder.append:(Ljava/lang/String;)Ljava/lang/StringBuilder;
     123: pop
     124: aload_0
     125: getfield      #11                 // Field proxyChain:[Lorg/apache/hc/core5/http/HttpHost;
     128: ifnull        174
     131: aload_0
     132: getfield      #11                 // Field proxyChain:[Lorg/apache/hc/core5/http/HttpHost;
     135: astore_2
     136: aload_2
     137: arraylength
     138: istore_3
     139: iconst_0
     140: istore        4
     142: iload         4
     144: iload_3
     145: if_icmpge     174
     148: aload_2
     149: iload         4
     151: aaload
     152: astore        5
     154: aload_1
     155: aload         5
     157: invokevirtual #43                 // Method java/lang/StringBuilder.append:(Ljava/lang/Object;)Ljava/lang/StringBuilder;
     160: pop
     161: aload_1
     162: ldc           #44                 // String ->
     164: invokevirtual #42                 // Method java/lang/StringBuilder.append:(Ljava/lang/String;)Ljava/lang/StringBuilder;
     167: pop
     168: iinc          4, 1
     171: goto          142
     174: aload_1
     175: aload_0
     176: getfield      #4                  // Field targetHost:Lorg/apache/hc/core5/http/HttpHost;
     179: invokevirtual #43                 // Method java/lang/StringBuilder.append:(Ljava/lang/Object;)Ljava/lang/StringBuilder;
     182: pop
     183: aload_1
     184: bipush        93
     186: invokevirtual #45                 // Method java/lang/StringBuilder.append:(C)Ljava/lang/StringBuilder;
     189: pop
     190: aload_1
     191: invokevirtual #47                 // Method java/lang/StringBuilder.toString:()Ljava/lang/String;
     194: areturn

  public java.lang.Object clone() throws java.lang.CloneNotSupportedException;
    Code:
       0: aload_0
       1: invokespecial #48                 // Method java/lang/Object.clone:()Ljava/lang/Object;
       4: areturn
}
