Compiled from "SecurityActions.java"
final class org.jboss.as.ejb3.remote.protocol.versionone.SecurityActions$RemotingContextAssociationActions$1 implements org.jboss.as.ejb3.remote.protocol.versionone.SecurityActions$RemotingContextAssociationActions {
  org.jboss.as.ejb3.remote.protocol.versionone.SecurityActions$RemotingContextAssociationActions$1();
    Code:
       0: aload_0
       1: invokespecial #1                  // Method java/lang/Object."<init>":()V
       4: return

  public void setConnection(org.jboss.remoting3.Connection);
    Code:
       0: aload_1
       1: invokestatic  #2                  // Method org/jboss/as/security/remoting/RemotingContext.setConnection:(Lorg/jboss/remoting3/Connection;)V
       4: return

  public void clear();
    Code:
       0: invokestatic  #3                  // Method org/jboss/as/security/remoting/RemotingContext.clear:()V
       3: return
}
