Compiled from "BaseEncoding.java"
class com.google.common.io.BaseEncoding$2 extends com.google.common.io.ByteSource {
  final com.google.common.io.CharSource val$encodedSource;

  final com.google.common.io.BaseEncoding this$0;

  com.google.common.io.BaseEncoding$2(com.google.common.io.BaseEncoding, com.google.common.io.CharSource);
    Code:
       0: aload_0
       1: aload_1
       2: putfield      #1                  // Field this$0:Lcom/google/common/io/BaseEncoding;
       5: aload_0
       6: aload_2
       7: putfield      #2                  // Field val$encodedSource:Lcom/google/common/io/CharSource;
      10: aload_0
      11: invokespecial #3                  // Method com/google/common/io/ByteSource."<init>":()V
      14: return

  public java.io.InputStream openStream() throws java.io.IOException;
    Code:
       0: aload_0
       1: getfield      #1                  // Field this$0:Lcom/google/common/io/BaseEncoding;
       4: aload_0
       5: getfield      #2                  // Field val$encodedSource:Lcom/google/common/io/CharSource;
       8: invokevirtual #4                  // Method com/google/common/io/CharSource.openStream:()Ljava/io/Reader;
      11: invokevirtual #5                  // Method com/google/common/io/BaseEncoding.decodingStream:(Ljava/io/Reader;)Ljava/io/InputStream;
      14: areturn
}
