Compiled from "CidrAddress.java"
public final class org.wildfly.common.net.CidrAddress implements java.io.Serializable, java.lang.Comparable<org.wildfly.common.net.CidrAddress> {
  private static final long serialVersionUID;

  public static final org.wildfly.common.net.CidrAddress INET4_ANY_CIDR;

  public static final org.wildfly.common.net.CidrAddress INET6_ANY_CIDR;

  private final java.net.InetAddress networkAddress;

  private final byte[] cachedBytes;

  private final int netmaskBits;

  private java.net.Inet4Address broadcast;

  private java.lang.String toString;

  private int hashCode;

  static final boolean $assertionsDisabled;

  private org.wildfly.common.net.CidrAddress(java.net.InetAddress, int);
    Code:
       0: aload_0
       1: invokespecial #1                  // Method java/lang/Object."<init>":()V
       4: aload_0
       5: aload_1
       6: putfield      #2                  // Field networkAddress:Ljava/net/InetAddress;
       9: aload_0
      10: aload_1
      11: invokevirtual #3                  // Method java/net/InetAddress.getAddress:()[B
      14: putfield      #4                  // Field cachedBytes:[B
      17: aload_0
      18: iload_2
      19: putfield      #5                  // Field netmaskBits:I
      22: return

  public static org.wildfly.common.net.CidrAddress create(java.net.InetAddress, int);
    Code:
       0: ldc           #6                  // String networkAddress
       2: aload_0
       3: invokestatic  #7                  // Method org/wildfly/common/Assert.checkNotNullParam:(Ljava/lang/String;Ljava/lang/Object;)Ljava/lang/Object;
       6: pop
       7: ldc           #8                  // String netmaskBits
       9: iconst_0
      10: iload_1
      11: invokestatic  #9                  // Method org/wildfly/common/Assert.checkMinimumParameter:(Ljava/lang/String;II)V
      14: aload_0
      15: invokestatic  #10                 // Method org/wildfly/common/net/Inet.getScopeId:(Ljava/net/InetAddress;)I
      18: istore_2
      19: aload_0
      20: instanceof    #11                 // class java/net/Inet4Address
      23: ifeq          42
      26: ldc           #8                  // String netmaskBits
      28: bipush        32
      30: iload_1
      31: invokestatic  #12                 // Method org/wildfly/common/Assert.checkMaximumParameter:(Ljava/lang/String;II)V
      34: iload_1
      35: ifne          74
      38: getstatic     #13                 // Field INET4_ANY_CIDR:Lorg/wildfly/common/net/CidrAddress;
      41: areturn
      42: aload_0
      43: instanceof    #14                 // class java/net/Inet6Address
      46: ifeq          70
      49: ldc           #8                  // String netmaskBits
      51: sipush        128
      54: iload_1
      55: invokestatic  #12                 // Method org/wildfly/common/Assert.checkMaximumParameter:(Ljava/lang/String;II)V
      58: iload_1
      59: ifne          74
      62: iload_2
      63: ifne          74
      66: getstatic     #15                 // Field INET6_ANY_CIDR:Lorg/wildfly/common/net/CidrAddress;
      69: areturn
      70: invokestatic  #16                 // Method org/wildfly/common/Assert.unreachableCode:()Ljava/lang/IllegalStateException;
      73: athrow
      74: aload_0
      75: invokevirtual #3                  // Method java/net/InetAddress.getAddress:()[B
      78: astore_3
      79: aload_3
      80: iload_1
      81: invokestatic  #17                 // Method maskBits0:([BI)[B
      84: pop
      85: aload_3
      86: invokestatic  #18                 // Method org/wildfly/common/net/Inet.toOptimalString:([B)Ljava/lang/String;
      89: astore        4
      91: aload_3
      92: arraylength
      93: iconst_4
      94: if_icmpne     112
      97: new           #19                 // class org/wildfly/common/net/CidrAddress
     100: dup
     101: aload         4
     103: aload_3
     104: invokestatic  #20                 // Method java/net/InetAddress.getByAddress:(Ljava/lang/String;[B)Ljava/net/InetAddress;
     107: iload_1
     108: invokespecial #21                 // Method "<init>":(Ljava/net/InetAddress;I)V
     111: areturn
     112: new           #19                 // class org/wildfly/common/net/CidrAddress
     115: dup
     116: aload         4
     118: aload_3
     119: iload_2
     120: invokestatic  #22                 // Method java/net/Inet6Address.getByAddress:(Ljava/lang/String;[BI)Ljava/net/Inet6Address;
     123: iload_1
     124: invokespecial #21                 // Method "<init>":(Ljava/net/InetAddress;I)V
     127: areturn
     128: astore        5
     130: invokestatic  #16                 // Method org/wildfly/common/Assert.unreachableCode:()Ljava/lang/IllegalStateException;
     133: athrow
    Exception table:
       from    to  target type
          91   111   128   Class java/net/UnknownHostException
         112   127   128   Class java/net/UnknownHostException

  public static org.wildfly.common.net.CidrAddress create(byte[], int);
    Code:
       0: aload_0
       1: iload_1
       2: iconst_1
       3: invokestatic  #24                 // Method create:([BIZ)Lorg/wildfly/common/net/CidrAddress;
       6: areturn

  static org.wildfly.common.net.CidrAddress create(byte[], int, boolean);
    Code:
       0: ldc           #6                  // String networkAddress
       2: aload_0
       3: invokestatic  #7                  // Method org/wildfly/common/Assert.checkNotNullParam:(Ljava/lang/String;Ljava/lang/Object;)Ljava/lang/Object;
       6: pop
       7: ldc           #8                  // String netmaskBits
       9: iconst_0
      10: iload_1
      11: invokestatic  #9                  // Method org/wildfly/common/Assert.checkMinimumParameter:(Ljava/lang/String;II)V
      14: aload_0
      15: arraylength
      16: istore_3
      17: iload_3
      18: iconst_4
      19: if_icmpne     38
      22: ldc           #8                  // String netmaskBits
      24: bipush        32
      26: iload_1
      27: invokestatic  #12                 // Method org/wildfly/common/Assert.checkMaximumParameter:(Ljava/lang/String;II)V
      30: iload_1
      31: ifne          71
      34: getstatic     #13                 // Field INET4_ANY_CIDR:Lorg/wildfly/common/net/CidrAddress;
      37: areturn
      38: iload_3
      39: bipush        16
      41: if_icmpne     61
      44: ldc           #8                  // String netmaskBits
      46: sipush        128
      49: iload_1
      50: invokestatic  #12                 // Method org/wildfly/common/Assert.checkMaximumParameter:(Ljava/lang/String;II)V
      53: iload_1
      54: ifne          71
      57: getstatic     #15                 // Field INET6_ANY_CIDR:Lorg/wildfly/common/net/CidrAddress;
      60: areturn
      61: getstatic     #25                 // Field org/wildfly/common/_private/CommonMessages.msg:Lorg/wildfly/common/_private/CommonMessages;
      64: iload_3
      65: invokeinterface #26,  2           // InterfaceMethod org/wildfly/common/_private/CommonMessages.invalidAddressBytes:(I)Ljava/lang/IllegalArgumentException;
      70: athrow
      71: iload_2
      72: ifeq          85
      75: aload_0
      76: invokevirtual #27                 // Method "[B".clone:()Ljava/lang/Object;
      79: checkcast     #28                 // class "[B"
      82: goto          86
      85: aload_0
      86: astore        4
      88: aload         4
      90: iload_1
      91: invokestatic  #17                 // Method maskBits0:([BI)[B
      94: pop
      95: aload         4
      97: invokestatic  #18                 // Method org/wildfly/common/net/Inet.toOptimalString:([B)Ljava/lang/String;
     100: astore        5
     102: new           #19                 // class org/wildfly/common/net/CidrAddress
     105: dup
     106: aload         5
     108: aload         4
     110: invokestatic  #20                 // Method java/net/InetAddress.getByAddress:(Ljava/lang/String;[B)Ljava/net/InetAddress;
     113: iload_1
     114: invokespecial #21                 // Method "<init>":(Ljava/net/InetAddress;I)V
     117: areturn
     118: astore        6
     120: invokestatic  #16                 // Method org/wildfly/common/Assert.unreachableCode:()Ljava/lang/IllegalStateException;
     123: athrow
    Exception table:
       from    to  target type
         102   117   118   Class java/net/UnknownHostException

  public boolean matches(java.net.InetAddress);
    Code:
       0: ldc           #29                 // String address
       2: aload_1
       3: invokestatic  #7                  // Method org/wildfly/common/Assert.checkNotNullParam:(Ljava/lang/String;Ljava/lang/Object;)Ljava/lang/Object;
       6: pop
       7: aload_1
       8: instanceof    #11                 // class java/net/Inet4Address
      11: ifeq          23
      14: aload_0
      15: aload_1
      16: checkcast     #11                 // class java/net/Inet4Address
      19: invokevirtual #30                 // Method matches:(Ljava/net/Inet4Address;)Z
      22: ireturn
      23: aload_1
      24: instanceof    #14                 // class java/net/Inet6Address
      27: ifeq          39
      30: aload_0
      31: aload_1
      32: checkcast     #14                 // class java/net/Inet6Address
      35: invokevirtual #31                 // Method matches:(Ljava/net/Inet6Address;)Z
      38: ireturn
      39: invokestatic  #16                 // Method org/wildfly/common/Assert.unreachableCode:()Ljava/lang/IllegalStateException;
      42: athrow

  public boolean matches(byte[]);
    Code:
       0: aload_0
       1: aload_1
       2: iconst_0
       3: invokevirtual #32                 // Method matches:([BI)Z
       6: ireturn

  public boolean matches(byte[], int);
    Code:
       0: ldc           #33                 // String bytes
       2: aload_1
       3: invokestatic  #7                  // Method org/wildfly/common/Assert.checkNotNullParam:(Ljava/lang/String;Ljava/lang/Object;)Ljava/lang/Object;
       6: pop
       7: aload_0
       8: getfield      #4                  // Field cachedBytes:[B
      11: arraylength
      12: aload_1
      13: arraylength
      14: if_icmpne     51
      17: aload_0
      18: invokevirtual #34                 // Method getScopeId:()I
      21: ifeq          32
      24: aload_0
      25: invokevirtual #34                 // Method getScopeId:()I
      28: iload_2
      29: if_icmpne     51
      32: aload_0
      33: getfield      #4                  // Field cachedBytes:[B
      36: aload_1
      37: aload_0
      38: getfield      #5                  // Field netmaskBits:I
      41: invokestatic  #35                 // Method bitsMatch:([B[BI)Z
      44: ifeq          51
      47: iconst_1
      48: goto          52
      51: iconst_0
      52: ireturn

  public boolean matches(java.net.Inet4Address);
    Code:
       0: ldc           #29                 // String address
       2: aload_1
       3: invokestatic  #7                  // Method org/wildfly/common/Assert.checkNotNullParam:(Ljava/lang/String;Ljava/lang/Object;)Ljava/lang/Object;
       6: pop
       7: aload_0
       8: getfield      #2                  // Field networkAddress:Ljava/net/InetAddress;
      11: instanceof    #11                 // class java/net/Inet4Address
      14: ifeq          39
      17: aload_0
      18: getfield      #4                  // Field cachedBytes:[B
      21: aload_1
      22: invokevirtual #36                 // Method java/net/Inet4Address.getAddress:()[B
      25: aload_0
      26: getfield      #5                  // Field netmaskBits:I
      29: invokestatic  #35                 // Method bitsMatch:([B[BI)Z
      32: ifeq          39
      35: iconst_1
      36: goto          40
      39: iconst_0
      40: ireturn

  public boolean matches(java.net.Inet6Address);
    Code:
       0: ldc           #29                 // String address
       2: aload_1
       3: invokestatic  #7                  // Method org/wildfly/common/Assert.checkNotNullParam:(Ljava/lang/String;Ljava/lang/Object;)Ljava/lang/Object;
       6: pop
       7: aload_0
       8: getfield      #2                  // Field networkAddress:Ljava/net/InetAddress;
      11: instanceof    #14                 // class java/net/Inet6Address
      14: ifeq          57
      17: aload_0
      18: getfield      #4                  // Field cachedBytes:[B
      21: aload_1
      22: invokevirtual #37                 // Method java/net/Inet6Address.getAddress:()[B
      25: aload_0
      26: getfield      #5                  // Field netmaskBits:I
      29: invokestatic  #35                 // Method bitsMatch:([B[BI)Z
      32: ifeq          57
      35: aload_0
      36: invokevirtual #34                 // Method getScopeId:()I
      39: ifeq          53
      42: aload_0
      43: invokevirtual #34                 // Method getScopeId:()I
      46: aload_1
      47: invokevirtual #38                 // Method java/net/Inet6Address.getScopeId:()I
      50: if_icmpne     57
      53: iconst_1
      54: goto          58
      57: iconst_0
      58: ireturn

  public boolean matches(org.wildfly.common.net.CidrAddress);
    Code:
       0: ldc           #29                 // String address
       2: aload_1
       3: invokestatic  #7                  // Method org/wildfly/common/Assert.checkNotNullParam:(Ljava/lang/String;Ljava/lang/Object;)Ljava/lang/Object;
       6: pop
       7: aload_0
       8: getfield      #5                  // Field netmaskBits:I
      11: aload_1
      12: getfield      #5                  // Field netmaskBits:I
      15: if_icmpgt     51
      18: aload_0
      19: aload_1
      20: getfield      #4                  // Field cachedBytes:[B
      23: invokevirtual #39                 // Method matches:([B)Z
      26: ifeq          51
      29: aload_0
      30: invokevirtual #34                 // Method getScopeId:()I
      33: ifeq          47
      36: aload_0
      37: invokevirtual #34                 // Method getScopeId:()I
      40: aload_1
      41: invokevirtual #34                 // Method getScopeId:()I
      44: if_icmpne     51
      47: iconst_1
      48: goto          52
      51: iconst_0
      52: ireturn

  public java.net.InetAddress getNetworkAddress();
    Code:
       0: aload_0
       1: getfield      #2                  // Field networkAddress:Ljava/net/InetAddress;
       4: areturn

  public java.net.Inet4Address getBroadcastAddress();
    Code:
       0: aload_0
       1: getfield      #40                 // Field broadcast:Ljava/net/Inet4Address;
       4: astore_1
       5: aload_1
       6: ifnonnull     86
       9: aload_0
      10: getfield      #5                  // Field netmaskBits:I
      13: istore_2
      14: iload_2
      15: bipush        31
      17: if_icmplt     22
      20: aconst_null
      21: areturn
      22: aload_0
      23: getfield      #4                  // Field cachedBytes:[B
      26: astore_3
      27: aload_3
      28: arraylength
      29: iconst_4
      30: if_icmpne     84
      33: iload_2
      34: ifne          46
      37: aload_0
      38: getstatic     #41                 // Field org/wildfly/common/net/Inet.INET4_BROADCAST:Ljava/net/Inet4Address;
      41: dup_x1
      42: putfield      #40                 // Field broadcast:Ljava/net/Inet4Address;
      45: areturn
      46: aload_3
      47: invokevirtual #42                 // Method "[B".clone:()Ljava/lang/Object;
      50: checkcast     #28                 // class "[B"
      53: iload_2
      54: invokestatic  #43                 // Method maskBits1:([BI)[B
      57: astore        4
      59: aload_0
      60: aload         4
      62: invokestatic  #18                 // Method org/wildfly/common/net/Inet.toOptimalString:([B)Ljava/lang/String;
      65: aload         4
      67: invokestatic  #20                 // Method java/net/InetAddress.getByAddress:(Ljava/lang/String;[B)Ljava/net/InetAddress;
      70: checkcast     #11                 // class java/net/Inet4Address
      73: dup_x1
      74: putfield      #40                 // Field broadcast:Ljava/net/Inet4Address;
      77: areturn
      78: astore        5
      80: invokestatic  #16                 // Method org/wildfly/common/Assert.unreachableCode:()Ljava/lang/IllegalStateException;
      83: athrow
      84: aconst_null
      85: areturn
      86: aload_1
      87: areturn
    Exception table:
       from    to  target type
          59    77    78   Class java/net/UnknownHostException

  public int getNetmaskBits();
    Code:
       0: aload_0
       1: getfield      #5                  // Field netmaskBits:I
       4: ireturn

  public int getScopeId();
    Code:
       0: aload_0
       1: invokevirtual #44                 // Method getNetworkAddress:()Ljava/net/InetAddress;
       4: invokestatic  #10                 // Method org/wildfly/common/net/Inet.getScopeId:(Ljava/net/InetAddress;)I
       7: ireturn

  public int compareTo(org.wildfly.common.net.CidrAddress);
    Code:
       0: ldc           #45                 // String other
       2: aload_1
       3: invokestatic  #7                  // Method org/wildfly/common/Assert.checkNotNullParam:(Ljava/lang/String;Ljava/lang/Object;)Ljava/lang/Object;
       6: pop
       7: aload_0
       8: aload_1
       9: if_acmpne     14
      12: iconst_0
      13: ireturn
      14: aload_0
      15: aload_1
      16: getfield      #4                  // Field cachedBytes:[B
      19: aload_1
      20: getfield      #5                  // Field netmaskBits:I
      23: aload_1
      24: invokevirtual #34                 // Method getScopeId:()I
      27: invokevirtual #46                 // Method compareAddressBytesTo:([BII)I
      30: ireturn

  public int compareAddressBytesTo(byte[], int, int);
    Code:
       0: ldc           #33                 // String bytes
       2: aload_1
       3: invokestatic  #7                  // Method org/wildfly/common/Assert.checkNotNullParam:(Ljava/lang/String;Ljava/lang/Object;)Ljava/lang/Object;
       6: pop
       7: aload_1
       8: arraylength
       9: istore        4
      11: iload         4
      13: iconst_4
      14: if_icmpeq     35
      17: iload         4
      19: bipush        16
      21: if_icmpeq     35
      24: getstatic     #25                 // Field org/wildfly/common/_private/CommonMessages.msg:Lorg/wildfly/common/_private/CommonMessages;
      27: iload         4
      29: invokeinterface #26,  2           // InterfaceMethod org/wildfly/common/_private/CommonMessages.invalidAddressBytes:(I)Ljava/lang/IllegalArgumentException;
      34: athrow
      35: aload_0
      36: getfield      #4                  // Field cachedBytes:[B
      39: astore        5
      41: aload         5
      43: arraylength
      44: iload         4
      46: isub
      47: invokestatic  #47                 // Method java/lang/Integer.signum:(I)I
      50: istore        6
      52: iload         6
      54: ifeq          60
      57: iload         6
      59: ireturn
      60: iload_3
      61: aload_0
      62: invokevirtual #34                 // Method getScopeId:()I
      65: isub
      66: invokestatic  #47                 // Method java/lang/Integer.signum:(I)I
      69: istore        6
      71: iload         6
      73: ifeq          79
      76: iload         6
      78: ireturn
      79: aload_0
      80: getfield      #5                  // Field netmaskBits:I
      83: istore        7
      85: iload         7
      87: iload_2
      88: invokestatic  #48                 // Method java/lang/Math.min:(II)I
      91: istore        8
      93: iconst_0
      94: istore        9
      96: iload         8
      98: bipush        8
     100: if_icmplt     143
     103: aload         5
     105: iload         9
     107: baload
     108: sipush        255
     111: iand
     112: aload_1
     113: iload         9
     115: baload
     116: sipush        255
     119: iand
     120: isub
     121: invokestatic  #47                 // Method java/lang/Integer.signum:(I)I
     124: istore        6
     126: iload         6
     128: ifeq          134
     131: iload         6
     133: ireturn
     134: iinc          9, 1
     137: iinc          8, -8
     140: goto          96
     143: iload         8
     145: ifle          189
     148: iconst_1
     149: iload         8
     151: ishl
     152: istore        10
     154: aload         5
     156: iload         9
     158: baload
     159: iload         10
     161: iand
     162: aload_1
     163: iload         9
     165: baload
     166: iload         10
     168: iand
     169: isub
     170: invokestatic  #47                 // Method java/lang/Integer.signum:(I)I
     173: istore        6
     175: iload         6
     177: ifeq          183
     180: iload         6
     182: ireturn
     183: iinc          8, -1
     186: goto          143
     189: iload         7
     191: iload_2
     192: isub
     193: invokestatic  #47                 // Method java/lang/Integer.signum:(I)I
     196: ireturn

  public boolean equals(java.lang.Object);
    Code:
       0: aload_1
       1: instanceof    #19                 // class org/wildfly/common/net/CidrAddress
       4: ifeq          22
       7: aload_0
       8: aload_1
       9: checkcast     #19                 // class org/wildfly/common/net/CidrAddress
      12: invokevirtual #49                 // Method equals:(Lorg/wildfly/common/net/CidrAddress;)Z
      15: ifeq          22
      18: iconst_1
      19: goto          23
      22: iconst_0
      23: ireturn

  public boolean equals(org.wildfly.common.net.CidrAddress);
    Code:
       0: aload_1
       1: aload_0
       2: if_acmpeq     34
       5: aload_1
       6: ifnull        38
       9: aload_0
      10: getfield      #5                  // Field netmaskBits:I
      13: aload_1
      14: getfield      #5                  // Field netmaskBits:I
      17: if_icmpne     38
      20: aload_0
      21: getfield      #4                  // Field cachedBytes:[B
      24: aload_1
      25: getfield      #4                  // Field cachedBytes:[B
      28: invokestatic  #50                 // Method java/util/Arrays.equals:([B[B)Z
      31: ifeq          38
      34: iconst_1
      35: goto          39
      38: iconst_0
      39: ireturn

  public int hashCode();
    Code:
       0: aload_0
       1: getfield      #51                 // Field hashCode:I
       4: istore_1
       5: iload_1
       6: ifne          35
       9: aload_0
      10: getfield      #5                  // Field netmaskBits:I
      13: aload_0
      14: getfield      #4                  // Field cachedBytes:[B
      17: invokestatic  #52                 // Method java/util/Arrays.hashCode:([B)I
      20: invokestatic  #53                 // Method org/wildfly/common/math/HashMath.multiHashOrdered:(II)I
      23: istore_1
      24: iload_1
      25: ifne          30
      28: iconst_1
      29: istore_1
      30: aload_0
      31: iload_1
      32: putfield      #51                 // Field hashCode:I
      35: iload_1
      36: ireturn

  public java.lang.String toString();
    Code:
       0: aload_0
       1: getfield      #54                 // Field toString:Ljava/lang/String;
       4: astore_1
       5: aload_1
       6: ifnonnull     95
       9: aload_0
      10: invokevirtual #34                 // Method getScopeId:()I
      13: istore_2
      14: iload_2
      15: ifne          53
      18: aload_0
      19: ldc           #55                 // String %s/%d
      21: iconst_2
      22: anewarray     #56                 // class java/lang/Object
      25: dup
      26: iconst_0
      27: aload_0
      28: getfield      #4                  // Field cachedBytes:[B
      31: invokestatic  #18                 // Method org/wildfly/common/net/Inet.toOptimalString:([B)Ljava/lang/String;
      34: aastore
      35: dup
      36: iconst_1
      37: aload_0
      38: getfield      #5                  // Field netmaskBits:I
      41: invokestatic  #57                 // Method java/lang/Integer.valueOf:(I)Ljava/lang/Integer;
      44: aastore
      45: invokestatic  #58                 // Method java/lang/String.format:(Ljava/lang/String;[Ljava/lang/Object;)Ljava/lang/String;
      48: dup_x1
      49: putfield      #54                 // Field toString:Ljava/lang/String;
      52: areturn
      53: aload_0
      54: ldc           #59                 // String %s%%%d/%d
      56: iconst_3
      57: anewarray     #56                 // class java/lang/Object
      60: dup
      61: iconst_0
      62: aload_0
      63: getfield      #4                  // Field cachedBytes:[B
      66: invokestatic  #18                 // Method org/wildfly/common/net/Inet.toOptimalString:([B)Ljava/lang/String;
      69: aastore
      70: dup
      71: iconst_1
      72: iload_2
      73: invokestatic  #57                 // Method java/lang/Integer.valueOf:(I)Ljava/lang/Integer;
      76: aastore
      77: dup
      78: iconst_2
      79: aload_0
      80: getfield      #5                  // Field netmaskBits:I
      83: invokestatic  #57                 // Method java/lang/Integer.valueOf:(I)Ljava/lang/Integer;
      86: aastore
      87: invokestatic  #58                 // Method java/lang/String.format:(Ljava/lang/String;[Ljava/lang/Object;)Ljava/lang/String;
      90: dup_x1
      91: putfield      #54                 // Field toString:Ljava/lang/String;
      94: areturn
      95: aload_1
      96: areturn

  java.lang.Object writeReplace();
    Code:
       0: new           #60                 // class org/wildfly/common/net/CidrAddress$Ser
       3: dup
       4: aload_0
       5: getfield      #4                  // Field cachedBytes:[B
       8: aload_0
       9: getfield      #5                  // Field netmaskBits:I
      12: invokespecial #61                 // Method org/wildfly/common/net/CidrAddress$Ser."<init>":([BI)V
      15: areturn

  private static boolean bitsMatch(byte[], byte[], int);
    Code:
       0: aload_0
       1: arraylength
       2: istore_3
       3: getstatic     #62                 // Field $assertionsDisabled:Z
       6: ifne          23
       9: iload_3
      10: aload_1
      11: arraylength
      12: if_icmpeq     23
      15: new           #63                 // class java/lang/AssertionError
      18: dup
      19: invokespecial #64                 // Method java/lang/AssertionError."<init>":()V
      22: athrow
      23: iconst_0
      24: istore        4
      26: iload_2
      27: bipush        8
      29: if_icmplt     60
      32: iload         4
      34: iload_3
      35: if_icmpge     60
      38: aload_0
      39: iload         4
      41: baload
      42: aload_1
      43: iload         4
      45: baload
      46: if_icmpeq     51
      49: iconst_0
      50: ireturn
      51: iinc          4, 1
      54: iinc          2, -8
      57: goto          26
      60: iload_2
      61: ifle          121
      64: getstatic     #62                 // Field $assertionsDisabled:Z
      67: ifne          84
      70: iload_2
      71: bipush        8
      73: if_icmplt     84
      76: new           #63                 // class java/lang/AssertionError
      79: dup
      80: invokespecial #64                 // Method java/lang/AssertionError."<init>":()V
      83: athrow
      84: sipush        255
      87: bipush        8
      89: iload_2
      90: isub
      91: ishl
      92: istore        5
      94: aload_0
      95: iload         4
      97: baload
      98: sipush        255
     101: iand
     102: iload         5
     104: iand
     105: aload_1
     106: iload         4
     108: baload
     109: sipush        255
     112: iand
     113: iload         5
     115: iand
     116: if_icmpeq     121
     119: iconst_0
     120: ireturn
     121: iconst_1
     122: ireturn

  private static byte[] maskBits0(byte[], int);
    Code:
       0: aload_0
       1: arraylength
       2: istore_2
       3: iconst_0
       4: istore_3
       5: iload_1
       6: bipush        8
       8: if_icmplt     25
      11: iload_3
      12: iload_2
      13: if_icmpge     25
      16: iinc          3, 1
      19: iinc          1, -8
      22: goto          5
      25: iload_1
      26: ifle          71
      29: getstatic     #62                 // Field $assertionsDisabled:Z
      32: ifne          49
      35: iload_1
      36: bipush        8
      38: if_icmplt     49
      41: new           #63                 // class java/lang/AssertionError
      44: dup
      45: invokespecial #64                 // Method java/lang/AssertionError."<init>":()V
      48: athrow
      49: sipush        255
      52: bipush        8
      54: iload_1
      55: isub
      56: ishl
      57: istore        4
      59: aload_0
      60: iload_3
      61: iinc          3, 1
      64: dup2
      65: baload
      66: iload         4
      68: iand
      69: i2b
      70: bastore
      71: iload_3
      72: iload_2
      73: if_icmpge     86
      76: aload_0
      77: iload_3
      78: iinc          3, 1
      81: iconst_0
      82: bastore
      83: goto          71
      86: aload_0
      87: areturn

  private static byte[] maskBits1(byte[], int);
    Code:
       0: aload_0
       1: arraylength
       2: istore_2
       3: iconst_0
       4: istore_3
       5: iload_1
       6: bipush        8
       8: if_icmplt     25
      11: iload_3
      12: iload_2
      13: if_icmpge     25
      16: iinc          3, 1
      19: iinc          1, -8
      22: goto          5
      25: iload_1
      26: ifle          71
      29: getstatic     #62                 // Field $assertionsDisabled:Z
      32: ifne          49
      35: iload_1
      36: bipush        8
      38: if_icmplt     49
      41: new           #63                 // class java/lang/AssertionError
      44: dup
      45: invokespecial #64                 // Method java/lang/AssertionError."<init>":()V
      48: athrow
      49: sipush        255
      52: bipush        8
      54: iload_1
      55: isub
      56: iushr
      57: istore        4
      59: aload_0
      60: iload_3
      61: iinc          3, 1
      64: dup2
      65: baload
      66: iload         4
      68: ior
      69: i2b
      70: bastore
      71: iload_3
      72: iload_2
      73: if_icmpge     86
      76: aload_0
      77: iload_3
      78: iinc          3, 1
      81: iconst_m1
      82: bastore
      83: goto          71
      86: aload_0
      87: areturn

  public int compareTo(java.lang.Object);
    Code:
       0: aload_0
       1: aload_1
       2: checkcast     #19                 // class org/wildfly/common/net/CidrAddress
       5: invokevirtual #65                 // Method compareTo:(Lorg/wildfly/common/net/CidrAddress;)I
       8: ireturn

  static {};
    Code:
       0: ldc           #19                 // class org/wildfly/common/net/CidrAddress
       2: invokevirtual #66                 // Method java/lang/Class.desiredAssertionStatus:()Z
       5: ifne          12
       8: iconst_1
       9: goto          13
      12: iconst_0
      13: putstatic     #62                 // Field $assertionsDisabled:Z
      16: new           #19                 // class org/wildfly/common/net/CidrAddress
      19: dup
      20: getstatic     #67                 // Field org/wildfly/common/net/Inet.INET4_ANY:Ljava/net/Inet4Address;
      23: iconst_0
      24: invokespecial #21                 // Method "<init>":(Ljava/net/InetAddress;I)V
      27: putstatic     #13                 // Field INET4_ANY_CIDR:Lorg/wildfly/common/net/CidrAddress;
      30: new           #19                 // class org/wildfly/common/net/CidrAddress
      33: dup
      34: getstatic     #68                 // Field org/wildfly/common/net/Inet.INET6_ANY:Ljava/net/Inet6Address;
      37: iconst_0
      38: invokespecial #21                 // Method "<init>":(Ljava/net/InetAddress;I)V
      41: putstatic     #15                 // Field INET6_ANY_CIDR:Lorg/wildfly/common/net/CidrAddress;
      44: return
}
