Compiled from "plotGrid.kt"
public final class org.jetbrains.kotlinx.ggdsl.letsplot.multiplot.PlotGrid {
  private final java.util.List<org.jetbrains.kotlinx.ggdsl.ir.Plot> items;

  private final int nCol;

  private final int cellWidth;

  private final int cellHeight;

  private final int hGap;

  private final int vGap;

  private final boolean fit;

  public org.jetbrains.kotlinx.ggdsl.letsplot.multiplot.PlotGrid(java.util.List<org.jetbrains.kotlinx.ggdsl.ir.Plot>, int, int, int, int, int, boolean);
    Code:
       0: aload_1
       1: ldc           #10                 // String items
       3: invokestatic  #16                 // Method kotlin/jvm/internal/Intrinsics.checkNotNullParameter:(Ljava/lang/Object;Ljava/lang/String;)V
       6: aload_0
       7: invokespecial #19                 // Method java/lang/Object."<init>":()V
      10: aload_0
      11: aload_1
      12: putfield      #22                 // Field items:Ljava/util/List;
      15: aload_0
      16: iload_2
      17: putfield      #26                 // Field nCol:I
      20: aload_0
      21: iload_3
      22: putfield      #29                 // Field cellWidth:I
      25: aload_0
      26: iload         4
      28: putfield      #32                 // Field cellHeight:I
      31: aload_0
      32: iload         5
      34: putfield      #35                 // Field hGap:I
      37: aload_0
      38: iload         6
      40: putfield      #38                 // Field vGap:I
      43: aload_0
      44: iload         7
      46: putfield      #42                 // Field fit:Z
      49: return

  public org.jetbrains.kotlinx.ggdsl.letsplot.multiplot.PlotGrid(java.util.List, int, int, int, int, int, boolean, int, kotlin.jvm.internal.DefaultConstructorMarker);
    Code:
       0: iload         8
       2: bipush        16
       4: iand
       5: ifeq          11
       8: iconst_0
       9: istore        5
      11: iload         8
      13: bipush        32
      15: iand
      16: ifeq          23
      19: bipush        50
      21: istore        6
      23: iload         8
      25: bipush        64
      27: iand
      28: ifeq          34
      31: iconst_0
      32: istore        7
      34: aload_0
      35: aload_1
      36: iload_2
      37: iload_3
      38: iload         4
      40: iload         5
      42: iload         6
      44: iload         7
      46: invokespecial #47                 // Method "<init>":(Ljava/util/List;IIIIIZ)V
      49: return

  public final java.util.List<org.jetbrains.kotlinx.ggdsl.ir.Plot> getItems();
    Code:
       0: aload_0
       1: getfield      #22                 // Field items:Ljava/util/List;
       4: areturn

  public final int getNCol();
    Code:
       0: aload_0
       1: getfield      #26                 // Field nCol:I
       4: ireturn

  public final int getCellWidth();
    Code:
       0: aload_0
       1: getfield      #29                 // Field cellWidth:I
       4: ireturn

  public final int getCellHeight();
    Code:
       0: aload_0
       1: getfield      #32                 // Field cellHeight:I
       4: ireturn

  public final int getHGap();
    Code:
       0: aload_0
       1: getfield      #35                 // Field hGap:I
       4: ireturn

  public final int getVGap();
    Code:
       0: aload_0
       1: getfield      #38                 // Field vGap:I
       4: ireturn

  public final boolean getFit();
    Code:
       0: aload_0
       1: getfield      #42                 // Field fit:Z
       4: ireturn

  public final java.util.List<org.jetbrains.kotlinx.ggdsl.ir.Plot> component1();
    Code:
       0: aload_0
       1: getfield      #22                 // Field items:Ljava/util/List;
       4: areturn

  public final int component2();
    Code:
       0: aload_0
       1: getfield      #26                 // Field nCol:I
       4: ireturn

  public final int component3();
    Code:
       0: aload_0
       1: getfield      #29                 // Field cellWidth:I
       4: ireturn

  public final int component4();
    Code:
       0: aload_0
       1: getfield      #32                 // Field cellHeight:I
       4: ireturn

  public final int component5();
    Code:
       0: aload_0
       1: getfield      #35                 // Field hGap:I
       4: ireturn

  public final int component6();
    Code:
       0: aload_0
       1: getfield      #38                 // Field vGap:I
       4: ireturn

  public final boolean component7();
    Code:
       0: aload_0
       1: getfield      #42                 // Field fit:Z
       4: ireturn

  public final org.jetbrains.kotlinx.ggdsl.letsplot.multiplot.PlotGrid copy(java.util.List<org.jetbrains.kotlinx.ggdsl.ir.Plot>, int, int, int, int, int, boolean);
    Code:
       0: aload_1
       1: ldc           #10                 // String items
       3: invokestatic  #16                 // Method kotlin/jvm/internal/Intrinsics.checkNotNullParameter:(Ljava/lang/Object;Ljava/lang/String;)V
       6: new           #2                  // class org/jetbrains/kotlinx/ggdsl/letsplot/multiplot/PlotGrid
       9: dup
      10: aload_1
      11: iload_2
      12: iload_3
      13: iload         4
      15: iload         5
      17: iload         6
      19: iload         7
      21: invokespecial #47                 // Method "<init>":(Ljava/util/List;IIIIIZ)V
      24: areturn

  public static org.jetbrains.kotlinx.ggdsl.letsplot.multiplot.PlotGrid copy$default(org.jetbrains.kotlinx.ggdsl.letsplot.multiplot.PlotGrid, java.util.List, int, int, int, int, int, boolean, int, java.lang.Object);
    Code:
       0: iload         8
       2: iconst_1
       3: iand
       4: ifeq          12
       7: aload_0
       8: getfield      #22                 // Field items:Ljava/util/List;
      11: astore_1
      12: iload         8
      14: iconst_2
      15: iand
      16: ifeq          24
      19: aload_0
      20: getfield      #26                 // Field nCol:I
      23: istore_2
      24: iload         8
      26: iconst_4
      27: iand
      28: ifeq          36
      31: aload_0
      32: getfield      #29                 // Field cellWidth:I
      35: istore_3
      36: iload         8
      38: bipush        8
      40: iand
      41: ifeq          50
      44: aload_0
      45: getfield      #32                 // Field cellHeight:I
      48: istore        4
      50: iload         8
      52: bipush        16
      54: iand
      55: ifeq          64
      58: aload_0
      59: getfield      #35                 // Field hGap:I
      62: istore        5
      64: iload         8
      66: bipush        32
      68: iand
      69: ifeq          78
      72: aload_0
      73: getfield      #38                 // Field vGap:I
      76: istore        6
      78: iload         8
      80: bipush        64
      82: iand
      83: ifeq          92
      86: aload_0
      87: getfield      #42                 // Field fit:Z
      90: istore        7
      92: aload_0
      93: aload_1
      94: iload_2
      95: iload_3
      96: iload         4
      98: iload         5
     100: iload         6
     102: iload         7
     104: invokevirtual #72                 // Method copy:(Ljava/util/List;IIIIIZ)Lorg/jetbrains/kotlinx/ggdsl/letsplot/multiplot/PlotGrid;
     107: areturn

  public java.lang.String toString();
    Code:
       0: aload_0
       1: getfield      #22                 // Field items:Ljava/util/List;
       4: aload_0
       5: getfield      #26                 // Field nCol:I
       8: aload_0
       9: getfield      #29                 // Field cellWidth:I
      12: aload_0
      13: getfield      #32                 // Field cellHeight:I
      16: aload_0
      17: getfield      #35                 // Field hGap:I
      20: aload_0
      21: getfield      #38                 // Field vGap:I
      24: aload_0
      25: getfield      #42                 // Field fit:Z
      28: invokedynamic #86,  0             // InvokeDynamic #0:makeConcatWithConstants:(Ljava/util/List;IIIIIZ)Ljava/lang/String;
      33: areturn

  public int hashCode();
    Code:
       0: aload_0
       1: getfield      #22                 // Field items:Ljava/util/List;
       4: invokevirtual #89                 // Method java/lang/Object.hashCode:()I
       7: istore_1
       8: iload_1
       9: bipush        31
      11: imul
      12: aload_0
      13: getfield      #26                 // Field nCol:I
      16: invokestatic  #94                 // Method java/lang/Integer.hashCode:(I)I
      19: iadd
      20: istore_1
      21: iload_1
      22: bipush        31
      24: imul
      25: aload_0
      26: getfield      #29                 // Field cellWidth:I
      29: invokestatic  #94                 // Method java/lang/Integer.hashCode:(I)I
      32: iadd
      33: istore_1
      34: iload_1
      35: bipush        31
      37: imul
      38: aload_0
      39: getfield      #32                 // Field cellHeight:I
      42: invokestatic  #94                 // Method java/lang/Integer.hashCode:(I)I
      45: iadd
      46: istore_1
      47: iload_1
      48: bipush        31
      50: imul
      51: aload_0
      52: getfield      #35                 // Field hGap:I
      55: invokestatic  #94                 // Method java/lang/Integer.hashCode:(I)I
      58: iadd
      59: istore_1
      60: iload_1
      61: bipush        31
      63: imul
      64: aload_0
      65: getfield      #38                 // Field vGap:I
      68: invokestatic  #94                 // Method java/lang/Integer.hashCode:(I)I
      71: iadd
      72: istore_1
      73: iload_1
      74: bipush        31
      76: imul
      77: aload_0
      78: getfield      #42                 // Field fit:Z
      81: dup
      82: ifeq          87
      85: pop
      86: iconst_1
      87: iadd
      88: istore_1
      89: iload_1
      90: ireturn

  public boolean equals(java.lang.Object);
    Code:
       0: aload_0
       1: aload_1
       2: if_acmpne     7
       5: iconst_1
       6: ireturn
       7: aload_1
       8: instanceof    #2                  // class org/jetbrains/kotlinx/ggdsl/letsplot/multiplot/PlotGrid
      11: ifne          16
      14: iconst_0
      15: ireturn
      16: aload_1
      17: checkcast     #2                  // class org/jetbrains/kotlinx/ggdsl/letsplot/multiplot/PlotGrid
      20: astore_2
      21: aload_0
      22: getfield      #22                 // Field items:Ljava/util/List;
      25: aload_2
      26: getfield      #22                 // Field items:Ljava/util/List;
      29: invokestatic  #102                // Method kotlin/jvm/internal/Intrinsics.areEqual:(Ljava/lang/Object;Ljava/lang/Object;)Z
      32: ifne          37
      35: iconst_0
      36: ireturn
      37: aload_0
      38: getfield      #26                 // Field nCol:I
      41: aload_2
      42: getfield      #26                 // Field nCol:I
      45: if_icmpeq     50
      48: iconst_0
      49: ireturn
      50: aload_0
      51: getfield      #29                 // Field cellWidth:I
      54: aload_2
      55: getfield      #29                 // Field cellWidth:I
      58: if_icmpeq     63
      61: iconst_0
      62: ireturn
      63: aload_0
      64: getfield      #32                 // Field cellHeight:I
      67: aload_2
      68: getfield      #32                 // Field cellHeight:I
      71: if_icmpeq     76
      74: iconst_0
      75: ireturn
      76: aload_0
      77: getfield      #35                 // Field hGap:I
      80: aload_2
      81: getfield      #35                 // Field hGap:I
      84: if_icmpeq     89
      87: iconst_0
      88: ireturn
      89: aload_0
      90: getfield      #38                 // Field vGap:I
      93: aload_2
      94: getfield      #38                 // Field vGap:I
      97: if_icmpeq     102
     100: iconst_0
     101: ireturn
     102: aload_0
     103: getfield      #42                 // Field fit:Z
     106: aload_2
     107: getfield      #42                 // Field fit:Z
     110: if_icmpeq     115
     113: iconst_0
     114: ireturn
     115: iconst_1
     116: ireturn
}
