Compiled from "ContextClassLoaderLogContextSelector.java"
class org.jboss.logmanager.ContextClassLoaderLogContextSelector$1 implements java.security.PrivilegedAction<org.jboss.logmanager.LogContext> {
  final org.jboss.logmanager.ContextClassLoaderLogContextSelector this$0;

  org.jboss.logmanager.ContextClassLoaderLogContextSelector$1(org.jboss.logmanager.ContextClassLoaderLogContextSelector);
    Code:
       0: aload_0
       1: aload_1
       2: putfield      #1                  // Field this$0:Lorg/jboss/logmanager/ContextClassLoaderLogContextSelector;
       5: aload_0
       6: invokespecial #2                  // Method java/lang/Object."<init>":()V
       9: return

  public org.jboss.logmanager.LogContext run();
    Code:
       0: invokestatic  #3                  // Method java/lang/Thread.currentThread:()Ljava/lang/Thread;
       3: invokevirtual #4                  // Method java/lang/Thread.getContextClassLoader:()Ljava/lang/ClassLoader;
       6: astore_1
       7: aload_1
       8: ifnull        34
      11: aload_0
      12: getfield      #1                  // Field this$0:Lorg/jboss/logmanager/ContextClassLoaderLogContextSelector;
      15: invokestatic  #5                  // Method org/jboss/logmanager/ContextClassLoaderLogContextSelector.access$000:(Lorg/jboss/logmanager/ContextClassLoaderLogContextSelector;)Ljava/util/concurrent/ConcurrentMap;
      18: aload_1
      19: invokeinterface #6,  2            // InterfaceMethod java/util/concurrent/ConcurrentMap.get:(Ljava/lang/Object;)Ljava/lang/Object;
      24: checkcast     #7                  // class org/jboss/logmanager/LogContext
      27: astore_2
      28: aload_2
      29: ifnull        34
      32: aload_2
      33: areturn
      34: aload_0
      35: getfield      #1                  // Field this$0:Lorg/jboss/logmanager/ContextClassLoaderLogContextSelector;
      38: invokestatic  #8                  // Method org/jboss/logmanager/ContextClassLoaderLogContextSelector.access$100:(Lorg/jboss/logmanager/ContextClassLoaderLogContextSelector;)Lorg/jboss/logmanager/LogContextSelector;
      41: invokeinterface #9,  1            // InterfaceMethod org/jboss/logmanager/LogContextSelector.getLogContext:()Lorg/jboss/logmanager/LogContext;
      46: areturn

  public java.lang.Object run();
    Code:
       0: aload_0
       1: invokevirtual #10                 // Method run:()Lorg/jboss/logmanager/LogContext;
       4: areturn
}
