Compiled from "CopyOnWriteWeakMap.java"
final class org.jboss.logmanager.CopyOnWriteWeakMap$Node<K, V> extends java.lang.ref.WeakReference<V> {
  private final K key;

  org.jboss.logmanager.CopyOnWriteWeakMap$Node(K, V, java.lang.ref.ReferenceQueue<? super V>);
    Code:
       0: aload_0
       1: aload_2
       2: aload_3
       3: invokespecial #1                  // Method java/lang/ref/WeakReference."<init>":(Ljava/lang/Object;Ljava/lang/ref/ReferenceQueue;)V
       6: aload_0
       7: aload_1
       8: putfield      #2                  // Field key:Ljava/lang/Object;
      11: return

  K getKey();
    Code:
       0: aload_0
       1: getfield      #2                  // Field key:Ljava/lang/Object;
       4: areturn
}
