Compiled from "LogContext.java"
class org.jboss.logmanager.LogContext$2 implements java.util.Enumeration<java.lang.String> {
  java.lang.String next;

  final java.util.Iterator val$iter;

  final org.jboss.logmanager.LogContext this$0;

  org.jboss.logmanager.LogContext$2(org.jboss.logmanager.LogContext, java.util.Iterator);
    Code:
       0: aload_0
       1: aload_1
       2: putfield      #1                  // Field this$0:Lorg/jboss/logmanager/LogContext;
       5: aload_0
       6: aload_2
       7: putfield      #2                  // Field val$iter:Ljava/util/Iterator;
      10: aload_0
      11: invokespecial #3                  // Method java/lang/Object."<init>":()V
      14: aload_0
      15: aconst_null
      16: putfield      #4                  // Field next:Ljava/lang/String;
      19: return

  public boolean hasMoreElements();
    Code:
       0: aload_0
       1: getfield      #4                  // Field next:Ljava/lang/String;
       4: ifnonnull     67
       7: aload_0
       8: getfield      #2                  // Field val$iter:Ljava/util/Iterator;
      11: invokeinterface #5,  1            // InterfaceMethod java/util/Iterator.hasNext:()Z
      16: ifeq          65
      19: aload_0
      20: getfield      #2                  // Field val$iter:Ljava/util/Iterator;
      23: invokeinterface #6,  1            // InterfaceMethod java/util/Iterator.next:()Ljava/lang/Object;
      28: checkcast     #7                  // class java/util/Map$Entry
      31: astore_1
      32: aload_1
      33: invokeinterface #8,  1            // InterfaceMethod java/util/Map$Entry.getValue:()Ljava/lang/Object;
      38: checkcast     #9                  // class java/util/concurrent/atomic/AtomicInteger
      41: invokevirtual #10                 // Method java/util/concurrent/atomic/AtomicInteger.get:()I
      44: ifle          62
      47: aload_0
      48: aload_1
      49: invokeinterface #11,  1           // InterfaceMethod java/util/Map$Entry.getKey:()Ljava/lang/Object;
      54: checkcast     #12                 // class java/lang/String
      57: putfield      #4                  // Field next:Ljava/lang/String;
      60: iconst_1
      61: ireturn
      62: goto          0
      65: iconst_0
      66: ireturn
      67: aload_0
      68: getfield      #4                  // Field next:Ljava/lang/String;
      71: ifnull        78
      74: iconst_1
      75: goto          79
      78: iconst_0
      79: ireturn

  public java.lang.String nextElement();
    Code:
       0: aload_0
       1: invokevirtual #13                 // Method hasMoreElements:()Z
       4: ifne          15
       7: new           #14                 // class java/util/NoSuchElementException
      10: dup
      11: invokespecial #15                 // Method java/util/NoSuchElementException."<init>":()V
      14: athrow
      15: aload_0
      16: getfield      #4                  // Field next:Ljava/lang/String;
      19: astore_1
      20: aload_0
      21: aconst_null
      22: putfield      #4                  // Field next:Ljava/lang/String;
      25: aload_1
      26: areturn
      27: astore_2
      28: aload_0
      29: aconst_null
      30: putfield      #4                  // Field next:Ljava/lang/String;
      33: aload_2
      34: athrow
    Exception table:
       from    to  target type
          15    20    27   any
          27    28    27   any

  public java.lang.Object nextElement();
    Code:
       0: aload_0
       1: invokevirtual #16                 // Method nextElement:()Ljava/lang/String;
       4: areturn
}
