Compiled from "LogContext.java"
final class org.jboss.logmanager.LogContext$WeakLevelRef extends java.lang.ref.WeakReference<java.util.logging.Level> implements org.jboss.logmanager.LogContext$LevelRef {
  private org.jboss.logmanager.LogContext$WeakLevelRef(java.util.logging.Level);
    Code:
       0: aload_0
       1: aload_1
       2: invokespecial #2                  // Method java/lang/ref/WeakReference."<init>":(Ljava/lang/Object;)V
       5: return

  public java.util.logging.Level get();
    Code:
       0: aload_0
       1: invokespecial #3                  // Method java/lang/ref/WeakReference.get:()Ljava/lang/Object;
       4: checkcast     #4                  // class java/util/logging/Level
       7: areturn

  org.jboss.logmanager.LogContext$WeakLevelRef(java.util.logging.Level, org.jboss.logmanager.LogContext$1);
    Code:
       0: aload_0
       1: aload_1
       2: invokespecial #1                  // Method "<init>":(Ljava/util/logging/Level;)V
       5: return
}
