Compiled from "SearchItems.java"
public class hudson.search.SearchItems {
  public hudson.search.SearchItems();
    Code:
       0: aload_0
       1: invokespecial #1                  // Method java/lang/Object."<init>":()V
       4: return

  public static hudson.search.SearchItem create(java.lang.String, java.lang.String);
    Code:
       0: aload_0
       1: aload_1
       2: getstatic     #2                  // Field hudson/search/SearchIndex.EMPTY:Lhudson/search/SearchIndex;
       5: invokestatic  #3                  // Method create:(Ljava/lang/String;Ljava/lang/String;Lhudson/search/SearchIndex;)Lhudson/search/SearchItem;
       8: areturn

  public static hudson.search.SearchItem create(java.lang.String, java.lang.String, hudson.search.SearchIndex);
    Code:
       0: new           #4                  // class hudson/search/SearchItems$1
       3: dup
       4: aload_0
       5: aload_1
       6: aload_2
       7: invokespecial #5                  // Method hudson/search/SearchItems$1."<init>":(Ljava/lang/String;Ljava/lang/String;Lhudson/search/SearchIndex;)V
      10: areturn

  public static hudson.search.SearchItem create(java.lang.String, java.lang.String, hudson.search.SearchableModelObject);
    Code:
       0: new           #6                  // class hudson/search/SearchItems$2
       3: dup
       4: aload_0
       5: aload_1
       6: aload_2
       7: invokespecial #7                  // Method hudson/search/SearchItems$2."<init>":(Ljava/lang/String;Ljava/lang/String;Lhudson/search/SearchableModelObject;)V
      10: areturn
}
