Compiled from "ComparingPropertySorter.java"
public class com.thoughtworks.xstream.converters.javabean.ComparingPropertySorter implements com.thoughtworks.xstream.converters.javabean.PropertySorter {
  private final java.util.Comparator comparator;

  public com.thoughtworks.xstream.converters.javabean.ComparingPropertySorter(java.util.Comparator);
    Code:
       0: aload_0
       1: invokespecial #1                  // Method java/lang/Object."<init>":()V
       4: aload_0
       5: aload_1
       6: putfield      #2                  // Field comparator:Ljava/util/Comparator;
       9: return

  public java.util.Map sort(java.lang.Class, java.util.Map);
    Code:
       0: new           #3                  // class java/util/TreeMap
       3: dup
       4: aload_0
       5: getfield      #2                  // Field comparator:Ljava/util/Comparator;
       8: invokespecial #4                  // Method java/util/TreeMap."<init>":(Ljava/util/Comparator;)V
      11: astore_3
      12: aload_3
      13: aload_2
      14: invokevirtual #5                  // Method java/util/TreeMap.putAll:(Ljava/util/Map;)V
      17: aload_3
      18: areturn
}
