Compiled from "SubjectDNMapping.java"
public class org.jboss.security.auth.certs.SubjectDNMapping implements org.jboss.security.CertificatePrincipal {
  public org.jboss.security.auth.certs.SubjectDNMapping();
    Code:
       0: aload_0
       1: invokespecial #1                  // Method java/lang/Object."<init>":()V
       4: return

  public java.security.Principal toPrincipal(java.security.cert.X509Certificate[]);
    Code:
       0: aload_1
       1: iconst_0
       2: aaload
       3: invokevirtual #2                  // Method java/security/cert/X509Certificate.getSubjectDN:()Ljava/security/Principal;
       6: astore_2
       7: aload_2
       8: instanceof    #3                  // class java/io/Serializable
      11: ifne          30
      14: aload_2
      15: invokeinterface #4,  1            // InterfaceMethod java/security/Principal.getName:()Ljava/lang/String;
      20: astore_3
      21: new           #5                  // class org/jboss/security/SimplePrincipal
      24: dup
      25: aload_3
      26: invokespecial #6                  // Method org/jboss/security/SimplePrincipal."<init>":(Ljava/lang/String;)V
      29: astore_2
      30: aload_2
      31: areturn

  public java.security.Principal toPrinicipal(java.security.cert.X509Certificate[]);
    Code:
       0: aload_0
       1: aload_1
       2: invokevirtual #7                  // Method toPrincipal:([Ljava/security/cert/X509Certificate;)Ljava/security/Principal;
       5: areturn
}
