Compiled from "LdapEncoder.java"
public final class org.springframework.ldap.support.LdapEncoder {
  private static final int HEX;

  private static java.lang.String[] NAME_ESCAPE_TABLE;

  private static java.lang.String[] FILTER_ESCAPE_TABLE;

  private static final int RFC2849_MAX_BASE64_CHARS_PER_LINE;

  private org.springframework.ldap.support.LdapEncoder();
    Code:
       0: aload_0
       1: invokespecial #1                  // Method java/lang/Object."<init>":()V
       4: return

  protected static java.lang.String toTwoCharHex(char);
    Code:
       0: iload_0
       1: invokestatic  #2                  // Method java/lang/Integer.toHexString:(I)Ljava/lang/String;
       4: invokevirtual #3                  // Method java/lang/String.toUpperCase:()Ljava/lang/String;
       7: astore_1
       8: aload_1
       9: invokevirtual #4                  // Method java/lang/String.length:()I
      12: iconst_1
      13: if_icmple     18
      16: aload_1
      17: areturn
      18: new           #5                  // class java/lang/StringBuilder
      21: dup
      22: invokespecial #6                  // Method java/lang/StringBuilder."<init>":()V
      25: ldc           #7                  // String 0
      27: invokevirtual #8                  // Method java/lang/StringBuilder.append:(Ljava/lang/String;)Ljava/lang/StringBuilder;
      30: aload_1
      31: invokevirtual #8                  // Method java/lang/StringBuilder.append:(Ljava/lang/String;)Ljava/lang/StringBuilder;
      34: invokevirtual #9                  // Method java/lang/StringBuilder.toString:()Ljava/lang/String;
      37: areturn

  public static java.lang.String filterEncode(java.lang.String);
    Code:
       0: aload_0
       1: ifnonnull     6
       4: aconst_null
       5: areturn
       6: new           #5                  // class java/lang/StringBuilder
       9: dup
      10: aload_0
      11: invokevirtual #4                  // Method java/lang/String.length:()I
      14: iconst_2
      15: imul
      16: invokespecial #10                 // Method java/lang/StringBuilder."<init>":(I)V
      19: astore_1
      20: aload_0
      21: invokevirtual #4                  // Method java/lang/String.length:()I
      24: istore_2
      25: iconst_0
      26: istore_3
      27: iload_3
      28: iload_2
      29: if_icmpge     75
      32: aload_0
      33: iload_3
      34: invokevirtual #11                 // Method java/lang/String.charAt:(I)C
      37: istore        4
      39: iload         4
      41: getstatic     #12                 // Field FILTER_ESCAPE_TABLE:[Ljava/lang/String;
      44: arraylength
      45: if_icmpge     62
      48: aload_1
      49: getstatic     #12                 // Field FILTER_ESCAPE_TABLE:[Ljava/lang/String;
      52: iload         4
      54: aaload
      55: invokevirtual #8                  // Method java/lang/StringBuilder.append:(Ljava/lang/String;)Ljava/lang/StringBuilder;
      58: pop
      59: goto          69
      62: aload_1
      63: iload         4
      65: invokevirtual #13                 // Method java/lang/StringBuilder.append:(C)Ljava/lang/StringBuilder;
      68: pop
      69: iinc          3, 1
      72: goto          27
      75: aload_1
      76: invokevirtual #9                  // Method java/lang/StringBuilder.toString:()Ljava/lang/String;
      79: areturn

  public static java.lang.String nameEncode(java.lang.String);
    Code:
       0: aload_0
       1: ifnonnull     6
       4: aconst_null
       5: areturn
       6: new           #5                  // class java/lang/StringBuilder
       9: dup
      10: aload_0
      11: invokevirtual #4                  // Method java/lang/String.length:()I
      14: iconst_2
      15: imul
      16: invokespecial #10                 // Method java/lang/StringBuilder."<init>":(I)V
      19: astore_1
      20: aload_0
      21: invokevirtual #4                  // Method java/lang/String.length:()I
      24: istore_2
      25: iload_2
      26: iconst_1
      27: isub
      28: istore_3
      29: iconst_0
      30: istore        4
      32: iload         4
      34: iload_2
      35: if_icmpge     119
      38: aload_0
      39: iload         4
      41: invokevirtual #11                 // Method java/lang/String.charAt:(I)C
      44: istore        5
      46: iload         5
      48: bipush        32
      50: if_icmpne     74
      53: iload         4
      55: ifeq          64
      58: iload         4
      60: iload_3
      61: if_icmpne     74
      64: aload_1
      65: ldc           #14                 // String \\
      67: invokevirtual #8                  // Method java/lang/StringBuilder.append:(Ljava/lang/String;)Ljava/lang/StringBuilder;
      70: pop
      71: goto          113
      74: iload         5
      76: getstatic     #15                 // Field NAME_ESCAPE_TABLE:[Ljava/lang/String;
      79: arraylength
      80: if_icmpge     106
      83: getstatic     #15                 // Field NAME_ESCAPE_TABLE:[Ljava/lang/String;
      86: iload         5
      88: aaload
      89: astore        6
      91: aload         6
      93: ifnull        106
      96: aload_1
      97: aload         6
      99: invokevirtual #8                  // Method java/lang/StringBuilder.append:(Ljava/lang/String;)Ljava/lang/StringBuilder;
     102: pop
     103: goto          113
     106: aload_1
     107: iload         5
     109: invokevirtual #13                 // Method java/lang/StringBuilder.append:(C)Ljava/lang/StringBuilder;
     112: pop
     113: iinc          4, 1
     116: goto          32
     119: aload_1
     120: invokevirtual #9                  // Method java/lang/StringBuilder.toString:()Ljava/lang/String;
     123: areturn

  public static java.lang.String nameDecode(java.lang.String) throws org.springframework.ldap.BadLdapGrammarException;
    Code:
       0: aload_0
       1: ifnonnull     6
       4: aconst_null
       5: areturn
       6: new           #5                  // class java/lang/StringBuilder
       9: dup
      10: aload_0
      11: invokevirtual #4                  // Method java/lang/String.length:()I
      14: invokespecial #10                 // Method java/lang/StringBuilder."<init>":(I)V
      17: astore_1
      18: iconst_0
      19: istore_2
      20: iload_2
      21: aload_0
      22: invokevirtual #4                  // Method java/lang/String.length:()I
      25: if_icmpge     258
      28: aload_0
      29: iload_2
      30: invokevirtual #11                 // Method java/lang/String.charAt:(I)C
      33: istore_3
      34: iload_3
      35: bipush        92
      37: if_icmpne     246
      40: aload_0
      41: invokevirtual #4                  // Method java/lang/String.length:()I
      44: iload_2
      45: iconst_1
      46: iadd
      47: if_icmpgt     60
      50: new           #16                 // class org/springframework/ldap/BadLdapGrammarException
      53: dup
      54: ldc           #17                 // String Unexpected end of value unterminated \'\\\'
      56: invokespecial #18                 // Method org/springframework/ldap/BadLdapGrammarException."<init>":(Ljava/lang/String;)V
      59: athrow
      60: aload_0
      61: iload_2
      62: iconst_1
      63: iadd
      64: invokevirtual #11                 // Method java/lang/String.charAt:(I)C
      67: istore        4
      69: iload         4
      71: bipush        44
      73: if_icmpeq     139
      76: iload         4
      78: bipush        61
      80: if_icmpeq     139
      83: iload         4
      85: bipush        43
      87: if_icmpeq     139
      90: iload         4
      92: bipush        60
      94: if_icmpeq     139
      97: iload         4
      99: bipush        62
     101: if_icmpeq     139
     104: iload         4
     106: bipush        35
     108: if_icmpeq     139
     111: iload         4
     113: bipush        59
     115: if_icmpeq     139
     118: iload         4
     120: bipush        92
     122: if_icmpeq     139
     125: iload         4
     127: bipush        34
     129: if_icmpeq     139
     132: iload         4
     134: bipush        32
     136: if_icmpne     152
     139: aload_1
     140: iload         4
     142: invokevirtual #13                 // Method java/lang/StringBuilder.append:(C)Ljava/lang/StringBuilder;
     145: pop
     146: iinc          2, 2
     149: goto          243
     152: aload_0
     153: invokevirtual #4                  // Method java/lang/String.length:()I
     156: iload_2
     157: iconst_2
     158: iadd
     159: if_icmpgt     195
     162: new           #16                 // class org/springframework/ldap/BadLdapGrammarException
     165: dup
     166: new           #5                  // class java/lang/StringBuilder
     169: dup
     170: invokespecial #6                  // Method java/lang/StringBuilder."<init>":()V
     173: ldc           #19                 // String Unexpected end of value expected special or hex, found \'
     175: invokevirtual #8                  // Method java/lang/StringBuilder.append:(Ljava/lang/String;)Ljava/lang/StringBuilder;
     178: iload         4
     180: invokevirtual #13                 // Method java/lang/StringBuilder.append:(C)Ljava/lang/StringBuilder;
     183: ldc           #20                 // String \'
     185: invokevirtual #8                  // Method java/lang/StringBuilder.append:(Ljava/lang/String;)Ljava/lang/StringBuilder;
     188: invokevirtual #9                  // Method java/lang/StringBuilder.toString:()Ljava/lang/String;
     191: invokespecial #18                 // Method org/springframework/ldap/BadLdapGrammarException."<init>":(Ljava/lang/String;)V
     194: athrow
     195: new           #5                  // class java/lang/StringBuilder
     198: dup
     199: invokespecial #6                  // Method java/lang/StringBuilder."<init>":()V
     202: ldc           #21                 // String
     204: invokevirtual #8                  // Method java/lang/StringBuilder.append:(Ljava/lang/String;)Ljava/lang/StringBuilder;
     207: iload         4
     209: invokevirtual #13                 // Method java/lang/StringBuilder.append:(C)Ljava/lang/StringBuilder;
     212: aload_0
     213: iload_2
     214: iconst_2
     215: iadd
     216: invokevirtual #11                 // Method java/lang/String.charAt:(I)C
     219: invokevirtual #13                 // Method java/lang/StringBuilder.append:(C)Ljava/lang/StringBuilder;
     222: invokevirtual #9                  // Method java/lang/StringBuilder.toString:()Ljava/lang/String;
     225: astore        5
     227: aload_1
     228: aload         5
     230: bipush        16
     232: invokestatic  #23                 // Method java/lang/Integer.parseInt:(Ljava/lang/String;I)I
     235: i2c
     236: invokevirtual #13                 // Method java/lang/StringBuilder.append:(C)Ljava/lang/StringBuilder;
     239: pop
     240: iinc          2, 3
     243: goto          255
     246: aload_1
     247: iload_3
     248: invokevirtual #13                 // Method java/lang/StringBuilder.append:(C)Ljava/lang/StringBuilder;
     251: pop
     252: iinc          2, 1
     255: goto          20
     258: aload_1
     259: invokevirtual #9                  // Method java/lang/StringBuilder.toString:()Ljava/lang/String;
     262: areturn

  public static java.lang.String printBase64Binary(byte[]);
    Code:
       0: aload_0
       1: ldc           #24                 // String val must not be null!
       3: invokestatic  #25                 // Method org/springframework/util/Assert.notNull:(Ljava/lang/Object;Ljava/lang/String;)V
       6: aload_0
       7: invokestatic  #26                 // Method javax/xml/bind/DatatypeConverter.printBase64Binary:([B)Ljava/lang/String;
      10: astore_1
      11: aload_1
      12: invokevirtual #4                  // Method java/lang/String.length:()I
      15: istore_2
      16: new           #5                  // class java/lang/StringBuilder
      19: dup
      20: iload_2
      21: iload_2
      22: bipush        76
      24: idiv
      25: iadd
      26: invokespecial #10                 // Method java/lang/StringBuilder."<init>":(I)V
      29: astore_3
      30: iconst_0
      31: istore        4
      33: iload_2
      34: istore        5
      36: iload         4
      38: iload         5
      40: if_icmpge     84
      43: aload_3
      44: aload_1
      45: iload         4
      47: invokevirtual #11                 // Method java/lang/String.charAt:(I)C
      50: invokevirtual #13                 // Method java/lang/StringBuilder.append:(C)Ljava/lang/StringBuilder;
      53: pop
      54: iload         4
      56: iconst_1
      57: iadd
      58: bipush        76
      60: irem
      61: ifne          78
      64: aload_3
      65: bipush        10
      67: invokevirtual #13                 // Method java/lang/StringBuilder.append:(C)Ljava/lang/StringBuilder;
      70: pop
      71: aload_3
      72: bipush        32
      74: invokevirtual #13                 // Method java/lang/StringBuilder.append:(C)Ljava/lang/StringBuilder;
      77: pop
      78: iinc          4, 1
      81: goto          36
      84: aload_3
      85: invokevirtual #9                  // Method java/lang/StringBuilder.toString:()Ljava/lang/String;
      88: areturn

  public static byte[] parseBase64Binary(java.lang.String);
    Code:
       0: aload_0
       1: ldc           #24                 // String val must not be null!
       3: invokestatic  #25                 // Method org/springframework/util/Assert.notNull:(Ljava/lang/Object;Ljava/lang/String;)V
       6: aload_0
       7: invokevirtual #4                  // Method java/lang/String.length:()I
      10: istore_1
      11: new           #5                  // class java/lang/StringBuilder
      14: dup
      15: iload_1
      16: invokespecial #10                 // Method java/lang/StringBuilder."<init>":(I)V
      19: astore_2
      20: iconst_0
      21: istore_3
      22: iload_1
      23: istore        4
      25: iload_3
      26: iload         4
      28: if_icmpge     84
      31: aload_0
      32: iload_3
      33: invokevirtual #11                 // Method java/lang/String.charAt:(I)C
      36: istore        5
      38: iload         5
      40: bipush        10
      42: if_icmpne     71
      45: iload_3
      46: iconst_1
      47: iadd
      48: iload         4
      50: if_icmpge     78
      53: aload_0
      54: iload_3
      55: iconst_1
      56: iadd
      57: invokevirtual #11                 // Method java/lang/String.charAt:(I)C
      60: bipush        32
      62: if_icmpne     78
      65: iinc          3, 1
      68: goto          78
      71: aload_2
      72: iload         5
      74: invokevirtual #13                 // Method java/lang/StringBuilder.append:(C)Ljava/lang/StringBuilder;
      77: pop
      78: iinc          3, 1
      81: goto          25
      84: aload_2
      85: invokevirtual #9                  // Method java/lang/StringBuilder.toString:()Ljava/lang/String;
      88: invokestatic  #27                 // Method javax/xml/bind/DatatypeConverter.parseBase64Binary:(Ljava/lang/String;)[B
      91: areturn

  static {};
    Code:
       0: bipush        96
       2: anewarray     #28                 // class java/lang/String
       5: putstatic     #15                 // Field NAME_ESCAPE_TABLE:[Ljava/lang/String;
       8: bipush        93
      10: anewarray     #28                 // class java/lang/String
      13: putstatic     #12                 // Field FILTER_ESCAPE_TABLE:[Ljava/lang/String;
      16: iconst_0
      17: istore_0
      18: iload_0
      19: bipush        32
      21: if_icmpge     59
      24: getstatic     #15                 // Field NAME_ESCAPE_TABLE:[Ljava/lang/String;
      27: iload_0
      28: new           #5                  // class java/lang/StringBuilder
      31: dup
      32: invokespecial #6                  // Method java/lang/StringBuilder."<init>":()V
      35: ldc           #29                 // String \\
      37: invokevirtual #8                  // Method java/lang/StringBuilder.append:(Ljava/lang/String;)Ljava/lang/StringBuilder;
      40: iload_0
      41: invokestatic  #30                 // Method toTwoCharHex:(C)Ljava/lang/String;
      44: invokevirtual #8                  // Method java/lang/StringBuilder.append:(Ljava/lang/String;)Ljava/lang/StringBuilder;
      47: invokevirtual #9                  // Method java/lang/StringBuilder.toString:()Ljava/lang/String;
      50: aastore
      51: iload_0
      52: iconst_1
      53: iadd
      54: i2c
      55: istore_0
      56: goto          18
      59: getstatic     #15                 // Field NAME_ESCAPE_TABLE:[Ljava/lang/String;
      62: bipush        35
      64: ldc           #31                 // String \\#
      66: aastore
      67: getstatic     #15                 // Field NAME_ESCAPE_TABLE:[Ljava/lang/String;
      70: bipush        44
      72: ldc           #32                 // String \\,
      74: aastore
      75: getstatic     #15                 // Field NAME_ESCAPE_TABLE:[Ljava/lang/String;
      78: bipush        59
      80: ldc           #33                 // String \\;
      82: aastore
      83: getstatic     #15                 // Field NAME_ESCAPE_TABLE:[Ljava/lang/String;
      86: bipush        61
      88: ldc           #34                 // String \\=
      90: aastore
      91: getstatic     #15                 // Field NAME_ESCAPE_TABLE:[Ljava/lang/String;
      94: bipush        43
      96: ldc           #35                 // String \\+
      98: aastore
      99: getstatic     #15                 // Field NAME_ESCAPE_TABLE:[Ljava/lang/String;
     102: bipush        60
     104: ldc           #36                 // String \\<
     106: aastore
     107: getstatic     #15                 // Field NAME_ESCAPE_TABLE:[Ljava/lang/String;
     110: bipush        62
     112: ldc           #37                 // String \\>
     114: aastore
     115: getstatic     #15                 // Field NAME_ESCAPE_TABLE:[Ljava/lang/String;
     118: bipush        34
     120: ldc           #38                 // String \\\"
     122: aastore
     123: getstatic     #15                 // Field NAME_ESCAPE_TABLE:[Ljava/lang/String;
     126: bipush        92
     128: ldc           #39                 // String \\\\
     130: aastore
     131: iconst_0
     132: istore_0
     133: iload_0
     134: getstatic     #12                 // Field FILTER_ESCAPE_TABLE:[Ljava/lang/String;
     137: arraylength
     138: if_icmpge     158
     141: getstatic     #12                 // Field FILTER_ESCAPE_TABLE:[Ljava/lang/String;
     144: iload_0
     145: iload_0
     146: invokestatic  #40                 // Method java/lang/String.valueOf:(C)Ljava/lang/String;
     149: aastore
     150: iload_0
     151: iconst_1
     152: iadd
     153: i2c
     154: istore_0
     155: goto          133
     158: getstatic     #12                 // Field FILTER_ESCAPE_TABLE:[Ljava/lang/String;
     161: bipush        42
     163: ldc           #41                 // String \\2a
     165: aastore
     166: getstatic     #12                 // Field FILTER_ESCAPE_TABLE:[Ljava/lang/String;
     169: bipush        40
     171: ldc           #42                 // String \\28
     173: aastore
     174: getstatic     #12                 // Field FILTER_ESCAPE_TABLE:[Ljava/lang/String;
     177: bipush        41
     179: ldc           #43                 // String \\29
     181: aastore
     182: getstatic     #12                 // Field FILTER_ESCAPE_TABLE:[Ljava/lang/String;
     185: bipush        92
     187: ldc           #44                 // String \\5c
     189: aastore
     190: getstatic     #12                 // Field FILTER_ESCAPE_TABLE:[Ljava/lang/String;
     193: iconst_0
     194: ldc           #45                 // String \\00
     196: aastore
     197: return
}
