Compiled from "DefaultConfiguration.java"
public class org.apache.logging.log4j.core.config.DefaultConfiguration extends org.apache.logging.log4j.core.config.AbstractConfiguration {
  public static final java.lang.String DEFAULT_NAME;

  public static final java.lang.String DEFAULT_LEVEL;

  public static final java.lang.String DEFAULT_PATTERN;

  public org.apache.logging.log4j.core.config.DefaultConfiguration();
    Code:
       0: aload_0
       1: aconst_null
       2: getstatic     #1                  // Field org/apache/logging/log4j/core/config/ConfigurationSource.NULL_SOURCE:Lorg/apache/logging/log4j/core/config/ConfigurationSource;
       5: invokespecial #2                  // Method org/apache/logging/log4j/core/config/AbstractConfiguration."<init>":(Lorg/apache/logging/log4j/core/LoggerContext;Lorg/apache/logging/log4j/core/config/ConfigurationSource;)V
       8: aload_0
       9: invokevirtual #3                  // Method setToDefault:()V
      12: return

  protected void doConfigure();
    Code:
       0: return
}
