Compiled from "LabelToNodeMap.java"
public class org.apache.jena.sparql.util.LabelToNodeMap {
  java.util.Map<java.lang.String, org.apache.jena.graph.Node> bNodeLabels;

  boolean generateVars;

  org.apache.jena.sparql.core.VarAlloc allocator;

  public static org.apache.jena.sparql.util.LabelToNodeMap createBNodeMap();
    Code:
       0: new           #1                  // class org/apache/jena/sparql/util/LabelToNodeMap
       3: dup
       4: iconst_0
       5: aconst_null
       6: invokespecial #2                  // Method "<init>":(ZLorg/apache/jena/sparql/core/VarAlloc;)V
       9: areturn

  public static org.apache.jena.sparql.util.LabelToNodeMap createVarMap();
    Code:
       0: new           #1                  // class org/apache/jena/sparql/util/LabelToNodeMap
       3: dup
       4: iconst_1
       5: new           #3                  // class org/apache/jena/sparql/core/VarAlloc
       8: dup
       9: ldc           #5                  // String ?
      11: invokespecial #6                  // Method org/apache/jena/sparql/core/VarAlloc."<init>":(Ljava/lang/String;)V
      14: invokespecial #2                  // Method "<init>":(ZLorg/apache/jena/sparql/core/VarAlloc;)V
      17: areturn

  private org.apache.jena.sparql.util.LabelToNodeMap(boolean, org.apache.jena.sparql.core.VarAlloc);
    Code:
       0: aload_0
       1: invokespecial #7                  // Method java/lang/Object."<init>":()V
       4: aload_0
       5: new           #8                  // class java/util/HashMap
       8: dup
       9: invokespecial #9                  // Method java/util/HashMap."<init>":()V
      12: putfield      #10                 // Field bNodeLabels:Ljava/util/Map;
      15: aload_0
      16: iconst_0
      17: putfield      #11                 // Field generateVars:Z
      20: aload_0
      21: aconst_null
      22: putfield      #12                 // Field allocator:Lorg/apache/jena/sparql/core/VarAlloc;
      25: aload_0
      26: iload_1
      27: putfield      #11                 // Field generateVars:Z
      30: aload_0
      31: aload_2
      32: putfield      #12                 // Field allocator:Lorg/apache/jena/sparql/core/VarAlloc;
      35: return

  public java.util.Set<java.lang.String> getLabels();
    Code:
       0: aload_0
       1: getfield      #10                 // Field bNodeLabels:Ljava/util/Map;
       4: invokeinterface #13,  1           // InterfaceMethod java/util/Map.keySet:()Ljava/util/Set;
       9: areturn

  public org.apache.jena.graph.Node asNode(java.lang.String);
    Code:
       0: aload_0
       1: getfield      #10                 // Field bNodeLabels:Ljava/util/Map;
       4: aload_1
       5: invokeinterface #14,  2           // InterfaceMethod java/util/Map.get:(Ljava/lang/Object;)Ljava/lang/Object;
      10: checkcast     #15                 // class org/apache/jena/graph/Node
      13: astore_2
      14: aload_2
      15: ifnull        20
      18: aload_2
      19: areturn
      20: aload_0
      21: invokevirtual #16                 // Method allocNode:()Lorg/apache/jena/graph/Node;
      24: astore_2
      25: aload_0
      26: getfield      #10                 // Field bNodeLabels:Ljava/util/Map;
      29: aload_1
      30: aload_2
      31: invokeinterface #17,  3           // InterfaceMethod java/util/Map.put:(Ljava/lang/Object;Ljava/lang/Object;)Ljava/lang/Object;
      36: pop
      37: aload_2
      38: areturn

  public org.apache.jena.graph.Node allocNode();
    Code:
       0: aload_0
       1: getfield      #11                 // Field generateVars:Z
       4: ifeq          12
       7: aload_0
       8: invokespecial #18                 // Method allocAnonVariable:()Lorg/apache/jena/graph/Node;
      11: areturn
      12: invokestatic  #19                 // Method org/apache/jena/graph/NodeFactory.createBlankNode:()Lorg/apache/jena/graph/Node;
      15: areturn

  private org.apache.jena.graph.Node allocAnonVariable();
    Code:
       0: aload_0
       1: getfield      #12                 // Field allocator:Lorg/apache/jena/sparql/core/VarAlloc;
       4: invokevirtual #20                 // Method org/apache/jena/sparql/core/VarAlloc.allocVar:()Lorg/apache/jena/sparql/core/Var;
       7: areturn

  public void clear();
    Code:
       0: aload_0
       1: getfield      #10                 // Field bNodeLabels:Ljava/util/Map;
       4: invokeinterface #21,  1           // InterfaceMethod java/util/Map.clear:()V
       9: return
}
