Compiled from "MappedLoader.java"
public class org.apache.jena.sparql.util.MappedLoader {
  static java.util.Map<java.lang.String, java.lang.String> uriMap;

  public org.apache.jena.sparql.util.MappedLoader();
    Code:
       0: aload_0
       1: invokespecial #1                  // Method java/lang/Object."<init>":()V
       4: return

  public static boolean isPossibleDynamicURI(java.lang.String, java.lang.Class<?>);
    Code:
       0: aload_0
       1: invokestatic  #2                  // Method mapDynamicURI:(Ljava/lang/String;)Ljava/lang/String;
       4: astore_2
       5: aload_2
       6: ifnonnull     11
       9: iconst_0
      10: ireturn
      11: aload_0
      12: aload_1
      13: invokestatic  #3                  // Method loadClass:(Ljava/lang/String;Ljava/lang/Class;)Ljava/lang/Class;
      16: ifnull        23
      19: iconst_1
      20: goto          24
      23: iconst_0
      24: ireturn

  public static java.lang.String mapDynamicURI(java.lang.String);
    Code:
       0: aload_0
       1: ldc           #4                  // String http://jena.hpl.hp.com/ARQ
       3: invokevirtual #5                  // Method java/lang/String.startsWith:(Ljava/lang/String;)Z
       6: ifeq          52
       9: aload_0
      10: ldc           #6                  // String http://jena.hpl.hp.com/
      12: ldc           #7                  // String http://jena.apache.org/
      14: invokevirtual #8                  // Method java/lang/String.replace:(Ljava/lang/CharSequence;Ljava/lang/CharSequence;)Ljava/lang/String;
      17: astore_1
      18: ldc           #9                  // class org/apache/jena/sparql/util/MappedLoader
      20: new           #10                 // class java/lang/StringBuilder
      23: dup
      24: invokespecial #11                 // Method java/lang/StringBuilder."<init>":()V
      27: ldc           #12                 // String Loading function or property function with old style \'jena.hpl.hp.com\' used - preferred style is to use \'jena.apache.org\':
      29: invokevirtual #13                 // Method java/lang/StringBuilder.append:(Ljava/lang/String;)Ljava/lang/StringBuilder;
      32: aload_0
      33: invokevirtual #13                 // Method java/lang/StringBuilder.append:(Ljava/lang/String;)Ljava/lang/StringBuilder;
      36: ldc           #14                 // String  =>
      38: invokevirtual #13                 // Method java/lang/StringBuilder.append:(Ljava/lang/String;)Ljava/lang/StringBuilder;
      41: aload_1
      42: invokevirtual #13                 // Method java/lang/StringBuilder.append:(Ljava/lang/String;)Ljava/lang/StringBuilder;
      45: invokevirtual #15                 // Method java/lang/StringBuilder.toString:()Ljava/lang/String;
      48: aload_0
      49: invokestatic  #16                 // Method org/apache/jena/atlas/logging/Log.warnOnce:(Ljava/lang/Class;Ljava/lang/String;Ljava/lang/Object;)V
      52: aload_0
      53: invokestatic  #17                 // Method find:(Ljava/lang/String;)Ljava/util/Map$Entry;
      56: astore_1
      57: aload_1
      58: ifnonnull     74
      61: aload_0
      62: ldc           #19                 // String java:
      64: invokevirtual #5                  // Method java/lang/String.startsWith:(Ljava/lang/String;)Z
      67: ifeq          72
      70: aload_0
      71: areturn
      72: aconst_null
      73: areturn
      74: aload_1
      75: invokeinterface #20,  1           // InterfaceMethod java/util/Map$Entry.getKey:()Ljava/lang/Object;
      80: checkcast     #21                 // class java/lang/String
      83: astore_2
      84: aload_1
      85: invokeinterface #22,  1           // InterfaceMethod java/util/Map$Entry.getValue:()Ljava/lang/Object;
      90: checkcast     #21                 // class java/lang/String
      93: astore_3
      94: aload_0
      95: aload_2
      96: invokevirtual #23                 // Method java/lang/String.length:()I
      99: invokevirtual #24                 // Method java/lang/String.substring:(I)Ljava/lang/String;
     102: astore_0
     103: new           #10                 // class java/lang/StringBuilder
     106: dup
     107: invokespecial #11                 // Method java/lang/StringBuilder."<init>":()V
     110: aload_3
     111: invokevirtual #13                 // Method java/lang/StringBuilder.append:(Ljava/lang/String;)Ljava/lang/StringBuilder;
     114: aload_0
     115: invokevirtual #13                 // Method java/lang/StringBuilder.append:(Ljava/lang/String;)Ljava/lang/StringBuilder;
     118: invokevirtual #15                 // Method java/lang/StringBuilder.toString:()Ljava/lang/String;
     121: astore_0
     122: aload_0
     123: areturn

  private static java.util.Map$Entry<java.lang.String, java.lang.String> find(java.lang.String);
    Code:
       0: getstatic     #25                 // Field uriMap:Ljava/util/Map;
       3: invokeinterface #26,  1           // InterfaceMethod java/util/Map.entrySet:()Ljava/util/Set;
       8: invokeinterface #27,  1           // InterfaceMethod java/util/Set.iterator:()Ljava/util/Iterator;
      13: astore_1
      14: aload_1
      15: invokeinterface #28,  1           // InterfaceMethod java/util/Iterator.hasNext:()Z
      20: ifeq          56
      23: aload_1
      24: invokeinterface #29,  1           // InterfaceMethod java/util/Iterator.next:()Ljava/lang/Object;
      29: checkcast     #30                 // class java/util/Map$Entry
      32: astore_2
      33: aload_2
      34: invokeinterface #20,  1           // InterfaceMethod java/util/Map$Entry.getKey:()Ljava/lang/Object;
      39: checkcast     #21                 // class java/lang/String
      42: astore_3
      43: aload_0
      44: aload_3
      45: invokevirtual #5                  // Method java/lang/String.startsWith:(Ljava/lang/String;)Z
      48: ifeq          53
      51: aload_2
      52: areturn
      53: goto          14
      56: aconst_null
      57: areturn

  public static java.lang.Class<?> loadClass(java.lang.String, java.lang.Class<?>);
    Code:
       0: aload_0
       1: invokestatic  #2                  // Method mapDynamicURI:(Ljava/lang/String;)Ljava/lang/String;
       4: astore_2
       5: aload_2
       6: ifnonnull     11
       9: aconst_null
      10: areturn
      11: aload_2
      12: aload_1
      13: invokestatic  #31                 // Method org/apache/jena/sparql/util/Loader.loadClass:(Ljava/lang/String;Ljava/lang/Class;)Ljava/lang/Class;
      16: areturn

  static {};
    Code:
       0: new           #32                 // class java/util/HashMap
       3: dup
       4: invokespecial #33                 // Method java/util/HashMap."<init>":()V
       7: putstatic     #25                 // Field uriMap:Ljava/util/Map;
      10: getstatic     #25                 // Field uriMap:Ljava/util/Map;
      13: ldc           #34                 // String http://jena.apache.org/ARQ/function#
      15: ldc           #35                 // String java:org.apache.jena.sparql.function.library.
      17: invokeinterface #36,  3           // InterfaceMethod java/util/Map.put:(Ljava/lang/Object;Ljava/lang/Object;)Ljava/lang/Object;
      22: pop
      23: getstatic     #25                 // Field uriMap:Ljava/util/Map;
      26: ldc           #37                 // String http://jena.hpl.hp.com/ARQ/function#
      28: ldc           #35                 // String java:org.apache.jena.sparql.function.library.
      30: invokeinterface #36,  3           // InterfaceMethod java/util/Map.put:(Ljava/lang/Object;Ljava/lang/Object;)Ljava/lang/Object;
      35: pop
      36: getstatic     #25                 // Field uriMap:Ljava/util/Map;
      39: ldc           #38                 // String http://jena.apache.org/ARQ/property#
      41: ldc           #39                 // String java:org.apache.jena.sparql.pfunction.library.
      43: invokeinterface #36,  3           // InterfaceMethod java/util/Map.put:(Ljava/lang/Object;Ljava/lang/Object;)Ljava/lang/Object;
      48: pop
      49: getstatic     #25                 // Field uriMap:Ljava/util/Map;
      52: ldc           #40                 // String http://jena.hpl.hp.com/ARQ/property#
      54: ldc           #39                 // String java:org.apache.jena.sparql.pfunction.library.
      56: invokeinterface #36,  3           // InterfaceMethod java/util/Map.put:(Ljava/lang/Object;Ljava/lang/Object;)Ljava/lang/Object;
      61: pop
      62: getstatic     #25                 // Field uriMap:Ljava/util/Map;
      65: ldc           #41                 // String http://jena.apache.org/ARQ/procedure#
      67: ldc           #42                 // String java:org.apache.jena.sparql.procedure.library.
      69: invokeinterface #36,  3           // InterfaceMethod java/util/Map.put:(Ljava/lang/Object;Ljava/lang/Object;)Ljava/lang/Object;
      74: pop
      75: getstatic     #25                 // Field uriMap:Ljava/util/Map;
      78: ldc           #43                 // String java:com.hp.hpl.jena.query.function.library.
      80: ldc           #35                 // String java:org.apache.jena.sparql.function.library.
      82: invokeinterface #36,  3           // InterfaceMethod java/util/Map.put:(Ljava/lang/Object;Ljava/lang/Object;)Ljava/lang/Object;
      87: pop
      88: getstatic     #25                 // Field uriMap:Ljava/util/Map;
      91: ldc           #44                 // String java:com.hp.hpl.jena.query.pfunction.library.
      93: ldc           #39                 // String java:org.apache.jena.sparql.pfunction.library.
      95: invokeinterface #36,  3           // InterfaceMethod java/util/Map.put:(Ljava/lang/Object;Ljava/lang/Object;)Ljava/lang/Object;
     100: pop
     101: getstatic     #25                 // Field uriMap:Ljava/util/Map;
     104: ldc           #46                 // String http://www.dotnetrdf.org/leviathan#
     106: ldc           #47                 // String java:org.apache.jena.sparql.function.library.leviathan.
     108: invokeinterface #36,  3           // InterfaceMethod java/util/Map.put:(Ljava/lang/Object;Ljava/lang/Object;)Ljava/lang/Object;
     113: pop
     114: return
}
