Compiled from "NodeUtils.java"
final class org.apache.jena.sparql.util.NodeUtils$3 implements org.apache.jena.sparql.util.NodeUtils$EqualityTest {
  org.apache.jena.sparql.util.NodeUtils$3();
    Code:
       0: aload_0
       1: invokespecial #1                  // Method java/lang/Object."<init>":()V
       4: return

  public boolean equal(org.apache.jena.graph.Node, org.apache.jena.graph.Node);
    Code:
       0: aload_1
       1: invokestatic  #2                  // Method org/apache/jena/sparql/expr/NodeValue.makeNode:(Lorg/apache/jena/graph/Node;)Lorg/apache/jena/sparql/expr/NodeValue;
       4: astore_3
       5: aload_2
       6: invokestatic  #2                  // Method org/apache/jena/sparql/expr/NodeValue.makeNode:(Lorg/apache/jena/graph/Node;)Lorg/apache/jena/sparql/expr/NodeValue;
       9: astore        4
      11: aload_3
      12: aload         4
      14: invokestatic  #3                  // Method org/apache/jena/sparql/expr/NodeValue.sameAs:(Lorg/apache/jena/sparql/expr/NodeValue;Lorg/apache/jena/sparql/expr/NodeValue;)Z
      17: ireturn
      18: astore        5
      20: iconst_0
      21: ireturn
    Exception table:
       from    to  target type
          11    17    18   Class org/apache/jena/sparql/expr/ExprEvalException
}
