Compiled from "AnnotatedFieldCollector.java"
public class com.fasterxml.jackson.databind.introspect.AnnotatedFieldCollector extends com.fasterxml.jackson.databind.introspect.CollectorBase {
  private final com.fasterxml.jackson.databind.type.TypeFactory _typeFactory;

  private final com.fasterxml.jackson.databind.introspect.ClassIntrospector$MixInResolver _mixInResolver;

  private final boolean _collectAnnotations;

  com.fasterxml.jackson.databind.introspect.AnnotatedFieldCollector(com.fasterxml.jackson.databind.AnnotationIntrospector, com.fasterxml.jackson.databind.type.TypeFactory, com.fasterxml.jackson.databind.introspect.ClassIntrospector$MixInResolver, boolean);
    Code:
       0: aload_0
       1: aload_1
       2: invokespecial #1                  // Method com/fasterxml/jackson/databind/introspect/CollectorBase."<init>":(Lcom/fasterxml/jackson/databind/AnnotationIntrospector;)V
       5: aload_0
       6: aload_2
       7: putfield      #2                  // Field _typeFactory:Lcom/fasterxml/jackson/databind/type/TypeFactory;
      10: aload_0
      11: aload_1
      12: ifnonnull     19
      15: aconst_null
      16: goto          20
      19: aload_3
      20: putfield      #3                  // Field _mixInResolver:Lcom/fasterxml/jackson/databind/introspect/ClassIntrospector$MixInResolver;
      23: aload_0
      24: iload         4
      26: putfield      #4                  // Field _collectAnnotations:Z
      29: return

  public static java.util.List<com.fasterxml.jackson.databind.introspect.AnnotatedField> collectFields(com.fasterxml.jackson.databind.AnnotationIntrospector, com.fasterxml.jackson.databind.introspect.TypeResolutionContext, com.fasterxml.jackson.databind.introspect.ClassIntrospector$MixInResolver, com.fasterxml.jackson.databind.type.TypeFactory, com.fasterxml.jackson.databind.JavaType, boolean);
    Code:
       0: new           #5                  // class com/fasterxml/jackson/databind/introspect/AnnotatedFieldCollector
       3: dup
       4: aload_0
       5: aload_3
       6: aload_2
       7: iload         5
       9: invokespecial #6                  // Method "<init>":(Lcom/fasterxml/jackson/databind/AnnotationIntrospector;Lcom/fasterxml/jackson/databind/type/TypeFactory;Lcom/fasterxml/jackson/databind/introspect/ClassIntrospector$MixInResolver;Z)V
      12: aload_1
      13: aload         4
      15: invokevirtual #7                  // Method collect:(Lcom/fasterxml/jackson/databind/introspect/TypeResolutionContext;Lcom/fasterxml/jackson/databind/JavaType;)Ljava/util/List;
      18: areturn

  java.util.List<com.fasterxml.jackson.databind.introspect.AnnotatedField> collect(com.fasterxml.jackson.databind.introspect.TypeResolutionContext, com.fasterxml.jackson.databind.JavaType);
    Code:
       0: aload_0
       1: aload_1
       2: aload_2
       3: aconst_null
       4: invokespecial #8                  // Method _findFields:(Lcom/fasterxml/jackson/databind/introspect/TypeResolutionContext;Lcom/fasterxml/jackson/databind/JavaType;Ljava/util/Map;)Ljava/util/Map;
       7: astore_3
       8: aload_3
       9: ifnonnull     16
      12: invokestatic  #9                  // Method java/util/Collections.emptyList:()Ljava/util/List;
      15: areturn
      16: new           #10                 // class java/util/ArrayList
      19: dup
      20: aload_3
      21: invokeinterface #11,  1           // InterfaceMethod java/util/Map.size:()I
      26: invokespecial #12                 // Method java/util/ArrayList."<init>":(I)V
      29: astore        4
      31: aload_3
      32: invokeinterface #13,  1           // InterfaceMethod java/util/Map.values:()Ljava/util/Collection;
      37: invokeinterface #14,  1           // InterfaceMethod java/util/Collection.iterator:()Ljava/util/Iterator;
      42: astore        5
      44: aload         5
      46: invokeinterface #15,  1           // InterfaceMethod java/util/Iterator.hasNext:()Z
      51: ifeq          82
      54: aload         5
      56: invokeinterface #16,  1           // InterfaceMethod java/util/Iterator.next:()Ljava/lang/Object;
      61: checkcast     #17                 // class com/fasterxml/jackson/databind/introspect/AnnotatedFieldCollector$FieldBuilder
      64: astore        6
      66: aload         4
      68: aload         6
      70: invokevirtual #18                 // Method com/fasterxml/jackson/databind/introspect/AnnotatedFieldCollector$FieldBuilder.build:()Lcom/fasterxml/jackson/databind/introspect/AnnotatedField;
      73: invokeinterface #19,  2           // InterfaceMethod java/util/List.add:(Ljava/lang/Object;)Z
      78: pop
      79: goto          44
      82: aload         4
      84: areturn

  private java.util.Map<java.lang.String, com.fasterxml.jackson.databind.introspect.AnnotatedFieldCollector$FieldBuilder> _findFields(com.fasterxml.jackson.databind.introspect.TypeResolutionContext, com.fasterxml.jackson.databind.JavaType, java.util.Map<java.lang.String, com.fasterxml.jackson.databind.introspect.AnnotatedFieldCollector$FieldBuilder>);
    Code:
       0: aload_2
       1: invokevirtual #20                 // Method com/fasterxml/jackson/databind/JavaType.getSuperClass:()Lcom/fasterxml/jackson/databind/JavaType;
       4: astore        4
       6: aload         4
       8: ifnonnull     13
      11: aload_3
      12: areturn
      13: aload_2
      14: invokevirtual #21                 // Method com/fasterxml/jackson/databind/JavaType.getRawClass:()Ljava/lang/Class;
      17: astore        5
      19: aload_0
      20: new           #22                 // class com/fasterxml/jackson/databind/introspect/TypeResolutionContext$Basic
      23: dup
      24: aload_0
      25: getfield      #2                  // Field _typeFactory:Lcom/fasterxml/jackson/databind/type/TypeFactory;
      28: aload         4
      30: invokevirtual #23                 // Method com/fasterxml/jackson/databind/JavaType.getBindings:()Lcom/fasterxml/jackson/databind/type/TypeBindings;
      33: invokespecial #24                 // Method com/fasterxml/jackson/databind/introspect/TypeResolutionContext$Basic."<init>":(Lcom/fasterxml/jackson/databind/type/TypeFactory;Lcom/fasterxml/jackson/databind/type/TypeBindings;)V
      36: aload         4
      38: aload_3
      39: invokespecial #8                  // Method _findFields:(Lcom/fasterxml/jackson/databind/introspect/TypeResolutionContext;Lcom/fasterxml/jackson/databind/JavaType;Ljava/util/Map;)Ljava/util/Map;
      42: astore_3
      43: aload         5
      45: invokevirtual #25                 // Method java/lang/Class.getDeclaredFields:()[Ljava/lang/reflect/Field;
      48: astore        6
      50: aload         6
      52: arraylength
      53: istore        7
      55: iconst_0
      56: istore        8
      58: iload         8
      60: iload         7
      62: if_icmpge     154
      65: aload         6
      67: iload         8
      69: aaload
      70: astore        9
      72: aload_0
      73: aload         9
      75: invokespecial #26                 // Method _isIncludableField:(Ljava/lang/reflect/Field;)Z
      78: ifne          84
      81: goto          148
      84: aload_3
      85: ifnonnull     96
      88: new           #27                 // class java/util/LinkedHashMap
      91: dup
      92: invokespecial #28                 // Method java/util/LinkedHashMap."<init>":()V
      95: astore_3
      96: new           #17                 // class com/fasterxml/jackson/databind/introspect/AnnotatedFieldCollector$FieldBuilder
      99: dup
     100: aload_1
     101: aload         9
     103: invokespecial #29                 // Method com/fasterxml/jackson/databind/introspect/AnnotatedFieldCollector$FieldBuilder."<init>":(Lcom/fasterxml/jackson/databind/introspect/TypeResolutionContext;Ljava/lang/reflect/Field;)V
     106: astore        10
     108: aload_0
     109: getfield      #4                  // Field _collectAnnotations:Z
     112: ifeq          134
     115: aload         10
     117: aload_0
     118: aload         10
     120: getfield      #30                 // Field com/fasterxml/jackson/databind/introspect/AnnotatedFieldCollector$FieldBuilder.annotations:Lcom/fasterxml/jackson/databind/introspect/AnnotationCollector;
     123: aload         9
     125: invokevirtual #31                 // Method java/lang/reflect/Field.getDeclaredAnnotations:()[Ljava/lang/annotation/Annotation;
     128: invokevirtual #32                 // Method collectAnnotations:(Lcom/fasterxml/jackson/databind/introspect/AnnotationCollector;[Ljava/lang/annotation/Annotation;)Lcom/fasterxml/jackson/databind/introspect/AnnotationCollector;
     131: putfield      #30                 // Field com/fasterxml/jackson/databind/introspect/AnnotatedFieldCollector$FieldBuilder.annotations:Lcom/fasterxml/jackson/databind/introspect/AnnotationCollector;
     134: aload_3
     135: aload         9
     137: invokevirtual #33                 // Method java/lang/reflect/Field.getName:()Ljava/lang/String;
     140: aload         10
     142: invokeinterface #34,  3           // InterfaceMethod java/util/Map.put:(Ljava/lang/Object;Ljava/lang/Object;)Ljava/lang/Object;
     147: pop
     148: iinc          8, 1
     151: goto          58
     154: aload_3
     155: ifnull        192
     158: aload_0
     159: getfield      #3                  // Field _mixInResolver:Lcom/fasterxml/jackson/databind/introspect/ClassIntrospector$MixInResolver;
     162: ifnull        192
     165: aload_0
     166: getfield      #3                  // Field _mixInResolver:Lcom/fasterxml/jackson/databind/introspect/ClassIntrospector$MixInResolver;
     169: aload         5
     171: invokeinterface #35,  2           // InterfaceMethod com/fasterxml/jackson/databind/introspect/ClassIntrospector$MixInResolver.findMixInClassFor:(Ljava/lang/Class;)Ljava/lang/Class;
     176: astore        6
     178: aload         6
     180: ifnull        192
     183: aload_0
     184: aload         6
     186: aload         5
     188: aload_3
     189: invokespecial #36                 // Method _addFieldMixIns:(Ljava/lang/Class;Ljava/lang/Class;Ljava/util/Map;)V
     192: aload_3
     193: areturn

  private void _addFieldMixIns(java.lang.Class<?>, java.lang.Class<?>, java.util.Map<java.lang.String, com.fasterxml.jackson.databind.introspect.AnnotatedFieldCollector$FieldBuilder>);
    Code:
       0: aload_1
       1: aload_2
       2: iconst_1
       3: invokestatic  #37                 // Method com/fasterxml/jackson/databind/util/ClassUtil.findSuperClasses:(Ljava/lang/Class;Ljava/lang/Class;Z)Ljava/util/List;
       6: astore        4
       8: aload         4
      10: invokeinterface #38,  1           // InterfaceMethod java/util/List.iterator:()Ljava/util/Iterator;
      15: astore        5
      17: aload         5
      19: invokeinterface #15,  1           // InterfaceMethod java/util/Iterator.hasNext:()Z
      24: ifeq          133
      27: aload         5
      29: invokeinterface #16,  1           // InterfaceMethod java/util/Iterator.next:()Ljava/lang/Object;
      34: checkcast     #39                 // class java/lang/Class
      37: astore        6
      39: aload         6
      41: invokevirtual #25                 // Method java/lang/Class.getDeclaredFields:()[Ljava/lang/reflect/Field;
      44: astore        7
      46: aload         7
      48: arraylength
      49: istore        8
      51: iconst_0
      52: istore        9
      54: iload         9
      56: iload         8
      58: if_icmpge     130
      61: aload         7
      63: iload         9
      65: aaload
      66: astore        10
      68: aload_0
      69: aload         10
      71: invokespecial #26                 // Method _isIncludableField:(Ljava/lang/reflect/Field;)Z
      74: ifne          80
      77: goto          124
      80: aload         10
      82: invokevirtual #33                 // Method java/lang/reflect/Field.getName:()Ljava/lang/String;
      85: astore        11
      87: aload_3
      88: aload         11
      90: invokeinterface #40,  2           // InterfaceMethod java/util/Map.get:(Ljava/lang/Object;)Ljava/lang/Object;
      95: checkcast     #17                 // class com/fasterxml/jackson/databind/introspect/AnnotatedFieldCollector$FieldBuilder
      98: astore        12
     100: aload         12
     102: ifnull        124
     105: aload         12
     107: aload_0
     108: aload         12
     110: getfield      #30                 // Field com/fasterxml/jackson/databind/introspect/AnnotatedFieldCollector$FieldBuilder.annotations:Lcom/fasterxml/jackson/databind/introspect/AnnotationCollector;
     113: aload         10
     115: invokevirtual #31                 // Method java/lang/reflect/Field.getDeclaredAnnotations:()[Ljava/lang/annotation/Annotation;
     118: invokevirtual #32                 // Method collectAnnotations:(Lcom/fasterxml/jackson/databind/introspect/AnnotationCollector;[Ljava/lang/annotation/Annotation;)Lcom/fasterxml/jackson/databind/introspect/AnnotationCollector;
     121: putfield      #30                 // Field com/fasterxml/jackson/databind/introspect/AnnotatedFieldCollector$FieldBuilder.annotations:Lcom/fasterxml/jackson/databind/introspect/AnnotationCollector;
     124: iinc          9, 1
     127: goto          54
     130: goto          17
     133: return

  private boolean _isIncludableField(java.lang.reflect.Field);
    Code:
       0: aload_1
       1: invokevirtual #41                 // Method java/lang/reflect/Field.isSynthetic:()Z
       4: ifeq          9
       7: iconst_0
       8: ireturn
       9: aload_1
      10: invokevirtual #42                 // Method java/lang/reflect/Field.getModifiers:()I
      13: istore_2
      14: iload_2
      15: invokestatic  #43                 // Method java/lang/reflect/Modifier.isStatic:(I)Z
      18: ifeq          23
      21: iconst_0
      22: ireturn
      23: iconst_1
      24: ireturn
}
