Compiled from "EntityBinder.java"
class org.hibernate.cfg.annotations.EntityBinder$SecondaryTableNameSource implements org.hibernate.cfg.ObjectNameSource {
  private final java.lang.String explicitName;

  private org.hibernate.cfg.annotations.EntityBinder$SecondaryTableNameSource(java.lang.String);
    Code:
       0: aload_0
       1: invokespecial #1                  // Method java/lang/Object."<init>":()V
       4: aload_0
       5: aload_1
       6: putfield      #2                  // Field explicitName:Ljava/lang/String;
       9: return

  public java.lang.String getExplicitName();
    Code:
       0: aload_0
       1: getfield      #2                  // Field explicitName:Ljava/lang/String;
       4: areturn

  public java.lang.String getLogicalName();
    Code:
       0: aload_0
       1: getfield      #2                  // Field explicitName:Ljava/lang/String;
       4: areturn
}
