Compiled from "NamedProcedureCallDefinition.java"
class org.hibernate.cfg.annotations.NamedProcedureCallDefinition$ParameterDefinition {
  private final java.lang.Integer position;

  private final java.lang.String name;

  private final javax.persistence.ParameterMode parameterMode;

  private final java.lang.Class type;

  private final java.lang.Boolean explicitPassNullSetting;

  static org.hibernate.cfg.annotations.NamedProcedureCallDefinition$ParameterDefinition from(org.hibernate.procedure.spi.ParameterStrategy, javax.persistence.StoredProcedureParameter, int, java.util.Map<java.lang.String, java.lang.Object>);
    Code:
       0: aload_0
       1: getstatic     #1                  // Field org/hibernate/procedure/spi/ParameterStrategy.NAMED:Lorg/hibernate/procedure/spi/ParameterStrategy;
       4: if_acmpne     42
       7: aload_3
       8: new           #2                  // class java/lang/StringBuilder
      11: dup
      12: invokespecial #3                  // Method java/lang/StringBuilder."<init>":()V
      15: ldc           #5                  // String hibernate.proc.param_null_passing.
      17: invokevirtual #6                  // Method java/lang/StringBuilder.append:(Ljava/lang/String;)Ljava/lang/StringBuilder;
      20: aload_1
      21: invokeinterface #7,  1            // InterfaceMethod javax/persistence/StoredProcedureParameter.name:()Ljava/lang/String;
      26: invokevirtual #6                  // Method java/lang/StringBuilder.append:(Ljava/lang/String;)Ljava/lang/StringBuilder;
      29: invokevirtual #8                  // Method java/lang/StringBuilder.toString:()Ljava/lang/String;
      32: invokeinterface #9,  2            // InterfaceMethod java/util/Map.get:(Ljava/lang/Object;)Ljava/lang/Object;
      37: astore        4
      39: goto          69
      42: aload_3
      43: new           #2                  // class java/lang/StringBuilder
      46: dup
      47: invokespecial #3                  // Method java/lang/StringBuilder."<init>":()V
      50: ldc           #5                  // String hibernate.proc.param_null_passing.
      52: invokevirtual #6                  // Method java/lang/StringBuilder.append:(Ljava/lang/String;)Ljava/lang/StringBuilder;
      55: iload_2
      56: invokevirtual #10                 // Method java/lang/StringBuilder.append:(I)Ljava/lang/StringBuilder;
      59: invokevirtual #8                  // Method java/lang/StringBuilder.toString:()Ljava/lang/String;
      62: invokeinterface #9,  2            // InterfaceMethod java/util/Map.get:(Ljava/lang/Object;)Ljava/lang/Object;
      67: astore        4
      69: new           #11                 // class org/hibernate/cfg/annotations/NamedProcedureCallDefinition$ParameterDefinition
      72: dup
      73: iload_2
      74: aload_1
      75: aload         4
      77: invokestatic  #12                 // Method interpretBoolean:(Ljava/lang/Object;)Ljava/lang/Boolean;
      80: invokespecial #13                 // Method "<init>":(ILjavax/persistence/StoredProcedureParameter;Ljava/lang/Boolean;)V
      83: areturn

  private static java.lang.Boolean interpretBoolean(java.lang.Object);
    Code:
       0: aload_0
       1: ifnonnull     6
       4: aconst_null
       5: areturn
       6: aload_0
       7: instanceof    #14                 // class java/lang/Boolean
      10: ifeq          18
      13: aload_0
      14: checkcast     #14                 // class java/lang/Boolean
      17: areturn
      18: aload_0
      19: invokevirtual #15                 // Method java/lang/Object.toString:()Ljava/lang/String;
      22: invokestatic  #16                 // Method java/lang/Boolean.valueOf:(Ljava/lang/String;)Ljava/lang/Boolean;
      25: areturn

  org.hibernate.cfg.annotations.NamedProcedureCallDefinition$ParameterDefinition(int, javax.persistence.StoredProcedureParameter, java.lang.Boolean);
    Code:
       0: aload_0
       1: invokespecial #17                 // Method java/lang/Object."<init>":()V
       4: aload_0
       5: iload_1
       6: invokestatic  #18                 // Method java/lang/Integer.valueOf:(I)Ljava/lang/Integer;
       9: putfield      #19                 // Field position:Ljava/lang/Integer;
      12: aload_0
      13: aload_2
      14: invokeinterface #7,  1            // InterfaceMethod javax/persistence/StoredProcedureParameter.name:()Ljava/lang/String;
      19: invokestatic  #20                 // Method org/hibernate/cfg/annotations/NamedProcedureCallDefinition.access$000:(Ljava/lang/String;)Ljava/lang/String;
      22: putfield      #21                 // Field name:Ljava/lang/String;
      25: aload_0
      26: aload_2
      27: invokeinterface #22,  1           // InterfaceMethod javax/persistence/StoredProcedureParameter.mode:()Ljavax/persistence/ParameterMode;
      32: putfield      #23                 // Field parameterMode:Ljavax/persistence/ParameterMode;
      35: aload_0
      36: aload_2
      37: invokeinterface #24,  1           // InterfaceMethod javax/persistence/StoredProcedureParameter.type:()Ljava/lang/Class;
      42: putfield      #25                 // Field type:Ljava/lang/Class;
      45: aload_0
      46: aload_3
      47: putfield      #26                 // Field explicitPassNullSetting:Ljava/lang/Boolean;
      50: return

  public org.hibernate.procedure.internal.ProcedureCallMementoImpl$ParameterMemento toMemento(org.hibernate.internal.SessionFactoryImpl);
    Code:
       0: aload_0
       1: getfield      #26                 // Field explicitPassNullSetting:Ljava/lang/Boolean;
       4: ifnull        17
       7: aload_0
       8: getfield      #26                 // Field explicitPassNullSetting:Ljava/lang/Boolean;
      11: invokevirtual #27                 // Method java/lang/Boolean.booleanValue:()Z
      14: goto          26
      17: aload_1
      18: invokevirtual #28                 // Method org/hibernate/internal/SessionFactoryImpl.getSessionFactoryOptions:()Lorg/hibernate/boot/spi/SessionFactoryOptions;
      21: invokeinterface #29,  1           // InterfaceMethod org/hibernate/boot/spi/SessionFactoryOptions.isProcedureParameterNullPassingEnabled:()Z
      26: istore_2
      27: new           #30                 // class org/hibernate/procedure/internal/ProcedureCallMementoImpl$ParameterMemento
      30: dup
      31: aload_0
      32: getfield      #19                 // Field position:Ljava/lang/Integer;
      35: invokevirtual #31                 // Method java/lang/Integer.intValue:()I
      38: aload_0
      39: getfield      #21                 // Field name:Ljava/lang/String;
      42: aload_0
      43: getfield      #23                 // Field parameterMode:Ljavax/persistence/ParameterMode;
      46: aload_0
      47: getfield      #25                 // Field type:Ljava/lang/Class;
      50: aload_1
      51: invokevirtual #32                 // Method org/hibernate/internal/SessionFactoryImpl.getTypeResolver:()Lorg/hibernate/type/TypeResolver;
      54: aload_0
      55: getfield      #25                 // Field type:Ljava/lang/Class;
      58: invokevirtual #33                 // Method java/lang/Class.getName:()Ljava/lang/String;
      61: invokevirtual #34                 // Method org/hibernate/type/TypeResolver.heuristicType:(Ljava/lang/String;)Lorg/hibernate/type/Type;
      64: iload_2
      65: invokespecial #35                 // Method org/hibernate/procedure/internal/ProcedureCallMementoImpl$ParameterMemento."<init>":(ILjava/lang/String;Ljavax/persistence/ParameterMode;Ljava/lang/Class;Lorg/hibernate/type/Type;Z)V
      68: areturn
}
