Compiled from "UserAgentAnnotationAnalyzer.java"
public class nl.basjes.parse.useragent.annotate.UserAgentAnnotationAnalyzer<T> {
  private nl.basjes.parse.useragent.annotate.UserAgentAnnotationMapper<T> mapper;

  private nl.basjes.parse.useragent.UserAgentAnalyzer userAgentAnalyzer;

  private int cacheSize;

  private static final org.apache.logging.log4j.Logger LOG;

  private final java.util.Map<java.lang.String, java.util.List<java.lang.reflect.Method>> fieldSetters;

  public nl.basjes.parse.useragent.annotate.UserAgentAnnotationAnalyzer();
    Code:
       0: aload_0
       1: invokespecial #52                 // Method java/lang/Object."<init>":()V
       4: aload_0
       5: aconst_null
       6: putfield      #54                 // Field mapper:Lnl/basjes/parse/useragent/annotate/UserAgentAnnotationMapper;
       9: aload_0
      10: aconst_null
      11: putfield      #56                 // Field userAgentAnalyzer:Lnl/basjes/parse/useragent/UserAgentAnalyzer;
      14: aload_0
      15: sipush        10000
      18: putfield      #58                 // Field cacheSize:I
      21: aload_0
      22: new           #60                 // class java/util/HashMap
      25: dup
      26: invokespecial #61                 // Method java/util/HashMap."<init>":()V
      29: putfield      #63                 // Field fieldSetters:Ljava/util/Map;
      32: return

  public void disableCaching();
    Code:
       0: aload_0
       1: iconst_0
       2: invokevirtual #71                 // Method setCacheSize:(I)V
       5: return

  public void setCacheSize(int);
    Code:
       0: aload_0
       1: iload_1
       2: iconst_0
       3: invokestatic  #77                 // Method java/lang/Math.max:(II)I
       6: putfield      #58                 // Field cacheSize:I
       9: aload_0
      10: getfield      #56                 // Field userAgentAnalyzer:Lnl/basjes/parse/useragent/UserAgentAnalyzer;
      13: ifnull        27
      16: aload_0
      17: getfield      #56                 // Field userAgentAnalyzer:Lnl/basjes/parse/useragent/UserAgentAnalyzer;
      20: aload_0
      21: getfield      #58                 // Field cacheSize:I
      24: invokevirtual #78                 // Method nl/basjes/parse/useragent/UserAgentAnalyzer.setCacheSize:(I)V
      27: return

  public int getCacheSize();
    Code:
       0: aload_0
       1: getfield      #58                 // Field cacheSize:I
       4: ireturn

  public void initialize(nl.basjes.parse.useragent.annotate.UserAgentAnnotationMapper<T>);
    Code:
       0: aload_0
       1: aload_1
       2: putfield      #54                 // Field mapper:Lnl/basjes/parse/useragent/annotate/UserAgentAnnotationMapper;
       5: aload_0
       6: getfield      #54                 // Field mapper:Lnl/basjes/parse/useragent/annotate/UserAgentAnnotationMapper;
       9: ifnonnull     22
      12: new           #86                 // class nl/basjes/parse/useragent/analyze/InvalidParserConfigurationException
      15: dup
      16: ldc           #88                 // String [Initialize] The mapper instance is null.
      18: invokespecial #91                 // Method nl/basjes/parse/useragent/analyze/InvalidParserConfigurationException."<init>":(Ljava/lang/String;)V
      21: athrow
      22: aload_0
      23: getfield      #54                 // Field mapper:Lnl/basjes/parse/useragent/annotate/UserAgentAnnotationMapper;
      26: invokevirtual #95                 // Method java/lang/Object.getClass:()Ljava/lang/Class;
      29: ldc           #97                 // class nl/basjes/parse/useragent/annotate/UserAgentAnnotationMapper
      31: invokestatic  #103                // Method nl/basjes/shaded/org/springframework/core/GenericTypeResolver.resolveTypeArguments:(Ljava/lang/Class;Ljava/lang/Class;)[Ljava/lang/Class;
      34: astore_2
      35: aload_2
      36: ifnonnull     49
      39: new           #86                 // class nl/basjes/parse/useragent/analyze/InvalidParserConfigurationException
      42: dup
      43: ldc           #105                // String Couldn\'t find the used generic type of the UserAgentAnnotationMapper.
      45: invokespecial #91                 // Method nl/basjes/parse/useragent/analyze/InvalidParserConfigurationException."<init>":(Ljava/lang/String;)V
      48: athrow
      49: aload_2
      50: iconst_0
      51: aaload
      52: astore_3
      53: aload_0
      54: getfield      #54                 // Field mapper:Lnl/basjes/parse/useragent/annotate/UserAgentAnnotationMapper;
      57: invokevirtual #95                 // Method java/lang/Object.getClass:()Ljava/lang/Class;
      60: invokevirtual #113                // Method java/lang/Class.getDeclaredMethods:()[Ljava/lang/reflect/Method;
      63: astore        4
      65: aload         4
      67: arraylength
      68: istore        5
      70: iconst_0
      71: istore        6
      73: iload         6
      75: iload         5
      77: if_icmpge     498
      80: aload         4
      82: iload         6
      84: aaload
      85: astore        7
      87: aload         7
      89: ldc           #117                // class nl/basjes/parse/useragent/annotate/YauaaField
      91: invokevirtual #123                // Method java/lang/reflect/Method.getAnnotation:(Ljava/lang/Class;)Ljava/lang/annotation/Annotation;
      94: checkcast     #117                // class nl/basjes/parse/useragent/annotate/YauaaField
      97: astore        8
      99: aload         8
     101: ifnull        492
     104: aload         7
     106: invokevirtual #126                // Method java/lang/reflect/Method.getReturnType:()Ljava/lang/Class;
     109: astore        9
     111: aload         7
     113: invokevirtual #130                // Method java/lang/reflect/Method.getParameterTypes:()[Ljava/lang/Class;
     116: astore        10
     118: aload         9
     120: invokevirtual #134                // Method java/lang/Class.getCanonicalName:()Ljava/lang/String;
     123: ldc           #136                // String void
     125: invokevirtual #142                // Method java/lang/String.equals:(Ljava/lang/Object;)Z
     128: ifeq          418
     131: aload         10
     133: arraylength
     134: iconst_2
     135: if_icmpne     418
     138: aload         10
     140: iconst_0
     141: aaload
     142: aload_3
     143: if_acmpne     418
     146: aload         10
     148: iconst_1
     149: aaload
     150: ldc           #138                // class java/lang/String
     152: if_acmpne     418
     155: aload_3
     156: invokevirtual #145                // Method java/lang/Class.getModifiers:()I
     159: invokestatic  #151                // Method java/lang/reflect/Modifier.isPublic:(I)Z
     162: ifne          200
     165: new           #86                 // class nl/basjes/parse/useragent/analyze/InvalidParserConfigurationException
     168: dup
     169: new           #153                // class java/lang/StringBuilder
     172: dup
     173: invokespecial #154                // Method java/lang/StringBuilder."<init>":()V
     176: ldc           #156                // String The class
     178: invokevirtual #160                // Method java/lang/StringBuilder.append:(Ljava/lang/String;)Ljava/lang/StringBuilder;
     181: aload_3
     182: invokevirtual #134                // Method java/lang/Class.getCanonicalName:()Ljava/lang/String;
     185: invokevirtual #160                // Method java/lang/StringBuilder.append:(Ljava/lang/String;)Ljava/lang/StringBuilder;
     188: ldc           #162                // String  is not public.
     190: invokevirtual #160                // Method java/lang/StringBuilder.append:(Ljava/lang/String;)Ljava/lang/StringBuilder;
     193: invokevirtual #165                // Method java/lang/StringBuilder.toString:()Ljava/lang/String;
     196: invokespecial #91                 // Method nl/basjes/parse/useragent/analyze/InvalidParserConfigurationException."<init>":(Ljava/lang/String;)V
     199: athrow
     200: aload         7
     202: invokevirtual #166                // Method java/lang/reflect/Method.getModifiers:()I
     205: invokestatic  #151                // Method java/lang/reflect/Modifier.isPublic:(I)Z
     208: ifne          242
     211: new           #86                 // class nl/basjes/parse/useragent/analyze/InvalidParserConfigurationException
     214: dup
     215: new           #153                // class java/lang/StringBuilder
     218: dup
     219: invokespecial #154                // Method java/lang/StringBuilder."<init>":()V
     222: ldc           #168                // String Method annotated with YauaaField is not public:
     224: invokevirtual #160                // Method java/lang/StringBuilder.append:(Ljava/lang/String;)Ljava/lang/StringBuilder;
     227: aload         7
     229: invokevirtual #171                // Method java/lang/reflect/Method.getName:()Ljava/lang/String;
     232: invokevirtual #160                // Method java/lang/StringBuilder.append:(Ljava/lang/String;)Ljava/lang/StringBuilder;
     235: invokevirtual #165                // Method java/lang/StringBuilder.toString:()Ljava/lang/String;
     238: invokespecial #91                 // Method nl/basjes/parse/useragent/analyze/InvalidParserConfigurationException."<init>":(Ljava/lang/String;)V
     241: athrow
     242: aload         7
     244: invokevirtual #174                // Method java/lang/reflect/Method.getDeclaringClass:()Ljava/lang/Class;
     247: invokevirtual #178                // Method java/lang/Class.isAnonymousClass:()Z
     250: ifeq          347
     253: new           #153                // class java/lang/StringBuilder
     256: dup
     257: invokespecial #154                // Method java/lang/StringBuilder."<init>":()V
     260: aload         7
     262: invokevirtual #126                // Method java/lang/reflect/Method.getReturnType:()Ljava/lang/Class;
     265: invokevirtual #179                // Method java/lang/Class.getName:()Ljava/lang/String;
     268: invokevirtual #160                // Method java/lang/StringBuilder.append:(Ljava/lang/String;)Ljava/lang/StringBuilder;
     271: ldc           #181                // String
     273: invokevirtual #160                // Method java/lang/StringBuilder.append:(Ljava/lang/String;)Ljava/lang/StringBuilder;
     276: aload         7
     278: invokevirtual #171                // Method java/lang/reflect/Method.getName:()Ljava/lang/String;
     281: invokevirtual #160                // Method java/lang/StringBuilder.append:(Ljava/lang/String;)Ljava/lang/StringBuilder;
     284: ldc           #183                // String (
     286: invokevirtual #160                // Method java/lang/StringBuilder.append:(Ljava/lang/String;)Ljava/lang/StringBuilder;
     289: aload         10
     291: iconst_0
     292: aaload
     293: invokevirtual #186                // Method java/lang/Class.getSimpleName:()Ljava/lang/String;
     296: invokevirtual #160                // Method java/lang/StringBuilder.append:(Ljava/lang/String;)Ljava/lang/StringBuilder;
     299: ldc           #188                // String  ,
     301: invokevirtual #160                // Method java/lang/StringBuilder.append:(Ljava/lang/String;)Ljava/lang/StringBuilder;
     304: aload         10
     306: iconst_1
     307: aaload
     308: invokevirtual #186                // Method java/lang/Class.getSimpleName:()Ljava/lang/String;
     311: invokevirtual #160                // Method java/lang/StringBuilder.append:(Ljava/lang/String;)Ljava/lang/StringBuilder;
     314: ldc           #190                // String );
     316: invokevirtual #160                // Method java/lang/StringBuilder.append:(Ljava/lang/String;)Ljava/lang/StringBuilder;
     319: invokevirtual #165                // Method java/lang/StringBuilder.toString:()Ljava/lang/String;
     322: astore        11
     324: getstatic     #192                // Field LOG:Lorg/apache/logging/log4j/Logger;
     327: ldc           #194                // String Trying to make anonymous {} {} accessible.
     329: aload         7
     331: invokevirtual #174                // Method java/lang/reflect/Method.getDeclaringClass:()Ljava/lang/Class;
     334: aload         11
     336: invokeinterface #200,  4          // InterfaceMethod org/apache/logging/log4j/Logger.warn:(Ljava/lang/String;Ljava/lang/Object;Ljava/lang/Object;)V
     341: aload         7
     343: iconst_1
     344: invokevirtual #204                // Method java/lang/reflect/Method.setAccessible:(Z)V
     347: aload         8
     349: invokeinterface #208,  1          // InterfaceMethod nl/basjes/parse/useragent/annotate/YauaaField.value:()[Ljava/lang/String;
     354: astore        11
     356: aload         11
     358: arraylength
     359: istore        12
     361: iconst_0
     362: istore        13
     364: iload         13
     366: iload         12
     368: if_icmpge     415
     371: aload         11
     373: iload         13
     375: aaload
     376: astore        14
     378: aload_0
     379: getfield      #63                 // Field fieldSetters:Ljava/util/Map;
     382: aload         14
     384: invokedynamic #229,  0            // InvokeDynamic #0:apply:()Ljava/util/function/Function;
     389: invokeinterface #233,  3          // InterfaceMethod java/util/Map.computeIfAbsent:(Ljava/lang/Object;Ljava/util/function/Function;)Ljava/lang/Object;
     394: checkcast     #235                // class java/util/List
     397: astore        15
     399: aload         15
     401: aload         7
     403: invokeinterface #238,  2          // InterfaceMethod java/util/List.add:(Ljava/lang/Object;)Z
     408: pop
     409: iinc          13, 1
     412: goto          364
     415: goto          492
     418: new           #86                 // class nl/basjes/parse/useragent/analyze/InvalidParserConfigurationException
     421: dup
     422: new           #153                // class java/lang/StringBuilder
     425: dup
     426: invokespecial #154                // Method java/lang/StringBuilder."<init>":()V
     429: ldc           #240                // String In class [
     431: invokevirtual #160                // Method java/lang/StringBuilder.append:(Ljava/lang/String;)Ljava/lang/StringBuilder;
     434: aload         7
     436: invokevirtual #174                // Method java/lang/reflect/Method.getDeclaringClass:()Ljava/lang/Class;
     439: invokevirtual #243                // Method java/lang/StringBuilder.append:(Ljava/lang/Object;)Ljava/lang/StringBuilder;
     442: ldc           #245                // String ] the method [
     444: invokevirtual #160                // Method java/lang/StringBuilder.append:(Ljava/lang/String;)Ljava/lang/StringBuilder;
     447: aload         7
     449: invokevirtual #171                // Method java/lang/reflect/Method.getName:()Ljava/lang/String;
     452: invokevirtual #160                // Method java/lang/StringBuilder.append:(Ljava/lang/String;)Ljava/lang/StringBuilder;
     455: ldc           #247                // String ] has been annotated with YauaaField but it has the wrong method signature. It must look like [ public void
     457: invokevirtual #160                // Method java/lang/StringBuilder.append:(Ljava/lang/String;)Ljava/lang/StringBuilder;
     460: aload         7
     462: invokevirtual #171                // Method java/lang/reflect/Method.getName:()Ljava/lang/String;
     465: invokevirtual #160                // Method java/lang/StringBuilder.append:(Ljava/lang/String;)Ljava/lang/StringBuilder;
     468: ldc           #183                // String (
     470: invokevirtual #160                // Method java/lang/StringBuilder.append:(Ljava/lang/String;)Ljava/lang/StringBuilder;
     473: aload_3
     474: invokevirtual #186                // Method java/lang/Class.getSimpleName:()Ljava/lang/String;
     477: invokevirtual #160                // Method java/lang/StringBuilder.append:(Ljava/lang/String;)Ljava/lang/StringBuilder;
     480: ldc           #249                // String  record, String value) ]
     482: invokevirtual #160                // Method java/lang/StringBuilder.append:(Ljava/lang/String;)Ljava/lang/StringBuilder;
     485: invokevirtual #165                // Method java/lang/StringBuilder.toString:()Ljava/lang/String;
     488: invokespecial #91                 // Method nl/basjes/parse/useragent/analyze/InvalidParserConfigurationException."<init>":(Ljava/lang/String;)V
     491: athrow
     492: iinc          6, 1
     495: goto          73
     498: aload_0
     499: getfield      #63                 // Field fieldSetters:Ljava/util/Map;
     502: invokeinterface #252,  1          // InterfaceMethod java/util/Map.isEmpty:()Z
     507: ifeq          520
     510: new           #86                 // class nl/basjes/parse/useragent/analyze/InvalidParserConfigurationException
     513: dup
     514: ldc           #254                // String You MUST specify at least 1 field to extract.
     516: invokespecial #91                 // Method nl/basjes/parse/useragent/analyze/InvalidParserConfigurationException."<init>":(Ljava/lang/String;)V
     519: athrow
     520: aload_0
     521: invokestatic  #258                // Method nl/basjes/parse/useragent/UserAgentAnalyzer.newBuilder:()Lnl/basjes/parse/useragent/UserAgentAnalyzer$UserAgentAnalyzerBuilder;
     524: invokevirtual #262                // Method nl/basjes/parse/useragent/UserAgentAnalyzer$UserAgentAnalyzerBuilder.hideMatcherLoadStats:()Lnl/basjes/parse/useragent/AbstractUserAgentAnalyzerDirect$AbstractUserAgentAnalyzerDirectBuilder;
     527: checkcast     #13                 // class nl/basjes/parse/useragent/UserAgentAnalyzer$UserAgentAnalyzerBuilder
     530: aload_0
     531: getfield      #58                 // Field cacheSize:I
     534: invokevirtual #266                // Method nl/basjes/parse/useragent/UserAgentAnalyzer$UserAgentAnalyzerBuilder.withCache:(I)Lnl/basjes/parse/useragent/AbstractUserAgentAnalyzer$AbstractUserAgentAnalyzerBuilder;
     537: checkcast     #13                 // class nl/basjes/parse/useragent/UserAgentAnalyzer$UserAgentAnalyzerBuilder
     540: aload_0
     541: getfield      #63                 // Field fieldSetters:Ljava/util/Map;
     544: invokeinterface #270,  1          // InterfaceMethod java/util/Map.keySet:()Ljava/util/Set;
     549: invokevirtual #274                // Method nl/basjes/parse/useragent/UserAgentAnalyzer$UserAgentAnalyzerBuilder.withFields:(Ljava/util/Collection;)Lnl/basjes/parse/useragent/AbstractUserAgentAnalyzerDirect$AbstractUserAgentAnalyzerDirectBuilder;
     552: checkcast     #13                 // class nl/basjes/parse/useragent/UserAgentAnalyzer$UserAgentAnalyzerBuilder
     555: invokevirtual #277                // Method nl/basjes/parse/useragent/UserAgentAnalyzer$UserAgentAnalyzerBuilder.dropTests:()Lnl/basjes/parse/useragent/AbstractUserAgentAnalyzerDirect$AbstractUserAgentAnalyzerDirectBuilder;
     558: checkcast     #13                 // class nl/basjes/parse/useragent/UserAgentAnalyzer$UserAgentAnalyzerBuilder
     561: invokevirtual #280                // Method nl/basjes/parse/useragent/UserAgentAnalyzer$UserAgentAnalyzerBuilder.immediateInitialization:()Lnl/basjes/parse/useragent/AbstractUserAgentAnalyzerDirect$AbstractUserAgentAnalyzerDirectBuilder;
     564: checkcast     #13                 // class nl/basjes/parse/useragent/UserAgentAnalyzer$UserAgentAnalyzerBuilder
     567: invokevirtual #284                // Method nl/basjes/parse/useragent/UserAgentAnalyzer$UserAgentAnalyzerBuilder.build:()Lnl/basjes/parse/useragent/AbstractUserAgentAnalyzer;
     570: checkcast     #15                 // class nl/basjes/parse/useragent/UserAgentAnalyzer
     573: putfield      #56                 // Field userAgentAnalyzer:Lnl/basjes/parse/useragent/UserAgentAnalyzer;
     576: return

  public T map(T);
    Code:
       0: aload_1
       1: ifnonnull     6
       4: aconst_null
       5: areturn
       6: aload_0
       7: getfield      #54                 // Field mapper:Lnl/basjes/parse/useragent/annotate/UserAgentAnnotationMapper;
      10: ifnonnull     24
      13: new           #86                 // class nl/basjes/parse/useragent/analyze/InvalidParserConfigurationException
      16: dup
      17: ldc_w         #310                // String [Map] The mapper instance is null.
      20: invokespecial #91                 // Method nl/basjes/parse/useragent/analyze/InvalidParserConfigurationException."<init>":(Ljava/lang/String;)V
      23: athrow
      24: aload_0
      25: getfield      #56                 // Field userAgentAnalyzer:Lnl/basjes/parse/useragent/UserAgentAnalyzer;
      28: aload_0
      29: getfield      #54                 // Field mapper:Lnl/basjes/parse/useragent/annotate/UserAgentAnnotationMapper;
      32: aload_1
      33: invokeinterface #314,  2          // InterfaceMethod nl/basjes/parse/useragent/annotate/UserAgentAnnotationMapper.getUserAgentString:(Ljava/lang/Object;)Ljava/lang/String;
      38: invokevirtual #318                // Method nl/basjes/parse/useragent/UserAgentAnalyzer.parse:(Ljava/lang/String;)Lnl/basjes/parse/useragent/UserAgent$ImmutableUserAgent;
      41: astore_2
      42: aload_0
      43: getfield      #63                 // Field fieldSetters:Ljava/util/Map;
      46: invokeinterface #321,  1          // InterfaceMethod java/util/Map.entrySet:()Ljava/util/Set;
      51: invokeinterface #327,  1          // InterfaceMethod java/util/Set.iterator:()Ljava/util/Iterator;
      56: astore_3
      57: aload_3
      58: invokeinterface #332,  1          // InterfaceMethod java/util/Iterator.hasNext:()Z
      63: ifeq          181
      66: aload_3
      67: invokeinterface #336,  1          // InterfaceMethod java/util/Iterator.next:()Ljava/lang/Object;
      72: checkcast     #8                  // class java/util/Map$Entry
      75: astore        4
      77: aload_2
      78: aload         4
      80: invokeinterface #339,  1          // InterfaceMethod java/util/Map$Entry.getKey:()Ljava/lang/Object;
      85: checkcast     #138                // class java/lang/String
      88: invokeinterface #343,  2          // InterfaceMethod nl/basjes/parse/useragent/UserAgent.getValue:(Ljava/lang/String;)Ljava/lang/String;
      93: astore        5
      95: aload         4
      97: invokeinterface #345,  1          // InterfaceMethod java/util/Map$Entry.getValue:()Ljava/lang/Object;
     102: checkcast     #235                // class java/util/List
     105: invokeinterface #346,  1          // InterfaceMethod java/util/List.iterator:()Ljava/util/Iterator;
     110: astore        6
     112: aload         6
     114: invokeinterface #332,  1          // InterfaceMethod java/util/Iterator.hasNext:()Z
     119: ifeq          178
     122: aload         6
     124: invokeinterface #336,  1          // InterfaceMethod java/util/Iterator.next:()Ljava/lang/Object;
     129: checkcast     #119                // class java/lang/reflect/Method
     132: astore        7
     134: aload         7
     136: aload_0
     137: getfield      #54                 // Field mapper:Lnl/basjes/parse/useragent/annotate/UserAgentAnnotationMapper;
     140: iconst_2
     141: anewarray     #5                  // class java/lang/Object
     144: dup
     145: iconst_0
     146: aload_1
     147: aastore
     148: dup
     149: iconst_1
     150: aload         5
     152: aastore
     153: invokevirtual #350                // Method java/lang/reflect/Method.invoke:(Ljava/lang/Object;[Ljava/lang/Object;)Ljava/lang/Object;
     156: pop
     157: goto          175
     160: astore        8
     162: new           #86                 // class nl/basjes/parse/useragent/analyze/InvalidParserConfigurationException
     165: dup
     166: ldc_w         #354                // String A problem occurred while calling the requested setter
     169: aload         8
     171: invokespecial #357                // Method nl/basjes/parse/useragent/analyze/InvalidParserConfigurationException."<init>":(Ljava/lang/String;Ljava/lang/Exception;)V
     174: athrow
     175: goto          112
     178: goto          57
     181: aload_1
     182: areturn
    Exception table:
       from    to  target type
         134   157   160   Class java/lang/IllegalAccessException
         134   157   160   Class java/lang/reflect/InvocationTargetException

  private static java.util.List lambda$initialize$0(java.lang.String);
    Code:
       0: new           #369                // class java/util/ArrayList
       3: dup
       4: invokespecial #370                // Method java/util/ArrayList."<init>":()V
       7: areturn

  static {};
    Code:
       0: ldc           #2                  // class nl/basjes/parse/useragent/annotate/UserAgentAnnotationAnalyzer
       2: invokestatic  #378                // Method org/apache/logging/log4j/LogManager.getLogger:(Ljava/lang/Class;)Lorg/apache/logging/log4j/Logger;
       5: putstatic     #192                // Field LOG:Lorg/apache/logging/log4j/Logger;
       8: return
}
