Compiled from "Closer.java"
public final class org.apache.hc.core5.io.Closer {
  public org.apache.hc.core5.io.Closer();
    Code:
       0: aload_0
       1: invokespecial #1                  // Method java/lang/Object."<init>":()V
       4: return

  public static void close(java.io.Closeable) throws java.io.IOException;
    Code:
       0: aload_0
       1: ifnull        10
       4: aload_0
       5: invokeinterface #2,  1            // InterfaceMethod java/io/Closeable.close:()V
      10: return

  public static void close(org.apache.hc.core5.io.ModalCloseable, org.apache.hc.core5.io.CloseMode);
    Code:
       0: aload_0
       1: ifnull        11
       4: aload_0
       5: aload_1
       6: invokeinterface #3,  2            // InterfaceMethod org/apache/hc/core5/io/ModalCloseable.close:(Lorg/apache/hc/core5/io/CloseMode;)V
      11: return

  public static void closeQuietly(java.io.Closeable);
    Code:
       0: aload_0
       1: invokestatic  #4                  // Method close:(Ljava/io/Closeable;)V
       4: goto          8
       7: astore_1
       8: return
    Exception table:
       from    to  target type
           0     4     7   Class java/io/IOException
}
