Compiled from "WonVerifier.java"
public class won.cryptography.rdfsign.WonVerifier {
  private static final org.slf4j.Logger logger;

  private org.apache.jena.query.Dataset dataset;

  private won.cryptography.rdfsign.SignatureVerificationState verificationState;

  public won.cryptography.rdfsign.WonVerifier(org.apache.jena.query.Dataset);
    Code:
       0: aload_0
       1: invokespecial #2                  // Method java/lang/Object."<init>":()V
       4: aload_0
       5: new           #3                  // class won/cryptography/rdfsign/SignatureVerificationState
       8: dup
       9: invokespecial #4                  // Method won/cryptography/rdfsign/SignatureVerificationState."<init>":()V
      12: putfield      #5                  // Field verificationState:Lwon/cryptography/rdfsign/SignatureVerificationState;
      15: new           #6                  // class org/bouncycastle/jce/provider/BouncyCastleProvider
      18: dup
      19: invokespecial #7                  // Method org/bouncycastle/jce/provider/BouncyCastleProvider."<init>":()V
      22: astore_2
      23: aload_0
      24: aload_1
      25: putfield      #8                  // Field dataset:Lorg/apache/jena/query/Dataset;
      28: aload_0
      29: invokespecial #9                  // Method prepareForVerifying:()V
      32: return

  private void prepareForVerifying();
    Code:
       0: aload_0
       1: getfield      #8                  // Field dataset:Lorg/apache/jena/query/Dataset;
       4: invokestatic  #10                 // Method won/protocol/util/RdfUtils.getModelNames:(Lorg/apache/jena/query/Dataset;)Ljava/util/List;
       7: invokeinterface #11,  1           // InterfaceMethod java/util/List.iterator:()Ljava/util/Iterator;
      12: astore_1
      13: aload_1
      14: invokeinterface #12,  1           // InterfaceMethod java/util/Iterator.hasNext:()Z
      19: ifeq          77
      22: aload_1
      23: invokeinterface #13,  1           // InterfaceMethod java/util/Iterator.next:()Ljava/lang/Object;
      28: checkcast     #14                 // class java/lang/String
      31: astore_2
      32: aload_0
      33: getfield      #8                  // Field dataset:Lorg/apache/jena/query/Dataset;
      36: aload_2
      37: invokeinterface #15,  2           // InterfaceMethod org/apache/jena/query/Dataset.getNamedModel:(Ljava/lang/String;)Lorg/apache/jena/rdf/model/Model;
      42: astore_3
      43: aload_2
      44: aload_3
      45: invokestatic  #16                 // Method won/protocol/util/WonRdfUtils$SignatureUtils.isSignatureGraph:(Ljava/lang/String;Lorg/apache/jena/rdf/model/Model;)Z
      48: ifeq          60
      51: aload_0
      52: aload_2
      53: aload_3
      54: invokespecial #17                 // Method addSignatureToResult:(Ljava/lang/String;Lorg/apache/jena/rdf/model/Model;)V
      57: goto          74
      60: aload_0
      61: getfield      #5                  // Field verificationState:Lwon/cryptography/rdfsign/SignatureVerificationState;
      64: aload_2
      65: invokevirtual #18                 // Method won/cryptography/rdfsign/SignatureVerificationState.addSignedGraphName:(Ljava/lang/String;)V
      68: aload_0
      69: aload_2
      70: aload_3
      71: invokespecial #19                 // Method addSignatureReferenceToResult:(Ljava/lang/String;Lorg/apache/jena/rdf/model/Model;)V
      74: goto          13
      77: return

  public won.cryptography.rdfsign.SignatureVerificationState getVerificationResult();
    Code:
       0: aload_0
       1: getfield      #5                  // Field verificationState:Lwon/cryptography/rdfsign/SignatureVerificationState;
       4: areturn

  public boolean verify(java.util.Map<java.lang.String, java.security.PublicKey>) throws java.lang.Exception;
    Code:
       0: aload_0
       1: getfield      #5                  // Field verificationState:Lwon/cryptography/rdfsign/SignatureVerificationState;
       4: invokevirtual #20                 // Method won/cryptography/rdfsign/SignatureVerificationState.getSignatures:()Ljava/util/List;
       7: invokeinterface #21,  1           // InterfaceMethod java/util/List.size:()I
      12: ifne          32
      15: aload_0
      16: getfield      #5                  // Field verificationState:Lwon/cryptography/rdfsign/SignatureVerificationState;
      19: ldc           #22                 // String No signatures found
      21: invokevirtual #23                 // Method won/cryptography/rdfsign/SignatureVerificationState.verificationFailed:(Ljava/lang/String;)V
      24: aload_0
      25: getfield      #5                  // Field verificationState:Lwon/cryptography/rdfsign/SignatureVerificationState;
      28: invokevirtual #24                 // Method won/cryptography/rdfsign/SignatureVerificationState.isVerificationPassed:()Z
      31: ireturn
      32: aload_0
      33: getfield      #8                  // Field dataset:Lorg/apache/jena/query/Dataset;
      36: invokeinterface #25,  1           // InterfaceMethod org/apache/jena/query/Dataset.getDefaultModel:()Lorg/apache/jena/rdf/model/Model;
      41: invokeinterface #26,  1           // InterfaceMethod org/apache/jena/rdf/model/Model.listStatements:()Lorg/apache/jena/rdf/model/StmtIterator;
      46: invokeinterface #27,  1           // InterfaceMethod org/apache/jena/rdf/model/StmtIterator.hasNext:()Z
      51: ifeq          71
      54: aload_0
      55: getfield      #5                  // Field verificationState:Lwon/cryptography/rdfsign/SignatureVerificationState;
      58: ldc           #28                 // String unsigned data found in default graph
      60: invokevirtual #23                 // Method won/cryptography/rdfsign/SignatureVerificationState.verificationFailed:(Ljava/lang/String;)V
      63: aload_0
      64: getfield      #5                  // Field verificationState:Lwon/cryptography/rdfsign/SignatureVerificationState;
      67: invokevirtual #24                 // Method won/cryptography/rdfsign/SignatureVerificationState.isVerificationPassed:()Z
      70: ireturn
      71: new           #29                 // class de/uni_koblenz/aggrimm/icp/crypto/sign/algorithm/algorithm/SignatureAlgorithmFisteus2010
      74: dup
      75: invokespecial #30                 // Method de/uni_koblenz/aggrimm/icp/crypto/sign/algorithm/algorithm/SignatureAlgorithmFisteus2010."<init>":()V
      78: astore_2
      79: aload_2
      80: astore_3
      81: ldc           #31                 // String sha-256
      83: ldc           #32                 // String BC
      85: invokestatic  #33                 // Method java/security/MessageDigest.getInstance:(Ljava/lang/String;Ljava/lang/String;)Ljava/security/MessageDigest;
      88: astore        4
      90: aload_0
      91: getfield      #5                  // Field verificationState:Lwon/cryptography/rdfsign/SignatureVerificationState;
      94: invokevirtual #20                 // Method won/cryptography/rdfsign/SignatureVerificationState.getSignatures:()Ljava/util/List;
      97: invokeinterface #11,  1           // InterfaceMethod java/util/List.iterator:()Ljava/util/Iterator;
     102: astore        5
     104: aload         5
     106: invokeinterface #12,  1           // InterfaceMethod java/util/Iterator.hasNext:()Z
     111: ifeq          860
     114: aload         5
     116: invokeinterface #13,  1           // InterfaceMethod java/util/Iterator.next:()Ljava/lang/Object;
     121: checkcast     #34                 // class won/protocol/message/WonSignatureData
     124: astore        6
     126: getstatic     #35                 // Field logger:Lorg/slf4j/Logger;
     129: invokeinterface #36,  1           // InterfaceMethod org/slf4j/Logger.isDebugEnabled:()Z
     134: ifeq          195
     137: aload_1
     138: aload         6
     140: invokevirtual #37                 // Method won/protocol/message/WonSignatureData.getVerificationCertificateUri:()Ljava/lang/String;
     143: invokeinterface #38,  2           // InterfaceMethod java/util/Map.containsKey:(Ljava/lang/Object;)Z
     148: ifeq          156
     151: ldc           #39                 // String loaded
     153: goto          158
     156: ldc           #40                 // String NOT LOADED
     158: astore        7
     160: getstatic     #35                 // Field logger:Lorg/slf4j/Logger;
     163: ldc           #41                 // String checking signature {} by certificate {}, which is {}
     165: iconst_3
     166: anewarray     #42                 // class java/lang/Object
     169: dup
     170: iconst_0
     171: aload         6
     173: invokevirtual #43                 // Method won/protocol/message/WonSignatureData.getSignatureUri:()Ljava/lang/String;
     176: aastore
     177: dup
     178: iconst_1
     179: aload         6
     181: invokevirtual #37                 // Method won/protocol/message/WonSignatureData.getVerificationCertificateUri:()Ljava/lang/String;
     184: aastore
     185: dup
     186: iconst_2
     187: aload         7
     189: aastore
     190: invokeinterface #44,  3           // InterfaceMethod org/slf4j/Logger.debug:(Ljava/lang/String;[Ljava/lang/Object;)V
     195: aload_0
     196: getfield      #8                  // Field dataset:Lorg/apache/jena/query/Dataset;
     199: aload         6
     201: invokevirtual #45                 // Method won/protocol/message/WonSignatureData.getSignedGraphUri:()Ljava/lang/String;
     204: invokeinterface #46,  2           // InterfaceMethod org/apache/jena/query/Dataset.containsNamedModel:(Ljava/lang/String;)Z
     209: ifne          230
     212: getstatic     #35                 // Field logger:Lorg/slf4j/Logger;
     215: ldc           #47                 // String cannot verify signature {} as it is not part of this message
     217: aload         6
     219: invokevirtual #43                 // Method won/protocol/message/WonSignatureData.getSignatureUri:()Ljava/lang/String;
     222: invokeinterface #48,  3           // InterfaceMethod org/slf4j/Logger.debug:(Ljava/lang/String;Ljava/lang/Object;)V
     227: goto          104
     230: aload         6
     232: invokevirtual #49                 // Method won/protocol/message/WonSignatureData.getSignatureValue:()Ljava/lang/String;
     235: astore        7
     237: aload         7
     239: ifnonnull     285
     242: aload_0
     243: getfield      #5                  // Field verificationState:Lwon/cryptography/rdfsign/SignatureVerificationState;
     246: aload         6
     248: invokevirtual #43                 // Method won/protocol/message/WonSignatureData.getSignatureUri:()Ljava/lang/String;
     251: new           #50                 // class java/lang/StringBuilder
     254: dup
     255: invokespecial #51                 // Method java/lang/StringBuilder."<init>":()V
     258: ldc           #52                 // String Failed to compute a signature value
     260: invokevirtual #53                 // Method java/lang/StringBuilder.append:(Ljava/lang/String;)Ljava/lang/StringBuilder;
     263: aload         6
     265: invokevirtual #43                 // Method won/protocol/message/WonSignatureData.getSignatureUri:()Ljava/lang/String;
     268: invokevirtual #53                 // Method java/lang/StringBuilder.append:(Ljava/lang/String;)Ljava/lang/StringBuilder;
     271: invokevirtual #54                 // Method java/lang/StringBuilder.toString:()Ljava/lang/String;
     274: invokevirtual #55                 // Method won/cryptography/rdfsign/SignatureVerificationState.setVerificationFailed:(Ljava/lang/String;Ljava/lang/String;)V
     277: aload_0
     278: getfield      #5                  // Field verificationState:Lwon/cryptography/rdfsign/SignatureVerificationState;
     281: invokevirtual #24                 // Method won/cryptography/rdfsign/SignatureVerificationState.isVerificationPassed:()Z
     284: ireturn
     285: aload         7
     287: invokevirtual #56                 // Method java/lang/String.length:()I
     290: ifne          336
     293: aload_0
     294: getfield      #5                  // Field verificationState:Lwon/cryptography/rdfsign/SignatureVerificationState;
     297: aload         6
     299: invokevirtual #43                 // Method won/protocol/message/WonSignatureData.getSignatureUri:()Ljava/lang/String;
     302: new           #50                 // class java/lang/StringBuilder
     305: dup
     306: invokespecial #51                 // Method java/lang/StringBuilder."<init>":()V
     309: ldc           #57                 // String Computed an empty signature value
     311: invokevirtual #53                 // Method java/lang/StringBuilder.append:(Ljava/lang/String;)Ljava/lang/StringBuilder;
     314: aload         6
     316: invokevirtual #43                 // Method won/protocol/message/WonSignatureData.getSignatureUri:()Ljava/lang/String;
     319: invokevirtual #53                 // Method java/lang/StringBuilder.append:(Ljava/lang/String;)Ljava/lang/StringBuilder;
     322: invokevirtual #54                 // Method java/lang/StringBuilder.toString:()Ljava/lang/String;
     325: invokevirtual #55                 // Method won/cryptography/rdfsign/SignatureVerificationState.setVerificationFailed:(Ljava/lang/String;Ljava/lang/String;)V
     328: aload_0
     329: getfield      #5                  // Field verificationState:Lwon/cryptography/rdfsign/SignatureVerificationState;
     332: invokevirtual #24                 // Method won/cryptography/rdfsign/SignatureVerificationState.isVerificationPassed:()Z
     335: ireturn
     336: aload_1
     337: aload         6
     339: invokevirtual #37                 // Method won/protocol/message/WonSignatureData.getVerificationCertificateUri:()Ljava/lang/String;
     342: invokeinterface #58,  2           // InterfaceMethod java/util/Map.get:(Ljava/lang/Object;)Ljava/lang/Object;
     347: checkcast     #59                 // class java/security/PublicKey
     350: astore        8
     352: aload         8
     354: ifnonnull     444
     357: aload_0
     358: getfield      #5                  // Field verificationState:Lwon/cryptography/rdfsign/SignatureVerificationState;
     361: aload         6
     363: invokevirtual #43                 // Method won/protocol/message/WonSignatureData.getSignatureUri:()Ljava/lang/String;
     366: new           #50                 // class java/lang/StringBuilder
     369: dup
     370: invokespecial #51                 // Method java/lang/StringBuilder."<init>":()V
     373: ldc           #60                 // String No public key found for
     375: invokevirtual #53                 // Method java/lang/StringBuilder.append:(Ljava/lang/String;)Ljava/lang/StringBuilder;
     378: aload         6
     380: invokevirtual #43                 // Method won/protocol/message/WonSignatureData.getSignatureUri:()Ljava/lang/String;
     383: invokevirtual #53                 // Method java/lang/StringBuilder.append:(Ljava/lang/String;)Ljava/lang/StringBuilder;
     386: invokevirtual #54                 // Method java/lang/StringBuilder.toString:()Ljava/lang/String;
     389: invokevirtual #55                 // Method won/cryptography/rdfsign/SignatureVerificationState.setVerificationFailed:(Ljava/lang/String;Ljava/lang/String;)V
     392: getstatic     #35                 // Field logger:Lorg/slf4j/Logger;
     395: invokeinterface #36,  1           // InterfaceMethod org/slf4j/Logger.isDebugEnabled:()Z
     400: ifeq          436
     403: getstatic     #35                 // Field logger:Lorg/slf4j/Logger;
     406: new           #50                 // class java/lang/StringBuilder
     409: dup
     410: invokespecial #51                 // Method java/lang/StringBuilder."<init>":()V
     413: ldc           #61                 // String offending message:\n
     415: invokevirtual #53                 // Method java/lang/StringBuilder.append:(Ljava/lang/String;)Ljava/lang/StringBuilder;
     418: aload_0
     419: getfield      #8                  // Field dataset:Lorg/apache/jena/query/Dataset;
     422: invokestatic  #62                 // Method won/protocol/util/RdfUtils.toString:(Lorg/apache/jena/query/Dataset;)Ljava/lang/String;
     425: invokevirtual #53                 // Method java/lang/StringBuilder.append:(Ljava/lang/String;)Ljava/lang/StringBuilder;
     428: invokevirtual #54                 // Method java/lang/StringBuilder.toString:()Ljava/lang/String;
     431: invokeinterface #63,  2           // InterfaceMethod org/slf4j/Logger.debug:(Ljava/lang/String;)V
     436: aload_0
     437: getfield      #5                  // Field verificationState:Lwon/cryptography/rdfsign/SignatureVerificationState;
     440: invokevirtual #24                 // Method won/cryptography/rdfsign/SignatureVerificationState.isVerificationPassed:()Z
     443: ireturn
     444: invokestatic  #64                 // Method java/util/Base64.getEncoder:()Ljava/util/Base64$Encoder;
     447: aload         4
     449: aload         8
     451: invokeinterface #65,  1           // InterfaceMethod java/security/PublicKey.getEncoded:()[B
     456: invokevirtual #66                 // Method java/security/MessageDigest.digest:([B)[B
     459: invokevirtual #67                 // Method java/util/Base64$Encoder.encodeToString:([B)Ljava/lang/String;
     462: astore        9
     464: aload         6
     466: invokevirtual #68                 // Method won/protocol/message/WonSignatureData.getPublicKeyFingerprint:()Ljava/lang/String;
     469: aload         9
     471: invokevirtual #69                 // Method java/lang/String.equals:(Ljava/lang/Object;)Z
     474: ifne          543
     477: aload_0
     478: getfield      #5                  // Field verificationState:Lwon/cryptography/rdfsign/SignatureVerificationState;
     481: aload         6
     483: invokevirtual #43                 // Method won/protocol/message/WonSignatureData.getSignatureUri:()Ljava/lang/String;
     486: new           #50                 // class java/lang/StringBuilder
     489: dup
     490: invokespecial #51                 // Method java/lang/StringBuilder."<init>":()V
     493: ldc           #70                 // String Fingerprint computed for the specified public key
     495: invokevirtual #53                 // Method java/lang/StringBuilder.append:(Ljava/lang/String;)Ljava/lang/StringBuilder;
     498: aload         6
     500: invokevirtual #37                 // Method won/protocol/message/WonSignatureData.getVerificationCertificateUri:()Ljava/lang/String;
     503: invokevirtual #53                 // Method java/lang/StringBuilder.append:(Ljava/lang/String;)Ljava/lang/StringBuilder;
     506: ldc           #71                 // String  is
     508: invokevirtual #53                 // Method java/lang/StringBuilder.append:(Ljava/lang/String;)Ljava/lang/StringBuilder;
     511: aload         9
     513: invokevirtual #53                 // Method java/lang/StringBuilder.append:(Ljava/lang/String;)Ljava/lang/StringBuilder;
     516: ldc           #72                 // String , which differs from the value found in signature
     518: invokevirtual #53                 // Method java/lang/StringBuilder.append:(Ljava/lang/String;)Ljava/lang/StringBuilder;
     521: aload         6
     523: invokevirtual #43                 // Method won/protocol/message/WonSignatureData.getSignatureUri:()Ljava/lang/String;
     526: invokevirtual #53                 // Method java/lang/StringBuilder.append:(Ljava/lang/String;)Ljava/lang/StringBuilder;
     529: invokevirtual #54                 // Method java/lang/StringBuilder.toString:()Ljava/lang/String;
     532: invokevirtual #55                 // Method won/cryptography/rdfsign/SignatureVerificationState.setVerificationFailed:(Ljava/lang/String;Ljava/lang/String;)V
     535: aload_0
     536: getfield      #5                  // Field verificationState:Lwon/cryptography/rdfsign/SignatureVerificationState;
     539: invokevirtual #24                 // Method won/cryptography/rdfsign/SignatureVerificationState.isVerificationPassed:()Z
     542: ireturn
     543: aload         6
     545: invokevirtual #45                 // Method won/protocol/message/WonSignatureData.getSignedGraphUri:()Ljava/lang/String;
     548: aload_0
     549: getfield      #8                  // Field dataset:Lorg/apache/jena/query/Dataset;
     552: invokestatic  #73                 // Method won/cryptography/rdfsign/ModelConverter.modelToGraphCollection:(Ljava/lang/String;Lorg/apache/jena/query/Dataset;)Lde/uni_koblenz/aggrimm/icp/crypto/sign/graph/GraphCollection;
     555: astore        10
     557: aload_2
     558: aload         10
     560: invokeinterface #74,  2           // InterfaceMethod de/uni_koblenz/aggrimm/icp/crypto/sign/algorithm/SignatureAlgorithmInterface.canonicalize:(Lde/uni_koblenz/aggrimm/icp/crypto/sign/graph/GraphCollection;)V
     565: aload_2
     566: aload         10
     568: invokeinterface #75,  2           // InterfaceMethod de/uni_koblenz/aggrimm/icp/crypto/sign/algorithm/SignatureAlgorithmInterface.postCanonicalize:(Lde/uni_koblenz/aggrimm/icp/crypto/sign/graph/GraphCollection;)V
     573: aload_3
     574: aload         10
     576: ldc           #31                 // String sha-256
     578: invokeinterface #76,  3           // InterfaceMethod de/uni_koblenz/aggrimm/icp/crypto/sign/algorithm/SignatureAlgorithmInterface.hash:(Lde/uni_koblenz/aggrimm/icp/crypto/sign/graph/GraphCollection;Ljava/lang/String;)V
     583: aload_3
     584: aload         10
     586: invokeinterface #77,  2           // InterfaceMethod de/uni_koblenz/aggrimm/icp/crypto/sign/algorithm/SignatureAlgorithmInterface.postHash:(Lde/uni_koblenz/aggrimm/icp/crypto/sign/graph/GraphCollection;)V
     591: aload         10
     593: invokevirtual #78                 // Method de/uni_koblenz/aggrimm/icp/crypto/sign/graph/GraphCollection.getSignature:()Lde/uni_koblenz/aggrimm/icp/crypto/sign/graph/SignatureData;
     596: invokevirtual #79                 // Method de/uni_koblenz/aggrimm/icp/crypto/sign/graph/SignatureData.getHash:()Ljava/math/BigInteger;
     599: astore        11
     601: invokestatic  #64                 // Method java/util/Base64.getEncoder:()Ljava/util/Base64$Encoder;
     604: aload         11
     606: invokevirtual #80                 // Method java/math/BigInteger.toByteArray:()[B
     609: invokevirtual #67                 // Method java/util/Base64$Encoder.encodeToString:([B)Ljava/lang/String;
     612: astore        12
     614: aload         6
     616: invokevirtual #81                 // Method won/protocol/message/WonSignatureData.getHash:()Ljava/lang/String;
     619: aload         12
     621: invokevirtual #69                 // Method java/lang/String.equals:(Ljava/lang/Object;)Z
     624: ifne          755
     627: aload_0
     628: getfield      #5                  // Field verificationState:Lwon/cryptography/rdfsign/SignatureVerificationState;
     631: aload         6
     633: invokevirtual #43                 // Method won/protocol/message/WonSignatureData.getSignatureUri:()Ljava/lang/String;
     636: new           #50                 // class java/lang/StringBuilder
     639: dup
     640: invokespecial #51                 // Method java/lang/StringBuilder."<init>":()V
     643: ldc           #82                 // String Computed hash value
     645: invokevirtual #53                 // Method java/lang/StringBuilder.append:(Ljava/lang/String;)Ljava/lang/StringBuilder;
     648: aload         12
     650: invokevirtual #53                 // Method java/lang/StringBuilder.append:(Ljava/lang/String;)Ljava/lang/StringBuilder;
     653: ldc           #83                 // String  differs from value
     655: invokevirtual #53                 // Method java/lang/StringBuilder.append:(Ljava/lang/String;)Ljava/lang/StringBuilder;
     658: aload         6
     660: invokevirtual #81                 // Method won/protocol/message/WonSignatureData.getHash:()Ljava/lang/String;
     663: invokevirtual #53                 // Method java/lang/StringBuilder.append:(Ljava/lang/String;)Ljava/lang/StringBuilder;
     666: ldc           #84                 // String  found in signature
     668: invokevirtual #53                 // Method java/lang/StringBuilder.append:(Ljava/lang/String;)Ljava/lang/StringBuilder;
     671: aload         6
     673: invokevirtual #43                 // Method won/protocol/message/WonSignatureData.getSignatureUri:()Ljava/lang/String;
     676: invokevirtual #53                 // Method java/lang/StringBuilder.append:(Ljava/lang/String;)Ljava/lang/StringBuilder;
     679: invokevirtual #54                 // Method java/lang/StringBuilder.toString:()Ljava/lang/String;
     682: invokevirtual #55                 // Method won/cryptography/rdfsign/SignatureVerificationState.setVerificationFailed:(Ljava/lang/String;Ljava/lang/String;)V
     685: getstatic     #35                 // Field logger:Lorg/slf4j/Logger;
     688: invokeinterface #36,  1           // InterfaceMethod org/slf4j/Logger.isDebugEnabled:()Z
     693: ifeq          747
     696: new           #85                 // class java/io/StringWriter
     699: dup
     700: invokespecial #86                 // Method java/io/StringWriter."<init>":()V
     703: astore        13
     705: aload         13
     707: aload_0
     708: getfield      #8                  // Field dataset:Lorg/apache/jena/query/Dataset;
     711: aload         6
     713: invokevirtual #45                 // Method won/protocol/message/WonSignatureData.getSignedGraphUri:()Ljava/lang/String;
     716: invokeinterface #15,  2           // InterfaceMethod org/apache/jena/query/Dataset.getNamedModel:(Ljava/lang/String;)Lorg/apache/jena/rdf/model/Model;
     721: getstatic     #87                 // Field org/apache/jena/riot/Lang.TRIG:Lorg/apache/jena/riot/Lang;
     724: invokestatic  #88                 // Method org/apache/jena/riot/RDFDataMgr.write:(Ljava/io/StringWriter;Lorg/apache/jena/rdf/model/Model;Lorg/apache/jena/riot/Lang;)V
     727: getstatic     #35                 // Field logger:Lorg/slf4j/Logger;
     730: ldc           #89                 // String wrong signature hash for graph {} with content: {}
     732: aload         6
     734: invokevirtual #45                 // Method won/protocol/message/WonSignatureData.getSignedGraphUri:()Ljava/lang/String;
     737: aload         13
     739: invokevirtual #90                 // Method java/io/StringWriter.toString:()Ljava/lang/String;
     742: invokeinterface #91,  4           // InterfaceMethod org/slf4j/Logger.debug:(Ljava/lang/String;Ljava/lang/Object;Ljava/lang/Object;)V
     747: aload_0
     748: getfield      #5                  // Field verificationState:Lwon/cryptography/rdfsign/SignatureVerificationState;
     751: invokevirtual #24                 // Method won/cryptography/rdfsign/SignatureVerificationState.isVerificationPassed:()Z
     754: ireturn
     755: ldc           #92                 // String NONEwithECDSA
     757: ldc           #32                 // String BC
     759: invokestatic  #93                 // Method java/security/Signature.getInstance:(Ljava/lang/String;Ljava/lang/String;)Ljava/security/Signature;
     762: astore        13
     764: aload         13
     766: aload         8
     768: invokevirtual #94                 // Method java/security/Signature.initVerify:(Ljava/security/PublicKey;)V
     771: aload         13
     773: aload         11
     775: invokevirtual #80                 // Method java/math/BigInteger.toByteArray:()[B
     778: invokevirtual #95                 // Method java/security/Signature.update:([B)V
     781: invokestatic  #96                 // Method java/util/Base64.getDecoder:()Ljava/util/Base64$Decoder;
     784: aload         7
     786: invokevirtual #97                 // Method java/util/Base64$Decoder.decode:(Ljava/lang/String;)[B
     789: astore        14
     791: aload         13
     793: aload         14
     795: invokevirtual #98                 // Method java/security/Signature.verify:([B)Z
     798: ifne          857
     801: aload_0
     802: getfield      #5                  // Field verificationState:Lwon/cryptography/rdfsign/SignatureVerificationState;
     805: aload         6
     807: invokevirtual #43                 // Method won/protocol/message/WonSignatureData.getSignatureUri:()Ljava/lang/String;
     810: new           #50                 // class java/lang/StringBuilder
     813: dup
     814: invokespecial #51                 // Method java/lang/StringBuilder."<init>":()V
     817: ldc           #99                 // String Failed to verify
     819: invokevirtual #53                 // Method java/lang/StringBuilder.append:(Ljava/lang/String;)Ljava/lang/StringBuilder;
     822: aload         6
     824: invokevirtual #43                 // Method won/protocol/message/WonSignatureData.getSignatureUri:()Ljava/lang/String;
     827: invokevirtual #53                 // Method java/lang/StringBuilder.append:(Ljava/lang/String;)Ljava/lang/StringBuilder;
     830: ldc           #100                // String  with public key
     832: invokevirtual #53                 // Method java/lang/StringBuilder.append:(Ljava/lang/String;)Ljava/lang/StringBuilder;
     835: aload         6
     837: invokevirtual #37                 // Method won/protocol/message/WonSignatureData.getVerificationCertificateUri:()Ljava/lang/String;
     840: invokevirtual #53                 // Method java/lang/StringBuilder.append:(Ljava/lang/String;)Ljava/lang/StringBuilder;
     843: invokevirtual #54                 // Method java/lang/StringBuilder.toString:()Ljava/lang/String;
     846: invokevirtual #55                 // Method won/cryptography/rdfsign/SignatureVerificationState.setVerificationFailed:(Ljava/lang/String;Ljava/lang/String;)V
     849: aload_0
     850: getfield      #5                  // Field verificationState:Lwon/cryptography/rdfsign/SignatureVerificationState;
     853: invokevirtual #24                 // Method won/cryptography/rdfsign/SignatureVerificationState.isVerificationPassed:()Z
     856: ireturn
     857: goto          104
     860: aload_0
     861: getfield      #5                  // Field verificationState:Lwon/cryptography/rdfsign/SignatureVerificationState;
     864: invokevirtual #24                 // Method won/cryptography/rdfsign/SignatureVerificationState.isVerificationPassed:()Z
     867: ireturn

  private void addSignatureToResult(java.lang.String, org.apache.jena.rdf.model.Model);
    Code:
       0: aload_1
       1: aload_2
       2: invokestatic  #101                // Method won/protocol/util/WonRdfUtils$SignatureUtils.extractWonSignatureData:(Ljava/lang/String;Lorg/apache/jena/rdf/model/Model;)Lwon/protocol/message/WonSignatureData;
       5: astore_3
       6: aload_3
       7: ifnull        25
      10: aload_3
      11: invokevirtual #49                 // Method won/protocol/message/WonSignatureData.getSignatureValue:()Ljava/lang/String;
      14: ifnull        25
      17: aload_0
      18: getfield      #5                  // Field verificationState:Lwon/cryptography/rdfsign/SignatureVerificationState;
      21: aload_3
      22: invokevirtual #102                // Method won/cryptography/rdfsign/SignatureVerificationState.addSignatureData:(Lwon/protocol/message/WonSignatureData;)V
      25: return

  private void addSignatureReferenceToResult(java.lang.String, org.apache.jena.rdf.model.Model);
    Code:
       0: aconst_null
       1: astore_3
       2: aload_2
       3: aconst_null
       4: getstatic     #103                // Field won/protocol/vocabulary/WONMSG.containsSignature:Lorg/apache/jena/rdf/model/Property;
       7: aload_3
       8: invokeinterface #104,  4          // InterfaceMethod org/apache/jena/rdf/model/Model.listStatements:(Lorg/apache/jena/rdf/model/Resource;Lorg/apache/jena/rdf/model/Property;Lorg/apache/jena/rdf/model/RDFNode;)Lorg/apache/jena/rdf/model/StmtIterator;
      13: astore        4
      15: aload         4
      17: invokeinterface #27,  1           // InterfaceMethod org/apache/jena/rdf/model/StmtIterator.hasNext:()Z
      22: ifeq          59
      25: aload         4
      27: invokeinterface #105,  1          // InterfaceMethod org/apache/jena/rdf/model/StmtIterator.nextStatement:()Lorg/apache/jena/rdf/model/Statement;
      32: invokeinterface #106,  1          // InterfaceMethod org/apache/jena/rdf/model/Statement.getObject:()Lorg/apache/jena/rdf/model/RDFNode;
      37: invokeinterface #107,  1          // InterfaceMethod org/apache/jena/rdf/model/RDFNode.asResource:()Lorg/apache/jena/rdf/model/Resource;
      42: invokestatic  #108                // Method won/protocol/util/WonRdfUtils$SignatureUtils.extractWonSignatureData:(Lorg/apache/jena/rdf/model/Resource;)Lwon/protocol/message/WonSignatureData;
      45: astore        5
      47: aload_0
      48: getfield      #5                  // Field verificationState:Lwon/cryptography/rdfsign/SignatureVerificationState;
      51: aload         5
      53: invokevirtual #102                // Method won/cryptography/rdfsign/SignatureVerificationState.addSignatureData:(Lwon/protocol/message/WonSignatureData;)V
      56: goto          15
      59: return

  static {};
    Code:
       0: invokestatic  #109                // Method java/lang/invoke/MethodHandles.lookup:()Ljava/lang/invoke/MethodHandles$Lookup;
       3: invokevirtual #110                // Method java/lang/invoke/MethodHandles$Lookup.lookupClass:()Ljava/lang/Class;
       6: invokestatic  #111                // Method org/slf4j/LoggerFactory.getLogger:(Ljava/lang/Class;)Lorg/slf4j/Logger;
       9: putstatic     #35                 // Field logger:Lorg/slf4j/Logger;
      12: return
}
