Compiled from "CoarseCachedClock.java"
public final class org.apache.logging.log4j.core.util.CoarseCachedClock implements org.apache.logging.log4j.core.util.Clock {
  private static volatile org.apache.logging.log4j.core.util.CoarseCachedClock instance;

  private static final java.lang.Object INSTANCE_LOCK;

  private volatile long millis;

  private final java.lang.Thread updater;

  private org.apache.logging.log4j.core.util.CoarseCachedClock();
    Code:
       0: aload_0
       1: invokespecial #2                  // Method java/lang/Object."<init>":()V
       4: aload_0
       5: invokestatic  #3                  // Method java/lang/System.currentTimeMillis:()J
       8: putfield      #1                  // Field millis:J
      11: aload_0
      12: new           #4                  // class org/apache/logging/log4j/core/util/CoarseCachedClock$1
      15: dup
      16: aload_0
      17: ldc           #5                  // String CoarseCachedClock Updater Thread
      19: invokespecial #6                  // Method org/apache/logging/log4j/core/util/CoarseCachedClock$1."<init>":(Lorg/apache/logging/log4j/core/util/CoarseCachedClock;Ljava/lang/String;)V
      22: putfield      #7                  // Field updater:Ljava/lang/Thread;
      25: aload_0
      26: getfield      #7                  // Field updater:Ljava/lang/Thread;
      29: iconst_1
      30: invokevirtual #8                  // Method java/lang/Thread.setDaemon:(Z)V
      33: aload_0
      34: getfield      #7                  // Field updater:Ljava/lang/Thread;
      37: invokevirtual #9                  // Method java/lang/Thread.start:()V
      40: return

  public static org.apache.logging.log4j.core.util.CoarseCachedClock instance();
    Code:
       0: getstatic     #10                 // Field instance:Lorg/apache/logging/log4j/core/util/CoarseCachedClock;
       3: astore_0
       4: aload_0
       5: ifnonnull     44
       8: getstatic     #11                 // Field INSTANCE_LOCK:Ljava/lang/Object;
      11: dup
      12: astore_1
      13: monitorenter
      14: getstatic     #10                 // Field instance:Lorg/apache/logging/log4j/core/util/CoarseCachedClock;
      17: astore_0
      18: aload_0
      19: ifnonnull     34
      22: new           #12                 // class org/apache/logging/log4j/core/util/CoarseCachedClock
      25: dup
      26: invokespecial #13                 // Method "<init>":()V
      29: dup
      30: astore_0
      31: putstatic     #10                 // Field instance:Lorg/apache/logging/log4j/core/util/CoarseCachedClock;
      34: aload_1
      35: monitorexit
      36: goto          44
      39: astore_2
      40: aload_1
      41: monitorexit
      42: aload_2
      43: athrow
      44: aload_0
      45: areturn
    Exception table:
       from    to  target type
          14    36    39   any
          39    42    39   any

  public long currentTimeMillis();
    Code:
       0: aload_0
       1: getfield      #1                  // Field millis:J
       4: lreturn

  static long access$002(org.apache.logging.log4j.core.util.CoarseCachedClock, long);
    Code:
       0: aload_0
       1: lload_1
       2: dup2_x1
       3: putfield      #1                  // Field millis:J
       6: lreturn

  static {};
    Code:
       0: new           #14                 // class java/lang/Object
       3: dup
       4: invokespecial #2                  // Method java/lang/Object."<init>":()V
       7: putstatic     #11                 // Field INSTANCE_LOCK:Ljava/lang/Object;
      10: return
}
