Compiled from "NullOutputStream.java"
public class org.apache.logging.log4j.core.util.NullOutputStream extends java.io.OutputStream {
  private static final org.apache.logging.log4j.core.util.NullOutputStream INSTANCE;

  public static final org.apache.logging.log4j.core.util.NullOutputStream NULL_OUTPUT_STREAM;

  public static org.apache.logging.log4j.core.util.NullOutputStream getInstance();
    Code:
       0: getstatic     #1                  // Field INSTANCE:Lorg/apache/logging/log4j/core/util/NullOutputStream;
       3: areturn

  private org.apache.logging.log4j.core.util.NullOutputStream();
    Code:
       0: aload_0
       1: invokespecial #2                  // Method java/io/OutputStream."<init>":()V
       4: return

  public void write(byte[], int, int);
    Code:
       0: return

  public void write(int);
    Code:
       0: return

  public void write(byte[]) throws java.io.IOException;
    Code:
       0: return

  static {};
    Code:
       0: new           #3                  // class org/apache/logging/log4j/core/util/NullOutputStream
       3: dup
       4: invokespecial #4                  // Method "<init>":()V
       7: putstatic     #1                  // Field INSTANCE:Lorg/apache/logging/log4j/core/util/NullOutputStream;
      10: getstatic     #1                  // Field INSTANCE:Lorg/apache/logging/log4j/core/util/NullOutputStream;
      13: putstatic     #5                  // Field NULL_OUTPUT_STREAM:Lorg/apache/logging/log4j/core/util/NullOutputStream;
      16: return
}
