Compiled from "WatchManager.java"
class org.apache.logging.log4j.core.util.WatchManager$LocalUUID {
  private static final long LOW_MASK;

  private static final long MID_MASK;

  private static final long HIGH_MASK;

  private static final int NODE_SIZE;

  private static final int SHIFT_2;

  private static final int SHIFT_4;

  private static final int SHIFT_6;

  private static final int HUNDRED_NANOS_PER_MILLI;

  private static final long NUM_100NS_INTERVALS_SINCE_UUID_EPOCH;

  private static final java.util.concurrent.atomic.AtomicInteger COUNT;

  private static final long TYPE1;

  private static final byte VARIANT;

  private static final int SEQUENCE_MASK;

  private org.apache.logging.log4j.core.util.WatchManager$LocalUUID();
    Code:
       0: aload_0
       1: invokespecial #1                  // Method java/lang/Object."<init>":()V
       4: return

  public static java.util.UUID get();
    Code:
       0: invokestatic  #2                  // Method java/lang/System.currentTimeMillis:()J
       3: ldc2_w        #4                  // long 10000l
       6: lmul
       7: ldc2_w        #6                  // long 122192928000000000l
      10: ladd
      11: getstatic     #8                  // Field COUNT:Ljava/util/concurrent/atomic/AtomicInteger;
      14: invokevirtual #9                  // Method java/util/concurrent/atomic/AtomicInteger.incrementAndGet:()I
      17: sipush        10000
      20: irem
      21: i2l
      22: ladd
      23: lstore_0
      24: lload_0
      25: ldc2_w        #10                 // long 4294967295l
      28: land
      29: bipush        32
      31: lshl
      32: lstore_2
      33: lload_0
      34: ldc2_w        #12                 // long 281470681743360l
      37: land
      38: bipush        16
      40: lshr
      41: lstore        4
      43: lload_0
      44: ldc2_w        #14                 // long 1152640029630136320l
      47: land
      48: bipush        48
      50: lshr
      51: lstore        6
      53: lload_2
      54: lload         4
      56: lor
      57: ldc2_w        #16                 // long 4096l
      60: lor
      61: lload         6
      63: lor
      64: lstore        8
      66: new           #18                 // class java/util/UUID
      69: dup
      70: lload         8
      72: getstatic     #8                  // Field COUNT:Ljava/util/concurrent/atomic/AtomicInteger;
      75: invokevirtual #9                  // Method java/util/concurrent/atomic/AtomicInteger.incrementAndGet:()I
      78: i2l
      79: invokespecial #19                 // Method java/util/UUID."<init>":(JJ)V
      82: areturn

  static {};
    Code:
       0: new           #20                 // class java/util/concurrent/atomic/AtomicInteger
       3: dup
       4: iconst_0
       5: invokespecial #21                 // Method java/util/concurrent/atomic/AtomicInteger."<init>":(I)V
       8: putstatic     #8                  // Field COUNT:Ljava/util/concurrent/atomic/AtomicInteger;
      11: return
}
