Compiled from "ExecWebSocketListener.java"
public class io.dekorate.deps.kubernetes.client.dsl.internal.ExecWebSocketListener extends io.dekorate.deps.okhttp3.WebSocketListener implements io.dekorate.deps.kubernetes.client.dsl.ExecWatch,java.lang.AutoCloseable {
  private static final org.slf4j.Logger LOGGER;

  private static final java.lang.String HEIGHT;

  private static final java.lang.String WIDTH;

  private final io.dekorate.deps.kubernetes.client.Config config;

  private final java.io.InputStream in;

  private final java.io.OutputStream out;

  private final java.io.OutputStream err;

  private final java.io.OutputStream errChannel;

  private final java.io.PipedOutputStream input;

  private final java.io.PipedInputStream output;

  private final java.io.PipedInputStream error;

  private final java.io.PipedInputStream errorChannel;

  private final java.util.concurrent.atomic.AtomicReference<io.dekorate.deps.okhttp3.WebSocket> webSocketRef;

  private final java.util.concurrent.ExecutorService executorService;

  private final io.dekorate.deps.kubernetes.client.utils.InputStreamPumper pumper;

  private final java.util.concurrent.atomic.AtomicBoolean started;

  private final java.util.concurrent.ArrayBlockingQueue<java.lang.Object> queue;

  private final io.dekorate.deps.kubernetes.client.dsl.ExecListener listener;

  private final java.util.concurrent.atomic.AtomicBoolean explicitlyClosed;

  private final java.util.concurrent.atomic.AtomicBoolean failed;

  private final java.util.concurrent.atomic.AtomicBoolean closed;

  private final java.util.concurrent.atomic.AtomicBoolean cleaned;

  private final java.util.Set<java.io.Closeable> toClose;

  private io.dekorate.deps.jackson.databind.ObjectMapper objectMapper;

  public io.dekorate.deps.kubernetes.client.dsl.internal.ExecWebSocketListener(java.io.InputStream, java.io.OutputStream, java.io.OutputStream, java.io.PipedOutputStream, java.io.PipedInputStream, java.io.PipedInputStream, io.dekorate.deps.kubernetes.client.dsl.ExecListener);
    Code:
       0: aload_0
       1: new           #65                 // class io/dekorate/deps/kubernetes/client/Config
       4: dup
       5: invokespecial #68                 // Method io/dekorate/deps/kubernetes/client/Config."<init>":()V
       8: aload_1
       9: aload_2
      10: aload_3
      11: aload         4
      13: aload         5
      15: aload         6
      17: aload         7
      19: invokespecial #71                 // Method "<init>":(Lio/dekorate/deps/kubernetes/client/Config;Ljava/io/InputStream;Ljava/io/OutputStream;Ljava/io/OutputStream;Ljava/io/PipedOutputStream;Ljava/io/PipedInputStream;Ljava/io/PipedInputStream;Lio/dekorate/deps/kubernetes/client/dsl/ExecListener;)V
      22: return

  public io.dekorate.deps.kubernetes.client.dsl.internal.ExecWebSocketListener(io.dekorate.deps.kubernetes.client.Config, java.io.InputStream, java.io.OutputStream, java.io.OutputStream, java.io.PipedOutputStream, java.io.PipedInputStream, java.io.PipedInputStream, io.dekorate.deps.kubernetes.client.dsl.ExecListener);
    Code:
       0: aload_0
       1: aload_1
       2: aload_2
       3: aload_3
       4: aload         4
       6: aconst_null
       7: aload         5
       9: aload         6
      11: aload         7
      13: aconst_null
      14: aload         8
      16: aconst_null
      17: invokespecial #79                 // Method "<init>":(Lio/dekorate/deps/kubernetes/client/Config;Ljava/io/InputStream;Ljava/io/OutputStream;Ljava/io/OutputStream;Ljava/io/OutputStream;Ljava/io/PipedOutputStream;Ljava/io/PipedInputStream;Ljava/io/PipedInputStream;Ljava/io/PipedInputStream;Lio/dekorate/deps/kubernetes/client/dsl/ExecListener;Ljava/lang/Integer;)V
      20: return

  public io.dekorate.deps.kubernetes.client.dsl.internal.ExecWebSocketListener(io.dekorate.deps.kubernetes.client.Config, java.io.InputStream, java.io.OutputStream, java.io.OutputStream, java.io.OutputStream, java.io.PipedOutputStream, java.io.PipedInputStream, java.io.PipedInputStream, java.io.PipedInputStream, io.dekorate.deps.kubernetes.client.dsl.ExecListener);
    Code:
       0: aload_0
       1: aload_1
       2: aload_2
       3: aload_3
       4: aload         4
       6: aload         5
       8: aload         6
      10: aload         7
      12: aload         8
      14: aload         9
      16: aload         10
      18: aconst_null
      19: invokespecial #79                 // Method "<init>":(Lio/dekorate/deps/kubernetes/client/Config;Ljava/io/InputStream;Ljava/io/OutputStream;Ljava/io/OutputStream;Ljava/io/OutputStream;Ljava/io/PipedOutputStream;Ljava/io/PipedInputStream;Ljava/io/PipedInputStream;Ljava/io/PipedInputStream;Lio/dekorate/deps/kubernetes/client/dsl/ExecListener;Ljava/lang/Integer;)V
      22: return

  public io.dekorate.deps.kubernetes.client.dsl.internal.ExecWebSocketListener(io.dekorate.deps.kubernetes.client.Config, java.io.InputStream, java.io.OutputStream, java.io.OutputStream, java.io.OutputStream, java.io.PipedOutputStream, java.io.PipedInputStream, java.io.PipedInputStream, java.io.PipedInputStream, io.dekorate.deps.kubernetes.client.dsl.ExecListener, java.lang.Integer);
    Code:
       0: aload_0
       1: invokespecial #82                 // Method io/dekorate/deps/okhttp3/WebSocketListener."<init>":()V
       4: aload_0
       5: new           #84                 // class java/util/concurrent/atomic/AtomicReference
       8: dup
       9: invokespecial #85                 // Method java/util/concurrent/atomic/AtomicReference."<init>":()V
      12: putfield      #87                 // Field webSocketRef:Ljava/util/concurrent/atomic/AtomicReference;
      15: aload_0
      16: invokestatic  #93                 // Method java/util/concurrent/Executors.newSingleThreadExecutor:()Ljava/util/concurrent/ExecutorService;
      19: putfield      #95                 // Field executorService:Ljava/util/concurrent/ExecutorService;
      22: aload_0
      23: new           #97                 // class java/util/concurrent/atomic/AtomicBoolean
      26: dup
      27: iconst_0
      28: invokespecial #100                // Method java/util/concurrent/atomic/AtomicBoolean."<init>":(Z)V
      31: putfield      #102                // Field started:Ljava/util/concurrent/atomic/AtomicBoolean;
      34: aload_0
      35: new           #104                // class java/util/concurrent/ArrayBlockingQueue
      38: dup
      39: iconst_1
      40: invokespecial #107                // Method java/util/concurrent/ArrayBlockingQueue."<init>":(I)V
      43: putfield      #109                // Field queue:Ljava/util/concurrent/ArrayBlockingQueue;
      46: aload_0
      47: new           #97                 // class java/util/concurrent/atomic/AtomicBoolean
      50: dup
      51: iconst_0
      52: invokespecial #100                // Method java/util/concurrent/atomic/AtomicBoolean."<init>":(Z)V
      55: putfield      #111                // Field explicitlyClosed:Ljava/util/concurrent/atomic/AtomicBoolean;
      58: aload_0
      59: new           #97                 // class java/util/concurrent/atomic/AtomicBoolean
      62: dup
      63: iconst_0
      64: invokespecial #100                // Method java/util/concurrent/atomic/AtomicBoolean."<init>":(Z)V
      67: putfield      #113                // Field failed:Ljava/util/concurrent/atomic/AtomicBoolean;
      70: aload_0
      71: new           #97                 // class java/util/concurrent/atomic/AtomicBoolean
      74: dup
      75: iconst_0
      76: invokespecial #100                // Method java/util/concurrent/atomic/AtomicBoolean."<init>":(Z)V
      79: putfield      #115                // Field closed:Ljava/util/concurrent/atomic/AtomicBoolean;
      82: aload_0
      83: new           #97                 // class java/util/concurrent/atomic/AtomicBoolean
      86: dup
      87: iconst_0
      88: invokespecial #100                // Method java/util/concurrent/atomic/AtomicBoolean."<init>":(Z)V
      91: putfield      #117                // Field cleaned:Ljava/util/concurrent/atomic/AtomicBoolean;
      94: aload_0
      95: new           #119                // class java/util/LinkedHashSet
      98: dup
      99: invokespecial #120                // Method java/util/LinkedHashSet."<init>":()V
     102: putfield      #122                // Field toClose:Ljava/util/Set;
     105: aload_0
     106: aload_1
     107: putfield      #124                // Field config:Lio/dekorate/deps/kubernetes/client/Config;
     110: aload_0
     111: aload         10
     113: putfield      #126                // Field listener:Lio/dekorate/deps/kubernetes/client/dsl/ExecListener;
     116: aload_0
     117: aload_2
     118: aload         6
     120: aload_0
     121: getfield      #122                // Field toClose:Ljava/util/Set;
     124: aload         11
     126: invokestatic  #130                // Method inputStreamOrPipe:(Ljava/io/InputStream;Ljava/io/PipedOutputStream;Ljava/util/Set;Ljava/lang/Integer;)Ljava/io/InputStream;
     129: putfield      #132                // Field in:Ljava/io/InputStream;
     132: aload_0
     133: aload_3
     134: aload         7
     136: aload_0
     137: getfield      #122                // Field toClose:Ljava/util/Set;
     140: invokestatic  #136                // Method outputStreamOrPipe:(Ljava/io/OutputStream;Ljava/io/PipedInputStream;Ljava/util/Set;)Ljava/io/OutputStream;
     143: putfield      #138                // Field out:Ljava/io/OutputStream;
     146: aload_0
     147: aload         4
     149: aload         8
     151: aload_0
     152: getfield      #122                // Field toClose:Ljava/util/Set;
     155: invokestatic  #136                // Method outputStreamOrPipe:(Ljava/io/OutputStream;Ljava/io/PipedInputStream;Ljava/util/Set;)Ljava/io/OutputStream;
     158: putfield      #140                // Field err:Ljava/io/OutputStream;
     161: aload_0
     162: aload         5
     164: aload         9
     166: aload_0
     167: getfield      #122                // Field toClose:Ljava/util/Set;
     170: invokestatic  #136                // Method outputStreamOrPipe:(Ljava/io/OutputStream;Ljava/io/PipedInputStream;Ljava/util/Set;)Ljava/io/OutputStream;
     173: putfield      #142                // Field errChannel:Ljava/io/OutputStream;
     176: aload_0
     177: aload         6
     179: putfield      #144                // Field input:Ljava/io/PipedOutputStream;
     182: aload_0
     183: aload         7
     185: putfield      #146                // Field output:Ljava/io/PipedInputStream;
     188: aload_0
     189: aload         8
     191: putfield      #148                // Field error:Ljava/io/PipedInputStream;
     194: aload_0
     195: aload         9
     197: putfield      #150                // Field errorChannel:Ljava/io/PipedInputStream;
     200: aload_0
     201: new           #152                // class io/dekorate/deps/kubernetes/client/utils/NonBlockingInputStreamPumper
     204: dup
     205: aload_0
     206: getfield      #132                // Field in:Ljava/io/InputStream;
     209: aload_0
     210: invokedynamic #171,  0            // InvokeDynamic #0:call:(Lio/dekorate/deps/kubernetes/client/dsl/internal/ExecWebSocketListener;)Lio/dekorate/deps/kubernetes/client/Callback;
     215: invokespecial #174                // Method io/dekorate/deps/kubernetes/client/utils/NonBlockingInputStreamPumper."<init>":(Ljava/io/InputStream;Lio/dekorate/deps/kubernetes/client/Callback;)V
     218: putfield      #176                // Field pumper:Lio/dekorate/deps/kubernetes/client/utils/InputStreamPumper;
     221: aload_0
     222: new           #178                // class io/dekorate/deps/jackson/databind/ObjectMapper
     225: dup
     226: invokespecial #179                // Method io/dekorate/deps/jackson/databind/ObjectMapper."<init>":()V
     229: putfield      #181                // Field objectMapper:Lio/dekorate/deps/jackson/databind/ObjectMapper;
     232: return

  public void close();
    Code:
       0: aload_0
       1: sipush        1000
       4: ldc           #186                // String Closing...
       6: invokevirtual #189                // Method close:(ILjava/lang/String;)V
       9: return

  public void close(int, java.lang.String);
    Code:
       0: aload_0
       1: aload_0
       2: getfield      #87                 // Field webSocketRef:Ljava/util/concurrent/atomic/AtomicReference;
       5: invokevirtual #193                // Method java/util/concurrent/atomic/AtomicReference.get:()Ljava/lang/Object;
       8: checkcast     #195                // class io/dekorate/deps/okhttp3/WebSocket
      11: iload_1
      12: aload_2
      13: invokespecial #198                // Method close:(Lio/dekorate/deps/okhttp3/WebSocket;ILjava/lang/String;)V
      16: return

  private void close(io.dekorate.deps.okhttp3.WebSocket, int, java.lang.String);
    Code:
       0: aload_0
       1: getfield      #111                // Field explicitlyClosed:Ljava/util/concurrent/atomic/AtomicBoolean;
       4: iconst_1
       5: invokevirtual #204                // Method java/util/concurrent/atomic/AtomicBoolean.set:(Z)V
       8: aload_0
       9: iload_2
      10: aload_3
      11: invokespecial #207                // Method closeWebSocketOnce:(ILjava/lang/String;)V
      14: aload_0
      15: aload_1
      16: iload_2
      17: aload_3
      18: invokevirtual #210                // Method onClosed:(Lio/dekorate/deps/okhttp3/WebSocket;ILjava/lang/String;)V
      21: return

  private void cleanUpOnce();
    Code:
       0: aload_0
       1: getfield      #117                // Field cleaned:Ljava/util/concurrent/atomic/AtomicBoolean;
       4: iconst_0
       5: iconst_1
       6: invokevirtual #217                // Method java/util/concurrent/atomic/AtomicBoolean.compareAndSet:(ZZ)Z
       9: ifne          13
      12: return
      13: iconst_1
      14: anewarray     #219                // class java/io/Closeable
      17: dup
      18: iconst_0
      19: aload_0
      20: getfield      #176                // Field pumper:Lio/dekorate/deps/kubernetes/client/utils/InputStreamPumper;
      23: aastore
      24: invokestatic  #225                // Method io/dekorate/deps/kubernetes/client/utils/Utils.closeQuietly:([Ljava/io/Closeable;)V
      27: aload_0
      28: getfield      #95                 // Field executorService:Ljava/util/concurrent/ExecutorService;
      31: invokestatic  #229                // Method io/dekorate/deps/kubernetes/client/utils/Utils.shutdownExecutorService:(Ljava/util/concurrent/ExecutorService;)Z
      34: pop
      35: aload_0
      36: getfield      #122                // Field toClose:Ljava/util/Set;
      39: invokestatic  #232                // Method io/dekorate/deps/kubernetes/client/utils/Utils.closeQuietly:(Ljava/lang/Iterable;)V
      42: goto          55
      45: astore_1
      46: aload_0
      47: getfield      #122                // Field toClose:Ljava/util/Set;
      50: invokestatic  #232                // Method io/dekorate/deps/kubernetes/client/utils/Utils.closeQuietly:(Ljava/lang/Iterable;)V
      53: aload_1
      54: athrow
      55: return
    Exception table:
       from    to  target type
          13    35    45   any

  private void closeWebSocketOnce(int, java.lang.String);
    Code:
       0: aload_0
       1: getfield      #115                // Field closed:Ljava/util/concurrent/atomic/AtomicBoolean;
       4: invokevirtual #237                // Method java/util/concurrent/atomic/AtomicBoolean.get:()Z
       7: ifeq          11
      10: return
      11: aload_0
      12: getfield      #87                 // Field webSocketRef:Ljava/util/concurrent/atomic/AtomicReference;
      15: invokevirtual #193                // Method java/util/concurrent/atomic/AtomicReference.get:()Ljava/lang/Object;
      18: checkcast     #195                // class io/dekorate/deps/okhttp3/WebSocket
      21: astore_3
      22: aload_3
      23: ifnull        35
      26: aload_3
      27: iload_1
      28: aload_2
      29: invokeinterface #240,  3          // InterfaceMethod io/dekorate/deps/okhttp3/WebSocket.close:(ILjava/lang/String;)Z
      34: pop
      35: goto          50
      38: astore_3
      39: getstatic     #242                // Field LOGGER:Lorg/slf4j/Logger;
      42: ldc           #244                // String Error closing WebSocket.
      44: aload_3
      45: invokeinterface #250,  3          // InterfaceMethod org/slf4j/Logger.debug:(Ljava/lang/String;Ljava/lang/Throwable;)V
      50: return
    Exception table:
       from    to  target type
          11    35    38   Class java/lang/Throwable

  public void waitUntilReady();
    Code:
       0: aload_0
       1: getfield      #109                // Field queue:Ljava/util/concurrent/ArrayBlockingQueue;
       4: aload_0
       5: getfield      #124                // Field config:Lio/dekorate/deps/kubernetes/client/Config;
       8: invokevirtual #257                // Method io/dekorate/deps/kubernetes/client/Config.getWebsocketTimeout:()J
      11: getstatic     #263                // Field java/util/concurrent/TimeUnit.MILLISECONDS:Ljava/util/concurrent/TimeUnit;
      14: invokestatic  #266                // Method io/dekorate/deps/kubernetes/client/utils/Utils.waitUntilReady:(Ljava/util/concurrent/BlockingQueue;JLjava/util/concurrent/TimeUnit;)Z
      17: pop
      18: return

  public void onOpen(io.dekorate.deps.okhttp3.WebSocket, io.dekorate.deps.okhttp3.Response);
    Code:
       0: aload_0
       1: getfield      #132                // Field in:Ljava/io/InputStream;
       4: instanceof    #272                // class java/io/PipedInputStream
       7: ifeq          31
      10: aload_0
      11: getfield      #144                // Field input:Ljava/io/PipedOutputStream;
      14: ifnull        31
      17: aload_0
      18: getfield      #144                // Field input:Ljava/io/PipedOutputStream;
      21: aload_0
      22: getfield      #132                // Field in:Ljava/io/InputStream;
      25: checkcast     #272                // class java/io/PipedInputStream
      28: invokevirtual #278                // Method java/io/PipedOutputStream.connect:(Ljava/io/PipedInputStream;)V
      31: aload_0
      32: getfield      #138                // Field out:Ljava/io/OutputStream;
      35: instanceof    #274                // class java/io/PipedOutputStream
      38: ifeq          62
      41: aload_0
      42: getfield      #146                // Field output:Ljava/io/PipedInputStream;
      45: ifnull        62
      48: aload_0
      49: getfield      #146                // Field output:Ljava/io/PipedInputStream;
      52: aload_0
      53: getfield      #138                // Field out:Ljava/io/OutputStream;
      56: checkcast     #274                // class java/io/PipedOutputStream
      59: invokevirtual #281                // Method java/io/PipedInputStream.connect:(Ljava/io/PipedOutputStream;)V
      62: aload_0
      63: getfield      #140                // Field err:Ljava/io/OutputStream;
      66: instanceof    #274                // class java/io/PipedOutputStream
      69: ifeq          93
      72: aload_0
      73: getfield      #148                // Field error:Ljava/io/PipedInputStream;
      76: ifnull        93
      79: aload_0
      80: getfield      #148                // Field error:Ljava/io/PipedInputStream;
      83: aload_0
      84: getfield      #140                // Field err:Ljava/io/OutputStream;
      87: checkcast     #274                // class java/io/PipedOutputStream
      90: invokevirtual #281                // Method java/io/PipedInputStream.connect:(Ljava/io/PipedOutputStream;)V
      93: aload_0
      94: getfield      #142                // Field errChannel:Ljava/io/OutputStream;
      97: instanceof    #274                // class java/io/PipedOutputStream
     100: ifeq          124
     103: aload_0
     104: getfield      #150                // Field errorChannel:Ljava/io/PipedInputStream;
     107: ifnull        124
     110: aload_0
     111: getfield      #150                // Field errorChannel:Ljava/io/PipedInputStream;
     114: aload_0
     115: getfield      #142                // Field errChannel:Ljava/io/OutputStream;
     118: checkcast     #274                // class java/io/PipedOutputStream
     121: invokevirtual #281                // Method java/io/PipedInputStream.connect:(Ljava/io/PipedOutputStream;)V
     124: aload_0
     125: getfield      #87                 // Field webSocketRef:Ljava/util/concurrent/atomic/AtomicReference;
     128: aload_1
     129: invokevirtual #283                // Method java/util/concurrent/atomic/AtomicReference.set:(Ljava/lang/Object;)V
     132: aload_0
     133: getfield      #95                 // Field executorService:Ljava/util/concurrent/ExecutorService;
     136: aload_0
     137: getfield      #176                // Field pumper:Lio/dekorate/deps/kubernetes/client/utils/InputStreamPumper;
     140: invokeinterface #289,  2          // InterfaceMethod java/util/concurrent/ExecutorService.submit:(Ljava/lang/Runnable;)Ljava/util/concurrent/Future;
     145: pop
     146: aload_0
     147: getfield      #102                // Field started:Ljava/util/concurrent/atomic/AtomicBoolean;
     150: iconst_1
     151: invokevirtual #204                // Method java/util/concurrent/atomic/AtomicBoolean.set:(Z)V
     154: aload_0
     155: getfield      #109                // Field queue:Ljava/util/concurrent/ArrayBlockingQueue;
     158: iconst_1
     159: invokestatic  #295                // Method java/lang/Boolean.valueOf:(Z)Ljava/lang/Boolean;
     162: invokevirtual #299                // Method java/util/concurrent/ArrayBlockingQueue.add:(Ljava/lang/Object;)Z
     165: pop
     166: aload_0
     167: getfield      #126                // Field listener:Lio/dekorate/deps/kubernetes/client/dsl/ExecListener;
     170: ifnull        248
     173: aload_0
     174: getfield      #126                // Field listener:Lio/dekorate/deps/kubernetes/client/dsl/ExecListener;
     177: aload_2
     178: invokeinterface #304,  2          // InterfaceMethod io/dekorate/deps/kubernetes/client/dsl/ExecListener.onOpen:(Lio/dekorate/deps/okhttp3/Response;)V
     183: goto          248
     186: astore_3
     187: aload_0
     188: getfield      #109                // Field queue:Ljava/util/concurrent/ArrayBlockingQueue;
     191: new           #306                // class io/dekorate/deps/kubernetes/client/KubernetesClientException
     194: dup
     195: aload_2
     196: invokestatic  #312                // Method io/dekorate/deps/kubernetes/client/dsl/base/OperationSupport.createStatus:(Lio/dekorate/deps/okhttp3/Response;)Lio/dekorate/deps/kubernetes/api/model/Status;
     199: invokespecial #315                // Method io/dekorate/deps/kubernetes/client/KubernetesClientException."<init>":(Lio/dekorate/deps/kubernetes/api/model/Status;)V
     202: invokevirtual #299                // Method java/util/concurrent/ArrayBlockingQueue.add:(Ljava/lang/Object;)Z
     205: pop
     206: aload_0
     207: getfield      #126                // Field listener:Lio/dekorate/deps/kubernetes/client/dsl/ExecListener;
     210: ifnull        248
     213: aload_0
     214: getfield      #126                // Field listener:Lio/dekorate/deps/kubernetes/client/dsl/ExecListener;
     217: aload_2
     218: invokeinterface #304,  2          // InterfaceMethod io/dekorate/deps/kubernetes/client/dsl/ExecListener.onOpen:(Lio/dekorate/deps/okhttp3/Response;)V
     223: goto          248
     226: astore        4
     228: aload_0
     229: getfield      #126                // Field listener:Lio/dekorate/deps/kubernetes/client/dsl/ExecListener;
     232: ifnull        245
     235: aload_0
     236: getfield      #126                // Field listener:Lio/dekorate/deps/kubernetes/client/dsl/ExecListener;
     239: aload_2
     240: invokeinterface #304,  2          // InterfaceMethod io/dekorate/deps/kubernetes/client/dsl/ExecListener.onOpen:(Lio/dekorate/deps/okhttp3/Response;)V
     245: aload         4
     247: athrow
     248: return
    Exception table:
       from    to  target type
           0   166   186   Class java/io/IOException
           0   166   226   any
         186   206   226   any
         226   228   226   any

  public void onFailure(io.dekorate.deps.okhttp3.WebSocket, java.lang.Throwable, io.dekorate.deps.okhttp3.Response);
    Code:
       0: aload_0
       1: getfield      #111                // Field explicitlyClosed:Ljava/util/concurrent/atomic/AtomicBoolean;
       4: invokevirtual #237                // Method java/util/concurrent/atomic/AtomicBoolean.get:()Z
       7: ifne          32
      10: aload_0
      11: getfield      #115                // Field closed:Ljava/util/concurrent/atomic/AtomicBoolean;
      14: invokevirtual #237                // Method java/util/concurrent/atomic/AtomicBoolean.get:()Z
      17: ifne          32
      20: aload_0
      21: getfield      #113                // Field failed:Ljava/util/concurrent/atomic/AtomicBoolean;
      24: iconst_0
      25: iconst_1
      26: invokevirtual #217                // Method java/util/concurrent/atomic/AtomicBoolean.compareAndSet:(ZZ)Z
      29: ifne          97
      32: getstatic     #242                // Field LOGGER:Lorg/slf4j/Logger;
      35: invokeinterface #325,  1          // InterfaceMethod org/slf4j/Logger.isDebugEnabled:()Z
      40: ifeq          96
      43: getstatic     #242                // Field LOGGER:Lorg/slf4j/Logger;
      46: new           #327                // class java/lang/StringBuilder
      49: dup
      50: invokespecial #328                // Method java/lang/StringBuilder."<init>":()V
      53: ldc_w         #330                // String Received [
      56: invokevirtual #334                // Method java/lang/StringBuilder.append:(Ljava/lang/String;)Ljava/lang/StringBuilder;
      59: aload_2
      60: invokevirtual #340                // Method java/lang/Object.getClass:()Ljava/lang/Class;
      63: invokevirtual #346                // Method java/lang/Class.getCanonicalName:()Ljava/lang/String;
      66: invokevirtual #334                // Method java/lang/StringBuilder.append:(Ljava/lang/String;)Ljava/lang/StringBuilder;
      69: ldc_w         #348                // String ], with message:[
      72: invokevirtual #334                // Method java/lang/StringBuilder.append:(Ljava/lang/String;)Ljava/lang/StringBuilder;
      75: aload_2
      76: invokevirtual #351                // Method java/lang/Throwable.getMessage:()Ljava/lang/String;
      79: invokevirtual #334                // Method java/lang/StringBuilder.append:(Ljava/lang/String;)Ljava/lang/StringBuilder;
      82: ldc_w         #353                // String ] after ExecWebSocketListener is closed, Ignoring.
      85: invokevirtual #334                // Method java/lang/StringBuilder.append:(Ljava/lang/String;)Ljava/lang/StringBuilder;
      88: invokevirtual #356                // Method java/lang/StringBuilder.toString:()Ljava/lang/String;
      91: invokeinterface #360,  2          // InterfaceMethod org/slf4j/Logger.warn:(Ljava/lang/String;)V
      96: return
      97: aload_3
      98: invokestatic  #312                // Method io/dekorate/deps/kubernetes/client/dsl/base/OperationSupport.createStatus:(Lio/dekorate/deps/okhttp3/Response;)Lio/dekorate/deps/kubernetes/api/model/Status;
     101: astore        4
     103: getstatic     #242                // Field LOGGER:Lorg/slf4j/Logger;
     106: new           #327                // class java/lang/StringBuilder
     109: dup
     110: invokespecial #328                // Method java/lang/StringBuilder."<init>":()V
     113: ldc_w         #362                // String Exec Failure: HTTP:
     116: invokevirtual #334                // Method java/lang/StringBuilder.append:(Ljava/lang/String;)Ljava/lang/StringBuilder;
     119: aload         4
     121: invokevirtual #368                // Method io/dekorate/deps/kubernetes/api/model/Status.getCode:()Ljava/lang/Integer;
     124: invokevirtual #371                // Method java/lang/StringBuilder.append:(Ljava/lang/Object;)Ljava/lang/StringBuilder;
     127: ldc_w         #373                // String . Message:
     130: invokevirtual #334                // Method java/lang/StringBuilder.append:(Ljava/lang/String;)Ljava/lang/StringBuilder;
     133: aload         4
     135: invokevirtual #374                // Method io/dekorate/deps/kubernetes/api/model/Status.getMessage:()Ljava/lang/String;
     138: invokevirtual #334                // Method java/lang/StringBuilder.append:(Ljava/lang/String;)Ljava/lang/StringBuilder;
     141: invokevirtual #356                // Method java/lang/StringBuilder.toString:()Ljava/lang/String;
     144: aload_2
     145: invokeinterface #376,  3          // InterfaceMethod org/slf4j/Logger.error:(Ljava/lang/String;Ljava/lang/Throwable;)V
     150: aload_0
     151: getfield      #102                // Field started:Ljava/util/concurrent/atomic/AtomicBoolean;
     154: invokevirtual #237                // Method java/util/concurrent/atomic/AtomicBoolean.get:()Z
     157: ifne          177
     160: aload_0
     161: getfield      #109                // Field queue:Ljava/util/concurrent/ArrayBlockingQueue;
     164: new           #306                // class io/dekorate/deps/kubernetes/client/KubernetesClientException
     167: dup
     168: aload         4
     170: invokespecial #315                // Method io/dekorate/deps/kubernetes/client/KubernetesClientException."<init>":(Lio/dekorate/deps/kubernetes/api/model/Status;)V
     173: invokevirtual #299                // Method java/util/concurrent/ArrayBlockingQueue.add:(Ljava/lang/Object;)Z
     176: pop
     177: aload_0
     178: invokespecial #378                // Method cleanUpOnce:()V
     181: aload_0
     182: getfield      #126                // Field listener:Lio/dekorate/deps/kubernetes/client/dsl/ExecListener;
     185: ifnull        225
     188: aload_0
     189: getfield      #126                // Field listener:Lio/dekorate/deps/kubernetes/client/dsl/ExecListener;
     192: aload_2
     193: aload_3
     194: invokeinterface #381,  3          // InterfaceMethod io/dekorate/deps/kubernetes/client/dsl/ExecListener.onFailure:(Ljava/lang/Throwable;Lio/dekorate/deps/okhttp3/Response;)V
     199: goto          225
     202: astore        5
     204: aload_0
     205: getfield      #126                // Field listener:Lio/dekorate/deps/kubernetes/client/dsl/ExecListener;
     208: ifnull        222
     211: aload_0
     212: getfield      #126                // Field listener:Lio/dekorate/deps/kubernetes/client/dsl/ExecListener;
     215: aload_2
     216: aload_3
     217: invokeinterface #381,  3          // InterfaceMethod io/dekorate/deps/kubernetes/client/dsl/ExecListener.onFailure:(Ljava/lang/Throwable;Lio/dekorate/deps/okhttp3/Response;)V
     222: aload         5
     224: athrow
     225: return
    Exception table:
       from    to  target type
          97   181   202   any
         202   204   202   any

  public void onMessage(io.dekorate.deps.okhttp3.WebSocket, io.dekorate.deps.okio.ByteString);
    Code:
       0: aload_2
       1: iconst_0
       2: invokevirtual #393                // Method io/dekorate/deps/okio/ByteString.getByte:(I)B
       5: istore_3
       6: aload_2
       7: iconst_1
       8: invokevirtual #397                // Method io/dekorate/deps/okio/ByteString.substring:(I)Lio/dekorate/deps/okio/ByteString;
      11: astore        4
      13: aload         4
      15: invokevirtual #401                // Method io/dekorate/deps/okio/ByteString.size:()I
      18: ifle          142
      21: iload_3
      22: tableswitch   { // 1 to 3
                     1: 48
                     2: 70
                     3: 92
               default: 114
          }
      48: aload_0
      49: getfield      #138                // Field out:Ljava/io/OutputStream;
      52: ifnull        142
      55: aload_0
      56: getfield      #138                // Field out:Ljava/io/OutputStream;
      59: aload         4
      61: invokevirtual #405                // Method io/dekorate/deps/okio/ByteString.toByteArray:()[B
      64: invokevirtual #410                // Method java/io/OutputStream.write:([B)V
      67: goto          142
      70: aload_0
      71: getfield      #140                // Field err:Ljava/io/OutputStream;
      74: ifnull        142
      77: aload_0
      78: getfield      #140                // Field err:Ljava/io/OutputStream;
      81: aload         4
      83: invokevirtual #405                // Method io/dekorate/deps/okio/ByteString.toByteArray:()[B
      86: invokevirtual #410                // Method java/io/OutputStream.write:([B)V
      89: goto          142
      92: aload_0
      93: getfield      #142                // Field errChannel:Ljava/io/OutputStream;
      96: ifnull        142
      99: aload_0
     100: getfield      #142                // Field errChannel:Ljava/io/OutputStream;
     103: aload         4
     105: invokevirtual #405                // Method io/dekorate/deps/okio/ByteString.toByteArray:()[B
     108: invokevirtual #410                // Method java/io/OutputStream.write:([B)V
     111: goto          142
     114: new           #270                // class java/io/IOException
     117: dup
     118: new           #327                // class java/lang/StringBuilder
     121: dup
     122: invokespecial #328                // Method java/lang/StringBuilder."<init>":()V
     125: ldc_w         #412                // String Unknown stream ID
     128: invokevirtual #334                // Method java/lang/StringBuilder.append:(Ljava/lang/String;)Ljava/lang/StringBuilder;
     131: iload_3
     132: invokevirtual #415                // Method java/lang/StringBuilder.append:(I)Ljava/lang/StringBuilder;
     135: invokevirtual #356                // Method java/lang/StringBuilder.toString:()Ljava/lang/String;
     138: invokespecial #417                // Method java/io/IOException."<init>":(Ljava/lang/String;)V
     141: athrow
     142: goto          151
     145: astore_3
     146: aload_3
     147: invokestatic  #421                // Method io/dekorate/deps/kubernetes/client/KubernetesClientException.launderThrowable:(Ljava/lang/Throwable;)Ljava/lang/RuntimeException;
     150: athrow
     151: return
    Exception table:
       from    to  target type
           0   142   145   Class java/io/IOException

  public void onClosing(io.dekorate.deps.okhttp3.WebSocket, int, java.lang.String);
    Code:
       0: aload_0
       1: aload_1
       2: iload_2
       3: aload_3
       4: invokespecial #198                // Method close:(Lio/dekorate/deps/okhttp3/WebSocket;ILjava/lang/String;)V
       7: return

  public void onClosed(io.dekorate.deps.okhttp3.WebSocket, int, java.lang.String);
    Code:
       0: aload_0
       1: getfield      #115                // Field closed:Ljava/util/concurrent/atomic/AtomicBoolean;
       4: iconst_0
       5: iconst_1
       6: invokevirtual #217                // Method java/util/concurrent/atomic/AtomicBoolean.compareAndSet:(ZZ)Z
       9: ifeq          22
      12: aload_0
      13: getfield      #113                // Field failed:Ljava/util/concurrent/atomic/AtomicBoolean;
      16: invokevirtual #237                // Method java/util/concurrent/atomic/AtomicBoolean.get:()Z
      19: ifeq          23
      22: return
      23: getstatic     #242                // Field LOGGER:Lorg/slf4j/Logger;
      26: ldc_w         #429                // String Exec Web Socket: On Close with code:[{}], due to: [{}]
      29: iload_2
      30: invokestatic  #434                // Method java/lang/Integer.valueOf:(I)Ljava/lang/Integer;
      33: aload_3
      34: invokeinterface #437,  4          // InterfaceMethod org/slf4j/Logger.debug:(Ljava/lang/String;Ljava/lang/Object;Ljava/lang/Object;)V
      39: aload_0
      40: getfield      #111                // Field explicitlyClosed:Ljava/util/concurrent/atomic/AtomicBoolean;
      43: invokevirtual #237                // Method java/util/concurrent/atomic/AtomicBoolean.get:()Z
      46: ifeq          53
      49: aload_0
      50: invokespecial #378                // Method cleanUpOnce:()V
      53: aload_0
      54: getfield      #126                // Field listener:Lio/dekorate/deps/kubernetes/client/dsl/ExecListener;
      57: ifnull        97
      60: aload_0
      61: getfield      #126                // Field listener:Lio/dekorate/deps/kubernetes/client/dsl/ExecListener;
      64: iload_2
      65: aload_3
      66: invokeinterface #440,  3          // InterfaceMethod io/dekorate/deps/kubernetes/client/dsl/ExecListener.onClose:(ILjava/lang/String;)V
      71: goto          97
      74: astore        4
      76: aload_0
      77: getfield      #126                // Field listener:Lio/dekorate/deps/kubernetes/client/dsl/ExecListener;
      80: ifnull        94
      83: aload_0
      84: getfield      #126                // Field listener:Lio/dekorate/deps/kubernetes/client/dsl/ExecListener;
      87: iload_2
      88: aload_3
      89: invokeinterface #440,  3          // InterfaceMethod io/dekorate/deps/kubernetes/client/dsl/ExecListener.onClose:(ILjava/lang/String;)V
      94: aload         4
      96: athrow
      97: return
    Exception table:
       from    to  target type
          39    53    74   any
          74    76    74   any

  public java.io.OutputStream getInput();
    Code:
       0: aload_0
       1: getfield      #144                // Field input:Ljava/io/PipedOutputStream;
       4: areturn

  public java.io.InputStream getOutput();
    Code:
       0: aload_0
       1: getfield      #146                // Field output:Ljava/io/PipedInputStream;
       4: areturn

  public java.io.InputStream getError();
    Code:
       0: aload_0
       1: getfield      #148                // Field error:Ljava/io/PipedInputStream;
       4: areturn

  public java.io.InputStream getErrorChannel();
    Code:
       0: aload_0
       1: getfield      #150                // Field errorChannel:Ljava/io/PipedInputStream;
       4: areturn

  public void resize(int, int);
    Code:
       0: iload_1
       1: iflt          8
       4: iload_2
       5: ifge          9
       8: return
       9: new           #452                // class java/util/HashMap
      12: dup
      13: iconst_4
      14: invokespecial #453                // Method java/util/HashMap."<init>":(I)V
      17: astore_3
      18: aload_3
      19: ldc           #20                 // String Height
      21: iload_2
      22: invokestatic  #434                // Method java/lang/Integer.valueOf:(I)Ljava/lang/Integer;
      25: invokeinterface #459,  3          // InterfaceMethod java/util/Map.put:(Ljava/lang/Object;Ljava/lang/Object;)Ljava/lang/Object;
      30: pop
      31: aload_3
      32: ldc           #23                 // String Width
      34: iload_1
      35: invokestatic  #434                // Method java/lang/Integer.valueOf:(I)Ljava/lang/Integer;
      38: invokeinterface #459,  3          // InterfaceMethod java/util/Map.put:(Ljava/lang/Object;Ljava/lang/Object;)Ljava/lang/Object;
      43: pop
      44: aload_0
      45: getfield      #181                // Field objectMapper:Lio/dekorate/deps/jackson/databind/ObjectMapper;
      48: aload_3
      49: invokevirtual #463                // Method io/dekorate/deps/jackson/databind/ObjectMapper.writeValueAsBytes:(Ljava/lang/Object;)[B
      52: astore        4
      54: aload_0
      55: aload         4
      57: iconst_4
      58: invokespecial #467                // Method send:([BB)V
      61: goto          70
      64: astore_3
      65: aload_3
      66: invokestatic  #421                // Method io/dekorate/deps/kubernetes/client/KubernetesClientException.launderThrowable:(Ljava/lang/Throwable;)Ljava/lang/RuntimeException;
      69: athrow
      70: return
    Exception table:
       from    to  target type
           9    61    64   Class java/lang/Exception

  private void send(byte[], byte) throws java.io.IOException;
    Code:
       0: aload_1
       1: arraylength
       2: ifle          55
       5: aload_0
       6: getfield      #87                 // Field webSocketRef:Ljava/util/concurrent/atomic/AtomicReference;
       9: invokevirtual #193                // Method java/util/concurrent/atomic/AtomicReference.get:()Ljava/lang/Object;
      12: checkcast     #195                // class io/dekorate/deps/okhttp3/WebSocket
      15: astore_3
      16: aload_3
      17: ifnull        55
      20: aload_1
      21: arraylength
      22: iconst_1
      23: iadd
      24: newarray       byte
      26: astore        4
      28: aload         4
      30: iconst_0
      31: iload_2
      32: bastore
      33: aload_1
      34: iconst_0
      35: aload         4
      37: iconst_1
      38: aload_1
      39: arraylength
      40: invokestatic  #480                // Method java/lang/System.arraycopy:(Ljava/lang/Object;ILjava/lang/Object;II)V
      43: aload_3
      44: aload         4
      46: invokestatic  #484                // Method io/dekorate/deps/okio/ByteString.of:([B)Lio/dekorate/deps/okio/ByteString;
      49: invokeinterface #487,  2          // InterfaceMethod io/dekorate/deps/okhttp3/WebSocket.send:(Lio/dekorate/deps/okio/ByteString;)Z
      54: pop
      55: return

  private void send(byte[]) throws java.io.IOException;
    Code:
       0: aload_0
       1: aload_1
       2: iconst_0
       3: invokespecial #467                // Method send:([BB)V
       6: return

  private static java.io.InputStream inputStreamOrPipe(java.io.InputStream, java.io.PipedOutputStream, java.util.Set<java.io.Closeable>, java.lang.Integer);
    Code:
       0: aload_0
       1: ifnull        6
       4: aload_0
       5: areturn
       6: aload_1
       7: ifnull        57
      10: aload_3
      11: ifnonnull     24
      14: new           #272                // class java/io/PipedInputStream
      17: dup
      18: invokespecial #491                // Method java/io/PipedInputStream."<init>":()V
      21: goto          35
      24: new           #272                // class java/io/PipedInputStream
      27: dup
      28: aload_3
      29: invokevirtual #494                // Method java/lang/Integer.intValue:()I
      32: invokespecial #495                // Method java/io/PipedInputStream."<init>":(I)V
      35: astore        4
      37: aload_2
      38: aload_1
      39: invokeinterface #498,  2          // InterfaceMethod java/util/Set.add:(Ljava/lang/Object;)Z
      44: pop
      45: aload_2
      46: aload         4
      48: invokeinterface #498,  2          // InterfaceMethod java/util/Set.add:(Ljava/lang/Object;)Z
      53: pop
      54: aload         4
      56: areturn
      57: aconst_null
      58: areturn

  private static java.io.OutputStream outputStreamOrPipe(java.io.OutputStream, java.io.PipedInputStream, java.util.Set<java.io.Closeable>);
    Code:
       0: aload_0
       1: ifnull        6
       4: aload_0
       5: areturn
       6: aload_1
       7: ifnull        36
      10: new           #274                // class java/io/PipedOutputStream
      13: dup
      14: invokespecial #502                // Method java/io/PipedOutputStream."<init>":()V
      17: astore_3
      18: aload_2
      19: aload_1
      20: invokeinterface #498,  2          // InterfaceMethod java/util/Set.add:(Ljava/lang/Object;)Z
      25: pop
      26: aload_2
      27: aload_3
      28: invokeinterface #498,  2          // InterfaceMethod java/util/Set.add:(Ljava/lang/Object;)Z
      33: pop
      34: aload_3
      35: areturn
      36: aconst_null
      37: areturn

  private void lambda$new$0(byte[]);
    Code:
       0: aload_0
       1: aload_1
       2: invokespecial #505                // Method send:([B)V
       5: goto          9
       8: astore_2
       9: return
    Exception table:
       from    to  target type
           0     5     8   Class java/lang/Exception

  static {};
    Code:
       0: ldc           #2                  // class io/dekorate/deps/kubernetes/client/dsl/internal/ExecWebSocketListener
       2: invokestatic  #513                // Method org/slf4j/LoggerFactory.getLogger:(Ljava/lang/Class;)Lorg/slf4j/Logger;
       5: putstatic     #242                // Field LOGGER:Lorg/slf4j/Logger;
       8: return
}
