Compiled from "JobOperationsImpl.java"
public class io.dekorate.deps.kubernetes.client.dsl.internal.JobOperationsImpl extends io.dekorate.deps.kubernetes.client.dsl.base.HasMetadataOperation<io.dekorate.deps.kubernetes.api.model.batch.Job, io.dekorate.deps.kubernetes.api.model.batch.JobList, io.dekorate.deps.kubernetes.api.model.batch.DoneableJob, io.dekorate.deps.kubernetes.client.dsl.ScalableResource<io.dekorate.deps.kubernetes.api.model.batch.Job, io.dekorate.deps.kubernetes.api.model.batch.DoneableJob>> implements io.dekorate.deps.kubernetes.client.dsl.ScalableResource<io.dekorate.deps.kubernetes.api.model.batch.Job, io.dekorate.deps.kubernetes.api.model.batch.DoneableJob> {
  static final transient org.slf4j.Logger LOG;

  public io.dekorate.deps.kubernetes.client.dsl.internal.JobOperationsImpl(io.dekorate.deps.okhttp3.OkHttpClient, io.dekorate.deps.kubernetes.client.Config);
    Code:
       0: aload_0
       1: aload_1
       2: aload_2
       3: aconst_null
       4: invokespecial #25                 // Method "<init>":(Lio/dekorate/deps/okhttp3/OkHttpClient;Lio/dekorate/deps/kubernetes/client/Config;Ljava/lang/String;)V
       7: return

  public io.dekorate.deps.kubernetes.client.dsl.internal.JobOperationsImpl(io.dekorate.deps.okhttp3.OkHttpClient, io.dekorate.deps.kubernetes.client.Config, java.lang.String);
    Code:
       0: aload_0
       1: new           #33                 // class io/dekorate/deps/kubernetes/client/dsl/base/OperationContext
       4: dup
       5: invokespecial #36                 // Method io/dekorate/deps/kubernetes/client/dsl/base/OperationContext."<init>":()V
       8: aload_1
       9: invokevirtual #40                 // Method io/dekorate/deps/kubernetes/client/dsl/base/OperationContext.withOkhttpClient:(Lio/dekorate/deps/okhttp3/OkHttpClient;)Lio/dekorate/deps/kubernetes/client/dsl/base/OperationContext;
      12: aload_2
      13: invokevirtual #44                 // Method io/dekorate/deps/kubernetes/client/dsl/base/OperationContext.withConfig:(Lio/dekorate/deps/kubernetes/client/Config;)Lio/dekorate/deps/kubernetes/client/dsl/base/OperationContext;
      16: aload_3
      17: invokevirtual #48                 // Method io/dekorate/deps/kubernetes/client/dsl/base/OperationContext.withNamespace:(Ljava/lang/String;)Lio/dekorate/deps/kubernetes/client/dsl/base/OperationContext;
      20: iconst_1
      21: invokevirtual #52                 // Method io/dekorate/deps/kubernetes/client/dsl/base/OperationContext.withCascading:(Z)Lio/dekorate/deps/kubernetes/client/dsl/base/OperationContext;
      24: invokespecial #55                 // Method "<init>":(Lio/dekorate/deps/kubernetes/client/dsl/base/OperationContext;)V
      27: return

  public io.dekorate.deps.kubernetes.client.dsl.internal.JobOperationsImpl(io.dekorate.deps.kubernetes.client.dsl.base.OperationContext);
    Code:
       0: aload_0
       1: aload_1
       2: ldc           #59                 // String batch
       4: invokevirtual #62                 // Method io/dekorate/deps/kubernetes/client/dsl/base/OperationContext.withApiGroupName:(Ljava/lang/String;)Lio/dekorate/deps/kubernetes/client/dsl/base/OperationContext;
       7: ldc           #64                 // String v1
       9: invokevirtual #67                 // Method io/dekorate/deps/kubernetes/client/dsl/base/OperationContext.withApiGroupVersion:(Ljava/lang/String;)Lio/dekorate/deps/kubernetes/client/dsl/base/OperationContext;
      12: ldc           #69                 // String jobs
      14: invokevirtual #72                 // Method io/dekorate/deps/kubernetes/client/dsl/base/OperationContext.withPlural:(Ljava/lang/String;)Lio/dekorate/deps/kubernetes/client/dsl/base/OperationContext;
      17: invokespecial #73                 // Method io/dekorate/deps/kubernetes/client/dsl/base/HasMetadataOperation."<init>":(Lio/dekorate/deps/kubernetes/client/dsl/base/OperationContext;)V
      20: aload_0
      21: ldc           #75                 // class io/dekorate/deps/kubernetes/api/model/batch/Job
      23: putfield      #79                 // Field type:Ljava/lang/Class;
      26: aload_0
      27: ldc           #81                 // class io/dekorate/deps/kubernetes/api/model/batch/JobList
      29: putfield      #84                 // Field listType:Ljava/lang/Class;
      32: aload_0
      33: ldc           #86                 // class io/dekorate/deps/kubernetes/api/model/batch/DoneableJob
      35: putfield      #89                 // Field doneableType:Ljava/lang/Class;
      38: return

  public io.dekorate.deps.kubernetes.client.dsl.internal.JobOperationsImpl newInstance(io.dekorate.deps.kubernetes.client.dsl.base.OperationContext);
    Code:
       0: new           #2                  // class io/dekorate/deps/kubernetes/client/dsl/internal/JobOperationsImpl
       3: dup
       4: aload_1
       5: invokespecial #55                 // Method "<init>":(Lio/dekorate/deps/kubernetes/client/dsl/base/OperationContext;)V
       8: areturn

  public io.dekorate.deps.kubernetes.client.dsl.ScalableResource<io.dekorate.deps.kubernetes.api.model.batch.Job, io.dekorate.deps.kubernetes.api.model.batch.DoneableJob> load(java.io.InputStream);
    Code:
       0: aload_1
       1: ldc           #75                 // class io/dekorate/deps/kubernetes/api/model/batch/Job
       3: invokestatic  #102                // Method unmarshal:(Ljava/io/InputStream;Ljava/lang/Class;)Ljava/lang/Object;
       6: checkcast     #75                 // class io/dekorate/deps/kubernetes/api/model/batch/Job
       9: astore_2
      10: new           #2                  // class io/dekorate/deps/kubernetes/client/dsl/internal/JobOperationsImpl
      13: dup
      14: aload_0
      15: getfield      #104                // Field context:Lio/dekorate/deps/kubernetes/client/dsl/base/OperationContext;
      18: aload_2
      19: invokevirtual #108                // Method io/dekorate/deps/kubernetes/client/dsl/base/OperationContext.withItem:(Ljava/lang/Object;)Lio/dekorate/deps/kubernetes/client/dsl/base/OperationContext;
      22: invokespecial #55                 // Method "<init>":(Lio/dekorate/deps/kubernetes/client/dsl/base/OperationContext;)V
      25: areturn
      26: astore_2
      27: aload_2
      28: invokestatic  #114                // Method io/dekorate/deps/kubernetes/client/KubernetesClientException.launderThrowable:(Ljava/lang/Throwable;)Ljava/lang/RuntimeException;
      31: athrow
    Exception table:
       from    to  target type
           0    25    26   Class java/lang/Throwable

  public io.dekorate.deps.kubernetes.client.dsl.ScalableResource<io.dekorate.deps.kubernetes.api.model.batch.Job, io.dekorate.deps.kubernetes.api.model.batch.DoneableJob> fromServer();
    Code:
       0: new           #2                  // class io/dekorate/deps/kubernetes/client/dsl/internal/JobOperationsImpl
       3: dup
       4: aload_0
       5: getfield      #104                // Field context:Lio/dekorate/deps/kubernetes/client/dsl/base/OperationContext;
       8: iconst_1
       9: invokevirtual #126                // Method io/dekorate/deps/kubernetes/client/dsl/base/OperationContext.withReloadingFromServer:(Z)Lio/dekorate/deps/kubernetes/client/dsl/base/OperationContext;
      12: invokespecial #55                 // Method "<init>":(Lio/dekorate/deps/kubernetes/client/dsl/base/OperationContext;)V
      15: areturn

  public io.dekorate.deps.kubernetes.api.model.batch.Job scale(int);
    Code:
       0: aload_0
       1: iload_1
       2: iconst_0
       3: invokevirtual #131                // Method scale:(IZ)Lio/dekorate/deps/kubernetes/api/model/batch/Job;
       6: areturn

  public io.dekorate.deps.kubernetes.api.model.v1.Scale scale();
    Code:
       0: aload_0
       1: aconst_null
       2: invokevirtual #138                // Method handleScale:(Lio/dekorate/deps/kubernetes/api/model/v1/Scale;)Lio/dekorate/deps/kubernetes/api/model/v1/Scale;
       5: areturn

  public io.dekorate.deps.kubernetes.api.model.v1.Scale scale(io.dekorate.deps.kubernetes.api.model.v1.Scale);
    Code:
       0: aload_0
       1: aload_1
       2: invokevirtual #138                // Method handleScale:(Lio/dekorate/deps/kubernetes/api/model/v1/Scale;)Lio/dekorate/deps/kubernetes/api/model/v1/Scale;
       5: areturn

  public io.dekorate.deps.kubernetes.api.model.batch.Job scale(int, boolean);
    Code:
       0: aload_0
       1: iconst_0
       2: invokevirtual #143                // Method cascading:(Z)Lio/dekorate/deps/kubernetes/client/dsl/EditReplacePatchDeletable;
       5: invokeinterface #149,  1          // InterfaceMethod io/dekorate/deps/kubernetes/client/dsl/EditReplacePatchDeletable.edit:()Ljava/lang/Object;
      10: checkcast     #86                 // class io/dekorate/deps/kubernetes/api/model/batch/DoneableJob
      13: invokevirtual #153                // Method io/dekorate/deps/kubernetes/api/model/batch/DoneableJob.editSpec:()Lio/dekorate/deps/kubernetes/api/model/batch/JobFluent$SpecNested;
      16: iload_1
      17: invokestatic  #159                // Method java/lang/Integer.valueOf:(I)Ljava/lang/Integer;
      20: invokeinterface #163,  2          // InterfaceMethod io/dekorate/deps/kubernetes/api/model/batch/JobFluent$SpecNested.withParallelism:(Ljava/lang/Integer;)Lio/dekorate/deps/kubernetes/api/model/batch/JobSpecFluent;
      25: checkcast     #10                 // class io/dekorate/deps/kubernetes/api/model/batch/JobFluent$SpecNested
      28: invokeinterface #166,  1          // InterfaceMethod io/dekorate/deps/kubernetes/api/model/batch/JobFluent$SpecNested.endSpec:()Ljava/lang/Object;
      33: checkcast     #86                 // class io/dekorate/deps/kubernetes/api/model/batch/DoneableJob
      36: invokevirtual #170                // Method io/dekorate/deps/kubernetes/api/model/batch/DoneableJob.done:()Lio/dekorate/deps/kubernetes/api/model/batch/Job;
      39: astore_3
      40: iload_2
      41: ifeq          56
      44: aload_0
      45: invokespecial #173                // Method waitUntilJobIsScaled:()V
      48: aload_0
      49: invokevirtual #176                // Method getMandatory:()Ljava/lang/Object;
      52: checkcast     #75                 // class io/dekorate/deps/kubernetes/api/model/batch/Job
      55: astore_3
      56: aload_3
      57: areturn

  private void waitUntilJobIsScaled();
    Code:
       0: new           #183                // class java/util/concurrent/CountDownLatch
       3: dup
       4: iconst_1
       5: invokespecial #186                // Method java/util/concurrent/CountDownLatch."<init>":(I)V
       8: astore_1
       9: new           #188                // class java/util/concurrent/atomic/AtomicReference
      12: dup
      13: invokespecial #189                // Method java/util/concurrent/atomic/AtomicReference."<init>":()V
      16: astore_2
      17: aload_0
      18: aload_2
      19: aload_1
      20: invokedynamic #206,  0            // InvokeDynamic #0:run:(Lio/dekorate/deps/kubernetes/client/dsl/internal/JobOperationsImpl;Ljava/util/concurrent/atomic/AtomicReference;Ljava/util/concurrent/CountDownLatch;)Ljava/lang/Runnable;
      25: astore_3
      26: invokestatic  #212                // Method java/util/concurrent/Executors.newSingleThreadScheduledExecutor:()Ljava/util/concurrent/ScheduledExecutorService;
      29: astore        4
      31: aload         4
      33: aload_3
      34: lconst_0
      35: ldc2_w        #213                // long 100l
      38: getstatic     #220                // Field java/util/concurrent/TimeUnit.MILLISECONDS:Ljava/util/concurrent/TimeUnit;
      41: invokeinterface #226,  7          // InterfaceMethod java/util/concurrent/ScheduledExecutorService.scheduleWithFixedDelay:(Ljava/lang/Runnable;JJLjava/util/concurrent/TimeUnit;)Ljava/util/concurrent/ScheduledFuture;
      46: astore        5
      48: aload_1
      49: aload_0
      50: invokevirtual #230                // Method getConfig:()Lio/dekorate/deps/kubernetes/client/Config;
      53: invokevirtual #236                // Method io/dekorate/deps/kubernetes/client/Config.getScaleTimeout:()J
      56: getstatic     #220                // Field java/util/concurrent/TimeUnit.MILLISECONDS:Ljava/util/concurrent/TimeUnit;
      59: invokevirtual #240                // Method java/util/concurrent/CountDownLatch.await:(JLjava/util/concurrent/TimeUnit;)Z
      62: pop
      63: aload         4
      65: invokeinterface #243,  1          // InterfaceMethod java/util/concurrent/ScheduledExecutorService.shutdown:()V
      70: goto          167
      73: astore        6
      75: invokestatic  #253                // Method java/lang/Thread.currentThread:()Ljava/lang/Thread;
      78: invokevirtual #256                // Method java/lang/Thread.interrupt:()V
      81: aload         5
      83: iconst_1
      84: invokeinterface #260,  2          // InterfaceMethod java/util/concurrent/ScheduledFuture.cancel:(Z)Z
      89: pop
      90: aload         4
      92: invokeinterface #243,  1          // InterfaceMethod java/util/concurrent/ScheduledExecutorService.shutdown:()V
      97: getstatic     #262                // Field LOG:Lorg/slf4j/Logger;
     100: ldc_w         #264                // String Only {}/{} pod(s) ready for Job: {} in namespace: {} - giving up
     103: iconst_4
     104: anewarray     #266                // class java/lang/Object
     107: dup
     108: iconst_0
     109: aload_2
     110: invokevirtual #269                // Method java/util/concurrent/atomic/AtomicReference.get:()Ljava/lang/Object;
     113: checkcast     #75                 // class io/dekorate/deps/kubernetes/api/model/batch/Job
     116: invokevirtual #273                // Method io/dekorate/deps/kubernetes/api/model/batch/Job.getStatus:()Lio/dekorate/deps/kubernetes/api/model/batch/JobStatus;
     119: invokevirtual #279                // Method io/dekorate/deps/kubernetes/api/model/batch/JobStatus.getActive:()Ljava/lang/Integer;
     122: aastore
     123: dup
     124: iconst_1
     125: aload_2
     126: invokevirtual #269                // Method java/util/concurrent/atomic/AtomicReference.get:()Ljava/lang/Object;
     129: checkcast     #75                 // class io/dekorate/deps/kubernetes/api/model/batch/Job
     132: invokevirtual #283                // Method io/dekorate/deps/kubernetes/api/model/batch/Job.getSpec:()Lio/dekorate/deps/kubernetes/api/model/batch/JobSpec;
     135: invokevirtual #288                // Method io/dekorate/deps/kubernetes/api/model/batch/JobSpec.getParallelism:()Ljava/lang/Integer;
     138: aastore
     139: dup
     140: iconst_2
     141: aload_2
     142: invokevirtual #269                // Method java/util/concurrent/atomic/AtomicReference.get:()Ljava/lang/Object;
     145: checkcast     #75                 // class io/dekorate/deps/kubernetes/api/model/batch/Job
     148: invokevirtual #292                // Method io/dekorate/deps/kubernetes/api/model/batch/Job.getMetadata:()Lio/dekorate/deps/kubernetes/api/model/ObjectMeta;
     151: invokevirtual #298                // Method io/dekorate/deps/kubernetes/api/model/ObjectMeta.getName:()Ljava/lang/String;
     154: aastore
     155: dup
     156: iconst_3
     157: aload_0
     158: getfield      #300                // Field namespace:Ljava/lang/String;
     161: aastore
     162: invokeinterface #306,  3          // InterfaceMethod org/slf4j/Logger.error:(Ljava/lang/String;[Ljava/lang/Object;)V
     167: return
    Exception table:
       from    to  target type
          48    70    73   Class java/lang/InterruptedException

  public java.lang.String getLog();
    Code:
       0: aload_0
       1: iconst_0
       2: invokestatic  #325                // Method java/lang/Boolean.valueOf:(Z)Ljava/lang/Boolean;
       5: invokevirtual #328                // Method getLog:(Ljava/lang/Boolean;)Ljava/lang/String;
       8: areturn

  public java.lang.String getLog(java.lang.Boolean);
    Code:
       0: new           #330                // class java/lang/StringBuilder
       3: dup
       4: invokespecial #331                // Method java/lang/StringBuilder."<init>":()V
       7: astore_2
       8: aload_0
       9: iconst_0
      10: invokespecial #335                // Method doGetLog:(Z)Ljava/util/List;
      13: astore_3
      14: aload_3
      15: invokeinterface #341,  1          // InterfaceMethod java/util/List.iterator:()Ljava/util/Iterator;
      20: astore        4
      22: aload         4
      24: invokeinterface #347,  1          // InterfaceMethod java/util/Iterator.hasNext:()Z
      29: ifeq          63
      32: aload         4
      34: invokeinterface #350,  1          // InterfaceMethod java/util/Iterator.next:()Ljava/lang/Object;
      39: checkcast     #352                // class io/dekorate/deps/kubernetes/client/dsl/PodResource
      42: astore        5
      44: aload_2
      45: aload         5
      47: aload_1
      48: invokeinterface #355,  2          // InterfaceMethod io/dekorate/deps/kubernetes/client/dsl/PodResource.getLog:(Ljava/lang/Boolean;)Ljava/lang/Object;
      53: checkcast     #357                // class java/lang/String
      56: invokevirtual #361                // Method java/lang/StringBuilder.append:(Ljava/lang/String;)Ljava/lang/StringBuilder;
      59: pop
      60: goto          22
      63: aload_2
      64: invokevirtual #364                // Method java/lang/StringBuilder.toString:()Ljava/lang/String;
      67: areturn

  private java.util.List<io.dekorate.deps.kubernetes.client.dsl.PodResource<io.dekorate.deps.kubernetes.api.model.Pod, io.dekorate.deps.kubernetes.api.model.DoneablePod>> doGetLog(boolean);
    Code:
       0: new           #377                // class java/util/ArrayList
       3: dup
       4: invokespecial #378                // Method java/util/ArrayList."<init>":()V
       7: astore_2
       8: aload_0
       9: invokevirtual #380                // Method fromServer:()Lio/dekorate/deps/kubernetes/client/dsl/ScalableResource;
      12: invokeinterface #381,  1          // InterfaceMethod io/dekorate/deps/kubernetes/client/dsl/ScalableResource.get:()Ljava/lang/Object;
      17: checkcast     #75                 // class io/dekorate/deps/kubernetes/api/model/batch/Job
      20: astore_3
      21: aload_3
      22: invokevirtual #292                // Method io/dekorate/deps/kubernetes/api/model/batch/Job.getMetadata:()Lio/dekorate/deps/kubernetes/api/model/ObjectMeta;
      25: invokevirtual #384                // Method io/dekorate/deps/kubernetes/api/model/ObjectMeta.getUid:()Ljava/lang/String;
      28: astore        4
      30: new           #386                // class io/dekorate/deps/kubernetes/client/dsl/internal/PodOperationsImpl
      33: dup
      34: new           #388                // class io/dekorate/deps/kubernetes/client/dsl/internal/PodOperationContext
      37: dup
      38: aload_0
      39: getfield      #104                // Field context:Lio/dekorate/deps/kubernetes/client/dsl/base/OperationContext;
      42: invokevirtual #392                // Method io/dekorate/deps/kubernetes/client/dsl/base/OperationContext.getClient:()Lio/dekorate/deps/okhttp3/OkHttpClient;
      45: aload_0
      46: getfield      #104                // Field context:Lio/dekorate/deps/kubernetes/client/dsl/base/OperationContext;
      49: invokevirtual #393                // Method io/dekorate/deps/kubernetes/client/dsl/base/OperationContext.getConfig:()Lio/dekorate/deps/kubernetes/client/Config;
      52: aload_0
      53: getfield      #104                // Field context:Lio/dekorate/deps/kubernetes/client/dsl/base/OperationContext;
      56: invokevirtual #396                // Method io/dekorate/deps/kubernetes/client/dsl/base/OperationContext.getPlural:()Ljava/lang/String;
      59: aload_0
      60: getfield      #104                // Field context:Lio/dekorate/deps/kubernetes/client/dsl/base/OperationContext;
      63: invokevirtual #399                // Method io/dekorate/deps/kubernetes/client/dsl/base/OperationContext.getNamespace:()Ljava/lang/String;
      66: aload_0
      67: getfield      #104                // Field context:Lio/dekorate/deps/kubernetes/client/dsl/base/OperationContext;
      70: invokevirtual #400                // Method io/dekorate/deps/kubernetes/client/dsl/base/OperationContext.getName:()Ljava/lang/String;
      73: aconst_null
      74: ldc           #64                 // String v1
      76: aload_0
      77: getfield      #104                // Field context:Lio/dekorate/deps/kubernetes/client/dsl/base/OperationContext;
      80: invokevirtual #403                // Method io/dekorate/deps/kubernetes/client/dsl/base/OperationContext.getCascading:()Z
      83: aload_0
      84: getfield      #104                // Field context:Lio/dekorate/deps/kubernetes/client/dsl/base/OperationContext;
      87: invokevirtual #406                // Method io/dekorate/deps/kubernetes/client/dsl/base/OperationContext.getItem:()Ljava/lang/Object;
      90: aload_0
      91: getfield      #104                // Field context:Lio/dekorate/deps/kubernetes/client/dsl/base/OperationContext;
      94: invokevirtual #410                // Method io/dekorate/deps/kubernetes/client/dsl/base/OperationContext.getLabels:()Ljava/util/Map;
      97: aload_0
      98: getfield      #104                // Field context:Lio/dekorate/deps/kubernetes/client/dsl/base/OperationContext;
     101: invokevirtual #413                // Method io/dekorate/deps/kubernetes/client/dsl/base/OperationContext.getLabelsNot:()Ljava/util/Map;
     104: aload_0
     105: getfield      #104                // Field context:Lio/dekorate/deps/kubernetes/client/dsl/base/OperationContext;
     108: invokevirtual #416                // Method io/dekorate/deps/kubernetes/client/dsl/base/OperationContext.getLabelsIn:()Ljava/util/Map;
     111: aload_0
     112: getfield      #104                // Field context:Lio/dekorate/deps/kubernetes/client/dsl/base/OperationContext;
     115: invokevirtual #419                // Method io/dekorate/deps/kubernetes/client/dsl/base/OperationContext.getLabelsNotIn:()Ljava/util/Map;
     118: aload_0
     119: getfield      #104                // Field context:Lio/dekorate/deps/kubernetes/client/dsl/base/OperationContext;
     122: invokevirtual #422                // Method io/dekorate/deps/kubernetes/client/dsl/base/OperationContext.getFields:()Ljava/util/Map;
     125: aload_0
     126: getfield      #104                // Field context:Lio/dekorate/deps/kubernetes/client/dsl/base/OperationContext;
     129: invokevirtual #425                // Method io/dekorate/deps/kubernetes/client/dsl/base/OperationContext.getFieldsNot:()Ljava/util/Map;
     132: aload_0
     133: getfield      #104                // Field context:Lio/dekorate/deps/kubernetes/client/dsl/base/OperationContext;
     136: invokevirtual #428                // Method io/dekorate/deps/kubernetes/client/dsl/base/OperationContext.getResourceVersion:()Ljava/lang/String;
     139: aload_0
     140: getfield      #104                // Field context:Lio/dekorate/deps/kubernetes/client/dsl/base/OperationContext;
     143: invokevirtual #431                // Method io/dekorate/deps/kubernetes/client/dsl/base/OperationContext.getReloadingFromServer:()Z
     146: aload_0
     147: getfield      #104                // Field context:Lio/dekorate/deps/kubernetes/client/dsl/base/OperationContext;
     150: invokevirtual #434                // Method io/dekorate/deps/kubernetes/client/dsl/base/OperationContext.getGracePeriodSeconds:()J
     153: aload_0
     154: getfield      #104                // Field context:Lio/dekorate/deps/kubernetes/client/dsl/base/OperationContext;
     157: invokevirtual #437                // Method io/dekorate/deps/kubernetes/client/dsl/base/OperationContext.getPropagationPolicy:()Ljava/lang/String;
     160: aconst_null
     161: aconst_null
     162: aconst_null
     163: aconst_null
     164: aconst_null
     165: aconst_null
     166: aconst_null
     167: aconst_null
     168: aconst_null
     169: iconst_0
     170: invokestatic  #325                // Method java/lang/Boolean.valueOf:(Z)Ljava/lang/Boolean;
     173: iconst_0
     174: invokestatic  #325                // Method java/lang/Boolean.valueOf:(Z)Ljava/lang/Boolean;
     177: iconst_0
     178: invokestatic  #325                // Method java/lang/Boolean.valueOf:(Z)Ljava/lang/Boolean;
     181: aconst_null
     182: aconst_null
     183: aconst_null
     184: iload_1
     185: invokestatic  #325                // Method java/lang/Boolean.valueOf:(Z)Ljava/lang/Boolean;
     188: aconst_null
     189: aconst_null
     190: aconst_null
     191: aconst_null
     192: aconst_null
     193: invokespecial #440                // Method io/dekorate/deps/kubernetes/client/dsl/internal/PodOperationContext."<init>":(Lio/dekorate/deps/okhttp3/OkHttpClient;Lio/dekorate/deps/kubernetes/client/Config;Ljava/lang/String;Ljava/lang/String;Ljava/lang/String;Ljava/lang/String;Ljava/lang/String;ZLjava/lang/Object;Ljava/util/Map;Ljava/util/Map;Ljava/util/Map;Ljava/util/Map;Ljava/util/Map;Ljava/util/Map;Ljava/lang/String;ZJLjava/lang/String;Ljava/lang/String;Ljava/io/InputStream;Ljava/io/OutputStream;Ljava/io/OutputStream;Ljava/io/OutputStream;Ljava/io/PipedOutputStream;Ljava/io/PipedInputStream;Ljava/io/PipedInputStream;Ljava/io/PipedInputStream;Ljava/lang/Boolean;Ljava/lang/Boolean;Ljava/lang/Boolean;Ljava/lang/String;Ljava/lang/Integer;Ljava/lang/Integer;Ljava/lang/Boolean;Ljava/lang/Integer;Ljava/lang/Integer;Lio/dekorate/deps/kubernetes/client/dsl/ExecListener;Ljava/lang/String;Ljava/lang/String;)V
     196: invokespecial #443                // Method io/dekorate/deps/kubernetes/client/dsl/internal/PodOperationsImpl."<init>":(Lio/dekorate/deps/kubernetes/client/dsl/internal/PodOperationContext;)V
     199: astore        5
     201: aload         5
     203: ldc_w         #445                // String controller-uid
     206: aload         4
     208: invokevirtual #449                // Method io/dekorate/deps/kubernetes/client/dsl/internal/PodOperationsImpl.withLabel:(Ljava/lang/String;Ljava/lang/String;)Lio/dekorate/deps/kubernetes/client/dsl/FilterWatchListDeletable;
     211: invokeinterface #454,  1          // InterfaceMethod io/dekorate/deps/kubernetes/client/dsl/FilterWatchListDeletable.list:()Ljava/lang/Object;
     216: checkcast     #456                // class io/dekorate/deps/kubernetes/api/model/PodList
     219: astore        6
     221: aload         6
     223: invokevirtual #460                // Method io/dekorate/deps/kubernetes/api/model/PodList.getItems:()Ljava/util/List;
     226: invokeinterface #341,  1          // InterfaceMethod java/util/List.iterator:()Ljava/util/Iterator;
     231: astore        7
     233: aload         7
     235: invokeinterface #347,  1          // InterfaceMethod java/util/Iterator.hasNext:()Z
     240: ifeq          303
     243: aload         7
     245: invokeinterface #350,  1          // InterfaceMethod java/util/Iterator.next:()Ljava/lang/Object;
     250: checkcast     #462                // class io/dekorate/deps/kubernetes/api/model/Pod
     253: astore        8
     255: aload         8
     257: invokestatic  #468                // Method io/dekorate/deps/kubernetes/client/utils/KubernetesResourceUtil.getControllerUid:(Lio/dekorate/deps/kubernetes/api/model/HasMetadata;)Lio/dekorate/deps/kubernetes/api/model/OwnerReference;
     260: astore        9
     262: aload         9
     264: ifnull        300
     267: aload         9
     269: invokevirtual #471                // Method io/dekorate/deps/kubernetes/api/model/OwnerReference.getUid:()Ljava/lang/String;
     272: aload         4
     274: invokevirtual #475                // Method java/lang/String.equals:(Ljava/lang/Object;)Z
     277: ifeq          300
     280: aload_2
     281: aload         5
     283: aload         8
     285: invokevirtual #476                // Method io/dekorate/deps/kubernetes/api/model/Pod.getMetadata:()Lio/dekorate/deps/kubernetes/api/model/ObjectMeta;
     288: invokevirtual #298                // Method io/dekorate/deps/kubernetes/api/model/ObjectMeta.getName:()Ljava/lang/String;
     291: invokevirtual #480                // Method io/dekorate/deps/kubernetes/client/dsl/internal/PodOperationsImpl.withName:(Ljava/lang/String;)Lio/dekorate/deps/kubernetes/client/dsl/Resource;
     294: invokeinterface #483,  2          // InterfaceMethod java/util/List.add:(Ljava/lang/Object;)Z
     299: pop
     300: goto          233
     303: aload_2
     304: areturn

  public java.io.Reader getLogReader();
    Code:
       0: aload_0
       1: iconst_0
       2: invokespecial #335                // Method doGetLog:(Z)Ljava/util/List;
       5: astore_1
       6: aload_1
       7: invokeinterface #500,  1          // InterfaceMethod java/util/List.size:()I
      12: iconst_1
      13: if_icmple     27
      16: new           #110                // class io/dekorate/deps/kubernetes/client/KubernetesClientException
      19: dup
      20: ldc_w         #502                // String Reading logs is not supported for multicontainer jobs
      23: invokespecial #505                // Method io/dekorate/deps/kubernetes/client/KubernetesClientException."<init>":(Ljava/lang/String;)V
      26: athrow
      27: aload_1
      28: invokeinterface #500,  1          // InterfaceMethod java/util/List.size:()I
      33: iconst_1
      34: if_icmpne     53
      37: aload_1
      38: iconst_0
      39: invokeinterface #508,  2          // InterfaceMethod java/util/List.get:(I)Ljava/lang/Object;
      44: checkcast     #352                // class io/dekorate/deps/kubernetes/client/dsl/PodResource
      47: invokeinterface #510,  1          // InterfaceMethod io/dekorate/deps/kubernetes/client/dsl/PodResource.getLogReader:()Ljava/io/Reader;
      52: areturn
      53: aconst_null
      54: areturn

  public io.dekorate.deps.kubernetes.client.dsl.LogWatch watchLog();
    Code:
       0: aload_0
       1: aconst_null
       2: invokevirtual #516                // Method watchLog:(Ljava/io/OutputStream;)Lio/dekorate/deps/kubernetes/client/dsl/LogWatch;
       5: areturn

  public io.dekorate.deps.kubernetes.client.dsl.LogWatch watchLog(java.io.OutputStream);
    Code:
       0: aload_0
       1: iconst_0
       2: invokespecial #335                // Method doGetLog:(Z)Ljava/util/List;
       5: astore_2
       6: aload_2
       7: invokeinterface #500,  1          // InterfaceMethod java/util/List.size:()I
      12: iconst_1
      13: if_icmple     27
      16: new           #110                // class io/dekorate/deps/kubernetes/client/KubernetesClientException
      19: dup
      20: ldc_w         #518                // String Watching logs is not supported for multicontainer jobs
      23: invokespecial #505                // Method io/dekorate/deps/kubernetes/client/KubernetesClientException."<init>":(Ljava/lang/String;)V
      26: athrow
      27: aload_2
      28: invokeinterface #500,  1          // InterfaceMethod java/util/List.size:()I
      33: iconst_1
      34: if_icmpne     57
      37: aload_2
      38: iconst_0
      39: invokeinterface #508,  2          // InterfaceMethod java/util/List.get:(I)Ljava/lang/Object;
      44: checkcast     #352                // class io/dekorate/deps/kubernetes/client/dsl/PodResource
      47: aload_1
      48: invokeinterface #521,  2          // InterfaceMethod io/dekorate/deps/kubernetes/client/dsl/PodResource.watchLog:(Ljava/io/OutputStream;)Ljava/lang/Object;
      53: checkcast     #523                // class io/dekorate/deps/kubernetes/client/dsl/LogWatch
      56: areturn
      57: aconst_null
      58: areturn

  public io.dekorate.deps.kubernetes.api.model.batch.Job replace(io.dekorate.deps.kubernetes.api.model.batch.Job);
    Code:
       0: aload_1
       1: ifnonnull     12
       4: aload_0
       5: invokevirtual #528                // Method getItem:()Ljava/lang/Object;
       8: checkcast     #75                 // class io/dekorate/deps/kubernetes/api/model/batch/Job
      11: astore_1
      12: aload_0
      13: invokevirtual #380                // Method fromServer:()Lio/dekorate/deps/kubernetes/client/dsl/ScalableResource;
      16: invokeinterface #381,  1          // InterfaceMethod io/dekorate/deps/kubernetes/client/dsl/ScalableResource.get:()Ljava/lang/Object;
      21: checkcast     #75                 // class io/dekorate/deps/kubernetes/api/model/batch/Job
      24: astore_2
      25: aload_1
      26: invokevirtual #283                // Method io/dekorate/deps/kubernetes/api/model/batch/Job.getSpec:()Lio/dekorate/deps/kubernetes/api/model/batch/JobSpec;
      29: invokevirtual #532                // Method io/dekorate/deps/kubernetes/api/model/batch/JobSpec.getSelector:()Lio/dekorate/deps/kubernetes/api/model/LabelSelector;
      32: ifnonnull     49
      35: aload_1
      36: invokevirtual #283                // Method io/dekorate/deps/kubernetes/api/model/batch/Job.getSpec:()Lio/dekorate/deps/kubernetes/api/model/batch/JobSpec;
      39: aload_2
      40: invokevirtual #283                // Method io/dekorate/deps/kubernetes/api/model/batch/Job.getSpec:()Lio/dekorate/deps/kubernetes/api/model/batch/JobSpec;
      43: invokevirtual #532                // Method io/dekorate/deps/kubernetes/api/model/batch/JobSpec.getSelector:()Lio/dekorate/deps/kubernetes/api/model/LabelSelector;
      46: invokevirtual #536                // Method io/dekorate/deps/kubernetes/api/model/batch/JobSpec.setSelector:(Lio/dekorate/deps/kubernetes/api/model/LabelSelector;)V
      49: aload_1
      50: invokevirtual #283                // Method io/dekorate/deps/kubernetes/api/model/batch/Job.getSpec:()Lio/dekorate/deps/kubernetes/api/model/batch/JobSpec;
      53: invokevirtual #540                // Method io/dekorate/deps/kubernetes/api/model/batch/JobSpec.getTemplate:()Lio/dekorate/deps/kubernetes/api/model/PodTemplateSpec;
      56: invokevirtual #543                // Method io/dekorate/deps/kubernetes/api/model/PodTemplateSpec.getMetadata:()Lio/dekorate/deps/kubernetes/api/model/ObjectMeta;
      59: ifnull        91
      62: aload_1
      63: invokevirtual #283                // Method io/dekorate/deps/kubernetes/api/model/batch/Job.getSpec:()Lio/dekorate/deps/kubernetes/api/model/batch/JobSpec;
      66: invokevirtual #540                // Method io/dekorate/deps/kubernetes/api/model/batch/JobSpec.getTemplate:()Lio/dekorate/deps/kubernetes/api/model/PodTemplateSpec;
      69: invokevirtual #543                // Method io/dekorate/deps/kubernetes/api/model/PodTemplateSpec.getMetadata:()Lio/dekorate/deps/kubernetes/api/model/ObjectMeta;
      72: aload_2
      73: invokevirtual #283                // Method io/dekorate/deps/kubernetes/api/model/batch/Job.getSpec:()Lio/dekorate/deps/kubernetes/api/model/batch/JobSpec;
      76: invokevirtual #540                // Method io/dekorate/deps/kubernetes/api/model/batch/JobSpec.getTemplate:()Lio/dekorate/deps/kubernetes/api/model/PodTemplateSpec;
      79: invokevirtual #543                // Method io/dekorate/deps/kubernetes/api/model/PodTemplateSpec.getMetadata:()Lio/dekorate/deps/kubernetes/api/model/ObjectMeta;
      82: invokevirtual #544                // Method io/dekorate/deps/kubernetes/api/model/ObjectMeta.getLabels:()Ljava/util/Map;
      85: invokevirtual #548                // Method io/dekorate/deps/kubernetes/api/model/ObjectMeta.setLabels:(Ljava/util/Map;)V
      88: goto          111
      91: aload_1
      92: invokevirtual #283                // Method io/dekorate/deps/kubernetes/api/model/batch/Job.getSpec:()Lio/dekorate/deps/kubernetes/api/model/batch/JobSpec;
      95: invokevirtual #540                // Method io/dekorate/deps/kubernetes/api/model/batch/JobSpec.getTemplate:()Lio/dekorate/deps/kubernetes/api/model/PodTemplateSpec;
      98: aload_2
      99: invokevirtual #283                // Method io/dekorate/deps/kubernetes/api/model/batch/Job.getSpec:()Lio/dekorate/deps/kubernetes/api/model/batch/JobSpec;
     102: invokevirtual #540                // Method io/dekorate/deps/kubernetes/api/model/batch/JobSpec.getTemplate:()Lio/dekorate/deps/kubernetes/api/model/PodTemplateSpec;
     105: invokevirtual #543                // Method io/dekorate/deps/kubernetes/api/model/PodTemplateSpec.getMetadata:()Lio/dekorate/deps/kubernetes/api/model/ObjectMeta;
     108: invokevirtual #552                // Method io/dekorate/deps/kubernetes/api/model/PodTemplateSpec.setMetadata:(Lio/dekorate/deps/kubernetes/api/model/ObjectMeta;)V
     111: aload_0
     112: aload_1
     113: invokespecial #555                // Method io/dekorate/deps/kubernetes/client/dsl/base/HasMetadataOperation.replace:(Lio/dekorate/deps/kubernetes/api/model/HasMetadata;)Lio/dekorate/deps/kubernetes/api/model/HasMetadata;
     116: checkcast     #75                 // class io/dekorate/deps/kubernetes/api/model/batch/Job
     119: areturn

  public io.dekorate.deps.kubernetes.api.model.HasMetadata replace(io.dekorate.deps.kubernetes.api.model.HasMetadata);
    Code:
       0: aload_0
       1: aload_1
       2: checkcast     #75                 // class io/dekorate/deps/kubernetes/api/model/batch/Job
       5: invokevirtual #558                // Method replace:(Lio/dekorate/deps/kubernetes/api/model/batch/Job;)Lio/dekorate/deps/kubernetes/api/model/batch/Job;
       8: areturn

  public java.lang.Object replace(java.lang.Object);
    Code:
       0: aload_0
       1: aload_1
       2: checkcast     #75                 // class io/dekorate/deps/kubernetes/api/model/batch/Job
       5: invokevirtual #558                // Method replace:(Lio/dekorate/deps/kubernetes/api/model/batch/Job;)Lio/dekorate/deps/kubernetes/api/model/batch/Job;
       8: areturn

  public io.dekorate.deps.kubernetes.client.dsl.Gettable fromServer();
    Code:
       0: aload_0
       1: invokevirtual #380                // Method fromServer:()Lio/dekorate/deps/kubernetes/client/dsl/ScalableResource;
       4: areturn

  public io.dekorate.deps.kubernetes.client.dsl.Resource load(java.io.InputStream);
    Code:
       0: aload_0
       1: aload_1
       2: invokevirtual #563                // Method load:(Ljava/io/InputStream;)Lio/dekorate/deps/kubernetes/client/dsl/ScalableResource;
       5: areturn

  public io.dekorate.deps.kubernetes.client.dsl.base.BaseOperation newInstance(io.dekorate.deps.kubernetes.client.dsl.base.OperationContext);
    Code:
       0: aload_0
       1: aload_1
       2: invokevirtual #566                // Method newInstance:(Lio/dekorate/deps/kubernetes/client/dsl/base/OperationContext;)Lio/dekorate/deps/kubernetes/client/dsl/internal/JobOperationsImpl;
       5: areturn

  public java.lang.Object load(java.io.InputStream);
    Code:
       0: aload_0
       1: aload_1
       2: invokevirtual #563                // Method load:(Ljava/io/InputStream;)Lio/dekorate/deps/kubernetes/client/dsl/ScalableResource;
       5: areturn

  public java.lang.Object fromServer();
    Code:
       0: aload_0
       1: invokevirtual #380                // Method fromServer:()Lio/dekorate/deps/kubernetes/client/dsl/ScalableResource;
       4: areturn

  public java.lang.Object scale(int, boolean);
    Code:
       0: aload_0
       1: iload_1
       2: iload_2
       3: invokevirtual #131                // Method scale:(IZ)Lio/dekorate/deps/kubernetes/api/model/batch/Job;
       6: areturn

  public java.lang.Object scale(int);
    Code:
       0: aload_0
       1: iload_1
       2: invokevirtual #570                // Method scale:(I)Lio/dekorate/deps/kubernetes/api/model/batch/Job;
       5: areturn

  public java.lang.Object watchLog(java.io.OutputStream);
    Code:
       0: aload_0
       1: aload_1
       2: invokevirtual #516                // Method watchLog:(Ljava/io/OutputStream;)Lio/dekorate/deps/kubernetes/client/dsl/LogWatch;
       5: areturn

  public java.lang.Object watchLog();
    Code:
       0: aload_0
       1: invokevirtual #572                // Method watchLog:()Lio/dekorate/deps/kubernetes/client/dsl/LogWatch;
       4: areturn

  public java.lang.Object getLog(java.lang.Boolean);
    Code:
       0: aload_0
       1: aload_1
       2: invokevirtual #328                // Method getLog:(Ljava/lang/Boolean;)Ljava/lang/String;
       5: areturn

  public java.lang.Object getLog();
    Code:
       0: aload_0
       1: invokevirtual #574                // Method getLog:()Ljava/lang/String;
       4: areturn

  private void lambda$waitUntilJobIsScaled$0(java.util.concurrent.atomic.AtomicReference, java.util.concurrent.CountDownLatch);
    Code:
       0: aload_0
       1: invokevirtual #176                // Method getMandatory:()Ljava/lang/Object;
       4: checkcast     #75                 // class io/dekorate/deps/kubernetes/api/model/batch/Job
       7: astore_3
       8: aload_1
       9: aload_3
      10: invokevirtual #578                // Method java/util/concurrent/atomic/AtomicReference.set:(Ljava/lang/Object;)V
      13: aload_3
      14: invokevirtual #273                // Method io/dekorate/deps/kubernetes/api/model/batch/Job.getStatus:()Lio/dekorate/deps/kubernetes/api/model/batch/JobStatus;
      17: invokevirtual #279                // Method io/dekorate/deps/kubernetes/api/model/batch/JobStatus.getActive:()Ljava/lang/Integer;
      20: astore        4
      22: aload         4
      24: ifnonnull     33
      27: iconst_0
      28: invokestatic  #159                // Method java/lang/Integer.valueOf:(I)Ljava/lang/Integer;
      31: astore        4
      33: aload_3
      34: invokevirtual #283                // Method io/dekorate/deps/kubernetes/api/model/batch/Job.getSpec:()Lio/dekorate/deps/kubernetes/api/model/batch/JobSpec;
      37: invokevirtual #288                // Method io/dekorate/deps/kubernetes/api/model/batch/JobSpec.getParallelism:()Ljava/lang/Integer;
      40: aload         4
      42: invokestatic  #583                // Method java/util/Objects.equals:(Ljava/lang/Object;Ljava/lang/Object;)Z
      45: ifeq          55
      48: aload_2
      49: invokevirtual #586                // Method java/util/concurrent/CountDownLatch.countDown:()V
      52: goto          107
      55: getstatic     #262                // Field LOG:Lorg/slf4j/Logger;
      58: ldc_w         #588                // String Only {}/{} pods scheduled for Job: {} in namespace: {} seconds so waiting...
      61: iconst_4
      62: anewarray     #266                // class java/lang/Object
      65: dup
      66: iconst_0
      67: aload_3
      68: invokevirtual #273                // Method io/dekorate/deps/kubernetes/api/model/batch/Job.getStatus:()Lio/dekorate/deps/kubernetes/api/model/batch/JobStatus;
      71: invokevirtual #279                // Method io/dekorate/deps/kubernetes/api/model/batch/JobStatus.getActive:()Ljava/lang/Integer;
      74: aastore
      75: dup
      76: iconst_1
      77: aload_3
      78: invokevirtual #283                // Method io/dekorate/deps/kubernetes/api/model/batch/Job.getSpec:()Lio/dekorate/deps/kubernetes/api/model/batch/JobSpec;
      81: invokevirtual #288                // Method io/dekorate/deps/kubernetes/api/model/batch/JobSpec.getParallelism:()Ljava/lang/Integer;
      84: aastore
      85: dup
      86: iconst_2
      87: aload_3
      88: invokevirtual #292                // Method io/dekorate/deps/kubernetes/api/model/batch/Job.getMetadata:()Lio/dekorate/deps/kubernetes/api/model/ObjectMeta;
      91: invokevirtual #298                // Method io/dekorate/deps/kubernetes/api/model/ObjectMeta.getName:()Ljava/lang/String;
      94: aastore
      95: dup
      96: iconst_3
      97: aload_0
      98: getfield      #300                // Field namespace:Ljava/lang/String;
     101: aastore
     102: invokeinterface #591,  3          // InterfaceMethod org/slf4j/Logger.debug:(Ljava/lang/String;[Ljava/lang/Object;)V
     107: goto          123
     110: astore_3
     111: getstatic     #262                // Field LOG:Lorg/slf4j/Logger;
     114: ldc_w         #593                // String Error while waiting for Job to be scaled.
     117: aload_3
     118: invokeinterface #596,  3          // InterfaceMethod org/slf4j/Logger.error:(Ljava/lang/String;Ljava/lang/Throwable;)V
     123: return
    Exception table:
       from    to  target type
           0   107   110   Class java/lang/Throwable

  static {};
    Code:
       0: ldc           #2                  // class io/dekorate/deps/kubernetes/client/dsl/internal/JobOperationsImpl
       2: invokestatic  #605                // Method org/slf4j/LoggerFactory.getLogger:(Ljava/lang/Class;)Lorg/slf4j/Logger;
       5: putstatic     #262                // Field LOG:Lorg/slf4j/Logger;
       8: return
}
