Compiled from "SubjectAccessReviewDSLImpl.java"
class io.dekorate.deps.kubernetes.client.dsl.internal.SubjectAccessReviewDSLImpl$CreatableLocalSubjectAccessReview implements io.dekorate.deps.kubernetes.client.dsl.Createable<io.dekorate.deps.kubernetes.api.model.authorization.LocalSubjectAccessReview, io.dekorate.deps.kubernetes.api.model.authorization.LocalSubjectAccessReview, io.dekorate.deps.kubernetes.api.model.authorization.DoneableLocalSubjectAccessReview> {
  private final java.lang.String namespace;

  final io.dekorate.deps.kubernetes.client.dsl.internal.SubjectAccessReviewDSLImpl this$0;

  io.dekorate.deps.kubernetes.client.dsl.internal.SubjectAccessReviewDSLImpl$CreatableLocalSubjectAccessReview(io.dekorate.deps.kubernetes.client.dsl.internal.SubjectAccessReviewDSLImpl, java.lang.String);
    Code:
       0: aload_0
       1: aload_1
       2: putfield      #24                 // Field this$0:Lio/dekorate/deps/kubernetes/client/dsl/internal/SubjectAccessReviewDSLImpl;
       5: aload_0
       6: invokespecial #27                 // Method java/lang/Object."<init>":()V
       9: aload_0
      10: aload_2
      11: putfield      #29                 // Field namespace:Ljava/lang/String;
      14: return

  public io.dekorate.deps.kubernetes.api.model.authorization.LocalSubjectAccessReview create(io.dekorate.deps.kubernetes.api.model.authorization.LocalSubjectAccessReview...);
    Code:
       0: aload_1
       1: arraylength
       2: iconst_1
       3: if_icmple     16
       6: new           #41                 // class java/lang/IllegalArgumentException
       9: dup
      10: ldc           #43                 // String Too many items to create.
      12: invokespecial #46                 // Method java/lang/IllegalArgumentException."<init>":(Ljava/lang/String;)V
      15: athrow
      16: aload_1
      17: arraylength
      18: iconst_1
      19: if_icmpne     45
      22: aload_0
      23: aload_1
      24: iconst_0
      25: aaload
      26: invokespecial #50                 // Method setNamespace:(Lio/dekorate/deps/kubernetes/api/model/authorization/LocalSubjectAccessReview;)V
      29: aload_0
      30: getfield      #24                 // Field this$0:Lio/dekorate/deps/kubernetes/client/dsl/internal/SubjectAccessReviewDSLImpl;
      33: aload_1
      34: iconst_0
      35: aaload
      36: ldc           #52                 // class io/dekorate/deps/kubernetes/api/model/authorization/LocalSubjectAccessReview
      38: invokestatic  #56                 // Method io/dekorate/deps/kubernetes/client/dsl/internal/SubjectAccessReviewDSLImpl.access$300:(Lio/dekorate/deps/kubernetes/client/dsl/internal/SubjectAccessReviewDSLImpl;Ljava/lang/Object;Ljava/lang/Class;)Ljava/lang/Object;
      41: checkcast     #52                 // class io/dekorate/deps/kubernetes/api/model/authorization/LocalSubjectAccessReview
      44: areturn
      45: new           #41                 // class java/lang/IllegalArgumentException
      48: dup
      49: ldc           #58                 // String Nothing to create.
      51: invokespecial #46                 // Method java/lang/IllegalArgumentException."<init>":(Ljava/lang/String;)V
      54: athrow
      55: astore_2
      56: aload_2
      57: invokestatic  #66                 // Method io/dekorate/deps/kubernetes/client/KubernetesClientException.launderThrowable:(Ljava/lang/Throwable;)Ljava/lang/RuntimeException;
      60: athrow
    Exception table:
       from    to  target type
           0    44    55   Class java/lang/InterruptedException
           0    44    55   Class java/util/concurrent/ExecutionException
           0    44    55   Class java/io/IOException
          45    55    55   Class java/lang/InterruptedException
          45    55    55   Class java/util/concurrent/ExecutionException
          45    55    55   Class java/io/IOException

  public io.dekorate.deps.kubernetes.api.model.authorization.LocalSubjectAccessReview create(io.dekorate.deps.kubernetes.api.model.authorization.LocalSubjectAccessReview);
    Code:
       0: aload_0
       1: iconst_1
       2: anewarray     #52                 // class io/dekorate/deps/kubernetes/api/model/authorization/LocalSubjectAccessReview
       5: dup
       6: iconst_0
       7: aload_1
       8: aastore
       9: invokevirtual #73                 // Method create:([Lio/dekorate/deps/kubernetes/api/model/authorization/LocalSubjectAccessReview;)Lio/dekorate/deps/kubernetes/api/model/authorization/LocalSubjectAccessReview;
      12: areturn

  private void setNamespace(io.dekorate.deps.kubernetes.api.model.authorization.LocalSubjectAccessReview);
    Code:
       0: aload_1
       1: invokevirtual #79                 // Method io/dekorate/deps/kubernetes/api/model/authorization/LocalSubjectAccessReview.getMetadata:()Lio/dekorate/deps/kubernetes/api/model/ObjectMeta;
       4: astore_2
       5: aload_2
       6: ifnonnull     22
       9: new           #81                 // class io/dekorate/deps/kubernetes/api/model/ObjectMeta
      12: dup
      13: invokespecial #82                 // Method io/dekorate/deps/kubernetes/api/model/ObjectMeta."<init>":()V
      16: astore_2
      17: aload_1
      18: aload_2
      19: invokevirtual #86                 // Method io/dekorate/deps/kubernetes/api/model/authorization/LocalSubjectAccessReview.setMetadata:(Lio/dekorate/deps/kubernetes/api/model/ObjectMeta;)V
      22: aload_2
      23: invokevirtual #90                 // Method io/dekorate/deps/kubernetes/api/model/ObjectMeta.getNamespace:()Ljava/lang/String;
      26: invokestatic  #96                 // Method io/dekorate/deps/kubernetes/client/utils/Utils.isNullOrEmpty:(Ljava/lang/String;)Z
      29: ifeq          40
      32: aload_2
      33: aload_0
      34: getfield      #29                 // Field namespace:Ljava/lang/String;
      37: invokevirtual #98                 // Method io/dekorate/deps/kubernetes/api/model/ObjectMeta.setNamespace:(Ljava/lang/String;)V
      40: aload_1
      41: invokevirtual #102                // Method io/dekorate/deps/kubernetes/api/model/authorization/LocalSubjectAccessReview.getSpec:()Lio/dekorate/deps/kubernetes/api/model/authorization/SubjectAccessReviewSpec;
      44: astore_3
      45: aload_3
      46: ifnull        80
      49: aload_3
      50: invokevirtual #108                // Method io/dekorate/deps/kubernetes/api/model/authorization/SubjectAccessReviewSpec.getResourceAttributes:()Lio/dekorate/deps/kubernetes/api/model/authorization/ResourceAttributes;
      53: ifnull        80
      56: aload_3
      57: invokevirtual #108                // Method io/dekorate/deps/kubernetes/api/model/authorization/SubjectAccessReviewSpec.getResourceAttributes:()Lio/dekorate/deps/kubernetes/api/model/authorization/ResourceAttributes;
      60: invokevirtual #111                // Method io/dekorate/deps/kubernetes/api/model/authorization/ResourceAttributes.getNamespace:()Ljava/lang/String;
      63: invokestatic  #96                 // Method io/dekorate/deps/kubernetes/client/utils/Utils.isNullOrEmpty:(Ljava/lang/String;)Z
      66: ifeq          80
      69: aload_3
      70: invokevirtual #108                // Method io/dekorate/deps/kubernetes/api/model/authorization/SubjectAccessReviewSpec.getResourceAttributes:()Lio/dekorate/deps/kubernetes/api/model/authorization/ResourceAttributes;
      73: aload_0
      74: getfield      #29                 // Field namespace:Ljava/lang/String;
      77: invokevirtual #112                // Method io/dekorate/deps/kubernetes/api/model/authorization/ResourceAttributes.setNamespace:(Ljava/lang/String;)V
      80: return

  public io.dekorate.deps.kubernetes.api.model.authorization.DoneableLocalSubjectAccessReview createNew();
    Code:
       0: new           #120                // class io/dekorate/deps/kubernetes/api/model/authorization/DoneableLocalSubjectAccessReview
       3: dup
       4: aload_0
       5: invokedynamic #137,  0            // InvokeDynamic #0:apply:(Lio/dekorate/deps/kubernetes/client/dsl/internal/SubjectAccessReviewDSLImpl$CreatableLocalSubjectAccessReview;)Lio/dekorate/deps/kubernetes/api/builder/Function;
      10: invokespecial #140                // Method io/dekorate/deps/kubernetes/api/model/authorization/DoneableLocalSubjectAccessReview."<init>":(Lio/dekorate/deps/kubernetes/api/builder/Function;)V
      13: areturn

  public java.lang.Object createNew();
    Code:
       0: aload_0
       1: invokevirtual #143                // Method createNew:()Lio/dekorate/deps/kubernetes/api/model/authorization/DoneableLocalSubjectAccessReview;
       4: areturn

  public java.lang.Object create(java.lang.Object);
    Code:
       0: aload_0
       1: aload_1
       2: checkcast     #52                 // class io/dekorate/deps/kubernetes/api/model/authorization/LocalSubjectAccessReview
       5: invokevirtual #124                // Method create:(Lio/dekorate/deps/kubernetes/api/model/authorization/LocalSubjectAccessReview;)Lio/dekorate/deps/kubernetes/api/model/authorization/LocalSubjectAccessReview;
       8: areturn

  public java.lang.Object create(java.lang.Object[]);
    Code:
       0: aload_0
       1: aload_1
       2: checkcast     #145                // class "[Lio/dekorate/deps/kubernetes/api/model/authorization/LocalSubjectAccessReview;"
       5: invokevirtual #73                 // Method create:([Lio/dekorate/deps/kubernetes/api/model/authorization/LocalSubjectAccessReview;)Lio/dekorate/deps/kubernetes/api/model/authorization/LocalSubjectAccessReview;
       8: areturn
}
