Compiled from "ChannelAgentForwarding.java"
class com.jcraft.jsch.ChannelAgentForwarding extends com.jcraft.jsch.Channel {
  private static final int LOCAL_WINDOW_SIZE_MAX;

  private static final int LOCAL_MAXIMUM_PACKET_SIZE;

  private final byte SSH_AGENTC_REQUEST_RSA_IDENTITIES;

  private final byte SSH_AGENT_RSA_IDENTITIES_ANSWER;

  private final byte SSH_AGENTC_RSA_CHALLENGE;

  private final byte SSH_AGENT_RSA_RESPONSE;

  private final byte SSH_AGENT_FAILURE;

  private final byte SSH_AGENT_SUCCESS;

  private final byte SSH_AGENTC_ADD_RSA_IDENTITY;

  private final byte SSH_AGENTC_REMOVE_RSA_IDENTITY;

  private final byte SSH_AGENTC_REMOVE_ALL_RSA_IDENTITIES;

  private final byte SSH2_AGENTC_REQUEST_IDENTITIES;

  private final byte SSH2_AGENT_IDENTITIES_ANSWER;

  private final byte SSH2_AGENTC_SIGN_REQUEST;

  private final byte SSH2_AGENT_SIGN_RESPONSE;

  private final byte SSH2_AGENTC_ADD_IDENTITY;

  private final byte SSH2_AGENTC_REMOVE_IDENTITY;

  private final byte SSH2_AGENTC_REMOVE_ALL_IDENTITIES;

  private final byte SSH2_AGENT_FAILURE;

  boolean init;

  private com.jcraft.jsch.Buffer rbuf;

  private com.jcraft.jsch.Buffer wbuf;

  private com.jcraft.jsch.Packet packet;

  private com.jcraft.jsch.Buffer mbuf;

  com.jcraft.jsch.ChannelAgentForwarding();
    Code:
       0: aload_0
       1: invokespecial #1                  // Method com/jcraft/jsch/Channel."<init>":()V
       4: aload_0
       5: iconst_1
       6: putfield      #2                  // Field SSH_AGENTC_REQUEST_RSA_IDENTITIES:B
       9: aload_0
      10: iconst_2
      11: putfield      #3                  // Field SSH_AGENT_RSA_IDENTITIES_ANSWER:B
      14: aload_0
      15: iconst_3
      16: putfield      #4                  // Field SSH_AGENTC_RSA_CHALLENGE:B
      19: aload_0
      20: iconst_4
      21: putfield      #5                  // Field SSH_AGENT_RSA_RESPONSE:B
      24: aload_0
      25: iconst_5
      26: putfield      #6                  // Field SSH_AGENT_FAILURE:B
      29: aload_0
      30: bipush        6
      32: putfield      #7                  // Field SSH_AGENT_SUCCESS:B
      35: aload_0
      36: bipush        7
      38: putfield      #8                  // Field SSH_AGENTC_ADD_RSA_IDENTITY:B
      41: aload_0
      42: bipush        8
      44: putfield      #9                  // Field SSH_AGENTC_REMOVE_RSA_IDENTITY:B
      47: aload_0
      48: bipush        9
      50: putfield      #10                 // Field SSH_AGENTC_REMOVE_ALL_RSA_IDENTITIES:B
      53: aload_0
      54: bipush        11
      56: putfield      #11                 // Field SSH2_AGENTC_REQUEST_IDENTITIES:B
      59: aload_0
      60: bipush        12
      62: putfield      #12                 // Field SSH2_AGENT_IDENTITIES_ANSWER:B
      65: aload_0
      66: bipush        13
      68: putfield      #13                 // Field SSH2_AGENTC_SIGN_REQUEST:B
      71: aload_0
      72: bipush        14
      74: putfield      #14                 // Field SSH2_AGENT_SIGN_RESPONSE:B
      77: aload_0
      78: bipush        17
      80: putfield      #15                 // Field SSH2_AGENTC_ADD_IDENTITY:B
      83: aload_0
      84: bipush        18
      86: putfield      #16                 // Field SSH2_AGENTC_REMOVE_IDENTITY:B
      89: aload_0
      90: bipush        19
      92: putfield      #17                 // Field SSH2_AGENTC_REMOVE_ALL_IDENTITIES:B
      95: aload_0
      96: bipush        30
      98: putfield      #18                 // Field SSH2_AGENT_FAILURE:B
     101: aload_0
     102: iconst_1
     103: putfield      #19                 // Field init:Z
     106: aload_0
     107: aconst_null
     108: putfield      #20                 // Field rbuf:Lcom/jcraft/jsch/Buffer;
     111: aload_0
     112: aconst_null
     113: putfield      #21                 // Field wbuf:Lcom/jcraft/jsch/Buffer;
     116: aload_0
     117: aconst_null
     118: putfield      #22                 // Field packet:Lcom/jcraft/jsch/Packet;
     121: aload_0
     122: aconst_null
     123: putfield      #23                 // Field mbuf:Lcom/jcraft/jsch/Buffer;
     126: aload_0
     127: ldc           #24                 // int 131072
     129: invokevirtual #25                 // Method setLocalWindowSizeMax:(I)V
     132: aload_0
     133: ldc           #24                 // int 131072
     135: invokevirtual #26                 // Method setLocalWindowSize:(I)V
     138: aload_0
     139: sipush        16384
     142: invokevirtual #27                 // Method setLocalPacketSize:(I)V
     145: aload_0
     146: ldc           #28                 // String auth-agent@openssh.com
     148: invokestatic  #29                 // Method com/jcraft/jsch/Util.str2byte:(Ljava/lang/String;)[B
     151: putfield      #30                 // Field type:[B
     154: aload_0
     155: new           #31                 // class com/jcraft/jsch/Buffer
     158: dup
     159: invokespecial #32                 // Method com/jcraft/jsch/Buffer."<init>":()V
     162: putfield      #20                 // Field rbuf:Lcom/jcraft/jsch/Buffer;
     165: aload_0
     166: getfield      #20                 // Field rbuf:Lcom/jcraft/jsch/Buffer;
     169: invokevirtual #33                 // Method com/jcraft/jsch/Buffer.reset:()V
     172: aload_0
     173: new           #31                 // class com/jcraft/jsch/Buffer
     176: dup
     177: invokespecial #32                 // Method com/jcraft/jsch/Buffer."<init>":()V
     180: putfield      #23                 // Field mbuf:Lcom/jcraft/jsch/Buffer;
     183: aload_0
     184: iconst_1
     185: putfield      #34                 // Field connected:Z
     188: return

  public void run();
    Code:
       0: aload_0
       1: invokevirtual #35                 // Method sendOpenConfirmation:()V
       4: goto          17
       7: astore_1
       8: aload_0
       9: iconst_1
      10: putfield      #37                 // Field close:Z
      13: aload_0
      14: invokevirtual #38                 // Method disconnect:()V
      17: return
    Exception table:
       from    to  target type
           0     4     7   Class java/lang/Exception

  void write(byte[], int, int) throws java.io.IOException;
    Code:
       0: aload_0
       1: getfield      #22                 // Field packet:Lcom/jcraft/jsch/Packet;
       4: ifnonnull     37
       7: aload_0
       8: new           #31                 // class com/jcraft/jsch/Buffer
      11: dup
      12: aload_0
      13: getfield      #39                 // Field rmpsize:I
      16: invokespecial #40                 // Method com/jcraft/jsch/Buffer."<init>":(I)V
      19: putfield      #21                 // Field wbuf:Lcom/jcraft/jsch/Buffer;
      22: aload_0
      23: new           #41                 // class com/jcraft/jsch/Packet
      26: dup
      27: aload_0
      28: getfield      #21                 // Field wbuf:Lcom/jcraft/jsch/Buffer;
      31: invokespecial #42                 // Method com/jcraft/jsch/Packet."<init>":(Lcom/jcraft/jsch/Buffer;)V
      34: putfield      #22                 // Field packet:Lcom/jcraft/jsch/Packet;
      37: aload_0
      38: getfield      #20                 // Field rbuf:Lcom/jcraft/jsch/Buffer;
      41: invokevirtual #43                 // Method com/jcraft/jsch/Buffer.shift:()V
      44: aload_0
      45: getfield      #20                 // Field rbuf:Lcom/jcraft/jsch/Buffer;
      48: getfield      #44                 // Field com/jcraft/jsch/Buffer.buffer:[B
      51: arraylength
      52: aload_0
      53: getfield      #20                 // Field rbuf:Lcom/jcraft/jsch/Buffer;
      56: getfield      #45                 // Field com/jcraft/jsch/Buffer.index:I
      59: iload_3
      60: iadd
      61: if_icmpge     108
      64: aload_0
      65: getfield      #20                 // Field rbuf:Lcom/jcraft/jsch/Buffer;
      68: getfield      #46                 // Field com/jcraft/jsch/Buffer.s:I
      71: iload_3
      72: iadd
      73: newarray       byte
      75: astore        4
      77: aload_0
      78: getfield      #20                 // Field rbuf:Lcom/jcraft/jsch/Buffer;
      81: getfield      #44                 // Field com/jcraft/jsch/Buffer.buffer:[B
      84: iconst_0
      85: aload         4
      87: iconst_0
      88: aload_0
      89: getfield      #20                 // Field rbuf:Lcom/jcraft/jsch/Buffer;
      92: getfield      #44                 // Field com/jcraft/jsch/Buffer.buffer:[B
      95: arraylength
      96: invokestatic  #47                 // Method java/lang/System.arraycopy:(Ljava/lang/Object;ILjava/lang/Object;II)V
      99: aload_0
     100: getfield      #20                 // Field rbuf:Lcom/jcraft/jsch/Buffer;
     103: aload         4
     105: putfield      #44                 // Field com/jcraft/jsch/Buffer.buffer:[B
     108: aload_0
     109: getfield      #20                 // Field rbuf:Lcom/jcraft/jsch/Buffer;
     112: aload_1
     113: iload_2
     114: iload_3
     115: invokevirtual #48                 // Method com/jcraft/jsch/Buffer.putByte:([BII)V
     118: aload_0
     119: getfield      #20                 // Field rbuf:Lcom/jcraft/jsch/Buffer;
     122: invokevirtual #49                 // Method com/jcraft/jsch/Buffer.getInt:()I
     125: istore        4
     127: iload         4
     129: aload_0
     130: getfield      #20                 // Field rbuf:Lcom/jcraft/jsch/Buffer;
     133: invokevirtual #50                 // Method com/jcraft/jsch/Buffer.getLength:()I
     136: if_icmple     153
     139: aload_0
     140: getfield      #20                 // Field rbuf:Lcom/jcraft/jsch/Buffer;
     143: dup
     144: getfield      #46                 // Field com/jcraft/jsch/Buffer.s:I
     147: iconst_4
     148: isub
     149: putfield      #46                 // Field com/jcraft/jsch/Buffer.s:I
     152: return
     153: aload_0
     154: getfield      #20                 // Field rbuf:Lcom/jcraft/jsch/Buffer;
     157: invokevirtual #51                 // Method com/jcraft/jsch/Buffer.getByte:()I
     160: istore        5
     162: aconst_null
     163: astore        6
     165: aload_0
     166: invokevirtual #52                 // Method getSession:()Lcom/jcraft/jsch/Session;
     169: astore        6
     171: goto          189
     174: astore        7
     176: new           #54                 // class java/io/IOException
     179: dup
     180: aload         7
     182: invokevirtual #55                 // Method com/jcraft/jsch/JSchException.toString:()Ljava/lang/String;
     185: invokespecial #56                 // Method java/io/IOException."<init>":(Ljava/lang/String;)V
     188: athrow
     189: aload         6
     191: invokevirtual #57                 // Method com/jcraft/jsch/Session.getIdentityRepository:()Lcom/jcraft/jsch/IdentityRepository;
     194: astore        7
     196: aload         6
     198: invokevirtual #58                 // Method com/jcraft/jsch/Session.getUserInfo:()Lcom/jcraft/jsch/UserInfo;
     201: astore        8
     203: aload_0
     204: getfield      #23                 // Field mbuf:Lcom/jcraft/jsch/Buffer;
     207: invokevirtual #33                 // Method com/jcraft/jsch/Buffer.reset:()V
     210: iload         5
     212: bipush        11
     214: if_icmpne     387
     217: aload_0
     218: getfield      #23                 // Field mbuf:Lcom/jcraft/jsch/Buffer;
     221: bipush        12
     223: invokevirtual #59                 // Method com/jcraft/jsch/Buffer.putByte:(B)V
     226: aload         7
     228: invokeinterface #60,  1           // InterfaceMethod com/jcraft/jsch/IdentityRepository.getIdentities:()Ljava/util/Vector;
     233: astore        9
     235: aload         9
     237: dup
     238: astore        10
     240: monitorenter
     241: iconst_0
     242: istore        11
     244: iconst_0
     245: istore        12
     247: iload         12
     249: aload         9
     251: invokevirtual #61                 // Method java/util/Vector.size:()I
     254: if_icmpge     291
     257: aload         9
     259: iload         12
     261: invokevirtual #62                 // Method java/util/Vector.elementAt:(I)Ljava/lang/Object;
     264: checkcast     #63                 // class com/jcraft/jsch/Identity
     267: checkcast     #63                 // class com/jcraft/jsch/Identity
     270: astore        13
     272: aload         13
     274: invokeinterface #64,  1           // InterfaceMethod com/jcraft/jsch/Identity.getPublicKeyBlob:()[B
     279: ifnull        285
     282: iinc          11, 1
     285: iinc          12, 1
     288: goto          247
     291: aload_0
     292: getfield      #23                 // Field mbuf:Lcom/jcraft/jsch/Buffer;
     295: iload         11
     297: invokevirtual #65                 // Method com/jcraft/jsch/Buffer.putInt:(I)V
     300: iconst_0
     301: istore        12
     303: iload         12
     305: aload         9
     307: invokevirtual #61                 // Method java/util/Vector.size:()I
     310: if_icmpge     370
     313: aload         9
     315: iload         12
     317: invokevirtual #62                 // Method java/util/Vector.elementAt:(I)Ljava/lang/Object;
     320: checkcast     #63                 // class com/jcraft/jsch/Identity
     323: checkcast     #63                 // class com/jcraft/jsch/Identity
     326: astore        13
     328: aload         13
     330: invokeinterface #64,  1           // InterfaceMethod com/jcraft/jsch/Identity.getPublicKeyBlob:()[B
     335: astore        14
     337: aload         14
     339: ifnonnull     345
     342: goto          364
     345: aload_0
     346: getfield      #23                 // Field mbuf:Lcom/jcraft/jsch/Buffer;
     349: aload         14
     351: invokevirtual #66                 // Method com/jcraft/jsch/Buffer.putString:([B)V
     354: aload_0
     355: getfield      #23                 // Field mbuf:Lcom/jcraft/jsch/Buffer;
     358: getstatic     #67                 // Field com/jcraft/jsch/Util.empty:[B
     361: invokevirtual #66                 // Method com/jcraft/jsch/Buffer.putString:([B)V
     364: iinc          12, 1
     367: goto          303
     370: aload         10
     372: monitorexit
     373: goto          384
     376: astore        15
     378: aload         10
     380: monitorexit
     381: aload         15
     383: athrow
     384: goto          903
     387: iload         5
     389: iconst_1
     390: if_icmpne     412
     393: aload_0
     394: getfield      #23                 // Field mbuf:Lcom/jcraft/jsch/Buffer;
     397: iconst_2
     398: invokevirtual #59                 // Method com/jcraft/jsch/Buffer.putByte:(B)V
     401: aload_0
     402: getfield      #23                 // Field mbuf:Lcom/jcraft/jsch/Buffer;
     405: iconst_0
     406: invokevirtual #65                 // Method com/jcraft/jsch/Buffer.putInt:(I)V
     409: goto          903
     412: iload         5
     414: bipush        13
     416: if_icmpne     733
     419: aload_0
     420: getfield      #20                 // Field rbuf:Lcom/jcraft/jsch/Buffer;
     423: invokevirtual #68                 // Method com/jcraft/jsch/Buffer.getString:()[B
     426: astore        9
     428: aload_0
     429: getfield      #20                 // Field rbuf:Lcom/jcraft/jsch/Buffer;
     432: invokevirtual #68                 // Method com/jcraft/jsch/Buffer.getString:()[B
     435: astore        10
     437: aload_0
     438: getfield      #20                 // Field rbuf:Lcom/jcraft/jsch/Buffer;
     441: invokevirtual #49                 // Method com/jcraft/jsch/Buffer.getInt:()I
     444: istore        11
     446: aload         7
     448: invokeinterface #60,  1           // InterfaceMethod com/jcraft/jsch/IdentityRepository.getIdentities:()Ljava/util/Vector;
     453: astore        12
     455: aconst_null
     456: astore        13
     458: aload         12
     460: dup
     461: astore        14
     463: monitorenter
     464: iconst_0
     465: istore        15
     467: iload         15
     469: aload         12
     471: invokevirtual #61                 // Method java/util/Vector.size:()I
     474: if_icmpge     662
     477: aload         12
     479: iload         15
     481: invokevirtual #62                 // Method java/util/Vector.elementAt:(I)Ljava/lang/Object;
     484: checkcast     #63                 // class com/jcraft/jsch/Identity
     487: checkcast     #63                 // class com/jcraft/jsch/Identity
     490: astore        16
     492: aload         16
     494: invokeinterface #64,  1           // InterfaceMethod com/jcraft/jsch/Identity.getPublicKeyBlob:()[B
     499: ifnonnull     505
     502: goto          656
     505: aload         9
     507: aload         16
     509: invokeinterface #64,  1           // InterfaceMethod com/jcraft/jsch/Identity.getPublicKeyBlob:()[B
     514: invokestatic  #69                 // Method com/jcraft/jsch/Util.array_equals:([B[B)Z
     517: ifne          523
     520: goto          656
     523: aload         16
     525: invokeinterface #70,  1           // InterfaceMethod com/jcraft/jsch/Identity.isEncrypted:()Z
     530: ifeq          639
     533: aload         8
     535: ifnonnull     541
     538: goto          656
     541: aload         16
     543: invokeinterface #70,  1           // InterfaceMethod com/jcraft/jsch/Identity.isEncrypted:()Z
     548: ifeq          639
     551: aload         8
     553: new           #71                 // class java/lang/StringBuilder
     556: dup
     557: invokespecial #72                 // Method java/lang/StringBuilder."<init>":()V
     560: ldc           #73                 // String Passphrase for
     562: invokevirtual #74                 // Method java/lang/StringBuilder.append:(Ljava/lang/String;)Ljava/lang/StringBuilder;
     565: aload         16
     567: invokeinterface #75,  1           // InterfaceMethod com/jcraft/jsch/Identity.getName:()Ljava/lang/String;
     572: invokevirtual #74                 // Method java/lang/StringBuilder.append:(Ljava/lang/String;)Ljava/lang/StringBuilder;
     575: invokevirtual #76                 // Method java/lang/StringBuilder.toString:()Ljava/lang/String;
     578: invokeinterface #77,  2           // InterfaceMethod com/jcraft/jsch/UserInfo.promptPassphrase:(Ljava/lang/String;)Z
     583: ifne          589
     586: goto          639
     589: aload         8
     591: invokeinterface #78,  1           // InterfaceMethod com/jcraft/jsch/UserInfo.getPassphrase:()Ljava/lang/String;
     596: astore        17
     598: aload         17
     600: ifnonnull     606
     603: goto          639
     606: aload         17
     608: invokestatic  #29                 // Method com/jcraft/jsch/Util.str2byte:(Ljava/lang/String;)[B
     611: astore        18
     613: aload         16
     615: aload         18
     617: invokeinterface #79,  2           // InterfaceMethod com/jcraft/jsch/Identity.setPassphrase:([B)Z
     622: ifeq          628
     625: goto          639
     628: goto          636
     631: astore        19
     633: goto          639
     636: goto          541
     639: aload         16
     641: invokeinterface #70,  1           // InterfaceMethod com/jcraft/jsch/Identity.isEncrypted:()Z
     646: ifne          656
     649: aload         16
     651: astore        13
     653: goto          662
     656: iinc          15, 1
     659: goto          467
     662: aload         14
     664: monitorexit
     665: goto          676
     668: astore        20
     670: aload         14
     672: monitorexit
     673: aload         20
     675: athrow
     676: aconst_null
     677: astore        14
     679: aload         13
     681: ifnull        695
     684: aload         13
     686: aload         10
     688: invokeinterface #80,  2           // InterfaceMethod com/jcraft/jsch/Identity.getSignature:([B)[B
     693: astore        14
     695: aload         14
     697: ifnonnull     712
     700: aload_0
     701: getfield      #23                 // Field mbuf:Lcom/jcraft/jsch/Buffer;
     704: bipush        30
     706: invokevirtual #59                 // Method com/jcraft/jsch/Buffer.putByte:(B)V
     709: goto          730
     712: aload_0
     713: getfield      #23                 // Field mbuf:Lcom/jcraft/jsch/Buffer;
     716: bipush        14
     718: invokevirtual #59                 // Method com/jcraft/jsch/Buffer.putByte:(B)V
     721: aload_0
     722: getfield      #23                 // Field mbuf:Lcom/jcraft/jsch/Buffer;
     725: aload         14
     727: invokevirtual #66                 // Method com/jcraft/jsch/Buffer.putString:([B)V
     730: goto          903
     733: iload         5
     735: bipush        18
     737: if_icmpne     771
     740: aload_0
     741: getfield      #20                 // Field rbuf:Lcom/jcraft/jsch/Buffer;
     744: invokevirtual #68                 // Method com/jcraft/jsch/Buffer.getString:()[B
     747: astore        9
     749: aload         7
     751: aload         9
     753: invokeinterface #81,  2           // InterfaceMethod com/jcraft/jsch/IdentityRepository.remove:([B)Z
     758: pop
     759: aload_0
     760: getfield      #23                 // Field mbuf:Lcom/jcraft/jsch/Buffer;
     763: bipush        6
     765: invokevirtual #59                 // Method com/jcraft/jsch/Buffer.putByte:(B)V
     768: goto          903
     771: iload         5
     773: bipush        9
     775: if_icmpne     790
     778: aload_0
     779: getfield      #23                 // Field mbuf:Lcom/jcraft/jsch/Buffer;
     782: bipush        6
     784: invokevirtual #59                 // Method com/jcraft/jsch/Buffer.putByte:(B)V
     787: goto          903
     790: iload         5
     792: bipush        19
     794: if_icmpne     816
     797: aload         7
     799: invokeinterface #82,  1           // InterfaceMethod com/jcraft/jsch/IdentityRepository.removeAll:()V
     804: aload_0
     805: getfield      #23                 // Field mbuf:Lcom/jcraft/jsch/Buffer;
     808: bipush        6
     810: invokevirtual #59                 // Method com/jcraft/jsch/Buffer.putByte:(B)V
     813: goto          903
     816: iload         5
     818: bipush        17
     820: if_icmpne     879
     823: aload_0
     824: getfield      #20                 // Field rbuf:Lcom/jcraft/jsch/Buffer;
     827: invokevirtual #50                 // Method com/jcraft/jsch/Buffer.getLength:()I
     830: istore        9
     832: iload         9
     834: newarray       byte
     836: astore        10
     838: aload_0
     839: getfield      #20                 // Field rbuf:Lcom/jcraft/jsch/Buffer;
     842: aload         10
     844: invokevirtual #83                 // Method com/jcraft/jsch/Buffer.getByte:([B)V
     847: aload         7
     849: aload         10
     851: invokeinterface #84,  2           // InterfaceMethod com/jcraft/jsch/IdentityRepository.add:([B)Z
     856: istore        11
     858: aload_0
     859: getfield      #23                 // Field mbuf:Lcom/jcraft/jsch/Buffer;
     862: iload         11
     864: ifeq          872
     867: bipush        6
     869: goto          873
     872: iconst_5
     873: invokevirtual #59                 // Method com/jcraft/jsch/Buffer.putByte:(B)V
     876: goto          903
     879: aload_0
     880: getfield      #20                 // Field rbuf:Lcom/jcraft/jsch/Buffer;
     883: aload_0
     884: getfield      #20                 // Field rbuf:Lcom/jcraft/jsch/Buffer;
     887: invokevirtual #50                 // Method com/jcraft/jsch/Buffer.getLength:()I
     890: iconst_1
     891: isub
     892: invokevirtual #85                 // Method com/jcraft/jsch/Buffer.skip:(I)V
     895: aload_0
     896: getfield      #23                 // Field mbuf:Lcom/jcraft/jsch/Buffer;
     899: iconst_5
     900: invokevirtual #59                 // Method com/jcraft/jsch/Buffer.putByte:(B)V
     903: aload_0
     904: getfield      #23                 // Field mbuf:Lcom/jcraft/jsch/Buffer;
     907: invokevirtual #50                 // Method com/jcraft/jsch/Buffer.getLength:()I
     910: newarray       byte
     912: astore        9
     914: aload_0
     915: getfield      #23                 // Field mbuf:Lcom/jcraft/jsch/Buffer;
     918: aload         9
     920: invokevirtual #83                 // Method com/jcraft/jsch/Buffer.getByte:([B)V
     923: aload_0
     924: aload         9
     926: invokespecial #86                 // Method send:([B)V
     929: return
    Exception table:
       from    to  target type
         165   171   174   Class com/jcraft/jsch/JSchException
         241   373   376   any
         376   381   376   any
         613   625   631   Class com/jcraft/jsch/JSchException
         464   665   668   any
         668   673   668   any

  private void send(byte[]);
    Code:
       0: aload_0
       1: getfield      #22                 // Field packet:Lcom/jcraft/jsch/Packet;
       4: invokevirtual #87                 // Method com/jcraft/jsch/Packet.reset:()V
       7: aload_0
       8: getfield      #21                 // Field wbuf:Lcom/jcraft/jsch/Buffer;
      11: bipush        94
      13: invokevirtual #59                 // Method com/jcraft/jsch/Buffer.putByte:(B)V
      16: aload_0
      17: getfield      #21                 // Field wbuf:Lcom/jcraft/jsch/Buffer;
      20: aload_0
      21: getfield      #88                 // Field recipient:I
      24: invokevirtual #65                 // Method com/jcraft/jsch/Buffer.putInt:(I)V
      27: aload_0
      28: getfield      #21                 // Field wbuf:Lcom/jcraft/jsch/Buffer;
      31: iconst_4
      32: aload_1
      33: arraylength
      34: iadd
      35: invokevirtual #65                 // Method com/jcraft/jsch/Buffer.putInt:(I)V
      38: aload_0
      39: getfield      #21                 // Field wbuf:Lcom/jcraft/jsch/Buffer;
      42: aload_1
      43: invokevirtual #66                 // Method com/jcraft/jsch/Buffer.putString:([B)V
      46: aload_0
      47: invokevirtual #52                 // Method getSession:()Lcom/jcraft/jsch/Session;
      50: aload_0
      51: getfield      #22                 // Field packet:Lcom/jcraft/jsch/Packet;
      54: aload_0
      55: iconst_4
      56: aload_1
      57: arraylength
      58: iadd
      59: invokevirtual #89                 // Method com/jcraft/jsch/Session.write:(Lcom/jcraft/jsch/Packet;Lcom/jcraft/jsch/Channel;I)V
      62: goto          66
      65: astore_2
      66: return
    Exception table:
       from    to  target type
          46    62    65   Class java/lang/Exception

  void eof_remote();
    Code:
       0: aload_0
       1: invokespecial #90                 // Method com/jcraft/jsch/Channel.eof_remote:()V
       4: aload_0
       5: invokevirtual #91                 // Method eof:()V
       8: return
}
