Compiled from "DefaultXMLFilter.java"
public class org.xwiki.rendering.wikimodel.xhtml.filter.DefaultXMLFilter extends org.xml.sax.helpers.XMLFilterImpl implements org.xml.sax.ext.LexicalHandler {
  public static final java.lang.String SAX_LEXICAL_HANDLER_PROPERTY;

  private org.xml.sax.ext.LexicalHandler lexicalHandler;

  public org.xwiki.rendering.wikimodel.xhtml.filter.DefaultXMLFilter();
    Code:
       0: aload_0
       1: invokespecial #1                  // Method org/xml/sax/helpers/XMLFilterImpl."<init>":()V
       4: return

  public org.xwiki.rendering.wikimodel.xhtml.filter.DefaultXMLFilter(org.xml.sax.XMLReader);
    Code:
       0: aload_0
       1: aload_1
       2: invokespecial #2                  // Method org/xml/sax/helpers/XMLFilterImpl."<init>":(Lorg/xml/sax/XMLReader;)V
       5: return

  public void parse(org.xml.sax.InputSource) throws org.xml.sax.SAXException, java.io.IOException;
    Code:
       0: aload_0
       1: invokevirtual #3                  // Method getParent:()Lorg/xml/sax/XMLReader;
       4: ifnull        19
       7: aload_0
       8: invokevirtual #3                  // Method getParent:()Lorg/xml/sax/XMLReader;
      11: ldc           #5                  // String http://xml.org/sax/properties/lexical-handler
      13: aload_0
      14: invokeinterface #6,  3            // InterfaceMethod org/xml/sax/XMLReader.setProperty:(Ljava/lang/String;Ljava/lang/Object;)V
      19: aload_0
      20: aload_1
      21: invokespecial #7                  // Method org/xml/sax/helpers/XMLFilterImpl.parse:(Lorg/xml/sax/InputSource;)V
      24: return

  public void setProperty(java.lang.String, java.lang.Object) throws org.xml.sax.SAXNotRecognizedException, org.xml.sax.SAXNotSupportedException;
    Code:
       0: ldc           #5                  // String http://xml.org/sax/properties/lexical-handler
       2: aload_1
       3: invokevirtual #8                  // Method java/lang/String.equals:(Ljava/lang/Object;)Z
       6: ifeq          20
       9: aload_0
      10: aload_2
      11: checkcast     #9                  // class org/xml/sax/ext/LexicalHandler
      14: putfield      #10                 // Field lexicalHandler:Lorg/xml/sax/ext/LexicalHandler;
      17: goto          26
      20: aload_0
      21: aload_1
      22: aload_2
      23: invokespecial #11                 // Method org/xml/sax/helpers/XMLFilterImpl.setProperty:(Ljava/lang/String;Ljava/lang/Object;)V
      26: return

  public java.lang.Object getProperty(java.lang.String) throws org.xml.sax.SAXNotRecognizedException, org.xml.sax.SAXNotSupportedException;
    Code:
       0: ldc           #5                  // String http://xml.org/sax/properties/lexical-handler
       2: aload_1
       3: invokevirtual #8                  // Method java/lang/String.equals:(Ljava/lang/Object;)Z
       6: ifeq          14
       9: aload_0
      10: getfield      #10                 // Field lexicalHandler:Lorg/xml/sax/ext/LexicalHandler;
      13: areturn
      14: aload_0
      15: aload_1
      16: invokespecial #12                 // Method org/xml/sax/helpers/XMLFilterImpl.getProperty:(Ljava/lang/String;)Ljava/lang/Object;
      19: areturn

  public void comment(char[], int, int) throws org.xml.sax.SAXException;
    Code:
       0: aload_0
       1: getfield      #10                 // Field lexicalHandler:Lorg/xml/sax/ext/LexicalHandler;
       4: ifnull        19
       7: aload_0
       8: getfield      #10                 // Field lexicalHandler:Lorg/xml/sax/ext/LexicalHandler;
      11: aload_1
      12: iload_2
      13: iload_3
      14: invokeinterface #13,  4           // InterfaceMethod org/xml/sax/ext/LexicalHandler.comment:([CII)V
      19: return

  public void endCDATA() throws org.xml.sax.SAXException;
    Code:
       0: aload_0
       1: getfield      #10                 // Field lexicalHandler:Lorg/xml/sax/ext/LexicalHandler;
       4: ifnull        16
       7: aload_0
       8: getfield      #10                 // Field lexicalHandler:Lorg/xml/sax/ext/LexicalHandler;
      11: invokeinterface #14,  1           // InterfaceMethod org/xml/sax/ext/LexicalHandler.endCDATA:()V
      16: return

  public void endDTD() throws org.xml.sax.SAXException;
    Code:
       0: aload_0
       1: getfield      #10                 // Field lexicalHandler:Lorg/xml/sax/ext/LexicalHandler;
       4: ifnull        16
       7: aload_0
       8: getfield      #10                 // Field lexicalHandler:Lorg/xml/sax/ext/LexicalHandler;
      11: invokeinterface #15,  1           // InterfaceMethod org/xml/sax/ext/LexicalHandler.endDTD:()V
      16: return

  public void endEntity(java.lang.String) throws org.xml.sax.SAXException;
    Code:
       0: aload_0
       1: getfield      #10                 // Field lexicalHandler:Lorg/xml/sax/ext/LexicalHandler;
       4: ifnull        17
       7: aload_0
       8: getfield      #10                 // Field lexicalHandler:Lorg/xml/sax/ext/LexicalHandler;
      11: aload_1
      12: invokeinterface #16,  2           // InterfaceMethod org/xml/sax/ext/LexicalHandler.endEntity:(Ljava/lang/String;)V
      17: return

  public void startCDATA() throws org.xml.sax.SAXException;
    Code:
       0: aload_0
       1: getfield      #10                 // Field lexicalHandler:Lorg/xml/sax/ext/LexicalHandler;
       4: ifnull        16
       7: aload_0
       8: getfield      #10                 // Field lexicalHandler:Lorg/xml/sax/ext/LexicalHandler;
      11: invokeinterface #17,  1           // InterfaceMethod org/xml/sax/ext/LexicalHandler.startCDATA:()V
      16: return

  public void startDTD(java.lang.String, java.lang.String, java.lang.String) throws org.xml.sax.SAXException;
    Code:
       0: aload_0
       1: getfield      #10                 // Field lexicalHandler:Lorg/xml/sax/ext/LexicalHandler;
       4: ifnull        19
       7: aload_0
       8: getfield      #10                 // Field lexicalHandler:Lorg/xml/sax/ext/LexicalHandler;
      11: aload_1
      12: aload_2
      13: aload_3
      14: invokeinterface #18,  4           // InterfaceMethod org/xml/sax/ext/LexicalHandler.startDTD:(Ljava/lang/String;Ljava/lang/String;Ljava/lang/String;)V
      19: return

  public void startEntity(java.lang.String) throws org.xml.sax.SAXException;
    Code:
       0: aload_0
       1: getfield      #10                 // Field lexicalHandler:Lorg/xml/sax/ext/LexicalHandler;
       4: ifnull        17
       7: aload_0
       8: getfield      #10                 // Field lexicalHandler:Lorg/xml/sax/ext/LexicalHandler;
      11: aload_1
      12: invokeinterface #19,  2           // InterfaceMethod org/xml/sax/ext/LexicalHandler.startEntity:(Ljava/lang/String;)V
      17: return
}
