Compiled from "ValidatorFactoryImpl.java"
class org.hibernate.validator.internal.engine.ValidatorFactoryImpl$ValidatorFactoryScopedContext$Builder {
  private final org.hibernate.validator.internal.engine.ValidatorFactoryImpl$ValidatorFactoryScopedContext defaultContext;

  private javax.validation.MessageInterpolator messageInterpolator;

  private javax.validation.TraversableResolver traversableResolver;

  private org.hibernate.validator.internal.util.ExecutableParameterNameProvider parameterNameProvider;

  private javax.validation.ClockProvider clockProvider;

  private org.hibernate.validator.spi.scripting.ScriptEvaluatorFactory scriptEvaluatorFactory;

  private java.time.Duration temporalValidationTolerance;

  private boolean failFast;

  private boolean traversableResolverResultCacheEnabled;

  private java.lang.Object constraintValidatorPayload;

  private org.hibernate.validator.internal.engine.constraintvalidation.HibernateConstraintValidatorInitializationContextImpl constraintValidatorInitializationContext;

  org.hibernate.validator.internal.engine.ValidatorFactoryImpl$ValidatorFactoryScopedContext$Builder(org.hibernate.validator.internal.engine.ValidatorFactoryImpl$ValidatorFactoryScopedContext);
    Code:
       0: aload_0
       1: invokespecial #1                  // Method java/lang/Object."<init>":()V
       4: aload_1
       5: ldc           #2                  // String Default context cannot be null.
       7: invokestatic  #3                  // Method org/hibernate/validator/internal/util/Contracts.assertNotNull:(Ljava/lang/Object;Ljava/lang/String;)V
      10: aload_0
      11: aload_1
      12: putfield      #4                  // Field defaultContext:Lorg/hibernate/validator/internal/engine/ValidatorFactoryImpl$ValidatorFactoryScopedContext;
      15: aload_0
      16: aload_1
      17: invokestatic  #5                  // Method org/hibernate/validator/internal/engine/ValidatorFactoryImpl$ValidatorFactoryScopedContext.access$100:(Lorg/hibernate/validator/internal/engine/ValidatorFactoryImpl$ValidatorFactoryScopedContext;)Ljavax/validation/MessageInterpolator;
      20: putfield      #6                  // Field messageInterpolator:Ljavax/validation/MessageInterpolator;
      23: aload_0
      24: aload_1
      25: invokestatic  #7                  // Method org/hibernate/validator/internal/engine/ValidatorFactoryImpl$ValidatorFactoryScopedContext.access$200:(Lorg/hibernate/validator/internal/engine/ValidatorFactoryImpl$ValidatorFactoryScopedContext;)Ljavax/validation/TraversableResolver;
      28: putfield      #8                  // Field traversableResolver:Ljavax/validation/TraversableResolver;
      31: aload_0
      32: aload_1
      33: invokestatic  #9                  // Method org/hibernate/validator/internal/engine/ValidatorFactoryImpl$ValidatorFactoryScopedContext.access$300:(Lorg/hibernate/validator/internal/engine/ValidatorFactoryImpl$ValidatorFactoryScopedContext;)Lorg/hibernate/validator/internal/util/ExecutableParameterNameProvider;
      36: putfield      #10                 // Field parameterNameProvider:Lorg/hibernate/validator/internal/util/ExecutableParameterNameProvider;
      39: aload_0
      40: aload_1
      41: invokestatic  #11                 // Method org/hibernate/validator/internal/engine/ValidatorFactoryImpl$ValidatorFactoryScopedContext.access$400:(Lorg/hibernate/validator/internal/engine/ValidatorFactoryImpl$ValidatorFactoryScopedContext;)Ljavax/validation/ClockProvider;
      44: putfield      #12                 // Field clockProvider:Ljavax/validation/ClockProvider;
      47: aload_0
      48: aload_1
      49: invokestatic  #13                 // Method org/hibernate/validator/internal/engine/ValidatorFactoryImpl$ValidatorFactoryScopedContext.access$500:(Lorg/hibernate/validator/internal/engine/ValidatorFactoryImpl$ValidatorFactoryScopedContext;)Lorg/hibernate/validator/spi/scripting/ScriptEvaluatorFactory;
      52: putfield      #14                 // Field scriptEvaluatorFactory:Lorg/hibernate/validator/spi/scripting/ScriptEvaluatorFactory;
      55: aload_0
      56: aload_1
      57: invokestatic  #15                 // Method org/hibernate/validator/internal/engine/ValidatorFactoryImpl$ValidatorFactoryScopedContext.access$600:(Lorg/hibernate/validator/internal/engine/ValidatorFactoryImpl$ValidatorFactoryScopedContext;)Ljava/time/Duration;
      60: putfield      #16                 // Field temporalValidationTolerance:Ljava/time/Duration;
      63: aload_0
      64: aload_1
      65: invokestatic  #17                 // Method org/hibernate/validator/internal/engine/ValidatorFactoryImpl$ValidatorFactoryScopedContext.access$700:(Lorg/hibernate/validator/internal/engine/ValidatorFactoryImpl$ValidatorFactoryScopedContext;)Z
      68: putfield      #18                 // Field failFast:Z
      71: aload_0
      72: aload_1
      73: invokestatic  #19                 // Method org/hibernate/validator/internal/engine/ValidatorFactoryImpl$ValidatorFactoryScopedContext.access$800:(Lorg/hibernate/validator/internal/engine/ValidatorFactoryImpl$ValidatorFactoryScopedContext;)Z
      76: putfield      #20                 // Field traversableResolverResultCacheEnabled:Z
      79: aload_0
      80: aload_1
      81: invokestatic  #21                 // Method org/hibernate/validator/internal/engine/ValidatorFactoryImpl$ValidatorFactoryScopedContext.access$900:(Lorg/hibernate/validator/internal/engine/ValidatorFactoryImpl$ValidatorFactoryScopedContext;)Ljava/lang/Object;
      84: putfield      #22                 // Field constraintValidatorPayload:Ljava/lang/Object;
      87: aload_0
      88: aload_1
      89: invokestatic  #23                 // Method org/hibernate/validator/internal/engine/ValidatorFactoryImpl$ValidatorFactoryScopedContext.access$1000:(Lorg/hibernate/validator/internal/engine/ValidatorFactoryImpl$ValidatorFactoryScopedContext;)Lorg/hibernate/validator/internal/engine/constraintvalidation/HibernateConstraintValidatorInitializationContextImpl;
      92: putfield      #24                 // Field constraintValidatorInitializationContext:Lorg/hibernate/validator/internal/engine/constraintvalidation/HibernateConstraintValidatorInitializationContextImpl;
      95: return

  public org.hibernate.validator.internal.engine.ValidatorFactoryImpl$ValidatorFactoryScopedContext$Builder setMessageInterpolator(javax.validation.MessageInterpolator);
    Code:
       0: aload_1
       1: ifnonnull     18
       4: aload_0
       5: aload_0
       6: getfield      #4                  // Field defaultContext:Lorg/hibernate/validator/internal/engine/ValidatorFactoryImpl$ValidatorFactoryScopedContext;
       9: invokestatic  #5                  // Method org/hibernate/validator/internal/engine/ValidatorFactoryImpl$ValidatorFactoryScopedContext.access$100:(Lorg/hibernate/validator/internal/engine/ValidatorFactoryImpl$ValidatorFactoryScopedContext;)Ljavax/validation/MessageInterpolator;
      12: putfield      #6                  // Field messageInterpolator:Ljavax/validation/MessageInterpolator;
      15: goto          23
      18: aload_0
      19: aload_1
      20: putfield      #6                  // Field messageInterpolator:Ljavax/validation/MessageInterpolator;
      23: aload_0
      24: areturn

  public org.hibernate.validator.internal.engine.ValidatorFactoryImpl$ValidatorFactoryScopedContext$Builder setTraversableResolver(javax.validation.TraversableResolver);
    Code:
       0: aload_1
       1: ifnonnull     18
       4: aload_0
       5: aload_0
       6: getfield      #4                  // Field defaultContext:Lorg/hibernate/validator/internal/engine/ValidatorFactoryImpl$ValidatorFactoryScopedContext;
       9: invokestatic  #7                  // Method org/hibernate/validator/internal/engine/ValidatorFactoryImpl$ValidatorFactoryScopedContext.access$200:(Lorg/hibernate/validator/internal/engine/ValidatorFactoryImpl$ValidatorFactoryScopedContext;)Ljavax/validation/TraversableResolver;
      12: putfield      #8                  // Field traversableResolver:Ljavax/validation/TraversableResolver;
      15: goto          23
      18: aload_0
      19: aload_1
      20: putfield      #8                  // Field traversableResolver:Ljavax/validation/TraversableResolver;
      23: aload_0
      24: areturn

  public org.hibernate.validator.internal.engine.ValidatorFactoryImpl$ValidatorFactoryScopedContext$Builder setParameterNameProvider(javax.validation.ParameterNameProvider);
    Code:
       0: aload_1
       1: ifnonnull     18
       4: aload_0
       5: aload_0
       6: getfield      #4                  // Field defaultContext:Lorg/hibernate/validator/internal/engine/ValidatorFactoryImpl$ValidatorFactoryScopedContext;
       9: invokestatic  #9                  // Method org/hibernate/validator/internal/engine/ValidatorFactoryImpl$ValidatorFactoryScopedContext.access$300:(Lorg/hibernate/validator/internal/engine/ValidatorFactoryImpl$ValidatorFactoryScopedContext;)Lorg/hibernate/validator/internal/util/ExecutableParameterNameProvider;
      12: putfield      #10                 // Field parameterNameProvider:Lorg/hibernate/validator/internal/util/ExecutableParameterNameProvider;
      15: goto          30
      18: aload_0
      19: new           #25                 // class org/hibernate/validator/internal/util/ExecutableParameterNameProvider
      22: dup
      23: aload_1
      24: invokespecial #26                 // Method org/hibernate/validator/internal/util/ExecutableParameterNameProvider."<init>":(Ljavax/validation/ParameterNameProvider;)V
      27: putfield      #10                 // Field parameterNameProvider:Lorg/hibernate/validator/internal/util/ExecutableParameterNameProvider;
      30: aload_0
      31: areturn

  public org.hibernate.validator.internal.engine.ValidatorFactoryImpl$ValidatorFactoryScopedContext$Builder setClockProvider(javax.validation.ClockProvider);
    Code:
       0: aload_1
       1: ifnonnull     18
       4: aload_0
       5: aload_0
       6: getfield      #4                  // Field defaultContext:Lorg/hibernate/validator/internal/engine/ValidatorFactoryImpl$ValidatorFactoryScopedContext;
       9: invokestatic  #11                 // Method org/hibernate/validator/internal/engine/ValidatorFactoryImpl$ValidatorFactoryScopedContext.access$400:(Lorg/hibernate/validator/internal/engine/ValidatorFactoryImpl$ValidatorFactoryScopedContext;)Ljavax/validation/ClockProvider;
      12: putfield      #12                 // Field clockProvider:Ljavax/validation/ClockProvider;
      15: goto          23
      18: aload_0
      19: aload_1
      20: putfield      #12                 // Field clockProvider:Ljavax/validation/ClockProvider;
      23: aload_0
      24: areturn

  public org.hibernate.validator.internal.engine.ValidatorFactoryImpl$ValidatorFactoryScopedContext$Builder setTemporalValidationTolerance(java.time.Duration);
    Code:
       0: aload_0
       1: aload_1
       2: ifnonnull     11
       5: getstatic     #27                 // Field java/time/Duration.ZERO:Ljava/time/Duration;
       8: goto          15
      11: aload_1
      12: invokevirtual #28                 // Method java/time/Duration.abs:()Ljava/time/Duration;
      15: putfield      #16                 // Field temporalValidationTolerance:Ljava/time/Duration;
      18: aload_0
      19: areturn

  public org.hibernate.validator.internal.engine.ValidatorFactoryImpl$ValidatorFactoryScopedContext$Builder setScriptEvaluatorFactory(org.hibernate.validator.spi.scripting.ScriptEvaluatorFactory);
    Code:
       0: aload_1
       1: ifnonnull     18
       4: aload_0
       5: aload_0
       6: getfield      #4                  // Field defaultContext:Lorg/hibernate/validator/internal/engine/ValidatorFactoryImpl$ValidatorFactoryScopedContext;
       9: invokestatic  #13                 // Method org/hibernate/validator/internal/engine/ValidatorFactoryImpl$ValidatorFactoryScopedContext.access$500:(Lorg/hibernate/validator/internal/engine/ValidatorFactoryImpl$ValidatorFactoryScopedContext;)Lorg/hibernate/validator/spi/scripting/ScriptEvaluatorFactory;
      12: putfield      #14                 // Field scriptEvaluatorFactory:Lorg/hibernate/validator/spi/scripting/ScriptEvaluatorFactory;
      15: goto          23
      18: aload_0
      19: aload_1
      20: putfield      #14                 // Field scriptEvaluatorFactory:Lorg/hibernate/validator/spi/scripting/ScriptEvaluatorFactory;
      23: aload_0
      24: areturn

  public org.hibernate.validator.internal.engine.ValidatorFactoryImpl$ValidatorFactoryScopedContext$Builder setFailFast(boolean);
    Code:
       0: aload_0
       1: iload_1
       2: putfield      #18                 // Field failFast:Z
       5: aload_0
       6: areturn

  public org.hibernate.validator.internal.engine.ValidatorFactoryImpl$ValidatorFactoryScopedContext$Builder setTraversableResolverResultCacheEnabled(boolean);
    Code:
       0: aload_0
       1: iload_1
       2: putfield      #20                 // Field traversableResolverResultCacheEnabled:Z
       5: aload_0
       6: areturn

  public org.hibernate.validator.internal.engine.ValidatorFactoryImpl$ValidatorFactoryScopedContext$Builder setConstraintValidatorPayload(java.lang.Object);
    Code:
       0: aload_0
       1: aload_1
       2: putfield      #22                 // Field constraintValidatorPayload:Ljava/lang/Object;
       5: aload_0
       6: areturn

  public org.hibernate.validator.internal.engine.ValidatorFactoryImpl$ValidatorFactoryScopedContext build();
    Code:
       0: new           #29                 // class org/hibernate/validator/internal/engine/ValidatorFactoryImpl$ValidatorFactoryScopedContext
       3: dup
       4: aload_0
       5: getfield      #6                  // Field messageInterpolator:Ljavax/validation/MessageInterpolator;
       8: aload_0
       9: getfield      #8                  // Field traversableResolver:Ljavax/validation/TraversableResolver;
      12: aload_0
      13: getfield      #10                 // Field parameterNameProvider:Lorg/hibernate/validator/internal/util/ExecutableParameterNameProvider;
      16: aload_0
      17: getfield      #12                 // Field clockProvider:Ljavax/validation/ClockProvider;
      20: aload_0
      21: getfield      #16                 // Field temporalValidationTolerance:Ljava/time/Duration;
      24: aload_0
      25: getfield      #14                 // Field scriptEvaluatorFactory:Lorg/hibernate/validator/spi/scripting/ScriptEvaluatorFactory;
      28: aload_0
      29: getfield      #18                 // Field failFast:Z
      32: aload_0
      33: getfield      #20                 // Field traversableResolverResultCacheEnabled:Z
      36: aload_0
      37: getfield      #22                 // Field constraintValidatorPayload:Ljava/lang/Object;
      40: aload_0
      41: getfield      #24                 // Field constraintValidatorInitializationContext:Lorg/hibernate/validator/internal/engine/constraintvalidation/HibernateConstraintValidatorInitializationContextImpl;
      44: aload_0
      45: getfield      #14                 // Field scriptEvaluatorFactory:Lorg/hibernate/validator/spi/scripting/ScriptEvaluatorFactory;
      48: aload_0
      49: getfield      #12                 // Field clockProvider:Ljavax/validation/ClockProvider;
      52: aload_0
      53: getfield      #16                 // Field temporalValidationTolerance:Ljava/time/Duration;
      56: invokestatic  #30                 // Method org/hibernate/validator/internal/engine/constraintvalidation/HibernateConstraintValidatorInitializationContextImpl.of:(Lorg/hibernate/validator/internal/engine/constraintvalidation/HibernateConstraintValidatorInitializationContextImpl;Lorg/hibernate/validator/spi/scripting/ScriptEvaluatorFactory;Ljavax/validation/ClockProvider;Ljava/time/Duration;)Lorg/hibernate/validator/internal/engine/constraintvalidation/HibernateConstraintValidatorInitializationContextImpl;
      59: aconst_null
      60: invokespecial #31                 // Method org/hibernate/validator/internal/engine/ValidatorFactoryImpl$ValidatorFactoryScopedContext."<init>":(Ljavax/validation/MessageInterpolator;Ljavax/validation/TraversableResolver;Lorg/hibernate/validator/internal/util/ExecutableParameterNameProvider;Ljavax/validation/ClockProvider;Ljava/time/Duration;Lorg/hibernate/validator/spi/scripting/ScriptEvaluatorFactory;ZZLjava/lang/Object;Lorg/hibernate/validator/internal/engine/constraintvalidation/HibernateConstraintValidatorInitializationContextImpl;Lorg/hibernate/validator/internal/engine/ValidatorFactoryImpl$1;)V
      63: areturn
}
