Compiled from "NettyDataBufferFactory.java"
public class org.springframework.core.io.buffer.NettyDataBufferFactory implements org.springframework.core.io.buffer.DataBufferFactory {
  private final io.netty.buffer.ByteBufAllocator byteBufAllocator;

  public org.springframework.core.io.buffer.NettyDataBufferFactory(io.netty.buffer.ByteBufAllocator);
    Code:
       0: aload_0
       1: invokespecial #1                  // Method java/lang/Object."<init>":()V
       4: aload_1
       5: ldc           #2                  // String ByteBufAllocator must not be null
       7: invokestatic  #3                  // Method org/springframework/util/Assert.notNull:(Ljava/lang/Object;Ljava/lang/String;)V
      10: aload_0
      11: aload_1
      12: putfield      #4                  // Field byteBufAllocator:Lio/netty/buffer/ByteBufAllocator;
      15: return

  public io.netty.buffer.ByteBufAllocator getByteBufAllocator();
    Code:
       0: aload_0
       1: getfield      #4                  // Field byteBufAllocator:Lio/netty/buffer/ByteBufAllocator;
       4: areturn

  public org.springframework.core.io.buffer.NettyDataBuffer allocateBuffer();
    Code:
       0: aload_0
       1: getfield      #4                  // Field byteBufAllocator:Lio/netty/buffer/ByteBufAllocator;
       4: invokeinterface #5,  1            // InterfaceMethod io/netty/buffer/ByteBufAllocator.buffer:()Lio/netty/buffer/ByteBuf;
       9: astore_1
      10: new           #6                  // class org/springframework/core/io/buffer/NettyDataBuffer
      13: dup
      14: aload_1
      15: aload_0
      16: invokespecial #7                  // Method org/springframework/core/io/buffer/NettyDataBuffer."<init>":(Lio/netty/buffer/ByteBuf;Lorg/springframework/core/io/buffer/NettyDataBufferFactory;)V
      19: areturn

  public org.springframework.core.io.buffer.NettyDataBuffer allocateBuffer(int);
    Code:
       0: aload_0
       1: getfield      #4                  // Field byteBufAllocator:Lio/netty/buffer/ByteBufAllocator;
       4: iload_1
       5: invokeinterface #8,  2            // InterfaceMethod io/netty/buffer/ByteBufAllocator.buffer:(I)Lio/netty/buffer/ByteBuf;
      10: astore_2
      11: new           #6                  // class org/springframework/core/io/buffer/NettyDataBuffer
      14: dup
      15: aload_2
      16: aload_0
      17: invokespecial #7                  // Method org/springframework/core/io/buffer/NettyDataBuffer."<init>":(Lio/netty/buffer/ByteBuf;Lorg/springframework/core/io/buffer/NettyDataBufferFactory;)V
      20: areturn

  public org.springframework.core.io.buffer.NettyDataBuffer wrap(java.nio.ByteBuffer);
    Code:
       0: aload_1
       1: invokestatic  #9                  // Method io/netty/buffer/Unpooled.wrappedBuffer:(Ljava/nio/ByteBuffer;)Lio/netty/buffer/ByteBuf;
       4: astore_2
       5: new           #6                  // class org/springframework/core/io/buffer/NettyDataBuffer
       8: dup
       9: aload_2
      10: aload_0
      11: invokespecial #7                  // Method org/springframework/core/io/buffer/NettyDataBuffer."<init>":(Lio/netty/buffer/ByteBuf;Lorg/springframework/core/io/buffer/NettyDataBufferFactory;)V
      14: areturn

  public org.springframework.core.io.buffer.DataBuffer wrap(byte[]);
    Code:
       0: aload_1
       1: invokestatic  #10                 // Method io/netty/buffer/Unpooled.wrappedBuffer:([B)Lio/netty/buffer/ByteBuf;
       4: astore_2
       5: new           #6                  // class org/springframework/core/io/buffer/NettyDataBuffer
       8: dup
       9: aload_2
      10: aload_0
      11: invokespecial #7                  // Method org/springframework/core/io/buffer/NettyDataBuffer."<init>":(Lio/netty/buffer/ByteBuf;Lorg/springframework/core/io/buffer/NettyDataBufferFactory;)V
      14: areturn

  public org.springframework.core.io.buffer.NettyDataBuffer wrap(io.netty.buffer.ByteBuf);
    Code:
       0: aload_1
       1: invokevirtual #11                 // Method io/netty/buffer/ByteBuf.touch:()Lio/netty/buffer/ByteBuf;
       4: pop
       5: new           #6                  // class org/springframework/core/io/buffer/NettyDataBuffer
       8: dup
       9: aload_1
      10: aload_0
      11: invokespecial #7                  // Method org/springframework/core/io/buffer/NettyDataBuffer."<init>":(Lio/netty/buffer/ByteBuf;Lorg/springframework/core/io/buffer/NettyDataBufferFactory;)V
      14: areturn

  public org.springframework.core.io.buffer.DataBuffer join(java.util.List<? extends org.springframework.core.io.buffer.DataBuffer>);
    Code:
       0: aload_1
       1: ldc           #12                 // String DataBuffer List must not be empty
       3: invokestatic  #13                 // Method org/springframework/util/Assert.notEmpty:(Ljava/util/Collection;Ljava/lang/String;)V
       6: aload_1
       7: invokeinterface #14,  1           // InterfaceMethod java/util/List.size:()I
      12: istore_2
      13: iload_2
      14: iconst_1
      15: if_icmpne     29
      18: aload_1
      19: iconst_0
      20: invokeinterface #15,  2           // InterfaceMethod java/util/List.get:(I)Ljava/lang/Object;
      25: checkcast     #16                 // class org/springframework/core/io/buffer/DataBuffer
      28: areturn
      29: aload_0
      30: getfield      #4                  // Field byteBufAllocator:Lio/netty/buffer/ByteBufAllocator;
      33: iload_2
      34: invokeinterface #17,  2           // InterfaceMethod io/netty/buffer/ByteBufAllocator.compositeBuffer:(I)Lio/netty/buffer/CompositeByteBuf;
      39: astore_3
      40: aload_1
      41: invokeinterface #18,  1           // InterfaceMethod java/util/List.iterator:()Ljava/util/Iterator;
      46: astore        4
      48: aload         4
      50: invokeinterface #19,  1           // InterfaceMethod java/util/Iterator.hasNext:()Z
      55: ifeq          94
      58: aload         4
      60: invokeinterface #20,  1           // InterfaceMethod java/util/Iterator.next:()Ljava/lang/Object;
      65: checkcast     #16                 // class org/springframework/core/io/buffer/DataBuffer
      68: astore        5
      70: ldc           #6                  // class org/springframework/core/io/buffer/NettyDataBuffer
      72: aload         5
      74: invokestatic  #21                 // Method org/springframework/util/Assert.isInstanceOf:(Ljava/lang/Class;Ljava/lang/Object;)V
      77: aload_3
      78: iconst_1
      79: aload         5
      81: checkcast     #6                  // class org/springframework/core/io/buffer/NettyDataBuffer
      84: invokevirtual #22                 // Method org/springframework/core/io/buffer/NettyDataBuffer.getNativeBuffer:()Lio/netty/buffer/ByteBuf;
      87: invokevirtual #23                 // Method io/netty/buffer/CompositeByteBuf.addComponent:(ZLio/netty/buffer/ByteBuf;)Lio/netty/buffer/CompositeByteBuf;
      90: pop
      91: goto          48
      94: new           #6                  // class org/springframework/core/io/buffer/NettyDataBuffer
      97: dup
      98: aload_3
      99: aload_0
     100: invokespecial #7                  // Method org/springframework/core/io/buffer/NettyDataBuffer."<init>":(Lio/netty/buffer/ByteBuf;Lorg/springframework/core/io/buffer/NettyDataBufferFactory;)V
     103: areturn

  public static io.netty.buffer.ByteBuf toByteBuf(org.springframework.core.io.buffer.DataBuffer);
    Code:
       0: aload_0
       1: instanceof    #6                  // class org/springframework/core/io/buffer/NettyDataBuffer
       4: ifeq          15
       7: aload_0
       8: checkcast     #6                  // class org/springframework/core/io/buffer/NettyDataBuffer
      11: invokevirtual #22                 // Method org/springframework/core/io/buffer/NettyDataBuffer.getNativeBuffer:()Lio/netty/buffer/ByteBuf;
      14: areturn
      15: aload_0
      16: invokeinterface #24,  1           // InterfaceMethod org/springframework/core/io/buffer/DataBuffer.asByteBuffer:()Ljava/nio/ByteBuffer;
      21: invokestatic  #9                  // Method io/netty/buffer/Unpooled.wrappedBuffer:(Ljava/nio/ByteBuffer;)Lio/netty/buffer/ByteBuf;
      24: areturn

  public java.lang.String toString();
    Code:
       0: new           #25                 // class java/lang/StringBuilder
       3: dup
       4: invokespecial #26                 // Method java/lang/StringBuilder."<init>":()V
       7: ldc           #27                 // String NettyDataBufferFactory (
       9: invokevirtual #28                 // Method java/lang/StringBuilder.append:(Ljava/lang/String;)Ljava/lang/StringBuilder;
      12: aload_0
      13: getfield      #4                  // Field byteBufAllocator:Lio/netty/buffer/ByteBufAllocator;
      16: invokevirtual #29                 // Method java/lang/StringBuilder.append:(Ljava/lang/Object;)Ljava/lang/StringBuilder;
      19: ldc           #30                 // String )
      21: invokevirtual #28                 // Method java/lang/StringBuilder.append:(Ljava/lang/String;)Ljava/lang/StringBuilder;
      24: invokevirtual #31                 // Method java/lang/StringBuilder.toString:()Ljava/lang/String;
      27: areturn

  public org.springframework.core.io.buffer.DataBuffer wrap(java.nio.ByteBuffer);
    Code:
       0: aload_0
       1: aload_1
       2: invokevirtual #32                 // Method wrap:(Ljava/nio/ByteBuffer;)Lorg/springframework/core/io/buffer/NettyDataBuffer;
       5: areturn

  public org.springframework.core.io.buffer.DataBuffer allocateBuffer(int);
    Code:
       0: aload_0
       1: iload_1
       2: invokevirtual #33                 // Method allocateBuffer:(I)Lorg/springframework/core/io/buffer/NettyDataBuffer;
       5: areturn

  public org.springframework.core.io.buffer.DataBuffer allocateBuffer();
    Code:
       0: aload_0
       1: invokevirtual #34                 // Method allocateBuffer:()Lorg/springframework/core/io/buffer/NettyDataBuffer;
       4: areturn
}
