Compiled from "TSimpleJSONProtocol.java"
public class org.apache.thrift.protocol.TSimpleJSONProtocol$StructContext extends org.apache.thrift.protocol.TSimpleJSONProtocol$Context {
  protected boolean first_;

  protected boolean colon_;

  final org.apache.thrift.protocol.TSimpleJSONProtocol this$0;

  protected org.apache.thrift.protocol.TSimpleJSONProtocol$StructContext(org.apache.thrift.protocol.TSimpleJSONProtocol);
    Code:
       0: aload_0
       1: aload_1
       2: putfield      #1                  // Field this$0:Lorg/apache/thrift/protocol/TSimpleJSONProtocol;
       5: aload_0
       6: aload_1
       7: invokespecial #2                  // Method org/apache/thrift/protocol/TSimpleJSONProtocol$Context."<init>":(Lorg/apache/thrift/protocol/TSimpleJSONProtocol;)V
      10: aload_0
      11: iconst_1
      12: putfield      #3                  // Field first_:Z
      15: aload_0
      16: iconst_1
      17: putfield      #4                  // Field colon_:Z
      20: return

  protected void write() throws org.apache.thrift.TException;
    Code:
       0: aload_0
       1: getfield      #3                  // Field first_:Z
       4: ifeq          20
       7: aload_0
       8: iconst_0
       9: putfield      #3                  // Field first_:Z
      12: aload_0
      13: iconst_1
      14: putfield      #4                  // Field colon_:Z
      17: goto          62
      20: aload_0
      21: getfield      #1                  // Field this$0:Lorg/apache/thrift/protocol/TSimpleJSONProtocol;
      24: getfield      #5                  // Field org/apache/thrift/protocol/TSimpleJSONProtocol.trans_:Lorg/apache/thrift/transport/TTransport;
      27: aload_0
      28: getfield      #4                  // Field colon_:Z
      31: ifeq          40
      34: invokestatic  #6                  // Method org/apache/thrift/protocol/TSimpleJSONProtocol.access$100:()[B
      37: goto          43
      40: invokestatic  #7                  // Method org/apache/thrift/protocol/TSimpleJSONProtocol.access$000:()[B
      43: invokevirtual #8                  // Method org/apache/thrift/transport/TTransport.write:([B)V
      46: aload_0
      47: aload_0
      48: getfield      #4                  // Field colon_:Z
      51: ifne          58
      54: iconst_1
      55: goto          59
      58: iconst_0
      59: putfield      #4                  // Field colon_:Z
      62: return
}
