Compiled from "ConfigurationDynaClass.java"
public class org.apache.commons.configuration2.beanutils.ConfigurationDynaClass implements org.apache.commons.beanutils.DynaClass {
  private static final org.apache.commons.logging.Log LOG;

  private final org.apache.commons.configuration2.Configuration configuration;

  public org.apache.commons.configuration2.beanutils.ConfigurationDynaClass(org.apache.commons.configuration2.Configuration);
    Code:
       0: aload_0
       1: invokespecial #1                  // Method java/lang/Object."<init>":()V
       4: getstatic     #2                  // Field LOG:Lorg/apache/commons/logging/Log;
       7: invokeinterface #3,  1            // InterfaceMethod org/apache/commons/logging/Log.isTraceEnabled:()Z
      12: ifeq          47
      15: getstatic     #2                  // Field LOG:Lorg/apache/commons/logging/Log;
      18: new           #4                  // class java/lang/StringBuilder
      21: dup
      22: invokespecial #5                  // Method java/lang/StringBuilder."<init>":()V
      25: ldc           #6                  // String ConfigurationDynaClass(
      27: invokevirtual #7                  // Method java/lang/StringBuilder.append:(Ljava/lang/String;)Ljava/lang/StringBuilder;
      30: aload_1
      31: invokevirtual #8                  // Method java/lang/StringBuilder.append:(Ljava/lang/Object;)Ljava/lang/StringBuilder;
      34: ldc           #9                  // String )
      36: invokevirtual #7                  // Method java/lang/StringBuilder.append:(Ljava/lang/String;)Ljava/lang/StringBuilder;
      39: invokevirtual #10                 // Method java/lang/StringBuilder.toString:()Ljava/lang/String;
      42: invokeinterface #11,  2           // InterfaceMethod org/apache/commons/logging/Log.trace:(Ljava/lang/Object;)V
      47: aload_0
      48: aload_1
      49: putfield      #12                 // Field configuration:Lorg/apache/commons/configuration2/Configuration;
      52: return

  public org.apache.commons.beanutils.DynaProperty getDynaProperty(java.lang.String);
    Code:
       0: getstatic     #2                  // Field LOG:Lorg/apache/commons/logging/Log;
       3: invokeinterface #3,  1            // InterfaceMethod org/apache/commons/logging/Log.isTraceEnabled:()Z
       8: ifeq          43
      11: getstatic     #2                  // Field LOG:Lorg/apache/commons/logging/Log;
      14: new           #4                  // class java/lang/StringBuilder
      17: dup
      18: invokespecial #5                  // Method java/lang/StringBuilder."<init>":()V
      21: ldc           #13                 // String getDynaProperty(
      23: invokevirtual #7                  // Method java/lang/StringBuilder.append:(Ljava/lang/String;)Ljava/lang/StringBuilder;
      26: aload_1
      27: invokevirtual #7                  // Method java/lang/StringBuilder.append:(Ljava/lang/String;)Ljava/lang/StringBuilder;
      30: ldc           #9                  // String )
      32: invokevirtual #7                  // Method java/lang/StringBuilder.append:(Ljava/lang/String;)Ljava/lang/StringBuilder;
      35: invokevirtual #10                 // Method java/lang/StringBuilder.toString:()Ljava/lang/String;
      38: invokeinterface #11,  2           // InterfaceMethod org/apache/commons/logging/Log.trace:(Ljava/lang/Object;)V
      43: aload_1
      44: ifnonnull     57
      47: new           #14                 // class java/lang/IllegalArgumentException
      50: dup
      51: ldc           #15                 // String Property name must not be null!
      53: invokespecial #16                 // Method java/lang/IllegalArgumentException."<init>":(Ljava/lang/String;)V
      56: athrow
      57: aload_0
      58: getfield      #12                 // Field configuration:Lorg/apache/commons/configuration2/Configuration;
      61: aload_1
      62: invokeinterface #17,  2           // InterfaceMethod org/apache/commons/configuration2/Configuration.getProperty:(Ljava/lang/String;)Ljava/lang/Object;
      67: astore_2
      68: aload_2
      69: ifnonnull     74
      72: aconst_null
      73: areturn
      74: aload_2
      75: invokevirtual #18                 // Method java/lang/Object.getClass:()Ljava/lang/Class;
      78: astore_3
      79: aload_3
      80: ldc           #19                 // class java/lang/Byte
      82: if_acmpne     89
      85: getstatic     #20                 // Field java/lang/Byte.TYPE:Ljava/lang/Class;
      88: astore_3
      89: aload_3
      90: ldc           #21                 // class java/lang/Character
      92: if_acmpne     102
      95: getstatic     #22                 // Field java/lang/Character.TYPE:Ljava/lang/Class;
      98: astore_3
      99: goto          177
     102: aload_3
     103: ldc           #23                 // class java/lang/Boolean
     105: if_acmpne     115
     108: getstatic     #24                 // Field java/lang/Boolean.TYPE:Ljava/lang/Class;
     111: astore_3
     112: goto          177
     115: aload_3
     116: ldc           #25                 // class java/lang/Double
     118: if_acmpne     128
     121: getstatic     #26                 // Field java/lang/Double.TYPE:Ljava/lang/Class;
     124: astore_3
     125: goto          177
     128: aload_3
     129: ldc           #27                 // class java/lang/Float
     131: if_acmpne     141
     134: getstatic     #28                 // Field java/lang/Float.TYPE:Ljava/lang/Class;
     137: astore_3
     138: goto          177
     141: aload_3
     142: ldc           #29                 // class java/lang/Integer
     144: if_acmpne     154
     147: getstatic     #30                 // Field java/lang/Integer.TYPE:Ljava/lang/Class;
     150: astore_3
     151: goto          177
     154: aload_3
     155: ldc           #31                 // class java/lang/Long
     157: if_acmpne     167
     160: getstatic     #32                 // Field java/lang/Long.TYPE:Ljava/lang/Class;
     163: astore_3
     164: goto          177
     167: aload_3
     168: ldc           #33                 // class java/lang/Short
     170: if_acmpne     177
     173: getstatic     #34                 // Field java/lang/Short.TYPE:Ljava/lang/Class;
     176: astore_3
     177: new           #35                 // class org/apache/commons/beanutils/DynaProperty
     180: dup
     181: aload_1
     182: aload_3
     183: invokespecial #36                 // Method org/apache/commons/beanutils/DynaProperty."<init>":(Ljava/lang/String;Ljava/lang/Class;)V
     186: areturn

  public org.apache.commons.beanutils.DynaProperty[] getDynaProperties();
    Code:
       0: getstatic     #2                  // Field LOG:Lorg/apache/commons/logging/Log;
       3: invokeinterface #3,  1            // InterfaceMethod org/apache/commons/logging/Log.isTraceEnabled:()Z
       8: ifeq          21
      11: getstatic     #2                  // Field LOG:Lorg/apache/commons/logging/Log;
      14: ldc           #37                 // String getDynaProperties()
      16: invokeinterface #11,  2           // InterfaceMethod org/apache/commons/logging/Log.trace:(Ljava/lang/Object;)V
      21: aload_0
      22: getfield      #12                 // Field configuration:Lorg/apache/commons/configuration2/Configuration;
      25: invokeinterface #38,  1           // InterfaceMethod org/apache/commons/configuration2/Configuration.getKeys:()Ljava/util/Iterator;
      30: astore_1
      31: new           #39                 // class java/util/ArrayList
      34: dup
      35: invokespecial #40                 // Method java/util/ArrayList."<init>":()V
      38: astore_2
      39: aload_1
      40: invokeinterface #41,  1           // InterfaceMethod java/util/Iterator.hasNext:()Z
      45: ifeq          77
      48: aload_1
      49: invokeinterface #42,  1           // InterfaceMethod java/util/Iterator.next:()Ljava/lang/Object;
      54: checkcast     #43                 // class java/lang/String
      57: astore_3
      58: aload_0
      59: aload_3
      60: invokevirtual #44                 // Method getDynaProperty:(Ljava/lang/String;)Lorg/apache/commons/beanutils/DynaProperty;
      63: astore        4
      65: aload_2
      66: aload         4
      68: invokeinterface #45,  2           // InterfaceMethod java/util/List.add:(Ljava/lang/Object;)Z
      73: pop
      74: goto          39
      77: aload_2
      78: invokeinterface #46,  1           // InterfaceMethod java/util/List.size:()I
      83: anewarray     #35                 // class org/apache/commons/beanutils/DynaProperty
      86: astore_3
      87: aload_2
      88: aload_3
      89: invokeinterface #47,  2           // InterfaceMethod java/util/List.toArray:([Ljava/lang/Object;)[Ljava/lang/Object;
      94: pop
      95: getstatic     #2                  // Field LOG:Lorg/apache/commons/logging/Log;
      98: invokeinterface #48,  1           // InterfaceMethod org/apache/commons/logging/Log.isDebugEnabled:()Z
     103: ifeq          143
     106: getstatic     #2                  // Field LOG:Lorg/apache/commons/logging/Log;
     109: new           #4                  // class java/lang/StringBuilder
     112: dup
     113: invokespecial #5                  // Method java/lang/StringBuilder."<init>":()V
     116: ldc           #49                 // String Found
     118: invokevirtual #7                  // Method java/lang/StringBuilder.append:(Ljava/lang/String;)Ljava/lang/StringBuilder;
     121: aload_2
     122: invokeinterface #46,  1           // InterfaceMethod java/util/List.size:()I
     127: invokevirtual #50                 // Method java/lang/StringBuilder.append:(I)Ljava/lang/StringBuilder;
     130: ldc           #51                 // String  properties.
     132: invokevirtual #7                  // Method java/lang/StringBuilder.append:(Ljava/lang/String;)Ljava/lang/StringBuilder;
     135: invokevirtual #10                 // Method java/lang/StringBuilder.toString:()Ljava/lang/String;
     138: invokeinterface #52,  2           // InterfaceMethod org/apache/commons/logging/Log.debug:(Ljava/lang/Object;)V
     143: aload_3
     144: areturn

  public java.lang.String getName();
    Code:
       0: ldc           #53                 // class org/apache/commons/configuration2/beanutils/ConfigurationDynaBean
       2: invokevirtual #54                 // Method java/lang/Class.getName:()Ljava/lang/String;
       5: areturn

  public org.apache.commons.beanutils.DynaBean newInstance() throws java.lang.IllegalAccessException, java.lang.InstantiationException;
    Code:
       0: new           #53                 // class org/apache/commons/configuration2/beanutils/ConfigurationDynaBean
       3: dup
       4: aload_0
       5: getfield      #12                 // Field configuration:Lorg/apache/commons/configuration2/Configuration;
       8: invokespecial #55                 // Method org/apache/commons/configuration2/beanutils/ConfigurationDynaBean."<init>":(Lorg/apache/commons/configuration2/Configuration;)V
      11: areturn

  static {};
    Code:
       0: ldc           #56                 // class org/apache/commons/configuration2/beanutils/ConfigurationDynaClass
       2: invokestatic  #57                 // Method org/apache/commons/logging/LogFactory.getLog:(Ljava/lang/Class;)Lorg/apache/commons/logging/Log;
       5: putstatic     #2                  // Field LOG:Lorg/apache/commons/logging/Log;
       8: return
}
