Compiled from "LangInfo.java"
public final class jnr.constants.platform.dragonflybsd.LangInfo extends java.lang.Enum<jnr.constants.platform.dragonflybsd.LangInfo> implements jnr.constants.Constant {
  public static final jnr.constants.platform.dragonflybsd.LangInfo CODESET;

  public static final jnr.constants.platform.dragonflybsd.LangInfo D_T_FMT;

  public static final jnr.constants.platform.dragonflybsd.LangInfo D_FMT;

  public static final jnr.constants.platform.dragonflybsd.LangInfo T_FMT;

  public static final jnr.constants.platform.dragonflybsd.LangInfo DAY_1;

  public static final jnr.constants.platform.dragonflybsd.LangInfo DAY_2;

  public static final jnr.constants.platform.dragonflybsd.LangInfo DAY_3;

  public static final jnr.constants.platform.dragonflybsd.LangInfo DAY_4;

  public static final jnr.constants.platform.dragonflybsd.LangInfo DAY_5;

  public static final jnr.constants.platform.dragonflybsd.LangInfo DAY_6;

  public static final jnr.constants.platform.dragonflybsd.LangInfo DAY_7;

  public static final jnr.constants.platform.dragonflybsd.LangInfo ABDAY_1;

  public static final jnr.constants.platform.dragonflybsd.LangInfo ABDAY_2;

  public static final jnr.constants.platform.dragonflybsd.LangInfo ABDAY_3;

  public static final jnr.constants.platform.dragonflybsd.LangInfo ABDAY_4;

  public static final jnr.constants.platform.dragonflybsd.LangInfo ABDAY_5;

  public static final jnr.constants.platform.dragonflybsd.LangInfo ABDAY_6;

  public static final jnr.constants.platform.dragonflybsd.LangInfo ABDAY_7;

  public static final jnr.constants.platform.dragonflybsd.LangInfo MON_1;

  public static final jnr.constants.platform.dragonflybsd.LangInfo MON_2;

  public static final jnr.constants.platform.dragonflybsd.LangInfo MON_3;

  public static final jnr.constants.platform.dragonflybsd.LangInfo MON_4;

  public static final jnr.constants.platform.dragonflybsd.LangInfo MON_5;

  public static final jnr.constants.platform.dragonflybsd.LangInfo MON_6;

  public static final jnr.constants.platform.dragonflybsd.LangInfo MON_7;

  public static final jnr.constants.platform.dragonflybsd.LangInfo MON_8;

  public static final jnr.constants.platform.dragonflybsd.LangInfo MON_9;

  public static final jnr.constants.platform.dragonflybsd.LangInfo MON_10;

  public static final jnr.constants.platform.dragonflybsd.LangInfo MON_11;

  public static final jnr.constants.platform.dragonflybsd.LangInfo MON_12;

  public static final jnr.constants.platform.dragonflybsd.LangInfo ABMON_1;

  public static final jnr.constants.platform.dragonflybsd.LangInfo ABMON_2;

  public static final jnr.constants.platform.dragonflybsd.LangInfo ABMON_3;

  public static final jnr.constants.platform.dragonflybsd.LangInfo ABMON_4;

  public static final jnr.constants.platform.dragonflybsd.LangInfo ABMON_5;

  public static final jnr.constants.platform.dragonflybsd.LangInfo ABMON_6;

  public static final jnr.constants.platform.dragonflybsd.LangInfo ABMON_7;

  public static final jnr.constants.platform.dragonflybsd.LangInfo ABMON_8;

  public static final jnr.constants.platform.dragonflybsd.LangInfo ABMON_9;

  public static final jnr.constants.platform.dragonflybsd.LangInfo ABMON_10;

  public static final jnr.constants.platform.dragonflybsd.LangInfo ABMON_11;

  public static final jnr.constants.platform.dragonflybsd.LangInfo ABMON_12;

  public static final jnr.constants.platform.dragonflybsd.LangInfo RADIXCHAR;

  public static final jnr.constants.platform.dragonflybsd.LangInfo THOUSEP;

  public static final jnr.constants.platform.dragonflybsd.LangInfo YESEXPR;

  public static final jnr.constants.platform.dragonflybsd.LangInfo NOEXPR;

  public static final jnr.constants.platform.dragonflybsd.LangInfo CRNCYSTR;

  private final long value;

  public static final long MIN_VALUE;

  public static final long MAX_VALUE;

  private static final jnr.constants.platform.dragonflybsd.LangInfo[] $VALUES;

  public static jnr.constants.platform.dragonflybsd.LangInfo[] values();
    Code:
       0: getstatic     #1                  // Field $VALUES:[Ljnr/constants/platform/dragonflybsd/LangInfo;
       3: invokevirtual #2                  // Method "[Ljnr/constants/platform/dragonflybsd/LangInfo;".clone:()Ljava/lang/Object;
       6: checkcast     #3                  // class "[Ljnr/constants/platform/dragonflybsd/LangInfo;"
       9: areturn

  public static jnr.constants.platform.dragonflybsd.LangInfo valueOf(java.lang.String);
    Code:
       0: ldc           #4                  // class jnr/constants/platform/dragonflybsd/LangInfo
       2: aload_0
       3: invokestatic  #5                  // Method java/lang/Enum.valueOf:(Ljava/lang/Class;Ljava/lang/String;)Ljava/lang/Enum;
       6: checkcast     #4                  // class jnr/constants/platform/dragonflybsd/LangInfo
       9: areturn

  private jnr.constants.platform.dragonflybsd.LangInfo(long);
    Code:
       0: aload_0
       1: aload_1
       2: iload_2
       3: invokespecial #6                  // Method java/lang/Enum."<init>":(Ljava/lang/String;I)V
       6: aload_0
       7: lload_3
       8: putfield      #7                  // Field value:J
      11: return

  public final java.lang.String toString();
    Code:
       0: getstatic     #8                  // Field jnr/constants/platform/dragonflybsd/LangInfo$StringTable.descriptions:Ljava/util/Map;
       3: aload_0
       4: invokeinterface #9,  2            // InterfaceMethod java/util/Map.get:(Ljava/lang/Object;)Ljava/lang/Object;
       9: checkcast     #10                 // class java/lang/String
      12: areturn

  public final int value();
    Code:
       0: aload_0
       1: getfield      #7                  // Field value:J
       4: l2i
       5: ireturn

  public final int intValue();
    Code:
       0: aload_0
       1: getfield      #7                  // Field value:J
       4: l2i
       5: ireturn

  public final long longValue();
    Code:
       0: aload_0
       1: getfield      #7                  // Field value:J
       4: lreturn

  public final boolean defined();
    Code:
       0: iconst_1
       1: ireturn

  static {};
    Code:
       0: new           #4                  // class jnr/constants/platform/dragonflybsd/LangInfo
       3: dup
       4: ldc           #11                 // String CODESET
       6: iconst_0
       7: lconst_0
       8: invokespecial #12                 // Method "<init>":(Ljava/lang/String;IJ)V
      11: putstatic     #13                 // Field CODESET:Ljnr/constants/platform/dragonflybsd/LangInfo;
      14: new           #4                  // class jnr/constants/platform/dragonflybsd/LangInfo
      17: dup
      18: ldc           #14                 // String D_T_FMT
      20: iconst_1
      21: lconst_1
      22: invokespecial #12                 // Method "<init>":(Ljava/lang/String;IJ)V
      25: putstatic     #15                 // Field D_T_FMT:Ljnr/constants/platform/dragonflybsd/LangInfo;
      28: new           #4                  // class jnr/constants/platform/dragonflybsd/LangInfo
      31: dup
      32: ldc           #16                 // String D_FMT
      34: iconst_2
      35: ldc2_w        #17                 // long 2l
      38: invokespecial #12                 // Method "<init>":(Ljava/lang/String;IJ)V
      41: putstatic     #19                 // Field D_FMT:Ljnr/constants/platform/dragonflybsd/LangInfo;
      44: new           #4                  // class jnr/constants/platform/dragonflybsd/LangInfo
      47: dup
      48: ldc           #20                 // String T_FMT
      50: iconst_3
      51: ldc2_w        #21                 // long 3l
      54: invokespecial #12                 // Method "<init>":(Ljava/lang/String;IJ)V
      57: putstatic     #23                 // Field T_FMT:Ljnr/constants/platform/dragonflybsd/LangInfo;
      60: new           #4                  // class jnr/constants/platform/dragonflybsd/LangInfo
      63: dup
      64: ldc           #24                 // String DAY_1
      66: iconst_4
      67: ldc2_w        #25                 // long 7l
      70: invokespecial #12                 // Method "<init>":(Ljava/lang/String;IJ)V
      73: putstatic     #27                 // Field DAY_1:Ljnr/constants/platform/dragonflybsd/LangInfo;
      76: new           #4                  // class jnr/constants/platform/dragonflybsd/LangInfo
      79: dup
      80: ldc           #28                 // String DAY_2
      82: iconst_5
      83: ldc2_w        #29                 // long 8l
      86: invokespecial #12                 // Method "<init>":(Ljava/lang/String;IJ)V
      89: putstatic     #31                 // Field DAY_2:Ljnr/constants/platform/dragonflybsd/LangInfo;
      92: new           #4                  // class jnr/constants/platform/dragonflybsd/LangInfo
      95: dup
      96: ldc           #32                 // String DAY_3
      98: bipush        6
     100: ldc2_w        #33                 // long 9l
     103: invokespecial #12                 // Method "<init>":(Ljava/lang/String;IJ)V
     106: putstatic     #35                 // Field DAY_3:Ljnr/constants/platform/dragonflybsd/LangInfo;
     109: new           #4                  // class jnr/constants/platform/dragonflybsd/LangInfo
     112: dup
     113: ldc           #36                 // String DAY_4
     115: bipush        7
     117: ldc2_w        #37                 // long 10l
     120: invokespecial #12                 // Method "<init>":(Ljava/lang/String;IJ)V
     123: putstatic     #39                 // Field DAY_4:Ljnr/constants/platform/dragonflybsd/LangInfo;
     126: new           #4                  // class jnr/constants/platform/dragonflybsd/LangInfo
     129: dup
     130: ldc           #40                 // String DAY_5
     132: bipush        8
     134: ldc2_w        #41                 // long 11l
     137: invokespecial #12                 // Method "<init>":(Ljava/lang/String;IJ)V
     140: putstatic     #43                 // Field DAY_5:Ljnr/constants/platform/dragonflybsd/LangInfo;
     143: new           #4                  // class jnr/constants/platform/dragonflybsd/LangInfo
     146: dup
     147: ldc           #44                 // String DAY_6
     149: bipush        9
     151: ldc2_w        #45                 // long 12l
     154: invokespecial #12                 // Method "<init>":(Ljava/lang/String;IJ)V
     157: putstatic     #47                 // Field DAY_6:Ljnr/constants/platform/dragonflybsd/LangInfo;
     160: new           #4                  // class jnr/constants/platform/dragonflybsd/LangInfo
     163: dup
     164: ldc           #48                 // String DAY_7
     166: bipush        10
     168: ldc2_w        #49                 // long 13l
     171: invokespecial #12                 // Method "<init>":(Ljava/lang/String;IJ)V
     174: putstatic     #51                 // Field DAY_7:Ljnr/constants/platform/dragonflybsd/LangInfo;
     177: new           #4                  // class jnr/constants/platform/dragonflybsd/LangInfo
     180: dup
     181: ldc           #52                 // String ABDAY_1
     183: bipush        11
     185: ldc2_w        #53                 // long 14l
     188: invokespecial #12                 // Method "<init>":(Ljava/lang/String;IJ)V
     191: putstatic     #55                 // Field ABDAY_1:Ljnr/constants/platform/dragonflybsd/LangInfo;
     194: new           #4                  // class jnr/constants/platform/dragonflybsd/LangInfo
     197: dup
     198: ldc           #56                 // String ABDAY_2
     200: bipush        12
     202: ldc2_w        #57                 // long 15l
     205: invokespecial #12                 // Method "<init>":(Ljava/lang/String;IJ)V
     208: putstatic     #59                 // Field ABDAY_2:Ljnr/constants/platform/dragonflybsd/LangInfo;
     211: new           #4                  // class jnr/constants/platform/dragonflybsd/LangInfo
     214: dup
     215: ldc           #60                 // String ABDAY_3
     217: bipush        13
     219: ldc2_w        #61                 // long 16l
     222: invokespecial #12                 // Method "<init>":(Ljava/lang/String;IJ)V
     225: putstatic     #63                 // Field ABDAY_3:Ljnr/constants/platform/dragonflybsd/LangInfo;
     228: new           #4                  // class jnr/constants/platform/dragonflybsd/LangInfo
     231: dup
     232: ldc           #64                 // String ABDAY_4
     234: bipush        14
     236: ldc2_w        #65                 // long 17l
     239: invokespecial #12                 // Method "<init>":(Ljava/lang/String;IJ)V
     242: putstatic     #67                 // Field ABDAY_4:Ljnr/constants/platform/dragonflybsd/LangInfo;
     245: new           #4                  // class jnr/constants/platform/dragonflybsd/LangInfo
     248: dup
     249: ldc           #68                 // String ABDAY_5
     251: bipush        15
     253: ldc2_w        #69                 // long 18l
     256: invokespecial #12                 // Method "<init>":(Ljava/lang/String;IJ)V
     259: putstatic     #71                 // Field ABDAY_5:Ljnr/constants/platform/dragonflybsd/LangInfo;
     262: new           #4                  // class jnr/constants/platform/dragonflybsd/LangInfo
     265: dup
     266: ldc           #72                 // String ABDAY_6
     268: bipush        16
     270: ldc2_w        #73                 // long 19l
     273: invokespecial #12                 // Method "<init>":(Ljava/lang/String;IJ)V
     276: putstatic     #75                 // Field ABDAY_6:Ljnr/constants/platform/dragonflybsd/LangInfo;
     279: new           #4                  // class jnr/constants/platform/dragonflybsd/LangInfo
     282: dup
     283: ldc           #76                 // String ABDAY_7
     285: bipush        17
     287: ldc2_w        #77                 // long 20l
     290: invokespecial #12                 // Method "<init>":(Ljava/lang/String;IJ)V
     293: putstatic     #79                 // Field ABDAY_7:Ljnr/constants/platform/dragonflybsd/LangInfo;
     296: new           #4                  // class jnr/constants/platform/dragonflybsd/LangInfo
     299: dup
     300: ldc           #80                 // String MON_1
     302: bipush        18
     304: ldc2_w        #81                 // long 21l
     307: invokespecial #12                 // Method "<init>":(Ljava/lang/String;IJ)V
     310: putstatic     #83                 // Field MON_1:Ljnr/constants/platform/dragonflybsd/LangInfo;
     313: new           #4                  // class jnr/constants/platform/dragonflybsd/LangInfo
     316: dup
     317: ldc           #84                 // String MON_2
     319: bipush        19
     321: ldc2_w        #85                 // long 22l
     324: invokespecial #12                 // Method "<init>":(Ljava/lang/String;IJ)V
     327: putstatic     #87                 // Field MON_2:Ljnr/constants/platform/dragonflybsd/LangInfo;
     330: new           #4                  // class jnr/constants/platform/dragonflybsd/LangInfo
     333: dup
     334: ldc           #88                 // String MON_3
     336: bipush        20
     338: ldc2_w        #89                 // long 23l
     341: invokespecial #12                 // Method "<init>":(Ljava/lang/String;IJ)V
     344: putstatic     #91                 // Field MON_3:Ljnr/constants/platform/dragonflybsd/LangInfo;
     347: new           #4                  // class jnr/constants/platform/dragonflybsd/LangInfo
     350: dup
     351: ldc           #92                 // String MON_4
     353: bipush        21
     355: ldc2_w        #93                 // long 24l
     358: invokespecial #12                 // Method "<init>":(Ljava/lang/String;IJ)V
     361: putstatic     #95                 // Field MON_4:Ljnr/constants/platform/dragonflybsd/LangInfo;
     364: new           #4                  // class jnr/constants/platform/dragonflybsd/LangInfo
     367: dup
     368: ldc           #96                 // String MON_5
     370: bipush        22
     372: ldc2_w        #97                 // long 25l
     375: invokespecial #12                 // Method "<init>":(Ljava/lang/String;IJ)V
     378: putstatic     #99                 // Field MON_5:Ljnr/constants/platform/dragonflybsd/LangInfo;
     381: new           #4                  // class jnr/constants/platform/dragonflybsd/LangInfo
     384: dup
     385: ldc           #100                // String MON_6
     387: bipush        23
     389: ldc2_w        #101                // long 26l
     392: invokespecial #12                 // Method "<init>":(Ljava/lang/String;IJ)V
     395: putstatic     #103                // Field MON_6:Ljnr/constants/platform/dragonflybsd/LangInfo;
     398: new           #4                  // class jnr/constants/platform/dragonflybsd/LangInfo
     401: dup
     402: ldc           #104                // String MON_7
     404: bipush        24
     406: ldc2_w        #105                // long 27l
     409: invokespecial #12                 // Method "<init>":(Ljava/lang/String;IJ)V
     412: putstatic     #107                // Field MON_7:Ljnr/constants/platform/dragonflybsd/LangInfo;
     415: new           #4                  // class jnr/constants/platform/dragonflybsd/LangInfo
     418: dup
     419: ldc           #108                // String MON_8
     421: bipush        25
     423: ldc2_w        #109                // long 28l
     426: invokespecial #12                 // Method "<init>":(Ljava/lang/String;IJ)V
     429: putstatic     #111                // Field MON_8:Ljnr/constants/platform/dragonflybsd/LangInfo;
     432: new           #4                  // class jnr/constants/platform/dragonflybsd/LangInfo
     435: dup
     436: ldc           #112                // String MON_9
     438: bipush        26
     440: ldc2_w        #113                // long 29l
     443: invokespecial #12                 // Method "<init>":(Ljava/lang/String;IJ)V
     446: putstatic     #115                // Field MON_9:Ljnr/constants/platform/dragonflybsd/LangInfo;
     449: new           #4                  // class jnr/constants/platform/dragonflybsd/LangInfo
     452: dup
     453: ldc           #116                // String MON_10
     455: bipush        27
     457: ldc2_w        #117                // long 30l
     460: invokespecial #12                 // Method "<init>":(Ljava/lang/String;IJ)V
     463: putstatic     #119                // Field MON_10:Ljnr/constants/platform/dragonflybsd/LangInfo;
     466: new           #4                  // class jnr/constants/platform/dragonflybsd/LangInfo
     469: dup
     470: ldc           #120                // String MON_11
     472: bipush        28
     474: ldc2_w        #121                // long 31l
     477: invokespecial #12                 // Method "<init>":(Ljava/lang/String;IJ)V
     480: putstatic     #123                // Field MON_11:Ljnr/constants/platform/dragonflybsd/LangInfo;
     483: new           #4                  // class jnr/constants/platform/dragonflybsd/LangInfo
     486: dup
     487: ldc           #124                // String MON_12
     489: bipush        29
     491: ldc2_w        #125                // long 32l
     494: invokespecial #12                 // Method "<init>":(Ljava/lang/String;IJ)V
     497: putstatic     #127                // Field MON_12:Ljnr/constants/platform/dragonflybsd/LangInfo;
     500: new           #4                  // class jnr/constants/platform/dragonflybsd/LangInfo
     503: dup
     504: ldc           #128                // String ABMON_1
     506: bipush        30
     508: ldc2_w        #129                // long 33l
     511: invokespecial #12                 // Method "<init>":(Ljava/lang/String;IJ)V
     514: putstatic     #131                // Field ABMON_1:Ljnr/constants/platform/dragonflybsd/LangInfo;
     517: new           #4                  // class jnr/constants/platform/dragonflybsd/LangInfo
     520: dup
     521: ldc           #132                // String ABMON_2
     523: bipush        31
     525: ldc2_w        #133                // long 34l
     528: invokespecial #12                 // Method "<init>":(Ljava/lang/String;IJ)V
     531: putstatic     #135                // Field ABMON_2:Ljnr/constants/platform/dragonflybsd/LangInfo;
     534: new           #4                  // class jnr/constants/platform/dragonflybsd/LangInfo
     537: dup
     538: ldc           #136                // String ABMON_3
     540: bipush        32
     542: ldc2_w        #137                // long 35l
     545: invokespecial #12                 // Method "<init>":(Ljava/lang/String;IJ)V
     548: putstatic     #139                // Field ABMON_3:Ljnr/constants/platform/dragonflybsd/LangInfo;
     551: new           #4                  // class jnr/constants/platform/dragonflybsd/LangInfo
     554: dup
     555: ldc           #140                // String ABMON_4
     557: bipush        33
     559: ldc2_w        #141                // long 36l
     562: invokespecial #12                 // Method "<init>":(Ljava/lang/String;IJ)V
     565: putstatic     #143                // Field ABMON_4:Ljnr/constants/platform/dragonflybsd/LangInfo;
     568: new           #4                  // class jnr/constants/platform/dragonflybsd/LangInfo
     571: dup
     572: ldc           #144                // String ABMON_5
     574: bipush        34
     576: ldc2_w        #145                // long 37l
     579: invokespecial #12                 // Method "<init>":(Ljava/lang/String;IJ)V
     582: putstatic     #147                // Field ABMON_5:Ljnr/constants/platform/dragonflybsd/LangInfo;
     585: new           #4                  // class jnr/constants/platform/dragonflybsd/LangInfo
     588: dup
     589: ldc           #148                // String ABMON_6
     591: bipush        35
     593: ldc2_w        #149                // long 38l
     596: invokespecial #12                 // Method "<init>":(Ljava/lang/String;IJ)V
     599: putstatic     #151                // Field ABMON_6:Ljnr/constants/platform/dragonflybsd/LangInfo;
     602: new           #4                  // class jnr/constants/platform/dragonflybsd/LangInfo
     605: dup
     606: ldc           #152                // String ABMON_7
     608: bipush        36
     610: ldc2_w        #153                // long 39l
     613: invokespecial #12                 // Method "<init>":(Ljava/lang/String;IJ)V
     616: putstatic     #155                // Field ABMON_7:Ljnr/constants/platform/dragonflybsd/LangInfo;
     619: new           #4                  // class jnr/constants/platform/dragonflybsd/LangInfo
     622: dup
     623: ldc           #156                // String ABMON_8
     625: bipush        37
     627: ldc2_w        #157                // long 40l
     630: invokespecial #12                 // Method "<init>":(Ljava/lang/String;IJ)V
     633: putstatic     #159                // Field ABMON_8:Ljnr/constants/platform/dragonflybsd/LangInfo;
     636: new           #4                  // class jnr/constants/platform/dragonflybsd/LangInfo
     639: dup
     640: ldc           #160                // String ABMON_9
     642: bipush        38
     644: ldc2_w        #161                // long 41l
     647: invokespecial #12                 // Method "<init>":(Ljava/lang/String;IJ)V
     650: putstatic     #163                // Field ABMON_9:Ljnr/constants/platform/dragonflybsd/LangInfo;
     653: new           #4                  // class jnr/constants/platform/dragonflybsd/LangInfo
     656: dup
     657: ldc           #164                // String ABMON_10
     659: bipush        39
     661: ldc2_w        #165                // long 42l
     664: invokespecial #12                 // Method "<init>":(Ljava/lang/String;IJ)V
     667: putstatic     #167                // Field ABMON_10:Ljnr/constants/platform/dragonflybsd/LangInfo;
     670: new           #4                  // class jnr/constants/platform/dragonflybsd/LangInfo
     673: dup
     674: ldc           #168                // String ABMON_11
     676: bipush        40
     678: ldc2_w        #169                // long 43l
     681: invokespecial #12                 // Method "<init>":(Ljava/lang/String;IJ)V
     684: putstatic     #171                // Field ABMON_11:Ljnr/constants/platform/dragonflybsd/LangInfo;
     687: new           #4                  // class jnr/constants/platform/dragonflybsd/LangInfo
     690: dup
     691: ldc           #172                // String ABMON_12
     693: bipush        41
     695: ldc2_w        #173                // long 44l
     698: invokespecial #12                 // Method "<init>":(Ljava/lang/String;IJ)V
     701: putstatic     #175                // Field ABMON_12:Ljnr/constants/platform/dragonflybsd/LangInfo;
     704: new           #4                  // class jnr/constants/platform/dragonflybsd/LangInfo
     707: dup
     708: ldc           #176                // String RADIXCHAR
     710: bipush        42
     712: ldc2_w        #177                // long 50l
     715: invokespecial #12                 // Method "<init>":(Ljava/lang/String;IJ)V
     718: putstatic     #179                // Field RADIXCHAR:Ljnr/constants/platform/dragonflybsd/LangInfo;
     721: new           #4                  // class jnr/constants/platform/dragonflybsd/LangInfo
     724: dup
     725: ldc           #180                // String THOUSEP
     727: bipush        43
     729: ldc2_w        #181                // long 51l
     732: invokespecial #12                 // Method "<init>":(Ljava/lang/String;IJ)V
     735: putstatic     #183                // Field THOUSEP:Ljnr/constants/platform/dragonflybsd/LangInfo;
     738: new           #4                  // class jnr/constants/platform/dragonflybsd/LangInfo
     741: dup
     742: ldc           #184                // String YESEXPR
     744: bipush        44
     746: ldc2_w        #185                // long 52l
     749: invokespecial #12                 // Method "<init>":(Ljava/lang/String;IJ)V
     752: putstatic     #187                // Field YESEXPR:Ljnr/constants/platform/dragonflybsd/LangInfo;
     755: new           #4                  // class jnr/constants/platform/dragonflybsd/LangInfo
     758: dup
     759: ldc           #188                // String NOEXPR
     761: bipush        45
     763: ldc2_w        #189                // long 53l
     766: invokespecial #12                 // Method "<init>":(Ljava/lang/String;IJ)V
     769: putstatic     #191                // Field NOEXPR:Ljnr/constants/platform/dragonflybsd/LangInfo;
     772: new           #4                  // class jnr/constants/platform/dragonflybsd/LangInfo
     775: dup
     776: ldc           #192                // String CRNCYSTR
     778: bipush        46
     780: ldc2_w        #193                // long 56l
     783: invokespecial #12                 // Method "<init>":(Ljava/lang/String;IJ)V
     786: putstatic     #195                // Field CRNCYSTR:Ljnr/constants/platform/dragonflybsd/LangInfo;
     789: bipush        47
     791: anewarray     #4                  // class jnr/constants/platform/dragonflybsd/LangInfo
     794: dup
     795: iconst_0
     796: getstatic     #13                 // Field CODESET:Ljnr/constants/platform/dragonflybsd/LangInfo;
     799: aastore
     800: dup
     801: iconst_1
     802: getstatic     #15                 // Field D_T_FMT:Ljnr/constants/platform/dragonflybsd/LangInfo;
     805: aastore
     806: dup
     807: iconst_2
     808: getstatic     #19                 // Field D_FMT:Ljnr/constants/platform/dragonflybsd/LangInfo;
     811: aastore
     812: dup
     813: iconst_3
     814: getstatic     #23                 // Field T_FMT:Ljnr/constants/platform/dragonflybsd/LangInfo;
     817: aastore
     818: dup
     819: iconst_4
     820: getstatic     #27                 // Field DAY_1:Ljnr/constants/platform/dragonflybsd/LangInfo;
     823: aastore
     824: dup
     825: iconst_5
     826: getstatic     #31                 // Field DAY_2:Ljnr/constants/platform/dragonflybsd/LangInfo;
     829: aastore
     830: dup
     831: bipush        6
     833: getstatic     #35                 // Field DAY_3:Ljnr/constants/platform/dragonflybsd/LangInfo;
     836: aastore
     837: dup
     838: bipush        7
     840: getstatic     #39                 // Field DAY_4:Ljnr/constants/platform/dragonflybsd/LangInfo;
     843: aastore
     844: dup
     845: bipush        8
     847: getstatic     #43                 // Field DAY_5:Ljnr/constants/platform/dragonflybsd/LangInfo;
     850: aastore
     851: dup
     852: bipush        9
     854: getstatic     #47                 // Field DAY_6:Ljnr/constants/platform/dragonflybsd/LangInfo;
     857: aastore
     858: dup
     859: bipush        10
     861: getstatic     #51                 // Field DAY_7:Ljnr/constants/platform/dragonflybsd/LangInfo;
     864: aastore
     865: dup
     866: bipush        11
     868: getstatic     #55                 // Field ABDAY_1:Ljnr/constants/platform/dragonflybsd/LangInfo;
     871: aastore
     872: dup
     873: bipush        12
     875: getstatic     #59                 // Field ABDAY_2:Ljnr/constants/platform/dragonflybsd/LangInfo;
     878: aastore
     879: dup
     880: bipush        13
     882: getstatic     #63                 // Field ABDAY_3:Ljnr/constants/platform/dragonflybsd/LangInfo;
     885: aastore
     886: dup
     887: bipush        14
     889: getstatic     #67                 // Field ABDAY_4:Ljnr/constants/platform/dragonflybsd/LangInfo;
     892: aastore
     893: dup
     894: bipush        15
     896: getstatic     #71                 // Field ABDAY_5:Ljnr/constants/platform/dragonflybsd/LangInfo;
     899: aastore
     900: dup
     901: bipush        16
     903: getstatic     #75                 // Field ABDAY_6:Ljnr/constants/platform/dragonflybsd/LangInfo;
     906: aastore
     907: dup
     908: bipush        17
     910: getstatic     #79                 // Field ABDAY_7:Ljnr/constants/platform/dragonflybsd/LangInfo;
     913: aastore
     914: dup
     915: bipush        18
     917: getstatic     #83                 // Field MON_1:Ljnr/constants/platform/dragonflybsd/LangInfo;
     920: aastore
     921: dup
     922: bipush        19
     924: getstatic     #87                 // Field MON_2:Ljnr/constants/platform/dragonflybsd/LangInfo;
     927: aastore
     928: dup
     929: bipush        20
     931: getstatic     #91                 // Field MON_3:Ljnr/constants/platform/dragonflybsd/LangInfo;
     934: aastore
     935: dup
     936: bipush        21
     938: getstatic     #95                 // Field MON_4:Ljnr/constants/platform/dragonflybsd/LangInfo;
     941: aastore
     942: dup
     943: bipush        22
     945: getstatic     #99                 // Field MON_5:Ljnr/constants/platform/dragonflybsd/LangInfo;
     948: aastore
     949: dup
     950: bipush        23
     952: getstatic     #103                // Field MON_6:Ljnr/constants/platform/dragonflybsd/LangInfo;
     955: aastore
     956: dup
     957: bipush        24
     959: getstatic     #107                // Field MON_7:Ljnr/constants/platform/dragonflybsd/LangInfo;
     962: aastore
     963: dup
     964: bipush        25
     966: getstatic     #111                // Field MON_8:Ljnr/constants/platform/dragonflybsd/LangInfo;
     969: aastore
     970: dup
     971: bipush        26
     973: getstatic     #115                // Field MON_9:Ljnr/constants/platform/dragonflybsd/LangInfo;
     976: aastore
     977: dup
     978: bipush        27
     980: getstatic     #119                // Field MON_10:Ljnr/constants/platform/dragonflybsd/LangInfo;
     983: aastore
     984: dup
     985: bipush        28
     987: getstatic     #123                // Field MON_11:Ljnr/constants/platform/dragonflybsd/LangInfo;
     990: aastore
     991: dup
     992: bipush        29
     994: getstatic     #127                // Field MON_12:Ljnr/constants/platform/dragonflybsd/LangInfo;
     997: aastore
     998: dup
     999: bipush        30
    1001: getstatic     #131                // Field ABMON_1:Ljnr/constants/platform/dragonflybsd/LangInfo;
    1004: aastore
    1005: dup
    1006: bipush        31
    1008: getstatic     #135                // Field ABMON_2:Ljnr/constants/platform/dragonflybsd/LangInfo;
    1011: aastore
    1012: dup
    1013: bipush        32
    1015: getstatic     #139                // Field ABMON_3:Ljnr/constants/platform/dragonflybsd/LangInfo;
    1018: aastore
    1019: dup
    1020: bipush        33
    1022: getstatic     #143                // Field ABMON_4:Ljnr/constants/platform/dragonflybsd/LangInfo;
    1025: aastore
    1026: dup
    1027: bipush        34
    1029: getstatic     #147                // Field ABMON_5:Ljnr/constants/platform/dragonflybsd/LangInfo;
    1032: aastore
    1033: dup
    1034: bipush        35
    1036: getstatic     #151                // Field ABMON_6:Ljnr/constants/platform/dragonflybsd/LangInfo;
    1039: aastore
    1040: dup
    1041: bipush        36
    1043: getstatic     #155                // Field ABMON_7:Ljnr/constants/platform/dragonflybsd/LangInfo;
    1046: aastore
    1047: dup
    1048: bipush        37
    1050: getstatic     #159                // Field ABMON_8:Ljnr/constants/platform/dragonflybsd/LangInfo;
    1053: aastore
    1054: dup
    1055: bipush        38
    1057: getstatic     #163                // Field ABMON_9:Ljnr/constants/platform/dragonflybsd/LangInfo;
    1060: aastore
    1061: dup
    1062: bipush        39
    1064: getstatic     #167                // Field ABMON_10:Ljnr/constants/platform/dragonflybsd/LangInfo;
    1067: aastore
    1068: dup
    1069: bipush        40
    1071: getstatic     #171                // Field ABMON_11:Ljnr/constants/platform/dragonflybsd/LangInfo;
    1074: aastore
    1075: dup
    1076: bipush        41
    1078: getstatic     #175                // Field ABMON_12:Ljnr/constants/platform/dragonflybsd/LangInfo;
    1081: aastore
    1082: dup
    1083: bipush        42
    1085: getstatic     #179                // Field RADIXCHAR:Ljnr/constants/platform/dragonflybsd/LangInfo;
    1088: aastore
    1089: dup
    1090: bipush        43
    1092: getstatic     #183                // Field THOUSEP:Ljnr/constants/platform/dragonflybsd/LangInfo;
    1095: aastore
    1096: dup
    1097: bipush        44
    1099: getstatic     #187                // Field YESEXPR:Ljnr/constants/platform/dragonflybsd/LangInfo;
    1102: aastore
    1103: dup
    1104: bipush        45
    1106: getstatic     #191                // Field NOEXPR:Ljnr/constants/platform/dragonflybsd/LangInfo;
    1109: aastore
    1110: dup
    1111: bipush        46
    1113: getstatic     #195                // Field CRNCYSTR:Ljnr/constants/platform/dragonflybsd/LangInfo;
    1116: aastore
    1117: putstatic     #1                  // Field $VALUES:[Ljnr/constants/platform/dragonflybsd/LangInfo;
    1120: return
}
