Compiled from "Base64.java"
public class ru.tinkoff.acquiring.sdk.utils.Base64 {
  public static final int DEFAULT;

  public static final int NO_PADDING;

  public static final int NO_WRAP;

  public static final int CRLF;

  public static final int URL_SAFE;

  public static final int NO_CLOSE;

  static final boolean $assertionsDisabled;

  public static byte[] decode(java.lang.String, int);
    Code:
       0: aload_0
       1: invokevirtual #1                  // Method java/lang/String.getBytes:()[B
       4: iload_1
       5: invokestatic  #2                  // Method decode:([BI)[B
       8: areturn

  public static byte[] decode(byte[], int);
    Code:
       0: aload_0
       1: iconst_0
       2: aload_0
       3: arraylength
       4: iload_1
       5: invokestatic  #3                  // Method decode:([BIII)[B
       8: areturn

  public static byte[] decode(byte[], int, int, int);
    Code:
       0: new           #4                  // class ru/tinkoff/acquiring/sdk/utils/Base64$Decoder
       3: dup
       4: iload_3
       5: iload_2
       6: iconst_3
       7: imul
       8: iconst_4
       9: idiv
      10: newarray       byte
      12: invokespecial #5                  // Method ru/tinkoff/acquiring/sdk/utils/Base64$Decoder."<init>":(I[B)V
      15: astore        4
      17: aload         4
      19: aload_0
      20: iload_1
      21: iload_2
      22: iconst_1
      23: invokevirtual #6                  // Method ru/tinkoff/acquiring/sdk/utils/Base64$Decoder.process:([BIIZ)Z
      26: ifne          39
      29: new           #7                  // class java/lang/IllegalArgumentException
      32: dup
      33: ldc           #8                  // String bad base-64
      35: invokespecial #9                  // Method java/lang/IllegalArgumentException."<init>":(Ljava/lang/String;)V
      38: athrow
      39: aload         4
      41: getfield      #10                 // Field ru/tinkoff/acquiring/sdk/utils/Base64$Decoder.op:I
      44: aload         4
      46: getfield      #11                 // Field ru/tinkoff/acquiring/sdk/utils/Base64$Decoder.output:[B
      49: arraylength
      50: if_icmpne     59
      53: aload         4
      55: getfield      #11                 // Field ru/tinkoff/acquiring/sdk/utils/Base64$Decoder.output:[B
      58: areturn
      59: aload         4
      61: getfield      #10                 // Field ru/tinkoff/acquiring/sdk/utils/Base64$Decoder.op:I
      64: newarray       byte
      66: astore        5
      68: aload         4
      70: getfield      #11                 // Field ru/tinkoff/acquiring/sdk/utils/Base64$Decoder.output:[B
      73: iconst_0
      74: aload         5
      76: iconst_0
      77: aload         4
      79: getfield      #10                 // Field ru/tinkoff/acquiring/sdk/utils/Base64$Decoder.op:I
      82: invokestatic  #12                 // Method java/lang/System.arraycopy:(Ljava/lang/Object;ILjava/lang/Object;II)V
      85: aload         5
      87: areturn

  public static java.lang.String encodeToString(byte[], int);
    Code:
       0: new           #13                 // class java/lang/String
       3: dup
       4: aload_0
       5: iload_1
       6: invokestatic  #14                 // Method encode:([BI)[B
       9: ldc           #15                 // String US-ASCII
      11: invokespecial #16                 // Method java/lang/String."<init>":([BLjava/lang/String;)V
      14: areturn
      15: astore_2
      16: new           #18                 // class java/lang/AssertionError
      19: dup
      20: aload_2
      21: invokespecial #19                 // Method java/lang/AssertionError."<init>":(Ljava/lang/Object;)V
      24: athrow
    Exception table:
       from    to  target type
           0    14    15   Class java/io/UnsupportedEncodingException

  public static java.lang.String encodeToString(byte[], int, int, int);
    Code:
       0: new           #13                 // class java/lang/String
       3: dup
       4: aload_0
       5: iload_1
       6: iload_2
       7: iload_3
       8: invokestatic  #20                 // Method encode:([BIII)[B
      11: ldc           #15                 // String US-ASCII
      13: invokespecial #16                 // Method java/lang/String."<init>":([BLjava/lang/String;)V
      16: areturn
      17: astore        4
      19: new           #18                 // class java/lang/AssertionError
      22: dup
      23: aload         4
      25: invokespecial #19                 // Method java/lang/AssertionError."<init>":(Ljava/lang/Object;)V
      28: athrow
    Exception table:
       from    to  target type
           0    16    17   Class java/io/UnsupportedEncodingException

  public static byte[] encode(byte[], int);
    Code:
       0: aload_0
       1: iconst_0
       2: aload_0
       3: arraylength
       4: iload_1
       5: invokestatic  #20                 // Method encode:([BIII)[B
       8: areturn

  public static byte[] encode(byte[], int, int, int);
    Code:
       0: new           #21                 // class ru/tinkoff/acquiring/sdk/utils/Base64$Encoder
       3: dup
       4: iload_3
       5: aconst_null
       6: invokespecial #22                 // Method ru/tinkoff/acquiring/sdk/utils/Base64$Encoder."<init>":(I[B)V
       9: astore        4
      11: iload_2
      12: iconst_3
      13: idiv
      14: iconst_4
      15: imul
      16: istore        5
      18: aload         4
      20: getfield      #23                 // Field ru/tinkoff/acquiring/sdk/utils/Base64$Encoder.do_padding:Z
      23: ifeq          38
      26: iload_2
      27: iconst_3
      28: irem
      29: ifle          80
      32: iinc          5, 4
      35: goto          80
      38: iload_2
      39: iconst_3
      40: irem
      41: tableswitch   { // 0 to 2
                     0: 68
                     1: 71
                     2: 77
               default: 80
          }
      68: goto          80
      71: iinc          5, 2
      74: goto          80
      77: iinc          5, 3
      80: aload         4
      82: getfield      #24                 // Field ru/tinkoff/acquiring/sdk/utils/Base64$Encoder.do_newline:Z
      85: ifeq          119
      88: iload_2
      89: ifle          119
      92: iload         5
      94: iload_2
      95: iconst_1
      96: isub
      97: bipush        57
      99: idiv
     100: iconst_1
     101: iadd
     102: aload         4
     104: getfield      #25                 // Field ru/tinkoff/acquiring/sdk/utils/Base64$Encoder.do_cr:Z
     107: ifeq          114
     110: iconst_2
     111: goto          115
     114: iconst_1
     115: imul
     116: iadd
     117: istore        5
     119: aload         4
     121: iload         5
     123: newarray       byte
     125: putfield      #26                 // Field ru/tinkoff/acquiring/sdk/utils/Base64$Encoder.output:[B
     128: aload         4
     130: aload_0
     131: iload_1
     132: iload_2
     133: iconst_1
     134: invokevirtual #27                 // Method ru/tinkoff/acquiring/sdk/utils/Base64$Encoder.process:([BIIZ)Z
     137: pop
     138: getstatic     #28                 // Field $assertionsDisabled:Z
     141: ifne          162
     144: aload         4
     146: getfield      #29                 // Field ru/tinkoff/acquiring/sdk/utils/Base64$Encoder.op:I
     149: iload         5
     151: if_icmpeq     162
     154: new           #18                 // class java/lang/AssertionError
     157: dup
     158: invokespecial #30                 // Method java/lang/AssertionError."<init>":()V
     161: athrow
     162: aload         4
     164: getfield      #26                 // Field ru/tinkoff/acquiring/sdk/utils/Base64$Encoder.output:[B
     167: areturn

  private ru.tinkoff.acquiring.sdk.utils.Base64();
    Code:
       0: aload_0
       1: invokespecial #31                 // Method java/lang/Object."<init>":()V
       4: return

  static {};
    Code:
       0: ldc           #32                 // class ru/tinkoff/acquiring/sdk/utils/Base64
       2: invokevirtual #33                 // Method java/lang/Class.desiredAssertionStatus:()Z
       5: ifne          12
       8: iconst_1
       9: goto          13
      12: iconst_0
      13: putstatic     #28                 // Field $assertionsDisabled:Z
      16: return
}
