Compiled from "SecurityContextServerWebExchange.java"
public class org.springframework.security.web.server.context.SecurityContextServerWebExchange extends org.springframework.web.server.ServerWebExchangeDecorator {
  private final reactor.core.publisher.Mono<org.springframework.security.core.context.SecurityContext> context;

  public org.springframework.security.web.server.context.SecurityContextServerWebExchange(org.springframework.web.server.ServerWebExchange, reactor.core.publisher.Mono<org.springframework.security.core.context.SecurityContext>);
    Code:
       0: aload_0
       1: aload_1
       2: invokespecial #1                  // Method org/springframework/web/server/ServerWebExchangeDecorator."<init>":(Lorg/springframework/web/server/ServerWebExchange;)V
       5: aload_0
       6: aload_2
       7: putfield      #2                  // Field context:Lreactor/core/publisher/Mono;
      10: return

  public <T extends java.security.Principal> reactor.core.publisher.Mono<T> getPrincipal();
    Code:
       0: aload_0
       1: getfield      #2                  // Field context:Lreactor/core/publisher/Mono;
       4: invokedynamic #3,  0              // InvokeDynamic #0:apply:()Ljava/util/function/Function;
       9: invokevirtual #4                  // Method reactor/core/publisher/Mono.map:(Ljava/util/function/Function;)Lreactor/core/publisher/Mono;
      12: areturn

  private static java.security.Principal lambda$getPrincipal$0(org.springframework.security.core.context.SecurityContext);
    Code:
       0: aload_0
       1: invokeinterface #5,  1            // InterfaceMethod org/springframework/security/core/context/SecurityContext.getAuthentication:()Lorg/springframework/security/core/Authentication;
       6: areturn
}
