Compiled from "RuleSource.java"
public abstract class org.graylog.plugins.pipelineprocessor.rest.RuleSource {
  public org.graylog.plugins.pipelineprocessor.rest.RuleSource();
    Code:
       0: aload_0
       1: invokespecial #1                  // Method java/lang/Object."<init>":()V
       4: return

  public abstract java.lang.String id();

  public abstract java.lang.String title();

  public abstract java.lang.String description();

  public abstract java.lang.String source();

  public abstract org.joda.time.DateTime createdAt();

  public abstract org.joda.time.DateTime modifiedAt();

  public abstract java.util.Set<org.graylog.plugins.pipelineprocessor.parser.errors.ParseError> errors();

  public static org.graylog.plugins.pipelineprocessor.rest.RuleSource$Builder builder();
    Code:
       0: new           #2                  // class org/graylog/plugins/pipelineprocessor/rest/AutoValue_RuleSource$Builder
       3: dup
       4: invokespecial #3                  // Method org/graylog/plugins/pipelineprocessor/rest/AutoValue_RuleSource$Builder."<init>":()V
       7: areturn

  public abstract org.graylog.plugins.pipelineprocessor.rest.RuleSource$Builder toBuilder();

  public static org.graylog.plugins.pipelineprocessor.rest.RuleSource create(java.lang.String, java.lang.String, java.lang.String, java.lang.String, org.joda.time.DateTime, org.joda.time.DateTime);
    Code:
       0: invokestatic  #4                  // Method builder:()Lorg/graylog/plugins/pipelineprocessor/rest/RuleSource$Builder;
       3: aload_0
       4: invokevirtual #5                  // Method org/graylog/plugins/pipelineprocessor/rest/RuleSource$Builder.id:(Ljava/lang/String;)Lorg/graylog/plugins/pipelineprocessor/rest/RuleSource$Builder;
       7: aload_3
       8: invokevirtual #6                  // Method org/graylog/plugins/pipelineprocessor/rest/RuleSource$Builder.source:(Ljava/lang/String;)Lorg/graylog/plugins/pipelineprocessor/rest/RuleSource$Builder;
      11: aload_1
      12: invokevirtual #7                  // Method org/graylog/plugins/pipelineprocessor/rest/RuleSource$Builder.title:(Ljava/lang/String;)Lorg/graylog/plugins/pipelineprocessor/rest/RuleSource$Builder;
      15: aload_2
      16: invokevirtual #8                  // Method org/graylog/plugins/pipelineprocessor/rest/RuleSource$Builder.description:(Ljava/lang/String;)Lorg/graylog/plugins/pipelineprocessor/rest/RuleSource$Builder;
      19: aload         4
      21: invokevirtual #9                  // Method org/graylog/plugins/pipelineprocessor/rest/RuleSource$Builder.createdAt:(Lorg/joda/time/DateTime;)Lorg/graylog/plugins/pipelineprocessor/rest/RuleSource$Builder;
      24: aload         5
      26: invokevirtual #10                 // Method org/graylog/plugins/pipelineprocessor/rest/RuleSource$Builder.modifiedAt:(Lorg/joda/time/DateTime;)Lorg/graylog/plugins/pipelineprocessor/rest/RuleSource$Builder;
      29: invokevirtual #11                 // Method org/graylog/plugins/pipelineprocessor/rest/RuleSource$Builder.build:()Lorg/graylog/plugins/pipelineprocessor/rest/RuleSource;
      32: areturn

  public static org.graylog.plugins.pipelineprocessor.rest.RuleSource fromDao(org.graylog.plugins.pipelineprocessor.parser.PipelineRuleParser, org.graylog.plugins.pipelineprocessor.db.RuleDao);
    Code:
       0: aconst_null
       1: astore_2
       2: aload_0
       3: aload_1
       4: invokevirtual #12                 // Method org/graylog/plugins/pipelineprocessor/db/RuleDao.id:()Ljava/lang/String;
       7: aload_1
       8: invokevirtual #13                 // Method org/graylog/plugins/pipelineprocessor/db/RuleDao.source:()Ljava/lang/String;
      11: iconst_0
      12: invokevirtual #14                 // Method org/graylog/plugins/pipelineprocessor/parser/PipelineRuleParser.parseRule:(Ljava/lang/String;Ljava/lang/String;Z)Lorg/graylog/plugins/pipelineprocessor/ast/Rule;
      15: pop
      16: goto          25
      19: astore_3
      20: aload_3
      21: invokevirtual #16                 // Method org/graylog/plugins/pipelineprocessor/parser/ParseException.getErrors:()Ljava/util/Set;
      24: astore_2
      25: invokestatic  #4                  // Method builder:()Lorg/graylog/plugins/pipelineprocessor/rest/RuleSource$Builder;
      28: aload_1
      29: invokevirtual #12                 // Method org/graylog/plugins/pipelineprocessor/db/RuleDao.id:()Ljava/lang/String;
      32: invokevirtual #5                  // Method org/graylog/plugins/pipelineprocessor/rest/RuleSource$Builder.id:(Ljava/lang/String;)Lorg/graylog/plugins/pipelineprocessor/rest/RuleSource$Builder;
      35: aload_1
      36: invokevirtual #13                 // Method org/graylog/plugins/pipelineprocessor/db/RuleDao.source:()Ljava/lang/String;
      39: invokevirtual #6                  // Method org/graylog/plugins/pipelineprocessor/rest/RuleSource$Builder.source:(Ljava/lang/String;)Lorg/graylog/plugins/pipelineprocessor/rest/RuleSource$Builder;
      42: aload_1
      43: invokevirtual #17                 // Method org/graylog/plugins/pipelineprocessor/db/RuleDao.title:()Ljava/lang/String;
      46: invokevirtual #7                  // Method org/graylog/plugins/pipelineprocessor/rest/RuleSource$Builder.title:(Ljava/lang/String;)Lorg/graylog/plugins/pipelineprocessor/rest/RuleSource$Builder;
      49: aload_1
      50: invokevirtual #18                 // Method org/graylog/plugins/pipelineprocessor/db/RuleDao.description:()Ljava/lang/String;
      53: invokevirtual #8                  // Method org/graylog/plugins/pipelineprocessor/rest/RuleSource$Builder.description:(Ljava/lang/String;)Lorg/graylog/plugins/pipelineprocessor/rest/RuleSource$Builder;
      56: aload_1
      57: invokevirtual #19                 // Method org/graylog/plugins/pipelineprocessor/db/RuleDao.createdAt:()Lorg/joda/time/DateTime;
      60: invokevirtual #9                  // Method org/graylog/plugins/pipelineprocessor/rest/RuleSource$Builder.createdAt:(Lorg/joda/time/DateTime;)Lorg/graylog/plugins/pipelineprocessor/rest/RuleSource$Builder;
      63: aload_1
      64: invokevirtual #20                 // Method org/graylog/plugins/pipelineprocessor/db/RuleDao.modifiedAt:()Lorg/joda/time/DateTime;
      67: invokevirtual #10                 // Method org/graylog/plugins/pipelineprocessor/rest/RuleSource$Builder.modifiedAt:(Lorg/joda/time/DateTime;)Lorg/graylog/plugins/pipelineprocessor/rest/RuleSource$Builder;
      70: aload_2
      71: invokevirtual #21                 // Method org/graylog/plugins/pipelineprocessor/rest/RuleSource$Builder.errors:(Ljava/util/Set;)Lorg/graylog/plugins/pipelineprocessor/rest/RuleSource$Builder;
      74: invokevirtual #11                 // Method org/graylog/plugins/pipelineprocessor/rest/RuleSource$Builder.build:()Lorg/graylog/plugins/pipelineprocessor/rest/RuleSource;
      77: areturn
    Exception table:
       from    to  target type
           2    16    19   Class org/graylog/plugins/pipelineprocessor/parser/ParseException
}
