Compiled from "MClassSerializer.java"
public class com.cloudera.nav.sdk.client.writer.serde.MClassSerializer<T> extends com.fasterxml.jackson.databind.ser.std.StdSerializer<T> {
  private final com.cloudera.nav.sdk.client.writer.registry.MClassRegistry registry;

  public com.cloudera.nav.sdk.client.writer.serde.MClassSerializer(java.lang.Class<T>, com.cloudera.nav.sdk.client.writer.registry.MClassRegistry);
    Code:
       0: aload_0
       1: aload_1
       2: invokespecial #1                  // Method com/fasterxml/jackson/databind/ser/std/StdSerializer."<init>":(Ljava/lang/Class;)V
       5: aload_0
       6: aload_2
       7: putfield      #2                  // Field registry:Lcom/cloudera/nav/sdk/client/writer/registry/MClassRegistry;
      10: return

  public void serialize(T, com.fasterxml.jackson.core.JsonGenerator, com.fasterxml.jackson.databind.SerializerProvider) throws java.io.IOException;
    Code:
       0: aload_2
       1: invokevirtual #3                  // Method com/fasterxml/jackson/core/JsonGenerator.writeStartObject:()V
       4: aload_0
       5: aload_1
       6: aload_2
       7: invokevirtual #4                  // Method writeProperties:(Ljava/lang/Object;Lcom/fasterxml/jackson/core/JsonGenerator;)V
      10: aload_2
      11: invokevirtual #5                  // Method com/fasterxml/jackson/core/JsonGenerator.writeEndObject:()V
      14: return

  protected void writeProperties(T, com.fasterxml.jackson.core.JsonGenerator) throws java.io.IOException;
    Code:
       0: aload_0
       1: getfield      #2                  // Field registry:Lcom/cloudera/nav/sdk/client/writer/registry/MClassRegistry;
       4: aload_1
       5: invokevirtual #6                  // Method java/lang/Object.getClass:()Ljava/lang/Class;
       8: invokevirtual #7                  // Method com/cloudera/nav/sdk/client/writer/registry/MClassRegistry.getProperties:(Ljava/lang/Class;)Ljava/util/Collection;
      11: invokeinterface #8,  1            // InterfaceMethod java/util/Collection.iterator:()Ljava/util/Iterator;
      16: astore_3
      17: aload_3
      18: invokeinterface #9,  1            // InterfaceMethod java/util/Iterator.hasNext:()Z
      23: ifeq          55
      26: aload_3
      27: invokeinterface #10,  1           // InterfaceMethod java/util/Iterator.next:()Ljava/lang/Object;
      32: checkcast     #11                 // class com/cloudera/nav/sdk/client/writer/registry/MPropertyEntry
      35: astore        4
      37: aload_2
      38: aload         4
      40: invokevirtual #12                 // Method com/cloudera/nav/sdk/client/writer/registry/MPropertyEntry.getAttribute:()Ljava/lang/String;
      43: aload         4
      45: aload_1
      46: invokevirtual #13                 // Method com/cloudera/nav/sdk/client/writer/registry/MPropertyEntry.getValue:(Ljava/lang/Object;)Ljava/lang/Object;
      49: invokevirtual #14                 // Method com/fasterxml/jackson/core/JsonGenerator.writeObjectField:(Ljava/lang/String;Ljava/lang/Object;)V
      52: goto          17
      55: return
}
