Compiled from "OSLabeler.java"
public class hudson.tasks.labelers.OSLabeler extends hudson.tasks.DynamicLabeler {
  public static hudson.tasks.labelers.OSLabeler INSTANCE;

  private hudson.tasks.labelers.OSLabeler();
    Code:
       0: aload_0
       1: invokespecial #1                  // Method hudson/tasks/DynamicLabeler."<init>":()V
       4: return

  public java.util.Set<java.lang.String> findLabels(hudson.remoting.VirtualChannel);
    Code:
       0: aload_1
       1: new           #2                  // class hudson/tasks/labelers/OSLabeler$OSLabelFinder
       4: dup
       5: aconst_null
       6: invokespecial #3                  // Method hudson/tasks/labelers/OSLabeler$OSLabelFinder."<init>":(Lhudson/tasks/labelers/OSLabeler$1;)V
       9: invokeinterface #4,  2            // InterfaceMethod hudson/remoting/VirtualChannel.call:(Lhudson/remoting/Callable;)Ljava/lang/Object;
      14: checkcast     #5                  // class java/util/Set
      17: areturn
      18: astore_2
      19: invokestatic  #7                  // Method java/util/Collections.emptySet:()Ljava/util/Set;
      22: areturn
    Exception table:
       from    to  target type
           0    17    18   Class java/lang/Exception

  static {};
    Code:
       0: new           #8                  // class hudson/tasks/labelers/OSLabeler
       3: dup
       4: invokespecial #9                  // Method "<init>":()V
       7: putstatic     #10                 // Field INSTANCE:Lhudson/tasks/labelers/OSLabeler;
      10: return
}
