Compiled from "Function.java"
public interface org.graylog.plugins.pipelineprocessor.ast.functions.Function<T> {
  public static final org.slf4j.Logger log;

  public static final org.graylog.plugins.pipelineprocessor.ast.functions.Function ERROR_FUNCTION;

  public default void preprocessArgs(org.graylog.plugins.pipelineprocessor.ast.functions.FunctionArgs);
    Code:
       0: aload_1
       1: invokevirtual #1                  // Method org/graylog/plugins/pipelineprocessor/ast/functions/FunctionArgs.getConstantArgs:()Ljava/util/Map;
       4: invokeinterface #2,  1            // InterfaceMethod java/util/Map.entrySet:()Ljava/util/Set;
       9: invokeinterface #3,  1            // InterfaceMethod java/util/Set.iterator:()Ljava/util/Iterator;
      14: astore_2
      15: aload_2
      16: invokeinterface #4,  1            // InterfaceMethod java/util/Iterator.hasNext:()Z
      21: ifeq          184
      24: aload_2
      25: invokeinterface #5,  1            // InterfaceMethod java/util/Iterator.next:()Ljava/lang/Object;
      30: checkcast     #6                  // class java/util/Map$Entry
      33: astore_3
      34: aload_3
      35: invokeinterface #7,  1            // InterfaceMethod java/util/Map$Entry.getKey:()Ljava/lang/Object;
      40: checkcast     #8                  // class java/lang/String
      43: astore        4
      45: aload_0
      46: aload_1
      47: aload         4
      49: aload_3
      50: invokeinterface #9,  1            // InterfaceMethod java/util/Map$Entry.getValue:()Ljava/lang/Object;
      55: checkcast     #10                 // class org/graylog/plugins/pipelineprocessor/ast/expressions/Expression
      58: invokeinterface #11,  4           // InterfaceMethod preComputeConstantArgument:(Lorg/graylog/plugins/pipelineprocessor/ast/functions/FunctionArgs;Ljava/lang/String;Lorg/graylog/plugins/pipelineprocessor/ast/expressions/Expression;)Ljava/lang/Object;
      63: astore        5
      65: aload         5
      67: ifnull        134
      70: aload_1
      71: aload         4
      73: invokevirtual #12                 // Method org/graylog/plugins/pipelineprocessor/ast/functions/FunctionArgs.param:(Ljava/lang/String;)Lorg/graylog/plugins/pipelineprocessor/ast/functions/ParameterDescriptor;
      76: astore        6
      78: aload         6
      80: ifnonnull     116
      83: new           #13                 // class java/lang/IllegalStateException
      86: dup
      87: new           #14                 // class java/lang/StringBuilder
      90: dup
      91: invokespecial #15                 // Method java/lang/StringBuilder."<init>":()V
      94: ldc           #16                 // String Unknown parameter
      96: invokevirtual #17                 // Method java/lang/StringBuilder.append:(Ljava/lang/String;)Ljava/lang/StringBuilder;
      99: aload         4
     101: invokevirtual #17                 // Method java/lang/StringBuilder.append:(Ljava/lang/String;)Ljava/lang/StringBuilder;
     104: ldc           #18                 // String ! Cannot continue.
     106: invokevirtual #17                 // Method java/lang/StringBuilder.append:(Ljava/lang/String;)Ljava/lang/StringBuilder;
     109: invokevirtual #19                 // Method java/lang/StringBuilder.toString:()Ljava/lang/String;
     112: invokespecial #20                 // Method java/lang/IllegalStateException."<init>":(Ljava/lang/String;)V
     115: athrow
     116: aload_1
     117: aload         4
     119: aload         6
     121: invokevirtual #21                 // Method org/graylog/plugins/pipelineprocessor/ast/functions/ParameterDescriptor.transform:()Ljava/util/function/Function;
     124: aload         5
     126: invokeinterface #22,  2           // InterfaceMethod java/util/function/Function.apply:(Ljava/lang/Object;)Ljava/lang/Object;
     131: invokevirtual #23                 // Method org/graylog/plugins/pipelineprocessor/ast/functions/FunctionArgs.setPreComputedValue:(Ljava/lang/String;Ljava/lang/Object;)V
     134: goto          181
     137: astore        5
     139: getstatic     #25                 // Field log:Lorg/slf4j/Logger;
     142: new           #14                 // class java/lang/StringBuilder
     145: dup
     146: invokespecial #15                 // Method java/lang/StringBuilder."<init>":()V
     149: ldc           #26                 // String Unable to precompute argument value for
     151: invokevirtual #17                 // Method java/lang/StringBuilder.append:(Ljava/lang/String;)Ljava/lang/StringBuilder;
     154: aload         4
     156: invokevirtual #17                 // Method java/lang/StringBuilder.append:(Ljava/lang/String;)Ljava/lang/StringBuilder;
     159: invokevirtual #19                 // Method java/lang/StringBuilder.toString:()Ljava/lang/String;
     162: aload         5
     164: invokeinterface #27,  3           // InterfaceMethod org/slf4j/Logger.debug:(Ljava/lang/String;Ljava/lang/Throwable;)V
     169: new           #28                 // class org/graylog/plugins/pipelineprocessor/ast/exceptions/PrecomputeFailure
     172: dup
     173: aload         4
     175: aload         5
     177: invokespecial #29                 // Method org/graylog/plugins/pipelineprocessor/ast/exceptions/PrecomputeFailure."<init>":(Ljava/lang/String;Ljava/lang/Exception;)V
     180: athrow
     181: goto          15
     184: return
    Exception table:
       from    to  target type
          45   134   137   Class java/lang/Exception

  public abstract java.lang.Object preComputeConstantArgument(org.graylog.plugins.pipelineprocessor.ast.functions.FunctionArgs, java.lang.String, org.graylog.plugins.pipelineprocessor.ast.expressions.Expression);

  public abstract T evaluate(org.graylog.plugins.pipelineprocessor.ast.functions.FunctionArgs, org.graylog.plugins.pipelineprocessor.EvaluationContext);

  public abstract org.graylog.plugins.pipelineprocessor.ast.functions.FunctionDescriptor<T> descriptor();

  static {};
    Code:
       0: ldc           #30                 // class org/graylog/plugins/pipelineprocessor/ast/functions/Function
       2: invokestatic  #31                 // Method org/slf4j/LoggerFactory.getLogger:(Ljava/lang/Class;)Lorg/slf4j/Logger;
       5: putstatic     #25                 // Field log:Lorg/slf4j/Logger;
       8: new           #32                 // class org/graylog/plugins/pipelineprocessor/ast/functions/Function$1
      11: dup
      12: invokespecial #33                 // Method org/graylog/plugins/pipelineprocessor/ast/functions/Function$1."<init>":()V
      15: putstatic     #34                 // Field ERROR_FUNCTION:Lorg/graylog/plugins/pipelineprocessor/ast/functions/Function;
      18: return
}
