Compiled from "SimpleTextOutputStream.java"
public class org.apache.pulsar.common.util.SimpleTextOutputStream {
  private final io.netty.buffer.ByteBuf buffer;

  private static final char[] hexChars;

  public org.apache.pulsar.common.util.SimpleTextOutputStream(io.netty.buffer.ByteBuf);
    Code:
       0: aload_0
       1: invokespecial #1                  // Method java/lang/Object."<init>":()V
       4: aload_0
       5: aload_1
       6: putfield      #2                  // Field buffer:Lio/netty/buffer/ByteBuf;
       9: return

  public org.apache.pulsar.common.util.SimpleTextOutputStream write(byte[]);
    Code:
       0: aload_0
       1: getfield      #2                  // Field buffer:Lio/netty/buffer/ByteBuf;
       4: aload_1
       5: iconst_0
       6: aload_1
       7: arraylength
       8: invokevirtual #3                  // Method io/netty/buffer/ByteBuf.writeBytes:([BII)Lio/netty/buffer/ByteBuf;
      11: pop
      12: aload_0
      13: areturn

  public org.apache.pulsar.common.util.SimpleTextOutputStream write(byte[], int, int);
    Code:
       0: aload_0
       1: getfield      #2                  // Field buffer:Lio/netty/buffer/ByteBuf;
       4: aload_1
       5: iload_2
       6: iload_3
       7: invokevirtual #3                  // Method io/netty/buffer/ByteBuf.writeBytes:([BII)Lio/netty/buffer/ByteBuf;
      10: pop
      11: aload_0
      12: areturn

  public org.apache.pulsar.common.util.SimpleTextOutputStream write(char);
    Code:
       0: aload_0
       1: getfield      #2                  // Field buffer:Lio/netty/buffer/ByteBuf;
       4: iload_1
       5: i2b
       6: invokevirtual #4                  // Method io/netty/buffer/ByteBuf.writeByte:(I)Lio/netty/buffer/ByteBuf;
       9: pop
      10: aload_0
      11: areturn

  public org.apache.pulsar.common.util.SimpleTextOutputStream write(java.lang.String);
    Code:
       0: aload_1
       1: ifnonnull     6
       4: aload_0
       5: areturn
       6: aload_1
       7: invokevirtual #5                  // Method java/lang/String.length:()I
      10: istore_2
      11: iconst_0
      12: istore_3
      13: iload_3
      14: iload_2
      15: if_icmpge     38
      18: aload_0
      19: getfield      #2                  // Field buffer:Lio/netty/buffer/ByteBuf;
      22: aload_1
      23: iload_3
      24: invokevirtual #6                  // Method java/lang/String.charAt:(I)C
      27: i2b
      28: invokevirtual #4                  // Method io/netty/buffer/ByteBuf.writeByte:(I)Lio/netty/buffer/ByteBuf;
      31: pop
      32: iinc          3, 1
      35: goto          13
      38: aload_0
      39: areturn

  public org.apache.pulsar.common.util.SimpleTextOutputStream write(java.lang.Number);
    Code:
       0: aload_1
       1: instanceof    #7                  // class java/lang/Integer
       4: ifeq          17
       7: aload_0
       8: aload_1
       9: invokevirtual #8                  // Method java/lang/Number.intValue:()I
      12: i2l
      13: invokevirtual #9                  // Method write:(J)Lorg/apache/pulsar/common/util/SimpleTextOutputStream;
      16: areturn
      17: aload_1
      18: instanceof    #10                 // class java/lang/Long
      21: ifeq          33
      24: aload_0
      25: aload_1
      26: invokevirtual #11                 // Method java/lang/Number.longValue:()J
      29: invokevirtual #9                  // Method write:(J)Lorg/apache/pulsar/common/util/SimpleTextOutputStream;
      32: areturn
      33: aload_1
      34: instanceof    #12                 // class java/lang/Double
      37: ifeq          49
      40: aload_0
      41: aload_1
      42: invokevirtual #13                 // Method java/lang/Number.doubleValue:()D
      45: invokevirtual #14                 // Method write:(D)Lorg/apache/pulsar/common/util/SimpleTextOutputStream;
      48: areturn
      49: aload_0
      50: aload_1
      51: invokevirtual #15                 // Method java/lang/Object.toString:()Ljava/lang/String;
      54: invokevirtual #16                 // Method write:(Ljava/lang/String;)Lorg/apache/pulsar/common/util/SimpleTextOutputStream;
      57: areturn

  public org.apache.pulsar.common.util.SimpleTextOutputStream writeEncoded(java.lang.String);
    Code:
       0: aload_1
       1: ifnonnull     6
       4: aload_0
       5: areturn
       6: aload_1
       7: invokevirtual #5                  // Method java/lang/String.length:()I
      10: istore_2
      11: iconst_0
      12: istore_3
      13: iload_3
      14: iload_2
      15: if_icmpge     181
      18: aload_1
      19: iload_3
      20: invokevirtual #6                  // Method java/lang/String.charAt:(I)C
      23: istore        4
      25: iload         4
      27: bipush        32
      29: if_icmplt     39
      32: iload         4
      34: bipush        126
      36: if_icmple     140
      39: aload_0
      40: getfield      #2                  // Field buffer:Lio/netty/buffer/ByteBuf;
      43: bipush        92
      45: invokevirtual #4                  // Method io/netty/buffer/ByteBuf.writeByte:(I)Lio/netty/buffer/ByteBuf;
      48: pop
      49: aload_0
      50: getfield      #2                  // Field buffer:Lio/netty/buffer/ByteBuf;
      53: bipush        117
      55: invokevirtual #4                  // Method io/netty/buffer/ByteBuf.writeByte:(I)Lio/netty/buffer/ByteBuf;
      58: pop
      59: aload_0
      60: getfield      #2                  // Field buffer:Lio/netty/buffer/ByteBuf;
      63: getstatic     #17                 // Field hexChars:[C
      66: iload         4
      68: ldc           #18                 // int 61440
      70: iand
      71: bipush        12
      73: ishr
      74: caload
      75: invokevirtual #4                  // Method io/netty/buffer/ByteBuf.writeByte:(I)Lio/netty/buffer/ByteBuf;
      78: pop
      79: aload_0
      80: getfield      #2                  // Field buffer:Lio/netty/buffer/ByteBuf;
      83: getstatic     #17                 // Field hexChars:[C
      86: iload         4
      88: sipush        3840
      91: iand
      92: bipush        8
      94: ishr
      95: caload
      96: invokevirtual #4                  // Method io/netty/buffer/ByteBuf.writeByte:(I)Lio/netty/buffer/ByteBuf;
      99: pop
     100: aload_0
     101: getfield      #2                  // Field buffer:Lio/netty/buffer/ByteBuf;
     104: getstatic     #17                 // Field hexChars:[C
     107: iload         4
     109: sipush        240
     112: iand
     113: iconst_4
     114: ishr
     115: caload
     116: invokevirtual #4                  // Method io/netty/buffer/ByteBuf.writeByte:(I)Lio/netty/buffer/ByteBuf;
     119: pop
     120: aload_0
     121: getfield      #2                  // Field buffer:Lio/netty/buffer/ByteBuf;
     124: getstatic     #17                 // Field hexChars:[C
     127: iload         4
     129: bipush        15
     131: iand
     132: caload
     133: invokevirtual #4                  // Method io/netty/buffer/ByteBuf.writeByte:(I)Lio/netty/buffer/ByteBuf;
     136: pop
     137: goto          175
     140: iload         4
     142: bipush        92
     144: if_icmpeq     154
     147: iload         4
     149: bipush        34
     151: if_icmpne     164
     154: aload_0
     155: getfield      #2                  // Field buffer:Lio/netty/buffer/ByteBuf;
     158: bipush        92
     160: invokevirtual #4                  // Method io/netty/buffer/ByteBuf.writeByte:(I)Lio/netty/buffer/ByteBuf;
     163: pop
     164: aload_0
     165: getfield      #2                  // Field buffer:Lio/netty/buffer/ByteBuf;
     168: iload         4
     170: i2b
     171: invokevirtual #4                  // Method io/netty/buffer/ByteBuf.writeByte:(I)Lio/netty/buffer/ByteBuf;
     174: pop
     175: iinc          3, 1
     178: goto          13
     181: aload_0
     182: areturn

  public org.apache.pulsar.common.util.SimpleTextOutputStream write(boolean);
    Code:
       0: aload_0
       1: iload_1
       2: ifeq          10
       5: ldc           #19                 // String true
       7: goto          12
      10: ldc           #20                 // String false
      12: invokevirtual #16                 // Method write:(Ljava/lang/String;)Lorg/apache/pulsar/common/util/SimpleTextOutputStream;
      15: pop
      16: aload_0
      17: areturn

  public org.apache.pulsar.common.util.SimpleTextOutputStream write(long);
    Code:
       0: aload_0
       1: getfield      #2                  // Field buffer:Lio/netty/buffer/ByteBuf;
       4: lload_1
       5: invokestatic  #21                 // Method org/apache/pulsar/common/util/NumberFormat.format:(Lio/netty/buffer/ByteBuf;J)V
       8: aload_0
       9: areturn

  public org.apache.pulsar.common.util.SimpleTextOutputStream write(double);
    Code:
       0: dload_1
       1: d2l
       2: lstore_3
       3: aload_0
       4: lload_3
       5: invokevirtual #9                  // Method write:(J)Lorg/apache/pulsar/common/util/SimpleTextOutputStream;
       8: pop
       9: ldc2_w        #22                 // double 1000.0d
      12: dload_1
      13: lload_3
      14: l2d
      15: dsub
      16: dmul
      17: d2l
      18: invokestatic  #24                 // Method java/lang/Math.abs:(J)J
      21: lstore        5
      23: aload_0
      24: bipush        46
      26: invokevirtual #25                 // Method write:(C)Lorg/apache/pulsar/common/util/SimpleTextOutputStream;
      29: pop
      30: lload         5
      32: lconst_0
      33: lcmp
      34: ifne          46
      37: aload_0
      38: bipush        48
      40: invokevirtual #25                 // Method write:(C)Lorg/apache/pulsar/common/util/SimpleTextOutputStream;
      43: pop
      44: aload_0
      45: areturn
      46: lload         5
      48: ldc2_w        #26                 // long 100l
      51: lcmp
      52: ifge          62
      55: aload_0
      56: bipush        48
      58: invokevirtual #25                 // Method write:(C)Lorg/apache/pulsar/common/util/SimpleTextOutputStream;
      61: pop
      62: lload         5
      64: ldc2_w        #28                 // long 10l
      67: lcmp
      68: ifge          78
      71: aload_0
      72: bipush        48
      74: invokevirtual #25                 // Method write:(C)Lorg/apache/pulsar/common/util/SimpleTextOutputStream;
      77: pop
      78: aload_0
      79: lload         5
      81: invokevirtual #9                  // Method write:(J)Lorg/apache/pulsar/common/util/SimpleTextOutputStream;
      84: pop
      85: aload_0
      86: areturn

  static {};
    Code:
       0: bipush        16
       2: newarray       char
       4: dup
       5: iconst_0
       6: bipush        48
       8: castore
       9: dup
      10: iconst_1
      11: bipush        49
      13: castore
      14: dup
      15: iconst_2
      16: bipush        50
      18: castore
      19: dup
      20: iconst_3
      21: bipush        51
      23: castore
      24: dup
      25: iconst_4
      26: bipush        52
      28: castore
      29: dup
      30: iconst_5
      31: bipush        53
      33: castore
      34: dup
      35: bipush        6
      37: bipush        54
      39: castore
      40: dup
      41: bipush        7
      43: bipush        55
      45: castore
      46: dup
      47: bipush        8
      49: bipush        56
      51: castore
      52: dup
      53: bipush        9
      55: bipush        57
      57: castore
      58: dup
      59: bipush        10
      61: bipush        97
      63: castore
      64: dup
      65: bipush        11
      67: bipush        98
      69: castore
      70: dup
      71: bipush        12
      73: bipush        99
      75: castore
      76: dup
      77: bipush        13
      79: bipush        100
      81: castore
      82: dup
      83: bipush        14
      85: bipush        101
      87: castore
      88: dup
      89: bipush        15
      91: bipush        102
      93: castore
      94: putstatic     #17                 // Field hexChars:[C
      97: return
}
