Compiled from "KOptionInfo.java"
public class org.apache.kerby.KOptionInfo {
  private java.lang.String name;

  private org.apache.kerby.KOptionGroup group;

  private org.apache.kerby.KOptionType type;

  private java.lang.String description;

  private java.lang.Object value;

  public org.apache.kerby.KOptionInfo(java.lang.String, java.lang.String);
    Code:
       0: aload_0
       1: aload_1
       2: aload_2
       3: getstatic     #1                  // Field org/apache/kerby/KOptionType.NOV:Lorg/apache/kerby/KOptionType;
       6: invokespecial #2                  // Method "<init>":(Ljava/lang/String;Ljava/lang/String;Lorg/apache/kerby/KOptionType;)V
       9: return

  public org.apache.kerby.KOptionInfo(java.lang.String, java.lang.String, org.apache.kerby.KOptionType);
    Code:
       0: aload_0
       1: aload_1
       2: aload_2
       3: aconst_null
       4: aload_3
       5: invokespecial #3                  // Method "<init>":(Ljava/lang/String;Ljava/lang/String;Lorg/apache/kerby/KOptionGroup;Lorg/apache/kerby/KOptionType;)V
       8: return

  public org.apache.kerby.KOptionInfo(java.lang.String, java.lang.String, org.apache.kerby.KOptionGroup);
    Code:
       0: aload_0
       1: aload_1
       2: aload_2
       3: aload_3
       4: getstatic     #1                  // Field org/apache/kerby/KOptionType.NOV:Lorg/apache/kerby/KOptionType;
       7: invokespecial #3                  // Method "<init>":(Ljava/lang/String;Ljava/lang/String;Lorg/apache/kerby/KOptionGroup;Lorg/apache/kerby/KOptionType;)V
      10: return

  public org.apache.kerby.KOptionInfo(java.lang.String, java.lang.String, org.apache.kerby.KOptionGroup, org.apache.kerby.KOptionType);
    Code:
       0: aload_0
       1: invokespecial #4                  // Method java/lang/Object."<init>":()V
       4: aload_0
       5: aload_1
       6: putfield      #5                  // Field name:Ljava/lang/String;
       9: aload_0
      10: aload_2
      11: putfield      #6                  // Field description:Ljava/lang/String;
      14: aload_0
      15: aload_3
      16: putfield      #7                  // Field group:Lorg/apache/kerby/KOptionGroup;
      19: aload_0
      20: aload         4
      22: putfield      #8                  // Field type:Lorg/apache/kerby/KOptionType;
      25: return

  public void setType(org.apache.kerby.KOptionType);
    Code:
       0: aload_0
       1: aload_1
       2: putfield      #8                  // Field type:Lorg/apache/kerby/KOptionType;
       5: return

  public org.apache.kerby.KOptionType getType();
    Code:
       0: aload_0
       1: getfield      #8                  // Field type:Lorg/apache/kerby/KOptionType;
       4: areturn

  public void setName(java.lang.String);
    Code:
       0: aload_0
       1: aload_1
       2: putfield      #5                  // Field name:Ljava/lang/String;
       5: return

  public java.lang.String getName();
    Code:
       0: aload_0
       1: getfield      #5                  // Field name:Ljava/lang/String;
       4: areturn

  public void setDescription(java.lang.String);
    Code:
       0: aload_0
       1: aload_1
       2: putfield      #6                  // Field description:Ljava/lang/String;
       5: return

  public java.lang.String getDescription();
    Code:
       0: aload_0
       1: getfield      #6                  // Field description:Ljava/lang/String;
       4: areturn

  public void setValue(java.lang.Object);
    Code:
       0: aload_0
       1: aload_1
       2: putfield      #9                  // Field value:Ljava/lang/Object;
       5: return

  public java.lang.Object getValue();
    Code:
       0: aload_0
       1: getfield      #9                  // Field value:Ljava/lang/Object;
       4: areturn

  public void setGroup(org.apache.kerby.KOptionGroup);
    Code:
       0: aload_0
       1: aload_1
       2: putfield      #7                  // Field group:Lorg/apache/kerby/KOptionGroup;
       5: return

  public org.apache.kerby.KOptionGroup getGroup();
    Code:
       0: aload_0
       1: getfield      #7                  // Field group:Lorg/apache/kerby/KOptionGroup;
       4: areturn
}
