Compiled from "AnsiOutputApplicationListener.java"
public class org.springframework.boot.context.config.AnsiOutputApplicationListener implements org.springframework.context.ApplicationListener<org.springframework.boot.context.event.ApplicationEnvironmentPreparedEvent>, org.springframework.core.Ordered {
  public org.springframework.boot.context.config.AnsiOutputApplicationListener();
    Code:
       0: aload_0
       1: invokespecial #1                  // Method java/lang/Object."<init>":()V
       4: return

  public void onApplicationEvent(org.springframework.boot.context.event.ApplicationEnvironmentPreparedEvent);
    Code:
       0: new           #2                  // class org/springframework/boot/bind/RelaxedPropertyResolver
       3: dup
       4: aload_1
       5: invokevirtual #3                  // Method org/springframework/boot/context/event/ApplicationEnvironmentPreparedEvent.getEnvironment:()Lorg/springframework/core/env/ConfigurableEnvironment;
       8: ldc           #4                  // String spring.output.ansi.
      10: invokespecial #5                  // Method org/springframework/boot/bind/RelaxedPropertyResolver."<init>":(Lorg/springframework/core/env/PropertyResolver;Ljava/lang/String;)V
      13: astore_2
      14: aload_2
      15: ldc           #6                  // String enabled
      17: invokevirtual #7                  // Method org/springframework/boot/bind/RelaxedPropertyResolver.containsProperty:(Ljava/lang/String;)Z
      20: ifeq          48
      23: aload_2
      24: ldc           #6                  // String enabled
      26: invokevirtual #8                  // Method org/springframework/boot/bind/RelaxedPropertyResolver.getProperty:(Ljava/lang/String;)Ljava/lang/String;
      29: astore_3
      30: ldc           #9                  // class org/springframework/boot/ansi/AnsiOutput$Enabled
      32: aload_3
      33: getstatic     #10                 // Field java/util/Locale.ENGLISH:Ljava/util/Locale;
      36: invokevirtual #11                 // Method java/lang/String.toUpperCase:(Ljava/util/Locale;)Ljava/lang/String;
      39: invokestatic  #12                 // Method java/lang/Enum.valueOf:(Ljava/lang/Class;Ljava/lang/String;)Ljava/lang/Enum;
      42: checkcast     #9                  // class org/springframework/boot/ansi/AnsiOutput$Enabled
      45: invokestatic  #13                 // Method org/springframework/boot/ansi/AnsiOutput.setEnabled:(Lorg/springframework/boot/ansi/AnsiOutput$Enabled;)V
      48: aload_2
      49: ldc           #14                 // String console-available
      51: invokevirtual #7                  // Method org/springframework/boot/bind/RelaxedPropertyResolver.containsProperty:(Ljava/lang/String;)Z
      54: ifeq          71
      57: aload_2
      58: ldc           #14                 // String console-available
      60: ldc           #15                 // class java/lang/Boolean
      62: invokevirtual #16                 // Method org/springframework/boot/bind/RelaxedPropertyResolver.getProperty:(Ljava/lang/String;Ljava/lang/Class;)Ljava/lang/Object;
      65: checkcast     #15                 // class java/lang/Boolean
      68: invokestatic  #17                 // Method org/springframework/boot/ansi/AnsiOutput.setConsoleAvailable:(Ljava/lang/Boolean;)V
      71: return

  public int getOrder();
    Code:
       0: ldc           #19                 // int -2147483637
       2: ireturn

  public void onApplicationEvent(org.springframework.context.ApplicationEvent);
    Code:
       0: aload_0
       1: aload_1
       2: checkcast     #20                 // class org/springframework/boot/context/event/ApplicationEnvironmentPreparedEvent
       5: invokevirtual #21                 // Method onApplicationEvent:(Lorg/springframework/boot/context/event/ApplicationEnvironmentPreparedEvent;)V
       8: return
}
