Compiled from "IPInformationProto.java"
public final class technology.dice.dicewhere.lineprocessing.serializers.protobuf.IPInformationProto$IpInformationProto extends com.google.protobuf.GeneratedMessageV3 implements technology.dice.dicewhere.lineprocessing.serializers.protobuf.IPInformationProto$IpInformationProtoOrBuilder {
  private static final long serialVersionUID;

  public static final int GEONAMEID_FIELD_NUMBER;

  private volatile java.lang.Object geonameId_;

  public static final int CITY_FIELD_NUMBER;

  private volatile java.lang.Object city_;

  public static final int LEASTSPECIFICDIVISION_FIELD_NUMBER;

  private volatile java.lang.Object leastSpecificDivision_;

  public static final int MOSTSPECIFICDIVISION_FIELD_NUMBER;

  private volatile java.lang.Object mostSpecificDivision_;

  public static final int POSTCODE_FIELD_NUMBER;

  private volatile java.lang.Object postcode_;

  public static final int COUNTRYCODEALPHA2_FIELD_NUMBER;

  private volatile java.lang.Object countryCodeAlpha2_;

  public static final int STARTOFRANGE_FIELD_NUMBER;

  private com.google.protobuf.ByteString startOfRange_;

  public static final int ENDOFRANGE_FIELD_NUMBER;

  private com.google.protobuf.ByteString endOfRange_;

  public static final int ORIGINALLINE_FIELD_NUMBER;

  private volatile java.lang.Object originalLine_;

  public static final int ISVPN_FIELD_NUMBER;

  private int isVpn_;

  private byte memoizedIsInitialized;

  private static final technology.dice.dicewhere.lineprocessing.serializers.protobuf.IPInformationProto$IpInformationProto DEFAULT_INSTANCE;

  private static final com.google.protobuf.Parser<technology.dice.dicewhere.lineprocessing.serializers.protobuf.IPInformationProto$IpInformationProto> PARSER;

  private technology.dice.dicewhere.lineprocessing.serializers.protobuf.IPInformationProto$IpInformationProto(com.google.protobuf.GeneratedMessageV3$Builder<?>);
    Code:
       0: aload_0
       1: aload_1
       2: invokespecial #17                 // Method com/google/protobuf/GeneratedMessageV3."<init>":(Lcom/google/protobuf/GeneratedMessageV3$Builder;)V
       5: aload_0
       6: iconst_m1
       7: putfield      #18                 // Field memoizedIsInitialized:B
      10: return

  private technology.dice.dicewhere.lineprocessing.serializers.protobuf.IPInformationProto$IpInformationProto();
    Code:
       0: aload_0
       1: invokespecial #19                 // Method com/google/protobuf/GeneratedMessageV3."<init>":()V
       4: aload_0
       5: iconst_m1
       6: putfield      #18                 // Field memoizedIsInitialized:B
       9: aload_0
      10: ldc           #20                 // String
      12: putfield      #14                 // Field geonameId_:Ljava/lang/Object;
      15: aload_0
      16: ldc           #20                 // String
      18: putfield      #13                 // Field city_:Ljava/lang/Object;
      21: aload_0
      22: ldc           #20                 // String
      24: putfield      #12                 // Field leastSpecificDivision_:Ljava/lang/Object;
      27: aload_0
      28: ldc           #20                 // String
      30: putfield      #11                 // Field mostSpecificDivision_:Ljava/lang/Object;
      33: aload_0
      34: ldc           #20                 // String
      36: putfield      #10                 // Field postcode_:Ljava/lang/Object;
      39: aload_0
      40: ldc           #20                 // String
      42: putfield      #9                  // Field countryCodeAlpha2_:Ljava/lang/Object;
      45: aload_0
      46: getstatic     #21                 // Field com/google/protobuf/ByteString.EMPTY:Lcom/google/protobuf/ByteString;
      49: putfield      #8                  // Field startOfRange_:Lcom/google/protobuf/ByteString;
      52: aload_0
      53: getstatic     #21                 // Field com/google/protobuf/ByteString.EMPTY:Lcom/google/protobuf/ByteString;
      56: putfield      #7                  // Field endOfRange_:Lcom/google/protobuf/ByteString;
      59: aload_0
      60: ldc           #20                 // String
      62: putfield      #6                  // Field originalLine_:Ljava/lang/Object;
      65: aload_0
      66: iconst_0
      67: putfield      #5                  // Field isVpn_:I
      70: return

  public final com.google.protobuf.UnknownFieldSet getUnknownFields();
    Code:
       0: aload_0
       1: getfield      #4                  // Field unknownFields:Lcom/google/protobuf/UnknownFieldSet;
       4: areturn

  private technology.dice.dicewhere.lineprocessing.serializers.protobuf.IPInformationProto$IpInformationProto(com.google.protobuf.CodedInputStream, com.google.protobuf.ExtensionRegistryLite) throws com.google.protobuf.InvalidProtocolBufferException;
    Code:
       0: aload_0
       1: invokespecial #22                 // Method "<init>":()V
       4: aload_2
       5: ifnonnull     16
       8: new           #23                 // class java/lang/NullPointerException
      11: dup
      12: invokespecial #24                 // Method java/lang/NullPointerException."<init>":()V
      15: athrow
      16: iconst_0
      17: istore_3
      18: invokestatic  #25                 // Method com/google/protobuf/UnknownFieldSet.newBuilder:()Lcom/google/protobuf/UnknownFieldSet$Builder;
      21: astore        4
      23: iconst_0
      24: istore        5
      26: iload         5
      28: ifne          303
      31: aload_1
      32: invokevirtual #26                 // Method com/google/protobuf/CodedInputStream.readTag:()I
      35: istore        6
      37: iload         6
      39: lookupswitch  { // 11
                     0: 136
                    10: 142
                    18: 157
                    26: 172
                    34: 187
                    42: 202
                    50: 217
                    58: 232
                    66: 243
                    74: 254
                    80: 269
               default: 284
          }
     136: iconst_1
     137: istore        5
     139: goto          300
     142: aload_1
     143: invokevirtual #27                 // Method com/google/protobuf/CodedInputStream.readStringRequireUtf8:()Ljava/lang/String;
     146: astore        7
     148: aload_0
     149: aload         7
     151: putfield      #14                 // Field geonameId_:Ljava/lang/Object;
     154: goto          300
     157: aload_1
     158: invokevirtual #27                 // Method com/google/protobuf/CodedInputStream.readStringRequireUtf8:()Ljava/lang/String;
     161: astore        7
     163: aload_0
     164: aload         7
     166: putfield      #13                 // Field city_:Ljava/lang/Object;
     169: goto          300
     172: aload_1
     173: invokevirtual #27                 // Method com/google/protobuf/CodedInputStream.readStringRequireUtf8:()Ljava/lang/String;
     176: astore        7
     178: aload_0
     179: aload         7
     181: putfield      #12                 // Field leastSpecificDivision_:Ljava/lang/Object;
     184: goto          300
     187: aload_1
     188: invokevirtual #27                 // Method com/google/protobuf/CodedInputStream.readStringRequireUtf8:()Ljava/lang/String;
     191: astore        7
     193: aload_0
     194: aload         7
     196: putfield      #11                 // Field mostSpecificDivision_:Ljava/lang/Object;
     199: goto          300
     202: aload_1
     203: invokevirtual #27                 // Method com/google/protobuf/CodedInputStream.readStringRequireUtf8:()Ljava/lang/String;
     206: astore        7
     208: aload_0
     209: aload         7
     211: putfield      #10                 // Field postcode_:Ljava/lang/Object;
     214: goto          300
     217: aload_1
     218: invokevirtual #27                 // Method com/google/protobuf/CodedInputStream.readStringRequireUtf8:()Ljava/lang/String;
     221: astore        7
     223: aload_0
     224: aload         7
     226: putfield      #9                  // Field countryCodeAlpha2_:Ljava/lang/Object;
     229: goto          300
     232: aload_0
     233: aload_1
     234: invokevirtual #28                 // Method com/google/protobuf/CodedInputStream.readBytes:()Lcom/google/protobuf/ByteString;
     237: putfield      #8                  // Field startOfRange_:Lcom/google/protobuf/ByteString;
     240: goto          300
     243: aload_0
     244: aload_1
     245: invokevirtual #28                 // Method com/google/protobuf/CodedInputStream.readBytes:()Lcom/google/protobuf/ByteString;
     248: putfield      #7                  // Field endOfRange_:Lcom/google/protobuf/ByteString;
     251: goto          300
     254: aload_1
     255: invokevirtual #27                 // Method com/google/protobuf/CodedInputStream.readStringRequireUtf8:()Ljava/lang/String;
     258: astore        7
     260: aload_0
     261: aload         7
     263: putfield      #6                  // Field originalLine_:Ljava/lang/Object;
     266: goto          300
     269: aload_1
     270: invokevirtual #29                 // Method com/google/protobuf/CodedInputStream.readEnum:()I
     273: istore        7
     275: aload_0
     276: iload         7
     278: putfield      #5                  // Field isVpn_:I
     281: goto          300
     284: aload_0
     285: aload_1
     286: aload         4
     288: aload_2
     289: iload         6
     291: invokevirtual #30                 // Method parseUnknownFieldProto3:(Lcom/google/protobuf/CodedInputStream;Lcom/google/protobuf/UnknownFieldSet$Builder;Lcom/google/protobuf/ExtensionRegistryLite;I)Z
     294: ifne          300
     297: iconst_1
     298: istore        5
     300: goto          26
     303: aload_0
     304: aload         4
     306: invokevirtual #31                 // Method com/google/protobuf/UnknownFieldSet$Builder.build:()Lcom/google/protobuf/UnknownFieldSet;
     309: putfield      #4                  // Field unknownFields:Lcom/google/protobuf/UnknownFieldSet;
     312: aload_0
     313: invokevirtual #32                 // Method makeExtensionsImmutable:()V
     316: goto          362
     319: astore        5
     321: aload         5
     323: aload_0
     324: invokevirtual #34                 // Method com/google/protobuf/InvalidProtocolBufferException.setUnfinishedMessage:(Lcom/google/protobuf/MessageLite;)Lcom/google/protobuf/InvalidProtocolBufferException;
     327: athrow
     328: astore        5
     330: new           #33                 // class com/google/protobuf/InvalidProtocolBufferException
     333: dup
     334: aload         5
     336: invokespecial #36                 // Method com/google/protobuf/InvalidProtocolBufferException."<init>":(Ljava/io/IOException;)V
     339: aload_0
     340: invokevirtual #34                 // Method com/google/protobuf/InvalidProtocolBufferException.setUnfinishedMessage:(Lcom/google/protobuf/MessageLite;)Lcom/google/protobuf/InvalidProtocolBufferException;
     343: athrow
     344: astore        8
     346: aload_0
     347: aload         4
     349: invokevirtual #31                 // Method com/google/protobuf/UnknownFieldSet$Builder.build:()Lcom/google/protobuf/UnknownFieldSet;
     352: putfield      #4                  // Field unknownFields:Lcom/google/protobuf/UnknownFieldSet;
     355: aload_0
     356: invokevirtual #32                 // Method makeExtensionsImmutable:()V
     359: aload         8
     361: athrow
     362: return
    Exception table:
       from    to  target type
          23   303   319   Class com/google/protobuf/InvalidProtocolBufferException
          23   303   328   Class java/io/IOException
          23   303   344   any
         319   346   344   any

  public static final com.google.protobuf.Descriptors$Descriptor getDescriptor();
    Code:
       0: invokestatic  #37                 // Method technology/dice/dicewhere/lineprocessing/serializers/protobuf/IPInformationProto.access$000:()Lcom/google/protobuf/Descriptors$Descriptor;
       3: areturn

  protected com.google.protobuf.GeneratedMessageV3$FieldAccessorTable internalGetFieldAccessorTable();
    Code:
       0: invokestatic  #38                 // Method technology/dice/dicewhere/lineprocessing/serializers/protobuf/IPInformationProto.access$100:()Lcom/google/protobuf/GeneratedMessageV3$FieldAccessorTable;
       3: ldc           #39                 // class technology/dice/dicewhere/lineprocessing/serializers/protobuf/IPInformationProto$IpInformationProto
       5: ldc           #40                 // class technology/dice/dicewhere/lineprocessing/serializers/protobuf/IPInformationProto$IpInformationProto$Builder
       7: invokevirtual #41                 // Method com/google/protobuf/GeneratedMessageV3$FieldAccessorTable.ensureFieldAccessorsInitialized:(Ljava/lang/Class;Ljava/lang/Class;)Lcom/google/protobuf/GeneratedMessageV3$FieldAccessorTable;
      10: areturn

  public java.lang.String getGeonameId();
    Code:
       0: aload_0
       1: getfield      #14                 // Field geonameId_:Ljava/lang/Object;
       4: astore_1
       5: aload_1
       6: instanceof    #42                 // class java/lang/String
       9: ifeq          17
      12: aload_1
      13: checkcast     #42                 // class java/lang/String
      16: areturn
      17: aload_1
      18: checkcast     #43                 // class com/google/protobuf/ByteString
      21: astore_2
      22: aload_2
      23: invokevirtual #44                 // Method com/google/protobuf/ByteString.toStringUtf8:()Ljava/lang/String;
      26: astore_3
      27: aload_0
      28: aload_3
      29: putfield      #14                 // Field geonameId_:Ljava/lang/Object;
      32: aload_3
      33: areturn

  public com.google.protobuf.ByteString getGeonameIdBytes();
    Code:
       0: aload_0
       1: getfield      #14                 // Field geonameId_:Ljava/lang/Object;
       4: astore_1
       5: aload_1
       6: instanceof    #42                 // class java/lang/String
       9: ifeq          27
      12: aload_1
      13: checkcast     #42                 // class java/lang/String
      16: invokestatic  #45                 // Method com/google/protobuf/ByteString.copyFromUtf8:(Ljava/lang/String;)Lcom/google/protobuf/ByteString;
      19: astore_2
      20: aload_0
      21: aload_2
      22: putfield      #14                 // Field geonameId_:Ljava/lang/Object;
      25: aload_2
      26: areturn
      27: aload_1
      28: checkcast     #43                 // class com/google/protobuf/ByteString
      31: areturn

  public java.lang.String getCity();
    Code:
       0: aload_0
       1: getfield      #13                 // Field city_:Ljava/lang/Object;
       4: astore_1
       5: aload_1
       6: instanceof    #42                 // class java/lang/String
       9: ifeq          17
      12: aload_1
      13: checkcast     #42                 // class java/lang/String
      16: areturn
      17: aload_1
      18: checkcast     #43                 // class com/google/protobuf/ByteString
      21: astore_2
      22: aload_2
      23: invokevirtual #44                 // Method com/google/protobuf/ByteString.toStringUtf8:()Ljava/lang/String;
      26: astore_3
      27: aload_0
      28: aload_3
      29: putfield      #13                 // Field city_:Ljava/lang/Object;
      32: aload_3
      33: areturn

  public com.google.protobuf.ByteString getCityBytes();
    Code:
       0: aload_0
       1: getfield      #13                 // Field city_:Ljava/lang/Object;
       4: astore_1
       5: aload_1
       6: instanceof    #42                 // class java/lang/String
       9: ifeq          27
      12: aload_1
      13: checkcast     #42                 // class java/lang/String
      16: invokestatic  #45                 // Method com/google/protobuf/ByteString.copyFromUtf8:(Ljava/lang/String;)Lcom/google/protobuf/ByteString;
      19: astore_2
      20: aload_0
      21: aload_2
      22: putfield      #13                 // Field city_:Ljava/lang/Object;
      25: aload_2
      26: areturn
      27: aload_1
      28: checkcast     #43                 // class com/google/protobuf/ByteString
      31: areturn

  public java.lang.String getLeastSpecificDivision();
    Code:
       0: aload_0
       1: getfield      #12                 // Field leastSpecificDivision_:Ljava/lang/Object;
       4: astore_1
       5: aload_1
       6: instanceof    #42                 // class java/lang/String
       9: ifeq          17
      12: aload_1
      13: checkcast     #42                 // class java/lang/String
      16: areturn
      17: aload_1
      18: checkcast     #43                 // class com/google/protobuf/ByteString
      21: astore_2
      22: aload_2
      23: invokevirtual #44                 // Method com/google/protobuf/ByteString.toStringUtf8:()Ljava/lang/String;
      26: astore_3
      27: aload_0
      28: aload_3
      29: putfield      #12                 // Field leastSpecificDivision_:Ljava/lang/Object;
      32: aload_3
      33: areturn

  public com.google.protobuf.ByteString getLeastSpecificDivisionBytes();
    Code:
       0: aload_0
       1: getfield      #12                 // Field leastSpecificDivision_:Ljava/lang/Object;
       4: astore_1
       5: aload_1
       6: instanceof    #42                 // class java/lang/String
       9: ifeq          27
      12: aload_1
      13: checkcast     #42                 // class java/lang/String
      16: invokestatic  #45                 // Method com/google/protobuf/ByteString.copyFromUtf8:(Ljava/lang/String;)Lcom/google/protobuf/ByteString;
      19: astore_2
      20: aload_0
      21: aload_2
      22: putfield      #12                 // Field leastSpecificDivision_:Ljava/lang/Object;
      25: aload_2
      26: areturn
      27: aload_1
      28: checkcast     #43                 // class com/google/protobuf/ByteString
      31: areturn

  public java.lang.String getMostSpecificDivision();
    Code:
       0: aload_0
       1: getfield      #11                 // Field mostSpecificDivision_:Ljava/lang/Object;
       4: astore_1
       5: aload_1
       6: instanceof    #42                 // class java/lang/String
       9: ifeq          17
      12: aload_1
      13: checkcast     #42                 // class java/lang/String
      16: areturn
      17: aload_1
      18: checkcast     #43                 // class com/google/protobuf/ByteString
      21: astore_2
      22: aload_2
      23: invokevirtual #44                 // Method com/google/protobuf/ByteString.toStringUtf8:()Ljava/lang/String;
      26: astore_3
      27: aload_0
      28: aload_3
      29: putfield      #11                 // Field mostSpecificDivision_:Ljava/lang/Object;
      32: aload_3
      33: areturn

  public com.google.protobuf.ByteString getMostSpecificDivisionBytes();
    Code:
       0: aload_0
       1: getfield      #11                 // Field mostSpecificDivision_:Ljava/lang/Object;
       4: astore_1
       5: aload_1
       6: instanceof    #42                 // class java/lang/String
       9: ifeq          27
      12: aload_1
      13: checkcast     #42                 // class java/lang/String
      16: invokestatic  #45                 // Method com/google/protobuf/ByteString.copyFromUtf8:(Ljava/lang/String;)Lcom/google/protobuf/ByteString;
      19: astore_2
      20: aload_0
      21: aload_2
      22: putfield      #11                 // Field mostSpecificDivision_:Ljava/lang/Object;
      25: aload_2
      26: areturn
      27: aload_1
      28: checkcast     #43                 // class com/google/protobuf/ByteString
      31: areturn

  public java.lang.String getPostcode();
    Code:
       0: aload_0
       1: getfield      #10                 // Field postcode_:Ljava/lang/Object;
       4: astore_1
       5: aload_1
       6: instanceof    #42                 // class java/lang/String
       9: ifeq          17
      12: aload_1
      13: checkcast     #42                 // class java/lang/String
      16: areturn
      17: aload_1
      18: checkcast     #43                 // class com/google/protobuf/ByteString
      21: astore_2
      22: aload_2
      23: invokevirtual #44                 // Method com/google/protobuf/ByteString.toStringUtf8:()Ljava/lang/String;
      26: astore_3
      27: aload_0
      28: aload_3
      29: putfield      #10                 // Field postcode_:Ljava/lang/Object;
      32: aload_3
      33: areturn

  public com.google.protobuf.ByteString getPostcodeBytes();
    Code:
       0: aload_0
       1: getfield      #10                 // Field postcode_:Ljava/lang/Object;
       4: astore_1
       5: aload_1
       6: instanceof    #42                 // class java/lang/String
       9: ifeq          27
      12: aload_1
      13: checkcast     #42                 // class java/lang/String
      16: invokestatic  #45                 // Method com/google/protobuf/ByteString.copyFromUtf8:(Ljava/lang/String;)Lcom/google/protobuf/ByteString;
      19: astore_2
      20: aload_0
      21: aload_2
      22: putfield      #10                 // Field postcode_:Ljava/lang/Object;
      25: aload_2
      26: areturn
      27: aload_1
      28: checkcast     #43                 // class com/google/protobuf/ByteString
      31: areturn

  public java.lang.String getCountryCodeAlpha2();
    Code:
       0: aload_0
       1: getfield      #9                  // Field countryCodeAlpha2_:Ljava/lang/Object;
       4: astore_1
       5: aload_1
       6: instanceof    #42                 // class java/lang/String
       9: ifeq          17
      12: aload_1
      13: checkcast     #42                 // class java/lang/String
      16: areturn
      17: aload_1
      18: checkcast     #43                 // class com/google/protobuf/ByteString
      21: astore_2
      22: aload_2
      23: invokevirtual #44                 // Method com/google/protobuf/ByteString.toStringUtf8:()Ljava/lang/String;
      26: astore_3
      27: aload_0
      28: aload_3
      29: putfield      #9                  // Field countryCodeAlpha2_:Ljava/lang/Object;
      32: aload_3
      33: areturn

  public com.google.protobuf.ByteString getCountryCodeAlpha2Bytes();
    Code:
       0: aload_0
       1: getfield      #9                  // Field countryCodeAlpha2_:Ljava/lang/Object;
       4: astore_1
       5: aload_1
       6: instanceof    #42                 // class java/lang/String
       9: ifeq          27
      12: aload_1
      13: checkcast     #42                 // class java/lang/String
      16: invokestatic  #45                 // Method com/google/protobuf/ByteString.copyFromUtf8:(Ljava/lang/String;)Lcom/google/protobuf/ByteString;
      19: astore_2
      20: aload_0
      21: aload_2
      22: putfield      #9                  // Field countryCodeAlpha2_:Ljava/lang/Object;
      25: aload_2
      26: areturn
      27: aload_1
      28: checkcast     #43                 // class com/google/protobuf/ByteString
      31: areturn

  public com.google.protobuf.ByteString getStartOfRange();
    Code:
       0: aload_0
       1: getfield      #8                  // Field startOfRange_:Lcom/google/protobuf/ByteString;
       4: areturn

  public com.google.protobuf.ByteString getEndOfRange();
    Code:
       0: aload_0
       1: getfield      #7                  // Field endOfRange_:Lcom/google/protobuf/ByteString;
       4: areturn

  public java.lang.String getOriginalLine();
    Code:
       0: aload_0
       1: getfield      #6                  // Field originalLine_:Ljava/lang/Object;
       4: astore_1
       5: aload_1
       6: instanceof    #42                 // class java/lang/String
       9: ifeq          17
      12: aload_1
      13: checkcast     #42                 // class java/lang/String
      16: areturn
      17: aload_1
      18: checkcast     #43                 // class com/google/protobuf/ByteString
      21: astore_2
      22: aload_2
      23: invokevirtual #44                 // Method com/google/protobuf/ByteString.toStringUtf8:()Ljava/lang/String;
      26: astore_3
      27: aload_0
      28: aload_3
      29: putfield      #6                  // Field originalLine_:Ljava/lang/Object;
      32: aload_3
      33: areturn

  public com.google.protobuf.ByteString getOriginalLineBytes();
    Code:
       0: aload_0
       1: getfield      #6                  // Field originalLine_:Ljava/lang/Object;
       4: astore_1
       5: aload_1
       6: instanceof    #42                 // class java/lang/String
       9: ifeq          27
      12: aload_1
      13: checkcast     #42                 // class java/lang/String
      16: invokestatic  #45                 // Method com/google/protobuf/ByteString.copyFromUtf8:(Ljava/lang/String;)Lcom/google/protobuf/ByteString;
      19: astore_2
      20: aload_0
      21: aload_2
      22: putfield      #6                  // Field originalLine_:Ljava/lang/Object;
      25: aload_2
      26: areturn
      27: aload_1
      28: checkcast     #43                 // class com/google/protobuf/ByteString
      31: areturn

  public int getIsVpnValue();
    Code:
       0: aload_0
       1: getfield      #5                  // Field isVpn_:I
       4: ireturn

  public technology.dice.dicewhere.lineprocessing.serializers.protobuf.ThreeStateValueProto$ThreeStateValue getIsVpn();
    Code:
       0: aload_0
       1: getfield      #5                  // Field isVpn_:I
       4: invokestatic  #46                 // Method technology/dice/dicewhere/lineprocessing/serializers/protobuf/ThreeStateValueProto$ThreeStateValue.valueOf:(I)Ltechnology/dice/dicewhere/lineprocessing/serializers/protobuf/ThreeStateValueProto$ThreeStateValue;
       7: astore_1
       8: aload_1
       9: ifnonnull     18
      12: getstatic     #47                 // Field technology/dice/dicewhere/lineprocessing/serializers/protobuf/ThreeStateValueProto$ThreeStateValue.UNRECOGNIZED:Ltechnology/dice/dicewhere/lineprocessing/serializers/protobuf/ThreeStateValueProto$ThreeStateValue;
      15: goto          19
      18: aload_1
      19: areturn

  public final boolean isInitialized();
    Code:
       0: aload_0
       1: getfield      #18                 // Field memoizedIsInitialized:B
       4: istore_1
       5: iload_1
       6: iconst_1
       7: if_icmpne     12
      10: iconst_1
      11: ireturn
      12: iload_1
      13: ifne          18
      16: iconst_0
      17: ireturn
      18: aload_0
      19: iconst_1
      20: putfield      #18                 // Field memoizedIsInitialized:B
      23: iconst_1
      24: ireturn

  public void writeTo(com.google.protobuf.CodedOutputStream) throws java.io.IOException;
    Code:
       0: aload_0
       1: invokevirtual #48                 // Method getGeonameIdBytes:()Lcom/google/protobuf/ByteString;
       4: invokevirtual #49                 // Method com/google/protobuf/ByteString.isEmpty:()Z
       7: ifne          19
      10: aload_1
      11: iconst_1
      12: aload_0
      13: getfield      #14                 // Field geonameId_:Ljava/lang/Object;
      16: invokestatic  #50                 // Method com/google/protobuf/GeneratedMessageV3.writeString:(Lcom/google/protobuf/CodedOutputStream;ILjava/lang/Object;)V
      19: aload_0
      20: invokevirtual #51                 // Method getCityBytes:()Lcom/google/protobuf/ByteString;
      23: invokevirtual #49                 // Method com/google/protobuf/ByteString.isEmpty:()Z
      26: ifne          38
      29: aload_1
      30: iconst_2
      31: aload_0
      32: getfield      #13                 // Field city_:Ljava/lang/Object;
      35: invokestatic  #50                 // Method com/google/protobuf/GeneratedMessageV3.writeString:(Lcom/google/protobuf/CodedOutputStream;ILjava/lang/Object;)V
      38: aload_0
      39: invokevirtual #52                 // Method getLeastSpecificDivisionBytes:()Lcom/google/protobuf/ByteString;
      42: invokevirtual #49                 // Method com/google/protobuf/ByteString.isEmpty:()Z
      45: ifne          57
      48: aload_1
      49: iconst_3
      50: aload_0
      51: getfield      #12                 // Field leastSpecificDivision_:Ljava/lang/Object;
      54: invokestatic  #50                 // Method com/google/protobuf/GeneratedMessageV3.writeString:(Lcom/google/protobuf/CodedOutputStream;ILjava/lang/Object;)V
      57: aload_0
      58: invokevirtual #53                 // Method getMostSpecificDivisionBytes:()Lcom/google/protobuf/ByteString;
      61: invokevirtual #49                 // Method com/google/protobuf/ByteString.isEmpty:()Z
      64: ifne          76
      67: aload_1
      68: iconst_4
      69: aload_0
      70: getfield      #11                 // Field mostSpecificDivision_:Ljava/lang/Object;
      73: invokestatic  #50                 // Method com/google/protobuf/GeneratedMessageV3.writeString:(Lcom/google/protobuf/CodedOutputStream;ILjava/lang/Object;)V
      76: aload_0
      77: invokevirtual #54                 // Method getPostcodeBytes:()Lcom/google/protobuf/ByteString;
      80: invokevirtual #49                 // Method com/google/protobuf/ByteString.isEmpty:()Z
      83: ifne          95
      86: aload_1
      87: iconst_5
      88: aload_0
      89: getfield      #10                 // Field postcode_:Ljava/lang/Object;
      92: invokestatic  #50                 // Method com/google/protobuf/GeneratedMessageV3.writeString:(Lcom/google/protobuf/CodedOutputStream;ILjava/lang/Object;)V
      95: aload_0
      96: invokevirtual #55                 // Method getCountryCodeAlpha2Bytes:()Lcom/google/protobuf/ByteString;
      99: invokevirtual #49                 // Method com/google/protobuf/ByteString.isEmpty:()Z
     102: ifne          115
     105: aload_1
     106: bipush        6
     108: aload_0
     109: getfield      #9                  // Field countryCodeAlpha2_:Ljava/lang/Object;
     112: invokestatic  #50                 // Method com/google/protobuf/GeneratedMessageV3.writeString:(Lcom/google/protobuf/CodedOutputStream;ILjava/lang/Object;)V
     115: aload_0
     116: getfield      #8                  // Field startOfRange_:Lcom/google/protobuf/ByteString;
     119: invokevirtual #49                 // Method com/google/protobuf/ByteString.isEmpty:()Z
     122: ifne          135
     125: aload_1
     126: bipush        7
     128: aload_0
     129: getfield      #8                  // Field startOfRange_:Lcom/google/protobuf/ByteString;
     132: invokevirtual #56                 // Method com/google/protobuf/CodedOutputStream.writeBytes:(ILcom/google/protobuf/ByteString;)V
     135: aload_0
     136: getfield      #7                  // Field endOfRange_:Lcom/google/protobuf/ByteString;
     139: invokevirtual #49                 // Method com/google/protobuf/ByteString.isEmpty:()Z
     142: ifne          155
     145: aload_1
     146: bipush        8
     148: aload_0
     149: getfield      #7                  // Field endOfRange_:Lcom/google/protobuf/ByteString;
     152: invokevirtual #56                 // Method com/google/protobuf/CodedOutputStream.writeBytes:(ILcom/google/protobuf/ByteString;)V
     155: aload_0
     156: invokevirtual #57                 // Method getOriginalLineBytes:()Lcom/google/protobuf/ByteString;
     159: invokevirtual #49                 // Method com/google/protobuf/ByteString.isEmpty:()Z
     162: ifne          175
     165: aload_1
     166: bipush        9
     168: aload_0
     169: getfield      #6                  // Field originalLine_:Ljava/lang/Object;
     172: invokestatic  #50                 // Method com/google/protobuf/GeneratedMessageV3.writeString:(Lcom/google/protobuf/CodedOutputStream;ILjava/lang/Object;)V
     175: aload_0
     176: getfield      #5                  // Field isVpn_:I
     179: getstatic     #58                 // Field technology/dice/dicewhere/lineprocessing/serializers/protobuf/ThreeStateValueProto$ThreeStateValue.NOT_SPECIFIED:Ltechnology/dice/dicewhere/lineprocessing/serializers/protobuf/ThreeStateValueProto$ThreeStateValue;
     182: invokevirtual #59                 // Method technology/dice/dicewhere/lineprocessing/serializers/protobuf/ThreeStateValueProto$ThreeStateValue.getNumber:()I
     185: if_icmpeq     198
     188: aload_1
     189: bipush        10
     191: aload_0
     192: getfield      #5                  // Field isVpn_:I
     195: invokevirtual #60                 // Method com/google/protobuf/CodedOutputStream.writeEnum:(II)V
     198: aload_0
     199: getfield      #4                  // Field unknownFields:Lcom/google/protobuf/UnknownFieldSet;
     202: aload_1
     203: invokevirtual #61                 // Method com/google/protobuf/UnknownFieldSet.writeTo:(Lcom/google/protobuf/CodedOutputStream;)V
     206: return

  public int getSerializedSize();
    Code:
       0: aload_0
       1: getfield      #62                 // Field memoizedSize:I
       4: istore_1
       5: iload_1
       6: iconst_m1
       7: if_icmpeq     12
      10: iload_1
      11: ireturn
      12: iconst_0
      13: istore_1
      14: aload_0
      15: invokevirtual #48                 // Method getGeonameIdBytes:()Lcom/google/protobuf/ByteString;
      18: invokevirtual #49                 // Method com/google/protobuf/ByteString.isEmpty:()Z
      21: ifne          35
      24: iload_1
      25: iconst_1
      26: aload_0
      27: getfield      #14                 // Field geonameId_:Ljava/lang/Object;
      30: invokestatic  #63                 // Method com/google/protobuf/GeneratedMessageV3.computeStringSize:(ILjava/lang/Object;)I
      33: iadd
      34: istore_1
      35: aload_0
      36: invokevirtual #51                 // Method getCityBytes:()Lcom/google/protobuf/ByteString;
      39: invokevirtual #49                 // Method com/google/protobuf/ByteString.isEmpty:()Z
      42: ifne          56
      45: iload_1
      46: iconst_2
      47: aload_0
      48: getfield      #13                 // Field city_:Ljava/lang/Object;
      51: invokestatic  #63                 // Method com/google/protobuf/GeneratedMessageV3.computeStringSize:(ILjava/lang/Object;)I
      54: iadd
      55: istore_1
      56: aload_0
      57: invokevirtual #52                 // Method getLeastSpecificDivisionBytes:()Lcom/google/protobuf/ByteString;
      60: invokevirtual #49                 // Method com/google/protobuf/ByteString.isEmpty:()Z
      63: ifne          77
      66: iload_1
      67: iconst_3
      68: aload_0
      69: getfield      #12                 // Field leastSpecificDivision_:Ljava/lang/Object;
      72: invokestatic  #63                 // Method com/google/protobuf/GeneratedMessageV3.computeStringSize:(ILjava/lang/Object;)I
      75: iadd
      76: istore_1
      77: aload_0
      78: invokevirtual #53                 // Method getMostSpecificDivisionBytes:()Lcom/google/protobuf/ByteString;
      81: invokevirtual #49                 // Method com/google/protobuf/ByteString.isEmpty:()Z
      84: ifne          98
      87: iload_1
      88: iconst_4
      89: aload_0
      90: getfield      #11                 // Field mostSpecificDivision_:Ljava/lang/Object;
      93: invokestatic  #63                 // Method com/google/protobuf/GeneratedMessageV3.computeStringSize:(ILjava/lang/Object;)I
      96: iadd
      97: istore_1
      98: aload_0
      99: invokevirtual #54                 // Method getPostcodeBytes:()Lcom/google/protobuf/ByteString;
     102: invokevirtual #49                 // Method com/google/protobuf/ByteString.isEmpty:()Z
     105: ifne          119
     108: iload_1
     109: iconst_5
     110: aload_0
     111: getfield      #10                 // Field postcode_:Ljava/lang/Object;
     114: invokestatic  #63                 // Method com/google/protobuf/GeneratedMessageV3.computeStringSize:(ILjava/lang/Object;)I
     117: iadd
     118: istore_1
     119: aload_0
     120: invokevirtual #55                 // Method getCountryCodeAlpha2Bytes:()Lcom/google/protobuf/ByteString;
     123: invokevirtual #49                 // Method com/google/protobuf/ByteString.isEmpty:()Z
     126: ifne          141
     129: iload_1
     130: bipush        6
     132: aload_0
     133: getfield      #9                  // Field countryCodeAlpha2_:Ljava/lang/Object;
     136: invokestatic  #63                 // Method com/google/protobuf/GeneratedMessageV3.computeStringSize:(ILjava/lang/Object;)I
     139: iadd
     140: istore_1
     141: aload_0
     142: getfield      #8                  // Field startOfRange_:Lcom/google/protobuf/ByteString;
     145: invokevirtual #49                 // Method com/google/protobuf/ByteString.isEmpty:()Z
     148: ifne          163
     151: iload_1
     152: bipush        7
     154: aload_0
     155: getfield      #8                  // Field startOfRange_:Lcom/google/protobuf/ByteString;
     158: invokestatic  #64                 // Method com/google/protobuf/CodedOutputStream.computeBytesSize:(ILcom/google/protobuf/ByteString;)I
     161: iadd
     162: istore_1
     163: aload_0
     164: getfield      #7                  // Field endOfRange_:Lcom/google/protobuf/ByteString;
     167: invokevirtual #49                 // Method com/google/protobuf/ByteString.isEmpty:()Z
     170: ifne          185
     173: iload_1
     174: bipush        8
     176: aload_0
     177: getfield      #7                  // Field endOfRange_:Lcom/google/protobuf/ByteString;
     180: invokestatic  #64                 // Method com/google/protobuf/CodedOutputStream.computeBytesSize:(ILcom/google/protobuf/ByteString;)I
     183: iadd
     184: istore_1
     185: aload_0
     186: invokevirtual #57                 // Method getOriginalLineBytes:()Lcom/google/protobuf/ByteString;
     189: invokevirtual #49                 // Method com/google/protobuf/ByteString.isEmpty:()Z
     192: ifne          207
     195: iload_1
     196: bipush        9
     198: aload_0
     199: getfield      #6                  // Field originalLine_:Ljava/lang/Object;
     202: invokestatic  #63                 // Method com/google/protobuf/GeneratedMessageV3.computeStringSize:(ILjava/lang/Object;)I
     205: iadd
     206: istore_1
     207: aload_0
     208: getfield      #5                  // Field isVpn_:I
     211: getstatic     #58                 // Field technology/dice/dicewhere/lineprocessing/serializers/protobuf/ThreeStateValueProto$ThreeStateValue.NOT_SPECIFIED:Ltechnology/dice/dicewhere/lineprocessing/serializers/protobuf/ThreeStateValueProto$ThreeStateValue;
     214: invokevirtual #59                 // Method technology/dice/dicewhere/lineprocessing/serializers/protobuf/ThreeStateValueProto$ThreeStateValue.getNumber:()I
     217: if_icmpeq     232
     220: iload_1
     221: bipush        10
     223: aload_0
     224: getfield      #5                  // Field isVpn_:I
     227: invokestatic  #65                 // Method com/google/protobuf/CodedOutputStream.computeEnumSize:(II)I
     230: iadd
     231: istore_1
     232: iload_1
     233: aload_0
     234: getfield      #4                  // Field unknownFields:Lcom/google/protobuf/UnknownFieldSet;
     237: invokevirtual #66                 // Method com/google/protobuf/UnknownFieldSet.getSerializedSize:()I
     240: iadd
     241: istore_1
     242: aload_0
     243: iload_1
     244: putfield      #62                 // Field memoizedSize:I
     247: iload_1
     248: ireturn

  public boolean equals(java.lang.Object);
    Code:
       0: aload_1
       1: aload_0
       2: if_acmpne     7
       5: iconst_1
       6: ireturn
       7: aload_1
       8: instanceof    #39                 // class technology/dice/dicewhere/lineprocessing/serializers/protobuf/IPInformationProto$IpInformationProto
      11: ifne          20
      14: aload_0
      15: aload_1
      16: invokespecial #67                 // Method com/google/protobuf/GeneratedMessageV3.equals:(Ljava/lang/Object;)Z
      19: ireturn
      20: aload_1
      21: checkcast     #39                 // class technology/dice/dicewhere/lineprocessing/serializers/protobuf/IPInformationProto$IpInformationProto
      24: astore_2
      25: iconst_1
      26: istore_3
      27: iload_3
      28: ifeq          49
      31: aload_0
      32: invokevirtual #68                 // Method getGeonameId:()Ljava/lang/String;
      35: aload_2
      36: invokevirtual #68                 // Method getGeonameId:()Ljava/lang/String;
      39: invokevirtual #69                 // Method java/lang/String.equals:(Ljava/lang/Object;)Z
      42: ifeq          49
      45: iconst_1
      46: goto          50
      49: iconst_0
      50: istore_3
      51: iload_3
      52: ifeq          73
      55: aload_0
      56: invokevirtual #70                 // Method getCity:()Ljava/lang/String;
      59: aload_2
      60: invokevirtual #70                 // Method getCity:()Ljava/lang/String;
      63: invokevirtual #69                 // Method java/lang/String.equals:(Ljava/lang/Object;)Z
      66: ifeq          73
      69: iconst_1
      70: goto          74
      73: iconst_0
      74: istore_3
      75: iload_3
      76: ifeq          97
      79: aload_0
      80: invokevirtual #71                 // Method getLeastSpecificDivision:()Ljava/lang/String;
      83: aload_2
      84: invokevirtual #71                 // Method getLeastSpecificDivision:()Ljava/lang/String;
      87: invokevirtual #69                 // Method java/lang/String.equals:(Ljava/lang/Object;)Z
      90: ifeq          97
      93: iconst_1
      94: goto          98
      97: iconst_0
      98: istore_3
      99: iload_3
     100: ifeq          121
     103: aload_0
     104: invokevirtual #72                 // Method getMostSpecificDivision:()Ljava/lang/String;
     107: aload_2
     108: invokevirtual #72                 // Method getMostSpecificDivision:()Ljava/lang/String;
     111: invokevirtual #69                 // Method java/lang/String.equals:(Ljava/lang/Object;)Z
     114: ifeq          121
     117: iconst_1
     118: goto          122
     121: iconst_0
     122: istore_3
     123: iload_3
     124: ifeq          145
     127: aload_0
     128: invokevirtual #73                 // Method getPostcode:()Ljava/lang/String;
     131: aload_2
     132: invokevirtual #73                 // Method getPostcode:()Ljava/lang/String;
     135: invokevirtual #69                 // Method java/lang/String.equals:(Ljava/lang/Object;)Z
     138: ifeq          145
     141: iconst_1
     142: goto          146
     145: iconst_0
     146: istore_3
     147: iload_3
     148: ifeq          169
     151: aload_0
     152: invokevirtual #74                 // Method getCountryCodeAlpha2:()Ljava/lang/String;
     155: aload_2
     156: invokevirtual #74                 // Method getCountryCodeAlpha2:()Ljava/lang/String;
     159: invokevirtual #69                 // Method java/lang/String.equals:(Ljava/lang/Object;)Z
     162: ifeq          169
     165: iconst_1
     166: goto          170
     169: iconst_0
     170: istore_3
     171: iload_3
     172: ifeq          193
     175: aload_0
     176: invokevirtual #75                 // Method getStartOfRange:()Lcom/google/protobuf/ByteString;
     179: aload_2
     180: invokevirtual #75                 // Method getStartOfRange:()Lcom/google/protobuf/ByteString;
     183: invokevirtual #76                 // Method com/google/protobuf/ByteString.equals:(Ljava/lang/Object;)Z
     186: ifeq          193
     189: iconst_1
     190: goto          194
     193: iconst_0
     194: istore_3
     195: iload_3
     196: ifeq          217
     199: aload_0
     200: invokevirtual #77                 // Method getEndOfRange:()Lcom/google/protobuf/ByteString;
     203: aload_2
     204: invokevirtual #77                 // Method getEndOfRange:()Lcom/google/protobuf/ByteString;
     207: invokevirtual #76                 // Method com/google/protobuf/ByteString.equals:(Ljava/lang/Object;)Z
     210: ifeq          217
     213: iconst_1
     214: goto          218
     217: iconst_0
     218: istore_3
     219: iload_3
     220: ifeq          241
     223: aload_0
     224: invokevirtual #78                 // Method getOriginalLine:()Ljava/lang/String;
     227: aload_2
     228: invokevirtual #78                 // Method getOriginalLine:()Ljava/lang/String;
     231: invokevirtual #69                 // Method java/lang/String.equals:(Ljava/lang/Object;)Z
     234: ifeq          241
     237: iconst_1
     238: goto          242
     241: iconst_0
     242: istore_3
     243: iload_3
     244: ifeq          262
     247: aload_0
     248: getfield      #5                  // Field isVpn_:I
     251: aload_2
     252: getfield      #5                  // Field isVpn_:I
     255: if_icmpne     262
     258: iconst_1
     259: goto          263
     262: iconst_0
     263: istore_3
     264: iload_3
     265: ifeq          286
     268: aload_0
     269: getfield      #4                  // Field unknownFields:Lcom/google/protobuf/UnknownFieldSet;
     272: aload_2
     273: getfield      #4                  // Field unknownFields:Lcom/google/protobuf/UnknownFieldSet;
     276: invokevirtual #79                 // Method com/google/protobuf/UnknownFieldSet.equals:(Ljava/lang/Object;)Z
     279: ifeq          286
     282: iconst_1
     283: goto          287
     286: iconst_0
     287: istore_3
     288: iload_3
     289: ireturn

  public int hashCode();
    Code:
       0: aload_0
       1: getfield      #80                 // Field memoizedHashCode:I
       4: ifeq          12
       7: aload_0
       8: getfield      #80                 // Field memoizedHashCode:I
      11: ireturn
      12: bipush        41
      14: istore_1
      15: bipush        19
      17: iload_1
      18: imul
      19: invokestatic  #81                 // Method getDescriptor:()Lcom/google/protobuf/Descriptors$Descriptor;
      22: invokevirtual #82                 // Method java/lang/Object.hashCode:()I
      25: iadd
      26: istore_1
      27: bipush        37
      29: iload_1
      30: imul
      31: iconst_1
      32: iadd
      33: istore_1
      34: bipush        53
      36: iload_1
      37: imul
      38: aload_0
      39: invokevirtual #68                 // Method getGeonameId:()Ljava/lang/String;
      42: invokevirtual #83                 // Method java/lang/String.hashCode:()I
      45: iadd
      46: istore_1
      47: bipush        37
      49: iload_1
      50: imul
      51: iconst_2
      52: iadd
      53: istore_1
      54: bipush        53
      56: iload_1
      57: imul
      58: aload_0
      59: invokevirtual #70                 // Method getCity:()Ljava/lang/String;
      62: invokevirtual #83                 // Method java/lang/String.hashCode:()I
      65: iadd
      66: istore_1
      67: bipush        37
      69: iload_1
      70: imul
      71: iconst_3
      72: iadd
      73: istore_1
      74: bipush        53
      76: iload_1
      77: imul
      78: aload_0
      79: invokevirtual #71                 // Method getLeastSpecificDivision:()Ljava/lang/String;
      82: invokevirtual #83                 // Method java/lang/String.hashCode:()I
      85: iadd
      86: istore_1
      87: bipush        37
      89: iload_1
      90: imul
      91: iconst_4
      92: iadd
      93: istore_1
      94: bipush        53
      96: iload_1
      97: imul
      98: aload_0
      99: invokevirtual #72                 // Method getMostSpecificDivision:()Ljava/lang/String;
     102: invokevirtual #83                 // Method java/lang/String.hashCode:()I
     105: iadd
     106: istore_1
     107: bipush        37
     109: iload_1
     110: imul
     111: iconst_5
     112: iadd
     113: istore_1
     114: bipush        53
     116: iload_1
     117: imul
     118: aload_0
     119: invokevirtual #73                 // Method getPostcode:()Ljava/lang/String;
     122: invokevirtual #83                 // Method java/lang/String.hashCode:()I
     125: iadd
     126: istore_1
     127: bipush        37
     129: iload_1
     130: imul
     131: bipush        6
     133: iadd
     134: istore_1
     135: bipush        53
     137: iload_1
     138: imul
     139: aload_0
     140: invokevirtual #74                 // Method getCountryCodeAlpha2:()Ljava/lang/String;
     143: invokevirtual #83                 // Method java/lang/String.hashCode:()I
     146: iadd
     147: istore_1
     148: bipush        37
     150: iload_1
     151: imul
     152: bipush        7
     154: iadd
     155: istore_1
     156: bipush        53
     158: iload_1
     159: imul
     160: aload_0
     161: invokevirtual #75                 // Method getStartOfRange:()Lcom/google/protobuf/ByteString;
     164: invokevirtual #84                 // Method com/google/protobuf/ByteString.hashCode:()I
     167: iadd
     168: istore_1
     169: bipush        37
     171: iload_1
     172: imul
     173: bipush        8
     175: iadd
     176: istore_1
     177: bipush        53
     179: iload_1
     180: imul
     181: aload_0
     182: invokevirtual #77                 // Method getEndOfRange:()Lcom/google/protobuf/ByteString;
     185: invokevirtual #84                 // Method com/google/protobuf/ByteString.hashCode:()I
     188: iadd
     189: istore_1
     190: bipush        37
     192: iload_1
     193: imul
     194: bipush        9
     196: iadd
     197: istore_1
     198: bipush        53
     200: iload_1
     201: imul
     202: aload_0
     203: invokevirtual #78                 // Method getOriginalLine:()Ljava/lang/String;
     206: invokevirtual #83                 // Method java/lang/String.hashCode:()I
     209: iadd
     210: istore_1
     211: bipush        37
     213: iload_1
     214: imul
     215: bipush        10
     217: iadd
     218: istore_1
     219: bipush        53
     221: iload_1
     222: imul
     223: aload_0
     224: getfield      #5                  // Field isVpn_:I
     227: iadd
     228: istore_1
     229: bipush        29
     231: iload_1
     232: imul
     233: aload_0
     234: getfield      #4                  // Field unknownFields:Lcom/google/protobuf/UnknownFieldSet;
     237: invokevirtual #85                 // Method com/google/protobuf/UnknownFieldSet.hashCode:()I
     240: iadd
     241: istore_1
     242: aload_0
     243: iload_1
     244: putfield      #80                 // Field memoizedHashCode:I
     247: iload_1
     248: ireturn

  public static technology.dice.dicewhere.lineprocessing.serializers.protobuf.IPInformationProto$IpInformationProto parseFrom(java.nio.ByteBuffer) throws com.google.protobuf.InvalidProtocolBufferException;
    Code:
       0: getstatic     #3                  // Field PARSER:Lcom/google/protobuf/Parser;
       3: aload_0
       4: invokeinterface #86,  2           // InterfaceMethod com/google/protobuf/Parser.parseFrom:(Ljava/nio/ByteBuffer;)Ljava/lang/Object;
       9: checkcast     #39                 // class technology/dice/dicewhere/lineprocessing/serializers/protobuf/IPInformationProto$IpInformationProto
      12: areturn

  public static technology.dice.dicewhere.lineprocessing.serializers.protobuf.IPInformationProto$IpInformationProto parseFrom(java.nio.ByteBuffer, com.google.protobuf.ExtensionRegistryLite) throws com.google.protobuf.InvalidProtocolBufferException;
    Code:
       0: getstatic     #3                  // Field PARSER:Lcom/google/protobuf/Parser;
       3: aload_0
       4: aload_1
       5: invokeinterface #87,  3           // InterfaceMethod com/google/protobuf/Parser.parseFrom:(Ljava/nio/ByteBuffer;Lcom/google/protobuf/ExtensionRegistryLite;)Ljava/lang/Object;
      10: checkcast     #39                 // class technology/dice/dicewhere/lineprocessing/serializers/protobuf/IPInformationProto$IpInformationProto
      13: areturn

  public static technology.dice.dicewhere.lineprocessing.serializers.protobuf.IPInformationProto$IpInformationProto parseFrom(com.google.protobuf.ByteString) throws com.google.protobuf.InvalidProtocolBufferException;
    Code:
       0: getstatic     #3                  // Field PARSER:Lcom/google/protobuf/Parser;
       3: aload_0
       4: invokeinterface #88,  2           // InterfaceMethod com/google/protobuf/Parser.parseFrom:(Lcom/google/protobuf/ByteString;)Ljava/lang/Object;
       9: checkcast     #39                 // class technology/dice/dicewhere/lineprocessing/serializers/protobuf/IPInformationProto$IpInformationProto
      12: areturn

  public static technology.dice.dicewhere.lineprocessing.serializers.protobuf.IPInformationProto$IpInformationProto parseFrom(com.google.protobuf.ByteString, com.google.protobuf.ExtensionRegistryLite) throws com.google.protobuf.InvalidProtocolBufferException;
    Code:
       0: getstatic     #3                  // Field PARSER:Lcom/google/protobuf/Parser;
       3: aload_0
       4: aload_1
       5: invokeinterface #89,  3           // InterfaceMethod com/google/protobuf/Parser.parseFrom:(Lcom/google/protobuf/ByteString;Lcom/google/protobuf/ExtensionRegistryLite;)Ljava/lang/Object;
      10: checkcast     #39                 // class technology/dice/dicewhere/lineprocessing/serializers/protobuf/IPInformationProto$IpInformationProto
      13: areturn

  public static technology.dice.dicewhere.lineprocessing.serializers.protobuf.IPInformationProto$IpInformationProto parseFrom(byte[]) throws com.google.protobuf.InvalidProtocolBufferException;
    Code:
       0: getstatic     #3                  // Field PARSER:Lcom/google/protobuf/Parser;
       3: aload_0
       4: invokeinterface #90,  2           // InterfaceMethod com/google/protobuf/Parser.parseFrom:([B)Ljava/lang/Object;
       9: checkcast     #39                 // class technology/dice/dicewhere/lineprocessing/serializers/protobuf/IPInformationProto$IpInformationProto
      12: areturn

  public static technology.dice.dicewhere.lineprocessing.serializers.protobuf.IPInformationProto$IpInformationProto parseFrom(byte[], com.google.protobuf.ExtensionRegistryLite) throws com.google.protobuf.InvalidProtocolBufferException;
    Code:
       0: getstatic     #3                  // Field PARSER:Lcom/google/protobuf/Parser;
       3: aload_0
       4: aload_1
       5: invokeinterface #91,  3           // InterfaceMethod com/google/protobuf/Parser.parseFrom:([BLcom/google/protobuf/ExtensionRegistryLite;)Ljava/lang/Object;
      10: checkcast     #39                 // class technology/dice/dicewhere/lineprocessing/serializers/protobuf/IPInformationProto$IpInformationProto
      13: areturn

  public static technology.dice.dicewhere.lineprocessing.serializers.protobuf.IPInformationProto$IpInformationProto parseFrom(java.io.InputStream) throws java.io.IOException;
    Code:
       0: getstatic     #3                  // Field PARSER:Lcom/google/protobuf/Parser;
       3: aload_0
       4: invokestatic  #92                 // Method com/google/protobuf/GeneratedMessageV3.parseWithIOException:(Lcom/google/protobuf/Parser;Ljava/io/InputStream;)Lcom/google/protobuf/Message;
       7: checkcast     #39                 // class technology/dice/dicewhere/lineprocessing/serializers/protobuf/IPInformationProto$IpInformationProto
      10: areturn

  public static technology.dice.dicewhere.lineprocessing.serializers.protobuf.IPInformationProto$IpInformationProto parseFrom(java.io.InputStream, com.google.protobuf.ExtensionRegistryLite) throws java.io.IOException;
    Code:
       0: getstatic     #3                  // Field PARSER:Lcom/google/protobuf/Parser;
       3: aload_0
       4: aload_1
       5: invokestatic  #93                 // Method com/google/protobuf/GeneratedMessageV3.parseWithIOException:(Lcom/google/protobuf/Parser;Ljava/io/InputStream;Lcom/google/protobuf/ExtensionRegistryLite;)Lcom/google/protobuf/Message;
       8: checkcast     #39                 // class technology/dice/dicewhere/lineprocessing/serializers/protobuf/IPInformationProto$IpInformationProto
      11: areturn

  public static technology.dice.dicewhere.lineprocessing.serializers.protobuf.IPInformationProto$IpInformationProto parseDelimitedFrom(java.io.InputStream) throws java.io.IOException;
    Code:
       0: getstatic     #3                  // Field PARSER:Lcom/google/protobuf/Parser;
       3: aload_0
       4: invokestatic  #94                 // Method com/google/protobuf/GeneratedMessageV3.parseDelimitedWithIOException:(Lcom/google/protobuf/Parser;Ljava/io/InputStream;)Lcom/google/protobuf/Message;
       7: checkcast     #39                 // class technology/dice/dicewhere/lineprocessing/serializers/protobuf/IPInformationProto$IpInformationProto
      10: areturn

  public static technology.dice.dicewhere.lineprocessing.serializers.protobuf.IPInformationProto$IpInformationProto parseDelimitedFrom(java.io.InputStream, com.google.protobuf.ExtensionRegistryLite) throws java.io.IOException;
    Code:
       0: getstatic     #3                  // Field PARSER:Lcom/google/protobuf/Parser;
       3: aload_0
       4: aload_1
       5: invokestatic  #95                 // Method com/google/protobuf/GeneratedMessageV3.parseDelimitedWithIOException:(Lcom/google/protobuf/Parser;Ljava/io/InputStream;Lcom/google/protobuf/ExtensionRegistryLite;)Lcom/google/protobuf/Message;
       8: checkcast     #39                 // class technology/dice/dicewhere/lineprocessing/serializers/protobuf/IPInformationProto$IpInformationProto
      11: areturn

  public static technology.dice.dicewhere.lineprocessing.serializers.protobuf.IPInformationProto$IpInformationProto parseFrom(com.google.protobuf.CodedInputStream) throws java.io.IOException;
    Code:
       0: getstatic     #3                  // Field PARSER:Lcom/google/protobuf/Parser;
       3: aload_0
       4: invokestatic  #96                 // Method com/google/protobuf/GeneratedMessageV3.parseWithIOException:(Lcom/google/protobuf/Parser;Lcom/google/protobuf/CodedInputStream;)Lcom/google/protobuf/Message;
       7: checkcast     #39                 // class technology/dice/dicewhere/lineprocessing/serializers/protobuf/IPInformationProto$IpInformationProto
      10: areturn

  public static technology.dice.dicewhere.lineprocessing.serializers.protobuf.IPInformationProto$IpInformationProto parseFrom(com.google.protobuf.CodedInputStream, com.google.protobuf.ExtensionRegistryLite) throws java.io.IOException;
    Code:
       0: getstatic     #3                  // Field PARSER:Lcom/google/protobuf/Parser;
       3: aload_0
       4: aload_1
       5: invokestatic  #97                 // Method com/google/protobuf/GeneratedMessageV3.parseWithIOException:(Lcom/google/protobuf/Parser;Lcom/google/protobuf/CodedInputStream;Lcom/google/protobuf/ExtensionRegistryLite;)Lcom/google/protobuf/Message;
       8: checkcast     #39                 // class technology/dice/dicewhere/lineprocessing/serializers/protobuf/IPInformationProto$IpInformationProto
      11: areturn

  public technology.dice.dicewhere.lineprocessing.serializers.protobuf.IPInformationProto$IpInformationProto$Builder newBuilderForType();
    Code:
       0: invokestatic  #98                 // Method newBuilder:()Ltechnology/dice/dicewhere/lineprocessing/serializers/protobuf/IPInformationProto$IpInformationProto$Builder;
       3: areturn

  public static technology.dice.dicewhere.lineprocessing.serializers.protobuf.IPInformationProto$IpInformationProto$Builder newBuilder();
    Code:
       0: getstatic     #99                 // Field DEFAULT_INSTANCE:Ltechnology/dice/dicewhere/lineprocessing/serializers/protobuf/IPInformationProto$IpInformationProto;
       3: invokevirtual #100                // Method toBuilder:()Ltechnology/dice/dicewhere/lineprocessing/serializers/protobuf/IPInformationProto$IpInformationProto$Builder;
       6: areturn

  public static technology.dice.dicewhere.lineprocessing.serializers.protobuf.IPInformationProto$IpInformationProto$Builder newBuilder(technology.dice.dicewhere.lineprocessing.serializers.protobuf.IPInformationProto$IpInformationProto);
    Code:
       0: getstatic     #99                 // Field DEFAULT_INSTANCE:Ltechnology/dice/dicewhere/lineprocessing/serializers/protobuf/IPInformationProto$IpInformationProto;
       3: invokevirtual #100                // Method toBuilder:()Ltechnology/dice/dicewhere/lineprocessing/serializers/protobuf/IPInformationProto$IpInformationProto$Builder;
       6: aload_0
       7: invokevirtual #101                // Method technology/dice/dicewhere/lineprocessing/serializers/protobuf/IPInformationProto$IpInformationProto$Builder.mergeFrom:(Ltechnology/dice/dicewhere/lineprocessing/serializers/protobuf/IPInformationProto$IpInformationProto;)Ltechnology/dice/dicewhere/lineprocessing/serializers/protobuf/IPInformationProto$IpInformationProto$Builder;
      10: areturn

  public technology.dice.dicewhere.lineprocessing.serializers.protobuf.IPInformationProto$IpInformationProto$Builder toBuilder();
    Code:
       0: aload_0
       1: getstatic     #99                 // Field DEFAULT_INSTANCE:Ltechnology/dice/dicewhere/lineprocessing/serializers/protobuf/IPInformationProto$IpInformationProto;
       4: if_acmpne     18
       7: new           #40                 // class technology/dice/dicewhere/lineprocessing/serializers/protobuf/IPInformationProto$IpInformationProto$Builder
      10: dup
      11: aconst_null
      12: invokespecial #102                // Method technology/dice/dicewhere/lineprocessing/serializers/protobuf/IPInformationProto$IpInformationProto$Builder."<init>":(Ltechnology/dice/dicewhere/lineprocessing/serializers/protobuf/IPInformationProto$1;)V
      15: goto          30
      18: new           #40                 // class technology/dice/dicewhere/lineprocessing/serializers/protobuf/IPInformationProto$IpInformationProto$Builder
      21: dup
      22: aconst_null
      23: invokespecial #102                // Method technology/dice/dicewhere/lineprocessing/serializers/protobuf/IPInformationProto$IpInformationProto$Builder."<init>":(Ltechnology/dice/dicewhere/lineprocessing/serializers/protobuf/IPInformationProto$1;)V
      26: aload_0
      27: invokevirtual #101                // Method technology/dice/dicewhere/lineprocessing/serializers/protobuf/IPInformationProto$IpInformationProto$Builder.mergeFrom:(Ltechnology/dice/dicewhere/lineprocessing/serializers/protobuf/IPInformationProto$IpInformationProto;)Ltechnology/dice/dicewhere/lineprocessing/serializers/protobuf/IPInformationProto$IpInformationProto$Builder;
      30: areturn

  protected technology.dice.dicewhere.lineprocessing.serializers.protobuf.IPInformationProto$IpInformationProto$Builder newBuilderForType(com.google.protobuf.GeneratedMessageV3$BuilderParent);
    Code:
       0: new           #40                 // class technology/dice/dicewhere/lineprocessing/serializers/protobuf/IPInformationProto$IpInformationProto$Builder
       3: dup
       4: aload_1
       5: aconst_null
       6: invokespecial #103                // Method technology/dice/dicewhere/lineprocessing/serializers/protobuf/IPInformationProto$IpInformationProto$Builder."<init>":(Lcom/google/protobuf/GeneratedMessageV3$BuilderParent;Ltechnology/dice/dicewhere/lineprocessing/serializers/protobuf/IPInformationProto$1;)V
       9: astore_2
      10: aload_2
      11: areturn

  public static technology.dice.dicewhere.lineprocessing.serializers.protobuf.IPInformationProto$IpInformationProto getDefaultInstance();
    Code:
       0: getstatic     #99                 // Field DEFAULT_INSTANCE:Ltechnology/dice/dicewhere/lineprocessing/serializers/protobuf/IPInformationProto$IpInformationProto;
       3: areturn

  public static com.google.protobuf.Parser<technology.dice.dicewhere.lineprocessing.serializers.protobuf.IPInformationProto$IpInformationProto> parser();
    Code:
       0: getstatic     #3                  // Field PARSER:Lcom/google/protobuf/Parser;
       3: areturn

  public com.google.protobuf.Parser<technology.dice.dicewhere.lineprocessing.serializers.protobuf.IPInformationProto$IpInformationProto> getParserForType();
    Code:
       0: getstatic     #3                  // Field PARSER:Lcom/google/protobuf/Parser;
       3: areturn

  public technology.dice.dicewhere.lineprocessing.serializers.protobuf.IPInformationProto$IpInformationProto getDefaultInstanceForType();
    Code:
       0: getstatic     #99                 // Field DEFAULT_INSTANCE:Ltechnology/dice/dicewhere/lineprocessing/serializers/protobuf/IPInformationProto$IpInformationProto;
       3: areturn

  protected com.google.protobuf.Message$Builder newBuilderForType(com.google.protobuf.GeneratedMessageV3$BuilderParent);
    Code:
       0: aload_0
       1: aload_1
       2: invokevirtual #104                // Method newBuilderForType:(Lcom/google/protobuf/GeneratedMessageV3$BuilderParent;)Ltechnology/dice/dicewhere/lineprocessing/serializers/protobuf/IPInformationProto$IpInformationProto$Builder;
       5: areturn

  public com.google.protobuf.Message$Builder toBuilder();
    Code:
       0: aload_0
       1: invokevirtual #100                // Method toBuilder:()Ltechnology/dice/dicewhere/lineprocessing/serializers/protobuf/IPInformationProto$IpInformationProto$Builder;
       4: areturn

  public com.google.protobuf.Message$Builder newBuilderForType();
    Code:
       0: aload_0
       1: invokevirtual #105                // Method newBuilderForType:()Ltechnology/dice/dicewhere/lineprocessing/serializers/protobuf/IPInformationProto$IpInformationProto$Builder;
       4: areturn

  public com.google.protobuf.MessageLite$Builder toBuilder();
    Code:
       0: aload_0
       1: invokevirtual #100                // Method toBuilder:()Ltechnology/dice/dicewhere/lineprocessing/serializers/protobuf/IPInformationProto$IpInformationProto$Builder;
       4: areturn

  public com.google.protobuf.MessageLite$Builder newBuilderForType();
    Code:
       0: aload_0
       1: invokevirtual #105                // Method newBuilderForType:()Ltechnology/dice/dicewhere/lineprocessing/serializers/protobuf/IPInformationProto$IpInformationProto$Builder;
       4: areturn

  public com.google.protobuf.MessageLite getDefaultInstanceForType();
    Code:
       0: aload_0
       1: invokevirtual #106                // Method getDefaultInstanceForType:()Ltechnology/dice/dicewhere/lineprocessing/serializers/protobuf/IPInformationProto$IpInformationProto;
       4: areturn

  public com.google.protobuf.Message getDefaultInstanceForType();
    Code:
       0: aload_0
       1: invokevirtual #106                // Method getDefaultInstanceForType:()Ltechnology/dice/dicewhere/lineprocessing/serializers/protobuf/IPInformationProto$IpInformationProto;
       4: areturn

  static boolean access$400();
    Code:
       0: getstatic     #16                 // Field alwaysUseFieldBuilders:Z
       3: ireturn

  technology.dice.dicewhere.lineprocessing.serializers.protobuf.IPInformationProto$IpInformationProto(com.google.protobuf.GeneratedMessageV3$Builder, technology.dice.dicewhere.lineprocessing.serializers.protobuf.IPInformationProto$1);
    Code:
       0: aload_0
       1: aload_1
       2: invokespecial #15                 // Method "<init>":(Lcom/google/protobuf/GeneratedMessageV3$Builder;)V
       5: return

  static java.lang.Object access$602(technology.dice.dicewhere.lineprocessing.serializers.protobuf.IPInformationProto$IpInformationProto, java.lang.Object);
    Code:
       0: aload_0
       1: aload_1
       2: dup_x1
       3: putfield      #14                 // Field geonameId_:Ljava/lang/Object;
       6: areturn

  static java.lang.Object access$702(technology.dice.dicewhere.lineprocessing.serializers.protobuf.IPInformationProto$IpInformationProto, java.lang.Object);
    Code:
       0: aload_0
       1: aload_1
       2: dup_x1
       3: putfield      #13                 // Field city_:Ljava/lang/Object;
       6: areturn

  static java.lang.Object access$802(technology.dice.dicewhere.lineprocessing.serializers.protobuf.IPInformationProto$IpInformationProto, java.lang.Object);
    Code:
       0: aload_0
       1: aload_1
       2: dup_x1
       3: putfield      #12                 // Field leastSpecificDivision_:Ljava/lang/Object;
       6: areturn

  static java.lang.Object access$902(technology.dice.dicewhere.lineprocessing.serializers.protobuf.IPInformationProto$IpInformationProto, java.lang.Object);
    Code:
       0: aload_0
       1: aload_1
       2: dup_x1
       3: putfield      #11                 // Field mostSpecificDivision_:Ljava/lang/Object;
       6: areturn

  static java.lang.Object access$1002(technology.dice.dicewhere.lineprocessing.serializers.protobuf.IPInformationProto$IpInformationProto, java.lang.Object);
    Code:
       0: aload_0
       1: aload_1
       2: dup_x1
       3: putfield      #10                 // Field postcode_:Ljava/lang/Object;
       6: areturn

  static java.lang.Object access$1102(technology.dice.dicewhere.lineprocessing.serializers.protobuf.IPInformationProto$IpInformationProto, java.lang.Object);
    Code:
       0: aload_0
       1: aload_1
       2: dup_x1
       3: putfield      #9                  // Field countryCodeAlpha2_:Ljava/lang/Object;
       6: areturn

  static com.google.protobuf.ByteString access$1202(technology.dice.dicewhere.lineprocessing.serializers.protobuf.IPInformationProto$IpInformationProto, com.google.protobuf.ByteString);
    Code:
       0: aload_0
       1: aload_1
       2: dup_x1
       3: putfield      #8                  // Field startOfRange_:Lcom/google/protobuf/ByteString;
       6: areturn

  static com.google.protobuf.ByteString access$1302(technology.dice.dicewhere.lineprocessing.serializers.protobuf.IPInformationProto$IpInformationProto, com.google.protobuf.ByteString);
    Code:
       0: aload_0
       1: aload_1
       2: dup_x1
       3: putfield      #7                  // Field endOfRange_:Lcom/google/protobuf/ByteString;
       6: areturn

  static java.lang.Object access$1402(technology.dice.dicewhere.lineprocessing.serializers.protobuf.IPInformationProto$IpInformationProto, java.lang.Object);
    Code:
       0: aload_0
       1: aload_1
       2: dup_x1
       3: putfield      #6                  // Field originalLine_:Ljava/lang/Object;
       6: areturn

  static int access$1502(technology.dice.dicewhere.lineprocessing.serializers.protobuf.IPInformationProto$IpInformationProto, int);
    Code:
       0: aload_0
       1: iload_1
       2: dup_x1
       3: putfield      #5                  // Field isVpn_:I
       6: ireturn

  static java.lang.Object access$600(technology.dice.dicewhere.lineprocessing.serializers.protobuf.IPInformationProto$IpInformationProto);
    Code:
       0: aload_0
       1: getfield      #14                 // Field geonameId_:Ljava/lang/Object;
       4: areturn

  static java.lang.Object access$700(technology.dice.dicewhere.lineprocessing.serializers.protobuf.IPInformationProto$IpInformationProto);
    Code:
       0: aload_0
       1: getfield      #13                 // Field city_:Ljava/lang/Object;
       4: areturn

  static java.lang.Object access$800(technology.dice.dicewhere.lineprocessing.serializers.protobuf.IPInformationProto$IpInformationProto);
    Code:
       0: aload_0
       1: getfield      #12                 // Field leastSpecificDivision_:Ljava/lang/Object;
       4: areturn

  static java.lang.Object access$900(technology.dice.dicewhere.lineprocessing.serializers.protobuf.IPInformationProto$IpInformationProto);
    Code:
       0: aload_0
       1: getfield      #11                 // Field mostSpecificDivision_:Ljava/lang/Object;
       4: areturn

  static java.lang.Object access$1000(technology.dice.dicewhere.lineprocessing.serializers.protobuf.IPInformationProto$IpInformationProto);
    Code:
       0: aload_0
       1: getfield      #10                 // Field postcode_:Ljava/lang/Object;
       4: areturn

  static java.lang.Object access$1100(technology.dice.dicewhere.lineprocessing.serializers.protobuf.IPInformationProto$IpInformationProto);
    Code:
       0: aload_0
       1: getfield      #9                  // Field countryCodeAlpha2_:Ljava/lang/Object;
       4: areturn

  static java.lang.Object access$1400(technology.dice.dicewhere.lineprocessing.serializers.protobuf.IPInformationProto$IpInformationProto);
    Code:
       0: aload_0
       1: getfield      #6                  // Field originalLine_:Ljava/lang/Object;
       4: areturn

  static int access$1500(technology.dice.dicewhere.lineprocessing.serializers.protobuf.IPInformationProto$IpInformationProto);
    Code:
       0: aload_0
       1: getfield      #5                  // Field isVpn_:I
       4: ireturn

  static com.google.protobuf.UnknownFieldSet access$1600(technology.dice.dicewhere.lineprocessing.serializers.protobuf.IPInformationProto$IpInformationProto);
    Code:
       0: aload_0
       1: getfield      #4                  // Field unknownFields:Lcom/google/protobuf/UnknownFieldSet;
       4: areturn

  static com.google.protobuf.Parser access$1700();
    Code:
       0: getstatic     #3                  // Field PARSER:Lcom/google/protobuf/Parser;
       3: areturn

  static void access$1800(com.google.protobuf.ByteString) throws java.lang.IllegalArgumentException;
    Code:
       0: aload_0
       1: invokestatic  #2                  // Method checkByteStringIsUtf8:(Lcom/google/protobuf/ByteString;)V
       4: return

  static void access$1900(com.google.protobuf.ByteString) throws java.lang.IllegalArgumentException;
    Code:
       0: aload_0
       1: invokestatic  #2                  // Method checkByteStringIsUtf8:(Lcom/google/protobuf/ByteString;)V
       4: return

  static void access$2000(com.google.protobuf.ByteString) throws java.lang.IllegalArgumentException;
    Code:
       0: aload_0
       1: invokestatic  #2                  // Method checkByteStringIsUtf8:(Lcom/google/protobuf/ByteString;)V
       4: return

  static void access$2100(com.google.protobuf.ByteString) throws java.lang.IllegalArgumentException;
    Code:
       0: aload_0
       1: invokestatic  #2                  // Method checkByteStringIsUtf8:(Lcom/google/protobuf/ByteString;)V
       4: return

  static void access$2200(com.google.protobuf.ByteString) throws java.lang.IllegalArgumentException;
    Code:
       0: aload_0
       1: invokestatic  #2                  // Method checkByteStringIsUtf8:(Lcom/google/protobuf/ByteString;)V
       4: return

  static void access$2300(com.google.protobuf.ByteString) throws java.lang.IllegalArgumentException;
    Code:
       0: aload_0
       1: invokestatic  #2                  // Method checkByteStringIsUtf8:(Lcom/google/protobuf/ByteString;)V
       4: return

  static void access$2400(com.google.protobuf.ByteString) throws java.lang.IllegalArgumentException;
    Code:
       0: aload_0
       1: invokestatic  #2                  // Method checkByteStringIsUtf8:(Lcom/google/protobuf/ByteString;)V
       4: return

  technology.dice.dicewhere.lineprocessing.serializers.protobuf.IPInformationProto$IpInformationProto(com.google.protobuf.CodedInputStream, com.google.protobuf.ExtensionRegistryLite, technology.dice.dicewhere.lineprocessing.serializers.protobuf.IPInformationProto$1) throws com.google.protobuf.InvalidProtocolBufferException;
    Code:
       0: aload_0
       1: aload_1
       2: aload_2
       3: invokespecial #1                  // Method "<init>":(Lcom/google/protobuf/CodedInputStream;Lcom/google/protobuf/ExtensionRegistryLite;)V
       6: return

  static {};
    Code:
       0: new           #39                 // class technology/dice/dicewhere/lineprocessing/serializers/protobuf/IPInformationProto$IpInformationProto
       3: dup
       4: invokespecial #22                 // Method "<init>":()V
       7: putstatic     #99                 // Field DEFAULT_INSTANCE:Ltechnology/dice/dicewhere/lineprocessing/serializers/protobuf/IPInformationProto$IpInformationProto;
      10: new           #107                // class technology/dice/dicewhere/lineprocessing/serializers/protobuf/IPInformationProto$IpInformationProto$1
      13: dup
      14: invokespecial #108                // Method technology/dice/dicewhere/lineprocessing/serializers/protobuf/IPInformationProto$IpInformationProto$1."<init>":()V
      17: putstatic     #3                  // Field PARSER:Lcom/google/protobuf/Parser;
      20: return
}
