Compiled from "DefaultTaskExecutorType.java"
public final class org.apache.camel.component.jms.DefaultTaskExecutorType extends java.lang.Enum<org.apache.camel.component.jms.DefaultTaskExecutorType> {
  public static final org.apache.camel.component.jms.DefaultTaskExecutorType ThreadPool;

  public static final org.apache.camel.component.jms.DefaultTaskExecutorType SimpleAsync;

  private static final org.apache.camel.component.jms.DefaultTaskExecutorType[] $VALUES;

  public static org.apache.camel.component.jms.DefaultTaskExecutorType[] values();
    Code:
       0: getstatic     #1                  // Field $VALUES:[Lorg/apache/camel/component/jms/DefaultTaskExecutorType;
       3: invokevirtual #2                  // Method "[Lorg/apache/camel/component/jms/DefaultTaskExecutorType;".clone:()Ljava/lang/Object;
       6: checkcast     #3                  // class "[Lorg/apache/camel/component/jms/DefaultTaskExecutorType;"
       9: areturn

  public static org.apache.camel.component.jms.DefaultTaskExecutorType valueOf(java.lang.String);
    Code:
       0: ldc_w         #4                  // class org/apache/camel/component/jms/DefaultTaskExecutorType
       3: aload_0
       4: invokestatic  #5                  // Method java/lang/Enum.valueOf:(Ljava/lang/Class;Ljava/lang/String;)Ljava/lang/Enum;
       7: checkcast     #4                  // class org/apache/camel/component/jms/DefaultTaskExecutorType
      10: areturn

  private org.apache.camel.component.jms.DefaultTaskExecutorType();
    Code:
       0: aload_0
       1: aload_1
       2: iload_2
       3: invokespecial #6                  // Method java/lang/Enum."<init>":(Ljava/lang/String;I)V
       6: return

  static {};
    Code:
       0: new           #4                  // class org/apache/camel/component/jms/DefaultTaskExecutorType
       3: dup
       4: ldc           #7                  // String ThreadPool
       6: iconst_0
       7: invokespecial #8                  // Method "<init>":(Ljava/lang/String;I)V
      10: putstatic     #9                  // Field ThreadPool:Lorg/apache/camel/component/jms/DefaultTaskExecutorType;
      13: new           #4                  // class org/apache/camel/component/jms/DefaultTaskExecutorType
      16: dup
      17: ldc           #10                 // String SimpleAsync
      19: iconst_1
      20: invokespecial #8                  // Method "<init>":(Ljava/lang/String;I)V
      23: putstatic     #11                 // Field SimpleAsync:Lorg/apache/camel/component/jms/DefaultTaskExecutorType;
      26: iconst_2
      27: anewarray     #4                  // class org/apache/camel/component/jms/DefaultTaskExecutorType
      30: dup
      31: iconst_0
      32: getstatic     #9                  // Field ThreadPool:Lorg/apache/camel/component/jms/DefaultTaskExecutorType;
      35: aastore
      36: dup
      37: iconst_1
      38: getstatic     #11                 // Field SimpleAsync:Lorg/apache/camel/component/jms/DefaultTaskExecutorType;
      41: aastore
      42: putstatic     #1                  // Field $VALUES:[Lorg/apache/camel/component/jms/DefaultTaskExecutorType;
      45: return
}
