Compiled from "JmsBinding.java"
public class org.apache.camel.component.jms.JmsBinding {
  private static final org.slf4j.Logger LOG;

  private final org.apache.camel.component.jms.JmsEndpoint endpoint;

  private final org.apache.camel.spi.HeaderFilterStrategy headerFilterStrategy;

  private final org.apache.camel.component.jms.JmsKeyFormatStrategy jmsKeyFormatStrategy;

  public org.apache.camel.component.jms.JmsBinding();
    Code:
       0: aload_0
       1: invokespecial #1                  // Method java/lang/Object."<init>":()V
       4: aload_0
       5: aconst_null
       6: putfield      #2                  // Field endpoint:Lorg/apache/camel/component/jms/JmsEndpoint;
       9: aload_0
      10: new           #3                  // class org/apache/camel/component/jms/JmsHeaderFilterStrategy
      13: dup
      14: iconst_0
      15: invokespecial #4                  // Method org/apache/camel/component/jms/JmsHeaderFilterStrategy."<init>":(Z)V
      18: putfield      #5                  // Field headerFilterStrategy:Lorg/apache/camel/spi/HeaderFilterStrategy;
      21: aload_0
      22: new           #6                  // class org/apache/camel/component/jms/DefaultJmsKeyFormatStrategy
      25: dup
      26: invokespecial #7                  // Method org/apache/camel/component/jms/DefaultJmsKeyFormatStrategy."<init>":()V
      29: putfield      #8                  // Field jmsKeyFormatStrategy:Lorg/apache/camel/component/jms/JmsKeyFormatStrategy;
      32: return

  public org.apache.camel.component.jms.JmsBinding(org.apache.camel.component.jms.JmsEndpoint);
    Code:
       0: aload_0
       1: invokespecial #1                  // Method java/lang/Object."<init>":()V
       4: aload_0
       5: aload_1
       6: putfield      #2                  // Field endpoint:Lorg/apache/camel/component/jms/JmsEndpoint;
       9: aload_1
      10: invokevirtual #9                  // Method org/apache/camel/component/jms/JmsEndpoint.getHeaderFilterStrategy:()Lorg/apache/camel/spi/HeaderFilterStrategy;
      13: ifnull        27
      16: aload_0
      17: aload_1
      18: invokevirtual #9                  // Method org/apache/camel/component/jms/JmsEndpoint.getHeaderFilterStrategy:()Lorg/apache/camel/spi/HeaderFilterStrategy;
      21: putfield      #5                  // Field headerFilterStrategy:Lorg/apache/camel/spi/HeaderFilterStrategy;
      24: goto          42
      27: aload_0
      28: new           #3                  // class org/apache/camel/component/jms/JmsHeaderFilterStrategy
      31: dup
      32: aload_1
      33: invokevirtual #10                 // Method org/apache/camel/component/jms/JmsEndpoint.isIncludeAllJMSXProperties:()Z
      36: invokespecial #4                  // Method org/apache/camel/component/jms/JmsHeaderFilterStrategy."<init>":(Z)V
      39: putfield      #5                  // Field headerFilterStrategy:Lorg/apache/camel/spi/HeaderFilterStrategy;
      42: aload_1
      43: invokevirtual #11                 // Method org/apache/camel/component/jms/JmsEndpoint.getJmsKeyFormatStrategy:()Lorg/apache/camel/component/jms/JmsKeyFormatStrategy;
      46: ifnull        60
      49: aload_0
      50: aload_1
      51: invokevirtual #11                 // Method org/apache/camel/component/jms/JmsEndpoint.getJmsKeyFormatStrategy:()Lorg/apache/camel/component/jms/JmsKeyFormatStrategy;
      54: putfield      #8                  // Field jmsKeyFormatStrategy:Lorg/apache/camel/component/jms/JmsKeyFormatStrategy;
      57: goto          71
      60: aload_0
      61: new           #6                  // class org/apache/camel/component/jms/DefaultJmsKeyFormatStrategy
      64: dup
      65: invokespecial #7                  // Method org/apache/camel/component/jms/DefaultJmsKeyFormatStrategy."<init>":()V
      68: putfield      #8                  // Field jmsKeyFormatStrategy:Lorg/apache/camel/component/jms/JmsKeyFormatStrategy;
      71: return

  public java.lang.Object extractBodyFromJms(org.apache.camel.Exchange, javax.jms.Message);
    Code:
       0: aload_0
       1: getfield      #2                  // Field endpoint:Lorg/apache/camel/component/jms/JmsEndpoint;
       4: ifnull        60
       7: aload_0
       8: getfield      #2                  // Field endpoint:Lorg/apache/camel/component/jms/JmsEndpoint;
      11: invokevirtual #12                 // Method org/apache/camel/component/jms/JmsEndpoint.getMessageConverter:()Lorg/springframework/jms/support/converter/MessageConverter;
      14: ifnull        60
      17: getstatic     #13                 // Field LOG:Lorg/slf4j/Logger;
      20: invokeinterface #14,  1           // InterfaceMethod org/slf4j/Logger.isTraceEnabled:()Z
      25: ifeq          46
      28: getstatic     #13                 // Field LOG:Lorg/slf4j/Logger;
      31: ldc           #15                 // String Extracting body using a custom MessageConverter: {} from JMS message: {}
      33: aload_0
      34: getfield      #2                  // Field endpoint:Lorg/apache/camel/component/jms/JmsEndpoint;
      37: invokevirtual #12                 // Method org/apache/camel/component/jms/JmsEndpoint.getMessageConverter:()Lorg/springframework/jms/support/converter/MessageConverter;
      40: aload_2
      41: invokeinterface #16,  4           // InterfaceMethod org/slf4j/Logger.trace:(Ljava/lang/String;Ljava/lang/Object;Ljava/lang/Object;)V
      46: aload_0
      47: getfield      #2                  // Field endpoint:Lorg/apache/camel/component/jms/JmsEndpoint;
      50: invokevirtual #12                 // Method org/apache/camel/component/jms/JmsEndpoint.getMessageConverter:()Lorg/springframework/jms/support/converter/MessageConverter;
      53: aload_2
      54: invokeinterface #17,  2           // InterfaceMethod org/springframework/jms/support/converter/MessageConverter.fromMessage:(Ljavax/jms/Message;)Ljava/lang/Object;
      59: areturn
      60: aload_0
      61: getfield      #2                  // Field endpoint:Lorg/apache/camel/component/jms/JmsEndpoint;
      64: ifnull        93
      67: aload_0
      68: getfield      #2                  // Field endpoint:Lorg/apache/camel/component/jms/JmsEndpoint;
      71: invokevirtual #18                 // Method org/apache/camel/component/jms/JmsEndpoint.getConfiguration:()Lorg/apache/camel/component/jms/JmsConfiguration;
      74: invokevirtual #19                 // Method org/apache/camel/component/jms/JmsConfiguration.isMapJmsMessage:()Z
      77: ifne          93
      80: getstatic     #13                 // Field LOG:Lorg/slf4j/Logger;
      83: ldc           #20                 // String Option map JMS message is false so using JMS message as body: {}
      85: aload_2
      86: invokeinterface #21,  3           // InterfaceMethod org/slf4j/Logger.trace:(Ljava/lang/String;Ljava/lang/Object;)V
      91: aload_2
      92: areturn
      93: aload_2
      94: instanceof    #22                 // class javax/jms/ObjectMessage
      97: ifeq          164
     100: getstatic     #13                 // Field LOG:Lorg/slf4j/Logger;
     103: ldc           #23                 // String Extracting body as a ObjectMessage from JMS message: {}
     105: aload_2
     106: invokeinterface #21,  3           // InterfaceMethod org/slf4j/Logger.trace:(Ljava/lang/String;Ljava/lang/Object;)V
     111: aload_2
     112: checkcast     #22                 // class javax/jms/ObjectMessage
     115: astore_3
     116: aload_3
     117: invokeinterface #24,  1           // InterfaceMethod javax/jms/ObjectMessage.getObject:()Ljava/io/Serializable;
     122: astore        4
     124: aload         4
     126: instanceof    #25                 // class org/apache/camel/impl/DefaultExchangeHolder
     129: ifeq          157
     132: aload         4
     134: checkcast     #25                 // class org/apache/camel/impl/DefaultExchangeHolder
     137: astore        5
     139: aload_1
     140: aload         5
     142: invokestatic  #26                 // Method org/apache/camel/impl/DefaultExchangeHolder.unmarshal:(Lorg/apache/camel/Exchange;Lorg/apache/camel/impl/DefaultExchangeHolder;)V
     145: aload_1
     146: invokeinterface #27,  1           // InterfaceMethod org/apache/camel/Exchange.getIn:()Lorg/apache/camel/Message;
     151: invokeinterface #28,  1           // InterfaceMethod org/apache/camel/Message.getBody:()Ljava/lang/Object;
     156: areturn
     157: aload_3
     158: invokeinterface #24,  1           // InterfaceMethod javax/jms/ObjectMessage.getObject:()Ljava/io/Serializable;
     163: areturn
     164: aload_2
     165: instanceof    #29                 // class javax/jms/TextMessage
     168: ifeq          194
     171: getstatic     #13                 // Field LOG:Lorg/slf4j/Logger;
     174: ldc           #30                 // String Extracting body as a TextMessage from JMS message: {}
     176: aload_2
     177: invokeinterface #21,  3           // InterfaceMethod org/slf4j/Logger.trace:(Ljava/lang/String;Ljava/lang/Object;)V
     182: aload_2
     183: checkcast     #29                 // class javax/jms/TextMessage
     186: astore_3
     187: aload_3
     188: invokeinterface #31,  1           // InterfaceMethod javax/jms/TextMessage.getText:()Ljava/lang/String;
     193: areturn
     194: aload_2
     195: instanceof    #32                 // class javax/jms/MapMessage
     198: ifeq          221
     201: getstatic     #13                 // Field LOG:Lorg/slf4j/Logger;
     204: ldc           #33                 // String Extracting body as a MapMessage from JMS message: {}
     206: aload_2
     207: invokeinterface #21,  3           // InterfaceMethod org/slf4j/Logger.trace:(Ljava/lang/String;Ljava/lang/Object;)V
     212: aload_0
     213: aload_2
     214: checkcast     #32                 // class javax/jms/MapMessage
     217: invokevirtual #34                 // Method createMapFromMapMessage:(Ljavax/jms/MapMessage;)Ljava/util/Map;
     220: areturn
     221: aload_2
     222: instanceof    #35                 // class javax/jms/BytesMessage
     225: ifeq          248
     228: getstatic     #13                 // Field LOG:Lorg/slf4j/Logger;
     231: ldc           #36                 // String Extracting body as a BytesMessage from JMS message: {}
     233: aload_2
     234: invokeinterface #21,  3           // InterfaceMethod org/slf4j/Logger.trace:(Ljava/lang/String;Ljava/lang/Object;)V
     239: aload_0
     240: aload_2
     241: checkcast     #35                 // class javax/jms/BytesMessage
     244: invokevirtual #37                 // Method createByteArrayFromBytesMessage:(Ljavax/jms/BytesMessage;)[B
     247: areturn
     248: aload_2
     249: instanceof    #38                 // class javax/jms/StreamMessage
     252: ifeq          268
     255: getstatic     #13                 // Field LOG:Lorg/slf4j/Logger;
     258: ldc           #39                 // String Extracting body as a StreamMessage from JMS message: {}
     260: aload_2
     261: invokeinterface #21,  3           // InterfaceMethod org/slf4j/Logger.trace:(Ljava/lang/String;Ljava/lang/Object;)V
     266: aload_2
     267: areturn
     268: aconst_null
     269: areturn
     270: astore_3
     271: new           #41                 // class org/apache/camel/RuntimeCamelException
     274: dup
     275: new           #42                 // class java/lang/StringBuilder
     278: dup
     279: invokespecial #43                 // Method java/lang/StringBuilder."<init>":()V
     282: ldc           #44                 // String Failed to extract body due to:
     284: invokevirtual #45                 // Method java/lang/StringBuilder.append:(Ljava/lang/String;)Ljava/lang/StringBuilder;
     287: aload_3
     288: invokevirtual #46                 // Method java/lang/StringBuilder.append:(Ljava/lang/Object;)Ljava/lang/StringBuilder;
     291: ldc           #47                 // String . Message:
     293: invokevirtual #45                 // Method java/lang/StringBuilder.append:(Ljava/lang/String;)Ljava/lang/StringBuilder;
     296: aload_2
     297: invokevirtual #46                 // Method java/lang/StringBuilder.append:(Ljava/lang/Object;)Ljava/lang/StringBuilder;
     300: invokevirtual #48                 // Method java/lang/StringBuilder.toString:()Ljava/lang/String;
     303: aload_3
     304: invokespecial #49                 // Method org/apache/camel/RuntimeCamelException."<init>":(Ljava/lang/String;Ljava/lang/Throwable;)V
     307: athrow
    Exception table:
       from    to  target type
           0    59   270   Class javax/jms/JMSException
          60    92   270   Class javax/jms/JMSException
          93   156   270   Class javax/jms/JMSException
         157   163   270   Class javax/jms/JMSException
         164   193   270   Class javax/jms/JMSException
         194   220   270   Class javax/jms/JMSException
         221   247   270   Class javax/jms/JMSException
         248   267   270   Class javax/jms/JMSException
         268   269   270   Class javax/jms/JMSException

  public java.util.Map<java.lang.String, java.lang.Object> extractHeadersFromJms(javax.jms.Message, org.apache.camel.Exchange);
    Code:
       0: new           #50                 // class java/util/HashMap
       3: dup
       4: invokespecial #51                 // Method java/util/HashMap."<init>":()V
       7: astore_3
       8: aload_1
       9: ifnull        346
      12: aload_3
      13: ldc           #52                 // String JMSCorrelationID
      15: aload_1
      16: invokeinterface #53,  1           // InterfaceMethod javax/jms/Message.getJMSCorrelationID:()Ljava/lang/String;
      21: invokeinterface #54,  3           // InterfaceMethod java/util/Map.put:(Ljava/lang/Object;Ljava/lang/Object;)Ljava/lang/Object;
      26: pop
      27: aload_3
      28: ldc           #55                 // String JMSDeliveryMode
      30: aload_1
      31: invokeinterface #56,  1           // InterfaceMethod javax/jms/Message.getJMSDeliveryMode:()I
      36: invokestatic  #57                 // Method java/lang/Integer.valueOf:(I)Ljava/lang/Integer;
      39: invokeinterface #54,  3           // InterfaceMethod java/util/Map.put:(Ljava/lang/Object;Ljava/lang/Object;)Ljava/lang/Object;
      44: pop
      45: aload_3
      46: ldc           #58                 // String JMSDestination
      48: aload_1
      49: invokeinterface #59,  1           // InterfaceMethod javax/jms/Message.getJMSDestination:()Ljavax/jms/Destination;
      54: invokeinterface #54,  3           // InterfaceMethod java/util/Map.put:(Ljava/lang/Object;Ljava/lang/Object;)Ljava/lang/Object;
      59: pop
      60: aload_3
      61: ldc           #60                 // String JMSExpiration
      63: aload_1
      64: invokeinterface #61,  1           // InterfaceMethod javax/jms/Message.getJMSExpiration:()J
      69: invokestatic  #62                 // Method java/lang/Long.valueOf:(J)Ljava/lang/Long;
      72: invokeinterface #54,  3           // InterfaceMethod java/util/Map.put:(Ljava/lang/Object;Ljava/lang/Object;)Ljava/lang/Object;
      77: pop
      78: aload_3
      79: ldc           #63                 // String JMSMessageID
      81: aload_1
      82: invokeinterface #64,  1           // InterfaceMethod javax/jms/Message.getJMSMessageID:()Ljava/lang/String;
      87: invokeinterface #54,  3           // InterfaceMethod java/util/Map.put:(Ljava/lang/Object;Ljava/lang/Object;)Ljava/lang/Object;
      92: pop
      93: aload_3
      94: ldc           #65                 // String JMSPriority
      96: aload_1
      97: invokeinterface #66,  1           // InterfaceMethod javax/jms/Message.getJMSPriority:()I
     102: invokestatic  #57                 // Method java/lang/Integer.valueOf:(I)Ljava/lang/Integer;
     105: invokeinterface #54,  3           // InterfaceMethod java/util/Map.put:(Ljava/lang/Object;Ljava/lang/Object;)Ljava/lang/Object;
     110: pop
     111: aload_3
     112: ldc           #67                 // String JMSRedelivered
     114: aload_1
     115: invokeinterface #68,  1           // InterfaceMethod javax/jms/Message.getJMSRedelivered:()Z
     120: invokestatic  #69                 // Method java/lang/Boolean.valueOf:(Z)Ljava/lang/Boolean;
     123: invokeinterface #54,  3           // InterfaceMethod java/util/Map.put:(Ljava/lang/Object;Ljava/lang/Object;)Ljava/lang/Object;
     128: pop
     129: aload_3
     130: ldc           #70                 // String JMSTimestamp
     132: aload_1
     133: invokeinterface #71,  1           // InterfaceMethod javax/jms/Message.getJMSTimestamp:()J
     138: invokestatic  #62                 // Method java/lang/Long.valueOf:(J)Ljava/lang/Long;
     141: invokeinterface #54,  3           // InterfaceMethod java/util/Map.put:(Ljava/lang/Object;Ljava/lang/Object;)Ljava/lang/Object;
     146: pop
     147: aload_3
     148: ldc           #72                 // String JMSReplyTo
     150: aload_1
     151: invokestatic  #73                 // Method org/apache/camel/component/jms/JmsMessageHelper.getJMSReplyTo:(Ljavax/jms/Message;)Ljavax/jms/Destination;
     154: invokeinterface #54,  3           // InterfaceMethod java/util/Map.put:(Ljava/lang/Object;Ljava/lang/Object;)Ljava/lang/Object;
     159: pop
     160: aload_3
     161: ldc           #74                 // String JMSType
     163: aload_1
     164: invokestatic  #75                 // Method org/apache/camel/component/jms/JmsMessageHelper.getJMSType:(Ljavax/jms/Message;)Ljava/lang/String;
     167: invokeinterface #54,  3           // InterfaceMethod java/util/Map.put:(Ljava/lang/Object;Ljava/lang/Object;)Ljava/lang/Object;
     172: pop
     173: aload_3
     174: ldc           #76                 // String JMSXGroupID
     176: aload_1
     177: ldc           #76                 // String JMSXGroupID
     179: invokeinterface #77,  2           // InterfaceMethod javax/jms/Message.getStringProperty:(Ljava/lang/String;)Ljava/lang/String;
     184: invokeinterface #54,  3           // InterfaceMethod java/util/Map.put:(Ljava/lang/Object;Ljava/lang/Object;)Ljava/lang/Object;
     189: pop
     190: aload_3
     191: ldc           #78                 // String JMSXUserID
     193: aload_1
     194: ldc           #78                 // String JMSXUserID
     196: invokeinterface #77,  2           // InterfaceMethod javax/jms/Message.getStringProperty:(Ljava/lang/String;)Ljava/lang/String;
     201: invokeinterface #54,  3           // InterfaceMethod java/util/Map.put:(Ljava/lang/Object;Ljava/lang/Object;)Ljava/lang/Object;
     206: pop
     207: goto          222
     210: astore        4
     212: new           #41                 // class org/apache/camel/RuntimeCamelException
     215: dup
     216: aload         4
     218: invokespecial #79                 // Method org/apache/camel/RuntimeCamelException."<init>":(Ljava/lang/Throwable;)V
     221: athrow
     222: aload_1
     223: invokeinterface #80,  1           // InterfaceMethod javax/jms/Message.getPropertyNames:()Ljava/util/Enumeration;
     228: astore        4
     230: goto          245
     233: astore        5
     235: new           #41                 // class org/apache/camel/RuntimeCamelException
     238: dup
     239: aload         5
     241: invokespecial #79                 // Method org/apache/camel/RuntimeCamelException."<init>":(Ljava/lang/Throwable;)V
     244: athrow
     245: aload         4
     247: invokeinterface #81,  1           // InterfaceMethod java/util/Enumeration.hasMoreElements:()Z
     252: ifeq          346
     255: aload         4
     257: invokeinterface #82,  1           // InterfaceMethod java/util/Enumeration.nextElement:()Ljava/lang/Object;
     262: invokevirtual #83                 // Method java/lang/Object.toString:()Ljava/lang/String;
     265: astore        5
     267: aload_1
     268: aload         5
     270: invokestatic  #84                 // Method org/apache/camel/component/jms/JmsMessageHelper.getProperty:(Ljavax/jms/Message;Ljava/lang/String;)Ljava/lang/Object;
     273: astore        6
     275: aload_0
     276: getfield      #5                  // Field headerFilterStrategy:Lorg/apache/camel/spi/HeaderFilterStrategy;
     279: ifnull        302
     282: aload_0
     283: getfield      #5                  // Field headerFilterStrategy:Lorg/apache/camel/spi/HeaderFilterStrategy;
     286: aload         5
     288: aload         6
     290: aload_2
     291: invokeinterface #85,  4           // InterfaceMethod org/apache/camel/spi/HeaderFilterStrategy.applyFilterToExternalHeaders:(Ljava/lang/String;Ljava/lang/Object;Lorg/apache/camel/Exchange;)Z
     296: ifeq          302
     299: goto          245
     302: aload_0
     303: getfield      #8                  // Field jmsKeyFormatStrategy:Lorg/apache/camel/component/jms/JmsKeyFormatStrategy;
     306: aload         5
     308: invokeinterface #86,  2           // InterfaceMethod org/apache/camel/component/jms/JmsKeyFormatStrategy.decodeKey:(Ljava/lang/String;)Ljava/lang/String;
     313: astore        7
     315: aload_3
     316: aload         7
     318: aload         6
     320: invokeinterface #54,  3           // InterfaceMethod java/util/Map.put:(Ljava/lang/Object;Ljava/lang/Object;)Ljava/lang/Object;
     325: pop
     326: goto          343
     329: astore        6
     331: new           #41                 // class org/apache/camel/RuntimeCamelException
     334: dup
     335: aload         5
     337: aload         6
     339: invokespecial #49                 // Method org/apache/camel/RuntimeCamelException."<init>":(Ljava/lang/String;Ljava/lang/Throwable;)V
     342: athrow
     343: goto          245
     346: aload_3
     347: areturn
    Exception table:
       from    to  target type
          12   207   210   Class javax/jms/JMSException
         222   230   233   Class javax/jms/JMSException
         267   299   329   Class javax/jms/JMSException
         302   326   329   Class javax/jms/JMSException

  public java.lang.Object getObjectProperty(javax.jms.Message, java.lang.String) throws javax.jms.JMSException;
    Code:
       0: aload_1
       1: aload_2
       2: invokeinterface #87,  2           // InterfaceMethod javax/jms/Message.getObjectProperty:(Ljava/lang/String;)Ljava/lang/Object;
       7: astore_3
       8: aload_3
       9: ifnonnull     33
      12: aload_0
      13: getfield      #8                  // Field jmsKeyFormatStrategy:Lorg/apache/camel/component/jms/JmsKeyFormatStrategy;
      16: aload_2
      17: invokeinterface #88,  2           // InterfaceMethod org/apache/camel/component/jms/JmsKeyFormatStrategy.encodeKey:(Ljava/lang/String;)Ljava/lang/String;
      22: astore        4
      24: aload_1
      25: aload         4
      27: invokeinterface #87,  2           // InterfaceMethod javax/jms/Message.getObjectProperty:(Ljava/lang/String;)Ljava/lang/Object;
      32: astore_3
      33: aload_3
      34: areturn

  protected byte[] createByteArrayFromBytesMessage(javax.jms.BytesMessage) throws javax.jms.JMSException;
    Code:
       0: aload_1
       1: invokeinterface #89,  1           // InterfaceMethod javax/jms/BytesMessage.getBodyLength:()J
       6: ldc2_w        #90                 // long 2147483647l
       9: lcmp
      10: ifle          34
      13: getstatic     #13                 // Field LOG:Lorg/slf4j/Logger;
      16: ldc           #92                 // String Length of BytesMessage is too long: {}
      18: aload_1
      19: invokeinterface #89,  1           // InterfaceMethod javax/jms/BytesMessage.getBodyLength:()J
      24: invokestatic  #62                 // Method java/lang/Long.valueOf:(J)Ljava/lang/Long;
      27: invokeinterface #93,  3           // InterfaceMethod org/slf4j/Logger.warn:(Ljava/lang/String;Ljava/lang/Object;)V
      32: aconst_null
      33: areturn
      34: aload_1
      35: invokeinterface #89,  1           // InterfaceMethod javax/jms/BytesMessage.getBodyLength:()J
      40: l2i
      41: newarray       byte
      43: astore_2
      44: aload_1
      45: aload_2
      46: invokeinterface #94,  2           // InterfaceMethod javax/jms/BytesMessage.readBytes:([B)I
      51: pop
      52: aload_2
      53: areturn

  public javax.jms.Message makeJmsMessage(org.apache.camel.Exchange, javax.jms.Session) throws javax.jms.JMSException;
    Code:
       0: aload_0
       1: aload_1
       2: aload_1
       3: invokeinterface #27,  1           // InterfaceMethod org/apache/camel/Exchange.getIn:()Lorg/apache/camel/Message;
       8: aload_2
       9: aconst_null
      10: invokevirtual #95                 // Method makeJmsMessage:(Lorg/apache/camel/Exchange;Lorg/apache/camel/Message;Ljavax/jms/Session;Ljava/lang/Exception;)Ljavax/jms/Message;
      13: areturn

  public javax.jms.Message makeJmsMessage(org.apache.camel.Exchange, org.apache.camel.Message, javax.jms.Session, java.lang.Exception) throws javax.jms.JMSException;
    Code:
       0: aconst_null
       1: astore        5
       3: aload_0
       4: getfield      #2                  // Field endpoint:Lorg/apache/camel/component/jms/JmsEndpoint;
       7: ifnull        27
      10: aload_0
      11: getfield      #2                  // Field endpoint:Lorg/apache/camel/component/jms/JmsEndpoint;
      14: invokevirtual #18                 // Method org/apache/camel/component/jms/JmsEndpoint.getConfiguration:()Lorg/apache/camel/component/jms/JmsConfiguration;
      17: invokevirtual #96                 // Method org/apache/camel/component/jms/JmsConfiguration.isAlwaysCopyMessage:()Z
      20: ifeq          27
      23: iconst_1
      24: goto          28
      27: iconst_0
      28: istore        6
      30: aload_0
      31: getfield      #2                  // Field endpoint:Lorg/apache/camel/component/jms/JmsEndpoint;
      34: ifnull        54
      37: aload_0
      38: getfield      #2                  // Field endpoint:Lorg/apache/camel/component/jms/JmsEndpoint;
      41: invokevirtual #18                 // Method org/apache/camel/component/jms/JmsEndpoint.getConfiguration:()Lorg/apache/camel/component/jms/JmsConfiguration;
      44: invokevirtual #97                 // Method org/apache/camel/component/jms/JmsConfiguration.isForceSendOriginalMessage:()Z
      47: ifeq          54
      50: iconst_1
      51: goto          55
      54: iconst_0
      55: istore        7
      57: iload         6
      59: ifne          265
      62: aload_2
      63: instanceof    #98                 // class org/apache/camel/component/jms/JmsMessage
      66: ifeq          265
      69: aload_2
      70: checkcast     #98                 // class org/apache/camel/component/jms/JmsMessage
      73: astore        8
      75: aload         8
      77: invokevirtual #99                 // Method org/apache/camel/component/jms/JmsMessage.shouldCreateNewMessage:()Z
      80: ifeq          88
      83: iload         7
      85: ifeq          265
      88: aload         8
      90: invokevirtual #100                // Method org/apache/camel/component/jms/JmsMessage.getJmsMessage:()Ljavax/jms/Message;
      93: astore        5
      95: iload         7
      97: ifne          265
     100: aload_0
     101: getfield      #2                  // Field endpoint:Lorg/apache/camel/component/jms/JmsEndpoint;
     104: ifnull        120
     107: aload_0
     108: getfield      #2                  // Field endpoint:Lorg/apache/camel/component/jms/JmsEndpoint;
     111: invokevirtual #18                 // Method org/apache/camel/component/jms/JmsEndpoint.getConfiguration:()Lorg/apache/camel/component/jms/JmsConfiguration;
     114: invokevirtual #101                // Method org/apache/camel/component/jms/JmsConfiguration.getJmsMessageType:()Lorg/apache/camel/component/jms/JmsMessageType;
     117: goto          121
     120: aconst_null
     121: astore        9
     123: aload         9
     125: ifnull        265
     128: aload         5
     130: ifnull        265
     133: aload         9
     135: getstatic     #102                // Field org/apache/camel/component/jms/JmsMessageType.Text:Lorg/apache/camel/component/jms/JmsMessageType;
     138: if_acmpne     160
     141: aload         5
     143: instanceof    #29                 // class javax/jms/TextMessage
     146: ifeq          154
     149: aload         5
     151: goto          155
     154: aconst_null
     155: astore        5
     157: goto          265
     160: aload         9
     162: getstatic     #103                // Field org/apache/camel/component/jms/JmsMessageType.Bytes:Lorg/apache/camel/component/jms/JmsMessageType;
     165: if_acmpne     187
     168: aload         5
     170: instanceof    #35                 // class javax/jms/BytesMessage
     173: ifeq          181
     176: aload         5
     178: goto          182
     181: aconst_null
     182: astore        5
     184: goto          265
     187: aload         9
     189: getstatic     #104                // Field org/apache/camel/component/jms/JmsMessageType.Map:Lorg/apache/camel/component/jms/JmsMessageType;
     192: if_acmpne     214
     195: aload         5
     197: instanceof    #32                 // class javax/jms/MapMessage
     200: ifeq          208
     203: aload         5
     205: goto          209
     208: aconst_null
     209: astore        5
     211: goto          265
     214: aload         9
     216: getstatic     #105                // Field org/apache/camel/component/jms/JmsMessageType.Object:Lorg/apache/camel/component/jms/JmsMessageType;
     219: if_acmpne     241
     222: aload         5
     224: instanceof    #22                 // class javax/jms/ObjectMessage
     227: ifeq          235
     230: aload         5
     232: goto          236
     235: aconst_null
     236: astore        5
     238: goto          265
     241: aload         9
     243: getstatic     #106                // Field org/apache/camel/component/jms/JmsMessageType.Stream:Lorg/apache/camel/component/jms/JmsMessageType;
     246: if_acmpne     265
     249: aload         5
     251: instanceof    #38                 // class javax/jms/StreamMessage
     254: ifeq          262
     257: aload         5
     259: goto          263
     262: aconst_null
     263: astore        5
     265: aload         5
     267: ifnonnull     340
     270: aload         4
     272: ifnull        299
     275: getstatic     #13                 // Field LOG:Lorg/slf4j/Logger;
     278: ldc           #107                // String Will create JmsMessage with caused exception: {}
     280: aload         4
     282: invokeinterface #108,  3          // InterfaceMethod org/slf4j/Logger.debug:(Ljava/lang/String;Ljava/lang/Throwable;)V
     287: aload_0
     288: aload         4
     290: aload_3
     291: invokevirtual #109                // Method createJmsMessage:(Ljava/lang/Exception;Ljavax/jms/Session;)Ljavax/jms/Message;
     294: astore        5
     296: goto          340
     299: aload_2
     300: ldc           #110                // String message
     302: invokestatic  #111                // Method org/apache/camel/util/ObjectHelper.notNull:(Ljava/lang/Object;Ljava/lang/String;)Ljava/lang/Object;
     305: pop
     306: aload_0
     307: aload_1
     308: aload_2
     309: invokeinterface #28,  1           // InterfaceMethod org/apache/camel/Message.getBody:()Ljava/lang/Object;
     314: aload_2
     315: invokeinterface #112,  1          // InterfaceMethod org/apache/camel/Message.getHeaders:()Ljava/util/Map;
     320: aload_3
     321: aload_1
     322: invokeinterface #113,  1          // InterfaceMethod org/apache/camel/Exchange.getContext:()Lorg/apache/camel/CamelContext;
     327: invokevirtual #114                // Method createJmsMessage:(Lorg/apache/camel/Exchange;Ljava/lang/Object;Ljava/util/Map;Ljavax/jms/Session;Lorg/apache/camel/CamelContext;)Ljavax/jms/Message;
     330: astore        5
     332: aload_0
     333: aload         5
     335: aload_1
     336: aload_2
     337: invokevirtual #115                // Method appendJmsProperties:(Ljavax/jms/Message;Lorg/apache/camel/Exchange;Lorg/apache/camel/Message;)V
     340: aload         5
     342: areturn

  public void appendJmsProperties(javax.jms.Message, org.apache.camel.Exchange) throws javax.jms.JMSException;
    Code:
       0: aload_0
       1: aload_1
       2: aload_2
       3: aload_2
       4: invokeinterface #27,  1           // InterfaceMethod org/apache/camel/Exchange.getIn:()Lorg/apache/camel/Message;
       9: invokevirtual #115                // Method appendJmsProperties:(Ljavax/jms/Message;Lorg/apache/camel/Exchange;Lorg/apache/camel/Message;)V
      12: return

  public void appendJmsProperties(javax.jms.Message, org.apache.camel.Exchange, org.apache.camel.Message) throws javax.jms.JMSException;
    Code:
       0: aload_3
       1: invokeinterface #112,  1          // InterfaceMethod org/apache/camel/Message.getHeaders:()Ljava/util/Map;
       6: invokeinterface #116,  1          // InterfaceMethod java/util/Map.entrySet:()Ljava/util/Set;
      11: astore        4
      13: aload         4
      15: invokeinterface #117,  1          // InterfaceMethod java/util/Set.iterator:()Ljava/util/Iterator;
      20: astore        5
      22: aload         5
      24: invokeinterface #118,  1          // InterfaceMethod java/util/Iterator.hasNext:()Z
      29: ifeq          79
      32: aload         5
      34: invokeinterface #119,  1          // InterfaceMethod java/util/Iterator.next:()Ljava/lang/Object;
      39: checkcast     #120                // class java/util/Map$Entry
      42: astore        6
      44: aload         6
      46: invokeinterface #121,  1          // InterfaceMethod java/util/Map$Entry.getKey:()Ljava/lang/Object;
      51: checkcast     #122                // class java/lang/String
      54: astore        7
      56: aload         6
      58: invokeinterface #123,  1          // InterfaceMethod java/util/Map$Entry.getValue:()Ljava/lang/Object;
      63: astore        8
      65: aload_0
      66: aload_1
      67: aload_2
      68: aload_3
      69: aload         7
      71: aload         8
      73: invokevirtual #124                // Method appendJmsProperty:(Ljavax/jms/Message;Lorg/apache/camel/Exchange;Lorg/apache/camel/Message;Ljava/lang/String;Ljava/lang/Object;)V
      76: goto          22
      79: return

  public void appendJmsProperty(javax.jms.Message, org.apache.camel.Exchange, org.apache.camel.Message, java.lang.String, java.lang.Object) throws javax.jms.JMSException;
    Code:
       0: aload_0
       1: aload         4
       3: invokevirtual #125                // Method isStandardJMSHeader:(Ljava/lang/String;)Z
       6: ifeq          232
       9: aload         4
      11: ldc           #52                 // String JMSCorrelationID
      13: invokevirtual #126                // Method java/lang/String.equals:(Ljava/lang/Object;)Z
      16: ifeq          40
      19: aload_1
      20: aload_2
      21: ldc_w         #122                // class java/lang/String
      24: aload         5
      26: invokestatic  #127                // Method org/apache/camel/util/ExchangeHelper.convertToType:(Lorg/apache/camel/Exchange;Ljava/lang/Class;Ljava/lang/Object;)Ljava/lang/Object;
      29: checkcast     #122                // class java/lang/String
      32: invokeinterface #128,  2          // InterfaceMethod javax/jms/Message.setJMSCorrelationID:(Ljava/lang/String;)V
      37: goto          330
      40: aload         4
      42: ldc           #72                 // String JMSReplyTo
      44: invokevirtual #126                // Method java/lang/String.equals:(Ljava/lang/Object;)Z
      47: ifeq          96
      50: aload         5
      52: ifnull        96
      55: aload         5
      57: instanceof    #122                // class java/lang/String
      60: ifeq          73
      63: aload         5
      65: checkcast     #122                // class java/lang/String
      68: invokestatic  #129                // Method org/apache/camel/component/jms/JmsMessageHelper.normalizeDestinationName:(Ljava/lang/String;)Ljava/lang/String;
      71: astore        5
      73: aload_2
      74: ldc_w         #130                // class javax/jms/Destination
      77: aload         5
      79: invokestatic  #127                // Method org/apache/camel/util/ExchangeHelper.convertToType:(Lorg/apache/camel/Exchange;Ljava/lang/Class;Ljava/lang/Object;)Ljava/lang/Object;
      82: checkcast     #130                // class javax/jms/Destination
      85: astore        6
      87: aload_1
      88: aload         6
      90: invokestatic  #131                // Method org/apache/camel/component/jms/JmsMessageHelper.setJMSReplyTo:(Ljavax/jms/Message;Ljavax/jms/Destination;)V
      93: goto          330
      96: aload         4
      98: ldc           #74                 // String JMSType
     100: invokevirtual #126                // Method java/lang/String.equals:(Ljava/lang/Object;)Z
     103: ifeq          127
     106: aload_1
     107: aload_2
     108: ldc_w         #122                // class java/lang/String
     111: aload         5
     113: invokestatic  #127                // Method org/apache/camel/util/ExchangeHelper.convertToType:(Lorg/apache/camel/Exchange;Ljava/lang/Class;Ljava/lang/Object;)Ljava/lang/Object;
     116: checkcast     #122                // class java/lang/String
     119: invokeinterface #132,  2          // InterfaceMethod javax/jms/Message.setJMSType:(Ljava/lang/String;)V
     124: goto          330
     127: aload         4
     129: ldc           #65                 // String JMSPriority
     131: invokevirtual #126                // Method java/lang/String.equals:(Ljava/lang/Object;)Z
     134: ifeq          161
     137: aload_1
     138: aload_2
     139: ldc_w         #133                // class java/lang/Integer
     142: aload         5
     144: invokestatic  #127                // Method org/apache/camel/util/ExchangeHelper.convertToType:(Lorg/apache/camel/Exchange;Ljava/lang/Class;Ljava/lang/Object;)Ljava/lang/Object;
     147: checkcast     #133                // class java/lang/Integer
     150: invokevirtual #134                // Method java/lang/Integer.intValue:()I
     153: invokeinterface #135,  2          // InterfaceMethod javax/jms/Message.setJMSPriority:(I)V
     158: goto          330
     161: aload         4
     163: ldc           #55                 // String JMSDeliveryMode
     165: invokevirtual #126                // Method java/lang/String.equals:(Ljava/lang/Object;)Z
     168: ifeq          181
     171: aload_2
     172: aload_1
     173: aload         5
     175: invokestatic  #136                // Method org/apache/camel/component/jms/JmsMessageHelper.setJMSDeliveryMode:(Lorg/apache/camel/Exchange;Ljavax/jms/Message;Ljava/lang/Object;)V
     178: goto          330
     181: aload         4
     183: ldc           #60                 // String JMSExpiration
     185: invokevirtual #126                // Method java/lang/String.equals:(Ljava/lang/Object;)Z
     188: ifeq          215
     191: aload_1
     192: aload_2
     193: ldc_w         #137                // class java/lang/Long
     196: aload         5
     198: invokestatic  #127                // Method org/apache/camel/util/ExchangeHelper.convertToType:(Lorg/apache/camel/Exchange;Ljava/lang/Class;Ljava/lang/Object;)Ljava/lang/Object;
     201: checkcast     #137                // class java/lang/Long
     204: invokevirtual #138                // Method java/lang/Long.longValue:()J
     207: invokeinterface #139,  3          // InterfaceMethod javax/jms/Message.setJMSExpiration:(J)V
     212: goto          330
     215: getstatic     #13                 // Field LOG:Lorg/slf4j/Logger;
     218: ldc           #140                // String Ignoring JMS header: {} with value: {}
     220: aload         4
     222: aload         5
     224: invokeinterface #16,  4           // InterfaceMethod org/slf4j/Logger.trace:(Ljava/lang/String;Ljava/lang/Object;Ljava/lang/Object;)V
     229: goto          330
     232: aload_0
     233: aload_3
     234: aload         4
     236: aload         5
     238: aload_2
     239: invokevirtual #141                // Method shouldOutputHeader:(Lorg/apache/camel/Message;Ljava/lang/String;Ljava/lang/Object;Lorg/apache/camel/Exchange;)Z
     242: ifeq          330
     245: aload_0
     246: aload         4
     248: aload         5
     250: invokevirtual #142                // Method getValidJMSHeaderValue:(Ljava/lang/String;Ljava/lang/Object;)Ljava/lang/Object;
     253: astore        6
     255: aload         6
     257: ifnull        284
     260: aload_0
     261: getfield      #8                  // Field jmsKeyFormatStrategy:Lorg/apache/camel/component/jms/JmsKeyFormatStrategy;
     264: aload         4
     266: invokeinterface #88,  2           // InterfaceMethod org/apache/camel/component/jms/JmsKeyFormatStrategy.encodeKey:(Ljava/lang/String;)Ljava/lang/String;
     271: astore        7
     273: aload_1
     274: aload         7
     276: aload         6
     278: invokestatic  #143                // Method org/apache/camel/component/jms/JmsMessageHelper.setProperty:(Ljavax/jms/Message;Ljava/lang/String;Ljava/lang/Object;)V
     281: goto          330
     284: getstatic     #13                 // Field LOG:Lorg/slf4j/Logger;
     287: invokeinterface #144,  1          // InterfaceMethod org/slf4j/Logger.isDebugEnabled:()Z
     292: ifeq          330
     295: getstatic     #13                 // Field LOG:Lorg/slf4j/Logger;
     298: ldc           #145                // String Ignoring non primitive header: {} of class: {} with value: {}
     300: iconst_3
     301: anewarray     #146                // class java/lang/Object
     304: dup
     305: iconst_0
     306: aload         4
     308: aastore
     309: dup
     310: iconst_1
     311: aload         5
     313: invokevirtual #147                // Method java/lang/Object.getClass:()Ljava/lang/Class;
     316: invokevirtual #148                // Method java/lang/Class.getName:()Ljava/lang/String;
     319: aastore
     320: dup
     321: iconst_2
     322: aload         5
     324: aastore
     325: invokeinterface #149,  3          // InterfaceMethod org/slf4j/Logger.debug:(Ljava/lang/String;[Ljava/lang/Object;)V
     330: return

  protected boolean isStandardJMSHeader(java.lang.String);
    Code:
       0: aload_1
       1: ldc           #150                // String JMS
       3: invokevirtual #151                // Method java/lang/String.startsWith:(Ljava/lang/String;)Z
       6: ifne          11
       9: iconst_0
      10: ireturn
      11: aload_1
      12: ldc           #152                // String JMSX
      14: invokevirtual #151                // Method java/lang/String.startsWith:(Ljava/lang/String;)Z
      17: ifeq          22
      20: iconst_0
      21: ireturn
      22: aload_1
      23: ldc           #153                // String JMS_
      25: invokevirtual #151                // Method java/lang/String.startsWith:(Ljava/lang/String;)Z
      28: ifeq          33
      31: iconst_0
      32: ireturn
      33: aload_1
      34: invokevirtual #154                // Method java/lang/String.length:()I
      37: iconst_3
      38: if_icmple     62
      41: aload_1
      42: iconst_3
      43: invokevirtual #155                // Method java/lang/String.charAt:(I)C
      46: invokestatic  #156                // Method java/lang/Character.valueOf:(C)Ljava/lang/Character;
      49: astore_2
      50: aload_2
      51: invokevirtual #157                // Method java/lang/Character.charValue:()C
      54: invokestatic  #158                // Method java/lang/Character.isLetter:(C)Z
      57: ifeq          62
      60: iconst_1
      61: ireturn
      62: iconst_0
      63: ireturn

  protected java.lang.Object getValidJMSHeaderValue(java.lang.String, java.lang.Object);
    Code:
       0: aload_2
       1: instanceof    #122                // class java/lang/String
       4: ifeq          9
       7: aload_2
       8: areturn
       9: aload_2
      10: instanceof    #159                // class java/math/BigInteger
      13: ifeq          21
      16: aload_2
      17: invokevirtual #83                 // Method java/lang/Object.toString:()Ljava/lang/String;
      20: areturn
      21: aload_2
      22: instanceof    #160                // class java/math/BigDecimal
      25: ifeq          33
      28: aload_2
      29: invokevirtual #83                 // Method java/lang/Object.toString:()Ljava/lang/String;
      32: areturn
      33: aload_2
      34: instanceof    #161                // class java/lang/Number
      37: ifeq          42
      40: aload_2
      41: areturn
      42: aload_2
      43: instanceof    #162                // class java/lang/Character
      46: ifeq          51
      49: aload_2
      50: areturn
      51: aload_2
      52: instanceof    #163                // class java/lang/CharSequence
      55: ifeq          63
      58: aload_2
      59: invokevirtual #83                 // Method java/lang/Object.toString:()Ljava/lang/String;
      62: areturn
      63: aload_2
      64: instanceof    #164                // class java/lang/Boolean
      67: ifeq          72
      70: aload_2
      71: areturn
      72: aload_2
      73: instanceof    #165                // class java/util/Date
      76: ifeq          84
      79: aload_2
      80: invokevirtual #83                 // Method java/lang/Object.toString:()Ljava/lang/String;
      83: areturn
      84: aconst_null
      85: areturn

  protected javax.jms.Message createJmsMessage(java.lang.Exception, javax.jms.Session) throws javax.jms.JMSException;
    Code:
       0: getstatic     #13                 // Field LOG:Lorg/slf4j/Logger;
       3: ldc           #166                // String Using JmsMessageType: {}
       5: getstatic     #105                // Field org/apache/camel/component/jms/JmsMessageType.Object:Lorg/apache/camel/component/jms/JmsMessageType;
       8: invokeinterface #21,  3           // InterfaceMethod org/slf4j/Logger.trace:(Ljava/lang/String;Ljava/lang/Object;)V
      13: aload_2
      14: aload_1
      15: invokeinterface #167,  2          // InterfaceMethod javax/jms/Session.createObjectMessage:(Ljava/io/Serializable;)Ljavax/jms/ObjectMessage;
      20: astore_3
      21: aload_3
      22: iconst_2
      23: invokeinterface #168,  2          // InterfaceMethod javax/jms/Message.setJMSDeliveryMode:(I)V
      28: aload_3
      29: areturn

  protected javax.jms.Message createJmsMessage(org.apache.camel.Exchange, java.lang.Object, java.util.Map<java.lang.String, java.lang.Object>, javax.jms.Session, org.apache.camel.CamelContext) throws javax.jms.JMSException;
    Code:
       0: aconst_null
       1: astore        6
       3: aload_0
       4: getfield      #2                  // Field endpoint:Lorg/apache/camel/component/jms/JmsEndpoint;
       7: ifnull        58
      10: aload_0
      11: getfield      #2                  // Field endpoint:Lorg/apache/camel/component/jms/JmsEndpoint;
      14: invokevirtual #169                // Method org/apache/camel/component/jms/JmsEndpoint.isTransferExchange:()Z
      17: ifeq          58
      20: getstatic     #13                 // Field LOG:Lorg/slf4j/Logger;
      23: ldc           #170                // String Option transferExchange=true so we use JmsMessageType: Object
      25: invokeinterface #171,  2          // InterfaceMethod org/slf4j/Logger.trace:(Ljava/lang/String;)V
      30: aload_1
      31: invokestatic  #172                // Method org/apache/camel/impl/DefaultExchangeHolder.marshal:(Lorg/apache/camel/Exchange;)Lorg/apache/camel/impl/DefaultExchangeHolder;
      34: astore        7
      36: aload         4
      38: aload         7
      40: invokeinterface #167,  2          // InterfaceMethod javax/jms/Session.createObjectMessage:(Ljava/io/Serializable;)Ljavax/jms/ObjectMessage;
      45: astore        8
      47: aload         8
      49: iconst_2
      50: invokeinterface #168,  2          // InterfaceMethod javax/jms/Message.setJMSDeliveryMode:(I)V
      55: aload         8
      57: areturn
      58: aload_0
      59: getfield      #2                  // Field endpoint:Lorg/apache/camel/component/jms/JmsEndpoint;
      62: ifnull        120
      65: aload_0
      66: getfield      #2                  // Field endpoint:Lorg/apache/camel/component/jms/JmsEndpoint;
      69: invokevirtual #12                 // Method org/apache/camel/component/jms/JmsEndpoint.getMessageConverter:()Lorg/springframework/jms/support/converter/MessageConverter;
      72: ifnull        120
      75: getstatic     #13                 // Field LOG:Lorg/slf4j/Logger;
      78: invokeinterface #14,  1           // InterfaceMethod org/slf4j/Logger.isTraceEnabled:()Z
      83: ifeq          104
      86: getstatic     #13                 // Field LOG:Lorg/slf4j/Logger;
      89: ldc           #173                // String Creating JmsMessage using a custom MessageConverter: {} with body: {}
      91: aload_0
      92: getfield      #2                  // Field endpoint:Lorg/apache/camel/component/jms/JmsEndpoint;
      95: invokevirtual #12                 // Method org/apache/camel/component/jms/JmsEndpoint.getMessageConverter:()Lorg/springframework/jms/support/converter/MessageConverter;
      98: aload_2
      99: invokeinterface #16,  4           // InterfaceMethod org/slf4j/Logger.trace:(Ljava/lang/String;Ljava/lang/Object;Ljava/lang/Object;)V
     104: aload_0
     105: getfield      #2                  // Field endpoint:Lorg/apache/camel/component/jms/JmsEndpoint;
     108: invokevirtual #12                 // Method org/apache/camel/component/jms/JmsEndpoint.getMessageConverter:()Lorg/springframework/jms/support/converter/MessageConverter;
     111: aload_2
     112: aload         4
     114: invokeinterface #174,  3          // InterfaceMethod org/springframework/jms/support/converter/MessageConverter.toMessage:(Ljava/lang/Object;Ljavax/jms/Session;)Ljavax/jms/Message;
     119: areturn
     120: aload_3
     121: ldc           #175                // String CamelJmsMessageType
     123: invokeinterface #176,  2          // InterfaceMethod java/util/Map.containsKey:(Ljava/lang/Object;)Z
     128: ifeq          162
     131: aload         5
     133: invokeinterface #177,  1          // InterfaceMethod org/apache/camel/CamelContext.getTypeConverter:()Lorg/apache/camel/TypeConverter;
     138: ldc_w         #178                // class org/apache/camel/component/jms/JmsMessageType
     141: aload_3
     142: ldc           #175                // String CamelJmsMessageType
     144: invokeinterface #179,  2          // InterfaceMethod java/util/Map.get:(Ljava/lang/Object;)Ljava/lang/Object;
     149: invokeinterface #180,  3          // InterfaceMethod org/apache/camel/TypeConverter.convertTo:(Ljava/lang/Class;Ljava/lang/Object;)Ljava/lang/Object;
     154: checkcast     #178                // class org/apache/camel/component/jms/JmsMessageType
     157: astore        6
     159: goto          210
     162: aload_0
     163: getfield      #2                  // Field endpoint:Lorg/apache/camel/component/jms/JmsEndpoint;
     166: ifnull        197
     169: aload_0
     170: getfield      #2                  // Field endpoint:Lorg/apache/camel/component/jms/JmsEndpoint;
     173: invokevirtual #18                 // Method org/apache/camel/component/jms/JmsEndpoint.getConfiguration:()Lorg/apache/camel/component/jms/JmsConfiguration;
     176: invokevirtual #101                // Method org/apache/camel/component/jms/JmsConfiguration.getJmsMessageType:()Lorg/apache/camel/component/jms/JmsMessageType;
     179: ifnull        197
     182: aload_0
     183: getfield      #2                  // Field endpoint:Lorg/apache/camel/component/jms/JmsEndpoint;
     186: invokevirtual #18                 // Method org/apache/camel/component/jms/JmsEndpoint.getConfiguration:()Lorg/apache/camel/component/jms/JmsConfiguration;
     189: invokevirtual #101                // Method org/apache/camel/component/jms/JmsConfiguration.getJmsMessageType:()Lorg/apache/camel/component/jms/JmsMessageType;
     192: astore        6
     194: goto          210
     197: aload_0
     198: aload_1
     199: aload_2
     200: aload_3
     201: aload         4
     203: aload         5
     205: invokevirtual #181                // Method getJMSMessageTypeForBody:(Lorg/apache/camel/Exchange;Ljava/lang/Object;Ljava/util/Map;Ljavax/jms/Session;Lorg/apache/camel/CamelContext;)Lorg/apache/camel/component/jms/JmsMessageType;
     208: astore        6
     210: aload         6
     212: ifnull        287
     215: aload_2
     216: ifnonnull     249
     219: aload_0
     220: getfield      #2                  // Field endpoint:Lorg/apache/camel/component/jms/JmsEndpoint;
     223: ifnull        249
     226: aload_0
     227: getfield      #2                  // Field endpoint:Lorg/apache/camel/component/jms/JmsEndpoint;
     230: invokevirtual #18                 // Method org/apache/camel/component/jms/JmsEndpoint.getConfiguration:()Lorg/apache/camel/component/jms/JmsConfiguration;
     233: invokevirtual #182                // Method org/apache/camel/component/jms/JmsConfiguration.isAllowNullBody:()Z
     236: ifne          249
     239: new           #40                 // class javax/jms/JMSException
     242: dup
     243: ldc           #183                // String Cannot send message as message body is null, and option allowNullBody is false.
     245: invokespecial #184                // Method javax/jms/JMSException."<init>":(Ljava/lang/String;)V
     248: athrow
     249: getstatic     #13                 // Field LOG:Lorg/slf4j/Logger;
     252: ldc           #166                // String Using JmsMessageType: {}
     254: aload         6
     256: invokeinterface #21,  3           // InterfaceMethod org/slf4j/Logger.trace:(Ljava/lang/String;Ljava/lang/Object;)V
     261: aload_0
     262: aload_1
     263: aload_2
     264: aload_3
     265: aload         4
     267: aload         5
     269: aload         6
     271: invokevirtual #185                // Method createJmsMessageForType:(Lorg/apache/camel/Exchange;Ljava/lang/Object;Ljava/util/Map;Ljavax/jms/Session;Lorg/apache/camel/CamelContext;Lorg/apache/camel/component/jms/JmsMessageType;)Ljavax/jms/Message;
     274: astore        7
     276: aload         7
     278: iconst_2
     279: invokeinterface #168,  2          // InterfaceMethod javax/jms/Message.setJMSDeliveryMode:(I)V
     284: aload         7
     286: areturn
     287: aload_2
     288: ifnonnull     321
     291: aload_0
     292: getfield      #2                  // Field endpoint:Lorg/apache/camel/component/jms/JmsEndpoint;
     295: ifnull        321
     298: aload_0
     299: getfield      #2                  // Field endpoint:Lorg/apache/camel/component/jms/JmsEndpoint;
     302: invokevirtual #18                 // Method org/apache/camel/component/jms/JmsEndpoint.getConfiguration:()Lorg/apache/camel/component/jms/JmsConfiguration;
     305: invokevirtual #182                // Method org/apache/camel/component/jms/JmsConfiguration.isAllowNullBody:()Z
     308: ifne          321
     311: new           #40                 // class javax/jms/JMSException
     314: dup
     315: ldc           #183                // String Cannot send message as message body is null, and option allowNullBody is false.
     317: invokespecial #184                // Method javax/jms/JMSException."<init>":(Ljava/lang/String;)V
     320: athrow
     321: aload_2
     322: ifnull        376
     325: getstatic     #13                 // Field LOG:Lorg/slf4j/Logger;
     328: invokeinterface #186,  1          // InterfaceMethod org/slf4j/Logger.isWarnEnabled:()Z
     333: ifeq          376
     336: getstatic     #13                 // Field LOG:Lorg/slf4j/Logger;
     339: new           #42                 // class java/lang/StringBuilder
     342: dup
     343: invokespecial #43                 // Method java/lang/StringBuilder."<init>":()V
     346: ldc           #187                // String Cannot determine specific JmsMessage type to use from body class. Will use generic JmsMessage. Body class:
     348: invokevirtual #45                 // Method java/lang/StringBuilder.append:(Ljava/lang/String;)Ljava/lang/StringBuilder;
     351: aload_2
     352: invokestatic  #188                // Method org/apache/camel/util/ObjectHelper.classCanonicalName:(Ljava/lang/Object;)Ljava/lang/String;
     355: invokevirtual #45                 // Method java/lang/StringBuilder.append:(Ljava/lang/String;)Ljava/lang/StringBuilder;
     358: ldc           #189                // String . If you want to send a POJO then your class might need to implement java.io.Serializable
     360: invokevirtual #45                 // Method java/lang/StringBuilder.append:(Ljava/lang/String;)Ljava/lang/StringBuilder;
     363: ldc           #190                // String , or you can force a specific type by setting the jmsMessageType option on the JMS endpoint.
     365: invokevirtual #45                 // Method java/lang/StringBuilder.append:(Ljava/lang/String;)Ljava/lang/StringBuilder;
     368: invokevirtual #48                 // Method java/lang/StringBuilder.toString:()Ljava/lang/String;
     371: invokeinterface #191,  2          // InterfaceMethod org/slf4j/Logger.warn:(Ljava/lang/String;)V
     376: aload         4
     378: invokeinterface #192,  1          // InterfaceMethod javax/jms/Session.createMessage:()Ljavax/jms/Message;
     383: astore        7
     385: aload         7
     387: iconst_2
     388: invokeinterface #168,  2          // InterfaceMethod javax/jms/Message.setJMSDeliveryMode:(I)V
     393: aload         7
     395: areturn

  protected org.apache.camel.component.jms.JmsMessageType getJMSMessageTypeForBody(org.apache.camel.Exchange, java.lang.Object, java.util.Map<java.lang.String, java.lang.Object>, javax.jms.Session, org.apache.camel.CamelContext);
    Code:
       0: aconst_null
       1: astore        6
       3: aload_2
       4: instanceof    #193                // class org/w3c/dom/Node
       7: ifne          17
      10: aload_2
      11: instanceof    #122                // class java/lang/String
      14: ifeq          25
      17: getstatic     #102                // Field org/apache/camel/component/jms/JmsMessageType.Text:Lorg/apache/camel/component/jms/JmsMessageType;
      20: astore        6
      22: goto          163
      25: aload_2
      26: instanceof    #194                // class "[B"
      29: ifne          74
      32: aload_2
      33: instanceof    #195                // class org/apache/camel/WrappedFile
      36: ifne          74
      39: aload_2
      40: instanceof    #196                // class java/io/File
      43: ifne          74
      46: aload_2
      47: instanceof    #197                // class java/io/Reader
      50: ifne          74
      53: aload_2
      54: instanceof    #198                // class java/io/InputStream
      57: ifne          74
      60: aload_2
      61: instanceof    #199                // class java/nio/ByteBuffer
      64: ifne          74
      67: aload_2
      68: instanceof    #200                // class org/apache/camel/StreamCache
      71: ifeq          82
      74: getstatic     #103                // Field org/apache/camel/component/jms/JmsMessageType.Bytes:Lorg/apache/camel/component/jms/JmsMessageType;
      77: astore        6
      79: goto          163
      82: aload_2
      83: instanceof    #201                // class java/util/Map
      86: ifeq          97
      89: getstatic     #104                // Field org/apache/camel/component/jms/JmsMessageType.Map:Lorg/apache/camel/component/jms/JmsMessageType;
      92: astore        6
      94: goto          163
      97: aload_2
      98: instanceof    #202                // class java/io/Serializable
     101: ifeq          112
     104: getstatic     #105                // Field org/apache/camel/component/jms/JmsMessageType.Object:Lorg/apache/camel/component/jms/JmsMessageType;
     107: astore        6
     109: goto          163
     112: aload_1
     113: invokeinterface #113,  1          // InterfaceMethod org/apache/camel/Exchange.getContext:()Lorg/apache/camel/CamelContext;
     118: invokeinterface #177,  1          // InterfaceMethod org/apache/camel/CamelContext.getTypeConverter:()Lorg/apache/camel/TypeConverter;
     123: ldc_w         #196                // class java/io/File
     126: aload_2
     127: invokeinterface #203,  3          // InterfaceMethod org/apache/camel/TypeConverter.tryConvertTo:(Ljava/lang/Class;Ljava/lang/Object;)Ljava/lang/Object;
     132: ifnonnull     158
     135: aload_1
     136: invokeinterface #113,  1          // InterfaceMethod org/apache/camel/Exchange.getContext:()Lorg/apache/camel/CamelContext;
     141: invokeinterface #177,  1          // InterfaceMethod org/apache/camel/CamelContext.getTypeConverter:()Lorg/apache/camel/TypeConverter;
     146: ldc_w         #198                // class java/io/InputStream
     149: aload_2
     150: invokeinterface #203,  3          // InterfaceMethod org/apache/camel/TypeConverter.tryConvertTo:(Ljava/lang/Class;Ljava/lang/Object;)Ljava/lang/Object;
     155: ifnull        163
     158: getstatic     #103                // Field org/apache/camel/component/jms/JmsMessageType.Bytes:Lorg/apache/camel/component/jms/JmsMessageType;
     161: astore        6
     163: aload         6
     165: areturn

  protected javax.jms.Message createJmsMessageForType(org.apache.camel.Exchange, java.lang.Object, java.util.Map<java.lang.String, java.lang.Object>, javax.jms.Session, org.apache.camel.CamelContext, org.apache.camel.component.jms.JmsMessageType) throws javax.jms.JMSException;
    Code:
       0: getstatic     #204                // Field org/apache/camel/component/jms/JmsBinding$1.$SwitchMap$org$apache$camel$component$jms$JmsMessageType:[I
       3: aload         6
       5: invokevirtual #205                // Method org/apache/camel/component/jms/JmsMessageType.ordinal:()I
       8: iaload
       9: tableswitch   { // 1 to 4
                     1: 40
                     2: 87
                     3: 134
                     4: 182
               default: 259
          }
      40: aload         4
      42: invokeinterface #206,  1          // InterfaceMethod javax/jms/Session.createTextMessage:()Ljavax/jms/TextMessage;
      47: astore        7
      49: aload_2
      50: ifnull        84
      53: aload         5
      55: invokeinterface #177,  1          // InterfaceMethod org/apache/camel/CamelContext.getTypeConverter:()Lorg/apache/camel/TypeConverter;
      60: ldc_w         #122                // class java/lang/String
      63: aload_1
      64: aload_2
      65: invokeinterface #207,  4          // InterfaceMethod org/apache/camel/TypeConverter.convertTo:(Ljava/lang/Class;Lorg/apache/camel/Exchange;Ljava/lang/Object;)Ljava/lang/Object;
      70: checkcast     #122                // class java/lang/String
      73: astore        8
      75: aload         7
      77: aload         8
      79: invokeinterface #208,  2          // InterfaceMethod javax/jms/TextMessage.setText:(Ljava/lang/String;)V
      84: aload         7
      86: areturn
      87: aload         4
      89: invokeinterface #209,  1          // InterfaceMethod javax/jms/Session.createBytesMessage:()Ljavax/jms/BytesMessage;
      94: astore        7
      96: aload_2
      97: ifnull        131
     100: aload         5
     102: invokeinterface #177,  1          // InterfaceMethod org/apache/camel/CamelContext.getTypeConverter:()Lorg/apache/camel/TypeConverter;
     107: ldc_w         #194                // class "[B"
     110: aload_1
     111: aload_2
     112: invokeinterface #207,  4          // InterfaceMethod org/apache/camel/TypeConverter.convertTo:(Ljava/lang/Class;Lorg/apache/camel/Exchange;Ljava/lang/Object;)Ljava/lang/Object;
     117: checkcast     #194                // class "[B"
     120: astore        8
     122: aload         7
     124: aload         8
     126: invokeinterface #210,  2          // InterfaceMethod javax/jms/BytesMessage.writeBytes:([B)V
     131: aload         7
     133: areturn
     134: aload         4
     136: invokeinterface #211,  1          // InterfaceMethod javax/jms/Session.createMapMessage:()Ljavax/jms/MapMessage;
     141: astore        7
     143: aload_2
     144: ifnull        179
     147: aload         5
     149: invokeinterface #177,  1          // InterfaceMethod org/apache/camel/CamelContext.getTypeConverter:()Lorg/apache/camel/TypeConverter;
     154: ldc_w         #201                // class java/util/Map
     157: aload_1
     158: aload_2
     159: invokeinterface #207,  4          // InterfaceMethod org/apache/camel/TypeConverter.convertTo:(Ljava/lang/Class;Lorg/apache/camel/Exchange;Ljava/lang/Object;)Ljava/lang/Object;
     164: checkcast     #201                // class java/util/Map
     167: astore        8
     169: aload_0
     170: aload         7
     172: aload         8
     174: aload         5
     176: invokevirtual #212                // Method populateMapMessage:(Ljavax/jms/MapMessage;Ljava/util/Map;Lorg/apache/camel/CamelContext;)V
     179: aload         7
     181: areturn
     182: aload         4
     184: invokeinterface #213,  1          // InterfaceMethod javax/jms/Session.createObjectMessage:()Ljavax/jms/ObjectMessage;
     189: astore        7
     191: aload_2
     192: ifnull        256
     195: aload         5
     197: invokeinterface #177,  1          // InterfaceMethod org/apache/camel/CamelContext.getTypeConverter:()Lorg/apache/camel/TypeConverter;
     202: ldc_w         #202                // class java/io/Serializable
     205: aload_1
     206: aload_2
     207: invokeinterface #214,  4          // InterfaceMethod org/apache/camel/TypeConverter.mandatoryConvertTo:(Ljava/lang/Class;Lorg/apache/camel/Exchange;Ljava/lang/Object;)Ljava/lang/Object;
     212: checkcast     #202                // class java/io/Serializable
     215: astore        8
     217: aload         7
     219: aload         8
     221: invokeinterface #215,  2          // InterfaceMethod javax/jms/ObjectMessage.setObject:(Ljava/io/Serializable;)V
     226: goto          256
     229: astore        8
     231: new           #217                // class javax/jms/MessageFormatException
     234: dup
     235: aload         8
     237: invokevirtual #218                // Method org/apache/camel/NoTypeConversionAvailableException.getMessage:()Ljava/lang/String;
     240: invokespecial #219                // Method javax/jms/MessageFormatException."<init>":(Ljava/lang/String;)V
     243: astore        9
     245: aload         9
     247: aload         8
     249: invokevirtual #220                // Method javax/jms/JMSException.initCause:(Ljava/lang/Throwable;)Ljava/lang/Throwable;
     252: pop
     253: aload         9
     255: athrow
     256: aload         7
     258: areturn
     259: aconst_null
     260: areturn
    Exception table:
       from    to  target type
         195   226   229   Class org/apache/camel/NoTypeConversionAvailableException

  protected void populateMapMessage(javax.jms.MapMessage, java.util.Map<?, ?>, org.apache.camel.CamelContext) throws javax.jms.JMSException;
    Code:
       0: aload_2
       1: invokeinterface #116,  1          // InterfaceMethod java/util/Map.entrySet:()Ljava/util/Set;
       6: invokeinterface #117,  1          // InterfaceMethod java/util/Set.iterator:()Ljava/util/Iterator;
      11: astore        4
      13: aload         4
      15: invokeinterface #118,  1          // InterfaceMethod java/util/Iterator.hasNext:()Z
      20: ifeq          77
      23: aload         4
      25: invokeinterface #119,  1          // InterfaceMethod java/util/Iterator.next:()Ljava/lang/Object;
      30: checkcast     #120                // class java/util/Map$Entry
      33: astore        5
      35: aload_3
      36: ldc_w         #122                // class java/lang/String
      39: aload         5
      41: invokeinterface #121,  1          // InterfaceMethod java/util/Map$Entry.getKey:()Ljava/lang/Object;
      46: invokestatic  #221                // Method org/apache/camel/util/CamelContextHelper.convertTo:(Lorg/apache/camel/CamelContext;Ljava/lang/Class;Ljava/lang/Object;)Ljava/lang/Object;
      49: checkcast     #122                // class java/lang/String
      52: astore        6
      54: aload         6
      56: ifnull        74
      59: aload_1
      60: aload         6
      62: aload         5
      64: invokeinterface #123,  1          // InterfaceMethod java/util/Map$Entry.getValue:()Ljava/lang/Object;
      69: invokeinterface #222,  3          // InterfaceMethod javax/jms/MapMessage.setObject:(Ljava/lang/String;Ljava/lang/Object;)V
      74: goto          13
      77: return

  public java.util.Map<java.lang.String, java.lang.Object> createMapFromMapMessage(javax.jms.MapMessage) throws javax.jms.JMSException;
    Code:
       0: new           #50                 // class java/util/HashMap
       3: dup
       4: invokespecial #51                 // Method java/util/HashMap."<init>":()V
       7: astore_2
       8: aload_1
       9: invokeinterface #223,  1          // InterfaceMethod javax/jms/MapMessage.getMapNames:()Ljava/util/Enumeration;
      14: astore_3
      15: aload_3
      16: invokeinterface #81,  1           // InterfaceMethod java/util/Enumeration.hasMoreElements:()Z
      21: ifeq          59
      24: aload_3
      25: invokeinterface #82,  1           // InterfaceMethod java/util/Enumeration.nextElement:()Ljava/lang/Object;
      30: invokevirtual #83                 // Method java/lang/Object.toString:()Ljava/lang/String;
      33: astore        4
      35: aload_1
      36: aload         4
      38: invokeinterface #224,  2          // InterfaceMethod javax/jms/MapMessage.getObject:(Ljava/lang/String;)Ljava/lang/Object;
      43: astore        5
      45: aload_2
      46: aload         4
      48: aload         5
      50: invokeinterface #54,  3           // InterfaceMethod java/util/Map.put:(Ljava/lang/Object;Ljava/lang/Object;)Ljava/lang/Object;
      55: pop
      56: goto          15
      59: aload_2
      60: areturn

  protected boolean shouldOutputHeader(org.apache.camel.Message, java.lang.String, java.lang.Object, org.apache.camel.Exchange);
    Code:
       0: aload_0
       1: getfield      #5                  // Field headerFilterStrategy:Lorg/apache/camel/spi/HeaderFilterStrategy;
       4: ifnull        23
       7: aload_0
       8: getfield      #5                  // Field headerFilterStrategy:Lorg/apache/camel/spi/HeaderFilterStrategy;
      11: aload_2
      12: aload_3
      13: aload         4
      15: invokeinterface #225,  4          // InterfaceMethod org/apache/camel/spi/HeaderFilterStrategy.applyFilterToCamelHeaders:(Ljava/lang/String;Ljava/lang/Object;Lorg/apache/camel/Exchange;)Z
      20: ifne          27
      23: iconst_1
      24: goto          28
      27: iconst_0
      28: ireturn

  static {};
    Code:
       0: ldc_w         #226                // class org/apache/camel/component/jms/JmsBinding
       3: invokestatic  #227                // Method org/slf4j/LoggerFactory.getLogger:(Ljava/lang/Class;)Lorg/slf4j/Logger;
       6: putstatic     #13                 // Field LOG:Lorg/slf4j/Logger;
       9: return
}
