Compiled from "JmsQueueEndpoint.java"
public class org.apache.camel.component.jms.JmsQueueEndpoint extends org.apache.camel.component.jms.JmsEndpoint implements org.apache.camel.spi.BrowsableEndpoint {
  private int maximumBrowseSize;

  private final org.apache.camel.component.jms.QueueBrowseStrategy queueBrowseStrategy;

  public org.apache.camel.component.jms.JmsQueueEndpoint(javax.jms.Queue) throws javax.jms.JMSException;
    Code:
       0: aload_0
       1: new           #1                  // class java/lang/StringBuilder
       4: dup
       5: invokespecial #2                  // Method java/lang/StringBuilder."<init>":()V
       8: ldc           #3                  // String jms:queue:
      10: invokevirtual #4                  // Method java/lang/StringBuilder.append:(Ljava/lang/String;)Ljava/lang/StringBuilder;
      13: aload_1
      14: invokeinterface #5,  1            // InterfaceMethod javax/jms/Queue.getQueueName:()Ljava/lang/String;
      19: invokevirtual #4                  // Method java/lang/StringBuilder.append:(Ljava/lang/String;)Ljava/lang/StringBuilder;
      22: invokevirtual #6                  // Method java/lang/StringBuilder.toString:()Ljava/lang/String;
      25: aconst_null
      26: invokespecial #7                  // Method "<init>":(Ljava/lang/String;Ljava/lang/String;)V
      29: aload_0
      30: aload_1
      31: invokevirtual #8                  // Method setDestination:(Ljavax/jms/Destination;)V
      34: return

  public org.apache.camel.component.jms.JmsQueueEndpoint(java.lang.String, org.apache.camel.component.jms.JmsComponent, java.lang.String, org.apache.camel.component.jms.JmsConfiguration);
    Code:
       0: aload_0
       1: aload_1
       2: aload_2
       3: aload_3
       4: aload         4
       6: aconst_null
       7: invokespecial #9                  // Method "<init>":(Ljava/lang/String;Lorg/apache/camel/component/jms/JmsComponent;Ljava/lang/String;Lorg/apache/camel/component/jms/JmsConfiguration;Lorg/apache/camel/component/jms/QueueBrowseStrategy;)V
      10: return

  public org.apache.camel.component.jms.JmsQueueEndpoint(java.lang.String, org.apache.camel.component.jms.JmsComponent, java.lang.String, org.apache.camel.component.jms.JmsConfiguration, org.apache.camel.component.jms.QueueBrowseStrategy);
    Code:
       0: aload_0
       1: aload_1
       2: aload_2
       3: aload_3
       4: iconst_0
       5: aload         4
       7: invokespecial #10                 // Method org/apache/camel/component/jms/JmsEndpoint."<init>":(Ljava/lang/String;Lorg/apache/camel/component/jms/JmsComponent;Ljava/lang/String;ZLorg/apache/camel/component/jms/JmsConfiguration;)V
      10: aload_0
      11: iconst_m1
      12: putfield      #11                 // Field maximumBrowseSize:I
      15: aload         5
      17: ifnonnull     31
      20: aload_0
      21: aload_0
      22: invokevirtual #12                 // Method createQueueBrowseStrategy:()Lorg/apache/camel/component/jms/QueueBrowseStrategy;
      25: putfield      #13                 // Field queueBrowseStrategy:Lorg/apache/camel/component/jms/QueueBrowseStrategy;
      28: goto          37
      31: aload_0
      32: aload         5
      34: putfield      #13                 // Field queueBrowseStrategy:Lorg/apache/camel/component/jms/QueueBrowseStrategy;
      37: return

  public org.apache.camel.component.jms.JmsQueueEndpoint(java.lang.String, java.lang.String, org.apache.camel.component.jms.QueueBrowseStrategy);
    Code:
       0: aload_0
       1: aload_1
       2: aload_2
       3: iconst_0
       4: invokespecial #14                 // Method org/apache/camel/component/jms/JmsEndpoint."<init>":(Ljava/lang/String;Ljava/lang/String;Z)V
       7: aload_0
       8: iconst_m1
       9: putfield      #11                 // Field maximumBrowseSize:I
      12: aload_3
      13: ifnonnull     27
      16: aload_0
      17: aload_0
      18: invokevirtual #12                 // Method createQueueBrowseStrategy:()Lorg/apache/camel/component/jms/QueueBrowseStrategy;
      21: putfield      #13                 // Field queueBrowseStrategy:Lorg/apache/camel/component/jms/QueueBrowseStrategy;
      24: goto          32
      27: aload_0
      28: aload_3
      29: putfield      #13                 // Field queueBrowseStrategy:Lorg/apache/camel/component/jms/QueueBrowseStrategy;
      32: return

  public org.apache.camel.component.jms.JmsQueueEndpoint(java.lang.String, java.lang.String);
    Code:
       0: aload_0
       1: aload_1
       2: aload_2
       3: iconst_0
       4: invokespecial #14                 // Method org/apache/camel/component/jms/JmsEndpoint."<init>":(Ljava/lang/String;Ljava/lang/String;Z)V
       7: aload_0
       8: iconst_m1
       9: putfield      #11                 // Field maximumBrowseSize:I
      12: aload_0
      13: aload_0
      14: invokevirtual #12                 // Method createQueueBrowseStrategy:()Lorg/apache/camel/component/jms/QueueBrowseStrategy;
      17: putfield      #13                 // Field queueBrowseStrategy:Lorg/apache/camel/component/jms/QueueBrowseStrategy;
      20: return

  public int getMaximumBrowseSize();
    Code:
       0: aload_0
       1: getfield      #11                 // Field maximumBrowseSize:I
       4: ireturn

  public void setMaximumBrowseSize(int);
    Code:
       0: aload_0
       1: iload_1
       2: putfield      #11                 // Field maximumBrowseSize:I
       5: return

  public java.util.List<org.apache.camel.Exchange> getExchanges();
    Code:
       0: aload_0
       1: getfield      #13                 // Field queueBrowseStrategy:Lorg/apache/camel/component/jms/QueueBrowseStrategy;
       4: ifnonnull     11
       7: invokestatic  #15                 // Method java/util/Collections.emptyList:()Ljava/util/List;
      10: areturn
      11: aload_0
      12: invokevirtual #16                 // Method getDestinationName:()Ljava/lang/String;
      15: astore_1
      16: aload_0
      17: invokevirtual #17                 // Method getConfiguration:()Lorg/apache/camel/component/jms/JmsConfiguration;
      20: aload_0
      21: iconst_0
      22: aload_1
      23: invokevirtual #18                 // Method org/apache/camel/component/jms/JmsConfiguration.createInOnlyTemplate:(Lorg/apache/camel/component/jms/JmsEndpoint;ZLjava/lang/String;)Lorg/springframework/jms/core/JmsOperations;
      26: astore_2
      27: aload_0
      28: getfield      #13                 // Field queueBrowseStrategy:Lorg/apache/camel/component/jms/QueueBrowseStrategy;
      31: aload_2
      32: aload_1
      33: aload_0
      34: invokeinterface #19,  4           // InterfaceMethod org/apache/camel/component/jms/QueueBrowseStrategy.browse:(Lorg/springframework/jms/core/JmsOperations;Ljava/lang/String;Lorg/apache/camel/component/jms/JmsQueueEndpoint;)Ljava/util/List;
      39: areturn

  public long queueSize();
    Code:
       0: aload_0
       1: invokevirtual #20                 // Method getExchanges:()Ljava/util/List;
       4: invokeinterface #21,  1           // InterfaceMethod java/util/List.size:()I
       9: i2l
      10: lreturn

  public java.lang.String browseExchange(java.lang.Integer);
    Code:
       0: aload_0
       1: invokevirtual #20                 // Method getExchanges:()Ljava/util/List;
       4: astore_2
       5: aload_1
       6: invokevirtual #22                 // Method java/lang/Integer.intValue:()I
       9: aload_2
      10: invokeinterface #21,  1           // InterfaceMethod java/util/List.size:()I
      15: if_icmplt     20
      18: aconst_null
      19: areturn
      20: aload_2
      21: aload_1
      22: invokevirtual #22                 // Method java/lang/Integer.intValue:()I
      25: invokeinterface #23,  2           // InterfaceMethod java/util/List.get:(I)Ljava/lang/Object;
      30: checkcast     #24                 // class org/apache/camel/Exchange
      33: astore_3
      34: aload_3
      35: ifnonnull     40
      38: aconst_null
      39: areturn
      40: aload_3
      41: invokevirtual #25                 // Method java/lang/Object.toString:()Ljava/lang/String;
      44: areturn

  public java.lang.String browseMessageBody(java.lang.Integer);
    Code:
       0: aload_0
       1: invokevirtual #20                 // Method getExchanges:()Ljava/util/List;
       4: astore_2
       5: aload_1
       6: invokevirtual #22                 // Method java/lang/Integer.intValue:()I
       9: aload_2
      10: invokeinterface #21,  1           // InterfaceMethod java/util/List.size:()I
      15: if_icmplt     20
      18: aconst_null
      19: areturn
      20: aload_2
      21: aload_1
      22: invokevirtual #22                 // Method java/lang/Integer.intValue:()I
      25: invokeinterface #23,  2           // InterfaceMethod java/util/List.get:(I)Ljava/lang/Object;
      30: checkcast     #24                 // class org/apache/camel/Exchange
      33: astore_3
      34: aload_3
      35: ifnonnull     40
      38: aconst_null
      39: areturn
      40: aload_3
      41: invokeinterface #26,  1           // InterfaceMethod org/apache/camel/Exchange.hasOut:()Z
      46: ifeq          71
      49: aload_3
      50: invokeinterface #27,  1           // InterfaceMethod org/apache/camel/Exchange.getOut:()Lorg/apache/camel/Message;
      55: ldc_w         #28                 // class java/lang/String
      58: invokeinterface #29,  2           // InterfaceMethod org/apache/camel/Message.getBody:(Ljava/lang/Class;)Ljava/lang/Object;
      63: checkcast     #28                 // class java/lang/String
      66: astore        4
      68: goto          90
      71: aload_3
      72: invokeinterface #30,  1           // InterfaceMethod org/apache/camel/Exchange.getIn:()Lorg/apache/camel/Message;
      77: ldc_w         #28                 // class java/lang/String
      80: invokeinterface #29,  2           // InterfaceMethod org/apache/camel/Message.getBody:(Ljava/lang/Class;)Ljava/lang/Object;
      85: checkcast     #28                 // class java/lang/String
      88: astore        4
      90: aload         4
      92: areturn

  public java.lang.String browseMessageAsXml(java.lang.Integer, java.lang.Boolean);
    Code:
       0: aload_0
       1: invokevirtual #20                 // Method getExchanges:()Ljava/util/List;
       4: astore_3
       5: aload_1
       6: invokevirtual #22                 // Method java/lang/Integer.intValue:()I
       9: aload_3
      10: invokeinterface #21,  1           // InterfaceMethod java/util/List.size:()I
      15: if_icmplt     20
      18: aconst_null
      19: areturn
      20: aload_3
      21: aload_1
      22: invokevirtual #22                 // Method java/lang/Integer.intValue:()I
      25: invokeinterface #23,  2           // InterfaceMethod java/util/List.get:(I)Ljava/lang/Object;
      30: checkcast     #24                 // class org/apache/camel/Exchange
      33: astore        4
      35: aload         4
      37: ifnonnull     42
      40: aconst_null
      41: areturn
      42: aload         4
      44: invokeinterface #26,  1           // InterfaceMethod org/apache/camel/Exchange.hasOut:()Z
      49: ifeq          62
      52: aload         4
      54: invokeinterface #27,  1           // InterfaceMethod org/apache/camel/Exchange.getOut:()Lorg/apache/camel/Message;
      59: goto          69
      62: aload         4
      64: invokeinterface #30,  1           // InterfaceMethod org/apache/camel/Exchange.getIn:()Lorg/apache/camel/Message;
      69: astore        5
      71: aload         5
      73: aload_2
      74: invokevirtual #31                 // Method java/lang/Boolean.booleanValue:()Z
      77: invokestatic  #32                 // Method org/apache/camel/util/MessageHelper.dumpAsXml:(Lorg/apache/camel/Message;Z)Ljava/lang/String;
      80: astore        6
      82: aload         6
      84: areturn

  public java.lang.String browseAllMessagesAsXml(java.lang.Boolean);
    Code:
       0: aload_0
       1: iconst_0
       2: invokestatic  #33                 // Method java/lang/Integer.valueOf:(I)Ljava/lang/Integer;
       5: ldc           #34                 // int 2147483647
       7: invokestatic  #33                 // Method java/lang/Integer.valueOf:(I)Ljava/lang/Integer;
      10: aload_1
      11: invokevirtual #35                 // Method browseRangeMessagesAsXml:(Ljava/lang/Integer;Ljava/lang/Integer;Ljava/lang/Boolean;)Ljava/lang/String;
      14: areturn

  public java.lang.String browseRangeMessagesAsXml(java.lang.Integer, java.lang.Integer, java.lang.Boolean);
    Code:
       0: aload_0
       1: aload_1
       2: aload_2
       3: aload_3
       4: invokestatic  #36                 // Method org/apache/camel/util/EndpointHelper.browseRangeMessagesAsXml:(Lorg/apache/camel/spi/BrowsableEndpoint;Ljava/lang/Integer;Ljava/lang/Integer;Ljava/lang/Boolean;)Ljava/lang/String;
       7: areturn

  protected org.apache.camel.component.jms.QueueBrowseStrategy createQueueBrowseStrategy();
    Code:
       0: new           #37                 // class org/apache/camel/component/jms/DefaultQueueBrowseStrategy
       3: dup
       4: invokespecial #38                 // Method org/apache/camel/component/jms/DefaultQueueBrowseStrategy."<init>":()V
       7: areturn
}
