Compiled from "AeronUri.java"
public class io.aeron.driver.uri.AeronUri {
  private static final java.lang.String AERON_PREFIX;

  private final java.lang.String scheme;

  private final java.lang.String media;

  private final java.util.Map<java.lang.String, java.lang.String> params;

  public io.aeron.driver.uri.AeronUri(java.lang.String, java.lang.String, java.util.Map<java.lang.String, java.lang.String>);
    Code:
       0: aload_0
       1: invokespecial #1                  // Method java/lang/Object."<init>":()V
       4: aload_0
       5: aload_1
       6: putfield      #2                  // Field scheme:Ljava/lang/String;
       9: aload_0
      10: aload_2
      11: putfield      #3                  // Field media:Ljava/lang/String;
      14: aload_0
      15: aload_3
      16: putfield      #4                  // Field params:Ljava/util/Map;
      19: aconst_null
      20: aload_3
      21: ldc           #6                  // String local
      23: invokeinterface #7,  2            // InterfaceMethod java/util/Map.get:(Ljava/lang/Object;)Ljava/lang/Object;
      28: if_acmpeq     39
      31: getstatic     #8                  // Field java/lang/System.err:Ljava/io/PrintStream;
      34: ldc           #9                  // String Warning: deprecated API usage - please use \'interface\' rather than \'local\'
      36: invokevirtual #10                 // Method java/io/PrintStream.println:(Ljava/lang/String;)V
      39: aconst_null
      40: aload_3
      41: ldc           #11                 // String remote
      43: invokeinterface #7,  2            // InterfaceMethod java/util/Map.get:(Ljava/lang/Object;)Ljava/lang/Object;
      48: if_acmpne     63
      51: aconst_null
      52: aload_3
      53: ldc           #12                 // String group
      55: invokeinterface #7,  2            // InterfaceMethod java/util/Map.get:(Ljava/lang/Object;)Ljava/lang/Object;
      60: if_acmpeq     71
      63: getstatic     #8                  // Field java/lang/System.err:Ljava/io/PrintStream;
      66: ldc           #13                 // String Warning: deprecated API usage - please use \'endpoint\' rather than \'remote\' or \'group\'
      68: invokevirtual #10                 // Method java/io/PrintStream.println:(Ljava/lang/String;)V
      71: return

  public java.lang.String media();
    Code:
       0: aload_0
       1: getfield      #3                  // Field media:Ljava/lang/String;
       4: areturn

  public java.lang.String scheme();
    Code:
       0: aload_0
       1: getfield      #2                  // Field scheme:Ljava/lang/String;
       4: areturn

  public java.lang.String get(java.lang.String);
    Code:
       0: aload_0
       1: getfield      #4                  // Field params:Ljava/util/Map;
       4: aload_1
       5: invokeinterface #7,  2            // InterfaceMethod java/util/Map.get:(Ljava/lang/Object;)Ljava/lang/Object;
      10: checkcast     #14                 // class java/lang/String
      13: areturn

  public java.lang.String get(java.lang.String, java.lang.String);
    Code:
       0: aload_0
       1: getfield      #4                  // Field params:Ljava/util/Map;
       4: aload_1
       5: invokeinterface #7,  2            // InterfaceMethod java/util/Map.get:(Ljava/lang/Object;)Ljava/lang/Object;
      10: checkcast     #14                 // class java/lang/String
      13: astore_3
      14: aconst_null
      15: aload_3
      16: if_acmpeq     21
      19: aload_3
      20: areturn
      21: aload_2
      22: areturn

  public java.net.InetAddress getInetAddress(java.lang.String) throws java.net.UnknownHostException;
    Code:
       0: aload_0
       1: aload_1
       2: invokevirtual #15                 // Method get:(Ljava/lang/String;)Ljava/lang/String;
       5: invokestatic  #16                 // Method java/net/InetAddress.getByName:(Ljava/lang/String;)Ljava/net/InetAddress;
       8: areturn

  public java.net.InetSocketAddress getSocketAddress(java.lang.String);
    Code:
       0: aload_0
       1: aload_1
       2: invokevirtual #15                 // Method get:(Ljava/lang/String;)Ljava/lang/String;
       5: invokestatic  #17                 // Method io/aeron/driver/uri/SocketAddressUtil.parse:(Ljava/lang/CharSequence;)Ljava/net/InetSocketAddress;
       8: areturn

  public java.net.InetSocketAddress getSocketAddress(java.lang.String, int, java.net.InetSocketAddress);
    Code:
       0: aload_0
       1: aload_1
       2: invokevirtual #18                 // Method containsKey:(Ljava/lang/String;)Z
       5: ifne          10
       8: aload_3
       9: areturn
      10: aload_0
      11: aload_1
      12: invokevirtual #15                 // Method get:(Ljava/lang/String;)Ljava/lang/String;
      15: iload_2
      16: invokestatic  #19                 // Method io/aeron/driver/uri/SocketAddressUtil.parse:(Ljava/lang/CharSequence;I)Ljava/net/InetSocketAddress;
      19: areturn

  public io.aeron.driver.uri.InterfaceSearchAddress getInterfaceSearchAddress(java.lang.String, io.aeron.driver.uri.InterfaceSearchAddress) throws java.net.UnknownHostException;
    Code:
       0: aload_0
       1: aload_1
       2: invokevirtual #18                 // Method containsKey:(Ljava/lang/String;)Z
       5: ifne          10
       8: aload_2
       9: areturn
      10: aload_0
      11: aload_1
      12: invokevirtual #15                 // Method get:(Ljava/lang/String;)Ljava/lang/String;
      15: invokestatic  #20                 // Method io/aeron/driver/uri/InterfaceSearchAddress.parse:(Ljava/lang/String;)Lio/aeron/driver/uri/InterfaceSearchAddress;
      18: areturn

  public boolean containsKey(java.lang.String);
    Code:
       0: aload_0
       1: getfield      #4                  // Field params:Ljava/util/Map;
       4: aload_1
       5: invokeinterface #21,  2           // InterfaceMethod java/util/Map.containsKey:(Ljava/lang/Object;)Z
      10: ireturn

  public boolean containsAnyKey(java.lang.String[]);
    Code:
       0: aload_1
       1: astore_2
       2: aload_2
       3: arraylength
       4: istore_3
       5: iconst_0
       6: istore        4
       8: iload         4
      10: iload_3
      11: if_icmpge     42
      14: aload_2
      15: iload         4
      17: aaload
      18: astore        5
      20: aload_0
      21: getfield      #4                  // Field params:Ljava/util/Map;
      24: aload         5
      26: invokeinterface #21,  2           // InterfaceMethod java/util/Map.containsKey:(Ljava/lang/Object;)Z
      31: ifeq          36
      34: iconst_1
      35: ireturn
      36: iinc          4, 1
      39: goto          8
      42: iconst_0
      43: ireturn

  public static io.aeron.driver.uri.AeronUri parse(java.lang.CharSequence);
    Code:
       0: aload_0
       1: ldc           #23                 // String aeron:
       3: invokestatic  #24                 // Method startsWith:(Ljava/lang/CharSequence;Ljava/lang/CharSequence;)Z
       6: ifne          41
       9: new           #25                 // class java/lang/IllegalArgumentException
      12: dup
      13: new           #26                 // class java/lang/StringBuilder
      16: dup
      17: invokespecial #27                 // Method java/lang/StringBuilder."<init>":()V
      20: ldc           #28                 // String AeronUri must start with \'aeron:\', found: \'
      22: invokevirtual #29                 // Method java/lang/StringBuilder.append:(Ljava/lang/String;)Ljava/lang/StringBuilder;
      25: aload_0
      26: invokevirtual #30                 // Method java/lang/StringBuilder.append:(Ljava/lang/Object;)Ljava/lang/StringBuilder;
      29: ldc           #31                 // String \'
      31: invokevirtual #29                 // Method java/lang/StringBuilder.append:(Ljava/lang/String;)Ljava/lang/StringBuilder;
      34: invokevirtual #32                 // Method java/lang/StringBuilder.toString:()Ljava/lang/String;
      37: invokespecial #33                 // Method java/lang/IllegalArgumentException."<init>":(Ljava/lang/String;)V
      40: athrow
      41: new           #26                 // class java/lang/StringBuilder
      44: dup
      45: invokespecial #27                 // Method java/lang/StringBuilder."<init>":()V
      48: astore_1
      49: ldc           #34                 // String aeron
      51: astore_2
      52: new           #35                 // class java/util/HashMap
      55: dup
      56: invokespecial #36                 // Method java/util/HashMap."<init>":()V
      59: astore_3
      60: aconst_null
      61: astore        4
      63: aconst_null
      64: astore        5
      66: getstatic     #37                 // Field io/aeron/driver/uri/AeronUri$State.MEDIA:Lio/aeron/driver/uri/AeronUri$State;
      69: astore        6
      71: ldc           #23                 // String aeron:
      73: invokevirtual #38                 // Method java/lang/String.length:()I
      76: istore        7
      78: iload         7
      80: aload_0
      81: invokeinterface #39,  1           // InterfaceMethod java/lang/CharSequence.length:()I
      86: if_icmpge     342
      89: aload_0
      90: iload         7
      92: invokeinterface #40,  2           // InterfaceMethod java/lang/CharSequence.charAt:(I)C
      97: istore        8
      99: getstatic     #41                 // Field io/aeron/driver/uri/AeronUri$1.$SwitchMap$io$aeron$driver$uri$AeronUri$State:[I
     102: aload         6
     104: invokevirtual #42                 // Method io/aeron/driver/uri/AeronUri$State.ordinal:()I
     107: iaload
     108: tableswitch   { // 1 to 3
                     1: 136
                     2: 203
                     3: 253
               default: 308
          }
     136: iload         8
     138: lookupswitch  { // 2
                    58: 183
                    63: 164
               default: 193
          }
     164: aload_1
     165: invokevirtual #32                 // Method java/lang/StringBuilder.toString:()Ljava/lang/String;
     168: astore        4
     170: aload_1
     171: iconst_0
     172: invokevirtual #43                 // Method java/lang/StringBuilder.setLength:(I)V
     175: getstatic     #44                 // Field io/aeron/driver/uri/AeronUri$State.PARAMS_KEY:Lio/aeron/driver/uri/AeronUri$State;
     178: astore        6
     180: goto          336
     183: new           #25                 // class java/lang/IllegalArgumentException
     186: dup
     187: ldc           #45                 // String Encountered \':\' within media definition
     189: invokespecial #33                 // Method java/lang/IllegalArgumentException."<init>":(Ljava/lang/String;)V
     192: athrow
     193: aload_1
     194: iload         8
     196: invokevirtual #46                 // Method java/lang/StringBuilder.append:(C)Ljava/lang/StringBuilder;
     199: pop
     200: goto          336
     203: iload         8
     205: lookupswitch  { // 1
                    61: 224
               default: 243
          }
     224: aload_1
     225: invokevirtual #32                 // Method java/lang/StringBuilder.toString:()Ljava/lang/String;
     228: astore        5
     230: aload_1
     231: iconst_0
     232: invokevirtual #43                 // Method java/lang/StringBuilder.setLength:(I)V
     235: getstatic     #47                 // Field io/aeron/driver/uri/AeronUri$State.PARAMS_VALUE:Lio/aeron/driver/uri/AeronUri$State;
     238: astore        6
     240: goto          336
     243: aload_1
     244: iload         8
     246: invokevirtual #46                 // Method java/lang/StringBuilder.append:(C)Ljava/lang/StringBuilder;
     249: pop
     250: goto          336
     253: iload         8
     255: lookupswitch  { // 1
                   124: 272
               default: 298
          }
     272: aload_3
     273: aload         5
     275: aload_1
     276: invokevirtual #32                 // Method java/lang/StringBuilder.toString:()Ljava/lang/String;
     279: invokeinterface #48,  3           // InterfaceMethod java/util/Map.put:(Ljava/lang/Object;Ljava/lang/Object;)Ljava/lang/Object;
     284: pop
     285: aload_1
     286: iconst_0
     287: invokevirtual #43                 // Method java/lang/StringBuilder.setLength:(I)V
     290: getstatic     #44                 // Field io/aeron/driver/uri/AeronUri$State.PARAMS_KEY:Lio/aeron/driver/uri/AeronUri$State;
     293: astore        6
     295: goto          336
     298: aload_1
     299: iload         8
     301: invokevirtual #46                 // Method java/lang/StringBuilder.append:(C)Ljava/lang/StringBuilder;
     304: pop
     305: goto          336
     308: new           #49                 // class java/lang/IllegalStateException
     311: dup
     312: new           #26                 // class java/lang/StringBuilder
     315: dup
     316: invokespecial #27                 // Method java/lang/StringBuilder."<init>":()V
     319: ldc           #50                 // String Que? State =
     321: invokevirtual #29                 // Method java/lang/StringBuilder.append:(Ljava/lang/String;)Ljava/lang/StringBuilder;
     324: aload         6
     326: invokevirtual #30                 // Method java/lang/StringBuilder.append:(Ljava/lang/Object;)Ljava/lang/StringBuilder;
     329: invokevirtual #32                 // Method java/lang/StringBuilder.toString:()Ljava/lang/String;
     332: invokespecial #51                 // Method java/lang/IllegalStateException."<init>":(Ljava/lang/String;)V
     335: athrow
     336: iinc          7, 1
     339: goto          78
     342: getstatic     #41                 // Field io/aeron/driver/uri/AeronUri$1.$SwitchMap$io$aeron$driver$uri$AeronUri$State:[I
     345: aload         6
     347: invokevirtual #42                 // Method io/aeron/driver/uri/AeronUri$State.ordinal:()I
     350: iaload
     351: lookupswitch  { // 2
                     1: 376
                     3: 385
               default: 401
          }
     376: aload_1
     377: invokevirtual #32                 // Method java/lang/StringBuilder.toString:()Ljava/lang/String;
     380: astore        4
     382: goto          429
     385: aload_3
     386: aload         5
     388: aload_1
     389: invokevirtual #32                 // Method java/lang/StringBuilder.toString:()Ljava/lang/String;
     392: invokeinterface #48,  3           // InterfaceMethod java/util/Map.put:(Ljava/lang/Object;Ljava/lang/Object;)Ljava/lang/Object;
     397: pop
     398: goto          429
     401: new           #25                 // class java/lang/IllegalArgumentException
     404: dup
     405: new           #26                 // class java/lang/StringBuilder
     408: dup
     409: invokespecial #27                 // Method java/lang/StringBuilder."<init>":()V
     412: ldc           #52                 // String No more input found, but was in state:
     414: invokevirtual #29                 // Method java/lang/StringBuilder.append:(Ljava/lang/String;)Ljava/lang/StringBuilder;
     417: aload         6
     419: invokevirtual #30                 // Method java/lang/StringBuilder.append:(Ljava/lang/Object;)Ljava/lang/StringBuilder;
     422: invokevirtual #32                 // Method java/lang/StringBuilder.toString:()Ljava/lang/String;
     425: invokespecial #33                 // Method java/lang/IllegalArgumentException."<init>":(Ljava/lang/String;)V
     428: athrow
     429: new           #22                 // class io/aeron/driver/uri/AeronUri
     432: dup
     433: ldc           #34                 // String aeron
     435: aload         4
     437: aload_3
     438: invokespecial #53                 // Method "<init>":(Ljava/lang/String;Ljava/lang/String;Ljava/util/Map;)V
     441: areturn

  private static boolean startsWith(java.lang.CharSequence, java.lang.CharSequence);
    Code:
       0: aload_0
       1: invokeinterface #39,  1           // InterfaceMethod java/lang/CharSequence.length:()I
       6: aload_1
       7: invokeinterface #39,  1           // InterfaceMethod java/lang/CharSequence.length:()I
      12: if_icmpge     17
      15: iconst_0
      16: ireturn
      17: iconst_0
      18: istore_2
      19: iload_2
      20: aload_1
      21: invokeinterface #39,  1           // InterfaceMethod java/lang/CharSequence.length:()I
      26: if_icmpge     54
      29: aload_0
      30: iload_2
      31: invokeinterface #40,  2           // InterfaceMethod java/lang/CharSequence.charAt:(I)C
      36: aload_1
      37: iload_2
      38: invokeinterface #40,  2           // InterfaceMethod java/lang/CharSequence.charAt:(I)C
      43: if_icmpeq     48
      46: iconst_0
      47: ireturn
      48: iinc          2, 1
      51: goto          19
      54: iconst_1
      55: ireturn

  public static io.aeron.driver.uri.AeronUri$Builder builder();
    Code:
       0: new           #54                 // class io/aeron/driver/uri/AeronUri$Builder
       3: dup
       4: invokespecial #55                 // Method io/aeron/driver/uri/AeronUri$Builder."<init>":()V
       7: areturn
}
