Compiled from "AeronUri.java"
public class io.aeron.driver.uri.AeronUri$Builder {
  private final java.util.Map<java.lang.String, java.lang.String> params;

  private java.lang.String media;

  public io.aeron.driver.uri.AeronUri$Builder();
    Code:
       0: aload_0
       1: invokespecial #1                  // Method java/lang/Object."<init>":()V
       4: aload_0
       5: new           #2                  // class java/util/HashMap
       8: dup
       9: invokespecial #3                  // Method java/util/HashMap."<init>":()V
      12: putfield      #4                  // Field params:Ljava/util/Map;
      15: return

  public io.aeron.driver.uri.AeronUri$Builder media(java.lang.String);
    Code:
       0: aload_0
       1: aload_1
       2: putfield      #5                  // Field media:Ljava/lang/String;
       5: aload_0
       6: areturn

  public io.aeron.driver.uri.AeronUri$Builder param(java.lang.String, java.lang.String);
    Code:
       0: aconst_null
       1: aload_1
       2: if_acmpeq     22
       5: aconst_null
       6: aload_2
       7: if_acmpeq     22
      10: aload_0
      11: getfield      #4                  // Field params:Ljava/util/Map;
      14: aload_1
      15: aload_2
      16: invokeinterface #6,  3            // InterfaceMethod java/util/Map.put:(Ljava/lang/Object;Ljava/lang/Object;)Ljava/lang/Object;
      21: pop
      22: aload_0
      23: areturn

  public io.aeron.driver.uri.AeronUri newInstance();
    Code:
       0: new           #7                  // class io/aeron/driver/uri/AeronUri
       3: dup
       4: ldc           #8                  // String aeron
       6: aload_0
       7: getfield      #5                  // Field media:Ljava/lang/String;
      10: aload_0
      11: getfield      #4                  // Field params:Ljava/util/Map;
      14: invokespecial #9                  // Method io/aeron/driver/uri/AeronUri."<init>":(Ljava/lang/String;Ljava/lang/String;Ljava/util/Map;)V
      17: areturn
}
