Compiled from "HttpServlet3RequestFactory.java"
final class org.springframework.security.web.servletapi.HttpServlet3RequestFactory implements org.springframework.security.web.servletapi.HttpServletRequestFactory {
  private org.apache.commons.logging.Log logger;

  private final java.lang.String rolePrefix;

  private org.springframework.security.authentication.AuthenticationTrustResolver trustResolver;

  private org.springframework.security.web.AuthenticationEntryPoint authenticationEntryPoint;

  private org.springframework.security.authentication.AuthenticationManager authenticationManager;

  private org.springframework.security.web.authentication.logout.LogoutHandler logoutHandler;

  org.springframework.security.web.servletapi.HttpServlet3RequestFactory(java.lang.String);
    Code:
       0: aload_0
       1: invokespecial #6                  // Method java/lang/Object."<init>":()V
       4: aload_0
       5: aload_0
       6: invokevirtual #7                  // Method java/lang/Object.getClass:()Ljava/lang/Class;
       9: invokestatic  #8                  // Method org/apache/commons/logging/LogFactory.getLog:(Ljava/lang/Class;)Lorg/apache/commons/logging/Log;
      12: putfield      #3                  // Field logger:Lorg/apache/commons/logging/Log;
      15: aload_0
      16: new           #9                  // class org/springframework/security/authentication/AuthenticationTrustResolverImpl
      19: dup
      20: invokespecial #10                 // Method org/springframework/security/authentication/AuthenticationTrustResolverImpl."<init>":()V
      23: putfield      #5                  // Field trustResolver:Lorg/springframework/security/authentication/AuthenticationTrustResolver;
      26: aload_0
      27: aload_1
      28: putfield      #11                 // Field rolePrefix:Ljava/lang/String;
      31: return

  public void setAuthenticationEntryPoint(org.springframework.security.web.AuthenticationEntryPoint);
    Code:
       0: aload_0
       1: aload_1
       2: putfield      #4                  // Field authenticationEntryPoint:Lorg/springframework/security/web/AuthenticationEntryPoint;
       5: return

  public void setAuthenticationManager(org.springframework.security.authentication.AuthenticationManager);
    Code:
       0: aload_0
       1: aload_1
       2: putfield      #2                  // Field authenticationManager:Lorg/springframework/security/authentication/AuthenticationManager;
       5: return

  public void setLogoutHandlers(java.util.List<org.springframework.security.web.authentication.logout.LogoutHandler>);
    Code:
       0: aload_0
       1: aload_1
       2: invokestatic  #12                 // Method org/springframework/util/CollectionUtils.isEmpty:(Ljava/util/Collection;)Z
       5: ifeq          12
       8: aconst_null
       9: goto          20
      12: new           #13                 // class org/springframework/security/web/authentication/logout/CompositeLogoutHandler
      15: dup
      16: aload_1
      17: invokespecial #14                 // Method org/springframework/security/web/authentication/logout/CompositeLogoutHandler."<init>":(Ljava/util/List;)V
      20: putfield      #1                  // Field logoutHandler:Lorg/springframework/security/web/authentication/logout/LogoutHandler;
      23: return

  public void setTrustResolver(org.springframework.security.authentication.AuthenticationTrustResolver);
    Code:
       0: aload_1
       1: ldc           #15                 // String trustResolver cannot be null
       3: invokestatic  #16                 // Method org/springframework/util/Assert.notNull:(Ljava/lang/Object;Ljava/lang/String;)V
       6: aload_0
       7: aload_1
       8: putfield      #5                  // Field trustResolver:Lorg/springframework/security/authentication/AuthenticationTrustResolver;
      11: return

  public javax.servlet.http.HttpServletRequest create(javax.servlet.http.HttpServletRequest, javax.servlet.http.HttpServletResponse);
    Code:
       0: new           #17                 // class org/springframework/security/web/servletapi/HttpServlet3RequestFactory$Servlet3SecurityContextHolderAwareRequestWrapper
       3: dup
       4: aload_0
       5: aload_1
       6: aload_0
       7: getfield      #11                 // Field rolePrefix:Ljava/lang/String;
      10: aload_2
      11: invokespecial #18                 // Method org/springframework/security/web/servletapi/HttpServlet3RequestFactory$Servlet3SecurityContextHolderAwareRequestWrapper."<init>":(Lorg/springframework/security/web/servletapi/HttpServlet3RequestFactory;Ljavax/servlet/http/HttpServletRequest;Ljava/lang/String;Ljavax/servlet/http/HttpServletResponse;)V
      14: areturn

  static org.springframework.security.authentication.AuthenticationTrustResolver access$000(org.springframework.security.web.servletapi.HttpServlet3RequestFactory);
    Code:
       0: aload_0
       1: getfield      #5                  // Field trustResolver:Lorg/springframework/security/authentication/AuthenticationTrustResolver;
       4: areturn

  static org.springframework.security.web.AuthenticationEntryPoint access$100(org.springframework.security.web.servletapi.HttpServlet3RequestFactory);
    Code:
       0: aload_0
       1: getfield      #4                  // Field authenticationEntryPoint:Lorg/springframework/security/web/AuthenticationEntryPoint;
       4: areturn

  static org.apache.commons.logging.Log access$200(org.springframework.security.web.servletapi.HttpServlet3RequestFactory);
    Code:
       0: aload_0
       1: getfield      #3                  // Field logger:Lorg/apache/commons/logging/Log;
       4: areturn

  static org.springframework.security.authentication.AuthenticationManager access$300(org.springframework.security.web.servletapi.HttpServlet3RequestFactory);
    Code:
       0: aload_0
       1: getfield      #2                  // Field authenticationManager:Lorg/springframework/security/authentication/AuthenticationManager;
       4: areturn

  static org.springframework.security.web.authentication.logout.LogoutHandler access$400(org.springframework.security.web.servletapi.HttpServlet3RequestFactory);
    Code:
       0: aload_0
       1: getfield      #1                  // Field logoutHandler:Lorg/springframework/security/web/authentication/logout/LogoutHandler;
       4: areturn
}
