Compiled from "Function2Ops.scala"
public final class scalaz.syntax.std.Function2Ops<T1, T2, R> {
  private final scala.Function2<T1, T2, R> scalaz$syntax$std$Function2Ops$$self;

  public static <T1, T2, R> boolean equals$extension(scala.Function2<T1, T2, R>, java.lang.Object);
    Code:
       0: getstatic     #28                 // Field scalaz/syntax/std/Function2Ops$.MODULE$:Lscalaz/syntax/std/Function2Ops$;
       3: ifnonnull     8
       6: aconst_null
       7: athrow
       8: aload_1
       9: instanceof    #2                  // class scalaz/syntax/std/Function2Ops
      12: ifeq          20
      15: iconst_1
      16: istore_2
      17: goto          22
      20: iconst_0
      21: istore_2
      22: iload_2
      23: ifeq          72
      26: aload_1
      27: ifnonnull     34
      30: aconst_null
      31: goto          41
      34: aload_1
      35: checkcast     #2                  // class scalaz/syntax/std/Function2Ops
      38: invokevirtual #31                 // Method scalaz$syntax$std$Function2Ops$$self:()Lscala/Function2;
      41: astore_3
      42: aload_0
      43: dup
      44: ifnonnull     55
      47: pop
      48: aload_3
      49: ifnull        62
      52: goto          66
      55: aload_3
      56: invokevirtual #35                 // Method java/lang/Object.equals:(Ljava/lang/Object;)Z
      59: ifeq          66
      62: iconst_1
      63: goto          67
      66: iconst_0
      67: ifeq          72
      70: iconst_1
      71: ireturn
      72: iconst_0
      73: ireturn

  public static <T1, T2, R> int hashCode$extension(scala.Function2<T1, T2, R>);
    Code:
       0: getstatic     #28                 // Field scalaz/syntax/std/Function2Ops$.MODULE$:Lscalaz/syntax/std/Function2Ops$;
       3: ifnonnull     8
       6: aconst_null
       7: athrow
       8: aload_0
       9: invokevirtual #44                 // Method java/lang/Object.hashCode:()I
      12: ireturn

  public static <T1, T2, R> scala.Function2<scala.Function0<T1>, scala.Function0<T2>, R> byName$extension(scala.Function2<T1, T2, R>);
    Code:
       0: getstatic     #28                 // Field scalaz/syntax/std/Function2Ops$.MODULE$:Lscalaz/syntax/std/Function2Ops$;
       3: ifnonnull     8
       6: aconst_null
       7: athrow
       8: aload_0
       9: invokedynamic #70,  0             // InvokeDynamic #0:apply:(Lscala/Function2;)Lscala/Function2;
      14: areturn

  public static <F, T1, T2, R> scala.Function2<F, F, F> lift$extension(scala.Function2<T1, T2, R>, scalaz.Applicative<F>);
    Code:
       0: getstatic     #28                 // Field scalaz/syntax/std/Function2Ops$.MODULE$:Lscalaz/syntax/std/Function2Ops$;
       3: ifnonnull     8
       6: aconst_null
       7: athrow
       8: aload_1
       9: aload_0
      10: invokeinterface #79,  2           // InterfaceMethod scalaz/Applicative.lift2:(Lscala/Function2;)Lscala/Function2;
      15: areturn

  public static <TT, T1, T2, R> scala.Function2<TT, TT, R> contramap$extension(scala.Function2<T1, T2, R>, scala.Function1<TT, T1>, scalaz.Leibniz<scala.runtime.Nothing$, java.lang.Object, T1, T2>);
    Code:
       0: getstatic     #28                 // Field scalaz/syntax/std/Function2Ops$.MODULE$:Lscalaz/syntax/std/Function2Ops$;
       3: ifnonnull     8
       6: aconst_null
       7: athrow
       8: aload_0
       9: aload_1
      10: aload_2
      11: invokedynamic #92,  0             // InvokeDynamic #1:apply:(Lscala/Function2;Lscala/Function1;Lscalaz/Leibniz;)Lscala/Function2;
      16: areturn

  public static <X, T1, T2, R> X on$extension(scala.Function2<T1, T2, R>, scala.Function2<R, R, X>, scala.Tuple2<T1, T1>, scala.Tuple2<T2, T2>);
    Code:
       0: getstatic     #28                 // Field scalaz/syntax/std/Function2Ops$.MODULE$:Lscalaz/syntax/std/Function2Ops$;
       3: ifnonnull     8
       6: aconst_null
       7: athrow
       8: aload_1
       9: aload_0
      10: aload_2
      11: invokevirtual #103                // Method scala/Tuple2._1:()Ljava/lang/Object;
      14: aload_3
      15: invokevirtual #103                // Method scala/Tuple2._1:()Ljava/lang/Object;
      18: invokeinterface #105,  3          // InterfaceMethod scala/Function2.apply:(Ljava/lang/Object;Ljava/lang/Object;)Ljava/lang/Object;
      23: aload_0
      24: aload_2
      25: invokevirtual #108                // Method scala/Tuple2._2:()Ljava/lang/Object;
      28: aload_3
      29: invokevirtual #108                // Method scala/Tuple2._2:()Ljava/lang/Object;
      32: invokeinterface #105,  3          // InterfaceMethod scala/Function2.apply:(Ljava/lang/Object;Ljava/lang/Object;)Ljava/lang/Object;
      37: invokeinterface #105,  3          // InterfaceMethod scala/Function2.apply:(Ljava/lang/Object;Ljava/lang/Object;)Ljava/lang/Object;
      42: areturn

  public static <T1, T2, R> scala.Function2<T2, T1, R> flip$extension(scala.Function2<T1, T2, R>);
    Code:
       0: getstatic     #28                 // Field scalaz/syntax/std/Function2Ops$.MODULE$:Lscalaz/syntax/std/Function2Ops$;
       3: ifnonnull     8
       6: aconst_null
       7: athrow
       8: aload_0
       9: invokedynamic #116,  0            // InvokeDynamic #2:apply:(Lscala/Function2;)Lscala/Function2;
      14: areturn

  public scala.Function2<T1, T2, R> scalaz$syntax$std$Function2Ops$$self();
    Code:
       0: aload_0
       1: getfield      #119                // Field scalaz$syntax$std$Function2Ops$$self:Lscala/Function2;
       4: areturn

  public scala.Function2<T2, T1, R> flip();
    Code:
       0: getstatic     #28                 // Field scalaz/syntax/std/Function2Ops$.MODULE$:Lscalaz/syntax/std/Function2Ops$;
       3: aload_0
       4: invokevirtual #31                 // Method scalaz$syntax$std$Function2Ops$$self:()Lscala/Function2;
       7: invokevirtual #125                // Method scalaz/syntax/std/Function2Ops$.flip$extension:(Lscala/Function2;)Lscala/Function2;
      10: areturn

  public <X> X on(scala.Function2<R, R, X>, scala.Tuple2<T1, T1>, scala.Tuple2<T2, T2>);
    Code:
       0: getstatic     #28                 // Field scalaz/syntax/std/Function2Ops$.MODULE$:Lscalaz/syntax/std/Function2Ops$;
       3: aload_0
       4: invokevirtual #31                 // Method scalaz$syntax$std$Function2Ops$$self:()Lscala/Function2;
       7: astore        4
       9: ifnonnull     14
      12: aconst_null
      13: athrow
      14: aload_1
      15: aload         4
      17: aload_2
      18: invokevirtual #103                // Method scala/Tuple2._1:()Ljava/lang/Object;
      21: aload_3
      22: invokevirtual #103                // Method scala/Tuple2._1:()Ljava/lang/Object;
      25: invokeinterface #105,  3          // InterfaceMethod scala/Function2.apply:(Ljava/lang/Object;Ljava/lang/Object;)Ljava/lang/Object;
      30: aload         4
      32: aload_2
      33: invokevirtual #108                // Method scala/Tuple2._2:()Ljava/lang/Object;
      36: aload_3
      37: invokevirtual #108                // Method scala/Tuple2._2:()Ljava/lang/Object;
      40: invokeinterface #105,  3          // InterfaceMethod scala/Function2.apply:(Ljava/lang/Object;Ljava/lang/Object;)Ljava/lang/Object;
      45: invokeinterface #105,  3          // InterfaceMethod scala/Function2.apply:(Ljava/lang/Object;Ljava/lang/Object;)Ljava/lang/Object;
      50: areturn

  public <TT> scala.Function2<TT, TT, R> contramap(scala.Function1<TT, T1>, scalaz.Leibniz<scala.runtime.Nothing$, java.lang.Object, T1, T2>);
    Code:
       0: getstatic     #28                 // Field scalaz/syntax/std/Function2Ops$.MODULE$:Lscalaz/syntax/std/Function2Ops$;
       3: aload_0
       4: invokevirtual #31                 // Method scalaz$syntax$std$Function2Ops$$self:()Lscala/Function2;
       7: astore_3
       8: ifnonnull     13
      11: aconst_null
      12: athrow
      13: aload_3
      14: aload_1
      15: aload_2
      16: invokedynamic #92,  0             // InvokeDynamic #1:apply:(Lscala/Function2;Lscala/Function1;Lscalaz/Leibniz;)Lscala/Function2;
      21: areturn

  public <F> scala.Function2<F, F, F> lift(scalaz.Applicative<F>);
    Code:
       0: getstatic     #28                 // Field scalaz/syntax/std/Function2Ops$.MODULE$:Lscalaz/syntax/std/Function2Ops$;
       3: aload_0
       4: invokevirtual #31                 // Method scalaz$syntax$std$Function2Ops$$self:()Lscala/Function2;
       7: aload_1
       8: invokevirtual #141                // Method scalaz/syntax/std/Function2Ops$.lift$extension:(Lscala/Function2;Lscalaz/Applicative;)Lscala/Function2;
      11: areturn

  public scala.Function2<scala.Function0<T1>, scala.Function0<T2>, R> byName();
    Code:
       0: getstatic     #28                 // Field scalaz/syntax/std/Function2Ops$.MODULE$:Lscalaz/syntax/std/Function2Ops$;
       3: aload_0
       4: invokevirtual #31                 // Method scalaz$syntax$std$Function2Ops$$self:()Lscala/Function2;
       7: invokevirtual #146                // Method scalaz/syntax/std/Function2Ops$.byName$extension:(Lscala/Function2;)Lscala/Function2;
      10: areturn

  public int hashCode();
    Code:
       0: getstatic     #28                 // Field scalaz/syntax/std/Function2Ops$.MODULE$:Lscalaz/syntax/std/Function2Ops$;
       3: aload_0
       4: invokevirtual #31                 // Method scalaz$syntax$std$Function2Ops$$self:()Lscala/Function2;
       7: invokevirtual #148                // Method scalaz/syntax/std/Function2Ops$.hashCode$extension:(Lscala/Function2;)I
      10: ireturn

  public boolean equals(java.lang.Object);
    Code:
       0: getstatic     #28                 // Field scalaz/syntax/std/Function2Ops$.MODULE$:Lscalaz/syntax/std/Function2Ops$;
       3: aload_0
       4: invokevirtual #31                 // Method scalaz$syntax$std$Function2Ops$$self:()Lscala/Function2;
       7: aload_1
       8: invokevirtual #150                // Method scalaz/syntax/std/Function2Ops$.equals$extension:(Lscala/Function2;Ljava/lang/Object;)Z
      11: ireturn

  public scalaz.syntax.std.Function2Ops(scala.Function2<T1, T2, R>);
    Code:
       0: aload_0
       1: aload_1
       2: putfield      #119                // Field scalaz$syntax$std$Function2Ops$$self:Lscala/Function2;
       5: aload_0
       6: invokespecial #158                // Method java/lang/Object."<init>":()V
       9: return

  private static java.lang.Object $deserializeLambda$(java.lang.invoke.SerializedLambda);
    Code:
       0: aload_0
       1: invokedynamic #170,  0            // InvokeDynamic #3:lambdaDeserialize:(Ljava/lang/invoke/SerializedLambda;)Ljava/lang/Object;
       6: areturn
}
