Compiled from "JuzuServlet.java"
public class juzu.test.protocol.servlet.JuzuServlet extends juzu.impl.bridge.spi.servlet.ServletBridge {
  public juzu.test.protocol.servlet.JuzuServlet();
    Code:
       0: aload_0
       1: invokespecial #1                  // Method juzu/impl/bridge/spi/servlet/ServletBridge."<init>":()V
       4: return

  protected java.lang.String getApplicationName(javax.servlet.ServletConfig);
    Code:
       0: invokestatic  #2                  // Method juzu/test/AbstractWebTestCase.asDefault:()Z
       3: ifeq          15
       6: invokestatic  #3                  // Method juzu/test/AbstractWebTestCase.getApplicationName:()Ljuzu/impl/common/Name;
       9: invokevirtual #4                  // Method juzu/impl/common/Name.toString:()Ljava/lang/String;
      12: goto          16
      15: aconst_null
      16: areturn
}
