Compiled from "Archive.java"
public class org.apache.commons.compress.harmony.unpack200.Archive {
  private java.io.InputStream inputStream;

  private final java.util.jar.JarOutputStream outputStream;

  private boolean removePackFile;

  private int logLevel;

  private java.io.FileOutputStream logFile;

  private boolean overrideDeflateHint;

  private boolean deflateHint;

  private java.lang.String inputFileName;

  private java.lang.String outputFileName;

  public org.apache.commons.compress.harmony.unpack200.Archive(java.lang.String, java.lang.String) throws java.io.FileNotFoundException, java.io.IOException;
    Code:
       0: aload_0
       1: invokespecial #1                  // Method java/lang/Object."<init>":()V
       4: aload_0
       5: iconst_1
       6: putfield      #3                  // Field logLevel:I
       9: aload_0
      10: aload_1
      11: putfield      #4                  // Field inputFileName:Ljava/lang/String;
      14: aload_0
      15: aload_2
      16: putfield      #5                  // Field outputFileName:Ljava/lang/String;
      19: aload_0
      20: new           #6                  // class java/io/FileInputStream
      23: dup
      24: aload_1
      25: invokespecial #7                  // Method java/io/FileInputStream."<init>":(Ljava/lang/String;)V
      28: putfield      #8                  // Field inputStream:Ljava/io/InputStream;
      31: aload_0
      32: new           #9                  // class java/util/jar/JarOutputStream
      35: dup
      36: new           #10                 // class java/io/BufferedOutputStream
      39: dup
      40: new           #11                 // class java/io/FileOutputStream
      43: dup
      44: aload_2
      45: invokespecial #12                 // Method java/io/FileOutputStream."<init>":(Ljava/lang/String;)V
      48: invokespecial #13                 // Method java/io/BufferedOutputStream."<init>":(Ljava/io/OutputStream;)V
      51: invokespecial #14                 // Method java/util/jar/JarOutputStream."<init>":(Ljava/io/OutputStream;)V
      54: putfield      #15                 // Field outputStream:Ljava/util/jar/JarOutputStream;
      57: return

  public org.apache.commons.compress.harmony.unpack200.Archive(java.io.InputStream, java.util.jar.JarOutputStream) throws java.io.IOException;
    Code:
       0: aload_0
       1: invokespecial #1                  // Method java/lang/Object."<init>":()V
       4: aload_0
       5: iconst_1
       6: putfield      #3                  // Field logLevel:I
       9: aload_0
      10: aload_1
      11: putfield      #8                  // Field inputStream:Ljava/io/InputStream;
      14: aload_0
      15: aload_2
      16: putfield      #15                 // Field outputStream:Ljava/util/jar/JarOutputStream;
      19: return

  public void unpack() throws org.apache.commons.compress.harmony.pack200.Pack200Exception, java.io.IOException;
    Code:
       0: aload_0
       1: getfield      #15                 // Field outputStream:Ljava/util/jar/JarOutputStream;
       4: ldc           #16                 // String PACK200
       6: invokevirtual #17                 // Method java/util/jar/JarOutputStream.setComment:(Ljava/lang/String;)V
       9: aload_0
      10: getfield      #8                  // Field inputStream:Ljava/io/InputStream;
      13: invokevirtual #18                 // Method java/io/InputStream.markSupported:()Z
      16: ifne          52
      19: aload_0
      20: new           #19                 // class java/io/BufferedInputStream
      23: dup
      24: aload_0
      25: getfield      #8                  // Field inputStream:Ljava/io/InputStream;
      28: invokespecial #20                 // Method java/io/BufferedInputStream."<init>":(Ljava/io/InputStream;)V
      31: putfield      #8                  // Field inputStream:Ljava/io/InputStream;
      34: aload_0
      35: getfield      #8                  // Field inputStream:Ljava/io/InputStream;
      38: invokevirtual #18                 // Method java/io/InputStream.markSupported:()Z
      41: ifne          52
      44: new           #21                 // class java/lang/IllegalStateException
      47: dup
      48: invokespecial #22                 // Method java/lang/IllegalStateException."<init>":()V
      51: athrow
      52: aload_0
      53: getfield      #8                  // Field inputStream:Ljava/io/InputStream;
      56: iconst_2
      57: invokevirtual #23                 // Method java/io/InputStream.mark:(I)V
      60: aload_0
      61: getfield      #8                  // Field inputStream:Ljava/io/InputStream;
      64: invokevirtual #24                 // Method java/io/InputStream.read:()I
      67: sipush        255
      70: iand
      71: aload_0
      72: getfield      #8                  // Field inputStream:Ljava/io/InputStream;
      75: invokevirtual #24                 // Method java/io/InputStream.read:()I
      78: sipush        255
      81: iand
      82: bipush        8
      84: ishl
      85: ior
      86: ldc           #26                 // int 35615
      88: if_icmpne     123
      91: aload_0
      92: getfield      #8                  // Field inputStream:Ljava/io/InputStream;
      95: invokevirtual #27                 // Method java/io/InputStream.reset:()V
      98: aload_0
      99: new           #19                 // class java/io/BufferedInputStream
     102: dup
     103: new           #25                 // class java/util/zip/GZIPInputStream
     106: dup
     107: aload_0
     108: getfield      #8                  // Field inputStream:Ljava/io/InputStream;
     111: invokespecial #28                 // Method java/util/zip/GZIPInputStream."<init>":(Ljava/io/InputStream;)V
     114: invokespecial #20                 // Method java/io/BufferedInputStream."<init>":(Ljava/io/InputStream;)V
     117: putfield      #8                  // Field inputStream:Ljava/io/InputStream;
     120: goto          130
     123: aload_0
     124: getfield      #8                  // Field inputStream:Ljava/io/InputStream;
     127: invokevirtual #27                 // Method java/io/InputStream.reset:()V
     130: aload_0
     131: getfield      #8                  // Field inputStream:Ljava/io/InputStream;
     134: iconst_4
     135: invokevirtual #23                 // Method java/io/InputStream.mark:(I)V
     138: iconst_4
     139: newarray       int
     141: dup
     142: iconst_0
     143: sipush        202
     146: iastore
     147: dup
     148: iconst_1
     149: sipush        254
     152: iastore
     153: dup
     154: iconst_2
     155: sipush        208
     158: iastore
     159: dup
     160: iconst_3
     161: bipush        13
     163: iastore
     164: astore_1
     165: iconst_4
     166: newarray       int
     168: astore_2
     169: iconst_0
     170: istore_3
     171: iload_3
     172: aload_2
     173: arraylength
     174: if_icmpge     193
     177: aload_2
     178: iload_3
     179: aload_0
     180: getfield      #8                  // Field inputStream:Ljava/io/InputStream;
     183: invokevirtual #24                 // Method java/io/InputStream.read:()I
     186: iastore
     187: iinc          3, 1
     190: goto          171
     193: iconst_0
     194: istore_3
     195: iconst_0
     196: istore        4
     198: iload         4
     200: aload_1
     201: arraylength
     202: if_icmpge     224
     205: aload_2
     206: iload         4
     208: iaload
     209: aload_1
     210: iload         4
     212: iaload
     213: if_icmpeq     218
     216: iconst_1
     217: istore_3
     218: iinc          4, 1
     221: goto          198
     224: aload_0
     225: getfield      #8                  // Field inputStream:Ljava/io/InputStream;
     228: invokevirtual #27                 // Method java/io/InputStream.reset:()V
     231: iload_3
     232: ifeq          327
     235: new           #29                 // class java/util/jar/JarInputStream
     238: dup
     239: aload_0
     240: getfield      #8                  // Field inputStream:Ljava/io/InputStream;
     243: invokespecial #30                 // Method java/util/jar/JarInputStream."<init>":(Ljava/io/InputStream;)V
     246: astore        4
     248: aload         4
     250: invokevirtual #31                 // Method java/util/jar/JarInputStream.getNextJarEntry:()Ljava/util/jar/JarEntry;
     253: dup
     254: astore        5
     256: ifnull        324
     259: aload_0
     260: getfield      #15                 // Field outputStream:Ljava/util/jar/JarOutputStream;
     263: aload         5
     265: invokevirtual #32                 // Method java/util/jar/JarOutputStream.putNextEntry:(Ljava/util/zip/ZipEntry;)V
     268: sipush        16384
     271: newarray       byte
     273: astore        6
     275: aload         4
     277: aload         6
     279: invokevirtual #33                 // Method java/util/jar/JarInputStream.read:([B)I
     282: istore        7
     284: iload         7
     286: iconst_m1
     287: if_icmpeq     314
     290: aload_0
     291: getfield      #15                 // Field outputStream:Ljava/util/jar/JarOutputStream;
     294: aload         6
     296: iconst_0
     297: iload         7
     299: invokevirtual #34                 // Method java/util/jar/JarOutputStream.write:([BII)V
     302: aload         4
     304: aload         6
     306: invokevirtual #33                 // Method java/util/jar/JarInputStream.read:([B)I
     309: istore        7
     311: goto          284
     314: aload_0
     315: getfield      #15                 // Field outputStream:Ljava/util/jar/JarOutputStream;
     318: invokevirtual #35                 // Method java/util/jar/JarOutputStream.closeEntry:()V
     321: goto          248
     324: goto          528
     327: iconst_0
     328: istore        4
     330: aload_0
     331: aload_0
     332: getfield      #8                  // Field inputStream:Ljava/io/InputStream;
     335: invokespecial #36                 // Method available:(Ljava/io/InputStream;)Z
     338: ifeq          528
     341: iinc          4, 1
     344: new           #2                  // class org/apache/commons/compress/harmony/unpack200/Segment
     347: dup
     348: invokespecial #37                 // Method org/apache/commons/compress/harmony/unpack200/Segment."<init>":()V
     351: astore        5
     353: aload         5
     355: aload_0
     356: getfield      #3                  // Field logLevel:I
     359: invokevirtual #38                 // Method org/apache/commons/compress/harmony/unpack200/Segment.setLogLevel:(I)V
     362: aload         5
     364: aload_0
     365: getfield      #39                 // Field logFile:Ljava/io/FileOutputStream;
     368: ifnull        378
     371: aload_0
     372: getfield      #39                 // Field logFile:Ljava/io/FileOutputStream;
     375: goto          381
     378: getstatic     #40                 // Field java/lang/System.out:Ljava/io/PrintStream;
     381: invokevirtual #41                 // Method org/apache/commons/compress/harmony/unpack200/Segment.setLogStream:(Ljava/io/OutputStream;)V
     384: aload         5
     386: iconst_0
     387: invokevirtual #42                 // Method org/apache/commons/compress/harmony/unpack200/Segment.setPreRead:(Z)V
     390: iload         4
     392: iconst_1
     393: if_icmpne     436
     396: aload         5
     398: iconst_2
     399: new           #43                 // class java/lang/StringBuilder
     402: dup
     403: invokespecial #44                 // Method java/lang/StringBuilder."<init>":()V
     406: ldc           #45                 // String Unpacking from
     408: invokevirtual #46                 // Method java/lang/StringBuilder.append:(Ljava/lang/String;)Ljava/lang/StringBuilder;
     411: aload_0
     412: getfield      #4                  // Field inputFileName:Ljava/lang/String;
     415: invokevirtual #46                 // Method java/lang/StringBuilder.append:(Ljava/lang/String;)Ljava/lang/StringBuilder;
     418: ldc           #47                 // String  to
     420: invokevirtual #46                 // Method java/lang/StringBuilder.append:(Ljava/lang/String;)Ljava/lang/StringBuilder;
     423: aload_0
     424: getfield      #5                  // Field outputFileName:Ljava/lang/String;
     427: invokevirtual #46                 // Method java/lang/StringBuilder.append:(Ljava/lang/String;)Ljava/lang/StringBuilder;
     430: invokevirtual #48                 // Method java/lang/StringBuilder.toString:()Ljava/lang/String;
     433: invokevirtual #49                 // Method org/apache/commons/compress/harmony/unpack200/Segment.log:(ILjava/lang/String;)V
     436: aload         5
     438: iconst_2
     439: new           #43                 // class java/lang/StringBuilder
     442: dup
     443: invokespecial #44                 // Method java/lang/StringBuilder."<init>":()V
     446: ldc           #50                 // String Reading segment
     448: invokevirtual #46                 // Method java/lang/StringBuilder.append:(Ljava/lang/String;)Ljava/lang/StringBuilder;
     451: iload         4
     453: invokevirtual #51                 // Method java/lang/StringBuilder.append:(I)Ljava/lang/StringBuilder;
     456: invokevirtual #48                 // Method java/lang/StringBuilder.toString:()Ljava/lang/String;
     459: invokevirtual #49                 // Method org/apache/commons/compress/harmony/unpack200/Segment.log:(ILjava/lang/String;)V
     462: aload_0
     463: getfield      #52                 // Field overrideDeflateHint:Z
     466: ifeq          478
     469: aload         5
     471: aload_0
     472: getfield      #53                 // Field deflateHint:Z
     475: invokevirtual #54                 // Method org/apache/commons/compress/harmony/unpack200/Segment.overrideDeflateHint:(Z)V
     478: aload         5
     480: aload_0
     481: getfield      #8                  // Field inputStream:Ljava/io/InputStream;
     484: aload_0
     485: getfield      #15                 // Field outputStream:Ljava/util/jar/JarOutputStream;
     488: invokevirtual #55                 // Method org/apache/commons/compress/harmony/unpack200/Segment.unpack:(Ljava/io/InputStream;Ljava/util/jar/JarOutputStream;)V
     491: aload_0
     492: getfield      #15                 // Field outputStream:Ljava/util/jar/JarOutputStream;
     495: invokevirtual #56                 // Method java/util/jar/JarOutputStream.flush:()V
     498: aload_0
     499: getfield      #8                  // Field inputStream:Ljava/io/InputStream;
     502: instanceof    #6                  // class java/io/FileInputStream
     505: ifeq          525
     508: aload_0
     509: aload_0
     510: getfield      #8                  // Field inputStream:Ljava/io/InputStream;
     513: checkcast     #6                  // class java/io/FileInputStream
     516: invokevirtual #57                 // Method java/io/FileInputStream.getFD:()Ljava/io/FileDescriptor;
     519: invokevirtual #58                 // Method java/lang/Object.toString:()Ljava/lang/String;
     522: putfield      #4                  // Field inputFileName:Ljava/lang/String;
     525: goto          330
     528: aload_0
     529: getfield      #8                  // Field inputStream:Ljava/io/InputStream;
     532: invokevirtual #59                 // Method java/io/InputStream.close:()V
     535: goto          539
     538: astore_1
     539: aload_0
     540: getfield      #15                 // Field outputStream:Ljava/util/jar/JarOutputStream;
     543: invokevirtual #61                 // Method java/util/jar/JarOutputStream.close:()V
     546: goto          550
     549: astore_1
     550: aload_0
     551: getfield      #39                 // Field logFile:Ljava/io/FileOutputStream;
     554: ifnull        619
     557: aload_0
     558: getfield      #39                 // Field logFile:Ljava/io/FileOutputStream;
     561: invokevirtual #62                 // Method java/io/FileOutputStream.close:()V
     564: goto          619
     567: astore_1
     568: goto          619
     571: astore        8
     573: aload_0
     574: getfield      #8                  // Field inputStream:Ljava/io/InputStream;
     577: invokevirtual #59                 // Method java/io/InputStream.close:()V
     580: goto          585
     583: astore        9
     585: aload_0
     586: getfield      #15                 // Field outputStream:Ljava/util/jar/JarOutputStream;
     589: invokevirtual #61                 // Method java/util/jar/JarOutputStream.close:()V
     592: goto          597
     595: astore        9
     597: aload_0
     598: getfield      #39                 // Field logFile:Ljava/io/FileOutputStream;
     601: ifnull        616
     604: aload_0
     605: getfield      #39                 // Field logFile:Ljava/io/FileOutputStream;
     608: invokevirtual #62                 // Method java/io/FileOutputStream.close:()V
     611: goto          616
     614: astore        9
     616: aload         8
     618: athrow
     619: aload_0
     620: getfield      #63                 // Field removePackFile:Z
     623: ifeq          666
     626: iconst_0
     627: istore_1
     628: aload_0
     629: getfield      #4                  // Field inputFileName:Ljava/lang/String;
     632: ifnull        652
     635: new           #64                 // class java/io/File
     638: dup
     639: aload_0
     640: getfield      #4                  // Field inputFileName:Ljava/lang/String;
     643: invokespecial #65                 // Method java/io/File."<init>":(Ljava/lang/String;)V
     646: astore_2
     647: aload_2
     648: invokevirtual #66                 // Method java/io/File.delete:()Z
     651: istore_1
     652: iload_1
     653: ifne          666
     656: new           #67                 // class org/apache/commons/compress/harmony/pack200/Pack200Exception
     659: dup
     660: ldc           #68                 // String Failed to delete the input file.
     662: invokespecial #69                 // Method org/apache/commons/compress/harmony/pack200/Pack200Exception."<init>":(Ljava/lang/String;)V
     665: athrow
     666: return
    Exception table:
       from    to  target type
         528   535   538   Class java/lang/Exception
         539   546   549   Class java/lang/Exception
         557   564   567   Class java/lang/Exception
           9   528   571   any
         573   580   583   Class java/lang/Exception
         585   592   595   Class java/lang/Exception
         604   611   614   Class java/lang/Exception
         571   573   571   any

  private boolean available(java.io.InputStream) throws java.io.IOException;
    Code:
       0: aload_1
       1: iconst_1
       2: invokevirtual #23                 // Method java/io/InputStream.mark:(I)V
       5: aload_1
       6: invokevirtual #24                 // Method java/io/InputStream.read:()I
       9: istore_2
      10: aload_1
      11: invokevirtual #27                 // Method java/io/InputStream.reset:()V
      14: iload_2
      15: iconst_m1
      16: if_icmpeq     23
      19: iconst_1
      20: goto          24
      23: iconst_0
      24: ireturn

  public void setRemovePackFile(boolean);
    Code:
       0: aload_0
       1: iload_1
       2: putfield      #63                 // Field removePackFile:Z
       5: return

  public void setVerbose(boolean);
    Code:
       0: iload_1
       1: ifeq          12
       4: aload_0
       5: iconst_2
       6: putfield      #3                  // Field logLevel:I
       9: goto          25
      12: aload_0
      13: getfield      #3                  // Field logLevel:I
      16: iconst_2
      17: if_icmpne     25
      20: aload_0
      21: iconst_1
      22: putfield      #3                  // Field logLevel:I
      25: return

  public void setQuiet(boolean);
    Code:
       0: iload_1
       1: ifeq          12
       4: aload_0
       5: iconst_0
       6: putfield      #3                  // Field logLevel:I
       9: goto          24
      12: aload_0
      13: getfield      #3                  // Field logLevel:I
      16: ifne          24
      19: aload_0
      20: iconst_0
      21: putfield      #3                  // Field logLevel:I
      24: return

  public void setLogFile(java.lang.String) throws java.io.FileNotFoundException;
    Code:
       0: aload_0
       1: new           #11                 // class java/io/FileOutputStream
       4: dup
       5: aload_1
       6: invokespecial #12                 // Method java/io/FileOutputStream."<init>":(Ljava/lang/String;)V
       9: putfield      #39                 // Field logFile:Ljava/io/FileOutputStream;
      12: return

  public void setLogFile(java.lang.String, boolean) throws java.io.FileNotFoundException;
    Code:
       0: aload_0
       1: new           #11                 // class java/io/FileOutputStream
       4: dup
       5: aload_1
       6: iload_2
       7: invokespecial #70                 // Method java/io/FileOutputStream."<init>":(Ljava/lang/String;Z)V
      10: putfield      #39                 // Field logFile:Ljava/io/FileOutputStream;
      13: return

  public void setDeflateHint(boolean);
    Code:
       0: aload_0
       1: iconst_1
       2: putfield      #52                 // Field overrideDeflateHint:Z
       5: aload_0
       6: iload_1
       7: putfield      #53                 // Field deflateHint:Z
      10: return
}
