Compiled from "AjpClientConnection.java"
class io.undertow.client.ajp.AjpClientConnection$ClientReceiveListener$1 implements java.lang.Runnable {
  final io.undertow.client.ajp.AjpClientConnection$ClientReceiveListener this$1;

  io.undertow.client.ajp.AjpClientConnection$ClientReceiveListener$1(io.undertow.client.ajp.AjpClientConnection$ClientReceiveListener);
    Code:
       0: aload_0
       1: aload_1
       2: putfield      #1                  // Field this$1:Lio/undertow/client/ajp/AjpClientConnection$ClientReceiveListener;
       5: aload_0
       6: invokespecial #2                  // Method java/lang/Object."<init>":()V
       9: return

  public void run();
    Code:
       0: aload_0
       1: getfield      #1                  // Field this$1:Lio/undertow/client/ajp/AjpClientConnection$ClientReceiveListener;
       4: getfield      #3                  // Field io/undertow/client/ajp/AjpClientConnection$ClientReceiveListener.this$0:Lio/undertow/client/ajp/AjpClientConnection;
       7: getfield      #4                  // Field io/undertow/client/ajp/AjpClientConnection.currentRequest:Lio/undertow/client/ajp/AjpClientExchange;
      10: ifnull        33
      13: aload_0
      14: getfield      #1                  // Field this$1:Lio/undertow/client/ajp/AjpClientConnection$ClientReceiveListener;
      17: getfield      #3                  // Field io/undertow/client/ajp/AjpClientConnection$ClientReceiveListener.this$0:Lio/undertow/client/ajp/AjpClientConnection;
      20: getfield      #4                  // Field io/undertow/client/ajp/AjpClientConnection.currentRequest:Lio/undertow/client/ajp/AjpClientExchange;
      23: new           #5                  // class java/nio/channels/ClosedChannelException
      26: dup
      27: invokespecial #6                  // Method java/nio/channels/ClosedChannelException."<init>":()V
      30: invokevirtual #7                  // Method io/undertow/client/ajp/AjpClientExchange.setFailed:(Ljava/io/IOException;)V
      33: return
}
