Compiled from "ListGroupResourcesItem.scala"
public final class zio.aws.resourcegroups.model.ListGroupResourcesItem implements scala.Product,scala.Serializable {
  private final zio.prelude.data.Optional<zio.aws.resourcegroups.model.ResourceIdentifier> identifier;

  private final zio.prelude.data.Optional<zio.aws.resourcegroups.model.ResourceStatus> status;

  public static zio.prelude.data.Optional<zio.aws.resourcegroups.model.ResourceStatus> $lessinit$greater$default$2();
    Code:
       0: getstatic     #47                 // Field zio/aws/resourcegroups/model/ListGroupResourcesItem$.MODULE$:Lzio/aws/resourcegroups/model/ListGroupResourcesItem$;
       3: invokevirtual #49                 // Method zio/aws/resourcegroups/model/ListGroupResourcesItem$.$lessinit$greater$default$2:()Lzio/prelude/data/Optional;
       6: areturn

  public static zio.prelude.data.Optional<zio.aws.resourcegroups.model.ResourceIdentifier> $lessinit$greater$default$1();
    Code:
       0: getstatic     #47                 // Field zio/aws/resourcegroups/model/ListGroupResourcesItem$.MODULE$:Lzio/aws/resourcegroups/model/ListGroupResourcesItem$;
       3: invokevirtual #53                 // Method zio/aws/resourcegroups/model/ListGroupResourcesItem$.$lessinit$greater$default$1:()Lzio/prelude/data/Optional;
       6: areturn

  public static scala.Option<scala.Tuple2<zio.prelude.data.Optional<zio.aws.resourcegroups.model.ResourceIdentifier>, zio.prelude.data.Optional<zio.aws.resourcegroups.model.ResourceStatus>>> unapply(zio.aws.resourcegroups.model.ListGroupResourcesItem);
    Code:
       0: getstatic     #47                 // Field zio/aws/resourcegroups/model/ListGroupResourcesItem$.MODULE$:Lzio/aws/resourcegroups/model/ListGroupResourcesItem$;
       3: aload_0
       4: invokevirtual #59                 // Method zio/aws/resourcegroups/model/ListGroupResourcesItem$.unapply:(Lzio/aws/resourcegroups/model/ListGroupResourcesItem;)Lscala/Option;
       7: areturn

  public static zio.prelude.data.Optional<zio.aws.resourcegroups.model.ResourceStatus> apply$default$2();
    Code:
       0: getstatic     #47                 // Field zio/aws/resourcegroups/model/ListGroupResourcesItem$.MODULE$:Lzio/aws/resourcegroups/model/ListGroupResourcesItem$;
       3: invokevirtual #62                 // Method zio/aws/resourcegroups/model/ListGroupResourcesItem$.apply$default$2:()Lzio/prelude/data/Optional;
       6: areturn

  public static zio.prelude.data.Optional<zio.aws.resourcegroups.model.ResourceIdentifier> apply$default$1();
    Code:
       0: getstatic     #47                 // Field zio/aws/resourcegroups/model/ListGroupResourcesItem$.MODULE$:Lzio/aws/resourcegroups/model/ListGroupResourcesItem$;
       3: invokevirtual #65                 // Method zio/aws/resourcegroups/model/ListGroupResourcesItem$.apply$default$1:()Lzio/prelude/data/Optional;
       6: areturn

  public static zio.aws.resourcegroups.model.ListGroupResourcesItem apply(zio.prelude.data.Optional<zio.aws.resourcegroups.model.ResourceIdentifier>, zio.prelude.data.Optional<zio.aws.resourcegroups.model.ResourceStatus>);
    Code:
       0: getstatic     #47                 // Field zio/aws/resourcegroups/model/ListGroupResourcesItem$.MODULE$:Lzio/aws/resourcegroups/model/ListGroupResourcesItem$;
       3: aload_0
       4: aload_1
       5: invokevirtual #70                 // Method zio/aws/resourcegroups/model/ListGroupResourcesItem$.apply:(Lzio/prelude/data/Optional;Lzio/prelude/data/Optional;)Lzio/aws/resourcegroups/model/ListGroupResourcesItem;
       8: areturn

  public static zio.aws.resourcegroups.model.ListGroupResourcesItem$ReadOnly wrap(software.amazon.awssdk.services.resourcegroups.model.ListGroupResourcesItem);
    Code:
       0: getstatic     #47                 // Field zio/aws/resourcegroups/model/ListGroupResourcesItem$.MODULE$:Lzio/aws/resourcegroups/model/ListGroupResourcesItem$;
       3: aload_0
       4: invokevirtual #75                 // Method zio/aws/resourcegroups/model/ListGroupResourcesItem$.wrap:(Lsoftware/amazon/awssdk/services/resourcegroups/model/ListGroupResourcesItem;)Lzio/aws/resourcegroups/model/ListGroupResourcesItem$ReadOnly;
       7: areturn

  public zio.prelude.data.Optional<zio.aws.resourcegroups.model.ResourceIdentifier> identifier();
    Code:
       0: aload_0
       1: getfield      #77                 // Field identifier:Lzio/prelude/data/Optional;
       4: areturn

  public zio.prelude.data.Optional<zio.aws.resourcegroups.model.ResourceStatus> status();
    Code:
       0: aload_0
       1: getfield      #81                 // Field status:Lzio/prelude/data/Optional;
       4: areturn

  public software.amazon.awssdk.services.resourcegroups.model.ListGroupResourcesItem buildAwsValue();
    Code:
       0: getstatic     #47                 // Field zio/aws/resourcegroups/model/ListGroupResourcesItem$.MODULE$:Lzio/aws/resourcegroups/model/ListGroupResourcesItem$;
       3: invokevirtual #87                 // Method zio/aws/resourcegroups/model/ListGroupResourcesItem$.zio$aws$resourcegroups$model$ListGroupResourcesItem$$zioAwsBuilderHelper:()Lzio/aws/core/BuilderHelper;
       6: getstatic     #47                 // Field zio/aws/resourcegroups/model/ListGroupResourcesItem$.MODULE$:Lzio/aws/resourcegroups/model/ListGroupResourcesItem$;
       9: invokevirtual #87                 // Method zio/aws/resourcegroups/model/ListGroupResourcesItem$.zio$aws$resourcegroups$model$ListGroupResourcesItem$$zioAwsBuilderHelper:()Lzio/aws/core/BuilderHelper;
      12: invokestatic  #91                 // Method software/amazon/awssdk/services/resourcegroups/model/ListGroupResourcesItem.builder:()Lsoftware/amazon/awssdk/services/resourcegroups/model/ListGroupResourcesItem$Builder;
      15: invokeinterface #94,  2           // InterfaceMethod zio/aws/core/BuilderHelper.BuilderOps:(Lsoftware/amazon/awssdk/utils/builder/SdkBuilder;)Lzio/aws/core/BuilderHelper$BuilderOps;
      20: aload_0
      21: invokevirtual #96                 // Method identifier:()Lzio/prelude/data/Optional;
      24: invokedynamic #116,  0            // InvokeDynamic #0:apply:()Lscala/Function1;
      29: invokeinterface #122,  2          // InterfaceMethod zio/prelude/data/Optional.map:(Lscala/Function1;)Lzio/prelude/data/Optional;
      34: invokedynamic #129,  0            // InvokeDynamic #1:apply:()Lscala/Function1;
      39: invokevirtual #133                // Method zio/aws/core/BuilderHelper$BuilderOps.optionallyWith:(Lzio/prelude/data/Optional;Lscala/Function1;)Lsoftware/amazon/awssdk/utils/builder/SdkBuilder;
      42: invokeinterface #94,  2           // InterfaceMethod zio/aws/core/BuilderHelper.BuilderOps:(Lsoftware/amazon/awssdk/utils/builder/SdkBuilder;)Lzio/aws/core/BuilderHelper$BuilderOps;
      47: aload_0
      48: invokevirtual #135                // Method status:()Lzio/prelude/data/Optional;
      51: invokedynamic #142,  0            // InvokeDynamic #2:apply:()Lscala/Function1;
      56: invokeinterface #122,  2          // InterfaceMethod zio/prelude/data/Optional.map:(Lscala/Function1;)Lzio/prelude/data/Optional;
      61: invokedynamic #147,  0            // InvokeDynamic #3:apply:()Lscala/Function1;
      66: invokevirtual #133                // Method zio/aws/core/BuilderHelper$BuilderOps.optionallyWith:(Lzio/prelude/data/Optional;Lscala/Function1;)Lsoftware/amazon/awssdk/utils/builder/SdkBuilder;
      69: invokeinterface #153,  1          // InterfaceMethod software/amazon/awssdk/utils/builder/SdkBuilder.build:()Ljava/lang/Object;
      74: checkcast     #21                 // class software/amazon/awssdk/services/resourcegroups/model/ListGroupResourcesItem
      77: areturn

  public zio.aws.resourcegroups.model.ListGroupResourcesItem$ReadOnly asReadOnly();
    Code:
       0: getstatic     #47                 // Field zio/aws/resourcegroups/model/ListGroupResourcesItem$.MODULE$:Lzio/aws/resourcegroups/model/ListGroupResourcesItem$;
       3: aload_0
       4: invokevirtual #157                // Method buildAwsValue:()Lsoftware/amazon/awssdk/services/resourcegroups/model/ListGroupResourcesItem;
       7: invokevirtual #75                 // Method zio/aws/resourcegroups/model/ListGroupResourcesItem$.wrap:(Lsoftware/amazon/awssdk/services/resourcegroups/model/ListGroupResourcesItem;)Lzio/aws/resourcegroups/model/ListGroupResourcesItem$ReadOnly;
      10: areturn

  public zio.aws.resourcegroups.model.ListGroupResourcesItem copy(zio.prelude.data.Optional<zio.aws.resourcegroups.model.ResourceIdentifier>, zio.prelude.data.Optional<zio.aws.resourcegroups.model.ResourceStatus>);
    Code:
       0: new           #2                  // class zio/aws/resourcegroups/model/ListGroupResourcesItem
       3: dup
       4: aload_1
       5: aload_2
       6: invokespecial #162                // Method "<init>":(Lzio/prelude/data/Optional;Lzio/prelude/data/Optional;)V
       9: areturn

  public zio.prelude.data.Optional<zio.aws.resourcegroups.model.ResourceIdentifier> copy$default$1();
    Code:
       0: aload_0
       1: invokevirtual #96                 // Method identifier:()Lzio/prelude/data/Optional;
       4: areturn

  public zio.prelude.data.Optional<zio.aws.resourcegroups.model.ResourceStatus> copy$default$2();
    Code:
       0: aload_0
       1: invokevirtual #135                // Method status:()Lzio/prelude/data/Optional;
       4: areturn

  public java.lang.String productPrefix();
    Code:
       0: ldc           #168                // String ListGroupResourcesItem
       2: areturn

  public int productArity();
    Code:
       0: iconst_2
       1: ireturn

  public java.lang.Object productElement(int);
    Code:
       0: iload_1
       1: istore_2
       2: iload_2
       3: tableswitch   { // 0 to 1
                     0: 24
                     1: 29
               default: 34
          }
      24: aload_0
      25: invokevirtual #96                 // Method identifier:()Lzio/prelude/data/Optional;
      28: areturn
      29: aload_0
      30: invokevirtual #135                // Method status:()Lzio/prelude/data/Optional;
      33: areturn
      34: new           #175                // class java/lang/IndexOutOfBoundsException
      37: dup
      38: iload_1
      39: invokestatic  #181                // Method java/lang/Integer.toString:(I)Ljava/lang/String;
      42: invokespecial #184                // Method java/lang/IndexOutOfBoundsException."<init>":(Ljava/lang/String;)V
      45: athrow

  public scala.collection.Iterator<java.lang.Object> productIterator();
    Code:
       0: getstatic     #193                // Field scala/runtime/ScalaRunTime$.MODULE$:Lscala/runtime/ScalaRunTime$;
       3: aload_0
       4: invokevirtual #197                // Method scala/runtime/ScalaRunTime$.typedProductIterator:(Lscala/Product;)Lscala/collection/Iterator;
       7: areturn

  public boolean canEqual(java.lang.Object);
    Code:
       0: aload_1
       1: instanceof    #2                  // class zio/aws/resourcegroups/model/ListGroupResourcesItem
       4: ireturn

  public int hashCode();
    Code:
       0: getstatic     #193                // Field scala/runtime/ScalaRunTime$.MODULE$:Lscala/runtime/ScalaRunTime$;
       3: aload_0
       4: invokevirtual #205                // Method scala/runtime/ScalaRunTime$._hashCode:(Lscala/Product;)I
       7: ireturn

  public java.lang.String toString();
    Code:
       0: getstatic     #193                // Field scala/runtime/ScalaRunTime$.MODULE$:Lscala/runtime/ScalaRunTime$;
       3: aload_0
       4: invokevirtual #209                // Method scala/runtime/ScalaRunTime$._toString:(Lscala/Product;)Ljava/lang/String;
       7: areturn

  public boolean equals(java.lang.Object);
    Code:
       0: aload_0
       1: aload_1
       2: if_acmpeq     98
       5: aload_1
       6: astore_3
       7: aload_3
       8: instanceof    #2                  // class zio/aws/resourcegroups/model/ListGroupResourcesItem
      11: ifeq          18
      14: iconst_1
      15: goto          25
      18: goto          21
      21: iconst_0
      22: goto          25
      25: ifeq          102
      28: aload_1
      29: checkcast     #2                  // class zio/aws/resourcegroups/model/ListGroupResourcesItem
      32: astore        4
      34: aload_0
      35: invokevirtual #96                 // Method identifier:()Lzio/prelude/data/Optional;
      38: aload         4
      40: invokevirtual #96                 // Method identifier:()Lzio/prelude/data/Optional;
      43: astore        5
      45: dup
      46: ifnonnull     58
      49: pop
      50: aload         5
      52: ifnull        66
      55: goto          102
      58: aload         5
      60: invokevirtual #212                // Method java/lang/Object.equals:(Ljava/lang/Object;)Z
      63: ifeq          102
      66: aload_0
      67: invokevirtual #135                // Method status:()Lzio/prelude/data/Optional;
      70: aload         4
      72: invokevirtual #135                // Method status:()Lzio/prelude/data/Optional;
      75: astore        6
      77: dup
      78: ifnonnull     90
      81: pop
      82: aload         6
      84: ifnull        98
      87: goto          102
      90: aload         6
      92: invokevirtual #212                // Method java/lang/Object.equals:(Ljava/lang/Object;)Z
      95: ifeq          102
      98: iconst_1
      99: goto          103
     102: iconst_0
     103: ireturn

  public static final software.amazon.awssdk.services.resourcegroups.model.ResourceIdentifier $anonfun$buildAwsValue$1(zio.aws.resourcegroups.model.ResourceIdentifier);
    Code:
       0: aload_0
       1: invokevirtual #218                // Method zio/aws/resourcegroups/model/ResourceIdentifier.buildAwsValue:()Lsoftware/amazon/awssdk/services/resourcegroups/model/ResourceIdentifier;
       4: areturn

  public static final software.amazon.awssdk.services.resourcegroups.model.ListGroupResourcesItem$Builder $anonfun$buildAwsValue$3(software.amazon.awssdk.services.resourcegroups.model.ListGroupResourcesItem$Builder, software.amazon.awssdk.services.resourcegroups.model.ResourceIdentifier);
    Code:
       0: aload_0
       1: aload_1
       2: invokeinterface #225,  2          // InterfaceMethod software/amazon/awssdk/services/resourcegroups/model/ListGroupResourcesItem$Builder.identifier:(Lsoftware/amazon/awssdk/services/resourcegroups/model/ResourceIdentifier;)Lsoftware/amazon/awssdk/services/resourcegroups/model/ListGroupResourcesItem$Builder;
       7: areturn

  public static final scala.Function1 $anonfun$buildAwsValue$2(software.amazon.awssdk.services.resourcegroups.model.ListGroupResourcesItem$Builder);
    Code:
       0: aload_0
       1: invokedynamic #233,  0            // InvokeDynamic #4:apply:(Lsoftware/amazon/awssdk/services/resourcegroups/model/ListGroupResourcesItem$Builder;)Lscala/Function1;
       6: areturn

  public static final software.amazon.awssdk.services.resourcegroups.model.ResourceStatus $anonfun$buildAwsValue$4(zio.aws.resourcegroups.model.ResourceStatus);
    Code:
       0: aload_0
       1: invokevirtual #238                // Method zio/aws/resourcegroups/model/ResourceStatus.buildAwsValue:()Lsoftware/amazon/awssdk/services/resourcegroups/model/ResourceStatus;
       4: areturn

  public static final software.amazon.awssdk.services.resourcegroups.model.ListGroupResourcesItem$Builder $anonfun$buildAwsValue$6(software.amazon.awssdk.services.resourcegroups.model.ListGroupResourcesItem$Builder, software.amazon.awssdk.services.resourcegroups.model.ResourceStatus);
    Code:
       0: aload_0
       1: aload_1
       2: invokeinterface #245,  2          // InterfaceMethod software/amazon/awssdk/services/resourcegroups/model/ListGroupResourcesItem$Builder.status:(Lsoftware/amazon/awssdk/services/resourcegroups/model/ResourceStatus;)Lsoftware/amazon/awssdk/services/resourcegroups/model/ListGroupResourcesItem$Builder;
       7: areturn

  public static final scala.Function1 $anonfun$buildAwsValue$5(software.amazon.awssdk.services.resourcegroups.model.ListGroupResourcesItem$Builder);
    Code:
       0: aload_0
       1: invokedynamic #252,  0            // InvokeDynamic #5:apply:(Lsoftware/amazon/awssdk/services/resourcegroups/model/ListGroupResourcesItem$Builder;)Lscala/Function1;
       6: areturn

  public zio.aws.resourcegroups.model.ListGroupResourcesItem(zio.prelude.data.Optional<zio.aws.resourcegroups.model.ResourceIdentifier>, zio.prelude.data.Optional<zio.aws.resourcegroups.model.ResourceStatus>);
    Code:
       0: aload_0
       1: aload_1
       2: putfield      #77                 // Field identifier:Lzio/prelude/data/Optional;
       5: aload_0
       6: aload_2
       7: putfield      #81                 // Field status:Lzio/prelude/data/Optional;
      10: aload_0
      11: invokespecial #256                // Method java/lang/Object."<init>":()V
      14: aload_0
      15: invokestatic  #260                // InterfaceMethod scala/Product.$init$:(Lscala/Product;)V
      18: return

  private static java.lang.Object $deserializeLambda$(java.lang.invoke.SerializedLambda);
    Code:
       0: aload_0
       1: invokedynamic #272,  0            // InvokeDynamic #6:lambdaDeserialize:(Ljava/lang/invoke/SerializedLambda;)Ljava/lang/Object;
       6: areturn
}
