Compiled from "ResourceQuery.scala"
public final class zio.aws.resourcegroups.model.ResourceQuery$Wrapper implements zio.aws.resourcegroups.model.ResourceQuery$ReadOnly {
  private final zio.aws.resourcegroups.model.QueryType type;

  private final java.lang.String query;

  public zio.aws.resourcegroups.model.ResourceQuery asEditable();
    Code:
       0: aload_0
       1: invokestatic  #29                 // InterfaceMethod zio/aws/resourcegroups/model/ResourceQuery$ReadOnly.asEditable$:(Lzio/aws/resourcegroups/model/ResourceQuery$ReadOnly;)Lzio/aws/resourcegroups/model/ResourceQuery;
       4: areturn

  public zio.ZIO<java.lang.Object, scala.runtime.Nothing$, zio.aws.resourcegroups.model.QueryType> getType();
    Code:
       0: aload_0
       1: invokestatic  #38                 // InterfaceMethod zio/aws/resourcegroups/model/ResourceQuery$ReadOnly.getType$:(Lzio/aws/resourcegroups/model/ResourceQuery$ReadOnly;)Lzio/ZIO;
       4: areturn

  public zio.ZIO<java.lang.Object, scala.runtime.Nothing$, java.lang.String> getQuery();
    Code:
       0: aload_0
       1: invokestatic  #43                 // InterfaceMethod zio/aws/resourcegroups/model/ResourceQuery$ReadOnly.getQuery$:(Lzio/aws/resourcegroups/model/ResourceQuery$ReadOnly;)Lzio/ZIO;
       4: areturn

  public zio.aws.resourcegroups.model.QueryType type();
    Code:
       0: aload_0
       1: getfield      #46                 // Field type:Lzio/aws/resourcegroups/model/QueryType;
       4: areturn

  public java.lang.String query();
    Code:
       0: aload_0
       1: getfield      #49                 // Field query:Ljava/lang/String;
       4: areturn

  public zio.aws.resourcegroups.model.ResourceQuery$Wrapper(software.amazon.awssdk.services.resourcegroups.model.ResourceQuery);
    Code:
       0: aload_0
       1: invokespecial #55                 // Method java/lang/Object."<init>":()V
       4: aload_0
       5: invokestatic  #59                 // InterfaceMethod zio/aws/resourcegroups/model/ResourceQuery$ReadOnly.$init$:(Lzio/aws/resourcegroups/model/ResourceQuery$ReadOnly;)V
       8: aload_0
       9: getstatic     #65                 // Field zio/aws/resourcegroups/model/QueryType$.MODULE$:Lzio/aws/resourcegroups/model/QueryType$;
      12: aload_1
      13: invokevirtual #70                 // Method software/amazon/awssdk/services/resourcegroups/model/ResourceQuery.type:()Lsoftware/amazon/awssdk/services/resourcegroups/model/QueryType;
      16: invokevirtual #74                 // Method zio/aws/resourcegroups/model/QueryType$.wrap:(Lsoftware/amazon/awssdk/services/resourcegroups/model/QueryType;)Lzio/aws/resourcegroups/model/QueryType;
      19: putfield      #46                 // Field type:Lzio/aws/resourcegroups/model/QueryType;
      22: aload_0
      23: getstatic     #79                 // Field zio/prelude/Newtype$.MODULE$:Lzio/prelude/Newtype$;
      26: getstatic     #82                 // Field zio/aws/resourcegroups/model/package$primitives$Query$.MODULE$:Lzio/aws/resourcegroups/model/package$primitives$Query$;
      29: aload_1
      30: invokevirtual #84                 // Method software/amazon/awssdk/services/resourcegroups/model/ResourceQuery.query:()Ljava/lang/String;
      33: invokevirtual #88                 // Method zio/prelude/Newtype$.unsafeWrap:(Lzio/prelude/Newtype;Ljava/lang/Object;)Ljava/lang/Object;
      36: checkcast     #90                 // class java/lang/String
      39: putfield      #49                 // Field query:Ljava/lang/String;
      42: return
}
