Compiled from "JvmProtoBuf.java"
public final class kotlin.reflect.jvm.internal.impl.metadata.jvm.JvmProtoBuf$StringTableTypes$Record$Builder extends kotlin.reflect.jvm.internal.impl.protobuf.GeneratedMessageLite$Builder<kotlin.reflect.jvm.internal.impl.metadata.jvm.JvmProtoBuf$StringTableTypes$Record, kotlin.reflect.jvm.internal.impl.metadata.jvm.JvmProtoBuf$StringTableTypes$Record$Builder> implements kotlin.reflect.jvm.internal.impl.metadata.jvm.JvmProtoBuf$StringTableTypes$RecordOrBuilder {
  private int bitField0_;

  private int range_;

  private int predefinedIndex_;

  private java.lang.Object string_;

  private kotlin.reflect.jvm.internal.impl.metadata.jvm.JvmProtoBuf$StringTableTypes$Record$Operation operation_;

  private java.util.List<java.lang.Integer> substringIndex_;

  private java.util.List<java.lang.Integer> replaceChar_;

  private kotlin.reflect.jvm.internal.impl.metadata.jvm.JvmProtoBuf$StringTableTypes$Record$Builder();
    Code:
       0: aload_0
       1: invokespecial #79                 // Method kotlin/reflect/jvm/internal/impl/protobuf/GeneratedMessageLite$Builder."<init>":()V
       4: aload_0
       5: iconst_1
       6: putfield      #31                 // Field range_:I
       9: aload_0
      10: ldc           #1                  // String
      12: putfield      #33                 // Field string_:Ljava/lang/Object;
      15: aload_0
      16: getstatic     #35                 // Field kotlin/reflect/jvm/internal/impl/metadata/jvm/JvmProtoBuf$StringTableTypes$Record$Operation.NONE:Lkotlin/reflect/jvm/internal/impl/metadata/jvm/JvmProtoBuf$StringTableTypes$Record$Operation;
      19: putfield      #29                 // Field operation_:Lkotlin/reflect/jvm/internal/impl/metadata/jvm/JvmProtoBuf$StringTableTypes$Record$Operation;
      22: aload_0
      23: invokestatic  #38                 // Method java/util/Collections.emptyList:()Ljava/util/List;
      26: putfield      #34                 // Field substringIndex_:Ljava/util/List;
      29: aload_0
      30: invokestatic  #38                 // Method java/util/Collections.emptyList:()Ljava/util/List;
      33: putfield      #32                 // Field replaceChar_:Ljava/util/List;
      36: aload_0
      37: invokespecial #70                 // Method maybeForceBuilderInitialization:()V
      40: return

  private void maybeForceBuilderInitialization();
    Code:
       0: return

  private static kotlin.reflect.jvm.internal.impl.metadata.jvm.JvmProtoBuf$StringTableTypes$Record$Builder create();
    Code:
       0: new           #13                 // class kotlin/reflect/jvm/internal/impl/metadata/jvm/JvmProtoBuf$StringTableTypes$Record$Builder
       3: dup
       4: invokespecial #61                 // Method "<init>":()V
       7: areturn

  public kotlin.reflect.jvm.internal.impl.metadata.jvm.JvmProtoBuf$StringTableTypes$Record$Builder clone();
    Code:
       0: invokestatic  #65                 // Method create:()Lkotlin/reflect/jvm/internal/impl/metadata/jvm/JvmProtoBuf$StringTableTypes$Record$Builder;
       3: aload_0
       4: invokevirtual #63                 // Method buildPartial:()Lkotlin/reflect/jvm/internal/impl/metadata/jvm/JvmProtoBuf$StringTableTypes$Record;
       7: invokevirtual #71                 // Method mergeFrom:(Lkotlin/reflect/jvm/internal/impl/metadata/jvm/JvmProtoBuf$StringTableTypes$Record;)Lkotlin/reflect/jvm/internal/impl/metadata/jvm/JvmProtoBuf$StringTableTypes$Record$Builder;
      10: areturn

  public kotlin.reflect.jvm.internal.impl.metadata.jvm.JvmProtoBuf$StringTableTypes$Record getDefaultInstanceForType();
    Code:
       0: invokestatic  #52                 // Method kotlin/reflect/jvm/internal/impl/metadata/jvm/JvmProtoBuf$StringTableTypes$Record.getDefaultInstance:()Lkotlin/reflect/jvm/internal/impl/metadata/jvm/JvmProtoBuf$StringTableTypes$Record;
       3: areturn

  public kotlin.reflect.jvm.internal.impl.metadata.jvm.JvmProtoBuf$StringTableTypes$Record build();
    Code:
       0: aload_0
       1: invokevirtual #63                 // Method buildPartial:()Lkotlin/reflect/jvm/internal/impl/metadata/jvm/JvmProtoBuf$StringTableTypes$Record;
       4: astore_1
       5: aload_1
       6: invokevirtual #60                 // Method kotlin/reflect/jvm/internal/impl/metadata/jvm/JvmProtoBuf$StringTableTypes$Record.isInitialized:()Z
       9: ifne          17
      12: aload_1
      13: invokestatic  #73                 // Method newUninitializedMessageException:(Lkotlin/reflect/jvm/internal/impl/protobuf/MessageLite;)Lkotlin/reflect/jvm/internal/impl/protobuf/UninitializedMessageException;
      16: athrow
      17: aload_1
      18: areturn

  public kotlin.reflect.jvm.internal.impl.metadata.jvm.JvmProtoBuf$StringTableTypes$Record buildPartial();
    Code:
       0: new           #12                 // class kotlin/reflect/jvm/internal/impl/metadata/jvm/JvmProtoBuf$StringTableTypes$Record
       3: dup
       4: aload_0
       5: aconst_null
       6: invokespecial #40                 // Method kotlin/reflect/jvm/internal/impl/metadata/jvm/JvmProtoBuf$StringTableTypes$Record."<init>":(Lkotlin/reflect/jvm/internal/impl/protobuf/GeneratedMessageLite$Builder;Lkotlin/reflect/jvm/internal/impl/metadata/jvm/JvmProtoBuf$1;)V
       9: astore_1
      10: aload_0
      11: getfield      #28                 // Field bitField0_:I
      14: istore_2
      15: iconst_0
      16: istore_3
      17: iload_2
      18: iconst_1
      19: iand
      20: iconst_1
      21: if_icmpne     28
      24: iload_3
      25: iconst_1
      26: ior
      27: istore_3
      28: aload_1
      29: aload_0
      30: getfield      #31                 // Field range_:I
      33: invokestatic  #43                 // Method kotlin/reflect/jvm/internal/impl/metadata/jvm/JvmProtoBuf$StringTableTypes$Record.access$402:(Lkotlin/reflect/jvm/internal/impl/metadata/jvm/JvmProtoBuf$StringTableTypes$Record;I)I
      36: pop
      37: iload_2
      38: iconst_2
      39: iand
      40: iconst_2
      41: if_icmpne     48
      44: iload_3
      45: iconst_2
      46: ior
      47: istore_3
      48: aload_1
      49: aload_0
      50: getfield      #30                 // Field predefinedIndex_:I
      53: invokestatic  #44                 // Method kotlin/reflect/jvm/internal/impl/metadata/jvm/JvmProtoBuf$StringTableTypes$Record.access$502:(Lkotlin/reflect/jvm/internal/impl/metadata/jvm/JvmProtoBuf$StringTableTypes$Record;I)I
      56: pop
      57: iload_2
      58: iconst_4
      59: iand
      60: iconst_4
      61: if_icmpne     68
      64: iload_3
      65: iconst_4
      66: ior
      67: istore_3
      68: aload_1
      69: aload_0
      70: getfield      #33                 // Field string_:Ljava/lang/Object;
      73: invokestatic  #46                 // Method kotlin/reflect/jvm/internal/impl/metadata/jvm/JvmProtoBuf$StringTableTypes$Record.access$602:(Lkotlin/reflect/jvm/internal/impl/metadata/jvm/JvmProtoBuf$StringTableTypes$Record;Ljava/lang/Object;)Ljava/lang/Object;
      76: pop
      77: iload_2
      78: bipush        8
      80: iand
      81: bipush        8
      83: if_icmpne     91
      86: iload_3
      87: bipush        8
      89: ior
      90: istore_3
      91: aload_1
      92: aload_0
      93: getfield      #29                 // Field operation_:Lkotlin/reflect/jvm/internal/impl/metadata/jvm/JvmProtoBuf$StringTableTypes$Record$Operation;
      96: invokestatic  #47                 // Method kotlin/reflect/jvm/internal/impl/metadata/jvm/JvmProtoBuf$StringTableTypes$Record.access$702:(Lkotlin/reflect/jvm/internal/impl/metadata/jvm/JvmProtoBuf$StringTableTypes$Record;Lkotlin/reflect/jvm/internal/impl/metadata/jvm/JvmProtoBuf$StringTableTypes$Record$Operation;)Lkotlin/reflect/jvm/internal/impl/metadata/jvm/JvmProtoBuf$StringTableTypes$Record$Operation;
      99: pop
     100: aload_0
     101: getfield      #28                 // Field bitField0_:I
     104: bipush        16
     106: iand
     107: bipush        16
     109: if_icmpne     134
     112: aload_0
     113: aload_0
     114: getfield      #34                 // Field substringIndex_:Ljava/util/List;
     117: invokestatic  #39                 // Method java/util/Collections.unmodifiableList:(Ljava/util/List;)Ljava/util/List;
     120: putfield      #34                 // Field substringIndex_:Ljava/util/List;
     123: aload_0
     124: aload_0
     125: getfield      #28                 // Field bitField0_:I
     128: bipush        -17
     130: iand
     131: putfield      #28                 // Field bitField0_:I
     134: aload_1
     135: aload_0
     136: getfield      #34                 // Field substringIndex_:Ljava/util/List;
     139: invokestatic  #49                 // Method kotlin/reflect/jvm/internal/impl/metadata/jvm/JvmProtoBuf$StringTableTypes$Record.access$802:(Lkotlin/reflect/jvm/internal/impl/metadata/jvm/JvmProtoBuf$StringTableTypes$Record;Ljava/util/List;)Ljava/util/List;
     142: pop
     143: aload_0
     144: getfield      #28                 // Field bitField0_:I
     147: bipush        32
     149: iand
     150: bipush        32
     152: if_icmpne     177
     155: aload_0
     156: aload_0
     157: getfield      #32                 // Field replaceChar_:Ljava/util/List;
     160: invokestatic  #39                 // Method java/util/Collections.unmodifiableList:(Ljava/util/List;)Ljava/util/List;
     163: putfield      #32                 // Field replaceChar_:Ljava/util/List;
     166: aload_0
     167: aload_0
     168: getfield      #28                 // Field bitField0_:I
     171: bipush        -33
     173: iand
     174: putfield      #28                 // Field bitField0_:I
     177: aload_1
     178: aload_0
     179: getfield      #32                 // Field replaceChar_:Ljava/util/List;
     182: invokestatic  #51                 // Method kotlin/reflect/jvm/internal/impl/metadata/jvm/JvmProtoBuf$StringTableTypes$Record.access$902:(Lkotlin/reflect/jvm/internal/impl/metadata/jvm/JvmProtoBuf$StringTableTypes$Record;Ljava/util/List;)Ljava/util/List;
     185: pop
     186: aload_1
     187: iload_3
     188: invokestatic  #41                 // Method kotlin/reflect/jvm/internal/impl/metadata/jvm/JvmProtoBuf$StringTableTypes$Record.access$1002:(Lkotlin/reflect/jvm/internal/impl/metadata/jvm/JvmProtoBuf$StringTableTypes$Record;I)I
     191: pop
     192: aload_1
     193: areturn

  public kotlin.reflect.jvm.internal.impl.metadata.jvm.JvmProtoBuf$StringTableTypes$Record$Builder mergeFrom(kotlin.reflect.jvm.internal.impl.metadata.jvm.JvmProtoBuf$StringTableTypes$Record);
    Code:
       0: aload_1
       1: invokestatic  #52                 // Method kotlin/reflect/jvm/internal/impl/metadata/jvm/JvmProtoBuf$StringTableTypes$Record.getDefaultInstance:()Lkotlin/reflect/jvm/internal/impl/metadata/jvm/JvmProtoBuf$StringTableTypes$Record;
       4: if_acmpne     9
       7: aload_0
       8: areturn
       9: aload_1
      10: invokevirtual #58                 // Method kotlin/reflect/jvm/internal/impl/metadata/jvm/JvmProtoBuf$StringTableTypes$Record.hasRange:()Z
      13: ifeq          25
      16: aload_0
      17: aload_1
      18: invokevirtual #55                 // Method kotlin/reflect/jvm/internal/impl/metadata/jvm/JvmProtoBuf$StringTableTypes$Record.getRange:()I
      21: invokevirtual #76                 // Method setRange:(I)Lkotlin/reflect/jvm/internal/impl/metadata/jvm/JvmProtoBuf$StringTableTypes$Record$Builder;
      24: pop
      25: aload_1
      26: invokevirtual #57                 // Method kotlin/reflect/jvm/internal/impl/metadata/jvm/JvmProtoBuf$StringTableTypes$Record.hasPredefinedIndex:()Z
      29: ifeq          41
      32: aload_0
      33: aload_1
      34: invokevirtual #54                 // Method kotlin/reflect/jvm/internal/impl/metadata/jvm/JvmProtoBuf$StringTableTypes$Record.getPredefinedIndex:()I
      37: invokevirtual #75                 // Method setPredefinedIndex:(I)Lkotlin/reflect/jvm/internal/impl/metadata/jvm/JvmProtoBuf$StringTableTypes$Record$Builder;
      40: pop
      41: aload_1
      42: invokevirtual #59                 // Method kotlin/reflect/jvm/internal/impl/metadata/jvm/JvmProtoBuf$StringTableTypes$Record.hasString:()Z
      45: ifeq          66
      48: aload_0
      49: dup
      50: getfield      #28                 // Field bitField0_:I
      53: iconst_4
      54: ior
      55: putfield      #28                 // Field bitField0_:I
      58: aload_0
      59: aload_1
      60: invokestatic  #45                 // Method kotlin/reflect/jvm/internal/impl/metadata/jvm/JvmProtoBuf$StringTableTypes$Record.access$600:(Lkotlin/reflect/jvm/internal/impl/metadata/jvm/JvmProtoBuf$StringTableTypes$Record;)Ljava/lang/Object;
      63: putfield      #33                 // Field string_:Ljava/lang/Object;
      66: aload_1
      67: invokevirtual #56                 // Method kotlin/reflect/jvm/internal/impl/metadata/jvm/JvmProtoBuf$StringTableTypes$Record.hasOperation:()Z
      70: ifeq          82
      73: aload_0
      74: aload_1
      75: invokevirtual #53                 // Method kotlin/reflect/jvm/internal/impl/metadata/jvm/JvmProtoBuf$StringTableTypes$Record.getOperation:()Lkotlin/reflect/jvm/internal/impl/metadata/jvm/JvmProtoBuf$StringTableTypes$Record$Operation;
      78: invokevirtual #74                 // Method setOperation:(Lkotlin/reflect/jvm/internal/impl/metadata/jvm/JvmProtoBuf$StringTableTypes$Record$Operation;)Lkotlin/reflect/jvm/internal/impl/metadata/jvm/JvmProtoBuf$StringTableTypes$Record$Builder;
      81: pop
      82: aload_1
      83: invokestatic  #48                 // Method kotlin/reflect/jvm/internal/impl/metadata/jvm/JvmProtoBuf$StringTableTypes$Record.access$800:(Lkotlin/reflect/jvm/internal/impl/metadata/jvm/JvmProtoBuf$StringTableTypes$Record;)Ljava/util/List;
      86: invokeinterface #82,  1           // InterfaceMethod java/util/List.isEmpty:()Z
      91: ifne          146
      94: aload_0
      95: getfield      #34                 // Field substringIndex_:Ljava/util/List;
      98: invokeinterface #82,  1           // InterfaceMethod java/util/List.isEmpty:()Z
     103: ifeq          128
     106: aload_0
     107: aload_1
     108: invokestatic  #48                 // Method kotlin/reflect/jvm/internal/impl/metadata/jvm/JvmProtoBuf$StringTableTypes$Record.access$800:(Lkotlin/reflect/jvm/internal/impl/metadata/jvm/JvmProtoBuf$StringTableTypes$Record;)Ljava/util/List;
     111: putfield      #34                 // Field substringIndex_:Ljava/util/List;
     114: aload_0
     115: aload_0
     116: getfield      #28                 // Field bitField0_:I
     119: bipush        -17
     121: iand
     122: putfield      #28                 // Field bitField0_:I
     125: goto          146
     128: aload_0
     129: invokespecial #67                 // Method ensureSubstringIndexIsMutable:()V
     132: aload_0
     133: getfield      #34                 // Field substringIndex_:Ljava/util/List;
     136: aload_1
     137: invokestatic  #48                 // Method kotlin/reflect/jvm/internal/impl/metadata/jvm/JvmProtoBuf$StringTableTypes$Record.access$800:(Lkotlin/reflect/jvm/internal/impl/metadata/jvm/JvmProtoBuf$StringTableTypes$Record;)Ljava/util/List;
     140: invokeinterface #81,  2           // InterfaceMethod java/util/List.addAll:(Ljava/util/Collection;)Z
     145: pop
     146: aload_1
     147: invokestatic  #50                 // Method kotlin/reflect/jvm/internal/impl/metadata/jvm/JvmProtoBuf$StringTableTypes$Record.access$900:(Lkotlin/reflect/jvm/internal/impl/metadata/jvm/JvmProtoBuf$StringTableTypes$Record;)Ljava/util/List;
     150: invokeinterface #82,  1           // InterfaceMethod java/util/List.isEmpty:()Z
     155: ifne          210
     158: aload_0
     159: getfield      #32                 // Field replaceChar_:Ljava/util/List;
     162: invokeinterface #82,  1           // InterfaceMethod java/util/List.isEmpty:()Z
     167: ifeq          192
     170: aload_0
     171: aload_1
     172: invokestatic  #50                 // Method kotlin/reflect/jvm/internal/impl/metadata/jvm/JvmProtoBuf$StringTableTypes$Record.access$900:(Lkotlin/reflect/jvm/internal/impl/metadata/jvm/JvmProtoBuf$StringTableTypes$Record;)Ljava/util/List;
     175: putfield      #32                 // Field replaceChar_:Ljava/util/List;
     178: aload_0
     179: aload_0
     180: getfield      #28                 // Field bitField0_:I
     183: bipush        -33
     185: iand
     186: putfield      #28                 // Field bitField0_:I
     189: goto          210
     192: aload_0
     193: invokespecial #66                 // Method ensureReplaceCharIsMutable:()V
     196: aload_0
     197: getfield      #32                 // Field replaceChar_:Ljava/util/List;
     200: aload_1
     201: invokestatic  #50                 // Method kotlin/reflect/jvm/internal/impl/metadata/jvm/JvmProtoBuf$StringTableTypes$Record.access$900:(Lkotlin/reflect/jvm/internal/impl/metadata/jvm/JvmProtoBuf$StringTableTypes$Record;)Ljava/util/List;
     204: invokeinterface #81,  2           // InterfaceMethod java/util/List.addAll:(Ljava/util/Collection;)Z
     209: pop
     210: aload_0
     211: aload_0
     212: invokevirtual #69                 // Method getUnknownFields:()Lkotlin/reflect/jvm/internal/impl/protobuf/ByteString;
     215: aload_1
     216: invokestatic  #42                 // Method kotlin/reflect/jvm/internal/impl/metadata/jvm/JvmProtoBuf$StringTableTypes$Record.access$1100:(Lkotlin/reflect/jvm/internal/impl/metadata/jvm/JvmProtoBuf$StringTableTypes$Record;)Lkotlin/reflect/jvm/internal/impl/protobuf/ByteString;
     219: invokevirtual #78                 // Method kotlin/reflect/jvm/internal/impl/protobuf/ByteString.concat:(Lkotlin/reflect/jvm/internal/impl/protobuf/ByteString;)Lkotlin/reflect/jvm/internal/impl/protobuf/ByteString;
     222: invokevirtual #77                 // Method setUnknownFields:(Lkotlin/reflect/jvm/internal/impl/protobuf/ByteString;)Lkotlin/reflect/jvm/internal/impl/protobuf/GeneratedMessageLite$Builder;
     225: pop
     226: aload_0
     227: areturn

  public final boolean isInitialized();
    Code:
       0: iconst_1
       1: ireturn

  public kotlin.reflect.jvm.internal.impl.metadata.jvm.JvmProtoBuf$StringTableTypes$Record$Builder mergeFrom(kotlin.reflect.jvm.internal.impl.protobuf.CodedInputStream, kotlin.reflect.jvm.internal.impl.protobuf.ExtensionRegistryLite) throws java.io.IOException;
    Code:
       0: aconst_null
       1: astore_3
       2: getstatic     #27                 // Field kotlin/reflect/jvm/internal/impl/metadata/jvm/JvmProtoBuf$StringTableTypes$Record.PARSER:Lkotlin/reflect/jvm/internal/impl/protobuf/Parser;
       5: aload_1
       6: aload_2
       7: invokeinterface #83,  3           // InterfaceMethod kotlin/reflect/jvm/internal/impl/protobuf/Parser.parsePartialFrom:(Lkotlin/reflect/jvm/internal/impl/protobuf/CodedInputStream;Lkotlin/reflect/jvm/internal/impl/protobuf/ExtensionRegistryLite;)Ljava/lang/Object;
      12: checkcast     #12                 // class kotlin/reflect/jvm/internal/impl/metadata/jvm/JvmProtoBuf$StringTableTypes$Record
      15: astore_3
      16: aload_3
      17: ifnull        58
      20: aload_0
      21: aload_3
      22: invokevirtual #71                 // Method mergeFrom:(Lkotlin/reflect/jvm/internal/impl/metadata/jvm/JvmProtoBuf$StringTableTypes$Record;)Lkotlin/reflect/jvm/internal/impl/metadata/jvm/JvmProtoBuf$StringTableTypes$Record$Builder;
      25: pop
      26: goto          58
      29: astore        4
      31: aload         4
      33: invokevirtual #80                 // Method kotlin/reflect/jvm/internal/impl/protobuf/InvalidProtocolBufferException.getUnfinishedMessage:()Lkotlin/reflect/jvm/internal/impl/protobuf/MessageLite;
      36: checkcast     #12                 // class kotlin/reflect/jvm/internal/impl/metadata/jvm/JvmProtoBuf$StringTableTypes$Record
      39: astore_3
      40: aload         4
      42: athrow
      43: astore        5
      45: aload_3
      46: ifnull        55
      49: aload_0
      50: aload_3
      51: invokevirtual #71                 // Method mergeFrom:(Lkotlin/reflect/jvm/internal/impl/metadata/jvm/JvmProtoBuf$StringTableTypes$Record;)Lkotlin/reflect/jvm/internal/impl/metadata/jvm/JvmProtoBuf$StringTableTypes$Record$Builder;
      54: pop
      55: aload         5
      57: athrow
      58: aload_0
      59: areturn
    Exception table:
       from    to  target type
           2    16    29   Class kotlin/reflect/jvm/internal/impl/protobuf/InvalidProtocolBufferException
           2    16    43   any
          29    45    43   any

  public kotlin.reflect.jvm.internal.impl.metadata.jvm.JvmProtoBuf$StringTableTypes$Record$Builder setRange(int);
    Code:
       0: aload_0
       1: dup
       2: getfield      #28                 // Field bitField0_:I
       5: iconst_1
       6: ior
       7: putfield      #28                 // Field bitField0_:I
      10: aload_0
      11: iload_1
      12: putfield      #31                 // Field range_:I
      15: aload_0
      16: areturn

  public kotlin.reflect.jvm.internal.impl.metadata.jvm.JvmProtoBuf$StringTableTypes$Record$Builder setPredefinedIndex(int);
    Code:
       0: aload_0
       1: dup
       2: getfield      #28                 // Field bitField0_:I
       5: iconst_2
       6: ior
       7: putfield      #28                 // Field bitField0_:I
      10: aload_0
      11: iload_1
      12: putfield      #30                 // Field predefinedIndex_:I
      15: aload_0
      16: areturn

  public kotlin.reflect.jvm.internal.impl.metadata.jvm.JvmProtoBuf$StringTableTypes$Record$Builder setOperation(kotlin.reflect.jvm.internal.impl.metadata.jvm.JvmProtoBuf$StringTableTypes$Record$Operation);
    Code:
       0: aload_1
       1: ifnonnull     12
       4: new           #4                  // class java/lang/NullPointerException
       7: dup
       8: invokespecial #36                 // Method java/lang/NullPointerException."<init>":()V
      11: athrow
      12: aload_0
      13: dup
      14: getfield      #28                 // Field bitField0_:I
      17: bipush        8
      19: ior
      20: putfield      #28                 // Field bitField0_:I
      23: aload_0
      24: aload_1
      25: putfield      #29                 // Field operation_:Lkotlin/reflect/jvm/internal/impl/metadata/jvm/JvmProtoBuf$StringTableTypes$Record$Operation;
      28: aload_0
      29: areturn

  private void ensureSubstringIndexIsMutable();
    Code:
       0: aload_0
       1: getfield      #28                 // Field bitField0_:I
       4: bipush        16
       6: iand
       7: bipush        16
       9: if_icmpeq     38
      12: aload_0
      13: new           #6                  // class java/util/ArrayList
      16: dup
      17: aload_0
      18: getfield      #34                 // Field substringIndex_:Ljava/util/List;
      21: invokespecial #37                 // Method java/util/ArrayList."<init>":(Ljava/util/Collection;)V
      24: putfield      #34                 // Field substringIndex_:Ljava/util/List;
      27: aload_0
      28: dup
      29: getfield      #28                 // Field bitField0_:I
      32: bipush        16
      34: ior
      35: putfield      #28                 // Field bitField0_:I
      38: return

  private void ensureReplaceCharIsMutable();
    Code:
       0: aload_0
       1: getfield      #28                 // Field bitField0_:I
       4: bipush        32
       6: iand
       7: bipush        32
       9: if_icmpeq     38
      12: aload_0
      13: new           #6                  // class java/util/ArrayList
      16: dup
      17: aload_0
      18: getfield      #32                 // Field replaceChar_:Ljava/util/List;
      21: invokespecial #37                 // Method java/util/ArrayList."<init>":(Ljava/util/Collection;)V
      24: putfield      #32                 // Field replaceChar_:Ljava/util/List;
      27: aload_0
      28: dup
      29: getfield      #28                 // Field bitField0_:I
      32: bipush        32
      34: ior
      35: putfield      #28                 // Field bitField0_:I
      38: return

  public kotlin.reflect.jvm.internal.impl.protobuf.GeneratedMessageLite getDefaultInstanceForType();
    Code:
       0: aload_0
       1: invokevirtual #68                 // Method getDefaultInstanceForType:()Lkotlin/reflect/jvm/internal/impl/metadata/jvm/JvmProtoBuf$StringTableTypes$Record;
       4: areturn

  public kotlin.reflect.jvm.internal.impl.protobuf.GeneratedMessageLite$Builder mergeFrom(kotlin.reflect.jvm.internal.impl.protobuf.GeneratedMessageLite);
    Code:
       0: aload_0
       1: aload_1
       2: checkcast     #12                 // class kotlin/reflect/jvm/internal/impl/metadata/jvm/JvmProtoBuf$StringTableTypes$Record
       5: invokevirtual #71                 // Method mergeFrom:(Lkotlin/reflect/jvm/internal/impl/metadata/jvm/JvmProtoBuf$StringTableTypes$Record;)Lkotlin/reflect/jvm/internal/impl/metadata/jvm/JvmProtoBuf$StringTableTypes$Record$Builder;
       8: areturn

  public kotlin.reflect.jvm.internal.impl.protobuf.GeneratedMessageLite$Builder clone();
    Code:
       0: aload_0
       1: invokevirtual #64                 // Method clone:()Lkotlin/reflect/jvm/internal/impl/metadata/jvm/JvmProtoBuf$StringTableTypes$Record$Builder;
       4: areturn

  public kotlin.reflect.jvm.internal.impl.protobuf.AbstractMessageLite$Builder mergeFrom(kotlin.reflect.jvm.internal.impl.protobuf.CodedInputStream, kotlin.reflect.jvm.internal.impl.protobuf.ExtensionRegistryLite) throws java.io.IOException;
    Code:
       0: aload_0
       1: aload_1
       2: aload_2
       3: invokevirtual #72                 // Method mergeFrom:(Lkotlin/reflect/jvm/internal/impl/protobuf/CodedInputStream;Lkotlin/reflect/jvm/internal/impl/protobuf/ExtensionRegistryLite;)Lkotlin/reflect/jvm/internal/impl/metadata/jvm/JvmProtoBuf$StringTableTypes$Record$Builder;
       6: areturn

  public kotlin.reflect.jvm.internal.impl.protobuf.AbstractMessageLite$Builder clone();
    Code:
       0: aload_0
       1: invokevirtual #64                 // Method clone:()Lkotlin/reflect/jvm/internal/impl/metadata/jvm/JvmProtoBuf$StringTableTypes$Record$Builder;
       4: areturn

  public kotlin.reflect.jvm.internal.impl.protobuf.MessageLite$Builder mergeFrom(kotlin.reflect.jvm.internal.impl.protobuf.CodedInputStream, kotlin.reflect.jvm.internal.impl.protobuf.ExtensionRegistryLite) throws java.io.IOException;
    Code:
       0: aload_0
       1: aload_1
       2: aload_2
       3: invokevirtual #72                 // Method mergeFrom:(Lkotlin/reflect/jvm/internal/impl/protobuf/CodedInputStream;Lkotlin/reflect/jvm/internal/impl/protobuf/ExtensionRegistryLite;)Lkotlin/reflect/jvm/internal/impl/metadata/jvm/JvmProtoBuf$StringTableTypes$Record$Builder;
       6: areturn

  public kotlin.reflect.jvm.internal.impl.protobuf.MessageLite build();
    Code:
       0: aload_0
       1: invokevirtual #62                 // Method build:()Lkotlin/reflect/jvm/internal/impl/metadata/jvm/JvmProtoBuf$StringTableTypes$Record;
       4: areturn

  public kotlin.reflect.jvm.internal.impl.protobuf.MessageLite getDefaultInstanceForType();
    Code:
       0: aload_0
       1: invokevirtual #68                 // Method getDefaultInstanceForType:()Lkotlin/reflect/jvm/internal/impl/metadata/jvm/JvmProtoBuf$StringTableTypes$Record;
       4: areturn

  public java.lang.Object clone() throws java.lang.CloneNotSupportedException;
    Code:
       0: aload_0
       1: invokevirtual #64                 // Method clone:()Lkotlin/reflect/jvm/internal/impl/metadata/jvm/JvmProtoBuf$StringTableTypes$Record$Builder;
       4: areturn

  static kotlin.reflect.jvm.internal.impl.metadata.jvm.JvmProtoBuf$StringTableTypes$Record$Builder access$200();
    Code:
       0: invokestatic  #65                 // Method create:()Lkotlin/reflect/jvm/internal/impl/metadata/jvm/JvmProtoBuf$StringTableTypes$Record$Builder;
       3: areturn
}
