Compiled from "RequestInfo.java"
public class org.apache.coyote.RequestInfo {
  private org.apache.coyote.RequestGroupInfo global;

  private final org.apache.coyote.Request req;

  private int stage;

  private java.lang.String workerThreadName;

  private javax.management.ObjectName rpName;

  private long bytesSent;

  private long bytesReceived;

  private long processingTime;

  private long maxTime;

  private java.lang.String maxRequestUri;

  private int requestCount;

  private int errorCount;

  private long lastRequestProcessingTime;

  public org.apache.coyote.RequestInfo(org.apache.coyote.Request);
    Code:
       0: aload_0
       1: invokespecial #1                  // Method java/lang/Object."<init>":()V
       4: aload_0
       5: aconst_null
       6: putfield      #2                  // Field global:Lorg/apache/coyote/RequestGroupInfo;
       9: aload_0
      10: iconst_0
      11: putfield      #4                  // Field stage:I
      14: aload_0
      15: lconst_0
      16: putfield      #5                  // Field lastRequestProcessingTime:J
      19: aload_0
      20: aload_1
      21: putfield      #6                  // Field req:Lorg/apache/coyote/Request;
      24: return

  public org.apache.coyote.RequestGroupInfo getGlobalProcessor();
    Code:
       0: aload_0
       1: getfield      #2                  // Field global:Lorg/apache/coyote/RequestGroupInfo;
       4: areturn

  public void setGlobalProcessor(org.apache.coyote.RequestGroupInfo);
    Code:
       0: aload_1
       1: ifnull        17
       4: aload_0
       5: aload_1
       6: putfield      #2                  // Field global:Lorg/apache/coyote/RequestGroupInfo;
       9: aload_1
      10: aload_0
      11: invokevirtual #7                  // Method org/apache/coyote/RequestGroupInfo.addRequestProcessor:(Lorg/apache/coyote/RequestInfo;)V
      14: goto          37
      17: aload_0
      18: getfield      #2                  // Field global:Lorg/apache/coyote/RequestGroupInfo;
      21: ifnull        37
      24: aload_0
      25: getfield      #2                  // Field global:Lorg/apache/coyote/RequestGroupInfo;
      28: aload_0
      29: invokevirtual #8                  // Method org/apache/coyote/RequestGroupInfo.removeRequestProcessor:(Lorg/apache/coyote/RequestInfo;)V
      32: aload_0
      33: aconst_null
      34: putfield      #2                  // Field global:Lorg/apache/coyote/RequestGroupInfo;
      37: return

  public java.lang.String getMethod();
    Code:
       0: aload_0
       1: getfield      #6                  // Field req:Lorg/apache/coyote/Request;
       4: invokevirtual #9                  // Method org/apache/coyote/Request.method:()Lorg/apache/tomcat/util/buf/MessageBytes;
       7: invokevirtual #10                 // Method org/apache/tomcat/util/buf/MessageBytes.toString:()Ljava/lang/String;
      10: areturn

  public java.lang.String getCurrentUri();
    Code:
       0: aload_0
       1: getfield      #6                  // Field req:Lorg/apache/coyote/Request;
       4: invokevirtual #11                 // Method org/apache/coyote/Request.requestURI:()Lorg/apache/tomcat/util/buf/MessageBytes;
       7: invokevirtual #10                 // Method org/apache/tomcat/util/buf/MessageBytes.toString:()Ljava/lang/String;
      10: areturn

  public java.lang.String getCurrentQueryString();
    Code:
       0: aload_0
       1: getfield      #6                  // Field req:Lorg/apache/coyote/Request;
       4: invokevirtual #12                 // Method org/apache/coyote/Request.queryString:()Lorg/apache/tomcat/util/buf/MessageBytes;
       7: invokevirtual #10                 // Method org/apache/tomcat/util/buf/MessageBytes.toString:()Ljava/lang/String;
      10: areturn

  public java.lang.String getProtocol();
    Code:
       0: aload_0
       1: getfield      #6                  // Field req:Lorg/apache/coyote/Request;
       4: invokevirtual #13                 // Method org/apache/coyote/Request.protocol:()Lorg/apache/tomcat/util/buf/MessageBytes;
       7: invokevirtual #10                 // Method org/apache/tomcat/util/buf/MessageBytes.toString:()Ljava/lang/String;
      10: areturn

  public java.lang.String getVirtualHost();
    Code:
       0: aload_0
       1: getfield      #6                  // Field req:Lorg/apache/coyote/Request;
       4: invokevirtual #14                 // Method org/apache/coyote/Request.serverName:()Lorg/apache/tomcat/util/buf/MessageBytes;
       7: invokevirtual #10                 // Method org/apache/tomcat/util/buf/MessageBytes.toString:()Ljava/lang/String;
      10: areturn

  public int getServerPort();
    Code:
       0: aload_0
       1: getfield      #6                  // Field req:Lorg/apache/coyote/Request;
       4: invokevirtual #15                 // Method org/apache/coyote/Request.getServerPort:()I
       7: ireturn

  public java.lang.String getRemoteAddr();
    Code:
       0: aload_0
       1: getfield      #6                  // Field req:Lorg/apache/coyote/Request;
       4: getstatic     #16                 // Field org/apache/coyote/ActionCode.REQ_HOST_ADDR_ATTRIBUTE:Lorg/apache/coyote/ActionCode;
       7: aconst_null
       8: invokevirtual #17                 // Method org/apache/coyote/Request.action:(Lorg/apache/coyote/ActionCode;Ljava/lang/Object;)V
      11: aload_0
      12: getfield      #6                  // Field req:Lorg/apache/coyote/Request;
      15: invokevirtual #18                 // Method org/apache/coyote/Request.remoteAddr:()Lorg/apache/tomcat/util/buf/MessageBytes;
      18: invokevirtual #10                 // Method org/apache/tomcat/util/buf/MessageBytes.toString:()Ljava/lang/String;
      21: areturn

  public java.lang.String getRemoteAddrForwarded();
    Code:
       0: aload_0
       1: getfield      #6                  // Field req:Lorg/apache/coyote/Request;
       4: ldc           #19                 // String org.apache.tomcat.remoteAddr
       6: invokevirtual #20                 // Method org/apache/coyote/Request.getAttribute:(Ljava/lang/String;)Ljava/lang/Object;
       9: checkcast     #21                 // class java/lang/String
      12: astore_1
      13: aload_1
      14: ifnonnull     22
      17: aload_0
      18: invokevirtual #22                 // Method getRemoteAddr:()Ljava/lang/String;
      21: areturn
      22: aload_1
      23: areturn

  public int getContentLength();
    Code:
       0: aload_0
       1: getfield      #6                  // Field req:Lorg/apache/coyote/Request;
       4: invokevirtual #23                 // Method org/apache/coyote/Request.getContentLength:()I
       7: ireturn

  public long getRequestBytesReceived();
    Code:
       0: aload_0
       1: getfield      #6                  // Field req:Lorg/apache/coyote/Request;
       4: invokevirtual #24                 // Method org/apache/coyote/Request.getBytesRead:()J
       7: lreturn

  public long getRequestBytesSent();
    Code:
       0: aload_0
       1: getfield      #6                  // Field req:Lorg/apache/coyote/Request;
       4: invokevirtual #25                 // Method org/apache/coyote/Request.getResponse:()Lorg/apache/coyote/Response;
       7: invokevirtual #26                 // Method org/apache/coyote/Response.getContentWritten:()J
      10: lreturn

  public long getRequestProcessingTime();
    Code:
       0: aload_0
       1: getfield      #6                  // Field req:Lorg/apache/coyote/Request;
       4: invokevirtual #27                 // Method org/apache/coyote/Request.getStartTime:()J
       7: lstore_1
       8: aload_0
       9: invokevirtual #28                 // Method getStage:()I
      12: bipush        7
      14: if_icmpeq     23
      17: lload_1
      18: lconst_0
      19: lcmp
      20: ifge          25
      23: lconst_0
      24: lreturn
      25: invokestatic  #29                 // Method java/lang/System.currentTimeMillis:()J
      28: lload_1
      29: lsub
      30: lreturn

  void updateCounters();
    Code:
       0: aload_0
       1: dup
       2: getfield      #30                 // Field bytesReceived:J
       5: aload_0
       6: getfield      #6                  // Field req:Lorg/apache/coyote/Request;
       9: invokevirtual #24                 // Method org/apache/coyote/Request.getBytesRead:()J
      12: ladd
      13: putfield      #30                 // Field bytesReceived:J
      16: aload_0
      17: dup
      18: getfield      #31                 // Field bytesSent:J
      21: aload_0
      22: getfield      #6                  // Field req:Lorg/apache/coyote/Request;
      25: invokevirtual #25                 // Method org/apache/coyote/Request.getResponse:()Lorg/apache/coyote/Response;
      28: invokevirtual #26                 // Method org/apache/coyote/Response.getContentWritten:()J
      31: ladd
      32: putfield      #31                 // Field bytesSent:J
      35: aload_0
      36: dup
      37: getfield      #32                 // Field requestCount:I
      40: iconst_1
      41: iadd
      42: putfield      #32                 // Field requestCount:I
      45: aload_0
      46: getfield      #6                  // Field req:Lorg/apache/coyote/Request;
      49: invokevirtual #25                 // Method org/apache/coyote/Request.getResponse:()Lorg/apache/coyote/Response;
      52: invokevirtual #33                 // Method org/apache/coyote/Response.getStatus:()I
      55: sipush        400
      58: if_icmplt     71
      61: aload_0
      62: dup
      63: getfield      #34                 // Field errorCount:I
      66: iconst_1
      67: iadd
      68: putfield      #34                 // Field errorCount:I
      71: aload_0
      72: getfield      #6                  // Field req:Lorg/apache/coyote/Request;
      75: invokevirtual #27                 // Method org/apache/coyote/Request.getStartTime:()J
      78: lstore_1
      79: invokestatic  #29                 // Method java/lang/System.currentTimeMillis:()J
      82: lstore_3
      83: lload_3
      84: lload_1
      85: lsub
      86: lstore        5
      88: aload_0
      89: lload         5
      91: putfield      #5                  // Field lastRequestProcessingTime:J
      94: aload_0
      95: dup
      96: getfield      #35                 // Field processingTime:J
      99: lload         5
     101: ladd
     102: putfield      #35                 // Field processingTime:J
     105: aload_0
     106: getfield      #36                 // Field maxTime:J
     109: lload         5
     111: lcmp
     112: ifge          135
     115: aload_0
     116: lload         5
     118: putfield      #36                 // Field maxTime:J
     121: aload_0
     122: aload_0
     123: getfield      #6                  // Field req:Lorg/apache/coyote/Request;
     126: invokevirtual #11                 // Method org/apache/coyote/Request.requestURI:()Lorg/apache/tomcat/util/buf/MessageBytes;
     129: invokevirtual #10                 // Method org/apache/tomcat/util/buf/MessageBytes.toString:()Ljava/lang/String;
     132: putfield      #37                 // Field maxRequestUri:Ljava/lang/String;
     135: return

  public int getStage();
    Code:
       0: aload_0
       1: getfield      #4                  // Field stage:I
       4: ireturn

  public void setStage(int);
    Code:
       0: aload_0
       1: iload_1
       2: putfield      #4                  // Field stage:I
       5: return

  public long getBytesSent();
    Code:
       0: aload_0
       1: getfield      #31                 // Field bytesSent:J
       4: lreturn

  public void setBytesSent(long);
    Code:
       0: aload_0
       1: lload_1
       2: putfield      #31                 // Field bytesSent:J
       5: return

  public long getBytesReceived();
    Code:
       0: aload_0
       1: getfield      #30                 // Field bytesReceived:J
       4: lreturn

  public void setBytesReceived(long);
    Code:
       0: aload_0
       1: lload_1
       2: putfield      #30                 // Field bytesReceived:J
       5: return

  public long getProcessingTime();
    Code:
       0: aload_0
       1: getfield      #35                 // Field processingTime:J
       4: lreturn

  public void setProcessingTime(long);
    Code:
       0: aload_0
       1: lload_1
       2: putfield      #35                 // Field processingTime:J
       5: return

  public long getMaxTime();
    Code:
       0: aload_0
       1: getfield      #36                 // Field maxTime:J
       4: lreturn

  public void setMaxTime(long);
    Code:
       0: aload_0
       1: lload_1
       2: putfield      #36                 // Field maxTime:J
       5: return

  public java.lang.String getMaxRequestUri();
    Code:
       0: aload_0
       1: getfield      #37                 // Field maxRequestUri:Ljava/lang/String;
       4: areturn

  public void setMaxRequestUri(java.lang.String);
    Code:
       0: aload_0
       1: aload_1
       2: putfield      #37                 // Field maxRequestUri:Ljava/lang/String;
       5: return

  public int getRequestCount();
    Code:
       0: aload_0
       1: getfield      #32                 // Field requestCount:I
       4: ireturn

  public void setRequestCount(int);
    Code:
       0: aload_0
       1: iload_1
       2: putfield      #32                 // Field requestCount:I
       5: return

  public int getErrorCount();
    Code:
       0: aload_0
       1: getfield      #34                 // Field errorCount:I
       4: ireturn

  public void setErrorCount(int);
    Code:
       0: aload_0
       1: iload_1
       2: putfield      #34                 // Field errorCount:I
       5: return

  public java.lang.String getWorkerThreadName();
    Code:
       0: aload_0
       1: getfield      #38                 // Field workerThreadName:Ljava/lang/String;
       4: areturn

  public javax.management.ObjectName getRpName();
    Code:
       0: aload_0
       1: getfield      #39                 // Field rpName:Ljavax/management/ObjectName;
       4: areturn

  public long getLastRequestProcessingTime();
    Code:
       0: aload_0
       1: getfield      #5                  // Field lastRequestProcessingTime:J
       4: lreturn

  public void setWorkerThreadName(java.lang.String);
    Code:
       0: aload_0
       1: aload_1
       2: putfield      #38                 // Field workerThreadName:Ljava/lang/String;
       5: return

  public void setRpName(javax.management.ObjectName);
    Code:
       0: aload_0
       1: aload_1
       2: putfield      #39                 // Field rpName:Ljavax/management/ObjectName;
       5: return

  public void setLastRequestProcessingTime(long);
    Code:
       0: aload_0
       1: lload_1
       2: putfield      #5                  // Field lastRequestProcessingTime:J
       5: return
}
