Compiled from "PackagesManagementException.java"
public class org.apache.pulsar.packages.management.core.exceptions.PackagesManagementException$NotFoundException extends org.apache.pulsar.packages.management.core.exceptions.PackagesManagementException {
  public org.apache.pulsar.packages.management.core.exceptions.PackagesManagementException$NotFoundException(java.lang.Throwable);
    Code:
       0: aload_0
       1: aload_1
       2: invokespecial #1                  // Method org/apache/pulsar/packages/management/core/exceptions/PackagesManagementException."<init>":(Ljava/lang/Throwable;)V
       5: return

  public org.apache.pulsar.packages.management.core.exceptions.PackagesManagementException$NotFoundException(java.lang.String);
    Code:
       0: aload_0
       1: aload_1
       2: invokespecial #2                  // Method org/apache/pulsar/packages/management/core/exceptions/PackagesManagementException."<init>":(Ljava/lang/String;)V
       5: return

  public org.apache.pulsar.packages.management.core.exceptions.PackagesManagementException$NotFoundException(java.lang.String, java.lang.Throwable);
    Code:
       0: aload_0
       1: aload_1
       2: aload_2
       3: invokespecial #3                  // Method org/apache/pulsar/packages/management/core/exceptions/PackagesManagementException."<init>":(Ljava/lang/String;Ljava/lang/Throwable;)V
       6: return
}
