Compiled from "RequiredPartsPolicyValidator.java"
public class org.apache.cxf.ws.security.wss4j.policyvalidators.RequiredPartsPolicyValidator implements org.apache.cxf.ws.security.wss4j.policyvalidators.SecurityPolicyValidator {
  public org.apache.cxf.ws.security.wss4j.policyvalidators.RequiredPartsPolicyValidator();
    Code:
       0: aload_0
       1: invokespecial #1                  // Method java/lang/Object."<init>":()V
       4: return

  public boolean canValidatePolicy(org.apache.cxf.ws.policy.AssertionInfo);
    Code:
       0: aload_1
       1: invokevirtual #2                  // Method org/apache/cxf/ws/policy/AssertionInfo.getAssertion:()Lorg/apache/neethi/Assertion;
       4: ifnull        47
       7: getstatic     #3                  // Field org/apache/wss4j/policy/SP12Constants.REQUIRED_PARTS:Ljavax/xml/namespace/QName;
      10: aload_1
      11: invokevirtual #2                  // Method org/apache/cxf/ws/policy/AssertionInfo.getAssertion:()Lorg/apache/neethi/Assertion;
      14: invokeinterface #4,  1            // InterfaceMethod org/apache/neethi/Assertion.getName:()Ljavax/xml/namespace/QName;
      19: invokevirtual #5                  // Method javax/xml/namespace/QName.equals:(Ljava/lang/Object;)Z
      22: ifne          43
      25: getstatic     #6                  // Field org/apache/wss4j/policy/SP11Constants.REQUIRED_PARTS:Ljavax/xml/namespace/QName;
      28: aload_1
      29: invokevirtual #2                  // Method org/apache/cxf/ws/policy/AssertionInfo.getAssertion:()Lorg/apache/neethi/Assertion;
      32: invokeinterface #4,  1            // InterfaceMethod org/apache/neethi/Assertion.getName:()Ljavax/xml/namespace/QName;
      37: invokevirtual #5                  // Method javax/xml/namespace/QName.equals:(Ljava/lang/Object;)Z
      40: ifeq          47
      43: iconst_1
      44: goto          48
      47: iconst_0
      48: ireturn

  public void validatePolicies(org.apache.cxf.ws.security.wss4j.policyvalidators.PolicyValidatorParameters, java.util.Collection<org.apache.cxf.ws.policy.AssertionInfo>);
    Code:
       0: aload_1
       1: invokevirtual #7                  // Method org/apache/cxf/ws/security/wss4j/policyvalidators/PolicyValidatorParameters.getSoapHeader:()Lorg/w3c/dom/Element;
       4: astore_3
       5: aload_2
       6: invokeinterface #8,  1            // InterfaceMethod java/util/Collection.iterator:()Ljava/util/Iterator;
      11: astore        4
      13: aload         4
      15: invokeinterface #9,  1            // InterfaceMethod java/util/Iterator.hasNext:()Z
      20: ifeq          153
      23: aload         4
      25: invokeinterface #10,  1           // InterfaceMethod java/util/Iterator.next:()Ljava/lang/Object;
      30: checkcast     #11                 // class org/apache/cxf/ws/policy/AssertionInfo
      33: astore        5
      35: aload         5
      37: invokevirtual #2                  // Method org/apache/cxf/ws/policy/AssertionInfo.getAssertion:()Lorg/apache/neethi/Assertion;
      40: checkcast     #12                 // class org/apache/wss4j/policy/model/RequiredParts
      43: astore        6
      45: aload         5
      47: iconst_1
      48: invokevirtual #13                 // Method org/apache/cxf/ws/policy/AssertionInfo.setAsserted:(Z)V
      51: aload         6
      53: invokevirtual #14                 // Method org/apache/wss4j/policy/model/RequiredParts.getHeaders:()Ljava/util/List;
      56: invokeinterface #15,  1           // InterfaceMethod java/util/List.iterator:()Ljava/util/Iterator;
      61: astore        7
      63: aload         7
      65: invokeinterface #9,  1            // InterfaceMethod java/util/Iterator.hasNext:()Z
      70: ifeq          150
      73: aload         7
      75: invokeinterface #10,  1           // InterfaceMethod java/util/Iterator.next:()Ljava/lang/Object;
      80: checkcast     #16                 // class org/apache/wss4j/policy/model/Header
      83: astore        8
      85: new           #17                 // class javax/xml/namespace/QName
      88: dup
      89: aload         8
      91: invokevirtual #18                 // Method org/apache/wss4j/policy/model/Header.getNamespace:()Ljava/lang/String;
      94: aload         8
      96: invokevirtual #19                 // Method org/apache/wss4j/policy/model/Header.getName:()Ljava/lang/String;
      99: invokespecial #20                 // Method javax/xml/namespace/QName."<init>":(Ljava/lang/String;Ljava/lang/String;)V
     102: astore        9
     104: aload_3
     105: ifnull        117
     108: aload_3
     109: aload         9
     111: invokestatic  #21                 // Method org/apache/cxf/helpers/DOMUtils.getFirstChildWithName:(Lorg/w3c/dom/Element;Ljavax/xml/namespace/QName;)Lorg/w3c/dom/Element;
     114: ifnonnull     147
     117: aload         5
     119: new           #22                 // class java/lang/StringBuilder
     122: dup
     123: invokespecial #23                 // Method java/lang/StringBuilder."<init>":()V
     126: ldc           #24                 // String No header element of name
     128: invokevirtual #25                 // Method java/lang/StringBuilder.append:(Ljava/lang/String;)Ljava/lang/StringBuilder;
     131: aload         9
     133: invokevirtual #26                 // Method java/lang/StringBuilder.append:(Ljava/lang/Object;)Ljava/lang/StringBuilder;
     136: ldc           #27                 // String  found.
     138: invokevirtual #25                 // Method java/lang/StringBuilder.append:(Ljava/lang/String;)Ljava/lang/StringBuilder;
     141: invokevirtual #28                 // Method java/lang/StringBuilder.toString:()Ljava/lang/String;
     144: invokevirtual #29                 // Method org/apache/cxf/ws/policy/AssertionInfo.setNotAsserted:(Ljava/lang/String;)V
     147: goto          63
     150: goto          13
     153: return
}
