Compiled from "BaseJsonNode.java"
public abstract class com.fasterxml.jackson.databind.node.BaseJsonNode extends com.fasterxml.jackson.databind.JsonNode implements java.io.Serializable {
  private static final long serialVersionUID;

  java.lang.Object writeReplace();
    Code:
       0: aload_0
       1: invokestatic  #1                  // Method com/fasterxml/jackson/databind/node/NodeSerialization.from:(Ljava/lang/Object;)Lcom/fasterxml/jackson/databind/node/NodeSerialization;
       4: areturn

  protected com.fasterxml.jackson.databind.node.BaseJsonNode();
    Code:
       0: aload_0
       1: invokespecial #2                  // Method com/fasterxml/jackson/databind/JsonNode."<init>":()V
       4: return

  public final com.fasterxml.jackson.databind.JsonNode findPath(java.lang.String);
    Code:
       0: aload_0
       1: aload_1
       2: invokevirtual #3                  // Method findValue:(Ljava/lang/String;)Lcom/fasterxml/jackson/databind/JsonNode;
       5: astore_2
       6: aload_2
       7: ifnonnull     14
      10: invokestatic  #4                  // Method com/fasterxml/jackson/databind/node/MissingNode.getInstance:()Lcom/fasterxml/jackson/databind/node/MissingNode;
      13: areturn
      14: aload_2
      15: areturn

  public abstract int hashCode();

  public com.fasterxml.jackson.databind.JsonNode required(java.lang.String);
    Code:
       0: aload_0
       1: ldc           #5                  // String Node of type `%s` has no fields
       3: iconst_1
       4: anewarray     #6                  // class java/lang/Object
       7: dup
       8: iconst_0
       9: aload_0
      10: invokevirtual #7                  // Method java/lang/Object.getClass:()Ljava/lang/Class;
      13: invokevirtual #8                  // Method java/lang/Class.getSimpleName:()Ljava/lang/String;
      16: aastore
      17: invokevirtual #9                  // Method _reportRequiredViolation:(Ljava/lang/String;[Ljava/lang/Object;)Ljava/lang/Object;
      20: checkcast     #10                 // class com/fasterxml/jackson/databind/JsonNode
      23: areturn

  public com.fasterxml.jackson.databind.JsonNode required(int);
    Code:
       0: aload_0
       1: ldc           #11                 // String Node of type `%s` has no indexed values
       3: iconst_1
       4: anewarray     #6                  // class java/lang/Object
       7: dup
       8: iconst_0
       9: aload_0
      10: invokevirtual #7                  // Method java/lang/Object.getClass:()Ljava/lang/Class;
      13: invokevirtual #8                  // Method java/lang/Class.getSimpleName:()Ljava/lang/String;
      16: aastore
      17: invokevirtual #9                  // Method _reportRequiredViolation:(Ljava/lang/String;[Ljava/lang/Object;)Ljava/lang/Object;
      20: checkcast     #10                 // class com/fasterxml/jackson/databind/JsonNode
      23: areturn

  public com.fasterxml.jackson.core.JsonParser traverse();
    Code:
       0: new           #12                 // class com/fasterxml/jackson/databind/node/TreeTraversingParser
       3: dup
       4: aload_0
       5: invokespecial #13                 // Method com/fasterxml/jackson/databind/node/TreeTraversingParser."<init>":(Lcom/fasterxml/jackson/databind/JsonNode;)V
       8: areturn

  public com.fasterxml.jackson.core.JsonParser traverse(com.fasterxml.jackson.core.ObjectCodec);
    Code:
       0: new           #12                 // class com/fasterxml/jackson/databind/node/TreeTraversingParser
       3: dup
       4: aload_0
       5: aload_1
       6: invokespecial #14                 // Method com/fasterxml/jackson/databind/node/TreeTraversingParser."<init>":(Lcom/fasterxml/jackson/databind/JsonNode;Lcom/fasterxml/jackson/core/ObjectCodec;)V
       9: areturn

  public abstract com.fasterxml.jackson.core.JsonToken asToken();

  public com.fasterxml.jackson.core.JsonParser$NumberType numberType();
    Code:
       0: aconst_null
       1: areturn

  public com.fasterxml.jackson.databind.node.ObjectNode withObject(com.fasterxml.jackson.core.JsonPointer, com.fasterxml.jackson.databind.JsonNode$OverwriteMode, boolean);
    Code:
       0: aload_1
       1: invokevirtual #15                 // Method com/fasterxml/jackson/core/JsonPointer.matches:()Z
       4: ifeq          40
       7: aload_0
       8: instanceof    #16                 // class com/fasterxml/jackson/databind/node/ObjectNode
      11: ifeq          19
      14: aload_0
      15: checkcast     #16                 // class com/fasterxml/jackson/databind/node/ObjectNode
      18: areturn
      19: aload_0
      20: ldc           #17                 // String Can only call `withObject()` with empty JSON Pointer on `ObjectNode`, not `%s`
      22: iconst_1
      23: anewarray     #6                  // class java/lang/Object
      26: dup
      27: iconst_0
      28: aload_0
      29: invokevirtual #7                  // Method java/lang/Object.getClass:()Ljava/lang/Class;
      32: invokevirtual #18                 // Method java/lang/Class.getName:()Ljava/lang/String;
      35: aastore
      36: invokevirtual #19                 // Method _reportWrongNodeType:(Ljava/lang/String;[Ljava/lang/Object;)Ljava/lang/Object;
      39: pop
      40: aload_0
      41: aload_1
      42: aload_1
      43: aload_2
      44: iload_3
      45: invokevirtual #20                 // Method _withObject:(Lcom/fasterxml/jackson/core/JsonPointer;Lcom/fasterxml/jackson/core/JsonPointer;Lcom/fasterxml/jackson/databind/JsonNode$OverwriteMode;Z)Lcom/fasterxml/jackson/databind/node/ObjectNode;
      48: astore        4
      50: aload         4
      52: ifnonnull     80
      55: aload_0
      56: ldc           #21                 // String Cannot replace context node (of type `%s`) using `withObject()` with  JSON Pointer \'%s\'
      58: iconst_2
      59: anewarray     #6                  // class java/lang/Object
      62: dup
      63: iconst_0
      64: aload_0
      65: invokevirtual #7                  // Method java/lang/Object.getClass:()Ljava/lang/Class;
      68: invokevirtual #18                 // Method java/lang/Class.getName:()Ljava/lang/String;
      71: aastore
      72: dup
      73: iconst_1
      74: aload_1
      75: aastore
      76: invokevirtual #19                 // Method _reportWrongNodeType:(Ljava/lang/String;[Ljava/lang/Object;)Ljava/lang/Object;
      79: pop
      80: aload         4
      82: areturn

  protected com.fasterxml.jackson.databind.node.ObjectNode _withObject(com.fasterxml.jackson.core.JsonPointer, com.fasterxml.jackson.core.JsonPointer, com.fasterxml.jackson.databind.JsonNode$OverwriteMode, boolean);
    Code:
       0: aconst_null
       1: areturn

  protected void _withXxxVerifyReplace(com.fasterxml.jackson.core.JsonPointer, com.fasterxml.jackson.core.JsonPointer, com.fasterxml.jackson.databind.JsonNode$OverwriteMode, boolean, com.fasterxml.jackson.databind.JsonNode);
    Code:
       0: aload_0
       1: aload         5
       3: aload_3
       4: invokevirtual #22                 // Method _withXxxMayReplace:(Lcom/fasterxml/jackson/databind/JsonNode;Lcom/fasterxml/jackson/databind/JsonNode$OverwriteMode;)Z
       7: ifne          47
      10: aload_0
      11: ldc           #23                 // String Cannot replace `JsonNode` of type `%s` for property \"%s\" in JSON Pointer \"%s\" (mode `OverwriteMode.%s`)
      13: iconst_4
      14: anewarray     #6                  // class java/lang/Object
      17: dup
      18: iconst_0
      19: aload         5
      21: invokevirtual #7                  // Method java/lang/Object.getClass:()Ljava/lang/Class;
      24: invokevirtual #18                 // Method java/lang/Class.getName:()Ljava/lang/String;
      27: aastore
      28: dup
      29: iconst_1
      30: aload_2
      31: invokevirtual #24                 // Method com/fasterxml/jackson/core/JsonPointer.getMatchingProperty:()Ljava/lang/String;
      34: aastore
      35: dup
      36: iconst_2
      37: aload_1
      38: aastore
      39: dup
      40: iconst_3
      41: aload_3
      42: aastore
      43: invokevirtual #19                 // Method _reportWrongNodeType:(Ljava/lang/String;[Ljava/lang/Object;)Ljava/lang/Object;
      46: pop
      47: return

  protected boolean _withXxxMayReplace(com.fasterxml.jackson.databind.JsonNode, com.fasterxml.jackson.databind.JsonNode$OverwriteMode);
    Code:
       0: getstatic     #25                 // Field com/fasterxml/jackson/databind/node/BaseJsonNode$1.$SwitchMap$com$fasterxml$jackson$databind$JsonNode$OverwriteMode:[I
       3: aload_2
       4: invokevirtual #26                 // Method com/fasterxml/jackson/databind/JsonNode$OverwriteMode.ordinal:()I
       7: iaload
       8: tableswitch   { // 1 to 4
                     1: 40
                     2: 42
                     3: 47
                     4: 60
               default: 60
          }
      40: iconst_0
      41: ireturn
      42: aload_1
      43: invokevirtual #27                 // Method com/fasterxml/jackson/databind/JsonNode.isNull:()Z
      46: ireturn
      47: aload_1
      48: invokevirtual #28                 // Method com/fasterxml/jackson/databind/JsonNode.isContainerNode:()Z
      51: ifne          58
      54: iconst_1
      55: goto          59
      58: iconst_0
      59: ireturn
      60: iconst_1
      61: ireturn

  public com.fasterxml.jackson.databind.node.ArrayNode withArray(com.fasterxml.jackson.core.JsonPointer, com.fasterxml.jackson.databind.JsonNode$OverwriteMode, boolean);
    Code:
       0: aload_1
       1: invokevirtual #15                 // Method com/fasterxml/jackson/core/JsonPointer.matches:()Z
       4: ifeq          40
       7: aload_0
       8: instanceof    #29                 // class com/fasterxml/jackson/databind/node/ArrayNode
      11: ifeq          19
      14: aload_0
      15: checkcast     #29                 // class com/fasterxml/jackson/databind/node/ArrayNode
      18: areturn
      19: aload_0
      20: ldc           #30                 // String Can only call `withArray()` with empty JSON Pointer on `ArrayNode`, not `%s`
      22: iconst_1
      23: anewarray     #6                  // class java/lang/Object
      26: dup
      27: iconst_0
      28: aload_0
      29: invokevirtual #7                  // Method java/lang/Object.getClass:()Ljava/lang/Class;
      32: invokevirtual #18                 // Method java/lang/Class.getName:()Ljava/lang/String;
      35: aastore
      36: invokevirtual #19                 // Method _reportWrongNodeType:(Ljava/lang/String;[Ljava/lang/Object;)Ljava/lang/Object;
      39: pop
      40: aload_0
      41: aload_1
      42: aload_1
      43: aload_2
      44: iload_3
      45: invokevirtual #31                 // Method _withArray:(Lcom/fasterxml/jackson/core/JsonPointer;Lcom/fasterxml/jackson/core/JsonPointer;Lcom/fasterxml/jackson/databind/JsonNode$OverwriteMode;Z)Lcom/fasterxml/jackson/databind/node/ArrayNode;
      48: astore        4
      50: aload         4
      52: ifnonnull     80
      55: aload_0
      56: ldc           #32                 // String Cannot replace context node (of type `%s`) using `withArray()` with  JSON Pointer \'%s\'
      58: iconst_2
      59: anewarray     #6                  // class java/lang/Object
      62: dup
      63: iconst_0
      64: aload_0
      65: invokevirtual #7                  // Method java/lang/Object.getClass:()Ljava/lang/Class;
      68: invokevirtual #18                 // Method java/lang/Class.getName:()Ljava/lang/String;
      71: aastore
      72: dup
      73: iconst_1
      74: aload_1
      75: aastore
      76: invokevirtual #19                 // Method _reportWrongNodeType:(Ljava/lang/String;[Ljava/lang/Object;)Ljava/lang/Object;
      79: pop
      80: aload         4
      82: areturn

  protected com.fasterxml.jackson.databind.node.ArrayNode _withArray(com.fasterxml.jackson.core.JsonPointer, com.fasterxml.jackson.core.JsonPointer, com.fasterxml.jackson.databind.JsonNode$OverwriteMode, boolean);
    Code:
       0: aconst_null
       1: areturn

  public abstract void serialize(com.fasterxml.jackson.core.JsonGenerator, com.fasterxml.jackson.databind.SerializerProvider) throws java.io.IOException;

  public abstract void serializeWithType(com.fasterxml.jackson.core.JsonGenerator, com.fasterxml.jackson.databind.SerializerProvider, com.fasterxml.jackson.databind.jsontype.TypeSerializer) throws java.io.IOException;

  public java.lang.String toString();
    Code:
       0: aload_0
       1: invokestatic  #33                 // Method com/fasterxml/jackson/databind/node/InternalNodeMapper.nodeToString:(Lcom/fasterxml/jackson/databind/node/BaseJsonNode;)Ljava/lang/String;
       4: areturn

  public java.lang.String toPrettyString();
    Code:
       0: aload_0
       1: invokestatic  #34                 // Method com/fasterxml/jackson/databind/node/InternalNodeMapper.nodeToPrettyString:(Lcom/fasterxml/jackson/databind/node/BaseJsonNode;)Ljava/lang/String;
       4: areturn

  protected <T> T _reportWrongNodeType(java.lang.String, java.lang.Object...);
    Code:
       0: new           #35                 // class java/lang/UnsupportedOperationException
       3: dup
       4: aload_1
       5: aload_2
       6: invokestatic  #36                 // Method java/lang/String.format:(Ljava/lang/String;[Ljava/lang/Object;)Ljava/lang/String;
       9: invokespecial #37                 // Method java/lang/UnsupportedOperationException."<init>":(Ljava/lang/String;)V
      12: athrow

  protected <T> T _reportWrongNodeOperation(java.lang.String, java.lang.Object...);
    Code:
       0: new           #35                 // class java/lang/UnsupportedOperationException
       3: dup
       4: aload_1
       5: aload_2
       6: invokestatic  #36                 // Method java/lang/String.format:(Ljava/lang/String;[Ljava/lang/Object;)Ljava/lang/String;
       9: invokespecial #37                 // Method java/lang/UnsupportedOperationException."<init>":(Ljava/lang/String;)V
      12: athrow

  protected com.fasterxml.jackson.core.JsonPointer _jsonPointerIfValid(java.lang.String);
    Code:
       0: aload_1
       1: invokevirtual #38                 // Method java/lang/String.isEmpty:()Z
       4: ifne          17
       7: aload_1
       8: iconst_0
       9: invokevirtual #39                 // Method java/lang/String.charAt:(I)C
      12: bipush        47
      14: if_icmpne     22
      17: aload_1
      18: invokestatic  #40                 // Method com/fasterxml/jackson/core/JsonPointer.compile:(Ljava/lang/String;)Lcom/fasterxml/jackson/core/JsonPointer;
      21: areturn
      22: aconst_null
      23: areturn

  protected java.math.BigInteger _bigIntFromBigDec(java.math.BigDecimal);
    Code:
       0: invokestatic  #41                 // Method com/fasterxml/jackson/core/StreamReadConstraints.defaults:()Lcom/fasterxml/jackson/core/StreamReadConstraints;
       3: aload_1
       4: invokevirtual #42                 // Method java/math/BigDecimal.scale:()I
       7: invokevirtual #43                 // Method com/fasterxml/jackson/core/StreamReadConstraints.validateBigIntegerScale:(I)V
      10: goto          19
      13: astore_2
      14: aload_2
      15: invokestatic  #45                 // Method com/fasterxml/jackson/databind/util/ExceptionUtil.throwSneaky:(Ljava/io/IOException;)Ljava/lang/Object;
      18: pop
      19: aload_1
      20: invokevirtual #46                 // Method java/math/BigDecimal.toBigInteger:()Ljava/math/BigInteger;
      23: areturn
    Exception table:
       from    to  target type
           0    10    13   Class com/fasterxml/jackson/core/exc/StreamConstraintsException
}
