Compiled from "CuratorCacheBridgeBuilderImpl.java"
class org.apache.curator.framework.recipes.cache.CuratorCacheBridgeBuilderImpl implements org.apache.curator.framework.recipes.cache.CuratorCacheBridgeBuilder {
  private final org.apache.curator.framework.CuratorFramework client;

  private final java.lang.String path;

  private org.apache.curator.framework.recipes.cache.CuratorCache$Options[] options;

  private boolean cacheData;

  private java.util.concurrent.ExecutorService executorService;

  private final boolean forceTreeCache;

  org.apache.curator.framework.recipes.cache.CuratorCacheBridgeBuilderImpl(org.apache.curator.framework.CuratorFramework, java.lang.String);
    Code:
       0: aload_0
       1: invokespecial #28                 // Method java/lang/Object."<init>":()V
       4: aload_0
       5: iconst_1
       6: putfield      #30                 // Field cacheData:Z
       9: aload_0
      10: aconst_null
      11: putfield      #32                 // Field executorService:Ljava/util/concurrent/ExecutorService;
      14: aload_0
      15: ldc           #34                 // String curator-cache-bridge-force-tree-cache
      17: invokestatic  #40                 // Method java/lang/Boolean.getBoolean:(Ljava/lang/String;)Z
      20: putfield      #42                 // Field forceTreeCache:Z
      23: aload_0
      24: aload_1
      25: putfield      #44                 // Field client:Lorg/apache/curator/framework/CuratorFramework;
      28: aload_0
      29: aload_2
      30: putfield      #46                 // Field path:Ljava/lang/String;
      33: return

  public org.apache.curator.framework.recipes.cache.CuratorCacheBridgeBuilder withOptions(org.apache.curator.framework.recipes.cache.CuratorCache$Options...);
    Code:
       0: aload_0
       1: aload_1
       2: putfield      #52                 // Field options:[Lorg/apache/curator/framework/recipes/cache/CuratorCache$Options;
       5: aload_0
       6: areturn

  public org.apache.curator.framework.recipes.cache.CuratorCacheBridgeBuilder withDataNotCached();
    Code:
       0: aload_0
       1: iconst_0
       2: putfield      #30                 // Field cacheData:Z
       5: aload_0
       6: areturn

  public org.apache.curator.framework.recipes.cache.CuratorCacheBridgeBuilder withExecutorService(java.util.concurrent.ExecutorService);
    Code:
       0: aload_0
       1: aload_1
       2: putfield      #32                 // Field executorService:Ljava/util/concurrent/ExecutorService;
       5: aload_0
       6: areturn

  public org.apache.curator.framework.recipes.cache.CuratorCacheBridge build();
    Code:
       0: aload_0
       1: getfield      #42                 // Field forceTreeCache:Z
       4: ifne          73
       7: invokestatic  #64                 // Method org/apache/curator/utils/Compatibility.hasPersistentWatchers:()Z
      10: ifeq          73
      13: aload_0
      14: getfield      #32                 // Field executorService:Ljava/util/concurrent/ExecutorService;
      17: ifnull        34
      20: aload_0
      21: invokevirtual #68                 // Method java/lang/Object.getClass:()Ljava/lang/Class;
      24: invokestatic  #74                 // Method org/slf4j/LoggerFactory.getLogger:(Ljava/lang/Class;)Lorg/slf4j/Logger;
      27: ldc           #76                 // String CuratorCache does not support custom ExecutorService
      29: invokeinterface #82,  2           // InterfaceMethod org/slf4j/Logger.warn:(Ljava/lang/String;)V
      34: aload_0
      35: getfield      #30                 // Field cacheData:Z
      38: ifeq          47
      41: invokestatic  #88                 // InterfaceMethod org/apache/curator/framework/recipes/cache/CuratorCacheStorage.standard:()Lorg/apache/curator/framework/recipes/cache/CuratorCacheStorage;
      44: goto          50
      47: invokestatic  #91                 // InterfaceMethod org/apache/curator/framework/recipes/cache/CuratorCacheStorage.dataNotCached:()Lorg/apache/curator/framework/recipes/cache/CuratorCacheStorage;
      50: astore_1
      51: new           #93                 // class org/apache/curator/framework/recipes/cache/CuratorCacheImpl
      54: dup
      55: aload_0
      56: getfield      #44                 // Field client:Lorg/apache/curator/framework/CuratorFramework;
      59: aload_1
      60: aload_0
      61: getfield      #46                 // Field path:Ljava/lang/String;
      64: aload_0
      65: getfield      #52                 // Field options:[Lorg/apache/curator/framework/recipes/cache/CuratorCache$Options;
      68: aconst_null
      69: invokespecial #96                 // Method org/apache/curator/framework/recipes/cache/CuratorCacheImpl."<init>":(Lorg/apache/curator/framework/CuratorFramework;Lorg/apache/curator/framework/recipes/cache/CuratorCacheStorage;Ljava/lang/String;[Lorg/apache/curator/framework/recipes/cache/CuratorCache$Options;Ljava/util/function/Consumer;)V
      72: areturn
      73: new           #98                 // class org/apache/curator/framework/recipes/cache/CompatibleCuratorCacheBridge
      76: dup
      77: aload_0
      78: getfield      #44                 // Field client:Lorg/apache/curator/framework/CuratorFramework;
      81: aload_0
      82: getfield      #46                 // Field path:Ljava/lang/String;
      85: aload_0
      86: getfield      #52                 // Field options:[Lorg/apache/curator/framework/recipes/cache/CuratorCache$Options;
      89: aload_0
      90: getfield      #32                 // Field executorService:Ljava/util/concurrent/ExecutorService;
      93: aload_0
      94: getfield      #30                 // Field cacheData:Z
      97: invokespecial #101                // Method org/apache/curator/framework/recipes/cache/CompatibleCuratorCacheBridge."<init>":(Lorg/apache/curator/framework/CuratorFramework;Ljava/lang/String;[Lorg/apache/curator/framework/recipes/cache/CuratorCache$Options;Ljava/util/concurrent/ExecutorService;Z)V
     100: areturn
}
