Compiled from "EventOperation.java"
class org.apache.curator.framework.recipes.cache.EventOperation implements org.apache.curator.framework.recipes.cache.Operation {
  private final org.apache.curator.framework.recipes.cache.PathChildrenCache cache;

  private final org.apache.curator.framework.recipes.cache.PathChildrenCacheEvent event;

  org.apache.curator.framework.recipes.cache.EventOperation(org.apache.curator.framework.recipes.cache.PathChildrenCache, org.apache.curator.framework.recipes.cache.PathChildrenCacheEvent);
    Code:
       0: aload_0
       1: invokespecial #16                 // Method java/lang/Object."<init>":()V
       4: aload_0
       5: aload_1
       6: putfield      #18                 // Field cache:Lorg/apache/curator/framework/recipes/cache/PathChildrenCache;
       9: aload_0
      10: aload_2
      11: putfield      #20                 // Field event:Lorg/apache/curator/framework/recipes/cache/PathChildrenCacheEvent;
      14: return

  public void invoke();
    Code:
       0: aload_0
       1: getfield      #18                 // Field cache:Lorg/apache/curator/framework/recipes/cache/PathChildrenCache;
       4: aload_0
       5: getfield      #20                 // Field event:Lorg/apache/curator/framework/recipes/cache/PathChildrenCacheEvent;
       8: invokevirtual #29                 // Method org/apache/curator/framework/recipes/cache/PathChildrenCache.callListeners:(Lorg/apache/curator/framework/recipes/cache/PathChildrenCacheEvent;)V
      11: return

  public java.lang.String toString();
    Code:
       0: new           #33                 // class java/lang/StringBuilder
       3: dup
       4: invokespecial #34                 // Method java/lang/StringBuilder."<init>":()V
       7: ldc           #36                 // String EventOperation{event=
       9: invokevirtual #40                 // Method java/lang/StringBuilder.append:(Ljava/lang/String;)Ljava/lang/StringBuilder;
      12: aload_0
      13: getfield      #20                 // Field event:Lorg/apache/curator/framework/recipes/cache/PathChildrenCacheEvent;
      16: invokevirtual #43                 // Method java/lang/StringBuilder.append:(Ljava/lang/Object;)Ljava/lang/StringBuilder;
      19: bipush        125
      21: invokevirtual #46                 // Method java/lang/StringBuilder.append:(C)Ljava/lang/StringBuilder;
      24: invokevirtual #48                 // Method java/lang/StringBuilder.toString:()Ljava/lang/String;
      27: areturn
}
