Compiled from "PathChildrenCache.java"
class org.apache.curator.framework.recipes.cache.PathChildrenCache$8 implements java.lang.Runnable {
  final org.apache.curator.framework.recipes.cache.Operation val$operation;

  final org.apache.curator.framework.recipes.cache.PathChildrenCache this$0;

  org.apache.curator.framework.recipes.cache.PathChildrenCache$8(org.apache.curator.framework.recipes.cache.PathChildrenCache, org.apache.curator.framework.recipes.cache.Operation);
    Code:
       0: aload_0
       1: aload_1
       2: putfield      #23                 // Field this$0:Lorg/apache/curator/framework/recipes/cache/PathChildrenCache;
       5: aload_0
       6: aload_2
       7: putfield      #25                 // Field val$operation:Lorg/apache/curator/framework/recipes/cache/Operation;
      10: aload_0
      11: invokespecial #28                 // Method java/lang/Object."<init>":()V
      14: return

  public void run();
    Code:
       0: aload_0
       1: getfield      #23                 // Field this$0:Lorg/apache/curator/framework/recipes/cache/PathChildrenCache;
       4: invokestatic  #39                 // Method org/apache/curator/framework/recipes/cache/PathChildrenCache.access$900:(Lorg/apache/curator/framework/recipes/cache/PathChildrenCache;)Ljava/util/Set;
       7: aload_0
       8: getfield      #25                 // Field val$operation:Lorg/apache/curator/framework/recipes/cache/Operation;
      11: invokeinterface #45,  2           // InterfaceMethod java/util/Set.remove:(Ljava/lang/Object;)Z
      16: pop
      17: aload_0
      18: getfield      #25                 // Field val$operation:Lorg/apache/curator/framework/recipes/cache/Operation;
      21: invokeinterface #50,  1           // InterfaceMethod org/apache/curator/framework/recipes/cache/Operation.invoke:()V
      26: goto          77
      29: astore_1
      30: aload_0
      31: getfield      #23                 // Field this$0:Lorg/apache/curator/framework/recipes/cache/PathChildrenCache;
      34: invokestatic  #54                 // Method org/apache/curator/framework/recipes/cache/PathChildrenCache.access$1000:(Lorg/apache/curator/framework/recipes/cache/PathChildrenCache;)Ljava/util/concurrent/atomic/AtomicReference;
      37: invokevirtual #60                 // Method java/util/concurrent/atomic/AtomicReference.get:()Ljava/lang/Object;
      40: getstatic     #64                 // Field org/apache/curator/framework/recipes/cache/PathChildrenCache$State.CLOSED:Lorg/apache/curator/framework/recipes/cache/PathChildrenCache$State;
      43: if_acmpeq     54
      46: aload_0
      47: getfield      #23                 // Field this$0:Lorg/apache/curator/framework/recipes/cache/PathChildrenCache;
      50: aload_1
      51: invokevirtual #68                 // Method org/apache/curator/framework/recipes/cache/PathChildrenCache.handleException:(Ljava/lang/Throwable;)V
      54: invokestatic  #74                 // Method java/lang/Thread.currentThread:()Ljava/lang/Thread;
      57: invokevirtual #77                 // Method java/lang/Thread.interrupt:()V
      60: goto          77
      63: astore_1
      64: aload_1
      65: invokestatic  #83                 // Method org/apache/curator/utils/ThreadUtils.checkInterrupted:(Ljava/lang/Throwable;)Z
      68: pop
      69: aload_0
      70: getfield      #23                 // Field this$0:Lorg/apache/curator/framework/recipes/cache/PathChildrenCache;
      73: aload_1
      74: invokevirtual #68                 // Method org/apache/curator/framework/recipes/cache/PathChildrenCache.handleException:(Ljava/lang/Throwable;)V
      77: return
    Exception table:
       from    to  target type
           0    26    29   Class java/lang/InterruptedException
           0    26    63   Class java/lang/Exception
}
