Compiled from "Factory.java"
public class org.apache.jena.graph.Factory {
  private static org.apache.jena.graph.Graph emptyGraph;

  private org.apache.jena.graph.Factory();
    Code:
       0: aload_0
       1: invokespecial #1                  // Method java/lang/Object."<init>":()V
       4: return

  public static org.apache.jena.graph.Graph createDefaultGraph();
    Code:
       0: invokestatic  #2                  // Method createGraphMem:()Lorg/apache/jena/graph/Graph;
       3: areturn

  public static org.apache.jena.graph.Graph createGraphMem();
    Code:
       0: new           #3                  // class org/apache/jena/mem/GraphMem
       3: dup
       4: invokespecial #4                  // Method org/apache/jena/mem/GraphMem."<init>":()V
       7: areturn

  public static org.apache.jena.graph.Graph createGraphMemWithTransactionHandler(org.apache.jena.graph.TransactionHandler);
    Code:
       0: new           #5                  // class org/apache/jena/graph/Factory$1
       3: dup
       4: aload_0
       5: invokespecial #6                  // Method org/apache/jena/graph/Factory$1."<init>":(Lorg/apache/jena/graph/TransactionHandler;)V
       8: astore_1
       9: aload_1
      10: areturn

  public static org.apache.jena.graph.Graph empty();
    Code:
       0: getstatic     #7                  // Field emptyGraph:Lorg/apache/jena/graph/Graph;
       3: areturn

  static {};
    Code:
       0: new           #8                  // class org/apache/jena/graph/Factory$2
       3: dup
       4: invokespecial #9                  // Method org/apache/jena/graph/Factory$2."<init>":()V
       7: putstatic     #7                  // Field emptyGraph:Lorg/apache/jena/graph/Graph;
      10: return
}
