Compiled from "Factory.java"
final class org.apache.jena.graph.Factory$1 extends org.apache.jena.mem.GraphMem {
  final org.apache.jena.graph.TransactionHandler val$th;

  org.apache.jena.graph.Factory$1(org.apache.jena.graph.TransactionHandler);
    Code:
       0: aload_0
       1: aload_1
       2: putfield      #1                  // Field val$th:Lorg/apache/jena/graph/TransactionHandler;
       5: aload_0
       6: invokespecial #2                  // Method org/apache/jena/mem/GraphMem."<init>":()V
       9: return

  public org.apache.jena.graph.TransactionHandler getTransactionHandler();
    Code:
       0: aload_0
       1: getfield      #1                  // Field val$th:Lorg/apache/jena/graph/TransactionHandler;
       4: areturn
}
