Compiled from "GraphExtract.java"
public class org.apache.jena.graph.GraphExtract$Extraction {
  protected org.apache.jena.graph.Graph toUpdate;

  protected org.apache.jena.graph.Graph extractFrom;

  protected java.util.Set<org.apache.jena.graph.Node> active;

  protected org.apache.jena.graph.TripleBoundary b;

  org.apache.jena.graph.GraphExtract$Extraction(org.apache.jena.graph.TripleBoundary, org.apache.jena.graph.Graph, org.apache.jena.graph.Graph);
    Code:
       0: aload_0
       1: invokespecial #1                  // Method java/lang/Object."<init>":()V
       4: aload_0
       5: aload_2
       6: putfield      #2                  // Field toUpdate:Lorg/apache/jena/graph/Graph;
       9: aload_0
      10: aload_3
      11: putfield      #3                  // Field extractFrom:Lorg/apache/jena/graph/Graph;
      14: aload_0
      15: invokestatic  #4                  // Method org/apache/jena/util/CollectionFactory.createHashedSet:()Ljava/util/Set;
      18: putfield      #5                  // Field active:Ljava/util/Set;
      21: aload_0
      22: aload_1
      23: putfield      #6                  // Field b:Lorg/apache/jena/graph/TripleBoundary;
      26: return

  public void extractInto(org.apache.jena.graph.Node);
    Code:
       0: aload_0
       1: getfield      #5                  // Field active:Ljava/util/Set;
       4: aload_1
       5: invokeinterface #7,  2            // InterfaceMethod java/util/Set.add:(Ljava/lang/Object;)Z
      10: pop
      11: aload_0
      12: getfield      #3                  // Field extractFrom:Lorg/apache/jena/graph/Graph;
      15: aload_1
      16: getstatic     #8                  // Field org/apache/jena/graph/Node.ANY:Lorg/apache/jena/graph/Node;
      19: getstatic     #8                  // Field org/apache/jena/graph/Node.ANY:Lorg/apache/jena/graph/Node;
      22: invokeinterface #9,  4            // InterfaceMethod org/apache/jena/graph/Graph.find:(Lorg/apache/jena/graph/Node;Lorg/apache/jena/graph/Node;Lorg/apache/jena/graph/Node;)Lorg/apache/jena/util/iterator/ExtendedIterator;
      27: astore_2
      28: aload_2
      29: invokeinterface #10,  1           // InterfaceMethod java/util/Iterator.hasNext:()Z
      34: ifeq          99
      37: aload_2
      38: invokeinterface #11,  1           // InterfaceMethod java/util/Iterator.next:()Ljava/lang/Object;
      43: checkcast     #12                 // class org/apache/jena/graph/Triple
      46: astore_3
      47: aload_3
      48: invokevirtual #13                 // Method org/apache/jena/graph/Triple.getObject:()Lorg/apache/jena/graph/Node;
      51: astore        4
      53: aload_0
      54: getfield      #2                  // Field toUpdate:Lorg/apache/jena/graph/Graph;
      57: aload_3
      58: invokeinterface #14,  2           // InterfaceMethod org/apache/jena/graph/Graph.add:(Lorg/apache/jena/graph/Triple;)V
      63: aload_0
      64: getfield      #5                  // Field active:Ljava/util/Set;
      67: aload         4
      69: invokeinterface #15,  2           // InterfaceMethod java/util/Set.contains:(Ljava/lang/Object;)Z
      74: ifne          96
      77: aload_0
      78: getfield      #6                  // Field b:Lorg/apache/jena/graph/TripleBoundary;
      81: aload_3
      82: invokeinterface #16,  2           // InterfaceMethod org/apache/jena/graph/TripleBoundary.stopAt:(Lorg/apache/jena/graph/Triple;)Z
      87: ifne          96
      90: aload_0
      91: aload         4
      93: invokevirtual #17                 // Method extractInto:(Lorg/apache/jena/graph/Node;)V
      96: goto          28
      99: return
}
