Compiled from "DFUArrayActionResponseWrapper.java"
public class org.hpccsystems.ws.client.wrappers.gen.wsdfu.DFUArrayActionResponseWrapper {
  protected org.hpccsystems.ws.client.wrappers.gen.wsdfu.ArrayOfEspExceptionWrapper local_exceptions;

  protected java.lang.String local_backToPage;

  protected java.lang.String local_redirectTo;

  protected org.hpccsystems.ws.client.wrappers.gen.wsdfu.ArrayOfDFUActionInfoWrapper local_actionResults;

  public org.hpccsystems.ws.client.wrappers.gen.wsdfu.DFUArrayActionResponseWrapper();
    Code:
       0: aload_0
       1: invokespecial #1                  // Method java/lang/Object."<init>":()V
       4: return

  public org.hpccsystems.ws.client.wrappers.gen.wsdfu.DFUArrayActionResponseWrapper(org.hpccsystems.ws.client.gen.axis2.wsdfu.v1_57.DFUArrayActionResponse);
    Code:
       0: aload_0
       1: invokespecial #1                  // Method java/lang/Object."<init>":()V
       4: aload_0
       5: aload_1
       6: invokespecial #2                  // Method copy:(Lorg/hpccsystems/ws/client/gen/axis2/wsdfu/v1_57/DFUArrayActionResponse;)V
       9: return

  public org.hpccsystems.ws.client.wrappers.gen.wsdfu.DFUArrayActionResponseWrapper(org.hpccsystems.ws.client.wrappers.gen.wsdfu.ArrayOfEspExceptionWrapper, java.lang.String, java.lang.String, org.hpccsystems.ws.client.wrappers.gen.wsdfu.ArrayOfDFUActionInfoWrapper);
    Code:
       0: aload_0
       1: invokespecial #1                  // Method java/lang/Object."<init>":()V
       4: aload_0
       5: aload_1
       6: putfield      #3                  // Field local_exceptions:Lorg/hpccsystems/ws/client/wrappers/gen/wsdfu/ArrayOfEspExceptionWrapper;
       9: aload_0
      10: aload_2
      11: putfield      #4                  // Field local_backToPage:Ljava/lang/String;
      14: aload_0
      15: aload_3
      16: putfield      #5                  // Field local_redirectTo:Ljava/lang/String;
      19: aload_0
      20: aload         4
      22: putfield      #6                  // Field local_actionResults:Lorg/hpccsystems/ws/client/wrappers/gen/wsdfu/ArrayOfDFUActionInfoWrapper;
      25: return

  private void copy(org.hpccsystems.ws.client.gen.axis2.wsdfu.v1_57.DFUArrayActionResponse);
    Code:
       0: aload_1
       1: ifnonnull     5
       4: return
       5: aload_1
       6: invokevirtual #7                  // Method org/hpccsystems/ws/client/gen/axis2/wsdfu/v1_57/DFUArrayActionResponse.getExceptions:()Lorg/hpccsystems/ws/client/gen/axis2/wsdfu/v1_57/ArrayOfEspException;
       9: ifnull        27
      12: aload_0
      13: new           #8                  // class org/hpccsystems/ws/client/wrappers/gen/wsdfu/ArrayOfEspExceptionWrapper
      16: dup
      17: aload_1
      18: invokevirtual #7                  // Method org/hpccsystems/ws/client/gen/axis2/wsdfu/v1_57/DFUArrayActionResponse.getExceptions:()Lorg/hpccsystems/ws/client/gen/axis2/wsdfu/v1_57/ArrayOfEspException;
      21: invokespecial #9                  // Method org/hpccsystems/ws/client/wrappers/gen/wsdfu/ArrayOfEspExceptionWrapper."<init>":(Lorg/hpccsystems/ws/client/gen/axis2/wsdfu/v1_57/ArrayOfEspException;)V
      24: putfield      #3                  // Field local_exceptions:Lorg/hpccsystems/ws/client/wrappers/gen/wsdfu/ArrayOfEspExceptionWrapper;
      27: aload_0
      28: aload_1
      29: invokevirtual #10                 // Method org/hpccsystems/ws/client/gen/axis2/wsdfu/v1_57/DFUArrayActionResponse.getBackToPage:()Ljava/lang/String;
      32: putfield      #4                  // Field local_backToPage:Ljava/lang/String;
      35: aload_0
      36: aload_1
      37: invokevirtual #11                 // Method org/hpccsystems/ws/client/gen/axis2/wsdfu/v1_57/DFUArrayActionResponse.getRedirectTo:()Ljava/lang/String;
      40: putfield      #5                  // Field local_redirectTo:Ljava/lang/String;
      43: aload_1
      44: invokevirtual #12                 // Method org/hpccsystems/ws/client/gen/axis2/wsdfu/v1_57/DFUArrayActionResponse.getActionResults:()Lorg/hpccsystems/ws/client/gen/axis2/wsdfu/v1_57/ArrayOfDFUActionInfo;
      47: ifnull        65
      50: aload_0
      51: new           #13                 // class org/hpccsystems/ws/client/wrappers/gen/wsdfu/ArrayOfDFUActionInfoWrapper
      54: dup
      55: aload_1
      56: invokevirtual #12                 // Method org/hpccsystems/ws/client/gen/axis2/wsdfu/v1_57/DFUArrayActionResponse.getActionResults:()Lorg/hpccsystems/ws/client/gen/axis2/wsdfu/v1_57/ArrayOfDFUActionInfo;
      59: invokespecial #14                 // Method org/hpccsystems/ws/client/wrappers/gen/wsdfu/ArrayOfDFUActionInfoWrapper."<init>":(Lorg/hpccsystems/ws/client/gen/axis2/wsdfu/v1_57/ArrayOfDFUActionInfo;)V
      62: putfield      #6                  // Field local_actionResults:Lorg/hpccsystems/ws/client/wrappers/gen/wsdfu/ArrayOfDFUActionInfoWrapper;
      65: return

  public java.lang.String toString();
    Code:
       0: new           #15                 // class java/lang/StringBuilder
       3: dup
       4: invokespecial #16                 // Method java/lang/StringBuilder."<init>":()V
       7: ldc           #17                 // String DFUArrayActionResponseWrapper [exceptions =
       9: invokevirtual #18                 // Method java/lang/StringBuilder.append:(Ljava/lang/String;)Ljava/lang/StringBuilder;
      12: aload_0
      13: getfield      #3                  // Field local_exceptions:Lorg/hpccsystems/ws/client/wrappers/gen/wsdfu/ArrayOfEspExceptionWrapper;
      16: invokevirtual #19                 // Method java/lang/StringBuilder.append:(Ljava/lang/Object;)Ljava/lang/StringBuilder;
      19: ldc           #20                 // String , backToPage =
      21: invokevirtual #18                 // Method java/lang/StringBuilder.append:(Ljava/lang/String;)Ljava/lang/StringBuilder;
      24: aload_0
      25: getfield      #4                  // Field local_backToPage:Ljava/lang/String;
      28: invokevirtual #18                 // Method java/lang/StringBuilder.append:(Ljava/lang/String;)Ljava/lang/StringBuilder;
      31: ldc           #21                 // String , redirectTo =
      33: invokevirtual #18                 // Method java/lang/StringBuilder.append:(Ljava/lang/String;)Ljava/lang/StringBuilder;
      36: aload_0
      37: getfield      #5                  // Field local_redirectTo:Ljava/lang/String;
      40: invokevirtual #18                 // Method java/lang/StringBuilder.append:(Ljava/lang/String;)Ljava/lang/StringBuilder;
      43: ldc           #22                 // String , actionResults =
      45: invokevirtual #18                 // Method java/lang/StringBuilder.append:(Ljava/lang/String;)Ljava/lang/StringBuilder;
      48: aload_0
      49: getfield      #6                  // Field local_actionResults:Lorg/hpccsystems/ws/client/wrappers/gen/wsdfu/ArrayOfDFUActionInfoWrapper;
      52: invokevirtual #19                 // Method java/lang/StringBuilder.append:(Ljava/lang/Object;)Ljava/lang/StringBuilder;
      55: ldc           #23                 // String ]
      57: invokevirtual #18                 // Method java/lang/StringBuilder.append:(Ljava/lang/String;)Ljava/lang/StringBuilder;
      60: invokevirtual #24                 // Method java/lang/StringBuilder.toString:()Ljava/lang/String;
      63: areturn

  public org.hpccsystems.ws.client.gen.axis2.wsdfu.v1_57.DFUArrayActionResponse getRaw();
    Code:
       0: new           #25                 // class org/hpccsystems/ws/client/gen/axis2/wsdfu/v1_57/DFUArrayActionResponse
       3: dup
       4: invokespecial #26                 // Method org/hpccsystems/ws/client/gen/axis2/wsdfu/v1_57/DFUArrayActionResponse."<init>":()V
       7: astore_1
       8: aload_1
       9: aload_0
      10: getfield      #4                  // Field local_backToPage:Ljava/lang/String;
      13: invokevirtual #27                 // Method org/hpccsystems/ws/client/gen/axis2/wsdfu/v1_57/DFUArrayActionResponse.setBackToPage:(Ljava/lang/String;)V
      16: aload_1
      17: aload_0
      18: getfield      #5                  // Field local_redirectTo:Ljava/lang/String;
      21: invokevirtual #28                 // Method org/hpccsystems/ws/client/gen/axis2/wsdfu/v1_57/DFUArrayActionResponse.setRedirectTo:(Ljava/lang/String;)V
      24: aload_1
      25: areturn

  public void setExceptions(org.hpccsystems.ws.client.wrappers.gen.wsdfu.ArrayOfEspExceptionWrapper);
    Code:
       0: aload_0
       1: aload_1
       2: putfield      #3                  // Field local_exceptions:Lorg/hpccsystems/ws/client/wrappers/gen/wsdfu/ArrayOfEspExceptionWrapper;
       5: return

  public org.hpccsystems.ws.client.wrappers.gen.wsdfu.ArrayOfEspExceptionWrapper getExceptions();
    Code:
       0: aload_0
       1: getfield      #3                  // Field local_exceptions:Lorg/hpccsystems/ws/client/wrappers/gen/wsdfu/ArrayOfEspExceptionWrapper;
       4: areturn

  public void setBackToPage(java.lang.String);
    Code:
       0: aload_0
       1: aload_1
       2: putfield      #4                  // Field local_backToPage:Ljava/lang/String;
       5: return

  public java.lang.String getBackToPage();
    Code:
       0: aload_0
       1: getfield      #4                  // Field local_backToPage:Ljava/lang/String;
       4: areturn

  public void setRedirectTo(java.lang.String);
    Code:
       0: aload_0
       1: aload_1
       2: putfield      #5                  // Field local_redirectTo:Ljava/lang/String;
       5: return

  public java.lang.String getRedirectTo();
    Code:
       0: aload_0
       1: getfield      #5                  // Field local_redirectTo:Ljava/lang/String;
       4: areturn

  public void setActionResults(org.hpccsystems.ws.client.wrappers.gen.wsdfu.ArrayOfDFUActionInfoWrapper);
    Code:
       0: aload_0
       1: aload_1
       2: putfield      #6                  // Field local_actionResults:Lorg/hpccsystems/ws/client/wrappers/gen/wsdfu/ArrayOfDFUActionInfoWrapper;
       5: return

  public org.hpccsystems.ws.client.wrappers.gen.wsdfu.ArrayOfDFUActionInfoWrapper getActionResults();
    Code:
       0: aload_0
       1: getfield      #6                  // Field local_actionResults:Lorg/hpccsystems/ws/client/wrappers/gen/wsdfu/ArrayOfDFUActionInfoWrapper;
       4: areturn
}
