Compiled from "WsDfuPingRequestWrapper.java"
public class org.hpccsystems.ws.client.wrappers.gen.wsdfu.WsDfuPingRequestWrapper {
  public org.hpccsystems.ws.client.wrappers.gen.wsdfu.WsDfuPingRequestWrapper();
    Code:
       0: aload_0
       1: invokespecial #1                  // Method java/lang/Object."<init>":()V
       4: return

  public org.hpccsystems.ws.client.gen.axis2.wsdfu.v1_57.WsDfuPingRequest getRaw();
    Code:
       0: new           #2                  // class org/hpccsystems/ws/client/gen/axis2/wsdfu/v1_57/WsDfuPingRequest
       3: dup
       4: invokespecial #3                  // Method org/hpccsystems/ws/client/gen/axis2/wsdfu/v1_57/WsDfuPingRequest."<init>":()V
       7: astore_1
       8: aload_1
       9: areturn
}
