Compiled from "DynamicType.java"
public abstract class net.bytebuddy.dynamic.DynamicType$Builder$MethodDefinition$ImplementationDefinition$AbstractBase<V> implements net.bytebuddy.dynamic.DynamicType$Builder$MethodDefinition$ImplementationDefinition<V> {
  public net.bytebuddy.dynamic.DynamicType$Builder$MethodDefinition$ImplementationDefinition$AbstractBase();
    Code:
       0: aload_0
       1: invokespecial #30                 // Method java/lang/Object."<init>":()V
       4: return

  public <W> net.bytebuddy.dynamic.DynamicType$Builder$MethodDefinition$ReceiverTypeDefinition<V> defaultValue(W, java.lang.Class<? extends W>);
    Code:
       0: aload_0
       1: aload_1
       2: aload_2
       3: invokestatic  #40                 // Method net/bytebuddy/description/annotation/AnnotationDescription$ForLoadedAnnotation.asValue:(Ljava/lang/Object;Ljava/lang/Class;)Lnet/bytebuddy/description/annotation/AnnotationValue;
       6: invokevirtual #43                 // Method defaultValue:(Lnet/bytebuddy/description/annotation/AnnotationValue;)Lnet/bytebuddy/dynamic/DynamicType$Builder$MethodDefinition$ReceiverTypeDefinition;
       9: areturn
}
