Compiled from "ForkJoinPool.java"
final class io.netty.util.internal.chmv8.ForkJoinPool$1 implements java.security.PrivilegedAction<io.netty.util.internal.chmv8.ForkJoinPool> {
  io.netty.util.internal.chmv8.ForkJoinPool$1();
    Code:
       0: aload_0
       1: invokespecial #1                  // Method java/lang/Object."<init>":()V
       4: return

  public io.netty.util.internal.chmv8.ForkJoinPool run();
    Code:
       0: invokestatic  #2                  // Method io/netty/util/internal/chmv8/ForkJoinPool.access$100:()Lio/netty/util/internal/chmv8/ForkJoinPool;
       3: areturn

  public java.lang.Object run();
    Code:
       0: aload_0
       1: invokevirtual #3                  // Method run:()Lio/netty/util/internal/chmv8/ForkJoinPool;
       4: areturn
}
