Compiled from "StateEnum.scala"
public final class zio.aws.rum.model.StateEnum$ implements scala.deriving.Mirror$Sum,java.io.Serializable {
  public static final zio.aws.rum.model.StateEnum$unknownToSdkVersion$ unknownToSdkVersion;

  public static final zio.aws.rum.model.StateEnum$CREATED$ CREATED;

  public static final zio.aws.rum.model.StateEnum$DELETING$ DELETING;

  public static final zio.aws.rum.model.StateEnum$ACTIVE$ ACTIVE;

  public static final zio.aws.rum.model.StateEnum$ MODULE$;

  private zio.aws.rum.model.StateEnum$();
    Code:
       0: aload_0
       1: invokespecial #43                 // Method java/lang/Object."<init>":()V
       4: return

  public static {};
    Code:
       0: new           #2                  // class zio/aws/rum/model/StateEnum$
       3: dup
       4: invokespecial #46                 // Method "<init>":()V
       7: putstatic     #48                 // Field MODULE$:Lzio/aws/rum/model/StateEnum$;
      10: return

  private java.lang.Object writeReplace();
    Code:
       0: new           #52                 // class scala/runtime/ModuleSerializationProxy
       3: dup
       4: ldc           #2                  // class zio/aws/rum/model/StateEnum$
       6: invokespecial #55                 // Method scala/runtime/ModuleSerializationProxy."<init>":(Ljava/lang/Class;)V
       9: areturn

  public zio.aws.rum.model.StateEnum wrap(software.amazon.awssdk.services.rum.model.StateEnum);
    Code:
       0: aload_1
       1: astore_2
       2: getstatic     #64                 // Field software/amazon/awssdk/services/rum/model/StateEnum.UNKNOWN_TO_SDK_VERSION:Lsoftware/amazon/awssdk/services/rum/model/StateEnum;
       5: aload_2
       6: astore_3
       7: dup
       8: ifnonnull     19
      11: pop
      12: aload_3
      13: ifnull        26
      16: goto          36
      19: aload_3
      20: invokevirtual #68                 // Method java/lang/Object.equals:(Ljava/lang/Object;)Z
      23: ifeq          36
      26: getstatic     #70                 // Field zio/aws/rum/model/StateEnum$unknownToSdkVersion$.MODULE$:Lzio/aws/rum/model/StateEnum$unknownToSdkVersion$;
      29: astore        4
      31: aload         4
      33: goto          156
      36: getstatic     #72                 // Field software/amazon/awssdk/services/rum/model/StateEnum.CREATED:Lsoftware/amazon/awssdk/services/rum/model/StateEnum;
      39: aload_2
      40: astore        5
      42: dup
      43: ifnonnull     55
      46: pop
      47: aload         5
      49: ifnull        63
      52: goto          73
      55: aload         5
      57: invokevirtual #68                 // Method java/lang/Object.equals:(Ljava/lang/Object;)Z
      60: ifeq          73
      63: getstatic     #74                 // Field zio/aws/rum/model/StateEnum$CREATED$.MODULE$:Lzio/aws/rum/model/StateEnum$CREATED$;
      66: astore        6
      68: aload         6
      70: goto          156
      73: getstatic     #76                 // Field software/amazon/awssdk/services/rum/model/StateEnum.DELETING:Lsoftware/amazon/awssdk/services/rum/model/StateEnum;
      76: aload_2
      77: astore        7
      79: dup
      80: ifnonnull     92
      83: pop
      84: aload         7
      86: ifnull        100
      89: goto          110
      92: aload         7
      94: invokevirtual #68                 // Method java/lang/Object.equals:(Ljava/lang/Object;)Z
      97: ifeq          110
     100: getstatic     #78                 // Field zio/aws/rum/model/StateEnum$DELETING$.MODULE$:Lzio/aws/rum/model/StateEnum$DELETING$;
     103: astore        8
     105: aload         8
     107: goto          156
     110: getstatic     #80                 // Field software/amazon/awssdk/services/rum/model/StateEnum.ACTIVE:Lsoftware/amazon/awssdk/services/rum/model/StateEnum;
     113: aload_2
     114: astore        9
     116: dup
     117: ifnonnull     129
     120: pop
     121: aload         9
     123: ifnull        137
     126: goto          147
     129: aload         9
     131: invokevirtual #68                 // Method java/lang/Object.equals:(Ljava/lang/Object;)Z
     134: ifeq          147
     137: getstatic     #82                 // Field zio/aws/rum/model/StateEnum$ACTIVE$.MODULE$:Lzio/aws/rum/model/StateEnum$ACTIVE$;
     140: astore        10
     142: aload         10
     144: goto          156
     147: new           #84                 // class scala/MatchError
     150: dup
     151: aload_2
     152: invokespecial #87                 // Method scala/MatchError."<init>":(Ljava/lang/Object;)V
     155: athrow
     156: checkcast     #19                 // class zio/aws/rum/model/StateEnum
     159: areturn

  public int ordinal(zio.aws.rum.model.StateEnum);
    Code:
       0: aload_1
       1: astore_2
       2: aload_2
       3: getstatic     #70                 // Field zio/aws/rum/model/StateEnum$unknownToSdkVersion$.MODULE$:Lzio/aws/rum/model/StateEnum$unknownToSdkVersion$;
       6: if_acmpne     13
       9: iconst_0
      10: goto          55
      13: aload_2
      14: getstatic     #74                 // Field zio/aws/rum/model/StateEnum$CREATED$.MODULE$:Lzio/aws/rum/model/StateEnum$CREATED$;
      17: if_acmpne     24
      20: iconst_1
      21: goto          55
      24: aload_2
      25: getstatic     #78                 // Field zio/aws/rum/model/StateEnum$DELETING$.MODULE$:Lzio/aws/rum/model/StateEnum$DELETING$;
      28: if_acmpne     35
      31: iconst_2
      32: goto          55
      35: aload_2
      36: getstatic     #82                 // Field zio/aws/rum/model/StateEnum$ACTIVE$.MODULE$:Lzio/aws/rum/model/StateEnum$ACTIVE$;
      39: if_acmpne     46
      42: iconst_3
      43: goto          55
      46: new           #84                 // class scala/MatchError
      49: dup
      50: aload_2
      51: invokespecial #87                 // Method scala/MatchError."<init>":(Ljava/lang/Object;)V
      54: athrow
      55: ireturn

  public int ordinal(java.lang.Object);
    Code:
       0: aload_0
       1: aload_1
       2: checkcast     #19                 // class zio/aws/rum/model/StateEnum
       5: invokevirtual #96                 // Method ordinal:(Lzio/aws/rum/model/StateEnum;)I
       8: ireturn
}
