Compiled from "TagResourceRequest.scala"
public interface zio.aws.rum.model.TagResourceRequest$ReadOnly {
  public static zio.aws.rum.model.TagResourceRequest asEditable$(zio.aws.rum.model.TagResourceRequest$ReadOnly);
    Code:
       0: aload_0
       1: invokespecial #15                 // InterfaceMethod asEditable:()Lzio/aws/rum/model/TagResourceRequest;
       4: areturn

  public default zio.aws.rum.model.TagResourceRequest asEditable();
    Code:
       0: getstatic     #22                 // Field zio/aws/rum/model/TagResourceRequest$.MODULE$:Lzio/aws/rum/model/TagResourceRequest$;
       3: aload_0
       4: invokeinterface #26,  1           // InterfaceMethod resourceArn:()Ljava/lang/String;
       9: aload_0
      10: invokeinterface #30,  1           // InterfaceMethod tags:()Lscala/collection/immutable/Map;
      15: invokevirtual #34                 // Method zio/aws/rum/model/TagResourceRequest$.apply:(Ljava/lang/String;Lscala/collection/immutable/Map;)Lzio/aws/rum/model/TagResourceRequest;
      18: areturn

  public abstract java.lang.String resourceArn();

  public abstract scala.collection.immutable.Map<java.lang.String, java.lang.String> tags();

  public static zio.ZIO getResourceArn$(zio.aws.rum.model.TagResourceRequest$ReadOnly);
    Code:
       0: aload_0
       1: invokespecial #42                 // InterfaceMethod getResourceArn:()Lzio/ZIO;
       4: areturn

  public default zio.ZIO<java.lang.Object, scala.runtime.Nothing$, java.lang.String> getResourceArn();
    Code:
       0: getstatic     #48                 // Field zio/ZIO$.MODULE$:Lzio/ZIO$;
       3: aload_0
       4: invokedynamic #67,  0             // InvokeDynamic #0:apply:(Lzio/aws/rum/model/TagResourceRequest$ReadOnly;)Lscala/Function0;
       9: ldc           #69                 // String zio.aws.rum.model.TagResourceRequest$.ReadOnly.getResourceArn.macro(TagResourceRequest.scala:38)
      11: invokevirtual #73                 // Method zio/ZIO$.succeed:(Lscala/Function0;Ljava/lang/Object;)Lzio/ZIO;
      14: areturn

  public static zio.ZIO getTags$(zio.aws.rum.model.TagResourceRequest$ReadOnly);
    Code:
       0: aload_0
       1: invokespecial #77                 // InterfaceMethod getTags:()Lzio/ZIO;
       4: areturn

  public default zio.ZIO<java.lang.Object, scala.runtime.Nothing$, scala.collection.immutable.Map<java.lang.String, java.lang.String>> getTags();
    Code:
       0: getstatic     #48                 // Field zio/ZIO$.MODULE$:Lzio/ZIO$;
       3: aload_0
       4: invokedynamic #84,  0             // InvokeDynamic #1:apply:(Lzio/aws/rum/model/TagResourceRequest$ReadOnly;)Lscala/Function0;
       9: ldc           #86                 // String zio.aws.rum.model.TagResourceRequest$.ReadOnly.getTags.macro(TagResourceRequest.scala:39)
      11: invokevirtual #73                 // Method zio/ZIO$.succeed:(Lscala/Function0;Ljava/lang/Object;)Lzio/ZIO;
      14: areturn

  private java.lang.String getResourceArn$$anonfun$1();
    Code:
       0: aload_0
       1: invokeinterface #26,  1           // InterfaceMethod resourceArn:()Ljava/lang/String;
       6: areturn

  private scala.collection.immutable.Map getTags$$anonfun$1();
    Code:
       0: aload_0
       1: invokeinterface #30,  1           // InterfaceMethod tags:()Lscala/collection/immutable/Map;
       6: areturn

  private static java.lang.Object $deserializeLambda$(java.lang.invoke.SerializedLambda);
    Code:
       0: aload_0
       1: invokedynamic #98,  0             // InvokeDynamic #2:lambdaDeserialize:(Ljava/lang/invoke/SerializedLambda;)Ljava/lang/Object;
       6: areturn
}
