Compiled from "RestRequest.scala"
public final class io.udash.rest.raw.HttpMethod extends com.avsystem.commons.misc.AbstractValueEnum {
  public static io.udash.rest.raw.HttpMethod PATCH();
    Code:
       0: getstatic     #16                 // Field io/udash/rest/raw/HttpMethod$.MODULE$:Lio/udash/rest/raw/HttpMethod$;
       3: invokevirtual #18                 // Method io/udash/rest/raw/HttpMethod$.PATCH:()Lio/udash/rest/raw/HttpMethod;
       6: areturn

  public static io.udash.rest.raw.HttpMethod TRACE();
    Code:
       0: getstatic     #16                 // Field io/udash/rest/raw/HttpMethod$.MODULE$:Lio/udash/rest/raw/HttpMethod$;
       3: invokevirtual #21                 // Method io/udash/rest/raw/HttpMethod$.TRACE:()Lio/udash/rest/raw/HttpMethod;
       6: areturn

  public static io.udash.rest.raw.HttpMethod OPTIONS();
    Code:
       0: getstatic     #16                 // Field io/udash/rest/raw/HttpMethod$.MODULE$:Lio/udash/rest/raw/HttpMethod$;
       3: invokevirtual #24                 // Method io/udash/rest/raw/HttpMethod$.OPTIONS:()Lio/udash/rest/raw/HttpMethod;
       6: areturn

  public static io.udash.rest.raw.HttpMethod CONNECT();
    Code:
       0: getstatic     #16                 // Field io/udash/rest/raw/HttpMethod$.MODULE$:Lio/udash/rest/raw/HttpMethod$;
       3: invokevirtual #27                 // Method io/udash/rest/raw/HttpMethod$.CONNECT:()Lio/udash/rest/raw/HttpMethod;
       6: areturn

  public static io.udash.rest.raw.HttpMethod DELETE();
    Code:
       0: getstatic     #16                 // Field io/udash/rest/raw/HttpMethod$.MODULE$:Lio/udash/rest/raw/HttpMethod$;
       3: invokevirtual #30                 // Method io/udash/rest/raw/HttpMethod$.DELETE:()Lio/udash/rest/raw/HttpMethod;
       6: areturn

  public static io.udash.rest.raw.HttpMethod PUT();
    Code:
       0: getstatic     #16                 // Field io/udash/rest/raw/HttpMethod$.MODULE$:Lio/udash/rest/raw/HttpMethod$;
       3: invokevirtual #33                 // Method io/udash/rest/raw/HttpMethod$.PUT:()Lio/udash/rest/raw/HttpMethod;
       6: areturn

  public static io.udash.rest.raw.HttpMethod POST();
    Code:
       0: getstatic     #16                 // Field io/udash/rest/raw/HttpMethod$.MODULE$:Lio/udash/rest/raw/HttpMethod$;
       3: invokevirtual #36                 // Method io/udash/rest/raw/HttpMethod$.POST:()Lio/udash/rest/raw/HttpMethod;
       6: areturn

  public static io.udash.rest.raw.HttpMethod HEAD();
    Code:
       0: getstatic     #16                 // Field io/udash/rest/raw/HttpMethod$.MODULE$:Lio/udash/rest/raw/HttpMethod$;
       3: invokevirtual #39                 // Method io/udash/rest/raw/HttpMethod$.HEAD:()Lio/udash/rest/raw/HttpMethod;
       6: areturn

  public static io.udash.rest.raw.HttpMethod GET();
    Code:
       0: getstatic     #16                 // Field io/udash/rest/raw/HttpMethod$.MODULE$:Lio/udash/rest/raw/HttpMethod$;
       3: invokevirtual #42                 // Method io/udash/rest/raw/HttpMethod$.GET:()Lio/udash/rest/raw/HttpMethod;
       6: areturn

  public static scala.math.Ordered ordered(com.avsystem.commons.misc.ValueEnum);
    Code:
       0: getstatic     #16                 // Field io/udash/rest/raw/HttpMethod$.MODULE$:Lio/udash/rest/raw/HttpMethod$;
       3: aload_0
       4: invokevirtual #47                 // Method io/udash/rest/raw/HttpMethod$.ordered:(Lcom/avsystem/commons/misc/ValueEnum;)Lscala/math/Ordered;
       7: areturn

  public static scala.math.Ordering<io.udash.rest.raw.HttpMethod> ordering();
    Code:
       0: getstatic     #16                 // Field io/udash/rest/raw/HttpMethod$.MODULE$:Lio/udash/rest/raw/HttpMethod$;
       3: invokevirtual #52                 // Method io/udash/rest/raw/HttpMethod$.ordering:()Lscala/math/Ordering;
       6: areturn

  public static scala.collection.immutable.IndexedSeq<io.udash.rest.raw.HttpMethod> values();
    Code:
       0: getstatic     #16                 // Field io/udash/rest/raw/HttpMethod$.MODULE$:Lio/udash/rest/raw/HttpMethod$;
       3: invokevirtual #57                 // Method io/udash/rest/raw/HttpMethod$.values:()Lscala/collection/immutable/IndexedSeq;
       6: areturn

  public static com.avsystem.commons.serialization.GenCodec<io.udash.rest.raw.HttpMethod> codec();
    Code:
       0: getstatic     #16                 // Field io/udash/rest/raw/HttpMethod$.MODULE$:Lio/udash/rest/raw/HttpMethod$;
       3: invokevirtual #62                 // Method io/udash/rest/raw/HttpMethod$.codec:()Lcom/avsystem/commons/serialization/GenCodec;
       6: areturn

  public static com.avsystem.commons.serialization.GenKeyCodec<io.udash.rest.raw.HttpMethod> keyCodec();
    Code:
       0: getstatic     #16                 // Field io/udash/rest/raw/HttpMethod$.MODULE$:Lio/udash/rest/raw/HttpMethod$;
       3: invokevirtual #67                 // Method io/udash/rest/raw/HttpMethod$.keyCodec:()Lcom/avsystem/commons/serialization/GenKeyCodec;
       6: areturn

  public static scala.collection.immutable.Map<java.lang.String, io.udash.rest.raw.HttpMethod> byName();
    Code:
       0: getstatic     #16                 // Field io/udash/rest/raw/HttpMethod$.MODULE$:Lio/udash/rest/raw/HttpMethod$;
       3: invokevirtual #72                 // Method io/udash/rest/raw/HttpMethod$.byName:()Lscala/collection/immutable/Map;
       6: areturn

  public static com.avsystem.commons.misc.SealedEnumCompanion evidence();
    Code:
       0: getstatic     #16                 // Field io/udash/rest/raw/HttpMethod$.MODULE$:Lio/udash/rest/raw/HttpMethod$;
       3: invokevirtual #76                 // Method io/udash/rest/raw/HttpMethod$.evidence:()Lcom/avsystem/commons/misc/SealedEnumCompanion;
       6: areturn

  public io.udash.rest.raw.HttpMethod(com.avsystem.commons.misc.EnumCtx);
    Code:
       0: aload_0
       1: aload_1
       2: invokespecial #81                 // Method com/avsystem/commons/misc/AbstractValueEnum."<init>":(Lcom/avsystem/commons/misc/EnumCtx;)V
       5: return
}
