Compiled from "RestMetadata.scala"
public final class io.udash.rest.raw.PathParamMetadata<T> implements com.avsystem.commons.meta.TypedMetadata<T>, scala.Product, scala.Serializable {
  private final java.lang.String name;

  private final io.udash.rest.Path pathAnnot;

  private final scala.collection.immutable.List<io.udash.rest.raw.PlainValue> pathSuffix;

  public static <T> scala.Option<scala.Tuple2<java.lang.String, io.udash.rest.Path>> unapply(io.udash.rest.raw.PathParamMetadata<T>);
    Code:
       0: getstatic     #32                 // Field io/udash/rest/raw/PathParamMetadata$.MODULE$:Lio/udash/rest/raw/PathParamMetadata$;
       3: aload_0
       4: invokevirtual #34                 // Method io/udash/rest/raw/PathParamMetadata$.unapply:(Lio/udash/rest/raw/PathParamMetadata;)Lscala/Option;
       7: areturn

  public static <T> io.udash.rest.raw.PathParamMetadata<T> apply(java.lang.String, io.udash.rest.Path);
    Code:
       0: getstatic     #32                 // Field io/udash/rest/raw/PathParamMetadata$.MODULE$:Lio/udash/rest/raw/PathParamMetadata$;
       3: aload_0
       4: aload_1
       5: invokevirtual #39                 // Method io/udash/rest/raw/PathParamMetadata$.apply:(Ljava/lang/String;Lio/udash/rest/Path;)Lio/udash/rest/raw/PathParamMetadata;
       8: areturn

  public java.lang.String name();
    Code:
       0: aload_0
       1: getfield      #42                 // Field name:Ljava/lang/String;
       4: areturn

  public io.udash.rest.Path pathAnnot();
    Code:
       0: aload_0
       1: getfield      #47                 // Field pathAnnot:Lio/udash/rest/Path;
       4: areturn

  public scala.collection.immutable.List<io.udash.rest.raw.PlainValue> pathSuffix();
    Code:
       0: aload_0
       1: getfield      #51                 // Field pathSuffix:Lscala/collection/immutable/List;
       4: areturn

  public <T> io.udash.rest.raw.PathParamMetadata<T> copy(java.lang.String, io.udash.rest.Path);
    Code:
       0: new           #2                  // class io/udash/rest/raw/PathParamMetadata
       3: dup
       4: aload_1
       5: aload_2
       6: invokespecial #56                 // Method "<init>":(Ljava/lang/String;Lio/udash/rest/Path;)V
       9: areturn

  public <T> java.lang.String copy$default$1();
    Code:
       0: aload_0
       1: invokevirtual #60                 // Method name:()Ljava/lang/String;
       4: areturn

  public <T> io.udash.rest.Path copy$default$2();
    Code:
       0: aload_0
       1: invokevirtual #64                 // Method pathAnnot:()Lio/udash/rest/Path;
       4: areturn

  public java.lang.String productPrefix();
    Code:
       0: ldc           #67                 // String PathParamMetadata
       2: areturn

  public int productArity();
    Code:
       0: iconst_2
       1: ireturn

  public java.lang.Object productElement(int);
    Code:
       0: iload_1
       1: istore_2
       2: iload_2
       3: tableswitch   { // 0 to 1
                     0: 24
                     1: 31
               default: 38
          }
      24: aload_0
      25: invokevirtual #60                 // Method name:()Ljava/lang/String;
      28: goto          50
      31: aload_0
      32: invokevirtual #64                 // Method pathAnnot:()Lio/udash/rest/Path;
      35: goto          50
      38: new           #74                 // class java/lang/IndexOutOfBoundsException
      41: dup
      42: iload_1
      43: invokestatic  #80                 // Method java/lang/Integer.toString:(I)Ljava/lang/String;
      46: invokespecial #83                 // Method java/lang/IndexOutOfBoundsException."<init>":(Ljava/lang/String;)V
      49: athrow
      50: areturn

  public scala.collection.Iterator<java.lang.Object> productIterator();
    Code:
       0: getstatic     #92                 // Field scala/runtime/ScalaRunTime$.MODULE$:Lscala/runtime/ScalaRunTime$;
       3: aload_0
       4: invokevirtual #96                 // Method scala/runtime/ScalaRunTime$.typedProductIterator:(Lscala/Product;)Lscala/collection/Iterator;
       7: areturn

  public boolean canEqual(java.lang.Object);
    Code:
       0: aload_1
       1: instanceof    #2                  // class io/udash/rest/raw/PathParamMetadata
       4: ireturn

  public int hashCode();
    Code:
       0: getstatic     #92                 // Field scala/runtime/ScalaRunTime$.MODULE$:Lscala/runtime/ScalaRunTime$;
       3: aload_0
       4: invokevirtual #104                // Method scala/runtime/ScalaRunTime$._hashCode:(Lscala/Product;)I
       7: ireturn

  public java.lang.String toString();
    Code:
       0: getstatic     #92                 // Field scala/runtime/ScalaRunTime$.MODULE$:Lscala/runtime/ScalaRunTime$;
       3: aload_0
       4: invokevirtual #108                // Method scala/runtime/ScalaRunTime$._toString:(Lscala/Product;)Ljava/lang/String;
       7: areturn

  public boolean equals(java.lang.Object);
    Code:
       0: aload_0
       1: aload_1
       2: if_acmpeq     109
       5: aload_1
       6: astore_3
       7: aload_3
       8: instanceof    #2                  // class io/udash/rest/raw/PathParamMetadata
      11: ifeq          19
      14: iconst_1
      15: istore_2
      16: goto          27
      19: goto          22
      22: iconst_0
      23: istore_2
      24: goto          27
      27: iload_2
      28: ifeq          113
      31: aload_1
      32: checkcast     #2                  // class io/udash/rest/raw/PathParamMetadata
      35: astore        4
      37: aload_0
      38: invokevirtual #60                 // Method name:()Ljava/lang/String;
      41: aload         4
      43: invokevirtual #60                 // Method name:()Ljava/lang/String;
      46: astore        5
      48: dup
      49: ifnonnull     61
      52: pop
      53: aload         5
      55: ifnull        69
      58: goto          105
      61: aload         5
      63: invokevirtual #111                // Method java/lang/Object.equals:(Ljava/lang/Object;)Z
      66: ifeq          105
      69: aload_0
      70: invokevirtual #64                 // Method pathAnnot:()Lio/udash/rest/Path;
      73: aload         4
      75: invokevirtual #64                 // Method pathAnnot:()Lio/udash/rest/Path;
      78: astore        6
      80: dup
      81: ifnonnull     93
      84: pop
      85: aload         6
      87: ifnull        101
      90: goto          105
      93: aload         6
      95: invokevirtual #111                // Method java/lang/Object.equals:(Ljava/lang/Object;)Z
      98: ifeq          105
     101: iconst_1
     102: goto          106
     105: iconst_0
     106: ifeq          113
     109: iconst_1
     110: goto          114
     113: iconst_0
     114: ireturn

  public io.udash.rest.raw.PathParamMetadata(java.lang.String, io.udash.rest.Path);
    Code:
       0: aload_0
       1: aload_1
       2: putfield      #42                 // Field name:Ljava/lang/String;
       5: aload_0
       6: aload_2
       7: putfield      #47                 // Field pathAnnot:Lio/udash/rest/Path;
      10: aload_0
      11: invokespecial #118                // Method java/lang/Object."<init>":()V
      14: aload_0
      15: invokestatic  #122                // InterfaceMethod scala/Product.$init$:(Lscala/Product;)V
      18: aload_0
      19: getstatic     #127                // Field io/udash/rest/raw/PlainValue$.MODULE$:Lio/udash/rest/raw/PlainValue$;
      22: aload_2
      23: invokevirtual #129                // Method io/udash/rest/Path.pathSuffix:()Ljava/lang/String;
      26: invokevirtual #133                // Method io/udash/rest/raw/PlainValue$.decodePath:(Ljava/lang/String;)Lscala/collection/immutable/List;
      29: putfield      #51                 // Field pathSuffix:Lscala/collection/immutable/List;
      32: return
}
