Compiled from "JWSAlgorithm.java"
public final class com.nimbusds.jose.JWSAlgorithm$Family extends com.nimbusds.jose.AlgorithmFamily<com.nimbusds.jose.JWSAlgorithm> {
  private static final long serialVersionUID;

  public static final com.nimbusds.jose.JWSAlgorithm$Family HMAC_SHA;

  public static final com.nimbusds.jose.JWSAlgorithm$Family RSA;

  public static final com.nimbusds.jose.JWSAlgorithm$Family EC;

  public static final com.nimbusds.jose.JWSAlgorithm$Family ED;

  public static final com.nimbusds.jose.JWSAlgorithm$Family SIGNATURE;

  public com.nimbusds.jose.JWSAlgorithm$Family(com.nimbusds.jose.JWSAlgorithm...);
    Code:
       0: aload_0
       1: aload_1
       2: invokespecial #24                 // Method com/nimbusds/jose/AlgorithmFamily."<init>":([Lcom/nimbusds/jose/Algorithm;)V
       5: return

  public boolean retainAll(java.util.Collection);
    Code:
       0: aload_0
       1: aload_1
       2: invokespecial #31                 // Method com/nimbusds/jose/AlgorithmFamily.retainAll:(Ljava/util/Collection;)Z
       5: ireturn

  public boolean removeAll(java.util.Collection);
    Code:
       0: aload_0
       1: aload_1
       2: invokespecial #34                 // Method com/nimbusds/jose/AlgorithmFamily.removeAll:(Ljava/util/Collection;)Z
       5: ireturn

  public boolean remove(java.lang.Object);
    Code:
       0: aload_0
       1: aload_1
       2: invokespecial #38                 // Method com/nimbusds/jose/AlgorithmFamily.remove:(Ljava/lang/Object;)Z
       5: ireturn

  public boolean addAll(java.util.Collection);
    Code:
       0: aload_0
       1: aload_1
       2: invokespecial #41                 // Method com/nimbusds/jose/AlgorithmFamily.addAll:(Ljava/util/Collection;)Z
       5: ireturn

  static {};
    Code:
       0: new           #2                  // class com/nimbusds/jose/JWSAlgorithm$Family
       3: dup
       4: iconst_3
       5: anewarray     #8                  // class com/nimbusds/jose/JWSAlgorithm
       8: dup
       9: iconst_0
      10: getstatic     #47                 // Field com/nimbusds/jose/JWSAlgorithm.HS256:Lcom/nimbusds/jose/JWSAlgorithm;
      13: aastore
      14: dup
      15: iconst_1
      16: getstatic     #50                 // Field com/nimbusds/jose/JWSAlgorithm.HS384:Lcom/nimbusds/jose/JWSAlgorithm;
      19: aastore
      20: dup
      21: iconst_2
      22: getstatic     #53                 // Field com/nimbusds/jose/JWSAlgorithm.HS512:Lcom/nimbusds/jose/JWSAlgorithm;
      25: aastore
      26: invokespecial #55                 // Method "<init>":([Lcom/nimbusds/jose/JWSAlgorithm;)V
      29: putstatic     #57                 // Field HMAC_SHA:Lcom/nimbusds/jose/JWSAlgorithm$Family;
      32: new           #2                  // class com/nimbusds/jose/JWSAlgorithm$Family
      35: dup
      36: bipush        6
      38: anewarray     #8                  // class com/nimbusds/jose/JWSAlgorithm
      41: dup
      42: iconst_0
      43: getstatic     #60                 // Field com/nimbusds/jose/JWSAlgorithm.RS256:Lcom/nimbusds/jose/JWSAlgorithm;
      46: aastore
      47: dup
      48: iconst_1
      49: getstatic     #63                 // Field com/nimbusds/jose/JWSAlgorithm.RS384:Lcom/nimbusds/jose/JWSAlgorithm;
      52: aastore
      53: dup
      54: iconst_2
      55: getstatic     #66                 // Field com/nimbusds/jose/JWSAlgorithm.RS512:Lcom/nimbusds/jose/JWSAlgorithm;
      58: aastore
      59: dup
      60: iconst_3
      61: getstatic     #69                 // Field com/nimbusds/jose/JWSAlgorithm.PS256:Lcom/nimbusds/jose/JWSAlgorithm;
      64: aastore
      65: dup
      66: iconst_4
      67: getstatic     #72                 // Field com/nimbusds/jose/JWSAlgorithm.PS384:Lcom/nimbusds/jose/JWSAlgorithm;
      70: aastore
      71: dup
      72: iconst_5
      73: getstatic     #75                 // Field com/nimbusds/jose/JWSAlgorithm.PS512:Lcom/nimbusds/jose/JWSAlgorithm;
      76: aastore
      77: invokespecial #55                 // Method "<init>":([Lcom/nimbusds/jose/JWSAlgorithm;)V
      80: putstatic     #77                 // Field RSA:Lcom/nimbusds/jose/JWSAlgorithm$Family;
      83: new           #2                  // class com/nimbusds/jose/JWSAlgorithm$Family
      86: dup
      87: iconst_4
      88: anewarray     #8                  // class com/nimbusds/jose/JWSAlgorithm
      91: dup
      92: iconst_0
      93: getstatic     #80                 // Field com/nimbusds/jose/JWSAlgorithm.ES256:Lcom/nimbusds/jose/JWSAlgorithm;
      96: aastore
      97: dup
      98: iconst_1
      99: getstatic     #83                 // Field com/nimbusds/jose/JWSAlgorithm.ES256K:Lcom/nimbusds/jose/JWSAlgorithm;
     102: aastore
     103: dup
     104: iconst_2
     105: getstatic     #86                 // Field com/nimbusds/jose/JWSAlgorithm.ES384:Lcom/nimbusds/jose/JWSAlgorithm;
     108: aastore
     109: dup
     110: iconst_3
     111: getstatic     #89                 // Field com/nimbusds/jose/JWSAlgorithm.ES512:Lcom/nimbusds/jose/JWSAlgorithm;
     114: aastore
     115: invokespecial #55                 // Method "<init>":([Lcom/nimbusds/jose/JWSAlgorithm;)V
     118: putstatic     #91                 // Field EC:Lcom/nimbusds/jose/JWSAlgorithm$Family;
     121: new           #2                  // class com/nimbusds/jose/JWSAlgorithm$Family
     124: dup
     125: iconst_1
     126: anewarray     #8                  // class com/nimbusds/jose/JWSAlgorithm
     129: dup
     130: iconst_0
     131: getstatic     #94                 // Field com/nimbusds/jose/JWSAlgorithm.EdDSA:Lcom/nimbusds/jose/JWSAlgorithm;
     134: aastore
     135: invokespecial #55                 // Method "<init>":([Lcom/nimbusds/jose/JWSAlgorithm;)V
     138: putstatic     #96                 // Field ED:Lcom/nimbusds/jose/JWSAlgorithm$Family;
     141: new           #2                  // class com/nimbusds/jose/JWSAlgorithm$Family
     144: dup
     145: getstatic     #77                 // Field RSA:Lcom/nimbusds/jose/JWSAlgorithm$Family;
     148: iconst_0
     149: anewarray     #8                  // class com/nimbusds/jose/JWSAlgorithm
     152: invokevirtual #100                // Method toArray:([Ljava/lang/Object;)[Ljava/lang/Object;
     155: iconst_2
     156: anewarray     #101                // class "[Lcom/nimbusds/jose/JWSAlgorithm;"
     159: dup
     160: iconst_0
     161: getstatic     #91                 // Field EC:Lcom/nimbusds/jose/JWSAlgorithm$Family;
     164: iconst_0
     165: anewarray     #8                  // class com/nimbusds/jose/JWSAlgorithm
     168: invokevirtual #100                // Method toArray:([Ljava/lang/Object;)[Ljava/lang/Object;
     171: checkcast     #101                // class "[Lcom/nimbusds/jose/JWSAlgorithm;"
     174: aastore
     175: dup
     176: iconst_1
     177: getstatic     #96                 // Field ED:Lcom/nimbusds/jose/JWSAlgorithm$Family;
     180: iconst_0
     181: anewarray     #8                  // class com/nimbusds/jose/JWSAlgorithm
     184: invokevirtual #100                // Method toArray:([Ljava/lang/Object;)[Ljava/lang/Object;
     187: checkcast     #101                // class "[Lcom/nimbusds/jose/JWSAlgorithm;"
     190: aastore
     191: invokestatic  #107                // Method com/nimbusds/jose/util/ArrayUtils.concat:([Ljava/lang/Object;[[Ljava/lang/Object;)[Ljava/lang/Object;
     194: checkcast     #101                // class "[Lcom/nimbusds/jose/JWSAlgorithm;"
     197: invokespecial #55                 // Method "<init>":([Lcom/nimbusds/jose/JWSAlgorithm;)V
     200: putstatic     #109                // Field SIGNATURE:Lcom/nimbusds/jose/JWSAlgorithm$Family;
     203: return
}
