Compiled from "ActivityTaskScheduledEventAttributes.java"
final class software.amazon.awssdk.services.swf.model.ActivityTaskScheduledEventAttributes$BuilderImpl implements software.amazon.awssdk.services.swf.model.ActivityTaskScheduledEventAttributes$Builder {
  private software.amazon.awssdk.services.swf.model.ActivityType activityType;

  private java.lang.String activityId;

  private java.lang.String input;

  private java.lang.String control;

  private java.lang.String scheduleToStartTimeout;

  private java.lang.String scheduleToCloseTimeout;

  private java.lang.String startToCloseTimeout;

  private software.amazon.awssdk.services.swf.model.TaskList taskList;

  private java.lang.String taskPriority;

  private java.lang.Long decisionTaskCompletedEventId;

  private java.lang.String heartbeatTimeout;

  private software.amazon.awssdk.services.swf.model.ActivityTaskScheduledEventAttributes$BuilderImpl();
    Code:
       0: aload_0
       1: invokespecial #14                 // Method java/lang/Object."<init>":()V
       4: return

  private software.amazon.awssdk.services.swf.model.ActivityTaskScheduledEventAttributes$BuilderImpl(software.amazon.awssdk.services.swf.model.ActivityTaskScheduledEventAttributes);
    Code:
       0: aload_0
       1: invokespecial #14                 // Method java/lang/Object."<init>":()V
       4: aload_0
       5: aload_1
       6: invokestatic  #15                 // Method software/amazon/awssdk/services/swf/model/ActivityTaskScheduledEventAttributes.access$1300:(Lsoftware/amazon/awssdk/services/swf/model/ActivityTaskScheduledEventAttributes;)Lsoftware/amazon/awssdk/services/swf/model/ActivityType;
       9: invokevirtual #16                 // Method activityType:(Lsoftware/amazon/awssdk/services/swf/model/ActivityType;)Lsoftware/amazon/awssdk/services/swf/model/ActivityTaskScheduledEventAttributes$Builder;
      12: pop
      13: aload_0
      14: aload_1
      15: invokestatic  #17                 // Method software/amazon/awssdk/services/swf/model/ActivityTaskScheduledEventAttributes.access$1400:(Lsoftware/amazon/awssdk/services/swf/model/ActivityTaskScheduledEventAttributes;)Ljava/lang/String;
      18: invokevirtual #18                 // Method activityId:(Ljava/lang/String;)Lsoftware/amazon/awssdk/services/swf/model/ActivityTaskScheduledEventAttributes$Builder;
      21: pop
      22: aload_0
      23: aload_1
      24: invokestatic  #19                 // Method software/amazon/awssdk/services/swf/model/ActivityTaskScheduledEventAttributes.access$1500:(Lsoftware/amazon/awssdk/services/swf/model/ActivityTaskScheduledEventAttributes;)Ljava/lang/String;
      27: invokevirtual #20                 // Method input:(Ljava/lang/String;)Lsoftware/amazon/awssdk/services/swf/model/ActivityTaskScheduledEventAttributes$Builder;
      30: pop
      31: aload_0
      32: aload_1
      33: invokestatic  #21                 // Method software/amazon/awssdk/services/swf/model/ActivityTaskScheduledEventAttributes.access$1600:(Lsoftware/amazon/awssdk/services/swf/model/ActivityTaskScheduledEventAttributes;)Ljava/lang/String;
      36: invokevirtual #22                 // Method control:(Ljava/lang/String;)Lsoftware/amazon/awssdk/services/swf/model/ActivityTaskScheduledEventAttributes$Builder;
      39: pop
      40: aload_0
      41: aload_1
      42: invokestatic  #23                 // Method software/amazon/awssdk/services/swf/model/ActivityTaskScheduledEventAttributes.access$1700:(Lsoftware/amazon/awssdk/services/swf/model/ActivityTaskScheduledEventAttributes;)Ljava/lang/String;
      45: invokevirtual #24                 // Method scheduleToStartTimeout:(Ljava/lang/String;)Lsoftware/amazon/awssdk/services/swf/model/ActivityTaskScheduledEventAttributes$Builder;
      48: pop
      49: aload_0
      50: aload_1
      51: invokestatic  #25                 // Method software/amazon/awssdk/services/swf/model/ActivityTaskScheduledEventAttributes.access$1800:(Lsoftware/amazon/awssdk/services/swf/model/ActivityTaskScheduledEventAttributes;)Ljava/lang/String;
      54: invokevirtual #26                 // Method scheduleToCloseTimeout:(Ljava/lang/String;)Lsoftware/amazon/awssdk/services/swf/model/ActivityTaskScheduledEventAttributes$Builder;
      57: pop
      58: aload_0
      59: aload_1
      60: invokestatic  #27                 // Method software/amazon/awssdk/services/swf/model/ActivityTaskScheduledEventAttributes.access$1900:(Lsoftware/amazon/awssdk/services/swf/model/ActivityTaskScheduledEventAttributes;)Ljava/lang/String;
      63: invokevirtual #28                 // Method startToCloseTimeout:(Ljava/lang/String;)Lsoftware/amazon/awssdk/services/swf/model/ActivityTaskScheduledEventAttributes$Builder;
      66: pop
      67: aload_0
      68: aload_1
      69: invokestatic  #29                 // Method software/amazon/awssdk/services/swf/model/ActivityTaskScheduledEventAttributes.access$2000:(Lsoftware/amazon/awssdk/services/swf/model/ActivityTaskScheduledEventAttributes;)Lsoftware/amazon/awssdk/services/swf/model/TaskList;
      72: invokevirtual #30                 // Method taskList:(Lsoftware/amazon/awssdk/services/swf/model/TaskList;)Lsoftware/amazon/awssdk/services/swf/model/ActivityTaskScheduledEventAttributes$Builder;
      75: pop
      76: aload_0
      77: aload_1
      78: invokestatic  #31                 // Method software/amazon/awssdk/services/swf/model/ActivityTaskScheduledEventAttributes.access$2100:(Lsoftware/amazon/awssdk/services/swf/model/ActivityTaskScheduledEventAttributes;)Ljava/lang/String;
      81: invokevirtual #32                 // Method taskPriority:(Ljava/lang/String;)Lsoftware/amazon/awssdk/services/swf/model/ActivityTaskScheduledEventAttributes$Builder;
      84: pop
      85: aload_0
      86: aload_1
      87: invokestatic  #33                 // Method software/amazon/awssdk/services/swf/model/ActivityTaskScheduledEventAttributes.access$2200:(Lsoftware/amazon/awssdk/services/swf/model/ActivityTaskScheduledEventAttributes;)Ljava/lang/Long;
      90: invokevirtual #34                 // Method decisionTaskCompletedEventId:(Ljava/lang/Long;)Lsoftware/amazon/awssdk/services/swf/model/ActivityTaskScheduledEventAttributes$Builder;
      93: pop
      94: aload_0
      95: aload_1
      96: invokestatic  #35                 // Method software/amazon/awssdk/services/swf/model/ActivityTaskScheduledEventAttributes.access$2300:(Lsoftware/amazon/awssdk/services/swf/model/ActivityTaskScheduledEventAttributes;)Ljava/lang/String;
      99: invokevirtual #36                 // Method heartbeatTimeout:(Ljava/lang/String;)Lsoftware/amazon/awssdk/services/swf/model/ActivityTaskScheduledEventAttributes$Builder;
     102: pop
     103: return

  public final software.amazon.awssdk.services.swf.model.ActivityType$Builder getActivityType();
    Code:
       0: aload_0
       1: getfield      #13                 // Field activityType:Lsoftware/amazon/awssdk/services/swf/model/ActivityType;
       4: ifnull        17
       7: aload_0
       8: getfield      #13                 // Field activityType:Lsoftware/amazon/awssdk/services/swf/model/ActivityType;
      11: invokevirtual #37                 // Method software/amazon/awssdk/services/swf/model/ActivityType.toBuilder:()Lsoftware/amazon/awssdk/services/swf/model/ActivityType$Builder;
      14: goto          18
      17: aconst_null
      18: areturn

  public final software.amazon.awssdk.services.swf.model.ActivityTaskScheduledEventAttributes$Builder activityType(software.amazon.awssdk.services.swf.model.ActivityType);
    Code:
       0: aload_0
       1: aload_1
       2: putfield      #13                 // Field activityType:Lsoftware/amazon/awssdk/services/swf/model/ActivityType;
       5: aload_0
       6: areturn

  public final void setActivityType(software.amazon.awssdk.services.swf.model.ActivityType$BuilderImpl);
    Code:
       0: aload_0
       1: aload_1
       2: ifnull        12
       5: aload_1
       6: invokevirtual #38                 // Method software/amazon/awssdk/services/swf/model/ActivityType$BuilderImpl.build:()Lsoftware/amazon/awssdk/services/swf/model/ActivityType;
       9: goto          13
      12: aconst_null
      13: putfield      #13                 // Field activityType:Lsoftware/amazon/awssdk/services/swf/model/ActivityType;
      16: return

  public final java.lang.String getActivityId();
    Code:
       0: aload_0
       1: getfield      #12                 // Field activityId:Ljava/lang/String;
       4: areturn

  public final software.amazon.awssdk.services.swf.model.ActivityTaskScheduledEventAttributes$Builder activityId(java.lang.String);
    Code:
       0: aload_0
       1: aload_1
       2: putfield      #12                 // Field activityId:Ljava/lang/String;
       5: aload_0
       6: areturn

  public final void setActivityId(java.lang.String);
    Code:
       0: aload_0
       1: aload_1
       2: putfield      #12                 // Field activityId:Ljava/lang/String;
       5: return

  public final java.lang.String getInput();
    Code:
       0: aload_0
       1: getfield      #11                 // Field input:Ljava/lang/String;
       4: areturn

  public final software.amazon.awssdk.services.swf.model.ActivityTaskScheduledEventAttributes$Builder input(java.lang.String);
    Code:
       0: aload_0
       1: aload_1
       2: putfield      #11                 // Field input:Ljava/lang/String;
       5: aload_0
       6: areturn

  public final void setInput(java.lang.String);
    Code:
       0: aload_0
       1: aload_1
       2: putfield      #11                 // Field input:Ljava/lang/String;
       5: return

  public final java.lang.String getControl();
    Code:
       0: aload_0
       1: getfield      #10                 // Field control:Ljava/lang/String;
       4: areturn

  public final software.amazon.awssdk.services.swf.model.ActivityTaskScheduledEventAttributes$Builder control(java.lang.String);
    Code:
       0: aload_0
       1: aload_1
       2: putfield      #10                 // Field control:Ljava/lang/String;
       5: aload_0
       6: areturn

  public final void setControl(java.lang.String);
    Code:
       0: aload_0
       1: aload_1
       2: putfield      #10                 // Field control:Ljava/lang/String;
       5: return

  public final java.lang.String getScheduleToStartTimeout();
    Code:
       0: aload_0
       1: getfield      #9                  // Field scheduleToStartTimeout:Ljava/lang/String;
       4: areturn

  public final software.amazon.awssdk.services.swf.model.ActivityTaskScheduledEventAttributes$Builder scheduleToStartTimeout(java.lang.String);
    Code:
       0: aload_0
       1: aload_1
       2: putfield      #9                  // Field scheduleToStartTimeout:Ljava/lang/String;
       5: aload_0
       6: areturn

  public final void setScheduleToStartTimeout(java.lang.String);
    Code:
       0: aload_0
       1: aload_1
       2: putfield      #9                  // Field scheduleToStartTimeout:Ljava/lang/String;
       5: return

  public final java.lang.String getScheduleToCloseTimeout();
    Code:
       0: aload_0
       1: getfield      #8                  // Field scheduleToCloseTimeout:Ljava/lang/String;
       4: areturn

  public final software.amazon.awssdk.services.swf.model.ActivityTaskScheduledEventAttributes$Builder scheduleToCloseTimeout(java.lang.String);
    Code:
       0: aload_0
       1: aload_1
       2: putfield      #8                  // Field scheduleToCloseTimeout:Ljava/lang/String;
       5: aload_0
       6: areturn

  public final void setScheduleToCloseTimeout(java.lang.String);
    Code:
       0: aload_0
       1: aload_1
       2: putfield      #8                  // Field scheduleToCloseTimeout:Ljava/lang/String;
       5: return

  public final java.lang.String getStartToCloseTimeout();
    Code:
       0: aload_0
       1: getfield      #7                  // Field startToCloseTimeout:Ljava/lang/String;
       4: areturn

  public final software.amazon.awssdk.services.swf.model.ActivityTaskScheduledEventAttributes$Builder startToCloseTimeout(java.lang.String);
    Code:
       0: aload_0
       1: aload_1
       2: putfield      #7                  // Field startToCloseTimeout:Ljava/lang/String;
       5: aload_0
       6: areturn

  public final void setStartToCloseTimeout(java.lang.String);
    Code:
       0: aload_0
       1: aload_1
       2: putfield      #7                  // Field startToCloseTimeout:Ljava/lang/String;
       5: return

  public final software.amazon.awssdk.services.swf.model.TaskList$Builder getTaskList();
    Code:
       0: aload_0
       1: getfield      #6                  // Field taskList:Lsoftware/amazon/awssdk/services/swf/model/TaskList;
       4: ifnull        17
       7: aload_0
       8: getfield      #6                  // Field taskList:Lsoftware/amazon/awssdk/services/swf/model/TaskList;
      11: invokevirtual #39                 // Method software/amazon/awssdk/services/swf/model/TaskList.toBuilder:()Lsoftware/amazon/awssdk/services/swf/model/TaskList$Builder;
      14: goto          18
      17: aconst_null
      18: areturn

  public final software.amazon.awssdk.services.swf.model.ActivityTaskScheduledEventAttributes$Builder taskList(software.amazon.awssdk.services.swf.model.TaskList);
    Code:
       0: aload_0
       1: aload_1
       2: putfield      #6                  // Field taskList:Lsoftware/amazon/awssdk/services/swf/model/TaskList;
       5: aload_0
       6: areturn

  public final void setTaskList(software.amazon.awssdk.services.swf.model.TaskList$BuilderImpl);
    Code:
       0: aload_0
       1: aload_1
       2: ifnull        12
       5: aload_1
       6: invokevirtual #40                 // Method software/amazon/awssdk/services/swf/model/TaskList$BuilderImpl.build:()Lsoftware/amazon/awssdk/services/swf/model/TaskList;
       9: goto          13
      12: aconst_null
      13: putfield      #6                  // Field taskList:Lsoftware/amazon/awssdk/services/swf/model/TaskList;
      16: return

  public final java.lang.String getTaskPriority();
    Code:
       0: aload_0
       1: getfield      #5                  // Field taskPriority:Ljava/lang/String;
       4: areturn

  public final software.amazon.awssdk.services.swf.model.ActivityTaskScheduledEventAttributes$Builder taskPriority(java.lang.String);
    Code:
       0: aload_0
       1: aload_1
       2: putfield      #5                  // Field taskPriority:Ljava/lang/String;
       5: aload_0
       6: areturn

  public final void setTaskPriority(java.lang.String);
    Code:
       0: aload_0
       1: aload_1
       2: putfield      #5                  // Field taskPriority:Ljava/lang/String;
       5: return

  public final java.lang.Long getDecisionTaskCompletedEventId();
    Code:
       0: aload_0
       1: getfield      #4                  // Field decisionTaskCompletedEventId:Ljava/lang/Long;
       4: areturn

  public final software.amazon.awssdk.services.swf.model.ActivityTaskScheduledEventAttributes$Builder decisionTaskCompletedEventId(java.lang.Long);
    Code:
       0: aload_0
       1: aload_1
       2: putfield      #4                  // Field decisionTaskCompletedEventId:Ljava/lang/Long;
       5: aload_0
       6: areturn

  public final void setDecisionTaskCompletedEventId(java.lang.Long);
    Code:
       0: aload_0
       1: aload_1
       2: putfield      #4                  // Field decisionTaskCompletedEventId:Ljava/lang/Long;
       5: return

  public final java.lang.String getHeartbeatTimeout();
    Code:
       0: aload_0
       1: getfield      #3                  // Field heartbeatTimeout:Ljava/lang/String;
       4: areturn

  public final software.amazon.awssdk.services.swf.model.ActivityTaskScheduledEventAttributes$Builder heartbeatTimeout(java.lang.String);
    Code:
       0: aload_0
       1: aload_1
       2: putfield      #3                  // Field heartbeatTimeout:Ljava/lang/String;
       5: aload_0
       6: areturn

  public final void setHeartbeatTimeout(java.lang.String);
    Code:
       0: aload_0
       1: aload_1
       2: putfield      #3                  // Field heartbeatTimeout:Ljava/lang/String;
       5: return

  public software.amazon.awssdk.services.swf.model.ActivityTaskScheduledEventAttributes build();
    Code:
       0: new           #41                 // class software/amazon/awssdk/services/swf/model/ActivityTaskScheduledEventAttributes
       3: dup
       4: aload_0
       5: aconst_null
       6: invokespecial #42                 // Method software/amazon/awssdk/services/swf/model/ActivityTaskScheduledEventAttributes."<init>":(Lsoftware/amazon/awssdk/services/swf/model/ActivityTaskScheduledEventAttributes$BuilderImpl;Lsoftware/amazon/awssdk/services/swf/model/ActivityTaskScheduledEventAttributes$1;)V
       9: areturn

  public java.util.List<software.amazon.awssdk.core.SdkField<?>> sdkFields();
    Code:
       0: invokestatic  #43                 // Method software/amazon/awssdk/services/swf/model/ActivityTaskScheduledEventAttributes.access$2500:()Ljava/util/List;
       3: areturn

  public java.lang.Object build();
    Code:
       0: aload_0
       1: invokevirtual #44                 // Method build:()Lsoftware/amazon/awssdk/services/swf/model/ActivityTaskScheduledEventAttributes;
       4: areturn

  static software.amazon.awssdk.services.swf.model.ActivityType access$000(software.amazon.awssdk.services.swf.model.ActivityTaskScheduledEventAttributes$BuilderImpl);
    Code:
       0: aload_0
       1: getfield      #13                 // Field activityType:Lsoftware/amazon/awssdk/services/swf/model/ActivityType;
       4: areturn

  static java.lang.String access$100(software.amazon.awssdk.services.swf.model.ActivityTaskScheduledEventAttributes$BuilderImpl);
    Code:
       0: aload_0
       1: getfield      #12                 // Field activityId:Ljava/lang/String;
       4: areturn

  static java.lang.String access$200(software.amazon.awssdk.services.swf.model.ActivityTaskScheduledEventAttributes$BuilderImpl);
    Code:
       0: aload_0
       1: getfield      #11                 // Field input:Ljava/lang/String;
       4: areturn

  static java.lang.String access$300(software.amazon.awssdk.services.swf.model.ActivityTaskScheduledEventAttributes$BuilderImpl);
    Code:
       0: aload_0
       1: getfield      #10                 // Field control:Ljava/lang/String;
       4: areturn

  static java.lang.String access$400(software.amazon.awssdk.services.swf.model.ActivityTaskScheduledEventAttributes$BuilderImpl);
    Code:
       0: aload_0
       1: getfield      #9                  // Field scheduleToStartTimeout:Ljava/lang/String;
       4: areturn

  static java.lang.String access$500(software.amazon.awssdk.services.swf.model.ActivityTaskScheduledEventAttributes$BuilderImpl);
    Code:
       0: aload_0
       1: getfield      #8                  // Field scheduleToCloseTimeout:Ljava/lang/String;
       4: areturn

  static java.lang.String access$600(software.amazon.awssdk.services.swf.model.ActivityTaskScheduledEventAttributes$BuilderImpl);
    Code:
       0: aload_0
       1: getfield      #7                  // Field startToCloseTimeout:Ljava/lang/String;
       4: areturn

  static software.amazon.awssdk.services.swf.model.TaskList access$700(software.amazon.awssdk.services.swf.model.ActivityTaskScheduledEventAttributes$BuilderImpl);
    Code:
       0: aload_0
       1: getfield      #6                  // Field taskList:Lsoftware/amazon/awssdk/services/swf/model/TaskList;
       4: areturn

  static java.lang.String access$800(software.amazon.awssdk.services.swf.model.ActivityTaskScheduledEventAttributes$BuilderImpl);
    Code:
       0: aload_0
       1: getfield      #5                  // Field taskPriority:Ljava/lang/String;
       4: areturn

  static java.lang.Long access$900(software.amazon.awssdk.services.swf.model.ActivityTaskScheduledEventAttributes$BuilderImpl);
    Code:
       0: aload_0
       1: getfield      #4                  // Field decisionTaskCompletedEventId:Ljava/lang/Long;
       4: areturn

  static java.lang.String access$1000(software.amazon.awssdk.services.swf.model.ActivityTaskScheduledEventAttributes$BuilderImpl);
    Code:
       0: aload_0
       1: getfield      #3                  // Field heartbeatTimeout:Ljava/lang/String;
       4: areturn

  software.amazon.awssdk.services.swf.model.ActivityTaskScheduledEventAttributes$BuilderImpl(software.amazon.awssdk.services.swf.model.ActivityTaskScheduledEventAttributes, software.amazon.awssdk.services.swf.model.ActivityTaskScheduledEventAttributes$1);
    Code:
       0: aload_0
       1: aload_1
       2: invokespecial #2                  // Method "<init>":(Lsoftware/amazon/awssdk/services/swf/model/ActivityTaskScheduledEventAttributes;)V
       5: return

  software.amazon.awssdk.services.swf.model.ActivityTaskScheduledEventAttributes$BuilderImpl(software.amazon.awssdk.services.swf.model.ActivityTaskScheduledEventAttributes$1);
    Code:
       0: aload_0
       1: invokespecial #1                  // Method "<init>":()V
       4: return
}
