Compiled from "Decision.java"
final class software.amazon.awssdk.services.swf.model.Decision$BuilderImpl implements software.amazon.awssdk.services.swf.model.Decision$Builder {
  private java.lang.String decisionType;

  private software.amazon.awssdk.services.swf.model.ScheduleActivityTaskDecisionAttributes scheduleActivityTaskDecisionAttributes;

  private software.amazon.awssdk.services.swf.model.RequestCancelActivityTaskDecisionAttributes requestCancelActivityTaskDecisionAttributes;

  private software.amazon.awssdk.services.swf.model.CompleteWorkflowExecutionDecisionAttributes completeWorkflowExecutionDecisionAttributes;

  private software.amazon.awssdk.services.swf.model.FailWorkflowExecutionDecisionAttributes failWorkflowExecutionDecisionAttributes;

  private software.amazon.awssdk.services.swf.model.CancelWorkflowExecutionDecisionAttributes cancelWorkflowExecutionDecisionAttributes;

  private software.amazon.awssdk.services.swf.model.ContinueAsNewWorkflowExecutionDecisionAttributes continueAsNewWorkflowExecutionDecisionAttributes;

  private software.amazon.awssdk.services.swf.model.RecordMarkerDecisionAttributes recordMarkerDecisionAttributes;

  private software.amazon.awssdk.services.swf.model.StartTimerDecisionAttributes startTimerDecisionAttributes;

  private software.amazon.awssdk.services.swf.model.CancelTimerDecisionAttributes cancelTimerDecisionAttributes;

  private software.amazon.awssdk.services.swf.model.SignalExternalWorkflowExecutionDecisionAttributes signalExternalWorkflowExecutionDecisionAttributes;

  private software.amazon.awssdk.services.swf.model.RequestCancelExternalWorkflowExecutionDecisionAttributes requestCancelExternalWorkflowExecutionDecisionAttributes;

  private software.amazon.awssdk.services.swf.model.StartChildWorkflowExecutionDecisionAttributes startChildWorkflowExecutionDecisionAttributes;

  private software.amazon.awssdk.services.swf.model.ScheduleLambdaFunctionDecisionAttributes scheduleLambdaFunctionDecisionAttributes;

  private software.amazon.awssdk.services.swf.model.Decision$BuilderImpl();
    Code:
       0: aload_0
       1: invokespecial #17                 // Method java/lang/Object."<init>":()V
       4: return

  private software.amazon.awssdk.services.swf.model.Decision$BuilderImpl(software.amazon.awssdk.services.swf.model.Decision);
    Code:
       0: aload_0
       1: invokespecial #17                 // Method java/lang/Object."<init>":()V
       4: aload_0
       5: aload_1
       6: invokestatic  #18                 // Method software/amazon/awssdk/services/swf/model/Decision.access$1600:(Lsoftware/amazon/awssdk/services/swf/model/Decision;)Ljava/lang/String;
       9: invokevirtual #19                 // Method decisionType:(Ljava/lang/String;)Lsoftware/amazon/awssdk/services/swf/model/Decision$Builder;
      12: pop
      13: aload_0
      14: aload_1
      15: invokestatic  #20                 // Method software/amazon/awssdk/services/swf/model/Decision.access$1700:(Lsoftware/amazon/awssdk/services/swf/model/Decision;)Lsoftware/amazon/awssdk/services/swf/model/ScheduleActivityTaskDecisionAttributes;
      18: invokevirtual #21                 // Method scheduleActivityTaskDecisionAttributes:(Lsoftware/amazon/awssdk/services/swf/model/ScheduleActivityTaskDecisionAttributes;)Lsoftware/amazon/awssdk/services/swf/model/Decision$Builder;
      21: pop
      22: aload_0
      23: aload_1
      24: invokestatic  #22                 // Method software/amazon/awssdk/services/swf/model/Decision.access$1800:(Lsoftware/amazon/awssdk/services/swf/model/Decision;)Lsoftware/amazon/awssdk/services/swf/model/RequestCancelActivityTaskDecisionAttributes;
      27: invokevirtual #23                 // Method requestCancelActivityTaskDecisionAttributes:(Lsoftware/amazon/awssdk/services/swf/model/RequestCancelActivityTaskDecisionAttributes;)Lsoftware/amazon/awssdk/services/swf/model/Decision$Builder;
      30: pop
      31: aload_0
      32: aload_1
      33: invokestatic  #24                 // Method software/amazon/awssdk/services/swf/model/Decision.access$1900:(Lsoftware/amazon/awssdk/services/swf/model/Decision;)Lsoftware/amazon/awssdk/services/swf/model/CompleteWorkflowExecutionDecisionAttributes;
      36: invokevirtual #25                 // Method completeWorkflowExecutionDecisionAttributes:(Lsoftware/amazon/awssdk/services/swf/model/CompleteWorkflowExecutionDecisionAttributes;)Lsoftware/amazon/awssdk/services/swf/model/Decision$Builder;
      39: pop
      40: aload_0
      41: aload_1
      42: invokestatic  #26                 // Method software/amazon/awssdk/services/swf/model/Decision.access$2000:(Lsoftware/amazon/awssdk/services/swf/model/Decision;)Lsoftware/amazon/awssdk/services/swf/model/FailWorkflowExecutionDecisionAttributes;
      45: invokevirtual #27                 // Method failWorkflowExecutionDecisionAttributes:(Lsoftware/amazon/awssdk/services/swf/model/FailWorkflowExecutionDecisionAttributes;)Lsoftware/amazon/awssdk/services/swf/model/Decision$Builder;
      48: pop
      49: aload_0
      50: aload_1
      51: invokestatic  #28                 // Method software/amazon/awssdk/services/swf/model/Decision.access$2100:(Lsoftware/amazon/awssdk/services/swf/model/Decision;)Lsoftware/amazon/awssdk/services/swf/model/CancelWorkflowExecutionDecisionAttributes;
      54: invokevirtual #29                 // Method cancelWorkflowExecutionDecisionAttributes:(Lsoftware/amazon/awssdk/services/swf/model/CancelWorkflowExecutionDecisionAttributes;)Lsoftware/amazon/awssdk/services/swf/model/Decision$Builder;
      57: pop
      58: aload_0
      59: aload_1
      60: invokestatic  #30                 // Method software/amazon/awssdk/services/swf/model/Decision.access$2200:(Lsoftware/amazon/awssdk/services/swf/model/Decision;)Lsoftware/amazon/awssdk/services/swf/model/ContinueAsNewWorkflowExecutionDecisionAttributes;
      63: invokevirtual #31                 // Method continueAsNewWorkflowExecutionDecisionAttributes:(Lsoftware/amazon/awssdk/services/swf/model/ContinueAsNewWorkflowExecutionDecisionAttributes;)Lsoftware/amazon/awssdk/services/swf/model/Decision$Builder;
      66: pop
      67: aload_0
      68: aload_1
      69: invokestatic  #32                 // Method software/amazon/awssdk/services/swf/model/Decision.access$2300:(Lsoftware/amazon/awssdk/services/swf/model/Decision;)Lsoftware/amazon/awssdk/services/swf/model/RecordMarkerDecisionAttributes;
      72: invokevirtual #33                 // Method recordMarkerDecisionAttributes:(Lsoftware/amazon/awssdk/services/swf/model/RecordMarkerDecisionAttributes;)Lsoftware/amazon/awssdk/services/swf/model/Decision$Builder;
      75: pop
      76: aload_0
      77: aload_1
      78: invokestatic  #34                 // Method software/amazon/awssdk/services/swf/model/Decision.access$2400:(Lsoftware/amazon/awssdk/services/swf/model/Decision;)Lsoftware/amazon/awssdk/services/swf/model/StartTimerDecisionAttributes;
      81: invokevirtual #35                 // Method startTimerDecisionAttributes:(Lsoftware/amazon/awssdk/services/swf/model/StartTimerDecisionAttributes;)Lsoftware/amazon/awssdk/services/swf/model/Decision$Builder;
      84: pop
      85: aload_0
      86: aload_1
      87: invokestatic  #36                 // Method software/amazon/awssdk/services/swf/model/Decision.access$2500:(Lsoftware/amazon/awssdk/services/swf/model/Decision;)Lsoftware/amazon/awssdk/services/swf/model/CancelTimerDecisionAttributes;
      90: invokevirtual #37                 // Method cancelTimerDecisionAttributes:(Lsoftware/amazon/awssdk/services/swf/model/CancelTimerDecisionAttributes;)Lsoftware/amazon/awssdk/services/swf/model/Decision$Builder;
      93: pop
      94: aload_0
      95: aload_1
      96: invokestatic  #38                 // Method software/amazon/awssdk/services/swf/model/Decision.access$2600:(Lsoftware/amazon/awssdk/services/swf/model/Decision;)Lsoftware/amazon/awssdk/services/swf/model/SignalExternalWorkflowExecutionDecisionAttributes;
      99: invokevirtual #39                 // Method signalExternalWorkflowExecutionDecisionAttributes:(Lsoftware/amazon/awssdk/services/swf/model/SignalExternalWorkflowExecutionDecisionAttributes;)Lsoftware/amazon/awssdk/services/swf/model/Decision$Builder;
     102: pop
     103: aload_0
     104: aload_1
     105: invokestatic  #40                 // Method software/amazon/awssdk/services/swf/model/Decision.access$2700:(Lsoftware/amazon/awssdk/services/swf/model/Decision;)Lsoftware/amazon/awssdk/services/swf/model/RequestCancelExternalWorkflowExecutionDecisionAttributes;
     108: invokevirtual #41                 // Method requestCancelExternalWorkflowExecutionDecisionAttributes:(Lsoftware/amazon/awssdk/services/swf/model/RequestCancelExternalWorkflowExecutionDecisionAttributes;)Lsoftware/amazon/awssdk/services/swf/model/Decision$Builder;
     111: pop
     112: aload_0
     113: aload_1
     114: invokestatic  #42                 // Method software/amazon/awssdk/services/swf/model/Decision.access$2800:(Lsoftware/amazon/awssdk/services/swf/model/Decision;)Lsoftware/amazon/awssdk/services/swf/model/StartChildWorkflowExecutionDecisionAttributes;
     117: invokevirtual #43                 // Method startChildWorkflowExecutionDecisionAttributes:(Lsoftware/amazon/awssdk/services/swf/model/StartChildWorkflowExecutionDecisionAttributes;)Lsoftware/amazon/awssdk/services/swf/model/Decision$Builder;
     120: pop
     121: aload_0
     122: aload_1
     123: invokestatic  #44                 // Method software/amazon/awssdk/services/swf/model/Decision.access$2900:(Lsoftware/amazon/awssdk/services/swf/model/Decision;)Lsoftware/amazon/awssdk/services/swf/model/ScheduleLambdaFunctionDecisionAttributes;
     126: invokevirtual #45                 // Method scheduleLambdaFunctionDecisionAttributes:(Lsoftware/amazon/awssdk/services/swf/model/ScheduleLambdaFunctionDecisionAttributes;)Lsoftware/amazon/awssdk/services/swf/model/Decision$Builder;
     129: pop
     130: return

  public final java.lang.String getDecisionTypeAsString();
    Code:
       0: aload_0
       1: getfield      #16                 // Field decisionType:Ljava/lang/String;
       4: areturn

  public final software.amazon.awssdk.services.swf.model.Decision$Builder decisionType(java.lang.String);
    Code:
       0: aload_0
       1: aload_1
       2: putfield      #16                 // Field decisionType:Ljava/lang/String;
       5: aload_0
       6: areturn

  public final software.amazon.awssdk.services.swf.model.Decision$Builder decisionType(software.amazon.awssdk.services.swf.model.DecisionType);
    Code:
       0: aload_0
       1: aload_1
       2: ifnonnull     9
       5: aconst_null
       6: goto          13
       9: aload_1
      10: invokevirtual #46                 // Method software/amazon/awssdk/services/swf/model/DecisionType.toString:()Ljava/lang/String;
      13: invokevirtual #19                 // Method decisionType:(Ljava/lang/String;)Lsoftware/amazon/awssdk/services/swf/model/Decision$Builder;
      16: pop
      17: aload_0
      18: areturn

  public final void setDecisionType(java.lang.String);
    Code:
       0: aload_0
       1: aload_1
       2: putfield      #16                 // Field decisionType:Ljava/lang/String;
       5: return

  public final software.amazon.awssdk.services.swf.model.ScheduleActivityTaskDecisionAttributes$Builder getScheduleActivityTaskDecisionAttributes();
    Code:
       0: aload_0
       1: getfield      #15                 // Field scheduleActivityTaskDecisionAttributes:Lsoftware/amazon/awssdk/services/swf/model/ScheduleActivityTaskDecisionAttributes;
       4: ifnull        17
       7: aload_0
       8: getfield      #15                 // Field scheduleActivityTaskDecisionAttributes:Lsoftware/amazon/awssdk/services/swf/model/ScheduleActivityTaskDecisionAttributes;
      11: invokevirtual #47                 // Method software/amazon/awssdk/services/swf/model/ScheduleActivityTaskDecisionAttributes.toBuilder:()Lsoftware/amazon/awssdk/services/swf/model/ScheduleActivityTaskDecisionAttributes$Builder;
      14: goto          18
      17: aconst_null
      18: areturn

  public final software.amazon.awssdk.services.swf.model.Decision$Builder scheduleActivityTaskDecisionAttributes(software.amazon.awssdk.services.swf.model.ScheduleActivityTaskDecisionAttributes);
    Code:
       0: aload_0
       1: aload_1
       2: putfield      #15                 // Field scheduleActivityTaskDecisionAttributes:Lsoftware/amazon/awssdk/services/swf/model/ScheduleActivityTaskDecisionAttributes;
       5: aload_0
       6: areturn

  public final void setScheduleActivityTaskDecisionAttributes(software.amazon.awssdk.services.swf.model.ScheduleActivityTaskDecisionAttributes$BuilderImpl);
    Code:
       0: aload_0
       1: aload_1
       2: ifnull        12
       5: aload_1
       6: invokevirtual #48                 // Method software/amazon/awssdk/services/swf/model/ScheduleActivityTaskDecisionAttributes$BuilderImpl.build:()Lsoftware/amazon/awssdk/services/swf/model/ScheduleActivityTaskDecisionAttributes;
       9: goto          13
      12: aconst_null
      13: putfield      #15                 // Field scheduleActivityTaskDecisionAttributes:Lsoftware/amazon/awssdk/services/swf/model/ScheduleActivityTaskDecisionAttributes;
      16: return

  public final software.amazon.awssdk.services.swf.model.RequestCancelActivityTaskDecisionAttributes$Builder getRequestCancelActivityTaskDecisionAttributes();
    Code:
       0: aload_0
       1: getfield      #14                 // Field requestCancelActivityTaskDecisionAttributes:Lsoftware/amazon/awssdk/services/swf/model/RequestCancelActivityTaskDecisionAttributes;
       4: ifnull        17
       7: aload_0
       8: getfield      #14                 // Field requestCancelActivityTaskDecisionAttributes:Lsoftware/amazon/awssdk/services/swf/model/RequestCancelActivityTaskDecisionAttributes;
      11: invokevirtual #49                 // Method software/amazon/awssdk/services/swf/model/RequestCancelActivityTaskDecisionAttributes.toBuilder:()Lsoftware/amazon/awssdk/services/swf/model/RequestCancelActivityTaskDecisionAttributes$Builder;
      14: goto          18
      17: aconst_null
      18: areturn

  public final software.amazon.awssdk.services.swf.model.Decision$Builder requestCancelActivityTaskDecisionAttributes(software.amazon.awssdk.services.swf.model.RequestCancelActivityTaskDecisionAttributes);
    Code:
       0: aload_0
       1: aload_1
       2: putfield      #14                 // Field requestCancelActivityTaskDecisionAttributes:Lsoftware/amazon/awssdk/services/swf/model/RequestCancelActivityTaskDecisionAttributes;
       5: aload_0
       6: areturn

  public final void setRequestCancelActivityTaskDecisionAttributes(software.amazon.awssdk.services.swf.model.RequestCancelActivityTaskDecisionAttributes$BuilderImpl);
    Code:
       0: aload_0
       1: aload_1
       2: ifnull        12
       5: aload_1
       6: invokevirtual #50                 // Method software/amazon/awssdk/services/swf/model/RequestCancelActivityTaskDecisionAttributes$BuilderImpl.build:()Lsoftware/amazon/awssdk/services/swf/model/RequestCancelActivityTaskDecisionAttributes;
       9: goto          13
      12: aconst_null
      13: putfield      #14                 // Field requestCancelActivityTaskDecisionAttributes:Lsoftware/amazon/awssdk/services/swf/model/RequestCancelActivityTaskDecisionAttributes;
      16: return

  public final software.amazon.awssdk.services.swf.model.CompleteWorkflowExecutionDecisionAttributes$Builder getCompleteWorkflowExecutionDecisionAttributes();
    Code:
       0: aload_0
       1: getfield      #13                 // Field completeWorkflowExecutionDecisionAttributes:Lsoftware/amazon/awssdk/services/swf/model/CompleteWorkflowExecutionDecisionAttributes;
       4: ifnull        17
       7: aload_0
       8: getfield      #13                 // Field completeWorkflowExecutionDecisionAttributes:Lsoftware/amazon/awssdk/services/swf/model/CompleteWorkflowExecutionDecisionAttributes;
      11: invokevirtual #51                 // Method software/amazon/awssdk/services/swf/model/CompleteWorkflowExecutionDecisionAttributes.toBuilder:()Lsoftware/amazon/awssdk/services/swf/model/CompleteWorkflowExecutionDecisionAttributes$Builder;
      14: goto          18
      17: aconst_null
      18: areturn

  public final software.amazon.awssdk.services.swf.model.Decision$Builder completeWorkflowExecutionDecisionAttributes(software.amazon.awssdk.services.swf.model.CompleteWorkflowExecutionDecisionAttributes);
    Code:
       0: aload_0
       1: aload_1
       2: putfield      #13                 // Field completeWorkflowExecutionDecisionAttributes:Lsoftware/amazon/awssdk/services/swf/model/CompleteWorkflowExecutionDecisionAttributes;
       5: aload_0
       6: areturn

  public final void setCompleteWorkflowExecutionDecisionAttributes(software.amazon.awssdk.services.swf.model.CompleteWorkflowExecutionDecisionAttributes$BuilderImpl);
    Code:
       0: aload_0
       1: aload_1
       2: ifnull        12
       5: aload_1
       6: invokevirtual #52                 // Method software/amazon/awssdk/services/swf/model/CompleteWorkflowExecutionDecisionAttributes$BuilderImpl.build:()Lsoftware/amazon/awssdk/services/swf/model/CompleteWorkflowExecutionDecisionAttributes;
       9: goto          13
      12: aconst_null
      13: putfield      #13                 // Field completeWorkflowExecutionDecisionAttributes:Lsoftware/amazon/awssdk/services/swf/model/CompleteWorkflowExecutionDecisionAttributes;
      16: return

  public final software.amazon.awssdk.services.swf.model.FailWorkflowExecutionDecisionAttributes$Builder getFailWorkflowExecutionDecisionAttributes();
    Code:
       0: aload_0
       1: getfield      #12                 // Field failWorkflowExecutionDecisionAttributes:Lsoftware/amazon/awssdk/services/swf/model/FailWorkflowExecutionDecisionAttributes;
       4: ifnull        17
       7: aload_0
       8: getfield      #12                 // Field failWorkflowExecutionDecisionAttributes:Lsoftware/amazon/awssdk/services/swf/model/FailWorkflowExecutionDecisionAttributes;
      11: invokevirtual #53                 // Method software/amazon/awssdk/services/swf/model/FailWorkflowExecutionDecisionAttributes.toBuilder:()Lsoftware/amazon/awssdk/services/swf/model/FailWorkflowExecutionDecisionAttributes$Builder;
      14: goto          18
      17: aconst_null
      18: areturn

  public final software.amazon.awssdk.services.swf.model.Decision$Builder failWorkflowExecutionDecisionAttributes(software.amazon.awssdk.services.swf.model.FailWorkflowExecutionDecisionAttributes);
    Code:
       0: aload_0
       1: aload_1
       2: putfield      #12                 // Field failWorkflowExecutionDecisionAttributes:Lsoftware/amazon/awssdk/services/swf/model/FailWorkflowExecutionDecisionAttributes;
       5: aload_0
       6: areturn

  public final void setFailWorkflowExecutionDecisionAttributes(software.amazon.awssdk.services.swf.model.FailWorkflowExecutionDecisionAttributes$BuilderImpl);
    Code:
       0: aload_0
       1: aload_1
       2: ifnull        12
       5: aload_1
       6: invokevirtual #54                 // Method software/amazon/awssdk/services/swf/model/FailWorkflowExecutionDecisionAttributes$BuilderImpl.build:()Lsoftware/amazon/awssdk/services/swf/model/FailWorkflowExecutionDecisionAttributes;
       9: goto          13
      12: aconst_null
      13: putfield      #12                 // Field failWorkflowExecutionDecisionAttributes:Lsoftware/amazon/awssdk/services/swf/model/FailWorkflowExecutionDecisionAttributes;
      16: return

  public final software.amazon.awssdk.services.swf.model.CancelWorkflowExecutionDecisionAttributes$Builder getCancelWorkflowExecutionDecisionAttributes();
    Code:
       0: aload_0
       1: getfield      #11                 // Field cancelWorkflowExecutionDecisionAttributes:Lsoftware/amazon/awssdk/services/swf/model/CancelWorkflowExecutionDecisionAttributes;
       4: ifnull        17
       7: aload_0
       8: getfield      #11                 // Field cancelWorkflowExecutionDecisionAttributes:Lsoftware/amazon/awssdk/services/swf/model/CancelWorkflowExecutionDecisionAttributes;
      11: invokevirtual #55                 // Method software/amazon/awssdk/services/swf/model/CancelWorkflowExecutionDecisionAttributes.toBuilder:()Lsoftware/amazon/awssdk/services/swf/model/CancelWorkflowExecutionDecisionAttributes$Builder;
      14: goto          18
      17: aconst_null
      18: areturn

  public final software.amazon.awssdk.services.swf.model.Decision$Builder cancelWorkflowExecutionDecisionAttributes(software.amazon.awssdk.services.swf.model.CancelWorkflowExecutionDecisionAttributes);
    Code:
       0: aload_0
       1: aload_1
       2: putfield      #11                 // Field cancelWorkflowExecutionDecisionAttributes:Lsoftware/amazon/awssdk/services/swf/model/CancelWorkflowExecutionDecisionAttributes;
       5: aload_0
       6: areturn

  public final void setCancelWorkflowExecutionDecisionAttributes(software.amazon.awssdk.services.swf.model.CancelWorkflowExecutionDecisionAttributes$BuilderImpl);
    Code:
       0: aload_0
       1: aload_1
       2: ifnull        12
       5: aload_1
       6: invokevirtual #56                 // Method software/amazon/awssdk/services/swf/model/CancelWorkflowExecutionDecisionAttributes$BuilderImpl.build:()Lsoftware/amazon/awssdk/services/swf/model/CancelWorkflowExecutionDecisionAttributes;
       9: goto          13
      12: aconst_null
      13: putfield      #11                 // Field cancelWorkflowExecutionDecisionAttributes:Lsoftware/amazon/awssdk/services/swf/model/CancelWorkflowExecutionDecisionAttributes;
      16: return

  public final software.amazon.awssdk.services.swf.model.ContinueAsNewWorkflowExecutionDecisionAttributes$Builder getContinueAsNewWorkflowExecutionDecisionAttributes();
    Code:
       0: aload_0
       1: getfield      #10                 // Field continueAsNewWorkflowExecutionDecisionAttributes:Lsoftware/amazon/awssdk/services/swf/model/ContinueAsNewWorkflowExecutionDecisionAttributes;
       4: ifnull        17
       7: aload_0
       8: getfield      #10                 // Field continueAsNewWorkflowExecutionDecisionAttributes:Lsoftware/amazon/awssdk/services/swf/model/ContinueAsNewWorkflowExecutionDecisionAttributes;
      11: invokevirtual #57                 // Method software/amazon/awssdk/services/swf/model/ContinueAsNewWorkflowExecutionDecisionAttributes.toBuilder:()Lsoftware/amazon/awssdk/services/swf/model/ContinueAsNewWorkflowExecutionDecisionAttributes$Builder;
      14: goto          18
      17: aconst_null
      18: areturn

  public final software.amazon.awssdk.services.swf.model.Decision$Builder continueAsNewWorkflowExecutionDecisionAttributes(software.amazon.awssdk.services.swf.model.ContinueAsNewWorkflowExecutionDecisionAttributes);
    Code:
       0: aload_0
       1: aload_1
       2: putfield      #10                 // Field continueAsNewWorkflowExecutionDecisionAttributes:Lsoftware/amazon/awssdk/services/swf/model/ContinueAsNewWorkflowExecutionDecisionAttributes;
       5: aload_0
       6: areturn

  public final void setContinueAsNewWorkflowExecutionDecisionAttributes(software.amazon.awssdk.services.swf.model.ContinueAsNewWorkflowExecutionDecisionAttributes$BuilderImpl);
    Code:
       0: aload_0
       1: aload_1
       2: ifnull        12
       5: aload_1
       6: invokevirtual #58                 // Method software/amazon/awssdk/services/swf/model/ContinueAsNewWorkflowExecutionDecisionAttributes$BuilderImpl.build:()Lsoftware/amazon/awssdk/services/swf/model/ContinueAsNewWorkflowExecutionDecisionAttributes;
       9: goto          13
      12: aconst_null
      13: putfield      #10                 // Field continueAsNewWorkflowExecutionDecisionAttributes:Lsoftware/amazon/awssdk/services/swf/model/ContinueAsNewWorkflowExecutionDecisionAttributes;
      16: return

  public final software.amazon.awssdk.services.swf.model.RecordMarkerDecisionAttributes$Builder getRecordMarkerDecisionAttributes();
    Code:
       0: aload_0
       1: getfield      #9                  // Field recordMarkerDecisionAttributes:Lsoftware/amazon/awssdk/services/swf/model/RecordMarkerDecisionAttributes;
       4: ifnull        17
       7: aload_0
       8: getfield      #9                  // Field recordMarkerDecisionAttributes:Lsoftware/amazon/awssdk/services/swf/model/RecordMarkerDecisionAttributes;
      11: invokevirtual #59                 // Method software/amazon/awssdk/services/swf/model/RecordMarkerDecisionAttributes.toBuilder:()Lsoftware/amazon/awssdk/services/swf/model/RecordMarkerDecisionAttributes$Builder;
      14: goto          18
      17: aconst_null
      18: areturn

  public final software.amazon.awssdk.services.swf.model.Decision$Builder recordMarkerDecisionAttributes(software.amazon.awssdk.services.swf.model.RecordMarkerDecisionAttributes);
    Code:
       0: aload_0
       1: aload_1
       2: putfield      #9                  // Field recordMarkerDecisionAttributes:Lsoftware/amazon/awssdk/services/swf/model/RecordMarkerDecisionAttributes;
       5: aload_0
       6: areturn

  public final void setRecordMarkerDecisionAttributes(software.amazon.awssdk.services.swf.model.RecordMarkerDecisionAttributes$BuilderImpl);
    Code:
       0: aload_0
       1: aload_1
       2: ifnull        12
       5: aload_1
       6: invokevirtual #60                 // Method software/amazon/awssdk/services/swf/model/RecordMarkerDecisionAttributes$BuilderImpl.build:()Lsoftware/amazon/awssdk/services/swf/model/RecordMarkerDecisionAttributes;
       9: goto          13
      12: aconst_null
      13: putfield      #9                  // Field recordMarkerDecisionAttributes:Lsoftware/amazon/awssdk/services/swf/model/RecordMarkerDecisionAttributes;
      16: return

  public final software.amazon.awssdk.services.swf.model.StartTimerDecisionAttributes$Builder getStartTimerDecisionAttributes();
    Code:
       0: aload_0
       1: getfield      #8                  // Field startTimerDecisionAttributes:Lsoftware/amazon/awssdk/services/swf/model/StartTimerDecisionAttributes;
       4: ifnull        17
       7: aload_0
       8: getfield      #8                  // Field startTimerDecisionAttributes:Lsoftware/amazon/awssdk/services/swf/model/StartTimerDecisionAttributes;
      11: invokevirtual #61                 // Method software/amazon/awssdk/services/swf/model/StartTimerDecisionAttributes.toBuilder:()Lsoftware/amazon/awssdk/services/swf/model/StartTimerDecisionAttributes$Builder;
      14: goto          18
      17: aconst_null
      18: areturn

  public final software.amazon.awssdk.services.swf.model.Decision$Builder startTimerDecisionAttributes(software.amazon.awssdk.services.swf.model.StartTimerDecisionAttributes);
    Code:
       0: aload_0
       1: aload_1
       2: putfield      #8                  // Field startTimerDecisionAttributes:Lsoftware/amazon/awssdk/services/swf/model/StartTimerDecisionAttributes;
       5: aload_0
       6: areturn

  public final void setStartTimerDecisionAttributes(software.amazon.awssdk.services.swf.model.StartTimerDecisionAttributes$BuilderImpl);
    Code:
       0: aload_0
       1: aload_1
       2: ifnull        12
       5: aload_1
       6: invokevirtual #62                 // Method software/amazon/awssdk/services/swf/model/StartTimerDecisionAttributes$BuilderImpl.build:()Lsoftware/amazon/awssdk/services/swf/model/StartTimerDecisionAttributes;
       9: goto          13
      12: aconst_null
      13: putfield      #8                  // Field startTimerDecisionAttributes:Lsoftware/amazon/awssdk/services/swf/model/StartTimerDecisionAttributes;
      16: return

  public final software.amazon.awssdk.services.swf.model.CancelTimerDecisionAttributes$Builder getCancelTimerDecisionAttributes();
    Code:
       0: aload_0
       1: getfield      #7                  // Field cancelTimerDecisionAttributes:Lsoftware/amazon/awssdk/services/swf/model/CancelTimerDecisionAttributes;
       4: ifnull        17
       7: aload_0
       8: getfield      #7                  // Field cancelTimerDecisionAttributes:Lsoftware/amazon/awssdk/services/swf/model/CancelTimerDecisionAttributes;
      11: invokevirtual #63                 // Method software/amazon/awssdk/services/swf/model/CancelTimerDecisionAttributes.toBuilder:()Lsoftware/amazon/awssdk/services/swf/model/CancelTimerDecisionAttributes$Builder;
      14: goto          18
      17: aconst_null
      18: areturn

  public final software.amazon.awssdk.services.swf.model.Decision$Builder cancelTimerDecisionAttributes(software.amazon.awssdk.services.swf.model.CancelTimerDecisionAttributes);
    Code:
       0: aload_0
       1: aload_1
       2: putfield      #7                  // Field cancelTimerDecisionAttributes:Lsoftware/amazon/awssdk/services/swf/model/CancelTimerDecisionAttributes;
       5: aload_0
       6: areturn

  public final void setCancelTimerDecisionAttributes(software.amazon.awssdk.services.swf.model.CancelTimerDecisionAttributes$BuilderImpl);
    Code:
       0: aload_0
       1: aload_1
       2: ifnull        12
       5: aload_1
       6: invokevirtual #64                 // Method software/amazon/awssdk/services/swf/model/CancelTimerDecisionAttributes$BuilderImpl.build:()Lsoftware/amazon/awssdk/services/swf/model/CancelTimerDecisionAttributes;
       9: goto          13
      12: aconst_null
      13: putfield      #7                  // Field cancelTimerDecisionAttributes:Lsoftware/amazon/awssdk/services/swf/model/CancelTimerDecisionAttributes;
      16: return

  public final software.amazon.awssdk.services.swf.model.SignalExternalWorkflowExecutionDecisionAttributes$Builder getSignalExternalWorkflowExecutionDecisionAttributes();
    Code:
       0: aload_0
       1: getfield      #6                  // Field signalExternalWorkflowExecutionDecisionAttributes:Lsoftware/amazon/awssdk/services/swf/model/SignalExternalWorkflowExecutionDecisionAttributes;
       4: ifnull        17
       7: aload_0
       8: getfield      #6                  // Field signalExternalWorkflowExecutionDecisionAttributes:Lsoftware/amazon/awssdk/services/swf/model/SignalExternalWorkflowExecutionDecisionAttributes;
      11: invokevirtual #65                 // Method software/amazon/awssdk/services/swf/model/SignalExternalWorkflowExecutionDecisionAttributes.toBuilder:()Lsoftware/amazon/awssdk/services/swf/model/SignalExternalWorkflowExecutionDecisionAttributes$Builder;
      14: goto          18
      17: aconst_null
      18: areturn

  public final software.amazon.awssdk.services.swf.model.Decision$Builder signalExternalWorkflowExecutionDecisionAttributes(software.amazon.awssdk.services.swf.model.SignalExternalWorkflowExecutionDecisionAttributes);
    Code:
       0: aload_0
       1: aload_1
       2: putfield      #6                  // Field signalExternalWorkflowExecutionDecisionAttributes:Lsoftware/amazon/awssdk/services/swf/model/SignalExternalWorkflowExecutionDecisionAttributes;
       5: aload_0
       6: areturn

  public final void setSignalExternalWorkflowExecutionDecisionAttributes(software.amazon.awssdk.services.swf.model.SignalExternalWorkflowExecutionDecisionAttributes$BuilderImpl);
    Code:
       0: aload_0
       1: aload_1
       2: ifnull        12
       5: aload_1
       6: invokevirtual #66                 // Method software/amazon/awssdk/services/swf/model/SignalExternalWorkflowExecutionDecisionAttributes$BuilderImpl.build:()Lsoftware/amazon/awssdk/services/swf/model/SignalExternalWorkflowExecutionDecisionAttributes;
       9: goto          13
      12: aconst_null
      13: putfield      #6                  // Field signalExternalWorkflowExecutionDecisionAttributes:Lsoftware/amazon/awssdk/services/swf/model/SignalExternalWorkflowExecutionDecisionAttributes;
      16: return

  public final software.amazon.awssdk.services.swf.model.RequestCancelExternalWorkflowExecutionDecisionAttributes$Builder getRequestCancelExternalWorkflowExecutionDecisionAttributes();
    Code:
       0: aload_0
       1: getfield      #5                  // Field requestCancelExternalWorkflowExecutionDecisionAttributes:Lsoftware/amazon/awssdk/services/swf/model/RequestCancelExternalWorkflowExecutionDecisionAttributes;
       4: ifnull        17
       7: aload_0
       8: getfield      #5                  // Field requestCancelExternalWorkflowExecutionDecisionAttributes:Lsoftware/amazon/awssdk/services/swf/model/RequestCancelExternalWorkflowExecutionDecisionAttributes;
      11: invokevirtual #67                 // Method software/amazon/awssdk/services/swf/model/RequestCancelExternalWorkflowExecutionDecisionAttributes.toBuilder:()Lsoftware/amazon/awssdk/services/swf/model/RequestCancelExternalWorkflowExecutionDecisionAttributes$Builder;
      14: goto          18
      17: aconst_null
      18: areturn

  public final software.amazon.awssdk.services.swf.model.Decision$Builder requestCancelExternalWorkflowExecutionDecisionAttributes(software.amazon.awssdk.services.swf.model.RequestCancelExternalWorkflowExecutionDecisionAttributes);
    Code:
       0: aload_0
       1: aload_1
       2: putfield      #5                  // Field requestCancelExternalWorkflowExecutionDecisionAttributes:Lsoftware/amazon/awssdk/services/swf/model/RequestCancelExternalWorkflowExecutionDecisionAttributes;
       5: aload_0
       6: areturn

  public final void setRequestCancelExternalWorkflowExecutionDecisionAttributes(software.amazon.awssdk.services.swf.model.RequestCancelExternalWorkflowExecutionDecisionAttributes$BuilderImpl);
    Code:
       0: aload_0
       1: aload_1
       2: ifnull        12
       5: aload_1
       6: invokevirtual #68                 // Method software/amazon/awssdk/services/swf/model/RequestCancelExternalWorkflowExecutionDecisionAttributes$BuilderImpl.build:()Lsoftware/amazon/awssdk/services/swf/model/RequestCancelExternalWorkflowExecutionDecisionAttributes;
       9: goto          13
      12: aconst_null
      13: putfield      #5                  // Field requestCancelExternalWorkflowExecutionDecisionAttributes:Lsoftware/amazon/awssdk/services/swf/model/RequestCancelExternalWorkflowExecutionDecisionAttributes;
      16: return

  public final software.amazon.awssdk.services.swf.model.StartChildWorkflowExecutionDecisionAttributes$Builder getStartChildWorkflowExecutionDecisionAttributes();
    Code:
       0: aload_0
       1: getfield      #4                  // Field startChildWorkflowExecutionDecisionAttributes:Lsoftware/amazon/awssdk/services/swf/model/StartChildWorkflowExecutionDecisionAttributes;
       4: ifnull        17
       7: aload_0
       8: getfield      #4                  // Field startChildWorkflowExecutionDecisionAttributes:Lsoftware/amazon/awssdk/services/swf/model/StartChildWorkflowExecutionDecisionAttributes;
      11: invokevirtual #69                 // Method software/amazon/awssdk/services/swf/model/StartChildWorkflowExecutionDecisionAttributes.toBuilder:()Lsoftware/amazon/awssdk/services/swf/model/StartChildWorkflowExecutionDecisionAttributes$Builder;
      14: goto          18
      17: aconst_null
      18: areturn

  public final software.amazon.awssdk.services.swf.model.Decision$Builder startChildWorkflowExecutionDecisionAttributes(software.amazon.awssdk.services.swf.model.StartChildWorkflowExecutionDecisionAttributes);
    Code:
       0: aload_0
       1: aload_1
       2: putfield      #4                  // Field startChildWorkflowExecutionDecisionAttributes:Lsoftware/amazon/awssdk/services/swf/model/StartChildWorkflowExecutionDecisionAttributes;
       5: aload_0
       6: areturn

  public final void setStartChildWorkflowExecutionDecisionAttributes(software.amazon.awssdk.services.swf.model.StartChildWorkflowExecutionDecisionAttributes$BuilderImpl);
    Code:
       0: aload_0
       1: aload_1
       2: ifnull        12
       5: aload_1
       6: invokevirtual #70                 // Method software/amazon/awssdk/services/swf/model/StartChildWorkflowExecutionDecisionAttributes$BuilderImpl.build:()Lsoftware/amazon/awssdk/services/swf/model/StartChildWorkflowExecutionDecisionAttributes;
       9: goto          13
      12: aconst_null
      13: putfield      #4                  // Field startChildWorkflowExecutionDecisionAttributes:Lsoftware/amazon/awssdk/services/swf/model/StartChildWorkflowExecutionDecisionAttributes;
      16: return

  public final software.amazon.awssdk.services.swf.model.ScheduleLambdaFunctionDecisionAttributes$Builder getScheduleLambdaFunctionDecisionAttributes();
    Code:
       0: aload_0
       1: getfield      #3                  // Field scheduleLambdaFunctionDecisionAttributes:Lsoftware/amazon/awssdk/services/swf/model/ScheduleLambdaFunctionDecisionAttributes;
       4: ifnull        17
       7: aload_0
       8: getfield      #3                  // Field scheduleLambdaFunctionDecisionAttributes:Lsoftware/amazon/awssdk/services/swf/model/ScheduleLambdaFunctionDecisionAttributes;
      11: invokevirtual #71                 // Method software/amazon/awssdk/services/swf/model/ScheduleLambdaFunctionDecisionAttributes.toBuilder:()Lsoftware/amazon/awssdk/services/swf/model/ScheduleLambdaFunctionDecisionAttributes$Builder;
      14: goto          18
      17: aconst_null
      18: areturn

  public final software.amazon.awssdk.services.swf.model.Decision$Builder scheduleLambdaFunctionDecisionAttributes(software.amazon.awssdk.services.swf.model.ScheduleLambdaFunctionDecisionAttributes);
    Code:
       0: aload_0
       1: aload_1
       2: putfield      #3                  // Field scheduleLambdaFunctionDecisionAttributes:Lsoftware/amazon/awssdk/services/swf/model/ScheduleLambdaFunctionDecisionAttributes;
       5: aload_0
       6: areturn

  public final void setScheduleLambdaFunctionDecisionAttributes(software.amazon.awssdk.services.swf.model.ScheduleLambdaFunctionDecisionAttributes$BuilderImpl);
    Code:
       0: aload_0
       1: aload_1
       2: ifnull        12
       5: aload_1
       6: invokevirtual #72                 // Method software/amazon/awssdk/services/swf/model/ScheduleLambdaFunctionDecisionAttributes$BuilderImpl.build:()Lsoftware/amazon/awssdk/services/swf/model/ScheduleLambdaFunctionDecisionAttributes;
       9: goto          13
      12: aconst_null
      13: putfield      #3                  // Field scheduleLambdaFunctionDecisionAttributes:Lsoftware/amazon/awssdk/services/swf/model/ScheduleLambdaFunctionDecisionAttributes;
      16: return

  public software.amazon.awssdk.services.swf.model.Decision build();
    Code:
       0: new           #73                 // class software/amazon/awssdk/services/swf/model/Decision
       3: dup
       4: aload_0
       5: aconst_null
       6: invokespecial #74                 // Method software/amazon/awssdk/services/swf/model/Decision."<init>":(Lsoftware/amazon/awssdk/services/swf/model/Decision$BuilderImpl;Lsoftware/amazon/awssdk/services/swf/model/Decision$1;)V
       9: areturn

  public java.util.List<software.amazon.awssdk.core.SdkField<?>> sdkFields();
    Code:
       0: invokestatic  #75                 // Method software/amazon/awssdk/services/swf/model/Decision.access$3100:()Ljava/util/List;
       3: areturn

  public java.lang.Object build();
    Code:
       0: aload_0
       1: invokevirtual #76                 // Method build:()Lsoftware/amazon/awssdk/services/swf/model/Decision;
       4: areturn

  static java.lang.String access$000(software.amazon.awssdk.services.swf.model.Decision$BuilderImpl);
    Code:
       0: aload_0
       1: getfield      #16                 // Field decisionType:Ljava/lang/String;
       4: areturn

  static software.amazon.awssdk.services.swf.model.ScheduleActivityTaskDecisionAttributes access$100(software.amazon.awssdk.services.swf.model.Decision$BuilderImpl);
    Code:
       0: aload_0
       1: getfield      #15                 // Field scheduleActivityTaskDecisionAttributes:Lsoftware/amazon/awssdk/services/swf/model/ScheduleActivityTaskDecisionAttributes;
       4: areturn

  static software.amazon.awssdk.services.swf.model.RequestCancelActivityTaskDecisionAttributes access$200(software.amazon.awssdk.services.swf.model.Decision$BuilderImpl);
    Code:
       0: aload_0
       1: getfield      #14                 // Field requestCancelActivityTaskDecisionAttributes:Lsoftware/amazon/awssdk/services/swf/model/RequestCancelActivityTaskDecisionAttributes;
       4: areturn

  static software.amazon.awssdk.services.swf.model.CompleteWorkflowExecutionDecisionAttributes access$300(software.amazon.awssdk.services.swf.model.Decision$BuilderImpl);
    Code:
       0: aload_0
       1: getfield      #13                 // Field completeWorkflowExecutionDecisionAttributes:Lsoftware/amazon/awssdk/services/swf/model/CompleteWorkflowExecutionDecisionAttributes;
       4: areturn

  static software.amazon.awssdk.services.swf.model.FailWorkflowExecutionDecisionAttributes access$400(software.amazon.awssdk.services.swf.model.Decision$BuilderImpl);
    Code:
       0: aload_0
       1: getfield      #12                 // Field failWorkflowExecutionDecisionAttributes:Lsoftware/amazon/awssdk/services/swf/model/FailWorkflowExecutionDecisionAttributes;
       4: areturn

  static software.amazon.awssdk.services.swf.model.CancelWorkflowExecutionDecisionAttributes access$500(software.amazon.awssdk.services.swf.model.Decision$BuilderImpl);
    Code:
       0: aload_0
       1: getfield      #11                 // Field cancelWorkflowExecutionDecisionAttributes:Lsoftware/amazon/awssdk/services/swf/model/CancelWorkflowExecutionDecisionAttributes;
       4: areturn

  static software.amazon.awssdk.services.swf.model.ContinueAsNewWorkflowExecutionDecisionAttributes access$600(software.amazon.awssdk.services.swf.model.Decision$BuilderImpl);
    Code:
       0: aload_0
       1: getfield      #10                 // Field continueAsNewWorkflowExecutionDecisionAttributes:Lsoftware/amazon/awssdk/services/swf/model/ContinueAsNewWorkflowExecutionDecisionAttributes;
       4: areturn

  static software.amazon.awssdk.services.swf.model.RecordMarkerDecisionAttributes access$700(software.amazon.awssdk.services.swf.model.Decision$BuilderImpl);
    Code:
       0: aload_0
       1: getfield      #9                  // Field recordMarkerDecisionAttributes:Lsoftware/amazon/awssdk/services/swf/model/RecordMarkerDecisionAttributes;
       4: areturn

  static software.amazon.awssdk.services.swf.model.StartTimerDecisionAttributes access$800(software.amazon.awssdk.services.swf.model.Decision$BuilderImpl);
    Code:
       0: aload_0
       1: getfield      #8                  // Field startTimerDecisionAttributes:Lsoftware/amazon/awssdk/services/swf/model/StartTimerDecisionAttributes;
       4: areturn

  static software.amazon.awssdk.services.swf.model.CancelTimerDecisionAttributes access$900(software.amazon.awssdk.services.swf.model.Decision$BuilderImpl);
    Code:
       0: aload_0
       1: getfield      #7                  // Field cancelTimerDecisionAttributes:Lsoftware/amazon/awssdk/services/swf/model/CancelTimerDecisionAttributes;
       4: areturn

  static software.amazon.awssdk.services.swf.model.SignalExternalWorkflowExecutionDecisionAttributes access$1000(software.amazon.awssdk.services.swf.model.Decision$BuilderImpl);
    Code:
       0: aload_0
       1: getfield      #6                  // Field signalExternalWorkflowExecutionDecisionAttributes:Lsoftware/amazon/awssdk/services/swf/model/SignalExternalWorkflowExecutionDecisionAttributes;
       4: areturn

  static software.amazon.awssdk.services.swf.model.RequestCancelExternalWorkflowExecutionDecisionAttributes access$1100(software.amazon.awssdk.services.swf.model.Decision$BuilderImpl);
    Code:
       0: aload_0
       1: getfield      #5                  // Field requestCancelExternalWorkflowExecutionDecisionAttributes:Lsoftware/amazon/awssdk/services/swf/model/RequestCancelExternalWorkflowExecutionDecisionAttributes;
       4: areturn

  static software.amazon.awssdk.services.swf.model.StartChildWorkflowExecutionDecisionAttributes access$1200(software.amazon.awssdk.services.swf.model.Decision$BuilderImpl);
    Code:
       0: aload_0
       1: getfield      #4                  // Field startChildWorkflowExecutionDecisionAttributes:Lsoftware/amazon/awssdk/services/swf/model/StartChildWorkflowExecutionDecisionAttributes;
       4: areturn

  static software.amazon.awssdk.services.swf.model.ScheduleLambdaFunctionDecisionAttributes access$1300(software.amazon.awssdk.services.swf.model.Decision$BuilderImpl);
    Code:
       0: aload_0
       1: getfield      #3                  // Field scheduleLambdaFunctionDecisionAttributes:Lsoftware/amazon/awssdk/services/swf/model/ScheduleLambdaFunctionDecisionAttributes;
       4: areturn

  software.amazon.awssdk.services.swf.model.Decision$BuilderImpl(software.amazon.awssdk.services.swf.model.Decision, software.amazon.awssdk.services.swf.model.Decision$1);
    Code:
       0: aload_0
       1: aload_1
       2: invokespecial #2                  // Method "<init>":(Lsoftware/amazon/awssdk/services/swf/model/Decision;)V
       5: return

  software.amazon.awssdk.services.swf.model.Decision$BuilderImpl(software.amazon.awssdk.services.swf.model.Decision$1);
    Code:
       0: aload_0
       1: invokespecial #1                  // Method "<init>":()V
       4: return
}
