Compiled from "EventType.java"
public final class software.amazon.awssdk.services.swf.model.EventType extends java.lang.Enum<software.amazon.awssdk.services.swf.model.EventType> {
  public static final software.amazon.awssdk.services.swf.model.EventType WORKFLOW_EXECUTION_STARTED;

  public static final software.amazon.awssdk.services.swf.model.EventType WORKFLOW_EXECUTION_CANCEL_REQUESTED;

  public static final software.amazon.awssdk.services.swf.model.EventType WORKFLOW_EXECUTION_COMPLETED;

  public static final software.amazon.awssdk.services.swf.model.EventType COMPLETE_WORKFLOW_EXECUTION_FAILED;

  public static final software.amazon.awssdk.services.swf.model.EventType WORKFLOW_EXECUTION_FAILED;

  public static final software.amazon.awssdk.services.swf.model.EventType FAIL_WORKFLOW_EXECUTION_FAILED;

  public static final software.amazon.awssdk.services.swf.model.EventType WORKFLOW_EXECUTION_TIMED_OUT;

  public static final software.amazon.awssdk.services.swf.model.EventType WORKFLOW_EXECUTION_CANCELED;

  public static final software.amazon.awssdk.services.swf.model.EventType CANCEL_WORKFLOW_EXECUTION_FAILED;

  public static final software.amazon.awssdk.services.swf.model.EventType WORKFLOW_EXECUTION_CONTINUED_AS_NEW;

  public static final software.amazon.awssdk.services.swf.model.EventType CONTINUE_AS_NEW_WORKFLOW_EXECUTION_FAILED;

  public static final software.amazon.awssdk.services.swf.model.EventType WORKFLOW_EXECUTION_TERMINATED;

  public static final software.amazon.awssdk.services.swf.model.EventType DECISION_TASK_SCHEDULED;

  public static final software.amazon.awssdk.services.swf.model.EventType DECISION_TASK_STARTED;

  public static final software.amazon.awssdk.services.swf.model.EventType DECISION_TASK_COMPLETED;

  public static final software.amazon.awssdk.services.swf.model.EventType DECISION_TASK_TIMED_OUT;

  public static final software.amazon.awssdk.services.swf.model.EventType ACTIVITY_TASK_SCHEDULED;

  public static final software.amazon.awssdk.services.swf.model.EventType SCHEDULE_ACTIVITY_TASK_FAILED;

  public static final software.amazon.awssdk.services.swf.model.EventType ACTIVITY_TASK_STARTED;

  public static final software.amazon.awssdk.services.swf.model.EventType ACTIVITY_TASK_COMPLETED;

  public static final software.amazon.awssdk.services.swf.model.EventType ACTIVITY_TASK_FAILED;

  public static final software.amazon.awssdk.services.swf.model.EventType ACTIVITY_TASK_TIMED_OUT;

  public static final software.amazon.awssdk.services.swf.model.EventType ACTIVITY_TASK_CANCELED;

  public static final software.amazon.awssdk.services.swf.model.EventType ACTIVITY_TASK_CANCEL_REQUESTED;

  public static final software.amazon.awssdk.services.swf.model.EventType REQUEST_CANCEL_ACTIVITY_TASK_FAILED;

  public static final software.amazon.awssdk.services.swf.model.EventType WORKFLOW_EXECUTION_SIGNALED;

  public static final software.amazon.awssdk.services.swf.model.EventType MARKER_RECORDED;

  public static final software.amazon.awssdk.services.swf.model.EventType RECORD_MARKER_FAILED;

  public static final software.amazon.awssdk.services.swf.model.EventType TIMER_STARTED;

  public static final software.amazon.awssdk.services.swf.model.EventType START_TIMER_FAILED;

  public static final software.amazon.awssdk.services.swf.model.EventType TIMER_FIRED;

  public static final software.amazon.awssdk.services.swf.model.EventType TIMER_CANCELED;

  public static final software.amazon.awssdk.services.swf.model.EventType CANCEL_TIMER_FAILED;

  public static final software.amazon.awssdk.services.swf.model.EventType START_CHILD_WORKFLOW_EXECUTION_INITIATED;

  public static final software.amazon.awssdk.services.swf.model.EventType START_CHILD_WORKFLOW_EXECUTION_FAILED;

  public static final software.amazon.awssdk.services.swf.model.EventType CHILD_WORKFLOW_EXECUTION_STARTED;

  public static final software.amazon.awssdk.services.swf.model.EventType CHILD_WORKFLOW_EXECUTION_COMPLETED;

  public static final software.amazon.awssdk.services.swf.model.EventType CHILD_WORKFLOW_EXECUTION_FAILED;

  public static final software.amazon.awssdk.services.swf.model.EventType CHILD_WORKFLOW_EXECUTION_TIMED_OUT;

  public static final software.amazon.awssdk.services.swf.model.EventType CHILD_WORKFLOW_EXECUTION_CANCELED;

  public static final software.amazon.awssdk.services.swf.model.EventType CHILD_WORKFLOW_EXECUTION_TERMINATED;

  public static final software.amazon.awssdk.services.swf.model.EventType SIGNAL_EXTERNAL_WORKFLOW_EXECUTION_INITIATED;

  public static final software.amazon.awssdk.services.swf.model.EventType SIGNAL_EXTERNAL_WORKFLOW_EXECUTION_FAILED;

  public static final software.amazon.awssdk.services.swf.model.EventType EXTERNAL_WORKFLOW_EXECUTION_SIGNALED;

  public static final software.amazon.awssdk.services.swf.model.EventType REQUEST_CANCEL_EXTERNAL_WORKFLOW_EXECUTION_INITIATED;

  public static final software.amazon.awssdk.services.swf.model.EventType REQUEST_CANCEL_EXTERNAL_WORKFLOW_EXECUTION_FAILED;

  public static final software.amazon.awssdk.services.swf.model.EventType EXTERNAL_WORKFLOW_EXECUTION_CANCEL_REQUESTED;

  public static final software.amazon.awssdk.services.swf.model.EventType LAMBDA_FUNCTION_SCHEDULED;

  public static final software.amazon.awssdk.services.swf.model.EventType LAMBDA_FUNCTION_STARTED;

  public static final software.amazon.awssdk.services.swf.model.EventType LAMBDA_FUNCTION_COMPLETED;

  public static final software.amazon.awssdk.services.swf.model.EventType LAMBDA_FUNCTION_FAILED;

  public static final software.amazon.awssdk.services.swf.model.EventType LAMBDA_FUNCTION_TIMED_OUT;

  public static final software.amazon.awssdk.services.swf.model.EventType SCHEDULE_LAMBDA_FUNCTION_FAILED;

  public static final software.amazon.awssdk.services.swf.model.EventType START_LAMBDA_FUNCTION_FAILED;

  public static final software.amazon.awssdk.services.swf.model.EventType UNKNOWN_TO_SDK_VERSION;

  private final java.lang.String value;

  private static final software.amazon.awssdk.services.swf.model.EventType[] $VALUES;

  public static software.amazon.awssdk.services.swf.model.EventType[] values();
    Code:
       0: getstatic     #1                  // Field $VALUES:[Lsoftware/amazon/awssdk/services/swf/model/EventType;
       3: invokevirtual #2                  // Method "[Lsoftware/amazon/awssdk/services/swf/model/EventType;".clone:()Ljava/lang/Object;
       6: checkcast     #3                  // class "[Lsoftware/amazon/awssdk/services/swf/model/EventType;"
       9: areturn

  public static software.amazon.awssdk.services.swf.model.EventType valueOf(java.lang.String);
    Code:
       0: ldc           #4                  // class software/amazon/awssdk/services/swf/model/EventType
       2: aload_0
       3: invokestatic  #5                  // Method java/lang/Enum.valueOf:(Ljava/lang/Class;Ljava/lang/String;)Ljava/lang/Enum;
       6: checkcast     #4                  // class software/amazon/awssdk/services/swf/model/EventType
       9: areturn

  private software.amazon.awssdk.services.swf.model.EventType(java.lang.String);
    Code:
       0: aload_0
       1: aload_1
       2: iload_2
       3: invokespecial #6                  // Method java/lang/Enum."<init>":(Ljava/lang/String;I)V
       6: aload_0
       7: aload_3
       8: putfield      #7                  // Field value:Ljava/lang/String;
      11: return

  public java.lang.String toString();
    Code:
       0: aload_0
       1: getfield      #7                  // Field value:Ljava/lang/String;
       4: invokestatic  #8                  // Method java/lang/String.valueOf:(Ljava/lang/Object;)Ljava/lang/String;
       7: areturn

  public static software.amazon.awssdk.services.swf.model.EventType fromValue(java.lang.String);
    Code:
       0: aload_0
       1: ifnonnull     6
       4: aconst_null
       5: areturn
       6: invokestatic  #9                  // Method values:()[Lsoftware/amazon/awssdk/services/swf/model/EventType;
       9: invokestatic  #10                 // InterfaceMethod java/util/stream/Stream.of:([Ljava/lang/Object;)Ljava/util/stream/Stream;
      12: aload_0
      13: invokedynamic #11,  0             // InvokeDynamic #0:test:(Ljava/lang/String;)Ljava/util/function/Predicate;
      18: invokeinterface #12,  2           // InterfaceMethod java/util/stream/Stream.filter:(Ljava/util/function/Predicate;)Ljava/util/stream/Stream;
      23: invokeinterface #13,  1           // InterfaceMethod java/util/stream/Stream.findFirst:()Ljava/util/Optional;
      28: getstatic     #14                 // Field UNKNOWN_TO_SDK_VERSION:Lsoftware/amazon/awssdk/services/swf/model/EventType;
      31: invokevirtual #15                 // Method java/util/Optional.orElse:(Ljava/lang/Object;)Ljava/lang/Object;
      34: checkcast     #4                  // class software/amazon/awssdk/services/swf/model/EventType
      37: areturn

  public static java.util.Set<software.amazon.awssdk.services.swf.model.EventType> knownValues();
    Code:
       0: invokestatic  #9                  // Method values:()[Lsoftware/amazon/awssdk/services/swf/model/EventType;
       3: invokestatic  #10                 // InterfaceMethod java/util/stream/Stream.of:([Ljava/lang/Object;)Ljava/util/stream/Stream;
       6: invokedynamic #16,  0             // InvokeDynamic #1:test:()Ljava/util/function/Predicate;
      11: invokeinterface #12,  2           // InterfaceMethod java/util/stream/Stream.filter:(Ljava/util/function/Predicate;)Ljava/util/stream/Stream;
      16: invokestatic  #17                 // Method java/util/stream/Collectors.toSet:()Ljava/util/stream/Collector;
      19: invokeinterface #18,  2           // InterfaceMethod java/util/stream/Stream.collect:(Ljava/util/stream/Collector;)Ljava/lang/Object;
      24: checkcast     #19                 // class java/util/Set
      27: areturn

  private static boolean lambda$knownValues$1(software.amazon.awssdk.services.swf.model.EventType);
    Code:
       0: aload_0
       1: getstatic     #14                 // Field UNKNOWN_TO_SDK_VERSION:Lsoftware/amazon/awssdk/services/swf/model/EventType;
       4: if_acmpeq     11
       7: iconst_1
       8: goto          12
      11: iconst_0
      12: ireturn

  private static boolean lambda$fromValue$0(java.lang.String, software.amazon.awssdk.services.swf.model.EventType);
    Code:
       0: aload_1
       1: invokevirtual #20                 // Method toString:()Ljava/lang/String;
       4: aload_0
       5: invokevirtual #21                 // Method java/lang/String.equals:(Ljava/lang/Object;)Z
       8: ireturn

  static {};
    Code:
       0: new           #4                  // class software/amazon/awssdk/services/swf/model/EventType
       3: dup
       4: ldc           #22                 // String WORKFLOW_EXECUTION_STARTED
       6: iconst_0
       7: ldc           #23                 // String WorkflowExecutionStarted
       9: invokespecial #24                 // Method "<init>":(Ljava/lang/String;ILjava/lang/String;)V
      12: putstatic     #25                 // Field WORKFLOW_EXECUTION_STARTED:Lsoftware/amazon/awssdk/services/swf/model/EventType;
      15: new           #4                  // class software/amazon/awssdk/services/swf/model/EventType
      18: dup
      19: ldc           #26                 // String WORKFLOW_EXECUTION_CANCEL_REQUESTED
      21: iconst_1
      22: ldc           #27                 // String WorkflowExecutionCancelRequested
      24: invokespecial #24                 // Method "<init>":(Ljava/lang/String;ILjava/lang/String;)V
      27: putstatic     #28                 // Field WORKFLOW_EXECUTION_CANCEL_REQUESTED:Lsoftware/amazon/awssdk/services/swf/model/EventType;
      30: new           #4                  // class software/amazon/awssdk/services/swf/model/EventType
      33: dup
      34: ldc           #29                 // String WORKFLOW_EXECUTION_COMPLETED
      36: iconst_2
      37: ldc           #30                 // String WorkflowExecutionCompleted
      39: invokespecial #24                 // Method "<init>":(Ljava/lang/String;ILjava/lang/String;)V
      42: putstatic     #31                 // Field WORKFLOW_EXECUTION_COMPLETED:Lsoftware/amazon/awssdk/services/swf/model/EventType;
      45: new           #4                  // class software/amazon/awssdk/services/swf/model/EventType
      48: dup
      49: ldc           #32                 // String COMPLETE_WORKFLOW_EXECUTION_FAILED
      51: iconst_3
      52: ldc           #33                 // String CompleteWorkflowExecutionFailed
      54: invokespecial #24                 // Method "<init>":(Ljava/lang/String;ILjava/lang/String;)V
      57: putstatic     #34                 // Field COMPLETE_WORKFLOW_EXECUTION_FAILED:Lsoftware/amazon/awssdk/services/swf/model/EventType;
      60: new           #4                  // class software/amazon/awssdk/services/swf/model/EventType
      63: dup
      64: ldc           #35                 // String WORKFLOW_EXECUTION_FAILED
      66: iconst_4
      67: ldc           #36                 // String WorkflowExecutionFailed
      69: invokespecial #24                 // Method "<init>":(Ljava/lang/String;ILjava/lang/String;)V
      72: putstatic     #37                 // Field WORKFLOW_EXECUTION_FAILED:Lsoftware/amazon/awssdk/services/swf/model/EventType;
      75: new           #4                  // class software/amazon/awssdk/services/swf/model/EventType
      78: dup
      79: ldc           #38                 // String FAIL_WORKFLOW_EXECUTION_FAILED
      81: iconst_5
      82: ldc           #39                 // String FailWorkflowExecutionFailed
      84: invokespecial #24                 // Method "<init>":(Ljava/lang/String;ILjava/lang/String;)V
      87: putstatic     #40                 // Field FAIL_WORKFLOW_EXECUTION_FAILED:Lsoftware/amazon/awssdk/services/swf/model/EventType;
      90: new           #4                  // class software/amazon/awssdk/services/swf/model/EventType
      93: dup
      94: ldc           #41                 // String WORKFLOW_EXECUTION_TIMED_OUT
      96: bipush        6
      98: ldc           #42                 // String WorkflowExecutionTimedOut
     100: invokespecial #24                 // Method "<init>":(Ljava/lang/String;ILjava/lang/String;)V
     103: putstatic     #43                 // Field WORKFLOW_EXECUTION_TIMED_OUT:Lsoftware/amazon/awssdk/services/swf/model/EventType;
     106: new           #4                  // class software/amazon/awssdk/services/swf/model/EventType
     109: dup
     110: ldc           #44                 // String WORKFLOW_EXECUTION_CANCELED
     112: bipush        7
     114: ldc           #45                 // String WorkflowExecutionCanceled
     116: invokespecial #24                 // Method "<init>":(Ljava/lang/String;ILjava/lang/String;)V
     119: putstatic     #46                 // Field WORKFLOW_EXECUTION_CANCELED:Lsoftware/amazon/awssdk/services/swf/model/EventType;
     122: new           #4                  // class software/amazon/awssdk/services/swf/model/EventType
     125: dup
     126: ldc           #47                 // String CANCEL_WORKFLOW_EXECUTION_FAILED
     128: bipush        8
     130: ldc           #48                 // String CancelWorkflowExecutionFailed
     132: invokespecial #24                 // Method "<init>":(Ljava/lang/String;ILjava/lang/String;)V
     135: putstatic     #49                 // Field CANCEL_WORKFLOW_EXECUTION_FAILED:Lsoftware/amazon/awssdk/services/swf/model/EventType;
     138: new           #4                  // class software/amazon/awssdk/services/swf/model/EventType
     141: dup
     142: ldc           #50                 // String WORKFLOW_EXECUTION_CONTINUED_AS_NEW
     144: bipush        9
     146: ldc           #51                 // String WorkflowExecutionContinuedAsNew
     148: invokespecial #24                 // Method "<init>":(Ljava/lang/String;ILjava/lang/String;)V
     151: putstatic     #52                 // Field WORKFLOW_EXECUTION_CONTINUED_AS_NEW:Lsoftware/amazon/awssdk/services/swf/model/EventType;
     154: new           #4                  // class software/amazon/awssdk/services/swf/model/EventType
     157: dup
     158: ldc           #53                 // String CONTINUE_AS_NEW_WORKFLOW_EXECUTION_FAILED
     160: bipush        10
     162: ldc           #54                 // String ContinueAsNewWorkflowExecutionFailed
     164: invokespecial #24                 // Method "<init>":(Ljava/lang/String;ILjava/lang/String;)V
     167: putstatic     #55                 // Field CONTINUE_AS_NEW_WORKFLOW_EXECUTION_FAILED:Lsoftware/amazon/awssdk/services/swf/model/EventType;
     170: new           #4                  // class software/amazon/awssdk/services/swf/model/EventType
     173: dup
     174: ldc           #56                 // String WORKFLOW_EXECUTION_TERMINATED
     176: bipush        11
     178: ldc           #57                 // String WorkflowExecutionTerminated
     180: invokespecial #24                 // Method "<init>":(Ljava/lang/String;ILjava/lang/String;)V
     183: putstatic     #58                 // Field WORKFLOW_EXECUTION_TERMINATED:Lsoftware/amazon/awssdk/services/swf/model/EventType;
     186: new           #4                  // class software/amazon/awssdk/services/swf/model/EventType
     189: dup
     190: ldc           #59                 // String DECISION_TASK_SCHEDULED
     192: bipush        12
     194: ldc           #60                 // String DecisionTaskScheduled
     196: invokespecial #24                 // Method "<init>":(Ljava/lang/String;ILjava/lang/String;)V
     199: putstatic     #61                 // Field DECISION_TASK_SCHEDULED:Lsoftware/amazon/awssdk/services/swf/model/EventType;
     202: new           #4                  // class software/amazon/awssdk/services/swf/model/EventType
     205: dup
     206: ldc           #62                 // String DECISION_TASK_STARTED
     208: bipush        13
     210: ldc           #63                 // String DecisionTaskStarted
     212: invokespecial #24                 // Method "<init>":(Ljava/lang/String;ILjava/lang/String;)V
     215: putstatic     #64                 // Field DECISION_TASK_STARTED:Lsoftware/amazon/awssdk/services/swf/model/EventType;
     218: new           #4                  // class software/amazon/awssdk/services/swf/model/EventType
     221: dup
     222: ldc           #65                 // String DECISION_TASK_COMPLETED
     224: bipush        14
     226: ldc           #66                 // String DecisionTaskCompleted
     228: invokespecial #24                 // Method "<init>":(Ljava/lang/String;ILjava/lang/String;)V
     231: putstatic     #67                 // Field DECISION_TASK_COMPLETED:Lsoftware/amazon/awssdk/services/swf/model/EventType;
     234: new           #4                  // class software/amazon/awssdk/services/swf/model/EventType
     237: dup
     238: ldc           #68                 // String DECISION_TASK_TIMED_OUT
     240: bipush        15
     242: ldc           #69                 // String DecisionTaskTimedOut
     244: invokespecial #24                 // Method "<init>":(Ljava/lang/String;ILjava/lang/String;)V
     247: putstatic     #70                 // Field DECISION_TASK_TIMED_OUT:Lsoftware/amazon/awssdk/services/swf/model/EventType;
     250: new           #4                  // class software/amazon/awssdk/services/swf/model/EventType
     253: dup
     254: ldc           #71                 // String ACTIVITY_TASK_SCHEDULED
     256: bipush        16
     258: ldc           #72                 // String ActivityTaskScheduled
     260: invokespecial #24                 // Method "<init>":(Ljava/lang/String;ILjava/lang/String;)V
     263: putstatic     #73                 // Field ACTIVITY_TASK_SCHEDULED:Lsoftware/amazon/awssdk/services/swf/model/EventType;
     266: new           #4                  // class software/amazon/awssdk/services/swf/model/EventType
     269: dup
     270: ldc           #74                 // String SCHEDULE_ACTIVITY_TASK_FAILED
     272: bipush        17
     274: ldc           #75                 // String ScheduleActivityTaskFailed
     276: invokespecial #24                 // Method "<init>":(Ljava/lang/String;ILjava/lang/String;)V
     279: putstatic     #76                 // Field SCHEDULE_ACTIVITY_TASK_FAILED:Lsoftware/amazon/awssdk/services/swf/model/EventType;
     282: new           #4                  // class software/amazon/awssdk/services/swf/model/EventType
     285: dup
     286: ldc           #77                 // String ACTIVITY_TASK_STARTED
     288: bipush        18
     290: ldc           #78                 // String ActivityTaskStarted
     292: invokespecial #24                 // Method "<init>":(Ljava/lang/String;ILjava/lang/String;)V
     295: putstatic     #79                 // Field ACTIVITY_TASK_STARTED:Lsoftware/amazon/awssdk/services/swf/model/EventType;
     298: new           #4                  // class software/amazon/awssdk/services/swf/model/EventType
     301: dup
     302: ldc           #80                 // String ACTIVITY_TASK_COMPLETED
     304: bipush        19
     306: ldc           #81                 // String ActivityTaskCompleted
     308: invokespecial #24                 // Method "<init>":(Ljava/lang/String;ILjava/lang/String;)V
     311: putstatic     #82                 // Field ACTIVITY_TASK_COMPLETED:Lsoftware/amazon/awssdk/services/swf/model/EventType;
     314: new           #4                  // class software/amazon/awssdk/services/swf/model/EventType
     317: dup
     318: ldc           #83                 // String ACTIVITY_TASK_FAILED
     320: bipush        20
     322: ldc           #84                 // String ActivityTaskFailed
     324: invokespecial #24                 // Method "<init>":(Ljava/lang/String;ILjava/lang/String;)V
     327: putstatic     #85                 // Field ACTIVITY_TASK_FAILED:Lsoftware/amazon/awssdk/services/swf/model/EventType;
     330: new           #4                  // class software/amazon/awssdk/services/swf/model/EventType
     333: dup
     334: ldc           #86                 // String ACTIVITY_TASK_TIMED_OUT
     336: bipush        21
     338: ldc           #87                 // String ActivityTaskTimedOut
     340: invokespecial #24                 // Method "<init>":(Ljava/lang/String;ILjava/lang/String;)V
     343: putstatic     #88                 // Field ACTIVITY_TASK_TIMED_OUT:Lsoftware/amazon/awssdk/services/swf/model/EventType;
     346: new           #4                  // class software/amazon/awssdk/services/swf/model/EventType
     349: dup
     350: ldc           #89                 // String ACTIVITY_TASK_CANCELED
     352: bipush        22
     354: ldc           #90                 // String ActivityTaskCanceled
     356: invokespecial #24                 // Method "<init>":(Ljava/lang/String;ILjava/lang/String;)V
     359: putstatic     #91                 // Field ACTIVITY_TASK_CANCELED:Lsoftware/amazon/awssdk/services/swf/model/EventType;
     362: new           #4                  // class software/amazon/awssdk/services/swf/model/EventType
     365: dup
     366: ldc           #92                 // String ACTIVITY_TASK_CANCEL_REQUESTED
     368: bipush        23
     370: ldc           #93                 // String ActivityTaskCancelRequested
     372: invokespecial #24                 // Method "<init>":(Ljava/lang/String;ILjava/lang/String;)V
     375: putstatic     #94                 // Field ACTIVITY_TASK_CANCEL_REQUESTED:Lsoftware/amazon/awssdk/services/swf/model/EventType;
     378: new           #4                  // class software/amazon/awssdk/services/swf/model/EventType
     381: dup
     382: ldc           #95                 // String REQUEST_CANCEL_ACTIVITY_TASK_FAILED
     384: bipush        24
     386: ldc           #96                 // String RequestCancelActivityTaskFailed
     388: invokespecial #24                 // Method "<init>":(Ljava/lang/String;ILjava/lang/String;)V
     391: putstatic     #97                 // Field REQUEST_CANCEL_ACTIVITY_TASK_FAILED:Lsoftware/amazon/awssdk/services/swf/model/EventType;
     394: new           #4                  // class software/amazon/awssdk/services/swf/model/EventType
     397: dup
     398: ldc           #98                 // String WORKFLOW_EXECUTION_SIGNALED
     400: bipush        25
     402: ldc           #99                 // String WorkflowExecutionSignaled
     404: invokespecial #24                 // Method "<init>":(Ljava/lang/String;ILjava/lang/String;)V
     407: putstatic     #100                // Field WORKFLOW_EXECUTION_SIGNALED:Lsoftware/amazon/awssdk/services/swf/model/EventType;
     410: new           #4                  // class software/amazon/awssdk/services/swf/model/EventType
     413: dup
     414: ldc           #101                // String MARKER_RECORDED
     416: bipush        26
     418: ldc           #102                // String MarkerRecorded
     420: invokespecial #24                 // Method "<init>":(Ljava/lang/String;ILjava/lang/String;)V
     423: putstatic     #103                // Field MARKER_RECORDED:Lsoftware/amazon/awssdk/services/swf/model/EventType;
     426: new           #4                  // class software/amazon/awssdk/services/swf/model/EventType
     429: dup
     430: ldc           #104                // String RECORD_MARKER_FAILED
     432: bipush        27
     434: ldc           #105                // String RecordMarkerFailed
     436: invokespecial #24                 // Method "<init>":(Ljava/lang/String;ILjava/lang/String;)V
     439: putstatic     #106                // Field RECORD_MARKER_FAILED:Lsoftware/amazon/awssdk/services/swf/model/EventType;
     442: new           #4                  // class software/amazon/awssdk/services/swf/model/EventType
     445: dup
     446: ldc           #107                // String TIMER_STARTED
     448: bipush        28
     450: ldc           #108                // String TimerStarted
     452: invokespecial #24                 // Method "<init>":(Ljava/lang/String;ILjava/lang/String;)V
     455: putstatic     #109                // Field TIMER_STARTED:Lsoftware/amazon/awssdk/services/swf/model/EventType;
     458: new           #4                  // class software/amazon/awssdk/services/swf/model/EventType
     461: dup
     462: ldc           #110                // String START_TIMER_FAILED
     464: bipush        29
     466: ldc           #111                // String StartTimerFailed
     468: invokespecial #24                 // Method "<init>":(Ljava/lang/String;ILjava/lang/String;)V
     471: putstatic     #112                // Field START_TIMER_FAILED:Lsoftware/amazon/awssdk/services/swf/model/EventType;
     474: new           #4                  // class software/amazon/awssdk/services/swf/model/EventType
     477: dup
     478: ldc           #113                // String TIMER_FIRED
     480: bipush        30
     482: ldc           #114                // String TimerFired
     484: invokespecial #24                 // Method "<init>":(Ljava/lang/String;ILjava/lang/String;)V
     487: putstatic     #115                // Field TIMER_FIRED:Lsoftware/amazon/awssdk/services/swf/model/EventType;
     490: new           #4                  // class software/amazon/awssdk/services/swf/model/EventType
     493: dup
     494: ldc           #116                // String TIMER_CANCELED
     496: bipush        31
     498: ldc           #117                // String TimerCanceled
     500: invokespecial #24                 // Method "<init>":(Ljava/lang/String;ILjava/lang/String;)V
     503: putstatic     #118                // Field TIMER_CANCELED:Lsoftware/amazon/awssdk/services/swf/model/EventType;
     506: new           #4                  // class software/amazon/awssdk/services/swf/model/EventType
     509: dup
     510: ldc           #119                // String CANCEL_TIMER_FAILED
     512: bipush        32
     514: ldc           #120                // String CancelTimerFailed
     516: invokespecial #24                 // Method "<init>":(Ljava/lang/String;ILjava/lang/String;)V
     519: putstatic     #121                // Field CANCEL_TIMER_FAILED:Lsoftware/amazon/awssdk/services/swf/model/EventType;
     522: new           #4                  // class software/amazon/awssdk/services/swf/model/EventType
     525: dup
     526: ldc           #122                // String START_CHILD_WORKFLOW_EXECUTION_INITIATED
     528: bipush        33
     530: ldc           #123                // String StartChildWorkflowExecutionInitiated
     532: invokespecial #24                 // Method "<init>":(Ljava/lang/String;ILjava/lang/String;)V
     535: putstatic     #124                // Field START_CHILD_WORKFLOW_EXECUTION_INITIATED:Lsoftware/amazon/awssdk/services/swf/model/EventType;
     538: new           #4                  // class software/amazon/awssdk/services/swf/model/EventType
     541: dup
     542: ldc           #125                // String START_CHILD_WORKFLOW_EXECUTION_FAILED
     544: bipush        34
     546: ldc           #126                // String StartChildWorkflowExecutionFailed
     548: invokespecial #24                 // Method "<init>":(Ljava/lang/String;ILjava/lang/String;)V
     551: putstatic     #127                // Field START_CHILD_WORKFLOW_EXECUTION_FAILED:Lsoftware/amazon/awssdk/services/swf/model/EventType;
     554: new           #4                  // class software/amazon/awssdk/services/swf/model/EventType
     557: dup
     558: ldc           #128                // String CHILD_WORKFLOW_EXECUTION_STARTED
     560: bipush        35
     562: ldc           #129                // String ChildWorkflowExecutionStarted
     564: invokespecial #24                 // Method "<init>":(Ljava/lang/String;ILjava/lang/String;)V
     567: putstatic     #130                // Field CHILD_WORKFLOW_EXECUTION_STARTED:Lsoftware/amazon/awssdk/services/swf/model/EventType;
     570: new           #4                  // class software/amazon/awssdk/services/swf/model/EventType
     573: dup
     574: ldc           #131                // String CHILD_WORKFLOW_EXECUTION_COMPLETED
     576: bipush        36
     578: ldc           #132                // String ChildWorkflowExecutionCompleted
     580: invokespecial #24                 // Method "<init>":(Ljava/lang/String;ILjava/lang/String;)V
     583: putstatic     #133                // Field CHILD_WORKFLOW_EXECUTION_COMPLETED:Lsoftware/amazon/awssdk/services/swf/model/EventType;
     586: new           #4                  // class software/amazon/awssdk/services/swf/model/EventType
     589: dup
     590: ldc           #134                // String CHILD_WORKFLOW_EXECUTION_FAILED
     592: bipush        37
     594: ldc           #135                // String ChildWorkflowExecutionFailed
     596: invokespecial #24                 // Method "<init>":(Ljava/lang/String;ILjava/lang/String;)V
     599: putstatic     #136                // Field CHILD_WORKFLOW_EXECUTION_FAILED:Lsoftware/amazon/awssdk/services/swf/model/EventType;
     602: new           #4                  // class software/amazon/awssdk/services/swf/model/EventType
     605: dup
     606: ldc           #137                // String CHILD_WORKFLOW_EXECUTION_TIMED_OUT
     608: bipush        38
     610: ldc           #138                // String ChildWorkflowExecutionTimedOut
     612: invokespecial #24                 // Method "<init>":(Ljava/lang/String;ILjava/lang/String;)V
     615: putstatic     #139                // Field CHILD_WORKFLOW_EXECUTION_TIMED_OUT:Lsoftware/amazon/awssdk/services/swf/model/EventType;
     618: new           #4                  // class software/amazon/awssdk/services/swf/model/EventType
     621: dup
     622: ldc           #140                // String CHILD_WORKFLOW_EXECUTION_CANCELED
     624: bipush        39
     626: ldc           #141                // String ChildWorkflowExecutionCanceled
     628: invokespecial #24                 // Method "<init>":(Ljava/lang/String;ILjava/lang/String;)V
     631: putstatic     #142                // Field CHILD_WORKFLOW_EXECUTION_CANCELED:Lsoftware/amazon/awssdk/services/swf/model/EventType;
     634: new           #4                  // class software/amazon/awssdk/services/swf/model/EventType
     637: dup
     638: ldc           #143                // String CHILD_WORKFLOW_EXECUTION_TERMINATED
     640: bipush        40
     642: ldc           #144                // String ChildWorkflowExecutionTerminated
     644: invokespecial #24                 // Method "<init>":(Ljava/lang/String;ILjava/lang/String;)V
     647: putstatic     #145                // Field CHILD_WORKFLOW_EXECUTION_TERMINATED:Lsoftware/amazon/awssdk/services/swf/model/EventType;
     650: new           #4                  // class software/amazon/awssdk/services/swf/model/EventType
     653: dup
     654: ldc           #146                // String SIGNAL_EXTERNAL_WORKFLOW_EXECUTION_INITIATED
     656: bipush        41
     658: ldc           #147                // String SignalExternalWorkflowExecutionInitiated
     660: invokespecial #24                 // Method "<init>":(Ljava/lang/String;ILjava/lang/String;)V
     663: putstatic     #148                // Field SIGNAL_EXTERNAL_WORKFLOW_EXECUTION_INITIATED:Lsoftware/amazon/awssdk/services/swf/model/EventType;
     666: new           #4                  // class software/amazon/awssdk/services/swf/model/EventType
     669: dup
     670: ldc           #149                // String SIGNAL_EXTERNAL_WORKFLOW_EXECUTION_FAILED
     672: bipush        42
     674: ldc           #150                // String SignalExternalWorkflowExecutionFailed
     676: invokespecial #24                 // Method "<init>":(Ljava/lang/String;ILjava/lang/String;)V
     679: putstatic     #151                // Field SIGNAL_EXTERNAL_WORKFLOW_EXECUTION_FAILED:Lsoftware/amazon/awssdk/services/swf/model/EventType;
     682: new           #4                  // class software/amazon/awssdk/services/swf/model/EventType
     685: dup
     686: ldc           #152                // String EXTERNAL_WORKFLOW_EXECUTION_SIGNALED
     688: bipush        43
     690: ldc           #153                // String ExternalWorkflowExecutionSignaled
     692: invokespecial #24                 // Method "<init>":(Ljava/lang/String;ILjava/lang/String;)V
     695: putstatic     #154                // Field EXTERNAL_WORKFLOW_EXECUTION_SIGNALED:Lsoftware/amazon/awssdk/services/swf/model/EventType;
     698: new           #4                  // class software/amazon/awssdk/services/swf/model/EventType
     701: dup
     702: ldc           #155                // String REQUEST_CANCEL_EXTERNAL_WORKFLOW_EXECUTION_INITIATED
     704: bipush        44
     706: ldc           #156                // String RequestCancelExternalWorkflowExecutionInitiated
     708: invokespecial #24                 // Method "<init>":(Ljava/lang/String;ILjava/lang/String;)V
     711: putstatic     #157                // Field REQUEST_CANCEL_EXTERNAL_WORKFLOW_EXECUTION_INITIATED:Lsoftware/amazon/awssdk/services/swf/model/EventType;
     714: new           #4                  // class software/amazon/awssdk/services/swf/model/EventType
     717: dup
     718: ldc           #158                // String REQUEST_CANCEL_EXTERNAL_WORKFLOW_EXECUTION_FAILED
     720: bipush        45
     722: ldc           #159                // String RequestCancelExternalWorkflowExecutionFailed
     724: invokespecial #24                 // Method "<init>":(Ljava/lang/String;ILjava/lang/String;)V
     727: putstatic     #160                // Field REQUEST_CANCEL_EXTERNAL_WORKFLOW_EXECUTION_FAILED:Lsoftware/amazon/awssdk/services/swf/model/EventType;
     730: new           #4                  // class software/amazon/awssdk/services/swf/model/EventType
     733: dup
     734: ldc           #161                // String EXTERNAL_WORKFLOW_EXECUTION_CANCEL_REQUESTED
     736: bipush        46
     738: ldc           #162                // String ExternalWorkflowExecutionCancelRequested
     740: invokespecial #24                 // Method "<init>":(Ljava/lang/String;ILjava/lang/String;)V
     743: putstatic     #163                // Field EXTERNAL_WORKFLOW_EXECUTION_CANCEL_REQUESTED:Lsoftware/amazon/awssdk/services/swf/model/EventType;
     746: new           #4                  // class software/amazon/awssdk/services/swf/model/EventType
     749: dup
     750: ldc           #164                // String LAMBDA_FUNCTION_SCHEDULED
     752: bipush        47
     754: ldc           #165                // String LambdaFunctionScheduled
     756: invokespecial #24                 // Method "<init>":(Ljava/lang/String;ILjava/lang/String;)V
     759: putstatic     #166                // Field LAMBDA_FUNCTION_SCHEDULED:Lsoftware/amazon/awssdk/services/swf/model/EventType;
     762: new           #4                  // class software/amazon/awssdk/services/swf/model/EventType
     765: dup
     766: ldc           #167                // String LAMBDA_FUNCTION_STARTED
     768: bipush        48
     770: ldc           #168                // String LambdaFunctionStarted
     772: invokespecial #24                 // Method "<init>":(Ljava/lang/String;ILjava/lang/String;)V
     775: putstatic     #169                // Field LAMBDA_FUNCTION_STARTED:Lsoftware/amazon/awssdk/services/swf/model/EventType;
     778: new           #4                  // class software/amazon/awssdk/services/swf/model/EventType
     781: dup
     782: ldc           #170                // String LAMBDA_FUNCTION_COMPLETED
     784: bipush        49
     786: ldc           #171                // String LambdaFunctionCompleted
     788: invokespecial #24                 // Method "<init>":(Ljava/lang/String;ILjava/lang/String;)V
     791: putstatic     #172                // Field LAMBDA_FUNCTION_COMPLETED:Lsoftware/amazon/awssdk/services/swf/model/EventType;
     794: new           #4                  // class software/amazon/awssdk/services/swf/model/EventType
     797: dup
     798: ldc           #173                // String LAMBDA_FUNCTION_FAILED
     800: bipush        50
     802: ldc           #174                // String LambdaFunctionFailed
     804: invokespecial #24                 // Method "<init>":(Ljava/lang/String;ILjava/lang/String;)V
     807: putstatic     #175                // Field LAMBDA_FUNCTION_FAILED:Lsoftware/amazon/awssdk/services/swf/model/EventType;
     810: new           #4                  // class software/amazon/awssdk/services/swf/model/EventType
     813: dup
     814: ldc           #176                // String LAMBDA_FUNCTION_TIMED_OUT
     816: bipush        51
     818: ldc           #177                // String LambdaFunctionTimedOut
     820: invokespecial #24                 // Method "<init>":(Ljava/lang/String;ILjava/lang/String;)V
     823: putstatic     #178                // Field LAMBDA_FUNCTION_TIMED_OUT:Lsoftware/amazon/awssdk/services/swf/model/EventType;
     826: new           #4                  // class software/amazon/awssdk/services/swf/model/EventType
     829: dup
     830: ldc           #179                // String SCHEDULE_LAMBDA_FUNCTION_FAILED
     832: bipush        52
     834: ldc           #180                // String ScheduleLambdaFunctionFailed
     836: invokespecial #24                 // Method "<init>":(Ljava/lang/String;ILjava/lang/String;)V
     839: putstatic     #181                // Field SCHEDULE_LAMBDA_FUNCTION_FAILED:Lsoftware/amazon/awssdk/services/swf/model/EventType;
     842: new           #4                  // class software/amazon/awssdk/services/swf/model/EventType
     845: dup
     846: ldc           #182                // String START_LAMBDA_FUNCTION_FAILED
     848: bipush        53
     850: ldc           #183                // String StartLambdaFunctionFailed
     852: invokespecial #24                 // Method "<init>":(Ljava/lang/String;ILjava/lang/String;)V
     855: putstatic     #184                // Field START_LAMBDA_FUNCTION_FAILED:Lsoftware/amazon/awssdk/services/swf/model/EventType;
     858: new           #4                  // class software/amazon/awssdk/services/swf/model/EventType
     861: dup
     862: ldc           #185                // String UNKNOWN_TO_SDK_VERSION
     864: bipush        54
     866: aconst_null
     867: invokespecial #24                 // Method "<init>":(Ljava/lang/String;ILjava/lang/String;)V
     870: putstatic     #14                 // Field UNKNOWN_TO_SDK_VERSION:Lsoftware/amazon/awssdk/services/swf/model/EventType;
     873: bipush        55
     875: anewarray     #4                  // class software/amazon/awssdk/services/swf/model/EventType
     878: dup
     879: iconst_0
     880: getstatic     #25                 // Field WORKFLOW_EXECUTION_STARTED:Lsoftware/amazon/awssdk/services/swf/model/EventType;
     883: aastore
     884: dup
     885: iconst_1
     886: getstatic     #28                 // Field WORKFLOW_EXECUTION_CANCEL_REQUESTED:Lsoftware/amazon/awssdk/services/swf/model/EventType;
     889: aastore
     890: dup
     891: iconst_2
     892: getstatic     #31                 // Field WORKFLOW_EXECUTION_COMPLETED:Lsoftware/amazon/awssdk/services/swf/model/EventType;
     895: aastore
     896: dup
     897: iconst_3
     898: getstatic     #34                 // Field COMPLETE_WORKFLOW_EXECUTION_FAILED:Lsoftware/amazon/awssdk/services/swf/model/EventType;
     901: aastore
     902: dup
     903: iconst_4
     904: getstatic     #37                 // Field WORKFLOW_EXECUTION_FAILED:Lsoftware/amazon/awssdk/services/swf/model/EventType;
     907: aastore
     908: dup
     909: iconst_5
     910: getstatic     #40                 // Field FAIL_WORKFLOW_EXECUTION_FAILED:Lsoftware/amazon/awssdk/services/swf/model/EventType;
     913: aastore
     914: dup
     915: bipush        6
     917: getstatic     #43                 // Field WORKFLOW_EXECUTION_TIMED_OUT:Lsoftware/amazon/awssdk/services/swf/model/EventType;
     920: aastore
     921: dup
     922: bipush        7
     924: getstatic     #46                 // Field WORKFLOW_EXECUTION_CANCELED:Lsoftware/amazon/awssdk/services/swf/model/EventType;
     927: aastore
     928: dup
     929: bipush        8
     931: getstatic     #49                 // Field CANCEL_WORKFLOW_EXECUTION_FAILED:Lsoftware/amazon/awssdk/services/swf/model/EventType;
     934: aastore
     935: dup
     936: bipush        9
     938: getstatic     #52                 // Field WORKFLOW_EXECUTION_CONTINUED_AS_NEW:Lsoftware/amazon/awssdk/services/swf/model/EventType;
     941: aastore
     942: dup
     943: bipush        10
     945: getstatic     #55                 // Field CONTINUE_AS_NEW_WORKFLOW_EXECUTION_FAILED:Lsoftware/amazon/awssdk/services/swf/model/EventType;
     948: aastore
     949: dup
     950: bipush        11
     952: getstatic     #58                 // Field WORKFLOW_EXECUTION_TERMINATED:Lsoftware/amazon/awssdk/services/swf/model/EventType;
     955: aastore
     956: dup
     957: bipush        12
     959: getstatic     #61                 // Field DECISION_TASK_SCHEDULED:Lsoftware/amazon/awssdk/services/swf/model/EventType;
     962: aastore
     963: dup
     964: bipush        13
     966: getstatic     #64                 // Field DECISION_TASK_STARTED:Lsoftware/amazon/awssdk/services/swf/model/EventType;
     969: aastore
     970: dup
     971: bipush        14
     973: getstatic     #67                 // Field DECISION_TASK_COMPLETED:Lsoftware/amazon/awssdk/services/swf/model/EventType;
     976: aastore
     977: dup
     978: bipush        15
     980: getstatic     #70                 // Field DECISION_TASK_TIMED_OUT:Lsoftware/amazon/awssdk/services/swf/model/EventType;
     983: aastore
     984: dup
     985: bipush        16
     987: getstatic     #73                 // Field ACTIVITY_TASK_SCHEDULED:Lsoftware/amazon/awssdk/services/swf/model/EventType;
     990: aastore
     991: dup
     992: bipush        17
     994: getstatic     #76                 // Field SCHEDULE_ACTIVITY_TASK_FAILED:Lsoftware/amazon/awssdk/services/swf/model/EventType;
     997: aastore
     998: dup
     999: bipush        18
    1001: getstatic     #79                 // Field ACTIVITY_TASK_STARTED:Lsoftware/amazon/awssdk/services/swf/model/EventType;
    1004: aastore
    1005: dup
    1006: bipush        19
    1008: getstatic     #82                 // Field ACTIVITY_TASK_COMPLETED:Lsoftware/amazon/awssdk/services/swf/model/EventType;
    1011: aastore
    1012: dup
    1013: bipush        20
    1015: getstatic     #85                 // Field ACTIVITY_TASK_FAILED:Lsoftware/amazon/awssdk/services/swf/model/EventType;
    1018: aastore
    1019: dup
    1020: bipush        21
    1022: getstatic     #88                 // Field ACTIVITY_TASK_TIMED_OUT:Lsoftware/amazon/awssdk/services/swf/model/EventType;
    1025: aastore
    1026: dup
    1027: bipush        22
    1029: getstatic     #91                 // Field ACTIVITY_TASK_CANCELED:Lsoftware/amazon/awssdk/services/swf/model/EventType;
    1032: aastore
    1033: dup
    1034: bipush        23
    1036: getstatic     #94                 // Field ACTIVITY_TASK_CANCEL_REQUESTED:Lsoftware/amazon/awssdk/services/swf/model/EventType;
    1039: aastore
    1040: dup
    1041: bipush        24
    1043: getstatic     #97                 // Field REQUEST_CANCEL_ACTIVITY_TASK_FAILED:Lsoftware/amazon/awssdk/services/swf/model/EventType;
    1046: aastore
    1047: dup
    1048: bipush        25
    1050: getstatic     #100                // Field WORKFLOW_EXECUTION_SIGNALED:Lsoftware/amazon/awssdk/services/swf/model/EventType;
    1053: aastore
    1054: dup
    1055: bipush        26
    1057: getstatic     #103                // Field MARKER_RECORDED:Lsoftware/amazon/awssdk/services/swf/model/EventType;
    1060: aastore
    1061: dup
    1062: bipush        27
    1064: getstatic     #106                // Field RECORD_MARKER_FAILED:Lsoftware/amazon/awssdk/services/swf/model/EventType;
    1067: aastore
    1068: dup
    1069: bipush        28
    1071: getstatic     #109                // Field TIMER_STARTED:Lsoftware/amazon/awssdk/services/swf/model/EventType;
    1074: aastore
    1075: dup
    1076: bipush        29
    1078: getstatic     #112                // Field START_TIMER_FAILED:Lsoftware/amazon/awssdk/services/swf/model/EventType;
    1081: aastore
    1082: dup
    1083: bipush        30
    1085: getstatic     #115                // Field TIMER_FIRED:Lsoftware/amazon/awssdk/services/swf/model/EventType;
    1088: aastore
    1089: dup
    1090: bipush        31
    1092: getstatic     #118                // Field TIMER_CANCELED:Lsoftware/amazon/awssdk/services/swf/model/EventType;
    1095: aastore
    1096: dup
    1097: bipush        32
    1099: getstatic     #121                // Field CANCEL_TIMER_FAILED:Lsoftware/amazon/awssdk/services/swf/model/EventType;
    1102: aastore
    1103: dup
    1104: bipush        33
    1106: getstatic     #124                // Field START_CHILD_WORKFLOW_EXECUTION_INITIATED:Lsoftware/amazon/awssdk/services/swf/model/EventType;
    1109: aastore
    1110: dup
    1111: bipush        34
    1113: getstatic     #127                // Field START_CHILD_WORKFLOW_EXECUTION_FAILED:Lsoftware/amazon/awssdk/services/swf/model/EventType;
    1116: aastore
    1117: dup
    1118: bipush        35
    1120: getstatic     #130                // Field CHILD_WORKFLOW_EXECUTION_STARTED:Lsoftware/amazon/awssdk/services/swf/model/EventType;
    1123: aastore
    1124: dup
    1125: bipush        36
    1127: getstatic     #133                // Field CHILD_WORKFLOW_EXECUTION_COMPLETED:Lsoftware/amazon/awssdk/services/swf/model/EventType;
    1130: aastore
    1131: dup
    1132: bipush        37
    1134: getstatic     #136                // Field CHILD_WORKFLOW_EXECUTION_FAILED:Lsoftware/amazon/awssdk/services/swf/model/EventType;
    1137: aastore
    1138: dup
    1139: bipush        38
    1141: getstatic     #139                // Field CHILD_WORKFLOW_EXECUTION_TIMED_OUT:Lsoftware/amazon/awssdk/services/swf/model/EventType;
    1144: aastore
    1145: dup
    1146: bipush        39
    1148: getstatic     #142                // Field CHILD_WORKFLOW_EXECUTION_CANCELED:Lsoftware/amazon/awssdk/services/swf/model/EventType;
    1151: aastore
    1152: dup
    1153: bipush        40
    1155: getstatic     #145                // Field CHILD_WORKFLOW_EXECUTION_TERMINATED:Lsoftware/amazon/awssdk/services/swf/model/EventType;
    1158: aastore
    1159: dup
    1160: bipush        41
    1162: getstatic     #148                // Field SIGNAL_EXTERNAL_WORKFLOW_EXECUTION_INITIATED:Lsoftware/amazon/awssdk/services/swf/model/EventType;
    1165: aastore
    1166: dup
    1167: bipush        42
    1169: getstatic     #151                // Field SIGNAL_EXTERNAL_WORKFLOW_EXECUTION_FAILED:Lsoftware/amazon/awssdk/services/swf/model/EventType;
    1172: aastore
    1173: dup
    1174: bipush        43
    1176: getstatic     #154                // Field EXTERNAL_WORKFLOW_EXECUTION_SIGNALED:Lsoftware/amazon/awssdk/services/swf/model/EventType;
    1179: aastore
    1180: dup
    1181: bipush        44
    1183: getstatic     #157                // Field REQUEST_CANCEL_EXTERNAL_WORKFLOW_EXECUTION_INITIATED:Lsoftware/amazon/awssdk/services/swf/model/EventType;
    1186: aastore
    1187: dup
    1188: bipush        45
    1190: getstatic     #160                // Field REQUEST_CANCEL_EXTERNAL_WORKFLOW_EXECUTION_FAILED:Lsoftware/amazon/awssdk/services/swf/model/EventType;
    1193: aastore
    1194: dup
    1195: bipush        46
    1197: getstatic     #163                // Field EXTERNAL_WORKFLOW_EXECUTION_CANCEL_REQUESTED:Lsoftware/amazon/awssdk/services/swf/model/EventType;
    1200: aastore
    1201: dup
    1202: bipush        47
    1204: getstatic     #166                // Field LAMBDA_FUNCTION_SCHEDULED:Lsoftware/amazon/awssdk/services/swf/model/EventType;
    1207: aastore
    1208: dup
    1209: bipush        48
    1211: getstatic     #169                // Field LAMBDA_FUNCTION_STARTED:Lsoftware/amazon/awssdk/services/swf/model/EventType;
    1214: aastore
    1215: dup
    1216: bipush        49
    1218: getstatic     #172                // Field LAMBDA_FUNCTION_COMPLETED:Lsoftware/amazon/awssdk/services/swf/model/EventType;
    1221: aastore
    1222: dup
    1223: bipush        50
    1225: getstatic     #175                // Field LAMBDA_FUNCTION_FAILED:Lsoftware/amazon/awssdk/services/swf/model/EventType;
    1228: aastore
    1229: dup
    1230: bipush        51
    1232: getstatic     #178                // Field LAMBDA_FUNCTION_TIMED_OUT:Lsoftware/amazon/awssdk/services/swf/model/EventType;
    1235: aastore
    1236: dup
    1237: bipush        52
    1239: getstatic     #181                // Field SCHEDULE_LAMBDA_FUNCTION_FAILED:Lsoftware/amazon/awssdk/services/swf/model/EventType;
    1242: aastore
    1243: dup
    1244: bipush        53
    1246: getstatic     #184                // Field START_LAMBDA_FUNCTION_FAILED:Lsoftware/amazon/awssdk/services/swf/model/EventType;
    1249: aastore
    1250: dup
    1251: bipush        54
    1253: getstatic     #14                 // Field UNKNOWN_TO_SDK_VERSION:Lsoftware/amazon/awssdk/services/swf/model/EventType;
    1256: aastore
    1257: putstatic     #1                  // Field $VALUES:[Lsoftware/amazon/awssdk/services/swf/model/EventType;
    1260: return
}
