Compiled from "ExternalWorkflowExecutionCancelRequestedEventAttributes.java"
final class software.amazon.awssdk.services.swf.model.ExternalWorkflowExecutionCancelRequestedEventAttributes$BuilderImpl implements software.amazon.awssdk.services.swf.model.ExternalWorkflowExecutionCancelRequestedEventAttributes$Builder {
  private software.amazon.awssdk.services.swf.model.WorkflowExecution workflowExecution;

  private java.lang.Long initiatedEventId;

  private software.amazon.awssdk.services.swf.model.ExternalWorkflowExecutionCancelRequestedEventAttributes$BuilderImpl();
    Code:
       0: aload_0
       1: invokespecial #5                  // Method java/lang/Object."<init>":()V
       4: return

  private software.amazon.awssdk.services.swf.model.ExternalWorkflowExecutionCancelRequestedEventAttributes$BuilderImpl(software.amazon.awssdk.services.swf.model.ExternalWorkflowExecutionCancelRequestedEventAttributes);
    Code:
       0: aload_0
       1: invokespecial #5                  // Method java/lang/Object."<init>":()V
       4: aload_0
       5: aload_1
       6: invokestatic  #6                  // Method software/amazon/awssdk/services/swf/model/ExternalWorkflowExecutionCancelRequestedEventAttributes.access$400:(Lsoftware/amazon/awssdk/services/swf/model/ExternalWorkflowExecutionCancelRequestedEventAttributes;)Lsoftware/amazon/awssdk/services/swf/model/WorkflowExecution;
       9: invokevirtual #7                  // Method workflowExecution:(Lsoftware/amazon/awssdk/services/swf/model/WorkflowExecution;)Lsoftware/amazon/awssdk/services/swf/model/ExternalWorkflowExecutionCancelRequestedEventAttributes$Builder;
      12: pop
      13: aload_0
      14: aload_1
      15: invokestatic  #8                  // Method software/amazon/awssdk/services/swf/model/ExternalWorkflowExecutionCancelRequestedEventAttributes.access$500:(Lsoftware/amazon/awssdk/services/swf/model/ExternalWorkflowExecutionCancelRequestedEventAttributes;)Ljava/lang/Long;
      18: invokevirtual #9                  // Method initiatedEventId:(Ljava/lang/Long;)Lsoftware/amazon/awssdk/services/swf/model/ExternalWorkflowExecutionCancelRequestedEventAttributes$Builder;
      21: pop
      22: return

  public final software.amazon.awssdk.services.swf.model.WorkflowExecution$Builder getWorkflowExecution();
    Code:
       0: aload_0
       1: getfield      #4                  // Field workflowExecution:Lsoftware/amazon/awssdk/services/swf/model/WorkflowExecution;
       4: ifnull        17
       7: aload_0
       8: getfield      #4                  // Field workflowExecution:Lsoftware/amazon/awssdk/services/swf/model/WorkflowExecution;
      11: invokevirtual #10                 // Method software/amazon/awssdk/services/swf/model/WorkflowExecution.toBuilder:()Lsoftware/amazon/awssdk/services/swf/model/WorkflowExecution$Builder;
      14: goto          18
      17: aconst_null
      18: areturn

  public final software.amazon.awssdk.services.swf.model.ExternalWorkflowExecutionCancelRequestedEventAttributes$Builder workflowExecution(software.amazon.awssdk.services.swf.model.WorkflowExecution);
    Code:
       0: aload_0
       1: aload_1
       2: putfield      #4                  // Field workflowExecution:Lsoftware/amazon/awssdk/services/swf/model/WorkflowExecution;
       5: aload_0
       6: areturn

  public final void setWorkflowExecution(software.amazon.awssdk.services.swf.model.WorkflowExecution$BuilderImpl);
    Code:
       0: aload_0
       1: aload_1
       2: ifnull        12
       5: aload_1
       6: invokevirtual #11                 // Method software/amazon/awssdk/services/swf/model/WorkflowExecution$BuilderImpl.build:()Lsoftware/amazon/awssdk/services/swf/model/WorkflowExecution;
       9: goto          13
      12: aconst_null
      13: putfield      #4                  // Field workflowExecution:Lsoftware/amazon/awssdk/services/swf/model/WorkflowExecution;
      16: return

  public final java.lang.Long getInitiatedEventId();
    Code:
       0: aload_0
       1: getfield      #3                  // Field initiatedEventId:Ljava/lang/Long;
       4: areturn

  public final software.amazon.awssdk.services.swf.model.ExternalWorkflowExecutionCancelRequestedEventAttributes$Builder initiatedEventId(java.lang.Long);
    Code:
       0: aload_0
       1: aload_1
       2: putfield      #3                  // Field initiatedEventId:Ljava/lang/Long;
       5: aload_0
       6: areturn

  public final void setInitiatedEventId(java.lang.Long);
    Code:
       0: aload_0
       1: aload_1
       2: putfield      #3                  // Field initiatedEventId:Ljava/lang/Long;
       5: return

  public software.amazon.awssdk.services.swf.model.ExternalWorkflowExecutionCancelRequestedEventAttributes build();
    Code:
       0: new           #12                 // class software/amazon/awssdk/services/swf/model/ExternalWorkflowExecutionCancelRequestedEventAttributes
       3: dup
       4: aload_0
       5: aconst_null
       6: invokespecial #13                 // Method software/amazon/awssdk/services/swf/model/ExternalWorkflowExecutionCancelRequestedEventAttributes."<init>":(Lsoftware/amazon/awssdk/services/swf/model/ExternalWorkflowExecutionCancelRequestedEventAttributes$BuilderImpl;Lsoftware/amazon/awssdk/services/swf/model/ExternalWorkflowExecutionCancelRequestedEventAttributes$1;)V
       9: areturn

  public java.util.List<software.amazon.awssdk.core.SdkField<?>> sdkFields();
    Code:
       0: invokestatic  #14                 // Method software/amazon/awssdk/services/swf/model/ExternalWorkflowExecutionCancelRequestedEventAttributes.access$700:()Ljava/util/List;
       3: areturn

  public java.lang.Object build();
    Code:
       0: aload_0
       1: invokevirtual #15                 // Method build:()Lsoftware/amazon/awssdk/services/swf/model/ExternalWorkflowExecutionCancelRequestedEventAttributes;
       4: areturn

  static software.amazon.awssdk.services.swf.model.WorkflowExecution access$000(software.amazon.awssdk.services.swf.model.ExternalWorkflowExecutionCancelRequestedEventAttributes$BuilderImpl);
    Code:
       0: aload_0
       1: getfield      #4                  // Field workflowExecution:Lsoftware/amazon/awssdk/services/swf/model/WorkflowExecution;
       4: areturn

  static java.lang.Long access$100(software.amazon.awssdk.services.swf.model.ExternalWorkflowExecutionCancelRequestedEventAttributes$BuilderImpl);
    Code:
       0: aload_0
       1: getfield      #3                  // Field initiatedEventId:Ljava/lang/Long;
       4: areturn

  software.amazon.awssdk.services.swf.model.ExternalWorkflowExecutionCancelRequestedEventAttributes$BuilderImpl(software.amazon.awssdk.services.swf.model.ExternalWorkflowExecutionCancelRequestedEventAttributes, software.amazon.awssdk.services.swf.model.ExternalWorkflowExecutionCancelRequestedEventAttributes$1);
    Code:
       0: aload_0
       1: aload_1
       2: invokespecial #2                  // Method "<init>":(Lsoftware/amazon/awssdk/services/swf/model/ExternalWorkflowExecutionCancelRequestedEventAttributes;)V
       5: return

  software.amazon.awssdk.services.swf.model.ExternalWorkflowExecutionCancelRequestedEventAttributes$BuilderImpl(software.amazon.awssdk.services.swf.model.ExternalWorkflowExecutionCancelRequestedEventAttributes$1);
    Code:
       0: aload_0
       1: invokespecial #1                  // Method "<init>":()V
       4: return
}
