Compiled from "ScheduleActivityTaskFailedEventAttributes.java"
final class software.amazon.awssdk.services.swf.model.ScheduleActivityTaskFailedEventAttributes$BuilderImpl implements software.amazon.awssdk.services.swf.model.ScheduleActivityTaskFailedEventAttributes$Builder {
  private software.amazon.awssdk.services.swf.model.ActivityType activityType;

  private java.lang.String activityId;

  private java.lang.String causeValue;

  private java.lang.Long decisionTaskCompletedEventId;

  private software.amazon.awssdk.services.swf.model.ScheduleActivityTaskFailedEventAttributes$BuilderImpl();
    Code:
       0: aload_0
       1: invokespecial #7                  // Method java/lang/Object."<init>":()V
       4: return

  private software.amazon.awssdk.services.swf.model.ScheduleActivityTaskFailedEventAttributes$BuilderImpl(software.amazon.awssdk.services.swf.model.ScheduleActivityTaskFailedEventAttributes);
    Code:
       0: aload_0
       1: invokespecial #7                  // Method java/lang/Object."<init>":()V
       4: aload_0
       5: aload_1
       6: invokestatic  #8                  // Method software/amazon/awssdk/services/swf/model/ScheduleActivityTaskFailedEventAttributes.access$600:(Lsoftware/amazon/awssdk/services/swf/model/ScheduleActivityTaskFailedEventAttributes;)Lsoftware/amazon/awssdk/services/swf/model/ActivityType;
       9: invokevirtual #9                  // Method activityType:(Lsoftware/amazon/awssdk/services/swf/model/ActivityType;)Lsoftware/amazon/awssdk/services/swf/model/ScheduleActivityTaskFailedEventAttributes$Builder;
      12: pop
      13: aload_0
      14: aload_1
      15: invokestatic  #10                 // Method software/amazon/awssdk/services/swf/model/ScheduleActivityTaskFailedEventAttributes.access$700:(Lsoftware/amazon/awssdk/services/swf/model/ScheduleActivityTaskFailedEventAttributes;)Ljava/lang/String;
      18: invokevirtual #11                 // Method activityId:(Ljava/lang/String;)Lsoftware/amazon/awssdk/services/swf/model/ScheduleActivityTaskFailedEventAttributes$Builder;
      21: pop
      22: aload_0
      23: aload_1
      24: invokestatic  #12                 // Method software/amazon/awssdk/services/swf/model/ScheduleActivityTaskFailedEventAttributes.access$800:(Lsoftware/amazon/awssdk/services/swf/model/ScheduleActivityTaskFailedEventAttributes;)Ljava/lang/String;
      27: invokevirtual #13                 // Method cause:(Ljava/lang/String;)Lsoftware/amazon/awssdk/services/swf/model/ScheduleActivityTaskFailedEventAttributes$Builder;
      30: pop
      31: aload_0
      32: aload_1
      33: invokestatic  #14                 // Method software/amazon/awssdk/services/swf/model/ScheduleActivityTaskFailedEventAttributes.access$900:(Lsoftware/amazon/awssdk/services/swf/model/ScheduleActivityTaskFailedEventAttributes;)Ljava/lang/Long;
      36: invokevirtual #15                 // Method decisionTaskCompletedEventId:(Ljava/lang/Long;)Lsoftware/amazon/awssdk/services/swf/model/ScheduleActivityTaskFailedEventAttributes$Builder;
      39: pop
      40: return

  public final software.amazon.awssdk.services.swf.model.ActivityType$Builder getActivityType();
    Code:
       0: aload_0
       1: getfield      #6                  // Field activityType:Lsoftware/amazon/awssdk/services/swf/model/ActivityType;
       4: ifnull        17
       7: aload_0
       8: getfield      #6                  // Field activityType:Lsoftware/amazon/awssdk/services/swf/model/ActivityType;
      11: invokevirtual #16                 // Method software/amazon/awssdk/services/swf/model/ActivityType.toBuilder:()Lsoftware/amazon/awssdk/services/swf/model/ActivityType$Builder;
      14: goto          18
      17: aconst_null
      18: areturn

  public final software.amazon.awssdk.services.swf.model.ScheduleActivityTaskFailedEventAttributes$Builder activityType(software.amazon.awssdk.services.swf.model.ActivityType);
    Code:
       0: aload_0
       1: aload_1
       2: putfield      #6                  // Field activityType:Lsoftware/amazon/awssdk/services/swf/model/ActivityType;
       5: aload_0
       6: areturn

  public final void setActivityType(software.amazon.awssdk.services.swf.model.ActivityType$BuilderImpl);
    Code:
       0: aload_0
       1: aload_1
       2: ifnull        12
       5: aload_1
       6: invokevirtual #17                 // Method software/amazon/awssdk/services/swf/model/ActivityType$BuilderImpl.build:()Lsoftware/amazon/awssdk/services/swf/model/ActivityType;
       9: goto          13
      12: aconst_null
      13: putfield      #6                  // Field activityType:Lsoftware/amazon/awssdk/services/swf/model/ActivityType;
      16: return

  public final java.lang.String getActivityId();
    Code:
       0: aload_0
       1: getfield      #5                  // Field activityId:Ljava/lang/String;
       4: areturn

  public final software.amazon.awssdk.services.swf.model.ScheduleActivityTaskFailedEventAttributes$Builder activityId(java.lang.String);
    Code:
       0: aload_0
       1: aload_1
       2: putfield      #5                  // Field activityId:Ljava/lang/String;
       5: aload_0
       6: areturn

  public final void setActivityId(java.lang.String);
    Code:
       0: aload_0
       1: aload_1
       2: putfield      #5                  // Field activityId:Ljava/lang/String;
       5: return

  public final java.lang.String getCauseAsString();
    Code:
       0: aload_0
       1: getfield      #4                  // Field causeValue:Ljava/lang/String;
       4: areturn

  public final software.amazon.awssdk.services.swf.model.ScheduleActivityTaskFailedEventAttributes$Builder cause(java.lang.String);
    Code:
       0: aload_0
       1: aload_1
       2: putfield      #4                  // Field causeValue:Ljava/lang/String;
       5: aload_0
       6: areturn

  public final software.amazon.awssdk.services.swf.model.ScheduleActivityTaskFailedEventAttributes$Builder cause(software.amazon.awssdk.services.swf.model.ScheduleActivityTaskFailedCause);
    Code:
       0: aload_0
       1: aload_1
       2: ifnonnull     9
       5: aconst_null
       6: goto          13
       9: aload_1
      10: invokevirtual #18                 // Method software/amazon/awssdk/services/swf/model/ScheduleActivityTaskFailedCause.toString:()Ljava/lang/String;
      13: invokevirtual #13                 // Method cause:(Ljava/lang/String;)Lsoftware/amazon/awssdk/services/swf/model/ScheduleActivityTaskFailedEventAttributes$Builder;
      16: pop
      17: aload_0
      18: areturn

  public final void setCause(java.lang.String);
    Code:
       0: aload_0
       1: aload_1
       2: putfield      #4                  // Field causeValue:Ljava/lang/String;
       5: return

  public final java.lang.Long getDecisionTaskCompletedEventId();
    Code:
       0: aload_0
       1: getfield      #3                  // Field decisionTaskCompletedEventId:Ljava/lang/Long;
       4: areturn

  public final software.amazon.awssdk.services.swf.model.ScheduleActivityTaskFailedEventAttributes$Builder decisionTaskCompletedEventId(java.lang.Long);
    Code:
       0: aload_0
       1: aload_1
       2: putfield      #3                  // Field decisionTaskCompletedEventId:Ljava/lang/Long;
       5: aload_0
       6: areturn

  public final void setDecisionTaskCompletedEventId(java.lang.Long);
    Code:
       0: aload_0
       1: aload_1
       2: putfield      #3                  // Field decisionTaskCompletedEventId:Ljava/lang/Long;
       5: return

  public software.amazon.awssdk.services.swf.model.ScheduleActivityTaskFailedEventAttributes build();
    Code:
       0: new           #19                 // class software/amazon/awssdk/services/swf/model/ScheduleActivityTaskFailedEventAttributes
       3: dup
       4: aload_0
       5: aconst_null
       6: invokespecial #20                 // Method software/amazon/awssdk/services/swf/model/ScheduleActivityTaskFailedEventAttributes."<init>":(Lsoftware/amazon/awssdk/services/swf/model/ScheduleActivityTaskFailedEventAttributes$BuilderImpl;Lsoftware/amazon/awssdk/services/swf/model/ScheduleActivityTaskFailedEventAttributes$1;)V
       9: areturn

  public java.util.List<software.amazon.awssdk.core.SdkField<?>> sdkFields();
    Code:
       0: invokestatic  #21                 // Method software/amazon/awssdk/services/swf/model/ScheduleActivityTaskFailedEventAttributes.access$1100:()Ljava/util/List;
       3: areturn

  public java.lang.Object build();
    Code:
       0: aload_0
       1: invokevirtual #22                 // Method build:()Lsoftware/amazon/awssdk/services/swf/model/ScheduleActivityTaskFailedEventAttributes;
       4: areturn

  static software.amazon.awssdk.services.swf.model.ActivityType access$000(software.amazon.awssdk.services.swf.model.ScheduleActivityTaskFailedEventAttributes$BuilderImpl);
    Code:
       0: aload_0
       1: getfield      #6                  // Field activityType:Lsoftware/amazon/awssdk/services/swf/model/ActivityType;
       4: areturn

  static java.lang.String access$100(software.amazon.awssdk.services.swf.model.ScheduleActivityTaskFailedEventAttributes$BuilderImpl);
    Code:
       0: aload_0
       1: getfield      #5                  // Field activityId:Ljava/lang/String;
       4: areturn

  static java.lang.String access$200(software.amazon.awssdk.services.swf.model.ScheduleActivityTaskFailedEventAttributes$BuilderImpl);
    Code:
       0: aload_0
       1: getfield      #4                  // Field causeValue:Ljava/lang/String;
       4: areturn

  static java.lang.Long access$300(software.amazon.awssdk.services.swf.model.ScheduleActivityTaskFailedEventAttributes$BuilderImpl);
    Code:
       0: aload_0
       1: getfield      #3                  // Field decisionTaskCompletedEventId:Ljava/lang/Long;
       4: areturn

  software.amazon.awssdk.services.swf.model.ScheduleActivityTaskFailedEventAttributes$BuilderImpl(software.amazon.awssdk.services.swf.model.ScheduleActivityTaskFailedEventAttributes, software.amazon.awssdk.services.swf.model.ScheduleActivityTaskFailedEventAttributes$1);
    Code:
       0: aload_0
       1: aload_1
       2: invokespecial #2                  // Method "<init>":(Lsoftware/amazon/awssdk/services/swf/model/ScheduleActivityTaskFailedEventAttributes;)V
       5: return

  software.amazon.awssdk.services.swf.model.ScheduleActivityTaskFailedEventAttributes$BuilderImpl(software.amazon.awssdk.services.swf.model.ScheduleActivityTaskFailedEventAttributes$1);
    Code:
       0: aload_0
       1: invokespecial #1                  // Method "<init>":()V
       4: return
}
