Compiled from "StartChildWorkflowExecutionFailedEventAttributes.java"
public interface software.amazon.awssdk.services.swf.model.StartChildWorkflowExecutionFailedEventAttributes$Builder extends software.amazon.awssdk.core.SdkPojo, software.amazon.awssdk.utils.builder.CopyableBuilder<software.amazon.awssdk.services.swf.model.StartChildWorkflowExecutionFailedEventAttributes$Builder, software.amazon.awssdk.services.swf.model.StartChildWorkflowExecutionFailedEventAttributes> {
  public abstract software.amazon.awssdk.services.swf.model.StartChildWorkflowExecutionFailedEventAttributes$Builder workflowType(software.amazon.awssdk.services.swf.model.WorkflowType);

  public default software.amazon.awssdk.services.swf.model.StartChildWorkflowExecutionFailedEventAttributes$Builder workflowType(java.util.function.Consumer<software.amazon.awssdk.services.swf.model.WorkflowType$Builder>);
    Code:
       0: aload_0
       1: invokestatic  #1                  // Method software/amazon/awssdk/services/swf/model/WorkflowType.builder:()Lsoftware/amazon/awssdk/services/swf/model/WorkflowType$Builder;
       4: aload_1
       5: invokeinterface #2,  2            // InterfaceMethod software/amazon/awssdk/services/swf/model/WorkflowType$Builder.applyMutation:(Ljava/util/function/Consumer;)Lsoftware/amazon/awssdk/utils/builder/SdkBuilder;
      10: checkcast     #3                  // class software/amazon/awssdk/services/swf/model/WorkflowType$Builder
      13: invokeinterface #4,  1            // InterfaceMethod software/amazon/awssdk/services/swf/model/WorkflowType$Builder.build:()Ljava/lang/Object;
      18: checkcast     #5                  // class software/amazon/awssdk/services/swf/model/WorkflowType
      21: invokeinterface #6,  2            // InterfaceMethod workflowType:(Lsoftware/amazon/awssdk/services/swf/model/WorkflowType;)Lsoftware/amazon/awssdk/services/swf/model/StartChildWorkflowExecutionFailedEventAttributes$Builder;
      26: areturn

  public abstract software.amazon.awssdk.services.swf.model.StartChildWorkflowExecutionFailedEventAttributes$Builder cause(java.lang.String);

  public abstract software.amazon.awssdk.services.swf.model.StartChildWorkflowExecutionFailedEventAttributes$Builder cause(software.amazon.awssdk.services.swf.model.StartChildWorkflowExecutionFailedCause);

  public abstract software.amazon.awssdk.services.swf.model.StartChildWorkflowExecutionFailedEventAttributes$Builder workflowId(java.lang.String);

  public abstract software.amazon.awssdk.services.swf.model.StartChildWorkflowExecutionFailedEventAttributes$Builder initiatedEventId(java.lang.Long);

  public abstract software.amazon.awssdk.services.swf.model.StartChildWorkflowExecutionFailedEventAttributes$Builder decisionTaskCompletedEventId(java.lang.Long);

  public abstract software.amazon.awssdk.services.swf.model.StartChildWorkflowExecutionFailedEventAttributes$Builder control(java.lang.String);
}
