Compiled from "TagFilter.java"
final class software.amazon.awssdk.services.swf.model.TagFilter$BuilderImpl implements software.amazon.awssdk.services.swf.model.TagFilter$Builder {
  private java.lang.String tag;

  private software.amazon.awssdk.services.swf.model.TagFilter$BuilderImpl();
    Code:
       0: aload_0
       1: invokespecial #4                  // Method java/lang/Object."<init>":()V
       4: return

  private software.amazon.awssdk.services.swf.model.TagFilter$BuilderImpl(software.amazon.awssdk.services.swf.model.TagFilter);
    Code:
       0: aload_0
       1: invokespecial #4                  // Method java/lang/Object."<init>":()V
       4: aload_0
       5: aload_1
       6: invokestatic  #5                  // Method software/amazon/awssdk/services/swf/model/TagFilter.access$300:(Lsoftware/amazon/awssdk/services/swf/model/TagFilter;)Ljava/lang/String;
       9: invokevirtual #6                  // Method tag:(Ljava/lang/String;)Lsoftware/amazon/awssdk/services/swf/model/TagFilter$Builder;
      12: pop
      13: return

  public final java.lang.String getTag();
    Code:
       0: aload_0
       1: getfield      #3                  // Field tag:Ljava/lang/String;
       4: areturn

  public final software.amazon.awssdk.services.swf.model.TagFilter$Builder tag(java.lang.String);
    Code:
       0: aload_0
       1: aload_1
       2: putfield      #3                  // Field tag:Ljava/lang/String;
       5: aload_0
       6: areturn

  public final void setTag(java.lang.String);
    Code:
       0: aload_0
       1: aload_1
       2: putfield      #3                  // Field tag:Ljava/lang/String;
       5: return

  public software.amazon.awssdk.services.swf.model.TagFilter build();
    Code:
       0: new           #7                  // class software/amazon/awssdk/services/swf/model/TagFilter
       3: dup
       4: aload_0
       5: aconst_null
       6: invokespecial #8                  // Method software/amazon/awssdk/services/swf/model/TagFilter."<init>":(Lsoftware/amazon/awssdk/services/swf/model/TagFilter$BuilderImpl;Lsoftware/amazon/awssdk/services/swf/model/TagFilter$1;)V
       9: areturn

  public java.util.List<software.amazon.awssdk.core.SdkField<?>> sdkFields();
    Code:
       0: invokestatic  #9                  // Method software/amazon/awssdk/services/swf/model/TagFilter.access$500:()Ljava/util/List;
       3: areturn

  public java.lang.Object build();
    Code:
       0: aload_0
       1: invokevirtual #10                 // Method build:()Lsoftware/amazon/awssdk/services/swf/model/TagFilter;
       4: areturn

  static java.lang.String access$000(software.amazon.awssdk.services.swf.model.TagFilter$BuilderImpl);
    Code:
       0: aload_0
       1: getfield      #3                  // Field tag:Ljava/lang/String;
       4: areturn

  software.amazon.awssdk.services.swf.model.TagFilter$BuilderImpl(software.amazon.awssdk.services.swf.model.TagFilter, software.amazon.awssdk.services.swf.model.TagFilter$1);
    Code:
       0: aload_0
       1: aload_1
       2: invokespecial #2                  // Method "<init>":(Lsoftware/amazon/awssdk/services/swf/model/TagFilter;)V
       5: return

  software.amazon.awssdk.services.swf.model.TagFilter$BuilderImpl(software.amazon.awssdk.services.swf.model.TagFilter$1);
    Code:
       0: aload_0
       1: invokespecial #1                  // Method "<init>":()V
       4: return
}
