Compiled from "WorkflowExecutionTimedOutEventAttributes.java"
final class software.amazon.awssdk.services.swf.model.WorkflowExecutionTimedOutEventAttributes$BuilderImpl implements software.amazon.awssdk.services.swf.model.WorkflowExecutionTimedOutEventAttributes$Builder {
  private java.lang.String timeoutType;

  private java.lang.String childPolicy;

  private software.amazon.awssdk.services.swf.model.WorkflowExecutionTimedOutEventAttributes$BuilderImpl();
    Code:
       0: aload_0
       1: invokespecial #5                  // Method java/lang/Object."<init>":()V
       4: return

  private software.amazon.awssdk.services.swf.model.WorkflowExecutionTimedOutEventAttributes$BuilderImpl(software.amazon.awssdk.services.swf.model.WorkflowExecutionTimedOutEventAttributes);
    Code:
       0: aload_0
       1: invokespecial #5                  // Method java/lang/Object."<init>":()V
       4: aload_0
       5: aload_1
       6: invokestatic  #6                  // Method software/amazon/awssdk/services/swf/model/WorkflowExecutionTimedOutEventAttributes.access$400:(Lsoftware/amazon/awssdk/services/swf/model/WorkflowExecutionTimedOutEventAttributes;)Ljava/lang/String;
       9: invokevirtual #7                  // Method timeoutType:(Ljava/lang/String;)Lsoftware/amazon/awssdk/services/swf/model/WorkflowExecutionTimedOutEventAttributes$Builder;
      12: pop
      13: aload_0
      14: aload_1
      15: invokestatic  #8                  // Method software/amazon/awssdk/services/swf/model/WorkflowExecutionTimedOutEventAttributes.access$500:(Lsoftware/amazon/awssdk/services/swf/model/WorkflowExecutionTimedOutEventAttributes;)Ljava/lang/String;
      18: invokevirtual #9                  // Method childPolicy:(Ljava/lang/String;)Lsoftware/amazon/awssdk/services/swf/model/WorkflowExecutionTimedOutEventAttributes$Builder;
      21: pop
      22: return

  public final java.lang.String getTimeoutTypeAsString();
    Code:
       0: aload_0
       1: getfield      #4                  // Field timeoutType:Ljava/lang/String;
       4: areturn

  public final software.amazon.awssdk.services.swf.model.WorkflowExecutionTimedOutEventAttributes$Builder timeoutType(java.lang.String);
    Code:
       0: aload_0
       1: aload_1
       2: putfield      #4                  // Field timeoutType:Ljava/lang/String;
       5: aload_0
       6: areturn

  public final software.amazon.awssdk.services.swf.model.WorkflowExecutionTimedOutEventAttributes$Builder timeoutType(software.amazon.awssdk.services.swf.model.WorkflowExecutionTimeoutType);
    Code:
       0: aload_0
       1: aload_1
       2: ifnonnull     9
       5: aconst_null
       6: goto          13
       9: aload_1
      10: invokevirtual #10                 // Method software/amazon/awssdk/services/swf/model/WorkflowExecutionTimeoutType.toString:()Ljava/lang/String;
      13: invokevirtual #7                  // Method timeoutType:(Ljava/lang/String;)Lsoftware/amazon/awssdk/services/swf/model/WorkflowExecutionTimedOutEventAttributes$Builder;
      16: pop
      17: aload_0
      18: areturn

  public final void setTimeoutType(java.lang.String);
    Code:
       0: aload_0
       1: aload_1
       2: putfield      #4                  // Field timeoutType:Ljava/lang/String;
       5: return

  public final java.lang.String getChildPolicyAsString();
    Code:
       0: aload_0
       1: getfield      #3                  // Field childPolicy:Ljava/lang/String;
       4: areturn

  public final software.amazon.awssdk.services.swf.model.WorkflowExecutionTimedOutEventAttributes$Builder childPolicy(java.lang.String);
    Code:
       0: aload_0
       1: aload_1
       2: putfield      #3                  // Field childPolicy:Ljava/lang/String;
       5: aload_0
       6: areturn

  public final software.amazon.awssdk.services.swf.model.WorkflowExecutionTimedOutEventAttributes$Builder childPolicy(software.amazon.awssdk.services.swf.model.ChildPolicy);
    Code:
       0: aload_0
       1: aload_1
       2: ifnonnull     9
       5: aconst_null
       6: goto          13
       9: aload_1
      10: invokevirtual #11                 // Method software/amazon/awssdk/services/swf/model/ChildPolicy.toString:()Ljava/lang/String;
      13: invokevirtual #9                  // Method childPolicy:(Ljava/lang/String;)Lsoftware/amazon/awssdk/services/swf/model/WorkflowExecutionTimedOutEventAttributes$Builder;
      16: pop
      17: aload_0
      18: areturn

  public final void setChildPolicy(java.lang.String);
    Code:
       0: aload_0
       1: aload_1
       2: putfield      #3                  // Field childPolicy:Ljava/lang/String;
       5: return

  public software.amazon.awssdk.services.swf.model.WorkflowExecutionTimedOutEventAttributes build();
    Code:
       0: new           #12                 // class software/amazon/awssdk/services/swf/model/WorkflowExecutionTimedOutEventAttributes
       3: dup
       4: aload_0
       5: aconst_null
       6: invokespecial #13                 // Method software/amazon/awssdk/services/swf/model/WorkflowExecutionTimedOutEventAttributes."<init>":(Lsoftware/amazon/awssdk/services/swf/model/WorkflowExecutionTimedOutEventAttributes$BuilderImpl;Lsoftware/amazon/awssdk/services/swf/model/WorkflowExecutionTimedOutEventAttributes$1;)V
       9: areturn

  public java.util.List<software.amazon.awssdk.core.SdkField<?>> sdkFields();
    Code:
       0: invokestatic  #14                 // Method software/amazon/awssdk/services/swf/model/WorkflowExecutionTimedOutEventAttributes.access$700:()Ljava/util/List;
       3: areturn

  public java.lang.Object build();
    Code:
       0: aload_0
       1: invokevirtual #15                 // Method build:()Lsoftware/amazon/awssdk/services/swf/model/WorkflowExecutionTimedOutEventAttributes;
       4: areturn

  static java.lang.String access$000(software.amazon.awssdk.services.swf.model.WorkflowExecutionTimedOutEventAttributes$BuilderImpl);
    Code:
       0: aload_0
       1: getfield      #4                  // Field timeoutType:Ljava/lang/String;
       4: areturn

  static java.lang.String access$100(software.amazon.awssdk.services.swf.model.WorkflowExecutionTimedOutEventAttributes$BuilderImpl);
    Code:
       0: aload_0
       1: getfield      #3                  // Field childPolicy:Ljava/lang/String;
       4: areturn

  software.amazon.awssdk.services.swf.model.WorkflowExecutionTimedOutEventAttributes$BuilderImpl(software.amazon.awssdk.services.swf.model.WorkflowExecutionTimedOutEventAttributes, software.amazon.awssdk.services.swf.model.WorkflowExecutionTimedOutEventAttributes$1);
    Code:
       0: aload_0
       1: aload_1
       2: invokespecial #2                  // Method "<init>":(Lsoftware/amazon/awssdk/services/swf/model/WorkflowExecutionTimedOutEventAttributes;)V
       5: return

  software.amazon.awssdk.services.swf.model.WorkflowExecutionTimedOutEventAttributes$BuilderImpl(software.amazon.awssdk.services.swf.model.WorkflowExecutionTimedOutEventAttributes$1);
    Code:
       0: aload_0
       1: invokespecial #1                  // Method "<init>":()V
       4: return
}
