Compiled from "AbstractCsvLayout.java"
public abstract class org.apache.logging.log4j.core.layout.AbstractCsvLayout extends org.apache.logging.log4j.core.layout.AbstractStringLayout {
  protected static final java.lang.String DEFAULT_CHARSET;

  protected static final java.lang.String DEFAULT_FORMAT;

  private static final java.lang.String CONTENT_TYPE;

  private final org.apache.commons.csv.CSVFormat format;

  protected static org.apache.commons.csv.CSVFormat createFormat(java.lang.String, java.lang.Character, java.lang.Character, java.lang.Character, org.apache.commons.csv.QuoteMode, java.lang.String, java.lang.String);
    Code:
       0: aload_0
       1: invokestatic  #1                  // Method org/apache/commons/csv/CSVFormat.valueOf:(Ljava/lang/String;)Lorg/apache/commons/csv/CSVFormat;
       4: astore        7
       6: aload_1
       7: invokestatic  #2                  // Method isNotNul:(Ljava/lang/Character;)Z
      10: ifeq          24
      13: aload         7
      15: aload_1
      16: invokevirtual #3                  // Method java/lang/Character.charValue:()C
      19: invokevirtual #4                  // Method org/apache/commons/csv/CSVFormat.withDelimiter:(C)Lorg/apache/commons/csv/CSVFormat;
      22: astore        7
      24: aload_2
      25: invokestatic  #2                  // Method isNotNul:(Ljava/lang/Character;)Z
      28: ifeq          39
      31: aload         7
      33: aload_2
      34: invokevirtual #5                  // Method org/apache/commons/csv/CSVFormat.withEscape:(Ljava/lang/Character;)Lorg/apache/commons/csv/CSVFormat;
      37: astore        7
      39: aload_3
      40: invokestatic  #2                  // Method isNotNul:(Ljava/lang/Character;)Z
      43: ifeq          54
      46: aload         7
      48: aload_3
      49: invokevirtual #6                  // Method org/apache/commons/csv/CSVFormat.withQuote:(Ljava/lang/Character;)Lorg/apache/commons/csv/CSVFormat;
      52: astore        7
      54: aload         4
      56: ifnull        68
      59: aload         7
      61: aload         4
      63: invokevirtual #7                  // Method org/apache/commons/csv/CSVFormat.withQuoteMode:(Lorg/apache/commons/csv/QuoteMode;)Lorg/apache/commons/csv/CSVFormat;
      66: astore        7
      68: aload         5
      70: ifnull        82
      73: aload         7
      75: aload         5
      77: invokevirtual #8                  // Method org/apache/commons/csv/CSVFormat.withNullString:(Ljava/lang/String;)Lorg/apache/commons/csv/CSVFormat;
      80: astore        7
      82: aload         6
      84: ifnull        96
      87: aload         7
      89: aload         6
      91: invokevirtual #9                  // Method org/apache/commons/csv/CSVFormat.withRecordSeparator:(Ljava/lang/String;)Lorg/apache/commons/csv/CSVFormat;
      94: astore        7
      96: aload         7
      98: areturn

  private static boolean isNotNul(java.lang.Character);
    Code:
       0: aload_0
       1: ifnull        15
       4: aload_0
       5: invokevirtual #3                  // Method java/lang/Character.charValue:()C
       8: ifeq          15
      11: iconst_1
      12: goto          16
      15: iconst_0
      16: ireturn

  protected org.apache.logging.log4j.core.layout.AbstractCsvLayout(org.apache.logging.log4j.core.config.Configuration, java.nio.charset.Charset, org.apache.commons.csv.CSVFormat, java.lang.String, java.lang.String);
    Code:
       0: aload_0
       1: aload_1
       2: aload_2
       3: invokestatic  #10                 // Method org/apache/logging/log4j/core/layout/PatternLayout.newSerializerBuilder:()Lorg/apache/logging/log4j/core/layout/PatternLayout$SerializerBuilder;
       6: aload_1
       7: invokevirtual #11                 // Method org/apache/logging/log4j/core/layout/PatternLayout$SerializerBuilder.setConfiguration:(Lorg/apache/logging/log4j/core/config/Configuration;)Lorg/apache/logging/log4j/core/layout/PatternLayout$SerializerBuilder;
      10: aload         4
      12: invokevirtual #12                 // Method org/apache/logging/log4j/core/layout/PatternLayout$SerializerBuilder.setPattern:(Ljava/lang/String;)Lorg/apache/logging/log4j/core/layout/PatternLayout$SerializerBuilder;
      15: invokevirtual #13                 // Method org/apache/logging/log4j/core/layout/PatternLayout$SerializerBuilder.build:()Lorg/apache/logging/log4j/core/layout/AbstractStringLayout$Serializer;
      18: invokestatic  #10                 // Method org/apache/logging/log4j/core/layout/PatternLayout.newSerializerBuilder:()Lorg/apache/logging/log4j/core/layout/PatternLayout$SerializerBuilder;
      21: aload_1
      22: invokevirtual #11                 // Method org/apache/logging/log4j/core/layout/PatternLayout$SerializerBuilder.setConfiguration:(Lorg/apache/logging/log4j/core/config/Configuration;)Lorg/apache/logging/log4j/core/layout/PatternLayout$SerializerBuilder;
      25: aload         5
      27: invokevirtual #12                 // Method org/apache/logging/log4j/core/layout/PatternLayout$SerializerBuilder.setPattern:(Ljava/lang/String;)Lorg/apache/logging/log4j/core/layout/PatternLayout$SerializerBuilder;
      30: invokevirtual #13                 // Method org/apache/logging/log4j/core/layout/PatternLayout$SerializerBuilder.build:()Lorg/apache/logging/log4j/core/layout/AbstractStringLayout$Serializer;
      33: invokespecial #14                 // Method org/apache/logging/log4j/core/layout/AbstractStringLayout."<init>":(Lorg/apache/logging/log4j/core/config/Configuration;Ljava/nio/charset/Charset;Lorg/apache/logging/log4j/core/layout/AbstractStringLayout$Serializer;Lorg/apache/logging/log4j/core/layout/AbstractStringLayout$Serializer;)V
      36: aload_0
      37: aload_3
      38: putfield      #15                 // Field format:Lorg/apache/commons/csv/CSVFormat;
      41: return

  public java.lang.String getContentType();
    Code:
       0: new           #16                 // class java/lang/StringBuilder
       3: dup
       4: invokespecial #17                 // Method java/lang/StringBuilder."<init>":()V
       7: ldc           #19                 // String text/csv; charset=
       9: invokevirtual #20                 // Method java/lang/StringBuilder.append:(Ljava/lang/String;)Ljava/lang/StringBuilder;
      12: aload_0
      13: invokevirtual #21                 // Method getCharset:()Ljava/nio/charset/Charset;
      16: invokevirtual #22                 // Method java/lang/StringBuilder.append:(Ljava/lang/Object;)Ljava/lang/StringBuilder;
      19: invokevirtual #23                 // Method java/lang/StringBuilder.toString:()Ljava/lang/String;
      22: areturn

  public org.apache.commons.csv.CSVFormat getFormat();
    Code:
       0: aload_0
       1: getfield      #15                 // Field format:Lorg/apache/commons/csv/CSVFormat;
       4: areturn
}
