Compiled from "JoinRecordReader.java"
public abstract class org.apache.hadoop.mapreduce.lib.join.JoinRecordReader<K extends org.apache.hadoop.io.WritableComparable<?>> extends org.apache.hadoop.mapreduce.lib.join.CompositeRecordReader<K, org.apache.hadoop.io.Writable, org.apache.hadoop.mapreduce.lib.join.TupleWritable> {
  public org.apache.hadoop.mapreduce.lib.join.JoinRecordReader(int, org.apache.hadoop.conf.Configuration, int, java.lang.Class<? extends org.apache.hadoop.io.WritableComparator>) throws java.io.IOException;
    Code:
       0: aload_0
       1: iload_1
       2: iload_3
       3: aload         4
       5: invokespecial #1                  // Method org/apache/hadoop/mapreduce/lib/join/CompositeRecordReader."<init>":(IILjava/lang/Class;)V
       8: aload_0
       9: aload_2
      10: invokevirtual #2                  // Method setConf:(Lorg/apache/hadoop/conf/Configuration;)V
      13: return

  public boolean nextKeyValue() throws java.io.IOException, java.lang.InterruptedException;
    Code:
       0: aload_0
       1: getfield      #3                  // Field key:Lorg/apache/hadoop/io/WritableComparable;
       4: ifnonnull     15
       7: aload_0
       8: aload_0
       9: invokevirtual #4                  // Method createKey:()Lorg/apache/hadoop/io/WritableComparable;
      12: putfield      #3                  // Field key:Lorg/apache/hadoop/io/WritableComparable;
      15: aload_0
      16: getfield      #5                  // Field jc:Lorg/apache/hadoop/mapreduce/lib/join/CompositeRecordReader$JoinCollector;
      19: aload_0
      20: getfield      #6                  // Field value:Lorg/apache/hadoop/io/Writable;
      23: checkcast     #7                  // class org/apache/hadoop/mapreduce/lib/join/TupleWritable
      26: invokevirtual #8                  // Method org/apache/hadoop/mapreduce/lib/join/CompositeRecordReader$JoinCollector.flush:(Lorg/apache/hadoop/mapreduce/lib/join/TupleWritable;)Z
      29: ifeq          53
      32: aload_0
      33: getfield      #9                  // Field conf:Lorg/apache/hadoop/conf/Configuration;
      36: aload_0
      37: getfield      #5                  // Field jc:Lorg/apache/hadoop/mapreduce/lib/join/CompositeRecordReader$JoinCollector;
      40: invokevirtual #10                 // Method org/apache/hadoop/mapreduce/lib/join/CompositeRecordReader$JoinCollector.key:()Lorg/apache/hadoop/io/WritableComparable;
      43: aload_0
      44: getfield      #3                  // Field key:Lorg/apache/hadoop/io/WritableComparable;
      47: invokestatic  #11                 // Method org/apache/hadoop/util/ReflectionUtils.copy:(Lorg/apache/hadoop/conf/Configuration;Ljava/lang/Object;Ljava/lang/Object;)Ljava/lang/Object;
      50: pop
      51: iconst_1
      52: ireturn
      53: aload_0
      54: getfield      #5                  // Field jc:Lorg/apache/hadoop/mapreduce/lib/join/CompositeRecordReader$JoinCollector;
      57: invokevirtual #12                 // Method org/apache/hadoop/mapreduce/lib/join/CompositeRecordReader$JoinCollector.clear:()V
      60: aload_0
      61: getfield      #6                  // Field value:Lorg/apache/hadoop/io/Writable;
      64: ifnonnull     75
      67: aload_0
      68: aload_0
      69: invokevirtual #13                 // Method createValue:()Lorg/apache/hadoop/mapreduce/lib/join/TupleWritable;
      72: putfield      #6                  // Field value:Lorg/apache/hadoop/io/Writable;
      75: aload_0
      76: invokevirtual #14                 // Method getRecordReaderQueue:()Ljava/util/PriorityQueue;
      79: astore_1
      80: aload_0
      81: invokevirtual #4                  // Method createKey:()Lorg/apache/hadoop/io/WritableComparable;
      84: astore_2
      85: aload_1
      86: ifnull        157
      89: aload_1
      90: invokevirtual #15                 // Method java/util/PriorityQueue.isEmpty:()Z
      93: ifne          157
      96: aload_0
      97: aload_2
      98: invokevirtual #16                 // Method fillJoinCollector:(Lorg/apache/hadoop/io/WritableComparable;)V
     101: aload_0
     102: getfield      #5                  // Field jc:Lorg/apache/hadoop/mapreduce/lib/join/CompositeRecordReader$JoinCollector;
     105: aload_2
     106: invokevirtual #17                 // Method org/apache/hadoop/mapreduce/lib/join/CompositeRecordReader$JoinCollector.reset:(Lorg/apache/hadoop/io/WritableComparable;)V
     109: aload_0
     110: getfield      #5                  // Field jc:Lorg/apache/hadoop/mapreduce/lib/join/CompositeRecordReader$JoinCollector;
     113: aload_0
     114: getfield      #6                  // Field value:Lorg/apache/hadoop/io/Writable;
     117: checkcast     #7                  // class org/apache/hadoop/mapreduce/lib/join/TupleWritable
     120: invokevirtual #8                  // Method org/apache/hadoop/mapreduce/lib/join/CompositeRecordReader$JoinCollector.flush:(Lorg/apache/hadoop/mapreduce/lib/join/TupleWritable;)Z
     123: ifeq          147
     126: aload_0
     127: getfield      #9                  // Field conf:Lorg/apache/hadoop/conf/Configuration;
     130: aload_0
     131: getfield      #5                  // Field jc:Lorg/apache/hadoop/mapreduce/lib/join/CompositeRecordReader$JoinCollector;
     134: invokevirtual #10                 // Method org/apache/hadoop/mapreduce/lib/join/CompositeRecordReader$JoinCollector.key:()Lorg/apache/hadoop/io/WritableComparable;
     137: aload_0
     138: getfield      #3                  // Field key:Lorg/apache/hadoop/io/WritableComparable;
     141: invokestatic  #11                 // Method org/apache/hadoop/util/ReflectionUtils.copy:(Lorg/apache/hadoop/conf/Configuration;Ljava/lang/Object;Ljava/lang/Object;)Ljava/lang/Object;
     144: pop
     145: iconst_1
     146: ireturn
     147: aload_0
     148: getfield      #5                  // Field jc:Lorg/apache/hadoop/mapreduce/lib/join/CompositeRecordReader$JoinCollector;
     151: invokevirtual #12                 // Method org/apache/hadoop/mapreduce/lib/join/CompositeRecordReader$JoinCollector.clear:()V
     154: goto          85
     157: iconst_0
     158: ireturn

  public org.apache.hadoop.mapreduce.lib.join.TupleWritable createValue();
    Code:
       0: aload_0
       1: invokevirtual #18                 // Method createTupleWritable:()Lorg/apache/hadoop/mapreduce/lib/join/TupleWritable;
       4: areturn

  protected org.apache.hadoop.mapreduce.lib.join.ResetableIterator<org.apache.hadoop.mapreduce.lib.join.TupleWritable> getDelegate();
    Code:
       0: new           #19                 // class org/apache/hadoop/mapreduce/lib/join/JoinRecordReader$JoinDelegationIterator
       3: dup
       4: aload_0
       5: invokespecial #20                 // Method org/apache/hadoop/mapreduce/lib/join/JoinRecordReader$JoinDelegationIterator."<init>":(Lorg/apache/hadoop/mapreduce/lib/join/JoinRecordReader;)V
       8: areturn

  public org.apache.hadoop.io.Writable createValue();
    Code:
       0: aload_0
       1: invokevirtual #13                 // Method createValue:()Lorg/apache/hadoop/mapreduce/lib/join/TupleWritable;
       4: areturn
}
