Compiled from "Parser.java"
class org.apache.hadoop.mapreduce.lib.join.Parser$Lexer {
  private java.io.StreamTokenizer tok;

  org.apache.hadoop.mapreduce.lib.join.Parser$Lexer(java.lang.String);
    Code:
       0: aload_0
       1: invokespecial #1                  // Method java/lang/Object."<init>":()V
       4: aload_0
       5: new           #2                  // class java/io/StreamTokenizer
       8: dup
       9: new           #3                  // class java/io/CharArrayReader
      12: dup
      13: aload_1
      14: invokevirtual #4                  // Method java/lang/String.toCharArray:()[C
      17: invokespecial #5                  // Method java/io/CharArrayReader."<init>":([C)V
      20: invokespecial #6                  // Method java/io/StreamTokenizer."<init>":(Ljava/io/Reader;)V
      23: putfield      #7                  // Field tok:Ljava/io/StreamTokenizer;
      26: aload_0
      27: getfield      #7                  // Field tok:Ljava/io/StreamTokenizer;
      30: bipush        34
      32: invokevirtual #8                  // Method java/io/StreamTokenizer.quoteChar:(I)V
      35: aload_0
      36: getfield      #7                  // Field tok:Ljava/io/StreamTokenizer;
      39: invokevirtual #9                  // Method java/io/StreamTokenizer.parseNumbers:()V
      42: aload_0
      43: getfield      #7                  // Field tok:Ljava/io/StreamTokenizer;
      46: bipush        44
      48: invokevirtual #10                 // Method java/io/StreamTokenizer.ordinaryChar:(I)V
      51: aload_0
      52: getfield      #7                  // Field tok:Ljava/io/StreamTokenizer;
      55: bipush        40
      57: invokevirtual #10                 // Method java/io/StreamTokenizer.ordinaryChar:(I)V
      60: aload_0
      61: getfield      #7                  // Field tok:Ljava/io/StreamTokenizer;
      64: bipush        41
      66: invokevirtual #10                 // Method java/io/StreamTokenizer.ordinaryChar:(I)V
      69: aload_0
      70: getfield      #7                  // Field tok:Ljava/io/StreamTokenizer;
      73: bipush        36
      75: bipush        36
      77: invokevirtual #11                 // Method java/io/StreamTokenizer.wordChars:(II)V
      80: aload_0
      81: getfield      #7                  // Field tok:Ljava/io/StreamTokenizer;
      84: bipush        95
      86: bipush        95
      88: invokevirtual #11                 // Method java/io/StreamTokenizer.wordChars:(II)V
      91: return

  org.apache.hadoop.mapreduce.lib.join.Parser$Token next() throws java.io.IOException;
    Code:
       0: aload_0
       1: getfield      #7                  // Field tok:Ljava/io/StreamTokenizer;
       4: invokevirtual #12                 // Method java/io/StreamTokenizer.nextToken:()I
       7: istore_1
       8: iload_1
       9: lookupswitch  { // 5
                    -3: 77
                    -2: 62
                    -1: 60
                    10: 60
                    34: 95
               default: 113
          }
      60: aconst_null
      61: areturn
      62: new           #13                 // class org/apache/hadoop/mapreduce/lib/join/Parser$NumToken
      65: dup
      66: aload_0
      67: getfield      #7                  // Field tok:Ljava/io/StreamTokenizer;
      70: getfield      #14                 // Field java/io/StreamTokenizer.nval:D
      73: invokespecial #15                 // Method org/apache/hadoop/mapreduce/lib/join/Parser$NumToken."<init>":(D)V
      76: areturn
      77: new           #16                 // class org/apache/hadoop/mapreduce/lib/join/Parser$StrToken
      80: dup
      81: getstatic     #17                 // Field org/apache/hadoop/mapreduce/lib/join/Parser$TType.IDENT:Lorg/apache/hadoop/mapreduce/lib/join/Parser$TType;
      84: aload_0
      85: getfield      #7                  // Field tok:Ljava/io/StreamTokenizer;
      88: getfield      #18                 // Field java/io/StreamTokenizer.sval:Ljava/lang/String;
      91: invokespecial #19                 // Method org/apache/hadoop/mapreduce/lib/join/Parser$StrToken."<init>":(Lorg/apache/hadoop/mapreduce/lib/join/Parser$TType;Ljava/lang/String;)V
      94: areturn
      95: new           #16                 // class org/apache/hadoop/mapreduce/lib/join/Parser$StrToken
      98: dup
      99: getstatic     #20                 // Field org/apache/hadoop/mapreduce/lib/join/Parser$TType.QUOT:Lorg/apache/hadoop/mapreduce/lib/join/Parser$TType;
     102: aload_0
     103: getfield      #7                  // Field tok:Ljava/io/StreamTokenizer;
     106: getfield      #18                 // Field java/io/StreamTokenizer.sval:Ljava/lang/String;
     109: invokespecial #19                 // Method org/apache/hadoop/mapreduce/lib/join/Parser$StrToken."<init>":(Lorg/apache/hadoop/mapreduce/lib/join/Parser$TType;Ljava/lang/String;)V
     112: areturn
     113: iload_1
     114: tableswitch   { // 40 to 44
                    40: 159
                    41: 170
                    42: 181
                    43: 181
                    44: 148
               default: 181
          }
     148: new           #21                 // class org/apache/hadoop/mapreduce/lib/join/Parser$Token
     151: dup
     152: getstatic     #22                 // Field org/apache/hadoop/mapreduce/lib/join/Parser$TType.COMMA:Lorg/apache/hadoop/mapreduce/lib/join/Parser$TType;
     155: invokespecial #23                 // Method org/apache/hadoop/mapreduce/lib/join/Parser$Token."<init>":(Lorg/apache/hadoop/mapreduce/lib/join/Parser$TType;)V
     158: areturn
     159: new           #21                 // class org/apache/hadoop/mapreduce/lib/join/Parser$Token
     162: dup
     163: getstatic     #24                 // Field org/apache/hadoop/mapreduce/lib/join/Parser$TType.LPAREN:Lorg/apache/hadoop/mapreduce/lib/join/Parser$TType;
     166: invokespecial #23                 // Method org/apache/hadoop/mapreduce/lib/join/Parser$Token."<init>":(Lorg/apache/hadoop/mapreduce/lib/join/Parser$TType;)V
     169: areturn
     170: new           #21                 // class org/apache/hadoop/mapreduce/lib/join/Parser$Token
     173: dup
     174: getstatic     #25                 // Field org/apache/hadoop/mapreduce/lib/join/Parser$TType.RPAREN:Lorg/apache/hadoop/mapreduce/lib/join/Parser$TType;
     177: invokespecial #23                 // Method org/apache/hadoop/mapreduce/lib/join/Parser$Token."<init>":(Lorg/apache/hadoop/mapreduce/lib/join/Parser$TType;)V
     180: areturn
     181: new           #26                 // class java/io/IOException
     184: dup
     185: new           #27                 // class java/lang/StringBuilder
     188: dup
     189: invokespecial #28                 // Method java/lang/StringBuilder."<init>":()V
     192: ldc           #29                 // String Unexpected:
     194: invokevirtual #30                 // Method java/lang/StringBuilder.append:(Ljava/lang/String;)Ljava/lang/StringBuilder;
     197: iload_1
     198: invokevirtual #31                 // Method java/lang/StringBuilder.append:(I)Ljava/lang/StringBuilder;
     201: invokevirtual #32                 // Method java/lang/StringBuilder.toString:()Ljava/lang/String;
     204: invokespecial #33                 // Method java/io/IOException."<init>":(Ljava/lang/String;)V
     207: athrow
}
