Compiled from "ReflectKotlinClass.kt"
public final class kotlin.reflect.jvm.internal.impl.descriptors.runtime.components.ReflectKotlinClassKt {
  private static final java.util.Set<java.lang.Class<?>> TYPES_ELIGIBLE_FOR_SIMPLE_VISIT;

  public static final java.util.Set access$getTYPES_ELIGIBLE_FOR_SIMPLE_VISIT$p();
    Code:
       0: getstatic     #22                 // Field TYPES_ELIGIBLE_FOR_SIMPLE_VISIT:Ljava/util/Set;
       3: areturn

  static {};
    Code:
       0: bipush        18
       2: anewarray     #12                 // class java/lang/Class
       5: astore_0
       6: aload_0
       7: iconst_0
       8: ldc           #15                 // class java/lang/Integer
      10: aastore
      11: aload_0
      12: iconst_1
      13: ldc           #11                 // class java/lang/Character
      15: aastore
      16: aload_0
      17: iconst_2
      18: ldc           #10                 // class java/lang/Byte
      20: aastore
      21: aload_0
      22: iconst_3
      23: ldc           #16                 // class java/lang/Long
      25: aastore
      26: aload_0
      27: iconst_4
      28: ldc           #18                 // class java/lang/Short
      30: aastore
      31: aload_0
      32: iconst_5
      33: ldc           #9                  // class java/lang/Boolean
      35: aastore
      36: aload_0
      37: bipush        6
      39: ldc           #13                 // class java/lang/Double
      41: aastore
      42: aload_0
      43: bipush        7
      45: ldc           #14                 // class java/lang/Float
      47: aastore
      48: aload_0
      49: bipush        8
      51: ldc           #5                  // class "[I"
      53: aastore
      54: aload_0
      55: bipush        9
      57: ldc           #2                  // class "[C"
      59: aastore
      60: aload_0
      61: bipush        10
      63: ldc           #1                  // class "[B"
      65: aastore
      66: aload_0
      67: bipush        11
      69: ldc           #6                  // class "[J"
      71: aastore
      72: aload_0
      73: bipush        12
      75: ldc           #7                  // class "[S"
      77: aastore
      78: aload_0
      79: bipush        13
      81: ldc           #8                  // class "[Z"
      83: aastore
      84: aload_0
      85: bipush        14
      87: ldc           #3                  // class "[D"
      89: aastore
      90: aload_0
      91: bipush        15
      93: ldc           #4                  // class "[F"
      95: aastore
      96: aload_0
      97: bipush        16
      99: ldc           #12                 // class java/lang/Class
     101: aastore
     102: aload_0
     103: bipush        17
     105: ldc           #19                 // class java/lang/String
     107: aastore
     108: aload_0
     109: invokestatic  #23                 // Method kotlin/collections/SetsKt.setOf:([Ljava/lang/Object;)Ljava/util/Set;
     112: putstatic     #22                 // Field TYPES_ELIGIBLE_FOR_SIMPLE_VISIT:Ljava/util/Set;
     115: return
}
