Compiled from "TemplateAssertionException.java"
public class org.thymeleaf.exceptions.TemplateAssertionException extends java.lang.RuntimeException {
  private static final long serialVersionUID;

  private static final java.lang.String ASSERTION_MESSAGE;

  private static final java.lang.String ASSERTION_MESSAGE_LINE_COL;

  public org.thymeleaf.exceptions.TemplateAssertionException(java.lang.String, java.lang.String, int, int);
    Code:
       0: aload_0
       1: aload_1
       2: aload_2
       3: iload_3
       4: invokestatic  #1                  // Method java/lang/Integer.valueOf:(I)Ljava/lang/Integer;
       7: iload         4
       9: invokestatic  #1                  // Method java/lang/Integer.valueOf:(I)Ljava/lang/Integer;
      12: invokestatic  #2                  // Method createMessage:(Ljava/lang/String;Ljava/lang/String;Ljava/lang/Integer;Ljava/lang/Integer;)Ljava/lang/String;
      15: invokespecial #3                  // Method java/lang/RuntimeException."<init>":(Ljava/lang/String;)V
      18: return

  public org.thymeleaf.exceptions.TemplateAssertionException(java.lang.String, java.lang.String);
    Code:
       0: aload_0
       1: aload_1
       2: aload_2
       3: aconst_null
       4: aconst_null
       5: invokestatic  #2                  // Method createMessage:(Ljava/lang/String;Ljava/lang/String;Ljava/lang/Integer;Ljava/lang/Integer;)Ljava/lang/String;
       8: invokespecial #3                  // Method java/lang/RuntimeException."<init>":(Ljava/lang/String;)V
      11: return

  private static java.lang.String createMessage(java.lang.String, java.lang.String, java.lang.Integer, java.lang.Integer);
    Code:
       0: aload_2
       1: ifnull        8
       4: aload_3
       5: ifnonnull     26
       8: ldc           #5                  // String Assertion \'%s\' not valid in template \'%s\'
      10: iconst_2
      11: anewarray     #6                  // class java/lang/Object
      14: dup
      15: iconst_0
      16: aload_0
      17: aastore
      18: dup
      19: iconst_1
      20: aload_1
      21: aastore
      22: invokestatic  #7                  // Method java/lang/String.format:(Ljava/lang/String;[Ljava/lang/Object;)Ljava/lang/String;
      25: areturn
      26: ldc           #8                  // String Assertion \'%s\' not valid in template \'%s\', line %d col %d
      28: iconst_4
      29: anewarray     #6                  // class java/lang/Object
      32: dup
      33: iconst_0
      34: aload_0
      35: aastore
      36: dup
      37: iconst_1
      38: aload_1
      39: aastore
      40: dup
      41: iconst_2
      42: aload_2
      43: aastore
      44: dup
      45: iconst_3
      46: aload_3
      47: aastore
      48: invokestatic  #7                  // Method java/lang/String.format:(Ljava/lang/String;[Ljava/lang/Object;)Ljava/lang/String;
      51: areturn
}
