Compiled from "ShiroAwareCharge.java"
public class org.sonatype.sisu.charger.shiro.ShiroAwareCharge<E> extends org.sonatype.sisu.charger.internal.Charge<E> {
  private final org.apache.shiro.subject.Subject subject;

  public org.sonatype.sisu.charger.shiro.ShiroAwareCharge(org.sonatype.sisu.charger.ChargeStrategy<E>, org.apache.shiro.subject.Subject);
    Code:
       0: aload_0
       1: aload_1
       2: invokespecial #1                  // Method org/sonatype/sisu/charger/internal/Charge."<init>":(Lorg/sonatype/sisu/charger/ChargeStrategy;)V
       5: aload_0
       6: aload_2
       7: putfield      #2                  // Field subject:Lorg/apache/shiro/subject/Subject;
      10: return

  public void addAmmo(java.util.concurrent.Callable<? extends E>, org.sonatype.sisu.charger.ExceptionHandler);
    Code:
       0: aload_0
       1: aload_0
       2: getfield      #2                  // Field subject:Lorg/apache/shiro/subject/Subject;
       5: aload_1
       6: invokeinterface #3,  2            // InterfaceMethod org/apache/shiro/subject/Subject.associateWith:(Ljava/util/concurrent/Callable;)Ljava/util/concurrent/Callable;
      11: aload_2
      12: invokespecial #4                  // Method org/sonatype/sisu/charger/internal/Charge.addAmmo:(Ljava/util/concurrent/Callable;Lorg/sonatype/sisu/charger/ExceptionHandler;)V
      15: return
}
