Compiled from "DnsProperties.java"
public interface software.amazon.awssdk.services.servicediscovery.model.DnsProperties$Builder extends software.amazon.awssdk.core.SdkPojo, software.amazon.awssdk.utils.builder.CopyableBuilder<software.amazon.awssdk.services.servicediscovery.model.DnsProperties$Builder, software.amazon.awssdk.services.servicediscovery.model.DnsProperties> {
  public abstract software.amazon.awssdk.services.servicediscovery.model.DnsProperties$Builder hostedZoneId(java.lang.String);

  public abstract software.amazon.awssdk.services.servicediscovery.model.DnsProperties$Builder soa(software.amazon.awssdk.services.servicediscovery.model.SOA);

  public default software.amazon.awssdk.services.servicediscovery.model.DnsProperties$Builder soa(java.util.function.Consumer<software.amazon.awssdk.services.servicediscovery.model.SOA$Builder>);
    Code:
       0: aload_0
       1: invokestatic  #1                  // Method software/amazon/awssdk/services/servicediscovery/model/SOA.builder:()Lsoftware/amazon/awssdk/services/servicediscovery/model/SOA$Builder;
       4: aload_1
       5: invokeinterface #2,  2            // InterfaceMethod software/amazon/awssdk/services/servicediscovery/model/SOA$Builder.applyMutation:(Ljava/util/function/Consumer;)Lsoftware/amazon/awssdk/utils/builder/SdkBuilder;
      10: checkcast     #3                  // class software/amazon/awssdk/services/servicediscovery/model/SOA$Builder
      13: invokeinterface #4,  1            // InterfaceMethod software/amazon/awssdk/services/servicediscovery/model/SOA$Builder.build:()Ljava/lang/Object;
      18: checkcast     #5                  // class software/amazon/awssdk/services/servicediscovery/model/SOA
      21: invokeinterface #6,  2            // InterfaceMethod soa:(Lsoftware/amazon/awssdk/services/servicediscovery/model/SOA;)Lsoftware/amazon/awssdk/services/servicediscovery/model/DnsProperties$Builder;
      26: areturn
}
