Compiled from "NamespaceFilter.java"
final class software.amazon.awssdk.services.servicediscovery.model.NamespaceFilter$BuilderImpl implements software.amazon.awssdk.services.servicediscovery.model.NamespaceFilter$Builder {
  private java.lang.String name;

  private java.util.List<java.lang.String> values;

  private java.lang.String condition;

  private software.amazon.awssdk.services.servicediscovery.model.NamespaceFilter$BuilderImpl();
    Code:
       0: aload_0
       1: invokespecial #6                  // Method java/lang/Object."<init>":()V
       4: aload_0
       5: invokestatic  #7                  // Method software/amazon/awssdk/core/util/DefaultSdkAutoConstructList.getInstance:()Lsoftware/amazon/awssdk/core/util/DefaultSdkAutoConstructList;
       8: putfield      #4                  // Field values:Ljava/util/List;
      11: return

  private software.amazon.awssdk.services.servicediscovery.model.NamespaceFilter$BuilderImpl(software.amazon.awssdk.services.servicediscovery.model.NamespaceFilter);
    Code:
       0: aload_0
       1: invokespecial #6                  // Method java/lang/Object."<init>":()V
       4: aload_0
       5: invokestatic  #7                  // Method software/amazon/awssdk/core/util/DefaultSdkAutoConstructList.getInstance:()Lsoftware/amazon/awssdk/core/util/DefaultSdkAutoConstructList;
       8: putfield      #4                  // Field values:Ljava/util/List;
      11: aload_0
      12: aload_1
      13: invokestatic  #8                  // Method software/amazon/awssdk/services/servicediscovery/model/NamespaceFilter.access$500:(Lsoftware/amazon/awssdk/services/servicediscovery/model/NamespaceFilter;)Ljava/lang/String;
      16: invokevirtual #9                  // Method name:(Ljava/lang/String;)Lsoftware/amazon/awssdk/services/servicediscovery/model/NamespaceFilter$Builder;
      19: pop
      20: aload_0
      21: aload_1
      22: invokestatic  #10                 // Method software/amazon/awssdk/services/servicediscovery/model/NamespaceFilter.access$600:(Lsoftware/amazon/awssdk/services/servicediscovery/model/NamespaceFilter;)Ljava/util/List;
      25: invokevirtual #11                 // Method values:(Ljava/util/Collection;)Lsoftware/amazon/awssdk/services/servicediscovery/model/NamespaceFilter$Builder;
      28: pop
      29: aload_0
      30: aload_1
      31: invokestatic  #12                 // Method software/amazon/awssdk/services/servicediscovery/model/NamespaceFilter.access$700:(Lsoftware/amazon/awssdk/services/servicediscovery/model/NamespaceFilter;)Ljava/lang/String;
      34: invokevirtual #13                 // Method condition:(Ljava/lang/String;)Lsoftware/amazon/awssdk/services/servicediscovery/model/NamespaceFilter$Builder;
      37: pop
      38: return

  public final java.lang.String getName();
    Code:
       0: aload_0
       1: getfield      #5                  // Field name:Ljava/lang/String;
       4: areturn

  public final void setName(java.lang.String);
    Code:
       0: aload_0
       1: aload_1
       2: putfield      #5                  // Field name:Ljava/lang/String;
       5: return

  public final software.amazon.awssdk.services.servicediscovery.model.NamespaceFilter$Builder name(java.lang.String);
    Code:
       0: aload_0
       1: aload_1
       2: putfield      #5                  // Field name:Ljava/lang/String;
       5: aload_0
       6: areturn

  public final software.amazon.awssdk.services.servicediscovery.model.NamespaceFilter$Builder name(software.amazon.awssdk.services.servicediscovery.model.NamespaceFilterName);
    Code:
       0: aload_0
       1: aload_1
       2: ifnonnull     9
       5: aconst_null
       6: goto          13
       9: aload_1
      10: invokevirtual #14                 // Method software/amazon/awssdk/services/servicediscovery/model/NamespaceFilterName.toString:()Ljava/lang/String;
      13: invokevirtual #9                  // Method name:(Ljava/lang/String;)Lsoftware/amazon/awssdk/services/servicediscovery/model/NamespaceFilter$Builder;
      16: pop
      17: aload_0
      18: areturn

  public final java.util.Collection<java.lang.String> getValues();
    Code:
       0: aload_0
       1: getfield      #4                  // Field values:Ljava/util/List;
       4: instanceof    #15                 // class software/amazon/awssdk/core/util/SdkAutoConstructList
       7: ifeq          12
      10: aconst_null
      11: areturn
      12: aload_0
      13: getfield      #4                  // Field values:Ljava/util/List;
      16: areturn

  public final void setValues(java.util.Collection<java.lang.String>);
    Code:
       0: aload_0
       1: aload_1
       2: invokestatic  #16                 // Method software/amazon/awssdk/services/servicediscovery/model/FilterValuesCopier.copy:(Ljava/util/Collection;)Ljava/util/List;
       5: putfield      #4                  // Field values:Ljava/util/List;
       8: return

  public final software.amazon.awssdk.services.servicediscovery.model.NamespaceFilter$Builder values(java.util.Collection<java.lang.String>);
    Code:
       0: aload_0
       1: aload_1
       2: invokestatic  #16                 // Method software/amazon/awssdk/services/servicediscovery/model/FilterValuesCopier.copy:(Ljava/util/Collection;)Ljava/util/List;
       5: putfield      #4                  // Field values:Ljava/util/List;
       8: aload_0
       9: areturn

  public final software.amazon.awssdk.services.servicediscovery.model.NamespaceFilter$Builder values(java.lang.String...);
    Code:
       0: aload_0
       1: aload_1
       2: invokestatic  #17                 // Method java/util/Arrays.asList:([Ljava/lang/Object;)Ljava/util/List;
       5: invokevirtual #11                 // Method values:(Ljava/util/Collection;)Lsoftware/amazon/awssdk/services/servicediscovery/model/NamespaceFilter$Builder;
       8: pop
       9: aload_0
      10: areturn

  public final java.lang.String getCondition();
    Code:
       0: aload_0
       1: getfield      #3                  // Field condition:Ljava/lang/String;
       4: areturn

  public final void setCondition(java.lang.String);
    Code:
       0: aload_0
       1: aload_1
       2: putfield      #3                  // Field condition:Ljava/lang/String;
       5: return

  public final software.amazon.awssdk.services.servicediscovery.model.NamespaceFilter$Builder condition(java.lang.String);
    Code:
       0: aload_0
       1: aload_1
       2: putfield      #3                  // Field condition:Ljava/lang/String;
       5: aload_0
       6: areturn

  public final software.amazon.awssdk.services.servicediscovery.model.NamespaceFilter$Builder condition(software.amazon.awssdk.services.servicediscovery.model.FilterCondition);
    Code:
       0: aload_0
       1: aload_1
       2: ifnonnull     9
       5: aconst_null
       6: goto          13
       9: aload_1
      10: invokevirtual #18                 // Method software/amazon/awssdk/services/servicediscovery/model/FilterCondition.toString:()Ljava/lang/String;
      13: invokevirtual #13                 // Method condition:(Ljava/lang/String;)Lsoftware/amazon/awssdk/services/servicediscovery/model/NamespaceFilter$Builder;
      16: pop
      17: aload_0
      18: areturn

  public software.amazon.awssdk.services.servicediscovery.model.NamespaceFilter build();
    Code:
       0: new           #19                 // class software/amazon/awssdk/services/servicediscovery/model/NamespaceFilter
       3: dup
       4: aload_0
       5: aconst_null
       6: invokespecial #20                 // Method software/amazon/awssdk/services/servicediscovery/model/NamespaceFilter."<init>":(Lsoftware/amazon/awssdk/services/servicediscovery/model/NamespaceFilter$BuilderImpl;Lsoftware/amazon/awssdk/services/servicediscovery/model/NamespaceFilter$1;)V
       9: areturn

  public java.util.List<software.amazon.awssdk.core.SdkField<?>> sdkFields();
    Code:
       0: invokestatic  #21                 // Method software/amazon/awssdk/services/servicediscovery/model/NamespaceFilter.access$900:()Ljava/util/List;
       3: areturn

  public java.lang.Object build();
    Code:
       0: aload_0
       1: invokevirtual #22                 // Method build:()Lsoftware/amazon/awssdk/services/servicediscovery/model/NamespaceFilter;
       4: areturn

  static java.lang.String access$000(software.amazon.awssdk.services.servicediscovery.model.NamespaceFilter$BuilderImpl);
    Code:
       0: aload_0
       1: getfield      #5                  // Field name:Ljava/lang/String;
       4: areturn

  static java.util.List access$100(software.amazon.awssdk.services.servicediscovery.model.NamespaceFilter$BuilderImpl);
    Code:
       0: aload_0
       1: getfield      #4                  // Field values:Ljava/util/List;
       4: areturn

  static java.lang.String access$200(software.amazon.awssdk.services.servicediscovery.model.NamespaceFilter$BuilderImpl);
    Code:
       0: aload_0
       1: getfield      #3                  // Field condition:Ljava/lang/String;
       4: areturn

  software.amazon.awssdk.services.servicediscovery.model.NamespaceFilter$BuilderImpl(software.amazon.awssdk.services.servicediscovery.model.NamespaceFilter, software.amazon.awssdk.services.servicediscovery.model.NamespaceFilter$1);
    Code:
       0: aload_0
       1: aload_1
       2: invokespecial #2                  // Method "<init>":(Lsoftware/amazon/awssdk/services/servicediscovery/model/NamespaceFilter;)V
       5: return

  software.amazon.awssdk.services.servicediscovery.model.NamespaceFilter$BuilderImpl(software.amazon.awssdk.services.servicediscovery.model.NamespaceFilter$1);
    Code:
       0: aload_0
       1: invokespecial #1                  // Method "<init>":()V
       4: return
}
