Compiled from "PublicDnsNamespaceProperties.java"
public interface software.amazon.awssdk.services.servicediscovery.model.PublicDnsNamespaceProperties$Builder extends software.amazon.awssdk.core.SdkPojo, software.amazon.awssdk.utils.builder.CopyableBuilder<software.amazon.awssdk.services.servicediscovery.model.PublicDnsNamespaceProperties$Builder, software.amazon.awssdk.services.servicediscovery.model.PublicDnsNamespaceProperties> {
  public abstract software.amazon.awssdk.services.servicediscovery.model.PublicDnsNamespaceProperties$Builder dnsProperties(software.amazon.awssdk.services.servicediscovery.model.PublicDnsPropertiesMutable);

  public default software.amazon.awssdk.services.servicediscovery.model.PublicDnsNamespaceProperties$Builder dnsProperties(java.util.function.Consumer<software.amazon.awssdk.services.servicediscovery.model.PublicDnsPropertiesMutable$Builder>);
    Code:
       0: aload_0
       1: invokestatic  #1                  // Method software/amazon/awssdk/services/servicediscovery/model/PublicDnsPropertiesMutable.builder:()Lsoftware/amazon/awssdk/services/servicediscovery/model/PublicDnsPropertiesMutable$Builder;
       4: aload_1
       5: invokeinterface #2,  2            // InterfaceMethod software/amazon/awssdk/services/servicediscovery/model/PublicDnsPropertiesMutable$Builder.applyMutation:(Ljava/util/function/Consumer;)Lsoftware/amazon/awssdk/utils/builder/SdkBuilder;
      10: checkcast     #3                  // class software/amazon/awssdk/services/servicediscovery/model/PublicDnsPropertiesMutable$Builder
      13: invokeinterface #4,  1            // InterfaceMethod software/amazon/awssdk/services/servicediscovery/model/PublicDnsPropertiesMutable$Builder.build:()Ljava/lang/Object;
      18: checkcast     #5                  // class software/amazon/awssdk/services/servicediscovery/model/PublicDnsPropertiesMutable
      21: invokeinterface #6,  2            // InterfaceMethod dnsProperties:(Lsoftware/amazon/awssdk/services/servicediscovery/model/PublicDnsPropertiesMutable;)Lsoftware/amazon/awssdk/services/servicediscovery/model/PublicDnsNamespaceProperties$Builder;
      26: areturn
}
