Compiled from "ClusteredInstanceFactoryWrapper.java"
public class net.sf.ehcache.terracotta.ClusteredInstanceFactoryWrapper implements net.sf.ehcache.terracotta.ClusteredInstanceFactory {
  private final net.sf.ehcache.terracotta.TerracottaClient client;

  private final net.sf.ehcache.terracotta.ClusteredInstanceFactory delegate;

  public net.sf.ehcache.terracotta.ClusteredInstanceFactoryWrapper(net.sf.ehcache.terracotta.TerracottaClient, net.sf.ehcache.terracotta.ClusteredInstanceFactory);
    Code:
       0: aload_0
       1: invokespecial #1                  // Method java/lang/Object."<init>":()V
       4: aload_0
       5: aload_1
       6: putfield      #2                  // Field client:Lnet/sf/ehcache/terracotta/TerracottaClient;
       9: aload_0
      10: aload_2
      11: putfield      #3                  // Field delegate:Lnet/sf/ehcache/terracotta/ClusteredInstanceFactory;
      14: return

  protected net.sf.ehcache.terracotta.ClusteredInstanceFactory getActualFactory();
    Code:
       0: aload_0
       1: getfield      #3                  // Field delegate:Lnet/sf/ehcache/terracotta/ClusteredInstanceFactory;
       4: areturn

  public net.sf.ehcache.cluster.CacheCluster getTopology();
    Code:
       0: aload_0
       1: getfield      #2                  // Field client:Lnet/sf/ehcache/terracotta/TerracottaClient;
       4: invokevirtual #4                  // Method net/sf/ehcache/terracotta/TerracottaClient.waitUntilRejoinComplete:()V
       7: aload_0
       8: getfield      #2                  // Field client:Lnet/sf/ehcache/terracotta/TerracottaClient;
      11: invokevirtual #5                  // Method net/sf/ehcache/terracotta/TerracottaClient.getCacheCluster:()Lnet/sf/ehcache/terracotta/TerracottaCacheCluster;
      14: areturn

  public java.lang.String getUUID();
    Code:
       0: aload_0
       1: getfield      #2                  // Field client:Lnet/sf/ehcache/terracotta/TerracottaClient;
       4: invokevirtual #4                  // Method net/sf/ehcache/terracotta/TerracottaClient.waitUntilRejoinComplete:()V
       7: aload_0
       8: getfield      #3                  // Field delegate:Lnet/sf/ehcache/terracotta/ClusteredInstanceFactory;
      11: invokeinterface #6,  1            // InterfaceMethod net/sf/ehcache/terracotta/ClusteredInstanceFactory.getUUID:()Ljava/lang/String;
      16: areturn

  public net.sf.ehcache.event.CacheEventListener createEventReplicator(net.sf.ehcache.Ehcache);
    Code:
       0: aload_0
       1: getfield      #2                  // Field client:Lnet/sf/ehcache/terracotta/TerracottaClient;
       4: invokevirtual #4                  // Method net/sf/ehcache/terracotta/TerracottaClient.waitUntilRejoinComplete:()V
       7: aload_0
       8: getfield      #3                  // Field delegate:Lnet/sf/ehcache/terracotta/ClusteredInstanceFactory;
      11: aload_1
      12: invokeinterface #7,  2            // InterfaceMethod net/sf/ehcache/terracotta/ClusteredInstanceFactory.createEventReplicator:(Lnet/sf/ehcache/Ehcache;)Lnet/sf/ehcache/event/CacheEventListener;
      17: areturn

  public net.sf.ehcache.store.Store createStore(net.sf.ehcache.Ehcache);
    Code:
       0: aload_0
       1: getfield      #2                  // Field client:Lnet/sf/ehcache/terracotta/TerracottaClient;
       4: invokevirtual #4                  // Method net/sf/ehcache/terracotta/TerracottaClient.waitUntilRejoinComplete:()V
       7: aload_0
       8: getfield      #3                  // Field delegate:Lnet/sf/ehcache/terracotta/ClusteredInstanceFactory;
      11: aload_1
      12: invokeinterface #8,  2            // InterfaceMethod net/sf/ehcache/terracotta/ClusteredInstanceFactory.createStore:(Lnet/sf/ehcache/Ehcache;)Lnet/sf/ehcache/store/Store;
      17: areturn

  public net.sf.ehcache.transaction.TransactionIDFactory createTransactionIDFactory(java.lang.String, java.lang.String);
    Code:
       0: aload_0
       1: getfield      #2                  // Field client:Lnet/sf/ehcache/terracotta/TerracottaClient;
       4: invokevirtual #4                  // Method net/sf/ehcache/terracotta/TerracottaClient.waitUntilRejoinComplete:()V
       7: aload_0
       8: getfield      #3                  // Field delegate:Lnet/sf/ehcache/terracotta/ClusteredInstanceFactory;
      11: aload_1
      12: aload_2
      13: invokeinterface #9,  3            // InterfaceMethod net/sf/ehcache/terracotta/ClusteredInstanceFactory.createTransactionIDFactory:(Ljava/lang/String;Ljava/lang/String;)Lnet/sf/ehcache/transaction/TransactionIDFactory;
      18: areturn

  public net.sf.ehcache.writer.writebehind.WriteBehind createWriteBehind(net.sf.ehcache.Ehcache);
    Code:
       0: aload_0
       1: getfield      #2                  // Field client:Lnet/sf/ehcache/terracotta/TerracottaClient;
       4: invokevirtual #4                  // Method net/sf/ehcache/terracotta/TerracottaClient.waitUntilRejoinComplete:()V
       7: aload_0
       8: getfield      #3                  // Field delegate:Lnet/sf/ehcache/terracotta/ClusteredInstanceFactory;
      11: aload_1
      12: invokeinterface #10,  2           // InterfaceMethod net/sf/ehcache/terracotta/ClusteredInstanceFactory.createWriteBehind:(Lnet/sf/ehcache/Ehcache;)Lnet/sf/ehcache/writer/writebehind/WriteBehind;
      17: areturn

  public net.sf.ehcache.transaction.SoftLockManager getOrCreateSoftLockManager(net.sf.ehcache.Ehcache);
    Code:
       0: aload_0
       1: getfield      #2                  // Field client:Lnet/sf/ehcache/terracotta/TerracottaClient;
       4: invokevirtual #4                  // Method net/sf/ehcache/terracotta/TerracottaClient.waitUntilRejoinComplete:()V
       7: aload_0
       8: getfield      #3                  // Field delegate:Lnet/sf/ehcache/terracotta/ClusteredInstanceFactory;
      11: aload_1
      12: invokeinterface #11,  2           // InterfaceMethod net/sf/ehcache/terracotta/ClusteredInstanceFactory.getOrCreateSoftLockManager:(Lnet/sf/ehcache/Ehcache;)Lnet/sf/ehcache/transaction/SoftLockManager;
      17: areturn

  public void shutdown();
    Code:
       0: aload_0
       1: getfield      #3                  // Field delegate:Lnet/sf/ehcache/terracotta/ClusteredInstanceFactory;
       4: invokeinterface #12,  1           // InterfaceMethod net/sf/ehcache/terracotta/ClusteredInstanceFactory.shutdown:()V
       9: return
}
