Compiled from "DAnnotation.java"
public class org.kohsuke.rngom.digested.DAnnotation$Attribute {
  private final java.lang.String ns;

  private final java.lang.String localName;

  private final java.lang.String prefix;

  private java.lang.String value;

  private org.xml.sax.Locator loc;

  public org.kohsuke.rngom.digested.DAnnotation$Attribute(java.lang.String, java.lang.String, java.lang.String);
    Code:
       0: aload_0
       1: invokespecial #1                  // Method java/lang/Object."<init>":()V
       4: aload_0
       5: aload_1
       6: putfield      #2                  // Field ns:Ljava/lang/String;
       9: aload_0
      10: aload_2
      11: putfield      #3                  // Field localName:Ljava/lang/String;
      14: aload_0
      15: aload_3
      16: putfield      #4                  // Field prefix:Ljava/lang/String;
      19: return

  public org.kohsuke.rngom.digested.DAnnotation$Attribute(java.lang.String, java.lang.String, java.lang.String, java.lang.String, org.xml.sax.Locator);
    Code:
       0: aload_0
       1: invokespecial #1                  // Method java/lang/Object."<init>":()V
       4: aload_0
       5: aload_1
       6: putfield      #2                  // Field ns:Ljava/lang/String;
       9: aload_0
      10: aload_2
      11: putfield      #3                  // Field localName:Ljava/lang/String;
      14: aload_0
      15: aload_3
      16: putfield      #4                  // Field prefix:Ljava/lang/String;
      19: aload_0
      20: aload         4
      22: putfield      #5                  // Field value:Ljava/lang/String;
      25: aload_0
      26: aload         5
      28: putfield      #6                  // Field loc:Lorg/xml/sax/Locator;
      31: return

  public java.lang.String getNs();
    Code:
       0: aload_0
       1: getfield      #2                  // Field ns:Ljava/lang/String;
       4: areturn

  public java.lang.String getLocalName();
    Code:
       0: aload_0
       1: getfield      #3                  // Field localName:Ljava/lang/String;
       4: areturn

  public java.lang.String getPrefix();
    Code:
       0: aload_0
       1: getfield      #4                  // Field prefix:Ljava/lang/String;
       4: areturn

  public java.lang.String getValue();
    Code:
       0: aload_0
       1: getfield      #5                  // Field value:Ljava/lang/String;
       4: areturn

  public org.xml.sax.Locator getLoc();
    Code:
       0: aload_0
       1: getfield      #6                  // Field loc:Lorg/xml/sax/Locator;
       4: areturn
}
