Compiled from "DOMPrinter.java"
class org.kohsuke.rngom.digested.DOMPrinter {
  protected javax.xml.stream.XMLStreamWriter out;

  public org.kohsuke.rngom.digested.DOMPrinter(javax.xml.stream.XMLStreamWriter);
    Code:
       0: aload_0
       1: invokespecial #1                  // Method java/lang/Object."<init>":()V
       4: aload_0
       5: aload_1
       6: putfield      #2                  // Field out:Ljavax/xml/stream/XMLStreamWriter;
       9: return

  public void print(org.w3c.dom.Node) throws javax.xml.stream.XMLStreamException;
    Code:
       0: aload_1
       1: invokeinterface #3,  1            // InterfaceMethod org/w3c/dom/Node.getNodeType:()S
       6: tableswitch   { // 1 to 11
                     1: 86
                     2: 155
                     3: 97
                     4: 108
                     5: 130
                     6: 155
                     7: 119
                     8: 141
                     9: 64
                    10: 152
                    11: 75
               default: 155
          }
      64: aload_0
      65: aload_1
      66: checkcast     #4                  // class org/w3c/dom/Document
      69: invokevirtual #5                  // Method visitDocument:(Lorg/w3c/dom/Document;)V
      72: goto          187
      75: aload_0
      76: aload_1
      77: checkcast     #6                  // class org/w3c/dom/DocumentFragment
      80: invokevirtual #7                  // Method visitDocumentFragment:(Lorg/w3c/dom/DocumentFragment;)V
      83: goto          187
      86: aload_0
      87: aload_1
      88: checkcast     #8                  // class org/w3c/dom/Element
      91: invokevirtual #9                  // Method visitElement:(Lorg/w3c/dom/Element;)V
      94: goto          187
      97: aload_0
      98: aload_1
      99: checkcast     #10                 // class org/w3c/dom/Text
     102: invokevirtual #11                 // Method visitText:(Lorg/w3c/dom/Text;)V
     105: goto          187
     108: aload_0
     109: aload_1
     110: checkcast     #12                 // class org/w3c/dom/CDATASection
     113: invokevirtual #13                 // Method visitCDATASection:(Lorg/w3c/dom/CDATASection;)V
     116: goto          187
     119: aload_0
     120: aload_1
     121: checkcast     #14                 // class org/w3c/dom/ProcessingInstruction
     124: invokevirtual #15                 // Method visitProcessingInstruction:(Lorg/w3c/dom/ProcessingInstruction;)V
     127: goto          187
     130: aload_0
     131: aload_1
     132: checkcast     #16                 // class org/w3c/dom/EntityReference
     135: invokevirtual #17                 // Method visitReference:(Lorg/w3c/dom/EntityReference;)V
     138: goto          187
     141: aload_0
     142: aload_1
     143: checkcast     #18                 // class org/w3c/dom/Comment
     146: invokevirtual #19                 // Method visitComment:(Lorg/w3c/dom/Comment;)V
     149: goto          187
     152: goto          187
     155: new           #20                 // class javax/xml/stream/XMLStreamException
     158: dup
     159: new           #21                 // class java/lang/StringBuilder
     162: dup
     163: invokespecial #22                 // Method java/lang/StringBuilder."<init>":()V
     166: ldc           #23                 // String Unexpected DOM Node Type
     168: invokevirtual #24                 // Method java/lang/StringBuilder.append:(Ljava/lang/String;)Ljava/lang/StringBuilder;
     171: aload_1
     172: invokeinterface #3,  1            // InterfaceMethod org/w3c/dom/Node.getNodeType:()S
     177: invokevirtual #25                 // Method java/lang/StringBuilder.append:(I)Ljava/lang/StringBuilder;
     180: invokevirtual #26                 // Method java/lang/StringBuilder.toString:()Ljava/lang/String;
     183: invokespecial #27                 // Method javax/xml/stream/XMLStreamException."<init>":(Ljava/lang/String;)V
     186: athrow
     187: return

  protected void visitChildren(org.w3c.dom.Node) throws javax.xml.stream.XMLStreamException;
    Code:
       0: aload_1
       1: invokeinterface #28,  1           // InterfaceMethod org/w3c/dom/Node.getChildNodes:()Lorg/w3c/dom/NodeList;
       6: astore_2
       7: aload_2
       8: ifnull        40
      11: iconst_0
      12: istore_3
      13: iload_3
      14: aload_2
      15: invokeinterface #29,  1           // InterfaceMethod org/w3c/dom/NodeList.getLength:()I
      20: if_icmpge     40
      23: aload_0
      24: aload_2
      25: iload_3
      26: invokeinterface #30,  2           // InterfaceMethod org/w3c/dom/NodeList.item:(I)Lorg/w3c/dom/Node;
      31: invokevirtual #31                 // Method print:(Lorg/w3c/dom/Node;)V
      34: iinc          3, 1
      37: goto          13
      40: return

  protected void visitDocument(org.w3c.dom.Document) throws javax.xml.stream.XMLStreamException;
    Code:
       0: aload_0
       1: getfield      #2                  // Field out:Ljavax/xml/stream/XMLStreamWriter;
       4: invokeinterface #32,  1           // InterfaceMethod javax/xml/stream/XMLStreamWriter.writeStartDocument:()V
       9: aload_0
      10: aload_1
      11: invokeinterface #33,  1           // InterfaceMethod org/w3c/dom/Document.getDocumentElement:()Lorg/w3c/dom/Element;
      16: invokevirtual #31                 // Method print:(Lorg/w3c/dom/Node;)V
      19: aload_0
      20: getfield      #2                  // Field out:Ljavax/xml/stream/XMLStreamWriter;
      23: invokeinterface #34,  1           // InterfaceMethod javax/xml/stream/XMLStreamWriter.writeEndDocument:()V
      28: return

  protected void visitDocumentFragment(org.w3c.dom.DocumentFragment) throws javax.xml.stream.XMLStreamException;
    Code:
       0: aload_0
       1: aload_1
       2: invokevirtual #35                 // Method visitChildren:(Lorg/w3c/dom/Node;)V
       5: return

  protected void visitElement(org.w3c.dom.Element) throws javax.xml.stream.XMLStreamException;
    Code:
       0: aload_0
       1: getfield      #2                  // Field out:Ljavax/xml/stream/XMLStreamWriter;
       4: aload_1
       5: invokeinterface #36,  1           // InterfaceMethod org/w3c/dom/Element.getPrefix:()Ljava/lang/String;
      10: aload_1
      11: invokeinterface #37,  1           // InterfaceMethod org/w3c/dom/Element.getLocalName:()Ljava/lang/String;
      16: aload_1
      17: invokeinterface #38,  1           // InterfaceMethod org/w3c/dom/Element.getNamespaceURI:()Ljava/lang/String;
      22: invokeinterface #39,  4           // InterfaceMethod javax/xml/stream/XMLStreamWriter.writeStartElement:(Ljava/lang/String;Ljava/lang/String;Ljava/lang/String;)V
      27: aload_1
      28: invokeinterface #40,  1           // InterfaceMethod org/w3c/dom/Element.getAttributes:()Lorg/w3c/dom/NamedNodeMap;
      33: astore_2
      34: iconst_0
      35: istore_3
      36: iload_3
      37: aload_2
      38: invokeinterface #41,  1           // InterfaceMethod org/w3c/dom/NamedNodeMap.getLength:()I
      43: if_icmpge     66
      46: aload_0
      47: aload_2
      48: iload_3
      49: invokeinterface #42,  2           // InterfaceMethod org/w3c/dom/NamedNodeMap.item:(I)Lorg/w3c/dom/Node;
      54: checkcast     #43                 // class org/w3c/dom/Attr
      57: invokevirtual #44                 // Method visitAttr:(Lorg/w3c/dom/Attr;)V
      60: iinc          3, 1
      63: goto          36
      66: aload_0
      67: aload_1
      68: invokevirtual #35                 // Method visitChildren:(Lorg/w3c/dom/Node;)V
      71: aload_0
      72: getfield      #2                  // Field out:Ljavax/xml/stream/XMLStreamWriter;
      75: invokeinterface #45,  1           // InterfaceMethod javax/xml/stream/XMLStreamWriter.writeEndElement:()V
      80: return

  protected void visitAttr(org.w3c.dom.Attr) throws javax.xml.stream.XMLStreamException;
    Code:
       0: aload_1
       1: invokeinterface #46,  1           // InterfaceMethod org/w3c/dom/Attr.getLocalName:()Ljava/lang/String;
       6: astore_2
       7: aload_2
       8: ldc           #47                 // String xmlns
      10: invokevirtual #48                 // Method java/lang/String.equals:(Ljava/lang/Object;)Z
      13: ifeq          34
      16: aload_0
      17: getfield      #2                  // Field out:Ljavax/xml/stream/XMLStreamWriter;
      20: aload_1
      21: invokeinterface #49,  1           // InterfaceMethod org/w3c/dom/Attr.getNamespaceURI:()Ljava/lang/String;
      26: invokeinterface #50,  2           // InterfaceMethod javax/xml/stream/XMLStreamWriter.writeDefaultNamespace:(Ljava/lang/String;)V
      31: goto          125
      34: aload_1
      35: invokeinterface #51,  1           // InterfaceMethod org/w3c/dom/Attr.getPrefix:()Ljava/lang/String;
      40: astore_3
      41: aload_3
      42: ifnull        73
      45: aload_3
      46: ldc           #47                 // String xmlns
      48: invokevirtual #48                 // Method java/lang/String.equals:(Ljava/lang/Object;)Z
      51: ifeq          73
      54: aload_0
      55: getfield      #2                  // Field out:Ljavax/xml/stream/XMLStreamWriter;
      58: aload_3
      59: aload_1
      60: invokeinterface #49,  1           // InterfaceMethod org/w3c/dom/Attr.getNamespaceURI:()Ljava/lang/String;
      65: invokeinterface #52,  3           // InterfaceMethod javax/xml/stream/XMLStreamWriter.writeNamespace:(Ljava/lang/String;Ljava/lang/String;)V
      70: goto          125
      73: aload_3
      74: ifnull        103
      77: aload_0
      78: getfield      #2                  // Field out:Ljavax/xml/stream/XMLStreamWriter;
      81: aload_3
      82: aload_1
      83: invokeinterface #49,  1           // InterfaceMethod org/w3c/dom/Attr.getNamespaceURI:()Ljava/lang/String;
      88: aload_2
      89: aload_1
      90: invokeinterface #53,  1           // InterfaceMethod org/w3c/dom/Attr.getNodeValue:()Ljava/lang/String;
      95: invokeinterface #54,  5           // InterfaceMethod javax/xml/stream/XMLStreamWriter.writeAttribute:(Ljava/lang/String;Ljava/lang/String;Ljava/lang/String;Ljava/lang/String;)V
     100: goto          125
     103: aload_0
     104: getfield      #2                  // Field out:Ljavax/xml/stream/XMLStreamWriter;
     107: aload_1
     108: invokeinterface #49,  1           // InterfaceMethod org/w3c/dom/Attr.getNamespaceURI:()Ljava/lang/String;
     113: aload_2
     114: aload_1
     115: invokeinterface #53,  1           // InterfaceMethod org/w3c/dom/Attr.getNodeValue:()Ljava/lang/String;
     120: invokeinterface #55,  4           // InterfaceMethod javax/xml/stream/XMLStreamWriter.writeAttribute:(Ljava/lang/String;Ljava/lang/String;Ljava/lang/String;)V
     125: return

  protected void visitComment(org.w3c.dom.Comment) throws javax.xml.stream.XMLStreamException;
    Code:
       0: aload_0
       1: getfield      #2                  // Field out:Ljavax/xml/stream/XMLStreamWriter;
       4: aload_1
       5: invokeinterface #56,  1           // InterfaceMethod org/w3c/dom/Comment.getData:()Ljava/lang/String;
      10: invokeinterface #57,  2           // InterfaceMethod javax/xml/stream/XMLStreamWriter.writeComment:(Ljava/lang/String;)V
      15: return

  protected void visitText(org.w3c.dom.Text) throws javax.xml.stream.XMLStreamException;
    Code:
       0: aload_0
       1: getfield      #2                  // Field out:Ljavax/xml/stream/XMLStreamWriter;
       4: aload_1
       5: invokeinterface #58,  1           // InterfaceMethod org/w3c/dom/Text.getNodeValue:()Ljava/lang/String;
      10: invokeinterface #59,  2           // InterfaceMethod javax/xml/stream/XMLStreamWriter.writeCharacters:(Ljava/lang/String;)V
      15: return

  protected void visitCDATASection(org.w3c.dom.CDATASection) throws javax.xml.stream.XMLStreamException;
    Code:
       0: aload_0
       1: getfield      #2                  // Field out:Ljavax/xml/stream/XMLStreamWriter;
       4: aload_1
       5: invokeinterface #60,  1           // InterfaceMethod org/w3c/dom/CDATASection.getNodeValue:()Ljava/lang/String;
      10: invokeinterface #61,  2           // InterfaceMethod javax/xml/stream/XMLStreamWriter.writeCData:(Ljava/lang/String;)V
      15: return

  protected void visitProcessingInstruction(org.w3c.dom.ProcessingInstruction) throws javax.xml.stream.XMLStreamException;
    Code:
       0: aload_0
       1: getfield      #2                  // Field out:Ljavax/xml/stream/XMLStreamWriter;
       4: aload_1
       5: invokeinterface #62,  1           // InterfaceMethod org/w3c/dom/ProcessingInstruction.getNodeName:()Ljava/lang/String;
      10: aload_1
      11: invokeinterface #63,  1           // InterfaceMethod org/w3c/dom/ProcessingInstruction.getData:()Ljava/lang/String;
      16: invokeinterface #64,  3           // InterfaceMethod javax/xml/stream/XMLStreamWriter.writeProcessingInstruction:(Ljava/lang/String;Ljava/lang/String;)V
      21: return

  protected void visitReference(org.w3c.dom.EntityReference) throws javax.xml.stream.XMLStreamException;
    Code:
       0: aload_0
       1: aload_1
       2: invokevirtual #35                 // Method visitChildren:(Lorg/w3c/dom/Node;)V
       5: return
}
