public final class kotlin.reflect.jvm.internal.impl.serialization.deserialization.AnnotationDeserializer$WhenMappings {
  public static final int[] $EnumSwitchMapping$0;

  public static final int[] $EnumSwitchMapping$1;

  static {};
    Code:
       0: invokestatic  #20                 // Method kotlin/reflect/jvm/internal/impl/metadata/ProtoBuf$Annotation$Argument$Value$Type.values:()[Lkotlin/reflect/jvm/internal/impl/metadata/ProtoBuf$Annotation$Argument$Value$Type;
       3: arraylength
       4: newarray       int
       6: putstatic     #17                 // Field $EnumSwitchMapping$0:[I
       9: getstatic     #17                 // Field $EnumSwitchMapping$0:[I
      12: getstatic     #7                  // Field kotlin/reflect/jvm/internal/impl/metadata/ProtoBuf$Annotation$Argument$Value$Type.BYTE:Lkotlin/reflect/jvm/internal/impl/metadata/ProtoBuf$Annotation$Argument$Value$Type;
      15: invokevirtual #19                 // Method kotlin/reflect/jvm/internal/impl/metadata/ProtoBuf$Annotation$Argument$Value$Type.ordinal:()I
      18: iconst_1
      19: iastore
      20: getstatic     #17                 // Field $EnumSwitchMapping$0:[I
      23: getstatic     #8                  // Field kotlin/reflect/jvm/internal/impl/metadata/ProtoBuf$Annotation$Argument$Value$Type.CHAR:Lkotlin/reflect/jvm/internal/impl/metadata/ProtoBuf$Annotation$Argument$Value$Type;
      26: invokevirtual #19                 // Method kotlin/reflect/jvm/internal/impl/metadata/ProtoBuf$Annotation$Argument$Value$Type.ordinal:()I
      29: iconst_2
      30: iastore
      31: getstatic     #17                 // Field $EnumSwitchMapping$0:[I
      34: getstatic     #15                 // Field kotlin/reflect/jvm/internal/impl/metadata/ProtoBuf$Annotation$Argument$Value$Type.SHORT:Lkotlin/reflect/jvm/internal/impl/metadata/ProtoBuf$Annotation$Argument$Value$Type;
      37: invokevirtual #19                 // Method kotlin/reflect/jvm/internal/impl/metadata/ProtoBuf$Annotation$Argument$Value$Type.ordinal:()I
      40: iconst_3
      41: iastore
      42: getstatic     #17                 // Field $EnumSwitchMapping$0:[I
      45: getstatic     #13                 // Field kotlin/reflect/jvm/internal/impl/metadata/ProtoBuf$Annotation$Argument$Value$Type.INT:Lkotlin/reflect/jvm/internal/impl/metadata/ProtoBuf$Annotation$Argument$Value$Type;
      48: invokevirtual #19                 // Method kotlin/reflect/jvm/internal/impl/metadata/ProtoBuf$Annotation$Argument$Value$Type.ordinal:()I
      51: iconst_4
      52: iastore
      53: getstatic     #17                 // Field $EnumSwitchMapping$0:[I
      56: getstatic     #14                 // Field kotlin/reflect/jvm/internal/impl/metadata/ProtoBuf$Annotation$Argument$Value$Type.LONG:Lkotlin/reflect/jvm/internal/impl/metadata/ProtoBuf$Annotation$Argument$Value$Type;
      59: invokevirtual #19                 // Method kotlin/reflect/jvm/internal/impl/metadata/ProtoBuf$Annotation$Argument$Value$Type.ordinal:()I
      62: iconst_5
      63: iastore
      64: getstatic     #17                 // Field $EnumSwitchMapping$0:[I
      67: getstatic     #12                 // Field kotlin/reflect/jvm/internal/impl/metadata/ProtoBuf$Annotation$Argument$Value$Type.FLOAT:Lkotlin/reflect/jvm/internal/impl/metadata/ProtoBuf$Annotation$Argument$Value$Type;
      70: invokevirtual #19                 // Method kotlin/reflect/jvm/internal/impl/metadata/ProtoBuf$Annotation$Argument$Value$Type.ordinal:()I
      73: bipush        6
      75: iastore
      76: getstatic     #17                 // Field $EnumSwitchMapping$0:[I
      79: getstatic     #10                 // Field kotlin/reflect/jvm/internal/impl/metadata/ProtoBuf$Annotation$Argument$Value$Type.DOUBLE:Lkotlin/reflect/jvm/internal/impl/metadata/ProtoBuf$Annotation$Argument$Value$Type;
      82: invokevirtual #19                 // Method kotlin/reflect/jvm/internal/impl/metadata/ProtoBuf$Annotation$Argument$Value$Type.ordinal:()I
      85: bipush        7
      87: iastore
      88: getstatic     #17                 // Field $EnumSwitchMapping$0:[I
      91: getstatic     #6                  // Field kotlin/reflect/jvm/internal/impl/metadata/ProtoBuf$Annotation$Argument$Value$Type.BOOLEAN:Lkotlin/reflect/jvm/internal/impl/metadata/ProtoBuf$Annotation$Argument$Value$Type;
      94: invokevirtual #19                 // Method kotlin/reflect/jvm/internal/impl/metadata/ProtoBuf$Annotation$Argument$Value$Type.ordinal:()I
      97: bipush        8
      99: iastore
     100: getstatic     #17                 // Field $EnumSwitchMapping$0:[I
     103: getstatic     #16                 // Field kotlin/reflect/jvm/internal/impl/metadata/ProtoBuf$Annotation$Argument$Value$Type.STRING:Lkotlin/reflect/jvm/internal/impl/metadata/ProtoBuf$Annotation$Argument$Value$Type;
     106: invokevirtual #19                 // Method kotlin/reflect/jvm/internal/impl/metadata/ProtoBuf$Annotation$Argument$Value$Type.ordinal:()I
     109: bipush        9
     111: iastore
     112: getstatic     #17                 // Field $EnumSwitchMapping$0:[I
     115: getstatic     #9                  // Field kotlin/reflect/jvm/internal/impl/metadata/ProtoBuf$Annotation$Argument$Value$Type.CLASS:Lkotlin/reflect/jvm/internal/impl/metadata/ProtoBuf$Annotation$Argument$Value$Type;
     118: invokevirtual #19                 // Method kotlin/reflect/jvm/internal/impl/metadata/ProtoBuf$Annotation$Argument$Value$Type.ordinal:()I
     121: bipush        10
     123: iastore
     124: getstatic     #17                 // Field $EnumSwitchMapping$0:[I
     127: getstatic     #11                 // Field kotlin/reflect/jvm/internal/impl/metadata/ProtoBuf$Annotation$Argument$Value$Type.ENUM:Lkotlin/reflect/jvm/internal/impl/metadata/ProtoBuf$Annotation$Argument$Value$Type;
     130: invokevirtual #19                 // Method kotlin/reflect/jvm/internal/impl/metadata/ProtoBuf$Annotation$Argument$Value$Type.ordinal:()I
     133: bipush        11
     135: iastore
     136: getstatic     #17                 // Field $EnumSwitchMapping$0:[I
     139: getstatic     #4                  // Field kotlin/reflect/jvm/internal/impl/metadata/ProtoBuf$Annotation$Argument$Value$Type.ANNOTATION:Lkotlin/reflect/jvm/internal/impl/metadata/ProtoBuf$Annotation$Argument$Value$Type;
     142: invokevirtual #19                 // Method kotlin/reflect/jvm/internal/impl/metadata/ProtoBuf$Annotation$Argument$Value$Type.ordinal:()I
     145: bipush        12
     147: iastore
     148: getstatic     #17                 // Field $EnumSwitchMapping$0:[I
     151: getstatic     #5                  // Field kotlin/reflect/jvm/internal/impl/metadata/ProtoBuf$Annotation$Argument$Value$Type.ARRAY:Lkotlin/reflect/jvm/internal/impl/metadata/ProtoBuf$Annotation$Argument$Value$Type;
     154: invokevirtual #19                 // Method kotlin/reflect/jvm/internal/impl/metadata/ProtoBuf$Annotation$Argument$Value$Type.ordinal:()I
     157: bipush        13
     159: iastore
     160: invokestatic  #20                 // Method kotlin/reflect/jvm/internal/impl/metadata/ProtoBuf$Annotation$Argument$Value$Type.values:()[Lkotlin/reflect/jvm/internal/impl/metadata/ProtoBuf$Annotation$Argument$Value$Type;
     163: arraylength
     164: newarray       int
     166: putstatic     #18                 // Field $EnumSwitchMapping$1:[I
     169: getstatic     #18                 // Field $EnumSwitchMapping$1:[I
     172: getstatic     #7                  // Field kotlin/reflect/jvm/internal/impl/metadata/ProtoBuf$Annotation$Argument$Value$Type.BYTE:Lkotlin/reflect/jvm/internal/impl/metadata/ProtoBuf$Annotation$Argument$Value$Type;
     175: invokevirtual #19                 // Method kotlin/reflect/jvm/internal/impl/metadata/ProtoBuf$Annotation$Argument$Value$Type.ordinal:()I
     178: iconst_1
     179: iastore
     180: getstatic     #18                 // Field $EnumSwitchMapping$1:[I
     183: getstatic     #8                  // Field kotlin/reflect/jvm/internal/impl/metadata/ProtoBuf$Annotation$Argument$Value$Type.CHAR:Lkotlin/reflect/jvm/internal/impl/metadata/ProtoBuf$Annotation$Argument$Value$Type;
     186: invokevirtual #19                 // Method kotlin/reflect/jvm/internal/impl/metadata/ProtoBuf$Annotation$Argument$Value$Type.ordinal:()I
     189: iconst_2
     190: iastore
     191: getstatic     #18                 // Field $EnumSwitchMapping$1:[I
     194: getstatic     #15                 // Field kotlin/reflect/jvm/internal/impl/metadata/ProtoBuf$Annotation$Argument$Value$Type.SHORT:Lkotlin/reflect/jvm/internal/impl/metadata/ProtoBuf$Annotation$Argument$Value$Type;
     197: invokevirtual #19                 // Method kotlin/reflect/jvm/internal/impl/metadata/ProtoBuf$Annotation$Argument$Value$Type.ordinal:()I
     200: iconst_3
     201: iastore
     202: getstatic     #18                 // Field $EnumSwitchMapping$1:[I
     205: getstatic     #13                 // Field kotlin/reflect/jvm/internal/impl/metadata/ProtoBuf$Annotation$Argument$Value$Type.INT:Lkotlin/reflect/jvm/internal/impl/metadata/ProtoBuf$Annotation$Argument$Value$Type;
     208: invokevirtual #19                 // Method kotlin/reflect/jvm/internal/impl/metadata/ProtoBuf$Annotation$Argument$Value$Type.ordinal:()I
     211: iconst_4
     212: iastore
     213: getstatic     #18                 // Field $EnumSwitchMapping$1:[I
     216: getstatic     #14                 // Field kotlin/reflect/jvm/internal/impl/metadata/ProtoBuf$Annotation$Argument$Value$Type.LONG:Lkotlin/reflect/jvm/internal/impl/metadata/ProtoBuf$Annotation$Argument$Value$Type;
     219: invokevirtual #19                 // Method kotlin/reflect/jvm/internal/impl/metadata/ProtoBuf$Annotation$Argument$Value$Type.ordinal:()I
     222: iconst_5
     223: iastore
     224: getstatic     #18                 // Field $EnumSwitchMapping$1:[I
     227: getstatic     #12                 // Field kotlin/reflect/jvm/internal/impl/metadata/ProtoBuf$Annotation$Argument$Value$Type.FLOAT:Lkotlin/reflect/jvm/internal/impl/metadata/ProtoBuf$Annotation$Argument$Value$Type;
     230: invokevirtual #19                 // Method kotlin/reflect/jvm/internal/impl/metadata/ProtoBuf$Annotation$Argument$Value$Type.ordinal:()I
     233: bipush        6
     235: iastore
     236: getstatic     #18                 // Field $EnumSwitchMapping$1:[I
     239: getstatic     #10                 // Field kotlin/reflect/jvm/internal/impl/metadata/ProtoBuf$Annotation$Argument$Value$Type.DOUBLE:Lkotlin/reflect/jvm/internal/impl/metadata/ProtoBuf$Annotation$Argument$Value$Type;
     242: invokevirtual #19                 // Method kotlin/reflect/jvm/internal/impl/metadata/ProtoBuf$Annotation$Argument$Value$Type.ordinal:()I
     245: bipush        7
     247: iastore
     248: getstatic     #18                 // Field $EnumSwitchMapping$1:[I
     251: getstatic     #6                  // Field kotlin/reflect/jvm/internal/impl/metadata/ProtoBuf$Annotation$Argument$Value$Type.BOOLEAN:Lkotlin/reflect/jvm/internal/impl/metadata/ProtoBuf$Annotation$Argument$Value$Type;
     254: invokevirtual #19                 // Method kotlin/reflect/jvm/internal/impl/metadata/ProtoBuf$Annotation$Argument$Value$Type.ordinal:()I
     257: bipush        8
     259: iastore
     260: getstatic     #18                 // Field $EnumSwitchMapping$1:[I
     263: getstatic     #16                 // Field kotlin/reflect/jvm/internal/impl/metadata/ProtoBuf$Annotation$Argument$Value$Type.STRING:Lkotlin/reflect/jvm/internal/impl/metadata/ProtoBuf$Annotation$Argument$Value$Type;
     266: invokevirtual #19                 // Method kotlin/reflect/jvm/internal/impl/metadata/ProtoBuf$Annotation$Argument$Value$Type.ordinal:()I
     269: bipush        9
     271: iastore
     272: getstatic     #18                 // Field $EnumSwitchMapping$1:[I
     275: getstatic     #9                  // Field kotlin/reflect/jvm/internal/impl/metadata/ProtoBuf$Annotation$Argument$Value$Type.CLASS:Lkotlin/reflect/jvm/internal/impl/metadata/ProtoBuf$Annotation$Argument$Value$Type;
     278: invokevirtual #19                 // Method kotlin/reflect/jvm/internal/impl/metadata/ProtoBuf$Annotation$Argument$Value$Type.ordinal:()I
     281: bipush        10
     283: iastore
     284: getstatic     #18                 // Field $EnumSwitchMapping$1:[I
     287: getstatic     #11                 // Field kotlin/reflect/jvm/internal/impl/metadata/ProtoBuf$Annotation$Argument$Value$Type.ENUM:Lkotlin/reflect/jvm/internal/impl/metadata/ProtoBuf$Annotation$Argument$Value$Type;
     290: invokevirtual #19                 // Method kotlin/reflect/jvm/internal/impl/metadata/ProtoBuf$Annotation$Argument$Value$Type.ordinal:()I
     293: bipush        11
     295: iastore
     296: getstatic     #18                 // Field $EnumSwitchMapping$1:[I
     299: getstatic     #4                  // Field kotlin/reflect/jvm/internal/impl/metadata/ProtoBuf$Annotation$Argument$Value$Type.ANNOTATION:Lkotlin/reflect/jvm/internal/impl/metadata/ProtoBuf$Annotation$Argument$Value$Type;
     302: invokevirtual #19                 // Method kotlin/reflect/jvm/internal/impl/metadata/ProtoBuf$Annotation$Argument$Value$Type.ordinal:()I
     305: bipush        12
     307: iastore
     308: getstatic     #18                 // Field $EnumSwitchMapping$1:[I
     311: getstatic     #5                  // Field kotlin/reflect/jvm/internal/impl/metadata/ProtoBuf$Annotation$Argument$Value$Type.ARRAY:Lkotlin/reflect/jvm/internal/impl/metadata/ProtoBuf$Annotation$Argument$Value$Type;
     314: invokevirtual #19                 // Method kotlin/reflect/jvm/internal/impl/metadata/ProtoBuf$Annotation$Argument$Value$Type.ordinal:()I
     317: bipush        13
     319: iastore
     320: return
}
