Compiled from "AnnotatedCallableKind.java"
public final class kotlin.reflect.jvm.internal.impl.serialization.deserialization.AnnotatedCallableKind extends java.lang.Enum<kotlin.reflect.jvm.internal.impl.serialization.deserialization.AnnotatedCallableKind> {
  public static final kotlin.reflect.jvm.internal.impl.serialization.deserialization.AnnotatedCallableKind FUNCTION;

  public static final kotlin.reflect.jvm.internal.impl.serialization.deserialization.AnnotatedCallableKind PROPERTY;

  public static final kotlin.reflect.jvm.internal.impl.serialization.deserialization.AnnotatedCallableKind PROPERTY_GETTER;

  public static final kotlin.reflect.jvm.internal.impl.serialization.deserialization.AnnotatedCallableKind PROPERTY_SETTER;

  private static final kotlin.reflect.jvm.internal.impl.serialization.deserialization.AnnotatedCallableKind[] $VALUES;

  public static kotlin.reflect.jvm.internal.impl.serialization.deserialization.AnnotatedCallableKind[] values();
    Code:
       0: getstatic     #8                  // Field $VALUES:[Lkotlin/reflect/jvm/internal/impl/serialization/deserialization/AnnotatedCallableKind;
       3: invokevirtual #13                 // Method "[Lkotlin/reflect/jvm/internal/impl/serialization/deserialization/AnnotatedCallableKind;".clone:()Ljava/lang/Object;
       6: checkcast     #5                  // class "[Lkotlin/reflect/jvm/internal/impl/serialization/deserialization/AnnotatedCallableKind;"
       9: areturn

  public static kotlin.reflect.jvm.internal.impl.serialization.deserialization.AnnotatedCallableKind valueOf(java.lang.String);
    Code:
       0: ldc           #7                  // class kotlin/reflect/jvm/internal/impl/serialization/deserialization/AnnotatedCallableKind
       2: aload_0
       3: invokestatic  #15                 // Method java/lang/Enum.valueOf:(Ljava/lang/Class;Ljava/lang/String;)Ljava/lang/Enum;
       6: checkcast     #7                  // class kotlin/reflect/jvm/internal/impl/serialization/deserialization/AnnotatedCallableKind
       9: areturn

  private kotlin.reflect.jvm.internal.impl.serialization.deserialization.AnnotatedCallableKind();
    Code:
       0: aload_0
       1: aload_1
       2: iload_2
       3: invokespecial #14                 // Method java/lang/Enum."<init>":(Ljava/lang/String;I)V
       6: return

  static {};
    Code:
       0: new           #7                  // class kotlin/reflect/jvm/internal/impl/serialization/deserialization/AnnotatedCallableKind
       3: dup
       4: ldc           #1                  // String FUNCTION
       6: iconst_0
       7: invokespecial #16                 // Method "<init>":(Ljava/lang/String;I)V
      10: putstatic     #9                  // Field FUNCTION:Lkotlin/reflect/jvm/internal/impl/serialization/deserialization/AnnotatedCallableKind;
      13: new           #7                  // class kotlin/reflect/jvm/internal/impl/serialization/deserialization/AnnotatedCallableKind
      16: dup
      17: ldc           #2                  // String PROPERTY
      19: iconst_1
      20: invokespecial #16                 // Method "<init>":(Ljava/lang/String;I)V
      23: putstatic     #10                 // Field PROPERTY:Lkotlin/reflect/jvm/internal/impl/serialization/deserialization/AnnotatedCallableKind;
      26: new           #7                  // class kotlin/reflect/jvm/internal/impl/serialization/deserialization/AnnotatedCallableKind
      29: dup
      30: ldc           #3                  // String PROPERTY_GETTER
      32: iconst_2
      33: invokespecial #16                 // Method "<init>":(Ljava/lang/String;I)V
      36: putstatic     #11                 // Field PROPERTY_GETTER:Lkotlin/reflect/jvm/internal/impl/serialization/deserialization/AnnotatedCallableKind;
      39: new           #7                  // class kotlin/reflect/jvm/internal/impl/serialization/deserialization/AnnotatedCallableKind
      42: dup
      43: ldc           #4                  // String PROPERTY_SETTER
      45: iconst_3
      46: invokespecial #16                 // Method "<init>":(Ljava/lang/String;I)V
      49: putstatic     #12                 // Field PROPERTY_SETTER:Lkotlin/reflect/jvm/internal/impl/serialization/deserialization/AnnotatedCallableKind;
      52: iconst_4
      53: anewarray     #7                  // class kotlin/reflect/jvm/internal/impl/serialization/deserialization/AnnotatedCallableKind
      56: dup
      57: iconst_0
      58: getstatic     #9                  // Field FUNCTION:Lkotlin/reflect/jvm/internal/impl/serialization/deserialization/AnnotatedCallableKind;
      61: aastore
      62: dup
      63: iconst_1
      64: getstatic     #10                 // Field PROPERTY:Lkotlin/reflect/jvm/internal/impl/serialization/deserialization/AnnotatedCallableKind;
      67: aastore
      68: dup
      69: iconst_2
      70: getstatic     #11                 // Field PROPERTY_GETTER:Lkotlin/reflect/jvm/internal/impl/serialization/deserialization/AnnotatedCallableKind;
      73: aastore
      74: dup
      75: iconst_3
      76: getstatic     #12                 // Field PROPERTY_SETTER:Lkotlin/reflect/jvm/internal/impl/serialization/deserialization/AnnotatedCallableKind;
      79: aastore
      80: putstatic     #8                  // Field $VALUES:[Lkotlin/reflect/jvm/internal/impl/serialization/deserialization/AnnotatedCallableKind;
      83: return
}
