Compiled from "DeserializedClassDataFinder.kt"
public final class kotlin.reflect.jvm.internal.impl.serialization.deserialization.DeserializedClassDataFinder implements kotlin.reflect.jvm.internal.impl.serialization.deserialization.ClassDataFinder {
  private final kotlin.reflect.jvm.internal.impl.descriptors.PackageFragmentProvider packageFragmentProvider;

  public kotlin.reflect.jvm.internal.impl.serialization.deserialization.ClassData findClassData(kotlin.reflect.jvm.internal.impl.name.ClassId);
    Code:
       0: aload_1
       1: ldc           #1                  // String classId
       3: invokestatic  #18                 // Method kotlin/jvm/internal/Intrinsics.checkParameterIsNotNull:(Ljava/lang/Object;Ljava/lang/String;)V
       6: aload_0
       7: getfield      #15                 // Field packageFragmentProvider:Lkotlin/reflect/jvm/internal/impl/descriptors/PackageFragmentProvider;
      10: aload_1
      11: invokevirtual #19                 // Method kotlin/reflect/jvm/internal/impl/name/ClassId.getPackageFqName:()Lkotlin/reflect/jvm/internal/impl/name/FqName;
      14: dup
      15: ldc           #2                  // String classId.packageFqName
      17: invokestatic  #17                 // Method kotlin/jvm/internal/Intrinsics.checkExpressionValueIsNotNull:(Ljava/lang/Object;Ljava/lang/String;)V
      20: invokeinterface #24,  2           // InterfaceMethod kotlin/reflect/jvm/internal/impl/descriptors/PackageFragmentProvider.getPackageFragments:(Lkotlin/reflect/jvm/internal/impl/name/FqName;)Ljava/util/List;
      25: astore_2
      26: aload_2
      27: invokeinterface #23,  1           // InterfaceMethod java/util/List.iterator:()Ljava/util/Iterator;
      32: astore        4
      34: aload         4
      36: invokeinterface #21,  1           // InterfaceMethod java/util/Iterator.hasNext:()Z
      41: ifeq          95
      44: aload         4
      46: invokeinterface #22,  1           // InterfaceMethod java/util/Iterator.next:()Ljava/lang/Object;
      51: checkcast     #8                  // class kotlin/reflect/jvm/internal/impl/descriptors/PackageFragmentDescriptor
      54: astore_3
      55: aload_3
      56: instanceof    #14                 // class kotlin/reflect/jvm/internal/impl/serialization/deserialization/DeserializedPackageFragment
      59: ifne          65
      62: goto          92
      65: aload_3
      66: checkcast     #14                 // class kotlin/reflect/jvm/internal/impl/serialization/deserialization/DeserializedPackageFragment
      69: invokevirtual #20                 // Method kotlin/reflect/jvm/internal/impl/serialization/deserialization/DeserializedPackageFragment.getClassDataFinder:()Lkotlin/reflect/jvm/internal/impl/serialization/deserialization/ClassDataFinder;
      72: aload_1
      73: invokeinterface #25,  2           // InterfaceMethod kotlin/reflect/jvm/internal/impl/serialization/deserialization/ClassDataFinder.findClassData:(Lkotlin/reflect/jvm/internal/impl/name/ClassId;)Lkotlin/reflect/jvm/internal/impl/serialization/deserialization/ClassData;
      78: dup
      79: ifnull        91
      82: astore        5
      84: aload         5
      86: astore        6
      88: aload         6
      90: areturn
      91: pop
      92: goto          34
      95: aconst_null
      96: areturn

  public kotlin.reflect.jvm.internal.impl.serialization.deserialization.DeserializedClassDataFinder(kotlin.reflect.jvm.internal.impl.descriptors.PackageFragmentProvider);
    Code:
       0: aload_1
       1: ldc           #3                  // String packageFragmentProvider
       3: invokestatic  #18                 // Method kotlin/jvm/internal/Intrinsics.checkParameterIsNotNull:(Ljava/lang/Object;Ljava/lang/String;)V
       6: aload_0
       7: invokespecial #16                 // Method java/lang/Object."<init>":()V
      10: aload_0
      11: aload_1
      12: putfield      #15                 // Field packageFragmentProvider:Lkotlin/reflect/jvm/internal/impl/descriptors/PackageFragmentProvider;
      15: return
}
