Compiled from "SecurityRequestConverters.java"
final class org.elasticsearch.client.SecurityRequestConverters {
  private org.elasticsearch.client.SecurityRequestConverters();
    Code:
       0: aload_0
       1: invokespecial #1                  // Method java/lang/Object."<init>":()V
       4: return

  static org.elasticsearch.client.Request changePassword(org.elasticsearch.client.security.ChangePasswordRequest) throws java.io.IOException;
    Code:
       0: new           #2                  // class org/elasticsearch/client/RequestConverters$EndpointBuilder
       3: dup
       4: invokespecial #3                  // Method org/elasticsearch/client/RequestConverters$EndpointBuilder."<init>":()V
       7: iconst_1
       8: anewarray     #4                  // class java/lang/String
      11: dup
      12: iconst_0
      13: ldc           #5                  // String _xpack/security/user
      15: aastore
      16: invokevirtual #6                  // Method org/elasticsearch/client/RequestConverters$EndpointBuilder.addPathPartAsIs:([Ljava/lang/String;)Lorg/elasticsearch/client/RequestConverters$EndpointBuilder;
      19: iconst_1
      20: anewarray     #4                  // class java/lang/String
      23: dup
      24: iconst_0
      25: aload_0
      26: invokevirtual #7                  // Method org/elasticsearch/client/security/ChangePasswordRequest.getUsername:()Ljava/lang/String;
      29: aastore
      30: invokevirtual #8                  // Method org/elasticsearch/client/RequestConverters$EndpointBuilder.addPathPart:([Ljava/lang/String;)Lorg/elasticsearch/client/RequestConverters$EndpointBuilder;
      33: iconst_1
      34: anewarray     #4                  // class java/lang/String
      37: dup
      38: iconst_0
      39: ldc           #9                  // String _password
      41: aastore
      42: invokevirtual #6                  // Method org/elasticsearch/client/RequestConverters$EndpointBuilder.addPathPartAsIs:([Ljava/lang/String;)Lorg/elasticsearch/client/RequestConverters$EndpointBuilder;
      45: invokevirtual #10                 // Method org/elasticsearch/client/RequestConverters$EndpointBuilder.build:()Ljava/lang/String;
      48: astore_1
      49: new           #11                 // class org/elasticsearch/client/Request
      52: dup
      53: ldc           #13                 // String POST
      55: aload_1
      56: invokespecial #14                 // Method org/elasticsearch/client/Request."<init>":(Ljava/lang/String;Ljava/lang/String;)V
      59: astore_2
      60: aload_2
      61: aload_0
      62: getstatic     #15                 // Field org/elasticsearch/client/RequestConverters.REQUEST_BODY_CONTENT_TYPE:Lorg/elasticsearch/common/xcontent/XContentType;
      65: invokestatic  #16                 // Method org/elasticsearch/client/RequestConverters.createEntity:(Lorg/elasticsearch/common/xcontent/ToXContent;Lorg/elasticsearch/common/xcontent/XContentType;)Lorg/apache/http/HttpEntity;
      68: invokevirtual #17                 // Method org/elasticsearch/client/Request.setEntity:(Lorg/apache/http/HttpEntity;)V
      71: new           #18                 // class org/elasticsearch/client/RequestConverters$Params
      74: dup
      75: aload_2
      76: invokespecial #19                 // Method org/elasticsearch/client/RequestConverters$Params."<init>":(Lorg/elasticsearch/client/Request;)V
      79: astore_3
      80: aload_3
      81: aload_0
      82: invokevirtual #20                 // Method org/elasticsearch/client/security/ChangePasswordRequest.getRefreshPolicy:()Lorg/elasticsearch/client/security/RefreshPolicy;
      85: invokevirtual #21                 // Method org/elasticsearch/client/RequestConverters$Params.withRefreshPolicy:(Lorg/elasticsearch/client/security/RefreshPolicy;)Lorg/elasticsearch/client/RequestConverters$Params;
      88: pop
      89: aload_2
      90: areturn

  static org.elasticsearch.client.Request getUsers(org.elasticsearch.client.security.GetUsersRequest);
    Code:
       0: new           #2                  // class org/elasticsearch/client/RequestConverters$EndpointBuilder
       3: dup
       4: invokespecial #3                  // Method org/elasticsearch/client/RequestConverters$EndpointBuilder."<init>":()V
       7: iconst_1
       8: anewarray     #4                  // class java/lang/String
      11: dup
      12: iconst_0
      13: ldc           #22                 // String _security/user
      15: aastore
      16: invokevirtual #6                  // Method org/elasticsearch/client/RequestConverters$EndpointBuilder.addPathPartAsIs:([Ljava/lang/String;)Lorg/elasticsearch/client/RequestConverters$EndpointBuilder;
      19: astore_1
      20: aload_0
      21: invokevirtual #23                 // Method org/elasticsearch/client/security/GetUsersRequest.getUsernames:()Ljava/util/Set;
      24: invokeinterface #24,  1           // InterfaceMethod java/util/Set.size:()I
      29: ifle          51
      32: aload_1
      33: iconst_1
      34: anewarray     #4                  // class java/lang/String
      37: dup
      38: iconst_0
      39: aload_0
      40: invokevirtual #23                 // Method org/elasticsearch/client/security/GetUsersRequest.getUsernames:()Ljava/util/Set;
      43: invokestatic  #25                 // Method org/elasticsearch/common/Strings.collectionToCommaDelimitedString:(Ljava/lang/Iterable;)Ljava/lang/String;
      46: aastore
      47: invokevirtual #8                  // Method org/elasticsearch/client/RequestConverters$EndpointBuilder.addPathPart:([Ljava/lang/String;)Lorg/elasticsearch/client/RequestConverters$EndpointBuilder;
      50: pop
      51: new           #11                 // class org/elasticsearch/client/Request
      54: dup
      55: ldc           #27                 // String GET
      57: aload_1
      58: invokevirtual #10                 // Method org/elasticsearch/client/RequestConverters$EndpointBuilder.build:()Ljava/lang/String;
      61: invokespecial #14                 // Method org/elasticsearch/client/Request."<init>":(Ljava/lang/String;Ljava/lang/String;)V
      64: areturn

  static org.elasticsearch.client.Request putUser(org.elasticsearch.client.security.PutUserRequest) throws java.io.IOException;
    Code:
       0: new           #2                  // class org/elasticsearch/client/RequestConverters$EndpointBuilder
       3: dup
       4: invokespecial #3                  // Method org/elasticsearch/client/RequestConverters$EndpointBuilder."<init>":()V
       7: iconst_1
       8: anewarray     #4                  // class java/lang/String
      11: dup
      12: iconst_0
      13: ldc           #5                  // String _xpack/security/user
      15: aastore
      16: invokevirtual #6                  // Method org/elasticsearch/client/RequestConverters$EndpointBuilder.addPathPartAsIs:([Ljava/lang/String;)Lorg/elasticsearch/client/RequestConverters$EndpointBuilder;
      19: iconst_1
      20: anewarray     #4                  // class java/lang/String
      23: dup
      24: iconst_0
      25: aload_0
      26: invokevirtual #28                 // Method org/elasticsearch/client/security/PutUserRequest.getUser:()Lorg/elasticsearch/client/security/user/User;
      29: invokevirtual #29                 // Method org/elasticsearch/client/security/user/User.getUsername:()Ljava/lang/String;
      32: aastore
      33: invokevirtual #8                  // Method org/elasticsearch/client/RequestConverters$EndpointBuilder.addPathPart:([Ljava/lang/String;)Lorg/elasticsearch/client/RequestConverters$EndpointBuilder;
      36: invokevirtual #10                 // Method org/elasticsearch/client/RequestConverters$EndpointBuilder.build:()Ljava/lang/String;
      39: astore_1
      40: new           #11                 // class org/elasticsearch/client/Request
      43: dup
      44: ldc           #31                 // String PUT
      46: aload_1
      47: invokespecial #14                 // Method org/elasticsearch/client/Request."<init>":(Ljava/lang/String;Ljava/lang/String;)V
      50: astore_2
      51: aload_2
      52: aload_0
      53: getstatic     #15                 // Field org/elasticsearch/client/RequestConverters.REQUEST_BODY_CONTENT_TYPE:Lorg/elasticsearch/common/xcontent/XContentType;
      56: invokestatic  #16                 // Method org/elasticsearch/client/RequestConverters.createEntity:(Lorg/elasticsearch/common/xcontent/ToXContent;Lorg/elasticsearch/common/xcontent/XContentType;)Lorg/apache/http/HttpEntity;
      59: invokevirtual #17                 // Method org/elasticsearch/client/Request.setEntity:(Lorg/apache/http/HttpEntity;)V
      62: new           #18                 // class org/elasticsearch/client/RequestConverters$Params
      65: dup
      66: aload_2
      67: invokespecial #19                 // Method org/elasticsearch/client/RequestConverters$Params."<init>":(Lorg/elasticsearch/client/Request;)V
      70: astore_3
      71: aload_3
      72: aload_0
      73: invokevirtual #32                 // Method org/elasticsearch/client/security/PutUserRequest.getRefreshPolicy:()Lorg/elasticsearch/client/security/RefreshPolicy;
      76: invokevirtual #21                 // Method org/elasticsearch/client/RequestConverters$Params.withRefreshPolicy:(Lorg/elasticsearch/client/security/RefreshPolicy;)Lorg/elasticsearch/client/RequestConverters$Params;
      79: pop
      80: aload_2
      81: areturn

  static org.elasticsearch.client.Request deleteUser(org.elasticsearch.client.security.DeleteUserRequest);
    Code:
       0: new           #2                  // class org/elasticsearch/client/RequestConverters$EndpointBuilder
       3: dup
       4: invokespecial #3                  // Method org/elasticsearch/client/RequestConverters$EndpointBuilder."<init>":()V
       7: iconst_3
       8: anewarray     #4                  // class java/lang/String
      11: dup
      12: iconst_0
      13: ldc           #33                 // String _xpack
      15: aastore
      16: dup
      17: iconst_1
      18: ldc           #34                 // String security
      20: aastore
      21: dup
      22: iconst_2
      23: ldc           #35                 // String user
      25: aastore
      26: invokevirtual #6                  // Method org/elasticsearch/client/RequestConverters$EndpointBuilder.addPathPartAsIs:([Ljava/lang/String;)Lorg/elasticsearch/client/RequestConverters$EndpointBuilder;
      29: iconst_1
      30: anewarray     #4                  // class java/lang/String
      33: dup
      34: iconst_0
      35: aload_0
      36: invokevirtual #36                 // Method org/elasticsearch/client/security/DeleteUserRequest.getName:()Ljava/lang/String;
      39: aastore
      40: invokevirtual #8                  // Method org/elasticsearch/client/RequestConverters$EndpointBuilder.addPathPart:([Ljava/lang/String;)Lorg/elasticsearch/client/RequestConverters$EndpointBuilder;
      43: invokevirtual #10                 // Method org/elasticsearch/client/RequestConverters$EndpointBuilder.build:()Ljava/lang/String;
      46: astore_1
      47: new           #11                 // class org/elasticsearch/client/Request
      50: dup
      51: ldc           #38                 // String DELETE
      53: aload_1
      54: invokespecial #14                 // Method org/elasticsearch/client/Request."<init>":(Ljava/lang/String;Ljava/lang/String;)V
      57: astore_2
      58: new           #18                 // class org/elasticsearch/client/RequestConverters$Params
      61: dup
      62: aload_2
      63: invokespecial #19                 // Method org/elasticsearch/client/RequestConverters$Params."<init>":(Lorg/elasticsearch/client/Request;)V
      66: astore_3
      67: aload_3
      68: aload_0
      69: invokevirtual #39                 // Method org/elasticsearch/client/security/DeleteUserRequest.getRefreshPolicy:()Lorg/elasticsearch/client/security/RefreshPolicy;
      72: invokevirtual #21                 // Method org/elasticsearch/client/RequestConverters$Params.withRefreshPolicy:(Lorg/elasticsearch/client/security/RefreshPolicy;)Lorg/elasticsearch/client/RequestConverters$Params;
      75: pop
      76: aload_2
      77: areturn

  static org.elasticsearch.client.Request putRoleMapping(org.elasticsearch.client.security.PutRoleMappingRequest) throws java.io.IOException;
    Code:
       0: new           #2                  // class org/elasticsearch/client/RequestConverters$EndpointBuilder
       3: dup
       4: invokespecial #3                  // Method org/elasticsearch/client/RequestConverters$EndpointBuilder."<init>":()V
       7: iconst_1
       8: anewarray     #4                  // class java/lang/String
      11: dup
      12: iconst_0
      13: ldc           #40                 // String _xpack/security/role_mapping
      15: aastore
      16: invokevirtual #6                  // Method org/elasticsearch/client/RequestConverters$EndpointBuilder.addPathPartAsIs:([Ljava/lang/String;)Lorg/elasticsearch/client/RequestConverters$EndpointBuilder;
      19: iconst_1
      20: anewarray     #4                  // class java/lang/String
      23: dup
      24: iconst_0
      25: aload_0
      26: invokevirtual #41                 // Method org/elasticsearch/client/security/PutRoleMappingRequest.getName:()Ljava/lang/String;
      29: aastore
      30: invokevirtual #8                  // Method org/elasticsearch/client/RequestConverters$EndpointBuilder.addPathPart:([Ljava/lang/String;)Lorg/elasticsearch/client/RequestConverters$EndpointBuilder;
      33: invokevirtual #10                 // Method org/elasticsearch/client/RequestConverters$EndpointBuilder.build:()Ljava/lang/String;
      36: astore_1
      37: new           #11                 // class org/elasticsearch/client/Request
      40: dup
      41: ldc           #31                 // String PUT
      43: aload_1
      44: invokespecial #14                 // Method org/elasticsearch/client/Request."<init>":(Ljava/lang/String;Ljava/lang/String;)V
      47: astore_2
      48: aload_2
      49: aload_0
      50: getstatic     #15                 // Field org/elasticsearch/client/RequestConverters.REQUEST_BODY_CONTENT_TYPE:Lorg/elasticsearch/common/xcontent/XContentType;
      53: invokestatic  #16                 // Method org/elasticsearch/client/RequestConverters.createEntity:(Lorg/elasticsearch/common/xcontent/ToXContent;Lorg/elasticsearch/common/xcontent/XContentType;)Lorg/apache/http/HttpEntity;
      56: invokevirtual #17                 // Method org/elasticsearch/client/Request.setEntity:(Lorg/apache/http/HttpEntity;)V
      59: new           #18                 // class org/elasticsearch/client/RequestConverters$Params
      62: dup
      63: aload_2
      64: invokespecial #19                 // Method org/elasticsearch/client/RequestConverters$Params."<init>":(Lorg/elasticsearch/client/Request;)V
      67: astore_3
      68: aload_3
      69: aload_0
      70: invokevirtual #42                 // Method org/elasticsearch/client/security/PutRoleMappingRequest.getRefreshPolicy:()Lorg/elasticsearch/client/security/RefreshPolicy;
      73: invokevirtual #21                 // Method org/elasticsearch/client/RequestConverters$Params.withRefreshPolicy:(Lorg/elasticsearch/client/security/RefreshPolicy;)Lorg/elasticsearch/client/RequestConverters$Params;
      76: pop
      77: aload_2
      78: areturn

  static org.elasticsearch.client.Request getRoleMappings(org.elasticsearch.client.security.GetRoleMappingsRequest) throws java.io.IOException;
    Code:
       0: new           #2                  // class org/elasticsearch/client/RequestConverters$EndpointBuilder
       3: dup
       4: invokespecial #3                  // Method org/elasticsearch/client/RequestConverters$EndpointBuilder."<init>":()V
       7: astore_1
       8: aload_1
       9: iconst_1
      10: anewarray     #4                  // class java/lang/String
      13: dup
      14: iconst_0
      15: ldc           #40                 // String _xpack/security/role_mapping
      17: aastore
      18: invokevirtual #6                  // Method org/elasticsearch/client/RequestConverters$EndpointBuilder.addPathPartAsIs:([Ljava/lang/String;)Lorg/elasticsearch/client/RequestConverters$EndpointBuilder;
      21: pop
      22: aload_0
      23: invokevirtual #43                 // Method org/elasticsearch/client/security/GetRoleMappingsRequest.getRoleMappingNames:()Ljava/util/Set;
      26: invokeinterface #24,  1           // InterfaceMethod java/util/Set.size:()I
      31: ifle          53
      34: aload_1
      35: iconst_1
      36: anewarray     #4                  // class java/lang/String
      39: dup
      40: iconst_0
      41: aload_0
      42: invokevirtual #43                 // Method org/elasticsearch/client/security/GetRoleMappingsRequest.getRoleMappingNames:()Ljava/util/Set;
      45: invokestatic  #25                 // Method org/elasticsearch/common/Strings.collectionToCommaDelimitedString:(Ljava/lang/Iterable;)Ljava/lang/String;
      48: aastore
      49: invokevirtual #8                  // Method org/elasticsearch/client/RequestConverters$EndpointBuilder.addPathPart:([Ljava/lang/String;)Lorg/elasticsearch/client/RequestConverters$EndpointBuilder;
      52: pop
      53: new           #11                 // class org/elasticsearch/client/Request
      56: dup
      57: ldc           #27                 // String GET
      59: aload_1
      60: invokevirtual #10                 // Method org/elasticsearch/client/RequestConverters$EndpointBuilder.build:()Ljava/lang/String;
      63: invokespecial #14                 // Method org/elasticsearch/client/Request."<init>":(Ljava/lang/String;Ljava/lang/String;)V
      66: areturn

  static org.elasticsearch.client.Request enableUser(org.elasticsearch.client.security.EnableUserRequest);
    Code:
       0: aload_0
       1: invokestatic  #44                 // Method setUserEnabled:(Lorg/elasticsearch/client/security/SetUserEnabledRequest;)Lorg/elasticsearch/client/Request;
       4: areturn

  static org.elasticsearch.client.Request disableUser(org.elasticsearch.client.security.DisableUserRequest);
    Code:
       0: aload_0
       1: invokestatic  #44                 // Method setUserEnabled:(Lorg/elasticsearch/client/security/SetUserEnabledRequest;)Lorg/elasticsearch/client/Request;
       4: areturn

  private static org.elasticsearch.client.Request setUserEnabled(org.elasticsearch.client.security.SetUserEnabledRequest);
    Code:
       0: new           #2                  // class org/elasticsearch/client/RequestConverters$EndpointBuilder
       3: dup
       4: invokespecial #3                  // Method org/elasticsearch/client/RequestConverters$EndpointBuilder."<init>":()V
       7: iconst_1
       8: anewarray     #4                  // class java/lang/String
      11: dup
      12: iconst_0
      13: ldc           #5                  // String _xpack/security/user
      15: aastore
      16: invokevirtual #6                  // Method org/elasticsearch/client/RequestConverters$EndpointBuilder.addPathPartAsIs:([Ljava/lang/String;)Lorg/elasticsearch/client/RequestConverters$EndpointBuilder;
      19: iconst_1
      20: anewarray     #4                  // class java/lang/String
      23: dup
      24: iconst_0
      25: aload_0
      26: invokevirtual #45                 // Method org/elasticsearch/client/security/SetUserEnabledRequest.getUsername:()Ljava/lang/String;
      29: aastore
      30: invokevirtual #8                  // Method org/elasticsearch/client/RequestConverters$EndpointBuilder.addPathPart:([Ljava/lang/String;)Lorg/elasticsearch/client/RequestConverters$EndpointBuilder;
      33: iconst_1
      34: anewarray     #4                  // class java/lang/String
      37: dup
      38: iconst_0
      39: aload_0
      40: invokevirtual #46                 // Method org/elasticsearch/client/security/SetUserEnabledRequest.isEnabled:()Z
      43: ifeq          51
      46: ldc           #47                 // String _enable
      48: goto          53
      51: ldc           #48                 // String _disable
      53: aastore
      54: invokevirtual #8                  // Method org/elasticsearch/client/RequestConverters$EndpointBuilder.addPathPart:([Ljava/lang/String;)Lorg/elasticsearch/client/RequestConverters$EndpointBuilder;
      57: invokevirtual #10                 // Method org/elasticsearch/client/RequestConverters$EndpointBuilder.build:()Ljava/lang/String;
      60: astore_1
      61: new           #11                 // class org/elasticsearch/client/Request
      64: dup
      65: ldc           #31                 // String PUT
      67: aload_1
      68: invokespecial #14                 // Method org/elasticsearch/client/Request."<init>":(Ljava/lang/String;Ljava/lang/String;)V
      71: astore_2
      72: new           #18                 // class org/elasticsearch/client/RequestConverters$Params
      75: dup
      76: aload_2
      77: invokespecial #19                 // Method org/elasticsearch/client/RequestConverters$Params."<init>":(Lorg/elasticsearch/client/Request;)V
      80: astore_3
      81: aload_3
      82: aload_0
      83: invokevirtual #49                 // Method org/elasticsearch/client/security/SetUserEnabledRequest.getRefreshPolicy:()Lorg/elasticsearch/client/security/RefreshPolicy;
      86: invokevirtual #21                 // Method org/elasticsearch/client/RequestConverters$Params.withRefreshPolicy:(Lorg/elasticsearch/client/security/RefreshPolicy;)Lorg/elasticsearch/client/RequestConverters$Params;
      89: pop
      90: aload_2
      91: areturn

  static org.elasticsearch.client.Request hasPrivileges(org.elasticsearch.client.security.HasPrivilegesRequest) throws java.io.IOException;
    Code:
       0: new           #11                 // class org/elasticsearch/client/Request
       3: dup
       4: ldc           #27                 // String GET
       6: ldc           #50                 // String /_xpack/security/user/_has_privileges
       8: invokespecial #14                 // Method org/elasticsearch/client/Request."<init>":(Ljava/lang/String;Ljava/lang/String;)V
      11: astore_1
      12: aload_1
      13: aload_0
      14: getstatic     #15                 // Field org/elasticsearch/client/RequestConverters.REQUEST_BODY_CONTENT_TYPE:Lorg/elasticsearch/common/xcontent/XContentType;
      17: invokestatic  #16                 // Method org/elasticsearch/client/RequestConverters.createEntity:(Lorg/elasticsearch/common/xcontent/ToXContent;Lorg/elasticsearch/common/xcontent/XContentType;)Lorg/apache/http/HttpEntity;
      20: invokevirtual #17                 // Method org/elasticsearch/client/Request.setEntity:(Lorg/apache/http/HttpEntity;)V
      23: aload_1
      24: areturn

  static org.elasticsearch.client.Request clearRealmCache(org.elasticsearch.client.security.ClearRealmCacheRequest);
    Code:
       0: new           #2                  // class org/elasticsearch/client/RequestConverters$EndpointBuilder
       3: dup
       4: invokespecial #3                  // Method org/elasticsearch/client/RequestConverters$EndpointBuilder."<init>":()V
       7: iconst_1
       8: anewarray     #4                  // class java/lang/String
      11: dup
      12: iconst_0
      13: ldc           #51                 // String _xpack/security/realm
      15: aastore
      16: invokevirtual #6                  // Method org/elasticsearch/client/RequestConverters$EndpointBuilder.addPathPartAsIs:([Ljava/lang/String;)Lorg/elasticsearch/client/RequestConverters$EndpointBuilder;
      19: astore_1
      20: aload_0
      21: invokevirtual #52                 // Method org/elasticsearch/client/security/ClearRealmCacheRequest.getRealms:()Ljava/util/List;
      24: invokeinterface #53,  1           // InterfaceMethod java/util/List.isEmpty:()Z
      29: ifne          55
      32: aload_1
      33: aload_0
      34: invokevirtual #52                 // Method org/elasticsearch/client/security/ClearRealmCacheRequest.getRealms:()Ljava/util/List;
      37: getstatic     #54                 // Field org/elasticsearch/common/Strings.EMPTY_ARRAY:[Ljava/lang/String;
      40: invokeinterface #55,  2           // InterfaceMethod java/util/List.toArray:([Ljava/lang/Object;)[Ljava/lang/Object;
      45: checkcast     #56                 // class "[Ljava/lang/String;"
      48: invokevirtual #57                 // Method org/elasticsearch/client/RequestConverters$EndpointBuilder.addCommaSeparatedPathParts:([Ljava/lang/String;)Lorg/elasticsearch/client/RequestConverters$EndpointBuilder;
      51: pop
      52: goto          69
      55: aload_1
      56: iconst_1
      57: anewarray     #4                  // class java/lang/String
      60: dup
      61: iconst_0
      62: ldc           #58                 // String _all
      64: aastore
      65: invokevirtual #8                  // Method org/elasticsearch/client/RequestConverters$EndpointBuilder.addPathPart:([Ljava/lang/String;)Lorg/elasticsearch/client/RequestConverters$EndpointBuilder;
      68: pop
      69: aload_1
      70: iconst_1
      71: anewarray     #4                  // class java/lang/String
      74: dup
      75: iconst_0
      76: ldc           #59                 // String _clear_cache
      78: aastore
      79: invokevirtual #6                  // Method org/elasticsearch/client/RequestConverters$EndpointBuilder.addPathPartAsIs:([Ljava/lang/String;)Lorg/elasticsearch/client/RequestConverters$EndpointBuilder;
      82: invokevirtual #10                 // Method org/elasticsearch/client/RequestConverters$EndpointBuilder.build:()Ljava/lang/String;
      85: astore_2
      86: new           #11                 // class org/elasticsearch/client/Request
      89: dup
      90: ldc           #13                 // String POST
      92: aload_2
      93: invokespecial #14                 // Method org/elasticsearch/client/Request."<init>":(Ljava/lang/String;Ljava/lang/String;)V
      96: astore_3
      97: aload_0
      98: invokevirtual #60                 // Method org/elasticsearch/client/security/ClearRealmCacheRequest.getUsernames:()Ljava/util/List;
     101: invokeinterface #53,  1           // InterfaceMethod java/util/List.isEmpty:()Z
     106: ifne          134
     109: new           #18                 // class org/elasticsearch/client/RequestConverters$Params
     112: dup
     113: aload_3
     114: invokespecial #19                 // Method org/elasticsearch/client/RequestConverters$Params."<init>":(Lorg/elasticsearch/client/Request;)V
     117: astore        4
     119: aload         4
     121: ldc           #61                 // String usernames
     123: aload_0
     124: invokevirtual #60                 // Method org/elasticsearch/client/security/ClearRealmCacheRequest.getUsernames:()Ljava/util/List;
     127: invokestatic  #25                 // Method org/elasticsearch/common/Strings.collectionToCommaDelimitedString:(Ljava/lang/Iterable;)Ljava/lang/String;
     130: invokevirtual #62                 // Method org/elasticsearch/client/RequestConverters$Params.putParam:(Ljava/lang/String;Ljava/lang/String;)Lorg/elasticsearch/client/RequestConverters$Params;
     133: pop
     134: aload_3
     135: areturn

  static org.elasticsearch.client.Request clearRolesCache(org.elasticsearch.client.security.ClearRolesCacheRequest);
    Code:
       0: new           #2                  // class org/elasticsearch/client/RequestConverters$EndpointBuilder
       3: dup
       4: invokespecial #3                  // Method org/elasticsearch/client/RequestConverters$EndpointBuilder."<init>":()V
       7: iconst_1
       8: anewarray     #4                  // class java/lang/String
      11: dup
      12: iconst_0
      13: ldc           #63                 // String _xpack/security/role
      15: aastore
      16: invokevirtual #6                  // Method org/elasticsearch/client/RequestConverters$EndpointBuilder.addPathPartAsIs:([Ljava/lang/String;)Lorg/elasticsearch/client/RequestConverters$EndpointBuilder;
      19: aload_0
      20: invokevirtual #64                 // Method org/elasticsearch/client/security/ClearRolesCacheRequest.names:()[Ljava/lang/String;
      23: invokevirtual #57                 // Method org/elasticsearch/client/RequestConverters$EndpointBuilder.addCommaSeparatedPathParts:([Ljava/lang/String;)Lorg/elasticsearch/client/RequestConverters$EndpointBuilder;
      26: iconst_1
      27: anewarray     #4                  // class java/lang/String
      30: dup
      31: iconst_0
      32: ldc           #59                 // String _clear_cache
      34: aastore
      35: invokevirtual #8                  // Method org/elasticsearch/client/RequestConverters$EndpointBuilder.addPathPart:([Ljava/lang/String;)Lorg/elasticsearch/client/RequestConverters$EndpointBuilder;
      38: invokevirtual #10                 // Method org/elasticsearch/client/RequestConverters$EndpointBuilder.build:()Ljava/lang/String;
      41: astore_1
      42: new           #11                 // class org/elasticsearch/client/Request
      45: dup
      46: ldc           #13                 // String POST
      48: aload_1
      49: invokespecial #14                 // Method org/elasticsearch/client/Request."<init>":(Ljava/lang/String;Ljava/lang/String;)V
      52: areturn

  static org.elasticsearch.client.Request deleteRoleMapping(org.elasticsearch.client.security.DeleteRoleMappingRequest);
    Code:
       0: new           #2                  // class org/elasticsearch/client/RequestConverters$EndpointBuilder
       3: dup
       4: invokespecial #3                  // Method org/elasticsearch/client/RequestConverters$EndpointBuilder."<init>":()V
       7: iconst_1
       8: anewarray     #4                  // class java/lang/String
      11: dup
      12: iconst_0
      13: ldc           #40                 // String _xpack/security/role_mapping
      15: aastore
      16: invokevirtual #6                  // Method org/elasticsearch/client/RequestConverters$EndpointBuilder.addPathPartAsIs:([Ljava/lang/String;)Lorg/elasticsearch/client/RequestConverters$EndpointBuilder;
      19: iconst_1
      20: anewarray     #4                  // class java/lang/String
      23: dup
      24: iconst_0
      25: aload_0
      26: invokevirtual #65                 // Method org/elasticsearch/client/security/DeleteRoleMappingRequest.getName:()Ljava/lang/String;
      29: aastore
      30: invokevirtual #8                  // Method org/elasticsearch/client/RequestConverters$EndpointBuilder.addPathPart:([Ljava/lang/String;)Lorg/elasticsearch/client/RequestConverters$EndpointBuilder;
      33: invokevirtual #10                 // Method org/elasticsearch/client/RequestConverters$EndpointBuilder.build:()Ljava/lang/String;
      36: astore_1
      37: new           #11                 // class org/elasticsearch/client/Request
      40: dup
      41: ldc           #38                 // String DELETE
      43: aload_1
      44: invokespecial #14                 // Method org/elasticsearch/client/Request."<init>":(Ljava/lang/String;Ljava/lang/String;)V
      47: astore_2
      48: new           #18                 // class org/elasticsearch/client/RequestConverters$Params
      51: dup
      52: aload_2
      53: invokespecial #19                 // Method org/elasticsearch/client/RequestConverters$Params."<init>":(Lorg/elasticsearch/client/Request;)V
      56: astore_3
      57: aload_3
      58: aload_0
      59: invokevirtual #66                 // Method org/elasticsearch/client/security/DeleteRoleMappingRequest.getRefreshPolicy:()Lorg/elasticsearch/client/security/RefreshPolicy;
      62: invokevirtual #21                 // Method org/elasticsearch/client/RequestConverters$Params.withRefreshPolicy:(Lorg/elasticsearch/client/security/RefreshPolicy;)Lorg/elasticsearch/client/RequestConverters$Params;
      65: pop
      66: aload_2
      67: areturn

  static org.elasticsearch.client.Request deleteRole(org.elasticsearch.client.security.DeleteRoleRequest);
    Code:
       0: new           #2                  // class org/elasticsearch/client/RequestConverters$EndpointBuilder
       3: dup
       4: invokespecial #3                  // Method org/elasticsearch/client/RequestConverters$EndpointBuilder."<init>":()V
       7: iconst_1
       8: anewarray     #4                  // class java/lang/String
      11: dup
      12: iconst_0
      13: ldc           #63                 // String _xpack/security/role
      15: aastore
      16: invokevirtual #6                  // Method org/elasticsearch/client/RequestConverters$EndpointBuilder.addPathPartAsIs:([Ljava/lang/String;)Lorg/elasticsearch/client/RequestConverters$EndpointBuilder;
      19: iconst_1
      20: anewarray     #4                  // class java/lang/String
      23: dup
      24: iconst_0
      25: aload_0
      26: invokevirtual #67                 // Method org/elasticsearch/client/security/DeleteRoleRequest.getName:()Ljava/lang/String;
      29: aastore
      30: invokevirtual #8                  // Method org/elasticsearch/client/RequestConverters$EndpointBuilder.addPathPart:([Ljava/lang/String;)Lorg/elasticsearch/client/RequestConverters$EndpointBuilder;
      33: invokevirtual #10                 // Method org/elasticsearch/client/RequestConverters$EndpointBuilder.build:()Ljava/lang/String;
      36: astore_1
      37: new           #11                 // class org/elasticsearch/client/Request
      40: dup
      41: ldc           #38                 // String DELETE
      43: aload_1
      44: invokespecial #14                 // Method org/elasticsearch/client/Request."<init>":(Ljava/lang/String;Ljava/lang/String;)V
      47: astore_2
      48: new           #18                 // class org/elasticsearch/client/RequestConverters$Params
      51: dup
      52: aload_2
      53: invokespecial #19                 // Method org/elasticsearch/client/RequestConverters$Params."<init>":(Lorg/elasticsearch/client/Request;)V
      56: astore_3
      57: aload_3
      58: aload_0
      59: invokevirtual #68                 // Method org/elasticsearch/client/security/DeleteRoleRequest.getRefreshPolicy:()Lorg/elasticsearch/client/security/RefreshPolicy;
      62: invokevirtual #21                 // Method org/elasticsearch/client/RequestConverters$Params.withRefreshPolicy:(Lorg/elasticsearch/client/security/RefreshPolicy;)Lorg/elasticsearch/client/RequestConverters$Params;
      65: pop
      66: aload_2
      67: areturn

  static org.elasticsearch.client.Request getRoles(org.elasticsearch.client.security.GetRolesRequest);
    Code:
       0: new           #2                  // class org/elasticsearch/client/RequestConverters$EndpointBuilder
       3: dup
       4: invokespecial #3                  // Method org/elasticsearch/client/RequestConverters$EndpointBuilder."<init>":()V
       7: astore_1
       8: aload_1
       9: iconst_1
      10: anewarray     #4                  // class java/lang/String
      13: dup
      14: iconst_0
      15: ldc           #63                 // String _xpack/security/role
      17: aastore
      18: invokevirtual #6                  // Method org/elasticsearch/client/RequestConverters$EndpointBuilder.addPathPartAsIs:([Ljava/lang/String;)Lorg/elasticsearch/client/RequestConverters$EndpointBuilder;
      21: pop
      22: aload_0
      23: invokevirtual #69                 // Method org/elasticsearch/client/security/GetRolesRequest.getRoleNames:()Ljava/util/Set;
      26: invokeinterface #24,  1           // InterfaceMethod java/util/Set.size:()I
      31: ifle          53
      34: aload_1
      35: iconst_1
      36: anewarray     #4                  // class java/lang/String
      39: dup
      40: iconst_0
      41: aload_0
      42: invokevirtual #69                 // Method org/elasticsearch/client/security/GetRolesRequest.getRoleNames:()Ljava/util/Set;
      45: invokestatic  #25                 // Method org/elasticsearch/common/Strings.collectionToCommaDelimitedString:(Ljava/lang/Iterable;)Ljava/lang/String;
      48: aastore
      49: invokevirtual #8                  // Method org/elasticsearch/client/RequestConverters$EndpointBuilder.addPathPart:([Ljava/lang/String;)Lorg/elasticsearch/client/RequestConverters$EndpointBuilder;
      52: pop
      53: new           #11                 // class org/elasticsearch/client/Request
      56: dup
      57: ldc           #27                 // String GET
      59: aload_1
      60: invokevirtual #10                 // Method org/elasticsearch/client/RequestConverters$EndpointBuilder.build:()Ljava/lang/String;
      63: invokespecial #14                 // Method org/elasticsearch/client/Request."<init>":(Ljava/lang/String;Ljava/lang/String;)V
      66: areturn

  static org.elasticsearch.client.Request createToken(org.elasticsearch.client.security.CreateTokenRequest) throws java.io.IOException;
    Code:
       0: new           #11                 // class org/elasticsearch/client/Request
       3: dup
       4: ldc           #13                 // String POST
       6: ldc           #70                 // String /_xpack/security/oauth2/token
       8: invokespecial #14                 // Method org/elasticsearch/client/Request."<init>":(Ljava/lang/String;Ljava/lang/String;)V
      11: astore_1
      12: aload_1
      13: aload_0
      14: getstatic     #15                 // Field org/elasticsearch/client/RequestConverters.REQUEST_BODY_CONTENT_TYPE:Lorg/elasticsearch/common/xcontent/XContentType;
      17: invokestatic  #16                 // Method org/elasticsearch/client/RequestConverters.createEntity:(Lorg/elasticsearch/common/xcontent/ToXContent;Lorg/elasticsearch/common/xcontent/XContentType;)Lorg/apache/http/HttpEntity;
      20: invokevirtual #17                 // Method org/elasticsearch/client/Request.setEntity:(Lorg/apache/http/HttpEntity;)V
      23: aload_1
      24: areturn

  static org.elasticsearch.client.Request invalidateToken(org.elasticsearch.client.security.InvalidateTokenRequest) throws java.io.IOException;
    Code:
       0: new           #11                 // class org/elasticsearch/client/Request
       3: dup
       4: ldc           #38                 // String DELETE
       6: ldc           #70                 // String /_xpack/security/oauth2/token
       8: invokespecial #14                 // Method org/elasticsearch/client/Request."<init>":(Ljava/lang/String;Ljava/lang/String;)V
      11: astore_1
      12: aload_1
      13: aload_0
      14: getstatic     #15                 // Field org/elasticsearch/client/RequestConverters.REQUEST_BODY_CONTENT_TYPE:Lorg/elasticsearch/common/xcontent/XContentType;
      17: invokestatic  #16                 // Method org/elasticsearch/client/RequestConverters.createEntity:(Lorg/elasticsearch/common/xcontent/ToXContent;Lorg/elasticsearch/common/xcontent/XContentType;)Lorg/apache/http/HttpEntity;
      20: invokevirtual #17                 // Method org/elasticsearch/client/Request.setEntity:(Lorg/apache/http/HttpEntity;)V
      23: aload_1
      24: areturn

  static org.elasticsearch.client.Request getPrivileges(org.elasticsearch.client.security.GetPrivilegesRequest);
    Code:
       0: new           #2                  // class org/elasticsearch/client/RequestConverters$EndpointBuilder
       3: dup
       4: invokespecial #3                  // Method org/elasticsearch/client/RequestConverters$EndpointBuilder."<init>":()V
       7: iconst_1
       8: anewarray     #4                  // class java/lang/String
      11: dup
      12: iconst_0
      13: ldc           #71                 // String _xpack/security/privilege
      15: aastore
      16: invokevirtual #6                  // Method org/elasticsearch/client/RequestConverters$EndpointBuilder.addPathPartAsIs:([Ljava/lang/String;)Lorg/elasticsearch/client/RequestConverters$EndpointBuilder;
      19: iconst_1
      20: anewarray     #4                  // class java/lang/String
      23: dup
      24: iconst_0
      25: aload_0
      26: invokevirtual #72                 // Method org/elasticsearch/client/security/GetPrivilegesRequest.getApplicationName:()Ljava/lang/String;
      29: aastore
      30: invokevirtual #8                  // Method org/elasticsearch/client/RequestConverters$EndpointBuilder.addPathPart:([Ljava/lang/String;)Lorg/elasticsearch/client/RequestConverters$EndpointBuilder;
      33: aload_0
      34: invokevirtual #73                 // Method org/elasticsearch/client/security/GetPrivilegesRequest.getPrivilegeNames:()[Ljava/lang/String;
      37: invokevirtual #57                 // Method org/elasticsearch/client/RequestConverters$EndpointBuilder.addCommaSeparatedPathParts:([Ljava/lang/String;)Lorg/elasticsearch/client/RequestConverters$EndpointBuilder;
      40: invokevirtual #10                 // Method org/elasticsearch/client/RequestConverters$EndpointBuilder.build:()Ljava/lang/String;
      43: astore_1
      44: new           #11                 // class org/elasticsearch/client/Request
      47: dup
      48: ldc           #27                 // String GET
      50: aload_1
      51: invokespecial #14                 // Method org/elasticsearch/client/Request."<init>":(Ljava/lang/String;Ljava/lang/String;)V
      54: areturn

  static org.elasticsearch.client.Request putPrivileges(org.elasticsearch.client.security.PutPrivilegesRequest) throws java.io.IOException;
    Code:
       0: new           #11                 // class org/elasticsearch/client/Request
       3: dup
       4: ldc           #31                 // String PUT
       6: ldc           #74                 // String /_xpack/security/privilege
       8: invokespecial #14                 // Method org/elasticsearch/client/Request."<init>":(Ljava/lang/String;Ljava/lang/String;)V
      11: astore_1
      12: aload_1
      13: aload_0
      14: getstatic     #15                 // Field org/elasticsearch/client/RequestConverters.REQUEST_BODY_CONTENT_TYPE:Lorg/elasticsearch/common/xcontent/XContentType;
      17: invokestatic  #16                 // Method org/elasticsearch/client/RequestConverters.createEntity:(Lorg/elasticsearch/common/xcontent/ToXContent;Lorg/elasticsearch/common/xcontent/XContentType;)Lorg/apache/http/HttpEntity;
      20: invokevirtual #17                 // Method org/elasticsearch/client/Request.setEntity:(Lorg/apache/http/HttpEntity;)V
      23: new           #18                 // class org/elasticsearch/client/RequestConverters$Params
      26: dup
      27: aload_1
      28: invokespecial #19                 // Method org/elasticsearch/client/RequestConverters$Params."<init>":(Lorg/elasticsearch/client/Request;)V
      31: astore_2
      32: aload_2
      33: aload_0
      34: invokevirtual #75                 // Method org/elasticsearch/client/security/PutPrivilegesRequest.getRefreshPolicy:()Lorg/elasticsearch/client/security/RefreshPolicy;
      37: invokevirtual #21                 // Method org/elasticsearch/client/RequestConverters$Params.withRefreshPolicy:(Lorg/elasticsearch/client/security/RefreshPolicy;)Lorg/elasticsearch/client/RequestConverters$Params;
      40: pop
      41: aload_1
      42: areturn

  static org.elasticsearch.client.Request deletePrivileges(org.elasticsearch.client.security.DeletePrivilegesRequest);
    Code:
       0: new           #2                  // class org/elasticsearch/client/RequestConverters$EndpointBuilder
       3: dup
       4: invokespecial #3                  // Method org/elasticsearch/client/RequestConverters$EndpointBuilder."<init>":()V
       7: iconst_1
       8: anewarray     #4                  // class java/lang/String
      11: dup
      12: iconst_0
      13: ldc           #71                 // String _xpack/security/privilege
      15: aastore
      16: invokevirtual #6                  // Method org/elasticsearch/client/RequestConverters$EndpointBuilder.addPathPartAsIs:([Ljava/lang/String;)Lorg/elasticsearch/client/RequestConverters$EndpointBuilder;
      19: iconst_1
      20: anewarray     #4                  // class java/lang/String
      23: dup
      24: iconst_0
      25: aload_0
      26: invokevirtual #76                 // Method org/elasticsearch/client/security/DeletePrivilegesRequest.getApplication:()Ljava/lang/String;
      29: aastore
      30: invokevirtual #8                  // Method org/elasticsearch/client/RequestConverters$EndpointBuilder.addPathPart:([Ljava/lang/String;)Lorg/elasticsearch/client/RequestConverters$EndpointBuilder;
      33: aload_0
      34: invokevirtual #77                 // Method org/elasticsearch/client/security/DeletePrivilegesRequest.getPrivileges:()[Ljava/lang/String;
      37: invokevirtual #57                 // Method org/elasticsearch/client/RequestConverters$EndpointBuilder.addCommaSeparatedPathParts:([Ljava/lang/String;)Lorg/elasticsearch/client/RequestConverters$EndpointBuilder;
      40: invokevirtual #10                 // Method org/elasticsearch/client/RequestConverters$EndpointBuilder.build:()Ljava/lang/String;
      43: astore_1
      44: new           #11                 // class org/elasticsearch/client/Request
      47: dup
      48: ldc           #38                 // String DELETE
      50: aload_1
      51: invokespecial #14                 // Method org/elasticsearch/client/Request."<init>":(Ljava/lang/String;Ljava/lang/String;)V
      54: astore_2
      55: new           #18                 // class org/elasticsearch/client/RequestConverters$Params
      58: dup
      59: aload_2
      60: invokespecial #19                 // Method org/elasticsearch/client/RequestConverters$Params."<init>":(Lorg/elasticsearch/client/Request;)V
      63: astore_3
      64: aload_3
      65: aload_0
      66: invokevirtual #78                 // Method org/elasticsearch/client/security/DeletePrivilegesRequest.getRefreshPolicy:()Lorg/elasticsearch/client/security/RefreshPolicy;
      69: invokevirtual #21                 // Method org/elasticsearch/client/RequestConverters$Params.withRefreshPolicy:(Lorg/elasticsearch/client/security/RefreshPolicy;)Lorg/elasticsearch/client/RequestConverters$Params;
      72: pop
      73: aload_2
      74: areturn

  static org.elasticsearch.client.Request putRole(org.elasticsearch.client.security.PutRoleRequest) throws java.io.IOException;
    Code:
       0: new           #2                  // class org/elasticsearch/client/RequestConverters$EndpointBuilder
       3: dup
       4: invokespecial #3                  // Method org/elasticsearch/client/RequestConverters$EndpointBuilder."<init>":()V
       7: iconst_1
       8: anewarray     #4                  // class java/lang/String
      11: dup
      12: iconst_0
      13: ldc           #63                 // String _xpack/security/role
      15: aastore
      16: invokevirtual #6                  // Method org/elasticsearch/client/RequestConverters$EndpointBuilder.addPathPartAsIs:([Ljava/lang/String;)Lorg/elasticsearch/client/RequestConverters$EndpointBuilder;
      19: iconst_1
      20: anewarray     #4                  // class java/lang/String
      23: dup
      24: iconst_0
      25: aload_0
      26: invokevirtual #79                 // Method org/elasticsearch/client/security/PutRoleRequest.getRole:()Lorg/elasticsearch/client/security/user/privileges/Role;
      29: invokevirtual #80                 // Method org/elasticsearch/client/security/user/privileges/Role.getName:()Ljava/lang/String;
      32: aastore
      33: invokevirtual #8                  // Method org/elasticsearch/client/RequestConverters$EndpointBuilder.addPathPart:([Ljava/lang/String;)Lorg/elasticsearch/client/RequestConverters$EndpointBuilder;
      36: invokevirtual #10                 // Method org/elasticsearch/client/RequestConverters$EndpointBuilder.build:()Ljava/lang/String;
      39: astore_1
      40: new           #11                 // class org/elasticsearch/client/Request
      43: dup
      44: ldc           #31                 // String PUT
      46: aload_1
      47: invokespecial #14                 // Method org/elasticsearch/client/Request."<init>":(Ljava/lang/String;Ljava/lang/String;)V
      50: astore_2
      51: aload_2
      52: aload_0
      53: getstatic     #15                 // Field org/elasticsearch/client/RequestConverters.REQUEST_BODY_CONTENT_TYPE:Lorg/elasticsearch/common/xcontent/XContentType;
      56: invokestatic  #16                 // Method org/elasticsearch/client/RequestConverters.createEntity:(Lorg/elasticsearch/common/xcontent/ToXContent;Lorg/elasticsearch/common/xcontent/XContentType;)Lorg/apache/http/HttpEntity;
      59: invokevirtual #17                 // Method org/elasticsearch/client/Request.setEntity:(Lorg/apache/http/HttpEntity;)V
      62: new           #18                 // class org/elasticsearch/client/RequestConverters$Params
      65: dup
      66: aload_2
      67: invokespecial #19                 // Method org/elasticsearch/client/RequestConverters$Params."<init>":(Lorg/elasticsearch/client/Request;)V
      70: astore_3
      71: aload_3
      72: aload_0
      73: invokevirtual #81                 // Method org/elasticsearch/client/security/PutRoleRequest.getRefreshPolicy:()Lorg/elasticsearch/client/security/RefreshPolicy;
      76: invokevirtual #21                 // Method org/elasticsearch/client/RequestConverters$Params.withRefreshPolicy:(Lorg/elasticsearch/client/security/RefreshPolicy;)Lorg/elasticsearch/client/RequestConverters$Params;
      79: pop
      80: aload_2
      81: areturn

  static org.elasticsearch.client.Request createApiKey(org.elasticsearch.client.security.CreateApiKeyRequest) throws java.io.IOException;
    Code:
       0: new           #11                 // class org/elasticsearch/client/Request
       3: dup
       4: ldc           #13                 // String POST
       6: ldc           #82                 // String /_security/api_key
       8: invokespecial #14                 // Method org/elasticsearch/client/Request."<init>":(Ljava/lang/String;Ljava/lang/String;)V
      11: astore_1
      12: aload_1
      13: aload_0
      14: getstatic     #15                 // Field org/elasticsearch/client/RequestConverters.REQUEST_BODY_CONTENT_TYPE:Lorg/elasticsearch/common/xcontent/XContentType;
      17: invokestatic  #16                 // Method org/elasticsearch/client/RequestConverters.createEntity:(Lorg/elasticsearch/common/xcontent/ToXContent;Lorg/elasticsearch/common/xcontent/XContentType;)Lorg/apache/http/HttpEntity;
      20: invokevirtual #17                 // Method org/elasticsearch/client/Request.setEntity:(Lorg/apache/http/HttpEntity;)V
      23: new           #18                 // class org/elasticsearch/client/RequestConverters$Params
      26: dup
      27: aload_1
      28: invokespecial #19                 // Method org/elasticsearch/client/RequestConverters$Params."<init>":(Lorg/elasticsearch/client/Request;)V
      31: astore_2
      32: aload_2
      33: aload_0
      34: invokevirtual #83                 // Method org/elasticsearch/client/security/CreateApiKeyRequest.getRefreshPolicy:()Lorg/elasticsearch/client/security/RefreshPolicy;
      37: invokevirtual #21                 // Method org/elasticsearch/client/RequestConverters$Params.withRefreshPolicy:(Lorg/elasticsearch/client/security/RefreshPolicy;)Lorg/elasticsearch/client/RequestConverters$Params;
      40: pop
      41: aload_1
      42: areturn

  static org.elasticsearch.client.Request getApiKey(org.elasticsearch.client.security.GetApiKeyRequest) throws java.io.IOException;
    Code:
       0: new           #11                 // class org/elasticsearch/client/Request
       3: dup
       4: ldc           #27                 // String GET
       6: ldc           #82                 // String /_security/api_key
       8: invokespecial #14                 // Method org/elasticsearch/client/Request."<init>":(Ljava/lang/String;Ljava/lang/String;)V
      11: astore_1
      12: aload_0
      13: invokevirtual #84                 // Method org/elasticsearch/client/security/GetApiKeyRequest.getId:()Ljava/lang/String;
      16: invokestatic  #85                 // Method org/elasticsearch/common/Strings.hasText:(Ljava/lang/String;)Z
      19: ifeq          32
      22: aload_1
      23: ldc           #86                 // String id
      25: aload_0
      26: invokevirtual #84                 // Method org/elasticsearch/client/security/GetApiKeyRequest.getId:()Ljava/lang/String;
      29: invokevirtual #87                 // Method org/elasticsearch/client/Request.addParameter:(Ljava/lang/String;Ljava/lang/String;)V
      32: aload_0
      33: invokevirtual #88                 // Method org/elasticsearch/client/security/GetApiKeyRequest.getName:()Ljava/lang/String;
      36: invokestatic  #85                 // Method org/elasticsearch/common/Strings.hasText:(Ljava/lang/String;)Z
      39: ifeq          52
      42: aload_1
      43: ldc           #89                 // String name
      45: aload_0
      46: invokevirtual #88                 // Method org/elasticsearch/client/security/GetApiKeyRequest.getName:()Ljava/lang/String;
      49: invokevirtual #87                 // Method org/elasticsearch/client/Request.addParameter:(Ljava/lang/String;Ljava/lang/String;)V
      52: aload_0
      53: invokevirtual #90                 // Method org/elasticsearch/client/security/GetApiKeyRequest.getUserName:()Ljava/lang/String;
      56: invokestatic  #85                 // Method org/elasticsearch/common/Strings.hasText:(Ljava/lang/String;)Z
      59: ifeq          72
      62: aload_1
      63: ldc           #91                 // String username
      65: aload_0
      66: invokevirtual #90                 // Method org/elasticsearch/client/security/GetApiKeyRequest.getUserName:()Ljava/lang/String;
      69: invokevirtual #87                 // Method org/elasticsearch/client/Request.addParameter:(Ljava/lang/String;Ljava/lang/String;)V
      72: aload_0
      73: invokevirtual #92                 // Method org/elasticsearch/client/security/GetApiKeyRequest.getRealmName:()Ljava/lang/String;
      76: invokestatic  #85                 // Method org/elasticsearch/common/Strings.hasText:(Ljava/lang/String;)Z
      79: ifeq          92
      82: aload_1
      83: ldc           #93                 // String realm_name
      85: aload_0
      86: invokevirtual #92                 // Method org/elasticsearch/client/security/GetApiKeyRequest.getRealmName:()Ljava/lang/String;
      89: invokevirtual #87                 // Method org/elasticsearch/client/Request.addParameter:(Ljava/lang/String;Ljava/lang/String;)V
      92: aload_1
      93: areturn

  static org.elasticsearch.client.Request invalidateApiKey(org.elasticsearch.client.security.InvalidateApiKeyRequest) throws java.io.IOException;
    Code:
       0: new           #11                 // class org/elasticsearch/client/Request
       3: dup
       4: ldc           #38                 // String DELETE
       6: ldc           #82                 // String /_security/api_key
       8: invokespecial #14                 // Method org/elasticsearch/client/Request."<init>":(Ljava/lang/String;Ljava/lang/String;)V
      11: astore_1
      12: aload_1
      13: aload_0
      14: getstatic     #15                 // Field org/elasticsearch/client/RequestConverters.REQUEST_BODY_CONTENT_TYPE:Lorg/elasticsearch/common/xcontent/XContentType;
      17: invokestatic  #16                 // Method org/elasticsearch/client/RequestConverters.createEntity:(Lorg/elasticsearch/common/xcontent/ToXContent;Lorg/elasticsearch/common/xcontent/XContentType;)Lorg/apache/http/HttpEntity;
      20: invokevirtual #17                 // Method org/elasticsearch/client/Request.setEntity:(Lorg/apache/http/HttpEntity;)V
      23: new           #18                 // class org/elasticsearch/client/RequestConverters$Params
      26: dup
      27: aload_1
      28: invokespecial #19                 // Method org/elasticsearch/client/RequestConverters$Params."<init>":(Lorg/elasticsearch/client/Request;)V
      31: astore_2
      32: aload_1
      33: areturn
}
