Compiled from "SyncedFlushResponse.java"
public final class org.elasticsearch.client.SyncedFlushResponse$ShardFailure implements org.elasticsearch.common.xcontent.ToXContentFragment {
  public static java.lang.String SHARD_ID_FIELD;

  public static java.lang.String FAILURE_REASON_FIELD;

  public static java.lang.String ROUTING_FIELD;

  private int shardId;

  private java.lang.String failureReason;

  private java.util.Map<java.lang.String, java.lang.Object> routing;

  static org.elasticsearch.common.xcontent.ConstructingObjectParser<org.elasticsearch.client.SyncedFlushResponse$ShardFailure, java.lang.Void> PARSER;

  org.elasticsearch.client.SyncedFlushResponse$ShardFailure(int, java.lang.String, java.util.Map<java.lang.String, java.lang.Object>);
    Code:
       0: aload_0
       1: invokespecial #1                  // Method java/lang/Object."<init>":()V
       4: aload_0
       5: iload_1
       6: putfield      #2                  // Field shardId:I
       9: aload_0
      10: aload_2
      11: putfield      #3                  // Field failureReason:Ljava/lang/String;
      14: aload_3
      15: ifnull        29
      18: aload_0
      19: aload_3
      20: invokestatic  #4                  // Method java/util/Collections.unmodifiableMap:(Ljava/util/Map;)Ljava/util/Map;
      23: putfield      #5                  // Field routing:Ljava/util/Map;
      26: goto          43
      29: aload_0
      30: new           #6                  // class java/util/HashMap
      33: dup
      34: invokespecial #7                  // Method java/util/HashMap."<init>":()V
      37: invokestatic  #4                  // Method java/util/Collections.unmodifiableMap:(Ljava/util/Map;)Ljava/util/Map;
      40: putfield      #5                  // Field routing:Ljava/util/Map;
      43: return

  public int getShardId();
    Code:
       0: aload_0
       1: getfield      #2                  // Field shardId:I
       4: ireturn

  public java.lang.String getFailureReason();
    Code:
       0: aload_0
       1: getfield      #3                  // Field failureReason:Ljava/lang/String;
       4: areturn

  public java.util.Map<java.lang.String, java.lang.Object> getRouting();
    Code:
       0: aload_0
       1: getfield      #5                  // Field routing:Ljava/util/Map;
       4: areturn

  public org.elasticsearch.common.xcontent.XContentBuilder toXContent(org.elasticsearch.common.xcontent.XContentBuilder, org.elasticsearch.common.xcontent.ToXContent$Params) throws java.io.IOException;
    Code:
       0: aload_1
       1: invokevirtual #8                  // Method org/elasticsearch/common/xcontent/XContentBuilder.startObject:()Lorg/elasticsearch/common/xcontent/XContentBuilder;
       4: pop
       5: aload_1
       6: getstatic     #9                  // Field SHARD_ID_FIELD:Ljava/lang/String;
       9: aload_0
      10: getfield      #2                  // Field shardId:I
      13: invokevirtual #10                 // Method org/elasticsearch/common/xcontent/XContentBuilder.field:(Ljava/lang/String;I)Lorg/elasticsearch/common/xcontent/XContentBuilder;
      16: pop
      17: aload_1
      18: getstatic     #11                 // Field FAILURE_REASON_FIELD:Ljava/lang/String;
      21: aload_0
      22: getfield      #3                  // Field failureReason:Ljava/lang/String;
      25: invokevirtual #12                 // Method org/elasticsearch/common/xcontent/XContentBuilder.field:(Ljava/lang/String;Ljava/lang/String;)Lorg/elasticsearch/common/xcontent/XContentBuilder;
      28: pop
      29: aload_0
      30: getfield      #5                  // Field routing:Ljava/util/Map;
      33: invokeinterface #13,  1           // InterfaceMethod java/util/Map.size:()I
      38: ifle          53
      41: aload_1
      42: getstatic     #14                 // Field ROUTING_FIELD:Ljava/lang/String;
      45: aload_0
      46: getfield      #5                  // Field routing:Ljava/util/Map;
      49: invokevirtual #15                 // Method org/elasticsearch/common/xcontent/XContentBuilder.field:(Ljava/lang/String;Ljava/util/Map;)Lorg/elasticsearch/common/xcontent/XContentBuilder;
      52: pop
      53: aload_1
      54: invokevirtual #16                 // Method org/elasticsearch/common/xcontent/XContentBuilder.endObject:()Lorg/elasticsearch/common/xcontent/XContentBuilder;
      57: pop
      58: aload_1
      59: areturn

  public static org.elasticsearch.client.SyncedFlushResponse$ShardFailure fromXContent(org.elasticsearch.common.xcontent.XContentParser) throws java.io.IOException;
    Code:
       0: getstatic     #17                 // Field PARSER:Lorg/elasticsearch/common/xcontent/ConstructingObjectParser;
       3: aload_0
       4: aconst_null
       5: invokevirtual #18                 // Method org/elasticsearch/common/xcontent/ConstructingObjectParser.parse:(Lorg/elasticsearch/common/xcontent/XContentParser;Ljava/lang/Object;)Ljava/lang/Object;
       8: checkcast     #19                 // class org/elasticsearch/client/SyncedFlushResponse$ShardFailure
      11: areturn

  private static java.util.Map lambda$static$1(org.elasticsearch.common.xcontent.XContentParser, java.lang.Void) throws java.io.IOException;
    Code:
       0: aload_0
       1: invokeinterface #20,  1           // InterfaceMethod org/elasticsearch/common/xcontent/XContentParser.map:()Ljava/util/Map;
       6: areturn

  private static org.elasticsearch.client.SyncedFlushResponse$ShardFailure lambda$static$0(java.lang.Object[]);
    Code:
       0: new           #19                 // class org/elasticsearch/client/SyncedFlushResponse$ShardFailure
       3: dup
       4: aload_0
       5: iconst_0
       6: aaload
       7: checkcast     #21                 // class java/lang/Integer
      10: invokevirtual #22                 // Method java/lang/Integer.intValue:()I
      13: aload_0
      14: iconst_1
      15: aaload
      16: checkcast     #23                 // class java/lang/String
      19: aload_0
      20: iconst_2
      21: aaload
      22: checkcast     #24                 // class java/util/Map
      25: invokespecial #25                 // Method "<init>":(ILjava/lang/String;Ljava/util/Map;)V
      28: areturn

  static {};
    Code:
       0: ldc           #26                 // String shard
       2: putstatic     #9                  // Field SHARD_ID_FIELD:Ljava/lang/String;
       5: ldc           #27                 // String reason
       7: putstatic     #11                 // Field FAILURE_REASON_FIELD:Ljava/lang/String;
      10: ldc           #28                 // String routing
      12: putstatic     #14                 // Field ROUTING_FIELD:Ljava/lang/String;
      15: new           #29                 // class org/elasticsearch/common/xcontent/ConstructingObjectParser
      18: dup
      19: ldc           #30                 // String shardfailure
      21: invokedynamic #31,  0             // InvokeDynamic #0:apply:()Ljava/util/function/Function;
      26: invokespecial #32                 // Method org/elasticsearch/common/xcontent/ConstructingObjectParser."<init>":(Ljava/lang/String;Ljava/util/function/Function;)V
      29: putstatic     #17                 // Field PARSER:Lorg/elasticsearch/common/xcontent/ConstructingObjectParser;
      32: getstatic     #17                 // Field PARSER:Lorg/elasticsearch/common/xcontent/ConstructingObjectParser;
      35: invokestatic  #33                 // Method org/elasticsearch/common/xcontent/ConstructingObjectParser.constructorArg:()Ljava/util/function/BiConsumer;
      38: new           #34                 // class org/elasticsearch/common/ParseField
      41: dup
      42: getstatic     #9                  // Field SHARD_ID_FIELD:Ljava/lang/String;
      45: iconst_0
      46: anewarray     #23                 // class java/lang/String
      49: invokespecial #35                 // Method org/elasticsearch/common/ParseField."<init>":(Ljava/lang/String;[Ljava/lang/String;)V
      52: invokevirtual #36                 // Method org/elasticsearch/common/xcontent/ConstructingObjectParser.declareInt:(Ljava/util/function/BiConsumer;Lorg/elasticsearch/common/ParseField;)V
      55: getstatic     #17                 // Field PARSER:Lorg/elasticsearch/common/xcontent/ConstructingObjectParser;
      58: invokestatic  #33                 // Method org/elasticsearch/common/xcontent/ConstructingObjectParser.constructorArg:()Ljava/util/function/BiConsumer;
      61: new           #34                 // class org/elasticsearch/common/ParseField
      64: dup
      65: getstatic     #11                 // Field FAILURE_REASON_FIELD:Ljava/lang/String;
      68: iconst_0
      69: anewarray     #23                 // class java/lang/String
      72: invokespecial #35                 // Method org/elasticsearch/common/ParseField."<init>":(Ljava/lang/String;[Ljava/lang/String;)V
      75: invokevirtual #37                 // Method org/elasticsearch/common/xcontent/ConstructingObjectParser.declareString:(Ljava/util/function/BiConsumer;Lorg/elasticsearch/common/ParseField;)V
      78: getstatic     #17                 // Field PARSER:Lorg/elasticsearch/common/xcontent/ConstructingObjectParser;
      81: invokestatic  #38                 // Method org/elasticsearch/common/xcontent/ConstructingObjectParser.optionalConstructorArg:()Ljava/util/function/BiConsumer;
      84: invokedynamic #39,  0             // InvokeDynamic #1:parse:()Lorg/elasticsearch/common/xcontent/ContextParser;
      89: new           #34                 // class org/elasticsearch/common/ParseField
      92: dup
      93: getstatic     #14                 // Field ROUTING_FIELD:Ljava/lang/String;
      96: iconst_0
      97: anewarray     #23                 // class java/lang/String
     100: invokespecial #35                 // Method org/elasticsearch/common/ParseField."<init>":(Ljava/lang/String;[Ljava/lang/String;)V
     103: invokevirtual #40                 // Method org/elasticsearch/common/xcontent/ConstructingObjectParser.declareObject:(Ljava/util/function/BiConsumer;Lorg/elasticsearch/common/xcontent/ContextParser;Lorg/elasticsearch/common/ParseField;)V
     106: return
}
