Compiled from "BoundedLocalCache.java"
abstract class org.apache.camel.com.github.benmanes.caffeine.cache.BLCHeader$DrainStatusRef<K, V> extends org.apache.camel.com.github.benmanes.caffeine.cache.BLCHeader$PadDrainStatus<K, V> {
  static final long DRAIN_STATUS_OFFSET;

  static final int IDLE;

  static final int REQUIRED;

  static final int PROCESSING_TO_IDLE;

  static final int PROCESSING_TO_REQUIRED;

  volatile int drainStatus;

  org.apache.camel.com.github.benmanes.caffeine.cache.BLCHeader$DrainStatusRef();
    Code:
       0: aload_0
       1: invokespecial #26                 // Method org/apache/camel/com/github/benmanes/caffeine/cache/BLCHeader$PadDrainStatus."<init>":()V
       4: aload_0
       5: iconst_0
       6: putfield      #28                 // Field drainStatus:I
       9: return

  boolean shouldDrainBuffers(boolean);
    Code:
       0: aload_0
       1: invokevirtual #36                 // Method drainStatus:()I
       4: tableswitch   { // 0 to 3
                     0: 36
                     1: 46
                     2: 48
                     3: 48
               default: 50
          }
      36: iload_1
      37: ifne          44
      40: iconst_1
      41: goto          45
      44: iconst_0
      45: ireturn
      46: iconst_1
      47: ireturn
      48: iconst_0
      49: ireturn
      50: new           #38                 // class java/lang/IllegalStateException
      53: dup
      54: invokespecial #39                 // Method java/lang/IllegalStateException."<init>":()V
      57: athrow

  int drainStatus();
    Code:
       0: getstatic     #47                 // Field org/apache/camel/com/github/benmanes/caffeine/base/UnsafeAccess.UNSAFE:Lsun/misc/Unsafe;
       3: aload_0
       4: getstatic     #49                 // Field DRAIN_STATUS_OFFSET:J
       7: invokevirtual #55                 // Method sun/misc/Unsafe.getInt:(Ljava/lang/Object;J)I
      10: ireturn

  void lazySetDrainStatus(int);
    Code:
       0: getstatic     #47                 // Field org/apache/camel/com/github/benmanes/caffeine/base/UnsafeAccess.UNSAFE:Lsun/misc/Unsafe;
       3: aload_0
       4: getstatic     #49                 // Field DRAIN_STATUS_OFFSET:J
       7: iload_1
       8: invokevirtual #61                 // Method sun/misc/Unsafe.putOrderedInt:(Ljava/lang/Object;JI)V
      11: return

  boolean casDrainStatus(int, int);
    Code:
       0: getstatic     #47                 // Field org/apache/camel/com/github/benmanes/caffeine/base/UnsafeAccess.UNSAFE:Lsun/misc/Unsafe;
       3: aload_0
       4: getstatic     #49                 // Field DRAIN_STATUS_OFFSET:J
       7: iload_1
       8: iload_2
       9: invokevirtual #67                 // Method sun/misc/Unsafe.compareAndSwapInt:(Ljava/lang/Object;JII)Z
      12: ireturn

  static {};
    Code:
       0: ldc           #2                  // class org/apache/camel/com/github/benmanes/caffeine/cache/BLCHeader$DrainStatusRef
       2: ldc           #71                 // String drainStatus
       4: invokestatic  #75                 // Method org/apache/camel/com/github/benmanes/caffeine/base/UnsafeAccess.objectFieldOffset:(Ljava/lang/Class;Ljava/lang/String;)J
       7: putstatic     #49                 // Field DRAIN_STATUS_OFFSET:J
      10: return
}
