Compiled from "BoundedLocalCache.java"
final class org.apache.camel.com.github.benmanes.caffeine.cache.BoundedLocalCache$RemovalTask implements java.lang.Runnable {
  final org.apache.camel.com.github.benmanes.caffeine.cache.Node<K, V> node;

  final org.apache.camel.com.github.benmanes.caffeine.cache.BoundedLocalCache this$0;

  org.apache.camel.com.github.benmanes.caffeine.cache.BoundedLocalCache$RemovalTask(org.apache.camel.com.github.benmanes.caffeine.cache.Node<K, V>);
    Code:
       0: aload_0
       1: aload_1
       2: putfield      #29                 // Field this$0:Lorg/apache/camel/com/github/benmanes/caffeine/cache/BoundedLocalCache;
       5: aload_0
       6: invokespecial #32                 // Method java/lang/Object."<init>":()V
       9: aload_0
      10: aload_2
      11: putfield      #34                 // Field node:Lorg/apache/camel/com/github/benmanes/caffeine/cache/Node;
      14: return

  public void run();
    Code:
       0: aload_0
       1: getfield      #34                 // Field node:Lorg/apache/camel/com/github/benmanes/caffeine/cache/Node;
       4: invokeinterface #47,  1           // InterfaceMethod org/apache/camel/com/github/benmanes/caffeine/cache/Node.inEden:()Z
       9: ifeq          50
      12: aload_0
      13: getfield      #29                 // Field this$0:Lorg/apache/camel/com/github/benmanes/caffeine/cache/BoundedLocalCache;
      16: invokevirtual #50                 // Method org/apache/camel/com/github/benmanes/caffeine/cache/BoundedLocalCache.evicts:()Z
      19: ifne          32
      22: aload_0
      23: getfield      #29                 // Field this$0:Lorg/apache/camel/com/github/benmanes/caffeine/cache/BoundedLocalCache;
      26: invokevirtual #53                 // Method org/apache/camel/com/github/benmanes/caffeine/cache/BoundedLocalCache.expiresAfterAccess:()Z
      29: ifeq          50
      32: aload_0
      33: getfield      #29                 // Field this$0:Lorg/apache/camel/com/github/benmanes/caffeine/cache/BoundedLocalCache;
      36: invokevirtual #57                 // Method org/apache/camel/com/github/benmanes/caffeine/cache/BoundedLocalCache.accessOrderEdenDeque:()Lorg/apache/camel/com/github/benmanes/caffeine/cache/AccessOrderDeque;
      39: aload_0
      40: getfield      #34                 // Field node:Lorg/apache/camel/com/github/benmanes/caffeine/cache/Node;
      43: invokevirtual #61                 // Method org/apache/camel/com/github/benmanes/caffeine/cache/AccessOrderDeque.remove:(Lorg/apache/camel/com/github/benmanes/caffeine/cache/AccessOrderDeque$AccessOrder;)Z
      46: pop
      47: goto          105
      50: aload_0
      51: getfield      #29                 // Field this$0:Lorg/apache/camel/com/github/benmanes/caffeine/cache/BoundedLocalCache;
      54: invokevirtual #50                 // Method org/apache/camel/com/github/benmanes/caffeine/cache/BoundedLocalCache.evicts:()Z
      57: ifeq          105
      60: aload_0
      61: getfield      #34                 // Field node:Lorg/apache/camel/com/github/benmanes/caffeine/cache/Node;
      64: invokeinterface #64,  1           // InterfaceMethod org/apache/camel/com/github/benmanes/caffeine/cache/Node.inMainProbation:()Z
      69: ifeq          90
      72: aload_0
      73: getfield      #29                 // Field this$0:Lorg/apache/camel/com/github/benmanes/caffeine/cache/BoundedLocalCache;
      76: invokevirtual #67                 // Method org/apache/camel/com/github/benmanes/caffeine/cache/BoundedLocalCache.accessOrderProbationDeque:()Lorg/apache/camel/com/github/benmanes/caffeine/cache/AccessOrderDeque;
      79: aload_0
      80: getfield      #34                 // Field node:Lorg/apache/camel/com/github/benmanes/caffeine/cache/Node;
      83: invokevirtual #61                 // Method org/apache/camel/com/github/benmanes/caffeine/cache/AccessOrderDeque.remove:(Lorg/apache/camel/com/github/benmanes/caffeine/cache/AccessOrderDeque$AccessOrder;)Z
      86: pop
      87: goto          105
      90: aload_0
      91: getfield      #29                 // Field this$0:Lorg/apache/camel/com/github/benmanes/caffeine/cache/BoundedLocalCache;
      94: invokevirtual #70                 // Method org/apache/camel/com/github/benmanes/caffeine/cache/BoundedLocalCache.accessOrderProtectedDeque:()Lorg/apache/camel/com/github/benmanes/caffeine/cache/AccessOrderDeque;
      97: aload_0
      98: getfield      #34                 // Field node:Lorg/apache/camel/com/github/benmanes/caffeine/cache/Node;
     101: invokevirtual #61                 // Method org/apache/camel/com/github/benmanes/caffeine/cache/AccessOrderDeque.remove:(Lorg/apache/camel/com/github/benmanes/caffeine/cache/AccessOrderDeque$AccessOrder;)Z
     104: pop
     105: aload_0
     106: getfield      #29                 // Field this$0:Lorg/apache/camel/com/github/benmanes/caffeine/cache/BoundedLocalCache;
     109: invokevirtual #73                 // Method org/apache/camel/com/github/benmanes/caffeine/cache/BoundedLocalCache.expiresAfterWrite:()Z
     112: ifeq          130
     115: aload_0
     116: getfield      #29                 // Field this$0:Lorg/apache/camel/com/github/benmanes/caffeine/cache/BoundedLocalCache;
     119: invokevirtual #77                 // Method org/apache/camel/com/github/benmanes/caffeine/cache/BoundedLocalCache.writeOrderDeque:()Lorg/apache/camel/com/github/benmanes/caffeine/cache/WriteOrderDeque;
     122: aload_0
     123: getfield      #34                 // Field node:Lorg/apache/camel/com/github/benmanes/caffeine/cache/Node;
     126: invokevirtual #80                 // Method org/apache/camel/com/github/benmanes/caffeine/cache/WriteOrderDeque.remove:(Lorg/apache/camel/com/github/benmanes/caffeine/cache/WriteOrderDeque$WriteOrder;)Z
     129: pop
     130: aload_0
     131: getfield      #29                 // Field this$0:Lorg/apache/camel/com/github/benmanes/caffeine/cache/BoundedLocalCache;
     134: aload_0
     135: getfield      #34                 // Field node:Lorg/apache/camel/com/github/benmanes/caffeine/cache/Node;
     138: invokevirtual #84                 // Method org/apache/camel/com/github/benmanes/caffeine/cache/BoundedLocalCache.makeDead:(Lorg/apache/camel/com/github/benmanes/caffeine/cache/Node;)V
     141: return
}
