Compiled from "BZip2CompressorInputStream.java"
public class org.apache.commons.compress.compressors.bzip2.BZip2CompressorInputStream extends org.apache.commons.compress.compressors.CompressorInputStream implements org.apache.commons.compress.compressors.bzip2.BZip2Constants,org.apache.commons.compress.utils.InputStreamStatistics {
  private int last;

  private int origPtr;

  private int blockSize100k;

  private boolean blockRandomised;

  private final org.apache.commons.compress.compressors.bzip2.CRC crc;

  private int nInUse;

  private org.apache.commons.compress.utils.BitInputStream bin;

  private final boolean decompressConcatenated;

  private static final int EOF;

  private static final int START_BLOCK_STATE;

  private static final int RAND_PART_A_STATE;

  private static final int RAND_PART_B_STATE;

  private static final int RAND_PART_C_STATE;

  private static final int NO_RAND_PART_A_STATE;

  private static final int NO_RAND_PART_B_STATE;

  private static final int NO_RAND_PART_C_STATE;

  private int currentState;

  private int storedBlockCRC;

  private int storedCombinedCRC;

  private int computedBlockCRC;

  private int computedCombinedCRC;

  private int su_count;

  private int su_ch2;

  private int su_chPrev;

  private int su_i2;

  private int su_j2;

  private int su_rNToGo;

  private int su_rTPos;

  private int su_tPos;

  private char su_z;

  private org.apache.commons.compress.compressors.bzip2.BZip2CompressorInputStream$Data data;

  public org.apache.commons.compress.compressors.bzip2.BZip2CompressorInputStream(java.io.InputStream) throws java.io.IOException;
    Code:
       0: aload_0
       1: aload_1
       2: iconst_0
       3: invokespecial #1                  // Method "<init>":(Ljava/io/InputStream;Z)V
       6: return

  public org.apache.commons.compress.compressors.bzip2.BZip2CompressorInputStream(java.io.InputStream, boolean) throws java.io.IOException;
    Code:
       0: aload_0
       1: invokespecial #2                  // Method org/apache/commons/compress/compressors/CompressorInputStream."<init>":()V
       4: aload_0
       5: new           #3                  // class org/apache/commons/compress/compressors/bzip2/CRC
       8: dup
       9: invokespecial #4                  // Method org/apache/commons/compress/compressors/bzip2/CRC."<init>":()V
      12: putfield      #5                  // Field crc:Lorg/apache/commons/compress/compressors/bzip2/CRC;
      15: aload_0
      16: iconst_1
      17: putfield      #7                  // Field currentState:I
      20: aload_0
      21: new           #8                  // class org/apache/commons/compress/utils/BitInputStream
      24: dup
      25: aload_1
      26: getstatic     #9                  // Field java/lang/System.in:Ljava/io/InputStream;
      29: if_acmpne     43
      32: new           #10                 // class org/apache/commons/compress/utils/CloseShieldFilterInputStream
      35: dup
      36: aload_1
      37: invokespecial #11                 // Method org/apache/commons/compress/utils/CloseShieldFilterInputStream."<init>":(Ljava/io/InputStream;)V
      40: goto          44
      43: aload_1
      44: getstatic     #12                 // Field java/nio/ByteOrder.BIG_ENDIAN:Ljava/nio/ByteOrder;
      47: invokespecial #13                 // Method org/apache/commons/compress/utils/BitInputStream."<init>":(Ljava/io/InputStream;Ljava/nio/ByteOrder;)V
      50: putfield      #14                 // Field bin:Lorg/apache/commons/compress/utils/BitInputStream;
      53: aload_0
      54: iload_2
      55: putfield      #15                 // Field decompressConcatenated:Z
      58: aload_0
      59: iconst_1
      60: invokespecial #16                 // Method init:(Z)Z
      63: pop
      64: aload_0
      65: invokespecial #17                 // Method initBlock:()V
      68: return

  public int read() throws java.io.IOException;
    Code:
       0: aload_0
       1: getfield      #14                 // Field bin:Lorg/apache/commons/compress/utils/BitInputStream;
       4: ifnull        27
       7: aload_0
       8: invokespecial #18                 // Method read0:()I
      11: istore_1
      12: aload_0
      13: iload_1
      14: ifge          21
      17: iconst_m1
      18: goto          22
      21: iconst_1
      22: invokevirtual #19                 // Method count:(I)V
      25: iload_1
      26: ireturn
      27: new           #20                 // class java/io/IOException
      30: dup
      31: ldc           #21                 // String Stream closed
      33: invokespecial #22                 // Method java/io/IOException."<init>":(Ljava/lang/String;)V
      36: athrow

  public int read(byte[], int, int) throws java.io.IOException;
    Code:
       0: iload_2
       1: ifge          36
       4: new           #23                 // class java/lang/IndexOutOfBoundsException
       7: dup
       8: new           #24                 // class java/lang/StringBuilder
      11: dup
      12: invokespecial #25                 // Method java/lang/StringBuilder."<init>":()V
      15: ldc           #26                 // String offs(
      17: invokevirtual #27                 // Method java/lang/StringBuilder.append:(Ljava/lang/String;)Ljava/lang/StringBuilder;
      20: iload_2
      21: invokevirtual #28                 // Method java/lang/StringBuilder.append:(I)Ljava/lang/StringBuilder;
      24: ldc           #29                 // String ) < 0.
      26: invokevirtual #27                 // Method java/lang/StringBuilder.append:(Ljava/lang/String;)Ljava/lang/StringBuilder;
      29: invokevirtual #30                 // Method java/lang/StringBuilder.toString:()Ljava/lang/String;
      32: invokespecial #31                 // Method java/lang/IndexOutOfBoundsException."<init>":(Ljava/lang/String;)V
      35: athrow
      36: iload_3
      37: ifge          72
      40: new           #23                 // class java/lang/IndexOutOfBoundsException
      43: dup
      44: new           #24                 // class java/lang/StringBuilder
      47: dup
      48: invokespecial #25                 // Method java/lang/StringBuilder."<init>":()V
      51: ldc           #32                 // String len(
      53: invokevirtual #27                 // Method java/lang/StringBuilder.append:(Ljava/lang/String;)Ljava/lang/StringBuilder;
      56: iload_3
      57: invokevirtual #28                 // Method java/lang/StringBuilder.append:(I)Ljava/lang/StringBuilder;
      60: ldc           #29                 // String ) < 0.
      62: invokevirtual #27                 // Method java/lang/StringBuilder.append:(Ljava/lang/String;)Ljava/lang/StringBuilder;
      65: invokevirtual #30                 // Method java/lang/StringBuilder.toString:()Ljava/lang/String;
      68: invokespecial #31                 // Method java/lang/IndexOutOfBoundsException."<init>":(Ljava/lang/String;)V
      71: athrow
      72: iload_2
      73: iload_3
      74: iadd
      75: aload_1
      76: arraylength
      77: if_icmple     131
      80: new           #23                 // class java/lang/IndexOutOfBoundsException
      83: dup
      84: new           #24                 // class java/lang/StringBuilder
      87: dup
      88: invokespecial #25                 // Method java/lang/StringBuilder."<init>":()V
      91: ldc           #26                 // String offs(
      93: invokevirtual #27                 // Method java/lang/StringBuilder.append:(Ljava/lang/String;)Ljava/lang/StringBuilder;
      96: iload_2
      97: invokevirtual #28                 // Method java/lang/StringBuilder.append:(I)Ljava/lang/StringBuilder;
     100: ldc           #33                 // String ) + len(
     102: invokevirtual #27                 // Method java/lang/StringBuilder.append:(Ljava/lang/String;)Ljava/lang/StringBuilder;
     105: iload_3
     106: invokevirtual #28                 // Method java/lang/StringBuilder.append:(I)Ljava/lang/StringBuilder;
     109: ldc           #34                 // String ) > dest.length(
     111: invokevirtual #27                 // Method java/lang/StringBuilder.append:(Ljava/lang/String;)Ljava/lang/StringBuilder;
     114: aload_1
     115: arraylength
     116: invokevirtual #28                 // Method java/lang/StringBuilder.append:(I)Ljava/lang/StringBuilder;
     119: ldc           #35                 // String ).
     121: invokevirtual #27                 // Method java/lang/StringBuilder.append:(Ljava/lang/String;)Ljava/lang/StringBuilder;
     124: invokevirtual #30                 // Method java/lang/StringBuilder.toString:()Ljava/lang/String;
     127: invokespecial #31                 // Method java/lang/IndexOutOfBoundsException."<init>":(Ljava/lang/String;)V
     130: athrow
     131: aload_0
     132: getfield      #14                 // Field bin:Lorg/apache/commons/compress/utils/BitInputStream;
     135: ifnonnull     148
     138: new           #20                 // class java/io/IOException
     141: dup
     142: ldc           #21                 // String Stream closed
     144: invokespecial #22                 // Method java/io/IOException."<init>":(Ljava/lang/String;)V
     147: athrow
     148: iload_3
     149: ifne          154
     152: iconst_0
     153: ireturn
     154: iload_2
     155: iload_3
     156: iadd
     157: istore        4
     159: iload_2
     160: istore        5
     162: iload         5
     164: iload         4
     166: if_icmpge     197
     169: aload_0
     170: invokespecial #18                 // Method read0:()I
     173: dup
     174: istore        6
     176: iflt          197
     179: aload_1
     180: iload         5
     182: iinc          5, 1
     185: iload         6
     187: i2b
     188: bastore
     189: aload_0
     190: iconst_1
     191: invokevirtual #19                 // Method count:(I)V
     194: goto          162
     197: iload         5
     199: iload_2
     200: if_icmpne     207
     203: iconst_m1
     204: goto          211
     207: iload         5
     209: iload_2
     210: isub
     211: ireturn

  public long getCompressedCount();
    Code:
       0: aload_0
       1: getfield      #14                 // Field bin:Lorg/apache/commons/compress/utils/BitInputStream;
       4: invokevirtual #36                 // Method org/apache/commons/compress/utils/BitInputStream.getBytesRead:()J
       7: lreturn

  private void makeMaps();
    Code:
       0: aload_0
       1: getfield      #37                 // Field data:Lorg/apache/commons/compress/compressors/bzip2/BZip2CompressorInputStream$Data;
       4: getfield      #38                 // Field org/apache/commons/compress/compressors/bzip2/BZip2CompressorInputStream$Data.inUse:[Z
       7: astore_1
       8: aload_0
       9: getfield      #37                 // Field data:Lorg/apache/commons/compress/compressors/bzip2/BZip2CompressorInputStream$Data;
      12: getfield      #39                 // Field org/apache/commons/compress/compressors/bzip2/BZip2CompressorInputStream$Data.seqToUnseq:[B
      15: astore_2
      16: iconst_0
      17: istore_3
      18: iconst_0
      19: istore        4
      21: iload         4
      23: sipush        256
      26: if_icmpge     51
      29: aload_1
      30: iload         4
      32: baload
      33: ifeq          45
      36: aload_2
      37: iload_3
      38: iinc          3, 1
      41: iload         4
      43: i2b
      44: bastore
      45: iinc          4, 1
      48: goto          21
      51: aload_0
      52: iload_3
      53: putfield      #40                 // Field nInUse:I
      56: return

  private int read0() throws java.io.IOException;
    Code:
       0: aload_0
       1: getfield      #7                  // Field currentState:I
       4: tableswitch   { // 0 to 7
                     0: 52
                     1: 54
                     2: 59
                     3: 67
                     4: 72
                     5: 77
                     6: 85
                     7: 90
               default: 95
          }
      52: iconst_m1
      53: ireturn
      54: aload_0
      55: invokespecial #41                 // Method setupBlock:()I
      58: ireturn
      59: new           #42                 // class java/lang/IllegalStateException
      62: dup
      63: invokespecial #43                 // Method java/lang/IllegalStateException."<init>":()V
      66: athrow
      67: aload_0
      68: invokespecial #44                 // Method setupRandPartB:()I
      71: ireturn
      72: aload_0
      73: invokespecial #45                 // Method setupRandPartC:()I
      76: ireturn
      77: new           #42                 // class java/lang/IllegalStateException
      80: dup
      81: invokespecial #43                 // Method java/lang/IllegalStateException."<init>":()V
      84: athrow
      85: aload_0
      86: invokespecial #46                 // Method setupNoRandPartB:()I
      89: ireturn
      90: aload_0
      91: invokespecial #47                 // Method setupNoRandPartC:()I
      94: ireturn
      95: new           #42                 // class java/lang/IllegalStateException
      98: dup
      99: invokespecial #43                 // Method java/lang/IllegalStateException."<init>":()V
     102: athrow

  private int readNextByte(org.apache.commons.compress.utils.BitInputStream) throws java.io.IOException;
    Code:
       0: aload_1
       1: bipush        8
       3: invokevirtual #48                 // Method org/apache/commons/compress/utils/BitInputStream.readBits:(I)J
       6: lstore_2
       7: lload_2
       8: l2i
       9: ireturn

  private boolean init(boolean) throws java.io.IOException;
    Code:
       0: aconst_null
       1: aload_0
       2: getfield      #14                 // Field bin:Lorg/apache/commons/compress/utils/BitInputStream;
       5: if_acmpne     18
       8: new           #20                 // class java/io/IOException
      11: dup
      12: ldc           #49                 // String No InputStream
      14: invokespecial #22                 // Method java/io/IOException."<init>":(Ljava/lang/String;)V
      17: athrow
      18: iload_1
      19: ifne          29
      22: aload_0
      23: getfield      #14                 // Field bin:Lorg/apache/commons/compress/utils/BitInputStream;
      26: invokevirtual #50                 // Method org/apache/commons/compress/utils/BitInputStream.clearBitCache:()V
      29: aload_0
      30: aload_0
      31: getfield      #14                 // Field bin:Lorg/apache/commons/compress/utils/BitInputStream;
      34: invokespecial #51                 // Method readNextByte:(Lorg/apache/commons/compress/utils/BitInputStream;)I
      37: istore_2
      38: iload_2
      39: iconst_m1
      40: if_icmpne     49
      43: iload_1
      44: ifne          49
      47: iconst_0
      48: ireturn
      49: aload_0
      50: aload_0
      51: getfield      #14                 // Field bin:Lorg/apache/commons/compress/utils/BitInputStream;
      54: invokespecial #51                 // Method readNextByte:(Lorg/apache/commons/compress/utils/BitInputStream;)I
      57: istore_3
      58: aload_0
      59: aload_0
      60: getfield      #14                 // Field bin:Lorg/apache/commons/compress/utils/BitInputStream;
      63: invokespecial #51                 // Method readNextByte:(Lorg/apache/commons/compress/utils/BitInputStream;)I
      66: istore        4
      68: iload_2
      69: bipush        66
      71: if_icmpne     87
      74: iload_3
      75: bipush        90
      77: if_icmpne     87
      80: iload         4
      82: bipush        104
      84: if_icmpeq     106
      87: new           #20                 // class java/io/IOException
      90: dup
      91: iload_1
      92: ifeq          100
      95: ldc           #52                 // String Stream is not in the BZip2 format
      97: goto          102
     100: ldc           #53                 // String Garbage after a valid BZip2 stream
     102: invokespecial #22                 // Method java/io/IOException."<init>":(Ljava/lang/String;)V
     105: athrow
     106: aload_0
     107: aload_0
     108: getfield      #14                 // Field bin:Lorg/apache/commons/compress/utils/BitInputStream;
     111: invokespecial #51                 // Method readNextByte:(Lorg/apache/commons/compress/utils/BitInputStream;)I
     114: istore        5
     116: iload         5
     118: bipush        49
     120: if_icmplt     130
     123: iload         5
     125: bipush        57
     127: if_icmple     140
     130: new           #20                 // class java/io/IOException
     133: dup
     134: ldc           #54                 // String BZip2 block size is invalid
     136: invokespecial #22                 // Method java/io/IOException."<init>":(Ljava/lang/String;)V
     139: athrow
     140: aload_0
     141: iload         5
     143: bipush        48
     145: isub
     146: putfield      #55                 // Field blockSize100k:I
     149: aload_0
     150: iconst_0
     151: putfield      #56                 // Field computedCombinedCRC:I
     154: iconst_1
     155: ireturn

  private void initBlock() throws java.io.IOException;
    Code:
       0: aload_0
       1: getfield      #14                 // Field bin:Lorg/apache/commons/compress/utils/BitInputStream;
       4: astore_1
       5: aload_1
       6: invokestatic  #57                 // Method bsGetUByte:(Lorg/apache/commons/compress/utils/BitInputStream;)C
       9: istore_2
      10: aload_1
      11: invokestatic  #57                 // Method bsGetUByte:(Lorg/apache/commons/compress/utils/BitInputStream;)C
      14: istore_3
      15: aload_1
      16: invokestatic  #57                 // Method bsGetUByte:(Lorg/apache/commons/compress/utils/BitInputStream;)C
      19: istore        4
      21: aload_1
      22: invokestatic  #57                 // Method bsGetUByte:(Lorg/apache/commons/compress/utils/BitInputStream;)C
      25: istore        5
      27: aload_1
      28: invokestatic  #57                 // Method bsGetUByte:(Lorg/apache/commons/compress/utils/BitInputStream;)C
      31: istore        6
      33: aload_1
      34: invokestatic  #57                 // Method bsGetUByte:(Lorg/apache/commons/compress/utils/BitInputStream;)C
      37: istore        7
      39: iload_2
      40: bipush        23
      42: if_icmpne     91
      45: iload_3
      46: bipush        114
      48: if_icmpne     91
      51: iload         4
      53: bipush        69
      55: if_icmpne     91
      58: iload         5
      60: bipush        56
      62: if_icmpne     91
      65: iload         6
      67: bipush        80
      69: if_icmpne     91
      72: iload         7
      74: sipush        144
      77: if_icmpeq     83
      80: goto          91
      83: aload_0
      84: invokespecial #58                 // Method complete:()Z
      87: ifeq          5
      90: return
      91: iload_2
      92: bipush        49
      94: if_icmpne     131
      97: iload_3
      98: bipush        65
     100: if_icmpne     131
     103: iload         4
     105: bipush        89
     107: if_icmpne     131
     110: iload         5
     112: bipush        38
     114: if_icmpne     131
     117: iload         6
     119: bipush        83
     121: if_icmpne     131
     124: iload         7
     126: bipush        89
     128: if_icmpeq     146
     131: aload_0
     132: iconst_0
     133: putfield      #7                  // Field currentState:I
     136: new           #20                 // class java/io/IOException
     139: dup
     140: ldc           #59                 // String Bad block header
     142: invokespecial #22                 // Method java/io/IOException."<init>":(Ljava/lang/String;)V
     145: athrow
     146: aload_0
     147: aload_1
     148: invokestatic  #60                 // Method bsGetInt:(Lorg/apache/commons/compress/utils/BitInputStream;)I
     151: putfield      #61                 // Field storedBlockCRC:I
     154: aload_0
     155: aload_1
     156: iconst_1
     157: invokestatic  #62                 // Method bsR:(Lorg/apache/commons/compress/utils/BitInputStream;I)I
     160: iconst_1
     161: if_icmpne     168
     164: iconst_1
     165: goto          169
     168: iconst_0
     169: putfield      #63                 // Field blockRandomised:Z
     172: aload_0
     173: getfield      #37                 // Field data:Lorg/apache/commons/compress/compressors/bzip2/BZip2CompressorInputStream$Data;
     176: ifnonnull     194
     179: aload_0
     180: new           #64                 // class org/apache/commons/compress/compressors/bzip2/BZip2CompressorInputStream$Data
     183: dup
     184: aload_0
     185: getfield      #55                 // Field blockSize100k:I
     188: invokespecial #65                 // Method org/apache/commons/compress/compressors/bzip2/BZip2CompressorInputStream$Data."<init>":(I)V
     191: putfield      #37                 // Field data:Lorg/apache/commons/compress/compressors/bzip2/BZip2CompressorInputStream$Data;
     194: aload_0
     195: invokespecial #66                 // Method getAndMoveToFrontDecode:()V
     198: aload_0
     199: getfield      #5                  // Field crc:Lorg/apache/commons/compress/compressors/bzip2/CRC;
     202: invokevirtual #67                 // Method org/apache/commons/compress/compressors/bzip2/CRC.initializeCRC:()V
     205: aload_0
     206: iconst_1
     207: putfield      #7                  // Field currentState:I
     210: return

  private void endBlock() throws java.io.IOException;
    Code:
       0: aload_0
       1: aload_0
       2: getfield      #5                  // Field crc:Lorg/apache/commons/compress/compressors/bzip2/CRC;
       5: invokevirtual #68                 // Method org/apache/commons/compress/compressors/bzip2/CRC.getFinalCRC:()I
       8: putfield      #69                 // Field computedBlockCRC:I
      11: aload_0
      12: getfield      #61                 // Field storedBlockCRC:I
      15: aload_0
      16: getfield      #69                 // Field computedBlockCRC:I
      19: if_icmpeq     63
      22: aload_0
      23: aload_0
      24: getfield      #70                 // Field storedCombinedCRC:I
      27: iconst_1
      28: ishl
      29: aload_0
      30: getfield      #70                 // Field storedCombinedCRC:I
      33: bipush        31
      35: iushr
      36: ior
      37: putfield      #56                 // Field computedCombinedCRC:I
      40: aload_0
      41: dup
      42: getfield      #56                 // Field computedCombinedCRC:I
      45: aload_0
      46: getfield      #61                 // Field storedBlockCRC:I
      49: ixor
      50: putfield      #56                 // Field computedCombinedCRC:I
      53: new           #20                 // class java/io/IOException
      56: dup
      57: ldc           #71                 // String BZip2 CRC error
      59: invokespecial #22                 // Method java/io/IOException."<init>":(Ljava/lang/String;)V
      62: athrow
      63: aload_0
      64: aload_0
      65: getfield      #56                 // Field computedCombinedCRC:I
      68: iconst_1
      69: ishl
      70: aload_0
      71: getfield      #56                 // Field computedCombinedCRC:I
      74: bipush        31
      76: iushr
      77: ior
      78: putfield      #56                 // Field computedCombinedCRC:I
      81: aload_0
      82: dup
      83: getfield      #56                 // Field computedCombinedCRC:I
      86: aload_0
      87: getfield      #69                 // Field computedBlockCRC:I
      90: ixor
      91: putfield      #56                 // Field computedCombinedCRC:I
      94: return

  private boolean complete() throws java.io.IOException;
    Code:
       0: aload_0
       1: aload_0
       2: getfield      #14                 // Field bin:Lorg/apache/commons/compress/utils/BitInputStream;
       5: invokestatic  #60                 // Method bsGetInt:(Lorg/apache/commons/compress/utils/BitInputStream;)I
       8: putfield      #70                 // Field storedCombinedCRC:I
      11: aload_0
      12: iconst_0
      13: putfield      #7                  // Field currentState:I
      16: aload_0
      17: aconst_null
      18: putfield      #37                 // Field data:Lorg/apache/commons/compress/compressors/bzip2/BZip2CompressorInputStream$Data;
      21: aload_0
      22: getfield      #70                 // Field storedCombinedCRC:I
      25: aload_0
      26: getfield      #56                 // Field computedCombinedCRC:I
      29: if_icmpeq     42
      32: new           #20                 // class java/io/IOException
      35: dup
      36: ldc           #71                 // String BZip2 CRC error
      38: invokespecial #22                 // Method java/io/IOException."<init>":(Ljava/lang/String;)V
      41: athrow
      42: aload_0
      43: getfield      #15                 // Field decompressConcatenated:Z
      46: ifeq          57
      49: aload_0
      50: iconst_0
      51: invokespecial #16                 // Method init:(Z)Z
      54: ifne          61
      57: iconst_1
      58: goto          62
      61: iconst_0
      62: ireturn

  public void close() throws java.io.IOException;
    Code:
       0: aload_0
       1: getfield      #14                 // Field bin:Lorg/apache/commons/compress/utils/BitInputStream;
       4: astore_1
       5: aload_1
       6: ifnull        39
       9: aload_1
      10: invokevirtual #72                 // Method org/apache/commons/compress/utils/BitInputStream.close:()V
      13: aload_0
      14: aconst_null
      15: putfield      #37                 // Field data:Lorg/apache/commons/compress/compressors/bzip2/BZip2CompressorInputStream$Data;
      18: aload_0
      19: aconst_null
      20: putfield      #14                 // Field bin:Lorg/apache/commons/compress/utils/BitInputStream;
      23: goto          39
      26: astore_2
      27: aload_0
      28: aconst_null
      29: putfield      #37                 // Field data:Lorg/apache/commons/compress/compressors/bzip2/BZip2CompressorInputStream$Data;
      32: aload_0
      33: aconst_null
      34: putfield      #14                 // Field bin:Lorg/apache/commons/compress/utils/BitInputStream;
      37: aload_2
      38: athrow
      39: return
    Exception table:
       from    to  target type
           9    13    26   any

  private static int bsR(org.apache.commons.compress.utils.BitInputStream, int) throws java.io.IOException;
    Code:
       0: aload_0
       1: iload_1
       2: invokevirtual #48                 // Method org/apache/commons/compress/utils/BitInputStream.readBits:(I)J
       5: lstore_2
       6: lload_2
       7: lconst_0
       8: lcmp
       9: ifge          22
      12: new           #20                 // class java/io/IOException
      15: dup
      16: ldc           #73                 // String Unexpected end of stream
      18: invokespecial #22                 // Method java/io/IOException."<init>":(Ljava/lang/String;)V
      21: athrow
      22: lload_2
      23: l2i
      24: ireturn

  private static boolean bsGetBit(org.apache.commons.compress.utils.BitInputStream) throws java.io.IOException;
    Code:
       0: aload_0
       1: iconst_1
       2: invokestatic  #62                 // Method bsR:(Lorg/apache/commons/compress/utils/BitInputStream;I)I
       5: ifeq          12
       8: iconst_1
       9: goto          13
      12: iconst_0
      13: ireturn

  private static char bsGetUByte(org.apache.commons.compress.utils.BitInputStream) throws java.io.IOException;
    Code:
       0: aload_0
       1: bipush        8
       3: invokestatic  #62                 // Method bsR:(Lorg/apache/commons/compress/utils/BitInputStream;I)I
       6: i2c
       7: ireturn

  private static int bsGetInt(org.apache.commons.compress.utils.BitInputStream) throws java.io.IOException;
    Code:
       0: aload_0
       1: bipush        32
       3: invokestatic  #62                 // Method bsR:(Lorg/apache/commons/compress/utils/BitInputStream;I)I
       6: ireturn

  private static void checkBounds(int, int, java.lang.String) throws java.io.IOException;
    Code:
       0: iload_0
       1: ifge          36
       4: new           #20                 // class java/io/IOException
       7: dup
       8: new           #24                 // class java/lang/StringBuilder
      11: dup
      12: invokespecial #25                 // Method java/lang/StringBuilder."<init>":()V
      15: ldc           #74                 // String Corrupted input,
      17: invokevirtual #27                 // Method java/lang/StringBuilder.append:(Ljava/lang/String;)Ljava/lang/StringBuilder;
      20: aload_2
      21: invokevirtual #27                 // Method java/lang/StringBuilder.append:(Ljava/lang/String;)Ljava/lang/StringBuilder;
      24: ldc           #75                 // String  value negative
      26: invokevirtual #27                 // Method java/lang/StringBuilder.append:(Ljava/lang/String;)Ljava/lang/StringBuilder;
      29: invokevirtual #30                 // Method java/lang/StringBuilder.toString:()Ljava/lang/String;
      32: invokespecial #22                 // Method java/io/IOException."<init>":(Ljava/lang/String;)V
      35: athrow
      36: iload_0
      37: iload_1
      38: if_icmplt     73
      41: new           #20                 // class java/io/IOException
      44: dup
      45: new           #24                 // class java/lang/StringBuilder
      48: dup
      49: invokespecial #25                 // Method java/lang/StringBuilder."<init>":()V
      52: ldc           #74                 // String Corrupted input,
      54: invokevirtual #27                 // Method java/lang/StringBuilder.append:(Ljava/lang/String;)Ljava/lang/StringBuilder;
      57: aload_2
      58: invokevirtual #27                 // Method java/lang/StringBuilder.append:(Ljava/lang/String;)Ljava/lang/StringBuilder;
      61: ldc           #76                 // String  value too big
      63: invokevirtual #27                 // Method java/lang/StringBuilder.append:(Ljava/lang/String;)Ljava/lang/StringBuilder;
      66: invokevirtual #30                 // Method java/lang/StringBuilder.toString:()Ljava/lang/String;
      69: invokespecial #22                 // Method java/io/IOException."<init>":(Ljava/lang/String;)V
      72: athrow
      73: return

  private static void hbCreateDecodeTables(int[], int[], int[], char[], int, int, int) throws java.io.IOException;
    Code:
       0: iload         4
       2: istore        7
       4: iconst_0
       5: istore        8
       7: iload         7
       9: iload         5
      11: if_icmpgt     54
      14: iconst_0
      15: istore        9
      17: iload         9
      19: iload         6
      21: if_icmpge     48
      24: aload_3
      25: iload         9
      27: caload
      28: iload         7
      30: if_icmpne     42
      33: aload_2
      34: iload         8
      36: iinc          8, 1
      39: iload         9
      41: iastore
      42: iinc          9, 1
      45: goto          17
      48: iinc          7, 1
      51: goto          7
      54: bipush        23
      56: istore        7
      58: iinc          7, -1
      61: iload         7
      63: ifle          79
      66: aload_1
      67: iload         7
      69: iconst_0
      70: iastore
      71: aload_0
      72: iload         7
      74: iconst_0
      75: iastore
      76: goto          58
      79: iconst_0
      80: istore        7
      82: iload         7
      84: iload         6
      86: if_icmpge     121
      89: aload_3
      90: iload         7
      92: caload
      93: istore        8
      95: iload         8
      97: sipush        258
     100: ldc           #78                 // String length
     102: invokestatic  #79                 // Method checkBounds:(IILjava/lang/String;)V
     105: aload_1
     106: iload         8
     108: iconst_1
     109: iadd
     110: dup2
     111: iaload
     112: iconst_1
     113: iadd
     114: iastore
     115: iinc          7, 1
     118: goto          82
     121: iconst_1
     122: istore        7
     124: aload_1
     125: iconst_0
     126: iaload
     127: istore        8
     129: iload         7
     131: bipush        23
     133: if_icmpge     157
     136: iload         8
     138: aload_1
     139: iload         7
     141: iaload
     142: iadd
     143: istore        8
     145: aload_1
     146: iload         7
     148: iload         8
     150: iastore
     151: iinc          7, 1
     154: goto          129
     157: iload         4
     159: istore        7
     161: iconst_0
     162: istore        8
     164: aload_1
     165: iload         7
     167: iaload
     168: istore        9
     170: iload         7
     172: iload         5
     174: if_icmpgt     219
     177: aload_1
     178: iload         7
     180: iconst_1
     181: iadd
     182: iaload
     183: istore        10
     185: iload         8
     187: iload         10
     189: iload         9
     191: isub
     192: iadd
     193: istore        8
     195: iload         10
     197: istore        9
     199: aload_0
     200: iload         7
     202: iload         8
     204: iconst_1
     205: isub
     206: iastore
     207: iload         8
     209: iconst_1
     210: ishl
     211: istore        8
     213: iinc          7, 1
     216: goto          170
     219: iload         4
     221: iconst_1
     222: iadd
     223: istore        7
     225: iload         7
     227: iload         5
     229: if_icmpgt     257
     232: aload_1
     233: iload         7
     235: aload_0
     236: iload         7
     238: iconst_1
     239: isub
     240: iaload
     241: iconst_1
     242: iadd
     243: iconst_1
     244: ishl
     245: aload_1
     246: iload         7
     248: iaload
     249: isub
     250: iastore
     251: iinc          7, 1
     254: goto          225
     257: return

  private void recvDecodingTables() throws java.io.IOException;
    Code:
       0: aload_0
       1: getfield      #14                 // Field bin:Lorg/apache/commons/compress/utils/BitInputStream;
       4: astore_1
       5: aload_0
       6: getfield      #37                 // Field data:Lorg/apache/commons/compress/compressors/bzip2/BZip2CompressorInputStream$Data;
       9: astore_2
      10: aload_2
      11: getfield      #38                 // Field org/apache/commons/compress/compressors/bzip2/BZip2CompressorInputStream$Data.inUse:[Z
      14: astore_3
      15: aload_2
      16: getfield      #80                 // Field org/apache/commons/compress/compressors/bzip2/BZip2CompressorInputStream$Data.recvDecodingTables_pos:[B
      19: astore        4
      21: aload_2
      22: getfield      #81                 // Field org/apache/commons/compress/compressors/bzip2/BZip2CompressorInputStream$Data.selector:[B
      25: astore        5
      27: aload_2
      28: getfield      #82                 // Field org/apache/commons/compress/compressors/bzip2/BZip2CompressorInputStream$Data.selectorMtf:[B
      31: astore        6
      33: iconst_0
      34: istore        7
      36: iconst_0
      37: istore        8
      39: iload         8
      41: bipush        16
      43: if_icmpge     68
      46: aload_1
      47: invokestatic  #83                 // Method bsGetBit:(Lorg/apache/commons/compress/utils/BitInputStream;)Z
      50: ifeq          62
      53: iload         7
      55: iconst_1
      56: iload         8
      58: ishl
      59: ior
      60: istore        7
      62: iinc          8, 1
      65: goto          39
      68: aload_3
      69: iconst_0
      70: invokestatic  #84                 // Method java/util/Arrays.fill:([ZZ)V
      73: iconst_0
      74: istore        8
      76: iload         8
      78: bipush        16
      80: if_icmpge     136
      83: iload         7
      85: iconst_1
      86: iload         8
      88: ishl
      89: iand
      90: ifeq          130
      93: iload         8
      95: iconst_4
      96: ishl
      97: istore        9
      99: iconst_0
     100: istore        10
     102: iload         10
     104: bipush        16
     106: if_icmpge     130
     109: aload_1
     110: invokestatic  #83                 // Method bsGetBit:(Lorg/apache/commons/compress/utils/BitInputStream;)Z
     113: ifeq          124
     116: aload_3
     117: iload         9
     119: iload         10
     121: iadd
     122: iconst_1
     123: bastore
     124: iinc          10, 1
     127: goto          102
     130: iinc          8, 1
     133: goto          76
     136: aload_0
     137: invokespecial #85                 // Method makeMaps:()V
     140: aload_0
     141: getfield      #40                 // Field nInUse:I
     144: iconst_2
     145: iadd
     146: istore        8
     148: aload_1
     149: iconst_3
     150: invokestatic  #62                 // Method bsR:(Lorg/apache/commons/compress/utils/BitInputStream;I)I
     153: istore        9
     155: aload_1
     156: bipush        15
     158: invokestatic  #62                 // Method bsR:(Lorg/apache/commons/compress/utils/BitInputStream;I)I
     161: istore        10
     163: iload         10
     165: ifge          178
     168: new           #20                 // class java/io/IOException
     171: dup
     172: ldc           #86                 // String Corrupted input, nSelectors value negative
     174: invokespecial #22                 // Method java/io/IOException."<init>":(Ljava/lang/String;)V
     177: athrow
     178: iload         8
     180: sipush        259
     183: ldc           #87                 // String alphaSize
     185: invokestatic  #79                 // Method checkBounds:(IILjava/lang/String;)V
     188: iload         9
     190: bipush        7
     192: ldc           #88                 // String nGroups
     194: invokestatic  #79                 // Method checkBounds:(IILjava/lang/String;)V
     197: iconst_0
     198: istore        11
     200: iload         11
     202: iload         10
     204: if_icmpge     245
     207: iconst_0
     208: istore        12
     210: aload_1
     211: invokestatic  #83                 // Method bsGetBit:(Lorg/apache/commons/compress/utils/BitInputStream;)Z
     214: ifeq          223
     217: iinc          12, 1
     220: goto          210
     223: iload         11
     225: sipush        18002
     228: if_icmpge     239
     231: aload         6
     233: iload         11
     235: iload         12
     237: i2b
     238: bastore
     239: iinc          11, 1
     242: goto          200
     245: iload         10
     247: sipush        18002
     250: if_icmple     259
     253: sipush        18002
     256: goto          261
     259: iload         10
     261: istore        11
     263: iload         9
     265: istore        12
     267: iinc          12, -1
     270: iload         12
     272: iflt          286
     275: aload         4
     277: iload         12
     279: iload         12
     281: i2b
     282: bastore
     283: goto          267
     286: iconst_0
     287: istore        12
     289: iload         12
     291: iload         11
     293: if_icmpge     365
     296: aload         6
     298: iload         12
     300: baload
     301: sipush        255
     304: iand
     305: istore        13
     307: iload         13
     309: bipush        6
     311: ldc           #89                 // String selectorMtf
     313: invokestatic  #79                 // Method checkBounds:(IILjava/lang/String;)V
     316: aload         4
     318: iload         13
     320: baload
     321: istore        14
     323: iload         13
     325: ifle          346
     328: aload         4
     330: iload         13
     332: aload         4
     334: iload         13
     336: iconst_1
     337: isub
     338: baload
     339: bastore
     340: iinc          13, -1
     343: goto          323
     346: aload         4
     348: iconst_0
     349: iload         14
     351: bastore
     352: aload         5
     354: iload         12
     356: iload         14
     358: bastore
     359: iinc          12, 1
     362: goto          289
     365: aload_2
     366: getfield      #90                 // Field org/apache/commons/compress/compressors/bzip2/BZip2CompressorInputStream$Data.temp_charArray2d:[[C
     369: astore        12
     371: iconst_0
     372: istore        13
     374: iload         13
     376: iload         9
     378: if_icmpge     452
     381: aload_1
     382: iconst_5
     383: invokestatic  #62                 // Method bsR:(Lorg/apache/commons/compress/utils/BitInputStream;I)I
     386: istore        14
     388: aload         12
     390: iload         13
     392: aaload
     393: astore        15
     395: iconst_0
     396: istore        16
     398: iload         16
     400: iload         8
     402: if_icmpge     446
     405: aload_1
     406: invokestatic  #83                 // Method bsGetBit:(Lorg/apache/commons/compress/utils/BitInputStream;)Z
     409: ifeq          432
     412: iload         14
     414: aload_1
     415: invokestatic  #83                 // Method bsGetBit:(Lorg/apache/commons/compress/utils/BitInputStream;)Z
     418: ifeq          425
     421: iconst_m1
     422: goto          426
     425: iconst_1
     426: iadd
     427: istore        14
     429: goto          405
     432: aload         15
     434: iload         16
     436: iload         14
     438: i2c
     439: castore
     440: iinc          16, 1
     443: goto          398
     446: iinc          13, 1
     449: goto          374
     452: aload_0
     453: iload         8
     455: iload         9
     457: invokespecial #91                 // Method createHuffmanDecodingTables:(II)V
     460: return

  private void createHuffmanDecodingTables(int, int) throws java.io.IOException;
    Code:
       0: aload_0
       1: getfield      #37                 // Field data:Lorg/apache/commons/compress/compressors/bzip2/BZip2CompressorInputStream$Data;
       4: astore_3
       5: aload_3
       6: getfield      #90                 // Field org/apache/commons/compress/compressors/bzip2/BZip2CompressorInputStream$Data.temp_charArray2d:[[C
       9: astore        4
      11: aload_3
      12: getfield      #92                 // Field org/apache/commons/compress/compressors/bzip2/BZip2CompressorInputStream$Data.minLens:[I
      15: astore        5
      17: aload_3
      18: getfield      #93                 // Field org/apache/commons/compress/compressors/bzip2/BZip2CompressorInputStream$Data.limit:[[I
      21: astore        6
      23: aload_3
      24: getfield      #94                 // Field org/apache/commons/compress/compressors/bzip2/BZip2CompressorInputStream$Data.base:[[I
      27: astore        7
      29: aload_3
      30: getfield      #95                 // Field org/apache/commons/compress/compressors/bzip2/BZip2CompressorInputStream$Data.perm:[[I
      33: astore        8
      35: iconst_0
      36: istore        9
      38: iload         9
      40: iload_2
      41: if_icmpge     142
      44: bipush        32
      46: istore        10
      48: iconst_0
      49: istore        11
      51: aload         4
      53: iload         9
      55: aaload
      56: astore        12
      58: iload_1
      59: istore        13
      61: iinc          13, -1
      64: iload         13
      66: iflt          101
      69: aload         12
      71: iload         13
      73: caload
      74: istore        14
      76: iload         14
      78: iload         11
      80: if_icmple     87
      83: iload         14
      85: istore        11
      87: iload         14
      89: iload         10
      91: if_icmpge     98
      94: iload         14
      96: istore        10
      98: goto          61
     101: aload         6
     103: iload         9
     105: aaload
     106: aload         7
     108: iload         9
     110: aaload
     111: aload         8
     113: iload         9
     115: aaload
     116: aload         4
     118: iload         9
     120: aaload
     121: iload         10
     123: iload         11
     125: iload_1
     126: invokestatic  #96                 // Method hbCreateDecodeTables:([I[I[I[CIII)V
     129: aload         5
     131: iload         9
     133: iload         10
     135: iastore
     136: iinc          9, 1
     139: goto          38
     142: return

  private void getAndMoveToFrontDecode() throws java.io.IOException;
    Code:
       0: aload_0
       1: getfield      #14                 // Field bin:Lorg/apache/commons/compress/utils/BitInputStream;
       4: astore_1
       5: aload_0
       6: aload_1
       7: bipush        24
       9: invokestatic  #62                 // Method bsR:(Lorg/apache/commons/compress/utils/BitInputStream;I)I
      12: putfield      #97                 // Field origPtr:I
      15: aload_0
      16: invokespecial #98                 // Method recvDecodingTables:()V
      19: aload_0
      20: getfield      #37                 // Field data:Lorg/apache/commons/compress/compressors/bzip2/BZip2CompressorInputStream$Data;
      23: astore_2
      24: aload_2
      25: getfield      #99                 // Field org/apache/commons/compress/compressors/bzip2/BZip2CompressorInputStream$Data.ll8:[B
      28: astore_3
      29: aload_2
      30: getfield      #100                // Field org/apache/commons/compress/compressors/bzip2/BZip2CompressorInputStream$Data.unzftab:[I
      33: astore        4
      35: aload_2
      36: getfield      #81                 // Field org/apache/commons/compress/compressors/bzip2/BZip2CompressorInputStream$Data.selector:[B
      39: astore        5
      41: aload_2
      42: getfield      #39                 // Field org/apache/commons/compress/compressors/bzip2/BZip2CompressorInputStream$Data.seqToUnseq:[B
      45: astore        6
      47: aload_2
      48: getfield      #101                // Field org/apache/commons/compress/compressors/bzip2/BZip2CompressorInputStream$Data.getAndMoveToFrontDecode_yy:[C
      51: astore        7
      53: aload_2
      54: getfield      #92                 // Field org/apache/commons/compress/compressors/bzip2/BZip2CompressorInputStream$Data.minLens:[I
      57: astore        8
      59: aload_2
      60: getfield      #93                 // Field org/apache/commons/compress/compressors/bzip2/BZip2CompressorInputStream$Data.limit:[[I
      63: astore        9
      65: aload_2
      66: getfield      #94                 // Field org/apache/commons/compress/compressors/bzip2/BZip2CompressorInputStream$Data.base:[[I
      69: astore        10
      71: aload_2
      72: getfield      #95                 // Field org/apache/commons/compress/compressors/bzip2/BZip2CompressorInputStream$Data.perm:[[I
      75: astore        11
      77: aload_0
      78: getfield      #55                 // Field blockSize100k:I
      81: ldc           #102                // int 100000
      83: imul
      84: istore        12
      86: sipush        256
      89: istore        13
      91: iinc          13, -1
      94: iload         13
      96: iflt          116
      99: aload         7
     101: iload         13
     103: iload         13
     105: i2c
     106: castore
     107: aload         4
     109: iload         13
     111: iconst_0
     112: iastore
     113: goto          91
     116: iconst_0
     117: istore        13
     119: bipush        49
     121: istore        14
     123: aload_0
     124: getfield      #40                 // Field nInUse:I
     127: iconst_1
     128: iadd
     129: istore        15
     131: aload_0
     132: invokespecial #103                // Method getAndMoveToFrontDecode0:()I
     135: istore        16
     137: iconst_m1
     138: istore        17
     140: aload         5
     142: iload         13
     144: baload
     145: sipush        255
     148: iand
     149: istore        18
     151: iload         18
     153: bipush        6
     155: ldc           #104                // String zt
     157: invokestatic  #79                 // Method checkBounds:(IILjava/lang/String;)V
     160: aload         10
     162: iload         18
     164: aaload
     165: astore        19
     167: aload         9
     169: iload         18
     171: aaload
     172: astore        20
     174: aload         11
     176: iload         18
     178: aaload
     179: astore        21
     181: aload         8
     183: iload         18
     185: iaload
     186: istore        22
     188: iload         16
     190: iload         15
     192: if_icmpeq     881
     195: iload         16
     197: ifeq          206
     200: iload         16
     202: iconst_1
     203: if_icmpne     557
     206: iconst_m1
     207: istore        23
     209: iconst_1
     210: istore        24
     212: iload         16
     214: ifne          227
     217: iload         23
     219: iload         24
     221: iadd
     222: istore        23
     224: goto          242
     227: iload         16
     229: iconst_1
     230: if_icmpne     414
     233: iload         23
     235: iload         24
     237: iconst_1
     238: ishl
     239: iadd
     240: istore        23
     242: iload         14
     244: ifne          315
     247: bipush        49
     249: istore        14
     251: iinc          13, 1
     254: iload         13
     256: sipush        18002
     259: ldc           #105                // String groupNo
     261: invokestatic  #79                 // Method checkBounds:(IILjava/lang/String;)V
     264: aload         5
     266: iload         13
     268: baload
     269: sipush        255
     272: iand
     273: istore        18
     275: iload         18
     277: bipush        6
     279: ldc           #104                // String zt
     281: invokestatic  #79                 // Method checkBounds:(IILjava/lang/String;)V
     284: aload         10
     286: iload         18
     288: aaload
     289: astore        19
     291: aload         9
     293: iload         18
     295: aaload
     296: astore        20
     298: aload         11
     300: iload         18
     302: aaload
     303: astore        21
     305: aload         8
     307: iload         18
     309: iaload
     310: istore        22
     312: goto          318
     315: iinc          14, -1
     318: iload         22
     320: istore        25
     322: iload         25
     324: sipush        258
     327: ldc           #106                // String zn
     329: invokestatic  #79                 // Method checkBounds:(IILjava/lang/String;)V
     332: aload_1
     333: iload         25
     335: invokestatic  #62                 // Method bsR:(Lorg/apache/commons/compress/utils/BitInputStream;I)I
     338: istore        26
     340: iload         26
     342: aload         20
     344: iload         25
     346: iaload
     347: if_icmple     378
     350: iinc          25, 1
     353: iload         25
     355: sipush        258
     358: ldc           #106                // String zn
     360: invokestatic  #79                 // Method checkBounds:(IILjava/lang/String;)V
     363: iload         26
     365: iconst_1
     366: ishl
     367: aload_1
     368: iconst_1
     369: invokestatic  #62                 // Method bsR:(Lorg/apache/commons/compress/utils/BitInputStream;I)I
     372: ior
     373: istore        26
     375: goto          340
     378: iload         26
     380: aload         19
     382: iload         25
     384: iaload
     385: isub
     386: istore        27
     388: iload         27
     390: sipush        258
     393: ldc           #107                // String zvec
     395: invokestatic  #79                 // Method checkBounds:(IILjava/lang/String;)V
     398: aload         21
     400: iload         27
     402: iaload
     403: istore        16
     405: iload         24
     407: iconst_1
     408: ishl
     409: istore        24
     411: goto          212
     414: iload         23
     416: aload_0
     417: getfield      #37                 // Field data:Lorg/apache/commons/compress/compressors/bzip2/BZip2CompressorInputStream$Data;
     420: getfield      #99                 // Field org/apache/commons/compress/compressors/bzip2/BZip2CompressorInputStream$Data.ll8:[B
     423: arraylength
     424: ldc           #108                // String s
     426: invokestatic  #79                 // Method checkBounds:(IILjava/lang/String;)V
     429: aload         7
     431: iconst_0
     432: caload
     433: istore        24
     435: iload         24
     437: sipush        256
     440: ldc           #109                // String yy
     442: invokestatic  #79                 // Method checkBounds:(IILjava/lang/String;)V
     445: aload         6
     447: iload         24
     449: baload
     450: istore        25
     452: aload         4
     454: iload         25
     456: sipush        255
     459: iand
     460: dup2
     461: iaload
     462: iload         23
     464: iconst_1
     465: iadd
     466: iadd
     467: iastore
     468: iinc          17, 1
     471: iload         17
     473: istore        26
     475: iload         17
     477: iload         23
     479: iadd
     480: istore        17
     482: iload         17
     484: aload_0
     485: getfield      #37                 // Field data:Lorg/apache/commons/compress/compressors/bzip2/BZip2CompressorInputStream$Data;
     488: getfield      #99                 // Field org/apache/commons/compress/compressors/bzip2/BZip2CompressorInputStream$Data.ll8:[B
     491: arraylength
     492: ldc           #110                // String lastShadow
     494: invokestatic  #79                 // Method checkBounds:(IILjava/lang/String;)V
     497: aload_3
     498: iload         26
     500: iload         17
     502: iconst_1
     503: iadd
     504: iload         25
     506: invokestatic  #111                // Method java/util/Arrays.fill:([BIIB)V
     509: iload         17
     511: iload         12
     513: if_icmplt     554
     516: new           #20                 // class java/io/IOException
     519: dup
     520: new           #24                 // class java/lang/StringBuilder
     523: dup
     524: invokespecial #25                 // Method java/lang/StringBuilder."<init>":()V
     527: ldc           #112                // String Block overrun while expanding RLE in MTF,
     529: invokevirtual #27                 // Method java/lang/StringBuilder.append:(Ljava/lang/String;)Ljava/lang/StringBuilder;
     532: iload         17
     534: invokevirtual #28                 // Method java/lang/StringBuilder.append:(I)Ljava/lang/StringBuilder;
     537: ldc           #113                // String  exceeds
     539: invokevirtual #27                 // Method java/lang/StringBuilder.append:(Ljava/lang/String;)Ljava/lang/StringBuilder;
     542: iload         12
     544: invokevirtual #28                 // Method java/lang/StringBuilder.append:(I)Ljava/lang/StringBuilder;
     547: invokevirtual #30                 // Method java/lang/StringBuilder.toString:()Ljava/lang/String;
     550: invokespecial #22                 // Method java/io/IOException."<init>":(Ljava/lang/String;)V
     553: athrow
     554: goto          188
     557: iinc          17, 1
     560: iload         17
     562: iload         12
     564: if_icmplt     605
     567: new           #20                 // class java/io/IOException
     570: dup
     571: new           #24                 // class java/lang/StringBuilder
     574: dup
     575: invokespecial #25                 // Method java/lang/StringBuilder."<init>":()V
     578: ldc           #114                // String Block overrun in MTF,
     580: invokevirtual #27                 // Method java/lang/StringBuilder.append:(Ljava/lang/String;)Ljava/lang/StringBuilder;
     583: iload         17
     585: invokevirtual #28                 // Method java/lang/StringBuilder.append:(I)Ljava/lang/StringBuilder;
     588: ldc           #113                // String  exceeds
     590: invokevirtual #27                 // Method java/lang/StringBuilder.append:(Ljava/lang/String;)Ljava/lang/StringBuilder;
     593: iload         12
     595: invokevirtual #28                 // Method java/lang/StringBuilder.append:(I)Ljava/lang/StringBuilder;
     598: invokevirtual #30                 // Method java/lang/StringBuilder.toString:()Ljava/lang/String;
     601: invokespecial #22                 // Method java/io/IOException."<init>":(Ljava/lang/String;)V
     604: athrow
     605: iload         16
     607: sipush        257
     610: ldc           #115                // String nextSym
     612: invokestatic  #79                 // Method checkBounds:(IILjava/lang/String;)V
     615: aload         7
     617: iload         16
     619: iconst_1
     620: isub
     621: caload
     622: istore        23
     624: iload         23
     626: sipush        256
     629: ldc           #109                // String yy
     631: invokestatic  #79                 // Method checkBounds:(IILjava/lang/String;)V
     634: aload         4
     636: aload         6
     638: iload         23
     640: baload
     641: sipush        255
     644: iand
     645: dup2
     646: iaload
     647: iconst_1
     648: iadd
     649: iastore
     650: aload_3
     651: iload         17
     653: aload         6
     655: iload         23
     657: baload
     658: bastore
     659: iload         16
     661: bipush        16
     663: if_icmpgt     696
     666: iload         16
     668: iconst_1
     669: isub
     670: istore        24
     672: iload         24
     674: ifle          693
     677: aload         7
     679: iload         24
     681: aload         7
     683: iinc          24, -1
     686: iload         24
     688: caload
     689: castore
     690: goto          672
     693: goto          709
     696: aload         7
     698: iconst_0
     699: aload         7
     701: iconst_1
     702: iload         16
     704: iconst_1
     705: isub
     706: invokestatic  #116                // Method java/lang/System.arraycopy:(Ljava/lang/Object;ILjava/lang/Object;II)V
     709: aload         7
     711: iconst_0
     712: iload         23
     714: castore
     715: iload         14
     717: ifne          788
     720: bipush        49
     722: istore        14
     724: iinc          13, 1
     727: iload         13
     729: sipush        18002
     732: ldc           #105                // String groupNo
     734: invokestatic  #79                 // Method checkBounds:(IILjava/lang/String;)V
     737: aload         5
     739: iload         13
     741: baload
     742: sipush        255
     745: iand
     746: istore        18
     748: iload         18
     750: bipush        6
     752: ldc           #104                // String zt
     754: invokestatic  #79                 // Method checkBounds:(IILjava/lang/String;)V
     757: aload         10
     759: iload         18
     761: aaload
     762: astore        19
     764: aload         9
     766: iload         18
     768: aaload
     769: astore        20
     771: aload         11
     773: iload         18
     775: aaload
     776: astore        21
     778: aload         8
     780: iload         18
     782: iaload
     783: istore        22
     785: goto          791
     788: iinc          14, -1
     791: iload         22
     793: istore        24
     795: iload         24
     797: sipush        258
     800: ldc           #106                // String zn
     802: invokestatic  #79                 // Method checkBounds:(IILjava/lang/String;)V
     805: aload_1
     806: iload         24
     808: invokestatic  #62                 // Method bsR:(Lorg/apache/commons/compress/utils/BitInputStream;I)I
     811: istore        25
     813: iload         25
     815: aload         20
     817: iload         24
     819: iaload
     820: if_icmple     851
     823: iinc          24, 1
     826: iload         24
     828: sipush        258
     831: ldc           #106                // String zn
     833: invokestatic  #79                 // Method checkBounds:(IILjava/lang/String;)V
     836: iload         25
     838: iconst_1
     839: ishl
     840: aload_1
     841: iconst_1
     842: invokestatic  #62                 // Method bsR:(Lorg/apache/commons/compress/utils/BitInputStream;I)I
     845: ior
     846: istore        25
     848: goto          813
     851: iload         25
     853: aload         19
     855: iload         24
     857: iaload
     858: isub
     859: istore        26
     861: iload         26
     863: sipush        258
     866: ldc           #107                // String zvec
     868: invokestatic  #79                 // Method checkBounds:(IILjava/lang/String;)V
     871: aload         21
     873: iload         26
     875: iaload
     876: istore        16
     878: goto          188
     881: aload_0
     882: iload         17
     884: putfield      #117                // Field last:I
     887: return

  private int getAndMoveToFrontDecode0() throws java.io.IOException;
    Code:
       0: aload_0
       1: getfield      #37                 // Field data:Lorg/apache/commons/compress/compressors/bzip2/BZip2CompressorInputStream$Data;
       4: astore_1
       5: aload_1
       6: getfield      #81                 // Field org/apache/commons/compress/compressors/bzip2/BZip2CompressorInputStream$Data.selector:[B
       9: iconst_0
      10: baload
      11: sipush        255
      14: iand
      15: istore_2
      16: iload_2
      17: bipush        6
      19: ldc           #104                // String zt
      21: invokestatic  #79                 // Method checkBounds:(IILjava/lang/String;)V
      24: aload_1
      25: getfield      #93                 // Field org/apache/commons/compress/compressors/bzip2/BZip2CompressorInputStream$Data.limit:[[I
      28: iload_2
      29: aaload
      30: astore_3
      31: aload_1
      32: getfield      #92                 // Field org/apache/commons/compress/compressors/bzip2/BZip2CompressorInputStream$Data.minLens:[I
      35: iload_2
      36: iaload
      37: istore        4
      39: iload         4
      41: sipush        258
      44: ldc           #106                // String zn
      46: invokestatic  #79                 // Method checkBounds:(IILjava/lang/String;)V
      49: aload_0
      50: getfield      #14                 // Field bin:Lorg/apache/commons/compress/utils/BitInputStream;
      53: iload         4
      55: invokestatic  #62                 // Method bsR:(Lorg/apache/commons/compress/utils/BitInputStream;I)I
      58: istore        5
      60: iload         5
      62: aload_3
      63: iload         4
      65: iaload
      66: if_icmple     100
      69: iinc          4, 1
      72: iload         4
      74: sipush        258
      77: ldc           #106                // String zn
      79: invokestatic  #79                 // Method checkBounds:(IILjava/lang/String;)V
      82: iload         5
      84: iconst_1
      85: ishl
      86: aload_0
      87: getfield      #14                 // Field bin:Lorg/apache/commons/compress/utils/BitInputStream;
      90: iconst_1
      91: invokestatic  #62                 // Method bsR:(Lorg/apache/commons/compress/utils/BitInputStream;I)I
      94: ior
      95: istore        5
      97: goto          60
     100: iload         5
     102: aload_1
     103: getfield      #94                 // Field org/apache/commons/compress/compressors/bzip2/BZip2CompressorInputStream$Data.base:[[I
     106: iload_2
     107: aaload
     108: iload         4
     110: iaload
     111: isub
     112: istore        6
     114: iload         6
     116: sipush        258
     119: ldc           #107                // String zvec
     121: invokestatic  #79                 // Method checkBounds:(IILjava/lang/String;)V
     124: aload_1
     125: getfield      #95                 // Field org/apache/commons/compress/compressors/bzip2/BZip2CompressorInputStream$Data.perm:[[I
     128: iload_2
     129: aaload
     130: iload         6
     132: iaload
     133: ireturn

  private int setupBlock() throws java.io.IOException;
    Code:
       0: aload_0
       1: getfield      #7                  // Field currentState:I
       4: ifeq          14
       7: aload_0
       8: getfield      #37                 // Field data:Lorg/apache/commons/compress/compressors/bzip2/BZip2CompressorInputStream$Data;
      11: ifnonnull     16
      14: iconst_m1
      15: ireturn
      16: aload_0
      17: getfield      #37                 // Field data:Lorg/apache/commons/compress/compressors/bzip2/BZip2CompressorInputStream$Data;
      20: getfield      #118                // Field org/apache/commons/compress/compressors/bzip2/BZip2CompressorInputStream$Data.cftab:[I
      23: astore_1
      24: aload_0
      25: getfield      #117                // Field last:I
      28: iconst_1
      29: iadd
      30: istore_2
      31: aload_0
      32: getfield      #37                 // Field data:Lorg/apache/commons/compress/compressors/bzip2/BZip2CompressorInputStream$Data;
      35: iload_2
      36: invokevirtual #119                // Method org/apache/commons/compress/compressors/bzip2/BZip2CompressorInputStream$Data.initTT:(I)[I
      39: astore_3
      40: aload_0
      41: getfield      #37                 // Field data:Lorg/apache/commons/compress/compressors/bzip2/BZip2CompressorInputStream$Data;
      44: getfield      #99                 // Field org/apache/commons/compress/compressors/bzip2/BZip2CompressorInputStream$Data.ll8:[B
      47: astore        4
      49: aload_1
      50: iconst_0
      51: iconst_0
      52: iastore
      53: aload_0
      54: getfield      #37                 // Field data:Lorg/apache/commons/compress/compressors/bzip2/BZip2CompressorInputStream$Data;
      57: getfield      #100                // Field org/apache/commons/compress/compressors/bzip2/BZip2CompressorInputStream$Data.unzftab:[I
      60: iconst_0
      61: aload_1
      62: iconst_1
      63: sipush        256
      66: invokestatic  #116                // Method java/lang/System.arraycopy:(Ljava/lang/Object;ILjava/lang/Object;II)V
      69: iconst_1
      70: istore        5
      72: aload_1
      73: iconst_0
      74: iaload
      75: istore        6
      77: iload         5
      79: sipush        256
      82: if_icmpgt     106
      85: iload         6
      87: aload_1
      88: iload         5
      90: iaload
      91: iadd
      92: istore        6
      94: aload_1
      95: iload         5
      97: iload         6
      99: iastore
     100: iinc          5, 1
     103: goto          77
     106: iconst_0
     107: istore        5
     109: aload_0
     110: getfield      #117                // Field last:I
     113: istore        6
     115: iload         5
     117: iload         6
     119: if_icmpgt     160
     122: aload_1
     123: aload         4
     125: iload         5
     127: baload
     128: sipush        255
     131: iand
     132: dup2
     133: iaload
     134: dup_x2
     135: iconst_1
     136: iadd
     137: iastore
     138: istore        7
     140: iload         7
     142: iload_2
     143: ldc           #120                // String tt index
     145: invokestatic  #79                 // Method checkBounds:(IILjava/lang/String;)V
     148: aload_3
     149: iload         7
     151: iload         5
     153: iastore
     154: iinc          5, 1
     157: goto          115
     160: aload_0
     161: getfield      #97                 // Field origPtr:I
     164: iflt          176
     167: aload_0
     168: getfield      #97                 // Field origPtr:I
     171: aload_3
     172: arraylength
     173: if_icmplt     186
     176: new           #20                 // class java/io/IOException
     179: dup
     180: ldc           #121                // String Stream corrupted
     182: invokespecial #22                 // Method java/io/IOException."<init>":(Ljava/lang/String;)V
     185: athrow
     186: aload_0
     187: aload_3
     188: aload_0
     189: getfield      #97                 // Field origPtr:I
     192: iaload
     193: putfield      #122                // Field su_tPos:I
     196: aload_0
     197: iconst_0
     198: putfield      #123                // Field su_count:I
     201: aload_0
     202: iconst_0
     203: putfield      #124                // Field su_i2:I
     206: aload_0
     207: sipush        256
     210: putfield      #125                // Field su_ch2:I
     213: aload_0
     214: getfield      #63                 // Field blockRandomised:Z
     217: ifeq          235
     220: aload_0
     221: iconst_0
     222: putfield      #126                // Field su_rNToGo:I
     225: aload_0
     226: iconst_0
     227: putfield      #127                // Field su_rTPos:I
     230: aload_0
     231: invokespecial #128                // Method setupRandPartA:()I
     234: ireturn
     235: aload_0
     236: invokespecial #129                // Method setupNoRandPartA:()I
     239: ireturn

  private int setupRandPartA() throws java.io.IOException;
    Code:
       0: aload_0
       1: getfield      #124                // Field su_i2:I
       4: aload_0
       5: getfield      #117                // Field last:I
       8: if_icmpgt     170
      11: aload_0
      12: aload_0
      13: getfield      #125                // Field su_ch2:I
      16: putfield      #130                // Field su_chPrev:I
      19: aload_0
      20: getfield      #37                 // Field data:Lorg/apache/commons/compress/compressors/bzip2/BZip2CompressorInputStream$Data;
      23: getfield      #99                 // Field org/apache/commons/compress/compressors/bzip2/BZip2CompressorInputStream$Data.ll8:[B
      26: aload_0
      27: getfield      #122                // Field su_tPos:I
      30: baload
      31: sipush        255
      34: iand
      35: istore_1
      36: aload_0
      37: getfield      #122                // Field su_tPos:I
      40: aload_0
      41: getfield      #37                 // Field data:Lorg/apache/commons/compress/compressors/bzip2/BZip2CompressorInputStream$Data;
      44: getfield      #131                // Field org/apache/commons/compress/compressors/bzip2/BZip2CompressorInputStream$Data.tt:[I
      47: arraylength
      48: ldc           #132                // String su_tPos
      50: invokestatic  #79                 // Method checkBounds:(IILjava/lang/String;)V
      53: aload_0
      54: aload_0
      55: getfield      #37                 // Field data:Lorg/apache/commons/compress/compressors/bzip2/BZip2CompressorInputStream$Data;
      58: getfield      #131                // Field org/apache/commons/compress/compressors/bzip2/BZip2CompressorInputStream$Data.tt:[I
      61: aload_0
      62: getfield      #122                // Field su_tPos:I
      65: iaload
      66: putfield      #122                // Field su_tPos:I
      69: aload_0
      70: getfield      #126                // Field su_rNToGo:I
      73: ifne          114
      76: aload_0
      77: aload_0
      78: getfield      #127                // Field su_rTPos:I
      81: invokestatic  #133                // Method org/apache/commons/compress/compressors/bzip2/Rand.rNums:(I)I
      84: iconst_1
      85: isub
      86: putfield      #126                // Field su_rNToGo:I
      89: aload_0
      90: dup
      91: getfield      #127                // Field su_rTPos:I
      94: iconst_1
      95: iadd
      96: dup_x1
      97: putfield      #127                // Field su_rTPos:I
     100: sipush        512
     103: if_icmpne     124
     106: aload_0
     107: iconst_0
     108: putfield      #127                // Field su_rTPos:I
     111: goto          124
     114: aload_0
     115: dup
     116: getfield      #126                // Field su_rNToGo:I
     119: iconst_1
     120: isub
     121: putfield      #126                // Field su_rNToGo:I
     124: aload_0
     125: iload_1
     126: aload_0
     127: getfield      #126                // Field su_rNToGo:I
     130: iconst_1
     131: if_icmpne     138
     134: iconst_1
     135: goto          139
     138: iconst_0
     139: ixor
     140: dup
     141: istore_1
     142: putfield      #125                // Field su_ch2:I
     145: aload_0
     146: dup
     147: getfield      #124                // Field su_i2:I
     150: iconst_1
     151: iadd
     152: putfield      #124                // Field su_i2:I
     155: aload_0
     156: iconst_3
     157: putfield      #7                  // Field currentState:I
     160: aload_0
     161: getfield      #5                  // Field crc:Lorg/apache/commons/compress/compressors/bzip2/CRC;
     164: iload_1
     165: invokevirtual #134                // Method org/apache/commons/compress/compressors/bzip2/CRC.updateCRC:(I)V
     168: iload_1
     169: ireturn
     170: aload_0
     171: invokespecial #135                // Method endBlock:()V
     174: aload_0
     175: invokespecial #17                 // Method initBlock:()V
     178: aload_0
     179: invokespecial #41                 // Method setupBlock:()I
     182: ireturn

  private int setupNoRandPartA() throws java.io.IOException;
    Code:
       0: aload_0
       1: getfield      #124                // Field su_i2:I
       4: aload_0
       5: getfield      #117                // Field last:I
       8: if_icmpgt     100
      11: aload_0
      12: aload_0
      13: getfield      #125                // Field su_ch2:I
      16: putfield      #130                // Field su_chPrev:I
      19: aload_0
      20: getfield      #37                 // Field data:Lorg/apache/commons/compress/compressors/bzip2/BZip2CompressorInputStream$Data;
      23: getfield      #99                 // Field org/apache/commons/compress/compressors/bzip2/BZip2CompressorInputStream$Data.ll8:[B
      26: aload_0
      27: getfield      #122                // Field su_tPos:I
      30: baload
      31: sipush        255
      34: iand
      35: istore_1
      36: aload_0
      37: iload_1
      38: putfield      #125                // Field su_ch2:I
      41: aload_0
      42: getfield      #122                // Field su_tPos:I
      45: aload_0
      46: getfield      #37                 // Field data:Lorg/apache/commons/compress/compressors/bzip2/BZip2CompressorInputStream$Data;
      49: getfield      #131                // Field org/apache/commons/compress/compressors/bzip2/BZip2CompressorInputStream$Data.tt:[I
      52: arraylength
      53: ldc           #132                // String su_tPos
      55: invokestatic  #79                 // Method checkBounds:(IILjava/lang/String;)V
      58: aload_0
      59: aload_0
      60: getfield      #37                 // Field data:Lorg/apache/commons/compress/compressors/bzip2/BZip2CompressorInputStream$Data;
      63: getfield      #131                // Field org/apache/commons/compress/compressors/bzip2/BZip2CompressorInputStream$Data.tt:[I
      66: aload_0
      67: getfield      #122                // Field su_tPos:I
      70: iaload
      71: putfield      #122                // Field su_tPos:I
      74: aload_0
      75: dup
      76: getfield      #124                // Field su_i2:I
      79: iconst_1
      80: iadd
      81: putfield      #124                // Field su_i2:I
      84: aload_0
      85: bipush        6
      87: putfield      #7                  // Field currentState:I
      90: aload_0
      91: getfield      #5                  // Field crc:Lorg/apache/commons/compress/compressors/bzip2/CRC;
      94: iload_1
      95: invokevirtual #134                // Method org/apache/commons/compress/compressors/bzip2/CRC.updateCRC:(I)V
      98: iload_1
      99: ireturn
     100: aload_0
     101: iconst_5
     102: putfield      #7                  // Field currentState:I
     105: aload_0
     106: invokespecial #135                // Method endBlock:()V
     109: aload_0
     110: invokespecial #17                 // Method initBlock:()V
     113: aload_0
     114: invokespecial #41                 // Method setupBlock:()I
     117: ireturn

  private int setupRandPartB() throws java.io.IOException;
    Code:
       0: aload_0
       1: getfield      #125                // Field su_ch2:I
       4: aload_0
       5: getfield      #130                // Field su_chPrev:I
       8: if_icmpeq     26
      11: aload_0
      12: iconst_2
      13: putfield      #7                  // Field currentState:I
      16: aload_0
      17: iconst_1
      18: putfield      #123                // Field su_count:I
      21: aload_0
      22: invokespecial #128                // Method setupRandPartA:()I
      25: ireturn
      26: aload_0
      27: dup
      28: getfield      #123                // Field su_count:I
      31: iconst_1
      32: iadd
      33: dup_x1
      34: putfield      #123                // Field su_count:I
      37: iconst_4
      38: if_icmpge     51
      41: aload_0
      42: iconst_2
      43: putfield      #7                  // Field currentState:I
      46: aload_0
      47: invokespecial #128                // Method setupRandPartA:()I
      50: ireturn
      51: aload_0
      52: aload_0
      53: getfield      #37                 // Field data:Lorg/apache/commons/compress/compressors/bzip2/BZip2CompressorInputStream$Data;
      56: getfield      #99                 // Field org/apache/commons/compress/compressors/bzip2/BZip2CompressorInputStream$Data.ll8:[B
      59: aload_0
      60: getfield      #122                // Field su_tPos:I
      63: baload
      64: sipush        255
      67: iand
      68: i2c
      69: putfield      #136                // Field su_z:C
      72: aload_0
      73: getfield      #122                // Field su_tPos:I
      76: aload_0
      77: getfield      #37                 // Field data:Lorg/apache/commons/compress/compressors/bzip2/BZip2CompressorInputStream$Data;
      80: getfield      #131                // Field org/apache/commons/compress/compressors/bzip2/BZip2CompressorInputStream$Data.tt:[I
      83: arraylength
      84: ldc           #132                // String su_tPos
      86: invokestatic  #79                 // Method checkBounds:(IILjava/lang/String;)V
      89: aload_0
      90: aload_0
      91: getfield      #37                 // Field data:Lorg/apache/commons/compress/compressors/bzip2/BZip2CompressorInputStream$Data;
      94: getfield      #131                // Field org/apache/commons/compress/compressors/bzip2/BZip2CompressorInputStream$Data.tt:[I
      97: aload_0
      98: getfield      #122                // Field su_tPos:I
     101: iaload
     102: putfield      #122                // Field su_tPos:I
     105: aload_0
     106: getfield      #126                // Field su_rNToGo:I
     109: ifne          150
     112: aload_0
     113: aload_0
     114: getfield      #127                // Field su_rTPos:I
     117: invokestatic  #133                // Method org/apache/commons/compress/compressors/bzip2/Rand.rNums:(I)I
     120: iconst_1
     121: isub
     122: putfield      #126                // Field su_rNToGo:I
     125: aload_0
     126: dup
     127: getfield      #127                // Field su_rTPos:I
     130: iconst_1
     131: iadd
     132: dup_x1
     133: putfield      #127                // Field su_rTPos:I
     136: sipush        512
     139: if_icmpne     160
     142: aload_0
     143: iconst_0
     144: putfield      #127                // Field su_rTPos:I
     147: goto          160
     150: aload_0
     151: dup
     152: getfield      #126                // Field su_rNToGo:I
     155: iconst_1
     156: isub
     157: putfield      #126                // Field su_rNToGo:I
     160: aload_0
     161: iconst_0
     162: putfield      #137                // Field su_j2:I
     165: aload_0
     166: iconst_4
     167: putfield      #7                  // Field currentState:I
     170: aload_0
     171: getfield      #126                // Field su_rNToGo:I
     174: iconst_1
     175: if_icmpne     189
     178: aload_0
     179: dup
     180: getfield      #136                // Field su_z:C
     183: iconst_1
     184: ixor
     185: i2c
     186: putfield      #136                // Field su_z:C
     189: aload_0
     190: invokespecial #45                 // Method setupRandPartC:()I
     193: ireturn

  private int setupRandPartC() throws java.io.IOException;
    Code:
       0: aload_0
       1: getfield      #137                // Field su_j2:I
       4: aload_0
       5: getfield      #136                // Field su_z:C
       8: if_icmpge     37
      11: aload_0
      12: getfield      #5                  // Field crc:Lorg/apache/commons/compress/compressors/bzip2/CRC;
      15: aload_0
      16: getfield      #125                // Field su_ch2:I
      19: invokevirtual #134                // Method org/apache/commons/compress/compressors/bzip2/CRC.updateCRC:(I)V
      22: aload_0
      23: dup
      24: getfield      #137                // Field su_j2:I
      27: iconst_1
      28: iadd
      29: putfield      #137                // Field su_j2:I
      32: aload_0
      33: getfield      #125                // Field su_ch2:I
      36: ireturn
      37: aload_0
      38: iconst_2
      39: putfield      #7                  // Field currentState:I
      42: aload_0
      43: dup
      44: getfield      #124                // Field su_i2:I
      47: iconst_1
      48: iadd
      49: putfield      #124                // Field su_i2:I
      52: aload_0
      53: iconst_0
      54: putfield      #123                // Field su_count:I
      57: aload_0
      58: invokespecial #128                // Method setupRandPartA:()I
      61: ireturn

  private int setupNoRandPartB() throws java.io.IOException;
    Code:
       0: aload_0
       1: getfield      #125                // Field su_ch2:I
       4: aload_0
       5: getfield      #130                // Field su_chPrev:I
       8: if_icmpeq     21
      11: aload_0
      12: iconst_1
      13: putfield      #123                // Field su_count:I
      16: aload_0
      17: invokespecial #129                // Method setupNoRandPartA:()I
      20: ireturn
      21: aload_0
      22: dup
      23: getfield      #123                // Field su_count:I
      26: iconst_1
      27: iadd
      28: dup_x1
      29: putfield      #123                // Field su_count:I
      32: iconst_4
      33: if_icmplt     100
      36: aload_0
      37: getfield      #122                // Field su_tPos:I
      40: aload_0
      41: getfield      #37                 // Field data:Lorg/apache/commons/compress/compressors/bzip2/BZip2CompressorInputStream$Data;
      44: getfield      #99                 // Field org/apache/commons/compress/compressors/bzip2/BZip2CompressorInputStream$Data.ll8:[B
      47: arraylength
      48: ldc           #132                // String su_tPos
      50: invokestatic  #79                 // Method checkBounds:(IILjava/lang/String;)V
      53: aload_0
      54: aload_0
      55: getfield      #37                 // Field data:Lorg/apache/commons/compress/compressors/bzip2/BZip2CompressorInputStream$Data;
      58: getfield      #99                 // Field org/apache/commons/compress/compressors/bzip2/BZip2CompressorInputStream$Data.ll8:[B
      61: aload_0
      62: getfield      #122                // Field su_tPos:I
      65: baload
      66: sipush        255
      69: iand
      70: i2c
      71: putfield      #136                // Field su_z:C
      74: aload_0
      75: aload_0
      76: getfield      #37                 // Field data:Lorg/apache/commons/compress/compressors/bzip2/BZip2CompressorInputStream$Data;
      79: getfield      #131                // Field org/apache/commons/compress/compressors/bzip2/BZip2CompressorInputStream$Data.tt:[I
      82: aload_0
      83: getfield      #122                // Field su_tPos:I
      86: iaload
      87: putfield      #122                // Field su_tPos:I
      90: aload_0
      91: iconst_0
      92: putfield      #137                // Field su_j2:I
      95: aload_0
      96: invokespecial #47                 // Method setupNoRandPartC:()I
      99: ireturn
     100: aload_0
     101: invokespecial #129                // Method setupNoRandPartA:()I
     104: ireturn

  private int setupNoRandPartC() throws java.io.IOException;
    Code:
       0: aload_0
       1: getfield      #137                // Field su_j2:I
       4: aload_0
       5: getfield      #136                // Field su_z:C
       8: if_icmpge     42
      11: aload_0
      12: getfield      #125                // Field su_ch2:I
      15: istore_1
      16: aload_0
      17: getfield      #5                  // Field crc:Lorg/apache/commons/compress/compressors/bzip2/CRC;
      20: iload_1
      21: invokevirtual #134                // Method org/apache/commons/compress/compressors/bzip2/CRC.updateCRC:(I)V
      24: aload_0
      25: dup
      26: getfield      #137                // Field su_j2:I
      29: iconst_1
      30: iadd
      31: putfield      #137                // Field su_j2:I
      34: aload_0
      35: bipush        7
      37: putfield      #7                  // Field currentState:I
      40: iload_1
      41: ireturn
      42: aload_0
      43: dup
      44: getfield      #124                // Field su_i2:I
      47: iconst_1
      48: iadd
      49: putfield      #124                // Field su_i2:I
      52: aload_0
      53: iconst_0
      54: putfield      #123                // Field su_count:I
      57: aload_0
      58: invokespecial #129                // Method setupNoRandPartA:()I
      61: ireturn

  public static boolean matches(byte[], int);
    Code:
       0: iload_1
       1: iconst_3
       2: if_icmplt     33
       5: aload_0
       6: iconst_0
       7: baload
       8: bipush        66
      10: if_icmpne     33
      13: aload_0
      14: iconst_1
      15: baload
      16: bipush        90
      18: if_icmpne     33
      21: aload_0
      22: iconst_2
      23: baload
      24: bipush        104
      26: if_icmpne     33
      29: iconst_1
      30: goto          34
      33: iconst_0
      34: ireturn
}
