Compiled from "ExtendedAccessLogValve.java"
public class org.apache.catalina.valves.ExtendedAccessLogValve$ResponseAllHeaderElement implements org.apache.catalina.valves.AbstractAccessLogValve$AccessLogElement {
  private final java.lang.String header;

  public org.apache.catalina.valves.ExtendedAccessLogValve$ResponseAllHeaderElement(java.lang.String);
    Code:
       0: aload_0
       1: invokespecial #1                  // Method java/lang/Object."<init>":()V
       4: aload_0
       5: aload_1
       6: putfield      #2                  // Field header:Ljava/lang/String;
       9: return

  public void addElement(java.io.CharArrayWriter, java.util.Date, org.apache.catalina.connector.Request, org.apache.catalina.connector.Response, long);
    Code:
       0: aconst_null
       1: aload         4
       3: if_acmpeq     106
       6: aload         4
       8: aload_0
       9: getfield      #2                  // Field header:Ljava/lang/String;
      12: invokevirtual #3                  // Method org/apache/catalina/connector/Response.getHeaders:(Ljava/lang/String;)Ljava/util/Collection;
      15: invokeinterface #4,  1            // InterfaceMethod java/util/Collection.iterator:()Ljava/util/Iterator;
      20: astore        7
      22: aload         7
      24: invokeinterface #5,  1            // InterfaceMethod java/util/Iterator.hasNext:()Z
      29: ifeq          105
      32: new           #6                  // class java/lang/StringBuilder
      35: dup
      36: invokespecial #7                  // Method java/lang/StringBuilder."<init>":()V
      39: astore        8
      41: iconst_1
      42: istore        9
      44: aload         7
      46: invokeinterface #5,  1            // InterfaceMethod java/util/Iterator.hasNext:()Z
      51: ifeq          92
      54: iload         9
      56: ifeq          65
      59: iconst_0
      60: istore        9
      62: goto          73
      65: aload         8
      67: ldc           #8                  // String ,
      69: invokevirtual #9                  // Method java/lang/StringBuilder.append:(Ljava/lang/String;)Ljava/lang/StringBuilder;
      72: pop
      73: aload         8
      75: aload         7
      77: invokeinterface #10,  1           // InterfaceMethod java/util/Iterator.next:()Ljava/lang/Object;
      82: checkcast     #11                 // class java/lang/String
      85: invokevirtual #9                  // Method java/lang/StringBuilder.append:(Ljava/lang/String;)Ljava/lang/StringBuilder;
      88: pop
      89: goto          44
      92: aload_1
      93: aload         8
      95: invokevirtual #12                 // Method java/lang/StringBuilder.toString:()Ljava/lang/String;
      98: invokestatic  #13                 // Method org/apache/catalina/valves/ExtendedAccessLogValve.wrap:(Ljava/lang/Object;)Ljava/lang/String;
     101: invokevirtual #14                 // Method java/io/CharArrayWriter.append:(Ljava/lang/CharSequence;)Ljava/io/CharArrayWriter;
     104: pop
     105: return
     106: aload_1
     107: ldc           #15                 // String -
     109: invokevirtual #14                 // Method java/io/CharArrayWriter.append:(Ljava/lang/CharSequence;)Ljava/io/CharArrayWriter;
     112: pop
     113: return
}
