Compiled from "WSDLElementImpl.java"
public class org.apache.woden.internal.wsdl20.WSDLElementImpl implements org.apache.woden.wsdl20.xml.WSDLElement {
  private static final java.lang.String emptyString;

  private org.apache.woden.internal.wsdl20.extensions.AttributeExtensibleImpl fAttrExt;

  private org.apache.woden.internal.wsdl20.extensions.ElementExtensibleImpl fElemExt;

  private java.util.Map namespaceToPrefixMap;

  private java.util.Map prefixToNamespaceMap;

  public org.apache.woden.internal.wsdl20.WSDLElementImpl();
    Code:
       0: aload_0
       1: invokespecial #1                  // Method java/lang/Object."<init>":()V
       4: aload_0
       5: new           #2                  // class org/apache/woden/internal/wsdl20/extensions/AttributeExtensibleImpl
       8: dup
       9: invokespecial #3                  // Method org/apache/woden/internal/wsdl20/extensions/AttributeExtensibleImpl."<init>":()V
      12: putfield      #4                  // Field fAttrExt:Lorg/apache/woden/internal/wsdl20/extensions/AttributeExtensibleImpl;
      15: aload_0
      16: new           #5                  // class org/apache/woden/internal/wsdl20/extensions/ElementExtensibleImpl
      19: dup
      20: invokespecial #6                  // Method org/apache/woden/internal/wsdl20/extensions/ElementExtensibleImpl."<init>":()V
      23: putfield      #7                  // Field fElemExt:Lorg/apache/woden/internal/wsdl20/extensions/ElementExtensibleImpl;
      26: aload_0
      27: new           #8                  // class java/util/HashMap
      30: dup
      31: invokespecial #9                  // Method java/util/HashMap."<init>":()V
      34: putfield      #10                 // Field namespaceToPrefixMap:Ljava/util/Map;
      37: aload_0
      38: new           #8                  // class java/util/HashMap
      41: dup
      42: invokespecial #9                  // Method java/util/HashMap."<init>":()V
      45: putfield      #11                 // Field prefixToNamespaceMap:Ljava/util/Map;
      48: return

  public void setExtensionAttribute(javax.xml.namespace.QName, org.apache.woden.xml.XMLAttr);
    Code:
       0: aload_0
       1: getfield      #4                  // Field fAttrExt:Lorg/apache/woden/internal/wsdl20/extensions/AttributeExtensibleImpl;
       4: aload_1
       5: aload_2
       6: invokevirtual #12                 // Method org/apache/woden/internal/wsdl20/extensions/AttributeExtensibleImpl.setExtensionAttribute:(Ljavax/xml/namespace/QName;Lorg/apache/woden/xml/XMLAttr;)V
       9: return

  public org.apache.woden.xml.XMLAttr getExtensionAttribute(javax.xml.namespace.QName);
    Code:
       0: aload_0
       1: getfield      #4                  // Field fAttrExt:Lorg/apache/woden/internal/wsdl20/extensions/AttributeExtensibleImpl;
       4: aload_1
       5: invokevirtual #13                 // Method org/apache/woden/internal/wsdl20/extensions/AttributeExtensibleImpl.getExtensionAttribute:(Ljavax/xml/namespace/QName;)Lorg/apache/woden/xml/XMLAttr;
       8: areturn

  public org.apache.woden.xml.XMLAttr[] getExtensionAttributesForNamespace(java.net.URI);
    Code:
       0: aload_0
       1: getfield      #4                  // Field fAttrExt:Lorg/apache/woden/internal/wsdl20/extensions/AttributeExtensibleImpl;
       4: aload_1
       5: invokevirtual #14                 // Method org/apache/woden/internal/wsdl20/extensions/AttributeExtensibleImpl.getExtensionAttributesForNamespace:(Ljava/net/URI;)[Lorg/apache/woden/xml/XMLAttr;
       8: areturn

  public org.apache.woden.xml.XMLAttr[] getExtensionAttributes();
    Code:
       0: aload_0
       1: getfield      #4                  // Field fAttrExt:Lorg/apache/woden/internal/wsdl20/extensions/AttributeExtensibleImpl;
       4: invokevirtual #15                 // Method org/apache/woden/internal/wsdl20/extensions/AttributeExtensibleImpl.getExtensionAttributes:()[Lorg/apache/woden/xml/XMLAttr;
       7: areturn

  public boolean hasExtensionAttributesForNamespace(java.net.URI);
    Code:
       0: aload_0
       1: getfield      #4                  // Field fAttrExt:Lorg/apache/woden/internal/wsdl20/extensions/AttributeExtensibleImpl;
       4: aload_1
       5: invokevirtual #16                 // Method org/apache/woden/internal/wsdl20/extensions/AttributeExtensibleImpl.hasExtensionAttributesForNamespace:(Ljava/net/URI;)Z
       8: ireturn

  public void addExtensionElement(org.apache.woden.wsdl20.extensions.ExtensionElement);
    Code:
       0: aload_0
       1: getfield      #7                  // Field fElemExt:Lorg/apache/woden/internal/wsdl20/extensions/ElementExtensibleImpl;
       4: aload_1
       5: invokevirtual #17                 // Method org/apache/woden/internal/wsdl20/extensions/ElementExtensibleImpl.addExtensionElement:(Lorg/apache/woden/wsdl20/extensions/ExtensionElement;)V
       8: return

  public void removeExtensionElement(org.apache.woden.wsdl20.extensions.ExtensionElement);
    Code:
       0: aload_0
       1: getfield      #7                  // Field fElemExt:Lorg/apache/woden/internal/wsdl20/extensions/ElementExtensibleImpl;
       4: aload_1
       5: invokevirtual #18                 // Method org/apache/woden/internal/wsdl20/extensions/ElementExtensibleImpl.removeExtensionElement:(Lorg/apache/woden/wsdl20/extensions/ExtensionElement;)V
       8: return

  public org.apache.woden.wsdl20.extensions.ExtensionElement[] getExtensionElements();
    Code:
       0: aload_0
       1: getfield      #7                  // Field fElemExt:Lorg/apache/woden/internal/wsdl20/extensions/ElementExtensibleImpl;
       4: invokevirtual #19                 // Method org/apache/woden/internal/wsdl20/extensions/ElementExtensibleImpl.getExtensionElements:()[Lorg/apache/woden/wsdl20/extensions/ExtensionElement;
       7: areturn

  public org.apache.woden.wsdl20.extensions.ExtensionElement[] getExtensionElementsOfType(javax.xml.namespace.QName);
    Code:
       0: aload_0
       1: getfield      #7                  // Field fElemExt:Lorg/apache/woden/internal/wsdl20/extensions/ElementExtensibleImpl;
       4: aload_1
       5: invokevirtual #20                 // Method org/apache/woden/internal/wsdl20/extensions/ElementExtensibleImpl.getExtensionElementsOfType:(Ljavax/xml/namespace/QName;)[Lorg/apache/woden/wsdl20/extensions/ExtensionElement;
       8: areturn

  public boolean hasExtensionElementsForNamespace(java.net.URI);
    Code:
       0: aload_0
       1: getfield      #7                  // Field fElemExt:Lorg/apache/woden/internal/wsdl20/extensions/ElementExtensibleImpl;
       4: aload_1
       5: invokevirtual #21                 // Method org/apache/woden/internal/wsdl20/extensions/ElementExtensibleImpl.hasExtensionElementsForNamespace:(Ljava/net/URI;)Z
       8: ireturn

  org.apache.woden.internal.WSDLContext getWsdlContext();
    Code:
       0: aload_0
       1: invokestatic  #22                 // Method getWsdlContext:(Lorg/apache/woden/wsdl20/xml/WSDLElement;)Lorg/apache/woden/internal/WSDLContext;
       4: areturn

  private static org.apache.woden.internal.WSDLContext getWsdlContext(org.apache.woden.wsdl20.xml.WSDLElement);
    Code:
       0: aload_0
       1: instanceof    #23                 // class org/apache/woden/wsdl20/xml/NestedElement
       4: ifeq          22
       7: aload_0
       8: checkcast     #23                 // class org/apache/woden/wsdl20/xml/NestedElement
      11: invokeinterface #24,  1           // InterfaceMethod org/apache/woden/wsdl20/xml/NestedElement.getParentElement:()Lorg/apache/woden/wsdl20/xml/WSDLElement;
      16: astore_1
      17: aload_1
      18: invokestatic  #22                 // Method getWsdlContext:(Lorg/apache/woden/wsdl20/xml/WSDLElement;)Lorg/apache/woden/internal/WSDLContext;
      21: areturn
      22: aload_0
      23: checkcast     #25                 // class org/apache/woden/internal/wsdl20/WSDLElementImpl
      26: invokevirtual #26                 // Method getWsdlContext:()Lorg/apache/woden/internal/WSDLContext;
      29: areturn

  public void addNamespace(java.lang.String, java.net.URI);
    Code:
       0: aload_1
       1: ifnull        8
       4: aload_1
       5: goto          11
       8: getstatic     #27                 // Field emptyString:Ljava/lang/String;
      11: astore_1
      12: aload_2
      13: ifnonnull     25
      16: aload_0
      17: aload_1
      18: invokevirtual #28                 // Method removeNamespace:(Ljava/lang/String;)Ljava/net/URI;
      21: pop
      22: goto          49
      25: aload_0
      26: getfield      #10                 // Field namespaceToPrefixMap:Ljava/util/Map;
      29: aload_2
      30: aload_1
      31: invokeinterface #29,  3           // InterfaceMethod java/util/Map.put:(Ljava/lang/Object;Ljava/lang/Object;)Ljava/lang/Object;
      36: pop
      37: aload_0
      38: getfield      #11                 // Field prefixToNamespaceMap:Ljava/util/Map;
      41: aload_1
      42: aload_2
      43: invokeinterface #29,  3           // InterfaceMethod java/util/Map.put:(Ljava/lang/Object;Ljava/lang/Object;)Ljava/lang/Object;
      48: pop
      49: return

  public java.net.URI removeNamespace(java.lang.String);
    Code:
       0: aload_1
       1: ifnull        8
       4: aload_1
       5: goto          11
       8: getstatic     #27                 // Field emptyString:Ljava/lang/String;
      11: astore_1
      12: aload_0
      13: getfield      #11                 // Field prefixToNamespaceMap:Ljava/util/Map;
      16: aload_1
      17: invokeinterface #30,  2           // InterfaceMethod java/util/Map.remove:(Ljava/lang/Object;)Ljava/lang/Object;
      22: checkcast     #31                 // class java/net/URI
      25: astore_2
      26: aload_0
      27: getfield      #10                 // Field namespaceToPrefixMap:Ljava/util/Map;
      30: aload_2
      31: invokeinterface #30,  2           // InterfaceMethod java/util/Map.remove:(Ljava/lang/Object;)Ljava/lang/Object;
      36: pop
      37: aload_2
      38: areturn

  public java.lang.String getNamespacePrefix(java.net.URI);
    Code:
       0: aload_0
       1: getfield      #10                 // Field namespaceToPrefixMap:Ljava/util/Map;
       4: aload_1
       5: invokeinterface #32,  2           // InterfaceMethod java/util/Map.get:(Ljava/lang/Object;)Ljava/lang/Object;
      10: checkcast     #33                 // class java/lang/String
      13: astore_2
      14: aload_2
      15: ifnonnull     41
      18: aload_0
      19: instanceof    #23                 // class org/apache/woden/wsdl20/xml/NestedElement
      22: ifeq          41
      25: aload_0
      26: checkcast     #23                 // class org/apache/woden/wsdl20/xml/NestedElement
      29: invokeinterface #24,  1           // InterfaceMethod org/apache/woden/wsdl20/xml/NestedElement.getParentElement:()Lorg/apache/woden/wsdl20/xml/WSDLElement;
      34: aload_1
      35: invokeinterface #34,  2           // InterfaceMethod org/apache/woden/wsdl20/xml/WSDLElement.getNamespacePrefix:(Ljava/net/URI;)Ljava/lang/String;
      40: areturn
      41: aload_2
      42: areturn

  public java.net.URI getNamespaceURI(java.lang.String);
    Code:
       0: aload_1
       1: ifnull        8
       4: aload_1
       5: goto          11
       8: getstatic     #27                 // Field emptyString:Ljava/lang/String;
      11: astore_1
      12: aload_0
      13: getfield      #11                 // Field prefixToNamespaceMap:Ljava/util/Map;
      16: aload_1
      17: invokeinterface #32,  2           // InterfaceMethod java/util/Map.get:(Ljava/lang/Object;)Ljava/lang/Object;
      22: checkcast     #31                 // class java/net/URI
      25: astore_2
      26: aload_2
      27: ifnonnull     53
      30: aload_0
      31: instanceof    #23                 // class org/apache/woden/wsdl20/xml/NestedElement
      34: ifeq          53
      37: aload_0
      38: checkcast     #23                 // class org/apache/woden/wsdl20/xml/NestedElement
      41: invokeinterface #24,  1           // InterfaceMethod org/apache/woden/wsdl20/xml/NestedElement.getParentElement:()Lorg/apache/woden/wsdl20/xml/WSDLElement;
      46: aload_1
      47: invokeinterface #35,  2           // InterfaceMethod org/apache/woden/wsdl20/xml/WSDLElement.getNamespaceURI:(Ljava/lang/String;)Ljava/net/URI;
      52: areturn
      53: aload_2
      54: areturn

  public org.apache.woden.types.NamespaceDeclaration[] getInScopeNamespaces();
    Code:
       0: aload_0
       1: new           #36                 // class java/util/ArrayList
       4: dup
       5: invokespecial #37                 // Method java/util/ArrayList."<init>":()V
       8: invokespecial #38                 // Method addInScopeNamespaces:(Ljava/util/ArrayList;)Ljava/util/ArrayList;
      11: astore_1
      12: aload_1
      13: aload_1
      14: invokevirtual #39                 // Method java/util/ArrayList.size:()I
      17: anewarray     #40                 // class org/apache/woden/types/NamespaceDeclaration
      20: invokevirtual #41                 // Method java/util/ArrayList.toArray:([Ljava/lang/Object;)[Ljava/lang/Object;
      23: checkcast     #42                 // class "[Lorg/apache/woden/types/NamespaceDeclaration;"
      26: checkcast     #42                 // class "[Lorg/apache/woden/types/NamespaceDeclaration;"
      29: areturn

  private java.util.ArrayList addInScopeNamespaces(java.util.ArrayList);
    Code:
       0: aload_0
       1: getfield      #10                 // Field namespaceToPrefixMap:Ljava/util/Map;
       4: invokeinterface #43,  1           // InterfaceMethod java/util/Map.keySet:()Ljava/util/Set;
       9: invokeinterface #44,  1           // InterfaceMethod java/util/Set.iterator:()Ljava/util/Iterator;
      14: astore_2
      15: aload_2
      16: invokeinterface #45,  1           // InterfaceMethod java/util/Iterator.hasNext:()Z
      21: ifeq          63
      24: aload_2
      25: invokeinterface #46,  1           // InterfaceMethod java/util/Iterator.next:()Ljava/lang/Object;
      30: checkcast     #31                 // class java/net/URI
      33: astore_3
      34: aload_1
      35: new           #40                 // class org/apache/woden/types/NamespaceDeclaration
      38: dup
      39: aload_0
      40: getfield      #10                 // Field namespaceToPrefixMap:Ljava/util/Map;
      43: aload_3
      44: invokeinterface #32,  2           // InterfaceMethod java/util/Map.get:(Ljava/lang/Object;)Ljava/lang/Object;
      49: checkcast     #33                 // class java/lang/String
      52: aload_3
      53: invokespecial #47                 // Method org/apache/woden/types/NamespaceDeclaration."<init>":(Ljava/lang/String;Ljava/net/URI;)V
      56: invokevirtual #48                 // Method java/util/ArrayList.add:(Ljava/lang/Object;)Z
      59: pop
      60: goto          15
      63: aload_0
      64: instanceof    #23                 // class org/apache/woden/wsdl20/xml/NestedElement
      67: ifeq          87
      70: aload_0
      71: checkcast     #23                 // class org/apache/woden/wsdl20/xml/NestedElement
      74: invokeinterface #24,  1           // InterfaceMethod org/apache/woden/wsdl20/xml/NestedElement.getParentElement:()Lorg/apache/woden/wsdl20/xml/WSDLElement;
      79: checkcast     #25                 // class org/apache/woden/internal/wsdl20/WSDLElementImpl
      82: aload_1
      83: invokespecial #38                 // Method addInScopeNamespaces:(Ljava/util/ArrayList;)Ljava/util/ArrayList;
      86: areturn
      87: aload_1
      88: areturn

  public org.apache.woden.types.NamespaceDeclaration[] getDeclaredNamespaces();
    Code:
       0: new           #36                 // class java/util/ArrayList
       3: dup
       4: invokespecial #37                 // Method java/util/ArrayList."<init>":()V
       7: astore_1
       8: aload_0
       9: getfield      #10                 // Field namespaceToPrefixMap:Ljava/util/Map;
      12: invokeinterface #43,  1           // InterfaceMethod java/util/Map.keySet:()Ljava/util/Set;
      17: invokeinterface #44,  1           // InterfaceMethod java/util/Set.iterator:()Ljava/util/Iterator;
      22: astore_2
      23: aload_2
      24: invokeinterface #45,  1           // InterfaceMethod java/util/Iterator.hasNext:()Z
      29: ifeq          71
      32: aload_2
      33: invokeinterface #46,  1           // InterfaceMethod java/util/Iterator.next:()Ljava/lang/Object;
      38: checkcast     #31                 // class java/net/URI
      41: astore_3
      42: aload_1
      43: new           #40                 // class org/apache/woden/types/NamespaceDeclaration
      46: dup
      47: aload_0
      48: getfield      #10                 // Field namespaceToPrefixMap:Ljava/util/Map;
      51: aload_3
      52: invokeinterface #32,  2           // InterfaceMethod java/util/Map.get:(Ljava/lang/Object;)Ljava/lang/Object;
      57: checkcast     #33                 // class java/lang/String
      60: aload_3
      61: invokespecial #47                 // Method org/apache/woden/types/NamespaceDeclaration."<init>":(Ljava/lang/String;Ljava/net/URI;)V
      64: invokevirtual #48                 // Method java/util/ArrayList.add:(Ljava/lang/Object;)Z
      67: pop
      68: goto          23
      71: aload_1
      72: aload_1
      73: invokevirtual #39                 // Method java/util/ArrayList.size:()I
      76: anewarray     #40                 // class org/apache/woden/types/NamespaceDeclaration
      79: invokevirtual #41                 // Method java/util/ArrayList.toArray:([Ljava/lang/Object;)[Ljava/lang/Object;
      82: checkcast     #42                 // class "[Lorg/apache/woden/types/NamespaceDeclaration;"
      85: checkcast     #42                 // class "[Lorg/apache/woden/types/NamespaceDeclaration;"
      88: areturn

  static {};
    Code:
       0: ldc           #49                 // String
       2: invokevirtual #50                 // Method java/lang/String.intern:()Ljava/lang/String;
       5: putstatic     #27                 // Field emptyString:Ljava/lang/String;
       8: return
}
