Compiled from "CompressedMessageHandler.java"
class org.jboss.ejb.client.remoting.CompressedMessageHandler extends org.jboss.ejb.client.remoting.ProtocolMessageHandler {
  private final org.jboss.ejb.client.remoting.ChannelAssociation channelAssociation;

  org.jboss.ejb.client.remoting.CompressedMessageHandler(org.jboss.ejb.client.remoting.ChannelAssociation);
    Code:
       0: aload_0
       1: invokespecial #1                  // Method org/jboss/ejb/client/remoting/ProtocolMessageHandler."<init>":()V
       4: aload_0
       5: aload_1
       6: putfield      #2                  // Field channelAssociation:Lorg/jboss/ejb/client/remoting/ChannelAssociation;
       9: return

  protected void processMessage(java.io.InputStream) throws java.io.IOException;
    Code:
       0: new           #3                  // class java/util/zip/InflaterInputStream
       3: dup
       4: aload_1
       5: invokespecial #4                  // Method java/util/zip/InflaterInputStream."<init>":(Ljava/io/InputStream;)V
       8: astore_2
       9: aload_0
      10: getfield      #2                  // Field channelAssociation:Lorg/jboss/ejb/client/remoting/ChannelAssociation;
      13: aload_2
      14: invokevirtual #5                  // Method org/jboss/ejb/client/remoting/ChannelAssociation.processResponse:(Ljava/io/InputStream;)V
      17: return
}
