Compiled from "ConnectionPool.java"
final class org.jboss.ejb.client.remoting.ConnectionPool$PooledConnection implements org.jboss.remoting3.Connection {
  private final java.util.concurrent.atomic.AtomicInteger referenceCount;

  private final org.jboss.ejb.client.remoting.ConnectionPool$CacheKey cacheKey;

  private final org.jboss.remoting3.Connection underlyingConnection;

  final org.jboss.ejb.client.remoting.ConnectionPool this$0;

  org.jboss.ejb.client.remoting.ConnectionPool$PooledConnection(org.jboss.ejb.client.remoting.ConnectionPool, org.jboss.ejb.client.remoting.ConnectionPool$CacheKey, org.jboss.remoting3.Connection);
    Code:
       0: aload_0
       1: aload_1
       2: putfield      #3                  // Field this$0:Lorg/jboss/ejb/client/remoting/ConnectionPool;
       5: aload_0
       6: invokespecial #4                  // Method java/lang/Object."<init>":()V
       9: aload_0
      10: new           #5                  // class java/util/concurrent/atomic/AtomicInteger
      13: dup
      14: iconst_0
      15: invokespecial #6                  // Method java/util/concurrent/atomic/AtomicInteger."<init>":(I)V
      18: putfield      #2                  // Field referenceCount:Ljava/util/concurrent/atomic/AtomicInteger;
      21: aload_0
      22: aload_2
      23: putfield      #7                  // Field cacheKey:Lorg/jboss/ejb/client/remoting/ConnectionPool$CacheKey;
      26: aload_0
      27: aload_3
      28: putfield      #1                  // Field underlyingConnection:Lorg/jboss/remoting3/Connection;
      31: return

  public void close() throws java.io.IOException;
    Code:
       0: aload_0
       1: getfield      #3                  // Field this$0:Lorg/jboss/ejb/client/remoting/ConnectionPool;
       4: aload_0
       5: getfield      #7                  // Field cacheKey:Lorg/jboss/ejb/client/remoting/ConnectionPool$CacheKey;
       8: iconst_0
       9: invokevirtual #8                  // Method org/jboss/ejb/client/remoting/ConnectionPool.release:(Lorg/jboss/ejb/client/remoting/ConnectionPool$CacheKey;Z)V
      12: return

  public void closeAsync();
    Code:
       0: aload_0
       1: getfield      #3                  // Field this$0:Lorg/jboss/ejb/client/remoting/ConnectionPool;
       4: aload_0
       5: getfield      #7                  // Field cacheKey:Lorg/jboss/ejb/client/remoting/ConnectionPool$CacheKey;
       8: iconst_1
       9: invokevirtual #8                  // Method org/jboss/ejb/client/remoting/ConnectionPool.release:(Lorg/jboss/ejb/client/remoting/ConnectionPool$CacheKey;Z)V
      12: return

  public void awaitClosed() throws java.lang.InterruptedException;
    Code:
       0: aload_0
       1: getfield      #1                  // Field underlyingConnection:Lorg/jboss/remoting3/Connection;
       4: invokeinterface #9,  1            // InterfaceMethod org/jboss/remoting3/Connection.awaitClosed:()V
       9: return

  public void awaitClosedUninterruptibly();
    Code:
       0: aload_0
       1: getfield      #1                  // Field underlyingConnection:Lorg/jboss/remoting3/Connection;
       4: invokeinterface #10,  1           // InterfaceMethod org/jboss/remoting3/Connection.awaitClosedUninterruptibly:()V
       9: return

  public org.jboss.remoting3.HandleableCloseable$Key addCloseHandler(org.jboss.remoting3.CloseHandler<? super org.jboss.remoting3.Connection>);
    Code:
       0: aload_0
       1: getfield      #1                  // Field underlyingConnection:Lorg/jboss/remoting3/Connection;
       4: aload_1
       5: invokeinterface #11,  2           // InterfaceMethod org/jboss/remoting3/Connection.addCloseHandler:(Lorg/jboss/remoting3/CloseHandler;)Lorg/jboss/remoting3/HandleableCloseable$Key;
      10: areturn

  public java.util.Collection<java.security.Principal> getPrincipals();
    Code:
       0: aload_0
       1: getfield      #1                  // Field underlyingConnection:Lorg/jboss/remoting3/Connection;
       4: invokeinterface #12,  1           // InterfaceMethod org/jboss/remoting3/Connection.getPrincipals:()Ljava/util/Collection;
       9: areturn

  public org.jboss.remoting3.security.UserInfo getUserInfo();
    Code:
       0: aload_0
       1: getfield      #1                  // Field underlyingConnection:Lorg/jboss/remoting3/Connection;
       4: invokeinterface #13,  1           // InterfaceMethod org/jboss/remoting3/Connection.getUserInfo:()Lorg/jboss/remoting3/security/UserInfo;
       9: areturn

  public org.xnio.IoFuture<org.jboss.remoting3.Channel> openChannel(java.lang.String, org.xnio.OptionMap);
    Code:
       0: aload_0
       1: getfield      #1                  // Field underlyingConnection:Lorg/jboss/remoting3/Connection;
       4: aload_1
       5: aload_2
       6: invokeinterface #14,  3           // InterfaceMethod org/jboss/remoting3/Connection.openChannel:(Ljava/lang/String;Lorg/xnio/OptionMap;)Lorg/xnio/IoFuture;
      11: areturn

  public java.lang.String getRemoteEndpointName();
    Code:
       0: aload_0
       1: getfield      #1                  // Field underlyingConnection:Lorg/jboss/remoting3/Connection;
       4: invokeinterface #15,  1           // InterfaceMethod org/jboss/remoting3/Connection.getRemoteEndpointName:()Ljava/lang/String;
       9: areturn

  public org.jboss.remoting3.Endpoint getEndpoint();
    Code:
       0: aload_0
       1: getfield      #1                  // Field underlyingConnection:Lorg/jboss/remoting3/Connection;
       4: invokeinterface #16,  1           // InterfaceMethod org/jboss/remoting3/Connection.getEndpoint:()Lorg/jboss/remoting3/Endpoint;
       9: areturn

  public org.jboss.remoting3.Attachments getAttachments();
    Code:
       0: aload_0
       1: getfield      #1                  // Field underlyingConnection:Lorg/jboss/remoting3/Connection;
       4: invokeinterface #17,  1           // InterfaceMethod org/jboss/remoting3/Connection.getAttachments:()Lorg/jboss/remoting3/Attachments;
       9: areturn

  public javax.net.ssl.SSLSession getSslSession();
    Code:
       0: aload_0
       1: getfield      #1                  // Field underlyingConnection:Lorg/jboss/remoting3/Connection;
       4: invokeinterface #18,  1           // InterfaceMethod org/jboss/remoting3/Connection.getSslSession:()Ljavax/net/ssl/SSLSession;
       9: areturn

  static java.util.concurrent.atomic.AtomicInteger access$100(org.jboss.ejb.client.remoting.ConnectionPool$PooledConnection);
    Code:
       0: aload_0
       1: getfield      #2                  // Field referenceCount:Ljava/util/concurrent/atomic/AtomicInteger;
       4: areturn

  static org.jboss.remoting3.Connection access$200(org.jboss.ejb.client.remoting.ConnectionPool$PooledConnection);
    Code:
       0: aload_0
       1: getfield      #1                  // Field underlyingConnection:Lorg/jboss/remoting3/Connection;
       4: areturn
}
