Compiled from "PortComponentHandlerType.java"
public class org.apache.cxf.jaxws.handler.types.PortComponentHandlerType {
  protected java.util.List<org.apache.cxf.jaxws.handler.types.DescriptionType> description;

  protected java.util.List<org.apache.cxf.jaxws.handler.types.DisplayNameType> displayName;

  protected java.util.List<org.apache.cxf.jaxws.handler.types.IconType> icon;

  protected org.apache.cxf.jaxws.handler.types.CString handlerName;

  protected org.apache.cxf.jaxws.handler.types.FullyQualifiedClassType handlerClass;

  protected java.util.List<org.apache.cxf.jaxws.handler.types.ParamValueType> initParam;

  protected java.util.List<org.apache.cxf.jaxws.handler.types.XsdQNameType> soapHeader;

  protected java.util.List<org.apache.cxf.jaxws.handler.types.CString> soapRole;

  protected java.lang.String id;

  public org.apache.cxf.jaxws.handler.types.PortComponentHandlerType();
    Code:
       0: aload_0
       1: invokespecial #1                  // Method java/lang/Object."<init>":()V
       4: return

  public java.util.List<org.apache.cxf.jaxws.handler.types.DescriptionType> getDescription();
    Code:
       0: aload_0
       1: getfield      #2                  // Field description:Ljava/util/List;
       4: ifnonnull     18
       7: aload_0
       8: new           #3                  // class java/util/ArrayList
      11: dup
      12: invokespecial #4                  // Method java/util/ArrayList."<init>":()V
      15: putfield      #2                  // Field description:Ljava/util/List;
      18: aload_0
      19: getfield      #2                  // Field description:Ljava/util/List;
      22: areturn

  public java.util.List<org.apache.cxf.jaxws.handler.types.DisplayNameType> getDisplayName();
    Code:
       0: aload_0
       1: getfield      #5                  // Field displayName:Ljava/util/List;
       4: ifnonnull     18
       7: aload_0
       8: new           #3                  // class java/util/ArrayList
      11: dup
      12: invokespecial #4                  // Method java/util/ArrayList."<init>":()V
      15: putfield      #5                  // Field displayName:Ljava/util/List;
      18: aload_0
      19: getfield      #5                  // Field displayName:Ljava/util/List;
      22: areturn

  public java.util.List<org.apache.cxf.jaxws.handler.types.IconType> getIcon();
    Code:
       0: aload_0
       1: getfield      #6                  // Field icon:Ljava/util/List;
       4: ifnonnull     18
       7: aload_0
       8: new           #3                  // class java/util/ArrayList
      11: dup
      12: invokespecial #4                  // Method java/util/ArrayList."<init>":()V
      15: putfield      #6                  // Field icon:Ljava/util/List;
      18: aload_0
      19: getfield      #6                  // Field icon:Ljava/util/List;
      22: areturn

  public org.apache.cxf.jaxws.handler.types.CString getHandlerName();
    Code:
       0: aload_0
       1: getfield      #7                  // Field handlerName:Lorg/apache/cxf/jaxws/handler/types/CString;
       4: ifnonnull     27
       7: aload_0
       8: new           #8                  // class org/apache/cxf/jaxws/handler/types/CString
      11: dup
      12: invokespecial #9                  // Method org/apache/cxf/jaxws/handler/types/CString."<init>":()V
      15: putfield      #7                  // Field handlerName:Lorg/apache/cxf/jaxws/handler/types/CString;
      18: aload_0
      19: getfield      #7                  // Field handlerName:Lorg/apache/cxf/jaxws/handler/types/CString;
      22: ldc           #10                 // String
      24: invokevirtual #11                 // Method org/apache/cxf/jaxws/handler/types/CString.setValue:(Ljava/lang/String;)V
      27: aload_0
      28: getfield      #7                  // Field handlerName:Lorg/apache/cxf/jaxws/handler/types/CString;
      31: areturn

  public void setHandlerName(org.apache.cxf.jaxws.handler.types.CString);
    Code:
       0: aload_0
       1: aload_1
       2: putfield      #7                  // Field handlerName:Lorg/apache/cxf/jaxws/handler/types/CString;
       5: return

  public org.apache.cxf.jaxws.handler.types.FullyQualifiedClassType getHandlerClass();
    Code:
       0: aload_0
       1: getfield      #12                 // Field handlerClass:Lorg/apache/cxf/jaxws/handler/types/FullyQualifiedClassType;
       4: areturn

  public void setHandlerClass(org.apache.cxf.jaxws.handler.types.FullyQualifiedClassType);
    Code:
       0: aload_0
       1: aload_1
       2: putfield      #12                 // Field handlerClass:Lorg/apache/cxf/jaxws/handler/types/FullyQualifiedClassType;
       5: return

  public java.util.List<org.apache.cxf.jaxws.handler.types.ParamValueType> getInitParam();
    Code:
       0: aload_0
       1: getfield      #13                 // Field initParam:Ljava/util/List;
       4: ifnonnull     18
       7: aload_0
       8: new           #3                  // class java/util/ArrayList
      11: dup
      12: invokespecial #4                  // Method java/util/ArrayList."<init>":()V
      15: putfield      #13                 // Field initParam:Ljava/util/List;
      18: aload_0
      19: getfield      #13                 // Field initParam:Ljava/util/List;
      22: areturn

  public java.util.List<org.apache.cxf.jaxws.handler.types.XsdQNameType> getSoapHeader();
    Code:
       0: aload_0
       1: getfield      #14                 // Field soapHeader:Ljava/util/List;
       4: ifnonnull     18
       7: aload_0
       8: new           #3                  // class java/util/ArrayList
      11: dup
      12: invokespecial #4                  // Method java/util/ArrayList."<init>":()V
      15: putfield      #14                 // Field soapHeader:Ljava/util/List;
      18: aload_0
      19: getfield      #14                 // Field soapHeader:Ljava/util/List;
      22: areturn

  public java.util.List<org.apache.cxf.jaxws.handler.types.CString> getSoapRole();
    Code:
       0: aload_0
       1: getfield      #15                 // Field soapRole:Ljava/util/List;
       4: ifnonnull     18
       7: aload_0
       8: new           #3                  // class java/util/ArrayList
      11: dup
      12: invokespecial #4                  // Method java/util/ArrayList."<init>":()V
      15: putfield      #15                 // Field soapRole:Ljava/util/List;
      18: aload_0
      19: getfield      #15                 // Field soapRole:Ljava/util/List;
      22: areturn

  public java.lang.String getId();
    Code:
       0: aload_0
       1: getfield      #16                 // Field id:Ljava/lang/String;
       4: areturn

  public void setId(java.lang.String);
    Code:
       0: aload_0
       1: aload_1
       2: putfield      #16                 // Field id:Ljava/lang/String;
       5: return
}
