public class org.bouncycastle.crypto.tls.LegacyTlsAuthentication extends org.bouncycastle.crypto.tls.ServerOnlyTlsAuthentication {
  protected org.bouncycastle.crypto.tls.CertificateVerifyer verifyer;

  public org.bouncycastle.crypto.tls.LegacyTlsAuthentication(org.bouncycastle.crypto.tls.CertificateVerifyer);
    Code:
       0: aload_0
       1: invokespecial #32                 // Method org/bouncycastle/crypto/tls/ServerOnlyTlsAuthentication."<init>":()V
       4: aload_0
       5: aload_1
       6: putfield      #30                 // Field verifyer:Lorg/bouncycastle/crypto/tls/CertificateVerifyer;
       9: return

  public void notifyServerCertificate(org.bouncycastle.crypto.tls.Certificate) throws java.io.IOException;
    Code:
       0: aload_0
       1: getfield      #30                 // Field verifyer:Lorg/bouncycastle/crypto/tls/CertificateVerifyer;
       4: aload_1
       5: invokevirtual #31                 // Method org/bouncycastle/crypto/tls/Certificate.getCertificateList:()[Lorg/bouncycastle/asn1/x509/Certificate;
       8: invokeinterface #34,  2           // InterfaceMethod org/bouncycastle/crypto/tls/CertificateVerifyer.isValid:([Lorg/bouncycastle/asn1/x509/Certificate;)Z
      13: ifne          26
      16: new           #19                 // class org/bouncycastle/crypto/tls/TlsFatalAlert
      19: dup
      20: bipush        90
      22: invokespecial #33                 // Method org/bouncycastle/crypto/tls/TlsFatalAlert."<init>":(S)V
      25: athrow
      26: return
}
