Compiled from "bla5.java"
public class org.jgroups.tests.bla5$ReadHandler implements java.nio.channels.CompletionHandler<java.lang.Integer, org.jgroups.tests.bla5$Request> {
  protected org.jgroups.tests.bla5$ReadHandler();
    Code:
       0: aload_0
       1: invokespecial #1                  // Method java/lang/Object."<init>":()V
       4: return

  public void completed(java.lang.Integer, org.jgroups.tests.bla5$Request);
    Code:
       0: aload_1
       1: invokevirtual #2                  // Method java/lang/Integer.intValue:()I
       4: ifge          25
       7: aload_2
       8: getfield      #3                  // Field org/jgroups/tests/bla5$Request.ch:Ljava/nio/channels/AsynchronousSocketChannel;
      11: invokevirtual #4                  // Method java/nio/channels/AsynchronousSocketChannel.close:()V
      14: goto          63
      17: astore_3
      18: aload_3
      19: invokevirtual #6                  // Method java/io/IOException.printStackTrace:()V
      22: goto          63
      25: getstatic     #7                  // Field java/lang/System.out:Ljava/io/PrintStream;
      28: ldc           #8                  // String read %d bytes\n
      30: iconst_1
      31: anewarray     #9                  // class java/lang/Object
      34: dup
      35: iconst_0
      36: aload_1
      37: aastore
      38: invokevirtual #10                 // Method java/io/PrintStream.printf:(Ljava/lang/String;[Ljava/lang/Object;)Ljava/io/PrintStream;
      41: pop
      42: aload_2
      43: getfield      #11                 // Field org/jgroups/tests/bla5$Request.buf:Ljava/nio/ByteBuffer;
      46: invokevirtual #12                 // Method java/nio/ByteBuffer.clear:()Ljava/nio/Buffer;
      49: pop
      50: aload_2
      51: getfield      #3                  // Field org/jgroups/tests/bla5$Request.ch:Ljava/nio/channels/AsynchronousSocketChannel;
      54: aload_2
      55: getfield      #11                 // Field org/jgroups/tests/bla5$Request.buf:Ljava/nio/ByteBuffer;
      58: aload_2
      59: aload_0
      60: invokevirtual #13                 // Method java/nio/channels/AsynchronousSocketChannel.read:(Ljava/nio/ByteBuffer;Ljava/lang/Object;Ljava/nio/channels/CompletionHandler;)V
      63: return
    Exception table:
       from    to  target type
           7    14    17   Class java/io/IOException

  public void failed(java.lang.Throwable, org.jgroups.tests.bla5$Request);
    Code:
       0: getstatic     #14                 // Field java/lang/System.err:Ljava/io/PrintStream;
       3: ldc           #15                 // String read(): failed: %s\n
       5: iconst_1
       6: anewarray     #9                  // class java/lang/Object
       9: dup
      10: iconst_0
      11: aload_1
      12: aastore
      13: invokevirtual #10                 // Method java/io/PrintStream.printf:(Ljava/lang/String;[Ljava/lang/Object;)Ljava/io/PrintStream;
      16: pop
      17: return

  public void failed(java.lang.Throwable, java.lang.Object);
    Code:
       0: aload_0
       1: aload_1
       2: aload_2
       3: checkcast     #16                 // class org/jgroups/tests/bla5$Request
       6: invokevirtual #17                 // Method failed:(Ljava/lang/Throwable;Lorg/jgroups/tests/bla5$Request;)V
       9: return

  public void completed(java.lang.Object, java.lang.Object);
    Code:
       0: aload_0
       1: aload_1
       2: checkcast     #18                 // class java/lang/Integer
       5: aload_2
       6: checkcast     #16                 // class org/jgroups/tests/bla5$Request
       9: invokevirtual #19                 // Method completed:(Ljava/lang/Integer;Lorg/jgroups/tests/bla5$Request;)V
      12: return
}
