Compiled from "FlowControlTest.java"
public class org.jgroups.tests.FlowControlTest extends org.jgroups.ReceiverAdapter {
  protected org.jgroups.JChannel ch;

  protected byte[] buf;

  public org.jgroups.tests.FlowControlTest();
    Code:
       0: aload_0
       1: invokespecial #1                  // Method org/jgroups/ReceiverAdapter."<init>":()V
       4: aload_0
       5: ldc           #2                  // int 50000
       7: newarray       byte
       9: putfield      #3                  // Field buf:[B
      12: return

  public void start(java.lang.String, java.lang.String) throws java.lang.Exception;
    Code:
       0: aload_0
       1: new           #4                  // class org/jgroups/JChannel
       4: dup
       5: aload_1
       6: invokespecial #5                  // Method org/jgroups/JChannel."<init>":(Ljava/lang/String;)V
       9: putfield      #6                  // Field ch:Lorg/jgroups/JChannel;
      12: aload_0
      13: getfield      #6                  // Field ch:Lorg/jgroups/JChannel;
      16: aload_2
      17: invokevirtual #7                  // Method org/jgroups/JChannel.setName:(Ljava/lang/String;)V
      20: aload_0
      21: getfield      #6                  // Field ch:Lorg/jgroups/JChannel;
      24: aload_0
      25: invokevirtual #8                  // Method org/jgroups/JChannel.setReceiver:(Lorg/jgroups/Receiver;)V
      28: aload_0
      29: getfield      #6                  // Field ch:Lorg/jgroups/JChannel;
      32: ldc           #9                  // String FlowControlTest
      34: invokevirtual #10                 // Method org/jgroups/JChannel.connect:(Ljava/lang/String;)V
      37: aload_0
      38: invokevirtual #11                 // Method loop:()V
      41: aload_0
      42: getfield      #6                  // Field ch:Lorg/jgroups/JChannel;
      45: invokestatic  #12                 // Method org/jgroups/util/Util.close:(Ljava/io/Closeable;)V
      48: return

  public void receive(org.jgroups.Message);
    Code:
       0: getstatic     #13                 // Field java/lang/System.out:Ljava/io/PrintStream;
       3: new           #14                 // class java/lang/StringBuilder
       6: dup
       7: invokespecial #15                 // Method java/lang/StringBuilder."<init>":()V
      10: ldc           #16                 // String <<
      12: invokevirtual #17                 // Method java/lang/StringBuilder.append:(Ljava/lang/String;)Ljava/lang/StringBuilder;
      15: aload_1
      16: invokevirtual #18                 // Method org/jgroups/Message.getLength:()I
      19: invokevirtual #19                 // Method java/lang/StringBuilder.append:(I)Ljava/lang/StringBuilder;
      22: ldc           #20                 // String  bytes from
      24: invokevirtual #17                 // Method java/lang/StringBuilder.append:(Ljava/lang/String;)Ljava/lang/StringBuilder;
      27: aload_1
      28: invokevirtual #21                 // Method org/jgroups/Message.getSrc:()Lorg/jgroups/Address;
      31: invokevirtual #22                 // Method java/lang/StringBuilder.append:(Ljava/lang/Object;)Ljava/lang/StringBuilder;
      34: invokevirtual #23                 // Method java/lang/StringBuilder.toString:()Ljava/lang/String;
      37: invokevirtual #24                 // Method java/io/PrintStream.println:(Ljava/lang/String;)V
      40: return

  public void viewAccepted(org.jgroups.View);
    Code:
       0: getstatic     #13                 // Field java/lang/System.out:Ljava/io/PrintStream;
       3: new           #14                 // class java/lang/StringBuilder
       6: dup
       7: invokespecial #15                 // Method java/lang/StringBuilder."<init>":()V
      10: ldc           #25                 // String view =
      12: invokevirtual #17                 // Method java/lang/StringBuilder.append:(Ljava/lang/String;)Ljava/lang/StringBuilder;
      15: aload_1
      16: invokevirtual #22                 // Method java/lang/StringBuilder.append:(Ljava/lang/Object;)Ljava/lang/StringBuilder;
      19: invokevirtual #23                 // Method java/lang/StringBuilder.toString:()Ljava/lang/String;
      22: invokevirtual #24                 // Method java/io/PrintStream.println:(Ljava/lang/String;)V
      25: return

  protected void loop();
    Code:
       0: ldc           #26                 // String [1] Send multicast message [2] Send unicast message [3] Set message size [4] Print credits MFC [5] Print credits UFC [q] quit
       2: invokestatic  #27                 // Method org/jgroups/util/Util.keyPress:(Ljava/lang/String;)I
       5: istore_1
       6: iload_1
       7: lookupswitch  { // 8
                    49: 80
                    50: 113
                    51: 153
                    52: 181
                    53: 229
                    81: 277
                   113: 277
                   120: 277
               default: 278
          }
      80: new           #28                 // class org/jgroups/Message
      83: dup
      84: aconst_null
      85: aconst_null
      86: aload_0
      87: getfield      #3                  // Field buf:[B
      90: invokespecial #29                 // Method org/jgroups/Message."<init>":(Lorg/jgroups/Address;Lorg/jgroups/Address;[B)V
      93: astore_2
      94: aload_0
      95: getfield      #6                  // Field ch:Lorg/jgroups/JChannel;
      98: aload_2
      99: invokevirtual #30                 // Method org/jgroups/JChannel.send:(Lorg/jgroups/Message;)V
     102: goto          278
     105: astore_3
     106: aload_3
     107: invokevirtual #32                 // Method java/lang/Exception.printStackTrace:()V
     110: goto          278
     113: aload_0
     114: invokespecial #33                 // Method getReceiver:()Lorg/jgroups/Address;
     117: astore_3
     118: new           #28                 // class org/jgroups/Message
     121: dup
     122: aload_3
     123: aconst_null
     124: aload_0
     125: getfield      #3                  // Field buf:[B
     128: invokespecial #29                 // Method org/jgroups/Message."<init>":(Lorg/jgroups/Address;Lorg/jgroups/Address;[B)V
     131: astore_2
     132: aload_0
     133: getfield      #6                  // Field ch:Lorg/jgroups/JChannel;
     136: aload_2
     137: invokevirtual #30                 // Method org/jgroups/JChannel.send:(Lorg/jgroups/Message;)V
     140: goto          278
     143: astore        4
     145: aload         4
     147: invokevirtual #32                 // Method java/lang/Exception.printStackTrace:()V
     150: goto          278
     153: ldc           #34                 // String New message size:
     155: invokestatic  #35                 // Method org/jgroups/util/Util.readIntFromStdin:(Ljava/lang/String;)I
     158: istore        4
     160: aload_0
     161: iload         4
     163: newarray       byte
     165: putfield      #3                  // Field buf:[B
     168: goto          278
     171: astore        4
     173: aload         4
     175: invokevirtual #32                 // Method java/lang/Exception.printStackTrace:()V
     178: goto          278
     181: aload_0
     182: getfield      #6                  // Field ch:Lorg/jgroups/JChannel;
     185: invokevirtual #36                 // Method org/jgroups/JChannel.getProtocolStack:()Lorg/jgroups/stack/ProtocolStack;
     188: ldc_w         #37                 // class org/jgroups/protocols/MFC
     191: invokevirtual #38                 // Method org/jgroups/stack/ProtocolStack.findProtocol:(Ljava/lang/Class;)Lorg/jgroups/stack/Protocol;
     194: checkcast     #37                 // class org/jgroups/protocols/MFC
     197: astore        4
     199: aload         4
     201: ifnonnull     215
     204: getstatic     #39                 // Field java/lang/System.err:Ljava/io/PrintStream;
     207: ldc           #40                 // String MFC not found
     209: invokevirtual #24                 // Method java/io/PrintStream.println:(Ljava/lang/String;)V
     212: goto          278
     215: getstatic     #13                 // Field java/lang/System.out:Ljava/io/PrintStream;
     218: aload         4
     220: invokevirtual #41                 // Method org/jgroups/protocols/MFC.printCredits:()Ljava/lang/String;
     223: invokevirtual #24                 // Method java/io/PrintStream.println:(Ljava/lang/String;)V
     226: goto          278
     229: aload_0
     230: getfield      #6                  // Field ch:Lorg/jgroups/JChannel;
     233: invokevirtual #36                 // Method org/jgroups/JChannel.getProtocolStack:()Lorg/jgroups/stack/ProtocolStack;
     236: ldc_w         #42                 // class org/jgroups/protocols/UFC
     239: invokevirtual #38                 // Method org/jgroups/stack/ProtocolStack.findProtocol:(Ljava/lang/Class;)Lorg/jgroups/stack/Protocol;
     242: checkcast     #42                 // class org/jgroups/protocols/UFC
     245: astore        5
     247: aload         5
     249: ifnonnull     263
     252: getstatic     #39                 // Field java/lang/System.err:Ljava/io/PrintStream;
     255: ldc           #43                 // String UFC not found
     257: invokevirtual #24                 // Method java/io/PrintStream.println:(Ljava/lang/String;)V
     260: goto          278
     263: getstatic     #13                 // Field java/lang/System.out:Ljava/io/PrintStream;
     266: aload         5
     268: invokevirtual #44                 // Method org/jgroups/protocols/UFC.printCredits:()Ljava/lang/String;
     271: invokevirtual #24                 // Method java/io/PrintStream.println:(Ljava/lang/String;)V
     274: goto          278
     277: return
     278: goto          0
    Exception table:
       from    to  target type
          94   102   105   Class java/lang/Exception
         132   140   143   Class java/lang/Exception
         153   168   171   Class java/lang/Exception

  private org.jgroups.Address getReceiver();
    Code:
       0: aconst_null
       1: astore_1
       2: aload_0
       3: getfield      #6                  // Field ch:Lorg/jgroups/JChannel;
       6: invokevirtual #45                 // Method org/jgroups/JChannel.getView:()Lorg/jgroups/View;
       9: invokevirtual #46                 // Method org/jgroups/View.getMembers:()Ljava/util/List;
      12: astore_1
      13: getstatic     #13                 // Field java/lang/System.out:Ljava/io/PrintStream;
      16: ldc           #47                 // String pick the target from the following members:
      18: invokevirtual #24                 // Method java/io/PrintStream.println:(Ljava/lang/String;)V
      21: iconst_0
      22: istore        5
      24: aload_1
      25: invokeinterface #48,  1           // InterfaceMethod java/util/List.iterator:()Ljava/util/Iterator;
      30: astore        6
      32: aload         6
      34: invokeinterface #49,  1           // InterfaceMethod java/util/Iterator.hasNext:()Z
      39: ifeq          155
      42: aload         6
      44: invokeinterface #50,  1           // InterfaceMethod java/util/Iterator.next:()Ljava/lang/Object;
      49: checkcast     #51                 // class org/jgroups/Address
      52: astore        7
      54: aload         7
      56: aload_0
      57: getfield      #6                  // Field ch:Lorg/jgroups/JChannel;
      60: invokevirtual #52                 // Method org/jgroups/JChannel.getAddress:()Lorg/jgroups/Address;
      63: invokevirtual #53                 // Method java/lang/Object.equals:(Ljava/lang/Object;)Z
      66: ifeq          113
      69: getstatic     #13                 // Field java/lang/System.out:Ljava/io/PrintStream;
      72: new           #14                 // class java/lang/StringBuilder
      75: dup
      76: invokespecial #15                 // Method java/lang/StringBuilder."<init>":()V
      79: ldc           #54                 // String [
      81: invokevirtual #17                 // Method java/lang/StringBuilder.append:(Ljava/lang/String;)Ljava/lang/StringBuilder;
      84: iload         5
      86: invokevirtual #19                 // Method java/lang/StringBuilder.append:(I)Ljava/lang/StringBuilder;
      89: ldc           #55                 // String ]:
      91: invokevirtual #17                 // Method java/lang/StringBuilder.append:(Ljava/lang/String;)Ljava/lang/StringBuilder;
      94: aload         7
      96: invokevirtual #22                 // Method java/lang/StringBuilder.append:(Ljava/lang/Object;)Ljava/lang/StringBuilder;
      99: ldc           #56                 // String  (self)
     101: invokevirtual #17                 // Method java/lang/StringBuilder.append:(Ljava/lang/String;)Ljava/lang/StringBuilder;
     104: invokevirtual #23                 // Method java/lang/StringBuilder.toString:()Ljava/lang/String;
     107: invokevirtual #24                 // Method java/io/PrintStream.println:(Ljava/lang/String;)V
     110: goto          149
     113: getstatic     #13                 // Field java/lang/System.out:Ljava/io/PrintStream;
     116: new           #14                 // class java/lang/StringBuilder
     119: dup
     120: invokespecial #15                 // Method java/lang/StringBuilder."<init>":()V
     123: ldc           #54                 // String [
     125: invokevirtual #17                 // Method java/lang/StringBuilder.append:(Ljava/lang/String;)Ljava/lang/StringBuilder;
     128: iload         5
     130: invokevirtual #19                 // Method java/lang/StringBuilder.append:(I)Ljava/lang/StringBuilder;
     133: ldc           #55                 // String ]:
     135: invokevirtual #17                 // Method java/lang/StringBuilder.append:(Ljava/lang/String;)Ljava/lang/StringBuilder;
     138: aload         7
     140: invokevirtual #22                 // Method java/lang/StringBuilder.append:(Ljava/lang/Object;)Ljava/lang/StringBuilder;
     143: invokevirtual #23                 // Method java/lang/StringBuilder.toString:()Ljava/lang/String;
     146: invokevirtual #24                 // Method java/io/PrintStream.println:(Ljava/lang/String;)V
     149: iinc          5, 1
     152: goto          32
     155: getstatic     #13                 // Field java/lang/System.out:Ljava/io/PrintStream;
     158: invokevirtual #57                 // Method java/io/PrintStream.flush:()V
     161: getstatic     #58                 // Field java/lang/System.in:Ljava/io/InputStream;
     164: getstatic     #58                 // Field java/lang/System.in:Ljava/io/InputStream;
     167: invokevirtual #59                 // Method java/io/InputStream.available:()I
     170: i2l
     171: invokevirtual #60                 // Method java/io/InputStream.skip:(J)J
     174: pop2
     175: new           #61                 // class java/io/BufferedReader
     178: dup
     179: new           #62                 // class java/io/InputStreamReader
     182: dup
     183: getstatic     #58                 // Field java/lang/System.in:Ljava/io/InputStream;
     186: invokespecial #63                 // Method java/io/InputStreamReader."<init>":(Ljava/io/InputStream;)V
     189: invokespecial #64                 // Method java/io/BufferedReader."<init>":(Ljava/io/Reader;)V
     192: astore_3
     193: aload_3
     194: invokevirtual #65                 // Method java/io/BufferedReader.readLine:()Ljava/lang/String;
     197: invokevirtual #66                 // Method java/lang/String.trim:()Ljava/lang/String;
     200: astore        4
     202: aload         4
     204: invokestatic  #67                 // Method java/lang/Integer.parseInt:(Ljava/lang/String;)I
     207: istore_2
     208: aload_1
     209: iload_2
     210: invokeinterface #68,  2           // InterfaceMethod java/util/List.get:(I)Ljava/lang/Object;
     215: checkcast     #51                 // class org/jgroups/Address
     218: areturn
     219: astore        5
     221: getstatic     #39                 // Field java/lang/System.err:Ljava/io/PrintStream;
     224: new           #14                 // class java/lang/StringBuilder
     227: dup
     228: invokespecial #15                 // Method java/lang/StringBuilder."<init>":()V
     231: ldc           #69                 // String getReceiver():
     233: invokevirtual #17                 // Method java/lang/StringBuilder.append:(Ljava/lang/String;)Ljava/lang/StringBuilder;
     236: aload         5
     238: invokevirtual #22                 // Method java/lang/StringBuilder.append:(Ljava/lang/Object;)Ljava/lang/StringBuilder;
     241: invokevirtual #23                 // Method java/lang/StringBuilder.toString:()Ljava/lang/String;
     244: invokevirtual #24                 // Method java/io/PrintStream.println:(Ljava/lang/String;)V
     247: aconst_null
     248: areturn
    Exception table:
       from    to  target type
           2   218   219   Class java/lang/Exception

  public static void main(java.lang.String[]) throws java.lang.Exception;
    Code:
       0: aconst_null
       1: astore_1
       2: aconst_null
       3: astore_2
       4: iconst_0
       5: istore_3
       6: iload_3
       7: aload_0
       8: arraylength
       9: if_icmpge     69
      12: aload_0
      13: iload_3
      14: aaload
      15: ldc           #70                 // String -name
      17: invokevirtual #71                 // Method java/lang/String.equals:(Ljava/lang/Object;)Z
      20: ifeq          33
      23: aload_0
      24: iinc          3, 1
      27: iload_3
      28: aaload
      29: astore_1
      30: goto          63
      33: aload_0
      34: iload_3
      35: aaload
      36: ldc           #72                 // String -props
      38: invokevirtual #71                 // Method java/lang/String.equals:(Ljava/lang/Object;)Z
      41: ifeq          54
      44: aload_0
      45: iinc          3, 1
      48: iload_3
      49: aaload
      50: astore_2
      51: goto          63
      54: getstatic     #13                 // Field java/lang/System.out:Ljava/io/PrintStream;
      57: ldc           #73                 // String FlowControlTest [-props <properties>] [-name <name>]
      59: invokevirtual #24                 // Method java/io/PrintStream.println:(Ljava/lang/String;)V
      62: return
      63: iinc          3, 1
      66: goto          6
      69: new           #74                 // class org/jgroups/tests/FlowControlTest
      72: dup
      73: invokespecial #75                 // Method "<init>":()V
      76: astore_3
      77: aload_3
      78: aload_2
      79: aload_1
      80: invokevirtual #76                 // Method start:(Ljava/lang/String;Ljava/lang/String;)V
      83: return
}
