Compiled from "mcast.java"
public class org.jgroups.tests.mcast$Receiver extends java.lang.Thread {
  protected java.net.MulticastSocket mcast_sock;

  final org.jgroups.tests.mcast this$0;

  protected org.jgroups.tests.mcast$Receiver(org.jgroups.tests.mcast) throws java.lang.Exception;
    Code:
       0: aload_0
       1: aload_1
       2: putfield      #1                  // Field this$0:Lorg/jgroups/tests/mcast;
       5: aload_0
       6: invokespecial #2                  // Method java/lang/Thread."<init>":()V
       9: new           #3                  // class java/net/InetSocketAddress
      12: dup
      13: aload_1
      14: getfield      #4                  // Field org/jgroups/tests/mcast.mcast_addr:Ljava/net/InetAddress;
      17: aload_1
      18: getfield      #5                  // Field org/jgroups/tests/mcast.mcast_port:I
      21: invokespecial #6                  // Method java/net/InetSocketAddress."<init>":(Ljava/net/InetAddress;I)V
      24: astore_2
      25: getstatic     #7                  // Field org/jgroups/tests/mcast.can_bind_to_mcast_addr:Z
      28: ifeq          46
      31: aload_0
      32: new           #8                  // class java/net/MulticastSocket
      35: dup
      36: aload_2
      37: invokespecial #9                  // Method java/net/MulticastSocket."<init>":(Ljava/net/SocketAddress;)V
      40: putfield      #10                 // Field mcast_sock:Ljava/net/MulticastSocket;
      43: goto          61
      46: aload_0
      47: new           #8                  // class java/net/MulticastSocket
      50: dup
      51: aload_1
      52: getfield      #5                  // Field org/jgroups/tests/mcast.mcast_port:I
      55: invokespecial #11                 // Method java/net/MulticastSocket."<init>":(I)V
      58: putfield      #10                 // Field mcast_sock:Ljava/net/MulticastSocket;
      61: aload_1
      62: getfield      #12                 // Field org/jgroups/tests/mcast.bind_addr:Ljava/net/InetAddress;
      65: ifnull        96
      68: aload_1
      69: iconst_1
      70: anewarray     #13                 // class java/net/NetworkInterface
      73: dup
      74: iconst_0
      75: aload_1
      76: getfield      #12                 // Field org/jgroups/tests/mcast.bind_addr:Ljava/net/InetAddress;
      79: invokestatic  #14                 // Method java/net/NetworkInterface.getByInetAddress:(Ljava/net/InetAddress;)Ljava/net/NetworkInterface;
      82: aastore
      83: invokestatic  #15                 // Method java/util/Arrays.asList:([Ljava/lang/Object;)Ljava/util/List;
      86: aload_0
      87: getfield      #10                 // Field mcast_sock:Ljava/net/MulticastSocket;
      90: invokevirtual #16                 // Method org/jgroups/tests/mcast.bindToInterfaces:(Ljava/util/List;Ljava/net/MulticastSocket;)V
      93: goto          143
      96: invokestatic  #17                 // Method org/jgroups/util/Util.getAllAvailableInterfaces:()Ljava/util/List;
      99: astore_3
     100: getstatic     #18                 // Field java/lang/System.out:Ljava/io/PrintStream;
     103: new           #19                 // class java/lang/StringBuilder
     106: dup
     107: invokespecial #20                 // Method java/lang/StringBuilder."<init>":()V
     110: ldc           #21                 // String Joining
     112: invokevirtual #22                 // Method java/lang/StringBuilder.append:(Ljava/lang/String;)Ljava/lang/StringBuilder;
     115: aload_2
     116: invokevirtual #23                 // Method java/lang/StringBuilder.append:(Ljava/lang/Object;)Ljava/lang/StringBuilder;
     119: ldc           #24                 // String  on interfaces:
     121: invokevirtual #22                 // Method java/lang/StringBuilder.append:(Ljava/lang/String;)Ljava/lang/StringBuilder;
     124: aload_3
     125: invokevirtual #23                 // Method java/lang/StringBuilder.append:(Ljava/lang/Object;)Ljava/lang/StringBuilder;
     128: invokevirtual #25                 // Method java/lang/StringBuilder.toString:()Ljava/lang/String;
     131: invokevirtual #26                 // Method java/io/PrintStream.println:(Ljava/lang/String;)V
     134: aload_1
     135: aload_3
     136: aload_0
     137: getfield      #10                 // Field mcast_sock:Ljava/net/MulticastSocket;
     140: invokevirtual #16                 // Method org/jgroups/tests/mcast.bindToInterfaces:(Ljava/util/List;Ljava/net/MulticastSocket;)V
     143: getstatic     #18                 // Field java/lang/System.out:Ljava/io/PrintStream;
     146: new           #19                 // class java/lang/StringBuilder
     149: dup
     150: invokespecial #20                 // Method java/lang/StringBuilder."<init>":()V
     153: ldc           #27                 // String Socket=
     155: invokevirtual #22                 // Method java/lang/StringBuilder.append:(Ljava/lang/String;)Ljava/lang/StringBuilder;
     158: aload_0
     159: getfield      #10                 // Field mcast_sock:Ljava/net/MulticastSocket;
     162: invokevirtual #28                 // Method java/net/MulticastSocket.getLocalAddress:()Ljava/net/InetAddress;
     165: invokevirtual #23                 // Method java/lang/StringBuilder.append:(Ljava/lang/Object;)Ljava/lang/StringBuilder;
     168: bipush        58
     170: invokevirtual #29                 // Method java/lang/StringBuilder.append:(C)Ljava/lang/StringBuilder;
     173: aload_0
     174: getfield      #10                 // Field mcast_sock:Ljava/net/MulticastSocket;
     177: invokevirtual #30                 // Method java/net/MulticastSocket.getLocalPort:()I
     180: invokevirtual #31                 // Method java/lang/StringBuilder.append:(I)Ljava/lang/StringBuilder;
     183: ldc           #32                 // String , bind interface=
     185: invokevirtual #22                 // Method java/lang/StringBuilder.append:(Ljava/lang/String;)Ljava/lang/StringBuilder;
     188: aload_0
     189: getfield      #10                 // Field mcast_sock:Ljava/net/MulticastSocket;
     192: invokevirtual #33                 // Method java/net/MulticastSocket.getInterface:()Ljava/net/InetAddress;
     195: invokevirtual #23                 // Method java/lang/StringBuilder.append:(Ljava/lang/Object;)Ljava/lang/StringBuilder;
     198: invokevirtual #25                 // Method java/lang/StringBuilder.toString:()Ljava/lang/String;
     201: invokevirtual #26                 // Method java/io/PrintStream.println:(Ljava/lang/String;)V
     204: return

  protected void kill();
    Code:
       0: aload_0
       1: getfield      #10                 // Field mcast_sock:Ljava/net/MulticastSocket;
       4: invokevirtual #34                 // Method java/net/MulticastSocket.close:()V
       7: return

  public void run();
    Code:
       0: sipush        1024
       3: newarray       byte
       5: astore_1
       6: new           #35                 // class java/net/DatagramPacket
       9: dup
      10: aload_1
      11: aload_1
      12: arraylength
      13: invokespecial #36                 // Method java/net/DatagramPacket."<init>":([BI)V
      16: astore_2
      17: aload_0
      18: getfield      #10                 // Field mcast_sock:Ljava/net/MulticastSocket;
      21: aload_2
      22: invokevirtual #37                 // Method java/net/MulticastSocket.receive:(Ljava/net/DatagramPacket;)V
      25: aload_2
      26: invokevirtual #38                 // Method java/net/DatagramPacket.getData:()[B
      29: astore_3
      30: aload_2
      31: invokevirtual #39                 // Method java/net/DatagramPacket.getLength:()I
      34: istore        4
      36: getstatic     #18                 // Field java/lang/System.out:Ljava/io/PrintStream;
      39: new           #19                 // class java/lang/StringBuilder
      42: dup
      43: invokespecial #20                 // Method java/lang/StringBuilder."<init>":()V
      46: new           #40                 // class java/lang/String
      49: dup
      50: aload_3
      51: iconst_0
      52: iload         4
      54: invokespecial #41                 // Method java/lang/String."<init>":([BII)V
      57: invokevirtual #22                 // Method java/lang/StringBuilder.append:(Ljava/lang/String;)Ljava/lang/StringBuilder;
      60: ldc           #42                 // String  [sender=
      62: invokevirtual #22                 // Method java/lang/StringBuilder.append:(Ljava/lang/String;)Ljava/lang/StringBuilder;
      65: aload_2
      66: invokevirtual #43                 // Method java/net/DatagramPacket.getAddress:()Ljava/net/InetAddress;
      69: invokevirtual #44                 // Method java/net/InetAddress.getHostAddress:()Ljava/lang/String;
      72: invokevirtual #22                 // Method java/lang/StringBuilder.append:(Ljava/lang/String;)Ljava/lang/StringBuilder;
      75: bipush        58
      77: invokevirtual #29                 // Method java/lang/StringBuilder.append:(C)Ljava/lang/StringBuilder;
      80: aload_2
      81: invokevirtual #45                 // Method java/net/DatagramPacket.getPort:()I
      84: invokevirtual #31                 // Method java/lang/StringBuilder.append:(I)Ljava/lang/StringBuilder;
      87: bipush        93
      89: invokevirtual #29                 // Method java/lang/StringBuilder.append:(C)Ljava/lang/StringBuilder;
      92: invokevirtual #25                 // Method java/lang/StringBuilder.toString:()Ljava/lang/String;
      95: invokevirtual #26                 // Method java/io/PrintStream.println:(Ljava/lang/String;)V
      98: goto          0
     101: astore_1
     102: getstatic     #47                 // Field java/lang/System.err:Ljava/io/PrintStream;
     105: new           #19                 // class java/lang/StringBuilder
     108: dup
     109: invokespecial #20                 // Method java/lang/StringBuilder."<init>":()V
     112: ldc           #48                 // String Receiver terminated:
     114: invokevirtual #22                 // Method java/lang/StringBuilder.append:(Ljava/lang/String;)Ljava/lang/StringBuilder;
     117: aload_1
     118: invokevirtual #23                 // Method java/lang/StringBuilder.append:(Ljava/lang/Object;)Ljava/lang/StringBuilder;
     121: invokevirtual #25                 // Method java/lang/StringBuilder.toString:()Ljava/lang/String;
     124: invokevirtual #26                 // Method java/io/PrintStream.println:(Ljava/lang/String;)V
     127: goto          130
     130: return
    Exception table:
       from    to  target type
           0    98   101   Class java/lang/Exception
}
