Compiled from "TestToaOrder.java"
class org.jgroups.tests.TestToaOrder$MyReceiver extends org.jgroups.ReceiverAdapter {
  private int expectedMembers;

  private int members;

  private final java.util.List<java.lang.String> messageList;

  private final org.jgroups.tests.TestToaOrder testGroupMulticastOrder;

  private long start;

  private long stop;

  private long receivedBytes;

  private int receivedMsgs;

  public org.jgroups.tests.TestToaOrder$MyReceiver(int, org.jgroups.tests.TestToaOrder);
    Code:
       0: aload_0
       1: invokespecial #1                  // Method org/jgroups/ReceiverAdapter."<init>":()V
       4: aload_0
       5: iconst_0
       6: putfield      #2                  // Field members:I
       9: aload_0
      10: lconst_0
      11: putfield      #3                  // Field start:J
      14: aload_0
      15: lconst_0
      16: putfield      #4                  // Field stop:J
      19: aload_0
      20: lconst_0
      21: putfield      #5                  // Field receivedBytes:J
      24: aload_0
      25: iconst_0
      26: putfield      #6                  // Field receivedMsgs:I
      29: aload_0
      30: iload_1
      31: putfield      #7                  // Field expectedMembers:I
      34: aload_0
      35: aload_2
      36: putfield      #8                  // Field testGroupMulticastOrder:Lorg/jgroups/tests/TestToaOrder;
      39: aload_0
      40: new           #9                  // class java/util/LinkedList
      43: dup
      44: invokespecial #10                 // Method java/util/LinkedList."<init>":()V
      47: putfield      #11                 // Field messageList:Ljava/util/List;
      50: return

  public void receive(org.jgroups.Message);
    Code:
       0: aload_1
       1: invokevirtual #12                 // Method org/jgroups/Message.getObject:()Ljava/lang/Object;
       4: checkcast     #13                 // class org/jgroups/tests/TestToaOrder$DataMessage
       7: astore_2
       8: aload_2
       9: invokestatic  #14                 // Method org/jgroups/tests/TestToaOrder$DataMessage.access$100:(Lorg/jgroups/tests/TestToaOrder$DataMessage;)B
      12: lookupswitch  { // 2
                     1: 40
                     2: 54
               default: 143
          }
      40: aload_0
      41: getfield      #8                  // Field testGroupMulticastOrder:Lorg/jgroups/tests/TestToaOrder;
      44: aload_1
      45: invokevirtual #15                 // Method org/jgroups/Message.getSrc:()Lorg/jgroups/Address;
      48: invokevirtual #16                 // Method org/jgroups/tests/TestToaOrder.memberFinished:(Lorg/jgroups/Address;)V
      51: goto          143
      54: aload_0
      55: getfield      #3                  // Field start:J
      58: lconst_0
      59: lcmp
      60: ifne          70
      63: aload_0
      64: invokestatic  #17                 // Method java/lang/System.nanoTime:()J
      67: putfield      #3                  // Field start:J
      70: aload_0
      71: getfield      #11                 // Field messageList:Ljava/util/List;
      74: dup
      75: astore_3
      76: monitorenter
      77: aload_0
      78: getfield      #11                 // Field messageList:Ljava/util/List;
      81: aload_2
      82: invokestatic  #18                 // Method org/jgroups/tests/TestToaOrder$DataMessage.access$200:(Lorg/jgroups/tests/TestToaOrder$DataMessage;)Ljava/lang/String;
      85: invokeinterface #19,  2           // InterfaceMethod java/util/List.add:(Ljava/lang/Object;)Z
      90: pop
      91: aload_3
      92: monitorexit
      93: goto          103
      96: astore        4
      98: aload_3
      99: monitorexit
     100: aload         4
     102: athrow
     103: aload_0
     104: dup
     105: getfield      #5                  // Field receivedBytes:J
     108: aload_2
     109: invokestatic  #18                 // Method org/jgroups/tests/TestToaOrder$DataMessage.access$200:(Lorg/jgroups/tests/TestToaOrder$DataMessage;)Ljava/lang/String;
     112: invokevirtual #20                 // Method java/lang/String.getBytes:()[B
     115: arraylength
     116: iconst_1
     117: iadd
     118: i2l
     119: ladd
     120: putfield      #5                  // Field receivedBytes:J
     123: aload_0
     124: dup
     125: getfield      #6                  // Field receivedMsgs:I
     128: iconst_1
     129: iadd
     130: putfield      #6                  // Field receivedMsgs:I
     133: aload_0
     134: invokestatic  #17                 // Method java/lang/System.nanoTime:()J
     137: putfield      #4                  // Field stop:J
     140: goto          143
     143: return
    Exception table:
       from    to  target type
          77    93    96   any
          96   100    96   any

  public void viewAccepted(org.jgroups.View);
    Code:
       0: getstatic     #21                 // Field java/lang/System.out:Ljava/io/PrintStream;
       3: new           #22                 // class java/lang/StringBuilder
       6: dup
       7: invokespecial #23                 // Method java/lang/StringBuilder."<init>":()V
      10: ldc           #24                 // String New View:
      12: invokevirtual #25                 // Method java/lang/StringBuilder.append:(Ljava/lang/String;)Ljava/lang/StringBuilder;
      15: aload_1
      16: invokevirtual #26                 // Method java/lang/StringBuilder.append:(Ljava/lang/Object;)Ljava/lang/StringBuilder;
      19: invokevirtual #27                 // Method java/lang/StringBuilder.toString:()Ljava/lang/String;
      22: invokevirtual #28                 // Method java/io/PrintStream.println:(Ljava/lang/String;)V
      25: aload_0
      26: aload_1
      27: invokespecial #29                 // Method org/jgroups/ReceiverAdapter.viewAccepted:(Lorg/jgroups/View;)V
      30: aload_0
      31: dup
      32: astore_2
      33: monitorenter
      34: aload_0
      35: aload_1
      36: invokevirtual #30                 // Method org/jgroups/View.getMembers:()Ljava/util/List;
      39: invokeinterface #31,  1           // InterfaceMethod java/util/List.size:()I
      44: putfield      #2                  // Field members:I
      47: aload_0
      48: invokevirtual #32                 // Method java/lang/Object.notify:()V
      51: aload_2
      52: monitorexit
      53: goto          61
      56: astore_3
      57: aload_2
      58: monitorexit
      59: aload_3
      60: athrow
      61: return
    Exception table:
       from    to  target type
          34    53    56   any
          56    59    56   any

  public synchronized void waitUntilClusterIsFormed() throws java.lang.InterruptedException;
    Code:
       0: aload_0
       1: getfield      #2                  // Field members:I
       4: aload_0
       5: getfield      #7                  // Field expectedMembers:I
       8: if_icmpge     58
      11: getstatic     #21                 // Field java/lang/System.out:Ljava/io/PrintStream;
      14: new           #22                 // class java/lang/StringBuilder
      17: dup
      18: invokespecial #23                 // Method java/lang/StringBuilder."<init>":()V
      21: ldc           #33                 // String Number of members is not the expected:
      23: invokevirtual #25                 // Method java/lang/StringBuilder.append:(Ljava/lang/String;)Ljava/lang/StringBuilder;
      26: aload_0
      27: getfield      #2                  // Field members:I
      30: invokevirtual #34                 // Method java/lang/StringBuilder.append:(I)Ljava/lang/StringBuilder;
      33: ldc           #35                 // String  of
      35: invokevirtual #25                 // Method java/lang/StringBuilder.append:(Ljava/lang/String;)Ljava/lang/StringBuilder;
      38: aload_0
      39: getfield      #7                  // Field expectedMembers:I
      42: invokevirtual #34                 // Method java/lang/StringBuilder.append:(I)Ljava/lang/StringBuilder;
      45: invokevirtual #27                 // Method java/lang/StringBuilder.toString:()Ljava/lang/String;
      48: invokevirtual #28                 // Method java/io/PrintStream.println:(Ljava/lang/String;)V
      51: aload_0
      52: invokevirtual #36                 // Method java/lang/Object.wait:()V
      55: goto          0
      58: return

  public void await(int) throws java.lang.InterruptedException;
    Code:
       0: aload_0
       1: getfield      #11                 // Field messageList:Ljava/util/List;
       4: dup
       5: astore_3
       6: monitorenter
       7: aload_0
       8: getfield      #11                 // Field messageList:Ljava/util/List;
      11: invokeinterface #31,  1           // InterfaceMethod java/util/List.size:()I
      16: istore_2
      17: aload_3
      18: monitorexit
      19: goto          29
      22: astore        4
      24: aload_3
      25: monitorexit
      26: aload         4
      28: athrow
      29: iload_2
      30: iload_1
      31: if_icmpge     77
      34: getstatic     #21                 // Field java/lang/System.out:Ljava/io/PrintStream;
      37: new           #22                 // class java/lang/StringBuilder
      40: dup
      41: invokespecial #23                 // Method java/lang/StringBuilder."<init>":()V
      44: ldc           #37                 // String waiting messages...
      46: invokevirtual #25                 // Method java/lang/StringBuilder.append:(Ljava/lang/String;)Ljava/lang/StringBuilder;
      49: iload_2
      50: invokevirtual #34                 // Method java/lang/StringBuilder.append:(I)Ljava/lang/StringBuilder;
      53: ldc           #35                 // String  of
      55: invokevirtual #25                 // Method java/lang/StringBuilder.append:(Ljava/lang/String;)Ljava/lang/StringBuilder;
      58: iload_1
      59: invokevirtual #34                 // Method java/lang/StringBuilder.append:(I)Ljava/lang/StringBuilder;
      62: invokevirtual #27                 // Method java/lang/StringBuilder.toString:()Ljava/lang/String;
      65: invokevirtual #28                 // Method java/io/PrintStream.println:(Ljava/lang/String;)V
      68: ldc2_w        #38                 // long 10000l
      71: invokestatic  #40                 // Method java/lang/Thread.sleep:(J)V
      74: goto          0
      77: return
    Exception table:
       from    to  target type
           7    19    22   any
          22    26    22   any

  public java.util.List<java.lang.String> getMessageList();
    Code:
       0: aload_0
       1: getfield      #11                 // Field messageList:Ljava/util/List;
       4: areturn

  public void printReceiverInfo();
    Code:
       0: getstatic     #21                 // Field java/lang/System.out:Ljava/io/PrintStream;
       3: ldc           #41                 // String +++ Receiver Information +++
       5: invokevirtual #28                 // Method java/io/PrintStream.println:(Ljava/lang/String;)V
       8: aload_0
       9: getfield      #4                  // Field stop:J
      12: aload_0
      13: getfield      #3                  // Field start:J
      16: lsub
      17: l2d
      18: dstore_1
      19: dload_1
      20: ldc2_w        #42                 // double 1000000.0d
      23: ddiv
      24: dstore_1
      25: getstatic     #21                 // Field java/lang/System.out:Ljava/io/PrintStream;
      28: new           #22                 // class java/lang/StringBuilder
      31: dup
      32: invokespecial #23                 // Method java/lang/StringBuilder."<init>":()V
      35: ldc           #44                 // String + Duration (msec)   =
      37: invokevirtual #25                 // Method java/lang/StringBuilder.append:(Ljava/lang/String;)Ljava/lang/StringBuilder;
      40: dload_1
      41: invokevirtual #45                 // Method java/lang/StringBuilder.append:(D)Ljava/lang/StringBuilder;
      44: invokevirtual #27                 // Method java/lang/StringBuilder.toString:()Ljava/lang/String;
      47: invokevirtual #28                 // Method java/io/PrintStream.println:(Ljava/lang/String;)V
      50: getstatic     #21                 // Field java/lang/System.out:Ljava/io/PrintStream;
      53: new           #22                 // class java/lang/StringBuilder
      56: dup
      57: invokespecial #23                 // Method java/lang/StringBuilder."<init>":()V
      60: ldc           #46                 // String + Received Bytes    =
      62: invokevirtual #25                 // Method java/lang/StringBuilder.append:(Ljava/lang/String;)Ljava/lang/StringBuilder;
      65: aload_0
      66: getfield      #5                  // Field receivedBytes:J
      69: invokevirtual #47                 // Method java/lang/StringBuilder.append:(J)Ljava/lang/StringBuilder;
      72: invokevirtual #27                 // Method java/lang/StringBuilder.toString:()Ljava/lang/String;
      75: invokevirtual #28                 // Method java/io/PrintStream.println:(Ljava/lang/String;)V
      78: getstatic     #21                 // Field java/lang/System.out:Ljava/io/PrintStream;
      81: new           #22                 // class java/lang/StringBuilder
      84: dup
      85: invokespecial #23                 // Method java/lang/StringBuilder."<init>":()V
      88: ldc           #48                 // String + Received Messages =
      90: invokevirtual #25                 // Method java/lang/StringBuilder.append:(Ljava/lang/String;)Ljava/lang/StringBuilder;
      93: aload_0
      94: getfield      #6                  // Field receivedMsgs:I
      97: invokevirtual #34                 // Method java/lang/StringBuilder.append:(I)Ljava/lang/StringBuilder;
     100: invokevirtual #27                 // Method java/lang/StringBuilder.toString:()Ljava/lang/String;
     103: invokevirtual #28                 // Method java/io/PrintStream.println:(Ljava/lang/String;)V
     106: dload_1
     107: ldc2_w        #49                 // double 1000.0d
     110: ddiv
     111: dstore_1
     112: getstatic     #21                 // Field java/lang/System.out:Ljava/io/PrintStream;
     115: ldc           #51                 // String ---------------------
     117: invokevirtual #28                 // Method java/io/PrintStream.println:(Ljava/lang/String;)V
     120: getstatic     #21                 // Field java/lang/System.out:Ljava/io/PrintStream;
     123: new           #22                 // class java/lang/StringBuilder
     126: dup
     127: invokespecial #23                 // Method java/lang/StringBuilder."<init>":()V
     130: ldc           #52                 // String + Receiving Throughput (bytes/sec)  =
     132: invokevirtual #25                 // Method java/lang/StringBuilder.append:(Ljava/lang/String;)Ljava/lang/StringBuilder;
     135: aload_0
     136: getfield      #5                  // Field receivedBytes:J
     139: l2d
     140: dload_1
     141: ddiv
     142: invokevirtual #45                 // Method java/lang/StringBuilder.append:(D)Ljava/lang/StringBuilder;
     145: invokevirtual #27                 // Method java/lang/StringBuilder.toString:()Ljava/lang/String;
     148: invokevirtual #28                 // Method java/io/PrintStream.println:(Ljava/lang/String;)V
     151: getstatic     #21                 // Field java/lang/System.out:Ljava/io/PrintStream;
     154: new           #22                 // class java/lang/StringBuilder
     157: dup
     158: invokespecial #23                 // Method java/lang/StringBuilder."<init>":()V
     161: ldc           #53                 // String + Receiving Messages (messages/sec) =
     163: invokevirtual #25                 // Method java/lang/StringBuilder.append:(Ljava/lang/String;)Ljava/lang/StringBuilder;
     166: aload_0
     167: getfield      #6                  // Field receivedMsgs:I
     170: i2d
     171: dload_1
     172: ddiv
     173: invokevirtual #45                 // Method java/lang/StringBuilder.append:(D)Ljava/lang/StringBuilder;
     176: invokevirtual #27                 // Method java/lang/StringBuilder.toString:()Ljava/lang/String;
     179: invokevirtual #28                 // Method java/io/PrintStream.println:(Ljava/lang/String;)V
     182: getstatic     #21                 // Field java/lang/System.out:Ljava/io/PrintStream;
     185: ldc           #54                 // String -------------------------------------
     187: invokevirtual #28                 // Method java/io/PrintStream.println:(Ljava/lang/String;)V
     190: return
}
