Compiled from "ArrayUtil.java"
final class org.jpmml.evaluator.ArrayUtil$1 extends com.google.common.cache.CacheLoader<org.dmg.pmml.Array, java.util.List<?>> {
  org.jpmml.evaluator.ArrayUtil$1();
    Code:
       0: aload_0
       1: invokespecial #1                  // Method com/google/common/cache/CacheLoader."<init>":()V
       4: return

  public java.util.List<?> load(org.dmg.pmml.Array);
    Code:
       0: aload_1
       1: invokestatic  #2                  // Method org/jpmml/evaluator/ArrayUtil.parse:(Lorg/dmg/pmml/Array;)Ljava/util/List;
       4: invokestatic  #3                  // Method com/google/common/collect/ImmutableList.copyOf:(Ljava/util/Collection;)Lcom/google/common/collect/ImmutableList;
       7: areturn

  public java.lang.Object load(java.lang.Object) throws java.lang.Exception;
    Code:
       0: aload_0
       1: aload_1
       2: checkcast     #4                  // class org/dmg/pmml/Array
       5: invokevirtual #5                  // Method load:(Lorg/dmg/pmml/Array;)Ljava/util/List;
       8: areturn
}
