Compiled from "EvaluationContext.java"
public abstract class org.jpmml.evaluator.EvaluationContext {
  private java.util.Map<org.dmg.pmml.FieldName, org.jpmml.evaluator.FieldValue> values;

  private java.util.List<java.lang.String> warnings;

  private static final org.jpmml.evaluator.FieldValue UNDECLARED_VALUE;

  public static final java.lang.ThreadLocal<org.jpmml.evaluator.SymbolTable<org.dmg.pmml.FieldName>> DERIVEDFIELD_GUARD_PROVIDER;

  public static final java.lang.ThreadLocal<org.jpmml.evaluator.SymbolTable<java.lang.String>> FUNCTION_GUARD_PROVIDER;

  org.jpmml.evaluator.EvaluationContext();
    Code:
       0: aload_0
       1: invokespecial #1                  // Method java/lang/Object."<init>":()V
       4: aload_0
       5: aconst_null
       6: putfield      #2                  // Field values:Ljava/util/Map;
       9: aload_0
      10: aconst_null
      11: putfield      #3                  // Field warnings:Ljava/util/List;
      14: aload_0
      15: new           #4                  // class java/util/HashMap
      18: dup
      19: invokespecial #5                  // Method java/util/HashMap."<init>":()V
      22: putfield      #2                  // Field values:Ljava/util/Map;
      25: return

  org.jpmml.evaluator.EvaluationContext(int);
    Code:
       0: aload_0
       1: invokespecial #1                  // Method java/lang/Object."<init>":()V
       4: aload_0
       5: aconst_null
       6: putfield      #2                  // Field values:Ljava/util/Map;
       9: aload_0
      10: aconst_null
      11: putfield      #3                  // Field warnings:Ljava/util/List;
      14: iload_1
      15: sipush        256
      18: if_icmpgt     43
      21: aload_0
      22: new           #4                  // class java/util/HashMap
      25: dup
      26: iconst_2
      27: iload_1
      28: imul
      29: bipush        16
      31: invokestatic  #6                  // Method java/lang/Math.max:(II)I
      34: invokespecial #7                  // Method java/util/HashMap."<init>":(I)V
      37: putfield      #2                  // Field values:Ljava/util/Map;
      40: goto          55
      43: aload_0
      44: new           #4                  // class java/util/HashMap
      47: dup
      48: iload_1
      49: invokespecial #7                  // Method java/util/HashMap."<init>":(I)V
      52: putfield      #2                  // Field values:Ljava/util/Map;
      55: return

  protected abstract org.jpmml.evaluator.FieldValue prepare(org.dmg.pmml.FieldName, java.lang.Object);

  protected void reset(boolean);
    Code:
       0: iload_1
       1: ifeq          13
       4: aload_0
       5: getfield      #2                  // Field values:Ljava/util/Map;
       8: invokeinterface #8,  1            // InterfaceMethod java/util/Map.clear:()V
      13: aload_0
      14: getfield      #3                  // Field warnings:Ljava/util/List;
      17: ifnull        29
      20: aload_0
      21: getfield      #3                  // Field warnings:Ljava/util/List;
      24: invokeinterface #9,  1            // InterfaceMethod java/util/List.clear:()V
      29: return

  public org.jpmml.evaluator.FieldValue lookup(org.dmg.pmml.FieldName);
    Code:
       0: aload_0
       1: invokevirtual #10                 // Method getValues:()Ljava/util/Map;
       4: astore_2
       5: aload_2
       6: aload_1
       7: getstatic     #11                 // Field UNDECLARED_VALUE:Lorg/jpmml/evaluator/FieldValue;
      10: invokeinterface #12,  3           // InterfaceMethod java/util/Map.getOrDefault:(Ljava/lang/Object;Ljava/lang/Object;)Ljava/lang/Object;
      15: checkcast     #13                 // class org/jpmml/evaluator/FieldValue
      18: astore_3
      19: aload_3
      20: getstatic     #11                 // Field UNDECLARED_VALUE:Lorg/jpmml/evaluator/FieldValue;
      23: if_acmpeq     28
      26: aload_3
      27: areturn
      28: new           #14                 // class org/jpmml/evaluator/MissingValueException
      31: dup
      32: aload_1
      33: invokespecial #15                 // Method org/jpmml/evaluator/MissingValueException."<init>":(Lorg/dmg/pmml/FieldName;)V
      36: athrow

  public org.jpmml.evaluator.FieldValue evaluate(org.dmg.pmml.FieldName);
    Code:
       0: aload_0
       1: invokevirtual #10                 // Method getValues:()Ljava/util/Map;
       4: astore_2
       5: aload_2
       6: aload_1
       7: getstatic     #11                 // Field UNDECLARED_VALUE:Lorg/jpmml/evaluator/FieldValue;
      10: invokeinterface #12,  3           // InterfaceMethod java/util/Map.getOrDefault:(Ljava/lang/Object;Ljava/lang/Object;)Ljava/lang/Object;
      15: checkcast     #13                 // class org/jpmml/evaluator/FieldValue
      18: astore_3
      19: aload_3
      20: getstatic     #11                 // Field UNDECLARED_VALUE:Lorg/jpmml/evaluator/FieldValue;
      23: if_acmpeq     28
      26: aload_3
      27: areturn
      28: aload_0
      29: aload_1
      30: invokevirtual #16                 // Method resolve:(Lorg/dmg/pmml/FieldName;)Lorg/jpmml/evaluator/FieldValue;
      33: areturn

  public java.util.List<org.jpmml.evaluator.FieldValue> evaluateAll(java.util.List<org.dmg.pmml.FieldName>);
    Code:
       0: new           #17                 // class java/util/ArrayList
       3: dup
       4: aload_1
       5: invokeinterface #18,  1           // InterfaceMethod java/util/List.size:()I
      10: invokespecial #19                 // Method java/util/ArrayList."<init>":(I)V
      13: astore_2
      14: aload_1
      15: invokeinterface #20,  1           // InterfaceMethod java/util/List.iterator:()Ljava/util/Iterator;
      20: astore_3
      21: aload_3
      22: invokeinterface #21,  1           // InterfaceMethod java/util/Iterator.hasNext:()Z
      27: ifeq          61
      30: aload_3
      31: invokeinterface #22,  1           // InterfaceMethod java/util/Iterator.next:()Ljava/lang/Object;
      36: checkcast     #23                 // class org/dmg/pmml/FieldName
      39: astore        4
      41: aload_0
      42: aload         4
      44: invokevirtual #24                 // Method evaluate:(Lorg/dmg/pmml/FieldName;)Lorg/jpmml/evaluator/FieldValue;
      47: astore        5
      49: aload_2
      50: aload         5
      52: invokeinterface #25,  2           // InterfaceMethod java/util/List.add:(Ljava/lang/Object;)Z
      57: pop
      58: goto          21
      61: aload_2
      62: areturn

  protected org.jpmml.evaluator.FieldValue resolve(org.dmg.pmml.FieldName);
    Code:
       0: new           #26                 // class org/jpmml/evaluator/MissingFieldException
       3: dup
       4: aload_1
       5: invokespecial #27                 // Method org/jpmml/evaluator/MissingFieldException."<init>":(Lorg/dmg/pmml/FieldName;)V
       8: athrow

  public org.jpmml.evaluator.FieldValue declare(org.dmg.pmml.FieldName, java.lang.Object);
    Code:
       0: aload_2
       1: instanceof    #13                 // class org/jpmml/evaluator/FieldValue
       4: ifeq          17
       7: aload_0
       8: aload_1
       9: aload_2
      10: checkcast     #13                 // class org/jpmml/evaluator/FieldValue
      13: invokevirtual #28                 // Method declare:(Lorg/dmg/pmml/FieldName;Lorg/jpmml/evaluator/FieldValue;)Lorg/jpmml/evaluator/FieldValue;
      16: areturn
      17: aload_0
      18: aload_1
      19: aload_2
      20: invokevirtual #29                 // Method prepare:(Lorg/dmg/pmml/FieldName;Ljava/lang/Object;)Lorg/jpmml/evaluator/FieldValue;
      23: astore_2
      24: aload_0
      25: aload_1
      26: aload_2
      27: checkcast     #13                 // class org/jpmml/evaluator/FieldValue
      30: invokevirtual #28                 // Method declare:(Lorg/dmg/pmml/FieldName;Lorg/jpmml/evaluator/FieldValue;)Lorg/jpmml/evaluator/FieldValue;
      33: areturn

  public org.jpmml.evaluator.FieldValue declare(org.dmg.pmml.FieldName, org.jpmml.evaluator.FieldValue);
    Code:
       0: aload_0
       1: invokevirtual #10                 // Method getValues:()Ljava/util/Map;
       4: astore_3
       5: aload_3
       6: aload_1
       7: aload_2
       8: invokeinterface #30,  3           // InterfaceMethod java/util/Map.putIfAbsent:(Ljava/lang/Object;Ljava/lang/Object;)Ljava/lang/Object;
      13: checkcast     #13                 // class org/jpmml/evaluator/FieldValue
      16: astore        4
      18: aload         4
      20: ifnull        32
      23: new           #31                 // class org/jpmml/evaluator/DuplicateValueException
      26: dup
      27: aload_1
      28: invokespecial #32                 // Method org/jpmml/evaluator/DuplicateValueException."<init>":(Lorg/dmg/pmml/FieldName;)V
      31: athrow
      32: aload_2
      33: areturn

  public void declareAll(java.util.Map<org.dmg.pmml.FieldName, ?>);
    Code:
       0: aload_1
       1: invokeinterface #33,  1           // InterfaceMethod java/util/Map.entrySet:()Ljava/util/Set;
       6: astore_2
       7: aload_2
       8: invokeinterface #34,  1           // InterfaceMethod java/util/Collection.iterator:()Ljava/util/Iterator;
      13: astore_3
      14: aload_3
      15: invokeinterface #21,  1           // InterfaceMethod java/util/Iterator.hasNext:()Z
      20: ifeq          59
      23: aload_3
      24: invokeinterface #22,  1           // InterfaceMethod java/util/Iterator.next:()Ljava/lang/Object;
      29: checkcast     #35                 // class java/util/Map$Entry
      32: astore        4
      34: aload_0
      35: aload         4
      37: invokeinterface #36,  1           // InterfaceMethod java/util/Map$Entry.getKey:()Ljava/lang/Object;
      42: checkcast     #23                 // class org/dmg/pmml/FieldName
      45: aload         4
      47: invokeinterface #37,  1           // InterfaceMethod java/util/Map$Entry.getValue:()Ljava/lang/Object;
      52: invokevirtual #38                 // Method declare:(Lorg/dmg/pmml/FieldName;Ljava/lang/Object;)Lorg/jpmml/evaluator/FieldValue;
      55: pop
      56: goto          14
      59: return

  protected org.dmg.pmml.DefineFunction getDefineFunction(java.lang.String);
    Code:
       0: new           #39                 // class java/lang/UnsupportedOperationException
       3: dup
       4: invokespecial #40                 // Method java/lang/UnsupportedOperationException."<init>":()V
       7: athrow

  public void addWarning(java.lang.String);
    Code:
       0: aload_0
       1: getfield      #3                  // Field warnings:Ljava/util/List;
       4: ifnonnull     18
       7: aload_0
       8: new           #17                 // class java/util/ArrayList
      11: dup
      12: invokespecial #41                 // Method java/util/ArrayList."<init>":()V
      15: putfield      #3                  // Field warnings:Ljava/util/List;
      18: aload_0
      19: getfield      #3                  // Field warnings:Ljava/util/List;
      22: aload_1
      23: invokeinterface #25,  2           // InterfaceMethod java/util/List.add:(Ljava/lang/Object;)Z
      28: pop
      29: return

  public java.util.Map<org.dmg.pmml.FieldName, org.jpmml.evaluator.FieldValue> getValues();
    Code:
       0: aload_0
       1: getfield      #2                  // Field values:Ljava/util/Map;
       4: areturn

  public java.util.List<java.lang.String> getWarnings();
    Code:
       0: aload_0
       1: getfield      #3                  // Field warnings:Ljava/util/List;
       4: ifnonnull     11
       7: invokestatic  #42                 // Method java/util/Collections.emptyList:()Ljava/util/List;
      10: areturn
      11: aload_0
      12: getfield      #3                  // Field warnings:Ljava/util/List;
      15: areturn

  static {};
    Code:
       0: new           #43                 // class org/jpmml/evaluator/EvaluationContext$1
       3: dup
       4: getstatic     #44                 // Field org/dmg/pmml/DataType.DOUBLE:Lorg/dmg/pmml/DataType;
       7: ldc2_w        #46                 // double NaNd
      10: invokestatic  #48                 // Method java/lang/Double.valueOf:(D)Ljava/lang/Double;
      13: invokespecial #49                 // Method org/jpmml/evaluator/EvaluationContext$1."<init>":(Lorg/dmg/pmml/DataType;Ljava/lang/Object;)V
      16: putstatic     #11                 // Field UNDECLARED_VALUE:Lorg/jpmml/evaluator/FieldValue;
      19: new           #50                 // class org/jpmml/evaluator/EvaluationContext$2
      22: dup
      23: invokespecial #51                 // Method org/jpmml/evaluator/EvaluationContext$2."<init>":()V
      26: putstatic     #52                 // Field DERIVEDFIELD_GUARD_PROVIDER:Ljava/lang/ThreadLocal;
      29: new           #53                 // class org/jpmml/evaluator/EvaluationContext$3
      32: dup
      33: invokespecial #54                 // Method org/jpmml/evaluator/EvaluationContext$3."<init>":()V
      36: putstatic     #55                 // Field FUNCTION_GUARD_PROVIDER:Ljava/lang/ThreadLocal;
      39: return
}
