Compiled from "ExpressionUtil.java"
class org.jpmml.evaluator.ExpressionUtil$1 {
  static final int[] $SwitchMap$org$dmg$pmml$DataType;

  static final int[] $SwitchMap$org$dmg$pmml$NormDiscrete$Method;

  static final int[] $SwitchMap$org$dmg$pmml$TextIndex$LocalTermWeights;

  static final int[] $SwitchMap$org$dmg$pmml$InvalidValueTreatmentMethod;

  static final int[] $SwitchMap$org$dmg$pmml$Aggregate$Function;

  static {};
    Code:
       0: invokestatic  #1                  // Method org/dmg/pmml/Aggregate$Function.values:()[Lorg/dmg/pmml/Aggregate$Function;
       3: arraylength
       4: newarray       int
       6: putstatic     #2                  // Field $SwitchMap$org$dmg$pmml$Aggregate$Function:[I
       9: getstatic     #2                  // Field $SwitchMap$org$dmg$pmml$Aggregate$Function:[I
      12: getstatic     #3                  // Field org/dmg/pmml/Aggregate$Function.COUNT:Lorg/dmg/pmml/Aggregate$Function;
      15: invokevirtual #4                  // Method org/dmg/pmml/Aggregate$Function.ordinal:()I
      18: iconst_1
      19: iastore
      20: goto          24
      23: astore_0
      24: getstatic     #2                  // Field $SwitchMap$org$dmg$pmml$Aggregate$Function:[I
      27: getstatic     #6                  // Field org/dmg/pmml/Aggregate$Function.SUM:Lorg/dmg/pmml/Aggregate$Function;
      30: invokevirtual #4                  // Method org/dmg/pmml/Aggregate$Function.ordinal:()I
      33: iconst_2
      34: iastore
      35: goto          39
      38: astore_0
      39: getstatic     #2                  // Field $SwitchMap$org$dmg$pmml$Aggregate$Function:[I
      42: getstatic     #7                  // Field org/dmg/pmml/Aggregate$Function.AVERAGE:Lorg/dmg/pmml/Aggregate$Function;
      45: invokevirtual #4                  // Method org/dmg/pmml/Aggregate$Function.ordinal:()I
      48: iconst_3
      49: iastore
      50: goto          54
      53: astore_0
      54: getstatic     #2                  // Field $SwitchMap$org$dmg$pmml$Aggregate$Function:[I
      57: getstatic     #8                  // Field org/dmg/pmml/Aggregate$Function.MIN:Lorg/dmg/pmml/Aggregate$Function;
      60: invokevirtual #4                  // Method org/dmg/pmml/Aggregate$Function.ordinal:()I
      63: iconst_4
      64: iastore
      65: goto          69
      68: astore_0
      69: getstatic     #2                  // Field $SwitchMap$org$dmg$pmml$Aggregate$Function:[I
      72: getstatic     #9                  // Field org/dmg/pmml/Aggregate$Function.MAX:Lorg/dmg/pmml/Aggregate$Function;
      75: invokevirtual #4                  // Method org/dmg/pmml/Aggregate$Function.ordinal:()I
      78: iconst_5
      79: iastore
      80: goto          84
      83: astore_0
      84: invokestatic  #10                 // Method org/dmg/pmml/InvalidValueTreatmentMethod.values:()[Lorg/dmg/pmml/InvalidValueTreatmentMethod;
      87: arraylength
      88: newarray       int
      90: putstatic     #11                 // Field $SwitchMap$org$dmg$pmml$InvalidValueTreatmentMethod:[I
      93: getstatic     #11                 // Field $SwitchMap$org$dmg$pmml$InvalidValueTreatmentMethod:[I
      96: getstatic     #12                 // Field org/dmg/pmml/InvalidValueTreatmentMethod.RETURN_INVALID:Lorg/dmg/pmml/InvalidValueTreatmentMethod;
      99: invokevirtual #13                 // Method org/dmg/pmml/InvalidValueTreatmentMethod.ordinal:()I
     102: iconst_1
     103: iastore
     104: goto          108
     107: astore_0
     108: getstatic     #11                 // Field $SwitchMap$org$dmg$pmml$InvalidValueTreatmentMethod:[I
     111: getstatic     #14                 // Field org/dmg/pmml/InvalidValueTreatmentMethod.AS_IS:Lorg/dmg/pmml/InvalidValueTreatmentMethod;
     114: invokevirtual #13                 // Method org/dmg/pmml/InvalidValueTreatmentMethod.ordinal:()I
     117: iconst_2
     118: iastore
     119: goto          123
     122: astore_0
     123: getstatic     #11                 // Field $SwitchMap$org$dmg$pmml$InvalidValueTreatmentMethod:[I
     126: getstatic     #15                 // Field org/dmg/pmml/InvalidValueTreatmentMethod.AS_MISSING:Lorg/dmg/pmml/InvalidValueTreatmentMethod;
     129: invokevirtual #13                 // Method org/dmg/pmml/InvalidValueTreatmentMethod.ordinal:()I
     132: iconst_3
     133: iastore
     134: goto          138
     137: astore_0
     138: invokestatic  #16                 // Method org/dmg/pmml/TextIndex$LocalTermWeights.values:()[Lorg/dmg/pmml/TextIndex$LocalTermWeights;
     141: arraylength
     142: newarray       int
     144: putstatic     #17                 // Field $SwitchMap$org$dmg$pmml$TextIndex$LocalTermWeights:[I
     147: getstatic     #17                 // Field $SwitchMap$org$dmg$pmml$TextIndex$LocalTermWeights:[I
     150: getstatic     #18                 // Field org/dmg/pmml/TextIndex$LocalTermWeights.BINARY:Lorg/dmg/pmml/TextIndex$LocalTermWeights;
     153: invokevirtual #19                 // Method org/dmg/pmml/TextIndex$LocalTermWeights.ordinal:()I
     156: iconst_1
     157: iastore
     158: goto          162
     161: astore_0
     162: getstatic     #17                 // Field $SwitchMap$org$dmg$pmml$TextIndex$LocalTermWeights:[I
     165: getstatic     #20                 // Field org/dmg/pmml/TextIndex$LocalTermWeights.TERM_FREQUENCY:Lorg/dmg/pmml/TextIndex$LocalTermWeights;
     168: invokevirtual #19                 // Method org/dmg/pmml/TextIndex$LocalTermWeights.ordinal:()I
     171: iconst_2
     172: iastore
     173: goto          177
     176: astore_0
     177: getstatic     #17                 // Field $SwitchMap$org$dmg$pmml$TextIndex$LocalTermWeights:[I
     180: getstatic     #21                 // Field org/dmg/pmml/TextIndex$LocalTermWeights.LOGARITHMIC:Lorg/dmg/pmml/TextIndex$LocalTermWeights;
     183: invokevirtual #19                 // Method org/dmg/pmml/TextIndex$LocalTermWeights.ordinal:()I
     186: iconst_3
     187: iastore
     188: goto          192
     191: astore_0
     192: invokestatic  #22                 // Method org/dmg/pmml/NormDiscrete$Method.values:()[Lorg/dmg/pmml/NormDiscrete$Method;
     195: arraylength
     196: newarray       int
     198: putstatic     #23                 // Field $SwitchMap$org$dmg$pmml$NormDiscrete$Method:[I
     201: getstatic     #23                 // Field $SwitchMap$org$dmg$pmml$NormDiscrete$Method:[I
     204: getstatic     #24                 // Field org/dmg/pmml/NormDiscrete$Method.INDICATOR:Lorg/dmg/pmml/NormDiscrete$Method;
     207: invokevirtual #25                 // Method org/dmg/pmml/NormDiscrete$Method.ordinal:()I
     210: iconst_1
     211: iastore
     212: goto          216
     215: astore_0
     216: invokestatic  #26                 // Method org/dmg/pmml/DataType.values:()[Lorg/dmg/pmml/DataType;
     219: arraylength
     220: newarray       int
     222: putstatic     #27                 // Field $SwitchMap$org$dmg$pmml$DataType:[I
     225: getstatic     #27                 // Field $SwitchMap$org$dmg$pmml$DataType:[I
     228: getstatic     #28                 // Field org/dmg/pmml/DataType.STRING:Lorg/dmg/pmml/DataType;
     231: invokevirtual #29                 // Method org/dmg/pmml/DataType.ordinal:()I
     234: iconst_1
     235: iastore
     236: goto          240
     239: astore_0
     240: return
    Exception table:
       from    to  target type
           9    20    23   Class java/lang/NoSuchFieldError
          24    35    38   Class java/lang/NoSuchFieldError
          39    50    53   Class java/lang/NoSuchFieldError
          54    65    68   Class java/lang/NoSuchFieldError
          69    80    83   Class java/lang/NoSuchFieldError
          93   104   107   Class java/lang/NoSuchFieldError
         108   119   122   Class java/lang/NoSuchFieldError
         123   134   137   Class java/lang/NoSuchFieldError
         147   158   161   Class java/lang/NoSuchFieldError
         162   173   176   Class java/lang/NoSuchFieldError
         177   188   191   Class java/lang/NoSuchFieldError
         201   212   215   Class java/lang/NoSuchFieldError
         225   236   239   Class java/lang/NoSuchFieldError
}
