Compiled from "Functions.java"
public interface org.jpmml.evaluator.Functions {
  public static final org.jpmml.evaluator.functions.ArithmeticFunction ADD;

  public static final org.jpmml.evaluator.functions.ArithmeticFunction SUBTRACT;

  public static final org.jpmml.evaluator.functions.ArithmeticFunction MULTIPLY;

  public static final org.jpmml.evaluator.functions.ArithmeticFunction DIVIDE;

  public static final org.jpmml.evaluator.functions.ArithmeticFunction MODULO;

  public static final org.jpmml.evaluator.functions.AggregateMathFunction MIN;

  public static final org.jpmml.evaluator.functions.AggregateMathFunction MAX;

  public static final org.jpmml.evaluator.functions.AggregateMathFunction AVG;

  public static final org.jpmml.evaluator.functions.AggregateMathFunction SUM;

  public static final org.jpmml.evaluator.functions.AggregateMathFunction PRODUCT;

  public static final org.jpmml.evaluator.functions.DoubleUnaryMathFunction LOG10;

  public static final org.jpmml.evaluator.functions.DoubleUnaryMathFunction LN;

  public static final org.jpmml.evaluator.functions.DoubleUnaryMathFunction LN1P;

  public static final org.jpmml.evaluator.functions.DoubleUnaryMathFunction EXP;

  public static final org.jpmml.evaluator.functions.DoubleUnaryMathFunction EXPM1;

  public static final org.jpmml.evaluator.functions.DoubleUnaryMathFunction SQRT;

  public static final org.jpmml.evaluator.functions.UnaryMathFunction ABS;

  public static final org.jpmml.evaluator.functions.BinaryFunction POW;

  public static final org.jpmml.evaluator.functions.BinaryFunction THRESHOLD;

  public static final org.jpmml.evaluator.functions.RoundingFunction FLOOR;

  public static final org.jpmml.evaluator.functions.RoundingFunction CEIL;

  public static final org.jpmml.evaluator.functions.RoundingFunction ROUND;

  public static final org.jpmml.evaluator.functions.UnaryMathFunction RINT;

  public static final org.jpmml.evaluator.functions.ValueFunction IS_MISSING;

  public static final org.jpmml.evaluator.functions.ValueFunction IS_NOT_MISSING;

  public static final org.jpmml.evaluator.functions.ValueFunction IS_VALID;

  public static final org.jpmml.evaluator.functions.ValueFunction IS_NOT_VALID;

  public static final org.jpmml.evaluator.functions.EqualityFunction EQUAL;

  public static final org.jpmml.evaluator.functions.EqualityFunction NOT_EQUAL;

  public static final org.jpmml.evaluator.functions.ComparisonFunction LESS_THAN;

  public static final org.jpmml.evaluator.functions.ComparisonFunction LESS_OR_EQUAL;

  public static final org.jpmml.evaluator.functions.ComparisonFunction GREATER_THAN;

  public static final org.jpmml.evaluator.functions.ComparisonFunction GREATER_OR_EQUAL;

  public static final org.jpmml.evaluator.functions.LogicalFunction AND;

  public static final org.jpmml.evaluator.functions.LogicalFunction OR;

  public static final org.jpmml.evaluator.functions.UnaryBooleanFunction NOT;

  public static final org.jpmml.evaluator.functions.ValueSpaceFunction IS_IN;

  public static final org.jpmml.evaluator.functions.ValueSpaceFunction IS_NOT_IN;

  public static final org.jpmml.evaluator.functions.MultiaryFunction IF;

  public static final org.jpmml.evaluator.functions.UnaryStringFunction UPPERCASE;

  public static final org.jpmml.evaluator.functions.UnaryStringFunction LOWERCASE;

  public static final org.jpmml.evaluator.functions.TernaryFunction SUBSTRING;

  public static final org.jpmml.evaluator.functions.UnaryStringFunction TRIM_BLANKS;

  public static final org.jpmml.evaluator.functions.AggregateStringFunction CONCAT;

  public static final org.jpmml.evaluator.functions.TernaryFunction REPLACE;

  public static final org.jpmml.evaluator.functions.BinaryFunction MATCHES;

  public static final org.jpmml.evaluator.functions.BinaryFunction FORMAT_NUMBER;

  public static final org.jpmml.evaluator.functions.BinaryFunction FORMAT_DATETIME;

  public static final org.jpmml.evaluator.functions.BinaryFunction DATE_DAYS_SINCE_YEAR;

  public static final org.jpmml.evaluator.functions.UnaryFunction DATE_SECONDS_SINCE_MIDNIGHT;

  public static final org.jpmml.evaluator.functions.BinaryFunction DATE_SECONDS_SINCE_YEAR;

  public static final org.jpmml.evaluator.functions.BinaryFunction HYPOT;

  public static final org.jpmml.evaluator.functions.TrigonometricFunction SIN;

  public static final org.jpmml.evaluator.functions.TrigonometricFunction COS;

  public static final org.jpmml.evaluator.functions.TrigonometricFunction TAN;

  public static final org.jpmml.evaluator.functions.TrigonometricFunction ASIN;

  public static final org.jpmml.evaluator.functions.TrigonometricFunction ACOS;

  public static final org.jpmml.evaluator.functions.TrigonometricFunction ATAN;

  public static final org.jpmml.evaluator.functions.BinaryFunction ATAN2;

  public static final org.jpmml.evaluator.functions.TrigonometricFunction SINH;

  public static final org.jpmml.evaluator.functions.TrigonometricFunction COSH;

  public static final org.jpmml.evaluator.functions.TrigonometricFunction TANH;

  static {};
    Code:
       0: new           #1                  // class org/jpmml/evaluator/Functions$1
       3: dup
       4: ldc           #3                  // String +
       6: invokespecial #4                  // Method org/jpmml/evaluator/Functions$1."<init>":(Ljava/lang/String;)V
       9: putstatic     #5                  // Field ADD:Lorg/jpmml/evaluator/functions/ArithmeticFunction;
      12: new           #6                  // class org/jpmml/evaluator/Functions$2
      15: dup
      16: ldc           #7                  // String -
      18: invokespecial #8                  // Method org/jpmml/evaluator/Functions$2."<init>":(Ljava/lang/String;)V
      21: putstatic     #9                  // Field SUBTRACT:Lorg/jpmml/evaluator/functions/ArithmeticFunction;
      24: new           #10                 // class org/jpmml/evaluator/Functions$3
      27: dup
      28: ldc           #11                 // String *
      30: invokespecial #12                 // Method org/jpmml/evaluator/Functions$3."<init>":(Ljava/lang/String;)V
      33: putstatic     #13                 // Field MULTIPLY:Lorg/jpmml/evaluator/functions/ArithmeticFunction;
      36: new           #14                 // class org/jpmml/evaluator/Functions$4
      39: dup
      40: ldc           #15                 // String /
      42: invokespecial #16                 // Method org/jpmml/evaluator/Functions$4."<init>":(Ljava/lang/String;)V
      45: putstatic     #17                 // Field DIVIDE:Lorg/jpmml/evaluator/functions/ArithmeticFunction;
      48: new           #18                 // class org/jpmml/evaluator/Functions$5
      51: dup
      52: ldc           #19                 // String modulo
      54: invokespecial #20                 // Method org/jpmml/evaluator/Functions$5."<init>":(Ljava/lang/String;)V
      57: putstatic     #21                 // Field MODULO:Lorg/jpmml/evaluator/functions/ArithmeticFunction;
      60: new           #22                 // class org/jpmml/evaluator/Functions$6
      63: dup
      64: ldc           #23                 // String min
      66: invokespecial #24                 // Method org/jpmml/evaluator/Functions$6."<init>":(Ljava/lang/String;)V
      69: putstatic     #25                 // Field MIN:Lorg/jpmml/evaluator/functions/AggregateMathFunction;
      72: new           #26                 // class org/jpmml/evaluator/Functions$7
      75: dup
      76: ldc           #27                 // String max
      78: invokespecial #28                 // Method org/jpmml/evaluator/Functions$7."<init>":(Ljava/lang/String;)V
      81: putstatic     #29                 // Field MAX:Lorg/jpmml/evaluator/functions/AggregateMathFunction;
      84: new           #30                 // class org/jpmml/evaluator/Functions$8
      87: dup
      88: ldc           #31                 // String avg
      90: invokespecial #32                 // Method org/jpmml/evaluator/Functions$8."<init>":(Ljava/lang/String;)V
      93: putstatic     #33                 // Field AVG:Lorg/jpmml/evaluator/functions/AggregateMathFunction;
      96: new           #34                 // class org/jpmml/evaluator/Functions$9
      99: dup
     100: ldc           #35                 // String sum
     102: invokespecial #36                 // Method org/jpmml/evaluator/Functions$9."<init>":(Ljava/lang/String;)V
     105: putstatic     #37                 // Field SUM:Lorg/jpmml/evaluator/functions/AggregateMathFunction;
     108: new           #38                 // class org/jpmml/evaluator/Functions$10
     111: dup
     112: ldc           #39                 // String product
     114: invokespecial #40                 // Method org/jpmml/evaluator/Functions$10."<init>":(Ljava/lang/String;)V
     117: putstatic     #41                 // Field PRODUCT:Lorg/jpmml/evaluator/functions/AggregateMathFunction;
     120: new           #42                 // class org/jpmml/evaluator/Functions$11
     123: dup
     124: ldc           #43                 // String log10
     126: invokespecial #44                 // Method org/jpmml/evaluator/Functions$11."<init>":(Ljava/lang/String;)V
     129: putstatic     #45                 // Field LOG10:Lorg/jpmml/evaluator/functions/DoubleUnaryMathFunction;
     132: new           #46                 // class org/jpmml/evaluator/Functions$12
     135: dup
     136: ldc           #47                 // String ln
     138: invokespecial #48                 // Method org/jpmml/evaluator/Functions$12."<init>":(Ljava/lang/String;)V
     141: putstatic     #49                 // Field LN:Lorg/jpmml/evaluator/functions/DoubleUnaryMathFunction;
     144: new           #50                 // class org/jpmml/evaluator/Functions$13
     147: dup
     148: ldc           #51                 // String ln1p
     150: invokespecial #52                 // Method org/jpmml/evaluator/Functions$13."<init>":(Ljava/lang/String;)V
     153: putstatic     #53                 // Field LN1P:Lorg/jpmml/evaluator/functions/DoubleUnaryMathFunction;
     156: new           #54                 // class org/jpmml/evaluator/Functions$14
     159: dup
     160: ldc           #55                 // String exp
     162: invokespecial #56                 // Method org/jpmml/evaluator/Functions$14."<init>":(Ljava/lang/String;)V
     165: putstatic     #57                 // Field EXP:Lorg/jpmml/evaluator/functions/DoubleUnaryMathFunction;
     168: new           #58                 // class org/jpmml/evaluator/Functions$15
     171: dup
     172: ldc           #59                 // String expm1
     174: invokespecial #60                 // Method org/jpmml/evaluator/Functions$15."<init>":(Ljava/lang/String;)V
     177: putstatic     #61                 // Field EXPM1:Lorg/jpmml/evaluator/functions/DoubleUnaryMathFunction;
     180: new           #62                 // class org/jpmml/evaluator/Functions$16
     183: dup
     184: ldc           #63                 // String sqrt
     186: invokespecial #64                 // Method org/jpmml/evaluator/Functions$16."<init>":(Ljava/lang/String;)V
     189: putstatic     #65                 // Field SQRT:Lorg/jpmml/evaluator/functions/DoubleUnaryMathFunction;
     192: new           #66                 // class org/jpmml/evaluator/Functions$17
     195: dup
     196: ldc           #67                 // String abs
     198: invokespecial #68                 // Method org/jpmml/evaluator/Functions$17."<init>":(Ljava/lang/String;)V
     201: putstatic     #69                 // Field ABS:Lorg/jpmml/evaluator/functions/UnaryMathFunction;
     204: new           #70                 // class org/jpmml/evaluator/Functions$18
     207: dup
     208: ldc           #71                 // String pow
     210: invokespecial #72                 // Method org/jpmml/evaluator/Functions$18."<init>":(Ljava/lang/String;)V
     213: putstatic     #73                 // Field POW:Lorg/jpmml/evaluator/functions/BinaryFunction;
     216: new           #74                 // class org/jpmml/evaluator/Functions$19
     219: dup
     220: ldc           #75                 // String threshold
     222: invokespecial #76                 // Method org/jpmml/evaluator/Functions$19."<init>":(Ljava/lang/String;)V
     225: putstatic     #77                 // Field THRESHOLD:Lorg/jpmml/evaluator/functions/BinaryFunction;
     228: new           #78                 // class org/jpmml/evaluator/Functions$20
     231: dup
     232: ldc           #79                 // String floor
     234: invokespecial #80                 // Method org/jpmml/evaluator/Functions$20."<init>":(Ljava/lang/String;)V
     237: putstatic     #81                 // Field FLOOR:Lorg/jpmml/evaluator/functions/RoundingFunction;
     240: new           #82                 // class org/jpmml/evaluator/Functions$21
     243: dup
     244: ldc           #83                 // String ceil
     246: invokespecial #84                 // Method org/jpmml/evaluator/Functions$21."<init>":(Ljava/lang/String;)V
     249: putstatic     #85                 // Field CEIL:Lorg/jpmml/evaluator/functions/RoundingFunction;
     252: new           #86                 // class org/jpmml/evaluator/Functions$22
     255: dup
     256: ldc           #87                 // String round
     258: invokespecial #88                 // Method org/jpmml/evaluator/Functions$22."<init>":(Ljava/lang/String;)V
     261: putstatic     #89                 // Field ROUND:Lorg/jpmml/evaluator/functions/RoundingFunction;
     264: new           #90                 // class org/jpmml/evaluator/Functions$23
     267: dup
     268: ldc           #91                 // String rint
     270: invokespecial #92                 // Method org/jpmml/evaluator/Functions$23."<init>":(Ljava/lang/String;)V
     273: putstatic     #93                 // Field RINT:Lorg/jpmml/evaluator/functions/UnaryMathFunction;
     276: new           #94                 // class org/jpmml/evaluator/Functions$24
     279: dup
     280: ldc           #95                 // String isMissing
     282: invokespecial #96                 // Method org/jpmml/evaluator/Functions$24."<init>":(Ljava/lang/String;)V
     285: putstatic     #97                 // Field IS_MISSING:Lorg/jpmml/evaluator/functions/ValueFunction;
     288: new           #98                 // class org/jpmml/evaluator/Functions$25
     291: dup
     292: ldc           #99                 // String isNotMissing
     294: invokespecial #100                // Method org/jpmml/evaluator/Functions$25."<init>":(Ljava/lang/String;)V
     297: putstatic     #101                // Field IS_NOT_MISSING:Lorg/jpmml/evaluator/functions/ValueFunction;
     300: new           #102                // class org/jpmml/evaluator/Functions$26
     303: dup
     304: ldc           #103                // String isValid
     306: invokespecial #104                // Method org/jpmml/evaluator/Functions$26."<init>":(Ljava/lang/String;)V
     309: putstatic     #105                // Field IS_VALID:Lorg/jpmml/evaluator/functions/ValueFunction;
     312: new           #106                // class org/jpmml/evaluator/Functions$27
     315: dup
     316: ldc           #107                // String isNotValid
     318: invokespecial #108                // Method org/jpmml/evaluator/Functions$27."<init>":(Ljava/lang/String;)V
     321: putstatic     #109                // Field IS_NOT_VALID:Lorg/jpmml/evaluator/functions/ValueFunction;
     324: new           #110                // class org/jpmml/evaluator/Functions$28
     327: dup
     328: ldc           #111                // String equal
     330: invokespecial #112                // Method org/jpmml/evaluator/Functions$28."<init>":(Ljava/lang/String;)V
     333: putstatic     #113                // Field EQUAL:Lorg/jpmml/evaluator/functions/EqualityFunction;
     336: new           #114                // class org/jpmml/evaluator/Functions$29
     339: dup
     340: ldc           #115                // String notEqual
     342: invokespecial #116                // Method org/jpmml/evaluator/Functions$29."<init>":(Ljava/lang/String;)V
     345: putstatic     #117                // Field NOT_EQUAL:Lorg/jpmml/evaluator/functions/EqualityFunction;
     348: new           #118                // class org/jpmml/evaluator/Functions$30
     351: dup
     352: ldc           #119                // String lessThan
     354: invokespecial #120                // Method org/jpmml/evaluator/Functions$30."<init>":(Ljava/lang/String;)V
     357: putstatic     #121                // Field LESS_THAN:Lorg/jpmml/evaluator/functions/ComparisonFunction;
     360: new           #122                // class org/jpmml/evaluator/Functions$31
     363: dup
     364: ldc           #123                // String lessOrEqual
     366: invokespecial #124                // Method org/jpmml/evaluator/Functions$31."<init>":(Ljava/lang/String;)V
     369: putstatic     #125                // Field LESS_OR_EQUAL:Lorg/jpmml/evaluator/functions/ComparisonFunction;
     372: new           #126                // class org/jpmml/evaluator/Functions$32
     375: dup
     376: ldc           #127                // String greaterThan
     378: invokespecial #128                // Method org/jpmml/evaluator/Functions$32."<init>":(Ljava/lang/String;)V
     381: putstatic     #129                // Field GREATER_THAN:Lorg/jpmml/evaluator/functions/ComparisonFunction;
     384: new           #130                // class org/jpmml/evaluator/Functions$33
     387: dup
     388: ldc           #131                // String greaterOrEqual
     390: invokespecial #132                // Method org/jpmml/evaluator/Functions$33."<init>":(Ljava/lang/String;)V
     393: putstatic     #133                // Field GREATER_OR_EQUAL:Lorg/jpmml/evaluator/functions/ComparisonFunction;
     396: new           #134                // class org/jpmml/evaluator/Functions$34
     399: dup
     400: ldc           #135                // String and
     402: invokespecial #136                // Method org/jpmml/evaluator/Functions$34."<init>":(Ljava/lang/String;)V
     405: putstatic     #137                // Field AND:Lorg/jpmml/evaluator/functions/LogicalFunction;
     408: new           #138                // class org/jpmml/evaluator/Functions$35
     411: dup
     412: ldc           #139                // String or
     414: invokespecial #140                // Method org/jpmml/evaluator/Functions$35."<init>":(Ljava/lang/String;)V
     417: putstatic     #141                // Field OR:Lorg/jpmml/evaluator/functions/LogicalFunction;
     420: new           #142                // class org/jpmml/evaluator/Functions$36
     423: dup
     424: ldc           #143                // String not
     426: invokespecial #144                // Method org/jpmml/evaluator/Functions$36."<init>":(Ljava/lang/String;)V
     429: putstatic     #145                // Field NOT:Lorg/jpmml/evaluator/functions/UnaryBooleanFunction;
     432: new           #146                // class org/jpmml/evaluator/Functions$37
     435: dup
     436: ldc           #147                // String isIn
     438: invokespecial #148                // Method org/jpmml/evaluator/Functions$37."<init>":(Ljava/lang/String;)V
     441: putstatic     #149                // Field IS_IN:Lorg/jpmml/evaluator/functions/ValueSpaceFunction;
     444: new           #150                // class org/jpmml/evaluator/Functions$38
     447: dup
     448: ldc           #151                // String isNotIn
     450: invokespecial #152                // Method org/jpmml/evaluator/Functions$38."<init>":(Ljava/lang/String;)V
     453: putstatic     #153                // Field IS_NOT_IN:Lorg/jpmml/evaluator/functions/ValueSpaceFunction;
     456: new           #154                // class org/jpmml/evaluator/Functions$39
     459: dup
     460: ldc           #155                // String if
     462: invokespecial #156                // Method org/jpmml/evaluator/Functions$39."<init>":(Ljava/lang/String;)V
     465: putstatic     #157                // Field IF:Lorg/jpmml/evaluator/functions/MultiaryFunction;
     468: new           #158                // class org/jpmml/evaluator/Functions$40
     471: dup
     472: ldc           #159                // String uppercase
     474: invokespecial #160                // Method org/jpmml/evaluator/Functions$40."<init>":(Ljava/lang/String;)V
     477: putstatic     #161                // Field UPPERCASE:Lorg/jpmml/evaluator/functions/UnaryStringFunction;
     480: new           #162                // class org/jpmml/evaluator/Functions$41
     483: dup
     484: ldc           #163                // String lowercase
     486: invokespecial #164                // Method org/jpmml/evaluator/Functions$41."<init>":(Ljava/lang/String;)V
     489: putstatic     #165                // Field LOWERCASE:Lorg/jpmml/evaluator/functions/UnaryStringFunction;
     492: new           #166                // class org/jpmml/evaluator/Functions$42
     495: dup
     496: ldc           #167                // String substring
     498: iconst_3
     499: anewarray     #168                // class java/lang/String
     502: dup
     503: iconst_0
     504: ldc           #169                // String input
     506: aastore
     507: dup
     508: iconst_1
     509: ldc           #170                // String startPos
     511: aastore
     512: dup
     513: iconst_2
     514: ldc           #171                // String length
     516: aastore
     517: invokestatic  #172                // Method java/util/Arrays.asList:([Ljava/lang/Object;)Ljava/util/List;
     520: invokespecial #173                // Method org/jpmml/evaluator/Functions$42."<init>":(Ljava/lang/String;Ljava/util/List;)V
     523: putstatic     #174                // Field SUBSTRING:Lorg/jpmml/evaluator/functions/TernaryFunction;
     526: new           #175                // class org/jpmml/evaluator/Functions$43
     529: dup
     530: ldc           #176                // String trimBlanks
     532: invokespecial #177                // Method org/jpmml/evaluator/Functions$43."<init>":(Ljava/lang/String;)V
     535: putstatic     #178                // Field TRIM_BLANKS:Lorg/jpmml/evaluator/functions/UnaryStringFunction;
     538: new           #179                // class org/jpmml/evaluator/Functions$44
     541: dup
     542: ldc           #180                // String concat
     544: invokespecial #181                // Method org/jpmml/evaluator/Functions$44."<init>":(Ljava/lang/String;)V
     547: putstatic     #182                // Field CONCAT:Lorg/jpmml/evaluator/functions/AggregateStringFunction;
     550: new           #183                // class org/jpmml/evaluator/Functions$45
     553: dup
     554: ldc           #184                // String replace
     556: iconst_3
     557: anewarray     #168                // class java/lang/String
     560: dup
     561: iconst_0
     562: ldc           #169                // String input
     564: aastore
     565: dup
     566: iconst_1
     567: ldc           #185                // String pattern
     569: aastore
     570: dup
     571: iconst_2
     572: ldc           #186                // String replacement
     574: aastore
     575: invokestatic  #172                // Method java/util/Arrays.asList:([Ljava/lang/Object;)Ljava/util/List;
     578: invokespecial #187                // Method org/jpmml/evaluator/Functions$45."<init>":(Ljava/lang/String;Ljava/util/List;)V
     581: putstatic     #188                // Field REPLACE:Lorg/jpmml/evaluator/functions/TernaryFunction;
     584: new           #189                // class org/jpmml/evaluator/Functions$46
     587: dup
     588: ldc           #190                // String matches
     590: iconst_2
     591: anewarray     #168                // class java/lang/String
     594: dup
     595: iconst_0
     596: ldc           #169                // String input
     598: aastore
     599: dup
     600: iconst_1
     601: ldc           #185                // String pattern
     603: aastore
     604: invokestatic  #172                // Method java/util/Arrays.asList:([Ljava/lang/Object;)Ljava/util/List;
     607: invokespecial #191                // Method org/jpmml/evaluator/Functions$46."<init>":(Ljava/lang/String;Ljava/util/List;)V
     610: putstatic     #192                // Field MATCHES:Lorg/jpmml/evaluator/functions/BinaryFunction;
     613: new           #193                // class org/jpmml/evaluator/Functions$47
     616: dup
     617: ldc           #194                // String formatNumber
     619: iconst_2
     620: anewarray     #168                // class java/lang/String
     623: dup
     624: iconst_0
     625: ldc           #169                // String input
     627: aastore
     628: dup
     629: iconst_1
     630: ldc           #185                // String pattern
     632: aastore
     633: invokestatic  #172                // Method java/util/Arrays.asList:([Ljava/lang/Object;)Ljava/util/List;
     636: invokespecial #195                // Method org/jpmml/evaluator/Functions$47."<init>":(Ljava/lang/String;Ljava/util/List;)V
     639: putstatic     #196                // Field FORMAT_NUMBER:Lorg/jpmml/evaluator/functions/BinaryFunction;
     642: new           #197                // class org/jpmml/evaluator/Functions$48
     645: dup
     646: ldc           #198                // String formatDatetime
     648: iconst_2
     649: anewarray     #168                // class java/lang/String
     652: dup
     653: iconst_0
     654: ldc           #169                // String input
     656: aastore
     657: dup
     658: iconst_1
     659: ldc           #185                // String pattern
     661: aastore
     662: invokestatic  #172                // Method java/util/Arrays.asList:([Ljava/lang/Object;)Ljava/util/List;
     665: invokespecial #199                // Method org/jpmml/evaluator/Functions$48."<init>":(Ljava/lang/String;Ljava/util/List;)V
     668: putstatic     #200                // Field FORMAT_DATETIME:Lorg/jpmml/evaluator/functions/BinaryFunction;
     671: new           #201                // class org/jpmml/evaluator/Functions$49
     674: dup
     675: ldc           #202                // String dateDaysSinceYear
     677: iconst_2
     678: anewarray     #168                // class java/lang/String
     681: dup
     682: iconst_0
     683: ldc           #169                // String input
     685: aastore
     686: dup
     687: iconst_1
     688: ldc           #203                // String referenceYear
     690: aastore
     691: invokestatic  #172                // Method java/util/Arrays.asList:([Ljava/lang/Object;)Ljava/util/List;
     694: invokespecial #204                // Method org/jpmml/evaluator/Functions$49."<init>":(Ljava/lang/String;Ljava/util/List;)V
     697: putstatic     #205                // Field DATE_DAYS_SINCE_YEAR:Lorg/jpmml/evaluator/functions/BinaryFunction;
     700: new           #206                // class org/jpmml/evaluator/Functions$50
     703: dup
     704: ldc           #207                // String dateSecondsSinceMidnight
     706: iconst_1
     707: anewarray     #168                // class java/lang/String
     710: dup
     711: iconst_0
     712: ldc           #169                // String input
     714: aastore
     715: invokestatic  #172                // Method java/util/Arrays.asList:([Ljava/lang/Object;)Ljava/util/List;
     718: invokespecial #208                // Method org/jpmml/evaluator/Functions$50."<init>":(Ljava/lang/String;Ljava/util/List;)V
     721: putstatic     #209                // Field DATE_SECONDS_SINCE_MIDNIGHT:Lorg/jpmml/evaluator/functions/UnaryFunction;
     724: new           #210                // class org/jpmml/evaluator/Functions$51
     727: dup
     728: ldc           #211                // String dateSecondsSinceYear
     730: iconst_2
     731: anewarray     #168                // class java/lang/String
     734: dup
     735: iconst_0
     736: ldc           #169                // String input
     738: aastore
     739: dup
     740: iconst_1
     741: ldc           #203                // String referenceYear
     743: aastore
     744: invokestatic  #172                // Method java/util/Arrays.asList:([Ljava/lang/Object;)Ljava/util/List;
     747: invokespecial #212                // Method org/jpmml/evaluator/Functions$51."<init>":(Ljava/lang/String;Ljava/util/List;)V
     750: putstatic     #213                // Field DATE_SECONDS_SINCE_YEAR:Lorg/jpmml/evaluator/functions/BinaryFunction;
     753: new           #214                // class org/jpmml/evaluator/Functions$52
     756: dup
     757: ldc           #215                // String hypot
     759: invokespecial #216                // Method org/jpmml/evaluator/Functions$52."<init>":(Ljava/lang/String;)V
     762: putstatic     #217                // Field HYPOT:Lorg/jpmml/evaluator/functions/BinaryFunction;
     765: new           #218                // class org/jpmml/evaluator/Functions$53
     768: dup
     769: ldc           #219                // String sin
     771: invokespecial #220                // Method org/jpmml/evaluator/Functions$53."<init>":(Ljava/lang/String;)V
     774: putstatic     #221                // Field SIN:Lorg/jpmml/evaluator/functions/TrigonometricFunction;
     777: new           #222                // class org/jpmml/evaluator/Functions$54
     780: dup
     781: ldc           #223                // String cos
     783: invokespecial #224                // Method org/jpmml/evaluator/Functions$54."<init>":(Ljava/lang/String;)V
     786: putstatic     #225                // Field COS:Lorg/jpmml/evaluator/functions/TrigonometricFunction;
     789: new           #226                // class org/jpmml/evaluator/Functions$55
     792: dup
     793: ldc           #227                // String tan
     795: invokespecial #228                // Method org/jpmml/evaluator/Functions$55."<init>":(Ljava/lang/String;)V
     798: putstatic     #229                // Field TAN:Lorg/jpmml/evaluator/functions/TrigonometricFunction;
     801: new           #230                // class org/jpmml/evaluator/Functions$56
     804: dup
     805: ldc           #231                // String asin
     807: invokespecial #232                // Method org/jpmml/evaluator/Functions$56."<init>":(Ljava/lang/String;)V
     810: putstatic     #233                // Field ASIN:Lorg/jpmml/evaluator/functions/TrigonometricFunction;
     813: new           #234                // class org/jpmml/evaluator/Functions$57
     816: dup
     817: ldc           #235                // String acos
     819: invokespecial #236                // Method org/jpmml/evaluator/Functions$57."<init>":(Ljava/lang/String;)V
     822: putstatic     #237                // Field ACOS:Lorg/jpmml/evaluator/functions/TrigonometricFunction;
     825: new           #238                // class org/jpmml/evaluator/Functions$58
     828: dup
     829: ldc           #239                // String atan
     831: invokespecial #240                // Method org/jpmml/evaluator/Functions$58."<init>":(Ljava/lang/String;)V
     834: putstatic     #241                // Field ATAN:Lorg/jpmml/evaluator/functions/TrigonometricFunction;
     837: new           #242                // class org/jpmml/evaluator/Functions$59
     840: dup
     841: ldc           #243                // String x-atan2
     843: invokespecial #244                // Method org/jpmml/evaluator/Functions$59."<init>":(Ljava/lang/String;)V
     846: putstatic     #245                // Field ATAN2:Lorg/jpmml/evaluator/functions/BinaryFunction;
     849: new           #246                // class org/jpmml/evaluator/Functions$60
     852: dup
     853: ldc           #247                // String sinh
     855: invokespecial #248                // Method org/jpmml/evaluator/Functions$60."<init>":(Ljava/lang/String;)V
     858: putstatic     #249                // Field SINH:Lorg/jpmml/evaluator/functions/TrigonometricFunction;
     861: new           #250                // class org/jpmml/evaluator/Functions$61
     864: dup
     865: ldc           #251                // String cosh
     867: invokespecial #252                // Method org/jpmml/evaluator/Functions$61."<init>":(Ljava/lang/String;)V
     870: putstatic     #253                // Field COSH:Lorg/jpmml/evaluator/functions/TrigonometricFunction;
     873: new           #254                // class org/jpmml/evaluator/Functions$62
     876: dup
     877: ldc           #255                // String tanh
     879: invokespecial #256                // Method org/jpmml/evaluator/Functions$62."<init>":(Ljava/lang/String;)V
     882: putstatic     #257                // Field TANH:Lorg/jpmml/evaluator/functions/TrigonometricFunction;
     885: return
}
