Compiled from "InputField.java"
public class org.jpmml.evaluator.InputField extends org.jpmml.evaluator.ModelField {
  private org.dmg.pmml.MiningField miningField;

  public org.jpmml.evaluator.InputField(org.dmg.pmml.Field<?>, org.dmg.pmml.MiningField);
    Code:
       0: aload_0
       1: aload_1
       2: invokespecial #1                  // Method org/jpmml/evaluator/ModelField."<init>":(Lorg/dmg/pmml/Field;)V
       5: aload_0
       6: aconst_null
       7: putfield      #2                  // Field miningField:Lorg/dmg/pmml/MiningField;
      10: aload_0
      11: aload_2
      12: invokestatic  #3                  // Method java/util/Objects.requireNonNull:(Ljava/lang/Object;)Ljava/lang/Object;
      15: checkcast     #4                  // class org/dmg/pmml/MiningField
      18: invokespecial #5                  // Method setMiningField:(Lorg/dmg/pmml/MiningField;)V
      21: aload_1
      22: invokevirtual #6                  // Method org/dmg/pmml/Field.getName:()Lorg/dmg/pmml/FieldName;
      25: aload_2
      26: invokevirtual #7                  // Method org/dmg/pmml/MiningField.getName:()Lorg/dmg/pmml/FieldName;
      29: invokestatic  #8                  // Method java/util/Objects.equals:(Ljava/lang/Object;Ljava/lang/Object;)Z
      32: ifne          43
      35: new           #9                  // class java/lang/IllegalArgumentException
      38: dup
      39: invokespecial #10                 // Method java/lang/IllegalArgumentException."<init>":()V
      42: athrow
      43: return

  public org.dmg.pmml.OpType getOpType();
    Code:
       0: aload_0
       1: invokevirtual #11                 // Method getField:()Lorg/dmg/pmml/Field;
       4: aload_0
       5: invokevirtual #12                 // Method getMiningField:()Lorg/dmg/pmml/MiningField;
       8: invokestatic  #13                 // Method org/jpmml/evaluator/FieldUtil.getOpType:(Lorg/dmg/pmml/Field;Lorg/dmg/pmml/MiningField;)Lorg/dmg/pmml/OpType;
      11: areturn

  public org.jpmml.evaluator.FieldValue prepare(java.lang.Object);
    Code:
       0: aload_0
       1: invokevirtual #11                 // Method getField:()Lorg/dmg/pmml/Field;
       4: aload_0
       5: invokevirtual #12                 // Method getMiningField:()Lorg/dmg/pmml/MiningField;
       8: aload_1
       9: invokestatic  #14                 // Method org/jpmml/evaluator/InputFieldUtil.prepareInputValue:(Lorg/dmg/pmml/Field;Lorg/dmg/pmml/MiningField;Ljava/lang/Object;)Lorg/jpmml/evaluator/FieldValue;
      12: areturn

  public com.google.common.collect.RangeSet<java.lang.Double> getContinuousDomain();
    Code:
       0: aload_0
       1: invokevirtual #11                 // Method getField:()Lorg/dmg/pmml/Field;
       4: astore_1
       5: aload_1
       6: instanceof    #15                 // class org/dmg/pmml/HasContinuousDomain
       9: ifeq          38
      12: aload_1
      13: checkcast     #15                 // class org/dmg/pmml/HasContinuousDomain
      16: checkcast     #16                 // class org/dmg/pmml/Field
      19: invokestatic  #17                 // Method org/jpmml/evaluator/FieldUtil.getValidRanges:(Lorg/dmg/pmml/Field;)Lcom/google/common/collect/RangeSet;
      22: astore_2
      23: aload_2
      24: ifnull        38
      27: aload_2
      28: invokeinterface #18,  1           // InterfaceMethod com/google/common/collect/RangeSet.isEmpty:()Z
      33: ifne          38
      36: aload_2
      37: areturn
      38: aconst_null
      39: areturn

  public java.util.List<?> getDiscreteDomain();
    Code:
       0: aload_0
       1: invokevirtual #11                 // Method getField:()Lorg/dmg/pmml/Field;
       4: astore_1
       5: aload_1
       6: instanceof    #19                 // class org/dmg/pmml/HasDiscreteDomain
       9: ifeq          38
      12: aload_1
      13: checkcast     #19                 // class org/dmg/pmml/HasDiscreteDomain
      16: checkcast     #16                 // class org/dmg/pmml/Field
      19: invokestatic  #20                 // Method org/jpmml/evaluator/FieldUtil.getValidValues:(Lorg/dmg/pmml/Field;)Ljava/util/List;
      22: astore_2
      23: aload_2
      24: ifnull        38
      27: aload_2
      28: invokeinterface #21,  1           // InterfaceMethod java/util/List.isEmpty:()Z
      33: ifne          38
      36: aload_2
      37: areturn
      38: aconst_null
      39: areturn

  public org.dmg.pmml.MiningField getMiningField();
    Code:
       0: aload_0
       1: getfield      #2                  // Field miningField:Lorg/dmg/pmml/MiningField;
       4: areturn

  private void setMiningField(org.dmg.pmml.MiningField);
    Code:
       0: aload_0
       1: aload_1
       2: putfield      #2                  // Field miningField:Lorg/dmg/pmml/MiningField;
       5: return
}
