Compiled from "InputFieldUtil.java"
final class org.jpmml.evaluator.InputFieldUtil$1 implements org.jpmml.evaluator.InputTypeInfo {
  final org.dmg.pmml.Field val$field;

  final org.dmg.pmml.MiningField val$miningField;

  org.jpmml.evaluator.InputFieldUtil$1(org.dmg.pmml.Field, org.dmg.pmml.MiningField);
    Code:
       0: aload_0
       1: aload_1
       2: putfield      #1                  // Field val$field:Lorg/dmg/pmml/Field;
       5: aload_0
       6: aload_2
       7: putfield      #2                  // Field val$miningField:Lorg/dmg/pmml/MiningField;
      10: aload_0
      11: invokespecial #3                  // Method java/lang/Object."<init>":()V
      14: return

  public org.dmg.pmml.Field<?> getField();
    Code:
       0: aload_0
       1: getfield      #1                  // Field val$field:Lorg/dmg/pmml/Field;
       4: areturn

  public org.dmg.pmml.MiningField getMiningField();
    Code:
       0: aload_0
       1: getfield      #2                  // Field val$miningField:Lorg/dmg/pmml/MiningField;
       4: areturn

  public org.dmg.pmml.DataType getDataType();
    Code:
       0: aload_0
       1: getfield      #1                  // Field val$field:Lorg/dmg/pmml/Field;
       4: invokestatic  #4                  // Method org/jpmml/evaluator/FieldUtil.getDataType:(Lorg/dmg/pmml/Field;)Lorg/dmg/pmml/DataType;
       7: astore_1
       8: aload_1
       9: ifnonnull     55
      12: new           #5                  // class org/jpmml/evaluator/MissingAttributeException
      15: dup
      16: new           #6                  // class java/lang/StringBuilder
      19: dup
      20: invokespecial #7                  // Method java/lang/StringBuilder."<init>":()V
      23: aload_0
      24: getfield      #1                  // Field val$field:Lorg/dmg/pmml/Field;
      27: invokevirtual #8                  // Method java/lang/Object.getClass:()Ljava/lang/Class;
      30: invokestatic  #9                  // Method org/jpmml/model/XPathUtil.formatElement:(Ljava/lang/Class;)Ljava/lang/String;
      33: invokevirtual #10                 // Method java/lang/StringBuilder.append:(Ljava/lang/String;)Ljava/lang/StringBuilder;
      36: ldc           #11                 // String @dataType
      38: invokevirtual #10                 // Method java/lang/StringBuilder.append:(Ljava/lang/String;)Ljava/lang/StringBuilder;
      41: invokevirtual #12                 // Method java/lang/StringBuilder.toString:()Ljava/lang/String;
      44: invokestatic  #13                 // Method org/jpmml/evaluator/MissingAttributeException.formatMessage:(Ljava/lang/String;)Ljava/lang/String;
      47: aload_0
      48: getfield      #1                  // Field val$field:Lorg/dmg/pmml/Field;
      51: invokespecial #14                 // Method org/jpmml/evaluator/MissingAttributeException."<init>":(Ljava/lang/String;Lorg/dmg/pmml/PMMLObject;)V
      54: athrow
      55: aload_1
      56: areturn

  public org.dmg.pmml.OpType getOpType();
    Code:
       0: aload_0
       1: getfield      #1                  // Field val$field:Lorg/dmg/pmml/Field;
       4: aload_0
       5: getfield      #2                  // Field val$miningField:Lorg/dmg/pmml/MiningField;
       8: invokestatic  #15                 // Method org/jpmml/evaluator/FieldUtil.getOpType:(Lorg/dmg/pmml/Field;Lorg/dmg/pmml/MiningField;)Lorg/dmg/pmml/OpType;
      11: astore_1
      12: aload_1
      13: ifnonnull     59
      16: new           #5                  // class org/jpmml/evaluator/MissingAttributeException
      19: dup
      20: new           #6                  // class java/lang/StringBuilder
      23: dup
      24: invokespecial #7                  // Method java/lang/StringBuilder."<init>":()V
      27: aload_0
      28: getfield      #1                  // Field val$field:Lorg/dmg/pmml/Field;
      31: invokevirtual #8                  // Method java/lang/Object.getClass:()Ljava/lang/Class;
      34: invokestatic  #9                  // Method org/jpmml/model/XPathUtil.formatElement:(Ljava/lang/Class;)Ljava/lang/String;
      37: invokevirtual #10                 // Method java/lang/StringBuilder.append:(Ljava/lang/String;)Ljava/lang/StringBuilder;
      40: ldc           #16                 // String @optype
      42: invokevirtual #10                 // Method java/lang/StringBuilder.append:(Ljava/lang/String;)Ljava/lang/StringBuilder;
      45: invokevirtual #12                 // Method java/lang/StringBuilder.toString:()Ljava/lang/String;
      48: invokestatic  #13                 // Method org/jpmml/evaluator/MissingAttributeException.formatMessage:(Ljava/lang/String;)Ljava/lang/String;
      51: aload_0
      52: getfield      #1                  // Field val$field:Lorg/dmg/pmml/Field;
      55: invokespecial #14                 // Method org/jpmml/evaluator/MissingAttributeException."<init>":(Ljava/lang/String;Lorg/dmg/pmml/PMMLObject;)V
      58: athrow
      59: aload_1
      60: areturn

  public java.util.List<?> getOrdering();
    Code:
       0: aconst_null
       1: astore_1
       2: aload_0
       3: getfield      #1                  // Field val$field:Lorg/dmg/pmml/Field;
       6: instanceof    #17                 // class org/dmg/pmml/HasDiscreteDomain
       9: ifeq          26
      12: aload_0
      13: getfield      #1                  // Field val$field:Lorg/dmg/pmml/Field;
      16: checkcast     #17                 // class org/dmg/pmml/HasDiscreteDomain
      19: checkcast     #18                 // class org/dmg/pmml/Field
      22: invokestatic  #19                 // Method org/jpmml/evaluator/FieldUtil.getValidValues:(Lorg/dmg/pmml/Field;)Ljava/util/List;
      25: astore_1
      26: aload_1
      27: areturn
}
