Compiled from "ModelManagerFactory.java"
public abstract class org.jpmml.evaluator.ModelManagerFactory<S extends org.jpmml.evaluator.ModelManager<?>> {
  private java.lang.Class<S> serviceClazz;

  private com.google.common.collect.ListMultimap<java.lang.Class<? extends org.dmg.pmml.Model>, java.lang.Class<? extends S>> serviceProviderClazzes;

  protected org.jpmml.evaluator.ModelManagerFactory();
    Code:
       0: aload_0
       1: invokespecial #1                  // Method java/lang/Object."<init>":()V
       4: aload_0
       5: aconst_null
       6: putfield      #2                  // Field serviceClazz:Ljava/lang/Class;
       9: aload_0
      10: aconst_null
      11: putfield      #3                  // Field serviceProviderClazzes:Lcom/google/common/collect/ListMultimap;
      14: return

  protected org.jpmml.evaluator.ModelManagerFactory(java.lang.Class<S>);
    Code:
       0: aload_0
       1: invokespecial #1                  // Method java/lang/Object."<init>":()V
       4: aload_0
       5: aconst_null
       6: putfield      #2                  // Field serviceClazz:Ljava/lang/Class;
       9: aload_0
      10: aconst_null
      11: putfield      #3                  // Field serviceProviderClazzes:Lcom/google/common/collect/ListMultimap;
      14: aload_0
      15: aload_1
      16: invokespecial #4                  // Method setServiceClass:(Ljava/lang/Class;)V
      19: return

  public S newModelManager(org.dmg.pmml.PMML, org.dmg.pmml.Model);
    Code:
       0: aload_1
       1: invokestatic  #5                  // Method java/util/Objects.requireNonNull:(Ljava/lang/Object;)Ljava/lang/Object;
       4: pop
       5: aload_2
       6: invokestatic  #5                  // Method java/util/Objects.requireNonNull:(Ljava/lang/Object;)Ljava/lang/Object;
       9: pop
      10: aload_0
      11: aload_2
      12: invokevirtual #6                  // Method java/lang/Object.getClass:()Ljava/lang/Class;
      15: invokevirtual #7                  // Method getServiceProviderClasses:(Ljava/lang/Class;)Ljava/util/List;
      18: astore_3
      19: aload_3
      20: invokeinterface #8,  1            // InterfaceMethod java/util/List.iterator:()Ljava/util/Iterator;
      25: astore        4
      27: aload         4
      29: invokeinterface #9,  1            // InterfaceMethod java/util/Iterator.hasNext:()Z
      34: ifeq          100
      37: aload         4
      39: invokeinterface #10,  1           // InterfaceMethod java/util/Iterator.next:()Ljava/lang/Object;
      44: checkcast     #11                 // class java/lang/Class
      47: astore        5
      49: aload         5
      51: invokestatic  #12                 // Method findConstructor:(Ljava/lang/Class;)Ljava/lang/reflect/Constructor;
      54: astore        6
      56: aload         6
      58: iconst_2
      59: anewarray     #13                 // class java/lang/Object
      62: dup
      63: iconst_0
      64: aload_1
      65: aastore
      66: dup
      67: iconst_1
      68: aload_2
      69: aastore
      70: invokevirtual #14                 // Method java/lang/reflect/Constructor.newInstance:([Ljava/lang/Object;)Ljava/lang/Object;
      73: checkcast     #15                 // class org/jpmml/evaluator/ModelManager
      76: areturn
      77: astore        7
      79: aload         7
      81: invokevirtual #17                 // Method java/lang/reflect/InvocationTargetException.getCause:()Ljava/lang/Throwable;
      84: astore        8
      86: aload         8
      88: instanceof    #18                 // class org/jpmml/evaluator/UnsupportedMarkupException
      91: ifeq          97
      94: goto          27
      97: aload         7
      99: athrow
     100: goto          113
     103: astore_3
     104: new           #21                 // class java/lang/IllegalArgumentException
     107: dup
     108: aload_3
     109: invokespecial #22                 // Method java/lang/IllegalArgumentException."<init>":(Ljava/lang/Throwable;)V
     112: athrow
     113: new           #23                 // class org/jpmml/evaluator/UnsupportedElementException
     116: dup
     117: aload_2
     118: invokespecial #24                 // Method org/jpmml/evaluator/UnsupportedElementException."<init>":(Lorg/dmg/pmml/PMMLObject;)V
     121: athrow
    Exception table:
       from    to  target type
          56    76    77   Class java/lang/reflect/InvocationTargetException
          10    76   103   Class java/lang/ReflectiveOperationException
          10    76   103   Class java/io/IOException
          77   100   103   Class java/lang/ReflectiveOperationException
          77   100   103   Class java/io/IOException

  public java.util.List<java.lang.Class<? extends S>> getServiceProviderClasses(java.lang.Class<? extends org.dmg.pmml.Model>) throws java.lang.ClassNotFoundException, java.io.IOException;
    Code:
       0: aload_0
       1: invokevirtual #25                 // Method getServiceProviderClasses:()Lcom/google/common/collect/ListMultimap;
       4: astore_2
       5: aload_1
       6: ifnull        62
       9: aload_2
      10: aload_1
      11: invokeinterface #26,  2           // InterfaceMethod com/google/common/collect/ListMultimap.get:(Ljava/lang/Object;)Ljava/util/List;
      16: astore_3
      17: aload_3
      18: ifnull        32
      21: aload_3
      22: invokeinterface #27,  1           // InterfaceMethod java/util/List.isEmpty:()Z
      27: ifne          32
      30: aload_3
      31: areturn
      32: aload_1
      33: invokevirtual #28                 // Method java/lang/Class.getSuperclass:()Ljava/lang/Class;
      36: astore        4
      38: ldc           #29                 // class org/dmg/pmml/Model
      40: aload         4
      42: invokevirtual #30                 // Method java/lang/Class.isAssignableFrom:(Ljava/lang/Class;)Z
      45: ifne          51
      48: goto          62
      51: aload         4
      53: ldc           #29                 // class org/dmg/pmml/Model
      55: invokevirtual #31                 // Method java/lang/Class.asSubclass:(Ljava/lang/Class;)Ljava/lang/Class;
      58: astore_1
      59: goto          5
      62: invokestatic  #32                 // Method java/util/Collections.emptyList:()Ljava/util/List;
      65: areturn

  public java.lang.Class<S> getServiceClass();
    Code:
       0: aload_0
       1: getfield      #2                  // Field serviceClazz:Ljava/lang/Class;
       4: areturn

  private void setServiceClass(java.lang.Class<S>);
    Code:
       0: aload_0
       1: aload_1
       2: putfield      #2                  // Field serviceClazz:Ljava/lang/Class;
       5: return

  public com.google.common.collect.ListMultimap<java.lang.Class<? extends org.dmg.pmml.Model>, java.lang.Class<? extends S>> getServiceProviderClasses() throws java.lang.ClassNotFoundException, java.io.IOException;
    Code:
       0: aload_0
       1: getfield      #3                  // Field serviceProviderClazzes:Lcom/google/common/collect/ListMultimap;
       4: ifnonnull     20
       7: aload_0
       8: invokevirtual #33                 // Method getServiceClass:()Ljava/lang/Class;
      11: astore_1
      12: aload_0
      13: aload_1
      14: invokestatic  #34                 // Method loadServiceProviderClasses:(Ljava/lang/Class;)Lcom/google/common/collect/ListMultimap;
      17: putfield      #3                  // Field serviceProviderClazzes:Lcom/google/common/collect/ListMultimap;
      20: aload_0
      21: getfield      #3                  // Field serviceProviderClazzes:Lcom/google/common/collect/ListMultimap;
      24: areturn

  private static <S extends org.jpmml.evaluator.ModelManager<?>> com.google.common.collect.ListMultimap<java.lang.Class<? extends org.dmg.pmml.Model>, java.lang.Class<? extends S>> loadServiceProviderClasses(java.lang.Class<S>) throws java.lang.ClassNotFoundException, java.io.IOException;
    Code:
       0: invokestatic  #35                 // Method java/lang/Thread.currentThread:()Ljava/lang/Thread;
       3: astore_1
       4: aload_1
       5: invokevirtual #36                 // Method java/lang/Thread.getContextClassLoader:()Ljava/lang/ClassLoader;
       8: astore_2
       9: aload_2
      10: ifnonnull     17
      13: invokestatic  #37                 // Method java/lang/ClassLoader.getSystemClassLoader:()Ljava/lang/ClassLoader;
      16: astore_2
      17: invokestatic  #38                 // Method com/google/common/collect/ArrayListMultimap.create:()Lcom/google/common/collect/ArrayListMultimap;
      20: astore_3
      21: aload_2
      22: new           #39                 // class java/lang/StringBuilder
      25: dup
      26: invokespecial #40                 // Method java/lang/StringBuilder."<init>":()V
      29: ldc           #41                 // String META-INF/services/
      31: invokevirtual #42                 // Method java/lang/StringBuilder.append:(Ljava/lang/String;)Ljava/lang/StringBuilder;
      34: aload_0
      35: invokevirtual #43                 // Method java/lang/Class.getName:()Ljava/lang/String;
      38: invokevirtual #42                 // Method java/lang/StringBuilder.append:(Ljava/lang/String;)Ljava/lang/StringBuilder;
      41: invokevirtual #44                 // Method java/lang/StringBuilder.toString:()Ljava/lang/String;
      44: invokevirtual #45                 // Method java/lang/ClassLoader.getResources:(Ljava/lang/String;)Ljava/util/Enumeration;
      47: astore        4
      49: aload         4
      51: invokeinterface #46,  1           // InterfaceMethod java/util/Enumeration.hasMoreElements:()Z
      56: ifeq          233
      59: aload         4
      61: invokeinterface #47,  1           // InterfaceMethod java/util/Enumeration.nextElement:()Ljava/lang/Object;
      66: checkcast     #48                 // class java/net/URL
      69: astore        5
      71: aload         5
      73: invokevirtual #49                 // Method java/net/URL.openStream:()Ljava/io/InputStream;
      76: astore        6
      78: aconst_null
      79: astore        7
      81: aload         6
      83: aload_2
      84: aload_0
      85: invokestatic  #50                 // Method loadServiceProviderClasses:(Ljava/io/InputStream;Ljava/lang/ClassLoader;Ljava/lang/Class;)Ljava/util/List;
      88: astore        8
      90: aload         8
      92: invokeinterface #8,  1            // InterfaceMethod java/util/List.iterator:()Ljava/util/Iterator;
      97: astore        9
      99: aload         9
     101: invokeinterface #9,  1            // InterfaceMethod java/util/Iterator.hasNext:()Z
     106: ifeq          143
     109: aload         9
     111: invokeinterface #10,  1           // InterfaceMethod java/util/Iterator.next:()Ljava/lang/Object;
     116: checkcast     #11                 // class java/lang/Class
     119: astore        10
     121: aload_0
     122: aload         10
     124: invokestatic  #51                 // Method findModelParameter:(Ljava/lang/Class;Ljava/lang/Class;)Ljava/lang/Class;
     127: astore        11
     129: aload_3
     130: aload         11
     132: aload         10
     134: invokeinterface #52,  3           // InterfaceMethod com/google/common/collect/ListMultimap.put:(Ljava/lang/Object;Ljava/lang/Object;)Z
     139: pop
     140: goto          99
     143: aload         6
     145: ifnull        230
     148: aload         7
     150: ifnull        173
     153: aload         6
     155: invokevirtual #53                 // Method java/io/InputStream.close:()V
     158: goto          230
     161: astore        8
     163: aload         7
     165: aload         8
     167: invokevirtual #55                 // Method java/lang/Throwable.addSuppressed:(Ljava/lang/Throwable;)V
     170: goto          230
     173: aload         6
     175: invokevirtual #53                 // Method java/io/InputStream.close:()V
     178: goto          230
     181: astore        8
     183: aload         8
     185: astore        7
     187: aload         8
     189: athrow
     190: astore        12
     192: aload         6
     194: ifnull        227
     197: aload         7
     199: ifnull        222
     202: aload         6
     204: invokevirtual #53                 // Method java/io/InputStream.close:()V
     207: goto          227
     210: astore        13
     212: aload         7
     214: aload         13
     216: invokevirtual #55                 // Method java/lang/Throwable.addSuppressed:(Ljava/lang/Throwable;)V
     219: goto          227
     222: aload         6
     224: invokevirtual #53                 // Method java/io/InputStream.close:()V
     227: aload         12
     229: athrow
     230: goto          49
     233: aload_3
     234: areturn
    Exception table:
       from    to  target type
         153   158   161   Class java/lang/Throwable
          81   143   181   Class java/lang/Throwable
          81   143   190   any
         202   207   210   Class java/lang/Throwable
         181   192   190   any

  private static <S> java.util.List<java.lang.Class<? extends S>> loadServiceProviderClasses(java.io.InputStream, java.lang.ClassLoader, java.lang.Class<S>) throws java.lang.ClassNotFoundException, java.io.IOException;
    Code:
       0: new           #56                 // class java/util/ArrayList
       3: dup
       4: invokespecial #57                 // Method java/util/ArrayList."<init>":()V
       7: astore_3
       8: new           #58                 // class java/io/BufferedReader
      11: dup
      12: new           #59                 // class java/io/InputStreamReader
      15: dup
      16: aload_0
      17: ldc           #60                 // String UTF-8
      19: invokespecial #61                 // Method java/io/InputStreamReader."<init>":(Ljava/io/InputStream;Ljava/lang/String;)V
      22: sipush        1024
      25: invokespecial #62                 // Method java/io/BufferedReader."<init>":(Ljava/io/Reader;I)V
      28: astore        4
      30: aload         4
      32: invokevirtual #63                 // Method java/io/BufferedReader.readLine:()Ljava/lang/String;
      35: astore        5
      37: aload         5
      39: ifnonnull     45
      42: goto          128
      45: aload         5
      47: bipush        35
      49: invokevirtual #64                 // Method java/lang/String.indexOf:(I)I
      52: istore        6
      54: iload         6
      56: iconst_m1
      57: if_icmple     70
      60: aload         5
      62: iconst_0
      63: iload         6
      65: invokevirtual #65                 // Method java/lang/String.substring:(II)Ljava/lang/String;
      68: astore        5
      70: aload         5
      72: invokevirtual #66                 // Method java/lang/String.trim:()Ljava/lang/String;
      75: astore        5
      77: aload         5
      79: invokevirtual #67                 // Method java/lang/String.isEmpty:()Z
      82: ifeq          88
      85: goto          30
      88: aload         5
      90: iconst_0
      91: aload_1
      92: invokestatic  #68                 // Method java/lang/Class.forName:(Ljava/lang/String;ZLjava/lang/ClassLoader;)Ljava/lang/Class;
      95: astore        7
      97: aload_2
      98: aload         7
     100: invokevirtual #30                 // Method java/lang/Class.isAssignableFrom:(Ljava/lang/Class;)Z
     103: ifne          116
     106: new           #21                 // class java/lang/IllegalArgumentException
     109: dup
     110: aload         5
     112: invokespecial #69                 // Method java/lang/IllegalArgumentException."<init>":(Ljava/lang/String;)V
     115: athrow
     116: aload_3
     117: aload         7
     119: invokeinterface #70,  2           // InterfaceMethod java/util/List.add:(Ljava/lang/Object;)Z
     124: pop
     125: goto          30
     128: aload         4
     130: invokevirtual #71                 // Method java/io/BufferedReader.close:()V
     133: aload_3
     134: areturn

  private static java.lang.reflect.Constructor<?> findConstructor(java.lang.Class<?>) throws java.lang.NoSuchMethodException;
    Code:
       0: aload_0
       1: invokevirtual #72                 // Method java/lang/Class.getConstructors:()[Ljava/lang/reflect/Constructor;
       4: astore_1
       5: aload_1
       6: astore_2
       7: aload_2
       8: arraylength
       9: istore_3
      10: iconst_0
      11: istore        4
      13: iload         4
      15: iload_3
      16: if_icmpge     89
      19: aload_2
      20: iload         4
      22: aaload
      23: astore        5
      25: aload         5
      27: invokevirtual #73                 // Method java/lang/reflect/Constructor.getParameters:()[Ljava/lang/reflect/Parameter;
      30: astore        6
      32: aload         6
      34: arraylength
      35: iconst_2
      36: if_icmpeq     42
      39: goto          83
      42: aload         6
      44: iconst_0
      45: aaload
      46: astore        7
      48: aload         6
      50: iconst_1
      51: aaload
      52: astore        8
      54: ldc           #74                 // class org/dmg/pmml/PMML
      56: aload         7
      58: invokevirtual #75                 // Method java/lang/reflect/Parameter.getType:()Ljava/lang/Class;
      61: invokevirtual #30                 // Method java/lang/Class.isAssignableFrom:(Ljava/lang/Class;)Z
      64: ifeq          83
      67: ldc           #29                 // class org/dmg/pmml/Model
      69: aload         8
      71: invokevirtual #75                 // Method java/lang/reflect/Parameter.getType:()Ljava/lang/Class;
      74: invokevirtual #30                 // Method java/lang/Class.isAssignableFrom:(Ljava/lang/Class;)Z
      77: ifeq          83
      80: aload         5
      82: areturn
      83: iinc          4, 1
      86: goto          13
      89: new           #76                 // class java/lang/NoSuchMethodException
      92: dup
      93: invokespecial #77                 // Method java/lang/NoSuchMethodException."<init>":()V
      96: athrow

  private static java.lang.Class<? extends org.dmg.pmml.Model> findModelParameter(java.lang.Class<?>, java.lang.Class<?>);
    Code:
       0: aload_1
       1: astore_2
       2: aload_2
       3: ifnull        78
       6: aload_2
       7: invokevirtual #28                 // Method java/lang/Class.getSuperclass:()Ljava/lang/Class;
      10: astore_3
      11: aload_0
      12: aload_3
      13: invokevirtual #78                 // Method java/lang/Object.equals:(Ljava/lang/Object;)Z
      16: ifeq          73
      19: aload_2
      20: invokevirtual #79                 // Method java/lang/Class.getGenericSuperclass:()Ljava/lang/reflect/Type;
      23: checkcast     #80                 // class java/lang/reflect/ParameterizedType
      26: astore        4
      28: aload         4
      30: invokeinterface #81,  1           // InterfaceMethod java/lang/reflect/ParameterizedType.getActualTypeArguments:()[Ljava/lang/reflect/Type;
      35: astore        5
      37: aload         5
      39: arraylength
      40: iconst_1
      41: if_icmpeq     56
      44: new           #21                 // class java/lang/IllegalArgumentException
      47: dup
      48: aload_2
      49: invokevirtual #43                 // Method java/lang/Class.getName:()Ljava/lang/String;
      52: invokespecial #69                 // Method java/lang/IllegalArgumentException."<init>":(Ljava/lang/String;)V
      55: athrow
      56: aload         5
      58: iconst_0
      59: aaload
      60: checkcast     #11                 // class java/lang/Class
      63: astore        6
      65: aload         6
      67: ldc           #29                 // class org/dmg/pmml/Model
      69: invokevirtual #31                 // Method java/lang/Class.asSubclass:(Ljava/lang/Class;)Ljava/lang/Class;
      72: areturn
      73: aload_3
      74: astore_2
      75: goto          2
      78: new           #21                 // class java/lang/IllegalArgumentException
      81: dup
      82: aload_1
      83: invokevirtual #43                 // Method java/lang/Class.getName:()Ljava/lang/String;
      86: invokespecial #69                 // Method java/lang/IllegalArgumentException."<init>":(Ljava/lang/String;)V
      89: athrow
}
