Compiled from "NumberUtil.java"
public class org.jpmml.evaluator.NumberUtil {
  private org.jpmml.evaluator.NumberUtil();
    Code:
       0: aload_0
       1: invokespecial #1                  // Method java/lang/Object."<init>":()V
       4: return

  public static java.lang.Double asDouble(java.lang.Number);
    Code:
       0: aload_0
       1: ifnonnull     6
       4: aconst_null
       5: areturn
       6: aload_0
       7: instanceof    #2                  // class java/lang/Double
      10: ifeq          18
      13: aload_0
      14: checkcast     #2                  // class java/lang/Double
      17: areturn
      18: aload_0
      19: invokevirtual #3                  // Method java/lang/Number.doubleValue:()D
      22: invokestatic  #4                  // Method java/lang/Double.valueOf:(D)Ljava/lang/Double;
      25: areturn

  public static int compare(java.lang.Number, java.lang.Number);
    Code:
       0: aload_0
       1: invokevirtual #3                  // Method java/lang/Number.doubleValue:()D
       4: aload_1
       5: invokevirtual #3                  // Method java/lang/Number.doubleValue:()D
       8: invokestatic  #5                  // Method java/lang/Double.compare:(DD)I
      11: ireturn
}
