Compiled from "AbstractJdbc2ResultSet.java"
class org.postgresql.jdbc2.AbstractJdbc2ResultSet$PrimaryKey {
  int index;

  java.lang.String name;

  final org.postgresql.jdbc2.AbstractJdbc2ResultSet this$0;

  org.postgresql.jdbc2.AbstractJdbc2ResultSet$PrimaryKey(org.postgresql.jdbc2.AbstractJdbc2ResultSet, int, java.lang.String);
    Code:
       0: aload_0
       1: aload_1
       2: putfield      #1                  // Field this$0:Lorg/postgresql/jdbc2/AbstractJdbc2ResultSet;
       5: aload_0
       6: invokespecial #2                  // Method java/lang/Object."<init>":()V
       9: aload_0
      10: iload_2
      11: putfield      #3                  // Field index:I
      14: aload_0
      15: aload_3
      16: putfield      #4                  // Field name:Ljava/lang/String;
      19: return

  java.lang.Object getValue() throws java.sql.SQLException;
    Code:
       0: aload_0
       1: getfield      #1                  // Field this$0:Lorg/postgresql/jdbc2/AbstractJdbc2ResultSet;
       4: aload_0
       5: getfield      #3                  // Field index:I
       8: invokevirtual #5                  // Method org/postgresql/jdbc2/AbstractJdbc2ResultSet.getObject:(I)Ljava/lang/Object;
      11: areturn
}
