Compiled from "AbstractJdbc2ResultSet.java"
public class org.postgresql.jdbc2.AbstractJdbc2ResultSet$CursorResultHandler implements org.postgresql.core.ResultHandler {
  private java.sql.SQLException error;

  final org.postgresql.jdbc2.AbstractJdbc2ResultSet this$0;

  public org.postgresql.jdbc2.AbstractJdbc2ResultSet$CursorResultHandler(org.postgresql.jdbc2.AbstractJdbc2ResultSet);
    Code:
       0: aload_0
       1: aload_1
       2: putfield      #1                  // Field this$0:Lorg/postgresql/jdbc2/AbstractJdbc2ResultSet;
       5: aload_0
       6: invokespecial #2                  // Method java/lang/Object."<init>":()V
       9: return

  public void handleResultRows(org.postgresql.core.Query, org.postgresql.core.Field[], java.util.List, org.postgresql.core.ResultCursor);
    Code:
       0: aload_0
       1: getfield      #1                  // Field this$0:Lorg/postgresql/jdbc2/AbstractJdbc2ResultSet;
       4: aload_3
       5: putfield      #3                  // Field org/postgresql/jdbc2/AbstractJdbc2ResultSet.rows:Ljava/util/List;
       8: aload_0
       9: getfield      #1                  // Field this$0:Lorg/postgresql/jdbc2/AbstractJdbc2ResultSet;
      12: aload         4
      14: putfield      #4                  // Field org/postgresql/jdbc2/AbstractJdbc2ResultSet.cursor:Lorg/postgresql/core/ResultCursor;
      17: return

  public void handleCommandStatus(java.lang.String, int, long);
    Code:
       0: aload_0
       1: new           #5                  // class org/postgresql/util/PSQLException
       4: dup
       5: ldc           #6                  // String Unexpected command status: {0}.
       7: aload_1
       8: invokestatic  #7                  // Method org/postgresql/util/GT.tr:(Ljava/lang/String;Ljava/lang/Object;)Ljava/lang/String;
      11: getstatic     #8                  // Field org/postgresql/util/PSQLState.PROTOCOL_VIOLATION:Lorg/postgresql/util/PSQLState;
      14: invokespecial #9                  // Method org/postgresql/util/PSQLException."<init>":(Ljava/lang/String;Lorg/postgresql/util/PSQLState;)V
      17: invokevirtual #10                 // Method handleError:(Ljava/sql/SQLException;)V
      20: return

  public void handleWarning(java.sql.SQLWarning);
    Code:
       0: aload_0
       1: getfield      #1                  // Field this$0:Lorg/postgresql/jdbc2/AbstractJdbc2ResultSet;
       4: aload_1
       5: invokevirtual #11                 // Method org/postgresql/jdbc2/AbstractJdbc2ResultSet.addWarning:(Ljava/sql/SQLWarning;)V
       8: return

  public void handleError(java.sql.SQLException);
    Code:
       0: aload_0
       1: getfield      #12                 // Field error:Ljava/sql/SQLException;
       4: ifnonnull     15
       7: aload_0
       8: aload_1
       9: putfield      #12                 // Field error:Ljava/sql/SQLException;
      12: goto          23
      15: aload_0
      16: getfield      #12                 // Field error:Ljava/sql/SQLException;
      19: aload_1
      20: invokevirtual #13                 // Method java/sql/SQLException.setNextException:(Ljava/sql/SQLException;)V
      23: return

  public void handleCompletion() throws java.sql.SQLException;
    Code:
       0: aload_0
       1: getfield      #12                 // Field error:Ljava/sql/SQLException;
       4: ifnull        12
       7: aload_0
       8: getfield      #12                 // Field error:Ljava/sql/SQLException;
      11: athrow
      12: return
}
