Compiled from "SystemPropertyUtils.java"
public abstract class org.springframework.util.SystemPropertyUtils {
  public static final java.lang.String PLACEHOLDER_PREFIX;

  public static final java.lang.String PLACEHOLDER_SUFFIX;

  public static final java.lang.String VALUE_SEPARATOR;

  private static final org.springframework.util.PropertyPlaceholderHelper strictHelper;

  private static final org.springframework.util.PropertyPlaceholderHelper nonStrictHelper;

  public org.springframework.util.SystemPropertyUtils();
    Code:
       0: aload_0
       1: invokespecial #1                  // Method java/lang/Object."<init>":()V
       4: return

  public static java.lang.String resolvePlaceholders(java.lang.String);
    Code:
       0: aload_0
       1: iconst_0
       2: invokestatic  #2                  // Method resolvePlaceholders:(Ljava/lang/String;Z)Ljava/lang/String;
       5: areturn

  public static java.lang.String resolvePlaceholders(java.lang.String, boolean);
    Code:
       0: iload_1
       1: ifeq          10
       4: getstatic     #3                  // Field nonStrictHelper:Lorg/springframework/util/PropertyPlaceholderHelper;
       7: goto          13
      10: getstatic     #4                  // Field strictHelper:Lorg/springframework/util/PropertyPlaceholderHelper;
      13: astore_2
      14: aload_2
      15: aload_0
      16: new           #5                  // class org/springframework/util/SystemPropertyUtils$SystemPropertyPlaceholderResolver
      19: dup
      20: aload_0
      21: invokespecial #6                  // Method org/springframework/util/SystemPropertyUtils$SystemPropertyPlaceholderResolver."<init>":(Ljava/lang/String;)V
      24: invokevirtual #7                  // Method org/springframework/util/PropertyPlaceholderHelper.replacePlaceholders:(Ljava/lang/String;Lorg/springframework/util/PropertyPlaceholderHelper$PlaceholderResolver;)Ljava/lang/String;
      27: areturn

  static {};
    Code:
       0: new           #8                  // class org/springframework/util/PropertyPlaceholderHelper
       3: dup
       4: ldc           #10                 // String ${
       6: ldc           #11                 // String }
       8: ldc           #12                 // String :
      10: iconst_0
      11: invokespecial #13                 // Method org/springframework/util/PropertyPlaceholderHelper."<init>":(Ljava/lang/String;Ljava/lang/String;Ljava/lang/String;Z)V
      14: putstatic     #4                  // Field strictHelper:Lorg/springframework/util/PropertyPlaceholderHelper;
      17: new           #8                  // class org/springframework/util/PropertyPlaceholderHelper
      20: dup
      21: ldc           #10                 // String ${
      23: ldc           #11                 // String }
      25: ldc           #12                 // String :
      27: iconst_1
      28: invokespecial #13                 // Method org/springframework/util/PropertyPlaceholderHelper."<init>":(Ljava/lang/String;Ljava/lang/String;Ljava/lang/String;Z)V
      31: putstatic     #3                  // Field nonStrictHelper:Lorg/springframework/util/PropertyPlaceholderHelper;
      34: return
}
