Compiled from "Continue100Interceptor.java"
class org.asynchttpclient.netty.handler.intercept.Continue100Interceptor$1 extends org.asynchttpclient.netty.OnLastHttpContentCallback {
  final io.netty.channel.Channel val$channel;

  final org.asynchttpclient.netty.handler.intercept.Continue100Interceptor this$0;

  org.asynchttpclient.netty.handler.intercept.Continue100Interceptor$1(org.asynchttpclient.netty.handler.intercept.Continue100Interceptor, org.asynchttpclient.netty.NettyResponseFuture, io.netty.channel.Channel);
    Code:
       0: aload_0
       1: aload_1
       2: putfield      #1                  // Field this$0:Lorg/asynchttpclient/netty/handler/intercept/Continue100Interceptor;
       5: aload_0
       6: aload_3
       7: putfield      #2                  // Field val$channel:Lio/netty/channel/Channel;
      10: aload_0
      11: aload_2
      12: invokespecial #3                  // Method org/asynchttpclient/netty/OnLastHttpContentCallback."<init>":(Lorg/asynchttpclient/netty/NettyResponseFuture;)V
      15: return

  public void call();
    Code:
       0: aload_0
       1: getfield      #2                  // Field val$channel:Lio/netty/channel/Channel;
       4: aload_0
       5: getfield      #4                  // Field future:Lorg/asynchttpclient/netty/NettyResponseFuture;
       8: invokestatic  #5                  // Method org/asynchttpclient/netty/channel/Channels.setAttribute:(Lio/netty/channel/Channel;Ljava/lang/Object;)V
      11: aload_0
      12: getfield      #1                  // Field this$0:Lorg/asynchttpclient/netty/handler/intercept/Continue100Interceptor;
      15: invokestatic  #6                  // Method org/asynchttpclient/netty/handler/intercept/Continue100Interceptor.access$000:(Lorg/asynchttpclient/netty/handler/intercept/Continue100Interceptor;)Lorg/asynchttpclient/netty/request/NettyRequestSender;
      18: aload_0
      19: getfield      #4                  // Field future:Lorg/asynchttpclient/netty/NettyResponseFuture;
      22: aload_0
      23: getfield      #2                  // Field val$channel:Lio/netty/channel/Channel;
      26: invokevirtual #7                  // Method org/asynchttpclient/netty/request/NettyRequestSender.writeRequest:(Lorg/asynchttpclient/netty/NettyResponseFuture;Lio/netty/channel/Channel;)V
      29: return
}
