Compiled from "ApplicativeErrorSyntax.scala"
public interface scalaz.syntax.ApplicativeErrorSyntax<F, S> extends scalaz.syntax.ApplicativeSyntax<F> {
  public static scalaz.syntax.ApplicativeErrorOps ToApplicativeErrorOps$(scalaz.syntax.ApplicativeErrorSyntax, java.lang.Object);
    Code:
       0: aload_0
       1: aload_1
       2: invokespecial #19                 // InterfaceMethod ToApplicativeErrorOps:(Ljava/lang/Object;)Lscalaz/syntax/ApplicativeErrorOps;
       5: areturn

  public default <A> scalaz.syntax.ApplicativeErrorOps<F, S, A> ToApplicativeErrorOps(F);
    Code:
       0: new           #24                 // class scalaz/syntax/ApplicativeErrorOps
       3: dup
       4: aload_1
       5: aload_0
       6: invokeinterface #28,  1           // InterfaceMethod F:()Lscalaz/ApplicativeError;
      11: invokespecial #32                 // Method scalaz/syntax/ApplicativeErrorOps."<init>":(Ljava/lang/Object;Lscalaz/ApplicativeError;)V
      14: areturn

  public abstract scalaz.ApplicativeError<F, S> F();

  public static void $init$(scalaz.syntax.ApplicativeErrorSyntax);
    Code:
       0: return
}
