Compiled from "BindSyntax.scala"
public interface scalaz.syntax.BindSyntax<F> extends scalaz.syntax.ApplySyntax<F> {
  public static scalaz.syntax.BindOps ToBindOps$(scalaz.syntax.BindSyntax, java.lang.Object);
    Code:
       0: aload_0
       1: aload_1
       2: invokespecial #19                 // InterfaceMethod ToBindOps:(Ljava/lang/Object;)Lscalaz/syntax/BindOps;
       5: areturn

  public default <A> scalaz.syntax.BindOps<F, A> ToBindOps(F);
    Code:
       0: new           #24                 // class scalaz/syntax/BindOps
       3: dup
       4: aload_1
       5: aload_0
       6: invokeinterface #28,  1           // InterfaceMethod F:()Lscalaz/Bind;
      11: invokespecial #32                 // Method scalaz/syntax/BindOps."<init>":(Ljava/lang/Object;Lscalaz/Bind;)V
      14: areturn

  public abstract scalaz.Bind<F> F();

  public static void $init$(scalaz.syntax.BindSyntax);
    Code:
       0: return
}
