Compiled from "StrongSyntax.scala"
public interface scalaz.syntax.StrongSyntax<F> extends scalaz.syntax.ProfunctorSyntax<F> {
  public static scalaz.syntax.StrongOps ToStrongOps$(scalaz.syntax.StrongSyntax, java.lang.Object);
    Code:
       0: aload_0
       1: aload_1
       2: invokespecial #19                 // InterfaceMethod ToStrongOps:(Ljava/lang/Object;)Lscalaz/syntax/StrongOps;
       5: areturn

  public default <A, B> scalaz.syntax.StrongOps<F, A, B> ToStrongOps(F);
    Code:
       0: new           #24                 // class scalaz/syntax/StrongOps
       3: dup
       4: aload_1
       5: aload_0
       6: invokeinterface #28,  1           // InterfaceMethod F:()Lscalaz/Strong;
      11: invokespecial #32                 // Method scalaz/syntax/StrongOps."<init>":(Ljava/lang/Object;Lscalaz/Strong;)V
      14: areturn

  public abstract scalaz.Strong<F> F();

  public static void $init$(scalaz.syntax.StrongSyntax);
    Code:
       0: return
}
