Compiled from "Syntax.scala"
public class scalaz.syntax.Syntaxes$bitraverse$ implements scalaz.syntax.ToBitraverseOps<scalaz.Bitraverse> {
  public scalaz.syntax.BifoldableOps ToBifoldableOps(java.lang.Object, scalaz.Bifoldable);
    Code:
       0: aload_0
       1: aload_1
       2: aload_2
       3: invokestatic  #21                 // InterfaceMethod scalaz/syntax/ToBifoldableOps0.ToBifoldableOps$:(Lscalaz/syntax/ToBifoldableOps0;Ljava/lang/Object;Lscalaz/Bifoldable;)Lscalaz/syntax/BifoldableOps;
       6: areturn

  public scalaz.syntax.BifoldableOps ToBifoldableVFromKleisliLike(java.lang.Object, scalaz.Bifoldable);
    Code:
       0: aload_0
       1: aload_1
       2: aload_2
       3: invokestatic  #29                 // InterfaceMethod scalaz/syntax/ToBifoldableOps0.ToBifoldableVFromKleisliLike$:(Lscalaz/syntax/ToBifoldableOps0;Ljava/lang/Object;Lscalaz/Bifoldable;)Lscalaz/syntax/BifoldableOps;
       6: areturn

  public <FA> scalaz.syntax.BifoldableOps<java.lang.Object, java.lang.Object, java.lang.Object> ToBifoldableOpsUnapply(FA, scalaz.Unapply2<scalaz.Bitraverse, FA>);
    Code:
       0: aload_0
       1: aload_1
       2: aload_2
       3: invokestatic  #38                 // InterfaceMethod scalaz/syntax/ToBifoldableOpsU.ToBifoldableOpsUnapply$:(Lscalaz/syntax/ToBifoldableOpsU;Ljava/lang/Object;Lscalaz/Unapply2;)Lscalaz/syntax/BifoldableOps;
       6: areturn

  public scalaz.syntax.BifunctorOps ToBifunctorOps(java.lang.Object, scalaz.Bifunctor);
    Code:
       0: aload_0
       1: aload_1
       2: aload_2
       3: invokestatic  #47                 // InterfaceMethod scalaz/syntax/ToBifunctorOps0.ToBifunctorOps$:(Lscalaz/syntax/ToBifunctorOps0;Ljava/lang/Object;Lscalaz/Bifunctor;)Lscalaz/syntax/BifunctorOps;
       6: areturn

  public scalaz.syntax.BifunctorOps ToBifunctorVFromKleisliLike(java.lang.Object, scalaz.Bifunctor);
    Code:
       0: aload_0
       1: aload_1
       2: aload_2
       3: invokestatic  #52                 // InterfaceMethod scalaz/syntax/ToBifunctorOps0.ToBifunctorVFromKleisliLike$:(Lscalaz/syntax/ToBifunctorOps0;Ljava/lang/Object;Lscalaz/Bifunctor;)Lscalaz/syntax/BifunctorOps;
       6: areturn

  public <FA> scalaz.syntax.BifunctorOps<java.lang.Object, java.lang.Object, java.lang.Object> ToBifunctorOpsUnapply(FA, scalaz.Unapply2<scalaz.Bitraverse, FA>);
    Code:
       0: aload_0
       1: aload_1
       2: aload_2
       3: invokestatic  #61                 // InterfaceMethod scalaz/syntax/ToBifunctorOpsU.ToBifunctorOpsUnapply$:(Lscalaz/syntax/ToBifunctorOpsU;Ljava/lang/Object;Lscalaz/Unapply2;)Lscalaz/syntax/BifunctorOps;
       6: areturn

  public <F, A, B> scalaz.syntax.BitraverseOps<F, A, B> ToBitraverseOps(F, scalaz.Bitraverse<F>);
    Code:
       0: aload_0
       1: aload_1
       2: aload_2
       3: invokestatic  #70                 // InterfaceMethod scalaz/syntax/ToBitraverseOps0.ToBitraverseOps$:(Lscalaz/syntax/ToBitraverseOps0;Ljava/lang/Object;Lscalaz/Bitraverse;)Lscalaz/syntax/BitraverseOps;
       6: areturn

  public <G, F, A, B> scalaz.syntax.BitraverseOps<?, A, B> ToBitraverseVFromKleisliLike(F, scalaz.Bitraverse<?>);
    Code:
       0: aload_0
       1: aload_1
       2: aload_2
       3: invokestatic  #76                 // InterfaceMethod scalaz/syntax/ToBitraverseOps0.ToBitraverseVFromKleisliLike$:(Lscalaz/syntax/ToBitraverseOps0;Ljava/lang/Object;Lscalaz/Bitraverse;)Lscalaz/syntax/BitraverseOps;
       6: areturn

  public <FA> scalaz.syntax.BitraverseOps<java.lang.Object, java.lang.Object, java.lang.Object> ToBitraverseOpsUnapply(FA, scalaz.Unapply2<scalaz.Bitraverse, FA>);
    Code:
       0: aload_0
       1: aload_1
       2: aload_2
       3: invokestatic  #85                 // InterfaceMethod scalaz/syntax/ToBitraverseOpsU.ToBitraverseOpsUnapply$:(Lscalaz/syntax/ToBitraverseOpsU;Ljava/lang/Object;Lscalaz/Unapply2;)Lscalaz/syntax/BitraverseOps;
       6: areturn

  public scalaz.syntax.Syntaxes$bitraverse$(scalaz.syntax.Syntaxes);
    Code:
       0: aload_0
       1: invokespecial #91                 // Method java/lang/Object."<init>":()V
       4: aload_0
       5: invokestatic  #95                 // InterfaceMethod scalaz/syntax/ToBitraverseOpsU.$init$:(Lscalaz/syntax/ToBitraverseOpsU;)V
       8: aload_0
       9: invokestatic  #98                 // InterfaceMethod scalaz/syntax/ToBitraverseOps0.$init$:(Lscalaz/syntax/ToBitraverseOps0;)V
      12: aload_0
      13: invokestatic  #101                // InterfaceMethod scalaz/syntax/ToBifunctorOpsU.$init$:(Lscalaz/syntax/ToBifunctorOpsU;)V
      16: aload_0
      17: invokestatic  #104                // InterfaceMethod scalaz/syntax/ToBifunctorOps0.$init$:(Lscalaz/syntax/ToBifunctorOps0;)V
      20: aload_0
      21: invokestatic  #107                // InterfaceMethod scalaz/syntax/ToBifoldableOpsU.$init$:(Lscalaz/syntax/ToBifoldableOpsU;)V
      24: aload_0
      25: invokestatic  #110                // InterfaceMethod scalaz/syntax/ToBifoldableOps0.$init$:(Lscalaz/syntax/ToBifoldableOps0;)V
      28: return
}
