Compiled from "AlignSyntax.scala"
public interface scalaz.syntax.ToAlignOpsU<TC extends scalaz.Align<java.lang.Object>> {
  public static scalaz.syntax.AlignOps ToAlignOpsUnapply$(scalaz.syntax.ToAlignOpsU, java.lang.Object, scalaz.Unapply);
    Code:
       0: aload_0
       1: aload_1
       2: aload_2
       3: invokespecial #18                 // InterfaceMethod ToAlignOpsUnapply:(Ljava/lang/Object;Lscalaz/Unapply;)Lscalaz/syntax/AlignOps;
       6: areturn

  public default <FA> scalaz.syntax.AlignOps<java.lang.Object, java.lang.Object> ToAlignOpsUnapply(FA, scalaz.Unapply<TC, FA>);
    Code:
       0: new           #24                 // class scalaz/syntax/AlignOps
       3: dup
       4: aload_2
       5: ifnonnull     10
       8: aconst_null
       9: athrow
      10: aload_2
      11: invokeinterface #30,  1           // InterfaceMethod scalaz/Unapply.leibniz:()Lscalaz/Leibniz;
      16: aload_1
      17: invokevirtual #36                 // Method scalaz/Leibniz.apply:(Ljava/lang/Object;)Ljava/lang/Object;
      20: aload_2
      21: invokeinterface #40,  1           // InterfaceMethod scalaz/Unapply.TC:()Ljava/lang/Object;
      26: checkcast     #42                 // class scalaz/Align
      29: invokespecial #46                 // Method scalaz/syntax/AlignOps."<init>":(Ljava/lang/Object;Lscalaz/Align;)V
      32: areturn

  public static void $init$(scalaz.syntax.ToAlignOpsU);
    Code:
       0: return
}
