Compiled from "ApplySyntax.scala"
public interface scalaz.syntax.ToApplyOps0<TC extends scalaz.Apply<java.lang.Object>> extends scalaz.syntax.ToApplyOpsU<TC> {
  public static scalaz.syntax.ApplyOps ToApplyOps$(scalaz.syntax.ToApplyOps0, java.lang.Object, scalaz.Apply);
    Code:
       0: aload_0
       1: aload_1
       2: aload_2
       3: invokespecial #20                 // InterfaceMethod ToApplyOps:(Ljava/lang/Object;Lscalaz/Apply;)Lscalaz/syntax/ApplyOps;
       6: areturn

  public default <F, A> scalaz.syntax.ApplyOps<F, A> ToApplyOps(F, TC);
    Code:
       0: new           #26                 // class scalaz/syntax/ApplyOps
       3: dup
       4: aload_1
       5: aload_2
       6: invokespecial #30                 // Method scalaz/syntax/ApplyOps."<init>":(Ljava/lang/Object;Lscalaz/Apply;)V
       9: areturn

  public static java.lang.Object $up$(scalaz.syntax.ToApplyOps0, scala.Function0, scala.Function0, scala.Function2, scalaz.Apply);
    Code:
       0: aload_0
       1: aload_1
       2: aload_2
       3: aload_3
       4: aload         4
       6: invokespecial #41                 // InterfaceMethod $up:(Lscala/Function0;Lscala/Function0;Lscala/Function2;Lscalaz/Apply;)Ljava/lang/Object;
       9: areturn

  public default <F, A, B, C> F $up(scala.Function0<F>, scala.Function0<F>, scala.Function2<A, B, C>, TC);
    Code:
       0: aload         4
       2: aload_1
       3: aload_2
       4: aload_3
       5: invokeinterface #50,  4           // InterfaceMethod scalaz/Apply.apply2:(Lscala/Function0;Lscala/Function0;Lscala/Function2;)Ljava/lang/Object;
      10: areturn

  public static java.lang.Object $up$up$(scalaz.syntax.ToApplyOps0, scala.Function0, scala.Function0, scala.Function0, scala.Function3, scalaz.Apply);
    Code:
       0: aload_0
       1: aload_1
       2: aload_2
       3: aload_3
       4: aload         4
       6: aload         5
       8: invokespecial #57                 // InterfaceMethod $up$up:(Lscala/Function0;Lscala/Function0;Lscala/Function0;Lscala/Function3;Lscalaz/Apply;)Ljava/lang/Object;
      11: areturn

  public default <F, A, B, C, D> F $up$up(scala.Function0<F>, scala.Function0<F>, scala.Function0<F>, scala.Function3<A, B, C, D>, TC);
    Code:
       0: aload         5
       2: aload_1
       3: aload_2
       4: aload_3
       5: aload         4
       7: invokeinterface #63,  5           // InterfaceMethod scalaz/Apply.apply3:(Lscala/Function0;Lscala/Function0;Lscala/Function0;Lscala/Function3;)Ljava/lang/Object;
      12: areturn

  public static java.lang.Object $up$up$up$(scalaz.syntax.ToApplyOps0, scala.Function0, scala.Function0, scala.Function0, scala.Function0, scala.Function4, scalaz.Apply);
    Code:
       0: aload_0
       1: aload_1
       2: aload_2
       3: aload_3
       4: aload         4
       6: aload         5
       8: aload         6
      10: invokespecial #70                 // InterfaceMethod $up$up$up:(Lscala/Function0;Lscala/Function0;Lscala/Function0;Lscala/Function0;Lscala/Function4;Lscalaz/Apply;)Ljava/lang/Object;
      13: areturn

  public default <F, A, B, C, D, E> F $up$up$up(scala.Function0<F>, scala.Function0<F>, scala.Function0<F>, scala.Function0<F>, scala.Function4<A, B, C, D, E>, TC);
    Code:
       0: aload         6
       2: aload_1
       3: aload_2
       4: aload_3
       5: aload         4
       7: aload         5
       9: invokeinterface #76,  6           // InterfaceMethod scalaz/Apply.apply4:(Lscala/Function0;Lscala/Function0;Lscala/Function0;Lscala/Function0;Lscala/Function4;)Ljava/lang/Object;
      14: areturn

  public static java.lang.Object $up$up$up$up$(scalaz.syntax.ToApplyOps0, scala.Function0, scala.Function0, scala.Function0, scala.Function0, scala.Function0, scala.Function5, scalaz.Apply);
    Code:
       0: aload_0
       1: aload_1
       2: aload_2
       3: aload_3
       4: aload         4
       6: aload         5
       8: aload         6
      10: aload         7
      12: invokespecial #83                 // InterfaceMethod $up$up$up$up:(Lscala/Function0;Lscala/Function0;Lscala/Function0;Lscala/Function0;Lscala/Function0;Lscala/Function5;Lscalaz/Apply;)Ljava/lang/Object;
      15: areturn

  public default <F, A, B, C, D, E, I> F $up$up$up$up(scala.Function0<F>, scala.Function0<F>, scala.Function0<F>, scala.Function0<F>, scala.Function0<F>, scala.Function5<A, B, C, D, E, I>, TC);
    Code:
       0: aload         7
       2: aload_1
       3: aload_2
       4: aload_3
       5: aload         4
       7: aload         5
       9: aload         6
      11: invokeinterface #89,  7           // InterfaceMethod scalaz/Apply.apply5:(Lscala/Function0;Lscala/Function0;Lscala/Function0;Lscala/Function0;Lscala/Function0;Lscala/Function5;)Ljava/lang/Object;
      16: areturn

  public static java.lang.Object $up$up$up$up$up$(scalaz.syntax.ToApplyOps0, scala.Function0, scala.Function0, scala.Function0, scala.Function0, scala.Function0, scala.Function0, scala.Function6, scalaz.Apply);
    Code:
       0: aload_0
       1: aload_1
       2: aload_2
       3: aload_3
       4: aload         4
       6: aload         5
       8: aload         6
      10: aload         7
      12: aload         8
      14: invokespecial #96                 // InterfaceMethod $up$up$up$up$up:(Lscala/Function0;Lscala/Function0;Lscala/Function0;Lscala/Function0;Lscala/Function0;Lscala/Function0;Lscala/Function6;Lscalaz/Apply;)Ljava/lang/Object;
      17: areturn

  public default <F, A, B, C, D, E, I, J> F $up$up$up$up$up(scala.Function0<F>, scala.Function0<F>, scala.Function0<F>, scala.Function0<F>, scala.Function0<F>, scala.Function0<F>, scala.Function6<A, B, C, D, E, I, J>, TC);
    Code:
       0: aload         8
       2: aload_1
       3: aload_2
       4: aload_3
       5: aload         4
       7: aload         5
       9: aload         6
      11: aload         7
      13: invokeinterface #102,  8          // InterfaceMethod scalaz/Apply.apply6:(Lscala/Function0;Lscala/Function0;Lscala/Function0;Lscala/Function0;Lscala/Function0;Lscala/Function0;Lscala/Function6;)Ljava/lang/Object;
      18: areturn

  public static java.lang.Object $up$up$up$up$up$up$(scalaz.syntax.ToApplyOps0, scala.Function0, scala.Function0, scala.Function0, scala.Function0, scala.Function0, scala.Function0, scala.Function0, scala.Function7, scalaz.Apply);
    Code:
       0: aload_0
       1: aload_1
       2: aload_2
       3: aload_3
       4: aload         4
       6: aload         5
       8: aload         6
      10: aload         7
      12: aload         8
      14: aload         9
      16: invokespecial #109                // InterfaceMethod $up$up$up$up$up$up:(Lscala/Function0;Lscala/Function0;Lscala/Function0;Lscala/Function0;Lscala/Function0;Lscala/Function0;Lscala/Function0;Lscala/Function7;Lscalaz/Apply;)Ljava/lang/Object;
      19: areturn

  public default <F, A, B, C, D, E, I, J, K> F $up$up$up$up$up$up(scala.Function0<F>, scala.Function0<F>, scala.Function0<F>, scala.Function0<F>, scala.Function0<F>, scala.Function0<F>, scala.Function0<F>, scala.Function7<A, B, C, D, E, I, J, K>, TC);
    Code:
       0: aload         9
       2: aload_1
       3: aload_2
       4: aload_3
       5: aload         4
       7: aload         5
       9: aload         6
      11: aload         7
      13: aload         8
      15: invokeinterface #115,  9          // InterfaceMethod scalaz/Apply.apply7:(Lscala/Function0;Lscala/Function0;Lscala/Function0;Lscala/Function0;Lscala/Function0;Lscala/Function0;Lscala/Function0;Lscala/Function7;)Ljava/lang/Object;
      20: areturn

  public static void $init$(scalaz.syntax.ToApplyOps0);
    Code:
       0: return
}
