Compiled from "CategorySyntax.scala"
public interface scalaz.syntax.ToCategoryOps0<TC extends scalaz.Category<java.lang.Object>> extends scalaz.syntax.ToCategoryOpsU<TC> {
  public static scalaz.syntax.CategoryOps ToCategoryOps$(scalaz.syntax.ToCategoryOps0, java.lang.Object, scalaz.Category);
    Code:
       0: aload_0
       1: aload_1
       2: aload_2
       3: invokespecial #20                 // InterfaceMethod ToCategoryOps:(Ljava/lang/Object;Lscalaz/Category;)Lscalaz/syntax/CategoryOps;
       6: areturn

  public default <F, A, B> scalaz.syntax.CategoryOps<F, A, B> ToCategoryOps(F, TC);
    Code:
       0: new           #26                 // class scalaz/syntax/CategoryOps
       3: dup
       4: aload_1
       5: aload_2
       6: invokespecial #30                 // Method scalaz/syntax/CategoryOps."<init>":(Ljava/lang/Object;Lscalaz/Category;)V
       9: areturn

  public static scalaz.syntax.CategoryOps ToCategoryVFromKleisliLike$(scalaz.syntax.ToCategoryOps0, java.lang.Object, scalaz.Category);
    Code:
       0: aload_0
       1: aload_1
       2: aload_2
       3: invokespecial #35                 // InterfaceMethod ToCategoryVFromKleisliLike:(Ljava/lang/Object;Lscalaz/Category;)Lscalaz/syntax/CategoryOps;
       6: areturn

  public default <G, F, A, B> scalaz.syntax.CategoryOps<?, A, B> ToCategoryVFromKleisliLike(F, TC);
    Code:
       0: new           #26                 // class scalaz/syntax/CategoryOps
       3: dup
       4: aload_1
       5: aload_2
       6: invokespecial #30                 // Method scalaz/syntax/CategoryOps."<init>":(Ljava/lang/Object;Lscalaz/Category;)V
       9: areturn

  public static void $init$(scalaz.syntax.ToCategoryOps0);
    Code:
       0: return
}
