Compiled from "Traverse1Syntax.scala"
public final class scalaz.syntax.Traverse1Ops<F, A> implements scalaz.syntax.Ops<F> {
  private final F self;

  private final scalaz.Traverse1<F> F;

  public F self();
    Code:
       0: aload_0
       1: getfield      #21                 // Field self:Ljava/lang/Object;
       4: areturn

  public scalaz.Traverse1<F> F();
    Code:
       0: aload_0
       1: getfield      #27                 // Field F:Lscalaz/Traverse1;
       4: areturn

  public final <G, B> G traverse1(scala.Function1<A, G>, scalaz.Apply<G>);
    Code:
       0: aload_2
       1: aload_0
       2: invokevirtual #34                 // Method self:()Ljava/lang/Object;
       5: aload_1
       6: aload_0
       7: invokevirtual #36                 // Method F:()Lscalaz/Traverse1;
      10: invokeinterface #41,  4           // InterfaceMethod scalaz/Apply.traverse1:(Ljava/lang/Object;Lscala/Function1;Lscalaz/Traverse1;)Ljava/lang/Object;
      15: areturn

  public final <GB> java.lang.Object traverse1U(scala.Function1<A, GB>, scalaz.Unapply<scalaz.Apply, GB>);
    Code:
       0: aload_0
       1: invokevirtual #36                 // Method F:()Lscalaz/Traverse1;
       4: aload_0
       5: invokevirtual #34                 // Method self:()Ljava/lang/Object;
       8: astore_3
       9: dup
      10: ifnonnull     15
      13: aconst_null
      14: athrow
      15: aload_3
      16: aload_2
      17: invokeinterface #52,  1           // InterfaceMethod scalaz/Unapply.leibniz:()Lscalaz/Leibniz;
      22: dup
      23: ifnonnull     28
      26: aconst_null
      27: athrow
      28: aload_1
      29: invokevirtual #58                 // Method scalaz/Leibniz.subst:(Ljava/lang/Object;)Ljava/lang/Object;
      32: checkcast     #60                 // class scala/Function1
      35: aload_2
      36: invokeinterface #63,  1           // InterfaceMethod scalaz/Unapply.TC:()Ljava/lang/Object;
      41: checkcast     #38                 // class scalaz/Apply
      44: invokeinterface #68,  4           // InterfaceMethod scalaz/Traverse1.traverse1:(Ljava/lang/Object;Lscala/Function1;Lscalaz/Apply;)Ljava/lang/Object;
      49: areturn

  public final <G, B> G sequence1(scalaz.Leibniz<scala.runtime.Nothing$, java.lang.Object, A, G>, scalaz.Apply<G>);
    Code:
       0: aload_1
       1: aload_0
       2: invokevirtual #34                 // Method self:()Ljava/lang/Object;
       5: invokevirtual #58                 // Method scalaz/Leibniz.subst:(Ljava/lang/Object;)Ljava/lang/Object;
       8: astore_3
       9: aload_0
      10: invokevirtual #36                 // Method F:()Lscalaz/Traverse1;
      13: aload_3
      14: aload_2
      15: invokeinterface #77,  3           // InterfaceMethod scalaz/Traverse1.sequence1:(Ljava/lang/Object;Lscalaz/Apply;)Ljava/lang/Object;
      20: areturn

  public final java.lang.Object sequence1U(scalaz.Unapply<scalaz.Apply, A>);
    Code:
       0: aload_0
       1: invokevirtual #36                 // Method F:()Lscalaz/Traverse1;
       4: aload_0
       5: invokevirtual #34                 // Method self:()Ljava/lang/Object;
       8: aload_1
       9: invokeinterface #85,  3           // InterfaceMethod scalaz/Traverse1.sequence1U:(Ljava/lang/Object;Lscalaz/Unapply;)Ljava/lang/Object;
      14: areturn

  public scalaz.syntax.Traverse1Ops(F, scalaz.Traverse1<F>);
    Code:
       0: aload_0
       1: aload_1
       2: putfield      #21                 // Field self:Ljava/lang/Object;
       5: aload_0
       6: aload_2
       7: putfield      #27                 // Field F:Lscalaz/Traverse1;
      10: aload_0
      11: invokespecial #91                 // Method java/lang/Object."<init>":()V
      14: return
}
