Compiled from "MulticastKeepaliveHeartbeatReceiver.java"
public final class net.sf.ehcache.distribution.MulticastKeepaliveHeartbeatReceiver {
  private static final org.slf4j.Logger LOG;

  private java.util.concurrent.ExecutorService processingThreadPool;

  private java.util.Set rmiUrlsProcessingQueue;

  private final java.net.InetAddress groupMulticastAddress;

  private final java.lang.Integer groupMulticastPort;

  private net.sf.ehcache.distribution.MulticastKeepaliveHeartbeatReceiver$MulticastReceiverThread receiverThread;

  private java.net.MulticastSocket socket;

  private volatile boolean stopped;

  private final net.sf.ehcache.distribution.MulticastRMICacheManagerPeerProvider peerProvider;

  private java.net.InetAddress hostAddress;

  public net.sf.ehcache.distribution.MulticastKeepaliveHeartbeatReceiver(net.sf.ehcache.distribution.MulticastRMICacheManagerPeerProvider, java.net.InetAddress, java.lang.Integer, java.net.InetAddress);
    Code:
       0: aload_0
       1: invokespecial #8                  // Method java/lang/Object."<init>":()V
       4: aload_0
       5: new           #9                  // class java/util/HashSet
       8: dup
       9: invokespecial #10                 // Method java/util/HashSet."<init>":()V
      12: invokestatic  #11                 // Method java/util/Collections.synchronizedSet:(Ljava/util/Set;)Ljava/util/Set;
      15: putfield      #4                  // Field rmiUrlsProcessingQueue:Ljava/util/Set;
      18: aload_0
      19: aload_1
      20: putfield      #2                  // Field peerProvider:Lnet/sf/ehcache/distribution/MulticastRMICacheManagerPeerProvider;
      23: aload_0
      24: aload_2
      25: putfield      #1                  // Field groupMulticastAddress:Ljava/net/InetAddress;
      28: aload_0
      29: aload_3
      30: putfield      #12                 // Field groupMulticastPort:Ljava/lang/Integer;
      33: aload_0
      34: aload         4
      36: putfield      #13                 // Field hostAddress:Ljava/net/InetAddress;
      39: return

  final void init() throws java.io.IOException;
    Code:
       0: aload_0
       1: new           #14                 // class java/net/MulticastSocket
       4: dup
       5: aload_0
       6: getfield      #12                 // Field groupMulticastPort:Ljava/lang/Integer;
       9: invokevirtual #15                 // Method java/lang/Integer.intValue:()I
      12: invokespecial #16                 // Method java/net/MulticastSocket."<init>":(I)V
      15: putfield      #6                  // Field socket:Ljava/net/MulticastSocket;
      18: aload_0
      19: getfield      #13                 // Field hostAddress:Ljava/net/InetAddress;
      22: ifnull        36
      25: aload_0
      26: getfield      #6                  // Field socket:Ljava/net/MulticastSocket;
      29: aload_0
      30: getfield      #13                 // Field hostAddress:Ljava/net/InetAddress;
      33: invokevirtual #17                 // Method java/net/MulticastSocket.setInterface:(Ljava/net/InetAddress;)V
      36: aload_0
      37: getfield      #6                  // Field socket:Ljava/net/MulticastSocket;
      40: aload_0
      41: getfield      #1                  // Field groupMulticastAddress:Ljava/net/InetAddress;
      44: invokevirtual #18                 // Method java/net/MulticastSocket.joinGroup:(Ljava/net/InetAddress;)V
      47: aload_0
      48: new           #19                 // class net/sf/ehcache/distribution/MulticastKeepaliveHeartbeatReceiver$MulticastReceiverThread
      51: dup
      52: aload_0
      53: invokespecial #20                 // Method net/sf/ehcache/distribution/MulticastKeepaliveHeartbeatReceiver$MulticastReceiverThread."<init>":(Lnet/sf/ehcache/distribution/MulticastKeepaliveHeartbeatReceiver;)V
      56: putfield      #21                 // Field receiverThread:Lnet/sf/ehcache/distribution/MulticastKeepaliveHeartbeatReceiver$MulticastReceiverThread;
      59: aload_0
      60: getfield      #21                 // Field receiverThread:Lnet/sf/ehcache/distribution/MulticastKeepaliveHeartbeatReceiver$MulticastReceiverThread;
      63: invokevirtual #22                 // Method net/sf/ehcache/distribution/MulticastKeepaliveHeartbeatReceiver$MulticastReceiverThread.start:()V
      66: aload_0
      67: new           #23                 // class net/sf/ehcache/util/NamedThreadFactory
      70: dup
      71: ldc           #24                 // String Multicast keep-alive Heartbeat Receiver
      73: invokespecial #25                 // Method net/sf/ehcache/util/NamedThreadFactory."<init>":(Ljava/lang/String;)V
      76: invokestatic  #26                 // Method java/util/concurrent/Executors.newCachedThreadPool:(Ljava/util/concurrent/ThreadFactory;)Ljava/util/concurrent/ExecutorService;
      79: putfield      #3                  // Field processingThreadPool:Ljava/util/concurrent/ExecutorService;
      82: return

  public final void dispose();
    Code:
       0: getstatic     #5                  // Field LOG:Lorg/slf4j/Logger;
       3: ldc           #27                 // String dispose called
       5: invokeinterface #28,  2           // InterfaceMethod org/slf4j/Logger.debug:(Ljava/lang/String;)V
      10: aload_0
      11: getfield      #3                  // Field processingThreadPool:Ljava/util/concurrent/ExecutorService;
      14: invokeinterface #29,  1           // InterfaceMethod java/util/concurrent/ExecutorService.shutdownNow:()Ljava/util/List;
      19: pop
      20: aload_0
      21: iconst_1
      22: putfield      #7                  // Field stopped:Z
      25: aload_0
      26: getfield      #21                 // Field receiverThread:Lnet/sf/ehcache/distribution/MulticastKeepaliveHeartbeatReceiver$MulticastReceiverThread;
      29: invokevirtual #30                 // Method net/sf/ehcache/distribution/MulticastKeepaliveHeartbeatReceiver$MulticastReceiverThread.interrupt:()V
      32: return

  static boolean access$000(net.sf.ehcache.distribution.MulticastKeepaliveHeartbeatReceiver);
    Code:
       0: aload_0
       1: getfield      #7                  // Field stopped:Z
       4: ireturn

  static java.net.MulticastSocket access$100(net.sf.ehcache.distribution.MulticastKeepaliveHeartbeatReceiver);
    Code:
       0: aload_0
       1: getfield      #6                  // Field socket:Ljava/net/MulticastSocket;
       4: areturn

  static org.slf4j.Logger access$200();
    Code:
       0: getstatic     #5                  // Field LOG:Lorg/slf4j/Logger;
       3: areturn

  static java.util.Set access$300(net.sf.ehcache.distribution.MulticastKeepaliveHeartbeatReceiver);
    Code:
       0: aload_0
       1: getfield      #4                  // Field rmiUrlsProcessingQueue:Ljava/util/Set;
       4: areturn

  static java.util.concurrent.ExecutorService access$400(net.sf.ehcache.distribution.MulticastKeepaliveHeartbeatReceiver);
    Code:
       0: aload_0
       1: getfield      #3                  // Field processingThreadPool:Ljava/util/concurrent/ExecutorService;
       4: areturn

  static net.sf.ehcache.distribution.MulticastRMICacheManagerPeerProvider access$600(net.sf.ehcache.distribution.MulticastKeepaliveHeartbeatReceiver);
    Code:
       0: aload_0
       1: getfield      #2                  // Field peerProvider:Lnet/sf/ehcache/distribution/MulticastRMICacheManagerPeerProvider;
       4: areturn

  static java.net.InetAddress access$700(net.sf.ehcache.distribution.MulticastKeepaliveHeartbeatReceiver);
    Code:
       0: aload_0
       1: getfield      #1                  // Field groupMulticastAddress:Ljava/net/InetAddress;
       4: areturn

  static {};
    Code:
       0: ldc_w         #31                 // class net/sf/ehcache/distribution/MulticastKeepaliveHeartbeatReceiver
       3: invokevirtual #32                 // Method java/lang/Class.getName:()Ljava/lang/String;
       6: invokestatic  #33                 // Method org/slf4j/LoggerFactory.getLogger:(Ljava/lang/String;)Lorg/slf4j/Logger;
       9: putstatic     #5                  // Field LOG:Lorg/slf4j/Logger;
      12: return
}
