Compiled from "ClientConnection.java"
class org.jboss.remotingjmx.protocol.v2.ClientConnection$IntegerResponseHandler extends org.jboss.remotingjmx.protocol.v2.ClientCommon$BaseResponseHandler<java.lang.Integer> {
  final org.jboss.remotingjmx.protocol.v2.ClientConnection this$0;

  private org.jboss.remotingjmx.protocol.v2.ClientConnection$IntegerResponseHandler(org.jboss.remotingjmx.protocol.v2.ClientConnection);
    Code:
       0: aload_0
       1: aload_1
       2: putfield      #2                  // Field this$0:Lorg/jboss/remotingjmx/protocol/v2/ClientConnection;
       5: aload_0
       6: aload_1
       7: invokespecial #3                  // Method org/jboss/remotingjmx/protocol/v2/ClientCommon$BaseResponseHandler."<init>":(Lorg/jboss/remotingjmx/protocol/v2/ClientCommon;)V
      10: return

  protected byte getExpectedType();
    Code:
       0: bipush        11
       2: ireturn

  protected java.lang.Integer readValue(java.io.DataInput) throws java.io.IOException;
    Code:
       0: aload_1
       1: invokeinterface #4,  1            // InterfaceMethod java/io/DataInput.readInt:()I
       6: invokestatic  #5                  // Method java/lang/Integer.valueOf:(I)Ljava/lang/Integer;
       9: areturn

  protected java.lang.Object readValue(java.io.DataInput) throws java.io.IOException;
    Code:
       0: aload_0
       1: aload_1
       2: invokevirtual #6                  // Method readValue:(Ljava/io/DataInput;)Ljava/lang/Integer;
       5: areturn

  org.jboss.remotingjmx.protocol.v2.ClientConnection$IntegerResponseHandler(org.jboss.remotingjmx.protocol.v2.ClientConnection, org.jboss.remotingjmx.protocol.v2.ClientConnection$1);
    Code:
       0: aload_0
       1: aload_1
       2: invokespecial #1                  // Method "<init>":(Lorg/jboss/remotingjmx/protocol/v2/ClientConnection;)V
       5: return
}
