Compiled from "Common.java"
class org.jboss.remotingjmx.protocol.v2.Common$1 extends java.io.OutputStream {
  final java.io.DataOutput val$dataOutput;

  final org.jboss.remotingjmx.protocol.v2.Common this$0;

  org.jboss.remotingjmx.protocol.v2.Common$1(org.jboss.remotingjmx.protocol.v2.Common, java.io.DataOutput);
    Code:
       0: aload_0
       1: aload_1
       2: putfield      #1                  // Field this$0:Lorg/jboss/remotingjmx/protocol/v2/Common;
       5: aload_0
       6: aload_2
       7: putfield      #2                  // Field val$dataOutput:Ljava/io/DataOutput;
      10: aload_0
      11: invokespecial #3                  // Method java/io/OutputStream."<init>":()V
      14: return

  public void write(int) throws java.io.IOException;
    Code:
       0: iload_1
       1: sipush        255
       4: iand
       5: istore_2
       6: aload_0
       7: getfield      #2                  // Field val$dataOutput:Ljava/io/DataOutput;
      10: iload_2
      11: invokeinterface #4,  2            // InterfaceMethod java/io/DataOutput.write:(I)V
      16: return
}
