Compiled from "DelegateBuilder.java"
public class org.opensaml.saml.ext.saml2delrestrict.impl.DelegateBuilder extends org.opensaml.saml.common.AbstractSAMLObjectBuilder<org.opensaml.saml.ext.saml2delrestrict.Delegate> {
  public org.opensaml.saml.ext.saml2delrestrict.impl.DelegateBuilder();
    Code:
       0: aload_0
       1: invokespecial #1                  // Method org/opensaml/saml/common/AbstractSAMLObjectBuilder."<init>":()V
       4: return

  public org.opensaml.saml.ext.saml2delrestrict.Delegate buildObject();
    Code:
       0: aload_0
       1: getstatic     #2                  // Field org/opensaml/saml/ext/saml2delrestrict/Delegate.DEFAULT_ELEMENT_NAME:Ljavax/xml/namespace/QName;
       4: invokevirtual #3                  // Method buildObject:(Ljavax/xml/namespace/QName;)Lorg/opensaml/core/xml/XMLObject;
       7: checkcast     #4                  // class org/opensaml/saml/ext/saml2delrestrict/Delegate
      10: areturn

  public org.opensaml.saml.ext.saml2delrestrict.Delegate buildObject(java.lang.String, java.lang.String, java.lang.String);
    Code:
       0: new           #5                  // class org/opensaml/saml/ext/saml2delrestrict/impl/DelegateImpl
       3: dup
       4: aload_1
       5: aload_2
       6: aload_3
       7: invokespecial #6                  // Method org/opensaml/saml/ext/saml2delrestrict/impl/DelegateImpl."<init>":(Ljava/lang/String;Ljava/lang/String;Ljava/lang/String;)V
      10: areturn

  public org.opensaml.saml.common.SAMLObject buildObject();
    Code:
       0: aload_0
       1: invokevirtual #7                  // Method buildObject:()Lorg/opensaml/saml/ext/saml2delrestrict/Delegate;
       4: areturn

  public org.opensaml.core.xml.XMLObject buildObject(java.lang.String, java.lang.String, java.lang.String);
    Code:
       0: aload_0
       1: aload_1
       2: aload_2
       3: aload_3
       4: invokevirtual #8                  // Method buildObject:(Ljava/lang/String;Ljava/lang/String;Ljava/lang/String;)Lorg/opensaml/saml/ext/saml2delrestrict/Delegate;
       7: areturn
}
