Compiled from "QueryExecutionConverters.java"
class org.springframework.data.repository.util.QueryExecutionConverters$NullableWrapperToCompletableFutureConverter extends org.springframework.data.repository.util.QueryExecutionConverters$AbstractWrapperTypeConverter {
  public org.springframework.data.repository.util.QueryExecutionConverters$NullableWrapperToCompletableFutureConverter(org.springframework.core.convert.ConversionService);
    Code:
       0: aload_0
       1: aload_1
       2: aconst_null
       3: invokestatic  #1                  // Method java/util/concurrent/CompletableFuture.completedFuture:(Ljava/lang/Object;)Ljava/util/concurrent/CompletableFuture;
       6: invokespecial #2                  // Method org/springframework/data/repository/util/QueryExecutionConverters$AbstractWrapperTypeConverter."<init>":(Lorg/springframework/core/convert/ConversionService;Ljava/lang/Object;)V
       9: return

  protected java.lang.Object wrap(java.lang.Object);
    Code:
       0: aload_1
       1: instanceof    #3                  // class java/util/concurrent/CompletableFuture
       4: ifeq          11
       7: aload_1
       8: goto          15
      11: aload_1
      12: invokestatic  #1                  // Method java/util/concurrent/CompletableFuture.completedFuture:(Ljava/lang/Object;)Ljava/util/concurrent/CompletableFuture;
      15: areturn

  public static org.springframework.data.repository.util.QueryExecutionConverters$WrapperType getWrapperType();
    Code:
       0: ldc           #3                  // class java/util/concurrent/CompletableFuture
       2: invokestatic  #4                  // Method org/springframework/data/repository/util/QueryExecutionConverters$WrapperType.singleValue:(Ljava/lang/Class;)Lorg/springframework/data/repository/util/QueryExecutionConverters$WrapperType;
       5: areturn
}
