Compiled from "ContainerRequestFilterRegistry.java"
class org.jboss.resteasy.core.interception.ContainerRequestFilterRegistry$ContainerRequestFilterFacade implements javax.ws.rs.container.ContainerRequestFilter {
  protected final org.jboss.resteasy.spi.interception.PreProcessInterceptor interceptor;

  private org.jboss.resteasy.core.interception.ContainerRequestFilterRegistry$ContainerRequestFilterFacade(org.jboss.resteasy.spi.interception.PreProcessInterceptor);
    Code:
       0: aload_0
       1: invokespecial #2                  // Method java/lang/Object."<init>":()V
       4: aload_0
       5: aload_1
       6: putfield      #3                  // Field interceptor:Lorg/jboss/resteasy/spi/interception/PreProcessInterceptor;
       9: return

  public void filter(javax.ws.rs.container.ContainerRequestContext) throws java.io.IOException;
    Code:
       0: aload_1
       1: checkcast     #4                  // class org/jboss/resteasy/core/interception/PostMatchContainerRequestContext
       4: astore_2
       5: aload_0
       6: getfield      #3                  // Field interceptor:Lorg/jboss/resteasy/spi/interception/PreProcessInterceptor;
       9: aload_2
      10: invokevirtual #5                  // Method org/jboss/resteasy/core/interception/PostMatchContainerRequestContext.getHttpRequest:()Lorg/jboss/resteasy/spi/HttpRequest;
      13: aload_2
      14: invokevirtual #6                  // Method org/jboss/resteasy/core/interception/PostMatchContainerRequestContext.getResourceMethod:()Lorg/jboss/resteasy/core/ResourceMethodInvoker;
      17: invokeinterface #7,  3            // InterfaceMethod org/jboss/resteasy/spi/interception/PreProcessInterceptor.preProcess:(Lorg/jboss/resteasy/spi/HttpRequest;Lorg/jboss/resteasy/core/ResourceMethodInvoker;)Lorg/jboss/resteasy/core/ServerResponse;
      22: astore_3
      23: aload_3
      24: ifnull        34
      27: aload_1
      28: aload_3
      29: invokeinterface #8,  2            // InterfaceMethod javax/ws/rs/container/ContainerRequestContext.abortWith:(Ljavax/ws/rs/core/Response;)V
      34: return

  org.jboss.resteasy.core.interception.ContainerRequestFilterRegistry$ContainerRequestFilterFacade(org.jboss.resteasy.spi.interception.PreProcessInterceptor, org.jboss.resteasy.core.interception.ContainerRequestFilterRegistry$1);
    Code:
       0: aload_0
       1: aload_1
       2: invokespecial #1                  // Method "<init>":(Lorg/jboss/resteasy/spi/interception/PreProcessInterceptor;)V
       5: return
}
