Compiled from "ReaderInterceptorRegistry.java"
class org.jboss.resteasy.core.interception.ReaderInterceptorRegistry$MessageBodyReaderContextFacade implements org.jboss.resteasy.spi.interception.MessageBodyReaderContext {
  protected final javax.ws.rs.ext.ReaderInterceptorContext readerInterceptorContext;

  private org.jboss.resteasy.core.interception.ReaderInterceptorRegistry$MessageBodyReaderContextFacade(javax.ws.rs.ext.ReaderInterceptorContext);
    Code:
       0: aload_0
       1: invokespecial #2                  // Method java/lang/Object."<init>":()V
       4: aload_0
       5: aload_1
       6: putfield      #3                  // Field readerInterceptorContext:Ljavax/ws/rs/ext/ReaderInterceptorContext;
       9: return

  public java.lang.Class getType();
    Code:
       0: aload_0
       1: getfield      #3                  // Field readerInterceptorContext:Ljavax/ws/rs/ext/ReaderInterceptorContext;
       4: invokeinterface #4,  1            // InterfaceMethod javax/ws/rs/ext/ReaderInterceptorContext.getType:()Ljava/lang/Class;
       9: areturn

  public void setType(java.lang.Class);
    Code:
       0: aload_0
       1: getfield      #3                  // Field readerInterceptorContext:Ljavax/ws/rs/ext/ReaderInterceptorContext;
       4: aload_1
       5: invokeinterface #5,  2            // InterfaceMethod javax/ws/rs/ext/ReaderInterceptorContext.setType:(Ljava/lang/Class;)V
      10: return

  public java.lang.reflect.Type getGenericType();
    Code:
       0: aload_0
       1: getfield      #3                  // Field readerInterceptorContext:Ljavax/ws/rs/ext/ReaderInterceptorContext;
       4: invokeinterface #6,  1            // InterfaceMethod javax/ws/rs/ext/ReaderInterceptorContext.getGenericType:()Ljava/lang/reflect/Type;
       9: areturn

  public void setGenericType(java.lang.reflect.Type);
    Code:
       0: aload_0
       1: getfield      #3                  // Field readerInterceptorContext:Ljavax/ws/rs/ext/ReaderInterceptorContext;
       4: aload_1
       5: invokeinterface #7,  2            // InterfaceMethod javax/ws/rs/ext/ReaderInterceptorContext.setGenericType:(Ljava/lang/reflect/Type;)V
      10: return

  public java.lang.annotation.Annotation[] getAnnotations();
    Code:
       0: aload_0
       1: getfield      #3                  // Field readerInterceptorContext:Ljavax/ws/rs/ext/ReaderInterceptorContext;
       4: invokeinterface #8,  1            // InterfaceMethod javax/ws/rs/ext/ReaderInterceptorContext.getAnnotations:()[Ljava/lang/annotation/Annotation;
       9: areturn

  public void setAnnotations(java.lang.annotation.Annotation[]);
    Code:
       0: aload_0
       1: getfield      #3                  // Field readerInterceptorContext:Ljavax/ws/rs/ext/ReaderInterceptorContext;
       4: aload_1
       5: invokeinterface #9,  2            // InterfaceMethod javax/ws/rs/ext/ReaderInterceptorContext.setAnnotations:([Ljava/lang/annotation/Annotation;)V
      10: return

  public javax.ws.rs.core.MediaType getMediaType();
    Code:
       0: aload_0
       1: getfield      #3                  // Field readerInterceptorContext:Ljavax/ws/rs/ext/ReaderInterceptorContext;
       4: invokeinterface #10,  1           // InterfaceMethod javax/ws/rs/ext/ReaderInterceptorContext.getMediaType:()Ljavax/ws/rs/core/MediaType;
       9: areturn

  public void setMediaType(javax.ws.rs.core.MediaType);
    Code:
       0: aload_0
       1: getfield      #3                  // Field readerInterceptorContext:Ljavax/ws/rs/ext/ReaderInterceptorContext;
       4: aload_1
       5: invokeinterface #11,  2           // InterfaceMethod javax/ws/rs/ext/ReaderInterceptorContext.setMediaType:(Ljavax/ws/rs/core/MediaType;)V
      10: return

  public javax.ws.rs.core.MultivaluedMap<java.lang.String, java.lang.String> getHeaders();
    Code:
       0: aload_0
       1: getfield      #3                  // Field readerInterceptorContext:Ljavax/ws/rs/ext/ReaderInterceptorContext;
       4: invokeinterface #12,  1           // InterfaceMethod javax/ws/rs/ext/ReaderInterceptorContext.getHeaders:()Ljavax/ws/rs/core/MultivaluedMap;
       9: areturn

  public java.io.InputStream getInputStream();
    Code:
       0: aload_0
       1: getfield      #3                  // Field readerInterceptorContext:Ljavax/ws/rs/ext/ReaderInterceptorContext;
       4: invokeinterface #13,  1           // InterfaceMethod javax/ws/rs/ext/ReaderInterceptorContext.getInputStream:()Ljava/io/InputStream;
       9: areturn

  public void setInputStream(java.io.InputStream);
    Code:
       0: aload_0
       1: getfield      #3                  // Field readerInterceptorContext:Ljavax/ws/rs/ext/ReaderInterceptorContext;
       4: aload_1
       5: invokeinterface #14,  2           // InterfaceMethod javax/ws/rs/ext/ReaderInterceptorContext.setInputStream:(Ljava/io/InputStream;)V
      10: return

  public java.lang.Object getAttribute(java.lang.String);
    Code:
       0: aload_0
       1: getfield      #3                  // Field readerInterceptorContext:Ljavax/ws/rs/ext/ReaderInterceptorContext;
       4: aload_1
       5: invokeinterface #15,  2           // InterfaceMethod javax/ws/rs/ext/ReaderInterceptorContext.getProperty:(Ljava/lang/String;)Ljava/lang/Object;
      10: areturn

  public void setAttribute(java.lang.String, java.lang.Object);
    Code:
       0: aload_0
       1: getfield      #3                  // Field readerInterceptorContext:Ljavax/ws/rs/ext/ReaderInterceptorContext;
       4: aload_1
       5: aload_2
       6: invokeinterface #16,  3           // InterfaceMethod javax/ws/rs/ext/ReaderInterceptorContext.setProperty:(Ljava/lang/String;Ljava/lang/Object;)V
      11: return

  public void removeAttribute(java.lang.String);
    Code:
       0: aload_0
       1: getfield      #3                  // Field readerInterceptorContext:Ljavax/ws/rs/ext/ReaderInterceptorContext;
       4: aload_1
       5: invokeinterface #17,  2           // InterfaceMethod javax/ws/rs/ext/ReaderInterceptorContext.removeProperty:(Ljava/lang/String;)V
      10: return

  public java.lang.Object proceed() throws java.io.IOException, javax.ws.rs.WebApplicationException;
    Code:
       0: aload_0
       1: getfield      #3                  // Field readerInterceptorContext:Ljavax/ws/rs/ext/ReaderInterceptorContext;
       4: invokeinterface #18,  1           // InterfaceMethod javax/ws/rs/ext/ReaderInterceptorContext.proceed:()Ljava/lang/Object;
       9: areturn

  org.jboss.resteasy.core.interception.ReaderInterceptorRegistry$MessageBodyReaderContextFacade(javax.ws.rs.ext.ReaderInterceptorContext, org.jboss.resteasy.core.interception.ReaderInterceptorRegistry$1);
    Code:
       0: aload_0
       1: aload_1
       2: invokespecial #1                  // Method "<init>":(Ljavax/ws/rs/ext/ReaderInterceptorContext;)V
       5: return
}
