Compiled from "StompBrokerRelayMessageHandler.java"
class org.springframework.messaging.simp.stomp.StompBrokerRelayMessageHandler$StompConnectionHandler$3 implements java.lang.Runnable {
  final long val$interval;

  final org.springframework.messaging.simp.stomp.StompBrokerRelayMessageHandler$StompConnectionHandler this$1;

  org.springframework.messaging.simp.stomp.StompBrokerRelayMessageHandler$StompConnectionHandler$3(org.springframework.messaging.simp.stomp.StompBrokerRelayMessageHandler$StompConnectionHandler, long);
    Code:
       0: aload_0
       1: aload_1
       2: putfield      #1                  // Field this$1:Lorg/springframework/messaging/simp/stomp/StompBrokerRelayMessageHandler$StompConnectionHandler;
       5: aload_0
       6: lload_2
       7: putfield      #2                  // Field val$interval:J
      10: aload_0
      11: invokespecial #3                  // Method java/lang/Object."<init>":()V
      14: return

  public void run();
    Code:
       0: aload_0
       1: getfield      #1                  // Field this$1:Lorg/springframework/messaging/simp/stomp/StompBrokerRelayMessageHandler$StompConnectionHandler;
       4: new           #4                  // class java/lang/StringBuilder
       7: dup
       8: invokespecial #5                  // Method java/lang/StringBuilder."<init>":()V
      11: ldc           #6                  // String No messages received in
      13: invokevirtual #7                  // Method java/lang/StringBuilder.append:(Ljava/lang/String;)Ljava/lang/StringBuilder;
      16: aload_0
      17: getfield      #2                  // Field val$interval:J
      20: invokevirtual #8                  // Method java/lang/StringBuilder.append:(J)Ljava/lang/StringBuilder;
      23: ldc           #9                  // String  ms.
      25: invokevirtual #7                  // Method java/lang/StringBuilder.append:(Ljava/lang/String;)Ljava/lang/StringBuilder;
      28: invokevirtual #10                 // Method java/lang/StringBuilder.toString:()Ljava/lang/String;
      31: aconst_null
      32: invokevirtual #11                 // Method org/springframework/messaging/simp/stomp/StompBrokerRelayMessageHandler$StompConnectionHandler.handleTcpConnectionFailure:(Ljava/lang/String;Ljava/lang/Throwable;)V
      35: return
}
