Compiled from "CatalogWSDLLocator.java"
public class org.apache.cxf.wsdl11.CatalogWSDLLocator implements javax.wsdl.xml.WSDLLocator {
  private java.lang.String wsdlUrl;

  private org.apache.cxf.resource.ExtendedURIResolver resolver;

  private org.apache.cxf.catalog.OASISCatalogManager manager;

  private java.lang.String baseUri;

  public org.apache.cxf.wsdl11.CatalogWSDLLocator(java.lang.String);
    Code:
       0: aload_0
       1: invokespecial #1                  // Method java/lang/Object."<init>":()V
       4: aload_0
       5: aload_1
       6: putfield      #2                  // Field baseUri:Ljava/lang/String;
       9: aload_0
      10: new           #3                  // class org/apache/cxf/resource/ExtendedURIResolver
      13: dup
      14: invokespecial #4                  // Method org/apache/cxf/resource/ExtendedURIResolver."<init>":()V
      17: putfield      #5                  // Field resolver:Lorg/apache/cxf/resource/ExtendedURIResolver;
      20: return

  public org.apache.cxf.wsdl11.CatalogWSDLLocator(java.lang.String, org.apache.cxf.catalog.OASISCatalogManager);
    Code:
       0: aload_0
       1: invokespecial #1                  // Method java/lang/Object."<init>":()V
       4: aload_0
       5: aload_1
       6: putfield      #2                  // Field baseUri:Ljava/lang/String;
       9: aload_0
      10: aload_2
      11: putfield      #6                  // Field manager:Lorg/apache/cxf/catalog/OASISCatalogManager;
      14: aload_0
      15: new           #3                  // class org/apache/cxf/resource/ExtendedURIResolver
      18: dup
      19: invokespecial #4                  // Method org/apache/cxf/resource/ExtendedURIResolver."<init>":()V
      22: putfield      #5                  // Field resolver:Lorg/apache/cxf/resource/ExtendedURIResolver;
      25: return

  public org.apache.cxf.wsdl11.CatalogWSDLLocator(java.lang.String, org.apache.cxf.Bus);
    Code:
       0: aload_0
       1: invokespecial #1                  // Method java/lang/Object."<init>":()V
       4: aload_0
       5: aload_1
       6: putfield      #2                  // Field baseUri:Ljava/lang/String;
       9: aload_0
      10: aload_2
      11: invokestatic  #7                  // Method org/apache/cxf/catalog/OASISCatalogManager.getCatalogManager:(Lorg/apache/cxf/Bus;)Lorg/apache/cxf/catalog/OASISCatalogManager;
      14: putfield      #6                  // Field manager:Lorg/apache/cxf/catalog/OASISCatalogManager;
      17: aload_0
      18: new           #8                  // class org/apache/cxf/transport/TransportURIResolver
      21: dup
      22: aload_2
      23: invokespecial #9                  // Method org/apache/cxf/transport/TransportURIResolver."<init>":(Lorg/apache/cxf/Bus;)V
      26: putfield      #5                  // Field resolver:Lorg/apache/cxf/resource/ExtendedURIResolver;
      29: return

  public org.xml.sax.InputSource getBaseInputSource();
    Code:
       0: aconst_null
       1: astore_1
       2: aload_0
       3: getfield      #6                  // Field manager:Lorg/apache/cxf/catalog/OASISCatalogManager;
       6: ifnull        43
       9: aload_0
      10: getfield      #6                  // Field manager:Lorg/apache/cxf/catalog/OASISCatalogManager;
      13: aload_0
      14: getfield      #2                  // Field baseUri:Ljava/lang/String;
      17: invokevirtual #10                 // Method org/apache/cxf/catalog/OASISCatalogManager.resolveSystem:(Ljava/lang/String;)Ljava/lang/String;
      20: astore_2
      21: aload_2
      22: ifnull        35
      25: aload_0
      26: getfield      #5                  // Field resolver:Lorg/apache/cxf/resource/ExtendedURIResolver;
      29: aload_2
      30: aconst_null
      31: invokevirtual #11                 // Method org/apache/cxf/resource/ExtendedURIResolver.resolve:(Ljava/lang/String;Ljava/lang/String;)Lorg/xml/sax/InputSource;
      34: astore_1
      35: goto          43
      38: astore_2
      39: goto          43
      42: astore_2
      43: aload_1
      44: ifnonnull     60
      47: aload_0
      48: getfield      #5                  // Field resolver:Lorg/apache/cxf/resource/ExtendedURIResolver;
      51: aload_0
      52: getfield      #2                  // Field baseUri:Ljava/lang/String;
      55: aconst_null
      56: invokevirtual #11                 // Method org/apache/cxf/resource/ExtendedURIResolver.resolve:(Ljava/lang/String;Ljava/lang/String;)Lorg/xml/sax/InputSource;
      59: astore_1
      60: aload_0
      61: getfield      #14                 // Field wsdlUrl:Ljava/lang/String;
      64: ifnonnull     79
      67: aload_1
      68: ifnull        79
      71: aload_0
      72: aload_1
      73: invokevirtual #15                 // Method org/xml/sax/InputSource.getSystemId:()Ljava/lang/String;
      76: putfield      #14                 // Field wsdlUrl:Ljava/lang/String;
      79: aload_0
      80: aload_0
      81: getfield      #5                  // Field resolver:Lorg/apache/cxf/resource/ExtendedURIResolver;
      84: invokevirtual #16                 // Method org/apache/cxf/resource/ExtendedURIResolver.getURI:()Ljava/lang/String;
      87: putfield      #2                  // Field baseUri:Ljava/lang/String;
      90: aload_1
      91: areturn
    Exception table:
       from    to  target type
           9    35    38   Class java/net/MalformedURLException
           9    35    42   Class java/io/IOException

  public java.lang.String getBaseURI();
    Code:
       0: aload_0
       1: getfield      #14                 // Field wsdlUrl:Ljava/lang/String;
       4: ifnonnull     30
       7: aload_0
       8: invokevirtual #17                 // Method getBaseInputSource:()Lorg/xml/sax/InputSource;
      11: astore_1
      12: aload_1
      13: invokevirtual #18                 // Method org/xml/sax/InputSource.getByteStream:()Ljava/io/InputStream;
      16: ifnull        30
      19: aload_1
      20: invokevirtual #18                 // Method org/xml/sax/InputSource.getByteStream:()Ljava/io/InputStream;
      23: invokevirtual #19                 // Method java/io/InputStream.close:()V
      26: goto          30
      29: astore_2
      30: aload_0
      31: getfield      #14                 // Field wsdlUrl:Ljava/lang/String;
      34: areturn
    Exception table:
       from    to  target type
          19    26    29   Class java/io/IOException

  public java.lang.String getLatestImportURI();
    Code:
       0: aload_0
       1: getfield      #5                  // Field resolver:Lorg/apache/cxf/resource/ExtendedURIResolver;
       4: invokevirtual #20                 // Method org/apache/cxf/resource/ExtendedURIResolver.getLatestImportURI:()Ljava/lang/String;
       7: areturn

  public org.xml.sax.InputSource getImportInputSource(java.lang.String, java.lang.String);
    Code:
       0: aconst_null
       1: astore_3
       2: new           #21                 // class org/apache/cxf/catalog/OASISCatalogManagerHelper
       5: dup
       6: invokespecial #22                 // Method org/apache/cxf/catalog/OASISCatalogManagerHelper."<init>":()V
       9: aload_0
      10: getfield      #6                  // Field manager:Lorg/apache/cxf/catalog/OASISCatalogManager;
      13: aload_2
      14: aload_1
      15: invokevirtual #23                 // Method org/apache/cxf/catalog/OASISCatalogManagerHelper.resolve:(Lorg/apache/cxf/catalog/OASISCatalogManager;Ljava/lang/String;Ljava/lang/String;)Ljava/lang/String;
      18: astore_3
      19: goto          36
      22: astore        4
      24: new           #24                 // class java/lang/RuntimeException
      27: dup
      28: ldc           #25                 // String Catalog resolution failed
      30: aload         4
      32: invokespecial #26                 // Method java/lang/RuntimeException."<init>":(Ljava/lang/String;Ljava/lang/Throwable;)V
      35: athrow
      36: aconst_null
      37: astore        4
      39: aload_3
      40: ifnonnull     57
      43: aload_0
      44: getfield      #5                  // Field resolver:Lorg/apache/cxf/resource/ExtendedURIResolver;
      47: aload_2
      48: aload_1
      49: invokevirtual #11                 // Method org/apache/cxf/resource/ExtendedURIResolver.resolve:(Ljava/lang/String;Ljava/lang/String;)Lorg/xml/sax/InputSource;
      52: astore        4
      54: goto          68
      57: aload_0
      58: getfield      #5                  // Field resolver:Lorg/apache/cxf/resource/ExtendedURIResolver;
      61: aload_3
      62: aconst_null
      63: invokevirtual #11                 // Method org/apache/cxf/resource/ExtendedURIResolver.resolve:(Ljava/lang/String;Ljava/lang/String;)Lorg/xml/sax/InputSource;
      66: astore        4
      68: aload         4
      70: ifnonnull     82
      73: new           #27                 // class org/xml/sax/InputSource
      76: dup
      77: invokespecial #28                 // Method org/xml/sax/InputSource."<init>":()V
      80: astore        4
      82: aload         4
      84: areturn
    Exception table:
       from    to  target type
           2    19    22   Class java/io/IOException

  public void close();
    Code:
       0: aload_0
       1: getfield      #5                  // Field resolver:Lorg/apache/cxf/resource/ExtendedURIResolver;
       4: invokevirtual #29                 // Method org/apache/cxf/resource/ExtendedURIResolver.close:()V
       7: return
}
