Compiled from "AbstractRequestExpectationManager.java"
public abstract class org.springframework.test.web.client.AbstractRequestExpectationManager implements org.springframework.test.web.client.RequestExpectationManager {
  private final java.util.List<org.springframework.test.web.client.RequestExpectation> expectations;

  private final java.util.List<org.springframework.http.client.ClientHttpRequest> requests;

  public org.springframework.test.web.client.AbstractRequestExpectationManager();
    Code:
       0: aload_0
       1: invokespecial #1                  // Method java/lang/Object."<init>":()V
       4: aload_0
       5: new           #2                  // class java/util/LinkedList
       8: dup
       9: invokespecial #3                  // Method java/util/LinkedList."<init>":()V
      12: putfield      #4                  // Field expectations:Ljava/util/List;
      15: aload_0
      16: new           #2                  // class java/util/LinkedList
      19: dup
      20: invokespecial #3                  // Method java/util/LinkedList."<init>":()V
      23: putfield      #5                  // Field requests:Ljava/util/List;
      26: return

  protected java.util.List<org.springframework.test.web.client.RequestExpectation> getExpectations();
    Code:
       0: aload_0
       1: getfield      #4                  // Field expectations:Ljava/util/List;
       4: invokestatic  #6                  // Method java/util/Collections.unmodifiableList:(Ljava/util/List;)Ljava/util/List;
       7: areturn

  protected java.util.List<org.springframework.http.client.ClientHttpRequest> getRequests();
    Code:
       0: aload_0
       1: getfield      #5                  // Field requests:Ljava/util/List;
       4: invokestatic  #6                  // Method java/util/Collections.unmodifiableList:(Ljava/util/List;)Ljava/util/List;
       7: areturn

  public org.springframework.test.web.client.ResponseActions expectRequest(org.springframework.test.web.client.ExpectedCount, org.springframework.test.web.client.RequestMatcher);
    Code:
       0: aload_0
       1: getfield      #5                  // Field requests:Ljava/util/List;
       4: invokeinterface #7,  1            // InterfaceMethod java/util/List.isEmpty:()Z
       9: ldc           #8                  // String Cannot add more expectations after actual requests are made
      11: invokestatic  #9                  // Method org/springframework/util/Assert.state:(ZLjava/lang/String;)V
      14: new           #10                 // class org/springframework/test/web/client/DefaultRequestExpectation
      17: dup
      18: aload_1
      19: aload_2
      20: invokespecial #11                 // Method org/springframework/test/web/client/DefaultRequestExpectation."<init>":(Lorg/springframework/test/web/client/ExpectedCount;Lorg/springframework/test/web/client/RequestMatcher;)V
      23: astore_3
      24: aload_0
      25: getfield      #4                  // Field expectations:Ljava/util/List;
      28: aload_3
      29: invokeinterface #12,  2           // InterfaceMethod java/util/List.add:(Ljava/lang/Object;)Z
      34: pop
      35: aload_3
      36: areturn

  public org.springframework.http.client.ClientHttpResponse validateRequest(org.springframework.http.client.ClientHttpRequest) throws java.io.IOException;
    Code:
       0: aconst_null
       1: astore_2
       2: aload_0
       3: getfield      #5                  // Field requests:Ljava/util/List;
       6: dup
       7: astore_3
       8: monitorenter
       9: aload_0
      10: getfield      #5                  // Field requests:Ljava/util/List;
      13: invokeinterface #7,  1            // InterfaceMethod java/util/List.isEmpty:()Z
      18: ifeq          25
      21: aload_0
      22: invokevirtual #13                 // Method afterExpectationsDeclared:()V
      25: aload_0
      26: aload_1
      27: invokevirtual #14                 // Method validateRequestInternal:(Lorg/springframework/http/client/ClientHttpRequest;)Lorg/springframework/http/client/ClientHttpResponse;
      30: astore        4
      32: aload         4
      34: ifnull        57
      37: aload         4
      39: astore        5
      41: aload_0
      42: getfield      #5                  // Field requests:Ljava/util/List;
      45: aload_1
      46: invokeinterface #12,  2           // InterfaceMethod java/util/List.add:(Ljava/lang/Object;)Z
      51: pop
      52: aload_3
      53: monitorexit
      54: aload         5
      56: areturn
      57: aload_0
      58: aload_1
      59: invokevirtual #15                 // Method matchRequest:(Lorg/springframework/http/client/ClientHttpRequest;)Lorg/springframework/test/web/client/RequestExpectation;
      62: astore_2
      63: aload_0
      64: getfield      #5                  // Field requests:Ljava/util/List;
      67: aload_1
      68: invokeinterface #12,  2           // InterfaceMethod java/util/List.add:(Ljava/lang/Object;)Z
      73: pop
      74: goto          93
      77: astore        6
      79: aload_0
      80: getfield      #5                  // Field requests:Ljava/util/List;
      83: aload_1
      84: invokeinterface #12,  2           // InterfaceMethod java/util/List.add:(Ljava/lang/Object;)Z
      89: pop
      90: aload         6
      92: athrow
      93: aload_3
      94: monitorexit
      95: goto          105
      98: astore        7
     100: aload_3
     101: monitorexit
     102: aload         7
     104: athrow
     105: aload_2
     106: aload_1
     107: invokeinterface #16,  2           // InterfaceMethod org/springframework/test/web/client/RequestExpectation.createResponse:(Lorg/springframework/http/client/ClientHttpRequest;)Lorg/springframework/http/client/ClientHttpResponse;
     112: areturn
    Exception table:
       from    to  target type
          25    41    77   any
          57    63    77   any
          77    79    77   any
           9    54    98   any
          57    95    98   any
          98   102    98   any

  protected void afterExpectationsDeclared();
    Code:
       0: return

  protected org.springframework.http.client.ClientHttpResponse validateRequestInternal(org.springframework.http.client.ClientHttpRequest) throws java.io.IOException;
    Code:
       0: aconst_null
       1: areturn

  protected org.springframework.test.web.client.RequestExpectation matchRequest(org.springframework.http.client.ClientHttpRequest) throws java.io.IOException;
    Code:
       0: new           #17                 // class java/lang/UnsupportedOperationException
       3: dup
       4: ldc           #18                 // String It looks like neither the deprecated \"validateRequestInternal\"nor its replacement (this method) are implemented.
       6: invokespecial #19                 // Method java/lang/UnsupportedOperationException."<init>":(Ljava/lang/String;)V
       9: athrow

  public void verify();
    Code:
       0: aload_0
       1: getfield      #4                  // Field expectations:Ljava/util/List;
       4: invokeinterface #7,  1            // InterfaceMethod java/util/List.isEmpty:()Z
       9: ifeq          13
      12: return
      13: iconst_0
      14: istore_1
      15: aload_0
      16: getfield      #4                  // Field expectations:Ljava/util/List;
      19: invokeinterface #20,  1           // InterfaceMethod java/util/List.iterator:()Ljava/util/Iterator;
      24: astore_2
      25: aload_2
      26: invokeinterface #21,  1           // InterfaceMethod java/util/Iterator.hasNext:()Z
      31: ifeq          59
      34: aload_2
      35: invokeinterface #22,  1           // InterfaceMethod java/util/Iterator.next:()Ljava/lang/Object;
      40: checkcast     #23                 // class org/springframework/test/web/client/RequestExpectation
      43: astore_3
      44: aload_3
      45: invokeinterface #24,  1           // InterfaceMethod org/springframework/test/web/client/RequestExpectation.isSatisfied:()Z
      50: ifne          56
      53: iinc          1, 1
      56: goto          25
      59: iload_1
      60: ifle          117
      63: new           #25                 // class java/lang/StringBuilder
      66: dup
      67: invokespecial #26                 // Method java/lang/StringBuilder."<init>":()V
      70: ldc           #27                 // String Further request(s) expected leaving
      72: invokevirtual #28                 // Method java/lang/StringBuilder.append:(Ljava/lang/String;)Ljava/lang/StringBuilder;
      75: iload_1
      76: invokevirtual #29                 // Method java/lang/StringBuilder.append:(I)Ljava/lang/StringBuilder;
      79: ldc           #30                 // String  unsatisfied expectation(s).\n
      81: invokevirtual #28                 // Method java/lang/StringBuilder.append:(Ljava/lang/String;)Ljava/lang/StringBuilder;
      84: invokevirtual #31                 // Method java/lang/StringBuilder.toString:()Ljava/lang/String;
      87: astore_2
      88: new           #32                 // class java/lang/AssertionError
      91: dup
      92: new           #25                 // class java/lang/StringBuilder
      95: dup
      96: invokespecial #26                 // Method java/lang/StringBuilder."<init>":()V
      99: aload_2
     100: invokevirtual #28                 // Method java/lang/StringBuilder.append:(Ljava/lang/String;)Ljava/lang/StringBuilder;
     103: aload_0
     104: invokevirtual #33                 // Method getRequestDetails:()Ljava/lang/String;
     107: invokevirtual #28                 // Method java/lang/StringBuilder.append:(Ljava/lang/String;)Ljava/lang/StringBuilder;
     110: invokevirtual #31                 // Method java/lang/StringBuilder.toString:()Ljava/lang/String;
     113: invokespecial #34                 // Method java/lang/AssertionError."<init>":(Ljava/lang/Object;)V
     116: athrow
     117: return

  protected java.lang.String getRequestDetails();
    Code:
       0: new           #25                 // class java/lang/StringBuilder
       3: dup
       4: invokespecial #26                 // Method java/lang/StringBuilder."<init>":()V
       7: astore_1
       8: aload_1
       9: aload_0
      10: getfield      #5                  // Field requests:Ljava/util/List;
      13: invokeinterface #35,  1           // InterfaceMethod java/util/List.size:()I
      18: invokevirtual #29                 // Method java/lang/StringBuilder.append:(I)Ljava/lang/StringBuilder;
      21: ldc           #36                 // String  request(s) executed
      23: invokevirtual #28                 // Method java/lang/StringBuilder.append:(Ljava/lang/String;)Ljava/lang/StringBuilder;
      26: pop
      27: aload_0
      28: getfield      #5                  // Field requests:Ljava/util/List;
      31: invokeinterface #7,  1            // InterfaceMethod java/util/List.isEmpty:()Z
      36: ifne          95
      39: aload_1
      40: ldc           #37                 // String :\n
      42: invokevirtual #28                 // Method java/lang/StringBuilder.append:(Ljava/lang/String;)Ljava/lang/StringBuilder;
      45: pop
      46: aload_0
      47: getfield      #5                  // Field requests:Ljava/util/List;
      50: invokeinterface #20,  1           // InterfaceMethod java/util/List.iterator:()Ljava/util/Iterator;
      55: astore_2
      56: aload_2
      57: invokeinterface #21,  1           // InterfaceMethod java/util/Iterator.hasNext:()Z
      62: ifeq          92
      65: aload_2
      66: invokeinterface #22,  1           // InterfaceMethod java/util/Iterator.next:()Ljava/lang/Object;
      71: checkcast     #38                 // class org/springframework/http/client/ClientHttpRequest
      74: astore_3
      75: aload_1
      76: aload_3
      77: invokevirtual #39                 // Method java/lang/Object.toString:()Ljava/lang/String;
      80: invokevirtual #28                 // Method java/lang/StringBuilder.append:(Ljava/lang/String;)Ljava/lang/StringBuilder;
      83: ldc           #40                 // String \n
      85: invokevirtual #28                 // Method java/lang/StringBuilder.append:(Ljava/lang/String;)Ljava/lang/StringBuilder;
      88: pop
      89: goto          56
      92: goto          102
      95: aload_1
      96: ldc           #41                 // String .\n
      98: invokevirtual #28                 // Method java/lang/StringBuilder.append:(Ljava/lang/String;)Ljava/lang/StringBuilder;
     101: pop
     102: aload_1
     103: invokevirtual #31                 // Method java/lang/StringBuilder.toString:()Ljava/lang/String;
     106: areturn

  protected java.lang.AssertionError createUnexpectedRequestError(org.springframework.http.client.ClientHttpRequest);
    Code:
       0: aload_1
       1: invokeinterface #42,  1           // InterfaceMethod org/springframework/http/client/ClientHttpRequest.getMethod:()Lorg/springframework/http/HttpMethod;
       6: astore_2
       7: aload_1
       8: invokeinterface #43,  1           // InterfaceMethod org/springframework/http/client/ClientHttpRequest.getURI:()Ljava/net/URI;
      13: astore_3
      14: new           #25                 // class java/lang/StringBuilder
      17: dup
      18: invokespecial #26                 // Method java/lang/StringBuilder."<init>":()V
      21: ldc           #44                 // String No further requests expected: HTTP
      23: invokevirtual #28                 // Method java/lang/StringBuilder.append:(Ljava/lang/String;)Ljava/lang/StringBuilder;
      26: aload_2
      27: invokevirtual #45                 // Method java/lang/StringBuilder.append:(Ljava/lang/Object;)Ljava/lang/StringBuilder;
      30: ldc           #46                 // String
      32: invokevirtual #28                 // Method java/lang/StringBuilder.append:(Ljava/lang/String;)Ljava/lang/StringBuilder;
      35: aload_3
      36: invokevirtual #45                 // Method java/lang/StringBuilder.append:(Ljava/lang/Object;)Ljava/lang/StringBuilder;
      39: ldc           #40                 // String \n
      41: invokevirtual #28                 // Method java/lang/StringBuilder.append:(Ljava/lang/String;)Ljava/lang/StringBuilder;
      44: invokevirtual #31                 // Method java/lang/StringBuilder.toString:()Ljava/lang/String;
      47: astore        4
      49: new           #32                 // class java/lang/AssertionError
      52: dup
      53: new           #25                 // class java/lang/StringBuilder
      56: dup
      57: invokespecial #26                 // Method java/lang/StringBuilder."<init>":()V
      60: aload         4
      62: invokevirtual #28                 // Method java/lang/StringBuilder.append:(Ljava/lang/String;)Ljava/lang/StringBuilder;
      65: aload_0
      66: invokevirtual #33                 // Method getRequestDetails:()Ljava/lang/String;
      69: invokevirtual #28                 // Method java/lang/StringBuilder.append:(Ljava/lang/String;)Ljava/lang/StringBuilder;
      72: invokevirtual #31                 // Method java/lang/StringBuilder.toString:()Ljava/lang/String;
      75: invokespecial #34                 // Method java/lang/AssertionError."<init>":(Ljava/lang/Object;)V
      78: areturn

  public void reset();
    Code:
       0: aload_0
       1: getfield      #4                  // Field expectations:Ljava/util/List;
       4: invokeinterface #47,  1           // InterfaceMethod java/util/List.clear:()V
       9: aload_0
      10: getfield      #5                  // Field requests:Ljava/util/List;
      13: invokeinterface #47,  1           // InterfaceMethod java/util/List.clear:()V
      18: return
}
