Compiled from "MockRestServiceServer.java"
class org.springframework.test.web.client.MockRestServiceServer$DefaultBuilder implements org.springframework.test.web.client.MockRestServiceServer$MockRestServiceServerBuilder {
  private final org.springframework.web.client.RestTemplate restTemplate;

  private final org.springframework.web.client.AsyncRestTemplate asyncRestTemplate;

  private boolean ignoreExpectOrder;

  private boolean bufferContent;

  public org.springframework.test.web.client.MockRestServiceServer$DefaultBuilder(org.springframework.web.client.RestTemplate);
    Code:
       0: aload_0
       1: invokespecial #1                  // Method java/lang/Object."<init>":()V
       4: aload_1
       5: ldc           #2                  // String RestTemplate must not be null
       7: invokestatic  #3                  // Method org/springframework/util/Assert.notNull:(Ljava/lang/Object;Ljava/lang/String;)V
      10: aload_0
      11: aload_1
      12: putfield      #4                  // Field restTemplate:Lorg/springframework/web/client/RestTemplate;
      15: aload_0
      16: aconst_null
      17: putfield      #5                  // Field asyncRestTemplate:Lorg/springframework/web/client/AsyncRestTemplate;
      20: return

  public org.springframework.test.web.client.MockRestServiceServer$DefaultBuilder(org.springframework.web.client.AsyncRestTemplate);
    Code:
       0: aload_0
       1: invokespecial #1                  // Method java/lang/Object."<init>":()V
       4: aload_1
       5: ldc           #6                  // String AsyncRestTemplate must not be null
       7: invokestatic  #3                  // Method org/springframework/util/Assert.notNull:(Ljava/lang/Object;Ljava/lang/String;)V
      10: aload_0
      11: aconst_null
      12: putfield      #4                  // Field restTemplate:Lorg/springframework/web/client/RestTemplate;
      15: aload_0
      16: aload_1
      17: putfield      #5                  // Field asyncRestTemplate:Lorg/springframework/web/client/AsyncRestTemplate;
      20: return

  public org.springframework.test.web.client.MockRestServiceServer$MockRestServiceServerBuilder ignoreExpectOrder(boolean);
    Code:
       0: aload_0
       1: iload_1
       2: putfield      #7                  // Field ignoreExpectOrder:Z
       5: aload_0
       6: areturn

  public org.springframework.test.web.client.MockRestServiceServer$MockRestServiceServerBuilder bufferContent();
    Code:
       0: aload_0
       1: iconst_1
       2: putfield      #8                  // Field bufferContent:Z
       5: aload_0
       6: areturn

  public org.springframework.test.web.client.MockRestServiceServer build();
    Code:
       0: aload_0
       1: getfield      #7                  // Field ignoreExpectOrder:Z
       4: ifeq          19
       7: aload_0
       8: new           #9                  // class org/springframework/test/web/client/UnorderedRequestExpectationManager
      11: dup
      12: invokespecial #10                 // Method org/springframework/test/web/client/UnorderedRequestExpectationManager."<init>":()V
      15: invokevirtual #11                 // Method build:(Lorg/springframework/test/web/client/RequestExpectationManager;)Lorg/springframework/test/web/client/MockRestServiceServer;
      18: areturn
      19: aload_0
      20: new           #12                 // class org/springframework/test/web/client/SimpleRequestExpectationManager
      23: dup
      24: invokespecial #13                 // Method org/springframework/test/web/client/SimpleRequestExpectationManager."<init>":()V
      27: invokevirtual #11                 // Method build:(Lorg/springframework/test/web/client/RequestExpectationManager;)Lorg/springframework/test/web/client/MockRestServiceServer;
      30: areturn

  public org.springframework.test.web.client.MockRestServiceServer build(org.springframework.test.web.client.RequestExpectationManager);
    Code:
       0: new           #14                 // class org/springframework/test/web/client/MockRestServiceServer
       3: dup
       4: aload_1
       5: aconst_null
       6: invokespecial #15                 // Method org/springframework/test/web/client/MockRestServiceServer."<init>":(Lorg/springframework/test/web/client/RequestExpectationManager;Lorg/springframework/test/web/client/MockRestServiceServer$1;)V
       9: astore_2
      10: new           #16                 // class org/springframework/test/web/client/MockRestServiceServer$MockClientHttpRequestFactory
      13: dup
      14: aload_2
      15: dup
      16: invokevirtual #17                 // Method java/lang/Object.getClass:()Ljava/lang/Class;
      19: pop
      20: aconst_null
      21: invokespecial #18                 // Method org/springframework/test/web/client/MockRestServiceServer$MockClientHttpRequestFactory."<init>":(Lorg/springframework/test/web/client/MockRestServiceServer;Lorg/springframework/test/web/client/MockRestServiceServer$1;)V
      24: astore_3
      25: aload_0
      26: getfield      #4                  // Field restTemplate:Lorg/springframework/web/client/RestTemplate;
      29: ifnull        65
      32: aload_0
      33: getfield      #8                  // Field bufferContent:Z
      36: ifeq          57
      39: aload_0
      40: getfield      #4                  // Field restTemplate:Lorg/springframework/web/client/RestTemplate;
      43: new           #19                 // class org/springframework/http/client/BufferingClientHttpRequestFactory
      46: dup
      47: aload_3
      48: invokespecial #20                 // Method org/springframework/http/client/BufferingClientHttpRequestFactory."<init>":(Lorg/springframework/http/client/ClientHttpRequestFactory;)V
      51: invokevirtual #21                 // Method org/springframework/web/client/RestTemplate.setRequestFactory:(Lorg/springframework/http/client/ClientHttpRequestFactory;)V
      54: goto          65
      57: aload_0
      58: getfield      #4                  // Field restTemplate:Lorg/springframework/web/client/RestTemplate;
      61: aload_3
      62: invokevirtual #21                 // Method org/springframework/web/client/RestTemplate.setRequestFactory:(Lorg/springframework/http/client/ClientHttpRequestFactory;)V
      65: aload_0
      66: getfield      #5                  // Field asyncRestTemplate:Lorg/springframework/web/client/AsyncRestTemplate;
      69: ifnull        80
      72: aload_0
      73: getfield      #5                  // Field asyncRestTemplate:Lorg/springframework/web/client/AsyncRestTemplate;
      76: aload_3
      77: invokevirtual #22                 // Method org/springframework/web/client/AsyncRestTemplate.setAsyncRequestFactory:(Lorg/springframework/http/client/AsyncClientHttpRequestFactory;)V
      80: aload_2
      81: areturn
}
