Compiled from "ProtobufJsonFormatHttpMessageConverter.java"
public class org.springframework.http.converter.protobuf.ProtobufJsonFormatHttpMessageConverter extends org.springframework.http.converter.protobuf.ProtobufHttpMessageConverter {
  public org.springframework.http.converter.protobuf.ProtobufJsonFormatHttpMessageConverter();
    Code:
       0: aload_0
       1: aconst_null
       2: aconst_null
       3: aconst_null
       4: invokespecial #1                  // Method "<init>":(Lcom/google/protobuf/util/JsonFormat$Parser;Lcom/google/protobuf/util/JsonFormat$Printer;Lorg/springframework/http/converter/protobuf/ExtensionRegistryInitializer;)V
       7: return

  public org.springframework.http.converter.protobuf.ProtobufJsonFormatHttpMessageConverter(com.google.protobuf.util.JsonFormat$Parser, com.google.protobuf.util.JsonFormat$Printer);
    Code:
       0: aload_0
       1: aload_1
       2: aload_2
       3: aconst_null
       4: invokespecial #1                  // Method "<init>":(Lcom/google/protobuf/util/JsonFormat$Parser;Lcom/google/protobuf/util/JsonFormat$Printer;Lorg/springframework/http/converter/protobuf/ExtensionRegistryInitializer;)V
       7: return

  public org.springframework.http.converter.protobuf.ProtobufJsonFormatHttpMessageConverter(com.google.protobuf.util.JsonFormat$Parser, com.google.protobuf.util.JsonFormat$Printer, org.springframework.http.converter.protobuf.ExtensionRegistryInitializer);
    Code:
       0: aload_0
       1: new           #2                  // class org/springframework/http/converter/protobuf/ProtobufHttpMessageConverter$ProtobufJavaUtilSupport
       4: dup
       5: aload_1
       6: aload_2
       7: invokespecial #3                  // Method org/springframework/http/converter/protobuf/ProtobufHttpMessageConverter$ProtobufJavaUtilSupport."<init>":(Lcom/google/protobuf/util/JsonFormat$Parser;Lcom/google/protobuf/util/JsonFormat$Printer;)V
      10: aload_3
      11: invokespecial #4                  // Method org/springframework/http/converter/protobuf/ProtobufHttpMessageConverter."<init>":(Lorg/springframework/http/converter/protobuf/ProtobufHttpMessageConverter$ProtobufFormatSupport;Lorg/springframework/http/converter/protobuf/ExtensionRegistryInitializer;)V
      14: return
}
