class org.bouncycastle.pqc.crypto.ntru.NTRUSigningKeyPairGenerator$BasisGenerationTask implements java.util.concurrent.Callable<org.bouncycastle.pqc.crypto.ntru.NTRUSigningPrivateKeyParameters$Basis> {
  final org.bouncycastle.pqc.crypto.ntru.NTRUSigningKeyPairGenerator this$0;

  private org.bouncycastle.pqc.crypto.ntru.NTRUSigningKeyPairGenerator$BasisGenerationTask(org.bouncycastle.pqc.crypto.ntru.NTRUSigningKeyPairGenerator);
    Code:
       0: aload_0
       1: aload_1
       2: putfield      #34                 // Field this$0:Lorg/bouncycastle/pqc/crypto/ntru/NTRUSigningKeyPairGenerator;
       5: aload_0
       6: invokespecial #35                 // Method java/lang/Object."<init>":()V
       9: return

  public org.bouncycastle.pqc.crypto.ntru.NTRUSigningPrivateKeyParameters$Basis call() throws java.lang.Exception;
    Code:
       0: aload_0
       1: getfield      #34                 // Field this$0:Lorg/bouncycastle/pqc/crypto/ntru/NTRUSigningKeyPairGenerator;
       4: invokevirtual #36                 // Method org/bouncycastle/pqc/crypto/ntru/NTRUSigningKeyPairGenerator.generateBoundedBasis:()Lorg/bouncycastle/pqc/crypto/ntru/NTRUSigningPrivateKeyParameters$Basis;
       7: areturn

  public java.lang.Object call() throws java.lang.Exception;
    Code:
       0: aload_0
       1: invokevirtual #38                 // Method call:()Lorg/bouncycastle/pqc/crypto/ntru/NTRUSigningPrivateKeyParameters$Basis;
       4: areturn

  org.bouncycastle.pqc.crypto.ntru.NTRUSigningKeyPairGenerator$BasisGenerationTask(org.bouncycastle.pqc.crypto.ntru.NTRUSigningKeyPairGenerator, org.bouncycastle.pqc.crypto.ntru.NTRUSigningKeyPairGenerator$1);
    Code:
       0: aload_0
       1: aload_1
       2: invokespecial #37                 // Method "<init>":(Lorg/bouncycastle/pqc/crypto/ntru/NTRUSigningKeyPairGenerator;)V
       5: return
}
