Compiled from "StagingWorkflowV3ServiceImpl.java"
public class com.sonatype.nexus.staging.client.internal.StagingWorkflowV3ServiceImpl extends com.sonatype.nexus.staging.client.internal.StagingWorkflowV2ServiceImpl implements com.sonatype.nexus.staging.client.StagingWorkflowV3Service {
  private final com.sonatype.nexus.staging.client.StagingWorkflowV3Service$ProgressMonitor defaultProgressMonitor;

  private com.sonatype.nexus.staging.client.StagingWorkflowV3Service$ProgressMonitor progressMonitor;

  private int progressTimeoutMinutes;

  private int progressPauseDurationSeconds;

  private static final java.lang.String RULE_FAILED_EVENT_NAME;

  public com.sonatype.nexus.staging.client.internal.StagingWorkflowV3ServiceImpl(org.sonatype.nexus.client.rest.jersey.JerseyNexusClient);
    Code:
       0: aload_0
       1: aload_1
       2: invokespecial #1                  // Method com/sonatype/nexus/staging/client/internal/StagingWorkflowV2ServiceImpl."<init>":(Lorg/sonatype/nexus/client/rest/jersey/JerseyNexusClient;)V
       5: aload_0
       6: new           #2                  // class com/sonatype/nexus/staging/client/internal/StagingWorkflowV3ServiceImpl$2
       9: dup
      10: aload_0
      11: invokespecial #3                  // Method com/sonatype/nexus/staging/client/internal/StagingWorkflowV3ServiceImpl$2."<init>":(Lcom/sonatype/nexus/staging/client/internal/StagingWorkflowV3ServiceImpl;)V
      14: putfield      #4                  // Field defaultProgressMonitor:Lcom/sonatype/nexus/staging/client/StagingWorkflowV3Service$ProgressMonitor;
      17: aload_0
      18: aload_0
      19: getfield      #4                  // Field defaultProgressMonitor:Lcom/sonatype/nexus/staging/client/StagingWorkflowV3Service$ProgressMonitor;
      22: putfield      #5                  // Field progressMonitor:Lcom/sonatype/nexus/staging/client/StagingWorkflowV3Service$ProgressMonitor;
      25: aload_0
      26: iconst_5
      27: putfield      #6                  // Field progressTimeoutMinutes:I
      30: aload_0
      31: iconst_3
      32: putfield      #7                  // Field progressPauseDurationSeconds:I
      35: return

  protected com.sonatype.nexus.staging.client.StagingRepository$State stateOf(com.sonatype.nexus.staging.api.dto.StagingProfileRepositoryDTO);
    Code:
       0: aload_1
       1: invokevirtual #8                  // Method com/sonatype/nexus/staging/api/dto/StagingProfileRepositoryDTO.getType:()Ljava/lang/String;
       4: astore_2
       5: ldc           #9                  // String released
       7: aload_2
       8: invokevirtual #10                 // Method java/lang/String.equals:(Ljava/lang/Object;)Z
      11: ifeq          18
      14: getstatic     #11                 // Field com/sonatype/nexus/staging/client/StagingRepository$State.RELEASED:Lcom/sonatype/nexus/staging/client/StagingRepository$State;
      17: areturn
      18: aload_0
      19: aload_1
      20: invokespecial #12                 // Method com/sonatype/nexus/staging/client/internal/StagingWorkflowV2ServiceImpl.stateOf:(Lcom/sonatype/nexus/staging/api/dto/StagingProfileRepositoryDTO;)Lcom/sonatype/nexus/staging/client/StagingRepository$State;
      23: areturn

  public com.sonatype.nexus.staging.api.dto.StagingProfileRepositoryDTO findRepository(java.lang.String);
    Code:
       0: new           #13                 // class com/sonatype/nexus/staging/client/internal/StagingWorkflowV3ServiceImpl$1
       3: dup
       4: aload_0
       5: aload_0
       6: aload_1
       7: invokespecial #14                 // Method com/sonatype/nexus/staging/client/internal/StagingWorkflowV3ServiceImpl$1."<init>":(Lcom/sonatype/nexus/staging/client/internal/StagingWorkflowV3ServiceImpl;Lcom/sonatype/nexus/staging/client/internal/StagingWorkflowV2ServiceImpl;Ljava/lang/String;)V
      10: invokevirtual #15                 // Method com/sonatype/nexus/staging/client/internal/StagingWorkflowV3ServiceImpl$1.runAndReturn:()Ljava/lang/Object;
      13: checkcast     #16                 // class com/sonatype/nexus/staging/api/dto/StagingProfileRepositoryDTO
      16: areturn

  public void releaseStagingRepositories(com.sonatype.nexus.staging.api.dto.StagingActionDTO);
    Code:
       0: aload_0
       1: aload_1
       2: invokespecial #17                 // Method com/sonatype/nexus/staging/client/internal/StagingWorkflowV2ServiceImpl.releaseStagingRepositories:(Lcom/sonatype/nexus/staging/api/dto/StagingActionDTO;)V
       5: return

  public void setProgressMonitor(com.sonatype.nexus.staging.client.StagingWorkflowV3Service$ProgressMonitor);
    Code:
       0: aload_1
       1: invokestatic  #18                 // Method com/google/common/base/Preconditions.checkNotNull:(Ljava/lang/Object;)Ljava/lang/Object;
       4: pop
       5: aload_0
       6: aload_1
       7: putfield      #5                  // Field progressMonitor:Lcom/sonatype/nexus/staging/client/StagingWorkflowV3Service$ProgressMonitor;
      10: return

  public void resetProgressMonitor();
    Code:
       0: aload_0
       1: aload_0
       2: getfield      #4                  // Field defaultProgressMonitor:Lcom/sonatype/nexus/staging/client/StagingWorkflowV3Service$ProgressMonitor;
       5: invokevirtual #19                 // Method setProgressMonitor:(Lcom/sonatype/nexus/staging/client/StagingWorkflowV3Service$ProgressMonitor;)V
       8: return

  public void setProgressTimeoutMinutes(int);
    Code:
       0: aload_0
       1: iload_1
       2: putfield      #6                  // Field progressTimeoutMinutes:I
       5: return

  public void setProgressPauseDurationSeconds(int);
    Code:
       0: iload_1
       1: iconst_1
       2: if_icmplt     9
       5: iconst_1
       6: goto          10
       9: iconst_0
      10: invokestatic  #20                 // Method com/google/common/base/Preconditions.checkArgument:(Z)V
      13: aload_0
      14: iload_1
      15: putfield      #7                  // Field progressPauseDurationSeconds:I
      18: return

  protected void monitorRepositoryTransition(com.sonatype.nexus.staging.client.internal.TransitioningListener, java.lang.String...);
    Code:
       0: aload_2
       1: invokestatic  #21                 // Method com/google/common/collect/Lists.newArrayList:([Ljava/lang/Object;)Ljava/util/ArrayList;
       4: astore_3
       5: aload_0
       6: getfield      #22                 // Field log:Lorg/slf4j/Logger;
       9: ldc           #23                 // String Monitoring transition of repositories: {}
      11: aload_2
      12: invokeinterface #24,  3           // InterfaceMethod org/slf4j/Logger.debug:(Ljava/lang/String;[Ljava/lang/Object;)V
      17: new           #25                 // class com/google/common/base/Stopwatch
      20: dup
      21: invokespecial #26                 // Method com/google/common/base/Stopwatch."<init>":()V
      24: astore        4
      26: aload         4
      28: invokevirtual #27                 // Method com/google/common/base/Stopwatch.start:()Lcom/google/common/base/Stopwatch;
      31: pop
      32: aload_0
      33: getfield      #5                  // Field progressMonitor:Lcom/sonatype/nexus/staging/client/StagingWorkflowV3Service$ProgressMonitor;
      36: invokeinterface #28,  1           // InterfaceMethod com/sonatype/nexus/staging/client/StagingWorkflowV3Service$ProgressMonitor.start:()V
      41: invokestatic  #29                 // Method com/google/common/collect/Lists.newArrayList:()Ljava/util/ArrayList;
      44: astore        5
      46: aload_3
      47: invokeinterface #30,  1           // InterfaceMethod java/util/List.isEmpty:()Z
      52: ifne          475
      55: aload_3
      56: invokeinterface #31,  1           // InterfaceMethod java/util/List.iterator:()Ljava/util/Iterator;
      61: astore        6
      63: aload         6
      65: invokeinterface #32,  1           // InterfaceMethod java/util/Iterator.hasNext:()Z
      70: ifeq          400
      73: aload_0
      74: getfield      #5                  // Field progressMonitor:Lcom/sonatype/nexus/staging/client/StagingWorkflowV3Service$ProgressMonitor;
      77: invokeinterface #33,  1           // InterfaceMethod com/sonatype/nexus/staging/client/StagingWorkflowV3Service$ProgressMonitor.tick:()V
      82: aload         4
      84: getstatic     #34                 // Field java/util/concurrent/TimeUnit.MINUTES:Ljava/util/concurrent/TimeUnit;
      87: invokevirtual #35                 // Method com/google/common/base/Stopwatch.elapsedTime:(Ljava/util/concurrent/TimeUnit;)J
      90: aload_0
      91: getfield      #6                  // Field progressTimeoutMinutes:I
      94: i2l
      95: lcmp
      96: iflt          138
      99: aload_0
     100: getfield      #22                 // Field log:Lorg/slf4j/Logger;
     103: ldc           #36                 // String Progress has timed out after: {}
     105: aload         4
     107: invokeinterface #37,  3           // InterfaceMethod org/slf4j/Logger.debug:(Ljava/lang/String;Ljava/lang/Object;)V
     112: aload_0
     113: getfield      #5                  // Field progressMonitor:Lcom/sonatype/nexus/staging/client/StagingWorkflowV3Service$ProgressMonitor;
     116: invokeinterface #38,  1           // InterfaceMethod com/sonatype/nexus/staging/client/StagingWorkflowV3Service$ProgressMonitor.timeout:()V
     121: new           #39                 // class com/sonatype/nexus/staging/client/StagingRuleFailuresException
     124: dup
     125: sipush        500
     128: ldc           #40                 // String Progress has timed-out
     130: aload         5
     132: ldc           #41                 // String
     134: invokespecial #42                 // Method com/sonatype/nexus/staging/client/StagingRuleFailuresException."<init>":(ILjava/lang/String;Ljava/util/Collection;Ljava/lang/String;)V
     137: athrow
     138: aload         6
     140: invokeinterface #43,  1           // InterfaceMethod java/util/Iterator.next:()Ljava/lang/Object;
     145: checkcast     #44                 // class java/lang/String
     148: astore        7
     150: aload_0
     151: getfield      #22                 // Field log:Lorg/slf4j/Logger;
     154: ldc           #45                 // String Checking repository: {}
     156: aload         7
     158: invokeinterface #37,  3           // InterfaceMethod org/slf4j/Logger.debug:(Ljava/lang/String;Ljava/lang/Object;)V
     163: aload_0
     164: aload         7
     166: invokevirtual #46                 // Method findRepository:(Ljava/lang/String;)Lcom/sonatype/nexus/staging/api/dto/StagingProfileRepositoryDTO;
     169: astore        8
     171: aload_0
     172: getfield      #22                 // Field log:Lorg/slf4j/Logger;
     175: ldc           #47                 // String Repository: {}
     177: aload         8
     179: invokeinterface #48,  3           // InterfaceMethod org/slf4j/Logger.trace:(Ljava/lang/String;Ljava/lang/Object;)V
     184: aload         8
     186: ifnonnull     249
     189: aload_0
     190: getfield      #22                 // Field log:Lorg/slf4j/Logger;
     193: ldc           #49                 // String Repository was removed; stop watching it
     195: invokeinterface #50,  2           // InterfaceMethod org/slf4j/Logger.debug:(Ljava/lang/String;)V
     200: aload         6
     202: invokeinterface #51,  1           // InterfaceMethod java/util/Iterator.remove:()V
     207: aload_1
     208: ifnull        217
     211: aload_1
     212: aload         7
     214: invokevirtual #52                 // Method com/sonatype/nexus/staging/client/internal/TransitioningListener.onRemoved:(Ljava/lang/String;)V
     217: aload_0
     218: getfield      #5                  // Field progressMonitor:Lcom/sonatype/nexus/staging/client/StagingWorkflowV3Service$ProgressMonitor;
     221: new           #53                 // class java/lang/StringBuilder
     224: dup
     225: invokespecial #54                 // Method java/lang/StringBuilder."<init>":()V
     228: aload         7
     230: invokevirtual #55                 // Method java/lang/StringBuilder.append:(Ljava/lang/String;)Ljava/lang/StringBuilder;
     233: ldc           #56                 // String  REMOVED
     235: invokevirtual #55                 // Method java/lang/StringBuilder.append:(Ljava/lang/String;)Ljava/lang/StringBuilder;
     238: invokevirtual #57                 // Method java/lang/StringBuilder.toString:()Ljava/lang/String;
     241: invokeinterface #58,  2           // InterfaceMethod com/sonatype/nexus/staging/client/StagingWorkflowV3Service$ProgressMonitor.info:(Ljava/lang/String;)V
     246: goto          397
     249: aload         8
     251: invokevirtual #59                 // Method com/sonatype/nexus/staging/api/dto/StagingProfileRepositoryDTO.isTransitioning:()Z
     254: ifne          397
     257: aload         6
     259: invokeinterface #51,  1           // InterfaceMethod java/util/Iterator.remove:()V
     264: aload         8
     266: invokevirtual #60                 // Method com/sonatype/nexus/staging/api/dto/StagingProfileRepositoryDTO.getNotifications:()I
     269: istore        9
     271: aload_0
     272: getfield      #22                 // Field log:Lorg/slf4j/Logger;
     275: ldc           #61                 // String Repository is no longer in transition; notifications: {}
     277: iload         9
     279: invokestatic  #62                 // Method java/lang/Integer.valueOf:(I)Ljava/lang/Integer;
     282: invokeinterface #37,  3           // InterfaceMethod org/slf4j/Logger.debug:(Ljava/lang/String;Ljava/lang/Object;)V
     287: iload         9
     289: ifeq          356
     292: aload_0
     293: getfield      #5                  // Field progressMonitor:Lcom/sonatype/nexus/staging/client/StagingWorkflowV3Service$ProgressMonitor;
     296: new           #53                 // class java/lang/StringBuilder
     299: dup
     300: invokespecial #54                 // Method java/lang/StringBuilder."<init>":()V
     303: aload         7
     305: invokevirtual #55                 // Method java/lang/StringBuilder.append:(Ljava/lang/String;)Ljava/lang/StringBuilder;
     308: ldc           #63                 // String  FAILED
     310: invokevirtual #55                 // Method java/lang/StringBuilder.append:(Ljava/lang/String;)Ljava/lang/StringBuilder;
     313: invokevirtual #57                 // Method java/lang/StringBuilder.toString:()Ljava/lang/String;
     316: invokeinterface #64,  2           // InterfaceMethod com/sonatype/nexus/staging/client/StagingWorkflowV3Service$ProgressMonitor.error:(Ljava/lang/String;)V
     321: aload_0
     322: aload         8
     324: invokespecial #65                 // Method collectRepositoryTransitionFailures:(Lcom/sonatype/nexus/staging/api/dto/StagingProfileRepositoryDTO;)Lcom/sonatype/nexus/staging/client/StagingRuleFailures;
     327: astore        10
     329: aload_1
     330: ifnull        343
     333: aload_1
     334: aload         7
     336: aload         8
     338: aload         10
     340: invokevirtual #66                 // Method com/sonatype/nexus/staging/client/internal/TransitioningListener.onTransitionedUnsuccessfully:(Ljava/lang/String;Lcom/sonatype/nexus/staging/api/dto/StagingProfileRepositoryDTO;Lcom/sonatype/nexus/staging/client/StagingRuleFailures;)V
     343: aload         5
     345: aload         10
     347: invokeinterface #67,  2           // InterfaceMethod java/util/List.add:(Ljava/lang/Object;)Z
     352: pop
     353: goto          397
     356: aload_0
     357: getfield      #5                  // Field progressMonitor:Lcom/sonatype/nexus/staging/client/StagingWorkflowV3Service$ProgressMonitor;
     360: new           #53                 // class java/lang/StringBuilder
     363: dup
     364: invokespecial #54                 // Method java/lang/StringBuilder."<init>":()V
     367: aload         7
     369: invokevirtual #55                 // Method java/lang/StringBuilder.append:(Ljava/lang/String;)Ljava/lang/StringBuilder;
     372: ldc           #68                 // String  OK
     374: invokevirtual #55                 // Method java/lang/StringBuilder.append:(Ljava/lang/String;)Ljava/lang/StringBuilder;
     377: invokevirtual #57                 // Method java/lang/StringBuilder.toString:()Ljava/lang/String;
     380: invokeinterface #58,  2           // InterfaceMethod com/sonatype/nexus/staging/client/StagingWorkflowV3Service$ProgressMonitor.info:(Ljava/lang/String;)V
     385: aload_1
     386: ifnull        397
     389: aload_1
     390: aload         7
     392: aload         8
     394: invokevirtual #69                 // Method com/sonatype/nexus/staging/client/internal/TransitioningListener.onTransitionedSuccessfully:(Ljava/lang/String;Lcom/sonatype/nexus/staging/api/dto/StagingProfileRepositoryDTO;)V
     397: goto          63
     400: aload_3
     401: invokeinterface #30,  1           // InterfaceMethod java/util/List.isEmpty:()Z
     406: ifne          472
     409: aload_0
     410: getfield      #5                  // Field progressMonitor:Lcom/sonatype/nexus/staging/client/StagingWorkflowV3Service$ProgressMonitor;
     413: invokeinterface #70,  1           // InterfaceMethod com/sonatype/nexus/staging/client/StagingWorkflowV3Service$ProgressMonitor.pause:()V
     418: aload_0
     419: getfield      #7                  // Field progressPauseDurationSeconds:I
     422: sipush        1000
     425: imul
     426: i2l
     427: invokestatic  #71                 // Method java/lang/Thread.sleep:(J)V
     430: goto          472
     433: astore        7
     435: aload_0
     436: getfield      #22                 // Field log:Lorg/slf4j/Logger;
     439: ldc           #73                 // String Progress interrupted
     441: invokeinterface #50,  2           // InterfaceMethod org/slf4j/Logger.debug:(Ljava/lang/String;)V
     446: aload_0
     447: getfield      #5                  // Field progressMonitor:Lcom/sonatype/nexus/staging/client/StagingWorkflowV3Service$ProgressMonitor;
     450: invokeinterface #74,  1           // InterfaceMethod com/sonatype/nexus/staging/client/StagingWorkflowV3Service$ProgressMonitor.interrupted:()V
     455: new           #39                 // class com/sonatype/nexus/staging/client/StagingRuleFailuresException
     458: dup
     459: sipush        500
     462: ldc           #73                 // String Progress interrupted
     464: aload         5
     466: ldc           #41                 // String
     468: invokespecial #42                 // Method com/sonatype/nexus/staging/client/StagingRuleFailuresException."<init>":(ILjava/lang/String;Ljava/util/Collection;Ljava/lang/String;)V
     471: athrow
     472: goto          46
     475: aload         5
     477: invokeinterface #30,  1           // InterfaceMethod java/util/List.isEmpty:()Z
     482: ifne          502
     485: new           #39                 // class com/sonatype/nexus/staging/client/StagingRuleFailuresException
     488: dup
     489: sipush        500
     492: ldc           #75                 // String Progress has failed with one or more errors
     494: aload         5
     496: ldc           #41                 // String
     498: invokespecial #42                 // Method com/sonatype/nexus/staging/client/StagingRuleFailuresException."<init>":(ILjava/lang/String;Ljava/util/Collection;Ljava/lang/String;)V
     501: athrow
     502: aload_0
     503: getfield      #5                  // Field progressMonitor:Lcom/sonatype/nexus/staging/client/StagingWorkflowV3Service$ProgressMonitor;
     506: invokeinterface #76,  1           // InterfaceMethod com/sonatype/nexus/staging/client/StagingWorkflowV3Service$ProgressMonitor.stop:()V
     511: aload         4
     513: invokevirtual #77                 // Method com/google/common/base/Stopwatch.stop:()Lcom/google/common/base/Stopwatch;
     516: pop
     517: goto          540
     520: astore        11
     522: aload_0
     523: getfield      #5                  // Field progressMonitor:Lcom/sonatype/nexus/staging/client/StagingWorkflowV3Service$ProgressMonitor;
     526: invokeinterface #76,  1           // InterfaceMethod com/sonatype/nexus/staging/client/StagingWorkflowV3Service$ProgressMonitor.stop:()V
     531: aload         4
     533: invokevirtual #77                 // Method com/google/common/base/Stopwatch.stop:()Lcom/google/common/base/Stopwatch;
     536: pop
     537: aload         11
     539: athrow
     540: return
    Exception table:
       from    to  target type
         418   430   433   Class java/lang/InterruptedException
          41   502   520   any
         520   522   520   any

  private com.sonatype.nexus.staging.client.StagingRuleFailures collectRepositoryTransitionFailures(com.sonatype.nexus.staging.api.dto.StagingProfileRepositoryDTO);
    Code:
       0: invokestatic  #29                 // Method com/google/common/collect/Lists.newArrayList:()Ljava/util/ArrayList;
       3: astore_2
       4: aload_0
       5: getfield      #22                 // Field log:Lorg/slf4j/Logger;
       8: ldc           #78                 // String Fetching activity for repository: {}
      10: aload_1
      11: invokevirtual #79                 // Method com/sonatype/nexus/staging/api/dto/StagingProfileRepositoryDTO.getRepositoryId:()Ljava/lang/String;
      14: invokeinterface #37,  3           // InterfaceMethod org/slf4j/Logger.debug:(Ljava/lang/String;Ljava/lang/Object;)V
      19: aload_0
      20: invokevirtual #80                 // Method getNexusClient:()Lorg/sonatype/nexus/client/core/NexusClient;
      23: checkcast     #81                 // class org/sonatype/nexus/client/rest/jersey/JerseyNexusClient
      26: ldc           #82                 // String staging/repository/%s/activity
      28: iconst_1
      29: anewarray     #83                 // class java/lang/Object
      32: dup
      33: iconst_0
      34: aload_1
      35: invokevirtual #79                 // Method com/sonatype/nexus/staging/api/dto/StagingProfileRepositoryDTO.getRepositoryId:()Ljava/lang/String;
      38: aastore
      39: invokestatic  #84                 // Method java/lang/String.format:(Ljava/lang/String;[Ljava/lang/Object;)Ljava/lang/String;
      42: invokevirtual #85                 // Method org/sonatype/nexus/client/rest/jersey/JerseyNexusClient.serviceResource:(Ljava/lang/String;)Lcom/sun/jersey/api/client/WebResource$Builder;
      45: ldc_w         #86                 // class com/sun/jersey/api/client/ClientResponse
      48: invokevirtual #87                 // Method com/sun/jersey/api/client/WebResource$Builder.get:(Ljava/lang/Class;)Ljava/lang/Object;
      51: checkcast     #86                 // class com/sun/jersey/api/client/ClientResponse
      54: astore_3
      55: aload_3
      56: invokevirtual #88                 // Method com/sun/jersey/api/client/ClientResponse.getClientResponseStatus:()Lcom/sun/jersey/api/client/ClientResponse$Status;
      59: getstatic     #89                 // Field com/sun/jersey/api/client/ClientResponse$Status.NOT_FOUND:Lcom/sun/jersey/api/client/ClientResponse$Status;
      62: if_acmpeq     69
      65: iconst_1
      66: goto          70
      69: iconst_0
      70: invokestatic  #90                 // Method com/google/common/base/Preconditions.checkState:(Z)V
      73: aload_3
      74: new           #91                 // class com/sonatype/nexus/staging/client/internal/StagingWorkflowV3ServiceImpl$3
      77: dup
      78: aload_0
      79: invokespecial #92                 // Method com/sonatype/nexus/staging/client/internal/StagingWorkflowV3ServiceImpl$3."<init>":(Lcom/sonatype/nexus/staging/client/internal/StagingWorkflowV3ServiceImpl;)V
      82: invokevirtual #93                 // Method com/sun/jersey/api/client/ClientResponse.getEntity:(Lcom/sun/jersey/api/client/GenericType;)Ljava/lang/Object;
      85: checkcast     #94                 // class java/util/List
      88: astore        4
      90: aload         4
      92: invokestatic  #18                 // Method com/google/common/base/Preconditions.checkNotNull:(Ljava/lang/Object;)Ljava/lang/Object;
      95: pop
      96: aload         4
      98: invokeinterface #30,  1           // InterfaceMethod java/util/List.isEmpty:()Z
     103: ifne          110
     106: iconst_1
     107: goto          111
     110: iconst_0
     111: invokestatic  #90                 // Method com/google/common/base/Preconditions.checkState:(Z)V
     114: aload         4
     116: aload         4
     118: invokeinterface #95,  1           // InterfaceMethod java/util/List.size:()I
     123: iconst_1
     124: isub
     125: invokeinterface #96,  2           // InterfaceMethod java/util/List.get:(I)Ljava/lang/Object;
     130: checkcast     #97                 // class com/sonatype/nexus/staging/api/dto/StagingActivityDTO
     133: astore        5
     135: iconst_0
     136: istore        6
     138: aload         5
     140: invokevirtual #98                 // Method com/sonatype/nexus/staging/api/dto/StagingActivityDTO.getEvents:()Ljava/util/List;
     143: invokeinterface #99,  1           // InterfaceMethod java/util/List.iterator:()Ljava/util/Iterator;
     148: astore        7
     150: aload         7
     152: invokeinterface #32,  1           // InterfaceMethod java/util/Iterator.hasNext:()Z
     157: ifeq          229
     160: aload         7
     162: invokeinterface #43,  1           // InterfaceMethod java/util/Iterator.next:()Ljava/lang/Object;
     167: checkcast     #100                // class com/sonatype/nexus/staging/api/dto/StagingActivityEventDTO
     170: astore        8
     172: aload         8
     174: invokevirtual #101                // Method com/sonatype/nexus/staging/api/dto/StagingActivityEventDTO.getSeverity:()I
     177: ifeq          183
     180: iinc          6, 1
     183: ldc           #102                // String ruleFailed
     185: aload         8
     187: invokevirtual #103                // Method com/sonatype/nexus/staging/api/dto/StagingActivityEventDTO.getName:()Ljava/lang/String;
     190: invokevirtual #10                 // Method java/lang/String.equals:(Ljava/lang/Object;)Z
     193: ifeq          226
     196: aload_2
     197: new           #104                // class com/sonatype/nexus/staging/client/StagingRuleFailures$RuleFailure
     200: dup
     201: aload_0
     202: aload         8
     204: ldc           #105                // String typeId
     206: invokespecial #106                // Method getActivityEventValue:(Lcom/sonatype/nexus/staging/api/dto/StagingActivityEventDTO;Ljava/lang/String;)Ljava/lang/String;
     209: aload_0
     210: aload         8
     212: ldc           #107                // String failureMessage
     214: invokespecial #108                // Method getActivityEventValues:(Lcom/sonatype/nexus/staging/api/dto/StagingActivityEventDTO;Ljava/lang/String;)Ljava/util/List;
     217: invokespecial #109                // Method com/sonatype/nexus/staging/client/StagingRuleFailures$RuleFailure."<init>":(Ljava/lang/String;Ljava/util/List;)V
     220: invokeinterface #67,  2           // InterfaceMethod java/util/List.add:(Ljava/lang/Object;)Z
     225: pop
     226: goto          150
     229: aload_2
     230: invokeinterface #30,  1           // InterfaceMethod java/util/List.isEmpty:()Z
     235: ifeq          286
     238: iload         6
     240: ifle          286
     243: aload_2
     244: new           #104                // class com/sonatype/nexus/staging/client/StagingRuleFailures$RuleFailure
     247: dup
     248: ldc           #110                // String operation-failed
     250: iconst_1
     251: anewarray     #44                 // class java/lang/String
     254: dup
     255: iconst_0
     256: ldc           #111                // String Operation has failed; repository has %d activity notifications
     258: iconst_1
     259: anewarray     #83                 // class java/lang/Object
     262: dup
     263: iconst_0
     264: iload         6
     266: invokestatic  #62                 // Method java/lang/Integer.valueOf:(I)Ljava/lang/Integer;
     269: aastore
     270: invokestatic  #84                 // Method java/lang/String.format:(Ljava/lang/String;[Ljava/lang/Object;)Ljava/lang/String;
     273: aastore
     274: invokestatic  #21                 // Method com/google/common/collect/Lists.newArrayList:([Ljava/lang/Object;)Ljava/util/ArrayList;
     277: invokespecial #109                // Method com/sonatype/nexus/staging/client/StagingRuleFailures$RuleFailure."<init>":(Ljava/lang/String;Ljava/util/List;)V
     280: invokeinterface #67,  2           // InterfaceMethod java/util/List.add:(Ljava/lang/Object;)Z
     285: pop
     286: new           #112                // class com/sonatype/nexus/staging/client/StagingRuleFailures
     289: dup
     290: aload_1
     291: invokevirtual #79                 // Method com/sonatype/nexus/staging/api/dto/StagingProfileRepositoryDTO.getRepositoryId:()Ljava/lang/String;
     294: aload_2
     295: invokespecial #113                // Method com/sonatype/nexus/staging/client/StagingRuleFailures."<init>":(Ljava/lang/String;Ljava/util/Collection;)V
     298: areturn

  private java.lang.String getActivityEventValue(com.sonatype.nexus.staging.api.dto.StagingActivityEventDTO, java.lang.String);
    Code:
       0: aload_1
       1: invokevirtual #114                // Method com/sonatype/nexus/staging/api/dto/StagingActivityEventDTO.getProperties:()Ljava/util/List;
       4: invokeinterface #99,  1           // InterfaceMethod java/util/List.iterator:()Ljava/util/Iterator;
       9: astore_3
      10: aload_3
      11: invokeinterface #32,  1           // InterfaceMethod java/util/Iterator.hasNext:()Z
      16: ifeq          51
      19: aload_3
      20: invokeinterface #43,  1           // InterfaceMethod java/util/Iterator.next:()Ljava/lang/Object;
      25: checkcast     #115                // class com/sonatype/nexus/staging/api/dto/StagingPropertyDTO
      28: astore        4
      30: aload_2
      31: aload         4
      33: invokevirtual #116                // Method com/sonatype/nexus/staging/api/dto/StagingPropertyDTO.getName:()Ljava/lang/String;
      36: invokevirtual #10                 // Method java/lang/String.equals:(Ljava/lang/Object;)Z
      39: ifeq          48
      42: aload         4
      44: invokevirtual #117                // Method com/sonatype/nexus/staging/api/dto/StagingPropertyDTO.getValue:()Ljava/lang/String;
      47: areturn
      48: goto          10
      51: aconst_null
      52: areturn

  private java.util.List<java.lang.String> getActivityEventValues(com.sonatype.nexus.staging.api.dto.StagingActivityEventDTO, java.lang.String);
    Code:
       0: invokestatic  #29                 // Method com/google/common/collect/Lists.newArrayList:()Ljava/util/ArrayList;
       3: astore_3
       4: aload_1
       5: invokevirtual #114                // Method com/sonatype/nexus/staging/api/dto/StagingActivityEventDTO.getProperties:()Ljava/util/List;
       8: invokeinterface #99,  1           // InterfaceMethod java/util/List.iterator:()Ljava/util/Iterator;
      13: astore        4
      15: aload         4
      17: invokeinterface #32,  1           // InterfaceMethod java/util/Iterator.hasNext:()Z
      22: ifeq          64
      25: aload         4
      27: invokeinterface #43,  1           // InterfaceMethod java/util/Iterator.next:()Ljava/lang/Object;
      32: checkcast     #115                // class com/sonatype/nexus/staging/api/dto/StagingPropertyDTO
      35: astore        5
      37: aload_2
      38: aload         5
      40: invokevirtual #116                // Method com/sonatype/nexus/staging/api/dto/StagingPropertyDTO.getName:()Ljava/lang/String;
      43: invokevirtual #10                 // Method java/lang/String.equals:(Ljava/lang/Object;)Z
      46: ifeq          61
      49: aload_3
      50: aload         5
      52: invokevirtual #117                // Method com/sonatype/nexus/staging/api/dto/StagingPropertyDTO.getValue:()Ljava/lang/String;
      55: invokeinterface #67,  2           // InterfaceMethod java/util/List.add:(Ljava/lang/Object;)Z
      60: pop
      61: goto          15
      64: aload_3
      65: areturn
}
