Compiled from "SelfSignedSslEngineSource.java"
public class org.littleshoot.proxy.extras.SelfSignedSslEngineSource implements org.littleshoot.proxy.SslEngineSource {
  private static final org.slf4j.Logger LOG;

  private static final java.lang.String PROTOCOL;

  private final java.lang.String alias;

  private final java.lang.String password;

  private final java.lang.String keyStoreFile;

  private final boolean trustAllServers;

  private final boolean sendCerts;

  private javax.net.ssl.SSLContext sslContext;

  public org.littleshoot.proxy.extras.SelfSignedSslEngineSource(java.lang.String, boolean, boolean, java.lang.String, java.lang.String);
    Code:
       0: aload_0
       1: invokespecial #1                  // Method java/lang/Object."<init>":()V
       4: aload_0
       5: iload_2
       6: putfield      #2                  // Field trustAllServers:Z
       9: aload_0
      10: iload_3
      11: putfield      #3                  // Field sendCerts:Z
      14: aload_0
      15: aload_1
      16: putfield      #4                  // Field keyStoreFile:Ljava/lang/String;
      19: aload_0
      20: aload         4
      22: putfield      #5                  // Field alias:Ljava/lang/String;
      25: aload_0
      26: aload         5
      28: putfield      #6                  // Field password:Ljava/lang/String;
      31: aload_0
      32: invokespecial #7                  // Method initializeSSLContext:()V
      35: return

  public org.littleshoot.proxy.extras.SelfSignedSslEngineSource(java.lang.String, boolean, boolean);
    Code:
       0: aload_0
       1: aload_1
       2: iload_2
       3: iload_3
       4: ldc           #8                  // String littleproxy
       6: ldc           #9                  // String Be Your Own Lantern
       8: invokespecial #10                 // Method "<init>":(Ljava/lang/String;ZZLjava/lang/String;Ljava/lang/String;)V
      11: return

  public org.littleshoot.proxy.extras.SelfSignedSslEngineSource(java.lang.String);
    Code:
       0: aload_0
       1: aload_1
       2: iconst_0
       3: iconst_1
       4: invokespecial #11                 // Method "<init>":(Ljava/lang/String;ZZ)V
       7: return

  public org.littleshoot.proxy.extras.SelfSignedSslEngineSource(boolean);
    Code:
       0: aload_0
       1: iload_1
       2: iconst_1
       3: invokespecial #12                 // Method "<init>":(ZZ)V
       6: return

  public org.littleshoot.proxy.extras.SelfSignedSslEngineSource(boolean, boolean);
    Code:
       0: aload_0
       1: ldc           #13                 // String littleproxy_keystore.jks
       3: iload_1
       4: iload_2
       5: invokespecial #11                 // Method "<init>":(Ljava/lang/String;ZZ)V
       8: return

  public org.littleshoot.proxy.extras.SelfSignedSslEngineSource();
    Code:
       0: aload_0
       1: iconst_0
       2: invokespecial #14                 // Method "<init>":(Z)V
       5: return

  public javax.net.ssl.SSLEngine newSslEngine();
    Code:
       0: aload_0
       1: getfield      #15                 // Field sslContext:Ljavax/net/ssl/SSLContext;
       4: invokevirtual #16                 // Method javax/net/ssl/SSLContext.createSSLEngine:()Ljavax/net/ssl/SSLEngine;
       7: areturn

  public javax.net.ssl.SSLEngine newSslEngine(java.lang.String, int);
    Code:
       0: aload_0
       1: getfield      #15                 // Field sslContext:Ljavax/net/ssl/SSLContext;
       4: aload_1
       5: iload_2
       6: invokevirtual #17                 // Method javax/net/ssl/SSLContext.createSSLEngine:(Ljava/lang/String;I)Ljavax/net/ssl/SSLEngine;
       9: areturn

  public javax.net.ssl.SSLContext getSslContext();
    Code:
       0: aload_0
       1: getfield      #15                 // Field sslContext:Ljavax/net/ssl/SSLContext;
       4: areturn

  private void initializeKeyStore(java.lang.String);
    Code:
       0: aload_0
       1: bipush        18
       3: anewarray     #18                 // class java/lang/String
       6: dup
       7: iconst_0
       8: ldc           #19                 // String keytool
      10: aastore
      11: dup
      12: iconst_1
      13: ldc           #20                 // String -genkey
      15: aastore
      16: dup
      17: iconst_2
      18: ldc           #21                 // String -alias
      20: aastore
      21: dup
      22: iconst_3
      23: aload_0
      24: getfield      #5                  // Field alias:Ljava/lang/String;
      27: aastore
      28: dup
      29: iconst_4
      30: ldc           #22                 // String -keysize
      32: aastore
      33: dup
      34: iconst_5
      35: ldc           #23                 // String 4096
      37: aastore
      38: dup
      39: bipush        6
      41: ldc           #24                 // String -validity
      43: aastore
      44: dup
      45: bipush        7
      47: ldc           #25                 // String 36500
      49: aastore
      50: dup
      51: bipush        8
      53: ldc           #26                 // String -keyalg
      55: aastore
      56: dup
      57: bipush        9
      59: ldc           #27                 // String RSA
      61: aastore
      62: dup
      63: bipush        10
      65: ldc           #28                 // String -dname
      67: aastore
      68: dup
      69: bipush        11
      71: ldc           #29                 // String CN=littleproxy
      73: aastore
      74: dup
      75: bipush        12
      77: ldc           #30                 // String -keypass
      79: aastore
      80: dup
      81: bipush        13
      83: aload_0
      84: getfield      #6                  // Field password:Ljava/lang/String;
      87: aastore
      88: dup
      89: bipush        14
      91: ldc           #31                 // String -storepass
      93: aastore
      94: dup
      95: bipush        15
      97: aload_0
      98: getfield      #6                  // Field password:Ljava/lang/String;
     101: aastore
     102: dup
     103: bipush        16
     105: ldc           #32                 // String -keystore
     107: aastore
     108: dup
     109: bipush        17
     111: aload_1
     112: aastore
     113: invokespecial #33                 // Method nativeCall:([Ljava/lang/String;)Ljava/lang/String;
     116: pop
     117: aload_0
     118: bipush        10
     120: anewarray     #18                 // class java/lang/String
     123: dup
     124: iconst_0
     125: ldc           #19                 // String keytool
     127: aastore
     128: dup
     129: iconst_1
     130: ldc           #34                 // String -exportcert
     132: aastore
     133: dup
     134: iconst_2
     135: ldc           #21                 // String -alias
     137: aastore
     138: dup
     139: iconst_3
     140: aload_0
     141: getfield      #5                  // Field alias:Ljava/lang/String;
     144: aastore
     145: dup
     146: iconst_4
     147: ldc           #32                 // String -keystore
     149: aastore
     150: dup
     151: iconst_5
     152: aload_1
     153: aastore
     154: dup
     155: bipush        6
     157: ldc           #31                 // String -storepass
     159: aastore
     160: dup
     161: bipush        7
     163: aload_0
     164: getfield      #6                  // Field password:Ljava/lang/String;
     167: aastore
     168: dup
     169: bipush        8
     171: ldc           #35                 // String -file
     173: aastore
     174: dup
     175: bipush        9
     177: ldc           #36                 // String littleproxy_cert
     179: aastore
     180: invokespecial #33                 // Method nativeCall:([Ljava/lang/String;)Ljava/lang/String;
     183: pop
     184: return

  private void initializeSSLContext();
    Code:
       0: ldc           #37                 // String ssl.KeyManagerFactory.algorithm
       2: invokestatic  #38                 // Method java/security/Security.getProperty:(Ljava/lang/String;)Ljava/lang/String;
       5: astore_1
       6: aload_1
       7: ifnonnull     13
      10: ldc           #39                 // String SunX509
      12: astore_1
      13: aload_0
      14: invokespecial #40                 // Method loadKeyStore:()Ljava/security/KeyStore;
      17: astore_2
      18: aload_1
      19: invokestatic  #41                 // Method javax/net/ssl/KeyManagerFactory.getInstance:(Ljava/lang/String;)Ljavax/net/ssl/KeyManagerFactory;
      22: astore_3
      23: aload_3
      24: aload_2
      25: aload_0
      26: getfield      #6                  // Field password:Ljava/lang/String;
      29: invokevirtual #42                 // Method java/lang/String.toCharArray:()[C
      32: invokevirtual #43                 // Method javax/net/ssl/KeyManagerFactory.init:(Ljava/security/KeyStore;[C)V
      35: aload_1
      36: invokestatic  #44                 // Method javax/net/ssl/TrustManagerFactory.getInstance:(Ljava/lang/String;)Ljavax/net/ssl/TrustManagerFactory;
      39: astore        4
      41: aload         4
      43: aload_2
      44: invokevirtual #45                 // Method javax/net/ssl/TrustManagerFactory.init:(Ljava/security/KeyStore;)V
      47: aload_0
      48: getfield      #2                  // Field trustAllServers:Z
      51: ifne          64
      54: aload         4
      56: invokevirtual #46                 // Method javax/net/ssl/TrustManagerFactory.getTrustManagers:()[Ljavax/net/ssl/TrustManager;
      59: astore        5
      61: goto          81
      64: iconst_1
      65: anewarray     #47                 // class javax/net/ssl/TrustManager
      68: dup
      69: iconst_0
      70: new           #48                 // class org/littleshoot/proxy/extras/SelfSignedSslEngineSource$1
      73: dup
      74: aload_0
      75: invokespecial #49                 // Method org/littleshoot/proxy/extras/SelfSignedSslEngineSource$1."<init>":(Lorg/littleshoot/proxy/extras/SelfSignedSslEngineSource;)V
      78: aastore
      79: astore        5
      81: aload_0
      82: getfield      #3                  // Field sendCerts:Z
      85: ifeq          97
      88: aload_3
      89: invokevirtual #50                 // Method javax/net/ssl/KeyManagerFactory.getKeyManagers:()[Ljavax/net/ssl/KeyManager;
      92: astore        6
      94: goto          103
      97: iconst_0
      98: anewarray     #51                 // class javax/net/ssl/KeyManager
     101: astore        6
     103: aload_0
     104: ldc           #53                 // String TLS
     106: invokestatic  #54                 // Method javax/net/ssl/SSLContext.getInstance:(Ljava/lang/String;)Ljavax/net/ssl/SSLContext;
     109: putfield      #15                 // Field sslContext:Ljavax/net/ssl/SSLContext;
     112: aload_0
     113: getfield      #15                 // Field sslContext:Ljavax/net/ssl/SSLContext;
     116: aload         6
     118: aload         5
     120: aconst_null
     121: invokevirtual #55                 // Method javax/net/ssl/SSLContext.init:([Ljavax/net/ssl/KeyManager;[Ljavax/net/ssl/TrustManager;Ljava/security/SecureRandom;)V
     124: goto          139
     127: astore_2
     128: new           #57                 // class java/lang/Error
     131: dup
     132: ldc           #58                 // String Failed to initialize the server-side SSLContext
     134: aload_2
     135: invokespecial #59                 // Method java/lang/Error."<init>":(Ljava/lang/String;Ljava/lang/Throwable;)V
     138: athrow
     139: return
    Exception table:
       from    to  target type
          13   124   127   Class java/lang/Exception

  private java.security.KeyStore loadKeyStore() throws java.io.IOException, java.security.GeneralSecurityException;
    Code:
       0: ldc           #60                 // String JKS
       2: invokestatic  #61                 // Method java/security/KeyStore.getInstance:(Ljava/lang/String;)Ljava/security/KeyStore;
       5: astore_1
       6: aload_0
       7: invokevirtual #62                 // Method java/lang/Object.getClass:()Ljava/lang/Class;
      10: aload_0
      11: getfield      #4                  // Field keyStoreFile:Ljava/lang/String;
      14: invokevirtual #63                 // Method java/lang/Class.getResource:(Ljava/lang/String;)Ljava/net/URL;
      17: astore_2
      18: aload_2
      19: ifnull        31
      22: aload_0
      23: aload_1
      24: aload_2
      25: invokespecial #64                 // Method loadKeyStore:(Ljava/security/KeyStore;Ljava/net/URL;)V
      28: goto          70
      31: new           #65                 // class java/io/File
      34: dup
      35: aload_0
      36: getfield      #4                  // Field keyStoreFile:Ljava/lang/String;
      39: invokespecial #66                 // Method java/io/File."<init>":(Ljava/lang/String;)V
      42: astore_3
      43: aload_3
      44: invokevirtual #67                 // Method java/io/File.isFile:()Z
      47: ifne          58
      50: aload_0
      51: aload_3
      52: invokevirtual #68                 // Method java/io/File.getName:()Ljava/lang/String;
      55: invokespecial #69                 // Method initializeKeyStore:(Ljava/lang/String;)V
      58: aload_0
      59: aload_1
      60: aload_3
      61: invokevirtual #70                 // Method java/io/File.toURI:()Ljava/net/URI;
      64: invokevirtual #71                 // Method java/net/URI.toURL:()Ljava/net/URL;
      67: invokespecial #64                 // Method loadKeyStore:(Ljava/security/KeyStore;Ljava/net/URL;)V
      70: aload_1
      71: areturn

  private void loadKeyStore(java.security.KeyStore, java.net.URL) throws java.io.IOException, java.security.GeneralSecurityException;
    Code:
       0: aload_2
       1: invokevirtual #72                 // Method java/net/URL.openStream:()Ljava/io/InputStream;
       4: astore_3
       5: aconst_null
       6: astore        4
       8: aload_1
       9: aload_3
      10: aload_0
      11: getfield      #6                  // Field password:Ljava/lang/String;
      14: invokevirtual #42                 // Method java/lang/String.toCharArray:()[C
      17: invokevirtual #73                 // Method java/security/KeyStore.load:(Ljava/io/InputStream;[C)V
      20: aload_3
      21: ifnull        101
      24: aload         4
      26: ifnull        48
      29: aload_3
      30: invokevirtual #74                 // Method java/io/InputStream.close:()V
      33: goto          101
      36: astore        5
      38: aload         4
      40: aload         5
      42: invokevirtual #76                 // Method java/lang/Throwable.addSuppressed:(Ljava/lang/Throwable;)V
      45: goto          101
      48: aload_3
      49: invokevirtual #74                 // Method java/io/InputStream.close:()V
      52: goto          101
      55: astore        5
      57: aload         5
      59: astore        4
      61: aload         5
      63: athrow
      64: astore        6
      66: aload_3
      67: ifnull        98
      70: aload         4
      72: ifnull        94
      75: aload_3
      76: invokevirtual #74                 // Method java/io/InputStream.close:()V
      79: goto          98
      82: astore        7
      84: aload         4
      86: aload         7
      88: invokevirtual #76                 // Method java/lang/Throwable.addSuppressed:(Ljava/lang/Throwable;)V
      91: goto          98
      94: aload_3
      95: invokevirtual #74                 // Method java/io/InputStream.close:()V
      98: aload         6
     100: athrow
     101: return
    Exception table:
       from    to  target type
          29    33    36   Class java/lang/Throwable
           8    20    55   Class java/lang/Throwable
           8    20    64   any
          75    79    82   Class java/lang/Throwable
          55    66    64   any

  private java.lang.String nativeCall(java.lang.String...);
    Code:
       0: getstatic     #77                 // Field LOG:Lorg/slf4j/Logger;
       3: ldc           #78                 // String Running \'{}\'
       5: aload_1
       6: invokestatic  #79                 // Method java/util/Arrays.asList:([Ljava/lang/Object;)Ljava/util/List;
       9: invokeinterface #80,  3           // InterfaceMethod org/slf4j/Logger.info:(Ljava/lang/String;Ljava/lang/Object;)V
      14: new           #81                 // class java/lang/ProcessBuilder
      17: dup
      18: aload_1
      19: invokespecial #82                 // Method java/lang/ProcessBuilder."<init>":([Ljava/lang/String;)V
      22: astore_2
      23: aload_2
      24: invokevirtual #83                 // Method java/lang/ProcessBuilder.start:()Ljava/lang/Process;
      27: astore_3
      28: aload_3
      29: invokevirtual #84                 // Method java/lang/Process.getInputStream:()Ljava/io/InputStream;
      32: astore        5
      34: aconst_null
      35: astore        6
      37: aload         5
      39: invokestatic  #85                 // Method com/google/common/io/ByteStreams.toByteArray:(Ljava/io/InputStream;)[B
      42: astore        4
      44: aload         5
      46: ifnull        131
      49: aload         6
      51: ifnull        74
      54: aload         5
      56: invokevirtual #74                 // Method java/io/InputStream.close:()V
      59: goto          131
      62: astore        7
      64: aload         6
      66: aload         7
      68: invokevirtual #76                 // Method java/lang/Throwable.addSuppressed:(Ljava/lang/Throwable;)V
      71: goto          131
      74: aload         5
      76: invokevirtual #74                 // Method java/io/InputStream.close:()V
      79: goto          131
      82: astore        7
      84: aload         7
      86: astore        6
      88: aload         7
      90: athrow
      91: astore        8
      93: aload         5
      95: ifnull        128
      98: aload         6
     100: ifnull        123
     103: aload         5
     105: invokevirtual #74                 // Method java/io/InputStream.close:()V
     108: goto          128
     111: astore        9
     113: aload         6
     115: aload         9
     117: invokevirtual #76                 // Method java/lang/Throwable.addSuppressed:(Ljava/lang/Throwable;)V
     120: goto          128
     123: aload         5
     125: invokevirtual #74                 // Method java/io/InputStream.close:()V
     128: aload         8
     130: athrow
     131: new           #18                 // class java/lang/String
     134: dup
     135: aload         4
     137: invokespecial #86                 // Method java/lang/String."<init>":([B)V
     140: astore        5
     142: getstatic     #77                 // Field LOG:Lorg/slf4j/Logger;
     145: ldc           #87                 // String Completed native call: \'{}\'\nResponse: \'{}\'
     147: aload_1
     148: invokestatic  #79                 // Method java/util/Arrays.asList:([Ljava/lang/Object;)Ljava/util/List;
     151: aload         5
     153: invokeinterface #88,  4           // InterfaceMethod org/slf4j/Logger.info:(Ljava/lang/String;Ljava/lang/Object;Ljava/lang/Object;)V
     158: aload         5
     160: areturn
     161: astore_3
     162: getstatic     #77                 // Field LOG:Lorg/slf4j/Logger;
     165: ldc           #90                 // String Error running commands: {}
     167: aload_1
     168: invokestatic  #79                 // Method java/util/Arrays.asList:([Ljava/lang/Object;)Ljava/util/List;
     171: aload_3
     172: invokeinterface #91,  4           // InterfaceMethod org/slf4j/Logger.error:(Ljava/lang/String;Ljava/lang/Object;Ljava/lang/Object;)V
     177: ldc           #92                 // String
     179: areturn
    Exception table:
       from    to  target type
          54    59    62   Class java/lang/Throwable
          37    44    82   Class java/lang/Throwable
          37    44    91   any
         103   108   111   Class java/lang/Throwable
          82    93    91   any
          23   160   161   Class java/io/IOException

  static {};
    Code:
       0: ldc           #52                 // class org/littleshoot/proxy/extras/SelfSignedSslEngineSource
       2: invokestatic  #93                 // Method org/slf4j/LoggerFactory.getLogger:(Ljava/lang/Class;)Lorg/slf4j/Logger;
       5: putstatic     #77                 // Field LOG:Lorg/slf4j/Logger;
       8: return
}
