Compiled from "SelfSignedMitmManager.java"
public class org.littleshoot.proxy.extras.SelfSignedMitmManager implements org.littleshoot.proxy.MitmManager {
  private final org.littleshoot.proxy.extras.SelfSignedSslEngineSource selfSignedSslEngineSource;

  public org.littleshoot.proxy.extras.SelfSignedMitmManager();
    Code:
       0: aload_0
       1: invokespecial #1                  // Method java/lang/Object."<init>":()V
       4: aload_0
       5: new           #2                  // class org/littleshoot/proxy/extras/SelfSignedSslEngineSource
       8: dup
       9: iconst_1
      10: invokespecial #3                  // Method org/littleshoot/proxy/extras/SelfSignedSslEngineSource."<init>":(Z)V
      13: putfield      #4                  // Field selfSignedSslEngineSource:Lorg/littleshoot/proxy/extras/SelfSignedSslEngineSource;
      16: return

  public org.littleshoot.proxy.extras.SelfSignedMitmManager(org.littleshoot.proxy.extras.SelfSignedSslEngineSource);
    Code:
       0: aload_0
       1: invokespecial #1                  // Method java/lang/Object."<init>":()V
       4: aload_0
       5: aload_1
       6: putfield      #4                  // Field selfSignedSslEngineSource:Lorg/littleshoot/proxy/extras/SelfSignedSslEngineSource;
       9: return

  public javax.net.ssl.SSLEngine serverSslEngine(java.lang.String, int);
    Code:
       0: aload_0
       1: getfield      #4                  // Field selfSignedSslEngineSource:Lorg/littleshoot/proxy/extras/SelfSignedSslEngineSource;
       4: aload_1
       5: iload_2
       6: invokevirtual #5                  // Method org/littleshoot/proxy/extras/SelfSignedSslEngineSource.newSslEngine:(Ljava/lang/String;I)Ljavax/net/ssl/SSLEngine;
       9: areturn

  public javax.net.ssl.SSLEngine serverSslEngine();
    Code:
       0: aload_0
       1: getfield      #4                  // Field selfSignedSslEngineSource:Lorg/littleshoot/proxy/extras/SelfSignedSslEngineSource;
       4: invokevirtual #6                  // Method org/littleshoot/proxy/extras/SelfSignedSslEngineSource.newSslEngine:()Ljavax/net/ssl/SSLEngine;
       7: areturn

  public javax.net.ssl.SSLEngine clientSslEngineFor(io.netty.handler.codec.http.HttpRequest, javax.net.ssl.SSLSession);
    Code:
       0: aload_0
       1: getfield      #4                  // Field selfSignedSslEngineSource:Lorg/littleshoot/proxy/extras/SelfSignedSslEngineSource;
       4: invokevirtual #6                  // Method org/littleshoot/proxy/extras/SelfSignedSslEngineSource.newSslEngine:()Ljavax/net/ssl/SSLEngine;
       7: areturn
}
