public class org.bouncycastle.asn1.x509.KeyPurposeId extends org.bouncycastle.asn1.ASN1Object {
  private static final org.bouncycastle.asn1.ASN1ObjectIdentifier id_kp;

  public static final org.bouncycastle.asn1.x509.KeyPurposeId anyExtendedKeyUsage;

  public static final org.bouncycastle.asn1.x509.KeyPurposeId id_kp_serverAuth;

  public static final org.bouncycastle.asn1.x509.KeyPurposeId id_kp_clientAuth;

  public static final org.bouncycastle.asn1.x509.KeyPurposeId id_kp_codeSigning;

  public static final org.bouncycastle.asn1.x509.KeyPurposeId id_kp_emailProtection;

  public static final org.bouncycastle.asn1.x509.KeyPurposeId id_kp_ipsecEndSystem;

  public static final org.bouncycastle.asn1.x509.KeyPurposeId id_kp_ipsecTunnel;

  public static final org.bouncycastle.asn1.x509.KeyPurposeId id_kp_ipsecUser;

  public static final org.bouncycastle.asn1.x509.KeyPurposeId id_kp_timeStamping;

  public static final org.bouncycastle.asn1.x509.KeyPurposeId id_kp_OCSPSigning;

  public static final org.bouncycastle.asn1.x509.KeyPurposeId id_kp_dvcs;

  public static final org.bouncycastle.asn1.x509.KeyPurposeId id_kp_sbgpCertAAServerAuth;

  public static final org.bouncycastle.asn1.x509.KeyPurposeId id_kp_scvp_responder;

  public static final org.bouncycastle.asn1.x509.KeyPurposeId id_kp_eapOverPPP;

  public static final org.bouncycastle.asn1.x509.KeyPurposeId id_kp_eapOverLAN;

  public static final org.bouncycastle.asn1.x509.KeyPurposeId id_kp_scvpServer;

  public static final org.bouncycastle.asn1.x509.KeyPurposeId id_kp_scvpClient;

  public static final org.bouncycastle.asn1.x509.KeyPurposeId id_kp_ipsecIKE;

  public static final org.bouncycastle.asn1.x509.KeyPurposeId id_kp_capwapAC;

  public static final org.bouncycastle.asn1.x509.KeyPurposeId id_kp_capwapWTP;

  public static final org.bouncycastle.asn1.x509.KeyPurposeId id_kp_smartcardlogon;

  public static final org.bouncycastle.asn1.x509.KeyPurposeId id_kp_macAddress;

  public static final org.bouncycastle.asn1.x509.KeyPurposeId id_kp_msSGC;

  public static final org.bouncycastle.asn1.x509.KeyPurposeId id_kp_nsSGC;

  private org.bouncycastle.asn1.ASN1ObjectIdentifier id;

  private org.bouncycastle.asn1.x509.KeyPurposeId(org.bouncycastle.asn1.ASN1ObjectIdentifier);
    Code:
       0: aload_0
       1: invokespecial #166                // Method org/bouncycastle/asn1/ASN1Object."<init>":()V
       4: aload_0
       5: aload_1
       6: putfield      #140                // Field id:Lorg/bouncycastle/asn1/ASN1ObjectIdentifier;
       9: return

  public org.bouncycastle.asn1.x509.KeyPurposeId(java.lang.String);
    Code:
       0: aload_0
       1: new           #92                 // class org/bouncycastle/asn1/ASN1ObjectIdentifier
       4: dup
       5: aload_1
       6: invokespecial #169                // Method org/bouncycastle/asn1/ASN1ObjectIdentifier."<init>":(Ljava/lang/String;)V
       9: invokespecial #172                // Method "<init>":(Lorg/bouncycastle/asn1/ASN1ObjectIdentifier;)V
      12: return

  public static org.bouncycastle.asn1.x509.KeyPurposeId getInstance(java.lang.Object);
    Code:
       0: aload_0
       1: instanceof    #94                 // class org/bouncycastle/asn1/x509/KeyPurposeId
       4: ifeq          12
       7: aload_0
       8: checkcast     #94                 // class org/bouncycastle/asn1/x509/KeyPurposeId
      11: areturn
      12: aload_0
      13: ifnull        28
      16: new           #94                 // class org/bouncycastle/asn1/x509/KeyPurposeId
      19: dup
      20: aload_0
      21: invokestatic  #170                // Method org/bouncycastle/asn1/ASN1ObjectIdentifier.getInstance:(Ljava/lang/Object;)Lorg/bouncycastle/asn1/ASN1ObjectIdentifier;
      24: invokespecial #172                // Method "<init>":(Lorg/bouncycastle/asn1/ASN1ObjectIdentifier;)V
      27: areturn
      28: aconst_null
      29: areturn

  public org.bouncycastle.asn1.ASN1ObjectIdentifier toOID();
    Code:
       0: aload_0
       1: getfield      #140                // Field id:Lorg/bouncycastle/asn1/ASN1ObjectIdentifier;
       4: areturn

  public org.bouncycastle.asn1.ASN1Primitive toASN1Primitive();
    Code:
       0: aload_0
       1: getfield      #140                // Field id:Lorg/bouncycastle/asn1/ASN1ObjectIdentifier;
       4: areturn

  public java.lang.String getId();
    Code:
       0: aload_0
       1: getfield      #140                // Field id:Lorg/bouncycastle/asn1/ASN1ObjectIdentifier;
       4: invokevirtual #167                // Method org/bouncycastle/asn1/ASN1ObjectIdentifier.getId:()Ljava/lang/String;
       7: areturn

  public java.lang.String toString();
    Code:
       0: aload_0
       1: getfield      #140                // Field id:Lorg/bouncycastle/asn1/ASN1ObjectIdentifier;
       4: invokevirtual #168                // Method org/bouncycastle/asn1/ASN1ObjectIdentifier.toString:()Ljava/lang/String;
       7: areturn

  static {};
    Code:
       0: new           #92                 // class org/bouncycastle/asn1/ASN1ObjectIdentifier
       3: dup
       4: ldc           #6                  // String 1.3.6.1.5.5.7.3
       6: invokespecial #169                // Method org/bouncycastle/asn1/ASN1ObjectIdentifier."<init>":(Ljava/lang/String;)V
       9: putstatic     #141                // Field id_kp:Lorg/bouncycastle/asn1/ASN1ObjectIdentifier;
      12: new           #94                 // class org/bouncycastle/asn1/x509/KeyPurposeId
      15: dup
      16: getstatic     #139                // Field org/bouncycastle/asn1/x509/Extension.extendedKeyUsage:Lorg/bouncycastle/asn1/ASN1ObjectIdentifier;
      19: ldc           #1                  // String 0
      21: invokevirtual #171                // Method org/bouncycastle/asn1/ASN1ObjectIdentifier.branch:(Ljava/lang/String;)Lorg/bouncycastle/asn1/ASN1ObjectIdentifier;
      24: invokespecial #172                // Method "<init>":(Lorg/bouncycastle/asn1/ASN1ObjectIdentifier;)V
      27: putstatic     #142                // Field anyExtendedKeyUsage:Lorg/bouncycastle/asn1/x509/KeyPurposeId;
      30: new           #94                 // class org/bouncycastle/asn1/x509/KeyPurposeId
      33: dup
      34: getstatic     #141                // Field id_kp:Lorg/bouncycastle/asn1/ASN1ObjectIdentifier;
      37: ldc           #2                  // String 1
      39: invokevirtual #171                // Method org/bouncycastle/asn1/ASN1ObjectIdentifier.branch:(Ljava/lang/String;)Lorg/bouncycastle/asn1/ASN1ObjectIdentifier;
      42: invokespecial #172                // Method "<init>":(Lorg/bouncycastle/asn1/ASN1ObjectIdentifier;)V
      45: putstatic     #163                // Field id_kp_serverAuth:Lorg/bouncycastle/asn1/x509/KeyPurposeId;
      48: new           #94                 // class org/bouncycastle/asn1/x509/KeyPurposeId
      51: dup
      52: getstatic     #141                // Field id_kp:Lorg/bouncycastle/asn1/ASN1ObjectIdentifier;
      55: ldc           #17                 // String 2
      57: invokevirtual #171                // Method org/bouncycastle/asn1/ASN1ObjectIdentifier.branch:(Ljava/lang/String;)Lorg/bouncycastle/asn1/ASN1ObjectIdentifier;
      60: invokespecial #172                // Method "<init>":(Lorg/bouncycastle/asn1/ASN1ObjectIdentifier;)V
      63: putstatic     #146                // Field id_kp_clientAuth:Lorg/bouncycastle/asn1/x509/KeyPurposeId;
      66: new           #94                 // class org/bouncycastle/asn1/x509/KeyPurposeId
      69: dup
      70: getstatic     #141                // Field id_kp:Lorg/bouncycastle/asn1/ASN1ObjectIdentifier;
      73: ldc           #19                 // String 3
      75: invokevirtual #171                // Method org/bouncycastle/asn1/ASN1ObjectIdentifier.branch:(Ljava/lang/String;)Lorg/bouncycastle/asn1/ASN1ObjectIdentifier;
      78: invokespecial #172                // Method "<init>":(Lorg/bouncycastle/asn1/ASN1ObjectIdentifier;)V
      81: putstatic     #147                // Field id_kp_codeSigning:Lorg/bouncycastle/asn1/x509/KeyPurposeId;
      84: new           #94                 // class org/bouncycastle/asn1/x509/KeyPurposeId
      87: dup
      88: getstatic     #141                // Field id_kp:Lorg/bouncycastle/asn1/ASN1ObjectIdentifier;
      91: ldc           #20                 // String 4
      93: invokevirtual #171                // Method org/bouncycastle/asn1/ASN1ObjectIdentifier.branch:(Ljava/lang/String;)Lorg/bouncycastle/asn1/ASN1ObjectIdentifier;
      96: invokespecial #172                // Method "<init>":(Lorg/bouncycastle/asn1/ASN1ObjectIdentifier;)V
      99: putstatic     #151                // Field id_kp_emailProtection:Lorg/bouncycastle/asn1/x509/KeyPurposeId;
     102: new           #94                 // class org/bouncycastle/asn1/x509/KeyPurposeId
     105: dup
     106: getstatic     #141                // Field id_kp:Lorg/bouncycastle/asn1/ASN1ObjectIdentifier;
     109: ldc           #21                 // String 5
     111: invokevirtual #171                // Method org/bouncycastle/asn1/ASN1ObjectIdentifier.branch:(Ljava/lang/String;)Lorg/bouncycastle/asn1/ASN1ObjectIdentifier;
     114: invokespecial #172                // Method "<init>":(Lorg/bouncycastle/asn1/ASN1ObjectIdentifier;)V
     117: putstatic     #152                // Field id_kp_ipsecEndSystem:Lorg/bouncycastle/asn1/x509/KeyPurposeId;
     120: new           #94                 // class org/bouncycastle/asn1/x509/KeyPurposeId
     123: dup
     124: getstatic     #141                // Field id_kp:Lorg/bouncycastle/asn1/ASN1ObjectIdentifier;
     127: ldc           #22                 // String 6
     129: invokevirtual #171                // Method org/bouncycastle/asn1/ASN1ObjectIdentifier.branch:(Ljava/lang/String;)Lorg/bouncycastle/asn1/ASN1ObjectIdentifier;
     132: invokespecial #172                // Method "<init>":(Lorg/bouncycastle/asn1/ASN1ObjectIdentifier;)V
     135: putstatic     #154                // Field id_kp_ipsecTunnel:Lorg/bouncycastle/asn1/x509/KeyPurposeId;
     138: new           #94                 // class org/bouncycastle/asn1/x509/KeyPurposeId
     141: dup
     142: getstatic     #141                // Field id_kp:Lorg/bouncycastle/asn1/ASN1ObjectIdentifier;
     145: ldc           #23                 // String 7
     147: invokevirtual #171                // Method org/bouncycastle/asn1/ASN1ObjectIdentifier.branch:(Ljava/lang/String;)Lorg/bouncycastle/asn1/ASN1ObjectIdentifier;
     150: invokespecial #172                // Method "<init>":(Lorg/bouncycastle/asn1/ASN1ObjectIdentifier;)V
     153: putstatic     #155                // Field id_kp_ipsecUser:Lorg/bouncycastle/asn1/x509/KeyPurposeId;
     156: new           #94                 // class org/bouncycastle/asn1/x509/KeyPurposeId
     159: dup
     160: getstatic     #141                // Field id_kp:Lorg/bouncycastle/asn1/ASN1ObjectIdentifier;
     163: ldc           #24                 // String 8
     165: invokevirtual #171                // Method org/bouncycastle/asn1/ASN1ObjectIdentifier.branch:(Ljava/lang/String;)Lorg/bouncycastle/asn1/ASN1ObjectIdentifier;
     168: invokespecial #172                // Method "<init>":(Lorg/bouncycastle/asn1/ASN1ObjectIdentifier;)V
     171: putstatic     #165                // Field id_kp_timeStamping:Lorg/bouncycastle/asn1/x509/KeyPurposeId;
     174: new           #94                 // class org/bouncycastle/asn1/x509/KeyPurposeId
     177: dup
     178: getstatic     #141                // Field id_kp:Lorg/bouncycastle/asn1/ASN1ObjectIdentifier;
     181: ldc           #25                 // String 9
     183: invokevirtual #171                // Method org/bouncycastle/asn1/ASN1ObjectIdentifier.branch:(Ljava/lang/String;)Lorg/bouncycastle/asn1/ASN1ObjectIdentifier;
     186: invokespecial #172                // Method "<init>":(Lorg/bouncycastle/asn1/ASN1ObjectIdentifier;)V
     189: putstatic     #143                // Field id_kp_OCSPSigning:Lorg/bouncycastle/asn1/x509/KeyPurposeId;
     192: new           #94                 // class org/bouncycastle/asn1/x509/KeyPurposeId
     195: dup
     196: getstatic     #141                // Field id_kp:Lorg/bouncycastle/asn1/ASN1ObjectIdentifier;
     199: ldc           #7                  // String 10
     201: invokevirtual #171                // Method org/bouncycastle/asn1/ASN1ObjectIdentifier.branch:(Ljava/lang/String;)Lorg/bouncycastle/asn1/ASN1ObjectIdentifier;
     204: invokespecial #172                // Method "<init>":(Lorg/bouncycastle/asn1/ASN1ObjectIdentifier;)V
     207: putstatic     #148                // Field id_kp_dvcs:Lorg/bouncycastle/asn1/x509/KeyPurposeId;
     210: new           #94                 // class org/bouncycastle/asn1/x509/KeyPurposeId
     213: dup
     214: getstatic     #141                // Field id_kp:Lorg/bouncycastle/asn1/ASN1ObjectIdentifier;
     217: ldc           #8                  // String 11
     219: invokevirtual #171                // Method org/bouncycastle/asn1/ASN1ObjectIdentifier.branch:(Ljava/lang/String;)Lorg/bouncycastle/asn1/ASN1ObjectIdentifier;
     222: invokespecial #172                // Method "<init>":(Lorg/bouncycastle/asn1/ASN1ObjectIdentifier;)V
     225: putstatic     #159                // Field id_kp_sbgpCertAAServerAuth:Lorg/bouncycastle/asn1/x509/KeyPurposeId;
     228: new           #94                 // class org/bouncycastle/asn1/x509/KeyPurposeId
     231: dup
     232: getstatic     #141                // Field id_kp:Lorg/bouncycastle/asn1/ASN1ObjectIdentifier;
     235: ldc           #9                  // String 12
     237: invokevirtual #171                // Method org/bouncycastle/asn1/ASN1ObjectIdentifier.branch:(Ljava/lang/String;)Lorg/bouncycastle/asn1/ASN1ObjectIdentifier;
     240: invokespecial #172                // Method "<init>":(Lorg/bouncycastle/asn1/ASN1ObjectIdentifier;)V
     243: putstatic     #162                // Field id_kp_scvp_responder:Lorg/bouncycastle/asn1/x509/KeyPurposeId;
     246: new           #94                 // class org/bouncycastle/asn1/x509/KeyPurposeId
     249: dup
     250: getstatic     #141                // Field id_kp:Lorg/bouncycastle/asn1/ASN1ObjectIdentifier;
     253: ldc           #10                 // String 13
     255: invokevirtual #171                // Method org/bouncycastle/asn1/ASN1ObjectIdentifier.branch:(Ljava/lang/String;)Lorg/bouncycastle/asn1/ASN1ObjectIdentifier;
     258: invokespecial #172                // Method "<init>":(Lorg/bouncycastle/asn1/ASN1ObjectIdentifier;)V
     261: putstatic     #150                // Field id_kp_eapOverPPP:Lorg/bouncycastle/asn1/x509/KeyPurposeId;
     264: new           #94                 // class org/bouncycastle/asn1/x509/KeyPurposeId
     267: dup
     268: getstatic     #141                // Field id_kp:Lorg/bouncycastle/asn1/ASN1ObjectIdentifier;
     271: ldc           #11                 // String 14
     273: invokevirtual #171                // Method org/bouncycastle/asn1/ASN1ObjectIdentifier.branch:(Ljava/lang/String;)Lorg/bouncycastle/asn1/ASN1ObjectIdentifier;
     276: invokespecial #172                // Method "<init>":(Lorg/bouncycastle/asn1/ASN1ObjectIdentifier;)V
     279: putstatic     #149                // Field id_kp_eapOverLAN:Lorg/bouncycastle/asn1/x509/KeyPurposeId;
     282: new           #94                 // class org/bouncycastle/asn1/x509/KeyPurposeId
     285: dup
     286: getstatic     #141                // Field id_kp:Lorg/bouncycastle/asn1/ASN1ObjectIdentifier;
     289: ldc           #12                 // String 15
     291: invokevirtual #171                // Method org/bouncycastle/asn1/ASN1ObjectIdentifier.branch:(Ljava/lang/String;)Lorg/bouncycastle/asn1/ASN1ObjectIdentifier;
     294: invokespecial #172                // Method "<init>":(Lorg/bouncycastle/asn1/ASN1ObjectIdentifier;)V
     297: putstatic     #161                // Field id_kp_scvpServer:Lorg/bouncycastle/asn1/x509/KeyPurposeId;
     300: new           #94                 // class org/bouncycastle/asn1/x509/KeyPurposeId
     303: dup
     304: getstatic     #141                // Field id_kp:Lorg/bouncycastle/asn1/ASN1ObjectIdentifier;
     307: ldc           #13                 // String 16
     309: invokevirtual #171                // Method org/bouncycastle/asn1/ASN1ObjectIdentifier.branch:(Ljava/lang/String;)Lorg/bouncycastle/asn1/ASN1ObjectIdentifier;
     312: invokespecial #172                // Method "<init>":(Lorg/bouncycastle/asn1/ASN1ObjectIdentifier;)V
     315: putstatic     #160                // Field id_kp_scvpClient:Lorg/bouncycastle/asn1/x509/KeyPurposeId;
     318: new           #94                 // class org/bouncycastle/asn1/x509/KeyPurposeId
     321: dup
     322: getstatic     #141                // Field id_kp:Lorg/bouncycastle/asn1/ASN1ObjectIdentifier;
     325: ldc           #14                 // String 17
     327: invokevirtual #171                // Method org/bouncycastle/asn1/ASN1ObjectIdentifier.branch:(Ljava/lang/String;)Lorg/bouncycastle/asn1/ASN1ObjectIdentifier;
     330: invokespecial #172                // Method "<init>":(Lorg/bouncycastle/asn1/ASN1ObjectIdentifier;)V
     333: putstatic     #153                // Field id_kp_ipsecIKE:Lorg/bouncycastle/asn1/x509/KeyPurposeId;
     336: new           #94                 // class org/bouncycastle/asn1/x509/KeyPurposeId
     339: dup
     340: getstatic     #141                // Field id_kp:Lorg/bouncycastle/asn1/ASN1ObjectIdentifier;
     343: ldc           #15                 // String 18
     345: invokevirtual #171                // Method org/bouncycastle/asn1/ASN1ObjectIdentifier.branch:(Ljava/lang/String;)Lorg/bouncycastle/asn1/ASN1ObjectIdentifier;
     348: invokespecial #172                // Method "<init>":(Lorg/bouncycastle/asn1/ASN1ObjectIdentifier;)V
     351: putstatic     #144                // Field id_kp_capwapAC:Lorg/bouncycastle/asn1/x509/KeyPurposeId;
     354: new           #94                 // class org/bouncycastle/asn1/x509/KeyPurposeId
     357: dup
     358: getstatic     #141                // Field id_kp:Lorg/bouncycastle/asn1/ASN1ObjectIdentifier;
     361: ldc           #16                 // String 19
     363: invokevirtual #171                // Method org/bouncycastle/asn1/ASN1ObjectIdentifier.branch:(Ljava/lang/String;)Lorg/bouncycastle/asn1/ASN1ObjectIdentifier;
     366: invokespecial #172                // Method "<init>":(Lorg/bouncycastle/asn1/ASN1ObjectIdentifier;)V
     369: putstatic     #145                // Field id_kp_capwapWTP:Lorg/bouncycastle/asn1/x509/KeyPurposeId;
     372: new           #94                 // class org/bouncycastle/asn1/x509/KeyPurposeId
     375: dup
     376: new           #92                 // class org/bouncycastle/asn1/ASN1ObjectIdentifier
     379: dup
     380: ldc           #5                  // String 1.3.6.1.4.1.311.20.2.2
     382: invokespecial #169                // Method org/bouncycastle/asn1/ASN1ObjectIdentifier."<init>":(Ljava/lang/String;)V
     385: invokespecial #172                // Method "<init>":(Lorg/bouncycastle/asn1/ASN1ObjectIdentifier;)V
     388: putstatic     #164                // Field id_kp_smartcardlogon:Lorg/bouncycastle/asn1/x509/KeyPurposeId;
     391: new           #94                 // class org/bouncycastle/asn1/x509/KeyPurposeId
     394: dup
     395: new           #92                 // class org/bouncycastle/asn1/ASN1ObjectIdentifier
     398: dup
     399: ldc           #3                  // String 1.3.6.1.1.1.1.22
     401: invokespecial #169                // Method org/bouncycastle/asn1/ASN1ObjectIdentifier."<init>":(Ljava/lang/String;)V
     404: invokespecial #172                // Method "<init>":(Lorg/bouncycastle/asn1/ASN1ObjectIdentifier;)V
     407: putstatic     #156                // Field id_kp_macAddress:Lorg/bouncycastle/asn1/x509/KeyPurposeId;
     410: new           #94                 // class org/bouncycastle/asn1/x509/KeyPurposeId
     413: dup
     414: new           #92                 // class org/bouncycastle/asn1/ASN1ObjectIdentifier
     417: dup
     418: ldc           #4                  // String 1.3.6.1.4.1.311.10.3.3
     420: invokespecial #169                // Method org/bouncycastle/asn1/ASN1ObjectIdentifier."<init>":(Ljava/lang/String;)V
     423: invokespecial #172                // Method "<init>":(Lorg/bouncycastle/asn1/ASN1ObjectIdentifier;)V
     426: putstatic     #157                // Field id_kp_msSGC:Lorg/bouncycastle/asn1/x509/KeyPurposeId;
     429: new           #94                 // class org/bouncycastle/asn1/x509/KeyPurposeId
     432: dup
     433: new           #92                 // class org/bouncycastle/asn1/ASN1ObjectIdentifier
     436: dup
     437: ldc           #18                 // String 2.16.840.1.113730.4.1
     439: invokespecial #169                // Method org/bouncycastle/asn1/ASN1ObjectIdentifier."<init>":(Ljava/lang/String;)V
     442: invokespecial #172                // Method "<init>":(Lorg/bouncycastle/asn1/ASN1ObjectIdentifier;)V
     445: putstatic     #158                // Field id_kp_nsSGC:Lorg/bouncycastle/asn1/x509/KeyPurposeId;
     448: return
}
