Compiled from "DefaultMeasurementModel.java"
public class org.apache.commons.math3.filter.DefaultMeasurementModel implements org.apache.commons.math3.filter.MeasurementModel {
  private org.apache.commons.math3.linear.RealMatrix measurementMatrix;

  private org.apache.commons.math3.linear.RealMatrix measurementNoise;

  public org.apache.commons.math3.filter.DefaultMeasurementModel(double[][], double[][]) throws org.apache.commons.math3.exception.NullArgumentException, org.apache.commons.math3.exception.NoDataException, org.apache.commons.math3.exception.DimensionMismatchException;
    Code:
       0: aload_0
       1: new           #1                  // class org/apache/commons/math3/linear/Array2DRowRealMatrix
       4: dup
       5: aload_1
       6: invokespecial #2                  // Method org/apache/commons/math3/linear/Array2DRowRealMatrix."<init>":([[D)V
       9: new           #1                  // class org/apache/commons/math3/linear/Array2DRowRealMatrix
      12: dup
      13: aload_2
      14: invokespecial #2                  // Method org/apache/commons/math3/linear/Array2DRowRealMatrix."<init>":([[D)V
      17: invokespecial #3                  // Method "<init>":(Lorg/apache/commons/math3/linear/RealMatrix;Lorg/apache/commons/math3/linear/RealMatrix;)V
      20: return

  public org.apache.commons.math3.filter.DefaultMeasurementModel(org.apache.commons.math3.linear.RealMatrix, org.apache.commons.math3.linear.RealMatrix);
    Code:
       0: aload_0
       1: invokespecial #4                  // Method java/lang/Object."<init>":()V
       4: aload_0
       5: aload_1
       6: putfield      #5                  // Field measurementMatrix:Lorg/apache/commons/math3/linear/RealMatrix;
       9: aload_0
      10: aload_2
      11: putfield      #6                  // Field measurementNoise:Lorg/apache/commons/math3/linear/RealMatrix;
      14: return

  public org.apache.commons.math3.linear.RealMatrix getMeasurementMatrix();
    Code:
       0: aload_0
       1: getfield      #5                  // Field measurementMatrix:Lorg/apache/commons/math3/linear/RealMatrix;
       4: areturn

  public org.apache.commons.math3.linear.RealMatrix getMeasurementNoise();
    Code:
       0: aload_0
       1: getfield      #6                  // Field measurementNoise:Lorg/apache/commons/math3/linear/RealMatrix;
       4: areturn
}
