Compiled from "Gson.java"
class com.google.gson.Gson$5 extends com.google.gson.TypeAdapter<java.util.concurrent.atomic.AtomicLongArray> {
  final com.google.gson.TypeAdapter val$longAdapter;

  com.google.gson.Gson$5(com.google.gson.TypeAdapter);
    Code:
       0: aload_0
       1: aload_1
       2: putfield      #1                  // Field val$longAdapter:Lcom/google/gson/TypeAdapter;
       5: aload_0
       6: invokespecial #2                  // Method com/google/gson/TypeAdapter."<init>":()V
       9: return

  public void write(com.google.gson.stream.JsonWriter, java.util.concurrent.atomic.AtomicLongArray) throws java.io.IOException;
    Code:
       0: aload_1
       1: invokevirtual #3                  // Method com/google/gson/stream/JsonWriter.beginArray:()Lcom/google/gson/stream/JsonWriter;
       4: pop
       5: iconst_0
       6: istore_3
       7: aload_2
       8: invokevirtual #4                  // Method java/util/concurrent/atomic/AtomicLongArray.length:()I
      11: istore        4
      13: iload_3
      14: iload         4
      16: if_icmpge     41
      19: aload_0
      20: getfield      #1                  // Field val$longAdapter:Lcom/google/gson/TypeAdapter;
      23: aload_1
      24: aload_2
      25: iload_3
      26: invokevirtual #5                  // Method java/util/concurrent/atomic/AtomicLongArray.get:(I)J
      29: invokestatic  #6                  // Method java/lang/Long.valueOf:(J)Ljava/lang/Long;
      32: invokevirtual #7                  // Method com/google/gson/TypeAdapter.write:(Lcom/google/gson/stream/JsonWriter;Ljava/lang/Object;)V
      35: iinc          3, 1
      38: goto          13
      41: aload_1
      42: invokevirtual #8                  // Method com/google/gson/stream/JsonWriter.endArray:()Lcom/google/gson/stream/JsonWriter;
      45: pop
      46: return

  public java.util.concurrent.atomic.AtomicLongArray read(com.google.gson.stream.JsonReader) throws java.io.IOException;
    Code:
       0: new           #9                  // class java/util/ArrayList
       3: dup
       4: invokespecial #10                 // Method java/util/ArrayList."<init>":()V
       7: astore_2
       8: aload_1
       9: invokevirtual #11                 // Method com/google/gson/stream/JsonReader.beginArray:()V
      12: aload_1
      13: invokevirtual #12                 // Method com/google/gson/stream/JsonReader.hasNext:()Z
      16: ifeq          48
      19: aload_0
      20: getfield      #1                  // Field val$longAdapter:Lcom/google/gson/TypeAdapter;
      23: aload_1
      24: invokevirtual #13                 // Method com/google/gson/TypeAdapter.read:(Lcom/google/gson/stream/JsonReader;)Ljava/lang/Object;
      27: checkcast     #14                 // class java/lang/Number
      30: invokevirtual #15                 // Method java/lang/Number.longValue:()J
      33: lstore_3
      34: aload_2
      35: lload_3
      36: invokestatic  #6                  // Method java/lang/Long.valueOf:(J)Ljava/lang/Long;
      39: invokeinterface #16,  2           // InterfaceMethod java/util/List.add:(Ljava/lang/Object;)Z
      44: pop
      45: goto          12
      48: aload_1
      49: invokevirtual #17                 // Method com/google/gson/stream/JsonReader.endArray:()V
      52: aload_2
      53: invokeinterface #18,  1           // InterfaceMethod java/util/List.size:()I
      58: istore_3
      59: new           #19                 // class java/util/concurrent/atomic/AtomicLongArray
      62: dup
      63: iload_3
      64: invokespecial #20                 // Method java/util/concurrent/atomic/AtomicLongArray."<init>":(I)V
      67: astore        4
      69: iconst_0
      70: istore        5
      72: iload         5
      74: iload_3
      75: if_icmpge     105
      78: aload         4
      80: iload         5
      82: aload_2
      83: iload         5
      85: invokeinterface #21,  2           // InterfaceMethod java/util/List.get:(I)Ljava/lang/Object;
      90: checkcast     #22                 // class java/lang/Long
      93: invokevirtual #23                 // Method java/lang/Long.longValue:()J
      96: invokevirtual #24                 // Method java/util/concurrent/atomic/AtomicLongArray.set:(IJ)V
      99: iinc          5, 1
     102: goto          72
     105: aload         4
     107: areturn

  public java.lang.Object read(com.google.gson.stream.JsonReader) throws java.io.IOException;
    Code:
       0: aload_0
       1: aload_1
       2: invokevirtual #25                 // Method read:(Lcom/google/gson/stream/JsonReader;)Ljava/util/concurrent/atomic/AtomicLongArray;
       5: areturn

  public void write(com.google.gson.stream.JsonWriter, java.lang.Object) throws java.io.IOException;
    Code:
       0: aload_0
       1: aload_1
       2: aload_2
       3: checkcast     #19                 // class java/util/concurrent/atomic/AtomicLongArray
       6: invokevirtual #26                 // Method write:(Lcom/google/gson/stream/JsonWriter;Ljava/util/concurrent/atomic/AtomicLongArray;)V
       9: return
}
