Compiled from "LdapUserDetailsManager.java"
class org.springframework.security.ldap.userdetails.LdapUserDetailsManager$PasswordModifyRequest implements javax.naming.ldap.ExtendedRequest {
  private static final byte SEQUENCE_TYPE;

  private static final java.lang.String PASSWORD_MODIFY_OID;

  private static final byte USER_IDENTITY_OCTET_TYPE;

  private static final byte OLD_PASSWORD_OCTET_TYPE;

  private static final byte NEW_PASSWORD_OCTET_TYPE;

  private final java.io.ByteArrayOutputStream value;

  org.springframework.security.ldap.userdetails.LdapUserDetailsManager$PasswordModifyRequest(java.lang.String, java.lang.String, java.lang.String);
    Code:
       0: aload_0
       1: invokespecial #1                  // Method java/lang/Object."<init>":()V
       4: aload_0
       5: new           #2                  // class java/io/ByteArrayOutputStream
       8: dup
       9: invokespecial #3                  // Method java/io/ByteArrayOutputStream."<init>":()V
      12: putfield      #4                  // Field value:Ljava/io/ByteArrayOutputStream;
      15: new           #2                  // class java/io/ByteArrayOutputStream
      18: dup
      19: invokespecial #3                  // Method java/io/ByteArrayOutputStream."<init>":()V
      22: astore        4
      24: aload_1
      25: ifnull        40
      28: aload_0
      29: bipush        -128
      31: aload_1
      32: invokevirtual #6                  // Method java/lang/String.getBytes:()[B
      35: aload         4
      37: invokespecial #7                  // Method berEncode:(B[BLjava/io/ByteArrayOutputStream;)V
      40: aload_2
      41: ifnull        56
      44: aload_0
      45: bipush        -127
      47: aload_2
      48: invokevirtual #6                  // Method java/lang/String.getBytes:()[B
      51: aload         4
      53: invokespecial #7                  // Method berEncode:(B[BLjava/io/ByteArrayOutputStream;)V
      56: aload_3
      57: ifnull        72
      60: aload_0
      61: bipush        -126
      63: aload_3
      64: invokevirtual #6                  // Method java/lang/String.getBytes:()[B
      67: aload         4
      69: invokespecial #7                  // Method berEncode:(B[BLjava/io/ByteArrayOutputStream;)V
      72: aload_0
      73: bipush        48
      75: aload         4
      77: invokevirtual #8                  // Method java/io/ByteArrayOutputStream.toByteArray:()[B
      80: aload_0
      81: getfield      #4                  // Field value:Ljava/io/ByteArrayOutputStream;
      84: invokespecial #7                  // Method berEncode:(B[BLjava/io/ByteArrayOutputStream;)V
      87: return

  public java.lang.String getID();
    Code:
       0: ldc           #9                  // String 1.3.6.1.4.1.4203.1.11.1
       2: areturn

  public byte[] getEncodedValue();
    Code:
       0: aload_0
       1: getfield      #4                  // Field value:Ljava/io/ByteArrayOutputStream;
       4: invokevirtual #8                  // Method java/io/ByteArrayOutputStream.toByteArray:()[B
       7: areturn

  public javax.naming.ldap.ExtendedResponse createExtendedResponse(java.lang.String, byte[], int, int);
    Code:
       0: aconst_null
       1: areturn

  private void berEncode(byte, byte[], java.io.ByteArrayOutputStream);
    Code:
       0: aload_2
       1: arraylength
       2: istore        4
       4: aload_3
       5: iload_1
       6: invokevirtual #10                 // Method java/io/ByteArrayOutputStream.write:(I)V
       9: iload         4
      11: sipush        128
      14: if_icmpge     26
      17: aload_3
      18: iload         4
      20: invokevirtual #10                 // Method java/io/ByteArrayOutputStream.write:(I)V
      23: goto          218
      26: iload         4
      28: sipush        255
      31: iand
      32: iload         4
      34: if_icmpne     57
      37: aload_3
      38: bipush        -127
      40: invokevirtual #10                 // Method java/io/ByteArrayOutputStream.write:(I)V
      43: aload_3
      44: iload         4
      46: sipush        255
      49: iand
      50: i2b
      51: invokevirtual #10                 // Method java/io/ByteArrayOutputStream.write:(I)V
      54: goto          218
      57: iload         4
      59: ldc           #11                 // int 65535
      61: iand
      62: iload         4
      64: if_icmpne     101
      67: aload_3
      68: bipush        -126
      70: invokevirtual #10                 // Method java/io/ByteArrayOutputStream.write:(I)V
      73: aload_3
      74: iload         4
      76: bipush        8
      78: ishr
      79: sipush        255
      82: iand
      83: i2b
      84: invokevirtual #10                 // Method java/io/ByteArrayOutputStream.write:(I)V
      87: aload_3
      88: iload         4
      90: sipush        255
      93: iand
      94: i2b
      95: invokevirtual #10                 // Method java/io/ByteArrayOutputStream.write:(I)V
      98: goto          218
     101: iload         4
     103: ldc           #12                 // int 16777215
     105: iand
     106: iload         4
     108: if_icmpne     159
     111: aload_3
     112: bipush        -125
     114: invokevirtual #10                 // Method java/io/ByteArrayOutputStream.write:(I)V
     117: aload_3
     118: iload         4
     120: bipush        16
     122: ishr
     123: sipush        255
     126: iand
     127: i2b
     128: invokevirtual #10                 // Method java/io/ByteArrayOutputStream.write:(I)V
     131: aload_3
     132: iload         4
     134: bipush        8
     136: ishr
     137: sipush        255
     140: iand
     141: i2b
     142: invokevirtual #10                 // Method java/io/ByteArrayOutputStream.write:(I)V
     145: aload_3
     146: iload         4
     148: sipush        255
     151: iand
     152: i2b
     153: invokevirtual #10                 // Method java/io/ByteArrayOutputStream.write:(I)V
     156: goto          218
     159: aload_3
     160: bipush        -124
     162: invokevirtual #10                 // Method java/io/ByteArrayOutputStream.write:(I)V
     165: aload_3
     166: iload         4
     168: bipush        24
     170: ishr
     171: sipush        255
     174: iand
     175: i2b
     176: invokevirtual #10                 // Method java/io/ByteArrayOutputStream.write:(I)V
     179: aload_3
     180: iload         4
     182: bipush        16
     184: ishr
     185: sipush        255
     188: iand
     189: i2b
     190: invokevirtual #10                 // Method java/io/ByteArrayOutputStream.write:(I)V
     193: aload_3
     194: iload         4
     196: bipush        8
     198: ishr
     199: sipush        255
     202: iand
     203: i2b
     204: invokevirtual #10                 // Method java/io/ByteArrayOutputStream.write:(I)V
     207: aload_3
     208: iload         4
     210: sipush        255
     213: iand
     214: i2b
     215: invokevirtual #10                 // Method java/io/ByteArrayOutputStream.write:(I)V
     218: aload_3
     219: aload_2
     220: invokevirtual #13                 // Method java/io/ByteArrayOutputStream.write:([B)V
     223: goto          255
     226: astore        5
     228: new           #15                 // class java/lang/IllegalArgumentException
     231: dup
     232: new           #16                 // class java/lang/StringBuilder
     235: dup
     236: invokespecial #17                 // Method java/lang/StringBuilder."<init>":()V
     239: ldc           #18                 // String Failed to BER encode provided value of type:
     241: invokevirtual #19                 // Method java/lang/StringBuilder.append:(Ljava/lang/String;)Ljava/lang/StringBuilder;
     244: iload_1
     245: invokevirtual #20                 // Method java/lang/StringBuilder.append:(I)Ljava/lang/StringBuilder;
     248: invokevirtual #21                 // Method java/lang/StringBuilder.toString:()Ljava/lang/String;
     251: invokespecial #22                 // Method java/lang/IllegalArgumentException."<init>":(Ljava/lang/String;)V
     254: athrow
     255: return
    Exception table:
       from    to  target type
         218   223   226   Class java/io/IOException
}
