Compiled from "LdapUserDetailsImpl.java"
public class org.springframework.security.ldap.userdetails.LdapUserDetailsImpl$Essence {
  protected org.springframework.security.ldap.userdetails.LdapUserDetailsImpl instance;

  private java.util.List<org.springframework.security.core.GrantedAuthority> mutableAuthorities;

  public org.springframework.security.ldap.userdetails.LdapUserDetailsImpl$Essence();
    Code:
       0: aload_0
       1: invokespecial #1                  // Method java/lang/Object."<init>":()V
       4: aload_0
       5: aload_0
       6: invokevirtual #2                  // Method createTarget:()Lorg/springframework/security/ldap/userdetails/LdapUserDetailsImpl;
       9: putfield      #3                  // Field instance:Lorg/springframework/security/ldap/userdetails/LdapUserDetailsImpl;
      12: aload_0
      13: new           #4                  // class java/util/ArrayList
      16: dup
      17: invokespecial #5                  // Method java/util/ArrayList."<init>":()V
      20: putfield      #6                  // Field mutableAuthorities:Ljava/util/List;
      23: return

  public org.springframework.security.ldap.userdetails.LdapUserDetailsImpl$Essence(org.springframework.ldap.core.DirContextOperations);
    Code:
       0: aload_0
       1: invokespecial #1                  // Method java/lang/Object."<init>":()V
       4: aload_0
       5: aload_0
       6: invokevirtual #2                  // Method createTarget:()Lorg/springframework/security/ldap/userdetails/LdapUserDetailsImpl;
       9: putfield      #3                  // Field instance:Lorg/springframework/security/ldap/userdetails/LdapUserDetailsImpl;
      12: aload_0
      13: new           #4                  // class java/util/ArrayList
      16: dup
      17: invokespecial #5                  // Method java/util/ArrayList."<init>":()V
      20: putfield      #6                  // Field mutableAuthorities:Ljava/util/List;
      23: aload_0
      24: aload_1
      25: invokeinterface #7,  1            // InterfaceMethod org/springframework/ldap/core/DirContextOperations.getDn:()Ljavax/naming/Name;
      30: invokevirtual #8                  // Method setDn:(Ljavax/naming/Name;)V
      33: return

  public org.springframework.security.ldap.userdetails.LdapUserDetailsImpl$Essence(org.springframework.security.ldap.userdetails.LdapUserDetails);
    Code:
       0: aload_0
       1: invokespecial #1                  // Method java/lang/Object."<init>":()V
       4: aload_0
       5: aload_0
       6: invokevirtual #2                  // Method createTarget:()Lorg/springframework/security/ldap/userdetails/LdapUserDetailsImpl;
       9: putfield      #3                  // Field instance:Lorg/springframework/security/ldap/userdetails/LdapUserDetailsImpl;
      12: aload_0
      13: new           #4                  // class java/util/ArrayList
      16: dup
      17: invokespecial #5                  // Method java/util/ArrayList."<init>":()V
      20: putfield      #6                  // Field mutableAuthorities:Ljava/util/List;
      23: aload_0
      24: aload_1
      25: invokeinterface #9,  1            // InterfaceMethod org/springframework/security/ldap/userdetails/LdapUserDetails.getDn:()Ljava/lang/String;
      30: invokevirtual #10                 // Method setDn:(Ljava/lang/String;)V
      33: aload_0
      34: aload_1
      35: invokeinterface #11,  1           // InterfaceMethod org/springframework/security/ldap/userdetails/LdapUserDetails.getUsername:()Ljava/lang/String;
      40: invokevirtual #12                 // Method setUsername:(Ljava/lang/String;)V
      43: aload_0
      44: aload_1
      45: invokeinterface #13,  1           // InterfaceMethod org/springframework/security/ldap/userdetails/LdapUserDetails.getPassword:()Ljava/lang/String;
      50: invokevirtual #14                 // Method setPassword:(Ljava/lang/String;)V
      53: aload_0
      54: aload_1
      55: invokeinterface #15,  1           // InterfaceMethod org/springframework/security/ldap/userdetails/LdapUserDetails.isEnabled:()Z
      60: invokevirtual #16                 // Method setEnabled:(Z)V
      63: aload_0
      64: aload_1
      65: invokeinterface #17,  1           // InterfaceMethod org/springframework/security/ldap/userdetails/LdapUserDetails.isAccountNonExpired:()Z
      70: invokevirtual #18                 // Method setAccountNonExpired:(Z)V
      73: aload_0
      74: aload_1
      75: invokeinterface #19,  1           // InterfaceMethod org/springframework/security/ldap/userdetails/LdapUserDetails.isCredentialsNonExpired:()Z
      80: invokevirtual #20                 // Method setCredentialsNonExpired:(Z)V
      83: aload_0
      84: aload_1
      85: invokeinterface #21,  1           // InterfaceMethod org/springframework/security/ldap/userdetails/LdapUserDetails.isAccountNonLocked:()Z
      90: invokevirtual #22                 // Method setAccountNonLocked:(Z)V
      93: aload_0
      94: aload_1
      95: invokeinterface #23,  1           // InterfaceMethod org/springframework/security/ldap/userdetails/LdapUserDetails.getAuthorities:()Ljava/util/Collection;
     100: invokevirtual #24                 // Method setAuthorities:(Ljava/util/Collection;)V
     103: return

  protected org.springframework.security.ldap.userdetails.LdapUserDetailsImpl createTarget();
    Code:
       0: new           #25                 // class org/springframework/security/ldap/userdetails/LdapUserDetailsImpl
       3: dup
       4: invokespecial #26                 // Method org/springframework/security/ldap/userdetails/LdapUserDetailsImpl."<init>":()V
       7: areturn

  public void addAuthority(org.springframework.security.core.GrantedAuthority);
    Code:
       0: aload_0
       1: aload_1
       2: invokespecial #27                 // Method hasAuthority:(Lorg/springframework/security/core/GrantedAuthority;)Z
       5: ifne          19
       8: aload_0
       9: getfield      #6                  // Field mutableAuthorities:Ljava/util/List;
      12: aload_1
      13: invokeinterface #28,  2           // InterfaceMethod java/util/List.add:(Ljava/lang/Object;)Z
      18: pop
      19: return

  private boolean hasAuthority(org.springframework.security.core.GrantedAuthority);
    Code:
       0: aload_0
       1: getfield      #6                  // Field mutableAuthorities:Ljava/util/List;
       4: invokeinterface #29,  1           // InterfaceMethod java/util/List.iterator:()Ljava/util/Iterator;
       9: astore_2
      10: aload_2
      11: invokeinterface #30,  1           // InterfaceMethod java/util/Iterator.hasNext:()Z
      16: ifeq          42
      19: aload_2
      20: invokeinterface #31,  1           // InterfaceMethod java/util/Iterator.next:()Ljava/lang/Object;
      25: checkcast     #32                 // class org/springframework/security/core/GrantedAuthority
      28: astore_3
      29: aload_3
      30: aload_1
      31: invokevirtual #33                 // Method java/lang/Object.equals:(Ljava/lang/Object;)Z
      34: ifeq          39
      37: iconst_1
      38: ireturn
      39: goto          10
      42: iconst_0
      43: ireturn

  public org.springframework.security.ldap.userdetails.LdapUserDetails createUserDetails();
    Code:
       0: aload_0
       1: getfield      #3                  // Field instance:Lorg/springframework/security/ldap/userdetails/LdapUserDetailsImpl;
       4: ldc           #34                 // String Essence can only be used to create a single instance
       6: invokestatic  #35                 // Method org/springframework/util/Assert.notNull:(Ljava/lang/Object;Ljava/lang/String;)V
       9: aload_0
      10: getfield      #3                  // Field instance:Lorg/springframework/security/ldap/userdetails/LdapUserDetailsImpl;
      13: invokestatic  #36                 // Method org/springframework/security/ldap/userdetails/LdapUserDetailsImpl.access$000:(Lorg/springframework/security/ldap/userdetails/LdapUserDetailsImpl;)Ljava/lang/String;
      16: ldc           #37                 // String username must not be null
      18: invokestatic  #35                 // Method org/springframework/util/Assert.notNull:(Ljava/lang/Object;Ljava/lang/String;)V
      21: aload_0
      22: getfield      #3                  // Field instance:Lorg/springframework/security/ldap/userdetails/LdapUserDetailsImpl;
      25: invokevirtual #38                 // Method org/springframework/security/ldap/userdetails/LdapUserDetailsImpl.getDn:()Ljava/lang/String;
      28: ldc           #39                 // String Distinguished name must not be null
      30: invokestatic  #35                 // Method org/springframework/util/Assert.notNull:(Ljava/lang/Object;Ljava/lang/String;)V
      33: aload_0
      34: getfield      #3                  // Field instance:Lorg/springframework/security/ldap/userdetails/LdapUserDetailsImpl;
      37: aload_0
      38: getfield      #6                  // Field mutableAuthorities:Ljava/util/List;
      41: invokestatic  #40                 // Method java/util/Collections.unmodifiableList:(Ljava/util/List;)Ljava/util/List;
      44: invokestatic  #41                 // Method org/springframework/security/ldap/userdetails/LdapUserDetailsImpl.access$102:(Lorg/springframework/security/ldap/userdetails/LdapUserDetailsImpl;Ljava/util/Collection;)Ljava/util/Collection;
      47: pop
      48: aload_0
      49: getfield      #3                  // Field instance:Lorg/springframework/security/ldap/userdetails/LdapUserDetailsImpl;
      52: astore_1
      53: aload_0
      54: aconst_null
      55: putfield      #3                  // Field instance:Lorg/springframework/security/ldap/userdetails/LdapUserDetailsImpl;
      58: aload_1
      59: areturn

  public java.util.Collection<org.springframework.security.core.GrantedAuthority> getGrantedAuthorities();
    Code:
       0: aload_0
       1: getfield      #6                  // Field mutableAuthorities:Ljava/util/List;
       4: areturn

  public void setAccountNonExpired(boolean);
    Code:
       0: aload_0
       1: getfield      #3                  // Field instance:Lorg/springframework/security/ldap/userdetails/LdapUserDetailsImpl;
       4: iload_1
       5: invokestatic  #42                 // Method org/springframework/security/ldap/userdetails/LdapUserDetailsImpl.access$202:(Lorg/springframework/security/ldap/userdetails/LdapUserDetailsImpl;Z)Z
       8: pop
       9: return

  public void setAccountNonLocked(boolean);
    Code:
       0: aload_0
       1: getfield      #3                  // Field instance:Lorg/springframework/security/ldap/userdetails/LdapUserDetailsImpl;
       4: iload_1
       5: invokestatic  #43                 // Method org/springframework/security/ldap/userdetails/LdapUserDetailsImpl.access$302:(Lorg/springframework/security/ldap/userdetails/LdapUserDetailsImpl;Z)Z
       8: pop
       9: return

  public void setAuthorities(java.util.Collection<? extends org.springframework.security.core.GrantedAuthority>);
    Code:
       0: aload_0
       1: new           #4                  // class java/util/ArrayList
       4: dup
       5: invokespecial #5                  // Method java/util/ArrayList."<init>":()V
       8: putfield      #6                  // Field mutableAuthorities:Ljava/util/List;
      11: aload_0
      12: getfield      #6                  // Field mutableAuthorities:Ljava/util/List;
      15: aload_1
      16: invokeinterface #44,  2           // InterfaceMethod java/util/List.addAll:(Ljava/util/Collection;)Z
      21: pop
      22: return

  public void setCredentialsNonExpired(boolean);
    Code:
       0: aload_0
       1: getfield      #3                  // Field instance:Lorg/springframework/security/ldap/userdetails/LdapUserDetailsImpl;
       4: iload_1
       5: invokestatic  #45                 // Method org/springframework/security/ldap/userdetails/LdapUserDetailsImpl.access$402:(Lorg/springframework/security/ldap/userdetails/LdapUserDetailsImpl;Z)Z
       8: pop
       9: return

  public void setDn(java.lang.String);
    Code:
       0: aload_0
       1: getfield      #3                  // Field instance:Lorg/springframework/security/ldap/userdetails/LdapUserDetailsImpl;
       4: aload_1
       5: invokestatic  #46                 // Method org/springframework/security/ldap/userdetails/LdapUserDetailsImpl.access$502:(Lorg/springframework/security/ldap/userdetails/LdapUserDetailsImpl;Ljava/lang/String;)Ljava/lang/String;
       8: pop
       9: return

  public void setDn(javax.naming.Name);
    Code:
       0: aload_0
       1: getfield      #3                  // Field instance:Lorg/springframework/security/ldap/userdetails/LdapUserDetailsImpl;
       4: aload_1
       5: invokevirtual #47                 // Method java/lang/Object.toString:()Ljava/lang/String;
       8: invokestatic  #46                 // Method org/springframework/security/ldap/userdetails/LdapUserDetailsImpl.access$502:(Lorg/springframework/security/ldap/userdetails/LdapUserDetailsImpl;Ljava/lang/String;)Ljava/lang/String;
      11: pop
      12: return

  public void setEnabled(boolean);
    Code:
       0: aload_0
       1: getfield      #3                  // Field instance:Lorg/springframework/security/ldap/userdetails/LdapUserDetailsImpl;
       4: iload_1
       5: invokestatic  #48                 // Method org/springframework/security/ldap/userdetails/LdapUserDetailsImpl.access$602:(Lorg/springframework/security/ldap/userdetails/LdapUserDetailsImpl;Z)Z
       8: pop
       9: return

  public void setPassword(java.lang.String);
    Code:
       0: aload_0
       1: getfield      #3                  // Field instance:Lorg/springframework/security/ldap/userdetails/LdapUserDetailsImpl;
       4: aload_1
       5: invokestatic  #49                 // Method org/springframework/security/ldap/userdetails/LdapUserDetailsImpl.access$702:(Lorg/springframework/security/ldap/userdetails/LdapUserDetailsImpl;Ljava/lang/String;)Ljava/lang/String;
       8: pop
       9: return

  public void setUsername(java.lang.String);
    Code:
       0: aload_0
       1: getfield      #3                  // Field instance:Lorg/springframework/security/ldap/userdetails/LdapUserDetailsImpl;
       4: aload_1
       5: invokestatic  #50                 // Method org/springframework/security/ldap/userdetails/LdapUserDetailsImpl.access$002:(Lorg/springframework/security/ldap/userdetails/LdapUserDetailsImpl;Ljava/lang/String;)Ljava/lang/String;
       8: pop
       9: return

  public void setTimeBeforeExpiration(int);
    Code:
       0: aload_0
       1: getfield      #3                  // Field instance:Lorg/springframework/security/ldap/userdetails/LdapUserDetailsImpl;
       4: iload_1
       5: invokestatic  #51                 // Method org/springframework/security/ldap/userdetails/LdapUserDetailsImpl.access$802:(Lorg/springframework/security/ldap/userdetails/LdapUserDetailsImpl;I)I
       8: pop
       9: return

  public void setGraceLoginsRemaining(int);
    Code:
       0: aload_0
       1: getfield      #3                  // Field instance:Lorg/springframework/security/ldap/userdetails/LdapUserDetailsImpl;
       4: iload_1
       5: invokestatic  #52                 // Method org/springframework/security/ldap/userdetails/LdapUserDetailsImpl.access$902:(Lorg/springframework/security/ldap/userdetails/LdapUserDetailsImpl;I)I
       8: pop
       9: return
}
