Compiled from "FakeContainerFactory.java"
public class com.nimbusds.jose.shaded.json.parser.FakeContainerFactory implements com.nimbusds.jose.shaded.json.parser.ContainerFactory {
  public com.nimbusds.jose.shaded.json.parser.FakeContainerFactory$FackList list;

  public com.nimbusds.jose.shaded.json.parser.FakeContainerFactory$FackMap map;

  public com.nimbusds.jose.shaded.json.parser.FakeContainerFactory();
    Code:
       0: aload_0
       1: invokespecial #21                 // Method java/lang/Object."<init>":()V
       4: return

  public java.util.List<java.lang.Object> createArrayContainer();
    Code:
       0: aload_0
       1: getfield      #28                 // Field list:Lcom/nimbusds/jose/shaded/json/parser/FakeContainerFactory$FackList;
       4: ifnonnull     18
       7: aload_0
       8: new           #9                  // class com/nimbusds/jose/shaded/json/parser/FakeContainerFactory$FackList
      11: dup
      12: invokespecial #29                 // Method com/nimbusds/jose/shaded/json/parser/FakeContainerFactory$FackList."<init>":()V
      15: putfield      #28                 // Field list:Lcom/nimbusds/jose/shaded/json/parser/FakeContainerFactory$FackList;
      18: aload_0
      19: getfield      #28                 // Field list:Lcom/nimbusds/jose/shaded/json/parser/FakeContainerFactory$FackList;
      22: areturn

  public java.util.Map<java.lang.String, java.lang.Object> createObjectContainer();
    Code:
       0: aload_0
       1: getfield      #34                 // Field map:Lcom/nimbusds/jose/shaded/json/parser/FakeContainerFactory$FackMap;
       4: ifnonnull     18
       7: aload_0
       8: new           #12                 // class com/nimbusds/jose/shaded/json/parser/FakeContainerFactory$FackMap
      11: dup
      12: invokespecial #35                 // Method com/nimbusds/jose/shaded/json/parser/FakeContainerFactory$FackMap."<init>":()V
      15: putfield      #34                 // Field map:Lcom/nimbusds/jose/shaded/json/parser/FakeContainerFactory$FackMap;
      18: aload_0
      19: getfield      #34                 // Field map:Lcom/nimbusds/jose/shaded/json/parser/FakeContainerFactory$FackMap;
      22: areturn
}
