Compiled from "RepeatApplyIterator.java"
public abstract class org.apache.jena.atlas.iterator.RepeatApplyIterator<T> implements java.util.Iterator<T>, org.apache.jena.atlas.lib.Closeable {
  private java.util.Iterator<T> input;

  private boolean finished;

  private java.util.Iterator<T> currentStage;

  protected org.apache.jena.atlas.iterator.RepeatApplyIterator(java.util.Iterator<T>);
    Code:
       0: aload_0
       1: invokespecial #1                  // Method java/lang/Object."<init>":()V
       4: aload_0
       5: iconst_0
       6: putfield      #2                  // Field finished:Z
       9: aload_0
      10: aconst_null
      11: putfield      #3                  // Field currentStage:Ljava/util/Iterator;
      14: aload_0
      15: aload_1
      16: putfield      #4                  // Field input:Ljava/util/Iterator;
      19: return

  public boolean hasNext();
    Code:
       0: aload_0
       1: getfield      #2                  // Field finished:Z
       4: ifeq          9
       7: iconst_0
       8: ireturn
       9: aload_0
      10: getfield      #3                  // Field currentStage:Ljava/util/Iterator;
      13: ifnonnull     47
      16: aload_0
      17: getfield      #4                  // Field input:Ljava/util/Iterator;
      20: invokeinterface #5,  1            // InterfaceMethod java/util/Iterator.hasNext:()Z
      25: ifeq          47
      28: aload_0
      29: getfield      #4                  // Field input:Ljava/util/Iterator;
      32: invokeinterface #6,  1            // InterfaceMethod java/util/Iterator.next:()Ljava/lang/Object;
      37: astore_1
      38: aload_0
      39: aload_0
      40: aload_1
      41: invokevirtual #7                  // Method makeNextStage:(Ljava/lang/Object;)Ljava/util/Iterator;
      44: putfield      #3                  // Field currentStage:Ljava/util/Iterator;
      47: aload_0
      48: getfield      #3                  // Field currentStage:Ljava/util/Iterator;
      51: ifnonnull     65
      54: aload_0
      55: invokevirtual #8                  // Method hasFinished:()V
      58: aload_0
      59: iconst_1
      60: putfield      #2                  // Field finished:Z
      63: iconst_0
      64: ireturn
      65: aload_0
      66: getfield      #3                  // Field currentStage:Ljava/util/Iterator;
      69: invokeinterface #5,  1            // InterfaceMethod java/util/Iterator.hasNext:()Z
      74: ifeq          79
      77: iconst_1
      78: ireturn
      79: aload_0
      80: aconst_null
      81: putfield      #3                  // Field currentStage:Ljava/util/Iterator;
      84: goto          9

  protected abstract java.util.Iterator<T> makeNextStage(T);

  protected void hasFinished();
    Code:
       0: return

  public T next();
    Code:
       0: aload_0
       1: invokevirtual #9                  // Method hasNext:()Z
       4: ifne          37
       7: new           #10                 // class java/util/NoSuchElementException
      10: dup
      11: new           #11                 // class java/lang/StringBuilder
      14: dup
      15: invokespecial #12                 // Method java/lang/StringBuilder."<init>":()V
      18: aload_0
      19: invokestatic  #13                 // Method org/apache/jena/atlas/lib/Lib.className:(Ljava/lang/Object;)Ljava/lang/String;
      22: invokevirtual #14                 // Method java/lang/StringBuilder.append:(Ljava/lang/String;)Ljava/lang/StringBuilder;
      25: ldc           #15                 // String .next()/finished
      27: invokevirtual #14                 // Method java/lang/StringBuilder.append:(Ljava/lang/String;)Ljava/lang/StringBuilder;
      30: invokevirtual #16                 // Method java/lang/StringBuilder.toString:()Ljava/lang/String;
      33: invokespecial #17                 // Method java/util/NoSuchElementException."<init>":(Ljava/lang/String;)V
      36: athrow
      37: aload_0
      38: getfield      #3                  // Field currentStage:Ljava/util/Iterator;
      41: invokeinterface #6,  1            // InterfaceMethod java/util/Iterator.next:()Ljava/lang/Object;
      46: areturn

  public final void remove();
    Code:
       0: new           #18                 // class java/lang/UnsupportedOperationException
       3: dup
       4: invokespecial #19                 // Method java/lang/UnsupportedOperationException."<init>":()V
       7: athrow

  public void close();
    Code:
       0: aload_0
       1: getfield      #4                  // Field input:Ljava/util/Iterator;
       4: invokestatic  #20                 // Method org/apache/jena/atlas/iterator/Iter.close:(Ljava/util/Iterator;)V
       7: return
}
