Compiled from "DefaultTranscriptEvent.java"
public final class software.amazon.awssdk.services.lexruntimev2.model.startconversationresponseeventstream.DefaultTranscriptEvent extends software.amazon.awssdk.services.lexruntimev2.model.TranscriptEvent {
  private static final long serialVersionUID;

  software.amazon.awssdk.services.lexruntimev2.model.startconversationresponseeventstream.DefaultTranscriptEvent(software.amazon.awssdk.services.lexruntimev2.model.startconversationresponseeventstream.DefaultTranscriptEvent$BuilderImpl);
    Code:
       0: aload_0
       1: aload_1
       2: invokespecial #1                  // Method software/amazon/awssdk/services/lexruntimev2/model/TranscriptEvent."<init>":(Lsoftware/amazon/awssdk/services/lexruntimev2/model/TranscriptEvent$BuilderImpl;)V
       5: return

  public software.amazon.awssdk.services.lexruntimev2.model.startconversationresponseeventstream.DefaultTranscriptEvent$Builder toBuilder();
    Code:
       0: new           #2                  // class software/amazon/awssdk/services/lexruntimev2/model/startconversationresponseeventstream/DefaultTranscriptEvent$BuilderImpl
       3: dup
       4: aload_0
       5: aconst_null
       6: invokespecial #3                  // Method software/amazon/awssdk/services/lexruntimev2/model/startconversationresponseeventstream/DefaultTranscriptEvent$BuilderImpl."<init>":(Lsoftware/amazon/awssdk/services/lexruntimev2/model/startconversationresponseeventstream/DefaultTranscriptEvent;Lsoftware/amazon/awssdk/services/lexruntimev2/model/startconversationresponseeventstream/DefaultTranscriptEvent$1;)V
       9: areturn

  public static software.amazon.awssdk.services.lexruntimev2.model.startconversationresponseeventstream.DefaultTranscriptEvent$Builder builder();
    Code:
       0: new           #2                  // class software/amazon/awssdk/services/lexruntimev2/model/startconversationresponseeventstream/DefaultTranscriptEvent$BuilderImpl
       3: dup
       4: aconst_null
       5: invokespecial #4                  // Method software/amazon/awssdk/services/lexruntimev2/model/startconversationresponseeventstream/DefaultTranscriptEvent$BuilderImpl."<init>":(Lsoftware/amazon/awssdk/services/lexruntimev2/model/startconversationresponseeventstream/DefaultTranscriptEvent$1;)V
       8: areturn

  public void accept(software.amazon.awssdk.services.lexruntimev2.model.StartConversationResponseHandler$Visitor);
    Code:
       0: aload_1
       1: aload_0
       2: invokeinterface #5,  2            // InterfaceMethod software/amazon/awssdk/services/lexruntimev2/model/StartConversationResponseHandler$Visitor.visitTranscriptEvent:(Lsoftware/amazon/awssdk/services/lexruntimev2/model/TranscriptEvent;)V
       7: return

  public software.amazon.awssdk.services.lexruntimev2.model.StartConversationResponseEventStream$EventType sdkEventType();
    Code:
       0: getstatic     #6                  // Field software/amazon/awssdk/services/lexruntimev2/model/StartConversationResponseEventStream$EventType.TRANSCRIPT_EVENT:Lsoftware/amazon/awssdk/services/lexruntimev2/model/StartConversationResponseEventStream$EventType;
       3: areturn

  public software.amazon.awssdk.services.lexruntimev2.model.TranscriptEvent$Builder toBuilder();
    Code:
       0: aload_0
       1: invokevirtual #7                  // Method toBuilder:()Lsoftware/amazon/awssdk/services/lexruntimev2/model/startconversationresponseeventstream/DefaultTranscriptEvent$Builder;
       4: areturn

  public software.amazon.awssdk.utils.builder.CopyableBuilder toBuilder();
    Code:
       0: aload_0
       1: invokevirtual #7                  // Method toBuilder:()Lsoftware/amazon/awssdk/services/lexruntimev2/model/startconversationresponseeventstream/DefaultTranscriptEvent$Builder;
       4: areturn
}
