Compiled from "AnnotationBeanWiringInfoResolver.java"
public class org.springframework.beans.factory.annotation.AnnotationBeanWiringInfoResolver implements org.springframework.beans.factory.wiring.BeanWiringInfoResolver {
  public org.springframework.beans.factory.annotation.AnnotationBeanWiringInfoResolver();
    Code:
       0: aload_0
       1: invokespecial #1                  // Method java/lang/Object."<init>":()V
       4: return

  public org.springframework.beans.factory.wiring.BeanWiringInfo resolveWiringInfo(java.lang.Object);
    Code:
       0: aload_1
       1: ldc           #2                  // String Bean instance must not be null
       3: invokestatic  #3                  // Method org/springframework/util/Assert.notNull:(Ljava/lang/Object;Ljava/lang/String;)V
       6: aload_1
       7: invokevirtual #4                  // Method java/lang/Object.getClass:()Ljava/lang/Class;
      10: ldc           #5                  // class org/springframework/beans/factory/annotation/Configurable
      12: invokevirtual #6                  // Method java/lang/Class.getAnnotation:(Ljava/lang/Class;)Ljava/lang/annotation/Annotation;
      15: checkcast     #5                  // class org/springframework/beans/factory/annotation/Configurable
      18: astore_2
      19: aload_2
      20: ifnull        32
      23: aload_0
      24: aload_1
      25: aload_2
      26: invokevirtual #7                  // Method buildWiringInfo:(Ljava/lang/Object;Lorg/springframework/beans/factory/annotation/Configurable;)Lorg/springframework/beans/factory/wiring/BeanWiringInfo;
      29: goto          33
      32: aconst_null
      33: areturn

  protected org.springframework.beans.factory.wiring.BeanWiringInfo buildWiringInfo(java.lang.Object, org.springframework.beans.factory.annotation.Configurable);
    Code:
       0: getstatic     #8                  // Field org/springframework/beans/factory/annotation/Autowire.NO:Lorg/springframework/beans/factory/annotation/Autowire;
       3: aload_2
       4: invokeinterface #9,  1            // InterfaceMethod org/springframework/beans/factory/annotation/Configurable.autowire:()Lorg/springframework/beans/factory/annotation/Autowire;
       9: invokevirtual #10                 // Method org/springframework/beans/factory/annotation/Autowire.equals:(Ljava/lang/Object;)Z
      12: ifne          38
      15: new           #11                 // class org/springframework/beans/factory/wiring/BeanWiringInfo
      18: dup
      19: aload_2
      20: invokeinterface #9,  1            // InterfaceMethod org/springframework/beans/factory/annotation/Configurable.autowire:()Lorg/springframework/beans/factory/annotation/Autowire;
      25: invokevirtual #12                 // Method org/springframework/beans/factory/annotation/Autowire.value:()I
      28: aload_2
      29: invokeinterface #13,  1           // InterfaceMethod org/springframework/beans/factory/annotation/Configurable.dependencyCheck:()Z
      34: invokespecial #14                 // Method org/springframework/beans/factory/wiring/BeanWiringInfo."<init>":(IZ)V
      37: areturn
      38: ldc           #15                 // String
      40: aload_2
      41: invokeinterface #16,  1           // InterfaceMethod org/springframework/beans/factory/annotation/Configurable.value:()Ljava/lang/String;
      46: invokevirtual #17                 // Method java/lang/String.equals:(Ljava/lang/Object;)Z
      49: ifne          67
      52: new           #11                 // class org/springframework/beans/factory/wiring/BeanWiringInfo
      55: dup
      56: aload_2
      57: invokeinterface #16,  1           // InterfaceMethod org/springframework/beans/factory/annotation/Configurable.value:()Ljava/lang/String;
      62: iconst_0
      63: invokespecial #18                 // Method org/springframework/beans/factory/wiring/BeanWiringInfo."<init>":(Ljava/lang/String;Z)V
      66: areturn
      67: new           #11                 // class org/springframework/beans/factory/wiring/BeanWiringInfo
      70: dup
      71: aload_0
      72: aload_1
      73: invokevirtual #19                 // Method getDefaultBeanName:(Ljava/lang/Object;)Ljava/lang/String;
      76: iconst_1
      77: invokespecial #18                 // Method org/springframework/beans/factory/wiring/BeanWiringInfo."<init>":(Ljava/lang/String;Z)V
      80: areturn

  protected java.lang.String getDefaultBeanName(java.lang.Object);
    Code:
       0: aload_1
       1: invokestatic  #20                 // Method org/springframework/util/ClassUtils.getUserClass:(Ljava/lang/Object;)Ljava/lang/Class;
       4: invokevirtual #21                 // Method java/lang/Class.getName:()Ljava/lang/String;
       7: areturn
}
