Compiled from "Factory.java"
public final class org.aspectj.runtime.reflect.Factory {
  java.lang.Class lexicalClass;

  java.lang.ClassLoader lookupClassLoader;

  java.lang.String filename;

  int count;

  private static final java.lang.Class[] NO_TYPES;

  private static final java.lang.String[] NO_STRINGS;

  static java.util.Hashtable prims;

  private static java.lang.Object[] NO_ARGS;

  static java.lang.Class makeClass(java.lang.String, java.lang.ClassLoader);
    Code:
       0: aload_0
       1: ldc           #1                  // String *
       3: invokevirtual #2                  // Method java/lang/String.equals:(Ljava/lang/Object;)Z
       6: ifeq          11
       9: aconst_null
      10: areturn
      11: getstatic     #3                  // Field prims:Ljava/util/Hashtable;
      14: aload_0
      15: invokevirtual #4                  // Method java/util/Hashtable.get:(Ljava/lang/Object;)Ljava/lang/Object;
      18: checkcast     #5                  // class java/lang/Class
      21: astore_2
      22: aload_2
      23: ifnull        28
      26: aload_2
      27: areturn
      28: aload_1
      29: ifnonnull     37
      32: aload_0
      33: invokestatic  #6                  // Method java/lang/Class.forName:(Ljava/lang/String;)Ljava/lang/Class;
      36: areturn
      37: aload_0
      38: iconst_0
      39: aload_1
      40: invokestatic  #7                  // Method java/lang/Class.forName:(Ljava/lang/String;ZLjava/lang/ClassLoader;)Ljava/lang/Class;
      43: areturn
      44: astore_3
      45: ldc           #8                  // class java/lang/ClassNotFoundException
      47: areturn
    Exception table:
       from    to  target type
          28    36    44   Class java/lang/ClassNotFoundException
          37    43    44   Class java/lang/ClassNotFoundException

  public org.aspectj.runtime.reflect.Factory(java.lang.String, java.lang.Class);
    Code:
       0: aload_0
       1: invokespecial #9                  // Method java/lang/Object."<init>":()V
       4: aload_0
       5: aload_1
       6: putfield      #10                 // Field filename:Ljava/lang/String;
       9: aload_0
      10: aload_2
      11: putfield      #11                 // Field lexicalClass:Ljava/lang/Class;
      14: aload_0
      15: iconst_0
      16: putfield      #12                 // Field count:I
      19: aload_0
      20: aload_2
      21: invokevirtual #13                 // Method java/lang/Class.getClassLoader:()Ljava/lang/ClassLoader;
      24: putfield      #14                 // Field lookupClassLoader:Ljava/lang/ClassLoader;
      27: return

  public org.aspectj.lang.JoinPoint$StaticPart makeSJP(java.lang.String, java.lang.String, java.lang.String, java.lang.String, java.lang.String, java.lang.String, java.lang.String, java.lang.String, int);
    Code:
       0: aload_0
       1: aload_2
       2: aload_3
       3: aload         4
       5: aload         5
       7: aload         6
       9: aload         7
      11: aload         8
      13: invokevirtual #15                 // Method makeMethodSig:(Ljava/lang/String;Ljava/lang/String;Ljava/lang/String;Ljava/lang/String;Ljava/lang/String;Ljava/lang/String;Ljava/lang/String;)Lorg/aspectj/lang/reflect/MethodSignature;
      16: astore        10
      18: new           #16                 // class org/aspectj/runtime/reflect/JoinPointImpl$StaticPartImpl
      21: dup
      22: aload_0
      23: dup
      24: getfield      #12                 // Field count:I
      27: dup_x1
      28: iconst_1
      29: iadd
      30: putfield      #12                 // Field count:I
      33: aload_1
      34: aload         10
      36: aload_0
      37: iload         9
      39: iconst_m1
      40: invokevirtual #17                 // Method makeSourceLoc:(II)Lorg/aspectj/lang/reflect/SourceLocation;
      43: invokespecial #18                 // Method org/aspectj/runtime/reflect/JoinPointImpl$StaticPartImpl."<init>":(ILjava/lang/String;Lorg/aspectj/lang/Signature;Lorg/aspectj/lang/reflect/SourceLocation;)V
      46: areturn

  public org.aspectj.lang.JoinPoint$StaticPart makeSJP(java.lang.String, java.lang.String, java.lang.String, java.lang.String, java.lang.String, java.lang.String, java.lang.String, int);
    Code:
       0: aload_0
       1: aload_2
       2: aload_3
       3: aload         4
       5: aload         5
       7: aload         6
       9: ldc           #19                 // String
      11: aload         7
      13: invokevirtual #15                 // Method makeMethodSig:(Ljava/lang/String;Ljava/lang/String;Ljava/lang/String;Ljava/lang/String;Ljava/lang/String;Ljava/lang/String;Ljava/lang/String;)Lorg/aspectj/lang/reflect/MethodSignature;
      16: astore        9
      18: new           #16                 // class org/aspectj/runtime/reflect/JoinPointImpl$StaticPartImpl
      21: dup
      22: aload_0
      23: dup
      24: getfield      #12                 // Field count:I
      27: dup_x1
      28: iconst_1
      29: iadd
      30: putfield      #12                 // Field count:I
      33: aload_1
      34: aload         9
      36: aload_0
      37: iload         8
      39: iconst_m1
      40: invokevirtual #17                 // Method makeSourceLoc:(II)Lorg/aspectj/lang/reflect/SourceLocation;
      43: invokespecial #18                 // Method org/aspectj/runtime/reflect/JoinPointImpl$StaticPartImpl."<init>":(ILjava/lang/String;Lorg/aspectj/lang/Signature;Lorg/aspectj/lang/reflect/SourceLocation;)V
      46: areturn

  public org.aspectj.lang.JoinPoint$StaticPart makeMethodSJP(java.lang.String, int, java.lang.String, java.lang.Class, java.lang.Class[], java.lang.String[], java.lang.Class[], java.lang.Class, int);
    Code:
       0: aload_0
       1: iload_2
       2: aload_3
       3: aload         4
       5: aload         5
       7: ifnonnull     16
      10: getstatic     #20                 // Field NO_TYPES:[Ljava/lang/Class;
      13: goto          18
      16: aload         5
      18: aload         6
      20: ifnonnull     29
      23: getstatic     #21                 // Field NO_STRINGS:[Ljava/lang/String;
      26: goto          31
      29: aload         6
      31: aload         7
      33: ifnonnull     42
      36: getstatic     #20                 // Field NO_TYPES:[Ljava/lang/Class;
      39: goto          44
      42: aload         7
      44: aload         8
      46: ifnonnull     55
      49: getstatic     #22                 // Field java/lang/Void.TYPE:Ljava/lang/Class;
      52: goto          57
      55: aload         8
      57: invokevirtual #23                 // Method makeMethodSig:(ILjava/lang/String;Ljava/lang/Class;[Ljava/lang/Class;[Ljava/lang/String;[Ljava/lang/Class;Ljava/lang/Class;)Lorg/aspectj/lang/reflect/MethodSignature;
      60: astore        10
      62: new           #16                 // class org/aspectj/runtime/reflect/JoinPointImpl$StaticPartImpl
      65: dup
      66: aload_0
      67: dup
      68: getfield      #12                 // Field count:I
      71: dup_x1
      72: iconst_1
      73: iadd
      74: putfield      #12                 // Field count:I
      77: aload_1
      78: aload         10
      80: aload_0
      81: iload         9
      83: iconst_m1
      84: invokevirtual #17                 // Method makeSourceLoc:(II)Lorg/aspectj/lang/reflect/SourceLocation;
      87: invokespecial #18                 // Method org/aspectj/runtime/reflect/JoinPointImpl$StaticPartImpl."<init>":(ILjava/lang/String;Lorg/aspectj/lang/Signature;Lorg/aspectj/lang/reflect/SourceLocation;)V
      90: areturn

  public org.aspectj.lang.JoinPoint$EnclosingStaticPart makeMethodESJP(java.lang.String, int, java.lang.String, java.lang.Class, java.lang.Class[], java.lang.String[], java.lang.Class[], java.lang.Class, int);
    Code:
       0: aload_0
       1: iload_2
       2: aload_3
       3: aload         4
       5: aload         5
       7: ifnonnull     16
      10: getstatic     #20                 // Field NO_TYPES:[Ljava/lang/Class;
      13: goto          18
      16: aload         5
      18: aload         6
      20: ifnonnull     29
      23: getstatic     #21                 // Field NO_STRINGS:[Ljava/lang/String;
      26: goto          31
      29: aload         6
      31: aload         7
      33: ifnonnull     42
      36: getstatic     #20                 // Field NO_TYPES:[Ljava/lang/Class;
      39: goto          44
      42: aload         7
      44: aload         8
      46: ifnonnull     55
      49: getstatic     #22                 // Field java/lang/Void.TYPE:Ljava/lang/Class;
      52: goto          57
      55: aload         8
      57: invokevirtual #23                 // Method makeMethodSig:(ILjava/lang/String;Ljava/lang/Class;[Ljava/lang/Class;[Ljava/lang/String;[Ljava/lang/Class;Ljava/lang/Class;)Lorg/aspectj/lang/reflect/MethodSignature;
      60: astore        10
      62: new           #24                 // class org/aspectj/runtime/reflect/JoinPointImpl$EnclosingStaticPartImpl
      65: dup
      66: aload_0
      67: dup
      68: getfield      #12                 // Field count:I
      71: dup_x1
      72: iconst_1
      73: iadd
      74: putfield      #12                 // Field count:I
      77: aload_1
      78: aload         10
      80: aload_0
      81: iload         9
      83: iconst_m1
      84: invokevirtual #17                 // Method makeSourceLoc:(II)Lorg/aspectj/lang/reflect/SourceLocation;
      87: invokespecial #25                 // Method org/aspectj/runtime/reflect/JoinPointImpl$EnclosingStaticPartImpl."<init>":(ILjava/lang/String;Lorg/aspectj/lang/Signature;Lorg/aspectj/lang/reflect/SourceLocation;)V
      90: areturn

  public org.aspectj.lang.JoinPoint$StaticPart makeConstructorSJP(java.lang.String, int, java.lang.Class, java.lang.Class[], java.lang.String[], java.lang.Class[], int);
    Code:
       0: new           #26                 // class org/aspectj/runtime/reflect/ConstructorSignatureImpl
       3: dup
       4: iload_2
       5: aload_3
       6: aload         4
       8: ifnonnull     17
      11: getstatic     #20                 // Field NO_TYPES:[Ljava/lang/Class;
      14: goto          19
      17: aload         4
      19: aload         5
      21: ifnonnull     30
      24: getstatic     #21                 // Field NO_STRINGS:[Ljava/lang/String;
      27: goto          32
      30: aload         5
      32: aload         6
      34: ifnonnull     43
      37: getstatic     #20                 // Field NO_TYPES:[Ljava/lang/Class;
      40: goto          45
      43: aload         6
      45: invokespecial #27                 // Method org/aspectj/runtime/reflect/ConstructorSignatureImpl."<init>":(ILjava/lang/Class;[Ljava/lang/Class;[Ljava/lang/String;[Ljava/lang/Class;)V
      48: astore        8
      50: new           #16                 // class org/aspectj/runtime/reflect/JoinPointImpl$StaticPartImpl
      53: dup
      54: aload_0
      55: dup
      56: getfield      #12                 // Field count:I
      59: dup_x1
      60: iconst_1
      61: iadd
      62: putfield      #12                 // Field count:I
      65: aload_1
      66: aload         8
      68: aload_0
      69: iload         7
      71: iconst_m1
      72: invokevirtual #17                 // Method makeSourceLoc:(II)Lorg/aspectj/lang/reflect/SourceLocation;
      75: invokespecial #18                 // Method org/aspectj/runtime/reflect/JoinPointImpl$StaticPartImpl."<init>":(ILjava/lang/String;Lorg/aspectj/lang/Signature;Lorg/aspectj/lang/reflect/SourceLocation;)V
      78: areturn

  public org.aspectj.lang.JoinPoint$EnclosingStaticPart makeConstructorESJP(java.lang.String, int, java.lang.Class, java.lang.Class[], java.lang.String[], java.lang.Class[], int);
    Code:
       0: new           #26                 // class org/aspectj/runtime/reflect/ConstructorSignatureImpl
       3: dup
       4: iload_2
       5: aload_3
       6: aload         4
       8: ifnonnull     17
      11: getstatic     #20                 // Field NO_TYPES:[Ljava/lang/Class;
      14: goto          19
      17: aload         4
      19: aload         5
      21: ifnonnull     30
      24: getstatic     #21                 // Field NO_STRINGS:[Ljava/lang/String;
      27: goto          32
      30: aload         5
      32: aload         6
      34: ifnonnull     43
      37: getstatic     #20                 // Field NO_TYPES:[Ljava/lang/Class;
      40: goto          45
      43: aload         6
      45: invokespecial #27                 // Method org/aspectj/runtime/reflect/ConstructorSignatureImpl."<init>":(ILjava/lang/Class;[Ljava/lang/Class;[Ljava/lang/String;[Ljava/lang/Class;)V
      48: astore        8
      50: new           #24                 // class org/aspectj/runtime/reflect/JoinPointImpl$EnclosingStaticPartImpl
      53: dup
      54: aload_0
      55: dup
      56: getfield      #12                 // Field count:I
      59: dup_x1
      60: iconst_1
      61: iadd
      62: putfield      #12                 // Field count:I
      65: aload_1
      66: aload         8
      68: aload_0
      69: iload         7
      71: iconst_m1
      72: invokevirtual #17                 // Method makeSourceLoc:(II)Lorg/aspectj/lang/reflect/SourceLocation;
      75: invokespecial #25                 // Method org/aspectj/runtime/reflect/JoinPointImpl$EnclosingStaticPartImpl."<init>":(ILjava/lang/String;Lorg/aspectj/lang/Signature;Lorg/aspectj/lang/reflect/SourceLocation;)V
      78: areturn

  public org.aspectj.lang.JoinPoint$StaticPart makeCatchClauseSJP(java.lang.String, java.lang.Class, java.lang.Class, java.lang.String, int);
    Code:
       0: new           #28                 // class org/aspectj/runtime/reflect/CatchClauseSignatureImpl
       3: dup
       4: aload_2
       5: aload_3
       6: aload         4
       8: ifnonnull     16
      11: ldc           #19                 // String
      13: goto          18
      16: aload         4
      18: invokespecial #29                 // Method org/aspectj/runtime/reflect/CatchClauseSignatureImpl."<init>":(Ljava/lang/Class;Ljava/lang/Class;Ljava/lang/String;)V
      21: astore        6
      23: new           #16                 // class org/aspectj/runtime/reflect/JoinPointImpl$StaticPartImpl
      26: dup
      27: aload_0
      28: dup
      29: getfield      #12                 // Field count:I
      32: dup_x1
      33: iconst_1
      34: iadd
      35: putfield      #12                 // Field count:I
      38: aload_1
      39: aload         6
      41: aload_0
      42: iload         5
      44: iconst_m1
      45: invokevirtual #17                 // Method makeSourceLoc:(II)Lorg/aspectj/lang/reflect/SourceLocation;
      48: invokespecial #18                 // Method org/aspectj/runtime/reflect/JoinPointImpl$StaticPartImpl."<init>":(ILjava/lang/String;Lorg/aspectj/lang/Signature;Lorg/aspectj/lang/reflect/SourceLocation;)V
      51: areturn

  public org.aspectj.lang.JoinPoint$EnclosingStaticPart makeCatchClauseESJP(java.lang.String, java.lang.Class, java.lang.Class, java.lang.String, int);
    Code:
       0: new           #28                 // class org/aspectj/runtime/reflect/CatchClauseSignatureImpl
       3: dup
       4: aload_2
       5: aload_3
       6: aload         4
       8: ifnonnull     16
      11: ldc           #19                 // String
      13: goto          18
      16: aload         4
      18: invokespecial #29                 // Method org/aspectj/runtime/reflect/CatchClauseSignatureImpl."<init>":(Ljava/lang/Class;Ljava/lang/Class;Ljava/lang/String;)V
      21: astore        6
      23: new           #24                 // class org/aspectj/runtime/reflect/JoinPointImpl$EnclosingStaticPartImpl
      26: dup
      27: aload_0
      28: dup
      29: getfield      #12                 // Field count:I
      32: dup_x1
      33: iconst_1
      34: iadd
      35: putfield      #12                 // Field count:I
      38: aload_1
      39: aload         6
      41: aload_0
      42: iload         5
      44: iconst_m1
      45: invokevirtual #17                 // Method makeSourceLoc:(II)Lorg/aspectj/lang/reflect/SourceLocation;
      48: invokespecial #25                 // Method org/aspectj/runtime/reflect/JoinPointImpl$EnclosingStaticPartImpl."<init>":(ILjava/lang/String;Lorg/aspectj/lang/Signature;Lorg/aspectj/lang/reflect/SourceLocation;)V
      51: areturn

  public org.aspectj.lang.JoinPoint$StaticPart makeFieldSJP(java.lang.String, int, java.lang.String, java.lang.Class, java.lang.Class, int);
    Code:
       0: new           #30                 // class org/aspectj/runtime/reflect/FieldSignatureImpl
       3: dup
       4: iload_2
       5: aload_3
       6: aload         4
       8: aload         5
      10: invokespecial #31                 // Method org/aspectj/runtime/reflect/FieldSignatureImpl."<init>":(ILjava/lang/String;Ljava/lang/Class;Ljava/lang/Class;)V
      13: astore        7
      15: new           #16                 // class org/aspectj/runtime/reflect/JoinPointImpl$StaticPartImpl
      18: dup
      19: aload_0
      20: dup
      21: getfield      #12                 // Field count:I
      24: dup_x1
      25: iconst_1
      26: iadd
      27: putfield      #12                 // Field count:I
      30: aload_1
      31: aload         7
      33: aload_0
      34: iload         6
      36: iconst_m1
      37: invokevirtual #17                 // Method makeSourceLoc:(II)Lorg/aspectj/lang/reflect/SourceLocation;
      40: invokespecial #18                 // Method org/aspectj/runtime/reflect/JoinPointImpl$StaticPartImpl."<init>":(ILjava/lang/String;Lorg/aspectj/lang/Signature;Lorg/aspectj/lang/reflect/SourceLocation;)V
      43: areturn

  public org.aspectj.lang.JoinPoint$EnclosingStaticPart makeFieldESJP(java.lang.String, int, java.lang.String, java.lang.Class, java.lang.Class, int);
    Code:
       0: new           #30                 // class org/aspectj/runtime/reflect/FieldSignatureImpl
       3: dup
       4: iload_2
       5: aload_3
       6: aload         4
       8: aload         5
      10: invokespecial #31                 // Method org/aspectj/runtime/reflect/FieldSignatureImpl."<init>":(ILjava/lang/String;Ljava/lang/Class;Ljava/lang/Class;)V
      13: astore        7
      15: new           #24                 // class org/aspectj/runtime/reflect/JoinPointImpl$EnclosingStaticPartImpl
      18: dup
      19: aload_0
      20: dup
      21: getfield      #12                 // Field count:I
      24: dup_x1
      25: iconst_1
      26: iadd
      27: putfield      #12                 // Field count:I
      30: aload_1
      31: aload         7
      33: aload_0
      34: iload         6
      36: iconst_m1
      37: invokevirtual #17                 // Method makeSourceLoc:(II)Lorg/aspectj/lang/reflect/SourceLocation;
      40: invokespecial #25                 // Method org/aspectj/runtime/reflect/JoinPointImpl$EnclosingStaticPartImpl."<init>":(ILjava/lang/String;Lorg/aspectj/lang/Signature;Lorg/aspectj/lang/reflect/SourceLocation;)V
      43: areturn

  public org.aspectj.lang.JoinPoint$StaticPart makeInitializerSJP(java.lang.String, int, java.lang.Class, int);
    Code:
       0: new           #32                 // class org/aspectj/runtime/reflect/InitializerSignatureImpl
       3: dup
       4: iload_2
       5: aload_3
       6: invokespecial #33                 // Method org/aspectj/runtime/reflect/InitializerSignatureImpl."<init>":(ILjava/lang/Class;)V
       9: astore        5
      11: new           #16                 // class org/aspectj/runtime/reflect/JoinPointImpl$StaticPartImpl
      14: dup
      15: aload_0
      16: dup
      17: getfield      #12                 // Field count:I
      20: dup_x1
      21: iconst_1
      22: iadd
      23: putfield      #12                 // Field count:I
      26: aload_1
      27: aload         5
      29: aload_0
      30: iload         4
      32: iconst_m1
      33: invokevirtual #17                 // Method makeSourceLoc:(II)Lorg/aspectj/lang/reflect/SourceLocation;
      36: invokespecial #18                 // Method org/aspectj/runtime/reflect/JoinPointImpl$StaticPartImpl."<init>":(ILjava/lang/String;Lorg/aspectj/lang/Signature;Lorg/aspectj/lang/reflect/SourceLocation;)V
      39: areturn

  public org.aspectj.lang.JoinPoint$EnclosingStaticPart makeInitializerESJP(java.lang.String, int, java.lang.Class, int);
    Code:
       0: new           #32                 // class org/aspectj/runtime/reflect/InitializerSignatureImpl
       3: dup
       4: iload_2
       5: aload_3
       6: invokespecial #33                 // Method org/aspectj/runtime/reflect/InitializerSignatureImpl."<init>":(ILjava/lang/Class;)V
       9: astore        5
      11: new           #24                 // class org/aspectj/runtime/reflect/JoinPointImpl$EnclosingStaticPartImpl
      14: dup
      15: aload_0
      16: dup
      17: getfield      #12                 // Field count:I
      20: dup_x1
      21: iconst_1
      22: iadd
      23: putfield      #12                 // Field count:I
      26: aload_1
      27: aload         5
      29: aload_0
      30: iload         4
      32: iconst_m1
      33: invokevirtual #17                 // Method makeSourceLoc:(II)Lorg/aspectj/lang/reflect/SourceLocation;
      36: invokespecial #25                 // Method org/aspectj/runtime/reflect/JoinPointImpl$EnclosingStaticPartImpl."<init>":(ILjava/lang/String;Lorg/aspectj/lang/Signature;Lorg/aspectj/lang/reflect/SourceLocation;)V
      39: areturn

  public org.aspectj.lang.JoinPoint$StaticPart makeLockSJP(java.lang.String, java.lang.Class, int);
    Code:
       0: new           #34                 // class org/aspectj/runtime/reflect/LockSignatureImpl
       3: dup
       4: aload_2
       5: invokespecial #35                 // Method org/aspectj/runtime/reflect/LockSignatureImpl."<init>":(Ljava/lang/Class;)V
       8: astore        4
      10: new           #16                 // class org/aspectj/runtime/reflect/JoinPointImpl$StaticPartImpl
      13: dup
      14: aload_0
      15: dup
      16: getfield      #12                 // Field count:I
      19: dup_x1
      20: iconst_1
      21: iadd
      22: putfield      #12                 // Field count:I
      25: aload_1
      26: aload         4
      28: aload_0
      29: iload_3
      30: iconst_m1
      31: invokevirtual #17                 // Method makeSourceLoc:(II)Lorg/aspectj/lang/reflect/SourceLocation;
      34: invokespecial #18                 // Method org/aspectj/runtime/reflect/JoinPointImpl$StaticPartImpl."<init>":(ILjava/lang/String;Lorg/aspectj/lang/Signature;Lorg/aspectj/lang/reflect/SourceLocation;)V
      37: areturn

  public org.aspectj.lang.JoinPoint$EnclosingStaticPart makeLockESJP(java.lang.String, java.lang.Class, int);
    Code:
       0: new           #34                 // class org/aspectj/runtime/reflect/LockSignatureImpl
       3: dup
       4: aload_2
       5: invokespecial #35                 // Method org/aspectj/runtime/reflect/LockSignatureImpl."<init>":(Ljava/lang/Class;)V
       8: astore        4
      10: new           #24                 // class org/aspectj/runtime/reflect/JoinPointImpl$EnclosingStaticPartImpl
      13: dup
      14: aload_0
      15: dup
      16: getfield      #12                 // Field count:I
      19: dup_x1
      20: iconst_1
      21: iadd
      22: putfield      #12                 // Field count:I
      25: aload_1
      26: aload         4
      28: aload_0
      29: iload_3
      30: iconst_m1
      31: invokevirtual #17                 // Method makeSourceLoc:(II)Lorg/aspectj/lang/reflect/SourceLocation;
      34: invokespecial #25                 // Method org/aspectj/runtime/reflect/JoinPointImpl$EnclosingStaticPartImpl."<init>":(ILjava/lang/String;Lorg/aspectj/lang/Signature;Lorg/aspectj/lang/reflect/SourceLocation;)V
      37: areturn

  public org.aspectj.lang.JoinPoint$StaticPart makeUnlockSJP(java.lang.String, java.lang.Class, int);
    Code:
       0: new           #36                 // class org/aspectj/runtime/reflect/UnlockSignatureImpl
       3: dup
       4: aload_2
       5: invokespecial #37                 // Method org/aspectj/runtime/reflect/UnlockSignatureImpl."<init>":(Ljava/lang/Class;)V
       8: astore        4
      10: new           #16                 // class org/aspectj/runtime/reflect/JoinPointImpl$StaticPartImpl
      13: dup
      14: aload_0
      15: dup
      16: getfield      #12                 // Field count:I
      19: dup_x1
      20: iconst_1
      21: iadd
      22: putfield      #12                 // Field count:I
      25: aload_1
      26: aload         4
      28: aload_0
      29: iload_3
      30: iconst_m1
      31: invokevirtual #17                 // Method makeSourceLoc:(II)Lorg/aspectj/lang/reflect/SourceLocation;
      34: invokespecial #18                 // Method org/aspectj/runtime/reflect/JoinPointImpl$StaticPartImpl."<init>":(ILjava/lang/String;Lorg/aspectj/lang/Signature;Lorg/aspectj/lang/reflect/SourceLocation;)V
      37: areturn

  public org.aspectj.lang.JoinPoint$EnclosingStaticPart makeUnlockESJP(java.lang.String, java.lang.Class, int);
    Code:
       0: new           #36                 // class org/aspectj/runtime/reflect/UnlockSignatureImpl
       3: dup
       4: aload_2
       5: invokespecial #37                 // Method org/aspectj/runtime/reflect/UnlockSignatureImpl."<init>":(Ljava/lang/Class;)V
       8: astore        4
      10: new           #24                 // class org/aspectj/runtime/reflect/JoinPointImpl$EnclosingStaticPartImpl
      13: dup
      14: aload_0
      15: dup
      16: getfield      #12                 // Field count:I
      19: dup_x1
      20: iconst_1
      21: iadd
      22: putfield      #12                 // Field count:I
      25: aload_1
      26: aload         4
      28: aload_0
      29: iload_3
      30: iconst_m1
      31: invokevirtual #17                 // Method makeSourceLoc:(II)Lorg/aspectj/lang/reflect/SourceLocation;
      34: invokespecial #25                 // Method org/aspectj/runtime/reflect/JoinPointImpl$EnclosingStaticPartImpl."<init>":(ILjava/lang/String;Lorg/aspectj/lang/Signature;Lorg/aspectj/lang/reflect/SourceLocation;)V
      37: areturn

  public org.aspectj.lang.JoinPoint$StaticPart makeAdviceSJP(java.lang.String, int, java.lang.String, java.lang.Class, java.lang.Class[], java.lang.String[], java.lang.Class[], java.lang.Class, int);
    Code:
       0: new           #38                 // class org/aspectj/runtime/reflect/AdviceSignatureImpl
       3: dup
       4: iload_2
       5: aload_3
       6: aload         4
       8: aload         5
      10: ifnonnull     19
      13: getstatic     #20                 // Field NO_TYPES:[Ljava/lang/Class;
      16: goto          21
      19: aload         5
      21: aload         6
      23: ifnonnull     32
      26: getstatic     #21                 // Field NO_STRINGS:[Ljava/lang/String;
      29: goto          34
      32: aload         6
      34: aload         7
      36: ifnonnull     45
      39: getstatic     #20                 // Field NO_TYPES:[Ljava/lang/Class;
      42: goto          47
      45: aload         7
      47: aload         8
      49: ifnonnull     58
      52: getstatic     #22                 // Field java/lang/Void.TYPE:Ljava/lang/Class;
      55: goto          60
      58: aload         8
      60: invokespecial #39                 // Method org/aspectj/runtime/reflect/AdviceSignatureImpl."<init>":(ILjava/lang/String;Ljava/lang/Class;[Ljava/lang/Class;[Ljava/lang/String;[Ljava/lang/Class;Ljava/lang/Class;)V
      63: astore        10
      65: new           #16                 // class org/aspectj/runtime/reflect/JoinPointImpl$StaticPartImpl
      68: dup
      69: aload_0
      70: dup
      71: getfield      #12                 // Field count:I
      74: dup_x1
      75: iconst_1
      76: iadd
      77: putfield      #12                 // Field count:I
      80: aload_1
      81: aload         10
      83: aload_0
      84: iload         9
      86: iconst_m1
      87: invokevirtual #17                 // Method makeSourceLoc:(II)Lorg/aspectj/lang/reflect/SourceLocation;
      90: invokespecial #18                 // Method org/aspectj/runtime/reflect/JoinPointImpl$StaticPartImpl."<init>":(ILjava/lang/String;Lorg/aspectj/lang/Signature;Lorg/aspectj/lang/reflect/SourceLocation;)V
      93: areturn

  public org.aspectj.lang.JoinPoint$EnclosingStaticPart makeAdviceESJP(java.lang.String, int, java.lang.String, java.lang.Class, java.lang.Class[], java.lang.String[], java.lang.Class[], java.lang.Class, int);
    Code:
       0: new           #38                 // class org/aspectj/runtime/reflect/AdviceSignatureImpl
       3: dup
       4: iload_2
       5: aload_3
       6: aload         4
       8: aload         5
      10: ifnonnull     19
      13: getstatic     #20                 // Field NO_TYPES:[Ljava/lang/Class;
      16: goto          21
      19: aload         5
      21: aload         6
      23: ifnonnull     32
      26: getstatic     #21                 // Field NO_STRINGS:[Ljava/lang/String;
      29: goto          34
      32: aload         6
      34: aload         7
      36: ifnonnull     45
      39: getstatic     #20                 // Field NO_TYPES:[Ljava/lang/Class;
      42: goto          47
      45: aload         7
      47: aload         8
      49: ifnonnull     58
      52: getstatic     #22                 // Field java/lang/Void.TYPE:Ljava/lang/Class;
      55: goto          60
      58: aload         8
      60: invokespecial #39                 // Method org/aspectj/runtime/reflect/AdviceSignatureImpl."<init>":(ILjava/lang/String;Ljava/lang/Class;[Ljava/lang/Class;[Ljava/lang/String;[Ljava/lang/Class;Ljava/lang/Class;)V
      63: astore        10
      65: new           #24                 // class org/aspectj/runtime/reflect/JoinPointImpl$EnclosingStaticPartImpl
      68: dup
      69: aload_0
      70: dup
      71: getfield      #12                 // Field count:I
      74: dup_x1
      75: iconst_1
      76: iadd
      77: putfield      #12                 // Field count:I
      80: aload_1
      81: aload         10
      83: aload_0
      84: iload         9
      86: iconst_m1
      87: invokevirtual #17                 // Method makeSourceLoc:(II)Lorg/aspectj/lang/reflect/SourceLocation;
      90: invokespecial #25                 // Method org/aspectj/runtime/reflect/JoinPointImpl$EnclosingStaticPartImpl."<init>":(ILjava/lang/String;Lorg/aspectj/lang/Signature;Lorg/aspectj/lang/reflect/SourceLocation;)V
      93: areturn

  public org.aspectj.lang.JoinPoint$StaticPart makeSJP(java.lang.String, org.aspectj.lang.Signature, org.aspectj.lang.reflect.SourceLocation);
    Code:
       0: new           #16                 // class org/aspectj/runtime/reflect/JoinPointImpl$StaticPartImpl
       3: dup
       4: aload_0
       5: dup
       6: getfield      #12                 // Field count:I
       9: dup_x1
      10: iconst_1
      11: iadd
      12: putfield      #12                 // Field count:I
      15: aload_1
      16: aload_2
      17: aload_3
      18: invokespecial #18                 // Method org/aspectj/runtime/reflect/JoinPointImpl$StaticPartImpl."<init>":(ILjava/lang/String;Lorg/aspectj/lang/Signature;Lorg/aspectj/lang/reflect/SourceLocation;)V
      21: areturn

  public org.aspectj.lang.JoinPoint$StaticPart makeSJP(java.lang.String, org.aspectj.lang.Signature, int, int);
    Code:
       0: new           #16                 // class org/aspectj/runtime/reflect/JoinPointImpl$StaticPartImpl
       3: dup
       4: aload_0
       5: dup
       6: getfield      #12                 // Field count:I
       9: dup_x1
      10: iconst_1
      11: iadd
      12: putfield      #12                 // Field count:I
      15: aload_1
      16: aload_2
      17: aload_0
      18: iload_3
      19: iload         4
      21: invokevirtual #17                 // Method makeSourceLoc:(II)Lorg/aspectj/lang/reflect/SourceLocation;
      24: invokespecial #18                 // Method org/aspectj/runtime/reflect/JoinPointImpl$StaticPartImpl."<init>":(ILjava/lang/String;Lorg/aspectj/lang/Signature;Lorg/aspectj/lang/reflect/SourceLocation;)V
      27: areturn

  public org.aspectj.lang.JoinPoint$StaticPart makeSJP(java.lang.String, org.aspectj.lang.Signature, int);
    Code:
       0: new           #16                 // class org/aspectj/runtime/reflect/JoinPointImpl$StaticPartImpl
       3: dup
       4: aload_0
       5: dup
       6: getfield      #12                 // Field count:I
       9: dup_x1
      10: iconst_1
      11: iadd
      12: putfield      #12                 // Field count:I
      15: aload_1
      16: aload_2
      17: aload_0
      18: iload_3
      19: iconst_m1
      20: invokevirtual #17                 // Method makeSourceLoc:(II)Lorg/aspectj/lang/reflect/SourceLocation;
      23: invokespecial #18                 // Method org/aspectj/runtime/reflect/JoinPointImpl$StaticPartImpl."<init>":(ILjava/lang/String;Lorg/aspectj/lang/Signature;Lorg/aspectj/lang/reflect/SourceLocation;)V
      26: areturn

  public org.aspectj.lang.JoinPoint$EnclosingStaticPart makeESJP(java.lang.String, org.aspectj.lang.Signature, org.aspectj.lang.reflect.SourceLocation);
    Code:
       0: new           #24                 // class org/aspectj/runtime/reflect/JoinPointImpl$EnclosingStaticPartImpl
       3: dup
       4: aload_0
       5: dup
       6: getfield      #12                 // Field count:I
       9: dup_x1
      10: iconst_1
      11: iadd
      12: putfield      #12                 // Field count:I
      15: aload_1
      16: aload_2
      17: aload_3
      18: invokespecial #25                 // Method org/aspectj/runtime/reflect/JoinPointImpl$EnclosingStaticPartImpl."<init>":(ILjava/lang/String;Lorg/aspectj/lang/Signature;Lorg/aspectj/lang/reflect/SourceLocation;)V
      21: areturn

  public org.aspectj.lang.JoinPoint$EnclosingStaticPart makeESJP(java.lang.String, org.aspectj.lang.Signature, int, int);
    Code:
       0: new           #24                 // class org/aspectj/runtime/reflect/JoinPointImpl$EnclosingStaticPartImpl
       3: dup
       4: aload_0
       5: dup
       6: getfield      #12                 // Field count:I
       9: dup_x1
      10: iconst_1
      11: iadd
      12: putfield      #12                 // Field count:I
      15: aload_1
      16: aload_2
      17: aload_0
      18: iload_3
      19: iload         4
      21: invokevirtual #17                 // Method makeSourceLoc:(II)Lorg/aspectj/lang/reflect/SourceLocation;
      24: invokespecial #25                 // Method org/aspectj/runtime/reflect/JoinPointImpl$EnclosingStaticPartImpl."<init>":(ILjava/lang/String;Lorg/aspectj/lang/Signature;Lorg/aspectj/lang/reflect/SourceLocation;)V
      27: areturn

  public org.aspectj.lang.JoinPoint$EnclosingStaticPart makeESJP(java.lang.String, org.aspectj.lang.Signature, int);
    Code:
       0: new           #24                 // class org/aspectj/runtime/reflect/JoinPointImpl$EnclosingStaticPartImpl
       3: dup
       4: aload_0
       5: dup
       6: getfield      #12                 // Field count:I
       9: dup_x1
      10: iconst_1
      11: iadd
      12: putfield      #12                 // Field count:I
      15: aload_1
      16: aload_2
      17: aload_0
      18: iload_3
      19: iconst_m1
      20: invokevirtual #17                 // Method makeSourceLoc:(II)Lorg/aspectj/lang/reflect/SourceLocation;
      23: invokespecial #25                 // Method org/aspectj/runtime/reflect/JoinPointImpl$EnclosingStaticPartImpl."<init>":(ILjava/lang/String;Lorg/aspectj/lang/Signature;Lorg/aspectj/lang/reflect/SourceLocation;)V
      26: areturn

  public static org.aspectj.lang.JoinPoint$StaticPart makeEncSJP(java.lang.reflect.Member);
    Code:
       0: aconst_null
       1: astore_1
       2: aconst_null
       3: astore_2
       4: aload_0
       5: instanceof    #40                 // class java/lang/reflect/Method
       8: ifeq          62
      11: aload_0
      12: checkcast     #40                 // class java/lang/reflect/Method
      15: astore_3
      16: new           #41                 // class org/aspectj/runtime/reflect/MethodSignatureImpl
      19: dup
      20: aload_3
      21: invokevirtual #42                 // Method java/lang/reflect/Method.getModifiers:()I
      24: aload_3
      25: invokevirtual #43                 // Method java/lang/reflect/Method.getName:()Ljava/lang/String;
      28: aload_3
      29: invokevirtual #44                 // Method java/lang/reflect/Method.getDeclaringClass:()Ljava/lang/Class;
      32: aload_3
      33: invokevirtual #45                 // Method java/lang/reflect/Method.getParameterTypes:()[Ljava/lang/Class;
      36: aload_3
      37: invokevirtual #45                 // Method java/lang/reflect/Method.getParameterTypes:()[Ljava/lang/Class;
      40: arraylength
      41: anewarray     #46                 // class java/lang/String
      44: aload_3
      45: invokevirtual #47                 // Method java/lang/reflect/Method.getExceptionTypes:()[Ljava/lang/Class;
      48: aload_3
      49: invokevirtual #48                 // Method java/lang/reflect/Method.getReturnType:()Ljava/lang/Class;
      52: invokespecial #49                 // Method org/aspectj/runtime/reflect/MethodSignatureImpl."<init>":(ILjava/lang/String;Ljava/lang/Class;[Ljava/lang/Class;[Ljava/lang/String;[Ljava/lang/Class;Ljava/lang/Class;)V
      55: astore_1
      56: ldc           #51                 // String method-execution
      58: astore_2
      59: goto          122
      62: aload_0
      63: instanceof    #52                 // class java/lang/reflect/Constructor
      66: ifeq          112
      69: aload_0
      70: checkcast     #52                 // class java/lang/reflect/Constructor
      73: astore_3
      74: new           #26                 // class org/aspectj/runtime/reflect/ConstructorSignatureImpl
      77: dup
      78: aload_3
      79: invokevirtual #53                 // Method java/lang/reflect/Constructor.getModifiers:()I
      82: aload_3
      83: invokevirtual #54                 // Method java/lang/reflect/Constructor.getDeclaringClass:()Ljava/lang/Class;
      86: aload_3
      87: invokevirtual #55                 // Method java/lang/reflect/Constructor.getParameterTypes:()[Ljava/lang/Class;
      90: aload_3
      91: invokevirtual #55                 // Method java/lang/reflect/Constructor.getParameterTypes:()[Ljava/lang/Class;
      94: arraylength
      95: anewarray     #46                 // class java/lang/String
      98: aload_3
      99: invokevirtual #56                 // Method java/lang/reflect/Constructor.getExceptionTypes:()[Ljava/lang/Class;
     102: invokespecial #27                 // Method org/aspectj/runtime/reflect/ConstructorSignatureImpl."<init>":(ILjava/lang/Class;[Ljava/lang/Class;[Ljava/lang/String;[Ljava/lang/Class;)V
     105: astore_1
     106: ldc           #57                 // String constructor-execution
     108: astore_2
     109: goto          122
     112: new           #58                 // class java/lang/IllegalArgumentException
     115: dup
     116: ldc           #59                 // String member must be either a method or constructor
     118: invokespecial #60                 // Method java/lang/IllegalArgumentException."<init>":(Ljava/lang/String;)V
     121: athrow
     122: new           #24                 // class org/aspectj/runtime/reflect/JoinPointImpl$EnclosingStaticPartImpl
     125: dup
     126: iconst_m1
     127: aload_2
     128: aload_1
     129: aconst_null
     130: invokespecial #25                 // Method org/aspectj/runtime/reflect/JoinPointImpl$EnclosingStaticPartImpl."<init>":(ILjava/lang/String;Lorg/aspectj/lang/Signature;Lorg/aspectj/lang/reflect/SourceLocation;)V
     133: areturn

  public static org.aspectj.lang.JoinPoint makeJP(org.aspectj.lang.JoinPoint$StaticPart, java.lang.Object, java.lang.Object);
    Code:
       0: new           #61                 // class org/aspectj/runtime/reflect/JoinPointImpl
       3: dup
       4: aload_0
       5: aload_1
       6: aload_2
       7: getstatic     #62                 // Field NO_ARGS:[Ljava/lang/Object;
      10: invokespecial #63                 // Method org/aspectj/runtime/reflect/JoinPointImpl."<init>":(Lorg/aspectj/lang/JoinPoint$StaticPart;Ljava/lang/Object;Ljava/lang/Object;[Ljava/lang/Object;)V
      13: areturn

  public static org.aspectj.lang.JoinPoint makeJP(org.aspectj.lang.JoinPoint$StaticPart, java.lang.Object, java.lang.Object, java.lang.Object);
    Code:
       0: new           #61                 // class org/aspectj/runtime/reflect/JoinPointImpl
       3: dup
       4: aload_0
       5: aload_1
       6: aload_2
       7: iconst_1
       8: anewarray     #64                 // class java/lang/Object
      11: dup
      12: iconst_0
      13: aload_3
      14: aastore
      15: invokespecial #63                 // Method org/aspectj/runtime/reflect/JoinPointImpl."<init>":(Lorg/aspectj/lang/JoinPoint$StaticPart;Ljava/lang/Object;Ljava/lang/Object;[Ljava/lang/Object;)V
      18: areturn

  public static org.aspectj.lang.JoinPoint makeJP(org.aspectj.lang.JoinPoint$StaticPart, java.lang.Object, java.lang.Object, java.lang.Object, java.lang.Object);
    Code:
       0: new           #61                 // class org/aspectj/runtime/reflect/JoinPointImpl
       3: dup
       4: aload_0
       5: aload_1
       6: aload_2
       7: iconst_2
       8: anewarray     #64                 // class java/lang/Object
      11: dup
      12: iconst_0
      13: aload_3
      14: aastore
      15: dup
      16: iconst_1
      17: aload         4
      19: aastore
      20: invokespecial #63                 // Method org/aspectj/runtime/reflect/JoinPointImpl."<init>":(Lorg/aspectj/lang/JoinPoint$StaticPart;Ljava/lang/Object;Ljava/lang/Object;[Ljava/lang/Object;)V
      23: areturn

  public static org.aspectj.lang.JoinPoint makeJP(org.aspectj.lang.JoinPoint$StaticPart, java.lang.Object, java.lang.Object, java.lang.Object[]);
    Code:
       0: new           #61                 // class org/aspectj/runtime/reflect/JoinPointImpl
       3: dup
       4: aload_0
       5: aload_1
       6: aload_2
       7: aload_3
       8: invokespecial #63                 // Method org/aspectj/runtime/reflect/JoinPointImpl."<init>":(Lorg/aspectj/lang/JoinPoint$StaticPart;Ljava/lang/Object;Ljava/lang/Object;[Ljava/lang/Object;)V
      11: areturn

  public org.aspectj.lang.reflect.MethodSignature makeMethodSig(java.lang.String);
    Code:
       0: new           #41                 // class org/aspectj/runtime/reflect/MethodSignatureImpl
       3: dup
       4: aload_1
       5: invokespecial #65                 // Method org/aspectj/runtime/reflect/MethodSignatureImpl."<init>":(Ljava/lang/String;)V
       8: astore_2
       9: aload_2
      10: aload_0
      11: getfield      #14                 // Field lookupClassLoader:Ljava/lang/ClassLoader;
      14: invokevirtual #66                 // Method org/aspectj/runtime/reflect/MethodSignatureImpl.setLookupClassLoader:(Ljava/lang/ClassLoader;)V
      17: aload_2
      18: areturn

  public org.aspectj.lang.reflect.MethodSignature makeMethodSig(java.lang.String, java.lang.String, java.lang.String, java.lang.String, java.lang.String, java.lang.String, java.lang.String);
    Code:
       0: aload_3
       1: aload_0
       2: getfield      #14                 // Field lookupClassLoader:Ljava/lang/ClassLoader;
       5: invokestatic  #67                 // Method makeClass:(Ljava/lang/String;Ljava/lang/ClassLoader;)Ljava/lang/Class;
       8: astore        8
      10: aload_0
      11: aload_1
      12: aload_2
      13: aload         8
      15: aload         4
      17: aload         5
      19: aload         6
      21: aload         7
      23: invokevirtual #68                 // Method makeMethodSig:(Ljava/lang/String;Ljava/lang/String;Ljava/lang/Class;Ljava/lang/String;Ljava/lang/String;Ljava/lang/String;Ljava/lang/String;)Lorg/aspectj/lang/reflect/MethodSignature;
      26: areturn

  public org.aspectj.lang.reflect.MethodSignature makeMethodSig(java.lang.String, java.lang.String, java.lang.Class, java.lang.String, java.lang.String, java.lang.String, java.lang.String);
    Code:
       0: aload_1
       1: bipush        16
       3: invokestatic  #69                 // Method java/lang/Integer.parseInt:(Ljava/lang/String;I)I
       6: istore        8
       8: new           #70                 // class java/util/StringTokenizer
      11: dup
      12: aload         4
      14: ldc           #71                 // String :
      16: invokespecial #72                 // Method java/util/StringTokenizer."<init>":(Ljava/lang/String;Ljava/lang/String;)V
      19: astore        9
      21: aload         9
      23: invokevirtual #73                 // Method java/util/StringTokenizer.countTokens:()I
      26: istore        10
      28: iload         10
      30: anewarray     #5                  // class java/lang/Class
      33: astore        11
      35: iconst_0
      36: istore        12
      38: iload         12
      40: iload         10
      42: if_icmpge     68
      45: aload         11
      47: iload         12
      49: aload         9
      51: invokevirtual #74                 // Method java/util/StringTokenizer.nextToken:()Ljava/lang/String;
      54: aload_0
      55: getfield      #14                 // Field lookupClassLoader:Ljava/lang/ClassLoader;
      58: invokestatic  #67                 // Method makeClass:(Ljava/lang/String;Ljava/lang/ClassLoader;)Ljava/lang/Class;
      61: aastore
      62: iinc          12, 1
      65: goto          38
      68: new           #70                 // class java/util/StringTokenizer
      71: dup
      72: aload         5
      74: ldc           #71                 // String :
      76: invokespecial #72                 // Method java/util/StringTokenizer."<init>":(Ljava/lang/String;Ljava/lang/String;)V
      79: astore        9
      81: aload         9
      83: invokevirtual #73                 // Method java/util/StringTokenizer.countTokens:()I
      86: istore        10
      88: iload         10
      90: anewarray     #46                 // class java/lang/String
      93: astore        12
      95: iconst_0
      96: istore        13
      98: iload         13
     100: iload         10
     102: if_icmpge     121
     105: aload         12
     107: iload         13
     109: aload         9
     111: invokevirtual #74                 // Method java/util/StringTokenizer.nextToken:()Ljava/lang/String;
     114: aastore
     115: iinc          13, 1
     118: goto          98
     121: new           #70                 // class java/util/StringTokenizer
     124: dup
     125: aload         6
     127: ldc           #71                 // String :
     129: invokespecial #72                 // Method java/util/StringTokenizer."<init>":(Ljava/lang/String;Ljava/lang/String;)V
     132: astore        9
     134: aload         9
     136: invokevirtual #73                 // Method java/util/StringTokenizer.countTokens:()I
     139: istore        10
     141: iload         10
     143: anewarray     #5                  // class java/lang/Class
     146: astore        13
     148: iconst_0
     149: istore        14
     151: iload         14
     153: iload         10
     155: if_icmpge     181
     158: aload         13
     160: iload         14
     162: aload         9
     164: invokevirtual #74                 // Method java/util/StringTokenizer.nextToken:()Ljava/lang/String;
     167: aload_0
     168: getfield      #14                 // Field lookupClassLoader:Ljava/lang/ClassLoader;
     171: invokestatic  #67                 // Method makeClass:(Ljava/lang/String;Ljava/lang/ClassLoader;)Ljava/lang/Class;
     174: aastore
     175: iinc          14, 1
     178: goto          151
     181: aload         7
     183: aload_0
     184: getfield      #14                 // Field lookupClassLoader:Ljava/lang/ClassLoader;
     187: invokestatic  #67                 // Method makeClass:(Ljava/lang/String;Ljava/lang/ClassLoader;)Ljava/lang/Class;
     190: astore        14
     192: new           #41                 // class org/aspectj/runtime/reflect/MethodSignatureImpl
     195: dup
     196: iload         8
     198: aload_2
     199: aload_3
     200: aload         11
     202: aload         12
     204: aload         13
     206: aload         14
     208: invokespecial #49                 // Method org/aspectj/runtime/reflect/MethodSignatureImpl."<init>":(ILjava/lang/String;Ljava/lang/Class;[Ljava/lang/Class;[Ljava/lang/String;[Ljava/lang/Class;Ljava/lang/Class;)V
     211: astore        15
     213: aload         15
     215: areturn

  public org.aspectj.lang.reflect.MethodSignature makeMethodSig(int, java.lang.String, java.lang.Class, java.lang.Class[], java.lang.String[], java.lang.Class[], java.lang.Class);
    Code:
       0: new           #41                 // class org/aspectj/runtime/reflect/MethodSignatureImpl
       3: dup
       4: iload_1
       5: aload_2
       6: aload_3
       7: aload         4
       9: ifnonnull     18
      12: getstatic     #20                 // Field NO_TYPES:[Ljava/lang/Class;
      15: goto          20
      18: aload         4
      20: aload         5
      22: aload         6
      24: ifnonnull     33
      27: getstatic     #20                 // Field NO_TYPES:[Ljava/lang/Class;
      30: goto          35
      33: aload         6
      35: aload         7
      37: invokespecial #49                 // Method org/aspectj/runtime/reflect/MethodSignatureImpl."<init>":(ILjava/lang/String;Ljava/lang/Class;[Ljava/lang/Class;[Ljava/lang/String;[Ljava/lang/Class;Ljava/lang/Class;)V
      40: astore        8
      42: aload         8
      44: aload_0
      45: getfield      #14                 // Field lookupClassLoader:Ljava/lang/ClassLoader;
      48: invokevirtual #66                 // Method org/aspectj/runtime/reflect/MethodSignatureImpl.setLookupClassLoader:(Ljava/lang/ClassLoader;)V
      51: aload         8
      53: areturn

  public org.aspectj.lang.reflect.ConstructorSignature makeConstructorSig(java.lang.String);
    Code:
       0: new           #26                 // class org/aspectj/runtime/reflect/ConstructorSignatureImpl
       3: dup
       4: aload_1
       5: invokespecial #75                 // Method org/aspectj/runtime/reflect/ConstructorSignatureImpl."<init>":(Ljava/lang/String;)V
       8: astore_2
       9: aload_2
      10: aload_0
      11: getfield      #14                 // Field lookupClassLoader:Ljava/lang/ClassLoader;
      14: invokevirtual #76                 // Method org/aspectj/runtime/reflect/ConstructorSignatureImpl.setLookupClassLoader:(Ljava/lang/ClassLoader;)V
      17: aload_2
      18: areturn

  public org.aspectj.lang.reflect.ConstructorSignature makeConstructorSig(java.lang.String, java.lang.String, java.lang.String, java.lang.String, java.lang.String);
    Code:
       0: aload_1
       1: bipush        16
       3: invokestatic  #69                 // Method java/lang/Integer.parseInt:(Ljava/lang/String;I)I
       6: istore        6
       8: aload_2
       9: aload_0
      10: getfield      #14                 // Field lookupClassLoader:Ljava/lang/ClassLoader;
      13: invokestatic  #67                 // Method makeClass:(Ljava/lang/String;Ljava/lang/ClassLoader;)Ljava/lang/Class;
      16: astore        7
      18: new           #70                 // class java/util/StringTokenizer
      21: dup
      22: aload_3
      23: ldc           #71                 // String :
      25: invokespecial #72                 // Method java/util/StringTokenizer."<init>":(Ljava/lang/String;Ljava/lang/String;)V
      28: astore        8
      30: aload         8
      32: invokevirtual #73                 // Method java/util/StringTokenizer.countTokens:()I
      35: istore        9
      37: iload         9
      39: anewarray     #5                  // class java/lang/Class
      42: astore        10
      44: iconst_0
      45: istore        11
      47: iload         11
      49: iload         9
      51: if_icmpge     77
      54: aload         10
      56: iload         11
      58: aload         8
      60: invokevirtual #74                 // Method java/util/StringTokenizer.nextToken:()Ljava/lang/String;
      63: aload_0
      64: getfield      #14                 // Field lookupClassLoader:Ljava/lang/ClassLoader;
      67: invokestatic  #67                 // Method makeClass:(Ljava/lang/String;Ljava/lang/ClassLoader;)Ljava/lang/Class;
      70: aastore
      71: iinc          11, 1
      74: goto          47
      77: new           #70                 // class java/util/StringTokenizer
      80: dup
      81: aload         4
      83: ldc           #71                 // String :
      85: invokespecial #72                 // Method java/util/StringTokenizer."<init>":(Ljava/lang/String;Ljava/lang/String;)V
      88: astore        8
      90: aload         8
      92: invokevirtual #73                 // Method java/util/StringTokenizer.countTokens:()I
      95: istore        9
      97: iload         9
      99: anewarray     #46                 // class java/lang/String
     102: astore        11
     104: iconst_0
     105: istore        12
     107: iload         12
     109: iload         9
     111: if_icmpge     130
     114: aload         11
     116: iload         12
     118: aload         8
     120: invokevirtual #74                 // Method java/util/StringTokenizer.nextToken:()Ljava/lang/String;
     123: aastore
     124: iinc          12, 1
     127: goto          107
     130: new           #70                 // class java/util/StringTokenizer
     133: dup
     134: aload         5
     136: ldc           #71                 // String :
     138: invokespecial #72                 // Method java/util/StringTokenizer."<init>":(Ljava/lang/String;Ljava/lang/String;)V
     141: astore        8
     143: aload         8
     145: invokevirtual #73                 // Method java/util/StringTokenizer.countTokens:()I
     148: istore        9
     150: iload         9
     152: anewarray     #5                  // class java/lang/Class
     155: astore        12
     157: iconst_0
     158: istore        13
     160: iload         13
     162: iload         9
     164: if_icmpge     190
     167: aload         12
     169: iload         13
     171: aload         8
     173: invokevirtual #74                 // Method java/util/StringTokenizer.nextToken:()Ljava/lang/String;
     176: aload_0
     177: getfield      #14                 // Field lookupClassLoader:Ljava/lang/ClassLoader;
     180: invokestatic  #67                 // Method makeClass:(Ljava/lang/String;Ljava/lang/ClassLoader;)Ljava/lang/Class;
     183: aastore
     184: iinc          13, 1
     187: goto          160
     190: new           #26                 // class org/aspectj/runtime/reflect/ConstructorSignatureImpl
     193: dup
     194: iload         6
     196: aload         7
     198: aload         10
     200: aload         11
     202: aload         12
     204: invokespecial #27                 // Method org/aspectj/runtime/reflect/ConstructorSignatureImpl."<init>":(ILjava/lang/Class;[Ljava/lang/Class;[Ljava/lang/String;[Ljava/lang/Class;)V
     207: astore        13
     209: aload         13
     211: aload_0
     212: getfield      #14                 // Field lookupClassLoader:Ljava/lang/ClassLoader;
     215: invokevirtual #76                 // Method org/aspectj/runtime/reflect/ConstructorSignatureImpl.setLookupClassLoader:(Ljava/lang/ClassLoader;)V
     218: aload         13
     220: areturn

  public org.aspectj.lang.reflect.ConstructorSignature makeConstructorSig(int, java.lang.Class, java.lang.Class[], java.lang.String[], java.lang.Class[]);
    Code:
       0: new           #26                 // class org/aspectj/runtime/reflect/ConstructorSignatureImpl
       3: dup
       4: iload_1
       5: aload_2
       6: aload_3
       7: aload         4
       9: aload         5
      11: invokespecial #27                 // Method org/aspectj/runtime/reflect/ConstructorSignatureImpl."<init>":(ILjava/lang/Class;[Ljava/lang/Class;[Ljava/lang/String;[Ljava/lang/Class;)V
      14: astore        6
      16: aload         6
      18: aload_0
      19: getfield      #14                 // Field lookupClassLoader:Ljava/lang/ClassLoader;
      22: invokevirtual #76                 // Method org/aspectj/runtime/reflect/ConstructorSignatureImpl.setLookupClassLoader:(Ljava/lang/ClassLoader;)V
      25: aload         6
      27: areturn

  public org.aspectj.lang.reflect.FieldSignature makeFieldSig(java.lang.String);
    Code:
       0: new           #30                 // class org/aspectj/runtime/reflect/FieldSignatureImpl
       3: dup
       4: aload_1
       5: invokespecial #77                 // Method org/aspectj/runtime/reflect/FieldSignatureImpl."<init>":(Ljava/lang/String;)V
       8: astore_2
       9: aload_2
      10: aload_0
      11: getfield      #14                 // Field lookupClassLoader:Ljava/lang/ClassLoader;
      14: invokevirtual #78                 // Method org/aspectj/runtime/reflect/FieldSignatureImpl.setLookupClassLoader:(Ljava/lang/ClassLoader;)V
      17: aload_2
      18: areturn

  public org.aspectj.lang.reflect.FieldSignature makeFieldSig(java.lang.String, java.lang.String, java.lang.String, java.lang.String);
    Code:
       0: aload_1
       1: bipush        16
       3: invokestatic  #69                 // Method java/lang/Integer.parseInt:(Ljava/lang/String;I)I
       6: istore        5
       8: aload_3
       9: aload_0
      10: getfield      #14                 // Field lookupClassLoader:Ljava/lang/ClassLoader;
      13: invokestatic  #67                 // Method makeClass:(Ljava/lang/String;Ljava/lang/ClassLoader;)Ljava/lang/Class;
      16: astore        6
      18: aload         4
      20: aload_0
      21: getfield      #14                 // Field lookupClassLoader:Ljava/lang/ClassLoader;
      24: invokestatic  #67                 // Method makeClass:(Ljava/lang/String;Ljava/lang/ClassLoader;)Ljava/lang/Class;
      27: astore        7
      29: new           #30                 // class org/aspectj/runtime/reflect/FieldSignatureImpl
      32: dup
      33: iload         5
      35: aload_2
      36: aload         6
      38: aload         7
      40: invokespecial #31                 // Method org/aspectj/runtime/reflect/FieldSignatureImpl."<init>":(ILjava/lang/String;Ljava/lang/Class;Ljava/lang/Class;)V
      43: astore        8
      45: aload         8
      47: aload_0
      48: getfield      #14                 // Field lookupClassLoader:Ljava/lang/ClassLoader;
      51: invokevirtual #78                 // Method org/aspectj/runtime/reflect/FieldSignatureImpl.setLookupClassLoader:(Ljava/lang/ClassLoader;)V
      54: aload         8
      56: areturn

  public org.aspectj.lang.reflect.FieldSignature makeFieldSig(int, java.lang.String, java.lang.Class, java.lang.Class);
    Code:
       0: new           #30                 // class org/aspectj/runtime/reflect/FieldSignatureImpl
       3: dup
       4: iload_1
       5: aload_2
       6: aload_3
       7: aload         4
       9: invokespecial #31                 // Method org/aspectj/runtime/reflect/FieldSignatureImpl."<init>":(ILjava/lang/String;Ljava/lang/Class;Ljava/lang/Class;)V
      12: astore        5
      14: aload         5
      16: aload_0
      17: getfield      #14                 // Field lookupClassLoader:Ljava/lang/ClassLoader;
      20: invokevirtual #78                 // Method org/aspectj/runtime/reflect/FieldSignatureImpl.setLookupClassLoader:(Ljava/lang/ClassLoader;)V
      23: aload         5
      25: areturn

  public org.aspectj.lang.reflect.AdviceSignature makeAdviceSig(java.lang.String);
    Code:
       0: new           #38                 // class org/aspectj/runtime/reflect/AdviceSignatureImpl
       3: dup
       4: aload_1
       5: invokespecial #79                 // Method org/aspectj/runtime/reflect/AdviceSignatureImpl."<init>":(Ljava/lang/String;)V
       8: astore_2
       9: aload_2
      10: aload_0
      11: getfield      #14                 // Field lookupClassLoader:Ljava/lang/ClassLoader;
      14: invokevirtual #80                 // Method org/aspectj/runtime/reflect/AdviceSignatureImpl.setLookupClassLoader:(Ljava/lang/ClassLoader;)V
      17: aload_2
      18: areturn

  public org.aspectj.lang.reflect.AdviceSignature makeAdviceSig(java.lang.String, java.lang.String, java.lang.String, java.lang.String, java.lang.String, java.lang.String, java.lang.String);
    Code:
       0: aload_1
       1: bipush        16
       3: invokestatic  #69                 // Method java/lang/Integer.parseInt:(Ljava/lang/String;I)I
       6: istore        8
       8: aload_3
       9: aload_0
      10: getfield      #14                 // Field lookupClassLoader:Ljava/lang/ClassLoader;
      13: invokestatic  #67                 // Method makeClass:(Ljava/lang/String;Ljava/lang/ClassLoader;)Ljava/lang/Class;
      16: astore        9
      18: new           #70                 // class java/util/StringTokenizer
      21: dup
      22: aload         4
      24: ldc           #71                 // String :
      26: invokespecial #72                 // Method java/util/StringTokenizer."<init>":(Ljava/lang/String;Ljava/lang/String;)V
      29: astore        10
      31: aload         10
      33: invokevirtual #73                 // Method java/util/StringTokenizer.countTokens:()I
      36: istore        11
      38: iload         11
      40: anewarray     #5                  // class java/lang/Class
      43: astore        12
      45: iconst_0
      46: istore        13
      48: iload         13
      50: iload         11
      52: if_icmpge     78
      55: aload         12
      57: iload         13
      59: aload         10
      61: invokevirtual #74                 // Method java/util/StringTokenizer.nextToken:()Ljava/lang/String;
      64: aload_0
      65: getfield      #14                 // Field lookupClassLoader:Ljava/lang/ClassLoader;
      68: invokestatic  #67                 // Method makeClass:(Ljava/lang/String;Ljava/lang/ClassLoader;)Ljava/lang/Class;
      71: aastore
      72: iinc          13, 1
      75: goto          48
      78: new           #70                 // class java/util/StringTokenizer
      81: dup
      82: aload         5
      84: ldc           #71                 // String :
      86: invokespecial #72                 // Method java/util/StringTokenizer."<init>":(Ljava/lang/String;Ljava/lang/String;)V
      89: astore        10
      91: aload         10
      93: invokevirtual #73                 // Method java/util/StringTokenizer.countTokens:()I
      96: istore        11
      98: iload         11
     100: anewarray     #46                 // class java/lang/String
     103: astore        13
     105: iconst_0
     106: istore        14
     108: iload         14
     110: iload         11
     112: if_icmpge     131
     115: aload         13
     117: iload         14
     119: aload         10
     121: invokevirtual #74                 // Method java/util/StringTokenizer.nextToken:()Ljava/lang/String;
     124: aastore
     125: iinc          14, 1
     128: goto          108
     131: new           #70                 // class java/util/StringTokenizer
     134: dup
     135: aload         6
     137: ldc           #71                 // String :
     139: invokespecial #72                 // Method java/util/StringTokenizer."<init>":(Ljava/lang/String;Ljava/lang/String;)V
     142: astore        10
     144: aload         10
     146: invokevirtual #73                 // Method java/util/StringTokenizer.countTokens:()I
     149: istore        11
     151: iload         11
     153: anewarray     #5                  // class java/lang/Class
     156: astore        14
     158: iconst_0
     159: istore        15
     161: iload         15
     163: iload         11
     165: if_icmpge     191
     168: aload         14
     170: iload         15
     172: aload         10
     174: invokevirtual #74                 // Method java/util/StringTokenizer.nextToken:()Ljava/lang/String;
     177: aload_0
     178: getfield      #14                 // Field lookupClassLoader:Ljava/lang/ClassLoader;
     181: invokestatic  #67                 // Method makeClass:(Ljava/lang/String;Ljava/lang/ClassLoader;)Ljava/lang/Class;
     184: aastore
     185: iinc          15, 1
     188: goto          161
     191: aload         7
     193: aload_0
     194: getfield      #14                 // Field lookupClassLoader:Ljava/lang/ClassLoader;
     197: invokestatic  #67                 // Method makeClass:(Ljava/lang/String;Ljava/lang/ClassLoader;)Ljava/lang/Class;
     200: astore        15
     202: new           #38                 // class org/aspectj/runtime/reflect/AdviceSignatureImpl
     205: dup
     206: iload         8
     208: aload_2
     209: aload         9
     211: aload         12
     213: aload         13
     215: aload         14
     217: aload         15
     219: invokespecial #39                 // Method org/aspectj/runtime/reflect/AdviceSignatureImpl."<init>":(ILjava/lang/String;Ljava/lang/Class;[Ljava/lang/Class;[Ljava/lang/String;[Ljava/lang/Class;Ljava/lang/Class;)V
     222: astore        16
     224: aload         16
     226: aload_0
     227: getfield      #14                 // Field lookupClassLoader:Ljava/lang/ClassLoader;
     230: invokevirtual #80                 // Method org/aspectj/runtime/reflect/AdviceSignatureImpl.setLookupClassLoader:(Ljava/lang/ClassLoader;)V
     233: aload         16
     235: areturn

  public org.aspectj.lang.reflect.AdviceSignature makeAdviceSig(int, java.lang.String, java.lang.Class, java.lang.Class[], java.lang.String[], java.lang.Class[], java.lang.Class);
    Code:
       0: new           #38                 // class org/aspectj/runtime/reflect/AdviceSignatureImpl
       3: dup
       4: iload_1
       5: aload_2
       6: aload_3
       7: aload         4
       9: aload         5
      11: aload         6
      13: aload         7
      15: invokespecial #39                 // Method org/aspectj/runtime/reflect/AdviceSignatureImpl."<init>":(ILjava/lang/String;Ljava/lang/Class;[Ljava/lang/Class;[Ljava/lang/String;[Ljava/lang/Class;Ljava/lang/Class;)V
      18: astore        8
      20: aload         8
      22: aload_0
      23: getfield      #14                 // Field lookupClassLoader:Ljava/lang/ClassLoader;
      26: invokevirtual #80                 // Method org/aspectj/runtime/reflect/AdviceSignatureImpl.setLookupClassLoader:(Ljava/lang/ClassLoader;)V
      29: aload         8
      31: areturn

  public org.aspectj.lang.reflect.InitializerSignature makeInitializerSig(java.lang.String);
    Code:
       0: new           #32                 // class org/aspectj/runtime/reflect/InitializerSignatureImpl
       3: dup
       4: aload_1
       5: invokespecial #81                 // Method org/aspectj/runtime/reflect/InitializerSignatureImpl."<init>":(Ljava/lang/String;)V
       8: astore_2
       9: aload_2
      10: aload_0
      11: getfield      #14                 // Field lookupClassLoader:Ljava/lang/ClassLoader;
      14: invokevirtual #82                 // Method org/aspectj/runtime/reflect/InitializerSignatureImpl.setLookupClassLoader:(Ljava/lang/ClassLoader;)V
      17: aload_2
      18: areturn

  public org.aspectj.lang.reflect.InitializerSignature makeInitializerSig(java.lang.String, java.lang.String);
    Code:
       0: aload_1
       1: bipush        16
       3: invokestatic  #69                 // Method java/lang/Integer.parseInt:(Ljava/lang/String;I)I
       6: istore_3
       7: aload_2
       8: aload_0
       9: getfield      #14                 // Field lookupClassLoader:Ljava/lang/ClassLoader;
      12: invokestatic  #67                 // Method makeClass:(Ljava/lang/String;Ljava/lang/ClassLoader;)Ljava/lang/Class;
      15: astore        4
      17: new           #32                 // class org/aspectj/runtime/reflect/InitializerSignatureImpl
      20: dup
      21: iload_3
      22: aload         4
      24: invokespecial #33                 // Method org/aspectj/runtime/reflect/InitializerSignatureImpl."<init>":(ILjava/lang/Class;)V
      27: astore        5
      29: aload         5
      31: aload_0
      32: getfield      #14                 // Field lookupClassLoader:Ljava/lang/ClassLoader;
      35: invokevirtual #82                 // Method org/aspectj/runtime/reflect/InitializerSignatureImpl.setLookupClassLoader:(Ljava/lang/ClassLoader;)V
      38: aload         5
      40: areturn

  public org.aspectj.lang.reflect.InitializerSignature makeInitializerSig(int, java.lang.Class);
    Code:
       0: new           #32                 // class org/aspectj/runtime/reflect/InitializerSignatureImpl
       3: dup
       4: iload_1
       5: aload_2
       6: invokespecial #33                 // Method org/aspectj/runtime/reflect/InitializerSignatureImpl."<init>":(ILjava/lang/Class;)V
       9: astore_3
      10: aload_3
      11: aload_0
      12: getfield      #14                 // Field lookupClassLoader:Ljava/lang/ClassLoader;
      15: invokevirtual #82                 // Method org/aspectj/runtime/reflect/InitializerSignatureImpl.setLookupClassLoader:(Ljava/lang/ClassLoader;)V
      18: aload_3
      19: areturn

  public org.aspectj.lang.reflect.CatchClauseSignature makeCatchClauseSig(java.lang.String);
    Code:
       0: new           #28                 // class org/aspectj/runtime/reflect/CatchClauseSignatureImpl
       3: dup
       4: aload_1
       5: invokespecial #83                 // Method org/aspectj/runtime/reflect/CatchClauseSignatureImpl."<init>":(Ljava/lang/String;)V
       8: astore_2
       9: aload_2
      10: aload_0
      11: getfield      #14                 // Field lookupClassLoader:Ljava/lang/ClassLoader;
      14: invokevirtual #84                 // Method org/aspectj/runtime/reflect/CatchClauseSignatureImpl.setLookupClassLoader:(Ljava/lang/ClassLoader;)V
      17: aload_2
      18: areturn

  public org.aspectj.lang.reflect.CatchClauseSignature makeCatchClauseSig(java.lang.String, java.lang.String, java.lang.String);
    Code:
       0: aload_1
       1: aload_0
       2: getfield      #14                 // Field lookupClassLoader:Ljava/lang/ClassLoader;
       5: invokestatic  #67                 // Method makeClass:(Ljava/lang/String;Ljava/lang/ClassLoader;)Ljava/lang/Class;
       8: astore        4
      10: new           #70                 // class java/util/StringTokenizer
      13: dup
      14: aload_2
      15: ldc           #71                 // String :
      17: invokespecial #72                 // Method java/util/StringTokenizer."<init>":(Ljava/lang/String;Ljava/lang/String;)V
      20: astore        5
      22: aload         5
      24: invokevirtual #74                 // Method java/util/StringTokenizer.nextToken:()Ljava/lang/String;
      27: aload_0
      28: getfield      #14                 // Field lookupClassLoader:Ljava/lang/ClassLoader;
      31: invokestatic  #67                 // Method makeClass:(Ljava/lang/String;Ljava/lang/ClassLoader;)Ljava/lang/Class;
      34: astore        6
      36: new           #70                 // class java/util/StringTokenizer
      39: dup
      40: aload_3
      41: ldc           #71                 // String :
      43: invokespecial #72                 // Method java/util/StringTokenizer."<init>":(Ljava/lang/String;Ljava/lang/String;)V
      46: astore        5
      48: aload         5
      50: invokevirtual #74                 // Method java/util/StringTokenizer.nextToken:()Ljava/lang/String;
      53: astore        7
      55: new           #28                 // class org/aspectj/runtime/reflect/CatchClauseSignatureImpl
      58: dup
      59: aload         4
      61: aload         6
      63: aload         7
      65: invokespecial #29                 // Method org/aspectj/runtime/reflect/CatchClauseSignatureImpl."<init>":(Ljava/lang/Class;Ljava/lang/Class;Ljava/lang/String;)V
      68: astore        8
      70: aload         8
      72: aload_0
      73: getfield      #14                 // Field lookupClassLoader:Ljava/lang/ClassLoader;
      76: invokevirtual #84                 // Method org/aspectj/runtime/reflect/CatchClauseSignatureImpl.setLookupClassLoader:(Ljava/lang/ClassLoader;)V
      79: aload         8
      81: areturn

  public org.aspectj.lang.reflect.CatchClauseSignature makeCatchClauseSig(java.lang.Class, java.lang.Class, java.lang.String);
    Code:
       0: new           #28                 // class org/aspectj/runtime/reflect/CatchClauseSignatureImpl
       3: dup
       4: aload_1
       5: aload_2
       6: aload_3
       7: invokespecial #29                 // Method org/aspectj/runtime/reflect/CatchClauseSignatureImpl."<init>":(Ljava/lang/Class;Ljava/lang/Class;Ljava/lang/String;)V
      10: astore        4
      12: aload         4
      14: aload_0
      15: getfield      #14                 // Field lookupClassLoader:Ljava/lang/ClassLoader;
      18: invokevirtual #84                 // Method org/aspectj/runtime/reflect/CatchClauseSignatureImpl.setLookupClassLoader:(Ljava/lang/ClassLoader;)V
      21: aload         4
      23: areturn

  public org.aspectj.lang.reflect.LockSignature makeLockSig(java.lang.String);
    Code:
       0: new           #34                 // class org/aspectj/runtime/reflect/LockSignatureImpl
       3: dup
       4: aload_1
       5: invokespecial #85                 // Method org/aspectj/runtime/reflect/LockSignatureImpl."<init>":(Ljava/lang/String;)V
       8: astore_2
       9: aload_2
      10: aload_0
      11: getfield      #14                 // Field lookupClassLoader:Ljava/lang/ClassLoader;
      14: invokevirtual #86                 // Method org/aspectj/runtime/reflect/LockSignatureImpl.setLookupClassLoader:(Ljava/lang/ClassLoader;)V
      17: aload_2
      18: areturn

  public org.aspectj.lang.reflect.LockSignature makeLockSig();
    Code:
       0: ldc           #87                 // String Ljava/lang/Object;
       2: aload_0
       3: getfield      #14                 // Field lookupClassLoader:Ljava/lang/ClassLoader;
       6: invokestatic  #67                 // Method makeClass:(Ljava/lang/String;Ljava/lang/ClassLoader;)Ljava/lang/Class;
       9: astore_1
      10: new           #34                 // class org/aspectj/runtime/reflect/LockSignatureImpl
      13: dup
      14: aload_1
      15: invokespecial #35                 // Method org/aspectj/runtime/reflect/LockSignatureImpl."<init>":(Ljava/lang/Class;)V
      18: astore_2
      19: aload_2
      20: aload_0
      21: getfield      #14                 // Field lookupClassLoader:Ljava/lang/ClassLoader;
      24: invokevirtual #86                 // Method org/aspectj/runtime/reflect/LockSignatureImpl.setLookupClassLoader:(Ljava/lang/ClassLoader;)V
      27: aload_2
      28: areturn

  public org.aspectj.lang.reflect.LockSignature makeLockSig(java.lang.Class);
    Code:
       0: new           #34                 // class org/aspectj/runtime/reflect/LockSignatureImpl
       3: dup
       4: aload_1
       5: invokespecial #35                 // Method org/aspectj/runtime/reflect/LockSignatureImpl."<init>":(Ljava/lang/Class;)V
       8: astore_2
       9: aload_2
      10: aload_0
      11: getfield      #14                 // Field lookupClassLoader:Ljava/lang/ClassLoader;
      14: invokevirtual #86                 // Method org/aspectj/runtime/reflect/LockSignatureImpl.setLookupClassLoader:(Ljava/lang/ClassLoader;)V
      17: aload_2
      18: areturn

  public org.aspectj.lang.reflect.UnlockSignature makeUnlockSig(java.lang.String);
    Code:
       0: new           #36                 // class org/aspectj/runtime/reflect/UnlockSignatureImpl
       3: dup
       4: aload_1
       5: invokespecial #88                 // Method org/aspectj/runtime/reflect/UnlockSignatureImpl."<init>":(Ljava/lang/String;)V
       8: astore_2
       9: aload_2
      10: aload_0
      11: getfield      #14                 // Field lookupClassLoader:Ljava/lang/ClassLoader;
      14: invokevirtual #89                 // Method org/aspectj/runtime/reflect/UnlockSignatureImpl.setLookupClassLoader:(Ljava/lang/ClassLoader;)V
      17: aload_2
      18: areturn

  public org.aspectj.lang.reflect.UnlockSignature makeUnlockSig();
    Code:
       0: ldc           #87                 // String Ljava/lang/Object;
       2: aload_0
       3: getfield      #14                 // Field lookupClassLoader:Ljava/lang/ClassLoader;
       6: invokestatic  #67                 // Method makeClass:(Ljava/lang/String;Ljava/lang/ClassLoader;)Ljava/lang/Class;
       9: astore_1
      10: new           #36                 // class org/aspectj/runtime/reflect/UnlockSignatureImpl
      13: dup
      14: aload_1
      15: invokespecial #37                 // Method org/aspectj/runtime/reflect/UnlockSignatureImpl."<init>":(Ljava/lang/Class;)V
      18: astore_2
      19: aload_2
      20: aload_0
      21: getfield      #14                 // Field lookupClassLoader:Ljava/lang/ClassLoader;
      24: invokevirtual #89                 // Method org/aspectj/runtime/reflect/UnlockSignatureImpl.setLookupClassLoader:(Ljava/lang/ClassLoader;)V
      27: aload_2
      28: areturn

  public org.aspectj.lang.reflect.UnlockSignature makeUnlockSig(java.lang.Class);
    Code:
       0: new           #36                 // class org/aspectj/runtime/reflect/UnlockSignatureImpl
       3: dup
       4: aload_1
       5: invokespecial #37                 // Method org/aspectj/runtime/reflect/UnlockSignatureImpl."<init>":(Ljava/lang/Class;)V
       8: astore_2
       9: aload_2
      10: aload_0
      11: getfield      #14                 // Field lookupClassLoader:Ljava/lang/ClassLoader;
      14: invokevirtual #89                 // Method org/aspectj/runtime/reflect/UnlockSignatureImpl.setLookupClassLoader:(Ljava/lang/ClassLoader;)V
      17: aload_2
      18: areturn

  public org.aspectj.lang.reflect.SourceLocation makeSourceLoc(int, int);
    Code:
       0: new           #90                 // class org/aspectj/runtime/reflect/SourceLocationImpl
       3: dup
       4: aload_0
       5: getfield      #11                 // Field lexicalClass:Ljava/lang/Class;
       8: aload_0
       9: getfield      #10                 // Field filename:Ljava/lang/String;
      12: iload_1
      13: invokespecial #91                 // Method org/aspectj/runtime/reflect/SourceLocationImpl."<init>":(Ljava/lang/Class;Ljava/lang/String;I)V
      16: areturn

  static {};
    Code:
       0: iconst_0
       1: anewarray     #5                  // class java/lang/Class
       4: putstatic     #20                 // Field NO_TYPES:[Ljava/lang/Class;
       7: iconst_0
       8: anewarray     #46                 // class java/lang/String
      11: putstatic     #21                 // Field NO_STRINGS:[Ljava/lang/String;
      14: new           #92                 // class java/util/Hashtable
      17: dup
      18: invokespecial #93                 // Method java/util/Hashtable."<init>":()V
      21: putstatic     #3                  // Field prims:Ljava/util/Hashtable;
      24: getstatic     #3                  // Field prims:Ljava/util/Hashtable;
      27: ldc           #94                 // String void
      29: getstatic     #22                 // Field java/lang/Void.TYPE:Ljava/lang/Class;
      32: invokevirtual #95                 // Method java/util/Hashtable.put:(Ljava/lang/Object;Ljava/lang/Object;)Ljava/lang/Object;
      35: pop
      36: getstatic     #3                  // Field prims:Ljava/util/Hashtable;
      39: ldc           #96                 // String boolean
      41: getstatic     #97                 // Field java/lang/Boolean.TYPE:Ljava/lang/Class;
      44: invokevirtual #95                 // Method java/util/Hashtable.put:(Ljava/lang/Object;Ljava/lang/Object;)Ljava/lang/Object;
      47: pop
      48: getstatic     #3                  // Field prims:Ljava/util/Hashtable;
      51: ldc           #98                 // String byte
      53: getstatic     #99                 // Field java/lang/Byte.TYPE:Ljava/lang/Class;
      56: invokevirtual #95                 // Method java/util/Hashtable.put:(Ljava/lang/Object;Ljava/lang/Object;)Ljava/lang/Object;
      59: pop
      60: getstatic     #3                  // Field prims:Ljava/util/Hashtable;
      63: ldc           #100                // String char
      65: getstatic     #101                // Field java/lang/Character.TYPE:Ljava/lang/Class;
      68: invokevirtual #95                 // Method java/util/Hashtable.put:(Ljava/lang/Object;Ljava/lang/Object;)Ljava/lang/Object;
      71: pop
      72: getstatic     #3                  // Field prims:Ljava/util/Hashtable;
      75: ldc           #102                // String short
      77: getstatic     #103                // Field java/lang/Short.TYPE:Ljava/lang/Class;
      80: invokevirtual #95                 // Method java/util/Hashtable.put:(Ljava/lang/Object;Ljava/lang/Object;)Ljava/lang/Object;
      83: pop
      84: getstatic     #3                  // Field prims:Ljava/util/Hashtable;
      87: ldc           #104                // String int
      89: getstatic     #105                // Field java/lang/Integer.TYPE:Ljava/lang/Class;
      92: invokevirtual #95                 // Method java/util/Hashtable.put:(Ljava/lang/Object;Ljava/lang/Object;)Ljava/lang/Object;
      95: pop
      96: getstatic     #3                  // Field prims:Ljava/util/Hashtable;
      99: ldc           #106                // String long
     101: getstatic     #107                // Field java/lang/Long.TYPE:Ljava/lang/Class;
     104: invokevirtual #95                 // Method java/util/Hashtable.put:(Ljava/lang/Object;Ljava/lang/Object;)Ljava/lang/Object;
     107: pop
     108: getstatic     #3                  // Field prims:Ljava/util/Hashtable;
     111: ldc           #108                // String float
     113: getstatic     #109                // Field java/lang/Float.TYPE:Ljava/lang/Class;
     116: invokevirtual #95                 // Method java/util/Hashtable.put:(Ljava/lang/Object;Ljava/lang/Object;)Ljava/lang/Object;
     119: pop
     120: getstatic     #3                  // Field prims:Ljava/util/Hashtable;
     123: ldc           #110                // String double
     125: getstatic     #111                // Field java/lang/Double.TYPE:Ljava/lang/Class;
     128: invokevirtual #95                 // Method java/util/Hashtable.put:(Ljava/lang/Object;Ljava/lang/Object;)Ljava/lang/Object;
     131: pop
     132: iconst_0
     133: anewarray     #64                 // class java/lang/Object
     136: putstatic     #62                 // Field NO_ARGS:[Ljava/lang/Object;
     139: return
}
