Compiled from "SourceLocationImpl.java"
class org.aspectj.runtime.reflect.SourceLocationImpl implements org.aspectj.lang.reflect.SourceLocation {
  java.lang.Class withinType;

  java.lang.String fileName;

  int line;

  org.aspectj.runtime.reflect.SourceLocationImpl(java.lang.Class, java.lang.String, int);
    Code:
       0: aload_0
       1: invokespecial #1                  // Method java/lang/Object."<init>":()V
       4: aload_0
       5: aload_1
       6: putfield      #2                  // Field withinType:Ljava/lang/Class;
       9: aload_0
      10: aload_2
      11: putfield      #3                  // Field fileName:Ljava/lang/String;
      14: aload_0
      15: iload_3
      16: putfield      #4                  // Field line:I
      19: return

  public java.lang.Class getWithinType();
    Code:
       0: aload_0
       1: getfield      #2                  // Field withinType:Ljava/lang/Class;
       4: areturn

  public java.lang.String getFileName();
    Code:
       0: aload_0
       1: getfield      #3                  // Field fileName:Ljava/lang/String;
       4: areturn

  public int getLine();
    Code:
       0: aload_0
       1: getfield      #4                  // Field line:I
       4: ireturn

  public int getColumn();
    Code:
       0: iconst_m1
       1: ireturn

  public java.lang.String toString();
    Code:
       0: new           #5                  // class java/lang/StringBuilder
       3: dup
       4: invokespecial #6                  // Method java/lang/StringBuilder."<init>":()V
       7: aload_0
       8: invokevirtual #7                  // Method getFileName:()Ljava/lang/String;
      11: invokevirtual #8                  // Method java/lang/StringBuilder.append:(Ljava/lang/String;)Ljava/lang/StringBuilder;
      14: ldc           #9                  // String :
      16: invokevirtual #8                  // Method java/lang/StringBuilder.append:(Ljava/lang/String;)Ljava/lang/StringBuilder;
      19: aload_0
      20: invokevirtual #10                 // Method getLine:()I
      23: invokevirtual #11                 // Method java/lang/StringBuilder.append:(I)Ljava/lang/StringBuilder;
      26: invokevirtual #12                 // Method java/lang/StringBuilder.toString:()Ljava/lang/String;
      29: areturn
}
