Compiled from "ComponentScanBeanDefinitionParser.java"
public class org.springframework.context.annotation.ComponentScanBeanDefinitionParser implements org.springframework.beans.factory.xml.BeanDefinitionParser {
  private static final java.lang.String BASE_PACKAGE_ATTRIBUTE;

  private static final java.lang.String RESOURCE_PATTERN_ATTRIBUTE;

  private static final java.lang.String USE_DEFAULT_FILTERS_ATTRIBUTE;

  private static final java.lang.String ANNOTATION_CONFIG_ATTRIBUTE;

  private static final java.lang.String NAME_GENERATOR_ATTRIBUTE;

  private static final java.lang.String SCOPE_RESOLVER_ATTRIBUTE;

  private static final java.lang.String SCOPED_PROXY_ATTRIBUTE;

  private static final java.lang.String EXCLUDE_FILTER_ELEMENT;

  private static final java.lang.String INCLUDE_FILTER_ELEMENT;

  private static final java.lang.String FILTER_TYPE_ATTRIBUTE;

  private static final java.lang.String FILTER_EXPRESSION_ATTRIBUTE;

  public org.springframework.context.annotation.ComponentScanBeanDefinitionParser();
    Code:
       0: aload_0
       1: invokespecial #1                  // Method java/lang/Object."<init>":()V
       4: return

  public org.springframework.beans.factory.config.BeanDefinition parse(org.w3c.dom.Element, org.springframework.beans.factory.xml.ParserContext);
    Code:
       0: aload_1
       1: ldc           #3                  // String base-package
       3: invokeinterface #4,  2            // InterfaceMethod org/w3c/dom/Element.getAttribute:(Ljava/lang/String;)Ljava/lang/String;
       8: astore_3
       9: aload_2
      10: invokevirtual #5                  // Method org/springframework/beans/factory/xml/ParserContext.getReaderContext:()Lorg/springframework/beans/factory/xml/XmlReaderContext;
      13: invokevirtual #6                  // Method org/springframework/beans/factory/xml/XmlReaderContext.getEnvironment:()Lorg/springframework/core/env/Environment;
      16: aload_3
      17: invokeinterface #7,  2            // InterfaceMethod org/springframework/core/env/Environment.resolvePlaceholders:(Ljava/lang/String;)Ljava/lang/String;
      22: astore_3
      23: aload_3
      24: ldc           #9                  // String ,; \t\n
      26: invokestatic  #10                 // Method org/springframework/util/StringUtils.tokenizeToStringArray:(Ljava/lang/String;Ljava/lang/String;)[Ljava/lang/String;
      29: astore        4
      31: aload_0
      32: aload_2
      33: aload_1
      34: invokevirtual #11                 // Method configureScanner:(Lorg/springframework/beans/factory/xml/ParserContext;Lorg/w3c/dom/Element;)Lorg/springframework/context/annotation/ClassPathBeanDefinitionScanner;
      37: astore        5
      39: aload         5
      41: aload         4
      43: invokevirtual #12                 // Method org/springframework/context/annotation/ClassPathBeanDefinitionScanner.doScan:([Ljava/lang/String;)Ljava/util/Set;
      46: astore        6
      48: aload_0
      49: aload_2
      50: invokevirtual #5                  // Method org/springframework/beans/factory/xml/ParserContext.getReaderContext:()Lorg/springframework/beans/factory/xml/XmlReaderContext;
      53: aload         6
      55: aload_1
      56: invokevirtual #13                 // Method registerComponents:(Lorg/springframework/beans/factory/xml/XmlReaderContext;Ljava/util/Set;Lorg/w3c/dom/Element;)V
      59: aconst_null
      60: areturn

  protected org.springframework.context.annotation.ClassPathBeanDefinitionScanner configureScanner(org.springframework.beans.factory.xml.ParserContext, org.w3c.dom.Element);
    Code:
       0: iconst_1
       1: istore_3
       2: aload_2
       3: ldc           #14                 // String use-default-filters
       5: invokeinterface #15,  2           // InterfaceMethod org/w3c/dom/Element.hasAttribute:(Ljava/lang/String;)Z
      10: ifeq          28
      13: aload_2
      14: ldc           #14                 // String use-default-filters
      16: invokeinterface #4,  2            // InterfaceMethod org/w3c/dom/Element.getAttribute:(Ljava/lang/String;)Ljava/lang/String;
      21: invokestatic  #16                 // Method java/lang/Boolean.valueOf:(Ljava/lang/String;)Ljava/lang/Boolean;
      24: invokevirtual #17                 // Method java/lang/Boolean.booleanValue:()Z
      27: istore_3
      28: aload_0
      29: aload_1
      30: invokevirtual #5                  // Method org/springframework/beans/factory/xml/ParserContext.getReaderContext:()Lorg/springframework/beans/factory/xml/XmlReaderContext;
      33: iload_3
      34: invokevirtual #18                 // Method createScanner:(Lorg/springframework/beans/factory/xml/XmlReaderContext;Z)Lorg/springframework/context/annotation/ClassPathBeanDefinitionScanner;
      37: astore        4
      39: aload         4
      41: aload_1
      42: invokevirtual #19                 // Method org/springframework/beans/factory/xml/ParserContext.getDelegate:()Lorg/springframework/beans/factory/xml/BeanDefinitionParserDelegate;
      45: invokevirtual #20                 // Method org/springframework/beans/factory/xml/BeanDefinitionParserDelegate.getBeanDefinitionDefaults:()Lorg/springframework/beans/factory/support/BeanDefinitionDefaults;
      48: invokevirtual #21                 // Method org/springframework/context/annotation/ClassPathBeanDefinitionScanner.setBeanDefinitionDefaults:(Lorg/springframework/beans/factory/support/BeanDefinitionDefaults;)V
      51: aload         4
      53: aload_1
      54: invokevirtual #19                 // Method org/springframework/beans/factory/xml/ParserContext.getDelegate:()Lorg/springframework/beans/factory/xml/BeanDefinitionParserDelegate;
      57: invokevirtual #22                 // Method org/springframework/beans/factory/xml/BeanDefinitionParserDelegate.getAutowireCandidatePatterns:()[Ljava/lang/String;
      60: invokevirtual #23                 // Method org/springframework/context/annotation/ClassPathBeanDefinitionScanner.setAutowireCandidatePatterns:([Ljava/lang/String;)V
      63: aload_2
      64: ldc           #24                 // String resource-pattern
      66: invokeinterface #15,  2           // InterfaceMethod org/w3c/dom/Element.hasAttribute:(Ljava/lang/String;)Z
      71: ifeq          87
      74: aload         4
      76: aload_2
      77: ldc           #24                 // String resource-pattern
      79: invokeinterface #4,  2            // InterfaceMethod org/w3c/dom/Element.getAttribute:(Ljava/lang/String;)Ljava/lang/String;
      84: invokevirtual #25                 // Method org/springframework/context/annotation/ClassPathBeanDefinitionScanner.setResourcePattern:(Ljava/lang/String;)V
      87: aload_0
      88: aload_2
      89: aload         4
      91: invokevirtual #26                 // Method parseBeanNameGenerator:(Lorg/w3c/dom/Element;Lorg/springframework/context/annotation/ClassPathBeanDefinitionScanner;)V
      94: goto          121
      97: astore        5
      99: aload_1
     100: invokevirtual #5                  // Method org/springframework/beans/factory/xml/ParserContext.getReaderContext:()Lorg/springframework/beans/factory/xml/XmlReaderContext;
     103: aload         5
     105: invokevirtual #28                 // Method java/lang/Exception.getMessage:()Ljava/lang/String;
     108: aload_1
     109: aload_2
     110: invokevirtual #29                 // Method org/springframework/beans/factory/xml/ParserContext.extractSource:(Ljava/lang/Object;)Ljava/lang/Object;
     113: aload         5
     115: invokevirtual #30                 // Method java/lang/Exception.getCause:()Ljava/lang/Throwable;
     118: invokevirtual #31                 // Method org/springframework/beans/factory/xml/XmlReaderContext.error:(Ljava/lang/String;Ljava/lang/Object;Ljava/lang/Throwable;)V
     121: aload_0
     122: aload_2
     123: aload         4
     125: invokevirtual #32                 // Method parseScope:(Lorg/w3c/dom/Element;Lorg/springframework/context/annotation/ClassPathBeanDefinitionScanner;)V
     128: goto          155
     131: astore        5
     133: aload_1
     134: invokevirtual #5                  // Method org/springframework/beans/factory/xml/ParserContext.getReaderContext:()Lorg/springframework/beans/factory/xml/XmlReaderContext;
     137: aload         5
     139: invokevirtual #28                 // Method java/lang/Exception.getMessage:()Ljava/lang/String;
     142: aload_1
     143: aload_2
     144: invokevirtual #29                 // Method org/springframework/beans/factory/xml/ParserContext.extractSource:(Ljava/lang/Object;)Ljava/lang/Object;
     147: aload         5
     149: invokevirtual #30                 // Method java/lang/Exception.getCause:()Ljava/lang/Throwable;
     152: invokevirtual #31                 // Method org/springframework/beans/factory/xml/XmlReaderContext.error:(Ljava/lang/String;Ljava/lang/Object;Ljava/lang/Throwable;)V
     155: aload_0
     156: aload_2
     157: aload         4
     159: aload_1
     160: invokevirtual #33                 // Method parseTypeFilters:(Lorg/w3c/dom/Element;Lorg/springframework/context/annotation/ClassPathBeanDefinitionScanner;Lorg/springframework/beans/factory/xml/ParserContext;)V
     163: aload         4
     165: areturn
    Exception table:
       from    to  target type
          87    94    97   Class java/lang/Exception
         121   128   131   Class java/lang/Exception

  protected org.springframework.context.annotation.ClassPathBeanDefinitionScanner createScanner(org.springframework.beans.factory.xml.XmlReaderContext, boolean);
    Code:
       0: new           #34                 // class org/springframework/context/annotation/ClassPathBeanDefinitionScanner
       3: dup
       4: aload_1
       5: invokevirtual #35                 // Method org/springframework/beans/factory/xml/XmlReaderContext.getRegistry:()Lorg/springframework/beans/factory/support/BeanDefinitionRegistry;
       8: iload_2
       9: aload_1
      10: invokevirtual #6                  // Method org/springframework/beans/factory/xml/XmlReaderContext.getEnvironment:()Lorg/springframework/core/env/Environment;
      13: aload_1
      14: invokevirtual #36                 // Method org/springframework/beans/factory/xml/XmlReaderContext.getResourceLoader:()Lorg/springframework/core/io/ResourceLoader;
      17: invokespecial #37                 // Method org/springframework/context/annotation/ClassPathBeanDefinitionScanner."<init>":(Lorg/springframework/beans/factory/support/BeanDefinitionRegistry;ZLorg/springframework/core/env/Environment;Lorg/springframework/core/io/ResourceLoader;)V
      20: areturn

  protected void registerComponents(org.springframework.beans.factory.xml.XmlReaderContext, java.util.Set<org.springframework.beans.factory.config.BeanDefinitionHolder>, org.w3c.dom.Element);
    Code:
       0: aload_1
       1: aload_3
       2: invokevirtual #38                 // Method org/springframework/beans/factory/xml/XmlReaderContext.extractSource:(Ljava/lang/Object;)Ljava/lang/Object;
       5: astore        4
       7: new           #39                 // class org/springframework/beans/factory/parsing/CompositeComponentDefinition
      10: dup
      11: aload_3
      12: invokeinterface #40,  1           // InterfaceMethod org/w3c/dom/Element.getTagName:()Ljava/lang/String;
      17: aload         4
      19: invokespecial #41                 // Method org/springframework/beans/factory/parsing/CompositeComponentDefinition."<init>":(Ljava/lang/String;Ljava/lang/Object;)V
      22: astore        5
      24: aload_2
      25: invokeinterface #42,  1           // InterfaceMethod java/util/Set.iterator:()Ljava/util/Iterator;
      30: astore        6
      32: aload         6
      34: invokeinterface #43,  1           // InterfaceMethod java/util/Iterator.hasNext:()Z
      39: ifeq          71
      42: aload         6
      44: invokeinterface #44,  1           // InterfaceMethod java/util/Iterator.next:()Ljava/lang/Object;
      49: checkcast     #45                 // class org/springframework/beans/factory/config/BeanDefinitionHolder
      52: astore        7
      54: aload         5
      56: new           #46                 // class org/springframework/beans/factory/parsing/BeanComponentDefinition
      59: dup
      60: aload         7
      62: invokespecial #47                 // Method org/springframework/beans/factory/parsing/BeanComponentDefinition."<init>":(Lorg/springframework/beans/factory/config/BeanDefinitionHolder;)V
      65: invokevirtual #48                 // Method org/springframework/beans/factory/parsing/CompositeComponentDefinition.addNestedComponent:(Lorg/springframework/beans/factory/parsing/ComponentDefinition;)V
      68: goto          32
      71: iconst_1
      72: istore        6
      74: aload_3
      75: ldc           #49                 // String annotation-config
      77: invokeinterface #15,  2           // InterfaceMethod org/w3c/dom/Element.hasAttribute:(Ljava/lang/String;)Z
      82: ifeq          101
      85: aload_3
      86: ldc           #49                 // String annotation-config
      88: invokeinterface #4,  2            // InterfaceMethod org/w3c/dom/Element.getAttribute:(Ljava/lang/String;)Ljava/lang/String;
      93: invokestatic  #16                 // Method java/lang/Boolean.valueOf:(Ljava/lang/String;)Ljava/lang/Boolean;
      96: invokevirtual #17                 // Method java/lang/Boolean.booleanValue:()Z
      99: istore        6
     101: iload         6
     103: ifeq          165
     106: aload_1
     107: invokevirtual #35                 // Method org/springframework/beans/factory/xml/XmlReaderContext.getRegistry:()Lorg/springframework/beans/factory/support/BeanDefinitionRegistry;
     110: aload         4
     112: invokestatic  #50                 // Method org/springframework/context/annotation/AnnotationConfigUtils.registerAnnotationConfigProcessors:(Lorg/springframework/beans/factory/support/BeanDefinitionRegistry;Ljava/lang/Object;)Ljava/util/Set;
     115: astore        7
     117: aload         7
     119: invokeinterface #42,  1           // InterfaceMethod java/util/Set.iterator:()Ljava/util/Iterator;
     124: astore        8
     126: aload         8
     128: invokeinterface #43,  1           // InterfaceMethod java/util/Iterator.hasNext:()Z
     133: ifeq          165
     136: aload         8
     138: invokeinterface #44,  1           // InterfaceMethod java/util/Iterator.next:()Ljava/lang/Object;
     143: checkcast     #45                 // class org/springframework/beans/factory/config/BeanDefinitionHolder
     146: astore        9
     148: aload         5
     150: new           #46                 // class org/springframework/beans/factory/parsing/BeanComponentDefinition
     153: dup
     154: aload         9
     156: invokespecial #47                 // Method org/springframework/beans/factory/parsing/BeanComponentDefinition."<init>":(Lorg/springframework/beans/factory/config/BeanDefinitionHolder;)V
     159: invokevirtual #48                 // Method org/springframework/beans/factory/parsing/CompositeComponentDefinition.addNestedComponent:(Lorg/springframework/beans/factory/parsing/ComponentDefinition;)V
     162: goto          126
     165: aload_1
     166: aload         5
     168: invokevirtual #51                 // Method org/springframework/beans/factory/xml/XmlReaderContext.fireComponentRegistered:(Lorg/springframework/beans/factory/parsing/ComponentDefinition;)V
     171: return

  protected void parseBeanNameGenerator(org.w3c.dom.Element, org.springframework.context.annotation.ClassPathBeanDefinitionScanner);
    Code:
       0: aload_1
       1: ldc           #52                 // String name-generator
       3: invokeinterface #15,  2           // InterfaceMethod org/w3c/dom/Element.hasAttribute:(Ljava/lang/String;)Z
       8: ifeq          43
      11: aload_0
      12: aload_1
      13: ldc           #52                 // String name-generator
      15: invokeinterface #4,  2            // InterfaceMethod org/w3c/dom/Element.getAttribute:(Ljava/lang/String;)Ljava/lang/String;
      20: ldc           #53                 // class org/springframework/beans/factory/support/BeanNameGenerator
      22: aload_2
      23: invokevirtual #54                 // Method org/springframework/context/annotation/ClassPathBeanDefinitionScanner.getResourceLoader:()Lorg/springframework/core/io/ResourceLoader;
      26: invokeinterface #55,  1           // InterfaceMethod org/springframework/core/io/ResourceLoader.getClassLoader:()Ljava/lang/ClassLoader;
      31: invokespecial #56                 // Method instantiateUserDefinedStrategy:(Ljava/lang/String;Ljava/lang/Class;Ljava/lang/ClassLoader;)Ljava/lang/Object;
      34: checkcast     #53                 // class org/springframework/beans/factory/support/BeanNameGenerator
      37: astore_3
      38: aload_2
      39: aload_3
      40: invokevirtual #57                 // Method org/springframework/context/annotation/ClassPathBeanDefinitionScanner.setBeanNameGenerator:(Lorg/springframework/beans/factory/support/BeanNameGenerator;)V
      43: return

  protected void parseScope(org.w3c.dom.Element, org.springframework.context.annotation.ClassPathBeanDefinitionScanner);
    Code:
       0: aload_1
       1: ldc           #58                 // String scope-resolver
       3: invokeinterface #15,  2           // InterfaceMethod org/w3c/dom/Element.hasAttribute:(Ljava/lang/String;)Z
       8: ifeq          64
      11: aload_1
      12: ldc           #59                 // String scoped-proxy
      14: invokeinterface #15,  2           // InterfaceMethod org/w3c/dom/Element.hasAttribute:(Ljava/lang/String;)Z
      19: ifeq          32
      22: new           #60                 // class java/lang/IllegalArgumentException
      25: dup
      26: ldc           #61                 // String Cannot define both \'scope-resolver\' and \'scoped-proxy\' on <component-scan> tag
      28: invokespecial #62                 // Method java/lang/IllegalArgumentException."<init>":(Ljava/lang/String;)V
      31: athrow
      32: aload_0
      33: aload_1
      34: ldc           #58                 // String scope-resolver
      36: invokeinterface #4,  2            // InterfaceMethod org/w3c/dom/Element.getAttribute:(Ljava/lang/String;)Ljava/lang/String;
      41: ldc           #63                 // class org/springframework/context/annotation/ScopeMetadataResolver
      43: aload_2
      44: invokevirtual #54                 // Method org/springframework/context/annotation/ClassPathBeanDefinitionScanner.getResourceLoader:()Lorg/springframework/core/io/ResourceLoader;
      47: invokeinterface #55,  1           // InterfaceMethod org/springframework/core/io/ResourceLoader.getClassLoader:()Ljava/lang/ClassLoader;
      52: invokespecial #56                 // Method instantiateUserDefinedStrategy:(Ljava/lang/String;Ljava/lang/Class;Ljava/lang/ClassLoader;)Ljava/lang/Object;
      55: checkcast     #63                 // class org/springframework/context/annotation/ScopeMetadataResolver
      58: astore_3
      59: aload_2
      60: aload_3
      61: invokevirtual #64                 // Method org/springframework/context/annotation/ClassPathBeanDefinitionScanner.setScopeMetadataResolver:(Lorg/springframework/context/annotation/ScopeMetadataResolver;)V
      64: aload_1
      65: ldc           #59                 // String scoped-proxy
      67: invokeinterface #15,  2           // InterfaceMethod org/w3c/dom/Element.hasAttribute:(Ljava/lang/String;)Z
      72: ifeq          151
      75: aload_1
      76: ldc           #59                 // String scoped-proxy
      78: invokeinterface #4,  2            // InterfaceMethod org/w3c/dom/Element.getAttribute:(Ljava/lang/String;)Ljava/lang/String;
      83: astore_3
      84: ldc           #65                 // String targetClass
      86: aload_3
      87: invokevirtual #66                 // Method java/lang/String.equals:(Ljava/lang/Object;)Z
      90: ifeq          103
      93: aload_2
      94: getstatic     #67                 // Field org/springframework/context/annotation/ScopedProxyMode.TARGET_CLASS:Lorg/springframework/context/annotation/ScopedProxyMode;
      97: invokevirtual #68                 // Method org/springframework/context/annotation/ClassPathBeanDefinitionScanner.setScopedProxyMode:(Lorg/springframework/context/annotation/ScopedProxyMode;)V
     100: goto          151
     103: ldc           #69                 // String interfaces
     105: aload_3
     106: invokevirtual #66                 // Method java/lang/String.equals:(Ljava/lang/Object;)Z
     109: ifeq          122
     112: aload_2
     113: getstatic     #70                 // Field org/springframework/context/annotation/ScopedProxyMode.INTERFACES:Lorg/springframework/context/annotation/ScopedProxyMode;
     116: invokevirtual #68                 // Method org/springframework/context/annotation/ClassPathBeanDefinitionScanner.setScopedProxyMode:(Lorg/springframework/context/annotation/ScopedProxyMode;)V
     119: goto          151
     122: ldc           #71                 // String no
     124: aload_3
     125: invokevirtual #66                 // Method java/lang/String.equals:(Ljava/lang/Object;)Z
     128: ifeq          141
     131: aload_2
     132: getstatic     #72                 // Field org/springframework/context/annotation/ScopedProxyMode.NO:Lorg/springframework/context/annotation/ScopedProxyMode;
     135: invokevirtual #68                 // Method org/springframework/context/annotation/ClassPathBeanDefinitionScanner.setScopedProxyMode:(Lorg/springframework/context/annotation/ScopedProxyMode;)V
     138: goto          151
     141: new           #60                 // class java/lang/IllegalArgumentException
     144: dup
     145: ldc           #73                 // String scoped-proxy only supports \'no\', \'interfaces\' and \'targetClass\'
     147: invokespecial #62                 // Method java/lang/IllegalArgumentException."<init>":(Ljava/lang/String;)V
     150: athrow
     151: return

  protected void parseTypeFilters(org.w3c.dom.Element, org.springframework.context.annotation.ClassPathBeanDefinitionScanner, org.springframework.beans.factory.xml.ParserContext);
    Code:
       0: aload_2
       1: invokevirtual #54                 // Method org/springframework/context/annotation/ClassPathBeanDefinitionScanner.getResourceLoader:()Lorg/springframework/core/io/ResourceLoader;
       4: invokeinterface #55,  1           // InterfaceMethod org/springframework/core/io/ResourceLoader.getClassLoader:()Ljava/lang/ClassLoader;
       9: astore        4
      11: aload_1
      12: invokeinterface #74,  1           // InterfaceMethod org/w3c/dom/Element.getChildNodes:()Lorg/w3c/dom/NodeList;
      17: astore        5
      19: iconst_0
      20: istore        6
      22: iload         6
      24: aload         5
      26: invokeinterface #75,  1           // InterfaceMethod org/w3c/dom/NodeList.getLength:()I
      31: if_icmpge     200
      34: aload         5
      36: iload         6
      38: invokeinterface #76,  2           // InterfaceMethod org/w3c/dom/NodeList.item:(I)Lorg/w3c/dom/Node;
      43: astore        7
      45: aload         7
      47: invokeinterface #77,  1           // InterfaceMethod org/w3c/dom/Node.getNodeType:()S
      52: iconst_1
      53: if_icmpne     194
      56: aload_3
      57: invokevirtual #19                 // Method org/springframework/beans/factory/xml/ParserContext.getDelegate:()Lorg/springframework/beans/factory/xml/BeanDefinitionParserDelegate;
      60: aload         7
      62: invokevirtual #79                 // Method org/springframework/beans/factory/xml/BeanDefinitionParserDelegate.getLocalName:(Lorg/w3c/dom/Node;)Ljava/lang/String;
      65: astore        8
      67: ldc           #80                 // String include-filter
      69: aload         8
      71: invokevirtual #66                 // Method java/lang/String.equals:(Ljava/lang/Object;)Z
      74: ifeq          100
      77: aload_0
      78: aload         7
      80: checkcast     #81                 // class org/w3c/dom/Element
      83: aload         4
      85: aload_3
      86: invokevirtual #82                 // Method createTypeFilter:(Lorg/w3c/dom/Element;Ljava/lang/ClassLoader;Lorg/springframework/beans/factory/xml/ParserContext;)Lorg/springframework/core/type/filter/TypeFilter;
      89: astore        9
      91: aload_2
      92: aload         9
      94: invokevirtual #83                 // Method org/springframework/context/annotation/ClassPathBeanDefinitionScanner.addIncludeFilter:(Lorg/springframework/core/type/filter/TypeFilter;)V
      97: goto          130
     100: ldc           #84                 // String exclude-filter
     102: aload         8
     104: invokevirtual #66                 // Method java/lang/String.equals:(Ljava/lang/Object;)Z
     107: ifeq          130
     110: aload_0
     111: aload         7
     113: checkcast     #81                 // class org/w3c/dom/Element
     116: aload         4
     118: aload_3
     119: invokevirtual #82                 // Method createTypeFilter:(Lorg/w3c/dom/Element;Ljava/lang/ClassLoader;Lorg/springframework/beans/factory/xml/ParserContext;)Lorg/springframework/core/type/filter/TypeFilter;
     122: astore        9
     124: aload_2
     125: aload         9
     127: invokevirtual #85                 // Method org/springframework/context/annotation/ClassPathBeanDefinitionScanner.addExcludeFilter:(Lorg/springframework/core/type/filter/TypeFilter;)V
     130: goto          194
     133: astore        9
     135: aload_3
     136: invokevirtual #5                  // Method org/springframework/beans/factory/xml/ParserContext.getReaderContext:()Lorg/springframework/beans/factory/xml/XmlReaderContext;
     139: new           #87                 // class java/lang/StringBuilder
     142: dup
     143: invokespecial #88                 // Method java/lang/StringBuilder."<init>":()V
     146: ldc           #89                 // String Ignoring non-present type filter class:
     148: invokevirtual #90                 // Method java/lang/StringBuilder.append:(Ljava/lang/String;)Ljava/lang/StringBuilder;
     151: aload         9
     153: invokevirtual #91                 // Method java/lang/StringBuilder.append:(Ljava/lang/Object;)Ljava/lang/StringBuilder;
     156: invokevirtual #92                 // Method java/lang/StringBuilder.toString:()Ljava/lang/String;
     159: aload_3
     160: aload_1
     161: invokevirtual #29                 // Method org/springframework/beans/factory/xml/ParserContext.extractSource:(Ljava/lang/Object;)Ljava/lang/Object;
     164: invokevirtual #93                 // Method org/springframework/beans/factory/xml/XmlReaderContext.warning:(Ljava/lang/String;Ljava/lang/Object;)V
     167: goto          194
     170: astore        9
     172: aload_3
     173: invokevirtual #5                  // Method org/springframework/beans/factory/xml/ParserContext.getReaderContext:()Lorg/springframework/beans/factory/xml/XmlReaderContext;
     176: aload         9
     178: invokevirtual #28                 // Method java/lang/Exception.getMessage:()Ljava/lang/String;
     181: aload_3
     182: aload_1
     183: invokevirtual #29                 // Method org/springframework/beans/factory/xml/ParserContext.extractSource:(Ljava/lang/Object;)Ljava/lang/Object;
     186: aload         9
     188: invokevirtual #30                 // Method java/lang/Exception.getCause:()Ljava/lang/Throwable;
     191: invokevirtual #31                 // Method org/springframework/beans/factory/xml/XmlReaderContext.error:(Ljava/lang/String;Ljava/lang/Object;Ljava/lang/Throwable;)V
     194: iinc          6, 1
     197: goto          22
     200: return
    Exception table:
       from    to  target type
          67   130   133   Class java/lang/ClassNotFoundException
          67   130   170   Class java/lang/Exception

  protected org.springframework.core.type.filter.TypeFilter createTypeFilter(org.w3c.dom.Element, java.lang.ClassLoader, org.springframework.beans.factory.xml.ParserContext) throws java.lang.ClassNotFoundException;
    Code:
       0: aload_1
       1: ldc           #94                 // String type
       3: invokeinterface #4,  2            // InterfaceMethod org/w3c/dom/Element.getAttribute:(Ljava/lang/String;)Ljava/lang/String;
       8: astore        4
      10: aload_1
      11: ldc           #95                 // String expression
      13: invokeinterface #4,  2            // InterfaceMethod org/w3c/dom/Element.getAttribute:(Ljava/lang/String;)Ljava/lang/String;
      18: astore        5
      20: aload_3
      21: invokevirtual #5                  // Method org/springframework/beans/factory/xml/ParserContext.getReaderContext:()Lorg/springframework/beans/factory/xml/XmlReaderContext;
      24: invokevirtual #6                  // Method org/springframework/beans/factory/xml/XmlReaderContext.getEnvironment:()Lorg/springframework/core/env/Environment;
      27: aload         5
      29: invokeinterface #7,  2            // InterfaceMethod org/springframework/core/env/Environment.resolvePlaceholders:(Ljava/lang/String;)Ljava/lang/String;
      34: astore        5
      36: ldc           #96                 // String annotation
      38: aload         4
      40: invokevirtual #66                 // Method java/lang/String.equals:(Ljava/lang/Object;)Z
      43: ifeq          60
      46: new           #97                 // class org/springframework/core/type/filter/AnnotationTypeFilter
      49: dup
      50: aload         5
      52: aload_2
      53: invokestatic  #98                 // Method org/springframework/util/ClassUtils.forName:(Ljava/lang/String;Ljava/lang/ClassLoader;)Ljava/lang/Class;
      56: invokespecial #99                 // Method org/springframework/core/type/filter/AnnotationTypeFilter."<init>":(Ljava/lang/Class;)V
      59: areturn
      60: ldc           #100                // String assignable
      62: aload         4
      64: invokevirtual #66                 // Method java/lang/String.equals:(Ljava/lang/Object;)Z
      67: ifeq          84
      70: new           #101                // class org/springframework/core/type/filter/AssignableTypeFilter
      73: dup
      74: aload         5
      76: aload_2
      77: invokestatic  #98                 // Method org/springframework/util/ClassUtils.forName:(Ljava/lang/String;Ljava/lang/ClassLoader;)Ljava/lang/Class;
      80: invokespecial #102                // Method org/springframework/core/type/filter/AssignableTypeFilter."<init>":(Ljava/lang/Class;)V
      83: areturn
      84: ldc           #103                // String aspectj
      86: aload         4
      88: invokevirtual #66                 // Method java/lang/String.equals:(Ljava/lang/Object;)Z
      91: ifeq          105
      94: new           #104                // class org/springframework/core/type/filter/AspectJTypeFilter
      97: dup
      98: aload         5
     100: aload_2
     101: invokespecial #105                // Method org/springframework/core/type/filter/AspectJTypeFilter."<init>":(Ljava/lang/String;Ljava/lang/ClassLoader;)V
     104: areturn
     105: ldc           #106                // String regex
     107: aload         4
     109: invokevirtual #66                 // Method java/lang/String.equals:(Ljava/lang/Object;)Z
     112: ifeq          128
     115: new           #107                // class org/springframework/core/type/filter/RegexPatternTypeFilter
     118: dup
     119: aload         5
     121: invokestatic  #108                // Method java/util/regex/Pattern.compile:(Ljava/lang/String;)Ljava/util/regex/Pattern;
     124: invokespecial #109                // Method org/springframework/core/type/filter/RegexPatternTypeFilter."<init>":(Ljava/util/regex/Pattern;)V
     127: areturn
     128: ldc           #110                // String custom
     130: aload         4
     132: invokevirtual #66                 // Method java/lang/String.equals:(Ljava/lang/Object;)Z
     135: ifeq          206
     138: aload         5
     140: aload_2
     141: invokestatic  #98                 // Method org/springframework/util/ClassUtils.forName:(Ljava/lang/String;Ljava/lang/ClassLoader;)Ljava/lang/Class;
     144: astore        6
     146: ldc           #111                // class org/springframework/core/type/filter/TypeFilter
     148: aload         6
     150: invokevirtual #112                // Method java/lang/Class.isAssignableFrom:(Ljava/lang/Class;)Z
     153: ifne          197
     156: new           #60                 // class java/lang/IllegalArgumentException
     159: dup
     160: new           #87                 // class java/lang/StringBuilder
     163: dup
     164: invokespecial #88                 // Method java/lang/StringBuilder."<init>":()V
     167: ldc           #113                // String Class is not assignable to [
     169: invokevirtual #90                 // Method java/lang/StringBuilder.append:(Ljava/lang/String;)Ljava/lang/StringBuilder;
     172: ldc           #111                // class org/springframework/core/type/filter/TypeFilter
     174: invokevirtual #114                // Method java/lang/Class.getName:()Ljava/lang/String;
     177: invokevirtual #90                 // Method java/lang/StringBuilder.append:(Ljava/lang/String;)Ljava/lang/StringBuilder;
     180: ldc           #115                // String ]:
     182: invokevirtual #90                 // Method java/lang/StringBuilder.append:(Ljava/lang/String;)Ljava/lang/StringBuilder;
     185: aload         5
     187: invokevirtual #90                 // Method java/lang/StringBuilder.append:(Ljava/lang/String;)Ljava/lang/StringBuilder;
     190: invokevirtual #92                 // Method java/lang/StringBuilder.toString:()Ljava/lang/String;
     193: invokespecial #62                 // Method java/lang/IllegalArgumentException."<init>":(Ljava/lang/String;)V
     196: athrow
     197: aload         6
     199: invokestatic  #116                // Method org/springframework/beans/BeanUtils.instantiateClass:(Ljava/lang/Class;)Ljava/lang/Object;
     202: checkcast     #111                // class org/springframework/core/type/filter/TypeFilter
     205: areturn
     206: new           #60                 // class java/lang/IllegalArgumentException
     209: dup
     210: new           #87                 // class java/lang/StringBuilder
     213: dup
     214: invokespecial #88                 // Method java/lang/StringBuilder."<init>":()V
     217: ldc           #117                // String Unsupported filter type:
     219: invokevirtual #90                 // Method java/lang/StringBuilder.append:(Ljava/lang/String;)Ljava/lang/StringBuilder;
     222: aload         4
     224: invokevirtual #90                 // Method java/lang/StringBuilder.append:(Ljava/lang/String;)Ljava/lang/StringBuilder;
     227: invokevirtual #92                 // Method java/lang/StringBuilder.toString:()Ljava/lang/String;
     230: invokespecial #62                 // Method java/lang/IllegalArgumentException."<init>":(Ljava/lang/String;)V
     233: athrow

  private java.lang.Object instantiateUserDefinedStrategy(java.lang.String, java.lang.Class<?>, java.lang.ClassLoader);
    Code:
       0: aload_3
       1: aload_1
       2: invokevirtual #118                // Method java/lang/ClassLoader.loadClass:(Ljava/lang/String;)Ljava/lang/Class;
       5: invokevirtual #119                // Method java/lang/Class.newInstance:()Ljava/lang/Object;
       8: astore        4
      10: goto          109
      13: astore        5
      15: new           #60                 // class java/lang/IllegalArgumentException
      18: dup
      19: new           #87                 // class java/lang/StringBuilder
      22: dup
      23: invokespecial #88                 // Method java/lang/StringBuilder."<init>":()V
      26: ldc           #120                // String Class [
      28: invokevirtual #90                 // Method java/lang/StringBuilder.append:(Ljava/lang/String;)Ljava/lang/StringBuilder;
      31: aload_1
      32: invokevirtual #90                 // Method java/lang/StringBuilder.append:(Ljava/lang/String;)Ljava/lang/StringBuilder;
      35: ldc           #121                // String ] for strategy [
      37: invokevirtual #90                 // Method java/lang/StringBuilder.append:(Ljava/lang/String;)Ljava/lang/StringBuilder;
      40: aload_2
      41: invokevirtual #114                // Method java/lang/Class.getName:()Ljava/lang/String;
      44: invokevirtual #90                 // Method java/lang/StringBuilder.append:(Ljava/lang/String;)Ljava/lang/StringBuilder;
      47: ldc           #122                // String ] not found
      49: invokevirtual #90                 // Method java/lang/StringBuilder.append:(Ljava/lang/String;)Ljava/lang/StringBuilder;
      52: invokevirtual #92                 // Method java/lang/StringBuilder.toString:()Ljava/lang/String;
      55: aload         5
      57: invokespecial #123                // Method java/lang/IllegalArgumentException."<init>":(Ljava/lang/String;Ljava/lang/Throwable;)V
      60: athrow
      61: astore        5
      63: new           #60                 // class java/lang/IllegalArgumentException
      66: dup
      67: new           #87                 // class java/lang/StringBuilder
      70: dup
      71: invokespecial #88                 // Method java/lang/StringBuilder."<init>":()V
      74: ldc           #125                // String Unable to instantiate class [
      76: invokevirtual #90                 // Method java/lang/StringBuilder.append:(Ljava/lang/String;)Ljava/lang/StringBuilder;
      79: aload_1
      80: invokevirtual #90                 // Method java/lang/StringBuilder.append:(Ljava/lang/String;)Ljava/lang/StringBuilder;
      83: ldc           #121                // String ] for strategy [
      85: invokevirtual #90                 // Method java/lang/StringBuilder.append:(Ljava/lang/String;)Ljava/lang/StringBuilder;
      88: aload_2
      89: invokevirtual #114                // Method java/lang/Class.getName:()Ljava/lang/String;
      92: invokevirtual #90                 // Method java/lang/StringBuilder.append:(Ljava/lang/String;)Ljava/lang/StringBuilder;
      95: ldc           #126                // String ]: a zero-argument constructor is required
      97: invokevirtual #90                 // Method java/lang/StringBuilder.append:(Ljava/lang/String;)Ljava/lang/StringBuilder;
     100: invokevirtual #92                 // Method java/lang/StringBuilder.toString:()Ljava/lang/String;
     103: aload         5
     105: invokespecial #123                // Method java/lang/IllegalArgumentException."<init>":(Ljava/lang/String;Ljava/lang/Throwable;)V
     108: athrow
     109: aload_2
     110: aload         4
     112: invokevirtual #127                // Method java/lang/Object.getClass:()Ljava/lang/Class;
     115: invokevirtual #112                // Method java/lang/Class.isAssignableFrom:(Ljava/lang/Class;)Z
     118: ifne          148
     121: new           #60                 // class java/lang/IllegalArgumentException
     124: dup
     125: new           #87                 // class java/lang/StringBuilder
     128: dup
     129: invokespecial #88                 // Method java/lang/StringBuilder."<init>":()V
     132: ldc           #128                // String Provided class name must be an implementation of
     134: invokevirtual #90                 // Method java/lang/StringBuilder.append:(Ljava/lang/String;)Ljava/lang/StringBuilder;
     137: aload_2
     138: invokevirtual #91                 // Method java/lang/StringBuilder.append:(Ljava/lang/Object;)Ljava/lang/StringBuilder;
     141: invokevirtual #92                 // Method java/lang/StringBuilder.toString:()Ljava/lang/String;
     144: invokespecial #62                 // Method java/lang/IllegalArgumentException."<init>":(Ljava/lang/String;)V
     147: athrow
     148: aload         4
     150: areturn
    Exception table:
       from    to  target type
           0    10    13   Class java/lang/ClassNotFoundException
           0    10    61   Class java/lang/Throwable
}
