Compiled from "ConfigurationClassParser.java"
final class org.springframework.context.annotation.ConfigurationClassParser$1 implements java.util.Comparator<org.springframework.context.annotation.ConfigurationClassParser$DeferredImportSelectorHolder> {
  org.springframework.context.annotation.ConfigurationClassParser$1();
    Code:
       0: aload_0
       1: invokespecial #1                  // Method java/lang/Object."<init>":()V
       4: return

  public int compare(org.springframework.context.annotation.ConfigurationClassParser$DeferredImportSelectorHolder, org.springframework.context.annotation.ConfigurationClassParser$DeferredImportSelectorHolder);
    Code:
       0: getstatic     #2                  // Field org/springframework/core/annotation/AnnotationAwareOrderComparator.INSTANCE:Lorg/springframework/core/annotation/AnnotationAwareOrderComparator;
       3: aload_1
       4: invokevirtual #3                  // Method org/springframework/context/annotation/ConfigurationClassParser$DeferredImportSelectorHolder.getImportSelector:()Lorg/springframework/context/annotation/DeferredImportSelector;
       7: aload_2
       8: invokevirtual #3                  // Method org/springframework/context/annotation/ConfigurationClassParser$DeferredImportSelectorHolder.getImportSelector:()Lorg/springframework/context/annotation/DeferredImportSelector;
      11: invokevirtual #4                  // Method org/springframework/core/annotation/AnnotationAwareOrderComparator.compare:(Ljava/lang/Object;Ljava/lang/Object;)I
      14: ireturn

  public int compare(java.lang.Object, java.lang.Object);
    Code:
       0: aload_0
       1: aload_1
       2: checkcast     #5                  // class org/springframework/context/annotation/ConfigurationClassParser$DeferredImportSelectorHolder
       5: aload_2
       6: checkcast     #5                  // class org/springframework/context/annotation/ConfigurationClassParser$DeferredImportSelectorHolder
       9: invokevirtual #6                  // Method compare:(Lorg/springframework/context/annotation/ConfigurationClassParser$DeferredImportSelectorHolder;Lorg/springframework/context/annotation/ConfigurationClassParser$DeferredImportSelectorHolder;)I
      12: ireturn
}
