Compiled from "UDPChangeSet.java"
public class com.cloudera.nav.sdk.model.entities.UDPChangeSet {
  private java.util.Map<java.lang.String, java.lang.String> newProperties;

  private java.util.Set<java.lang.String> removeProperties;

  private java.util.Map<java.lang.String, java.lang.String> overrideProperties;

  public com.cloudera.nav.sdk.model.entities.UDPChangeSet();
    Code:
       0: aload_0
       1: invokespecial #1                  // Method java/lang/Object."<init>":()V
       4: aload_0
       5: invokestatic  #2                  // Method com/google/common/collect/Maps.newHashMap:()Ljava/util/HashMap;
       8: putfield      #3                  // Field newProperties:Ljava/util/Map;
      11: aload_0
      12: invokestatic  #4                  // Method com/google/common/collect/Sets.newHashSet:()Ljava/util/HashSet;
      15: putfield      #5                  // Field removeProperties:Ljava/util/Set;
      18: aload_0
      19: aconst_null
      20: putfield      #6                  // Field overrideProperties:Ljava/util/Map;
      23: return

  public void reset();
    Code:
       0: aload_0
       1: getfield      #3                  // Field newProperties:Ljava/util/Map;
       4: invokeinterface #7,  1            // InterfaceMethod java/util/Map.clear:()V
       9: aload_0
      10: getfield      #5                  // Field removeProperties:Ljava/util/Set;
      13: invokeinterface #8,  1            // InterfaceMethod java/util/Set.clear:()V
      18: aload_0
      19: aconst_null
      20: putfield      #6                  // Field overrideProperties:Ljava/util/Map;
      23: return

  public void addProperties(java.util.Map<java.lang.String, java.lang.String>);
    Code:
       0: aload_1
       1: invokestatic  #9                  // Method org/apache/commons/collections/MapUtils.isNotEmpty:(Ljava/util/Map;)Z
       4: ifeq          60
       7: aload_0
       8: getfield      #3                  // Field newProperties:Ljava/util/Map;
      11: aload_1
      12: invokeinterface #10,  2           // InterfaceMethod java/util/Map.putAll:(Ljava/util/Map;)V
      17: aload_0
      18: getfield      #5                  // Field removeProperties:Ljava/util/Set;
      21: aload_1
      22: invokeinterface #11,  1           // InterfaceMethod java/util/Map.keySet:()Ljava/util/Set;
      27: invokeinterface #12,  2           // InterfaceMethod java/util/Set.removeAll:(Ljava/util/Collection;)Z
      32: pop
      33: aload_0
      34: getfield      #6                  // Field overrideProperties:Ljava/util/Map;
      37: ifnull        60
      40: aload_0
      41: aload_0
      42: getfield      #6                  // Field overrideProperties:Ljava/util/Map;
      45: aload_1
      46: invokestatic  #13                 // Method com/google/common/collect/Maps.difference:(Ljava/util/Map;Ljava/util/Map;)Lcom/google/common/collect/MapDifference;
      49: invokeinterface #14,  1           // InterfaceMethod com/google/common/collect/MapDifference.entriesOnlyOnLeft:()Ljava/util/Map;
      54: invokestatic  #15                 // Method com/google/common/collect/Maps.newHashMap:(Ljava/util/Map;)Ljava/util/HashMap;
      57: putfield      #6                  // Field overrideProperties:Ljava/util/Map;
      60: return

  public void removeProperties(java.util.Collection<java.lang.String>);
    Code:
       0: aload_1
       1: invokestatic  #16                 // Method org/apache/commons/collections/CollectionUtils.isNotEmpty:(Ljava/util/Collection;)Z
       4: ifeq          105
       7: aload_0
       8: getfield      #5                  // Field removeProperties:Ljava/util/Set;
      11: aload_1
      12: invokeinterface #17,  2           // InterfaceMethod java/util/Set.addAll:(Ljava/util/Collection;)Z
      17: pop
      18: aload_1
      19: invokeinterface #18,  1           // InterfaceMethod java/util/Collection.iterator:()Ljava/util/Iterator;
      24: astore_2
      25: aload_2
      26: invokeinterface #19,  1           // InterfaceMethod java/util/Iterator.hasNext:()Z
      31: ifeq          58
      34: aload_2
      35: invokeinterface #20,  1           // InterfaceMethod java/util/Iterator.next:()Ljava/lang/Object;
      40: checkcast     #21                 // class java/lang/String
      43: astore_3
      44: aload_0
      45: getfield      #3                  // Field newProperties:Ljava/util/Map;
      48: aload_3
      49: invokeinterface #22,  2           // InterfaceMethod java/util/Map.remove:(Ljava/lang/Object;)Ljava/lang/Object;
      54: pop
      55: goto          25
      58: aload_0
      59: getfield      #6                  // Field overrideProperties:Ljava/util/Map;
      62: ifnull        105
      65: aload_1
      66: invokeinterface #18,  1           // InterfaceMethod java/util/Collection.iterator:()Ljava/util/Iterator;
      71: astore_2
      72: aload_2
      73: invokeinterface #19,  1           // InterfaceMethod java/util/Iterator.hasNext:()Z
      78: ifeq          105
      81: aload_2
      82: invokeinterface #20,  1           // InterfaceMethod java/util/Iterator.next:()Ljava/lang/Object;
      87: checkcast     #21                 // class java/lang/String
      90: astore_3
      91: aload_0
      92: getfield      #6                  // Field overrideProperties:Ljava/util/Map;
      95: aload_3
      96: invokeinterface #22,  2           // InterfaceMethod java/util/Map.remove:(Ljava/lang/Object;)Ljava/lang/Object;
     101: pop
     102: goto          72
     105: return

  public void setProperties(java.util.Map<java.lang.String, java.lang.String>);
    Code:
       0: aload_1
       1: ifnonnull     12
       4: aload_0
       5: aconst_null
       6: putfield      #6                  // Field overrideProperties:Ljava/util/Map;
       9: goto          56
      12: aload_0
      13: getfield      #5                  // Field removeProperties:Ljava/util/Set;
      16: aload_1
      17: invokeinterface #11,  1           // InterfaceMethod java/util/Map.keySet:()Ljava/util/Set;
      22: invokeinterface #12,  2           // InterfaceMethod java/util/Set.removeAll:(Ljava/util/Collection;)Z
      27: pop
      28: aload_0
      29: aload_0
      30: getfield      #3                  // Field newProperties:Ljava/util/Map;
      33: aload_1
      34: invokestatic  #13                 // Method com/google/common/collect/Maps.difference:(Ljava/util/Map;Ljava/util/Map;)Lcom/google/common/collect/MapDifference;
      37: invokeinterface #14,  1           // InterfaceMethod com/google/common/collect/MapDifference.entriesOnlyOnLeft:()Ljava/util/Map;
      42: invokestatic  #15                 // Method com/google/common/collect/Maps.newHashMap:(Ljava/util/Map;)Ljava/util/HashMap;
      45: putfield      #3                  // Field newProperties:Ljava/util/Map;
      48: aload_0
      49: aload_1
      50: invokestatic  #15                 // Method com/google/common/collect/Maps.newHashMap:(Ljava/util/Map;)Ljava/util/HashMap;
      53: putfield      #6                  // Field overrideProperties:Ljava/util/Map;
      56: return

  public java.util.Map<java.lang.String, java.lang.String> getNewProperties();
    Code:
       0: aload_0
       1: getfield      #3                  // Field newProperties:Ljava/util/Map;
       4: areturn

  public void setNewProperties(java.util.Map<java.lang.String, java.lang.String>);
    Code:
       0: aload_1
       1: ifnonnull     8
       4: invokestatic  #2                  // Method com/google/common/collect/Maps.newHashMap:()Ljava/util/HashMap;
       7: astore_1
       8: aload_0
       9: aload_1
      10: putfield      #3                  // Field newProperties:Ljava/util/Map;
      13: return

  public java.util.Map<java.lang.String, java.lang.String> getOverrideProperties();
    Code:
       0: aload_0
       1: getfield      #6                  // Field overrideProperties:Ljava/util/Map;
       4: areturn

  public void setOverrideProperties(java.util.Map<java.lang.String, java.lang.String>);
    Code:
       0: aload_0
       1: aload_1
       2: putfield      #6                  // Field overrideProperties:Ljava/util/Map;
       5: return

  public boolean hasOverrides();
    Code:
       0: aload_0
       1: getfield      #6                  // Field overrideProperties:Ljava/util/Map;
       4: ifnull        11
       7: iconst_1
       8: goto          12
      11: iconst_0
      12: ireturn

  public java.util.Set<java.lang.String> getRemoveProperties();
    Code:
       0: aload_0
       1: getfield      #5                  // Field removeProperties:Ljava/util/Set;
       4: areturn

  public void setRemoveProperties(java.util.Set<java.lang.String>);
    Code:
       0: aload_1
       1: ifnonnull     8
       4: invokestatic  #4                  // Method com/google/common/collect/Sets.newHashSet:()Ljava/util/HashSet;
       7: astore_1
       8: aload_0
       9: aload_1
      10: putfield      #5                  // Field removeProperties:Ljava/util/Set;
      13: return
}
