Compiled from "OAuth2ClientConfigurerUtils.java"
final class org.springframework.security.config.annotation.web.configurers.oauth2.client.OAuth2ClientConfigurerUtils {
  private org.springframework.security.config.annotation.web.configurers.oauth2.client.OAuth2ClientConfigurerUtils();
    Code:
       0: aload_0
       1: invokespecial #1                  // Method java/lang/Object."<init>":()V
       4: return

  static <B extends org.springframework.security.config.annotation.web.HttpSecurityBuilder<B>> org.springframework.security.oauth2.client.registration.ClientRegistrationRepository getClientRegistrationRepository(B);
    Code:
       0: aload_0
       1: ldc           #2                  // class org/springframework/security/oauth2/client/registration/ClientRegistrationRepository
       3: invokeinterface #3,  2            // InterfaceMethod org/springframework/security/config/annotation/web/HttpSecurityBuilder.getSharedObject:(Ljava/lang/Class;)Ljava/lang/Object;
       8: checkcast     #2                  // class org/springframework/security/oauth2/client/registration/ClientRegistrationRepository
      11: astore_1
      12: aload_1
      13: ifnonnull     30
      16: aload_0
      17: invokestatic  #4                  // Method getClientRegistrationRepositoryBean:(Lorg/springframework/security/config/annotation/web/HttpSecurityBuilder;)Lorg/springframework/security/oauth2/client/registration/ClientRegistrationRepository;
      20: astore_1
      21: aload_0
      22: ldc           #2                  // class org/springframework/security/oauth2/client/registration/ClientRegistrationRepository
      24: aload_1
      25: invokeinterface #5,  3            // InterfaceMethod org/springframework/security/config/annotation/web/HttpSecurityBuilder.setSharedObject:(Ljava/lang/Class;Ljava/lang/Object;)V
      30: aload_1
      31: areturn

  private static <B extends org.springframework.security.config.annotation.web.HttpSecurityBuilder<B>> org.springframework.security.oauth2.client.registration.ClientRegistrationRepository getClientRegistrationRepositoryBean(B);
    Code:
       0: aload_0
       1: ldc           #6                  // class org/springframework/context/ApplicationContext
       3: invokeinterface #3,  2            // InterfaceMethod org/springframework/security/config/annotation/web/HttpSecurityBuilder.getSharedObject:(Ljava/lang/Class;)Ljava/lang/Object;
       8: checkcast     #6                  // class org/springframework/context/ApplicationContext
      11: ldc           #2                  // class org/springframework/security/oauth2/client/registration/ClientRegistrationRepository
      13: invokeinterface #7,  2            // InterfaceMethod org/springframework/context/ApplicationContext.getBean:(Ljava/lang/Class;)Ljava/lang/Object;
      18: checkcast     #2                  // class org/springframework/security/oauth2/client/registration/ClientRegistrationRepository
      21: areturn

  static <B extends org.springframework.security.config.annotation.web.HttpSecurityBuilder<B>> org.springframework.security.oauth2.client.web.OAuth2AuthorizedClientRepository getAuthorizedClientRepository(B);
    Code:
       0: aload_0
       1: ldc           #8                  // class org/springframework/security/oauth2/client/web/OAuth2AuthorizedClientRepository
       3: invokeinterface #3,  2            // InterfaceMethod org/springframework/security/config/annotation/web/HttpSecurityBuilder.getSharedObject:(Ljava/lang/Class;)Ljava/lang/Object;
       8: checkcast     #8                  // class org/springframework/security/oauth2/client/web/OAuth2AuthorizedClientRepository
      11: astore_1
      12: aload_1
      13: ifnonnull     46
      16: aload_0
      17: invokestatic  #9                  // Method getAuthorizedClientRepositoryBean:(Lorg/springframework/security/config/annotation/web/HttpSecurityBuilder;)Lorg/springframework/security/oauth2/client/web/OAuth2AuthorizedClientRepository;
      20: astore_1
      21: aload_1
      22: ifnonnull     37
      25: new           #10                 // class org/springframework/security/oauth2/client/web/AuthenticatedPrincipalOAuth2AuthorizedClientRepository
      28: dup
      29: aload_0
      30: invokestatic  #11                 // Method getAuthorizedClientService:(Lorg/springframework/security/config/annotation/web/HttpSecurityBuilder;)Lorg/springframework/security/oauth2/client/OAuth2AuthorizedClientService;
      33: invokespecial #12                 // Method org/springframework/security/oauth2/client/web/AuthenticatedPrincipalOAuth2AuthorizedClientRepository."<init>":(Lorg/springframework/security/oauth2/client/OAuth2AuthorizedClientService;)V
      36: astore_1
      37: aload_0
      38: ldc           #8                  // class org/springframework/security/oauth2/client/web/OAuth2AuthorizedClientRepository
      40: aload_1
      41: invokeinterface #5,  3            // InterfaceMethod org/springframework/security/config/annotation/web/HttpSecurityBuilder.setSharedObject:(Ljava/lang/Class;Ljava/lang/Object;)V
      46: aload_1
      47: areturn

  private static <B extends org.springframework.security.config.annotation.web.HttpSecurityBuilder<B>> org.springframework.security.oauth2.client.web.OAuth2AuthorizedClientRepository getAuthorizedClientRepositoryBean(B);
    Code:
       0: aload_0
       1: ldc           #6                  // class org/springframework/context/ApplicationContext
       3: invokeinterface #3,  2            // InterfaceMethod org/springframework/security/config/annotation/web/HttpSecurityBuilder.getSharedObject:(Ljava/lang/Class;)Ljava/lang/Object;
       8: checkcast     #13                 // class org/springframework/beans/factory/ListableBeanFactory
      11: ldc           #8                  // class org/springframework/security/oauth2/client/web/OAuth2AuthorizedClientRepository
      13: invokestatic  #14                 // Method org/springframework/beans/factory/BeanFactoryUtils.beansOfTypeIncludingAncestors:(Lorg/springframework/beans/factory/ListableBeanFactory;Ljava/lang/Class;)Ljava/util/Map;
      16: astore_1
      17: aload_1
      18: invokeinterface #15,  1           // InterfaceMethod java/util/Map.size:()I
      23: iconst_1
      24: if_icmple     97
      27: new           #16                 // class org/springframework/beans/factory/NoUniqueBeanDefinitionException
      30: dup
      31: ldc           #8                  // class org/springframework/security/oauth2/client/web/OAuth2AuthorizedClientRepository
      33: aload_1
      34: invokeinterface #15,  1           // InterfaceMethod java/util/Map.size:()I
      39: new           #17                 // class java/lang/StringBuilder
      42: dup
      43: invokespecial #18                 // Method java/lang/StringBuilder."<init>":()V
      46: ldc           #19                 // String Expected single matching bean of type \'
      48: invokevirtual #20                 // Method java/lang/StringBuilder.append:(Ljava/lang/String;)Ljava/lang/StringBuilder;
      51: ldc           #8                  // class org/springframework/security/oauth2/client/web/OAuth2AuthorizedClientRepository
      53: invokevirtual #21                 // Method java/lang/Class.getName:()Ljava/lang/String;
      56: invokevirtual #20                 // Method java/lang/StringBuilder.append:(Ljava/lang/String;)Ljava/lang/StringBuilder;
      59: ldc           #22                 // String \' but found
      61: invokevirtual #20                 // Method java/lang/StringBuilder.append:(Ljava/lang/String;)Ljava/lang/StringBuilder;
      64: aload_1
      65: invokeinterface #15,  1           // InterfaceMethod java/util/Map.size:()I
      70: invokevirtual #23                 // Method java/lang/StringBuilder.append:(I)Ljava/lang/StringBuilder;
      73: ldc           #24                 // String :
      75: invokevirtual #20                 // Method java/lang/StringBuilder.append:(Ljava/lang/String;)Ljava/lang/StringBuilder;
      78: aload_1
      79: invokeinterface #25,  1           // InterfaceMethod java/util/Map.keySet:()Ljava/util/Set;
      84: invokestatic  #26                 // Method org/springframework/util/StringUtils.collectionToCommaDelimitedString:(Ljava/util/Collection;)Ljava/lang/String;
      87: invokevirtual #20                 // Method java/lang/StringBuilder.append:(Ljava/lang/String;)Ljava/lang/StringBuilder;
      90: invokevirtual #27                 // Method java/lang/StringBuilder.toString:()Ljava/lang/String;
      93: invokespecial #28                 // Method org/springframework/beans/factory/NoUniqueBeanDefinitionException."<init>":(Ljava/lang/Class;ILjava/lang/String;)V
      96: athrow
      97: aload_1
      98: invokeinterface #29,  1           // InterfaceMethod java/util/Map.isEmpty:()Z
     103: ifne          128
     106: aload_1
     107: invokeinterface #30,  1           // InterfaceMethod java/util/Map.values:()Ljava/util/Collection;
     112: invokeinterface #31,  1           // InterfaceMethod java/util/Collection.iterator:()Ljava/util/Iterator;
     117: invokeinterface #32,  1           // InterfaceMethod java/util/Iterator.next:()Ljava/lang/Object;
     122: checkcast     #8                  // class org/springframework/security/oauth2/client/web/OAuth2AuthorizedClientRepository
     125: goto          129
     128: aconst_null
     129: areturn

  private static <B extends org.springframework.security.config.annotation.web.HttpSecurityBuilder<B>> org.springframework.security.oauth2.client.OAuth2AuthorizedClientService getAuthorizedClientService(B);
    Code:
       0: aload_0
       1: invokestatic  #33                 // Method getAuthorizedClientServiceBean:(Lorg/springframework/security/config/annotation/web/HttpSecurityBuilder;)Lorg/springframework/security/oauth2/client/OAuth2AuthorizedClientService;
       4: astore_1
       5: aload_1
       6: ifnonnull     21
       9: new           #34                 // class org/springframework/security/oauth2/client/InMemoryOAuth2AuthorizedClientService
      12: dup
      13: aload_0
      14: invokestatic  #35                 // Method getClientRegistrationRepository:(Lorg/springframework/security/config/annotation/web/HttpSecurityBuilder;)Lorg/springframework/security/oauth2/client/registration/ClientRegistrationRepository;
      17: invokespecial #36                 // Method org/springframework/security/oauth2/client/InMemoryOAuth2AuthorizedClientService."<init>":(Lorg/springframework/security/oauth2/client/registration/ClientRegistrationRepository;)V
      20: astore_1
      21: aload_1
      22: areturn

  private static <B extends org.springframework.security.config.annotation.web.HttpSecurityBuilder<B>> org.springframework.security.oauth2.client.OAuth2AuthorizedClientService getAuthorizedClientServiceBean(B);
    Code:
       0: aload_0
       1: ldc           #6                  // class org/springframework/context/ApplicationContext
       3: invokeinterface #3,  2            // InterfaceMethod org/springframework/security/config/annotation/web/HttpSecurityBuilder.getSharedObject:(Ljava/lang/Class;)Ljava/lang/Object;
       8: checkcast     #13                 // class org/springframework/beans/factory/ListableBeanFactory
      11: ldc           #37                 // class org/springframework/security/oauth2/client/OAuth2AuthorizedClientService
      13: invokestatic  #14                 // Method org/springframework/beans/factory/BeanFactoryUtils.beansOfTypeIncludingAncestors:(Lorg/springframework/beans/factory/ListableBeanFactory;Ljava/lang/Class;)Ljava/util/Map;
      16: astore_1
      17: aload_1
      18: invokeinterface #15,  1           // InterfaceMethod java/util/Map.size:()I
      23: iconst_1
      24: if_icmple     97
      27: new           #16                 // class org/springframework/beans/factory/NoUniqueBeanDefinitionException
      30: dup
      31: ldc           #37                 // class org/springframework/security/oauth2/client/OAuth2AuthorizedClientService
      33: aload_1
      34: invokeinterface #15,  1           // InterfaceMethod java/util/Map.size:()I
      39: new           #17                 // class java/lang/StringBuilder
      42: dup
      43: invokespecial #18                 // Method java/lang/StringBuilder."<init>":()V
      46: ldc           #19                 // String Expected single matching bean of type \'
      48: invokevirtual #20                 // Method java/lang/StringBuilder.append:(Ljava/lang/String;)Ljava/lang/StringBuilder;
      51: ldc           #37                 // class org/springframework/security/oauth2/client/OAuth2AuthorizedClientService
      53: invokevirtual #21                 // Method java/lang/Class.getName:()Ljava/lang/String;
      56: invokevirtual #20                 // Method java/lang/StringBuilder.append:(Ljava/lang/String;)Ljava/lang/StringBuilder;
      59: ldc           #22                 // String \' but found
      61: invokevirtual #20                 // Method java/lang/StringBuilder.append:(Ljava/lang/String;)Ljava/lang/StringBuilder;
      64: aload_1
      65: invokeinterface #15,  1           // InterfaceMethod java/util/Map.size:()I
      70: invokevirtual #23                 // Method java/lang/StringBuilder.append:(I)Ljava/lang/StringBuilder;
      73: ldc           #24                 // String :
      75: invokevirtual #20                 // Method java/lang/StringBuilder.append:(Ljava/lang/String;)Ljava/lang/StringBuilder;
      78: aload_1
      79: invokeinterface #25,  1           // InterfaceMethod java/util/Map.keySet:()Ljava/util/Set;
      84: invokestatic  #26                 // Method org/springframework/util/StringUtils.collectionToCommaDelimitedString:(Ljava/util/Collection;)Ljava/lang/String;
      87: invokevirtual #20                 // Method java/lang/StringBuilder.append:(Ljava/lang/String;)Ljava/lang/StringBuilder;
      90: invokevirtual #27                 // Method java/lang/StringBuilder.toString:()Ljava/lang/String;
      93: invokespecial #28                 // Method org/springframework/beans/factory/NoUniqueBeanDefinitionException."<init>":(Ljava/lang/Class;ILjava/lang/String;)V
      96: athrow
      97: aload_1
      98: invokeinterface #29,  1           // InterfaceMethod java/util/Map.isEmpty:()Z
     103: ifne          128
     106: aload_1
     107: invokeinterface #30,  1           // InterfaceMethod java/util/Map.values:()Ljava/util/Collection;
     112: invokeinterface #31,  1           // InterfaceMethod java/util/Collection.iterator:()Ljava/util/Iterator;
     117: invokeinterface #32,  1           // InterfaceMethod java/util/Iterator.next:()Ljava/lang/Object;
     122: checkcast     #37                 // class org/springframework/security/oauth2/client/OAuth2AuthorizedClientService
     125: goto          129
     128: aconst_null
     129: areturn
}
