Compiled from "ScopedProxyCreator.java"
class org.springframework.context.annotation.ScopedProxyCreator {
  org.springframework.context.annotation.ScopedProxyCreator();
    Code:
       0: aload_0
       1: invokespecial #1                  // Method java/lang/Object."<init>":()V
       4: return

  public static org.springframework.beans.factory.config.BeanDefinitionHolder createScopedProxy(org.springframework.beans.factory.config.BeanDefinitionHolder, org.springframework.beans.factory.support.BeanDefinitionRegistry, boolean);
    Code:
       0: aload_0
       1: aload_1
       2: iload_2
       3: invokestatic  #2                  // Method org/springframework/aop/scope/ScopedProxyUtils.createScopedProxy:(Lorg/springframework/beans/factory/config/BeanDefinitionHolder;Lorg/springframework/beans/factory/support/BeanDefinitionRegistry;Z)Lorg/springframework/beans/factory/config/BeanDefinitionHolder;
       6: areturn

  public static java.lang.String getTargetBeanName(java.lang.String);
    Code:
       0: aload_0
       1: invokestatic  #3                  // Method org/springframework/aop/scope/ScopedProxyUtils.getTargetBeanName:(Ljava/lang/String;)Ljava/lang/String;
       4: areturn
}
