Compiled from "FileUploadBase.java"
class org.apache.tomcat.util.http.fileupload.FileUploadBase$FileItemIteratorImpl$FileItemStreamImpl$1 extends org.apache.tomcat.util.http.fileupload.util.LimitedInputStream {
  final org.apache.tomcat.util.http.fileupload.FileUploadBase$FileItemIteratorImpl val$this$1;

  final org.apache.tomcat.util.http.fileupload.MultipartStream$ItemInputStream val$itemStream;

  final org.apache.tomcat.util.http.fileupload.FileUploadBase$FileItemIteratorImpl$FileItemStreamImpl this$2;

  org.apache.tomcat.util.http.fileupload.FileUploadBase$FileItemIteratorImpl$FileItemStreamImpl$1(org.apache.tomcat.util.http.fileupload.FileUploadBase$FileItemIteratorImpl$FileItemStreamImpl, java.io.InputStream, long, org.apache.tomcat.util.http.fileupload.FileUploadBase$FileItemIteratorImpl, org.apache.tomcat.util.http.fileupload.MultipartStream$ItemInputStream);
    Code:
       0: aload_0
       1: aload_1
       2: putfield      #1                  // Field this$2:Lorg/apache/tomcat/util/http/fileupload/FileUploadBase$FileItemIteratorImpl$FileItemStreamImpl;
       5: aload_0
       6: aload         5
       8: putfield      #2                  // Field val$this$1:Lorg/apache/tomcat/util/http/fileupload/FileUploadBase$FileItemIteratorImpl;
      11: aload_0
      12: aload         6
      14: putfield      #3                  // Field val$itemStream:Lorg/apache/tomcat/util/http/fileupload/MultipartStream$ItemInputStream;
      17: aload_0
      18: aload_2
      19: lload_3
      20: invokespecial #4                  // Method org/apache/tomcat/util/http/fileupload/util/LimitedInputStream."<init>":(Ljava/io/InputStream;J)V
      23: return

  protected void raiseError(long, long) throws java.io.IOException;
    Code:
       0: aload_0
       1: getfield      #3                  // Field val$itemStream:Lorg/apache/tomcat/util/http/fileupload/MultipartStream$ItemInputStream;
       4: iconst_1
       5: invokevirtual #5                  // Method org/apache/tomcat/util/http/fileupload/MultipartStream$ItemInputStream.close:(Z)V
       8: new           #6                  // class org/apache/tomcat/util/http/fileupload/FileUploadBase$FileSizeLimitExceededException
      11: dup
      12: ldc           #7                  // String The field %s exceeds its maximum permitted size of %s bytes.
      14: iconst_2
      15: anewarray     #8                  // class java/lang/Object
      18: dup
      19: iconst_0
      20: aload_0
      21: getfield      #1                  // Field this$2:Lorg/apache/tomcat/util/http/fileupload/FileUploadBase$FileItemIteratorImpl$FileItemStreamImpl;
      24: invokestatic  #9                  // Method org/apache/tomcat/util/http/fileupload/FileUploadBase$FileItemIteratorImpl$FileItemStreamImpl.access$300:(Lorg/apache/tomcat/util/http/fileupload/FileUploadBase$FileItemIteratorImpl$FileItemStreamImpl;)Ljava/lang/String;
      27: aastore
      28: dup
      29: iconst_1
      30: lload_1
      31: invokestatic  #10                 // Method java/lang/Long.valueOf:(J)Ljava/lang/Long;
      34: aastore
      35: invokestatic  #11                 // Method java/lang/String.format:(Ljava/lang/String;[Ljava/lang/Object;)Ljava/lang/String;
      38: lload_3
      39: lload_1
      40: invokespecial #12                 // Method org/apache/tomcat/util/http/fileupload/FileUploadBase$FileSizeLimitExceededException."<init>":(Ljava/lang/String;JJ)V
      43: astore        5
      45: aload         5
      47: aload_0
      48: getfield      #1                  // Field this$2:Lorg/apache/tomcat/util/http/fileupload/FileUploadBase$FileItemIteratorImpl$FileItemStreamImpl;
      51: invokestatic  #9                  // Method org/apache/tomcat/util/http/fileupload/FileUploadBase$FileItemIteratorImpl$FileItemStreamImpl.access$300:(Lorg/apache/tomcat/util/http/fileupload/FileUploadBase$FileItemIteratorImpl$FileItemStreamImpl;)Ljava/lang/String;
      54: invokevirtual #13                 // Method org/apache/tomcat/util/http/fileupload/FileUploadBase$FileSizeLimitExceededException.setFieldName:(Ljava/lang/String;)V
      57: aload         5
      59: aload_0
      60: getfield      #1                  // Field this$2:Lorg/apache/tomcat/util/http/fileupload/FileUploadBase$FileItemIteratorImpl$FileItemStreamImpl;
      63: invokestatic  #14                 // Method org/apache/tomcat/util/http/fileupload/FileUploadBase$FileItemIteratorImpl$FileItemStreamImpl.access$000:(Lorg/apache/tomcat/util/http/fileupload/FileUploadBase$FileItemIteratorImpl$FileItemStreamImpl;)Ljava/lang/String;
      66: invokevirtual #15                 // Method org/apache/tomcat/util/http/fileupload/FileUploadBase$FileSizeLimitExceededException.setFileName:(Ljava/lang/String;)V
      69: new           #16                 // class org/apache/tomcat/util/http/fileupload/FileUploadBase$FileUploadIOException
      72: dup
      73: aload         5
      75: invokespecial #17                 // Method org/apache/tomcat/util/http/fileupload/FileUploadBase$FileUploadIOException."<init>":(Ljava/lang/Throwable;)V
      78: athrow
}
