Compiled from "InOrderWrapper.java"
public class org.mockito.internal.verification.InOrderWrapper implements org.mockito.verification.VerificationMode {
  private final org.mockito.internal.verification.api.VerificationInOrderMode mode;

  private final org.mockito.internal.InOrderImpl inOrder;

  public org.mockito.internal.verification.InOrderWrapper(org.mockito.internal.verification.api.VerificationInOrderMode, org.mockito.internal.InOrderImpl);
    Code:
       0: aload_0
       1: invokespecial #1                  // Method java/lang/Object."<init>":()V
       4: aload_0
       5: aload_1
       6: putfield      #2                  // Field mode:Lorg/mockito/internal/verification/api/VerificationInOrderMode;
       9: aload_0
      10: aload_2
      11: putfield      #3                  // Field inOrder:Lorg/mockito/internal/InOrderImpl;
      14: return

  public void verify(org.mockito.internal.verification.api.VerificationData);
    Code:
       0: aload_0
       1: getfield      #3                  // Field inOrder:Lorg/mockito/internal/InOrderImpl;
       4: invokevirtual #4                  // Method org/mockito/internal/InOrderImpl.getMocksToBeVerifiedInOrder:()Ljava/util/List;
       7: invokestatic  #5                  // Method org/mockito/internal/invocation/finder/VerifiableInvocationsFinder.find:(Ljava/util/List;)Ljava/util/List;
      10: astore_2
      11: new           #6                  // class org/mockito/internal/verification/api/VerificationDataInOrderImpl
      14: dup
      15: aload_0
      16: getfield      #3                  // Field inOrder:Lorg/mockito/internal/InOrderImpl;
      19: aload_2
      20: aload_1
      21: invokeinterface #7,  1            // InterfaceMethod org/mockito/internal/verification/api/VerificationData.getTarget:()Lorg/mockito/invocation/MatchableInvocation;
      26: invokespecial #8                  // Method org/mockito/internal/verification/api/VerificationDataInOrderImpl."<init>":(Lorg/mockito/internal/verification/api/InOrderContext;Ljava/util/List;Lorg/mockito/invocation/MatchableInvocation;)V
      29: astore_3
      30: aload_0
      31: getfield      #2                  // Field mode:Lorg/mockito/internal/verification/api/VerificationInOrderMode;
      34: aload_3
      35: invokeinterface #9,  2            // InterfaceMethod org/mockito/internal/verification/api/VerificationInOrderMode.verifyInOrder:(Lorg/mockito/internal/verification/api/VerificationDataInOrder;)V
      40: return

  public org.mockito.verification.VerificationMode description(java.lang.String);
    Code:
       0: aload_0
       1: aload_1
       2: invokestatic  #10                 // Method org/mockito/internal/verification/VerificationModeFactory.description:(Lorg/mockito/verification/VerificationMode;Ljava/lang/String;)Lorg/mockito/verification/VerificationMode;
       5: areturn
}
