Compiled from "StateMachineFactory.java"
class org.apache.hadoop.yarn.state.StateMachineFactory$MultipleInternalArc implements org.apache.hadoop.yarn.state.StateMachineFactory$Transition<OPERAND, STATE, EVENTTYPE, EVENT> {
  private java.util.Set<STATE> validPostStates;

  private org.apache.hadoop.yarn.state.MultipleArcTransition<OPERAND, EVENT, STATE> hook;

  final org.apache.hadoop.yarn.state.StateMachineFactory this$0;

  org.apache.hadoop.yarn.state.StateMachineFactory$MultipleInternalArc(java.util.Set<STATE>, org.apache.hadoop.yarn.state.MultipleArcTransition<OPERAND, EVENT, STATE>);
    Code:
       0: aload_0
       1: aload_1
       2: putfield      #2                  // Field this$0:Lorg/apache/hadoop/yarn/state/StateMachineFactory;
       5: aload_0
       6: invokespecial #3                  // Method java/lang/Object."<init>":()V
       9: aload_0
      10: aload_2
      11: putfield      #1                  // Field validPostStates:Ljava/util/Set;
      14: aload_0
      15: aload_3
      16: putfield      #4                  // Field hook:Lorg/apache/hadoop/yarn/state/MultipleArcTransition;
      19: return

  public STATE doTransition(OPERAND, STATE, EVENT, EVENTTYPE) throws org.apache.hadoop.yarn.state.InvalidStateTransitionException;
    Code:
       0: aload_0
       1: getfield      #4                  // Field hook:Lorg/apache/hadoop/yarn/state/MultipleArcTransition;
       4: aload_1
       5: aload_3
       6: invokeinterface #5,  3            // InterfaceMethod org/apache/hadoop/yarn/state/MultipleArcTransition.transition:(Ljava/lang/Object;Ljava/lang/Object;)Ljava/lang/Enum;
      11: astore        5
      13: aload_0
      14: getfield      #1                  // Field validPostStates:Ljava/util/Set;
      17: aload         5
      19: invokeinterface #6,  2            // InterfaceMethod java/util/Set.contains:(Ljava/lang/Object;)Z
      24: ifne          38
      27: new           #7                  // class org/apache/hadoop/yarn/state/InvalidStateTransitionException
      30: dup
      31: aload_2
      32: aload         4
      34: invokespecial #8                  // Method org/apache/hadoop/yarn/state/InvalidStateTransitionException."<init>":(Ljava/lang/Enum;Ljava/lang/Enum;)V
      37: athrow
      38: aload         5
      40: areturn

  static java.util.Set access$700(org.apache.hadoop.yarn.state.StateMachineFactory$MultipleInternalArc);
    Code:
       0: aload_0
       1: getfield      #1                  // Field validPostStates:Ljava/util/Set;
       4: areturn
}
