Compiled from "JodaTimeConverters.java"
class org.springframework.format.datetime.joda.JodaTimeConverters$DateTimeToMutableDateTimeConverter implements org.springframework.core.convert.converter.Converter<org.joda.time.DateTime, org.joda.time.MutableDateTime> {
  private org.springframework.format.datetime.joda.JodaTimeConverters$DateTimeToMutableDateTimeConverter();
    Code:
       0: aload_0
       1: invokespecial #2                  // Method java/lang/Object."<init>":()V
       4: return

  public org.joda.time.MutableDateTime convert(org.joda.time.DateTime);
    Code:
       0: aload_1
       1: invokevirtual #3                  // Method org/joda/time/DateTime.toMutableDateTime:()Lorg/joda/time/MutableDateTime;
       4: areturn

  public java.lang.Object convert(java.lang.Object);
    Code:
       0: aload_0
       1: aload_1
       2: checkcast     #4                  // class org/joda/time/DateTime
       5: invokevirtual #5                  // Method convert:(Lorg/joda/time/DateTime;)Lorg/joda/time/MutableDateTime;
       8: areturn

  org.springframework.format.datetime.joda.JodaTimeConverters$DateTimeToMutableDateTimeConverter(org.springframework.format.datetime.joda.JodaTimeConverters$1);
    Code:
       0: aload_0
       1: invokespecial #1                  // Method "<init>":()V
       4: return
}
