Compiled from "Des3CbcHmacSha1KdDecoder.java"
public class org.jboss.security.negotiation.cipher.Des3CbcHmacSha1KdDecoder extends org.jboss.security.negotiation.cipher.Decoder {
  private static final byte[] ZERO_IV;

  private static final byte[] PARITY_BIT_MASK;

  public org.jboss.security.negotiation.cipher.Des3CbcHmacSha1KdDecoder();
    Code:
       0: aload_0
       1: invokespecial #1                  // Method org/jboss/security/negotiation/cipher/Decoder."<init>":()V
       4: return

  public int blockSize();
    Code:
       0: bipush        8
       2: ireturn

  public int checksumSize();
    Code:
       0: bipush        20
       2: ireturn

  public int confounderSize();
    Code:
       0: aload_0
       1: invokevirtual #2                  // Method blockSize:()I
       4: ireturn

  public int keySize();
    Code:
       0: bipush        24
       2: ireturn

  public byte[] decrypt(byte[], byte[], int) throws org.jboss.security.negotiation.NegotiationException;
    Code:
       0: aload_0
       1: invokevirtual #2                  // Method blockSize:()I
       4: newarray       byte
       6: astore        4
       8: aload_0
       9: aload_1
      10: aload_2
      11: aload         4
      13: iload_3
      14: invokevirtual #3                  // Method decrypt:([B[B[BI)[B
      17: areturn

  public byte[] decrypt(byte[], byte[], byte[], int) throws org.jboss.security.negotiation.NegotiationException;
    Code:
       0: aload_0
       1: aload_2
       2: iload         4
       4: aload_3
       5: aload_1
       6: iconst_0
       7: aload_1
       8: arraylength
       9: invokespecial #4                  // Method decrypt:([BI[B[BII)[B
      12: areturn
      13: astore        5
      15: new           #6                  // class org/jboss/security/negotiation/NegotiationException
      18: dup
      19: aload         5
      21: invokevirtual #7                  // Method java/security/GeneralSecurityException.getMessage:()Ljava/lang/String;
      24: invokespecial #8                  // Method org/jboss/security/negotiation/NegotiationException."<init>":(Ljava/lang/String;)V
      27: astore        6
      29: aload         6
      31: aload         5
      33: invokevirtual #9                  // Method org/jboss/security/negotiation/NegotiationException.initCause:(Ljava/lang/Throwable;)Ljava/lang/Throwable;
      36: pop
      37: aload         6
      39: athrow
    Exception table:
       from    to  target type
           0    12    13   Class java/security/GeneralSecurityException

  private byte[] decrypt(byte[], int, byte[], byte[], int, int) throws java.security.GeneralSecurityException;
    Code:
       0: aconst_null
       1: astore        7
       3: aconst_null
       4: astore        8
       6: iconst_5
       7: newarray       byte
       9: astore        9
      11: aload         9
      13: iconst_0
      14: iload_2
      15: bipush        24
      17: ishr
      18: sipush        255
      21: iand
      22: i2b
      23: bastore
      24: aload         9
      26: iconst_1
      27: iload_2
      28: bipush        16
      30: ishr
      31: sipush        255
      34: iand
      35: i2b
      36: bastore
      37: aload         9
      39: iconst_2
      40: iload_2
      41: bipush        8
      43: ishr
      44: sipush        255
      47: iand
      48: i2b
      49: bastore
      50: aload         9
      52: iconst_3
      53: iload_2
      54: sipush        255
      57: iand
      58: i2b
      59: bastore
      60: aload         9
      62: iconst_4
      63: bipush        -86
      65: bastore
      66: aload_0
      67: aload_1
      68: aload         9
      70: invokevirtual #10                 // Method dk:([B[B)[B
      73: astore        7
      75: aload_0
      76: aload         7
      78: aload_3
      79: iconst_2
      80: invokevirtual #12                 // Method getCipher:([B[BI)Ljavax/crypto/Cipher;
      83: astore        10
      85: aload         10
      87: invokevirtual #13                 // Method javax/crypto/Cipher.getBlockSize:()I
      90: istore        11
      92: aload_0
      93: invokevirtual #14                 // Method checksumSize:()I
      96: istore        12
      98: iload         6
     100: iload         12
     102: isub
     103: istore        13
     105: aload         10
     107: aload         4
     109: iload         5
     111: iload         13
     113: invokevirtual #15                 // Method javax/crypto/Cipher.doFinal:([BII)[B
     116: astore        14
     118: aload         9
     120: iconst_4
     121: bipush        85
     123: bastore
     124: aload_0
     125: aload_1
     126: aload         9
     128: invokevirtual #10                 // Method dk:([B[B)[B
     131: astore        8
     133: aload_0
     134: aload         8
     136: aload         14
     138: invokevirtual #16                 // Method getHmac:([B[B)[B
     141: astore        15
     143: iconst_0
     144: istore        16
     146: aload         15
     148: arraylength
     149: iload         12
     151: if_icmplt     192
     154: iconst_0
     155: istore        17
     157: iload         17
     159: iload         12
     161: if_icmpge     192
     164: aload         15
     166: iload         17
     168: baload
     169: aload         4
     171: iload         13
     173: iload         17
     175: iadd
     176: baload
     177: if_icmpeq     186
     180: iconst_1
     181: istore        16
     183: goto          192
     186: iinc          17, 1
     189: goto          157
     192: iload         16
     194: ifeq          207
     197: new           #5                  // class java/security/GeneralSecurityException
     200: dup
     201: ldc           #17                 // String Checksum failed
     203: invokespecial #18                 // Method java/security/GeneralSecurityException."<init>":(Ljava/lang/String;)V
     206: athrow
     207: aload_3
     208: ifnull        235
     211: aload_3
     212: arraylength
     213: iload         11
     215: if_icmpne     235
     218: aload         4
     220: iload         5
     222: iload         13
     224: iadd
     225: iload         11
     227: isub
     228: aload_3
     229: iconst_0
     230: iload         11
     232: invokestatic  #19                 // Method java/lang/System.arraycopy:(Ljava/lang/Object;ILjava/lang/Object;II)V
     235: aload         14
     237: arraylength
     238: iload         11
     240: isub
     241: newarray       byte
     243: astore        17
     245: aload         14
     247: iload         11
     249: aload         17
     251: iconst_0
     252: aload         17
     254: arraylength
     255: invokestatic  #19                 // Method java/lang/System.arraycopy:(Ljava/lang/Object;ILjava/lang/Object;II)V
     258: aload         17
     260: astore        18
     262: aload         7
     264: ifnull        277
     267: aload         7
     269: iconst_0
     270: aload         7
     272: arraylength
     273: iconst_0
     274: invokestatic  #20                 // Method java/util/Arrays.fill:([BIIB)V
     277: aload         8
     279: ifnull        292
     282: aload         8
     284: iconst_0
     285: aload         8
     287: arraylength
     288: iconst_0
     289: invokestatic  #20                 // Method java/util/Arrays.fill:([BIIB)V
     292: aload         18
     294: areturn
     295: astore        19
     297: aload         7
     299: ifnull        312
     302: aload         7
     304: iconst_0
     305: aload         7
     307: arraylength
     308: iconst_0
     309: invokestatic  #20                 // Method java/util/Arrays.fill:([BIIB)V
     312: aload         8
     314: ifnull        327
     317: aload         8
     319: iconst_0
     320: aload         8
     322: arraylength
     323: iconst_0
     324: invokestatic  #20                 // Method java/util/Arrays.fill:([BIIB)V
     327: aload         19
     329: athrow
    Exception table:
       from    to  target type
           6   262   295   any
         295   297   295   any

  protected javax.crypto.Cipher getCipher(byte[], byte[], int) throws java.security.GeneralSecurityException;
    Code:
       0: ldc           #21                 // String desede
       2: invokestatic  #22                 // Method javax/crypto/SecretKeyFactory.getInstance:(Ljava/lang/String;)Ljavax/crypto/SecretKeyFactory;
       5: astore        4
       7: new           #23                 // class javax/crypto/spec/DESedeKeySpec
      10: dup
      11: aload_1
      12: iconst_0
      13: invokespecial #24                 // Method javax/crypto/spec/DESedeKeySpec."<init>":([BI)V
      16: astore        5
      18: aload         4
      20: aload         5
      22: invokevirtual #25                 // Method javax/crypto/SecretKeyFactory.generateSecret:(Ljava/security/spec/KeySpec;)Ljavax/crypto/SecretKey;
      25: astore        6
      27: aload_2
      28: ifnonnull     35
      31: getstatic     #26                 // Field ZERO_IV:[B
      34: astore_2
      35: ldc           #27                 // String DESede/CBC/NoPadding
      37: invokestatic  #28                 // Method javax/crypto/Cipher.getInstance:(Ljava/lang/String;)Ljavax/crypto/Cipher;
      40: astore        7
      42: new           #29                 // class javax/crypto/spec/IvParameterSpec
      45: dup
      46: aload_2
      47: iconst_0
      48: aload_2
      49: arraylength
      50: invokespecial #30                 // Method javax/crypto/spec/IvParameterSpec."<init>":([BII)V
      53: astore        8
      55: aload         7
      57: iload_3
      58: aload         6
      60: aload         8
      62: invokevirtual #31                 // Method javax/crypto/Cipher.init:(ILjava/security/Key;Ljava/security/spec/AlgorithmParameterSpec;)V
      65: aload         7
      67: areturn

  protected byte[] getHmac(byte[], byte[]) throws java.security.GeneralSecurityException;
    Code:
       0: new           #32                 // class javax/crypto/spec/SecretKeySpec
       3: dup
       4: aload_1
       5: ldc           #33                 // String HmacSHA1
       7: invokespecial #34                 // Method javax/crypto/spec/SecretKeySpec."<init>":([BLjava/lang/String;)V
      10: astore_3
      11: ldc           #33                 // String HmacSHA1
      13: invokestatic  #35                 // Method javax/crypto/Mac.getInstance:(Ljava/lang/String;)Ljavax/crypto/Mac;
      16: astore        4
      18: aload         4
      20: aload_3
      21: invokevirtual #36                 // Method javax/crypto/Mac.init:(Ljava/security/Key;)V
      24: aload         4
      26: aload_2
      27: invokevirtual #37                 // Method javax/crypto/Mac.doFinal:([B)[B
      30: areturn

  protected byte[] randomToKey(byte[]);
    Code:
       0: aload_1
       1: arraylength
       2: bipush        21
       4: if_icmpeq     17
       7: new           #38                 // class java/lang/IllegalArgumentException
      10: dup
      11: ldc           #39                 // String input must be 168 bits
      13: invokespecial #40                 // Method java/lang/IllegalArgumentException."<init>":(Ljava/lang/String;)V
      16: athrow
      17: aload_1
      18: iconst_0
      19: bipush        7
      21: invokestatic  #41                 // Method des3Expand:([BII)[B
      24: invokestatic  #42                 // Method keyCorrection:([B)[B
      27: astore_2
      28: aload_1
      29: bipush        7
      31: bipush        14
      33: invokestatic  #41                 // Method des3Expand:([BII)[B
      36: invokestatic  #42                 // Method keyCorrection:([B)[B
      39: astore_3
      40: aload_1
      41: bipush        14
      43: bipush        21
      45: invokestatic  #41                 // Method des3Expand:([BII)[B
      48: invokestatic  #42                 // Method keyCorrection:([B)[B
      51: astore        4
      53: bipush        24
      55: newarray       byte
      57: astore        5
      59: aload_2
      60: iconst_0
      61: aload         5
      63: iconst_0
      64: bipush        8
      66: invokestatic  #19                 // Method java/lang/System.arraycopy:(Ljava/lang/Object;ILjava/lang/Object;II)V
      69: aload_3
      70: iconst_0
      71: aload         5
      73: bipush        8
      75: bipush        8
      77: invokestatic  #19                 // Method java/lang/System.arraycopy:(Ljava/lang/Object;ILjava/lang/Object;II)V
      80: aload         4
      82: iconst_0
      83: aload         5
      85: bipush        16
      87: bipush        8
      89: invokestatic  #19                 // Method java/lang/System.arraycopy:(Ljava/lang/Object;ILjava/lang/Object;II)V
      92: aload         5
      94: areturn

  byte[] dk(byte[], byte[]) throws java.security.GeneralSecurityException;
    Code:
       0: aload_0
       1: aload_0
       2: aload_1
       3: aload_2
       4: invokespecial #43                 // Method dr:([B[B)[B
       7: invokevirtual #44                 // Method randomToKey:([B)[B
      10: areturn

  private byte[] dr(byte[], byte[]) throws java.security.GeneralSecurityException;
    Code:
       0: aload_0
       1: aload_1
       2: aconst_null
       3: iconst_1
       4: invokevirtual #12                 // Method getCipher:([B[BI)Ljavax/crypto/Cipher;
       7: astore_3
       8: aload_3
       9: invokevirtual #13                 // Method javax/crypto/Cipher.getBlockSize:()I
      12: istore        4
      14: aload_2
      15: arraylength
      16: iload         4
      18: if_icmpeq     31
      21: aload_2
      22: iload         4
      24: bipush        8
      26: imul
      27: invokestatic  #45                 // Method nfold:([BI)[B
      30: astore_2
      31: aload_2
      32: astore        5
      34: aload_0
      35: invokevirtual #46                 // Method getKeySeedLength:()I
      38: iconst_3
      39: ishr
      40: istore        6
      42: iload         6
      44: newarray       byte
      46: astore        7
      48: iconst_0
      49: istore        8
      51: iload         8
      53: iload         6
      55: if_icmpge     116
      58: aload_3
      59: aload         5
      61: invokevirtual #47                 // Method javax/crypto/Cipher.doFinal:([B)[B
      64: astore        10
      66: iload         6
      68: iload         8
      70: isub
      71: aload         10
      73: arraylength
      74: if_icmpgt     85
      77: iload         6
      79: iload         8
      81: isub
      82: goto          88
      85: aload         10
      87: arraylength
      88: istore        9
      90: aload         10
      92: iconst_0
      93: aload         7
      95: iload         8
      97: iload         9
      99: invokestatic  #19                 // Method java/lang/System.arraycopy:(Ljava/lang/Object;ILjava/lang/Object;II)V
     102: iload         8
     104: iload         9
     106: iadd
     107: istore        8
     109: aload         10
     111: astore        5
     113: goto          51
     116: aload         7
     118: areturn

  protected int getKeySeedLength();
    Code:
       0: sipush        168
       3: ireturn

  static byte[] nfold(byte[], int);
    Code:
       0: aload_0
       1: arraylength
       2: istore_2
       3: iload_1
       4: iconst_3
       5: ishr
       6: istore_1
       7: iload_1
       8: istore_3
       9: iload_2
      10: istore        4
      12: iload         4
      14: ifeq          33
      17: iload         4
      19: istore        5
      21: iload_3
      22: iload         4
      24: irem
      25: istore        4
      27: iload         5
      29: istore_3
      30: goto          12
      33: iload_1
      34: iload_2
      35: imul
      36: iload_3
      37: idiv
      38: istore        6
      40: iload_1
      41: newarray       byte
      43: astore        7
      45: aload         7
      47: iconst_0
      48: invokestatic  #48                 // Method java/util/Arrays.fill:([BB)V
      51: iconst_0
      52: istore        8
      54: iload         6
      56: iconst_1
      57: isub
      58: istore        10
      60: iload         10
      62: iflt          199
      65: iload_2
      66: iconst_3
      67: ishl
      68: iconst_1
      69: isub
      70: iload_2
      71: iconst_3
      72: ishl
      73: bipush        13
      75: iadd
      76: iload         10
      78: iload_2
      79: idiv
      80: imul
      81: iadd
      82: iload_2
      83: iload         10
      85: iload_2
      86: irem
      87: isub
      88: iconst_3
      89: ishl
      90: iadd
      91: iload_2
      92: iconst_3
      93: ishl
      94: irem
      95: istore        9
      97: aload_0
      98: iload_2
      99: iconst_1
     100: isub
     101: iload         9
     103: iconst_3
     104: iushr
     105: isub
     106: iload_2
     107: irem
     108: baload
     109: sipush        255
     112: iand
     113: bipush        8
     115: ishl
     116: aload_0
     117: iload_2
     118: iload         9
     120: iconst_3
     121: iushr
     122: isub
     123: iload_2
     124: irem
     125: baload
     126: sipush        255
     129: iand
     130: ior
     131: iload         9
     133: bipush        7
     135: iand
     136: iconst_1
     137: iadd
     138: iushr
     139: sipush        255
     142: iand
     143: istore        11
     145: iload         8
     147: iload         11
     149: iadd
     150: istore        8
     152: aload         7
     154: iload         10
     156: iload_1
     157: irem
     158: baload
     159: sipush        255
     162: iand
     163: istore        12
     165: iload         8
     167: iload         12
     169: iadd
     170: istore        8
     172: aload         7
     174: iload         10
     176: iload_1
     177: irem
     178: iload         8
     180: sipush        255
     183: iand
     184: i2b
     185: bastore
     186: iload         8
     188: bipush        8
     190: iushr
     191: istore        8
     193: iinc          10, -1
     196: goto          60
     199: iload         8
     201: ifeq          253
     204: iload_1
     205: iconst_1
     206: isub
     207: istore        10
     209: iload         10
     211: iflt          253
     214: iload         8
     216: aload         7
     218: iload         10
     220: baload
     221: sipush        255
     224: iand
     225: iadd
     226: istore        8
     228: aload         7
     230: iload         10
     232: iload         8
     234: sipush        255
     237: iand
     238: i2b
     239: bastore
     240: iload         8
     242: bipush        8
     244: iushr
     245: istore        8
     247: iinc          10, -1
     250: goto          209
     253: aload         7
     255: areturn

  private static byte[] des3Expand(byte[], int, int);
    Code:
       0: iload_2
       1: iload_1
       2: isub
       3: bipush        7
       5: if_icmpeq     44
       8: new           #38                 // class java/lang/IllegalArgumentException
      11: dup
      12: new           #49                 // class java/lang/StringBuilder
      15: dup
      16: invokespecial #50                 // Method java/lang/StringBuilder."<init>":()V
      19: ldc           #51                 // String Invalid length of DES Key Value:
      21: invokevirtual #52                 // Method java/lang/StringBuilder.append:(Ljava/lang/String;)Ljava/lang/StringBuilder;
      24: iload_1
      25: invokevirtual #53                 // Method java/lang/StringBuilder.append:(I)Ljava/lang/StringBuilder;
      28: ldc           #54                 // String ,
      30: invokevirtual #52                 // Method java/lang/StringBuilder.append:(Ljava/lang/String;)Ljava/lang/StringBuilder;
      33: iload_2
      34: invokevirtual #53                 // Method java/lang/StringBuilder.append:(I)Ljava/lang/StringBuilder;
      37: invokevirtual #55                 // Method java/lang/StringBuilder.toString:()Ljava/lang/String;
      40: invokespecial #40                 // Method java/lang/IllegalArgumentException."<init>":(Ljava/lang/String;)V
      43: athrow
      44: bipush        8
      46: newarray       byte
      48: astore_3
      49: iconst_0
      50: istore        4
      52: aload_0
      53: iload_1
      54: aload_3
      55: iconst_0
      56: bipush        7
      58: invokestatic  #19                 // Method java/lang/System.arraycopy:(Ljava/lang/Object;ILjava/lang/Object;II)V
      61: iconst_0
      62: istore        5
      64: iload_1
      65: istore        6
      67: iload         6
      69: iload_2
      70: if_icmpge     111
      73: aload_0
      74: iload         6
      76: baload
      77: iconst_1
      78: iand
      79: i2b
      80: istore        7
      82: iload         5
      84: iconst_1
      85: iadd
      86: i2b
      87: istore        5
      89: iload         7
      91: ifeq          105
      94: iload         4
      96: iload         7
      98: iload         5
     100: ishl
     101: ior
     102: i2b
     103: istore        4
     105: iinc          6, 1
     108: goto          67
     111: aload_3
     112: bipush        7
     114: iload         4
     116: bastore
     117: aload_3
     118: invokestatic  #56                 // Method setParityBit:([B)V
     121: aload_3
     122: areturn

  private static void setParityBit(byte[]);
    Code:
       0: iconst_0
       1: istore_1
       2: iload_1
       3: aload_0
       4: arraylength
       5: if_icmpge     81
       8: iconst_0
       9: istore_2
      10: iconst_0
      11: istore_3
      12: iload_3
      13: getstatic     #57                 // Field PARITY_BIT_MASK:[B
      16: arraylength
      17: if_icmpge     46
      20: aload_0
      21: iload_1
      22: baload
      23: getstatic     #57                 // Field PARITY_BIT_MASK:[B
      26: iload_3
      27: baload
      28: iand
      29: getstatic     #57                 // Field PARITY_BIT_MASK:[B
      32: iload_3
      33: baload
      34: if_icmpne     40
      37: iinc          2, 1
      40: iinc          3, 1
      43: goto          12
      46: iload_2
      47: iconst_1
      48: iand
      49: iconst_1
      50: if_icmpne     66
      53: aload_0
      54: iload_1
      55: aload_0
      56: iload_1
      57: baload
      58: bipush        -2
      60: iand
      61: i2b
      62: bastore
      63: goto          75
      66: aload_0
      67: iload_1
      68: aload_0
      69: iload_1
      70: baload
      71: iconst_1
      72: ior
      73: i2b
      74: bastore
      75: iinc          1, 1
      78: goto          2
      81: return

  private static byte[] keyCorrection(byte[]);
    Code:
       0: aload_0
       1: iconst_0
       2: invokestatic  #58                 // Method javax/crypto/spec/DESKeySpec.isWeak:([BI)Z
       5: ifeq          21
       8: aload_0
       9: bipush        7
      11: aload_0
      12: bipush        7
      14: baload
      15: sipush        240
      18: ixor
      19: i2b
      20: bastore
      21: goto          25
      24: astore_1
      25: aload_0
      26: areturn
    Exception table:
       from    to  target type
           0    21    24   Class java/security/InvalidKeyException

  public byte[] decryptedData(byte[]);
    Code:
       0: aload_1
       1: areturn

  static {};
    Code:
       0: bipush        8
       2: newarray       byte
       4: dup
       5: iconst_0
       6: iconst_0
       7: bastore
       8: dup
       9: iconst_1
      10: iconst_0
      11: bastore
      12: dup
      13: iconst_2
      14: iconst_0
      15: bastore
      16: dup
      17: iconst_3
      18: iconst_0
      19: bastore
      20: dup
      21: iconst_4
      22: iconst_0
      23: bastore
      24: dup
      25: iconst_5
      26: iconst_0
      27: bastore
      28: dup
      29: bipush        6
      31: iconst_0
      32: bastore
      33: dup
      34: bipush        7
      36: iconst_0
      37: bastore
      38: putstatic     #26                 // Field ZERO_IV:[B
      41: bipush        7
      43: newarray       byte
      45: dup
      46: iconst_0
      47: bipush        -128
      49: bastore
      50: dup
      51: iconst_1
      52: bipush        64
      54: bastore
      55: dup
      56: iconst_2
      57: bipush        32
      59: bastore
      60: dup
      61: iconst_3
      62: bipush        16
      64: bastore
      65: dup
      66: iconst_4
      67: bipush        8
      69: bastore
      70: dup
      71: iconst_5
      72: iconst_4
      73: bastore
      74: dup
      75: bipush        6
      77: iconst_2
      78: bastore
      79: putstatic     #57                 // Field PARITY_BIT_MASK:[B
      82: return
}
