Compiled from "AbstractActor.scala"
public final class akka.actor.AbstractActor$ {
  public static final akka.actor.AbstractActor$ MODULE$;

  private final akka.actor.Actor$emptyBehavior$ emptyBehavior;

  public static {};
    Code:
       0: new           #2                  // class akka/actor/AbstractActor$
       3: invokespecial #12                 // Method "<init>":()V
       6: return

  public final akka.actor.Actor$emptyBehavior$ emptyBehavior();
    Code:
       0: aload_0
       1: getfield      #17                 // Field emptyBehavior:Lakka/actor/Actor$emptyBehavior$;
       4: areturn

  private akka.actor.AbstractActor$();
    Code:
       0: aload_0
       1: invokespecial #19                 // Method java/lang/Object."<init>":()V
       4: aload_0
       5: putstatic     #21                 // Field MODULE$:Lakka/actor/AbstractActor$;
       8: aload_0
       9: getstatic     #25                 // Field akka/actor/Actor$emptyBehavior$.MODULE$:Lakka/actor/Actor$emptyBehavior$;
      12: putfield      #17                 // Field emptyBehavior:Lakka/actor/Actor$emptyBehavior$;
      15: return
}
