Compiled from "Actor.scala"
public class akka.actor.ActorInitializationException extends akka.AkkaException {
  public static final long serialVersionUID;

  private final akka.actor.ActorRef actor;

  public static java.lang.Throwable apply$default$3();
    Code:
       0: getstatic     #16                 // Field akka/actor/ActorInitializationException$.MODULE$:Lakka/actor/ActorInitializationException$;
       3: invokevirtual #18                 // Method akka/actor/ActorInitializationException$.apply$default$3:()Ljava/lang/Throwable;
       6: areturn

  public static scala.Option<scala.Tuple3<akka.actor.ActorRef, java.lang.String, java.lang.Throwable>> unapply(akka.actor.ActorInitializationException);
    Code:
       0: getstatic     #16                 // Field akka/actor/ActorInitializationException$.MODULE$:Lakka/actor/ActorInitializationException$;
       3: aload_0
       4: invokevirtual #22                 // Method akka/actor/ActorInitializationException$.unapply:(Lakka/actor/ActorInitializationException;)Lscala/Option;
       7: areturn

  public akka.actor.ActorRef getActor();
    Code:
       0: aload_0
       1: getfield      #32                 // Field actor:Lakka/actor/ActorRef;
       4: areturn

  public akka.actor.ActorInitializationException(akka.actor.ActorRef, java.lang.String, java.lang.Throwable);
    Code:
       0: aload_0
       1: aload_1
       2: putfield      #32                 // Field actor:Lakka/actor/ActorRef;
       5: aload_0
       6: getstatic     #16                 // Field akka/actor/ActorInitializationException$.MODULE$:Lakka/actor/ActorInitializationException$;
       9: aload_1
      10: aload_2
      11: invokevirtual #40                 // Method akka/actor/ActorInitializationException$.akka$actor$ActorInitializationException$$enrichedMessage:(Lakka/actor/ActorRef;Ljava/lang/String;)Ljava/lang/String;
      14: aload_3
      15: invokespecial #43                 // Method akka/AkkaException."<init>":(Ljava/lang/String;Ljava/lang/Throwable;)V
      18: return
}
