Compiled from "FSM.scala"
public final class akka.actor.FSM$$anonfun$register$1 extends scala.runtime.AbstractFunction0<scala.Option<scala.concurrent.duration.FiniteDuration>> implements scala.Serializable {
  public static final long serialVersionUID;

  private final akka.actor.FSM $outer;

  private final java.lang.Object name$1;

  public final scala.Option<scala.concurrent.duration.FiniteDuration> apply();
    Code:
       0: aload_0
       1: getfield      #22                 // Field $outer:Lakka/actor/FSM;
       4: invokeinterface #26,  1           // InterfaceMethod akka/actor/FSM.akka$actor$FSM$$stateTimeouts:()Lscala/collection/mutable/Map;
       9: aload_0
      10: getfield      #28                 // Field name$1:Ljava/lang/Object;
      13: invokeinterface #33,  2           // InterfaceMethod scala/collection/mutable/Map.apply:(Ljava/lang/Object;)Ljava/lang/Object;
      18: checkcast     #35                 // class scala/Option
      21: areturn

  public final java.lang.Object apply();
    Code:
       0: aload_0
       1: invokevirtual #40                 // Method apply:()Lscala/Option;
       4: areturn

  public akka.actor.FSM$$anonfun$register$1(akka.actor.FSM$class);
    Code:
       0: aload_1
       1: ifnonnull     6
       4: aconst_null
       5: athrow
       6: aload_0
       7: aload_1
       8: putfield      #22                 // Field $outer:Lakka/actor/FSM;
      11: aload_0
      12: aload_2
      13: putfield      #28                 // Field name$1:Ljava/lang/Object;
      16: aload_0
      17: invokespecial #45                 // Method scala/runtime/AbstractFunction0."<init>":()V
      20: return
}
