Compiled from "Actor.scala"
public abstract class akka.actor.Kill implements akka.actor.AutoReceivedMessage,akka.actor.PossiblyHarmful {
  public static boolean canEqual(java.lang.Object);
    Code:
       0: getstatic     #20                 // Field akka/actor/Kill$.MODULE$:Lakka/actor/Kill$;
       3: aload_0
       4: invokevirtual #22                 // Method akka/actor/Kill$.canEqual:(Ljava/lang/Object;)Z
       7: ireturn

  public static scala.collection.Iterator<java.lang.Object> productIterator();
    Code:
       0: getstatic     #20                 // Field akka/actor/Kill$.MODULE$:Lakka/actor/Kill$;
       3: invokevirtual #26                 // Method akka/actor/Kill$.productIterator:()Lscala/collection/Iterator;
       6: areturn

  public static java.lang.Object productElement(int);
    Code:
       0: getstatic     #20                 // Field akka/actor/Kill$.MODULE$:Lakka/actor/Kill$;
       3: iload_0
       4: invokevirtual #30                 // Method akka/actor/Kill$.productElement:(I)Ljava/lang/Object;
       7: areturn

  public static int productArity();
    Code:
       0: getstatic     #20                 // Field akka/actor/Kill$.MODULE$:Lakka/actor/Kill$;
       3: invokevirtual #34                 // Method akka/actor/Kill$.productArity:()I
       6: ireturn

  public static java.lang.String productPrefix();
    Code:
       0: getstatic     #20                 // Field akka/actor/Kill$.MODULE$:Lakka/actor/Kill$;
       3: invokevirtual #38                 // Method akka/actor/Kill$.productPrefix:()Ljava/lang/String;
       6: areturn

  public static akka.actor.Kill$ getInstance();
    Code:
       0: getstatic     #20                 // Field akka/actor/Kill$.MODULE$:Lakka/actor/Kill$;
       3: invokevirtual #42                 // Method akka/actor/Kill$.getInstance:()Lakka/actor/Kill$;
       6: areturn

  public akka.actor.Kill();
    Code:
       0: aload_0
       1: invokespecial #46                 // Method java/lang/Object."<init>":()V
       4: return
}
