Compiled from "FSM.scala"
public final class akka.actor.LoggingFSM$$anonfun$3 extends scala.runtime.AbstractFunction1<scala.Tuple2<akka.actor.FSM$Event<D>, java.lang.Object>, akka.actor.FSM$LogEntry<S, D>> implements scala.Serializable {
  public static final long serialVersionUID;

  public final akka.actor.FSM$LogEntry<S, D> apply(scala.Tuple2<akka.actor.FSM$Event<D>, java.lang.Object>);
    Code:
       0: new           #21                 // class akka/actor/FSM$LogEntry
       3: dup
       4: aload_1
       5: invokevirtual #27                 // Method scala/Tuple2._2:()Ljava/lang/Object;
       8: aload_1
       9: invokevirtual #30                 // Method scala/Tuple2._1:()Ljava/lang/Object;
      12: checkcast     #32                 // class akka/actor/FSM$Event
      15: invokevirtual #35                 // Method akka/actor/FSM$Event.stateData:()Ljava/lang/Object;
      18: aload_1
      19: invokevirtual #30                 // Method scala/Tuple2._1:()Ljava/lang/Object;
      22: checkcast     #32                 // class akka/actor/FSM$Event
      25: invokevirtual #38                 // Method akka/actor/FSM$Event.event:()Ljava/lang/Object;
      28: invokespecial #42                 // Method akka/actor/FSM$LogEntry."<init>":(Ljava/lang/Object;Ljava/lang/Object;Ljava/lang/Object;)V
      31: areturn

  public final java.lang.Object apply(java.lang.Object);
    Code:
       0: aload_0
       1: aload_1
       2: checkcast     #23                 // class scala/Tuple2
       5: invokevirtual #49                 // Method apply:(Lscala/Tuple2;)Lakka/actor/FSM$LogEntry;
       8: areturn

  public akka.actor.LoggingFSM$$anonfun$3(akka.actor.LoggingFSM<S, D>);
    Code:
       0: aload_0
       1: invokespecial #55                 // Method scala/runtime/AbstractFunction1."<init>":()V
       4: return
}
