Compiled from "ActorRef.scala"
public abstract class akka.actor.MinimalActorRef$class {
  public static akka.actor.InternalActorRef getParent(akka.actor.MinimalActorRef);
    Code:
       0: getstatic     #13                 // Field akka/actor/Nobody$.MODULE$:Lakka/actor/Nobody$;
       3: areturn

  public static akka.actor.InternalActorRef getChild(akka.actor.MinimalActorRef, scala.collection.Iterator);
    Code:
       0: aload_1
       1: new           #19                 // class akka/actor/MinimalActorRef$$anonfun$getChild$1
       4: dup
       5: aload_0
       6: invokespecial #23                 // Method akka/actor/MinimalActorRef$$anonfun$getChild$1."<init>":(Lakka/actor/MinimalActorRef;)V
       9: invokeinterface #29,  2           // InterfaceMethod scala/collection/Iterator.forall:(Lscala/Function1;)Z
      14: ifeq          24
      17: aload_0
      18: checkcast     #31                 // class akka/actor/InternalActorRef
      21: goto          27
      24: getstatic     #13                 // Field akka/actor/Nobody$.MODULE$:Lakka/actor/Nobody$;
      27: areturn

  public static void start(akka.actor.MinimalActorRef);
    Code:
       0: return

  public static void suspend(akka.actor.MinimalActorRef);
    Code:
       0: return

  public static void resume(akka.actor.MinimalActorRef, java.lang.Throwable);
    Code:
       0: return

  public static void stop(akka.actor.MinimalActorRef);
    Code:
       0: return

  public static boolean isTerminated(akka.actor.MinimalActorRef);
    Code:
       0: iconst_0
       1: ireturn

  public static void $bang(akka.actor.MinimalActorRef, java.lang.Object, akka.actor.ActorRef);
    Code:
       0: return

  public static akka.actor.ActorRef $bang$default$2(akka.actor.MinimalActorRef, java.lang.Object);
    Code:
       0: getstatic     #55                 // Field akka/actor/Actor$.MODULE$:Lakka/actor/Actor$;
       3: invokevirtual #59                 // Method akka/actor/Actor$.noSender:()Lakka/actor/ActorRef;
       6: areturn

  public static void sendSystemMessage(akka.actor.MinimalActorRef, akka.dispatch.sysmsg.SystemMessage);
    Code:
       0: return

  public static void restart(akka.actor.MinimalActorRef, java.lang.Throwable);
    Code:
       0: return

  public static java.lang.Object writeReplace(akka.actor.MinimalActorRef) throws java.io.ObjectStreamException;
    Code:
       0: getstatic     #73                 // Field akka/actor/SerializedActorRef$.MODULE$:Lakka/actor/SerializedActorRef$;
       3: aload_0
       4: checkcast     #75                 // class akka/actor/ActorRef
       7: invokevirtual #79                 // Method akka/actor/SerializedActorRef$.apply:(Lakka/actor/ActorRef;)Lakka/actor/SerializedActorRef;
      10: areturn

  public static void $init$(akka.actor.MinimalActorRef);
    Code:
       0: return
}
