Compiled from "Deployer.scala"
public abstract class akka.actor.NoScopeGiven implements akka.actor.Scope {
  public static final long serialVersionUID;

  public static boolean canEqual(java.lang.Object);
    Code:
       0: getstatic     #18                 // Field akka/actor/NoScopeGiven$.MODULE$:Lakka/actor/NoScopeGiven$;
       3: aload_0
       4: invokevirtual #20                 // Method akka/actor/NoScopeGiven$.canEqual:(Ljava/lang/Object;)Z
       7: ireturn

  public static scala.collection.Iterator<java.lang.Object> productIterator();
    Code:
       0: getstatic     #18                 // Field akka/actor/NoScopeGiven$.MODULE$:Lakka/actor/NoScopeGiven$;
       3: invokevirtual #24                 // Method akka/actor/NoScopeGiven$.productIterator:()Lscala/collection/Iterator;
       6: areturn

  public static java.lang.Object productElement(int);
    Code:
       0: getstatic     #18                 // Field akka/actor/NoScopeGiven$.MODULE$:Lakka/actor/NoScopeGiven$;
       3: iload_0
       4: invokevirtual #28                 // Method akka/actor/NoScopeGiven$.productElement:(I)Ljava/lang/Object;
       7: areturn

  public static int productArity();
    Code:
       0: getstatic     #18                 // Field akka/actor/NoScopeGiven$.MODULE$:Lakka/actor/NoScopeGiven$;
       3: invokevirtual #32                 // Method akka/actor/NoScopeGiven$.productArity:()I
       6: ireturn

  public static java.lang.String productPrefix();
    Code:
       0: getstatic     #18                 // Field akka/actor/NoScopeGiven$.MODULE$:Lakka/actor/NoScopeGiven$;
       3: invokevirtual #36                 // Method akka/actor/NoScopeGiven$.productPrefix:()Ljava/lang/String;
       6: areturn

  public static akka.actor.NoScopeGiven$ getInstance();
    Code:
       0: getstatic     #18                 // Field akka/actor/NoScopeGiven$.MODULE$:Lakka/actor/NoScopeGiven$;
       3: invokevirtual #40                 // Method akka/actor/NoScopeGiven$.getInstance:()Lakka/actor/NoScopeGiven$;
       6: areturn

  public akka.actor.NoScopeGiven();
    Code:
       0: aload_0
       1: invokespecial #48                 // Method java/lang/Object."<init>":()V
       4: return
}
