Compiled from "Actor.scala"
public final class akka.actor.PreRestartException extends akka.actor.ActorInitializationException implements scala.Product {
  public static final long serialVersionUID;

  private final akka.actor.ActorRef actor;

  private final java.lang.Throwable cause;

  private final java.lang.Throwable originalCause;

  private final scala.Option<java.lang.Object> messageOption;

  public static scala.Option<scala.Tuple4<akka.actor.ActorRef, java.lang.Throwable, java.lang.Throwable, scala.Option<java.lang.Object>>> unapply(akka.actor.PreRestartException);
    Code:
       0: getstatic     #18                 // Field akka/actor/PreRestartException$.MODULE$:Lakka/actor/PreRestartException$;
       3: aload_0
       4: invokevirtual #20                 // Method akka/actor/PreRestartException$.unapply:(Lakka/actor/PreRestartException;)Lscala/Option;
       7: areturn

  public static akka.actor.PreRestartException apply(akka.actor.ActorRef, java.lang.Throwable, java.lang.Throwable, scala.Option<java.lang.Object>);
    Code:
       0: getstatic     #18                 // Field akka/actor/PreRestartException$.MODULE$:Lakka/actor/PreRestartException$;
       3: aload_0
       4: aload_1
       5: aload_2
       6: aload_3
       7: invokevirtual #24                 // Method akka/actor/PreRestartException$.apply:(Lakka/actor/ActorRef;Ljava/lang/Throwable;Ljava/lang/Throwable;Lscala/Option;)Lakka/actor/PreRestartException;
      10: areturn

  public static scala.Function1<scala.Tuple4<akka.actor.ActorRef, java.lang.Throwable, java.lang.Throwable, scala.Option<java.lang.Object>>, akka.actor.PreRestartException> tupled();
    Code:
       0: getstatic     #18                 // Field akka/actor/PreRestartException$.MODULE$:Lakka/actor/PreRestartException$;
       3: invokevirtual #28                 // Method akka/actor/PreRestartException$.tupled:()Lscala/Function1;
       6: areturn

  public static scala.Function1<akka.actor.ActorRef, scala.Function1<java.lang.Throwable, scala.Function1<java.lang.Throwable, scala.Function1<scala.Option<java.lang.Object>, akka.actor.PreRestartException>>>> curried();
    Code:
       0: getstatic     #18                 // Field akka/actor/PreRestartException$.MODULE$:Lakka/actor/PreRestartException$;
       3: invokevirtual #31                 // Method akka/actor/PreRestartException$.curried:()Lscala/Function1;
       6: areturn

  public akka.actor.ActorRef actor();
    Code:
       0: aload_0
       1: getfield      #46                 // Field actor:Lakka/actor/ActorRef;
       4: areturn

  public java.lang.Throwable cause();
    Code:
       0: aload_0
       1: getfield      #51                 // Field cause:Ljava/lang/Throwable;
       4: areturn

  public java.lang.Throwable originalCause();
    Code:
       0: aload_0
       1: getfield      #53                 // Field originalCause:Ljava/lang/Throwable;
       4: areturn

  public scala.Option<java.lang.Object> messageOption();
    Code:
       0: aload_0
       1: getfield      #56                 // Field messageOption:Lscala/Option;
       4: areturn

  public akka.actor.PreRestartException copy(akka.actor.ActorRef, java.lang.Throwable, java.lang.Throwable, scala.Option<java.lang.Object>);
    Code:
       0: new           #2                  // class akka/actor/PreRestartException
       3: dup
       4: aload_1
       5: aload_2
       6: aload_3
       7: aload         4
       9: invokespecial #61                 // Method "<init>":(Lakka/actor/ActorRef;Ljava/lang/Throwable;Ljava/lang/Throwable;Lscala/Option;)V
      12: areturn

  public akka.actor.ActorRef copy$default$1();
    Code:
       0: aload_0
       1: invokevirtual #64                 // Method actor:()Lakka/actor/ActorRef;
       4: areturn

  public java.lang.Throwable copy$default$2();
    Code:
       0: aload_0
       1: invokevirtual #67                 // Method cause:()Ljava/lang/Throwable;
       4: areturn

  public java.lang.Throwable copy$default$3();
    Code:
       0: aload_0
       1: invokevirtual #70                 // Method originalCause:()Ljava/lang/Throwable;
       4: areturn

  public scala.Option<java.lang.Object> copy$default$4();
    Code:
       0: aload_0
       1: invokevirtual #73                 // Method messageOption:()Lscala/Option;
       4: areturn

  public java.lang.String productPrefix();
    Code:
       0: ldc           #77                 // String PreRestartException
       2: areturn

  public int productArity();
    Code:
       0: iconst_4
       1: ireturn

  public java.lang.Object productElement(int);
    Code:
       0: iload_1
       1: istore_2
       2: iload_2
       3: tableswitch   { // 0 to 3
                     0: 68
                     1: 61
                     2: 54
                     3: 47
               default: 32
          }
      32: new           #83                 // class java/lang/IndexOutOfBoundsException
      35: dup
      36: iload_1
      37: invokestatic  #89                 // Method scala/runtime/BoxesRunTime.boxToInteger:(I)Ljava/lang/Integer;
      40: invokevirtual #94                 // Method java/lang/Object.toString:()Ljava/lang/String;
      43: invokespecial #97                 // Method java/lang/IndexOutOfBoundsException."<init>":(Ljava/lang/String;)V
      46: athrow
      47: aload_0
      48: invokevirtual #73                 // Method messageOption:()Lscala/Option;
      51: goto          72
      54: aload_0
      55: invokevirtual #70                 // Method originalCause:()Ljava/lang/Throwable;
      58: goto          72
      61: aload_0
      62: invokevirtual #67                 // Method cause:()Ljava/lang/Throwable;
      65: goto          72
      68: aload_0
      69: invokevirtual #64                 // Method actor:()Lakka/actor/ActorRef;
      72: areturn

  public scala.collection.Iterator<java.lang.Object> productIterator();
    Code:
       0: getstatic     #106                // Field scala/runtime/ScalaRunTime$.MODULE$:Lscala/runtime/ScalaRunTime$;
       3: aload_0
       4: invokevirtual #110                // Method scala/runtime/ScalaRunTime$.typedProductIterator:(Lscala/Product;)Lscala/collection/Iterator;
       7: areturn

  public boolean canEqual(java.lang.Object);
    Code:
       0: aload_1
       1: instanceof    #2                  // class akka/actor/PreRestartException
       4: ireturn

  public int hashCode();
    Code:
       0: getstatic     #106                // Field scala/runtime/ScalaRunTime$.MODULE$:Lscala/runtime/ScalaRunTime$;
       3: aload_0
       4: invokevirtual #118                // Method scala/runtime/ScalaRunTime$._hashCode:(Lscala/Product;)I
       7: ireturn

  public boolean equals(java.lang.Object);
    Code:
       0: aload_0
       1: aload_1
       2: if_acmpeq     167
       5: aload_1
       6: astore_2
       7: aload_2
       8: instanceof    #2                  // class akka/actor/PreRestartException
      11: ifeq          19
      14: iconst_1
      15: istore_3
      16: goto          21
      19: iconst_0
      20: istore_3
      21: iload_3
      22: ifeq          171
      25: aload_1
      26: checkcast     #2                  // class akka/actor/PreRestartException
      29: astore        4
      31: aload_0
      32: invokevirtual #64                 // Method actor:()Lakka/actor/ActorRef;
      35: aload         4
      37: invokevirtual #64                 // Method actor:()Lakka/actor/ActorRef;
      40: astore        5
      42: dup
      43: ifnonnull     55
      46: pop
      47: aload         5
      49: ifnull        63
      52: goto          163
      55: aload         5
      57: invokevirtual #121                // Method java/lang/Object.equals:(Ljava/lang/Object;)Z
      60: ifeq          163
      63: aload_0
      64: invokevirtual #67                 // Method cause:()Ljava/lang/Throwable;
      67: aload         4
      69: invokevirtual #67                 // Method cause:()Ljava/lang/Throwable;
      72: astore        6
      74: dup
      75: ifnonnull     87
      78: pop
      79: aload         6
      81: ifnull        95
      84: goto          163
      87: aload         6
      89: invokevirtual #121                // Method java/lang/Object.equals:(Ljava/lang/Object;)Z
      92: ifeq          163
      95: aload_0
      96: invokevirtual #70                 // Method originalCause:()Ljava/lang/Throwable;
      99: aload         4
     101: invokevirtual #70                 // Method originalCause:()Ljava/lang/Throwable;
     104: astore        7
     106: dup
     107: ifnonnull     119
     110: pop
     111: aload         7
     113: ifnull        127
     116: goto          163
     119: aload         7
     121: invokevirtual #121                // Method java/lang/Object.equals:(Ljava/lang/Object;)Z
     124: ifeq          163
     127: aload_0
     128: invokevirtual #73                 // Method messageOption:()Lscala/Option;
     131: aload         4
     133: invokevirtual #73                 // Method messageOption:()Lscala/Option;
     136: astore        8
     138: dup
     139: ifnonnull     151
     142: pop
     143: aload         8
     145: ifnull        159
     148: goto          163
     151: aload         8
     153: invokevirtual #121                // Method java/lang/Object.equals:(Ljava/lang/Object;)Z
     156: ifeq          163
     159: iconst_1
     160: goto          164
     163: iconst_0
     164: ifeq          171
     167: iconst_1
     168: goto          172
     171: iconst_0
     172: ireturn

  public akka.actor.PreRestartException(akka.actor.ActorRef, java.lang.Throwable, java.lang.Throwable, scala.Option<java.lang.Object>);
    Code:
       0: aload_0
       1: aload_1
       2: putfield      #46                 // Field actor:Lakka/actor/ActorRef;
       5: aload_0
       6: aload_2
       7: putfield      #51                 // Field cause:Ljava/lang/Throwable;
      10: aload_0
      11: aload_3
      12: putfield      #53                 // Field originalCause:Ljava/lang/Throwable;
      15: aload_0
      16: aload         4
      18: putfield      #56                 // Field messageOption:Lscala/Option;
      21: aload_0
      22: aload_1
      23: new           #129                // class scala/collection/mutable/StringBuilder
      26: dup
      27: invokespecial #132                // Method scala/collection/mutable/StringBuilder."<init>":()V
      30: ldc           #134                // String exception in preRestart(
      32: invokevirtual #138                // Method scala/collection/mutable/StringBuilder.append:(Ljava/lang/Object;)Lscala/collection/mutable/StringBuilder;
      35: aload_3
      36: ifnonnull     44
      39: ldc           #140                // String null
      41: goto          48
      44: aload_3
      45: invokevirtual #144                // Method java/lang/Object.getClass:()Ljava/lang/Class;
      48: invokevirtual #138                // Method scala/collection/mutable/StringBuilder.append:(Ljava/lang/Object;)Lscala/collection/mutable/StringBuilder;
      51: ldc           #146                // String ,
      53: invokevirtual #138                // Method scala/collection/mutable/StringBuilder.append:(Ljava/lang/Object;)Lscala/collection/mutable/StringBuilder;
      56: aload         4
      58: astore        5
      60: aload         5
      62: instanceof    #148                // class scala/Some
      65: ifeq          104
      68: aload         5
      70: checkcast     #148                // class scala/Some
      73: astore        6
      75: aload         6
      77: invokevirtual #152                // Method scala/Some.x:()Ljava/lang/Object;
      80: astore        7
      82: aload         7
      84: instanceof    #91                 // class java/lang/Object
      87: ifeq          104
      90: aload         7
      92: astore        8
      94: aload         8
      96: invokevirtual #144                // Method java/lang/Object.getClass:()Ljava/lang/Class;
      99: astore        9
     101: goto          108
     104: ldc           #154                // String None
     106: astore        9
     108: aload         9
     110: invokevirtual #138                // Method scala/collection/mutable/StringBuilder.append:(Ljava/lang/Object;)Lscala/collection/mutable/StringBuilder;
     113: ldc           #156                // String )
     115: invokevirtual #138                // Method scala/collection/mutable/StringBuilder.append:(Ljava/lang/Object;)Lscala/collection/mutable/StringBuilder;
     118: invokevirtual #157                // Method scala/collection/mutable/StringBuilder.toString:()Ljava/lang/String;
     121: aload_2
     122: invokespecial #160                // Method akka/actor/ActorInitializationException."<init>":(Lakka/actor/ActorRef;Ljava/lang/String;Ljava/lang/Throwable;)V
     125: aload_0
     126: invokestatic  #166                // Method scala/Product$class.$init$:(Lscala/Product;)V
     129: return
}
