Compiled from "TypedActor.scala"
public final class akka.actor.TypedActor$SerializedMethodCall$$anonfun$readResolve$1 extends scala.runtime.AbstractFunction1$mcVI$sp implements scala.Serializable {
  public static final long serialVersionUID;

  private final akka.serialization.Serialization serialization$2;

  private final java.lang.Object[] deserializedParameters$1;

  private final scala.Tuple3[] x1$2;

  public final void apply(int);
    Code:
       0: aload_0
       1: iload_1
       2: invokevirtual #27                 // Method apply$mcVI$sp:(I)V
       5: return

  public void apply$mcVI$sp(int);
    Code:
       0: aload_0
       1: getfield      #33                 // Field x1$2:[Lscala/Tuple3;
       4: iload_1
       5: aaload
       6: astore_3
       7: aload_3
       8: ifnull        128
      11: aload_3
      12: invokevirtual #38                 // Method scala/Tuple3._1:()Ljava/lang/Object;
      15: invokestatic  #44                 // Method scala/runtime/BoxesRunTime.unboxToInt:(Ljava/lang/Object;)I
      18: istore        4
      20: aload_3
      21: invokevirtual #47                 // Method scala/Tuple3._2:()Ljava/lang/Object;
      24: checkcast     #49                 // class java/lang/Class
      27: astore        5
      29: aload_3
      30: invokevirtual #52                 // Method scala/Tuple3._3:()Ljava/lang/Object;
      33: checkcast     #54                 // class "[B"
      36: astore        6
      38: new           #35                 // class scala/Tuple3
      41: dup
      42: iload         4
      44: invokestatic  #58                 // Method scala/runtime/BoxesRunTime.boxToInteger:(I)Ljava/lang/Integer;
      47: aload         5
      49: aload         6
      51: invokespecial #62                 // Method scala/Tuple3."<init>":(Ljava/lang/Object;Ljava/lang/Object;Ljava/lang/Object;)V
      54: astore        7
      56: aload         7
      58: astore_2
      59: aload_2
      60: invokevirtual #38                 // Method scala/Tuple3._1:()Ljava/lang/Object;
      63: invokestatic  #44                 // Method scala/runtime/BoxesRunTime.unboxToInt:(Ljava/lang/Object;)I
      66: istore        8
      68: aload_2
      69: invokevirtual #47                 // Method scala/Tuple3._2:()Ljava/lang/Object;
      72: checkcast     #49                 // class java/lang/Class
      75: astore        9
      77: aload_2
      78: invokevirtual #52                 // Method scala/Tuple3._3:()Ljava/lang/Object;
      81: checkcast     #54                 // class "[B"
      84: astore        10
      86: aload_0
      87: getfield      #64                 // Field deserializedParameters$1:[Ljava/lang/Object;
      90: iload_1
      91: aload_0
      92: getfield      #66                 // Field serialization$2:Lakka/serialization/Serialization;
      95: invokevirtual #72                 // Method akka/serialization/Serialization.serializerByIdentity:()Lscala/collection/immutable/Map;
      98: iload         8
     100: invokestatic  #58                 // Method scala/runtime/BoxesRunTime.boxToInteger:(I)Ljava/lang/Integer;
     103: invokeinterface #77,  2           // InterfaceMethod scala/collection/immutable/Map.apply:(Ljava/lang/Object;)Ljava/lang/Object;
     108: checkcast     #79                 // class akka/serialization/Serializer
     111: aload         10
     113: getstatic     #85                 // Field scala/Option$.MODULE$:Lscala/Option$;
     116: aload         9
     118: invokevirtual #88                 // Method scala/Option$.apply:(Ljava/lang/Object;)Lscala/Option;
     121: invokeinterface #92,  3           // InterfaceMethod akka/serialization/Serializer.fromBinary:([BLscala/Option;)Ljava/lang/Object;
     126: aastore
     127: return
     128: new           #94                 // class scala/MatchError
     131: dup
     132: aload_3
     133: invokespecial #97                 // Method scala/MatchError."<init>":(Ljava/lang/Object;)V
     136: athrow

  public final java.lang.Object apply(java.lang.Object);
    Code:
       0: aload_0
       1: aload_1
       2: invokestatic  #44                 // Method scala/runtime/BoxesRunTime.unboxToInt:(Ljava/lang/Object;)I
       5: invokevirtual #103                // Method apply:(I)V
       8: getstatic     #109                // Field scala/runtime/BoxedUnit.UNIT:Lscala/runtime/BoxedUnit;
      11: areturn

  public akka.actor.TypedActor$SerializedMethodCall$$anonfun$readResolve$1(akka.actor.TypedActor$SerializedMethodCall, akka.serialization.Serialization, java.lang.Object[], scala.Tuple3[]);
    Code:
       0: aload_0
       1: aload_2
       2: putfield      #66                 // Field serialization$2:Lakka/serialization/Serialization;
       5: aload_0
       6: aload_3
       7: putfield      #64                 // Field deserializedParameters$1:[Ljava/lang/Object;
      10: aload_0
      11: aload         4
      13: putfield      #33                 // Field x1$2:[Lscala/Tuple3;
      16: aload_0
      17: invokespecial #115                // Method scala/runtime/AbstractFunction1$mcVI$sp."<init>":()V
      20: return
}
