Compiled from "TypedActor.scala"
public final class akka.actor.TypedActor$TypedActor$$anonfun$receive$1$$anonfun$applyOrElse$1 extends scala.runtime.AbstractFunction0$mcV$sp implements scala.Serializable {
  public static final long serialVersionUID;

  private final akka.actor.TypedActor$TypedActor$$anonfun$receive$1 $outer;

  private final java.lang.Object x1$3;

  public final void apply();
    Code:
       0: aload_0
       1: invokevirtual #25                 // Method apply$mcV$sp:()V
       4: return

  public void apply$mcV$sp();
    Code:
       0: aload_0
       1: getfield      #29                 // Field $outer:Lakka/actor/TypedActor$TypedActor$$anonfun$receive$1;
       4: invokevirtual #33                 // Method akka/actor/TypedActor$TypedActor$$anonfun$receive$1.akka$actor$TypedActor$TypedActor$$anonfun$$$outer:()Lakka/actor/TypedActor$TypedActor;
       7: invokevirtual #39                 // Method akka/actor/TypedActor$TypedActor.akka$actor$TypedActor$TypedActor$$me:()Ljava/lang/Object;
      10: checkcast     #41                 // class akka/actor/TypedActor$Receiver
      13: aload_0
      14: getfield      #43                 // Field x1$3:Ljava/lang/Object;
      17: aload_0
      18: getfield      #29                 // Field $outer:Lakka/actor/TypedActor$TypedActor$$anonfun$receive$1;
      21: invokevirtual #33                 // Method akka/actor/TypedActor$TypedActor$$anonfun$receive$1.akka$actor$TypedActor$TypedActor$$anonfun$$$outer:()Lakka/actor/TypedActor$TypedActor;
      24: invokevirtual #47                 // Method akka/actor/TypedActor$TypedActor.sender:()Lakka/actor/ActorRef;
      27: invokeinterface #51,  3           // InterfaceMethod akka/actor/TypedActor$Receiver.onReceive:(Ljava/lang/Object;Lakka/actor/ActorRef;)V
      32: return

  public final java.lang.Object apply();
    Code:
       0: aload_0
       1: invokevirtual #53                 // Method apply:()V
       4: getstatic     #59                 // Field scala/runtime/BoxedUnit.UNIT:Lscala/runtime/BoxedUnit;
       7: areturn

  public akka.actor.TypedActor$TypedActor$$anonfun$receive$1$$anonfun$applyOrElse$1(akka.actor.TypedActor$TypedActor<R, T>.$anonfun$receive$1);
    Code:
       0: aload_1
       1: ifnonnull     6
       4: aconst_null
       5: athrow
       6: aload_0
       7: aload_1
       8: putfield      #29                 // Field $outer:Lakka/actor/TypedActor$TypedActor$$anonfun$receive$1;
      11: aload_0
      12: aload_2
      13: putfield      #43                 // Field x1$3:Ljava/lang/Object;
      16: aload_0
      17: invokespecial #63                 // Method scala/runtime/AbstractFunction0$mcV$sp."<init>":()V
      20: return
}
