Compiled from "PathActionLevel.java"
public final class de.tum.in.test.api.PathActionLevel extends java.lang.Enum<de.tum.in.test.api.PathActionLevel> {
  public static final de.tum.in.test.api.PathActionLevel READ;

  public static final de.tum.in.test.api.PathActionLevel READLINK;

  public static final de.tum.in.test.api.PathActionLevel WRITE;

  public static final de.tum.in.test.api.PathActionLevel DELETE;

  public static final de.tum.in.test.api.PathActionLevel EXECUTE;

  private static final de.tum.in.test.api.PathActionLevel[] $VALUES;

  public static de.tum.in.test.api.PathActionLevel[] values();
    Code:
       0: getstatic     #1                  // Field $VALUES:[Lde/tum/in/test/api/PathActionLevel;
       3: invokevirtual #2                  // Method "[Lde/tum/in/test/api/PathActionLevel;".clone:()Ljava/lang/Object;
       6: checkcast     #3                  // class "[Lde/tum/in/test/api/PathActionLevel;"
       9: areturn

  public static de.tum.in.test.api.PathActionLevel valueOf(java.lang.String);
    Code:
       0: ldc           #4                  // class de/tum/in/test/api/PathActionLevel
       2: aload_0
       3: invokestatic  #5                  // Method java/lang/Enum.valueOf:(Ljava/lang/Class;Ljava/lang/String;)Ljava/lang/Enum;
       6: checkcast     #4                  // class de/tum/in/test/api/PathActionLevel
       9: areturn

  private de.tum.in.test.api.PathActionLevel();
    Code:
       0: aload_0
       1: aload_1
       2: iload_2
       3: invokespecial #6                  // Method java/lang/Enum."<init>":(Ljava/lang/String;I)V
       6: return

  public boolean isAboveOrEqual(de.tum.in.test.api.PathActionLevel);
    Code:
       0: aload_0
       1: invokevirtual #7                  // Method ordinal:()I
       4: aload_1
       5: invokevirtual #7                  // Method ordinal:()I
       8: if_icmplt     15
      11: iconst_1
      12: goto          16
      15: iconst_0
      16: ireturn

  public boolean isBelowOrEqual(de.tum.in.test.api.PathActionLevel);
    Code:
       0: aload_0
       1: invokevirtual #7                  // Method ordinal:()I
       4: aload_1
       5: invokevirtual #7                  // Method ordinal:()I
       8: if_icmpgt     15
      11: iconst_1
      12: goto          16
      15: iconst_0
      16: ireturn

  public static de.tum.in.test.api.PathActionLevel getLevelOf(java.lang.String);
    Code:
       0: aload_0
       1: ldc           #8                  // String execute
       3: invokevirtual #9                  // Method java/lang/String.contains:(Ljava/lang/CharSequence;)Z
       6: ifeq          13
       9: getstatic     #10                 // Field EXECUTE:Lde/tum/in/test/api/PathActionLevel;
      12: areturn
      13: aload_0
      14: ldc           #11                 // String delete
      16: invokevirtual #9                  // Method java/lang/String.contains:(Ljava/lang/CharSequence;)Z
      19: ifeq          26
      22: getstatic     #12                 // Field DELETE:Lde/tum/in/test/api/PathActionLevel;
      25: areturn
      26: aload_0
      27: ldc           #13                 // String write
      29: invokevirtual #9                  // Method java/lang/String.contains:(Ljava/lang/CharSequence;)Z
      32: ifeq          39
      35: getstatic     #14                 // Field WRITE:Lde/tum/in/test/api/PathActionLevel;
      38: areturn
      39: aload_0
      40: ldc           #15                 // String readlink
      42: invokevirtual #9                  // Method java/lang/String.contains:(Ljava/lang/CharSequence;)Z
      45: ifeq          52
      48: getstatic     #16                 // Field READLINK:Lde/tum/in/test/api/PathActionLevel;
      51: areturn
      52: getstatic     #17                 // Field READ:Lde/tum/in/test/api/PathActionLevel;
      55: areturn

  static {};
    Code:
       0: new           #4                  // class de/tum/in/test/api/PathActionLevel
       3: dup
       4: ldc           #18                 // String READ
       6: iconst_0
       7: invokespecial #19                 // Method "<init>":(Ljava/lang/String;I)V
      10: putstatic     #17                 // Field READ:Lde/tum/in/test/api/PathActionLevel;
      13: new           #4                  // class de/tum/in/test/api/PathActionLevel
      16: dup
      17: ldc           #20                 // String READLINK
      19: iconst_1
      20: invokespecial #19                 // Method "<init>":(Ljava/lang/String;I)V
      23: putstatic     #16                 // Field READLINK:Lde/tum/in/test/api/PathActionLevel;
      26: new           #4                  // class de/tum/in/test/api/PathActionLevel
      29: dup
      30: ldc           #21                 // String WRITE
      32: iconst_2
      33: invokespecial #19                 // Method "<init>":(Ljava/lang/String;I)V
      36: putstatic     #14                 // Field WRITE:Lde/tum/in/test/api/PathActionLevel;
      39: new           #4                  // class de/tum/in/test/api/PathActionLevel
      42: dup
      43: ldc           #22                 // String DELETE
      45: iconst_3
      46: invokespecial #19                 // Method "<init>":(Ljava/lang/String;I)V
      49: putstatic     #12                 // Field DELETE:Lde/tum/in/test/api/PathActionLevel;
      52: new           #4                  // class de/tum/in/test/api/PathActionLevel
      55: dup
      56: ldc           #23                 // String EXECUTE
      58: iconst_4
      59: invokespecial #19                 // Method "<init>":(Ljava/lang/String;I)V
      62: putstatic     #10                 // Field EXECUTE:Lde/tum/in/test/api/PathActionLevel;
      65: iconst_5
      66: anewarray     #4                  // class de/tum/in/test/api/PathActionLevel
      69: dup
      70: iconst_0
      71: getstatic     #17                 // Field READ:Lde/tum/in/test/api/PathActionLevel;
      74: aastore
      75: dup
      76: iconst_1
      77: getstatic     #16                 // Field READLINK:Lde/tum/in/test/api/PathActionLevel;
      80: aastore
      81: dup
      82: iconst_2
      83: getstatic     #14                 // Field WRITE:Lde/tum/in/test/api/PathActionLevel;
      86: aastore
      87: dup
      88: iconst_3
      89: getstatic     #12                 // Field DELETE:Lde/tum/in/test/api/PathActionLevel;
      92: aastore
      93: dup
      94: iconst_4
      95: getstatic     #10                 // Field EXECUTE:Lde/tum/in/test/api/PathActionLevel;
      98: aastore
      99: putstatic     #1                  // Field $VALUES:[Lde/tum/in/test/api/PathActionLevel;
     102: return
}
