Compiled from "WithIOManager.java"
public final class de.tum.in.test.api.WithIOManager$None implements de.tum.in.test.api.io.IOManager<java.lang.Void> {
  public de.tum.in.test.api.WithIOManager$None();
    Code:
       0: aload_0
       1: invokespecial #1                  // Method java/lang/Object."<init>":()V
       4: return

  public void beforeTestExecution(de.tum.in.test.api.io.AresIOContext);
    Code:
       0: return

  public void afterTestExecution(de.tum.in.test.api.io.AresIOContext);
    Code:
       0: return

  public java.lang.Void getControllerInstance(de.tum.in.test.api.io.AresIOContext);
    Code:
       0: aconst_null
       1: areturn

  public java.lang.Class<java.lang.Void> getControllerClass();
    Code:
       0: aconst_null
       1: areturn

  public java.lang.Object getControllerInstance(de.tum.in.test.api.io.AresIOContext);
    Code:
       0: aload_0
       1: aload_1
       2: invokevirtual #2                  // Method getControllerInstance:(Lde/tum/in/test/api/io/AresIOContext;)Ljava/lang/Void;
       5: areturn
}
