Compiled from "LogFileWebEndpoint.java"
public class org.springframework.boot.actuate.logging.LogFileWebEndpoint {
  private static final org.apache.commons.logging.Log logger;

  private java.io.File externalFile;

  private final org.springframework.boot.logging.LogFile logFile;

  public org.springframework.boot.actuate.logging.LogFileWebEndpoint(org.springframework.boot.logging.LogFile, java.io.File);
    Code:
       0: aload_0
       1: invokespecial #1                  // Method java/lang/Object."<init>":()V
       4: aload_0
       5: aload_2
       6: putfield      #2                  // Field externalFile:Ljava/io/File;
       9: aload_0
      10: aload_1
      11: putfield      #3                  // Field logFile:Lorg/springframework/boot/logging/LogFile;
      14: return

  public org.springframework.core.io.Resource logFile();
    Code:
       0: aload_0
       1: invokespecial #4                  // Method getLogFileResource:()Lorg/springframework/core/io/Resource;
       4: astore_1
       5: aload_1
       6: ifnull        18
       9: aload_1
      10: invokeinterface #5,  1            // InterfaceMethod org/springframework/core/io/Resource.isReadable:()Z
      15: ifne          20
      18: aconst_null
      19: areturn
      20: aload_1
      21: areturn

  private org.springframework.core.io.Resource getLogFileResource();
    Code:
       0: aload_0
       1: getfield      #2                  // Field externalFile:Ljava/io/File;
       4: ifnull        19
       7: new           #6                  // class org/springframework/core/io/FileSystemResource
      10: dup
      11: aload_0
      12: getfield      #2                  // Field externalFile:Ljava/io/File;
      15: invokespecial #7                  // Method org/springframework/core/io/FileSystemResource."<init>":(Ljava/io/File;)V
      18: areturn
      19: aload_0
      20: getfield      #3                  // Field logFile:Lorg/springframework/boot/logging/LogFile;
      23: ifnonnull     38
      26: getstatic     #8                  // Field logger:Lorg/apache/commons/logging/Log;
      29: ldc           #9                  // String Missing \'logging.file\' or \'logging.path\' properties
      31: invokeinterface #10,  2           // InterfaceMethod org/apache/commons/logging/Log.debug:(Ljava/lang/Object;)V
      36: aconst_null
      37: areturn
      38: new           #6                  // class org/springframework/core/io/FileSystemResource
      41: dup
      42: aload_0
      43: getfield      #3                  // Field logFile:Lorg/springframework/boot/logging/LogFile;
      46: invokevirtual #11                 // Method org/springframework/boot/logging/LogFile.toString:()Ljava/lang/String;
      49: invokespecial #12                 // Method org/springframework/core/io/FileSystemResource."<init>":(Ljava/lang/String;)V
      52: areturn

  static {};
    Code:
       0: ldc           #13                 // class org/springframework/boot/actuate/logging/LogFileWebEndpoint
       2: invokestatic  #14                 // Method org/apache/commons/logging/LogFactory.getLog:(Ljava/lang/Class;)Lorg/apache/commons/logging/Log;
       5: putstatic     #8                  // Field logger:Lorg/apache/commons/logging/Log;
       8: return
}
