Compiled from "ExceptionUtils.java"
public class org.flywaydb.core.internal.util.ExceptionUtils {
  private org.flywaydb.core.internal.util.ExceptionUtils();
    Code:
       0: aload_0
       1: invokespecial #1                  // Method java/lang/Object."<init>":()V
       4: return

  public static java.lang.Throwable getRootCause(java.lang.Throwable);
    Code:
       0: aload_0
       1: ifnonnull     6
       4: aconst_null
       5: areturn
       6: aload_0
       7: astore_1
       8: aload_1
       9: invokevirtual #2                  // Method java/lang/Throwable.getCause:()Ljava/lang/Throwable;
      12: dup
      13: astore_2
      14: ifnull        22
      17: aload_2
      18: astore_1
      19: goto          8
      22: aload_1
      23: areturn
}
