Compiled from "AuditApplicationEvent.java"
public class org.springframework.boot.actuate.audit.listener.AuditApplicationEvent extends org.springframework.context.ApplicationEvent {
  private final org.springframework.boot.actuate.audit.AuditEvent auditEvent;

  public org.springframework.boot.actuate.audit.listener.AuditApplicationEvent(java.lang.String, java.lang.String, java.util.Map<java.lang.String, java.lang.Object>);
    Code:
       0: aload_0
       1: new           #1                  // class org/springframework/boot/actuate/audit/AuditEvent
       4: dup
       5: aload_1
       6: aload_2
       7: aload_3
       8: invokespecial #2                  // Method org/springframework/boot/actuate/audit/AuditEvent."<init>":(Ljava/lang/String;Ljava/lang/String;Ljava/util/Map;)V
      11: invokespecial #3                  // Method "<init>":(Lorg/springframework/boot/actuate/audit/AuditEvent;)V
      14: return

  public org.springframework.boot.actuate.audit.listener.AuditApplicationEvent(java.lang.String, java.lang.String, java.lang.String...);
    Code:
       0: aload_0
       1: new           #1                  // class org/springframework/boot/actuate/audit/AuditEvent
       4: dup
       5: aload_1
       6: aload_2
       7: aload_3
       8: invokespecial #4                  // Method org/springframework/boot/actuate/audit/AuditEvent."<init>":(Ljava/lang/String;Ljava/lang/String;[Ljava/lang/String;)V
      11: invokespecial #3                  // Method "<init>":(Lorg/springframework/boot/actuate/audit/AuditEvent;)V
      14: return

  public org.springframework.boot.actuate.audit.listener.AuditApplicationEvent(java.time.Instant, java.lang.String, java.lang.String, java.util.Map<java.lang.String, java.lang.Object>);
    Code:
       0: aload_0
       1: new           #1                  // class org/springframework/boot/actuate/audit/AuditEvent
       4: dup
       5: aload_1
       6: aload_2
       7: aload_3
       8: aload         4
      10: invokespecial #5                  // Method org/springframework/boot/actuate/audit/AuditEvent."<init>":(Ljava/time/Instant;Ljava/lang/String;Ljava/lang/String;Ljava/util/Map;)V
      13: invokespecial #3                  // Method "<init>":(Lorg/springframework/boot/actuate/audit/AuditEvent;)V
      16: return

  public org.springframework.boot.actuate.audit.listener.AuditApplicationEvent(org.springframework.boot.actuate.audit.AuditEvent);
    Code:
       0: aload_0
       1: aload_1
       2: invokespecial #6                  // Method org/springframework/context/ApplicationEvent."<init>":(Ljava/lang/Object;)V
       5: aload_1
       6: ldc           #7                  // String AuditEvent must not be null
       8: invokestatic  #8                  // Method org/springframework/util/Assert.notNull:(Ljava/lang/Object;Ljava/lang/String;)V
      11: aload_0
      12: aload_1
      13: putfield      #9                  // Field auditEvent:Lorg/springframework/boot/actuate/audit/AuditEvent;
      16: return

  public org.springframework.boot.actuate.audit.AuditEvent getAuditEvent();
    Code:
       0: aload_0
       1: getfield      #9                  // Field auditEvent:Lorg/springframework/boot/actuate/audit/AuditEvent;
       4: areturn
}
