Compiled from "IterableUtils.java"
class org.apache.commons.collections4.IterableUtils$7$1 extends org.apache.commons.collections4.iterators.LazyIteratorChain<E> {
  final org.apache.commons.collections4.IterableUtils$7 this$0;

  org.apache.commons.collections4.IterableUtils$7$1(org.apache.commons.collections4.IterableUtils$7);
    Code:
       0: aload_0
       1: aload_1
       2: putfield      #1                  // Field this$0:Lorg/apache/commons/collections4/IterableUtils$7;
       5: aload_0
       6: invokespecial #2                  // Method org/apache/commons/collections4/iterators/LazyIteratorChain."<init>":()V
       9: return

  protected java.util.Iterator<? extends E> nextIterator(int);
    Code:
       0: aload_0
       1: getfield      #1                  // Field this$0:Lorg/apache/commons/collections4/IterableUtils$7;
       4: getfield      #3                  // Field org/apache/commons/collections4/IterableUtils$7.val$iterable:Ljava/lang/Iterable;
       7: invokestatic  #4                  // Method org/apache/commons/collections4/IterableUtils.isEmpty:(Ljava/lang/Iterable;)Z
      10: ifeq          15
      13: aconst_null
      14: areturn
      15: aload_0
      16: getfield      #1                  // Field this$0:Lorg/apache/commons/collections4/IterableUtils$7;
      19: getfield      #3                  // Field org/apache/commons/collections4/IterableUtils$7.val$iterable:Ljava/lang/Iterable;
      22: invokeinterface #5,  1            // InterfaceMethod java/lang/Iterable.iterator:()Ljava/util/Iterator;
      27: areturn
}
