Compiled from "AssetModelPropertyDefinition.java"
final class software.amazon.awssdk.services.iotsitewise.model.AssetModelPropertyDefinition$BuilderImpl implements software.amazon.awssdk.services.iotsitewise.model.AssetModelPropertyDefinition$Builder {
  private java.lang.String name;

  private java.lang.String dataType;

  private java.lang.String dataTypeSpec;

  private java.lang.String unit;

  private software.amazon.awssdk.services.iotsitewise.model.PropertyType type;

  private software.amazon.awssdk.services.iotsitewise.model.AssetModelPropertyDefinition$BuilderImpl();
    Code:
       0: aload_0
       1: invokespecial #8                  // Method java/lang/Object."<init>":()V
       4: return

  private software.amazon.awssdk.services.iotsitewise.model.AssetModelPropertyDefinition$BuilderImpl(software.amazon.awssdk.services.iotsitewise.model.AssetModelPropertyDefinition);
    Code:
       0: aload_0
       1: invokespecial #8                  // Method java/lang/Object."<init>":()V
       4: aload_0
       5: aload_1
       6: invokestatic  #9                  // Method software/amazon/awssdk/services/iotsitewise/model/AssetModelPropertyDefinition.access$700:(Lsoftware/amazon/awssdk/services/iotsitewise/model/AssetModelPropertyDefinition;)Ljava/lang/String;
       9: invokevirtual #10                 // Method name:(Ljava/lang/String;)Lsoftware/amazon/awssdk/services/iotsitewise/model/AssetModelPropertyDefinition$Builder;
      12: pop
      13: aload_0
      14: aload_1
      15: invokestatic  #11                 // Method software/amazon/awssdk/services/iotsitewise/model/AssetModelPropertyDefinition.access$800:(Lsoftware/amazon/awssdk/services/iotsitewise/model/AssetModelPropertyDefinition;)Ljava/lang/String;
      18: invokevirtual #12                 // Method dataType:(Ljava/lang/String;)Lsoftware/amazon/awssdk/services/iotsitewise/model/AssetModelPropertyDefinition$Builder;
      21: pop
      22: aload_0
      23: aload_1
      24: invokestatic  #13                 // Method software/amazon/awssdk/services/iotsitewise/model/AssetModelPropertyDefinition.access$900:(Lsoftware/amazon/awssdk/services/iotsitewise/model/AssetModelPropertyDefinition;)Ljava/lang/String;
      27: invokevirtual #14                 // Method dataTypeSpec:(Ljava/lang/String;)Lsoftware/amazon/awssdk/services/iotsitewise/model/AssetModelPropertyDefinition$Builder;
      30: pop
      31: aload_0
      32: aload_1
      33: invokestatic  #15                 // Method software/amazon/awssdk/services/iotsitewise/model/AssetModelPropertyDefinition.access$1000:(Lsoftware/amazon/awssdk/services/iotsitewise/model/AssetModelPropertyDefinition;)Ljava/lang/String;
      36: invokevirtual #16                 // Method unit:(Ljava/lang/String;)Lsoftware/amazon/awssdk/services/iotsitewise/model/AssetModelPropertyDefinition$Builder;
      39: pop
      40: aload_0
      41: aload_1
      42: invokestatic  #17                 // Method software/amazon/awssdk/services/iotsitewise/model/AssetModelPropertyDefinition.access$1100:(Lsoftware/amazon/awssdk/services/iotsitewise/model/AssetModelPropertyDefinition;)Lsoftware/amazon/awssdk/services/iotsitewise/model/PropertyType;
      45: invokevirtual #18                 // Method type:(Lsoftware/amazon/awssdk/services/iotsitewise/model/PropertyType;)Lsoftware/amazon/awssdk/services/iotsitewise/model/AssetModelPropertyDefinition$Builder;
      48: pop
      49: return

  public final java.lang.String getName();
    Code:
       0: aload_0
       1: getfield      #7                  // Field name:Ljava/lang/String;
       4: areturn

  public final void setName(java.lang.String);
    Code:
       0: aload_0
       1: aload_1
       2: putfield      #7                  // Field name:Ljava/lang/String;
       5: return

  public final software.amazon.awssdk.services.iotsitewise.model.AssetModelPropertyDefinition$Builder name(java.lang.String);
    Code:
       0: aload_0
       1: aload_1
       2: putfield      #7                  // Field name:Ljava/lang/String;
       5: aload_0
       6: areturn

  public final java.lang.String getDataType();
    Code:
       0: aload_0
       1: getfield      #6                  // Field dataType:Ljava/lang/String;
       4: areturn

  public final void setDataType(java.lang.String);
    Code:
       0: aload_0
       1: aload_1
       2: putfield      #6                  // Field dataType:Ljava/lang/String;
       5: return

  public final software.amazon.awssdk.services.iotsitewise.model.AssetModelPropertyDefinition$Builder dataType(java.lang.String);
    Code:
       0: aload_0
       1: aload_1
       2: putfield      #6                  // Field dataType:Ljava/lang/String;
       5: aload_0
       6: areturn

  public final software.amazon.awssdk.services.iotsitewise.model.AssetModelPropertyDefinition$Builder dataType(software.amazon.awssdk.services.iotsitewise.model.PropertyDataType);
    Code:
       0: aload_0
       1: aload_1
       2: ifnonnull     9
       5: aconst_null
       6: goto          13
       9: aload_1
      10: invokevirtual #19                 // Method software/amazon/awssdk/services/iotsitewise/model/PropertyDataType.toString:()Ljava/lang/String;
      13: invokevirtual #12                 // Method dataType:(Ljava/lang/String;)Lsoftware/amazon/awssdk/services/iotsitewise/model/AssetModelPropertyDefinition$Builder;
      16: pop
      17: aload_0
      18: areturn

  public final java.lang.String getDataTypeSpec();
    Code:
       0: aload_0
       1: getfield      #5                  // Field dataTypeSpec:Ljava/lang/String;
       4: areturn

  public final void setDataTypeSpec(java.lang.String);
    Code:
       0: aload_0
       1: aload_1
       2: putfield      #5                  // Field dataTypeSpec:Ljava/lang/String;
       5: return

  public final software.amazon.awssdk.services.iotsitewise.model.AssetModelPropertyDefinition$Builder dataTypeSpec(java.lang.String);
    Code:
       0: aload_0
       1: aload_1
       2: putfield      #5                  // Field dataTypeSpec:Ljava/lang/String;
       5: aload_0
       6: areturn

  public final java.lang.String getUnit();
    Code:
       0: aload_0
       1: getfield      #4                  // Field unit:Ljava/lang/String;
       4: areturn

  public final void setUnit(java.lang.String);
    Code:
       0: aload_0
       1: aload_1
       2: putfield      #4                  // Field unit:Ljava/lang/String;
       5: return

  public final software.amazon.awssdk.services.iotsitewise.model.AssetModelPropertyDefinition$Builder unit(java.lang.String);
    Code:
       0: aload_0
       1: aload_1
       2: putfield      #4                  // Field unit:Ljava/lang/String;
       5: aload_0
       6: areturn

  public final software.amazon.awssdk.services.iotsitewise.model.PropertyType$Builder getType();
    Code:
       0: aload_0
       1: getfield      #3                  // Field type:Lsoftware/amazon/awssdk/services/iotsitewise/model/PropertyType;
       4: ifnull        17
       7: aload_0
       8: getfield      #3                  // Field type:Lsoftware/amazon/awssdk/services/iotsitewise/model/PropertyType;
      11: invokevirtual #20                 // Method software/amazon/awssdk/services/iotsitewise/model/PropertyType.toBuilder:()Lsoftware/amazon/awssdk/services/iotsitewise/model/PropertyType$Builder;
      14: goto          18
      17: aconst_null
      18: areturn

  public final void setType(software.amazon.awssdk.services.iotsitewise.model.PropertyType$BuilderImpl);
    Code:
       0: aload_0
       1: aload_1
       2: ifnull        12
       5: aload_1
       6: invokevirtual #21                 // Method software/amazon/awssdk/services/iotsitewise/model/PropertyType$BuilderImpl.build:()Lsoftware/amazon/awssdk/services/iotsitewise/model/PropertyType;
       9: goto          13
      12: aconst_null
      13: putfield      #3                  // Field type:Lsoftware/amazon/awssdk/services/iotsitewise/model/PropertyType;
      16: return

  public final software.amazon.awssdk.services.iotsitewise.model.AssetModelPropertyDefinition$Builder type(software.amazon.awssdk.services.iotsitewise.model.PropertyType);
    Code:
       0: aload_0
       1: aload_1
       2: putfield      #3                  // Field type:Lsoftware/amazon/awssdk/services/iotsitewise/model/PropertyType;
       5: aload_0
       6: areturn

  public software.amazon.awssdk.services.iotsitewise.model.AssetModelPropertyDefinition build();
    Code:
       0: new           #22                 // class software/amazon/awssdk/services/iotsitewise/model/AssetModelPropertyDefinition
       3: dup
       4: aload_0
       5: aconst_null
       6: invokespecial #23                 // Method software/amazon/awssdk/services/iotsitewise/model/AssetModelPropertyDefinition."<init>":(Lsoftware/amazon/awssdk/services/iotsitewise/model/AssetModelPropertyDefinition$BuilderImpl;Lsoftware/amazon/awssdk/services/iotsitewise/model/AssetModelPropertyDefinition$1;)V
       9: areturn

  public java.util.List<software.amazon.awssdk.core.SdkField<?>> sdkFields();
    Code:
       0: invokestatic  #24                 // Method software/amazon/awssdk/services/iotsitewise/model/AssetModelPropertyDefinition.access$1300:()Ljava/util/List;
       3: areturn

  public java.lang.Object build();
    Code:
       0: aload_0
       1: invokevirtual #25                 // Method build:()Lsoftware/amazon/awssdk/services/iotsitewise/model/AssetModelPropertyDefinition;
       4: areturn

  static java.lang.String access$000(software.amazon.awssdk.services.iotsitewise.model.AssetModelPropertyDefinition$BuilderImpl);
    Code:
       0: aload_0
       1: getfield      #7                  // Field name:Ljava/lang/String;
       4: areturn

  static java.lang.String access$100(software.amazon.awssdk.services.iotsitewise.model.AssetModelPropertyDefinition$BuilderImpl);
    Code:
       0: aload_0
       1: getfield      #6                  // Field dataType:Ljava/lang/String;
       4: areturn

  static java.lang.String access$200(software.amazon.awssdk.services.iotsitewise.model.AssetModelPropertyDefinition$BuilderImpl);
    Code:
       0: aload_0
       1: getfield      #5                  // Field dataTypeSpec:Ljava/lang/String;
       4: areturn

  static java.lang.String access$300(software.amazon.awssdk.services.iotsitewise.model.AssetModelPropertyDefinition$BuilderImpl);
    Code:
       0: aload_0
       1: getfield      #4                  // Field unit:Ljava/lang/String;
       4: areturn

  static software.amazon.awssdk.services.iotsitewise.model.PropertyType access$400(software.amazon.awssdk.services.iotsitewise.model.AssetModelPropertyDefinition$BuilderImpl);
    Code:
       0: aload_0
       1: getfield      #3                  // Field type:Lsoftware/amazon/awssdk/services/iotsitewise/model/PropertyType;
       4: areturn

  software.amazon.awssdk.services.iotsitewise.model.AssetModelPropertyDefinition$BuilderImpl(software.amazon.awssdk.services.iotsitewise.model.AssetModelPropertyDefinition, software.amazon.awssdk.services.iotsitewise.model.AssetModelPropertyDefinition$1);
    Code:
       0: aload_0
       1: aload_1
       2: invokespecial #2                  // Method "<init>":(Lsoftware/amazon/awssdk/services/iotsitewise/model/AssetModelPropertyDefinition;)V
       5: return

  software.amazon.awssdk.services.iotsitewise.model.AssetModelPropertyDefinition$BuilderImpl(software.amazon.awssdk.services.iotsitewise.model.AssetModelPropertyDefinition$1);
    Code:
       0: aload_0
       1: invokespecial #1                  // Method "<init>":()V
       4: return
}
