Compiled from "BatchGetAssetPropertyValueHistorySuccessEntry.java"
final class software.amazon.awssdk.services.iotsitewise.model.BatchGetAssetPropertyValueHistorySuccessEntry$BuilderImpl implements software.amazon.awssdk.services.iotsitewise.model.BatchGetAssetPropertyValueHistorySuccessEntry$Builder {
  private java.lang.String entryId;

  private java.util.List<software.amazon.awssdk.services.iotsitewise.model.AssetPropertyValue> assetPropertyValueHistory;

  private software.amazon.awssdk.services.iotsitewise.model.BatchGetAssetPropertyValueHistorySuccessEntry$BuilderImpl();
    Code:
       0: aload_0
       1: invokespecial #5                  // Method java/lang/Object."<init>":()V
       4: aload_0
       5: invokestatic  #6                  // Method software/amazon/awssdk/core/util/DefaultSdkAutoConstructList.getInstance:()Lsoftware/amazon/awssdk/core/util/DefaultSdkAutoConstructList;
       8: putfield      #3                  // Field assetPropertyValueHistory:Ljava/util/List;
      11: return

  private software.amazon.awssdk.services.iotsitewise.model.BatchGetAssetPropertyValueHistorySuccessEntry$BuilderImpl(software.amazon.awssdk.services.iotsitewise.model.BatchGetAssetPropertyValueHistorySuccessEntry);
    Code:
       0: aload_0
       1: invokespecial #5                  // Method java/lang/Object."<init>":()V
       4: aload_0
       5: invokestatic  #6                  // Method software/amazon/awssdk/core/util/DefaultSdkAutoConstructList.getInstance:()Lsoftware/amazon/awssdk/core/util/DefaultSdkAutoConstructList;
       8: putfield      #3                  // Field assetPropertyValueHistory:Ljava/util/List;
      11: aload_0
      12: aload_1
      13: invokestatic  #7                  // Method software/amazon/awssdk/services/iotsitewise/model/BatchGetAssetPropertyValueHistorySuccessEntry.access$400:(Lsoftware/amazon/awssdk/services/iotsitewise/model/BatchGetAssetPropertyValueHistorySuccessEntry;)Ljava/lang/String;
      16: invokevirtual #8                  // Method entryId:(Ljava/lang/String;)Lsoftware/amazon/awssdk/services/iotsitewise/model/BatchGetAssetPropertyValueHistorySuccessEntry$Builder;
      19: pop
      20: aload_0
      21: aload_1
      22: invokestatic  #9                  // Method software/amazon/awssdk/services/iotsitewise/model/BatchGetAssetPropertyValueHistorySuccessEntry.access$500:(Lsoftware/amazon/awssdk/services/iotsitewise/model/BatchGetAssetPropertyValueHistorySuccessEntry;)Ljava/util/List;
      25: invokevirtual #10                 // Method assetPropertyValueHistory:(Ljava/util/Collection;)Lsoftware/amazon/awssdk/services/iotsitewise/model/BatchGetAssetPropertyValueHistorySuccessEntry$Builder;
      28: pop
      29: return

  public final java.lang.String getEntryId();
    Code:
       0: aload_0
       1: getfield      #4                  // Field entryId:Ljava/lang/String;
       4: areturn

  public final void setEntryId(java.lang.String);
    Code:
       0: aload_0
       1: aload_1
       2: putfield      #4                  // Field entryId:Ljava/lang/String;
       5: return

  public final software.amazon.awssdk.services.iotsitewise.model.BatchGetAssetPropertyValueHistorySuccessEntry$Builder entryId(java.lang.String);
    Code:
       0: aload_0
       1: aload_1
       2: putfield      #4                  // Field entryId:Ljava/lang/String;
       5: aload_0
       6: areturn

  public final java.util.List<software.amazon.awssdk.services.iotsitewise.model.AssetPropertyValue$Builder> getAssetPropertyValueHistory();
    Code:
       0: aload_0
       1: getfield      #3                  // Field assetPropertyValueHistory:Ljava/util/List;
       4: invokestatic  #11                 // Method software/amazon/awssdk/services/iotsitewise/model/AssetPropertyValueHistoryCopier.copyToBuilder:(Ljava/util/Collection;)Ljava/util/List;
       7: astore_1
       8: aload_1
       9: instanceof    #12                 // class software/amazon/awssdk/core/util/SdkAutoConstructList
      12: ifeq          17
      15: aconst_null
      16: areturn
      17: aload_1
      18: areturn

  public final void setAssetPropertyValueHistory(java.util.Collection<software.amazon.awssdk.services.iotsitewise.model.AssetPropertyValue$BuilderImpl>);
    Code:
       0: aload_0
       1: aload_1
       2: invokestatic  #13                 // Method software/amazon/awssdk/services/iotsitewise/model/AssetPropertyValueHistoryCopier.copyFromBuilder:(Ljava/util/Collection;)Ljava/util/List;
       5: putfield      #3                  // Field assetPropertyValueHistory:Ljava/util/List;
       8: return

  public final software.amazon.awssdk.services.iotsitewise.model.BatchGetAssetPropertyValueHistorySuccessEntry$Builder assetPropertyValueHistory(java.util.Collection<software.amazon.awssdk.services.iotsitewise.model.AssetPropertyValue>);
    Code:
       0: aload_0
       1: aload_1
       2: invokestatic  #14                 // Method software/amazon/awssdk/services/iotsitewise/model/AssetPropertyValueHistoryCopier.copy:(Ljava/util/Collection;)Ljava/util/List;
       5: putfield      #3                  // Field assetPropertyValueHistory:Ljava/util/List;
       8: aload_0
       9: areturn

  public final software.amazon.awssdk.services.iotsitewise.model.BatchGetAssetPropertyValueHistorySuccessEntry$Builder assetPropertyValueHistory(software.amazon.awssdk.services.iotsitewise.model.AssetPropertyValue...);
    Code:
       0: aload_0
       1: aload_1
       2: invokestatic  #15                 // Method java/util/Arrays.asList:([Ljava/lang/Object;)Ljava/util/List;
       5: invokevirtual #10                 // Method assetPropertyValueHistory:(Ljava/util/Collection;)Lsoftware/amazon/awssdk/services/iotsitewise/model/BatchGetAssetPropertyValueHistorySuccessEntry$Builder;
       8: pop
       9: aload_0
      10: areturn

  public final software.amazon.awssdk.services.iotsitewise.model.BatchGetAssetPropertyValueHistorySuccessEntry$Builder assetPropertyValueHistory(java.util.function.Consumer<software.amazon.awssdk.services.iotsitewise.model.AssetPropertyValue$Builder>...);
    Code:
       0: aload_0
       1: aload_1
       2: invokestatic  #16                 // InterfaceMethod java/util/stream/Stream.of:([Ljava/lang/Object;)Ljava/util/stream/Stream;
       5: invokedynamic #17,  0             // InvokeDynamic #0:apply:()Ljava/util/function/Function;
      10: invokeinterface #18,  2           // InterfaceMethod java/util/stream/Stream.map:(Ljava/util/function/Function;)Ljava/util/stream/Stream;
      15: invokestatic  #19                 // Method java/util/stream/Collectors.toList:()Ljava/util/stream/Collector;
      18: invokeinterface #20,  2           // InterfaceMethod java/util/stream/Stream.collect:(Ljava/util/stream/Collector;)Ljava/lang/Object;
      23: checkcast     #21                 // class java/util/Collection
      26: invokevirtual #10                 // Method assetPropertyValueHistory:(Ljava/util/Collection;)Lsoftware/amazon/awssdk/services/iotsitewise/model/BatchGetAssetPropertyValueHistorySuccessEntry$Builder;
      29: pop
      30: aload_0
      31: areturn

  public software.amazon.awssdk.services.iotsitewise.model.BatchGetAssetPropertyValueHistorySuccessEntry build();
    Code:
       0: new           #22                 // class software/amazon/awssdk/services/iotsitewise/model/BatchGetAssetPropertyValueHistorySuccessEntry
       3: dup
       4: aload_0
       5: aconst_null
       6: invokespecial #23                 // Method software/amazon/awssdk/services/iotsitewise/model/BatchGetAssetPropertyValueHistorySuccessEntry."<init>":(Lsoftware/amazon/awssdk/services/iotsitewise/model/BatchGetAssetPropertyValueHistorySuccessEntry$BuilderImpl;Lsoftware/amazon/awssdk/services/iotsitewise/model/BatchGetAssetPropertyValueHistorySuccessEntry$1;)V
       9: areturn

  public java.util.List<software.amazon.awssdk.core.SdkField<?>> sdkFields();
    Code:
       0: invokestatic  #24                 // Method software/amazon/awssdk/services/iotsitewise/model/BatchGetAssetPropertyValueHistorySuccessEntry.access$700:()Ljava/util/List;
       3: areturn

  public java.lang.Object build();
    Code:
       0: aload_0
       1: invokevirtual #25                 // Method build:()Lsoftware/amazon/awssdk/services/iotsitewise/model/BatchGetAssetPropertyValueHistorySuccessEntry;
       4: areturn

  private static software.amazon.awssdk.services.iotsitewise.model.AssetPropertyValue lambda$assetPropertyValueHistory$0(java.util.function.Consumer);
    Code:
       0: invokestatic  #26                 // Method software/amazon/awssdk/services/iotsitewise/model/AssetPropertyValue.builder:()Lsoftware/amazon/awssdk/services/iotsitewise/model/AssetPropertyValue$Builder;
       3: aload_0
       4: invokeinterface #27,  2           // InterfaceMethod software/amazon/awssdk/services/iotsitewise/model/AssetPropertyValue$Builder.applyMutation:(Ljava/util/function/Consumer;)Lsoftware/amazon/awssdk/utils/builder/SdkBuilder;
       9: checkcast     #28                 // class software/amazon/awssdk/services/iotsitewise/model/AssetPropertyValue$Builder
      12: invokeinterface #29,  1           // InterfaceMethod software/amazon/awssdk/services/iotsitewise/model/AssetPropertyValue$Builder.build:()Ljava/lang/Object;
      17: checkcast     #30                 // class software/amazon/awssdk/services/iotsitewise/model/AssetPropertyValue
      20: areturn

  static java.lang.String access$000(software.amazon.awssdk.services.iotsitewise.model.BatchGetAssetPropertyValueHistorySuccessEntry$BuilderImpl);
    Code:
       0: aload_0
       1: getfield      #4                  // Field entryId:Ljava/lang/String;
       4: areturn

  static java.util.List access$100(software.amazon.awssdk.services.iotsitewise.model.BatchGetAssetPropertyValueHistorySuccessEntry$BuilderImpl);
    Code:
       0: aload_0
       1: getfield      #3                  // Field assetPropertyValueHistory:Ljava/util/List;
       4: areturn

  software.amazon.awssdk.services.iotsitewise.model.BatchGetAssetPropertyValueHistorySuccessEntry$BuilderImpl(software.amazon.awssdk.services.iotsitewise.model.BatchGetAssetPropertyValueHistorySuccessEntry, software.amazon.awssdk.services.iotsitewise.model.BatchGetAssetPropertyValueHistorySuccessEntry$1);
    Code:
       0: aload_0
       1: aload_1
       2: invokespecial #2                  // Method "<init>":(Lsoftware/amazon/awssdk/services/iotsitewise/model/BatchGetAssetPropertyValueHistorySuccessEntry;)V
       5: return

  software.amazon.awssdk.services.iotsitewise.model.BatchGetAssetPropertyValueHistorySuccessEntry$BuilderImpl(software.amazon.awssdk.services.iotsitewise.model.BatchGetAssetPropertyValueHistorySuccessEntry$1);
    Code:
       0: aload_0
       1: invokespecial #1                  // Method "<init>":()V
       4: return
}
