Compiled from "CreatePortalResponse.java"
final class software.amazon.awssdk.services.iotsitewise.model.CreatePortalResponse$BuilderImpl extends software.amazon.awssdk.services.iotsitewise.model.IoTSiteWiseResponse$BuilderImpl implements software.amazon.awssdk.services.iotsitewise.model.CreatePortalResponse$Builder {
  private java.lang.String portalId;

  private java.lang.String portalArn;

  private java.lang.String portalStartUrl;

  private software.amazon.awssdk.services.iotsitewise.model.PortalStatus portalStatus;

  private java.lang.String ssoApplicationId;

  private software.amazon.awssdk.services.iotsitewise.model.CreatePortalResponse$BuilderImpl();
    Code:
       0: aload_0
       1: invokespecial #8                  // Method software/amazon/awssdk/services/iotsitewise/model/IoTSiteWiseResponse$BuilderImpl."<init>":()V
       4: return

  private software.amazon.awssdk.services.iotsitewise.model.CreatePortalResponse$BuilderImpl(software.amazon.awssdk.services.iotsitewise.model.CreatePortalResponse);
    Code:
       0: aload_0
       1: aload_1
       2: invokespecial #9                  // Method software/amazon/awssdk/services/iotsitewise/model/IoTSiteWiseResponse$BuilderImpl."<init>":(Lsoftware/amazon/awssdk/services/iotsitewise/model/IoTSiteWiseResponse;)V
       5: aload_0
       6: aload_1
       7: invokestatic  #10                 // Method software/amazon/awssdk/services/iotsitewise/model/CreatePortalResponse.access$700:(Lsoftware/amazon/awssdk/services/iotsitewise/model/CreatePortalResponse;)Ljava/lang/String;
      10: invokevirtual #11                 // Method portalId:(Ljava/lang/String;)Lsoftware/amazon/awssdk/services/iotsitewise/model/CreatePortalResponse$Builder;
      13: pop
      14: aload_0
      15: aload_1
      16: invokestatic  #12                 // Method software/amazon/awssdk/services/iotsitewise/model/CreatePortalResponse.access$800:(Lsoftware/amazon/awssdk/services/iotsitewise/model/CreatePortalResponse;)Ljava/lang/String;
      19: invokevirtual #13                 // Method portalArn:(Ljava/lang/String;)Lsoftware/amazon/awssdk/services/iotsitewise/model/CreatePortalResponse$Builder;
      22: pop
      23: aload_0
      24: aload_1
      25: invokestatic  #14                 // Method software/amazon/awssdk/services/iotsitewise/model/CreatePortalResponse.access$900:(Lsoftware/amazon/awssdk/services/iotsitewise/model/CreatePortalResponse;)Ljava/lang/String;
      28: invokevirtual #15                 // Method portalStartUrl:(Ljava/lang/String;)Lsoftware/amazon/awssdk/services/iotsitewise/model/CreatePortalResponse$Builder;
      31: pop
      32: aload_0
      33: aload_1
      34: invokestatic  #16                 // Method software/amazon/awssdk/services/iotsitewise/model/CreatePortalResponse.access$1000:(Lsoftware/amazon/awssdk/services/iotsitewise/model/CreatePortalResponse;)Lsoftware/amazon/awssdk/services/iotsitewise/model/PortalStatus;
      37: invokevirtual #17                 // Method portalStatus:(Lsoftware/amazon/awssdk/services/iotsitewise/model/PortalStatus;)Lsoftware/amazon/awssdk/services/iotsitewise/model/CreatePortalResponse$Builder;
      40: pop
      41: aload_0
      42: aload_1
      43: invokestatic  #18                 // Method software/amazon/awssdk/services/iotsitewise/model/CreatePortalResponse.access$1100:(Lsoftware/amazon/awssdk/services/iotsitewise/model/CreatePortalResponse;)Ljava/lang/String;
      46: invokevirtual #19                 // Method ssoApplicationId:(Ljava/lang/String;)Lsoftware/amazon/awssdk/services/iotsitewise/model/CreatePortalResponse$Builder;
      49: pop
      50: return

  public final java.lang.String getPortalId();
    Code:
       0: aload_0
       1: getfield      #7                  // Field portalId:Ljava/lang/String;
       4: areturn

  public final void setPortalId(java.lang.String);
    Code:
       0: aload_0
       1: aload_1
       2: putfield      #7                  // Field portalId:Ljava/lang/String;
       5: return

  public final software.amazon.awssdk.services.iotsitewise.model.CreatePortalResponse$Builder portalId(java.lang.String);
    Code:
       0: aload_0
       1: aload_1
       2: putfield      #7                  // Field portalId:Ljava/lang/String;
       5: aload_0
       6: areturn

  public final java.lang.String getPortalArn();
    Code:
       0: aload_0
       1: getfield      #6                  // Field portalArn:Ljava/lang/String;
       4: areturn

  public final void setPortalArn(java.lang.String);
    Code:
       0: aload_0
       1: aload_1
       2: putfield      #6                  // Field portalArn:Ljava/lang/String;
       5: return

  public final software.amazon.awssdk.services.iotsitewise.model.CreatePortalResponse$Builder portalArn(java.lang.String);
    Code:
       0: aload_0
       1: aload_1
       2: putfield      #6                  // Field portalArn:Ljava/lang/String;
       5: aload_0
       6: areturn

  public final java.lang.String getPortalStartUrl();
    Code:
       0: aload_0
       1: getfield      #5                  // Field portalStartUrl:Ljava/lang/String;
       4: areturn

  public final void setPortalStartUrl(java.lang.String);
    Code:
       0: aload_0
       1: aload_1
       2: putfield      #5                  // Field portalStartUrl:Ljava/lang/String;
       5: return

  public final software.amazon.awssdk.services.iotsitewise.model.CreatePortalResponse$Builder portalStartUrl(java.lang.String);
    Code:
       0: aload_0
       1: aload_1
       2: putfield      #5                  // Field portalStartUrl:Ljava/lang/String;
       5: aload_0
       6: areturn

  public final software.amazon.awssdk.services.iotsitewise.model.PortalStatus$Builder getPortalStatus();
    Code:
       0: aload_0
       1: getfield      #4                  // Field portalStatus:Lsoftware/amazon/awssdk/services/iotsitewise/model/PortalStatus;
       4: ifnull        17
       7: aload_0
       8: getfield      #4                  // Field portalStatus:Lsoftware/amazon/awssdk/services/iotsitewise/model/PortalStatus;
      11: invokevirtual #20                 // Method software/amazon/awssdk/services/iotsitewise/model/PortalStatus.toBuilder:()Lsoftware/amazon/awssdk/services/iotsitewise/model/PortalStatus$Builder;
      14: goto          18
      17: aconst_null
      18: areturn

  public final void setPortalStatus(software.amazon.awssdk.services.iotsitewise.model.PortalStatus$BuilderImpl);
    Code:
       0: aload_0
       1: aload_1
       2: ifnull        12
       5: aload_1
       6: invokevirtual #21                 // Method software/amazon/awssdk/services/iotsitewise/model/PortalStatus$BuilderImpl.build:()Lsoftware/amazon/awssdk/services/iotsitewise/model/PortalStatus;
       9: goto          13
      12: aconst_null
      13: putfield      #4                  // Field portalStatus:Lsoftware/amazon/awssdk/services/iotsitewise/model/PortalStatus;
      16: return

  public final software.amazon.awssdk.services.iotsitewise.model.CreatePortalResponse$Builder portalStatus(software.amazon.awssdk.services.iotsitewise.model.PortalStatus);
    Code:
       0: aload_0
       1: aload_1
       2: putfield      #4                  // Field portalStatus:Lsoftware/amazon/awssdk/services/iotsitewise/model/PortalStatus;
       5: aload_0
       6: areturn

  public final java.lang.String getSsoApplicationId();
    Code:
       0: aload_0
       1: getfield      #3                  // Field ssoApplicationId:Ljava/lang/String;
       4: areturn

  public final void setSsoApplicationId(java.lang.String);
    Code:
       0: aload_0
       1: aload_1
       2: putfield      #3                  // Field ssoApplicationId:Ljava/lang/String;
       5: return

  public final software.amazon.awssdk.services.iotsitewise.model.CreatePortalResponse$Builder ssoApplicationId(java.lang.String);
    Code:
       0: aload_0
       1: aload_1
       2: putfield      #3                  // Field ssoApplicationId:Ljava/lang/String;
       5: aload_0
       6: areturn

  public software.amazon.awssdk.services.iotsitewise.model.CreatePortalResponse build();
    Code:
       0: new           #22                 // class software/amazon/awssdk/services/iotsitewise/model/CreatePortalResponse
       3: dup
       4: aload_0
       5: aconst_null
       6: invokespecial #23                 // Method software/amazon/awssdk/services/iotsitewise/model/CreatePortalResponse."<init>":(Lsoftware/amazon/awssdk/services/iotsitewise/model/CreatePortalResponse$BuilderImpl;Lsoftware/amazon/awssdk/services/iotsitewise/model/CreatePortalResponse$1;)V
       9: areturn

  public java.util.List<software.amazon.awssdk.core.SdkField<?>> sdkFields();
    Code:
       0: invokestatic  #24                 // Method software/amazon/awssdk/services/iotsitewise/model/CreatePortalResponse.access$1300:()Ljava/util/List;
       3: areturn

  public software.amazon.awssdk.services.iotsitewise.model.IoTSiteWiseResponse build();
    Code:
       0: aload_0
       1: invokevirtual #25                 // Method build:()Lsoftware/amazon/awssdk/services/iotsitewise/model/CreatePortalResponse;
       4: areturn

  public software.amazon.awssdk.awscore.AwsResponse build();
    Code:
       0: aload_0
       1: invokevirtual #25                 // Method build:()Lsoftware/amazon/awssdk/services/iotsitewise/model/CreatePortalResponse;
       4: areturn

  public software.amazon.awssdk.core.SdkResponse build();
    Code:
       0: aload_0
       1: invokevirtual #25                 // Method build:()Lsoftware/amazon/awssdk/services/iotsitewise/model/CreatePortalResponse;
       4: areturn

  public java.lang.Object build();
    Code:
       0: aload_0
       1: invokevirtual #25                 // Method build:()Lsoftware/amazon/awssdk/services/iotsitewise/model/CreatePortalResponse;
       4: areturn

  static java.lang.String access$000(software.amazon.awssdk.services.iotsitewise.model.CreatePortalResponse$BuilderImpl);
    Code:
       0: aload_0
       1: getfield      #7                  // Field portalId:Ljava/lang/String;
       4: areturn

  static java.lang.String access$100(software.amazon.awssdk.services.iotsitewise.model.CreatePortalResponse$BuilderImpl);
    Code:
       0: aload_0
       1: getfield      #6                  // Field portalArn:Ljava/lang/String;
       4: areturn

  static java.lang.String access$200(software.amazon.awssdk.services.iotsitewise.model.CreatePortalResponse$BuilderImpl);
    Code:
       0: aload_0
       1: getfield      #5                  // Field portalStartUrl:Ljava/lang/String;
       4: areturn

  static software.amazon.awssdk.services.iotsitewise.model.PortalStatus access$300(software.amazon.awssdk.services.iotsitewise.model.CreatePortalResponse$BuilderImpl);
    Code:
       0: aload_0
       1: getfield      #4                  // Field portalStatus:Lsoftware/amazon/awssdk/services/iotsitewise/model/PortalStatus;
       4: areturn

  static java.lang.String access$400(software.amazon.awssdk.services.iotsitewise.model.CreatePortalResponse$BuilderImpl);
    Code:
       0: aload_0
       1: getfield      #3                  // Field ssoApplicationId:Ljava/lang/String;
       4: areturn

  software.amazon.awssdk.services.iotsitewise.model.CreatePortalResponse$BuilderImpl(software.amazon.awssdk.services.iotsitewise.model.CreatePortalResponse, software.amazon.awssdk.services.iotsitewise.model.CreatePortalResponse$1);
    Code:
       0: aload_0
       1: aload_1
       2: invokespecial #2                  // Method "<init>":(Lsoftware/amazon/awssdk/services/iotsitewise/model/CreatePortalResponse;)V
       5: return

  software.amazon.awssdk.services.iotsitewise.model.CreatePortalResponse$BuilderImpl(software.amazon.awssdk.services.iotsitewise.model.CreatePortalResponse$1);
    Code:
       0: aload_0
       1: invokespecial #1                  // Method "<init>":()V
       4: return
}
