Compiled from "PooledByteBufAllocator.java"
final class io.netty.buffer.PooledByteBufAllocator$PoolThreadLocalCache extends io.netty.util.concurrent.FastThreadLocal<io.netty.buffer.PoolThreadCache> {
  private final boolean useCacheForAllThreads;

  final io.netty.buffer.PooledByteBufAllocator this$0;

  io.netty.buffer.PooledByteBufAllocator$PoolThreadLocalCache(io.netty.buffer.PooledByteBufAllocator, boolean);
    Code:
       0: aload_0
       1: aload_1
       2: putfield      #1                  // Field this$0:Lio/netty/buffer/PooledByteBufAllocator;
       5: aload_0
       6: invokespecial #2                  // Method io/netty/util/concurrent/FastThreadLocal."<init>":()V
       9: aload_0
      10: iload_2
      11: putfield      #3                  // Field useCacheForAllThreads:Z
      14: return

  protected synchronized io.netty.buffer.PoolThreadCache initialValue();
    Code:
       0: aload_0
       1: aload_0
       2: getfield      #1                  // Field this$0:Lio/netty/buffer/PooledByteBufAllocator;
       5: invokestatic  #4                  // Method io/netty/buffer/PooledByteBufAllocator.access$000:(Lio/netty/buffer/PooledByteBufAllocator;)[Lio/netty/buffer/PoolArena;
       8: invokespecial #5                  // Method leastUsedArena:([Lio/netty/buffer/PoolArena;)Lio/netty/buffer/PoolArena;
      11: astore_1
      12: aload_0
      13: aload_0
      14: getfield      #1                  // Field this$0:Lio/netty/buffer/PooledByteBufAllocator;
      17: invokestatic  #6                  // Method io/netty/buffer/PooledByteBufAllocator.access$100:(Lio/netty/buffer/PooledByteBufAllocator;)[Lio/netty/buffer/PoolArena;
      20: invokespecial #5                  // Method leastUsedArena:([Lio/netty/buffer/PoolArena;)Lio/netty/buffer/PoolArena;
      23: astore_2
      24: invokestatic  #7                  // Method java/lang/Thread.currentThread:()Ljava/lang/Thread;
      27: astore_3
      28: aload_0
      29: getfield      #3                  // Field useCacheForAllThreads:Z
      32: ifne          42
      35: aload_3
      36: instanceof    #8                  // class io/netty/util/concurrent/FastThreadLocalThread
      39: ifeq          118
      42: new           #9                  // class io/netty/buffer/PoolThreadCache
      45: dup
      46: aload_1
      47: aload_2
      48: aload_0
      49: getfield      #1                  // Field this$0:Lio/netty/buffer/PooledByteBufAllocator;
      52: invokestatic  #10                 // Method io/netty/buffer/PooledByteBufAllocator.access$200:(Lio/netty/buffer/PooledByteBufAllocator;)I
      55: aload_0
      56: getfield      #1                  // Field this$0:Lio/netty/buffer/PooledByteBufAllocator;
      59: invokestatic  #11                 // Method io/netty/buffer/PooledByteBufAllocator.access$300:(Lio/netty/buffer/PooledByteBufAllocator;)I
      62: getstatic     #12                 // Field io/netty/buffer/PooledByteBufAllocator.DEFAULT_MAX_CACHED_BUFFER_CAPACITY:I
      65: invokestatic  #13                 // Method io/netty/buffer/PooledByteBufAllocator.access$400:()I
      68: invokespecial #14                 // Method io/netty/buffer/PoolThreadCache."<init>":(Lio/netty/buffer/PoolArena;Lio/netty/buffer/PoolArena;IIII)V
      71: astore        4
      73: invokestatic  #15                 // Method io/netty/buffer/PooledByteBufAllocator.access$500:()J
      76: lconst_0
      77: lcmp
      78: ifle          115
      81: invokestatic  #16                 // Method io/netty/util/internal/ThreadExecutorMap.currentExecutor:()Lio/netty/util/concurrent/EventExecutor;
      84: astore        5
      86: aload         5
      88: ifnull        115
      91: aload         5
      93: aload_0
      94: getfield      #1                  // Field this$0:Lio/netty/buffer/PooledByteBufAllocator;
      97: invokestatic  #17                 // Method io/netty/buffer/PooledByteBufAllocator.access$600:(Lio/netty/buffer/PooledByteBufAllocator;)Ljava/lang/Runnable;
     100: invokestatic  #15                 // Method io/netty/buffer/PooledByteBufAllocator.access$500:()J
     103: invokestatic  #15                 // Method io/netty/buffer/PooledByteBufAllocator.access$500:()J
     106: getstatic     #18                 // Field java/util/concurrent/TimeUnit.MILLISECONDS:Ljava/util/concurrent/TimeUnit;
     109: invokeinterface #19,  7           // InterfaceMethod io/netty/util/concurrent/EventExecutor.scheduleAtFixedRate:(Ljava/lang/Runnable;JJLjava/util/concurrent/TimeUnit;)Lio/netty/util/concurrent/ScheduledFuture;
     114: pop
     115: aload         4
     117: areturn
     118: new           #9                  // class io/netty/buffer/PoolThreadCache
     121: dup
     122: aload_1
     123: aload_2
     124: iconst_0
     125: iconst_0
     126: iconst_0
     127: iconst_0
     128: invokespecial #14                 // Method io/netty/buffer/PoolThreadCache."<init>":(Lio/netty/buffer/PoolArena;Lio/netty/buffer/PoolArena;IIII)V
     131: areturn

  protected void onRemoval(io.netty.buffer.PoolThreadCache);
    Code:
       0: aload_1
       1: iconst_0
       2: invokevirtual #20                 // Method io/netty/buffer/PoolThreadCache.free:(Z)V
       5: return

  private <T> io.netty.buffer.PoolArena<T> leastUsedArena(io.netty.buffer.PoolArena<T>[]);
    Code:
       0: aload_1
       1: ifnull        9
       4: aload_1
       5: arraylength
       6: ifne          11
       9: aconst_null
      10: areturn
      11: aload_1
      12: iconst_0
      13: aaload
      14: astore_2
      15: iconst_1
      16: istore_3
      17: iload_3
      18: aload_1
      19: arraylength
      20: if_icmpge     55
      23: aload_1
      24: iload_3
      25: aaload
      26: astore        4
      28: aload         4
      30: getfield      #21                 // Field io/netty/buffer/PoolArena.numThreadCaches:Ljava/util/concurrent/atomic/AtomicInteger;
      33: invokevirtual #22                 // Method java/util/concurrent/atomic/AtomicInteger.get:()I
      36: aload_2
      37: getfield      #21                 // Field io/netty/buffer/PoolArena.numThreadCaches:Ljava/util/concurrent/atomic/AtomicInteger;
      40: invokevirtual #22                 // Method java/util/concurrent/atomic/AtomicInteger.get:()I
      43: if_icmpge     49
      46: aload         4
      48: astore_2
      49: iinc          3, 1
      52: goto          17
      55: aload_2
      56: areturn

  protected void onRemoval(java.lang.Object) throws java.lang.Exception;
    Code:
       0: aload_0
       1: aload_1
       2: checkcast     #9                  // class io/netty/buffer/PoolThreadCache
       5: invokevirtual #23                 // Method onRemoval:(Lio/netty/buffer/PoolThreadCache;)V
       8: return

  protected java.lang.Object initialValue() throws java.lang.Exception;
    Code:
       0: aload_0
       1: invokevirtual #24                 // Method initialValue:()Lio/netty/buffer/PoolThreadCache;
       4: areturn
}
