Compiled from "SonarLintInputFile.java"
public class org.sonarsource.sonarlint.core.analysis.container.analysis.filesystem.SonarLintInputFile implements org.sonar.api.batch.fs.InputFile {
  private final org.sonarsource.sonarlint.core.analysis.api.ClientInputFile clientInputFile;

  private final java.lang.String relativePath;

  private org.sonarsource.sonarlint.core.commons.Language language;

  private org.sonar.api.batch.fs.InputFile$Type type;

  private org.sonarsource.sonarlint.core.analysis.container.analysis.filesystem.FileMetadata$Metadata metadata;

  private final java.util.function.Function<org.sonarsource.sonarlint.core.analysis.container.analysis.filesystem.SonarLintInputFile, org.sonarsource.sonarlint.core.analysis.container.analysis.filesystem.FileMetadata$Metadata> metadataGenerator;

  private boolean ignoreAllIssues;

  private final java.util.Set<java.lang.Integer> noSonarLines;

  private java.util.Collection<int[]> ignoreIssuesOnlineRanges;

  public org.sonarsource.sonarlint.core.analysis.container.analysis.filesystem.SonarLintInputFile(org.sonarsource.sonarlint.core.analysis.api.ClientInputFile, java.util.function.Function<org.sonarsource.sonarlint.core.analysis.container.analysis.filesystem.SonarLintInputFile, org.sonarsource.sonarlint.core.analysis.container.analysis.filesystem.FileMetadata$Metadata>);
    Code:
       0: aload_0
       1: invokespecial #50                 // Method java/lang/Object."<init>":()V
       4: aload_0
       5: new           #52                 // class java/util/HashSet
       8: dup
       9: invokespecial #53                 // Method java/util/HashSet."<init>":()V
      12: putfield      #55                 // Field noSonarLines:Ljava/util/Set;
      15: aload_0
      16: aload_1
      17: putfield      #57                 // Field clientInputFile:Lorg/sonarsource/sonarlint/core/analysis/api/ClientInputFile;
      20: aload_0
      21: aload_2
      22: putfield      #59                 // Field metadataGenerator:Ljava/util/function/Function;
      25: aload_0
      26: aload_1
      27: invokeinterface #64,  1           // InterfaceMethod org/sonarsource/sonarlint/core/analysis/api/ClientInputFile.relativePath:()Ljava/lang/String;
      32: invokestatic  #70                 // Method org/sonar/api/utils/PathUtils.sanitize:(Ljava/lang/String;)Ljava/lang/String;
      35: putfield      #72                 // Field relativePath:Ljava/lang/String;
      38: return

  public void checkMetadata();
    Code:
       0: aload_0
       1: getfield      #77                 // Field metadata:Lorg/sonarsource/sonarlint/core/analysis/container/analysis/filesystem/FileMetadata$Metadata;
       4: ifnonnull     24
       7: aload_0
       8: aload_0
       9: getfield      #59                 // Field metadataGenerator:Ljava/util/function/Function;
      12: aload_0
      13: invokeinterface #83,  2           // InterfaceMethod java/util/function/Function.apply:(Ljava/lang/Object;)Ljava/lang/Object;
      18: checkcast     #12                 // class org/sonarsource/sonarlint/core/analysis/container/analysis/filesystem/FileMetadata$Metadata
      21: putfield      #77                 // Field metadata:Lorg/sonarsource/sonarlint/core/analysis/container/analysis/filesystem/FileMetadata$Metadata;
      24: return

  public org.sonarsource.sonarlint.core.analysis.api.ClientInputFile getClientInputFile();
    Code:
       0: aload_0
       1: getfield      #57                 // Field clientInputFile:Lorg/sonarsource/sonarlint/core/analysis/api/ClientInputFile;
       4: areturn

  public java.lang.String relativePath();
    Code:
       0: aload_0
       1: getfield      #72                 // Field relativePath:Ljava/lang/String;
       4: areturn

  public org.sonarsource.sonarlint.core.analysis.container.analysis.filesystem.SonarLintInputFile setLanguage(org.sonarsource.sonarlint.core.commons.Language);
    Code:
       0: aload_0
       1: aload_1
       2: putfield      #90                 // Field language:Lorg/sonarsource/sonarlint/core/commons/Language;
       5: aload_0
       6: areturn

  public org.sonarsource.sonarlint.core.analysis.container.analysis.filesystem.SonarLintInputFile setType(org.sonar.api.batch.fs.InputFile$Type);
    Code:
       0: aload_0
       1: aload_1
       2: putfield      #94                 // Field type:Lorg/sonar/api/batch/fs/InputFile$Type;
       5: aload_0
       6: areturn

  public java.lang.String language();
    Code:
       0: aload_0
       1: getfield      #90                 // Field language:Lorg/sonarsource/sonarlint/core/commons/Language;
       4: ifnull        17
       7: aload_0
       8: getfield      #90                 // Field language:Lorg/sonarsource/sonarlint/core/commons/Language;
      11: invokevirtual #100                // Method org/sonarsource/sonarlint/core/commons/Language.getLanguageKey:()Ljava/lang/String;
      14: goto          18
      17: aconst_null
      18: areturn

  public org.sonarsource.sonarlint.core.commons.Language getLanguage();
    Code:
       0: aload_0
       1: getfield      #90                 // Field language:Lorg/sonarsource/sonarlint/core/commons/Language;
       4: areturn

  public org.sonar.api.batch.fs.InputFile$Type type();
    Code:
       0: aload_0
       1: getfield      #94                 // Field type:Lorg/sonar/api/batch/fs/InputFile$Type;
       4: areturn

  public java.lang.String absolutePath();
    Code:
       0: aload_0
       1: getfield      #57                 // Field clientInputFile:Lorg/sonarsource/sonarlint/core/analysis/api/ClientInputFile;
       4: invokeinterface #110,  1          // InterfaceMethod org/sonarsource/sonarlint/core/analysis/api/ClientInputFile.getPath:()Ljava/lang/String;
       9: invokestatic  #70                 // Method org/sonar/api/utils/PathUtils.sanitize:(Ljava/lang/String;)Ljava/lang/String;
      12: areturn

  public java.io.File file();
    Code:
       0: aload_0
       1: invokevirtual #116                // Method path:()Ljava/nio/file/Path;
       4: invokeinterface #121,  1          // InterfaceMethod java/nio/file/Path.toFile:()Ljava/io/File;
       9: areturn

  public java.nio.file.Path path();
    Code:
       0: aload_0
       1: getfield      #57                 // Field clientInputFile:Lorg/sonarsource/sonarlint/core/analysis/api/ClientInputFile;
       4: invokeinterface #110,  1          // InterfaceMethod org/sonarsource/sonarlint/core/analysis/api/ClientInputFile.getPath:()Ljava/lang/String;
       9: iconst_0
      10: anewarray     #102                // class java/lang/String
      13: invokestatic  #127                // Method java/nio/file/Paths.get:(Ljava/lang/String;[Ljava/lang/String;)Ljava/nio/file/Path;
      16: areturn

  public java.io.InputStream inputStream() throws java.io.IOException;
    Code:
       0: aload_0
       1: getfield      #57                 // Field clientInputFile:Lorg/sonarsource/sonarlint/core/analysis/api/ClientInputFile;
       4: invokeinterface #133,  1          // InterfaceMethod org/sonarsource/sonarlint/core/analysis/api/ClientInputFile.inputStream:()Ljava/io/InputStream;
       9: areturn

  public java.lang.String contents() throws java.io.IOException;
    Code:
       0: aload_0
       1: getfield      #57                 // Field clientInputFile:Lorg/sonarsource/sonarlint/core/analysis/api/ClientInputFile;
       4: invokeinterface #136,  1          // InterfaceMethod org/sonarsource/sonarlint/core/analysis/api/ClientInputFile.contents:()Ljava/lang/String;
       9: areturn

  public org.sonar.api.batch.fs.InputFile$Status status();
    Code:
       0: getstatic     #142                // Field org/sonar/api/batch/fs/InputFile$Status.ADDED:Lorg/sonar/api/batch/fs/InputFile$Status;
       3: areturn

  public java.lang.String key();
    Code:
       0: aload_0
       1: invokevirtual #147                // Method uri:()Ljava/net/URI;
       4: invokevirtual #152                // Method java/net/URI.toString:()Ljava/lang/String;
       7: areturn

  public java.net.URI uri();
    Code:
       0: aload_0
       1: getfield      #57                 // Field clientInputFile:Lorg/sonarsource/sonarlint/core/analysis/api/ClientInputFile;
       4: invokeinterface #153,  1          // InterfaceMethod org/sonarsource/sonarlint/core/analysis/api/ClientInputFile.uri:()Ljava/net/URI;
       9: areturn

  public java.nio.charset.Charset charset();
    Code:
       0: aload_0
       1: getfield      #57                 // Field clientInputFile:Lorg/sonarsource/sonarlint/core/analysis/api/ClientInputFile;
       4: invokeinterface #158,  1          // InterfaceMethod org/sonarsource/sonarlint/core/analysis/api/ClientInputFile.getCharset:()Ljava/nio/charset/Charset;
       9: astore_1
      10: aload_1
      11: ifnull        18
      14: aload_1
      15: goto          21
      18: invokestatic  #163                // Method java/nio/charset/Charset.defaultCharset:()Ljava/nio/charset/Charset;
      21: areturn

  public boolean equals(java.lang.Object);
    Code:
       0: aload_0
       1: aload_1
       2: if_acmpne     7
       5: iconst_1
       6: ireturn
       7: aload_1
       8: instanceof    #2                  // class org/sonarsource/sonarlint/core/analysis/container/analysis/filesystem/SonarLintInputFile
      11: ifne          16
      14: iconst_0
      15: ireturn
      16: aload_1
      17: checkcast     #2                  // class org/sonarsource/sonarlint/core/analysis/container/analysis/filesystem/SonarLintInputFile
      20: astore_2
      21: aload_0
      22: invokevirtual #147                // Method uri:()Ljava/net/URI;
      25: aload_2
      26: invokevirtual #147                // Method uri:()Ljava/net/URI;
      29: invokevirtual #168                // Method java/net/URI.equals:(Ljava/lang/Object;)Z
      32: ireturn

  public int hashCode();
    Code:
       0: aload_0
       1: invokevirtual #147                // Method uri:()Ljava/net/URI;
       4: invokevirtual #175                // Method java/net/URI.hashCode:()I
       7: ireturn

  public java.lang.String toString();
    Code:
       0: aload_0
       1: invokevirtual #147                // Method uri:()Ljava/net/URI;
       4: invokedynamic #187,  0            // InvokeDynamic #0:makeConcatWithConstants:(Ljava/net/URI;)Ljava/lang/String;
       9: areturn

  public boolean isFile();
    Code:
       0: iconst_1
       1: ireturn

  public java.lang.String filename();
    Code:
       0: aload_0
       1: getfield      #72                 // Field relativePath:Ljava/lang/String;
       4: iconst_0
       5: anewarray     #102                // class java/lang/String
       8: invokestatic  #127                // Method java/nio/file/Paths.get:(Ljava/lang/String;[Ljava/lang/String;)Ljava/nio/file/Path;
      11: invokeinterface #193,  1          // InterfaceMethod java/nio/file/Path.getFileName:()Ljava/nio/file/Path;
      16: invokeinterface #194,  1          // InterfaceMethod java/nio/file/Path.toString:()Ljava/lang/String;
      21: areturn

  public int lines();
    Code:
       0: aload_0
       1: invokevirtual #197                // Method checkMetadata:()V
       4: aload_0
       5: getfield      #77                 // Field metadata:Lorg/sonarsource/sonarlint/core/analysis/container/analysis/filesystem/FileMetadata$Metadata;
       8: invokevirtual #199                // Method org/sonarsource/sonarlint/core/analysis/container/analysis/filesystem/FileMetadata$Metadata.lines:()I
      11: ireturn

  public boolean isEmpty();
    Code:
       0: aload_0
       1: invokevirtual #197                // Method checkMetadata:()V
       4: aload_0
       5: getfield      #77                 // Field metadata:Lorg/sonarsource/sonarlint/core/analysis/container/analysis/filesystem/FileMetadata$Metadata;
       8: invokevirtual #203                // Method org/sonarsource/sonarlint/core/analysis/container/analysis/filesystem/FileMetadata$Metadata.lastValidOffset:()I
      11: ifne          18
      14: iconst_1
      15: goto          19
      18: iconst_0
      19: ireturn

  public org.sonar.api.batch.fs.TextPointer newPointer(int, int);
    Code:
       0: aload_0
       1: invokevirtual #197                // Method checkMetadata:()V
       4: new           #207                // class org/sonarsource/sonarlint/core/analysis/container/analysis/filesystem/DefaultTextPointer
       7: dup
       8: iload_1
       9: iload_2
      10: invokespecial #210                // Method org/sonarsource/sonarlint/core/analysis/container/analysis/filesystem/DefaultTextPointer."<init>":(II)V
      13: areturn

  public org.sonar.api.batch.fs.TextRange newRange(org.sonar.api.batch.fs.TextPointer, org.sonar.api.batch.fs.TextPointer);
    Code:
       0: aload_0
       1: invokevirtual #197                // Method checkMetadata:()V
       4: aload_1
       5: aload_2
       6: invokestatic  #218                // Method newRangeValidPointers:(Lorg/sonar/api/batch/fs/TextPointer;Lorg/sonar/api/batch/fs/TextPointer;)Lorg/sonar/api/batch/fs/TextRange;
       9: areturn

  public org.sonar.api.batch.fs.TextRange newRange(int, int, int, int);
    Code:
       0: aload_0
       1: invokevirtual #197                // Method checkMetadata:()V
       4: aload_0
       5: iload_1
       6: iload_2
       7: invokevirtual #224                // Method newPointer:(II)Lorg/sonar/api/batch/fs/TextPointer;
      10: astore        5
      12: aload_0
      13: iload_3
      14: iload         4
      16: invokevirtual #224                // Method newPointer:(II)Lorg/sonar/api/batch/fs/TextPointer;
      19: astore        6
      21: aload         5
      23: aload         6
      25: invokestatic  #218                // Method newRangeValidPointers:(Lorg/sonar/api/batch/fs/TextPointer;Lorg/sonar/api/batch/fs/TextPointer;)Lorg/sonar/api/batch/fs/TextRange;
      28: areturn

  public org.sonar.api.batch.fs.TextRange selectLine(int);
    Code:
       0: aload_0
       1: invokevirtual #197                // Method checkMetadata:()V
       4: aload_0
       5: iload_1
       6: iconst_0
       7: invokevirtual #224                // Method newPointer:(II)Lorg/sonar/api/batch/fs/TextPointer;
      10: astore_2
      11: aload_0
      12: iload_1
      13: aload_0
      14: iload_1
      15: invokevirtual #234                // Method lineLength:(I)I
      18: invokevirtual #224                // Method newPointer:(II)Lorg/sonar/api/batch/fs/TextPointer;
      21: astore_3
      22: aload_2
      23: aload_3
      24: invokestatic  #218                // Method newRangeValidPointers:(Lorg/sonar/api/batch/fs/TextPointer;Lorg/sonar/api/batch/fs/TextPointer;)Lorg/sonar/api/batch/fs/TextRange;
      27: areturn

  private static org.sonar.api.batch.fs.TextRange newRangeValidPointers(org.sonar.api.batch.fs.TextPointer, org.sonar.api.batch.fs.TextPointer);
    Code:
       0: new           #238                // class org/sonarsource/sonarlint/core/analysis/container/analysis/filesystem/DefaultTextRange
       3: dup
       4: aload_0
       5: aload_1
       6: invokespecial #241                // Method org/sonarsource/sonarlint/core/analysis/container/analysis/filesystem/DefaultTextRange."<init>":(Lorg/sonar/api/batch/fs/TextPointer;Lorg/sonar/api/batch/fs/TextPointer;)V
       9: areturn

  private int lineLength(int);
    Code:
       0: aload_0
       1: iload_1
       2: invokevirtual #244                // Method lastValidGlobalOffsetForLine:(I)I
       5: aload_0
       6: getfield      #77                 // Field metadata:Lorg/sonarsource/sonarlint/core/analysis/container/analysis/filesystem/FileMetadata$Metadata;
       9: invokevirtual #248                // Method org/sonarsource/sonarlint/core/analysis/container/analysis/filesystem/FileMetadata$Metadata.originalLineOffsets:()[I
      12: iload_1
      13: iconst_1
      14: isub
      15: iaload
      16: isub
      17: ireturn

  private int lastValidGlobalOffsetForLine(int);
    Code:
       0: iload_1
       1: aload_0
       2: getfield      #77                 // Field metadata:Lorg/sonarsource/sonarlint/core/analysis/container/analysis/filesystem/FileMetadata$Metadata;
       5: invokevirtual #199                // Method org/sonarsource/sonarlint/core/analysis/container/analysis/filesystem/FileMetadata$Metadata.lines:()I
       8: if_icmpge     25
      11: aload_0
      12: getfield      #77                 // Field metadata:Lorg/sonarsource/sonarlint/core/analysis/container/analysis/filesystem/FileMetadata$Metadata;
      15: invokevirtual #248                // Method org/sonarsource/sonarlint/core/analysis/container/analysis/filesystem/FileMetadata$Metadata.originalLineOffsets:()[I
      18: iload_1
      19: iaload
      20: iconst_1
      21: isub
      22: goto          32
      25: aload_0
      26: getfield      #77                 // Field metadata:Lorg/sonarsource/sonarlint/core/analysis/container/analysis/filesystem/FileMetadata$Metadata;
      29: invokevirtual #203                // Method org/sonarsource/sonarlint/core/analysis/container/analysis/filesystem/FileMetadata$Metadata.lastValidOffset:()I
      32: ireturn

  public void noSonarAt(java.util.Set<java.lang.Integer>);
    Code:
       0: aload_0
       1: getfield      #55                 // Field noSonarLines:Ljava/util/Set;
       4: aload_1
       5: invokeinterface #257,  2          // InterfaceMethod java/util/Set.addAll:(Ljava/util/Collection;)Z
      10: pop
      11: return

  public boolean hasNoSonarAt(int);
    Code:
       0: aload_0
       1: getfield      #55                 // Field noSonarLines:Ljava/util/Set;
       4: iload_1
       5: invokestatic  #265                // Method java/lang/Integer.valueOf:(I)Ljava/lang/Integer;
       8: invokeinterface #268,  2          // InterfaceMethod java/util/Set.contains:(Ljava/lang/Object;)Z
      13: ireturn

  public boolean isIgnoreAllIssues();
    Code:
       0: aload_0
       1: invokevirtual #197                // Method checkMetadata:()V
       4: aload_0
       5: getfield      #271                // Field ignoreAllIssues:Z
       8: ireturn

  public void setIgnoreAllIssues(boolean);
    Code:
       0: aload_0
       1: iload_1
       2: putfield      #271                // Field ignoreAllIssues:Z
       5: return

  public void addIgnoreIssuesOnLineRanges(java.util.Collection<int[]>);
    Code:
       0: aload_0
       1: getfield      #278                // Field ignoreIssuesOnlineRanges:Ljava/util/Collection;
       4: ifnonnull     18
       7: aload_0
       8: new           #280                // class java/util/ArrayList
      11: dup
      12: invokespecial #281                // Method java/util/ArrayList."<init>":()V
      15: putfield      #278                // Field ignoreIssuesOnlineRanges:Ljava/util/Collection;
      18: aload_0
      19: getfield      #278                // Field ignoreIssuesOnlineRanges:Ljava/util/Collection;
      22: aload_1
      23: invokeinterface #284,  2          // InterfaceMethod java/util/Collection.addAll:(Ljava/util/Collection;)Z
      28: pop
      29: return

  public boolean isIgnoreAllIssuesOnLine(java.lang.Integer);
    Code:
       0: aload_0
       1: invokevirtual #197                // Method checkMetadata:()V
       4: aload_1
       5: ifnull        15
       8: aload_0
       9: getfield      #278                // Field ignoreIssuesOnlineRanges:Ljava/util/Collection;
      12: ifnonnull     17
      15: iconst_0
      16: ireturn
      17: aload_0
      18: getfield      #278                // Field ignoreIssuesOnlineRanges:Ljava/util/Collection;
      21: invokeinterface #291,  1          // InterfaceMethod java/util/Collection.stream:()Ljava/util/stream/Stream;
      26: aload_1
      27: invokedynamic #310,  0            // InvokeDynamic #1:test:(Ljava/lang/Integer;)Ljava/util/function/Predicate;
      32: invokeinterface #316,  2          // InterfaceMethod java/util/stream/Stream.anyMatch:(Ljava/util/function/Predicate;)Z
      37: ireturn

  private static boolean lambda$isIgnoreAllIssuesOnLine$0(java.lang.Integer, int[]);
    Code:
       0: aload_1
       1: iconst_0
       2: iaload
       3: aload_0
       4: invokevirtual #320                // Method java/lang/Integer.intValue:()I
       7: if_icmpgt     24
      10: aload_0
      11: invokevirtual #320                // Method java/lang/Integer.intValue:()I
      14: aload_1
      15: iconst_1
      16: iaload
      17: if_icmpgt     24
      20: iconst_1
      21: goto          25
      24: iconst_0
      25: ireturn
}
