Compiled from "ConstantAttribute.java"
public class javassist.bytecode.ConstantAttribute extends javassist.bytecode.AttributeInfo {
  public static final java.lang.String tag;

  javassist.bytecode.ConstantAttribute(javassist.bytecode.ConstPool, int, java.io.DataInputStream) throws java.io.IOException;
    Code:
       0: aload_0
       1: aload_1
       2: iload_2
       3: aload_3
       4: invokespecial #1                  // Method javassist/bytecode/AttributeInfo."<init>":(Ljavassist/bytecode/ConstPool;ILjava/io/DataInputStream;)V
       7: return

  public javassist.bytecode.ConstantAttribute(javassist.bytecode.ConstPool, int);
    Code:
       0: aload_0
       1: aload_1
       2: ldc           #3                  // String ConstantValue
       4: invokespecial #4                  // Method javassist/bytecode/AttributeInfo."<init>":(Ljavassist/bytecode/ConstPool;Ljava/lang/String;)V
       7: iconst_2
       8: newarray       byte
      10: astore_3
      11: aload_3
      12: iconst_0
      13: iload_2
      14: bipush        8
      16: iushr
      17: i2b
      18: bastore
      19: aload_3
      20: iconst_1
      21: iload_2
      22: i2b
      23: bastore
      24: aload_0
      25: aload_3
      26: invokevirtual #5                  // Method set:([B)V
      29: return

  public int getConstantValue();
    Code:
       0: aload_0
       1: invokevirtual #6                  // Method get:()[B
       4: iconst_0
       5: invokestatic  #7                  // Method javassist/bytecode/ByteArray.readU16bit:([BI)I
       8: ireturn

  public javassist.bytecode.AttributeInfo copy(javassist.bytecode.ConstPool, java.util.Map<java.lang.String, java.lang.String>);
    Code:
       0: aload_0
       1: invokevirtual #8                  // Method getConstPool:()Ljavassist/bytecode/ConstPool;
       4: aload_0
       5: invokevirtual #9                  // Method getConstantValue:()I
       8: aload_1
       9: aload_2
      10: invokevirtual #10                 // Method javassist/bytecode/ConstPool.copy:(ILjavassist/bytecode/ConstPool;Ljava/util/Map;)I
      13: istore_3
      14: new           #2                  // class javassist/bytecode/ConstantAttribute
      17: dup
      18: aload_1
      19: iload_3
      20: invokespecial #11                 // Method "<init>":(Ljavassist/bytecode/ConstPool;I)V
      23: areturn
}
