Compiled from "YamlPropertiesFactoryBean.java"
public class org.springframework.beans.factory.config.YamlPropertiesFactoryBean extends org.springframework.beans.factory.config.YamlProcessor implements org.springframework.beans.factory.FactoryBean<java.util.Properties>, org.springframework.beans.factory.InitializingBean {
  private boolean singleton;

  private java.util.Properties properties;

  public org.springframework.beans.factory.config.YamlPropertiesFactoryBean();
    Code:
       0: aload_0
       1: invokespecial #1                  // Method org/springframework/beans/factory/config/YamlProcessor."<init>":()V
       4: aload_0
       5: iconst_1
       6: putfield      #2                  // Field singleton:Z
       9: return

  public void setSingleton(boolean);
    Code:
       0: aload_0
       1: iload_1
       2: putfield      #2                  // Field singleton:Z
       5: return

  public boolean isSingleton();
    Code:
       0: aload_0
       1: getfield      #2                  // Field singleton:Z
       4: ireturn

  public void afterPropertiesSet();
    Code:
       0: aload_0
       1: invokevirtual #3                  // Method isSingleton:()Z
       4: ifeq          15
       7: aload_0
       8: aload_0
       9: invokevirtual #4                  // Method createProperties:()Ljava/util/Properties;
      12: putfield      #5                  // Field properties:Ljava/util/Properties;
      15: return

  public java.util.Properties getObject();
    Code:
       0: aload_0
       1: getfield      #5                  // Field properties:Ljava/util/Properties;
       4: ifnull        14
       7: aload_0
       8: getfield      #5                  // Field properties:Ljava/util/Properties;
      11: goto          18
      14: aload_0
      15: invokevirtual #4                  // Method createProperties:()Ljava/util/Properties;
      18: areturn

  public java.lang.Class<?> getObjectType();
    Code:
       0: ldc           #6                  // class java/util/Properties
       2: areturn

  protected java.util.Properties createProperties();
    Code:
       0: invokestatic  #7                  // Method org/springframework/core/CollectionFactory.createStringAdaptingProperties:()Ljava/util/Properties;
       3: astore_1
       4: aload_0
       5: aload_1
       6: invokedynamic #8,  0              // InvokeDynamic #0:process:(Ljava/util/Properties;)Lorg/springframework/beans/factory/config/YamlProcessor$MatchCallback;
      11: invokevirtual #9                  // Method process:(Lorg/springframework/beans/factory/config/YamlProcessor$MatchCallback;)V
      14: aload_1
      15: areturn

  public java.lang.Object getObject() throws java.lang.Exception;
    Code:
       0: aload_0
       1: invokevirtual #10                 // Method getObject:()Ljava/util/Properties;
       4: areturn

  private static void lambda$createProperties$0(java.util.Properties, java.util.Properties, java.util.Map);
    Code:
       0: aload_0
       1: aload_1
       2: invokevirtual #11                 // Method java/util/Properties.putAll:(Ljava/util/Map;)V
       5: return
}
