Compiled from "ForTokensTag.java"
public class org.apache.taglibs.standard.tag.el.core.ForTokensTag extends org.apache.taglibs.standard.tag.common.core.ForTokensSupport implements javax.servlet.jsp.jstl.core.LoopTag,javax.servlet.jsp.tagext.IterationTag {
  private java.lang.String begin_;

  private java.lang.String end_;

  private java.lang.String step_;

  private java.lang.String items_;

  private java.lang.String delims_;

  public org.apache.taglibs.standard.tag.el.core.ForTokensTag();
    Code:
       0: aload_0
       1: invokespecial #1                  // Method org/apache/taglibs/standard/tag/common/core/ForTokensSupport."<init>":()V
       4: aload_0
       5: invokespecial #2                  // Method init:()V
       8: return

  public int doStartTag() throws javax.servlet.jsp.JspException;
    Code:
       0: aload_0
       1: invokespecial #3                  // Method evaluateExpressions:()V
       4: aload_0
       5: invokespecial #4                  // Method org/apache/taglibs/standard/tag/common/core/ForTokensSupport.doStartTag:()I
       8: ireturn

  public void release();
    Code:
       0: aload_0
       1: invokespecial #5                  // Method org/apache/taglibs/standard/tag/common/core/ForTokensSupport.release:()V
       4: aload_0
       5: invokespecial #2                  // Method init:()V
       8: return

  public void setBegin(java.lang.String);
    Code:
       0: aload_0
       1: aload_1
       2: putfield      #6                  // Field begin_:Ljava/lang/String;
       5: aload_0
       6: iconst_1
       7: putfield      #7                  // Field beginSpecified:Z
      10: return

  public void setEnd(java.lang.String);
    Code:
       0: aload_0
       1: aload_1
       2: putfield      #8                  // Field end_:Ljava/lang/String;
       5: aload_0
       6: iconst_1
       7: putfield      #9                  // Field endSpecified:Z
      10: return

  public void setStep(java.lang.String);
    Code:
       0: aload_0
       1: aload_1
       2: putfield      #10                 // Field step_:Ljava/lang/String;
       5: aload_0
       6: iconst_1
       7: putfield      #11                 // Field stepSpecified:Z
      10: return

  public void setItems(java.lang.String);
    Code:
       0: aload_0
       1: aload_1
       2: putfield      #12                 // Field items_:Ljava/lang/String;
       5: return

  public void setDelims(java.lang.String);
    Code:
       0: aload_0
       1: aload_1
       2: putfield      #13                 // Field delims_:Ljava/lang/String;
       5: return

  private void init();
    Code:
       0: aload_0
       1: aconst_null
       2: putfield      #6                  // Field begin_:Ljava/lang/String;
       5: aload_0
       6: aconst_null
       7: putfield      #8                  // Field end_:Ljava/lang/String;
      10: aload_0
      11: aconst_null
      12: putfield      #10                 // Field step_:Ljava/lang/String;
      15: aload_0
      16: aconst_null
      17: putfield      #12                 // Field items_:Ljava/lang/String;
      20: aload_0
      21: aconst_null
      22: putfield      #13                 // Field delims_:Ljava/lang/String;
      25: return

  private void evaluateExpressions() throws javax.servlet.jsp.JspException;
    Code:
       0: aload_0
       1: getfield      #6                  // Field begin_:Ljava/lang/String;
       4: ifnull        56
       7: ldc           #14                 // String begin
       9: aload_0
      10: getfield      #6                  // Field begin_:Ljava/lang/String;
      13: ldc_w         #15                 // class java/lang/Integer
      16: aload_0
      17: aload_0
      18: getfield      #16                 // Field pageContext:Ljavax/servlet/jsp/PageContext;
      21: invokestatic  #17                 // Method org/apache/taglibs/standard/lang/support/ExpressionEvaluatorManager.evaluate:(Ljava/lang/String;Ljava/lang/String;Ljava/lang/Class;Ljavax/servlet/jsp/tagext/Tag;Ljavax/servlet/jsp/PageContext;)Ljava/lang/Object;
      24: astore_1
      25: aload_1
      26: ifnonnull     41
      29: new           #18                 // class org/apache/taglibs/standard/tag/common/core/NullAttributeException
      32: dup
      33: ldc           #19                 // String forTokens
      35: ldc           #14                 // String begin
      37: invokespecial #20                 // Method org/apache/taglibs/standard/tag/common/core/NullAttributeException."<init>":(Ljava/lang/String;Ljava/lang/String;)V
      40: athrow
      41: aload_0
      42: aload_1
      43: checkcast     #15                 // class java/lang/Integer
      46: invokevirtual #21                 // Method java/lang/Integer.intValue:()I
      49: putfield      #22                 // Field begin:I
      52: aload_0
      53: invokevirtual #23                 // Method validateBegin:()V
      56: aload_0
      57: getfield      #8                  // Field end_:Ljava/lang/String;
      60: ifnull        112
      63: ldc           #24                 // String end
      65: aload_0
      66: getfield      #8                  // Field end_:Ljava/lang/String;
      69: ldc_w         #15                 // class java/lang/Integer
      72: aload_0
      73: aload_0
      74: getfield      #16                 // Field pageContext:Ljavax/servlet/jsp/PageContext;
      77: invokestatic  #17                 // Method org/apache/taglibs/standard/lang/support/ExpressionEvaluatorManager.evaluate:(Ljava/lang/String;Ljava/lang/String;Ljava/lang/Class;Ljavax/servlet/jsp/tagext/Tag;Ljavax/servlet/jsp/PageContext;)Ljava/lang/Object;
      80: astore_1
      81: aload_1
      82: ifnonnull     97
      85: new           #18                 // class org/apache/taglibs/standard/tag/common/core/NullAttributeException
      88: dup
      89: ldc           #19                 // String forTokens
      91: ldc           #24                 // String end
      93: invokespecial #20                 // Method org/apache/taglibs/standard/tag/common/core/NullAttributeException."<init>":(Ljava/lang/String;Ljava/lang/String;)V
      96: athrow
      97: aload_0
      98: aload_1
      99: checkcast     #15                 // class java/lang/Integer
     102: invokevirtual #21                 // Method java/lang/Integer.intValue:()I
     105: putfield      #25                 // Field end:I
     108: aload_0
     109: invokevirtual #26                 // Method validateEnd:()V
     112: aload_0
     113: getfield      #10                 // Field step_:Ljava/lang/String;
     116: ifnull        168
     119: ldc           #27                 // String step
     121: aload_0
     122: getfield      #10                 // Field step_:Ljava/lang/String;
     125: ldc_w         #15                 // class java/lang/Integer
     128: aload_0
     129: aload_0
     130: getfield      #16                 // Field pageContext:Ljavax/servlet/jsp/PageContext;
     133: invokestatic  #17                 // Method org/apache/taglibs/standard/lang/support/ExpressionEvaluatorManager.evaluate:(Ljava/lang/String;Ljava/lang/String;Ljava/lang/Class;Ljavax/servlet/jsp/tagext/Tag;Ljavax/servlet/jsp/PageContext;)Ljava/lang/Object;
     136: astore_1
     137: aload_1
     138: ifnonnull     153
     141: new           #18                 // class org/apache/taglibs/standard/tag/common/core/NullAttributeException
     144: dup
     145: ldc           #19                 // String forTokens
     147: ldc           #27                 // String step
     149: invokespecial #20                 // Method org/apache/taglibs/standard/tag/common/core/NullAttributeException."<init>":(Ljava/lang/String;Ljava/lang/String;)V
     152: athrow
     153: aload_0
     154: aload_1
     155: checkcast     #15                 // class java/lang/Integer
     158: invokevirtual #21                 // Method java/lang/Integer.intValue:()I
     161: putfield      #28                 // Field step:I
     164: aload_0
     165: invokevirtual #29                 // Method validateStep:()V
     168: aload_0
     169: getfield      #12                 // Field items_:Ljava/lang/String;
     172: ifnull        212
     175: aload_0
     176: ldc           #30                 // String items
     178: aload_0
     179: getfield      #12                 // Field items_:Ljava/lang/String;
     182: ldc_w         #31                 // class java/lang/String
     185: aload_0
     186: aload_0
     187: getfield      #16                 // Field pageContext:Ljavax/servlet/jsp/PageContext;
     190: invokestatic  #17                 // Method org/apache/taglibs/standard/lang/support/ExpressionEvaluatorManager.evaluate:(Ljava/lang/String;Ljava/lang/String;Ljava/lang/Class;Ljavax/servlet/jsp/tagext/Tag;Ljavax/servlet/jsp/PageContext;)Ljava/lang/Object;
     193: checkcast     #31                 // class java/lang/String
     196: putfield      #32                 // Field items:Ljava/lang/Object;
     199: aload_0
     200: getfield      #32                 // Field items:Ljava/lang/Object;
     203: ifnonnull     212
     206: aload_0
     207: ldc           #33                 // String
     209: putfield      #32                 // Field items:Ljava/lang/Object;
     212: aload_0
     213: getfield      #13                 // Field delims_:Ljava/lang/String;
     216: ifnull        256
     219: aload_0
     220: ldc           #34                 // String delims
     222: aload_0
     223: getfield      #13                 // Field delims_:Ljava/lang/String;
     226: ldc_w         #31                 // class java/lang/String
     229: aload_0
     230: aload_0
     231: getfield      #16                 // Field pageContext:Ljavax/servlet/jsp/PageContext;
     234: invokestatic  #17                 // Method org/apache/taglibs/standard/lang/support/ExpressionEvaluatorManager.evaluate:(Ljava/lang/String;Ljava/lang/String;Ljava/lang/Class;Ljavax/servlet/jsp/tagext/Tag;Ljavax/servlet/jsp/PageContext;)Ljava/lang/Object;
     237: checkcast     #31                 // class java/lang/String
     240: putfield      #35                 // Field delims:Ljava/lang/String;
     243: aload_0
     244: getfield      #35                 // Field delims:Ljava/lang/String;
     247: ifnonnull     256
     250: aload_0
     251: ldc           #33                 // String
     253: putfield      #35                 // Field delims:Ljava/lang/String;
     256: return
}
