Compiled from "OutTag.java"
public class org.apache.taglibs.standard.tag.el.core.OutTag extends org.apache.taglibs.standard.tag.common.core.OutSupport {
  private java.lang.String valueExpression;

  private java.lang.String defaultExpression;

  private java.lang.String escapeXmlExpression;

  public org.apache.taglibs.standard.tag.el.core.OutTag();
    Code:
       0: aload_0
       1: invokespecial #1                  // Method org/apache/taglibs/standard/tag/common/core/OutSupport."<init>":()V
       4: return

  public void release();
    Code:
       0: aload_0
       1: aconst_null
       2: putfield      #2                  // Field valueExpression:Ljava/lang/String;
       5: aload_0
       6: aconst_null
       7: putfield      #3                  // Field defaultExpression:Ljava/lang/String;
      10: aload_0
      11: aconst_null
      12: putfield      #4                  // Field escapeXmlExpression:Ljava/lang/String;
      15: aload_0
      16: invokespecial #5                  // Method org/apache/taglibs/standard/tag/common/core/OutSupport.release:()V
      19: return

  public void setValue(java.lang.String);
    Code:
       0: aload_0
       1: aload_1
       2: putfield      #2                  // Field valueExpression:Ljava/lang/String;
       5: return

  public void setDefault(java.lang.String);
    Code:
       0: aload_0
       1: aload_1
       2: putfield      #3                  // Field defaultExpression:Ljava/lang/String;
       5: return

  public void setEscapeXml(java.lang.String);
    Code:
       0: aload_0
       1: aload_1
       2: putfield      #4                  // Field escapeXmlExpression:Ljava/lang/String;
       5: return

  protected java.lang.Object evalValue() throws javax.servlet.jsp.JspException;
    Code:
       0: aload_0
       1: getfield      #2                  // Field valueExpression:Ljava/lang/String;
       4: ifnonnull     9
       7: aconst_null
       8: areturn
       9: ldc           #6                  // String value
      11: aload_0
      12: getfield      #2                  // Field valueExpression:Ljava/lang/String;
      15: ldc_w         #7                  // class java/lang/Object
      18: aload_0
      19: aload_0
      20: getfield      #8                  // Field pageContext:Ljavax/servlet/jsp/PageContext;
      23: invokestatic  #9                  // Method org/apache/taglibs/standard/lang/support/ExpressionEvaluatorManager.evaluate:(Ljava/lang/String;Ljava/lang/String;Ljava/lang/Class;Ljavax/servlet/jsp/tagext/Tag;Ljavax/servlet/jsp/PageContext;)Ljava/lang/Object;
      26: areturn

  protected java.lang.String evalDefault() throws javax.servlet.jsp.JspException;
    Code:
       0: aload_0
       1: getfield      #3                  // Field defaultExpression:Ljava/lang/String;
       4: ifnonnull     9
       7: aconst_null
       8: areturn
       9: ldc           #10                 // String default
      11: aload_0
      12: getfield      #3                  // Field defaultExpression:Ljava/lang/String;
      15: ldc_w         #11                 // class java/lang/String
      18: aload_0
      19: aload_0
      20: getfield      #8                  // Field pageContext:Ljavax/servlet/jsp/PageContext;
      23: invokestatic  #9                  // Method org/apache/taglibs/standard/lang/support/ExpressionEvaluatorManager.evaluate:(Ljava/lang/String;Ljava/lang/String;Ljava/lang/Class;Ljavax/servlet/jsp/tagext/Tag;Ljavax/servlet/jsp/PageContext;)Ljava/lang/Object;
      26: checkcast     #11                 // class java/lang/String
      29: areturn

  protected boolean evalEscapeXml() throws javax.servlet.jsp.JspException;
    Code:
       0: aload_0
       1: getfield      #4                  // Field escapeXmlExpression:Ljava/lang/String;
       4: ifnonnull     9
       7: iconst_1
       8: ireturn
       9: ldc           #12                 // String escapeXml
      11: aload_0
      12: getfield      #4                  // Field escapeXmlExpression:Ljava/lang/String;
      15: ldc_w         #13                 // class java/lang/Boolean
      18: aload_0
      19: aload_0
      20: getfield      #8                  // Field pageContext:Ljavax/servlet/jsp/PageContext;
      23: invokestatic  #9                  // Method org/apache/taglibs/standard/lang/support/ExpressionEvaluatorManager.evaluate:(Ljava/lang/String;Ljava/lang/String;Ljava/lang/Class;Ljavax/servlet/jsp/tagext/Tag;Ljavax/servlet/jsp/PageContext;)Ljava/lang/Object;
      26: checkcast     #13                 // class java/lang/Boolean
      29: astore_1
      30: aload_1
      31: ifnonnull     36
      34: iconst_1
      35: ireturn
      36: aload_1
      37: invokevirtual #14                 // Method java/lang/Boolean.booleanValue:()Z
      40: ireturn
}
