Compiled from "Smartcardio.java"
public class jnasmartcardio.Smartcardio$JnaCardTerminal extends javax.smartcardio.CardTerminal {
  private final jnasmartcardio.Winscard$WinscardLibInfo libInfo;

  private final jnasmartcardio.Smartcardio$JnaCardTerminals cardTerminals;

  private final java.lang.String name;

  public static final int SCARD_SHARE_EXCLUSIVE;

  public static final int SCARD_SHARE_SHARED;

  public static final int SCARD_SHARE_DIRECT;

  public static final int SCARD_PROTOCOL_T0;

  public static final int SCARD_PROTOCOL_T1;

  public static final int SCARD_PROTOCOL_ANY;

  public static final int SCARD_UNKNOWN;

  public static final int SCARD_ABSENT;

  public static final int SCARD_PRESENT;

  public static final int SCARD_SWALLOWED;

  public static final int SCARD_POWERED;

  public static final int SCARD_NEGOTIABLE;

  public static final int SCARD_SPECIFIC;

  public jnasmartcardio.Smartcardio$JnaCardTerminal(jnasmartcardio.Winscard$WinscardLibInfo, jnasmartcardio.Smartcardio$JnaCardTerminals, java.lang.String);
    Code:
       0: aload_0
       1: invokespecial #3                  // Method javax/smartcardio/CardTerminal."<init>":()V
       4: aload_0
       5: aload_1
       6: putfield      #4                  // Field libInfo:Ljnasmartcardio/Winscard$WinscardLibInfo;
       9: aload_0
      10: aload_2
      11: putfield      #5                  // Field cardTerminals:Ljnasmartcardio/Smartcardio$JnaCardTerminals;
      14: aload_0
      15: aload_3
      16: putfield      #6                  // Field name:Ljava/lang/String;
      19: return

  public java.lang.String getName();
    Code:
       0: aload_0
       1: getfield      #6                  // Field name:Ljava/lang/String;
       4: areturn

  public javax.smartcardio.Card connect(java.lang.String) throws javax.smartcardio.CardException;
    Code:
       0: iconst_2
       1: istore_3
       2: aload_1
       3: invokevirtual #7                  // Method java/lang/String.toUpperCase:()Ljava/lang/String;
       6: astore_1
       7: aload_1
       8: ldc           #8                  // String EXCLUSIVE;
      10: invokevirtual #9                  // Method java/lang/String.startsWith:(Ljava/lang/String;)Z
      13: ifeq          28
      16: iconst_1
      17: istore_3
      18: aload_1
      19: ldc           #8                  // String EXCLUSIVE;
      21: invokevirtual #10                 // Method java/lang/String.length:()I
      24: invokevirtual #11                 // Method java/lang/String.substring:(I)Ljava/lang/String;
      27: astore_1
      28: ldc           #12                 // String T=0
      30: aload_1
      31: invokevirtual #13                 // Method java/lang/String.equals:(Ljava/lang/Object;)Z
      34: ifeq          42
      37: iconst_1
      38: istore_2
      39: goto          121
      42: ldc           #14                 // String T=1
      44: aload_1
      45: invokevirtual #13                 // Method java/lang/String.equals:(Ljava/lang/Object;)Z
      48: ifeq          56
      51: iconst_2
      52: istore_2
      53: goto          121
      56: ldc           #15                 // String *
      58: aload_1
      59: invokevirtual #13                 // Method java/lang/String.equals:(Ljava/lang/Object;)Z
      62: ifeq          70
      65: iconst_3
      66: istore_2
      67: goto          121
      70: ldc           #16                 // String DIRECT
      72: aload_1
      73: invokevirtual #17                 // Method java/lang/String.equalsIgnoreCase:(Ljava/lang/String;)Z
      76: ifeq          94
      79: iconst_0
      80: istore_2
      81: invokestatic  #18                 // Method com/sun/jna/Platform.isMac:()Z
      84: ifeq          89
      87: iconst_3
      88: istore_2
      89: iconst_3
      90: istore_3
      91: goto          121
      94: new           #19                 // class java/lang/IllegalArgumentException
      97: dup
      98: new           #20                 // class java/lang/StringBuilder
     101: dup
     102: invokespecial #21                 // Method java/lang/StringBuilder."<init>":()V
     105: ldc           #22                 // String Protocol should be one of (prepended with EXCLUSIVE;) T=0, T=1, *, DIRECT. Got
     107: invokevirtual #23                 // Method java/lang/StringBuilder.append:(Ljava/lang/String;)Ljava/lang/StringBuilder;
     110: aload_1
     111: invokevirtual #23                 // Method java/lang/StringBuilder.append:(Ljava/lang/String;)Ljava/lang/StringBuilder;
     114: invokevirtual #24                 // Method java/lang/StringBuilder.toString:()Ljava/lang/String;
     117: invokespecial #25                 // Method java/lang/IllegalArgumentException."<init>":(Ljava/lang/String;)V
     120: athrow
     121: new           #26                 // class jnasmartcardio/Winscard$SCardHandleByReference
     124: dup
     125: invokespecial #27                 // Method jnasmartcardio/Winscard$SCardHandleByReference."<init>":()V
     128: astore        4
     130: new           #28                 // class jnasmartcardio/Winscard$DwordByReference
     133: dup
     134: invokespecial #29                 // Method jnasmartcardio/Winscard$DwordByReference."<init>":()V
     137: astore        5
     139: aload_0
     140: getfield      #4                  // Field libInfo:Ljnasmartcardio/Winscard$WinscardLibInfo;
     143: getfield      #30                 // Field jnasmartcardio/Winscard$WinscardLibInfo.lib:Ljnasmartcardio/Winscard$WinscardLibrary;
     146: aload_0
     147: getfield      #5                  // Field cardTerminals:Ljnasmartcardio/Smartcardio$JnaCardTerminals;
     150: invokestatic  #31                 // Method jnasmartcardio/Smartcardio$JnaCardTerminals.access$300:(Ljnasmartcardio/Smartcardio$JnaCardTerminals;)Ljnasmartcardio/Winscard$SCardContext;
     153: aload_0
     154: getfield      #6                  // Field name:Ljava/lang/String;
     157: new           #32                 // class jnasmartcardio/Winscard$Dword
     160: dup
     161: iload_3
     162: i2l
     163: invokespecial #33                 // Method jnasmartcardio/Winscard$Dword."<init>":(J)V
     166: new           #32                 // class jnasmartcardio/Winscard$Dword
     169: dup
     170: iload_2
     171: i2l
     172: invokespecial #33                 // Method jnasmartcardio/Winscard$Dword."<init>":(J)V
     175: aload         4
     177: aload         5
     179: invokeinterface #34,  7           // InterfaceMethod jnasmartcardio/Winscard$WinscardLibrary.SCardConnect:(Ljnasmartcardio/Winscard$SCardContext;Ljava/lang/String;Ljnasmartcardio/Winscard$Dword;Ljnasmartcardio/Winscard$Dword;Ljnasmartcardio/Winscard$SCardHandleByReference;Ljnasmartcardio/Winscard$DwordByReference;)Ljnasmartcardio/Winscard$Dword;
     184: invokevirtual #35                 // Method jnasmartcardio/Winscard$Dword.longValue:()J
     187: lstore        6
     189: lload         6
     191: l2i
     192: lookupswitch  { // 2
           -2146434967: 385
                     0: 220
               default: 397
          }
     220: aload         4
     222: invokevirtual #36                 // Method jnasmartcardio/Winscard$SCardHandleByReference.getValue:()Ljnasmartcardio/Winscard$SCardHandle;
     225: astore        8
     227: new           #28                 // class jnasmartcardio/Winscard$DwordByReference
     230: dup
     231: invokespecial #29                 // Method jnasmartcardio/Winscard$DwordByReference."<init>":()V
     234: astore        9
     236: new           #28                 // class jnasmartcardio/Winscard$DwordByReference
     239: dup
     240: invokespecial #29                 // Method jnasmartcardio/Winscard$DwordByReference."<init>":()V
     243: astore        10
     245: new           #28                 // class jnasmartcardio/Winscard$DwordByReference
     248: dup
     249: invokespecial #29                 // Method jnasmartcardio/Winscard$DwordByReference."<init>":()V
     252: astore        11
     254: bipush        33
     256: invokestatic  #37                 // Method java/nio/ByteBuffer.allocate:(I)Ljava/nio/ByteBuffer;
     259: astore        12
     261: new           #28                 // class jnasmartcardio/Winscard$DwordByReference
     264: dup
     265: new           #32                 // class jnasmartcardio/Winscard$Dword
     268: dup
     269: ldc2_w        #38                 // long 33l
     272: invokespecial #33                 // Method jnasmartcardio/Winscard$Dword."<init>":(J)V
     275: invokespecial #40                 // Method jnasmartcardio/Winscard$DwordByReference."<init>":(Ljnasmartcardio/Winscard$Dword;)V
     278: astore        13
     280: ldc           #41                 // String SCardStatus
     282: aload_0
     283: getfield      #4                  // Field libInfo:Ljnasmartcardio/Winscard$WinscardLibInfo;
     286: getfield      #30                 // Field jnasmartcardio/Winscard$WinscardLibInfo.lib:Ljnasmartcardio/Winscard$WinscardLibrary;
     289: aload         8
     291: aconst_null
     292: aload         9
     294: aload         10
     296: aload         11
     298: aload         12
     300: aload         13
     302: invokeinterface #42,  8           // InterfaceMethod jnasmartcardio/Winscard$WinscardLibrary.SCardStatus:(Ljnasmartcardio/Winscard$SCardHandle;Ljava/nio/ByteBuffer;Ljnasmartcardio/Winscard$DwordByReference;Ljnasmartcardio/Winscard$DwordByReference;Ljnasmartcardio/Winscard$DwordByReference;Ljava/nio/ByteBuffer;Ljnasmartcardio/Winscard$DwordByReference;)Ljnasmartcardio/Winscard$Dword;
     307: invokestatic  #43                 // Method jnasmartcardio/Smartcardio.access$000:(Ljava/lang/String;Ljnasmartcardio/Winscard$Dword;)V
     310: aload         13
     312: invokevirtual #44                 // Method jnasmartcardio/Winscard$DwordByReference.getValue:()Ljnasmartcardio/Winscard$Dword;
     315: invokevirtual #45                 // Method jnasmartcardio/Winscard$Dword.intValue:()I
     318: istore        14
     320: aload         12
     322: iload         14
     324: invokevirtual #46                 // Method java/nio/ByteBuffer.limit:(I)Ljava/nio/Buffer;
     327: pop
     328: aload         12
     330: invokevirtual #47                 // Method java/nio/ByteBuffer.remaining:()I
     333: newarray       byte
     335: astore        15
     337: aload         12
     339: aload         15
     341: invokevirtual #48                 // Method java/nio/ByteBuffer.get:([B)Ljava/nio/ByteBuffer;
     344: pop
     345: new           #49                 // class javax/smartcardio/ATR
     348: dup
     349: aload         15
     351: invokespecial #50                 // Method javax/smartcardio/ATR."<init>":([B)V
     354: astore        16
     356: aload         11
     358: invokevirtual #44                 // Method jnasmartcardio/Winscard$DwordByReference.getValue:()Ljnasmartcardio/Winscard$Dword;
     361: invokevirtual #45                 // Method jnasmartcardio/Winscard$Dword.intValue:()I
     364: istore        17
     366: new           #51                 // class jnasmartcardio/Smartcardio$JnaCard
     369: dup
     370: aload_0
     371: getfield      #4                  // Field libInfo:Ljnasmartcardio/Winscard$WinscardLibInfo;
     374: aload_0
     375: aload         8
     377: aload         16
     379: iload         17
     381: invokespecial #52                 // Method jnasmartcardio/Smartcardio$JnaCard."<init>":(Ljnasmartcardio/Winscard$WinscardLibInfo;Ljnasmartcardio/Smartcardio$JnaCardTerminal;Ljnasmartcardio/Winscard$SCardHandle;Ljavax/smartcardio/ATR;I)V
     384: areturn
     385: new           #53                 // class jnasmartcardio/Smartcardio$JnaCardNotPresentException
     388: dup
     389: lload         6
     391: ldc           #54                 // String Card not present.
     393: invokespecial #55                 // Method jnasmartcardio/Smartcardio$JnaCardNotPresentException."<init>":(JLjava/lang/String;)V
     396: athrow
     397: ldc           #56                 // String SCardConnect
     399: lload         6
     401: invokestatic  #57                 // Method jnasmartcardio/Smartcardio.access$200:(Ljava/lang/String;J)V
     404: new           #58                 // class java/lang/RuntimeException
     407: dup
     408: ldc           #59                 // String Should not reach here.
     410: invokespecial #60                 // Method java/lang/RuntimeException."<init>":(Ljava/lang/String;)V
     413: athrow

  public boolean isCardPresent() throws javax.smartcardio.CardException;
    Code:
       0: iconst_1
       1: anewarray     #61                 // class jnasmartcardio/Winscard$SCardReaderState
       4: astore_1
       5: new           #61                 // class jnasmartcardio/Winscard$SCardReaderState
       8: dup
       9: invokespecial #62                 // Method jnasmartcardio/Winscard$SCardReaderState."<init>":()V
      12: aload_1
      13: checkcast     #63                 // class "[Lcom/sun/jna/Structure;"
      16: invokevirtual #64                 // Method jnasmartcardio/Winscard$SCardReaderState.toArray:([Lcom/sun/jna/Structure;)[Lcom/sun/jna/Structure;
      19: pop
      20: aload_1
      21: iconst_0
      22: aaload
      23: aload_0
      24: getfield      #6                  // Field name:Ljava/lang/String;
      27: putfield      #65                 // Field jnasmartcardio/Winscard$SCardReaderState.szReader:Ljava/lang/String;
      30: aload_1
      31: iconst_0
      32: aaload
      33: astore_2
      34: ldc           #66                 // String SCardGetStatusChange
      36: aload_0
      37: getfield      #4                  // Field libInfo:Ljnasmartcardio/Winscard$WinscardLibInfo;
      40: getfield      #30                 // Field jnasmartcardio/Winscard$WinscardLibInfo.lib:Ljnasmartcardio/Winscard$WinscardLibrary;
      43: aload_0
      44: getfield      #5                  // Field cardTerminals:Ljnasmartcardio/Smartcardio$JnaCardTerminals;
      47: invokestatic  #31                 // Method jnasmartcardio/Smartcardio$JnaCardTerminals.access$300:(Ljnasmartcardio/Smartcardio$JnaCardTerminals;)Ljnasmartcardio/Winscard$SCardContext;
      50: new           #32                 // class jnasmartcardio/Winscard$Dword
      53: dup
      54: lconst_0
      55: invokespecial #33                 // Method jnasmartcardio/Winscard$Dword."<init>":(J)V
      58: aload_1
      59: new           #32                 // class jnasmartcardio/Winscard$Dword
      62: dup
      63: aload_1
      64: arraylength
      65: i2l
      66: invokespecial #33                 // Method jnasmartcardio/Winscard$Dword."<init>":(J)V
      69: invokeinterface #67,  5           // InterfaceMethod jnasmartcardio/Winscard$WinscardLibrary.SCardGetStatusChange:(Ljnasmartcardio/Winscard$SCardContext;Ljnasmartcardio/Winscard$Dword;[Ljnasmartcardio/Winscard$SCardReaderState;Ljnasmartcardio/Winscard$Dword;)Ljnasmartcardio/Winscard$Dword;
      74: invokestatic  #43                 // Method jnasmartcardio/Smartcardio.access$000:(Ljava/lang/String;Ljnasmartcardio/Winscard$Dword;)V
      77: iconst_0
      78: aload_2
      79: getfield      #68                 // Field jnasmartcardio/Winscard$SCardReaderState.dwEventState:Ljnasmartcardio/Winscard$Dword;
      82: invokevirtual #45                 // Method jnasmartcardio/Winscard$Dword.intValue:()I
      85: bipush        32
      87: iand
      88: if_icmpeq     95
      91: iconst_1
      92: goto          96
      95: iconst_0
      96: ireturn

  private boolean waitHelper(long, boolean) throws jnasmartcardio.Smartcardio$JnaPCSCException;
    Code:
       0: lload_1
       1: lconst_0
       2: lcmp
       3: ifge          33
       6: new           #19                 // class java/lang/IllegalArgumentException
       9: dup
      10: new           #20                 // class java/lang/StringBuilder
      13: dup
      14: invokespecial #21                 // Method java/lang/StringBuilder."<init>":()V
      17: ldc           #70                 // String Negative timeout
      19: invokevirtual #23                 // Method java/lang/StringBuilder.append:(Ljava/lang/String;)Ljava/lang/StringBuilder;
      22: lload_1
      23: invokevirtual #71                 // Method java/lang/StringBuilder.append:(J)Ljava/lang/StringBuilder;
      26: invokevirtual #24                 // Method java/lang/StringBuilder.toString:()Ljava/lang/String;
      29: invokespecial #25                 // Method java/lang/IllegalArgumentException."<init>":(Ljava/lang/String;)V
      32: athrow
      33: lload_1
      34: lconst_0
      35: lcmp
      36: ifne          43
      39: ldc2_w        #72                 // long -1l
      42: lstore_1
      43: iconst_1
      44: anewarray     #61                 // class jnasmartcardio/Winscard$SCardReaderState
      47: astore        4
      49: new           #61                 // class jnasmartcardio/Winscard$SCardReaderState
      52: dup
      53: invokespecial #62                 // Method jnasmartcardio/Winscard$SCardReaderState."<init>":()V
      56: aload         4
      58: checkcast     #63                 // class "[Lcom/sun/jna/Structure;"
      61: invokevirtual #64                 // Method jnasmartcardio/Winscard$SCardReaderState.toArray:([Lcom/sun/jna/Structure;)[Lcom/sun/jna/Structure;
      64: pop
      65: aload         4
      67: iconst_0
      68: aaload
      69: astore        5
      71: aload         5
      73: aload_0
      74: getfield      #6                  // Field name:Ljava/lang/String;
      77: putfield      #65                 // Field jnasmartcardio/Winscard$SCardReaderState.szReader:Ljava/lang/String;
      80: ldc           #66                 // String SCardGetStatusChange
      82: aload_0
      83: getfield      #4                  // Field libInfo:Ljnasmartcardio/Winscard$WinscardLibInfo;
      86: getfield      #30                 // Field jnasmartcardio/Winscard$WinscardLibInfo.lib:Ljnasmartcardio/Winscard$WinscardLibrary;
      89: aload_0
      90: getfield      #5                  // Field cardTerminals:Ljnasmartcardio/Smartcardio$JnaCardTerminals;
      93: invokestatic  #31                 // Method jnasmartcardio/Smartcardio$JnaCardTerminals.access$300:(Ljnasmartcardio/Smartcardio$JnaCardTerminals;)Ljnasmartcardio/Winscard$SCardContext;
      96: new           #32                 // class jnasmartcardio/Winscard$Dword
      99: dup
     100: lconst_0
     101: invokespecial #33                 // Method jnasmartcardio/Winscard$Dword."<init>":(J)V
     104: aload         4
     106: new           #32                 // class jnasmartcardio/Winscard$Dword
     109: dup
     110: aload         4
     112: arraylength
     113: i2l
     114: invokespecial #33                 // Method jnasmartcardio/Winscard$Dword."<init>":(J)V
     117: invokeinterface #67,  5           // InterfaceMethod jnasmartcardio/Winscard$WinscardLibrary.SCardGetStatusChange:(Ljnasmartcardio/Winscard$SCardContext;Ljnasmartcardio/Winscard$Dword;[Ljnasmartcardio/Winscard$SCardReaderState;Ljnasmartcardio/Winscard$Dword;)Ljnasmartcardio/Winscard$Dword;
     122: invokestatic  #43                 // Method jnasmartcardio/Smartcardio.access$000:(Ljava/lang/String;Ljnasmartcardio/Winscard$Dword;)V
     125: lload_1
     126: l2i
     127: istore        6
     129: iload_3
     130: iconst_0
     131: aload         5
     133: getfield      #68                 // Field jnasmartcardio/Winscard$SCardReaderState.dwEventState:Ljnasmartcardio/Winscard$Dword;
     136: invokevirtual #45                 // Method jnasmartcardio/Winscard$Dword.intValue:()I
     139: bipush        32
     141: iand
     142: if_icmpeq     149
     145: iconst_1
     146: goto          150
     149: iconst_0
     150: if_icmpeq     284
     153: aload         5
     155: aload         5
     157: getfield      #68                 // Field jnasmartcardio/Winscard$SCardReaderState.dwEventState:Ljnasmartcardio/Winscard$Dword;
     160: putfield      #74                 // Field jnasmartcardio/Winscard$SCardReaderState.dwCurrentState:Ljnasmartcardio/Winscard$Dword;
     163: aload         5
     165: new           #32                 // class jnasmartcardio/Winscard$Dword
     168: dup
     169: lconst_0
     170: invokespecial #33                 // Method jnasmartcardio/Winscard$Dword."<init>":(J)V
     173: putfield      #68                 // Field jnasmartcardio/Winscard$SCardReaderState.dwEventState:Ljnasmartcardio/Winscard$Dword;
     176: invokestatic  #75                 // Method java/lang/System.currentTimeMillis:()J
     179: lstore        7
     181: aload_0
     182: getfield      #4                  // Field libInfo:Ljnasmartcardio/Winscard$WinscardLibInfo;
     185: getfield      #30                 // Field jnasmartcardio/Winscard$WinscardLibInfo.lib:Ljnasmartcardio/Winscard$WinscardLibrary;
     188: aload_0
     189: getfield      #5                  // Field cardTerminals:Ljnasmartcardio/Smartcardio$JnaCardTerminals;
     192: invokestatic  #31                 // Method jnasmartcardio/Smartcardio$JnaCardTerminals.access$300:(Ljnasmartcardio/Smartcardio$JnaCardTerminals;)Ljnasmartcardio/Winscard$SCardContext;
     195: new           #32                 // class jnasmartcardio/Winscard$Dword
     198: dup
     199: iload         6
     201: i2l
     202: invokespecial #33                 // Method jnasmartcardio/Winscard$Dword."<init>":(J)V
     205: aload         4
     207: new           #32                 // class jnasmartcardio/Winscard$Dword
     210: dup
     211: aload         4
     213: arraylength
     214: i2l
     215: invokespecial #33                 // Method jnasmartcardio/Winscard$Dword."<init>":(J)V
     218: invokeinterface #67,  5           // InterfaceMethod jnasmartcardio/Winscard$WinscardLibrary.SCardGetStatusChange:(Ljnasmartcardio/Winscard$SCardContext;Ljnasmartcardio/Winscard$Dword;[Ljnasmartcardio/Winscard$SCardReaderState;Ljnasmartcardio/Winscard$Dword;)Ljnasmartcardio/Winscard$Dword;
     223: astore        9
     225: invokestatic  #75                 // Method java/lang/System.currentTimeMillis:()J
     228: lstore        10
     230: ldc           #76                 // int -2146435062
     232: aload         9
     234: invokevirtual #45                 // Method jnasmartcardio/Winscard$Dword.intValue:()I
     237: if_icmpne     242
     240: iconst_0
     241: ireturn
     242: ldc           #66                 // String SCardGetStatusChange
     244: aload         9
     246: invokestatic  #43                 // Method jnasmartcardio/Smartcardio.access$000:(Ljava/lang/String;Ljnasmartcardio/Winscard$Dword;)V
     249: iload         6
     251: iconst_m1
     252: if_icmpeq     281
     255: iload         6
     257: i2l
     258: lload         10
     260: lload         7
     262: lsub
     263: lcmp
     264: ifge          269
     267: iconst_0
     268: ireturn
     269: iload         6
     271: i2l
     272: lload         10
     274: lload         7
     276: lsub
     277: lsub
     278: l2i
     279: istore        6
     281: goto          129
     284: iconst_1
     285: ireturn

  public boolean waitForCardAbsent(long) throws javax.smartcardio.CardException;
    Code:
       0: aload_0
       1: lload_1
       2: iconst_0
       3: invokespecial #77                 // Method waitHelper:(JZ)Z
       6: ireturn

  public boolean waitForCardPresent(long) throws javax.smartcardio.CardException;
    Code:
       0: aload_0
       1: lload_1
       2: iconst_1
       3: invokespecial #77                 // Method waitHelper:(JZ)Z
       6: ireturn

  public java.lang.String toString();
    Code:
       0: ldc           #78                 // String %s{scardHandle=%s, name=%s}
       2: iconst_3
       3: anewarray     #79                 // class java/lang/Object
       6: dup
       7: iconst_0
       8: aload_0
       9: invokevirtual #80                 // Method java/lang/Object.getClass:()Ljava/lang/Class;
      12: invokevirtual #81                 // Method java/lang/Class.getSimpleName:()Ljava/lang/String;
      15: aastore
      16: dup
      17: iconst_1
      18: aload_0
      19: getfield      #5                  // Field cardTerminals:Ljnasmartcardio/Smartcardio$JnaCardTerminals;
      22: invokestatic  #31                 // Method jnasmartcardio/Smartcardio$JnaCardTerminals.access$300:(Ljnasmartcardio/Smartcardio$JnaCardTerminals;)Ljnasmartcardio/Winscard$SCardContext;
      25: aastore
      26: dup
      27: iconst_2
      28: aload_0
      29: getfield      #6                  // Field name:Ljava/lang/String;
      32: aastore
      33: invokestatic  #82                 // Method java/lang/String.format:(Ljava/lang/String;[Ljava/lang/Object;)Ljava/lang/String;
      36: areturn
}
