Compiled from "DropIndex.java"
public class org.h2.command.ddl.DropIndex extends org.h2.command.ddl.SchemaCommand {
  private java.lang.String indexName;

  private boolean ifExists;

  public org.h2.command.ddl.DropIndex(org.h2.engine.Session, org.h2.schema.Schema);
    Code:
       0: aload_0
       1: aload_1
       2: aload_2
       3: invokespecial #1                  // Method org/h2/command/ddl/SchemaCommand."<init>":(Lorg/h2/engine/Session;Lorg/h2/schema/Schema;)V
       6: return

  public void setIfExists(boolean);
    Code:
       0: aload_0
       1: iload_1
       2: putfield      #2                  // Field ifExists:Z
       5: return

  public void setIndexName(java.lang.String);
    Code:
       0: aload_0
       1: aload_1
       2: putfield      #3                  // Field indexName:Ljava/lang/String;
       5: return

  public int update();
    Code:
       0: aload_0
       1: getfield      #4                  // Field session:Lorg/h2/engine/Session;
       4: iconst_1
       5: invokevirtual #5                  // Method org/h2/engine/Session.commit:(Z)V
       8: aload_0
       9: getfield      #4                  // Field session:Lorg/h2/engine/Session;
      12: invokevirtual #6                  // Method org/h2/engine/Session.getDatabase:()Lorg/h2/engine/Database;
      15: astore_1
      16: aload_0
      17: invokevirtual #7                  // Method getSchema:()Lorg/h2/schema/Schema;
      20: aload_0
      21: getfield      #4                  // Field session:Lorg/h2/engine/Session;
      24: aload_0
      25: getfield      #3                  // Field indexName:Ljava/lang/String;
      28: invokevirtual #8                  // Method org/h2/schema/Schema.findIndex:(Lorg/h2/engine/Session;Ljava/lang/String;)Lorg/h2/index/Index;
      31: astore_2
      32: aload_2
      33: ifnonnull     53
      36: aload_0
      37: getfield      #2                  // Field ifExists:Z
      40: ifne          211
      43: ldc           #9                  // int 42112
      45: aload_0
      46: getfield      #3                  // Field indexName:Ljava/lang/String;
      49: invokestatic  #10                 // Method org/h2/message/DbException.get:(ILjava/lang/String;)Lorg/h2/message/DbException;
      52: athrow
      53: aload_2
      54: invokeinterface #11,  1           // InterfaceMethod org/h2/index/Index.getTable:()Lorg/h2/table/Table;
      59: astore_3
      60: aload_0
      61: getfield      #4                  // Field session:Lorg/h2/engine/Session;
      64: invokevirtual #12                 // Method org/h2/engine/Session.getUser:()Lorg/h2/engine/User;
      67: aload_2
      68: invokeinterface #11,  1           // InterfaceMethod org/h2/index/Index.getTable:()Lorg/h2/table/Table;
      73: bipush        15
      75: invokevirtual #13                 // Method org/h2/engine/User.checkRight:(Lorg/h2/table/Table;I)V
      78: aconst_null
      79: astore        4
      81: aload_3
      82: invokevirtual #14                 // Method org/h2/table/Table.getConstraints:()Ljava/util/ArrayList;
      85: astore        5
      87: iconst_0
      88: istore        6
      90: aload         5
      92: ifnull        175
      95: iload         6
      97: aload         5
      99: invokevirtual #15                 // Method java/util/ArrayList.size:()I
     102: if_icmpge     175
     105: aload         5
     107: iload         6
     109: invokevirtual #16                 // Method java/util/ArrayList.get:(I)Ljava/lang/Object;
     112: checkcast     #17                 // class org/h2/constraint/Constraint
     115: astore        7
     117: aload         7
     119: aload_2
     120: invokevirtual #18                 // Method org/h2/constraint/Constraint.usesIndex:(Lorg/h2/index/Index;)Z
     123: ifeq          169
     126: getstatic     #19                 // Field org/h2/constraint/Constraint$Type.PRIMARY_KEY:Lorg/h2/constraint/Constraint$Type;
     129: aload         7
     131: invokevirtual #20                 // Method org/h2/constraint/Constraint.getConstraintType:()Lorg/h2/constraint/Constraint$Type;
     134: if_acmpne     144
     137: aload         7
     139: astore        4
     141: goto          169
     144: ldc           #21                 // int 90085
     146: iconst_2
     147: anewarray     #22                 // class java/lang/String
     150: dup
     151: iconst_0
     152: aload_0
     153: getfield      #3                  // Field indexName:Ljava/lang/String;
     156: aastore
     157: dup
     158: iconst_1
     159: aload         7
     161: invokevirtual #23                 // Method org/h2/constraint/Constraint.getName:()Ljava/lang/String;
     164: aastore
     165: invokestatic  #24                 // Method org/h2/message/DbException.get:(I[Ljava/lang/String;)Lorg/h2/message/DbException;
     168: athrow
     169: iinc          6, 1
     172: goto          90
     175: aload_2
     176: invokeinterface #11,  1           // InterfaceMethod org/h2/index/Index.getTable:()Lorg/h2/table/Table;
     181: invokevirtual #25                 // Method org/h2/table/Table.setModified:()V
     184: aload         4
     186: ifnull        202
     189: aload_1
     190: aload_0
     191: getfield      #4                  // Field session:Lorg/h2/engine/Session;
     194: aload         4
     196: invokevirtual #26                 // Method org/h2/engine/Database.removeSchemaObject:(Lorg/h2/engine/Session;Lorg/h2/schema/SchemaObject;)V
     199: goto          211
     202: aload_1
     203: aload_0
     204: getfield      #4                  // Field session:Lorg/h2/engine/Session;
     207: aload_2
     208: invokevirtual #26                 // Method org/h2/engine/Database.removeSchemaObject:(Lorg/h2/engine/Session;Lorg/h2/schema/SchemaObject;)V
     211: iconst_0
     212: ireturn

  public int getType();
    Code:
       0: bipush        40
       2: ireturn
}
