Compiled from "H2ConsoleAutoConfiguration.java"
public class org.springframework.boot.autoconfigure.h2.H2ConsoleAutoConfiguration {
  private final org.springframework.boot.autoconfigure.h2.H2ConsoleProperties properties;

  public org.springframework.boot.autoconfigure.h2.H2ConsoleAutoConfiguration(org.springframework.boot.autoconfigure.h2.H2ConsoleProperties);
    Code:
       0: aload_0
       1: invokespecial #1                  // Method java/lang/Object."<init>":()V
       4: aload_0
       5: aload_1
       6: putfield      #2                  // Field properties:Lorg/springframework/boot/autoconfigure/h2/H2ConsoleProperties;
       9: return

  public org.springframework.boot.web.servlet.ServletRegistrationBean h2Console();
    Code:
       0: aload_0
       1: getfield      #2                  // Field properties:Lorg/springframework/boot/autoconfigure/h2/H2ConsoleProperties;
       4: invokevirtual #3                  // Method org/springframework/boot/autoconfigure/h2/H2ConsoleProperties.getPath:()Ljava/lang/String;
       7: astore_1
       8: aload_1
       9: ldc           #4                  // String /
      11: invokevirtual #5                  // Method java/lang/String.endsWith:(Ljava/lang/String;)Z
      14: ifeq          39
      17: new           #6                  // class java/lang/StringBuilder
      20: dup
      21: invokespecial #7                  // Method java/lang/StringBuilder."<init>":()V
      24: aload_1
      25: invokevirtual #8                  // Method java/lang/StringBuilder.append:(Ljava/lang/String;)Ljava/lang/StringBuilder;
      28: ldc           #9                  // String *
      30: invokevirtual #8                  // Method java/lang/StringBuilder.append:(Ljava/lang/String;)Ljava/lang/StringBuilder;
      33: invokevirtual #10                 // Method java/lang/StringBuilder.toString:()Ljava/lang/String;
      36: goto          58
      39: new           #6                  // class java/lang/StringBuilder
      42: dup
      43: invokespecial #7                  // Method java/lang/StringBuilder."<init>":()V
      46: aload_1
      47: invokevirtual #8                  // Method java/lang/StringBuilder.append:(Ljava/lang/String;)Ljava/lang/StringBuilder;
      50: ldc           #11                 // String /*
      52: invokevirtual #8                  // Method java/lang/StringBuilder.append:(Ljava/lang/String;)Ljava/lang/StringBuilder;
      55: invokevirtual #10                 // Method java/lang/StringBuilder.toString:()Ljava/lang/String;
      58: astore_2
      59: new           #12                 // class org/springframework/boot/web/servlet/ServletRegistrationBean
      62: dup
      63: new           #13                 // class org/h2/server/web/WebServlet
      66: dup
      67: invokespecial #14                 // Method org/h2/server/web/WebServlet."<init>":()V
      70: iconst_1
      71: anewarray     #15                 // class java/lang/String
      74: dup
      75: iconst_0
      76: aload_2
      77: aastore
      78: invokespecial #16                 // Method org/springframework/boot/web/servlet/ServletRegistrationBean."<init>":(Ljavax/servlet/Servlet;[Ljava/lang/String;)V
      81: astore_3
      82: aload_0
      83: getfield      #2                  // Field properties:Lorg/springframework/boot/autoconfigure/h2/H2ConsoleProperties;
      86: invokevirtual #17                 // Method org/springframework/boot/autoconfigure/h2/H2ConsoleProperties.getSettings:()Lorg/springframework/boot/autoconfigure/h2/H2ConsoleProperties$Settings;
      89: astore        4
      91: aload         4
      93: invokevirtual #18                 // Method org/springframework/boot/autoconfigure/h2/H2ConsoleProperties$Settings.isTrace:()Z
      96: ifeq          107
      99: aload_3
     100: ldc           #19                 // String trace
     102: ldc           #20                 // String
     104: invokevirtual #21                 // Method org/springframework/boot/web/servlet/ServletRegistrationBean.addInitParameter:(Ljava/lang/String;Ljava/lang/String;)V
     107: aload         4
     109: invokevirtual #22                 // Method org/springframework/boot/autoconfigure/h2/H2ConsoleProperties$Settings.isWebAllowOthers:()Z
     112: ifeq          123
     115: aload_3
     116: ldc           #23                 // String webAllowOthers
     118: ldc           #20                 // String
     120: invokevirtual #21                 // Method org/springframework/boot/web/servlet/ServletRegistrationBean.addInitParameter:(Ljava/lang/String;Ljava/lang/String;)V
     123: aload_3
     124: areturn
}
