Compiled from "ModelFunction.java"
public class org.apache.commons.math3.optim.nonlinear.vector.ModelFunction implements org.apache.commons.math3.optim.OptimizationData {
  private final org.apache.commons.math3.analysis.MultivariateVectorFunction model;

  public org.apache.commons.math3.optim.nonlinear.vector.ModelFunction(org.apache.commons.math3.analysis.MultivariateVectorFunction);
    Code:
       0: aload_0
       1: invokespecial #1                  // Method java/lang/Object."<init>":()V
       4: aload_0
       5: aload_1
       6: putfield      #2                  // Field model:Lorg/apache/commons/math3/analysis/MultivariateVectorFunction;
       9: return

  public org.apache.commons.math3.analysis.MultivariateVectorFunction getModelFunction();
    Code:
       0: aload_0
       1: getfield      #2                  // Field model:Lorg/apache/commons/math3/analysis/MultivariateVectorFunction;
       4: areturn
}
