Compiled from "JsonLdProcessor.java"
public class com.github.jsonldjava.core.JsonLdProcessor {
  private static java.util.Map<java.lang.String, com.github.jsonldjava.core.RDFParser> rdfParsers;

  public com.github.jsonldjava.core.JsonLdProcessor();
    Code:
       0: aload_0
       1: invokespecial #1                  // Method java/lang/Object."<init>":()V
       4: return

  public static java.util.Map<java.lang.String, java.lang.Object> compact(java.lang.Object, java.lang.Object, com.github.jsonldjava.core.JsonLdOptions) throws com.github.jsonldjava.core.JsonLdError;
    Code:
       0: aload_0
       1: aload_2
       2: invokestatic  #2                  // Method expand:(Ljava/lang/Object;Lcom/github/jsonldjava/core/JsonLdOptions;)Ljava/util/List;
       5: astore_3
       6: aload_1
       7: instanceof    #3                  // class java/util/Map
      10: ifeq          39
      13: aload_1
      14: checkcast     #3                  // class java/util/Map
      17: ldc           #5                  // String @context
      19: invokeinterface #6,  2            // InterfaceMethod java/util/Map.containsKey:(Ljava/lang/Object;)Z
      24: ifeq          39
      27: aload_1
      28: checkcast     #3                  // class java/util/Map
      31: ldc           #5                  // String @context
      33: invokeinterface #7,  2            // InterfaceMethod java/util/Map.get:(Ljava/lang/Object;)Ljava/lang/Object;
      38: astore_1
      39: new           #8                  // class com/github/jsonldjava/core/Context
      42: dup
      43: aload_2
      44: invokespecial #9                  // Method com/github/jsonldjava/core/Context."<init>":(Lcom/github/jsonldjava/core/JsonLdOptions;)V
      47: astore        4
      49: aload         4
      51: aload_1
      52: invokevirtual #10                 // Method com/github/jsonldjava/core/Context.parse:(Ljava/lang/Object;)Lcom/github/jsonldjava/core/Context;
      55: astore        4
      57: new           #11                 // class com/github/jsonldjava/core/JsonLdApi
      60: dup
      61: aload_2
      62: invokespecial #12                 // Method com/github/jsonldjava/core/JsonLdApi."<init>":(Lcom/github/jsonldjava/core/JsonLdOptions;)V
      65: aload         4
      67: aconst_null
      68: aload_3
      69: aload_2
      70: invokevirtual #13                 // Method com/github/jsonldjava/core/JsonLdOptions.getCompactArrays:()Ljava/lang/Boolean;
      73: invokevirtual #14                 // Method java/lang/Boolean.booleanValue:()Z
      76: invokevirtual #15                 // Method com/github/jsonldjava/core/JsonLdApi.compact:(Lcom/github/jsonldjava/core/Context;Ljava/lang/String;Ljava/lang/Object;Z)Ljava/lang/Object;
      79: astore        5
      81: aload         5
      83: instanceof    #16                 // class java/util/List
      86: ifeq          137
      89: aload         5
      91: checkcast     #16                 // class java/util/List
      94: invokeinterface #17,  1           // InterfaceMethod java/util/List.isEmpty:()Z
      99: ifeq          110
     102: invokestatic  #18                 // Method com/github/jsonldjava/utils/Obj.newMap:()Ljava/util/Map;
     105: astore        5
     107: goto          137
     110: invokestatic  #18                 // Method com/github/jsonldjava/utils/Obj.newMap:()Ljava/util/Map;
     113: astore        6
     115: aload         6
     117: aload         4
     119: ldc           #19                 // String @graph
     121: iconst_1
     122: invokevirtual #20                 // Method com/github/jsonldjava/core/Context.compactIri:(Ljava/lang/String;Z)Ljava/lang/String;
     125: aload         5
     127: invokeinterface #21,  3           // InterfaceMethod java/util/Map.put:(Ljava/lang/Object;Ljava/lang/Object;)Ljava/lang/Object;
     132: pop
     133: aload         6
     135: astore        5
     137: aload         5
     139: ifnull        254
     142: aload_1
     143: ifnull        254
     146: aload_1
     147: instanceof    #3                  // class java/util/Map
     150: ifeq          165
     153: aload_1
     154: checkcast     #3                  // class java/util/Map
     157: invokeinterface #22,  1           // InterfaceMethod java/util/Map.isEmpty:()Z
     162: ifeq          184
     165: aload_1
     166: instanceof    #16                 // class java/util/List
     169: ifeq          254
     172: aload_1
     173: checkcast     #16                 // class java/util/List
     176: invokeinterface #17,  1           // InterfaceMethod java/util/List.isEmpty:()Z
     181: ifne          254
     184: aload_1
     185: instanceof    #16                 // class java/util/List
     188: ifeq          240
     191: aload_1
     192: checkcast     #16                 // class java/util/List
     195: invokeinterface #23,  1           // InterfaceMethod java/util/List.size:()I
     200: iconst_1
     201: if_icmpne     240
     204: aload_2
     205: invokevirtual #13                 // Method com/github/jsonldjava/core/JsonLdOptions.getCompactArrays:()Ljava/lang/Boolean;
     208: invokevirtual #14                 // Method java/lang/Boolean.booleanValue:()Z
     211: ifeq          240
     214: aload         5
     216: checkcast     #3                  // class java/util/Map
     219: ldc           #5                  // String @context
     221: aload_1
     222: checkcast     #16                 // class java/util/List
     225: iconst_0
     226: invokeinterface #24,  2           // InterfaceMethod java/util/List.get:(I)Ljava/lang/Object;
     231: invokeinterface #21,  3           // InterfaceMethod java/util/Map.put:(Ljava/lang/Object;Ljava/lang/Object;)Ljava/lang/Object;
     236: pop
     237: goto          254
     240: aload         5
     242: checkcast     #3                  // class java/util/Map
     245: ldc           #5                  // String @context
     247: aload_1
     248: invokeinterface #21,  3           // InterfaceMethod java/util/Map.put:(Ljava/lang/Object;Ljava/lang/Object;)Ljava/lang/Object;
     253: pop
     254: aload         5
     256: checkcast     #3                  // class java/util/Map
     259: areturn

  public static java.util.List<java.lang.Object> expand(java.lang.Object, com.github.jsonldjava.core.JsonLdOptions) throws com.github.jsonldjava.core.JsonLdError;
    Code:
       0: aload_0
       1: instanceof    #25                 // class java/lang/String
       4: ifeq          67
       7: aload_0
       8: checkcast     #25                 // class java/lang/String
      11: ldc           #26                 // String :
      13: invokevirtual #27                 // Method java/lang/String.contains:(Ljava/lang/CharSequence;)Z
      16: ifeq          67
      19: aload_1
      20: invokevirtual #28                 // Method com/github/jsonldjava/core/JsonLdOptions.getDocumentLoader:()Lcom/github/jsonldjava/core/DocumentLoader;
      23: aload_0
      24: checkcast     #25                 // class java/lang/String
      27: invokevirtual #29                 // Method com/github/jsonldjava/core/DocumentLoader.loadDocument:(Ljava/lang/String;)Lcom/github/jsonldjava/core/RemoteDocument;
      30: astore_2
      31: aload_2
      32: getfield      #30                 // Field com/github/jsonldjava/core/RemoteDocument.document:Ljava/lang/Object;
      35: astore_0
      36: goto          52
      39: astore_2
      40: new           #32                 // class com/github/jsonldjava/core/JsonLdError
      43: dup
      44: getstatic     #33                 // Field com/github/jsonldjava/core/JsonLdError$Error.LOADING_DOCUMENT_FAILED:Lcom/github/jsonldjava/core/JsonLdError$Error;
      47: aload_2
      48: invokespecial #34                 // Method com/github/jsonldjava/core/JsonLdError."<init>":(Lcom/github/jsonldjava/core/JsonLdError$Error;Ljava/lang/Throwable;)V
      51: athrow
      52: aload_1
      53: invokevirtual #35                 // Method com/github/jsonldjava/core/JsonLdOptions.getBase:()Ljava/lang/String;
      56: ifnonnull     67
      59: aload_1
      60: aload_0
      61: checkcast     #25                 // class java/lang/String
      64: invokevirtual #36                 // Method com/github/jsonldjava/core/JsonLdOptions.setBase:(Ljava/lang/String;)V
      67: new           #8                  // class com/github/jsonldjava/core/Context
      70: dup
      71: aload_1
      72: invokespecial #9                  // Method com/github/jsonldjava/core/Context."<init>":(Lcom/github/jsonldjava/core/JsonLdOptions;)V
      75: astore_2
      76: aload_1
      77: invokevirtual #37                 // Method com/github/jsonldjava/core/JsonLdOptions.getExpandContext:()Ljava/lang/Object;
      80: ifnull        127
      83: aload_1
      84: invokevirtual #37                 // Method com/github/jsonldjava/core/JsonLdOptions.getExpandContext:()Ljava/lang/Object;
      87: astore_3
      88: aload_3
      89: instanceof    #3                  // class java/util/Map
      92: ifeq          121
      95: aload_3
      96: checkcast     #3                  // class java/util/Map
      99: ldc           #5                  // String @context
     101: invokeinterface #6,  2            // InterfaceMethod java/util/Map.containsKey:(Ljava/lang/Object;)Z
     106: ifeq          121
     109: aload_3
     110: checkcast     #3                  // class java/util/Map
     113: ldc           #5                  // String @context
     115: invokeinterface #7,  2            // InterfaceMethod java/util/Map.get:(Ljava/lang/Object;)Ljava/lang/Object;
     120: astore_3
     121: aload_2
     122: aload_3
     123: invokevirtual #10                 // Method com/github/jsonldjava/core/Context.parse:(Ljava/lang/Object;)Lcom/github/jsonldjava/core/Context;
     126: astore_2
     127: new           #11                 // class com/github/jsonldjava/core/JsonLdApi
     130: dup
     131: aload_1
     132: invokespecial #12                 // Method com/github/jsonldjava/core/JsonLdApi."<init>":(Lcom/github/jsonldjava/core/JsonLdOptions;)V
     135: aload_2
     136: aload_0
     137: invokevirtual #38                 // Method com/github/jsonldjava/core/JsonLdApi.expand:(Lcom/github/jsonldjava/core/Context;Ljava/lang/Object;)Ljava/lang/Object;
     140: astore_3
     141: aload_3
     142: instanceof    #3                  // class java/util/Map
     145: ifeq          190
     148: aload_3
     149: checkcast     #3                  // class java/util/Map
     152: ldc           #19                 // String @graph
     154: invokeinterface #6,  2            // InterfaceMethod java/util/Map.containsKey:(Ljava/lang/Object;)Z
     159: ifeq          190
     162: aload_3
     163: checkcast     #3                  // class java/util/Map
     166: invokeinterface #39,  1           // InterfaceMethod java/util/Map.size:()I
     171: iconst_1
     172: if_icmpne     190
     175: aload_3
     176: checkcast     #3                  // class java/util/Map
     179: ldc           #19                 // String @graph
     181: invokeinterface #7,  2            // InterfaceMethod java/util/Map.get:(Ljava/lang/Object;)Ljava/lang/Object;
     186: astore_3
     187: goto          202
     190: aload_3
     191: ifnonnull     202
     194: new           #40                 // class java/util/ArrayList
     197: dup
     198: invokespecial #41                 // Method java/util/ArrayList."<init>":()V
     201: astore_3
     202: aload_3
     203: instanceof    #16                 // class java/util/List
     206: ifne          230
     209: new           #40                 // class java/util/ArrayList
     212: dup
     213: invokespecial #41                 // Method java/util/ArrayList."<init>":()V
     216: astore        4
     218: aload         4
     220: aload_3
     221: invokeinterface #42,  2           // InterfaceMethod java/util/List.add:(Ljava/lang/Object;)Z
     226: pop
     227: aload         4
     229: astore_3
     230: aload_3
     231: checkcast     #16                 // class java/util/List
     234: areturn
    Exception table:
       from    to  target type
          19    36    39   Class java/lang/Exception

  public static java.util.List<java.lang.Object> expand(java.lang.Object) throws com.github.jsonldjava.core.JsonLdError;
    Code:
       0: aload_0
       1: new           #43                 // class com/github/jsonldjava/core/JsonLdOptions
       4: dup
       5: ldc           #44                 // String
       7: invokespecial #45                 // Method com/github/jsonldjava/core/JsonLdOptions."<init>":(Ljava/lang/String;)V
      10: invokestatic  #2                  // Method expand:(Ljava/lang/Object;Lcom/github/jsonldjava/core/JsonLdOptions;)Ljava/util/List;
      13: areturn

  public static java.lang.Object flatten(java.lang.Object, java.lang.Object, com.github.jsonldjava.core.JsonLdOptions) throws com.github.jsonldjava.core.JsonLdError;
    Code:
       0: aload_0
       1: aload_2
       2: invokestatic  #2                  // Method expand:(Ljava/lang/Object;Lcom/github/jsonldjava/core/JsonLdOptions;)Ljava/util/List;
       5: astore_3
       6: aload_1
       7: instanceof    #3                  // class java/util/Map
      10: ifeq          39
      13: aload_1
      14: checkcast     #3                  // class java/util/Map
      17: ldc           #5                  // String @context
      19: invokeinterface #6,  2            // InterfaceMethod java/util/Map.containsKey:(Ljava/lang/Object;)Z
      24: ifeq          39
      27: aload_1
      28: checkcast     #3                  // class java/util/Map
      31: ldc           #5                  // String @context
      33: invokeinterface #7,  2            // InterfaceMethod java/util/Map.get:(Ljava/lang/Object;)Ljava/lang/Object;
      38: astore_1
      39: invokestatic  #18                 // Method com/github/jsonldjava/utils/Obj.newMap:()Ljava/util/Map;
      42: astore        4
      44: aload         4
      46: ldc           #46                 // String @default
      48: invokestatic  #18                 // Method com/github/jsonldjava/utils/Obj.newMap:()Ljava/util/Map;
      51: invokeinterface #21,  3           // InterfaceMethod java/util/Map.put:(Ljava/lang/Object;Ljava/lang/Object;)Ljava/lang/Object;
      56: pop
      57: new           #11                 // class com/github/jsonldjava/core/JsonLdApi
      60: dup
      61: aload_2
      62: invokespecial #12                 // Method com/github/jsonldjava/core/JsonLdApi."<init>":(Lcom/github/jsonldjava/core/JsonLdOptions;)V
      65: aload_3
      66: aload         4
      68: invokevirtual #47                 // Method com/github/jsonldjava/core/JsonLdApi.generateNodeMap:(Ljava/lang/Object;Ljava/util/Map;)V
      71: aload         4
      73: ldc           #46                 // String @default
      75: invokeinterface #48,  2           // InterfaceMethod java/util/Map.remove:(Ljava/lang/Object;)Ljava/lang/Object;
      80: checkcast     #3                  // class java/util/Map
      83: astore        5
      85: aload         4
      87: invokeinterface #49,  1           // InterfaceMethod java/util/Map.keySet:()Ljava/util/Set;
      92: invokeinterface #50,  1           // InterfaceMethod java/util/Set.iterator:()Ljava/util/Iterator;
      97: astore        6
      99: aload         6
     101: invokeinterface #51,  1           // InterfaceMethod java/util/Iterator.hasNext:()Z
     106: ifeq          337
     109: aload         6
     111: invokeinterface #52,  1           // InterfaceMethod java/util/Iterator.next:()Ljava/lang/Object;
     116: checkcast     #25                 // class java/lang/String
     119: astore        7
     121: aload         4
     123: aload         7
     125: invokeinterface #7,  2            // InterfaceMethod java/util/Map.get:(Ljava/lang/Object;)Ljava/lang/Object;
     130: checkcast     #3                  // class java/util/Map
     133: astore        8
     135: aload         5
     137: aload         7
     139: invokeinterface #6,  2            // InterfaceMethod java/util/Map.containsKey:(Ljava/lang/Object;)Z
     144: ifne          179
     147: invokestatic  #18                 // Method com/github/jsonldjava/utils/Obj.newMap:()Ljava/util/Map;
     150: astore        9
     152: aload         9
     154: ldc           #53                 // String @id
     156: aload         7
     158: invokeinterface #21,  3           // InterfaceMethod java/util/Map.put:(Ljava/lang/Object;Ljava/lang/Object;)Ljava/lang/Object;
     163: pop
     164: aload         5
     166: aload         7
     168: aload         9
     170: invokeinterface #21,  3           // InterfaceMethod java/util/Map.put:(Ljava/lang/Object;Ljava/lang/Object;)Ljava/lang/Object;
     175: pop
     176: goto          193
     179: aload         5
     181: aload         7
     183: invokeinterface #7,  2            // InterfaceMethod java/util/Map.get:(Ljava/lang/Object;)Ljava/lang/Object;
     188: checkcast     #3                  // class java/util/Map
     191: astore        9
     193: aload         9
     195: ldc           #19                 // String @graph
     197: invokeinterface #6,  2            // InterfaceMethod java/util/Map.containsKey:(Ljava/lang/Object;)Z
     202: ifne          222
     205: aload         9
     207: ldc           #19                 // String @graph
     209: new           #40                 // class java/util/ArrayList
     212: dup
     213: invokespecial #41                 // Method java/util/ArrayList."<init>":()V
     216: invokeinterface #21,  3           // InterfaceMethod java/util/Map.put:(Ljava/lang/Object;Ljava/lang/Object;)Ljava/lang/Object;
     221: pop
     222: new           #40                 // class java/util/ArrayList
     225: dup
     226: aload         8
     228: invokeinterface #49,  1           // InterfaceMethod java/util/Map.keySet:()Ljava/util/Set;
     233: invokespecial #54                 // Method java/util/ArrayList."<init>":(Ljava/util/Collection;)V
     236: astore        10
     238: aload         10
     240: invokestatic  #55                 // Method java/util/Collections.sort:(Ljava/util/List;)V
     243: aload         10
     245: invokeinterface #56,  1           // InterfaceMethod java/util/List.iterator:()Ljava/util/Iterator;
     250: astore        11
     252: aload         11
     254: invokeinterface #51,  1           // InterfaceMethod java/util/Iterator.hasNext:()Z
     259: ifeq          334
     262: aload         11
     264: invokeinterface #52,  1           // InterfaceMethod java/util/Iterator.next:()Ljava/lang/Object;
     269: checkcast     #25                 // class java/lang/String
     272: astore        12
     274: aload         8
     276: aload         12
     278: invokeinterface #7,  2            // InterfaceMethod java/util/Map.get:(Ljava/lang/Object;)Ljava/lang/Object;
     283: checkcast     #3                  // class java/util/Map
     286: astore        13
     288: aload         13
     290: ldc           #53                 // String @id
     292: invokeinterface #6,  2            // InterfaceMethod java/util/Map.containsKey:(Ljava/lang/Object;)Z
     297: ifeq          311
     300: aload         13
     302: invokeinterface #39,  1           // InterfaceMethod java/util/Map.size:()I
     307: iconst_1
     308: if_icmpeq     331
     311: aload         9
     313: ldc           #19                 // String @graph
     315: invokeinterface #7,  2            // InterfaceMethod java/util/Map.get:(Ljava/lang/Object;)Ljava/lang/Object;
     320: checkcast     #16                 // class java/util/List
     323: aload         13
     325: invokeinterface #42,  2           // InterfaceMethod java/util/List.add:(Ljava/lang/Object;)Z
     330: pop
     331: goto          252
     334: goto          99
     337: new           #40                 // class java/util/ArrayList
     340: dup
     341: invokespecial #41                 // Method java/util/ArrayList."<init>":()V
     344: astore        6
     346: new           #40                 // class java/util/ArrayList
     349: dup
     350: aload         5
     352: invokeinterface #49,  1           // InterfaceMethod java/util/Map.keySet:()Ljava/util/Set;
     357: invokespecial #54                 // Method java/util/ArrayList."<init>":(Ljava/util/Collection;)V
     360: astore        7
     362: aload         7
     364: invokestatic  #55                 // Method java/util/Collections.sort:(Ljava/util/List;)V
     367: aload         7
     369: invokeinterface #56,  1           // InterfaceMethod java/util/List.iterator:()Ljava/util/Iterator;
     374: astore        8
     376: aload         8
     378: invokeinterface #51,  1           // InterfaceMethod java/util/Iterator.hasNext:()Z
     383: ifeq          448
     386: aload         8
     388: invokeinterface #52,  1           // InterfaceMethod java/util/Iterator.next:()Ljava/lang/Object;
     393: checkcast     #25                 // class java/lang/String
     396: astore        9
     398: aload         5
     400: aload         9
     402: invokeinterface #7,  2            // InterfaceMethod java/util/Map.get:(Ljava/lang/Object;)Ljava/lang/Object;
     407: checkcast     #3                  // class java/util/Map
     410: astore        10
     412: aload         10
     414: ldc           #53                 // String @id
     416: invokeinterface #6,  2            // InterfaceMethod java/util/Map.containsKey:(Ljava/lang/Object;)Z
     421: ifeq          435
     424: aload         10
     426: invokeinterface #39,  1           // InterfaceMethod java/util/Map.size:()I
     431: iconst_1
     432: if_icmpeq     445
     435: aload         6
     437: aload         10
     439: invokeinterface #42,  2           // InterfaceMethod java/util/List.add:(Ljava/lang/Object;)Z
     444: pop
     445: goto          376
     448: aload_1
     449: ifnull        567
     452: aload         6
     454: invokeinterface #17,  1           // InterfaceMethod java/util/List.isEmpty:()Z
     459: ifne          567
     462: new           #8                  // class com/github/jsonldjava/core/Context
     465: dup
     466: aload_2
     467: invokespecial #9                  // Method com/github/jsonldjava/core/Context."<init>":(Lcom/github/jsonldjava/core/JsonLdOptions;)V
     470: astore        8
     472: aload         8
     474: aload_1
     475: invokevirtual #10                 // Method com/github/jsonldjava/core/Context.parse:(Ljava/lang/Object;)Lcom/github/jsonldjava/core/Context;
     478: astore        8
     480: new           #11                 // class com/github/jsonldjava/core/JsonLdApi
     483: dup
     484: aload_2
     485: invokespecial #12                 // Method com/github/jsonldjava/core/JsonLdApi."<init>":(Lcom/github/jsonldjava/core/JsonLdOptions;)V
     488: aload         8
     490: aconst_null
     491: aload         6
     493: aload_2
     494: invokevirtual #13                 // Method com/github/jsonldjava/core/JsonLdOptions.getCompactArrays:()Ljava/lang/Boolean;
     497: invokevirtual #14                 // Method java/lang/Boolean.booleanValue:()Z
     500: invokevirtual #15                 // Method com/github/jsonldjava/core/JsonLdApi.compact:(Lcom/github/jsonldjava/core/Context;Ljava/lang/String;Ljava/lang/Object;Z)Ljava/lang/Object;
     503: astore        9
     505: aload         9
     507: instanceof    #16                 // class java/util/List
     510: ifne          536
     513: new           #40                 // class java/util/ArrayList
     516: dup
     517: invokespecial #41                 // Method java/util/ArrayList."<init>":()V
     520: astore        10
     522: aload         10
     524: aload         9
     526: invokeinterface #42,  2           // InterfaceMethod java/util/List.add:(Ljava/lang/Object;)Z
     531: pop
     532: aload         10
     534: astore        9
     536: aload         8
     538: ldc           #19                 // String @graph
     540: invokevirtual #57                 // Method com/github/jsonldjava/core/Context.compactIri:(Ljava/lang/String;)Ljava/lang/String;
     543: astore        10
     545: aload         8
     547: invokevirtual #58                 // Method com/github/jsonldjava/core/Context.serialize:()Ljava/util/Map;
     550: astore        11
     552: aload         11
     554: aload         10
     556: aload         9
     558: invokeinterface #21,  3           // InterfaceMethod java/util/Map.put:(Ljava/lang/Object;Ljava/lang/Object;)Ljava/lang/Object;
     563: pop
     564: aload         11
     566: areturn
     567: aload         6
     569: areturn

  public static java.lang.Object flatten(java.lang.Object, com.github.jsonldjava.core.JsonLdOptions) throws com.github.jsonldjava.core.JsonLdError;
    Code:
       0: aload_0
       1: aconst_null
       2: aload_1
       3: invokestatic  #59                 // Method flatten:(Ljava/lang/Object;Ljava/lang/Object;Lcom/github/jsonldjava/core/JsonLdOptions;)Ljava/lang/Object;
       6: areturn

  public static java.util.Map<java.lang.String, java.lang.Object> frame(java.lang.Object, java.lang.Object, com.github.jsonldjava.core.JsonLdOptions) throws com.github.jsonldjava.core.JsonLdError;
    Code:
       0: aload_1
       1: instanceof    #3                  // class java/util/Map
       4: ifeq          12
       7: aload_1
       8: invokestatic  #60                 // Method com/github/jsonldjava/core/JsonLdUtils.clone:(Ljava/lang/Object;)Ljava/lang/Object;
      11: astore_1
      12: aload_0
      13: aload_2
      14: invokestatic  #2                  // Method expand:(Ljava/lang/Object;Lcom/github/jsonldjava/core/JsonLdOptions;)Ljava/util/List;
      17: astore_3
      18: aload_2
      19: invokevirtual #61                 // Method com/github/jsonldjava/core/JsonLdOptions.getProcessingMode:()Ljava/lang/String;
      22: astore        4
      24: aload_2
      25: invokevirtual #37                 // Method com/github/jsonldjava/core/JsonLdOptions.getExpandContext:()Ljava/lang/Object;
      28: astore        5
      30: aload_2
      31: ldc           #62                 // String json-ld-1.1-expand-frame
      33: invokevirtual #63                 // Method com/github/jsonldjava/core/JsonLdOptions.setProcessingMode:(Ljava/lang/String;)V
      36: aload_2
      37: aconst_null
      38: invokevirtual #64                 // Method com/github/jsonldjava/core/JsonLdOptions.setExpandContext:(Ljava/lang/Object;)V
      41: aload_1
      42: aload_2
      43: invokestatic  #2                  // Method expand:(Ljava/lang/Object;Lcom/github/jsonldjava/core/JsonLdOptions;)Ljava/util/List;
      46: astore        6
      48: aload_2
      49: aload         4
      51: invokevirtual #63                 // Method com/github/jsonldjava/core/JsonLdOptions.setProcessingMode:(Ljava/lang/String;)V
      54: aload_2
      55: aload         5
      57: invokevirtual #64                 // Method com/github/jsonldjava/core/JsonLdOptions.setExpandContext:(Ljava/lang/Object;)V
      60: new           #11                 // class com/github/jsonldjava/core/JsonLdApi
      63: dup
      64: aload_3
      65: aload_2
      66: invokespecial #65                 // Method com/github/jsonldjava/core/JsonLdApi."<init>":(Ljava/lang/Object;Lcom/github/jsonldjava/core/JsonLdOptions;)V
      69: astore        7
      71: aload         7
      73: getfield      #66                 // Field com/github/jsonldjava/core/JsonLdApi.context:Lcom/github/jsonldjava/core/Context;
      76: aload_1
      77: checkcast     #3                  // class java/util/Map
      80: ldc           #5                  // String @context
      82: invokeinterface #7,  2            // InterfaceMethod java/util/Map.get:(Ljava/lang/Object;)Ljava/lang/Object;
      87: invokevirtual #10                 // Method com/github/jsonldjava/core/Context.parse:(Ljava/lang/Object;)Lcom/github/jsonldjava/core/Context;
      90: astore        8
      92: aload         7
      94: aload_3
      95: aload         6
      97: invokevirtual #67                 // Method com/github/jsonldjava/core/JsonLdApi.frame:(Ljava/lang/Object;Ljava/util/List;)Ljava/util/List;
     100: astore        9
     102: aload         7
     104: aload         8
     106: aconst_null
     107: aload         9
     109: aload_2
     110: invokevirtual #13                 // Method com/github/jsonldjava/core/JsonLdOptions.getCompactArrays:()Ljava/lang/Boolean;
     113: invokevirtual #14                 // Method java/lang/Boolean.booleanValue:()Z
     116: invokevirtual #15                 // Method com/github/jsonldjava/core/JsonLdApi.compact:(Lcom/github/jsonldjava/core/Context;Ljava/lang/String;Ljava/lang/Object;Z)Ljava/lang/Object;
     119: astore        10
     121: aload         10
     123: instanceof    #16                 // class java/util/List
     126: ifne          152
     129: new           #40                 // class java/util/ArrayList
     132: dup
     133: invokespecial #41                 // Method java/util/ArrayList."<init>":()V
     136: astore        11
     138: aload         11
     140: aload         10
     142: invokeinterface #42,  2           // InterfaceMethod java/util/List.add:(Ljava/lang/Object;)Z
     147: pop
     148: aload         11
     150: astore        10
     152: aload         8
     154: ldc           #19                 // String @graph
     156: invokevirtual #57                 // Method com/github/jsonldjava/core/Context.compactIri:(Ljava/lang/String;)Ljava/lang/String;
     159: astore        11
     161: aload         8
     163: invokevirtual #58                 // Method com/github/jsonldjava/core/Context.serialize:()Ljava/util/Map;
     166: astore        12
     168: aload         12
     170: aload         11
     172: aload         10
     174: invokeinterface #21,  3           // InterfaceMethod java/util/Map.put:(Ljava/lang/Object;Ljava/lang/Object;)Ljava/lang/Object;
     179: pop
     180: aload_2
     181: invokevirtual #68                 // Method com/github/jsonldjava/core/JsonLdOptions.getPruneBlankNodeIdentifiers:()Ljava/lang/Boolean;
     184: invokevirtual #14                 // Method java/lang/Boolean.booleanValue:()Z
     187: ifeq          198
     190: aload         12
     192: invokestatic  #69                 // Method blankNodeIdsToPrune:(Ljava/util/Map;)Ljava/util/Set;
     195: goto          201
     198: invokestatic  #70                 // Method java/util/Collections.emptySet:()Ljava/util/Set;
     201: astore        13
     203: aload         8
     205: aload         12
     207: aload_2
     208: aload         13
     210: invokestatic  #71                 // Method com/github/jsonldjava/core/JsonLdUtils.removePreserveAndPrune:(Lcom/github/jsonldjava/core/Context;Ljava/lang/Object;Lcom/github/jsonldjava/core/JsonLdOptions;Ljava/util/Set;)Ljava/lang/Object;
     213: pop
     214: aload         12
     216: areturn

  private static java.util.Set<java.lang.Object> blankNodeIdsToPrune(java.util.Map<java.lang.String, java.lang.Object>);
    Code:
       0: aload_0
       1: new           #72                 // class java/util/HashMap
       4: dup
       5: invokespecial #73                 // Method java/util/HashMap."<init>":()V
       8: invokestatic  #74                 // Method countBlankNodeIds:(Ljava/lang/Object;Ljava/util/Map;)Ljava/util/Map;
      11: invokeinterface #75,  1           // InterfaceMethod java/util/Map.entrySet:()Ljava/util/Set;
      16: invokeinterface #76,  1           // InterfaceMethod java/util/Set.stream:()Ljava/util/stream/Stream;
      21: invokedynamic #77,  0             // InvokeDynamic #0:test:()Ljava/util/function/Predicate;
      26: invokeinterface #78,  2           // InterfaceMethod java/util/stream/Stream.filter:(Ljava/util/function/Predicate;)Ljava/util/stream/Stream;
      31: invokedynamic #79,  0             // InvokeDynamic #1:apply:()Ljava/util/function/Function;
      36: invokeinterface #80,  2           // InterfaceMethod java/util/stream/Stream.map:(Ljava/util/function/Function;)Ljava/util/stream/Stream;
      41: invokestatic  #81                 // Method java/util/stream/Collectors.toSet:()Ljava/util/stream/Collector;
      44: invokeinterface #82,  2           // InterfaceMethod java/util/stream/Stream.collect:(Ljava/util/stream/Collector;)Ljava/lang/Object;
      49: checkcast     #83                 // class java/util/Set
      52: areturn

  private static java.util.Map<java.lang.Object, java.lang.Integer> countBlankNodeIds(java.lang.Object, java.util.Map<java.lang.Object, java.lang.Integer>);
    Code:
       0: aload_0
       1: instanceof    #16                 // class java/util/List
       4: ifeq          25
       7: aload_0
       8: checkcast     #16                 // class java/util/List
      11: aload_1
      12: invokedynamic #84,  0             // InvokeDynamic #2:accept:(Ljava/util/Map;)Ljava/util/function/Consumer;
      17: invokeinterface #85,  2           // InterfaceMethod java/util/List.forEach:(Ljava/util/function/Consumer;)V
      22: goto          116
      25: aload_0
      26: instanceof    #3                  // class java/util/Map
      29: ifeq          55
      32: aload_0
      33: checkcast     #3                  // class java/util/Map
      36: invokeinterface #75,  1           // InterfaceMethod java/util/Map.entrySet:()Ljava/util/Set;
      41: aload_1
      42: invokedynamic #86,  0             // InvokeDynamic #3:accept:(Ljava/util/Map;)Ljava/util/function/Consumer;
      47: invokeinterface #87,  2           // InterfaceMethod java/util/Set.forEach:(Ljava/util/function/Consumer;)V
      52: goto          116
      55: aload_0
      56: instanceof    #25                 // class java/lang/String
      59: ifeq          116
      62: aload_0
      63: checkcast     #25                 // class java/lang/String
      66: astore_2
      67: aload_2
      68: ldc           #88                 // String _:
      70: invokevirtual #89                 // Method java/lang/String.startsWith:(Ljava/lang/String;)Z
      73: ifeq          116
      76: aload_1
      77: aload_2
      78: aload_1
      79: aload_2
      80: invokeinterface #6,  2            // InterfaceMethod java/util/Map.containsKey:(Ljava/lang/Object;)Z
      85: ifeq          106
      88: aload_1
      89: aload_2
      90: invokeinterface #7,  2            // InterfaceMethod java/util/Map.get:(Ljava/lang/Object;)Ljava/lang/Object;
      95: checkcast     #90                 // class java/lang/Integer
      98: invokevirtual #91                 // Method java/lang/Integer.intValue:()I
     101: iconst_1
     102: iadd
     103: goto          107
     106: iconst_1
     107: invokestatic  #92                 // Method java/lang/Integer.valueOf:(I)Ljava/lang/Integer;
     110: invokeinterface #21,  3           // InterfaceMethod java/util/Map.put:(Ljava/lang/Object;Ljava/lang/Object;)Ljava/lang/Object;
     115: pop
     116: aload_1
     117: areturn

  public static void registerRDFParser(java.lang.String, com.github.jsonldjava.core.RDFParser);
    Code:
       0: getstatic     #93                 // Field rdfParsers:Ljava/util/Map;
       3: aload_0
       4: aload_1
       5: invokeinterface #21,  3           // InterfaceMethod java/util/Map.put:(Ljava/lang/Object;Ljava/lang/Object;)Ljava/lang/Object;
      10: pop
      11: return

  public static void removeRDFParser(java.lang.String);
    Code:
       0: getstatic     #93                 // Field rdfParsers:Ljava/util/Map;
       3: aload_0
       4: invokeinterface #48,  2           // InterfaceMethod java/util/Map.remove:(Ljava/lang/Object;)Ljava/lang/Object;
       9: pop
      10: return

  public static java.lang.Object fromRDF(java.lang.Object, com.github.jsonldjava.core.JsonLdOptions) throws com.github.jsonldjava.core.JsonLdError;
    Code:
       0: aconst_null
       1: astore_2
       2: aload_1
       3: getfield      #94                 // Field com/github/jsonldjava/core/JsonLdOptions.format:Ljava/lang/String;
       6: ifnonnull     22
       9: aload_0
      10: instanceof    #25                 // class java/lang/String
      13: ifeq          22
      16: aload_1
      17: ldc           #95                 // String application/n-quads
      19: putfield      #94                 // Field com/github/jsonldjava/core/JsonLdOptions.format:Ljava/lang/String;
      22: getstatic     #93                 // Field rdfParsers:Ljava/util/Map;
      25: aload_1
      26: getfield      #94                 // Field com/github/jsonldjava/core/JsonLdOptions.format:Ljava/lang/String;
      29: invokeinterface #6,  2            // InterfaceMethod java/util/Map.containsKey:(Ljava/lang/Object;)Z
      34: ifeq          56
      37: getstatic     #93                 // Field rdfParsers:Ljava/util/Map;
      40: aload_1
      41: getfield      #94                 // Field com/github/jsonldjava/core/JsonLdOptions.format:Ljava/lang/String;
      44: invokeinterface #7,  2            // InterfaceMethod java/util/Map.get:(Ljava/lang/Object;)Ljava/lang/Object;
      49: checkcast     #96                 // class com/github/jsonldjava/core/RDFParser
      52: astore_2
      53: goto          71
      56: new           #32                 // class com/github/jsonldjava/core/JsonLdError
      59: dup
      60: getstatic     #97                 // Field com/github/jsonldjava/core/JsonLdError$Error.UNKNOWN_FORMAT:Lcom/github/jsonldjava/core/JsonLdError$Error;
      63: aload_1
      64: getfield      #94                 // Field com/github/jsonldjava/core/JsonLdOptions.format:Ljava/lang/String;
      67: invokespecial #98                 // Method com/github/jsonldjava/core/JsonLdError."<init>":(Lcom/github/jsonldjava/core/JsonLdError$Error;Ljava/lang/Object;)V
      70: athrow
      71: aload_0
      72: aload_1
      73: aload_2
      74: invokestatic  #99                 // Method fromRDF:(Ljava/lang/Object;Lcom/github/jsonldjava/core/JsonLdOptions;Lcom/github/jsonldjava/core/RDFParser;)Ljava/lang/Object;
      77: areturn

  public static java.lang.Object fromRDF(java.lang.Object) throws com.github.jsonldjava.core.JsonLdError;
    Code:
       0: aload_0
       1: new           #43                 // class com/github/jsonldjava/core/JsonLdOptions
       4: dup
       5: ldc           #44                 // String
       7: invokespecial #45                 // Method com/github/jsonldjava/core/JsonLdOptions."<init>":(Ljava/lang/String;)V
      10: invokestatic  #100                // Method fromRDF:(Ljava/lang/Object;Lcom/github/jsonldjava/core/JsonLdOptions;)Ljava/lang/Object;
      13: areturn

  public static java.lang.Object fromRDF(java.lang.Object, com.github.jsonldjava.core.JsonLdOptions, com.github.jsonldjava.core.RDFParser) throws com.github.jsonldjava.core.JsonLdError;
    Code:
       0: aload_2
       1: aload_0
       2: invokeinterface #101,  2          // InterfaceMethod com/github/jsonldjava/core/RDFParser.parse:(Ljava/lang/Object;)Lcom/github/jsonldjava/core/RDFDataset;
       7: astore_3
       8: new           #11                 // class com/github/jsonldjava/core/JsonLdApi
      11: dup
      12: aload_1
      13: invokespecial #12                 // Method com/github/jsonldjava/core/JsonLdApi."<init>":(Lcom/github/jsonldjava/core/JsonLdOptions;)V
      16: aload_3
      17: invokevirtual #102                // Method com/github/jsonldjava/core/JsonLdApi.fromRDF:(Lcom/github/jsonldjava/core/RDFDataset;)Ljava/util/List;
      20: astore        4
      22: aload_1
      23: getfield      #103                // Field com/github/jsonldjava/core/JsonLdOptions.outputForm:Ljava/lang/String;
      26: ifnull        123
      29: ldc           #104                // String expanded
      31: aload_1
      32: getfield      #103                // Field com/github/jsonldjava/core/JsonLdOptions.outputForm:Ljava/lang/String;
      35: invokevirtual #105                // Method java/lang/String.equals:(Ljava/lang/Object;)Z
      38: ifeq          44
      41: aload         4
      43: areturn
      44: ldc           #106                // String compacted
      46: aload_1
      47: getfield      #103                // Field com/github/jsonldjava/core/JsonLdOptions.outputForm:Ljava/lang/String;
      50: invokevirtual #105                // Method java/lang/String.equals:(Ljava/lang/Object;)Z
      53: ifeq          67
      56: aload         4
      58: aload_3
      59: invokevirtual #107                // Method com/github/jsonldjava/core/RDFDataset.getContext:()Ljava/util/Map;
      62: aload_1
      63: invokestatic  #108                // Method compact:(Ljava/lang/Object;Ljava/lang/Object;Lcom/github/jsonldjava/core/JsonLdOptions;)Ljava/util/Map;
      66: areturn
      67: ldc           #109                // String flattened
      69: aload_1
      70: getfield      #103                // Field com/github/jsonldjava/core/JsonLdOptions.outputForm:Ljava/lang/String;
      73: invokevirtual #105                // Method java/lang/String.equals:(Ljava/lang/Object;)Z
      76: ifeq          90
      79: aload         4
      81: aload_3
      82: invokevirtual #107                // Method com/github/jsonldjava/core/RDFDataset.getContext:()Ljava/util/Map;
      85: aload_1
      86: invokestatic  #59                 // Method flatten:(Ljava/lang/Object;Ljava/lang/Object;Lcom/github/jsonldjava/core/JsonLdOptions;)Ljava/lang/Object;
      89: areturn
      90: new           #32                 // class com/github/jsonldjava/core/JsonLdError
      93: dup
      94: getstatic     #110                // Field com/github/jsonldjava/core/JsonLdError$Error.UNKNOWN_ERROR:Lcom/github/jsonldjava/core/JsonLdError$Error;
      97: new           #111                // class java/lang/StringBuilder
     100: dup
     101: invokespecial #112                // Method java/lang/StringBuilder."<init>":()V
     104: ldc           #113                // String Output form was unknown:
     106: invokevirtual #114                // Method java/lang/StringBuilder.append:(Ljava/lang/String;)Ljava/lang/StringBuilder;
     109: aload_1
     110: getfield      #103                // Field com/github/jsonldjava/core/JsonLdOptions.outputForm:Ljava/lang/String;
     113: invokevirtual #114                // Method java/lang/StringBuilder.append:(Ljava/lang/String;)Ljava/lang/StringBuilder;
     116: invokevirtual #115                // Method java/lang/StringBuilder.toString:()Ljava/lang/String;
     119: invokespecial #98                 // Method com/github/jsonldjava/core/JsonLdError."<init>":(Lcom/github/jsonldjava/core/JsonLdError$Error;Ljava/lang/Object;)V
     122: athrow
     123: aload         4
     125: areturn

  public static java.lang.Object fromRDF(java.lang.Object, com.github.jsonldjava.core.RDFParser) throws com.github.jsonldjava.core.JsonLdError;
    Code:
       0: aload_0
       1: new           #43                 // class com/github/jsonldjava/core/JsonLdOptions
       4: dup
       5: ldc           #44                 // String
       7: invokespecial #45                 // Method com/github/jsonldjava/core/JsonLdOptions."<init>":(Ljava/lang/String;)V
      10: aload_1
      11: invokestatic  #99                 // Method fromRDF:(Ljava/lang/Object;Lcom/github/jsonldjava/core/JsonLdOptions;Lcom/github/jsonldjava/core/RDFParser;)Ljava/lang/Object;
      14: areturn

  public static java.lang.Object toRDF(java.lang.Object, com.github.jsonldjava.core.JsonLdTripleCallback, com.github.jsonldjava.core.JsonLdOptions) throws com.github.jsonldjava.core.JsonLdError;
    Code:
       0: aload_0
       1: aload_2
       2: invokestatic  #2                  // Method expand:(Ljava/lang/Object;Lcom/github/jsonldjava/core/JsonLdOptions;)Ljava/util/List;
       5: astore_3
       6: new           #11                 // class com/github/jsonldjava/core/JsonLdApi
       9: dup
      10: aload_3
      11: aload_2
      12: invokespecial #65                 // Method com/github/jsonldjava/core/JsonLdApi."<init>":(Ljava/lang/Object;Lcom/github/jsonldjava/core/JsonLdOptions;)V
      15: astore        4
      17: aload         4
      19: invokevirtual #116                // Method com/github/jsonldjava/core/JsonLdApi.toRDF:()Lcom/github/jsonldjava/core/RDFDataset;
      22: astore        5
      24: aload_2
      25: getfield      #117                // Field com/github/jsonldjava/core/JsonLdOptions.useNamespaces:Ljava/lang/Boolean;
      28: invokevirtual #14                 // Method java/lang/Boolean.booleanValue:()Z
      31: ifeq          131
      34: aload_0
      35: instanceof    #16                 // class java/util/List
      38: ifeq          50
      41: aload_0
      42: checkcast     #16                 // class java/util/List
      45: astore        6
      47: goto          71
      50: new           #40                 // class java/util/ArrayList
      53: dup
      54: invokespecial #41                 // Method java/util/ArrayList."<init>":()V
      57: astore        6
      59: aload         6
      61: aload_0
      62: checkcast     #3                  // class java/util/Map
      65: invokeinterface #42,  2           // InterfaceMethod java/util/List.add:(Ljava/lang/Object;)Z
      70: pop
      71: aload         6
      73: invokeinterface #56,  1           // InterfaceMethod java/util/List.iterator:()Ljava/util/Iterator;
      78: astore        7
      80: aload         7
      82: invokeinterface #51,  1           // InterfaceMethod java/util/Iterator.hasNext:()Z
      87: ifeq          131
      90: aload         7
      92: invokeinterface #52,  1           // InterfaceMethod java/util/Iterator.next:()Ljava/lang/Object;
      97: checkcast     #3                  // class java/util/Map
     100: astore        8
     102: aload         8
     104: ldc           #5                  // String @context
     106: invokeinterface #6,  2            // InterfaceMethod java/util/Map.containsKey:(Ljava/lang/Object;)Z
     111: ifeq          128
     114: aload         5
     116: aload         8
     118: ldc           #5                  // String @context
     120: invokeinterface #7,  2            // InterfaceMethod java/util/Map.get:(Ljava/lang/Object;)Ljava/lang/Object;
     125: invokevirtual #118                // Method com/github/jsonldjava/core/RDFDataset.parseContext:(Ljava/lang/Object;)V
     128: goto          80
     131: aload_1
     132: ifnull        144
     135: aload_1
     136: aload         5
     138: invokeinterface #119,  2          // InterfaceMethod com/github/jsonldjava/core/JsonLdTripleCallback.call:(Lcom/github/jsonldjava/core/RDFDataset;)Ljava/lang/Object;
     143: areturn
     144: aload_2
     145: getfield      #94                 // Field com/github/jsonldjava/core/JsonLdOptions.format:Ljava/lang/String;
     148: ifnull        191
     151: ldc           #95                 // String application/n-quads
     153: aload_2
     154: getfield      #94                 // Field com/github/jsonldjava/core/JsonLdOptions.format:Ljava/lang/String;
     157: invokevirtual #105                // Method java/lang/String.equals:(Ljava/lang/Object;)Z
     160: ifeq          176
     163: new           #120                // class com/github/jsonldjava/impl/NQuadTripleCallback
     166: dup
     167: invokespecial #121                // Method com/github/jsonldjava/impl/NQuadTripleCallback."<init>":()V
     170: aload         5
     172: invokevirtual #122                // Method com/github/jsonldjava/impl/NQuadTripleCallback.call:(Lcom/github/jsonldjava/core/RDFDataset;)Ljava/lang/Object;
     175: areturn
     176: new           #32                 // class com/github/jsonldjava/core/JsonLdError
     179: dup
     180: getstatic     #97                 // Field com/github/jsonldjava/core/JsonLdError$Error.UNKNOWN_FORMAT:Lcom/github/jsonldjava/core/JsonLdError$Error;
     183: aload_2
     184: getfield      #94                 // Field com/github/jsonldjava/core/JsonLdOptions.format:Ljava/lang/String;
     187: invokespecial #98                 // Method com/github/jsonldjava/core/JsonLdError."<init>":(Lcom/github/jsonldjava/core/JsonLdError$Error;Ljava/lang/Object;)V
     190: athrow
     191: aload         5
     193: areturn

  public static java.lang.Object toRDF(java.lang.Object, com.github.jsonldjava.core.JsonLdOptions) throws com.github.jsonldjava.core.JsonLdError;
    Code:
       0: aload_0
       1: aconst_null
       2: aload_1
       3: invokestatic  #123                // Method toRDF:(Ljava/lang/Object;Lcom/github/jsonldjava/core/JsonLdTripleCallback;Lcom/github/jsonldjava/core/JsonLdOptions;)Ljava/lang/Object;
       6: areturn

  public static java.lang.Object toRDF(java.lang.Object, com.github.jsonldjava.core.JsonLdTripleCallback) throws com.github.jsonldjava.core.JsonLdError;
    Code:
       0: aload_0
       1: aload_1
       2: new           #43                 // class com/github/jsonldjava/core/JsonLdOptions
       5: dup
       6: ldc           #44                 // String
       8: invokespecial #45                 // Method com/github/jsonldjava/core/JsonLdOptions."<init>":(Ljava/lang/String;)V
      11: invokestatic  #123                // Method toRDF:(Ljava/lang/Object;Lcom/github/jsonldjava/core/JsonLdTripleCallback;Lcom/github/jsonldjava/core/JsonLdOptions;)Ljava/lang/Object;
      14: areturn

  public static java.lang.Object toRDF(java.lang.Object) throws com.github.jsonldjava.core.JsonLdError;
    Code:
       0: aload_0
       1: new           #43                 // class com/github/jsonldjava/core/JsonLdOptions
       4: dup
       5: ldc           #44                 // String
       7: invokespecial #45                 // Method com/github/jsonldjava/core/JsonLdOptions."<init>":(Ljava/lang/String;)V
      10: invokestatic  #124                // Method toRDF:(Ljava/lang/Object;Lcom/github/jsonldjava/core/JsonLdOptions;)Ljava/lang/Object;
      13: areturn

  public static java.lang.Object normalize(java.lang.Object, com.github.jsonldjava.core.JsonLdOptions) throws com.github.jsonldjava.core.JsonLdError;
    Code:
       0: new           #43                 // class com/github/jsonldjava/core/JsonLdOptions
       3: dup
       4: aload_1
       5: invokevirtual #35                 // Method com/github/jsonldjava/core/JsonLdOptions.getBase:()Ljava/lang/String;
       8: invokespecial #45                 // Method com/github/jsonldjava/core/JsonLdOptions."<init>":(Ljava/lang/String;)V
      11: astore_2
      12: aload_2
      13: aconst_null
      14: putfield      #94                 // Field com/github/jsonldjava/core/JsonLdOptions.format:Ljava/lang/String;
      17: aload_0
      18: aload_2
      19: invokestatic  #124                // Method toRDF:(Ljava/lang/Object;Lcom/github/jsonldjava/core/JsonLdOptions;)Ljava/lang/Object;
      22: checkcast     #125                // class com/github/jsonldjava/core/RDFDataset
      25: astore_3
      26: new           #11                 // class com/github/jsonldjava/core/JsonLdApi
      29: dup
      30: aload_1
      31: invokespecial #12                 // Method com/github/jsonldjava/core/JsonLdApi."<init>":(Lcom/github/jsonldjava/core/JsonLdOptions;)V
      34: aload_3
      35: invokevirtual #126                // Method com/github/jsonldjava/core/JsonLdApi.normalize:(Ljava/util/Map;)Ljava/lang/Object;
      38: areturn

  public static java.lang.Object normalize(java.lang.Object) throws com.github.jsonldjava.core.JsonLdError;
    Code:
       0: aload_0
       1: new           #43                 // class com/github/jsonldjava/core/JsonLdOptions
       4: dup
       5: ldc           #44                 // String
       7: invokespecial #45                 // Method com/github/jsonldjava/core/JsonLdOptions."<init>":(Ljava/lang/String;)V
      10: invokestatic  #127                // Method normalize:(Ljava/lang/Object;Lcom/github/jsonldjava/core/JsonLdOptions;)Ljava/lang/Object;
      13: areturn

  private static void lambda$countBlankNodeIds$3(java.util.Map, java.util.Map$Entry);
    Code:
       0: aload_1
       1: invokeinterface #128,  1          // InterfaceMethod java/util/Map$Entry.getValue:()Ljava/lang/Object;
       6: aload_0
       7: invokestatic  #74                 // Method countBlankNodeIds:(Ljava/lang/Object;Ljava/util/Map;)Ljava/util/Map;
      10: pop
      11: return

  private static void lambda$countBlankNodeIds$2(java.util.Map, java.lang.Object);
    Code:
       0: aload_1
       1: aload_0
       2: invokestatic  #74                 // Method countBlankNodeIds:(Ljava/lang/Object;Ljava/util/Map;)Ljava/util/Map;
       5: pop
       6: return

  private static java.lang.Object lambda$blankNodeIdsToPrune$1(java.util.Map$Entry);
    Code:
       0: aload_0
       1: invokeinterface #129,  1          // InterfaceMethod java/util/Map$Entry.getKey:()Ljava/lang/Object;
       6: areturn

  private static boolean lambda$blankNodeIdsToPrune$0(java.util.Map$Entry);
    Code:
       0: aload_0
       1: invokeinterface #128,  1          // InterfaceMethod java/util/Map$Entry.getValue:()Ljava/lang/Object;
       6: checkcast     #90                 // class java/lang/Integer
       9: invokevirtual #91                 // Method java/lang/Integer.intValue:()I
      12: iconst_1
      13: if_icmpne     20
      16: iconst_1
      17: goto          21
      20: iconst_0
      21: ireturn

  static {};
    Code:
       0: new           #130                // class com/github/jsonldjava/core/JsonLdProcessor$1
       3: dup
       4: invokespecial #131                // Method com/github/jsonldjava/core/JsonLdProcessor$1."<init>":()V
       7: putstatic     #93                 // Field rdfParsers:Ljava/util/Map;
      10: return
}
