Compiled from "CtMethod.java"
public final class javassist.CtMethod extends javassist.CtBehavior {
  protected java.lang.String cachedStringRep;

  javassist.CtMethod(javassist.bytecode.MethodInfo, javassist.CtClass);
    Code:
       0: aload_0
       1: aload_2
       2: aload_1
       3: invokespecial #1                  // Method javassist/CtBehavior."<init>":(Ljavassist/CtClass;Ljavassist/bytecode/MethodInfo;)V
       6: aload_0
       7: aconst_null
       8: putfield      #2                  // Field cachedStringRep:Ljava/lang/String;
      11: return

  public javassist.CtMethod(javassist.CtClass, java.lang.String, javassist.CtClass[], javassist.CtClass);
    Code:
       0: aload_0
       1: aconst_null
       2: aload         4
       4: invokespecial #3                  // Method "<init>":(Ljavassist/bytecode/MethodInfo;Ljavassist/CtClass;)V
       7: aload         4
       9: invokevirtual #4                  // Method javassist/CtClass.getClassFile2:()Ljavassist/bytecode/ClassFile;
      12: invokevirtual #5                  // Method javassist/bytecode/ClassFile.getConstPool:()Ljavassist/bytecode/ConstPool;
      15: astore        5
      17: aload_1
      18: aload_3
      19: invokestatic  #6                  // Method javassist/bytecode/Descriptor.ofMethod:(Ljavassist/CtClass;[Ljavassist/CtClass;)Ljava/lang/String;
      22: astore        6
      24: aload_0
      25: new           #7                  // class javassist/bytecode/MethodInfo
      28: dup
      29: aload         5
      31: aload_2
      32: aload         6
      34: invokespecial #8                  // Method javassist/bytecode/MethodInfo."<init>":(Ljavassist/bytecode/ConstPool;Ljava/lang/String;Ljava/lang/String;)V
      37: putfield      #9                  // Field methodInfo:Ljavassist/bytecode/MethodInfo;
      40: aload_0
      41: sipush        1025
      44: invokevirtual #10                 // Method setModifiers:(I)V
      47: return

  public javassist.CtMethod(javassist.CtMethod, javassist.CtClass, javassist.ClassMap) throws javassist.CannotCompileException;
    Code:
       0: aload_0
       1: aconst_null
       2: aload_2
       3: invokespecial #3                  // Method "<init>":(Ljavassist/bytecode/MethodInfo;Ljavassist/CtClass;)V
       6: aload_0
       7: aload_1
       8: iconst_0
       9: aload_3
      10: invokevirtual #11                 // Method copy:(Ljavassist/CtBehavior;ZLjavassist/ClassMap;)V
      13: return

  public static javassist.CtMethod make(java.lang.String, javassist.CtClass) throws javassist.CannotCompileException;
    Code:
       0: aload_0
       1: aload_1
       2: invokestatic  #12                 // Method javassist/CtNewMethod.make:(Ljava/lang/String;Ljavassist/CtClass;)Ljavassist/CtMethod;
       5: areturn

  public static javassist.CtMethod make(javassist.bytecode.MethodInfo, javassist.CtClass) throws javassist.CannotCompileException;
    Code:
       0: aload_1
       1: invokevirtual #4                  // Method javassist/CtClass.getClassFile2:()Ljavassist/bytecode/ClassFile;
       4: invokevirtual #5                  // Method javassist/bytecode/ClassFile.getConstPool:()Ljavassist/bytecode/ConstPool;
       7: aload_0
       8: invokevirtual #13                 // Method javassist/bytecode/MethodInfo.getConstPool:()Ljavassist/bytecode/ConstPool;
      11: if_acmpeq     24
      14: new           #14                 // class javassist/CannotCompileException
      17: dup
      18: ldc           #15                 // String bad declaring class
      20: invokespecial #16                 // Method javassist/CannotCompileException."<init>":(Ljava/lang/String;)V
      23: athrow
      24: new           #17                 // class javassist/CtMethod
      27: dup
      28: aload_0
      29: aload_1
      30: invokespecial #3                  // Method "<init>":(Ljavassist/bytecode/MethodInfo;Ljavassist/CtClass;)V
      33: areturn

  public int hashCode();
    Code:
       0: aload_0
       1: invokevirtual #18                 // Method getStringRep:()Ljava/lang/String;
       4: invokevirtual #19                 // Method java/lang/String.hashCode:()I
       7: ireturn

  void nameReplaced();
    Code:
       0: aload_0
       1: aconst_null
       2: putfield      #2                  // Field cachedStringRep:Ljava/lang/String;
       5: return

  final java.lang.String getStringRep();
    Code:
       0: aload_0
       1: getfield      #2                  // Field cachedStringRep:Ljava/lang/String;
       4: ifnonnull     44
       7: aload_0
       8: new           #20                 // class java/lang/StringBuilder
      11: dup
      12: invokespecial #21                 // Method java/lang/StringBuilder."<init>":()V
      15: aload_0
      16: getfield      #9                  // Field methodInfo:Ljavassist/bytecode/MethodInfo;
      19: invokevirtual #22                 // Method javassist/bytecode/MethodInfo.getName:()Ljava/lang/String;
      22: invokevirtual #23                 // Method java/lang/StringBuilder.append:(Ljava/lang/String;)Ljava/lang/StringBuilder;
      25: aload_0
      26: getfield      #9                  // Field methodInfo:Ljavassist/bytecode/MethodInfo;
      29: invokevirtual #24                 // Method javassist/bytecode/MethodInfo.getDescriptor:()Ljava/lang/String;
      32: invokestatic  #25                 // Method javassist/bytecode/Descriptor.getParamDescriptor:(Ljava/lang/String;)Ljava/lang/String;
      35: invokevirtual #23                 // Method java/lang/StringBuilder.append:(Ljava/lang/String;)Ljava/lang/StringBuilder;
      38: invokevirtual #26                 // Method java/lang/StringBuilder.toString:()Ljava/lang/String;
      41: putfield      #2                  // Field cachedStringRep:Ljava/lang/String;
      44: aload_0
      45: getfield      #2                  // Field cachedStringRep:Ljava/lang/String;
      48: areturn

  public boolean equals(java.lang.Object);
    Code:
       0: aload_1
       1: ifnull        32
       4: aload_1
       5: instanceof    #17                 // class javassist/CtMethod
       8: ifeq          32
      11: aload_1
      12: checkcast     #17                 // class javassist/CtMethod
      15: invokevirtual #18                 // Method getStringRep:()Ljava/lang/String;
      18: aload_0
      19: invokevirtual #18                 // Method getStringRep:()Ljava/lang/String;
      22: invokevirtual #27                 // Method java/lang/String.equals:(Ljava/lang/Object;)Z
      25: ifeq          32
      28: iconst_1
      29: goto          33
      32: iconst_0
      33: ireturn

  public java.lang.String getLongName();
    Code:
       0: new           #20                 // class java/lang/StringBuilder
       3: dup
       4: invokespecial #21                 // Method java/lang/StringBuilder."<init>":()V
       7: aload_0
       8: invokevirtual #28                 // Method getDeclaringClass:()Ljavassist/CtClass;
      11: invokevirtual #29                 // Method javassist/CtClass.getName:()Ljava/lang/String;
      14: invokevirtual #23                 // Method java/lang/StringBuilder.append:(Ljava/lang/String;)Ljava/lang/StringBuilder;
      17: ldc           #30                 // String .
      19: invokevirtual #23                 // Method java/lang/StringBuilder.append:(Ljava/lang/String;)Ljava/lang/StringBuilder;
      22: aload_0
      23: invokevirtual #31                 // Method getName:()Ljava/lang/String;
      26: invokevirtual #23                 // Method java/lang/StringBuilder.append:(Ljava/lang/String;)Ljava/lang/StringBuilder;
      29: aload_0
      30: invokevirtual #32                 // Method getSignature:()Ljava/lang/String;
      33: invokestatic  #33                 // Method javassist/bytecode/Descriptor.toString:(Ljava/lang/String;)Ljava/lang/String;
      36: invokevirtual #23                 // Method java/lang/StringBuilder.append:(Ljava/lang/String;)Ljava/lang/StringBuilder;
      39: invokevirtual #26                 // Method java/lang/StringBuilder.toString:()Ljava/lang/String;
      42: areturn

  public java.lang.String getName();
    Code:
       0: aload_0
       1: getfield      #9                  // Field methodInfo:Ljavassist/bytecode/MethodInfo;
       4: invokevirtual #22                 // Method javassist/bytecode/MethodInfo.getName:()Ljava/lang/String;
       7: areturn

  public void setName(java.lang.String);
    Code:
       0: aload_0
       1: getfield      #34                 // Field declaringClass:Ljavassist/CtClass;
       4: invokevirtual #35                 // Method javassist/CtClass.checkModify:()V
       7: aload_0
       8: getfield      #9                  // Field methodInfo:Ljavassist/bytecode/MethodInfo;
      11: aload_1
      12: invokevirtual #36                 // Method javassist/bytecode/MethodInfo.setName:(Ljava/lang/String;)V
      15: return

  public javassist.CtClass getReturnType() throws javassist.NotFoundException;
    Code:
       0: aload_0
       1: invokevirtual #37                 // Method getReturnType0:()Ljavassist/CtClass;
       4: areturn

  public boolean isEmpty();
    Code:
       0: aload_0
       1: invokevirtual #38                 // Method getMethodInfo2:()Ljavassist/bytecode/MethodInfo;
       4: invokevirtual #39                 // Method javassist/bytecode/MethodInfo.getCodeAttribute:()Ljavassist/bytecode/CodeAttribute;
       7: astore_1
       8: aload_1
       9: ifnonnull     29
      12: aload_0
      13: invokevirtual #40                 // Method getModifiers:()I
      16: sipush        1024
      19: iand
      20: ifeq          27
      23: iconst_1
      24: goto          28
      27: iconst_0
      28: ireturn
      29: aload_1
      30: invokevirtual #41                 // Method javassist/bytecode/CodeAttribute.iterator:()Ljavassist/bytecode/CodeIterator;
      33: astore_2
      34: aload_2
      35: invokevirtual #42                 // Method javassist/bytecode/CodeIterator.hasNext:()Z
      38: ifeq          66
      41: aload_2
      42: aload_2
      43: invokevirtual #43                 // Method javassist/bytecode/CodeIterator.next:()I
      46: invokevirtual #44                 // Method javassist/bytecode/CodeIterator.byteAt:(I)I
      49: sipush        177
      52: if_icmpne     66
      55: aload_2
      56: invokevirtual #42                 // Method javassist/bytecode/CodeIterator.hasNext:()Z
      59: ifne          66
      62: iconst_1
      63: goto          67
      66: iconst_0
      67: ireturn
      68: astore_3
      69: iconst_0
      70: ireturn
    Exception table:
       from    to  target type
          34    67    68   Class javassist/bytecode/BadBytecode

  public void setBody(javassist.CtMethod, javassist.ClassMap) throws javassist.CannotCompileException;
    Code:
       0: aload_1
       1: getfield      #34                 // Field declaringClass:Ljavassist/CtClass;
       4: aload_1
       5: getfield      #9                  // Field methodInfo:Ljavassist/bytecode/MethodInfo;
       8: aload_0
       9: getfield      #34                 // Field declaringClass:Ljavassist/CtClass;
      12: aload_0
      13: getfield      #9                  // Field methodInfo:Ljavassist/bytecode/MethodInfo;
      16: aload_2
      17: invokestatic  #46                 // Method setBody0:(Ljavassist/CtClass;Ljavassist/bytecode/MethodInfo;Ljavassist/CtClass;Ljavassist/bytecode/MethodInfo;Ljavassist/ClassMap;)V
      20: return

  public void setWrappedBody(javassist.CtMethod, javassist.CtMethod$ConstParameter) throws javassist.CannotCompileException;
    Code:
       0: aload_0
       1: getfield      #34                 // Field declaringClass:Ljavassist/CtClass;
       4: invokevirtual #35                 // Method javassist/CtClass.checkModify:()V
       7: aload_0
       8: invokevirtual #28                 // Method getDeclaringClass:()Ljavassist/CtClass;
      11: astore_3
      12: aload_0
      13: invokevirtual #47                 // Method getParameterTypes:()[Ljavassist/CtClass;
      16: astore        4
      18: aload_0
      19: invokevirtual #48                 // Method getReturnType:()Ljavassist/CtClass;
      22: astore        5
      24: goto          39
      27: astore        6
      29: new           #14                 // class javassist/CannotCompileException
      32: dup
      33: aload         6
      35: invokespecial #50                 // Method javassist/CannotCompileException."<init>":(Ljavassist/NotFoundException;)V
      38: athrow
      39: aload_3
      40: aload_3
      41: invokevirtual #4                  // Method javassist/CtClass.getClassFile2:()Ljavassist/bytecode/ClassFile;
      44: aload_1
      45: aload         4
      47: aload         5
      49: aload_2
      50: invokestatic  #51                 // Method javassist/CtNewWrappedMethod.makeBody:(Ljavassist/CtClass;Ljavassist/bytecode/ClassFile;Ljavassist/CtMethod;[Ljavassist/CtClass;Ljavassist/CtClass;Ljavassist/CtMethod$ConstParameter;)Ljavassist/bytecode/Bytecode;
      53: astore        6
      55: aload         6
      57: invokevirtual #52                 // Method javassist/bytecode/Bytecode.toCodeAttribute:()Ljavassist/bytecode/CodeAttribute;
      60: astore        7
      62: aload_0
      63: getfield      #9                  // Field methodInfo:Ljavassist/bytecode/MethodInfo;
      66: aload         7
      68: invokevirtual #53                 // Method javassist/bytecode/MethodInfo.setCodeAttribute:(Ljavassist/bytecode/CodeAttribute;)V
      71: aload_0
      72: getfield      #9                  // Field methodInfo:Ljavassist/bytecode/MethodInfo;
      75: aload_0
      76: getfield      #9                  // Field methodInfo:Ljavassist/bytecode/MethodInfo;
      79: invokevirtual #54                 // Method javassist/bytecode/MethodInfo.getAccessFlags:()I
      82: sipush        -1025
      85: iand
      86: invokevirtual #55                 // Method javassist/bytecode/MethodInfo.setAccessFlags:(I)V
      89: return
    Exception table:
       from    to  target type
          12    24    27   Class javassist/NotFoundException
}
