Compiled from "WebSocketVersion.java"
public final class io.undertow.websockets.core.WebSocketVersion extends java.lang.Enum<io.undertow.websockets.core.WebSocketVersion> {
  public static final io.undertow.websockets.core.WebSocketVersion UNKNOWN;

  public static final io.undertow.websockets.core.WebSocketVersion V00;

  public static final io.undertow.websockets.core.WebSocketVersion V07;

  public static final io.undertow.websockets.core.WebSocketVersion V08;

  public static final io.undertow.websockets.core.WebSocketVersion V13;

  public static final io.undertow.util.AttachmentKey<io.undertow.websockets.core.WebSocketVersion> ATTACHMENT_KEY;

  private static final io.undertow.websockets.core.WebSocketVersion[] $VALUES;

  public static io.undertow.websockets.core.WebSocketVersion[] values();
    Code:
       0: getstatic     #1                  // Field $VALUES:[Lio/undertow/websockets/core/WebSocketVersion;
       3: invokevirtual #2                  // Method "[Lio/undertow/websockets/core/WebSocketVersion;".clone:()Ljava/lang/Object;
       6: checkcast     #3                  // class "[Lio/undertow/websockets/core/WebSocketVersion;"
       9: areturn

  public static io.undertow.websockets.core.WebSocketVersion valueOf(java.lang.String);
    Code:
       0: ldc           #4                  // class io/undertow/websockets/core/WebSocketVersion
       2: aload_0
       3: invokestatic  #5                  // Method java/lang/Enum.valueOf:(Ljava/lang/Class;Ljava/lang/String;)Ljava/lang/Enum;
       6: checkcast     #4                  // class io/undertow/websockets/core/WebSocketVersion
       9: areturn

  private io.undertow.websockets.core.WebSocketVersion();
    Code:
       0: aload_0
       1: aload_1
       2: iload_2
       3: invokespecial #6                  // Method java/lang/Enum."<init>":(Ljava/lang/String;I)V
       6: return

  public java.lang.String toHttpHeaderValue();
    Code:
       0: aload_0
       1: getstatic     #7                  // Field V00:Lio/undertow/websockets/core/WebSocketVersion;
       4: if_acmpne     10
       7: ldc           #8                  // String 0
       9: areturn
      10: aload_0
      11: getstatic     #9                  // Field V07:Lio/undertow/websockets/core/WebSocketVersion;
      14: if_acmpne     20
      17: ldc           #10                 // String 7
      19: areturn
      20: aload_0
      21: getstatic     #11                 // Field V08:Lio/undertow/websockets/core/WebSocketVersion;
      24: if_acmpne     30
      27: ldc           #12                 // String 8
      29: areturn
      30: aload_0
      31: getstatic     #13                 // Field V13:Lio/undertow/websockets/core/WebSocketVersion;
      34: if_acmpne     40
      37: ldc           #14                 // String 13
      39: areturn
      40: new           #15                 // class java/lang/IllegalStateException
      43: dup
      44: new           #16                 // class java/lang/StringBuilder
      47: dup
      48: invokespecial #17                 // Method java/lang/StringBuilder."<init>":()V
      51: ldc           #18                 // String Unknown WebSocket version:
      53: invokevirtual #19                 // Method java/lang/StringBuilder.append:(Ljava/lang/String;)Ljava/lang/StringBuilder;
      56: aload_0
      57: invokevirtual #20                 // Method java/lang/StringBuilder.append:(Ljava/lang/Object;)Ljava/lang/StringBuilder;
      60: invokevirtual #21                 // Method java/lang/StringBuilder.toString:()Ljava/lang/String;
      63: invokespecial #22                 // Method java/lang/IllegalStateException."<init>":(Ljava/lang/String;)V
      66: athrow

  static {};
    Code:
       0: new           #4                  // class io/undertow/websockets/core/WebSocketVersion
       3: dup
       4: ldc           #23                 // String UNKNOWN
       6: iconst_0
       7: invokespecial #24                 // Method "<init>":(Ljava/lang/String;I)V
      10: putstatic     #25                 // Field UNKNOWN:Lio/undertow/websockets/core/WebSocketVersion;
      13: new           #4                  // class io/undertow/websockets/core/WebSocketVersion
      16: dup
      17: ldc           #26                 // String V00
      19: iconst_1
      20: invokespecial #24                 // Method "<init>":(Ljava/lang/String;I)V
      23: putstatic     #7                  // Field V00:Lio/undertow/websockets/core/WebSocketVersion;
      26: new           #4                  // class io/undertow/websockets/core/WebSocketVersion
      29: dup
      30: ldc           #27                 // String V07
      32: iconst_2
      33: invokespecial #24                 // Method "<init>":(Ljava/lang/String;I)V
      36: putstatic     #9                  // Field V07:Lio/undertow/websockets/core/WebSocketVersion;
      39: new           #4                  // class io/undertow/websockets/core/WebSocketVersion
      42: dup
      43: ldc           #28                 // String V08
      45: iconst_3
      46: invokespecial #24                 // Method "<init>":(Ljava/lang/String;I)V
      49: putstatic     #11                 // Field V08:Lio/undertow/websockets/core/WebSocketVersion;
      52: new           #4                  // class io/undertow/websockets/core/WebSocketVersion
      55: dup
      56: ldc           #29                 // String V13
      58: iconst_4
      59: invokespecial #24                 // Method "<init>":(Ljava/lang/String;I)V
      62: putstatic     #13                 // Field V13:Lio/undertow/websockets/core/WebSocketVersion;
      65: iconst_5
      66: anewarray     #4                  // class io/undertow/websockets/core/WebSocketVersion
      69: dup
      70: iconst_0
      71: getstatic     #25                 // Field UNKNOWN:Lio/undertow/websockets/core/WebSocketVersion;
      74: aastore
      75: dup
      76: iconst_1
      77: getstatic     #7                  // Field V00:Lio/undertow/websockets/core/WebSocketVersion;
      80: aastore
      81: dup
      82: iconst_2
      83: getstatic     #9                  // Field V07:Lio/undertow/websockets/core/WebSocketVersion;
      86: aastore
      87: dup
      88: iconst_3
      89: getstatic     #11                 // Field V08:Lio/undertow/websockets/core/WebSocketVersion;
      92: aastore
      93: dup
      94: iconst_4
      95: getstatic     #13                 // Field V13:Lio/undertow/websockets/core/WebSocketVersion;
      98: aastore
      99: putstatic     #1                  // Field $VALUES:[Lio/undertow/websockets/core/WebSocketVersion;
     102: ldc           #4                  // class io/undertow/websockets/core/WebSocketVersion
     104: invokestatic  #30                 // Method io/undertow/util/AttachmentKey.create:(Ljava/lang/Class;)Lio/undertow/util/AttachmentKey;
     107: putstatic     #31                 // Field ATTACHMENT_KEY:Lio/undertow/util/AttachmentKey;
     110: return
}
