Compiled from "AsyncLogger.java"
class org.apache.logging.log4j.core.async.AsyncLogger$2 extends org.apache.logging.log4j.core.async.AsyncLogger$TranslatorType {
  final org.apache.logging.log4j.core.async.AsyncLogger this$0;

  org.apache.logging.log4j.core.async.AsyncLogger$2(org.apache.logging.log4j.core.async.AsyncLogger);
    Code:
       0: aload_0
       1: aload_1
       2: putfield      #1                  // Field this$0:Lorg/apache/logging/log4j/core/async/AsyncLogger;
       5: aload_0
       6: aload_1
       7: invokespecial #2                  // Method org/apache/logging/log4j/core/async/AsyncLogger$TranslatorType."<init>":(Lorg/apache/logging/log4j/core/async/AsyncLogger;)V
      10: return

  void log(java.lang.String, java.lang.StackTraceElement, org.apache.logging.log4j.Level, org.apache.logging.log4j.Marker, org.apache.logging.log4j.message.Message, java.lang.Throwable);
    Code:
       0: aload_0
       1: getfield      #1                  // Field this$0:Lorg/apache/logging/log4j/core/async/AsyncLogger;
       4: aload_1
       5: aload_2
       6: aload_3
       7: aload         4
       9: aload         5
      11: aload         6
      13: invokestatic  #3                  // Method org/apache/logging/log4j/core/async/AsyncLogger.access$200:(Lorg/apache/logging/log4j/core/async/AsyncLogger;Ljava/lang/String;Ljava/lang/StackTraceElement;Lorg/apache/logging/log4j/Level;Lorg/apache/logging/log4j/Marker;Lorg/apache/logging/log4j/message/Message;Ljava/lang/Throwable;)V
      16: return

  void log(java.lang.String, org.apache.logging.log4j.Level, org.apache.logging.log4j.Marker, org.apache.logging.log4j.message.Message, java.lang.Throwable);
    Code:
       0: aload_0
       1: getfield      #1                  // Field this$0:Lorg/apache/logging/log4j/core/async/AsyncLogger;
       4: aload_1
       5: aload_2
       6: aload_3
       7: aload         4
       9: aload         5
      11: invokestatic  #4                  // Method org/apache/logging/log4j/core/async/AsyncLogger.access$300:(Lorg/apache/logging/log4j/core/async/AsyncLogger;Ljava/lang/String;Lorg/apache/logging/log4j/Level;Lorg/apache/logging/log4j/Marker;Lorg/apache/logging/log4j/message/Message;Ljava/lang/Throwable;)V
      14: return
}
