Compiled from "ByteBuddy.java"
public class org.assertj.core.internal.bytebuddy.ByteBuddy$EnumerationImplementation$InitializationAppender implements org.assertj.core.internal.bytebuddy.implementation.bytecode.ByteCodeAppender {
  private final java.util.List<java.lang.String> values;

  protected org.assertj.core.internal.bytebuddy.ByteBuddy$EnumerationImplementation$InitializationAppender(java.util.List<java.lang.String>);
    Code:
       0: aload_0
       1: invokespecial #64                 // Method java/lang/Object."<init>":()V
       4: aload_0
       5: aload_1
       6: putfield      #66                 // Field values:Ljava/util/List;
       9: return

  public org.assertj.core.internal.bytebuddy.implementation.bytecode.ByteCodeAppender$Size apply(org.assertj.core.internal.bytebuddy.jar.asm.MethodVisitor, org.assertj.core.internal.bytebuddy.implementation.Implementation$Context, org.assertj.core.internal.bytebuddy.description.method.MethodDescription);
    Code:
       0: aload_3
       1: invokeinterface #76,  1           // InterfaceMethod org/assertj/core/internal/bytebuddy/description/method/MethodDescription.getDeclaringType:()Lorg/assertj/core/internal/bytebuddy/description/type/TypeDefinition;
       6: invokeinterface #82,  1           // InterfaceMethod org/assertj/core/internal/bytebuddy/description/type/TypeDefinition.asErasure:()Lorg/assertj/core/internal/bytebuddy/description/type/TypeDescription;
      11: astore        4
      13: aload         4
      15: invokeinterface #86,  1           // InterfaceMethod org/assertj/core/internal/bytebuddy/description/type/TypeDescription.getDeclaredMethods:()Lorg/assertj/core/internal/bytebuddy/description/method/MethodList;
      20: invokestatic  #92                 // Method org/assertj/core/internal/bytebuddy/matcher/ElementMatchers.isConstructor:()Lorg/assertj/core/internal/bytebuddy/matcher/ElementMatcher$Junction;
      23: iconst_2
      24: anewarray     #94                 // class java/lang/Class
      27: dup
      28: iconst_0
      29: ldc           #96                 // class java/lang/String
      31: aastore
      32: dup
      33: iconst_1
      34: getstatic     #102                // Field java/lang/Integer.TYPE:Ljava/lang/Class;
      37: aastore
      38: invokestatic  #106                // Method org/assertj/core/internal/bytebuddy/matcher/ElementMatchers.takesArguments:([Ljava/lang/Class;)Lorg/assertj/core/internal/bytebuddy/matcher/ElementMatcher$Junction;
      41: invokeinterface #110,  2          // InterfaceMethod org/assertj/core/internal/bytebuddy/matcher/ElementMatcher$Junction.and:(Lorg/assertj/core/internal/bytebuddy/matcher/ElementMatcher;)Lorg/assertj/core/internal/bytebuddy/matcher/ElementMatcher$Junction;
      46: invokeinterface #116,  2          // InterfaceMethod org/assertj/core/internal/bytebuddy/description/method/MethodList.filter:(Lorg/assertj/core/internal/bytebuddy/matcher/ElementMatcher;)Lorg/assertj/core/internal/bytebuddy/matcher/FilterableList;
      51: checkcast     #112                // class org/assertj/core/internal/bytebuddy/description/method/MethodList
      54: invokeinterface #120,  1          // InterfaceMethod org/assertj/core/internal/bytebuddy/description/method/MethodList.getOnly:()Ljava/lang/Object;
      59: checkcast     #72                 // class org/assertj/core/internal/bytebuddy/description/method/MethodDescription
      62: astore        5
      64: iconst_0
      65: istore        6
      67: getstatic     #124                // Field org/assertj/core/internal/bytebuddy/implementation/bytecode/StackManipulation$Trivial.INSTANCE:Lorg/assertj/core/internal/bytebuddy/implementation/bytecode/StackManipulation$Trivial;
      70: astore        7
      72: new           #126                // class java/util/ArrayList
      75: dup
      76: aload_0
      77: getfield      #66                 // Field values:Ljava/util/List;
      80: invokeinterface #132,  1          // InterfaceMethod java/util/List.size:()I
      85: invokespecial #135                // Method java/util/ArrayList."<init>":(I)V
      88: astore        8
      90: aload_0
      91: getfield      #66                 // Field values:Ljava/util/List;
      94: invokeinterface #139,  1          // InterfaceMethod java/util/List.iterator:()Ljava/util/Iterator;
      99: astore        9
     101: aload         9
     103: invokeinterface #147,  1          // InterfaceMethod java/util/Iterator.hasNext:()Z
     108: ifeq          244
     111: aload         9
     113: invokeinterface #150,  1          // InterfaceMethod java/util/Iterator.next:()Ljava/lang/Object;
     118: checkcast     #96                 // class java/lang/String
     121: astore        10
     123: aload         4
     125: invokeinterface #154,  1          // InterfaceMethod org/assertj/core/internal/bytebuddy/description/type/TypeDescription.getDeclaredFields:()Lorg/assertj/core/internal/bytebuddy/description/field/FieldList;
     130: aload         10
     132: invokestatic  #158                // Method org/assertj/core/internal/bytebuddy/matcher/ElementMatchers.named:(Ljava/lang/String;)Lorg/assertj/core/internal/bytebuddy/matcher/ElementMatcher$Junction;
     135: invokeinterface #161,  2          // InterfaceMethod org/assertj/core/internal/bytebuddy/description/field/FieldList.filter:(Lorg/assertj/core/internal/bytebuddy/matcher/ElementMatcher;)Lorg/assertj/core/internal/bytebuddy/matcher/FilterableList;
     140: checkcast     #160                // class org/assertj/core/internal/bytebuddy/description/field/FieldList
     143: invokeinterface #162,  1          // InterfaceMethod org/assertj/core/internal/bytebuddy/description/field/FieldList.getOnly:()Ljava/lang/Object;
     148: checkcast     #30                 // class org/assertj/core/internal/bytebuddy/description/field/FieldDescription
     151: astore        11
     153: new           #23                 // class org/assertj/core/internal/bytebuddy/implementation/bytecode/StackManipulation$Compound
     156: dup
     157: bipush        7
     159: anewarray     #25                 // class org/assertj/core/internal/bytebuddy/implementation/bytecode/StackManipulation
     162: dup
     163: iconst_0
     164: aload         7
     166: aastore
     167: dup
     168: iconst_1
     169: aload         4
     171: invokestatic  #168                // Method org/assertj/core/internal/bytebuddy/implementation/bytecode/TypeCreation.of:(Lorg/assertj/core/internal/bytebuddy/description/type/TypeDescription;)Lorg/assertj/core/internal/bytebuddy/implementation/bytecode/StackManipulation;
     174: aastore
     175: dup
     176: iconst_2
     177: getstatic     #174                // Field org/assertj/core/internal/bytebuddy/implementation/bytecode/Duplication.SINGLE:Lorg/assertj/core/internal/bytebuddy/implementation/bytecode/Duplication;
     180: aastore
     181: dup
     182: iconst_3
     183: new           #176                // class org/assertj/core/internal/bytebuddy/implementation/bytecode/constant/TextConstant
     186: dup
     187: aload         10
     189: invokespecial #179                // Method org/assertj/core/internal/bytebuddy/implementation/bytecode/constant/TextConstant."<init>":(Ljava/lang/String;)V
     192: aastore
     193: dup
     194: iconst_4
     195: iload         6
     197: iinc          6, 1
     200: invokestatic  #185                // Method org/assertj/core/internal/bytebuddy/implementation/bytecode/constant/IntegerConstant.forValue:(I)Lorg/assertj/core/internal/bytebuddy/implementation/bytecode/StackManipulation;
     203: aastore
     204: dup
     205: iconst_5
     206: aload         5
     208: invokestatic  #189                // Method org/assertj/core/internal/bytebuddy/implementation/bytecode/member/MethodInvocation.invoke:(Lorg/assertj/core/internal/bytebuddy/description/method/MethodDescription;)Lorg/assertj/core/internal/bytebuddy/implementation/bytecode/member/MethodInvocation$WithImplicitInvocationTargetType;
     211: aastore
     212: dup
     213: bipush        6
     215: aload         11
     217: invokestatic  #193                // Method org/assertj/core/internal/bytebuddy/implementation/bytecode/member/FieldAccess.forField:(Lorg/assertj/core/internal/bytebuddy/description/field/FieldDescription;)Lorg/assertj/core/internal/bytebuddy/implementation/bytecode/member/FieldAccess$Defined;
     220: invokeinterface #197,  1          // InterfaceMethod org/assertj/core/internal/bytebuddy/implementation/bytecode/member/FieldAccess$Defined.write:()Lorg/assertj/core/internal/bytebuddy/implementation/bytecode/StackManipulation;
     225: aastore
     226: invokespecial #200                // Method org/assertj/core/internal/bytebuddy/implementation/bytecode/StackManipulation$Compound."<init>":([Lorg/assertj/core/internal/bytebuddy/implementation/bytecode/StackManipulation;)V
     229: astore        7
     231: aload         8
     233: aload         11
     235: invokeinterface #204,  2          // InterfaceMethod java/util/List.add:(Ljava/lang/Object;)Z
     240: pop
     241: goto          101
     244: new           #126                // class java/util/ArrayList
     247: dup
     248: aload_0
     249: getfield      #66                 // Field values:Ljava/util/List;
     252: invokeinterface #132,  1          // InterfaceMethod java/util/List.size:()I
     257: invokespecial #135                // Method java/util/ArrayList."<init>":(I)V
     260: astore        9
     262: aload         8
     264: invokeinterface #139,  1          // InterfaceMethod java/util/List.iterator:()Ljava/util/Iterator;
     269: astore        10
     271: aload         10
     273: invokeinterface #147,  1          // InterfaceMethod java/util/Iterator.hasNext:()Z
     278: ifeq          314
     281: aload         10
     283: invokeinterface #150,  1          // InterfaceMethod java/util/Iterator.next:()Ljava/lang/Object;
     288: checkcast     #30                 // class org/assertj/core/internal/bytebuddy/description/field/FieldDescription
     291: astore        11
     293: aload         9
     295: aload         11
     297: invokestatic  #193                // Method org/assertj/core/internal/bytebuddy/implementation/bytecode/member/FieldAccess.forField:(Lorg/assertj/core/internal/bytebuddy/description/field/FieldDescription;)Lorg/assertj/core/internal/bytebuddy/implementation/bytecode/member/FieldAccess$Defined;
     300: invokeinterface #207,  1          // InterfaceMethod org/assertj/core/internal/bytebuddy/implementation/bytecode/member/FieldAccess$Defined.read:()Lorg/assertj/core/internal/bytebuddy/implementation/bytecode/StackManipulation;
     305: invokeinterface #204,  2          // InterfaceMethod java/util/List.add:(Ljava/lang/Object;)Z
     310: pop
     311: goto          271
     314: new           #23                 // class org/assertj/core/internal/bytebuddy/implementation/bytecode/StackManipulation$Compound
     317: dup
     318: iconst_3
     319: anewarray     #25                 // class org/assertj/core/internal/bytebuddy/implementation/bytecode/StackManipulation
     322: dup
     323: iconst_0
     324: aload         7
     326: aastore
     327: dup
     328: iconst_1
     329: aload         4
     331: invokeinterface #211,  1          // InterfaceMethod org/assertj/core/internal/bytebuddy/description/type/TypeDescription.asGenericType:()Lorg/assertj/core/internal/bytebuddy/description/type/TypeDescription$Generic;
     336: invokestatic  #217                // Method org/assertj/core/internal/bytebuddy/implementation/bytecode/collection/ArrayFactory.forType:(Lorg/assertj/core/internal/bytebuddy/description/type/TypeDescription$Generic;)Lorg/assertj/core/internal/bytebuddy/implementation/bytecode/collection/ArrayFactory;
     339: aload         9
     341: invokevirtual #221                // Method org/assertj/core/internal/bytebuddy/implementation/bytecode/collection/ArrayFactory.withValues:(Ljava/util/List;)Lorg/assertj/core/internal/bytebuddy/implementation/bytecode/StackManipulation;
     344: aastore
     345: dup
     346: iconst_2
     347: aload         4
     349: invokeinterface #154,  1          // InterfaceMethod org/assertj/core/internal/bytebuddy/description/type/TypeDescription.getDeclaredFields:()Lorg/assertj/core/internal/bytebuddy/description/field/FieldList;
     354: ldc           #223                // String $VALUES
     356: invokestatic  #158                // Method org/assertj/core/internal/bytebuddy/matcher/ElementMatchers.named:(Ljava/lang/String;)Lorg/assertj/core/internal/bytebuddy/matcher/ElementMatcher$Junction;
     359: invokeinterface #161,  2          // InterfaceMethod org/assertj/core/internal/bytebuddy/description/field/FieldList.filter:(Lorg/assertj/core/internal/bytebuddy/matcher/ElementMatcher;)Lorg/assertj/core/internal/bytebuddy/matcher/FilterableList;
     364: checkcast     #160                // class org/assertj/core/internal/bytebuddy/description/field/FieldList
     367: invokeinterface #162,  1          // InterfaceMethod org/assertj/core/internal/bytebuddy/description/field/FieldList.getOnly:()Ljava/lang/Object;
     372: checkcast     #28                 // class org/assertj/core/internal/bytebuddy/description/field/FieldDescription$InDefinedShape
     375: invokestatic  #226                // Method org/assertj/core/internal/bytebuddy/implementation/bytecode/member/FieldAccess.forField:(Lorg/assertj/core/internal/bytebuddy/description/field/FieldDescription$InDefinedShape;)Lorg/assertj/core/internal/bytebuddy/implementation/bytecode/member/FieldAccess$Defined;
     378: invokeinterface #197,  1          // InterfaceMethod org/assertj/core/internal/bytebuddy/implementation/bytecode/member/FieldAccess$Defined.write:()Lorg/assertj/core/internal/bytebuddy/implementation/bytecode/StackManipulation;
     383: aastore
     384: invokespecial #200                // Method org/assertj/core/internal/bytebuddy/implementation/bytecode/StackManipulation$Compound."<init>":([Lorg/assertj/core/internal/bytebuddy/implementation/bytecode/StackManipulation;)V
     387: astore        7
     389: new           #20                 // class org/assertj/core/internal/bytebuddy/implementation/bytecode/ByteCodeAppender$Size
     392: dup
     393: aload         7
     395: aload_1
     396: aload_2
     397: invokeinterface #229,  3          // InterfaceMethod org/assertj/core/internal/bytebuddy/implementation/bytecode/StackManipulation.apply:(Lorg/assertj/core/internal/bytebuddy/jar/asm/MethodVisitor;Lorg/assertj/core/internal/bytebuddy/implementation/Implementation$Context;)Lorg/assertj/core/internal/bytebuddy/implementation/bytecode/StackManipulation$Size;
     402: invokevirtual #232                // Method org/assertj/core/internal/bytebuddy/implementation/bytecode/StackManipulation$Size.getMaximalSize:()I
     405: aload_3
     406: invokeinterface #235,  1          // InterfaceMethod org/assertj/core/internal/bytebuddy/description/method/MethodDescription.getStackSize:()I
     411: invokespecial #238                // Method org/assertj/core/internal/bytebuddy/implementation/bytecode/ByteCodeAppender$Size."<init>":(II)V
     414: areturn

  public boolean equals(java.lang.Object);
    Code:
       0: aload_1
       1: aload_0
       2: if_acmpne     7
       5: iconst_1
       6: ireturn
       7: aload_1
       8: instanceof    #2                  // class org/assertj/core/internal/bytebuddy/ByteBuddy$EnumerationImplementation$InitializationAppender
      11: ifne          16
      14: iconst_0
      15: ireturn
      16: aload_1
      17: checkcast     #2                  // class org/assertj/core/internal/bytebuddy/ByteBuddy$EnumerationImplementation$InitializationAppender
      20: astore_2
      21: aload_2
      22: aload_0
      23: invokevirtual #263                // Method canEqual:(Ljava/lang/Object;)Z
      26: ifne          31
      29: iconst_0
      30: ireturn
      31: aload_0
      32: getfield      #66                 // Field values:Ljava/util/List;
      35: astore_3
      36: aload_2
      37: getfield      #66                 // Field values:Ljava/util/List;
      40: astore        4
      42: aload_3
      43: ifnonnull     54
      46: aload         4
      48: ifnull        65
      51: goto          63
      54: aload_3
      55: aload         4
      57: invokevirtual #265                // Method java/lang/Object.equals:(Ljava/lang/Object;)Z
      60: ifne          65
      63: iconst_0
      64: ireturn
      65: iconst_1
      66: ireturn

  protected boolean canEqual(java.lang.Object);
    Code:
       0: aload_1
       1: instanceof    #2                  // class org/assertj/core/internal/bytebuddy/ByteBuddy$EnumerationImplementation$InitializationAppender
       4: ireturn

  public int hashCode();
    Code:
       0: bipush        59
       2: istore_1
       3: iconst_1
       4: istore_2
       5: aload_0
       6: getfield      #66                 // Field values:Ljava/util/List;
       9: astore_3
      10: iload_2
      11: bipush        59
      13: imul
      14: aload_3
      15: ifnonnull     23
      18: bipush        43
      20: goto          27
      23: aload_3
      24: invokevirtual #273                // Method java/lang/Object.hashCode:()I
      27: iadd
      28: istore_2
      29: iload_2
      30: ireturn
}
