Compiled from "Content.java"
public abstract class org.jdom2.Content extends org.jdom2.CloneBase implements java.io.Serializable,org.jdom2.NamespaceAware {
  private static final long serialVersionUID;

  protected transient org.jdom2.Parent parent;

  protected final org.jdom2.Content$CType ctype;

  protected org.jdom2.Content(org.jdom2.Content$CType);
    Code:
       0: aload_0
       1: invokespecial #1                  // Method org/jdom2/CloneBase."<init>":()V
       4: aload_0
       5: aconst_null
       6: putfield      #2                  // Field parent:Lorg/jdom2/Parent;
       9: aload_0
      10: aload_1
      11: putfield      #3                  // Field ctype:Lorg/jdom2/Content$CType;
      14: return

  public final org.jdom2.Content$CType getCType();
    Code:
       0: aload_0
       1: getfield      #3                  // Field ctype:Lorg/jdom2/Content$CType;
       4: areturn

  public org.jdom2.Content detach();
    Code:
       0: aload_0
       1: getfield      #2                  // Field parent:Lorg/jdom2/Parent;
       4: ifnull        18
       7: aload_0
       8: getfield      #2                  // Field parent:Lorg/jdom2/Parent;
      11: aload_0
      12: invokeinterface #4,  2            // InterfaceMethod org/jdom2/Parent.removeContent:(Lorg/jdom2/Content;)Z
      17: pop
      18: aload_0
      19: areturn

  public org.jdom2.Parent getParent();
    Code:
       0: aload_0
       1: getfield      #2                  // Field parent:Lorg/jdom2/Parent;
       4: areturn

  public final org.jdom2.Element getParentElement();
    Code:
       0: aload_0
       1: invokevirtual #5                  // Method getParent:()Lorg/jdom2/Parent;
       4: astore_1
       5: aload_1
       6: instanceof    #6                  // class org/jdom2/Element
       9: ifeq          16
      12: aload_1
      13: goto          17
      16: aconst_null
      17: checkcast     #6                  // class org/jdom2/Element
      20: areturn

  protected org.jdom2.Content setParent(org.jdom2.Parent);
    Code:
       0: aload_0
       1: aload_1
       2: putfield      #2                  // Field parent:Lorg/jdom2/Parent;
       5: aload_0
       6: areturn

  public org.jdom2.Document getDocument();
    Code:
       0: aload_0
       1: getfield      #2                  // Field parent:Lorg/jdom2/Parent;
       4: ifnonnull     9
       7: aconst_null
       8: areturn
       9: aload_0
      10: getfield      #2                  // Field parent:Lorg/jdom2/Parent;
      13: invokeinterface #7,  1            // InterfaceMethod org/jdom2/Parent.getDocument:()Lorg/jdom2/Document;
      18: areturn

  public abstract java.lang.String getValue();

  public org.jdom2.Content clone();
    Code:
       0: aload_0
       1: invokespecial #8                  // Method org/jdom2/CloneBase.clone:()Lorg/jdom2/CloneBase;
       4: checkcast     #9                  // class org/jdom2/Content
       7: astore_1
       8: aload_1
       9: aconst_null
      10: putfield      #2                  // Field parent:Lorg/jdom2/Parent;
      13: aload_1
      14: areturn

  public final boolean equals(java.lang.Object);
    Code:
       0: aload_1
       1: aload_0
       2: if_acmpne     9
       5: iconst_1
       6: goto          10
       9: iconst_0
      10: ireturn

  public final int hashCode();
    Code:
       0: aload_0
       1: invokespecial #10                 // Method java/lang/Object.hashCode:()I
       4: ireturn

  public java.util.List<org.jdom2.Namespace> getNamespacesInScope();
    Code:
       0: aload_0
       1: invokevirtual #11                 // Method getParentElement:()Lorg/jdom2/Element;
       4: astore_1
       5: aload_1
       6: ifnonnull     16
       9: getstatic     #12                 // Field org/jdom2/Namespace.XML_NAMESPACE:Lorg/jdom2/Namespace;
      12: invokestatic  #13                 // Method java/util/Collections.singletonList:(Ljava/lang/Object;)Ljava/util/List;
      15: areturn
      16: aload_1
      17: invokevirtual #14                 // Method org/jdom2/Element.getNamespacesInScope:()Ljava/util/List;
      20: areturn

  public java.util.List<org.jdom2.Namespace> getNamespacesIntroduced();
    Code:
       0: invokestatic  #15                 // Method java/util/Collections.emptyList:()Ljava/util/List;
       3: areturn

  public java.util.List<org.jdom2.Namespace> getNamespacesInherited();
    Code:
       0: aload_0
       1: invokevirtual #16                 // Method getNamespacesInScope:()Ljava/util/List;
       4: areturn

  public org.jdom2.CloneBase clone();
    Code:
       0: aload_0
       1: invokevirtual #17                 // Method clone:()Lorg/jdom2/Content;
       4: areturn

  public java.lang.Object clone() throws java.lang.CloneNotSupportedException;
    Code:
       0: aload_0
       1: invokevirtual #17                 // Method clone:()Lorg/jdom2/Content;
       4: areturn
}
