public class org.bouncycastle.crypto.tls.AlertDescription {
  public static final short close_notify;

  public static final short unexpected_message;

  public static final short bad_record_mac;

  public static final short decryption_failed;

  public static final short record_overflow;

  public static final short decompression_failure;

  public static final short handshake_failure;

  public static final short no_certificate;

  public static final short bad_certificate;

  public static final short unsupported_certificate;

  public static final short certificate_revoked;

  public static final short certificate_expired;

  public static final short certificate_unknown;

  public static final short illegal_parameter;

  public static final short unknown_ca;

  public static final short access_denied;

  public static final short decode_error;

  public static final short decrypt_error;

  public static final short export_restriction;

  public static final short protocol_version;

  public static final short insufficient_security;

  public static final short internal_error;

  public static final short user_canceled;

  public static final short no_renegotiation;

  public static final short unsupported_extension;

  public static final short certificate_unobtainable;

  public static final short unrecognized_name;

  public static final short bad_certificate_status_response;

  public static final short bad_certificate_hash_value;

  public static final short unknown_psk_identity;

  public static final short inappropriate_fallback;

  public org.bouncycastle.crypto.tls.AlertDescription();
    Code:
       0: aload_0
       1: invokespecial #122                // Method java/lang/Object."<init>":()V
       4: return

  public static java.lang.String getName(short);
    Code:
       0: iload_0
       1: tableswitch   { // 0 to 115
                     0: 480
                     1: 573
                     2: 573
                     3: 573
                     4: 573
                     5: 573
                     6: 573
                     7: 573
                     8: 573
                     9: 573
                    10: 483
                    11: 573
                    12: 573
                    13: 573
                    14: 573
                    15: 573
                    16: 573
                    17: 573
                    18: 573
                    19: 573
                    20: 486
                    21: 489
                    22: 492
                    23: 573
                    24: 573
                    25: 573
                    26: 573
                    27: 573
                    28: 573
                    29: 573
                    30: 495
                    31: 573
                    32: 573
                    33: 573
                    34: 573
                    35: 573
                    36: 573
                    37: 573
                    38: 573
                    39: 573
                    40: 498
                    41: 501
                    42: 504
                    43: 507
                    44: 510
                    45: 513
                    46: 516
                    47: 519
                    48: 522
                    49: 525
                    50: 528
                    51: 531
                    52: 573
                    53: 573
                    54: 573
                    55: 573
                    56: 573
                    57: 573
                    58: 573
                    59: 573
                    60: 534
                    61: 573
                    62: 573
                    63: 573
                    64: 573
                    65: 573
                    66: 573
                    67: 573
                    68: 573
                    69: 573
                    70: 537
                    71: 540
                    72: 573
                    73: 573
                    74: 573
                    75: 573
                    76: 573
                    77: 573
                    78: 573
                    79: 573
                    80: 543
                    81: 573
                    82: 573
                    83: 573
                    84: 573
                    85: 573
                    86: 570
                    87: 573
                    88: 573
                    89: 573
                    90: 546
                    91: 573
                    92: 573
                    93: 573
                    94: 573
                    95: 573
                    96: 573
                    97: 573
                    98: 573
                    99: 573
                   100: 549
                   101: 573
                   102: 573
                   103: 573
                   104: 573
                   105: 573
                   106: 573
                   107: 573
                   108: 573
                   109: 573
                   110: 552
                   111: 555
                   112: 558
                   113: 561
                   114: 564
                   115: 567
               default: 573
          }
     480: ldc           #13                 // String close_notify
     482: areturn
     483: ldc           #28                 // String unexpected_message
     485: areturn
     486: ldc           #8                  // String bad_record_mac
     488: areturn
     489: ldc           #17                 // String decryption_failed
     491: areturn
     492: ldc           #27                 // String record_overflow
     494: areturn
     495: ldc           #15                 // String decompression_failure
     497: areturn
     498: ldc           #19                 // String handshake_failure
     500: areturn
     501: ldc           #24                 // String no_certificate
     503: areturn
     504: ldc           #5                  // String bad_certificate
     506: areturn
     507: ldc           #32                 // String unsupported_certificate
     509: areturn
     510: ldc           #10                 // String certificate_revoked
     512: areturn
     513: ldc           #9                  // String certificate_expired
     515: areturn
     516: ldc           #11                 // String certificate_unknown
     518: areturn
     519: ldc           #20                 // String illegal_parameter
     521: areturn
     522: ldc           #29                 // String unknown_ca
     524: areturn
     525: ldc           #4                  // String access_denied
     527: areturn
     528: ldc           #14                 // String decode_error
     530: areturn
     531: ldc           #16                 // String decrypt_error
     533: areturn
     534: ldc           #18                 // String export_restriction
     536: areturn
     537: ldc           #26                 // String protocol_version
     539: areturn
     540: ldc           #22                 // String insufficient_security
     542: areturn
     543: ldc           #23                 // String internal_error
     545: areturn
     546: ldc           #34                 // String user_canceled
     548: areturn
     549: ldc           #25                 // String no_renegotiation
     551: areturn
     552: ldc           #33                 // String unsupported_extension
     554: areturn
     555: ldc           #12                 // String certificate_unobtainable
     557: areturn
     558: ldc           #31                 // String unrecognized_name
     560: areturn
     561: ldc           #7                  // String bad_certificate_status_response
     563: areturn
     564: ldc           #6                  // String bad_certificate_hash_value
     566: areturn
     567: ldc           #30                 // String unknown_psk_identity
     569: areturn
     570: ldc           #21                 // String inappropriate_fallback
     572: areturn
     573: ldc           #3                  // String UNKNOWN
     575: areturn

  public static java.lang.String getText(short);
    Code:
       0: new           #111                // class java/lang/StringBuilder
       3: dup
       4: invokespecial #123                // Method java/lang/StringBuilder."<init>":()V
       7: iload_0
       8: invokestatic  #127                // Method getName:(S)Ljava/lang/String;
      11: invokevirtual #126                // Method java/lang/StringBuilder.append:(Ljava/lang/String;)Ljava/lang/StringBuilder;
      14: ldc           #1                  // String (
      16: invokevirtual #126                // Method java/lang/StringBuilder.append:(Ljava/lang/String;)Ljava/lang/StringBuilder;
      19: iload_0
      20: invokevirtual #125                // Method java/lang/StringBuilder.append:(I)Ljava/lang/StringBuilder;
      23: ldc           #2                  // String )
      25: invokevirtual #126                // Method java/lang/StringBuilder.append:(Ljava/lang/String;)Ljava/lang/StringBuilder;
      28: invokevirtual #124                // Method java/lang/StringBuilder.toString:()Ljava/lang/String;
      31: areturn
}
