public class org.bouncycastle.crypto.tls.SRPTlsServer extends org.bouncycastle.crypto.tls.AbstractTlsServer {
  protected org.bouncycastle.crypto.tls.TlsSRPIdentityManager srpIdentityManager;

  protected byte[] srpIdentity;

  protected org.bouncycastle.crypto.tls.TlsSRPLoginParameters loginParameters;

  public org.bouncycastle.crypto.tls.SRPTlsServer(org.bouncycastle.crypto.tls.TlsSRPIdentityManager);
    Code:
       0: aload_0
       1: new           #44                 // class org/bouncycastle/crypto/tls/DefaultTlsCipherFactory
       4: dup
       5: invokespecial #92                 // Method org/bouncycastle/crypto/tls/DefaultTlsCipherFactory."<init>":()V
       8: aload_1
       9: invokespecial #96                 // Method "<init>":(Lorg/bouncycastle/crypto/tls/TlsCipherFactory;Lorg/bouncycastle/crypto/tls/TlsSRPIdentityManager;)V
      12: return

  public org.bouncycastle.crypto.tls.SRPTlsServer(org.bouncycastle.crypto.tls.TlsCipherFactory, org.bouncycastle.crypto.tls.TlsSRPIdentityManager);
    Code:
       0: aload_0
       1: aload_1
       2: invokespecial #91                 // Method org/bouncycastle/crypto/tls/AbstractTlsServer."<init>":(Lorg/bouncycastle/crypto/tls/TlsCipherFactory;)V
       5: aload_0
       6: aconst_null
       7: putfield      #85                 // Field srpIdentity:[B
      10: aload_0
      11: aconst_null
      12: putfield      #88                 // Field loginParameters:Lorg/bouncycastle/crypto/tls/TlsSRPLoginParameters;
      15: aload_0
      16: aload_2
      17: putfield      #87                 // Field srpIdentityManager:Lorg/bouncycastle/crypto/tls/TlsSRPIdentityManager;
      20: return

  protected org.bouncycastle.crypto.tls.TlsSignerCredentials getDSASignerCredentials() throws java.io.IOException;
    Code:
       0: new           #46                 // class org/bouncycastle/crypto/tls/TlsFatalAlert
       3: dup
       4: bipush        80
       6: invokespecial #97                 // Method org/bouncycastle/crypto/tls/TlsFatalAlert."<init>":(S)V
       9: athrow

  protected org.bouncycastle.crypto.tls.TlsSignerCredentials getRSASignerCredentials() throws java.io.IOException;
    Code:
       0: new           #46                 // class org/bouncycastle/crypto/tls/TlsFatalAlert
       3: dup
       4: bipush        80
       6: invokespecial #97                 // Method org/bouncycastle/crypto/tls/TlsFatalAlert."<init>":(S)V
       9: athrow

  protected int[] getCipherSuites();
    Code:
       0: bipush        6
       2: newarray       int
       4: dup
       5: iconst_0
       6: ldc           #6                  // int 49186
       8: iastore
       9: dup
      10: iconst_1
      11: ldc           #3                  // int 49183
      13: iastore
      14: dup
      15: iconst_2
      16: ldc           #5                  // int 49185
      18: iastore
      19: dup
      20: iconst_3
      21: ldc           #2                  // int 49182
      23: iastore
      24: dup
      25: iconst_4
      26: ldc           #4                  // int 49184
      28: iastore
      29: dup
      30: iconst_5
      31: ldc           #1                  // int 49181
      33: iastore
      34: areturn

  public void processClientExtensions(java.util.Hashtable) throws java.io.IOException;
    Code:
       0: aload_0
       1: aload_1
       2: invokespecial #90                 // Method org/bouncycastle/crypto/tls/AbstractTlsServer.processClientExtensions:(Ljava/util/Hashtable;)V
       5: aload_0
       6: aload_1
       7: invokestatic  #100                // Method org/bouncycastle/crypto/tls/TlsSRPUtils.getSRPExtension:(Ljava/util/Hashtable;)[B
      10: putfield      #85                 // Field srpIdentity:[B
      13: return

  public int getSelectedCipherSuite() throws java.io.IOException;
    Code:
       0: aload_0
       1: invokespecial #89                 // Method org/bouncycastle/crypto/tls/AbstractTlsServer.getSelectedCipherSuite:()I
       4: istore_1
       5: iload_1
       6: invokestatic  #99                 // Method org/bouncycastle/crypto/tls/TlsSRPUtils.isSRPCipherSuite:(I)Z
       9: ifeq          53
      12: aload_0
      13: getfield      #85                 // Field srpIdentity:[B
      16: ifnull        36
      19: aload_0
      20: aload_0
      21: getfield      #87                 // Field srpIdentityManager:Lorg/bouncycastle/crypto/tls/TlsSRPIdentityManager;
      24: aload_0
      25: getfield      #85                 // Field srpIdentity:[B
      28: invokeinterface #102,  2          // InterfaceMethod org/bouncycastle/crypto/tls/TlsSRPIdentityManager.getLoginParameters:([B)Lorg/bouncycastle/crypto/tls/TlsSRPLoginParameters;
      33: putfield      #88                 // Field loginParameters:Lorg/bouncycastle/crypto/tls/TlsSRPLoginParameters;
      36: aload_0
      37: getfield      #88                 // Field loginParameters:Lorg/bouncycastle/crypto/tls/TlsSRPLoginParameters;
      40: ifnonnull     53
      43: new           #46                 // class org/bouncycastle/crypto/tls/TlsFatalAlert
      46: dup
      47: bipush        115
      49: invokespecial #97                 // Method org/bouncycastle/crypto/tls/TlsFatalAlert."<init>":(S)V
      52: athrow
      53: iload_1
      54: ireturn

  public org.bouncycastle.crypto.tls.TlsCredentials getCredentials() throws java.io.IOException;
    Code:
       0: aload_0
       1: getfield      #84                 // Field selectedCipherSuite:I
       4: invokestatic  #101                // Method org/bouncycastle/crypto/tls/TlsUtils.getKeyExchangeAlgorithm:(I)I
       7: istore_1
       8: iload_1
       9: tableswitch   { // 21 to 23
                    21: 36
                    22: 38
                    23: 43
               default: 48
          }
      36: aconst_null
      37: areturn
      38: aload_0
      39: invokevirtual #94                 // Method getDSASignerCredentials:()Lorg/bouncycastle/crypto/tls/TlsSignerCredentials;
      42: areturn
      43: aload_0
      44: invokevirtual #95                 // Method getRSASignerCredentials:()Lorg/bouncycastle/crypto/tls/TlsSignerCredentials;
      47: areturn
      48: new           #46                 // class org/bouncycastle/crypto/tls/TlsFatalAlert
      51: dup
      52: bipush        80
      54: invokespecial #97                 // Method org/bouncycastle/crypto/tls/TlsFatalAlert."<init>":(S)V
      57: athrow

  public org.bouncycastle.crypto.tls.TlsKeyExchange getKeyExchange() throws java.io.IOException;
    Code:
       0: aload_0
       1: getfield      #84                 // Field selectedCipherSuite:I
       4: invokestatic  #101                // Method org/bouncycastle/crypto/tls/TlsUtils.getKeyExchangeAlgorithm:(I)I
       7: istore_1
       8: iload_1
       9: tableswitch   { // 21 to 23
                    21: 36
                    22: 36
                    23: 36
               default: 42
          }
      36: aload_0
      37: iload_1
      38: invokevirtual #93                 // Method createSRPKeyExchange:(I)Lorg/bouncycastle/crypto/tls/TlsKeyExchange;
      41: areturn
      42: new           #46                 // class org/bouncycastle/crypto/tls/TlsFatalAlert
      45: dup
      46: bipush        80
      48: invokespecial #97                 // Method org/bouncycastle/crypto/tls/TlsFatalAlert."<init>":(S)V
      51: athrow

  protected org.bouncycastle.crypto.tls.TlsKeyExchange createSRPKeyExchange(int);
    Code:
       0: new           #48                 // class org/bouncycastle/crypto/tls/TlsSRPKeyExchange
       3: dup
       4: iload_1
       5: aload_0
       6: getfield      #86                 // Field supportedSignatureAlgorithms:Ljava/util/Vector;
       9: aload_0
      10: getfield      #85                 // Field srpIdentity:[B
      13: aload_0
      14: getfield      #88                 // Field loginParameters:Lorg/bouncycastle/crypto/tls/TlsSRPLoginParameters;
      17: invokespecial #98                 // Method org/bouncycastle/crypto/tls/TlsSRPKeyExchange."<init>":(ILjava/util/Vector;[BLorg/bouncycastle/crypto/tls/TlsSRPLoginParameters;)V
      20: areturn
}
