public class org.bouncycastle.crypto.tls.TlsSRTPUtils {
  public static final java.lang.Integer EXT_use_srtp;

  public org.bouncycastle.crypto.tls.TlsSRTPUtils();
    Code:
       0: aload_0
       1: invokespecial #94                 // Method java/lang/Object."<init>":()V
       4: return

  public static void addUseSRTPExtension(java.util.Hashtable, org.bouncycastle.crypto.tls.UseSRTPData) throws java.io.IOException;
    Code:
       0: aload_0
       1: getstatic     #89                 // Field EXT_use_srtp:Ljava/lang/Integer;
       4: aload_1
       5: invokestatic  #98                 // Method createUseSRTPExtension:(Lorg/bouncycastle/crypto/tls/UseSRTPData;)[B
       8: invokevirtual #95                 // Method java/util/Hashtable.put:(Ljava/lang/Object;Ljava/lang/Object;)Ljava/lang/Object;
      11: pop
      12: return

  public static org.bouncycastle.crypto.tls.UseSRTPData getUseSRTPExtension(java.util.Hashtable) throws java.io.IOException;
    Code:
       0: aload_0
       1: getstatic     #89                 // Field EXT_use_srtp:Ljava/lang/Integer;
       4: invokestatic  #105                // Method org/bouncycastle/crypto/tls/TlsUtils.getExtensionData:(Ljava/util/Hashtable;Ljava/lang/Integer;)[B
       7: astore_1
       8: aload_1
       9: ifnonnull     16
      12: aconst_null
      13: goto          20
      16: aload_1
      17: invokestatic  #99                 // Method readUseSRTPExtension:([B)Lorg/bouncycastle/crypto/tls/UseSRTPData;
      20: areturn

  public static byte[] createUseSRTPExtension(org.bouncycastle.crypto.tls.UseSRTPData) throws java.io.IOException;
    Code:
       0: aload_0
       1: ifnonnull     14
       4: new           #45                 // class java/lang/IllegalArgumentException
       7: dup
       8: ldc           #2                  // String \'useSRTPData\' cannot be null
      10: invokespecial #93                 // Method java/lang/IllegalArgumentException."<init>":(Ljava/lang/String;)V
      13: athrow
      14: new           #43                 // class java/io/ByteArrayOutputStream
      17: dup
      18: invokespecial #91                 // Method java/io/ByteArrayOutputStream."<init>":()V
      21: astore_1
      22: aload_0
      23: invokevirtual #107                // Method org/bouncycastle/crypto/tls/UseSRTPData.getProtectionProfiles:()[I
      26: aload_1
      27: invokestatic  #104                // Method org/bouncycastle/crypto/tls/TlsUtils.writeUint16ArrayWithUint16Length:([ILjava/io/OutputStream;)V
      30: aload_0
      31: invokevirtual #106                // Method org/bouncycastle/crypto/tls/UseSRTPData.getMki:()[B
      34: aload_1
      35: invokestatic  #103                // Method org/bouncycastle/crypto/tls/TlsUtils.writeOpaque8:([BLjava/io/OutputStream;)V
      38: aload_1
      39: invokevirtual #92                 // Method java/io/ByteArrayOutputStream.toByteArray:()[B
      42: areturn

  public static org.bouncycastle.crypto.tls.UseSRTPData readUseSRTPExtension(byte[]) throws java.io.IOException;
    Code:
       0: aload_0
       1: ifnonnull     14
       4: new           #45                 // class java/lang/IllegalArgumentException
       7: dup
       8: ldc           #1                  // String \'extensionData\' cannot be null
      10: invokespecial #93                 // Method java/lang/IllegalArgumentException."<init>":(Ljava/lang/String;)V
      13: athrow
      14: new           #42                 // class java/io/ByteArrayInputStream
      17: dup
      18: aload_0
      19: invokespecial #90                 // Method java/io/ByteArrayInputStream."<init>":([B)V
      22: astore_1
      23: aload_1
      24: invokestatic  #101                // Method org/bouncycastle/crypto/tls/TlsUtils.readUint16:(Ljava/io/InputStream;)I
      27: istore_2
      28: iload_2
      29: iconst_2
      30: if_icmplt     39
      33: iload_2
      34: iconst_1
      35: iand
      36: ifeq          49
      39: new           #48                 // class org/bouncycastle/crypto/tls/TlsFatalAlert
      42: dup
      43: bipush        50
      45: invokespecial #96                 // Method org/bouncycastle/crypto/tls/TlsFatalAlert."<init>":(S)V
      48: athrow
      49: iload_2
      50: iconst_2
      51: idiv
      52: aload_1
      53: invokestatic  #100                // Method org/bouncycastle/crypto/tls/TlsUtils.readUint16Array:(ILjava/io/InputStream;)[I
      56: astore_3
      57: aload_1
      58: invokestatic  #102                // Method org/bouncycastle/crypto/tls/TlsUtils.readOpaque8:(Ljava/io/InputStream;)[B
      61: astore        4
      63: aload_1
      64: invokestatic  #97                 // Method org/bouncycastle/crypto/tls/TlsProtocol.assertEmpty:(Ljava/io/ByteArrayInputStream;)V
      67: new           #52                 // class org/bouncycastle/crypto/tls/UseSRTPData
      70: dup
      71: aload_3
      72: aload         4
      74: invokespecial #108                // Method org/bouncycastle/crypto/tls/UseSRTPData."<init>":([I[B)V
      77: areturn

  static {};
    Code:
       0: bipush        14
       2: invokestatic  #109                // Method org/bouncycastle/util/Integers.valueOf:(I)Ljava/lang/Integer;
       5: putstatic     #89                 // Field EXT_use_srtp:Ljava/lang/Integer;
       8: return
}
