Compiled from "RedeliveryErrorHandler.java"
class org.apache.camel.processor.RedeliveryErrorHandler$AsyncRedeliveryTask implements java.util.concurrent.Callable<java.lang.Boolean> {
  private final org.apache.camel.Exchange exchange;

  private final org.apache.camel.AsyncCallback callback;

  private final org.apache.camel.processor.RedeliveryErrorHandler$RedeliveryData data;

  final org.apache.camel.processor.RedeliveryErrorHandler this$0;

  public org.apache.camel.processor.RedeliveryErrorHandler$AsyncRedeliveryTask(org.apache.camel.processor.RedeliveryErrorHandler, org.apache.camel.Exchange, org.apache.camel.AsyncCallback, org.apache.camel.processor.RedeliveryErrorHandler$RedeliveryData);
    Code:
       0: aload_0
       1: aload_1
       2: putfield      #30                 // Field this$0:Lorg/apache/camel/processor/RedeliveryErrorHandler;
       5: aload_0
       6: invokespecial #33                 // Method java/lang/Object."<init>":()V
       9: aload_0
      10: aload_2
      11: putfield      #35                 // Field exchange:Lorg/apache/camel/Exchange;
      14: aload_0
      15: aload_3
      16: putfield      #37                 // Field callback:Lorg/apache/camel/AsyncCallback;
      19: aload_0
      20: aload         4
      22: putfield      #39                 // Field data:Lorg/apache/camel/processor/RedeliveryErrorHandler$RedeliveryData;
      25: return

  public java.lang.Boolean call() throws java.lang.Exception;
    Code:
       0: aload_0
       1: getfield      #30                 // Field this$0:Lorg/apache/camel/processor/RedeliveryErrorHandler;
       4: aload_0
       5: getfield      #35                 // Field exchange:Lorg/apache/camel/Exchange;
       8: aload_0
       9: getfield      #39                 // Field data:Lorg/apache/camel/processor/RedeliveryErrorHandler$RedeliveryData;
      12: invokevirtual #49                 // Method org/apache/camel/processor/RedeliveryErrorHandler.prepareExchangeForRedelivery:(Lorg/apache/camel/Exchange;Lorg/apache/camel/processor/RedeliveryErrorHandler$RedeliveryData;)V
      15: aload_0
      16: getfield      #30                 // Field this$0:Lorg/apache/camel/processor/RedeliveryErrorHandler;
      19: aload_0
      20: getfield      #35                 // Field exchange:Lorg/apache/camel/Exchange;
      23: aload_0
      24: getfield      #39                 // Field data:Lorg/apache/camel/processor/RedeliveryErrorHandler$RedeliveryData;
      27: invokevirtual #52                 // Method org/apache/camel/processor/RedeliveryErrorHandler.deliverToOnRedeliveryProcessor:(Lorg/apache/camel/Exchange;Lorg/apache/camel/processor/RedeliveryErrorHandler$RedeliveryData;)V
      30: aload_0
      31: getfield      #30                 // Field this$0:Lorg/apache/camel/processor/RedeliveryErrorHandler;
      34: getfield      #56                 // Field org/apache/camel/processor/RedeliveryErrorHandler.log:Lorg/slf4j/Logger;
      37: invokeinterface #62,  1           // InterfaceMethod org/slf4j/Logger.isTraceEnabled:()Z
      42: ifeq          92
      45: aload_0
      46: getfield      #30                 // Field this$0:Lorg/apache/camel/processor/RedeliveryErrorHandler;
      49: getfield      #56                 // Field org/apache/camel/processor/RedeliveryErrorHandler.log:Lorg/slf4j/Logger;
      52: ldc           #64                 // String Redelivering exchangeId: {} -> {} for Exchange: {}
      54: iconst_3
      55: anewarray     #5                  // class java/lang/Object
      58: dup
      59: iconst_0
      60: aload_0
      61: getfield      #35                 // Field exchange:Lorg/apache/camel/Exchange;
      64: invokeinterface #70,  1           // InterfaceMethod org/apache/camel/Exchange.getExchangeId:()Ljava/lang/String;
      69: aastore
      70: dup
      71: iconst_1
      72: aload_0
      73: getfield      #30                 // Field this$0:Lorg/apache/camel/processor/RedeliveryErrorHandler;
      76: getfield      #74                 // Field org/apache/camel/processor/RedeliveryErrorHandler.outputAsync:Lorg/apache/camel/AsyncProcessor;
      79: aastore
      80: dup
      81: iconst_2
      82: aload_0
      83: getfield      #35                 // Field exchange:Lorg/apache/camel/Exchange;
      86: aastore
      87: invokeinterface #78,  3           // InterfaceMethod org/slf4j/Logger.trace:(Ljava/lang/String;[Ljava/lang/Object;)V
      92: aload_0
      93: getfield      #35                 // Field exchange:Lorg/apache/camel/Exchange;
      96: invokeinterface #82,  1           // InterfaceMethod org/apache/camel/Exchange.getContext:()Lorg/apache/camel/CamelContext;
     101: aload_0
     102: getfield      #35                 // Field exchange:Lorg/apache/camel/Exchange;
     105: aload_0
     106: getfield      #39                 // Field data:Lorg/apache/camel/processor/RedeliveryErrorHandler$RedeliveryData;
     109: getfield      #86                 // Field org/apache/camel/processor/RedeliveryErrorHandler$RedeliveryData.redeliveryCounter:I
     112: invokestatic  #92                 // Method org/apache/camel/util/EventHelper.notifyExchangeRedelivery:(Lorg/apache/camel/CamelContext;Lorg/apache/camel/Exchange;I)V
     115: aload_0
     116: getfield      #39                 // Field data:Lorg/apache/camel/processor/RedeliveryErrorHandler$RedeliveryData;
     119: getfield      #96                 // Field org/apache/camel/processor/RedeliveryErrorHandler$RedeliveryData.redeliverFromSync:Z
     122: ifeq          153
     125: aload_0
     126: getfield      #30                 // Field this$0:Lorg/apache/camel/processor/RedeliveryErrorHandler;
     129: getfield      #74                 // Field org/apache/camel/processor/RedeliveryErrorHandler.outputAsync:Lorg/apache/camel/AsyncProcessor;
     132: aload_0
     133: getfield      #35                 // Field exchange:Lorg/apache/camel/Exchange;
     136: new           #15                 // class org/apache/camel/processor/RedeliveryErrorHandler$AsyncRedeliveryTask$1
     139: dup
     140: aload_0
     141: invokespecial #99                 // Method org/apache/camel/processor/RedeliveryErrorHandler$AsyncRedeliveryTask$1."<init>":(Lorg/apache/camel/processor/RedeliveryErrorHandler$AsyncRedeliveryTask;)V
     144: invokeinterface #105,  3          // InterfaceMethod org/apache/camel/AsyncProcessor.process:(Lorg/apache/camel/Exchange;Lorg/apache/camel/AsyncCallback;)Z
     149: istore_1
     150: goto          178
     153: aload_0
     154: getfield      #30                 // Field this$0:Lorg/apache/camel/processor/RedeliveryErrorHandler;
     157: getfield      #74                 // Field org/apache/camel/processor/RedeliveryErrorHandler.outputAsync:Lorg/apache/camel/AsyncProcessor;
     160: aload_0
     161: getfield      #35                 // Field exchange:Lorg/apache/camel/Exchange;
     164: new           #13                 // class org/apache/camel/processor/RedeliveryErrorHandler$AsyncRedeliveryTask$2
     167: dup
     168: aload_0
     169: invokespecial #106                // Method org/apache/camel/processor/RedeliveryErrorHandler$AsyncRedeliveryTask$2."<init>":(Lorg/apache/camel/processor/RedeliveryErrorHandler$AsyncRedeliveryTask;)V
     172: invokeinterface #105,  3          // InterfaceMethod org/apache/camel/AsyncProcessor.process:(Lorg/apache/camel/Exchange;Lorg/apache/camel/AsyncCallback;)Z
     177: istore_1
     178: iload_1
     179: invokestatic  #112                // Method java/lang/Boolean.valueOf:(Z)Ljava/lang/Boolean;
     182: areturn

  public java.lang.Object call() throws java.lang.Exception;
    Code:
       0: aload_0
       1: invokevirtual #116                // Method call:()Ljava/lang/Boolean;
       4: areturn

  static org.apache.camel.Exchange access$000(org.apache.camel.processor.RedeliveryErrorHandler$AsyncRedeliveryTask);
    Code:
       0: aload_0
       1: getfield      #35                 // Field exchange:Lorg/apache/camel/Exchange;
       4: areturn

  static org.apache.camel.processor.RedeliveryErrorHandler$RedeliveryData access$100(org.apache.camel.processor.RedeliveryErrorHandler$AsyncRedeliveryTask);
    Code:
       0: aload_0
       1: getfield      #39                 // Field data:Lorg/apache/camel/processor/RedeliveryErrorHandler$RedeliveryData;
       4: areturn

  static org.apache.camel.AsyncCallback access$200(org.apache.camel.processor.RedeliveryErrorHandler$AsyncRedeliveryTask);
    Code:
       0: aload_0
       1: getfield      #37                 // Field callback:Lorg/apache/camel/AsyncCallback;
       4: areturn
}
