Compiled from "WireTapProcessor.java"
public class org.apache.camel.processor.WireTapProcessor extends org.apache.camel.support.ServiceSupport implements org.apache.camel.AsyncProcessor,org.apache.camel.Traceable {
  private static final org.slf4j.Logger LOG;

  private final org.apache.camel.Endpoint destination;

  private final org.apache.camel.Processor processor;

  private final org.apache.camel.ExchangePattern exchangePattern;

  private final java.util.concurrent.ExecutorService executorService;

  private volatile boolean shutdownExecutorService;

  private org.apache.camel.Expression newExchangeExpression;

  private java.util.List<org.apache.camel.Processor> newExchangeProcessors;

  private boolean copy;

  private org.apache.camel.Processor onPrepare;

  public org.apache.camel.processor.WireTapProcessor(org.apache.camel.Endpoint, org.apache.camel.Processor, org.apache.camel.ExchangePattern, java.util.concurrent.ExecutorService, boolean);
    Code:
       0: aload_0
       1: invokespecial #35                 // Method org/apache/camel/support/ServiceSupport."<init>":()V
       4: aload_0
       5: aload_1
       6: putfield      #37                 // Field destination:Lorg/apache/camel/Endpoint;
       9: aload_0
      10: aload_2
      11: putfield      #39                 // Field processor:Lorg/apache/camel/Processor;
      14: aload_0
      15: aload_3
      16: putfield      #41                 // Field exchangePattern:Lorg/apache/camel/ExchangePattern;
      19: aload         4
      21: ldc           #42                 // String executorService
      23: invokestatic  #48                 // Method org/apache/camel/util/ObjectHelper.notNull:(Ljava/lang/Object;Ljava/lang/String;)Ljava/lang/Object;
      26: pop
      27: aload_0
      28: aload         4
      30: putfield      #50                 // Field executorService:Ljava/util/concurrent/ExecutorService;
      33: aload_0
      34: iload         5
      36: putfield      #52                 // Field shutdownExecutorService:Z
      39: return

  public java.lang.String toString();
    Code:
       0: new           #58                 // class java/lang/StringBuilder
       3: dup
       4: invokespecial #59                 // Method java/lang/StringBuilder."<init>":()V
       7: ldc           #61                 // String WireTap[
       9: invokevirtual #65                 // Method java/lang/StringBuilder.append:(Ljava/lang/String;)Ljava/lang/StringBuilder;
      12: aload_0
      13: getfield      #37                 // Field destination:Lorg/apache/camel/Endpoint;
      16: invokevirtual #68                 // Method java/lang/StringBuilder.append:(Ljava/lang/Object;)Ljava/lang/StringBuilder;
      19: ldc           #70                 // String ]
      21: invokevirtual #65                 // Method java/lang/StringBuilder.append:(Ljava/lang/String;)Ljava/lang/StringBuilder;
      24: invokevirtual #72                 // Method java/lang/StringBuilder.toString:()Ljava/lang/String;
      27: areturn

  public java.lang.String getTraceLabel();
    Code:
       0: new           #58                 // class java/lang/StringBuilder
       3: dup
       4: invokespecial #59                 // Method java/lang/StringBuilder."<init>":()V
       7: ldc           #75                 // String wireTap(
       9: invokevirtual #65                 // Method java/lang/StringBuilder.append:(Ljava/lang/String;)Ljava/lang/StringBuilder;
      12: aload_0
      13: getfield      #37                 // Field destination:Lorg/apache/camel/Endpoint;
      16: invokevirtual #68                 // Method java/lang/StringBuilder.append:(Ljava/lang/Object;)Ljava/lang/StringBuilder;
      19: ldc           #77                 // String )
      21: invokevirtual #65                 // Method java/lang/StringBuilder.append:(Ljava/lang/String;)Ljava/lang/StringBuilder;
      24: invokevirtual #72                 // Method java/lang/StringBuilder.toString:()Ljava/lang/String;
      27: areturn

  public void process(org.apache.camel.Exchange) throws java.lang.Exception;
    Code:
       0: aload_0
       1: aload_1
       2: invokestatic  #86                 // Method org/apache/camel/util/AsyncProcessorHelper.process:(Lorg/apache/camel/AsyncProcessor;Lorg/apache/camel/Exchange;)V
       5: return

  public boolean process(org.apache.camel.Exchange, org.apache.camel.AsyncCallback);
    Code:
       0: aload_0
       1: invokevirtual #93                 // Method isStarted:()Z
       4: ifne          34
       7: new           #95                 // class java/lang/IllegalStateException
      10: dup
      11: new           #58                 // class java/lang/StringBuilder
      14: dup
      15: invokespecial #59                 // Method java/lang/StringBuilder."<init>":()V
      18: ldc           #97                 // String WireTapProcessor has not been started:
      20: invokevirtual #65                 // Method java/lang/StringBuilder.append:(Ljava/lang/String;)Ljava/lang/StringBuilder;
      23: aload_0
      24: invokevirtual #68                 // Method java/lang/StringBuilder.append:(Ljava/lang/Object;)Ljava/lang/StringBuilder;
      27: invokevirtual #72                 // Method java/lang/StringBuilder.toString:()Ljava/lang/String;
      30: invokespecial #100                // Method java/lang/IllegalStateException."<init>":(Ljava/lang/String;)V
      33: athrow
      34: aload_0
      35: aload_1
      36: aload_0
      37: getfield      #41                 // Field exchangePattern:Lorg/apache/camel/ExchangePattern;
      40: invokevirtual #104                // Method configureExchange:(Lorg/apache/camel/Exchange;Lorg/apache/camel/ExchangePattern;)Lorg/apache/camel/Exchange;
      43: astore_3
      44: aload_0
      45: getfield      #50                 // Field executorService:Ljava/util/concurrent/ExecutorService;
      48: new           #11                 // class org/apache/camel/processor/WireTapProcessor$1
      51: dup
      52: aload_0
      53: aload_3
      54: invokespecial #107                // Method org/apache/camel/processor/WireTapProcessor$1."<init>":(Lorg/apache/camel/processor/WireTapProcessor;Lorg/apache/camel/Exchange;)V
      57: invokeinterface #113,  2          // InterfaceMethod java/util/concurrent/ExecutorService.submit:(Ljava/util/concurrent/Callable;)Ljava/util/concurrent/Future;
      62: pop
      63: aload_2
      64: iconst_1
      65: invokeinterface #119,  2          // InterfaceMethod org/apache/camel/AsyncCallback.done:(Z)V
      70: iconst_1
      71: ireturn

  protected org.apache.camel.Exchange configureExchange(org.apache.camel.Exchange, org.apache.camel.ExchangePattern);
    Code:
       0: aload_0
       1: getfield      #124                // Field copy:Z
       4: ifeq          16
       7: aload_0
       8: aload_1
       9: invokespecial #128                // Method configureCopyExchange:(Lorg/apache/camel/Exchange;)Lorg/apache/camel/Exchange;
      12: astore_3
      13: goto          22
      16: aload_0
      17: aload_1
      18: invokespecial #131                // Method configureNewExchange:(Lorg/apache/camel/Exchange;)Lorg/apache/camel/Exchange;
      21: astore_3
      22: aload_3
      23: ldc           #135                // String CamelToEndpoint
      25: aload_0
      26: getfield      #37                 // Field destination:Lorg/apache/camel/Endpoint;
      29: invokeinterface #140,  1          // InterfaceMethod org/apache/camel/Endpoint.getEndpointUri:()Ljava/lang/String;
      34: invokeinterface #144,  3          // InterfaceMethod org/apache/camel/Exchange.setProperty:(Ljava/lang/String;Ljava/lang/Object;)V
      39: aload_0
      40: getfield      #146                // Field newExchangeExpression:Lorg/apache/camel/Expression;
      43: ifnull        78
      46: aload_0
      47: getfield      #146                // Field newExchangeExpression:Lorg/apache/camel/Expression;
      50: aload_3
      51: ldc           #148                // class java/lang/Object
      53: invokeinterface #154,  3          // InterfaceMethod org/apache/camel/Expression.evaluate:(Lorg/apache/camel/Exchange;Ljava/lang/Class;)Ljava/lang/Object;
      58: astore        4
      60: aload         4
      62: ifnull        78
      65: aload_3
      66: invokeinterface #158,  1          // InterfaceMethod org/apache/camel/Exchange.getIn:()Lorg/apache/camel/Message;
      71: aload         4
      73: invokeinterface #164,  2          // InterfaceMethod org/apache/camel/Message.setBody:(Ljava/lang/Object;)V
      78: aload_0
      79: getfield      #166                // Field newExchangeProcessors:Ljava/util/List;
      82: ifnull        140
      85: aload_0
      86: getfield      #166                // Field newExchangeProcessors:Ljava/util/List;
      89: invokeinterface #172,  1          // InterfaceMethod java/util/List.iterator:()Ljava/util/Iterator;
      94: astore        4
      96: aload         4
      98: invokeinterface #177,  1          // InterfaceMethod java/util/Iterator.hasNext:()Z
     103: ifeq          140
     106: aload         4
     108: invokeinterface #181,  1          // InterfaceMethod java/util/Iterator.next:()Ljava/lang/Object;
     113: checkcast     #183                // class org/apache/camel/Processor
     116: astore        5
     118: aload         5
     120: aload_3
     121: invokeinterface #185,  2          // InterfaceMethod org/apache/camel/Processor.process:(Lorg/apache/camel/Exchange;)V
     126: goto          137
     129: astore        6
     131: aload         6
     133: invokestatic  #191                // Method org/apache/camel/util/ObjectHelper.wrapRuntimeCamelException:(Ljava/lang/Throwable;)Lorg/apache/camel/RuntimeCamelException;
     136: athrow
     137: goto          96
     140: aload_0
     141: getfield      #193                // Field onPrepare:Lorg/apache/camel/Processor;
     144: ifnull        168
     147: aload_0
     148: getfield      #193                // Field onPrepare:Lorg/apache/camel/Processor;
     151: aload_3
     152: invokeinterface #185,  2          // InterfaceMethod org/apache/camel/Processor.process:(Lorg/apache/camel/Exchange;)V
     157: goto          168
     160: astore        4
     162: aload         4
     164: invokestatic  #191                // Method org/apache/camel/util/ObjectHelper.wrapRuntimeCamelException:(Ljava/lang/Throwable;)Lorg/apache/camel/RuntimeCamelException;
     167: athrow
     168: aload_3
     169: areturn
    Exception table:
       from    to  target type
         118   126   129   Class java/lang/Exception
         147   157   160   Class java/lang/Exception

  private org.apache.camel.Exchange configureCopyExchange(org.apache.camel.Exchange);
    Code:
       0: aload_1
       1: iconst_0
       2: invokestatic  #207                // Method org/apache/camel/util/ExchangeHelper.createCorrelatedCopy:(Lorg/apache/camel/Exchange;Z)Lorg/apache/camel/Exchange;
       5: astore_2
       6: aload_2
       7: getstatic     #210                // Field org/apache/camel/ExchangePattern.InOnly:Lorg/apache/camel/ExchangePattern;
      10: invokeinterface #214,  2          // InterfaceMethod org/apache/camel/Exchange.setPattern:(Lorg/apache/camel/ExchangePattern;)V
      15: aload_2
      16: areturn

  private org.apache.camel.Exchange configureNewExchange(org.apache.camel.Exchange);
    Code:
       0: new           #216                // class org/apache/camel/impl/DefaultExchange
       3: dup
       4: aload_1
       5: invokeinterface #220,  1          // InterfaceMethod org/apache/camel/Exchange.getFromEndpoint:()Lorg/apache/camel/Endpoint;
      10: getstatic     #210                // Field org/apache/camel/ExchangePattern.InOnly:Lorg/apache/camel/ExchangePattern;
      13: invokespecial #223                // Method org/apache/camel/impl/DefaultExchange."<init>":(Lorg/apache/camel/Endpoint;Lorg/apache/camel/ExchangePattern;)V
      16: areturn

  public java.util.List<org.apache.camel.Processor> getNewExchangeProcessors();
    Code:
       0: aload_0
       1: getfield      #166                // Field newExchangeProcessors:Ljava/util/List;
       4: areturn

  public void setNewExchangeProcessors(java.util.List<org.apache.camel.Processor>);
    Code:
       0: aload_0
       1: aload_1
       2: putfield      #166                // Field newExchangeProcessors:Ljava/util/List;
       5: return

  public org.apache.camel.Expression getNewExchangeExpression();
    Code:
       0: aload_0
       1: getfield      #146                // Field newExchangeExpression:Lorg/apache/camel/Expression;
       4: areturn

  public void setNewExchangeExpression(org.apache.camel.Expression);
    Code:
       0: aload_0
       1: aload_1
       2: putfield      #146                // Field newExchangeExpression:Lorg/apache/camel/Expression;
       5: return

  public void addNewExchangeProcessor(org.apache.camel.Processor);
    Code:
       0: aload_0
       1: getfield      #166                // Field newExchangeProcessors:Ljava/util/List;
       4: ifnonnull     18
       7: aload_0
       8: new           #235                // class java/util/ArrayList
      11: dup
      12: invokespecial #236                // Method java/util/ArrayList."<init>":()V
      15: putfield      #166                // Field newExchangeProcessors:Ljava/util/List;
      18: aload_0
      19: getfield      #166                // Field newExchangeProcessors:Ljava/util/List;
      22: aload_1
      23: invokeinterface #240,  2          // InterfaceMethod java/util/List.add:(Ljava/lang/Object;)Z
      28: pop
      29: return

  public boolean isCopy();
    Code:
       0: aload_0
       1: getfield      #124                // Field copy:Z
       4: ireturn

  public void setCopy(boolean);
    Code:
       0: aload_0
       1: iload_1
       2: putfield      #124                // Field copy:Z
       5: return

  public org.apache.camel.Processor getOnPrepare();
    Code:
       0: aload_0
       1: getfield      #193                // Field onPrepare:Lorg/apache/camel/Processor;
       4: areturn

  public void setOnPrepare(org.apache.camel.Processor);
    Code:
       0: aload_0
       1: aload_1
       2: putfield      #193                // Field onPrepare:Lorg/apache/camel/Processor;
       5: return

  protected void doStart() throws java.lang.Exception;
    Code:
       0: aload_0
       1: getfield      #39                 // Field processor:Lorg/apache/camel/Processor;
       4: invokestatic  #251                // Method org/apache/camel/util/ServiceHelper.startService:(Ljava/lang/Object;)V
       7: return

  protected void doStop() throws java.lang.Exception;
    Code:
       0: aload_0
       1: getfield      #39                 // Field processor:Lorg/apache/camel/Processor;
       4: invokestatic  #255                // Method org/apache/camel/util/ServiceHelper.stopService:(Ljava/lang/Object;)V
       7: return

  protected void doShutdown() throws java.lang.Exception;
    Code:
       0: aload_0
       1: getfield      #39                 // Field processor:Lorg/apache/camel/Processor;
       4: invokestatic  #259                // Method org/apache/camel/util/ServiceHelper.stopAndShutdownService:(Ljava/lang/Object;)V
       7: aload_0
       8: getfield      #52                 // Field shutdownExecutorService:Z
      11: ifeq          38
      14: aload_0
      15: getfield      #37                 // Field destination:Lorg/apache/camel/Endpoint;
      18: invokeinterface #263,  1          // InterfaceMethod org/apache/camel/Endpoint.getCamelContext:()Lorg/apache/camel/CamelContext;
      23: invokeinterface #269,  1          // InterfaceMethod org/apache/camel/CamelContext.getExecutorServiceManager:()Lorg/apache/camel/spi/ExecutorServiceManager;
      28: aload_0
      29: getfield      #50                 // Field executorService:Ljava/util/concurrent/ExecutorService;
      32: invokeinterface #275,  2          // InterfaceMethod org/apache/camel/spi/ExecutorServiceManager.shutdownNow:(Ljava/util/concurrent/ExecutorService;)Ljava/util/List;
      37: pop
      38: return

  static org.apache.camel.Endpoint access$000(org.apache.camel.processor.WireTapProcessor);
    Code:
       0: aload_0
       1: getfield      #37                 // Field destination:Lorg/apache/camel/Endpoint;
       4: areturn

  static org.slf4j.Logger access$100();
    Code:
       0: getstatic     #282                // Field LOG:Lorg/slf4j/Logger;
       3: areturn

  static org.apache.camel.Processor access$200(org.apache.camel.processor.WireTapProcessor);
    Code:
       0: aload_0
       1: getfield      #39                 // Field processor:Lorg/apache/camel/Processor;
       4: areturn

  static {};
    Code:
       0: ldc           #2                  // class org/apache/camel/processor/WireTapProcessor
       2: invokestatic  #291                // Method org/slf4j/LoggerFactory.getLogger:(Ljava/lang/Class;)Lorg/slf4j/Logger;
       5: putstatic     #282                // Field LOG:Lorg/slf4j/Logger;
       8: return
}
