Compiled from "Dispatcher.java"
class org.apache.hadoop.yarn.webapp.Dispatcher$1 extends java.util.TimerTask {
  final org.apache.hadoop.yarn.webapp.Dispatcher this$0;

  org.apache.hadoop.yarn.webapp.Dispatcher$1(org.apache.hadoop.yarn.webapp.Dispatcher);
    Code:
       0: aload_0
       1: aload_1
       2: putfield      #1                  // Field this$0:Lorg/apache/hadoop/yarn/webapp/Dispatcher;
       5: aload_0
       6: invokespecial #2                  // Method java/util/TimerTask."<init>":()V
       9: return

  public void run();
    Code:
       0: getstatic     #3                  // Field org/apache/hadoop/yarn/webapp/Dispatcher.LOG:Lorg/slf4j/Logger;
       3: ldc           #4                  // String WebAppp /{} exiting...
       5: aload_0
       6: getfield      #1                  // Field this$0:Lorg/apache/hadoop/yarn/webapp/Dispatcher;
       9: invokestatic  #5                  // Method org/apache/hadoop/yarn/webapp/Dispatcher.access$000:(Lorg/apache/hadoop/yarn/webapp/Dispatcher;)Lorg/apache/hadoop/yarn/webapp/WebApp;
      12: invokevirtual #6                  // Method org/apache/hadoop/yarn/webapp/WebApp.name:()Ljava/lang/String;
      15: invokeinterface #7,  3            // InterfaceMethod org/slf4j/Logger.info:(Ljava/lang/String;Ljava/lang/Object;)V
      20: aload_0
      21: getfield      #1                  // Field this$0:Lorg/apache/hadoop/yarn/webapp/Dispatcher;
      24: invokestatic  #5                  // Method org/apache/hadoop/yarn/webapp/Dispatcher.access$000:(Lorg/apache/hadoop/yarn/webapp/Dispatcher;)Lorg/apache/hadoop/yarn/webapp/WebApp;
      27: invokevirtual #8                  // Method org/apache/hadoop/yarn/webapp/WebApp.stop:()V
      30: iconst_0
      31: invokestatic  #9                  // Method java/lang/System.exit:(I)V
      34: return
}
