Compiled from "StrMatcher.java"
final class org.sonar.api.internal.apachecommons.lang.text.StrMatcher$CharMatcher extends org.sonar.api.internal.apachecommons.lang.text.StrMatcher {
  private final char ch;

  org.sonar.api.internal.apachecommons.lang.text.StrMatcher$CharMatcher(char);
    Code:
       0: aload_0
       1: invokespecial #13                 // Method org/sonar/api/internal/apachecommons/lang/text/StrMatcher."<init>":()V
       4: aload_0
       5: iload_1
       6: putfield      #15                 // Field ch:C
       9: return

  public int isMatch(char[], int, int, int);
    Code:
       0: aload_0
       1: getfield      #15                 // Field ch:C
       4: aload_1
       5: iload_2
       6: caload
       7: if_icmpne     14
      10: iconst_1
      11: goto          15
      14: iconst_0
      15: ireturn
}
