Compiled from "ConsoleTextEditor.java"
class groovy.ui.ConsoleTextEditor$3 implements javax.swing.event.DocumentListener {
  final groovy.ui.ConsoleTextEditor this$0;

  groovy.ui.ConsoleTextEditor$3(groovy.ui.ConsoleTextEditor);
    Code:
       0: aload_0
       1: aload_1
       2: putfield      #20                 // Field this$0:Lgroovy/ui/ConsoleTextEditor;
       5: aload_0
       6: invokespecial #21                 // Method java/lang/Object."<init>":()V
       9: return

  public void insertUpdate(javax.swing.event.DocumentEvent);
    Code:
       0: aload_0
       1: getfield      #20                 // Field this$0:Lgroovy/ui/ConsoleTextEditor;
       4: iconst_1
       5: invokestatic  #29                 // Method groovy/ui/ConsoleTextEditor.access$102:(Lgroovy/ui/ConsoleTextEditor;Z)Z
       8: pop
       9: return

  public void removeUpdate(javax.swing.event.DocumentEvent);
    Code:
       0: aload_0
       1: getfield      #20                 // Field this$0:Lgroovy/ui/ConsoleTextEditor;
       4: iconst_1
       5: invokestatic  #29                 // Method groovy/ui/ConsoleTextEditor.access$102:(Lgroovy/ui/ConsoleTextEditor;Z)Z
       8: pop
       9: return

  public void changedUpdate(javax.swing.event.DocumentEvent);
    Code:
       0: aload_0
       1: getfield      #20                 // Field this$0:Lgroovy/ui/ConsoleTextEditor;
       4: iconst_1
       5: invokestatic  #29                 // Method groovy/ui/ConsoleTextEditor.access$102:(Lgroovy/ui/ConsoleTextEditor;Z)Z
       8: pop
       9: iconst_3
      10: ldc           #35                 // class groovy/ui/Console
      12: invokestatic  #41                 // Method java/util/prefs/Preferences.userNodeForPackage:(Ljava/lang/Class;)Ljava/util/prefs/Preferences;
      15: ldc           #43                 // String fontSize
      17: bipush        12
      19: invokevirtual #47                 // Method java/util/prefs/Preferences.getInt:(Ljava/lang/String;I)I
      22: imul
      23: istore_2
      24: aload_0
      25: getfield      #20                 // Field this$0:Lgroovy/ui/ConsoleTextEditor;
      28: invokestatic  #51                 // Method groovy/ui/ConsoleTextEditor.access$200:(Lgroovy/ui/ConsoleTextEditor;)Lgroovy/ui/ConsoleTextEditor$LineNumbersPanel;
      31: new           #53                 // class java/awt/Dimension
      34: dup
      35: iload_2
      36: iload_2
      37: invokespecial #56                 // Method java/awt/Dimension."<init>":(II)V
      40: invokevirtual #60                 // Method groovy/ui/ConsoleTextEditor$LineNumbersPanel.setPreferredSize:(Ljava/awt/Dimension;)V
      43: return
}
