Compiled from "SystemOutputInterceptor.java"
final class groovy.ui.SystemOutputInterceptor$1 extends java.lang.InheritableThreadLocal<java.lang.Integer> {
  groovy.ui.SystemOutputInterceptor$1();
    Code:
       0: aload_0
       1: invokespecial #12                 // Method java/lang/InheritableThreadLocal."<init>":()V
       4: return

  protected java.lang.Integer initialValue();
    Code:
       0: iconst_0
       1: invokestatic  #22                 // Method java/lang/Integer.valueOf:(I)Ljava/lang/Integer;
       4: areturn

  protected java.lang.Object initialValue();
    Code:
       0: aload_0
       1: invokevirtual #25                 // Method initialValue:()Ljava/lang/Integer;
       4: areturn
}
