Compiled from "PixelsAreaRequestMsgOut.java"
public class org.webswing.model.s2c.PixelsAreaRequestMsgOut implements org.webswing.model.MsgOut,org.webswing.model.SyncMsg {
  private java.lang.String correlationId;

  private int x;

  private int y;

  private int w;

  private int h;

  public org.webswing.model.s2c.PixelsAreaRequestMsgOut();
    Code:
       0: aload_0
       1: invokespecial #1                  // Method java/lang/Object."<init>":()V
       4: return

  public java.lang.String getCorrelationId();
    Code:
       0: aload_0
       1: getfield      #2                  // Field correlationId:Ljava/lang/String;
       4: areturn

  public void setCorrelationId(java.lang.String);
    Code:
       0: aload_0
       1: aload_1
       2: putfield      #2                  // Field correlationId:Ljava/lang/String;
       5: return

  public int getX();
    Code:
       0: aload_0
       1: getfield      #3                  // Field x:I
       4: ireturn

  public void setX(int);
    Code:
       0: aload_0
       1: iload_1
       2: putfield      #3                  // Field x:I
       5: return

  public int getY();
    Code:
       0: aload_0
       1: getfield      #4                  // Field y:I
       4: ireturn

  public void setY(int);
    Code:
       0: aload_0
       1: iload_1
       2: putfield      #4                  // Field y:I
       5: return

  public int getW();
    Code:
       0: aload_0
       1: getfield      #5                  // Field w:I
       4: ireturn

  public void setW(int);
    Code:
       0: aload_0
       1: iload_1
       2: putfield      #5                  // Field w:I
       5: return

  public int getH();
    Code:
       0: aload_0
       1: getfield      #6                  // Field h:I
       4: ireturn

  public void setH(int);
    Code:
       0: aload_0
       1: iload_1
       2: putfield      #6                  // Field h:I
       5: return
}
