Compiled from "MongoDatabaseImpl.java"
class com.mongodb.MongoDatabaseImpl$1 implements com.mongodb.Function<org.bson.BsonDocument, java.lang.String> {
  final com.mongodb.MongoDatabaseImpl this$0;

  com.mongodb.MongoDatabaseImpl$1(com.mongodb.MongoDatabaseImpl);
    Code:
       0: aload_0
       1: aload_1
       2: putfield      #1                  // Field this$0:Lcom/mongodb/MongoDatabaseImpl;
       5: aload_0
       6: invokespecial #2                  // Method java/lang/Object."<init>":()V
       9: return

  public java.lang.String apply(org.bson.BsonDocument);
    Code:
       0: aload_1
       1: ldc           #3                  // String name
       3: invokevirtual #4                  // Method org/bson/BsonDocument.getString:(Ljava/lang/Object;)Lorg/bson/BsonString;
       6: invokevirtual #5                  // Method org/bson/BsonString.getValue:()Ljava/lang/String;
       9: areturn

  public java.lang.Object apply(java.lang.Object);
    Code:
       0: aload_0
       1: aload_1
       2: checkcast     #6                  // class org/bson/BsonDocument
       5: invokevirtual #7                  // Method apply:(Lorg/bson/BsonDocument;)Ljava/lang/String;
       8: areturn
}
