Compiled from "CorsWebFilter.java"
public class org.springframework.web.cors.reactive.CorsWebFilter implements org.springframework.web.server.WebFilter {
  private final org.springframework.web.cors.reactive.CorsConfigurationSource configSource;

  private final org.springframework.web.cors.reactive.CorsProcessor processor;

  public org.springframework.web.cors.reactive.CorsWebFilter(org.springframework.web.cors.reactive.CorsConfigurationSource);
    Code:
       0: aload_0
       1: aload_1
       2: new           #1                  // class org/springframework/web/cors/reactive/DefaultCorsProcessor
       5: dup
       6: invokespecial #2                  // Method org/springframework/web/cors/reactive/DefaultCorsProcessor."<init>":()V
       9: invokespecial #3                  // Method "<init>":(Lorg/springframework/web/cors/reactive/CorsConfigurationSource;Lorg/springframework/web/cors/reactive/CorsProcessor;)V
      12: return

  public org.springframework.web.cors.reactive.CorsWebFilter(org.springframework.web.cors.reactive.CorsConfigurationSource, org.springframework.web.cors.reactive.CorsProcessor);
    Code:
       0: aload_0
       1: invokespecial #4                  // Method java/lang/Object."<init>":()V
       4: aload_1
       5: ldc           #5                  // String CorsConfigurationSource must not be null
       7: invokestatic  #6                  // Method org/springframework/util/Assert.notNull:(Ljava/lang/Object;Ljava/lang/String;)V
      10: aload_2
      11: ldc           #7                  // String CorsProcessor must not be null
      13: invokestatic  #6                  // Method org/springframework/util/Assert.notNull:(Ljava/lang/Object;Ljava/lang/String;)V
      16: aload_0
      17: aload_1
      18: putfield      #8                  // Field configSource:Lorg/springframework/web/cors/reactive/CorsConfigurationSource;
      21: aload_0
      22: aload_2
      23: putfield      #9                  // Field processor:Lorg/springframework/web/cors/reactive/CorsProcessor;
      26: return

  public reactor.core.publisher.Mono<java.lang.Void> filter(org.springframework.web.server.ServerWebExchange, org.springframework.web.server.WebFilterChain);
    Code:
       0: aload_1
       1: invokeinterface #10,  1           // InterfaceMethod org/springframework/web/server/ServerWebExchange.getRequest:()Lorg/springframework/http/server/reactive/ServerHttpRequest;
       6: astore_3
       7: aload_3
       8: invokestatic  #11                 // Method org/springframework/web/cors/reactive/CorsUtils.isCorsRequest:(Lorg/springframework/http/server/reactive/ServerHttpRequest;)Z
      11: ifeq          61
      14: aload_0
      15: getfield      #8                  // Field configSource:Lorg/springframework/web/cors/reactive/CorsConfigurationSource;
      18: aload_1
      19: invokeinterface #12,  2           // InterfaceMethod org/springframework/web/cors/reactive/CorsConfigurationSource.getCorsConfiguration:(Lorg/springframework/web/server/ServerWebExchange;)Lorg/springframework/web/cors/CorsConfiguration;
      24: astore        4
      26: aload         4
      28: ifnull        61
      31: aload_0
      32: getfield      #9                  // Field processor:Lorg/springframework/web/cors/reactive/CorsProcessor;
      35: aload         4
      37: aload_1
      38: invokeinterface #13,  3           // InterfaceMethod org/springframework/web/cors/reactive/CorsProcessor.process:(Lorg/springframework/web/cors/CorsConfiguration;Lorg/springframework/web/server/ServerWebExchange;)Z
      43: istore        5
      45: iload         5
      47: ifeq          57
      50: aload_3
      51: invokestatic  #14                 // Method org/springframework/web/cors/reactive/CorsUtils.isPreFlightRequest:(Lorg/springframework/http/server/reactive/ServerHttpRequest;)Z
      54: ifeq          61
      57: invokestatic  #15                 // Method reactor/core/publisher/Mono.empty:()Lreactor/core/publisher/Mono;
      60: areturn
      61: aload_2
      62: aload_1
      63: invokeinterface #16,  2           // InterfaceMethod org/springframework/web/server/WebFilterChain.filter:(Lorg/springframework/web/server/ServerWebExchange;)Lreactor/core/publisher/Mono;
      68: areturn
}
