Compiled from "CorsUtils.java"
public abstract class org.springframework.web.cors.reactive.CorsUtils {
  public org.springframework.web.cors.reactive.CorsUtils();
    Code:
       0: aload_0
       1: invokespecial #1                  // Method java/lang/Object."<init>":()V
       4: return

  public static boolean isCorsRequest(org.springframework.http.server.reactive.ServerHttpRequest);
    Code:
       0: aload_0
       1: invokeinterface #2,  1            // InterfaceMethod org/springframework/http/server/reactive/ServerHttpRequest.getHeaders:()Lorg/springframework/http/HttpHeaders;
       6: ldc           #4                  // String Origin
       8: invokevirtual #5                  // Method org/springframework/http/HttpHeaders.get:(Ljava/lang/Object;)Ljava/util/List;
      11: ifnull        18
      14: iconst_1
      15: goto          19
      18: iconst_0
      19: ireturn

  public static boolean isPreFlightRequest(org.springframework.http.server.reactive.ServerHttpRequest);
    Code:
       0: aload_0
       1: invokeinterface #6,  1            // InterfaceMethod org/springframework/http/server/reactive/ServerHttpRequest.getMethod:()Lorg/springframework/http/HttpMethod;
       6: getstatic     #7                  // Field org/springframework/http/HttpMethod.OPTIONS:Lorg/springframework/http/HttpMethod;
       9: if_acmpne     37
      12: aload_0
      13: invokestatic  #8                  // Method isCorsRequest:(Lorg/springframework/http/server/reactive/ServerHttpRequest;)Z
      16: ifeq          37
      19: aload_0
      20: invokeinterface #2,  1            // InterfaceMethod org/springframework/http/server/reactive/ServerHttpRequest.getHeaders:()Lorg/springframework/http/HttpHeaders;
      25: ldc           #9                  // String Access-Control-Request-Method
      27: invokevirtual #5                  // Method org/springframework/http/HttpHeaders.get:(Ljava/lang/Object;)Ljava/util/List;
      30: ifnull        37
      33: iconst_1
      34: goto          38
      37: iconst_0
      38: ireturn

  public static boolean isSameOrigin(org.springframework.http.server.reactive.ServerHttpRequest);
    Code:
       0: aload_0
       1: invokeinterface #2,  1            // InterfaceMethod org/springframework/http/server/reactive/ServerHttpRequest.getHeaders:()Lorg/springframework/http/HttpHeaders;
       6: invokevirtual #10                 // Method org/springframework/http/HttpHeaders.getOrigin:()Ljava/lang/String;
       9: astore_1
      10: aload_1
      11: ifnonnull     16
      14: iconst_1
      15: ireturn
      16: aload_0
      17: invokeinterface #11,  1           // InterfaceMethod org/springframework/http/server/reactive/ServerHttpRequest.getURI:()Ljava/net/URI;
      22: astore_2
      23: aload_2
      24: invokevirtual #12                 // Method java/net/URI.getScheme:()Ljava/lang/String;
      27: astore_3
      28: aload_2
      29: invokevirtual #13                 // Method java/net/URI.getHost:()Ljava/lang/String;
      32: astore        4
      34: aload_2
      35: invokevirtual #12                 // Method java/net/URI.getScheme:()Ljava/lang/String;
      38: aload_2
      39: invokevirtual #14                 // Method java/net/URI.getPort:()I
      42: invokestatic  #15                 // Method getPort:(Ljava/lang/String;I)I
      45: istore        5
      47: aload_3
      48: ldc           #16                 // String Actual request scheme must not be null
      50: invokestatic  #17                 // Method org/springframework/util/Assert.notNull:(Ljava/lang/Object;Ljava/lang/String;)V
      53: aload         4
      55: ldc           #18                 // String Actual request host must not be null
      57: invokestatic  #17                 // Method org/springframework/util/Assert.notNull:(Ljava/lang/Object;Ljava/lang/String;)V
      60: iload         5
      62: iconst_m1
      63: if_icmpeq     70
      66: iconst_1
      67: goto          71
      70: iconst_0
      71: ldc           #19                 // String Actual request port must not be undefined
      73: invokestatic  #20                 // Method org/springframework/util/Assert.isTrue:(ZLjava/lang/String;)V
      76: aload_1
      77: invokestatic  #21                 // Method org/springframework/web/util/UriComponentsBuilder.fromOriginHeader:(Ljava/lang/String;)Lorg/springframework/web/util/UriComponentsBuilder;
      80: invokevirtual #22                 // Method org/springframework/web/util/UriComponentsBuilder.build:()Lorg/springframework/web/util/UriComponents;
      83: astore        6
      85: aload_3
      86: aload         6
      88: invokevirtual #23                 // Method org/springframework/web/util/UriComponents.getScheme:()Ljava/lang/String;
      91: invokevirtual #24                 // Method java/lang/String.equals:(Ljava/lang/Object;)Z
      94: ifeq          132
      97: aload         4
      99: aload         6
     101: invokevirtual #25                 // Method org/springframework/web/util/UriComponents.getHost:()Ljava/lang/String;
     104: invokevirtual #24                 // Method java/lang/String.equals:(Ljava/lang/Object;)Z
     107: ifeq          132
     110: iload         5
     112: aload         6
     114: invokevirtual #23                 // Method org/springframework/web/util/UriComponents.getScheme:()Ljava/lang/String;
     117: aload         6
     119: invokevirtual #26                 // Method org/springframework/web/util/UriComponents.getPort:()I
     122: invokestatic  #15                 // Method getPort:(Ljava/lang/String;I)I
     125: if_icmpne     132
     128: iconst_1
     129: goto          133
     132: iconst_0
     133: ireturn

  private static int getPort(java.lang.String, int);
    Code:
       0: iload_1
       1: iconst_m1
       2: if_icmpne     51
       5: ldc           #27                 // String http
       7: aload_0
       8: invokevirtual #24                 // Method java/lang/String.equals:(Ljava/lang/Object;)Z
      11: ifne          23
      14: ldc           #28                 // String ws
      16: aload_0
      17: invokevirtual #24                 // Method java/lang/String.equals:(Ljava/lang/Object;)Z
      20: ifeq          29
      23: bipush        80
      25: istore_1
      26: goto          51
      29: ldc           #29                 // String https
      31: aload_0
      32: invokevirtual #24                 // Method java/lang/String.equals:(Ljava/lang/Object;)Z
      35: ifne          47
      38: ldc           #30                 // String wss
      40: aload_0
      41: invokevirtual #24                 // Method java/lang/String.equals:(Ljava/lang/Object;)Z
      44: ifeq          51
      47: sipush        443
      50: istore_1
      51: iload_1
      52: ireturn
}
