Compiled from "Name1.java"
public final class io.dekorate.deps.jackson.core.sym.Name1 extends io.dekorate.deps.jackson.core.sym.Name {
  private static final io.dekorate.deps.jackson.core.sym.Name1 EMPTY;

  private final int q;

  io.dekorate.deps.jackson.core.sym.Name1(java.lang.String, int, int);
    Code:
       0: aload_0
       1: aload_1
       2: iload_2
       3: invokespecial #14                 // Method io/dekorate/deps/jackson/core/sym/Name."<init>":(Ljava/lang/String;I)V
       6: aload_0
       7: iload_3
       8: putfield      #16                 // Field q:I
      11: return

  public static io.dekorate.deps.jackson.core.sym.Name1 getEmptyName();
    Code:
       0: getstatic     #25                 // Field EMPTY:Lio/dekorate/deps/jackson/core/sym/Name1;
       3: areturn

  public boolean equals(int);
    Code:
       0: iload_1
       1: aload_0
       2: getfield      #16                 // Field q:I
       5: if_icmpne     12
       8: iconst_1
       9: goto          13
      12: iconst_0
      13: ireturn

  public boolean equals(int, int);
    Code:
       0: iload_1
       1: aload_0
       2: getfield      #16                 // Field q:I
       5: if_icmpne     16
       8: iload_2
       9: ifne          16
      12: iconst_1
      13: goto          17
      16: iconst_0
      17: ireturn

  public boolean equals(int, int, int);
    Code:
       0: iconst_0
       1: ireturn

  public boolean equals(int[], int);
    Code:
       0: iload_2
       1: iconst_1
       2: if_icmpne     19
       5: aload_1
       6: iconst_0
       7: iaload
       8: aload_0
       9: getfield      #16                 // Field q:I
      12: if_icmpne     19
      15: iconst_1
      16: goto          20
      19: iconst_0
      20: ireturn

  static {};
    Code:
       0: new           #2                  // class io/dekorate/deps/jackson/core/sym/Name1
       3: dup
       4: ldc           #42                 // String
       6: iconst_0
       7: iconst_0
       8: invokespecial #44                 // Method "<init>":(Ljava/lang/String;II)V
      11: putstatic     #25                 // Field EMPTY:Lio/dekorate/deps/jackson/core/sym/Name1;
      14: return
}
