Compiled from "AliasFromCNGenerator.java"
public class won.cryptography.ssl.AliasFromCNGenerator implements won.cryptography.ssl.AliasGenerator {
  public won.cryptography.ssl.AliasFromCNGenerator();
    Code:
       0: aload_0
       1: invokespecial #1                  // Method java/lang/Object."<init>":()V
       4: return

  public java.lang.String generateAlias(java.security.cert.X509Certificate) throws java.security.cert.CertificateException;
    Code:
       0: aconst_null
       1: astore_2
       2: new           #2                  // class sun/security/x509/X500Name
       5: dup
       6: aload_1
       7: invokevirtual #3                  // Method java/security/cert/X509Certificate.getSubjectDN:()Ljava/security/Principal;
      10: invokeinterface #4,  1            // InterfaceMethod java/security/Principal.getName:()Ljava/lang/String;
      15: invokespecial #5                  // Method sun/security/x509/X500Name."<init>":(Ljava/lang/String;)V
      18: astore_3
      19: aload_3
      20: invokevirtual #6                  // Method sun/security/x509/X500Name.getCommonName:()Ljava/lang/String;
      23: astore_2
      24: goto          39
      27: astore_3
      28: new           #8                  // class java/security/cert/CertificateException
      31: dup
      32: ldc           #9                  // String SubjectDN problem - cannot generate alias
      34: aload_3
      35: invokespecial #10                 // Method java/security/cert/CertificateException."<init>":(Ljava/lang/String;Ljava/lang/Throwable;)V
      38: athrow
      39: aload_2
      40: ifnull        50
      43: aload_2
      44: invokevirtual #11                 // Method java/lang/String.isEmpty:()Z
      47: ifeq          60
      50: new           #8                  // class java/security/cert/CertificateException
      53: dup
      54: ldc           #12                 // String CN is null - cannot accept as alias
      56: invokespecial #13                 // Method java/security/cert/CertificateException."<init>":(Ljava/lang/String;)V
      59: athrow
      60: aload_2
      61: areturn
    Exception table:
       from    to  target type
           2    24    27   Class java/io/IOException
}
