Compiled from "KeyManagerWrapperWithKeyServiceAndStrategy.java"
public class won.cryptography.ssl.KeyManagerWrapperWithKeyServiceAndStrategy implements javax.net.ssl.X509KeyManager {
  private static final org.slf4j.Logger logger;

  private final javax.net.ssl.X509KeyManager keyManager;

  private final org.apache.http.ssl.PrivateKeyStrategy aliasStrategy;

  public won.cryptography.ssl.KeyManagerWrapperWithKeyServiceAndStrategy(won.cryptography.service.keystore.KeyStoreService, org.apache.http.ssl.PrivateKeyStrategy);
    Code:
       0: aload_0
       1: invokespecial #1                  // Method java/lang/Object."<init>":()V
       4: aload_0
       5: aload_2
       6: putfield      #2                  // Field aliasStrategy:Lorg/apache/http/ssl/PrivateKeyStrategy;
       9: aconst_null
      10: astore_3
      11: ldc           #3                  // String SunX509
      13: invokestatic  #4                  // Method javax/net/ssl/KeyManagerFactory.getInstance:(Ljava/lang/String;)Ljavax/net/ssl/KeyManagerFactory;
      16: astore_3
      17: aload_3
      18: aload_1
      19: invokeinterface #5,  1            // InterfaceMethod won/cryptography/service/keystore/KeyStoreService.getUnderlyingKeyStore:()Ljava/security/KeyStore;
      24: aload_1
      25: invokeinterface #6,  1            // InterfaceMethod won/cryptography/service/keystore/KeyStoreService.getPassword:()Ljava/lang/String;
      30: invokevirtual #7                  // Method java/lang/String.toCharArray:()[C
      33: invokevirtual #8                  // Method javax/net/ssl/KeyManagerFactory.init:(Ljava/security/KeyStore;[C)V
      36: goto          63
      39: astore        4
      41: getstatic     #10                 // Field logger:Lorg/slf4j/Logger;
      44: ldc           #11                 // String KeyManager could not be initialized
      46: invokeinterface #12,  2           // InterfaceMethod org/slf4j/Logger.error:(Ljava/lang/String;)V
      51: new           #13                 // class java/lang/RuntimeException
      54: dup
      55: ldc           #11                 // String KeyManager could not be initialized
      57: aload         4
      59: invokespecial #14                 // Method java/lang/RuntimeException."<init>":(Ljava/lang/String;Ljava/lang/Throwable;)V
      62: athrow
      63: aload_3
      64: invokevirtual #15                 // Method javax/net/ssl/KeyManagerFactory.getKeyManagers:()[Ljavax/net/ssl/KeyManager;
      67: astore        4
      69: aload         4
      71: ifnull        120
      74: aload_2
      75: ifnull        120
      78: iconst_0
      79: istore        5
      81: iload         5
      83: aload         4
      85: arraylength
      86: if_icmpge     120
      89: aload         4
      91: iload         5
      93: aaload
      94: astore        6
      96: aload         6
      98: instanceof    #16                 // class javax/net/ssl/X509KeyManager
     101: ifeq          114
     104: aload_0
     105: aload         6
     107: checkcast     #16                 // class javax/net/ssl/X509KeyManager
     110: putfield      #17                 // Field keyManager:Ljavax/net/ssl/X509KeyManager;
     113: return
     114: iinc          5, 1
     117: goto          81
     120: aload_0
     121: aconst_null
     122: putfield      #17                 // Field keyManager:Ljavax/net/ssl/X509KeyManager;
     125: new           #13                 // class java/lang/RuntimeException
     128: dup
     129: ldc           #18                 // String X509KeyManager could not be initialized
     131: invokespecial #19                 // Method java/lang/RuntimeException."<init>":(Ljava/lang/String;)V
     134: athrow
    Exception table:
       from    to  target type
          11    36    39   Class java/lang/Exception

  public java.lang.String[] getClientAliases(java.lang.String, java.security.Principal[]);
    Code:
       0: aload_0
       1: getfield      #17                 // Field keyManager:Ljavax/net/ssl/X509KeyManager;
       4: aload_1
       5: aload_2
       6: invokeinterface #20,  3           // InterfaceMethod javax/net/ssl/X509KeyManager.getClientAliases:(Ljava/lang/String;[Ljava/security/Principal;)[Ljava/lang/String;
      11: areturn

  public java.lang.String chooseClientAlias(java.lang.String[], java.security.Principal[], java.net.Socket);
    Code:
       0: new           #21                 // class java/util/HashMap
       3: dup
       4: invokespecial #22                 // Method java/util/HashMap."<init>":()V
       7: astore        4
       9: aload_1
      10: astore        5
      12: aload         5
      14: arraylength
      15: istore        6
      17: iconst_0
      18: istore        7
      20: iload         7
      22: iload         6
      24: if_icmpge     121
      27: aload         5
      29: iload         7
      31: aaload
      32: astore        8
      34: aload_0
      35: getfield      #17                 // Field keyManager:Ljavax/net/ssl/X509KeyManager;
      38: aload         8
      40: aload_2
      41: invokeinterface #20,  3           // InterfaceMethod javax/net/ssl/X509KeyManager.getClientAliases:(Ljava/lang/String;[Ljava/security/Principal;)[Ljava/lang/String;
      46: astore        9
      48: aload         9
      50: ifnull        115
      53: aload         9
      55: astore        10
      57: aload         10
      59: arraylength
      60: istore        11
      62: iconst_0
      63: istore        12
      65: iload         12
      67: iload         11
      69: if_icmpge     115
      72: aload         10
      74: iload         12
      76: aaload
      77: astore        13
      79: aload         4
      81: aload         13
      83: new           #23                 // class org/apache/http/ssl/PrivateKeyDetails
      86: dup
      87: aload         8
      89: aload_0
      90: getfield      #17                 // Field keyManager:Ljavax/net/ssl/X509KeyManager;
      93: aload         13
      95: invokeinterface #24,  2           // InterfaceMethod javax/net/ssl/X509KeyManager.getCertificateChain:(Ljava/lang/String;)[Ljava/security/cert/X509Certificate;
     100: invokespecial #25                 // Method org/apache/http/ssl/PrivateKeyDetails."<init>":(Ljava/lang/String;[Ljava/security/cert/X509Certificate;)V
     103: invokeinterface #26,  3           // InterfaceMethod java/util/Map.put:(Ljava/lang/Object;Ljava/lang/Object;)Ljava/lang/Object;
     108: pop
     109: iinc          12, 1
     112: goto          65
     115: iinc          7, 1
     118: goto          20
     121: aload_0
     122: getfield      #2                  // Field aliasStrategy:Lorg/apache/http/ssl/PrivateKeyStrategy;
     125: aload         4
     127: aload_3
     128: invokeinterface #27,  3           // InterfaceMethod org/apache/http/ssl/PrivateKeyStrategy.chooseAlias:(Ljava/util/Map;Ljava/net/Socket;)Ljava/lang/String;
     133: areturn

  public java.lang.String[] getServerAliases(java.lang.String, java.security.Principal[]);
    Code:
       0: aload_0
       1: getfield      #17                 // Field keyManager:Ljavax/net/ssl/X509KeyManager;
       4: aload_1
       5: aload_2
       6: invokeinterface #28,  3           // InterfaceMethod javax/net/ssl/X509KeyManager.getServerAliases:(Ljava/lang/String;[Ljava/security/Principal;)[Ljava/lang/String;
      11: areturn

  public java.lang.String chooseServerAlias(java.lang.String, java.security.Principal[], java.net.Socket);
    Code:
       0: new           #21                 // class java/util/HashMap
       3: dup
       4: invokespecial #22                 // Method java/util/HashMap."<init>":()V
       7: astore        4
       9: aload_0
      10: getfield      #17                 // Field keyManager:Ljavax/net/ssl/X509KeyManager;
      13: aload_1
      14: aload_2
      15: invokeinterface #28,  3           // InterfaceMethod javax/net/ssl/X509KeyManager.getServerAliases:(Ljava/lang/String;[Ljava/security/Principal;)[Ljava/lang/String;
      20: astore        5
      22: aload         5
      24: ifnull        88
      27: aload         5
      29: astore        6
      31: aload         6
      33: arraylength
      34: istore        7
      36: iconst_0
      37: istore        8
      39: iload         8
      41: iload         7
      43: if_icmpge     88
      46: aload         6
      48: iload         8
      50: aaload
      51: astore        9
      53: aload         4
      55: aload         9
      57: new           #23                 // class org/apache/http/ssl/PrivateKeyDetails
      60: dup
      61: aload_1
      62: aload_0
      63: getfield      #17                 // Field keyManager:Ljavax/net/ssl/X509KeyManager;
      66: aload         9
      68: invokeinterface #24,  2           // InterfaceMethod javax/net/ssl/X509KeyManager.getCertificateChain:(Ljava/lang/String;)[Ljava/security/cert/X509Certificate;
      73: invokespecial #25                 // Method org/apache/http/ssl/PrivateKeyDetails."<init>":(Ljava/lang/String;[Ljava/security/cert/X509Certificate;)V
      76: invokeinterface #26,  3           // InterfaceMethod java/util/Map.put:(Ljava/lang/Object;Ljava/lang/Object;)Ljava/lang/Object;
      81: pop
      82: iinc          8, 1
      85: goto          39
      88: aload_0
      89: getfield      #2                  // Field aliasStrategy:Lorg/apache/http/ssl/PrivateKeyStrategy;
      92: aload         4
      94: aload_3
      95: invokeinterface #27,  3           // InterfaceMethod org/apache/http/ssl/PrivateKeyStrategy.chooseAlias:(Ljava/util/Map;Ljava/net/Socket;)Ljava/lang/String;
     100: areturn

  public java.security.cert.X509Certificate[] getCertificateChain(java.lang.String);
    Code:
       0: aload_0
       1: getfield      #17                 // Field keyManager:Ljavax/net/ssl/X509KeyManager;
       4: aload_1
       5: invokeinterface #24,  2           // InterfaceMethod javax/net/ssl/X509KeyManager.getCertificateChain:(Ljava/lang/String;)[Ljava/security/cert/X509Certificate;
      10: areturn

  public java.security.PrivateKey getPrivateKey(java.lang.String);
    Code:
       0: aload_0
       1: getfield      #17                 // Field keyManager:Ljavax/net/ssl/X509KeyManager;
       4: aload_1
       5: invokeinterface #29,  2           // InterfaceMethod javax/net/ssl/X509KeyManager.getPrivateKey:(Ljava/lang/String;)Ljava/security/PrivateKey;
      10: areturn

  static {};
    Code:
       0: invokestatic  #30                 // Method java/lang/invoke/MethodHandles.lookup:()Ljava/lang/invoke/MethodHandles$Lookup;
       3: invokevirtual #31                 // Method java/lang/invoke/MethodHandles$Lookup.lookupClass:()Ljava/lang/Class;
       6: invokestatic  #32                 // Method org/slf4j/LoggerFactory.getLogger:(Ljava/lang/Class;)Lorg/slf4j/Logger;
       9: putstatic     #10                 // Field logger:Lorg/slf4j/Logger;
      12: return
}
