Compiled from "SessionCreationMetaDataEntryExternalizer.java"
public class org.wildfly.clustering.web.infinispan.session.SessionCreationMetaDataEntryExternalizer implements org.wildfly.clustering.marshalling.Externalizer<org.wildfly.clustering.web.infinispan.session.SessionCreationMetaDataEntry<java.lang.Object>> {
  private static final org.wildfly.clustering.marshalling.Externalizer<java.time.Instant> INSTANT_EXTERNALIZER;

  public org.wildfly.clustering.web.infinispan.session.SessionCreationMetaDataEntryExternalizer();
    Code:
       0: aload_0
       1: invokespecial #1                  // Method java/lang/Object."<init>":()V
       4: return

  public void writeObject(java.io.ObjectOutput, org.wildfly.clustering.web.infinispan.session.SessionCreationMetaDataEntry<java.lang.Object>) throws java.io.IOException;
    Code:
       0: aload_2
       1: invokevirtual #2                  // Method org/wildfly/clustering/web/infinispan/session/SessionCreationMetaDataEntry.getMetaData:()Lorg/wildfly/clustering/web/infinispan/session/SessionCreationMetaData;
       4: astore_3
       5: getstatic     #3                  // Field INSTANT_EXTERNALIZER:Lorg/wildfly/clustering/marshalling/Externalizer;
       8: aload_1
       9: aload_3
      10: invokeinterface #4,  1            // InterfaceMethod org/wildfly/clustering/web/infinispan/session/SessionCreationMetaData.getCreationTime:()Ljava/time/Instant;
      15: invokeinterface #5,  3            // InterfaceMethod org/wildfly/clustering/marshalling/Externalizer.writeObject:(Ljava/io/ObjectOutput;Ljava/lang/Object;)V
      20: getstatic     #6                  // Field org/wildfly/clustering/marshalling/jboss/IndexExternalizer.VARIABLE:Lorg/wildfly/clustering/marshalling/jboss/IndexExternalizer;
      23: aload_1
      24: aload_3
      25: invokeinterface #7,  1            // InterfaceMethod org/wildfly/clustering/web/infinispan/session/SessionCreationMetaData.getMaxInactiveInterval:()Ljava/time/Duration;
      30: invokevirtual #8                  // Method java/time/Duration.getSeconds:()J
      33: l2i
      34: invokestatic  #9                  // Method java/lang/Integer.valueOf:(I)Ljava/lang/Integer;
      37: invokevirtual #10                 // Method org/wildfly/clustering/marshalling/jboss/IndexExternalizer.writeObject:(Ljava/io/ObjectOutput;Ljava/lang/Integer;)V
      40: return

  public org.wildfly.clustering.web.infinispan.session.SessionCreationMetaDataEntry<java.lang.Object> readObject(java.io.ObjectInput) throws java.io.IOException, java.lang.ClassNotFoundException;
    Code:
       0: new           #11                 // class org/wildfly/clustering/web/infinispan/session/SimpleSessionCreationMetaData
       3: dup
       4: getstatic     #3                  // Field INSTANT_EXTERNALIZER:Lorg/wildfly/clustering/marshalling/Externalizer;
       7: aload_1
       8: invokeinterface #12,  2           // InterfaceMethod org/wildfly/clustering/marshalling/Externalizer.readObject:(Ljava/io/ObjectInput;)Ljava/lang/Object;
      13: checkcast     #13                 // class java/time/Instant
      16: invokespecial #14                 // Method org/wildfly/clustering/web/infinispan/session/SimpleSessionCreationMetaData."<init>":(Ljava/time/Instant;)V
      19: astore_2
      20: aload_2
      21: getstatic     #6                  // Field org/wildfly/clustering/marshalling/jboss/IndexExternalizer.VARIABLE:Lorg/wildfly/clustering/marshalling/jboss/IndexExternalizer;
      24: aload_1
      25: invokevirtual #15                 // Method org/wildfly/clustering/marshalling/jboss/IndexExternalizer.readObject:(Ljava/io/ObjectInput;)Ljava/lang/Integer;
      28: invokevirtual #16                 // Method java/lang/Integer.intValue:()I
      31: i2l
      32: invokestatic  #17                 // Method java/time/Duration.ofSeconds:(J)Ljava/time/Duration;
      35: invokeinterface #18,  2           // InterfaceMethod org/wildfly/clustering/web/infinispan/session/SessionCreationMetaData.setMaxInactiveInterval:(Ljava/time/Duration;)V
      40: new           #19                 // class org/wildfly/clustering/web/infinispan/session/SessionCreationMetaDataEntry
      43: dup
      44: aload_2
      45: invokespecial #20                 // Method org/wildfly/clustering/web/infinispan/session/SessionCreationMetaDataEntry."<init>":(Lorg/wildfly/clustering/web/infinispan/session/SessionCreationMetaData;)V
      48: areturn

  public java.lang.Class getTargetClass();
    Code:
       0: ldc           #19                 // class org/wildfly/clustering/web/infinispan/session/SessionCreationMetaDataEntry
       2: areturn

  public java.lang.Object readObject(java.io.ObjectInput) throws java.io.IOException, java.lang.ClassNotFoundException;
    Code:
       0: aload_0
       1: aload_1
       2: invokevirtual #21                 // Method readObject:(Ljava/io/ObjectInput;)Lorg/wildfly/clustering/web/infinispan/session/SessionCreationMetaDataEntry;
       5: areturn

  public void writeObject(java.io.ObjectOutput, java.lang.Object) throws java.io.IOException;
    Code:
       0: aload_0
       1: aload_1
       2: aload_2
       3: checkcast     #19                 // class org/wildfly/clustering/web/infinispan/session/SessionCreationMetaDataEntry
       6: invokevirtual #22                 // Method writeObject:(Ljava/io/ObjectOutput;Lorg/wildfly/clustering/web/infinispan/session/SessionCreationMetaDataEntry;)V
       9: return

  static {};
    Code:
       0: new           #23                 // class org/wildfly/clustering/marshalling/jboss/InstantExternalizer
       3: dup
       4: invokespecial #24                 // Method org/wildfly/clustering/marshalling/jboss/InstantExternalizer."<init>":()V
       7: putstatic     #3                  // Field INSTANT_EXTERNALIZER:Lorg/wildfly/clustering/marshalling/Externalizer;
      10: return
}
