Compiled from "MessageUtil.java"
class org.aspectj.bridge.MessageUtil$1HandlerPrintStream extends java.io.PrintStream {
  final java.io.OutputStream val$overage;

  final java.lang.String val$prefix;

  final org.aspectj.bridge.IMessage$Kind val$kind;

  final org.aspectj.bridge.IMessageHandler val$handler;

  org.aspectj.bridge.MessageUtil$1HandlerPrintStream();
    Code:
       0: aload_0
       1: aload_1
       2: putfield      #1                  // Field val$overage:Ljava/io/OutputStream;
       5: aload_0
       6: aload_2
       7: putfield      #2                  // Field val$prefix:Ljava/lang/String;
      10: aload_0
      11: aload_3
      12: putfield      #3                  // Field val$kind:Lorg/aspectj/bridge/IMessage$Kind;
      15: aload_0
      16: aload         4
      18: putfield      #4                  // Field val$handler:Lorg/aspectj/bridge/IMessageHandler;
      21: aload_0
      22: aconst_null
      23: aload_1
      24: if_acmpne     33
      27: getstatic     #5                  // Field java/lang/System.out:Ljava/io/PrintStream;
      30: goto          34
      33: aload_1
      34: invokespecial #6                  // Method java/io/PrintStream."<init>":(Ljava/io/OutputStream;)V
      37: return

  public void println();
    Code:
       0: aload_0
       1: ldc           #7                  // String
       3: invokevirtual #8                  // Method println:(Ljava/lang/String;)V
       6: return

  public void println(java.lang.Object);
    Code:
       0: aload_0
       1: aconst_null
       2: aload_1
       3: if_acmpne     11
       6: ldc           #9                  // String null
       8: goto          15
      11: aload_1
      12: invokevirtual #10                 // Method java/lang/Object.toString:()Ljava/lang/String;
      15: invokevirtual #8                  // Method println:(Ljava/lang/String;)V
      18: return

  public void println(java.lang.String);
    Code:
       0: aconst_null
       1: aload_0
       2: getfield      #2                  // Field val$prefix:Ljava/lang/String;
       5: if_acmpne     12
       8: aload_1
       9: goto          33
      12: new           #11                 // class java/lang/StringBuilder
      15: dup
      16: invokespecial #12                 // Method java/lang/StringBuilder."<init>":()V
      19: aload_0
      20: getfield      #2                  // Field val$prefix:Ljava/lang/String;
      23: invokevirtual #13                 // Method java/lang/StringBuilder.append:(Ljava/lang/String;)Ljava/lang/StringBuilder;
      26: aload_1
      27: invokevirtual #13                 // Method java/lang/StringBuilder.append:(Ljava/lang/String;)Ljava/lang/StringBuilder;
      30: invokevirtual #14                 // Method java/lang/StringBuilder.toString:()Ljava/lang/String;
      33: astore_2
      34: new           #15                 // class org/aspectj/bridge/Message
      37: dup
      38: aload_2
      39: aload_0
      40: getfield      #3                  // Field val$kind:Lorg/aspectj/bridge/IMessage$Kind;
      43: aconst_null
      44: aconst_null
      45: invokespecial #16                 // Method org/aspectj/bridge/Message."<init>":(Ljava/lang/String;Lorg/aspectj/bridge/IMessage$Kind;Ljava/lang/Throwable;Lorg/aspectj/bridge/ISourceLocation;)V
      48: astore_3
      49: aload_0
      50: getfield      #4                  // Field val$handler:Lorg/aspectj/bridge/IMessageHandler;
      53: aload_3
      54: invokeinterface #17,  2           // InterfaceMethod org/aspectj/bridge/IMessageHandler.handleMessage:(Lorg/aspectj/bridge/IMessage;)Z
      59: pop
      60: return
}
