Compiled from "XmlSchemaAnnotation.java"
public class org.apache.ws.commons.schema.XmlSchemaAnnotation extends org.apache.ws.commons.schema.XmlSchemaObject {
  private java.util.List<org.apache.ws.commons.schema.XmlSchemaAnnotationItem> items;

  public org.apache.ws.commons.schema.XmlSchemaAnnotation();
    Code:
       0: aload_0
       1: invokespecial #1                  // Method org/apache/ws/commons/schema/XmlSchemaObject."<init>":()V
       4: aload_0
       5: new           #2                  // class java/util/ArrayList
       8: dup
       9: invokespecial #3                  // Method java/util/ArrayList."<init>":()V
      12: putfield      #4                  // Field items:Ljava/util/List;
      15: return

  public java.util.List<org.apache.ws.commons.schema.XmlSchemaAnnotationItem> getItems();
    Code:
       0: aload_0
       1: getfield      #4                  // Field items:Ljava/util/List;
       4: areturn
}
