Compiled from "GenericBeanDefinition.java"
public class org.springframework.beans.factory.support.GenericBeanDefinition extends org.springframework.beans.factory.support.AbstractBeanDefinition {
  private java.lang.String parentName;

  public org.springframework.beans.factory.support.GenericBeanDefinition();
    Code:
       0: aload_0
       1: invokespecial #1                  // Method org/springframework/beans/factory/support/AbstractBeanDefinition."<init>":()V
       4: return

  public org.springframework.beans.factory.support.GenericBeanDefinition(org.springframework.beans.factory.config.BeanDefinition);
    Code:
       0: aload_0
       1: aload_1
       2: invokespecial #2                  // Method org/springframework/beans/factory/support/AbstractBeanDefinition."<init>":(Lorg/springframework/beans/factory/config/BeanDefinition;)V
       5: return

  public void setParentName(java.lang.String);
    Code:
       0: aload_0
       1: aload_1
       2: putfield      #3                  // Field parentName:Ljava/lang/String;
       5: return

  public java.lang.String getParentName();
    Code:
       0: aload_0
       1: getfield      #3                  // Field parentName:Ljava/lang/String;
       4: areturn

  public org.springframework.beans.factory.support.AbstractBeanDefinition cloneBeanDefinition();
    Code:
       0: new           #4                  // class org/springframework/beans/factory/support/GenericBeanDefinition
       3: dup
       4: aload_0
       5: invokespecial #5                  // Method "<init>":(Lorg/springframework/beans/factory/config/BeanDefinition;)V
       8: areturn

  public boolean equals(java.lang.Object);
    Code:
       0: aload_0
       1: aload_1
       2: if_acmpne     7
       5: iconst_1
       6: ireturn
       7: aload_1
       8: instanceof    #4                  // class org/springframework/beans/factory/support/GenericBeanDefinition
      11: ifne          16
      14: iconst_0
      15: ireturn
      16: aload_1
      17: checkcast     #4                  // class org/springframework/beans/factory/support/GenericBeanDefinition
      20: astore_2
      21: aload_0
      22: getfield      #3                  // Field parentName:Ljava/lang/String;
      25: aload_2
      26: getfield      #3                  // Field parentName:Ljava/lang/String;
      29: invokestatic  #6                  // Method org/springframework/util/ObjectUtils.nullSafeEquals:(Ljava/lang/Object;Ljava/lang/Object;)Z
      32: ifeq          47
      35: aload_0
      36: aload_1
      37: invokespecial #7                  // Method org/springframework/beans/factory/support/AbstractBeanDefinition.equals:(Ljava/lang/Object;)Z
      40: ifeq          47
      43: iconst_1
      44: goto          48
      47: iconst_0
      48: ireturn

  public java.lang.String toString();
    Code:
       0: aload_0
       1: getfield      #3                  // Field parentName:Ljava/lang/String;
       4: ifnull        42
       7: new           #8                  // class java/lang/StringBuilder
      10: dup
      11: invokespecial #9                  // Method java/lang/StringBuilder."<init>":()V
      14: ldc           #10                 // String Generic bean with parent \'
      16: invokevirtual #11                 // Method java/lang/StringBuilder.append:(Ljava/lang/String;)Ljava/lang/StringBuilder;
      19: aload_0
      20: getfield      #3                  // Field parentName:Ljava/lang/String;
      23: invokevirtual #11                 // Method java/lang/StringBuilder.append:(Ljava/lang/String;)Ljava/lang/StringBuilder;
      26: ldc           #12                 // String \':
      28: invokevirtual #11                 // Method java/lang/StringBuilder.append:(Ljava/lang/String;)Ljava/lang/StringBuilder;
      31: aload_0
      32: invokespecial #13                 // Method org/springframework/beans/factory/support/AbstractBeanDefinition.toString:()Ljava/lang/String;
      35: invokevirtual #11                 // Method java/lang/StringBuilder.append:(Ljava/lang/String;)Ljava/lang/StringBuilder;
      38: invokevirtual #14                 // Method java/lang/StringBuilder.toString:()Ljava/lang/String;
      41: areturn
      42: new           #8                  // class java/lang/StringBuilder
      45: dup
      46: invokespecial #9                  // Method java/lang/StringBuilder."<init>":()V
      49: ldc           #15                 // String Generic bean:
      51: invokevirtual #11                 // Method java/lang/StringBuilder.append:(Ljava/lang/String;)Ljava/lang/StringBuilder;
      54: aload_0
      55: invokespecial #13                 // Method org/springframework/beans/factory/support/AbstractBeanDefinition.toString:()Ljava/lang/String;
      58: invokevirtual #11                 // Method java/lang/StringBuilder.append:(Ljava/lang/String;)Ljava/lang/StringBuilder;
      61: invokevirtual #14                 // Method java/lang/StringBuilder.toString:()Ljava/lang/String;
      64: areturn
}
