Compiled from "JournalResource.java"
public class org.graylog2.rest.resources.system.JournalResource extends org.graylog2.shared.rest.resources.RestResource {
  private static final org.slf4j.Logger log;

  private final boolean journalEnabled;

  private final org.graylog2.shared.journal.Journal journal;

  private final org.graylog2.plugin.KafkaJournalConfiguration kafkaJournalConfiguration;

  public org.graylog2.rest.resources.system.JournalResource(org.graylog2.Configuration, org.graylog2.plugin.KafkaJournalConfiguration, org.graylog2.shared.journal.Journal);
    Code:
       0: aload_0
       1: invokespecial #1                  // Method org/graylog2/shared/rest/resources/RestResource."<init>":()V
       4: aload_0
       5: aload_2
       6: putfield      #2                  // Field kafkaJournalConfiguration:Lorg/graylog2/plugin/KafkaJournalConfiguration;
       9: aload_0
      10: aload_1
      11: invokevirtual #3                  // Method org/graylog2/Configuration.isMessageJournalEnabled:()Z
      14: putfield      #4                  // Field journalEnabled:Z
      17: aload_0
      18: aload_3
      19: putfield      #5                  // Field journal:Lorg/graylog2/shared/journal/Journal;
      22: return

  public org.graylog2.rest.resources.system.responses.JournalSummaryResponse show();
    Code:
       0: aload_0
       1: getfield      #4                  // Field journalEnabled:Z
       4: ifne          11
       7: invokestatic  #6                  // Method org/graylog2/rest/resources/system/responses/JournalSummaryResponse.createDisabled:()Lorg/graylog2/rest/resources/system/responses/JournalSummaryResponse;
      10: areturn
      11: aload_0
      12: getfield      #5                  // Field journal:Lorg/graylog2/shared/journal/Journal;
      15: instanceof    #7                  // class org/graylog2/shared/journal/KafkaJournal
      18: ifeq          133
      21: aload_0
      22: getfield      #5                  // Field journal:Lorg/graylog2/shared/journal/Journal;
      25: checkcast     #7                  // class org/graylog2/shared/journal/KafkaJournal
      28: astore_1
      29: aload_1
      30: invokevirtual #8                  // Method org/graylog2/shared/journal/KafkaJournal.getThrottleState:()Lorg/graylog2/plugin/ThrottleState;
      33: astore_2
      34: ldc2_w        #10                 // long 9223372036854775807l
      37: lstore_3
      38: aload_1
      39: invokevirtual #12                 // Method org/graylog2/shared/journal/KafkaJournal.getSegments:()Ljava/lang/Iterable;
      42: invokeinterface #13,  1           // InterfaceMethod java/lang/Iterable.iterator:()Ljava/util/Iterator;
      47: astore        5
      49: aload         5
      51: invokeinterface #14,  1           // InterfaceMethod java/util/Iterator.hasNext:()Z
      56: ifeq          84
      59: aload         5
      61: invokeinterface #15,  1           // InterfaceMethod java/util/Iterator.next:()Ljava/lang/Object;
      66: checkcast     #16                 // class kafka/log/LogSegment
      69: astore        6
      71: lload_3
      72: aload         6
      74: invokevirtual #17                 // Method kafka/log/LogSegment.created:()J
      77: invokestatic  #18                 // Method java/lang/Math.min:(JJ)J
      80: lstore_3
      81: goto          49
      84: aload_2
      85: getfield      #19                 // Field org/graylog2/plugin/ThrottleState.appendEventsPerSec:J
      88: aload_2
      89: getfield      #20                 // Field org/graylog2/plugin/ThrottleState.readEventsPerSec:J
      92: aload_2
      93: getfield      #21                 // Field org/graylog2/plugin/ThrottleState.uncommittedJournalEntries:J
      96: aload_2
      97: getfield      #22                 // Field org/graylog2/plugin/ThrottleState.journalSize:J
     100: invokestatic  #23                 // Method com/github/joschi/jadconfig/util/Size.bytes:(J)Lcom/github/joschi/jadconfig/util/Size;
     103: aload_2
     104: getfield      #24                 // Field org/graylog2/plugin/ThrottleState.journalSizeLimit:J
     107: invokestatic  #23                 // Method com/github/joschi/jadconfig/util/Size.bytes:(J)Lcom/github/joschi/jadconfig/util/Size;
     110: aload_1
     111: invokevirtual #25                 // Method org/graylog2/shared/journal/KafkaJournal.numberOfSegments:()I
     114: new           #26                 // class org/joda/time/DateTime
     117: dup
     118: lload_3
     119: getstatic     #27                 // Field org/joda/time/DateTimeZone.UTC:Lorg/joda/time/DateTimeZone;
     122: invokespecial #28                 // Method org/joda/time/DateTime."<init>":(JLorg/joda/time/DateTimeZone;)V
     125: aload_0
     126: getfield      #2                  // Field kafkaJournalConfiguration:Lorg/graylog2/plugin/KafkaJournalConfiguration;
     129: invokestatic  #29                 // Method org/graylog2/rest/resources/system/responses/JournalSummaryResponse.createEnabled:(JJJLcom/github/joschi/jadconfig/util/Size;Lcom/github/joschi/jadconfig/util/Size;ILorg/joda/time/DateTime;Lorg/graylog2/plugin/KafkaJournalConfiguration;)Lorg/graylog2/rest/resources/system/responses/JournalSummaryResponse;
     132: areturn
     133: getstatic     #30                 // Field log:Lorg/slf4j/Logger;
     136: ldc           #31                 // String Unknown Journal implementation {} in use, cannot get information about it. Pretending journal is disabled.
     138: aload_0
     139: getfield      #5                  // Field journal:Lorg/graylog2/shared/journal/Journal;
     142: invokevirtual #32                 // Method java/lang/Object.getClass:()Ljava/lang/Class;
     145: invokeinterface #33,  3           // InterfaceMethod org/slf4j/Logger.warn:(Ljava/lang/String;Ljava/lang/Object;)V
     150: invokestatic  #6                  // Method org/graylog2/rest/resources/system/responses/JournalSummaryResponse.createDisabled:()Lorg/graylog2/rest/resources/system/responses/JournalSummaryResponse;
     153: areturn

  static {};
    Code:
       0: ldc           #34                 // class org/graylog2/rest/resources/system/JournalResource
       2: invokestatic  #35                 // Method org/slf4j/LoggerFactory.getLogger:(Ljava/lang/Class;)Lorg/slf4j/Logger;
       5: putstatic     #30                 // Field log:Lorg/slf4j/Logger;
       8: return
}
