Compiled from "MessageProcessorsResource.java"
public class org.graylog2.rest.resources.system.MessageProcessorsResource extends org.graylog2.shared.rest.resources.RestResource {
  private final java.util.Set<java.lang.String> processorClassNames;

  private final org.graylog2.plugin.cluster.ClusterConfigService clusterConfigService;

  private final java.util.Set<org.graylog2.plugin.messageprocessors.MessageProcessor$Descriptor> processorDescriptors;

  public org.graylog2.rest.resources.system.MessageProcessorsResource(java.util.Set<org.graylog2.plugin.messageprocessors.MessageProcessor$Descriptor>, org.graylog2.plugin.cluster.ClusterConfigService);
    Code:
       0: aload_0
       1: invokespecial #1                  // Method org/graylog2/shared/rest/resources/RestResource."<init>":()V
       4: aload_0
       5: aload_1
       6: putfield      #2                  // Field processorDescriptors:Ljava/util/Set;
       9: aload_0
      10: aload_1
      11: invokeinterface #3,  1            // InterfaceMethod java/util/Set.stream:()Ljava/util/stream/Stream;
      16: invokedynamic #4,  0              // InvokeDynamic #0:apply:()Ljava/util/function/Function;
      21: invokeinterface #5,  2            // InterfaceMethod java/util/stream/Stream.map:(Ljava/util/function/Function;)Ljava/util/stream/Stream;
      26: invokestatic  #6                  // Method java/util/stream/Collectors.toSet:()Ljava/util/stream/Collector;
      29: invokeinterface #7,  2            // InterfaceMethod java/util/stream/Stream.collect:(Ljava/util/stream/Collector;)Ljava/lang/Object;
      34: checkcast     #8                  // class java/util/Set
      37: putfield      #9                  // Field processorClassNames:Ljava/util/Set;
      40: aload_0
      41: aload_2
      42: putfield      #10                 // Field clusterConfigService:Lorg/graylog2/plugin/cluster/ClusterConfigService;
      45: return

  public org.graylog2.messageprocessors.MessageProcessorsConfigWithDescriptors config();
    Code:
       0: aload_0
       1: ldc           #12                 // String clusterconfigentry:read
       3: invokevirtual #13                 // Method checkPermission:(Ljava/lang/String;)V
       6: aload_0
       7: getfield      #10                 // Field clusterConfigService:Lorg/graylog2/plugin/cluster/ClusterConfigService;
      10: ldc           #14                 // class org/graylog2/messageprocessors/MessageProcessorsConfig
      12: invokestatic  #15                 // Method org/graylog2/messageprocessors/MessageProcessorsConfig.defaultConfig:()Lorg/graylog2/messageprocessors/MessageProcessorsConfig;
      15: invokeinterface #16,  3           // InterfaceMethod org/graylog2/plugin/cluster/ClusterConfigService.getOrDefault:(Ljava/lang/Class;Ljava/lang/Object;)Ljava/lang/Object;
      20: checkcast     #14                 // class org/graylog2/messageprocessors/MessageProcessorsConfig
      23: astore_1
      24: aload_1
      25: aload_0
      26: getfield      #9                  // Field processorClassNames:Ljava/util/Set;
      29: invokevirtual #17                 // Method org/graylog2/messageprocessors/MessageProcessorsConfig.withProcessors:(Ljava/util/Set;)Lorg/graylog2/messageprocessors/MessageProcessorsConfig;
      32: aload_0
      33: getfield      #2                  // Field processorDescriptors:Ljava/util/Set;
      36: invokestatic  #18                 // Method org/graylog2/messageprocessors/MessageProcessorsConfigWithDescriptors.fromConfig:(Lorg/graylog2/messageprocessors/MessageProcessorsConfig;Ljava/util/Set;)Lorg/graylog2/messageprocessors/MessageProcessorsConfigWithDescriptors;
      39: areturn

  public org.graylog2.messageprocessors.MessageProcessorsConfigWithDescriptors updateConfig(org.graylog2.messageprocessors.MessageProcessorsConfigWithDescriptors);
    Code:
       0: aload_0
       1: ldc           #19                 // String clusterconfigentry:edit
       3: invokevirtual #13                 // Method checkPermission:(Ljava/lang/String;)V
       6: aload_1
       7: invokevirtual #20                 // Method org/graylog2/messageprocessors/MessageProcessorsConfigWithDescriptors.toConfig:()Lorg/graylog2/messageprocessors/MessageProcessorsConfig;
      10: astore_2
      11: aload_0
      12: getfield      #10                 // Field clusterConfigService:Lorg/graylog2/plugin/cluster/ClusterConfigService;
      15: aload_2
      16: aload_0
      17: getfield      #9                  // Field processorClassNames:Ljava/util/Set;
      20: invokevirtual #17                 // Method org/graylog2/messageprocessors/MessageProcessorsConfig.withProcessors:(Ljava/util/Set;)Lorg/graylog2/messageprocessors/MessageProcessorsConfig;
      23: invokeinterface #21,  2           // InterfaceMethod org/graylog2/plugin/cluster/ClusterConfigService.write:(Ljava/lang/Object;)V
      28: aload_1
      29: areturn
}
