Compiled from "GuildListRequest.kt"
public final class love.forte.simbot.kaiheila.api.guild.GuildListRequestKt {
  public static final boolean isAsc(love.forte.simbot.kaiheila.api.guild.GuildApiRespSort);
    Code:
       0: aload_0
       1: ldc           #10                 // String <this>
       3: invokestatic  #16                 // Method kotlin/jvm/internal/Intrinsics.checkNotNullParameter:(Ljava/lang/Object;Ljava/lang/String;)V
       6: iconst_0
       7: istore_1
       8: aload_0
       9: invokevirtual #22                 // Method love/forte/simbot/kaiheila/api/guild/GuildApiRespSort.getId:()I
      12: iconst_1
      13: if_icmpne     20
      16: iconst_1
      17: goto          21
      20: iconst_0
      21: ireturn

  public static final boolean isDesc(love.forte.simbot.kaiheila.api.guild.GuildApiRespSort);
    Code:
       0: aload_0
       1: ldc           #10                 // String <this>
       3: invokestatic  #16                 // Method kotlin/jvm/internal/Intrinsics.checkNotNullParameter:(Ljava/lang/Object;Ljava/lang/String;)V
       6: iconst_0
       7: istore_1
       8: aload_0
       9: astore_2
      10: iconst_0
      11: istore_3
      12: aload_2
      13: invokevirtual #22                 // Method love/forte/simbot/kaiheila/api/guild/GuildApiRespSort.getId:()I
      16: iconst_1
      17: if_icmpne     24
      20: iconst_1
      21: goto          25
      24: iconst_0
      25: ifne          32
      28: iconst_1
      29: goto          33
      32: iconst_0
      33: ireturn
}
