Compiled from "EntityReferenceAliasesImpl.java"
public class org.hibernate.loader.plan.exec.internal.EntityReferenceAliasesImpl implements org.hibernate.loader.plan.exec.spi.EntityReferenceAliases {
  private final java.lang.String tableAlias;

  private final org.hibernate.loader.EntityAliases columnAliases;

  public org.hibernate.loader.plan.exec.internal.EntityReferenceAliasesImpl(java.lang.String, org.hibernate.loader.EntityAliases);
    Code:
       0: aload_0
       1: invokespecial #1                  // Method java/lang/Object."<init>":()V
       4: aload_0
       5: aload_1
       6: putfield      #2                  // Field tableAlias:Ljava/lang/String;
       9: aload_0
      10: aload_2
      11: putfield      #3                  // Field columnAliases:Lorg/hibernate/loader/EntityAliases;
      14: return

  public java.lang.String getTableAlias();
    Code:
       0: aload_0
       1: getfield      #2                  // Field tableAlias:Ljava/lang/String;
       4: areturn

  public org.hibernate.loader.EntityAliases getColumnAliases();
    Code:
       0: aload_0
       1: getfield      #3                  // Field columnAliases:Lorg/hibernate/loader/EntityAliases;
       4: areturn
}
