Compiled from "ShellProperties.java"
public class org.springframework.boot.actuate.autoconfigure.ShellProperties$Ssh extends org.springframework.boot.actuate.autoconfigure.ShellProperties$CrshShellProperties {
  private boolean enabled;

  private java.lang.String keyPath;

  private java.lang.Integer port;

  private java.lang.Integer authTimeout;

  private java.lang.Integer idleTimeout;

  public org.springframework.boot.actuate.autoconfigure.ShellProperties$Ssh();
    Code:
       0: aload_0
       1: invokespecial #1                  // Method org/springframework/boot/actuate/autoconfigure/ShellProperties$CrshShellProperties."<init>":()V
       4: aload_0
       5: iconst_1
       6: putfield      #2                  // Field enabled:Z
       9: aload_0
      10: sipush        2000
      13: invokestatic  #3                  // Method java/lang/Integer.valueOf:(I)Ljava/lang/Integer;
      16: putfield      #4                  // Field port:Ljava/lang/Integer;
      19: aload_0
      20: ldc           #5                  // int 600000
      22: invokestatic  #3                  // Method java/lang/Integer.valueOf:(I)Ljava/lang/Integer;
      25: putfield      #6                  // Field authTimeout:Ljava/lang/Integer;
      28: aload_0
      29: ldc           #5                  // int 600000
      31: invokestatic  #3                  // Method java/lang/Integer.valueOf:(I)Ljava/lang/Integer;
      34: putfield      #7                  // Field idleTimeout:Ljava/lang/Integer;
      37: return

  protected void applyToCrshShellConfig(java.util.Properties);
    Code:
       0: aload_0
       1: getfield      #2                  // Field enabled:Z
       4: ifeq          67
       7: aload_1
       8: ldc           #8                  // String crash.ssh.port
      10: aload_0
      11: getfield      #4                  // Field port:Ljava/lang/Integer;
      14: invokestatic  #9                  // Method java/lang/String.valueOf:(Ljava/lang/Object;)Ljava/lang/String;
      17: invokevirtual #10                 // Method java/util/Properties.put:(Ljava/lang/Object;Ljava/lang/Object;)Ljava/lang/Object;
      20: pop
      21: aload_1
      22: ldc           #11                 // String crash.ssh.auth_timeout
      24: aload_0
      25: getfield      #6                  // Field authTimeout:Ljava/lang/Integer;
      28: invokestatic  #9                  // Method java/lang/String.valueOf:(Ljava/lang/Object;)Ljava/lang/String;
      31: invokevirtual #10                 // Method java/util/Properties.put:(Ljava/lang/Object;Ljava/lang/Object;)Ljava/lang/Object;
      34: pop
      35: aload_1
      36: ldc           #12                 // String crash.ssh.idle_timeout
      38: aload_0
      39: getfield      #7                  // Field idleTimeout:Ljava/lang/Integer;
      42: invokestatic  #9                  // Method java/lang/String.valueOf:(Ljava/lang/Object;)Ljava/lang/String;
      45: invokevirtual #10                 // Method java/util/Properties.put:(Ljava/lang/Object;Ljava/lang/Object;)Ljava/lang/Object;
      48: pop
      49: aload_0
      50: getfield      #13                 // Field keyPath:Ljava/lang/String;
      53: ifnull        67
      56: aload_1
      57: ldc           #14                 // String crash.ssh.keypath
      59: aload_0
      60: getfield      #13                 // Field keyPath:Ljava/lang/String;
      63: invokevirtual #10                 // Method java/util/Properties.put:(Ljava/lang/Object;Ljava/lang/Object;)Ljava/lang/Object;
      66: pop
      67: return

  public void setEnabled(boolean);
    Code:
       0: aload_0
       1: iload_1
       2: putfield      #2                  // Field enabled:Z
       5: return

  public boolean isEnabled();
    Code:
       0: aload_0
       1: getfield      #2                  // Field enabled:Z
       4: ireturn

  public void setKeyPath(java.lang.String);
    Code:
       0: aload_1
       1: ldc           #15                 // String keyPath must have text
       3: invokestatic  #16                 // Method org/springframework/util/Assert.hasText:(Ljava/lang/String;Ljava/lang/String;)V
       6: aload_0
       7: aload_1
       8: putfield      #13                 // Field keyPath:Ljava/lang/String;
      11: return

  public java.lang.String getKeyPath();
    Code:
       0: aload_0
       1: getfield      #13                 // Field keyPath:Ljava/lang/String;
       4: areturn

  public void setPort(java.lang.Integer);
    Code:
       0: aload_1
       1: ldc           #17                 // String port must not be null
       3: invokestatic  #18                 // Method org/springframework/util/Assert.notNull:(Ljava/lang/Object;Ljava/lang/String;)V
       6: aload_0
       7: aload_1
       8: putfield      #4                  // Field port:Ljava/lang/Integer;
      11: return

  public java.lang.Integer getPort();
    Code:
       0: aload_0
       1: getfield      #4                  // Field port:Ljava/lang/Integer;
       4: areturn

  public java.lang.Integer getIdleTimeout();
    Code:
       0: aload_0
       1: getfield      #7                  // Field idleTimeout:Ljava/lang/Integer;
       4: areturn

  public void setIdleTimeout(java.lang.Integer);
    Code:
       0: aload_0
       1: aload_1
       2: putfield      #7                  // Field idleTimeout:Ljava/lang/Integer;
       5: return

  public java.lang.Integer getAuthTimeout();
    Code:
       0: aload_0
       1: getfield      #6                  // Field authTimeout:Ljava/lang/Integer;
       4: areturn

  public void setAuthTimeout(java.lang.Integer);
    Code:
       0: aload_0
       1: aload_1
       2: putfield      #6                  // Field authTimeout:Ljava/lang/Integer;
       5: return
}
