Compiled from "ContentHandlerPrintRenderer.java"
public class org.xwiki.rendering.xml.internal.renderer.ContentHandlerPrintRenderer extends org.xwiki.rendering.listener.WrappingListener implements org.xwiki.rendering.renderer.PrintRenderer {
  private org.xwiki.rendering.internal.renderer.printer.WikiWriter wikiWriter;

  private org.dom4j.io.XMLWriter xmlWriter;

  public org.xwiki.rendering.xml.internal.renderer.ContentHandlerPrintRenderer(org.xwiki.rendering.renderer.xml.ContentHandlerStreamRenderer, org.xwiki.rendering.renderer.printer.WikiPrinter);
    Code:
       0: aload_0
       1: invokespecial #1                  // Method org/xwiki/rendering/listener/WrappingListener."<init>":()V
       4: aload_0
       5: aload_1
       6: invokevirtual #2                  // Method setWrappedListener:(Lorg/xwiki/rendering/listener/Listener;)V
       9: aload_0
      10: new           #3                  // class org/xwiki/rendering/internal/renderer/printer/WikiWriter
      13: dup
      14: aload_2
      15: invokespecial #4                  // Method org/xwiki/rendering/internal/renderer/printer/WikiWriter."<init>":(Lorg/xwiki/rendering/renderer/printer/WikiPrinter;)V
      18: putfield      #5                  // Field wikiWriter:Lorg/xwiki/rendering/internal/renderer/printer/WikiWriter;
      21: aload_0
      22: new           #6                  // class org/xwiki/rendering/xml/internal/renderer/SAXSerializer
      25: dup
      26: aload_0
      27: getfield      #5                  // Field wikiWriter:Lorg/xwiki/rendering/internal/renderer/printer/WikiWriter;
      30: invokespecial #7                  // Method org/xwiki/rendering/xml/internal/renderer/SAXSerializer."<init>":(Ljava/io/Writer;)V
      33: putfield      #8                  // Field xmlWriter:Lorg/dom4j/io/XMLWriter;
      36: aload_0
      37: getfield      #8                  // Field xmlWriter:Lorg/dom4j/io/XMLWriter;
      40: bipush        127
      42: invokevirtual #9                  // Method org/dom4j/io/XMLWriter.setMaximumAllowedCharacter:(I)V
      45: aload_1
      46: aload_0
      47: getfield      #8                  // Field xmlWriter:Lorg/dom4j/io/XMLWriter;
      50: invokeinterface #10,  2           // InterfaceMethod org/xwiki/rendering/renderer/xml/ContentHandlerStreamRenderer.setContentHandler:(Lorg/xml/sax/ContentHandler;)V
      55: return

  public org.xwiki.rendering.renderer.printer.WikiPrinter getPrinter();
    Code:
       0: aload_0
       1: getfield      #5                  // Field wikiWriter:Lorg/xwiki/rendering/internal/renderer/printer/WikiWriter;
       4: invokevirtual #11                 // Method org/xwiki/rendering/internal/renderer/printer/WikiWriter.getWikiPrinter:()Lorg/xwiki/rendering/renderer/printer/WikiPrinter;
       7: areturn

  public void setPrinter(org.xwiki.rendering.renderer.printer.WikiPrinter);
    Code:
       0: aload_0
       1: getfield      #5                  // Field wikiWriter:Lorg/xwiki/rendering/internal/renderer/printer/WikiWriter;
       4: aload_1
       5: invokevirtual #12                 // Method org/xwiki/rendering/internal/renderer/printer/WikiWriter.setWikiPrinter:(Lorg/xwiki/rendering/renderer/printer/WikiPrinter;)V
       8: return
}
