Compiled from "SessionSendMessage.java"
public class org.hornetq.core.protocol.core.impl.wireformat.SessionSendMessage extends org.hornetq.core.protocol.core.impl.wireformat.MessagePacket {
  private boolean requiresResponse;

  private final transient org.hornetq.api.core.client.SendAcknowledgementHandler handler;

  public org.hornetq.core.protocol.core.impl.wireformat.SessionSendMessage(org.hornetq.core.message.impl.MessageInternal, boolean, org.hornetq.api.core.client.SendAcknowledgementHandler);
    Code:
       0: aload_0
       1: bipush        71
       3: aload_1
       4: invokespecial #2                  // Method org/hornetq/core/protocol/core/impl/wireformat/MessagePacket."<init>":(BLorg/hornetq/core/message/impl/MessageInternal;)V
       7: aload_0
       8: aload_3
       9: putfield      #3                  // Field handler:Lorg/hornetq/api/core/client/SendAcknowledgementHandler;
      12: aload_0
      13: iload_2
      14: putfield      #4                  // Field requiresResponse:Z
      17: return

  public org.hornetq.core.protocol.core.impl.wireformat.SessionSendMessage(org.hornetq.core.message.impl.MessageInternal);
    Code:
       0: aload_0
       1: bipush        71
       3: aload_1
       4: invokespecial #2                  // Method org/hornetq/core/protocol/core/impl/wireformat/MessagePacket."<init>":(BLorg/hornetq/core/message/impl/MessageInternal;)V
       7: aload_0
       8: aconst_null
       9: putfield      #3                  // Field handler:Lorg/hornetq/api/core/client/SendAcknowledgementHandler;
      12: return

  public boolean isRequiresResponse();
    Code:
       0: aload_0
       1: getfield      #4                  // Field requiresResponse:Z
       4: ireturn

  public org.hornetq.api.core.client.SendAcknowledgementHandler getHandler();
    Code:
       0: aload_0
       1: getfield      #3                  // Field handler:Lorg/hornetq/api/core/client/SendAcknowledgementHandler;
       4: areturn

  public org.hornetq.api.core.HornetQBuffer encode(org.hornetq.spi.core.protocol.RemotingConnection);
    Code:
       0: aload_0
       1: getfield      #5                  // Field message:Lorg/hornetq/core/message/impl/MessageInternal;
       4: invokeinterface #6,  1            // InterfaceMethod org/hornetq/core/message/impl/MessageInternal.getEncodedBuffer:()Lorg/hornetq/api/core/HornetQBuffer;
       9: astore_2
      10: aload_2
      11: invokeinterface #7,  1            // InterfaceMethod org/hornetq/api/core/HornetQBuffer.writerIndex:()I
      16: aload_0
      17: getfield      #5                  // Field message:Lorg/hornetq/core/message/impl/MessageInternal;
      20: invokeinterface #8,  1            // InterfaceMethod org/hornetq/core/message/impl/MessageInternal.getEndOfMessagePosition:()I
      25: if_icmpeq     38
      28: new           #9                  // class java/lang/IllegalStateException
      31: dup
      32: ldc           #10                 // String Wrong encode position
      34: invokespecial #11                 // Method java/lang/IllegalStateException."<init>":(Ljava/lang/String;)V
      37: athrow
      38: aload_2
      39: aload_0
      40: getfield      #4                  // Field requiresResponse:Z
      43: invokeinterface #12,  2           // InterfaceMethod org/hornetq/api/core/HornetQBuffer.writeBoolean:(Z)V
      48: aload_0
      49: aload_2
      50: invokeinterface #7,  1            // InterfaceMethod org/hornetq/api/core/HornetQBuffer.writerIndex:()I
      55: putfield      #13                 // Field size:I
      58: aload_0
      59: getfield      #13                 // Field size:I
      62: iconst_4
      63: isub
      64: istore_3
      65: aload_2
      66: iconst_0
      67: iload_3
      68: invokeinterface #15,  3           // InterfaceMethod org/hornetq/api/core/HornetQBuffer.setInt:(II)V
      73: aload_2
      74: iconst_4
      75: aload_0
      76: invokevirtual #16                 // Method getType:()B
      79: invokeinterface #17,  3           // InterfaceMethod org/hornetq/api/core/HornetQBuffer.setByte:(IB)V
      84: aload_2
      85: iconst_5
      86: aload_0
      87: getfield      #18                 // Field channelID:J
      90: invokeinterface #19,  4           // InterfaceMethod org/hornetq/api/core/HornetQBuffer.setLong:(IJ)V
      95: aload_2
      96: iconst_0
      97: invokeinterface #20,  2           // InterfaceMethod org/hornetq/api/core/HornetQBuffer.readerIndex:(I)V
     102: aload_0
     103: getfield      #5                  // Field message:Lorg/hornetq/core/message/impl/MessageInternal;
     106: invokeinterface #21,  1           // InterfaceMethod org/hornetq/core/message/impl/MessageInternal.resetCopied:()V
     111: aload_2
     112: areturn

  public void decodeRest(org.hornetq.api.core.HornetQBuffer);
    Code:
       0: aload_0
       1: getfield      #5                  // Field message:Lorg/hornetq/core/message/impl/MessageInternal;
       4: aload_1
       5: invokeinterface #22,  2           // InterfaceMethod org/hornetq/core/message/impl/MessageInternal.decodeFromBuffer:(Lorg/hornetq/api/core/HornetQBuffer;)V
      10: aload_1
      11: invokeinterface #23,  1           // InterfaceMethod org/hornetq/api/core/HornetQBuffer.readerIndex:()I
      16: istore_2
      17: aload_0
      18: aload_1
      19: invokeinterface #24,  1           // InterfaceMethod org/hornetq/api/core/HornetQBuffer.readBoolean:()Z
      24: putfield      #4                  // Field requiresResponse:Z
      27: aload_1
      28: iload_2
      29: invokeinterface #20,  2           // InterfaceMethod org/hornetq/api/core/HornetQBuffer.readerIndex:(I)V
      34: return

  public int hashCode();
    Code:
       0: bipush        31
       2: istore_1
       3: aload_0
       4: invokespecial #25                 // Method org/hornetq/core/protocol/core/impl/wireformat/MessagePacket.hashCode:()I
       7: istore_2
       8: bipush        31
      10: iload_2
      11: imul
      12: aload_0
      13: getfield      #4                  // Field requiresResponse:Z
      16: ifeq          25
      19: sipush        1231
      22: goto          28
      25: sipush        1237
      28: iadd
      29: istore_2
      30: iload_2
      31: ireturn

  public boolean equals(java.lang.Object);
    Code:
       0: aload_0
       1: aload_1
       2: if_acmpne     7
       5: iconst_1
       6: ireturn
       7: aload_0
       8: aload_1
       9: invokespecial #26                 // Method org/hornetq/core/protocol/core/impl/wireformat/MessagePacket.equals:(Ljava/lang/Object;)Z
      12: ifne          17
      15: iconst_0
      16: ireturn
      17: aload_1
      18: instanceof    #27                 // class org/hornetq/core/protocol/core/impl/wireformat/SessionSendMessage
      21: ifne          26
      24: iconst_0
      25: ireturn
      26: aload_1
      27: checkcast     #27                 // class org/hornetq/core/protocol/core/impl/wireformat/SessionSendMessage
      30: astore_2
      31: aload_0
      32: getfield      #4                  // Field requiresResponse:Z
      35: aload_2
      36: getfield      #4                  // Field requiresResponse:Z
      39: if_icmpeq     44
      42: iconst_0
      43: ireturn
      44: iconst_1
      45: ireturn
}
