Compiled from "MapAdapter.java"
class com.github.andrewoma.dexx.collection.internal.adapter.MapAdapter$3$1 implements com.github.andrewoma.dexx.collection.Function<com.github.andrewoma.dexx.collection.Pair<K, V>, java.util.Map$Entry<K, V>> {
  final com.github.andrewoma.dexx.collection.internal.adapter.MapAdapter$3 this$1;

  com.github.andrewoma.dexx.collection.internal.adapter.MapAdapter$3$1(com.github.andrewoma.dexx.collection.internal.adapter.MapAdapter$3);
    Code:
       0: aload_0
       1: aload_1
       2: putfield      #1                  // Field this$1:Lcom/github/andrewoma/dexx/collection/internal/adapter/MapAdapter$3;
       5: aload_0
       6: invokespecial #2                  // Method java/lang/Object."<init>":()V
       9: return

  public java.util.Map$Entry<K, V> invoke(com.github.andrewoma.dexx.collection.Pair<K, V>);
    Code:
       0: new           #3                  // class com/github/andrewoma/dexx/collection/internal/adapter/MapAdapter$3$1$1
       3: dup
       4: aload_0
       5: aload_1
       6: invokespecial #4                  // Method com/github/andrewoma/dexx/collection/internal/adapter/MapAdapter$3$1$1."<init>":(Lcom/github/andrewoma/dexx/collection/internal/adapter/MapAdapter$3$1;Lcom/github/andrewoma/dexx/collection/Pair;)V
       9: areturn

  public java.lang.Object invoke(java.lang.Object);
    Code:
       0: aload_0
       1: aload_1
       2: checkcast     #5                  // class com/github/andrewoma/dexx/collection/Pair
       5: invokevirtual #6                  // Method invoke:(Lcom/github/andrewoma/dexx/collection/Pair;)Ljava/util/Map$Entry;
       8: areturn
}
