Compiled from "SimpleBuffer.kt"
public final class org.rsmod.plugins.info.player.buffer.SimpleBuffer {
  private final byte[] data;

  private int offset;

  public org.rsmod.plugins.info.player.buffer.SimpleBuffer(byte[], int);
    Code:
       0: aload_1
       1: ldc           #9                  // String data
       3: invokestatic  #15                 // Method kotlin/jvm/internal/Intrinsics.checkNotNullParameter:(Ljava/lang/Object;Ljava/lang/String;)V
       6: aload_0
       7: invokespecial #18                 // Method java/lang/Object."<init>":()V
      10: aload_0
      11: aload_1
      12: putfield      #21                 // Field data:[B
      15: aload_0
      16: iload_2
      17: putfield      #25                 // Field offset:I
      20: return

  public org.rsmod.plugins.info.player.buffer.SimpleBuffer(byte[], int, int, kotlin.jvm.internal.DefaultConstructorMarker);
    Code:
       0: iload_3
       1: iconst_2
       2: iand
       3: ifeq          8
       6: iconst_0
       7: istore_2
       8: aload_0
       9: aload_1
      10: iload_2
      11: invokespecial #30                 // Method "<init>":([BI)V
      14: return

  public final byte[] getData();
    Code:
       0: aload_0
       1: getfield      #21                 // Field data:[B
       4: areturn

  public final int getOffset();
    Code:
       0: aload_0
       1: getfield      #25                 // Field offset:I
       4: ireturn

  public final void setOffset(int);
    Code:
       0: aload_0
       1: iload_1
       2: putfield      #25                 // Field offset:I
       5: return

  public final int getCapacity();
    Code:
       0: aload_0
       1: getfield      #21                 // Field data:[B
       4: arraylength
       5: ireturn

  public org.rsmod.plugins.info.player.buffer.SimpleBuffer(int);
    Code:
       0: aload_0
       1: iload_1
       2: newarray       byte
       4: iconst_0
       5: iconst_2
       6: aconst_null
       7: invokespecial #40                 // Method "<init>":([BIILkotlin/jvm/internal/DefaultConstructorMarker;)V
      10: return

  public final org.rsmod.plugins.info.player.buffer.SimpleBuffer clear();
    Code:
       0: aload_0
       1: iconst_0
       2: putfield      #25                 // Field offset:I
       5: aload_0
       6: areturn

  public final org.rsmod.plugins.info.player.buffer.SimpleBuffer putBytes(byte[], int);
    Code:
       0: aload_1
       1: ldc           #47                 // String src
       3: invokestatic  #15                 // Method kotlin/jvm/internal/Intrinsics.checkNotNullParameter:(Ljava/lang/Object;Ljava/lang/String;)V
       6: iconst_0
       7: istore_3
       8: iload_3
       9: iload_2
      10: if_icmpge     33
      13: aload_0
      14: getfield      #21                 // Field data:[B
      17: aload_0
      18: getfield      #25                 // Field offset:I
      21: iload_3
      22: iadd
      23: aload_1
      24: iload_3
      25: baload
      26: bastore
      27: iinc          3, 1
      30: goto          8
      33: aload_0
      34: aload_0
      35: getfield      #25                 // Field offset:I
      38: iload_2
      39: iadd
      40: putfield      #25                 // Field offset:I
      43: aload_0
      44: areturn

  public java.lang.String toString();
    Code:
       0: aload_0
       1: getfield      #25                 // Field offset:I
       4: aload_0
       5: invokevirtual #53                 // Method getCapacity:()I
       8: invokedynamic #65,  0             // InvokeDynamic #0:makeConcatWithConstants:(II)Ljava/lang/String;
      13: areturn
}
