Compiled from "PackedArrayRecorder.java"
public class org.HdrHistogram.packedarray.PackedArrayRecorder {
  private static java.util.concurrent.atomic.AtomicLong instanceIdSequencer;

  private final long instanceId;

  private final org.HdrHistogram.WriterReaderPhaser recordingPhaser;

  private volatile org.HdrHistogram.packedarray.PackedLongArray activeArray;

  public org.HdrHistogram.packedarray.PackedArrayRecorder(int);
    Code:
       0: aload_0
       1: invokespecial #1                  // Method java/lang/Object."<init>":()V
       4: aload_0
       5: getstatic     #2                  // Field instanceIdSequencer:Ljava/util/concurrent/atomic/AtomicLong;
       8: invokevirtual #3                  // Method java/util/concurrent/atomic/AtomicLong.getAndIncrement:()J
      11: putfield      #4                  // Field instanceId:J
      14: aload_0
      15: new           #5                  // class org/HdrHistogram/WriterReaderPhaser
      18: dup
      19: invokespecial #6                  // Method org/HdrHistogram/WriterReaderPhaser."<init>":()V
      22: putfield      #7                  // Field recordingPhaser:Lorg/HdrHistogram/WriterReaderPhaser;
      25: aload_0
      26: new           #8                  // class org/HdrHistogram/packedarray/PackedArrayRecorder$InternalConcurrentPackedLongArray
      29: dup
      30: aload_0
      31: getfield      #4                  // Field instanceId:J
      34: iload_1
      35: aconst_null
      36: invokespecial #9                  // Method org/HdrHistogram/packedarray/PackedArrayRecorder$InternalConcurrentPackedLongArray."<init>":(JILorg/HdrHistogram/packedarray/PackedArrayRecorder$1;)V
      39: putfield      #10                 // Field activeArray:Lorg/HdrHistogram/packedarray/PackedLongArray;
      42: aload_0
      43: getfield      #10                 // Field activeArray:Lorg/HdrHistogram/packedarray/PackedLongArray;
      46: invokestatic  #11                 // Method java/lang/System.currentTimeMillis:()J
      49: invokevirtual #12                 // Method org/HdrHistogram/packedarray/PackedLongArray.setStartTimeStamp:(J)V
      52: return

  public org.HdrHistogram.packedarray.PackedArrayRecorder(int, int);
    Code:
       0: aload_0
       1: invokespecial #1                  // Method java/lang/Object."<init>":()V
       4: aload_0
       5: getstatic     #2                  // Field instanceIdSequencer:Ljava/util/concurrent/atomic/AtomicLong;
       8: invokevirtual #3                  // Method java/util/concurrent/atomic/AtomicLong.getAndIncrement:()J
      11: putfield      #4                  // Field instanceId:J
      14: aload_0
      15: new           #5                  // class org/HdrHistogram/WriterReaderPhaser
      18: dup
      19: invokespecial #6                  // Method org/HdrHistogram/WriterReaderPhaser."<init>":()V
      22: putfield      #7                  // Field recordingPhaser:Lorg/HdrHistogram/WriterReaderPhaser;
      25: aload_0
      26: new           #8                  // class org/HdrHistogram/packedarray/PackedArrayRecorder$InternalConcurrentPackedLongArray
      29: dup
      30: aload_0
      31: getfield      #4                  // Field instanceId:J
      34: iload_1
      35: iload_2
      36: aconst_null
      37: invokespecial #13                 // Method org/HdrHistogram/packedarray/PackedArrayRecorder$InternalConcurrentPackedLongArray."<init>":(JIILorg/HdrHistogram/packedarray/PackedArrayRecorder$1;)V
      40: putfield      #10                 // Field activeArray:Lorg/HdrHistogram/packedarray/PackedLongArray;
      43: aload_0
      44: getfield      #10                 // Field activeArray:Lorg/HdrHistogram/packedarray/PackedLongArray;
      47: invokestatic  #11                 // Method java/lang/System.currentTimeMillis:()J
      50: invokevirtual #12                 // Method org/HdrHistogram/packedarray/PackedLongArray.setStartTimeStamp:(J)V
      53: return

  public int length();
    Code:
       0: aload_0
       1: getfield      #10                 // Field activeArray:Lorg/HdrHistogram/packedarray/PackedLongArray;
       4: invokevirtual #14                 // Method org/HdrHistogram/packedarray/PackedLongArray.length:()I
       7: ireturn

  public void setVirtualLength(int);
    Code:
       0: aload_0
       1: getfield      #7                  // Field recordingPhaser:Lorg/HdrHistogram/WriterReaderPhaser;
       4: invokevirtual #15                 // Method org/HdrHistogram/WriterReaderPhaser.readerLock:()V
       7: aload_0
       8: getfield      #10                 // Field activeArray:Lorg/HdrHistogram/packedarray/PackedLongArray;
      11: iload_1
      12: invokevirtual #16                 // Method org/HdrHistogram/packedarray/PackedLongArray.setVirtualLength:(I)V
      15: aload_0
      16: getfield      #7                  // Field recordingPhaser:Lorg/HdrHistogram/WriterReaderPhaser;
      19: invokevirtual #17                 // Method org/HdrHistogram/WriterReaderPhaser.readerUnlock:()V
      22: goto          35
      25: astore_2
      26: aload_0
      27: getfield      #7                  // Field recordingPhaser:Lorg/HdrHistogram/WriterReaderPhaser;
      30: invokevirtual #17                 // Method org/HdrHistogram/WriterReaderPhaser.readerUnlock:()V
      33: aload_2
      34: athrow
      35: return
    Exception table:
       from    to  target type
           0    15    25   any

  public void increment(int) throws java.lang.ArrayIndexOutOfBoundsException;
    Code:
       0: aload_0
       1: getfield      #7                  // Field recordingPhaser:Lorg/HdrHistogram/WriterReaderPhaser;
       4: invokevirtual #18                 // Method org/HdrHistogram/WriterReaderPhaser.writerCriticalSectionEnter:()J
       7: lstore_2
       8: aload_0
       9: getfield      #10                 // Field activeArray:Lorg/HdrHistogram/packedarray/PackedLongArray;
      12: iload_1
      13: invokevirtual #19                 // Method org/HdrHistogram/packedarray/PackedLongArray.increment:(I)V
      16: aload_0
      17: getfield      #7                  // Field recordingPhaser:Lorg/HdrHistogram/WriterReaderPhaser;
      20: lload_2
      21: invokevirtual #20                 // Method org/HdrHistogram/WriterReaderPhaser.writerCriticalSectionExit:(J)V
      24: goto          40
      27: astore        4
      29: aload_0
      30: getfield      #7                  // Field recordingPhaser:Lorg/HdrHistogram/WriterReaderPhaser;
      33: lload_2
      34: invokevirtual #20                 // Method org/HdrHistogram/WriterReaderPhaser.writerCriticalSectionExit:(J)V
      37: aload         4
      39: athrow
      40: return
    Exception table:
       from    to  target type
           8    16    27   any
          27    29    27   any

  public void add(int, long) throws java.lang.ArrayIndexOutOfBoundsException;
    Code:
       0: aload_0
       1: getfield      #7                  // Field recordingPhaser:Lorg/HdrHistogram/WriterReaderPhaser;
       4: invokevirtual #18                 // Method org/HdrHistogram/WriterReaderPhaser.writerCriticalSectionEnter:()J
       7: lstore        4
       9: aload_0
      10: getfield      #10                 // Field activeArray:Lorg/HdrHistogram/packedarray/PackedLongArray;
      13: iload_1
      14: lload_2
      15: invokevirtual #21                 // Method org/HdrHistogram/packedarray/PackedLongArray.add:(IJ)V
      18: aload_0
      19: getfield      #7                  // Field recordingPhaser:Lorg/HdrHistogram/WriterReaderPhaser;
      22: lload         4
      24: invokevirtual #20                 // Method org/HdrHistogram/WriterReaderPhaser.writerCriticalSectionExit:(J)V
      27: goto          44
      30: astore        6
      32: aload_0
      33: getfield      #7                  // Field recordingPhaser:Lorg/HdrHistogram/WriterReaderPhaser;
      36: lload         4
      38: invokevirtual #20                 // Method org/HdrHistogram/WriterReaderPhaser.writerCriticalSectionExit:(J)V
      41: aload         6
      43: athrow
      44: return
    Exception table:
       from    to  target type
           9    18    30   any
          30    32    30   any

  public synchronized org.HdrHistogram.packedarray.PackedLongArray getIntervalArray();
    Code:
       0: aload_0
       1: aconst_null
       2: invokevirtual #22                 // Method getIntervalArray:(Lorg/HdrHistogram/packedarray/PackedLongArray;)Lorg/HdrHistogram/packedarray/PackedLongArray;
       5: areturn

  public synchronized org.HdrHistogram.packedarray.PackedLongArray getIntervalArray(org.HdrHistogram.packedarray.PackedLongArray);
    Code:
       0: aload_0
       1: aload_1
       2: iconst_1
       3: invokevirtual #23                 // Method getIntervalArray:(Lorg/HdrHistogram/packedarray/PackedLongArray;Z)Lorg/HdrHistogram/packedarray/PackedLongArray;
       6: areturn

  public synchronized org.HdrHistogram.packedarray.PackedLongArray getIntervalArray(org.HdrHistogram.packedarray.PackedLongArray, boolean);
    Code:
       0: aload_0
       1: aload_1
       2: iload_2
       3: invokespecial #24                 // Method validateFitAsReplacementArray:(Lorg/HdrHistogram/packedarray/PackedLongArray;Z)V
       6: aload_0
       7: aload_1
       8: invokespecial #25                 // Method performIntervalSample:(Lorg/HdrHistogram/packedarray/PackedLongArray;)Lorg/HdrHistogram/packedarray/PackedLongArray;
      11: astore_3
      12: aload_3
      13: areturn

  public synchronized void reset();
    Code:
       0: aload_0
       1: aconst_null
       2: invokespecial #25                 // Method performIntervalSample:(Lorg/HdrHistogram/packedarray/PackedLongArray;)Lorg/HdrHistogram/packedarray/PackedLongArray;
       5: pop
       6: return

  private org.HdrHistogram.packedarray.PackedLongArray performIntervalSample(org.HdrHistogram.packedarray.PackedLongArray);
    Code:
       0: aload_1
       1: astore_2
       2: aload_0
       3: getfield      #7                  // Field recordingPhaser:Lorg/HdrHistogram/WriterReaderPhaser;
       6: invokevirtual #15                 // Method org/HdrHistogram/WriterReaderPhaser.readerLock:()V
       9: aload_2
      10: ifnonnull     56
      13: aload_0
      14: getfield      #10                 // Field activeArray:Lorg/HdrHistogram/packedarray/PackedLongArray;
      17: instanceof    #8                  // class org/HdrHistogram/packedarray/PackedArrayRecorder$InternalConcurrentPackedLongArray
      20: ifeq          46
      23: new           #8                  // class org/HdrHistogram/packedarray/PackedArrayRecorder$InternalConcurrentPackedLongArray
      26: dup
      27: aload_0
      28: getfield      #4                  // Field instanceId:J
      31: aload_0
      32: getfield      #10                 // Field activeArray:Lorg/HdrHistogram/packedarray/PackedLongArray;
      35: invokevirtual #14                 // Method org/HdrHistogram/packedarray/PackedLongArray.length:()I
      38: aconst_null
      39: invokespecial #9                  // Method org/HdrHistogram/packedarray/PackedArrayRecorder$InternalConcurrentPackedLongArray."<init>":(JILorg/HdrHistogram/packedarray/PackedArrayRecorder$1;)V
      42: astore_2
      43: goto          60
      46: new           #26                 // class java/lang/IllegalStateException
      49: dup
      50: ldc           #27                 // String Unexpected internal array type for activeArray
      52: invokespecial #28                 // Method java/lang/IllegalStateException."<init>":(Ljava/lang/String;)V
      55: athrow
      56: aload_2
      57: invokevirtual #29                 // Method org/HdrHistogram/packedarray/PackedLongArray.clear:()V
      60: aload_2
      61: astore_3
      62: aload_0
      63: getfield      #10                 // Field activeArray:Lorg/HdrHistogram/packedarray/PackedLongArray;
      66: astore_2
      67: aload_0
      68: aload_3
      69: putfield      #10                 // Field activeArray:Lorg/HdrHistogram/packedarray/PackedLongArray;
      72: invokestatic  #11                 // Method java/lang/System.currentTimeMillis:()J
      75: lstore        4
      77: aload_0
      78: getfield      #10                 // Field activeArray:Lorg/HdrHistogram/packedarray/PackedLongArray;
      81: lload         4
      83: invokevirtual #12                 // Method org/HdrHistogram/packedarray/PackedLongArray.setStartTimeStamp:(J)V
      86: aload_2
      87: lload         4
      89: invokevirtual #30                 // Method org/HdrHistogram/packedarray/PackedLongArray.setEndTimeStamp:(J)V
      92: aload_0
      93: getfield      #7                  // Field recordingPhaser:Lorg/HdrHistogram/WriterReaderPhaser;
      96: ldc2_w        #31                 // long 500000l
      99: invokevirtual #33                 // Method org/HdrHistogram/WriterReaderPhaser.flipPhase:(J)V
     102: aload_0
     103: getfield      #7                  // Field recordingPhaser:Lorg/HdrHistogram/WriterReaderPhaser;
     106: invokevirtual #17                 // Method org/HdrHistogram/WriterReaderPhaser.readerUnlock:()V
     109: goto          124
     112: astore        6
     114: aload_0
     115: getfield      #7                  // Field recordingPhaser:Lorg/HdrHistogram/WriterReaderPhaser;
     118: invokevirtual #17                 // Method org/HdrHistogram/WriterReaderPhaser.readerUnlock:()V
     121: aload         6
     123: athrow
     124: aload_2
     125: areturn
    Exception table:
       from    to  target type
           2   102   112   any
         112   114   112   any

  private void validateFitAsReplacementArray(org.HdrHistogram.packedarray.PackedLongArray, boolean);
    Code:
       0: iconst_1
       1: istore_3
       2: aload_1
       3: ifnonnull     11
       6: iconst_0
       7: istore_3
       8: goto          55
      11: aload_1
      12: instanceof    #8                  // class org/HdrHistogram/packedarray/PackedArrayRecorder$InternalConcurrentPackedLongArray
      15: ifeq          55
      18: aload_0
      19: getfield      #10                 // Field activeArray:Lorg/HdrHistogram/packedarray/PackedLongArray;
      22: instanceof    #8                  // class org/HdrHistogram/packedarray/PackedArrayRecorder$InternalConcurrentPackedLongArray
      25: ifeq          55
      28: iload_2
      29: ifeq          53
      32: aload_1
      33: checkcast     #8                  // class org/HdrHistogram/packedarray/PackedArrayRecorder$InternalConcurrentPackedLongArray
      36: invokestatic  #34                 // Method org/HdrHistogram/packedarray/PackedArrayRecorder$InternalConcurrentPackedLongArray.access$200:(Lorg/HdrHistogram/packedarray/PackedArrayRecorder$InternalConcurrentPackedLongArray;)J
      39: aload_0
      40: getfield      #10                 // Field activeArray:Lorg/HdrHistogram/packedarray/PackedLongArray;
      43: checkcast     #8                  // class org/HdrHistogram/packedarray/PackedArrayRecorder$InternalConcurrentPackedLongArray
      46: invokestatic  #34                 // Method org/HdrHistogram/packedarray/PackedArrayRecorder$InternalConcurrentPackedLongArray.access$200:(Lorg/HdrHistogram/packedarray/PackedArrayRecorder$InternalConcurrentPackedLongArray;)J
      49: lcmp
      50: ifne          55
      53: iconst_0
      54: istore_3
      55: iload_3
      56: ifeq          106
      59: new           #35                 // class java/lang/IllegalArgumentException
      62: dup
      63: new           #36                 // class java/lang/StringBuilder
      66: dup
      67: invokespecial #37                 // Method java/lang/StringBuilder."<init>":()V
      70: ldc           #38                 // String replacement array must have been obtained via a previous getIntervalArray() call from this
      72: invokevirtual #39                 // Method java/lang/StringBuilder.append:(Ljava/lang/String;)Ljava/lang/StringBuilder;
      75: aload_0
      76: invokevirtual #40                 // Method java/lang/Object.getClass:()Ljava/lang/Class;
      79: invokevirtual #41                 // Method java/lang/Class.getName:()Ljava/lang/String;
      82: invokevirtual #39                 // Method java/lang/StringBuilder.append:(Ljava/lang/String;)Ljava/lang/StringBuilder;
      85: iload_2
      86: ifeq          94
      89: ldc           #42                 // String  insatnce
      91: goto          96
      94: ldc           #43                 // String  class
      96: invokevirtual #39                 // Method java/lang/StringBuilder.append:(Ljava/lang/String;)Ljava/lang/StringBuilder;
      99: invokevirtual #44                 // Method java/lang/StringBuilder.toString:()Ljava/lang/String;
     102: invokespecial #45                 // Method java/lang/IllegalArgumentException."<init>":(Ljava/lang/String;)V
     105: athrow
     106: return

  static {};
    Code:
       0: new           #46                 // class java/util/concurrent/atomic/AtomicLong
       3: dup
       4: lconst_1
       5: invokespecial #47                 // Method java/util/concurrent/atomic/AtomicLong."<init>":(J)V
       8: putstatic     #2                  // Field instanceIdSequencer:Ljava/util/concurrent/atomic/AtomicLong;
      11: return
}
