Compiled from "ModelSizeStats.java"
public class org.elasticsearch.client.ml.job.process.ModelSizeStats$Builder {
  private final java.lang.String jobId;

  private long modelBytes;

  private long totalByFieldCount;

  private long totalOverFieldCount;

  private long totalPartitionFieldCount;

  private long bucketAllocationFailuresCount;

  private org.elasticsearch.client.ml.job.process.ModelSizeStats$MemoryStatus memoryStatus;

  private java.util.Date timestamp;

  private java.util.Date logTime;

  public org.elasticsearch.client.ml.job.process.ModelSizeStats$Builder(java.lang.String);
    Code:
       0: aload_0
       1: invokespecial #1                  // Method java/lang/Object."<init>":()V
       4: aload_0
       5: aload_1
       6: putfield      #2                  // Field jobId:Ljava/lang/String;
       9: aload_0
      10: getstatic     #3                  // Field org/elasticsearch/client/ml/job/process/ModelSizeStats$MemoryStatus.OK:Lorg/elasticsearch/client/ml/job/process/ModelSizeStats$MemoryStatus;
      13: putfield      #4                  // Field memoryStatus:Lorg/elasticsearch/client/ml/job/process/ModelSizeStats$MemoryStatus;
      16: aload_0
      17: new           #5                  // class java/util/Date
      20: dup
      21: invokespecial #6                  // Method java/util/Date."<init>":()V
      24: putfield      #7                  // Field logTime:Ljava/util/Date;
      27: return

  public org.elasticsearch.client.ml.job.process.ModelSizeStats$Builder(org.elasticsearch.client.ml.job.process.ModelSizeStats);
    Code:
       0: aload_0
       1: invokespecial #1                  // Method java/lang/Object."<init>":()V
       4: aload_0
       5: aload_1
       6: invokestatic  #8                  // Method org/elasticsearch/client/ml/job/process/ModelSizeStats.access$000:(Lorg/elasticsearch/client/ml/job/process/ModelSizeStats;)Ljava/lang/String;
       9: putfield      #2                  // Field jobId:Ljava/lang/String;
      12: aload_0
      13: aload_1
      14: invokestatic  #9                  // Method org/elasticsearch/client/ml/job/process/ModelSizeStats.access$100:(Lorg/elasticsearch/client/ml/job/process/ModelSizeStats;)J
      17: putfield      #10                 // Field modelBytes:J
      20: aload_0
      21: aload_1
      22: invokestatic  #11                 // Method org/elasticsearch/client/ml/job/process/ModelSizeStats.access$200:(Lorg/elasticsearch/client/ml/job/process/ModelSizeStats;)J
      25: putfield      #12                 // Field totalByFieldCount:J
      28: aload_0
      29: aload_1
      30: invokestatic  #13                 // Method org/elasticsearch/client/ml/job/process/ModelSizeStats.access$300:(Lorg/elasticsearch/client/ml/job/process/ModelSizeStats;)J
      33: putfield      #14                 // Field totalOverFieldCount:J
      36: aload_0
      37: aload_1
      38: invokestatic  #15                 // Method org/elasticsearch/client/ml/job/process/ModelSizeStats.access$400:(Lorg/elasticsearch/client/ml/job/process/ModelSizeStats;)J
      41: putfield      #16                 // Field totalPartitionFieldCount:J
      44: aload_0
      45: aload_1
      46: invokestatic  #17                 // Method org/elasticsearch/client/ml/job/process/ModelSizeStats.access$500:(Lorg/elasticsearch/client/ml/job/process/ModelSizeStats;)J
      49: putfield      #18                 // Field bucketAllocationFailuresCount:J
      52: aload_0
      53: aload_1
      54: invokestatic  #19                 // Method org/elasticsearch/client/ml/job/process/ModelSizeStats.access$600:(Lorg/elasticsearch/client/ml/job/process/ModelSizeStats;)Lorg/elasticsearch/client/ml/job/process/ModelSizeStats$MemoryStatus;
      57: putfield      #4                  // Field memoryStatus:Lorg/elasticsearch/client/ml/job/process/ModelSizeStats$MemoryStatus;
      60: aload_0
      61: aload_1
      62: invokestatic  #20                 // Method org/elasticsearch/client/ml/job/process/ModelSizeStats.access$700:(Lorg/elasticsearch/client/ml/job/process/ModelSizeStats;)Ljava/util/Date;
      65: putfield      #21                 // Field timestamp:Ljava/util/Date;
      68: aload_0
      69: aload_1
      70: invokestatic  #22                 // Method org/elasticsearch/client/ml/job/process/ModelSizeStats.access$800:(Lorg/elasticsearch/client/ml/job/process/ModelSizeStats;)Ljava/util/Date;
      73: putfield      #7                  // Field logTime:Ljava/util/Date;
      76: return

  public org.elasticsearch.client.ml.job.process.ModelSizeStats$Builder setModelBytes(long);
    Code:
       0: aload_0
       1: lload_1
       2: putfield      #10                 // Field modelBytes:J
       5: aload_0
       6: areturn

  public org.elasticsearch.client.ml.job.process.ModelSizeStats$Builder setTotalByFieldCount(long);
    Code:
       0: aload_0
       1: lload_1
       2: putfield      #12                 // Field totalByFieldCount:J
       5: aload_0
       6: areturn

  public org.elasticsearch.client.ml.job.process.ModelSizeStats$Builder setTotalPartitionFieldCount(long);
    Code:
       0: aload_0
       1: lload_1
       2: putfield      #16                 // Field totalPartitionFieldCount:J
       5: aload_0
       6: areturn

  public org.elasticsearch.client.ml.job.process.ModelSizeStats$Builder setTotalOverFieldCount(long);
    Code:
       0: aload_0
       1: lload_1
       2: putfield      #14                 // Field totalOverFieldCount:J
       5: aload_0
       6: areturn

  public org.elasticsearch.client.ml.job.process.ModelSizeStats$Builder setBucketAllocationFailuresCount(long);
    Code:
       0: aload_0
       1: lload_1
       2: putfield      #18                 // Field bucketAllocationFailuresCount:J
       5: aload_0
       6: areturn

  public org.elasticsearch.client.ml.job.process.ModelSizeStats$Builder setMemoryStatus(org.elasticsearch.client.ml.job.process.ModelSizeStats$MemoryStatus);
    Code:
       0: aload_1
       1: new           #23                 // class java/lang/StringBuilder
       4: dup
       5: invokespecial #24                 // Method java/lang/StringBuilder."<init>":()V
       8: ldc           #25                 // String [
      10: invokevirtual #26                 // Method java/lang/StringBuilder.append:(Ljava/lang/String;)Ljava/lang/StringBuilder;
      13: getstatic     #27                 // Field org/elasticsearch/client/ml/job/process/ModelSizeStats.MEMORY_STATUS_FIELD:Lorg/elasticsearch/common/ParseField;
      16: invokevirtual #28                 // Method org/elasticsearch/common/ParseField.getPreferredName:()Ljava/lang/String;
      19: invokevirtual #26                 // Method java/lang/StringBuilder.append:(Ljava/lang/String;)Ljava/lang/StringBuilder;
      22: ldc           #29                 // String ] must not be null
      24: invokevirtual #26                 // Method java/lang/StringBuilder.append:(Ljava/lang/String;)Ljava/lang/StringBuilder;
      27: invokevirtual #30                 // Method java/lang/StringBuilder.toString:()Ljava/lang/String;
      30: invokestatic  #31                 // Method java/util/Objects.requireNonNull:(Ljava/lang/Object;Ljava/lang/String;)Ljava/lang/Object;
      33: pop
      34: aload_0
      35: aload_1
      36: putfield      #4                  // Field memoryStatus:Lorg/elasticsearch/client/ml/job/process/ModelSizeStats$MemoryStatus;
      39: aload_0
      40: areturn

  public org.elasticsearch.client.ml.job.process.ModelSizeStats$Builder setTimestamp(java.util.Date);
    Code:
       0: aload_0
       1: aload_1
       2: putfield      #21                 // Field timestamp:Ljava/util/Date;
       5: aload_0
       6: areturn

  public org.elasticsearch.client.ml.job.process.ModelSizeStats$Builder setLogTime(java.util.Date);
    Code:
       0: aload_0
       1: aload_1
       2: putfield      #7                  // Field logTime:Ljava/util/Date;
       5: aload_0
       6: areturn

  public org.elasticsearch.client.ml.job.process.ModelSizeStats build();
    Code:
       0: new           #32                 // class org/elasticsearch/client/ml/job/process/ModelSizeStats
       3: dup
       4: aload_0
       5: getfield      #2                  // Field jobId:Ljava/lang/String;
       8: aload_0
       9: getfield      #10                 // Field modelBytes:J
      12: aload_0
      13: getfield      #12                 // Field totalByFieldCount:J
      16: aload_0
      17: getfield      #14                 // Field totalOverFieldCount:J
      20: aload_0
      21: getfield      #16                 // Field totalPartitionFieldCount:J
      24: aload_0
      25: getfield      #18                 // Field bucketAllocationFailuresCount:J
      28: aload_0
      29: getfield      #4                  // Field memoryStatus:Lorg/elasticsearch/client/ml/job/process/ModelSizeStats$MemoryStatus;
      32: aload_0
      33: getfield      #21                 // Field timestamp:Ljava/util/Date;
      36: aload_0
      37: getfield      #7                  // Field logTime:Ljava/util/Date;
      40: aconst_null
      41: invokespecial #33                 // Method org/elasticsearch/client/ml/job/process/ModelSizeStats."<init>":(Ljava/lang/String;JJJJJLorg/elasticsearch/client/ml/job/process/ModelSizeStats$MemoryStatus;Ljava/util/Date;Ljava/util/Date;Lorg/elasticsearch/client/ml/job/process/ModelSizeStats$1;)V
      44: areturn
}
