Compiled from "CamelServiceExporter.java"
public class org.apache.camel.spring.remoting.CamelServiceExporter extends org.springframework.remoting.support.RemoteExporter implements org.springframework.beans.factory.InitializingBean,org.springframework.beans.factory.DisposableBean,org.springframework.context.ApplicationContextAware,org.apache.camel.CamelContextAware {
  private java.lang.String uri;

  private org.apache.camel.CamelContext camelContext;

  private java.lang.String camelContextId;

  private org.apache.camel.Consumer consumer;

  private java.lang.String serviceRef;

  private org.springframework.context.ApplicationContext applicationContext;

  public org.apache.camel.spring.remoting.CamelServiceExporter();
    Code:
       0: aload_0
       1: invokespecial #1                  // Method org/springframework/remoting/support/RemoteExporter."<init>":()V
       4: return

  public java.lang.String getUri();
    Code:
       0: aload_0
       1: getfield      #2                  // Field uri:Ljava/lang/String;
       4: areturn

  public void setUri(java.lang.String);
    Code:
       0: aload_0
       1: aload_1
       2: putfield      #2                  // Field uri:Ljava/lang/String;
       5: return

  public org.apache.camel.CamelContext getCamelContext();
    Code:
       0: aload_0
       1: getfield      #3                  // Field camelContext:Lorg/apache/camel/CamelContext;
       4: areturn

  public void setCamelContext(org.apache.camel.CamelContext);
    Code:
       0: aload_0
       1: aload_1
       2: putfield      #3                  // Field camelContext:Lorg/apache/camel/CamelContext;
       5: return

  public void setCamelContextId(java.lang.String);
    Code:
       0: aload_0
       1: aload_1
       2: putfield      #4                  // Field camelContextId:Ljava/lang/String;
       5: return

  public java.lang.String getServiceRef();
    Code:
       0: aload_0
       1: getfield      #5                  // Field serviceRef:Ljava/lang/String;
       4: areturn

  public void setServiceRef(java.lang.String);
    Code:
       0: aload_0
       1: aload_1
       2: putfield      #5                  // Field serviceRef:Ljava/lang/String;
       5: return

  public org.springframework.context.ApplicationContext getApplicationContext();
    Code:
       0: aload_0
       1: getfield      #6                  // Field applicationContext:Lorg/springframework/context/ApplicationContext;
       4: areturn

  public void setApplicationContext(org.springframework.context.ApplicationContext) throws org.springframework.beans.BeansException;
    Code:
       0: aload_0
       1: aload_1
       2: putfield      #6                  // Field applicationContext:Lorg/springframework/context/ApplicationContext;
       5: return

  public void afterPropertiesSet() throws java.lang.Exception;
    Code:
       0: aload_0
       1: getfield      #2                  // Field uri:Ljava/lang/String;
       4: ldc           #7                  // String uri
       6: invokestatic  #8                  // Method org/apache/camel/util/ObjectHelper.notNull:(Ljava/lang/Object;Ljava/lang/String;)Ljava/lang/Object;
       9: pop
      10: aload_0
      11: getfield      #4                  // Field camelContextId:Ljava/lang/String;
      14: invokestatic  #9                  // Method org/apache/camel/util/ObjectHelper.isNotEmpty:(Ljava/lang/Object;)Z
      17: ifeq          35
      20: aload_0
      21: aload_0
      22: getfield      #6                  // Field applicationContext:Lorg/springframework/context/ApplicationContext;
      25: aload_0
      26: getfield      #4                  // Field camelContextId:Ljava/lang/String;
      29: invokestatic  #10                 // Method org/apache/camel/spring/util/CamelContextResolverHelper.getCamelContextWithId:(Lorg/springframework/context/ApplicationContext;Ljava/lang/String;)Lorg/apache/camel/CamelContext;
      32: putfield      #3                  // Field camelContext:Lorg/apache/camel/CamelContext;
      35: aload_0
      36: getfield      #3                  // Field camelContext:Lorg/apache/camel/CamelContext;
      39: ldc           #11                 // String camelContext
      41: invokestatic  #8                  // Method org/apache/camel/util/ObjectHelper.notNull:(Ljava/lang/Object;Ljava/lang/String;)Ljava/lang/Object;
      44: pop
      45: aload_0
      46: getfield      #5                  // Field serviceRef:Ljava/lang/String;
      49: ifnull        83
      52: aload_0
      53: invokevirtual #12                 // Method getService:()Ljava/lang/Object;
      56: ifnonnull     83
      59: aload_0
      60: getfield      #6                  // Field applicationContext:Lorg/springframework/context/ApplicationContext;
      63: ifnull        83
      66: aload_0
      67: aload_0
      68: getfield      #6                  // Field applicationContext:Lorg/springframework/context/ApplicationContext;
      71: aload_0
      72: getfield      #5                  // Field serviceRef:Ljava/lang/String;
      75: invokeinterface #13,  2           // InterfaceMethod org/springframework/context/ApplicationContext.getBean:(Ljava/lang/String;)Ljava/lang/Object;
      80: invokevirtual #14                 // Method setService:(Ljava/lang/Object;)V
      83: aload_0
      84: getfield      #3                  // Field camelContext:Lorg/apache/camel/CamelContext;
      87: aload_0
      88: getfield      #2                  // Field uri:Ljava/lang/String;
      91: invokestatic  #15                 // Method org/apache/camel/util/CamelContextHelper.getMandatoryEndpoint:(Lorg/apache/camel/CamelContext;Ljava/lang/String;)Lorg/apache/camel/Endpoint;
      94: astore_1
      95: aload_0
      96: invokevirtual #12                 // Method getService:()Ljava/lang/Object;
      99: ldc           #16                 // String service
     101: invokestatic  #8                  // Method org/apache/camel/util/ObjectHelper.notNull:(Ljava/lang/Object;Ljava/lang/String;)Ljava/lang/Object;
     104: pop
     105: aload_0
     106: invokevirtual #17                 // Method getProxyForService:()Ljava/lang/Object;
     109: astore_2
     110: aload_0
     111: aload_1
     112: new           #18                 // class org/apache/camel/component/bean/BeanProcessor
     115: dup
     116: aload_2
     117: aload_0
     118: getfield      #3                  // Field camelContext:Lorg/apache/camel/CamelContext;
     121: invokespecial #19                 // Method org/apache/camel/component/bean/BeanProcessor."<init>":(Ljava/lang/Object;Lorg/apache/camel/CamelContext;)V
     124: invokeinterface #20,  2           // InterfaceMethod org/apache/camel/Endpoint.createConsumer:(Lorg/apache/camel/Processor;)Lorg/apache/camel/Consumer;
     129: putfield      #21                 // Field consumer:Lorg/apache/camel/Consumer;
     132: aload_0
     133: getfield      #21                 // Field consumer:Lorg/apache/camel/Consumer;
     136: invokeinterface #22,  1           // InterfaceMethod org/apache/camel/Consumer.start:()V
     141: return

  public void destroy() throws java.lang.Exception;
    Code:
       0: aload_0
       1: getfield      #21                 // Field consumer:Lorg/apache/camel/Consumer;
       4: ifnull        16
       7: aload_0
       8: getfield      #21                 // Field consumer:Lorg/apache/camel/Consumer;
      11: invokeinterface #23,  1           // InterfaceMethod org/apache/camel/Consumer.stop:()V
      16: return
}
