Compiled from "AbstractPropertyDomainFrameSection.java"
public abstract class org.protege.editor.owl.ui.frame.property.AbstractPropertyDomainFrameSection<P extends org.semanticweb.owlapi.model.OWLProperty, A extends org.semanticweb.owlapi.model.OWLPropertyDomainAxiom> extends org.protege.editor.owl.ui.frame.AbstractOWLFrameSection<P, A, org.semanticweb.owlapi.model.OWLClassExpression> {
  public static final java.lang.String LABEL;

  java.util.Set<org.semanticweb.owlapi.model.OWLClassExpression> addedDomains;

  public org.protege.editor.owl.ui.frame.property.AbstractPropertyDomainFrameSection(org.protege.editor.owl.OWLEditorKit, org.protege.editor.owl.ui.frame.OWLFrame<P>);
    Code:
       0: aload_0
       1: aload_1
       2: ldc           #2                  // String Domains (intersection)
       4: ldc           #3                  // String Domain
       6: aload_2
       7: invokespecial #4                  // Method org/protege/editor/owl/ui/frame/AbstractOWLFrameSection."<init>":(Lorg/protege/editor/owl/OWLEditorKit;Ljava/lang/String;Ljava/lang/String;Lorg/protege/editor/owl/ui/frame/OWLFrame;)V
      10: aload_0
      11: new           #5                  // class java/util/HashSet
      14: dup
      15: invokespecial #6                  // Method java/util/HashSet."<init>":()V
      18: putfield      #7                  // Field addedDomains:Ljava/util/Set;
      21: return

  public org.protege.editor.owl.ui.editor.OWLObjectEditor<org.semanticweb.owlapi.model.OWLClassExpression> getObjectEditor();
    Code:
       0: aload_0
       1: invokevirtual #8                  // Method getRootObject:()Ljava/lang/Object;
       4: instanceof    #9                  // class org/semanticweb/owlapi/model/OWLObjectProperty
       7: ifeq          17
      10: getstatic     #10                 // Field org/semanticweb/owlapi/model/AxiomType.OBJECT_PROPERTY_DOMAIN:Lorg/semanticweb/owlapi/model/AxiomType;
      13: astore_1
      14: goto          21
      17: getstatic     #11                 // Field org/semanticweb/owlapi/model/AxiomType.DATA_PROPERTY_DOMAIN:Lorg/semanticweb/owlapi/model/AxiomType;
      20: astore_1
      21: aload_0
      22: invokevirtual #12                 // Method getOWLEditorKit:()Lorg/protege/editor/owl/OWLEditorKit;
      25: invokevirtual #13                 // Method org/protege/editor/owl/OWLEditorKit.getWorkspace:()Lorg/protege/editor/owl/model/OWLWorkspace;
      28: invokevirtual #14                 // Method org/protege/editor/owl/model/OWLWorkspace.getOWLComponentFactory:()Lorg/protege/editor/owl/ui/util/OWLComponentFactory;
      31: aconst_null
      32: aload_1
      33: invokeinterface #15,  3           // InterfaceMethod org/protege/editor/owl/ui/util/OWLComponentFactory.getOWLClassDescriptionEditor:(Lorg/semanticweb/owlapi/model/OWLClassExpression;Lorg/semanticweb/owlapi/model/AxiomType;)Lorg/protege/editor/owl/ui/editor/OWLClassDescriptionEditor;
      38: areturn

  public final boolean canAcceptDrop(java.util.List<org.semanticweb.owlapi.model.OWLObject>);
    Code:
       0: aload_1
       1: invokeinterface #16,  1           // InterfaceMethod java/util/List.iterator:()Ljava/util/Iterator;
       6: astore_2
       7: aload_2
       8: invokeinterface #17,  1           // InterfaceMethod java/util/Iterator.hasNext:()Z
      13: ifeq          38
      16: aload_2
      17: invokeinterface #18,  1           // InterfaceMethod java/util/Iterator.next:()Ljava/lang/Object;
      22: checkcast     #19                 // class org/semanticweb/owlapi/model/OWLObject
      25: astore_3
      26: aload_3
      27: instanceof    #20                 // class org/semanticweb/owlapi/model/OWLClassExpression
      30: ifne          35
      33: iconst_0
      34: ireturn
      35: goto          7
      38: iconst_1
      39: ireturn

  public final boolean dropObjects(java.util.List<org.semanticweb.owlapi.model.OWLObject>);
    Code:
       0: new           #21                 // class java/util/ArrayList
       3: dup
       4: invokespecial #22                 // Method java/util/ArrayList."<init>":()V
       7: astore_2
       8: aload_1
       9: invokeinterface #16,  1           // InterfaceMethod java/util/List.iterator:()Ljava/util/Iterator;
      14: astore_3
      15: aload_3
      16: invokeinterface #17,  1           // InterfaceMethod java/util/Iterator.hasNext:()Z
      21: ifeq          91
      24: aload_3
      25: invokeinterface #18,  1           // InterfaceMethod java/util/Iterator.next:()Ljava/lang/Object;
      30: checkcast     #19                 // class org/semanticweb/owlapi/model/OWLObject
      33: astore        4
      35: aload         4
      37: instanceof    #20                 // class org/semanticweb/owlapi/model/OWLClassExpression
      40: ifeq          86
      43: aload         4
      45: checkcast     #20                 // class org/semanticweb/owlapi/model/OWLClassExpression
      48: astore        5
      50: aload_0
      51: aload         5
      53: invokevirtual #23                 // Method createAxiom:(Ljava/lang/Object;)Lorg/semanticweb/owlapi/model/OWLAxiom;
      56: astore        6
      58: aload_2
      59: new           #24                 // class org/semanticweb/owlapi/model/AddAxiom
      62: dup
      63: aload_0
      64: invokevirtual #25                 // Method getOWLModelManager:()Lorg/protege/editor/owl/model/OWLModelManager;
      67: invokeinterface #26,  1           // InterfaceMethod org/protege/editor/owl/model/OWLModelManager.getActiveOntology:()Lorg/semanticweb/owlapi/model/OWLOntology;
      72: aload         6
      74: invokespecial #27                 // Method org/semanticweb/owlapi/model/AddAxiom."<init>":(Lorg/semanticweb/owlapi/model/OWLOntology;Lorg/semanticweb/owlapi/model/OWLAxiom;)V
      77: invokeinterface #28,  2           // InterfaceMethod java/util/List.add:(Ljava/lang/Object;)Z
      82: pop
      83: goto          88
      86: iconst_0
      87: ireturn
      88: goto          15
      91: aload_0
      92: invokevirtual #25                 // Method getOWLModelManager:()Lorg/protege/editor/owl/model/OWLModelManager;
      95: aload_2
      96: invokeinterface #29,  2           // InterfaceMethod org/protege/editor/owl/model/OWLModelManager.applyChanges:(Ljava/util/List;)V
     101: iconst_1
     102: ireturn

  protected abstract org.protege.editor.owl.ui.frame.property.AbstractPropertyDomainFrameSectionRow<P, A> createFrameSectionRow(A, org.semanticweb.owlapi.model.OWLOntology);

  protected abstract java.util.Set<A> getAxioms(org.semanticweb.owlapi.model.OWLOntology);

  protected abstract org.semanticweb.owlapi.reasoner.NodeSet<org.semanticweb.owlapi.model.OWLClass> getInferredDomains();

  protected void clear();
    Code:
       0: aload_0
       1: getfield      #7                  // Field addedDomains:Ljava/util/Set;
       4: invokeinterface #30,  1           // InterfaceMethod java/util/Set.clear:()V
       9: return

  protected final void refill(org.semanticweb.owlapi.model.OWLOntology);
    Code:
       0: aload_0
       1: aload_1
       2: invokevirtual #31                 // Method getAxioms:(Lorg/semanticweb/owlapi/model/OWLOntology;)Ljava/util/Set;
       5: invokeinterface #32,  1           // InterfaceMethod java/util/Set.iterator:()Ljava/util/Iterator;
      10: astore_2
      11: aload_2
      12: invokeinterface #17,  1           // InterfaceMethod java/util/Iterator.hasNext:()Z
      17: ifeq          59
      20: aload_2
      21: invokeinterface #18,  1           // InterfaceMethod java/util/Iterator.next:()Ljava/lang/Object;
      26: checkcast     #33                 // class org/semanticweb/owlapi/model/OWLPropertyDomainAxiom
      29: astore_3
      30: aload_0
      31: aload_0
      32: aload_3
      33: aload_1
      34: invokevirtual #34                 // Method createFrameSectionRow:(Lorg/semanticweb/owlapi/model/OWLPropertyDomainAxiom;Lorg/semanticweb/owlapi/model/OWLOntology;)Lorg/protege/editor/owl/ui/frame/property/AbstractPropertyDomainFrameSectionRow;
      37: invokevirtual #35                 // Method addRow:(Lorg/protege/editor/owl/ui/frame/OWLFrameSectionRow;)V
      40: aload_0
      41: getfield      #7                  // Field addedDomains:Ljava/util/Set;
      44: aload_3
      45: invokeinterface #36,  1           // InterfaceMethod org/semanticweb/owlapi/model/OWLPropertyDomainAxiom.getDomain:()Lorg/semanticweb/owlapi/model/OWLClassExpression;
      50: invokeinterface #37,  2           // InterfaceMethod java/util/Set.add:(Ljava/lang/Object;)Z
      55: pop
      56: goto          11
      59: return

  protected void refillInferred();
    Code:
       0: aload_0
       1: invokevirtual #38                 // Method getInferredDomains:()Lorg/semanticweb/owlapi/reasoner/NodeSet;
       4: invokeinterface #39,  1           // InterfaceMethod org/semanticweb/owlapi/reasoner/NodeSet.iterator:()Ljava/util/Iterator;
       9: astore_1
      10: aload_1
      11: invokeinterface #17,  1           // InterfaceMethod java/util/Iterator.hasNext:()Z
      16: ifeq          106
      19: aload_1
      20: invokeinterface #18,  1           // InterfaceMethod java/util/Iterator.next:()Ljava/lang/Object;
      25: checkcast     #40                 // class org/semanticweb/owlapi/reasoner/Node
      28: astore_2
      29: aload_2
      30: invokeinterface #41,  1           // InterfaceMethod org/semanticweb/owlapi/reasoner/Node.iterator:()Ljava/util/Iterator;
      35: astore_3
      36: aload_3
      37: invokeinterface #17,  1           // InterfaceMethod java/util/Iterator.hasNext:()Z
      42: ifeq          103
      45: aload_3
      46: invokeinterface #18,  1           // InterfaceMethod java/util/Iterator.next:()Ljava/lang/Object;
      51: checkcast     #20                 // class org/semanticweb/owlapi/model/OWLClassExpression
      54: astore        4
      56: aload_0
      57: getfield      #7                  // Field addedDomains:Ljava/util/Set;
      60: aload         4
      62: invokeinterface #42,  2           // InterfaceMethod java/util/Set.contains:(Ljava/lang/Object;)Z
      67: ifne          100
      70: aload_0
      71: aload_0
      72: aload_0
      73: aload         4
      75: invokevirtual #23                 // Method createAxiom:(Ljava/lang/Object;)Lorg/semanticweb/owlapi/model/OWLAxiom;
      78: checkcast     #33                 // class org/semanticweb/owlapi/model/OWLPropertyDomainAxiom
      81: aconst_null
      82: invokevirtual #34                 // Method createFrameSectionRow:(Lorg/semanticweb/owlapi/model/OWLPropertyDomainAxiom;Lorg/semanticweb/owlapi/model/OWLOntology;)Lorg/protege/editor/owl/ui/frame/property/AbstractPropertyDomainFrameSectionRow;
      85: invokevirtual #43                 // Method addInferredRowIfNontrivial:(Lorg/protege/editor/owl/ui/frame/OWLFrameSectionRow;)V
      88: aload_0
      89: getfield      #7                  // Field addedDomains:Ljava/util/Set;
      92: aload         4
      94: invokeinterface #37,  2           // InterfaceMethod java/util/Set.add:(Ljava/lang/Object;)Z
      99: pop
     100: goto          36
     103: goto          10
     106: return

  public java.util.Comparator<org.protege.editor.owl.ui.frame.OWLFrameSectionRow<P, A, org.semanticweb.owlapi.model.OWLClassExpression>> getRowComparator();
    Code:
       0: aconst_null
       1: areturn
}
