Compiled from "AltsContextUtil.java"
public final class io.grpc.alts.AltsContextUtil {
  private io.grpc.alts.AltsContextUtil();
    Code:
       0: aload_0
       1: invokespecial #17                 // Method java/lang/Object."<init>":()V
       4: return

  public static io.grpc.alts.AltsContext createFrom(io.grpc.ServerCall<?, ?>);
    Code:
       0: aload_0
       1: invokevirtual #28                 // Method io/grpc/ServerCall.getAttributes:()Lio/grpc/Attributes;
       4: getstatic     #34                 // Field io/grpc/alts/internal/AltsProtocolNegotiator.AUTH_CONTEXT_KEY:Lio/grpc/Attributes$Key;
       7: invokevirtual #38                 // Method io/grpc/Attributes.get:(Lio/grpc/Attributes$Key;)Ljava/lang/Object;
      10: astore_1
      11: aload_1
      12: instanceof    #40                 // class io/grpc/alts/internal/AltsInternalContext
      15: ifne          28
      18: new           #42                 // class java/lang/IllegalArgumentException
      21: dup
      22: ldc           #44                 // String No ALTS context information found
      24: invokespecial #47                 // Method java/lang/IllegalArgumentException."<init>":(Ljava/lang/String;)V
      27: athrow
      28: new           #49                 // class io/grpc/alts/AltsContext
      31: dup
      32: aload_1
      33: checkcast     #40                 // class io/grpc/alts/internal/AltsInternalContext
      36: invokespecial #52                 // Method io/grpc/alts/AltsContext."<init>":(Lio/grpc/alts/internal/AltsInternalContext;)V
      39: areturn

  public static boolean check(io.grpc.ServerCall<?, ?>);
    Code:
       0: aload_0
       1: invokevirtual #28                 // Method io/grpc/ServerCall.getAttributes:()Lio/grpc/Attributes;
       4: getstatic     #34                 // Field io/grpc/alts/internal/AltsProtocolNegotiator.AUTH_CONTEXT_KEY:Lio/grpc/Attributes$Key;
       7: invokevirtual #38                 // Method io/grpc/Attributes.get:(Lio/grpc/Attributes$Key;)Ljava/lang/Object;
      10: astore_1
      11: aload_1
      12: instanceof    #40                 // class io/grpc/alts/internal/AltsInternalContext
      15: ireturn
}
