Compiled from "Console.kt"
final class kotlin.io.ConsoleKt$decoder$2 extends kotlin.jvm.internal.Lambda implements kotlin.jvm.functions.Function0<java.nio.charset.CharsetDecoder> {
  public static final kotlin.io.ConsoleKt$decoder$2 INSTANCE;

  public java.lang.Object invoke();
    Code:
       0: aload_0
       1: invokevirtual #12                 // Method invoke:()Ljava/nio/charset/CharsetDecoder;
       4: areturn

  public final java.nio.charset.CharsetDecoder invoke();
    Code:
       0: invokestatic  #18                 // Method java/nio/charset/Charset.defaultCharset:()Ljava/nio/charset/Charset;
       3: invokevirtual #21                 // Method java/nio/charset/Charset.newDecoder:()Ljava/nio/charset/CharsetDecoder;
       6: areturn

  kotlin.io.ConsoleKt$decoder$2();
    Code:
       0: aload_0
       1: iconst_0
       2: invokespecial #28                 // Method kotlin/jvm/internal/Lambda."<init>":(I)V
       5: return

  static {};
    Code:
       0: new           #2                  // class kotlin/io/ConsoleKt$decoder$2
       3: dup
       4: invokespecial #48                 // Method "<init>":()V
       7: putstatic     #50                 // Field INSTANCE:Lkotlin/io/ConsoleKt$decoder$2;
      10: return
}
