Compiled from "NamedBeanQualifier.java"
public class org.hibernate.resource.beans.container.internal.NamedBeanQualifier extends javax.enterprise.util.AnnotationLiteral<javax.inject.Named> implements javax.inject.Named {
  private final java.lang.String name;

  org.hibernate.resource.beans.container.internal.NamedBeanQualifier(java.lang.String);
    Code:
       0: aload_0
       1: invokespecial #1                  // Method javax/enterprise/util/AnnotationLiteral."<init>":()V
       4: aload_0
       5: aload_1
       6: putfield      #2                  // Field name:Ljava/lang/String;
       9: return

  public java.lang.String value();
    Code:
       0: aload_0
       1: getfield      #2                  // Field name:Ljava/lang/String;
       4: areturn
}
