Compiled from "ResolvedLink.java"
public class com.vladsch.flexmark.html.renderer.ResolvedLink {
  private final com.vladsch.flexmark.html.renderer.LinkType myLinkType;

  private final java.lang.String myUrl;

  private final com.vladsch.flexmark.html.renderer.LinkStatus myStatus;

  private com.vladsch.flexmark.util.html.Attributes myAttributes;

  public com.vladsch.flexmark.html.renderer.ResolvedLink(com.vladsch.flexmark.html.renderer.LinkType, java.lang.CharSequence);
    Code:
       0: aload_0
       1: aload_1
       2: aload_2
       3: aconst_null
       4: getstatic     #1                  // Field com/vladsch/flexmark/html/renderer/LinkStatus.UNKNOWN:Lcom/vladsch/flexmark/html/renderer/LinkStatus;
       7: invokespecial #2                  // Method "<init>":(Lcom/vladsch/flexmark/html/renderer/LinkType;Ljava/lang/CharSequence;Lcom/vladsch/flexmark/util/html/Attributes;Lcom/vladsch/flexmark/html/renderer/LinkStatus;)V
      10: return

  public com.vladsch.flexmark.html.renderer.ResolvedLink(com.vladsch.flexmark.html.renderer.LinkType, java.lang.CharSequence, com.vladsch.flexmark.util.html.Attributes);
    Code:
       0: aload_0
       1: aload_1
       2: aload_2
       3: aload_3
       4: getstatic     #1                  // Field com/vladsch/flexmark/html/renderer/LinkStatus.UNKNOWN:Lcom/vladsch/flexmark/html/renderer/LinkStatus;
       7: invokespecial #2                  // Method "<init>":(Lcom/vladsch/flexmark/html/renderer/LinkType;Ljava/lang/CharSequence;Lcom/vladsch/flexmark/util/html/Attributes;Lcom/vladsch/flexmark/html/renderer/LinkStatus;)V
      10: return

  public com.vladsch.flexmark.util.html.Attributes getAttributes();
    Code:
       0: aload_0
       1: getfield      #3                  // Field myAttributes:Lcom/vladsch/flexmark/util/html/Attributes;
       4: areturn

  public com.vladsch.flexmark.util.html.Attributes getNonNullAttributes();
    Code:
       0: aload_0
       1: getfield      #3                  // Field myAttributes:Lcom/vladsch/flexmark/util/html/Attributes;
       4: ifnonnull     18
       7: aload_0
       8: new           #4                  // class com/vladsch/flexmark/util/html/Attributes
      11: dup
      12: invokespecial #5                  // Method com/vladsch/flexmark/util/html/Attributes."<init>":()V
      15: putfield      #3                  // Field myAttributes:Lcom/vladsch/flexmark/util/html/Attributes;
      18: aload_0
      19: getfield      #3                  // Field myAttributes:Lcom/vladsch/flexmark/util/html/Attributes;
      22: areturn

  public com.vladsch.flexmark.html.renderer.ResolvedLink(com.vladsch.flexmark.html.renderer.LinkType, java.lang.CharSequence, com.vladsch.flexmark.util.html.Attributes, com.vladsch.flexmark.html.renderer.LinkStatus);
    Code:
       0: aload_0
       1: invokespecial #6                  // Method java/lang/Object."<init>":()V
       4: aload_0
       5: aload_1
       6: putfield      #7                  // Field myLinkType:Lcom/vladsch/flexmark/html/renderer/LinkType;
       9: aload_0
      10: aload_2
      11: instanceof    #8                  // class java/lang/String
      14: ifeq          24
      17: aload_2
      18: checkcast     #8                  // class java/lang/String
      21: goto          28
      24: aload_2
      25: invokestatic  #9                  // Method java/lang/String.valueOf:(Ljava/lang/Object;)Ljava/lang/String;
      28: putfield      #10                 // Field myUrl:Ljava/lang/String;
      31: aload_0
      32: aload         4
      34: putfield      #11                 // Field myStatus:Lcom/vladsch/flexmark/html/renderer/LinkStatus;
      37: aload_3
      38: ifnull        50
      41: aload_0
      42: invokevirtual #12                 // Method getNonNullAttributes:()Lcom/vladsch/flexmark/util/html/Attributes;
      45: aload_3
      46: invokevirtual #13                 // Method com/vladsch/flexmark/util/html/Attributes.addValues:(Lcom/vladsch/flexmark/util/html/Attributes;)Lcom/vladsch/flexmark/util/html/Attributes;
      49: pop
      50: return

  public com.vladsch.flexmark.html.renderer.ResolvedLink withLinkType(com.vladsch.flexmark.html.renderer.LinkType);
    Code:
       0: aload_1
       1: aload_0
       2: getfield      #7                  // Field myLinkType:Lcom/vladsch/flexmark/html/renderer/LinkType;
       5: if_acmpne     12
       8: aload_0
       9: goto          32
      12: new           #14                 // class com/vladsch/flexmark/html/renderer/ResolvedLink
      15: dup
      16: aload_1
      17: aload_0
      18: getfield      #10                 // Field myUrl:Ljava/lang/String;
      21: aload_0
      22: getfield      #3                  // Field myAttributes:Lcom/vladsch/flexmark/util/html/Attributes;
      25: aload_0
      26: getfield      #11                 // Field myStatus:Lcom/vladsch/flexmark/html/renderer/LinkStatus;
      29: invokespecial #2                  // Method "<init>":(Lcom/vladsch/flexmark/html/renderer/LinkType;Ljava/lang/CharSequence;Lcom/vladsch/flexmark/util/html/Attributes;Lcom/vladsch/flexmark/html/renderer/LinkStatus;)V
      32: areturn

  public com.vladsch.flexmark.html.renderer.ResolvedLink withStatus(com.vladsch.flexmark.html.renderer.LinkStatus);
    Code:
       0: aload_1
       1: aload_0
       2: getfield      #11                 // Field myStatus:Lcom/vladsch/flexmark/html/renderer/LinkStatus;
       5: if_acmpne     12
       8: aload_0
       9: goto          32
      12: new           #14                 // class com/vladsch/flexmark/html/renderer/ResolvedLink
      15: dup
      16: aload_0
      17: getfield      #7                  // Field myLinkType:Lcom/vladsch/flexmark/html/renderer/LinkType;
      20: aload_0
      21: getfield      #10                 // Field myUrl:Ljava/lang/String;
      24: aload_0
      25: getfield      #3                  // Field myAttributes:Lcom/vladsch/flexmark/util/html/Attributes;
      28: aload_1
      29: invokespecial #2                  // Method "<init>":(Lcom/vladsch/flexmark/html/renderer/LinkType;Ljava/lang/CharSequence;Lcom/vladsch/flexmark/util/html/Attributes;Lcom/vladsch/flexmark/html/renderer/LinkStatus;)V
      32: areturn

  public com.vladsch.flexmark.html.renderer.LinkType getLinkType();
    Code:
       0: aload_0
       1: getfield      #7                  // Field myLinkType:Lcom/vladsch/flexmark/html/renderer/LinkType;
       4: areturn

  public com.vladsch.flexmark.html.renderer.LinkStatus getStatus();
    Code:
       0: aload_0
       1: getfield      #11                 // Field myStatus:Lcom/vladsch/flexmark/html/renderer/LinkStatus;
       4: areturn

  public com.vladsch.flexmark.html.renderer.ResolvedLink withUrl(java.lang.CharSequence);
    Code:
       0: aload_1
       1: instanceof    #8                  // class java/lang/String
       4: ifeq          14
       7: aload_1
       8: checkcast     #8                  // class java/lang/String
      11: goto          18
      14: aload_1
      15: invokestatic  #9                  // Method java/lang/String.valueOf:(Ljava/lang/Object;)Ljava/lang/String;
      18: astore_2
      19: aload_0
      20: getfield      #10                 // Field myUrl:Ljava/lang/String;
      23: aload_2
      24: invokevirtual #15                 // Method java/lang/String.equals:(Ljava/lang/Object;)Z
      27: ifeq          34
      30: aload_0
      31: goto          54
      34: new           #14                 // class com/vladsch/flexmark/html/renderer/ResolvedLink
      37: dup
      38: aload_0
      39: getfield      #7                  // Field myLinkType:Lcom/vladsch/flexmark/html/renderer/LinkType;
      42: aload_2
      43: aload_0
      44: getfield      #3                  // Field myAttributes:Lcom/vladsch/flexmark/util/html/Attributes;
      47: aload_0
      48: getfield      #11                 // Field myStatus:Lcom/vladsch/flexmark/html/renderer/LinkStatus;
      51: invokespecial #2                  // Method "<init>":(Lcom/vladsch/flexmark/html/renderer/LinkType;Ljava/lang/CharSequence;Lcom/vladsch/flexmark/util/html/Attributes;Lcom/vladsch/flexmark/html/renderer/LinkStatus;)V
      54: areturn

  public java.lang.String getUrl();
    Code:
       0: aload_0
       1: getfield      #10                 // Field myUrl:Ljava/lang/String;
       4: areturn

  public com.vladsch.flexmark.html.renderer.ResolvedLink withTitle(java.lang.CharSequence);
    Code:
       0: aload_0
       1: getfield      #3                  // Field myAttributes:Lcom/vladsch/flexmark/util/html/Attributes;
       4: ifnonnull     11
       7: aconst_null
       8: goto          20
      11: aload_0
      12: getfield      #3                  // Field myAttributes:Lcom/vladsch/flexmark/util/html/Attributes;
      15: ldc           #17                 // String title
      17: invokevirtual #18                 // Method com/vladsch/flexmark/util/html/Attributes.getValue:(Ljava/lang/CharSequence;)Ljava/lang/String;
      20: astore_2
      21: aload_1
      22: aload_2
      23: if_acmpeq     38
      26: aload_2
      27: ifnull        40
      30: aload_2
      31: aload_1
      32: invokevirtual #15                 // Method java/lang/String.equals:(Ljava/lang/Object;)Z
      35: ifeq          40
      38: aload_0
      39: areturn
      40: new           #4                  // class com/vladsch/flexmark/util/html/Attributes
      43: dup
      44: aload_0
      45: getfield      #3                  // Field myAttributes:Lcom/vladsch/flexmark/util/html/Attributes;
      48: invokespecial #19                 // Method com/vladsch/flexmark/util/html/Attributes."<init>":(Lcom/vladsch/flexmark/util/html/Attributes;)V
      51: astore_3
      52: aload_1
      53: ifnonnull     75
      56: aload_3
      57: ldc           #17                 // String title
      59: invokevirtual #20                 // Method com/vladsch/flexmark/util/html/Attributes.remove:(Ljava/lang/CharSequence;)Lcom/vladsch/flexmark/util/html/Attribute;
      62: pop
      63: aload_3
      64: invokevirtual #21                 // Method com/vladsch/flexmark/util/html/Attributes.isEmpty:()Z
      67: ifeq          83
      70: aconst_null
      71: astore_3
      72: goto          83
      75: aload_3
      76: ldc           #17                 // String title
      78: aload_1
      79: invokevirtual #22                 // Method com/vladsch/flexmark/util/html/Attributes.replaceValue:(Ljava/lang/CharSequence;Ljava/lang/CharSequence;)Lcom/vladsch/flexmark/util/html/Attribute;
      82: pop
      83: new           #14                 // class com/vladsch/flexmark/html/renderer/ResolvedLink
      86: dup
      87: aload_0
      88: getfield      #7                  // Field myLinkType:Lcom/vladsch/flexmark/html/renderer/LinkType;
      91: aload_0
      92: getfield      #10                 // Field myUrl:Ljava/lang/String;
      95: aload_3
      96: aload_0
      97: getfield      #11                 // Field myStatus:Lcom/vladsch/flexmark/html/renderer/LinkStatus;
     100: invokespecial #2                  // Method "<init>":(Lcom/vladsch/flexmark/html/renderer/LinkType;Ljava/lang/CharSequence;Lcom/vladsch/flexmark/util/html/Attributes;Lcom/vladsch/flexmark/html/renderer/LinkStatus;)V
     103: areturn

  public java.lang.String getTitle();
    Code:
       0: aload_0
       1: getfield      #3                  // Field myAttributes:Lcom/vladsch/flexmark/util/html/Attributes;
       4: ifnonnull     11
       7: aconst_null
       8: goto          20
      11: aload_0
      12: getfield      #3                  // Field myAttributes:Lcom/vladsch/flexmark/util/html/Attributes;
      15: ldc           #17                 // String title
      17: invokevirtual #18                 // Method com/vladsch/flexmark/util/html/Attributes.getValue:(Ljava/lang/CharSequence;)Ljava/lang/String;
      20: areturn

  public com.vladsch.flexmark.html.renderer.ResolvedLink withTarget(java.lang.CharSequence);
    Code:
       0: aload_0
       1: getfield      #3                  // Field myAttributes:Lcom/vladsch/flexmark/util/html/Attributes;
       4: ifnonnull     11
       7: aconst_null
       8: goto          20
      11: aload_0
      12: getfield      #3                  // Field myAttributes:Lcom/vladsch/flexmark/util/html/Attributes;
      15: ldc           #23                 // String target
      17: invokevirtual #18                 // Method com/vladsch/flexmark/util/html/Attributes.getValue:(Ljava/lang/CharSequence;)Ljava/lang/String;
      20: astore_2
      21: aload_1
      22: aload_2
      23: if_acmpeq     38
      26: aload_2
      27: ifnull        40
      30: aload_2
      31: aload_1
      32: invokevirtual #15                 // Method java/lang/String.equals:(Ljava/lang/Object;)Z
      35: ifeq          40
      38: aload_0
      39: areturn
      40: new           #4                  // class com/vladsch/flexmark/util/html/Attributes
      43: dup
      44: aload_0
      45: getfield      #3                  // Field myAttributes:Lcom/vladsch/flexmark/util/html/Attributes;
      48: invokespecial #19                 // Method com/vladsch/flexmark/util/html/Attributes."<init>":(Lcom/vladsch/flexmark/util/html/Attributes;)V
      51: astore_3
      52: aload_1
      53: ifnonnull     75
      56: aload_3
      57: ldc           #23                 // String target
      59: invokevirtual #20                 // Method com/vladsch/flexmark/util/html/Attributes.remove:(Ljava/lang/CharSequence;)Lcom/vladsch/flexmark/util/html/Attribute;
      62: pop
      63: aload_3
      64: invokevirtual #21                 // Method com/vladsch/flexmark/util/html/Attributes.isEmpty:()Z
      67: ifeq          83
      70: aconst_null
      71: astore_3
      72: goto          83
      75: aload_3
      76: ldc           #23                 // String target
      78: aload_1
      79: invokevirtual #22                 // Method com/vladsch/flexmark/util/html/Attributes.replaceValue:(Ljava/lang/CharSequence;Ljava/lang/CharSequence;)Lcom/vladsch/flexmark/util/html/Attribute;
      82: pop
      83: new           #14                 // class com/vladsch/flexmark/html/renderer/ResolvedLink
      86: dup
      87: aload_0
      88: getfield      #7                  // Field myLinkType:Lcom/vladsch/flexmark/html/renderer/LinkType;
      91: aload_0
      92: getfield      #10                 // Field myUrl:Ljava/lang/String;
      95: aload_3
      96: aload_0
      97: getfield      #11                 // Field myStatus:Lcom/vladsch/flexmark/html/renderer/LinkStatus;
     100: invokespecial #2                  // Method "<init>":(Lcom/vladsch/flexmark/html/renderer/LinkType;Ljava/lang/CharSequence;Lcom/vladsch/flexmark/util/html/Attributes;Lcom/vladsch/flexmark/html/renderer/LinkStatus;)V
     103: areturn

  public java.lang.String getTarget();
    Code:
       0: aload_0
       1: getfield      #3                  // Field myAttributes:Lcom/vladsch/flexmark/util/html/Attributes;
       4: ifnonnull     11
       7: aconst_null
       8: goto          20
      11: aload_0
      12: getfield      #3                  // Field myAttributes:Lcom/vladsch/flexmark/util/html/Attributes;
      15: ldc           #23                 // String target
      17: invokevirtual #18                 // Method com/vladsch/flexmark/util/html/Attributes.getValue:(Ljava/lang/CharSequence;)Ljava/lang/String;
      20: areturn

  public boolean equals(java.lang.Object);
    Code:
       0: aload_0
       1: aload_1
       2: if_acmpne     7
       5: iconst_1
       6: ireturn
       7: aload_1
       8: instanceof    #14                 // class com/vladsch/flexmark/html/renderer/ResolvedLink
      11: ifne          16
      14: iconst_0
      15: ireturn
      16: aload_1
      17: checkcast     #14                 // class com/vladsch/flexmark/html/renderer/ResolvedLink
      20: astore_2
      21: aload_0
      22: getfield      #7                  // Field myLinkType:Lcom/vladsch/flexmark/html/renderer/LinkType;
      25: aload_2
      26: getfield      #7                  // Field myLinkType:Lcom/vladsch/flexmark/html/renderer/LinkType;
      29: invokevirtual #24                 // Method com/vladsch/flexmark/html/renderer/LinkType.equals:(Ljava/lang/Object;)Z
      32: ifne          37
      35: iconst_0
      36: ireturn
      37: aload_0
      38: getfield      #10                 // Field myUrl:Ljava/lang/String;
      41: aload_2
      42: getfield      #10                 // Field myUrl:Ljava/lang/String;
      45: invokevirtual #15                 // Method java/lang/String.equals:(Ljava/lang/Object;)Z
      48: ifne          53
      51: iconst_0
      52: ireturn
      53: aload_0
      54: getfield      #11                 // Field myStatus:Lcom/vladsch/flexmark/html/renderer/LinkStatus;
      57: aload_2
      58: getfield      #11                 // Field myStatus:Lcom/vladsch/flexmark/html/renderer/LinkStatus;
      61: invokevirtual #25                 // Method com/vladsch/flexmark/html/renderer/LinkStatus.equals:(Ljava/lang/Object;)Z
      64: ireturn

  public int hashCode();
    Code:
       0: aload_0
       1: getfield      #7                  // Field myLinkType:Lcom/vladsch/flexmark/html/renderer/LinkType;
       4: invokevirtual #26                 // Method com/vladsch/flexmark/html/renderer/LinkType.hashCode:()I
       7: istore_1
       8: bipush        31
      10: iload_1
      11: imul
      12: aload_0
      13: getfield      #10                 // Field myUrl:Ljava/lang/String;
      16: invokevirtual #27                 // Method java/lang/String.hashCode:()I
      19: iadd
      20: istore_1
      21: bipush        31
      23: iload_1
      24: imul
      25: aload_0
      26: getfield      #11                 // Field myStatus:Lcom/vladsch/flexmark/html/renderer/LinkStatus;
      29: invokevirtual #28                 // Method com/vladsch/flexmark/html/renderer/LinkStatus.hashCode:()I
      32: iadd
      33: istore_1
      34: iload_1
      35: ireturn
}
