Compiled from "AggCount.java"
public class org.apache.jena.sparql.expr.aggregate.AggCount extends org.apache.jena.sparql.expr.aggregate.AggregatorBase {
  public org.apache.jena.sparql.expr.aggregate.AggCount();
    Code:
       0: aload_0
       1: ldc           #1                  // String COUNT
       3: iconst_0
       4: aconst_null
       5: checkcast     #2                  // class org/apache/jena/sparql/expr/ExprList
       8: invokespecial #3                  // Method org/apache/jena/sparql/expr/aggregate/AggregatorBase."<init>":(Ljava/lang/String;ZLorg/apache/jena/sparql/expr/ExprList;)V
      11: return

  public org.apache.jena.sparql.expr.aggregate.Aggregator copy(org.apache.jena.sparql.expr.ExprList);
    Code:
       0: aload_1
       1: ifnull        10
       4: aload_0
       5: ldc           #4                  // String Copying non-null expression for COUNT(*)
       7: invokestatic  #5                  // Method org/apache/jena/atlas/logging/Log.warn:(Ljava/lang/Object;Ljava/lang/String;)V
      10: new           #6                  // class org/apache/jena/sparql/expr/aggregate/AggCount
      13: dup
      14: invokespecial #7                  // Method "<init>":()V
      17: areturn

  public org.apache.jena.sparql.expr.Expr getExpr();
    Code:
       0: aconst_null
       1: areturn

  public org.apache.jena.sparql.expr.aggregate.Accumulator createAccumulator();
    Code:
       0: new           #8                  // class org/apache/jena/sparql/expr/aggregate/AggCount$AccCount
       3: dup
       4: invokespecial #9                  // Method org/apache/jena/sparql/expr/aggregate/AggCount$AccCount."<init>":()V
       7: areturn

  public java.lang.String asSparqlExpr(org.apache.jena.sparql.serializer.SerializationContext);
    Code:
       0: ldc           #10                 // String count(*)
       2: areturn

  public java.lang.String toString();
    Code:
       0: ldc           #10                 // String count(*)
       2: areturn

  public java.lang.String toPrefixString();
    Code:
       0: ldc           #11                 // String (count)
       2: areturn

  public org.apache.jena.graph.Node getValueEmpty();
    Code:
       0: getstatic     #12                 // Field org/apache/jena/sparql/graph/NodeConst.nodeZero:Lorg/apache/jena/graph/Node;
       3: areturn

  public int hashCode();
    Code:
       0: sipush        370
       3: ireturn

  public boolean equals(org.apache.jena.sparql.expr.aggregate.Aggregator, boolean);
    Code:
       0: aload_1
       1: ifnonnull     6
       4: iconst_0
       5: ireturn
       6: aload_0
       7: aload_1
       8: if_acmpne     13
      11: iconst_1
      12: ireturn
      13: aload_1
      14: instanceof    #6                  // class org/apache/jena/sparql/expr/aggregate/AggCount
      17: ifne          22
      20: iconst_0
      21: ireturn
      22: iconst_1
      23: ireturn
}
