Compiled from "DefaultResultOutputTarget.java"
public class org.xwiki.filter.xml.output.DefaultResultOutputTarget implements org.xwiki.filter.xml.output.ResultOutputTarget {
  private javax.xml.transform.Result result;

  public org.xwiki.filter.xml.output.DefaultResultOutputTarget(javax.xml.transform.Result);
    Code:
       0: aload_0
       1: invokespecial #1                  // Method java/lang/Object."<init>":()V
       4: aload_0
       5: aload_1
       6: putfield      #2                  // Field result:Ljavax/xml/transform/Result;
       9: return

  public boolean restartSupported();
    Code:
       0: iconst_0
       1: ireturn

  public javax.xml.transform.Result getResult();
    Code:
       0: aload_0
       1: getfield      #2                  // Field result:Ljavax/xml/transform/Result;
       4: areturn

  public void close() throws java.io.IOException;
    Code:
       0: return
}
