Compiled from "NamingStrategy.java"
public class net.bytebuddy.NamingStrategy$SuffixingRandom extends net.bytebuddy.NamingStrategy$AbstractBase {
  public static final java.lang.String BYTE_BUDDY_RENAME_PACKAGE;

  public static final java.lang.String NO_PREFIX;

  private static final java.lang.String JAVA_PACKAGE;

  private final java.lang.String suffix;

  private final java.lang.String javaLangPackagePrefix;

  private final net.bytebuddy.utility.RandomString randomString;

  private final net.bytebuddy.NamingStrategy$SuffixingRandom$BaseNameResolver baseNameResolver;

  public net.bytebuddy.NamingStrategy$SuffixingRandom(java.lang.String);
    Code:
       0: aload_0
       1: aload_1
       2: getstatic     #37                 // Field net/bytebuddy/NamingStrategy$SuffixingRandom$BaseNameResolver$ForUnnamedType.INSTANCE:Lnet/bytebuddy/NamingStrategy$SuffixingRandom$BaseNameResolver$ForUnnamedType;
       5: invokespecial #40                 // Method "<init>":(Ljava/lang/String;Lnet/bytebuddy/NamingStrategy$SuffixingRandom$BaseNameResolver;)V
       8: return

  public net.bytebuddy.NamingStrategy$SuffixingRandom(java.lang.String, java.lang.String);
    Code:
       0: aload_0
       1: aload_1
       2: getstatic     #37                 // Field net/bytebuddy/NamingStrategy$SuffixingRandom$BaseNameResolver$ForUnnamedType.INSTANCE:Lnet/bytebuddy/NamingStrategy$SuffixingRandom$BaseNameResolver$ForUnnamedType;
       5: aload_2
       6: invokespecial #46                 // Method "<init>":(Ljava/lang/String;Lnet/bytebuddy/NamingStrategy$SuffixingRandom$BaseNameResolver;Ljava/lang/String;)V
       9: return

  public net.bytebuddy.NamingStrategy$SuffixingRandom(java.lang.String, net.bytebuddy.NamingStrategy$SuffixingRandom$BaseNameResolver);
    Code:
       0: aload_0
       1: aload_1
       2: aload_2
       3: ldc           #19                 // String net.bytebuddy.renamed
       5: invokespecial #46                 // Method "<init>":(Ljava/lang/String;Lnet/bytebuddy/NamingStrategy$SuffixingRandom$BaseNameResolver;Ljava/lang/String;)V
       8: return

  public net.bytebuddy.NamingStrategy$SuffixingRandom(java.lang.String, net.bytebuddy.NamingStrategy$SuffixingRandom$BaseNameResolver, java.lang.String);
    Code:
       0: aload_0
       1: invokespecial #49                 // Method net/bytebuddy/NamingStrategy$AbstractBase."<init>":()V
       4: aload_0
       5: aload_1
       6: putfield      #51                 // Field suffix:Ljava/lang/String;
       9: aload_0
      10: aload_2
      11: putfield      #53                 // Field baseNameResolver:Lnet/bytebuddy/NamingStrategy$SuffixingRandom$BaseNameResolver;
      14: aload_0
      15: aload_3
      16: putfield      #55                 // Field javaLangPackagePrefix:Ljava/lang/String;
      19: aload_0
      20: new           #57                 // class net/bytebuddy/utility/RandomString
      23: dup
      24: invokespecial #58                 // Method net/bytebuddy/utility/RandomString."<init>":()V
      27: putfield      #60                 // Field randomString:Lnet/bytebuddy/utility/RandomString;
      30: return

  protected java.lang.String name(net.bytebuddy.description.type.TypeDescription);
    Code:
       0: aload_0
       1: getfield      #53                 // Field baseNameResolver:Lnet/bytebuddy/NamingStrategy$SuffixingRandom$BaseNameResolver;
       4: aload_1
       5: invokeinterface #65,  2           // InterfaceMethod net/bytebuddy/NamingStrategy$SuffixingRandom$BaseNameResolver.resolve:(Lnet/bytebuddy/description/type/TypeDescription;)Ljava/lang/String;
      10: astore_2
      11: aload_2
      12: ldc           #25                 // String java.
      14: invokevirtual #71                 // Method java/lang/String.startsWith:(Ljava/lang/String;)Z
      17: ifeq          59
      20: aload_0
      21: getfield      #55                 // Field javaLangPackagePrefix:Ljava/lang/String;
      24: ldc           #22                 // String
      26: invokevirtual #75                 // Method java/lang/String.equals:(Ljava/lang/Object;)Z
      29: ifne          59
      32: new           #77                 // class java/lang/StringBuilder
      35: dup
      36: invokespecial #78                 // Method java/lang/StringBuilder."<init>":()V
      39: aload_0
      40: getfield      #55                 // Field javaLangPackagePrefix:Ljava/lang/String;
      43: invokevirtual #82                 // Method java/lang/StringBuilder.append:(Ljava/lang/String;)Ljava/lang/StringBuilder;
      46: ldc           #84                 // String .
      48: invokevirtual #82                 // Method java/lang/StringBuilder.append:(Ljava/lang/String;)Ljava/lang/StringBuilder;
      51: aload_2
      52: invokevirtual #82                 // Method java/lang/StringBuilder.append:(Ljava/lang/String;)Ljava/lang/StringBuilder;
      55: invokevirtual #88                 // Method java/lang/StringBuilder.toString:()Ljava/lang/String;
      58: astore_2
      59: ldc           #90                 // String %s$%s$%s
      61: iconst_3
      62: anewarray     #92                 // class java/lang/Object
      65: dup
      66: iconst_0
      67: aload_2
      68: aastore
      69: dup
      70: iconst_1
      71: aload_0
      72: getfield      #51                 // Field suffix:Ljava/lang/String;
      75: aastore
      76: dup
      77: iconst_2
      78: aload_0
      79: getfield      #60                 // Field randomString:Lnet/bytebuddy/utility/RandomString;
      82: invokevirtual #95                 // Method net/bytebuddy/utility/RandomString.nextString:()Ljava/lang/String;
      85: aastore
      86: invokestatic  #99                 // Method java/lang/String.format:(Ljava/lang/String;[Ljava/lang/Object;)Ljava/lang/String;
      89: areturn

  public boolean equals(java.lang.Object);
    Code:
       0: aload_1
       1: aload_0
       2: if_acmpne     7
       5: iconst_1
       6: ireturn
       7: aload_1
       8: instanceof    #2                  // class net/bytebuddy/NamingStrategy$SuffixingRandom
      11: ifne          16
      14: iconst_0
      15: ireturn
      16: aload_1
      17: checkcast     #2                  // class net/bytebuddy/NamingStrategy$SuffixingRandom
      20: astore_2
      21: aload_2
      22: aload_0
      23: invokevirtual #105                // Method canEqual:(Ljava/lang/Object;)Z
      26: ifne          31
      29: iconst_0
      30: ireturn
      31: aload_0
      32: getfield      #51                 // Field suffix:Ljava/lang/String;
      35: astore_3
      36: aload_2
      37: getfield      #51                 // Field suffix:Ljava/lang/String;
      40: astore        4
      42: aload_3
      43: ifnonnull     54
      46: aload         4
      48: ifnull        65
      51: goto          63
      54: aload_3
      55: aload         4
      57: invokevirtual #106                // Method java/lang/Object.equals:(Ljava/lang/Object;)Z
      60: ifne          65
      63: iconst_0
      64: ireturn
      65: aload_0
      66: getfield      #55                 // Field javaLangPackagePrefix:Ljava/lang/String;
      69: astore        5
      71: aload_2
      72: getfield      #55                 // Field javaLangPackagePrefix:Ljava/lang/String;
      75: astore        6
      77: aload         5
      79: ifnonnull     90
      82: aload         6
      84: ifnull        102
      87: goto          100
      90: aload         5
      92: aload         6
      94: invokevirtual #106                // Method java/lang/Object.equals:(Ljava/lang/Object;)Z
      97: ifne          102
     100: iconst_0
     101: ireturn
     102: aload_0
     103: getfield      #53                 // Field baseNameResolver:Lnet/bytebuddy/NamingStrategy$SuffixingRandom$BaseNameResolver;
     106: astore        7
     108: aload_2
     109: getfield      #53                 // Field baseNameResolver:Lnet/bytebuddy/NamingStrategy$SuffixingRandom$BaseNameResolver;
     112: astore        8
     114: aload         7
     116: ifnonnull     127
     119: aload         8
     121: ifnull        139
     124: goto          137
     127: aload         7
     129: aload         8
     131: invokevirtual #106                // Method java/lang/Object.equals:(Ljava/lang/Object;)Z
     134: ifne          139
     137: iconst_0
     138: ireturn
     139: iconst_1
     140: ireturn

  protected boolean canEqual(java.lang.Object);
    Code:
       0: aload_1
       1: instanceof    #2                  // class net/bytebuddy/NamingStrategy$SuffixingRandom
       4: ireturn

  public int hashCode();
    Code:
       0: bipush        59
       2: istore_1
       3: iconst_1
       4: istore_2
       5: aload_0
       6: getfield      #51                 // Field suffix:Ljava/lang/String;
       9: astore_3
      10: iload_2
      11: bipush        59
      13: imul
      14: aload_3
      15: ifnonnull     23
      18: bipush        43
      20: goto          27
      23: aload_3
      24: invokevirtual #119                // Method java/lang/Object.hashCode:()I
      27: iadd
      28: istore_2
      29: aload_0
      30: getfield      #55                 // Field javaLangPackagePrefix:Ljava/lang/String;
      33: astore        4
      35: iload_2
      36: bipush        59
      38: imul
      39: aload         4
      41: ifnonnull     49
      44: bipush        43
      46: goto          54
      49: aload         4
      51: invokevirtual #119                // Method java/lang/Object.hashCode:()I
      54: iadd
      55: istore_2
      56: aload_0
      57: getfield      #53                 // Field baseNameResolver:Lnet/bytebuddy/NamingStrategy$SuffixingRandom$BaseNameResolver;
      60: astore        5
      62: iload_2
      63: bipush        59
      65: imul
      66: aload         5
      68: ifnonnull     76
      71: bipush        43
      73: goto          81
      76: aload         5
      78: invokevirtual #119                // Method java/lang/Object.hashCode:()I
      81: iadd
      82: istore_2
      83: iload_2
      84: ireturn
}
