Compiled from "Pair.java"
public class net.shibboleth.utilities.java.support.collection.Pair<T1, T2> {
  private T1 first;

  private T2 second;

  public net.shibboleth.utilities.java.support.collection.Pair();
    Code:
       0: aload_0
       1: invokespecial #1                  // Method java/lang/Object."<init>":()V
       4: return

  public net.shibboleth.utilities.java.support.collection.Pair(T1, T2);
    Code:
       0: aload_0
       1: invokespecial #1                  // Method java/lang/Object."<init>":()V
       4: aload_0
       5: aload_1
       6: putfield      #2                  // Field first:Ljava/lang/Object;
       9: aload_0
      10: aload_2
      11: putfield      #3                  // Field second:Ljava/lang/Object;
      14: return

  public net.shibboleth.utilities.java.support.collection.Pair(net.shibboleth.utilities.java.support.collection.Pair<? extends T1, ? extends T2>);
    Code:
       0: aload_0
       1: invokespecial #1                  // Method java/lang/Object."<init>":()V
       4: aload_1
       5: ldc           #4                  // String Pair to be copied can not be null
       7: invokestatic  #5                  // Method net/shibboleth/utilities/java/support/logic/Constraint.isNotNull:(Ljava/lang/Object;Ljava/lang/String;)Ljava/lang/Object;
      10: pop
      11: aload_0
      12: aload_1
      13: invokevirtual #6                  // Method getFirst:()Ljava/lang/Object;
      16: putfield      #2                  // Field first:Ljava/lang/Object;
      19: aload_0
      20: aload_1
      21: invokevirtual #7                  // Method getSecond:()Ljava/lang/Object;
      24: putfield      #3                  // Field second:Ljava/lang/Object;
      27: return

  public T1 getFirst();
    Code:
       0: aload_0
       1: getfield      #2                  // Field first:Ljava/lang/Object;
       4: areturn

  public void setFirst(T1);
    Code:
       0: aload_0
       1: aload_1
       2: putfield      #2                  // Field first:Ljava/lang/Object;
       5: return

  public T2 getSecond();
    Code:
       0: aload_0
       1: getfield      #3                  // Field second:Ljava/lang/Object;
       4: areturn

  public void setSecond(T2);
    Code:
       0: aload_0
       1: aload_1
       2: putfield      #3                  // Field second:Ljava/lang/Object;
       5: return

  public boolean equals(java.lang.Object);
    Code:
       0: aload_1
       1: aload_0
       2: if_acmpne     7
       5: iconst_1
       6: ireturn
       7: aload_1
       8: instanceof    #8                  // class net/shibboleth/utilities/java/support/collection/Pair
      11: ifeq          53
      14: aload_1
      15: checkcast     #8                  // class net/shibboleth/utilities/java/support/collection/Pair
      18: astore_2
      19: aload_0
      20: invokevirtual #6                  // Method getFirst:()Ljava/lang/Object;
      23: aload_2
      24: invokevirtual #6                  // Method getFirst:()Ljava/lang/Object;
      27: invokestatic  #9                  // Method java/util/Objects.equals:(Ljava/lang/Object;Ljava/lang/Object;)Z
      30: ifeq          51
      33: aload_0
      34: invokevirtual #7                  // Method getSecond:()Ljava/lang/Object;
      37: aload_2
      38: invokevirtual #7                  // Method getSecond:()Ljava/lang/Object;
      41: invokestatic  #9                  // Method java/util/Objects.equals:(Ljava/lang/Object;Ljava/lang/Object;)Z
      44: ifeq          51
      47: iconst_1
      48: goto          52
      51: iconst_0
      52: ireturn
      53: iconst_0
      54: ireturn

  public int hashCode();
    Code:
       0: iconst_2
       1: anewarray     #10                 // class java/lang/Object
       4: dup
       5: iconst_0
       6: aload_0
       7: getfield      #2                  // Field first:Ljava/lang/Object;
      10: aastore
      11: dup
      12: iconst_1
      13: aload_0
      14: getfield      #3                  // Field second:Ljava/lang/Object;
      17: aastore
      18: invokestatic  #11                 // Method com/google/common/base/Objects.hashCode:([Ljava/lang/Object;)I
      21: ireturn

  public java.lang.String toString();
    Code:
       0: aload_0
       1: invokestatic  #12                 // Method com/google/common/base/MoreObjects.toStringHelper:(Ljava/lang/Object;)Lcom/google/common/base/MoreObjects$ToStringHelper;
       4: ldc           #13                 // String first
       6: aload_0
       7: getfield      #2                  // Field first:Ljava/lang/Object;
      10: invokevirtual #14                 // Method com/google/common/base/MoreObjects$ToStringHelper.add:(Ljava/lang/String;Ljava/lang/Object;)Lcom/google/common/base/MoreObjects$ToStringHelper;
      13: ldc           #15                 // String second
      15: aload_0
      16: getfield      #3                  // Field second:Ljava/lang/Object;
      19: invokevirtual #14                 // Method com/google/common/base/MoreObjects$ToStringHelper.add:(Ljava/lang/String;Ljava/lang/Object;)Lcom/google/common/base/MoreObjects$ToStringHelper;
      22: invokevirtual #16                 // Method com/google/common/base/MoreObjects$ToStringHelper.toString:()Ljava/lang/String;
      25: areturn
}
