Compiled from "SQLParser.scala"
public final class wvlet.airframe.sql.parser.SQLParser$$anon$1 extends org.antlr.v4.runtime.BaseErrorListener {
  public wvlet.airframe.sql.parser.SQLParser$$anon$1();
    Code:
       0: aload_0
       1: invokespecial #27                 // Method org/antlr/v4/runtime/BaseErrorListener."<init>":()V
       4: return

  public void syntaxError(org.antlr.v4.runtime.Recognizer, java.lang.Object, int, int, java.lang.String, org.antlr.v4.runtime.RecognitionException);
    Code:
       0: getstatic     #41                 // Field wvlet/airframe/sql/SQLErrorCode$SyntaxError$.MODULE$:Lwvlet/airframe/sql/SQLErrorCode$SyntaxError$;
       3: getstatic     #46                 // Field scala/Predef$.MODULE$:Lscala/Predef$;
       6: invokevirtual #50                 // Method scala/Predef$.Map:()Lscala/collection/immutable/Map$;
       9: getstatic     #55                 // Field scala/runtime/ScalaRunTime$.MODULE$:Lscala/runtime/ScalaRunTime$;
      12: iconst_2
      13: anewarray     #57                 // class scala/Tuple2
      16: dup
      17: iconst_0
      18: getstatic     #46                 // Field scala/Predef$.MODULE$:Lscala/Predef$;
      21: ldc           #58                 // String line
      23: invokevirtual #62                 // Method scala/Predef$.ArrowAssoc:(Ljava/lang/Object;)Ljava/lang/Object;
      26: checkcast     #64                 // class java/lang/String
      29: astore        7
      31: getstatic     #67                 // Field scala/Predef$ArrowAssoc$.MODULE$:Lscala/Predef$ArrowAssoc$;
      34: aload         7
      36: iload_3
      37: invokestatic  #73                 // Method scala/runtime/BoxesRunTime.boxToInteger:(I)Ljava/lang/Integer;
      40: invokevirtual #77                 // Method scala/Predef$ArrowAssoc$.$minus$greater$extension:(Ljava/lang/Object;Ljava/lang/Object;)Lscala/Tuple2;
      43: aastore
      44: dup
      45: iconst_1
      46: getstatic     #46                 // Field scala/Predef$.MODULE$:Lscala/Predef$;
      49: ldc           #79                 // String pos
      51: invokevirtual #62                 // Method scala/Predef$.ArrowAssoc:(Ljava/lang/Object;)Ljava/lang/Object;
      54: checkcast     #64                 // class java/lang/String
      57: astore        8
      59: getstatic     #67                 // Field scala/Predef$ArrowAssoc$.MODULE$:Lscala/Predef$ArrowAssoc$;
      62: aload         8
      64: iload         4
      66: invokestatic  #73                 // Method scala/runtime/BoxesRunTime.boxToInteger:(I)Ljava/lang/Integer;
      69: invokevirtual #77                 // Method scala/Predef$ArrowAssoc$.$minus$greater$extension:(Ljava/lang/Object;Ljava/lang/Object;)Lscala/Tuple2;
      72: aastore
      73: invokevirtual #83                 // Method scala/runtime/ScalaRunTime$.wrapRefArray:([Ljava/lang/Object;)Lscala/collection/immutable/ArraySeq;
      76: invokevirtual #89                 // Method scala/collection/immutable/Map$.apply:(Lscala/collection/immutable/Seq;)Ljava/lang/Object;
      79: checkcast     #91                 // class scala/collection/immutable/Map
      82: invokevirtual #95                 // Method wvlet/airframe/sql/SQLErrorCode$SyntaxError$.withMetadata:(Lscala/collection/immutable/Map;)Lwvlet/airframe/sql/SQLErrorCode$SQLErrorBuilder;
      85: new           #97                 // class java/lang/StringBuilder
      88: dup
      89: ldc           #98                 // int 28
      91: invokespecial #101                // Method java/lang/StringBuilder."<init>":(I)V
      94: ldc           #103                // String Parse error at line:
      96: invokevirtual #107                // Method java/lang/StringBuilder.append:(Ljava/lang/String;)Ljava/lang/StringBuilder;
      99: iload_3
     100: invokevirtual #110                // Method java/lang/StringBuilder.append:(I)Ljava/lang/StringBuilder;
     103: ldc           #112                // String , pos:
     105: invokevirtual #107                // Method java/lang/StringBuilder.append:(Ljava/lang/String;)Ljava/lang/StringBuilder;
     108: iload         4
     110: invokevirtual #110                // Method java/lang/StringBuilder.append:(I)Ljava/lang/StringBuilder;
     113: ldc           #114                // String .
     115: invokevirtual #107                // Method java/lang/StringBuilder.append:(Ljava/lang/String;)Ljava/lang/StringBuilder;
     118: aload         5
     120: invokevirtual #107                // Method java/lang/StringBuilder.append:(Ljava/lang/String;)Ljava/lang/StringBuilder;
     123: invokevirtual #118                // Method java/lang/StringBuilder.toString:()Ljava/lang/String;
     126: aload         6
     128: invokevirtual #122                // Method wvlet/airframe/sql/SQLErrorCode$SQLErrorBuilder.newException:(Ljava/lang/String;Ljava/lang/Throwable;)Lwvlet/airframe/sql/SQLError;
     131: athrow
}
