public class org.bouncycastle.jcajce.BCFKSLoadStoreParameter$Builder {
  private final java.io.OutputStream out;

  private final java.io.InputStream in;

  private final java.security.KeyStore$ProtectionParameter protectionParameter;

  private final java.security.Key sigKey;

  private org.bouncycastle.crypto.util.PBKDFConfig storeConfig;

  private org.bouncycastle.jcajce.BCFKSLoadStoreParameter$EncryptionAlgorithm encAlg;

  private org.bouncycastle.jcajce.BCFKSLoadStoreParameter$MacAlgorithm macAlg;

  private org.bouncycastle.jcajce.BCFKSLoadStoreParameter$SignatureAlgorithm sigAlg;

  private java.security.cert.X509Certificate[] certs;

  private org.bouncycastle.jcajce.BCFKSLoadStoreParameter$CertChainValidator validator;

  public org.bouncycastle.jcajce.BCFKSLoadStoreParameter$Builder();
    Code:
       0: aload_0
       1: aconst_null
       2: checkcast     #54                 // class java/io/OutputStream
       5: aconst_null
       6: checkcast     #59                 // class java/security/KeyStore$ProtectionParameter
       9: invokespecial #157                // Method "<init>":(Ljava/io/OutputStream;Ljava/security/KeyStore$ProtectionParameter;)V
      12: return

  public org.bouncycastle.jcajce.BCFKSLoadStoreParameter$Builder(java.io.OutputStream, char[]);
    Code:
       0: aload_0
       1: aload_1
       2: new           #58                 // class java/security/KeyStore$PasswordProtection
       5: dup
       6: aload_2
       7: invokespecial #149                // Method java/security/KeyStore$PasswordProtection."<init>":([C)V
      10: invokespecial #157                // Method "<init>":(Ljava/io/OutputStream;Ljava/security/KeyStore$ProtectionParameter;)V
      13: return

  public org.bouncycastle.jcajce.BCFKSLoadStoreParameter$Builder(java.io.OutputStream, java.security.KeyStore$ProtectionParameter);
    Code:
       0: aload_0
       1: invokespecial #147                // Method java/lang/Object."<init>":()V
       4: aload_0
       5: new           #62                 // class org/bouncycastle/crypto/util/PBKDF2Config$Builder
       8: dup
       9: invokespecial #150                // Method org/bouncycastle/crypto/util/PBKDF2Config$Builder."<init>":()V
      12: sipush        16384
      15: invokevirtual #152                // Method org/bouncycastle/crypto/util/PBKDF2Config$Builder.withIterationCount:(I)Lorg/bouncycastle/crypto/util/PBKDF2Config$Builder;
      18: bipush        64
      20: invokevirtual #153                // Method org/bouncycastle/crypto/util/PBKDF2Config$Builder.withSaltLength:(I)Lorg/bouncycastle/crypto/util/PBKDF2Config$Builder;
      23: getstatic     #133                // Field org/bouncycastle/crypto/util/PBKDF2Config.PRF_SHA512:Lorg/bouncycastle/asn1/x509/AlgorithmIdentifier;
      26: invokevirtual #154                // Method org/bouncycastle/crypto/util/PBKDF2Config$Builder.withPRF:(Lorg/bouncycastle/asn1/x509/AlgorithmIdentifier;)Lorg/bouncycastle/crypto/util/PBKDF2Config$Builder;
      29: invokevirtual #151                // Method org/bouncycastle/crypto/util/PBKDF2Config$Builder.build:()Lorg/bouncycastle/crypto/util/PBKDF2Config;
      32: putfield      #139                // Field storeConfig:Lorg/bouncycastle/crypto/util/PBKDFConfig;
      35: aload_0
      36: getstatic     #144                // Field org/bouncycastle/jcajce/BCFKSLoadStoreParameter$EncryptionAlgorithm.AES256_CCM:Lorg/bouncycastle/jcajce/BCFKSLoadStoreParameter$EncryptionAlgorithm;
      39: putfield      #141                // Field encAlg:Lorg/bouncycastle/jcajce/BCFKSLoadStoreParameter$EncryptionAlgorithm;
      42: aload_0
      43: getstatic     #145                // Field org/bouncycastle/jcajce/BCFKSLoadStoreParameter$MacAlgorithm.HmacSHA512:Lorg/bouncycastle/jcajce/BCFKSLoadStoreParameter$MacAlgorithm;
      46: putfield      #142                // Field macAlg:Lorg/bouncycastle/jcajce/BCFKSLoadStoreParameter$MacAlgorithm;
      49: aload_0
      50: getstatic     #146                // Field org/bouncycastle/jcajce/BCFKSLoadStoreParameter$SignatureAlgorithm.SHA512withECDSA:Lorg/bouncycastle/jcajce/BCFKSLoadStoreParameter$SignatureAlgorithm;
      53: putfield      #143                // Field sigAlg:Lorg/bouncycastle/jcajce/BCFKSLoadStoreParameter$SignatureAlgorithm;
      56: aload_0
      57: aconst_null
      58: putfield      #138                // Field certs:[Ljava/security/cert/X509Certificate;
      61: aload_0
      62: aconst_null
      63: putfield      #134                // Field in:Ljava/io/InputStream;
      66: aload_0
      67: aload_1
      68: putfield      #135                // Field out:Ljava/io/OutputStream;
      71: aload_0
      72: aload_2
      73: putfield      #137                // Field protectionParameter:Ljava/security/KeyStore$ProtectionParameter;
      76: aload_0
      77: aconst_null
      78: putfield      #136                // Field sigKey:Ljava/security/Key;
      81: return

  public org.bouncycastle.jcajce.BCFKSLoadStoreParameter$Builder(java.io.OutputStream, java.security.PrivateKey);
    Code:
       0: aload_0
       1: invokespecial #147                // Method java/lang/Object."<init>":()V
       4: aload_0
       5: new           #62                 // class org/bouncycastle/crypto/util/PBKDF2Config$Builder
       8: dup
       9: invokespecial #150                // Method org/bouncycastle/crypto/util/PBKDF2Config$Builder."<init>":()V
      12: sipush        16384
      15: invokevirtual #152                // Method org/bouncycastle/crypto/util/PBKDF2Config$Builder.withIterationCount:(I)Lorg/bouncycastle/crypto/util/PBKDF2Config$Builder;
      18: bipush        64
      20: invokevirtual #153                // Method org/bouncycastle/crypto/util/PBKDF2Config$Builder.withSaltLength:(I)Lorg/bouncycastle/crypto/util/PBKDF2Config$Builder;
      23: getstatic     #133                // Field org/bouncycastle/crypto/util/PBKDF2Config.PRF_SHA512:Lorg/bouncycastle/asn1/x509/AlgorithmIdentifier;
      26: invokevirtual #154                // Method org/bouncycastle/crypto/util/PBKDF2Config$Builder.withPRF:(Lorg/bouncycastle/asn1/x509/AlgorithmIdentifier;)Lorg/bouncycastle/crypto/util/PBKDF2Config$Builder;
      29: invokevirtual #151                // Method org/bouncycastle/crypto/util/PBKDF2Config$Builder.build:()Lorg/bouncycastle/crypto/util/PBKDF2Config;
      32: putfield      #139                // Field storeConfig:Lorg/bouncycastle/crypto/util/PBKDFConfig;
      35: aload_0
      36: getstatic     #144                // Field org/bouncycastle/jcajce/BCFKSLoadStoreParameter$EncryptionAlgorithm.AES256_CCM:Lorg/bouncycastle/jcajce/BCFKSLoadStoreParameter$EncryptionAlgorithm;
      39: putfield      #141                // Field encAlg:Lorg/bouncycastle/jcajce/BCFKSLoadStoreParameter$EncryptionAlgorithm;
      42: aload_0
      43: getstatic     #145                // Field org/bouncycastle/jcajce/BCFKSLoadStoreParameter$MacAlgorithm.HmacSHA512:Lorg/bouncycastle/jcajce/BCFKSLoadStoreParameter$MacAlgorithm;
      46: putfield      #142                // Field macAlg:Lorg/bouncycastle/jcajce/BCFKSLoadStoreParameter$MacAlgorithm;
      49: aload_0
      50: getstatic     #146                // Field org/bouncycastle/jcajce/BCFKSLoadStoreParameter$SignatureAlgorithm.SHA512withECDSA:Lorg/bouncycastle/jcajce/BCFKSLoadStoreParameter$SignatureAlgorithm;
      53: putfield      #143                // Field sigAlg:Lorg/bouncycastle/jcajce/BCFKSLoadStoreParameter$SignatureAlgorithm;
      56: aload_0
      57: aconst_null
      58: putfield      #138                // Field certs:[Ljava/security/cert/X509Certificate;
      61: aload_0
      62: aconst_null
      63: putfield      #134                // Field in:Ljava/io/InputStream;
      66: aload_0
      67: aload_1
      68: putfield      #135                // Field out:Ljava/io/OutputStream;
      71: aload_0
      72: aconst_null
      73: putfield      #137                // Field protectionParameter:Ljava/security/KeyStore$ProtectionParameter;
      76: aload_0
      77: aload_2
      78: putfield      #136                // Field sigKey:Ljava/security/Key;
      81: return

  public org.bouncycastle.jcajce.BCFKSLoadStoreParameter$Builder(java.io.InputStream, java.security.PublicKey);
    Code:
       0: aload_0
       1: invokespecial #147                // Method java/lang/Object."<init>":()V
       4: aload_0
       5: new           #62                 // class org/bouncycastle/crypto/util/PBKDF2Config$Builder
       8: dup
       9: invokespecial #150                // Method org/bouncycastle/crypto/util/PBKDF2Config$Builder."<init>":()V
      12: sipush        16384
      15: invokevirtual #152                // Method org/bouncycastle/crypto/util/PBKDF2Config$Builder.withIterationCount:(I)Lorg/bouncycastle/crypto/util/PBKDF2Config$Builder;
      18: bipush        64
      20: invokevirtual #153                // Method org/bouncycastle/crypto/util/PBKDF2Config$Builder.withSaltLength:(I)Lorg/bouncycastle/crypto/util/PBKDF2Config$Builder;
      23: getstatic     #133                // Field org/bouncycastle/crypto/util/PBKDF2Config.PRF_SHA512:Lorg/bouncycastle/asn1/x509/AlgorithmIdentifier;
      26: invokevirtual #154                // Method org/bouncycastle/crypto/util/PBKDF2Config$Builder.withPRF:(Lorg/bouncycastle/asn1/x509/AlgorithmIdentifier;)Lorg/bouncycastle/crypto/util/PBKDF2Config$Builder;
      29: invokevirtual #151                // Method org/bouncycastle/crypto/util/PBKDF2Config$Builder.build:()Lorg/bouncycastle/crypto/util/PBKDF2Config;
      32: putfield      #139                // Field storeConfig:Lorg/bouncycastle/crypto/util/PBKDFConfig;
      35: aload_0
      36: getstatic     #144                // Field org/bouncycastle/jcajce/BCFKSLoadStoreParameter$EncryptionAlgorithm.AES256_CCM:Lorg/bouncycastle/jcajce/BCFKSLoadStoreParameter$EncryptionAlgorithm;
      39: putfield      #141                // Field encAlg:Lorg/bouncycastle/jcajce/BCFKSLoadStoreParameter$EncryptionAlgorithm;
      42: aload_0
      43: getstatic     #145                // Field org/bouncycastle/jcajce/BCFKSLoadStoreParameter$MacAlgorithm.HmacSHA512:Lorg/bouncycastle/jcajce/BCFKSLoadStoreParameter$MacAlgorithm;
      46: putfield      #142                // Field macAlg:Lorg/bouncycastle/jcajce/BCFKSLoadStoreParameter$MacAlgorithm;
      49: aload_0
      50: getstatic     #146                // Field org/bouncycastle/jcajce/BCFKSLoadStoreParameter$SignatureAlgorithm.SHA512withECDSA:Lorg/bouncycastle/jcajce/BCFKSLoadStoreParameter$SignatureAlgorithm;
      53: putfield      #143                // Field sigAlg:Lorg/bouncycastle/jcajce/BCFKSLoadStoreParameter$SignatureAlgorithm;
      56: aload_0
      57: aconst_null
      58: putfield      #138                // Field certs:[Ljava/security/cert/X509Certificate;
      61: aload_0
      62: aload_1
      63: putfield      #134                // Field in:Ljava/io/InputStream;
      66: aload_0
      67: aconst_null
      68: putfield      #135                // Field out:Ljava/io/OutputStream;
      71: aload_0
      72: aconst_null
      73: putfield      #137                // Field protectionParameter:Ljava/security/KeyStore$ProtectionParameter;
      76: aload_0
      77: aload_2
      78: putfield      #136                // Field sigKey:Ljava/security/Key;
      81: return

  public org.bouncycastle.jcajce.BCFKSLoadStoreParameter$Builder(java.io.InputStream, org.bouncycastle.jcajce.BCFKSLoadStoreParameter$CertChainValidator);
    Code:
       0: aload_0
       1: invokespecial #147                // Method java/lang/Object."<init>":()V
       4: aload_0
       5: new           #62                 // class org/bouncycastle/crypto/util/PBKDF2Config$Builder
       8: dup
       9: invokespecial #150                // Method org/bouncycastle/crypto/util/PBKDF2Config$Builder."<init>":()V
      12: sipush        16384
      15: invokevirtual #152                // Method org/bouncycastle/crypto/util/PBKDF2Config$Builder.withIterationCount:(I)Lorg/bouncycastle/crypto/util/PBKDF2Config$Builder;
      18: bipush        64
      20: invokevirtual #153                // Method org/bouncycastle/crypto/util/PBKDF2Config$Builder.withSaltLength:(I)Lorg/bouncycastle/crypto/util/PBKDF2Config$Builder;
      23: getstatic     #133                // Field org/bouncycastle/crypto/util/PBKDF2Config.PRF_SHA512:Lorg/bouncycastle/asn1/x509/AlgorithmIdentifier;
      26: invokevirtual #154                // Method org/bouncycastle/crypto/util/PBKDF2Config$Builder.withPRF:(Lorg/bouncycastle/asn1/x509/AlgorithmIdentifier;)Lorg/bouncycastle/crypto/util/PBKDF2Config$Builder;
      29: invokevirtual #151                // Method org/bouncycastle/crypto/util/PBKDF2Config$Builder.build:()Lorg/bouncycastle/crypto/util/PBKDF2Config;
      32: putfield      #139                // Field storeConfig:Lorg/bouncycastle/crypto/util/PBKDFConfig;
      35: aload_0
      36: getstatic     #144                // Field org/bouncycastle/jcajce/BCFKSLoadStoreParameter$EncryptionAlgorithm.AES256_CCM:Lorg/bouncycastle/jcajce/BCFKSLoadStoreParameter$EncryptionAlgorithm;
      39: putfield      #141                // Field encAlg:Lorg/bouncycastle/jcajce/BCFKSLoadStoreParameter$EncryptionAlgorithm;
      42: aload_0
      43: getstatic     #145                // Field org/bouncycastle/jcajce/BCFKSLoadStoreParameter$MacAlgorithm.HmacSHA512:Lorg/bouncycastle/jcajce/BCFKSLoadStoreParameter$MacAlgorithm;
      46: putfield      #142                // Field macAlg:Lorg/bouncycastle/jcajce/BCFKSLoadStoreParameter$MacAlgorithm;
      49: aload_0
      50: getstatic     #146                // Field org/bouncycastle/jcajce/BCFKSLoadStoreParameter$SignatureAlgorithm.SHA512withECDSA:Lorg/bouncycastle/jcajce/BCFKSLoadStoreParameter$SignatureAlgorithm;
      53: putfield      #143                // Field sigAlg:Lorg/bouncycastle/jcajce/BCFKSLoadStoreParameter$SignatureAlgorithm;
      56: aload_0
      57: aconst_null
      58: putfield      #138                // Field certs:[Ljava/security/cert/X509Certificate;
      61: aload_0
      62: aload_1
      63: putfield      #134                // Field in:Ljava/io/InputStream;
      66: aload_0
      67: aconst_null
      68: putfield      #135                // Field out:Ljava/io/OutputStream;
      71: aload_0
      72: aconst_null
      73: putfield      #137                // Field protectionParameter:Ljava/security/KeyStore$ProtectionParameter;
      76: aload_0
      77: aload_2
      78: putfield      #140                // Field validator:Lorg/bouncycastle/jcajce/BCFKSLoadStoreParameter$CertChainValidator;
      81: aload_0
      82: aconst_null
      83: putfield      #136                // Field sigKey:Ljava/security/Key;
      86: return

  public org.bouncycastle.jcajce.BCFKSLoadStoreParameter$Builder(java.io.InputStream, char[]);
    Code:
       0: aload_0
       1: aload_1
       2: new           #58                 // class java/security/KeyStore$PasswordProtection
       5: dup
       6: aload_2
       7: invokespecial #149                // Method java/security/KeyStore$PasswordProtection."<init>":([C)V
      10: invokespecial #156                // Method "<init>":(Ljava/io/InputStream;Ljava/security/KeyStore$ProtectionParameter;)V
      13: return

  public org.bouncycastle.jcajce.BCFKSLoadStoreParameter$Builder(java.io.InputStream, java.security.KeyStore$ProtectionParameter);
    Code:
       0: aload_0
       1: invokespecial #147                // Method java/lang/Object."<init>":()V
       4: aload_0
       5: new           #62                 // class org/bouncycastle/crypto/util/PBKDF2Config$Builder
       8: dup
       9: invokespecial #150                // Method org/bouncycastle/crypto/util/PBKDF2Config$Builder."<init>":()V
      12: sipush        16384
      15: invokevirtual #152                // Method org/bouncycastle/crypto/util/PBKDF2Config$Builder.withIterationCount:(I)Lorg/bouncycastle/crypto/util/PBKDF2Config$Builder;
      18: bipush        64
      20: invokevirtual #153                // Method org/bouncycastle/crypto/util/PBKDF2Config$Builder.withSaltLength:(I)Lorg/bouncycastle/crypto/util/PBKDF2Config$Builder;
      23: getstatic     #133                // Field org/bouncycastle/crypto/util/PBKDF2Config.PRF_SHA512:Lorg/bouncycastle/asn1/x509/AlgorithmIdentifier;
      26: invokevirtual #154                // Method org/bouncycastle/crypto/util/PBKDF2Config$Builder.withPRF:(Lorg/bouncycastle/asn1/x509/AlgorithmIdentifier;)Lorg/bouncycastle/crypto/util/PBKDF2Config$Builder;
      29: invokevirtual #151                // Method org/bouncycastle/crypto/util/PBKDF2Config$Builder.build:()Lorg/bouncycastle/crypto/util/PBKDF2Config;
      32: putfield      #139                // Field storeConfig:Lorg/bouncycastle/crypto/util/PBKDFConfig;
      35: aload_0
      36: getstatic     #144                // Field org/bouncycastle/jcajce/BCFKSLoadStoreParameter$EncryptionAlgorithm.AES256_CCM:Lorg/bouncycastle/jcajce/BCFKSLoadStoreParameter$EncryptionAlgorithm;
      39: putfield      #141                // Field encAlg:Lorg/bouncycastle/jcajce/BCFKSLoadStoreParameter$EncryptionAlgorithm;
      42: aload_0
      43: getstatic     #145                // Field org/bouncycastle/jcajce/BCFKSLoadStoreParameter$MacAlgorithm.HmacSHA512:Lorg/bouncycastle/jcajce/BCFKSLoadStoreParameter$MacAlgorithm;
      46: putfield      #142                // Field macAlg:Lorg/bouncycastle/jcajce/BCFKSLoadStoreParameter$MacAlgorithm;
      49: aload_0
      50: getstatic     #146                // Field org/bouncycastle/jcajce/BCFKSLoadStoreParameter$SignatureAlgorithm.SHA512withECDSA:Lorg/bouncycastle/jcajce/BCFKSLoadStoreParameter$SignatureAlgorithm;
      53: putfield      #143                // Field sigAlg:Lorg/bouncycastle/jcajce/BCFKSLoadStoreParameter$SignatureAlgorithm;
      56: aload_0
      57: aconst_null
      58: putfield      #138                // Field certs:[Ljava/security/cert/X509Certificate;
      61: aload_0
      62: aload_1
      63: putfield      #134                // Field in:Ljava/io/InputStream;
      66: aload_0
      67: aconst_null
      68: putfield      #135                // Field out:Ljava/io/OutputStream;
      71: aload_0
      72: aload_2
      73: putfield      #137                // Field protectionParameter:Ljava/security/KeyStore$ProtectionParameter;
      76: aload_0
      77: aconst_null
      78: putfield      #136                // Field sigKey:Ljava/security/Key;
      81: return

  public org.bouncycastle.jcajce.BCFKSLoadStoreParameter$Builder withStorePBKDFConfig(org.bouncycastle.crypto.util.PBKDFConfig);
    Code:
       0: aload_0
       1: aload_1
       2: putfield      #139                // Field storeConfig:Lorg/bouncycastle/crypto/util/PBKDFConfig;
       5: aload_0
       6: areturn

  public org.bouncycastle.jcajce.BCFKSLoadStoreParameter$Builder withStoreEncryptionAlgorithm(org.bouncycastle.jcajce.BCFKSLoadStoreParameter$EncryptionAlgorithm);
    Code:
       0: aload_0
       1: aload_1
       2: putfield      #141                // Field encAlg:Lorg/bouncycastle/jcajce/BCFKSLoadStoreParameter$EncryptionAlgorithm;
       5: aload_0
       6: areturn

  public org.bouncycastle.jcajce.BCFKSLoadStoreParameter$Builder withStoreMacAlgorithm(org.bouncycastle.jcajce.BCFKSLoadStoreParameter$MacAlgorithm);
    Code:
       0: aload_0
       1: aload_1
       2: putfield      #142                // Field macAlg:Lorg/bouncycastle/jcajce/BCFKSLoadStoreParameter$MacAlgorithm;
       5: aload_0
       6: areturn

  public org.bouncycastle.jcajce.BCFKSLoadStoreParameter$Builder withCertificates(java.security.cert.X509Certificate[]);
    Code:
       0: aload_1
       1: arraylength
       2: anewarray     #60                 // class java/security/cert/X509Certificate
       5: astore_2
       6: aload_1
       7: iconst_0
       8: aload_2
       9: iconst_0
      10: aload_2
      11: arraylength
      12: invokestatic  #148                // Method java/lang/System.arraycopy:(Ljava/lang/Object;ILjava/lang/Object;II)V
      15: aload_0
      16: aload_2
      17: putfield      #138                // Field certs:[Ljava/security/cert/X509Certificate;
      20: aload_0
      21: areturn

  public org.bouncycastle.jcajce.BCFKSLoadStoreParameter$Builder withStoreSignatureAlgorithm(org.bouncycastle.jcajce.BCFKSLoadStoreParameter$SignatureAlgorithm);
    Code:
       0: aload_0
       1: aload_1
       2: putfield      #143                // Field sigAlg:Lorg/bouncycastle/jcajce/BCFKSLoadStoreParameter$SignatureAlgorithm;
       5: aload_0
       6: areturn

  public org.bouncycastle.jcajce.BCFKSLoadStoreParameter build();
    Code:
       0: new           #63                 // class org/bouncycastle/jcajce/BCFKSLoadStoreParameter
       3: dup
       4: aload_0
       5: aconst_null
       6: invokespecial #155                // Method org/bouncycastle/jcajce/BCFKSLoadStoreParameter."<init>":(Lorg/bouncycastle/jcajce/BCFKSLoadStoreParameter$Builder;Lorg/bouncycastle/jcajce/BCFKSLoadStoreParameter$1;)V
       9: areturn

  static java.io.InputStream access$100(org.bouncycastle.jcajce.BCFKSLoadStoreParameter$Builder);
    Code:
       0: aload_0
       1: getfield      #134                // Field in:Ljava/io/InputStream;
       4: areturn

  static java.io.OutputStream access$200(org.bouncycastle.jcajce.BCFKSLoadStoreParameter$Builder);
    Code:
       0: aload_0
       1: getfield      #135                // Field out:Ljava/io/OutputStream;
       4: areturn

  static java.security.KeyStore$ProtectionParameter access$300(org.bouncycastle.jcajce.BCFKSLoadStoreParameter$Builder);
    Code:
       0: aload_0
       1: getfield      #137                // Field protectionParameter:Ljava/security/KeyStore$ProtectionParameter;
       4: areturn

  static org.bouncycastle.crypto.util.PBKDFConfig access$400(org.bouncycastle.jcajce.BCFKSLoadStoreParameter$Builder);
    Code:
       0: aload_0
       1: getfield      #139                // Field storeConfig:Lorg/bouncycastle/crypto/util/PBKDFConfig;
       4: areturn

  static org.bouncycastle.jcajce.BCFKSLoadStoreParameter$EncryptionAlgorithm access$500(org.bouncycastle.jcajce.BCFKSLoadStoreParameter$Builder);
    Code:
       0: aload_0
       1: getfield      #141                // Field encAlg:Lorg/bouncycastle/jcajce/BCFKSLoadStoreParameter$EncryptionAlgorithm;
       4: areturn

  static org.bouncycastle.jcajce.BCFKSLoadStoreParameter$MacAlgorithm access$600(org.bouncycastle.jcajce.BCFKSLoadStoreParameter$Builder);
    Code:
       0: aload_0
       1: getfield      #142                // Field macAlg:Lorg/bouncycastle/jcajce/BCFKSLoadStoreParameter$MacAlgorithm;
       4: areturn

  static org.bouncycastle.jcajce.BCFKSLoadStoreParameter$SignatureAlgorithm access$700(org.bouncycastle.jcajce.BCFKSLoadStoreParameter$Builder);
    Code:
       0: aload_0
       1: getfield      #143                // Field sigAlg:Lorg/bouncycastle/jcajce/BCFKSLoadStoreParameter$SignatureAlgorithm;
       4: areturn

  static java.security.Key access$800(org.bouncycastle.jcajce.BCFKSLoadStoreParameter$Builder);
    Code:
       0: aload_0
       1: getfield      #136                // Field sigKey:Ljava/security/Key;
       4: areturn

  static java.security.cert.X509Certificate[] access$900(org.bouncycastle.jcajce.BCFKSLoadStoreParameter$Builder);
    Code:
       0: aload_0
       1: getfield      #138                // Field certs:[Ljava/security/cert/X509Certificate;
       4: areturn

  static org.bouncycastle.jcajce.BCFKSLoadStoreParameter$CertChainValidator access$1000(org.bouncycastle.jcajce.BCFKSLoadStoreParameter$Builder);
    Code:
       0: aload_0
       1: getfield      #140                // Field validator:Lorg/bouncycastle/jcajce/BCFKSLoadStoreParameter$CertChainValidator;
       4: areturn
}
