Compiled from "SchemaGenAction.java"
public final class org.hibernate.jpa.SchemaGenAction extends java.lang.Enum<org.hibernate.jpa.SchemaGenAction> {
  public static final org.hibernate.jpa.SchemaGenAction NONE;

  public static final org.hibernate.jpa.SchemaGenAction CREATE;

  public static final org.hibernate.jpa.SchemaGenAction DROP;

  public static final org.hibernate.jpa.SchemaGenAction BOTH;

  private final java.lang.String externalName;

  private static final org.hibernate.jpa.SchemaGenAction[] $VALUES;

  public static org.hibernate.jpa.SchemaGenAction[] values();
    Code:
       0: getstatic     #1                  // Field $VALUES:[Lorg/hibernate/jpa/SchemaGenAction;
       3: invokevirtual #2                  // Method "[Lorg/hibernate/jpa/SchemaGenAction;".clone:()Ljava/lang/Object;
       6: checkcast     #3                  // class "[Lorg/hibernate/jpa/SchemaGenAction;"
       9: areturn

  public static org.hibernate.jpa.SchemaGenAction valueOf(java.lang.String);
    Code:
       0: ldc           #4                  // class org/hibernate/jpa/SchemaGenAction
       2: aload_0
       3: invokestatic  #5                  // Method java/lang/Enum.valueOf:(Ljava/lang/Class;Ljava/lang/String;)Ljava/lang/Enum;
       6: checkcast     #4                  // class org/hibernate/jpa/SchemaGenAction
       9: areturn

  private org.hibernate.jpa.SchemaGenAction(java.lang.String);
    Code:
       0: aload_0
       1: aload_1
       2: iload_2
       3: invokespecial #6                  // Method java/lang/Enum."<init>":(Ljava/lang/String;I)V
       6: aload_0
       7: aload_3
       8: putfield      #7                  // Field externalName:Ljava/lang/String;
      11: return

  public static org.hibernate.jpa.SchemaGenAction interpret(java.lang.Object);
    Code:
       0: aload_0
       1: ifnonnull     8
       4: getstatic     #8                  // Field NONE:Lorg/hibernate/jpa/SchemaGenAction;
       7: areturn
       8: ldc           #4                  // class org/hibernate/jpa/SchemaGenAction
      10: aload_0
      11: invokevirtual #9                  // Method java/lang/Class.isInstance:(Ljava/lang/Object;)Z
      14: ifeq          22
      17: aload_0
      18: checkcast     #4                  // class org/hibernate/jpa/SchemaGenAction
      21: areturn
      22: aload_0
      23: invokevirtual #10                 // Method java/lang/Object.toString:()Ljava/lang/String;
      26: astore_1
      27: aload_1
      28: invokestatic  #11                 // Method org/hibernate/internal/util/StringHelper.isEmpty:(Ljava/lang/String;)Z
      31: ifne          47
      34: getstatic     #8                  // Field NONE:Lorg/hibernate/jpa/SchemaGenAction;
      37: getfield      #7                  // Field externalName:Ljava/lang/String;
      40: aload_1
      41: invokevirtual #12                 // Method java/lang/String.equals:(Ljava/lang/Object;)Z
      44: ifeq          51
      47: getstatic     #8                  // Field NONE:Lorg/hibernate/jpa/SchemaGenAction;
      50: areturn
      51: getstatic     #13                 // Field CREATE:Lorg/hibernate/jpa/SchemaGenAction;
      54: getfield      #7                  // Field externalName:Ljava/lang/String;
      57: aload_1
      58: invokevirtual #12                 // Method java/lang/String.equals:(Ljava/lang/Object;)Z
      61: ifeq          68
      64: getstatic     #13                 // Field CREATE:Lorg/hibernate/jpa/SchemaGenAction;
      67: areturn
      68: getstatic     #14                 // Field DROP:Lorg/hibernate/jpa/SchemaGenAction;
      71: getfield      #7                  // Field externalName:Ljava/lang/String;
      74: aload_1
      75: invokevirtual #12                 // Method java/lang/String.equals:(Ljava/lang/Object;)Z
      78: ifeq          85
      81: getstatic     #14                 // Field DROP:Lorg/hibernate/jpa/SchemaGenAction;
      84: areturn
      85: getstatic     #15                 // Field BOTH:Lorg/hibernate/jpa/SchemaGenAction;
      88: getfield      #7                  // Field externalName:Ljava/lang/String;
      91: aload_1
      92: invokevirtual #12                 // Method java/lang/String.equals:(Ljava/lang/Object;)Z
      95: ifeq          102
      98: getstatic     #15                 // Field BOTH:Lorg/hibernate/jpa/SchemaGenAction;
     101: areturn
     102: new           #16                 // class java/lang/IllegalArgumentException
     105: dup
     106: ldc           #17                 // String Unrecognized \'%s\' or \'%s\' value : %s
     108: iconst_3
     109: anewarray     #18                 // class java/lang/Object
     112: dup
     113: iconst_0
     114: ldc           #20                 // String javax.persistence.schema-generation.database.action
     116: aastore
     117: dup
     118: iconst_1
     119: ldc           #21                 // String javax.persistence.schema-generation.scripts.action
     121: aastore
     122: dup
     123: iconst_2
     124: aload_0
     125: aastore
     126: invokestatic  #22                 // Method java/lang/String.format:(Ljava/lang/String;[Ljava/lang/Object;)Ljava/lang/String;
     129: invokespecial #23                 // Method java/lang/IllegalArgumentException."<init>":(Ljava/lang/String;)V
     132: athrow

  public boolean includesCreate();
    Code:
       0: aload_0
       1: getstatic     #13                 // Field CREATE:Lorg/hibernate/jpa/SchemaGenAction;
       4: if_acmpeq     14
       7: aload_0
       8: getstatic     #15                 // Field BOTH:Lorg/hibernate/jpa/SchemaGenAction;
      11: if_acmpne     18
      14: iconst_1
      15: goto          19
      18: iconst_0
      19: ireturn

  public boolean includesDrop();
    Code:
       0: aload_0
       1: getstatic     #14                 // Field DROP:Lorg/hibernate/jpa/SchemaGenAction;
       4: if_acmpeq     14
       7: aload_0
       8: getstatic     #15                 // Field BOTH:Lorg/hibernate/jpa/SchemaGenAction;
      11: if_acmpne     18
      14: iconst_1
      15: goto          19
      18: iconst_0
      19: ireturn

  public java.lang.String toString();
    Code:
       0: new           #24                 // class java/lang/StringBuilder
       3: dup
       4: invokespecial #25                 // Method java/lang/StringBuilder."<init>":()V
       7: aload_0
       8: invokevirtual #26                 // Method java/lang/Object.getClass:()Ljava/lang/Class;
      11: invokevirtual #27                 // Method java/lang/Class.getSimpleName:()Ljava/lang/String;
      14: invokevirtual #28                 // Method java/lang/StringBuilder.append:(Ljava/lang/String;)Ljava/lang/StringBuilder;
      17: ldc           #29                 // String (
      19: invokevirtual #28                 // Method java/lang/StringBuilder.append:(Ljava/lang/String;)Ljava/lang/StringBuilder;
      22: aload_0
      23: getfield      #7                  // Field externalName:Ljava/lang/String;
      26: invokevirtual #28                 // Method java/lang/StringBuilder.append:(Ljava/lang/String;)Ljava/lang/StringBuilder;
      29: ldc           #30                 // String )
      31: invokevirtual #28                 // Method java/lang/StringBuilder.append:(Ljava/lang/String;)Ljava/lang/StringBuilder;
      34: invokevirtual #31                 // Method java/lang/StringBuilder.toString:()Ljava/lang/String;
      37: areturn

  static {};
    Code:
       0: new           #4                  // class org/hibernate/jpa/SchemaGenAction
       3: dup
       4: ldc           #32                 // String NONE
       6: iconst_0
       7: ldc           #33                 // String none
       9: invokespecial #34                 // Method "<init>":(Ljava/lang/String;ILjava/lang/String;)V
      12: putstatic     #8                  // Field NONE:Lorg/hibernate/jpa/SchemaGenAction;
      15: new           #4                  // class org/hibernate/jpa/SchemaGenAction
      18: dup
      19: ldc           #35                 // String CREATE
      21: iconst_1
      22: ldc           #36                 // String create
      24: invokespecial #34                 // Method "<init>":(Ljava/lang/String;ILjava/lang/String;)V
      27: putstatic     #13                 // Field CREATE:Lorg/hibernate/jpa/SchemaGenAction;
      30: new           #4                  // class org/hibernate/jpa/SchemaGenAction
      33: dup
      34: ldc           #37                 // String DROP
      36: iconst_2
      37: ldc           #38                 // String drop
      39: invokespecial #34                 // Method "<init>":(Ljava/lang/String;ILjava/lang/String;)V
      42: putstatic     #14                 // Field DROP:Lorg/hibernate/jpa/SchemaGenAction;
      45: new           #4                  // class org/hibernate/jpa/SchemaGenAction
      48: dup
      49: ldc           #39                 // String BOTH
      51: iconst_3
      52: ldc           #40                 // String drop-and-create
      54: invokespecial #34                 // Method "<init>":(Ljava/lang/String;ILjava/lang/String;)V
      57: putstatic     #15                 // Field BOTH:Lorg/hibernate/jpa/SchemaGenAction;
      60: iconst_4
      61: anewarray     #4                  // class org/hibernate/jpa/SchemaGenAction
      64: dup
      65: iconst_0
      66: getstatic     #8                  // Field NONE:Lorg/hibernate/jpa/SchemaGenAction;
      69: aastore
      70: dup
      71: iconst_1
      72: getstatic     #13                 // Field CREATE:Lorg/hibernate/jpa/SchemaGenAction;
      75: aastore
      76: dup
      77: iconst_2
      78: getstatic     #14                 // Field DROP:Lorg/hibernate/jpa/SchemaGenAction;
      81: aastore
      82: dup
      83: iconst_3
      84: getstatic     #15                 // Field BOTH:Lorg/hibernate/jpa/SchemaGenAction;
      87: aastore
      88: putstatic     #1                  // Field $VALUES:[Lorg/hibernate/jpa/SchemaGenAction;
      91: return
}
