Compiled from "Glue.scala"
public interface facade.amazonaws.services.glue.GlueTable {
  public static scala.scalajs.js.$bar<java.lang.String, scala.runtime.BoxedUnit> apply$default$4();
    Code:
       0: getstatic     #17                 // Field facade/amazonaws/services/glue/GlueTable$.MODULE$:Lfacade/amazonaws/services/glue/GlueTable$;
       3: invokevirtual #19                 // Method facade/amazonaws/services/glue/GlueTable$.apply$default$4:()Lscala/scalajs/js/$bar;
       6: areturn

  public static scala.scalajs.js.$bar<java.lang.String, scala.runtime.BoxedUnit> apply$default$3();
    Code:
       0: getstatic     #17                 // Field facade/amazonaws/services/glue/GlueTable$.MODULE$:Lfacade/amazonaws/services/glue/GlueTable$;
       3: invokevirtual #22                 // Method facade/amazonaws/services/glue/GlueTable$.apply$default$3:()Lscala/scalajs/js/$bar;
       6: areturn

  public static facade.amazonaws.services.glue.GlueTable apply(java.lang.String, java.lang.String, scala.scalajs.js.$bar<java.lang.String, scala.runtime.BoxedUnit>, scala.scalajs.js.$bar<java.lang.String, scala.runtime.BoxedUnit>);
    Code:
       0: getstatic     #17                 // Field facade/amazonaws/services/glue/GlueTable$.MODULE$:Lfacade/amazonaws/services/glue/GlueTable$;
       3: aload_0
       4: aload_1
       5: aload_2
       6: aload_3
       7: invokevirtual #31                 // Method facade/amazonaws/services/glue/GlueTable$.apply:(Ljava/lang/String;Ljava/lang/String;Lscala/scalajs/js/$bar;Lscala/scalajs/js/$bar;)Lfacade/amazonaws/services/glue/GlueTable;
      10: areturn

  public abstract java.lang.String DatabaseName();

  public abstract void DatabaseName_$eq(java.lang.String);

  public abstract java.lang.String TableName();

  public abstract void TableName_$eq(java.lang.String);

  public abstract scala.scalajs.js.$bar<java.lang.String, scala.runtime.BoxedUnit> CatalogId();

  public abstract void CatalogId_$eq(scala.scalajs.js.$bar<java.lang.String, scala.runtime.BoxedUnit>);

  public abstract scala.scalajs.js.$bar<java.lang.String, scala.runtime.BoxedUnit> ConnectionName();

  public abstract void ConnectionName_$eq(scala.scalajs.js.$bar<java.lang.String, scala.runtime.BoxedUnit>);
}
