Compiled from "Glue.scala"
public final class facade.amazonaws.services.glue.Permission$ extends scala.scalajs.js.Object {
  public static facade.amazonaws.services.glue.Permission$ MODULE$;

  private final facade.amazonaws.services.glue.Permission ALL;

  private final facade.amazonaws.services.glue.Permission SELECT;

  private final facade.amazonaws.services.glue.Permission ALTER;

  private final facade.amazonaws.services.glue.Permission DROP;

  private final facade.amazonaws.services.glue.Permission DELETE;

  private final facade.amazonaws.services.glue.Permission INSERT;

  private final facade.amazonaws.services.glue.Permission CREATE_DATABASE;

  private final facade.amazonaws.services.glue.Permission CREATE_TABLE;

  private final facade.amazonaws.services.glue.Permission DATA_LOCATION_ACCESS;

  private final scala.scalajs.js.Array<facade.amazonaws.services.glue.Permission> values;

  public static {};
    Code:
       0: new           #2                  // class facade/amazonaws/services/glue/Permission$
       3: invokespecial #25                 // Method "<init>":()V
       6: return

  public facade.amazonaws.services.glue.Permission ALL();
    Code:
       0: aload_0
       1: getfield      #28                 // Field ALL:Lfacade/amazonaws/services/glue/Permission;
       4: areturn

  public facade.amazonaws.services.glue.Permission SELECT();
    Code:
       0: aload_0
       1: getfield      #31                 // Field SELECT:Lfacade/amazonaws/services/glue/Permission;
       4: areturn

  public facade.amazonaws.services.glue.Permission ALTER();
    Code:
       0: aload_0
       1: getfield      #33                 // Field ALTER:Lfacade/amazonaws/services/glue/Permission;
       4: areturn

  public facade.amazonaws.services.glue.Permission DROP();
    Code:
       0: aload_0
       1: getfield      #35                 // Field DROP:Lfacade/amazonaws/services/glue/Permission;
       4: areturn

  public facade.amazonaws.services.glue.Permission DELETE();
    Code:
       0: aload_0
       1: getfield      #37                 // Field DELETE:Lfacade/amazonaws/services/glue/Permission;
       4: areturn

  public facade.amazonaws.services.glue.Permission INSERT();
    Code:
       0: aload_0
       1: getfield      #39                 // Field INSERT:Lfacade/amazonaws/services/glue/Permission;
       4: areturn

  public facade.amazonaws.services.glue.Permission CREATE_DATABASE();
    Code:
       0: aload_0
       1: getfield      #41                 // Field CREATE_DATABASE:Lfacade/amazonaws/services/glue/Permission;
       4: areturn

  public facade.amazonaws.services.glue.Permission CREATE_TABLE();
    Code:
       0: aload_0
       1: getfield      #43                 // Field CREATE_TABLE:Lfacade/amazonaws/services/glue/Permission;
       4: areturn

  public facade.amazonaws.services.glue.Permission DATA_LOCATION_ACCESS();
    Code:
       0: aload_0
       1: getfield      #45                 // Field DATA_LOCATION_ACCESS:Lfacade/amazonaws/services/glue/Permission;
       4: areturn

  public scala.scalajs.js.Array<facade.amazonaws.services.glue.Permission> values();
    Code:
       0: aload_0
       1: getfield      #49                 // Field values:Lscala/scalajs/js/Array;
       4: areturn

  private facade.amazonaws.services.glue.Permission$();
    Code:
       0: aload_0
       1: invokespecial #50                 // Method scala/scalajs/js/Object."<init>":()V
       4: aload_0
       5: putstatic     #52                 // Field MODULE$:Lfacade/amazonaws/services/glue/Permission$;
       8: aload_0
       9: ldc           #53                 // String ALL
      11: checkcast     #55                 // class facade/amazonaws/services/glue/Permission
      14: putfield      #28                 // Field ALL:Lfacade/amazonaws/services/glue/Permission;
      17: aload_0
      18: ldc           #56                 // String SELECT
      20: checkcast     #55                 // class facade/amazonaws/services/glue/Permission
      23: putfield      #31                 // Field SELECT:Lfacade/amazonaws/services/glue/Permission;
      26: aload_0
      27: ldc           #57                 // String ALTER
      29: checkcast     #55                 // class facade/amazonaws/services/glue/Permission
      32: putfield      #33                 // Field ALTER:Lfacade/amazonaws/services/glue/Permission;
      35: aload_0
      36: ldc           #58                 // String DROP
      38: checkcast     #55                 // class facade/amazonaws/services/glue/Permission
      41: putfield      #35                 // Field DROP:Lfacade/amazonaws/services/glue/Permission;
      44: aload_0
      45: ldc           #59                 // String DELETE
      47: checkcast     #55                 // class facade/amazonaws/services/glue/Permission
      50: putfield      #37                 // Field DELETE:Lfacade/amazonaws/services/glue/Permission;
      53: aload_0
      54: ldc           #60                 // String INSERT
      56: checkcast     #55                 // class facade/amazonaws/services/glue/Permission
      59: putfield      #39                 // Field INSERT:Lfacade/amazonaws/services/glue/Permission;
      62: aload_0
      63: ldc           #61                 // String CREATE_DATABASE
      65: checkcast     #55                 // class facade/amazonaws/services/glue/Permission
      68: putfield      #41                 // Field CREATE_DATABASE:Lfacade/amazonaws/services/glue/Permission;
      71: aload_0
      72: ldc           #62                 // String CREATE_TABLE
      74: checkcast     #55                 // class facade/amazonaws/services/glue/Permission
      77: putfield      #43                 // Field CREATE_TABLE:Lfacade/amazonaws/services/glue/Permission;
      80: aload_0
      81: ldc           #63                 // String DATA_LOCATION_ACCESS
      83: checkcast     #55                 // class facade/amazonaws/services/glue/Permission
      86: putfield      #45                 // Field DATA_LOCATION_ACCESS:Lfacade/amazonaws/services/glue/Permission;
      89: aload_0
      90: getstatic     #68                 // Field scala/scalajs/js/Object$.MODULE$:Lscala/scalajs/js/Object$;
      93: getstatic     #73                 // Field scala/scalajs/js/Array$.MODULE$:Lscala/scalajs/js/Array$;
      96: getstatic     #78                 // Field scala/Predef$.MODULE$:Lscala/Predef$;
      99: bipush        9
     101: anewarray     #55                 // class facade/amazonaws/services/glue/Permission
     104: dup
     105: iconst_0
     106: aload_0
     107: invokevirtual #80                 // Method ALL:()Lfacade/amazonaws/services/glue/Permission;
     110: aastore
     111: dup
     112: iconst_1
     113: aload_0
     114: invokevirtual #82                 // Method SELECT:()Lfacade/amazonaws/services/glue/Permission;
     117: aastore
     118: dup
     119: iconst_2
     120: aload_0
     121: invokevirtual #84                 // Method ALTER:()Lfacade/amazonaws/services/glue/Permission;
     124: aastore
     125: dup
     126: iconst_3
     127: aload_0
     128: invokevirtual #86                 // Method DROP:()Lfacade/amazonaws/services/glue/Permission;
     131: aastore
     132: dup
     133: iconst_4
     134: aload_0
     135: invokevirtual #88                 // Method DELETE:()Lfacade/amazonaws/services/glue/Permission;
     138: aastore
     139: dup
     140: iconst_5
     141: aload_0
     142: invokevirtual #90                 // Method INSERT:()Lfacade/amazonaws/services/glue/Permission;
     145: aastore
     146: dup
     147: bipush        6
     149: aload_0
     150: invokevirtual #92                 // Method CREATE_DATABASE:()Lfacade/amazonaws/services/glue/Permission;
     153: aastore
     154: dup
     155: bipush        7
     157: aload_0
     158: invokevirtual #94                 // Method CREATE_TABLE:()Lfacade/amazonaws/services/glue/Permission;
     161: aastore
     162: dup
     163: bipush        8
     165: aload_0
     166: invokevirtual #96                 // Method DATA_LOCATION_ACCESS:()Lfacade/amazonaws/services/glue/Permission;
     169: aastore
     170: checkcast     #98                 // class "[Ljava/lang/Object;"
     173: invokevirtual #102                // Method scala/Predef$.wrapRefArray:([Ljava/lang/Object;)Lscala/collection/mutable/WrappedArray;
     176: invokevirtual #106                // Method scala/scalajs/js/Array$.apply:(Lscala/collection/Seq;)Lscala/scalajs/js/Array;
     179: invokevirtual #110                // Method scala/scalajs/js/Object$.freeze:(Lscala/scalajs/js/Object;)Lscala/scalajs/js/Object;
     182: checkcast     #112                // class scala/scalajs/js/Array
     185: putfield      #49                 // Field values:Lscala/scalajs/js/Array;
     188: return
}
