Compiled from "Glue.scala"
public interface facade.amazonaws.services.glue.Predecessor {
  public static scala.scalajs.js.$bar<java.lang.String, scala.runtime.BoxedUnit> apply$default$2();
    Code:
       0: getstatic     #17                 // Field facade/amazonaws/services/glue/Predecessor$.MODULE$:Lfacade/amazonaws/services/glue/Predecessor$;
       3: invokevirtual #19                 // Method facade/amazonaws/services/glue/Predecessor$.apply$default$2:()Lscala/scalajs/js/$bar;
       6: areturn

  public static scala.scalajs.js.$bar<java.lang.String, scala.runtime.BoxedUnit> apply$default$1();
    Code:
       0: getstatic     #17                 // Field facade/amazonaws/services/glue/Predecessor$.MODULE$:Lfacade/amazonaws/services/glue/Predecessor$;
       3: invokevirtual #22                 // Method facade/amazonaws/services/glue/Predecessor$.apply$default$1:()Lscala/scalajs/js/$bar;
       6: areturn

  public static facade.amazonaws.services.glue.Predecessor apply(scala.scalajs.js.$bar<java.lang.String, scala.runtime.BoxedUnit>, scala.scalajs.js.$bar<java.lang.String, scala.runtime.BoxedUnit>);
    Code:
       0: getstatic     #17                 // Field facade/amazonaws/services/glue/Predecessor$.MODULE$:Lfacade/amazonaws/services/glue/Predecessor$;
       3: aload_0
       4: aload_1
       5: invokevirtual #29                 // Method facade/amazonaws/services/glue/Predecessor$.apply:(Lscala/scalajs/js/$bar;Lscala/scalajs/js/$bar;)Lfacade/amazonaws/services/glue/Predecessor;
       8: areturn

  public abstract scala.scalajs.js.$bar<java.lang.String, scala.runtime.BoxedUnit> JobName();

  public abstract void JobName_$eq(scala.scalajs.js.$bar<java.lang.String, scala.runtime.BoxedUnit>);

  public abstract scala.scalajs.js.$bar<java.lang.String, scala.runtime.BoxedUnit> RunId();

  public abstract void RunId_$eq(scala.scalajs.js.$bar<java.lang.String, scala.runtime.BoxedUnit>);
}
