Compiled from "Glue.scala"
public interface facade.amazonaws.services.glue.TaskRunProperties {
  public static scala.scalajs.js.$bar<facade.amazonaws.services.glue.TaskType, scala.runtime.BoxedUnit> apply$default$5();
    Code:
       0: getstatic     #17                 // Field facade/amazonaws/services/glue/TaskRunProperties$.MODULE$:Lfacade/amazonaws/services/glue/TaskRunProperties$;
       3: invokevirtual #19                 // Method facade/amazonaws/services/glue/TaskRunProperties$.apply$default$5:()Lscala/scalajs/js/$bar;
       6: areturn

  public static scala.scalajs.js.$bar<facade.amazonaws.services.glue.LabelingSetGenerationTaskRunProperties, scala.runtime.BoxedUnit> apply$default$4();
    Code:
       0: getstatic     #17                 // Field facade/amazonaws/services/glue/TaskRunProperties$.MODULE$:Lfacade/amazonaws/services/glue/TaskRunProperties$;
       3: invokevirtual #23                 // Method facade/amazonaws/services/glue/TaskRunProperties$.apply$default$4:()Lscala/scalajs/js/$bar;
       6: areturn

  public static scala.scalajs.js.$bar<facade.amazonaws.services.glue.ImportLabelsTaskRunProperties, scala.runtime.BoxedUnit> apply$default$3();
    Code:
       0: getstatic     #17                 // Field facade/amazonaws/services/glue/TaskRunProperties$.MODULE$:Lfacade/amazonaws/services/glue/TaskRunProperties$;
       3: invokevirtual #27                 // Method facade/amazonaws/services/glue/TaskRunProperties$.apply$default$3:()Lscala/scalajs/js/$bar;
       6: areturn

  public static scala.scalajs.js.$bar<facade.amazonaws.services.glue.FindMatchesTaskRunProperties, scala.runtime.BoxedUnit> apply$default$2();
    Code:
       0: getstatic     #17                 // Field facade/amazonaws/services/glue/TaskRunProperties$.MODULE$:Lfacade/amazonaws/services/glue/TaskRunProperties$;
       3: invokevirtual #31                 // Method facade/amazonaws/services/glue/TaskRunProperties$.apply$default$2:()Lscala/scalajs/js/$bar;
       6: areturn

  public static scala.scalajs.js.$bar<facade.amazonaws.services.glue.ExportLabelsTaskRunProperties, scala.runtime.BoxedUnit> apply$default$1();
    Code:
       0: getstatic     #17                 // Field facade/amazonaws/services/glue/TaskRunProperties$.MODULE$:Lfacade/amazonaws/services/glue/TaskRunProperties$;
       3: invokevirtual #35                 // Method facade/amazonaws/services/glue/TaskRunProperties$.apply$default$1:()Lscala/scalajs/js/$bar;
       6: areturn

  public static facade.amazonaws.services.glue.TaskRunProperties apply(scala.scalajs.js.$bar<facade.amazonaws.services.glue.ExportLabelsTaskRunProperties, scala.runtime.BoxedUnit>, scala.scalajs.js.$bar<facade.amazonaws.services.glue.FindMatchesTaskRunProperties, scala.runtime.BoxedUnit>, scala.scalajs.js.$bar<facade.amazonaws.services.glue.ImportLabelsTaskRunProperties, scala.runtime.BoxedUnit>, scala.scalajs.js.$bar<facade.amazonaws.services.glue.LabelingSetGenerationTaskRunProperties, scala.runtime.BoxedUnit>, scala.scalajs.js.$bar<facade.amazonaws.services.glue.TaskType, scala.runtime.BoxedUnit>);
    Code:
       0: getstatic     #17                 // Field facade/amazonaws/services/glue/TaskRunProperties$.MODULE$:Lfacade/amazonaws/services/glue/TaskRunProperties$;
       3: aload_0
       4: aload_1
       5: aload_2
       6: aload_3
       7: aload         4
       9: invokevirtual #45                 // Method facade/amazonaws/services/glue/TaskRunProperties$.apply:(Lscala/scalajs/js/$bar;Lscala/scalajs/js/$bar;Lscala/scalajs/js/$bar;Lscala/scalajs/js/$bar;Lscala/scalajs/js/$bar;)Lfacade/amazonaws/services/glue/TaskRunProperties;
      12: areturn

  public abstract scala.scalajs.js.$bar<facade.amazonaws.services.glue.ExportLabelsTaskRunProperties, scala.runtime.BoxedUnit> ExportLabelsTaskRunProperties();

  public abstract void ExportLabelsTaskRunProperties_$eq(scala.scalajs.js.$bar<facade.amazonaws.services.glue.ExportLabelsTaskRunProperties, scala.runtime.BoxedUnit>);

  public abstract scala.scalajs.js.$bar<facade.amazonaws.services.glue.FindMatchesTaskRunProperties, scala.runtime.BoxedUnit> FindMatchesTaskRunProperties();

  public abstract void FindMatchesTaskRunProperties_$eq(scala.scalajs.js.$bar<facade.amazonaws.services.glue.FindMatchesTaskRunProperties, scala.runtime.BoxedUnit>);

  public abstract scala.scalajs.js.$bar<facade.amazonaws.services.glue.ImportLabelsTaskRunProperties, scala.runtime.BoxedUnit> ImportLabelsTaskRunProperties();

  public abstract void ImportLabelsTaskRunProperties_$eq(scala.scalajs.js.$bar<facade.amazonaws.services.glue.ImportLabelsTaskRunProperties, scala.runtime.BoxedUnit>);

  public abstract scala.scalajs.js.$bar<facade.amazonaws.services.glue.LabelingSetGenerationTaskRunProperties, scala.runtime.BoxedUnit> LabelingSetGenerationTaskRunProperties();

  public abstract void LabelingSetGenerationTaskRunProperties_$eq(scala.scalajs.js.$bar<facade.amazonaws.services.glue.LabelingSetGenerationTaskRunProperties, scala.runtime.BoxedUnit>);

  public abstract scala.scalajs.js.$bar<facade.amazonaws.services.glue.TaskType, scala.runtime.BoxedUnit> TaskType();

  public abstract void TaskType_$eq(scala.scalajs.js.$bar<facade.amazonaws.services.glue.TaskType, scala.runtime.BoxedUnit>);
}
