Compiled from "Glue.scala"
public interface facade.amazonaws.services.glue.WorkflowGraph {
  public static scala.scalajs.js.$bar<scala.scalajs.js.Array<facade.amazonaws.services.glue.Node>, scala.runtime.BoxedUnit> apply$default$2();
    Code:
       0: getstatic     #17                 // Field facade/amazonaws/services/glue/WorkflowGraph$.MODULE$:Lfacade/amazonaws/services/glue/WorkflowGraph$;
       3: invokevirtual #19                 // Method facade/amazonaws/services/glue/WorkflowGraph$.apply$default$2:()Lscala/scalajs/js/$bar;
       6: areturn

  public static scala.scalajs.js.$bar<scala.scalajs.js.Array<facade.amazonaws.services.glue.Edge>, scala.runtime.BoxedUnit> apply$default$1();
    Code:
       0: getstatic     #17                 // Field facade/amazonaws/services/glue/WorkflowGraph$.MODULE$:Lfacade/amazonaws/services/glue/WorkflowGraph$;
       3: invokevirtual #23                 // Method facade/amazonaws/services/glue/WorkflowGraph$.apply$default$1:()Lscala/scalajs/js/$bar;
       6: areturn

  public static facade.amazonaws.services.glue.WorkflowGraph apply(scala.scalajs.js.$bar<scala.scalajs.js.Array<facade.amazonaws.services.glue.Edge>, scala.runtime.BoxedUnit>, scala.scalajs.js.$bar<scala.scalajs.js.Array<facade.amazonaws.services.glue.Node>, scala.runtime.BoxedUnit>);
    Code:
       0: getstatic     #17                 // Field facade/amazonaws/services/glue/WorkflowGraph$.MODULE$:Lfacade/amazonaws/services/glue/WorkflowGraph$;
       3: aload_0
       4: aload_1
       5: invokevirtual #30                 // Method facade/amazonaws/services/glue/WorkflowGraph$.apply:(Lscala/scalajs/js/$bar;Lscala/scalajs/js/$bar;)Lfacade/amazonaws/services/glue/WorkflowGraph;
       8: areturn

  public abstract scala.scalajs.js.$bar<scala.scalajs.js.Array<facade.amazonaws.services.glue.Edge>, scala.runtime.BoxedUnit> Edges();

  public abstract void Edges_$eq(scala.scalajs.js.$bar<scala.scalajs.js.Array<facade.amazonaws.services.glue.Edge>, scala.runtime.BoxedUnit>);

  public abstract scala.scalajs.js.$bar<scala.scalajs.js.Array<facade.amazonaws.services.glue.Node>, scala.runtime.BoxedUnit> Nodes();

  public abstract void Nodes_$eq(scala.scalajs.js.$bar<scala.scalajs.js.Array<facade.amazonaws.services.glue.Node>, scala.runtime.BoxedUnit>);
}
