Compiled from "HostStatsByPeriodMap.java"
public class org.jumpmind.symmetric.statistic.HostStatsByPeriodMap extends org.jumpmind.symmetric.statistic.AbstractStatsByPeriodMap<org.jumpmind.symmetric.statistic.HostStats, org.jumpmind.symmetric.statistic.HostStats> {
  private static final long serialVersionUID;

  public org.jumpmind.symmetric.statistic.HostStatsByPeriodMap(java.util.Date, java.util.Date, java.util.List<org.jumpmind.symmetric.statistic.HostStats>, int);
    Code:
       0: aload_0
       1: aload_1
       2: aload_2
       3: aload_3
       4: iload         4
       6: invokespecial #1                  // Method org/jumpmind/symmetric/statistic/AbstractStatsByPeriodMap."<init>":(Ljava/util/Date;Ljava/util/Date;Ljava/util/List;I)V
       9: return

  protected void add(java.util.Date, org.jumpmind.symmetric.statistic.HostStats);
    Code:
       0: aload_0
       1: aload_1
       2: aload_2
       3: invokevirtual #2                  // Method put:(Ljava/lang/Object;Ljava/lang/Object;)Ljava/lang/Object;
       6: pop
       7: return

  protected void addBlank(java.util.Date);
    Code:
       0: aload_0
       1: aload_1
       2: new           #3                  // class org/jumpmind/symmetric/statistic/HostStats
       5: dup
       6: invokespecial #4                  // Method org/jumpmind/symmetric/statistic/HostStats."<init>":()V
       9: invokevirtual #2                  // Method put:(Ljava/lang/Object;Ljava/lang/Object;)Ljava/lang/Object;
      12: pop
      13: return

  protected void add(java.util.Date, org.jumpmind.symmetric.statistic.AbstractNodeHostStats);
    Code:
       0: aload_0
       1: aload_1
       2: aload_2
       3: checkcast     #3                  // class org/jumpmind/symmetric/statistic/HostStats
       6: invokevirtual #5                  // Method add:(Ljava/util/Date;Lorg/jumpmind/symmetric/statistic/HostStats;)V
       9: return
}
