Compiled from "WSSecDerivedKeyBase.java"
public abstract class org.apache.wss4j.dom.message.WSSecDerivedKeyBase extends org.apache.wss4j.dom.message.WSSecSignatureBase {
  private static final org.slf4j.Logger LOG;

  protected org.w3c.dom.Document document;

  private org.apache.wss4j.dom.message.token.DerivedKeyToken dkt;

  private byte[] ephemeralKey;

  private java.lang.String clientLabel;

  private java.lang.String serviceLabel;

  private java.lang.String tokenIdentifier;

  private boolean tokenIdDirectId;

  private org.w3c.dom.Element strElem;

  private java.lang.String dktId;

  private byte[] derivedKeyBytes;

  private int wscVersion;

  private java.lang.String customValueType;

  private java.security.cert.X509Certificate useThisCert;

  private org.apache.wss4j.common.crypto.Crypto crypto;

  public org.apache.wss4j.dom.message.WSSecDerivedKeyBase();
    Code:
       0: aload_0
       1: invokespecial #1                  // Method org/apache/wss4j/dom/message/WSSecSignatureBase."<init>":()V
       4: aload_0
       5: ldc           #2                  // String WS-SecureConversation
       7: putfield      #3                  // Field clientLabel:Ljava/lang/String;
      10: aload_0
      11: ldc           #2                  // String WS-SecureConversation
      13: putfield      #4                  // Field serviceLabel:Ljava/lang/String;
      16: aload_0
      17: iconst_2
      18: putfield      #5                  // Field wscVersion:I
      21: aload_0
      22: iconst_0
      23: invokevirtual #6                  // Method setKeyIdentifierType:(I)V
      26: return

  protected abstract int getDerivedKeyLength() throws org.apache.wss4j.common.ext.WSSecurityException;

  public void setExternalKey(byte[], java.lang.String);
    Code:
       0: aload_0
       1: aload_1
       2: putfield      #7                  // Field ephemeralKey:[B
       5: aload_0
       6: aload_2
       7: putfield      #8                  // Field tokenIdentifier:Ljava/lang/String;
      10: return

  public void setExternalKey(byte[], org.w3c.dom.Element);
    Code:
       0: aload_0
       1: aload_1
       2: putfield      #7                  // Field ephemeralKey:[B
       5: aload_0
       6: aload_2
       7: putfield      #9                  // Field strElem:Lorg/w3c/dom/Element;
      10: return

  public java.lang.String getTokenIdentifier();
    Code:
       0: aload_0
       1: getfield      #8                  // Field tokenIdentifier:Ljava/lang/String;
       4: areturn

  public void setX509Certificate(java.security.cert.X509Certificate);
    Code:
       0: aload_0
       1: aload_1
       2: putfield      #10                 // Field useThisCert:Ljava/security/cert/X509Certificate;
       5: return

  public java.lang.String getId();
    Code:
       0: aload_0
       1: getfield      #11                 // Field dktId:Ljava/lang/String;
       4: areturn

  public void setClientLabel(java.lang.String);
    Code:
       0: aload_0
       1: aload_1
       2: putfield      #3                  // Field clientLabel:Ljava/lang/String;
       5: return

  public void setServiceLabel(java.lang.String);
    Code:
       0: aload_0
       1: aload_1
       2: putfield      #4                  // Field serviceLabel:Ljava/lang/String;
       5: return

  public void prepare(org.w3c.dom.Document) throws org.apache.wss4j.common.ext.WSSecurityException;
    Code:
       0: aload_0
       1: aload_1
       2: putfield      #12                 // Field document:Lorg/w3c/dom/Document;
       5: iconst_0
       6: istore_2
       7: aload_0
       8: invokevirtual #13                 // Method getDerivedKeyLength:()I
      11: istore_3
      12: new           #14                 // class java/lang/StringBuilder
      15: dup
      16: invokespecial #15                 // Method java/lang/StringBuilder."<init>":()V
      19: aload_0
      20: getfield      #3                  // Field clientLabel:Ljava/lang/String;
      23: invokevirtual #16                 // Method java/lang/StringBuilder.append:(Ljava/lang/String;)Ljava/lang/StringBuilder;
      26: aload_0
      27: getfield      #4                  // Field serviceLabel:Ljava/lang/String;
      30: invokevirtual #16                 // Method java/lang/StringBuilder.append:(Ljava/lang/String;)Ljava/lang/StringBuilder;
      33: invokevirtual #17                 // Method java/lang/StringBuilder.toString:()Ljava/lang/String;
      36: astore        5
      38: aload         5
      40: ldc           #18                 // String UTF-8
      42: invokevirtual #19                 // Method java/lang/String.getBytes:(Ljava/lang/String;)[B
      45: astore        4
      47: goto          76
      50: astore        5
      52: new           #21                 // class org/apache/wss4j/common/ext/WSSecurityException
      55: dup
      56: getstatic     #22                 // Field org/apache/wss4j/common/ext/WSSecurityException$ErrorCode.FAILURE:Lorg/apache/wss4j/common/ext/WSSecurityException$ErrorCode;
      59: aload         5
      61: ldc           #23                 // String empty
      63: iconst_1
      64: anewarray     #24                 // class java/lang/Object
      67: dup
      68: iconst_0
      69: ldc           #25                 // String UTF-8 encoding is not supported
      71: aastore
      72: invokespecial #26                 // Method org/apache/wss4j/common/ext/WSSecurityException."<init>":(Lorg/apache/wss4j/common/ext/WSSecurityException$ErrorCode;Ljava/lang/Exception;Ljava/lang/String;[Ljava/lang/Object;)V
      75: athrow
      76: bipush        16
      78: invokestatic  #27                 // Method org/apache/wss4j/dom/util/WSSecurityUtil.generateNonce:(I)[B
      81: astore        5
      83: aload         4
      85: arraylength
      86: aload         5
      88: arraylength
      89: iadd
      90: newarray       byte
      92: astore        6
      94: aload         4
      96: iconst_0
      97: aload         6
      99: iconst_0
     100: aload         4
     102: arraylength
     103: invokestatic  #28                 // Method java/lang/System.arraycopy:(Ljava/lang/Object;ILjava/lang/Object;II)V
     106: aload         5
     108: iconst_0
     109: aload         6
     111: aload         4
     113: arraylength
     114: aload         5
     116: arraylength
     117: invokestatic  #28                 // Method java/lang/System.arraycopy:(Ljava/lang/Object;ILjava/lang/Object;II)V
     120: ldc           #29                 // String http://schemas.xmlsoap.org/ws/2005/02/sc/dk/p_sha1
     122: invokestatic  #30                 // Method org/apache/wss4j/common/derivedKey/AlgoFactory.getInstance:(Ljava/lang/String;)Lorg/apache/wss4j/common/derivedKey/DerivationAlgorithm;
     125: astore        7
     127: aload_0
     128: getfield      #7                  // Field ephemeralKey:[B
     131: ifnull        142
     134: aload_0
     135: getfield      #7                  // Field ephemeralKey:[B
     138: arraylength
     139: ifne          183
     142: getstatic     #31                 // Field LOG:Lorg/slf4j/Logger;
     145: new           #14                 // class java/lang/StringBuilder
     148: dup
     149: invokespecial #15                 // Method java/lang/StringBuilder."<init>":()V
     152: ldc           #32                 // String No ephemeral key is supplied for id:
     154: invokevirtual #16                 // Method java/lang/StringBuilder.append:(Ljava/lang/String;)Ljava/lang/StringBuilder;
     157: aload_0
     158: getfield      #8                  // Field tokenIdentifier:Ljava/lang/String;
     161: invokevirtual #16                 // Method java/lang/StringBuilder.append:(Ljava/lang/String;)Ljava/lang/StringBuilder;
     164: invokevirtual #17                 // Method java/lang/StringBuilder.toString:()Ljava/lang/String;
     167: invokeinterface #33,  2           // InterfaceMethod org/slf4j/Logger.debug:(Ljava/lang/String;)V
     172: new           #21                 // class org/apache/wss4j/common/ext/WSSecurityException
     175: dup
     176: getstatic     #22                 // Field org/apache/wss4j/common/ext/WSSecurityException$ErrorCode.FAILURE:Lorg/apache/wss4j/common/ext/WSSecurityException$ErrorCode;
     179: invokespecial #34                 // Method org/apache/wss4j/common/ext/WSSecurityException."<init>":(Lorg/apache/wss4j/common/ext/WSSecurityException$ErrorCode;)V
     182: athrow
     183: aload_0
     184: aload         7
     186: aload_0
     187: getfield      #7                  // Field ephemeralKey:[B
     190: aload         6
     192: iload_2
     193: iload_3
     194: i2l
     195: invokeinterface #35,  6           // InterfaceMethod org/apache/wss4j/common/derivedKey/DerivationAlgorithm.createKey:([B[BIJ)[B
     200: putfield      #36                 // Field derivedKeyBytes:[B
     203: aload_0
     204: new           #37                 // class org/apache/wss4j/dom/message/token/DerivedKeyToken
     207: dup
     208: aload_0
     209: getfield      #5                  // Field wscVersion:I
     212: aload_0
     213: getfield      #12                 // Field document:Lorg/w3c/dom/Document;
     216: invokespecial #38                 // Method org/apache/wss4j/dom/message/token/DerivedKeyToken."<init>":(ILorg/w3c/dom/Document;)V
     219: putfield      #39                 // Field dkt:Lorg/apache/wss4j/dom/message/token/DerivedKeyToken;
     222: aload_0
     223: aload_0
     224: invokevirtual #40                 // Method getIdAllocator:()Lorg/apache/wss4j/dom/WsuIdAllocator;
     227: ldc           #41                 // String DK-
     229: aload_0
     230: getfield      #39                 // Field dkt:Lorg/apache/wss4j/dom/message/token/DerivedKeyToken;
     233: invokeinterface #42,  3           // InterfaceMethod org/apache/wss4j/dom/WsuIdAllocator.createId:(Ljava/lang/String;Ljava/lang/Object;)Ljava/lang/String;
     238: putfield      #11                 // Field dktId:Ljava/lang/String;
     241: aload_0
     242: getfield      #39                 // Field dkt:Lorg/apache/wss4j/dom/message/token/DerivedKeyToken;
     245: iload_2
     246: invokevirtual #43                 // Method org/apache/wss4j/dom/message/token/DerivedKeyToken.setOffset:(I)V
     249: aload_0
     250: getfield      #39                 // Field dkt:Lorg/apache/wss4j/dom/message/token/DerivedKeyToken;
     253: iload_3
     254: invokevirtual #44                 // Method org/apache/wss4j/dom/message/token/DerivedKeyToken.setLength:(I)V
     257: aload_0
     258: getfield      #39                 // Field dkt:Lorg/apache/wss4j/dom/message/token/DerivedKeyToken;
     261: aload         5
     263: invokestatic  #45                 // Method org/apache/xml/security/utils/Base64.encode:([B)Ljava/lang/String;
     266: invokevirtual #46                 // Method org/apache/wss4j/dom/message/token/DerivedKeyToken.setNonce:(Ljava/lang/String;)V
     269: aload_0
     270: getfield      #39                 // Field dkt:Lorg/apache/wss4j/dom/message/token/DerivedKeyToken;
     273: aload_0
     274: getfield      #11                 // Field dktId:Ljava/lang/String;
     277: invokevirtual #47                 // Method org/apache/wss4j/dom/message/token/DerivedKeyToken.setID:(Ljava/lang/String;)V
     280: aload_0
     281: getfield      #9                  // Field strElem:Lorg/w3c/dom/Element;
     284: ifnonnull     783
     287: new           #48                 // class org/apache/wss4j/common/token/SecurityTokenReference
     290: dup
     291: aload_0
     292: getfield      #12                 // Field document:Lorg/w3c/dom/Document;
     295: invokespecial #49                 // Method org/apache/wss4j/common/token/SecurityTokenReference."<init>":(Lorg/w3c/dom/Document;)V
     298: astore        8
     300: aload_0
     301: invokevirtual #40                 // Method getIdAllocator:()Lorg/apache/wss4j/dom/WsuIdAllocator;
     304: ldc           #50                 // String STR-
     306: aload         8
     308: invokeinterface #51,  3           // InterfaceMethod org/apache/wss4j/dom/WsuIdAllocator.createSecureId:(Ljava/lang/String;Ljava/lang/Object;)Ljava/lang/String;
     313: astore        9
     315: aload         8
     317: aload         9
     319: invokevirtual #52                 // Method org/apache/wss4j/common/token/SecurityTokenReference.setID:(Ljava/lang/String;)V
     322: aload_0
     323: invokespecial #53                 // Method getSigningCerts:()[Ljava/security/cert/X509Certificate;
     326: astore        10
     328: aload_0
     329: getfield      #54                 // Field keyIdentifierType:I
     332: tableswitch   { // 3 to 12
                     3: 388
                     4: 400
                     5: 507
                     6: 507
                     7: 507
                     8: 416
                     9: 507
                    10: 507
                    11: 507
                    12: 428
               default: 507
          }
     388: aload         8
     390: aload         10
     392: iconst_0
     393: aaload
     394: invokevirtual #55                 // Method org/apache/wss4j/common/token/SecurityTokenReference.setKeyIdentifier:(Ljava/security/cert/X509Certificate;)V
     397: goto          771
     400: aload         8
     402: aload         10
     404: iconst_0
     405: aaload
     406: aload_0
     407: getfield      #56                 // Field crypto:Lorg/apache/wss4j/common/crypto/Crypto;
     410: invokevirtual #57                 // Method org/apache/wss4j/common/token/SecurityTokenReference.setKeyIdentifierSKI:(Ljava/security/cert/X509Certificate;Lorg/apache/wss4j/common/crypto/Crypto;)V
     413: goto          771
     416: aload         8
     418: aload         10
     420: iconst_0
     421: aaload
     422: invokevirtual #58                 // Method org/apache/wss4j/common/token/SecurityTokenReference.setKeyIdentifierThumb:(Ljava/security/cert/X509Certificate;)V
     425: goto          771
     428: aload         8
     430: aload_0
     431: getfield      #59                 // Field customValueType:Ljava/lang/String;
     434: aload_0
     435: getfield      #8                  // Field tokenIdentifier:Ljava/lang/String;
     438: invokevirtual #60                 // Method org/apache/wss4j/common/token/SecurityTokenReference.setKeyIdentifier:(Ljava/lang/String;Ljava/lang/String;)V
     441: ldc           #61                 // String http://docs.oasis-open.org/wss/oasis-wss-saml-token-profile-1.0#SAMLAssertionID
     443: aload_0
     444: getfield      #59                 // Field customValueType:Ljava/lang/String;
     447: invokevirtual #62                 // Method java/lang/String.equals:(Ljava/lang/Object;)Z
     450: ifeq          463
     453: aload         8
     455: ldc           #63                 // String http://docs.oasis-open.org/wss/oasis-wss-saml-token-profile-1.1#SAMLV1.1
     457: invokevirtual #64                 // Method org/apache/wss4j/common/token/SecurityTokenReference.addTokenType:(Ljava/lang/String;)V
     460: goto          771
     463: ldc           #65                 // String http://docs.oasis-open.org/wss/oasis-wss-saml-token-profile-1.1#SAMLID
     465: aload_0
     466: getfield      #59                 // Field customValueType:Ljava/lang/String;
     469: invokevirtual #62                 // Method java/lang/String.equals:(Ljava/lang/Object;)Z
     472: ifeq          485
     475: aload         8
     477: ldc           #66                 // String http://docs.oasis-open.org/wss/oasis-wss-saml-token-profile-1.1#SAMLV2.0
     479: invokevirtual #64                 // Method org/apache/wss4j/common/token/SecurityTokenReference.addTokenType:(Ljava/lang/String;)V
     482: goto          771
     485: ldc           #67                 // String http://docs.oasis-open.org/wss/oasis-wss-soap-message-security-1.1#EncryptedKey
     487: aload_0
     488: getfield      #59                 // Field customValueType:Ljava/lang/String;
     491: invokevirtual #62                 // Method java/lang/String.equals:(Ljava/lang/Object;)Z
     494: ifeq          771
     497: aload         8
     499: ldc           #67                 // String http://docs.oasis-open.org/wss/oasis-wss-soap-message-security-1.1#EncryptedKey
     501: invokevirtual #64                 // Method org/apache/wss4j/common/token/SecurityTokenReference.addTokenType:(Ljava/lang/String;)V
     504: goto          771
     507: new           #68                 // class org/apache/wss4j/common/token/Reference
     510: dup
     511: aload_0
     512: getfield      #12                 // Field document:Lorg/w3c/dom/Document;
     515: invokespecial #69                 // Method org/apache/wss4j/common/token/Reference."<init>":(Lorg/w3c/dom/Document;)V
     518: astore        11
     520: aload_0
     521: getfield      #70                 // Field tokenIdDirectId:Z
     524: ifeq          539
     527: aload         11
     529: aload_0
     530: getfield      #8                  // Field tokenIdentifier:Ljava/lang/String;
     533: invokevirtual #71                 // Method org/apache/wss4j/common/token/Reference.setURI:(Ljava/lang/String;)V
     536: goto          566
     539: aload         11
     541: new           #14                 // class java/lang/StringBuilder
     544: dup
     545: invokespecial #15                 // Method java/lang/StringBuilder."<init>":()V
     548: ldc           #72                 // String #
     550: invokevirtual #16                 // Method java/lang/StringBuilder.append:(Ljava/lang/String;)Ljava/lang/StringBuilder;
     553: aload_0
     554: getfield      #8                  // Field tokenIdentifier:Ljava/lang/String;
     557: invokevirtual #16                 // Method java/lang/StringBuilder.append:(Ljava/lang/String;)Ljava/lang/StringBuilder;
     560: invokevirtual #17                 // Method java/lang/StringBuilder.toString:()Ljava/lang/String;
     563: invokevirtual #71                 // Method org/apache/wss4j/common/token/Reference.setURI:(Ljava/lang/String;)V
     566: aload_0
     567: getfield      #59                 // Field customValueType:Ljava/lang/String;
     570: ifnull        594
     573: ldc           #73                 // String
     575: aload_0
     576: getfield      #59                 // Field customValueType:Ljava/lang/String;
     579: invokevirtual #62                 // Method java/lang/String.equals:(Ljava/lang/Object;)Z
     582: ifne          594
     585: aload         11
     587: aload_0
     588: getfield      #59                 // Field customValueType:Ljava/lang/String;
     591: invokevirtual #74                 // Method org/apache/wss4j/common/token/Reference.setValueType:(Ljava/lang/String;)V
     594: ldc           #61                 // String http://docs.oasis-open.org/wss/oasis-wss-saml-token-profile-1.0#SAMLAssertionID
     596: aload_0
     597: getfield      #59                 // Field customValueType:Ljava/lang/String;
     600: invokevirtual #62                 // Method java/lang/String.equals:(Ljava/lang/Object;)Z
     603: ifeq          625
     606: aload         8
     608: ldc           #63                 // String http://docs.oasis-open.org/wss/oasis-wss-saml-token-profile-1.1#SAMLV1.1
     610: invokevirtual #64                 // Method org/apache/wss4j/common/token/SecurityTokenReference.addTokenType:(Ljava/lang/String;)V
     613: aload         11
     615: aload_0
     616: getfield      #59                 // Field customValueType:Ljava/lang/String;
     619: invokevirtual #74                 // Method org/apache/wss4j/common/token/Reference.setValueType:(Ljava/lang/String;)V
     622: goto          764
     625: ldc           #65                 // String http://docs.oasis-open.org/wss/oasis-wss-saml-token-profile-1.1#SAMLID
     627: aload_0
     628: getfield      #59                 // Field customValueType:Ljava/lang/String;
     631: invokevirtual #62                 // Method java/lang/String.equals:(Ljava/lang/Object;)Z
     634: ifeq          647
     637: aload         8
     639: ldc           #66                 // String http://docs.oasis-open.org/wss/oasis-wss-saml-token-profile-1.1#SAMLV2.0
     641: invokevirtual #64                 // Method org/apache/wss4j/common/token/SecurityTokenReference.addTokenType:(Ljava/lang/String;)V
     644: goto          764
     647: ldc           #67                 // String http://docs.oasis-open.org/wss/oasis-wss-soap-message-security-1.1#EncryptedKey
     649: aload_0
     650: getfield      #59                 // Field customValueType:Ljava/lang/String;
     653: invokevirtual #62                 // Method java/lang/String.equals:(Ljava/lang/Object;)Z
     656: ifeq          678
     659: aload         8
     661: ldc           #67                 // String http://docs.oasis-open.org/wss/oasis-wss-soap-message-security-1.1#EncryptedKey
     663: invokevirtual #64                 // Method org/apache/wss4j/common/token/SecurityTokenReference.addTokenType:(Ljava/lang/String;)V
     666: aload         11
     668: aload_0
     669: getfield      #59                 // Field customValueType:Ljava/lang/String;
     672: invokevirtual #74                 // Method org/apache/wss4j/common/token/Reference.setValueType:(Ljava/lang/String;)V
     675: goto          764
     678: aload_0
     679: getfield      #59                 // Field customValueType:Ljava/lang/String;
     682: invokestatic  #75                 // Method org/apache/wss4j/dom/message/token/KerberosSecurity.isKerberosToken:(Ljava/lang/String;)Z
     685: ifeq          709
     688: aload         8
     690: aload_0
     691: getfield      #59                 // Field customValueType:Ljava/lang/String;
     694: invokevirtual #64                 // Method org/apache/wss4j/common/token/SecurityTokenReference.addTokenType:(Ljava/lang/String;)V
     697: aload         11
     699: aload_0
     700: getfield      #59                 // Field customValueType:Ljava/lang/String;
     703: invokevirtual #74                 // Method org/apache/wss4j/common/token/Reference.setValueType:(Ljava/lang/String;)V
     706: goto          764
     709: ldc           #76                 // String http://schemas.xmlsoap.org/ws/2005/02/sc/sct
     711: aload_0
     712: getfield      #59                 // Field customValueType:Ljava/lang/String;
     715: invokevirtual #62                 // Method java/lang/String.equals:(Ljava/lang/Object;)Z
     718: ifne          733
     721: ldc           #77                 // String http://docs.oasis-open.org/ws-sx/ws-secureconversation/200512/sct
     723: aload_0
     724: getfield      #59                 // Field customValueType:Ljava/lang/String;
     727: invokevirtual #62                 // Method java/lang/String.equals:(Ljava/lang/Object;)Z
     730: ifeq          745
     733: aload         11
     735: aload_0
     736: getfield      #59                 // Field customValueType:Ljava/lang/String;
     739: invokevirtual #74                 // Method org/apache/wss4j/common/token/Reference.setValueType:(Ljava/lang/String;)V
     742: goto          764
     745: ldc           #78                 // String http://docs.oasis-open.org/wss/2004/01/oasis-200401-wss-username-token-profile-1.0#UsernameToken
     747: aload_0
     748: getfield      #59                 // Field customValueType:Ljava/lang/String;
     751: invokevirtual #62                 // Method java/lang/String.equals:(Ljava/lang/Object;)Z
     754: ifne          764
     757: aload         8
     759: ldc           #67                 // String http://docs.oasis-open.org/wss/oasis-wss-soap-message-security-1.1#EncryptedKey
     761: invokevirtual #64                 // Method org/apache/wss4j/common/token/SecurityTokenReference.addTokenType:(Ljava/lang/String;)V
     764: aload         8
     766: aload         11
     768: invokevirtual #79                 // Method org/apache/wss4j/common/token/SecurityTokenReference.setReference:(Lorg/apache/wss4j/common/token/Reference;)V
     771: aload_0
     772: getfield      #39                 // Field dkt:Lorg/apache/wss4j/dom/message/token/DerivedKeyToken;
     775: aload         8
     777: invokevirtual #80                 // Method org/apache/wss4j/dom/message/token/DerivedKeyToken.setSecurityTokenReference:(Lorg/apache/wss4j/common/token/SecurityTokenReference;)V
     780: goto          794
     783: aload_0
     784: getfield      #39                 // Field dkt:Lorg/apache/wss4j/dom/message/token/DerivedKeyToken;
     787: aload_0
     788: getfield      #9                  // Field strElem:Lorg/w3c/dom/Element;
     791: invokevirtual #81                 // Method org/apache/wss4j/dom/message/token/DerivedKeyToken.setSecurityTokenReference:(Lorg/w3c/dom/Element;)V
     794: return
    Exception table:
       from    to  target type
          12    47    50   Class java/io/UnsupportedEncodingException

  public void prependDKElementToHeader(org.apache.wss4j.dom.message.WSSecHeader);
    Code:
       0: aload_1
       1: invokevirtual #82                 // Method org/apache/wss4j/dom/message/WSSecHeader.getSecurityHeader:()Lorg/w3c/dom/Element;
       4: aload_0
       5: getfield      #39                 // Field dkt:Lorg/apache/wss4j/dom/message/token/DerivedKeyToken;
       8: invokevirtual #83                 // Method org/apache/wss4j/dom/message/token/DerivedKeyToken.getElement:()Lorg/w3c/dom/Element;
      11: invokestatic  #84                 // Method org/apache/wss4j/dom/util/WSSecurityUtil.prependChildElement:(Lorg/w3c/dom/Element;Lorg/w3c/dom/Element;)Lorg/w3c/dom/Element;
      14: pop
      15: return

  public void appendDKElementToHeader(org.apache.wss4j.dom.message.WSSecHeader);
    Code:
       0: aload_1
       1: invokevirtual #82                 // Method org/apache/wss4j/dom/message/WSSecHeader.getSecurityHeader:()Lorg/w3c/dom/Element;
       4: astore_2
       5: aload_2
       6: aload_0
       7: getfield      #39                 // Field dkt:Lorg/apache/wss4j/dom/message/token/DerivedKeyToken;
      10: invokevirtual #83                 // Method org/apache/wss4j/dom/message/token/DerivedKeyToken.getElement:()Lorg/w3c/dom/Element;
      13: invokeinterface #85,  2           // InterfaceMethod org/w3c/dom/Element.appendChild:(Lorg/w3c/dom/Node;)Lorg/w3c/dom/Node;
      18: pop
      19: return

  public void setWscVersion(int);
    Code:
       0: aload_0
       1: iload_1
       2: putfield      #5                  // Field wscVersion:I
       5: return

  public int getWscVersion();
    Code:
       0: aload_0
       1: getfield      #5                  // Field wscVersion:I
       4: ireturn

  public org.w3c.dom.Element getdktElement();
    Code:
       0: aload_0
       1: getfield      #39                 // Field dkt:Lorg/apache/wss4j/dom/message/token/DerivedKeyToken;
       4: invokevirtual #83                 // Method org/apache/wss4j/dom/message/token/DerivedKeyToken.getElement:()Lorg/w3c/dom/Element;
       7: areturn

  public void setCustomValueType(java.lang.String);
    Code:
       0: aload_0
       1: aload_1
       2: putfield      #59                 // Field customValueType:Ljava/lang/String;
       5: return

  public void setTokenIdDirectId(boolean);
    Code:
       0: aload_0
       1: iload_1
       2: putfield      #70                 // Field tokenIdDirectId:Z
       5: return

  private java.security.cert.X509Certificate[] getSigningCerts() throws org.apache.wss4j.common.ext.WSSecurityException;
    Code:
       0: aconst_null
       1: astore_1
       2: aload_0
       3: getfield      #54                 // Field keyIdentifierType:I
       6: iconst_2
       7: if_icmpeq     35
      10: aload_0
      11: getfield      #54                 // Field keyIdentifierType:I
      14: iconst_3
      15: if_icmpeq     35
      18: aload_0
      19: getfield      #54                 // Field keyIdentifierType:I
      22: iconst_4
      23: if_icmpeq     35
      26: aload_0
      27: getfield      #54                 // Field keyIdentifierType:I
      30: bipush        8
      32: if_icmpne     145
      35: aload_0
      36: getfield      #10                 // Field useThisCert:Ljava/security/cert/X509Certificate;
      39: ifnonnull     95
      42: new           #86                 // class org/apache/wss4j/common/crypto/CryptoType
      45: dup
      46: getstatic     #87                 // Field org/apache/wss4j/common/crypto/CryptoType$TYPE.ALIAS:Lorg/apache/wss4j/common/crypto/CryptoType$TYPE;
      49: invokespecial #88                 // Method org/apache/wss4j/common/crypto/CryptoType."<init>":(Lorg/apache/wss4j/common/crypto/CryptoType$TYPE;)V
      52: astore_2
      53: aload_2
      54: aload_0
      55: getfield      #89                 // Field user:Ljava/lang/String;
      58: invokevirtual #90                 // Method org/apache/wss4j/common/crypto/CryptoType.setAlias:(Ljava/lang/String;)V
      61: aload_0
      62: getfield      #56                 // Field crypto:Lorg/apache/wss4j/common/crypto/Crypto;
      65: ifnonnull     81
      68: new           #21                 // class org/apache/wss4j/common/ext/WSSecurityException
      71: dup
      72: getstatic     #22                 // Field org/apache/wss4j/common/ext/WSSecurityException$ErrorCode.FAILURE:Lorg/apache/wss4j/common/ext/WSSecurityException$ErrorCode;
      75: ldc           #91                 // String noSigCryptoFile
      77: invokespecial #92                 // Method org/apache/wss4j/common/ext/WSSecurityException."<init>":(Lorg/apache/wss4j/common/ext/WSSecurityException$ErrorCode;Ljava/lang/String;)V
      80: athrow
      81: aload_0
      82: getfield      #56                 // Field crypto:Lorg/apache/wss4j/common/crypto/Crypto;
      85: aload_2
      86: invokeinterface #93,  2           // InterfaceMethod org/apache/wss4j/common/crypto/Crypto.getX509Certificates:(Lorg/apache/wss4j/common/crypto/CryptoType;)[Ljava/security/cert/X509Certificate;
      91: astore_1
      92: goto          107
      95: iconst_1
      96: anewarray     #94                 // class java/security/cert/X509Certificate
      99: dup
     100: iconst_0
     101: aload_0
     102: getfield      #10                 // Field useThisCert:Ljava/security/cert/X509Certificate;
     105: aastore
     106: astore_1
     107: aload_1
     108: ifnull        116
     111: aload_1
     112: arraylength
     113: ifgt          145
     116: new           #21                 // class org/apache/wss4j/common/ext/WSSecurityException
     119: dup
     120: getstatic     #22                 // Field org/apache/wss4j/common/ext/WSSecurityException$ErrorCode.FAILURE:Lorg/apache/wss4j/common/ext/WSSecurityException$ErrorCode;
     123: ldc           #95                 // String noUserCertsFound
     125: iconst_2
     126: anewarray     #24                 // class java/lang/Object
     129: dup
     130: iconst_0
     131: aload_0
     132: getfield      #89                 // Field user:Ljava/lang/String;
     135: aastore
     136: dup
     137: iconst_1
     138: ldc           #96                 // String signature
     140: aastore
     141: invokespecial #97                 // Method org/apache/wss4j/common/ext/WSSecurityException."<init>":(Lorg/apache/wss4j/common/ext/WSSecurityException$ErrorCode;Ljava/lang/String;[Ljava/lang/Object;)V
     144: athrow
     145: aload_1
     146: areturn

  public void setCrypto(org.apache.wss4j.common.crypto.Crypto);
    Code:
       0: aload_0
       1: aload_1
       2: putfield      #56                 // Field crypto:Lorg/apache/wss4j/common/crypto/Crypto;
       5: return

  protected javax.crypto.SecretKey getDerivedKey(java.lang.String);
    Code:
       0: aload_1
       1: aload_0
       2: getfield      #36                 // Field derivedKeyBytes:[B
       5: invokestatic  #98                 // Method org/apache/wss4j/common/util/KeyUtils.prepareSecretKey:(Ljava/lang/String;[B)Ljavax/crypto/SecretKey;
       8: areturn

  static {};
    Code:
       0: ldc_w         #99                 // class org/apache/wss4j/dom/message/WSSecDerivedKeyBase
       3: invokestatic  #100                // Method org/slf4j/LoggerFactory.getLogger:(Ljava/lang/Class;)Lorg/slf4j/Logger;
       6: putstatic     #31                 // Field LOG:Lorg/slf4j/Logger;
       9: return
}
