Compiled from "BroadCastStatsLogger.java"
public class org.apache.bookkeeper.common.stats.BroadCastStatsLogger {
  public org.apache.bookkeeper.common.stats.BroadCastStatsLogger();
    Code:
       0: aload_0
       1: invokespecial #1                  // Method java/lang/Object."<init>":()V
       4: return

  public static org.apache.bookkeeper.stats.StatsLogger two(org.apache.bookkeeper.stats.StatsLogger, org.apache.bookkeeper.stats.StatsLogger);
    Code:
       0: new           #2                  // class org/apache/bookkeeper/stats/CachingStatsLogger
       3: dup
       4: new           #3                  // class org/apache/bookkeeper/common/stats/BroadCastStatsLogger$Two
       7: dup
       8: aload_0
       9: aload_1
      10: aconst_null
      11: invokespecial #4                  // Method org/apache/bookkeeper/common/stats/BroadCastStatsLogger$Two."<init>":(Lorg/apache/bookkeeper/stats/StatsLogger;Lorg/apache/bookkeeper/stats/StatsLogger;Lorg/apache/bookkeeper/common/stats/BroadCastStatsLogger$1;)V
      14: invokespecial #5                  // Method org/apache/bookkeeper/stats/CachingStatsLogger."<init>":(Lorg/apache/bookkeeper/stats/StatsLogger;)V
      17: areturn

  public static org.apache.bookkeeper.stats.StatsLogger masterslave(org.apache.bookkeeper.stats.StatsLogger, org.apache.bookkeeper.stats.StatsLogger);
    Code:
       0: new           #2                  // class org/apache/bookkeeper/stats/CachingStatsLogger
       3: dup
       4: new           #6                  // class org/apache/bookkeeper/common/stats/BroadCastStatsLogger$MasterSlave
       7: dup
       8: aload_0
       9: aload_1
      10: aconst_null
      11: invokespecial #7                  // Method org/apache/bookkeeper/common/stats/BroadCastStatsLogger$MasterSlave."<init>":(Lorg/apache/bookkeeper/stats/StatsLogger;Lorg/apache/bookkeeper/stats/StatsLogger;Lorg/apache/bookkeeper/common/stats/BroadCastStatsLogger$1;)V
      14: invokespecial #5                  // Method org/apache/bookkeeper/stats/CachingStatsLogger."<init>":(Lorg/apache/bookkeeper/stats/StatsLogger;)V
      17: areturn
}
