public class org.bouncycastle.mail.smime.examples.ExampleUtils {
  public org.bouncycastle.mail.smime.examples.ExampleUtils();
    Code:
       0: aload_0
       1: invokespecial #95                 // Method java/lang/Object."<init>":()V
       4: return

  public static void dumpContent(javax.mail.internet.MimeBodyPart, java.lang.String) throws javax.mail.MessagingException, java.io.IOException;
    Code:
       0: getstatic     #87                 // Field java/lang/System.out:Ljava/io/PrintStream;
       3: new           #53                 // class java/lang/StringBuilder
       6: dup
       7: invokespecial #96                 // Method java/lang/StringBuilder."<init>":()V
      10: ldc           #2                  // String content type:
      12: invokevirtual #98                 // Method java/lang/StringBuilder.append:(Ljava/lang/String;)Ljava/lang/StringBuilder;
      15: aload_0
      16: invokevirtual #103                // Method javax/mail/internet/MimeBodyPart.getContentType:()Ljava/lang/String;
      19: invokevirtual #98                 // Method java/lang/StringBuilder.append:(Ljava/lang/String;)Ljava/lang/StringBuilder;
      22: invokevirtual #97                 // Method java/lang/StringBuilder.toString:()Ljava/lang/String;
      25: invokevirtual #93                 // Method java/io/PrintStream.println:(Ljava/lang/String;)V
      28: new           #44                 // class java/io/FileOutputStream
      31: dup
      32: aload_1
      33: invokespecial #89                 // Method java/io/FileOutputStream."<init>":(Ljava/lang/String;)V
      36: astore_2
      37: aload_0
      38: invokevirtual #102                // Method javax/mail/internet/MimeBodyPart.getInputStream:()Ljava/io/InputStream;
      41: astore_3
      42: sipush        10000
      45: newarray       byte
      47: astore        4
      49: aload_3
      50: aload         4
      52: iconst_0
      53: aload         4
      55: arraylength
      56: invokevirtual #90                 // Method java/io/InputStream.read:([BII)I
      59: dup
      60: istore        5
      62: ifle          77
      65: aload_2
      66: aload         4
      68: iconst_0
      69: iload         5
      71: invokevirtual #92                 // Method java/io/OutputStream.write:([BII)V
      74: goto          49
      77: aload_2
      78: invokevirtual #91                 // Method java/io/OutputStream.close:()V
      81: return

  public static java.lang.String findKeyAlias(java.security.KeyStore, java.lang.String, char[]) throws java.lang.Exception;
    Code:
       0: aload_0
       1: new           #43                 // class java/io/FileInputStream
       4: dup
       5: aload_1
       6: invokespecial #88                 // Method java/io/FileInputStream."<init>":(Ljava/lang/String;)V
       9: aload_2
      10: invokevirtual #99                 // Method java/security/KeyStore.load:(Ljava/io/InputStream;[C)V
      13: aload_0
      14: invokevirtual #101                // Method java/security/KeyStore.aliases:()Ljava/util/Enumeration;
      17: astore_3
      18: aconst_null
      19: astore        4
      21: aload_3
      22: invokeinterface #104,  1          // InterfaceMethod java/util/Enumeration.hasMoreElements:()Z
      27: ifeq          57
      30: aload_3
      31: invokeinterface #105,  1          // InterfaceMethod java/util/Enumeration.nextElement:()Ljava/lang/Object;
      36: checkcast     #52                 // class java/lang/String
      39: astore        5
      41: aload_0
      42: aload         5
      44: invokevirtual #100                // Method java/security/KeyStore.isKeyEntry:(Ljava/lang/String;)Z
      47: ifeq          54
      50: aload         5
      52: astore        4
      54: goto          21
      57: aload         4
      59: ifnonnull     89
      62: new           #50                 // class java/lang/IllegalArgumentException
      65: dup
      66: new           #53                 // class java/lang/StringBuilder
      69: dup
      70: invokespecial #96                 // Method java/lang/StringBuilder."<init>":()V
      73: ldc           #1                  // String can\'t find a private key in keyStore:
      75: invokevirtual #98                 // Method java/lang/StringBuilder.append:(Ljava/lang/String;)Ljava/lang/StringBuilder;
      78: aload_1
      79: invokevirtual #98                 // Method java/lang/StringBuilder.append:(Ljava/lang/String;)Ljava/lang/StringBuilder;
      82: invokevirtual #97                 // Method java/lang/StringBuilder.toString:()Ljava/lang/String;
      85: invokespecial #94                 // Method java/lang/IllegalArgumentException."<init>":(Ljava/lang/String;)V
      88: athrow
      89: aload         4
      91: areturn
}
