Compiled from "ThreadPool.java"
public class org.apache.axis2.util.threadpool.ThreadPool implements org.apache.axis2.util.threadpool.ThreadFactory {
  private static final org.apache.commons.logging.Log log;

  protected static long SLEEP_INTERVAL;

  private static boolean shutDown;

  protected java.util.concurrent.ThreadPoolExecutor executor;

  private int corePoolSize;

  private int maxPoolSize;

  public org.apache.axis2.util.threadpool.ThreadPool();
    Code:
       0: aload_0
       1: invokespecial #2                  // Method java/lang/Object."<init>":()V
       4: aload_0
       5: iconst_5
       6: putfield      #3                  // Field corePoolSize:I
       9: aload_0
      10: bipush        100
      12: putfield      #4                  // Field maxPoolSize:I
      15: aload_0
      16: aload_0
      17: ldc           #5                  // String Axis2 Task
      19: iconst_5
      20: iconst_1
      21: invokevirtual #7                  // Method createDefaultExecutor:(Ljava/lang/String;IZ)Ljava/util/concurrent/ThreadPoolExecutor;
      24: invokevirtual #8                  // Method setExecutor:(Ljava/util/concurrent/ThreadPoolExecutor;)V
      27: return

  public org.apache.axis2.util.threadpool.ThreadPool(int, int);
    Code:
       0: aload_0
       1: invokespecial #2                  // Method java/lang/Object."<init>":()V
       4: aload_0
       5: iconst_5
       6: putfield      #3                  // Field corePoolSize:I
       9: aload_0
      10: bipush        100
      12: putfield      #4                  // Field maxPoolSize:I
      15: aload_0
      16: iload_1
      17: putfield      #3                  // Field corePoolSize:I
      20: aload_0
      21: iload_2
      22: putfield      #4                  // Field maxPoolSize:I
      25: aload_0
      26: aload_0
      27: ldc           #5                  // String Axis2 Task
      29: iconst_5
      30: iconst_1
      31: invokevirtual #7                  // Method createDefaultExecutor:(Ljava/lang/String;IZ)Ljava/util/concurrent/ThreadPoolExecutor;
      34: invokevirtual #8                  // Method setExecutor:(Ljava/util/concurrent/ThreadPoolExecutor;)V
      37: return

  public java.util.concurrent.Executor getExecutor();
    Code:
       0: aload_0
       1: getfield      #9                  // Field executor:Ljava/util/concurrent/ThreadPoolExecutor;
       4: areturn

  public void setExecutor(java.util.concurrent.ThreadPoolExecutor);
    Code:
       0: aload_0
       1: aload_1
       2: putfield      #9                  // Field executor:Ljava/util/concurrent/ThreadPoolExecutor;
       5: return

  public void execute(java.lang.Runnable);
    Code:
       0: getstatic     #10                 // Field shutDown:Z
       3: ifeq          19
       6: new           #11                 // class java/lang/RuntimeException
       9: dup
      10: ldc           #12                 // String threadpoolshutdown
      12: invokestatic  #13                 // Method org/apache/axis2/i18n/Messages.getMessage:(Ljava/lang/String;)Ljava/lang/String;
      15: invokespecial #14                 // Method java/lang/RuntimeException."<init>":(Ljava/lang/String;)V
      18: athrow
      19: aload_0
      20: getfield      #9                  // Field executor:Ljava/util/concurrent/ThreadPoolExecutor;
      23: aload_1
      24: invokevirtual #15                 // Method java/util/concurrent/ThreadPoolExecutor.execute:(Ljava/lang/Runnable;)V
      27: return

  public void forceShutDown();
    Code:
       0: getstatic     #1                  // Field log:Lorg/apache/commons/logging/Log;
       3: invokeinterface #16,  1           // InterfaceMethod org/apache/commons/logging/Log.isDebugEnabled:()Z
       8: ifeq          21
      11: getstatic     #1                  // Field log:Lorg/apache/commons/logging/Log;
      14: ldc           #17                 // String forceShutDown called. Thread workers will be stopped
      16: invokeinterface #18,  2           // InterfaceMethod org/apache/commons/logging/Log.debug:(Ljava/lang/Object;)V
      21: aload_0
      22: getfield      #9                  // Field executor:Ljava/util/concurrent/ThreadPoolExecutor;
      25: invokevirtual #19                 // Method java/util/concurrent/ThreadPoolExecutor.shutdownNow:()Ljava/util/List;
      28: pop
      29: return

  public void safeShutDown() throws org.apache.axis2.AxisFault;
    Code:
       0: aload_0
       1: dup
       2: astore_1
       3: monitorenter
       4: iconst_1
       5: putstatic     #10                 // Field shutDown:Z
       8: aload_1
       9: monitorexit
      10: goto          18
      13: astore_2
      14: aload_1
      15: monitorexit
      16: aload_2
      17: athrow
      18: aload_0
      19: getfield      #9                  // Field executor:Ljava/util/concurrent/ThreadPoolExecutor;
      22: invokevirtual #20                 // Method java/util/concurrent/ThreadPoolExecutor.shutdown:()V
      25: return
    Exception table:
       from    to  target type
           4    10    13   any
          13    16    13   any

  protected java.util.concurrent.ThreadPoolExecutor createDefaultExecutor(java.lang.String, int, boolean);
    Code:
       0: aload_0
       1: getfield      #4                  // Field maxPoolSize:I
       4: ldc           #22                 // int 2147483647
       6: if_icmpne     52
       9: new           #23                 // class java/util/concurrent/ThreadPoolExecutor
      12: dup
      13: aload_0
      14: getfield      #3                  // Field corePoolSize:I
      17: aload_0
      18: getfield      #4                  // Field maxPoolSize:I
      21: ldc2_w        #24                 // long 10l
      24: getstatic     #26                 // Field java/util/concurrent/TimeUnit.SECONDS:Ljava/util/concurrent/TimeUnit;
      27: new           #27                 // class java/util/concurrent/SynchronousQueue
      30: dup
      31: invokespecial #28                 // Method java/util/concurrent/SynchronousQueue."<init>":()V
      34: new           #29                 // class org/apache/axis2/util/threadpool/ThreadPool$DefaultThreadFactory
      37: dup
      38: aload_1
      39: iload_3
      40: iload_2
      41: invokespecial #30                 // Method org/apache/axis2/util/threadpool/ThreadPool$DefaultThreadFactory."<init>":(Ljava/lang/String;ZI)V
      44: invokespecial #31                 // Method java/util/concurrent/ThreadPoolExecutor."<init>":(IIJLjava/util/concurrent/TimeUnit;Ljava/util/concurrent/BlockingQueue;Ljava/util/concurrent/ThreadFactory;)V
      47: astore        4
      49: goto          92
      52: new           #23                 // class java/util/concurrent/ThreadPoolExecutor
      55: dup
      56: aload_0
      57: getfield      #3                  // Field corePoolSize:I
      60: aload_0
      61: getfield      #4                  // Field maxPoolSize:I
      64: ldc2_w        #24                 // long 10l
      67: getstatic     #26                 // Field java/util/concurrent/TimeUnit.SECONDS:Ljava/util/concurrent/TimeUnit;
      70: new           #32                 // class java/util/concurrent/LinkedBlockingQueue
      73: dup
      74: invokespecial #33                 // Method java/util/concurrent/LinkedBlockingQueue."<init>":()V
      77: new           #29                 // class org/apache/axis2/util/threadpool/ThreadPool$DefaultThreadFactory
      80: dup
      81: aload_1
      82: iload_3
      83: iload_2
      84: invokespecial #30                 // Method org/apache/axis2/util/threadpool/ThreadPool$DefaultThreadFactory."<init>":(Ljava/lang/String;ZI)V
      87: invokespecial #31                 // Method java/util/concurrent/ThreadPoolExecutor."<init>":(IIJLjava/util/concurrent/TimeUnit;Ljava/util/concurrent/BlockingQueue;Ljava/util/concurrent/ThreadFactory;)V
      90: astore        4
      92: aload         4
      94: areturn

  static org.apache.commons.logging.Log access$300();
    Code:
       0: getstatic     #1                  // Field log:Lorg/apache/commons/logging/Log;
       3: areturn

  static {};
    Code:
       0: ldc           #34                 // class org/apache/axis2/util/threadpool/ThreadPool
       2: invokestatic  #35                 // Method org/apache/commons/logging/LogFactory.getLog:(Ljava/lang/Class;)Lorg/apache/commons/logging/Log;
       5: putstatic     #1                  // Field log:Lorg/apache/commons/logging/Log;
       8: ldc2_w        #36                 // long 1000l
      11: putstatic     #38                 // Field SLEEP_INTERVAL:J
      14: return
}
