Compiled from "FlushingStreamWriter.java"
public class org.codehaus.groovy.runtime.FlushingStreamWriter extends java.io.OutputStreamWriter {
  public org.codehaus.groovy.runtime.FlushingStreamWriter(java.io.OutputStream);
    Code:
       0: aload_0
       1: aload_1
       2: invokespecial #9                  // Method java/io/OutputStreamWriter."<init>":(Ljava/io/OutputStream;)V
       5: return

  public void write(char[], int, int) throws java.io.IOException;
    Code:
       0: aload_0
       1: aload_1
       2: iload_2
       3: iload_3
       4: invokespecial #19                 // Method java/io/OutputStreamWriter.write:([CII)V
       7: aload_0
       8: invokevirtual #23                 // Method flush:()V
      11: return

  public void write(int) throws java.io.IOException;
    Code:
       0: aload_0
       1: iload_1
       2: invokespecial #31                 // Method java/io/OutputStreamWriter.write:(I)V
       5: aload_0
       6: invokevirtual #23                 // Method flush:()V
       9: return

  public void write(java.lang.String, int, int) throws java.io.IOException;
    Code:
       0: aload_0
       1: aload_1
       2: iload_2
       3: iload_3
       4: invokespecial #35                 // Method java/io/OutputStreamWriter.write:(Ljava/lang/String;II)V
       7: aload_0
       8: invokevirtual #23                 // Method flush:()V
      11: return
}
