Compiled from "GroovyCategorySupport.java"
class org.codehaus.groovy.runtime.GroovyCategorySupport$MyThreadLocal extends java.lang.ThreadLocal<java.lang.ref.SoftReference> {
  java.util.concurrent.ConcurrentHashMap<java.lang.String, java.util.concurrent.atomic.AtomicInteger> usage;

  private org.codehaus.groovy.runtime.GroovyCategorySupport$MyThreadLocal();
    Code:
       0: aload_0
       1: invokespecial #21                 // Method java/lang/ThreadLocal."<init>":()V
       4: aload_0
       5: new           #23                 // class java/util/concurrent/ConcurrentHashMap
       8: dup
       9: invokespecial #24                 // Method java/util/concurrent/ConcurrentHashMap."<init>":()V
      12: putfield      #26                 // Field usage:Ljava/util/concurrent/ConcurrentHashMap;
      15: return

  public org.codehaus.groovy.runtime.GroovyCategorySupport$ThreadCategoryInfo getInfo();
    Code:
       0: aload_0
       1: invokevirtual #34                 // Method get:()Ljava/lang/Object;
       4: checkcast     #36                 // class java/lang/ref/SoftReference
       7: astore_1
       8: aload_1
       9: ifnull        47
      12: aload_1
      13: invokevirtual #37                 // Method java/lang/ref/SoftReference.get:()Ljava/lang/Object;
      16: checkcast     #11                 // class org/codehaus/groovy/runtime/GroovyCategorySupport$ThreadCategoryInfo
      19: astore_2
      20: aload_2
      21: ifnonnull     67
      24: new           #11                 // class org/codehaus/groovy/runtime/GroovyCategorySupport$ThreadCategoryInfo
      27: dup
      28: invokespecial #38                 // Method org/codehaus/groovy/runtime/GroovyCategorySupport$ThreadCategoryInfo."<init>":()V
      31: astore_2
      32: aload_0
      33: new           #36                 // class java/lang/ref/SoftReference
      36: dup
      37: aload_2
      38: invokespecial #41                 // Method java/lang/ref/SoftReference."<init>":(Ljava/lang/Object;)V
      41: invokevirtual #44                 // Method set:(Ljava/lang/Object;)V
      44: goto          67
      47: new           #11                 // class org/codehaus/groovy/runtime/GroovyCategorySupport$ThreadCategoryInfo
      50: dup
      51: invokespecial #38                 // Method org/codehaus/groovy/runtime/GroovyCategorySupport$ThreadCategoryInfo."<init>":()V
      54: astore_2
      55: aload_0
      56: new           #36                 // class java/lang/ref/SoftReference
      59: dup
      60: aload_2
      61: invokespecial #41                 // Method java/lang/ref/SoftReference."<init>":(Ljava/lang/Object;)V
      64: invokevirtual #44                 // Method set:(Ljava/lang/Object;)V
      67: aload_2
      68: areturn

  public org.codehaus.groovy.runtime.GroovyCategorySupport$ThreadCategoryInfo getInfoNullable();
    Code:
       0: aload_0
       1: invokevirtual #34                 // Method get:()Ljava/lang/Object;
       4: checkcast     #36                 // class java/lang/ref/SoftReference
       7: astore_1
       8: aload_1
       9: ifnonnull     16
      12: aconst_null
      13: goto          23
      16: aload_1
      17: invokevirtual #37                 // Method java/lang/ref/SoftReference.get:()Ljava/lang/Object;
      20: checkcast     #11                 // class org/codehaus/groovy/runtime/GroovyCategorySupport$ThreadCategoryInfo
      23: areturn

  public java.util.concurrent.atomic.AtomicInteger getUsage(java.lang.String);
    Code:
       0: aload_0
       1: getfield      #26                 // Field usage:Ljava/util/concurrent/ConcurrentHashMap;
       4: aload_1
       5: invokevirtual #54                 // Method java/util/concurrent/ConcurrentHashMap.get:(Ljava/lang/Object;)Ljava/lang/Object;
       8: checkcast     #56                 // class java/util/concurrent/atomic/AtomicInteger
      11: astore_2
      12: aload_2
      13: ifnull        18
      16: aload_2
      17: areturn
      18: new           #56                 // class java/util/concurrent/atomic/AtomicInteger
      21: dup
      22: invokespecial #57                 // Method java/util/concurrent/atomic/AtomicInteger."<init>":()V
      25: astore_3
      26: aload_0
      27: getfield      #26                 // Field usage:Ljava/util/concurrent/ConcurrentHashMap;
      30: aload_1
      31: aload_3
      32: invokevirtual #61                 // Method java/util/concurrent/ConcurrentHashMap.putIfAbsent:(Ljava/lang/Object;Ljava/lang/Object;)Ljava/lang/Object;
      35: checkcast     #56                 // class java/util/concurrent/atomic/AtomicInteger
      38: astore        4
      40: aload         4
      42: ifnonnull     49
      45: aload_3
      46: goto          51
      49: aload         4
      51: areturn

  org.codehaus.groovy.runtime.GroovyCategorySupport$MyThreadLocal(org.codehaus.groovy.runtime.GroovyCategorySupport$1);
    Code:
       0: aload_0
       1: invokespecial #69                 // Method "<init>":()V
       4: return
}
