Compiled from "ScriptTestAdapter.java"
public class org.codehaus.groovy.runtime.ScriptTestAdapter implements junit.framework.Test {
  private java.lang.Class scriptClass;

  private java.lang.String[] arguments;

  public org.codehaus.groovy.runtime.ScriptTestAdapter(java.lang.Class, java.lang.String[]);
    Code:
       0: aload_0
       1: invokespecial #16                 // Method java/lang/Object."<init>":()V
       4: aload_0
       5: aload_1
       6: putfield      #18                 // Field scriptClass:Ljava/lang/Class;
       9: aload_0
      10: aload_2
      11: putfield      #20                 // Field arguments:[Ljava/lang/String;
      14: return

  public int countTestCases();
    Code:
       0: iconst_1
       1: ireturn

  public void run(junit.framework.TestResult);
    Code:
       0: aload_1
       1: aload_0
       2: invokevirtual #34                 // Method junit/framework/TestResult.startTest:(Ljunit/framework/Test;)V
       5: aload_0
       6: getfield      #18                 // Field scriptClass:Ljava/lang/Class;
       9: aload_0
      10: getfield      #20                 // Field arguments:[Ljava/lang/String;
      13: invokestatic  #40                 // Method org/codehaus/groovy/runtime/InvokerHelper.runScript:(Ljava/lang/Class;[Ljava/lang/String;)Ljava/lang/Object;
      16: pop
      17: aload_1
      18: aload_0
      19: invokevirtual #43                 // Method junit/framework/TestResult.endTest:(Ljunit/framework/Test;)V
      22: goto          32
      25: astore_2
      26: aload_1
      27: aload_0
      28: aload_2
      29: invokevirtual #47                 // Method junit/framework/TestResult.addError:(Ljunit/framework/Test;Ljava/lang/Throwable;)V
      32: return
    Exception table:
       from    to  target type
           0    22    25   Class java/lang/Exception

  public java.lang.String toString();
    Code:
       0: new           #55                 // class java/lang/StringBuilder
       3: dup
       4: invokespecial #56                 // Method java/lang/StringBuilder."<init>":()V
       7: ldc           #58                 // String TestCase for script:
       9: invokevirtual #62                 // Method java/lang/StringBuilder.append:(Ljava/lang/String;)Ljava/lang/StringBuilder;
      12: aload_0
      13: getfield      #18                 // Field scriptClass:Ljava/lang/Class;
      16: invokevirtual #67                 // Method java/lang/Class.getName:()Ljava/lang/String;
      19: invokevirtual #62                 // Method java/lang/StringBuilder.append:(Ljava/lang/String;)Ljava/lang/StringBuilder;
      22: invokevirtual #69                 // Method java/lang/StringBuilder.toString:()Ljava/lang/String;
      25: areturn
}
