Compiled from "SwingGroovyMethods.java"
public class org.codehaus.groovy.runtime.SwingGroovyMethods {
  public org.codehaus.groovy.runtime.SwingGroovyMethods();
    Code:
       0: aload_0
       1: invokespecial #23                 // Method java/lang/Object."<init>":()V
       4: return

  public static int size(java.awt.Container);
    Code:
       0: aload_0
       1: invokevirtual #33                 // Method java/awt/Container.getComponentCount:()I
       4: ireturn

  public static java.awt.Component getAt(java.awt.Container, int);
    Code:
       0: aload_0
       1: iload_1
       2: invokevirtual #41                 // Method java/awt/Container.getComponent:(I)Ljava/awt/Component;
       5: areturn

  public static java.awt.Container leftShift(java.awt.Container, java.awt.Component);
    Code:
       0: aload_0
       1: aload_1
       2: invokevirtual #49                 // Method java/awt/Container.add:(Ljava/awt/Component;)Ljava/awt/Component;
       5: pop
       6: aload_0
       7: areturn

  public static java.util.Iterator<java.awt.Component> iterator(java.awt.Container);
    Code:
       0: aload_0
       1: invokevirtual #57                 // Method java/awt/Container.getComponents:()[Ljava/awt/Component;
       4: invokestatic  #62                 // Method org/codehaus/groovy/runtime/DefaultGroovyMethods.iterator:([Ljava/lang/Object;)Ljava/util/Iterator;
       7: areturn

  public static void clear(java.awt.Container);
    Code:
       0: aload_0
       1: invokevirtual #67                 // Method java/awt/Container.removeAll:()V
       4: return

  public static int size(javax.swing.ButtonGroup);
    Code:
       0: aload_0
       1: invokevirtual #73                 // Method javax/swing/ButtonGroup.getButtonCount:()I
       4: ireturn

  public static javax.swing.AbstractButton getAt(javax.swing.ButtonGroup, int);
    Code:
       0: aload_0
       1: invokevirtual #73                 // Method javax/swing/ButtonGroup.getButtonCount:()I
       4: istore_2
       5: iload_1
       6: iflt          14
       9: iload_1
      10: iload_2
      11: if_icmplt     16
      14: aconst_null
      15: areturn
      16: aload_0
      17: invokevirtual #79                 // Method javax/swing/ButtonGroup.getElements:()Ljava/util/Enumeration;
      20: astore_3
      21: iconst_0
      22: istore        4
      24: iload         4
      26: iload_1
      27: if_icmpgt     56
      30: aload_3
      31: invokeinterface #85,  1           // InterfaceMethod java/util/Enumeration.nextElement:()Ljava/lang/Object;
      36: checkcast     #87                 // class javax/swing/AbstractButton
      39: astore        5
      41: iload         4
      43: iload_1
      44: if_icmpne     50
      47: aload         5
      49: areturn
      50: iinc          4, 1
      53: goto          24
      56: aconst_null
      57: areturn

  public static javax.swing.ButtonGroup leftShift(javax.swing.ButtonGroup, javax.swing.AbstractButton);
    Code:
       0: aload_0
       1: aload_1
       2: invokevirtual #96                 // Method javax/swing/ButtonGroup.add:(Ljavax/swing/AbstractButton;)V
       5: aload_0
       6: areturn

  public static java.util.Iterator<javax.swing.AbstractButton> iterator(javax.swing.ButtonGroup);
    Code:
       0: aload_0
       1: invokevirtual #79                 // Method javax/swing/ButtonGroup.getElements:()Ljava/util/Enumeration;
       4: invokestatic  #100                // Method org/codehaus/groovy/runtime/DefaultGroovyMethods.iterator:(Ljava/util/Enumeration;)Ljava/util/Iterator;
       7: areturn

  public static int size(javax.swing.ListModel);
    Code:
       0: aload_0
       1: invokeinterface #106,  1          // InterfaceMethod javax/swing/ListModel.getSize:()I
       6: ireturn

  public static java.lang.Object getAt(javax.swing.ListModel, int);
    Code:
       0: aload_0
       1: iload_1
       2: invokeinterface #112,  2          // InterfaceMethod javax/swing/ListModel.getElementAt:(I)Ljava/lang/Object;
       7: areturn

  public static java.util.Iterator iterator(javax.swing.ListModel);
    Code:
       0: new           #19                 // class org/codehaus/groovy/runtime/SwingGroovyMethods$1
       3: dup
       4: aload_0
       5: invokespecial #116                // Method org/codehaus/groovy/runtime/SwingGroovyMethods$1."<init>":(Ljavax/swing/ListModel;)V
       8: areturn

  public static javax.swing.DefaultListModel leftShift(javax.swing.DefaultListModel, java.lang.Object);
    Code:
       0: aload_0
       1: aload_1
       2: invokevirtual #123                // Method javax/swing/DefaultListModel.addElement:(Ljava/lang/Object;)V
       5: aload_0
       6: areturn

  public static void putAt(javax.swing.DefaultListModel, int, java.lang.Object);
    Code:
       0: aload_0
       1: iload_1
       2: aload_2
       3: invokevirtual #132                // Method javax/swing/DefaultListModel.set:(ILjava/lang/Object;)Ljava/lang/Object;
       6: pop
       7: return

  public static void clear(javax.swing.DefaultListModel);
    Code:
       0: aload_0
       1: invokevirtual #136                // Method javax/swing/DefaultListModel.removeAllElements:()V
       4: return

  public static java.util.Iterator iterator(javax.swing.DefaultListModel);
    Code:
       0: new           #17                 // class org/codehaus/groovy/runtime/SwingGroovyMethods$2
       3: dup
       4: aload_0
       5: invokespecial #139                // Method org/codehaus/groovy/runtime/SwingGroovyMethods$2."<init>":(Ljavax/swing/DefaultListModel;)V
       8: areturn

  public static int size(javax.swing.JComboBox);
    Code:
       0: aload_0
       1: invokevirtual #145                // Method javax/swing/JComboBox.getItemCount:()I
       4: ireturn

  public static java.lang.Object getAt(javax.swing.JComboBox, int);
    Code:
       0: aload_0
       1: iload_1
       2: invokevirtual #150                // Method javax/swing/JComboBox.getItemAt:(I)Ljava/lang/Object;
       5: areturn

  public static javax.swing.JComboBox leftShift(javax.swing.JComboBox, java.lang.Object);
    Code:
       0: aload_0
       1: aload_1
       2: invokevirtual #154                // Method javax/swing/JComboBox.addItem:(Ljava/lang/Object;)V
       5: aload_0
       6: areturn

  public static void clear(javax.swing.JComboBox);
    Code:
       0: aload_0
       1: invokevirtual #158                // Method javax/swing/JComboBox.removeAllItems:()V
       4: return

  public static java.util.Iterator iterator(javax.swing.JComboBox);
    Code:
       0: aload_0
       1: invokevirtual #163                // Method javax/swing/JComboBox.getModel:()Ljavax/swing/ComboBoxModel;
       4: invokestatic  #165                // Method iterator:(Ljavax/swing/ListModel;)Ljava/util/Iterator;
       7: areturn

  public static javax.swing.MutableComboBoxModel leftShift(javax.swing.MutableComboBoxModel, java.lang.Object);
    Code:
       0: aload_0
       1: aload_1
       2: invokeinterface #169,  2          // InterfaceMethod javax/swing/MutableComboBoxModel.addElement:(Ljava/lang/Object;)V
       7: aload_0
       8: areturn

  public static void putAt(javax.swing.MutableComboBoxModel, int, java.lang.Object);
    Code:
       0: aload_0
       1: aload_2
       2: iload_1
       3: invokeinterface #175,  3          // InterfaceMethod javax/swing/MutableComboBoxModel.insertElementAt:(Ljava/lang/Object;I)V
       8: return

  public static java.util.Iterator iterator(javax.swing.MutableComboBoxModel);
    Code:
       0: new           #15                 // class org/codehaus/groovy/runtime/SwingGroovyMethods$3
       3: dup
       4: aload_0
       5: invokespecial #179                // Method org/codehaus/groovy/runtime/SwingGroovyMethods$3."<init>":(Ljavax/swing/MutableComboBoxModel;)V
       8: areturn

  public static void clear(javax.swing.DefaultComboBoxModel);
    Code:
       0: aload_0
       1: invokevirtual #183                // Method javax/swing/DefaultComboBoxModel.removeAllElements:()V
       4: return

  public static int size(javax.swing.table.TableModel);
    Code:
       0: aload_0
       1: invokeinterface #190,  1          // InterfaceMethod javax/swing/table/TableModel.getRowCount:()I
       6: ireturn

  public static java.lang.Object[] getAt(javax.swing.table.TableModel, int);
    Code:
       0: aload_0
       1: invokeinterface #195,  1          // InterfaceMethod javax/swing/table/TableModel.getColumnCount:()I
       6: istore_2
       7: iload_2
       8: anewarray     #4                  // class java/lang/Object
      11: astore_3
      12: iconst_0
      13: istore        4
      15: iload         4
      17: iload_2
      18: if_icmpge     40
      21: aload_3
      22: iload         4
      24: aload_0
      25: iload_1
      26: iload         4
      28: invokeinterface #201,  3          // InterfaceMethod javax/swing/table/TableModel.getValueAt:(II)Ljava/lang/Object;
      33: aastore
      34: iinc          4, 1
      37: goto          15
      40: aload_3
      41: areturn

  public static java.util.Iterator iterator(javax.swing.table.TableModel);
    Code:
       0: new           #13                 // class org/codehaus/groovy/runtime/SwingGroovyMethods$4
       3: dup
       4: aload_0
       5: invokespecial #208                // Method org/codehaus/groovy/runtime/SwingGroovyMethods$4."<init>":(Ljavax/swing/table/TableModel;)V
       8: areturn

  public static javax.swing.table.DefaultTableModel leftShift(javax.swing.table.DefaultTableModel, java.lang.Object);
    Code:
       0: aload_1
       1: ifnonnull     14
       4: aload_0
       5: aconst_null
       6: checkcast     #197                // class "[Ljava/lang/Object;"
       9: invokevirtual #215                // Method javax/swing/table/DefaultTableModel.addRow:([Ljava/lang/Object;)V
      12: aload_0
      13: areturn
      14: aload_0
      15: aload_0
      16: aload_1
      17: invokestatic  #219                // Method buildRowData:(Ljavax/swing/table/DefaultTableModel;Ljava/lang/Object;)[Ljava/lang/Object;
      20: invokevirtual #215                // Method javax/swing/table/DefaultTableModel.addRow:([Ljava/lang/Object;)V
      23: aload_0
      24: areturn

  public static void putAt(javax.swing.table.DefaultTableModel, int, java.lang.Object);
    Code:
       0: aload_2
       1: ifnonnull     14
       4: aload_0
       5: iload_1
       6: aconst_null
       7: checkcast     #197                // class "[Ljava/lang/Object;"
      10: invokevirtual #226                // Method javax/swing/table/DefaultTableModel.insertRow:(I[Ljava/lang/Object;)V
      13: return
      14: aload_0
      15: iload_1
      16: aload_0
      17: aload_2
      18: invokestatic  #219                // Method buildRowData:(Ljavax/swing/table/DefaultTableModel;Ljava/lang/Object;)[Ljava/lang/Object;
      21: invokevirtual #226                // Method javax/swing/table/DefaultTableModel.insertRow:(I[Ljava/lang/Object;)V
      24: return

  private static java.lang.Object[] buildRowData(javax.swing.table.DefaultTableModel, java.lang.Object);
    Code:
       0: aload_0
       1: invokevirtual #227                // Method javax/swing/table/DefaultTableModel.getColumnCount:()I
       4: istore_2
       5: iload_2
       6: anewarray     #4                  // class java/lang/Object
       9: astore_3
      10: iconst_0
      11: istore        4
      13: aload_1
      14: invokestatic  #230                // Method org/codehaus/groovy/runtime/DefaultGroovyMethods.iterator:(Ljava/lang/Object;)Ljava/util/Iterator;
      17: astore        5
      19: aload         5
      21: invokeinterface #236,  1          // InterfaceMethod java/util/Iterator.hasNext:()Z
      26: ifeq          52
      29: iload         4
      31: iload_2
      32: if_icmpge     52
      35: aload_3
      36: iload         4
      38: iinc          4, 1
      41: aload         5
      43: invokeinterface #239,  1          // InterfaceMethod java/util/Iterator.next:()Ljava/lang/Object;
      48: aastore
      49: goto          19
      52: aload_3
      53: areturn

  public static java.util.Iterator iterator(javax.swing.table.DefaultTableModel);
    Code:
       0: new           #11                 // class org/codehaus/groovy/runtime/SwingGroovyMethods$5
       3: dup
       4: aload_0
       5: invokespecial #246                // Method org/codehaus/groovy/runtime/SwingGroovyMethods$5."<init>":(Ljavax/swing/table/DefaultTableModel;)V
       8: areturn

  public static int size(javax.swing.table.TableColumnModel);
    Code:
       0: aload_0
       1: invokeinterface #250,  1          // InterfaceMethod javax/swing/table/TableColumnModel.getColumnCount:()I
       6: ireturn

  public static javax.swing.table.TableColumn getAt(javax.swing.table.TableColumnModel, int);
    Code:
       0: aload_0
       1: iload_1
       2: invokeinterface #256,  2          // InterfaceMethod javax/swing/table/TableColumnModel.getColumn:(I)Ljavax/swing/table/TableColumn;
       7: areturn

  public static java.util.Iterator<javax.swing.table.TableColumn> iterator(javax.swing.table.TableColumnModel);
    Code:
       0: new           #9                  // class org/codehaus/groovy/runtime/SwingGroovyMethods$6
       3: dup
       4: aload_0
       5: invokespecial #260                // Method org/codehaus/groovy/runtime/SwingGroovyMethods$6."<init>":(Ljavax/swing/table/TableColumnModel;)V
       8: areturn

  public static javax.swing.table.TableColumnModel leftShift(javax.swing.table.TableColumnModel, javax.swing.table.TableColumn);
    Code:
       0: aload_0
       1: aload_1
       2: invokeinterface #265,  2          // InterfaceMethod javax/swing/table/TableColumnModel.addColumn:(Ljavax/swing/table/TableColumn;)V
       7: aload_0
       8: areturn

  public static int size(javax.swing.tree.TreePath);
    Code:
       0: aload_0
       1: invokevirtual #273                // Method javax/swing/tree/TreePath.getPathCount:()I
       4: ireturn

  public static java.lang.Object getAt(javax.swing.tree.TreePath, int);
    Code:
       0: aload_0
       1: invokevirtual #279                // Method javax/swing/tree/TreePath.getPath:()[Ljava/lang/Object;
       4: iload_1
       5: aaload
       6: areturn

  public static javax.swing.tree.TreePath leftShift(javax.swing.tree.TreePath, java.lang.Object);
    Code:
       0: aload_0
       1: aload_1
       2: invokevirtual #284                // Method javax/swing/tree/TreePath.pathByAddingChild:(Ljava/lang/Object;)Ljavax/swing/tree/TreePath;
       5: areturn

  public static java.util.Iterator iterator(javax.swing.tree.TreePath);
    Code:
       0: aload_0
       1: invokevirtual #279                // Method javax/swing/tree/TreePath.getPath:()[Ljava/lang/Object;
       4: invokestatic  #62                 // Method org/codehaus/groovy/runtime/DefaultGroovyMethods.iterator:([Ljava/lang/Object;)Ljava/util/Iterator;
       7: areturn

  public static int size(javax.swing.tree.TreeNode);
    Code:
       0: aload_0
       1: invokeinterface #292,  1          // InterfaceMethod javax/swing/tree/TreeNode.getChildCount:()I
       6: ireturn

  public static javax.swing.tree.TreeNode getAt(javax.swing.tree.TreeNode, int);
    Code:
       0: aload_0
       1: iload_1
       2: invokeinterface #298,  2          // InterfaceMethod javax/swing/tree/TreeNode.getChildAt:(I)Ljavax/swing/tree/TreeNode;
       7: areturn

  public static java.util.Iterator<javax.swing.tree.TreeNode> iterator(javax.swing.tree.TreeNode);
    Code:
       0: aload_0
       1: invokeinterface #302,  1          // InterfaceMethod javax/swing/tree/TreeNode.children:()Ljava/util/Enumeration;
       6: invokestatic  #100                // Method org/codehaus/groovy/runtime/DefaultGroovyMethods.iterator:(Ljava/util/Enumeration;)Ljava/util/Iterator;
       9: areturn

  public static javax.swing.tree.MutableTreeNode leftShift(javax.swing.tree.MutableTreeNode, javax.swing.tree.MutableTreeNode);
    Code:
       0: aload_0
       1: aload_1
       2: aload_0
       3: invokeinterface #306,  1          // InterfaceMethod javax/swing/tree/MutableTreeNode.getChildCount:()I
       8: invokeinterface #310,  3          // InterfaceMethod javax/swing/tree/MutableTreeNode.insert:(Ljavax/swing/tree/MutableTreeNode;I)V
      13: aload_0
      14: areturn

  public static void putAt(javax.swing.tree.MutableTreeNode, int, javax.swing.tree.MutableTreeNode);
    Code:
       0: aload_0
       1: aload_2
       2: iload_1
       3: invokeinterface #310,  3          // InterfaceMethod javax/swing/tree/MutableTreeNode.insert:(Ljavax/swing/tree/MutableTreeNode;I)V
       8: return

  public static javax.swing.tree.DefaultMutableTreeNode leftShift(javax.swing.tree.DefaultMutableTreeNode, javax.swing.tree.DefaultMutableTreeNode);
    Code:
       0: aload_0
       1: aload_1
       2: invokevirtual #319                // Method javax/swing/tree/DefaultMutableTreeNode.add:(Ljavax/swing/tree/MutableTreeNode;)V
       5: aload_0
       6: areturn

  public static void clear(javax.swing.tree.DefaultMutableTreeNode);
    Code:
       0: aload_0
       1: invokevirtual #324                // Method javax/swing/tree/DefaultMutableTreeNode.removeAllChildren:()V
       4: return

  public static int size(javax.swing.JMenu);
    Code:
       0: aload_0
       1: invokevirtual #330                // Method javax/swing/JMenu.getMenuComponentCount:()I
       4: ireturn

  public static java.awt.Component getAt(javax.swing.JMenu, int);
    Code:
       0: aload_0
       1: iload_1
       2: invokevirtual #335                // Method javax/swing/JMenu.getMenuComponent:(I)Ljava/awt/Component;
       5: areturn

  public static javax.swing.JMenu leftShift(javax.swing.JMenu, javax.swing.Action);
    Code:
       0: aload_0
       1: aload_1
       2: invokevirtual #339                // Method javax/swing/JMenu.add:(Ljavax/swing/Action;)Ljavax/swing/JMenuItem;
       5: pop
       6: aload_0
       7: areturn

  public static javax.swing.JMenu leftShift(javax.swing.JMenu, java.awt.Component);
    Code:
       0: aload_0
       1: aload_1
       2: invokevirtual #343                // Method javax/swing/JMenu.add:(Ljava/awt/Component;)Ljava/awt/Component;
       5: pop
       6: aload_0
       7: areturn

  public static javax.swing.JMenu leftShift(javax.swing.JMenu, javax.swing.JMenuItem);
    Code:
       0: aload_0
       1: aload_1
       2: invokevirtual #348                // Method javax/swing/JMenu.add:(Ljavax/swing/JMenuItem;)Ljavax/swing/JMenuItem;
       5: pop
       6: aload_0
       7: areturn

  public static javax.swing.JMenu leftShift(javax.swing.JMenu, java.lang.String);
    Code:
       0: aload_0
       1: aload_1
       2: invokevirtual #354                // Method javax/swing/JMenu.add:(Ljava/lang/String;)Ljavax/swing/JMenuItem;
       5: pop
       6: aload_0
       7: areturn

  public static javax.swing.JMenu leftShift(javax.swing.JMenu, groovy.lang.GString);
    Code:
       0: aload_0
       1: aload_1
       2: invokevirtual #363                // Method groovy/lang/GString.toString:()Ljava/lang/String;
       5: invokevirtual #354                // Method javax/swing/JMenu.add:(Ljava/lang/String;)Ljavax/swing/JMenuItem;
       8: pop
       9: aload_0
      10: areturn

  public static java.util.Iterator iterator(javax.swing.JMenu);
    Code:
       0: aload_0
       1: invokevirtual #369                // Method javax/swing/JMenu.getMenuComponents:()[Ljava/awt/Component;
       4: invokestatic  #62                 // Method org/codehaus/groovy/runtime/DefaultGroovyMethods.iterator:([Ljava/lang/Object;)Ljava/util/Iterator;
       7: areturn

  public static int size(javax.swing.JMenuBar);
    Code:
       0: aload_0
       1: invokevirtual #375                // Method javax/swing/JMenuBar.getMenuCount:()I
       4: ireturn

  public static javax.swing.JMenu getAt(javax.swing.JMenuBar, int);
    Code:
       0: aload_0
       1: iload_1
       2: invokevirtual #381                // Method javax/swing/JMenuBar.getMenu:(I)Ljavax/swing/JMenu;
       5: areturn

  public static javax.swing.JMenuBar leftShift(javax.swing.JMenuBar, javax.swing.JMenu);
    Code:
       0: aload_0
       1: aload_1
       2: invokevirtual #385                // Method javax/swing/JMenuBar.add:(Ljavax/swing/JMenu;)Ljavax/swing/JMenu;
       5: pop
       6: aload_0
       7: areturn

  public static java.util.Iterator iterator(javax.swing.JMenuBar);
    Code:
       0: aload_0
       1: invokevirtual #391                // Method javax/swing/JMenuBar.getSubElements:()[Ljavax/swing/MenuElement;
       4: invokestatic  #62                 // Method org/codehaus/groovy/runtime/DefaultGroovyMethods.iterator:([Ljava/lang/Object;)Ljava/util/Iterator;
       7: areturn

  public static javax.swing.JPopupMenu leftShift(javax.swing.JPopupMenu, javax.swing.Action);
    Code:
       0: aload_0
       1: aload_1
       2: invokevirtual #395                // Method javax/swing/JPopupMenu.add:(Ljavax/swing/Action;)Ljavax/swing/JMenuItem;
       5: pop
       6: aload_0
       7: areturn

  public static javax.swing.JPopupMenu leftShift(javax.swing.JPopupMenu, java.awt.Component);
    Code:
       0: aload_0
       1: aload_1
       2: invokevirtual #398                // Method javax/swing/JPopupMenu.add:(Ljava/awt/Component;)Ljava/awt/Component;
       5: pop
       6: aload_0
       7: areturn

  public static javax.swing.JPopupMenu leftShift(javax.swing.JPopupMenu, javax.swing.JMenuItem);
    Code:
       0: aload_0
       1: aload_1
       2: invokevirtual #400                // Method javax/swing/JPopupMenu.add:(Ljavax/swing/JMenuItem;)Ljavax/swing/JMenuItem;
       5: pop
       6: aload_0
       7: areturn

  public static javax.swing.JPopupMenu leftShift(javax.swing.JPopupMenu, java.lang.String);
    Code:
       0: aload_0
       1: aload_1
       2: invokevirtual #402                // Method javax/swing/JPopupMenu.add:(Ljava/lang/String;)Ljavax/swing/JMenuItem;
       5: pop
       6: aload_0
       7: areturn

  public static javax.swing.JPopupMenu leftShift(javax.swing.JPopupMenu, groovy.lang.GString);
    Code:
       0: aload_0
       1: aload_1
       2: invokevirtual #363                // Method groovy/lang/GString.toString:()Ljava/lang/String;
       5: invokevirtual #402                // Method javax/swing/JPopupMenu.add:(Ljava/lang/String;)Ljavax/swing/JMenuItem;
       8: pop
       9: aload_0
      10: areturn

  public static java.util.Iterator<javax.swing.MenuElement> iterator(javax.swing.JPopupMenu);
    Code:
       0: aload_0
       1: invokevirtual #405                // Method javax/swing/JPopupMenu.getSubElements:()[Ljavax/swing/MenuElement;
       4: invokestatic  #62                 // Method org/codehaus/groovy/runtime/DefaultGroovyMethods.iterator:([Ljava/lang/Object;)Ljava/util/Iterator;
       7: areturn

  public static int size(javax.swing.JTabbedPane);
    Code:
       0: aload_0
       1: invokevirtual #411                // Method javax/swing/JTabbedPane.getTabCount:()I
       4: ireturn

  public static void clear(javax.swing.JTabbedPane);
    Code:
       0: aload_0
       1: invokevirtual #414                // Method javax/swing/JTabbedPane.removeAll:()V
       4: return

  public static java.awt.Component getAt(javax.swing.JTabbedPane, int);
    Code:
       0: aload_0
       1: iload_1
       2: invokevirtual #418                // Method javax/swing/JTabbedPane.getComponentAt:(I)Ljava/awt/Component;
       5: areturn

  public static java.util.Iterator<java.awt.Component> iterator(javax.swing.JTabbedPane);
    Code:
       0: new           #7                  // class org/codehaus/groovy/runtime/SwingGroovyMethods$7
       3: dup
       4: aload_0
       5: invokespecial #421                // Method org/codehaus/groovy/runtime/SwingGroovyMethods$7."<init>":(Ljavax/swing/JTabbedPane;)V
       8: areturn

  public static javax.swing.JToolBar leftShift(javax.swing.JToolBar, javax.swing.Action);
    Code:
       0: aload_0
       1: aload_1
       2: invokevirtual #427                // Method javax/swing/JToolBar.add:(Ljavax/swing/Action;)Ljavax/swing/JButton;
       5: pop
       6: aload_0
       7: areturn

  public static java.awt.Component getAt(javax.swing.JToolBar, int);
    Code:
       0: aload_0
       1: iload_1
       2: invokevirtual #432                // Method javax/swing/JToolBar.getComponentAtIndex:(I)Ljava/awt/Component;
       5: areturn

  public static void setMnemonic(javax.swing.AbstractButton, java.lang.String);
    Code:
       0: aload_1
       1: invokestatic  #440                // Method org/codehaus/groovy/runtime/typehandling/ShortTypeHandling.castToChar:(Ljava/lang/Object;)Ljava/lang/Character;
       4: invokevirtual #446                // Method java/lang/Character.charValue:()C
       7: istore_2
       8: aload_0
       9: iload_2
      10: invokevirtual #449                // Method javax/swing/AbstractButton.setMnemonic:(C)V
      13: return
}
