Compiled from "CommandLineUtils.java"
class org.codehaus.plexus.util.cli.CommandLineUtils$ProcessHook extends java.lang.Thread {
  private final java.lang.Process process;

  private org.codehaus.plexus.util.cli.CommandLineUtils$ProcessHook(java.lang.Process);
    Code:
       0: aload_0
       1: ldc           #2                  // String CommandlineUtils process shutdown hook
       3: invokespecial #3                  // Method java/lang/Thread."<init>":(Ljava/lang/String;)V
       6: aload_0
       7: aload_1
       8: putfield      #4                  // Field process:Ljava/lang/Process;
      11: aload_0
      12: aconst_null
      13: invokevirtual #5                  // Method setContextClassLoader:(Ljava/lang/ClassLoader;)V
      16: return

  public void run();
    Code:
       0: aload_0
       1: getfield      #4                  // Field process:Ljava/lang/Process;
       4: invokevirtual #6                  // Method java/lang/Process.destroy:()V
       7: return

  org.codehaus.plexus.util.cli.CommandLineUtils$ProcessHook(java.lang.Process, org.codehaus.plexus.util.cli.CommandLineUtils$1);
    Code:
       0: aload_0
       1: aload_1
       2: invokespecial #1                  // Method "<init>":(Ljava/lang/Process;)V
       5: return
}
