Compiled from "Step.scala"
public abstract class es.weso.shapepath.Step {
  public static es.weso.shapepath.Step mkStep(scala.Option<es.weso.shapepath.Axis>, es.weso.shapepath.NodeTest);
    Code:
       0: getstatic     #19                 // Field es/weso/shapepath/Step$.MODULE$:Les/weso/shapepath/Step$;
       3: aload_0
       4: aload_1
       5: invokevirtual #21                 // Method es/weso/shapepath/Step$.mkStep:(Lscala/Option;Les/weso/shapepath/NodeTest;)Les/weso/shapepath/Step;
       8: areturn

  public static es.weso.shapepath.Step fromShapeLabel(es.weso.rdf.nodes.IRI);
    Code:
       0: getstatic     #19                 // Field es/weso/shapepath/Step$.MODULE$:Les/weso/shapepath/Step$;
       3: aload_0
       4: invokevirtual #26                 // Method es/weso/shapepath/Step$.fromShapeLabel:(Les/weso/rdf/nodes/IRI;)Les/weso/shapepath/Step;
       7: areturn

  public static es.weso.shapepath.Step fromIRI(es.weso.rdf.nodes.IRI);
    Code:
       0: getstatic     #19                 // Field es/weso/shapepath/Step$.MODULE$:Les/weso/shapepath/Step$;
       3: aload_0
       4: invokevirtual #30                 // Method es/weso/shapepath/Step$.fromIRI:(Les/weso/rdf/nodes/IRI;)Les/weso/shapepath/Step;
       7: areturn

  public static cats.Show<es.weso.shapepath.Step> stepShow();
    Code:
       0: getstatic     #19                 // Field es/weso/shapepath/Step$.MODULE$:Les/weso/shapepath/Step$;
       3: invokevirtual #35                 // Method es/weso/shapepath/Step$.stepShow:()Lcats/Show;
       6: areturn

  public abstract java.lang.String showQualify(es.weso.rdf.PrefixMap);

  public abstract es.weso.shapepath.Step addPredicates(scala.collection.immutable.List<es.weso.shapepath.Predicate>);

  public es.weso.shapepath.Step();
    Code:
       0: aload_0
       1: invokespecial #46                 // Method java/lang/Object."<init>":()V
       4: return
}
