Compiled from "ShapeNode.scala"
public class es.weso.shapepath.TripleExprItem extends es.weso.shapepath.ShapeNode implements scala.Product,scala.Serializable {
  private final es.weso.shex.TripleExpr te;

  public static scala.Option<es.weso.shex.TripleExpr> unapply(es.weso.shapepath.TripleExprItem);
    Code:
       0: getstatic     #24                 // Field es/weso/shapepath/TripleExprItem$.MODULE$:Les/weso/shapepath/TripleExprItem$;
       3: aload_0
       4: invokevirtual #26                 // Method es/weso/shapepath/TripleExprItem$.unapply:(Les/weso/shapepath/TripleExprItem;)Lscala/Option;
       7: areturn

  public static es.weso.shapepath.TripleExprItem apply(es.weso.shex.TripleExpr);
    Code:
       0: getstatic     #24                 // Field es/weso/shapepath/TripleExprItem$.MODULE$:Les/weso/shapepath/TripleExprItem$;
       3: aload_0
       4: invokevirtual #30                 // Method es/weso/shapepath/TripleExprItem$.apply:(Les/weso/shex/TripleExpr;)Les/weso/shapepath/TripleExprItem;
       7: areturn

  public static <A> scala.Function1<es.weso.shex.TripleExpr, A> andThen(scala.Function1<es.weso.shapepath.TripleExprItem, A>);
    Code:
       0: getstatic     #24                 // Field es/weso/shapepath/TripleExprItem$.MODULE$:Les/weso/shapepath/TripleExprItem$;
       3: aload_0
       4: invokevirtual #36                 // Method es/weso/shapepath/TripleExprItem$.andThen:(Lscala/Function1;)Lscala/Function1;
       7: areturn

  public static <A> scala.Function1<A, es.weso.shapepath.TripleExprItem> compose(scala.Function1<A, es.weso.shex.TripleExpr>);
    Code:
       0: getstatic     #24                 // Field es/weso/shapepath/TripleExprItem$.MODULE$:Les/weso/shapepath/TripleExprItem$;
       3: aload_0
       4: invokevirtual #40                 // Method es/weso/shapepath/TripleExprItem$.compose:(Lscala/Function1;)Lscala/Function1;
       7: areturn

  public es.weso.shex.TripleExpr te();
    Code:
       0: aload_0
       1: getfield      #43                 // Field te:Les/weso/shex/TripleExpr;
       4: areturn

  public boolean hasLabel(es.weso.shex.ShapeLabel);
    Code:
       0: aload_0
       1: invokevirtual #50                 // Method te:()Les/weso/shex/TripleExpr;
       4: invokeinterface #56,  1           // InterfaceMethod es/weso/shex/TripleExpr.id:()Lscala/Option;
       9: astore_3
      10: getstatic     #61                 // Field scala/None$.MODULE$:Lscala/None$;
      13: aload_3
      14: invokevirtual #67                 // Method java/lang/Object.equals:(Ljava/lang/Object;)Z
      17: ifeq          25
      20: iconst_0
      21: istore_2
      22: goto          98
      25: goto          28
      28: aload_3
      29: instanceof    #69                 // class scala/Some
      32: ifeq          86
      35: aload_3
      36: checkcast     #69                 // class scala/Some
      39: astore        4
      41: aload         4
      43: invokevirtual #73                 // Method scala/Some.value:()Ljava/lang/Object;
      46: checkcast     #75                 // class es/weso/shex/ShapeLabel
      49: astore        5
      51: aload         5
      53: aload_1
      54: astore        6
      56: dup
      57: ifnonnull     69
      60: pop
      61: aload         6
      63: ifnull        77
      66: goto          81
      69: aload         6
      71: invokevirtual #67                 // Method java/lang/Object.equals:(Ljava/lang/Object;)Z
      74: ifeq          81
      77: iconst_1
      78: goto          82
      81: iconst_0
      82: istore_2
      83: goto          98
      86: goto          89
      89: new           #77                 // class scala/MatchError
      92: dup
      93: aload_3
      94: invokespecial #81                 // Method scala/MatchError."<init>":(Ljava/lang/Object;)V
      97: athrow
      98: iload_2
      99: ireturn

  public scala.Option<es.weso.shex.TripleExpr> getTripleExprByLabel(es.weso.shex.ShapeLabel, scala.Option<java.lang.Object>);
    Code:
       0: new           #69                 // class scala/Some
       3: dup
       4: aload_0
       5: invokevirtual #50                 // Method te:()Les/weso/shex/TripleExpr;
       8: invokespecial #90                 // Method scala/Some."<init>":(Ljava/lang/Object;)V
      11: areturn

  public es.weso.shapepath.ShapeNodeType _type();
    Code:
       0: getstatic     #98                 // Field es/weso/shapepath/TripleExprType$.MODULE$:Les/weso/shapepath/TripleExprType$;
       3: areturn

  public es.weso.shapepath.TripleExprItem copy(es.weso.shex.TripleExpr);
    Code:
       0: new           #2                  // class es/weso/shapepath/TripleExprItem
       3: dup
       4: aload_1
       5: invokespecial #102                // Method "<init>":(Les/weso/shex/TripleExpr;)V
       8: areturn

  public es.weso.shex.TripleExpr copy$default$1();
    Code:
       0: aload_0
       1: invokevirtual #50                 // Method te:()Les/weso/shex/TripleExpr;
       4: areturn

  public java.lang.String productPrefix();
    Code:
       0: ldc           #107                // String TripleExprItem
       2: areturn

  public int productArity();
    Code:
       0: iconst_1
       1: ireturn

  public java.lang.Object productElement(int);
    Code:
       0: iload_1
       1: istore_2
       2: iload_2
       3: tableswitch   { // 0 to 0
                     0: 20
               default: 27
          }
      20: aload_0
      21: invokevirtual #50                 // Method te:()Les/weso/shex/TripleExpr;
      24: goto          39
      27: new           #114                // class java/lang/IndexOutOfBoundsException
      30: dup
      31: iload_1
      32: invokestatic  #120                // Method java/lang/Integer.toString:(I)Ljava/lang/String;
      35: invokespecial #123                // Method java/lang/IndexOutOfBoundsException."<init>":(Ljava/lang/String;)V
      38: athrow
      39: areturn

  public scala.collection.Iterator<java.lang.Object> productIterator();
    Code:
       0: getstatic     #132                // Field scala/runtime/ScalaRunTime$.MODULE$:Lscala/runtime/ScalaRunTime$;
       3: aload_0
       4: invokevirtual #136                // Method scala/runtime/ScalaRunTime$.typedProductIterator:(Lscala/Product;)Lscala/collection/Iterator;
       7: areturn

  public boolean canEqual(java.lang.Object);
    Code:
       0: aload_1
       1: instanceof    #2                  // class es/weso/shapepath/TripleExprItem
       4: ireturn

  public int hashCode();
    Code:
       0: getstatic     #132                // Field scala/runtime/ScalaRunTime$.MODULE$:Lscala/runtime/ScalaRunTime$;
       3: aload_0
       4: invokevirtual #143                // Method scala/runtime/ScalaRunTime$._hashCode:(Lscala/Product;)I
       7: ireturn

  public java.lang.String toString();
    Code:
       0: getstatic     #132                // Field scala/runtime/ScalaRunTime$.MODULE$:Lscala/runtime/ScalaRunTime$;
       3: aload_0
       4: invokevirtual #147                // Method scala/runtime/ScalaRunTime$._toString:(Lscala/Product;)Ljava/lang/String;
       7: areturn

  public boolean equals(java.lang.Object);
    Code:
       0: aload_0
       1: aload_1
       2: if_acmpeq     86
       5: aload_1
       6: astore_3
       7: aload_3
       8: instanceof    #2                  // class es/weso/shapepath/TripleExprItem
      11: ifeq          19
      14: iconst_1
      15: istore_2
      16: goto          27
      19: goto          22
      22: iconst_0
      23: istore_2
      24: goto          27
      27: iload_2
      28: ifeq          90
      31: aload_1
      32: checkcast     #2                  // class es/weso/shapepath/TripleExprItem
      35: astore        4
      37: aload_0
      38: invokevirtual #50                 // Method te:()Les/weso/shex/TripleExpr;
      41: aload         4
      43: invokevirtual #50                 // Method te:()Les/weso/shex/TripleExpr;
      46: astore        5
      48: dup
      49: ifnonnull     61
      52: pop
      53: aload         5
      55: ifnull        69
      58: goto          82
      61: aload         5
      63: invokevirtual #67                 // Method java/lang/Object.equals:(Ljava/lang/Object;)Z
      66: ifeq          82
      69: aload         4
      71: aload_0
      72: invokevirtual #149                // Method canEqual:(Ljava/lang/Object;)Z
      75: ifeq          82
      78: iconst_1
      79: goto          83
      82: iconst_0
      83: ifeq          90
      86: iconst_1
      87: goto          91
      90: iconst_0
      91: ireturn

  public es.weso.shapepath.TripleExprItem(es.weso.shex.TripleExpr);
    Code:
       0: aload_0
       1: aload_1
       2: putfield      #43                 // Field te:Les/weso/shex/TripleExpr;
       5: aload_0
       6: invokespecial #152                // Method es/weso/shapepath/ShapeNode."<init>":()V
       9: aload_0
      10: invokestatic  #156                // InterfaceMethod scala/Product.$init$:(Lscala/Product;)V
      13: return
}
