Compiled from "ProcessingError.scala"
public class es.weso.shapepath.UnmatchItemContextLabel extends es.weso.shapepath.ProcessingError implements scala.Product,scala.Serializable {
  private final es.weso.shapepath.ShapeNode item;

  private final es.weso.shapepath.Step step;

  private final es.weso.shapepath.ContextType typeLabel;

  public static scala.Option<scala.Tuple3<es.weso.shapepath.ShapeNode, es.weso.shapepath.Step, es.weso.shapepath.ContextType>> unapply(es.weso.shapepath.UnmatchItemContextLabel);
    Code:
       0: getstatic     #28                 // Field es/weso/shapepath/UnmatchItemContextLabel$.MODULE$:Les/weso/shapepath/UnmatchItemContextLabel$;
       3: aload_0
       4: invokevirtual #30                 // Method es/weso/shapepath/UnmatchItemContextLabel$.unapply:(Les/weso/shapepath/UnmatchItemContextLabel;)Lscala/Option;
       7: areturn

  public static es.weso.shapepath.UnmatchItemContextLabel apply(es.weso.shapepath.ShapeNode, es.weso.shapepath.Step, es.weso.shapepath.ContextType);
    Code:
       0: getstatic     #28                 // Field es/weso/shapepath/UnmatchItemContextLabel$.MODULE$:Les/weso/shapepath/UnmatchItemContextLabel$;
       3: aload_0
       4: aload_1
       5: aload_2
       6: invokevirtual #34                 // Method es/weso/shapepath/UnmatchItemContextLabel$.apply:(Les/weso/shapepath/ShapeNode;Les/weso/shapepath/Step;Les/weso/shapepath/ContextType;)Les/weso/shapepath/UnmatchItemContextLabel;
       9: areturn

  public static scala.Function1<scala.Tuple3<es.weso.shapepath.ShapeNode, es.weso.shapepath.Step, es.weso.shapepath.ContextType>, es.weso.shapepath.UnmatchItemContextLabel> tupled();
    Code:
       0: getstatic     #28                 // Field es/weso/shapepath/UnmatchItemContextLabel$.MODULE$:Les/weso/shapepath/UnmatchItemContextLabel$;
       3: invokevirtual #39                 // Method es/weso/shapepath/UnmatchItemContextLabel$.tupled:()Lscala/Function1;
       6: areturn

  public static scala.Function1<es.weso.shapepath.ShapeNode, scala.Function1<es.weso.shapepath.Step, scala.Function1<es.weso.shapepath.ContextType, es.weso.shapepath.UnmatchItemContextLabel>>> curried();
    Code:
       0: getstatic     #28                 // Field es/weso/shapepath/UnmatchItemContextLabel$.MODULE$:Les/weso/shapepath/UnmatchItemContextLabel$;
       3: invokevirtual #43                 // Method es/weso/shapepath/UnmatchItemContextLabel$.curried:()Lscala/Function1;
       6: areturn

  public es.weso.shapepath.ShapeNode item();
    Code:
       0: aload_0
       1: getfield      #46                 // Field item:Les/weso/shapepath/ShapeNode;
       4: areturn

  public es.weso.shapepath.Step step();
    Code:
       0: aload_0
       1: getfield      #51                 // Field step:Les/weso/shapepath/Step;
       4: areturn

  public es.weso.shapepath.ContextType typeLabel();
    Code:
       0: aload_0
       1: getfield      #54                 // Field typeLabel:Les/weso/shapepath/ContextType;
       4: areturn

  public java.lang.String toString();
    Code:
       0: new           #58                 // class scala/collection/immutable/StringOps
       3: dup
       4: getstatic     #63                 // Field scala/Predef$.MODULE$:Lscala/Predef$;
       7: new           #65                 // class java/lang/StringBuilder
      10: dup
      11: ldc           #66                 // int 173
      13: invokespecial #70                 // Method java/lang/StringBuilder."<init>":(I)V
      16: ldc           #72                 // String |Processing error: \n                              |Item:
      18: invokevirtual #76                 // Method java/lang/StringBuilder.append:(Ljava/lang/String;)Ljava/lang/StringBuilder;
      21: aload_0
      22: invokevirtual #78                 // Method item:()Les/weso/shapepath/ShapeNode;
      25: invokevirtual #82                 // Method es/weso/shapepath/ShapeNode.toString:()Ljava/lang/String;
      28: invokevirtual #76                 // Method java/lang/StringBuilder.append:(Ljava/lang/String;)Ljava/lang/StringBuilder;
      31: ldc           #84                 // String \n                              |Step:
      33: invokevirtual #76                 // Method java/lang/StringBuilder.append:(Ljava/lang/String;)Ljava/lang/StringBuilder;
      36: aload_0
      37: invokevirtual #86                 // Method step:()Les/weso/shapepath/Step;
      40: invokevirtual #89                 // Method es/weso/shapepath/Step.toString:()Ljava/lang/String;
      43: invokevirtual #76                 // Method java/lang/StringBuilder.append:(Ljava/lang/String;)Ljava/lang/StringBuilder;
      46: ldc           #91                 // String \n                              |ContextLabel:
      48: invokevirtual #76                 // Method java/lang/StringBuilder.append:(Ljava/lang/String;)Ljava/lang/StringBuilder;
      51: aload_0
      52: invokevirtual #93                 // Method typeLabel:()Les/weso/shapepath/ContextType;
      55: invokevirtual #96                 // Method es/weso/shapepath/ContextType.toString:()Ljava/lang/String;
      58: invokevirtual #76                 // Method java/lang/StringBuilder.append:(Ljava/lang/String;)Ljava/lang/StringBuilder;
      61: ldc           #98                 // String \n                              |
      63: invokevirtual #76                 // Method java/lang/StringBuilder.append:(Ljava/lang/String;)Ljava/lang/StringBuilder;
      66: invokevirtual #99                 // Method java/lang/StringBuilder.toString:()Ljava/lang/String;
      69: invokevirtual #103                // Method scala/Predef$.augmentString:(Ljava/lang/String;)Ljava/lang/String;
      72: invokespecial #106                // Method scala/collection/immutable/StringOps."<init>":(Ljava/lang/String;)V
      75: invokevirtual #109                // Method scala/collection/immutable/StringOps.stripMargin:()Ljava/lang/String;
      78: areturn

  public es.weso.shapepath.UnmatchItemContextLabel copy(es.weso.shapepath.ShapeNode, es.weso.shapepath.Step, es.weso.shapepath.ContextType);
    Code:
       0: new           #2                  // class es/weso/shapepath/UnmatchItemContextLabel
       3: dup
       4: aload_1
       5: aload_2
       6: aload_3
       7: invokespecial #113                // Method "<init>":(Les/weso/shapepath/ShapeNode;Les/weso/shapepath/Step;Les/weso/shapepath/ContextType;)V
      10: areturn

  public es.weso.shapepath.ShapeNode copy$default$1();
    Code:
       0: aload_0
       1: invokevirtual #78                 // Method item:()Les/weso/shapepath/ShapeNode;
       4: areturn

  public es.weso.shapepath.Step copy$default$2();
    Code:
       0: aload_0
       1: invokevirtual #86                 // Method step:()Les/weso/shapepath/Step;
       4: areturn

  public es.weso.shapepath.ContextType copy$default$3();
    Code:
       0: aload_0
       1: invokevirtual #93                 // Method typeLabel:()Les/weso/shapepath/ContextType;
       4: areturn

  public java.lang.String productPrefix();
    Code:
       0: ldc           #119                // String UnmatchItemContextLabel
       2: areturn

  public int productArity();
    Code:
       0: iconst_3
       1: ireturn

  public java.lang.Object productElement(int);
    Code:
       0: iload_1
       1: istore_2
       2: iload_2
       3: tableswitch   { // 0 to 2
                     0: 28
                     1: 35
                     2: 42
               default: 49
          }
      28: aload_0
      29: invokevirtual #78                 // Method item:()Les/weso/shapepath/ShapeNode;
      32: goto          61
      35: aload_0
      36: invokevirtual #86                 // Method step:()Les/weso/shapepath/Step;
      39: goto          61
      42: aload_0
      43: invokevirtual #93                 // Method typeLabel:()Les/weso/shapepath/ContextType;
      46: goto          61
      49: new           #126                // class java/lang/IndexOutOfBoundsException
      52: dup
      53: iload_1
      54: invokestatic  #131                // Method java/lang/Integer.toString:(I)Ljava/lang/String;
      57: invokespecial #132                // Method java/lang/IndexOutOfBoundsException."<init>":(Ljava/lang/String;)V
      60: athrow
      61: areturn

  public scala.collection.Iterator<java.lang.Object> productIterator();
    Code:
       0: getstatic     #143                // Field scala/runtime/ScalaRunTime$.MODULE$:Lscala/runtime/ScalaRunTime$;
       3: aload_0
       4: invokevirtual #147                // Method scala/runtime/ScalaRunTime$.typedProductIterator:(Lscala/Product;)Lscala/collection/Iterator;
       7: areturn

  public boolean canEqual(java.lang.Object);
    Code:
       0: aload_1
       1: instanceof    #2                  // class es/weso/shapepath/UnmatchItemContextLabel
       4: ireturn

  public int hashCode();
    Code:
       0: getstatic     #143                // Field scala/runtime/ScalaRunTime$.MODULE$:Lscala/runtime/ScalaRunTime$;
       3: aload_0
       4: invokevirtual #155                // Method scala/runtime/ScalaRunTime$._hashCode:(Lscala/Product;)I
       7: ireturn

  public boolean equals(java.lang.Object);
    Code:
       0: aload_0
       1: aload_1
       2: if_acmpeq     150
       5: aload_1
       6: astore_3
       7: aload_3
       8: instanceof    #2                  // class es/weso/shapepath/UnmatchItemContextLabel
      11: ifeq          19
      14: iconst_1
      15: istore_2
      16: goto          27
      19: goto          22
      22: iconst_0
      23: istore_2
      24: goto          27
      27: iload_2
      28: ifeq          154
      31: aload_1
      32: checkcast     #2                  // class es/weso/shapepath/UnmatchItemContextLabel
      35: astore        4
      37: aload_0
      38: invokevirtual #78                 // Method item:()Les/weso/shapepath/ShapeNode;
      41: aload         4
      43: invokevirtual #78                 // Method item:()Les/weso/shapepath/ShapeNode;
      46: astore        5
      48: dup
      49: ifnonnull     61
      52: pop
      53: aload         5
      55: ifnull        69
      58: goto          146
      61: aload         5
      63: invokevirtual #158                // Method java/lang/Object.equals:(Ljava/lang/Object;)Z
      66: ifeq          146
      69: aload_0
      70: invokevirtual #86                 // Method step:()Les/weso/shapepath/Step;
      73: aload         4
      75: invokevirtual #86                 // Method step:()Les/weso/shapepath/Step;
      78: astore        6
      80: dup
      81: ifnonnull     93
      84: pop
      85: aload         6
      87: ifnull        101
      90: goto          146
      93: aload         6
      95: invokevirtual #158                // Method java/lang/Object.equals:(Ljava/lang/Object;)Z
      98: ifeq          146
     101: aload_0
     102: invokevirtual #93                 // Method typeLabel:()Les/weso/shapepath/ContextType;
     105: aload         4
     107: invokevirtual #93                 // Method typeLabel:()Les/weso/shapepath/ContextType;
     110: astore        7
     112: dup
     113: ifnonnull     125
     116: pop
     117: aload         7
     119: ifnull        133
     122: goto          146
     125: aload         7
     127: invokevirtual #158                // Method java/lang/Object.equals:(Ljava/lang/Object;)Z
     130: ifeq          146
     133: aload         4
     135: aload_0
     136: invokevirtual #160                // Method canEqual:(Ljava/lang/Object;)Z
     139: ifeq          146
     142: iconst_1
     143: goto          147
     146: iconst_0
     147: ifeq          154
     150: iconst_1
     151: goto          155
     154: iconst_0
     155: ireturn

  public es.weso.shapepath.UnmatchItemContextLabel(es.weso.shapepath.ShapeNode, es.weso.shapepath.Step, es.weso.shapepath.ContextType);
    Code:
       0: aload_0
       1: aload_1
       2: putfield      #46                 // Field item:Les/weso/shapepath/ShapeNode;
       5: aload_0
       6: aload_2
       7: putfield      #51                 // Field step:Les/weso/shapepath/Step;
      10: aload_0
      11: aload_3
      12: putfield      #54                 // Field typeLabel:Les/weso/shapepath/ContextType;
      15: aload_0
      16: invokespecial #163                // Method es/weso/shapepath/ProcessingError."<init>":()V
      19: aload_0
      20: invokestatic  #167                // InterfaceMethod scala/Product.$init$:(Lscala/Product;)V
      23: return
}
