Compiled from "DatabaseCertLoginModule.java"
public class org.jboss.security.auth.spi.DatabaseCertLoginModule extends org.jboss.security.auth.spi.BaseCertLoginModule {
  private static final java.lang.String DS_JNDI_NAME;

  private static final java.lang.String ROLES_QUERY;

  private static final java.lang.String SUSPEND_RESUME;

  private static final java.lang.String TRANSACTION_MANAGER_JNDI_NAME;

  private static final java.lang.String[] ALL_VALID_OPTIONS;

  private java.lang.String dsJndiName;

  protected java.lang.String txManagerJndiName;

  private java.lang.String rolesQuery;

  protected boolean suspendResume;

  public org.jboss.security.auth.spi.DatabaseCertLoginModule();
    Code:
       0: aload_0
       1: invokespecial #1                  // Method org/jboss/security/auth/spi/BaseCertLoginModule."<init>":()V
       4: aload_0
       5: ldc           #2                  // String java:/TransactionManager
       7: putfield      #3                  // Field txManagerJndiName:Ljava/lang/String;
      10: aload_0
      11: ldc           #4                  // String select Role, RoleGroup from Roles where PrincipalID=?
      13: putfield      #5                  // Field rolesQuery:Ljava/lang/String;
      16: aload_0
      17: iconst_1
      18: putfield      #6                  // Field suspendResume:Z
      21: return

  public void initialize(javax.security.auth.Subject, javax.security.auth.callback.CallbackHandler, java.util.Map<java.lang.String, ?>, java.util.Map<java.lang.String, ?>);
    Code:
       0: aload_0
       1: getstatic     #7                  // Field ALL_VALID_OPTIONS:[Ljava/lang/String;
       4: invokevirtual #8                  // Method addValidOptions:([Ljava/lang/String;)V
       7: aload_0
       8: aload_1
       9: aload_2
      10: aload_3
      11: aload         4
      13: invokespecial #9                  // Method org/jboss/security/auth/spi/BaseCertLoginModule.initialize:(Ljavax/security/auth/Subject;Ljavax/security/auth/callback/CallbackHandler;Ljava/util/Map;Ljava/util/Map;)V
      16: aload_0
      17: aload         4
      19: ldc           #11                 // String dsJndiName
      21: invokeinterface #12,  2           // InterfaceMethod java/util/Map.get:(Ljava/lang/Object;)Ljava/lang/Object;
      26: checkcast     #13                 // class java/lang/String
      29: putfield      #14                 // Field dsJndiName:Ljava/lang/String;
      32: aload_0
      33: getfield      #14                 // Field dsJndiName:Ljava/lang/String;
      36: ifnonnull     45
      39: aload_0
      40: ldc           #15                 // String java:/DefaultDS
      42: putfield      #14                 // Field dsJndiName:Ljava/lang/String;
      45: aload         4
      47: ldc           #16                 // String rolesQuery
      49: invokeinterface #12,  2           // InterfaceMethod java/util/Map.get:(Ljava/lang/Object;)Ljava/lang/Object;
      54: astore        5
      56: aload         5
      58: ifnull        70
      61: aload_0
      62: aload         5
      64: invokevirtual #17                 // Method java/lang/Object.toString:()Ljava/lang/String;
      67: putfield      #5                  // Field rolesQuery:Ljava/lang/String;
      70: aload         4
      72: ldc           #18                 // String suspendResume
      74: invokeinterface #12,  2           // InterfaceMethod java/util/Map.get:(Ljava/lang/Object;)Ljava/lang/Object;
      79: astore        5
      81: aload         5
      83: ifnull        101
      86: aload_0
      87: aload         5
      89: invokevirtual #17                 // Method java/lang/Object.toString:()Ljava/lang/String;
      92: invokestatic  #19                 // Method java/lang/Boolean.valueOf:(Ljava/lang/String;)Ljava/lang/Boolean;
      95: invokevirtual #20                 // Method java/lang/Boolean.booleanValue:()Z
      98: putfield      #6                  // Field suspendResume:Z
     101: aload         4
     103: ldc           #21                 // String transactionManagerJndiName
     105: invokeinterface #12,  2           // InterfaceMethod java/util/Map.get:(Ljava/lang/Object;)Ljava/lang/Object;
     110: astore        5
     112: aload         5
     114: ifnull        126
     117: aload_0
     118: aload         5
     120: invokevirtual #17                 // Method java/lang/Object.toString:()Ljava/lang/String;
     123: putfield      #3                  // Field txManagerJndiName:Ljava/lang/String;
     126: getstatic     #22                 // Field org/jboss/security/PicketBoxLogger.LOGGER:Lorg/jboss/security/PicketBoxLogger;
     129: aload_0
     130: getfield      #14                 // Field dsJndiName:Ljava/lang/String;
     133: ldc           #23                 // String
     135: aload_0
     136: getfield      #5                  // Field rolesQuery:Ljava/lang/String;
     139: aload_0
     140: getfield      #6                  // Field suspendResume:Z
     143: invokeinterface #24,  5           // InterfaceMethod org/jboss/security/PicketBoxLogger.traceDBCertLoginModuleOptions:(Ljava/lang/String;Ljava/lang/String;Ljava/lang/String;Z)V
     148: return

  protected java.security.acl.Group[] getRoleSets() throws javax.security.auth.login.LoginException;
    Code:
       0: aload_0
       1: invokevirtual #25                 // Method getUsername:()Ljava/lang/String;
       4: astore_1
       5: aload_1
       6: aload_0
       7: getfield      #14                 // Field dsJndiName:Ljava/lang/String;
      10: aload_0
      11: getfield      #3                  // Field txManagerJndiName:Ljava/lang/String;
      14: aload_0
      15: getfield      #5                  // Field rolesQuery:Ljava/lang/String;
      18: aload_0
      19: aload_0
      20: getfield      #6                  // Field suspendResume:Z
      23: invokestatic  #26                 // Method org/jboss/security/auth/spi/Util.getRoleSets:(Ljava/lang/String;Ljava/lang/String;Ljava/lang/String;Ljava/lang/String;Lorg/jboss/security/auth/spi/AbstractServerLoginModule;Z)[Ljava/security/acl/Group;
      26: astore_2
      27: aload_2
      28: areturn

  static {};
    Code:
       0: iconst_3
       1: anewarray     #13                 // class java/lang/String
       4: dup
       5: iconst_0
       6: ldc           #11                 // String dsJndiName
       8: aastore
       9: dup
      10: iconst_1
      11: ldc           #16                 // String rolesQuery
      13: aastore
      14: dup
      15: iconst_2
      16: ldc           #18                 // String suspendResume
      18: aastore
      19: putstatic     #7                  // Field ALL_VALID_OPTIONS:[Ljava/lang/String;
      22: return
}
