Compiled from "SimpleServerLoginModule.java"
public class org.jboss.security.auth.spi.SimpleServerLoginModule extends org.jboss.security.auth.spi.UsernamePasswordLoginModule {
  private org.jboss.security.SimplePrincipal user;

  private boolean guestOnly;

  public org.jboss.security.auth.spi.SimpleServerLoginModule();
    Code:
       0: aload_0
       1: invokespecial #1                  // Method org/jboss/security/auth/spi/UsernamePasswordLoginModule."<init>":()V
       4: return

  protected java.security.Principal getIdentity();
    Code:
       0: aload_0
       1: getfield      #2                  // Field user:Lorg/jboss/security/SimplePrincipal;
       4: astore_1
       5: aload_1
       6: ifnonnull     14
       9: aload_0
      10: invokespecial #3                  // Method org/jboss/security/auth/spi/UsernamePasswordLoginModule.getIdentity:()Ljava/security/Principal;
      13: astore_1
      14: aload_1
      15: areturn

  protected boolean validatePassword(java.lang.String, java.lang.String);
    Code:
       0: iconst_0
       1: istore_3
       2: aload_1
       3: ifnonnull     29
       6: aload_0
       7: iconst_1
       8: putfield      #4                  // Field guestOnly:Z
      11: iconst_1
      12: istore_3
      13: aload_0
      14: new           #5                  // class org/jboss/security/SimplePrincipal
      17: dup
      18: ldc           #6                  // String guest
      20: invokespecial #7                  // Method org/jboss/security/SimplePrincipal."<init>":(Ljava/lang/String;)V
      23: putfield      #2                  // Field user:Lorg/jboss/security/SimplePrincipal;
      26: goto          35
      29: aload_1
      30: aload_2
      31: invokevirtual #8                  // Method java/lang/String.equals:(Ljava/lang/Object;)Z
      34: istore_3
      35: iload_3
      36: ireturn

  protected java.security.acl.Group[] getRoleSets() throws javax.security.auth.login.LoginException;
    Code:
       0: iconst_1
       1: anewarray     #9                  // class java/security/acl/Group
       4: dup
       5: iconst_0
       6: new           #10                 // class org/jboss/security/SimpleGroup
       9: dup
      10: ldc           #11                 // String Roles
      12: invokespecial #12                 // Method org/jboss/security/SimpleGroup."<init>":(Ljava/lang/String;)V
      15: aastore
      16: astore_1
      17: aload_0
      18: getfield      #4                  // Field guestOnly:Z
      21: ifne          42
      24: aload_1
      25: iconst_0
      26: aaload
      27: new           #5                  // class org/jboss/security/SimplePrincipal
      30: dup
      31: ldc           #13                 // String user
      33: invokespecial #7                  // Method org/jboss/security/SimplePrincipal."<init>":(Ljava/lang/String;)V
      36: invokeinterface #14,  2           // InterfaceMethod java/security/acl/Group.addMember:(Ljava/security/Principal;)Z
      41: pop
      42: aload_1
      43: iconst_0
      44: aaload
      45: new           #5                  // class org/jboss/security/SimplePrincipal
      48: dup
      49: ldc           #6                  // String guest
      51: invokespecial #7                  // Method org/jboss/security/SimplePrincipal."<init>":(Ljava/lang/String;)V
      54: invokeinterface #14,  2           // InterfaceMethod java/security/acl/Group.addMember:(Ljava/security/Principal;)Z
      59: pop
      60: aload_1
      61: areturn

  protected java.lang.String getUsersPassword() throws javax.security.auth.login.LoginException;
    Code:
       0: aload_0
       1: invokevirtual #15                 // Method getUsername:()Ljava/lang/String;
       4: areturn

  public boolean logout() throws javax.security.auth.login.LoginException;
    Code:
       0: aload_0
       1: invokevirtual #16                 // Method getRoleSets:()[Ljava/security/acl/Group;
       4: astore_1
       5: aload_0
       6: getfield      #17                 // Field subject:Ljavax/security/auth/Subject;
       9: invokevirtual #18                 // Method javax/security/auth/Subject.getPrincipals:()Ljava/util/Set;
      12: aload_1
      13: iconst_0
      14: aaload
      15: invokeinterface #19,  2           // InterfaceMethod java/util/Set.remove:(Ljava/lang/Object;)Z
      20: pop
      21: aload_0
      22: invokespecial #20                 // Method org/jboss/security/auth/spi/UsernamePasswordLoginModule.logout:()Z
      25: ireturn
}
