Compiled from "UserTransactionListenerImpl.java"
public class org.jboss.jca.core.tx.jbossts.UserTransactionListenerImpl implements org.jboss.jca.core.spi.transaction.usertx.UserTransactionListener,org.jboss.tm.usertx.UserTransactionListener {
  private org.jboss.jca.core.spi.transaction.usertx.UserTransactionListener utl;

  public org.jboss.jca.core.tx.jbossts.UserTransactionListenerImpl(org.jboss.jca.core.spi.transaction.usertx.UserTransactionListener);
    Code:
       0: aload_0
       1: invokespecial #1                  // Method java/lang/Object."<init>":()V
       4: aload_0
       5: aload_1
       6: putfield      #2                  // Field utl:Lorg/jboss/jca/core/spi/transaction/usertx/UserTransactionListener;
       9: return

  public void userTransactionStarted() throws javax.transaction.SystemException;
    Code:
       0: aload_0
       1: getfield      #2                  // Field utl:Lorg/jboss/jca/core/spi/transaction/usertx/UserTransactionListener;
       4: invokeinterface #3,  1            // InterfaceMethod org/jboss/jca/core/spi/transaction/usertx/UserTransactionListener.userTransactionStarted:()V
       9: return
}
