Compiled from "KryoConfig.java"
public final class nl.basjes.parse.useragent.utils.KryoConfig {
  private nl.basjes.parse.useragent.utils.KryoConfig();
    Code:
       0: aload_0
       1: invokespecial #38                 // Method java/lang/Object."<init>":()V
       4: return

  public static void configureKryo(com.esotericsoftware.kryo.Kryo);
    Code:
       0: aload_0
       1: iconst_1
       2: invokevirtual #48                 // Method com/esotericsoftware/kryo/Kryo.setReferences:(Z)Z
       5: pop
       6: aload_0
       7: invokestatic  #54                 // Method java/util/Collections.emptySet:()Ljava/util/Set;
      10: invokevirtual #58                 // Method java/lang/Object.getClass:()Ljava/lang/Class;
      13: invokevirtual #62                 // Method com/esotericsoftware/kryo/Kryo.register:(Ljava/lang/Class;)Lcom/esotericsoftware/kryo/Registration;
      16: pop
      17: aload_0
      18: invokestatic  #66                 // Method java/util/Collections.emptyList:()Ljava/util/List;
      21: invokevirtual #58                 // Method java/lang/Object.getClass:()Ljava/lang/Class;
      24: invokevirtual #62                 // Method com/esotericsoftware/kryo/Kryo.register:(Ljava/lang/Class;)Lcom/esotericsoftware/kryo/Registration;
      27: pop
      28: aload_0
      29: invokestatic  #70                 // Method java/util/Collections.emptyMap:()Ljava/util/Map;
      32: invokevirtual #58                 // Method java/lang/Object.getClass:()Ljava/lang/Class;
      35: invokevirtual #62                 // Method com/esotericsoftware/kryo/Kryo.register:(Ljava/lang/Class;)Lcom/esotericsoftware/kryo/Registration;
      38: pop
      39: aload_0
      40: ldc           #72                 // class java/util/ArrayList
      42: invokevirtual #62                 // Method com/esotericsoftware/kryo/Kryo.register:(Ljava/lang/Class;)Lcom/esotericsoftware/kryo/Registration;
      45: pop
      46: aload_0
      47: ldc           #74                 // class java/util/LinkedHashSet
      49: invokevirtual #62                 // Method com/esotericsoftware/kryo/Kryo.register:(Ljava/lang/Class;)Lcom/esotericsoftware/kryo/Registration;
      52: pop
      53: aload_0
      54: ldc           #76                 // class java/util/LinkedHashMap
      56: invokevirtual #62                 // Method com/esotericsoftware/kryo/Kryo.register:(Ljava/lang/Class;)Lcom/esotericsoftware/kryo/Registration;
      59: pop
      60: aload_0
      61: ldc           #78                 // class java/util/HashSet
      63: invokevirtual #62                 // Method com/esotericsoftware/kryo/Kryo.register:(Ljava/lang/Class;)Lcom/esotericsoftware/kryo/Registration;
      66: pop
      67: aload_0
      68: ldc           #80                 // class java/util/HashMap
      70: invokevirtual #62                 // Method com/esotericsoftware/kryo/Kryo.register:(Ljava/lang/Class;)Lcom/esotericsoftware/kryo/Registration;
      73: pop
      74: aload_0
      75: ldc           #82                 // class java/util/TreeSet
      77: invokevirtual #62                 // Method com/esotericsoftware/kryo/Kryo.register:(Ljava/lang/Class;)Lcom/esotericsoftware/kryo/Registration;
      80: pop
      81: aload_0
      82: ldc           #84                 // class java/util/TreeMap
      84: invokevirtual #62                 // Method com/esotericsoftware/kryo/Kryo.register:(Ljava/lang/Class;)Lcom/esotericsoftware/kryo/Registration;
      87: pop
      88: aload_0
      89: ldc           #86                 // class nl/basjes/parse/useragent/AbstractUserAgentAnalyzerDirect
      91: invokevirtual #62                 // Method com/esotericsoftware/kryo/Kryo.register:(Ljava/lang/Class;)Lcom/esotericsoftware/kryo/Registration;
      94: pop
      95: aload_0
      96: ldc           #9                  // class nl/basjes/parse/useragent/config/MatcherConfig
      98: invokevirtual #62                 // Method com/esotericsoftware/kryo/Kryo.register:(Ljava/lang/Class;)Lcom/esotericsoftware/kryo/Registration;
     101: pop
     102: aload_0
     103: ldc           #7                  // class nl/basjes/parse/useragent/config/MatcherConfig$ConfigLine
     105: invokevirtual #62                 // Method com/esotericsoftware/kryo/Kryo.register:(Ljava/lang/Class;)Lcom/esotericsoftware/kryo/Registration;
     108: pop
     109: aload_0
     110: ldc           #12                 // class nl/basjes/parse/useragent/config/MatcherConfig$ConfigLine$Type
     112: invokevirtual #62                 // Method com/esotericsoftware/kryo/Kryo.register:(Ljava/lang/Class;)Lcom/esotericsoftware/kryo/Registration;
     115: pop
     116: aload_0
     117: ldc           #88                 // class nl/basjes/parse/useragent/config/AnalyzerConfig
     119: invokevirtual #62                 // Method com/esotericsoftware/kryo/Kryo.register:(Ljava/lang/Class;)Lcom/esotericsoftware/kryo/Registration;
     122: pop
     123: aload_0
     124: ldc           #9                  // class nl/basjes/parse/useragent/config/MatcherConfig
     126: invokevirtual #62                 // Method com/esotericsoftware/kryo/Kryo.register:(Ljava/lang/Class;)Lcom/esotericsoftware/kryo/Registration;
     129: pop
     130: aload_0
     131: ldc           #90                 // class nl/basjes/parse/useragent/config/TestCase
     133: invokevirtual #62                 // Method com/esotericsoftware/kryo/Kryo.register:(Ljava/lang/Class;)Lcom/esotericsoftware/kryo/Registration;
     136: pop
     137: aload_0
     138: ldc           #92                 // class nl/basjes/parse/useragent/analyze/Analyzer
     140: invokevirtual #62                 // Method com/esotericsoftware/kryo/Kryo.register:(Ljava/lang/Class;)Lcom/esotericsoftware/kryo/Registration;
     143: pop
     144: aload_0
     145: ldc           #15                 // class nl/basjes/parse/useragent/UserAgent$ImmutableUserAgent
     147: invokevirtual #62                 // Method com/esotericsoftware/kryo/Kryo.register:(Ljava/lang/Class;)Lcom/esotericsoftware/kryo/Registration;
     150: pop
     151: aload_0
     152: ldc           #20                 // class nl/basjes/parse/useragent/AgentField$ImmutableAgentField
     154: invokevirtual #62                 // Method com/esotericsoftware/kryo/Kryo.register:(Ljava/lang/Class;)Lcom/esotericsoftware/kryo/Registration;
     157: pop
     158: aload_0
     159: ldc           #25                 // class nl/basjes/parse/useragent/UserAgent$MutableUserAgent
     161: invokevirtual #62                 // Method com/esotericsoftware/kryo/Kryo.register:(Ljava/lang/Class;)Lcom/esotericsoftware/kryo/Registration;
     164: pop
     165: aload_0
     166: ldc           #28                 // class nl/basjes/parse/useragent/AgentField$MutableAgentField
     168: invokevirtual #62                 // Method com/esotericsoftware/kryo/Kryo.register:(Ljava/lang/Class;)Lcom/esotericsoftware/kryo/Registration;
     171: pop
     172: aload_0
     173: ldc           #94                 // class nl/basjes/parse/useragent/analyze/Matcher
     175: invokevirtual #62                 // Method com/esotericsoftware/kryo/Kryo.register:(Ljava/lang/Class;)Lcom/esotericsoftware/kryo/Registration;
     178: pop
     179: aload_0
     180: ldc           #96                 // class nl/basjes/parse/useragent/analyze/MatcherAction
     182: invokevirtual #62                 // Method com/esotericsoftware/kryo/Kryo.register:(Ljava/lang/Class;)Lcom/esotericsoftware/kryo/Registration;
     185: pop
     186: aload_0
     187: ldc           #98                 // class nl/basjes/parse/useragent/analyze/MatcherList
     189: invokevirtual #62                 // Method com/esotericsoftware/kryo/Kryo.register:(Ljava/lang/Class;)Lcom/esotericsoftware/kryo/Registration;
     192: pop
     193: aload_0
     194: ldc           #100                // class nl/basjes/parse/useragent/analyze/MatchesList
     196: invokevirtual #62                 // Method com/esotericsoftware/kryo/Kryo.register:(Ljava/lang/Class;)Lcom/esotericsoftware/kryo/Registration;
     199: pop
     200: aload_0
     201: ldc           #102                // class nl/basjes/parse/useragent/analyze/MatcherExtractAction
     203: invokevirtual #62                 // Method com/esotericsoftware/kryo/Kryo.register:(Ljava/lang/Class;)Lcom/esotericsoftware/kryo/Registration;
     206: pop
     207: aload_0
     208: ldc           #104                // class nl/basjes/parse/useragent/analyze/MatcherVariableAction
     210: invokevirtual #62                 // Method com/esotericsoftware/kryo/Kryo.register:(Ljava/lang/Class;)Lcom/esotericsoftware/kryo/Registration;
     213: pop
     214: aload_0
     215: ldc           #106                // class nl/basjes/parse/useragent/analyze/MatcherRequireAction
     217: invokevirtual #62                 // Method com/esotericsoftware/kryo/Kryo.register:(Ljava/lang/Class;)Lcom/esotericsoftware/kryo/Registration;
     220: pop
     221: aload_0
     222: ldc           #108                // class nl/basjes/parse/useragent/analyze/MatcherFailIfFoundAction
     224: invokevirtual #62                 // Method com/esotericsoftware/kryo/Kryo.register:(Ljava/lang/Class;)Lcom/esotericsoftware/kryo/Registration;
     227: pop
     228: aload_0
     229: ldc           #31                 // class nl/basjes/parse/useragent/analyze/WordRangeVisitor$Range
     231: invokevirtual #62                 // Method com/esotericsoftware/kryo/Kryo.register:(Ljava/lang/Class;)Lcom/esotericsoftware/kryo/Registration;
     234: pop
     235: aload_0
     236: ldc           #110                // class nl/basjes/parse/useragent/calculate/CalculateAgentEmail
     238: invokevirtual #62                 // Method com/esotericsoftware/kryo/Kryo.register:(Ljava/lang/Class;)Lcom/esotericsoftware/kryo/Registration;
     241: pop
     242: aload_0
     243: ldc           #112                // class nl/basjes/parse/useragent/calculate/CalculateAgentName
     245: invokevirtual #62                 // Method com/esotericsoftware/kryo/Kryo.register:(Ljava/lang/Class;)Lcom/esotericsoftware/kryo/Registration;
     248: pop
     249: aload_0
     250: ldc           #114                // class nl/basjes/parse/useragent/calculate/CalculateAgentClass
     252: invokevirtual #62                 // Method com/esotericsoftware/kryo/Kryo.register:(Ljava/lang/Class;)Lcom/esotericsoftware/kryo/Registration;
     255: pop
     256: aload_0
     257: ldc           #116                // class nl/basjes/parse/useragent/calculate/CalculateDeviceBrand
     259: invokevirtual #62                 // Method com/esotericsoftware/kryo/Kryo.register:(Ljava/lang/Class;)Lcom/esotericsoftware/kryo/Registration;
     262: pop
     263: aload_0
     264: ldc           #118                // class nl/basjes/parse/useragent/calculate/CalculateDeviceName
     266: invokevirtual #62                 // Method com/esotericsoftware/kryo/Kryo.register:(Ljava/lang/Class;)Lcom/esotericsoftware/kryo/Registration;
     269: pop
     270: aload_0
     271: ldc           #120                // class nl/basjes/parse/useragent/calculate/CalculateNetworkType
     273: invokevirtual #62                 // Method com/esotericsoftware/kryo/Kryo.register:(Ljava/lang/Class;)Lcom/esotericsoftware/kryo/Registration;
     276: pop
     277: aload_0
     278: ldc           #122                // class nl/basjes/parse/useragent/calculate/ConcatNONDuplicatedCalculator
     280: invokevirtual #62                 // Method com/esotericsoftware/kryo/Kryo.register:(Ljava/lang/Class;)Lcom/esotericsoftware/kryo/Registration;
     283: pop
     284: aload_0
     285: ldc           #124                // class nl/basjes/parse/useragent/calculate/FieldCalculator
     287: invokevirtual #62                 // Method com/esotericsoftware/kryo/Kryo.register:(Ljava/lang/Class;)Lcom/esotericsoftware/kryo/Registration;
     290: pop
     291: aload_0
     292: ldc           #126                // class nl/basjes/parse/useragent/calculate/MajorVersionCalculator
     294: invokevirtual #62                 // Method com/esotericsoftware/kryo/Kryo.register:(Ljava/lang/Class;)Lcom/esotericsoftware/kryo/Registration;
     297: pop
     298: aload_0
     299: ldc           #128                // class nl/basjes/parse/useragent/parse/UserAgentTreeFlattener
     301: invokevirtual #62                 // Method com/esotericsoftware/kryo/Kryo.register:(Ljava/lang/Class;)Lcom/esotericsoftware/kryo/Registration;
     304: pop
     305: aload_0
     306: ldc           #130                // class nl/basjes/parse/useragent/analyze/treewalker/TreeExpressionEvaluator
     308: invokevirtual #62                 // Method com/esotericsoftware/kryo/Kryo.register:(Ljava/lang/Class;)Lcom/esotericsoftware/kryo/Registration;
     311: pop
     312: aload_0
     313: ldc           #132                // class nl/basjes/parse/useragent/analyze/treewalker/steps/WalkList
     315: invokevirtual #62                 // Method com/esotericsoftware/kryo/Kryo.register:(Ljava/lang/Class;)Lcom/esotericsoftware/kryo/Registration;
     318: pop
     319: aload_0
     320: ldc           #134                // class nl/basjes/parse/useragent/analyze/treewalker/steps/compare/StepContains
     322: invokevirtual #62                 // Method com/esotericsoftware/kryo/Kryo.register:(Ljava/lang/Class;)Lcom/esotericsoftware/kryo/Registration;
     325: pop
     326: aload_0
     327: ldc           #136                // class nl/basjes/parse/useragent/analyze/treewalker/steps/compare/StepNotContains
     329: invokevirtual #62                 // Method com/esotericsoftware/kryo/Kryo.register:(Ljava/lang/Class;)Lcom/esotericsoftware/kryo/Registration;
     332: pop
     333: aload_0
     334: ldc           #138                // class nl/basjes/parse/useragent/analyze/treewalker/steps/compare/StepDefaultIfNull
     336: invokevirtual #62                 // Method com/esotericsoftware/kryo/Kryo.register:(Ljava/lang/Class;)Lcom/esotericsoftware/kryo/Registration;
     339: pop
     340: aload_0
     341: ldc           #140                // class nl/basjes/parse/useragent/analyze/treewalker/steps/compare/StepEndsWith
     343: invokevirtual #62                 // Method com/esotericsoftware/kryo/Kryo.register:(Ljava/lang/Class;)Lcom/esotericsoftware/kryo/Registration;
     346: pop
     347: aload_0
     348: ldc           #142                // class nl/basjes/parse/useragent/analyze/treewalker/steps/compare/StepEquals
     350: invokevirtual #62                 // Method com/esotericsoftware/kryo/Kryo.register:(Ljava/lang/Class;)Lcom/esotericsoftware/kryo/Registration;
     353: pop
     354: aload_0
     355: ldc           #144                // class nl/basjes/parse/useragent/analyze/treewalker/steps/compare/StepIsInSet
     357: invokevirtual #62                 // Method com/esotericsoftware/kryo/Kryo.register:(Ljava/lang/Class;)Lcom/esotericsoftware/kryo/Registration;
     360: pop
     361: aload_0
     362: ldc           #146                // class nl/basjes/parse/useragent/analyze/treewalker/steps/compare/StepIsNotInSet
     364: invokevirtual #62                 // Method com/esotericsoftware/kryo/Kryo.register:(Ljava/lang/Class;)Lcom/esotericsoftware/kryo/Registration;
     367: pop
     368: aload_0
     369: ldc           #148                // class nl/basjes/parse/useragent/analyze/treewalker/steps/compare/StepIsNull
     371: invokevirtual #62                 // Method com/esotericsoftware/kryo/Kryo.register:(Ljava/lang/Class;)Lcom/esotericsoftware/kryo/Registration;
     374: pop
     375: aload_0
     376: ldc           #150                // class nl/basjes/parse/useragent/analyze/treewalker/steps/compare/StepNotEquals
     378: invokevirtual #62                 // Method com/esotericsoftware/kryo/Kryo.register:(Ljava/lang/Class;)Lcom/esotericsoftware/kryo/Registration;
     381: pop
     382: aload_0
     383: ldc           #152                // class nl/basjes/parse/useragent/analyze/treewalker/steps/compare/StepStartsWith
     385: invokevirtual #62                 // Method com/esotericsoftware/kryo/Kryo.register:(Ljava/lang/Class;)Lcom/esotericsoftware/kryo/Registration;
     388: pop
     389: aload_0
     390: ldc           #154                // class nl/basjes/parse/useragent/analyze/treewalker/steps/lookup/StepIsInLookupContains
     392: invokevirtual #62                 // Method com/esotericsoftware/kryo/Kryo.register:(Ljava/lang/Class;)Lcom/esotericsoftware/kryo/Registration;
     395: pop
     396: aload_0
     397: ldc           #156                // class nl/basjes/parse/useragent/analyze/treewalker/steps/lookup/StepIsInLookupPrefix
     399: invokevirtual #62                 // Method com/esotericsoftware/kryo/Kryo.register:(Ljava/lang/Class;)Lcom/esotericsoftware/kryo/Registration;
     402: pop
     403: aload_0
     404: ldc           #158                // class nl/basjes/parse/useragent/analyze/treewalker/steps/lookup/StepIsNotInLookupPrefix
     406: invokevirtual #62                 // Method com/esotericsoftware/kryo/Kryo.register:(Ljava/lang/Class;)Lcom/esotericsoftware/kryo/Registration;
     409: pop
     410: aload_0
     411: ldc           #160                // class nl/basjes/parse/useragent/analyze/treewalker/steps/lookup/StepLookup
     413: invokevirtual #62                 // Method com/esotericsoftware/kryo/Kryo.register:(Ljava/lang/Class;)Lcom/esotericsoftware/kryo/Registration;
     416: pop
     417: aload_0
     418: ldc           #162                // class nl/basjes/parse/useragent/analyze/treewalker/steps/lookup/StepLookupContains
     420: invokevirtual #62                 // Method com/esotericsoftware/kryo/Kryo.register:(Ljava/lang/Class;)Lcom/esotericsoftware/kryo/Registration;
     423: pop
     424: aload_0
     425: ldc           #164                // class nl/basjes/parse/useragent/analyze/treewalker/steps/lookup/StepLookupPrefix
     427: invokevirtual #62                 // Method com/esotericsoftware/kryo/Kryo.register:(Ljava/lang/Class;)Lcom/esotericsoftware/kryo/Registration;
     430: pop
     431: aload_0
     432: ldc           #166                // class nl/basjes/parse/useragent/analyze/treewalker/steps/value/StepBackToFull
     434: invokevirtual #62                 // Method com/esotericsoftware/kryo/Kryo.register:(Ljava/lang/Class;)Lcom/esotericsoftware/kryo/Registration;
     437: pop
     438: aload_0
     439: ldc           #168                // class nl/basjes/parse/useragent/analyze/treewalker/steps/value/StepCleanVersion
     441: invokevirtual #62                 // Method com/esotericsoftware/kryo/Kryo.register:(Ljava/lang/Class;)Lcom/esotericsoftware/kryo/Registration;
     444: pop
     445: aload_0
     446: ldc           #170                // class nl/basjes/parse/useragent/analyze/treewalker/steps/value/StepConcat
     448: invokevirtual #62                 // Method com/esotericsoftware/kryo/Kryo.register:(Ljava/lang/Class;)Lcom/esotericsoftware/kryo/Registration;
     451: pop
     452: aload_0
     453: ldc           #172                // class nl/basjes/parse/useragent/analyze/treewalker/steps/value/StepConcatPostfix
     455: invokevirtual #62                 // Method com/esotericsoftware/kryo/Kryo.register:(Ljava/lang/Class;)Lcom/esotericsoftware/kryo/Registration;
     458: pop
     459: aload_0
     460: ldc           #174                // class nl/basjes/parse/useragent/analyze/treewalker/steps/value/StepConcatPrefix
     462: invokevirtual #62                 // Method com/esotericsoftware/kryo/Kryo.register:(Ljava/lang/Class;)Lcom/esotericsoftware/kryo/Registration;
     465: pop
     466: aload_0
     467: ldc           #176                // class nl/basjes/parse/useragent/analyze/treewalker/steps/value/StepNormalizeBrand
     469: invokevirtual #62                 // Method com/esotericsoftware/kryo/Kryo.register:(Ljava/lang/Class;)Lcom/esotericsoftware/kryo/Registration;
     472: pop
     473: aload_0
     474: ldc           #178                // class nl/basjes/parse/useragent/analyze/treewalker/steps/value/StepExtractBrandFromUrl
     476: invokevirtual #62                 // Method com/esotericsoftware/kryo/Kryo.register:(Ljava/lang/Class;)Lcom/esotericsoftware/kryo/Registration;
     479: pop
     480: aload_0
     481: ldc           #180                // class nl/basjes/parse/useragent/analyze/treewalker/steps/value/StepReplaceString
     483: invokevirtual #62                 // Method com/esotericsoftware/kryo/Kryo.register:(Ljava/lang/Class;)Lcom/esotericsoftware/kryo/Registration;
     486: pop
     487: aload_0
     488: ldc           #182                // class nl/basjes/parse/useragent/analyze/treewalker/steps/value/StepSegmentRange
     490: invokevirtual #62                 // Method com/esotericsoftware/kryo/Kryo.register:(Ljava/lang/Class;)Lcom/esotericsoftware/kryo/Registration;
     493: pop
     494: aload_0
     495: ldc           #184                // class nl/basjes/parse/useragent/analyze/treewalker/steps/value/StepWordRange
     497: invokevirtual #62                 // Method com/esotericsoftware/kryo/Kryo.register:(Ljava/lang/Class;)Lcom/esotericsoftware/kryo/Registration;
     500: pop
     501: aload_0
     502: ldc           #186                // class nl/basjes/parse/useragent/analyze/treewalker/steps/walk/StepDown
     504: invokevirtual #62                 // Method com/esotericsoftware/kryo/Kryo.register:(Ljava/lang/Class;)Lcom/esotericsoftware/kryo/Registration;
     507: pop
     508: aload_0
     509: ldc           #188                // class nl/basjes/parse/useragent/analyze/treewalker/steps/walk/StepNext
     511: invokevirtual #62                 // Method com/esotericsoftware/kryo/Kryo.register:(Ljava/lang/Class;)Lcom/esotericsoftware/kryo/Registration;
     514: pop
     515: aload_0
     516: ldc           #190                // class nl/basjes/parse/useragent/analyze/treewalker/steps/walk/StepNextN
     518: invokevirtual #62                 // Method com/esotericsoftware/kryo/Kryo.register:(Ljava/lang/Class;)Lcom/esotericsoftware/kryo/Registration;
     521: pop
     522: aload_0
     523: ldc           #192                // class nl/basjes/parse/useragent/analyze/treewalker/steps/walk/StepPrev
     525: invokevirtual #62                 // Method com/esotericsoftware/kryo/Kryo.register:(Ljava/lang/Class;)Lcom/esotericsoftware/kryo/Registration;
     528: pop
     529: aload_0
     530: ldc           #194                // class nl/basjes/parse/useragent/analyze/treewalker/steps/walk/StepPrevN
     532: invokevirtual #62                 // Method com/esotericsoftware/kryo/Kryo.register:(Ljava/lang/Class;)Lcom/esotericsoftware/kryo/Registration;
     535: pop
     536: aload_0
     537: ldc           #196                // class nl/basjes/parse/useragent/analyze/treewalker/steps/walk/StepUp
     539: invokevirtual #62                 // Method com/esotericsoftware/kryo/Kryo.register:(Ljava/lang/Class;)Lcom/esotericsoftware/kryo/Registration;
     542: pop
     543: aload_0
     544: invokestatic  #201                // Method nl/basjes/collections/prefixmap/StringPrefixMap.configureKryo:(Ljava/lang/Object;)V
     547: return
}
