Compiled from "BSPRule.java"
public final class org.apache.wss4j.common.bsp.BSPRule extends java.lang.Enum<org.apache.wss4j.common.bsp.BSPRule> {
  public static final org.apache.wss4j.common.bsp.BSPRule R3203;

  public static final org.apache.wss4j.common.bsp.BSPRule R3224;

  public static final org.apache.wss4j.common.bsp.BSPRule R3221;

  public static final org.apache.wss4j.common.bsp.BSPRule R3222;

  public static final org.apache.wss4j.common.bsp.BSPRule R3220;

  public static final org.apache.wss4j.common.bsp.BSPRule R3229;

  public static final org.apache.wss4j.common.bsp.BSPRule R3213;

  public static final org.apache.wss4j.common.bsp.BSPRule R3215;

  public static final org.apache.wss4j.common.bsp.BSPRule R3225;

  public static final org.apache.wss4j.common.bsp.BSPRule R3226;

  public static final org.apache.wss4j.common.bsp.BSPRule R3217;

  public static final org.apache.wss4j.common.bsp.BSPRule R3223;

  public static final org.apache.wss4j.common.bsp.BSPRule R3227;

  public static final org.apache.wss4j.common.bsp.BSPRule R3061;

  public static final org.apache.wss4j.common.bsp.BSPRule R3074;

  public static final org.apache.wss4j.common.bsp.BSPRule R3057;

  public static final org.apache.wss4j.common.bsp.BSPRule R3064;

  public static final org.apache.wss4j.common.bsp.BSPRule R3059;

  public static final org.apache.wss4j.common.bsp.BSPRule R3058;

  public static final org.apache.wss4j.common.bsp.BSPRule R3062;

  public static final org.apache.wss4j.common.bsp.BSPRule R3027;

  public static final org.apache.wss4j.common.bsp.BSPRule R3054;

  public static final org.apache.wss4j.common.bsp.BSPRule R3063;

  public static final org.apache.wss4j.common.bsp.BSPRule R3070;

  public static final org.apache.wss4j.common.bsp.BSPRule R3071;

  public static final org.apache.wss4j.common.bsp.BSPRule R3060;

  public static final org.apache.wss4j.common.bsp.BSPRule R3025;

  public static final org.apache.wss4j.common.bsp.BSPRule R3056;

  public static final org.apache.wss4j.common.bsp.BSPRule R3022;

  public static final org.apache.wss4j.common.bsp.BSPRule R3023;

  public static final org.apache.wss4j.common.bsp.BSPRule R5204;

  public static final org.apache.wss4j.common.bsp.BSPRule R5205;

  public static final org.apache.wss4j.common.bsp.BSPRule R3066;

  public static final org.apache.wss4j.common.bsp.BSPRule R3067;

  public static final org.apache.wss4j.common.bsp.BSPRule R3024;

  public static final org.apache.wss4j.common.bsp.BSPRule R3211;

  public static final org.apache.wss4j.common.bsp.BSPRule R3102;

  public static final org.apache.wss4j.common.bsp.BSPRule R3104;

  public static final org.apache.wss4j.common.bsp.BSPRule R3103;

  public static final org.apache.wss4j.common.bsp.BSPRule R3001;

  public static final org.apache.wss4j.common.bsp.BSPRule R3003;

  public static final org.apache.wss4j.common.bsp.BSPRule R3004;

  public static final org.apache.wss4j.common.bsp.BSPRule R3005;

  public static final org.apache.wss4j.common.bsp.BSPRule R3002;

  public static final org.apache.wss4j.common.bsp.BSPRule R5416;

  public static final org.apache.wss4j.common.bsp.BSPRule R5411;

  public static final org.apache.wss4j.common.bsp.BSPRule R5423;

  public static final org.apache.wss4j.common.bsp.BSPRule R5412;

  public static final org.apache.wss4j.common.bsp.BSPRule R5407;

  public static final org.apache.wss4j.common.bsp.BSPRule R5413;

  public static final org.apache.wss4j.common.bsp.BSPRule R3065;

  public static final org.apache.wss4j.common.bsp.BSPRule R5404;

  public static final org.apache.wss4j.common.bsp.BSPRule R5406;

  public static final org.apache.wss4j.common.bsp.BSPRule R5414;

  public static final org.apache.wss4j.common.bsp.BSPRule R5415;

  public static final org.apache.wss4j.common.bsp.BSPRule R5405;

  public static final org.apache.wss4j.common.bsp.BSPRule R5408;

  public static final org.apache.wss4j.common.bsp.BSPRule R5420;

  public static final org.apache.wss4j.common.bsp.BSPRule R5421;

  public static final org.apache.wss4j.common.bsp.BSPRule R5401;

  public static final org.apache.wss4j.common.bsp.BSPRule R5402;

  public static final org.apache.wss4j.common.bsp.BSPRule R5417;

  public static final org.apache.wss4j.common.bsp.BSPRule R5403;

  public static final org.apache.wss4j.common.bsp.BSPRule R5440;

  public static final org.apache.wss4j.common.bsp.BSPRule R5441;

  public static final org.apache.wss4j.common.bsp.BSPRule R3228;

  public static final org.apache.wss4j.common.bsp.BSPRule R3299;

  public static final org.apache.wss4j.common.bsp.BSPRule R3230;

  public static final org.apache.wss4j.common.bsp.BSPRule R3232;

  public static final org.apache.wss4j.common.bsp.BSPRule R3205;

  public static final org.apache.wss4j.common.bsp.BSPRule R3231;

  public static final org.apache.wss4j.common.bsp.BSPRule R3214;

  public static final org.apache.wss4j.common.bsp.BSPRule R3208;

  public static final org.apache.wss4j.common.bsp.BSPRule R3209;

  public static final org.apache.wss4j.common.bsp.BSPRule R5622;

  public static final org.apache.wss4j.common.bsp.BSPRule R5623;

  public static final org.apache.wss4j.common.bsp.BSPRule R5602;

  public static final org.apache.wss4j.common.bsp.BSPRule R5603;

  public static final org.apache.wss4j.common.bsp.BSPRule R5629;

  public static final org.apache.wss4j.common.bsp.BSPRule R5624;

  public static final org.apache.wss4j.common.bsp.BSPRule R5627;

  public static final org.apache.wss4j.common.bsp.BSPRule R5601;

  public static final org.apache.wss4j.common.bsp.BSPRule R5424;

  public static final org.apache.wss4j.common.bsp.BSPRule R5426;

  public static final org.apache.wss4j.common.bsp.BSPRule R5608;

  public static final org.apache.wss4j.common.bsp.BSPRule R3006;

  public static final org.apache.wss4j.common.bsp.BSPRule R5613;

  public static final org.apache.wss4j.common.bsp.BSPRule R3007;

  public static final org.apache.wss4j.common.bsp.BSPRule R5620;

  public static final org.apache.wss4j.common.bsp.BSPRule R5621;

  public static final org.apache.wss4j.common.bsp.BSPRule R5625;

  public static final org.apache.wss4j.common.bsp.BSPRule R5626;

  public static final org.apache.wss4j.common.bsp.BSPRule R5614;

  public static final org.apache.wss4j.common.bsp.BSPRule R5606;

  public static final org.apache.wss4j.common.bsp.BSPRule R3029;

  public static final org.apache.wss4j.common.bsp.BSPRule R3030;

  public static final org.apache.wss4j.common.bsp.BSPRule R3031;

  public static final org.apache.wss4j.common.bsp.BSPRule R3032;

  public static final org.apache.wss4j.common.bsp.BSPRule R4222;

  public static final org.apache.wss4j.common.bsp.BSPRule R4201;

  public static final org.apache.wss4j.common.bsp.BSPRule R4212;

  public static final org.apache.wss4j.common.bsp.BSPRule R4216;

  public static final org.apache.wss4j.common.bsp.BSPRule R4217;

  public static final org.apache.wss4j.common.bsp.BSPRule R4218;

  public static final org.apache.wss4j.common.bsp.BSPRule R4223;

  public static final org.apache.wss4j.common.bsp.BSPRule R4225;

  public static final org.apache.wss4j.common.bsp.BSPRule R4220;

  public static final org.apache.wss4j.common.bsp.BSPRule R4221;

  public static final org.apache.wss4j.common.bsp.BSPRule R4214;

  public static final org.apache.wss4j.common.bsp.BSPRule R4215;

  public static final org.apache.wss4j.common.bsp.BSPRule R3033;

  public static final org.apache.wss4j.common.bsp.BSPRule R5201;

  public static final org.apache.wss4j.common.bsp.BSPRule R5202;

  public static final org.apache.wss4j.common.bsp.BSPRule R5211;

  public static final org.apache.wss4j.common.bsp.BSPRule R5218;

  public static final org.apache.wss4j.common.bsp.BSPRule R5212;

  public static final org.apache.wss4j.common.bsp.BSPRule R5213;

  public static final org.apache.wss4j.common.bsp.BSPRule R5214;

  public static final org.apache.wss4j.common.bsp.BSPRule R5215;

  public static final org.apache.wss4j.common.bsp.BSPRule R5216;

  public static final org.apache.wss4j.common.bsp.BSPRule R5209;

  public static final org.apache.wss4j.common.bsp.BSPRule R5206;

  public static final org.apache.wss4j.common.bsp.BSPRule R5208;

  public static final org.apache.wss4j.common.bsp.BSPRule R5210;

  public static final org.apache.wss4j.common.bsp.BSPRule R5409;

  public static final org.apache.wss4j.common.bsp.BSPRule R6304;

  public static final org.apache.wss4j.common.bsp.BSPRule R6301;

  public static final org.apache.wss4j.common.bsp.BSPRule R6302;

  public static final org.apache.wss4j.common.bsp.BSPRule R6902;

  public static final org.apache.wss4j.common.bsp.BSPRule R6903;

  public static final org.apache.wss4j.common.bsp.BSPRule R6904;

  public static final org.apache.wss4j.common.bsp.BSPRule R6907;

  public static final org.apache.wss4j.common.bsp.BSPRule R6906;

  public static final org.apache.wss4j.common.bsp.BSPRule R6905;

  public static final org.apache.wss4j.common.bsp.BSPRule R6601;

  public static final org.apache.wss4j.common.bsp.BSPRule R6611;

  public static final org.apache.wss4j.common.bsp.BSPRule R6617;

  public static final org.apache.wss4j.common.bsp.BSPRule R6614;

  public static final org.apache.wss4j.common.bsp.BSPRule R6602;

  public static final org.apache.wss4j.common.bsp.BSPRule R6609;

  public static final org.apache.wss4j.common.bsp.BSPRule R6603;

  public static final org.apache.wss4j.common.bsp.BSPRule R6616;

  public static final org.apache.wss4j.common.bsp.BSPRule R6604;

  public static final org.apache.wss4j.common.bsp.BSPRule R6605;

  public static final org.apache.wss4j.common.bsp.BSPRule R6610;

  public static final org.apache.wss4j.common.bsp.BSPRule R6612;

  public static final org.apache.wss4j.common.bsp.BSPRule R6606;

  public static final org.apache.wss4j.common.bsp.BSPRule R6607;

  public static final org.apache.wss4j.common.bsp.BSPRule R6608;

  public static final org.apache.wss4j.common.bsp.BSPRule R6613;

  public static final org.apache.wss4j.common.bsp.BSPRule R3069;

  public static final org.apache.wss4j.common.bsp.BSPRule R3072;

  private final java.lang.String msg;

  private static final org.apache.wss4j.common.bsp.BSPRule[] $VALUES;

  public static org.apache.wss4j.common.bsp.BSPRule[] values();
    Code:
       0: getstatic     #1                  // Field $VALUES:[Lorg/apache/wss4j/common/bsp/BSPRule;
       3: invokevirtual #2                  // Method "[Lorg/apache/wss4j/common/bsp/BSPRule;".clone:()Ljava/lang/Object;
       6: checkcast     #3                  // class "[Lorg/apache/wss4j/common/bsp/BSPRule;"
       9: areturn

  public static org.apache.wss4j.common.bsp.BSPRule valueOf(java.lang.String);
    Code:
       0: ldc_w         #4                  // class org/apache/wss4j/common/bsp/BSPRule
       3: aload_0
       4: invokestatic  #5                  // Method java/lang/Enum.valueOf:(Ljava/lang/Class;Ljava/lang/String;)Ljava/lang/Enum;
       7: checkcast     #4                  // class org/apache/wss4j/common/bsp/BSPRule
      10: areturn

  private org.apache.wss4j.common.bsp.BSPRule(java.lang.String);
    Code:
       0: aload_0
       1: aload_1
       2: iload_2
       3: invokespecial #6                  // Method java/lang/Enum."<init>":(Ljava/lang/String;I)V
       6: aload_0
       7: aload_3
       8: putfield      #7                  // Field msg:Ljava/lang/String;
      11: return

  public java.lang.String getMsg();
    Code:
       0: aload_0
       1: getfield      #7                  // Field msg:Ljava/lang/String;
       4: areturn

  static {};
    Code:
       0: new           #4                  // class org/apache/wss4j/common/bsp/BSPRule
       3: dup
       4: ldc           #8                  // String R3203
       6: iconst_0
       7: ldc           #9                  // String A TIMESTAMP MUST contain exactly one CREATED
       9: invokespecial #10                 // Method "<init>":(Ljava/lang/String;ILjava/lang/String;)V
      12: putstatic     #11                 // Field R3203:Lorg/apache/wss4j/common/bsp/BSPRule;
      15: new           #4                  // class org/apache/wss4j/common/bsp/BSPRule
      18: dup
      19: ldc           #12                 // String R3224
      21: iconst_1
      22: ldc           #13                 // String Any TIMESTAMP MUST NOT contain more than one EXPIRES
      24: invokespecial #10                 // Method "<init>":(Ljava/lang/String;ILjava/lang/String;)V
      27: putstatic     #14                 // Field R3224:Lorg/apache/wss4j/common/bsp/BSPRule;
      30: new           #4                  // class org/apache/wss4j/common/bsp/BSPRule
      33: dup
      34: ldc           #15                 // String R3221
      36: iconst_2
      37: ldc           #16                 // String Any TIMESTAMP containing an EXPIRES MUST contain a CREATED that precedes its sibling EXPIRES
      39: invokespecial #10                 // Method "<init>":(Ljava/lang/String;ILjava/lang/String;)V
      42: putstatic     #17                 // Field R3221:Lorg/apache/wss4j/common/bsp/BSPRule;
      45: new           #4                  // class org/apache/wss4j/common/bsp/BSPRule
      48: dup
      49: ldc           #18                 // String R3222
      51: iconst_3
      52: ldc           #19                 // String Any TIMESTAMP MUST NOT contain anything other than CREATED or EXPIRES elements
      54: invokespecial #10                 // Method "<init>":(Ljava/lang/String;ILjava/lang/String;)V
      57: putstatic     #20                 // Field R3222:Lorg/apache/wss4j/common/bsp/BSPRule;
      60: new           #4                  // class org/apache/wss4j/common/bsp/BSPRule
      63: dup
      64: ldc           #21                 // String R3220
      66: iconst_4
      67: ldc           #22                 // String Any CREATED SHOULD NOT contain a seconds value with more than three digits to the right of the decimal (milliseconds)
      69: invokespecial #10                 // Method "<init>":(Ljava/lang/String;ILjava/lang/String;)V
      72: putstatic     #23                 // Field R3220:Lorg/apache/wss4j/common/bsp/BSPRule;
      75: new           #4                  // class org/apache/wss4j/common/bsp/BSPRule
      78: dup
      79: ldc           #24                 // String R3229
      81: iconst_5
      82: ldc           #25                 // String Any EXPIRES SHOULD NOT contain a seconds value with more than three digits to the right of the decimal (milliseconds)
      84: invokespecial #10                 // Method "<init>":(Ljava/lang/String;ILjava/lang/String;)V
      87: putstatic     #26                 // Field R3229:Lorg/apache/wss4j/common/bsp/BSPRule;
      90: new           #4                  // class org/apache/wss4j/common/bsp/BSPRule
      93: dup
      94: ldc           #27                 // String R3213
      96: bipush        6
      98: ldc           #28                 // String Any CREATED containing second values MUST specify seconds values less than 60
     100: invokespecial #10                 // Method "<init>":(Ljava/lang/String;ILjava/lang/String;)V
     103: putstatic     #29                 // Field R3213:Lorg/apache/wss4j/common/bsp/BSPRule;
     106: new           #4                  // class org/apache/wss4j/common/bsp/BSPRule
     109: dup
     110: ldc           #30                 // String R3215
     112: bipush        7
     114: ldc           #31                 // String Any EXPIRES containing second values MUST specify seconds values less than 60
     116: invokespecial #10                 // Method "<init>":(Ljava/lang/String;ILjava/lang/String;)V
     119: putstatic     #32                 // Field R3215:Lorg/apache/wss4j/common/bsp/BSPRule;
     122: new           #4                  // class org/apache/wss4j/common/bsp/BSPRule
     125: dup
     126: ldc           #33                 // String R3225
     128: bipush        8
     130: ldc           #34                 // String Any CREATED MUST NOT include a ValueType attribute
     132: invokespecial #10                 // Method "<init>":(Ljava/lang/String;ILjava/lang/String;)V
     135: putstatic     #35                 // Field R3225:Lorg/apache/wss4j/common/bsp/BSPRule;
     138: new           #4                  // class org/apache/wss4j/common/bsp/BSPRule
     141: dup
     142: ldc           #36                 // String R3226
     144: bipush        9
     146: ldc           #37                 // String Any EXPIRES MUST NOT include a ValueType attribute
     148: invokespecial #10                 // Method "<init>":(Ljava/lang/String;ILjava/lang/String;)V
     151: putstatic     #38                 // Field R3226:Lorg/apache/wss4j/common/bsp/BSPRule;
     154: new           #4                  // class org/apache/wss4j/common/bsp/BSPRule
     157: dup
     158: ldc           #39                 // String R3217
     160: bipush        10
     162: ldc           #40                 // String Any CREATED MUST contain time values in UTC format as specified by the XML Schema type (dateTime)
     164: invokespecial #10                 // Method "<init>":(Ljava/lang/String;ILjava/lang/String;)V
     167: putstatic     #41                 // Field R3217:Lorg/apache/wss4j/common/bsp/BSPRule;
     170: new           #4                  // class org/apache/wss4j/common/bsp/BSPRule
     173: dup
     174: ldc           #42                 // String R3223
     176: bipush        11
     178: ldc           #43                 // String Any EXPIRES MUST contain time values in UTC format as specified by the XML Schema type (dateTime)
     180: invokespecial #10                 // Method "<init>":(Ljava/lang/String;ILjava/lang/String;)V
     183: putstatic     #44                 // Field R3223:Lorg/apache/wss4j/common/bsp/BSPRule;
     186: new           #4                  // class org/apache/wss4j/common/bsp/BSPRule
     189: dup
     190: ldc           #45                 // String R3227
     192: bipush        12
     194: ldc           #46                 // String A SECURITY_HEADER MUST NOT contain more than one TIMESTAMP
     196: invokespecial #10                 // Method "<init>":(Ljava/lang/String;ILjava/lang/String;)V
     199: putstatic     #47                 // Field R3227:Lorg/apache/wss4j/common/bsp/BSPRule;
     202: new           #4                  // class org/apache/wss4j/common/bsp/BSPRule
     205: dup
     206: ldc           #48                 // String R3061
     208: bipush        13
     210: ldc           #49                 // String A SECURITY_TOKEN_REFERENCE MUST provide exactly one token reference
     212: invokespecial #10                 // Method "<init>":(Ljava/lang/String;ILjava/lang/String;)V
     215: putstatic     #50                 // Field R3061:Lorg/apache/wss4j/common/bsp/BSPRule;
     218: new           #4                  // class org/apache/wss4j/common/bsp/BSPRule
     221: dup
     222: ldc           #51                 // String R3074
     224: bipush        14
     226: ldc           #52                 // String Any wsse:11:TokenType Attribute in a SECURITY_TOKEN_REFERENCE MUST specify a value that a TokenType specified by a security token profile for the referenced SECURITY_TOKEN
     228: invokespecial #10                 // Method "<init>":(Ljava/lang/String;ILjava/lang/String;)V
     231: putstatic     #53                 // Field R3074:Lorg/apache/wss4j/common/bsp/BSPRule;
     234: new           #4                  // class org/apache/wss4j/common/bsp/BSPRule
     237: dup
     238: ldc           #54                 // String R3057
     240: bipush        15
     242: ldc           #55                 // String Any STR_REFERENCE MUST NOT reference a SECURITY_TOKEN_REFERENCE
     244: invokespecial #10                 // Method "<init>":(Ljava/lang/String;ILjava/lang/String;)V
     247: putstatic     #56                 // Field R3057:Lorg/apache/wss4j/common/bsp/BSPRule;
     250: new           #4                  // class org/apache/wss4j/common/bsp/BSPRule
     253: dup
     254: ldc           #57                 // String R3064
     256: bipush        16
     258: ldc           #58                 // String Any STR_REFERENCE MUST NOT reference an STR_EMBEDDED
     260: invokespecial #10                 // Method "<init>":(Ljava/lang/String;ILjava/lang/String;)V
     263: putstatic     #59                 // Field R3064:Lorg/apache/wss4j/common/bsp/BSPRule;
     266: new           #4                  // class org/apache/wss4j/common/bsp/BSPRule
     269: dup
     270: ldc           #60                 // String R3059
     272: bipush        17
     274: ldc           #61                 // String Any STR_REFERENCE MUST specify a ValueType attribute with the exception of STR_REFERENCE pointing to a SAML_V2_0_TOKEN or a KERBEROS_TOKEN or an ENCRYPTED_KEY_TOKEN
     276: invokespecial #10                 // Method "<init>":(Ljava/lang/String;ILjava/lang/String;)V
     279: putstatic     #62                 // Field R3059:Lorg/apache/wss4j/common/bsp/BSPRule;
     282: new           #4                  // class org/apache/wss4j/common/bsp/BSPRule
     285: dup
     286: ldc           #63                 // String R3058
     288: bipush        18
     290: ldc           #64                 // String Any STR_REFERENCE ValueType attribute MUST contain a value for the referenced SECURITY_TOKEN specified by the corresponding security token profile
     292: invokespecial #10                 // Method "<init>":(Ljava/lang/String;ILjava/lang/String;)V
     295: putstatic     #65                 // Field R3058:Lorg/apache/wss4j/common/bsp/BSPRule;
     298: new           #4                  // class org/apache/wss4j/common/bsp/BSPRule
     301: dup
     302: ldc           #66                 // String R3062
     304: bipush        19
     306: ldc           #67                 // String Any STR_REFERENCE MUST specify a URI attribute
     308: invokespecial #10                 // Method "<init>":(Ljava/lang/String;ILjava/lang/String;)V
     311: putstatic     #68                 // Field R3062:Lorg/apache/wss4j/common/bsp/BSPRule;
     314: new           #4                  // class org/apache/wss4j/common/bsp/BSPRule
     317: dup
     318: ldc           #69                 // String R3027
     320: bipush        20
     322: ldc           #70                 // String Any SECURITY_TOKEN_REFERENCE MUST NOT contain an STR_KEY_NAME
     324: invokespecial #10                 // Method "<init>":(Ljava/lang/String;ILjava/lang/String;)V
     327: putstatic     #71                 // Field R3027:Lorg/apache/wss4j/common/bsp/BSPRule;
     330: new           #4                  // class org/apache/wss4j/common/bsp/BSPRule
     333: dup
     334: ldc           #72                 // String R3054
     336: bipush        21
     338: ldc           #73                 // String Any STR_KEY_IDENTIFIER MUST specify a ValueType attribute
     340: invokespecial #10                 // Method "<init>":(Ljava/lang/String;ILjava/lang/String;)V
     343: putstatic     #74                 // Field R3054:Lorg/apache/wss4j/common/bsp/BSPRule;
     346: new           #4                  // class org/apache/wss4j/common/bsp/BSPRule
     349: dup
     350: ldc           #75                 // String R3063
     352: bipush        22
     354: ldc           #76                 // String Any STR_KEY_IDENTIFIER ValueType attribute MUST contain a value specified within the security token profile associated with the referenced SECURITY_TOKEN
     356: invokespecial #10                 // Method "<init>":(Ljava/lang/String;ILjava/lang/String;)V
     359: putstatic     #77                 // Field R3063:Lorg/apache/wss4j/common/bsp/BSPRule;
     362: new           #4                  // class org/apache/wss4j/common/bsp/BSPRule
     365: dup
     366: ldc           #78                 // String R3070
     368: bipush        23
     370: ldc           #79                 // String Any STR_KEY_IDENTIFIER that refers to a SECURITY_TOKEN other than a SAML_TOKEN MUST specify an EncodingType attribute
     372: invokespecial #10                 // Method "<init>":(Ljava/lang/String;ILjava/lang/String;)V
     375: putstatic     #80                 // Field R3070:Lorg/apache/wss4j/common/bsp/BSPRule;
     378: new           #4                  // class org/apache/wss4j/common/bsp/BSPRule
     381: dup
     382: ldc           #81                 // String R3071
     384: bipush        24
     386: ldc           #82                 // String Any STR_KEY_IDENTIFIER EncodingType attribute MUST have a value of \"http://docs.oasis-open.org/wss/2004/01/oasis-200401-wss-soap-message-security-1.0#Base64Binary\"
     388: invokespecial #10                 // Method "<init>":(Ljava/lang/String;ILjava/lang/String;)V
     391: putstatic     #83                 // Field R3071:Lorg/apache/wss4j/common/bsp/BSPRule;
     394: new           #4                  // class org/apache/wss4j/common/bsp/BSPRule
     397: dup
     398: ldc           #84                 // String R3060
     400: bipush        25
     402: ldc           #85                 // String Any STR_EMBEDDED MUST contain only a single child element which is an INTERNAL_SECURITY_TOKEN
     404: invokespecial #10                 // Method "<init>":(Ljava/lang/String;ILjava/lang/String;)V
     407: putstatic     #86                 // Field R3060:Lorg/apache/wss4j/common/bsp/BSPRule;
     410: new           #4                  // class org/apache/wss4j/common/bsp/BSPRule
     413: dup
     414: ldc           #87                 // String R3025
     416: bipush        26
     418: ldc           #88                 // String Any INTERNAL_SECURITY_TOKEN contained in an STR_EMBEDDED MUST be in the same format as if it were a child of a SECURITY_HEADER
     420: invokespecial #10                 // Method "<init>":(Ljava/lang/String;ILjava/lang/String;)V
     423: putstatic     #89                 // Field R3025:Lorg/apache/wss4j/common/bsp/BSPRule;
     426: new           #4                  // class org/apache/wss4j/common/bsp/BSPRule
     429: dup
     430: ldc           #90                 // String R3056
     432: bipush        27
     434: ldc           #91                 // String Any STR_EMBEDDED MUST NOT contain a wsse:SecurityTokenReference child element
     436: invokespecial #10                 // Method "<init>":(Ljava/lang/String;ILjava/lang/String;)V
     439: putstatic     #92                 // Field R3056:Lorg/apache/wss4j/common/bsp/BSPRule;
     442: new           #4                  // class org/apache/wss4j/common/bsp/BSPRule
     445: dup
     446: ldc           #93                 // String R3022
     448: bipush        28
     450: ldc           #94                 // String Any SECURITY_TOKEN_REFERENCE that references an INTERNAL_SECURITY_TOKEN which has a wsu:Id attribute MUST contain an STR_REFERENCE or STR_EMBEDDED
     452: invokespecial #10                 // Method "<init>":(Ljava/lang/String;ILjava/lang/String;)V
     455: putstatic     #95                 // Field R3022:Lorg/apache/wss4j/common/bsp/BSPRule;
     458: new           #4                  // class org/apache/wss4j/common/bsp/BSPRule
     461: dup
     462: ldc           #96                 // String R3023
     464: bipush        29
     466: ldc           #97                 // String Any SECURITY_TOKEN_REFERENCE that references an INTERNAL_SECURITY_TOKEN that is referenced several times SHOULD contain an STR_REFERENCE rather than an STR_EMBEDDED
     468: invokespecial #10                 // Method "<init>":(Ljava/lang/String;ILjava/lang/String;)V
     471: putstatic     #98                 // Field R3023:Lorg/apache/wss4j/common/bsp/BSPRule;
     474: new           #4                  // class org/apache/wss4j/common/bsp/BSPRule
     477: dup
     478: ldc           #99                 // String R5204
     480: bipush        30
     482: ldc           #100                // String Any STR_REFERENCE to an INTERNAL_SECURITY_TOKEN having an ID attribute MUST contain a URI attribute with a Shorthand XPointer value
     484: invokespecial #10                 // Method "<init>":(Ljava/lang/String;ILjava/lang/String;)V
     487: putstatic     #101                // Field R5204:Lorg/apache/wss4j/common/bsp/BSPRule;
     490: new           #4                  // class org/apache/wss4j/common/bsp/BSPRule
     493: dup
     494: ldc           #102                // String R5205
     496: bipush        31
     498: ldc           #103                // String Any INTERNAL_SECURITY_TOKEN that is not contained in an STR_EMBEDDED MUST precede all SECURITY_TOKEN_REFERENCE elements that reference it in the SOAP_ENVELOPE
     500: invokespecial #10                 // Method "<init>":(Ljava/lang/String;ILjava/lang/String;)V
     503: putstatic     #104                // Field R5205:Lorg/apache/wss4j/common/bsp/BSPRule;
     506: new           #4                  // class org/apache/wss4j/common/bsp/BSPRule
     509: dup
     510: ldc           #105                // String R3066
     512: bipush        32
     514: ldc           #106                // String Any STR_REFERENCE that is a descendant of a SECURITY_HEADER MUST NOT use a Shorthand XPointer to refer to an INTERNAL_SECURITY_TOKEN located in a SECURITY_HEADER other than the SECURITY_HEADER that contains the STR_REFERENCE
     516: invokespecial #10                 // Method "<init>":(Ljava/lang/String;ILjava/lang/String;)V
     519: putstatic     #107                // Field R3066:Lorg/apache/wss4j/common/bsp/BSPRule;
     522: new           #4                  // class org/apache/wss4j/common/bsp/BSPRule
     525: dup
     526: ldc           #108                // String R3067
     528: bipush        33
     530: ldc           #109                // String Any STR_REFERENCE that is a descendant of an ENCRYPTED_DATA MUST NOT use a Shorthand XPointer to refer to an INTERNAL_SECURITY_TOKEN located in a SECURITY_HEADER other than the SECURITY_HEADER containing a reference (EK_REFERENCE_LIST or an ENC_REFERENCE_LIST) to the ENCRYPTED_DATA
     532: invokespecial #10                 // Method "<init>":(Ljava/lang/String;ILjava/lang/String;)V
     535: putstatic     #110                // Field R3067:Lorg/apache/wss4j/common/bsp/BSPRule;
     538: new           #4                  // class org/apache/wss4j/common/bsp/BSPRule
     541: dup
     542: ldc           #111                // String R3024
     544: bipush        34
     546: ldc           #112                // String Any EXTERNAL_TOKEN_REFERENCE that can use an STR_REFERENCE MUST contain an STR_REFERENCE
     548: invokespecial #10                 // Method "<init>":(Ljava/lang/String;ILjava/lang/String;)V
     551: putstatic     #113                // Field R3024:Lorg/apache/wss4j/common/bsp/BSPRule;
     554: new           #4                  // class org/apache/wss4j/common/bsp/BSPRule
     557: dup
     558: ldc           #114                // String R3211
     560: bipush        35
     562: ldc           #115                // String Any SECURITY_TOKEN_REFERENCE MUST NOT reference a ds:KeyInfo element
     564: invokespecial #10                 // Method "<init>":(Ljava/lang/String;ILjava/lang/String;)V
     567: putstatic     #116                // Field R3211:Lorg/apache/wss4j/common/bsp/BSPRule;
     570: new           #4                  // class org/apache/wss4j/common/bsp/BSPRule
     573: dup
     574: ldc           #117                // String R3102
     576: bipush        36
     578: ldc           #118                // String A SIGNATURE MUST NOT be an Enveloping Signature as defined by the XML Signature specification
     580: invokespecial #10                 // Method "<init>":(Ljava/lang/String;ILjava/lang/String;)V
     583: putstatic     #119                // Field R3102:Lorg/apache/wss4j/common/bsp/BSPRule;
     586: new           #4                  // class org/apache/wss4j/common/bsp/BSPRule
     589: dup
     590: ldc           #120                // String R3104
     592: bipush        37
     594: ldc           #121                // String A SIGNATURE SHOULD NOT be an Enveloped Signature as defined by the XML Signature specification
     596: invokespecial #10                 // Method "<init>":(Ljava/lang/String;ILjava/lang/String;)V
     599: putstatic     #122                // Field R3104:Lorg/apache/wss4j/common/bsp/BSPRule;
     602: new           #4                  // class org/apache/wss4j/common/bsp/BSPRule
     605: dup
     606: ldc           #123                // String R3103
     608: bipush        38
     610: ldc           #124                // String A SIGNATURE SHOULD be a Detached Signature as defined by the XML Signature specification
     612: invokespecial #10                 // Method "<init>":(Ljava/lang/String;ILjava/lang/String;)V
     615: putstatic     #125                // Field R3103:Lorg/apache/wss4j/common/bsp/BSPRule;
     618: new           #4                  // class org/apache/wss4j/common/bsp/BSPRule
     621: dup
     622: ldc           #126                // String R3001
     624: bipush        39
     626: ldc           #127                // String Any SIG_REFERENCE SHOULD contain a URI attribute containing a Shorthand XPointer
     628: invokespecial #10                 // Method "<init>":(Ljava/lang/String;ILjava/lang/String;)V
     631: putstatic     #128                // Field R3001:Lorg/apache/wss4j/common/bsp/BSPRule;
     634: new           #4                  // class org/apache/wss4j/common/bsp/BSPRule
     637: dup
     638: ldc           #129                // String R3003
     640: bipush        40
     642: ldc           #130                // String Any SIG_REFERENCE to a SIGNATURE or descendant of a SIGNATURE MUST contain a URI attribute with a reference value that is a Shorthand XPointer to Local ID attribute defined by XML Signature
     644: invokespecial #10                 // Method "<init>":(Ljava/lang/String;ILjava/lang/String;)V
     647: putstatic     #131                // Field R3003:Lorg/apache/wss4j/common/bsp/BSPRule;
     650: new           #4                  // class org/apache/wss4j/common/bsp/BSPRule
     653: dup
     654: ldc           #132                // String R3004
     656: bipush        41
     658: ldc           #133                // String Any SIG_REFERENCE to an element defined in XML Encryption MUST contain a URI attribute with a reference value that is a Shorthand XPointer to Local ID attribute defined by XML Encryption
     660: invokespecial #10                 // Method "<init>":(Ljava/lang/String;ILjava/lang/String;)V
     663: putstatic     #134                // Field R3004:Lorg/apache/wss4j/common/bsp/BSPRule;
     666: new           #4                  // class org/apache/wss4j/common/bsp/BSPRule
     669: dup
     670: ldc           #135                // String R3005
     672: bipush        42
     674: ldc           #136                // String Any SIG_REFERENCE to an element that is not defined in XML Encryption, a SIGNATURE, or a descendant of a SIGNATURE SHOULD contain a URI attribute with a reference value that is a Shorthand XPointer to a wsu:Id attribute
     676: invokespecial #10                 // Method "<init>":(Ljava/lang/String;ILjava/lang/String;)V
     679: putstatic     #137                // Field R3005:Lorg/apache/wss4j/common/bsp/BSPRule;
     682: new           #4                  // class org/apache/wss4j/common/bsp/BSPRule
     685: dup
     686: ldc           #138                // String R3002
     688: bipush        43
     690: ldc           #139                // String Any SIG_REFERENCE to an element that does not have an ID attribute MUST contain a TRANSFORM with an Algorithm attribute value of \"http://www.w3.org/2002/06/xmldsig-filter2\"
     692: invokespecial #10                 // Method "<init>":(Ljava/lang/String;ILjava/lang/String;)V
     695: putstatic     #140                // Field R3002:Lorg/apache/wss4j/common/bsp/BSPRule;
     698: new           #4                  // class org/apache/wss4j/common/bsp/BSPRule
     701: dup
     702: ldc           #141                // String R5416
     704: bipush        44
     706: ldc           #142                // String Any SIG_REFERENCE MUST contain a SIG_TRANSFORMS child element
     708: invokespecial #10                 // Method "<init>":(Ljava/lang/String;ILjava/lang/String;)V
     711: putstatic     #143                // Field R5416:Lorg/apache/wss4j/common/bsp/BSPRule;
     714: new           #4                  // class org/apache/wss4j/common/bsp/BSPRule
     717: dup
     718: ldc           #144                // String R5411
     720: bipush        45
     722: ldc           #145                // String Any SIG_TRANSFORMS MUST contain at least one SIG_TRANSFORM child element
     724: invokespecial #10                 // Method "<init>":(Ljava/lang/String;ILjava/lang/String;)V
     727: putstatic     #146                // Field R5411:Lorg/apache/wss4j/common/bsp/BSPRule;
     730: new           #4                  // class org/apache/wss4j/common/bsp/BSPRule
     733: dup
     734: ldc           #147                // String R5423
     736: bipush        46
     738: ldc           #148                // String Any SIG_TRANSFORM Algorithm attribute MUST have a value of \"http://www.w3.org/2001/10/xml-exc-c14n#\" or \"http://www.w3.org/2002/06/xmldsig-filter2\" or \"http://docs.oasis-open.org/wss/2004/01/oasis-200401-wss-soap-message-security-1.0#STR-Transform\" or \"http://www.w3.org/2000/09/xmldsig#enveloped-signature\" or \"http://docs.oasis-open.org/wss/oasis-wss-SwAProfile-1.1#Attachment-Content-Signature-Transform\" or \"http://docs.oasis-open.org/wss/oasis-wss-SwAProfile-1.1#Attachment-Complete-Signature-Transform\"
     740: invokespecial #10                 // Method "<init>":(Ljava/lang/String;ILjava/lang/String;)V
     743: putstatic     #149                // Field R5423:Lorg/apache/wss4j/common/bsp/BSPRule;
     746: new           #4                  // class org/apache/wss4j/common/bsp/BSPRule
     749: dup
     750: ldc           #150                // String R5412
     752: bipush        47
     754: ldc           #151                // String Any SIG_TRANSFORMS MUST contain as its last child a SIG_TRANSFORM with an Algorithm attribute with a value of \"http://www.w3.org/2001/10/xml-exc-c14n#\" or \"http://docs.oasis-open.org/wss/2004/01/oasis-200401-wss-soap-message-security-1.0#STR-Transform\" or \"http://docs.oasis-open.org/wss/oasis-wss-SwAProfile-1.1#Attachment-Content-Signature-Transform\" or \"http://docs.oasis-open.org/wss/oasis-wss-SwAProfile-1.1#Attachment-Complete-Signature-Transform\"
     756: invokespecial #10                 // Method "<init>":(Ljava/lang/String;ILjava/lang/String;)V
     759: putstatic     #152                // Field R5412:Lorg/apache/wss4j/common/bsp/BSPRule;
     762: new           #4                  // class org/apache/wss4j/common/bsp/BSPRule
     765: dup
     766: ldc           #153                // String R5407
     768: bipush        48
     770: ldc           #154                // String Any SIG_TRANSFORM with an Algorithm attribute with a value of \"http://www.w3.org/2001/10/xml-exc-c14n#\" MUST contain an INCLUSIVE_NAMESPACES with an PrefixList attribute unless the PrefixList is empty
     772: invokespecial #10                 // Method "<init>":(Ljava/lang/String;ILjava/lang/String;)V
     775: putstatic     #155                // Field R5407:Lorg/apache/wss4j/common/bsp/BSPRule;
     778: new           #4                  // class org/apache/wss4j/common/bsp/BSPRule
     781: dup
     782: ldc           #156                // String R5413
     784: bipush        49
     786: ldc           #157                // String Any SIG_TRANSFORM with an Algorithm attribute with a value of \"http://docs.oasis-open.org/wss/2004/01/oasis-200401-wss-soap-message-security-1.0#STR-Transform\" MUST have an INCLUSIVE_NAMESPACES with an PrefixList attribute unless the PrefixList is empty
     788: invokespecial #10                 // Method "<init>":(Ljava/lang/String;ILjava/lang/String;)V
     791: putstatic     #158                // Field R5413:Lorg/apache/wss4j/common/bsp/BSPRule;
     794: new           #4                  // class org/apache/wss4j/common/bsp/BSPRule
     797: dup
     798: ldc           #159                // String R3065
     800: bipush        50
     802: ldc           #160                // String Any SIG_TRANSFORM with an Algorithm attribute with a value of \"http://docs.oasis-open.org/wss/2004/01/oasis-200401-wss-soap-message-security-1.0#STR-Transform\" MUST contain a child wsse:TransformationParameters element containing a child ds:CanonicalizationMethod element
     804: invokespecial #10                 // Method "<init>":(Ljava/lang/String;ILjava/lang/String;)V
     807: putstatic     #161                // Field R3065:Lorg/apache/wss4j/common/bsp/BSPRule;
     810: new           #4                  // class org/apache/wss4j/common/bsp/BSPRule
     813: dup
     814: ldc           #162                // String R5404
     816: bipush        51
     818: ldc           #163                // String Any CANONICALIZATION_METHOD Algorithm attribute MUST have a value of \"http://www.w3.org/2001/10/xml-exc-c14n#\" indicating that it uses Exclusive C14N without comments for canonicalization
     820: invokespecial #10                 // Method "<init>":(Ljava/lang/String;ILjava/lang/String;)V
     823: putstatic     #164                // Field R5404:Lorg/apache/wss4j/common/bsp/BSPRule;
     826: new           #4                  // class org/apache/wss4j/common/bsp/BSPRule
     829: dup
     830: ldc           #165                // String R5406
     832: bipush        52
     834: ldc           #166                // String Any CANONICALIZATION_METHOD MUST contain an INCLUSIVE_NAMESPACES with a PrefixList attribute unless the PrefixList is empty
     836: invokespecial #10                 // Method "<init>":(Ljava/lang/String;ILjava/lang/String;)V
     839: putstatic     #167                // Field R5406:Lorg/apache/wss4j/common/bsp/BSPRule;
     842: new           #4                  // class org/apache/wss4j/common/bsp/BSPRule
     845: dup
     846: ldc           #168                // String R5414
     848: bipush        53
     850: ldc           #169                // String A RECEIVER MUST be capable of accepting and processing an INCLUSIVE_NAMESPACES PrefixList attribute containing prefixes in any order within the string
     852: invokespecial #10                 // Method "<init>":(Ljava/lang/String;ILjava/lang/String;)V
     855: putstatic     #170                // Field R5414:Lorg/apache/wss4j/common/bsp/BSPRule;
     858: new           #4                  // class org/apache/wss4j/common/bsp/BSPRule
     861: dup
     862: ldc           #171                // String R5415
     864: bipush        54
     866: ldc           #172                // String A RECEIVER MUST be capable of accepting and processing an INCLUSIVE_NAMESPACES PrefixList attribute containing arbitrary whitespace before, after and between the prefixes within the string
     868: invokespecial #10                 // Method "<init>":(Ljava/lang/String;ILjava/lang/String;)V
     871: putstatic     #173                // Field R5415:Lorg/apache/wss4j/common/bsp/BSPRule;
     874: new           #4                  // class org/apache/wss4j/common/bsp/BSPRule
     877: dup
     878: ldc           #174                // String R5405
     880: bipush        55
     882: ldc           #175                // String Any INCLUSIVE_NAMESPACES MUST contain the prefix of all namespaces that are in-scope and desired to be protected, but not visibly utilized, for the element being signed and its descendants, per Exclusive XML Canonicalization Version 1.0
     884: invokespecial #10                 // Method "<init>":(Ljava/lang/String;ILjava/lang/String;)V
     887: putstatic     #176                // Field R5405:Lorg/apache/wss4j/common/bsp/BSPRule;
     890: new           #4                  // class org/apache/wss4j/common/bsp/BSPRule
     893: dup
     894: ldc           #177                // String R5408
     896: bipush        56
     898: ldc           #178                // String Any INCLUSIVE_NAMESPACES MUST contain the string \"#default\" if a default namespace is in-scope and desired to be protected, but not visibly utilized, for the element being signed and its descendants, per Exclusive XML Canonicalization Version 1.0
     900: invokespecial #10                 // Method "<init>":(Ljava/lang/String;ILjava/lang/String;)V
     903: putstatic     #179                // Field R5408:Lorg/apache/wss4j/common/bsp/BSPRule;
     906: new           #4                  // class org/apache/wss4j/common/bsp/BSPRule
     909: dup
     910: ldc           #180                // String R5420
     912: bipush        57
     914: ldc           #181                // String Any DIGEST_METHOD Algorithm attribute SHOULD have the value \"http://www.w3.org/2000/09/xmldsig#sha1\"
     916: invokespecial #10                 // Method "<init>":(Ljava/lang/String;ILjava/lang/String;)V
     919: putstatic     #182                // Field R5420:Lorg/apache/wss4j/common/bsp/BSPRule;
     922: new           #4                  // class org/apache/wss4j/common/bsp/BSPRule
     925: dup
     926: ldc           #183                // String R5421
     928: bipush        58
     930: ldc           #184                // String Any SIGNATURE_METHOD Algorithm attribute SHOULD have a value of \"http://www.w3.org/2000/09/xmldsig#hmac-sha1\" or \"http://www.w3.org/2000/09/xmldsig#rsa-sha1\"
     932: invokespecial #10                 // Method "<init>":(Ljava/lang/String;ILjava/lang/String;)V
     935: putstatic     #185                // Field R5421:Lorg/apache/wss4j/common/bsp/BSPRule;
     938: new           #4                  // class org/apache/wss4j/common/bsp/BSPRule
     941: dup
     942: ldc           #186                // String R5401
     944: bipush        59
     946: ldc           #187                // String Any SIGNATURE_METHOD MUST NOT contain a ds:HMACOutputLength child element
     948: invokespecial #10                 // Method "<init>":(Ljava/lang/String;ILjava/lang/String;)V
     951: putstatic     #188                // Field R5401:Lorg/apache/wss4j/common/bsp/BSPRule;
     954: new           #4                  // class org/apache/wss4j/common/bsp/BSPRule
     957: dup
     958: ldc           #189                // String R5402
     960: bipush        60
     962: ldc           #190                // String Any SIG_KEY_INFO MUST contain exactly one child element
     964: invokespecial #10                 // Method "<init>":(Ljava/lang/String;ILjava/lang/String;)V
     967: putstatic     #191                // Field R5402:Lorg/apache/wss4j/common/bsp/BSPRule;
     970: new           #4                  // class org/apache/wss4j/common/bsp/BSPRule
     973: dup
     974: ldc           #192                // String R5417
     976: bipush        61
     978: ldc           #193                // String Any SIG_KEY_INFO MUST contain a SECURITY_TOKEN_REFERENCE child element
     980: invokespecial #10                 // Method "<init>":(Ljava/lang/String;ILjava/lang/String;)V
     983: putstatic     #194                // Field R5417:Lorg/apache/wss4j/common/bsp/BSPRule;
     986: new           #4                  // class org/apache/wss4j/common/bsp/BSPRule
     989: dup
     990: ldc           #195                // String R5403
     992: bipush        62
     994: ldc           #196                // String A SIGNATURE MUST NOT contain a ds:Manifest descendant element
     996: invokespecial #10                 // Method "<init>":(Ljava/lang/String;ILjava/lang/String;)V
     999: putstatic     #197                // Field R5403:Lorg/apache/wss4j/common/bsp/BSPRule;
    1002: new           #4                  // class org/apache/wss4j/common/bsp/BSPRule
    1005: dup
    1006: ldc           #198                // String R5440
    1008: bipush        63
    1010: ldc           #199                // String A SIGNATURE MUST NOT have any xenc:EncryptedData elements amongst its descendants
    1012: invokespecial #10                 // Method "<init>":(Ljava/lang/String;ILjava/lang/String;)V
    1015: putstatic     #200                // Field R5440:Lorg/apache/wss4j/common/bsp/BSPRule;
    1018: new           #4                  // class org/apache/wss4j/common/bsp/BSPRule
    1021: dup
    1022: ldc           #201                // String R5441
    1024: bipush        64
    1026: ldc           #202                // String A SIGNATURE_CONFIRMATION MUST contain a wsu:Id attribute
    1028: invokespecial #10                 // Method "<init>":(Ljava/lang/String;ILjava/lang/String;)V
    1031: putstatic     #203                // Field R5441:Lorg/apache/wss4j/common/bsp/BSPRule;
    1034: new           #4                  // class org/apache/wss4j/common/bsp/BSPRule
    1037: dup
    1038: ldc           #204                // String R3228
    1040: bipush        65
    1042: ldc           #205                // String A soap:Header element in a SECURE_ENVELOPE MUST NOT contain any child ENCRYPTED_DATA
    1044: invokespecial #10                 // Method "<init>":(Ljava/lang/String;ILjava/lang/String;)V
    1047: putstatic     #206                // Field R3228:Lorg/apache/wss4j/common/bsp/BSPRule;
    1050: new           #4                  // class org/apache/wss4j/common/bsp/BSPRule
    1053: dup
    1054: ldc           #207                // String R3299
    1056: bipush        66
    1058: ldc           #208                // String A soap:Header element in a SECURE_ENVELOPE MAY contain ENCRYPTED_HEADER children
    1060: invokespecial #10                 // Method "<init>":(Ljava/lang/String;ILjava/lang/String;)V
    1063: putstatic     #209                // Field R3299:Lorg/apache/wss4j/common/bsp/BSPRule;
    1066: new           #4                  // class org/apache/wss4j/common/bsp/BSPRule
    1069: dup
    1070: ldc           #210                // String R3230
    1072: bipush        67
    1074: ldc           #211                // String An ENCRYPTED_HEADER MUST NOT contain any children other than a single required ENCRYPTED_DATA
    1076: invokespecial #10                 // Method "<init>":(Ljava/lang/String;ILjava/lang/String;)V
    1079: putstatic     #212                // Field R3230:Lorg/apache/wss4j/common/bsp/BSPRule;
    1082: new           #4                  // class org/apache/wss4j/common/bsp/BSPRule
    1085: dup
    1086: ldc           #213                // String R3232
    1088: bipush        68
    1090: ldc           #214                // String In cases where a wsu:Id does exist on the ENCRYPTED_HEADER, the child ENCRYPTED_DATA MAY contain an Id attribute
    1092: invokespecial #10                 // Method "<init>":(Ljava/lang/String;ILjava/lang/String;)V
    1095: putstatic     #215                // Field R3232:Lorg/apache/wss4j/common/bsp/BSPRule;
    1098: new           #4                  // class org/apache/wss4j/common/bsp/BSPRule
    1101: dup
    1102: ldc           #216                // String R3205
    1104: bipush        69
    1106: ldc           #217                // String Any ENC_REFERENCE_LIST produced as part of an encryption step MUST use a single key
    1108: invokespecial #10                 // Method "<init>":(Ljava/lang/String;ILjava/lang/String;)V
    1111: putstatic     #218                // Field R3205:Lorg/apache/wss4j/common/bsp/BSPRule;
    1114: new           #4                  // class org/apache/wss4j/common/bsp/BSPRule
    1117: dup
    1118: ldc           #219                // String R3231
    1120: bipush        70
    1122: ldc           #220                // String Any ENC_REFERENCE_LIST MUST contain an xenc:DataReference element for each ENCRYPTED_DATA produced in the associated encryption step
    1124: invokespecial #10                 // Method "<init>":(Ljava/lang/String;ILjava/lang/String;)V
    1127: putstatic     #221                // Field R3231:Lorg/apache/wss4j/common/bsp/BSPRule;
    1130: new           #4                  // class org/apache/wss4j/common/bsp/BSPRule
    1133: dup
    1134: ldc           #222                // String R3214
    1136: bipush        71
    1138: ldc           #223                // String Any EK_REFERENCE_LIST MUST contain a xenc:DataReference for each ENCRYPTED_DATA produced in the associated encryption step
    1140: invokespecial #10                 // Method "<init>":(Ljava/lang/String;ILjava/lang/String;)V
    1143: putstatic     #224                // Field R3214:Lorg/apache/wss4j/common/bsp/BSPRule;
    1146: new           #4                  // class org/apache/wss4j/common/bsp/BSPRule
    1149: dup
    1150: ldc           #225                // String R3208
    1152: bipush        72
    1154: ldc           #226                // String Any ENCRYPTED_KEY MUST precede any ENCRYPTED_DATA in the same SECURITY_HEADER referenced by the associated EK_REFERENCE_LIST
    1156: invokespecial #10                 // Method "<init>":(Ljava/lang/String;ILjava/lang/String;)V
    1159: putstatic     #227                // Field R3208:Lorg/apache/wss4j/common/bsp/BSPRule;
    1162: new           #4                  // class org/apache/wss4j/common/bsp/BSPRule
    1165: dup
    1166: ldc           #228                // String R3209
    1168: bipush        73
    1170: ldc           #229                // String Any ENCRYPTED_KEY MUST NOT specify a Type attribute
    1172: invokespecial #10                 // Method "<init>":(Ljava/lang/String;ILjava/lang/String;)V
    1175: putstatic     #230                // Field R3209:Lorg/apache/wss4j/common/bsp/BSPRule;
    1178: new           #4                  // class org/apache/wss4j/common/bsp/BSPRule
    1181: dup
    1182: ldc           #231                // String R5622
    1184: bipush        74
    1186: ldc           #232                // String Any ENCRYPTED_KEY MUST NOT specify a MimeType attribute
    1188: invokespecial #10                 // Method "<init>":(Ljava/lang/String;ILjava/lang/String;)V
    1191: putstatic     #233                // Field R5622:Lorg/apache/wss4j/common/bsp/BSPRule;
    1194: new           #4                  // class org/apache/wss4j/common/bsp/BSPRule
    1197: dup
    1198: ldc           #234                // String R5623
    1200: bipush        75
    1202: ldc           #235                // String Any ENCRYPTED_KEY MUST NOT specify a Encoding attribute
    1204: invokespecial #10                 // Method "<init>":(Ljava/lang/String;ILjava/lang/String;)V
    1207: putstatic     #236                // Field R5623:Lorg/apache/wss4j/common/bsp/BSPRule;
    1210: new           #4                  // class org/apache/wss4j/common/bsp/BSPRule
    1213: dup
    1214: ldc           #237                // String R5602
    1216: bipush        76
    1218: ldc           #238                // String Any ENCRYPTED_KEY MUST NOT contain a Recipient attribute
    1220: invokespecial #10                 // Method "<init>":(Ljava/lang/String;ILjava/lang/String;)V
    1223: putstatic     #239                // Field R5602:Lorg/apache/wss4j/common/bsp/BSPRule;
    1226: new           #4                  // class org/apache/wss4j/common/bsp/BSPRule
    1229: dup
    1230: ldc           #240                // String R5603
    1232: bipush        77
    1234: ldc           #241                // String Any ENCRYPTED_KEY MUST contain an xenc:EncryptionMethod child element
    1236: invokespecial #10                 // Method "<init>":(Ljava/lang/String;ILjava/lang/String;)V
    1239: putstatic     #242                // Field R5603:Lorg/apache/wss4j/common/bsp/BSPRule;
    1242: new           #4                  // class org/apache/wss4j/common/bsp/BSPRule
    1245: dup
    1246: ldc           #243                // String R5629
    1248: bipush        78
    1250: ldc           #244                // String An ENCRYPTED_DATA which is not referenced from an ENCRYPTED_KEY MUST contain a ds:KeyInfo
    1252: invokespecial #10                 // Method "<init>":(Ljava/lang/String;ILjava/lang/String;)V
    1255: putstatic     #245                // Field R5629:Lorg/apache/wss4j/common/bsp/BSPRule;
    1258: new           #4                  // class org/apache/wss4j/common/bsp/BSPRule
    1261: dup
    1262: ldc           #246                // String R5624
    1264: bipush        79
    1266: ldc           #247                // String In cases where a wsu:Id does not exist on the ENCRYPTED_HEADER, the child ENCRYPTED_DATA MUST contain an ID attribute
    1268: invokespecial #10                 // Method "<init>":(Ljava/lang/String;ILjava/lang/String;)V
    1271: putstatic     #248                // Field R5624:Lorg/apache/wss4j/common/bsp/BSPRule;
    1274: new           #4                  // class org/apache/wss4j/common/bsp/BSPRule
    1277: dup
    1278: ldc           #249                // String R5627
    1280: bipush        80
    1282: ldc           #250                // String In cases where an ID does not exist on the ENCRYPTED_DATA, the parent ENCRYPTED_HEADER MUST contain a wsu:Id attribute
    1284: invokespecial #10                 // Method "<init>":(Ljava/lang/String;ILjava/lang/String;)V
    1287: putstatic     #251                // Field R5627:Lorg/apache/wss4j/common/bsp/BSPRule;
    1290: new           #4                  // class org/apache/wss4j/common/bsp/BSPRule
    1293: dup
    1294: ldc           #252                // String R5601
    1296: bipush        81
    1298: ldc           #253                // String Any ENCRYPTED_DATA MUST contain an xenc:EncryptionMethod child element
    1300: invokespecial #10                 // Method "<init>":(Ljava/lang/String;ILjava/lang/String;)V
    1303: putstatic     #254                // Field R5601:Lorg/apache/wss4j/common/bsp/BSPRule;
    1306: new           #4                  // class org/apache/wss4j/common/bsp/BSPRule
    1309: dup
    1310: ldc           #255                // String R5424
    1312: bipush        82
    1314: ldc_w         #256                // String Any ENC_KEY_INFO MUST have exactly one child element
    1317: invokespecial #10                 // Method "<init>":(Ljava/lang/String;ILjava/lang/String;)V
    1320: putstatic     #257                // Field R5424:Lorg/apache/wss4j/common/bsp/BSPRule;
    1323: new           #4                  // class org/apache/wss4j/common/bsp/BSPRule
    1326: dup
    1327: ldc_w         #258                // String R5426
    1330: bipush        83
    1332: ldc_w         #259                // String Any ENC_KEY_INFO MUST contain a child SECURITY_TOKEN_REFERENCE
    1335: invokespecial #10                 // Method "<init>":(Ljava/lang/String;ILjava/lang/String;)V
    1338: putstatic     #260                // Field R5426:Lorg/apache/wss4j/common/bsp/BSPRule;
    1341: new           #4                  // class org/apache/wss4j/common/bsp/BSPRule
    1344: dup
    1345: ldc_w         #261                // String R5608
    1348: bipush        84
    1350: ldc_w         #262                // String Any ENC_DATA_REFERENCE MUST contain a URI attribute containing a Shorthand XPointer reference value based on either the Id attribute of the referenced ENCRYPTED_DATA or the wsu:Id attribute of the referenced ENCRYPTED_HEADER
    1353: invokespecial #10                 // Method "<init>":(Ljava/lang/String;ILjava/lang/String;)V
    1356: putstatic     #263                // Field R5608:Lorg/apache/wss4j/common/bsp/BSPRule;
    1359: new           #4                  // class org/apache/wss4j/common/bsp/BSPRule
    1362: dup
    1363: ldc_w         #264                // String R3006
    1366: bipush        85
    1368: ldc_w         #265                // String Any EK_DATA_REFERENCE MUST contain a URI attribute containing a Shorthand XPointer reference value based on either the Id attribute of the referenced ENCRYPTED_DATA or the wsu:Id attribute of the referenced ENCRYPTED_HEADER
    1371: invokespecial #10                 // Method "<init>":(Ljava/lang/String;ILjava/lang/String;)V
    1374: putstatic     #266                // Field R3006:Lorg/apache/wss4j/common/bsp/BSPRule;
    1377: new           #4                  // class org/apache/wss4j/common/bsp/BSPRule
    1380: dup
    1381: ldc_w         #267                // String R5613
    1384: bipush        86
    1386: ldc_w         #268                // String Any ENC_KEY_REFERENCE MUST contain a URI attribute containing a Shorthand XPointer reference value based on the Id attribute of the referred to ENCRYPTED_KEY
    1389: invokespecial #10                 // Method "<init>":(Ljava/lang/String;ILjava/lang/String;)V
    1392: putstatic     #269                // Field R5613:Lorg/apache/wss4j/common/bsp/BSPRule;
    1395: new           #4                  // class org/apache/wss4j/common/bsp/BSPRule
    1398: dup
    1399: ldc_w         #270                // String R3007
    1402: bipush        87
    1404: ldc_w         #271                // String Any EK_KEY_REFERENCE MUST contain a URI attribute containing a Shorthand XPointer reference value based on the Id attribute of the referred to ENCRYPTED_KEY
    1407: invokespecial #10                 // Method "<init>":(Ljava/lang/String;ILjava/lang/String;)V
    1410: putstatic     #272                // Field R3007:Lorg/apache/wss4j/common/bsp/BSPRule;
    1413: new           #4                  // class org/apache/wss4j/common/bsp/BSPRule
    1416: dup
    1417: ldc_w         #273                // String R5620
    1420: bipush        88
    1422: ldc_w         #274                // String Any ED_ENCRYPTION_METHOD Algorithm attribute MUST have a value of \"http://www.w3.org/2001/04/xmlenc#tripledes-cbc\", \"http://www.w3.org/2001/04/xmlenc#aes128-cbc\" or \"http://www.w3.org/2001/04/xmlenc#aes256-cbc\"
    1425: invokespecial #10                 // Method "<init>":(Ljava/lang/String;ILjava/lang/String;)V
    1428: putstatic     #275                // Field R5620:Lorg/apache/wss4j/common/bsp/BSPRule;
    1431: new           #4                  // class org/apache/wss4j/common/bsp/BSPRule
    1434: dup
    1435: ldc_w         #276                // String R5621
    1438: bipush        89
    1440: ldc_w         #277                // String When used for Key Transport, any EK_ENCRYPTION_METHOD Algorithm attribute MUST have a value of \"http://www.w3.org/2001/04/xmlenc#rsa-1_5\" or \"http://www.w3.org/2001/04/xmlenc#rsa-oaep-mgf1p\"
    1443: invokespecial #10                 // Method "<init>":(Ljava/lang/String;ILjava/lang/String;)V
    1446: putstatic     #278                // Field R5621:Lorg/apache/wss4j/common/bsp/BSPRule;
    1449: new           #4                  // class org/apache/wss4j/common/bsp/BSPRule
    1452: dup
    1453: ldc_w         #279                // String R5625
    1456: bipush        90
    1458: ldc_w         #280                // String When used for Key Wrap, any EK_ENCRYPTION_METHOD Algorithm attribute MUST have a value of \"http://www.w3.org/2001/04/xmlenc#kw-tripledes\", \"http://www.w3.org/2001/04/xmlenc#kw-aes128\", or \"http://www.w3.org/2001/04/xmlenc#kw-aes256\"
    1461: invokespecial #10                 // Method "<init>":(Ljava/lang/String;ILjava/lang/String;)V
    1464: putstatic     #281                // Field R5625:Lorg/apache/wss4j/common/bsp/BSPRule;
    1467: new           #4                  // class org/apache/wss4j/common/bsp/BSPRule
    1470: dup
    1471: ldc_w         #282                // String R5626
    1474: bipush        91
    1476: ldc_w         #283                // String Any EK_ENCRYPTION_METHOD Algorithm attribute MUST have a value of \"http://www.w3.org/2001/04/xmlenc#rsa-1_5\" or \"http://www.w3.org/2001/04/xmlenc#rsa-oaep-mgf1p\" or \"http://www.w3.org/2001/04/xmlenc#kw-tripledes\" or \"http://www.w3.org/2001/04/xmlenc#kw-aes128\" or \"http://www.w3.org/2001/04/xmlenc#kw-aes256\"
    1479: invokespecial #10                 // Method "<init>":(Ljava/lang/String;ILjava/lang/String;)V
    1482: putstatic     #284                // Field R5626:Lorg/apache/wss4j/common/bsp/BSPRule;
    1485: new           #4                  // class org/apache/wss4j/common/bsp/BSPRule
    1488: dup
    1489: ldc_w         #285                // String R5614
    1492: bipush        92
    1494: ldc_w         #286                // String A HEADER encrypted as a result of an encryption step MUST be replaced by a corresponding ENCRYPTED_HEADER
    1497: invokespecial #10                 // Method "<init>":(Ljava/lang/String;ILjava/lang/String;)V
    1500: putstatic     #287                // Field R5614:Lorg/apache/wss4j/common/bsp/BSPRule;
    1503: new           #4                  // class org/apache/wss4j/common/bsp/BSPRule
    1506: dup
    1507: ldc_w         #288                // String R5606
    1510: bipush        93
    1512: ldc_w         #289                // String Any encrypted element or element content within a SECURE_ENVELOPE, encrypted as a result of an encryption step, MUST be replaced by a corresponding ENCRYPTED_DATA, unless the element is a HEADER_ELEMENT
    1515: invokespecial #10                 // Method "<init>":(Ljava/lang/String;ILjava/lang/String;)V
    1518: putstatic     #290                // Field R5606:Lorg/apache/wss4j/common/bsp/BSPRule;
    1521: new           #4                  // class org/apache/wss4j/common/bsp/BSPRule
    1524: dup
    1525: ldc_w         #291                // String R3029
    1528: bipush        94
    1530: ldc_w         #292                // String Any BINARY_SECURITY_TOKEN MUST specify an EncodingType attribute
    1533: invokespecial #10                 // Method "<init>":(Ljava/lang/String;ILjava/lang/String;)V
    1536: putstatic     #293                // Field R3029:Lorg/apache/wss4j/common/bsp/BSPRule;
    1539: new           #4                  // class org/apache/wss4j/common/bsp/BSPRule
    1542: dup
    1543: ldc_w         #294                // String R3030
    1546: bipush        95
    1548: ldc_w         #295                // String Any BINARY_SECURITY_TOKEN EncodingType attribute MUST have a value of \"http://docs.oasis-open.org/wss/2004/01/oasis-200401-wss-soap-message-security-1.0#Base64Binary\"
    1551: invokespecial #10                 // Method "<init>":(Ljava/lang/String;ILjava/lang/String;)V
    1554: putstatic     #296                // Field R3030:Lorg/apache/wss4j/common/bsp/BSPRule;
    1557: new           #4                  // class org/apache/wss4j/common/bsp/BSPRule
    1560: dup
    1561: ldc_w         #297                // String R3031
    1564: bipush        96
    1566: ldc_w         #298                // String Any BINARY_SECURITY_TOKEN MUST specify an ValueType attribute
    1569: invokespecial #10                 // Method "<init>":(Ljava/lang/String;ILjava/lang/String;)V
    1572: putstatic     #299                // Field R3031:Lorg/apache/wss4j/common/bsp/BSPRule;
    1575: new           #4                  // class org/apache/wss4j/common/bsp/BSPRule
    1578: dup
    1579: ldc_w         #300                // String R3032
    1582: bipush        97
    1584: ldc_w         #301                // String Any BINARY_SECURITY_TOKEN ValueType attribute MUST have a value specified by the related security token profile
    1587: invokespecial #10                 // Method "<init>":(Ljava/lang/String;ILjava/lang/String;)V
    1590: putstatic     #302                // Field R3032:Lorg/apache/wss4j/common/bsp/BSPRule;
    1593: new           #4                  // class org/apache/wss4j/common/bsp/BSPRule
    1596: dup
    1597: ldc_w         #303                // String R4222
    1600: bipush        98
    1602: ldc_w         #304                // String Any USERNAME_TOKEN MUST NOT have more than one PASSWORD
    1605: invokespecial #10                 // Method "<init>":(Ljava/lang/String;ILjava/lang/String;)V
    1608: putstatic     #305                // Field R4222:Lorg/apache/wss4j/common/bsp/BSPRule;
    1611: new           #4                  // class org/apache/wss4j/common/bsp/BSPRule
    1614: dup
    1615: ldc_w         #306                // String R4201
    1618: bipush        99
    1620: ldc_w         #307                // String Any PASSWORD MUST specify a Type attribute
    1623: invokespecial #10                 // Method "<init>":(Ljava/lang/String;ILjava/lang/String;)V
    1626: putstatic     #308                // Field R4201:Lorg/apache/wss4j/common/bsp/BSPRule;
    1629: new           #4                  // class org/apache/wss4j/common/bsp/BSPRule
    1632: dup
    1633: ldc_w         #309                // String R4212
    1636: bipush        100
    1638: ldc_w         #310                // String Any PASSWORD with a Type attribute value of \"http://docs.oasis-open.org/wss/2004/01/oasis-200401-wss-username-token-profile-1.0#PasswordDigest\" MUST have its value computed using the following formula, where \"+\" indicates concatenation: Password_Digest = Base64 ( SHA-1 ( nonce + created + password ) ). That is, concatenate the text forms of the nonce, creation time, and the password (or shared secret or password equivalent), digest the combination using the SHA-1 hash algorithm, then include the Base64 encoding of that result as the password (digest). Any elements that are not present are simply omitted from the concatenation
    1641: invokespecial #10                 // Method "<init>":(Ljava/lang/String;ILjava/lang/String;)V
    1644: putstatic     #311                // Field R4212:Lorg/apache/wss4j/common/bsp/BSPRule;
    1647: new           #4                  // class org/apache/wss4j/common/bsp/BSPRule
    1650: dup
    1651: ldc_w         #312                // String R4216
    1654: bipush        101
    1656: ldc_w         #313                // String When a SECURITY_TOKEN_REFERENCE, within a SIGNATURE or ENCRYPTED_KEY, refers to a SECURITY_TOKEN named wsse:UsernameToken to derive a key, the key MUST be derived using the algorithm specified in Section 4 of Web Services Security: UsernameToken Profile 1.1
    1659: invokespecial #10                 // Method "<init>":(Ljava/lang/String;ILjava/lang/String;)V
    1662: putstatic     #314                // Field R4216:Lorg/apache/wss4j/common/bsp/BSPRule;
    1665: new           #4                  // class org/apache/wss4j/common/bsp/BSPRule
    1668: dup
    1669: ldc_w         #315                // String R4217
    1672: bipush        102
    1674: ldc_w         #316                // String When a SECURITY_TOKEN_REFERENCE, within a SIGNATURE or ENCRYPTED_KEY, refers to a SECURITY_TOKEN named wsse:UsernameToken to derive a key, the SECURITY_TOKEN MUST contain a wsse11:Salt child element
    1677: invokespecial #10                 // Method "<init>":(Ljava/lang/String;ILjava/lang/String;)V
    1680: putstatic     #317                // Field R4217:Lorg/apache/wss4j/common/bsp/BSPRule;
    1683: new           #4                  // class org/apache/wss4j/common/bsp/BSPRule
    1686: dup
    1687: ldc_w         #318                // String R4218
    1690: bipush        103
    1692: ldc_w         #319                // String When a SECURITY_TOKEN_REFERENCE, within a SIGNATURE or ENCRYPTED_KEY, refers to a SECURITY_TOKEN named wsse:UsernameToken to derive a key, the SECURITY_TOKEN MUST contain a wsse11:Iteration child element with a value greater than or equal to 1000
    1695: invokespecial #10                 // Method "<init>":(Ljava/lang/String;ILjava/lang/String;)V
    1698: putstatic     #320                // Field R4218:Lorg/apache/wss4j/common/bsp/BSPRule;
    1701: new           #4                  // class org/apache/wss4j/common/bsp/BSPRule
    1704: dup
    1705: ldc_w         #321                // String R4223
    1708: bipush        104
    1710: ldc_w         #322                // String Any USERNAME_TOKEN MUST NOT have more than one CREATED
    1713: invokespecial #10                 // Method "<init>":(Ljava/lang/String;ILjava/lang/String;)V
    1716: putstatic     #323                // Field R4223:Lorg/apache/wss4j/common/bsp/BSPRule;
    1719: new           #4                  // class org/apache/wss4j/common/bsp/BSPRule
    1722: dup
    1723: ldc_w         #324                // String R4225
    1726: bipush        105
    1728: ldc_w         #325                // String Any USERNAME_TOKEN MUST NOT have more than one NONCE
    1731: invokespecial #10                 // Method "<init>":(Ljava/lang/String;ILjava/lang/String;)V
    1734: putstatic     #326                // Field R4225:Lorg/apache/wss4j/common/bsp/BSPRule;
    1737: new           #4                  // class org/apache/wss4j/common/bsp/BSPRule
    1740: dup
    1741: ldc_w         #327                // String R4220
    1744: bipush        106
    1746: ldc_w         #328                // String Any NONCE MUST specify an EncodingType attribute
    1749: invokespecial #10                 // Method "<init>":(Ljava/lang/String;ILjava/lang/String;)V
    1752: putstatic     #329                // Field R4220:Lorg/apache/wss4j/common/bsp/BSPRule;
    1755: new           #4                  // class org/apache/wss4j/common/bsp/BSPRule
    1758: dup
    1759: ldc_w         #330                // String R4221
    1762: bipush        107
    1764: ldc_w         #331                // String Any NONCE EncodingType attribute MUST have a value of \"http://docs.oasis-open.org/wss/2004/01/oasis-200401-wss-soap-message-security-1.0#Base64Binary\"
    1767: invokespecial #10                 // Method "<init>":(Ljava/lang/String;ILjava/lang/String;)V
    1770: putstatic     #332                // Field R4221:Lorg/apache/wss4j/common/bsp/BSPRule;
    1773: new           #4                  // class org/apache/wss4j/common/bsp/BSPRule
    1776: dup
    1777: ldc_w         #333                // String R4214
    1780: bipush        108
    1782: ldc_w         #334                // String Any STR_REFERENCE to a USERNAME_TOKEN MUST have a ValueType attribute with a value of \"http://docs.oasis-open.org/wss/2004/01/oasis-200401-wss-username-token-profile-1.0#UsernameToken\"
    1785: invokespecial #10                 // Method "<init>":(Ljava/lang/String;ILjava/lang/String;)V
    1788: putstatic     #335                // Field R4214:Lorg/apache/wss4j/common/bsp/BSPRule;
    1791: new           #4                  // class org/apache/wss4j/common/bsp/BSPRule
    1794: dup
    1795: ldc_w         #336                // String R4215
    1798: bipush        109
    1800: ldc_w         #337                // String Any SECURITY_TOKEN_REFERENCE to a USERNAME_TOKEN MUST NOT contain an STR_KEY_IDENTIFIER
    1803: invokespecial #10                 // Method "<init>":(Ljava/lang/String;ILjava/lang/String;)V
    1806: putstatic     #338                // Field R4215:Lorg/apache/wss4j/common/bsp/BSPRule;
    1809: new           #4                  // class org/apache/wss4j/common/bsp/BSPRule
    1812: dup
    1813: ldc_w         #339                // String R3033
    1816: bipush        110
    1818: ldc_w         #340                // String Any X509_TOKEN MUST contain a ValueType attribute with a value of \"http://docs.oasis-open.org/wss/2004/01/oasis-200401-wss-x509-token-profile-1.0#X509v3\"
    1821: invokespecial #10                 // Method "<init>":(Ljava/lang/String;ILjava/lang/String;)V
    1824: putstatic     #341                // Field R3033:Lorg/apache/wss4j/common/bsp/BSPRule;
    1827: new           #4                  // class org/apache/wss4j/common/bsp/BSPRule
    1830: dup
    1831: ldc_w         #342                // String R5201
    1834: bipush        111
    1836: ldc_w         #343                // String Any BINARY_SECURITY_TOKEN containing an X.509 Certificate Path MUST be either a PKCS7_TOKEN or a PKIPATH_TOKEN
    1839: invokespecial #10                 // Method "<init>":(Ljava/lang/String;ILjava/lang/String;)V
    1842: putstatic     #344                // Field R5201:Lorg/apache/wss4j/common/bsp/BSPRule;
    1845: new           #4                  // class org/apache/wss4j/common/bsp/BSPRule
    1848: dup
    1849: ldc_w         #345                // String R5202
    1852: bipush        112
    1854: ldc_w         #346                // String Any BINARY_SECURITY_TOKEN containing an X.509 Certificate Path SHOULD be a PKIPATH_TOKEN
    1857: invokespecial #10                 // Method "<init>":(Ljava/lang/String;ILjava/lang/String;)V
    1860: putstatic     #347                // Field R5202:Lorg/apache/wss4j/common/bsp/BSPRule;
    1863: new           #4                  // class org/apache/wss4j/common/bsp/BSPRule
    1866: dup
    1867: ldc_w         #348                // String R5211
    1870: bipush        113
    1872: ldc_w         #349                // String Any PKCS7_TOKEN MUST contain a ValueType attribute with a value of \"http://docs.oasis-open.org/wss/2004/01/oasis-200401-wss-x509-token-profile-1.0#PKCS7\"
    1875: invokespecial #10                 // Method "<init>":(Ljava/lang/String;ILjava/lang/String;)V
    1878: putstatic     #350                // Field R5211:Lorg/apache/wss4j/common/bsp/BSPRule;
    1881: new           #4                  // class org/apache/wss4j/common/bsp/BSPRule
    1884: dup
    1885: ldc_w         #351                // String R5218
    1888: bipush        114
    1890: ldc_w         #352                // String Any STR_REFERENCE to a X509_TOKEN MUST contain a ValueType attribute with a value of \"http://docs.oasis-open.org/wss/2004/01/oasis-200401-wss-x509-token-profile-1.0#X509v3\"
    1893: invokespecial #10                 // Method "<init>":(Ljava/lang/String;ILjava/lang/String;)V
    1896: putstatic     #353                // Field R5218:Lorg/apache/wss4j/common/bsp/BSPRule;
    1899: new           #4                  // class org/apache/wss4j/common/bsp/BSPRule
    1902: dup
    1903: ldc_w         #354                // String R5212
    1906: bipush        115
    1908: ldc_w         #355                // String Any SECURITY_TOKEN_REFERENCE to a PKCS7_TOKEN MUST contain a wsse11:TokenType attribute with a value of \"http://docs.oasis-open.org/wss/2004/01/oasis-200401-wss-x509-token-profile-1.0#PKCS7\"
    1911: invokespecial #10                 // Method "<init>":(Ljava/lang/String;ILjava/lang/String;)V
    1914: putstatic     #356                // Field R5212:Lorg/apache/wss4j/common/bsp/BSPRule;
    1917: new           #4                  // class org/apache/wss4j/common/bsp/BSPRule
    1920: dup
    1921: ldc_w         #357                // String R5213
    1924: bipush        116
    1926: ldc_w         #358                // String Any STR_REFERENCE to a PKCS7_TOKEN MUST contain a ValueType attribute with a value of \"http://docs.oasis-open.org/wss/2004/01/oasis-200401-wss-x509-token-profile-1.0#PKCS7\"
    1929: invokespecial #10                 // Method "<init>":(Ljava/lang/String;ILjava/lang/String;)V
    1932: putstatic     #359                // Field R5213:Lorg/apache/wss4j/common/bsp/BSPRule;
    1935: new           #4                  // class org/apache/wss4j/common/bsp/BSPRule
    1938: dup
    1939: ldc_w         #360                // String R5214
    1942: bipush        117
    1944: ldc_w         #361                // String Any PKIPATH_TOKEN MUST contain a ValueType attribute with a value of \"http://docs.oasis-open.org/wss/2004/01/oasis-200401-wss-x509-token-profile-1.0#X509PKIPathv1\"
    1947: invokespecial #10                 // Method "<init>":(Ljava/lang/String;ILjava/lang/String;)V
    1950: putstatic     #362                // Field R5214:Lorg/apache/wss4j/common/bsp/BSPRule;
    1953: new           #4                  // class org/apache/wss4j/common/bsp/BSPRule
    1956: dup
    1957: ldc_w         #363                // String R5215
    1960: bipush        118
    1962: ldc_w         #364                // String Any SECURITY_TOKEN_REFERENCE to a PKIPATH_TOKEN MUST contain a wsse11:TokenType attribute with a value of \"http://docs.oasis-open.org/wss/2004/01/oasis-200401-wss-x509-token-profile-1.0#X509PKIPathv1\"
    1965: invokespecial #10                 // Method "<init>":(Ljava/lang/String;ILjava/lang/String;)V
    1968: putstatic     #365                // Field R5215:Lorg/apache/wss4j/common/bsp/BSPRule;
    1971: new           #4                  // class org/apache/wss4j/common/bsp/BSPRule
    1974: dup
    1975: ldc_w         #366                // String R5216
    1978: bipush        119
    1980: ldc_w         #367                // String Any STR_REFERENCE to a PKIPATH_TOKEN MUST contain a ValueType attribute with a value of \"http://docs.oasis-open.org/wss/2004/01/oasis-200401-wss-x509-token-profile-1.0#X509PKIPathv1\"
    1983: invokespecial #10                 // Method "<init>":(Ljava/lang/String;ILjava/lang/String;)V
    1986: putstatic     #368                // Field R5216:Lorg/apache/wss4j/common/bsp/BSPRule;
    1989: new           #4                  // class org/apache/wss4j/common/bsp/BSPRule
    1992: dup
    1993: ldc_w         #369                // String R5209
    1996: bipush        120
    1998: ldc_w         #370                // String When a SECURITY_TOKEN_REFERENCE references an EXTERNAL_SECURITY_TOKEN that cannot be referred to using an STR_REFERENCE but can be referred to using an STR_KEY_IDENTIFIER or STR_ISSUER_SERIAL, an STR_KEY_IDENTIFIER or STR_ISSUER_SERIAL MUST be used
    2001: invokespecial #10                 // Method "<init>":(Ljava/lang/String;ILjava/lang/String;)V
    2004: putstatic     #371                // Field R5209:Lorg/apache/wss4j/common/bsp/BSPRule;
    2007: new           #4                  // class org/apache/wss4j/common/bsp/BSPRule
    2010: dup
    2011: ldc_w         #372                // String R5206
    2014: bipush        121
    2016: ldc_w         #373                // String Any STR_KEY_IDENTIFIER that references an X509_TOKEN MUST have a ValueType attribute with the value of \"http://docs.oasis-open.org/wss/2004/01/oasis-200401-wss-x509-token-profile-1.0#X509SubjectKeyIdentifier\" or \"http://docs.oasis-open.org/wss/oasis-wss-soap-message-security-1.1#ThumbprintSHA1\"
    2019: invokespecial #10                 // Method "<init>":(Ljava/lang/String;ILjava/lang/String;)V
    2022: putstatic     #374                // Field R5206:Lorg/apache/wss4j/common/bsp/BSPRule;
    2025: new           #4                  // class org/apache/wss4j/common/bsp/BSPRule
    2028: dup
    2029: ldc_w         #375                // String R5208
    2032: bipush        122
    2034: ldc_w         #376                // String Any STR_KEY_IDENTIFIER that references an X509_TOKEN and has a ValueType attribute with the value of \"http://docs.oasis-open.org/wss/2004/01/oasis-200401-wss-x509-token-profile-1.0#X509SubjectKeyIdentifier\" MUST contain the value of the token\'s SubjectKeyIdentifier extension
    2037: invokespecial #10                 // Method "<init>":(Ljava/lang/String;ILjava/lang/String;)V
    2040: putstatic     #377                // Field R5208:Lorg/apache/wss4j/common/bsp/BSPRule;
    2043: new           #4                  // class org/apache/wss4j/common/bsp/BSPRule
    2046: dup
    2047: ldc_w         #378                // String R5210
    2050: bipush        123
    2052: ldc_w         #379                // String Any STR_KEY_IDENTIFIER that references an X509_TOKEN which does not contain a SubjectKeyIdentifier extension MUST have a ValueType attribute with the value of \"http://docs.oasis-open.org/wss/oasis-wss-soap-message-security-1.1#ThumbprintSHA1\" and MUST contain the value of the SHA1 of the raw octets of the X509_TOKEN that is referenced
    2055: invokespecial #10                 // Method "<init>":(Ljava/lang/String;ILjava/lang/String;)V
    2058: putstatic     #380                // Field R5210:Lorg/apache/wss4j/common/bsp/BSPRule;
    2061: new           #4                  // class org/apache/wss4j/common/bsp/BSPRule
    2064: dup
    2065: ldc_w         #381                // String R5409
    2068: bipush        124
    2070: ldc_w         #382                // String Any STR_ISSUER_SERIAL MUST contain a value following the encoding rules specified in the XML Signature specification for DNames
    2073: invokespecial #10                 // Method "<init>":(Ljava/lang/String;ILjava/lang/String;)V
    2076: putstatic     #383                // Field R5409:Lorg/apache/wss4j/common/bsp/BSPRule;
    2079: new           #4                  // class org/apache/wss4j/common/bsp/BSPRule
    2082: dup
    2083: ldc_w         #384                // String R6304
    2086: bipush        125
    2088: ldc_w         #385                // String Any STR_REFERENCE to a REL_TOKEN MUST contain a ValueType attribute with a value of \"http://docs.oasis-open.org/wss/oasis-wss-rel-token-profile-1.0.pdf#license\"
    2091: invokespecial #10                 // Method "<init>":(Ljava/lang/String;ILjava/lang/String;)V
    2094: putstatic     #386                // Field R6304:Lorg/apache/wss4j/common/bsp/BSPRule;
    2097: new           #4                  // class org/apache/wss4j/common/bsp/BSPRule
    2100: dup
    2101: ldc_w         #387                // String R6301
    2104: bipush        126
    2106: ldc_w         #388                // String Any STR_REFERENCE to a INTERNAL_SECURITY_TOKEN that is an REL_TOKEN containing a wsu:Id attribute, MUST NOT use a licenseId reference
    2109: invokespecial #10                 // Method "<init>":(Ljava/lang/String;ILjava/lang/String;)V
    2112: putstatic     #389                // Field R6301:Lorg/apache/wss4j/common/bsp/BSPRule;
    2115: new           #4                  // class org/apache/wss4j/common/bsp/BSPRule
    2118: dup
    2119: ldc_w         #390                // String R6302
    2122: bipush        127
    2124: ldc_w         #391                // String Any SECURITY_HEADER child elements MUST be ordered so that any SIGNATURE necessary to verify the issuance of an REL_TOKEN precedes the first SECURITY_TOKEN_REFERENCE that refers to that REL_TOKEN
    2127: invokespecial #10                 // Method "<init>":(Ljava/lang/String;ILjava/lang/String;)V
    2130: putstatic     #392                // Field R6302:Lorg/apache/wss4j/common/bsp/BSPRule;
    2133: new           #4                  // class org/apache/wss4j/common/bsp/BSPRule
    2136: dup
    2137: ldc_w         #393                // String R6902
    2140: sipush        128
    2143: ldc_w         #394                // String Any KERBEROS_TOKEN MUST contain a ValueType attribute with a value of \"http://docs.oasis-open.org/wss/oasis-wss-kerberos-token-profile-1.1#GSS_Kerberosv5_AP_REQ\"
    2146: invokespecial #10                 // Method "<init>":(Ljava/lang/String;ILjava/lang/String;)V
    2149: putstatic     #395                // Field R6902:Lorg/apache/wss4j/common/bsp/BSPRule;
    2152: new           #4                  // class org/apache/wss4j/common/bsp/BSPRule
    2155: dup
    2156: ldc_w         #396                // String R6903
    2159: sipush        129
    2162: ldc_w         #397                // String Any KERBEROS_TOKEN MUST be an INTERNAL_SECURITY_TOKEN in the initial SECURE_ENVELOPE of an authenticated message exchange between a SENDER and RECEIVER
    2165: invokespecial #10                 // Method "<init>":(Ljava/lang/String;ILjava/lang/String;)V
    2168: putstatic     #398                // Field R6903:Lorg/apache/wss4j/common/bsp/BSPRule;
    2171: new           #4                  // class org/apache/wss4j/common/bsp/BSPRule
    2174: dup
    2175: ldc_w         #399                // String R6904
    2178: sipush        130
    2181: ldc_w         #400                // String Any KERBEROS_TOKEN MUST be an EXTERNAL_SECURITY_TOKEN in each SECURE_ENVELOPE after the initial SECURE_ENVELOPE of an authenticated message exchange between a SENDER and RECEIVER
    2184: invokespecial #10                 // Method "<init>":(Ljava/lang/String;ILjava/lang/String;)V
    2187: putstatic     #401                // Field R6904:Lorg/apache/wss4j/common/bsp/BSPRule;
    2190: new           #4                  // class org/apache/wss4j/common/bsp/BSPRule
    2193: dup
    2194: ldc_w         #402                // String R6907
    2197: sipush        131
    2200: ldc_w         #403                // String Any SECURITY_TOKEN_REFERENCE to a KERBEROS_TOKEN MUST contain a wsse11:TokenType attribute with a value of \"http://docs.oasis-open.org/wss/oasis-wss-kerberos-token-profile-1.1#GSS_Kerberosv5_AP_REQ\"
    2203: invokespecial #10                 // Method "<init>":(Ljava/lang/String;ILjava/lang/String;)V
    2206: putstatic     #404                // Field R6907:Lorg/apache/wss4j/common/bsp/BSPRule;
    2209: new           #4                  // class org/apache/wss4j/common/bsp/BSPRule
    2212: dup
    2213: ldc_w         #405                // String R6906
    2216: sipush        132
    2219: ldc_w         #406                // String Any STR_KEY_IDENTIFIER to a KERBEROS_TOKEN MUST contain a ValueType attribute with a value of \"http://docs.oasis-open.org/wss/oasis-wss-kerberos-tokenprofile-1.1#Kerberosv5APREQSHA1\"
    2222: invokespecial #10                 // Method "<init>":(Ljava/lang/String;ILjava/lang/String;)V
    2225: putstatic     #407                // Field R6906:Lorg/apache/wss4j/common/bsp/BSPRule;
    2228: new           #4                  // class org/apache/wss4j/common/bsp/BSPRule
    2231: dup
    2232: ldc_w         #408                // String R6905
    2235: sipush        133
    2238: ldc_w         #409                // String Any SECURITY_TOKEN_REFERENCE to an EXTERNAL_SECURITY_TOKEN which is a KERBEROS_TOKEN MUST contain an STR_KEY_IDENTIFIER
    2241: invokespecial #10                 // Method "<init>":(Ljava/lang/String;ILjava/lang/String;)V
    2244: putstatic     #410                // Field R6905:Lorg/apache/wss4j/common/bsp/BSPRule;
    2247: new           #4                  // class org/apache/wss4j/common/bsp/BSPRule
    2250: dup
    2251: ldc_w         #411                // String R6601
    2254: sipush        134
    2257: ldc_w         #412                // String Any SAML_SC_KEY_INFO MUST NOT contain a reference to a SAML_TOKEN
    2260: invokespecial #10                 // Method "<init>":(Ljava/lang/String;ILjava/lang/String;)V
    2263: putstatic     #413                // Field R6601:Lorg/apache/wss4j/common/bsp/BSPRule;
    2266: new           #4                  // class org/apache/wss4j/common/bsp/BSPRule
    2269: dup
    2270: ldc_w         #414                // String R6611
    2273: sipush        135
    2276: ldc_w         #415                // String Any SECURITY_TOKEN_REFERENCE to a SAML_V1_1_TOKEN MUST contain a wsse11:TokenType attribute with a value of \"http://docs.oasis-open.org/wss/oasis-wss-saml-token-profile-1.1#SAMLV1.1\"
    2279: invokespecial #10                 // Method "<init>":(Ljava/lang/String;ILjava/lang/String;)V
    2282: putstatic     #416                // Field R6611:Lorg/apache/wss4j/common/bsp/BSPRule;
    2285: new           #4                  // class org/apache/wss4j/common/bsp/BSPRule
    2288: dup
    2289: ldc_w         #417                // String R6617
    2292: sipush        136
    2295: ldc_w         #418                // String Any SECURITY_TOKEN_REFERENCE to a SAML_V2_0_TOKEN MUST contain a wsse11:TokenType attribute with a value of \"http://docs.oasis-open.org/wss/oasis-wss-saml-token-profile-1.1#SAMLV2.0\"
    2298: invokespecial #10                 // Method "<init>":(Ljava/lang/String;ILjava/lang/String;)V
    2301: putstatic     #419                // Field R6617:Lorg/apache/wss4j/common/bsp/BSPRule;
    2304: new           #4                  // class org/apache/wss4j/common/bsp/BSPRule
    2307: dup
    2308: ldc_w         #420                // String R6614
    2311: sipush        137
    2314: ldc_w         #421                // String Any SECURITY_TOKEN_REFERENCE that references an INTERNAL_SAML_V2_0_TOKEN using a STR_REFERENCE MUST NOT contain a ValueType attribute
    2317: invokespecial #10                 // Method "<init>":(Ljava/lang/String;ILjava/lang/String;)V
    2320: putstatic     #422                // Field R6614:Lorg/apache/wss4j/common/bsp/BSPRule;
    2323: new           #4                  // class org/apache/wss4j/common/bsp/BSPRule
    2326: dup
    2327: ldc_w         #423                // String R6602
    2330: sipush        138
    2333: ldc_w         #424                // String Any STR_KEY_IDENTIFIER that references a INTERNAL_SAML_TOKEN MUST include a ValueType attribute
    2336: invokespecial #10                 // Method "<init>":(Ljava/lang/String;ILjava/lang/String;)V
    2339: putstatic     #425                // Field R6602:Lorg/apache/wss4j/common/bsp/BSPRule;
    2342: new           #4                  // class org/apache/wss4j/common/bsp/BSPRule
    2345: dup
    2346: ldc_w         #426                // String R6609
    2349: sipush        139
    2352: ldc_w         #427                // String Any STR_KEY_IDENTIFIER that references a EXTERNAL_SAML_TOKEN MUST include a ValueType attribute
    2355: invokespecial #10                 // Method "<init>":(Ljava/lang/String;ILjava/lang/String;)V
    2358: putstatic     #428                // Field R6609:Lorg/apache/wss4j/common/bsp/BSPRule;
    2361: new           #4                  // class org/apache/wss4j/common/bsp/BSPRule
    2364: dup
    2365: ldc_w         #429                // String R6603
    2368: sipush        140
    2371: ldc_w         #430                // String Any STR_KEY_IDENTIFIER ValueType attribute that references a SAML_V1_1_TOKEN MUST have a value of \"http://docs.oasis-open.org/wss/oasis-wss-saml-token-profile-1.0#SAMLAssertionID\"
    2374: invokespecial #10                 // Method "<init>":(Ljava/lang/String;ILjava/lang/String;)V
    2377: putstatic     #431                // Field R6603:Lorg/apache/wss4j/common/bsp/BSPRule;
    2380: new           #4                  // class org/apache/wss4j/common/bsp/BSPRule
    2383: dup
    2384: ldc_w         #432                // String R6616
    2387: sipush        141
    2390: ldc_w         #433                // String Any STR_KEY_IDENTIFIER ValueType attribute that references a SAML_V2_0_TOKEN MUST have a value of \"http://docs.oasis-open.org/wss/oasis-wss-saml-token-profile-1.1#SAMLID\"
    2393: invokespecial #10                 // Method "<init>":(Ljava/lang/String;ILjava/lang/String;)V
    2396: putstatic     #434                // Field R6616:Lorg/apache/wss4j/common/bsp/BSPRule;
    2399: new           #4                  // class org/apache/wss4j/common/bsp/BSPRule
    2402: dup
    2403: ldc_w         #435                // String R6604
    2406: sipush        142
    2409: ldc_w         #436                // String Any STR_KEY_IDENTIFIER that references a SAML_TOKEN MUST NOT include an EncodingType attribute
    2412: invokespecial #10                 // Method "<init>":(Ljava/lang/String;ILjava/lang/String;)V
    2415: putstatic     #437                // Field R6604:Lorg/apache/wss4j/common/bsp/BSPRule;
    2418: new           #4                  // class org/apache/wss4j/common/bsp/BSPRule
    2421: dup
    2422: ldc_w         #438                // String R6605
    2425: sipush        143
    2428: ldc_w         #439                // String Any STR_KEY_IDENTIFIER that references a SAML_TOKEN MUST have a value encoded as an xs:string
    2431: invokespecial #10                 // Method "<init>":(Ljava/lang/String;ILjava/lang/String;)V
    2434: putstatic     #440                // Field R6605:Lorg/apache/wss4j/common/bsp/BSPRule;
    2437: new           #4                  // class org/apache/wss4j/common/bsp/BSPRule
    2440: dup
    2441: ldc_w         #441                // String R6610
    2444: sipush        144
    2447: ldc_w         #442                // String Any SECURITY_TOKEN_REFERENCE that references an INTERNAL_SAML_TOKEN that has an ID attribute, the reference MUST contain an STR_REFERENCE or an STR_EMBEDDED
    2450: invokespecial #10                 // Method "<init>":(Ljava/lang/String;ILjava/lang/String;)V
    2453: putstatic     #443                // Field R6610:Lorg/apache/wss4j/common/bsp/BSPRule;
    2456: new           #4                  // class org/apache/wss4j/common/bsp/BSPRule
    2459: dup
    2460: ldc_w         #444                // String R6612
    2463: sipush        145
    2466: ldc_w         #445                // String Any SIG_REFERENCE to a SECURITY_TOKEN_REFERENCE which contains an STR_EMBEDDED which contains an INTERNAL_SAML_V2_0_TOKEN MUST NOT include a SIG_TRANSFORM with an Algorithm attribute value of \"http://docs.oasis-open.org/wss/2004/01/oasis-200401-wss-soap-message-security-1.0#STR-Transform\"
    2469: invokespecial #10                 // Method "<init>":(Ljava/lang/String;ILjava/lang/String;)V
    2472: putstatic     #446                // Field R6612:Lorg/apache/wss4j/common/bsp/BSPRule;
    2475: new           #4                  // class org/apache/wss4j/common/bsp/BSPRule
    2478: dup
    2479: ldc_w         #447                // String R6606
    2482: sipush        146
    2485: ldc_w         #448                // String Any SECURITY_TOKEN_REFERENCE that references an EXTERNAL_SAML_TOKEN MUST contain a SAML_AUTHORITY_BINDING
    2488: invokespecial #10                 // Method "<init>":(Ljava/lang/String;ILjava/lang/String;)V
    2491: putstatic     #449                // Field R6606:Lorg/apache/wss4j/common/bsp/BSPRule;
    2494: new           #4                  // class org/apache/wss4j/common/bsp/BSPRule
    2497: dup
    2498: ldc_w         #450                // String R6607
    2501: sipush        147
    2504: ldc_w         #451                // String Any AuthorityKind attribute of a SAML_AUTHORITY_BINDING MUST have a value of saml:AssertionIDReference
    2507: invokespecial #10                 // Method "<init>":(Ljava/lang/String;ILjava/lang/String;)V
    2510: putstatic     #452                // Field R6607:Lorg/apache/wss4j/common/bsp/BSPRule;
    2513: new           #4                  // class org/apache/wss4j/common/bsp/BSPRule
    2516: dup
    2517: ldc_w         #453                // String R6608
    2520: sipush        148
    2523: ldc_w         #454                // String Any SECURITY_TOKEN_REFERENCE that references an INTERNAL_SAML_TOKEN MUST NOT contain a SAML_AUTHORITY_BINDING
    2526: invokespecial #10                 // Method "<init>":(Ljava/lang/String;ILjava/lang/String;)V
    2529: putstatic     #455                // Field R6608:Lorg/apache/wss4j/common/bsp/BSPRule;
    2532: new           #4                  // class org/apache/wss4j/common/bsp/BSPRule
    2535: dup
    2536: ldc_w         #456                // String R6613
    2539: sipush        149
    2542: ldc_w         #457                // String Any SECURITY_TOKEN_REFERENCE to an EXTERNAL_SAML_V2_0_TOKEN MUST contain an STR_REFERENCE
    2545: invokespecial #10                 // Method "<init>":(Ljava/lang/String;ILjava/lang/String;)V
    2548: putstatic     #458                // Field R6613:Lorg/apache/wss4j/common/bsp/BSPRule;
    2551: new           #4                  // class org/apache/wss4j/common/bsp/BSPRule
    2554: dup
    2555: ldc_w         #459                // String R3069
    2558: sipush        150
    2561: ldc_w         #460                // String Any SECURITY_TOKEN_REFERENCE to a ENCRYPTED_KEY_TOKEN MUST contain a wsse11:TokenType attribute with a value of \"http://docs.oasis-open.org/wss/oasis-wss-soap-message-security-1.1#EncryptedKey\"
    2564: invokespecial #10                 // Method "<init>":(Ljava/lang/String;ILjava/lang/String;)V
    2567: putstatic     #461                // Field R3069:Lorg/apache/wss4j/common/bsp/BSPRule;
    2570: new           #4                  // class org/apache/wss4j/common/bsp/BSPRule
    2573: dup
    2574: ldc_w         #462                // String R3072
    2577: sipush        151
    2580: ldc_w         #463                // String Any STR_KEY_IDENTIFIER element in a SECURITY_TOKEN_REFERENCE that refers to an ENCRYPTED_KEY_TOKEN MUST contain a ValueType attribute with a value of \"http://docs.oasis-open.org/wss/oasis-wss-soap-message-security-1.1#EncryptedKeySHA1\"
    2583: invokespecial #10                 // Method "<init>":(Ljava/lang/String;ILjava/lang/String;)V
    2586: putstatic     #464                // Field R3072:Lorg/apache/wss4j/common/bsp/BSPRule;
    2589: sipush        152
    2592: anewarray     #4                  // class org/apache/wss4j/common/bsp/BSPRule
    2595: dup
    2596: iconst_0
    2597: getstatic     #11                 // Field R3203:Lorg/apache/wss4j/common/bsp/BSPRule;
    2600: aastore
    2601: dup
    2602: iconst_1
    2603: getstatic     #14                 // Field R3224:Lorg/apache/wss4j/common/bsp/BSPRule;
    2606: aastore
    2607: dup
    2608: iconst_2
    2609: getstatic     #17                 // Field R3221:Lorg/apache/wss4j/common/bsp/BSPRule;
    2612: aastore
    2613: dup
    2614: iconst_3
    2615: getstatic     #20                 // Field R3222:Lorg/apache/wss4j/common/bsp/BSPRule;
    2618: aastore
    2619: dup
    2620: iconst_4
    2621: getstatic     #23                 // Field R3220:Lorg/apache/wss4j/common/bsp/BSPRule;
    2624: aastore
    2625: dup
    2626: iconst_5
    2627: getstatic     #26                 // Field R3229:Lorg/apache/wss4j/common/bsp/BSPRule;
    2630: aastore
    2631: dup
    2632: bipush        6
    2634: getstatic     #29                 // Field R3213:Lorg/apache/wss4j/common/bsp/BSPRule;
    2637: aastore
    2638: dup
    2639: bipush        7
    2641: getstatic     #32                 // Field R3215:Lorg/apache/wss4j/common/bsp/BSPRule;
    2644: aastore
    2645: dup
    2646: bipush        8
    2648: getstatic     #35                 // Field R3225:Lorg/apache/wss4j/common/bsp/BSPRule;
    2651: aastore
    2652: dup
    2653: bipush        9
    2655: getstatic     #38                 // Field R3226:Lorg/apache/wss4j/common/bsp/BSPRule;
    2658: aastore
    2659: dup
    2660: bipush        10
    2662: getstatic     #41                 // Field R3217:Lorg/apache/wss4j/common/bsp/BSPRule;
    2665: aastore
    2666: dup
    2667: bipush        11
    2669: getstatic     #44                 // Field R3223:Lorg/apache/wss4j/common/bsp/BSPRule;
    2672: aastore
    2673: dup
    2674: bipush        12
    2676: getstatic     #47                 // Field R3227:Lorg/apache/wss4j/common/bsp/BSPRule;
    2679: aastore
    2680: dup
    2681: bipush        13
    2683: getstatic     #50                 // Field R3061:Lorg/apache/wss4j/common/bsp/BSPRule;
    2686: aastore
    2687: dup
    2688: bipush        14
    2690: getstatic     #53                 // Field R3074:Lorg/apache/wss4j/common/bsp/BSPRule;
    2693: aastore
    2694: dup
    2695: bipush        15
    2697: getstatic     #56                 // Field R3057:Lorg/apache/wss4j/common/bsp/BSPRule;
    2700: aastore
    2701: dup
    2702: bipush        16
    2704: getstatic     #59                 // Field R3064:Lorg/apache/wss4j/common/bsp/BSPRule;
    2707: aastore
    2708: dup
    2709: bipush        17
    2711: getstatic     #62                 // Field R3059:Lorg/apache/wss4j/common/bsp/BSPRule;
    2714: aastore
    2715: dup
    2716: bipush        18
    2718: getstatic     #65                 // Field R3058:Lorg/apache/wss4j/common/bsp/BSPRule;
    2721: aastore
    2722: dup
    2723: bipush        19
    2725: getstatic     #68                 // Field R3062:Lorg/apache/wss4j/common/bsp/BSPRule;
    2728: aastore
    2729: dup
    2730: bipush        20
    2732: getstatic     #71                 // Field R3027:Lorg/apache/wss4j/common/bsp/BSPRule;
    2735: aastore
    2736: dup
    2737: bipush        21
    2739: getstatic     #74                 // Field R3054:Lorg/apache/wss4j/common/bsp/BSPRule;
    2742: aastore
    2743: dup
    2744: bipush        22
    2746: getstatic     #77                 // Field R3063:Lorg/apache/wss4j/common/bsp/BSPRule;
    2749: aastore
    2750: dup
    2751: bipush        23
    2753: getstatic     #80                 // Field R3070:Lorg/apache/wss4j/common/bsp/BSPRule;
    2756: aastore
    2757: dup
    2758: bipush        24
    2760: getstatic     #83                 // Field R3071:Lorg/apache/wss4j/common/bsp/BSPRule;
    2763: aastore
    2764: dup
    2765: bipush        25
    2767: getstatic     #86                 // Field R3060:Lorg/apache/wss4j/common/bsp/BSPRule;
    2770: aastore
    2771: dup
    2772: bipush        26
    2774: getstatic     #89                 // Field R3025:Lorg/apache/wss4j/common/bsp/BSPRule;
    2777: aastore
    2778: dup
    2779: bipush        27
    2781: getstatic     #92                 // Field R3056:Lorg/apache/wss4j/common/bsp/BSPRule;
    2784: aastore
    2785: dup
    2786: bipush        28
    2788: getstatic     #95                 // Field R3022:Lorg/apache/wss4j/common/bsp/BSPRule;
    2791: aastore
    2792: dup
    2793: bipush        29
    2795: getstatic     #98                 // Field R3023:Lorg/apache/wss4j/common/bsp/BSPRule;
    2798: aastore
    2799: dup
    2800: bipush        30
    2802: getstatic     #101                // Field R5204:Lorg/apache/wss4j/common/bsp/BSPRule;
    2805: aastore
    2806: dup
    2807: bipush        31
    2809: getstatic     #104                // Field R5205:Lorg/apache/wss4j/common/bsp/BSPRule;
    2812: aastore
    2813: dup
    2814: bipush        32
    2816: getstatic     #107                // Field R3066:Lorg/apache/wss4j/common/bsp/BSPRule;
    2819: aastore
    2820: dup
    2821: bipush        33
    2823: getstatic     #110                // Field R3067:Lorg/apache/wss4j/common/bsp/BSPRule;
    2826: aastore
    2827: dup
    2828: bipush        34
    2830: getstatic     #113                // Field R3024:Lorg/apache/wss4j/common/bsp/BSPRule;
    2833: aastore
    2834: dup
    2835: bipush        35
    2837: getstatic     #116                // Field R3211:Lorg/apache/wss4j/common/bsp/BSPRule;
    2840: aastore
    2841: dup
    2842: bipush        36
    2844: getstatic     #119                // Field R3102:Lorg/apache/wss4j/common/bsp/BSPRule;
    2847: aastore
    2848: dup
    2849: bipush        37
    2851: getstatic     #122                // Field R3104:Lorg/apache/wss4j/common/bsp/BSPRule;
    2854: aastore
    2855: dup
    2856: bipush        38
    2858: getstatic     #125                // Field R3103:Lorg/apache/wss4j/common/bsp/BSPRule;
    2861: aastore
    2862: dup
    2863: bipush        39
    2865: getstatic     #128                // Field R3001:Lorg/apache/wss4j/common/bsp/BSPRule;
    2868: aastore
    2869: dup
    2870: bipush        40
    2872: getstatic     #131                // Field R3003:Lorg/apache/wss4j/common/bsp/BSPRule;
    2875: aastore
    2876: dup
    2877: bipush        41
    2879: getstatic     #134                // Field R3004:Lorg/apache/wss4j/common/bsp/BSPRule;
    2882: aastore
    2883: dup
    2884: bipush        42
    2886: getstatic     #137                // Field R3005:Lorg/apache/wss4j/common/bsp/BSPRule;
    2889: aastore
    2890: dup
    2891: bipush        43
    2893: getstatic     #140                // Field R3002:Lorg/apache/wss4j/common/bsp/BSPRule;
    2896: aastore
    2897: dup
    2898: bipush        44
    2900: getstatic     #143                // Field R5416:Lorg/apache/wss4j/common/bsp/BSPRule;
    2903: aastore
    2904: dup
    2905: bipush        45
    2907: getstatic     #146                // Field R5411:Lorg/apache/wss4j/common/bsp/BSPRule;
    2910: aastore
    2911: dup
    2912: bipush        46
    2914: getstatic     #149                // Field R5423:Lorg/apache/wss4j/common/bsp/BSPRule;
    2917: aastore
    2918: dup
    2919: bipush        47
    2921: getstatic     #152                // Field R5412:Lorg/apache/wss4j/common/bsp/BSPRule;
    2924: aastore
    2925: dup
    2926: bipush        48
    2928: getstatic     #155                // Field R5407:Lorg/apache/wss4j/common/bsp/BSPRule;
    2931: aastore
    2932: dup
    2933: bipush        49
    2935: getstatic     #158                // Field R5413:Lorg/apache/wss4j/common/bsp/BSPRule;
    2938: aastore
    2939: dup
    2940: bipush        50
    2942: getstatic     #161                // Field R3065:Lorg/apache/wss4j/common/bsp/BSPRule;
    2945: aastore
    2946: dup
    2947: bipush        51
    2949: getstatic     #164                // Field R5404:Lorg/apache/wss4j/common/bsp/BSPRule;
    2952: aastore
    2953: dup
    2954: bipush        52
    2956: getstatic     #167                // Field R5406:Lorg/apache/wss4j/common/bsp/BSPRule;
    2959: aastore
    2960: dup
    2961: bipush        53
    2963: getstatic     #170                // Field R5414:Lorg/apache/wss4j/common/bsp/BSPRule;
    2966: aastore
    2967: dup
    2968: bipush        54
    2970: getstatic     #173                // Field R5415:Lorg/apache/wss4j/common/bsp/BSPRule;
    2973: aastore
    2974: dup
    2975: bipush        55
    2977: getstatic     #176                // Field R5405:Lorg/apache/wss4j/common/bsp/BSPRule;
    2980: aastore
    2981: dup
    2982: bipush        56
    2984: getstatic     #179                // Field R5408:Lorg/apache/wss4j/common/bsp/BSPRule;
    2987: aastore
    2988: dup
    2989: bipush        57
    2991: getstatic     #182                // Field R5420:Lorg/apache/wss4j/common/bsp/BSPRule;
    2994: aastore
    2995: dup
    2996: bipush        58
    2998: getstatic     #185                // Field R5421:Lorg/apache/wss4j/common/bsp/BSPRule;
    3001: aastore
    3002: dup
    3003: bipush        59
    3005: getstatic     #188                // Field R5401:Lorg/apache/wss4j/common/bsp/BSPRule;
    3008: aastore
    3009: dup
    3010: bipush        60
    3012: getstatic     #191                // Field R5402:Lorg/apache/wss4j/common/bsp/BSPRule;
    3015: aastore
    3016: dup
    3017: bipush        61
    3019: getstatic     #194                // Field R5417:Lorg/apache/wss4j/common/bsp/BSPRule;
    3022: aastore
    3023: dup
    3024: bipush        62
    3026: getstatic     #197                // Field R5403:Lorg/apache/wss4j/common/bsp/BSPRule;
    3029: aastore
    3030: dup
    3031: bipush        63
    3033: getstatic     #200                // Field R5440:Lorg/apache/wss4j/common/bsp/BSPRule;
    3036: aastore
    3037: dup
    3038: bipush        64
    3040: getstatic     #203                // Field R5441:Lorg/apache/wss4j/common/bsp/BSPRule;
    3043: aastore
    3044: dup
    3045: bipush        65
    3047: getstatic     #206                // Field R3228:Lorg/apache/wss4j/common/bsp/BSPRule;
    3050: aastore
    3051: dup
    3052: bipush        66
    3054: getstatic     #209                // Field R3299:Lorg/apache/wss4j/common/bsp/BSPRule;
    3057: aastore
    3058: dup
    3059: bipush        67
    3061: getstatic     #212                // Field R3230:Lorg/apache/wss4j/common/bsp/BSPRule;
    3064: aastore
    3065: dup
    3066: bipush        68
    3068: getstatic     #215                // Field R3232:Lorg/apache/wss4j/common/bsp/BSPRule;
    3071: aastore
    3072: dup
    3073: bipush        69
    3075: getstatic     #218                // Field R3205:Lorg/apache/wss4j/common/bsp/BSPRule;
    3078: aastore
    3079: dup
    3080: bipush        70
    3082: getstatic     #221                // Field R3231:Lorg/apache/wss4j/common/bsp/BSPRule;
    3085: aastore
    3086: dup
    3087: bipush        71
    3089: getstatic     #224                // Field R3214:Lorg/apache/wss4j/common/bsp/BSPRule;
    3092: aastore
    3093: dup
    3094: bipush        72
    3096: getstatic     #227                // Field R3208:Lorg/apache/wss4j/common/bsp/BSPRule;
    3099: aastore
    3100: dup
    3101: bipush        73
    3103: getstatic     #230                // Field R3209:Lorg/apache/wss4j/common/bsp/BSPRule;
    3106: aastore
    3107: dup
    3108: bipush        74
    3110: getstatic     #233                // Field R5622:Lorg/apache/wss4j/common/bsp/BSPRule;
    3113: aastore
    3114: dup
    3115: bipush        75
    3117: getstatic     #236                // Field R5623:Lorg/apache/wss4j/common/bsp/BSPRule;
    3120: aastore
    3121: dup
    3122: bipush        76
    3124: getstatic     #239                // Field R5602:Lorg/apache/wss4j/common/bsp/BSPRule;
    3127: aastore
    3128: dup
    3129: bipush        77
    3131: getstatic     #242                // Field R5603:Lorg/apache/wss4j/common/bsp/BSPRule;
    3134: aastore
    3135: dup
    3136: bipush        78
    3138: getstatic     #245                // Field R5629:Lorg/apache/wss4j/common/bsp/BSPRule;
    3141: aastore
    3142: dup
    3143: bipush        79
    3145: getstatic     #248                // Field R5624:Lorg/apache/wss4j/common/bsp/BSPRule;
    3148: aastore
    3149: dup
    3150: bipush        80
    3152: getstatic     #251                // Field R5627:Lorg/apache/wss4j/common/bsp/BSPRule;
    3155: aastore
    3156: dup
    3157: bipush        81
    3159: getstatic     #254                // Field R5601:Lorg/apache/wss4j/common/bsp/BSPRule;
    3162: aastore
    3163: dup
    3164: bipush        82
    3166: getstatic     #257                // Field R5424:Lorg/apache/wss4j/common/bsp/BSPRule;
    3169: aastore
    3170: dup
    3171: bipush        83
    3173: getstatic     #260                // Field R5426:Lorg/apache/wss4j/common/bsp/BSPRule;
    3176: aastore
    3177: dup
    3178: bipush        84
    3180: getstatic     #263                // Field R5608:Lorg/apache/wss4j/common/bsp/BSPRule;
    3183: aastore
    3184: dup
    3185: bipush        85
    3187: getstatic     #266                // Field R3006:Lorg/apache/wss4j/common/bsp/BSPRule;
    3190: aastore
    3191: dup
    3192: bipush        86
    3194: getstatic     #269                // Field R5613:Lorg/apache/wss4j/common/bsp/BSPRule;
    3197: aastore
    3198: dup
    3199: bipush        87
    3201: getstatic     #272                // Field R3007:Lorg/apache/wss4j/common/bsp/BSPRule;
    3204: aastore
    3205: dup
    3206: bipush        88
    3208: getstatic     #275                // Field R5620:Lorg/apache/wss4j/common/bsp/BSPRule;
    3211: aastore
    3212: dup
    3213: bipush        89
    3215: getstatic     #278                // Field R5621:Lorg/apache/wss4j/common/bsp/BSPRule;
    3218: aastore
    3219: dup
    3220: bipush        90
    3222: getstatic     #281                // Field R5625:Lorg/apache/wss4j/common/bsp/BSPRule;
    3225: aastore
    3226: dup
    3227: bipush        91
    3229: getstatic     #284                // Field R5626:Lorg/apache/wss4j/common/bsp/BSPRule;
    3232: aastore
    3233: dup
    3234: bipush        92
    3236: getstatic     #287                // Field R5614:Lorg/apache/wss4j/common/bsp/BSPRule;
    3239: aastore
    3240: dup
    3241: bipush        93
    3243: getstatic     #290                // Field R5606:Lorg/apache/wss4j/common/bsp/BSPRule;
    3246: aastore
    3247: dup
    3248: bipush        94
    3250: getstatic     #293                // Field R3029:Lorg/apache/wss4j/common/bsp/BSPRule;
    3253: aastore
    3254: dup
    3255: bipush        95
    3257: getstatic     #296                // Field R3030:Lorg/apache/wss4j/common/bsp/BSPRule;
    3260: aastore
    3261: dup
    3262: bipush        96
    3264: getstatic     #299                // Field R3031:Lorg/apache/wss4j/common/bsp/BSPRule;
    3267: aastore
    3268: dup
    3269: bipush        97
    3271: getstatic     #302                // Field R3032:Lorg/apache/wss4j/common/bsp/BSPRule;
    3274: aastore
    3275: dup
    3276: bipush        98
    3278: getstatic     #305                // Field R4222:Lorg/apache/wss4j/common/bsp/BSPRule;
    3281: aastore
    3282: dup
    3283: bipush        99
    3285: getstatic     #308                // Field R4201:Lorg/apache/wss4j/common/bsp/BSPRule;
    3288: aastore
    3289: dup
    3290: bipush        100
    3292: getstatic     #311                // Field R4212:Lorg/apache/wss4j/common/bsp/BSPRule;
    3295: aastore
    3296: dup
    3297: bipush        101
    3299: getstatic     #314                // Field R4216:Lorg/apache/wss4j/common/bsp/BSPRule;
    3302: aastore
    3303: dup
    3304: bipush        102
    3306: getstatic     #317                // Field R4217:Lorg/apache/wss4j/common/bsp/BSPRule;
    3309: aastore
    3310: dup
    3311: bipush        103
    3313: getstatic     #320                // Field R4218:Lorg/apache/wss4j/common/bsp/BSPRule;
    3316: aastore
    3317: dup
    3318: bipush        104
    3320: getstatic     #323                // Field R4223:Lorg/apache/wss4j/common/bsp/BSPRule;
    3323: aastore
    3324: dup
    3325: bipush        105
    3327: getstatic     #326                // Field R4225:Lorg/apache/wss4j/common/bsp/BSPRule;
    3330: aastore
    3331: dup
    3332: bipush        106
    3334: getstatic     #329                // Field R4220:Lorg/apache/wss4j/common/bsp/BSPRule;
    3337: aastore
    3338: dup
    3339: bipush        107
    3341: getstatic     #332                // Field R4221:Lorg/apache/wss4j/common/bsp/BSPRule;
    3344: aastore
    3345: dup
    3346: bipush        108
    3348: getstatic     #335                // Field R4214:Lorg/apache/wss4j/common/bsp/BSPRule;
    3351: aastore
    3352: dup
    3353: bipush        109
    3355: getstatic     #338                // Field R4215:Lorg/apache/wss4j/common/bsp/BSPRule;
    3358: aastore
    3359: dup
    3360: bipush        110
    3362: getstatic     #341                // Field R3033:Lorg/apache/wss4j/common/bsp/BSPRule;
    3365: aastore
    3366: dup
    3367: bipush        111
    3369: getstatic     #344                // Field R5201:Lorg/apache/wss4j/common/bsp/BSPRule;
    3372: aastore
    3373: dup
    3374: bipush        112
    3376: getstatic     #347                // Field R5202:Lorg/apache/wss4j/common/bsp/BSPRule;
    3379: aastore
    3380: dup
    3381: bipush        113
    3383: getstatic     #350                // Field R5211:Lorg/apache/wss4j/common/bsp/BSPRule;
    3386: aastore
    3387: dup
    3388: bipush        114
    3390: getstatic     #353                // Field R5218:Lorg/apache/wss4j/common/bsp/BSPRule;
    3393: aastore
    3394: dup
    3395: bipush        115
    3397: getstatic     #356                // Field R5212:Lorg/apache/wss4j/common/bsp/BSPRule;
    3400: aastore
    3401: dup
    3402: bipush        116
    3404: getstatic     #359                // Field R5213:Lorg/apache/wss4j/common/bsp/BSPRule;
    3407: aastore
    3408: dup
    3409: bipush        117
    3411: getstatic     #362                // Field R5214:Lorg/apache/wss4j/common/bsp/BSPRule;
    3414: aastore
    3415: dup
    3416: bipush        118
    3418: getstatic     #365                // Field R5215:Lorg/apache/wss4j/common/bsp/BSPRule;
    3421: aastore
    3422: dup
    3423: bipush        119
    3425: getstatic     #368                // Field R5216:Lorg/apache/wss4j/common/bsp/BSPRule;
    3428: aastore
    3429: dup
    3430: bipush        120
    3432: getstatic     #371                // Field R5209:Lorg/apache/wss4j/common/bsp/BSPRule;
    3435: aastore
    3436: dup
    3437: bipush        121
    3439: getstatic     #374                // Field R5206:Lorg/apache/wss4j/common/bsp/BSPRule;
    3442: aastore
    3443: dup
    3444: bipush        122
    3446: getstatic     #377                // Field R5208:Lorg/apache/wss4j/common/bsp/BSPRule;
    3449: aastore
    3450: dup
    3451: bipush        123
    3453: getstatic     #380                // Field R5210:Lorg/apache/wss4j/common/bsp/BSPRule;
    3456: aastore
    3457: dup
    3458: bipush        124
    3460: getstatic     #383                // Field R5409:Lorg/apache/wss4j/common/bsp/BSPRule;
    3463: aastore
    3464: dup
    3465: bipush        125
    3467: getstatic     #386                // Field R6304:Lorg/apache/wss4j/common/bsp/BSPRule;
    3470: aastore
    3471: dup
    3472: bipush        126
    3474: getstatic     #389                // Field R6301:Lorg/apache/wss4j/common/bsp/BSPRule;
    3477: aastore
    3478: dup
    3479: bipush        127
    3481: getstatic     #392                // Field R6302:Lorg/apache/wss4j/common/bsp/BSPRule;
    3484: aastore
    3485: dup
    3486: sipush        128
    3489: getstatic     #395                // Field R6902:Lorg/apache/wss4j/common/bsp/BSPRule;
    3492: aastore
    3493: dup
    3494: sipush        129
    3497: getstatic     #398                // Field R6903:Lorg/apache/wss4j/common/bsp/BSPRule;
    3500: aastore
    3501: dup
    3502: sipush        130
    3505: getstatic     #401                // Field R6904:Lorg/apache/wss4j/common/bsp/BSPRule;
    3508: aastore
    3509: dup
    3510: sipush        131
    3513: getstatic     #404                // Field R6907:Lorg/apache/wss4j/common/bsp/BSPRule;
    3516: aastore
    3517: dup
    3518: sipush        132
    3521: getstatic     #407                // Field R6906:Lorg/apache/wss4j/common/bsp/BSPRule;
    3524: aastore
    3525: dup
    3526: sipush        133
    3529: getstatic     #410                // Field R6905:Lorg/apache/wss4j/common/bsp/BSPRule;
    3532: aastore
    3533: dup
    3534: sipush        134
    3537: getstatic     #413                // Field R6601:Lorg/apache/wss4j/common/bsp/BSPRule;
    3540: aastore
    3541: dup
    3542: sipush        135
    3545: getstatic     #416                // Field R6611:Lorg/apache/wss4j/common/bsp/BSPRule;
    3548: aastore
    3549: dup
    3550: sipush        136
    3553: getstatic     #419                // Field R6617:Lorg/apache/wss4j/common/bsp/BSPRule;
    3556: aastore
    3557: dup
    3558: sipush        137
    3561: getstatic     #422                // Field R6614:Lorg/apache/wss4j/common/bsp/BSPRule;
    3564: aastore
    3565: dup
    3566: sipush        138
    3569: getstatic     #425                // Field R6602:Lorg/apache/wss4j/common/bsp/BSPRule;
    3572: aastore
    3573: dup
    3574: sipush        139
    3577: getstatic     #428                // Field R6609:Lorg/apache/wss4j/common/bsp/BSPRule;
    3580: aastore
    3581: dup
    3582: sipush        140
    3585: getstatic     #431                // Field R6603:Lorg/apache/wss4j/common/bsp/BSPRule;
    3588: aastore
    3589: dup
    3590: sipush        141
    3593: getstatic     #434                // Field R6616:Lorg/apache/wss4j/common/bsp/BSPRule;
    3596: aastore
    3597: dup
    3598: sipush        142
    3601: getstatic     #437                // Field R6604:Lorg/apache/wss4j/common/bsp/BSPRule;
    3604: aastore
    3605: dup
    3606: sipush        143
    3609: getstatic     #440                // Field R6605:Lorg/apache/wss4j/common/bsp/BSPRule;
    3612: aastore
    3613: dup
    3614: sipush        144
    3617: getstatic     #443                // Field R6610:Lorg/apache/wss4j/common/bsp/BSPRule;
    3620: aastore
    3621: dup
    3622: sipush        145
    3625: getstatic     #446                // Field R6612:Lorg/apache/wss4j/common/bsp/BSPRule;
    3628: aastore
    3629: dup
    3630: sipush        146
    3633: getstatic     #449                // Field R6606:Lorg/apache/wss4j/common/bsp/BSPRule;
    3636: aastore
    3637: dup
    3638: sipush        147
    3641: getstatic     #452                // Field R6607:Lorg/apache/wss4j/common/bsp/BSPRule;
    3644: aastore
    3645: dup
    3646: sipush        148
    3649: getstatic     #455                // Field R6608:Lorg/apache/wss4j/common/bsp/BSPRule;
    3652: aastore
    3653: dup
    3654: sipush        149
    3657: getstatic     #458                // Field R6613:Lorg/apache/wss4j/common/bsp/BSPRule;
    3660: aastore
    3661: dup
    3662: sipush        150
    3665: getstatic     #461                // Field R3069:Lorg/apache/wss4j/common/bsp/BSPRule;
    3668: aastore
    3669: dup
    3670: sipush        151
    3673: getstatic     #464                // Field R3072:Lorg/apache/wss4j/common/bsp/BSPRule;
    3676: aastore
    3677: putstatic     #1                  // Field $VALUES:[Lorg/apache/wss4j/common/bsp/BSPRule;
    3680: return
}
