Compiled from "ClientApplication.scala"
public final class io.youi.app.ClientApplication$anon$importedEncoder$macro$173$1$$anon$8 implements shapeless.DefaultSymbolicLabelling<scala.collection.immutable.Nil$> {
  public shapeless.HNil apply();
    Code:
       0: getstatic     #21                 // Field shapeless/HNil$.MODULE$:Lshapeless/HNil$;
       3: areturn

  public java.lang.Object apply();
    Code:
       0: aload_0
       1: invokevirtual #26                 // Method apply:()Lshapeless/HNil;
       4: areturn

  public io.youi.app.ClientApplication$anon$importedEncoder$macro$173$1$$anon$8(io.youi.app.ClientApplication$anon$importedEncoder$macro$173$1);
    Code:
       0: aload_0
       1: invokespecial #31                 // Method java/lang/Object."<init>":()V
       4: return
}
