Compiled from "DTDEntityResolver.java"
public class org.hibernate.internal.util.xml.DTDEntityResolver implements org.xml.sax.EntityResolver,java.io.Serializable {
  private static final org.hibernate.internal.CoreMessageLogger LOG;

  private static final java.lang.String HIBERNATE_NAMESPACE;

  private static final java.lang.String OLD_HIBERNATE_NAMESPACE;

  private static final java.lang.String USER_NAMESPACE;

  public org.hibernate.internal.util.xml.DTDEntityResolver();
    Code:
       0: aload_0
       1: invokespecial #1                  // Method java/lang/Object."<init>":()V
       4: return

  public org.xml.sax.InputSource resolveEntity(java.lang.String, java.lang.String);
    Code:
       0: aconst_null
       1: astore_3
       2: aload_2
       3: ifnull        179
       6: getstatic     #2                  // Field LOG:Lorg/hibernate/internal/CoreMessageLogger;
       9: ldc           #3                  // String Trying to resolve system-id [%s]
      11: aload_2
      12: invokeinterface #4,  3            // InterfaceMethod org/hibernate/internal/CoreMessageLogger.debugf:(Ljava/lang/String;Ljava/lang/Object;)V
      17: aload_2
      18: ldc           #6                  // String http://www.hibernate.org/dtd/
      20: invokevirtual #7                  // Method java/lang/String.startsWith:(Ljava/lang/String;)Z
      23: ifeq          48
      26: getstatic     #2                  // Field LOG:Lorg/hibernate/internal/CoreMessageLogger;
      29: ldc           #8                  // String Recognized hibernate namespace; attempting to resolve on classpath under org/hibernate/
      31: invokeinterface #9,  2            // InterfaceMethod org/hibernate/internal/CoreMessageLogger.debug:(Ljava/lang/Object;)V
      36: aload_0
      37: aload_1
      38: aload_2
      39: ldc           #6                  // String http://www.hibernate.org/dtd/
      41: invokespecial #10                 // Method resolveOnClassPath:(Ljava/lang/String;Ljava/lang/String;Ljava/lang/String;)Lorg/xml/sax/InputSource;
      44: astore_3
      45: goto          179
      48: aload_2
      49: ldc           #11                 // String http://hibernate.sourceforge.net/
      51: invokevirtual #7                  // Method java/lang/String.startsWith:(Ljava/lang/String;)Z
      54: ifeq          91
      57: getstatic     #2                  // Field LOG:Lorg/hibernate/internal/CoreMessageLogger;
      60: ldc           #11                 // String http://hibernate.sourceforge.net/
      62: ldc           #6                  // String http://www.hibernate.org/dtd/
      64: invokeinterface #12,  3           // InterfaceMethod org/hibernate/internal/CoreMessageLogger.recognizedObsoleteHibernateNamespace:(Ljava/lang/String;Ljava/lang/String;)V
      69: getstatic     #2                  // Field LOG:Lorg/hibernate/internal/CoreMessageLogger;
      72: ldc           #13                 // String Attempting to resolve on classpath under org/hibernate/
      74: invokeinterface #9,  2            // InterfaceMethod org/hibernate/internal/CoreMessageLogger.debug:(Ljava/lang/Object;)V
      79: aload_0
      80: aload_1
      81: aload_2
      82: ldc           #11                 // String http://hibernate.sourceforge.net/
      84: invokespecial #10                 // Method resolveOnClassPath:(Ljava/lang/String;Ljava/lang/String;Ljava/lang/String;)Lorg/xml/sax/InputSource;
      87: astore_3
      88: goto          179
      91: aload_2
      92: ldc           #14                 // String classpath://
      94: invokevirtual #7                  // Method java/lang/String.startsWith:(Ljava/lang/String;)Z
      97: ifeq          179
     100: getstatic     #2                  // Field LOG:Lorg/hibernate/internal/CoreMessageLogger;
     103: ldc           #15                 // String Recognized local namespace; attempting to resolve on classpath
     105: invokeinterface #9,  2            // InterfaceMethod org/hibernate/internal/CoreMessageLogger.debug:(Ljava/lang/Object;)V
     110: aload_2
     111: ldc           #14                 // String classpath://
     113: invokevirtual #16                 // Method java/lang/String.length:()I
     116: invokevirtual #17                 // Method java/lang/String.substring:(I)Ljava/lang/String;
     119: astore        4
     121: aload_0
     122: aload         4
     124: invokevirtual #18                 // Method resolveInLocalNamespace:(Ljava/lang/String;)Ljava/io/InputStream;
     127: astore        5
     129: aload         5
     131: ifnonnull     148
     134: getstatic     #2                  // Field LOG:Lorg/hibernate/internal/CoreMessageLogger;
     137: ldc           #19                 // String Unable to locate [%s] on classpath
     139: aload_2
     140: invokeinterface #4,  3            // InterfaceMethod org/hibernate/internal/CoreMessageLogger.debugf:(Ljava/lang/String;Ljava/lang/Object;)V
     145: goto          179
     148: getstatic     #2                  // Field LOG:Lorg/hibernate/internal/CoreMessageLogger;
     151: ldc           #20                 // String Located [%s] in classpath
     153: aload_2
     154: invokeinterface #4,  3            // InterfaceMethod org/hibernate/internal/CoreMessageLogger.debugf:(Ljava/lang/String;Ljava/lang/Object;)V
     159: new           #21                 // class org/xml/sax/InputSource
     162: dup
     163: aload         5
     165: invokespecial #22                 // Method org/xml/sax/InputSource."<init>":(Ljava/io/InputStream;)V
     168: astore_3
     169: aload_3
     170: aload_1
     171: invokevirtual #23                 // Method org/xml/sax/InputSource.setPublicId:(Ljava/lang/String;)V
     174: aload_3
     175: aload_2
     176: invokevirtual #24                 // Method org/xml/sax/InputSource.setSystemId:(Ljava/lang/String;)V
     179: aload_3
     180: areturn

  private org.xml.sax.InputSource resolveOnClassPath(java.lang.String, java.lang.String, java.lang.String);
    Code:
       0: aconst_null
       1: astore        4
       3: new           #25                 // class java/lang/StringBuilder
       6: dup
       7: invokespecial #26                 // Method java/lang/StringBuilder."<init>":()V
      10: ldc           #27                 // String org/hibernate/
      12: invokevirtual #28                 // Method java/lang/StringBuilder.append:(Ljava/lang/String;)Ljava/lang/StringBuilder;
      15: aload_2
      16: aload_3
      17: invokevirtual #16                 // Method java/lang/String.length:()I
      20: invokevirtual #17                 // Method java/lang/String.substring:(I)Ljava/lang/String;
      23: invokevirtual #28                 // Method java/lang/StringBuilder.append:(Ljava/lang/String;)Ljava/lang/StringBuilder;
      26: invokevirtual #29                 // Method java/lang/StringBuilder.toString:()Ljava/lang/String;
      29: astore        5
      31: aload_0
      32: aload         5
      34: invokevirtual #30                 // Method resolveInHibernateNamespace:(Ljava/lang/String;)Ljava/io/InputStream;
      37: astore        6
      39: aload         6
      41: ifnonnull     83
      44: getstatic     #2                  // Field LOG:Lorg/hibernate/internal/CoreMessageLogger;
      47: ldc           #19                 // String Unable to locate [%s] on classpath
      49: aload_2
      50: invokeinterface #4,  3            // InterfaceMethod org/hibernate/internal/CoreMessageLogger.debugf:(Ljava/lang/String;Ljava/lang/Object;)V
      55: aload_2
      56: aload_3
      57: invokevirtual #16                 // Method java/lang/String.length:()I
      60: invokevirtual #17                 // Method java/lang/String.substring:(I)Ljava/lang/String;
      63: ldc           #31                 // String 2.0
      65: invokevirtual #32                 // Method java/lang/String.indexOf:(Ljava/lang/String;)I
      68: iconst_m1
      69: if_icmple     117
      72: getstatic     #2                  // Field LOG:Lorg/hibernate/internal/CoreMessageLogger;
      75: invokeinterface #33,  1           // InterfaceMethod org/hibernate/internal/CoreMessageLogger.usingOldDtd:()V
      80: goto          117
      83: getstatic     #2                  // Field LOG:Lorg/hibernate/internal/CoreMessageLogger;
      86: ldc           #20                 // String Located [%s] in classpath
      88: aload_2
      89: invokeinterface #4,  3            // InterfaceMethod org/hibernate/internal/CoreMessageLogger.debugf:(Ljava/lang/String;Ljava/lang/Object;)V
      94: new           #21                 // class org/xml/sax/InputSource
      97: dup
      98: aload         6
     100: invokespecial #22                 // Method org/xml/sax/InputSource."<init>":(Ljava/io/InputStream;)V
     103: astore        4
     105: aload         4
     107: aload_1
     108: invokevirtual #23                 // Method org/xml/sax/InputSource.setPublicId:(Ljava/lang/String;)V
     111: aload         4
     113: aload_2
     114: invokevirtual #24                 // Method org/xml/sax/InputSource.setSystemId:(Ljava/lang/String;)V
     117: aload         4
     119: areturn

  protected java.io.InputStream resolveInHibernateNamespace(java.lang.String);
    Code:
       0: aload_0
       1: invokevirtual #34                 // Method java/lang/Object.getClass:()Ljava/lang/Class;
       4: invokevirtual #35                 // Method java/lang/Class.getClassLoader:()Ljava/lang/ClassLoader;
       7: aload_1
       8: invokevirtual #36                 // Method java/lang/ClassLoader.getResourceAsStream:(Ljava/lang/String;)Ljava/io/InputStream;
      11: areturn

  protected java.io.InputStream resolveInLocalNamespace(java.lang.String);
    Code:
       0: aload_1
       1: invokestatic  #37                 // Method org/hibernate/internal/util/ConfigHelper.getUserResourceAsStream:(Ljava/lang/String;)Ljava/io/InputStream;
       4: areturn
       5: astore_2
       6: aconst_null
       7: areturn
    Exception table:
       from    to  target type
           0     4     5   Class java/lang/Throwable

  static {};
    Code:
       0: ldc           #39                 // class org/hibernate/internal/CoreMessageLogger
       2: ldc           #5                  // class org/hibernate/internal/util/xml/DTDEntityResolver
       4: invokevirtual #40                 // Method java/lang/Class.getName:()Ljava/lang/String;
       7: invokestatic  #41                 // Method org/jboss/logging/Logger.getMessageLogger:(Ljava/lang/Class;Ljava/lang/String;)Ljava/lang/Object;
      10: checkcast     #39                 // class org/hibernate/internal/CoreMessageLogger
      13: putstatic     #2                  // Field LOG:Lorg/hibernate/internal/CoreMessageLogger;
      16: return
}
