Compiled from "TimelineSample.java"
public class org.javasimon.callback.timeline.TimelineSample<TR extends org.javasimon.callback.timeline.TimeRange> {
  private final int capacity;

  private final long width;

  private final TR[] timeRanges;

  public org.javasimon.callback.timeline.TimelineSample(int, long, TR[]);
    Code:
       0: aload_0
       1: invokespecial #1                  // Method java/lang/Object."<init>":()V
       4: aload_0
       5: iload_1
       6: putfield      #2                  // Field capacity:I
       9: aload_0
      10: lload_2
      11: putfield      #3                  // Field width:J
      14: aload_0
      15: aload         4
      17: putfield      #4                  // Field timeRanges:[Lorg/javasimon/callback/timeline/TimeRange;
      20: return

  public int getCapacity();
    Code:
       0: aload_0
       1: getfield      #2                  // Field capacity:I
       4: ireturn

  public long getWidth();
    Code:
       0: aload_0
       1: getfield      #3                  // Field width:J
       4: lreturn

  public TR[] getTimeRanges();
    Code:
       0: aload_0
       1: getfield      #4                  // Field timeRanges:[Lorg/javasimon/callback/timeline/TimeRange;
       4: areturn
}
