Compiled from "ClientSessionFactoryImpl.java"
class org.apache.activemq.artemis.core.client.impl.ClientSessionFactoryImpl$2 implements java.security.PrivilegedAction<org.apache.activemq.artemis.spi.core.remoting.ConnectorFactory> {
  final java.lang.String val$connectorFactoryClassName;

  final org.apache.activemq.artemis.core.client.impl.ClientSessionFactoryImpl this$0;

  org.apache.activemq.artemis.core.client.impl.ClientSessionFactoryImpl$2(org.apache.activemq.artemis.core.client.impl.ClientSessionFactoryImpl, java.lang.String);
    Code:
       0: aload_0
       1: aload_1
       2: putfield      #1                  // Field this$0:Lorg/apache/activemq/artemis/core/client/impl/ClientSessionFactoryImpl;
       5: aload_0
       6: aload_2
       7: putfield      #2                  // Field val$connectorFactoryClassName:Ljava/lang/String;
      10: aload_0
      11: invokespecial #3                  // Method java/lang/Object."<init>":()V
      14: return

  public org.apache.activemq.artemis.spi.core.remoting.ConnectorFactory run();
    Code:
       0: aload_0
       1: getfield      #2                  // Field val$connectorFactoryClassName:Ljava/lang/String;
       4: invokestatic  #4                  // Method org/apache/activemq/artemis/utils/ClassloadingUtil.newInstanceFromClassLoader:(Ljava/lang/String;)Ljava/lang/Object;
       7: checkcast     #5                  // class org/apache/activemq/artemis/spi/core/remoting/ConnectorFactory
      10: areturn

  public java.lang.Object run();
    Code:
       0: aload_0
       1: invokevirtual #6                  // Method run:()Lorg/apache/activemq/artemis/spi/core/remoting/ConnectorFactory;
       4: areturn
}
