Compiled from "ClientSessionFactoryImpl.java"
final class org.apache.activemq.artemis.core.client.impl.ClientSessionFactoryImpl$DelegatingFailureListener implements org.apache.activemq.artemis.core.remoting.FailureListener {
  private final java.lang.Object connectionID;

  final org.apache.activemq.artemis.core.client.impl.ClientSessionFactoryImpl this$0;

  org.apache.activemq.artemis.core.client.impl.ClientSessionFactoryImpl$DelegatingFailureListener(org.apache.activemq.artemis.core.client.impl.ClientSessionFactoryImpl, java.lang.Object);
    Code:
       0: aload_0
       1: aload_1
       2: putfield      #1                  // Field this$0:Lorg/apache/activemq/artemis/core/client/impl/ClientSessionFactoryImpl;
       5: aload_0
       6: invokespecial #2                  // Method java/lang/Object."<init>":()V
       9: aload_0
      10: aload_2
      11: putfield      #3                  // Field connectionID:Ljava/lang/Object;
      14: return

  public void connectionFailed(org.apache.activemq.artemis.api.core.ActiveMQException, boolean);
    Code:
       0: aload_0
       1: aload_1
       2: iload_2
       3: aconst_null
       4: invokevirtual #4                  // Method connectionFailed:(Lorg/apache/activemq/artemis/api/core/ActiveMQException;ZLjava/lang/String;)V
       7: return

  public void connectionFailed(org.apache.activemq.artemis.api.core.ActiveMQException, boolean, java.lang.String);
    Code:
       0: aload_0
       1: getfield      #1                  // Field this$0:Lorg/apache/activemq/artemis/core/client/impl/ClientSessionFactoryImpl;
       4: aload_0
       5: getfield      #3                  // Field connectionID:Ljava/lang/Object;
       8: aload_1
       9: aload_3
      10: invokestatic  #5                  // Method org/apache/activemq/artemis/core/client/impl/ClientSessionFactoryImpl.access$400:(Lorg/apache/activemq/artemis/core/client/impl/ClientSessionFactoryImpl;Ljava/lang/Object;Lorg/apache/activemq/artemis/api/core/ActiveMQException;Ljava/lang/String;)V
      13: return

  public java.lang.String toString();
    Code:
       0: new           #6                  // class java/lang/StringBuilder
       3: dup
       4: invokespecial #7                  // Method java/lang/StringBuilder."<init>":()V
       7: ldc           #8                  // class org/apache/activemq/artemis/core/client/impl/ClientSessionFactoryImpl$DelegatingFailureListener
       9: invokevirtual #9                  // Method java/lang/Class.getSimpleName:()Ljava/lang/String;
      12: invokevirtual #10                 // Method java/lang/StringBuilder.append:(Ljava/lang/String;)Ljava/lang/StringBuilder;
      15: ldc           #11                 // String (\'reconnectsOrFailover\', hash=
      17: invokevirtual #10                 // Method java/lang/StringBuilder.append:(Ljava/lang/String;)Ljava/lang/StringBuilder;
      20: aload_0
      21: invokespecial #12                 // Method java/lang/Object.hashCode:()I
      24: invokevirtual #13                 // Method java/lang/StringBuilder.append:(I)Ljava/lang/StringBuilder;
      27: ldc           #14                 // String )
      29: invokevirtual #10                 // Method java/lang/StringBuilder.append:(Ljava/lang/String;)Ljava/lang/StringBuilder;
      32: invokevirtual #15                 // Method java/lang/StringBuilder.toString:()Ljava/lang/String;
      35: areturn
}
