Compiled from "ArrayTypeAdapter.java"
class com.google.gson.internal.bind.ArrayTypeAdapter$1 implements com.google.gson.TypeAdapterFactory {
  com.google.gson.internal.bind.ArrayTypeAdapter$1();
    Code:
       0: aload_0
       1: invokespecial #1                  // Method java/lang/Object."<init>":()V
       4: return

  public <T> com.google.gson.TypeAdapter<T> create(com.google.gson.Gson, com.google.gson.reflect.TypeToken<T>);
    Code:
       0: aload_2
       1: invokevirtual #2                  // Method com/google/gson/reflect/TypeToken.getType:()Ljava/lang/reflect/Type;
       4: astore_3
       5: aload_3
       6: instanceof    #3                  // class java/lang/reflect/GenericArrayType
       9: ifne          31
      12: aload_3
      13: instanceof    #4                  // class java/lang/Class
      16: ifeq          29
      19: aload_3
      20: checkcast     #4                  // class java/lang/Class
      23: invokevirtual #5                  // Method java/lang/Class.isArray:()Z
      26: ifne          31
      29: aconst_null
      30: areturn
      31: aload_3
      32: invokestatic  #6                  // Method com/google/gson/internal/$Gson$Types.getArrayComponentType:(Ljava/lang/reflect/Type;)Ljava/lang/reflect/Type;
      35: astore        4
      37: aload_1
      38: aload         4
      40: invokestatic  #7                  // Method com/google/gson/reflect/TypeToken.get:(Ljava/lang/reflect/Type;)Lcom/google/gson/reflect/TypeToken;
      43: invokevirtual #8                  // Method com/google/gson/Gson.getAdapter:(Lcom/google/gson/reflect/TypeToken;)Lcom/google/gson/TypeAdapter;
      46: astore        5
      48: new           #9                  // class com/google/gson/internal/bind/ArrayTypeAdapter
      51: dup
      52: aload_1
      53: aload         5
      55: aload         4
      57: invokestatic  #10                 // Method com/google/gson/internal/$Gson$Types.getRawType:(Ljava/lang/reflect/Type;)Ljava/lang/Class;
      60: invokespecial #11                 // Method com/google/gson/internal/bind/ArrayTypeAdapter."<init>":(Lcom/google/gson/Gson;Lcom/google/gson/TypeAdapter;Ljava/lang/Class;)V
      63: areturn
}
