Compiled from "DocFileManager.java"
public class org.hibernate.tool.hbm2x.doc.DocFileManager {
  private org.hibernate.tool.hbm2x.doc.DocFolder rootDocFolder;

  private org.hibernate.tool.hbm2x.doc.DocFile mainIndexDocFile;

  private org.hibernate.tool.hbm2x.doc.DocFolder assetsDocFolder;

  private org.hibernate.tool.hbm2x.doc.DocFile hibernateImageDocFile;

  private org.hibernate.tool.hbm2x.doc.DocFile extendsImageDocFile;

  private org.hibernate.tool.hbm2x.doc.DocFile cssStylesDocFile;

  private org.hibernate.tool.hbm2x.doc.DocFolder rootTablesDocFolder;

  private org.hibernate.tool.hbm2x.doc.DocFolder rootEntitiesDocFolder;

  private org.hibernate.tool.hbm2x.doc.DocFile classIndexDocFile;

  private org.hibernate.tool.hbm2x.doc.DocFile entitySummaryDocFile;

  private org.hibernate.tool.hbm2x.doc.DocFile allPackagesDocFile;

  private org.hibernate.tool.hbm2x.doc.DocFile allEntitiesDocFile;

  private org.hibernate.tool.hbm2x.doc.DocFile tableIndexDocFile;

  private org.hibernate.tool.hbm2x.doc.DocFile tableSummaryDocFile;

  private org.hibernate.tool.hbm2x.doc.DocFile allSchemasDocFile;

  private org.hibernate.tool.hbm2x.doc.DocFile allTablesDocFile;

  private java.util.Map tableDocFiles;

  private java.util.Map entityDocFiles;

  private java.util.Map schemaSummaryDocFiles;

  private java.util.Map packageSummaryDocFiles;

  private java.util.Map schemaTableListDocFiles;

  private java.util.Map packageEntityListDocFile;

  public org.hibernate.tool.hbm2x.doc.DocFolder getRootDocFolder();
    Code:
       0: aload_0
       1: getfield      #1                  // Field rootDocFolder:Lorg/hibernate/tool/hbm2x/doc/DocFolder;
       4: areturn

  public org.hibernate.tool.hbm2x.doc.DocFileManager(org.hibernate.tool.hbm2x.doc.DocHelper, java.io.File);
    Code:
       0: aload_0
       1: invokespecial #2                  // Method java/lang/Object."<init>":()V
       4: aload_0
       5: new           #3                  // class java/util/HashMap
       8: dup
       9: invokespecial #4                  // Method java/util/HashMap."<init>":()V
      12: putfield      #5                  // Field tableDocFiles:Ljava/util/Map;
      15: aload_0
      16: new           #3                  // class java/util/HashMap
      19: dup
      20: invokespecial #4                  // Method java/util/HashMap."<init>":()V
      23: putfield      #6                  // Field entityDocFiles:Ljava/util/Map;
      26: aload_0
      27: new           #3                  // class java/util/HashMap
      30: dup
      31: invokespecial #4                  // Method java/util/HashMap."<init>":()V
      34: putfield      #7                  // Field schemaSummaryDocFiles:Ljava/util/Map;
      37: aload_0
      38: new           #3                  // class java/util/HashMap
      41: dup
      42: invokespecial #4                  // Method java/util/HashMap."<init>":()V
      45: putfield      #8                  // Field packageSummaryDocFiles:Ljava/util/Map;
      48: aload_0
      49: new           #3                  // class java/util/HashMap
      52: dup
      53: invokespecial #4                  // Method java/util/HashMap."<init>":()V
      56: putfield      #9                  // Field schemaTableListDocFiles:Ljava/util/Map;
      59: aload_0
      60: new           #3                  // class java/util/HashMap
      63: dup
      64: invokespecial #4                  // Method java/util/HashMap."<init>":()V
      67: putfield      #10                 // Field packageEntityListDocFile:Ljava/util/Map;
      70: aload_0
      71: new           #11                 // class org/hibernate/tool/hbm2x/doc/DocFolder
      74: dup
      75: aload_2
      76: invokespecial #12                 // Method org/hibernate/tool/hbm2x/doc/DocFolder."<init>":(Ljava/io/File;)V
      79: putfield      #1                  // Field rootDocFolder:Lorg/hibernate/tool/hbm2x/doc/DocFolder;
      82: aload_0
      83: new           #13                 // class org/hibernate/tool/hbm2x/doc/DocFile
      86: dup
      87: ldc           #14                 // String index.html
      89: aload_0
      90: getfield      #1                  // Field rootDocFolder:Lorg/hibernate/tool/hbm2x/doc/DocFolder;
      93: invokespecial #15                 // Method org/hibernate/tool/hbm2x/doc/DocFile."<init>":(Ljava/lang/String;Lorg/hibernate/tool/hbm2x/doc/DocFolder;)V
      96: putfield      #16                 // Field mainIndexDocFile:Lorg/hibernate/tool/hbm2x/doc/DocFile;
      99: aload_0
     100: new           #11                 // class org/hibernate/tool/hbm2x/doc/DocFolder
     103: dup
     104: ldc           #17                 // String assets
     106: aload_0
     107: getfield      #1                  // Field rootDocFolder:Lorg/hibernate/tool/hbm2x/doc/DocFolder;
     110: invokespecial #18                 // Method org/hibernate/tool/hbm2x/doc/DocFolder."<init>":(Ljava/lang/String;Lorg/hibernate/tool/hbm2x/doc/DocFolder;)V
     113: putfield      #19                 // Field assetsDocFolder:Lorg/hibernate/tool/hbm2x/doc/DocFolder;
     116: aload_0
     117: new           #13                 // class org/hibernate/tool/hbm2x/doc/DocFile
     120: dup
     121: ldc           #20                 // String hibernate_logo.gif
     123: aload_0
     124: getfield      #19                 // Field assetsDocFolder:Lorg/hibernate/tool/hbm2x/doc/DocFolder;
     127: invokespecial #15                 // Method org/hibernate/tool/hbm2x/doc/DocFile."<init>":(Ljava/lang/String;Lorg/hibernate/tool/hbm2x/doc/DocFolder;)V
     130: putfield      #21                 // Field hibernateImageDocFile:Lorg/hibernate/tool/hbm2x/doc/DocFile;
     133: aload_0
     134: new           #13                 // class org/hibernate/tool/hbm2x/doc/DocFile
     137: dup
     138: ldc           #22                 // String inherit.gif
     140: aload_0
     141: getfield      #19                 // Field assetsDocFolder:Lorg/hibernate/tool/hbm2x/doc/DocFolder;
     144: invokespecial #15                 // Method org/hibernate/tool/hbm2x/doc/DocFile."<init>":(Ljava/lang/String;Lorg/hibernate/tool/hbm2x/doc/DocFolder;)V
     147: putfield      #23                 // Field extendsImageDocFile:Lorg/hibernate/tool/hbm2x/doc/DocFile;
     150: aload_0
     151: new           #13                 // class org/hibernate/tool/hbm2x/doc/DocFile
     154: dup
     155: ldc           #24                 // String doc-style.css
     157: aload_0
     158: getfield      #19                 // Field assetsDocFolder:Lorg/hibernate/tool/hbm2x/doc/DocFolder;
     161: invokespecial #15                 // Method org/hibernate/tool/hbm2x/doc/DocFile."<init>":(Ljava/lang/String;Lorg/hibernate/tool/hbm2x/doc/DocFolder;)V
     164: putfield      #25                 // Field cssStylesDocFile:Lorg/hibernate/tool/hbm2x/doc/DocFile;
     167: aload_0
     168: new           #11                 // class org/hibernate/tool/hbm2x/doc/DocFolder
     171: dup
     172: ldc           #26                 // String entities
     174: aload_0
     175: getfield      #1                  // Field rootDocFolder:Lorg/hibernate/tool/hbm2x/doc/DocFolder;
     178: invokespecial #18                 // Method org/hibernate/tool/hbm2x/doc/DocFolder."<init>":(Ljava/lang/String;Lorg/hibernate/tool/hbm2x/doc/DocFolder;)V
     181: putfield      #27                 // Field rootEntitiesDocFolder:Lorg/hibernate/tool/hbm2x/doc/DocFolder;
     184: aload_0
     185: new           #13                 // class org/hibernate/tool/hbm2x/doc/DocFile
     188: dup
     189: ldc           #14                 // String index.html
     191: aload_0
     192: getfield      #27                 // Field rootEntitiesDocFolder:Lorg/hibernate/tool/hbm2x/doc/DocFolder;
     195: invokespecial #15                 // Method org/hibernate/tool/hbm2x/doc/DocFile."<init>":(Ljava/lang/String;Lorg/hibernate/tool/hbm2x/doc/DocFolder;)V
     198: putfield      #28                 // Field classIndexDocFile:Lorg/hibernate/tool/hbm2x/doc/DocFile;
     201: aload_0
     202: new           #13                 // class org/hibernate/tool/hbm2x/doc/DocFile
     205: dup
     206: ldc           #29                 // String summary.html
     208: aload_0
     209: getfield      #27                 // Field rootEntitiesDocFolder:Lorg/hibernate/tool/hbm2x/doc/DocFolder;
     212: invokespecial #15                 // Method org/hibernate/tool/hbm2x/doc/DocFile."<init>":(Ljava/lang/String;Lorg/hibernate/tool/hbm2x/doc/DocFolder;)V
     215: putfield      #30                 // Field entitySummaryDocFile:Lorg/hibernate/tool/hbm2x/doc/DocFile;
     218: aload_0
     219: new           #13                 // class org/hibernate/tool/hbm2x/doc/DocFile
     222: dup
     223: ldc           #31                 // String allpackages.html
     225: aload_0
     226: getfield      #27                 // Field rootEntitiesDocFolder:Lorg/hibernate/tool/hbm2x/doc/DocFolder;
     229: invokespecial #15                 // Method org/hibernate/tool/hbm2x/doc/DocFile."<init>":(Ljava/lang/String;Lorg/hibernate/tool/hbm2x/doc/DocFolder;)V
     232: putfield      #32                 // Field allPackagesDocFile:Lorg/hibernate/tool/hbm2x/doc/DocFile;
     235: aload_0
     236: new           #13                 // class org/hibernate/tool/hbm2x/doc/DocFile
     239: dup
     240: ldc           #33                 // String allentities.html
     242: aload_0
     243: getfield      #27                 // Field rootEntitiesDocFolder:Lorg/hibernate/tool/hbm2x/doc/DocFolder;
     246: invokespecial #15                 // Method org/hibernate/tool/hbm2x/doc/DocFile."<init>":(Ljava/lang/String;Lorg/hibernate/tool/hbm2x/doc/DocFolder;)V
     249: putfield      #34                 // Field allEntitiesDocFile:Lorg/hibernate/tool/hbm2x/doc/DocFile;
     252: aload_0
     253: new           #11                 // class org/hibernate/tool/hbm2x/doc/DocFolder
     256: dup
     257: ldc           #35                 // String tables
     259: aload_0
     260: getfield      #1                  // Field rootDocFolder:Lorg/hibernate/tool/hbm2x/doc/DocFolder;
     263: invokespecial #18                 // Method org/hibernate/tool/hbm2x/doc/DocFolder."<init>":(Ljava/lang/String;Lorg/hibernate/tool/hbm2x/doc/DocFolder;)V
     266: putfield      #36                 // Field rootTablesDocFolder:Lorg/hibernate/tool/hbm2x/doc/DocFolder;
     269: aload_0
     270: new           #13                 // class org/hibernate/tool/hbm2x/doc/DocFile
     273: dup
     274: ldc           #14                 // String index.html
     276: aload_0
     277: getfield      #36                 // Field rootTablesDocFolder:Lorg/hibernate/tool/hbm2x/doc/DocFolder;
     280: invokespecial #15                 // Method org/hibernate/tool/hbm2x/doc/DocFile."<init>":(Ljava/lang/String;Lorg/hibernate/tool/hbm2x/doc/DocFolder;)V
     283: putfield      #37                 // Field tableIndexDocFile:Lorg/hibernate/tool/hbm2x/doc/DocFile;
     286: aload_0
     287: new           #13                 // class org/hibernate/tool/hbm2x/doc/DocFile
     290: dup
     291: ldc           #29                 // String summary.html
     293: aload_0
     294: getfield      #36                 // Field rootTablesDocFolder:Lorg/hibernate/tool/hbm2x/doc/DocFolder;
     297: invokespecial #15                 // Method org/hibernate/tool/hbm2x/doc/DocFile."<init>":(Ljava/lang/String;Lorg/hibernate/tool/hbm2x/doc/DocFolder;)V
     300: putfield      #38                 // Field tableSummaryDocFile:Lorg/hibernate/tool/hbm2x/doc/DocFile;
     303: aload_0
     304: new           #13                 // class org/hibernate/tool/hbm2x/doc/DocFile
     307: dup
     308: ldc           #39                 // String allschemas.html
     310: aload_0
     311: getfield      #36                 // Field rootTablesDocFolder:Lorg/hibernate/tool/hbm2x/doc/DocFolder;
     314: invokespecial #15                 // Method org/hibernate/tool/hbm2x/doc/DocFile."<init>":(Ljava/lang/String;Lorg/hibernate/tool/hbm2x/doc/DocFolder;)V
     317: putfield      #40                 // Field allSchemasDocFile:Lorg/hibernate/tool/hbm2x/doc/DocFile;
     320: aload_0
     321: new           #13                 // class org/hibernate/tool/hbm2x/doc/DocFile
     324: dup
     325: ldc           #41                 // String alltables.html
     327: aload_0
     328: getfield      #36                 // Field rootTablesDocFolder:Lorg/hibernate/tool/hbm2x/doc/DocFolder;
     331: invokespecial #15                 // Method org/hibernate/tool/hbm2x/doc/DocFile."<init>":(Ljava/lang/String;Lorg/hibernate/tool/hbm2x/doc/DocFolder;)V
     334: putfield      #42                 // Field allTablesDocFile:Lorg/hibernate/tool/hbm2x/doc/DocFile;
     337: new           #3                  // class java/util/HashMap
     340: dup
     341: invokespecial #4                  // Method java/util/HashMap."<init>":()V
     344: astore_3
     345: aload_1
     346: invokevirtual #43                 // Method org/hibernate/tool/hbm2x/doc/DocHelper.getPackages:()Ljava/util/List;
     349: invokeinterface #44,  1           // InterfaceMethod java/util/List.iterator:()Ljava/util/Iterator;
     354: astore        4
     356: aload         4
     358: invokeinterface #45,  1           // InterfaceMethod java/util/Iterator.hasNext:()Z
     363: ifeq          605
     366: aload         4
     368: invokeinterface #46,  1           // InterfaceMethod java/util/Iterator.next:()Ljava/lang/Object;
     373: checkcast     #47                 // class java/lang/String
     376: astore        5
     378: aconst_null
     379: astore        6
     381: aload_0
     382: getfield      #27                 // Field rootEntitiesDocFolder:Lorg/hibernate/tool/hbm2x/doc/DocFolder;
     385: astore        7
     387: aload         5
     389: ldc           #48                 // String All Entities
     391: invokevirtual #49                 // Method java/lang/String.equals:(Ljava/lang/Object;)Z
     394: ifne          500
     397: aload         5
     399: ldc           #50                 // String \\.
     401: invokevirtual #51                 // Method java/lang/String.split:(Ljava/lang/String;)[Ljava/lang/String;
     404: astore        8
     406: iconst_0
     407: istore        9
     409: iload         9
     411: aload         8
     413: arraylength
     414: if_icmpge     443
     417: new           #11                 // class org/hibernate/tool/hbm2x/doc/DocFolder
     420: dup
     421: aload         8
     423: iload         9
     425: aaload
     426: aload         7
     428: invokespecial #18                 // Method org/hibernate/tool/hbm2x/doc/DocFolder."<init>":(Ljava/lang/String;Lorg/hibernate/tool/hbm2x/doc/DocFolder;)V
     431: astore        6
     433: aload         6
     435: astore        7
     437: iinc          9, 1
     440: goto          409
     443: new           #13                 // class org/hibernate/tool/hbm2x/doc/DocFile
     446: dup
     447: ldc           #29                 // String summary.html
     449: aload         6
     451: invokespecial #15                 // Method org/hibernate/tool/hbm2x/doc/DocFile."<init>":(Ljava/lang/String;Lorg/hibernate/tool/hbm2x/doc/DocFolder;)V
     454: astore        9
     456: aload_0
     457: getfield      #8                  // Field packageSummaryDocFiles:Ljava/util/Map;
     460: aload         5
     462: aload         9
     464: invokeinterface #52,  3           // InterfaceMethod java/util/Map.put:(Ljava/lang/Object;Ljava/lang/Object;)Ljava/lang/Object;
     469: pop
     470: new           #13                 // class org/hibernate/tool/hbm2x/doc/DocFile
     473: dup
     474: ldc           #53                 // String entities.html
     476: aload         6
     478: invokespecial #15                 // Method org/hibernate/tool/hbm2x/doc/DocFile."<init>":(Ljava/lang/String;Lorg/hibernate/tool/hbm2x/doc/DocFolder;)V
     481: astore        10
     483: aload_0
     484: getfield      #10                 // Field packageEntityListDocFile:Ljava/util/Map;
     487: aload         5
     489: aload         10
     491: invokeinterface #52,  3           // InterfaceMethod java/util/Map.put:(Ljava/lang/Object;Ljava/lang/Object;)Ljava/lang/Object;
     496: pop
     497: goto          506
     500: aload_0
     501: getfield      #27                 // Field rootEntitiesDocFolder:Lorg/hibernate/tool/hbm2x/doc/DocFolder;
     504: astore        6
     506: aload_1
     507: aload         5
     509: invokevirtual #54                 // Method org/hibernate/tool/hbm2x/doc/DocHelper.getClasses:(Ljava/lang/String;)Ljava/util/List;
     512: invokeinterface #44,  1           // InterfaceMethod java/util/List.iterator:()Ljava/util/Iterator;
     517: astore        8
     519: aload         8
     521: invokeinterface #45,  1           // InterfaceMethod java/util/Iterator.hasNext:()Z
     526: ifeq          602
     529: aload         8
     531: invokeinterface #46,  1           // InterfaceMethod java/util/Iterator.next:()Ljava/lang/Object;
     536: checkcast     #55                 // class org/hibernate/tool/hbm2x/pojo/POJOClass
     539: astore        9
     541: aload         9
     543: invokeinterface #56,  1           // InterfaceMethod org/hibernate/tool/hbm2x/pojo/POJOClass.getDeclarationName:()Ljava/lang/String;
     548: astore        10
     550: new           #57                 // class java/lang/StringBuffer
     553: dup
     554: invokespecial #58                 // Method java/lang/StringBuffer."<init>":()V
     557: aload         10
     559: invokevirtual #59                 // Method java/lang/StringBuffer.append:(Ljava/lang/String;)Ljava/lang/StringBuffer;
     562: ldc           #60                 // String .html
     564: invokevirtual #59                 // Method java/lang/StringBuffer.append:(Ljava/lang/String;)Ljava/lang/StringBuffer;
     567: invokevirtual #61                 // Method java/lang/StringBuffer.toString:()Ljava/lang/String;
     570: astore        10
     572: new           #13                 // class org/hibernate/tool/hbm2x/doc/DocFile
     575: dup
     576: aload         10
     578: aload         6
     580: invokespecial #15                 // Method org/hibernate/tool/hbm2x/doc/DocFile."<init>":(Ljava/lang/String;Lorg/hibernate/tool/hbm2x/doc/DocFolder;)V
     583: astore        11
     585: aload_0
     586: getfield      #6                  // Field entityDocFiles:Ljava/util/Map;
     589: aload         9
     591: aload         11
     593: invokeinterface #52,  3           // InterfaceMethod java/util/Map.put:(Ljava/lang/Object;Ljava/lang/Object;)Ljava/lang/Object;
     598: pop
     599: goto          519
     602: goto          356
     605: aload_1
     606: invokevirtual #62                 // Method org/hibernate/tool/hbm2x/doc/DocHelper.getSchemas:()Ljava/util/List;
     609: invokeinterface #44,  1           // InterfaceMethod java/util/List.iterator:()Ljava/util/Iterator;
     614: astore        5
     616: aload         5
     618: invokeinterface #45,  1           // InterfaceMethod java/util/Iterator.hasNext:()Z
     623: ifeq          819
     626: aload         5
     628: invokeinterface #46,  1           // InterfaceMethod java/util/Iterator.next:()Ljava/lang/Object;
     633: checkcast     #47                 // class java/lang/String
     636: astore        6
     638: new           #11                 // class org/hibernate/tool/hbm2x/doc/DocFolder
     641: dup
     642: aload         6
     644: aload_0
     645: getfield      #36                 // Field rootTablesDocFolder:Lorg/hibernate/tool/hbm2x/doc/DocFolder;
     648: invokespecial #18                 // Method org/hibernate/tool/hbm2x/doc/DocFolder."<init>":(Ljava/lang/String;Lorg/hibernate/tool/hbm2x/doc/DocFolder;)V
     651: astore        7
     653: aload_3
     654: aload         6
     656: aload         7
     658: invokeinterface #52,  3           // InterfaceMethod java/util/Map.put:(Ljava/lang/Object;Ljava/lang/Object;)Ljava/lang/Object;
     663: pop
     664: new           #13                 // class org/hibernate/tool/hbm2x/doc/DocFile
     667: dup
     668: ldc           #29                 // String summary.html
     670: aload         7
     672: invokespecial #15                 // Method org/hibernate/tool/hbm2x/doc/DocFile."<init>":(Ljava/lang/String;Lorg/hibernate/tool/hbm2x/doc/DocFolder;)V
     675: astore        8
     677: aload_0
     678: getfield      #7                  // Field schemaSummaryDocFiles:Ljava/util/Map;
     681: aload         6
     683: aload         8
     685: invokeinterface #52,  3           // InterfaceMethod java/util/Map.put:(Ljava/lang/Object;Ljava/lang/Object;)Ljava/lang/Object;
     690: pop
     691: new           #13                 // class org/hibernate/tool/hbm2x/doc/DocFile
     694: dup
     695: ldc           #63                 // String tables.html
     697: aload         7
     699: invokespecial #15                 // Method org/hibernate/tool/hbm2x/doc/DocFile."<init>":(Ljava/lang/String;Lorg/hibernate/tool/hbm2x/doc/DocFolder;)V
     702: astore        9
     704: aload_0
     705: getfield      #9                  // Field schemaTableListDocFiles:Ljava/util/Map;
     708: aload         6
     710: aload         9
     712: invokeinterface #52,  3           // InterfaceMethod java/util/Map.put:(Ljava/lang/Object;Ljava/lang/Object;)Ljava/lang/Object;
     717: pop
     718: aload_1
     719: aload         6
     721: invokevirtual #64                 // Method org/hibernate/tool/hbm2x/doc/DocHelper.getTables:(Ljava/lang/String;)Ljava/util/List;
     724: invokeinterface #44,  1           // InterfaceMethod java/util/List.iterator:()Ljava/util/Iterator;
     729: astore        10
     731: aload         10
     733: invokeinterface #45,  1           // InterfaceMethod java/util/Iterator.hasNext:()Z
     738: ifeq          816
     741: aload         10
     743: invokeinterface #46,  1           // InterfaceMethod java/util/Iterator.next:()Ljava/lang/Object;
     748: checkcast     #65                 // class org/hibernate/mapping/Table
     751: astore        11
     753: aload         11
     755: invokevirtual #66                 // Method org/hibernate/mapping/Table.isPhysicalTable:()Z
     758: ifeq          813
     761: new           #57                 // class java/lang/StringBuffer
     764: dup
     765: invokespecial #58                 // Method java/lang/StringBuffer."<init>":()V
     768: aload         11
     770: invokevirtual #67                 // Method org/hibernate/mapping/Table.getName:()Ljava/lang/String;
     773: invokevirtual #59                 // Method java/lang/StringBuffer.append:(Ljava/lang/String;)Ljava/lang/StringBuffer;
     776: ldc           #60                 // String .html
     778: invokevirtual #59                 // Method java/lang/StringBuffer.append:(Ljava/lang/String;)Ljava/lang/StringBuffer;
     781: invokevirtual #61                 // Method java/lang/StringBuffer.toString:()Ljava/lang/String;
     784: astore        12
     786: new           #13                 // class org/hibernate/tool/hbm2x/doc/DocFile
     789: dup
     790: aload         12
     792: aload         7
     794: invokespecial #15                 // Method org/hibernate/tool/hbm2x/doc/DocFile."<init>":(Ljava/lang/String;Lorg/hibernate/tool/hbm2x/doc/DocFolder;)V
     797: astore        13
     799: aload_0
     800: getfield      #5                  // Field tableDocFiles:Ljava/util/Map;
     803: aload         11
     805: aload         13
     807: invokeinterface #52,  3           // InterfaceMethod java/util/Map.put:(Ljava/lang/Object;Ljava/lang/Object;)Ljava/lang/Object;
     812: pop
     813: goto          731
     816: goto          616
     819: return

  public org.hibernate.tool.hbm2x.doc.DocFolder getAssetsDocFolder();
    Code:
       0: aload_0
       1: getfield      #19                 // Field assetsDocFolder:Lorg/hibernate/tool/hbm2x/doc/DocFolder;
       4: areturn

  public org.hibernate.tool.hbm2x.doc.DocFile getCssStylesDocFile();
    Code:
       0: aload_0
       1: getfield      #25                 // Field cssStylesDocFile:Lorg/hibernate/tool/hbm2x/doc/DocFile;
       4: areturn

  public org.hibernate.tool.hbm2x.doc.DocFile getHibernateImageDocFile();
    Code:
       0: aload_0
       1: getfield      #21                 // Field hibernateImageDocFile:Lorg/hibernate/tool/hbm2x/doc/DocFile;
       4: areturn

  public org.hibernate.tool.hbm2x.doc.DocFile getExtendsImageDocFile();
    Code:
       0: aload_0
       1: getfield      #23                 // Field extendsImageDocFile:Lorg/hibernate/tool/hbm2x/doc/DocFile;
       4: areturn

  public org.hibernate.tool.hbm2x.doc.DocFile getMainIndexDocFile();
    Code:
       0: aload_0
       1: getfield      #16                 // Field mainIndexDocFile:Lorg/hibernate/tool/hbm2x/doc/DocFile;
       4: areturn

  public org.hibernate.tool.hbm2x.doc.DocFile getTableIndexDocFile();
    Code:
       0: aload_0
       1: getfield      #37                 // Field tableIndexDocFile:Lorg/hibernate/tool/hbm2x/doc/DocFile;
       4: areturn

  public org.hibernate.tool.hbm2x.doc.DocFile getClassIndexDocFile();
    Code:
       0: aload_0
       1: getfield      #28                 // Field classIndexDocFile:Lorg/hibernate/tool/hbm2x/doc/DocFile;
       4: areturn

  public org.hibernate.tool.hbm2x.doc.DocFile getClassSummaryFile();
    Code:
       0: aload_0
       1: getfield      #30                 // Field entitySummaryDocFile:Lorg/hibernate/tool/hbm2x/doc/DocFile;
       4: areturn

  public org.hibernate.tool.hbm2x.doc.DocFile getAllPackagesDocFile();
    Code:
       0: aload_0
       1: getfield      #32                 // Field allPackagesDocFile:Lorg/hibernate/tool/hbm2x/doc/DocFile;
       4: areturn

  public org.hibernate.tool.hbm2x.doc.DocFile getAllEntitiesDocFile();
    Code:
       0: aload_0
       1: getfield      #34                 // Field allEntitiesDocFile:Lorg/hibernate/tool/hbm2x/doc/DocFile;
       4: areturn

  public org.hibernate.tool.hbm2x.doc.DocFile getPackageEntityListDocFile(java.lang.String);
    Code:
       0: aload_0
       1: getfield      #10                 // Field packageEntityListDocFile:Ljava/util/Map;
       4: aload_1
       5: invokeinterface #68,  2           // InterfaceMethod java/util/Map.get:(Ljava/lang/Object;)Ljava/lang/Object;
      10: checkcast     #13                 // class org/hibernate/tool/hbm2x/doc/DocFile
      13: areturn

  public org.hibernate.tool.hbm2x.doc.DocFile getTableSummaryDocFile();
    Code:
       0: aload_0
       1: getfield      #38                 // Field tableSummaryDocFile:Lorg/hibernate/tool/hbm2x/doc/DocFile;
       4: areturn

  public org.hibernate.tool.hbm2x.doc.DocFile getAllSchemasDocFile();
    Code:
       0: aload_0
       1: getfield      #40                 // Field allSchemasDocFile:Lorg/hibernate/tool/hbm2x/doc/DocFile;
       4: areturn

  public org.hibernate.tool.hbm2x.doc.DocFile getAllTablesDocFile();
    Code:
       0: aload_0
       1: getfield      #42                 // Field allTablesDocFile:Lorg/hibernate/tool/hbm2x/doc/DocFile;
       4: areturn

  public org.hibernate.tool.hbm2x.doc.DocFile getTableDocFile(org.hibernate.mapping.Table);
    Code:
       0: aload_0
       1: getfield      #5                  // Field tableDocFiles:Ljava/util/Map;
       4: aload_1
       5: invokeinterface #68,  2           // InterfaceMethod java/util/Map.get:(Ljava/lang/Object;)Ljava/lang/Object;
      10: checkcast     #13                 // class org/hibernate/tool/hbm2x/doc/DocFile
      13: astore_2
      14: aload_2
      15: areturn

  public org.hibernate.tool.hbm2x.doc.DocFile getEntityDocFileByDeclarationName(org.hibernate.tool.hbm2x.pojo.POJOClass);
    Code:
       0: aload_0
       1: aload_1
       2: invokevirtual #69                 // Method getEntityDocFile:(Lorg/hibernate/tool/hbm2x/pojo/POJOClass;)Lorg/hibernate/tool/hbm2x/doc/DocFile;
       5: astore_2
       6: aload_1
       7: invokeinterface #70,  1           // InterfaceMethod org/hibernate/tool/hbm2x/pojo/POJOClass.getQualifiedDeclarationName:()Ljava/lang/String;
      12: astore_3
      13: aload_2
      14: ifnonnull     94
      17: aload_0
      18: getfield      #6                  // Field entityDocFiles:Ljava/util/Map;
      21: invokeinterface #71,  1           // InterfaceMethod java/util/Map.keySet:()Ljava/util/Set;
      26: invokeinterface #72,  1           // InterfaceMethod java/util/Set.iterator:()Ljava/util/Iterator;
      31: astore        5
      33: aload         5
      35: invokeinterface #45,  1           // InterfaceMethod java/util/Iterator.hasNext:()Z
      40: ifeq          94
      43: aload         5
      45: invokeinterface #46,  1           // InterfaceMethod java/util/Iterator.next:()Ljava/lang/Object;
      50: checkcast     #55                 // class org/hibernate/tool/hbm2x/pojo/POJOClass
      53: astore        6
      55: aload         6
      57: invokeinterface #70,  1           // InterfaceMethod org/hibernate/tool/hbm2x/pojo/POJOClass.getQualifiedDeclarationName:()Ljava/lang/String;
      62: astore        4
      64: aload_3
      65: aload         4
      67: invokevirtual #49                 // Method java/lang/String.equals:(Ljava/lang/Object;)Z
      70: ifeq          91
      73: aload_0
      74: getfield      #6                  // Field entityDocFiles:Ljava/util/Map;
      77: aload         6
      79: invokeinterface #68,  2           // InterfaceMethod java/util/Map.get:(Ljava/lang/Object;)Ljava/lang/Object;
      84: checkcast     #13                 // class org/hibernate/tool/hbm2x/doc/DocFile
      87: astore_2
      88: goto          94
      91: goto          33
      94: aload_2
      95: areturn

  public org.hibernate.tool.hbm2x.doc.DocFile getEntityDocFile(org.hibernate.tool.hbm2x.pojo.POJOClass);
    Code:
       0: aload_0
       1: getfield      #6                  // Field entityDocFiles:Ljava/util/Map;
       4: aload_1
       5: invokeinterface #68,  2           // InterfaceMethod java/util/Map.get:(Ljava/lang/Object;)Ljava/lang/Object;
      10: checkcast     #13                 // class org/hibernate/tool/hbm2x/doc/DocFile
      13: areturn

  public org.hibernate.tool.hbm2x.doc.DocFile getSchemaSummaryDocFile(java.lang.String);
    Code:
       0: aload_0
       1: getfield      #7                  // Field schemaSummaryDocFiles:Ljava/util/Map;
       4: aload_1
       5: invokeinterface #68,  2           // InterfaceMethod java/util/Map.get:(Ljava/lang/Object;)Ljava/lang/Object;
      10: checkcast     #13                 // class org/hibernate/tool/hbm2x/doc/DocFile
      13: areturn

  public org.hibernate.tool.hbm2x.doc.DocFile getPackageSummaryDocFile(java.lang.String);
    Code:
       0: aload_0
       1: getfield      #8                  // Field packageSummaryDocFiles:Ljava/util/Map;
       4: aload_1
       5: invokeinterface #68,  2           // InterfaceMethod java/util/Map.get:(Ljava/lang/Object;)Ljava/lang/Object;
      10: checkcast     #13                 // class org/hibernate/tool/hbm2x/doc/DocFile
      13: areturn

  public org.hibernate.tool.hbm2x.doc.DocFile getSchemaTableListDocFile(java.lang.String);
    Code:
       0: aload_0
       1: getfield      #9                  // Field schemaTableListDocFiles:Ljava/util/Map;
       4: aload_1
       5: invokeinterface #68,  2           // InterfaceMethod java/util/Map.get:(Ljava/lang/Object;)Ljava/lang/Object;
      10: checkcast     #13                 // class org/hibernate/tool/hbm2x/doc/DocFile
      13: areturn

  public java.lang.String getRef(org.hibernate.tool.hbm2x.doc.DocFile, org.hibernate.tool.hbm2x.doc.DocFile);
    Code:
       0: aload_1
       1: ifnonnull     14
       4: new           #73                 // class java/lang/IllegalArgumentException
       7: dup
       8: ldc           #74                 // String From cannot be null.
      10: invokespecial #75                 // Method java/lang/IllegalArgumentException."<init>":(Ljava/lang/String;)V
      13: athrow
      14: aload_2
      15: ifnonnull     28
      18: new           #73                 // class java/lang/IllegalArgumentException
      21: dup
      22: ldc           #76                 // String To cannot be null.
      24: invokespecial #75                 // Method java/lang/IllegalArgumentException."<init>":(Ljava/lang/String;)V
      27: athrow
      28: aload_1
      29: aload_2
      30: invokevirtual #77                 // Method org/hibernate/tool/hbm2x/doc/DocFile.buildRefTo:(Lorg/hibernate/tool/hbm2x/doc/DocFile;)Ljava/lang/String;
      33: areturn

  public static void copy(java.lang.ClassLoader, java.lang.String, java.io.File) throws java.io.IOException;
    Code:
       0: aconst_null
       1: astore_3
       2: aconst_null
       3: astore        4
       5: aload_0
       6: aload_1
       7: invokevirtual #78                 // Method java/lang/ClassLoader.getResourceAsStream:(Ljava/lang/String;)Ljava/io/InputStream;
      10: astore_3
      11: aload_3
      12: ifnonnull     42
      15: new           #73                 // class java/lang/IllegalArgumentException
      18: dup
      19: new           #57                 // class java/lang/StringBuffer
      22: dup
      23: invokespecial #58                 // Method java/lang/StringBuffer."<init>":()V
      26: ldc           #79                 // String File not found:
      28: invokevirtual #59                 // Method java/lang/StringBuffer.append:(Ljava/lang/String;)Ljava/lang/StringBuffer;
      31: aload_1
      32: invokevirtual #59                 // Method java/lang/StringBuffer.append:(Ljava/lang/String;)Ljava/lang/StringBuffer;
      35: invokevirtual #61                 // Method java/lang/StringBuffer.toString:()Ljava/lang/String;
      38: invokespecial #75                 // Method java/lang/IllegalArgumentException."<init>":(Ljava/lang/String;)V
      41: athrow
      42: new           #80                 // class java/io/FileOutputStream
      45: dup
      46: aload_2
      47: invokespecial #81                 // Method java/io/FileOutputStream."<init>":(Ljava/io/File;)V
      50: astore        4
      52: aload_3
      53: invokevirtual #82                 // Method java/io/InputStream.read:()I
      56: dup
      57: istore        5
      59: iconst_m1
      60: if_icmpeq     73
      63: aload         4
      65: iload         5
      67: invokevirtual #83                 // Method java/io/FileOutputStream.write:(I)V
      70: goto          52
      73: aload_3
      74: ifnull        81
      77: aload_3
      78: invokevirtual #84                 // Method java/io/InputStream.close:()V
      81: aload         4
      83: ifnull        117
      86: aload         4
      88: invokevirtual #85                 // Method java/io/FileOutputStream.close:()V
      91: goto          117
      94: astore        6
      96: aload_3
      97: ifnull        104
     100: aload_3
     101: invokevirtual #84                 // Method java/io/InputStream.close:()V
     104: aload         4
     106: ifnull        114
     109: aload         4
     111: invokevirtual #85                 // Method java/io/FileOutputStream.close:()V
     114: aload         6
     116: athrow
     117: return
    Exception table:
       from    to  target type
           5    73    94   any
          94    96    94   any
}
