Compiled from "EnhancingClassTransformerImpl.java"
class org.hibernate.jpa.internal.enhance.EnhancingClassTransformerImpl$1 extends java.lang.instrument.IllegalClassFormatException {
  final java.lang.Exception val$e;

  final org.hibernate.jpa.internal.enhance.EnhancingClassTransformerImpl this$0;

  org.hibernate.jpa.internal.enhance.EnhancingClassTransformerImpl$1(org.hibernate.jpa.internal.enhance.EnhancingClassTransformerImpl, java.lang.String, java.lang.Exception);
    Code:
       0: aload_0
       1: aload_1
       2: putfield      #1                  // Field this$0:Lorg/hibernate/jpa/internal/enhance/EnhancingClassTransformerImpl;
       5: aload_0
       6: aload_3
       7: putfield      #2                  // Field val$e:Ljava/lang/Exception;
      10: aload_0
      11: aload_2
      12: invokespecial #3                  // Method java/lang/instrument/IllegalClassFormatException."<init>":(Ljava/lang/String;)V
      15: return

  public synchronized java.lang.Throwable getCause();
    Code:
       0: aload_0
       1: getfield      #2                  // Field val$e:Ljava/lang/Exception;
       4: areturn
}
