Compiled from "LocalesResponse.java"
public abstract class org.graylog2.rest.models.system.responses.LocalesResponse$LocaleDescription {
  public org.graylog2.rest.models.system.responses.LocalesResponse$LocaleDescription();
    Code:
       0: aload_0
       1: invokespecial #1                  // Method java/lang/Object."<init>":()V
       4: return

  public abstract java.lang.String languageTag();

  public abstract java.lang.String displayName();

  public static org.graylog2.rest.models.system.responses.LocalesResponse$LocaleDescription create(java.util.Locale);
    Code:
       0: aload_0
       1: invokevirtual #2                  // Method java/util/Locale.toLanguageTag:()Ljava/lang/String;
       4: aload_0
       5: getstatic     #3                  // Field java/util/Locale.ENGLISH:Ljava/util/Locale;
       8: invokevirtual #4                  // Method java/util/Locale.getDisplayName:(Ljava/util/Locale;)Ljava/lang/String;
      11: invokestatic  #5                  // Method create:(Ljava/lang/String;Ljava/lang/String;)Lorg/graylog2/rest/models/system/responses/LocalesResponse$LocaleDescription;
      14: areturn

  private static org.graylog2.rest.models.system.responses.LocalesResponse$LocaleDescription create(java.lang.String, java.lang.String);
    Code:
       0: new           #6                  // class org/graylog2/rest/models/system/responses/AutoValue_LocalesResponse_LocaleDescription
       3: dup
       4: aload_0
       5: aload_1
       6: invokespecial #7                  // Method org/graylog2/rest/models/system/responses/AutoValue_LocalesResponse_LocaleDescription."<init>":(Ljava/lang/String;Ljava/lang/String;)V
       9: areturn
}
