Compiled from "TimeBasedRotationStrategyResponse.java"
public abstract class org.graylog2.rest.models.system.responses.TimeBasedRotationStrategyResponse implements org.graylog2.rest.models.system.responses.DeflectorConfigResponse {
  public org.graylog2.rest.models.system.responses.TimeBasedRotationStrategyResponse();
    Code:
       0: aload_0
       1: invokespecial #1                  // Method java/lang/Object."<init>":()V
       4: return

  public abstract org.joda.time.Period maxTimePerIndex();

  public static org.graylog2.rest.models.system.responses.TimeBasedRotationStrategyResponse create(java.lang.String, int, org.joda.time.Period);
    Code:
       0: new           #2                  // class org/graylog2/rest/models/system/responses/AutoValue_TimeBasedRotationStrategyResponse
       3: dup
       4: aload_0
       5: iload_1
       6: aload_2
       7: invokespecial #3                  // Method org/graylog2/rest/models/system/responses/AutoValue_TimeBasedRotationStrategyResponse."<init>":(Ljava/lang/String;ILorg/joda/time/Period;)V
      10: areturn

  public static org.graylog2.rest.models.system.responses.TimeBasedRotationStrategyResponse create(int, org.joda.time.Period);
    Code:
       0: ldc           #4                  // class org/graylog2/rest/models/system/responses/TimeBasedRotationStrategyResponse
       2: invokevirtual #5                  // Method java/lang/Class.getCanonicalName:()Ljava/lang/String;
       5: iload_0
       6: aload_1
       7: invokestatic  #6                  // Method create:(Ljava/lang/String;ILorg/joda/time/Period;)Lorg/graylog2/rest/models/system/responses/TimeBasedRotationStrategyResponse;
      10: areturn
}
