Compiled from "FormBodyPart.java"
public class org.apache.hc.client5.http.entity.mime.FormBodyPart extends org.apache.hc.client5.http.entity.mime.MultipartPart {
  private final java.lang.String name;

  org.apache.hc.client5.http.entity.mime.FormBodyPart(java.lang.String, org.apache.hc.client5.http.entity.mime.ContentBody, org.apache.hc.client5.http.entity.mime.Header);
    Code:
       0: aload_0
       1: aload_2
       2: aload_3
       3: invokespecial #1                  // Method org/apache/hc/client5/http/entity/mime/MultipartPart."<init>":(Lorg/apache/hc/client5/http/entity/mime/ContentBody;Lorg/apache/hc/client5/http/entity/mime/Header;)V
       6: aload_1
       7: ldc           #2                  // String Name
       9: invokestatic  #3                  // Method org/apache/hc/core5/util/Args.notNull:(Ljava/lang/Object;Ljava/lang/String;)Ljava/lang/Object;
      12: pop
      13: aload_2
      14: ldc           #4                  // String Body
      16: invokestatic  #3                  // Method org/apache/hc/core5/util/Args.notNull:(Ljava/lang/Object;Ljava/lang/String;)Ljava/lang/Object;
      19: pop
      20: aload_0
      21: aload_1
      22: putfield      #5                  // Field name:Ljava/lang/String;
      25: return

  public java.lang.String getName();
    Code:
       0: aload_0
       1: getfield      #5                  // Field name:Ljava/lang/String;
       4: areturn

  public void addField(java.lang.String, java.lang.String);
    Code:
       0: aload_1
       1: ldc           #6                  // String Field name
       3: invokestatic  #3                  // Method org/apache/hc/core5/util/Args.notNull:(Ljava/lang/Object;Ljava/lang/String;)Ljava/lang/Object;
       6: pop
       7: aload_0
       8: aload_1
       9: aload_2
      10: invokespecial #7                  // Method org/apache/hc/client5/http/entity/mime/MultipartPart.addField:(Ljava/lang/String;Ljava/lang/String;)V
      13: return
}
