Compiled from "ServiceLoaderImpl.java"
class org.glassfish.hk2.osgiresourcelocator.ServiceLoaderImpl$BundleTracker implements org.osgi.framework.BundleListener {
  final org.glassfish.hk2.osgiresourcelocator.ServiceLoaderImpl this$0;

  private org.glassfish.hk2.osgiresourcelocator.ServiceLoaderImpl$BundleTracker(org.glassfish.hk2.osgiresourcelocator.ServiceLoaderImpl);
    Code:
       0: aload_0
       1: aload_1
       2: putfield      #2                  // Field this$0:Lorg/glassfish/hk2/osgiresourcelocator/ServiceLoaderImpl;
       5: aload_0
       6: invokespecial #3                  // Method java/lang/Object."<init>":()V
       9: return

  public void bundleChanged(org.osgi.framework.BundleEvent);
    Code:
       0: aload_1
       1: invokevirtual #4                  // Method org/osgi/framework/BundleEvent.getBundle:()Lorg/osgi/framework/Bundle;
       4: astore_2
       5: aload_1
       6: invokevirtual #5                  // Method org/osgi/framework/BundleEvent.getType:()I
       9: lookupswitch  { // 3
                     1: 44
                     8: 66
                    16: 55
               default: 82
          }
      44: aload_0
      45: getfield      #2                  // Field this$0:Lorg/glassfish/hk2/osgiresourcelocator/ServiceLoaderImpl;
      48: aload_2
      49: invokestatic  #6                  // Method org/glassfish/hk2/osgiresourcelocator/ServiceLoaderImpl.access$300:(Lorg/glassfish/hk2/osgiresourcelocator/ServiceLoaderImpl;Lorg/osgi/framework/Bundle;)V
      52: goto          82
      55: aload_0
      56: getfield      #2                  // Field this$0:Lorg/glassfish/hk2/osgiresourcelocator/ServiceLoaderImpl;
      59: aload_2
      60: invokestatic  #7                  // Method org/glassfish/hk2/osgiresourcelocator/ServiceLoaderImpl.access$400:(Lorg/glassfish/hk2/osgiresourcelocator/ServiceLoaderImpl;Lorg/osgi/framework/Bundle;)V
      63: goto          82
      66: aload_0
      67: getfield      #2                  // Field this$0:Lorg/glassfish/hk2/osgiresourcelocator/ServiceLoaderImpl;
      70: aload_2
      71: invokestatic  #7                  // Method org/glassfish/hk2/osgiresourcelocator/ServiceLoaderImpl.access$400:(Lorg/glassfish/hk2/osgiresourcelocator/ServiceLoaderImpl;Lorg/osgi/framework/Bundle;)V
      74: aload_0
      75: getfield      #2                  // Field this$0:Lorg/glassfish/hk2/osgiresourcelocator/ServiceLoaderImpl;
      78: aload_2
      79: invokestatic  #6                  // Method org/glassfish/hk2/osgiresourcelocator/ServiceLoaderImpl.access$300:(Lorg/glassfish/hk2/osgiresourcelocator/ServiceLoaderImpl;Lorg/osgi/framework/Bundle;)V
      82: return

  org.glassfish.hk2.osgiresourcelocator.ServiceLoaderImpl$BundleTracker(org.glassfish.hk2.osgiresourcelocator.ServiceLoaderImpl, org.glassfish.hk2.osgiresourcelocator.ServiceLoaderImpl$1);
    Code:
       0: aload_0
       1: aload_1
       2: invokespecial #1                  // Method "<init>":(Lorg/glassfish/hk2/osgiresourcelocator/ServiceLoaderImpl;)V
       5: return
}
