Compiled from "StandardServletEnvironment.java"
public class org.springframework.web.context.support.StandardServletEnvironment extends org.springframework.core.env.StandardEnvironment implements org.springframework.web.context.ConfigurableWebEnvironment {
  public static final java.lang.String SERVLET_CONTEXT_PROPERTY_SOURCE_NAME;

  public static final java.lang.String SERVLET_CONFIG_PROPERTY_SOURCE_NAME;

  public static final java.lang.String JNDI_PROPERTY_SOURCE_NAME;

  public org.springframework.web.context.support.StandardServletEnvironment();
    Code:
       0: aload_0
       1: invokespecial #1                  // Method org/springframework/core/env/StandardEnvironment."<init>":()V
       4: return

  protected void customizePropertySources(org.springframework.core.env.MutablePropertySources);
    Code:
       0: aload_1
       1: new           #2                  // class org/springframework/core/env/PropertySource$StubPropertySource
       4: dup
       5: ldc           #4                  // String servletConfigInitParams
       7: invokespecial #5                  // Method org/springframework/core/env/PropertySource$StubPropertySource."<init>":(Ljava/lang/String;)V
      10: invokevirtual #6                  // Method org/springframework/core/env/MutablePropertySources.addLast:(Lorg/springframework/core/env/PropertySource;)V
      13: aload_1
      14: new           #2                  // class org/springframework/core/env/PropertySource$StubPropertySource
      17: dup
      18: ldc           #7                  // String servletContextInitParams
      20: invokespecial #5                  // Method org/springframework/core/env/PropertySource$StubPropertySource."<init>":(Ljava/lang/String;)V
      23: invokevirtual #6                  // Method org/springframework/core/env/MutablePropertySources.addLast:(Lorg/springframework/core/env/PropertySource;)V
      26: invokestatic  #8                  // Method org/springframework/jndi/JndiLocatorDelegate.isDefaultJndiEnvironmentAvailable:()Z
      29: ifeq          45
      32: aload_1
      33: new           #9                  // class org/springframework/jndi/JndiPropertySource
      36: dup
      37: ldc           #10                 // String jndiProperties
      39: invokespecial #11                 // Method org/springframework/jndi/JndiPropertySource."<init>":(Ljava/lang/String;)V
      42: invokevirtual #6                  // Method org/springframework/core/env/MutablePropertySources.addLast:(Lorg/springframework/core/env/PropertySource;)V
      45: aload_0
      46: aload_1
      47: invokespecial #12                 // Method org/springframework/core/env/StandardEnvironment.customizePropertySources:(Lorg/springframework/core/env/MutablePropertySources;)V
      50: return

  public void initPropertySources(javax.servlet.ServletContext, javax.servlet.ServletConfig);
    Code:
       0: aload_0
       1: invokevirtual #13                 // Method getPropertySources:()Lorg/springframework/core/env/MutablePropertySources;
       4: aload_1
       5: aload_2
       6: invokestatic  #14                 // Method org/springframework/web/context/support/WebApplicationContextUtils.initServletPropertySources:(Lorg/springframework/core/env/MutablePropertySources;Ljavax/servlet/ServletContext;Ljavax/servlet/ServletConfig;)V
       9: return
}
