Compiled from "Verifier.java"
class org.codehaus.groovy.classgen.Verifier$10$1 extends org.codehaus.groovy.ast.CodeVisitorSupport {
  final org.codehaus.groovy.ast.stmt.BlockStatement val$code;

  final java.util.List val$newMethodNodeParameters;

  final org.codehaus.groovy.classgen.Verifier$10 this$1;

  org.codehaus.groovy.classgen.Verifier$10$1(org.codehaus.groovy.classgen.Verifier$10, org.codehaus.groovy.ast.stmt.BlockStatement, java.util.List);
    Code:
       0: aload_0
       1: aload_1
       2: putfield      #20                 // Field this$1:Lorg/codehaus/groovy/classgen/Verifier$10;
       5: aload_0
       6: aload_2
       7: putfield      #22                 // Field val$code:Lorg/codehaus/groovy/ast/stmt/BlockStatement;
      10: aload_0
      11: aload_3
      12: putfield      #24                 // Field val$newMethodNodeParameters:Ljava/util/List;
      15: aload_0
      16: invokespecial #27                 // Method org/codehaus/groovy/ast/CodeVisitorSupport."<init>":()V
      19: return

  public void visitVariableExpression(org.codehaus.groovy.ast.expr.VariableExpression);
    Code:
       0: aload_1
       1: invokevirtual #37                 // Method org/codehaus/groovy/ast/expr/VariableExpression.getAccessedVariable:()Lorg/codehaus/groovy/ast/Variable;
       4: astore_2
       5: aload_2
       6: instanceof    #39                 // class org/codehaus/groovy/ast/Parameter
       9: ifne          13
      12: return
      13: aload_2
      14: checkcast     #39                 // class org/codehaus/groovy/ast/Parameter
      17: astore_3
      18: aload_3
      19: invokevirtual #45                 // Method org/codehaus/groovy/ast/Parameter.hasInitialExpression:()Z
      22: ifeq          131
      25: aload_0
      26: getfield      #22                 // Field val$code:Lorg/codehaus/groovy/ast/stmt/BlockStatement;
      29: invokevirtual #51                 // Method org/codehaus/groovy/ast/stmt/BlockStatement.getVariableScope:()Lorg/codehaus/groovy/ast/VariableScope;
      32: aload_3
      33: invokevirtual #55                 // Method org/codehaus/groovy/ast/Parameter.getName:()Ljava/lang/String;
      36: invokevirtual #61                 // Method org/codehaus/groovy/ast/VariableScope.getDeclaredVariable:(Ljava/lang/String;)Lorg/codehaus/groovy/ast/Variable;
      39: ifnonnull     131
      42: aload_0
      43: getfield      #24                 // Field val$newMethodNodeParameters:Ljava/util/List;
      46: aload_3
      47: invokeinterface #67,  2           // InterfaceMethod java/util/List.contains:(Ljava/lang/Object;)Z
      52: ifne          131
      55: new           #33                 // class org/codehaus/groovy/ast/expr/VariableExpression
      58: dup
      59: aload_3
      60: invokevirtual #55                 // Method org/codehaus/groovy/ast/Parameter.getName:()Ljava/lang/String;
      63: invokestatic  #73                 // Method org/codehaus/groovy/ast/ClassHelper.makeReference:()Lorg/codehaus/groovy/ast/ClassNode;
      66: invokespecial #76                 // Method org/codehaus/groovy/ast/expr/VariableExpression."<init>":(Ljava/lang/String;Lorg/codehaus/groovy/ast/ClassNode;)V
      69: astore        4
      71: new           #78                 // class org/codehaus/groovy/ast/expr/DeclarationExpression
      74: dup
      75: aload         4
      77: bipush        100
      79: iconst_m1
      80: iconst_m1
      81: invokestatic  #84                 // Method org/codehaus/groovy/syntax/Token.newSymbol:(III)Lorg/codehaus/groovy/syntax/Token;
      84: new           #86                 // class org/codehaus/groovy/ast/expr/ConstructorCallExpression
      87: dup
      88: invokestatic  #73                 // Method org/codehaus/groovy/ast/ClassHelper.makeReference:()Lorg/codehaus/groovy/ast/ClassNode;
      91: aload_3
      92: invokevirtual #90                 // Method org/codehaus/groovy/ast/Parameter.getInitialExpression:()Lorg/codehaus/groovy/ast/expr/Expression;
      95: invokespecial #93                 // Method org/codehaus/groovy/ast/expr/ConstructorCallExpression."<init>":(Lorg/codehaus/groovy/ast/ClassNode;Lorg/codehaus/groovy/ast/expr/Expression;)V
      98: invokespecial #96                 // Method org/codehaus/groovy/ast/expr/DeclarationExpression."<init>":(Lorg/codehaus/groovy/ast/expr/VariableExpression;Lorg/codehaus/groovy/syntax/Token;Lorg/codehaus/groovy/ast/expr/Expression;)V
     101: astore        5
     103: aload_0
     104: getfield      #22                 // Field val$code:Lorg/codehaus/groovy/ast/stmt/BlockStatement;
     107: new           #98                 // class org/codehaus/groovy/ast/stmt/ExpressionStatement
     110: dup
     111: aload         5
     113: invokespecial #101                // Method org/codehaus/groovy/ast/stmt/ExpressionStatement."<init>":(Lorg/codehaus/groovy/ast/expr/Expression;)V
     116: invokevirtual #105                // Method org/codehaus/groovy/ast/stmt/BlockStatement.addStatement:(Lorg/codehaus/groovy/ast/stmt/Statement;)V
     119: aload_0
     120: getfield      #22                 // Field val$code:Lorg/codehaus/groovy/ast/stmt/BlockStatement;
     123: invokevirtual #51                 // Method org/codehaus/groovy/ast/stmt/BlockStatement.getVariableScope:()Lorg/codehaus/groovy/ast/VariableScope;
     126: aload         4
     128: invokevirtual #109                // Method org/codehaus/groovy/ast/VariableScope.putDeclaredVariable:(Lorg/codehaus/groovy/ast/Variable;)V
     131: return
}
