Compiled from "DefaultMediaPackageV2AsyncClientBuilder.java"
final class software.amazon.awssdk.services.mediapackagev2.DefaultMediaPackageV2AsyncClientBuilder extends software.amazon.awssdk.services.mediapackagev2.DefaultMediaPackageV2BaseClientBuilder<software.amazon.awssdk.services.mediapackagev2.MediaPackageV2AsyncClientBuilder, software.amazon.awssdk.services.mediapackagev2.MediaPackageV2AsyncClient> implements software.amazon.awssdk.services.mediapackagev2.MediaPackageV2AsyncClientBuilder {
  software.amazon.awssdk.services.mediapackagev2.DefaultMediaPackageV2AsyncClientBuilder();
    Code:
       0: aload_0
       1: invokespecial #1                  // Method software/amazon/awssdk/services/mediapackagev2/DefaultMediaPackageV2BaseClientBuilder."<init>":()V
       4: return

  public software.amazon.awssdk.services.mediapackagev2.DefaultMediaPackageV2AsyncClientBuilder endpointProvider(software.amazon.awssdk.services.mediapackagev2.endpoints.MediaPackageV2EndpointProvider);
    Code:
       0: aload_0
       1: getfield      #2                  // Field clientConfiguration:Lsoftware/amazon/awssdk/core/client/config/SdkClientConfiguration$Builder;
       4: getstatic     #3                  // Field software/amazon/awssdk/core/client/config/SdkClientOption.ENDPOINT_PROVIDER:Lsoftware/amazon/awssdk/core/client/config/SdkClientOption;
       7: aload_1
       8: invokevirtual #4                  // Method software/amazon/awssdk/core/client/config/SdkClientConfiguration$Builder.option:(Lsoftware/amazon/awssdk/core/client/config/ClientOption;Ljava/lang/Object;)Lsoftware/amazon/awssdk/core/client/config/SdkClientConfiguration$Builder;
      11: pop
      12: aload_0
      13: areturn

  protected final software.amazon.awssdk.services.mediapackagev2.MediaPackageV2AsyncClient buildClient();
    Code:
       0: aload_0
       1: invokespecial #5                  // Method software/amazon/awssdk/services/mediapackagev2/DefaultMediaPackageV2BaseClientBuilder.asyncClientConfiguration:()Lsoftware/amazon/awssdk/core/client/config/SdkClientConfiguration;
       4: astore_1
       5: aload_0
       6: pop
       7: aload_1
       8: invokestatic  #6                  // Method validateClientOptions:(Lsoftware/amazon/awssdk/core/client/config/SdkClientConfiguration;)V
      11: aload_0
      12: aload_1
      13: invokespecial #7                  // Method initializeServiceClientConfig:(Lsoftware/amazon/awssdk/core/client/config/SdkClientConfiguration;)Lsoftware/amazon/awssdk/services/mediapackagev2/MediaPackageV2ServiceClientConfiguration;
      16: astore_2
      17: new           #8                  // class software/amazon/awssdk/services/mediapackagev2/DefaultMediaPackageV2AsyncClient
      20: dup
      21: aload_2
      22: aload_1
      23: invokespecial #9                  // Method software/amazon/awssdk/services/mediapackagev2/DefaultMediaPackageV2AsyncClient."<init>":(Lsoftware/amazon/awssdk/services/mediapackagev2/MediaPackageV2ServiceClientConfiguration;Lsoftware/amazon/awssdk/core/client/config/SdkClientConfiguration;)V
      26: astore_3
      27: aload_3
      28: areturn

  private software.amazon.awssdk.services.mediapackagev2.MediaPackageV2ServiceClientConfiguration initializeServiceClientConfig(software.amazon.awssdk.core.client.config.SdkClientConfiguration);
    Code:
       0: aconst_null
       1: astore_2
       2: aload_1
       3: getstatic     #3                  // Field software/amazon/awssdk/core/client/config/SdkClientOption.ENDPOINT_PROVIDER:Lsoftware/amazon/awssdk/core/client/config/SdkClientOption;
       6: invokevirtual #10                 // Method software/amazon/awssdk/core/client/config/SdkClientConfiguration.option:(Lsoftware/amazon/awssdk/core/client/config/ClientOption;)Ljava/lang/Object;
       9: checkcast     #11                 // class software/amazon/awssdk/endpoints/EndpointProvider
      12: astore_3
      13: aload_1
      14: getstatic     #12                 // Field software/amazon/awssdk/core/client/config/SdkClientOption.ENDPOINT_OVERRIDDEN:Lsoftware/amazon/awssdk/core/client/config/SdkClientOption;
      17: invokevirtual #10                 // Method software/amazon/awssdk/core/client/config/SdkClientConfiguration.option:(Lsoftware/amazon/awssdk/core/client/config/ClientOption;)Ljava/lang/Object;
      20: ifnull        50
      23: getstatic     #13                 // Field java/lang/Boolean.TRUE:Ljava/lang/Boolean;
      26: aload_1
      27: getstatic     #12                 // Field software/amazon/awssdk/core/client/config/SdkClientOption.ENDPOINT_OVERRIDDEN:Lsoftware/amazon/awssdk/core/client/config/SdkClientOption;
      30: invokevirtual #10                 // Method software/amazon/awssdk/core/client/config/SdkClientConfiguration.option:(Lsoftware/amazon/awssdk/core/client/config/ClientOption;)Ljava/lang/Object;
      33: invokevirtual #14                 // Method java/lang/Boolean.equals:(Ljava/lang/Object;)Z
      36: ifeq          50
      39: aload_1
      40: getstatic     #15                 // Field software/amazon/awssdk/core/client/config/SdkClientOption.ENDPOINT:Lsoftware/amazon/awssdk/core/client/config/SdkClientOption;
      43: invokevirtual #10                 // Method software/amazon/awssdk/core/client/config/SdkClientConfiguration.option:(Lsoftware/amazon/awssdk/core/client/config/ClientOption;)Ljava/lang/Object;
      46: checkcast     #16                 // class java/net/URI
      49: astore_2
      50: invokestatic  #17                 // Method software/amazon/awssdk/services/mediapackagev2/MediaPackageV2ServiceClientConfiguration.builder:()Lsoftware/amazon/awssdk/services/mediapackagev2/MediaPackageV2ServiceClientConfiguration$Builder;
      53: aload_0
      54: invokevirtual #18                 // Method overrideConfiguration:()Lsoftware/amazon/awssdk/core/client/config/ClientOverrideConfiguration;
      57: invokeinterface #19,  2           // InterfaceMethod software/amazon/awssdk/services/mediapackagev2/MediaPackageV2ServiceClientConfiguration$Builder.overrideConfiguration:(Lsoftware/amazon/awssdk/core/client/config/ClientOverrideConfiguration;)Lsoftware/amazon/awssdk/services/mediapackagev2/MediaPackageV2ServiceClientConfiguration$Builder;
      62: aload_1
      63: getstatic     #20                 // Field software/amazon/awssdk/awscore/client/config/AwsClientOption.AWS_REGION:Lsoftware/amazon/awssdk/awscore/client/config/AwsClientOption;
      66: invokevirtual #10                 // Method software/amazon/awssdk/core/client/config/SdkClientConfiguration.option:(Lsoftware/amazon/awssdk/core/client/config/ClientOption;)Ljava/lang/Object;
      69: checkcast     #21                 // class software/amazon/awssdk/regions/Region
      72: invokeinterface #22,  2           // InterfaceMethod software/amazon/awssdk/services/mediapackagev2/MediaPackageV2ServiceClientConfiguration$Builder.region:(Lsoftware/amazon/awssdk/regions/Region;)Lsoftware/amazon/awssdk/services/mediapackagev2/MediaPackageV2ServiceClientConfiguration$Builder;
      77: aload_2
      78: invokeinterface #23,  2           // InterfaceMethod software/amazon/awssdk/services/mediapackagev2/MediaPackageV2ServiceClientConfiguration$Builder.endpointOverride:(Ljava/net/URI;)Lsoftware/amazon/awssdk/services/mediapackagev2/MediaPackageV2ServiceClientConfiguration$Builder;
      83: aload_3
      84: invokeinterface #24,  2           // InterfaceMethod software/amazon/awssdk/services/mediapackagev2/MediaPackageV2ServiceClientConfiguration$Builder.endpointProvider:(Lsoftware/amazon/awssdk/endpoints/EndpointProvider;)Lsoftware/amazon/awssdk/services/mediapackagev2/MediaPackageV2ServiceClientConfiguration$Builder;
      89: invokeinterface #25,  1           // InterfaceMethod software/amazon/awssdk/services/mediapackagev2/MediaPackageV2ServiceClientConfiguration$Builder.build:()Lsoftware/amazon/awssdk/services/mediapackagev2/MediaPackageV2ServiceClientConfiguration;
      94: areturn

  protected java.lang.Object buildClient();
    Code:
       0: aload_0
       1: invokevirtual #26                 // Method buildClient:()Lsoftware/amazon/awssdk/services/mediapackagev2/MediaPackageV2AsyncClient;
       4: areturn

  public software.amazon.awssdk.core.client.builder.SdkAsyncClientBuilder httpClientBuilder(software.amazon.awssdk.http.async.SdkAsyncHttpClient$Builder);
    Code:
       0: aload_0
       1: aload_1
       2: invokespecial #27                 // Method software/amazon/awssdk/services/mediapackagev2/DefaultMediaPackageV2BaseClientBuilder.httpClientBuilder:(Lsoftware/amazon/awssdk/http/async/SdkAsyncHttpClient$Builder;)Lsoftware/amazon/awssdk/core/client/builder/SdkClientBuilder;
       5: checkcast     #28                 // class software/amazon/awssdk/core/client/builder/SdkAsyncClientBuilder
       8: areturn

  public software.amazon.awssdk.core.client.builder.SdkAsyncClientBuilder httpClient(software.amazon.awssdk.http.async.SdkAsyncHttpClient);
    Code:
       0: aload_0
       1: aload_1
       2: invokespecial #29                 // Method software/amazon/awssdk/services/mediapackagev2/DefaultMediaPackageV2BaseClientBuilder.httpClient:(Lsoftware/amazon/awssdk/http/async/SdkAsyncHttpClient;)Lsoftware/amazon/awssdk/core/client/builder/SdkClientBuilder;
       5: checkcast     #28                 // class software/amazon/awssdk/core/client/builder/SdkAsyncClientBuilder
       8: areturn

  public software.amazon.awssdk.core.client.builder.SdkAsyncClientBuilder asyncConfiguration(software.amazon.awssdk.core.client.config.ClientAsyncConfiguration);
    Code:
       0: aload_0
       1: aload_1
       2: invokespecial #30                 // Method software/amazon/awssdk/services/mediapackagev2/DefaultMediaPackageV2BaseClientBuilder.asyncConfiguration:(Lsoftware/amazon/awssdk/core/client/config/ClientAsyncConfiguration;)Lsoftware/amazon/awssdk/core/client/builder/SdkClientBuilder;
       5: checkcast     #28                 // class software/amazon/awssdk/core/client/builder/SdkAsyncClientBuilder
       8: areturn

  public software.amazon.awssdk.services.mediapackagev2.MediaPackageV2BaseClientBuilder endpointProvider(software.amazon.awssdk.services.mediapackagev2.endpoints.MediaPackageV2EndpointProvider);
    Code:
       0: aload_0
       1: aload_1
       2: invokevirtual #31                 // Method endpointProvider:(Lsoftware/amazon/awssdk/services/mediapackagev2/endpoints/MediaPackageV2EndpointProvider;)Lsoftware/amazon/awssdk/services/mediapackagev2/DefaultMediaPackageV2AsyncClientBuilder;
       5: areturn
}
