Compiled from "AbstractAmazonCloudFront.java"
public class com.amazonaws.services.cloudfront.AbstractAmazonCloudFront implements com.amazonaws.services.cloudfront.AmazonCloudFront {
  protected com.amazonaws.services.cloudfront.AbstractAmazonCloudFront();
    Code:
       0: aload_0
       1: invokespecial #1                  // Method java/lang/Object."<init>":()V
       4: return

  public void setEndpoint(java.lang.String);
    Code:
       0: new           #2                  // class java/lang/UnsupportedOperationException
       3: dup
       4: invokespecial #3                  // Method java/lang/UnsupportedOperationException."<init>":()V
       7: athrow

  public void setRegion(com.amazonaws.regions.Region);
    Code:
       0: new           #2                  // class java/lang/UnsupportedOperationException
       3: dup
       4: invokespecial #3                  // Method java/lang/UnsupportedOperationException."<init>":()V
       7: athrow

  public com.amazonaws.services.cloudfront.model.CreateCloudFrontOriginAccessIdentityResult createCloudFrontOriginAccessIdentity(com.amazonaws.services.cloudfront.model.CreateCloudFrontOriginAccessIdentityRequest);
    Code:
       0: new           #2                  // class java/lang/UnsupportedOperationException
       3: dup
       4: invokespecial #3                  // Method java/lang/UnsupportedOperationException."<init>":()V
       7: athrow

  public com.amazonaws.services.cloudfront.model.CreateDistributionResult createDistribution(com.amazonaws.services.cloudfront.model.CreateDistributionRequest);
    Code:
       0: new           #2                  // class java/lang/UnsupportedOperationException
       3: dup
       4: invokespecial #3                  // Method java/lang/UnsupportedOperationException."<init>":()V
       7: athrow

  public com.amazonaws.services.cloudfront.model.CreateInvalidationResult createInvalidation(com.amazonaws.services.cloudfront.model.CreateInvalidationRequest);
    Code:
       0: new           #2                  // class java/lang/UnsupportedOperationException
       3: dup
       4: invokespecial #3                  // Method java/lang/UnsupportedOperationException."<init>":()V
       7: athrow

  public com.amazonaws.services.cloudfront.model.CreateStreamingDistributionResult createStreamingDistribution(com.amazonaws.services.cloudfront.model.CreateStreamingDistributionRequest);
    Code:
       0: new           #2                  // class java/lang/UnsupportedOperationException
       3: dup
       4: invokespecial #3                  // Method java/lang/UnsupportedOperationException."<init>":()V
       7: athrow

  public com.amazonaws.services.cloudfront.model.DeleteCloudFrontOriginAccessIdentityResult deleteCloudFrontOriginAccessIdentity(com.amazonaws.services.cloudfront.model.DeleteCloudFrontOriginAccessIdentityRequest);
    Code:
       0: new           #2                  // class java/lang/UnsupportedOperationException
       3: dup
       4: invokespecial #3                  // Method java/lang/UnsupportedOperationException."<init>":()V
       7: athrow

  public com.amazonaws.services.cloudfront.model.DeleteDistributionResult deleteDistribution(com.amazonaws.services.cloudfront.model.DeleteDistributionRequest);
    Code:
       0: new           #2                  // class java/lang/UnsupportedOperationException
       3: dup
       4: invokespecial #3                  // Method java/lang/UnsupportedOperationException."<init>":()V
       7: athrow

  public com.amazonaws.services.cloudfront.model.DeleteStreamingDistributionResult deleteStreamingDistribution(com.amazonaws.services.cloudfront.model.DeleteStreamingDistributionRequest);
    Code:
       0: new           #2                  // class java/lang/UnsupportedOperationException
       3: dup
       4: invokespecial #3                  // Method java/lang/UnsupportedOperationException."<init>":()V
       7: athrow

  public com.amazonaws.services.cloudfront.model.GetCloudFrontOriginAccessIdentityResult getCloudFrontOriginAccessIdentity(com.amazonaws.services.cloudfront.model.GetCloudFrontOriginAccessIdentityRequest);
    Code:
       0: new           #2                  // class java/lang/UnsupportedOperationException
       3: dup
       4: invokespecial #3                  // Method java/lang/UnsupportedOperationException."<init>":()V
       7: athrow

  public com.amazonaws.services.cloudfront.model.GetCloudFrontOriginAccessIdentityConfigResult getCloudFrontOriginAccessIdentityConfig(com.amazonaws.services.cloudfront.model.GetCloudFrontOriginAccessIdentityConfigRequest);
    Code:
       0: new           #2                  // class java/lang/UnsupportedOperationException
       3: dup
       4: invokespecial #3                  // Method java/lang/UnsupportedOperationException."<init>":()V
       7: athrow

  public com.amazonaws.services.cloudfront.model.GetDistributionResult getDistribution(com.amazonaws.services.cloudfront.model.GetDistributionRequest);
    Code:
       0: new           #2                  // class java/lang/UnsupportedOperationException
       3: dup
       4: invokespecial #3                  // Method java/lang/UnsupportedOperationException."<init>":()V
       7: athrow

  public com.amazonaws.services.cloudfront.model.GetDistributionConfigResult getDistributionConfig(com.amazonaws.services.cloudfront.model.GetDistributionConfigRequest);
    Code:
       0: new           #2                  // class java/lang/UnsupportedOperationException
       3: dup
       4: invokespecial #3                  // Method java/lang/UnsupportedOperationException."<init>":()V
       7: athrow

  public com.amazonaws.services.cloudfront.model.GetInvalidationResult getInvalidation(com.amazonaws.services.cloudfront.model.GetInvalidationRequest);
    Code:
       0: new           #2                  // class java/lang/UnsupportedOperationException
       3: dup
       4: invokespecial #3                  // Method java/lang/UnsupportedOperationException."<init>":()V
       7: athrow

  public com.amazonaws.services.cloudfront.model.GetStreamingDistributionResult getStreamingDistribution(com.amazonaws.services.cloudfront.model.GetStreamingDistributionRequest);
    Code:
       0: new           #2                  // class java/lang/UnsupportedOperationException
       3: dup
       4: invokespecial #3                  // Method java/lang/UnsupportedOperationException."<init>":()V
       7: athrow

  public com.amazonaws.services.cloudfront.model.GetStreamingDistributionConfigResult getStreamingDistributionConfig(com.amazonaws.services.cloudfront.model.GetStreamingDistributionConfigRequest);
    Code:
       0: new           #2                  // class java/lang/UnsupportedOperationException
       3: dup
       4: invokespecial #3                  // Method java/lang/UnsupportedOperationException."<init>":()V
       7: athrow

  public com.amazonaws.services.cloudfront.model.ListCloudFrontOriginAccessIdentitiesResult listCloudFrontOriginAccessIdentities(com.amazonaws.services.cloudfront.model.ListCloudFrontOriginAccessIdentitiesRequest);
    Code:
       0: new           #2                  // class java/lang/UnsupportedOperationException
       3: dup
       4: invokespecial #3                  // Method java/lang/UnsupportedOperationException."<init>":()V
       7: athrow

  public com.amazonaws.services.cloudfront.model.ListDistributionsResult listDistributions(com.amazonaws.services.cloudfront.model.ListDistributionsRequest);
    Code:
       0: new           #2                  // class java/lang/UnsupportedOperationException
       3: dup
       4: invokespecial #3                  // Method java/lang/UnsupportedOperationException."<init>":()V
       7: athrow

  public com.amazonaws.services.cloudfront.model.ListDistributionsByWebACLIdResult listDistributionsByWebACLId(com.amazonaws.services.cloudfront.model.ListDistributionsByWebACLIdRequest);
    Code:
       0: new           #2                  // class java/lang/UnsupportedOperationException
       3: dup
       4: invokespecial #3                  // Method java/lang/UnsupportedOperationException."<init>":()V
       7: athrow

  public com.amazonaws.services.cloudfront.model.ListInvalidationsResult listInvalidations(com.amazonaws.services.cloudfront.model.ListInvalidationsRequest);
    Code:
       0: new           #2                  // class java/lang/UnsupportedOperationException
       3: dup
       4: invokespecial #3                  // Method java/lang/UnsupportedOperationException."<init>":()V
       7: athrow

  public com.amazonaws.services.cloudfront.model.ListStreamingDistributionsResult listStreamingDistributions(com.amazonaws.services.cloudfront.model.ListStreamingDistributionsRequest);
    Code:
       0: new           #2                  // class java/lang/UnsupportedOperationException
       3: dup
       4: invokespecial #3                  // Method java/lang/UnsupportedOperationException."<init>":()V
       7: athrow

  public com.amazonaws.services.cloudfront.model.UpdateCloudFrontOriginAccessIdentityResult updateCloudFrontOriginAccessIdentity(com.amazonaws.services.cloudfront.model.UpdateCloudFrontOriginAccessIdentityRequest);
    Code:
       0: new           #2                  // class java/lang/UnsupportedOperationException
       3: dup
       4: invokespecial #3                  // Method java/lang/UnsupportedOperationException."<init>":()V
       7: athrow

  public com.amazonaws.services.cloudfront.model.UpdateDistributionResult updateDistribution(com.amazonaws.services.cloudfront.model.UpdateDistributionRequest);
    Code:
       0: new           #2                  // class java/lang/UnsupportedOperationException
       3: dup
       4: invokespecial #3                  // Method java/lang/UnsupportedOperationException."<init>":()V
       7: athrow

  public com.amazonaws.services.cloudfront.model.UpdateStreamingDistributionResult updateStreamingDistribution(com.amazonaws.services.cloudfront.model.UpdateStreamingDistributionRequest);
    Code:
       0: new           #2                  // class java/lang/UnsupportedOperationException
       3: dup
       4: invokespecial #3                  // Method java/lang/UnsupportedOperationException."<init>":()V
       7: athrow

  public void shutdown();
    Code:
       0: new           #2                  // class java/lang/UnsupportedOperationException
       3: dup
       4: invokespecial #3                  // Method java/lang/UnsupportedOperationException."<init>":()V
       7: athrow

  public com.amazonaws.ResponseMetadata getCachedResponseMetadata(com.amazonaws.AmazonWebServiceRequest);
    Code:
       0: new           #2                  // class java/lang/UnsupportedOperationException
       3: dup
       4: invokespecial #3                  // Method java/lang/UnsupportedOperationException."<init>":()V
       7: athrow
}
