Compiled from "WindowsHelpers.java"
final class jnr.posix.util.WindowsHelpers$InternalType extends java.lang.Enum<jnr.posix.util.WindowsHelpers$InternalType> {
  public static final jnr.posix.util.WindowsHelpers$InternalType SHELL;

  public static final jnr.posix.util.WindowsHelpers$InternalType COMMAND;

  public static final jnr.posix.util.WindowsHelpers$InternalType BOTH;

  private static final jnr.posix.util.WindowsHelpers$InternalType[] $VALUES;

  public static jnr.posix.util.WindowsHelpers$InternalType[] values();
    Code:
       0: getstatic     #1                  // Field $VALUES:[Ljnr/posix/util/WindowsHelpers$InternalType;
       3: invokevirtual #2                  // Method "[Ljnr/posix/util/WindowsHelpers$InternalType;".clone:()Ljava/lang/Object;
       6: checkcast     #3                  // class "[Ljnr/posix/util/WindowsHelpers$InternalType;"
       9: areturn

  public static jnr.posix.util.WindowsHelpers$InternalType valueOf(java.lang.String);
    Code:
       0: ldc           #4                  // class jnr/posix/util/WindowsHelpers$InternalType
       2: aload_0
       3: invokestatic  #5                  // Method java/lang/Enum.valueOf:(Ljava/lang/Class;Ljava/lang/String;)Ljava/lang/Enum;
       6: checkcast     #4                  // class jnr/posix/util/WindowsHelpers$InternalType
       9: areturn

  private jnr.posix.util.WindowsHelpers$InternalType();
    Code:
       0: aload_0
       1: aload_1
       2: iload_2
       3: invokespecial #6                  // Method java/lang/Enum."<init>":(Ljava/lang/String;I)V
       6: return

  static {};
    Code:
       0: new           #4                  // class jnr/posix/util/WindowsHelpers$InternalType
       3: dup
       4: ldc           #7                  // String SHELL
       6: iconst_0
       7: invokespecial #8                  // Method "<init>":(Ljava/lang/String;I)V
      10: putstatic     #9                  // Field SHELL:Ljnr/posix/util/WindowsHelpers$InternalType;
      13: new           #4                  // class jnr/posix/util/WindowsHelpers$InternalType
      16: dup
      17: ldc           #10                 // String COMMAND
      19: iconst_1
      20: invokespecial #8                  // Method "<init>":(Ljava/lang/String;I)V
      23: putstatic     #11                 // Field COMMAND:Ljnr/posix/util/WindowsHelpers$InternalType;
      26: new           #4                  // class jnr/posix/util/WindowsHelpers$InternalType
      29: dup
      30: ldc           #12                 // String BOTH
      32: iconst_2
      33: invokespecial #8                  // Method "<init>":(Ljava/lang/String;I)V
      36: putstatic     #13                 // Field BOTH:Ljnr/posix/util/WindowsHelpers$InternalType;
      39: iconst_3
      40: anewarray     #4                  // class jnr/posix/util/WindowsHelpers$InternalType
      43: dup
      44: iconst_0
      45: getstatic     #9                  // Field SHELL:Ljnr/posix/util/WindowsHelpers$InternalType;
      48: aastore
      49: dup
      50: iconst_1
      51: getstatic     #11                 // Field COMMAND:Ljnr/posix/util/WindowsHelpers$InternalType;
      54: aastore
      55: dup
      56: iconst_2
      57: getstatic     #13                 // Field BOTH:Ljnr/posix/util/WindowsHelpers$InternalType;
      60: aastore
      61: putstatic     #1                  // Field $VALUES:[Ljnr/posix/util/WindowsHelpers$InternalType;
      64: return
}
