Compiled from "AuralAttributeImpl.scala"
final class de.sciss.proc.impl.AuralAttributeImpl$Playing<T extends de.sciss.lucre.Txn<T>> {
  private final de.sciss.proc.TimeRef timeRef;

  private final long wallClock;

  private final de.sciss.proc.AuralAttribute$Target target;

  private final de.sciss.proc.AuralAttribute$Value value;

  public de.sciss.proc.impl.AuralAttributeImpl$Playing(de.sciss.proc.TimeRef, long, de.sciss.proc.AuralAttribute$Target<T>, de.sciss.proc.AuralAttribute$Value);
    Code:
       0: aload_0
       1: aload_1
       2: putfield      #30                 // Field timeRef:Lde/sciss/proc/TimeRef;
       5: aload_0
       6: lload_2
       7: putfield      #32                 // Field wallClock:J
      10: aload_0
      11: aload         4
      13: putfield      #34                 // Field target:Lde/sciss/proc/AuralAttribute$Target;
      16: aload_0
      17: aload         5
      19: putfield      #36                 // Field value:Lde/sciss/proc/AuralAttribute$Value;
      22: aload_0
      23: invokespecial #39                 // Method java/lang/Object."<init>":()V
      26: return

  public de.sciss.proc.TimeRef timeRef();
    Code:
       0: aload_0
       1: getfield      #30                 // Field timeRef:Lde/sciss/proc/TimeRef;
       4: areturn

  public long wallClock();
    Code:
       0: aload_0
       1: getfield      #32                 // Field wallClock:J
       4: lreturn

  public de.sciss.proc.AuralAttribute$Target<T> target();
    Code:
       0: aload_0
       1: getfield      #34                 // Field target:Lde/sciss/proc/AuralAttribute$Target;
       4: areturn

  public de.sciss.proc.AuralAttribute$Value value();
    Code:
       0: aload_0
       1: getfield      #36                 // Field value:Lde/sciss/proc/AuralAttribute$Value;
       4: areturn

  public de.sciss.proc.TimeRef shiftTo(long);
    Code:
       0: lload_1
       1: aload_0
       2: invokevirtual #51                 // Method wallClock:()J
       5: lsub
       6: lstore_3
       7: aload_0
       8: invokevirtual #53                 // Method timeRef:()Lde/sciss/proc/TimeRef;
      11: lload_3
      12: invokevirtual #58                 // Method de/sciss/proc/TimeRef.shift:(J)Lde/sciss/proc/TimeRef;
      15: areturn

  public de.sciss.proc.impl.AuralAttributeImpl$Playing<T> updateValue(de.sciss.proc.AuralAttribute$Value);
    Code:
       0: new           #2                  // class de/sciss/proc/impl/AuralAttributeImpl$Playing
       3: dup
       4: aload_0
       5: invokevirtual #53                 // Method timeRef:()Lde/sciss/proc/TimeRef;
       8: aload_0
       9: invokevirtual #51                 // Method wallClock:()J
      12: aload_0
      13: invokevirtual #65                 // Method target:()Lde/sciss/proc/AuralAttribute$Target;
      16: aload_1
      17: invokespecial #67                 // Method "<init>":(Lde/sciss/proc/TimeRef;JLde/sciss/proc/AuralAttribute$Target;Lde/sciss/proc/AuralAttribute$Value;)V
      20: areturn
}
