Compiled from "AuralNodeImpl.scala"
final class de.sciss.proc.impl.AuralNodeImpl$Impl<T extends de.sciss.lucre.synth.Txn<T>> implements de.sciss.proc.AuralNode$Builder<T> {
  private final de.sciss.proc.TimeRef timeRef;

  private final long wallClock;

  private final de.sciss.proc.impl.AuralNodeImpl$Tree tree;

  private scala.collection.immutable.List<de.sciss.synth.ControlSet> setMap;

  private final scala.concurrent.stm.Ref<scala.collection.immutable.List<de.sciss.lucre.synth.DynamicUser>> users;

  private final scala.concurrent.stm.Ref<scala.collection.immutable.List<de.sciss.lucre.synth.Resource>> resources;

  private final scala.concurrent.stm.Ref<scala.collection.immutable.List<de.sciss.lucre.Disposable<T>>> disposables;

  private final scala.concurrent.stm.Ref<scala.Option<de.sciss.proc.impl.AuralNodeImpl$AllGroups>> groupsRef;

  public de.sciss.proc.impl.AuralNodeImpl$Impl(de.sciss.proc.TimeRef, long, de.sciss.proc.impl.AuralNodeImpl$Tree, scala.collection.immutable.List<de.sciss.synth.ControlSet>, scala.collection.immutable.List<de.sciss.lucre.synth.DynamicUser>);
    Code:
       0: aload_0
       1: aload_1
       2: putfield      #47                 // Field timeRef:Lde/sciss/proc/TimeRef;
       5: aload_0
       6: lload_2
       7: putfield      #49                 // Field wallClock:J
      10: aload_0
      11: aload         4
      13: putfield      #51                 // Field tree:Lde/sciss/proc/impl/AuralNodeImpl$Tree;
      16: aload_0
      17: aload         5
      19: putfield      #53                 // Field setMap:Lscala/collection/immutable/List;
      22: aload_0
      23: invokespecial #56                 // Method java/lang/Object."<init>":()V
      26: aload_0
      27: getstatic     #62                 // Field scala/concurrent/stm/Ref$.MODULE$:Lscala/concurrent/stm/Ref$;
      30: aload         6
      32: invokevirtual #66                 // Method scala/concurrent/stm/Ref$.apply:(Ljava/lang/Object;)Lscala/concurrent/stm/Ref;
      35: putfield      #68                 // Field users:Lscala/concurrent/stm/Ref;
      38: aload_0
      39: getstatic     #62                 // Field scala/concurrent/stm/Ref$.MODULE$:Lscala/concurrent/stm/Ref$;
      42: getstatic     #73                 // Field scala/package$.MODULE$:Lscala/package$;
      45: invokevirtual #77                 // Method scala/package$.List:()Lscala/collection/immutable/List$;
      48: invokevirtual #83                 // Method scala/collection/immutable/List$.empty:()Lscala/collection/immutable/List;
      51: invokevirtual #66                 // Method scala/concurrent/stm/Ref$.apply:(Ljava/lang/Object;)Lscala/concurrent/stm/Ref;
      54: putfield      #85                 // Field resources:Lscala/concurrent/stm/Ref;
      57: aload_0
      58: getstatic     #62                 // Field scala/concurrent/stm/Ref$.MODULE$:Lscala/concurrent/stm/Ref$;
      61: getstatic     #73                 // Field scala/package$.MODULE$:Lscala/package$;
      64: invokevirtual #77                 // Method scala/package$.List:()Lscala/collection/immutable/List$;
      67: invokevirtual #83                 // Method scala/collection/immutable/List$.empty:()Lscala/collection/immutable/List;
      70: invokevirtual #66                 // Method scala/concurrent/stm/Ref$.apply:(Ljava/lang/Object;)Lscala/concurrent/stm/Ref;
      73: putfield      #87                 // Field disposables:Lscala/concurrent/stm/Ref;
      76: aload_0
      77: getstatic     #62                 // Field scala/concurrent/stm/Ref$.MODULE$:Lscala/concurrent/stm/Ref$;
      80: aload         4
      82: invokeinterface #91,  1           // InterfaceMethod de/sciss/proc/impl/AuralNodeImpl$Tree.main:()Lde/sciss/lucre/synth/Node;
      87: astore        7
      89: aload         7
      91: instanceof    #93                 // class de/sciss/lucre/synth/Group
      94: ifeq          145
      97: aload         7
      99: checkcast     #93                 // class de/sciss/lucre/synth/Group
     102: astore        8
     104: getstatic     #98                 // Field scala/Some$.MODULE$:Lscala/Some$;
     107: getstatic     #101                // Field de/sciss/proc/impl/AuralNodeImpl$AllGroups$.MODULE$:Lde/sciss/proc/impl/AuralNodeImpl$AllGroups$;
     110: aload         8
     112: getstatic     #101                // Field de/sciss/proc/impl/AuralNodeImpl$AllGroups$.MODULE$:Lde/sciss/proc/impl/AuralNodeImpl$AllGroups$;
     115: invokevirtual #105                // Method de/sciss/proc/impl/AuralNodeImpl$AllGroups$.$lessinit$greater$default$2:()Lscala/Option;
     118: getstatic     #101                // Field de/sciss/proc/impl/AuralNodeImpl$AllGroups$.MODULE$:Lde/sciss/proc/impl/AuralNodeImpl$AllGroups$;
     121: invokevirtual #108                // Method de/sciss/proc/impl/AuralNodeImpl$AllGroups$.$lessinit$greater$default$3:()Lscala/Option;
     124: getstatic     #101                // Field de/sciss/proc/impl/AuralNodeImpl$AllGroups$.MODULE$:Lde/sciss/proc/impl/AuralNodeImpl$AllGroups$;
     127: invokevirtual #111                // Method de/sciss/proc/impl/AuralNodeImpl$AllGroups$.$lessinit$greater$default$4:()Lscala/Option;
     130: getstatic     #101                // Field de/sciss/proc/impl/AuralNodeImpl$AllGroups$.MODULE$:Lde/sciss/proc/impl/AuralNodeImpl$AllGroups$;
     133: invokevirtual #114                // Method de/sciss/proc/impl/AuralNodeImpl$AllGroups$.$lessinit$greater$default$5:()Lscala/Option;
     136: invokevirtual #117                // Method de/sciss/proc/impl/AuralNodeImpl$AllGroups$.apply:(Lde/sciss/lucre/synth/Group;Lscala/Option;Lscala/Option;Lscala/Option;Lscala/Option;)Lde/sciss/proc/impl/AuralNodeImpl$AllGroups;
     139: invokevirtual #120                // Method scala/Some$.apply:(Ljava/lang/Object;)Lscala/Some;
     142: goto          151
     145: getstatic     #125                // Field scala/None$.MODULE$:Lscala/None$;
     148: goto          151
     151: invokevirtual #66                 // Method scala/concurrent/stm/Ref$.apply:(Ljava/lang/Object;)Lscala/concurrent/stm/Ref;
     154: putfield      #127                // Field groupsRef:Lscala/concurrent/stm/Ref;
     157: return

  public de.sciss.proc.TimeRef timeRef();
    Code:
       0: aload_0
       1: getfield      #47                 // Field timeRef:Lde/sciss/proc/TimeRef;
       4: areturn

  public java.lang.String toString();
    Code:
       0: new           #144                // class java/lang/StringBuilder
       3: dup
       4: ldc           #145                // int 11
       6: invokespecial #148                // Method java/lang/StringBuilder."<init>":(I)V
       9: ldc           #150                // String AuralProc(
      11: invokevirtual #154                // Method java/lang/StringBuilder.append:(Ljava/lang/String;)Ljava/lang/StringBuilder;
      14: aload_0
      15: getfield      #51                 // Field tree:Lde/sciss/proc/impl/AuralNodeImpl$Tree;
      18: invokeinterface #91,  1           // InterfaceMethod de/sciss/proc/impl/AuralNodeImpl$Tree.main:()Lde/sciss/lucre/synth/Node;
      23: invokevirtual #157                // Method java/lang/StringBuilder.append:(Ljava/lang/Object;)Ljava/lang/StringBuilder;
      26: ldc           #159                // String )
      28: invokevirtual #154                // Method java/lang/StringBuilder.append:(Ljava/lang/String;)Ljava/lang/StringBuilder;
      31: invokevirtual #161                // Method java/lang/StringBuilder.toString:()Ljava/lang/String;
      34: areturn

  public de.sciss.lucre.synth.Server server();
    Code:
       0: aload_0
       1: getfield      #51                 // Field tree:Lde/sciss/proc/impl/AuralNodeImpl$Tree;
       4: invokeinterface #91,  1           // InterfaceMethod de/sciss/proc/impl/AuralNodeImpl$Tree.main:()Lde/sciss/lucre/synth/Node;
       9: invokeinterface #165,  1          // InterfaceMethod de/sciss/lucre/synth/Node.server:()Lde/sciss/lucre/synth/Server;
      14: areturn

  public scala.Option<de.sciss.lucre.synth.Group> groupOption(de.sciss.lucre.synth.RT);
    Code:
       0: aload_0
       1: getfield      #127                // Field groupsRef:Lscala/concurrent/stm/Ref;
       4: getstatic     #174                // Field de/sciss/lucre/Txn$.MODULE$:Lde/sciss/lucre/Txn$;
       7: aload_1
       8: invokevirtual #178                // Method de/sciss/lucre/Txn$.peer:(Lde/sciss/lucre/TxnLike;)Lscala/concurrent/stm/InTxn;
      11: invokeinterface #183,  2          // InterfaceMethod scala/concurrent/stm/Ref.apply:(Ljava/lang/Object;)Ljava/lang/Object;
      16: checkcast     #139                // class scala/Option
      19: aload_0
      20: invokedynamic #202,  0            // InvokeDynamic #0:apply:(Lde/sciss/proc/impl/AuralNodeImpl$Impl;)Lscala/Function1;
      25: invokevirtual #206                // Method scala/Option.map:(Lscala/Function1;)Lscala/Option;
      28: areturn

  public de.sciss.lucre.synth.Node node(de.sciss.lucre.synth.RT);
    Code:
       0: aload_0
       1: aload_1
       2: invokevirtual #211                // Method groupOption:(Lde/sciss/lucre/synth/RT;)Lscala/Option;
       5: aload_0
       6: invokedynamic #221,  0            // InvokeDynamic #1:apply:(Lde/sciss/proc/impl/AuralNodeImpl$Impl;)Lscala/Function0;
      11: invokevirtual #225                // Method scala/Option.getOrElse:(Lscala/Function0;)Ljava/lang/Object;
      14: checkcast     #137                // class de/sciss/lucre/synth/Node
      17: areturn

  public de.sciss.lucre.synth.Synth synth();
    Code:
       0: aload_0
       1: getfield      #51                 // Field tree:Lde/sciss/proc/impl/AuralNodeImpl$Tree;
       4: invokeinterface #229,  1          // InterfaceMethod de/sciss/proc/impl/AuralNodeImpl$Tree.synth:()Lde/sciss/lucre/synth/Synth;
       9: areturn

  public void play(T);
    Code:
       0: aload_0
       1: invokevirtual #233                // Method server:()Lde/sciss/lucre/synth/Server;
       4: invokeinterface #239,  1          // InterfaceMethod de/sciss/lucre/synth/Server.defaultGroup:()Lde/sciss/lucre/synth/Group;
       9: astore_2
      10: getstatic     #244                // Field de/sciss/synth/addToHead$.MODULE$:Lde/sciss/synth/addToHead$;
      13: astore_3
      14: aload_0
      15: getfield      #53                 // Field setMap:Lscala/collection/immutable/List;
      18: invokevirtual #247                // Method scala/collection/immutable/List.reverse:()Lscala/collection/immutable/List;
      21: astore        4
      23: aload_0
      24: getfield      #85                 // Field resources:Lscala/concurrent/stm/Ref;
      27: getstatic     #174                // Field de/sciss/lucre/Txn$.MODULE$:Lde/sciss/lucre/Txn$;
      30: aload_1
      31: invokevirtual #178                // Method de/sciss/lucre/Txn$.peer:(Lde/sciss/lucre/TxnLike;)Lscala/concurrent/stm/InTxn;
      34: invokeinterface #183,  2          // InterfaceMethod scala/concurrent/stm/Ref.apply:(Ljava/lang/Object;)Ljava/lang/Object;
      39: checkcast     #135                // class scala/collection/immutable/List
      42: invokevirtual #247                // Method scala/collection/immutable/List.reverse:()Lscala/collection/immutable/List;
      45: astore        5
      47: aload_0
      48: getfield      #51                 // Field tree:Lde/sciss/proc/impl/AuralNodeImpl$Tree;
      51: aload_2
      52: aload         4
      54: aload_3
      55: aload         5
      57: aload_1
      58: invokeinterface #250,  6          // InterfaceMethod de/sciss/proc/impl/AuralNodeImpl$Tree.play:(Lde/sciss/lucre/synth/Node;Lscala/collection/immutable/Seq;Lde/sciss/synth/AddAction;Lscala/collection/immutable/List;Lde/sciss/lucre/synth/RT;)V
      63: aload_0
      64: getfield      #68                 // Field users:Lscala/concurrent/stm/Ref;
      67: getstatic     #174                // Field de/sciss/lucre/Txn$.MODULE$:Lde/sciss/lucre/Txn$;
      70: aload_1
      71: invokevirtual #178                // Method de/sciss/lucre/Txn$.peer:(Lde/sciss/lucre/TxnLike;)Lscala/concurrent/stm/InTxn;
      74: invokeinterface #183,  2          // InterfaceMethod scala/concurrent/stm/Ref.apply:(Ljava/lang/Object;)Ljava/lang/Object;
      79: checkcast     #135                // class scala/collection/immutable/List
      82: invokevirtual #247                // Method scala/collection/immutable/List.reverse:()Lscala/collection/immutable/List;
      85: aload_0
      86: aload_1
      87: invokedynamic #263,  0            // InvokeDynamic #2:applyVoid:(Lde/sciss/proc/impl/AuralNodeImpl$Impl;Lde/sciss/lucre/synth/Txn;)Lscala/runtime/function/JProcedure1;
      92: invokevirtual #267                // Method scala/collection/immutable/List.foreach:(Lscala/Function1;)V
      95: return

  public de.sciss.proc.TimeRef shiftTo(long);
    Code:
       0: lload_1
       1: aload_0
       2: getfield      #49                 // Field wallClock:J
       5: lsub
       6: lstore_3
       7: aload_0
       8: invokevirtual #274                // Method timeRef:()Lde/sciss/proc/TimeRef;
      11: lload_3
      12: invokevirtual #277                // Method de/sciss/proc/TimeRef.shift:(J)Lde/sciss/proc/TimeRef;
      15: areturn

  public de.sciss.lucre.synth.Group group(T);
    Code:
       0: aload_0
       1: aload_1
       2: invokevirtual #211                // Method groupOption:(Lde/sciss/lucre/synth/RT;)Lscala/Option;
       5: aload_0
       6: aload_1
       7: invokedynamic #289,  0            // InvokeDynamic #3:apply:(Lde/sciss/proc/impl/AuralNodeImpl$Impl;Lde/sciss/lucre/synth/Txn;)Lscala/Function0;
      12: invokevirtual #225                // Method scala/Option.getOrElse:(Lscala/Function0;)Ljava/lang/Object;
      15: checkcast     #93                 // class de/sciss/lucre/synth/Group
      18: areturn

  public void group_$eq(de.sciss.lucre.synth.Group, T);
    Code:
       0: aload_0
       1: getfield      #127                // Field groupsRef:Lscala/concurrent/stm/Ref;
       4: aload_0
       5: aload_1
       6: aload_2
       7: invokedynamic #303,  0            // InvokeDynamic #4:apply:(Lde/sciss/proc/impl/AuralNodeImpl$Impl;Lde/sciss/lucre/synth/Group;Lde/sciss/lucre/synth/Txn;)Lscala/Function1;
      12: getstatic     #174                // Field de/sciss/lucre/Txn$.MODULE$:Lde/sciss/lucre/Txn$;
      15: aload_2
      16: invokevirtual #178                // Method de/sciss/lucre/Txn$.peer:(Lde/sciss/lucre/TxnLike;)Lscala/concurrent/stm/InTxn;
      19: invokeinterface #307,  3          // InterfaceMethod scala/concurrent/stm/Ref.transform:(Lscala/Function1;Ljava/lang/Object;)V
      24: return

  private scala.Option<de.sciss.lucre.synth.Group> preGroupOption(T);
    Code:
       0: aload_0
       1: getfield      #127                // Field groupsRef:Lscala/concurrent/stm/Ref;
       4: aload_1
       5: invokeinterface #315,  1          // InterfaceMethod de/sciss/lucre/synth/Txn.peer:()Lscala/concurrent/stm/InTxn;
      10: invokeinterface #318,  2          // InterfaceMethod scala/concurrent/stm/Ref.get:(Ljava/lang/Object;)Ljava/lang/Object;
      15: checkcast     #139                // class scala/Option
      18: aload_0
      19: invokedynamic #325,  0            // InvokeDynamic #5:apply:(Lde/sciss/proc/impl/AuralNodeImpl$Impl;)Lscala/Function1;
      24: invokevirtual #328                // Method scala/Option.flatMap:(Lscala/Function1;)Lscala/Option;
      27: areturn

  public de.sciss.lucre.synth.Group preGroup(T);
    Code:
       0: aload_0
       1: aload_1
       2: invokespecial #331                // Method preGroupOption:(Lde/sciss/lucre/synth/Txn;)Lscala/Option;
       5: aload_0
       6: aload_1
       7: invokedynamic #336,  0            // InvokeDynamic #6:apply:(Lde/sciss/proc/impl/AuralNodeImpl$Impl;Lde/sciss/lucre/synth/Txn;)Lscala/Function0;
      12: invokevirtual #225                // Method scala/Option.getOrElse:(Lscala/Function0;)Ljava/lang/Object;
      15: checkcast     #93                 // class de/sciss/lucre/synth/Group
      18: areturn

  private de.sciss.lucre.synth.Node anchorNode(T);
    Code:
       0: aload_0
       1: getfield      #127                // Field groupsRef:Lscala/concurrent/stm/Ref;
       4: getstatic     #174                // Field de/sciss/lucre/Txn$.MODULE$:Lde/sciss/lucre/Txn$;
       7: aload_1
       8: invokevirtual #178                // Method de/sciss/lucre/Txn$.peer:(Lde/sciss/lucre/TxnLike;)Lscala/concurrent/stm/InTxn;
      11: invokeinterface #183,  2          // InterfaceMethod scala/concurrent/stm/Ref.apply:(Ljava/lang/Object;)Ljava/lang/Object;
      16: checkcast     #139                // class scala/Option
      19: aload_0
      20: invokedynamic #344,  0            // InvokeDynamic #7:apply:(Lde/sciss/proc/impl/AuralNodeImpl$Impl;)Lscala/Function1;
      25: invokevirtual #328                // Method scala/Option.flatMap:(Lscala/Function1;)Lscala/Option;
      28: aload_0
      29: invokedynamic #349,  0            // InvokeDynamic #8:apply:(Lde/sciss/proc/impl/AuralNodeImpl$Impl;)Lscala/Function0;
      34: invokevirtual #225                // Method scala/Option.getOrElse:(Lscala/Function0;)Ljava/lang/Object;
      37: checkcast     #137                // class de/sciss/lucre/synth/Node
      40: areturn

  private void moveAllTo(de.sciss.proc.impl.AuralNodeImpl$AllGroups, de.sciss.lucre.synth.Group, T);
    Code:
       0: aload_0
       1: aload_3
       2: invokespecial #355                // Method anchorNode:(Lde/sciss/lucre/synth/Txn;)Lde/sciss/lucre/synth/Node;
       5: astore        4
       7: aload         4
       9: aload_2
      10: aload_3
      11: invokeinterface #359,  3          // InterfaceMethod de/sciss/lucre/synth/Node.moveToTail:(Lde/sciss/lucre/synth/Group;Lde/sciss/lucre/synth/RT;)V
      16: aload_1
      17: invokevirtual #362                // Method de/sciss/proc/impl/AuralNodeImpl$AllGroups.pre:()Lscala/Option;
      20: aload_0
      21: aload_3
      22: aload         4
      24: invokedynamic #372,  0            // InvokeDynamic #9:applyVoid:(Lde/sciss/proc/impl/AuralNodeImpl$Impl;Lde/sciss/lucre/synth/Txn;Lde/sciss/lucre/synth/Node;)Lscala/runtime/function/JProcedure1;
      29: invokevirtual #373                // Method scala/Option.foreach:(Lscala/Function1;)V
      32: aload_1
      33: invokevirtual #376                // Method de/sciss/proc/impl/AuralNodeImpl$AllGroups.post:()Lscala/Option;
      36: aload_0
      37: aload_3
      38: aload         4
      40: invokedynamic #381,  0            // InvokeDynamic #10:applyVoid:(Lde/sciss/proc/impl/AuralNodeImpl$Impl;Lde/sciss/lucre/synth/Txn;Lde/sciss/lucre/synth/Node;)Lscala/runtime/function/JProcedure1;
      45: invokevirtual #373                // Method scala/Option.foreach:(Lscala/Function1;)V
      48: aload_1
      49: invokevirtual #384                // Method de/sciss/proc/impl/AuralNodeImpl$AllGroups.back:()Lscala/Option;
      52: aload_0
      53: aload_2
      54: aload_3
      55: invokedynamic #392,  0            // InvokeDynamic #11:applyVoid:(Lde/sciss/proc/impl/AuralNodeImpl$Impl;Lde/sciss/lucre/synth/Group;Lde/sciss/lucre/synth/Txn;)Lscala/runtime/function/JProcedure1;
      60: invokevirtual #373                // Method scala/Option.foreach:(Lscala/Function1;)V
      63: return

  public void dispose(T);
    Code:
       0: aload_0
       1: aload_1
       2: invokevirtual #398                // Method node:(Lde/sciss/lucre/synth/RT;)Lde/sciss/lucre/synth/Node;
       5: aload_1
       6: invokeinterface #402,  2          // InterfaceMethod de/sciss/lucre/synth/Node.free:(Lde/sciss/lucre/synth/RT;)V
      11: aload_0
      12: getfield      #68                 // Field users:Lscala/concurrent/stm/Ref;
      15: getstatic     #73                 // Field scala/package$.MODULE$:Lscala/package$;
      18: invokevirtual #406                // Method scala/package$.Nil:()Lscala/collection/immutable/Nil$;
      21: getstatic     #174                // Field de/sciss/lucre/Txn$.MODULE$:Lde/sciss/lucre/Txn$;
      24: aload_1
      25: invokevirtual #178                // Method de/sciss/lucre/Txn$.peer:(Lde/sciss/lucre/TxnLike;)Lscala/concurrent/stm/InTxn;
      28: invokeinterface #410,  3          // InterfaceMethod scala/concurrent/stm/Ref.swap:(Ljava/lang/Object;Ljava/lang/Object;)Ljava/lang/Object;
      33: checkcast     #135                // class scala/collection/immutable/List
      36: invokevirtual #247                // Method scala/collection/immutable/List.reverse:()Lscala/collection/immutable/List;
      39: aload_0
      40: aload_1
      41: invokedynamic #415,  0            // InvokeDynamic #12:applyVoid:(Lde/sciss/proc/impl/AuralNodeImpl$Impl;Lde/sciss/lucre/synth/Txn;)Lscala/runtime/function/JProcedure1;
      46: invokevirtual #267                // Method scala/collection/immutable/List.foreach:(Lscala/Function1;)V
      49: aload_0
      50: getfield      #85                 // Field resources:Lscala/concurrent/stm/Ref;
      53: getstatic     #73                 // Field scala/package$.MODULE$:Lscala/package$;
      56: invokevirtual #406                // Method scala/package$.Nil:()Lscala/collection/immutable/Nil$;
      59: getstatic     #174                // Field de/sciss/lucre/Txn$.MODULE$:Lde/sciss/lucre/Txn$;
      62: aload_1
      63: invokevirtual #178                // Method de/sciss/lucre/Txn$.peer:(Lde/sciss/lucre/TxnLike;)Lscala/concurrent/stm/InTxn;
      66: invokeinterface #410,  3          // InterfaceMethod scala/concurrent/stm/Ref.swap:(Ljava/lang/Object;Ljava/lang/Object;)Ljava/lang/Object;
      71: checkcast     #135                // class scala/collection/immutable/List
      74: invokevirtual #247                // Method scala/collection/immutable/List.reverse:()Lscala/collection/immutable/List;
      77: aload_0
      78: aload_1
      79: invokedynamic #423,  0            // InvokeDynamic #13:applyVoid:(Lde/sciss/proc/impl/AuralNodeImpl$Impl;Lde/sciss/lucre/synth/Txn;)Lscala/runtime/function/JProcedure1;
      84: invokevirtual #267                // Method scala/collection/immutable/List.foreach:(Lscala/Function1;)V
      87: aload_0
      88: getfield      #87                 // Field disposables:Lscala/concurrent/stm/Ref;
      91: getstatic     #73                 // Field scala/package$.MODULE$:Lscala/package$;
      94: invokevirtual #406                // Method scala/package$.Nil:()Lscala/collection/immutable/Nil$;
      97: getstatic     #174                // Field de/sciss/lucre/Txn$.MODULE$:Lde/sciss/lucre/Txn$;
     100: aload_1
     101: invokevirtual #178                // Method de/sciss/lucre/Txn$.peer:(Lde/sciss/lucre/TxnLike;)Lscala/concurrent/stm/InTxn;
     104: invokeinterface #410,  3          // InterfaceMethod scala/concurrent/stm/Ref.swap:(Ljava/lang/Object;Ljava/lang/Object;)Ljava/lang/Object;
     109: checkcast     #135                // class scala/collection/immutable/List
     112: invokevirtual #247                // Method scala/collection/immutable/List.reverse:()Lscala/collection/immutable/List;
     115: aload_0
     116: aload_1
     117: invokedynamic #431,  0            // InvokeDynamic #14:applyVoid:(Lde/sciss/proc/impl/AuralNodeImpl$Impl;Lde/sciss/lucre/synth/Txn;)Lscala/runtime/function/JProcedure1;
     122: invokevirtual #267                // Method scala/collection/immutable/List.foreach:(Lscala/Function1;)V
     125: aload_0
     126: invokevirtual #233                // Method server:()Lde/sciss/lucre/synth/Server;
     129: aload_0
     130: aload_1
     131: invokeinterface #435,  3          // InterfaceMethod de/sciss/lucre/synth/Server.removeVertex:(Lde/sciss/lucre/synth/NodeRef;Lde/sciss/lucre/synth/RT;)V
     136: return

  public void addControl(de.sciss.synth.ControlSet, T);
    Code:
       0: aload_0
       1: getfield      #51                 // Field tree:Lde/sciss/proc/impl/AuralNodeImpl$Tree;
       4: invokeinterface #91,  1           // InterfaceMethod de/sciss/proc/impl/AuralNodeImpl$Tree.main:()Lde/sciss/lucre/synth/Node;
       9: aload_2
      10: invokeinterface #443,  2          // InterfaceMethod de/sciss/lucre/synth/Node.isOnline:(Lde/sciss/lucre/synth/RT;)Z
      15: ifeq          46
      18: aload_0
      19: aload_2
      20: invokevirtual #398                // Method node:(Lde/sciss/lucre/synth/RT;)Lde/sciss/lucre/synth/Node;
      23: getstatic     #448                // Field scala/runtime/ScalaRunTime$.MODULE$:Lscala/runtime/ScalaRunTime$;
      26: iconst_1
      27: anewarray     #450                // class de/sciss/synth/ControlSet
      30: dup
      31: iconst_0
      32: aload_1
      33: aastore
      34: invokevirtual #454                // Method scala/runtime/ScalaRunTime$.wrapRefArray:([Ljava/lang/Object;)Lscala/collection/immutable/ArraySeq;
      37: aload_2
      38: invokeinterface #458,  3          // InterfaceMethod de/sciss/lucre/synth/Node.set:(Lscala/collection/immutable/Seq;Lde/sciss/lucre/synth/RT;)V
      43: goto          58
      46: aload_0
      47: aload_0
      48: getfield      #53                 // Field setMap:Lscala/collection/immutable/List;
      51: aload_1
      52: invokevirtual #462                // Method scala/collection/immutable/List.$colon$colon:(Ljava/lang/Object;)Lscala/collection/immutable/List;
      55: putfield      #53                 // Field setMap:Lscala/collection/immutable/List;
      58: return

  public void addUser(de.sciss.lucre.synth.DynamicUser, de.sciss.lucre.synth.RT);
    Code:
       0: aload_0
       1: getfield      #68                 // Field users:Lscala/concurrent/stm/Ref;
       4: aload_0
       5: aload_1
       6: invokedynamic #476,  0            // InvokeDynamic #15:apply:(Lde/sciss/proc/impl/AuralNodeImpl$Impl;Lde/sciss/lucre/synth/DynamicUser;)Lscala/Function1;
      11: getstatic     #174                // Field de/sciss/lucre/Txn$.MODULE$:Lde/sciss/lucre/Txn$;
      14: aload_2
      15: invokevirtual #178                // Method de/sciss/lucre/Txn$.peer:(Lde/sciss/lucre/TxnLike;)Lscala/concurrent/stm/InTxn;
      18: invokeinterface #307,  3          // InterfaceMethod scala/concurrent/stm/Ref.transform:(Lscala/Function1;Ljava/lang/Object;)V
      23: aload_0
      24: getfield      #51                 // Field tree:Lde/sciss/proc/impl/AuralNodeImpl$Tree;
      27: invokeinterface #91,  1           // InterfaceMethod de/sciss/proc/impl/AuralNodeImpl$Tree.main:()Lde/sciss/lucre/synth/Node;
      32: aload_2
      33: invokeinterface #443,  2          // InterfaceMethod de/sciss/lucre/synth/Node.isOnline:(Lde/sciss/lucre/synth/RT;)Z
      38: ifeq          48
      41: aload_1
      42: aload_2
      43: invokeinterface #481,  2          // InterfaceMethod de/sciss/lucre/synth/DynamicUser.add:(Lde/sciss/lucre/synth/RT;)V
      48: return

  public void removeUser(de.sciss.lucre.synth.DynamicUser, de.sciss.lucre.synth.RT);
    Code:
       0: aload_0
       1: getfield      #68                 // Field users:Lscala/concurrent/stm/Ref;
       4: aload_0
       5: aload_1
       6: invokedynamic #488,  0            // InvokeDynamic #16:apply:(Lde/sciss/proc/impl/AuralNodeImpl$Impl;Lde/sciss/lucre/synth/DynamicUser;)Lscala/Function1;
      11: getstatic     #174                // Field de/sciss/lucre/Txn$.MODULE$:Lde/sciss/lucre/Txn$;
      14: aload_2
      15: invokevirtual #178                // Method de/sciss/lucre/Txn$.peer:(Lde/sciss/lucre/TxnLike;)Lscala/concurrent/stm/InTxn;
      18: invokeinterface #307,  3          // InterfaceMethod scala/concurrent/stm/Ref.transform:(Lscala/Function1;Ljava/lang/Object;)V
      23: return

  public void addResource(de.sciss.lucre.synth.Resource, de.sciss.lucre.synth.RT);
    Code:
       0: aload_0
       1: getfield      #85                 // Field resources:Lscala/concurrent/stm/Ref;
       4: aload_0
       5: aload_1
       6: invokedynamic #499,  0            // InvokeDynamic #17:apply:(Lde/sciss/proc/impl/AuralNodeImpl$Impl;Lde/sciss/lucre/synth/Resource;)Lscala/Function1;
      11: getstatic     #174                // Field de/sciss/lucre/Txn$.MODULE$:Lde/sciss/lucre/Txn$;
      14: aload_2
      15: invokevirtual #178                // Method de/sciss/lucre/Txn$.peer:(Lde/sciss/lucre/TxnLike;)Lscala/concurrent/stm/InTxn;
      18: invokeinterface #307,  3          // InterfaceMethod scala/concurrent/stm/Ref.transform:(Lscala/Function1;Ljava/lang/Object;)V
      23: return

  public void removeResource(de.sciss.lucre.synth.Resource, de.sciss.lucre.synth.RT);
    Code:
       0: aload_0
       1: getfield      #85                 // Field resources:Lscala/concurrent/stm/Ref;
       4: aload_0
       5: aload_1
       6: invokedynamic #506,  0            // InvokeDynamic #18:apply:(Lde/sciss/proc/impl/AuralNodeImpl$Impl;Lde/sciss/lucre/synth/Resource;)Lscala/Function1;
      11: getstatic     #174                // Field de/sciss/lucre/Txn$.MODULE$:Lde/sciss/lucre/Txn$;
      14: aload_2
      15: invokevirtual #178                // Method de/sciss/lucre/Txn$.peer:(Lde/sciss/lucre/TxnLike;)Lscala/concurrent/stm/InTxn;
      18: invokeinterface #307,  3          // InterfaceMethod scala/concurrent/stm/Ref.transform:(Lscala/Function1;Ljava/lang/Object;)V
      23: return

  public void addDisposable(de.sciss.lucre.Disposable<T>, T);
    Code:
       0: aload_0
       1: getfield      #87                 // Field disposables:Lscala/concurrent/stm/Ref;
       4: aload_0
       5: aload_1
       6: invokedynamic #518,  0            // InvokeDynamic #19:apply:(Lde/sciss/proc/impl/AuralNodeImpl$Impl;Lde/sciss/lucre/Disposable;)Lscala/Function1;
      11: getstatic     #174                // Field de/sciss/lucre/Txn$.MODULE$:Lde/sciss/lucre/Txn$;
      14: aload_2
      15: invokevirtual #178                // Method de/sciss/lucre/Txn$.peer:(Lde/sciss/lucre/TxnLike;)Lscala/concurrent/stm/InTxn;
      18: invokeinterface #307,  3          // InterfaceMethod scala/concurrent/stm/Ref.transform:(Lscala/Function1;Ljava/lang/Object;)V
      23: return

  public void play(de.sciss.lucre.Txn);
    Code:
       0: aload_0
       1: aload_1
       2: checkcast     #312                // class de/sciss/lucre/synth/Txn
       5: invokevirtual #522                // Method play:(Lde/sciss/lucre/synth/Txn;)V
       8: return

  public de.sciss.lucre.synth.Group group(de.sciss.lucre.Txn);
    Code:
       0: aload_0
       1: aload_1
       2: checkcast     #312                // class de/sciss/lucre/synth/Txn
       5: invokevirtual #526                // Method group:(Lde/sciss/lucre/synth/Txn;)Lde/sciss/lucre/synth/Group;
       8: areturn

  public void group_$eq(de.sciss.lucre.synth.Group, de.sciss.lucre.Txn);
    Code:
       0: aload_0
       1: aload_1
       2: aload_2
       3: checkcast     #312                // class de/sciss/lucre/synth/Txn
       6: invokevirtual #530                // Method group_$eq:(Lde/sciss/lucre/synth/Group;Lde/sciss/lucre/synth/Txn;)V
       9: return

  public de.sciss.lucre.synth.Group preGroup(de.sciss.lucre.Txn);
    Code:
       0: aload_0
       1: aload_1
       2: checkcast     #312                // class de/sciss/lucre/synth/Txn
       5: invokevirtual #532                // Method preGroup:(Lde/sciss/lucre/synth/Txn;)Lde/sciss/lucre/synth/Group;
       8: areturn

  public void dispose(java.lang.Object);
    Code:
       0: aload_0
       1: aload_1
       2: checkcast     #312                // class de/sciss/lucre/synth/Txn
       5: invokevirtual #534                // Method dispose:(Lde/sciss/lucre/synth/Txn;)V
       8: return

  public void addControl(de.sciss.synth.ControlSet, de.sciss.lucre.Txn);
    Code:
       0: aload_0
       1: aload_1
       2: aload_2
       3: checkcast     #312                // class de/sciss/lucre/synth/Txn
       6: invokevirtual #538                // Method addControl:(Lde/sciss/synth/ControlSet;Lde/sciss/lucre/synth/Txn;)V
       9: return

  public void addDisposable(de.sciss.lucre.Disposable, de.sciss.lucre.Txn);
    Code:
       0: aload_0
       1: aload_1
       2: aload_2
       3: checkcast     #312                // class de/sciss/lucre/synth/Txn
       6: invokevirtual #541                // Method addDisposable:(Lde/sciss/lucre/Disposable;Lde/sciss/lucre/synth/Txn;)V
       9: return

  private final de.sciss.lucre.synth.Group groupOption$$anonfun$1(de.sciss.proc.impl.AuralNodeImpl$AllGroups);
    Code:
       0: aload_1
       1: invokevirtual #544                // Method de/sciss/proc/impl/AuralNodeImpl$AllGroups.main:()Lde/sciss/lucre/synth/Group;
       4: areturn

  private final de.sciss.lucre.synth.Node node$$anonfun$1();
    Code:
       0: aload_0
       1: getfield      #51                 // Field tree:Lde/sciss/proc/impl/AuralNodeImpl$Tree;
       4: invokeinterface #91,  1           // InterfaceMethod de/sciss/proc/impl/AuralNodeImpl$Tree.main:()Lde/sciss/lucre/synth/Node;
       9: areturn

  private final void play$$anonfun$1(de.sciss.lucre.synth.Txn, de.sciss.lucre.synth.DynamicUser);
    Code:
       0: aload_2
       1: aload_1
       2: invokeinterface #481,  2          // InterfaceMethod de/sciss/lucre/synth/DynamicUser.add:(Lde/sciss/lucre/synth/RT;)V
       7: return

  private final de.sciss.lucre.synth.Group group$$anonfun$1(de.sciss.lucre.synth.Txn);
    Code:
       0: getstatic     #552                // Field de/sciss/lucre/synth/Group$.MODULE$:Lde/sciss/lucre/synth/Group$;
       3: aload_0
       4: getfield      #51                 // Field tree:Lde/sciss/proc/impl/AuralNodeImpl$Tree;
       7: invokeinterface #91,  1           // InterfaceMethod de/sciss/proc/impl/AuralNodeImpl$Tree.main:()Lde/sciss/lucre/synth/Node;
      12: getstatic     #557                // Field de/sciss/synth/addBefore$.MODULE$:Lde/sciss/synth/addBefore$;
      15: aload_1
      16: invokevirtual #560                // Method de/sciss/lucre/synth/Group$.play:(Lde/sciss/lucre/synth/Node;Lde/sciss/synth/AddAction;Lde/sciss/lucre/synth/RT;)Lde/sciss/lucre/synth/Group;
      19: astore_2
      20: aload_0
      21: aload_2
      22: aload_1
      23: invokevirtual #530                // Method group_$eq:(Lde/sciss/lucre/synth/Group;Lde/sciss/lucre/synth/Txn;)V
      26: aload_2
      27: areturn

  private final de.sciss.proc.impl.AuralNodeImpl$AllGroups $anonfun$1(de.sciss.lucre.synth.Group, de.sciss.lucre.synth.Txn);
    Code:
       0: getstatic     #101                // Field de/sciss/proc/impl/AuralNodeImpl$AllGroups$.MODULE$:Lde/sciss/proc/impl/AuralNodeImpl$AllGroups$;
       3: aload_1
       4: getstatic     #101                // Field de/sciss/proc/impl/AuralNodeImpl$AllGroups$.MODULE$:Lde/sciss/proc/impl/AuralNodeImpl$AllGroups$;
       7: invokevirtual #105                // Method de/sciss/proc/impl/AuralNodeImpl$AllGroups$.$lessinit$greater$default$2:()Lscala/Option;
      10: getstatic     #101                // Field de/sciss/proc/impl/AuralNodeImpl$AllGroups$.MODULE$:Lde/sciss/proc/impl/AuralNodeImpl$AllGroups$;
      13: invokevirtual #108                // Method de/sciss/proc/impl/AuralNodeImpl$AllGroups$.$lessinit$greater$default$3:()Lscala/Option;
      16: getstatic     #101                // Field de/sciss/proc/impl/AuralNodeImpl$AllGroups$.MODULE$:Lde/sciss/proc/impl/AuralNodeImpl$AllGroups$;
      19: invokevirtual #111                // Method de/sciss/proc/impl/AuralNodeImpl$AllGroups$.$lessinit$greater$default$4:()Lscala/Option;
      22: getstatic     #101                // Field de/sciss/proc/impl/AuralNodeImpl$AllGroups$.MODULE$:Lde/sciss/proc/impl/AuralNodeImpl$AllGroups$;
      25: invokevirtual #114                // Method de/sciss/proc/impl/AuralNodeImpl$AllGroups$.$lessinit$greater$default$5:()Lscala/Option;
      28: invokevirtual #117                // Method de/sciss/proc/impl/AuralNodeImpl$AllGroups$.apply:(Lde/sciss/lucre/synth/Group;Lscala/Option;Lscala/Option;Lscala/Option;Lscala/Option;)Lde/sciss/proc/impl/AuralNodeImpl$AllGroups;
      31: astore_3
      32: aload_0
      33: getfield      #51                 // Field tree:Lde/sciss/proc/impl/AuralNodeImpl$Tree;
      36: invokeinterface #91,  1           // InterfaceMethod de/sciss/proc/impl/AuralNodeImpl$Tree.main:()Lde/sciss/lucre/synth/Node;
      41: aload_1
      42: aload_2
      43: invokeinterface #568,  3          // InterfaceMethod de/sciss/lucre/synth/Node.moveToHead:(Lde/sciss/lucre/synth/Group;Lde/sciss/lucre/synth/RT;)V
      48: aload_3
      49: areturn

  private final de.sciss.proc.impl.AuralNodeImpl$AllGroups $anonfun$2(de.sciss.lucre.synth.Group, de.sciss.lucre.synth.Txn, de.sciss.proc.impl.AuralNodeImpl$AllGroups);
    Code:
       0: aload_0
       1: aload_3
       2: aload_1
       3: aload_2
       4: invokespecial #574                // Method moveAllTo:(Lde/sciss/proc/impl/AuralNodeImpl$AllGroups;Lde/sciss/lucre/synth/Group;Lde/sciss/lucre/synth/Txn;)V
       7: aload_3
       8: invokevirtual #544                // Method de/sciss/proc/impl/AuralNodeImpl$AllGroups.main:()Lde/sciss/lucre/synth/Group;
      11: aload_2
      12: invokeinterface #575,  2          // InterfaceMethod de/sciss/lucre/synth/Group.free:(Lde/sciss/lucre/synth/RT;)V
      17: aload_3
      18: aload_1
      19: aload_3
      20: invokevirtual #578                // Method de/sciss/proc/impl/AuralNodeImpl$AllGroups.copy$default$2:()Lscala/Option;
      23: aload_3
      24: invokevirtual #581                // Method de/sciss/proc/impl/AuralNodeImpl$AllGroups.copy$default$3:()Lscala/Option;
      27: aload_3
      28: invokevirtual #584                // Method de/sciss/proc/impl/AuralNodeImpl$AllGroups.copy$default$4:()Lscala/Option;
      31: aload_3
      32: invokevirtual #587                // Method de/sciss/proc/impl/AuralNodeImpl$AllGroups.copy$default$5:()Lscala/Option;
      35: invokevirtual #590                // Method de/sciss/proc/impl/AuralNodeImpl$AllGroups.copy:(Lde/sciss/lucre/synth/Group;Lscala/Option;Lscala/Option;Lscala/Option;Lscala/Option;)Lde/sciss/proc/impl/AuralNodeImpl$AllGroups;
      38: areturn

  private final scala.Option group_$eq$$anonfun$1(de.sciss.lucre.synth.Group, de.sciss.lucre.synth.Txn, scala.Option);
    Code:
       0: aload_3
       1: aload_0
       2: aload_1
       3: aload_2
       4: invokedynamic #601,  0            // InvokeDynamic #20:apply:(Lde/sciss/proc/impl/AuralNodeImpl$Impl;Lde/sciss/lucre/synth/Group;Lde/sciss/lucre/synth/Txn;)Lscala/Function0;
       9: aload_0
      10: aload_1
      11: aload_2
      12: invokedynamic #607,  0            // InvokeDynamic #21:apply:(Lde/sciss/proc/impl/AuralNodeImpl$Impl;Lde/sciss/lucre/synth/Group;Lde/sciss/lucre/synth/Txn;)Lscala/Function1;
      17: invokevirtual #611                // Method scala/Option.fold:(Lscala/Function0;Lscala/Function1;)Ljava/lang/Object;
      20: checkcast     #13                 // class de/sciss/proc/impl/AuralNodeImpl$AllGroups
      23: astore        4
      25: getstatic     #98                 // Field scala/Some$.MODULE$:Lscala/Some$;
      28: aload         4
      30: invokevirtual #120                // Method scala/Some$.apply:(Ljava/lang/Object;)Lscala/Some;
      33: areturn

  private final scala.Option preGroupOption$$anonfun$1(de.sciss.proc.impl.AuralNodeImpl$AllGroups);
    Code:
       0: aload_1
       1: invokevirtual #362                // Method de/sciss/proc/impl/AuralNodeImpl$AllGroups.pre:()Lscala/Option;
       4: areturn

  private final de.sciss.lucre.synth.Group preGroup$$anonfun$1(de.sciss.lucre.synth.Txn);
    Code:
       0: aload_0
       1: aload_1
       2: invokevirtual #526                // Method group:(Lde/sciss/lucre/synth/Txn;)Lde/sciss/lucre/synth/Group;
       5: pop
       6: aload_0
       7: getfield      #127                // Field groupsRef:Lscala/concurrent/stm/Ref;
      10: getstatic     #174                // Field de/sciss/lucre/Txn$.MODULE$:Lde/sciss/lucre/Txn$;
      13: aload_1
      14: invokevirtual #178                // Method de/sciss/lucre/Txn$.peer:(Lde/sciss/lucre/TxnLike;)Lscala/concurrent/stm/InTxn;
      17: invokeinterface #183,  2          // InterfaceMethod scala/concurrent/stm/Ref.apply:(Ljava/lang/Object;)Ljava/lang/Object;
      22: checkcast     #139                // class scala/Option
      25: invokevirtual #616                // Method scala/Option.get:()Ljava/lang/Object;
      28: checkcast     #13                 // class de/sciss/proc/impl/AuralNodeImpl$AllGroups
      31: astore_2
      32: aload_0
      33: aload_1
      34: invokespecial #355                // Method anchorNode:(Lde/sciss/lucre/synth/Txn;)Lde/sciss/lucre/synth/Node;
      37: astore_3
      38: getstatic     #557                // Field de/sciss/synth/addBefore$.MODULE$:Lde/sciss/synth/addBefore$;
      41: astore        4
      43: getstatic     #552                // Field de/sciss/lucre/synth/Group$.MODULE$:Lde/sciss/lucre/synth/Group$;
      46: aload_3
      47: aload         4
      49: aload_1
      50: invokevirtual #560                // Method de/sciss/lucre/synth/Group$.play:(Lde/sciss/lucre/synth/Node;Lde/sciss/synth/AddAction;Lde/sciss/lucre/synth/RT;)Lde/sciss/lucre/synth/Group;
      53: astore        5
      55: aload_0
      56: getfield      #127                // Field groupsRef:Lscala/concurrent/stm/Ref;
      59: getstatic     #98                 // Field scala/Some$.MODULE$:Lscala/Some$;
      62: getstatic     #98                 // Field scala/Some$.MODULE$:Lscala/Some$;
      65: aload         5
      67: invokevirtual #120                // Method scala/Some$.apply:(Ljava/lang/Object;)Lscala/Some;
      70: astore        6
      72: aload_2
      73: invokevirtual #619                // Method de/sciss/proc/impl/AuralNodeImpl$AllGroups.copy$default$1:()Lde/sciss/lucre/synth/Group;
      76: astore        7
      78: aload_2
      79: invokevirtual #581                // Method de/sciss/proc/impl/AuralNodeImpl$AllGroups.copy$default$3:()Lscala/Option;
      82: astore        8
      84: aload_2
      85: invokevirtual #584                // Method de/sciss/proc/impl/AuralNodeImpl$AllGroups.copy$default$4:()Lscala/Option;
      88: astore        9
      90: aload_2
      91: invokevirtual #587                // Method de/sciss/proc/impl/AuralNodeImpl$AllGroups.copy$default$5:()Lscala/Option;
      94: astore        10
      96: aload_2
      97: aload         7
      99: aload         6
     101: aload         8
     103: aload         9
     105: aload         10
     107: invokevirtual #590                // Method de/sciss/proc/impl/AuralNodeImpl$AllGroups.copy:(Lde/sciss/lucre/synth/Group;Lscala/Option;Lscala/Option;Lscala/Option;Lscala/Option;)Lde/sciss/proc/impl/AuralNodeImpl$AllGroups;
     110: invokevirtual #120                // Method scala/Some$.apply:(Ljava/lang/Object;)Lscala/Some;
     113: getstatic     #174                // Field de/sciss/lucre/Txn$.MODULE$:Lde/sciss/lucre/Txn$;
     116: aload_1
     117: invokevirtual #178                // Method de/sciss/lucre/Txn$.peer:(Lde/sciss/lucre/TxnLike;)Lscala/concurrent/stm/InTxn;
     120: invokeinterface #622,  3          // InterfaceMethod scala/concurrent/stm/Ref.set:(Ljava/lang/Object;Ljava/lang/Object;)V
     125: aload         5
     127: areturn

  private final scala.Option anchorNode$$anonfun$1(de.sciss.proc.impl.AuralNodeImpl$AllGroups);
    Code:
       0: aload_1
       1: invokevirtual #626                // Method de/sciss/proc/impl/AuralNodeImpl$AllGroups.core:()Lscala/Option;
       4: areturn

  private final de.sciss.lucre.synth.Node anchorNode$$anonfun$2();
    Code:
       0: aload_0
       1: getfield      #51                 // Field tree:Lde/sciss/proc/impl/AuralNodeImpl$Tree;
       4: invokeinterface #91,  1           // InterfaceMethod de/sciss/proc/impl/AuralNodeImpl$Tree.main:()Lde/sciss/lucre/synth/Node;
       9: areturn

  private final void moveAllTo$$anonfun$1(de.sciss.lucre.synth.Txn, de.sciss.lucre.synth.Node, de.sciss.lucre.synth.Group);
    Code:
       0: aload_3
       1: aload_2
       2: aload_1
       3: invokeinterface #633,  3          // InterfaceMethod de/sciss/lucre/synth/Group.moveBefore:(Lde/sciss/lucre/synth/Node;Lde/sciss/lucre/synth/RT;)V
       8: return

  private final void moveAllTo$$anonfun$2(de.sciss.lucre.synth.Txn, de.sciss.lucre.synth.Node, de.sciss.lucre.synth.Group);
    Code:
       0: aload_3
       1: aload_2
       2: aload_1
       3: invokeinterface #639,  3          // InterfaceMethod de/sciss/lucre/synth/Group.moveAfter:(Lde/sciss/lucre/synth/Node;Lde/sciss/lucre/synth/RT;)V
       8: return

  private final void moveAllTo$$anonfun$3(de.sciss.lucre.synth.Group, de.sciss.lucre.synth.Txn, de.sciss.lucre.synth.Group);
    Code:
       0: aload_3
       1: aload_2
       2: invokeinterface #642,  2          // InterfaceMethod de/sciss/lucre/synth/Group.isOnline:(Lde/sciss/lucre/synth/RT;)Z
       7: ifeq          18
      10: aload_3
      11: aload_1
      12: aload_2
      13: invokeinterface #643,  3          // InterfaceMethod de/sciss/lucre/synth/Group.moveToHead:(Lde/sciss/lucre/synth/Group;Lde/sciss/lucre/synth/RT;)V
      18: return

  private final void dispose$$anonfun$1(de.sciss.lucre.synth.Txn, de.sciss.lucre.synth.DynamicUser);
    Code:
       0: aload_2
       1: aload_1
       2: invokeinterface #647,  2          // InterfaceMethod de/sciss/lucre/synth/DynamicUser.dispose:(Lde/sciss/lucre/synth/RT;)V
       7: return

  private final void dispose$$anonfun$2(de.sciss.lucre.synth.Txn, de.sciss.lucre.synth.Resource);
    Code:
       0: aload_2
       1: aload_1
       2: invokeinterface #653,  2          // InterfaceMethod de/sciss/lucre/synth/Resource.dispose:(Ljava/lang/Object;)V
       7: return

  private final void dispose$$anonfun$3(de.sciss.lucre.synth.Txn, de.sciss.lucre.Disposable);
    Code:
       0: aload_2
       1: aload_1
       2: invokeinterface #658,  2          // InterfaceMethod de/sciss/lucre/Disposable.dispose:(Ljava/lang/Object;)V
       7: return

  private final scala.collection.immutable.List addUser$$anonfun$1(de.sciss.lucre.synth.DynamicUser, scala.collection.immutable.List);
    Code:
       0: aload_2
       1: aload_1
       2: invokevirtual #462                // Method scala/collection/immutable/List.$colon$colon:(Ljava/lang/Object;)Lscala/collection/immutable/List;
       5: areturn

  private final boolean removeUser$$anonfun$2$$anonfun$1(de.sciss.lucre.synth.DynamicUser, de.sciss.lucre.synth.DynamicUser);
    Code:
       0: aload_2
       1: aload_1
       2: astore_3
       3: dup
       4: ifnonnull     15
       7: pop
       8: aload_3
       9: ifnull        22
      12: goto          26
      15: aload_3
      16: invokevirtual #668                // Method java/lang/Object.equals:(Ljava/lang/Object;)Z
      19: ifeq          26
      22: iconst_1
      23: goto          27
      26: iconst_0
      27: ireturn

  private final scala.collection.immutable.List removeUser$$anonfun$1(de.sciss.lucre.synth.DynamicUser, scala.collection.immutable.List);
    Code:
       0: aload_2
       1: aload_0
       2: aload_1
       3: invokedynamic #676,  0            // InvokeDynamic #22:apply:(Lde/sciss/proc/impl/AuralNodeImpl$Impl;Lde/sciss/lucre/synth/DynamicUser;)Lscala/Function1;
       8: invokevirtual #680                // Method scala/collection/immutable/List.filterNot:(Lscala/Function1;)Lscala/collection/immutable/List;
      11: areturn

  private final scala.collection.immutable.List addResource$$anonfun$1(de.sciss.lucre.synth.Resource, scala.collection.immutable.List);
    Code:
       0: aload_2
       1: aload_1
       2: invokevirtual #462                // Method scala/collection/immutable/List.$colon$colon:(Ljava/lang/Object;)Lscala/collection/immutable/List;
       5: areturn

  private final boolean removeResource$$anonfun$2$$anonfun$1(de.sciss.lucre.synth.Resource, de.sciss.lucre.synth.Resource);
    Code:
       0: aload_2
       1: aload_1
       2: astore_3
       3: dup
       4: ifnonnull     15
       7: pop
       8: aload_3
       9: ifnull        22
      12: goto          26
      15: aload_3
      16: invokevirtual #668                // Method java/lang/Object.equals:(Ljava/lang/Object;)Z
      19: ifeq          26
      22: iconst_1
      23: goto          27
      26: iconst_0
      27: ireturn

  private final scala.collection.immutable.List removeResource$$anonfun$1(de.sciss.lucre.synth.Resource, scala.collection.immutable.List);
    Code:
       0: aload_2
       1: aload_0
       2: aload_1
       3: invokedynamic #694,  0            // InvokeDynamic #23:apply:(Lde/sciss/proc/impl/AuralNodeImpl$Impl;Lde/sciss/lucre/synth/Resource;)Lscala/Function1;
       8: invokevirtual #680                // Method scala/collection/immutable/List.filterNot:(Lscala/Function1;)Lscala/collection/immutable/List;
      11: areturn

  private final scala.collection.immutable.List addDisposable$$anonfun$1(de.sciss.lucre.Disposable, scala.collection.immutable.List);
    Code:
       0: aload_2
       1: aload_1
       2: invokevirtual #462                // Method scala/collection/immutable/List.$colon$colon:(Ljava/lang/Object;)Lscala/collection/immutable/List;
       5: areturn

  private static java.lang.Object $deserializeLambda$(java.lang.invoke.SerializedLambda);
    Code:
       0: aload_0
       1: invokedynamic #708,  0            // InvokeDynamic #24:lambdaDeserialize:(Ljava/lang/invoke/SerializedLambda;)Ljava/lang/Object;
       6: areturn
}
