Compiled from "AuralAttributeTargetImpl.scala"
final class de.sciss.proc.impl.AuralAttributeTargetImpl$Multiple implements de.sciss.proc.impl.AuralAttributeTargetImpl$State {
  private final de.sciss.lucre.synth.DynamicUser tgtBusUser;

  private final de.sciss.proc.impl.AuralAttributeTargetImpl<T> $outer;

  public de.sciss.proc.impl.AuralAttributeTargetImpl$Multiple(de.sciss.proc.impl.AuralAttributeTargetImpl, de.sciss.lucre.synth.DynamicUser);
    Code:
       0: aload_0
       1: aload_2
       2: putfield      #42                 // Field tgtBusUser:Lde/sciss/lucre/synth/DynamicUser;
       5: aload_1
       6: ifnonnull     17
       9: new           #44                 // class java/lang/NullPointerException
      12: dup
      13: invokespecial #47                 // Method java/lang/NullPointerException."<init>":()V
      16: athrow
      17: aload_0
      18: aload_1
      19: putfield      #49                 // Field $outer:Lde/sciss/proc/impl/AuralAttributeTargetImpl;
      22: aload_0
      23: invokespecial #50                 // Method java/lang/Object."<init>":()V
      26: return

  public scala.Option<de.sciss.proc.AuralAttribute$Value> valueOption(T);
    Code:
       0: getstatic     #62                 // Field scala/Some$.MODULE$:Lscala/Some$;
       3: getstatic     #65                 // Field de/sciss/proc/AuralAttribute$Stream$.MODULE$:Lde/sciss/proc/AuralAttribute$Stream$;
       6: aload_0
       7: getfield      #49                 // Field $outer:Lde/sciss/proc/impl/AuralAttributeTargetImpl;
      10: getfield      #69                 // Field de/sciss/proc/impl/AuralAttributeTargetImpl.de$sciss$proc$impl$AuralAttributeTargetImpl$$target:Lde/sciss/proc/AuralNode;
      13: aload_0
      14: getfield      #49                 // Field $outer:Lde/sciss/proc/impl/AuralAttributeTargetImpl;
      17: getfield      #73                 // Field de/sciss/proc/impl/AuralAttributeTargetImpl.de$sciss$proc$impl$AuralAttributeTargetImpl$$targetBus:Lde/sciss/lucre/synth/AudioBus;
      20: invokevirtual #77                 // Method de/sciss/proc/AuralAttribute$Stream$.apply:(Lde/sciss/lucre/synth/NodeRef;Lde/sciss/lucre/synth/AudioBus;)Lde/sciss/proc/AuralAttribute$Stream;
      23: invokevirtual #80                 // Method scala/Some$.apply:(Ljava/lang/Object;)Lscala/Some;
      26: areturn

  public de.sciss.proc.impl.AuralAttributeTargetImpl<T>.State put(de.sciss.proc.AuralAttribute<T>, de.sciss.proc.AuralAttribute$Value, T);
    Code:
       0: aload_0
       1: getfield      #49                 // Field $outer:Lde/sciss/proc/impl/AuralAttributeTargetImpl;
       4: aload_2
       5: aload_3
       6: invokevirtual #90                 // Method de/sciss/proc/impl/AuralAttributeTargetImpl.de$sciss$proc$impl$AuralAttributeTargetImpl$$mkVertex:(Lde/sciss/proc/AuralAttribute$Value;Lde/sciss/lucre/synth/Txn;)Lde/sciss/proc/impl/AuralAttributeTargetImpl$Connected;
       9: astore        4
      11: aload_0
      12: getfield      #49                 // Field $outer:Lde/sciss/proc/impl/AuralAttributeTargetImpl;
      15: getfield      #94                 // Field de/sciss/proc/impl/AuralAttributeTargetImpl.de$sciss$proc$impl$AuralAttributeTargetImpl$$map:Lscala/concurrent/stm/TMap;
      18: aload_1
      19: aload         4
      21: getstatic     #99                 // Field de/sciss/lucre/Txn$.MODULE$:Lde/sciss/lucre/Txn$;
      24: aload_3
      25: invokevirtual #103                // Method de/sciss/lucre/Txn$.peer:(Lde/sciss/lucre/TxnLike;)Lscala/concurrent/stm/InTxn;
      28: invokeinterface #106,  4          // InterfaceMethod scala/concurrent/stm/TMap.put:(Ljava/lang/Object;Ljava/lang/Object;Lscala/concurrent/stm/InTxn;)Lscala/Option;
      33: aload_3
      34: invokedynamic #128,  0            // InvokeDynamic #0:applyVoid:(Lde/sciss/lucre/synth/Txn;)Lscala/runtime/function/JProcedure1;
      39: invokevirtual #134                // Method scala/Option.foreach:(Lscala/Function1;)V
      42: aload_0
      43: areturn

  public de.sciss.proc.impl.AuralAttributeTargetImpl<T>.State remove(de.sciss.proc.AuralAttribute<T>, T);
    Code:
       0: aload_0
       1: getfield      #49                 // Field $outer:Lde/sciss/proc/impl/AuralAttributeTargetImpl;
       4: getfield      #94                 // Field de/sciss/proc/impl/AuralAttributeTargetImpl.de$sciss$proc$impl$AuralAttributeTargetImpl$$map:Lscala/concurrent/stm/TMap;
       7: aload_1
       8: getstatic     #99                 // Field de/sciss/lucre/Txn$.MODULE$:Lde/sciss/lucre/Txn$;
      11: aload_2
      12: invokevirtual #103                // Method de/sciss/lucre/Txn$.peer:(Lde/sciss/lucre/TxnLike;)Lscala/concurrent/stm/InTxn;
      15: invokeinterface #144,  3          // InterfaceMethod scala/concurrent/stm/TMap.remove:(Ljava/lang/Object;Lscala/concurrent/stm/InTxn;)Lscala/Option;
      20: astore_3
      21: aload_3
      22: aload_0
      23: invokedynamic #155,  0            // InvokeDynamic #1:apply:(Lde/sciss/proc/impl/AuralAttributeTargetImpl$Multiple;)Lscala/Function0;
      28: aload_0
      29: aload_2
      30: invokedynamic #167,  0            // InvokeDynamic #2:apply:(Lde/sciss/proc/impl/AuralAttributeTargetImpl$Multiple;Lde/sciss/lucre/synth/Txn;)Lscala/Function1;
      35: invokevirtual #171                // Method scala/Option.fold:(Lscala/Function0;Lscala/Function1;)Ljava/lang/Object;
      38: checkcast     #6                  // class de/sciss/proc/impl/AuralAttributeTargetImpl$State
      41: areturn

  public java.lang.String toString();
    Code:
       0: ldc           #176                // String Multiple
       2: areturn

  public final de.sciss.proc.impl.AuralAttributeTargetImpl<T> de$sciss$proc$impl$AuralAttributeTargetImpl$Multiple$$$outer();
    Code:
       0: aload_0
       1: getfield      #49                 // Field $outer:Lde/sciss/proc/impl/AuralAttributeTargetImpl;
       4: areturn

  private final de.sciss.proc.impl.AuralAttributeTargetImpl$Multiple remove$$anonfun$1();
    Code:
       0: aload_0
       1: areturn

  private final de.sciss.proc.impl.AuralAttributeTargetImpl$State remove$$anonfun$2(de.sciss.lucre.synth.Txn, de.sciss.proc.impl.AuralAttributeTargetImpl$Connected);
    Code:
       0: aload_2
       1: aload_1
       2: invokevirtual #184                // Method de/sciss/proc/impl/AuralAttributeTargetImpl$Connected.dispose:(Lde/sciss/lucre/synth/RT;)V
       5: aload_0
       6: getfield      #49                 // Field $outer:Lde/sciss/proc/impl/AuralAttributeTargetImpl;
       9: getfield      #94                 // Field de/sciss/proc/impl/AuralAttributeTargetImpl.de$sciss$proc$impl$AuralAttributeTargetImpl$$map:Lscala/concurrent/stm/TMap;
      12: getstatic     #99                 // Field de/sciss/lucre/Txn$.MODULE$:Lde/sciss/lucre/Txn$;
      15: aload_1
      16: invokevirtual #103                // Method de/sciss/lucre/Txn$.peer:(Lde/sciss/lucre/TxnLike;)Lscala/concurrent/stm/InTxn;
      19: invokeinterface #188,  2          // InterfaceMethod scala/concurrent/stm/TMap.size:(Lscala/concurrent/stm/InTxn;)I
      24: istore_3
      25: iconst_1
      26: iload_3
      27: if_icmpne     184
      30: getstatic     #193                // Field scala/concurrent/stm/TMap$.MODULE$:Lscala/concurrent/stm/TMap$;
      33: aload_0
      34: getfield      #49                 // Field $outer:Lde/sciss/proc/impl/AuralAttributeTargetImpl;
      37: getfield      #94                 // Field de/sciss/proc/impl/AuralAttributeTargetImpl.de$sciss$proc$impl$AuralAttributeTargetImpl$$map:Lscala/concurrent/stm/TMap;
      40: getstatic     #99                 // Field de/sciss/lucre/Txn$.MODULE$:Lde/sciss/lucre/Txn$;
      43: aload_1
      44: invokevirtual #103                // Method de/sciss/lucre/Txn$.peer:(Lde/sciss/lucre/TxnLike;)Lscala/concurrent/stm/InTxn;
      47: invokevirtual #197                // Method scala/concurrent/stm/TMap$.asMap:(Lscala/concurrent/stm/TMap;Lscala/concurrent/stm/InTxn;)Lscala/concurrent/stm/TMap$View;
      50: invokeinterface #200,  1          // InterfaceMethod scala/concurrent/stm/TMap$View.head:()Ljava/lang/Object;
      55: checkcast     #202                // class scala/Tuple2
      58: astore        5
      60: aload         5
      62: ifnull        98
      65: aload         5
      67: invokevirtual #205                // Method scala/Tuple2._1:()Ljava/lang/Object;
      70: checkcast     #11                 // class de/sciss/proc/AuralAttribute
      73: astore        6
      75: aload         5
      77: invokevirtual #208                // Method scala/Tuple2._2:()Ljava/lang/Object;
      80: checkcast     #20                 // class de/sciss/proc/impl/AuralAttributeTargetImpl$Connected
      83: astore        7
      85: getstatic     #213                // Field scala/Tuple2$.MODULE$:Lscala/Tuple2$;
      88: aload         6
      90: aload         7
      92: invokevirtual #216                // Method scala/Tuple2$.apply:(Ljava/lang/Object;Ljava/lang/Object;)Lscala/Tuple2;
      95: goto          108
      98: new           #218                // class scala/MatchError
     101: dup
     102: aload         5
     104: invokespecial #220                // Method scala/MatchError."<init>":(Ljava/lang/Object;)V
     107: athrow
     108: astore        4
     110: aload         4
     112: invokevirtual #205                // Method scala/Tuple2._1:()Ljava/lang/Object;
     115: checkcast     #11                 // class de/sciss/proc/AuralAttribute
     118: astore        8
     120: aload         4
     122: invokevirtual #208                // Method scala/Tuple2._2:()Ljava/lang/Object;
     125: checkcast     #20                 // class de/sciss/proc/impl/AuralAttributeTargetImpl$Connected
     128: astore        9
     130: aload_0
     131: getfield      #49                 // Field $outer:Lde/sciss/proc/impl/AuralAttributeTargetImpl;
     134: getfield      #69                 // Field de/sciss/proc/impl/AuralAttributeTargetImpl.de$sciss$proc$impl$AuralAttributeTargetImpl$$target:Lde/sciss/proc/AuralNode;
     137: aload_0
     138: getfield      #42                 // Field tgtBusUser:Lde/sciss/lucre/synth/DynamicUser;
     141: aload_1
     142: invokeinterface #226,  3          // InterfaceMethod de/sciss/proc/AuralNode.removeUser:(Lde/sciss/lucre/synth/DynamicUser;Lde/sciss/lucre/synth/RT;)V
     147: aload_0
     148: getfield      #42                 // Field tgtBusUser:Lde/sciss/lucre/synth/DynamicUser;
     151: aload_1
     152: invokeinterface #229,  2          // InterfaceMethod de/sciss/lucre/synth/DynamicUser.dispose:(Lde/sciss/lucre/synth/RT;)V
     157: aload         9
     159: aload_1
     160: invokevirtual #184                // Method de/sciss/proc/impl/AuralAttributeTargetImpl$Connected.dispose:(Lde/sciss/lucre/synth/RT;)V
     163: aload_0
     164: getfield      #49                 // Field $outer:Lde/sciss/proc/impl/AuralAttributeTargetImpl;
     167: invokevirtual #233                // Method de/sciss/proc/impl/AuralAttributeTargetImpl.de$sciss$proc$impl$AuralAttributeTargetImpl$$Empty:()Lde/sciss/proc/impl/AuralAttributeTargetImpl$Empty$;
     170: aload         8
     172: aload         9
     174: invokevirtual #236                // Method de/sciss/proc/impl/AuralAttributeTargetImpl$Connected.value:()Lde/sciss/proc/AuralAttribute$Value;
     177: aload_1
     178: invokevirtual #238                // Method de/sciss/proc/impl/AuralAttributeTargetImpl$Empty$.put:(Lde/sciss/proc/AuralAttribute;Lde/sciss/proc/AuralAttribute$Value;Lde/sciss/lucre/synth/Txn;)Lde/sciss/proc/impl/AuralAttributeTargetImpl$State;
     181: goto          226
     184: iload_3
     185: istore        10
     187: iload         10
     189: iconst_1
     190: if_icmpgt     222
     193: getstatic     #243                // Field scala/runtime/Scala3RunTime$.MODULE$:Lscala/runtime/Scala3RunTime$;
     196: new           #245                // class java/lang/StringBuilder
     199: dup
     200: ldc           #246                // int 12
     202: invokespecial #249                // Method java/lang/StringBuilder."<init>":(I)V
     205: ldc           #251                // String map.size is
     207: invokevirtual #255                // Method java/lang/StringBuilder.append:(Ljava/lang/String;)Ljava/lang/StringBuilder;
     210: iload         10
     212: invokevirtual #258                // Method java/lang/StringBuilder.append:(I)Ljava/lang/StringBuilder;
     215: invokevirtual #260                // Method java/lang/StringBuilder.toString:()Ljava/lang/String;
     218: invokevirtual #264                // Method scala/runtime/Scala3RunTime$.assertFailed:(Ljava/lang/Object;)Lscala/runtime/Nothing$;
     221: athrow
     222: aload_0
     223: goto          226
     226: areturn

  private static java.lang.Object $deserializeLambda$(java.lang.invoke.SerializedLambda);
    Code:
       0: aload_0
       1: invokedynamic #282,  0            // InvokeDynamic #3:lambdaDeserialize:(Ljava/lang/invoke/SerializedLambda;)Ljava/lang/Object;
       6: areturn
}
