Compiled from "AuralTimelineAttribute.scala"
public final class de.sciss.proc.impl.AuralTimelineAttribute<T extends de.sciss.lucre.synth.Txn<T>, I extends de.sciss.lucre.Txn<I>> implements de.sciss.proc.impl.AuralTimelineBase<T, I, de.sciss.proc.AuralAttribute$Target<T>, de.sciss.proc.AuralAttribute<T>>, de.sciss.proc.AuralAttribute<T>, de.sciss.proc.AuralAttribute$Observer<T> {
  public static final long OFFSET$0;

  private scala.concurrent.stm.Ref de$sciss$lucre$impl$ObservableImpl$$obsRef;

  public de.sciss.proc.impl.AuralScheduledBase$IStopped$ IStopped$lzy1;

  public long 0bitmap$1;

  private scala.concurrent.stm.Ref de$sciss$proc$impl$AuralScheduledBase$$internalRef;

  private scala.concurrent.stm.Ref de$sciss$proc$impl$AuralScheduledBase$$prepareSpanRef;

  private scala.concurrent.stm.Ref de$sciss$proc$impl$AuralScheduledBase$$schedEvtToken;

  private scala.concurrent.stm.Ref de$sciss$proc$impl$AuralScheduledBase$$schedGridToken;

  private scala.concurrent.stm.TSet de$sciss$proc$impl$AuralTimelineBase$$playingRef;

  private de.sciss.lucre.IdentMap de$sciss$proc$impl$AuralTimelineBase$$viewMap;

  private de.sciss.lucre.Disposable de$sciss$proc$impl$AuralTimelineBase$$tlObserver;

  private final java.lang.String key;

  private final de.sciss.lucre.Source<T, de.sciss.proc.Timeline<T>> objH;

  private final de.sciss.proc.AuralAttribute$Observer<T> observer;

  private final de.sciss.lucre.data.SkipOctree tree;

  private final de.sciss.proc.AuralContext context;

  private final scala.Function1 iSys;

  private final scala.concurrent.stm.Ref<scala.collection.immutable.IndexedSeq<de.sciss.proc.AuralAttribute<T>>> prefChansElemRef;

  private final scala.concurrent.stm.Ref<java.lang.Object> prefChansNumRef;

  public static <T extends de.sciss.lucre.synth.Txn<T>> de.sciss.proc.AuralAttribute<T> apply(java.lang.String, de.sciss.proc.Timeline<T>, de.sciss.proc.AuralAttribute$Observer<T>, T, de.sciss.proc.AuralContext<T>);
    Code:
       0: getstatic     #103                // Field de/sciss/proc/impl/AuralTimelineAttribute$.MODULE$:Lde/sciss/proc/impl/AuralTimelineAttribute$;
       3: aload_0
       4: aload_1
       5: aload_2
       6: aload_3
       7: aload         4
       9: invokevirtual #105                // Method de/sciss/proc/impl/AuralTimelineAttribute$.apply:(Ljava/lang/String;Lde/sciss/proc/Timeline;Lde/sciss/proc/AuralAttribute$Observer;Lde/sciss/lucre/synth/Txn;Lde/sciss/proc/AuralContext;)Lde/sciss/proc/AuralAttribute;
      12: areturn

  public de.sciss.proc.impl.AuralTimelineAttribute(java.lang.String, de.sciss.lucre.Source<T, de.sciss.proc.Timeline<T>>, de.sciss.proc.AuralAttribute$Observer<T>, de.sciss.lucre.data.SkipOctree<I, de.sciss.lucre.geom.LongPoint2DLike, de.sciss.lucre.geom.LongSquare, scala.Tuple2<de.sciss.span.SpanLike, scala.collection.immutable.IndexedSeq<scala.Tuple2<de.sciss.lucre.Source<T, de.sciss.lucre.Ident<T>>, de.sciss.proc.AuralAttribute<T>>>>>, de.sciss.proc.AuralContext<T>, scala.Function1<T, I>);
    Code:
       0: aload_0
       1: aload_1
       2: putfield      #110                // Field key:Ljava/lang/String;
       5: aload_0
       6: aload_2
       7: putfield      #112                // Field objH:Lde/sciss/lucre/Source;
      10: aload_0
      11: aload_3
      12: putfield      #114                // Field observer:Lde/sciss/proc/AuralAttribute$Observer;
      15: aload_0
      16: aload         4
      18: putfield      #116                // Field tree:Lde/sciss/lucre/data/SkipOctree;
      21: aload_0
      22: aload         5
      24: putfield      #118                // Field context:Lde/sciss/proc/AuralContext;
      27: aload_0
      28: aload         6
      30: putfield      #120                // Field iSys:Lscala/Function1;
      33: aload_0
      34: invokespecial #123                // Method java/lang/Object."<init>":()V
      37: aload_0
      38: invokestatic  #127                // InterfaceMethod de/sciss/lucre/impl/ObservableImpl.$init$:(Lde/sciss/lucre/impl/ObservableImpl;)V
      41: aload_0
      42: invokestatic  #130                // InterfaceMethod de/sciss/proc/impl/AuralScheduledBase.$init$:(Lde/sciss/proc/impl/AuralScheduledBase;)V
      45: aload_0
      46: invokestatic  #133                // InterfaceMethod de/sciss/proc/impl/AuralTimelineBase.$init$:(Lde/sciss/proc/impl/AuralTimelineBase;)V
      49: aload_0
      50: getstatic     #138                // Field scala/concurrent/stm/Ref$.MODULE$:Lscala/concurrent/stm/Ref$;
      53: getstatic     #143                // Field scala/package$.MODULE$:Lscala/package$;
      56: invokevirtual #147                // Method scala/package$.Vector:()Lscala/collection/immutable/Vector$;
      59: invokevirtual #153                // Method scala/collection/immutable/Vector$.empty:()Lscala/collection/immutable/Vector;
      62: invokevirtual #156                // Method scala/concurrent/stm/Ref$.apply:(Ljava/lang/Object;)Lscala/concurrent/stm/Ref;
      65: putfield      #158                // Field prefChansElemRef:Lscala/concurrent/stm/Ref;
      68: aload_0
      69: getstatic     #138                // Field scala/concurrent/stm/Ref$.MODULE$:Lscala/concurrent/stm/Ref$;
      72: bipush        -2
      74: invokevirtual #161                // Method scala/concurrent/stm/Ref$.apply:(I)Lscala/concurrent/stm/Ref;
      77: putfield      #163                // Field prefChansNumRef:Lscala/concurrent/stm/Ref;
      80: invokestatic  #168                // Method scala/runtime/Statics.releaseFence:()V
      83: return

  private static {};
    Code:
       0: getstatic     #176                // Field scala/runtime/LazyVals$.MODULE$:Lscala/runtime/LazyVals$;
       3: ldc           #2                  // class de/sciss/proc/impl/AuralTimelineAttribute
       5: ldc           #177                // String 0bitmap$1
       7: invokevirtual #181                // Method scala/runtime/LazyVals$.getOffset:(Ljava/lang/Class;Ljava/lang/String;)J
      10: putstatic     #183                // Field OFFSET$0:J
      13: return

  public de.sciss.lucre.Disposable reactNow(scala.Function1, de.sciss.lucre.Txn);
    Code:
       0: aload_0
       1: aload_1
       2: aload_2
       3: invokestatic  #191                // InterfaceMethod de/sciss/proc/ViewBase.reactNow$:(Lde/sciss/proc/ViewBase;Lscala/Function1;Lde/sciss/lucre/Txn;)Lde/sciss/lucre/Disposable;
       6: areturn

  public scala.concurrent.stm.Ref de$sciss$lucre$impl$ObservableImpl$$obsRef();
    Code:
       0: aload_0
       1: getfield      #195                // Field de$sciss$lucre$impl$ObservableImpl$$obsRef:Lscala/concurrent/stm/Ref;
       4: areturn

  public void de$sciss$lucre$impl$ObservableImpl$_setter_$de$sciss$lucre$impl$ObservableImpl$$obsRef_$eq(scala.concurrent.stm.Ref);
    Code:
       0: aload_0
       1: aload_1
       2: putfield      #195                // Field de$sciss$lucre$impl$ObservableImpl$$obsRef:Lscala/concurrent/stm/Ref;
       5: return

  public void fire(java.lang.Object, de.sciss.lucre.Txn);
    Code:
       0: aload_0
       1: aload_1
       2: aload_2
       3: invokestatic  #205                // InterfaceMethod de/sciss/lucre/impl/ObservableImpl.fire$:(Lde/sciss/lucre/impl/ObservableImpl;Ljava/lang/Object;Lde/sciss/lucre/Txn;)V
       6: return

  public de.sciss.lucre.Disposable react(scala.Function1, de.sciss.lucre.Txn);
    Code:
       0: aload_0
       1: aload_1
       2: aload_2
       3: invokestatic  #211                // InterfaceMethod de/sciss/lucre/impl/ObservableImpl.react$:(Lde/sciss/lucre/impl/ObservableImpl;Lscala/Function1;Lde/sciss/lucre/Txn;)Lde/sciss/lucre/Disposable;
       6: areturn

  public final de.sciss.proc.impl.AuralScheduledBase$IStopped$ IStopped();
    Code:
       0: getstatic     #176                // Field scala/runtime/LazyVals$.MODULE$:Lscala/runtime/LazyVals$;
       3: aload_0
       4: getstatic     #183                // Field OFFSET$0:J
       7: invokevirtual #219                // Method scala/runtime/LazyVals$.get:(Ljava/lang/Object;J)J
      10: lstore_1
      11: getstatic     #176                // Field scala/runtime/LazyVals$.MODULE$:Lscala/runtime/LazyVals$;
      14: lload_1
      15: iconst_0
      16: invokevirtual #223                // Method scala/runtime/LazyVals$.STATE:(JI)J
      19: lstore_3
      20: lload_3
      21: ldc2_w        #224                // long 3l
      24: lcmp
      25: ifne          36
      28: aload_0
      29: getfield      #227                // Field IStopped$lzy1:Lde/sciss/proc/impl/AuralScheduledBase$IStopped$;
      32: areturn
      33: nop
      34: nop
      35: athrow
      36: lload_3
      37: lconst_0
      38: lcmp
      39: ifne          116
      42: getstatic     #176                // Field scala/runtime/LazyVals$.MODULE$:Lscala/runtime/LazyVals$;
      45: aload_0
      46: getstatic     #183                // Field OFFSET$0:J
      49: lload_1
      50: iconst_1
      51: iconst_0
      52: invokevirtual #231                // Method scala/runtime/LazyVals$.CAS:(Ljava/lang/Object;JJII)Z
      55: ifeq          113
      58: new           #44                 // class de/sciss/proc/impl/AuralScheduledBase$IStopped$
      61: dup
      62: aload_0
      63: invokespecial #233                // Method de/sciss/proc/impl/AuralScheduledBase$IStopped$."<init>":(Lde/sciss/proc/impl/AuralScheduledBase;)V
      66: astore        5
      68: aload_0
      69: aload         5
      71: putfield      #227                // Field IStopped$lzy1:Lde/sciss/proc/impl/AuralScheduledBase$IStopped$;
      74: getstatic     #176                // Field scala/runtime/LazyVals$.MODULE$:Lscala/runtime/LazyVals$;
      77: aload_0
      78: getstatic     #183                // Field OFFSET$0:J
      81: iconst_3
      82: iconst_0
      83: invokevirtual #237                // Method scala/runtime/LazyVals$.setFlag:(Ljava/lang/Object;JII)V
      86: aload         5
      88: areturn
      89: nop
      90: nop
      91: athrow
      92: astore        6
      94: getstatic     #176                // Field scala/runtime/LazyVals$.MODULE$:Lscala/runtime/LazyVals$;
      97: aload_0
      98: getstatic     #183                // Field OFFSET$0:J
     101: iconst_0
     102: iconst_0
     103: invokevirtual #237                // Method scala/runtime/LazyVals$.setFlag:(Ljava/lang/Object;JII)V
     106: aload         6
     108: athrow
     109: nop
     110: nop
     111: athrow
     112: athrow
     113: goto          128
     116: getstatic     #176                // Field scala/runtime/LazyVals$.MODULE$:Lscala/runtime/LazyVals$;
     119: aload_0
     120: getstatic     #183                // Field OFFSET$0:J
     123: lload_1
     124: iconst_0
     125: invokevirtual #241                // Method scala/runtime/LazyVals$.wait4Notification:(Ljava/lang/Object;JJI)V
     128: goto          0
     131: nop
     132: athrow
    Exception table:
       from    to  target type
          58    89    92   Class java/lang/Throwable

  public scala.concurrent.stm.Ref de$sciss$proc$impl$AuralScheduledBase$$internalRef();
    Code:
       0: aload_0
       1: getfield      #243                // Field de$sciss$proc$impl$AuralScheduledBase$$internalRef:Lscala/concurrent/stm/Ref;
       4: areturn

  public scala.concurrent.stm.Ref de$sciss$proc$impl$AuralScheduledBase$$prepareSpanRef();
    Code:
       0: aload_0
       1: getfield      #245                // Field de$sciss$proc$impl$AuralScheduledBase$$prepareSpanRef:Lscala/concurrent/stm/Ref;
       4: areturn

  public scala.concurrent.stm.Ref de$sciss$proc$impl$AuralScheduledBase$$schedEvtToken();
    Code:
       0: aload_0
       1: getfield      #247                // Field de$sciss$proc$impl$AuralScheduledBase$$schedEvtToken:Lscala/concurrent/stm/Ref;
       4: areturn

  public scala.concurrent.stm.Ref de$sciss$proc$impl$AuralScheduledBase$$schedGridToken();
    Code:
       0: aload_0
       1: getfield      #249                // Field de$sciss$proc$impl$AuralScheduledBase$$schedGridToken:Lscala/concurrent/stm/Ref;
       4: areturn

  public void de$sciss$proc$impl$AuralScheduledBase$_setter_$de$sciss$proc$impl$AuralScheduledBase$$internalRef_$eq(scala.concurrent.stm.Ref);
    Code:
       0: aload_0
       1: aload_1
       2: putfield      #243                // Field de$sciss$proc$impl$AuralScheduledBase$$internalRef:Lscala/concurrent/stm/Ref;
       5: return

  public void de$sciss$proc$impl$AuralScheduledBase$_setter_$de$sciss$proc$impl$AuralScheduledBase$$prepareSpanRef_$eq(scala.concurrent.stm.Ref);
    Code:
       0: aload_0
       1: aload_1
       2: putfield      #245                // Field de$sciss$proc$impl$AuralScheduledBase$$prepareSpanRef:Lscala/concurrent/stm/Ref;
       5: return

  public void de$sciss$proc$impl$AuralScheduledBase$_setter_$de$sciss$proc$impl$AuralScheduledBase$$schedEvtToken_$eq(scala.concurrent.stm.Ref);
    Code:
       0: aload_0
       1: aload_1
       2: putfield      #247                // Field de$sciss$proc$impl$AuralScheduledBase$$schedEvtToken:Lscala/concurrent/stm/Ref;
       5: return

  public void de$sciss$proc$impl$AuralScheduledBase$_setter_$de$sciss$proc$impl$AuralScheduledBase$$schedGridToken_$eq(scala.concurrent.stm.Ref);
    Code:
       0: aload_0
       1: aload_1
       2: putfield      #249                // Field de$sciss$proc$impl$AuralScheduledBase$$schedGridToken:Lscala/concurrent/stm/Ref;
       5: return

  public de.sciss.proc.Runner$State state(de.sciss.lucre.Txn);
    Code:
       0: aload_0
       1: aload_1
       2: invokestatic  #259                // InterfaceMethod de/sciss/proc/impl/AuralScheduledBase.state$:(Lde/sciss/proc/impl/AuralScheduledBase;Lde/sciss/lucre/Txn;)Lde/sciss/proc/Runner$State;
       5: areturn

  public de.sciss.proc.impl.AuralScheduledBase$InternalState internalState(de.sciss.lucre.Txn);
    Code:
       0: aload_0
       1: aload_1
       2: invokestatic  #265                // InterfaceMethod de/sciss/proc/impl/AuralScheduledBase.internalState$:(Lde/sciss/proc/impl/AuralScheduledBase;Lde/sciss/lucre/Txn;)Lde/sciss/proc/impl/AuralScheduledBase$InternalState;
       5: areturn

  public void internalState_$eq(de.sciss.proc.impl.AuralScheduledBase$InternalState, de.sciss.lucre.Txn);
    Code:
       0: aload_0
       1: aload_1
       2: aload_2
       3: invokestatic  #272                // InterfaceMethod de/sciss/proc/impl/AuralScheduledBase.internalState_$eq$:(Lde/sciss/proc/impl/AuralScheduledBase;Lde/sciss/proc/impl/AuralScheduledBase$InternalState;Lde/sciss/lucre/Txn;)V
       6: return

  public scala.Option targetOption(de.sciss.lucre.Txn);
    Code:
       0: aload_0
       1: aload_1
       2: invokestatic  #279                // InterfaceMethod de/sciss/proc/impl/AuralScheduledBase.targetOption$:(Lde/sciss/proc/impl/AuralScheduledBase;Lde/sciss/lucre/Txn;)Lscala/Option;
       5: areturn

  public void childPreparedOrRemoved(de.sciss.proc.AuralViewBase, de.sciss.lucre.Txn);
    Code:
       0: aload_0
       1: aload_1
       2: aload_2
       3: invokestatic  #286                // InterfaceMethod de/sciss/proc/impl/AuralScheduledBase.childPreparedOrRemoved$:(Lde/sciss/proc/impl/AuralScheduledBase;Lde/sciss/proc/AuralViewBase;Lde/sciss/lucre/Txn;)V
       6: return

  public void prepare(de.sciss.proc.TimeRef$Option, de.sciss.lucre.Txn);
    Code:
       0: aload_0
       1: aload_1
       2: aload_2
       3: invokestatic  #294                // InterfaceMethod de/sciss/proc/impl/AuralScheduledBase.prepare$:(Lde/sciss/proc/impl/AuralScheduledBase;Lde/sciss/proc/TimeRef$Option;Lde/sciss/lucre/Txn;)V
       6: return

  public de.sciss.proc.impl.AuralScheduledBase$Scheduled scheduledEvent(de.sciss.lucre.Txn);
    Code:
       0: aload_0
       1: aload_1
       2: invokestatic  #301                // InterfaceMethod de/sciss/proc/impl/AuralScheduledBase.scheduledEvent$:(Lde/sciss/proc/impl/AuralScheduledBase;Lde/sciss/lucre/Txn;)Lde/sciss/proc/impl/AuralScheduledBase$Scheduled;
       5: areturn

  public de.sciss.proc.impl.AuralScheduledBase$Scheduled scheduledGrid(de.sciss.lucre.Txn);
    Code:
       0: aload_0
       1: aload_1
       2: invokestatic  #305                // InterfaceMethod de/sciss/proc/impl/AuralScheduledBase.scheduledGrid$:(Lde/sciss/proc/impl/AuralScheduledBase;Lde/sciss/lucre/Txn;)Lde/sciss/proc/impl/AuralScheduledBase$Scheduled;
       5: areturn

  public de.sciss.span.Span prepareSpan(de.sciss.lucre.Txn);
    Code:
       0: aload_0
       1: aload_1
       2: invokestatic  #311                // InterfaceMethod de/sciss/proc/impl/AuralScheduledBase.prepareSpan$:(Lde/sciss/proc/impl/AuralScheduledBase;Lde/sciss/lucre/Txn;)Lde/sciss/span/Span;
       5: areturn

  public void run(de.sciss.proc.TimeRef$Option, java.lang.Object, de.sciss.lucre.Txn);
    Code:
       0: aload_0
       1: aload_1
       2: aload_2
       3: aload_3
       4: invokestatic  #318                // InterfaceMethod de/sciss/proc/impl/AuralScheduledBase.run$:(Lde/sciss/proc/impl/AuralScheduledBase;Lde/sciss/proc/TimeRef$Option;Ljava/lang/Object;Lde/sciss/lucre/Txn;)V
       7: return

  public void stop(de.sciss.lucre.Txn);
    Code:
       0: aload_0
       1: aload_1
       2: invokestatic  #324                // InterfaceMethod de/sciss/proc/impl/AuralScheduledBase.stop$:(Lde/sciss/proc/impl/AuralScheduledBase;Lde/sciss/lucre/Txn;)V
       5: return

  public void elemAdded(java.lang.Object, de.sciss.span.SpanLike, java.lang.Object, de.sciss.lucre.Txn);
    Code:
       0: aload_0
       1: aload_1
       2: aload_2
       3: aload_3
       4: aload         4
       6: invokestatic  #333                // InterfaceMethod de/sciss/proc/impl/AuralScheduledBase.elemAdded$:(Lde/sciss/proc/impl/AuralScheduledBase;Ljava/lang/Object;Lde/sciss/span/SpanLike;Ljava/lang/Object;Lde/sciss/lucre/Txn;)V
       9: return

  public void elemRemoved(java.lang.Object, boolean, de.sciss.lucre.Txn);
    Code:
       0: aload_0
       1: aload_1
       2: iload_2
       3: aload_3
       4: invokestatic  #342                // InterfaceMethod de/sciss/proc/impl/AuralScheduledBase.elemRemoved$:(Lde/sciss/proc/impl/AuralScheduledBase;Ljava/lang/Object;ZLde/sciss/lucre/Txn;)V
       7: return

  public scala.concurrent.stm.TSet de$sciss$proc$impl$AuralTimelineBase$$playingRef();
    Code:
       0: aload_0
       1: getfield      #346                // Field de$sciss$proc$impl$AuralTimelineBase$$playingRef:Lscala/concurrent/stm/TSet;
       4: areturn

  public de.sciss.lucre.IdentMap de$sciss$proc$impl$AuralTimelineBase$$viewMap();
    Code:
       0: aload_0
       1: getfield      #349                // Field de$sciss$proc$impl$AuralTimelineBase$$viewMap:Lde/sciss/lucre/IdentMap;
       4: areturn

  public de.sciss.lucre.Disposable de$sciss$proc$impl$AuralTimelineBase$$tlObserver();
    Code:
       0: aload_0
       1: getfield      #352                // Field de$sciss$proc$impl$AuralTimelineBase$$tlObserver:Lde/sciss/lucre/Disposable;
       4: areturn

  public void de$sciss$proc$impl$AuralTimelineBase$$viewMap_$eq(de.sciss.lucre.IdentMap);
    Code:
       0: aload_0
       1: aload_1
       2: putfield      #349                // Field de$sciss$proc$impl$AuralTimelineBase$$viewMap:Lde/sciss/lucre/IdentMap;
       5: return

  public void de$sciss$proc$impl$AuralTimelineBase$$tlObserver_$eq(de.sciss.lucre.Disposable);
    Code:
       0: aload_0
       1: aload_1
       2: putfield      #352                // Field de$sciss$proc$impl$AuralTimelineBase$$tlObserver:Lde/sciss/lucre/Disposable;
       5: return

  public void de$sciss$proc$impl$AuralTimelineBase$_setter_$de$sciss$proc$impl$AuralTimelineBase$$playingRef_$eq(scala.concurrent.stm.TSet);
    Code:
       0: aload_0
       1: aload_1
       2: putfield      #346                // Field de$sciss$proc$impl$AuralTimelineBase$$playingRef:Lscala/concurrent/stm/TSet;
       5: return

  public de.sciss.proc.AuralViewBase elemFromHandle(de.sciss.proc.impl.AuralTimelineBase$ElemHandle);
    Code:
       0: aload_0
       1: aload_1
       2: invokestatic  #365                // InterfaceMethod de/sciss/proc/impl/AuralTimelineBase.elemFromHandle$:(Lde/sciss/proc/impl/AuralTimelineBase;Lde/sciss/proc/impl/AuralTimelineBase$ElemHandle;)Lde/sciss/proc/AuralViewBase;
       5: areturn

  public scala.collection.immutable.Set views(de.sciss.lucre.Txn);
    Code:
       0: aload_0
       1: aload_1
       2: invokestatic  #372                // InterfaceMethod de/sciss/proc/impl/AuralTimelineBase.views$:(Lde/sciss/proc/impl/AuralTimelineBase;Lde/sciss/lucre/Txn;)Lscala/collection/immutable/Set;
       5: areturn

  public de.sciss.lucre.Obj$Type tpe();
    Code:
       0: aload_0
       1: invokestatic  #378                // InterfaceMethod de/sciss/proc/impl/AuralTimelineBase.tpe$:(Lde/sciss/proc/impl/AuralTimelineBase;)Lde/sciss/lucre/Obj$Type;
       4: areturn

  public long viewEventAfter(long, de.sciss.lucre.Txn);
    Code:
       0: aload_0
       1: lload_1
       2: aload_3
       3: invokestatic  #385                // InterfaceMethod de/sciss/proc/impl/AuralTimelineBase.viewEventAfter$:(Lde/sciss/proc/impl/AuralTimelineBase;JLde/sciss/lucre/Txn;)J
       6: lreturn

  public long modelEventAfter(long, de.sciss.lucre.Txn);
    Code:
       0: aload_0
       1: lload_1
       2: aload_3
       3: invokestatic  #389                // InterfaceMethod de/sciss/proc/impl/AuralTimelineBase.modelEventAfter$:(Lde/sciss/proc/impl/AuralTimelineBase;JLde/sciss/lucre/Txn;)J
       6: lreturn

  public void processPlay(de.sciss.proc.TimeRef, java.lang.Object, de.sciss.lucre.Txn);
    Code:
       0: aload_0
       1: aload_1
       2: aload_2
       3: aload_3
       4: invokestatic  #395                // InterfaceMethod de/sciss/proc/impl/AuralTimelineBase.processPlay$:(Lde/sciss/proc/impl/AuralTimelineBase;Lde/sciss/proc/TimeRef;Ljava/lang/Object;Lde/sciss/lucre/Txn;)V
       7: return

  public scala.collection.Iterator processPrepare(de.sciss.span.Span, de.sciss.proc.TimeRef, boolean, de.sciss.lucre.Txn);
    Code:
       0: aload_0
       1: aload_1
       2: aload_2
       3: iload_3
       4: aload         4
       6: invokestatic  #403                // InterfaceMethod de/sciss/proc/impl/AuralTimelineBase.processPrepare$:(Lde/sciss/proc/impl/AuralTimelineBase;Lde/sciss/span/Span;Lde/sciss/proc/TimeRef;ZLde/sciss/lucre/Txn;)Lscala/collection/Iterator;
       9: areturn

  public void playView(de.sciss.proc.impl.AuralTimelineBase$ElemHandle, de.sciss.proc.TimeRef$Option, java.lang.Object, de.sciss.lucre.Txn);
    Code:
       0: aload_0
       1: aload_1
       2: aload_2
       3: aload_3
       4: aload         4
       6: invokestatic  #410                // InterfaceMethod de/sciss/proc/impl/AuralTimelineBase.playView$:(Lde/sciss/proc/impl/AuralTimelineBase;Lde/sciss/proc/impl/AuralTimelineBase$ElemHandle;Lde/sciss/proc/TimeRef$Option;Ljava/lang/Object;Lde/sciss/lucre/Txn;)V
       9: return

  public void stopView(de.sciss.proc.impl.AuralTimelineBase$ElemHandle, de.sciss.lucre.Txn);
    Code:
       0: aload_0
       1: aload_1
       2: aload_2
       3: invokestatic  #416                // InterfaceMethod de/sciss/proc/impl/AuralTimelineBase.stopView$:(Lde/sciss/proc/impl/AuralTimelineBase;Lde/sciss/proc/impl/AuralTimelineBase$ElemHandle;Lde/sciss/lucre/Txn;)V
       6: return

  public void stopViews(de.sciss.lucre.Txn);
    Code:
       0: aload_0
       1: aload_1
       2: invokestatic  #421                // InterfaceMethod de/sciss/proc/impl/AuralTimelineBase.stopViews$:(Lde/sciss/proc/impl/AuralTimelineBase;Lde/sciss/lucre/Txn;)V
       5: return

  public void processEvent(de.sciss.proc.impl.AuralScheduledBase$IPlaying, de.sciss.proc.TimeRef, de.sciss.lucre.Txn);
    Code:
       0: aload_0
       1: aload_1
       2: aload_2
       3: aload_3
       4: invokestatic  #428                // InterfaceMethod de/sciss/proc/impl/AuralTimelineBase.processEvent$:(Lde/sciss/proc/impl/AuralTimelineBase;Lde/sciss/proc/impl/AuralScheduledBase$IPlaying;Lde/sciss/proc/TimeRef;Lde/sciss/lucre/Txn;)V
       7: return

  public de.sciss.proc.impl.AuralTimelineBase init(de.sciss.proc.Timeline, de.sciss.lucre.Txn);
    Code:
       0: aload_0
       1: aload_1
       2: aload_2
       3: invokestatic  #436                // InterfaceMethod de/sciss/proc/impl/AuralTimelineBase.init$:(Lde/sciss/proc/impl/AuralTimelineBase;Lde/sciss/proc/Timeline;Lde/sciss/lucre/Txn;)Lde/sciss/proc/impl/AuralTimelineBase;
       6: areturn

  public scala.Option getView(de.sciss.lucre.BiGroup$Entry, de.sciss.lucre.Txn);
    Code:
       0: aload_0
       1: aload_1
       2: aload_2
       3: invokestatic  #444                // InterfaceMethod de/sciss/proc/impl/AuralTimelineBase.getView$:(Lde/sciss/proc/impl/AuralTimelineBase;Lde/sciss/lucre/BiGroup$Entry;Lde/sciss/lucre/Txn;)Lscala/Option;
       6: areturn

  public scala.Option getViewById(de.sciss.lucre.Ident, de.sciss.lucre.Txn);
    Code:
       0: aload_0
       1: aload_1
       2: aload_2
       3: invokestatic  #452                // InterfaceMethod de/sciss/proc/impl/AuralTimelineBase.getViewById$:(Lde/sciss/proc/impl/AuralTimelineBase;Lde/sciss/lucre/Ident;Lde/sciss/lucre/Txn;)Lscala/Option;
       6: areturn

  public void addObject(de.sciss.lucre.Ident, de.sciss.lucre.SpanLikeObj, de.sciss.lucre.Obj, de.sciss.lucre.Txn);
    Code:
       0: aload_0
       1: aload_1
       2: aload_2
       3: aload_3
       4: aload         4
       6: invokestatic  #459                // InterfaceMethod de/sciss/proc/impl/AuralTimelineBase.addObject$:(Lde/sciss/proc/impl/AuralTimelineBase;Lde/sciss/lucre/Ident;Lde/sciss/lucre/SpanLikeObj;Lde/sciss/lucre/Obj;Lde/sciss/lucre/Txn;)V
       9: return

  public void removeObject(de.sciss.lucre.Ident, de.sciss.lucre.SpanLikeObj, de.sciss.lucre.Obj, de.sciss.lucre.Txn);
    Code:
       0: aload_0
       1: aload_1
       2: aload_2
       3: aload_3
       4: aload         4
       6: invokestatic  #465                // InterfaceMethod de/sciss/proc/impl/AuralTimelineBase.removeObject$:(Lde/sciss/proc/impl/AuralTimelineBase;Lde/sciss/lucre/Ident;Lde/sciss/lucre/SpanLikeObj;Lde/sciss/lucre/Obj;Lde/sciss/lucre/Txn;)V
       9: return

  public de.sciss.proc.impl.AuralTimelineBase$ElemHandle mkView(de.sciss.lucre.Ident, de.sciss.span.SpanLike, de.sciss.lucre.Obj, de.sciss.lucre.Txn);
    Code:
       0: aload_0
       1: aload_1
       2: aload_2
       3: aload_3
       4: aload         4
       6: invokestatic  #472                // InterfaceMethod de/sciss/proc/impl/AuralTimelineBase.mkView$:(Lde/sciss/proc/impl/AuralTimelineBase;Lde/sciss/lucre/Ident;Lde/sciss/span/SpanLike;Lde/sciss/lucre/Obj;Lde/sciss/lucre/Txn;)Lde/sciss/proc/impl/AuralTimelineBase$ElemHandle;
       9: areturn

  public boolean checkReschedule(de.sciss.proc.impl.AuralTimelineBase$ElemHandle, long, long, boolean, de.sciss.lucre.Txn);
    Code:
       0: aload_0
       1: aload_1
       2: lload_2
       3: lload         4
       5: iload         6
       7: aload         7
       9: invokestatic  #480                // InterfaceMethod de/sciss/proc/impl/AuralTimelineBase.checkReschedule$:(Lde/sciss/proc/impl/AuralTimelineBase;Lde/sciss/proc/impl/AuralTimelineBase$ElemHandle;JJZLde/sciss/lucre/Txn;)Z
      12: ireturn

  public void de$sciss$proc$impl$AuralTimelineBase$$super$dispose(de.sciss.lucre.synth.Txn);
    Code:
       0: aload_0
       1: aload_1
       2: invokestatic  #485                // InterfaceMethod de/sciss/proc/impl/AuralScheduledBase.dispose$:(Lde/sciss/proc/impl/AuralScheduledBase;Lde/sciss/lucre/Txn;)V
       5: return

  public java.lang.String key();
    Code:
       0: aload_0
       1: getfield      #110                // Field key:Ljava/lang/String;
       4: areturn

  public de.sciss.lucre.data.SkipOctree<I, de.sciss.lucre.geom.LongPoint2DLike, de.sciss.lucre.geom.LongSquare, scala.Tuple2<de.sciss.span.SpanLike, scala.collection.immutable.IndexedSeq<scala.Tuple2<de.sciss.lucre.Source<T, de.sciss.lucre.Ident<T>>, de.sciss.proc.AuralAttribute<T>>>>> tree();
    Code:
       0: aload_0
       1: getfield      #116                // Field tree:Lde/sciss/lucre/data/SkipOctree;
       4: areturn

  public de.sciss.proc.AuralContext<T> context();
    Code:
       0: aload_0
       1: getfield      #118                // Field context:Lde/sciss/proc/AuralContext;
       4: areturn

  public scala.Function1<T, I> iSys();
    Code:
       0: aload_0
       1: getfield      #120                // Field iSys:Lscala/Function1;
       4: areturn

  public de.sciss.proc.Timeline<T> obj(T);
    Code:
       0: aload_0
       1: getfield      #112                // Field objH:Lde/sciss/lucre/Source;
       4: aload_1
       5: invokeinterface #500,  2          // InterfaceMethod de/sciss/lucre/Source.apply:(Ljava/lang/Object;)Ljava/lang/Object;
      10: checkcast     #502                // class de/sciss/proc/Timeline
      13: areturn

  public de.sciss.proc.AuralAttribute<T> makeViewElem(de.sciss.lucre.Obj<T>, T);
    Code:
       0: getstatic     #510                // Field de/sciss/proc/AuralAttribute$.MODULE$:Lde/sciss/proc/AuralAttribute$;
       3: aload_0
       4: invokevirtual #512                // Method key:()Ljava/lang/String;
       7: aload_1
       8: aload_0
       9: aload_2
      10: aload_0
      11: invokevirtual #514                // Method context:()Lde/sciss/proc/AuralContext;
      14: invokevirtual #517                // Method de/sciss/proc/AuralAttribute$.apply:(Ljava/lang/String;Lde/sciss/lucre/Obj;Lde/sciss/proc/AuralAttribute$Observer;Lde/sciss/lucre/synth/Txn;Lde/sciss/proc/AuralContext;)Lde/sciss/proc/AuralAttribute;
      17: areturn

  public void viewPlaying(de.sciss.proc.impl.AuralTimelineBase$ElemHandle<T, de.sciss.proc.AuralAttribute<T>>, T);
    Code:
       0: return

  public void viewStopped(de.sciss.proc.impl.AuralTimelineBase$ElemHandle<T, de.sciss.proc.AuralAttribute<T>>, T);
    Code:
       0: return

  public int preferredNumChannels(T);
    Code:
       0: aload_0
       1: getfield      #163                // Field prefChansNumRef:Lscala/concurrent/stm/Ref;
       4: getstatic     #529                // Field de/sciss/lucre/Txn$.MODULE$:Lde/sciss/lucre/Txn$;
       7: aload_1
       8: invokevirtual #533                // Method de/sciss/lucre/Txn$.peer:(Lde/sciss/lucre/TxnLike;)Lscala/concurrent/stm/InTxn;
      11: invokeinterface #536,  2          // InterfaceMethod scala/concurrent/stm/Ref.apply:(Ljava/lang/Object;)Ljava/lang/Object;
      16: invokestatic  #542                // Method scala/runtime/BoxesRunTime.unboxToInt:(Ljava/lang/Object;)I
      19: istore_2
      20: iload_2
      21: bipush        -2
      23: if_icmple     28
      26: iload_2
      27: ireturn
      28: aload_0
      29: getfield      #112                // Field objH:Lde/sciss/lucre/Source;
      32: aload_1
      33: invokeinterface #500,  2          // InterfaceMethod de/sciss/lucre/Source.apply:(Ljava/lang/Object;)Ljava/lang/Object;
      38: checkcast     #502                // class de/sciss/proc/Timeline
      41: astore_3
      42: aload_3
      43: aload_1
      44: invokeinterface #545,  2          // InterfaceMethod de/sciss/proc/Timeline.firstEvent:(Lde/sciss/lucre/Txn;)Lscala/Option;
      49: invokedynamic #565,  0            // InvokeDynamic #0:apply:()Lscala/Function0;
      54: invokevirtual #571                // Method scala/Option.getOrElse:(Lscala/Function0;)Ljava/lang/Object;
      57: invokestatic  #575                // Method scala/runtime/BoxesRunTime.unboxToLong:(Ljava/lang/Object;)J
      60: lstore        4
      62: lload         4
      64: lconst_0
      65: lcmp
      66: ifge          71
      69: iconst_m1
      70: ireturn
      71: aload_3
      72: lload         4
      74: aload_1
      75: invokeinterface #579,  4          // InterfaceMethod de/sciss/proc/Timeline.intersect:(JLde/sciss/lucre/Txn;)Lscala/collection/Iterator;
      80: astore        6
      82: aload         6
      84: invokeinterface #585,  1          // InterfaceMethod scala/collection/Iterator.isEmpty:()Z
      89: ifeq          94
      92: iconst_m1
      93: ireturn
      94: aload         6
      96: invokedynamic #594,  0            // InvokeDynamic #1:apply:()Lscala/Function1;
     101: invokeinterface #598,  2          // InterfaceMethod scala/collection/Iterator.flatMap:(Lscala/Function1;)Lscala/collection/Iterator;
     106: invokeinterface #601,  1          // InterfaceMethod scala/collection/Iterator.toVector:()Lscala/collection/immutable/Vector;
     111: astore        7
     113: aload         7
     115: aload_0
     116: aload_1
     117: invokedynamic #611,  0            // InvokeDynamic #2:apply:(Lde/sciss/proc/impl/AuralTimelineAttribute;Lde/sciss/lucre/synth/Txn;)Lscala/Function1;
     122: invokevirtual #617                // Method scala/collection/immutable/Vector.map:(Lscala/Function1;)Ljava/lang/Object;
     125: checkcast     #613                // class scala/collection/immutable/Vector
     128: astore        8
     130: aload_0
     131: getfield      #158                // Field prefChansElemRef:Lscala/concurrent/stm/Ref;
     134: aload         8
     136: getstatic     #529                // Field de/sciss/lucre/Txn$.MODULE$:Lde/sciss/lucre/Txn$;
     139: aload_1
     140: invokevirtual #533                // Method de/sciss/lucre/Txn$.peer:(Lde/sciss/lucre/TxnLike;)Lscala/concurrent/stm/InTxn;
     143: invokeinterface #621,  3          // InterfaceMethod scala/concurrent/stm/Ref.swap:(Ljava/lang/Object;Ljava/lang/Object;)Ljava/lang/Object;
     148: checkcast     #623                // class scala/collection/IterableOnceOps
     151: aload_1
     152: invokedynamic #636,  0            // InvokeDynamic #3:applyVoid:(Lde/sciss/lucre/synth/Txn;)Lscala/runtime/function/JProcedure1;
     157: invokeinterface #640,  2          // InterfaceMethod scala/collection/IterableOnceOps.foreach:(Lscala/Function1;)V
     162: aload_1
     163: aload         8
     165: iconst_m1
     166: invokestatic  #644                // Method loop$1:(Lde/sciss/lucre/synth/Txn;Lscala/collection/immutable/Vector;I)I
     169: istore        9
     171: aload_0
     172: getfield      #163                // Field prefChansNumRef:Lscala/concurrent/stm/Ref;
     175: iload         9
     177: invokestatic  #648                // Method scala/runtime/BoxesRunTime.boxToInteger:(I)Ljava/lang/Integer;
     180: getstatic     #529                // Field de/sciss/lucre/Txn$.MODULE$:Lde/sciss/lucre/Txn$;
     183: aload_1
     184: invokevirtual #533                // Method de/sciss/lucre/Txn$.peer:(Lde/sciss/lucre/TxnLike;)Lscala/concurrent/stm/InTxn;
     187: invokeinterface #651,  3          // InterfaceMethod scala/concurrent/stm/Ref.update:(Ljava/lang/Object;Ljava/lang/Object;)V
     192: iload         9
     194: ireturn

  public void attrNumChannelsChanged(de.sciss.proc.AuralAttribute<T>, T);
    Code:
       0: aload_0
       1: getfield      #158                // Field prefChansElemRef:Lscala/concurrent/stm/Ref;
       4: getstatic     #529                // Field de/sciss/lucre/Txn$.MODULE$:Lde/sciss/lucre/Txn$;
       7: aload_2
       8: invokevirtual #533                // Method de/sciss/lucre/Txn$.peer:(Lde/sciss/lucre/TxnLike;)Lscala/concurrent/stm/InTxn;
      11: invokeinterface #536,  2          // InterfaceMethod scala/concurrent/stm/Ref.apply:(Ljava/lang/Object;)Ljava/lang/Object;
      16: checkcast     #666                // class scala/collection/SeqOps
      19: aload_1
      20: invokeinterface #670,  2          // InterfaceMethod scala/collection/SeqOps.contains:(Ljava/lang/Object;)Z
      25: ifeq          60
      28: aload_0
      29: getfield      #163                // Field prefChansNumRef:Lscala/concurrent/stm/Ref;
      32: bipush        -2
      34: invokestatic  #648                // Method scala/runtime/BoxesRunTime.boxToInteger:(I)Ljava/lang/Integer;
      37: getstatic     #529                // Field de/sciss/lucre/Txn$.MODULE$:Lde/sciss/lucre/Txn$;
      40: aload_2
      41: invokevirtual #533                // Method de/sciss/lucre/Txn$.peer:(Lde/sciss/lucre/TxnLike;)Lscala/concurrent/stm/InTxn;
      44: invokeinterface #651,  3          // InterfaceMethod scala/concurrent/stm/Ref.update:(Ljava/lang/Object;Ljava/lang/Object;)V
      49: aload_0
      50: getfield      #114                // Field observer:Lde/sciss/proc/AuralAttribute$Observer;
      53: aload_0
      54: aload_2
      55: invokeinterface #673,  3          // InterfaceMethod de/sciss/proc/AuralAttribute$Observer.attrNumChannelsChanged:(Lde/sciss/proc/AuralAttribute;Lde/sciss/lucre/Txn;)V
      60: return

  public void dispose(T);
    Code:
       0: aload_0
       1: aload_1
       2: invokestatic  #678                // InterfaceMethod de/sciss/proc/impl/AuralTimelineBase.dispose$:(Lde/sciss/proc/impl/AuralTimelineBase;Lde/sciss/lucre/Txn;)V
       5: aload_0
       6: getfield      #158                // Field prefChansElemRef:Lscala/concurrent/stm/Ref;
       9: getstatic     #143                // Field scala/package$.MODULE$:Lscala/package$;
      12: invokevirtual #147                // Method scala/package$.Vector:()Lscala/collection/immutable/Vector$;
      15: invokevirtual #153                // Method scala/collection/immutable/Vector$.empty:()Lscala/collection/immutable/Vector;
      18: getstatic     #529                // Field de/sciss/lucre/Txn$.MODULE$:Lde/sciss/lucre/Txn$;
      21: aload_1
      22: invokevirtual #533                // Method de/sciss/lucre/Txn$.peer:(Lde/sciss/lucre/TxnLike;)Lscala/concurrent/stm/InTxn;
      25: invokeinterface #621,  3          // InterfaceMethod scala/concurrent/stm/Ref.swap:(Ljava/lang/Object;Ljava/lang/Object;)Ljava/lang/Object;
      30: checkcast     #623                // class scala/collection/IterableOnceOps
      33: aload_1
      34: invokedynamic #683,  0            // InvokeDynamic #4:applyVoid:(Lde/sciss/lucre/synth/Txn;)Lscala/runtime/function/JProcedure1;
      39: invokeinterface #640,  2          // InterfaceMethod scala/collection/IterableOnceOps.foreach:(Lscala/Function1;)V
      44: return

  public de.sciss.lucre.Form obj(de.sciss.lucre.Txn);
    Code:
       0: aload_0
       1: aload_1
       2: checkcast     #686                // class de/sciss/lucre/synth/Txn
       5: invokevirtual #688                // Method obj:(Lde/sciss/lucre/synth/Txn;)Lde/sciss/proc/Timeline;
       8: areturn

  public de.sciss.proc.AuralViewBase makeViewElem(de.sciss.lucre.Obj, de.sciss.lucre.Txn);
    Code:
       0: aload_0
       1: aload_1
       2: aload_2
       3: checkcast     #686                // class de/sciss/lucre/synth/Txn
       6: invokevirtual #691                // Method makeViewElem:(Lde/sciss/lucre/Obj;Lde/sciss/lucre/synth/Txn;)Lde/sciss/proc/AuralAttribute;
       9: areturn

  public void viewPlaying(de.sciss.proc.impl.AuralTimelineBase$ElemHandle, de.sciss.lucre.Txn);
    Code:
       0: aload_0
       1: aload_1
       2: aload_2
       3: checkcast     #686                // class de/sciss/lucre/synth/Txn
       6: invokevirtual #693                // Method viewPlaying:(Lde/sciss/proc/impl/AuralTimelineBase$ElemHandle;Lde/sciss/lucre/synth/Txn;)V
       9: return

  public void viewStopped(de.sciss.proc.impl.AuralTimelineBase$ElemHandle, de.sciss.lucre.Txn);
    Code:
       0: aload_0
       1: aload_1
       2: aload_2
       3: checkcast     #686                // class de/sciss/lucre/synth/Txn
       6: invokevirtual #695                // Method viewStopped:(Lde/sciss/proc/impl/AuralTimelineBase$ElemHandle;Lde/sciss/lucre/synth/Txn;)V
       9: return

  public int preferredNumChannels(de.sciss.lucre.Txn);
    Code:
       0: aload_0
       1: aload_1
       2: checkcast     #686                // class de/sciss/lucre/synth/Txn
       5: invokevirtual #698                // Method preferredNumChannels:(Lde/sciss/lucre/synth/Txn;)I
       8: ireturn

  public void attrNumChannelsChanged(de.sciss.proc.AuralAttribute, de.sciss.lucre.Txn);
    Code:
       0: aload_0
       1: aload_1
       2: aload_2
       3: checkcast     #686                // class de/sciss/lucre/synth/Txn
       6: invokevirtual #700                // Method attrNumChannelsChanged:(Lde/sciss/proc/AuralAttribute;Lde/sciss/lucre/synth/Txn;)V
       9: return

  public void dispose(de.sciss.lucre.Txn);
    Code:
       0: aload_0
       1: aload_1
       2: checkcast     #686                // class de/sciss/lucre/synth/Txn
       5: invokevirtual #702                // Method dispose:(Lde/sciss/lucre/synth/Txn;)V
       8: return

  public void dispose(java.lang.Object);
    Code:
       0: aload_0
       1: aload_1
       2: checkcast     #686                // class de/sciss/lucre/synth/Txn
       5: invokevirtual #702                // Method dispose:(Lde/sciss/lucre/synth/Txn;)V
       8: return

  public void de$sciss$proc$impl$AuralTimelineBase$$super$dispose(de.sciss.lucre.Txn);
    Code:
       0: aload_0
       1: aload_1
       2: checkcast     #686                // class de/sciss/lucre/synth/Txn
       5: invokevirtual #704                // Method de$sciss$proc$impl$AuralTimelineBase$$super$dispose:(Lde/sciss/lucre/synth/Txn;)V
       8: return

  public de.sciss.proc.AuralViewBase elemFromHandle(java.lang.Object);
    Code:
       0: aload_0
       1: aload_1
       2: checkcast     #53                 // class de/sciss/proc/impl/AuralTimelineBase$ElemHandle
       5: invokevirtual #707                // Method elemFromHandle:(Lde/sciss/proc/impl/AuralTimelineBase$ElemHandle;)Lde/sciss/proc/AuralViewBase;
       8: areturn

  public void playView(java.lang.Object, de.sciss.proc.TimeRef$Option, java.lang.Object, de.sciss.lucre.Txn);
    Code:
       0: aload_0
       1: aload_1
       2: checkcast     #53                 // class de/sciss/proc/impl/AuralTimelineBase$ElemHandle
       5: aload_2
       6: aload_3
       7: aload         4
       9: invokevirtual #710                // Method playView:(Lde/sciss/proc/impl/AuralTimelineBase$ElemHandle;Lde/sciss/proc/TimeRef$Option;Ljava/lang/Object;Lde/sciss/lucre/Txn;)V
      12: return

  public void stopView(java.lang.Object, de.sciss.lucre.Txn);
    Code:
       0: aload_0
       1: aload_1
       2: checkcast     #53                 // class de/sciss/proc/impl/AuralTimelineBase$ElemHandle
       5: aload_2
       6: invokevirtual #712                // Method stopView:(Lde/sciss/proc/impl/AuralTimelineBase$ElemHandle;Lde/sciss/lucre/Txn;)V
       9: return

  public java.lang.Object mkView(java.lang.Object, de.sciss.span.SpanLike, java.lang.Object, de.sciss.lucre.Txn);
    Code:
       0: aload_0
       1: aload_1
       2: checkcast     #715                // class de/sciss/lucre/Ident
       5: aload_2
       6: aload_3
       7: checkcast     #27                 // class de/sciss/lucre/Obj
      10: aload         4
      12: invokevirtual #717                // Method mkView:(Lde/sciss/lucre/Ident;Lde/sciss/span/SpanLike;Lde/sciss/lucre/Obj;Lde/sciss/lucre/Txn;)Lde/sciss/proc/impl/AuralTimelineBase$ElemHandle;
      15: areturn

  public boolean checkReschedule(java.lang.Object, long, long, boolean, de.sciss.lucre.Txn);
    Code:
       0: aload_0
       1: aload_1
       2: checkcast     #53                 // class de/sciss/proc/impl/AuralTimelineBase$ElemHandle
       5: lload_2
       6: lload         4
       8: iload         6
      10: aload         7
      12: invokevirtual #720                // Method checkReschedule:(Lde/sciss/proc/impl/AuralTimelineBase$ElemHandle;JJZLde/sciss/lucre/Txn;)Z
      15: ireturn

  public de.sciss.lucre.Disposable react(scala.Function1, java.lang.Object);
    Code:
       0: aload_0
       1: aload_1
       2: aload_2
       3: checkcast     #723                // class de/sciss/lucre/Txn
       6: invokevirtual #725                // Method react:(Lscala/Function1;Lde/sciss/lucre/Txn;)Lde/sciss/lucre/Disposable;
       9: areturn

  private static final long $anonfun$1();
    Code:
       0: ldc2_w        #726                // long -1l
       3: lreturn

  private static final de.sciss.lucre.Obj $anonfun$4$$anonfun$1(de.sciss.lucre.BiGroup$Entry);
    Code:
       0: aload_0
       1: invokeinterface #732,  1          // InterfaceMethod de/sciss/lucre/BiGroup$Entry.value:()Ljava/lang/Object;
       6: checkcast     #27                 // class de/sciss/lucre/Obj
       9: areturn

  private static final scala.collection.IterableOnce $anonfun$2(scala.Tuple2);
    Code:
       0: aload_0
       1: invokevirtual #738                // Method scala/Tuple2._2:()Ljava/lang/Object;
       4: checkcast     #740                // class scala/collection/IndexedSeqOps
       7: invokedynamic #745,  0            // InvokeDynamic #5:apply:()Lscala/Function1;
      12: invokeinterface #746,  2          // InterfaceMethod scala/collection/IndexedSeqOps.map:(Lscala/Function1;)Ljava/lang/Object;
      17: checkcast     #748                // class scala/collection/IterableOnce
      20: areturn

  private final de.sciss.proc.AuralAttribute $anonfun$3(de.sciss.lucre.synth.Txn, de.sciss.lucre.Obj);
    Code:
       0: aload_0
       1: aload_2
       2: aload_1
       3: invokevirtual #691                // Method makeViewElem:(Lde/sciss/lucre/Obj;Lde/sciss/lucre/synth/Txn;)Lde/sciss/proc/AuralAttribute;
       6: areturn

  private static final void preferredNumChannels$$anonfun$1(de.sciss.lucre.synth.Txn, de.sciss.proc.AuralAttribute);
    Code:
       0: aload_1
       1: aload_0
       2: invokeinterface #754,  2          // InterfaceMethod de/sciss/proc/AuralAttribute.dispose:(Ljava/lang/Object;)V
       7: return

  private static final int loop$1(de.sciss.lucre.synth.Txn, scala.collection.immutable.Vector, int);
    Code:
       0: iload_2
       1: istore_3
       2: aload_1
       3: astore        4
       5: aload         4
       7: astore        5
       9: aload         5
      11: ifnull        114
      14: getstatic     #143                // Field scala/package$.MODULE$:Lscala/package$;
      17: invokevirtual #759                // Method scala/package$.$plus$colon:()Lscala/collection/package$$plus$colon$;
      20: aload         5
      22: invokevirtual #763                // Method scala/collection/package$$plus$colon$.unapply:(Lscala/collection/SeqOps;)Lscala/Option;
      25: astore        6
      27: aload         6
      29: invokevirtual #764                // Method scala/Option.isEmpty:()Z
      32: ifne          114
      35: aload         6
      37: invokevirtual #766                // Method scala/Option.get:()Ljava/lang/Object;
      40: checkcast     #735                // class scala/Tuple2
      43: astore        7
      45: aload         7
      47: invokevirtual #769                // Method scala/Tuple2._1:()Ljava/lang/Object;
      50: checkcast     #15                 // class de/sciss/proc/AuralAttribute
      53: astore        8
      55: aload         7
      57: invokevirtual #738                // Method scala/Tuple2._2:()Ljava/lang/Object;
      60: checkcast     #613                // class scala/collection/immutable/Vector
      63: astore        9
      65: aload         8
      67: aload_0
      68: invokeinterface #771,  2          // InterfaceMethod de/sciss/proc/AuralAttribute.preferredNumChannels:(Lde/sciss/lucre/Txn;)I
      73: istore        10
      75: iload         10
      77: iconst_m1
      78: if_icmpne     86
      81: iload         10
      83: goto          111
      86: aload         9
      88: astore        11
      90: getstatic     #776                // Field scala/math/package$.MODULE$:Lscala/math/package$;
      93: iload_3
      94: iload         10
      96: invokevirtual #780                // Method scala/math/package$.max:(II)I
      99: istore        12
     101: aload         11
     103: astore        4
     105: iload         12
     107: istore_3
     108: goto          119
     111: goto          118
     114: iload_3
     115: goto          118
     118: ireturn
     119: goto          5
     122: athrow
     123: athrow

  private static final void dispose$$anonfun$1(de.sciss.lucre.synth.Txn, de.sciss.proc.AuralAttribute);
    Code:
       0: aload_1
       1: aload_0
       2: invokeinterface #754,  2          // InterfaceMethod de/sciss/proc/AuralAttribute.dispose:(Ljava/lang/Object;)V
       7: return

  private static java.lang.Object $deserializeLambda$(java.lang.invoke.SerializedLambda);
    Code:
       0: aload_0
       1: invokedynamic #797,  0            // InvokeDynamic #6:lambdaDeserialize:(Ljava/lang/invoke/SerializedLambda;)Ljava/lang/Object;
       6: areturn
}
