Compiled from "KeyMapImpl.scala"
public final class de.sciss.proc.impl.KeyMapImpl$Entry<T extends de.sciss.lucre.Txn<T>, Key, Value> implements de.sciss.serial.Writable, de.sciss.lucre.Disposable<T> {
  private final java.lang.Object key;

  private final java.lang.Object value;

  private final de.sciss.proc.impl.KeyMapImpl$ValueInfo<T, Key, Value> info;

  public de.sciss.proc.impl.KeyMapImpl$Entry(Key, Value, de.sciss.proc.impl.KeyMapImpl$ValueInfo<T, Key, Value>);
    Code:
       0: aload_0
       1: aload_1
       2: putfield      #27                 // Field key:Ljava/lang/Object;
       5: aload_0
       6: aload_2
       7: putfield      #29                 // Field value:Ljava/lang/Object;
      10: aload_0
      11: aload_3
      12: putfield      #31                 // Field info:Lde/sciss/proc/impl/KeyMapImpl$ValueInfo;
      15: aload_0
      16: invokespecial #34                 // Method java/lang/Object."<init>":()V
      19: return

  public Key key();
    Code:
       0: aload_0
       1: getfield      #27                 // Field key:Ljava/lang/Object;
       4: areturn

  public Value value();
    Code:
       0: aload_0
       1: getfield      #29                 // Field value:Ljava/lang/Object;
       4: areturn

  public void write(de.sciss.serial.DataOutput);
    Code:
       0: aload_0
       1: getfield      #31                 // Field info:Lde/sciss/proc/impl/KeyMapImpl$ValueInfo;
       4: invokeinterface #46,  1           // InterfaceMethod de/sciss/proc/impl/KeyMapImpl$ValueInfo.keyFormat:()Lde/sciss/serial/TFormat;
       9: aload_0
      10: invokevirtual #48                 // Method key:()Ljava/lang/Object;
      13: aload_1
      14: invokeinterface #53,  3           // InterfaceMethod de/sciss/serial/TFormat.write:(Ljava/lang/Object;Lde/sciss/serial/DataOutput;)V
      19: aload_0
      20: getfield      #31                 // Field info:Lde/sciss/proc/impl/KeyMapImpl$ValueInfo;
      23: invokeinterface #56,  1           // InterfaceMethod de/sciss/proc/impl/KeyMapImpl$ValueInfo.valueFormat:()Lde/sciss/serial/TFormat;
      28: aload_0
      29: invokevirtual #58                 // Method value:()Ljava/lang/Object;
      32: aload_1
      33: invokeinterface #53,  3           // InterfaceMethod de/sciss/serial/TFormat.write:(Ljava/lang/Object;Lde/sciss/serial/DataOutput;)V
      38: return

  public void dispose(T);
    Code:
       0: return

  public void dispose(java.lang.Object);
    Code:
       0: aload_0
       1: aload_1
       2: checkcast     #67                 // class de/sciss/lucre/Txn
       5: invokevirtual #69                 // Method dispose:(Lde/sciss/lucre/Txn;)V
       8: return
}
