Compiled from "ProcOutputImpl.scala"
public final class de.sciss.proc.impl.ProcOutputImpl {
  public static <T extends de.sciss.lucre.Txn<T>> de.sciss.proc.Proc$Output<T> apply(de.sciss.proc.Proc<T>, java.lang.String, T);
    Code:
       0: getstatic     #28                 // Field de/sciss/proc/impl/ProcOutputImpl$.MODULE$:Lde/sciss/proc/impl/ProcOutputImpl$;
       3: aload_0
       4: aload_1
       5: aload_2
       6: invokevirtual #30                 // Method de/sciss/proc/impl/ProcOutputImpl$.apply:(Lde/sciss/proc/Proc;Ljava/lang/String;Lde/sciss/lucre/Txn;)Lde/sciss/proc/Proc$Output;
       9: areturn

  public static <T extends de.sciss.lucre.Txn<T>> de.sciss.serial.TFormat<T, de.sciss.proc.Proc$Output<T>> format();
    Code:
       0: getstatic     #28                 // Field de/sciss/proc/impl/ProcOutputImpl$.MODULE$:Lde/sciss/proc/impl/ProcOutputImpl$;
       3: invokevirtual #35                 // Method de/sciss/proc/impl/ProcOutputImpl$.format:()Lde/sciss/serial/TFormat;
       6: areturn

  public static <T extends de.sciss.lucre.Txn<T>> de.sciss.proc.Proc$Output<T> read(de.sciss.serial.DataInput, T);
    Code:
       0: getstatic     #28                 // Field de/sciss/proc/impl/ProcOutputImpl$.MODULE$:Lde/sciss/proc/impl/ProcOutputImpl$;
       3: aload_0
       4: aload_1
       5: invokevirtual #40                 // Method de/sciss/proc/impl/ProcOutputImpl$.read:(Lde/sciss/serial/DataInput;Lde/sciss/lucre/Txn;)Lde/sciss/proc/Proc$Output;
       8: areturn

  public static <T extends de.sciss.lucre.Txn<T>> de.sciss.proc.Proc$Output<T> readIdentifiedObj(de.sciss.serial.DataInput, T);
    Code:
       0: getstatic     #28                 // Field de/sciss/proc/impl/ProcOutputImpl$.MODULE$:Lde/sciss/proc/impl/ProcOutputImpl$;
       3: aload_0
       4: aload_1
       5: invokevirtual #43                 // Method de/sciss/proc/impl/ProcOutputImpl$.readIdentifiedObj:(Lde/sciss/serial/DataInput;Lde/sciss/lucre/Txn;)Lde/sciss/proc/Proc$Output;
       8: areturn
}
