Compiled from "SchedulerImpl.scala"
public final class de.sciss.proc.impl.SchedulerImpl$ implements java.io.Serializable {
  public static final de.sciss.proc.impl.SchedulerImpl$Info de$sciss$proc$impl$SchedulerImpl$$$infInfo;

  public static final de.sciss.proc.impl.SchedulerImpl$ MODULE$;

  private de.sciss.proc.impl.SchedulerImpl$();
    Code:
       0: aload_0
       1: invokespecial #60                 // Method java/lang/Object."<init>":()V
       4: return

  public static {};
    Code:
       0: new           #2                  // class de/sciss/proc/impl/SchedulerImpl$
       3: dup
       4: invokespecial #63                 // Method "<init>":()V
       7: putstatic     #65                 // Field MODULE$:Lde/sciss/proc/impl/SchedulerImpl$;
      10: new           #33                 // class de/sciss/proc/impl/SchedulerImpl$Info
      13: dup
      14: lconst_0
      15: ldc2_w        #66                 // long 9223372036854775807l
      18: invokespecial #70                 // Method de/sciss/proc/impl/SchedulerImpl$Info."<init>":(JJ)V
      21: putstatic     #72                 // Field de$sciss$proc$impl$SchedulerImpl$$$infInfo:Lde/sciss/proc/impl/SchedulerImpl$Info;
      24: return

  private java.lang.Object writeReplace();
    Code:
       0: new           #76                 // class scala/runtime/ModuleSerializationProxy
       3: dup
       4: ldc           #2                  // class de/sciss/proc/impl/SchedulerImpl$
       6: invokespecial #79                 // Method scala/runtime/ModuleSerializationProxy."<init>":(Ljava/lang/Class;)V
       9: areturn

  public <T extends de.sciss.lucre.Txn<T>> de.sciss.proc.Scheduler<T> apply(T, de.sciss.lucre.Cursor<T>);
    Code:
       0: aload_0
       1: aload_1
       2: aload_1
       3: invokeinterface #90,  1           // InterfaceMethod de/sciss/lucre/Txn.inMemoryBridge:()Lscala/Function1;
       8: invokespecial #94                 // Method mkPriorityQueue:(Lde/sciss/lucre/Txn;Lscala/Function1;)Lde/sciss/lucre/data/SkipList$Map;
      11: astore_3
      12: new           #39                 // class de/sciss/proc/impl/SchedulerImpl$RealtimeImpl
      15: dup
      16: aload_3
      17: aload_2
      18: aload_1
      19: invokeinterface #90,  1           // InterfaceMethod de/sciss/lucre/Txn.inMemoryBridge:()Lscala/Function1;
      24: invokespecial #97                 // Method de/sciss/proc/impl/SchedulerImpl$RealtimeImpl."<init>":(Lde/sciss/lucre/data/SkipList$Map;Lde/sciss/lucre/Cursor;Lscala/Function1;)V
      27: areturn

  public <T extends de.sciss.lucre.Txn<T>> de.sciss.proc.Scheduler$Offline<T> offline(T, de.sciss.lucre.Cursor<T>);
    Code:
       0: aload_0
       1: aload_1
       2: aload_1
       3: invokeinterface #90,  1           // InterfaceMethod de/sciss/lucre/Txn.inMemoryBridge:()Lscala/Function1;
       8: invokespecial #94                 // Method mkPriorityQueue:(Lde/sciss/lucre/Txn;Lscala/Function1;)Lde/sciss/lucre/data/SkipList$Map;
      11: astore_3
      12: new           #36                 // class de/sciss/proc/impl/SchedulerImpl$OfflineImpl
      15: dup
      16: aload_3
      17: aload_2
      18: aload_1
      19: invokeinterface #90,  1           // InterfaceMethod de/sciss/lucre/Txn.inMemoryBridge:()Lscala/Function1;
      24: invokespecial #105                // Method de/sciss/proc/impl/SchedulerImpl$OfflineImpl."<init>":(Lde/sciss/lucre/data/SkipList$Map;Lde/sciss/lucre/Cursor;Lscala/Function1;)V
      27: areturn

  private <T extends de.sciss.lucre.Txn<T>, I1 extends de.sciss.lucre.Txn<I1>> de.sciss.lucre.data.SkipList$Map<I1, java.lang.Object, scala.collection.immutable.Set<java.lang.Object>> mkPriorityQueue(T, scala.Function1<T, I1>);
    Code:
       0: aload_2
       1: aload_1
       2: invokeinterface #112,  2          // InterfaceMethod scala/Function1.apply:(Ljava/lang/Object;)Ljava/lang/Object;
       7: checkcast     #86                 // class de/sciss/lucre/Txn
      10: astore_3
      11: getstatic     #117                // Field de/sciss/serial/ConstFormat$.MODULE$:Lde/sciss/serial/ConstFormat$;
      14: getstatic     #120                // Field de/sciss/serial/TFormat$Int$.MODULE$:Lde/sciss/serial/TFormat$Int$;
      17: invokevirtual #124                // Method de/sciss/serial/ConstFormat$.set:(Lde/sciss/serial/ConstFormat;)Lde/sciss/serial/ConstFormat;
      20: astore        4
      22: getstatic     #127                // Field de/sciss/lucre/data/SkipList$Map$.MODULE$:Lde/sciss/lucre/data/SkipList$Map$;
      25: getstatic     #127                // Field de/sciss/lucre/data/SkipList$Map$.MODULE$:Lde/sciss/lucre/data/SkipList$Map$;
      28: invokevirtual #131                // Method de/sciss/lucre/data/SkipList$Map$.empty$default$1:()Lde/sciss/lucre/data/SkipList$NoKeyObserver$;
      31: aload_3
      32: getstatic     #134                // Field scala/math/Ordering$Long$.MODULE$:Lscala/math/Ordering$Long$;
      35: getstatic     #137                // Field de/sciss/serial/TFormat$Long$.MODULE$:Lde/sciss/serial/TFormat$Long$;
      38: aload         4
      40: invokevirtual #141                // Method de/sciss/lucre/data/SkipList$Map$.empty:(Lde/sciss/lucre/data/SkipList$KeyObserver;Lde/sciss/lucre/Exec;Lscala/math/Ordering;Lde/sciss/serial/ConstFormat;Lde/sciss/serial/TFormat;)Lde/sciss/lucre/data/SkipList$Map;
      43: areturn
}
