Compiled from "SensorSystemImpl.scala"
final class de.sciss.proc.impl.SensorSystemImpl$$anon$1 implements java.lang.Runnable {
  private final de.sciss.proc.impl.SensorSystemImpl$Impl $outer;

  public de.sciss.proc.impl.SensorSystemImpl$$anon$1(de.sciss.proc.impl.SensorSystemImpl$Impl);
    Code:
       0: aload_1
       1: ifnonnull     12
       4: new           #21                 // class java/lang/NullPointerException
       7: dup
       8: invokespecial #24                 // Method java/lang/NullPointerException."<init>":()V
      11: athrow
      12: aload_0
      13: aload_1
      14: putfield      #26                 // Field $outer:Lde/sciss/proc/impl/SensorSystemImpl$Impl;
      17: aload_0
      18: invokespecial #27                 // Method java/lang/Object."<init>":()V
      21: return

  public void run();
    Code:
       0: aload_0
       1: getfield      #26                 // Field $outer:Lde/sciss/proc/impl/SensorSystemImpl$Impl;
       4: invokevirtual #33                 // Method de/sciss/proc/impl/SensorSystemImpl$Impl.de$sciss$proc$impl$SensorSystemImpl$Impl$$shutdown:()V
       7: return
}
