Compiled from "SensorSystemImpl.scala"
class de.sciss.proc.impl.SensorSystemImpl$Impl$StateBooting implements de.sciss.proc.impl.SensorSystemImpl$Impl$State,scala.Product,java.io.Serializable {
  private final de.sciss.proc.SensorSystem$Config config;

  private final de.sciss.proc.impl.SensorSystemImpl$Impl $outer;

  public de.sciss.proc.impl.SensorSystemImpl$Impl$StateBooting(de.sciss.proc.impl.SensorSystemImpl$Impl, de.sciss.proc.SensorSystem$Config);
    Code:
       0: aload_0
       1: aload_2
       2: putfield      #57                 // Field config:Lde/sciss/proc/SensorSystem$Config;
       5: aload_1
       6: ifnonnull     17
       9: new           #59                 // class java/lang/NullPointerException
      12: dup
      13: invokespecial #62                 // Method java/lang/NullPointerException."<init>":()V
      16: athrow
      17: aload_0
      18: aload_1
      19: putfield      #64                 // Field $outer:Lde/sciss/proc/impl/SensorSystemImpl$Impl;
      22: aload_0
      23: invokespecial #65                 // Method java/lang/Object."<init>":()V
      26: return

  public scala.collection.Iterator productIterator();
    Code:
       0: aload_0
       1: invokestatic  #73                 // InterfaceMethod scala/Product.productIterator$:(Lscala/Product;)Lscala/collection/Iterator;
       4: areturn

  public scala.collection.Iterator productElementNames();
    Code:
       0: aload_0
       1: invokestatic  #77                 // InterfaceMethod scala/Product.productElementNames$:(Lscala/Product;)Lscala/collection/Iterator;
       4: areturn

  public int hashCode();
    Code:
       0: getstatic     #85                 // Field scala/runtime/ScalaRunTime$.MODULE$:Lscala/runtime/ScalaRunTime$;
       3: aload_0
       4: invokevirtual #89                 // Method scala/runtime/ScalaRunTime$._hashCode:(Lscala/Product;)I
       7: ireturn

  public boolean equals(java.lang.Object);
    Code:
       0: aload_0
       1: aload_1
       2: if_acmpeq     87
       5: aload_1
       6: astore_2
       7: aload_2
       8: instanceof    #2                  // class de/sciss/proc/impl/SensorSystemImpl$Impl$StateBooting
      11: ifeq          80
      14: aload_2
      15: checkcast     #2                  // class de/sciss/proc/impl/SensorSystemImpl$Impl$StateBooting
      18: invokevirtual #96                 // Method de$sciss$proc$impl$SensorSystemImpl$Impl$StateBooting$$$outer:()Lde/sciss/proc/impl/SensorSystemImpl$Impl;
      21: aload_0
      22: getfield      #64                 // Field $outer:Lde/sciss/proc/impl/SensorSystemImpl$Impl;
      25: if_acmpne     80
      28: aload_2
      29: checkcast     #2                  // class de/sciss/proc/impl/SensorSystemImpl$Impl$StateBooting
      32: astore_3
      33: aload_0
      34: invokevirtual #99                 // Method config:()Lde/sciss/proc/SensorSystem$Config;
      37: aload_3
      38: invokevirtual #99                 // Method config:()Lde/sciss/proc/SensorSystem$Config;
      41: astore        4
      43: dup
      44: ifnonnull     56
      47: pop
      48: aload         4
      50: ifnull        64
      53: goto          76
      56: aload         4
      58: invokevirtual #101                // Method java/lang/Object.equals:(Ljava/lang/Object;)Z
      61: ifeq          76
      64: aload_3
      65: aload_0
      66: invokevirtual #104                // Method canEqual:(Ljava/lang/Object;)Z
      69: ifeq          76
      72: iconst_1
      73: goto          77
      76: iconst_0
      77: goto          84
      80: iconst_0
      81: goto          84
      84: ifeq          91
      87: iconst_1
      88: goto          92
      91: iconst_0
      92: ireturn

  public java.lang.String toString();
    Code:
       0: getstatic     #85                 // Field scala/runtime/ScalaRunTime$.MODULE$:Lscala/runtime/ScalaRunTime$;
       3: aload_0
       4: invokevirtual #111                // Method scala/runtime/ScalaRunTime$._toString:(Lscala/Product;)Ljava/lang/String;
       7: areturn

  public boolean canEqual(java.lang.Object);
    Code:
       0: aload_1
       1: instanceof    #2                  // class de/sciss/proc/impl/SensorSystemImpl$Impl$StateBooting
       4: ireturn

  public int productArity();
    Code:
       0: iconst_1
       1: ireturn

  public java.lang.String productPrefix();
    Code:
       0: ldc           #115                // String StateBooting
       2: areturn

  public java.lang.Object productElement(int);
    Code:
       0: iload_1
       1: istore_2
       2: iconst_0
       3: iload_2
       4: if_icmpne     14
       7: aload_0
       8: invokevirtual #121                // Method _1:()Lde/sciss/proc/SensorSystem$Config;
      11: goto          29
      14: new           #123                // class java/lang/IndexOutOfBoundsException
      17: dup
      18: iload_1
      19: invokestatic  #129                // Method scala/runtime/BoxesRunTime.boxToInteger:(I)Ljava/lang/Integer;
      22: invokevirtual #133                // Method java/lang/Integer.toString:()Ljava/lang/String;
      25: invokespecial #136                // Method java/lang/IndexOutOfBoundsException."<init>":(Ljava/lang/String;)V
      28: athrow
      29: areturn

  public java.lang.String productElementName(int);
    Code:
       0: iload_1
       1: istore_2
       2: iconst_0
       3: iload_2
       4: if_icmpne     12
       7: ldc           #140                // String config
       9: goto          27
      12: new           #123                // class java/lang/IndexOutOfBoundsException
      15: dup
      16: iload_1
      17: invokestatic  #129                // Method scala/runtime/BoxesRunTime.boxToInteger:(I)Ljava/lang/Integer;
      20: invokevirtual #133                // Method java/lang/Integer.toString:()Ljava/lang/String;
      23: invokespecial #136                // Method java/lang/IndexOutOfBoundsException."<init>":(Ljava/lang/String;)V
      26: athrow
      27: areturn

  public de.sciss.proc.SensorSystem$Config config();
    Code:
       0: aload_0
       1: getfield      #57                 // Field config:Lde/sciss/proc/SensorSystem$Config;
       4: areturn

  public void init(de.sciss.lucre.TxnLike);
    Code:
       0: getstatic     #150                // Field de/sciss/proc/impl/SensorSystemImpl$.MODULE$:Lde/sciss/proc/impl/SensorSystemImpl$;
       3: aload_0
       4: invokedynamic #167,  0            // InvokeDynamic #0:apply$mcV$sp:(Lde/sciss/proc/impl/SensorSystemImpl$Impl$StateBooting;)Lscala/runtime/java8/JFunction0$mcV$sp;
       9: aload_1
      10: invokevirtual #171                // Method de/sciss/proc/impl/SensorSystemImpl$.de$sciss$proc$impl$SensorSystemImpl$$$afterCommit:(Lscala/Function0;Lde/sciss/lucre/TxnLike;)V
      13: return

  public void dispose(de.sciss.lucre.TxnLike);
    Code:
       0: return

  public scala.Option<de.sciss.osc.Channel$Undirected$Input$Net> serverOption();
    Code:
       0: getstatic     #181                // Field scala/None$.MODULE$:Lscala/None$;
       3: areturn

  public void shutdown();
    Code:
       0: return

  public de.sciss.proc.impl.SensorSystemImpl$Impl$StateBooting copy(de.sciss.proc.SensorSystem$Config);
    Code:
       0: new           #2                  // class de/sciss/proc/impl/SensorSystemImpl$Impl$StateBooting
       3: dup
       4: aload_0
       5: getfield      #64                 // Field $outer:Lde/sciss/proc/impl/SensorSystemImpl$Impl;
       8: aload_1
       9: invokespecial #186                // Method "<init>":(Lde/sciss/proc/impl/SensorSystemImpl$Impl;Lde/sciss/proc/SensorSystem$Config;)V
      12: areturn

  public de.sciss.proc.SensorSystem$Config copy$default$1();
    Code:
       0: aload_0
       1: invokevirtual #99                 // Method config:()Lde/sciss/proc/SensorSystem$Config;
       4: areturn

  public de.sciss.proc.SensorSystem$Config _1();
    Code:
       0: aload_0
       1: invokevirtual #99                 // Method config:()Lde/sciss/proc/SensorSystem$Config;
       4: areturn

  public final de.sciss.proc.impl.SensorSystemImpl$Impl de$sciss$proc$impl$SensorSystemImpl$Impl$StateBooting$$$outer();
    Code:
       0: aload_0
       1: getfield      #64                 // Field $outer:Lde/sciss/proc/impl/SensorSystemImpl$Impl;
       4: areturn

  public void dispose(java.lang.Object);
    Code:
       0: aload_0
       1: aload_1
       2: checkcast     #190                // class de/sciss/lucre/TxnLike
       5: invokevirtual #192                // Method dispose:(Lde/sciss/lucre/TxnLike;)V
       8: return

  private final void init$$anonfun$1();
    Code:
       0: aload_0
       1: invokevirtual #99                 // Method config:()Lde/sciss/proc/SensorSystem$Config;
       4: invokevirtual #196                // Method de/sciss/proc/SensorSystem$Config.osc:()Lde/sciss/osc/Channel$Net$Config;
       7: astore_2
       8: aload_2
       9: instanceof    #33                 // class de/sciss/osc/UDP$Config
      12: ifeq          41
      15: aload_2
      16: checkcast     #33                 // class de/sciss/osc/UDP$Config
      19: astore_3
      20: getstatic     #199                // Field de/sciss/osc/UDP$Receiver$.MODULE$:Lde/sciss/osc/UDP$Receiver$;
      23: aload_3
      24: invokevirtual #203                // Method de/sciss/osc/UDP$Receiver$.apply:(Lde/sciss/osc/UDP$Config;)Lde/sciss/osc/Channel$Undirected$Input$Net;
      27: astore        4
      29: aload         4
      31: invokeinterface #206,  1          // InterfaceMethod de/sciss/osc/Channel$Undirected$Input$Net.connect:()V
      36: aload         4
      38: goto          62
      41: aload_2
      42: astore        5
      44: new           #208                // class java/lang/IllegalArgumentException
      47: dup
      48: aload         5
      50: invokeinterface #209,  1          // InterfaceMethod de/sciss/osc/Channel$Net$Config.toString:()Ljava/lang/String;
      55: invokespecial #210                // Method java/lang/IllegalArgumentException."<init>":(Ljava/lang/String;)V
      58: athrow
      59: nop
      60: nop
      61: athrow
      62: astore_1
      63: aload_0
      64: getfield      #64                 // Field $outer:Lde/sciss/proc/impl/SensorSystemImpl$Impl;
      67: aload_1
      68: aload_0
      69: getfield      #64                 // Field $outer:Lde/sciss/proc/impl/SensorSystemImpl$Impl;
      72: getfield      #214                // Field de/sciss/proc/impl/SensorSystemImpl$Impl.de$sciss$proc$impl$SensorSystemImpl$Impl$$_dumpOSC:Z
      75: invokevirtual #218                // Method de/sciss/proc/impl/SensorSystemImpl$Impl.de$sciss$proc$impl$SensorSystemImpl$Impl$$setDumpOSC:(Lde/sciss/osc/Channel$Undirected$Input$Net;Z)V
      78: getstatic     #223                // Field scala/Predef$.MODULE$:Lscala/Predef$;
      81: aload_1
      82: checkcast     #21                 // class de/sciss/osc/Channel$Net$ConfigLike
      85: invokeinterface #227,  1          // InterfaceMethod de/sciss/osc/Channel$Net$ConfigLike.localSocketAddress:()Ljava/net/InetSocketAddress;
      90: invokevirtual #230                // Method scala/Predef$.println:(Ljava/lang/Object;)V
      93: aload_0
      94: getfield      #64                 // Field $outer:Lde/sciss/proc/impl/SensorSystemImpl$Impl;
      97: aload_1
      98: aload_0
      99: invokevirtual #99                 // Method config:()Lde/sciss/proc/SensorSystem$Config;
     102: invokevirtual #233                // Method de/sciss/proc/SensorSystem$Config.command:()Ljava/lang/String;
     105: invokevirtual #237                // Method de/sciss/proc/impl/SensorSystemImpl$Impl.de$sciss$proc$impl$SensorSystemImpl$Impl$$clientStarted:(Lde/sciss/osc/Channel$Undirected$Input$Net;Ljava/lang/String;)V
     108: return

  private static java.lang.Object $deserializeLambda$(java.lang.invoke.SerializedLambda);
    Code:
       0: aload_0
       1: invokedynamic #258,  0            // InvokeDynamic #1:lambdaDeserialize:(Ljava/lang/invoke/SerializedLambda;)Ljava/lang/Object;
       6: areturn
}
