Compiled from "WorkspacePlatformImpl.scala"
public final class de.sciss.proc.impl.WorkspacePlatformImpl {
  public static de.sciss.proc.WorkspacePlatform$Confluent emptyConfluent(java.net.URI, de.sciss.lucre.DataStore$Factory, scala.collection.immutable.Map);
    Code:
       0: getstatic     #32                 // Field de/sciss/proc/impl/WorkspacePlatformImpl$.MODULE$:Lde/sciss/proc/impl/WorkspacePlatformImpl$;
       3: aload_0
       4: aload_1
       5: aload_2
       6: invokevirtual #34                 // Method de/sciss/proc/impl/WorkspacePlatformImpl$.emptyConfluent:(Ljava/net/URI;Lde/sciss/lucre/DataStore$Factory;Lscala/collection/immutable/Map;)Lde/sciss/proc/WorkspacePlatform$Confluent;
       9: areturn

  public static de.sciss.proc.WorkspacePlatform$Durable emptyDurable(java.net.URI, de.sciss.lucre.DataStore$Factory, scala.collection.immutable.Map);
    Code:
       0: getstatic     #32                 // Field de/sciss/proc/impl/WorkspacePlatformImpl$.MODULE$:Lde/sciss/proc/impl/WorkspacePlatformImpl$;
       3: aload_0
       4: aload_1
       5: aload_2
       6: invokevirtual #38                 // Method de/sciss/proc/impl/WorkspacePlatformImpl$.emptyDurable:(Ljava/net/URI;Lde/sciss/lucre/DataStore$Factory;Lscala/collection/immutable/Map;)Lde/sciss/proc/WorkspacePlatform$Durable;
       9: areturn

  public static de.sciss.proc.Workspace<?> read(java.net.URI, de.sciss.lucre.DataStore$Factory, scala.collection.immutable.Map<java.lang.String, java.lang.String>);
    Code:
       0: getstatic     #32                 // Field de/sciss/proc/impl/WorkspacePlatformImpl$.MODULE$:Lde/sciss/proc/impl/WorkspacePlatformImpl$;
       3: aload_0
       4: aload_1
       5: aload_2
       6: invokevirtual #43                 // Method de/sciss/proc/impl/WorkspacePlatformImpl$.read:(Ljava/net/URI;Lde/sciss/lucre/DataStore$Factory;Lscala/collection/immutable/Map;)Lde/sciss/proc/Workspace;
       9: areturn

  public static de.sciss.proc.WorkspacePlatform$Confluent readConfluent(java.net.URI, de.sciss.lucre.DataStore$Factory, scala.collection.immutable.Map);
    Code:
       0: getstatic     #32                 // Field de/sciss/proc/impl/WorkspacePlatformImpl$.MODULE$:Lde/sciss/proc/impl/WorkspacePlatformImpl$;
       3: aload_0
       4: aload_1
       5: aload_2
       6: invokevirtual #46                 // Method de/sciss/proc/impl/WorkspacePlatformImpl$.readConfluent:(Ljava/net/URI;Lde/sciss/lucre/DataStore$Factory;Lscala/collection/immutable/Map;)Lde/sciss/proc/WorkspacePlatform$Confluent;
       9: areturn

  public static de.sciss.proc.WorkspacePlatform$Durable readDurable(java.net.URI, de.sciss.lucre.DataStore$Factory, scala.collection.immutable.Map);
    Code:
       0: getstatic     #32                 // Field de/sciss/proc/impl/WorkspacePlatformImpl$.MODULE$:Lde/sciss/proc/impl/WorkspacePlatformImpl$;
       3: aload_0
       4: aload_1
       5: aload_2
       6: invokevirtual #49                 // Method de/sciss/proc/impl/WorkspacePlatformImpl$.readDurable:(Ljava/net/URI;Lde/sciss/lucre/DataStore$Factory;Lscala/collection/immutable/Map;)Lde/sciss/proc/WorkspacePlatform$Durable;
       9: areturn
}
