Compiled from "WorkspacePlatformImpl.scala"
public final class de.sciss.proc.impl.WorkspacePlatformImpl$ implements java.io.Serializable {
  public static final de.sciss.proc.impl.WorkspacePlatformImpl$ MODULE$;

  private de.sciss.proc.impl.WorkspacePlatformImpl$();
    Code:
       0: aload_0
       1: invokespecial #64                 // Method java/lang/Object."<init>":()V
       4: return

  public static {};
    Code:
       0: new           #2                  // class de/sciss/proc/impl/WorkspacePlatformImpl$
       3: dup
       4: invokespecial #67                 // Method "<init>":()V
       7: putstatic     #69                 // Field MODULE$:Lde/sciss/proc/impl/WorkspacePlatformImpl$;
      10: return

  private java.lang.Object writeReplace();
    Code:
       0: new           #73                 // class scala/runtime/ModuleSerializationProxy
       3: dup
       4: ldc           #2                  // class de/sciss/proc/impl/WorkspacePlatformImpl$
       6: invokespecial #76                 // Method scala/runtime/ModuleSerializationProxy."<init>":(Ljava/lang/Class;)V
       9: areturn

  private de.sciss.proc.impl.WorkspaceImpl$Fmt<de.sciss.proc.Confluent$Txn> ConfluentFmt();
    Code:
       0: getstatic     #84                 // Field de/sciss/proc/impl/WorkspaceImpl$.MODULE$:Lde/sciss/proc/impl/WorkspaceImpl$;
       3: invokevirtual #87                 // Method de/sciss/proc/impl/WorkspaceImpl$.fmt:()Lde/sciss/proc/impl/WorkspaceImpl$Fmt;
       6: areturn

  private void requireExists(java.io.File);
    Code:
       0: new           #92                 // class java/io/File
       3: dup
       4: aload_1
       5: ldc           #94                 // String open
       7: invokespecial #97                 // Method java/io/File."<init>":(Ljava/io/File;Ljava/lang/String;)V
      10: invokevirtual #101                // Method java/io/File.isFile:()Z
      13: ifne          53
      16: new           #103                // class java/io/FileNotFoundException
      19: dup
      20: new           #105                // class java/lang/StringBuilder
      23: dup
      24: ldc           #106                // int 25
      26: invokespecial #109                // Method java/lang/StringBuilder."<init>":(I)V
      29: ldc           #111                // String Workspace
      31: invokevirtual #115                // Method java/lang/StringBuilder.append:(Ljava/lang/String;)Ljava/lang/StringBuilder;
      34: aload_1
      35: invokevirtual #119                // Method java/io/File.getPath:()Ljava/lang/String;
      38: invokevirtual #115                // Method java/lang/StringBuilder.append:(Ljava/lang/String;)Ljava/lang/StringBuilder;
      41: ldc           #121                // String  does not exist
      43: invokevirtual #115                // Method java/lang/StringBuilder.append:(Ljava/lang/String;)Ljava/lang/StringBuilder;
      46: invokevirtual #124                // Method java/lang/StringBuilder.toString:()Ljava/lang/String;
      49: invokespecial #127                // Method java/io/FileNotFoundException."<init>":(Ljava/lang/String;)V
      52: athrow
      53: return

  private void requireExistsNot(java.io.File);
    Code:
       0: new           #92                 // class java/io/File
       3: dup
       4: aload_1
       5: ldc           #94                 // String open
       7: invokespecial #97                 // Method java/io/File."<init>":(Ljava/io/File;Ljava/lang/String;)V
      10: invokevirtual #132                // Method java/io/File.exists:()Z
      13: ifeq          53
      16: new           #134                // class java/io/IOException
      19: dup
      20: new           #105                // class java/lang/StringBuilder
      23: dup
      24: ldc           #106                // int 25
      26: invokespecial #109                // Method java/lang/StringBuilder."<init>":(I)V
      29: ldc           #111                // String Workspace
      31: invokevirtual #115                // Method java/lang/StringBuilder.append:(Ljava/lang/String;)Ljava/lang/StringBuilder;
      34: aload_1
      35: invokevirtual #119                // Method java/io/File.getPath:()Ljava/lang/String;
      38: invokevirtual #115                // Method java/lang/StringBuilder.append:(Ljava/lang/String;)Ljava/lang/StringBuilder;
      41: ldc           #136                // String  already exists
      43: invokevirtual #115                // Method java/lang/StringBuilder.append:(Ljava/lang/String;)Ljava/lang/StringBuilder;
      46: invokevirtual #124                // Method java/lang/StringBuilder.toString:()Ljava/lang/String;
      49: invokespecial #137                // Method java/io/IOException."<init>":(Ljava/lang/String;)V
      52: athrow
      53: return

  public de.sciss.proc.Workspace<?> read(java.net.URI, de.sciss.lucre.DataStore$Factory, scala.collection.immutable.Map<java.lang.String, java.lang.String>);
    Code:
       0: new           #92                 // class java/io/File
       3: dup
       4: aload_1
       5: invokespecial #145                // Method java/io/File."<init>":(Ljava/net/URI;)V
       8: astore        4
      10: aload_0
      11: aload         4
      13: invokespecial #147                // Method requireExists:(Ljava/io/File;)V
      16: new           #149                // class java/io/FileInputStream
      19: dup
      20: new           #92                 // class java/io/File
      23: dup
      24: aload         4
      26: ldc           #94                 // String open
      28: invokespecial #97                 // Method java/io/File."<init>":(Ljava/io/File;Ljava/lang/String;)V
      31: invokespecial #151                // Method java/io/FileInputStream."<init>":(Ljava/io/File;)V
      34: astore        5
      36: new           #153                // class java/util/Properties
      39: dup
      40: invokespecial #154                // Method java/util/Properties."<init>":()V
      43: astore        6
      45: aload         6
      47: aload         5
      49: invokevirtual #158                // Method java/util/Properties.load:(Ljava/io/InputStream;)V
      52: aload         5
      54: invokevirtual #161                // Method java/io/FileInputStream.close:()V
      57: aload         6
      59: ldc           #163                // String type
      61: invokevirtual #167                // Method java/util/Properties.getProperty:(Ljava/lang/String;)Ljava/lang/String;
      64: astore        8
      66: ldc           #169                // String confluent
      68: aload         8
      70: invokevirtual #173                // Method java/lang/Object.equals:(Ljava/lang/Object;)Z
      73: ifeq          80
      76: iconst_1
      77: goto          130
      80: ldc           #175                // String ephemeral
      82: aload         8
      84: invokevirtual #173                // Method java/lang/Object.equals:(Ljava/lang/Object;)Z
      87: ifeq          94
      90: iconst_0
      91: goto          130
      94: aload         8
      96: astore        9
      98: getstatic     #180                // Field scala/sys/package$.MODULE$:Lscala/sys/package$;
     101: new           #105                // class java/lang/StringBuilder
     104: dup
     105: ldc           #106                // int 25
     107: invokespecial #109                // Method java/lang/StringBuilder."<init>":(I)V
     110: ldc           #182                // String Invalid property \'type\':
     112: invokevirtual #115                // Method java/lang/StringBuilder.append:(Ljava/lang/String;)Ljava/lang/StringBuilder;
     115: aload         9
     117: invokevirtual #115                // Method java/lang/StringBuilder.append:(Ljava/lang/String;)Ljava/lang/StringBuilder;
     120: invokevirtual #124                // Method java/lang/StringBuilder.toString:()Ljava/lang/String;
     123: invokevirtual #186                // Method scala/sys/package$.error:(Ljava/lang/String;)Lscala/runtime/Nothing$;
     126: athrow
     127: nop
     128: nop
     129: athrow
     130: istore        7
     132: iload         7
     134: ifeq          151
     137: aload_0
     138: aload_1
     139: aload_2
     140: aload_3
     141: invokevirtual #190                // Method readConfluent:(Ljava/net/URI;Lde/sciss/lucre/DataStore$Factory;Lscala/collection/immutable/Map;)Lde/sciss/proc/WorkspacePlatform$Confluent;
     144: astore        11
     146: aload         11
     148: goto          162
     151: aload_0
     152: aload_1
     153: aload_2
     154: aload_3
     155: invokevirtual #194                // Method readDurable:(Ljava/net/URI;Lde/sciss/lucre/DataStore$Factory;Lscala/collection/immutable/Map;)Lde/sciss/proc/WorkspacePlatform$Durable;
     158: astore        12
     160: aload         12
     162: astore        10
     164: aload         10
     166: areturn

  public de.sciss.proc.WorkspacePlatform$Confluent readConfluent(java.net.URI, de.sciss.lucre.DataStore$Factory, scala.collection.immutable.Map);
    Code:
       0: new           #92                 // class java/io/File
       3: dup
       4: aload_1
       5: invokespecial #145                // Method java/io/File."<init>":(Ljava/net/URI;)V
       8: astore        4
      10: aload_0
      11: aload         4
      13: invokespecial #147                // Method requireExists:(Ljava/io/File;)V
      16: aload_0
      17: aload         4
      19: aload_2
      20: aload_3
      21: invokespecial #222                // Method applyConfluent:(Ljava/io/File;Lde/sciss/lucre/DataStore$Factory;Lscala/collection/immutable/Map;)Lde/sciss/proc/WorkspacePlatform$Confluent;
      24: areturn

  public de.sciss.proc.WorkspacePlatform$Confluent emptyConfluent(java.net.URI, de.sciss.lucre.DataStore$Factory, scala.collection.immutable.Map);
    Code:
       0: new           #92                 // class java/io/File
       3: dup
       4: aload_1
       5: invokespecial #145                // Method java/io/File."<init>":(Ljava/net/URI;)V
       8: astore        4
      10: aload_0
      11: aload         4
      13: invokespecial #225                // Method requireExistsNot:(Ljava/io/File;)V
      16: aload_0
      17: aload         4
      19: aload_2
      20: aload_3
      21: invokespecial #222                // Method applyConfluent:(Ljava/io/File;Lde/sciss/lucre/DataStore$Factory;Lscala/collection/immutable/Map;)Lde/sciss/proc/WorkspacePlatform$Confluent;
      24: areturn

  public de.sciss.proc.WorkspacePlatform$Durable readDurable(java.net.URI, de.sciss.lucre.DataStore$Factory, scala.collection.immutable.Map);
    Code:
       0: new           #92                 // class java/io/File
       3: dup
       4: aload_1
       5: invokespecial #145                // Method java/io/File."<init>":(Ljava/net/URI;)V
       8: astore        4
      10: aload_0
      11: aload         4
      13: invokespecial #147                // Method requireExists:(Ljava/io/File;)V
      16: aload_0
      17: aload         4
      19: aload_2
      20: aload_3
      21: invokespecial #229                // Method applyDurable:(Ljava/io/File;Lde/sciss/lucre/DataStore$Factory;Lscala/collection/immutable/Map;)Lde/sciss/proc/WorkspacePlatform$Durable;
      24: areturn

  public de.sciss.proc.WorkspacePlatform$Durable emptyDurable(java.net.URI, de.sciss.lucre.DataStore$Factory, scala.collection.immutable.Map);
    Code:
       0: new           #92                 // class java/io/File
       3: dup
       4: aload_1
       5: invokespecial #145                // Method java/io/File."<init>":(Ljava/net/URI;)V
       8: astore        4
      10: aload_0
      11: aload         4
      13: invokespecial #225                // Method requireExistsNot:(Ljava/io/File;)V
      16: aload_0
      17: aload         4
      19: aload_2
      20: aload_3
      21: invokespecial #229                // Method applyDurable:(Ljava/io/File;Lde/sciss/lucre/DataStore$Factory;Lscala/collection/immutable/Map;)Lde/sciss/proc/WorkspacePlatform$Durable;
      24: areturn

  private scala.Tuple2<de.sciss.lucre.DataStore$Factory, scala.collection.immutable.Map<java.lang.String, java.lang.String>> openDataStore(java.io.File, de.sciss.lucre.DataStore$Factory, boolean, scala.collection.immutable.Map<java.lang.String, java.lang.String>);
    Code:
       0: new           #153                // class java/util/Properties
       3: dup
       4: invokespecial #154                // Method java/util/Properties."<init>":()V
       7: astore        5
       9: new           #92                 // class java/io/File
      12: dup
      13: aload_1
      14: ldc           #94                 // String open
      16: invokespecial #97                 // Method java/io/File."<init>":(Ljava/io/File;Ljava/lang/String;)V
      19: astore        6
      21: aload         6
      23: invokevirtual #101                // Method java/io/File.isFile:()Z
      26: ifeq          65
      29: new           #149                // class java/io/FileInputStream
      32: dup
      33: aload         6
      35: invokespecial #151                // Method java/io/FileInputStream."<init>":(Ljava/io/File;)V
      38: astore        7
      40: aload         5
      42: aload         7
      44: invokevirtual #158                // Method java/util/Properties.load:(Ljava/io/InputStream;)V
      47: goto          60
      50: astore        8
      52: aload         7
      54: invokevirtual #161                // Method java/io/FileInputStream.close:()V
      57: aload         8
      59: athrow
      60: aload         7
      62: invokevirtual #161                // Method java/io/FileInputStream.close:()V
      65: new           #235                // class java/io/FileOutputStream
      68: dup
      69: aload         6
      71: invokespecial #236                // Method java/io/FileOutputStream."<init>":(Ljava/io/File;)V
      74: astore        9
      76: aload         5
      78: ldc           #163                // String type
      80: iload_3
      81: ifeq          89
      84: ldc           #169                // String confluent
      86: goto          91
      89: ldc           #175                // String ephemeral
      91: invokevirtual #240                // Method java/util/Properties.setProperty:(Ljava/lang/String;Ljava/lang/String;)Ljava/lang/Object;
      94: pop
      95: aload         4
      97: aload_0
      98: aload         5
     100: invokedynamic #262,  0            // InvokeDynamic #0:apply:(Lde/sciss/proc/impl/WorkspacePlatformImpl$;Ljava/util/Properties;)Lscala/Function1;
     105: invokeinterface #266,  2          // InterfaceMethod scala/collection/immutable/Map.foreach:(Lscala/Function1;)V
     110: aload         5
     112: aload         9
     114: ldc_w         #268                // String Mellite Workspace Meta-Info
     117: invokevirtual #272                // Method java/util/Properties.store:(Ljava/io/OutputStream;Ljava/lang/String;)V
     120: goto          133
     123: astore        10
     125: aload         9
     127: invokevirtual #273                // Method java/io/FileOutputStream.close:()V
     130: aload         10
     132: athrow
     133: aload         9
     135: invokevirtual #273                // Method java/io/FileOutputStream.close:()V
     138: getstatic     #278                // Field scala/Predef$.MODULE$:Lscala/Predef$;
     141: invokevirtual #282                // Method scala/Predef$.Map:()Lscala/collection/immutable/Map$;
     144: invokevirtual #288                // Method scala/collection/immutable/Map$.newBuilder:()Lscala/collection/mutable/Builder;
     147: astore        12
     149: aload         12
     151: aload         5
     153: invokevirtual #292                // Method java/util/Properties.size:()I
     156: invokeinterface #297,  2          // InterfaceMethod scala/collection/mutable/Builder.sizeHint:(I)V
     161: getstatic     #302                // Field scala/collection/JavaConverters$.MODULE$:Lscala/collection/JavaConverters$;
     164: aload         5
     166: invokevirtual #306                // Method java/util/Properties.stringPropertyNames:()Ljava/util/Set;
     169: invokevirtual #310                // Method scala/collection/JavaConverters$.asScalaSetConverter:(Ljava/util/Set;)Lscala/collection/JavaConverters$AsScala;
     172: invokevirtual #313                // Method scala/collection/JavaConverters$AsScala.asScala:()Ljava/lang/Object;
     175: checkcast     #315                // class scala/collection/mutable/Set
     178: astore        13
     180: aload         13
     182: aload_0
     183: aload         5
     185: aload         12
     187: invokedynamic #325,  0            // InvokeDynamic #1:apply:(Lde/sciss/proc/impl/WorkspacePlatformImpl$;Ljava/util/Properties;Lscala/collection/mutable/Builder;)Lscala/Function1;
     192: invokeinterface #326,  2          // InterfaceMethod scala/collection/mutable/Set.foreach:(Lscala/Function1;)V
     197: aload         12
     199: invokeinterface #329,  1          // InterfaceMethod scala/collection/mutable/Builder.result:()Ljava/lang/Object;
     204: checkcast     #214                // class scala/collection/immutable/Map
     207: astore        11
     209: getstatic     #334                // Field scala/Tuple2$.MODULE$:Lscala/Tuple2$;
     212: aload_2
     213: aload         11
     215: invokevirtual #337                // Method scala/Tuple2$.apply:(Ljava/lang/Object;Ljava/lang/Object;)Lscala/Tuple2;
     218: areturn
    Exception table:
       from    to  target type
          40    50    50   any
          76   123   123   any

  private de.sciss.proc.WorkspacePlatform$Confluent applyConfluent(java.io.File, de.sciss.lucre.DataStore$Factory, scala.collection.immutable.Map);
    Code:
       0: aload_0
       1: aload_1
       2: aload_2
       3: iconst_1
       4: aload_3
       5: invokespecial #347                // Method openDataStore:(Ljava/io/File;Lde/sciss/lucre/DataStore$Factory;ZLscala/collection/immutable/Map;)Lscala/Tuple2;
       8: astore        5
      10: aload         5
      12: ifnull        48
      15: aload         5
      17: invokevirtual #352                // Method scala/Tuple2._1:()Ljava/lang/Object;
      20: checkcast     #9                  // class de/sciss/lucre/DataStore$Factory
      23: astore        6
      25: aload         5
      27: invokevirtual #355                // Method scala/Tuple2._2:()Ljava/lang/Object;
      30: checkcast     #214                // class scala/collection/immutable/Map
      33: astore        7
      35: getstatic     #334                // Field scala/Tuple2$.MODULE$:Lscala/Tuple2$;
      38: aload         6
      40: aload         7
      42: invokevirtual #337                // Method scala/Tuple2$.apply:(Ljava/lang/Object;Ljava/lang/Object;)Lscala/Tuple2;
      45: goto          58
      48: new           #357                // class scala/MatchError
      51: dup
      52: aload         5
      54: invokespecial #360                // Method scala/MatchError."<init>":(Ljava/lang/Object;)V
      57: athrow
      58: astore        4
      60: aload         4
      62: invokevirtual #352                // Method scala/Tuple2._1:()Ljava/lang/Object;
      65: checkcast     #9                  // class de/sciss/lucre/DataStore$Factory
      68: astore        8
      70: aload         4
      72: invokevirtual #355                // Method scala/Tuple2._2:()Ljava/lang/Object;
      75: checkcast     #214                // class scala/collection/immutable/Map
      78: astore        9
      80: getstatic     #365                // Field de/sciss/proc/Confluent$.MODULE$:Lde/sciss/proc/Confluent$;
      83: aload         8
      85: invokevirtual #368                // Method de/sciss/proc/Confluent$.apply:(Lde/sciss/lucre/DataStore$Factory;)Lde/sciss/proc/Confluent;
      88: astore        10
      90: getstatic     #373                // Field de/sciss/proc/Cursors$.MODULE$:Lde/sciss/proc/Cursors$;
      93: invokevirtual #377                // Method de/sciss/proc/Cursors$.format:()Lde/sciss/serial/TFormat;
      96: astore        11
      98: aload         10
     100: aload_0
     101: invokedynamic #386,  0            // InvokeDynamic #2:apply:(Lde/sciss/proc/impl/WorkspacePlatformImpl$;)Lscala/Function1;
     106: aload_0
     107: invokedynamic #393,  0            // InvokeDynamic #3:apply:(Lde/sciss/proc/impl/WorkspacePlatformImpl$;)Lscala/Function1;
     112: aload_0
     113: invokespecial #395                // Method ConfluentFmt:()Lde/sciss/proc/impl/WorkspaceImpl$Fmt;
     116: aload         11
     118: invokeinterface #399,  5          // InterfaceMethod de/sciss/proc/Confluent.rootWithDurable:(Lscala/Function1;Lscala/Function1;Lde/sciss/serial/TFormat;Lde/sciss/serial/TFormat;)Lscala/Tuple2;
     123: astore        13
     125: aload         13
     127: ifnull        163
     130: aload         13
     132: invokevirtual #352                // Method scala/Tuple2._1:()Ljava/lang/Object;
     135: checkcast     #401                // class de/sciss/lucre/confluent/Source
     138: astore        14
     140: aload         13
     142: invokevirtual #355                // Method scala/Tuple2._2:()Ljava/lang/Object;
     145: checkcast     #403                // class de/sciss/proc/Cursors
     148: astore        15
     150: getstatic     #334                // Field scala/Tuple2$.MODULE$:Lscala/Tuple2$;
     153: aload         14
     155: aload         15
     157: invokevirtual #337                // Method scala/Tuple2$.apply:(Ljava/lang/Object;Ljava/lang/Object;)Lscala/Tuple2;
     160: goto          173
     163: new           #357                // class scala/MatchError
     166: dup
     167: aload         13
     169: invokespecial #360                // Method scala/MatchError."<init>":(Ljava/lang/Object;)V
     172: athrow
     173: astore        12
     175: aload         12
     177: invokevirtual #352                // Method scala/Tuple2._1:()Ljava/lang/Object;
     180: checkcast     #401                // class de/sciss/lucre/confluent/Source
     183: astore        16
     185: aload         12
     187: invokevirtual #355                // Method scala/Tuple2._2:()Ljava/lang/Object;
     190: checkcast     #403                // class de/sciss/proc/Cursors
     193: astore        17
     195: new           #47                 // class de/sciss/proc/impl/WorkspacePlatformImpl$ConfluentImpl
     198: dup
     199: aload_1
     200: aload         10
     202: aload         9
     204: aload         16
     206: aload         17
     208: invokespecial #406                // Method de/sciss/proc/impl/WorkspacePlatformImpl$ConfluentImpl."<init>":(Ljava/io/File;Lde/sciss/proc/Confluent;Lscala/collection/immutable/Map;Lde/sciss/lucre/Source;Lde/sciss/proc/Cursors;)V
     211: areturn

  private de.sciss.proc.WorkspacePlatform$Durable applyDurable(java.io.File, de.sciss.lucre.DataStore$Factory, scala.collection.immutable.Map);
    Code:
       0: aload_0
       1: aload_1
       2: aload_2
       3: iconst_0
       4: aload_3
       5: invokespecial #347                // Method openDataStore:(Ljava/io/File;Lde/sciss/lucre/DataStore$Factory;ZLscala/collection/immutable/Map;)Lscala/Tuple2;
       8: astore        5
      10: aload         5
      12: ifnull        48
      15: aload         5
      17: invokevirtual #352                // Method scala/Tuple2._1:()Ljava/lang/Object;
      20: checkcast     #9                  // class de/sciss/lucre/DataStore$Factory
      23: astore        6
      25: aload         5
      27: invokevirtual #355                // Method scala/Tuple2._2:()Ljava/lang/Object;
      30: checkcast     #214                // class scala/collection/immutable/Map
      33: astore        7
      35: getstatic     #334                // Field scala/Tuple2$.MODULE$:Lscala/Tuple2$;
      38: aload         6
      40: aload         7
      42: invokevirtual #337                // Method scala/Tuple2$.apply:(Ljava/lang/Object;Ljava/lang/Object;)Lscala/Tuple2;
      45: goto          58
      48: new           #357                // class scala/MatchError
      51: dup
      52: aload         5
      54: invokespecial #360                // Method scala/MatchError."<init>":(Ljava/lang/Object;)V
      57: athrow
      58: astore        4
      60: aload         4
      62: invokevirtual #352                // Method scala/Tuple2._1:()Ljava/lang/Object;
      65: checkcast     #9                  // class de/sciss/lucre/DataStore$Factory
      68: astore        8
      70: aload         4
      72: invokevirtual #355                // Method scala/Tuple2._2:()Ljava/lang/Object;
      75: checkcast     #214                // class scala/collection/immutable/Map
      78: astore        9
      80: getstatic     #421                // Field de/sciss/proc/Durable$.MODULE$:Lde/sciss/proc/Durable$;
      83: aload         8
      85: getstatic     #421                // Field de/sciss/proc/Durable$.MODULE$:Lde/sciss/proc/Durable$;
      88: invokevirtual #424                // Method de/sciss/proc/Durable$.apply$default$2:()Ljava/lang/String;
      91: invokevirtual #427                // Method de/sciss/proc/Durable$.apply:(Lde/sciss/lucre/DataStore$Factory;Ljava/lang/String;)Lde/sciss/proc/Durable;
      94: astore        10
      96: getstatic     #84                 // Field de/sciss/proc/impl/WorkspaceImpl$.MODULE$:Lde/sciss/proc/impl/WorkspaceImpl$;
      99: aload         10
     101: invokevirtual #431                // Method de/sciss/proc/impl/WorkspaceImpl$.initAccess:(Lde/sciss/lucre/Sys;)Lde/sciss/lucre/Source;
     104: astore        11
     106: new           #52                 // class de/sciss/proc/impl/WorkspacePlatformImpl$DurableImpl
     109: dup
     110: aload_1
     111: aload         10
     113: aload         9
     115: aload         11
     117: invokespecial #434                // Method de/sciss/proc/impl/WorkspacePlatformImpl$DurableImpl."<init>":(Ljava/io/File;Lde/sciss/proc/Durable;Lscala/collection/immutable/Map;Lde/sciss/lucre/Source;)V
     120: areturn

  public java.lang.String de$sciss$proc$impl$WorkspacePlatformImpl$$$fileBase(java.io.File);
    Code:
       0: aload_1
       1: invokevirtual #442                // Method java/io/File.getName:()Ljava/lang/String;
       4: astore_2
       5: aload_2
       6: bipush        46
       8: invokevirtual #446                // Method java/lang/String.lastIndexOf:(I)I
      11: istore_3
      12: iload_3
      13: iconst_0
      14: if_icmpge     21
      17: aload_2
      18: goto          27
      21: aload_2
      22: iconst_0
      23: iload_3
      24: invokevirtual #450                // Method java/lang/String.substring:(II)Ljava/lang/String;
      27: areturn

  private final java.lang.Object openDataStore$$anonfun$1(java.util.Properties, scala.Tuple2);
    Code:
       0: aload_2
       1: astore_3
       2: aload_3
       3: ifnull        35
       6: aload_3
       7: invokevirtual #352                // Method scala/Tuple2._1:()Ljava/lang/Object;
      10: checkcast     #216                // class java/lang/String
      13: astore        4
      15: aload_3
      16: invokevirtual #355                // Method scala/Tuple2._2:()Ljava/lang/Object;
      19: checkcast     #216                // class java/lang/String
      22: astore        5
      24: aload_1
      25: aload         4
      27: aload         5
      29: invokevirtual #240                // Method java/util/Properties.setProperty:(Ljava/lang/String;Ljava/lang/String;)Ljava/lang/Object;
      32: goto          44
      35: new           #357                // class scala/MatchError
      38: dup
      39: aload_3
      40: invokespecial #360                // Method scala/MatchError."<init>":(Ljava/lang/Object;)V
      43: athrow
      44: areturn

  private final scala.collection.mutable.Builder $anonfun$1(java.util.Properties, scala.collection.mutable.Builder, java.lang.String);
    Code:
       0: aload_1
       1: aload_3
       2: invokevirtual #167                // Method java/util/Properties.getProperty:(Ljava/lang/String;)Ljava/lang/String;
       5: astore        4
       7: aload_2
       8: getstatic     #334                // Field scala/Tuple2$.MODULE$:Lscala/Tuple2$;
      11: aload_3
      12: aload         4
      14: invokevirtual #337                // Method scala/Tuple2$.apply:(Ljava/lang/Object;Ljava/lang/Object;)Lscala/Tuple2;
      17: invokeinterface #464,  2          // InterfaceMethod scala/collection/mutable/Builder.$plus$eq:(Ljava/lang/Object;)Lscala/collection/mutable/Growable;
      22: checkcast     #294                // class scala/collection/mutable/Builder
      25: areturn

  private final de.sciss.proc.impl.WorkspaceImpl$Data $anonfun$2(de.sciss.proc.Confluent$Txn);
    Code:
       0: getstatic     #468                // Field de/sciss/proc/impl/WorkspaceImpl$Data$.MODULE$:Lde/sciss/proc/impl/WorkspaceImpl$Data$;
       3: aload_1
       4: invokevirtual #471                // Method de/sciss/proc/impl/WorkspaceImpl$Data$.apply:(Lde/sciss/lucre/Txn;)Lde/sciss/proc/impl/WorkspaceImpl$Data;
       7: areturn

  private final de.sciss.proc.Cursors $anonfun$3(de.sciss.proc.Durable$Txn);
    Code:
       0: getstatic     #373                // Field de/sciss/proc/Cursors$.MODULE$:Lde/sciss/proc/Cursors$;
       3: getstatic     #477                // Field de/sciss/lucre/confluent/Access$.MODULE$:Lde/sciss/lucre/confluent/Access$;
       6: invokevirtual #481                // Method de/sciss/lucre/confluent/Access$.root:()Lde/sciss/lucre/confluent/Access;
       9: aload_1
      10: invokevirtual #484                // Method de/sciss/proc/Cursors$.apply:(Lde/sciss/lucre/confluent/Access;Lde/sciss/lucre/Txn;)Lde/sciss/proc/Cursors;
      13: astore_2
      14: aload_2
      15: getstatic     #489                // Field de/sciss/lucre/StringObj$.MODULE$:Lde/sciss/lucre/StringObj$;
      18: ldc_w         #490                // String root
      21: aload_1
      22: invokevirtual #494                // Method de/sciss/lucre/StringObj$.newConst:(Ljava/lang/Object;Lde/sciss/lucre/Txn;)Lde/sciss/lucre/Expr$Const;
      25: checkcast     #496                // class de/sciss/lucre/StringObj
      28: aload_1
      29: invokeinterface #500,  3          // InterfaceMethod de/sciss/proc/Cursors.name_$eq:(Lde/sciss/lucre/StringObj;Lde/sciss/lucre/Txn;)V
      34: aload_2
      35: areturn

  private static java.lang.Object $deserializeLambda$(java.lang.invoke.SerializedLambda);
    Code:
       0: aload_0
       1: invokedynamic #514,  0            // InvokeDynamic #4:lambdaDeserialize:(Ljava/lang/invoke/SerializedLambda;)Ljava/lang/Object;
       6: areturn
}
