Compiled from "MetadataBuilder.java"
public class org.jboss.wsf.stack.cxf.metadata.MetadataBuilder {
  public org.jboss.wsf.stack.cxf.metadata.MetadataBuilder();
    Code:
       0: aload_0
       1: invokespecial #1                  // Method java/lang/Object."<init>":()V
       4: return

  public org.jboss.wsf.stack.cxf.metadata.services.DDBeans build(org.jboss.wsf.spi.deployment.Deployment);
    Code:
       0: aload_1
       1: ldc           #2                  // class org/jboss/wsf/spi/metadata/config/SOAPAddressRewriteMetadata
       3: invokeinterface #3,  2            // InterfaceMethod org/jboss/wsf/spi/deployment/Deployment.getAttachment:(Ljava/lang/Class;)Ljava/lang/Object;
       8: checkcast     #2                  // class org/jboss/wsf/spi/metadata/config/SOAPAddressRewriteMetadata
      11: astore_2
      12: new           #4                  // class java/util/HashMap
      15: dup
      16: invokespecial #5                  // Method java/util/HashMap."<init>":()V
      19: astore_3
      20: new           #4                  // class java/util/HashMap
      23: dup
      24: invokespecial #5                  // Method java/util/HashMap."<init>":()V
      27: astore        4
      29: new           #6                  // class org/jboss/wsf/stack/cxf/metadata/services/DDBeans
      32: dup
      33: invokespecial #7                  // Method org/jboss/wsf/stack/cxf/metadata/services/DDBeans."<init>":()V
      36: astore        5
      38: aload_1
      39: invokeinterface #8,  1            // InterfaceMethod org/jboss/wsf/spi/deployment/Deployment.getService:()Lorg/jboss/wsf/spi/deployment/Service;
      44: invokeinterface #9,  1            // InterfaceMethod org/jboss/wsf/spi/deployment/Service.getEndpoints:()Ljava/util/List;
      49: invokeinterface #10,  1           // InterfaceMethod java/util/List.iterator:()Ljava/util/Iterator;
      54: astore        6
      56: aload         6
      58: invokeinterface #11,  1           // InterfaceMethod java/util/Iterator.hasNext:()Z
      63: ifeq          212
      66: aload         6
      68: invokeinterface #12,  1           // InterfaceMethod java/util/Iterator.next:()Ljava/lang/Object;
      73: checkcast     #13                 // class org/jboss/wsf/spi/deployment/Endpoint
      76: astore        7
      78: aload_0
      79: aload         7
      81: invokeinterface #14,  1           // InterfaceMethod org/jboss/wsf/spi/deployment/Endpoint.getTargetBeanClass:()Ljava/lang/Class;
      86: aload_1
      87: checkcast     #15                 // class org/jboss/wsf/spi/deployment/ArchiveDeployment
      90: aload         7
      92: invokevirtual #16                 // Method createDDEndpoint:(Ljava/lang/Class;Lorg/jboss/wsf/spi/deployment/ArchiveDeployment;Lorg/jboss/wsf/spi/deployment/Endpoint;)Lorg/jboss/wsf/stack/cxf/metadata/services/DDEndpoint;
      95: astore        8
      97: aload         7
      99: instanceof    #17                 // class org/jboss/wsf/spi/deployment/HttpEndpoint
     102: ifeq          115
     105: aload         8
     107: ldc           #18                 // class org/jboss/wsf/stack/cxf/JBossWSInvoker
     109: invokevirtual #19                 // Method java/lang/Class.getName:()Ljava/lang/String;
     112: invokevirtual #20                 // Method org/jboss/wsf/stack/cxf/metadata/services/DDEndpoint.setInvoker:(Ljava/lang/String;)V
     115: aload_0
     116: aload         8
     118: aload_1
     119: checkcast     #15                 // class org/jboss/wsf/spi/deployment/ArchiveDeployment
     122: invokespecial #21                 // Method processWSDDContribution:(Lorg/jboss/wsf/stack/cxf/metadata/services/DDEndpoint;Lorg/jboss/wsf/spi/deployment/ArchiveDeployment;)V
     125: aload_0
     126: aload         8
     128: aload_1
     129: checkcast     #15                 // class org/jboss/wsf/spi/deployment/ArchiveDeployment
     132: invokeinterface #22,  1           // InterfaceMethod org/jboss/wsf/spi/deployment/ArchiveDeployment.getResourceResolver:()Lorg/jboss/wsf/spi/deployment/ResourceResolver;
     137: invokevirtual #23                 // Method getWsdlLocationURL:(Lorg/jboss/wsf/stack/cxf/metadata/services/DDEndpoint;Lorg/jboss/wsf/spi/deployment/ResourceResolver;)Ljava/net/URL;
     140: astore        9
     142: aload_0
     143: aload         8
     145: aload         9
     147: aload_2
     148: aload         4
     150: invokevirtual #24                 // Method processAddressRewrite:(Lorg/jboss/wsf/stack/cxf/metadata/services/DDEndpoint;Ljava/net/URL;Lorg/jboss/wsf/spi/metadata/config/SOAPAddressRewriteMetadata;Ljava/util/Map;)V
     153: getstatic     #25                 // Field org/jboss/wsf/stack/cxf/Loggers.METADATA_LOGGER:Lorg/jboss/wsf/stack/cxf/Loggers;
     156: getstatic     #25                 // Field org/jboss/wsf/stack/cxf/Loggers.METADATA_LOGGER:Lorg/jboss/wsf/stack/cxf/Loggers;
     159: invokeinterface #26,  1           // InterfaceMethod org/jboss/wsf/stack/cxf/Loggers.isDebugEnabled:()Z
     164: ifeq          175
     167: aload         8
     169: invokevirtual #27                 // Method org/jboss/wsf/stack/cxf/metadata/services/DDEndpoint.toStringExtended:()Ljava/lang/String;
     172: goto          180
     175: aload         8
     177: invokevirtual #28                 // Method org/jboss/wsf/stack/cxf/metadata/services/DDEndpoint.toString:()Ljava/lang/String;
     180: invokeinterface #29,  2           // InterfaceMethod org/jboss/wsf/stack/cxf/Loggers.addingServiceEndpointMetadata:(Ljava/lang/Object;)V
     185: aload         5
     187: aload         8
     189: invokevirtual #30                 // Method org/jboss/wsf/stack/cxf/metadata/services/DDBeans.addEndpoint:(Lorg/jboss/wsf/stack/cxf/metadata/services/DDEndpoint;)V
     192: aload_3
     193: aload         8
     195: invokevirtual #31                 // Method org/jboss/wsf/stack/cxf/metadata/services/DDEndpoint.getServiceName:()Ljavax/xml/namespace/QName;
     198: aload         8
     200: invokevirtual #32                 // Method org/jboss/wsf/stack/cxf/metadata/services/DDEndpoint.getAddress:()Ljava/lang/String;
     203: invokeinterface #33,  3           // InterfaceMethod java/util/Map.put:(Ljava/lang/Object;Ljava/lang/Object;)Ljava/lang/Object;
     208: pop
     209: goto          56
     212: aload_1
     213: ldc           #34                 // String ServiceAddressMap
     215: aload_3
     216: invokeinterface #35,  3           // InterfaceMethod org/jboss/wsf/spi/deployment/Deployment.setProperty:(Ljava/lang/String;Ljava/lang/Object;)V
     221: aload         5
     223: areturn

  protected boolean isMtomEnabled(java.lang.Class<?>);
    Code:
       0: aload_1
       1: ldc           #36                 // class javax/xml/ws/BindingType
       3: invokevirtual #37                 // Method java/lang/Class.getAnnotation:(Ljava/lang/Class;)Ljava/lang/annotation/Annotation;
       6: checkcast     #36                 // class javax/xml/ws/BindingType
       9: astore_2
      10: aload_1
      11: ldc           #38                 // class javax/xml/ws/soap/MTOM
      13: invokevirtual #37                 // Method java/lang/Class.getAnnotation:(Ljava/lang/Class;)Ljava/lang/annotation/Annotation;
      16: checkcast     #38                 // class javax/xml/ws/soap/MTOM
      19: astore_3
      20: aload_3
      21: ifnull        37
      24: aload_3
      25: invokeinterface #39,  1           // InterfaceMethod javax/xml/ws/soap/MTOM.enabled:()Z
      30: ifeq          37
      33: iconst_1
      34: goto          38
      37: iconst_0
      38: istore        4
      40: iload         4
      42: ifne          84
      45: aload_2
      46: ifnull        84
      49: aload_2
      50: invokeinterface #40,  1           // InterfaceMethod javax/xml/ws/BindingType.value:()Ljava/lang/String;
      55: astore        5
      57: aload         5
      59: ldc           #42                 // String http://schemas.xmlsoap.org/wsdl/soap/http?mtom=true
      61: invokevirtual #43                 // Method java/lang/String.equals:(Ljava/lang/Object;)Z
      64: ifne          77
      67: aload         5
      69: ldc           #44                 // String http://www.w3.org/2003/05/soap/bindings/HTTP/?mtom=true
      71: invokevirtual #43                 // Method java/lang/String.equals:(Ljava/lang/Object;)Z
      74: ifeq          81
      77: iconst_1
      78: goto          82
      81: iconst_0
      82: istore        4
      84: iload         4
      86: ireturn

  private void processWSDDContribution(org.jboss.wsf.stack.cxf.metadata.services.DDEndpoint, org.jboss.wsf.spi.deployment.ArchiveDeployment);
    Code:
       0: aload_2
       1: ldc           #45                 // class org/jboss/wsf/spi/metadata/webservices/WebservicesMetaData
       3: invokeinterface #46,  2           // InterfaceMethod org/jboss/wsf/spi/deployment/ArchiveDeployment.getAttachment:(Ljava/lang/Class;)Ljava/lang/Object;
       8: checkcast     #45                 // class org/jboss/wsf/spi/metadata/webservices/WebservicesMetaData
      11: astore_3
      12: aload_3
      13: ifnull        353
      16: aload_3
      17: invokevirtual #47                 // Method org/jboss/wsf/spi/metadata/webservices/WebservicesMetaData.getWebserviceDescriptions:()[Lorg/jboss/wsf/spi/metadata/webservices/WebserviceDescriptionMetaData;
      20: astore        4
      22: aload         4
      24: arraylength
      25: istore        5
      27: iconst_0
      28: istore        6
      30: iload         6
      32: iload         5
      34: if_icmpge     353
      37: aload         4
      39: iload         6
      41: aaload
      42: astore        7
      44: aload         7
      46: invokevirtual #48                 // Method org/jboss/wsf/spi/metadata/webservices/WebserviceDescriptionMetaData.getPortComponents:()[Lorg/jboss/wsf/spi/metadata/webservices/PortComponentMetaData;
      49: astore        8
      51: aload         8
      53: arraylength
      54: istore        9
      56: iconst_0
      57: istore        10
      59: iload         10
      61: iload         9
      63: if_icmpge     347
      66: aload         8
      68: iload         10
      70: aaload
      71: astore        11
      73: aload         11
      75: invokevirtual #49                 // Method org/jboss/wsf/spi/metadata/webservices/PortComponentMetaData.getEjbLink:()Ljava/lang/String;
      78: ifnull        89
      81: aload         11
      83: invokevirtual #49                 // Method org/jboss/wsf/spi/metadata/webservices/PortComponentMetaData.getEjbLink:()Ljava/lang/String;
      86: goto          94
      89: aload         11
      91: invokevirtual #50                 // Method org/jboss/wsf/spi/metadata/webservices/PortComponentMetaData.getServletLink:()Ljava/lang/String;
      94: astore        12
      96: aload_1
      97: invokevirtual #51                 // Method org/jboss/wsf/stack/cxf/metadata/services/DDEndpoint.getId:()Ljava/lang/String;
     100: astore        13
     102: aload         13
     104: aload         12
     106: invokevirtual #43                 // Method java/lang/String.equals:(Ljava/lang/Object;)Z
     109: ifne          115
     112: goto          341
     115: aload         11
     117: invokevirtual #52                 // Method org/jboss/wsf/spi/metadata/webservices/PortComponentMetaData.getWsdlPort:()Ljavax/xml/namespace/QName;
     120: ifnull        151
     123: getstatic     #25                 // Field org/jboss/wsf/stack/cxf/Loggers.METADATA_LOGGER:Lorg/jboss/wsf/stack/cxf/Loggers;
     126: aload         13
     128: aload_1
     129: invokevirtual #53                 // Method org/jboss/wsf/stack/cxf/metadata/services/DDEndpoint.getPortName:()Ljavax/xml/namespace/QName;
     132: aload         11
     134: invokevirtual #52                 // Method org/jboss/wsf/spi/metadata/webservices/PortComponentMetaData.getWsdlPort:()Ljavax/xml/namespace/QName;
     137: invokeinterface #54,  4           // InterfaceMethod org/jboss/wsf/stack/cxf/Loggers.overridePortName:(Ljava/lang/String;Ljavax/xml/namespace/QName;Ljavax/xml/namespace/QName;)V
     142: aload_1
     143: aload         11
     145: invokevirtual #52                 // Method org/jboss/wsf/spi/metadata/webservices/PortComponentMetaData.getWsdlPort:()Ljavax/xml/namespace/QName;
     148: invokevirtual #55                 // Method org/jboss/wsf/stack/cxf/metadata/services/DDEndpoint.setPortName:(Ljavax/xml/namespace/QName;)V
     151: aload         11
     153: invokevirtual #56                 // Method org/jboss/wsf/spi/metadata/webservices/PortComponentMetaData.getWsdlService:()Ljavax/xml/namespace/QName;
     156: ifnull        187
     159: getstatic     #25                 // Field org/jboss/wsf/stack/cxf/Loggers.METADATA_LOGGER:Lorg/jboss/wsf/stack/cxf/Loggers;
     162: aload         13
     164: aload_1
     165: invokevirtual #31                 // Method org/jboss/wsf/stack/cxf/metadata/services/DDEndpoint.getServiceName:()Ljavax/xml/namespace/QName;
     168: aload         11
     170: invokevirtual #56                 // Method org/jboss/wsf/spi/metadata/webservices/PortComponentMetaData.getWsdlService:()Ljavax/xml/namespace/QName;
     173: invokeinterface #57,  4           // InterfaceMethod org/jboss/wsf/stack/cxf/Loggers.overrideServiceName:(Ljava/lang/String;Ljavax/xml/namespace/QName;Ljavax/xml/namespace/QName;)V
     178: aload_1
     179: aload         11
     181: invokevirtual #56                 // Method org/jboss/wsf/spi/metadata/webservices/PortComponentMetaData.getWsdlService:()Ljavax/xml/namespace/QName;
     184: invokevirtual #58                 // Method org/jboss/wsf/stack/cxf/metadata/services/DDEndpoint.setServiceName:(Ljavax/xml/namespace/QName;)V
     187: aload         11
     189: invokevirtual #59                 // Method org/jboss/wsf/spi/metadata/webservices/PortComponentMetaData.getHandlerChains:()Lorg/jboss/wsf/spi/metadata/j2ee/serviceref/UnifiedHandlerChainsMetaData;
     192: astore        14
     194: aload         14
     196: ifnull        212
     199: aload_1
     200: aload_0
     201: aload         14
     203: invokevirtual #60                 // Method org/jboss/wsf/spi/metadata/j2ee/serviceref/UnifiedHandlerChainsMetaData.getHandlerChains:()Ljava/util/List;
     206: invokespecial #61                 // Method convertEndpointHandlers:(Ljava/util/List;)Ljava/util/List;
     209: invokevirtual #62                 // Method org/jboss/wsf/stack/cxf/metadata/services/DDEndpoint.setHandlers:(Ljava/util/List;)V
     212: aload         11
     214: invokevirtual #63                 // Method org/jboss/wsf/spi/metadata/webservices/PortComponentMetaData.isMtomEnabled:()Z
     217: ifeq          244
     220: getstatic     #25                 // Field org/jboss/wsf/stack/cxf/Loggers.METADATA_LOGGER:Lorg/jboss/wsf/stack/cxf/Loggers;
     223: aload         13
     225: invokeinterface #64,  2           // InterfaceMethod org/jboss/wsf/stack/cxf/Loggers.enableMTOM:(Ljava/lang/String;)V
     230: aload_1
     231: iconst_1
     232: invokevirtual #65                 // Method org/jboss/wsf/stack/cxf/metadata/services/DDEndpoint.setMtomEnabled:(Z)V
     235: aload_1
     236: aload         11
     238: invokevirtual #66                 // Method org/jboss/wsf/spi/metadata/webservices/PortComponentMetaData.getMtomThreshold:()I
     241: invokevirtual #67                 // Method org/jboss/wsf/stack/cxf/metadata/services/DDEndpoint.setMtomThreshold:(I)V
     244: aload         11
     246: invokevirtual #68                 // Method org/jboss/wsf/spi/metadata/webservices/PortComponentMetaData.isAddressingEnabled:()Z
     249: ifeq          285
     252: getstatic     #25                 // Field org/jboss/wsf/stack/cxf/Loggers.METADATA_LOGGER:Lorg/jboss/wsf/stack/cxf/Loggers;
     255: aload         13
     257: invokeinterface #69,  2           // InterfaceMethod org/jboss/wsf/stack/cxf/Loggers.enableAddressing:(Ljava/lang/String;)V
     262: aload_1
     263: iconst_1
     264: invokevirtual #70                 // Method org/jboss/wsf/stack/cxf/metadata/services/DDEndpoint.setAddressingEnabled:(Z)V
     267: aload_1
     268: aload         11
     270: invokevirtual #71                 // Method org/jboss/wsf/spi/metadata/webservices/PortComponentMetaData.isAddressingRequired:()Z
     273: invokevirtual #72                 // Method org/jboss/wsf/stack/cxf/metadata/services/DDEndpoint.setAddressingRequired:(Z)V
     276: aload_1
     277: aload         11
     279: invokevirtual #73                 // Method org/jboss/wsf/spi/metadata/webservices/PortComponentMetaData.getAddressingResponses:()Ljava/lang/String;
     282: invokevirtual #74                 // Method org/jboss/wsf/stack/cxf/metadata/services/DDEndpoint.setAddressingResponses:(Ljava/lang/String;)V
     285: aload         11
     287: invokevirtual #75                 // Method org/jboss/wsf/spi/metadata/webservices/PortComponentMetaData.isRespectBindingEnabled:()Z
     290: ifeq          308
     293: getstatic     #25                 // Field org/jboss/wsf/stack/cxf/Loggers.METADATA_LOGGER:Lorg/jboss/wsf/stack/cxf/Loggers;
     296: aload         13
     298: invokeinterface #76,  2           // InterfaceMethod org/jboss/wsf/stack/cxf/Loggers.enableRespectBinding:(Ljava/lang/String;)V
     303: aload_1
     304: iconst_1
     305: invokevirtual #77                 // Method org/jboss/wsf/stack/cxf/metadata/services/DDEndpoint.setRespectBindingEnabled:(Z)V
     308: aload         11
     310: invokevirtual #78                 // Method org/jboss/wsf/spi/metadata/webservices/PortComponentMetaData.getWebserviceDescription:()Lorg/jboss/wsf/spi/metadata/webservices/WebserviceDescriptionMetaData;
     313: invokevirtual #79                 // Method org/jboss/wsf/spi/metadata/webservices/WebserviceDescriptionMetaData.getWsdlFile:()Ljava/lang/String;
     316: astore        15
     318: aload         15
     320: ifnull        341
     323: getstatic     #25                 // Field org/jboss/wsf/stack/cxf/Loggers.METADATA_LOGGER:Lorg/jboss/wsf/stack/cxf/Loggers;
     326: aload         13
     328: aload         15
     330: invokeinterface #80,  3           // InterfaceMethod org/jboss/wsf/stack/cxf/Loggers.overridingWsdlFileLocation:(Ljava/lang/String;Ljava/lang/String;)V
     335: aload_1
     336: aload         15
     338: invokevirtual #81                 // Method org/jboss/wsf/stack/cxf/metadata/services/DDEndpoint.setWsdlLocation:(Ljava/lang/String;)V
     341: iinc          10, 1
     344: goto          59
     347: iinc          6, 1
     350: goto          30
     353: return

  private java.util.List<java.lang.String> convertEndpointHandlers(java.util.List<org.jboss.wsf.spi.metadata.j2ee.serviceref.UnifiedHandlerChainMetaData>);
    Code:
       0: new           #82                 // class java/util/LinkedList
       3: dup
       4: invokespecial #83                 // Method java/util/LinkedList."<init>":()V
       7: astore_2
       8: aload_1
       9: ifnull        157
      12: aload_1
      13: invokeinterface #10,  1           // InterfaceMethod java/util/List.iterator:()Ljava/util/Iterator;
      18: astore_3
      19: aload_3
      20: invokeinterface #11,  1           // InterfaceMethod java/util/Iterator.hasNext:()Z
      25: ifeq          157
      28: aload_3
      29: invokeinterface #12,  1           // InterfaceMethod java/util/Iterator.next:()Ljava/lang/Object;
      34: checkcast     #84                 // class org/jboss/wsf/spi/metadata/j2ee/serviceref/UnifiedHandlerChainMetaData
      37: astore        4
      39: aload         4
      41: invokevirtual #85                 // Method org/jboss/wsf/spi/metadata/j2ee/serviceref/UnifiedHandlerChainMetaData.getPortNamePattern:()Ljavax/xml/namespace/QName;
      44: ifnonnull     63
      47: aload         4
      49: invokevirtual #86                 // Method org/jboss/wsf/spi/metadata/j2ee/serviceref/UnifiedHandlerChainMetaData.getProtocolBindings:()Ljava/lang/String;
      52: ifnonnull     63
      55: aload         4
      57: invokevirtual #87                 // Method org/jboss/wsf/spi/metadata/j2ee/serviceref/UnifiedHandlerChainMetaData.getServiceNamePattern:()Ljavax/xml/namespace/QName;
      60: ifnull        71
      63: getstatic     #25                 // Field org/jboss/wsf/stack/cxf/Loggers.METADATA_LOGGER:Lorg/jboss/wsf/stack/cxf/Loggers;
      66: invokeinterface #88,  1           // InterfaceMethod org/jboss/wsf/stack/cxf/Loggers.filtersNotSupported:()V
      71: aload         4
      73: invokevirtual #89                 // Method org/jboss/wsf/spi/metadata/j2ee/serviceref/UnifiedHandlerChainMetaData.getHandlers:()Ljava/util/List;
      76: invokeinterface #10,  1           // InterfaceMethod java/util/List.iterator:()Ljava/util/Iterator;
      81: astore        5
      83: aload         5
      85: invokeinterface #11,  1           // InterfaceMethod java/util/Iterator.hasNext:()Z
      90: ifeq          154
      93: aload         5
      95: invokeinterface #12,  1           // InterfaceMethod java/util/Iterator.next:()Ljava/lang/Object;
     100: checkcast     #90                 // class org/jboss/wsf/spi/metadata/j2ee/serviceref/UnifiedHandlerMetaData
     103: astore        6
     105: aload         6
     107: invokevirtual #91                 // Method org/jboss/wsf/spi/metadata/j2ee/serviceref/UnifiedHandlerMetaData.getInitParams:()Ljava/util/List;
     110: ifnull        139
     113: aload         6
     115: invokevirtual #91                 // Method org/jboss/wsf/spi/metadata/j2ee/serviceref/UnifiedHandlerMetaData.getInitParams:()Ljava/util/List;
     118: invokeinterface #92,  1           // InterfaceMethod java/util/List.isEmpty:()Z
     123: ifne          139
     126: getstatic     #25                 // Field org/jboss/wsf/stack/cxf/Loggers.METADATA_LOGGER:Lorg/jboss/wsf/stack/cxf/Loggers;
     129: aload         6
     131: invokevirtual #93                 // Method org/jboss/wsf/spi/metadata/j2ee/serviceref/UnifiedHandlerMetaData.getHandlerName:()Ljava/lang/String;
     134: invokeinterface #94,  2           // InterfaceMethod org/jboss/wsf/stack/cxf/Loggers.initParamsSupported:(Ljava/lang/String;)V
     139: aload_2
     140: aload         6
     142: invokevirtual #95                 // Method org/jboss/wsf/spi/metadata/j2ee/serviceref/UnifiedHandlerMetaData.getHandlerClass:()Ljava/lang/String;
     145: invokeinterface #96,  2           // InterfaceMethod java/util/List.add:(Ljava/lang/Object;)Z
     150: pop
     151: goto          83
     154: goto          19
     157: aload_2
     158: areturn

  protected org.jboss.wsf.stack.cxf.metadata.services.DDEndpoint createDDEndpoint(java.lang.Class<?>, org.jboss.wsf.spi.deployment.ArchiveDeployment, org.jboss.wsf.spi.deployment.Endpoint);
    Code:
       0: aload_1
       1: ldc           #97                 // class javax/jws/WebService
       3: invokevirtual #37                 // Method java/lang/Class.getAnnotation:(Ljava/lang/Class;)Ljava/lang/annotation/Annotation;
       6: checkcast     #97                 // class javax/jws/WebService
       9: astore        4
      11: aload_1
      12: ldc           #98                 // class javax/xml/ws/WebServiceProvider
      14: invokevirtual #37                 // Method java/lang/Class.getAnnotation:(Ljava/lang/Class;)Ljava/lang/annotation/Annotation;
      17: checkcast     #98                 // class javax/xml/ws/WebServiceProvider
      20: astore        5
      22: aconst_null
      23: astore        6
      25: aload         4
      27: ifnull        40
      30: aload         4
      32: invokeinterface #99,  1           // InterfaceMethod javax/jws/WebService.name:()Ljava/lang/String;
      37: goto          42
      40: ldc           #100                // String
      42: astore        8
      44: aload         8
      46: invokevirtual #101                // Method java/lang/String.length:()I
      49: ifne          58
      52: aload_1
      53: invokestatic  #102                // Method org/jboss/ws/common/JavaUtils.getJustClassName:(Ljava/lang/Class;)Ljava/lang/String;
      56: astore        8
      58: aload         4
      60: ifnull        73
      63: aload         4
      65: invokeinterface #103,  1          // InterfaceMethod javax/jws/WebService.serviceName:()Ljava/lang/String;
      70: goto          80
      73: aload         5
      75: invokeinterface #104,  1          // InterfaceMethod javax/xml/ws/WebServiceProvider.serviceName:()Ljava/lang/String;
      80: astore        9
      82: aload         9
      84: invokevirtual #101                // Method java/lang/String.length:()I
      87: ifne          114
      90: new           #105                // class java/lang/StringBuilder
      93: dup
      94: invokespecial #106                // Method java/lang/StringBuilder."<init>":()V
      97: aload_1
      98: invokestatic  #102                // Method org/jboss/ws/common/JavaUtils.getJustClassName:(Ljava/lang/Class;)Ljava/lang/String;
     101: invokevirtual #107                // Method java/lang/StringBuilder.append:(Ljava/lang/String;)Ljava/lang/StringBuilder;
     104: ldc           #108                // String Service
     106: invokevirtual #107                // Method java/lang/StringBuilder.append:(Ljava/lang/String;)Ljava/lang/StringBuilder;
     109: invokevirtual #109                // Method java/lang/StringBuilder.toString:()Ljava/lang/String;
     112: astore        9
     114: aload         4
     116: ifnull        129
     119: aload         4
     121: invokeinterface #110,  1          // InterfaceMethod javax/jws/WebService.targetNamespace:()Ljava/lang/String;
     126: goto          136
     129: aload         5
     131: invokeinterface #111,  1          // InterfaceMethod javax/xml/ws/WebServiceProvider.targetNamespace:()Ljava/lang/String;
     136: astore        10
     138: aload         10
     140: invokevirtual #101                // Method java/lang/String.length:()I
     143: ifne          155
     146: aload_1
     147: invokestatic  #112                // Method org/jboss/ws/common/JavaUtils.getPackageName:(Ljava/lang/Class;)Ljava/lang/String;
     150: invokestatic  #113                // Method getTypeNamespace:(Ljava/lang/String;)Ljava/lang/String;
     153: astore        10
     155: aload         4
     157: ifnull        170
     160: aload         4
     162: invokeinterface #114,  1          // InterfaceMethod javax/jws/WebService.portName:()Ljava/lang/String;
     167: goto          177
     170: aload         5
     172: invokeinterface #115,  1          // InterfaceMethod javax/xml/ws/WebServiceProvider.portName:()Ljava/lang/String;
     177: astore        11
     179: aload         11
     181: invokevirtual #101                // Method java/lang/String.length:()I
     184: ifne          209
     187: new           #105                // class java/lang/StringBuilder
     190: dup
     191: invokespecial #106                // Method java/lang/StringBuilder."<init>":()V
     194: aload         8
     196: invokevirtual #107                // Method java/lang/StringBuilder.append:(Ljava/lang/String;)Ljava/lang/StringBuilder;
     199: ldc           #116                // String Port
     201: invokevirtual #107                // Method java/lang/StringBuilder.append:(Ljava/lang/String;)Ljava/lang/StringBuilder;
     204: invokevirtual #109                // Method java/lang/StringBuilder.toString:()Ljava/lang/String;
     207: astore        11
     209: aload         4
     211: ifnull        399
     214: aload         4
     216: invokeinterface #117,  1          // InterfaceMethod javax/jws/WebService.endpointInterface:()Ljava/lang/String;
     221: invokevirtual #101                // Method java/lang/String.length:()I
     224: ifle          399
     227: aload         4
     229: invokeinterface #117,  1          // InterfaceMethod javax/jws/WebService.endpointInterface:()Ljava/lang/String;
     234: astore        7
     236: aload_2
     237: invokeinterface #118,  1          // InterfaceMethod org/jboss/wsf/spi/deployment/ArchiveDeployment.getClassLoader:()Ljava/lang/ClassLoader;
     242: astore        13
     244: aconst_null
     245: aload         13
     247: if_acmpne     260
     250: getstatic     #119                // Field org/jboss/wsf/stack/cxf/Messages.MESSAGES:Lorg/jboss/wsf/stack/cxf/Messages;
     253: aload_2
     254: invokeinterface #120,  2          // InterfaceMethod org/jboss/wsf/stack/cxf/Messages.runtimeLoaderCannotBeNull:(Lorg/jboss/wsf/spi/deployment/Deployment;)Ljava/lang/IllegalStateException;
     259: athrow
     260: aload         13
     262: aload         7
     264: invokevirtual #121                // Method java/lang/ClassLoader.loadClass:(Ljava/lang/String;)Ljava/lang/Class;
     267: astore        6
     269: goto          284
     272: astore        14
     274: new           #123                // class java/lang/RuntimeException
     277: dup
     278: aload         14
     280: invokespecial #124                // Method java/lang/RuntimeException."<init>":(Ljava/lang/Throwable;)V
     283: athrow
     284: aload         6
     286: ldc           #97                 // class javax/jws/WebService
     288: invokevirtual #37                 // Method java/lang/Class.getAnnotation:(Ljava/lang/Class;)Ljava/lang/annotation/Annotation;
     291: checkcast     #97                 // class javax/jws/WebService
     294: astore        14
     296: aload         14
     298: ifnonnull     312
     301: getstatic     #119                // Field org/jboss/wsf/stack/cxf/Messages.MESSAGES:Lorg/jboss/wsf/stack/cxf/Messages;
     304: aload         7
     306: invokeinterface #125,  2          // InterfaceMethod org/jboss/wsf/stack/cxf/Messages.webserviceAnnotationNotFound:(Ljava/lang/String;)Ljava/lang/RuntimeException;
     311: athrow
     312: aload         14
     314: invokeinterface #114,  1          // InterfaceMethod javax/jws/WebService.portName:()Ljava/lang/String;
     319: invokevirtual #101                // Method java/lang/String.length:()I
     322: ifgt          351
     325: aload         14
     327: invokeinterface #103,  1          // InterfaceMethod javax/jws/WebService.serviceName:()Ljava/lang/String;
     332: invokevirtual #101                // Method java/lang/String.length:()I
     335: ifgt          351
     338: aload         14
     340: invokeinterface #117,  1          // InterfaceMethod javax/jws/WebService.endpointInterface:()Ljava/lang/String;
     345: invokevirtual #101                // Method java/lang/String.length:()I
     348: ifle          362
     351: getstatic     #119                // Field org/jboss/wsf/stack/cxf/Messages.MESSAGES:Lorg/jboss/wsf/stack/cxf/Messages;
     354: aload         7
     356: invokeinterface #126,  2          // InterfaceMethod org/jboss/wsf/stack/cxf/Messages.webserviceAnnotationSEIAttributes:(Ljava/lang/String;)Ljava/lang/RuntimeException;
     361: athrow
     362: ldc           #100                // String
     364: aload         4
     366: invokeinterface #127,  1          // InterfaceMethod javax/jws/WebService.wsdlLocation:()Ljava/lang/String;
     371: invokevirtual #43                 // Method java/lang/String.equals:(Ljava/lang/Object;)Z
     374: ifne          387
     377: aload         4
     379: invokeinterface #127,  1          // InterfaceMethod javax/jws/WebService.wsdlLocation:()Ljava/lang/String;
     384: goto          394
     387: aload         14
     389: invokeinterface #127,  1          // InterfaceMethod javax/jws/WebService.wsdlLocation:()Ljava/lang/String;
     394: astore        12
     396: goto          423
     399: aload         4
     401: ifnull        414
     404: aload         4
     406: invokeinterface #127,  1          // InterfaceMethod javax/jws/WebService.wsdlLocation:()Ljava/lang/String;
     411: goto          421
     414: aload         5
     416: invokeinterface #128,  1          // InterfaceMethod javax/xml/ws/WebServiceProvider.wsdlLocation:()Ljava/lang/String;
     421: astore        12
     423: new           #129                // class org/jboss/wsf/stack/cxf/metadata/services/DDEndpoint
     426: dup
     427: invokespecial #130                // Method org/jboss/wsf/stack/cxf/metadata/services/DDEndpoint."<init>":()V
     430: astore        13
     432: aload         13
     434: aload_3
     435: invokeinterface #131,  1          // InterfaceMethod org/jboss/wsf/spi/deployment/Endpoint.getShortName:()Ljava/lang/String;
     440: invokevirtual #132                // Method org/jboss/wsf/stack/cxf/metadata/services/DDEndpoint.setId:(Ljava/lang/String;)V
     443: aload         13
     445: aload_3
     446: invokeinterface #133,  1          // InterfaceMethod org/jboss/wsf/spi/deployment/Endpoint.getAddress:()Ljava/lang/String;
     451: invokevirtual #134                // Method org/jboss/wsf/stack/cxf/metadata/services/DDEndpoint.setAddress:(Ljava/lang/String;)V
     454: aload         13
     456: aload_3
     457: invokeinterface #135,  1          // InterfaceMethod org/jboss/wsf/spi/deployment/Endpoint.getTargetBeanName:()Ljava/lang/String;
     462: invokevirtual #136                // Method org/jboss/wsf/stack/cxf/metadata/services/DDEndpoint.setImplementor:(Ljava/lang/String;)V
     465: aload         13
     467: aload_0
     468: aload_3
     469: invokeinterface #14,  1           // InterfaceMethod org/jboss/wsf/spi/deployment/Endpoint.getTargetBeanClass:()Ljava/lang/Class;
     474: invokevirtual #137                // Method isMtomEnabled:(Ljava/lang/Class;)Z
     477: invokevirtual #65                 // Method org/jboss/wsf/stack/cxf/metadata/services/DDEndpoint.setMtomEnabled:(Z)V
     480: aload         13
     482: aload         6
     484: ifnull        492
     487: aload         6
     489: goto          493
     492: aload_1
     493: invokevirtual #138                // Method org/jboss/wsf/stack/cxf/metadata/services/DDEndpoint.setEpClass:(Ljava/lang/Class;)V
     496: aload         13
     498: new           #139                // class javax/xml/namespace/QName
     501: dup
     502: aload         10
     504: aload         11
     506: invokespecial #140                // Method javax/xml/namespace/QName."<init>":(Ljava/lang/String;Ljava/lang/String;)V
     509: invokevirtual #55                 // Method org/jboss/wsf/stack/cxf/metadata/services/DDEndpoint.setPortName:(Ljavax/xml/namespace/QName;)V
     512: aload         13
     514: new           #139                // class javax/xml/namespace/QName
     517: dup
     518: aload         10
     520: aload         9
     522: invokespecial #140                // Method javax/xml/namespace/QName."<init>":(Ljava/lang/String;Ljava/lang/String;)V
     525: invokevirtual #58                 // Method org/jboss/wsf/stack/cxf/metadata/services/DDEndpoint.setServiceName:(Ljavax/xml/namespace/QName;)V
     528: aload         12
     530: invokevirtual #101                // Method java/lang/String.length:()I
     533: ifle          543
     536: aload         13
     538: aload         12
     540: invokevirtual #141                // Method org/jboss/wsf/stack/cxf/metadata/services/DDEndpoint.setAnnotationWsdlLocation:(Ljava/lang/String;)V
     543: aload         13
     545: areturn
    Exception table:
       from    to  target type
         260   269   272   Class java/lang/ClassNotFoundException

  protected java.net.URL getWsdlLocationURL(org.jboss.wsf.stack.cxf.metadata.services.DDEndpoint, org.jboss.wsf.spi.deployment.ResourceResolver);
    Code:
       0: aload_1
       1: invokevirtual #142                // Method org/jboss/wsf/stack/cxf/metadata/services/DDEndpoint.getWsdlLocation:()Ljava/lang/String;
       4: astore_3
       5: aload_3
       6: ifnonnull     14
       9: aload_1
      10: invokevirtual #143                // Method org/jboss/wsf/stack/cxf/metadata/services/DDEndpoint.getAnnotationWsdlLocation:()Ljava/lang/String;
      13: astore_3
      14: aload_3
      15: ifnull        49
      18: aload_2
      19: aload_3
      20: invokeinterface #144,  2          // InterfaceMethod org/jboss/wsf/spi/deployment/ResourceResolver.resolveFailSafe:(Ljava/lang/String;)Ljava/net/URL;
      25: astore        4
      27: aload         4
      29: ifnull        35
      32: aload         4
      34: areturn
      35: getstatic     #119                // Field org/jboss/wsf/stack/cxf/Messages.MESSAGES:Lorg/jboss/wsf/stack/cxf/Messages;
      38: aload_1
      39: invokevirtual #145                // Method org/jboss/wsf/stack/cxf/metadata/services/DDEndpoint.getImplementor:()Ljava/lang/String;
      42: aload_3
      43: invokeinterface #146,  3          // InterfaceMethod org/jboss/wsf/stack/cxf/Messages.couldNotFetchWSDLContract:(Ljava/lang/String;Ljava/lang/String;)Lorg/jboss/wsf/spi/WSFException;
      48: athrow
      49: aconst_null
      50: areturn

  protected void processAddressRewrite(org.jboss.wsf.stack.cxf.metadata.services.DDEndpoint, java.net.URL, org.jboss.wsf.spi.metadata.config.SOAPAddressRewriteMetadata, java.util.Map<java.lang.String, org.jboss.ws.common.deployment.SOAPAddressWSDLParser>);
    Code:
       0: aload_2
       1: ifnull        58
       4: aload_0
       5: aload_2
       6: aload         4
       8: invokespecial #147                // Method getCurrentSOAPAddressWSDLParser:(Ljava/net/URL;Ljava/util/Map;)Lorg/jboss/ws/common/deployment/SOAPAddressWSDLParser;
      11: astore        5
      13: aload         5
      15: aload_1
      16: invokevirtual #31                 // Method org/jboss/wsf/stack/cxf/metadata/services/DDEndpoint.getServiceName:()Ljavax/xml/namespace/QName;
      19: aload_1
      20: invokevirtual #53                 // Method org/jboss/wsf/stack/cxf/metadata/services/DDEndpoint.getPortName:()Ljavax/xml/namespace/QName;
      23: ldc           #149                // String http://schemas.xmlsoap.org/soap/http
      25: invokevirtual #150                // Method org/jboss/ws/common/deployment/SOAPAddressWSDLParser.filterSoapAddress:(Ljavax/xml/namespace/QName;Ljavax/xml/namespace/QName;Ljava/lang/String;)Ljava/lang/String;
      28: astore        6
      30: aload         6
      32: aload_1
      33: invokevirtual #32                 // Method org/jboss/wsf/stack/cxf/metadata/services/DDEndpoint.getAddress:()Ljava/lang/String;
      36: aload_3
      37: invokestatic  #151                // Method org/jboss/wsf/stack/cxf/addressRewrite/SoapAddressRewriteHelper.getRewrittenPublishedEndpointUrl:(Ljava/lang/String;Ljava/lang/String;Lorg/jboss/wsf/spi/metadata/config/SOAPAddressRewriteMetadata;)Ljava/lang/String;
      40: astore        7
      42: aload_3
      43: invokestatic  #152                // Method org/jboss/wsf/stack/cxf/addressRewrite/SoapAddressRewriteHelper.isAutoRewriteOn:(Lorg/jboss/wsf/spi/metadata/config/SOAPAddressRewriteMetadata;)Z
      46: ifne          55
      49: aload_1
      50: aload         7
      52: invokevirtual #153                // Method org/jboss/wsf/stack/cxf/metadata/services/DDEndpoint.setPublishedEndpointUrl:(Ljava/lang/String;)V
      55: goto          77
      58: aload_3
      59: invokestatic  #152                // Method org/jboss/wsf/stack/cxf/addressRewrite/SoapAddressRewriteHelper.isAutoRewriteOn:(Lorg/jboss/wsf/spi/metadata/config/SOAPAddressRewriteMetadata;)Z
      62: ifne          77
      65: aload_1
      66: aload_1
      67: invokevirtual #32                 // Method org/jboss/wsf/stack/cxf/metadata/services/DDEndpoint.getAddress:()Ljava/lang/String;
      70: aload_3
      71: invokestatic  #154                // Method org/jboss/wsf/stack/cxf/addressRewrite/SoapAddressRewriteHelper.getRewrittenPublishedEndpointUrl:(Ljava/lang/String;Lorg/jboss/wsf/spi/metadata/config/SOAPAddressRewriteMetadata;)Ljava/lang/String;
      74: invokevirtual #153                // Method org/jboss/wsf/stack/cxf/metadata/services/DDEndpoint.setPublishedEndpointUrl:(Ljava/lang/String;)V
      77: return

  private org.jboss.ws.common.deployment.SOAPAddressWSDLParser getCurrentSOAPAddressWSDLParser(java.net.URL, java.util.Map<java.lang.String, org.jboss.ws.common.deployment.SOAPAddressWSDLParser>);
    Code:
       0: aload_1
       1: invokevirtual #155                // Method java/net/URL.toString:()Ljava/lang/String;
       4: astore_3
       5: aload_2
       6: aload_3
       7: invokeinterface #156,  2          // InterfaceMethod java/util/Map.get:(Ljava/lang/Object;)Ljava/lang/Object;
      12: checkcast     #148                // class org/jboss/ws/common/deployment/SOAPAddressWSDLParser
      15: astore        4
      17: aload         4
      19: ifnull        25
      22: aload         4
      24: areturn
      25: new           #148                // class org/jboss/ws/common/deployment/SOAPAddressWSDLParser
      28: dup
      29: aload_1
      30: invokespecial #157                // Method org/jboss/ws/common/deployment/SOAPAddressWSDLParser."<init>":(Ljava/net/URL;)V
      33: astore        4
      35: aload_2
      36: aload_3
      37: aload         4
      39: invokeinterface #33,  3           // InterfaceMethod java/util/Map.put:(Ljava/lang/Object;Ljava/lang/Object;)Ljava/lang/Object;
      44: pop
      45: aload         4
      47: areturn

  private static java.lang.String getTypeNamespace(java.lang.String);
    Code:
       0: new           #105                // class java/lang/StringBuilder
       3: dup
       4: ldc           #158                // String http://
       6: invokespecial #159                // Method java/lang/StringBuilder."<init>":(Ljava/lang/String;)V
       9: astore_1
      10: new           #160                // class java/util/StringTokenizer
      13: dup
      14: aload_0
      15: ldc           #161                // String .
      17: invokespecial #162                // Method java/util/StringTokenizer."<init>":(Ljava/lang/String;Ljava/lang/String;)V
      20: astore_2
      21: new           #163                // class java/util/Stack
      24: dup
      25: invokespecial #164                // Method java/util/Stack."<init>":()V
      28: astore_3
      29: aload_2
      30: ifnull        52
      33: aload_2
      34: invokevirtual #165                // Method java/util/StringTokenizer.hasMoreTokens:()Z
      37: ifeq          52
      40: aload_3
      41: aload_2
      42: invokevirtual #166                // Method java/util/StringTokenizer.nextToken:()Ljava/lang/String;
      45: invokevirtual #167                // Method java/util/Stack.push:(Ljava/lang/Object;)Ljava/lang/Object;
      48: pop
      49: goto          29
      52: aload_3
      53: invokevirtual #168                // Method java/util/Stack.isEmpty:()Z
      56: ifne          101
      59: aload_3
      60: invokevirtual #169                // Method java/util/Stack.pop:()Ljava/lang/Object;
      63: checkcast     #170                // class java/lang/String
      66: dup
      67: astore        4
      69: ifnull        101
      72: aload_1
      73: invokevirtual #109                // Method java/lang/StringBuilder.toString:()Ljava/lang/String;
      76: ldc           #158                // String http://
      78: invokevirtual #43                 // Method java/lang/String.equals:(Ljava/lang/Object;)Z
      81: ifne          91
      84: aload_1
      85: bipush        46
      87: invokevirtual #171                // Method java/lang/StringBuilder.append:(C)Ljava/lang/StringBuilder;
      90: pop
      91: aload_1
      92: aload         4
      94: invokevirtual #107                // Method java/lang/StringBuilder.append:(Ljava/lang/String;)Ljava/lang/StringBuilder;
      97: pop
      98: goto          52
     101: aload_1
     102: bipush        47
     104: invokevirtual #171                // Method java/lang/StringBuilder.append:(C)Ljava/lang/StringBuilder;
     107: pop
     108: aload_1
     109: invokevirtual #109                // Method java/lang/StringBuilder.toString:()Ljava/lang/String;
     112: areturn
}
