Compiled from "JsonPathCodec.java"
public interface org.graylog2.inputs.codecs.JsonPathCodec$Factory extends org.graylog2.plugin.inputs.codecs.Codec$Factory<org.graylog2.inputs.codecs.JsonPathCodec> {
  public abstract org.graylog2.inputs.codecs.JsonPathCodec create(org.graylog2.plugin.configuration.Configuration);

  public abstract org.graylog2.inputs.codecs.JsonPathCodec$Config getConfig();

  public abstract org.graylog2.inputs.codecs.JsonPathCodec$Descriptor getDescriptor();

  public default org.graylog2.plugin.inputs.codecs.Codec$Descriptor getDescriptor();
    Code:
       0: aload_0
       1: invokeinterface #1,  1            // InterfaceMethod getDescriptor:()Lorg/graylog2/inputs/codecs/JsonPathCodec$Descriptor;
       6: areturn

  public default org.graylog2.plugin.inputs.codecs.Codec$Config getConfig();
    Code:
       0: aload_0
       1: invokeinterface #2,  1            // InterfaceMethod getConfig:()Lorg/graylog2/inputs/codecs/JsonPathCodec$Config;
       6: areturn

  public default java.lang.Object create(org.graylog2.plugin.configuration.Configuration);
    Code:
       0: aload_0
       1: aload_1
       2: invokeinterface #3,  2            // InterfaceMethod create:(Lorg/graylog2/plugin/configuration/Configuration;)Lorg/graylog2/inputs/codecs/JsonPathCodec;
       7: areturn
}
