Compiled from "DivFinder.java"
public class org.openqa.selenium.lift.find.DivFinder extends org.openqa.selenium.lift.find.HtmlTagFinder {
  public org.openqa.selenium.lift.find.DivFinder();
    Code:
       0: aload_0
       1: invokespecial #1                  // Method org/openqa/selenium/lift/find/HtmlTagFinder."<init>":()V
       4: return

  protected java.lang.String tagDescription();
    Code:
       0: ldc           #2                  // String div
       2: areturn

  protected java.lang.String tagName();
    Code:
       0: ldc           #2                  // String div
       2: areturn

  public static org.openqa.selenium.lift.find.HtmlTagFinder div();
    Code:
       0: new           #3                  // class org/openqa/selenium/lift/find/DivFinder
       3: dup
       4: invokespecial #4                  // Method "<init>":()V
       7: areturn

  public static org.openqa.selenium.lift.find.HtmlTagFinder div(java.lang.String);
    Code:
       0: invokestatic  #5                  // Method div:()Lorg/openqa/selenium/lift/find/HtmlTagFinder;
       3: ldc           #6                  // String id
       5: aload_0
       6: invokestatic  #7                  // Method org/hamcrest/Matchers.equalTo:(Ljava/lang/Object;)Lorg/hamcrest/Matcher;
       9: invokestatic  #8                  // Method org/openqa/selenium/lift/match/AttributeMatcher.attribute:(Ljava/lang/String;Lorg/hamcrest/Matcher;)Lorg/hamcrest/Matcher;
      12: invokevirtual #9                  // Method org/openqa/selenium/lift/find/HtmlTagFinder.with:(Lorg/hamcrest/Matcher;)Lorg/openqa/selenium/lift/find/HtmlTagFinder;
      15: areturn
}
