Compiled from "QueryExecutionResultHandler.java"
class org.springframework.data.repository.core.support.QueryExecutionResultHandler {
  private static final org.springframework.core.convert.TypeDescriptor WRAPPER_TYPE;

  private final org.springframework.core.convert.support.GenericConversionService conversionService;

  public org.springframework.data.repository.core.support.QueryExecutionResultHandler();
    Code:
       0: aload_0
       1: invokespecial #1                  // Method java/lang/Object."<init>":()V
       4: new           #2                  // class org/springframework/core/convert/support/DefaultConversionService
       7: dup
       8: invokespecial #3                  // Method org/springframework/core/convert/support/DefaultConversionService."<init>":()V
      11: astore_1
      12: aload_1
      13: invokestatic  #4                  // Method org/springframework/data/repository/util/QueryExecutionConverters.registerConvertersIn:(Lorg/springframework/core/convert/support/ConfigurableConversionService;)V
      16: aload_1
      17: ldc           #5                  // class java/lang/Object
      19: ldc           #5                  // class java/lang/Object
      21: invokevirtual #6                  // Method org/springframework/core/convert/support/GenericConversionService.removeConvertible:(Ljava/lang/Class;Ljava/lang/Class;)V
      24: aload_0
      25: aload_1
      26: putfield      #7                  // Field conversionService:Lorg/springframework/core/convert/support/GenericConversionService;
      29: return

  public java.lang.Object postProcessInvocationResult(java.lang.Object, java.lang.reflect.Method);
    Code:
       0: aload_1
       1: aload_2
       2: invokevirtual #8                  // Method java/lang/reflect/Method.getReturnType:()Ljava/lang/Class;
       5: invokestatic  #9                  // Method processingRequired:(Ljava/lang/Object;Ljava/lang/Class;)Z
       8: ifne          13
      11: aload_1
      12: areturn
      13: new           #10                 // class org/springframework/core/MethodParameter
      16: dup
      17: aload_2
      18: iconst_m1
      19: invokespecial #11                 // Method org/springframework/core/MethodParameter."<init>":(Ljava/lang/reflect/Method;I)V
      22: astore_3
      23: aload_0
      24: aload_1
      25: iconst_0
      26: aload_3
      27: invokevirtual #12                 // Method postProcessInvocationResult:(Ljava/lang/Object;ILorg/springframework/core/MethodParameter;)Ljava/lang/Object;
      30: areturn

  java.lang.Object postProcessInvocationResult(java.lang.Object, int, org.springframework.core.MethodParameter);
    Code:
       0: aload_3
       1: iload_2
       2: invokestatic  #13                 // Method org/springframework/core/convert/TypeDescriptor.nested:(Lorg/springframework/core/MethodParameter;I)Lorg/springframework/core/convert/TypeDescriptor;
       5: astore        4
       7: aload         4
       9: ifnonnull     14
      12: aload_1
      13: areturn
      14: aload         4
      16: invokevirtual #14                 // Method org/springframework/core/convert/TypeDescriptor.getType:()Ljava/lang/Class;
      19: astore        5
      21: aload_1
      22: invokestatic  #15                 // Method unwrapOptional:(Ljava/lang/Object;)Ljava/lang/Object;
      25: astore_1
      26: aload         5
      28: invokestatic  #16                 // Method org/springframework/data/repository/util/QueryExecutionConverters.supports:(Ljava/lang/Class;)Z
      31: ifeq          109
      34: aload_0
      35: aload_1
      36: iload_2
      37: iconst_1
      38: iadd
      39: aload_3
      40: invokevirtual #12                 // Method postProcessInvocationResult:(Ljava/lang/Object;ILorg/springframework/core/MethodParameter;)Ljava/lang/Object;
      43: astore_1
      44: aload_0
      45: getstatic     #17                 // Field WRAPPER_TYPE:Lorg/springframework/core/convert/TypeDescriptor;
      48: aload         4
      50: invokespecial #18                 // Method conversionRequired:(Lorg/springframework/core/convert/TypeDescriptor;Lorg/springframework/core/convert/TypeDescriptor;)Z
      53: ifeq          74
      56: aload_0
      57: getfield      #7                  // Field conversionService:Lorg/springframework/core/convert/support/GenericConversionService;
      60: new           #19                 // class org/springframework/data/repository/util/NullableWrapper
      63: dup
      64: aload_1
      65: invokespecial #20                 // Method org/springframework/data/repository/util/NullableWrapper."<init>":(Ljava/lang/Object;)V
      68: aload         4
      70: invokevirtual #21                 // Method org/springframework/core/convert/support/GenericConversionService.convert:(Ljava/lang/Object;Lorg/springframework/core/convert/TypeDescriptor;)Ljava/lang/Object;
      73: areturn
      74: aload_1
      75: ifnull        109
      78: aload_1
      79: invokevirtual #22                 // Method java/lang/Object.getClass:()Ljava/lang/Class;
      82: invokestatic  #23                 // Method org/springframework/core/convert/TypeDescriptor.valueOf:(Ljava/lang/Class;)Lorg/springframework/core/convert/TypeDescriptor;
      85: astore        6
      87: aload_0
      88: aload         6
      90: aload         4
      92: invokespecial #18                 // Method conversionRequired:(Lorg/springframework/core/convert/TypeDescriptor;Lorg/springframework/core/convert/TypeDescriptor;)Z
      95: ifeq          109
      98: aload_0
      99: getfield      #7                  // Field conversionService:Lorg/springframework/core/convert/support/GenericConversionService;
     102: aload_1
     103: aload         4
     105: invokevirtual #21                 // Method org/springframework/core/convert/support/GenericConversionService.convert:(Ljava/lang/Object;Lorg/springframework/core/convert/TypeDescriptor;)Ljava/lang/Object;
     108: areturn
     109: aload_1
     110: ifnull        159
     113: aload         5
     115: invokestatic  #24                 // Method org/springframework/data/repository/util/ReactiveWrapperConverters.supports:(Ljava/lang/Class;)Z
     118: ifeq          128
     121: aload_1
     122: aload         5
     124: invokestatic  #25                 // Method org/springframework/data/repository/util/ReactiveWrapperConverters.toWrapper:(Ljava/lang/Object;Ljava/lang/Class;)Ljava/lang/Object;
     127: areturn
     128: aload_0
     129: getfield      #7                  // Field conversionService:Lorg/springframework/core/convert/support/GenericConversionService;
     132: aload_1
     133: invokestatic  #26                 // Method org/springframework/core/convert/TypeDescriptor.forObject:(Ljava/lang/Object;)Lorg/springframework/core/convert/TypeDescriptor;
     136: aload         4
     138: invokevirtual #27                 // Method org/springframework/core/convert/support/GenericConversionService.canConvert:(Lorg/springframework/core/convert/TypeDescriptor;Lorg/springframework/core/convert/TypeDescriptor;)Z
     141: ifeq          157
     144: aload_0
     145: getfield      #7                  // Field conversionService:Lorg/springframework/core/convert/support/GenericConversionService;
     148: aload_1
     149: aload         4
     151: invokevirtual #21                 // Method org/springframework/core/convert/support/GenericConversionService.convert:(Ljava/lang/Object;Lorg/springframework/core/convert/TypeDescriptor;)Ljava/lang/Object;
     154: goto          158
     157: aload_1
     158: areturn
     159: ldc           #28                 // class java/util/Map
     161: aload         5
     163: invokevirtual #29                 // Method java/lang/Object.equals:(Ljava/lang/Object;)Z
     166: ifeq          178
     169: aload         5
     171: iconst_0
     172: invokestatic  #30                 // Method org/springframework/core/CollectionFactory.createMap:(Ljava/lang/Class;I)Ljava/util/Map;
     175: goto          179
     178: aconst_null
     179: areturn

  private boolean conversionRequired(org.springframework.core.convert.TypeDescriptor, org.springframework.core.convert.TypeDescriptor);
    Code:
       0: aload_0
       1: getfield      #7                  // Field conversionService:Lorg/springframework/core/convert/support/GenericConversionService;
       4: aload_1
       5: aload_2
       6: invokevirtual #27                 // Method org/springframework/core/convert/support/GenericConversionService.canConvert:(Lorg/springframework/core/convert/TypeDescriptor;Lorg/springframework/core/convert/TypeDescriptor;)Z
       9: ifeq          28
      12: aload_0
      13: getfield      #7                  // Field conversionService:Lorg/springframework/core/convert/support/GenericConversionService;
      16: aload_1
      17: aload_2
      18: invokevirtual #31                 // Method org/springframework/core/convert/support/GenericConversionService.canBypassConvert:(Lorg/springframework/core/convert/TypeDescriptor;Lorg/springframework/core/convert/TypeDescriptor;)Z
      21: ifne          28
      24: iconst_1
      25: goto          29
      28: iconst_0
      29: ireturn

  private static java.lang.Object unwrapOptional(java.lang.Object);
    Code:
       0: aload_0
       1: ifnonnull     6
       4: aconst_null
       5: areturn
       6: ldc           #32                 // class java/util/Optional
       8: aload_0
       9: invokevirtual #33                 // Method java/lang/Class.isInstance:(Ljava/lang/Object;)Z
      12: ifeq          31
      15: ldc           #32                 // class java/util/Optional
      17: aload_0
      18: invokevirtual #34                 // Method java/lang/Class.cast:(Ljava/lang/Object;)Ljava/lang/Object;
      21: checkcast     #32                 // class java/util/Optional
      24: aconst_null
      25: invokevirtual #35                 // Method java/util/Optional.orElse:(Ljava/lang/Object;)Ljava/lang/Object;
      28: goto          32
      31: aload_0
      32: areturn

  private static boolean processingRequired(java.lang.Object, java.lang.Class<?>);
    Code:
       0: aload_1
       1: aload_0
       2: invokevirtual #33                 // Method java/lang/Class.isInstance:(Ljava/lang/Object;)Z
       5: ifeq          21
       8: aload_0
       9: ifnull        21
      12: ldc           #36                 // class java/util/Collection
      14: aload_0
      15: invokevirtual #33                 // Method java/lang/Class.isInstance:(Ljava/lang/Object;)Z
      18: ifeq          25
      21: iconst_1
      22: goto          26
      25: iconst_0
      26: ireturn

  static {};
    Code:
       0: ldc           #19                 // class org/springframework/data/repository/util/NullableWrapper
       2: invokestatic  #23                 // Method org/springframework/core/convert/TypeDescriptor.valueOf:(Ljava/lang/Class;)Lorg/springframework/core/convert/TypeDescriptor;
       5: putstatic     #17                 // Field WRAPPER_TYPE:Lorg/springframework/core/convert/TypeDescriptor;
       8: return
}
