Compiled from "Shorts.java"
public final class com.google.common.primitives.Shorts {
  public static final int BYTES;

  public static final short MAX_POWER_OF_TWO;

  private com.google.common.primitives.Shorts();
    Code:
       0: aload_0
       1: invokespecial #7                  // Method java/lang/Object."<init>":()V
       4: return

  public static int hashCode(short);
    Code:
       0: iload_0
       1: ireturn

  public static short checkedCast(long);
    Code:
       0: lload_0
       1: l2i
       2: i2s
       3: istore_2
       4: iload_2
       5: i2l
       6: lload_0
       7: lcmp
       8: ifne          15
      11: iconst_1
      12: goto          16
      15: iconst_0
      16: ldc           #8                  // String Out of range: %s
      18: iconst_1
      19: anewarray     #9                  // class java/lang/Object
      22: dup
      23: iconst_0
      24: lload_0
      25: invokestatic  #10                 // Method java/lang/Long.valueOf:(J)Ljava/lang/Long;
      28: aastore
      29: invokestatic  #11                 // Method com/google/common/base/Preconditions.checkArgument:(ZLjava/lang/String;[Ljava/lang/Object;)V
      32: iload_2
      33: ireturn

  public static short saturatedCast(long);
    Code:
       0: lload_0
       1: ldc2_w        #12                 // long 32767l
       4: lcmp
       5: ifle          12
       8: sipush        32767
      11: ireturn
      12: lload_0
      13: ldc2_w        #14                 // long -32768l
      16: lcmp
      17: ifge          24
      20: sipush        -32768
      23: ireturn
      24: lload_0
      25: l2i
      26: i2s
      27: ireturn

  public static int compare(short, short);
    Code:
       0: iload_0
       1: iload_1
       2: isub
       3: ireturn

  public static boolean contains(short[], short);
    Code:
       0: aload_0
       1: astore_2
       2: aload_2
       3: arraylength
       4: istore_3
       5: iconst_0
       6: istore        4
       8: iload         4
      10: iload_3
      11: if_icmpge     34
      14: aload_2
      15: iload         4
      17: saload
      18: istore        5
      20: iload         5
      22: iload_1
      23: if_icmpne     28
      26: iconst_1
      27: ireturn
      28: iinc          4, 1
      31: goto          8
      34: iconst_0
      35: ireturn

  public static int indexOf(short[], short);
    Code:
       0: aload_0
       1: iload_1
       2: iconst_0
       3: aload_0
       4: arraylength
       5: invokestatic  #6                  // Method indexOf:([SSII)I
       8: ireturn

  private static int indexOf(short[], short, int, int);
    Code:
       0: iload_2
       1: istore        4
       3: iload         4
       5: iload_3
       6: if_icmpge     26
       9: aload_0
      10: iload         4
      12: saload
      13: iload_1
      14: if_icmpne     20
      17: iload         4
      19: ireturn
      20: iinc          4, 1
      23: goto          3
      26: iconst_m1
      27: ireturn

  public static int indexOf(short[], short[]);
    Code:
       0: aload_0
       1: ldc           #16                 // String array
       3: invokestatic  #17                 // Method com/google/common/base/Preconditions.checkNotNull:(Ljava/lang/Object;Ljava/lang/Object;)Ljava/lang/Object;
       6: pop
       7: aload_1
       8: ldc           #18                 // String target
      10: invokestatic  #17                 // Method com/google/common/base/Preconditions.checkNotNull:(Ljava/lang/Object;Ljava/lang/Object;)Ljava/lang/Object;
      13: pop
      14: aload_1
      15: arraylength
      16: ifne          21
      19: iconst_0
      20: ireturn
      21: iconst_0
      22: istore_2
      23: iload_2
      24: aload_0
      25: arraylength
      26: aload_1
      27: arraylength
      28: isub
      29: iconst_1
      30: iadd
      31: if_icmpge     70
      34: iconst_0
      35: istore_3
      36: iload_3
      37: aload_1
      38: arraylength
      39: if_icmpge     62
      42: aload_0
      43: iload_2
      44: iload_3
      45: iadd
      46: saload
      47: aload_1
      48: iload_3
      49: saload
      50: if_icmpeq     56
      53: goto          64
      56: iinc          3, 1
      59: goto          36
      62: iload_2
      63: ireturn
      64: iinc          2, 1
      67: goto          23
      70: iconst_m1
      71: ireturn

  public static int lastIndexOf(short[], short);
    Code:
       0: aload_0
       1: iload_1
       2: iconst_0
       3: aload_0
       4: arraylength
       5: invokestatic  #5                  // Method lastIndexOf:([SSII)I
       8: ireturn

  private static int lastIndexOf(short[], short, int, int);
    Code:
       0: iload_3
       1: iconst_1
       2: isub
       3: istore        4
       5: iload         4
       7: iload_2
       8: if_icmplt     28
      11: aload_0
      12: iload         4
      14: saload
      15: iload_1
      16: if_icmpne     22
      19: iload         4
      21: ireturn
      22: iinc          4, -1
      25: goto          5
      28: iconst_m1
      29: ireturn

  public static short min(short...);
    Code:
       0: aload_0
       1: arraylength
       2: ifle          9
       5: iconst_1
       6: goto          10
       9: iconst_0
      10: invokestatic  #19                 // Method com/google/common/base/Preconditions.checkArgument:(Z)V
      13: aload_0
      14: iconst_0
      15: saload
      16: istore_1
      17: iconst_1
      18: istore_2
      19: iload_2
      20: aload_0
      21: arraylength
      22: if_icmpge     42
      25: aload_0
      26: iload_2
      27: saload
      28: iload_1
      29: if_icmpge     36
      32: aload_0
      33: iload_2
      34: saload
      35: istore_1
      36: iinc          2, 1
      39: goto          19
      42: iload_1
      43: ireturn

  public static short max(short...);
    Code:
       0: aload_0
       1: arraylength
       2: ifle          9
       5: iconst_1
       6: goto          10
       9: iconst_0
      10: invokestatic  #19                 // Method com/google/common/base/Preconditions.checkArgument:(Z)V
      13: aload_0
      14: iconst_0
      15: saload
      16: istore_1
      17: iconst_1
      18: istore_2
      19: iload_2
      20: aload_0
      21: arraylength
      22: if_icmpge     42
      25: aload_0
      26: iload_2
      27: saload
      28: iload_1
      29: if_icmple     36
      32: aload_0
      33: iload_2
      34: saload
      35: istore_1
      36: iinc          2, 1
      39: goto          19
      42: iload_1
      43: ireturn

  public static short[] concat(short[]...);
    Code:
       0: iconst_0
       1: istore_1
       2: aload_0
       3: astore_2
       4: aload_2
       5: arraylength
       6: istore_3
       7: iconst_0
       8: istore        4
      10: iload         4
      12: iload_3
      13: if_icmpge     34
      16: aload_2
      17: iload         4
      19: aaload
      20: astore        5
      22: iload_1
      23: aload         5
      25: arraylength
      26: iadd
      27: istore_1
      28: iinc          4, 1
      31: goto          10
      34: iload_1
      35: newarray       short
      37: astore_2
      38: iconst_0
      39: istore_3
      40: aload_0
      41: astore        4
      43: aload         4
      45: arraylength
      46: istore        5
      48: iconst_0
      49: istore        6
      51: iload         6
      53: iload         5
      55: if_icmpge     88
      58: aload         4
      60: iload         6
      62: aaload
      63: astore        7
      65: aload         7
      67: iconst_0
      68: aload_2
      69: iload_3
      70: aload         7
      72: arraylength
      73: invokestatic  #20                 // Method java/lang/System.arraycopy:(Ljava/lang/Object;ILjava/lang/Object;II)V
      76: iload_3
      77: aload         7
      79: arraylength
      80: iadd
      81: istore_3
      82: iinc          6, 1
      85: goto          51
      88: aload_2
      89: areturn

  public static byte[] toByteArray(short);
    Code:
       0: iconst_2
       1: newarray       byte
       3: dup
       4: iconst_0
       5: iload_0
       6: bipush        8
       8: ishr
       9: i2b
      10: bastore
      11: dup
      12: iconst_1
      13: iload_0
      14: i2b
      15: bastore
      16: areturn

  public static short fromByteArray(byte[]);
    Code:
       0: aload_0
       1: arraylength
       2: iconst_2
       3: if_icmplt     10
       6: iconst_1
       7: goto          11
      10: iconst_0
      11: ldc           #21                 // String array too small: %s < %s
      13: iconst_2
      14: anewarray     #9                  // class java/lang/Object
      17: dup
      18: iconst_0
      19: aload_0
      20: arraylength
      21: invokestatic  #22                 // Method java/lang/Integer.valueOf:(I)Ljava/lang/Integer;
      24: aastore
      25: dup
      26: iconst_1
      27: iconst_2
      28: invokestatic  #22                 // Method java/lang/Integer.valueOf:(I)Ljava/lang/Integer;
      31: aastore
      32: invokestatic  #11                 // Method com/google/common/base/Preconditions.checkArgument:(ZLjava/lang/String;[Ljava/lang/Object;)V
      35: aload_0
      36: iconst_0
      37: baload
      38: aload_0
      39: iconst_1
      40: baload
      41: invokestatic  #23                 // Method fromBytes:(BB)S
      44: ireturn

  public static short fromBytes(byte, byte);
    Code:
       0: iload_0
       1: bipush        8
       3: ishl
       4: iload_1
       5: sipush        255
       8: iand
       9: ior
      10: i2s
      11: ireturn

  public static short[] ensureCapacity(short[], int, int);
    Code:
       0: iload_1
       1: iflt          8
       4: iconst_1
       5: goto          9
       8: iconst_0
       9: ldc           #24                 // String Invalid minLength: %s
      11: iconst_1
      12: anewarray     #9                  // class java/lang/Object
      15: dup
      16: iconst_0
      17: iload_1
      18: invokestatic  #22                 // Method java/lang/Integer.valueOf:(I)Ljava/lang/Integer;
      21: aastore
      22: invokestatic  #11                 // Method com/google/common/base/Preconditions.checkArgument:(ZLjava/lang/String;[Ljava/lang/Object;)V
      25: iload_2
      26: iflt          33
      29: iconst_1
      30: goto          34
      33: iconst_0
      34: ldc           #25                 // String Invalid padding: %s
      36: iconst_1
      37: anewarray     #9                  // class java/lang/Object
      40: dup
      41: iconst_0
      42: iload_2
      43: invokestatic  #22                 // Method java/lang/Integer.valueOf:(I)Ljava/lang/Integer;
      46: aastore
      47: invokestatic  #11                 // Method com/google/common/base/Preconditions.checkArgument:(ZLjava/lang/String;[Ljava/lang/Object;)V
      50: aload_0
      51: arraylength
      52: iload_1
      53: if_icmpge     66
      56: aload_0
      57: iload_1
      58: iload_2
      59: iadd
      60: invokestatic  #26                 // Method copyOf:([SI)[S
      63: goto          67
      66: aload_0
      67: areturn

  private static short[] copyOf(short[], int);
    Code:
       0: iload_1
       1: newarray       short
       3: astore_2
       4: aload_0
       5: iconst_0
       6: aload_2
       7: iconst_0
       8: aload_0
       9: arraylength
      10: iload_1
      11: invokestatic  #27                 // Method java/lang/Math.min:(II)I
      14: invokestatic  #20                 // Method java/lang/System.arraycopy:(Ljava/lang/Object;ILjava/lang/Object;II)V
      17: aload_2
      18: areturn

  public static java.lang.String join(java.lang.String, short...);
    Code:
       0: aload_0
       1: invokestatic  #28                 // Method com/google/common/base/Preconditions.checkNotNull:(Ljava/lang/Object;)Ljava/lang/Object;
       4: pop
       5: aload_1
       6: arraylength
       7: ifne          13
      10: ldc           #29                 // String
      12: areturn
      13: new           #30                 // class java/lang/StringBuilder
      16: dup
      17: aload_1
      18: arraylength
      19: bipush        6
      21: imul
      22: invokespecial #31                 // Method java/lang/StringBuilder."<init>":(I)V
      25: astore_2
      26: aload_2
      27: aload_1
      28: iconst_0
      29: saload
      30: invokevirtual #32                 // Method java/lang/StringBuilder.append:(I)Ljava/lang/StringBuilder;
      33: pop
      34: iconst_1
      35: istore_3
      36: iload_3
      37: aload_1
      38: arraylength
      39: if_icmpge     60
      42: aload_2
      43: aload_0
      44: invokevirtual #33                 // Method java/lang/StringBuilder.append:(Ljava/lang/String;)Ljava/lang/StringBuilder;
      47: aload_1
      48: iload_3
      49: saload
      50: invokevirtual #32                 // Method java/lang/StringBuilder.append:(I)Ljava/lang/StringBuilder;
      53: pop
      54: iinc          3, 1
      57: goto          36
      60: aload_2
      61: invokevirtual #34                 // Method java/lang/StringBuilder.toString:()Ljava/lang/String;
      64: areturn

  public static java.util.Comparator<short[]> lexicographicalComparator();
    Code:
       0: getstatic     #35                 // Field com/google/common/primitives/Shorts$LexicographicalComparator.INSTANCE:Lcom/google/common/primitives/Shorts$LexicographicalComparator;
       3: areturn

  public static short[] toArray(java.util.Collection<java.lang.Short>);
    Code:
       0: aload_0
       1: instanceof    #36                 // class com/google/common/primitives/Shorts$ShortArrayAsList
       4: ifeq          15
       7: aload_0
       8: checkcast     #36                 // class com/google/common/primitives/Shorts$ShortArrayAsList
      11: invokevirtual #37                 // Method com/google/common/primitives/Shorts$ShortArrayAsList.toShortArray:()[S
      14: areturn
      15: aload_0
      16: invokeinterface #38,  1           // InterfaceMethod java/util/Collection.toArray:()[Ljava/lang/Object;
      21: astore_1
      22: aload_1
      23: arraylength
      24: istore_2
      25: iload_2
      26: newarray       short
      28: astore_3
      29: iconst_0
      30: istore        4
      32: iload         4
      34: iload_2
      35: if_icmpge     61
      38: aload_3
      39: iload         4
      41: aload_1
      42: iload         4
      44: aaload
      45: invokestatic  #28                 // Method com/google/common/base/Preconditions.checkNotNull:(Ljava/lang/Object;)Ljava/lang/Object;
      48: checkcast     #39                 // class java/lang/Short
      51: invokevirtual #40                 // Method java/lang/Short.shortValue:()S
      54: sastore
      55: iinc          4, 1
      58: goto          32
      61: aload_3
      62: areturn

  public static java.util.List<java.lang.Short> asList(short...);
    Code:
       0: aload_0
       1: arraylength
       2: ifne          9
       5: invokestatic  #41                 // Method java/util/Collections.emptyList:()Ljava/util/List;
       8: areturn
       9: new           #36                 // class com/google/common/primitives/Shorts$ShortArrayAsList
      12: dup
      13: aload_0
      14: invokespecial #42                 // Method com/google/common/primitives/Shorts$ShortArrayAsList."<init>":([S)V
      17: areturn

  static int access$000(short[], short, int, int);
    Code:
       0: aload_0
       1: iload_1
       2: iload_2
       3: iload_3
       4: invokestatic  #6                  // Method indexOf:([SSII)I
       7: ireturn

  static int access$100(short[], short, int, int);
    Code:
       0: aload_0
       1: iload_1
       2: iload_2
       3: iload_3
       4: invokestatic  #5                  // Method lastIndexOf:([SSII)I
       7: ireturn
}
