Compiled from "ParserGenerator.java"
public class org.jboss.aesh.cl.parser.ParserGenerator {
  public org.jboss.aesh.cl.parser.ParserGenerator();
    Code:
       0: aload_0
       1: invokespecial #1                  // Method java/lang/Object."<init>":()V
       4: return

  public static org.jboss.aesh.console.command.container.AeshCommandContainer generateCommandLineParser(org.jboss.aesh.console.command.Command) throws org.jboss.aesh.cl.parser.CommandLineParserException;
    Code:
       0: aload_0
       1: invokestatic  #2                  // Method doGenerateCommandLineParser:(Lorg/jboss/aesh/console/command/Command;)Lorg/jboss/aesh/console/command/container/AeshCommandContainer;
       4: areturn

  public static org.jboss.aesh.console.command.container.AeshCommandContainer generateCommandLineParser(java.lang.Class<? extends org.jboss.aesh.console.command.Command>) throws org.jboss.aesh.cl.parser.CommandLineParserException;
    Code:
       0: aload_0
       1: invokestatic  #3                  // Method org/jboss/aesh/util/ReflectionUtil.newInstance:(Ljava/lang/Class;)Ljava/lang/Object;
       4: checkcast     #4                  // class org/jboss/aesh/console/command/Command
       7: invokestatic  #2                  // Method doGenerateCommandLineParser:(Lorg/jboss/aesh/console/command/Command;)Lorg/jboss/aesh/console/command/container/AeshCommandContainer;
      10: areturn

  private static org.jboss.aesh.console.command.container.AeshCommandContainer doGenerateCommandLineParser(org.jboss.aesh.console.command.Command) throws org.jboss.aesh.cl.parser.CommandLineParserException;
    Code:
       0: aload_0
       1: invokevirtual #5                  // Method java/lang/Object.getClass:()Ljava/lang/Class;
       4: astore_1
       5: aload_1
       6: ldc           #6                  // class org/jboss/aesh/cl/CommandDefinition
       8: invokevirtual #7                  // Method java/lang/Class.getAnnotation:(Ljava/lang/Class;)Ljava/lang/annotation/Annotation;
      11: checkcast     #6                  // class org/jboss/aesh/cl/CommandDefinition
      14: astore_2
      15: aload_2
      16: ifnull        97
      19: new           #8                  // class org/jboss/aesh/cl/internal/ProcessedCommandBuilder
      22: dup
      23: invokespecial #9                  // Method org/jboss/aesh/cl/internal/ProcessedCommandBuilder."<init>":()V
      26: aload_2
      27: invokeinterface #10,  1           // InterfaceMethod org/jboss/aesh/cl/CommandDefinition.name:()Ljava/lang/String;
      32: invokevirtual #11                 // Method org/jboss/aesh/cl/internal/ProcessedCommandBuilder.name:(Ljava/lang/String;)Lorg/jboss/aesh/cl/internal/ProcessedCommandBuilder;
      35: aload_2
      36: invokeinterface #12,  1           // InterfaceMethod org/jboss/aesh/cl/CommandDefinition.description:()Ljava/lang/String;
      41: invokevirtual #13                 // Method org/jboss/aesh/cl/internal/ProcessedCommandBuilder.description:(Ljava/lang/String;)Lorg/jboss/aesh/cl/internal/ProcessedCommandBuilder;
      44: aload_2
      45: invokeinterface #14,  1           // InterfaceMethod org/jboss/aesh/cl/CommandDefinition.validator:()Ljava/lang/Class;
      50: invokevirtual #15                 // Method org/jboss/aesh/cl/internal/ProcessedCommandBuilder.validator:(Ljava/lang/Class;)Lorg/jboss/aesh/cl/internal/ProcessedCommandBuilder;
      53: aload_0
      54: invokevirtual #16                 // Method org/jboss/aesh/cl/internal/ProcessedCommandBuilder.command:(Lorg/jboss/aesh/console/command/Command;)Lorg/jboss/aesh/cl/internal/ProcessedCommandBuilder;
      57: aload_2
      58: invokeinterface #17,  1           // InterfaceMethod org/jboss/aesh/cl/CommandDefinition.resultHandler:()Ljava/lang/Class;
      63: invokevirtual #18                 // Method org/jboss/aesh/cl/internal/ProcessedCommandBuilder.resultHandler:(Ljava/lang/Class;)Lorg/jboss/aesh/cl/internal/ProcessedCommandBuilder;
      66: invokevirtual #19                 // Method org/jboss/aesh/cl/internal/ProcessedCommandBuilder.create:()Lorg/jboss/aesh/cl/internal/ProcessedCommand;
      69: astore_3
      70: aload_3
      71: aload_1
      72: invokestatic  #20                 // Method processCommand:(Lorg/jboss/aesh/cl/internal/ProcessedCommand;Ljava/lang/Class;)V
      75: new           #21                 // class org/jboss/aesh/console/command/container/AeshCommandContainer
      78: dup
      79: new           #22                 // class org/jboss/aesh/cl/parser/CommandLineParserBuilder
      82: dup
      83: invokespecial #23                 // Method org/jboss/aesh/cl/parser/CommandLineParserBuilder."<init>":()V
      86: aload_3
      87: invokevirtual #24                 // Method org/jboss/aesh/cl/parser/CommandLineParserBuilder.processedCommand:(Lorg/jboss/aesh/cl/internal/ProcessedCommand;)Lorg/jboss/aesh/cl/parser/CommandLineParserBuilder;
      90: invokevirtual #25                 // Method org/jboss/aesh/cl/parser/CommandLineParserBuilder.create:()Lorg/jboss/aesh/cl/parser/CommandLineParser;
      93: invokespecial #26                 // Method org/jboss/aesh/console/command/container/AeshCommandContainer."<init>":(Lorg/jboss/aesh/cl/parser/CommandLineParser;)V
      96: areturn
      97: aload_1
      98: ldc           #27                 // class org/jboss/aesh/cl/GroupCommandDefinition
     100: invokevirtual #7                  // Method java/lang/Class.getAnnotation:(Ljava/lang/Class;)Ljava/lang/annotation/Annotation;
     103: checkcast     #27                 // class org/jboss/aesh/cl/GroupCommandDefinition
     106: astore_3
     107: aload_3
     108: ifnull        252
     111: new           #8                  // class org/jboss/aesh/cl/internal/ProcessedCommandBuilder
     114: dup
     115: invokespecial #9                  // Method org/jboss/aesh/cl/internal/ProcessedCommandBuilder."<init>":()V
     118: aload_3
     119: invokeinterface #28,  1           // InterfaceMethod org/jboss/aesh/cl/GroupCommandDefinition.name:()Ljava/lang/String;
     124: invokevirtual #11                 // Method org/jboss/aesh/cl/internal/ProcessedCommandBuilder.name:(Ljava/lang/String;)Lorg/jboss/aesh/cl/internal/ProcessedCommandBuilder;
     127: aload_3
     128: invokeinterface #29,  1           // InterfaceMethod org/jboss/aesh/cl/GroupCommandDefinition.description:()Ljava/lang/String;
     133: invokevirtual #13                 // Method org/jboss/aesh/cl/internal/ProcessedCommandBuilder.description:(Ljava/lang/String;)Lorg/jboss/aesh/cl/internal/ProcessedCommandBuilder;
     136: aload_3
     137: invokeinterface #30,  1           // InterfaceMethod org/jboss/aesh/cl/GroupCommandDefinition.validator:()Ljava/lang/Class;
     142: invokevirtual #15                 // Method org/jboss/aesh/cl/internal/ProcessedCommandBuilder.validator:(Ljava/lang/Class;)Lorg/jboss/aesh/cl/internal/ProcessedCommandBuilder;
     145: aload_0
     146: invokevirtual #16                 // Method org/jboss/aesh/cl/internal/ProcessedCommandBuilder.command:(Lorg/jboss/aesh/console/command/Command;)Lorg/jboss/aesh/cl/internal/ProcessedCommandBuilder;
     149: aload_3
     150: invokeinterface #31,  1           // InterfaceMethod org/jboss/aesh/cl/GroupCommandDefinition.resultHandler:()Ljava/lang/Class;
     155: invokevirtual #18                 // Method org/jboss/aesh/cl/internal/ProcessedCommandBuilder.resultHandler:(Ljava/lang/Class;)Lorg/jboss/aesh/cl/internal/ProcessedCommandBuilder;
     158: invokevirtual #19                 // Method org/jboss/aesh/cl/internal/ProcessedCommandBuilder.create:()Lorg/jboss/aesh/cl/internal/ProcessedCommand;
     161: astore        4
     163: aload         4
     165: aload_1
     166: invokestatic  #20                 // Method processCommand:(Lorg/jboss/aesh/cl/internal/ProcessedCommand;Ljava/lang/Class;)V
     169: new           #21                 // class org/jboss/aesh/console/command/container/AeshCommandContainer
     172: dup
     173: new           #22                 // class org/jboss/aesh/cl/parser/CommandLineParserBuilder
     176: dup
     177: invokespecial #23                 // Method org/jboss/aesh/cl/parser/CommandLineParserBuilder."<init>":()V
     180: aload         4
     182: invokevirtual #24                 // Method org/jboss/aesh/cl/parser/CommandLineParserBuilder.processedCommand:(Lorg/jboss/aesh/cl/internal/ProcessedCommand;)Lorg/jboss/aesh/cl/parser/CommandLineParserBuilder;
     185: invokevirtual #25                 // Method org/jboss/aesh/cl/parser/CommandLineParserBuilder.create:()Lorg/jboss/aesh/cl/parser/CommandLineParser;
     188: invokespecial #26                 // Method org/jboss/aesh/console/command/container/AeshCommandContainer."<init>":(Lorg/jboss/aesh/cl/parser/CommandLineParser;)V
     191: astore        5
     193: aload_3
     194: invokeinterface #32,  1           // InterfaceMethod org/jboss/aesh/cl/GroupCommandDefinition.groupCommands:()[Ljava/lang/Class;
     199: astore        6
     201: aload         6
     203: arraylength
     204: istore        7
     206: iconst_0
     207: istore        8
     209: iload         8
     211: iload         7
     213: if_icmpge     249
     216: aload         6
     218: iload         8
     220: aaload
     221: astore        9
     223: aload         9
     225: invokestatic  #3                  // Method org/jboss/aesh/util/ReflectionUtil.newInstance:(Ljava/lang/Class;)Ljava/lang/Object;
     228: checkcast     #4                  // class org/jboss/aesh/console/command/Command
     231: astore        10
     233: aload         5
     235: aload         10
     237: invokestatic  #2                  // Method doGenerateCommandLineParser:(Lorg/jboss/aesh/console/command/Command;)Lorg/jboss/aesh/console/command/container/AeshCommandContainer;
     240: invokevirtual #33                 // Method org/jboss/aesh/console/command/container/AeshCommandContainer.addChild:(Lorg/jboss/aesh/console/command/container/CommandContainer;)V
     243: iinc          8, 1
     246: goto          209
     249: aload         5
     251: areturn
     252: new           #34                 // class org/jboss/aesh/cl/parser/CommandLineParserException
     255: dup
     256: ldc           #35                 // String Commands must be annotated with @CommandDefinition or @GroupCommandDefinition
     258: invokespecial #36                 // Method org/jboss/aesh/cl/parser/CommandLineParserException."<init>":(Ljava/lang/String;)V
     261: athrow

  private static void processCommand(org.jboss.aesh.cl.internal.ProcessedCommand, java.lang.Class) throws org.jboss.aesh.cl.parser.CommandLineParserException;
    Code:
       0: aload_1
       1: invokevirtual #37                 // Method java/lang/Class.getDeclaredFields:()[Ljava/lang/reflect/Field;
       4: astore_2
       5: aload_2
       6: arraylength
       7: istore_3
       8: iconst_0
       9: istore        4
      11: iload         4
      13: iload_3
      14: if_icmpge     35
      17: aload_2
      18: iload         4
      20: aaload
      21: astore        5
      23: aload_0
      24: aload         5
      26: invokestatic  #38                 // Method processField:(Lorg/jboss/aesh/cl/internal/ProcessedCommand;Ljava/lang/reflect/Field;)V
      29: iinc          4, 1
      32: goto          11
      35: aload_1
      36: invokevirtual #39                 // Method java/lang/Class.getSuperclass:()Ljava/lang/Class;
      39: ifnull        50
      42: aload_0
      43: aload_1
      44: invokevirtual #39                 // Method java/lang/Class.getSuperclass:()Ljava/lang/Class;
      47: invokestatic  #20                 // Method processCommand:(Lorg/jboss/aesh/cl/internal/ProcessedCommand;Ljava/lang/Class;)V
      50: return

  private static void processField(org.jboss.aesh.cl.internal.ProcessedCommand, java.lang.reflect.Field) throws org.jboss.aesh.cl.parser.CommandLineParserException;
    Code:
       0: aload_1
       1: ldc           #40                 // class org/jboss/aesh/cl/Option
       3: invokevirtual #41                 // Method java/lang/reflect/Field.getAnnotation:(Ljava/lang/Class;)Ljava/lang/annotation/Annotation;
       6: checkcast     #40                 // class org/jboss/aesh/cl/Option
       9: dup
      10: astore_2
      11: ifnull        336
      14: aload_2
      15: invokeinterface #42,  1           // InterfaceMethod org/jboss/aesh/cl/Option.hasValue:()Z
      20: ifeq          31
      23: getstatic     #43                 // Field org/jboss/aesh/cl/internal/OptionType.NORMAL:Lorg/jboss/aesh/cl/internal/OptionType;
      26: astore        6
      28: goto          36
      31: getstatic     #44                 // Field org/jboss/aesh/cl/internal/OptionType.BOOLEAN:Lorg/jboss/aesh/cl/internal/OptionType;
      34: astore        6
      36: aload_2
      37: invokeinterface #45,  1           // InterfaceMethod org/jboss/aesh/cl/Option.name:()Ljava/lang/String;
      42: ifnull        58
      45: aload_2
      46: invokeinterface #45,  1           // InterfaceMethod org/jboss/aesh/cl/Option.name:()Ljava/lang/String;
      51: invokevirtual #46                 // Method java/lang/String.length:()I
      54: iconst_1
      55: if_icmpge     196
      58: aload_0
      59: new           #47                 // class org/jboss/aesh/cl/internal/ProcessedOptionBuilder
      62: dup
      63: invokespecial #48                 // Method org/jboss/aesh/cl/internal/ProcessedOptionBuilder."<init>":()V
      66: aload_2
      67: invokeinterface #49,  1           // InterfaceMethod org/jboss/aesh/cl/Option.shortName:()C
      72: invokevirtual #50                 // Method org/jboss/aesh/cl/internal/ProcessedOptionBuilder.shortName:(C)Lorg/jboss/aesh/cl/internal/ProcessedOptionBuilder;
      75: aload_1
      76: invokevirtual #51                 // Method java/lang/reflect/Field.getName:()Ljava/lang/String;
      79: invokevirtual #52                 // Method org/jboss/aesh/cl/internal/ProcessedOptionBuilder.name:(Ljava/lang/String;)Lorg/jboss/aesh/cl/internal/ProcessedOptionBuilder;
      82: aload_2
      83: invokeinterface #53,  1           // InterfaceMethod org/jboss/aesh/cl/Option.description:()Ljava/lang/String;
      88: invokevirtual #54                 // Method org/jboss/aesh/cl/internal/ProcessedOptionBuilder.description:(Ljava/lang/String;)Lorg/jboss/aesh/cl/internal/ProcessedOptionBuilder;
      91: aload_2
      92: invokeinterface #55,  1           // InterfaceMethod org/jboss/aesh/cl/Option.required:()Z
      97: invokevirtual #56                 // Method org/jboss/aesh/cl/internal/ProcessedOptionBuilder.required:(Z)Lorg/jboss/aesh/cl/internal/ProcessedOptionBuilder;
     100: bipush        44
     102: invokevirtual #57                 // Method org/jboss/aesh/cl/internal/ProcessedOptionBuilder.valueSeparator:(C)Lorg/jboss/aesh/cl/internal/ProcessedOptionBuilder;
     105: aload_2
     106: invokeinterface #58,  1           // InterfaceMethod org/jboss/aesh/cl/Option.defaultValue:()[Ljava/lang/String;
     111: invokevirtual #59                 // Method org/jboss/aesh/cl/internal/ProcessedOptionBuilder.addAllDefaultValues:([Ljava/lang/String;)Lorg/jboss/aesh/cl/internal/ProcessedOptionBuilder;
     114: aload_1
     115: invokevirtual #60                 // Method java/lang/reflect/Field.getType:()Ljava/lang/Class;
     118: invokevirtual #61                 // Method org/jboss/aesh/cl/internal/ProcessedOptionBuilder.type:(Ljava/lang/Class;)Lorg/jboss/aesh/cl/internal/ProcessedOptionBuilder;
     121: aload_1
     122: invokevirtual #51                 // Method java/lang/reflect/Field.getName:()Ljava/lang/String;
     125: invokevirtual #62                 // Method org/jboss/aesh/cl/internal/ProcessedOptionBuilder.fieldName:(Ljava/lang/String;)Lorg/jboss/aesh/cl/internal/ProcessedOptionBuilder;
     128: aload         6
     130: invokevirtual #63                 // Method org/jboss/aesh/cl/internal/ProcessedOptionBuilder.optionType:(Lorg/jboss/aesh/cl/internal/OptionType;)Lorg/jboss/aesh/cl/internal/ProcessedOptionBuilder;
     133: aload_2
     134: invokeinterface #64,  1           // InterfaceMethod org/jboss/aesh/cl/Option.converter:()Ljava/lang/Class;
     139: invokevirtual #65                 // Method org/jboss/aesh/cl/internal/ProcessedOptionBuilder.converter:(Ljava/lang/Class;)Lorg/jboss/aesh/cl/internal/ProcessedOptionBuilder;
     142: aload_2
     143: invokeinterface #66,  1           // InterfaceMethod org/jboss/aesh/cl/Option.completer:()Ljava/lang/Class;
     148: invokevirtual #67                 // Method org/jboss/aesh/cl/internal/ProcessedOptionBuilder.completer:(Ljava/lang/Class;)Lorg/jboss/aesh/cl/internal/ProcessedOptionBuilder;
     151: aload_2
     152: invokeinterface #68,  1           // InterfaceMethod org/jboss/aesh/cl/Option.validator:()Ljava/lang/Class;
     157: invokevirtual #69                 // Method org/jboss/aesh/cl/internal/ProcessedOptionBuilder.validator:(Ljava/lang/Class;)Lorg/jboss/aesh/cl/internal/ProcessedOptionBuilder;
     160: aload_2
     161: invokeinterface #70,  1           // InterfaceMethod org/jboss/aesh/cl/Option.activator:()Ljava/lang/Class;
     166: invokevirtual #71                 // Method org/jboss/aesh/cl/internal/ProcessedOptionBuilder.activator:(Ljava/lang/Class;)Lorg/jboss/aesh/cl/internal/ProcessedOptionBuilder;
     169: aload_2
     170: invokeinterface #72,  1           // InterfaceMethod org/jboss/aesh/cl/Option.renderer:()Ljava/lang/Class;
     175: invokevirtual #73                 // Method org/jboss/aesh/cl/internal/ProcessedOptionBuilder.renderer:(Ljava/lang/Class;)Lorg/jboss/aesh/cl/internal/ProcessedOptionBuilder;
     178: aload_2
     179: invokeinterface #74,  1           // InterfaceMethod org/jboss/aesh/cl/Option.overrideRequired:()Z
     184: invokevirtual #75                 // Method org/jboss/aesh/cl/internal/ProcessedOptionBuilder.overrideRequired:(Z)Lorg/jboss/aesh/cl/internal/ProcessedOptionBuilder;
     187: invokevirtual #76                 // Method org/jboss/aesh/cl/internal/ProcessedOptionBuilder.create:()Lorg/jboss/aesh/cl/internal/ProcessedOption;
     190: invokevirtual #77                 // Method org/jboss/aesh/cl/internal/ProcessedCommand.addOption:(Lorg/jboss/aesh/cl/internal/ProcessedOption;)V
     193: goto          333
     196: aload_0
     197: new           #47                 // class org/jboss/aesh/cl/internal/ProcessedOptionBuilder
     200: dup
     201: invokespecial #48                 // Method org/jboss/aesh/cl/internal/ProcessedOptionBuilder."<init>":()V
     204: aload_2
     205: invokeinterface #49,  1           // InterfaceMethod org/jboss/aesh/cl/Option.shortName:()C
     210: invokevirtual #50                 // Method org/jboss/aesh/cl/internal/ProcessedOptionBuilder.shortName:(C)Lorg/jboss/aesh/cl/internal/ProcessedOptionBuilder;
     213: aload_2
     214: invokeinterface #45,  1           // InterfaceMethod org/jboss/aesh/cl/Option.name:()Ljava/lang/String;
     219: invokevirtual #52                 // Method org/jboss/aesh/cl/internal/ProcessedOptionBuilder.name:(Ljava/lang/String;)Lorg/jboss/aesh/cl/internal/ProcessedOptionBuilder;
     222: aload_2
     223: invokeinterface #53,  1           // InterfaceMethod org/jboss/aesh/cl/Option.description:()Ljava/lang/String;
     228: invokevirtual #54                 // Method org/jboss/aesh/cl/internal/ProcessedOptionBuilder.description:(Ljava/lang/String;)Lorg/jboss/aesh/cl/internal/ProcessedOptionBuilder;
     231: aload_2
     232: invokeinterface #55,  1           // InterfaceMethod org/jboss/aesh/cl/Option.required:()Z
     237: invokevirtual #56                 // Method org/jboss/aesh/cl/internal/ProcessedOptionBuilder.required:(Z)Lorg/jboss/aesh/cl/internal/ProcessedOptionBuilder;
     240: bipush        44
     242: invokevirtual #57                 // Method org/jboss/aesh/cl/internal/ProcessedOptionBuilder.valueSeparator:(C)Lorg/jboss/aesh/cl/internal/ProcessedOptionBuilder;
     245: aload_2
     246: invokeinterface #58,  1           // InterfaceMethod org/jboss/aesh/cl/Option.defaultValue:()[Ljava/lang/String;
     251: invokevirtual #59                 // Method org/jboss/aesh/cl/internal/ProcessedOptionBuilder.addAllDefaultValues:([Ljava/lang/String;)Lorg/jboss/aesh/cl/internal/ProcessedOptionBuilder;
     254: aload_1
     255: invokevirtual #60                 // Method java/lang/reflect/Field.getType:()Ljava/lang/Class;
     258: invokevirtual #61                 // Method org/jboss/aesh/cl/internal/ProcessedOptionBuilder.type:(Ljava/lang/Class;)Lorg/jboss/aesh/cl/internal/ProcessedOptionBuilder;
     261: aload_1
     262: invokevirtual #51                 // Method java/lang/reflect/Field.getName:()Ljava/lang/String;
     265: invokevirtual #62                 // Method org/jboss/aesh/cl/internal/ProcessedOptionBuilder.fieldName:(Ljava/lang/String;)Lorg/jboss/aesh/cl/internal/ProcessedOptionBuilder;
     268: aload         6
     270: invokevirtual #63                 // Method org/jboss/aesh/cl/internal/ProcessedOptionBuilder.optionType:(Lorg/jboss/aesh/cl/internal/OptionType;)Lorg/jboss/aesh/cl/internal/ProcessedOptionBuilder;
     273: aload_2
     274: invokeinterface #64,  1           // InterfaceMethod org/jboss/aesh/cl/Option.converter:()Ljava/lang/Class;
     279: invokevirtual #65                 // Method org/jboss/aesh/cl/internal/ProcessedOptionBuilder.converter:(Ljava/lang/Class;)Lorg/jboss/aesh/cl/internal/ProcessedOptionBuilder;
     282: aload_2
     283: invokeinterface #66,  1           // InterfaceMethod org/jboss/aesh/cl/Option.completer:()Ljava/lang/Class;
     288: invokevirtual #67                 // Method org/jboss/aesh/cl/internal/ProcessedOptionBuilder.completer:(Ljava/lang/Class;)Lorg/jboss/aesh/cl/internal/ProcessedOptionBuilder;
     291: aload_2
     292: invokeinterface #68,  1           // InterfaceMethod org/jboss/aesh/cl/Option.validator:()Ljava/lang/Class;
     297: invokevirtual #69                 // Method org/jboss/aesh/cl/internal/ProcessedOptionBuilder.validator:(Ljava/lang/Class;)Lorg/jboss/aesh/cl/internal/ProcessedOptionBuilder;
     300: aload_2
     301: invokeinterface #70,  1           // InterfaceMethod org/jboss/aesh/cl/Option.activator:()Ljava/lang/Class;
     306: invokevirtual #71                 // Method org/jboss/aesh/cl/internal/ProcessedOptionBuilder.activator:(Ljava/lang/Class;)Lorg/jboss/aesh/cl/internal/ProcessedOptionBuilder;
     309: aload_2
     310: invokeinterface #72,  1           // InterfaceMethod org/jboss/aesh/cl/Option.renderer:()Ljava/lang/Class;
     315: invokevirtual #73                 // Method org/jboss/aesh/cl/internal/ProcessedOptionBuilder.renderer:(Ljava/lang/Class;)Lorg/jboss/aesh/cl/internal/ProcessedOptionBuilder;
     318: aload_2
     319: invokeinterface #74,  1           // InterfaceMethod org/jboss/aesh/cl/Option.overrideRequired:()Z
     324: invokevirtual #75                 // Method org/jboss/aesh/cl/internal/ProcessedOptionBuilder.overrideRequired:(Z)Lorg/jboss/aesh/cl/internal/ProcessedOptionBuilder;
     327: invokevirtual #76                 // Method org/jboss/aesh/cl/internal/ProcessedOptionBuilder.create:()Lorg/jboss/aesh/cl/internal/ProcessedOption;
     330: invokevirtual #77                 // Method org/jboss/aesh/cl/internal/ProcessedCommand.addOption:(Lorg/jboss/aesh/cl/internal/ProcessedOption;)V
     333: goto          1129
     336: aload_1
     337: ldc           #78                 // class org/jboss/aesh/cl/OptionList
     339: invokevirtual #41                 // Method java/lang/reflect/Field.getAnnotation:(Ljava/lang/Class;)Ljava/lang/annotation/Annotation;
     342: checkcast     #78                 // class org/jboss/aesh/cl/OptionList
     345: dup
     346: astore        4
     348: ifnull        718
     351: ldc           #79                 // class java/util/Collection
     353: aload_1
     354: invokevirtual #60                 // Method java/lang/reflect/Field.getType:()Ljava/lang/Class;
     357: invokevirtual #80                 // Method java/lang/Class.isAssignableFrom:(Ljava/lang/Class;)Z
     360: ifne          373
     363: new           #34                 // class org/jboss/aesh/cl/parser/CommandLineParserException
     366: dup
     367: ldc           #81                 // String OptionList field must be instance of Collection
     369: invokespecial #36                 // Method org/jboss/aesh/cl/parser/CommandLineParserException."<init>":(Ljava/lang/String;)V
     372: athrow
     373: ldc           #82                 // class java/lang/Object
     375: astore        6
     377: aload_1
     378: invokevirtual #83                 // Method java/lang/reflect/Field.getGenericType:()Ljava/lang/reflect/Type;
     381: ifnull        407
     384: aload_1
     385: invokevirtual #83                 // Method java/lang/reflect/Field.getGenericType:()Ljava/lang/reflect/Type;
     388: checkcast     #84                 // class java/lang/reflect/ParameterizedType
     391: astore        7
     393: aload         7
     395: invokeinterface #85,  1           // InterfaceMethod java/lang/reflect/ParameterizedType.getActualTypeArguments:()[Ljava/lang/reflect/Type;
     400: iconst_0
     401: aaload
     402: checkcast     #86                 // class java/lang/Class
     405: astore        6
     407: aload         4
     409: invokeinterface #87,  1           // InterfaceMethod org/jboss/aesh/cl/OptionList.name:()Ljava/lang/String;
     414: ifnull        431
     417: aload         4
     419: invokeinterface #87,  1           // InterfaceMethod org/jboss/aesh/cl/OptionList.name:()Ljava/lang/String;
     424: invokevirtual #46                 // Method java/lang/String.length:()I
     427: iconst_1
     428: if_icmpge     573
     431: aload_0
     432: new           #47                 // class org/jboss/aesh/cl/internal/ProcessedOptionBuilder
     435: dup
     436: invokespecial #48                 // Method org/jboss/aesh/cl/internal/ProcessedOptionBuilder."<init>":()V
     439: aload         4
     441: invokeinterface #88,  1           // InterfaceMethod org/jboss/aesh/cl/OptionList.shortName:()C
     446: invokevirtual #50                 // Method org/jboss/aesh/cl/internal/ProcessedOptionBuilder.shortName:(C)Lorg/jboss/aesh/cl/internal/ProcessedOptionBuilder;
     449: aload_1
     450: invokevirtual #51                 // Method java/lang/reflect/Field.getName:()Ljava/lang/String;
     453: invokevirtual #52                 // Method org/jboss/aesh/cl/internal/ProcessedOptionBuilder.name:(Ljava/lang/String;)Lorg/jboss/aesh/cl/internal/ProcessedOptionBuilder;
     456: aload         4
     458: invokeinterface #89,  1           // InterfaceMethod org/jboss/aesh/cl/OptionList.description:()Ljava/lang/String;
     463: invokevirtual #54                 // Method org/jboss/aesh/cl/internal/ProcessedOptionBuilder.description:(Ljava/lang/String;)Lorg/jboss/aesh/cl/internal/ProcessedOptionBuilder;
     466: aload         4
     468: invokeinterface #90,  1           // InterfaceMethod org/jboss/aesh/cl/OptionList.required:()Z
     473: invokevirtual #56                 // Method org/jboss/aesh/cl/internal/ProcessedOptionBuilder.required:(Z)Lorg/jboss/aesh/cl/internal/ProcessedOptionBuilder;
     476: aload         4
     478: invokeinterface #91,  1           // InterfaceMethod org/jboss/aesh/cl/OptionList.valueSeparator:()C
     483: invokevirtual #57                 // Method org/jboss/aesh/cl/internal/ProcessedOptionBuilder.valueSeparator:(C)Lorg/jboss/aesh/cl/internal/ProcessedOptionBuilder;
     486: aload         4
     488: invokeinterface #92,  1           // InterfaceMethod org/jboss/aesh/cl/OptionList.defaultValue:()[Ljava/lang/String;
     493: invokevirtual #59                 // Method org/jboss/aesh/cl/internal/ProcessedOptionBuilder.addAllDefaultValues:([Ljava/lang/String;)Lorg/jboss/aesh/cl/internal/ProcessedOptionBuilder;
     496: aload         6
     498: invokevirtual #61                 // Method org/jboss/aesh/cl/internal/ProcessedOptionBuilder.type:(Ljava/lang/Class;)Lorg/jboss/aesh/cl/internal/ProcessedOptionBuilder;
     501: aload_1
     502: invokevirtual #51                 // Method java/lang/reflect/Field.getName:()Ljava/lang/String;
     505: invokevirtual #62                 // Method org/jboss/aesh/cl/internal/ProcessedOptionBuilder.fieldName:(Ljava/lang/String;)Lorg/jboss/aesh/cl/internal/ProcessedOptionBuilder;
     508: getstatic     #93                 // Field org/jboss/aesh/cl/internal/OptionType.LIST:Lorg/jboss/aesh/cl/internal/OptionType;
     511: invokevirtual #63                 // Method org/jboss/aesh/cl/internal/ProcessedOptionBuilder.optionType:(Lorg/jboss/aesh/cl/internal/OptionType;)Lorg/jboss/aesh/cl/internal/ProcessedOptionBuilder;
     514: aload         4
     516: invokeinterface #94,  1           // InterfaceMethod org/jboss/aesh/cl/OptionList.converter:()Ljava/lang/Class;
     521: invokevirtual #65                 // Method org/jboss/aesh/cl/internal/ProcessedOptionBuilder.converter:(Ljava/lang/Class;)Lorg/jboss/aesh/cl/internal/ProcessedOptionBuilder;
     524: aload         4
     526: invokeinterface #95,  1           // InterfaceMethod org/jboss/aesh/cl/OptionList.completer:()Ljava/lang/Class;
     531: invokevirtual #67                 // Method org/jboss/aesh/cl/internal/ProcessedOptionBuilder.completer:(Ljava/lang/Class;)Lorg/jboss/aesh/cl/internal/ProcessedOptionBuilder;
     534: aload         4
     536: invokeinterface #96,  1           // InterfaceMethod org/jboss/aesh/cl/OptionList.validator:()Ljava/lang/Class;
     541: invokevirtual #69                 // Method org/jboss/aesh/cl/internal/ProcessedOptionBuilder.validator:(Ljava/lang/Class;)Lorg/jboss/aesh/cl/internal/ProcessedOptionBuilder;
     544: aload         4
     546: invokeinterface #97,  1           // InterfaceMethod org/jboss/aesh/cl/OptionList.activator:()Ljava/lang/Class;
     551: invokevirtual #71                 // Method org/jboss/aesh/cl/internal/ProcessedOptionBuilder.activator:(Ljava/lang/Class;)Lorg/jboss/aesh/cl/internal/ProcessedOptionBuilder;
     554: aload         4
     556: invokeinterface #98,  1           // InterfaceMethod org/jboss/aesh/cl/OptionList.renderer:()Ljava/lang/Class;
     561: invokevirtual #73                 // Method org/jboss/aesh/cl/internal/ProcessedOptionBuilder.renderer:(Ljava/lang/Class;)Lorg/jboss/aesh/cl/internal/ProcessedOptionBuilder;
     564: invokevirtual #76                 // Method org/jboss/aesh/cl/internal/ProcessedOptionBuilder.create:()Lorg/jboss/aesh/cl/internal/ProcessedOption;
     567: invokevirtual #77                 // Method org/jboss/aesh/cl/internal/ProcessedCommand.addOption:(Lorg/jboss/aesh/cl/internal/ProcessedOption;)V
     570: goto          715
     573: aload_0
     574: new           #47                 // class org/jboss/aesh/cl/internal/ProcessedOptionBuilder
     577: dup
     578: invokespecial #48                 // Method org/jboss/aesh/cl/internal/ProcessedOptionBuilder."<init>":()V
     581: aload         4
     583: invokeinterface #88,  1           // InterfaceMethod org/jboss/aesh/cl/OptionList.shortName:()C
     588: invokevirtual #50                 // Method org/jboss/aesh/cl/internal/ProcessedOptionBuilder.shortName:(C)Lorg/jboss/aesh/cl/internal/ProcessedOptionBuilder;
     591: aload         4
     593: invokeinterface #87,  1           // InterfaceMethod org/jboss/aesh/cl/OptionList.name:()Ljava/lang/String;
     598: invokevirtual #52                 // Method org/jboss/aesh/cl/internal/ProcessedOptionBuilder.name:(Ljava/lang/String;)Lorg/jboss/aesh/cl/internal/ProcessedOptionBuilder;
     601: aload         4
     603: invokeinterface #89,  1           // InterfaceMethod org/jboss/aesh/cl/OptionList.description:()Ljava/lang/String;
     608: invokevirtual #54                 // Method org/jboss/aesh/cl/internal/ProcessedOptionBuilder.description:(Ljava/lang/String;)Lorg/jboss/aesh/cl/internal/ProcessedOptionBuilder;
     611: aload         4
     613: invokeinterface #90,  1           // InterfaceMethod org/jboss/aesh/cl/OptionList.required:()Z
     618: invokevirtual #56                 // Method org/jboss/aesh/cl/internal/ProcessedOptionBuilder.required:(Z)Lorg/jboss/aesh/cl/internal/ProcessedOptionBuilder;
     621: aload         4
     623: invokeinterface #91,  1           // InterfaceMethod org/jboss/aesh/cl/OptionList.valueSeparator:()C
     628: invokevirtual #57                 // Method org/jboss/aesh/cl/internal/ProcessedOptionBuilder.valueSeparator:(C)Lorg/jboss/aesh/cl/internal/ProcessedOptionBuilder;
     631: aload         4
     633: invokeinterface #92,  1           // InterfaceMethod org/jboss/aesh/cl/OptionList.defaultValue:()[Ljava/lang/String;
     638: invokevirtual #59                 // Method org/jboss/aesh/cl/internal/ProcessedOptionBuilder.addAllDefaultValues:([Ljava/lang/String;)Lorg/jboss/aesh/cl/internal/ProcessedOptionBuilder;
     641: aload         6
     643: invokevirtual #61                 // Method org/jboss/aesh/cl/internal/ProcessedOptionBuilder.type:(Ljava/lang/Class;)Lorg/jboss/aesh/cl/internal/ProcessedOptionBuilder;
     646: aload_1
     647: invokevirtual #51                 // Method java/lang/reflect/Field.getName:()Ljava/lang/String;
     650: invokevirtual #62                 // Method org/jboss/aesh/cl/internal/ProcessedOptionBuilder.fieldName:(Ljava/lang/String;)Lorg/jboss/aesh/cl/internal/ProcessedOptionBuilder;
     653: getstatic     #93                 // Field org/jboss/aesh/cl/internal/OptionType.LIST:Lorg/jboss/aesh/cl/internal/OptionType;
     656: invokevirtual #63                 // Method org/jboss/aesh/cl/internal/ProcessedOptionBuilder.optionType:(Lorg/jboss/aesh/cl/internal/OptionType;)Lorg/jboss/aesh/cl/internal/ProcessedOptionBuilder;
     659: aload         4
     661: invokeinterface #94,  1           // InterfaceMethod org/jboss/aesh/cl/OptionList.converter:()Ljava/lang/Class;
     666: invokevirtual #65                 // Method org/jboss/aesh/cl/internal/ProcessedOptionBuilder.converter:(Ljava/lang/Class;)Lorg/jboss/aesh/cl/internal/ProcessedOptionBuilder;
     669: aload         4
     671: invokeinterface #95,  1           // InterfaceMethod org/jboss/aesh/cl/OptionList.completer:()Ljava/lang/Class;
     676: invokevirtual #67                 // Method org/jboss/aesh/cl/internal/ProcessedOptionBuilder.completer:(Ljava/lang/Class;)Lorg/jboss/aesh/cl/internal/ProcessedOptionBuilder;
     679: aload         4
     681: invokeinterface #96,  1           // InterfaceMethod org/jboss/aesh/cl/OptionList.validator:()Ljava/lang/Class;
     686: invokevirtual #69                 // Method org/jboss/aesh/cl/internal/ProcessedOptionBuilder.validator:(Ljava/lang/Class;)Lorg/jboss/aesh/cl/internal/ProcessedOptionBuilder;
     689: aload         4
     691: invokeinterface #97,  1           // InterfaceMethod org/jboss/aesh/cl/OptionList.activator:()Ljava/lang/Class;
     696: invokevirtual #71                 // Method org/jboss/aesh/cl/internal/ProcessedOptionBuilder.activator:(Ljava/lang/Class;)Lorg/jboss/aesh/cl/internal/ProcessedOptionBuilder;
     699: aload         4
     701: invokeinterface #98,  1           // InterfaceMethod org/jboss/aesh/cl/OptionList.renderer:()Ljava/lang/Class;
     706: invokevirtual #73                 // Method org/jboss/aesh/cl/internal/ProcessedOptionBuilder.renderer:(Ljava/lang/Class;)Lorg/jboss/aesh/cl/internal/ProcessedOptionBuilder;
     709: invokevirtual #76                 // Method org/jboss/aesh/cl/internal/ProcessedOptionBuilder.create:()Lorg/jboss/aesh/cl/internal/ProcessedOption;
     712: invokevirtual #77                 // Method org/jboss/aesh/cl/internal/ProcessedCommand.addOption:(Lorg/jboss/aesh/cl/internal/ProcessedOption;)V
     715: goto          1129
     718: aload_1
     719: ldc           #99                 // class org/jboss/aesh/cl/OptionGroup
     721: invokevirtual #41                 // Method java/lang/reflect/Field.getAnnotation:(Ljava/lang/Class;)Ljava/lang/annotation/Annotation;
     724: checkcast     #99                 // class org/jboss/aesh/cl/OptionGroup
     727: dup
     728: astore_3
     729: ifnull        953
     732: ldc           #100                // class java/util/Map
     734: aload_1
     735: invokevirtual #60                 // Method java/lang/reflect/Field.getType:()Ljava/lang/Class;
     738: invokevirtual #80                 // Method java/lang/Class.isAssignableFrom:(Ljava/lang/Class;)Z
     741: ifne          754
     744: new           #34                 // class org/jboss/aesh/cl/parser/CommandLineParserException
     747: dup
     748: ldc           #101                // String OptionGroup field must be instance of Map
     750: invokespecial #36                 // Method org/jboss/aesh/cl/parser/CommandLineParserException."<init>":(Ljava/lang/String;)V
     753: athrow
     754: ldc           #82                 // class java/lang/Object
     756: astore        6
     758: aload_1
     759: invokevirtual #83                 // Method java/lang/reflect/Field.getGenericType:()Ljava/lang/reflect/Type;
     762: ifnull        788
     765: aload_1
     766: invokevirtual #83                 // Method java/lang/reflect/Field.getGenericType:()Ljava/lang/reflect/Type;
     769: checkcast     #84                 // class java/lang/reflect/ParameterizedType
     772: astore        7
     774: aload         7
     776: invokeinterface #85,  1           // InterfaceMethod java/lang/reflect/ParameterizedType.getActualTypeArguments:()[Ljava/lang/reflect/Type;
     781: iconst_1
     782: aaload
     783: checkcast     #86                 // class java/lang/Class
     786: astore        6
     788: aload_3
     789: invokeinterface #102,  1          // InterfaceMethod org/jboss/aesh/cl/OptionGroup.name:()Ljava/lang/String;
     794: ifnull        810
     797: aload_3
     798: invokeinterface #102,  1          // InterfaceMethod org/jboss/aesh/cl/OptionGroup.name:()Ljava/lang/String;
     803: invokevirtual #46                 // Method java/lang/String.length:()I
     806: iconst_1
     807: if_icmpge     819
     810: aload_1
     811: invokevirtual #51                 // Method java/lang/reflect/Field.getName:()Ljava/lang/String;
     814: astore        7
     816: goto          827
     819: aload_3
     820: invokeinterface #102,  1          // InterfaceMethod org/jboss/aesh/cl/OptionGroup.name:()Ljava/lang/String;
     825: astore        7
     827: aload_0
     828: new           #47                 // class org/jboss/aesh/cl/internal/ProcessedOptionBuilder
     831: dup
     832: invokespecial #48                 // Method org/jboss/aesh/cl/internal/ProcessedOptionBuilder."<init>":()V
     835: aload_3
     836: invokeinterface #103,  1          // InterfaceMethod org/jboss/aesh/cl/OptionGroup.shortName:()C
     841: invokevirtual #50                 // Method org/jboss/aesh/cl/internal/ProcessedOptionBuilder.shortName:(C)Lorg/jboss/aesh/cl/internal/ProcessedOptionBuilder;
     844: aload         7
     846: invokevirtual #52                 // Method org/jboss/aesh/cl/internal/ProcessedOptionBuilder.name:(Ljava/lang/String;)Lorg/jboss/aesh/cl/internal/ProcessedOptionBuilder;
     849: aload_3
     850: invokeinterface #104,  1          // InterfaceMethod org/jboss/aesh/cl/OptionGroup.description:()Ljava/lang/String;
     855: invokevirtual #54                 // Method org/jboss/aesh/cl/internal/ProcessedOptionBuilder.description:(Ljava/lang/String;)Lorg/jboss/aesh/cl/internal/ProcessedOptionBuilder;
     858: aload_3
     859: invokeinterface #105,  1          // InterfaceMethod org/jboss/aesh/cl/OptionGroup.required:()Z
     864: invokevirtual #56                 // Method org/jboss/aesh/cl/internal/ProcessedOptionBuilder.required:(Z)Lorg/jboss/aesh/cl/internal/ProcessedOptionBuilder;
     867: bipush        44
     869: invokevirtual #57                 // Method org/jboss/aesh/cl/internal/ProcessedOptionBuilder.valueSeparator:(C)Lorg/jboss/aesh/cl/internal/ProcessedOptionBuilder;
     872: aload_3
     873: invokeinterface #106,  1          // InterfaceMethod org/jboss/aesh/cl/OptionGroup.defaultValue:()[Ljava/lang/String;
     878: invokevirtual #59                 // Method org/jboss/aesh/cl/internal/ProcessedOptionBuilder.addAllDefaultValues:([Ljava/lang/String;)Lorg/jboss/aesh/cl/internal/ProcessedOptionBuilder;
     881: aload         6
     883: invokevirtual #61                 // Method org/jboss/aesh/cl/internal/ProcessedOptionBuilder.type:(Ljava/lang/Class;)Lorg/jboss/aesh/cl/internal/ProcessedOptionBuilder;
     886: aload_1
     887: invokevirtual #51                 // Method java/lang/reflect/Field.getName:()Ljava/lang/String;
     890: invokevirtual #62                 // Method org/jboss/aesh/cl/internal/ProcessedOptionBuilder.fieldName:(Ljava/lang/String;)Lorg/jboss/aesh/cl/internal/ProcessedOptionBuilder;
     893: getstatic     #107                // Field org/jboss/aesh/cl/internal/OptionType.GROUP:Lorg/jboss/aesh/cl/internal/OptionType;
     896: invokevirtual #63                 // Method org/jboss/aesh/cl/internal/ProcessedOptionBuilder.optionType:(Lorg/jboss/aesh/cl/internal/OptionType;)Lorg/jboss/aesh/cl/internal/ProcessedOptionBuilder;
     899: aload_3
     900: invokeinterface #108,  1          // InterfaceMethod org/jboss/aesh/cl/OptionGroup.converter:()Ljava/lang/Class;
     905: invokevirtual #65                 // Method org/jboss/aesh/cl/internal/ProcessedOptionBuilder.converter:(Ljava/lang/Class;)Lorg/jboss/aesh/cl/internal/ProcessedOptionBuilder;
     908: aload_3
     909: invokeinterface #109,  1          // InterfaceMethod org/jboss/aesh/cl/OptionGroup.completer:()Ljava/lang/Class;
     914: invokevirtual #67                 // Method org/jboss/aesh/cl/internal/ProcessedOptionBuilder.completer:(Ljava/lang/Class;)Lorg/jboss/aesh/cl/internal/ProcessedOptionBuilder;
     917: aload_3
     918: invokeinterface #110,  1          // InterfaceMethod org/jboss/aesh/cl/OptionGroup.validator:()Ljava/lang/Class;
     923: invokevirtual #69                 // Method org/jboss/aesh/cl/internal/ProcessedOptionBuilder.validator:(Ljava/lang/Class;)Lorg/jboss/aesh/cl/internal/ProcessedOptionBuilder;
     926: aload_3
     927: invokeinterface #111,  1          // InterfaceMethod org/jboss/aesh/cl/OptionGroup.activator:()Ljava/lang/Class;
     932: invokevirtual #71                 // Method org/jboss/aesh/cl/internal/ProcessedOptionBuilder.activator:(Ljava/lang/Class;)Lorg/jboss/aesh/cl/internal/ProcessedOptionBuilder;
     935: aload_3
     936: invokeinterface #112,  1          // InterfaceMethod org/jboss/aesh/cl/OptionGroup.renderer:()Ljava/lang/Class;
     941: invokevirtual #73                 // Method org/jboss/aesh/cl/internal/ProcessedOptionBuilder.renderer:(Ljava/lang/Class;)Lorg/jboss/aesh/cl/internal/ProcessedOptionBuilder;
     944: invokevirtual #76                 // Method org/jboss/aesh/cl/internal/ProcessedOptionBuilder.create:()Lorg/jboss/aesh/cl/internal/ProcessedOption;
     947: invokevirtual #77                 // Method org/jboss/aesh/cl/internal/ProcessedCommand.addOption:(Lorg/jboss/aesh/cl/internal/ProcessedOption;)V
     950: goto          1129
     953: aload_1
     954: ldc           #113                // class org/jboss/aesh/cl/Arguments
     956: invokevirtual #41                 // Method java/lang/reflect/Field.getAnnotation:(Ljava/lang/Class;)Ljava/lang/annotation/Annotation;
     959: checkcast     #113                // class org/jboss/aesh/cl/Arguments
     962: dup
     963: astore        5
     965: ifnull        1129
     968: ldc           #79                 // class java/util/Collection
     970: aload_1
     971: invokevirtual #60                 // Method java/lang/reflect/Field.getType:()Ljava/lang/Class;
     974: invokevirtual #80                 // Method java/lang/Class.isAssignableFrom:(Ljava/lang/Class;)Z
     977: ifne          990
     980: new           #34                 // class org/jboss/aesh/cl/parser/CommandLineParserException
     983: dup
     984: ldc           #114                // String Arguments field must be instance of Collection
     986: invokespecial #36                 // Method org/jboss/aesh/cl/parser/CommandLineParserException."<init>":(Ljava/lang/String;)V
     989: athrow
     990: ldc           #82                 // class java/lang/Object
     992: astore        6
     994: aload_1
     995: invokevirtual #83                 // Method java/lang/reflect/Field.getGenericType:()Ljava/lang/reflect/Type;
     998: ifnull        1024
    1001: aload_1
    1002: invokevirtual #83                 // Method java/lang/reflect/Field.getGenericType:()Ljava/lang/reflect/Type;
    1005: checkcast     #84                 // class java/lang/reflect/ParameterizedType
    1008: astore        7
    1010: aload         7
    1012: invokeinterface #85,  1           // InterfaceMethod java/lang/reflect/ParameterizedType.getActualTypeArguments:()[Ljava/lang/reflect/Type;
    1017: iconst_0
    1018: aaload
    1019: checkcast     #86                 // class java/lang/Class
    1022: astore        6
    1024: aload_0
    1025: new           #47                 // class org/jboss/aesh/cl/internal/ProcessedOptionBuilder
    1028: dup
    1029: invokespecial #48                 // Method org/jboss/aesh/cl/internal/ProcessedOptionBuilder."<init>":()V
    1032: iconst_0
    1033: invokevirtual #50                 // Method org/jboss/aesh/cl/internal/ProcessedOptionBuilder.shortName:(C)Lorg/jboss/aesh/cl/internal/ProcessedOptionBuilder;
    1036: ldc           #115                // String
    1038: invokevirtual #52                 // Method org/jboss/aesh/cl/internal/ProcessedOptionBuilder.name:(Ljava/lang/String;)Lorg/jboss/aesh/cl/internal/ProcessedOptionBuilder;
    1041: aload         5
    1043: invokeinterface #116,  1          // InterfaceMethod org/jboss/aesh/cl/Arguments.description:()Ljava/lang/String;
    1048: invokevirtual #54                 // Method org/jboss/aesh/cl/internal/ProcessedOptionBuilder.description:(Ljava/lang/String;)Lorg/jboss/aesh/cl/internal/ProcessedOptionBuilder;
    1051: iconst_0
    1052: invokevirtual #56                 // Method org/jboss/aesh/cl/internal/ProcessedOptionBuilder.required:(Z)Lorg/jboss/aesh/cl/internal/ProcessedOptionBuilder;
    1055: aload         5
    1057: invokeinterface #117,  1          // InterfaceMethod org/jboss/aesh/cl/Arguments.valueSeparator:()C
    1062: invokevirtual #57                 // Method org/jboss/aesh/cl/internal/ProcessedOptionBuilder.valueSeparator:(C)Lorg/jboss/aesh/cl/internal/ProcessedOptionBuilder;
    1065: aload         5
    1067: invokeinterface #118,  1          // InterfaceMethod org/jboss/aesh/cl/Arguments.defaultValue:()[Ljava/lang/String;
    1072: invokevirtual #59                 // Method org/jboss/aesh/cl/internal/ProcessedOptionBuilder.addAllDefaultValues:([Ljava/lang/String;)Lorg/jboss/aesh/cl/internal/ProcessedOptionBuilder;
    1075: aload         6
    1077: invokevirtual #61                 // Method org/jboss/aesh/cl/internal/ProcessedOptionBuilder.type:(Ljava/lang/Class;)Lorg/jboss/aesh/cl/internal/ProcessedOptionBuilder;
    1080: aload_1
    1081: invokevirtual #51                 // Method java/lang/reflect/Field.getName:()Ljava/lang/String;
    1084: invokevirtual #62                 // Method org/jboss/aesh/cl/internal/ProcessedOptionBuilder.fieldName:(Ljava/lang/String;)Lorg/jboss/aesh/cl/internal/ProcessedOptionBuilder;
    1087: getstatic     #119                // Field org/jboss/aesh/cl/internal/OptionType.ARGUMENT:Lorg/jboss/aesh/cl/internal/OptionType;
    1090: invokevirtual #63                 // Method org/jboss/aesh/cl/internal/ProcessedOptionBuilder.optionType:(Lorg/jboss/aesh/cl/internal/OptionType;)Lorg/jboss/aesh/cl/internal/ProcessedOptionBuilder;
    1093: aload         5
    1095: invokeinterface #120,  1          // InterfaceMethod org/jboss/aesh/cl/Arguments.converter:()Ljava/lang/Class;
    1100: invokevirtual #65                 // Method org/jboss/aesh/cl/internal/ProcessedOptionBuilder.converter:(Ljava/lang/Class;)Lorg/jboss/aesh/cl/internal/ProcessedOptionBuilder;
    1103: aload         5
    1105: invokeinterface #121,  1          // InterfaceMethod org/jboss/aesh/cl/Arguments.completer:()Ljava/lang/Class;
    1110: invokevirtual #67                 // Method org/jboss/aesh/cl/internal/ProcessedOptionBuilder.completer:(Ljava/lang/Class;)Lorg/jboss/aesh/cl/internal/ProcessedOptionBuilder;
    1113: aload         5
    1115: invokeinterface #122,  1          // InterfaceMethod org/jboss/aesh/cl/Arguments.validator:()Ljava/lang/Class;
    1120: invokevirtual #69                 // Method org/jboss/aesh/cl/internal/ProcessedOptionBuilder.validator:(Ljava/lang/Class;)Lorg/jboss/aesh/cl/internal/ProcessedOptionBuilder;
    1123: invokevirtual #76                 // Method org/jboss/aesh/cl/internal/ProcessedOptionBuilder.create:()Lorg/jboss/aesh/cl/internal/ProcessedOption;
    1126: invokevirtual #123                // Method org/jboss/aesh/cl/internal/ProcessedCommand.setArgument:(Lorg/jboss/aesh/cl/internal/ProcessedOption;)V
    1129: return

  public static void parseAndPopulate(org.jboss.aesh.console.command.Command, java.lang.String, java.lang.String...) throws org.jboss.aesh.cl.parser.CommandLineParserException, org.jboss.aesh.cl.validator.OptionValidatorException;
    Code:
       0: new           #124                // class java/lang/StringBuilder
       3: dup
       4: aload_1
       5: invokespecial #125                // Method java/lang/StringBuilder."<init>":(Ljava/lang/String;)V
       8: astore_3
       9: aload_2
      10: astore        4
      12: aload         4
      14: arraylength
      15: istore        5
      17: iconst_0
      18: istore        6
      20: iload         6
      22: iload         5
      24: if_icmpge     52
      27: aload         4
      29: iload         6
      31: aaload
      32: astore        7
      34: aload_3
      35: ldc           #126                // String
      37: invokevirtual #127                // Method java/lang/StringBuilder.append:(Ljava/lang/String;)Ljava/lang/StringBuilder;
      40: aload         7
      42: invokevirtual #127                // Method java/lang/StringBuilder.append:(Ljava/lang/String;)Ljava/lang/StringBuilder;
      45: pop
      46: iinc          6, 1
      49: goto          20
      52: aload_0
      53: aload_3
      54: invokevirtual #128                // Method java/lang/StringBuilder.toString:()Ljava/lang/String;
      57: invokestatic  #129                // Method parseAndPopulate:(Lorg/jboss/aesh/console/command/Command;Ljava/lang/String;)V
      60: return

  public static void parseAndPopulate(org.jboss.aesh.console.command.Command, java.lang.String) throws org.jboss.aesh.cl.parser.CommandLineParserException, org.jboss.aesh.cl.validator.OptionValidatorException;
    Code:
       0: aload_0
       1: invokestatic  #2                  // Method doGenerateCommandLineParser:(Lorg/jboss/aesh/console/command/Command;)Lorg/jboss/aesh/console/command/container/AeshCommandContainer;
       4: invokevirtual #130                // Method org/jboss/aesh/console/command/container/AeshCommandContainer.getParser:()Lorg/jboss/aesh/cl/parser/CommandLineParser;
       7: astore_2
       8: new           #131                // class org/jboss/aesh/console/AeshInvocationProviders
      11: dup
      12: new           #132                // class org/jboss/aesh/console/command/converter/AeshConverterInvocationProvider
      15: dup
      16: invokespecial #133                // Method org/jboss/aesh/console/command/converter/AeshConverterInvocationProvider."<init>":()V
      19: new           #134                // class org/jboss/aesh/console/command/completer/AeshCompleterInvocationProvider
      22: dup
      23: invokespecial #135                // Method org/jboss/aesh/console/command/completer/AeshCompleterInvocationProvider."<init>":()V
      26: new           #136                // class org/jboss/aesh/console/command/validator/AeshValidatorInvocationProvider
      29: dup
      30: invokespecial #137                // Method org/jboss/aesh/console/command/validator/AeshValidatorInvocationProvider."<init>":()V
      33: new           #138                // class org/jboss/aesh/console/command/activator/AeshOptionActivatorProvider
      36: dup
      37: invokespecial #139                // Method org/jboss/aesh/console/command/activator/AeshOptionActivatorProvider."<init>":()V
      40: invokespecial #140                // Method org/jboss/aesh/console/AeshInvocationProviders."<init>":(Lorg/jboss/aesh/console/command/converter/ConverterInvocationProvider;Lorg/jboss/aesh/console/command/completer/CompleterInvocationProvider;Lorg/jboss/aesh/console/command/validator/ValidatorInvocationProvider;Lorg/jboss/aesh/console/command/activator/OptionActivatorProvider;)V
      43: astore_3
      44: aload_2
      45: invokeinterface #141,  1          // InterfaceMethod org/jboss/aesh/cl/parser/CommandLineParser.getCommandPopulator:()Lorg/jboss/aesh/cl/populator/CommandPopulator;
      50: aload_2
      51: aload_1
      52: invokeinterface #142,  2          // InterfaceMethod org/jboss/aesh/cl/parser/CommandLineParser.parse:(Ljava/lang/String;)Lorg/jboss/aesh/cl/CommandLine;
      57: aload_3
      58: aconst_null
      59: iconst_1
      60: invokeinterface #143,  5          // InterfaceMethod org/jboss/aesh/cl/populator/CommandPopulator.populateObject:(Lorg/jboss/aesh/cl/CommandLine;Lorg/jboss/aesh/console/InvocationProviders;Lorg/jboss/aesh/console/AeshContext;Z)V
      65: return
}
