Compiled from "FileDescriptor.java"
public class io.netty.channel.unix.FileDescriptor {
  private static final java.util.concurrent.atomic.AtomicIntegerFieldUpdater<io.netty.channel.unix.FileDescriptor> stateUpdater;

  private static final int STATE_CLOSED_MASK;

  private static final int STATE_INPUT_SHUTDOWN_MASK;

  private static final int STATE_OUTPUT_SHUTDOWN_MASK;

  private static final int STATE_ALL_MASK;

  volatile int state;

  final int fd;

  public io.netty.channel.unix.FileDescriptor(int);
    Code:
       0: aload_0
       1: invokespecial #2                  // Method java/lang/Object."<init>":()V
       4: iload_1
       5: ldc           #3                  // String fd
       7: invokestatic  #4                  // Method io/netty/util/internal/ObjectUtil.checkPositiveOrZero:(ILjava/lang/String;)I
      10: pop
      11: aload_0
      12: iload_1
      13: putfield      #5                  // Field fd:I
      16: return

  public final int intValue();
    Code:
       0: aload_0
       1: getfield      #5                  // Field fd:I
       4: ireturn

  protected boolean markClosed();
    Code:
       0: aload_0
       1: getfield      #6                  // Field state:I
       4: istore_1
       5: iload_1
       6: invokestatic  #7                  // Method isClosed:(I)Z
       9: ifeq          14
      12: iconst_0
      13: ireturn
      14: aload_0
      15: iload_1
      16: iload_1
      17: bipush        7
      19: ior
      20: invokevirtual #8                  // Method casState:(II)Z
      23: ifeq          28
      26: iconst_1
      27: ireturn
      28: goto          0

  public void close() throws java.io.IOException;
    Code:
       0: aload_0
       1: invokevirtual #9                  // Method markClosed:()Z
       4: ifeq          26
       7: aload_0
       8: getfield      #5                  // Field fd:I
      11: invokestatic  #10                 // Method close:(I)I
      14: istore_1
      15: iload_1
      16: ifge          26
      19: ldc           #11                 // String close
      21: iload_1
      22: invokestatic  #12                 // Method io/netty/channel/unix/Errors.newIOException:(Ljava/lang/String;I)Lio/netty/channel/unix/Errors$NativeIoException;
      25: athrow
      26: return

  public boolean isOpen();
    Code:
       0: aload_0
       1: getfield      #6                  // Field state:I
       4: invokestatic  #7                  // Method isClosed:(I)Z
       7: ifne          14
      10: iconst_1
      11: goto          15
      14: iconst_0
      15: ireturn

  public final int write(java.nio.ByteBuffer, int, int) throws java.io.IOException;
    Code:
       0: aload_0
       1: getfield      #5                  // Field fd:I
       4: aload_1
       5: iload_2
       6: iload_3
       7: invokestatic  #13                 // Method write:(ILjava/nio/ByteBuffer;II)I
      10: istore        4
      12: iload         4
      14: iflt          20
      17: iload         4
      19: ireturn
      20: ldc           #14                 // String write
      22: iload         4
      24: invokestatic  #15                 // Method io/netty/channel/unix/Errors.ioResult:(Ljava/lang/String;I)I
      27: ireturn

  public final int writeAddress(long, int, int) throws java.io.IOException;
    Code:
       0: aload_0
       1: getfield      #5                  // Field fd:I
       4: lload_1
       5: iload_3
       6: iload         4
       8: invokestatic  #16                 // Method writeAddress:(IJII)I
      11: istore        5
      13: iload         5
      15: iflt          21
      18: iload         5
      20: ireturn
      21: ldc           #17                 // String writeAddress
      23: iload         5
      25: invokestatic  #15                 // Method io/netty/channel/unix/Errors.ioResult:(Ljava/lang/String;I)I
      28: ireturn

  public final long writev(java.nio.ByteBuffer[], int, int, long) throws java.io.IOException;
    Code:
       0: aload_0
       1: getfield      #5                  // Field fd:I
       4: aload_1
       5: iload_2
       6: getstatic     #18                 // Field io/netty/channel/unix/Limits.IOV_MAX:I
       9: iload_3
      10: invokestatic  #19                 // Method java/lang/Math.min:(II)I
      13: lload         4
      15: invokestatic  #20                 // Method writev:(I[Ljava/nio/ByteBuffer;IIJ)J
      18: lstore        6
      20: lload         6
      22: lconst_0
      23: lcmp
      24: iflt          30
      27: lload         6
      29: lreturn
      30: ldc           #21                 // String writev
      32: lload         6
      34: l2i
      35: invokestatic  #15                 // Method io/netty/channel/unix/Errors.ioResult:(Ljava/lang/String;I)I
      38: i2l
      39: lreturn

  public final long writevAddresses(long, int) throws java.io.IOException;
    Code:
       0: aload_0
       1: getfield      #5                  // Field fd:I
       4: lload_1
       5: iload_3
       6: invokestatic  #22                 // Method writevAddresses:(IJI)J
       9: lstore        4
      11: lload         4
      13: lconst_0
      14: lcmp
      15: iflt          21
      18: lload         4
      20: lreturn
      21: ldc           #23                 // String writevAddresses
      23: lload         4
      25: l2i
      26: invokestatic  #15                 // Method io/netty/channel/unix/Errors.ioResult:(Ljava/lang/String;I)I
      29: i2l
      30: lreturn

  public final int read(java.nio.ByteBuffer, int, int) throws java.io.IOException;
    Code:
       0: aload_0
       1: getfield      #5                  // Field fd:I
       4: aload_1
       5: iload_2
       6: iload_3
       7: invokestatic  #24                 // Method read:(ILjava/nio/ByteBuffer;II)I
      10: istore        4
      12: iload         4
      14: ifle          20
      17: iload         4
      19: ireturn
      20: iload         4
      22: ifne          27
      25: iconst_m1
      26: ireturn
      27: ldc           #25                 // String read
      29: iload         4
      31: invokestatic  #15                 // Method io/netty/channel/unix/Errors.ioResult:(Ljava/lang/String;I)I
      34: ireturn

  public final int readAddress(long, int, int) throws java.io.IOException;
    Code:
       0: aload_0
       1: getfield      #5                  // Field fd:I
       4: lload_1
       5: iload_3
       6: iload         4
       8: invokestatic  #26                 // Method readAddress:(IJII)I
      11: istore        5
      13: iload         5
      15: ifle          21
      18: iload         5
      20: ireturn
      21: iload         5
      23: ifne          28
      26: iconst_m1
      27: ireturn
      28: ldc           #27                 // String readAddress
      30: iload         5
      32: invokestatic  #15                 // Method io/netty/channel/unix/Errors.ioResult:(Ljava/lang/String;I)I
      35: ireturn

  public java.lang.String toString();
    Code:
       0: new           #28                 // class java/lang/StringBuilder
       3: dup
       4: invokespecial #29                 // Method java/lang/StringBuilder."<init>":()V
       7: ldc           #30                 // String FileDescriptor{fd=
       9: invokevirtual #31                 // Method java/lang/StringBuilder.append:(Ljava/lang/String;)Ljava/lang/StringBuilder;
      12: aload_0
      13: getfield      #5                  // Field fd:I
      16: invokevirtual #32                 // Method java/lang/StringBuilder.append:(I)Ljava/lang/StringBuilder;
      19: bipush        125
      21: invokevirtual #33                 // Method java/lang/StringBuilder.append:(C)Ljava/lang/StringBuilder;
      24: invokevirtual #34                 // Method java/lang/StringBuilder.toString:()Ljava/lang/String;
      27: areturn

  public boolean equals(java.lang.Object);
    Code:
       0: aload_0
       1: aload_1
       2: if_acmpne     7
       5: iconst_1
       6: ireturn
       7: aload_1
       8: instanceof    #1                  // class io/netty/channel/unix/FileDescriptor
      11: ifne          16
      14: iconst_0
      15: ireturn
      16: aload_0
      17: getfield      #5                  // Field fd:I
      20: aload_1
      21: checkcast     #1                  // class io/netty/channel/unix/FileDescriptor
      24: getfield      #5                  // Field fd:I
      27: if_icmpne     34
      30: iconst_1
      31: goto          35
      34: iconst_0
      35: ireturn

  public int hashCode();
    Code:
       0: aload_0
       1: getfield      #5                  // Field fd:I
       4: ireturn

  public static io.netty.channel.unix.FileDescriptor from(java.lang.String) throws java.io.IOException;
    Code:
       0: aload_0
       1: ldc           #35                 // String path
       3: invokestatic  #36                 // Method io/netty/util/internal/ObjectUtil.checkNotNull:(Ljava/lang/Object;Ljava/lang/String;)Ljava/lang/Object;
       6: checkcast     #37                 // class java/lang/String
       9: invokestatic  #38                 // Method open:(Ljava/lang/String;)I
      12: istore_1
      13: iload_1
      14: ifge          24
      17: ldc           #39                 // String open
      19: iload_1
      20: invokestatic  #12                 // Method io/netty/channel/unix/Errors.newIOException:(Ljava/lang/String;I)Lio/netty/channel/unix/Errors$NativeIoException;
      23: athrow
      24: new           #1                  // class io/netty/channel/unix/FileDescriptor
      27: dup
      28: iload_1
      29: invokespecial #40                 // Method "<init>":(I)V
      32: areturn

  public static io.netty.channel.unix.FileDescriptor from(java.io.File) throws java.io.IOException;
    Code:
       0: aload_0
       1: ldc           #41                 // String file
       3: invokestatic  #36                 // Method io/netty/util/internal/ObjectUtil.checkNotNull:(Ljava/lang/Object;Ljava/lang/String;)Ljava/lang/Object;
       6: checkcast     #42                 // class java/io/File
       9: invokevirtual #43                 // Method java/io/File.getPath:()Ljava/lang/String;
      12: invokestatic  #44                 // Method from:(Ljava/lang/String;)Lio/netty/channel/unix/FileDescriptor;
      15: areturn

  public static io.netty.channel.unix.FileDescriptor[] pipe() throws java.io.IOException;
    Code:
       0: invokestatic  #45                 // Method newPipe:()J
       3: lstore_0
       4: lload_0
       5: lconst_0
       6: lcmp
       7: ifge          18
      10: ldc           #46                 // String newPipe
      12: lload_0
      13: l2i
      14: invokestatic  #12                 // Method io/netty/channel/unix/Errors.newIOException:(Ljava/lang/String;I)Lio/netty/channel/unix/Errors$NativeIoException;
      17: athrow
      18: iconst_2
      19: anewarray     #1                  // class io/netty/channel/unix/FileDescriptor
      22: dup
      23: iconst_0
      24: new           #1                  // class io/netty/channel/unix/FileDescriptor
      27: dup
      28: lload_0
      29: bipush        32
      31: lushr
      32: l2i
      33: invokespecial #40                 // Method "<init>":(I)V
      36: aastore
      37: dup
      38: iconst_1
      39: new           #1                  // class io/netty/channel/unix/FileDescriptor
      42: dup
      43: lload_0
      44: l2i
      45: invokespecial #40                 // Method "<init>":(I)V
      48: aastore
      49: areturn

  final boolean casState(int, int);
    Code:
       0: getstatic     #47                 // Field stateUpdater:Ljava/util/concurrent/atomic/AtomicIntegerFieldUpdater;
       3: aload_0
       4: iload_1
       5: iload_2
       6: invokevirtual #48                 // Method java/util/concurrent/atomic/AtomicIntegerFieldUpdater.compareAndSet:(Ljava/lang/Object;II)Z
       9: ireturn

  static boolean isClosed(int);
    Code:
       0: iload_0
       1: iconst_1
       2: iand
       3: ifeq          10
       6: iconst_1
       7: goto          11
      10: iconst_0
      11: ireturn

  static boolean isInputShutdown(int);
    Code:
       0: iload_0
       1: iconst_2
       2: iand
       3: ifeq          10
       6: iconst_1
       7: goto          11
      10: iconst_0
      11: ireturn

  static boolean isOutputShutdown(int);
    Code:
       0: iload_0
       1: iconst_4
       2: iand
       3: ifeq          10
       6: iconst_1
       7: goto          11
      10: iconst_0
      11: ireturn

  static int inputShutdown(int);
    Code:
       0: iload_0
       1: iconst_2
       2: ior
       3: ireturn

  static int outputShutdown(int);
    Code:
       0: iload_0
       1: iconst_4
       2: ior
       3: ireturn

  private static native int open(java.lang.String);

  private static native int close(int);

  private static native int write(int, java.nio.ByteBuffer, int, int);

  private static native int writeAddress(int, long, int, int);

  private static native long writev(int, java.nio.ByteBuffer[], int, int, long);

  private static native long writevAddresses(int, long, int);

  private static native int read(int, java.nio.ByteBuffer, int, int);

  private static native int readAddress(int, long, int, int);

  private static native long newPipe();

  static {};
    Code:
       0: ldc           #1                  // class io/netty/channel/unix/FileDescriptor
       2: ldc           #49                 // String state
       4: invokestatic  #50                 // Method java/util/concurrent/atomic/AtomicIntegerFieldUpdater.newUpdater:(Ljava/lang/Class;Ljava/lang/String;)Ljava/util/concurrent/atomic/AtomicIntegerFieldUpdater;
       7: putstatic     #47                 // Field stateUpdater:Ljava/util/concurrent/atomic/AtomicIntegerFieldUpdater;
      10: return
}
