Compiled from "PluginProtos.java"
public final class com.google.protobuf.compiler.PluginProtos$CodeGeneratorResponse$File$Builder extends com.google.protobuf.GeneratedMessage$Builder<com.google.protobuf.compiler.PluginProtos$CodeGeneratorResponse$File$Builder> implements com.google.protobuf.compiler.PluginProtos$CodeGeneratorResponse$FileOrBuilder {
  private int bitField0_;

  private java.lang.Object name_;

  private java.lang.Object insertionPoint_;

  private java.lang.Object content_;

  public static final com.google.protobuf.Descriptors$Descriptor getDescriptor();
    Code:
       0: invokestatic  #3                  // Method com/google/protobuf/compiler/PluginProtos.access$1500:()Lcom/google/protobuf/Descriptors$Descriptor;
       3: areturn

  protected com.google.protobuf.GeneratedMessage$FieldAccessorTable internalGetFieldAccessorTable();
    Code:
       0: invokestatic  #4                  // Method com/google/protobuf/compiler/PluginProtos.access$1600:()Lcom/google/protobuf/GeneratedMessage$FieldAccessorTable;
       3: ldc           #5                  // class com/google/protobuf/compiler/PluginProtos$CodeGeneratorResponse$File
       5: ldc           #6                  // class com/google/protobuf/compiler/PluginProtos$CodeGeneratorResponse$File$Builder
       7: invokevirtual #7                  // Method com/google/protobuf/GeneratedMessage$FieldAccessorTable.ensureFieldAccessorsInitialized:(Ljava/lang/Class;Ljava/lang/Class;)Lcom/google/protobuf/GeneratedMessage$FieldAccessorTable;
      10: areturn

  private com.google.protobuf.compiler.PluginProtos$CodeGeneratorResponse$File$Builder();
    Code:
       0: aload_0
       1: invokespecial #8                  // Method com/google/protobuf/GeneratedMessage$Builder."<init>":()V
       4: aload_0
       5: ldc           #9                  // String
       7: putfield      #10                 // Field name_:Ljava/lang/Object;
      10: aload_0
      11: ldc           #9                  // String
      13: putfield      #11                 // Field insertionPoint_:Ljava/lang/Object;
      16: aload_0
      17: ldc           #9                  // String
      19: putfield      #12                 // Field content_:Ljava/lang/Object;
      22: aload_0
      23: invokespecial #13                 // Method maybeForceBuilderInitialization:()V
      26: return

  private com.google.protobuf.compiler.PluginProtos$CodeGeneratorResponse$File$Builder(com.google.protobuf.GeneratedMessage$BuilderParent);
    Code:
       0: aload_0
       1: aload_1
       2: invokespecial #14                 // Method com/google/protobuf/GeneratedMessage$Builder."<init>":(Lcom/google/protobuf/GeneratedMessage$BuilderParent;)V
       5: aload_0
       6: ldc           #9                  // String
       8: putfield      #10                 // Field name_:Ljava/lang/Object;
      11: aload_0
      12: ldc           #9                  // String
      14: putfield      #11                 // Field insertionPoint_:Ljava/lang/Object;
      17: aload_0
      18: ldc           #9                  // String
      20: putfield      #12                 // Field content_:Ljava/lang/Object;
      23: aload_0
      24: invokespecial #13                 // Method maybeForceBuilderInitialization:()V
      27: return

  private void maybeForceBuilderInitialization();
    Code:
       0: invokestatic  #15                 // Method com/google/protobuf/compiler/PluginProtos$CodeGeneratorResponse$File.access$1900:()Z
       3: ifeq          6
       6: return

  public com.google.protobuf.compiler.PluginProtos$CodeGeneratorResponse$File$Builder clear();
    Code:
       0: aload_0
       1: invokespecial #16                 // Method com/google/protobuf/GeneratedMessage$Builder.clear:()Lcom/google/protobuf/GeneratedMessage$Builder;
       4: pop
       5: aload_0
       6: ldc           #9                  // String
       8: putfield      #10                 // Field name_:Ljava/lang/Object;
      11: aload_0
      12: aload_0
      13: getfield      #17                 // Field bitField0_:I
      16: bipush        -2
      18: iand
      19: putfield      #17                 // Field bitField0_:I
      22: aload_0
      23: ldc           #9                  // String
      25: putfield      #11                 // Field insertionPoint_:Ljava/lang/Object;
      28: aload_0
      29: aload_0
      30: getfield      #17                 // Field bitField0_:I
      33: bipush        -3
      35: iand
      36: putfield      #17                 // Field bitField0_:I
      39: aload_0
      40: ldc           #9                  // String
      42: putfield      #12                 // Field content_:Ljava/lang/Object;
      45: aload_0
      46: aload_0
      47: getfield      #17                 // Field bitField0_:I
      50: bipush        -5
      52: iand
      53: putfield      #17                 // Field bitField0_:I
      56: aload_0
      57: areturn

  public com.google.protobuf.Descriptors$Descriptor getDescriptorForType();
    Code:
       0: invokestatic  #3                  // Method com/google/protobuf/compiler/PluginProtos.access$1500:()Lcom/google/protobuf/Descriptors$Descriptor;
       3: areturn

  public com.google.protobuf.compiler.PluginProtos$CodeGeneratorResponse$File getDefaultInstanceForType();
    Code:
       0: invokestatic  #18                 // Method com/google/protobuf/compiler/PluginProtos$CodeGeneratorResponse$File.getDefaultInstance:()Lcom/google/protobuf/compiler/PluginProtos$CodeGeneratorResponse$File;
       3: areturn

  public com.google.protobuf.compiler.PluginProtos$CodeGeneratorResponse$File build();
    Code:
       0: aload_0
       1: invokevirtual #19                 // Method buildPartial:()Lcom/google/protobuf/compiler/PluginProtos$CodeGeneratorResponse$File;
       4: astore_1
       5: aload_1
       6: invokevirtual #20                 // Method com/google/protobuf/compiler/PluginProtos$CodeGeneratorResponse$File.isInitialized:()Z
       9: ifne          17
      12: aload_1
      13: invokestatic  #21                 // Method newUninitializedMessageException:(Lcom/google/protobuf/Message;)Lcom/google/protobuf/UninitializedMessageException;
      16: athrow
      17: aload_1
      18: areturn

  public com.google.protobuf.compiler.PluginProtos$CodeGeneratorResponse$File buildPartial();
    Code:
       0: new           #5                  // class com/google/protobuf/compiler/PluginProtos$CodeGeneratorResponse$File
       3: dup
       4: aload_0
       5: aconst_null
       6: invokespecial #22                 // Method com/google/protobuf/compiler/PluginProtos$CodeGeneratorResponse$File."<init>":(Lcom/google/protobuf/GeneratedMessage$Builder;Lcom/google/protobuf/compiler/PluginProtos$1;)V
       9: astore_1
      10: aload_0
      11: getfield      #17                 // Field bitField0_:I
      14: istore_2
      15: iconst_0
      16: istore_3
      17: iload_2
      18: iconst_1
      19: iand
      20: iconst_1
      21: if_icmpne     28
      24: iload_3
      25: iconst_1
      26: ior
      27: istore_3
      28: aload_1
      29: aload_0
      30: getfield      #10                 // Field name_:Ljava/lang/Object;
      33: invokestatic  #23                 // Method com/google/protobuf/compiler/PluginProtos$CodeGeneratorResponse$File.access$2102:(Lcom/google/protobuf/compiler/PluginProtos$CodeGeneratorResponse$File;Ljava/lang/Object;)Ljava/lang/Object;
      36: pop
      37: iload_2
      38: iconst_2
      39: iand
      40: iconst_2
      41: if_icmpne     48
      44: iload_3
      45: iconst_2
      46: ior
      47: istore_3
      48: aload_1
      49: aload_0
      50: getfield      #11                 // Field insertionPoint_:Ljava/lang/Object;
      53: invokestatic  #24                 // Method com/google/protobuf/compiler/PluginProtos$CodeGeneratorResponse$File.access$2202:(Lcom/google/protobuf/compiler/PluginProtos$CodeGeneratorResponse$File;Ljava/lang/Object;)Ljava/lang/Object;
      56: pop
      57: iload_2
      58: iconst_4
      59: iand
      60: iconst_4
      61: if_icmpne     68
      64: iload_3
      65: iconst_4
      66: ior
      67: istore_3
      68: aload_1
      69: aload_0
      70: getfield      #12                 // Field content_:Ljava/lang/Object;
      73: invokestatic  #25                 // Method com/google/protobuf/compiler/PluginProtos$CodeGeneratorResponse$File.access$2302:(Lcom/google/protobuf/compiler/PluginProtos$CodeGeneratorResponse$File;Ljava/lang/Object;)Ljava/lang/Object;
      76: pop
      77: aload_1
      78: iload_3
      79: invokestatic  #26                 // Method com/google/protobuf/compiler/PluginProtos$CodeGeneratorResponse$File.access$2402:(Lcom/google/protobuf/compiler/PluginProtos$CodeGeneratorResponse$File;I)I
      82: pop
      83: aload_0
      84: invokevirtual #27                 // Method onBuilt:()V
      87: aload_1
      88: areturn

  public com.google.protobuf.compiler.PluginProtos$CodeGeneratorResponse$File$Builder mergeFrom(com.google.protobuf.Message);
    Code:
       0: aload_1
       1: instanceof    #5                  // class com/google/protobuf/compiler/PluginProtos$CodeGeneratorResponse$File
       4: ifeq          16
       7: aload_0
       8: aload_1
       9: checkcast     #5                  // class com/google/protobuf/compiler/PluginProtos$CodeGeneratorResponse$File
      12: invokevirtual #28                 // Method mergeFrom:(Lcom/google/protobuf/compiler/PluginProtos$CodeGeneratorResponse$File;)Lcom/google/protobuf/compiler/PluginProtos$CodeGeneratorResponse$File$Builder;
      15: areturn
      16: aload_0
      17: aload_1
      18: invokespecial #29                 // Method com/google/protobuf/GeneratedMessage$Builder.mergeFrom:(Lcom/google/protobuf/Message;)Lcom/google/protobuf/AbstractMessage$Builder;
      21: pop
      22: aload_0
      23: areturn

  public com.google.protobuf.compiler.PluginProtos$CodeGeneratorResponse$File$Builder mergeFrom(com.google.protobuf.compiler.PluginProtos$CodeGeneratorResponse$File);
    Code:
       0: aload_1
       1: invokestatic  #18                 // Method com/google/protobuf/compiler/PluginProtos$CodeGeneratorResponse$File.getDefaultInstance:()Lcom/google/protobuf/compiler/PluginProtos$CodeGeneratorResponse$File;
       4: if_acmpne     9
       7: aload_0
       8: areturn
       9: aload_1
      10: invokevirtual #30                 // Method com/google/protobuf/compiler/PluginProtos$CodeGeneratorResponse$File.hasName:()Z
      13: ifeq          38
      16: aload_0
      17: dup
      18: getfield      #17                 // Field bitField0_:I
      21: iconst_1
      22: ior
      23: putfield      #17                 // Field bitField0_:I
      26: aload_0
      27: aload_1
      28: invokestatic  #31                 // Method com/google/protobuf/compiler/PluginProtos$CodeGeneratorResponse$File.access$2100:(Lcom/google/protobuf/compiler/PluginProtos$CodeGeneratorResponse$File;)Ljava/lang/Object;
      31: putfield      #10                 // Field name_:Ljava/lang/Object;
      34: aload_0
      35: invokevirtual #32                 // Method onChanged:()V
      38: aload_1
      39: invokevirtual #33                 // Method com/google/protobuf/compiler/PluginProtos$CodeGeneratorResponse$File.hasInsertionPoint:()Z
      42: ifeq          67
      45: aload_0
      46: dup
      47: getfield      #17                 // Field bitField0_:I
      50: iconst_2
      51: ior
      52: putfield      #17                 // Field bitField0_:I
      55: aload_0
      56: aload_1
      57: invokestatic  #34                 // Method com/google/protobuf/compiler/PluginProtos$CodeGeneratorResponse$File.access$2200:(Lcom/google/protobuf/compiler/PluginProtos$CodeGeneratorResponse$File;)Ljava/lang/Object;
      60: putfield      #11                 // Field insertionPoint_:Ljava/lang/Object;
      63: aload_0
      64: invokevirtual #32                 // Method onChanged:()V
      67: aload_1
      68: invokevirtual #35                 // Method com/google/protobuf/compiler/PluginProtos$CodeGeneratorResponse$File.hasContent:()Z
      71: ifeq          96
      74: aload_0
      75: dup
      76: getfield      #17                 // Field bitField0_:I
      79: iconst_4
      80: ior
      81: putfield      #17                 // Field bitField0_:I
      84: aload_0
      85: aload_1
      86: invokestatic  #36                 // Method com/google/protobuf/compiler/PluginProtos$CodeGeneratorResponse$File.access$2300:(Lcom/google/protobuf/compiler/PluginProtos$CodeGeneratorResponse$File;)Ljava/lang/Object;
      89: putfield      #12                 // Field content_:Ljava/lang/Object;
      92: aload_0
      93: invokevirtual #32                 // Method onChanged:()V
      96: aload_0
      97: aload_1
      98: invokestatic  #37                 // Method com/google/protobuf/compiler/PluginProtos$CodeGeneratorResponse$File.access$2500:(Lcom/google/protobuf/compiler/PluginProtos$CodeGeneratorResponse$File;)Lcom/google/protobuf/UnknownFieldSet;
     101: invokevirtual #38                 // Method mergeUnknownFields:(Lcom/google/protobuf/UnknownFieldSet;)Lcom/google/protobuf/GeneratedMessage$Builder;
     104: pop
     105: aload_0
     106: invokevirtual #32                 // Method onChanged:()V
     109: aload_0
     110: areturn

  public final boolean isInitialized();
    Code:
       0: iconst_1
       1: ireturn

  public com.google.protobuf.compiler.PluginProtos$CodeGeneratorResponse$File$Builder mergeFrom(com.google.protobuf.CodedInputStream, com.google.protobuf.ExtensionRegistryLite) throws java.io.IOException;
    Code:
       0: aconst_null
       1: astore_3
       2: getstatic     #39                 // Field com/google/protobuf/compiler/PluginProtos$CodeGeneratorResponse$File.PARSER:Lcom/google/protobuf/Parser;
       5: aload_1
       6: aload_2
       7: invokeinterface #40,  3           // InterfaceMethod com/google/protobuf/Parser.parsePartialFrom:(Lcom/google/protobuf/CodedInputStream;Lcom/google/protobuf/ExtensionRegistryLite;)Ljava/lang/Object;
      12: checkcast     #5                  // class com/google/protobuf/compiler/PluginProtos$CodeGeneratorResponse$File
      15: astore_3
      16: jsr           44
      19: goto          58
      22: astore        4
      24: aload         4
      26: invokevirtual #42                 // Method com/google/protobuf/InvalidProtocolBufferException.getUnfinishedMessage:()Lcom/google/protobuf/MessageLite;
      29: checkcast     #5                  // class com/google/protobuf/compiler/PluginProtos$CodeGeneratorResponse$File
      32: astore_3
      33: aload         4
      35: athrow
      36: astore        5
      38: jsr           44
      41: aload         5
      43: athrow
      44: astore        6
      46: aload_3
      47: ifnull        56
      50: aload_0
      51: aload_3
      52: invokevirtual #28                 // Method mergeFrom:(Lcom/google/protobuf/compiler/PluginProtos$CodeGeneratorResponse$File;)Lcom/google/protobuf/compiler/PluginProtos$CodeGeneratorResponse$File$Builder;
      55: pop
      56: ret           6
      58: aload_0
      59: areturn
    Exception table:
       from    to  target type
           2    16    22   Class com/google/protobuf/InvalidProtocolBufferException
           2    19    36   any
          22    41    36   any

  public boolean hasName();
    Code:
       0: aload_0
       1: getfield      #17                 // Field bitField0_:I
       4: iconst_1
       5: iand
       6: iconst_1
       7: if_icmpne     14
      10: iconst_1
      11: goto          15
      14: iconst_0
      15: ireturn

  public java.lang.String getName();
    Code:
       0: aload_0
       1: getfield      #10                 // Field name_:Ljava/lang/Object;
       4: astore_1
       5: aload_1
       6: instanceof    #43                 // class java/lang/String
       9: ifne          36
      12: aload_1
      13: checkcast     #44                 // class com/google/protobuf/ByteString
      16: astore_2
      17: aload_2
      18: invokevirtual #45                 // Method com/google/protobuf/ByteString.toStringUtf8:()Ljava/lang/String;
      21: astore_3
      22: aload_2
      23: invokevirtual #46                 // Method com/google/protobuf/ByteString.isValidUtf8:()Z
      26: ifeq          34
      29: aload_0
      30: aload_3
      31: putfield      #10                 // Field name_:Ljava/lang/Object;
      34: aload_3
      35: areturn
      36: aload_1
      37: checkcast     #43                 // class java/lang/String
      40: areturn

  public com.google.protobuf.ByteString getNameBytes();
    Code:
       0: aload_0
       1: getfield      #10                 // Field name_:Ljava/lang/Object;
       4: astore_1
       5: aload_1
       6: instanceof    #43                 // class java/lang/String
       9: ifeq          27
      12: aload_1
      13: checkcast     #43                 // class java/lang/String
      16: invokestatic  #47                 // Method com/google/protobuf/ByteString.copyFromUtf8:(Ljava/lang/String;)Lcom/google/protobuf/ByteString;
      19: astore_2
      20: aload_0
      21: aload_2
      22: putfield      #10                 // Field name_:Ljava/lang/Object;
      25: aload_2
      26: areturn
      27: aload_1
      28: checkcast     #44                 // class com/google/protobuf/ByteString
      31: areturn

  public com.google.protobuf.compiler.PluginProtos$CodeGeneratorResponse$File$Builder setName(java.lang.String);
    Code:
       0: aload_1
       1: ifnonnull     12
       4: new           #48                 // class java/lang/NullPointerException
       7: dup
       8: invokespecial #49                 // Method java/lang/NullPointerException."<init>":()V
      11: athrow
      12: aload_0
      13: dup
      14: getfield      #17                 // Field bitField0_:I
      17: iconst_1
      18: ior
      19: putfield      #17                 // Field bitField0_:I
      22: aload_0
      23: aload_1
      24: putfield      #10                 // Field name_:Ljava/lang/Object;
      27: aload_0
      28: invokevirtual #32                 // Method onChanged:()V
      31: aload_0
      32: areturn

  public com.google.protobuf.compiler.PluginProtos$CodeGeneratorResponse$File$Builder clearName();
    Code:
       0: aload_0
       1: aload_0
       2: getfield      #17                 // Field bitField0_:I
       5: bipush        -2
       7: iand
       8: putfield      #17                 // Field bitField0_:I
      11: aload_0
      12: invokestatic  #18                 // Method com/google/protobuf/compiler/PluginProtos$CodeGeneratorResponse$File.getDefaultInstance:()Lcom/google/protobuf/compiler/PluginProtos$CodeGeneratorResponse$File;
      15: invokevirtual #50                 // Method com/google/protobuf/compiler/PluginProtos$CodeGeneratorResponse$File.getName:()Ljava/lang/String;
      18: putfield      #10                 // Field name_:Ljava/lang/Object;
      21: aload_0
      22: invokevirtual #32                 // Method onChanged:()V
      25: aload_0
      26: areturn

  public com.google.protobuf.compiler.PluginProtos$CodeGeneratorResponse$File$Builder setNameBytes(com.google.protobuf.ByteString);
    Code:
       0: aload_1
       1: ifnonnull     12
       4: new           #48                 // class java/lang/NullPointerException
       7: dup
       8: invokespecial #49                 // Method java/lang/NullPointerException."<init>":()V
      11: athrow
      12: aload_0
      13: dup
      14: getfield      #17                 // Field bitField0_:I
      17: iconst_1
      18: ior
      19: putfield      #17                 // Field bitField0_:I
      22: aload_0
      23: aload_1
      24: putfield      #10                 // Field name_:Ljava/lang/Object;
      27: aload_0
      28: invokevirtual #32                 // Method onChanged:()V
      31: aload_0
      32: areturn

  public boolean hasInsertionPoint();
    Code:
       0: aload_0
       1: getfield      #17                 // Field bitField0_:I
       4: iconst_2
       5: iand
       6: iconst_2
       7: if_icmpne     14
      10: iconst_1
      11: goto          15
      14: iconst_0
      15: ireturn

  public java.lang.String getInsertionPoint();
    Code:
       0: aload_0
       1: getfield      #11                 // Field insertionPoint_:Ljava/lang/Object;
       4: astore_1
       5: aload_1
       6: instanceof    #43                 // class java/lang/String
       9: ifne          36
      12: aload_1
      13: checkcast     #44                 // class com/google/protobuf/ByteString
      16: astore_2
      17: aload_2
      18: invokevirtual #45                 // Method com/google/protobuf/ByteString.toStringUtf8:()Ljava/lang/String;
      21: astore_3
      22: aload_2
      23: invokevirtual #46                 // Method com/google/protobuf/ByteString.isValidUtf8:()Z
      26: ifeq          34
      29: aload_0
      30: aload_3
      31: putfield      #11                 // Field insertionPoint_:Ljava/lang/Object;
      34: aload_3
      35: areturn
      36: aload_1
      37: checkcast     #43                 // class java/lang/String
      40: areturn

  public com.google.protobuf.ByteString getInsertionPointBytes();
    Code:
       0: aload_0
       1: getfield      #11                 // Field insertionPoint_:Ljava/lang/Object;
       4: astore_1
       5: aload_1
       6: instanceof    #43                 // class java/lang/String
       9: ifeq          27
      12: aload_1
      13: checkcast     #43                 // class java/lang/String
      16: invokestatic  #47                 // Method com/google/protobuf/ByteString.copyFromUtf8:(Ljava/lang/String;)Lcom/google/protobuf/ByteString;
      19: astore_2
      20: aload_0
      21: aload_2
      22: putfield      #11                 // Field insertionPoint_:Ljava/lang/Object;
      25: aload_2
      26: areturn
      27: aload_1
      28: checkcast     #44                 // class com/google/protobuf/ByteString
      31: areturn

  public com.google.protobuf.compiler.PluginProtos$CodeGeneratorResponse$File$Builder setInsertionPoint(java.lang.String);
    Code:
       0: aload_1
       1: ifnonnull     12
       4: new           #48                 // class java/lang/NullPointerException
       7: dup
       8: invokespecial #49                 // Method java/lang/NullPointerException."<init>":()V
      11: athrow
      12: aload_0
      13: dup
      14: getfield      #17                 // Field bitField0_:I
      17: iconst_2
      18: ior
      19: putfield      #17                 // Field bitField0_:I
      22: aload_0
      23: aload_1
      24: putfield      #11                 // Field insertionPoint_:Ljava/lang/Object;
      27: aload_0
      28: invokevirtual #32                 // Method onChanged:()V
      31: aload_0
      32: areturn

  public com.google.protobuf.compiler.PluginProtos$CodeGeneratorResponse$File$Builder clearInsertionPoint();
    Code:
       0: aload_0
       1: aload_0
       2: getfield      #17                 // Field bitField0_:I
       5: bipush        -3
       7: iand
       8: putfield      #17                 // Field bitField0_:I
      11: aload_0
      12: invokestatic  #18                 // Method com/google/protobuf/compiler/PluginProtos$CodeGeneratorResponse$File.getDefaultInstance:()Lcom/google/protobuf/compiler/PluginProtos$CodeGeneratorResponse$File;
      15: invokevirtual #51                 // Method com/google/protobuf/compiler/PluginProtos$CodeGeneratorResponse$File.getInsertionPoint:()Ljava/lang/String;
      18: putfield      #11                 // Field insertionPoint_:Ljava/lang/Object;
      21: aload_0
      22: invokevirtual #32                 // Method onChanged:()V
      25: aload_0
      26: areturn

  public com.google.protobuf.compiler.PluginProtos$CodeGeneratorResponse$File$Builder setInsertionPointBytes(com.google.protobuf.ByteString);
    Code:
       0: aload_1
       1: ifnonnull     12
       4: new           #48                 // class java/lang/NullPointerException
       7: dup
       8: invokespecial #49                 // Method java/lang/NullPointerException."<init>":()V
      11: athrow
      12: aload_0
      13: dup
      14: getfield      #17                 // Field bitField0_:I
      17: iconst_2
      18: ior
      19: putfield      #17                 // Field bitField0_:I
      22: aload_0
      23: aload_1
      24: putfield      #11                 // Field insertionPoint_:Ljava/lang/Object;
      27: aload_0
      28: invokevirtual #32                 // Method onChanged:()V
      31: aload_0
      32: areturn

  public boolean hasContent();
    Code:
       0: aload_0
       1: getfield      #17                 // Field bitField0_:I
       4: iconst_4
       5: iand
       6: iconst_4
       7: if_icmpne     14
      10: iconst_1
      11: goto          15
      14: iconst_0
      15: ireturn

  public java.lang.String getContent();
    Code:
       0: aload_0
       1: getfield      #12                 // Field content_:Ljava/lang/Object;
       4: astore_1
       5: aload_1
       6: instanceof    #43                 // class java/lang/String
       9: ifne          36
      12: aload_1
      13: checkcast     #44                 // class com/google/protobuf/ByteString
      16: astore_2
      17: aload_2
      18: invokevirtual #45                 // Method com/google/protobuf/ByteString.toStringUtf8:()Ljava/lang/String;
      21: astore_3
      22: aload_2
      23: invokevirtual #46                 // Method com/google/protobuf/ByteString.isValidUtf8:()Z
      26: ifeq          34
      29: aload_0
      30: aload_3
      31: putfield      #12                 // Field content_:Ljava/lang/Object;
      34: aload_3
      35: areturn
      36: aload_1
      37: checkcast     #43                 // class java/lang/String
      40: areturn

  public com.google.protobuf.ByteString getContentBytes();
    Code:
       0: aload_0
       1: getfield      #12                 // Field content_:Ljava/lang/Object;
       4: astore_1
       5: aload_1
       6: instanceof    #43                 // class java/lang/String
       9: ifeq          27
      12: aload_1
      13: checkcast     #43                 // class java/lang/String
      16: invokestatic  #47                 // Method com/google/protobuf/ByteString.copyFromUtf8:(Ljava/lang/String;)Lcom/google/protobuf/ByteString;
      19: astore_2
      20: aload_0
      21: aload_2
      22: putfield      #12                 // Field content_:Ljava/lang/Object;
      25: aload_2
      26: areturn
      27: aload_1
      28: checkcast     #44                 // class com/google/protobuf/ByteString
      31: areturn

  public com.google.protobuf.compiler.PluginProtos$CodeGeneratorResponse$File$Builder setContent(java.lang.String);
    Code:
       0: aload_1
       1: ifnonnull     12
       4: new           #48                 // class java/lang/NullPointerException
       7: dup
       8: invokespecial #49                 // Method java/lang/NullPointerException."<init>":()V
      11: athrow
      12: aload_0
      13: dup
      14: getfield      #17                 // Field bitField0_:I
      17: iconst_4
      18: ior
      19: putfield      #17                 // Field bitField0_:I
      22: aload_0
      23: aload_1
      24: putfield      #12                 // Field content_:Ljava/lang/Object;
      27: aload_0
      28: invokevirtual #32                 // Method onChanged:()V
      31: aload_0
      32: areturn

  public com.google.protobuf.compiler.PluginProtos$CodeGeneratorResponse$File$Builder clearContent();
    Code:
       0: aload_0
       1: aload_0
       2: getfield      #17                 // Field bitField0_:I
       5: bipush        -5
       7: iand
       8: putfield      #17                 // Field bitField0_:I
      11: aload_0
      12: invokestatic  #18                 // Method com/google/protobuf/compiler/PluginProtos$CodeGeneratorResponse$File.getDefaultInstance:()Lcom/google/protobuf/compiler/PluginProtos$CodeGeneratorResponse$File;
      15: invokevirtual #52                 // Method com/google/protobuf/compiler/PluginProtos$CodeGeneratorResponse$File.getContent:()Ljava/lang/String;
      18: putfield      #12                 // Field content_:Ljava/lang/Object;
      21: aload_0
      22: invokevirtual #32                 // Method onChanged:()V
      25: aload_0
      26: areturn

  public com.google.protobuf.compiler.PluginProtos$CodeGeneratorResponse$File$Builder setContentBytes(com.google.protobuf.ByteString);
    Code:
       0: aload_1
       1: ifnonnull     12
       4: new           #48                 // class java/lang/NullPointerException
       7: dup
       8: invokespecial #49                 // Method java/lang/NullPointerException."<init>":()V
      11: athrow
      12: aload_0
      13: dup
      14: getfield      #17                 // Field bitField0_:I
      17: iconst_4
      18: ior
      19: putfield      #17                 // Field bitField0_:I
      22: aload_0
      23: aload_1
      24: putfield      #12                 // Field content_:Ljava/lang/Object;
      27: aload_0
      28: invokevirtual #32                 // Method onChanged:()V
      31: aload_0
      32: areturn

  public com.google.protobuf.GeneratedMessage$Builder clear();
    Code:
       0: aload_0
       1: invokevirtual #53                 // Method clear:()Lcom/google/protobuf/compiler/PluginProtos$CodeGeneratorResponse$File$Builder;
       4: areturn

  public com.google.protobuf.AbstractMessage$Builder mergeFrom(com.google.protobuf.CodedInputStream, com.google.protobuf.ExtensionRegistryLite) throws java.io.IOException;
    Code:
       0: aload_0
       1: aload_1
       2: aload_2
       3: invokevirtual #54                 // Method mergeFrom:(Lcom/google/protobuf/CodedInputStream;Lcom/google/protobuf/ExtensionRegistryLite;)Lcom/google/protobuf/compiler/PluginProtos$CodeGeneratorResponse$File$Builder;
       6: areturn

  public com.google.protobuf.AbstractMessage$Builder mergeFrom(com.google.protobuf.Message);
    Code:
       0: aload_0
       1: aload_1
       2: invokevirtual #55                 // Method mergeFrom:(Lcom/google/protobuf/Message;)Lcom/google/protobuf/compiler/PluginProtos$CodeGeneratorResponse$File$Builder;
       5: areturn

  public com.google.protobuf.AbstractMessage$Builder clear();
    Code:
       0: aload_0
       1: invokevirtual #53                 // Method clear:()Lcom/google/protobuf/compiler/PluginProtos$CodeGeneratorResponse$File$Builder;
       4: areturn

  public com.google.protobuf.Message$Builder mergeFrom(com.google.protobuf.CodedInputStream, com.google.protobuf.ExtensionRegistryLite) throws java.io.IOException;
    Code:
       0: aload_0
       1: aload_1
       2: aload_2
       3: invokevirtual #54                 // Method mergeFrom:(Lcom/google/protobuf/CodedInputStream;Lcom/google/protobuf/ExtensionRegistryLite;)Lcom/google/protobuf/compiler/PluginProtos$CodeGeneratorResponse$File$Builder;
       6: areturn

  public com.google.protobuf.Message buildPartial();
    Code:
       0: aload_0
       1: invokevirtual #19                 // Method buildPartial:()Lcom/google/protobuf/compiler/PluginProtos$CodeGeneratorResponse$File;
       4: areturn

  public com.google.protobuf.Message build();
    Code:
       0: aload_0
       1: invokevirtual #56                 // Method build:()Lcom/google/protobuf/compiler/PluginProtos$CodeGeneratorResponse$File;
       4: areturn

  public com.google.protobuf.Message$Builder mergeFrom(com.google.protobuf.Message);
    Code:
       0: aload_0
       1: aload_1
       2: invokevirtual #55                 // Method mergeFrom:(Lcom/google/protobuf/Message;)Lcom/google/protobuf/compiler/PluginProtos$CodeGeneratorResponse$File$Builder;
       5: areturn

  public com.google.protobuf.Message$Builder clear();
    Code:
       0: aload_0
       1: invokevirtual #53                 // Method clear:()Lcom/google/protobuf/compiler/PluginProtos$CodeGeneratorResponse$File$Builder;
       4: areturn

  public com.google.protobuf.MessageLite$Builder mergeFrom(com.google.protobuf.CodedInputStream, com.google.protobuf.ExtensionRegistryLite) throws java.io.IOException;
    Code:
       0: aload_0
       1: aload_1
       2: aload_2
       3: invokevirtual #54                 // Method mergeFrom:(Lcom/google/protobuf/CodedInputStream;Lcom/google/protobuf/ExtensionRegistryLite;)Lcom/google/protobuf/compiler/PluginProtos$CodeGeneratorResponse$File$Builder;
       6: areturn

  public com.google.protobuf.MessageLite buildPartial();
    Code:
       0: aload_0
       1: invokevirtual #19                 // Method buildPartial:()Lcom/google/protobuf/compiler/PluginProtos$CodeGeneratorResponse$File;
       4: areturn

  public com.google.protobuf.MessageLite build();
    Code:
       0: aload_0
       1: invokevirtual #56                 // Method build:()Lcom/google/protobuf/compiler/PluginProtos$CodeGeneratorResponse$File;
       4: areturn

  public com.google.protobuf.MessageLite$Builder clear();
    Code:
       0: aload_0
       1: invokevirtual #53                 // Method clear:()Lcom/google/protobuf/compiler/PluginProtos$CodeGeneratorResponse$File$Builder;
       4: areturn

  public com.google.protobuf.MessageLite getDefaultInstanceForType();
    Code:
       0: aload_0
       1: invokevirtual #57                 // Method getDefaultInstanceForType:()Lcom/google/protobuf/compiler/PluginProtos$CodeGeneratorResponse$File;
       4: areturn

  public com.google.protobuf.Message getDefaultInstanceForType();
    Code:
       0: aload_0
       1: invokevirtual #57                 // Method getDefaultInstanceForType:()Lcom/google/protobuf/compiler/PluginProtos$CodeGeneratorResponse$File;
       4: areturn

  public com.google.protobuf.AbstractMessageLite$Builder mergeFrom(com.google.protobuf.CodedInputStream, com.google.protobuf.ExtensionRegistryLite) throws java.io.IOException;
    Code:
       0: aload_0
       1: aload_1
       2: aload_2
       3: invokevirtual #54                 // Method mergeFrom:(Lcom/google/protobuf/CodedInputStream;Lcom/google/protobuf/ExtensionRegistryLite;)Lcom/google/protobuf/compiler/PluginProtos$CodeGeneratorResponse$File$Builder;
       6: areturn

  com.google.protobuf.compiler.PluginProtos$CodeGeneratorResponse$File$Builder(com.google.protobuf.compiler.PluginProtos$1);
    Code:
       0: aload_0
       1: invokespecial #2                  // Method "<init>":()V
       4: return

  com.google.protobuf.compiler.PluginProtos$CodeGeneratorResponse$File$Builder(com.google.protobuf.GeneratedMessage$BuilderParent, com.google.protobuf.compiler.PluginProtos$1);
    Code:
       0: aload_0
       1: aload_1
       2: invokespecial #1                  // Method "<init>":(Lcom/google/protobuf/GeneratedMessage$BuilderParent;)V
       5: return
}
