Compiled from "PathWatcher.java"
public final class org.eclipse.jetty.util.PathWatcher$PathWatchEventType extends java.lang.Enum<org.eclipse.jetty.util.PathWatcher$PathWatchEventType> {
  public static final org.eclipse.jetty.util.PathWatcher$PathWatchEventType ADDED;

  public static final org.eclipse.jetty.util.PathWatcher$PathWatchEventType DELETED;

  public static final org.eclipse.jetty.util.PathWatcher$PathWatchEventType MODIFIED;

  public static final org.eclipse.jetty.util.PathWatcher$PathWatchEventType UNKNOWN;

  private static final org.eclipse.jetty.util.PathWatcher$PathWatchEventType[] $VALUES;

  public static org.eclipse.jetty.util.PathWatcher$PathWatchEventType[] values();
    Code:
       0: getstatic     #1                  // Field $VALUES:[Lorg/eclipse/jetty/util/PathWatcher$PathWatchEventType;
       3: invokevirtual #2                  // Method "[Lorg/eclipse/jetty/util/PathWatcher$PathWatchEventType;".clone:()Ljava/lang/Object;
       6: checkcast     #3                  // class "[Lorg/eclipse/jetty/util/PathWatcher$PathWatchEventType;"
       9: areturn

  public static org.eclipse.jetty.util.PathWatcher$PathWatchEventType valueOf(java.lang.String);
    Code:
       0: ldc           #4                  // class org/eclipse/jetty/util/PathWatcher$PathWatchEventType
       2: aload_0
       3: invokestatic  #5                  // Method java/lang/Enum.valueOf:(Ljava/lang/Class;Ljava/lang/String;)Ljava/lang/Enum;
       6: checkcast     #4                  // class org/eclipse/jetty/util/PathWatcher$PathWatchEventType
       9: areturn

  private org.eclipse.jetty.util.PathWatcher$PathWatchEventType();
    Code:
       0: aload_0
       1: aload_1
       2: iload_2
       3: invokespecial #6                  // Method java/lang/Enum."<init>":(Ljava/lang/String;I)V
       6: return

  static {};
    Code:
       0: new           #4                  // class org/eclipse/jetty/util/PathWatcher$PathWatchEventType
       3: dup
       4: ldc           #7                  // String ADDED
       6: iconst_0
       7: invokespecial #8                  // Method "<init>":(Ljava/lang/String;I)V
      10: putstatic     #9                  // Field ADDED:Lorg/eclipse/jetty/util/PathWatcher$PathWatchEventType;
      13: new           #4                  // class org/eclipse/jetty/util/PathWatcher$PathWatchEventType
      16: dup
      17: ldc           #10                 // String DELETED
      19: iconst_1
      20: invokespecial #8                  // Method "<init>":(Ljava/lang/String;I)V
      23: putstatic     #11                 // Field DELETED:Lorg/eclipse/jetty/util/PathWatcher$PathWatchEventType;
      26: new           #4                  // class org/eclipse/jetty/util/PathWatcher$PathWatchEventType
      29: dup
      30: ldc           #12                 // String MODIFIED
      32: iconst_2
      33: invokespecial #8                  // Method "<init>":(Ljava/lang/String;I)V
      36: putstatic     #13                 // Field MODIFIED:Lorg/eclipse/jetty/util/PathWatcher$PathWatchEventType;
      39: new           #4                  // class org/eclipse/jetty/util/PathWatcher$PathWatchEventType
      42: dup
      43: ldc           #14                 // String UNKNOWN
      45: iconst_3
      46: invokespecial #8                  // Method "<init>":(Ljava/lang/String;I)V
      49: putstatic     #15                 // Field UNKNOWN:Lorg/eclipse/jetty/util/PathWatcher$PathWatchEventType;
      52: iconst_4
      53: anewarray     #4                  // class org/eclipse/jetty/util/PathWatcher$PathWatchEventType
      56: dup
      57: iconst_0
      58: getstatic     #9                  // Field ADDED:Lorg/eclipse/jetty/util/PathWatcher$PathWatchEventType;
      61: aastore
      62: dup
      63: iconst_1
      64: getstatic     #11                 // Field DELETED:Lorg/eclipse/jetty/util/PathWatcher$PathWatchEventType;
      67: aastore
      68: dup
      69: iconst_2
      70: getstatic     #13                 // Field MODIFIED:Lorg/eclipse/jetty/util/PathWatcher$PathWatchEventType;
      73: aastore
      74: dup
      75: iconst_3
      76: getstatic     #15                 // Field UNKNOWN:Lorg/eclipse/jetty/util/PathWatcher$PathWatchEventType;
      79: aastore
      80: putstatic     #1                  // Field $VALUES:[Lorg/eclipse/jetty/util/PathWatcher$PathWatchEventType;
      83: return
}
