Compiled from "InjectedTest.java"
final class org.sonatype.guice.bean.containers.InjectedTest$SetUpModule implements com.google.inject.Module {
  final org.sonatype.guice.bean.containers.InjectedTest this$0;

  org.sonatype.guice.bean.containers.InjectedTest$SetUpModule(org.sonatype.guice.bean.containers.InjectedTest);
    Code:
       0: aload_0
       1: aload_1
       2: putfield      #1                  // Field this$0:Lorg/sonatype/guice/bean/containers/InjectedTest;
       5: aload_0
       6: invokespecial #2                  // Method java/lang/Object."<init>":()V
       9: return

  public void configure(com.google.inject.Binder);
    Code:
       0: aload_1
       1: aload_0
       2: getfield      #1                  // Field this$0:Lorg/sonatype/guice/bean/containers/InjectedTest;
       5: invokeinterface #3,  2            // InterfaceMethod com/google/inject/Binder.install:(Lcom/google/inject/Module;)V
      10: new           #4                  // class java/util/Properties
      13: dup
      14: invokespecial #5                  // Method java/util/Properties."<init>":()V
      17: astore_2
      18: aload_2
      19: ldc           #6                  // String basedir
      21: aload_0
      22: getfield      #1                  // Field this$0:Lorg/sonatype/guice/bean/containers/InjectedTest;
      25: invokevirtual #7                  // Method org/sonatype/guice/bean/containers/InjectedTest.getBasedir:()Ljava/lang/String;
      28: invokevirtual #8                  // Method java/util/Properties.put:(Ljava/lang/Object;Ljava/lang/Object;)Ljava/lang/Object;
      31: pop
      32: aload_0
      33: getfield      #1                  // Field this$0:Lorg/sonatype/guice/bean/containers/InjectedTest;
      36: aload_2
      37: invokevirtual #9                  // Method org/sonatype/guice/bean/containers/InjectedTest.configure:(Ljava/util/Properties;)V
      40: aload_1
      41: getstatic     #10                 // Field org/sonatype/guice/bean/binders/ParameterKeys.PROPERTIES:Lcom/google/inject/Key;
      44: invokeinterface #11,  2           // InterfaceMethod com/google/inject/Binder.bind:(Lcom/google/inject/Key;)Lcom/google/inject/binder/LinkedBindingBuilder;
      49: aload_2
      50: invokeinterface #12,  2           // InterfaceMethod com/google/inject/binder/LinkedBindingBuilder.toInstance:(Ljava/lang/Object;)V
      55: aload_1
      56: aload_0
      57: getfield      #1                  // Field this$0:Lorg/sonatype/guice/bean/containers/InjectedTest;
      60: invokeinterface #13,  2           // InterfaceMethod com/google/inject/Binder.requestInjection:(Ljava/lang/Object;)V
      65: return
}
