Compiled from "SisuGuice.java"
final class org.sonatype.guice.bean.containers.SisuGuice$1 extends org.sonatype.guice.bean.binders.WireModule {
  final org.sonatype.guice.bean.locators.BeanLocator val$locator;

  final java.lang.Object val$that;

  org.sonatype.guice.bean.containers.SisuGuice$1(com.google.inject.Module..., org.sonatype.guice.bean.locators.BeanLocator, java.lang.Object);
    Code:
       0: aload_0
       1: aload_2
       2: putfield      #1                  // Field val$locator:Lorg/sonatype/guice/bean/locators/BeanLocator;
       5: aload_0
       6: aload_3
       7: putfield      #2                  // Field val$that:Ljava/lang/Object;
      10: aload_0
      11: aload_1
      12: invokespecial #3                  // Method org/sonatype/guice/bean/binders/WireModule."<init>":([Lcom/google/inject/Module;)V
      15: return

  public void configure(com.google.inject.Binder);
    Code:
       0: aload_1
       1: ldc_w         #4                  // class org/sonatype/guice/bean/locators/BeanLocator
       4: invokeinterface #5,  2            // InterfaceMethod com/google/inject/Binder.bind:(Ljava/lang/Class;)Lcom/google/inject/binder/AnnotatedBindingBuilder;
       9: aload_0
      10: getfield      #1                  // Field val$locator:Lorg/sonatype/guice/bean/locators/BeanLocator;
      13: invokestatic  #6                  // Method com/google/inject/util/Providers.of:(Ljava/lang/Object;)Lcom/google/inject/Provider;
      16: invokeinterface #7,  2            // InterfaceMethod com/google/inject/binder/AnnotatedBindingBuilder.toProvider:(Lcom/google/inject/Provider;)Lcom/google/inject/binder/ScopedBindingBuilder;
      21: pop
      22: aload_1
      23: aload_0
      24: getfield      #2                  // Field val$that:Ljava/lang/Object;
      27: invokeinterface #8,  2            // InterfaceMethod com/google/inject/Binder.requestInjection:(Ljava/lang/Object;)V
      32: return
}
