Compiled from "HttpMeasureConstants.java"
public final class io.opencensus.contrib.http.util.HttpMeasureConstants {
  private static final java.lang.String UNIT_SIZE_BYTE;

  private static final java.lang.String UNIT_LATENCY_MS;

  public static final io.opencensus.stats.Measure$MeasureLong HTTP_CLIENT_SENT_BYTES;

  public static final io.opencensus.stats.Measure$MeasureLong HTTP_CLIENT_RECEIVED_BYTES;

  public static final io.opencensus.stats.Measure$MeasureDouble HTTP_CLIENT_ROUNDTRIP_LATENCY;

  public static final io.opencensus.stats.Measure$MeasureLong HTTP_SERVER_RECEIVED_BYTES;

  public static final io.opencensus.stats.Measure$MeasureLong HTTP_SERVER_SENT_BYTES;

  public static final io.opencensus.stats.Measure$MeasureDouble HTTP_SERVER_LATENCY;

  public static final io.opencensus.tags.TagKey HTTP_CLIENT_HOST;

  public static final io.opencensus.tags.TagKey HTTP_SERVER_HOST;

  public static final io.opencensus.tags.TagKey HTTP_CLIENT_STATUS;

  public static final io.opencensus.tags.TagKey HTTP_SERVER_STATUS;

  public static final io.opencensus.tags.TagKey HTTP_CLIENT_PATH;

  public static final io.opencensus.tags.TagKey HTTP_SERVER_PATH;

  public static final io.opencensus.tags.TagKey HTTP_CLIENT_METHOD;

  public static final io.opencensus.tags.TagKey HTTP_SERVER_METHOD;

  public static final io.opencensus.tags.TagKey HTTP_SERVER_ROUTE;

  private io.opencensus.contrib.http.util.HttpMeasureConstants();
    Code:
       0: aload_0
       1: invokespecial #1                  // Method java/lang/Object."<init>":()V
       4: return

  static {};
    Code:
       0: ldc           #2                  // String opencensus.io/http/client/sent_bytes
       2: ldc           #3                  // String Client-side total bytes sent in request body (uncompressed)
       4: ldc           #5                  // String By
       6: invokestatic  #6                  // Method io/opencensus/stats/Measure$MeasureLong.create:(Ljava/lang/String;Ljava/lang/String;Ljava/lang/String;)Lio/opencensus/stats/Measure$MeasureLong;
       9: putstatic     #7                  // Field HTTP_CLIENT_SENT_BYTES:Lio/opencensus/stats/Measure$MeasureLong;
      12: ldc           #8                  // String opencensus.io/http/client/received_bytes
      14: ldc           #9                  // String Client-side total bytes received in response bodies (uncompressed)
      16: ldc           #5                  // String By
      18: invokestatic  #6                  // Method io/opencensus/stats/Measure$MeasureLong.create:(Ljava/lang/String;Ljava/lang/String;Ljava/lang/String;)Lio/opencensus/stats/Measure$MeasureLong;
      21: putstatic     #10                 // Field HTTP_CLIENT_RECEIVED_BYTES:Lio/opencensus/stats/Measure$MeasureLong;
      24: ldc           #11                 // String opencensus.io/http/client/roundtrip_latency
      26: ldc           #12                 // String Client-side time between first byte of request headers sent to last byte of response received, or terminal error
      28: ldc           #13                 // String ms
      30: invokestatic  #14                 // Method io/opencensus/stats/Measure$MeasureDouble.create:(Ljava/lang/String;Ljava/lang/String;Ljava/lang/String;)Lio/opencensus/stats/Measure$MeasureDouble;
      33: putstatic     #15                 // Field HTTP_CLIENT_ROUNDTRIP_LATENCY:Lio/opencensus/stats/Measure$MeasureDouble;
      36: ldc           #16                 // String opencensus.io/http/server/received_bytes
      38: ldc           #17                 // String Server-side total bytes received in request body (uncompressed)
      40: ldc           #5                  // String By
      42: invokestatic  #6                  // Method io/opencensus/stats/Measure$MeasureLong.create:(Ljava/lang/String;Ljava/lang/String;Ljava/lang/String;)Lio/opencensus/stats/Measure$MeasureLong;
      45: putstatic     #18                 // Field HTTP_SERVER_RECEIVED_BYTES:Lio/opencensus/stats/Measure$MeasureLong;
      48: ldc           #19                 // String opencensus.io/http/server/sent_bytes
      50: ldc           #20                 // String Server-side total bytes sent in response bodies (uncompressed)
      52: ldc           #5                  // String By
      54: invokestatic  #6                  // Method io/opencensus/stats/Measure$MeasureLong.create:(Ljava/lang/String;Ljava/lang/String;Ljava/lang/String;)Lio/opencensus/stats/Measure$MeasureLong;
      57: putstatic     #21                 // Field HTTP_SERVER_SENT_BYTES:Lio/opencensus/stats/Measure$MeasureLong;
      60: ldc           #22                 // String opencensus.io/http/server/server_latency
      62: ldc           #23                 // String Server-side time between first byte of request headers received to last byte of response sent, or terminal error
      64: ldc           #13                 // String ms
      66: invokestatic  #14                 // Method io/opencensus/stats/Measure$MeasureDouble.create:(Ljava/lang/String;Ljava/lang/String;Ljava/lang/String;)Lio/opencensus/stats/Measure$MeasureDouble;
      69: putstatic     #24                 // Field HTTP_SERVER_LATENCY:Lio/opencensus/stats/Measure$MeasureDouble;
      72: ldc           #25                 // String http_client_host
      74: invokestatic  #26                 // Method io/opencensus/tags/TagKey.create:(Ljava/lang/String;)Lio/opencensus/tags/TagKey;
      77: putstatic     #27                 // Field HTTP_CLIENT_HOST:Lio/opencensus/tags/TagKey;
      80: ldc           #28                 // String http_server_host
      82: invokestatic  #26                 // Method io/opencensus/tags/TagKey.create:(Ljava/lang/String;)Lio/opencensus/tags/TagKey;
      85: putstatic     #29                 // Field HTTP_SERVER_HOST:Lio/opencensus/tags/TagKey;
      88: ldc           #30                 // String http_client_status
      90: invokestatic  #26                 // Method io/opencensus/tags/TagKey.create:(Ljava/lang/String;)Lio/opencensus/tags/TagKey;
      93: putstatic     #31                 // Field HTTP_CLIENT_STATUS:Lio/opencensus/tags/TagKey;
      96: ldc           #32                 // String http_server_status
      98: invokestatic  #26                 // Method io/opencensus/tags/TagKey.create:(Ljava/lang/String;)Lio/opencensus/tags/TagKey;
     101: putstatic     #33                 // Field HTTP_SERVER_STATUS:Lio/opencensus/tags/TagKey;
     104: ldc           #34                 // String http_client_path
     106: invokestatic  #26                 // Method io/opencensus/tags/TagKey.create:(Ljava/lang/String;)Lio/opencensus/tags/TagKey;
     109: putstatic     #35                 // Field HTTP_CLIENT_PATH:Lio/opencensus/tags/TagKey;
     112: ldc           #36                 // String http_server_path
     114: invokestatic  #26                 // Method io/opencensus/tags/TagKey.create:(Ljava/lang/String;)Lio/opencensus/tags/TagKey;
     117: putstatic     #37                 // Field HTTP_SERVER_PATH:Lio/opencensus/tags/TagKey;
     120: ldc           #38                 // String http_client_method
     122: invokestatic  #26                 // Method io/opencensus/tags/TagKey.create:(Ljava/lang/String;)Lio/opencensus/tags/TagKey;
     125: putstatic     #39                 // Field HTTP_CLIENT_METHOD:Lio/opencensus/tags/TagKey;
     128: ldc           #40                 // String http_server_method
     130: invokestatic  #26                 // Method io/opencensus/tags/TagKey.create:(Ljava/lang/String;)Lio/opencensus/tags/TagKey;
     133: putstatic     #41                 // Field HTTP_SERVER_METHOD:Lio/opencensus/tags/TagKey;
     136: ldc           #42                 // String http_server_route
     138: invokestatic  #26                 // Method io/opencensus/tags/TagKey.create:(Ljava/lang/String;)Lio/opencensus/tags/TagKey;
     141: putstatic     #43                 // Field HTTP_SERVER_ROUTE:Lio/opencensus/tags/TagKey;
     144: return
}
