Compiled from "__DatatypeFactory.java"
public final class __redirected.__DatatypeFactory extends javax.xml.datatype.DatatypeFactory {
  private static final java.lang.reflect.Constructor<? extends javax.xml.datatype.DatatypeFactory> PLATFORM_FACTORY;

  private static volatile java.lang.reflect.Constructor<? extends javax.xml.datatype.DatatypeFactory> DEFAULT_FACTORY;

  private final javax.xml.datatype.DatatypeFactory actual;

  public static void changeDefaultFactory(org.jboss.modules.ModuleIdentifier, org.jboss.modules.ModuleLoader);
    Code:
       0: aload_0
       1: ldc           #1                  // class javax/xml/datatype/DatatypeFactory
       3: aload_1
       4: invokestatic  #2                  // Method __redirected/__RedirectedUtils.loadProvider:(Lorg/jboss/modules/ModuleIdentifier;Ljava/lang/Class;Lorg/jboss/modules/ModuleLoader;)Ljava/lang/Class;
       7: astore_2
       8: aload_2
       9: ifnull        46
      12: aload_2
      13: iconst_0
      14: anewarray     #3                  // class java/lang/Class
      17: invokevirtual #4                  // Method java/lang/Class.getConstructor:([Ljava/lang/Class;)Ljava/lang/reflect/Constructor;
      20: putstatic     #5                  // Field DEFAULT_FACTORY:Ljava/lang/reflect/Constructor;
      23: goto          46
      26: astore_3
      27: new           #7                  // class java/lang/NoSuchMethodError
      30: dup
      31: aload_3
      32: invokevirtual #8                  // Method java/lang/NoSuchMethodException.getMessage:()Ljava/lang/String;
      35: invokespecial #9                  // Method java/lang/NoSuchMethodError."<init>":(Ljava/lang/String;)V
      38: aload_3
      39: invokestatic  #10                 // Method __redirected/__RedirectedUtils.wrapped:(Ljava/lang/Throwable;Ljava/lang/Throwable;)Ljava/lang/Throwable;
      42: checkcast     #7                  // class java/lang/NoSuchMethodError
      45: athrow
      46: return
    Exception table:
       from    to  target type
          12    23    26   Class java/lang/NoSuchMethodException

  public static void restorePlatformFactory();
    Code:
       0: getstatic     #11                 // Field PLATFORM_FACTORY:Ljava/lang/reflect/Constructor;
       3: putstatic     #5                  // Field DEFAULT_FACTORY:Ljava/lang/reflect/Constructor;
       6: return

  public static void init();
    Code:
       0: return

  public __redirected.__DatatypeFactory();
    Code:
       0: aload_0
       1: invokespecial #12                 // Method javax/xml/datatype/DatatypeFactory."<init>":()V
       4: getstatic     #5                  // Field DEFAULT_FACTORY:Ljava/lang/reflect/Constructor;
       7: astore_1
       8: invokestatic  #13                 // Method java/lang/Thread.currentThread:()Ljava/lang/Thread;
      11: invokevirtual #14                 // Method java/lang/Thread.getContextClassLoader:()Ljava/lang/ClassLoader;
      14: astore_2
      15: aload_2
      16: ifnull        39
      19: ldc           #1                  // class javax/xml/datatype/DatatypeFactory
      21: aload_2
      22: invokestatic  #15                 // Method __redirected/__RedirectedUtils.loadProvider:(Ljava/lang/Class;Ljava/lang/ClassLoader;)Ljava/lang/Class;
      25: astore_3
      26: aload_3
      27: ifnull        39
      30: aload_3
      31: iconst_0
      32: anewarray     #3                  // class java/lang/Class
      35: invokevirtual #4                  // Method java/lang/Class.getConstructor:([Ljava/lang/Class;)Ljava/lang/reflect/Constructor;
      38: astore_1
      39: aload_0
      40: aload_1
      41: iconst_0
      42: anewarray     #16                 // class java/lang/Object
      45: invokevirtual #17                 // Method java/lang/reflect/Constructor.newInstance:([Ljava/lang/Object;)Ljava/lang/Object;
      48: checkcast     #1                  // class javax/xml/datatype/DatatypeFactory
      51: putfield      #18                 // Field actual:Ljavax/xml/datatype/DatatypeFactory;
      54: goto          123
      57: astore_3
      58: new           #20                 // class java/lang/InstantiationError
      61: dup
      62: aload_3
      63: invokevirtual #21                 // Method java/lang/InstantiationException.getMessage:()Ljava/lang/String;
      66: invokespecial #22                 // Method java/lang/InstantiationError."<init>":(Ljava/lang/String;)V
      69: aload_3
      70: invokestatic  #10                 // Method __redirected/__RedirectedUtils.wrapped:(Ljava/lang/Throwable;Ljava/lang/Throwable;)Ljava/lang/Throwable;
      73: checkcast     #20                 // class java/lang/InstantiationError
      76: athrow
      77: astore_3
      78: new           #24                 // class java/lang/IllegalAccessError
      81: dup
      82: aload_3
      83: invokevirtual #25                 // Method java/lang/IllegalAccessException.getMessage:()Ljava/lang/String;
      86: invokespecial #26                 // Method java/lang/IllegalAccessError."<init>":(Ljava/lang/String;)V
      89: aload_3
      90: invokestatic  #10                 // Method __redirected/__RedirectedUtils.wrapped:(Ljava/lang/Throwable;Ljava/lang/Throwable;)Ljava/lang/Throwable;
      93: checkcast     #24                 // class java/lang/IllegalAccessError
      96: athrow
      97: astore_3
      98: aload_3
      99: invokestatic  #28                 // Method __redirected/__RedirectedUtils.rethrowCause:(Ljava/lang/Throwable;)Ljava/lang/RuntimeException;
     102: athrow
     103: astore_3
     104: new           #7                  // class java/lang/NoSuchMethodError
     107: dup
     108: aload_3
     109: invokevirtual #8                  // Method java/lang/NoSuchMethodException.getMessage:()Ljava/lang/String;
     112: invokespecial #9                  // Method java/lang/NoSuchMethodError."<init>":(Ljava/lang/String;)V
     115: aload_3
     116: invokestatic  #10                 // Method __redirected/__RedirectedUtils.wrapped:(Ljava/lang/Throwable;Ljava/lang/Throwable;)Ljava/lang/Throwable;
     119: checkcast     #7                  // class java/lang/NoSuchMethodError
     122: athrow
     123: return
    Exception table:
       from    to  target type
          15    54    57   Class java/lang/InstantiationException
          15    54    77   Class java/lang/IllegalAccessException
          15    54    97   Class java/lang/reflect/InvocationTargetException
          15    54   103   Class java/lang/NoSuchMethodException

  public javax.xml.datatype.Duration newDuration(java.lang.String);
    Code:
       0: aload_0
       1: getfield      #18                 // Field actual:Ljavax/xml/datatype/DatatypeFactory;
       4: aload_1
       5: invokevirtual #29                 // Method javax/xml/datatype/DatatypeFactory.newDuration:(Ljava/lang/String;)Ljavax/xml/datatype/Duration;
       8: areturn

  public java.lang.String toString();
    Code:
       0: aload_0
       1: getfield      #18                 // Field actual:Ljavax/xml/datatype/DatatypeFactory;
       4: invokevirtual #30                 // Method java/lang/Object.toString:()Ljava/lang/String;
       7: areturn

  public javax.xml.datatype.Duration newDuration(long);
    Code:
       0: aload_0
       1: getfield      #18                 // Field actual:Ljavax/xml/datatype/DatatypeFactory;
       4: lload_1
       5: invokevirtual #31                 // Method javax/xml/datatype/DatatypeFactory.newDuration:(J)Ljavax/xml/datatype/Duration;
       8: areturn

  public javax.xml.datatype.Duration newDuration(boolean, java.math.BigInteger, java.math.BigInteger, java.math.BigInteger, java.math.BigInteger, java.math.BigInteger, java.math.BigDecimal);
    Code:
       0: aload_0
       1: getfield      #18                 // Field actual:Ljavax/xml/datatype/DatatypeFactory;
       4: iload_1
       5: aload_2
       6: aload_3
       7: aload         4
       9: aload         5
      11: aload         6
      13: aload         7
      15: invokevirtual #32                 // Method javax/xml/datatype/DatatypeFactory.newDuration:(ZLjava/math/BigInteger;Ljava/math/BigInteger;Ljava/math/BigInteger;Ljava/math/BigInteger;Ljava/math/BigInteger;Ljava/math/BigDecimal;)Ljavax/xml/datatype/Duration;
      18: areturn

  public javax.xml.datatype.Duration newDuration(boolean, int, int, int, int, int, int);
    Code:
       0: aload_0
       1: getfield      #18                 // Field actual:Ljavax/xml/datatype/DatatypeFactory;
       4: iload_1
       5: iload_2
       6: iload_3
       7: iload         4
       9: iload         5
      11: iload         6
      13: iload         7
      15: invokevirtual #33                 // Method javax/xml/datatype/DatatypeFactory.newDuration:(ZIIIIII)Ljavax/xml/datatype/Duration;
      18: areturn

  public javax.xml.datatype.Duration newDurationDayTime(java.lang.String);
    Code:
       0: aload_0
       1: getfield      #18                 // Field actual:Ljavax/xml/datatype/DatatypeFactory;
       4: aload_1
       5: invokevirtual #34                 // Method javax/xml/datatype/DatatypeFactory.newDurationDayTime:(Ljava/lang/String;)Ljavax/xml/datatype/Duration;
       8: areturn

  public javax.xml.datatype.Duration newDurationDayTime(long);
    Code:
       0: aload_0
       1: getfield      #18                 // Field actual:Ljavax/xml/datatype/DatatypeFactory;
       4: lload_1
       5: invokevirtual #35                 // Method javax/xml/datatype/DatatypeFactory.newDurationDayTime:(J)Ljavax/xml/datatype/Duration;
       8: areturn

  public javax.xml.datatype.Duration newDurationDayTime(boolean, java.math.BigInteger, java.math.BigInteger, java.math.BigInteger, java.math.BigInteger);
    Code:
       0: aload_0
       1: getfield      #18                 // Field actual:Ljavax/xml/datatype/DatatypeFactory;
       4: iload_1
       5: aload_2
       6: aload_3
       7: aload         4
       9: aload         5
      11: invokevirtual #36                 // Method javax/xml/datatype/DatatypeFactory.newDurationDayTime:(ZLjava/math/BigInteger;Ljava/math/BigInteger;Ljava/math/BigInteger;Ljava/math/BigInteger;)Ljavax/xml/datatype/Duration;
      14: areturn

  public javax.xml.datatype.Duration newDurationDayTime(boolean, int, int, int, int);
    Code:
       0: aload_0
       1: getfield      #18                 // Field actual:Ljavax/xml/datatype/DatatypeFactory;
       4: iload_1
       5: iload_2
       6: iload_3
       7: iload         4
       9: iload         5
      11: invokevirtual #37                 // Method javax/xml/datatype/DatatypeFactory.newDurationDayTime:(ZIIII)Ljavax/xml/datatype/Duration;
      14: areturn

  public javax.xml.datatype.Duration newDurationYearMonth(java.lang.String);
    Code:
       0: aload_0
       1: getfield      #18                 // Field actual:Ljavax/xml/datatype/DatatypeFactory;
       4: aload_1
       5: invokevirtual #38                 // Method javax/xml/datatype/DatatypeFactory.newDurationYearMonth:(Ljava/lang/String;)Ljavax/xml/datatype/Duration;
       8: areturn

  public javax.xml.datatype.Duration newDurationYearMonth(long);
    Code:
       0: aload_0
       1: getfield      #18                 // Field actual:Ljavax/xml/datatype/DatatypeFactory;
       4: lload_1
       5: invokevirtual #39                 // Method javax/xml/datatype/DatatypeFactory.newDurationYearMonth:(J)Ljavax/xml/datatype/Duration;
       8: areturn

  public javax.xml.datatype.Duration newDurationYearMonth(boolean, java.math.BigInteger, java.math.BigInteger);
    Code:
       0: aload_0
       1: getfield      #18                 // Field actual:Ljavax/xml/datatype/DatatypeFactory;
       4: iload_1
       5: aload_2
       6: aload_3
       7: invokevirtual #40                 // Method javax/xml/datatype/DatatypeFactory.newDurationYearMonth:(ZLjava/math/BigInteger;Ljava/math/BigInteger;)Ljavax/xml/datatype/Duration;
      10: areturn

  public javax.xml.datatype.Duration newDurationYearMonth(boolean, int, int);
    Code:
       0: aload_0
       1: getfield      #18                 // Field actual:Ljavax/xml/datatype/DatatypeFactory;
       4: iload_1
       5: iload_2
       6: iload_3
       7: invokevirtual #41                 // Method javax/xml/datatype/DatatypeFactory.newDurationYearMonth:(ZII)Ljavax/xml/datatype/Duration;
      10: areturn

  public javax.xml.datatype.XMLGregorianCalendar newXMLGregorianCalendar();
    Code:
       0: aload_0
       1: getfield      #18                 // Field actual:Ljavax/xml/datatype/DatatypeFactory;
       4: invokevirtual #42                 // Method javax/xml/datatype/DatatypeFactory.newXMLGregorianCalendar:()Ljavax/xml/datatype/XMLGregorianCalendar;
       7: areturn

  public javax.xml.datatype.XMLGregorianCalendar newXMLGregorianCalendar(java.lang.String);
    Code:
       0: aload_0
       1: getfield      #18                 // Field actual:Ljavax/xml/datatype/DatatypeFactory;
       4: aload_1
       5: invokevirtual #43                 // Method javax/xml/datatype/DatatypeFactory.newXMLGregorianCalendar:(Ljava/lang/String;)Ljavax/xml/datatype/XMLGregorianCalendar;
       8: areturn

  public javax.xml.datatype.XMLGregorianCalendar newXMLGregorianCalendar(java.util.GregorianCalendar);
    Code:
       0: aload_0
       1: getfield      #18                 // Field actual:Ljavax/xml/datatype/DatatypeFactory;
       4: aload_1
       5: invokevirtual #44                 // Method javax/xml/datatype/DatatypeFactory.newXMLGregorianCalendar:(Ljava/util/GregorianCalendar;)Ljavax/xml/datatype/XMLGregorianCalendar;
       8: areturn

  public javax.xml.datatype.XMLGregorianCalendar newXMLGregorianCalendar(java.math.BigInteger, int, int, int, int, int, java.math.BigDecimal, int);
    Code:
       0: aload_0
       1: getfield      #18                 // Field actual:Ljavax/xml/datatype/DatatypeFactory;
       4: aload_1
       5: iload_2
       6: iload_3
       7: iload         4
       9: iload         5
      11: iload         6
      13: aload         7
      15: iload         8
      17: invokevirtual #45                 // Method javax/xml/datatype/DatatypeFactory.newXMLGregorianCalendar:(Ljava/math/BigInteger;IIIIILjava/math/BigDecimal;I)Ljavax/xml/datatype/XMLGregorianCalendar;
      20: areturn

  public javax.xml.datatype.XMLGregorianCalendar newXMLGregorianCalendar(int, int, int, int, int, int, int, int);
    Code:
       0: aload_0
       1: getfield      #18                 // Field actual:Ljavax/xml/datatype/DatatypeFactory;
       4: iload_1
       5: iload_2
       6: iload_3
       7: iload         4
       9: iload         5
      11: iload         6
      13: iload         7
      15: iload         8
      17: invokevirtual #46                 // Method javax/xml/datatype/DatatypeFactory.newXMLGregorianCalendar:(IIIIIIII)Ljavax/xml/datatype/XMLGregorianCalendar;
      20: areturn

  public javax.xml.datatype.XMLGregorianCalendar newXMLGregorianCalendarDate(int, int, int, int);
    Code:
       0: aload_0
       1: getfield      #18                 // Field actual:Ljavax/xml/datatype/DatatypeFactory;
       4: iload_1
       5: iload_2
       6: iload_3
       7: iload         4
       9: invokevirtual #47                 // Method javax/xml/datatype/DatatypeFactory.newXMLGregorianCalendarDate:(IIII)Ljavax/xml/datatype/XMLGregorianCalendar;
      12: areturn

  public javax.xml.datatype.XMLGregorianCalendar newXMLGregorianCalendarTime(int, int, int, int);
    Code:
       0: aload_0
       1: getfield      #18                 // Field actual:Ljavax/xml/datatype/DatatypeFactory;
       4: iload_1
       5: iload_2
       6: iload_3
       7: iload         4
       9: invokevirtual #48                 // Method javax/xml/datatype/DatatypeFactory.newXMLGregorianCalendarTime:(IIII)Ljavax/xml/datatype/XMLGregorianCalendar;
      12: areturn

  public javax.xml.datatype.XMLGregorianCalendar newXMLGregorianCalendarTime(int, int, int, java.math.BigDecimal, int);
    Code:
       0: aload_0
       1: getfield      #18                 // Field actual:Ljavax/xml/datatype/DatatypeFactory;
       4: iload_1
       5: iload_2
       6: iload_3
       7: aload         4
       9: iload         5
      11: invokevirtual #49                 // Method javax/xml/datatype/DatatypeFactory.newXMLGregorianCalendarTime:(IIILjava/math/BigDecimal;I)Ljavax/xml/datatype/XMLGregorianCalendar;
      14: areturn

  public javax.xml.datatype.XMLGregorianCalendar newXMLGregorianCalendarTime(int, int, int, int, int);
    Code:
       0: aload_0
       1: getfield      #18                 // Field actual:Ljavax/xml/datatype/DatatypeFactory;
       4: iload_1
       5: iload_2
       6: iload_3
       7: iload         4
       9: iload         5
      11: invokevirtual #50                 // Method javax/xml/datatype/DatatypeFactory.newXMLGregorianCalendarTime:(IIIII)Ljavax/xml/datatype/XMLGregorianCalendar;
      14: areturn

  static {};
    Code:
       0: invokestatic  #13                 // Method java/lang/Thread.currentThread:()Ljava/lang/Thread;
       3: astore_0
       4: aload_0
       5: invokevirtual #14                 // Method java/lang/Thread.getContextClassLoader:()Ljava/lang/ClassLoader;
       8: astore_1
       9: aload_0
      10: invokestatic  #51                 // Method java/lang/ClassLoader.getSystemClassLoader:()Ljava/lang/ClassLoader;
      13: invokevirtual #52                 // Method java/lang/Thread.setContextClassLoader:(Ljava/lang/ClassLoader;)V
      16: ldc           #1                  // class javax/xml/datatype/DatatypeFactory
      18: invokevirtual #53                 // Method java/lang/Class.getName:()Ljava/lang/String;
      21: ldc           #54                 // String
      23: invokestatic  #55                 // Method java/lang/System.getProperty:(Ljava/lang/String;Ljava/lang/String;)Ljava/lang/String;
      26: ldc           #56                 // class __redirected/__DatatypeFactory
      28: invokevirtual #53                 // Method java/lang/Class.getName:()Ljava/lang/String;
      31: invokevirtual #57                 // Method java/lang/String.equals:(Ljava/lang/Object;)Z
      34: ifeq          46
      37: ldc           #1                  // class javax/xml/datatype/DatatypeFactory
      39: invokevirtual #53                 // Method java/lang/Class.getName:()Ljava/lang/String;
      42: invokestatic  #58                 // Method java/lang/System.clearProperty:(Ljava/lang/String;)Ljava/lang/String;
      45: pop
      46: invokestatic  #59                 // Method javax/xml/datatype/DatatypeFactory.newInstance:()Ljavax/xml/datatype/DatatypeFactory;
      49: astore_2
      50: aload_2
      51: invokevirtual #60                 // Method java/lang/Object.getClass:()Ljava/lang/Class;
      54: iconst_0
      55: anewarray     #3                  // class java/lang/Class
      58: invokevirtual #4                  // Method java/lang/Class.getConstructor:([Ljava/lang/Class;)Ljava/lang/reflect/Constructor;
      61: dup
      62: putstatic     #11                 // Field PLATFORM_FACTORY:Ljava/lang/reflect/Constructor;
      65: putstatic     #5                  // Field DEFAULT_FACTORY:Ljava/lang/reflect/Constructor;
      68: goto          91
      71: astore_3
      72: new           #7                  // class java/lang/NoSuchMethodError
      75: dup
      76: aload_3
      77: invokevirtual #8                  // Method java/lang/NoSuchMethodException.getMessage:()Ljava/lang/String;
      80: invokespecial #9                  // Method java/lang/NoSuchMethodError."<init>":(Ljava/lang/String;)V
      83: aload_3
      84: invokestatic  #10                 // Method __redirected/__RedirectedUtils.wrapped:(Ljava/lang/Throwable;Ljava/lang/Throwable;)Ljava/lang/Throwable;
      87: checkcast     #7                  // class java/lang/NoSuchMethodError
      90: athrow
      91: ldc           #1                  // class javax/xml/datatype/DatatypeFactory
      93: invokevirtual #53                 // Method java/lang/Class.getName:()Ljava/lang/String;
      96: ldc           #56                 // class __redirected/__DatatypeFactory
      98: invokevirtual #53                 // Method java/lang/Class.getName:()Ljava/lang/String;
     101: invokestatic  #61                 // Method java/lang/System.setProperty:(Ljava/lang/String;Ljava/lang/String;)Ljava/lang/String;
     104: pop
     105: aload_0
     106: aload_1
     107: invokevirtual #52                 // Method java/lang/Thread.setContextClassLoader:(Ljava/lang/ClassLoader;)V
     110: goto          135
     113: astore_2
     114: new           #63                 // class java/lang/IllegalArgumentException
     117: dup
     118: ldc           #64                 // String Problem configuring DatatypeFactory
     120: aload_2
     121: invokespecial #65                 // Method java/lang/IllegalArgumentException."<init>":(Ljava/lang/String;Ljava/lang/Throwable;)V
     124: athrow
     125: astore        4
     127: aload_0
     128: aload_1
     129: invokevirtual #52                 // Method java/lang/Thread.setContextClassLoader:(Ljava/lang/ClassLoader;)V
     132: aload         4
     134: athrow
     135: return
    Exception table:
       from    to  target type
          50    68    71   Class java/lang/NoSuchMethodException
          16   105   113   Class javax/xml/datatype/DatatypeConfigurationException
          16   105   125   any
         113   127   125   any
}
