Compiled from "AutoValue_Bootstrapper_ServerInfo.java"
final class io.grpc.xds.AutoValue_Bootstrapper_ServerInfo extends io.grpc.xds.Bootstrapper$ServerInfo {
  private final java.lang.String target;

  private final io.grpc.ChannelCredentials channelCredentials;

  private final boolean useProtocolV3;

  io.grpc.xds.AutoValue_Bootstrapper_ServerInfo(java.lang.String, io.grpc.ChannelCredentials, boolean);
    Code:
       0: aload_0
       1: invokespecial #19                 // Method io/grpc/xds/Bootstrapper$ServerInfo."<init>":()V
       4: aload_1
       5: ifnonnull     18
       8: new           #21                 // class java/lang/NullPointerException
      11: dup
      12: ldc           #23                 // String Null target
      14: invokespecial #26                 // Method java/lang/NullPointerException."<init>":(Ljava/lang/String;)V
      17: athrow
      18: aload_0
      19: aload_1
      20: putfield      #32                 // Field target:Ljava/lang/String;
      23: aload_2
      24: ifnonnull     37
      27: new           #21                 // class java/lang/NullPointerException
      30: dup
      31: ldc           #34                 // String Null channelCredentials
      33: invokespecial #26                 // Method java/lang/NullPointerException."<init>":(Ljava/lang/String;)V
      36: athrow
      37: aload_0
      38: aload_2
      39: putfield      #36                 // Field channelCredentials:Lio/grpc/ChannelCredentials;
      42: aload_0
      43: iload_3
      44: putfield      #38                 // Field useProtocolV3:Z
      47: return

  java.lang.String target();
    Code:
       0: aload_0
       1: getfield      #32                 // Field target:Ljava/lang/String;
       4: areturn

  io.grpc.ChannelCredentials channelCredentials();
    Code:
       0: aload_0
       1: getfield      #36                 // Field channelCredentials:Lio/grpc/ChannelCredentials;
       4: areturn

  boolean useProtocolV3();
    Code:
       0: aload_0
       1: getfield      #38                 // Field useProtocolV3:Z
       4: ireturn

  public java.lang.String toString();
    Code:
       0: new           #46                 // class java/lang/StringBuilder
       3: dup
       4: invokespecial #47                 // Method java/lang/StringBuilder."<init>":()V
       7: ldc           #49                 // String ServerInfo{target=
       9: invokevirtual #53                 // Method java/lang/StringBuilder.append:(Ljava/lang/String;)Ljava/lang/StringBuilder;
      12: aload_0
      13: getfield      #32                 // Field target:Ljava/lang/String;
      16: invokevirtual #53                 // Method java/lang/StringBuilder.append:(Ljava/lang/String;)Ljava/lang/StringBuilder;
      19: ldc           #55                 // String , channelCredentials=
      21: invokevirtual #53                 // Method java/lang/StringBuilder.append:(Ljava/lang/String;)Ljava/lang/StringBuilder;
      24: aload_0
      25: getfield      #36                 // Field channelCredentials:Lio/grpc/ChannelCredentials;
      28: invokevirtual #58                 // Method java/lang/StringBuilder.append:(Ljava/lang/Object;)Ljava/lang/StringBuilder;
      31: ldc           #60                 // String , useProtocolV3=
      33: invokevirtual #53                 // Method java/lang/StringBuilder.append:(Ljava/lang/String;)Ljava/lang/StringBuilder;
      36: aload_0
      37: getfield      #38                 // Field useProtocolV3:Z
      40: invokevirtual #63                 // Method java/lang/StringBuilder.append:(Z)Ljava/lang/StringBuilder;
      43: ldc           #65                 // String }
      45: invokevirtual #53                 // Method java/lang/StringBuilder.append:(Ljava/lang/String;)Ljava/lang/StringBuilder;
      48: invokevirtual #67                 // Method java/lang/StringBuilder.toString:()Ljava/lang/String;
      51: areturn

  public boolean equals(java.lang.Object);
    Code:
       0: aload_1
       1: aload_0
       2: if_acmpne     7
       5: iconst_1
       6: ireturn
       7: aload_1
       8: instanceof    #4                  // class io/grpc/xds/Bootstrapper$ServerInfo
      11: ifeq          64
      14: aload_1
      15: checkcast     #4                  // class io/grpc/xds/Bootstrapper$ServerInfo
      18: astore_2
      19: aload_0
      20: getfield      #32                 // Field target:Ljava/lang/String;
      23: aload_2
      24: invokevirtual #71                 // Method io/grpc/xds/Bootstrapper$ServerInfo.target:()Ljava/lang/String;
      27: invokevirtual #73                 // Method java/lang/String.equals:(Ljava/lang/Object;)Z
      30: ifeq          62
      33: aload_0
      34: getfield      #36                 // Field channelCredentials:Lio/grpc/ChannelCredentials;
      37: aload_2
      38: invokevirtual #75                 // Method io/grpc/xds/Bootstrapper$ServerInfo.channelCredentials:()Lio/grpc/ChannelCredentials;
      41: invokevirtual #78                 // Method java/lang/Object.equals:(Ljava/lang/Object;)Z
      44: ifeq          62
      47: aload_0
      48: getfield      #38                 // Field useProtocolV3:Z
      51: aload_2
      52: invokevirtual #80                 // Method io/grpc/xds/Bootstrapper$ServerInfo.useProtocolV3:()Z
      55: if_icmpne     62
      58: iconst_1
      59: goto          63
      62: iconst_0
      63: ireturn
      64: iconst_0
      65: ireturn

  public int hashCode();
    Code:
       0: iconst_1
       1: istore_1
       2: iload_1
       3: ldc           #87                 // int 1000003
       5: imul
       6: istore_1
       7: iload_1
       8: aload_0
       9: getfield      #32                 // Field target:Ljava/lang/String;
      12: invokevirtual #89                 // Method java/lang/String.hashCode:()I
      15: ixor
      16: istore_1
      17: iload_1
      18: ldc           #87                 // int 1000003
      20: imul
      21: istore_1
      22: iload_1
      23: aload_0
      24: getfield      #36                 // Field channelCredentials:Lio/grpc/ChannelCredentials;
      27: invokevirtual #90                 // Method java/lang/Object.hashCode:()I
      30: ixor
      31: istore_1
      32: iload_1
      33: ldc           #87                 // int 1000003
      35: imul
      36: istore_1
      37: iload_1
      38: aload_0
      39: getfield      #38                 // Field useProtocolV3:Z
      42: ifeq          51
      45: sipush        1231
      48: goto          54
      51: sipush        1237
      54: ixor
      55: istore_1
      56: iload_1
      57: ireturn
}
