Compiled from "AutoValue_VirtualHost_Route_RouteAction_HashPolicy.java"
final class io.grpc.xds.AutoValue_VirtualHost_Route_RouteAction_HashPolicy extends io.grpc.xds.VirtualHost$Route$RouteAction$HashPolicy {
  private final io.grpc.xds.VirtualHost$Route$RouteAction$HashPolicy$Type type;

  private final boolean isTerminal;

  private final java.lang.String headerName;

  private final com.google.re2j.Pattern regEx;

  private final java.lang.String regExSubstitution;

  io.grpc.xds.AutoValue_VirtualHost_Route_RouteAction_HashPolicy(io.grpc.xds.VirtualHost$Route$RouteAction$HashPolicy$Type, boolean, java.lang.String, com.google.re2j.Pattern, java.lang.String);
    Code:
       0: aload_0
       1: invokespecial #32                 // Method io/grpc/xds/VirtualHost$Route$RouteAction$HashPolicy."<init>":()V
       4: aload_1
       5: ifnonnull     18
       8: new           #34                 // class java/lang/NullPointerException
      11: dup
      12: ldc           #36                 // String Null type
      14: invokespecial #39                 // Method java/lang/NullPointerException."<init>":(Ljava/lang/String;)V
      17: athrow
      18: aload_0
      19: aload_1
      20: putfield      #45                 // Field type:Lio/grpc/xds/VirtualHost$Route$RouteAction$HashPolicy$Type;
      23: aload_0
      24: iload_2
      25: putfield      #47                 // Field isTerminal:Z
      28: aload_0
      29: aload_3
      30: putfield      #49                 // Field headerName:Ljava/lang/String;
      33: aload_0
      34: aload         4
      36: putfield      #51                 // Field regEx:Lcom/google/re2j/Pattern;
      39: aload_0
      40: aload         5
      42: putfield      #53                 // Field regExSubstitution:Ljava/lang/String;
      45: return

  io.grpc.xds.VirtualHost$Route$RouteAction$HashPolicy$Type type();
    Code:
       0: aload_0
       1: getfield      #45                 // Field type:Lio/grpc/xds/VirtualHost$Route$RouteAction$HashPolicy$Type;
       4: areturn

  boolean isTerminal();
    Code:
       0: aload_0
       1: getfield      #47                 // Field isTerminal:Z
       4: ireturn

  java.lang.String headerName();
    Code:
       0: aload_0
       1: getfield      #49                 // Field headerName:Ljava/lang/String;
       4: areturn

  com.google.re2j.Pattern regEx();
    Code:
       0: aload_0
       1: getfield      #51                 // Field regEx:Lcom/google/re2j/Pattern;
       4: areturn

  java.lang.String regExSubstitution();
    Code:
       0: aload_0
       1: getfield      #53                 // Field regExSubstitution:Ljava/lang/String;
       4: areturn

  public java.lang.String toString();
    Code:
       0: new           #62                 // class java/lang/StringBuilder
       3: dup
       4: invokespecial #63                 // Method java/lang/StringBuilder."<init>":()V
       7: ldc           #65                 // String HashPolicy{type=
       9: invokevirtual #69                 // Method java/lang/StringBuilder.append:(Ljava/lang/String;)Ljava/lang/StringBuilder;
      12: aload_0
      13: getfield      #45                 // Field type:Lio/grpc/xds/VirtualHost$Route$RouteAction$HashPolicy$Type;
      16: invokevirtual #72                 // Method java/lang/StringBuilder.append:(Ljava/lang/Object;)Ljava/lang/StringBuilder;
      19: ldc           #74                 // String , isTerminal=
      21: invokevirtual #69                 // Method java/lang/StringBuilder.append:(Ljava/lang/String;)Ljava/lang/StringBuilder;
      24: aload_0
      25: getfield      #47                 // Field isTerminal:Z
      28: invokevirtual #77                 // Method java/lang/StringBuilder.append:(Z)Ljava/lang/StringBuilder;
      31: ldc           #79                 // String , headerName=
      33: invokevirtual #69                 // Method java/lang/StringBuilder.append:(Ljava/lang/String;)Ljava/lang/StringBuilder;
      36: aload_0
      37: getfield      #49                 // Field headerName:Ljava/lang/String;
      40: invokevirtual #69                 // Method java/lang/StringBuilder.append:(Ljava/lang/String;)Ljava/lang/StringBuilder;
      43: ldc           #81                 // String , regEx=
      45: invokevirtual #69                 // Method java/lang/StringBuilder.append:(Ljava/lang/String;)Ljava/lang/StringBuilder;
      48: aload_0
      49: getfield      #51                 // Field regEx:Lcom/google/re2j/Pattern;
      52: invokevirtual #72                 // Method java/lang/StringBuilder.append:(Ljava/lang/Object;)Ljava/lang/StringBuilder;
      55: ldc           #83                 // String , regExSubstitution=
      57: invokevirtual #69                 // Method java/lang/StringBuilder.append:(Ljava/lang/String;)Ljava/lang/StringBuilder;
      60: aload_0
      61: getfield      #53                 // Field regExSubstitution:Ljava/lang/String;
      64: invokevirtual #69                 // Method java/lang/StringBuilder.append:(Ljava/lang/String;)Ljava/lang/StringBuilder;
      67: ldc           #85                 // String }
      69: invokevirtual #69                 // Method java/lang/StringBuilder.append:(Ljava/lang/String;)Ljava/lang/StringBuilder;
      72: invokevirtual #87                 // Method java/lang/StringBuilder.toString:()Ljava/lang/String;
      75: areturn

  public boolean equals(java.lang.Object);
    Code:
       0: aload_1
       1: aload_0
       2: if_acmpne     7
       5: iconst_1
       6: ireturn
       7: aload_1
       8: instanceof    #4                  // class io/grpc/xds/VirtualHost$Route$RouteAction$HashPolicy
      11: ifeq          143
      14: aload_1
      15: checkcast     #4                  // class io/grpc/xds/VirtualHost$Route$RouteAction$HashPolicy
      18: astore_2
      19: aload_0
      20: getfield      #45                 // Field type:Lio/grpc/xds/VirtualHost$Route$RouteAction$HashPolicy$Type;
      23: aload_2
      24: invokevirtual #91                 // Method io/grpc/xds/VirtualHost$Route$RouteAction$HashPolicy.type:()Lio/grpc/xds/VirtualHost$Route$RouteAction$HashPolicy$Type;
      27: invokevirtual #93                 // Method io/grpc/xds/VirtualHost$Route$RouteAction$HashPolicy$Type.equals:(Ljava/lang/Object;)Z
      30: ifeq          141
      33: aload_0
      34: getfield      #47                 // Field isTerminal:Z
      37: aload_2
      38: invokevirtual #95                 // Method io/grpc/xds/VirtualHost$Route$RouteAction$HashPolicy.isTerminal:()Z
      41: if_icmpne     141
      44: aload_0
      45: getfield      #49                 // Field headerName:Ljava/lang/String;
      48: ifnonnull     61
      51: aload_2
      52: invokevirtual #97                 // Method io/grpc/xds/VirtualHost$Route$RouteAction$HashPolicy.headerName:()Ljava/lang/String;
      55: ifnonnull     141
      58: goto          75
      61: aload_0
      62: getfield      #49                 // Field headerName:Ljava/lang/String;
      65: aload_2
      66: invokevirtual #97                 // Method io/grpc/xds/VirtualHost$Route$RouteAction$HashPolicy.headerName:()Ljava/lang/String;
      69: invokevirtual #98                 // Method java/lang/String.equals:(Ljava/lang/Object;)Z
      72: ifeq          141
      75: aload_0
      76: getfield      #51                 // Field regEx:Lcom/google/re2j/Pattern;
      79: ifnonnull     92
      82: aload_2
      83: invokevirtual #100                // Method io/grpc/xds/VirtualHost$Route$RouteAction$HashPolicy.regEx:()Lcom/google/re2j/Pattern;
      86: ifnonnull     141
      89: goto          106
      92: aload_0
      93: getfield      #51                 // Field regEx:Lcom/google/re2j/Pattern;
      96: aload_2
      97: invokevirtual #100                // Method io/grpc/xds/VirtualHost$Route$RouteAction$HashPolicy.regEx:()Lcom/google/re2j/Pattern;
     100: invokevirtual #101                // Method com/google/re2j/Pattern.equals:(Ljava/lang/Object;)Z
     103: ifeq          141
     106: aload_0
     107: getfield      #53                 // Field regExSubstitution:Ljava/lang/String;
     110: ifnonnull     123
     113: aload_2
     114: invokevirtual #103                // Method io/grpc/xds/VirtualHost$Route$RouteAction$HashPolicy.regExSubstitution:()Ljava/lang/String;
     117: ifnonnull     141
     120: goto          137
     123: aload_0
     124: getfield      #53                 // Field regExSubstitution:Ljava/lang/String;
     127: aload_2
     128: invokevirtual #103                // Method io/grpc/xds/VirtualHost$Route$RouteAction$HashPolicy.regExSubstitution:()Ljava/lang/String;
     131: invokevirtual #98                 // Method java/lang/String.equals:(Ljava/lang/Object;)Z
     134: ifeq          141
     137: iconst_1
     138: goto          142
     141: iconst_0
     142: ireturn
     143: iconst_0
     144: ireturn

  public int hashCode();
    Code:
       0: iconst_1
       1: istore_1
       2: iload_1
       3: ldc           #110                // int 1000003
       5: imul
       6: istore_1
       7: iload_1
       8: aload_0
       9: getfield      #45                 // Field type:Lio/grpc/xds/VirtualHost$Route$RouteAction$HashPolicy$Type;
      12: invokevirtual #112                // Method io/grpc/xds/VirtualHost$Route$RouteAction$HashPolicy$Type.hashCode:()I
      15: ixor
      16: istore_1
      17: iload_1
      18: ldc           #110                // int 1000003
      20: imul
      21: istore_1
      22: iload_1
      23: aload_0
      24: getfield      #47                 // Field isTerminal:Z
      27: ifeq          36
      30: sipush        1231
      33: goto          39
      36: sipush        1237
      39: ixor
      40: istore_1
      41: iload_1
      42: ldc           #110                // int 1000003
      44: imul
      45: istore_1
      46: iload_1
      47: aload_0
      48: getfield      #49                 // Field headerName:Ljava/lang/String;
      51: ifnonnull     58
      54: iconst_0
      55: goto          65
      58: aload_0
      59: getfield      #49                 // Field headerName:Ljava/lang/String;
      62: invokevirtual #113                // Method java/lang/String.hashCode:()I
      65: ixor
      66: istore_1
      67: iload_1
      68: ldc           #110                // int 1000003
      70: imul
      71: istore_1
      72: iload_1
      73: aload_0
      74: getfield      #51                 // Field regEx:Lcom/google/re2j/Pattern;
      77: ifnonnull     84
      80: iconst_0
      81: goto          91
      84: aload_0
      85: getfield      #51                 // Field regEx:Lcom/google/re2j/Pattern;
      88: invokevirtual #114                // Method com/google/re2j/Pattern.hashCode:()I
      91: ixor
      92: istore_1
      93: iload_1
      94: ldc           #110                // int 1000003
      96: imul
      97: istore_1
      98: iload_1
      99: aload_0
     100: getfield      #53                 // Field regExSubstitution:Ljava/lang/String;
     103: ifnonnull     110
     106: iconst_0
     107: goto          117
     110: aload_0
     111: getfield      #53                 // Field regExSubstitution:Ljava/lang/String;
     114: invokevirtual #113                // Method java/lang/String.hashCode:()I
     117: ixor
     118: istore_1
     119: iload_1
     120: ireturn
}
