Compiled from "CdsLoadBalancerProvider.java"
final class io.grpc.xds.CdsLoadBalancerProvider$CdsConfig {
  final java.lang.String name;

  io.grpc.xds.CdsLoadBalancerProvider$CdsConfig(java.lang.String);
    Code:
       0: aload_0
       1: invokespecial #20                 // Method java/lang/Object."<init>":()V
       4: aload_1
       5: ifnull        19
       8: aload_1
       9: invokevirtual #26                 // Method java/lang/String.isEmpty:()Z
      12: ifne          19
      15: iconst_1
      16: goto          20
      19: iconst_0
      20: ldc           #28                 // String name is null or empty
      22: invokestatic  #34                 // Method com/google/common/base/Preconditions.checkArgument:(ZLjava/lang/Object;)V
      25: aload_0
      26: aload_1
      27: putfield      #36                 // Field name:Ljava/lang/String;
      30: return

  public java.lang.String toString();
    Code:
       0: aload_0
       1: invokestatic  #44                 // Method com/google/common/base/MoreObjects.toStringHelper:(Ljava/lang/Object;)Lcom/google/common/base/MoreObjects$ToStringHelper;
       4: ldc           #45                 // String name
       6: aload_0
       7: getfield      #36                 // Field name:Ljava/lang/String;
      10: invokevirtual #49                 // Method com/google/common/base/MoreObjects$ToStringHelper.add:(Ljava/lang/String;Ljava/lang/Object;)Lcom/google/common/base/MoreObjects$ToStringHelper;
      13: invokevirtual #51                 // Method com/google/common/base/MoreObjects$ToStringHelper.toString:()Ljava/lang/String;
      16: areturn
}
