Compiled from "ClientXdsClient.java"
final class io.grpc.xds.ClientXdsClient$StructOrError<T> {
  private final java.lang.String errorDetail;

  private final T struct;

  private static <T> io.grpc.xds.ClientXdsClient$StructOrError<T> fromStruct(T);
    Code:
       0: new           #2                  // class io/grpc/xds/ClientXdsClient$StructOrError
       3: dup
       4: aload_0
       5: invokespecial #22                 // Method "<init>":(Ljava/lang/Object;)V
       8: areturn

  private static <T> io.grpc.xds.ClientXdsClient$StructOrError<T> fromError(java.lang.String);
    Code:
       0: new           #2                  // class io/grpc/xds/ClientXdsClient$StructOrError
       3: dup
       4: aload_0
       5: invokespecial #28                 // Method "<init>":(Ljava/lang/String;)V
       8: areturn

  private io.grpc.xds.ClientXdsClient$StructOrError(T);
    Code:
       0: aload_0
       1: invokespecial #32                 // Method java/lang/Object."<init>":()V
       4: aload_0
       5: aload_1
       6: ldc           #33                 // String struct
       8: invokestatic  #39                 // Method com/google/common/base/Preconditions.checkNotNull:(Ljava/lang/Object;Ljava/lang/Object;)Ljava/lang/Object;
      11: putfield      #41                 // Field struct:Ljava/lang/Object;
      14: aload_0
      15: aconst_null
      16: putfield      #43                 // Field errorDetail:Ljava/lang/String;
      19: return

  private io.grpc.xds.ClientXdsClient$StructOrError(java.lang.String);
    Code:
       0: aload_0
       1: invokespecial #32                 // Method java/lang/Object."<init>":()V
       4: aload_0
       5: aconst_null
       6: putfield      #41                 // Field struct:Ljava/lang/Object;
       9: aload_0
      10: aload_1
      11: ldc           #47                 // String errorDetail
      13: invokestatic  #39                 // Method com/google/common/base/Preconditions.checkNotNull:(Ljava/lang/Object;Ljava/lang/Object;)Ljava/lang/Object;
      16: checkcast     #49                 // class java/lang/String
      19: putfield      #43                 // Field errorDetail:Ljava/lang/String;
      22: return

  T getStruct();
    Code:
       0: aload_0
       1: getfield      #41                 // Field struct:Ljava/lang/Object;
       4: areturn

  java.lang.String getErrorDetail();
    Code:
       0: aload_0
       1: getfield      #43                 // Field errorDetail:Ljava/lang/String;
       4: areturn

  static java.lang.Object access$300(io.grpc.xds.ClientXdsClient$StructOrError);
    Code:
       0: aload_0
       1: getfield      #41                 // Field struct:Ljava/lang/Object;
       4: areturn

  static io.grpc.xds.ClientXdsClient$StructOrError access$400(java.lang.String);
    Code:
       0: aload_0
       1: invokestatic  #61                 // Method fromError:(Ljava/lang/String;)Lio/grpc/xds/ClientXdsClient$StructOrError;
       4: areturn

  static io.grpc.xds.ClientXdsClient$StructOrError access$500(java.lang.Object);
    Code:
       0: aload_0
       1: invokestatic  #64                 // Method fromStruct:(Ljava/lang/Object;)Lio/grpc/xds/ClientXdsClient$StructOrError;
       4: areturn

  static java.lang.String access$600(io.grpc.xds.ClientXdsClient$StructOrError);
    Code:
       0: aload_0
       1: getfield      #43                 // Field errorDetail:Ljava/lang/String;
       4: areturn
}
