Compiled from "ClusterResolverLoadBalancer.java"
final class io.grpc.xds.ClusterResolverLoadBalancer$ClusterResolverLbState$EdsClusterState extends io.grpc.xds.ClusterResolverLoadBalancer$ClusterResolverLbState$ClusterState implements io.grpc.xds.XdsClient$EdsResourceWatcher {
  private final java.lang.String edsServiceName;

  final io.grpc.xds.ClusterResolverLoadBalancer$ClusterResolverLbState this$1;

  private io.grpc.xds.ClusterResolverLoadBalancer$ClusterResolverLbState$EdsClusterState(io.grpc.xds.ClusterResolverLoadBalancer$ClusterResolverLbState, java.lang.String, java.lang.String, java.lang.String, java.lang.Long, io.grpc.xds.EnvoyServerProtoData$UpstreamTlsContext);
    Code:
       0: aload_0
       1: aload_1
       2: putfield      #48                 // Field this$1:Lio/grpc/xds/ClusterResolverLoadBalancer$ClusterResolverLbState;
       5: aload_0
       6: aload_1
       7: aload_2
       8: aload         4
      10: aload         5
      12: aload         6
      14: aconst_null
      15: invokespecial #51                 // Method io/grpc/xds/ClusterResolverLoadBalancer$ClusterResolverLbState$ClusterState."<init>":(Lio/grpc/xds/ClusterResolverLoadBalancer$ClusterResolverLbState;Ljava/lang/String;Ljava/lang/String;Ljava/lang/Long;Lio/grpc/xds/EnvoyServerProtoData$UpstreamTlsContext;Lio/grpc/xds/ClusterResolverLoadBalancer$1;)V
      18: aload_0
      19: aload_3
      20: putfield      #53                 // Field edsServiceName:Ljava/lang/String;
      23: return

  void start();
    Code:
       0: aload_0
       1: getfield      #53                 // Field edsServiceName:Ljava/lang/String;
       4: ifnull        14
       7: aload_0
       8: getfield      #53                 // Field edsServiceName:Ljava/lang/String;
      11: goto          18
      14: aload_0
      15: getfield      #65                 // Field name:Ljava/lang/String;
      18: astore_1
      19: aload_0
      20: getfield      #48                 // Field this$1:Lio/grpc/xds/ClusterResolverLoadBalancer$ClusterResolverLbState;
      23: getfield      #71                 // Field io/grpc/xds/ClusterResolverLoadBalancer$ClusterResolverLbState.this$0:Lio/grpc/xds/ClusterResolverLoadBalancer;
      26: invokestatic  #75                 // Method io/grpc/xds/ClusterResolverLoadBalancer.access$200:(Lio/grpc/xds/ClusterResolverLoadBalancer;)Lio/grpc/xds/XdsLogger;
      29: getstatic     #79                 // Field io/grpc/xds/XdsLogger$XdsLogLevel.INFO:Lio/grpc/xds/XdsLogger$XdsLogLevel;
      32: ldc           #81                 // String Start watching EDS resource {0}
      34: iconst_1
      35: anewarray     #83                 // class java/lang/Object
      38: dup
      39: iconst_0
      40: aload_1
      41: aastore
      42: invokevirtual #87                 // Method io/grpc/xds/XdsLogger.log:(Lio/grpc/xds/XdsLogger$XdsLogLevel;Ljava/lang/String;[Ljava/lang/Object;)V
      45: aload_0
      46: getfield      #48                 // Field this$1:Lio/grpc/xds/ClusterResolverLoadBalancer$ClusterResolverLbState;
      49: getfield      #71                 // Field io/grpc/xds/ClusterResolverLoadBalancer$ClusterResolverLbState.this$0:Lio/grpc/xds/ClusterResolverLoadBalancer;
      52: invokestatic  #91                 // Method io/grpc/xds/ClusterResolverLoadBalancer.access$1100:(Lio/grpc/xds/ClusterResolverLoadBalancer;)Lio/grpc/xds/XdsClient;
      55: aload_1
      56: aload_0
      57: invokevirtual #95                 // Method io/grpc/xds/XdsClient.watchEdsResource:(Ljava/lang/String;Lio/grpc/xds/XdsClient$EdsResourceWatcher;)V
      60: return

  protected void shutdown();
    Code:
       0: aload_0
       1: invokespecial #99                 // Method io/grpc/xds/ClusterResolverLoadBalancer$ClusterResolverLbState$ClusterState.shutdown:()V
       4: aload_0
       5: getfield      #53                 // Field edsServiceName:Ljava/lang/String;
       8: ifnull        18
      11: aload_0
      12: getfield      #53                 // Field edsServiceName:Ljava/lang/String;
      15: goto          22
      18: aload_0
      19: getfield      #65                 // Field name:Ljava/lang/String;
      22: astore_1
      23: aload_0
      24: getfield      #48                 // Field this$1:Lio/grpc/xds/ClusterResolverLoadBalancer$ClusterResolverLbState;
      27: getfield      #71                 // Field io/grpc/xds/ClusterResolverLoadBalancer$ClusterResolverLbState.this$0:Lio/grpc/xds/ClusterResolverLoadBalancer;
      30: invokestatic  #75                 // Method io/grpc/xds/ClusterResolverLoadBalancer.access$200:(Lio/grpc/xds/ClusterResolverLoadBalancer;)Lio/grpc/xds/XdsLogger;
      33: getstatic     #79                 // Field io/grpc/xds/XdsLogger$XdsLogLevel.INFO:Lio/grpc/xds/XdsLogger$XdsLogLevel;
      36: ldc           #101                // String Stop watching EDS resource {0}
      38: iconst_1
      39: anewarray     #83                 // class java/lang/Object
      42: dup
      43: iconst_0
      44: aload_1
      45: aastore
      46: invokevirtual #87                 // Method io/grpc/xds/XdsLogger.log:(Lio/grpc/xds/XdsLogger$XdsLogLevel;Ljava/lang/String;[Ljava/lang/Object;)V
      49: aload_0
      50: getfield      #48                 // Field this$1:Lio/grpc/xds/ClusterResolverLoadBalancer$ClusterResolverLbState;
      53: getfield      #71                 // Field io/grpc/xds/ClusterResolverLoadBalancer$ClusterResolverLbState.this$0:Lio/grpc/xds/ClusterResolverLoadBalancer;
      56: invokestatic  #91                 // Method io/grpc/xds/ClusterResolverLoadBalancer.access$1100:(Lio/grpc/xds/ClusterResolverLoadBalancer;)Lio/grpc/xds/XdsClient;
      59: aload_1
      60: aload_0
      61: invokevirtual #104                // Method io/grpc/xds/XdsClient.cancelEdsResourceWatch:(Ljava/lang/String;Lio/grpc/xds/XdsClient$EdsResourceWatcher;)V
      64: return

  public void onChanged(io.grpc.xds.XdsClient$EdsUpdate);
    Code:
       0: aload_0
       1: getfield      #48                 // Field this$1:Lio/grpc/xds/ClusterResolverLoadBalancer$ClusterResolverLbState;
       4: getfield      #71                 // Field io/grpc/xds/ClusterResolverLoadBalancer$ClusterResolverLbState.this$0:Lio/grpc/xds/ClusterResolverLoadBalancer;
       7: invokestatic  #110                // Method io/grpc/xds/ClusterResolverLoadBalancer.access$1800:(Lio/grpc/xds/ClusterResolverLoadBalancer;)Lio/grpc/SynchronizationContext;
      10: new           #19                 // class io/grpc/xds/ClusterResolverLoadBalancer$ClusterResolverLbState$EdsClusterState$1EndpointsUpdated
      13: dup
      14: aload_0
      15: aload_1
      16: invokespecial #113                // Method io/grpc/xds/ClusterResolverLoadBalancer$ClusterResolverLbState$EdsClusterState$1EndpointsUpdated."<init>":(Lio/grpc/xds/ClusterResolverLoadBalancer$ClusterResolverLbState$EdsClusterState;Lio/grpc/xds/XdsClient$EdsUpdate;)V
      19: invokevirtual #119                // Method io/grpc/SynchronizationContext.execute:(Ljava/lang/Runnable;)V
      22: return

  public void onResourceDoesNotExist(java.lang.String);
    Code:
       0: aload_0
       1: getfield      #48                 // Field this$1:Lio/grpc/xds/ClusterResolverLoadBalancer$ClusterResolverLbState;
       4: getfield      #71                 // Field io/grpc/xds/ClusterResolverLoadBalancer$ClusterResolverLbState.this$0:Lio/grpc/xds/ClusterResolverLoadBalancer;
       7: invokestatic  #110                // Method io/grpc/xds/ClusterResolverLoadBalancer.access$1800:(Lio/grpc/xds/ClusterResolverLoadBalancer;)Lio/grpc/SynchronizationContext;
      10: new           #17                 // class io/grpc/xds/ClusterResolverLoadBalancer$ClusterResolverLbState$EdsClusterState$1
      13: dup
      14: aload_0
      15: aload_1
      16: invokespecial #126                // Method io/grpc/xds/ClusterResolverLoadBalancer$ClusterResolverLbState$EdsClusterState$1."<init>":(Lio/grpc/xds/ClusterResolverLoadBalancer$ClusterResolverLbState$EdsClusterState;Ljava/lang/String;)V
      19: invokevirtual #119                // Method io/grpc/SynchronizationContext.execute:(Ljava/lang/Runnable;)V
      22: return

  public void onError(io.grpc.Status);
    Code:
       0: aload_0
       1: getfield      #48                 // Field this$1:Lio/grpc/xds/ClusterResolverLoadBalancer$ClusterResolverLbState;
       4: getfield      #71                 // Field io/grpc/xds/ClusterResolverLoadBalancer$ClusterResolverLbState.this$0:Lio/grpc/xds/ClusterResolverLoadBalancer;
       7: invokestatic  #110                // Method io/grpc/xds/ClusterResolverLoadBalancer.access$1800:(Lio/grpc/xds/ClusterResolverLoadBalancer;)Lio/grpc/SynchronizationContext;
      10: new           #15                 // class io/grpc/xds/ClusterResolverLoadBalancer$ClusterResolverLbState$EdsClusterState$2
      13: dup
      14: aload_0
      15: aload_1
      16: invokespecial #131                // Method io/grpc/xds/ClusterResolverLoadBalancer$ClusterResolverLbState$EdsClusterState$2."<init>":(Lio/grpc/xds/ClusterResolverLoadBalancer$ClusterResolverLbState$EdsClusterState;Lio/grpc/Status;)V
      19: invokevirtual #119                // Method io/grpc/SynchronizationContext.execute:(Ljava/lang/Runnable;)V
      22: return

  io.grpc.xds.ClusterResolverLoadBalancer$ClusterResolverLbState$EdsClusterState(io.grpc.xds.ClusterResolverLoadBalancer$ClusterResolverLbState, java.lang.String, java.lang.String, java.lang.String, java.lang.Long, io.grpc.xds.EnvoyServerProtoData$UpstreamTlsContext, io.grpc.xds.ClusterResolverLoadBalancer$1);
    Code:
       0: aload_0
       1: aload_1
       2: aload_2
       3: aload_3
       4: aload         4
       6: aload         5
       8: aload         6
      10: invokespecial #136                // Method "<init>":(Lio/grpc/xds/ClusterResolverLoadBalancer$ClusterResolverLbState;Ljava/lang/String;Ljava/lang/String;Ljava/lang/String;Ljava/lang/Long;Lio/grpc/xds/EnvoyServerProtoData$UpstreamTlsContext;)V
      13: return

  static java.lang.String access$1400(io.grpc.xds.ClusterResolverLoadBalancer$ClusterResolverLbState$EdsClusterState);
    Code:
       0: aload_0
       1: getfield      #53                 // Field edsServiceName:Ljava/lang/String;
       4: areturn
}
