Compiled from "FilterChainMatchingProtocolNegotiators.java"
class io.grpc.xds.FilterChainMatchingProtocolNegotiators$FilterChainSelectorManagerDeregister implements io.grpc.netty.shaded.io.netty.channel.ChannelFutureListener {
  private final io.grpc.xds.FilterChainSelectorManager filterChainSelectorManager;

  private final io.grpc.xds.FilterChainSelectorManager$Closer closer;

  public io.grpc.xds.FilterChainMatchingProtocolNegotiators$FilterChainSelectorManagerDeregister(io.grpc.xds.FilterChainSelectorManager, io.grpc.xds.FilterChainSelectorManager$Closer);
    Code:
       0: aload_0
       1: invokespecial #24                 // Method java/lang/Object."<init>":()V
       4: aload_0
       5: aload_1
       6: ldc           #25                 // String filterChainSelectorManager
       8: invokestatic  #31                 // Method com/google/common/base/Preconditions.checkNotNull:(Ljava/lang/Object;Ljava/lang/Object;)Ljava/lang/Object;
      11: checkcast     #11                 // class io/grpc/xds/FilterChainSelectorManager
      14: putfield      #33                 // Field filterChainSelectorManager:Lio/grpc/xds/FilterChainSelectorManager;
      17: aload_0
      18: aload_2
      19: ldc           #34                 // String closer
      21: invokestatic  #31                 // Method com/google/common/base/Preconditions.checkNotNull:(Ljava/lang/Object;Ljava/lang/Object;)Ljava/lang/Object;
      24: checkcast     #9                  // class io/grpc/xds/FilterChainSelectorManager$Closer
      27: putfield      #36                 // Field closer:Lio/grpc/xds/FilterChainSelectorManager$Closer;
      30: return

  public void operationComplete(io.grpc.netty.shaded.io.netty.channel.ChannelFuture) throws java.lang.Exception;
    Code:
       0: aload_0
       1: getfield      #33                 // Field filterChainSelectorManager:Lio/grpc/xds/FilterChainSelectorManager;
       4: aload_0
       5: getfield      #36                 // Field closer:Lio/grpc/xds/FilterChainSelectorManager$Closer;
       8: invokevirtual #46                 // Method io/grpc/xds/FilterChainSelectorManager.deregister:(Lio/grpc/xds/FilterChainSelectorManager$Closer;)V
      11: return

  public void operationComplete(io.grpc.netty.shaded.io.netty.util.concurrent.Future) throws java.lang.Exception;
    Code:
       0: aload_0
       1: aload_1
       2: checkcast     #51                 // class io/grpc/netty/shaded/io/netty/channel/ChannelFuture
       5: invokevirtual #53                 // Method operationComplete:(Lio/grpc/netty/shaded/io/netty/channel/ChannelFuture;)V
       8: return
}
