Compiled from "RbacFilter.java"
final class io.grpc.xds.RbacFilter implements io.grpc.xds.Filter,io.grpc.xds.Filter$ServerInterceptorBuilder {
  private static final java.util.logging.Logger logger;

  static final io.grpc.xds.RbacFilter INSTANCE;

  static final java.lang.String TYPE_URL;

  private static final java.lang.String TYPE_URL_OVERRIDE_CONFIG;

  io.grpc.xds.RbacFilter();
    Code:
       0: aload_0
       1: invokespecial #127                // Method java/lang/Object."<init>":()V
       4: return

  public java.lang.String[] typeUrls();
    Code:
       0: iconst_2
       1: anewarray     #132                // class java/lang/String
       4: dup
       5: iconst_0
       6: ldc           #120                // String type.googleapis.com/envoy.extensions.filters.http.rbac.v3.RBAC
       8: aastore
       9: dup
      10: iconst_1
      11: ldc           #123                // String type.googleapis.com/envoy.extensions.filters.http.rbac.v3.RBACPerRoute
      13: aastore
      14: areturn

  public io.grpc.xds.Filter$ConfigOrError<io.grpc.xds.RbacConfig> parseFilterConfig(com.google.protobuf.Message);
    Code:
       0: aload_1
       1: instanceof    #139                // class com/google/protobuf/Any
       4: ifne          33
       7: new           #141                // class java/lang/StringBuilder
      10: dup
      11: invokespecial #142                // Method java/lang/StringBuilder."<init>":()V
      14: ldc           #144                // String Invalid config type:
      16: invokevirtual #148                // Method java/lang/StringBuilder.append:(Ljava/lang/String;)Ljava/lang/StringBuilder;
      19: aload_1
      20: invokevirtual #152                // Method java/lang/Object.getClass:()Ljava/lang/Class;
      23: invokevirtual #155                // Method java/lang/StringBuilder.append:(Ljava/lang/Object;)Ljava/lang/StringBuilder;
      26: invokevirtual #159                // Method java/lang/StringBuilder.toString:()Ljava/lang/String;
      29: invokestatic  #163                // Method io/grpc/xds/Filter$ConfigOrError.fromError:(Ljava/lang/String;)Lio/grpc/xds/Filter$ConfigOrError;
      32: areturn
      33: aload_1
      34: checkcast     #139                // class com/google/protobuf/Any
      37: astore_3
      38: aload_3
      39: ldc           #165                // class io/grpc/xds/shaded/io/envoyproxy/envoy/extensions/filters/http/rbac/v3/RBAC
      41: invokevirtual #169                // Method com/google/protobuf/Any.unpack:(Ljava/lang/Class;)Lcom/google/protobuf/Message;
      44: checkcast     #165                // class io/grpc/xds/shaded/io/envoyproxy/envoy/extensions/filters/http/rbac/v3/RBAC
      47: astore_2
      48: goto          77
      51: astore        4
      53: new           #141                // class java/lang/StringBuilder
      56: dup
      57: invokespecial #142                // Method java/lang/StringBuilder."<init>":()V
      60: ldc           #173                // String Invalid proto:
      62: invokevirtual #148                // Method java/lang/StringBuilder.append:(Ljava/lang/String;)Ljava/lang/StringBuilder;
      65: aload         4
      67: invokevirtual #155                // Method java/lang/StringBuilder.append:(Ljava/lang/Object;)Ljava/lang/StringBuilder;
      70: invokevirtual #159                // Method java/lang/StringBuilder.toString:()Ljava/lang/String;
      73: invokestatic  #163                // Method io/grpc/xds/Filter$ConfigOrError.fromError:(Ljava/lang/String;)Lio/grpc/xds/Filter$ConfigOrError;
      76: areturn
      77: aload_2
      78: invokestatic  #177                // Method parseRbacConfig:(Lio/grpc/xds/shaded/io/envoyproxy/envoy/extensions/filters/http/rbac/v3/RBAC;)Lio/grpc/xds/Filter$ConfigOrError;
      81: areturn
    Exception table:
       from    to  target type
          38    48    51   Class com/google/protobuf/InvalidProtocolBufferException

  static io.grpc.xds.Filter$ConfigOrError<io.grpc.xds.RbacConfig> parseRbacConfig(io.grpc.xds.shaded.io.envoyproxy.envoy.extensions.filters.http.rbac.v3.RBAC);
    Code:
       0: aload_0
       1: invokevirtual #193                // Method io/grpc/xds/shaded/io/envoyproxy/envoy/extensions/filters/http/rbac/v3/RBAC.hasRules:()Z
       4: ifne          15
       7: aconst_null
       8: invokestatic  #199                // Method io/grpc/xds/RbacConfig.create:(Lio/grpc/xds/internal/rbac/engine/GrpcAuthorizationEngine$AuthConfig;)Lio/grpc/xds/RbacConfig;
      11: invokestatic  #203                // Method io/grpc/xds/Filter$ConfigOrError.fromConfig:(Ljava/lang/Object;)Lio/grpc/xds/Filter$ConfigOrError;
      14: areturn
      15: aload_0
      16: invokevirtual #207                // Method io/grpc/xds/shaded/io/envoyproxy/envoy/extensions/filters/http/rbac/v3/RBAC.getRules:()Lio/grpc/xds/shaded/io/envoyproxy/envoy/config/rbac/v3/RBAC;
      19: astore_1
      20: getstatic     #211                // Field io/grpc/xds/RbacFilter$2.$SwitchMap$io$envoyproxy$envoy$config$rbac$v3$RBAC$Action:[I
      23: aload_1
      24: invokevirtual #215                // Method io/grpc/xds/shaded/io/envoyproxy/envoy/config/rbac/v3/RBAC.getAction:()Lio/grpc/xds/shaded/io/envoyproxy/envoy/config/rbac/v3/RBAC$Action;
      27: invokevirtual #219                // Method io/grpc/xds/shaded/io/envoyproxy/envoy/config/rbac/v3/RBAC$Action.ordinal:()I
      30: iaload
      31: tableswitch   { // 1 to 4
                     1: 60
                     2: 67
                     3: 74
                     4: 82
               default: 82
          }
      60: getstatic     #223                // Field io/grpc/xds/internal/rbac/engine/GrpcAuthorizationEngine$Action.ALLOW:Lio/grpc/xds/internal/rbac/engine/GrpcAuthorizationEngine$Action;
      63: astore_2
      64: goto          108
      67: getstatic     #226                // Field io/grpc/xds/internal/rbac/engine/GrpcAuthorizationEngine$Action.DENY:Lio/grpc/xds/internal/rbac/engine/GrpcAuthorizationEngine$Action;
      70: astore_2
      71: goto          108
      74: aconst_null
      75: invokestatic  #199                // Method io/grpc/xds/RbacConfig.create:(Lio/grpc/xds/internal/rbac/engine/GrpcAuthorizationEngine$AuthConfig;)Lio/grpc/xds/RbacConfig;
      78: invokestatic  #203                // Method io/grpc/xds/Filter$ConfigOrError.fromConfig:(Ljava/lang/Object;)Lio/grpc/xds/Filter$ConfigOrError;
      81: areturn
      82: new           #141                // class java/lang/StringBuilder
      85: dup
      86: invokespecial #142                // Method java/lang/StringBuilder."<init>":()V
      89: ldc           #228                // String Unknown rbacConfig action type:
      91: invokevirtual #148                // Method java/lang/StringBuilder.append:(Ljava/lang/String;)Ljava/lang/StringBuilder;
      94: aload_1
      95: invokevirtual #215                // Method io/grpc/xds/shaded/io/envoyproxy/envoy/config/rbac/v3/RBAC.getAction:()Lio/grpc/xds/shaded/io/envoyproxy/envoy/config/rbac/v3/RBAC$Action;
      98: invokevirtual #155                // Method java/lang/StringBuilder.append:(Ljava/lang/Object;)Ljava/lang/StringBuilder;
     101: invokevirtual #159                // Method java/lang/StringBuilder.toString:()Ljava/lang/String;
     104: invokestatic  #163                // Method io/grpc/xds/Filter$ConfigOrError.fromError:(Ljava/lang/String;)Lio/grpc/xds/Filter$ConfigOrError;
     107: areturn
     108: aload_1
     109: invokevirtual #232                // Method io/grpc/xds/shaded/io/envoyproxy/envoy/config/rbac/v3/RBAC.getPoliciesMap:()Ljava/util/Map;
     112: astore_3
     113: new           #234                // class java/util/ArrayList
     116: dup
     117: invokespecial #235                // Method java/util/ArrayList."<init>":()V
     120: astore        4
     122: aload_3
     123: invokeinterface #239,  1          // InterfaceMethod java/util/Map.entrySet:()Ljava/util/Set;
     128: invokeinterface #245,  1          // InterfaceMethod java/util/Set.iterator:()Ljava/util/Iterator;
     133: astore        5
     135: aload         5
     137: invokeinterface #252,  1          // InterfaceMethod java/util/Iterator.hasNext:()Z
     142: ifeq          288
     145: aload         5
     147: invokeinterface #256,  1          // InterfaceMethod java/util/Iterator.next:()Ljava/lang/Object;
     152: checkcast     #23                 // class java/util/Map$Entry
     155: astore        6
     157: aload         6
     159: invokeinterface #259,  1          // InterfaceMethod java/util/Map$Entry.getValue:()Ljava/lang/Object;
     164: checkcast     #261                // class io/grpc/xds/shaded/io/envoyproxy/envoy/config/rbac/v3/Policy
     167: astore        7
     169: aload         7
     171: invokevirtual #264                // Method io/grpc/xds/shaded/io/envoyproxy/envoy/config/rbac/v3/Policy.hasCondition:()Z
     174: ifne          185
     177: aload         7
     179: invokevirtual #267                // Method io/grpc/xds/shaded/io/envoyproxy/envoy/config/rbac/v3/Policy.hasCheckedCondition:()Z
     182: ifeq          218
     185: new           #141                // class java/lang/StringBuilder
     188: dup
     189: invokespecial #142                // Method java/lang/StringBuilder."<init>":()V
     192: ldc_w         #269                // String Policy.condition and Policy.checked_condition must not set:
     195: invokevirtual #148                // Method java/lang/StringBuilder.append:(Ljava/lang/String;)Ljava/lang/StringBuilder;
     198: aload         6
     200: invokeinterface #272,  1          // InterfaceMethod java/util/Map$Entry.getKey:()Ljava/lang/Object;
     205: checkcast     #132                // class java/lang/String
     208: invokevirtual #148                // Method java/lang/StringBuilder.append:(Ljava/lang/String;)Ljava/lang/StringBuilder;
     211: invokevirtual #159                // Method java/lang/StringBuilder.toString:()Ljava/lang/String;
     214: invokestatic  #163                // Method io/grpc/xds/Filter$ConfigOrError.fromError:(Ljava/lang/String;)Lio/grpc/xds/Filter$ConfigOrError;
     217: areturn
     218: aload         4
     220: aload         6
     222: invokeinterface #272,  1          // InterfaceMethod java/util/Map$Entry.getKey:()Ljava/lang/Object;
     227: checkcast     #132                // class java/lang/String
     230: aload         7
     232: invokevirtual #276                // Method io/grpc/xds/shaded/io/envoyproxy/envoy/config/rbac/v3/Policy.getPermissionsList:()Ljava/util/List;
     235: invokestatic  #280                // Method parsePermissionList:(Ljava/util/List;)Lio/grpc/xds/internal/rbac/engine/GrpcAuthorizationEngine$OrMatcher;
     238: aload         7
     240: invokevirtual #283                // Method io/grpc/xds/shaded/io/envoyproxy/envoy/config/rbac/v3/Policy.getPrincipalsList:()Ljava/util/List;
     243: invokestatic  #286                // Method parsePrincipalList:(Ljava/util/List;)Lio/grpc/xds/internal/rbac/engine/GrpcAuthorizationEngine$OrMatcher;
     246: invokestatic  #289                // Method io/grpc/xds/internal/rbac/engine/GrpcAuthorizationEngine$PolicyMatcher.create:(Ljava/lang/String;Lio/grpc/xds/internal/rbac/engine/GrpcAuthorizationEngine$OrMatcher;Lio/grpc/xds/internal/rbac/engine/GrpcAuthorizationEngine$OrMatcher;)Lio/grpc/xds/internal/rbac/engine/GrpcAuthorizationEngine$PolicyMatcher;
     249: invokeinterface #293,  2          // InterfaceMethod java/util/List.add:(Ljava/lang/Object;)Z
     254: pop
     255: goto          285
     258: astore        7
     260: new           #141                // class java/lang/StringBuilder
     263: dup
     264: invokespecial #142                // Method java/lang/StringBuilder."<init>":()V
     267: ldc_w         #295                // String Encountered error parsing policy:
     270: invokevirtual #148                // Method java/lang/StringBuilder.append:(Ljava/lang/String;)Ljava/lang/StringBuilder;
     273: aload         7
     275: invokevirtual #155                // Method java/lang/StringBuilder.append:(Ljava/lang/Object;)Ljava/lang/StringBuilder;
     278: invokevirtual #159                // Method java/lang/StringBuilder.toString:()Ljava/lang/String;
     281: invokestatic  #163                // Method io/grpc/xds/Filter$ConfigOrError.fromError:(Ljava/lang/String;)Lio/grpc/xds/Filter$ConfigOrError;
     284: areturn
     285: goto          135
     288: aload         4
     290: aload_2
     291: invokestatic  #298                // Method io/grpc/xds/internal/rbac/engine/GrpcAuthorizationEngine$AuthConfig.create:(Ljava/util/List;Lio/grpc/xds/internal/rbac/engine/GrpcAuthorizationEngine$Action;)Lio/grpc/xds/internal/rbac/engine/GrpcAuthorizationEngine$AuthConfig;
     294: invokestatic  #199                // Method io/grpc/xds/RbacConfig.create:(Lio/grpc/xds/internal/rbac/engine/GrpcAuthorizationEngine$AuthConfig;)Lio/grpc/xds/RbacConfig;
     297: invokestatic  #203                // Method io/grpc/xds/Filter$ConfigOrError.fromConfig:(Ljava/lang/Object;)Lio/grpc/xds/Filter$ConfigOrError;
     300: areturn
    Exception table:
       from    to  target type
         157   217   258   Class java/lang/Exception
         218   255   258   Class java/lang/Exception

  public io.grpc.xds.Filter$ConfigOrError<io.grpc.xds.RbacConfig> parseFilterConfigOverride(com.google.protobuf.Message);
    Code:
       0: aload_1
       1: instanceof    #139                // class com/google/protobuf/Any
       4: ifne          33
       7: new           #141                // class java/lang/StringBuilder
      10: dup
      11: invokespecial #142                // Method java/lang/StringBuilder."<init>":()V
      14: ldc           #144                // String Invalid config type:
      16: invokevirtual #148                // Method java/lang/StringBuilder.append:(Ljava/lang/String;)Ljava/lang/StringBuilder;
      19: aload_1
      20: invokevirtual #152                // Method java/lang/Object.getClass:()Ljava/lang/Class;
      23: invokevirtual #155                // Method java/lang/StringBuilder.append:(Ljava/lang/Object;)Ljava/lang/StringBuilder;
      26: invokevirtual #159                // Method java/lang/StringBuilder.toString:()Ljava/lang/String;
      29: invokestatic  #163                // Method io/grpc/xds/Filter$ConfigOrError.fromError:(Ljava/lang/String;)Lio/grpc/xds/Filter$ConfigOrError;
      32: areturn
      33: aload_1
      34: checkcast     #139                // class com/google/protobuf/Any
      37: astore_3
      38: aload_3
      39: ldc_w         #317                // class io/grpc/xds/shaded/io/envoyproxy/envoy/extensions/filters/http/rbac/v3/RBACPerRoute
      42: invokevirtual #169                // Method com/google/protobuf/Any.unpack:(Ljava/lang/Class;)Lcom/google/protobuf/Message;
      45: checkcast     #317                // class io/grpc/xds/shaded/io/envoyproxy/envoy/extensions/filters/http/rbac/v3/RBACPerRoute
      48: astore_2
      49: goto          78
      52: astore        4
      54: new           #141                // class java/lang/StringBuilder
      57: dup
      58: invokespecial #142                // Method java/lang/StringBuilder."<init>":()V
      61: ldc           #173                // String Invalid proto:
      63: invokevirtual #148                // Method java/lang/StringBuilder.append:(Ljava/lang/String;)Ljava/lang/StringBuilder;
      66: aload         4
      68: invokevirtual #155                // Method java/lang/StringBuilder.append:(Ljava/lang/Object;)Ljava/lang/StringBuilder;
      71: invokevirtual #159                // Method java/lang/StringBuilder.toString:()Ljava/lang/String;
      74: invokestatic  #163                // Method io/grpc/xds/Filter$ConfigOrError.fromError:(Ljava/lang/String;)Lio/grpc/xds/Filter$ConfigOrError;
      77: areturn
      78: aload_2
      79: invokevirtual #320                // Method io/grpc/xds/shaded/io/envoyproxy/envoy/extensions/filters/http/rbac/v3/RBACPerRoute.hasRbac:()Z
      82: ifeq          93
      85: aload_2
      86: invokevirtual #324                // Method io/grpc/xds/shaded/io/envoyproxy/envoy/extensions/filters/http/rbac/v3/RBACPerRoute.getRbac:()Lio/grpc/xds/shaded/io/envoyproxy/envoy/extensions/filters/http/rbac/v3/RBAC;
      89: invokestatic  #177                // Method parseRbacConfig:(Lio/grpc/xds/shaded/io/envoyproxy/envoy/extensions/filters/http/rbac/v3/RBAC;)Lio/grpc/xds/Filter$ConfigOrError;
      92: areturn
      93: aconst_null
      94: invokestatic  #199                // Method io/grpc/xds/RbacConfig.create:(Lio/grpc/xds/internal/rbac/engine/GrpcAuthorizationEngine$AuthConfig;)Lio/grpc/xds/RbacConfig;
      97: invokestatic  #203                // Method io/grpc/xds/Filter$ConfigOrError.fromConfig:(Ljava/lang/Object;)Lio/grpc/xds/Filter$ConfigOrError;
     100: areturn
    Exception table:
       from    to  target type
          38    49    52   Class com/google/protobuf/InvalidProtocolBufferException

  public io.grpc.ServerInterceptor buildServerInterceptor(io.grpc.xds.Filter$FilterConfig, io.grpc.xds.Filter$FilterConfig);
    Code:
       0: aload_1
       1: ldc_w         #331                // String config
       4: invokestatic  #337                // Method com/google/common/base/Preconditions.checkNotNull:(Ljava/lang/Object;Ljava/lang/Object;)Ljava/lang/Object;
       7: pop
       8: aload_2
       9: ifnull        14
      12: aload_2
      13: astore_1
      14: aload_1
      15: checkcast     #195                // class io/grpc/xds/RbacConfig
      18: invokevirtual #341                // Method io/grpc/xds/RbacConfig.authConfig:()Lio/grpc/xds/internal/rbac/engine/GrpcAuthorizationEngine$AuthConfig;
      21: astore_3
      22: aload_3
      23: ifnonnull     30
      26: aconst_null
      27: goto          35
      30: aload_0
      31: aload_3
      32: invokespecial #345                // Method generateAuthorizationInterceptor:(Lio/grpc/xds/internal/rbac/engine/GrpcAuthorizationEngine$AuthConfig;)Lio/grpc/ServerInterceptor;
      35: areturn

  private io.grpc.ServerInterceptor generateAuthorizationInterceptor(io.grpc.xds.internal.rbac.engine.GrpcAuthorizationEngine$AuthConfig);
    Code:
       0: aload_1
       1: ldc_w         #331                // String config
       4: invokestatic  #337                // Method com/google/common/base/Preconditions.checkNotNull:(Ljava/lang/Object;Ljava/lang/Object;)Ljava/lang/Object;
       7: pop
       8: new           #20                 // class io/grpc/xds/internal/rbac/engine/GrpcAuthorizationEngine
      11: dup
      12: aload_1
      13: invokespecial #353                // Method io/grpc/xds/internal/rbac/engine/GrpcAuthorizationEngine."<init>":(Lio/grpc/xds/internal/rbac/engine/GrpcAuthorizationEngine$AuthConfig;)V
      16: astore_2
      17: new           #13                 // class io/grpc/xds/RbacFilter$1
      20: dup
      21: aload_0
      22: aload_2
      23: invokespecial #356                // Method io/grpc/xds/RbacFilter$1."<init>":(Lio/grpc/xds/RbacFilter;Lio/grpc/xds/internal/rbac/engine/GrpcAuthorizationEngine;)V
      26: areturn

  private static io.grpc.xds.internal.rbac.engine.GrpcAuthorizationEngine$OrMatcher parsePermissionList(java.util.List<io.grpc.xds.shaded.io.envoyproxy.envoy.config.rbac.v3.Permission>);
    Code:
       0: new           #234                // class java/util/ArrayList
       3: dup
       4: invokespecial #235                // Method java/util/ArrayList."<init>":()V
       7: astore_1
       8: aload_0
       9: invokeinterface #360,  1          // InterfaceMethod java/util/List.iterator:()Ljava/util/Iterator;
      14: astore_2
      15: aload_2
      16: invokeinterface #252,  1          // InterfaceMethod java/util/Iterator.hasNext:()Z
      21: ifeq          48
      24: aload_2
      25: invokeinterface #256,  1          // InterfaceMethod java/util/Iterator.next:()Ljava/lang/Object;
      30: checkcast     #84                 // class io/grpc/xds/shaded/io/envoyproxy/envoy/config/rbac/v3/Permission
      33: astore_3
      34: aload_1
      35: aload_3
      36: invokestatic  #364                // Method parsePermission:(Lio/grpc/xds/shaded/io/envoyproxy/envoy/config/rbac/v3/Permission;)Lio/grpc/xds/internal/rbac/engine/GrpcAuthorizationEngine$Matcher;
      39: invokeinterface #293,  2          // InterfaceMethod java/util/List.add:(Ljava/lang/Object;)Z
      44: pop
      45: goto          15
      48: aload_1
      49: invokestatic  #366                // Method io/grpc/xds/internal/rbac/engine/GrpcAuthorizationEngine$OrMatcher.create:(Ljava/util/List;)Lio/grpc/xds/internal/rbac/engine/GrpcAuthorizationEngine$OrMatcher;
      52: areturn

  private static io.grpc.xds.internal.rbac.engine.GrpcAuthorizationEngine$Matcher parsePermission(io.grpc.xds.shaded.io.envoyproxy.envoy.config.rbac.v3.Permission);
    Code:
       0: getstatic     #375                // Field io/grpc/xds/RbacFilter$2.$SwitchMap$io$envoyproxy$envoy$config$rbac$v3$Permission$RuleCase:[I
       3: aload_0
       4: invokevirtual #379                // Method io/grpc/xds/shaded/io/envoyproxy/envoy/config/rbac/v3/Permission.getRuleCase:()Lio/grpc/xds/shaded/io/envoyproxy/envoy/config/rbac/v3/Permission$RuleCase;
       7: invokevirtual #380                // Method io/grpc/xds/shaded/io/envoyproxy/envoy/config/rbac/v3/Permission$RuleCase.ordinal:()I
      10: iaload
      11: tableswitch   { // 1 to 12
                     1: 72
                     2: 131
                     3: 142
                     4: 146
                     5: 154
                     6: 162
                     7: 170
                     8: 178
                     9: 186
                    10: 197
                    11: 204
                    12: 212
               default: 212
          }
      72: new           #234                // class java/util/ArrayList
      75: dup
      76: invokespecial #235                // Method java/util/ArrayList."<init>":()V
      79: astore_1
      80: aload_0
      81: invokevirtual #384                // Method io/grpc/xds/shaded/io/envoyproxy/envoy/config/rbac/v3/Permission.getAndRules:()Lio/grpc/xds/shaded/io/envoyproxy/envoy/config/rbac/v3/Permission$Set;
      84: invokevirtual #387                // Method io/grpc/xds/shaded/io/envoyproxy/envoy/config/rbac/v3/Permission$Set.getRulesList:()Ljava/util/List;
      87: invokeinterface #360,  1          // InterfaceMethod java/util/List.iterator:()Ljava/util/Iterator;
      92: astore_2
      93: aload_2
      94: invokeinterface #252,  1          // InterfaceMethod java/util/Iterator.hasNext:()Z
      99: ifeq          126
     102: aload_2
     103: invokeinterface #256,  1          // InterfaceMethod java/util/Iterator.next:()Ljava/lang/Object;
     108: checkcast     #84                 // class io/grpc/xds/shaded/io/envoyproxy/envoy/config/rbac/v3/Permission
     111: astore_3
     112: aload_1
     113: aload_3
     114: invokestatic  #364                // Method parsePermission:(Lio/grpc/xds/shaded/io/envoyproxy/envoy/config/rbac/v3/Permission;)Lio/grpc/xds/internal/rbac/engine/GrpcAuthorizationEngine$Matcher;
     117: invokeinterface #293,  2          // InterfaceMethod java/util/List.add:(Ljava/lang/Object;)Z
     122: pop
     123: goto          93
     126: aload_1
     127: invokestatic  #390                // Method io/grpc/xds/internal/rbac/engine/GrpcAuthorizationEngine$AndMatcher.create:(Ljava/util/List;)Lio/grpc/xds/internal/rbac/engine/GrpcAuthorizationEngine$AndMatcher;
     130: areturn
     131: aload_0
     132: invokevirtual #393                // Method io/grpc/xds/shaded/io/envoyproxy/envoy/config/rbac/v3/Permission.getOrRules:()Lio/grpc/xds/shaded/io/envoyproxy/envoy/config/rbac/v3/Permission$Set;
     135: invokevirtual #387                // Method io/grpc/xds/shaded/io/envoyproxy/envoy/config/rbac/v3/Permission$Set.getRulesList:()Ljava/util/List;
     138: invokestatic  #280                // Method parsePermissionList:(Ljava/util/List;)Lio/grpc/xds/internal/rbac/engine/GrpcAuthorizationEngine$OrMatcher;
     141: areturn
     142: getstatic     #396                // Field io/grpc/xds/internal/rbac/engine/GrpcAuthorizationEngine$AlwaysTrueMatcher.INSTANCE:Lio/grpc/xds/internal/rbac/engine/GrpcAuthorizationEngine$AlwaysTrueMatcher;
     145: areturn
     146: aload_0
     147: invokevirtual #400                // Method io/grpc/xds/shaded/io/envoyproxy/envoy/config/rbac/v3/Permission.getHeader:()Lio/grpc/xds/shaded/io/envoyproxy/envoy/config/route/v3/HeaderMatcher;
     150: invokestatic  #404                // Method parseHeaderMatcher:(Lio/grpc/xds/shaded/io/envoyproxy/envoy/config/route/v3/HeaderMatcher;)Lio/grpc/xds/internal/rbac/engine/GrpcAuthorizationEngine$AuthHeaderMatcher;
     153: areturn
     154: aload_0
     155: invokevirtual #408                // Method io/grpc/xds/shaded/io/envoyproxy/envoy/config/rbac/v3/Permission.getUrlPath:()Lio/grpc/xds/shaded/io/envoyproxy/envoy/type/matcher/v3/PathMatcher;
     158: invokestatic  #412                // Method parsePathMatcher:(Lio/grpc/xds/shaded/io/envoyproxy/envoy/type/matcher/v3/PathMatcher;)Lio/grpc/xds/internal/rbac/engine/GrpcAuthorizationEngine$PathMatcher;
     161: areturn
     162: aload_0
     163: invokevirtual #416                // Method io/grpc/xds/shaded/io/envoyproxy/envoy/config/rbac/v3/Permission.getDestinationIp:()Lio/grpc/xds/shaded/io/envoyproxy/envoy/config/core/v3/CidrRange;
     166: invokestatic  #420                // Method createDestinationIpMatcher:(Lio/grpc/xds/shaded/io/envoyproxy/envoy/config/core/v3/CidrRange;)Lio/grpc/xds/internal/rbac/engine/GrpcAuthorizationEngine$DestinationIpMatcher;
     169: areturn
     170: aload_0
     171: invokevirtual #423                // Method io/grpc/xds/shaded/io/envoyproxy/envoy/config/rbac/v3/Permission.getDestinationPort:()I
     174: invokestatic  #427                // Method createDestinationPortMatcher:(I)Lio/grpc/xds/internal/rbac/engine/GrpcAuthorizationEngine$DestinationPortMatcher;
     177: areturn
     178: aload_0
     179: invokevirtual #431                // Method io/grpc/xds/shaded/io/envoyproxy/envoy/config/rbac/v3/Permission.getDestinationPortRange:()Lio/grpc/xds/shaded/io/envoyproxy/envoy/type/v3/Int32Range;
     182: invokestatic  #435                // Method parseDestinationPortRangeMatcher:(Lio/grpc/xds/shaded/io/envoyproxy/envoy/type/v3/Int32Range;)Lio/grpc/xds/internal/rbac/engine/GrpcAuthorizationEngine$DestinationPortRangeMatcher;
     185: areturn
     186: aload_0
     187: invokevirtual #439                // Method io/grpc/xds/shaded/io/envoyproxy/envoy/config/rbac/v3/Permission.getNotRule:()Lio/grpc/xds/shaded/io/envoyproxy/envoy/config/rbac/v3/Permission;
     190: invokestatic  #364                // Method parsePermission:(Lio/grpc/xds/shaded/io/envoyproxy/envoy/config/rbac/v3/Permission;)Lio/grpc/xds/internal/rbac/engine/GrpcAuthorizationEngine$Matcher;
     193: invokestatic  #442                // Method io/grpc/xds/internal/rbac/engine/GrpcAuthorizationEngine$InvertMatcher.create:(Lio/grpc/xds/internal/rbac/engine/GrpcAuthorizationEngine$Matcher;)Lio/grpc/xds/internal/rbac/engine/GrpcAuthorizationEngine$InvertMatcher;
     196: areturn
     197: getstatic     #396                // Field io/grpc/xds/internal/rbac/engine/GrpcAuthorizationEngine$AlwaysTrueMatcher.INSTANCE:Lio/grpc/xds/internal/rbac/engine/GrpcAuthorizationEngine$AlwaysTrueMatcher;
     200: invokestatic  #442                // Method io/grpc/xds/internal/rbac/engine/GrpcAuthorizationEngine$InvertMatcher.create:(Lio/grpc/xds/internal/rbac/engine/GrpcAuthorizationEngine$Matcher;)Lio/grpc/xds/internal/rbac/engine/GrpcAuthorizationEngine$InvertMatcher;
     203: areturn
     204: aload_0
     205: invokevirtual #446                // Method io/grpc/xds/shaded/io/envoyproxy/envoy/config/rbac/v3/Permission.getRequestedServerName:()Lio/grpc/xds/shaded/io/envoyproxy/envoy/type/matcher/v3/StringMatcher;
     208: invokestatic  #450                // Method parseRequestedServerNameMatcher:(Lio/grpc/xds/shaded/io/envoyproxy/envoy/type/matcher/v3/StringMatcher;)Lio/grpc/xds/internal/rbac/engine/GrpcAuthorizationEngine$RequestedServerNameMatcher;
     211: areturn
     212: new           #452                // class java/lang/IllegalArgumentException
     215: dup
     216: new           #141                // class java/lang/StringBuilder
     219: dup
     220: invokespecial #142                // Method java/lang/StringBuilder."<init>":()V
     223: ldc_w         #454                // String Unknown permission rule case:
     226: invokevirtual #148                // Method java/lang/StringBuilder.append:(Ljava/lang/String;)Ljava/lang/StringBuilder;
     229: aload_0
     230: invokevirtual #379                // Method io/grpc/xds/shaded/io/envoyproxy/envoy/config/rbac/v3/Permission.getRuleCase:()Lio/grpc/xds/shaded/io/envoyproxy/envoy/config/rbac/v3/Permission$RuleCase;
     233: invokevirtual #155                // Method java/lang/StringBuilder.append:(Ljava/lang/Object;)Ljava/lang/StringBuilder;
     236: invokevirtual #159                // Method java/lang/StringBuilder.toString:()Ljava/lang/String;
     239: invokespecial #457                // Method java/lang/IllegalArgumentException."<init>":(Ljava/lang/String;)V
     242: athrow

  private static io.grpc.xds.internal.rbac.engine.GrpcAuthorizationEngine$OrMatcher parsePrincipalList(java.util.List<io.grpc.xds.shaded.io.envoyproxy.envoy.config.rbac.v3.Principal>);
    Code:
       0: new           #234                // class java/util/ArrayList
       3: dup
       4: invokespecial #235                // Method java/util/ArrayList."<init>":()V
       7: astore_1
       8: aload_0
       9: invokeinterface #360,  1          // InterfaceMethod java/util/List.iterator:()Ljava/util/Iterator;
      14: astore_2
      15: aload_2
      16: invokeinterface #252,  1          // InterfaceMethod java/util/Iterator.hasNext:()Z
      21: ifeq          48
      24: aload_2
      25: invokeinterface #256,  1          // InterfaceMethod java/util/Iterator.next:()Ljava/lang/Object;
      30: checkcast     #54                 // class io/grpc/xds/shaded/io/envoyproxy/envoy/config/rbac/v3/Principal
      33: astore_3
      34: aload_1
      35: aload_3
      36: invokestatic  #464                // Method parsePrincipal:(Lio/grpc/xds/shaded/io/envoyproxy/envoy/config/rbac/v3/Principal;)Lio/grpc/xds/internal/rbac/engine/GrpcAuthorizationEngine$Matcher;
      39: invokeinterface #293,  2          // InterfaceMethod java/util/List.add:(Ljava/lang/Object;)Z
      44: pop
      45: goto          15
      48: aload_1
      49: invokestatic  #366                // Method io/grpc/xds/internal/rbac/engine/GrpcAuthorizationEngine$OrMatcher.create:(Ljava/util/List;)Lio/grpc/xds/internal/rbac/engine/GrpcAuthorizationEngine$OrMatcher;
      52: areturn

  private static io.grpc.xds.internal.rbac.engine.GrpcAuthorizationEngine$Matcher parsePrincipal(io.grpc.xds.shaded.io.envoyproxy.envoy.config.rbac.v3.Principal);
    Code:
       0: getstatic     #471                // Field io/grpc/xds/RbacFilter$2.$SwitchMap$io$envoyproxy$envoy$config$rbac$v3$Principal$IdentifierCase:[I
       3: aload_0
       4: invokevirtual #475                // Method io/grpc/xds/shaded/io/envoyproxy/envoy/config/rbac/v3/Principal.getIdentifierCase:()Lio/grpc/xds/shaded/io/envoyproxy/envoy/config/rbac/v3/Principal$IdentifierCase;
       7: invokevirtual #476                // Method io/grpc/xds/shaded/io/envoyproxy/envoy/config/rbac/v3/Principal$IdentifierCase.ordinal:()I
      10: iaload
      11: tableswitch   { // 1 to 12
                     1: 72
                     2: 83
                     3: 142
                     4: 146
                     5: 154
                     6: 162
                     7: 170
                     8: 178
                     9: 186
                    10: 197
                    11: 205
                    12: 212
               default: 212
          }
      72: aload_0
      73: invokevirtual #480                // Method io/grpc/xds/shaded/io/envoyproxy/envoy/config/rbac/v3/Principal.getOrIds:()Lio/grpc/xds/shaded/io/envoyproxy/envoy/config/rbac/v3/Principal$Set;
      76: invokevirtual #483                // Method io/grpc/xds/shaded/io/envoyproxy/envoy/config/rbac/v3/Principal$Set.getIdsList:()Ljava/util/List;
      79: invokestatic  #286                // Method parsePrincipalList:(Ljava/util/List;)Lio/grpc/xds/internal/rbac/engine/GrpcAuthorizationEngine$OrMatcher;
      82: areturn
      83: new           #234                // class java/util/ArrayList
      86: dup
      87: invokespecial #235                // Method java/util/ArrayList."<init>":()V
      90: astore_1
      91: aload_0
      92: invokevirtual #486                // Method io/grpc/xds/shaded/io/envoyproxy/envoy/config/rbac/v3/Principal.getAndIds:()Lio/grpc/xds/shaded/io/envoyproxy/envoy/config/rbac/v3/Principal$Set;
      95: invokevirtual #483                // Method io/grpc/xds/shaded/io/envoyproxy/envoy/config/rbac/v3/Principal$Set.getIdsList:()Ljava/util/List;
      98: invokeinterface #360,  1          // InterfaceMethod java/util/List.iterator:()Ljava/util/Iterator;
     103: astore_2
     104: aload_2
     105: invokeinterface #252,  1          // InterfaceMethod java/util/Iterator.hasNext:()Z
     110: ifeq          137
     113: aload_2
     114: invokeinterface #256,  1          // InterfaceMethod java/util/Iterator.next:()Ljava/lang/Object;
     119: checkcast     #54                 // class io/grpc/xds/shaded/io/envoyproxy/envoy/config/rbac/v3/Principal
     122: astore_3
     123: aload_1
     124: aload_3
     125: invokestatic  #464                // Method parsePrincipal:(Lio/grpc/xds/shaded/io/envoyproxy/envoy/config/rbac/v3/Principal;)Lio/grpc/xds/internal/rbac/engine/GrpcAuthorizationEngine$Matcher;
     128: invokeinterface #293,  2          // InterfaceMethod java/util/List.add:(Ljava/lang/Object;)Z
     133: pop
     134: goto          104
     137: aload_1
     138: invokestatic  #390                // Method io/grpc/xds/internal/rbac/engine/GrpcAuthorizationEngine$AndMatcher.create:(Ljava/util/List;)Lio/grpc/xds/internal/rbac/engine/GrpcAuthorizationEngine$AndMatcher;
     141: areturn
     142: getstatic     #396                // Field io/grpc/xds/internal/rbac/engine/GrpcAuthorizationEngine$AlwaysTrueMatcher.INSTANCE:Lio/grpc/xds/internal/rbac/engine/GrpcAuthorizationEngine$AlwaysTrueMatcher;
     145: areturn
     146: aload_0
     147: invokevirtual #490                // Method io/grpc/xds/shaded/io/envoyproxy/envoy/config/rbac/v3/Principal.getAuthenticated:()Lio/grpc/xds/shaded/io/envoyproxy/envoy/config/rbac/v3/Principal$Authenticated;
     150: invokestatic  #494                // Method parseAuthenticatedMatcher:(Lio/grpc/xds/shaded/io/envoyproxy/envoy/config/rbac/v3/Principal$Authenticated;)Lio/grpc/xds/internal/rbac/engine/GrpcAuthorizationEngine$AuthenticatedMatcher;
     153: areturn
     154: aload_0
     155: invokevirtual #497                // Method io/grpc/xds/shaded/io/envoyproxy/envoy/config/rbac/v3/Principal.getDirectRemoteIp:()Lio/grpc/xds/shaded/io/envoyproxy/envoy/config/core/v3/CidrRange;
     158: invokestatic  #501                // Method createSourceIpMatcher:(Lio/grpc/xds/shaded/io/envoyproxy/envoy/config/core/v3/CidrRange;)Lio/grpc/xds/internal/rbac/engine/GrpcAuthorizationEngine$SourceIpMatcher;
     161: areturn
     162: aload_0
     163: invokevirtual #504                // Method io/grpc/xds/shaded/io/envoyproxy/envoy/config/rbac/v3/Principal.getRemoteIp:()Lio/grpc/xds/shaded/io/envoyproxy/envoy/config/core/v3/CidrRange;
     166: invokestatic  #501                // Method createSourceIpMatcher:(Lio/grpc/xds/shaded/io/envoyproxy/envoy/config/core/v3/CidrRange;)Lio/grpc/xds/internal/rbac/engine/GrpcAuthorizationEngine$SourceIpMatcher;
     169: areturn
     170: aload_0
     171: invokevirtual #507                // Method io/grpc/xds/shaded/io/envoyproxy/envoy/config/rbac/v3/Principal.getSourceIp:()Lio/grpc/xds/shaded/io/envoyproxy/envoy/config/core/v3/CidrRange;
     174: invokestatic  #501                // Method createSourceIpMatcher:(Lio/grpc/xds/shaded/io/envoyproxy/envoy/config/core/v3/CidrRange;)Lio/grpc/xds/internal/rbac/engine/GrpcAuthorizationEngine$SourceIpMatcher;
     177: areturn
     178: aload_0
     179: invokevirtual #508                // Method io/grpc/xds/shaded/io/envoyproxy/envoy/config/rbac/v3/Principal.getHeader:()Lio/grpc/xds/shaded/io/envoyproxy/envoy/config/route/v3/HeaderMatcher;
     182: invokestatic  #404                // Method parseHeaderMatcher:(Lio/grpc/xds/shaded/io/envoyproxy/envoy/config/route/v3/HeaderMatcher;)Lio/grpc/xds/internal/rbac/engine/GrpcAuthorizationEngine$AuthHeaderMatcher;
     185: areturn
     186: aload_0
     187: invokevirtual #512                // Method io/grpc/xds/shaded/io/envoyproxy/envoy/config/rbac/v3/Principal.getNotId:()Lio/grpc/xds/shaded/io/envoyproxy/envoy/config/rbac/v3/Principal;
     190: invokestatic  #464                // Method parsePrincipal:(Lio/grpc/xds/shaded/io/envoyproxy/envoy/config/rbac/v3/Principal;)Lio/grpc/xds/internal/rbac/engine/GrpcAuthorizationEngine$Matcher;
     193: invokestatic  #442                // Method io/grpc/xds/internal/rbac/engine/GrpcAuthorizationEngine$InvertMatcher.create:(Lio/grpc/xds/internal/rbac/engine/GrpcAuthorizationEngine$Matcher;)Lio/grpc/xds/internal/rbac/engine/GrpcAuthorizationEngine$InvertMatcher;
     196: areturn
     197: aload_0
     198: invokevirtual #513                // Method io/grpc/xds/shaded/io/envoyproxy/envoy/config/rbac/v3/Principal.getUrlPath:()Lio/grpc/xds/shaded/io/envoyproxy/envoy/type/matcher/v3/PathMatcher;
     201: invokestatic  #412                // Method parsePathMatcher:(Lio/grpc/xds/shaded/io/envoyproxy/envoy/type/matcher/v3/PathMatcher;)Lio/grpc/xds/internal/rbac/engine/GrpcAuthorizationEngine$PathMatcher;
     204: areturn
     205: getstatic     #396                // Field io/grpc/xds/internal/rbac/engine/GrpcAuthorizationEngine$AlwaysTrueMatcher.INSTANCE:Lio/grpc/xds/internal/rbac/engine/GrpcAuthorizationEngine$AlwaysTrueMatcher;
     208: invokestatic  #442                // Method io/grpc/xds/internal/rbac/engine/GrpcAuthorizationEngine$InvertMatcher.create:(Lio/grpc/xds/internal/rbac/engine/GrpcAuthorizationEngine$Matcher;)Lio/grpc/xds/internal/rbac/engine/GrpcAuthorizationEngine$InvertMatcher;
     211: areturn
     212: new           #452                // class java/lang/IllegalArgumentException
     215: dup
     216: new           #141                // class java/lang/StringBuilder
     219: dup
     220: invokespecial #142                // Method java/lang/StringBuilder."<init>":()V
     223: ldc_w         #515                // String Unknown principal identifier case:
     226: invokevirtual #148                // Method java/lang/StringBuilder.append:(Ljava/lang/String;)Ljava/lang/StringBuilder;
     229: aload_0
     230: invokevirtual #475                // Method io/grpc/xds/shaded/io/envoyproxy/envoy/config/rbac/v3/Principal.getIdentifierCase:()Lio/grpc/xds/shaded/io/envoyproxy/envoy/config/rbac/v3/Principal$IdentifierCase;
     233: invokevirtual #155                // Method java/lang/StringBuilder.append:(Ljava/lang/Object;)Ljava/lang/StringBuilder;
     236: invokevirtual #159                // Method java/lang/StringBuilder.toString:()Ljava/lang/String;
     239: invokespecial #457                // Method java/lang/IllegalArgumentException."<init>":(Ljava/lang/String;)V
     242: athrow

  private static io.grpc.xds.internal.rbac.engine.GrpcAuthorizationEngine$PathMatcher parsePathMatcher(io.grpc.xds.shaded.io.envoyproxy.envoy.type.matcher.v3.PathMatcher);
    Code:
       0: getstatic     #519                // Field io/grpc/xds/RbacFilter$2.$SwitchMap$io$envoyproxy$envoy$type$matcher$v3$PathMatcher$RuleCase:[I
       3: aload_0
       4: invokevirtual #522                // Method io/grpc/xds/shaded/io/envoyproxy/envoy/type/matcher/v3/PathMatcher.getRuleCase:()Lio/grpc/xds/shaded/io/envoyproxy/envoy/type/matcher/v3/PathMatcher$RuleCase;
       7: invokevirtual #523                // Method io/grpc/xds/shaded/io/envoyproxy/envoy/type/matcher/v3/PathMatcher$RuleCase.ordinal:()I
      10: iaload
      11: lookupswitch  { // 2
                     1: 36
                     2: 47
               default: 47
          }
      36: aload_0
      37: invokevirtual #526                // Method io/grpc/xds/shaded/io/envoyproxy/envoy/type/matcher/v3/PathMatcher.getPath:()Lio/grpc/xds/shaded/io/envoyproxy/envoy/type/matcher/v3/StringMatcher;
      40: invokestatic  #532                // Method io/grpc/xds/internal/MatcherParser.parseStringMatcher:(Lio/grpc/xds/shaded/io/envoyproxy/envoy/type/matcher/v3/StringMatcher;)Lio/grpc/xds/internal/Matchers$StringMatcher;
      43: invokestatic  #535                // Method io/grpc/xds/internal/rbac/engine/GrpcAuthorizationEngine$PathMatcher.create:(Lio/grpc/xds/internal/Matchers$StringMatcher;)Lio/grpc/xds/internal/rbac/engine/GrpcAuthorizationEngine$PathMatcher;
      46: areturn
      47: new           #452                // class java/lang/IllegalArgumentException
      50: dup
      51: new           #141                // class java/lang/StringBuilder
      54: dup
      55: invokespecial #142                // Method java/lang/StringBuilder."<init>":()V
      58: ldc_w         #537                // String Unknown path matcher rule type:
      61: invokevirtual #148                // Method java/lang/StringBuilder.append:(Ljava/lang/String;)Ljava/lang/StringBuilder;
      64: aload_0
      65: invokevirtual #522                // Method io/grpc/xds/shaded/io/envoyproxy/envoy/type/matcher/v3/PathMatcher.getRuleCase:()Lio/grpc/xds/shaded/io/envoyproxy/envoy/type/matcher/v3/PathMatcher$RuleCase;
      68: invokevirtual #155                // Method java/lang/StringBuilder.append:(Ljava/lang/Object;)Ljava/lang/StringBuilder;
      71: invokevirtual #159                // Method java/lang/StringBuilder.toString:()Ljava/lang/String;
      74: invokespecial #457                // Method java/lang/IllegalArgumentException."<init>":(Ljava/lang/String;)V
      77: athrow

  private static io.grpc.xds.internal.rbac.engine.GrpcAuthorizationEngine$RequestedServerNameMatcher parseRequestedServerNameMatcher(io.grpc.xds.shaded.io.envoyproxy.envoy.type.matcher.v3.StringMatcher);
    Code:
       0: aload_0
       1: invokestatic  #532                // Method io/grpc/xds/internal/MatcherParser.parseStringMatcher:(Lio/grpc/xds/shaded/io/envoyproxy/envoy/type/matcher/v3/StringMatcher;)Lio/grpc/xds/internal/Matchers$StringMatcher;
       4: invokestatic  #542                // Method io/grpc/xds/internal/rbac/engine/GrpcAuthorizationEngine$RequestedServerNameMatcher.create:(Lio/grpc/xds/internal/Matchers$StringMatcher;)Lio/grpc/xds/internal/rbac/engine/GrpcAuthorizationEngine$RequestedServerNameMatcher;
       7: areturn

  private static io.grpc.xds.internal.rbac.engine.GrpcAuthorizationEngine$AuthHeaderMatcher parseHeaderMatcher(io.grpc.xds.shaded.io.envoyproxy.envoy.config.route.v3.HeaderMatcher);
    Code:
       0: aload_0
       1: invokevirtual #548                // Method io/grpc/xds/shaded/io/envoyproxy/envoy/config/route/v3/HeaderMatcher.getName:()Ljava/lang/String;
       4: ldc_w         #550                // String grpc-
       7: invokevirtual #554                // Method java/lang/String.startsWith:(Ljava/lang/String;)Z
      10: ifeq          24
      13: new           #452                // class java/lang/IllegalArgumentException
      16: dup
      17: ldc_w         #556                // String Invalid header matcher config: [grpc-] prefixed header name is not allowed.
      20: invokespecial #457                // Method java/lang/IllegalArgumentException."<init>":(Ljava/lang/String;)V
      23: athrow
      24: ldc_w         #558                // String :scheme
      27: aload_0
      28: invokevirtual #548                // Method io/grpc/xds/shaded/io/envoyproxy/envoy/config/route/v3/HeaderMatcher.getName:()Ljava/lang/String;
      31: invokevirtual #561                // Method java/lang/String.equals:(Ljava/lang/Object;)Z
      34: ifeq          48
      37: new           #452                // class java/lang/IllegalArgumentException
      40: dup
      41: ldc_w         #563                // String Invalid header matcher config: header name [:scheme] is not allowed.
      44: invokespecial #457                // Method java/lang/IllegalArgumentException."<init>":(Ljava/lang/String;)V
      47: athrow
      48: aload_0
      49: invokestatic  #566                // Method io/grpc/xds/internal/MatcherParser.parseHeaderMatcher:(Lio/grpc/xds/shaded/io/envoyproxy/envoy/config/route/v3/HeaderMatcher;)Lio/grpc/xds/internal/Matchers$HeaderMatcher;
      52: invokestatic  #569                // Method io/grpc/xds/internal/rbac/engine/GrpcAuthorizationEngine$AuthHeaderMatcher.create:(Lio/grpc/xds/internal/Matchers$HeaderMatcher;)Lio/grpc/xds/internal/rbac/engine/GrpcAuthorizationEngine$AuthHeaderMatcher;
      55: areturn

  private static io.grpc.xds.internal.rbac.engine.GrpcAuthorizationEngine$AuthenticatedMatcher parseAuthenticatedMatcher(io.grpc.xds.shaded.io.envoyproxy.envoy.config.rbac.v3.Principal$Authenticated);
    Code:
       0: aload_0
       1: invokevirtual #573                // Method io/grpc/xds/shaded/io/envoyproxy/envoy/config/rbac/v3/Principal$Authenticated.getPrincipalName:()Lio/grpc/xds/shaded/io/envoyproxy/envoy/type/matcher/v3/StringMatcher;
       4: invokestatic  #532                // Method io/grpc/xds/internal/MatcherParser.parseStringMatcher:(Lio/grpc/xds/shaded/io/envoyproxy/envoy/type/matcher/v3/StringMatcher;)Lio/grpc/xds/internal/Matchers$StringMatcher;
       7: astore_1
       8: aload_1
       9: invokestatic  #576                // Method io/grpc/xds/internal/rbac/engine/GrpcAuthorizationEngine$AuthenticatedMatcher.create:(Lio/grpc/xds/internal/Matchers$StringMatcher;)Lio/grpc/xds/internal/rbac/engine/GrpcAuthorizationEngine$AuthenticatedMatcher;
      12: areturn

  private static io.grpc.xds.internal.rbac.engine.GrpcAuthorizationEngine$DestinationPortMatcher createDestinationPortMatcher(int);
    Code:
       0: iload_0
       1: invokestatic  #581                // Method io/grpc/xds/internal/rbac/engine/GrpcAuthorizationEngine$DestinationPortMatcher.create:(I)Lio/grpc/xds/internal/rbac/engine/GrpcAuthorizationEngine$DestinationPortMatcher;
       4: areturn

  private static io.grpc.xds.internal.rbac.engine.GrpcAuthorizationEngine$DestinationPortRangeMatcher parseDestinationPortRangeMatcher(io.grpc.xds.shaded.io.envoyproxy.envoy.type.v3.Int32Range);
    Code:
       0: aload_0
       1: invokevirtual #588                // Method io/grpc/xds/shaded/io/envoyproxy/envoy/type/v3/Int32Range.getStart:()I
       4: aload_0
       5: invokevirtual #591                // Method io/grpc/xds/shaded/io/envoyproxy/envoy/type/v3/Int32Range.getEnd:()I
       8: invokestatic  #594                // Method io/grpc/xds/internal/rbac/engine/GrpcAuthorizationEngine$DestinationPortRangeMatcher.create:(II)Lio/grpc/xds/internal/rbac/engine/GrpcAuthorizationEngine$DestinationPortRangeMatcher;
      11: areturn

  private static io.grpc.xds.internal.rbac.engine.GrpcAuthorizationEngine$DestinationIpMatcher createDestinationIpMatcher(io.grpc.xds.shaded.io.envoyproxy.envoy.config.core.v3.CidrRange);
    Code:
       0: aload_0
       1: invokestatic  #600                // Method resolve:(Lio/grpc/xds/shaded/io/envoyproxy/envoy/config/core/v3/CidrRange;)Ljava/net/InetAddress;
       4: aload_0
       5: invokevirtual #606                // Method io/grpc/xds/shaded/io/envoyproxy/envoy/config/core/v3/CidrRange.getPrefixLen:()Lcom/google/protobuf/UInt32Value;
       8: invokevirtual #610                // Method com/google/protobuf/UInt32Value.getValue:()I
      11: invokestatic  #613                // Method io/grpc/xds/internal/Matchers$CidrMatcher.create:(Ljava/net/InetAddress;I)Lio/grpc/xds/internal/Matchers$CidrMatcher;
      14: invokestatic  #616                // Method io/grpc/xds/internal/rbac/engine/GrpcAuthorizationEngine$DestinationIpMatcher.create:(Lio/grpc/xds/internal/Matchers$CidrMatcher;)Lio/grpc/xds/internal/rbac/engine/GrpcAuthorizationEngine$DestinationIpMatcher;
      17: areturn

  private static io.grpc.xds.internal.rbac.engine.GrpcAuthorizationEngine$SourceIpMatcher createSourceIpMatcher(io.grpc.xds.shaded.io.envoyproxy.envoy.config.core.v3.CidrRange);
    Code:
       0: aload_0
       1: invokestatic  #600                // Method resolve:(Lio/grpc/xds/shaded/io/envoyproxy/envoy/config/core/v3/CidrRange;)Ljava/net/InetAddress;
       4: aload_0
       5: invokevirtual #606                // Method io/grpc/xds/shaded/io/envoyproxy/envoy/config/core/v3/CidrRange.getPrefixLen:()Lcom/google/protobuf/UInt32Value;
       8: invokevirtual #610                // Method com/google/protobuf/UInt32Value.getValue:()I
      11: invokestatic  #613                // Method io/grpc/xds/internal/Matchers$CidrMatcher.create:(Ljava/net/InetAddress;I)Lio/grpc/xds/internal/Matchers$CidrMatcher;
      14: invokestatic  #621                // Method io/grpc/xds/internal/rbac/engine/GrpcAuthorizationEngine$SourceIpMatcher.create:(Lio/grpc/xds/internal/Matchers$CidrMatcher;)Lio/grpc/xds/internal/rbac/engine/GrpcAuthorizationEngine$SourceIpMatcher;
      17: areturn

  private static java.net.InetAddress resolve(io.grpc.xds.shaded.io.envoyproxy.envoy.config.core.v3.CidrRange);
    Code:
       0: aload_0
       1: invokevirtual #626                // Method io/grpc/xds/shaded/io/envoyproxy/envoy/config/core/v3/CidrRange.getAddressPrefix:()Ljava/lang/String;
       4: invokestatic  #632                // Method java/net/InetAddress.getByName:(Ljava/lang/String;)Ljava/net/InetAddress;
       7: areturn
       8: astore_1
       9: new           #452                // class java/lang/IllegalArgumentException
      12: dup
      13: new           #141                // class java/lang/StringBuilder
      16: dup
      17: invokespecial #142                // Method java/lang/StringBuilder."<init>":()V
      20: ldc_w         #634                // String IP address can not be found:
      23: invokevirtual #148                // Method java/lang/StringBuilder.append:(Ljava/lang/String;)Ljava/lang/StringBuilder;
      26: aload_1
      27: invokevirtual #155                // Method java/lang/StringBuilder.append:(Ljava/lang/Object;)Ljava/lang/StringBuilder;
      30: invokevirtual #159                // Method java/lang/StringBuilder.toString:()Ljava/lang/String;
      33: invokespecial #457                // Method java/lang/IllegalArgumentException."<init>":(Ljava/lang/String;)V
      36: athrow
    Exception table:
       from    to  target type
           0     7     8   Class java/net/UnknownHostException

  static java.util.logging.Logger access$000();
    Code:
       0: getstatic     #640                // Field logger:Ljava/util/logging/Logger;
       3: areturn

  static {};
    Code:
       0: ldc           #2                  // class io/grpc/xds/RbacFilter
       2: invokevirtual #644                // Method java/lang/Class.getName:()Ljava/lang/String;
       5: invokestatic  #650                // Method java/util/logging/Logger.getLogger:(Ljava/lang/String;)Ljava/util/logging/Logger;
       8: putstatic     #640                // Field logger:Ljava/util/logging/Logger;
      11: new           #2                  // class io/grpc/xds/RbacFilter
      14: dup
      15: invokespecial #651                // Method "<init>":()V
      18: putstatic     #653                // Field INSTANCE:Lio/grpc/xds/RbacFilter;
      21: return
}
