Compiled from "RingHashLoadBalancer.java"
class io.grpc.xds.RingHashLoadBalancer$RingHashPicker$1 implements java.lang.Runnable {
  final io.grpc.LoadBalancer$Subchannel val$finalSubchannel;

  final io.grpc.xds.RingHashLoadBalancer$RingHashPicker this$0;

  io.grpc.xds.RingHashLoadBalancer$RingHashPicker$1(io.grpc.xds.RingHashLoadBalancer$RingHashPicker, io.grpc.LoadBalancer$Subchannel);
    Code:
       0: aload_0
       1: aload_1
       2: putfield      #34                 // Field this$0:Lio/grpc/xds/RingHashLoadBalancer$RingHashPicker;
       5: aload_0
       6: aload_2
       7: putfield      #36                 // Field val$finalSubchannel:Lio/grpc/LoadBalancer$Subchannel;
      10: aload_0
      11: invokespecial #39                 // Method java/lang/Object."<init>":()V
      14: return

  public void run();
    Code:
       0: aload_0
       1: getfield      #36                 // Field val$finalSubchannel:Lio/grpc/LoadBalancer$Subchannel;
       4: invokevirtual #45                 // Method io/grpc/LoadBalancer$Subchannel.requestConnection:()V
       7: return
}
