Compiled from "XdsServerWrapper.java"
class io.grpc.xds.XdsServerWrapper$DiscoveryState$4 implements java.lang.Runnable {
  final io.grpc.Status val$error;

  final io.grpc.xds.XdsServerWrapper$DiscoveryState this$1;

  io.grpc.xds.XdsServerWrapper$DiscoveryState$4(io.grpc.xds.XdsServerWrapper$DiscoveryState, io.grpc.Status);
    Code:
       0: aload_0
       1: aload_1
       2: putfield      #28                 // Field this$1:Lio/grpc/xds/XdsServerWrapper$DiscoveryState;
       5: aload_0
       6: aload_2
       7: putfield      #30                 // Field val$error:Lio/grpc/Status;
      10: aload_0
      11: invokespecial #33                 // Method java/lang/Object."<init>":()V
      14: return

  public void run();
    Code:
       0: aload_0
       1: getfield      #28                 // Field this$1:Lio/grpc/xds/XdsServerWrapper$DiscoveryState;
       4: invokestatic  #40                 // Method io/grpc/xds/XdsServerWrapper$DiscoveryState.access$900:(Lio/grpc/xds/XdsServerWrapper$DiscoveryState;)Z
       7: ifeq          11
      10: return
      11: aload_0
      12: getfield      #28                 // Field this$1:Lio/grpc/xds/XdsServerWrapper$DiscoveryState;
      15: aload_0
      16: getfield      #30                 // Field val$error:Lio/grpc/Status;
      19: invokestatic  #44                 // Method io/grpc/xds/XdsServerWrapper$DiscoveryState.access$2000:(Lio/grpc/xds/XdsServerWrapper$DiscoveryState;Lio/grpc/Status;)Z
      22: istore_1
      23: invokestatic  #48                 // Method io/grpc/xds/XdsServerWrapper.access$000:()Ljava/util/logging/Logger;
      26: getstatic     #54                 // Field java/util/logging/Level.FINE:Ljava/util/logging/Level;
      29: ldc           #56                 // String {0} error from XdsClient: {1}
      31: iconst_2
      32: anewarray     #4                  // class java/lang/Object
      35: dup
      36: iconst_0
      37: iload_1
      38: ifeq          46
      41: ldc           #58                 // String Permanent
      43: goto          48
      46: ldc           #66                 // String Transient
      48: aastore
      49: dup
      50: iconst_1
      51: aload_0
      52: getfield      #30                 // Field val$error:Lio/grpc/Status;
      55: aastore
      56: invokevirtual #70                 // Method java/util/logging/Logger.log:(Ljava/util/logging/Level;Ljava/lang/String;[Ljava/lang/Object;)V
      59: iload_1
      60: ifeq          80
      63: aload_0
      64: getfield      #28                 // Field this$1:Lio/grpc/xds/XdsServerWrapper$DiscoveryState;
      67: aload_0
      68: getfield      #30                 // Field val$error:Lio/grpc/Status;
      71: invokevirtual #76                 // Method io/grpc/Status.asException:()Lio/grpc/StatusException;
      74: invokestatic  #80                 // Method io/grpc/xds/XdsServerWrapper$DiscoveryState.access$1900:(Lio/grpc/xds/XdsServerWrapper$DiscoveryState;Lio/grpc/StatusException;)V
      77: goto          115
      80: aload_0
      81: getfield      #28                 // Field this$1:Lio/grpc/xds/XdsServerWrapper$DiscoveryState;
      84: getfield      #84                 // Field io/grpc/xds/XdsServerWrapper$DiscoveryState.this$0:Lio/grpc/xds/XdsServerWrapper;
      87: invokestatic  #88                 // Method io/grpc/xds/XdsServerWrapper.access$2100:(Lio/grpc/xds/XdsServerWrapper;)Z
      90: ifne          115
      93: aload_0
      94: getfield      #28                 // Field this$1:Lio/grpc/xds/XdsServerWrapper$DiscoveryState;
      97: getfield      #84                 // Field io/grpc/xds/XdsServerWrapper$DiscoveryState.this$0:Lio/grpc/xds/XdsServerWrapper;
     100: invokestatic  #92                 // Method io/grpc/xds/XdsServerWrapper.access$2200:(Lio/grpc/xds/XdsServerWrapper;)Lio/grpc/xds/XdsServerBuilder$XdsServingStatusListener;
     103: aload_0
     104: getfield      #30                 // Field val$error:Lio/grpc/Status;
     107: invokevirtual #76                 // Method io/grpc/Status.asException:()Lio/grpc/StatusException;
     110: invokeinterface #96,  2           // InterfaceMethod io/grpc/xds/XdsServerBuilder$XdsServingStatusListener.onNotServing:(Ljava/lang/Throwable;)V
     115: return
}
