Compiled from "XdsServerWrapper.java"
class io.grpc.xds.XdsServerWrapper$DiscoveryState$3 implements java.lang.Runnable {
  final java.lang.String val$resourceName;

  final io.grpc.xds.XdsServerWrapper$DiscoveryState this$1;

  io.grpc.xds.XdsServerWrapper$DiscoveryState$3(io.grpc.xds.XdsServerWrapper$DiscoveryState, java.lang.String);
    Code:
       0: aload_0
       1: aload_1
       2: putfield      #23                 // Field this$1:Lio/grpc/xds/XdsServerWrapper$DiscoveryState;
       5: aload_0
       6: aload_2
       7: putfield      #25                 // Field val$resourceName:Ljava/lang/String;
      10: aload_0
      11: invokespecial #28                 // Method java/lang/Object."<init>":()V
      14: return

  public void run();
    Code:
       0: aload_0
       1: getfield      #23                 // Field this$1:Lio/grpc/xds/XdsServerWrapper$DiscoveryState;
       4: invokestatic  #35                 // Method io/grpc/xds/XdsServerWrapper$DiscoveryState.access$900:(Lio/grpc/xds/XdsServerWrapper$DiscoveryState;)Z
       7: ifeq          11
      10: return
      11: getstatic     #41                 // Field io/grpc/Status.UNAVAILABLE:Lio/grpc/Status;
      14: new           #43                 // class java/lang/StringBuilder
      17: dup
      18: invokespecial #44                 // Method java/lang/StringBuilder."<init>":()V
      21: ldc           #46                 // String Listener
      23: invokevirtual #50                 // Method java/lang/StringBuilder.append:(Ljava/lang/String;)Ljava/lang/StringBuilder;
      26: aload_0
      27: getfield      #25                 // Field val$resourceName:Ljava/lang/String;
      30: invokevirtual #50                 // Method java/lang/StringBuilder.append:(Ljava/lang/String;)Ljava/lang/StringBuilder;
      33: ldc           #52                 // String  unavailable
      35: invokevirtual #50                 // Method java/lang/StringBuilder.append:(Ljava/lang/String;)Ljava/lang/StringBuilder;
      38: invokevirtual #56                 // Method java/lang/StringBuilder.toString:()Ljava/lang/String;
      41: invokevirtual #60                 // Method io/grpc/Status.withDescription:(Ljava/lang/String;)Lio/grpc/Status;
      44: invokevirtual #64                 // Method io/grpc/Status.asException:()Lio/grpc/StatusException;
      47: astore_1
      48: aload_0
      49: getfield      #23                 // Field this$1:Lio/grpc/xds/XdsServerWrapper$DiscoveryState;
      52: aload_1
      53: invokestatic  #68                 // Method io/grpc/xds/XdsServerWrapper$DiscoveryState.access$1900:(Lio/grpc/xds/XdsServerWrapper$DiscoveryState;Lio/grpc/StatusException;)V
      56: return
}
