Compiled from "XdsServerWrapper.java"
final class io.grpc.xds.XdsServerWrapper$DiscoveryState implements io.grpc.xds.XdsClient$LdsResourceWatcher {
  private final java.lang.String resourceName;

  private final java.util.Map<java.lang.String, io.grpc.xds.XdsServerWrapper$DiscoveryState$RouteDiscoveryState> routeDiscoveryStates;

  private final java.util.Set<java.lang.String> pendingRds;

  private java.util.List<io.grpc.xds.EnvoyServerProtoData$FilterChain> filterChains;

  private io.grpc.xds.EnvoyServerProtoData$FilterChain defaultFilterChain;

  private boolean stopped;

  private final java.util.Map<io.grpc.xds.EnvoyServerProtoData$FilterChain, java.util.concurrent.atomic.AtomicReference<io.grpc.xds.XdsServerWrapper$ServerRoutingConfig>> savedRdsRoutingConfigRef;

  private final io.grpc.ServerInterceptor noopInterceptor;

  final io.grpc.xds.XdsServerWrapper this$0;

  private io.grpc.xds.XdsServerWrapper$DiscoveryState(io.grpc.xds.XdsServerWrapper, java.lang.String);
    Code:
       0: aload_0
       1: aload_1
       2: putfield      #112                // Field this$0:Lio/grpc/xds/XdsServerWrapper;
       5: aload_0
       6: invokespecial #115                // Method java/lang/Object."<init>":()V
       9: aload_0
      10: new           #117                // class java/util/HashMap
      13: dup
      14: invokespecial #118                // Method java/util/HashMap."<init>":()V
      17: putfield      #120                // Field routeDiscoveryStates:Ljava/util/Map;
      20: aload_0
      21: new           #122                // class java/util/HashSet
      24: dup
      25: invokespecial #123                // Method java/util/HashSet."<init>":()V
      28: putfield      #125                // Field pendingRds:Ljava/util/Set;
      31: aload_0
      32: new           #127                // class java/util/ArrayList
      35: dup
      36: invokespecial #128                // Method java/util/ArrayList."<init>":()V
      39: putfield      #130                // Field filterChains:Ljava/util/List;
      42: aload_0
      43: new           #117                // class java/util/HashMap
      46: dup
      47: invokespecial #118                // Method java/util/HashMap."<init>":()V
      50: putfield      #132                // Field savedRdsRoutingConfigRef:Ljava/util/Map;
      53: aload_0
      54: new           #23                 // class io/grpc/xds/XdsServerWrapper$DiscoveryState$1
      57: dup
      58: aload_0
      59: invokespecial #135                // Method io/grpc/xds/XdsServerWrapper$DiscoveryState$1."<init>":(Lio/grpc/xds/XdsServerWrapper$DiscoveryState;)V
      62: putfield      #137                // Field noopInterceptor:Lio/grpc/ServerInterceptor;
      65: aload_0
      66: aload_2
      67: ldc           #138                // String resourceName
      69: invokestatic  #144                // Method com/google/common/base/Preconditions.checkNotNull:(Ljava/lang/Object;Ljava/lang/Object;)Ljava/lang/Object;
      72: checkcast     #146                // class java/lang/String
      75: putfield      #148                // Field resourceName:Ljava/lang/String;
      78: aload_1
      79: invokestatic  #152                // Method io/grpc/xds/XdsServerWrapper.access$800:(Lio/grpc/xds/XdsServerWrapper;)Lio/grpc/xds/XdsClient;
      82: aload_2
      83: aload_0
      84: invokevirtual #156                // Method io/grpc/xds/XdsClient.watchLdsResource:(Ljava/lang/String;Lio/grpc/xds/XdsClient$LdsResourceWatcher;)V
      87: return

  public void onChanged(io.grpc.xds.XdsClient$LdsUpdate);
    Code:
       0: aload_0
       1: getfield      #112                // Field this$0:Lio/grpc/xds/XdsServerWrapper;
       4: invokestatic  #164                // Method io/grpc/xds/XdsServerWrapper.access$1800:(Lio/grpc/xds/XdsServerWrapper;)Lio/grpc/SynchronizationContext;
       7: new           #21                 // class io/grpc/xds/XdsServerWrapper$DiscoveryState$2
      10: dup
      11: aload_0
      12: aload_1
      13: invokespecial #167                // Method io/grpc/xds/XdsServerWrapper$DiscoveryState$2."<init>":(Lio/grpc/xds/XdsServerWrapper$DiscoveryState;Lio/grpc/xds/XdsClient$LdsUpdate;)V
      16: invokevirtual #171                // Method io/grpc/SynchronizationContext.execute:(Ljava/lang/Runnable;)V
      19: return

  public void onResourceDoesNotExist(java.lang.String);
    Code:
       0: aload_0
       1: getfield      #112                // Field this$0:Lio/grpc/xds/XdsServerWrapper;
       4: invokestatic  #164                // Method io/grpc/xds/XdsServerWrapper.access$1800:(Lio/grpc/xds/XdsServerWrapper;)Lio/grpc/SynchronizationContext;
       7: new           #19                 // class io/grpc/xds/XdsServerWrapper$DiscoveryState$3
      10: dup
      11: aload_0
      12: aload_1
      13: invokespecial #178                // Method io/grpc/xds/XdsServerWrapper$DiscoveryState$3."<init>":(Lio/grpc/xds/XdsServerWrapper$DiscoveryState;Ljava/lang/String;)V
      16: invokevirtual #171                // Method io/grpc/SynchronizationContext.execute:(Ljava/lang/Runnable;)V
      19: return

  public void onError(io.grpc.Status);
    Code:
       0: aload_0
       1: getfield      #112                // Field this$0:Lio/grpc/xds/XdsServerWrapper;
       4: invokestatic  #164                // Method io/grpc/xds/XdsServerWrapper.access$1800:(Lio/grpc/xds/XdsServerWrapper;)Lio/grpc/SynchronizationContext;
       7: new           #17                 // class io/grpc/xds/XdsServerWrapper$DiscoveryState$4
      10: dup
      11: aload_0
      12: aload_1
      13: invokespecial #183                // Method io/grpc/xds/XdsServerWrapper$DiscoveryState$4."<init>":(Lio/grpc/xds/XdsServerWrapper$DiscoveryState;Lio/grpc/Status;)V
      16: invokevirtual #171                // Method io/grpc/SynchronizationContext.execute:(Ljava/lang/Runnable;)V
      19: return

  private void shutdown();
    Code:
       0: aload_0
       1: iconst_1
       2: putfield      #188                // Field stopped:Z
       5: aload_0
       6: invokespecial #191                // Method cleanUpRouteDiscoveryStates:()V
       9: invokestatic  #195                // Method io/grpc/xds/XdsServerWrapper.access$000:()Ljava/util/logging/Logger;
      12: getstatic     #201                // Field java/util/logging/Level.FINE:Ljava/util/logging/Level;
      15: ldc           #203                // String Stop watching LDS resource {0}
      17: aload_0
      18: getfield      #148                // Field resourceName:Ljava/lang/String;
      21: invokevirtual #209                // Method java/util/logging/Logger.log:(Ljava/util/logging/Level;Ljava/lang/String;Ljava/lang/Object;)V
      24: aload_0
      25: getfield      #112                // Field this$0:Lio/grpc/xds/XdsServerWrapper;
      28: invokestatic  #152                // Method io/grpc/xds/XdsServerWrapper.access$800:(Lio/grpc/xds/XdsServerWrapper;)Lio/grpc/xds/XdsClient;
      31: aload_0
      32: getfield      #148                // Field resourceName:Ljava/lang/String;
      35: aload_0
      36: invokevirtual #212                // Method io/grpc/xds/XdsClient.cancelLdsResourceWatch:(Ljava/lang/String;Lio/grpc/xds/XdsClient$LdsResourceWatcher;)V
      39: aload_0
      40: invokespecial #216                // Method getSuppliersInUse:()Ljava/util/List;
      43: astore_1
      44: aload_0
      45: getfield      #112                // Field this$0:Lio/grpc/xds/XdsServerWrapper;
      48: invokestatic  #220                // Method io/grpc/xds/XdsServerWrapper.access$2300:(Lio/grpc/xds/XdsServerWrapper;)Lio/grpc/xds/FilterChainSelectorManager;
      51: getstatic     #224                // Field io/grpc/xds/FilterChainMatchingProtocolNegotiators$FilterChainMatchingHandler$FilterChainSelector.NO_FILTER_CHAIN:Lio/grpc/xds/FilterChainMatchingProtocolNegotiators$FilterChainMatchingHandler$FilterChainSelector;
      54: invokevirtual #230                // Method io/grpc/xds/FilterChainSelectorManager.updateSelector:(Lio/grpc/xds/FilterChainMatchingProtocolNegotiators$FilterChainMatchingHandler$FilterChainSelector;)V
      57: aload_1
      58: invokeinterface #236,  1          // InterfaceMethod java/util/List.iterator:()Ljava/util/Iterator;
      63: astore_2
      64: aload_2
      65: invokeinterface #242,  1          // InterfaceMethod java/util/Iterator.hasNext:()Z
      70: ifeq          90
      73: aload_2
      74: invokeinterface #246,  1          // InterfaceMethod java/util/Iterator.next:()Ljava/lang/Object;
      79: checkcast     #248                // class io/grpc/xds/internal/sds/SslContextProviderSupplier
      82: astore_3
      83: aload_3
      84: invokevirtual #251                // Method io/grpc/xds/internal/sds/SslContextProviderSupplier.close:()V
      87: goto          64
      90: aload_0
      91: invokespecial #254                // Method releaseSuppliersInFlight:()V
      94: return

  private void updateSelector();
    Code:
       0: new           #117                // class java/util/HashMap
       3: dup
       4: invokespecial #118                // Method java/util/HashMap."<init>":()V
       7: astore_1
       8: aload_0
       9: getfield      #132                // Field savedRdsRoutingConfigRef:Ljava/util/Map;
      12: invokeinterface #263,  1          // InterfaceMethod java/util/Map.clear:()V
      17: aload_0
      18: getfield      #130                // Field filterChains:Ljava/util/List;
      21: invokeinterface #236,  1          // InterfaceMethod java/util/List.iterator:()Ljava/util/Iterator;
      26: astore_2
      27: aload_2
      28: invokeinterface #242,  1          // InterfaceMethod java/util/Iterator.hasNext:()Z
      33: ifeq          62
      36: aload_2
      37: invokeinterface #246,  1          // InterfaceMethod java/util/Iterator.next:()Ljava/lang/Object;
      42: checkcast     #25                 // class io/grpc/xds/EnvoyServerProtoData$FilterChain
      45: astore_3
      46: aload_1
      47: aload_3
      48: aload_0
      49: aload_3
      50: invokespecial #267                // Method generateRoutingConfig:(Lio/grpc/xds/EnvoyServerProtoData$FilterChain;)Ljava/util/concurrent/atomic/AtomicReference;
      53: invokeinterface #270,  3          // InterfaceMethod java/util/Map.put:(Ljava/lang/Object;Ljava/lang/Object;)Ljava/lang/Object;
      58: pop
      59: goto          27
      62: new           #43                 // class io/grpc/xds/FilterChainMatchingProtocolNegotiators$FilterChainMatchingHandler$FilterChainSelector
      65: dup
      66: aload_1
      67: invokestatic  #276                // Method java/util/Collections.unmodifiableMap:(Ljava/util/Map;)Ljava/util/Map;
      70: aload_0
      71: getfield      #278                // Field defaultFilterChain:Lio/grpc/xds/EnvoyServerProtoData$FilterChain;
      74: ifnonnull     81
      77: aconst_null
      78: goto          88
      81: aload_0
      82: getfield      #278                // Field defaultFilterChain:Lio/grpc/xds/EnvoyServerProtoData$FilterChain;
      85: invokevirtual #282                // Method io/grpc/xds/EnvoyServerProtoData$FilterChain.getSslContextProviderSupplier:()Lio/grpc/xds/internal/sds/SslContextProviderSupplier;
      88: aload_0
      89: getfield      #278                // Field defaultFilterChain:Lio/grpc/xds/EnvoyServerProtoData$FilterChain;
      92: ifnonnull     105
      95: new           #284                // class java/util/concurrent/atomic/AtomicReference
      98: dup
      99: invokespecial #285                // Method java/util/concurrent/atomic/AtomicReference."<init>":()V
     102: goto          113
     105: aload_0
     106: aload_0
     107: getfield      #278                // Field defaultFilterChain:Lio/grpc/xds/EnvoyServerProtoData$FilterChain;
     110: invokespecial #267                // Method generateRoutingConfig:(Lio/grpc/xds/EnvoyServerProtoData$FilterChain;)Ljava/util/concurrent/atomic/AtomicReference;
     113: invokespecial #288                // Method io/grpc/xds/FilterChainMatchingProtocolNegotiators$FilterChainMatchingHandler$FilterChainSelector."<init>":(Ljava/util/Map;Lio/grpc/xds/internal/sds/SslContextProviderSupplier;Ljava/util/concurrent/atomic/AtomicReference;)V
     116: astore_2
     117: aload_0
     118: invokespecial #216                // Method getSuppliersInUse:()Ljava/util/List;
     121: astore_3
     122: invokestatic  #195                // Method io/grpc/xds/XdsServerWrapper.access$000:()Ljava/util/logging/Logger;
     125: getstatic     #291                // Field java/util/logging/Level.FINEST:Ljava/util/logging/Level;
     128: ldc_w         #293                // String Updating selector {0}
     131: aload_2
     132: invokevirtual #209                // Method java/util/logging/Logger.log:(Ljava/util/logging/Level;Ljava/lang/String;Ljava/lang/Object;)V
     135: aload_0
     136: getfield      #112                // Field this$0:Lio/grpc/xds/XdsServerWrapper;
     139: invokestatic  #220                // Method io/grpc/xds/XdsServerWrapper.access$2300:(Lio/grpc/xds/XdsServerWrapper;)Lio/grpc/xds/FilterChainSelectorManager;
     142: aload_2
     143: invokevirtual #230                // Method io/grpc/xds/FilterChainSelectorManager.updateSelector:(Lio/grpc/xds/FilterChainMatchingProtocolNegotiators$FilterChainMatchingHandler$FilterChainSelector;)V
     146: aload_3
     147: invokeinterface #236,  1          // InterfaceMethod java/util/List.iterator:()Ljava/util/Iterator;
     152: astore        4
     154: aload         4
     156: invokeinterface #242,  1          // InterfaceMethod java/util/Iterator.hasNext:()Z
     161: ifeq          184
     164: aload         4
     166: invokeinterface #246,  1          // InterfaceMethod java/util/Iterator.next:()Ljava/lang/Object;
     171: checkcast     #248                // class io/grpc/xds/internal/sds/SslContextProviderSupplier
     174: astore        5
     176: aload         5
     178: invokevirtual #251                // Method io/grpc/xds/internal/sds/SslContextProviderSupplier.close:()V
     181: goto          154
     184: aload_0
     185: getfield      #112                // Field this$0:Lio/grpc/xds/XdsServerWrapper;
     188: invokestatic  #297                // Method io/grpc/xds/XdsServerWrapper.access$700:(Lio/grpc/xds/XdsServerWrapper;)V
     191: return

  private java.util.concurrent.atomic.AtomicReference<io.grpc.xds.XdsServerWrapper$ServerRoutingConfig> generateRoutingConfig(io.grpc.xds.EnvoyServerProtoData$FilterChain);
    Code:
       0: aload_1
       1: invokevirtual #306                // Method io/grpc/xds/EnvoyServerProtoData$FilterChain.getHttpConnectionManager:()Lio/grpc/xds/HttpConnectionManager;
       4: astore_2
       5: aload_2
       6: invokevirtual #312                // Method io/grpc/xds/HttpConnectionManager.virtualHosts:()Lcom/google/common/collect/ImmutableList;
       9: ifnull        41
      12: aload_0
      13: aload_2
      14: invokevirtual #315                // Method io/grpc/xds/HttpConnectionManager.httpFilterConfigs:()Lcom/google/common/collect/ImmutableList;
      17: aload_2
      18: invokevirtual #312                // Method io/grpc/xds/HttpConnectionManager.virtualHosts:()Lcom/google/common/collect/ImmutableList;
      21: invokespecial #319                // Method generatePerRouteInterceptors:(Ljava/util/List;Ljava/util/List;)Lcom/google/common/collect/ImmutableMap;
      24: astore_3
      25: new           #284                // class java/util/concurrent/atomic/AtomicReference
      28: dup
      29: aload_2
      30: invokevirtual #312                // Method io/grpc/xds/HttpConnectionManager.virtualHosts:()Lcom/google/common/collect/ImmutableList;
      33: aload_3
      34: invokestatic  #323                // Method io/grpc/xds/XdsServerWrapper$ServerRoutingConfig.create:(Lcom/google/common/collect/ImmutableList;Lcom/google/common/collect/ImmutableMap;)Lio/grpc/xds/XdsServerWrapper$ServerRoutingConfig;
      37: invokespecial #326                // Method java/util/concurrent/atomic/AtomicReference."<init>":(Ljava/lang/Object;)V
      40: areturn
      41: aload_0
      42: getfield      #120                // Field routeDiscoveryStates:Ljava/util/Map;
      45: aload_2
      46: invokevirtual #330                // Method io/grpc/xds/HttpConnectionManager.rdsName:()Ljava/lang/String;
      49: invokeinterface #334,  2          // InterfaceMethod java/util/Map.get:(Ljava/lang/Object;)Ljava/lang/Object;
      54: checkcast     #12                 // class io/grpc/xds/XdsServerWrapper$DiscoveryState$RouteDiscoveryState
      57: astore_3
      58: aload_3
      59: ldc_w         #336                // String rds
      62: invokestatic  #144                // Method com/google/common/base/Preconditions.checkNotNull:(Ljava/lang/Object;Ljava/lang/Object;)Ljava/lang/Object;
      65: pop
      66: new           #284                // class java/util/concurrent/atomic/AtomicReference
      69: dup
      70: invokespecial #285                // Method java/util/concurrent/atomic/AtomicReference."<init>":()V
      73: astore        4
      75: aload_3
      76: invokestatic  #340                // Method io/grpc/xds/XdsServerWrapper$DiscoveryState$RouteDiscoveryState.access$2400:(Lio/grpc/xds/XdsServerWrapper$DiscoveryState$RouteDiscoveryState;)Lcom/google/common/collect/ImmutableList;
      79: ifnull        117
      82: aload_0
      83: aload_2
      84: invokevirtual #315                // Method io/grpc/xds/HttpConnectionManager.httpFilterConfigs:()Lcom/google/common/collect/ImmutableList;
      87: aload_3
      88: invokestatic  #340                // Method io/grpc/xds/XdsServerWrapper$DiscoveryState$RouteDiscoveryState.access$2400:(Lio/grpc/xds/XdsServerWrapper$DiscoveryState$RouteDiscoveryState;)Lcom/google/common/collect/ImmutableList;
      91: invokespecial #319                // Method generatePerRouteInterceptors:(Ljava/util/List;Ljava/util/List;)Lcom/google/common/collect/ImmutableMap;
      94: astore        5
      96: aload_3
      97: invokestatic  #340                // Method io/grpc/xds/XdsServerWrapper$DiscoveryState$RouteDiscoveryState.access$2400:(Lio/grpc/xds/XdsServerWrapper$DiscoveryState$RouteDiscoveryState;)Lcom/google/common/collect/ImmutableList;
     100: aload         5
     102: invokestatic  #323                // Method io/grpc/xds/XdsServerWrapper$ServerRoutingConfig.create:(Lcom/google/common/collect/ImmutableList;Lcom/google/common/collect/ImmutableMap;)Lio/grpc/xds/XdsServerWrapper$ServerRoutingConfig;
     105: astore        6
     107: aload         4
     109: aload         6
     111: invokevirtual #343                // Method java/util/concurrent/atomic/AtomicReference.set:(Ljava/lang/Object;)V
     114: goto          125
     117: aload         4
     119: getstatic     #347                // Field io/grpc/xds/XdsServerWrapper$ServerRoutingConfig.FAILING_ROUTING_CONFIG:Lio/grpc/xds/XdsServerWrapper$ServerRoutingConfig;
     122: invokevirtual #343                // Method java/util/concurrent/atomic/AtomicReference.set:(Ljava/lang/Object;)V
     125: aload_0
     126: getfield      #132                // Field savedRdsRoutingConfigRef:Ljava/util/Map;
     129: aload_1
     130: aload         4
     132: invokeinterface #270,  3          // InterfaceMethod java/util/Map.put:(Ljava/lang/Object;Ljava/lang/Object;)Ljava/lang/Object;
     137: pop
     138: aload         4
     140: areturn

  private com.google.common.collect.ImmutableMap<io.grpc.xds.VirtualHost$Route, io.grpc.ServerInterceptor> generatePerRouteInterceptors(java.util.List<io.grpc.xds.Filter$NamedFilterConfig>, java.util.List<io.grpc.xds.VirtualHost>);
    Code:
       0: new           #59                 // class com/google/common/collect/ImmutableMap$Builder
       3: dup
       4: invokespecial #359                // Method com/google/common/collect/ImmutableMap$Builder."<init>":()V
       7: astore_3
       8: aload_2
       9: invokeinterface #236,  1          // InterfaceMethod java/util/List.iterator:()Ljava/util/Iterator;
      14: astore        4
      16: aload         4
      18: invokeinterface #242,  1          // InterfaceMethod java/util/Iterator.hasNext:()Z
      23: ifeq          287
      26: aload         4
      28: invokeinterface #246,  1          // InterfaceMethod java/util/Iterator.next:()Ljava/lang/Object;
      33: checkcast     #48                 // class io/grpc/xds/VirtualHost
      36: astore        5
      38: aload         5
      40: invokevirtual #362                // Method io/grpc/xds/VirtualHost.routes:()Lcom/google/common/collect/ImmutableList;
      43: invokevirtual #367                // Method com/google/common/collect/ImmutableList.iterator:()Lcom/google/common/collect/UnmodifiableIterator;
      46: astore        6
      48: aload         6
      50: invokeinterface #242,  1          // InterfaceMethod java/util/Iterator.hasNext:()Z
      55: ifeq          284
      58: aload         6
      60: invokeinterface #246,  1          // InterfaceMethod java/util/Iterator.next:()Ljava/lang/Object;
      65: checkcast     #46                 // class io/grpc/xds/VirtualHost$Route
      68: astore        7
      70: new           #127                // class java/util/ArrayList
      73: dup
      74: invokespecial #128                // Method java/util/ArrayList."<init>":()V
      77: astore        8
      79: new           #117                // class java/util/HashMap
      82: dup
      83: aload         5
      85: invokevirtual #371                // Method io/grpc/xds/VirtualHost.filterConfigOverrides:()Lcom/google/common/collect/ImmutableMap;
      88: invokespecial #374                // Method java/util/HashMap."<init>":(Ljava/util/Map;)V
      91: astore        9
      93: aload         9
      95: aload         7
      97: invokevirtual #375                // Method io/grpc/xds/VirtualHost$Route.filterConfigOverrides:()Lcom/google/common/collect/ImmutableMap;
     100: invokeinterface #378,  2          // InterfaceMethod java/util/Map.putAll:(Ljava/util/Map;)V
     105: aload_1
     106: ifnull        264
     109: aload_1
     110: invokeinterface #236,  1          // InterfaceMethod java/util/List.iterator:()Ljava/util/Iterator;
     115: astore        10
     117: aload         10
     119: invokeinterface #242,  1          // InterfaceMethod java/util/Iterator.hasNext:()Z
     124: ifeq          264
     127: aload         10
     129: invokeinterface #246,  1          // InterfaceMethod java/util/Iterator.next:()Ljava/lang/Object;
     134: checkcast     #56                 // class io/grpc/xds/Filter$NamedFilterConfig
     137: astore        11
     139: aload         11
     141: getfield      #382                // Field io/grpc/xds/Filter$NamedFilterConfig.filterConfig:Lio/grpc/xds/Filter$FilterConfig;
     144: astore        12
     146: aload_0
     147: getfield      #112                // Field this$0:Lio/grpc/xds/XdsServerWrapper;
     150: invokestatic  #386                // Method io/grpc/xds/XdsServerWrapper.access$2500:(Lio/grpc/xds/XdsServerWrapper;)Lio/grpc/xds/FilterRegistry;
     153: aload         12
     155: invokeinterface #389,  1          // InterfaceMethod io/grpc/xds/Filter$FilterConfig.typeUrl:()Ljava/lang/String;
     160: invokevirtual #394                // Method io/grpc/xds/FilterRegistry.get:(Ljava/lang/String;)Lio/grpc/xds/Filter;
     163: astore        13
     165: aload         13
     167: instanceof    #66                 // class io/grpc/xds/Filter$ServerInterceptorBuilder
     170: ifeq          220
     173: aload         13
     175: checkcast     #66                 // class io/grpc/xds/Filter$ServerInterceptorBuilder
     178: aload         12
     180: aload         9
     182: aload         11
     184: getfield      #397                // Field io/grpc/xds/Filter$NamedFilterConfig.name:Ljava/lang/String;
     187: invokeinterface #334,  2          // InterfaceMethod java/util/Map.get:(Ljava/lang/Object;)Ljava/lang/Object;
     192: checkcast     #51                 // class io/grpc/xds/Filter$FilterConfig
     195: invokeinterface #401,  3          // InterfaceMethod io/grpc/xds/Filter$ServerInterceptorBuilder.buildServerInterceptor:(Lio/grpc/xds/Filter$FilterConfig;Lio/grpc/xds/Filter$FilterConfig;)Lio/grpc/ServerInterceptor;
     200: astore        14
     202: aload         14
     204: ifnull        217
     207: aload         8
     209: aload         14
     211: invokeinterface #405,  2          // InterfaceMethod java/util/List.add:(Ljava/lang/Object;)Z
     216: pop
     217: goto          261
     220: invokestatic  #195                // Method io/grpc/xds/XdsServerWrapper.access$000:()Ljava/util/logging/Logger;
     223: getstatic     #408                // Field java/util/logging/Level.WARNING:Ljava/util/logging/Level;
     226: new           #410                // class java/lang/StringBuilder
     229: dup
     230: invokespecial #411                // Method java/lang/StringBuilder."<init>":()V
     233: ldc_w         #413                // String HttpFilterConfig(type URL:
     236: invokevirtual #417                // Method java/lang/StringBuilder.append:(Ljava/lang/String;)Ljava/lang/StringBuilder;
     239: aload         12
     241: invokeinterface #389,  1          // InterfaceMethod io/grpc/xds/Filter$FilterConfig.typeUrl:()Ljava/lang/String;
     246: invokevirtual #417                // Method java/lang/StringBuilder.append:(Ljava/lang/String;)Ljava/lang/StringBuilder;
     249: ldc_w         #419                // String ) is not supported on server-side. Probably a bug at ClientXdsClient verification.
     252: invokevirtual #417                // Method java/lang/StringBuilder.append:(Ljava/lang/String;)Ljava/lang/StringBuilder;
     255: invokevirtual #422                // Method java/lang/StringBuilder.toString:()Ljava/lang/String;
     258: invokevirtual #425                // Method java/util/logging/Logger.log:(Ljava/util/logging/Level;Ljava/lang/String;)V
     261: goto          117
     264: aload_0
     265: aload         8
     267: invokespecial #429                // Method combineInterceptors:(Ljava/util/List;)Lio/grpc/ServerInterceptor;
     270: astore        10
     272: aload_3
     273: aload         7
     275: aload         10
     277: invokevirtual #432                // Method com/google/common/collect/ImmutableMap$Builder.put:(Ljava/lang/Object;Ljava/lang/Object;)Lcom/google/common/collect/ImmutableMap$Builder;
     280: pop
     281: goto          48
     284: goto          16
     287: aload_3
     288: invokevirtual #435                // Method com/google/common/collect/ImmutableMap$Builder.build:()Lcom/google/common/collect/ImmutableMap;
     291: areturn

  private io.grpc.ServerInterceptor combineInterceptors(java.util.List<io.grpc.ServerInterceptor>);
    Code:
       0: aload_1
       1: invokeinterface #458,  1          // InterfaceMethod java/util/List.isEmpty:()Z
       6: ifeq          14
       9: aload_0
      10: getfield      #137                // Field noopInterceptor:Lio/grpc/ServerInterceptor;
      13: areturn
      14: aload_1
      15: invokeinterface #462,  1          // InterfaceMethod java/util/List.size:()I
      20: iconst_1
      21: if_icmpne     35
      24: aload_1
      25: iconst_0
      26: invokeinterface #465,  2          // InterfaceMethod java/util/List.get:(I)Ljava/lang/Object;
      31: checkcast     #467                // class io/grpc/ServerInterceptor
      34: areturn
      35: new           #15                 // class io/grpc/xds/XdsServerWrapper$DiscoveryState$5
      38: dup
      39: aload_0
      40: aload_1
      41: invokespecial #470                // Method io/grpc/xds/XdsServerWrapper$DiscoveryState$5."<init>":(Lio/grpc/xds/XdsServerWrapper$DiscoveryState;Ljava/util/List;)V
      44: areturn

  private void handleConfigNotFound(io.grpc.StatusException);
    Code:
       0: aload_0
       1: invokespecial #191                // Method cleanUpRouteDiscoveryStates:()V
       4: aload_0
       5: invokespecial #216                // Method getSuppliersInUse:()Ljava/util/List;
       8: astore_2
       9: aload_0
      10: getfield      #112                // Field this$0:Lio/grpc/xds/XdsServerWrapper;
      13: invokestatic  #220                // Method io/grpc/xds/XdsServerWrapper.access$2300:(Lio/grpc/xds/XdsServerWrapper;)Lio/grpc/xds/FilterChainSelectorManager;
      16: getstatic     #224                // Field io/grpc/xds/FilterChainMatchingProtocolNegotiators$FilterChainMatchingHandler$FilterChainSelector.NO_FILTER_CHAIN:Lio/grpc/xds/FilterChainMatchingProtocolNegotiators$FilterChainMatchingHandler$FilterChainSelector;
      19: invokevirtual #230                // Method io/grpc/xds/FilterChainSelectorManager.updateSelector:(Lio/grpc/xds/FilterChainMatchingProtocolNegotiators$FilterChainMatchingHandler$FilterChainSelector;)V
      22: aload_2
      23: invokeinterface #236,  1          // InterfaceMethod java/util/List.iterator:()Ljava/util/Iterator;
      28: astore_3
      29: aload_3
      30: invokeinterface #242,  1          // InterfaceMethod java/util/Iterator.hasNext:()Z
      35: ifeq          57
      38: aload_3
      39: invokeinterface #246,  1          // InterfaceMethod java/util/Iterator.next:()Ljava/lang/Object;
      44: checkcast     #248                // class io/grpc/xds/internal/sds/SslContextProviderSupplier
      47: astore        4
      49: aload         4
      51: invokevirtual #251                // Method io/grpc/xds/internal/sds/SslContextProviderSupplier.close:()V
      54: goto          29
      57: aload_0
      58: getfield      #112                // Field this$0:Lio/grpc/xds/XdsServerWrapper;
      61: invokestatic  #476                // Method io/grpc/xds/XdsServerWrapper.access$2600:(Lio/grpc/xds/XdsServerWrapper;)Lio/grpc/SynchronizationContext$ScheduledHandle;
      64: ifnull        77
      67: aload_0
      68: getfield      #112                // Field this$0:Lio/grpc/xds/XdsServerWrapper;
      71: invokestatic  #476                // Method io/grpc/xds/XdsServerWrapper.access$2600:(Lio/grpc/xds/XdsServerWrapper;)Lio/grpc/SynchronizationContext$ScheduledHandle;
      74: invokevirtual #479                // Method io/grpc/SynchronizationContext$ScheduledHandle.cancel:()V
      77: aload_0
      78: getfield      #112                // Field this$0:Lio/grpc/xds/XdsServerWrapper;
      81: invokestatic  #483                // Method io/grpc/xds/XdsServerWrapper.access$300:(Lio/grpc/xds/XdsServerWrapper;)Lio/grpc/Server;
      84: invokevirtual #488                // Method io/grpc/Server.isShutdown:()Z
      87: ifne          101
      90: aload_0
      91: getfield      #112                // Field this$0:Lio/grpc/xds/XdsServerWrapper;
      94: invokestatic  #483                // Method io/grpc/xds/XdsServerWrapper.access$300:(Lio/grpc/xds/XdsServerWrapper;)Lio/grpc/Server;
      97: invokevirtual #491                // Method io/grpc/Server.shutdown:()Lio/grpc/Server;
     100: pop
     101: aload_0
     102: getfield      #112                // Field this$0:Lio/grpc/xds/XdsServerWrapper;
     105: iconst_0
     106: invokestatic  #495                // Method io/grpc/xds/XdsServerWrapper.access$2102:(Lio/grpc/xds/XdsServerWrapper;Z)Z
     109: pop
     110: aload_0
     111: getfield      #112                // Field this$0:Lio/grpc/xds/XdsServerWrapper;
     114: invokestatic  #499                // Method io/grpc/xds/XdsServerWrapper.access$2200:(Lio/grpc/xds/XdsServerWrapper;)Lio/grpc/xds/XdsServerBuilder$XdsServingStatusListener;
     117: aload_1
     118: invokeinterface #503,  2          // InterfaceMethod io/grpc/xds/XdsServerBuilder$XdsServingStatusListener.onNotServing:(Ljava/lang/Throwable;)V
     123: return

  private void cleanUpRouteDiscoveryStates();
    Code:
       0: aload_0
       1: getfield      #120                // Field routeDiscoveryStates:Ljava/util/Map;
       4: invokeinterface #509,  1          // InterfaceMethod java/util/Map.values:()Ljava/util/Collection;
       9: invokeinterface #512,  1          // InterfaceMethod java/util/Collection.iterator:()Ljava/util/Iterator;
      14: astore_1
      15: aload_1
      16: invokeinterface #242,  1          // InterfaceMethod java/util/Iterator.hasNext:()Z
      21: ifeq          67
      24: aload_1
      25: invokeinterface #246,  1          // InterfaceMethod java/util/Iterator.next:()Ljava/lang/Object;
      30: checkcast     #12                 // class io/grpc/xds/XdsServerWrapper$DiscoveryState$RouteDiscoveryState
      33: astore_2
      34: aload_2
      35: invokestatic  #516                // Method io/grpc/xds/XdsServerWrapper$DiscoveryState$RouteDiscoveryState.access$2700:(Lio/grpc/xds/XdsServerWrapper$DiscoveryState$RouteDiscoveryState;)Ljava/lang/String;
      38: astore_3
      39: invokestatic  #195                // Method io/grpc/xds/XdsServerWrapper.access$000:()Ljava/util/logging/Logger;
      42: getstatic     #201                // Field java/util/logging/Level.FINE:Ljava/util/logging/Level;
      45: ldc_w         #518                // String Stop watching RDS resource {0}
      48: aload_3
      49: invokevirtual #209                // Method java/util/logging/Logger.log:(Ljava/util/logging/Level;Ljava/lang/String;Ljava/lang/Object;)V
      52: aload_0
      53: getfield      #112                // Field this$0:Lio/grpc/xds/XdsServerWrapper;
      56: invokestatic  #152                // Method io/grpc/xds/XdsServerWrapper.access$800:(Lio/grpc/xds/XdsServerWrapper;)Lio/grpc/xds/XdsClient;
      59: aload_3
      60: aload_2
      61: invokevirtual #522                // Method io/grpc/xds/XdsClient.cancelRdsResourceWatch:(Ljava/lang/String;Lio/grpc/xds/XdsClient$RdsResourceWatcher;)V
      64: goto          15
      67: aload_0
      68: getfield      #120                // Field routeDiscoveryStates:Ljava/util/Map;
      71: invokeinterface #263,  1          // InterfaceMethod java/util/Map.clear:()V
      76: aload_0
      77: getfield      #132                // Field savedRdsRoutingConfigRef:Ljava/util/Map;
      80: invokeinterface #263,  1          // InterfaceMethod java/util/Map.clear:()V
      85: return

  private java.util.List<io.grpc.xds.internal.sds.SslContextProviderSupplier> getSuppliersInUse();
    Code:
       0: new           #127                // class java/util/ArrayList
       3: dup
       4: invokespecial #128                // Method java/util/ArrayList."<init>":()V
       7: astore_1
       8: aload_0
       9: getfield      #112                // Field this$0:Lio/grpc/xds/XdsServerWrapper;
      12: invokestatic  #220                // Method io/grpc/xds/XdsServerWrapper.access$2300:(Lio/grpc/xds/XdsServerWrapper;)Lio/grpc/xds/FilterChainSelectorManager;
      15: invokevirtual #528                // Method io/grpc/xds/FilterChainSelectorManager.getSelectorToUpdateSelector:()Lio/grpc/xds/FilterChainMatchingProtocolNegotiators$FilterChainMatchingHandler$FilterChainSelector;
      18: astore_2
      19: aload_2
      20: ifnull        98
      23: aload_2
      24: invokevirtual #532                // Method io/grpc/xds/FilterChainMatchingProtocolNegotiators$FilterChainMatchingHandler$FilterChainSelector.getRoutingConfigs:()Ljava/util/Map;
      27: invokeinterface #536,  1          // InterfaceMethod java/util/Map.keySet:()Ljava/util/Set;
      32: invokeinterface #539,  1          // InterfaceMethod java/util/Set.iterator:()Ljava/util/Iterator;
      37: astore_3
      38: aload_3
      39: invokeinterface #242,  1          // InterfaceMethod java/util/Iterator.hasNext:()Z
      44: ifeq          81
      47: aload_3
      48: invokeinterface #246,  1          // InterfaceMethod java/util/Iterator.next:()Ljava/lang/Object;
      53: checkcast     #25                 // class io/grpc/xds/EnvoyServerProtoData$FilterChain
      56: astore        4
      58: aload         4
      60: invokevirtual #282                // Method io/grpc/xds/EnvoyServerProtoData$FilterChain.getSslContextProviderSupplier:()Lio/grpc/xds/internal/sds/SslContextProviderSupplier;
      63: ifnull        78
      66: aload_1
      67: aload         4
      69: invokevirtual #282                // Method io/grpc/xds/EnvoyServerProtoData$FilterChain.getSslContextProviderSupplier:()Lio/grpc/xds/internal/sds/SslContextProviderSupplier;
      72: invokeinterface #405,  2          // InterfaceMethod java/util/List.add:(Ljava/lang/Object;)Z
      77: pop
      78: goto          38
      81: aload_2
      82: invokevirtual #542                // Method io/grpc/xds/FilterChainMatchingProtocolNegotiators$FilterChainMatchingHandler$FilterChainSelector.getDefaultSslContextProviderSupplier:()Lio/grpc/xds/internal/sds/SslContextProviderSupplier;
      85: astore_3
      86: aload_3
      87: ifnull        98
      90: aload_1
      91: aload_3
      92: invokeinterface #405,  2          // InterfaceMethod java/util/List.add:(Ljava/lang/Object;)Z
      97: pop
      98: aload_1
      99: areturn

  private void releaseSuppliersInFlight();
    Code:
       0: aload_0
       1: getfield      #130                // Field filterChains:Ljava/util/List;
       4: invokeinterface #236,  1          // InterfaceMethod java/util/List.iterator:()Ljava/util/Iterator;
       9: astore_2
      10: aload_2
      11: invokeinterface #242,  1          // InterfaceMethod java/util/Iterator.hasNext:()Z
      16: ifeq          45
      19: aload_2
      20: invokeinterface #246,  1          // InterfaceMethod java/util/Iterator.next:()Ljava/lang/Object;
      25: checkcast     #25                 // class io/grpc/xds/EnvoyServerProtoData$FilterChain
      28: astore_3
      29: aload_3
      30: invokevirtual #282                // Method io/grpc/xds/EnvoyServerProtoData$FilterChain.getSslContextProviderSupplier:()Lio/grpc/xds/internal/sds/SslContextProviderSupplier;
      33: astore_1
      34: aload_1
      35: ifnull        42
      38: aload_1
      39: invokevirtual #251                // Method io/grpc/xds/internal/sds/SslContextProviderSupplier.close:()V
      42: goto          10
      45: aload_0
      46: getfield      #278                // Field defaultFilterChain:Lio/grpc/xds/EnvoyServerProtoData$FilterChain;
      49: ifnull        68
      52: aload_0
      53: getfield      #278                // Field defaultFilterChain:Lio/grpc/xds/EnvoyServerProtoData$FilterChain;
      56: invokevirtual #282                // Method io/grpc/xds/EnvoyServerProtoData$FilterChain.getSslContextProviderSupplier:()Lio/grpc/xds/internal/sds/SslContextProviderSupplier;
      59: dup
      60: astore_1
      61: ifnull        68
      64: aload_1
      65: invokevirtual #251                // Method io/grpc/xds/internal/sds/SslContextProviderSupplier.close:()V
      68: return

  private boolean isPermanentError(io.grpc.Status);
    Code:
       0: getstatic     #551                // Field io/grpc/Status$Code.INTERNAL:Lio/grpc/Status$Code;
       3: getstatic     #554                // Field io/grpc/Status$Code.INVALID_ARGUMENT:Lio/grpc/Status$Code;
       6: getstatic     #557                // Field io/grpc/Status$Code.FAILED_PRECONDITION:Lio/grpc/Status$Code;
       9: getstatic     #560                // Field io/grpc/Status$Code.PERMISSION_DENIED:Lio/grpc/Status$Code;
      12: getstatic     #563                // Field io/grpc/Status$Code.UNAUTHENTICATED:Lio/grpc/Status$Code;
      15: invokestatic  #569                // Method java/util/EnumSet.of:(Ljava/lang/Enum;Ljava/lang/Enum;Ljava/lang/Enum;Ljava/lang/Enum;Ljava/lang/Enum;)Ljava/util/EnumSet;
      18: aload_1
      19: invokevirtual #573                // Method io/grpc/Status.getCode:()Lio/grpc/Status$Code;
      22: invokevirtual #576                // Method java/util/EnumSet.contains:(Ljava/lang/Object;)Z
      25: ireturn

  io.grpc.xds.XdsServerWrapper$DiscoveryState(io.grpc.xds.XdsServerWrapper, java.lang.String, io.grpc.xds.XdsServerWrapper$1);
    Code:
       0: aload_0
       1: aload_1
       2: aload_2
       3: invokespecial #579                // Method "<init>":(Lio/grpc/xds/XdsServerWrapper;Ljava/lang/String;)V
       6: return

  static void access$500(io.grpc.xds.XdsServerWrapper$DiscoveryState);
    Code:
       0: aload_0
       1: invokespecial #586                // Method shutdown:()V
       4: return

  static boolean access$900(io.grpc.xds.XdsServerWrapper$DiscoveryState);
    Code:
       0: aload_0
       1: getfield      #188                // Field stopped:Z
       4: ireturn

  static java.util.Set access$1000(io.grpc.xds.XdsServerWrapper$DiscoveryState);
    Code:
       0: aload_0
       1: getfield      #125                // Field pendingRds:Ljava/util/Set;
       4: areturn

  static void access$1100(io.grpc.xds.XdsServerWrapper$DiscoveryState);
    Code:
       0: aload_0
       1: invokespecial #254                // Method releaseSuppliersInFlight:()V
       4: return

  static java.util.List access$1202(io.grpc.xds.XdsServerWrapper$DiscoveryState, java.util.List);
    Code:
       0: aload_0
       1: aload_1
       2: dup_x1
       3: putfield      #130                // Field filterChains:Ljava/util/List;
       6: areturn

  static io.grpc.xds.EnvoyServerProtoData$FilterChain access$1302(io.grpc.xds.XdsServerWrapper$DiscoveryState, io.grpc.xds.EnvoyServerProtoData$FilterChain);
    Code:
       0: aload_0
       1: aload_1
       2: dup_x1
       3: putfield      #278                // Field defaultFilterChain:Lio/grpc/xds/EnvoyServerProtoData$FilterChain;
       6: areturn

  static java.util.List access$1200(io.grpc.xds.XdsServerWrapper$DiscoveryState);
    Code:
       0: aload_0
       1: getfield      #130                // Field filterChains:Ljava/util/List;
       4: areturn

  static io.grpc.xds.EnvoyServerProtoData$FilterChain access$1300(io.grpc.xds.XdsServerWrapper$DiscoveryState);
    Code:
       0: aload_0
       1: getfield      #278                // Field defaultFilterChain:Lio/grpc/xds/EnvoyServerProtoData$FilterChain;
       4: areturn

  static java.util.Map access$1400(io.grpc.xds.XdsServerWrapper$DiscoveryState);
    Code:
       0: aload_0
       1: getfield      #120                // Field routeDiscoveryStates:Ljava/util/Map;
       4: areturn

  static void access$1700(io.grpc.xds.XdsServerWrapper$DiscoveryState);
    Code:
       0: aload_0
       1: invokespecial #604                // Method updateSelector:()V
       4: return

  static void access$1900(io.grpc.xds.XdsServerWrapper$DiscoveryState, io.grpc.StatusException);
    Code:
       0: aload_0
       1: aload_1
       2: invokespecial #608                // Method handleConfigNotFound:(Lio/grpc/StatusException;)V
       5: return

  static boolean access$2000(io.grpc.xds.XdsServerWrapper$DiscoveryState, io.grpc.Status);
    Code:
       0: aload_0
       1: aload_1
       2: invokespecial #612                // Method isPermanentError:(Lio/grpc/Status;)Z
       5: ireturn

  static java.util.Map access$3000(io.grpc.xds.XdsServerWrapper$DiscoveryState);
    Code:
       0: aload_0
       1: getfield      #132                // Field savedRdsRoutingConfigRef:Ljava/util/Map;
       4: areturn

  static com.google.common.collect.ImmutableMap access$3100(io.grpc.xds.XdsServerWrapper$DiscoveryState, java.util.List, java.util.List);
    Code:
       0: aload_0
       1: aload_1
       2: aload_2
       3: invokespecial #319                // Method generatePerRouteInterceptors:(Ljava/util/List;Ljava/util/List;)Lcom/google/common/collect/ImmutableMap;
       6: areturn
}
