Compiled from "XdsServerWrapper.java"
final class io.grpc.xds.XdsServerWrapper$RestartTask implements java.lang.Runnable {
  final io.grpc.xds.XdsServerWrapper this$0;

  private io.grpc.xds.XdsServerWrapper$RestartTask(io.grpc.xds.XdsServerWrapper);
    Code:
       0: aload_0
       1: aload_1
       2: putfield      #18                 // Field this$0:Lio/grpc/xds/XdsServerWrapper;
       5: aload_0
       6: invokespecial #21                 // Method java/lang/Object."<init>":()V
       9: return

  public void run();
    Code:
       0: aload_0
       1: getfield      #18                 // Field this$0:Lio/grpc/xds/XdsServerWrapper;
       4: invokestatic  #27                 // Method io/grpc/xds/XdsServerWrapper.access$700:(Lio/grpc/xds/XdsServerWrapper;)V
       7: return

  io.grpc.xds.XdsServerWrapper$RestartTask(io.grpc.xds.XdsServerWrapper, io.grpc.xds.XdsServerWrapper$1);
    Code:
       0: aload_0
       1: aload_1
       2: invokespecial #30                 // Method "<init>":(Lio/grpc/xds/XdsServerWrapper;)V
       5: return
}
