Compiled from "LogbackMetrics.java"
class io.micrometer.core.instrument.binder.logging.MetricsTurboFilter extends ch.qos.logback.classic.turbo.TurboFilter {
  private final io.micrometer.core.instrument.Counter errorCounter;

  private final io.micrometer.core.instrument.Counter warnCounter;

  private final io.micrometer.core.instrument.Counter infoCounter;

  private final io.micrometer.core.instrument.Counter debugCounter;

  private final io.micrometer.core.instrument.Counter traceCounter;

  io.micrometer.core.instrument.binder.logging.MetricsTurboFilter(io.micrometer.core.instrument.MeterRegistry, java.lang.Iterable<io.micrometer.core.instrument.Tag>);
    Code:
       0: aload_0
       1: invokespecial #1                  // Method ch/qos/logback/classic/turbo/TurboFilter."<init>":()V
       4: aload_0
       5: ldc           #7                  // String logback.events
       7: invokestatic  #9                  // InterfaceMethod io/micrometer/core/instrument/Counter.builder:(Ljava/lang/String;)Lio/micrometer/core/instrument/Counter$Builder;
      10: aload_2
      11: invokevirtual #15                 // Method io/micrometer/core/instrument/Counter$Builder.tags:(Ljava/lang/Iterable;)Lio/micrometer/core/instrument/Counter$Builder;
      14: iconst_2
      15: anewarray     #21                 // class java/lang/String
      18: dup
      19: iconst_0
      20: ldc           #23                 // String level
      22: aastore
      23: dup
      24: iconst_1
      25: ldc           #25                 // String error
      27: aastore
      28: invokevirtual #27                 // Method io/micrometer/core/instrument/Counter$Builder.tags:([Ljava/lang/String;)Lio/micrometer/core/instrument/Counter$Builder;
      31: ldc           #30                 // String Number of error level events that made it to the logs
      33: invokevirtual #32                 // Method io/micrometer/core/instrument/Counter$Builder.description:(Ljava/lang/String;)Lio/micrometer/core/instrument/Counter$Builder;
      36: ldc           #37                 // String events
      38: invokevirtual #39                 // Method io/micrometer/core/instrument/Counter$Builder.baseUnit:(Ljava/lang/String;)Lio/micrometer/core/instrument/Counter$Builder;
      41: aload_1
      42: invokevirtual #42                 // Method io/micrometer/core/instrument/Counter$Builder.register:(Lio/micrometer/core/instrument/MeterRegistry;)Lio/micrometer/core/instrument/Counter;
      45: putfield      #46                 // Field errorCounter:Lio/micrometer/core/instrument/Counter;
      48: aload_0
      49: ldc           #7                  // String logback.events
      51: invokestatic  #9                  // InterfaceMethod io/micrometer/core/instrument/Counter.builder:(Ljava/lang/String;)Lio/micrometer/core/instrument/Counter$Builder;
      54: aload_2
      55: invokevirtual #15                 // Method io/micrometer/core/instrument/Counter$Builder.tags:(Ljava/lang/Iterable;)Lio/micrometer/core/instrument/Counter$Builder;
      58: iconst_2
      59: anewarray     #21                 // class java/lang/String
      62: dup
      63: iconst_0
      64: ldc           #23                 // String level
      66: aastore
      67: dup
      68: iconst_1
      69: ldc           #52                 // String warn
      71: aastore
      72: invokevirtual #27                 // Method io/micrometer/core/instrument/Counter$Builder.tags:([Ljava/lang/String;)Lio/micrometer/core/instrument/Counter$Builder;
      75: ldc           #54                 // String Number of warn level events that made it to the logs
      77: invokevirtual #32                 // Method io/micrometer/core/instrument/Counter$Builder.description:(Ljava/lang/String;)Lio/micrometer/core/instrument/Counter$Builder;
      80: ldc           #37                 // String events
      82: invokevirtual #39                 // Method io/micrometer/core/instrument/Counter$Builder.baseUnit:(Ljava/lang/String;)Lio/micrometer/core/instrument/Counter$Builder;
      85: aload_1
      86: invokevirtual #42                 // Method io/micrometer/core/instrument/Counter$Builder.register:(Lio/micrometer/core/instrument/MeterRegistry;)Lio/micrometer/core/instrument/Counter;
      89: putfield      #56                 // Field warnCounter:Lio/micrometer/core/instrument/Counter;
      92: aload_0
      93: ldc           #7                  // String logback.events
      95: invokestatic  #9                  // InterfaceMethod io/micrometer/core/instrument/Counter.builder:(Ljava/lang/String;)Lio/micrometer/core/instrument/Counter$Builder;
      98: aload_2
      99: invokevirtual #15                 // Method io/micrometer/core/instrument/Counter$Builder.tags:(Ljava/lang/Iterable;)Lio/micrometer/core/instrument/Counter$Builder;
     102: iconst_2
     103: anewarray     #21                 // class java/lang/String
     106: dup
     107: iconst_0
     108: ldc           #23                 // String level
     110: aastore
     111: dup
     112: iconst_1
     113: ldc           #59                 // String info
     115: aastore
     116: invokevirtual #27                 // Method io/micrometer/core/instrument/Counter$Builder.tags:([Ljava/lang/String;)Lio/micrometer/core/instrument/Counter$Builder;
     119: ldc           #61                 // String Number of info level events that made it to the logs
     121: invokevirtual #32                 // Method io/micrometer/core/instrument/Counter$Builder.description:(Ljava/lang/String;)Lio/micrometer/core/instrument/Counter$Builder;
     124: ldc           #37                 // String events
     126: invokevirtual #39                 // Method io/micrometer/core/instrument/Counter$Builder.baseUnit:(Ljava/lang/String;)Lio/micrometer/core/instrument/Counter$Builder;
     129: aload_1
     130: invokevirtual #42                 // Method io/micrometer/core/instrument/Counter$Builder.register:(Lio/micrometer/core/instrument/MeterRegistry;)Lio/micrometer/core/instrument/Counter;
     133: putfield      #63                 // Field infoCounter:Lio/micrometer/core/instrument/Counter;
     136: aload_0
     137: ldc           #7                  // String logback.events
     139: invokestatic  #9                  // InterfaceMethod io/micrometer/core/instrument/Counter.builder:(Ljava/lang/String;)Lio/micrometer/core/instrument/Counter$Builder;
     142: aload_2
     143: invokevirtual #15                 // Method io/micrometer/core/instrument/Counter$Builder.tags:(Ljava/lang/Iterable;)Lio/micrometer/core/instrument/Counter$Builder;
     146: iconst_2
     147: anewarray     #21                 // class java/lang/String
     150: dup
     151: iconst_0
     152: ldc           #23                 // String level
     154: aastore
     155: dup
     156: iconst_1
     157: ldc           #66                 // String debug
     159: aastore
     160: invokevirtual #27                 // Method io/micrometer/core/instrument/Counter$Builder.tags:([Ljava/lang/String;)Lio/micrometer/core/instrument/Counter$Builder;
     163: ldc           #68                 // String Number of debug level events that made it to the logs
     165: invokevirtual #32                 // Method io/micrometer/core/instrument/Counter$Builder.description:(Ljava/lang/String;)Lio/micrometer/core/instrument/Counter$Builder;
     168: ldc           #37                 // String events
     170: invokevirtual #39                 // Method io/micrometer/core/instrument/Counter$Builder.baseUnit:(Ljava/lang/String;)Lio/micrometer/core/instrument/Counter$Builder;
     173: aload_1
     174: invokevirtual #42                 // Method io/micrometer/core/instrument/Counter$Builder.register:(Lio/micrometer/core/instrument/MeterRegistry;)Lio/micrometer/core/instrument/Counter;
     177: putfield      #70                 // Field debugCounter:Lio/micrometer/core/instrument/Counter;
     180: aload_0
     181: ldc           #7                  // String logback.events
     183: invokestatic  #9                  // InterfaceMethod io/micrometer/core/instrument/Counter.builder:(Ljava/lang/String;)Lio/micrometer/core/instrument/Counter$Builder;
     186: aload_2
     187: invokevirtual #15                 // Method io/micrometer/core/instrument/Counter$Builder.tags:(Ljava/lang/Iterable;)Lio/micrometer/core/instrument/Counter$Builder;
     190: iconst_2
     191: anewarray     #21                 // class java/lang/String
     194: dup
     195: iconst_0
     196: ldc           #23                 // String level
     198: aastore
     199: dup
     200: iconst_1
     201: ldc           #73                 // String trace
     203: aastore
     204: invokevirtual #27                 // Method io/micrometer/core/instrument/Counter$Builder.tags:([Ljava/lang/String;)Lio/micrometer/core/instrument/Counter$Builder;
     207: ldc           #75                 // String Number of trace level events that made it to the logs
     209: invokevirtual #32                 // Method io/micrometer/core/instrument/Counter$Builder.description:(Ljava/lang/String;)Lio/micrometer/core/instrument/Counter$Builder;
     212: ldc           #37                 // String events
     214: invokevirtual #39                 // Method io/micrometer/core/instrument/Counter$Builder.baseUnit:(Ljava/lang/String;)Lio/micrometer/core/instrument/Counter$Builder;
     217: aload_1
     218: invokevirtual #42                 // Method io/micrometer/core/instrument/Counter$Builder.register:(Lio/micrometer/core/instrument/MeterRegistry;)Lio/micrometer/core/instrument/Counter;
     221: putfield      #77                 // Field traceCounter:Lio/micrometer/core/instrument/Counter;
     224: return

  public ch.qos.logback.core.spi.FilterReply decide(org.slf4j.Marker, ch.qos.logback.classic.Logger, ch.qos.logback.classic.Level, java.lang.String, java.lang.Object[], java.lang.Throwable);
    Code:
       0: aload         4
       2: ifnonnull     9
       5: getstatic     #80                 // Field ch/qos/logback/core/spi/FilterReply.NEUTRAL:Lch/qos/logback/core/spi/FilterReply;
       8: areturn
       9: getstatic     #86                 // Field io/micrometer/core/instrument/binder/logging/LogbackMetrics.ignoreMetrics:Ljava/lang/ThreadLocal;
      12: invokevirtual #92                 // Method java/lang/ThreadLocal.get:()Ljava/lang/Object;
      15: checkcast     #98                 // class java/lang/Boolean
      18: astore        7
      20: aload         7
      22: ifnull        37
      25: aload         7
      27: invokevirtual #100                // Method java/lang/Boolean.booleanValue:()Z
      30: ifeq          37
      33: getstatic     #80                 // Field ch/qos/logback/core/spi/FilterReply.NEUTRAL:Lch/qos/logback/core/spi/FilterReply;
      36: areturn
      37: aload_3
      38: aload_2
      39: invokevirtual #104                // Method ch/qos/logback/classic/Logger.getEffectiveLevel:()Lch/qos/logback/classic/Level;
      42: invokevirtual #110                // Method ch/qos/logback/classic/Level.isGreaterOrEqual:(Lch/qos/logback/classic/Level;)Z
      45: ifeq          161
      48: aload_3
      49: invokevirtual #116                // Method ch/qos/logback/classic/Level.toInt:()I
      52: lookupswitch  { // 5
                  5000: 152
                 10000: 140
                 20000: 128
                 30000: 116
                 40000: 104
               default: 161
          }
     104: aload_0
     105: getfield      #46                 // Field errorCounter:Lio/micrometer/core/instrument/Counter;
     108: invokeinterface #120,  1          // InterfaceMethod io/micrometer/core/instrument/Counter.increment:()V
     113: goto          161
     116: aload_0
     117: getfield      #56                 // Field warnCounter:Lio/micrometer/core/instrument/Counter;
     120: invokeinterface #120,  1          // InterfaceMethod io/micrometer/core/instrument/Counter.increment:()V
     125: goto          161
     128: aload_0
     129: getfield      #63                 // Field infoCounter:Lio/micrometer/core/instrument/Counter;
     132: invokeinterface #120,  1          // InterfaceMethod io/micrometer/core/instrument/Counter.increment:()V
     137: goto          161
     140: aload_0
     141: getfield      #70                 // Field debugCounter:Lio/micrometer/core/instrument/Counter;
     144: invokeinterface #120,  1          // InterfaceMethod io/micrometer/core/instrument/Counter.increment:()V
     149: goto          161
     152: aload_0
     153: getfield      #77                 // Field traceCounter:Lio/micrometer/core/instrument/Counter;
     156: invokeinterface #120,  1          // InterfaceMethod io/micrometer/core/instrument/Counter.increment:()V
     161: getstatic     #80                 // Field ch/qos/logback/core/spi/FilterReply.NEUTRAL:Lch/qos/logback/core/spi/FilterReply;
     164: areturn
}
