Compiled from "UnderlineAttribute.java"
public class org.protege.editor.owl.ui.renderer.styledstring.UnderlineAttribute extends org.protege.editor.owl.ui.renderer.styledstring.StyleAttribute {
  private static final org.protege.editor.owl.ui.renderer.styledstring.UnderlineAttribute NONE;

  private static final org.protege.editor.owl.ui.renderer.styledstring.UnderlineAttribute SINGLE;

  private org.protege.editor.owl.ui.renderer.styledstring.Underline underline;

  public org.protege.editor.owl.ui.renderer.styledstring.UnderlineAttribute(org.protege.editor.owl.ui.renderer.styledstring.Underline);
    Code:
       0: aload_0
       1: invokespecial #1                  // Method org/protege/editor/owl/ui/renderer/styledstring/StyleAttribute."<init>":()V
       4: aload_0
       5: aload_1
       6: putfield      #2                  // Field underline:Lorg/protege/editor/owl/ui/renderer/styledstring/Underline;
       9: return

  public org.protege.editor.owl.ui.renderer.styledstring.Underline getUnderline();
    Code:
       0: aload_0
       1: getfield      #2                  // Field underline:Lorg/protege/editor/owl/ui/renderer/styledstring/Underline;
       4: areturn

  public static org.protege.editor.owl.ui.renderer.styledstring.UnderlineAttribute getNone();
    Code:
       0: getstatic     #3                  // Field NONE:Lorg/protege/editor/owl/ui/renderer/styledstring/UnderlineAttribute;
       3: areturn

  public static org.protege.editor.owl.ui.renderer.styledstring.UnderlineAttribute getSingle();
    Code:
       0: getstatic     #4                  // Field SINGLE:Lorg/protege/editor/owl/ui/renderer/styledstring/UnderlineAttribute;
       3: areturn

  public java.lang.String getCSSPropertyName();
    Code:
       0: getstatic     #5                  // Field org/protege/editor/owl/ui/renderer/styledstring/CSSConstants.TEXT_DECORATION:Lorg/protege/editor/owl/ui/renderer/styledstring/CSSConstants;
       3: invokevirtual #6                  // Method org/protege/editor/owl/ui/renderer/styledstring/CSSConstants.getName:()Ljava/lang/String;
       6: areturn

  public java.lang.String getCSSValue();
    Code:
       0: aload_0
       1: getfield      #2                  // Field underline:Lorg/protege/editor/owl/ui/renderer/styledstring/Underline;
       4: getstatic     #7                  // Field org/protege/editor/owl/ui/renderer/styledstring/Underline.SINGLE:Lorg/protege/editor/owl/ui/renderer/styledstring/Underline;
       7: if_acmpne     19
      10: getstatic     #8                  // Field org/protege/editor/owl/ui/renderer/styledstring/CSSConstants.UNDERLINE:Lorg/protege/editor/owl/ui/renderer/styledstring/CSSConstants;
      13: invokevirtual #6                  // Method org/protege/editor/owl/ui/renderer/styledstring/CSSConstants.getName:()Ljava/lang/String;
      16: goto          25
      19: getstatic     #9                  // Field org/protege/editor/owl/ui/renderer/styledstring/CSSConstants.NONE:Lorg/protege/editor/owl/ui/renderer/styledstring/CSSConstants;
      22: invokevirtual #6                  // Method org/protege/editor/owl/ui/renderer/styledstring/CSSConstants.getName:()Ljava/lang/String;
      25: areturn

  public java.text.AttributedCharacterIterator$Attribute getAttributedStringAttribute();
    Code:
       0: getstatic     #10                 // Field java/awt/font/TextAttribute.UNDERLINE:Ljava/awt/font/TextAttribute;
       3: areturn

  public java.lang.Object getAttributesStringValue();
    Code:
       0: getstatic     #11                 // Field java/awt/font/TextAttribute.UNDERLINE_LOW_ONE_PIXEL:Ljava/lang/Integer;
       3: areturn

  public javax.swing.text.StyleConstants getTextAttribute();
    Code:
       0: getstatic     #12                 // Field javax/swing/text/StyleConstants.Underline:Ljava/lang/Object;
       3: checkcast     #13                 // class javax/swing/text/StyleConstants$CharacterConstants
       6: areturn

  public java.lang.Object getTextValue();
    Code:
       0: aload_0
       1: getfield      #2                  // Field underline:Lorg/protege/editor/owl/ui/renderer/styledstring/Underline;
       4: getstatic     #7                  // Field org/protege/editor/owl/ui/renderer/styledstring/Underline.SINGLE:Lorg/protege/editor/owl/ui/renderer/styledstring/Underline;
       7: if_acmpne     14
      10: iconst_1
      11: goto          15
      14: iconst_0
      15: invokestatic  #14                 // Method java/lang/Boolean.valueOf:(Z)Ljava/lang/Boolean;
      18: areturn

  public int hashCode();
    Code:
       0: ldc           #15                 // class org/protege/editor/owl/ui/renderer/styledstring/UnderlineAttribute
       2: invokevirtual #16                 // Method java/lang/Class.getSimpleName:()Ljava/lang/String;
       5: invokevirtual #17                 // Method java/lang/String.hashCode:()I
       8: aload_0
       9: getfield      #2                  // Field underline:Lorg/protege/editor/owl/ui/renderer/styledstring/Underline;
      12: invokevirtual #18                 // Method org/protege/editor/owl/ui/renderer/styledstring/Underline.hashCode:()I
      15: iadd
      16: ireturn

  public boolean equals(java.lang.Object);
    Code:
       0: aload_1
       1: aload_0
       2: if_acmpne     7
       5: iconst_1
       6: ireturn
       7: aload_1
       8: instanceof    #15                 // class org/protege/editor/owl/ui/renderer/styledstring/UnderlineAttribute
      11: ifne          16
      14: iconst_0
      15: ireturn
      16: aload_1
      17: checkcast     #15                 // class org/protege/editor/owl/ui/renderer/styledstring/UnderlineAttribute
      20: astore_2
      21: aload_0
      22: getfield      #2                  // Field underline:Lorg/protege/editor/owl/ui/renderer/styledstring/Underline;
      25: aload_2
      26: getfield      #2                  // Field underline:Lorg/protege/editor/owl/ui/renderer/styledstring/Underline;
      29: invokevirtual #19                 // Method org/protege/editor/owl/ui/renderer/styledstring/Underline.equals:(Ljava/lang/Object;)Z
      32: ireturn

  static {};
    Code:
       0: new           #15                 // class org/protege/editor/owl/ui/renderer/styledstring/UnderlineAttribute
       3: dup
       4: getstatic     #20                 // Field org/protege/editor/owl/ui/renderer/styledstring/Underline.NONE:Lorg/protege/editor/owl/ui/renderer/styledstring/Underline;
       7: invokespecial #21                 // Method "<init>":(Lorg/protege/editor/owl/ui/renderer/styledstring/Underline;)V
      10: putstatic     #3                  // Field NONE:Lorg/protege/editor/owl/ui/renderer/styledstring/UnderlineAttribute;
      13: new           #15                 // class org/protege/editor/owl/ui/renderer/styledstring/UnderlineAttribute
      16: dup
      17: getstatic     #7                  // Field org/protege/editor/owl/ui/renderer/styledstring/Underline.SINGLE:Lorg/protege/editor/owl/ui/renderer/styledstring/Underline;
      20: invokespecial #21                 // Method "<init>":(Lorg/protege/editor/owl/ui/renderer/styledstring/Underline;)V
      23: putstatic     #4                  // Field SINGLE:Lorg/protege/editor/owl/ui/renderer/styledstring/UnderlineAttribute;
      26: return
}
