Compiled from "WriterStreamRDFPlain.java"
public class org.apache.jena.riot.writer.WriterStreamRDFPlain implements org.apache.jena.riot.system.StreamRDF {
  protected final org.apache.jena.atlas.io.AWriter out;

  protected final org.apache.jena.riot.out.NodeFormatter nodeFmt;

  public org.apache.jena.riot.writer.WriterStreamRDFPlain(org.apache.jena.atlas.io.AWriter);
    Code:
       0: aload_0
       1: aload_1
       2: getstatic     #1                  // Field org/apache/jena/atlas/lib/CharSpace.UTF8:Lorg/apache/jena/atlas/lib/CharSpace;
       5: invokespecial #2                  // Method "<init>":(Lorg/apache/jena/atlas/io/AWriter;Lorg/apache/jena/atlas/lib/CharSpace;)V
       8: return

  public org.apache.jena.riot.writer.WriterStreamRDFPlain(org.apache.jena.atlas.io.AWriter, org.apache.jena.atlas.lib.CharSpace);
    Code:
       0: aload_0
       1: invokespecial #3                  // Method java/lang/Object."<init>":()V
       4: aload_0
       5: aload_1
       6: putfield      #4                  // Field out:Lorg/apache/jena/atlas/io/AWriter;
       9: aload_0
      10: new           #5                  // class org/apache/jena/riot/out/NodeFormatterNT
      13: dup
      14: aload_2
      15: invokespecial #6                  // Method org/apache/jena/riot/out/NodeFormatterNT."<init>":(Lorg/apache/jena/atlas/lib/CharSpace;)V
      18: putfield      #7                  // Field nodeFmt:Lorg/apache/jena/riot/out/NodeFormatter;
      21: return

  public void start();
    Code:
       0: return

  public void finish();
    Code:
       0: aload_0
       1: getfield      #4                  // Field out:Lorg/apache/jena/atlas/io/AWriter;
       4: invokestatic  #8                  // Method org/apache/jena/atlas/io/IO.flush:(Lorg/apache/jena/atlas/io/AWriter;)V
       7: return

  public void triple(org.apache.jena.graph.Triple);
    Code:
       0: aload_1
       1: invokevirtual #9                  // Method org/apache/jena/graph/Triple.getSubject:()Lorg/apache/jena/graph/Node;
       4: astore_2
       5: aload_1
       6: invokevirtual #10                 // Method org/apache/jena/graph/Triple.getPredicate:()Lorg/apache/jena/graph/Node;
       9: astore_3
      10: aload_1
      11: invokevirtual #11                 // Method org/apache/jena/graph/Triple.getObject:()Lorg/apache/jena/graph/Node;
      14: astore        4
      16: aload_0
      17: aload_2
      18: invokespecial #12                 // Method format:(Lorg/apache/jena/graph/Node;)V
      21: aload_0
      22: getfield      #4                  // Field out:Lorg/apache/jena/atlas/io/AWriter;
      25: ldc           #13                 // String
      27: invokeinterface #14,  2           // InterfaceMethod org/apache/jena/atlas/io/AWriter.print:(Ljava/lang/String;)V
      32: aload_0
      33: aload_3
      34: invokespecial #12                 // Method format:(Lorg/apache/jena/graph/Node;)V
      37: aload_0
      38: getfield      #4                  // Field out:Lorg/apache/jena/atlas/io/AWriter;
      41: ldc           #13                 // String
      43: invokeinterface #14,  2           // InterfaceMethod org/apache/jena/atlas/io/AWriter.print:(Ljava/lang/String;)V
      48: aload_0
      49: aload         4
      51: invokespecial #12                 // Method format:(Lorg/apache/jena/graph/Node;)V
      54: aload_0
      55: getfield      #4                  // Field out:Lorg/apache/jena/atlas/io/AWriter;
      58: ldc           #15                 // String  .\n
      60: invokeinterface #14,  2           // InterfaceMethod org/apache/jena/atlas/io/AWriter.print:(Ljava/lang/String;)V
      65: return

  public void quad(org.apache.jena.sparql.core.Quad);
    Code:
       0: aload_1
       1: invokevirtual #16                 // Method org/apache/jena/sparql/core/Quad.getSubject:()Lorg/apache/jena/graph/Node;
       4: astore_2
       5: aload_1
       6: invokevirtual #17                 // Method org/apache/jena/sparql/core/Quad.getPredicate:()Lorg/apache/jena/graph/Node;
       9: astore_3
      10: aload_1
      11: invokevirtual #18                 // Method org/apache/jena/sparql/core/Quad.getObject:()Lorg/apache/jena/graph/Node;
      14: astore        4
      16: aload_1
      17: invokevirtual #19                 // Method org/apache/jena/sparql/core/Quad.getGraph:()Lorg/apache/jena/graph/Node;
      20: astore        5
      22: aload_0
      23: aload_2
      24: invokespecial #12                 // Method format:(Lorg/apache/jena/graph/Node;)V
      27: aload_0
      28: getfield      #4                  // Field out:Lorg/apache/jena/atlas/io/AWriter;
      31: ldc           #13                 // String
      33: invokeinterface #14,  2           // InterfaceMethod org/apache/jena/atlas/io/AWriter.print:(Ljava/lang/String;)V
      38: aload_0
      39: aload_3
      40: invokespecial #12                 // Method format:(Lorg/apache/jena/graph/Node;)V
      43: aload_0
      44: getfield      #4                  // Field out:Lorg/apache/jena/atlas/io/AWriter;
      47: ldc           #13                 // String
      49: invokeinterface #14,  2           // InterfaceMethod org/apache/jena/atlas/io/AWriter.print:(Ljava/lang/String;)V
      54: aload_0
      55: aload         4
      57: invokespecial #12                 // Method format:(Lorg/apache/jena/graph/Node;)V
      60: aload         5
      62: invokestatic  #20                 // Method outputGraphSlot:(Lorg/apache/jena/graph/Node;)Z
      65: ifeq          85
      68: aload_0
      69: getfield      #4                  // Field out:Lorg/apache/jena/atlas/io/AWriter;
      72: ldc           #13                 // String
      74: invokeinterface #14,  2           // InterfaceMethod org/apache/jena/atlas/io/AWriter.print:(Ljava/lang/String;)V
      79: aload_0
      80: aload         5
      82: invokespecial #12                 // Method format:(Lorg/apache/jena/graph/Node;)V
      85: aload_0
      86: getfield      #4                  // Field out:Lorg/apache/jena/atlas/io/AWriter;
      89: ldc           #15                 // String  .\n
      91: invokeinterface #14,  2           // InterfaceMethod org/apache/jena/atlas/io/AWriter.print:(Ljava/lang/String;)V
      96: return

  private void format(org.apache.jena.graph.Node);
    Code:
       0: aload_0
       1: getfield      #7                  // Field nodeFmt:Lorg/apache/jena/riot/out/NodeFormatter;
       4: aload_0
       5: getfield      #4                  // Field out:Lorg/apache/jena/atlas/io/AWriter;
       8: aload_1
       9: invokeinterface #21,  3           // InterfaceMethod org/apache/jena/riot/out/NodeFormatter.format:(Lorg/apache/jena/atlas/io/AWriter;Lorg/apache/jena/graph/Node;)V
      14: return

  public void base(java.lang.String);
    Code:
       0: return

  public void prefix(java.lang.String, java.lang.String);
    Code:
       0: return

  private static boolean outputGraphSlot(org.apache.jena.graph.Node);
    Code:
       0: aload_0
       1: ifnull        22
       4: aload_0
       5: getstatic     #22                 // Field org/apache/jena/sparql/core/Quad.tripleInQuad:Lorg/apache/jena/graph/Node;
       8: if_acmpeq     22
      11: aload_0
      12: invokestatic  #23                 // Method org/apache/jena/sparql/core/Quad.isDefaultGraph:(Lorg/apache/jena/graph/Node;)Z
      15: ifne          22
      18: iconst_1
      19: goto          23
      22: iconst_0
      23: ireturn
}
