Compiled from "AbstractIndexSelectWhereTypeMap.java"
public abstract class info.archinnov.achilles.internals.dsl.query.select.AbstractIndexSelectWhereTypeMap<T extends info.archinnov.achilles.internals.dsl.query.select.AbstractIndexSelectWhereTypeMap<T, ENTITY>, ENTITY> extends info.archinnov.achilles.internals.dsl.query.select.AbstractSelectWhereTypeMap<T, ENTITY> {
  private static final org.slf4j.Logger LOGGER;

  protected info.archinnov.achilles.internals.dsl.query.select.AbstractIndexSelectWhereTypeMap(com.datastax.driver.core.querybuilder.Select$Where);
    Code:
       0: aload_0
       1: aload_1
       2: invokespecial #1                  // Method info/archinnov/achilles/internals/dsl/query/select/AbstractSelectWhereTypeMap."<init>":(Lcom/datastax/driver/core/querybuilder/Select$Where;)V
       5: return

  protected info.archinnov.achilles.internals.statements.StatementWrapper getInternalBoundStatementWrapper();
    Code:
       0: getstatic     #2                  // Field LOGGER:Lorg/slf4j/Logger;
       3: invokeinterface #3,  1            // InterfaceMethod org/slf4j/Logger.isTraceEnabled:()Z
       8: ifeq          28
      11: getstatic     #2                  // Field LOGGER:Lorg/slf4j/Logger;
      14: ldc           #4                  // String Get bound statement wrapper
      16: iconst_0
      17: anewarray     #5                  // class java/lang/Object
      20: invokestatic  #6                  // Method java/lang/String.format:(Ljava/lang/String;[Ljava/lang/Object;)Ljava/lang/String;
      23: invokeinterface #7,  2            // InterfaceMethod org/slf4j/Logger.trace:(Ljava/lang/String;)V
      28: aload_0
      29: invokevirtual #8                  // Method getRte:()Linfo/archinnov/achilles/internals/runtime/RuntimeEngine;
      32: astore_1
      33: aload_0
      34: invokevirtual #9                  // Method getMetaInternal:()Linfo/archinnov/achilles/internals/metamodel/AbstractEntityProperty;
      37: astore_2
      38: aload_0
      39: invokevirtual #10                 // Method getOptions:()Linfo/archinnov/achilles/internals/options/Options;
      42: astore_3
      43: aload_3
      44: invokevirtual #11                 // Method info/archinnov/achilles/internals/options/Options.hasRawSolrQuery:()Z
      47: ifeq          90
      50: aload_0
      51: invokevirtual #12                 // Method getBoundValuesInternal:()Ljava/util/List;
      54: iconst_0
      55: aload_3
      56: invokevirtual #13                 // Method info/archinnov/achilles/internals/options/Options.generateRawSolrQuery:()Ljava/lang/String;
      59: invokeinterface #14,  3           // InterfaceMethod java/util/List.add:(ILjava/lang/Object;)V
      64: aload_0
      65: invokevirtual #15                 // Method getEncodedValuesInternal:()Ljava/util/List;
      68: iconst_0
      69: aload_3
      70: invokevirtual #13                 // Method info/archinnov/achilles/internals/options/Options.generateRawSolrQuery:()Ljava/lang/String;
      73: invokeinterface #14,  3           // InterfaceMethod java/util/List.add:(ILjava/lang/Object;)V
      78: aload_0
      79: getfield      #16                 // Field where:Lcom/datastax/driver/core/querybuilder/Select$Where;
      82: invokevirtual #17                 // Method com/datastax/driver/core/querybuilder/Select$Where.getQueryString:()Ljava/lang/String;
      85: astore        4
      87: goto          156
      90: aload_3
      91: invokevirtual #18                 // Method info/archinnov/achilles/internals/options/Options.hasSolrQuery:()Z
      94: ifeq          137
      97: aload_0
      98: invokevirtual #12                 // Method getBoundValuesInternal:()Ljava/util/List;
     101: iconst_0
     102: aload_3
     103: invokevirtual #19                 // Method info/archinnov/achilles/internals/options/Options.generateSolrQuery:()Ljava/lang/String;
     106: invokeinterface #14,  3           // InterfaceMethod java/util/List.add:(ILjava/lang/Object;)V
     111: aload_0
     112: invokevirtual #15                 // Method getEncodedValuesInternal:()Ljava/util/List;
     115: iconst_0
     116: aload_3
     117: invokevirtual #19                 // Method info/archinnov/achilles/internals/options/Options.generateSolrQuery:()Ljava/lang/String;
     120: invokeinterface #14,  3           // InterfaceMethod java/util/List.add:(ILjava/lang/Object;)V
     125: aload_0
     126: getfield      #16                 // Field where:Lcom/datastax/driver/core/querybuilder/Select$Where;
     129: invokevirtual #17                 // Method com/datastax/driver/core/querybuilder/Select$Where.getQueryString:()Ljava/lang/String;
     132: astore        4
     134: goto          156
     137: aload_0
     138: getfield      #16                 // Field where:Lcom/datastax/driver/core/querybuilder/Select$Where;
     141: invokevirtual #17                 // Method com/datastax/driver/core/querybuilder/Select$Where.getQueryString:()Ljava/lang/String;
     144: invokevirtual #20                 // Method java/lang/String.trim:()Ljava/lang/String;
     147: ldc           #21                 // String ;$
     149: ldc           #22                 // String  ALLOW FILTERING;
     151: invokevirtual #23                 // Method java/lang/String.replaceFirst:(Ljava/lang/String;Ljava/lang/String;)Ljava/lang/String;
     154: astore        4
     156: aload_1
     157: aload         4
     159: invokevirtual #24                 // Method info/archinnov/achilles/internals/runtime/RuntimeEngine.prepareDynamicQuery:(Ljava/lang/String;)Lcom/datastax/driver/core/PreparedStatement;
     162: astore        5
     164: new           #25                 // class info/archinnov/achilles/internals/statements/BoundStatementWrapper
     167: dup
     168: getstatic     #26                 // Field info/archinnov/achilles/internals/statements/OperationType.SELECT:Linfo/archinnov/achilles/internals/statements/OperationType;
     171: aload_2
     172: aload         5
     174: aload_0
     175: invokevirtual #12                 // Method getBoundValuesInternal:()Ljava/util/List;
     178: invokeinterface #27,  1           // InterfaceMethod java/util/List.toArray:()[Ljava/lang/Object;
     183: aload_0
     184: invokevirtual #15                 // Method getEncodedValuesInternal:()Ljava/util/List;
     187: invokeinterface #27,  1           // InterfaceMethod java/util/List.toArray:()[Ljava/lang/Object;
     192: invokespecial #28                 // Method info/archinnov/achilles/internals/statements/BoundStatementWrapper."<init>":(Linfo/archinnov/achilles/internals/statements/OperationType;Linfo/archinnov/achilles/internals/metamodel/AbstractEntityProperty;Lcom/datastax/driver/core/PreparedStatement;[Ljava/lang/Object;[Ljava/lang/Object;)V
     195: astore        6
     197: aload         6
     199: aload_3
     200: invokeinterface #29,  2           // InterfaceMethod info/archinnov/achilles/internals/statements/StatementWrapper.applyOptions:(Linfo/archinnov/achilles/internals/options/Options;)V
     205: aload         6
     207: areturn

  static {};
    Code:
       0: ldc           #30                 // class info/archinnov/achilles/internals/dsl/query/select/AbstractIndexSelectWhereTypeMap
       2: invokestatic  #31                 // Method org/slf4j/LoggerFactory.getLogger:(Ljava/lang/Class;)Lorg/slf4j/Logger;
       5: putstatic     #2                  // Field LOGGER:Lorg/slf4j/Logger;
       8: return
}
