Compiled from "AbstractDigestMD5Factory.java"
public abstract class org.jboss.sasl.digest.AbstractDigestMD5Factory extends org.jboss.sasl.util.AbstractSaslFactory {
  public static final java.lang.String DIGEST_MD5;

  public org.jboss.sasl.digest.AbstractDigestMD5Factory();
    Code:
       0: aload_0
       1: ldc           #1                  // String DIGEST-MD5
       3: invokespecial #2                  // Method org/jboss/sasl/util/AbstractSaslFactory."<init>":(Ljava/lang/String;)V
       6: return

  protected boolean isAnonymous();
    Code:
       0: iconst_0
       1: ireturn

  protected boolean isPlainText();
    Code:
       0: iconst_0
       1: ireturn
}
