Compiled from "Immutables.java"
public class org.infinispan.commons.util.Immutables {
  public org.infinispan.commons.util.Immutables();
    Code:
       0: aload_0
       1: invokespecial #1                  // Method java/lang/Object."<init>":()V
       4: return

  public static boolean isImmutable(java.lang.Object);
    Code:
       0: aload_0
       1: instanceof    #2                  // class org/infinispan/commons/util/Immutables$Immutable
       4: ireturn

  public static <T> java.util.List<T> immutableListConvert(java.util.Collection<? extends T>);
    Code:
       0: new           #3                  // class org/infinispan/commons/util/ImmutableListCopy
       3: dup
       4: aload_0
       5: invokespecial #4                  // Method org/infinispan/commons/util/ImmutableListCopy."<init>":(Ljava/util/Collection;)V
       8: areturn

  public static <T> java.util.List<T> immutableListCopy(java.util.List<T>);
    Code:
       0: aload_0
       1: ifnonnull     6
       4: aconst_null
       5: areturn
       6: aload_0
       7: invokeinterface #5,  1            // InterfaceMethod java/util/List.isEmpty:()Z
      12: ifeq          19
      15: invokestatic  #6                  // Method org/infinispan/commons/util/InfinispanCollections.emptyList:()Ljava/util/List;
      18: areturn
      19: aload_0
      20: invokeinterface #7,  1            // InterfaceMethod java/util/List.size:()I
      25: iconst_1
      26: if_icmpne     40
      29: aload_0
      30: iconst_0
      31: invokeinterface #8,  2            // InterfaceMethod java/util/List.get:(I)Ljava/lang/Object;
      36: invokestatic  #9                  // Method java/util/Collections.singletonList:(Ljava/lang/Object;)Ljava/util/List;
      39: areturn
      40: new           #3                  // class org/infinispan/commons/util/ImmutableListCopy
      43: dup
      44: aload_0
      45: invokespecial #4                  // Method org/infinispan/commons/util/ImmutableListCopy."<init>":(Ljava/util/Collection;)V
      48: areturn

  public static org.infinispan.commons.util.TypedProperties immutableTypedProperties(org.infinispan.commons.util.TypedProperties);
    Code:
       0: aload_0
       1: ifnonnull     6
       4: aconst_null
       5: areturn
       6: new           #10                 // class org/infinispan/commons/util/Immutables$ImmutableTypedProperties
       9: dup
      10: aload_0
      11: invokespecial #11                 // Method org/infinispan/commons/util/Immutables$ImmutableTypedProperties."<init>":(Lorg/infinispan/commons/util/TypedProperties;)V
      14: areturn

  public static <T> java.util.List<T> immutableListWrap(T...);
    Code:
       0: new           #3                  // class org/infinispan/commons/util/ImmutableListCopy
       3: dup
       4: aload_0
       5: invokespecial #12                 // Method org/infinispan/commons/util/ImmutableListCopy."<init>":([Ljava/lang/Object;)V
       8: areturn

  public static <T> java.util.List<T> immutableListMerge(java.util.List<? extends T>, java.util.List<? extends T>);
    Code:
       0: new           #3                  // class org/infinispan/commons/util/ImmutableListCopy
       3: dup
       4: aload_0
       5: aload_1
       6: invokespecial #13                 // Method org/infinispan/commons/util/ImmutableListCopy."<init>":(Ljava/util/Collection;Ljava/util/Collection;)V
       9: areturn

  public static <T> java.util.Set<T> immutableSetConvert(java.util.Collection<? extends T>);
    Code:
       0: new           #14                 // class java/util/HashSet
       3: dup
       4: aload_0
       5: invokespecial #15                 // Method java/util/HashSet."<init>":(Ljava/util/Collection;)V
       8: invokestatic  #16                 // Method immutableSetWrap:(Ljava/util/Set;)Ljava/util/Set;
      11: areturn

  public static <T> java.util.Set<T> immutableSetWrap(java.util.Set<? extends T>);
    Code:
       0: new           #17                 // class org/infinispan/commons/util/Immutables$ImmutableSetWrapper
       3: dup
       4: aload_0
       5: invokespecial #18                 // Method org/infinispan/commons/util/Immutables$ImmutableSetWrapper."<init>":(Ljava/util/Set;)V
       8: areturn

  public static <T> java.util.Set<T> immutableSetCopy(java.util.Set<T>);
    Code:
       0: aload_0
       1: ifnonnull     6
       4: aconst_null
       5: areturn
       6: aload_0
       7: invokeinterface #19,  1           // InterfaceMethod java/util/Set.isEmpty:()Z
      12: ifeq          19
      15: invokestatic  #20                 // Method org/infinispan/commons/util/InfinispanCollections.emptySet:()Ljava/util/Set;
      18: areturn
      19: aload_0
      20: invokeinterface #21,  1           // InterfaceMethod java/util/Set.size:()I
      25: iconst_1
      26: if_icmpne     44
      29: aload_0
      30: invokeinterface #22,  1           // InterfaceMethod java/util/Set.iterator:()Ljava/util/Iterator;
      35: invokeinterface #23,  1           // InterfaceMethod java/util/Iterator.next:()Ljava/lang/Object;
      40: invokestatic  #24                 // Method java/util/Collections.singleton:(Ljava/lang/Object;)Ljava/util/Set;
      43: areturn
      44: aload_0
      45: invokestatic  #25                 // Method org/infinispan/commons/util/ObjectDuplicator.duplicateSet:(Ljava/util/Set;)Ljava/util/Set;
      48: astore_1
      49: aload_1
      50: ifnonnull     63
      53: aload_0
      54: ldc           #26                 // class java/util/Collection
      56: invokestatic  #27                 // Method attemptCopyConstructor:(Ljava/lang/Object;Ljava/lang/Class;)Ljava/lang/Object;
      59: checkcast     #28                 // class java/util/Set
      62: astore_1
      63: aload_1
      64: ifnonnull     76
      67: new           #14                 // class java/util/HashSet
      70: dup
      71: aload_0
      72: invokespecial #15                 // Method java/util/HashSet."<init>":(Ljava/util/Collection;)V
      75: astore_1
      76: new           #17                 // class org/infinispan/commons/util/Immutables$ImmutableSetWrapper
      79: dup
      80: aload_1
      81: invokespecial #18                 // Method org/infinispan/commons/util/Immutables$ImmutableSetWrapper."<init>":(Ljava/util/Set;)V
      84: areturn

  public static <K, V> java.util.Map<K, V> immutableMapWrap(java.util.Map<? extends K, ? extends V>);
    Code:
       0: new           #29                 // class org/infinispan/commons/util/Immutables$ImmutableMapWrapper
       3: dup
       4: aload_0
       5: invokespecial #30                 // Method org/infinispan/commons/util/Immutables$ImmutableMapWrapper."<init>":(Ljava/util/Map;)V
       8: areturn

  public static <K, V> java.util.Map<K, V> immutableMapCopy(java.util.Map<K, V>);
    Code:
       0: aload_0
       1: ifnonnull     6
       4: aconst_null
       5: areturn
       6: aload_0
       7: invokeinterface #31,  1           // InterfaceMethod java/util/Map.isEmpty:()Z
      12: ifeq          19
      15: invokestatic  #32                 // Method org/infinispan/commons/util/InfinispanCollections.emptyMap:()Ljava/util/Map;
      18: areturn
      19: aload_0
      20: invokeinterface #33,  1           // InterfaceMethod java/util/Map.size:()I
      25: iconst_1
      26: if_icmpne     65
      29: aload_0
      30: invokeinterface #34,  1           // InterfaceMethod java/util/Map.entrySet:()Ljava/util/Set;
      35: invokeinterface #22,  1           // InterfaceMethod java/util/Set.iterator:()Ljava/util/Iterator;
      40: invokeinterface #23,  1           // InterfaceMethod java/util/Iterator.next:()Ljava/lang/Object;
      45: checkcast     #35                 // class java/util/Map$Entry
      48: astore_1
      49: aload_1
      50: invokeinterface #36,  1           // InterfaceMethod java/util/Map$Entry.getKey:()Ljava/lang/Object;
      55: aload_1
      56: invokeinterface #37,  1           // InterfaceMethod java/util/Map$Entry.getValue:()Ljava/lang/Object;
      61: invokestatic  #38                 // Method java/util/Collections.singletonMap:(Ljava/lang/Object;Ljava/lang/Object;)Ljava/util/Map;
      64: areturn
      65: aload_0
      66: invokestatic  #39                 // Method org/infinispan/commons/util/ObjectDuplicator.duplicateMap:(Ljava/util/Map;)Ljava/util/Map;
      69: astore_1
      70: aload_1
      71: ifnonnull     84
      74: aload_0
      75: ldc           #40                 // class java/util/Map
      77: invokestatic  #27                 // Method attemptCopyConstructor:(Ljava/lang/Object;Ljava/lang/Class;)Ljava/lang/Object;
      80: checkcast     #40                 // class java/util/Map
      83: astore_1
      84: aload_1
      85: ifnonnull     97
      88: new           #41                 // class java/util/HashMap
      91: dup
      92: aload_0
      93: invokespecial #42                 // Method java/util/HashMap."<init>":(Ljava/util/Map;)V
      96: astore_1
      97: new           #29                 // class org/infinispan/commons/util/Immutables$ImmutableMapWrapper
     100: dup
     101: aload_1
     102: invokespecial #30                 // Method org/infinispan/commons/util/Immutables$ImmutableMapWrapper."<init>":(Ljava/util/Map;)V
     105: areturn

  public static <T> java.util.Collection<T> immutableCollectionCopy(java.util.Collection<T>);
    Code:
       0: aload_0
       1: ifnonnull     6
       4: aconst_null
       5: areturn
       6: aload_0
       7: invokeinterface #43,  1           // InterfaceMethod java/util/Collection.isEmpty:()Z
      12: ifeq          19
      15: invokestatic  #20                 // Method org/infinispan/commons/util/InfinispanCollections.emptySet:()Ljava/util/Set;
      18: areturn
      19: aload_0
      20: invokeinterface #44,  1           // InterfaceMethod java/util/Collection.size:()I
      25: iconst_1
      26: if_icmpne     44
      29: aload_0
      30: invokeinterface #45,  1           // InterfaceMethod java/util/Collection.iterator:()Ljava/util/Iterator;
      35: invokeinterface #23,  1           // InterfaceMethod java/util/Iterator.next:()Ljava/lang/Object;
      40: invokestatic  #24                 // Method java/util/Collections.singleton:(Ljava/lang/Object;)Ljava/util/Set;
      43: areturn
      44: aload_0
      45: invokestatic  #46                 // Method org/infinispan/commons/util/ObjectDuplicator.duplicateCollection:(Ljava/util/Collection;)Ljava/util/Collection;
      48: astore_1
      49: aload_1
      50: ifnonnull     63
      53: aload_0
      54: ldc           #26                 // class java/util/Collection
      56: invokestatic  #27                 // Method attemptCopyConstructor:(Ljava/lang/Object;Ljava/lang/Class;)Ljava/lang/Object;
      59: checkcast     #26                 // class java/util/Collection
      62: astore_1
      63: aload_1
      64: ifnonnull     76
      67: new           #47                 // class java/util/ArrayList
      70: dup
      71: aload_0
      72: invokespecial #48                 // Method java/util/ArrayList."<init>":(Ljava/util/Collection;)V
      75: astore_1
      76: new           #49                 // class org/infinispan/commons/util/Immutables$ImmutableCollectionWrapper
      79: dup
      80: aload_1
      81: invokespecial #50                 // Method org/infinispan/commons/util/Immutables$ImmutableCollectionWrapper."<init>":(Ljava/util/Collection;)V
      84: areturn

  public static <T> java.util.Collection<T> immutableCollectionWrap(java.util.Collection<? extends T>);
    Code:
       0: new           #49                 // class org/infinispan/commons/util/Immutables$ImmutableCollectionWrapper
       3: dup
       4: aload_0
       5: invokespecial #50                 // Method org/infinispan/commons/util/Immutables$ImmutableCollectionWrapper."<init>":(Ljava/util/Collection;)V
       8: areturn

  private static <T> T attemptCopyConstructor(T, java.lang.Class<? super T>);
    Code:
       0: aload_0
       1: invokevirtual #51                 // Method java/lang/Object.getClass:()Ljava/lang/Class;
       4: iconst_1
       5: anewarray     #52                 // class java/lang/Class
       8: dup
       9: iconst_0
      10: aload_1
      11: aastore
      12: invokevirtual #53                 // Method java/lang/Class.getConstructor:([Ljava/lang/Class;)Ljava/lang/reflect/Constructor;
      15: iconst_1
      16: anewarray     #54                 // class java/lang/Object
      19: dup
      20: iconst_0
      21: aload_0
      22: aastore
      23: invokevirtual #55                 // Method java/lang/reflect/Constructor.newInstance:([Ljava/lang/Object;)Ljava/lang/Object;
      26: areturn
      27: astore_2
      28: aconst_null
      29: areturn
    Exception table:
       from    to  target type
           0    26    27   Class java/lang/Exception

  public static <K, V> java.util.Map$Entry<K, V> immutableEntry(java.util.Map$Entry<K, V>);
    Code:
       0: new           #57                 // class org/infinispan/commons/util/Immutables$ImmutableEntry
       3: dup
       4: aload_0
       5: invokespecial #58                 // Method org/infinispan/commons/util/Immutables$ImmutableEntry."<init>":(Ljava/util/Map$Entry;)V
       8: areturn
}
