Compiled from "IndexColumn.java"
public class org.hibernate.cfg.IndexColumn extends org.hibernate.cfg.Ejb3Column {
  private int base;

  public org.hibernate.cfg.IndexColumn(boolean, java.lang.String, int, int, int, java.lang.String, boolean, boolean, boolean, boolean, java.lang.String, java.util.Map<java.lang.String, org.hibernate.mapping.Join>, org.hibernate.cfg.PropertyHolder, org.hibernate.boot.spi.MetadataBuildingContext);
    Code:
       0: aload_0
       1: invokespecial #1                  // Method org/hibernate/cfg/Ejb3Column."<init>":()V
       4: aload_0
       5: iload_1
       6: invokevirtual #2                  // Method setImplicit:(Z)V
       9: aload_0
      10: aload_2
      11: invokevirtual #3                  // Method setSqlType:(Ljava/lang/String;)V
      14: aload_0
      15: iload_3
      16: invokevirtual #4                  // Method setLength:(I)V
      19: aload_0
      20: iload         4
      22: invokevirtual #5                  // Method setPrecision:(I)V
      25: aload_0
      26: iload         5
      28: invokevirtual #6                  // Method setScale:(I)V
      31: aload_0
      32: aload         6
      34: invokevirtual #7                  // Method setLogicalColumnName:(Ljava/lang/String;)V
      37: aload_0
      38: iload         7
      40: invokevirtual #8                  // Method setNullable:(Z)V
      43: aload_0
      44: iload         8
      46: invokevirtual #9                  // Method setUnique:(Z)V
      49: aload_0
      50: iload         9
      52: invokevirtual #10                 // Method setInsertable:(Z)V
      55: aload_0
      56: iload         10
      58: invokevirtual #11                 // Method setUpdatable:(Z)V
      61: aload_0
      62: aload         11
      64: invokevirtual #12                 // Method setExplicitTableName:(Ljava/lang/String;)V
      67: aload_0
      68: aload         13
      70: invokevirtual #13                 // Method setPropertyHolder:(Lorg/hibernate/cfg/PropertyHolder;)V
      73: aload_0
      74: aload         12
      76: invokevirtual #14                 // Method setJoins:(Ljava/util/Map;)V
      79: aload_0
      80: aload         14
      82: invokevirtual #15                 // Method setBuildingContext:(Lorg/hibernate/boot/spi/MetadataBuildingContext;)V
      85: aload_0
      86: invokevirtual #16                 // Method bind:()V
      89: return

  public int getBase();
    Code:
       0: aload_0
       1: getfield      #17                 // Field base:I
       4: ireturn

  public void setBase(int);
    Code:
       0: aload_0
       1: iload_1
       2: putfield      #17                 // Field base:I
       5: return

  public static org.hibernate.cfg.IndexColumn buildColumnFromAnnotation(javax.persistence.OrderColumn, org.hibernate.cfg.PropertyHolder, org.hibernate.cfg.PropertyData, java.util.Map<java.lang.String, org.hibernate.mapping.Join>, org.hibernate.boot.spi.MetadataBuildingContext);
    Code:
       0: aload_0
       1: ifnull        119
       4: aload_0
       5: invokeinterface #18,  1           // InterfaceMethod javax/persistence/OrderColumn.columnDefinition:()Ljava/lang/String;
      10: invokestatic  #19                 // Method org/hibernate/cfg/BinderHelper.isEmptyAnnotationValue:(Ljava/lang/String;)Z
      13: ifeq          20
      16: aconst_null
      17: goto          26
      20: aload_0
      21: invokeinterface #18,  1           // InterfaceMethod javax/persistence/OrderColumn.columnDefinition:()Ljava/lang/String;
      26: astore        6
      28: aload_0
      29: invokeinterface #20,  1           // InterfaceMethod javax/persistence/OrderColumn.name:()Ljava/lang/String;
      34: invokestatic  #19                 // Method org/hibernate/cfg/BinderHelper.isEmptyAnnotationValue:(Ljava/lang/String;)Z
      37: ifeq          67
      40: new           #21                 // class java/lang/StringBuilder
      43: dup
      44: invokespecial #22                 // Method java/lang/StringBuilder."<init>":()V
      47: aload_2
      48: invokeinterface #23,  1           // InterfaceMethod org/hibernate/cfg/PropertyData.getPropertyName:()Ljava/lang/String;
      53: invokevirtual #24                 // Method java/lang/StringBuilder.append:(Ljava/lang/String;)Ljava/lang/StringBuilder;
      56: ldc           #25                 // String _ORDER
      58: invokevirtual #24                 // Method java/lang/StringBuilder.append:(Ljava/lang/String;)Ljava/lang/StringBuilder;
      61: invokevirtual #26                 // Method java/lang/StringBuilder.toString:()Ljava/lang/String;
      64: goto          73
      67: aload_0
      68: invokeinterface #20,  1           // InterfaceMethod javax/persistence/OrderColumn.name:()Ljava/lang/String;
      73: astore        7
      75: new           #27                 // class org/hibernate/cfg/IndexColumn
      78: dup
      79: iconst_0
      80: aload         6
      82: iconst_0
      83: iconst_0
      84: iconst_0
      85: aload         7
      87: aload_0
      88: invokeinterface #28,  1           // InterfaceMethod javax/persistence/OrderColumn.nullable:()Z
      93: iconst_0
      94: aload_0
      95: invokeinterface #29,  1           // InterfaceMethod javax/persistence/OrderColumn.insertable:()Z
     100: aload_0
     101: invokeinterface #30,  1           // InterfaceMethod javax/persistence/OrderColumn.updatable:()Z
     106: aconst_null
     107: aload_3
     108: aload_1
     109: aload         4
     111: invokespecial #31                 // Method "<init>":(ZLjava/lang/String;IIILjava/lang/String;ZZZZLjava/lang/String;Ljava/util/Map;Lorg/hibernate/cfg/PropertyHolder;Lorg/hibernate/boot/spi/MetadataBuildingContext;)V
     114: astore        5
     116: goto          143
     119: new           #27                 // class org/hibernate/cfg/IndexColumn
     122: dup
     123: iconst_1
     124: aconst_null
     125: iconst_0
     126: iconst_0
     127: iconst_0
     128: aconst_null
     129: iconst_1
     130: iconst_0
     131: iconst_1
     132: iconst_1
     133: aconst_null
     134: aconst_null
     135: aload_1
     136: aload         4
     138: invokespecial #31                 // Method "<init>":(ZLjava/lang/String;IIILjava/lang/String;ZZZZLjava/lang/String;Ljava/util/Map;Lorg/hibernate/cfg/PropertyHolder;Lorg/hibernate/boot/spi/MetadataBuildingContext;)V
     141: astore        5
     143: aload         5
     145: areturn

  public static org.hibernate.cfg.IndexColumn buildColumnFromAnnotation(org.hibernate.annotations.IndexColumn, org.hibernate.cfg.PropertyHolder, org.hibernate.cfg.PropertyData, org.hibernate.boot.spi.MetadataBuildingContext);
    Code:
       0: aload_0
       1: ifnull        101
       4: aload_0
       5: invokeinterface #32,  1           // InterfaceMethod org/hibernate/annotations/IndexColumn.columnDefinition:()Ljava/lang/String;
      10: invokestatic  #19                 // Method org/hibernate/cfg/BinderHelper.isEmptyAnnotationValue:(Ljava/lang/String;)Z
      13: ifeq          20
      16: aconst_null
      17: goto          26
      20: aload_0
      21: invokeinterface #32,  1           // InterfaceMethod org/hibernate/annotations/IndexColumn.columnDefinition:()Ljava/lang/String;
      26: astore        5
      28: aload_0
      29: invokeinterface #33,  1           // InterfaceMethod org/hibernate/annotations/IndexColumn.name:()Ljava/lang/String;
      34: invokestatic  #19                 // Method org/hibernate/cfg/BinderHelper.isEmptyAnnotationValue:(Ljava/lang/String;)Z
      37: ifeq          49
      40: aload_2
      41: invokeinterface #23,  1           // InterfaceMethod org/hibernate/cfg/PropertyData.getPropertyName:()Ljava/lang/String;
      46: goto          55
      49: aload_0
      50: invokeinterface #33,  1           // InterfaceMethod org/hibernate/annotations/IndexColumn.name:()Ljava/lang/String;
      55: astore        6
      57: new           #27                 // class org/hibernate/cfg/IndexColumn
      60: dup
      61: iconst_0
      62: aload         5
      64: iconst_0
      65: iconst_0
      66: iconst_0
      67: aload         6
      69: aload_0
      70: invokeinterface #34,  1           // InterfaceMethod org/hibernate/annotations/IndexColumn.nullable:()Z
      75: iconst_0
      76: iconst_1
      77: iconst_1
      78: aconst_null
      79: aconst_null
      80: aload_1
      81: aload_3
      82: invokespecial #31                 // Method "<init>":(ZLjava/lang/String;IIILjava/lang/String;ZZZZLjava/lang/String;Ljava/util/Map;Lorg/hibernate/cfg/PropertyHolder;Lorg/hibernate/boot/spi/MetadataBuildingContext;)V
      85: astore        4
      87: aload         4
      89: aload_0
      90: invokeinterface #35,  1           // InterfaceMethod org/hibernate/annotations/IndexColumn.base:()I
      95: invokevirtual #36                 // Method setBase:(I)V
      98: goto          124
     101: new           #27                 // class org/hibernate/cfg/IndexColumn
     104: dup
     105: iconst_1
     106: aconst_null
     107: iconst_0
     108: iconst_0
     109: iconst_0
     110: aconst_null
     111: iconst_1
     112: iconst_0
     113: iconst_1
     114: iconst_1
     115: aconst_null
     116: aconst_null
     117: aload_1
     118: aload_3
     119: invokespecial #31                 // Method "<init>":(ZLjava/lang/String;IIILjava/lang/String;ZZZZLjava/lang/String;Ljava/util/Map;Lorg/hibernate/cfg/PropertyHolder;Lorg/hibernate/boot/spi/MetadataBuildingContext;)V
     122: astore        4
     124: aload         4
     126: areturn
}
