Compiled from "CouchbaseDataConfiguration.java"
class org.springframework.boot.autoconfigure.data.couchbase.CouchbaseDataConfiguration {
  org.springframework.boot.autoconfigure.data.couchbase.CouchbaseDataConfiguration();
    Code:
       0: aload_0
       1: invokespecial #1                  // Method java/lang/Object."<init>":()V
       4: return

  org.springframework.data.couchbase.core.convert.MappingCouchbaseConverter couchbaseMappingConverter(org.springframework.boot.autoconfigure.data.couchbase.CouchbaseDataProperties, org.springframework.data.couchbase.core.mapping.CouchbaseMappingContext, org.springframework.data.couchbase.core.convert.CouchbaseCustomConversions);
    Code:
       0: new           #2                  // class org/springframework/data/couchbase/core/convert/MappingCouchbaseConverter
       3: dup
       4: aload_2
       5: aload_1
       6: invokevirtual #3                  // Method org/springframework/boot/autoconfigure/data/couchbase/CouchbaseDataProperties.getTypeKey:()Ljava/lang/String;
       9: invokespecial #4                  // Method org/springframework/data/couchbase/core/convert/MappingCouchbaseConverter."<init>":(Lorg/springframework/data/mapping/context/MappingContext;Ljava/lang/String;)V
      12: astore        4
      14: aload         4
      16: aload_3
      17: invokevirtual #5                  // Method org/springframework/data/couchbase/core/convert/MappingCouchbaseConverter.setCustomConversions:(Lorg/springframework/data/convert/CustomConversions;)V
      20: aload         4
      22: areturn

  org.springframework.data.couchbase.core.convert.translation.TranslationService couchbaseTranslationService();
    Code:
       0: new           #6                  // class org/springframework/data/couchbase/core/convert/translation/JacksonTranslationService
       3: dup
       4: invokespecial #7                  // Method org/springframework/data/couchbase/core/convert/translation/JacksonTranslationService."<init>":()V
       7: areturn

  org.springframework.data.couchbase.core.mapping.CouchbaseMappingContext couchbaseMappingContext(org.springframework.boot.autoconfigure.data.couchbase.CouchbaseDataProperties, org.springframework.context.ApplicationContext, org.springframework.data.couchbase.core.convert.CouchbaseCustomConversions) throws java.lang.Exception;
    Code:
       0: new           #8                  // class org/springframework/data/couchbase/core/mapping/CouchbaseMappingContext
       3: dup
       4: invokespecial #9                  // Method org/springframework/data/couchbase/core/mapping/CouchbaseMappingContext."<init>":()V
       7: astore        4
       9: aload         4
      11: new           #10                 // class org/springframework/boot/autoconfigure/domain/EntityScanner
      14: dup
      15: aload_2
      16: invokespecial #11                 // Method org/springframework/boot/autoconfigure/domain/EntityScanner."<init>":(Lorg/springframework/context/ApplicationContext;)V
      19: iconst_2
      20: anewarray     #12                 // class java/lang/Class
      23: dup
      24: iconst_0
      25: ldc           #13                 // class org/springframework/data/couchbase/core/mapping/Document
      27: aastore
      28: dup
      29: iconst_1
      30: ldc           #14                 // class org/springframework/data/annotation/Persistent
      32: aastore
      33: invokevirtual #15                 // Method org/springframework/boot/autoconfigure/domain/EntityScanner.scan:([Ljava/lang/Class;)Ljava/util/Set;
      36: invokevirtual #16                 // Method org/springframework/data/couchbase/core/mapping/CouchbaseMappingContext.setInitialEntitySet:(Ljava/util/Set;)V
      39: aload         4
      41: aload_3
      42: invokevirtual #17                 // Method org/springframework/data/couchbase/core/convert/CouchbaseCustomConversions.getSimpleTypeHolder:()Lorg/springframework/data/mapping/model/SimpleTypeHolder;
      45: invokevirtual #18                 // Method org/springframework/data/couchbase/core/mapping/CouchbaseMappingContext.setSimpleTypeHolder:(Lorg/springframework/data/mapping/model/SimpleTypeHolder;)V
      48: aload_1
      49: invokevirtual #19                 // Method org/springframework/boot/autoconfigure/data/couchbase/CouchbaseDataProperties.getFieldNamingStrategy:()Ljava/lang/Class;
      52: astore        5
      54: aload         5
      56: ifnull        72
      59: aload         4
      61: aload         5
      63: invokestatic  #20                 // Method org/springframework/beans/BeanUtils.instantiateClass:(Ljava/lang/Class;)Ljava/lang/Object;
      66: checkcast     #21                 // class org/springframework/data/mapping/model/FieldNamingStrategy
      69: invokevirtual #22                 // Method org/springframework/data/couchbase/core/mapping/CouchbaseMappingContext.setFieldNamingStrategy:(Lorg/springframework/data/mapping/model/FieldNamingStrategy;)V
      72: aload         4
      74: aload_1
      75: invokevirtual #23                 // Method org/springframework/boot/autoconfigure/data/couchbase/CouchbaseDataProperties.isAutoIndex:()Z
      78: invokevirtual #24                 // Method org/springframework/data/couchbase/core/mapping/CouchbaseMappingContext.setAutoIndexCreation:(Z)V
      81: aload         4
      83: areturn

  org.springframework.data.couchbase.core.convert.CouchbaseCustomConversions couchbaseCustomConversions();
    Code:
       0: new           #25                 // class org/springframework/data/couchbase/core/convert/CouchbaseCustomConversions
       3: dup
       4: invokestatic  #26                 // Method java/util/Collections.emptyList:()Ljava/util/List;
       7: invokespecial #27                 // Method org/springframework/data/couchbase/core/convert/CouchbaseCustomConversions."<init>":(Ljava/util/List;)V
      10: areturn
}
