Compiled from "ListFilesOnDiscCommand.java"
public class org.apache.bookkeeper.tools.cli.commands.bookie.ListFilesOnDiscCommand$LFODFlags extends org.apache.bookkeeper.tools.framework.CliFlags {
  private boolean journal;

  private boolean entrylog;

  private boolean index;

  public org.apache.bookkeeper.tools.cli.commands.bookie.ListFilesOnDiscCommand$LFODFlags();
    Code:
       0: aload_0
       1: invokespecial #4                  // Method org/apache/bookkeeper/tools/framework/CliFlags."<init>":()V
       4: return

  public org.apache.bookkeeper.tools.cli.commands.bookie.ListFilesOnDiscCommand$LFODFlags journal(boolean);
    Code:
       0: aload_0
       1: iload_1
       2: putfield      #3                  // Field journal:Z
       5: aload_0
       6: areturn

  public org.apache.bookkeeper.tools.cli.commands.bookie.ListFilesOnDiscCommand$LFODFlags entrylog(boolean);
    Code:
       0: aload_0
       1: iload_1
       2: putfield      #2                  // Field entrylog:Z
       5: aload_0
       6: areturn

  public org.apache.bookkeeper.tools.cli.commands.bookie.ListFilesOnDiscCommand$LFODFlags index(boolean);
    Code:
       0: aload_0
       1: iload_1
       2: putfield      #1                  // Field index:Z
       5: aload_0
       6: areturn

  static boolean access$000(org.apache.bookkeeper.tools.cli.commands.bookie.ListFilesOnDiscCommand$LFODFlags);
    Code:
       0: aload_0
       1: getfield      #3                  // Field journal:Z
       4: ireturn

  static boolean access$100(org.apache.bookkeeper.tools.cli.commands.bookie.ListFilesOnDiscCommand$LFODFlags);
    Code:
       0: aload_0
       1: getfield      #2                  // Field entrylog:Z
       4: ireturn

  static boolean access$200(org.apache.bookkeeper.tools.cli.commands.bookie.ListFilesOnDiscCommand$LFODFlags);
    Code:
       0: aload_0
       1: getfield      #1                  // Field index:Z
       4: ireturn
}
