Compiled from "NumberDomainsExceededException.java"
public class com.amazonaws.services.simpledb.model.NumberDomainsExceededException extends com.amazonaws.AmazonServiceException {
  private static final long serialVersionUID;

  private java.lang.Float boxUsage;

  public com.amazonaws.services.simpledb.model.NumberDomainsExceededException(java.lang.String);
    Code:
       0: aload_0
       1: aload_1
       2: invokespecial #1                  // Method com/amazonaws/AmazonServiceException."<init>":(Ljava/lang/String;)V
       5: return

  public void setBoxUsage(java.lang.Float);
    Code:
       0: aload_0
       1: aload_1
       2: putfield      #2                  // Field boxUsage:Ljava/lang/Float;
       5: return

  public java.lang.Float getBoxUsage();
    Code:
       0: aload_0
       1: getfield      #2                  // Field boxUsage:Ljava/lang/Float;
       4: areturn

  public com.amazonaws.services.simpledb.model.NumberDomainsExceededException withBoxUsage(java.lang.Float);
    Code:
       0: aload_0
       1: aload_1
       2: invokevirtual #3                  // Method setBoxUsage:(Ljava/lang/Float;)V
       5: aload_0
       6: areturn
}
