Compiled from "Stream.java"
public final class org.graylog2.plugin.streams.Stream$MatchingType extends java.lang.Enum<org.graylog2.plugin.streams.Stream$MatchingType> {
  public static final org.graylog2.plugin.streams.Stream$MatchingType AND;

  public static final org.graylog2.plugin.streams.Stream$MatchingType OR;

  public static final org.graylog2.plugin.streams.Stream$MatchingType DEFAULT;

  private static final org.graylog2.plugin.streams.Stream$MatchingType[] $VALUES;

  public static org.graylog2.plugin.streams.Stream$MatchingType[] values();
    Code:
       0: getstatic     #1                  // Field $VALUES:[Lorg/graylog2/plugin/streams/Stream$MatchingType;
       3: invokevirtual #2                  // Method "[Lorg/graylog2/plugin/streams/Stream$MatchingType;".clone:()Ljava/lang/Object;
       6: checkcast     #3                  // class "[Lorg/graylog2/plugin/streams/Stream$MatchingType;"
       9: areturn

  public static org.graylog2.plugin.streams.Stream$MatchingType valueOf(java.lang.String);
    Code:
       0: ldc           #4                  // class org/graylog2/plugin/streams/Stream$MatchingType
       2: aload_0
       3: invokestatic  #5                  // Method java/lang/Enum.valueOf:(Ljava/lang/Class;Ljava/lang/String;)Ljava/lang/Enum;
       6: checkcast     #4                  // class org/graylog2/plugin/streams/Stream$MatchingType
       9: areturn

  private org.graylog2.plugin.streams.Stream$MatchingType();
    Code:
       0: aload_0
       1: aload_1
       2: iload_2
       3: invokespecial #6                  // Method java/lang/Enum."<init>":(Ljava/lang/String;I)V
       6: return

  public static org.graylog2.plugin.streams.Stream$MatchingType valueOfOrDefault(java.lang.String);
    Code:
       0: aload_0
       1: invokestatic  #7                  // Method com/google/common/base/Strings.emptyToNull:(Ljava/lang/String;)Ljava/lang/String;
       4: ifnonnull     13
       7: getstatic     #8                  // Field DEFAULT:Lorg/graylog2/plugin/streams/Stream$MatchingType;
      10: goto          17
      13: aload_0
      14: invokestatic  #9                  // Method valueOf:(Ljava/lang/String;)Lorg/graylog2/plugin/streams/Stream$MatchingType;
      17: areturn

  static {};
    Code:
       0: new           #4                  // class org/graylog2/plugin/streams/Stream$MatchingType
       3: dup
       4: ldc           #10                 // String AND
       6: iconst_0
       7: invokespecial #11                 // Method "<init>":(Ljava/lang/String;I)V
      10: putstatic     #12                 // Field AND:Lorg/graylog2/plugin/streams/Stream$MatchingType;
      13: new           #4                  // class org/graylog2/plugin/streams/Stream$MatchingType
      16: dup
      17: ldc           #13                 // String OR
      19: iconst_1
      20: invokespecial #11                 // Method "<init>":(Ljava/lang/String;I)V
      23: putstatic     #14                 // Field OR:Lorg/graylog2/plugin/streams/Stream$MatchingType;
      26: iconst_2
      27: anewarray     #4                  // class org/graylog2/plugin/streams/Stream$MatchingType
      30: dup
      31: iconst_0
      32: getstatic     #12                 // Field AND:Lorg/graylog2/plugin/streams/Stream$MatchingType;
      35: aastore
      36: dup
      37: iconst_1
      38: getstatic     #14                 // Field OR:Lorg/graylog2/plugin/streams/Stream$MatchingType;
      41: aastore
      42: putstatic     #1                  // Field $VALUES:[Lorg/graylog2/plugin/streams/Stream$MatchingType;
      45: getstatic     #12                 // Field AND:Lorg/graylog2/plugin/streams/Stream$MatchingType;
      48: putstatic     #8                  // Field DEFAULT:Lorg/graylog2/plugin/streams/Stream$MatchingType;
      51: return
}
