Compiled from "DefaultSchemaNameResolver.java"
public class org.hibernate.engine.jdbc.env.internal.DefaultSchemaNameResolver implements org.hibernate.engine.jdbc.env.spi.SchemaNameResolver {
  private static final org.jboss.logging.Logger log;

  public static final org.hibernate.engine.jdbc.env.internal.DefaultSchemaNameResolver INSTANCE;

  private org.hibernate.engine.jdbc.env.internal.DefaultSchemaNameResolver();
    Code:
       0: aload_0
       1: invokespecial #1                  // Method java/lang/Object."<init>":()V
       4: return

  private org.hibernate.engine.jdbc.env.spi.SchemaNameResolver determineAppropriateResolverDelegate(java.sql.Connection);
    Code:
       0: aload_1
       1: invokevirtual #2                  // Method java/lang/Object.getClass:()Ljava/lang/Class;
       4: astore_2
       5: aload_2
       6: ldc           #3                  // String getSchema
       8: iconst_0
       9: anewarray     #4                  // class java/lang/Class
      12: invokevirtual #5                  // Method java/lang/Class.getMethod:(Ljava/lang/String;[Ljava/lang/Class;)Ljava/lang/reflect/Method;
      15: astore_3
      16: aload_3
      17: ifnull        65
      20: aload_3
      21: invokevirtual #6                  // Method java/lang/reflect/Method.getReturnType:()Ljava/lang/Class;
      24: ldc           #7                  // class java/lang/String
      26: invokevirtual #8                  // Method java/lang/Object.equals:(Ljava/lang/Object;)Z
      29: ifeq          65
      32: aload_1
      33: invokeinterface #9,  1            // InterfaceMethod java/sql/Connection.getSchema:()Ljava/lang/String;
      38: pop
      39: new           #10                 // class org/hibernate/engine/jdbc/env/internal/DefaultSchemaNameResolver$SchemaNameResolverJava17Delegate
      42: dup
      43: invokespecial #11                 // Method org/hibernate/engine/jdbc/env/internal/DefaultSchemaNameResolver$SchemaNameResolverJava17Delegate."<init>":()V
      46: areturn
      47: astore        4
      49: getstatic     #13                 // Field log:Lorg/jboss/logging/Logger;
      52: ldc           #14                 // String Unable to use Java 1.7 Connection#getSchema
      54: iconst_0
      55: anewarray     #15                 // class java/lang/Object
      58: invokevirtual #16                 // Method org/jboss/logging/Logger.debugf:(Ljava/lang/String;[Ljava/lang/Object;)V
      61: getstatic     #17                 // Field org/hibernate/engine/jdbc/env/internal/DefaultSchemaNameResolver$SchemaNameResolverFallbackDelegate.INSTANCE:Lorg/hibernate/engine/jdbc/env/internal/DefaultSchemaNameResolver$SchemaNameResolverFallbackDelegate;
      64: areturn
      65: getstatic     #13                 // Field log:Lorg/jboss/logging/Logger;
      68: ldc           #14                 // String Unable to use Java 1.7 Connection#getSchema
      70: iconst_0
      71: anewarray     #15                 // class java/lang/Object
      74: invokevirtual #16                 // Method org/jboss/logging/Logger.debugf:(Ljava/lang/String;[Ljava/lang/Object;)V
      77: getstatic     #17                 // Field org/hibernate/engine/jdbc/env/internal/DefaultSchemaNameResolver$SchemaNameResolverFallbackDelegate.INSTANCE:Lorg/hibernate/engine/jdbc/env/internal/DefaultSchemaNameResolver$SchemaNameResolverFallbackDelegate;
      80: areturn
      81: astore_2
      82: getstatic     #13                 // Field log:Lorg/jboss/logging/Logger;
      85: new           #19                 // class java/lang/StringBuilder
      88: dup
      89: invokespecial #20                 // Method java/lang/StringBuilder."<init>":()V
      92: ldc           #21                 // String Unable to use Java 1.7 Connection#getSchema : An error occurred trying to resolve the connection default schema resolver:
      94: invokevirtual #22                 // Method java/lang/StringBuilder.append:(Ljava/lang/String;)Ljava/lang/StringBuilder;
      97: aload_2
      98: invokevirtual #23                 // Method java/lang/Exception.getMessage:()Ljava/lang/String;
     101: invokevirtual #22                 // Method java/lang/StringBuilder.append:(Ljava/lang/String;)Ljava/lang/StringBuilder;
     104: invokevirtual #24                 // Method java/lang/StringBuilder.toString:()Ljava/lang/String;
     107: iconst_0
     108: anewarray     #15                 // class java/lang/Object
     111: invokevirtual #16                 // Method org/jboss/logging/Logger.debugf:(Ljava/lang/String;[Ljava/lang/Object;)V
     114: getstatic     #17                 // Field org/hibernate/engine/jdbc/env/internal/DefaultSchemaNameResolver$SchemaNameResolverFallbackDelegate.INSTANCE:Lorg/hibernate/engine/jdbc/env/internal/DefaultSchemaNameResolver$SchemaNameResolverFallbackDelegate;
     117: areturn
    Exception table:
       from    to  target type
          32    46    47   Class java/lang/AbstractMethodError
           0    46    81   Class java/lang/Exception
          47    64    81   Class java/lang/Exception
          65    80    81   Class java/lang/Exception

  public java.lang.String resolveSchemaName(java.sql.Connection, org.hibernate.dialect.Dialect) throws java.sql.SQLException;
    Code:
       0: aload_0
       1: aload_1
       2: invokespecial #25                 // Method determineAppropriateResolverDelegate:(Ljava/sql/Connection;)Lorg/hibernate/engine/jdbc/env/spi/SchemaNameResolver;
       5: astore_3
       6: aload_3
       7: aload_1
       8: aload_2
       9: invokeinterface #26,  3           // InterfaceMethod org/hibernate/engine/jdbc/env/spi/SchemaNameResolver.resolveSchemaName:(Ljava/sql/Connection;Lorg/hibernate/dialect/Dialect;)Ljava/lang/String;
      14: areturn

  static {};
    Code:
       0: ldc           #27                 // class org/hibernate/engine/jdbc/env/internal/DefaultSchemaNameResolver
       2: invokestatic  #28                 // Method org/jboss/logging/Logger.getLogger:(Ljava/lang/Class;)Lorg/jboss/logging/Logger;
       5: putstatic     #13                 // Field log:Lorg/jboss/logging/Logger;
       8: new           #27                 // class org/hibernate/engine/jdbc/env/internal/DefaultSchemaNameResolver
      11: dup
      12: invokespecial #29                 // Method "<init>":()V
      15: putstatic     #30                 // Field INSTANCE:Lorg/hibernate/engine/jdbc/env/internal/DefaultSchemaNameResolver;
      18: return
}
