Compiled from "LogbackServletContainerInitializer.java"
public class ch.qos.logback.classic.servlet.LogbackServletContainerInitializer implements javax.servlet.ServletContainerInitializer {
  public ch.qos.logback.classic.servlet.LogbackServletContainerInitializer();
    Code:
       0: aload_0
       1: invokespecial #1                  // Method java/lang/Object."<init>":()V
       4: return

  public void onStartup(java.util.Set<java.lang.Class<?>>, javax.servlet.ServletContext) throws javax.servlet.ServletException;
    Code:
       0: aload_0
       1: aload_2
       2: invokevirtual #2                  // Method isDisabledByConfiguration:(Ljavax/servlet/ServletContext;)Z
       5: ifeq          39
       8: new           #3                  // class java/lang/StringBuilder
      11: dup
      12: invokespecial #4                  // Method java/lang/StringBuilder."<init>":()V
      15: ldc           #5                  // String Due to deployment instructions will NOT register an instance of
      17: invokevirtual #6                  // Method java/lang/StringBuilder.append:(Ljava/lang/String;)Ljava/lang/StringBuilder;
      20: ldc_w         #7                  // class ch/qos/logback/classic/servlet/LogbackServletContextListener
      23: invokevirtual #8                  // Method java/lang/StringBuilder.append:(Ljava/lang/Object;)Ljava/lang/StringBuilder;
      26: ldc           #9                  // String  to the current web-app
      28: invokevirtual #6                  // Method java/lang/StringBuilder.append:(Ljava/lang/String;)Ljava/lang/StringBuilder;
      31: invokevirtual #10                 // Method java/lang/StringBuilder.toString:()Ljava/lang/String;
      34: aload_0
      35: invokestatic  #11                 // Method ch/qos/logback/classic/util/StatusViaSLF4JLoggerFactory.addInfo:(Ljava/lang/String;Ljava/lang/Object;)V
      38: return
      39: new           #3                  // class java/lang/StringBuilder
      42: dup
      43: invokespecial #4                  // Method java/lang/StringBuilder."<init>":()V
      46: ldc           #12                 // String Adding an instance of
      48: invokevirtual #6                  // Method java/lang/StringBuilder.append:(Ljava/lang/String;)Ljava/lang/StringBuilder;
      51: ldc_w         #7                  // class ch/qos/logback/classic/servlet/LogbackServletContextListener
      54: invokevirtual #8                  // Method java/lang/StringBuilder.append:(Ljava/lang/Object;)Ljava/lang/StringBuilder;
      57: ldc           #9                  // String  to the current web-app
      59: invokevirtual #6                  // Method java/lang/StringBuilder.append:(Ljava/lang/String;)Ljava/lang/StringBuilder;
      62: invokevirtual #10                 // Method java/lang/StringBuilder.toString:()Ljava/lang/String;
      65: aload_0
      66: invokestatic  #11                 // Method ch/qos/logback/classic/util/StatusViaSLF4JLoggerFactory.addInfo:(Ljava/lang/String;Ljava/lang/Object;)V
      69: new           #7                  // class ch/qos/logback/classic/servlet/LogbackServletContextListener
      72: dup
      73: invokespecial #13                 // Method ch/qos/logback/classic/servlet/LogbackServletContextListener."<init>":()V
      76: astore_3
      77: aload_2
      78: aload_3
      79: invokeinterface #14,  2           // InterfaceMethod javax/servlet/ServletContext.addListener:(Ljava/util/EventListener;)V
      84: return

  boolean isDisabledByConfiguration(javax.servlet.ServletContext);
    Code:
       0: aconst_null
       1: astore_2
       2: aload_1
       3: ldc           #15                 // String logbackDisableServletContainerInitializer
       5: invokeinterface #16,  2           // InterfaceMethod javax/servlet/ServletContext.getInitParameter:(Ljava/lang/String;)Ljava/lang/String;
      10: astore_3
      11: aload_3
      12: instanceof    #17                 // class java/lang/String
      15: ifeq          23
      18: aload_3
      19: checkcast     #17                 // class java/lang/String
      22: astore_2
      23: aload_2
      24: invokestatic  #18                 // Method ch/qos/logback/core/util/OptionHelper.isEmpty:(Ljava/lang/String;)Z
      27: ifeq          36
      30: ldc           #15                 // String logbackDisableServletContainerInitializer
      32: invokestatic  #19                 // Method ch/qos/logback/core/util/OptionHelper.getSystemProperty:(Ljava/lang/String;)Ljava/lang/String;
      35: astore_2
      36: aload_2
      37: invokestatic  #18                 // Method ch/qos/logback/core/util/OptionHelper.isEmpty:(Ljava/lang/String;)Z
      40: ifeq          49
      43: ldc           #15                 // String logbackDisableServletContainerInitializer
      45: invokestatic  #20                 // Method ch/qos/logback/core/util/OptionHelper.getEnv:(Ljava/lang/String;)Ljava/lang/String;
      48: astore_2
      49: aload_2
      50: invokestatic  #18                 // Method ch/qos/logback/core/util/OptionHelper.isEmpty:(Ljava/lang/String;)Z
      53: ifeq          58
      56: iconst_0
      57: ireturn
      58: aload_2
      59: ldc           #21                 // String true
      61: invokevirtual #22                 // Method java/lang/String.equalsIgnoreCase:(Ljava/lang/String;)Z
      64: ireturn
}
