Compiled from "ValidationHandler.java"
public class io.fabric8.camel.tooling.util.ValidationHandler implements org.xml.sax.ErrorHandler {
  java.util.List<org.xml.sax.SAXParseException> warnings;

  java.util.List<org.xml.sax.SAXParseException> errors;

  java.util.List<org.xml.sax.SAXParseException> fatalErrors;

  public io.fabric8.camel.tooling.util.ValidationHandler();
    Code:
       0: aload_0
       1: invokespecial #1                  // Method java/lang/Object."<init>":()V
       4: aload_0
       5: new           #2                  // class java/util/LinkedList
       8: dup
       9: invokespecial #3                  // Method java/util/LinkedList."<init>":()V
      12: putfield      #4                  // Field warnings:Ljava/util/List;
      15: aload_0
      16: new           #2                  // class java/util/LinkedList
      19: dup
      20: invokespecial #3                  // Method java/util/LinkedList."<init>":()V
      23: putfield      #5                  // Field errors:Ljava/util/List;
      26: aload_0
      27: new           #2                  // class java/util/LinkedList
      30: dup
      31: invokespecial #3                  // Method java/util/LinkedList."<init>":()V
      34: putfield      #6                  // Field fatalErrors:Ljava/util/List;
      37: return

  public void warning(org.xml.sax.SAXParseException) throws org.xml.sax.SAXException;
    Code:
       0: aload_0
       1: getfield      #4                  // Field warnings:Ljava/util/List;
       4: aload_1
       5: invokeinterface #7,  2            // InterfaceMethod java/util/List.add:(Ljava/lang/Object;)Z
      10: pop
      11: return

  public void error(org.xml.sax.SAXParseException) throws org.xml.sax.SAXException;
    Code:
       0: aload_0
       1: getfield      #5                  // Field errors:Ljava/util/List;
       4: aload_1
       5: invokeinterface #7,  2            // InterfaceMethod java/util/List.add:(Ljava/lang/Object;)Z
      10: pop
      11: return

  public void fatalError(org.xml.sax.SAXParseException) throws org.xml.sax.SAXException;
    Code:
       0: aload_0
       1: getfield      #6                  // Field fatalErrors:Ljava/util/List;
       4: aload_1
       5: invokeinterface #7,  2            // InterfaceMethod java/util/List.add:(Ljava/lang/Object;)Z
      10: pop
      11: return

  public java.util.List<org.xml.sax.SAXParseException> getWarnings();
    Code:
       0: aload_0
       1: getfield      #4                  // Field warnings:Ljava/util/List;
       4: areturn

  public java.util.List<org.xml.sax.SAXParseException> getErrors();
    Code:
       0: aload_0
       1: getfield      #5                  // Field errors:Ljava/util/List;
       4: areturn

  public java.util.List<org.xml.sax.SAXParseException> getFatalErrors();
    Code:
       0: aload_0
       1: getfield      #6                  // Field fatalErrors:Ljava/util/List;
       4: areturn

  public java.lang.String userMessage();
    Code:
       0: new           #8                  // class java/io/StringWriter
       3: dup
       4: invokespecial #9                  // Method java/io/StringWriter."<init>":()V
       7: astore_1
       8: aload_0
       9: getfield      #5                  // Field errors:Ljava/util/List;
      12: invokeinterface #10,  1           // InterfaceMethod java/util/List.iterator:()Ljava/util/Iterator;
      17: astore_2
      18: aload_2
      19: invokeinterface #11,  1           // InterfaceMethod java/util/Iterator.hasNext:()Z
      24: ifeq          54
      27: aload_2
      28: invokeinterface #12,  1           // InterfaceMethod java/util/Iterator.next:()Ljava/lang/Object;
      33: checkcast     #13                 // class org/xml/sax/SAXParseException
      36: astore_3
      37: aload_1
      38: ldc           #14                 // String ,
      40: invokevirtual #15                 // Method java/io/StringWriter.append:(Ljava/lang/CharSequence;)Ljava/io/StringWriter;
      43: aload_3
      44: invokevirtual #16                 // Method org/xml/sax/SAXParseException.getMessage:()Ljava/lang/String;
      47: invokevirtual #15                 // Method java/io/StringWriter.append:(Ljava/lang/CharSequence;)Ljava/io/StringWriter;
      50: pop
      51: goto          18
      54: aload_0
      55: getfield      #6                  // Field fatalErrors:Ljava/util/List;
      58: invokeinterface #10,  1           // InterfaceMethod java/util/List.iterator:()Ljava/util/Iterator;
      63: astore_2
      64: aload_2
      65: invokeinterface #11,  1           // InterfaceMethod java/util/Iterator.hasNext:()Z
      70: ifeq          100
      73: aload_2
      74: invokeinterface #12,  1           // InterfaceMethod java/util/Iterator.next:()Ljava/lang/Object;
      79: checkcast     #13                 // class org/xml/sax/SAXParseException
      82: astore_3
      83: aload_1
      84: ldc           #14                 // String ,
      86: invokevirtual #15                 // Method java/io/StringWriter.append:(Ljava/lang/CharSequence;)Ljava/io/StringWriter;
      89: aload_3
      90: invokevirtual #16                 // Method org/xml/sax/SAXParseException.getMessage:()Ljava/lang/String;
      93: invokevirtual #15                 // Method java/io/StringWriter.append:(Ljava/lang/CharSequence;)Ljava/io/StringWriter;
      96: pop
      97: goto          64
     100: aload_1
     101: invokevirtual #17                 // Method java/io/StringWriter.toString:()Ljava/lang/String;
     104: astore_2
     105: aload_2
     106: invokevirtual #18                 // Method java/lang/String.length:()I
     109: iconst_2
     110: if_icmple     119
     113: aload_2
     114: iconst_2
     115: invokevirtual #19                 // Method java/lang/String.substring:(I)Ljava/lang/String;
     118: astore_2
     119: aload_2
     120: ldc           #20                 // String :
     122: invokevirtual #21                 // Method java/lang/String.indexOf:(Ljava/lang/String;)I
     125: istore_3
     126: aload_2
     127: ldc           #22                 // String cvc-complex-type
     129: invokevirtual #23                 // Method java/lang/String.startsWith:(Ljava/lang/String;)Z
     132: ifeq          150
     135: iload_3
     136: ifle          150
     139: aload_2
     140: iload_3
     141: iconst_1
     142: iadd
     143: invokevirtual #19                 // Method java/lang/String.substring:(I)Ljava/lang/String;
     146: invokevirtual #24                 // Method java/lang/String.trim:()Ljava/lang/String;
     149: astore_2
     150: getstatic     #25                 // Field io/fabric8/camel/tooling/util/CamelNamespaces.camelNamespaces:[Ljava/lang/String;
     153: astore        4
     155: aload         4
     157: arraylength
     158: istore        5
     160: iconst_0
     161: istore        6
     163: iload         6
     165: iload         5
     167: if_icmpge     215
     170: aload         4
     172: iload         6
     174: aaload
     175: astore        7
     177: aload_2
     178: new           #26                 // class java/lang/StringBuilder
     181: dup
     182: invokespecial #27                 // Method java/lang/StringBuilder."<init>":()V
     185: ldc           #28                 // String \"
     187: invokevirtual #29                 // Method java/lang/StringBuilder.append:(Ljava/lang/String;)Ljava/lang/StringBuilder;
     190: aload         7
     192: invokevirtual #29                 // Method java/lang/StringBuilder.append:(Ljava/lang/String;)Ljava/lang/StringBuilder;
     195: ldc           #30                 // String \":
     197: invokevirtual #29                 // Method java/lang/StringBuilder.append:(Ljava/lang/String;)Ljava/lang/StringBuilder;
     200: invokevirtual #31                 // Method java/lang/StringBuilder.toString:()Ljava/lang/String;
     203: ldc           #32                 // String
     205: invokevirtual #33                 // Method java/lang/String.replaceAll:(Ljava/lang/String;Ljava/lang/String;)Ljava/lang/String;
     208: astore_2
     209: iinc          6, 1
     212: goto          163
     215: aload_2
     216: areturn

  public void validate(de.pdark.decentxml.Document) throws java.io.IOException, org.xml.sax.SAXException;
    Code:
       0: invokestatic  #34                 // Method io/fabric8/camel/tooling/util/CamelNamespaces.camelSchemas:()Ljavax/xml/validation/Schema;
       3: invokevirtual #35                 // Method javax/xml/validation/Schema.newValidator:()Ljavax/xml/validation/Validator;
       6: astore_2
       7: aload_2
       8: aload_0
       9: invokevirtual #36                 // Method javax/xml/validation/Validator.setErrorHandler:(Lorg/xml/sax/ErrorHandler;)V
      12: aload_0
      13: aload_2
      14: aload_1
      15: invokevirtual #37                 // Method de/pdark/decentxml/Document.getRootElement:()Lde/pdark/decentxml/Element;
      18: invokespecial #38                 // Method validate:(Ljavax/xml/validation/Validator;Lde/pdark/decentxml/Element;)V
      21: return

  private void validate(javax.xml.validation.Validator, de.pdark.decentxml.Element) throws java.io.IOException, org.xml.sax.SAXException;
    Code:
       0: aload_2
       1: invokestatic  #39                 // Method io/fabric8/camel/tooling/util/CamelNamespaces.getNamespaceURI:(Lde/pdark/decentxml/Node;)Ljava/lang/String;
       4: astore_3
       5: aload_3
       6: ifnull        54
       9: getstatic     #25                 // Field io/fabric8/camel/tooling/util/CamelNamespaces.camelNamespaces:[Ljava/lang/String;
      12: invokestatic  #40                 // Method java/util/Arrays.asList:([Ljava/lang/Object;)Ljava/util/List;
      15: aload_3
      16: invokeinterface #41,  2           // InterfaceMethod java/util/List.contains:(Ljava/lang/Object;)Z
      21: ifeq          54
      24: aload_2
      25: aload_2
      26: invokestatic  #42                 // Method io/fabric8/camel/tooling/util/CamelNamespaces.nodeWithNamespacesToText:(Lde/pdark/decentxml/Node;Lde/pdark/decentxml/Element;)Ljava/lang/String;
      29: astore        4
      31: aload_1
      32: new           #43                 // class javax/xml/transform/stream/StreamSource
      35: dup
      36: new           #44                 // class java/io/StringReader
      39: dup
      40: aload         4
      42: invokespecial #45                 // Method java/io/StringReader."<init>":(Ljava/lang/String;)V
      45: invokespecial #46                 // Method javax/xml/transform/stream/StreamSource."<init>":(Ljava/io/Reader;)V
      48: invokevirtual #47                 // Method javax/xml/validation/Validator.validate:(Ljavax/xml/transform/Source;)V
      51: goto          108
      54: aload_2
      55: invokevirtual #48                 // Method de/pdark/decentxml/Element.getNodes:()Ljava/util/List;
      58: invokeinterface #10,  1           // InterfaceMethod java/util/List.iterator:()Ljava/util/Iterator;
      63: astore        4
      65: aload         4
      67: invokeinterface #11,  1           // InterfaceMethod java/util/Iterator.hasNext:()Z
      72: ifeq          108
      75: aload         4
      77: invokeinterface #12,  1           // InterfaceMethod java/util/Iterator.next:()Ljava/lang/Object;
      82: checkcast     #49                 // class de/pdark/decentxml/Node
      85: astore        5
      87: aload         5
      89: instanceof    #50                 // class de/pdark/decentxml/Element
      92: ifeq          105
      95: aload_0
      96: aload_1
      97: aload         5
      99: checkcast     #50                 // class de/pdark/decentxml/Element
     102: invokespecial #38                 // Method validate:(Ljavax/xml/validation/Validator;Lde/pdark/decentxml/Element;)V
     105: goto          65
     108: return

  public boolean hasErrors();
    Code:
       0: aload_0
       1: getfield      #5                  // Field errors:Ljava/util/List;
       4: invokeinterface #51,  1           // InterfaceMethod java/util/List.isEmpty:()Z
       9: ifeq          24
      12: aload_0
      13: getfield      #6                  // Field fatalErrors:Ljava/util/List;
      16: invokeinterface #51,  1           // InterfaceMethod java/util/List.isEmpty:()Z
      21: ifne          28
      24: iconst_1
      25: goto          29
      28: iconst_0
      29: ireturn

  public void checkForErrors() throws io.fabric8.camel.tooling.util.ValidationException;
    Code:
       0: aload_0
       1: invokevirtual #52                 // Method hasErrors:()Z
       4: ifeq          169
       7: new           #8                  // class java/io/StringWriter
      10: dup
      11: invokespecial #9                  // Method java/io/StringWriter."<init>":()V
      14: astore_1
      15: aload_0
      16: getfield      #5                  // Field errors:Ljava/util/List;
      19: invokeinterface #10,  1           // InterfaceMethod java/util/List.iterator:()Ljava/util/Iterator;
      24: astore_2
      25: aload_2
      26: invokeinterface #11,  1           // InterfaceMethod java/util/Iterator.hasNext:()Z
      31: ifeq          61
      34: aload_2
      35: invokeinterface #12,  1           // InterfaceMethod java/util/Iterator.next:()Ljava/lang/Object;
      40: checkcast     #13                 // class org/xml/sax/SAXParseException
      43: astore_3
      44: aload_1
      45: ldc           #14                 // String ,
      47: invokevirtual #15                 // Method java/io/StringWriter.append:(Ljava/lang/CharSequence;)Ljava/io/StringWriter;
      50: aload_3
      51: invokevirtual #16                 // Method org/xml/sax/SAXParseException.getMessage:()Ljava/lang/String;
      54: invokevirtual #15                 // Method java/io/StringWriter.append:(Ljava/lang/CharSequence;)Ljava/io/StringWriter;
      57: pop
      58: goto          25
      61: aload_0
      62: getfield      #6                  // Field fatalErrors:Ljava/util/List;
      65: invokeinterface #10,  1           // InterfaceMethod java/util/List.iterator:()Ljava/util/Iterator;
      70: astore_2
      71: aload_2
      72: invokeinterface #11,  1           // InterfaceMethod java/util/Iterator.hasNext:()Z
      77: ifeq          107
      80: aload_2
      81: invokeinterface #12,  1           // InterfaceMethod java/util/Iterator.next:()Ljava/lang/Object;
      86: checkcast     #13                 // class org/xml/sax/SAXParseException
      89: astore_3
      90: aload_1
      91: ldc           #14                 // String ,
      93: invokevirtual #15                 // Method java/io/StringWriter.append:(Ljava/lang/CharSequence;)Ljava/io/StringWriter;
      96: aload_3
      97: invokevirtual #16                 // Method org/xml/sax/SAXParseException.getMessage:()Ljava/lang/String;
     100: invokevirtual #15                 // Method java/io/StringWriter.append:(Ljava/lang/CharSequence;)Ljava/io/StringWriter;
     103: pop
     104: goto          71
     107: aload_1
     108: invokevirtual #17                 // Method java/io/StringWriter.toString:()Ljava/lang/String;
     111: astore_2
     112: aload_2
     113: invokevirtual #18                 // Method java/lang/String.length:()I
     116: iconst_2
     117: if_icmple     126
     120: aload_2
     121: iconst_2
     122: invokevirtual #19                 // Method java/lang/String.substring:(I)Ljava/lang/String;
     125: astore_2
     126: new           #53                 // class io/fabric8/camel/tooling/util/ValidationException
     129: dup
     130: new           #26                 // class java/lang/StringBuilder
     133: dup
     134: invokespecial #27                 // Method java/lang/StringBuilder."<init>":()V
     137: ldc           #54                 // String Validation failed:
     139: invokevirtual #29                 // Method java/lang/StringBuilder.append:(Ljava/lang/String;)Ljava/lang/StringBuilder;
     142: aload_2
     143: invokevirtual #29                 // Method java/lang/StringBuilder.append:(Ljava/lang/String;)Ljava/lang/StringBuilder;
     146: invokevirtual #31                 // Method java/lang/StringBuilder.toString:()Ljava/lang/String;
     149: aload_0
     150: invokevirtual #55                 // Method userMessage:()Ljava/lang/String;
     153: aload_0
     154: getfield      #5                  // Field errors:Ljava/util/List;
     157: aload_0
     158: getfield      #6                  // Field fatalErrors:Ljava/util/List;
     161: aload_0
     162: getfield      #4                  // Field warnings:Ljava/util/List;
     165: invokespecial #56                 // Method io/fabric8/camel/tooling/util/ValidationException."<init>":(Ljava/lang/String;Ljava/lang/String;Ljava/util/List;Ljava/util/List;Ljava/util/List;)V
     168: athrow
     169: return
}
