Compiled from "JDKStringConverter.java"
final class org.joda.convert.JDKStringConverter$16 extends org.joda.convert.JDKStringConverter {
  org.joda.convert.JDKStringConverter$16(java.lang.String, int, java.lang.Class);
    Code:
       0: aload_0
       1: aload_1
       2: iload_2
       3: aload_3
       4: aconst_null
       5: invokespecial #1                  // Method org/joda/convert/JDKStringConverter."<init>":(Ljava/lang/String;ILjava/lang/Class;Lorg/joda/convert/JDKStringConverter$1;)V
       8: return

  public java.lang.Object convertFromString(java.lang.Class<?>, java.lang.String);
    Code:
       0: aload_2
       1: invokestatic  #2                  // Method java/lang/Integer.parseInt:(Ljava/lang/String;)I
       4: istore_3
       5: new           #3                  // class java/util/concurrent/atomic/AtomicInteger
       8: dup
       9: iload_3
      10: invokespecial #4                  // Method java/util/concurrent/atomic/AtomicInteger."<init>":(I)V
      13: areturn
}
