Compiled from "FilterBasedLdapUserSearch.java"
public class org.springframework.security.ldap.search.FilterBasedLdapUserSearch implements org.springframework.security.ldap.search.LdapUserSearch {
  private static final org.apache.commons.logging.Log logger;

  private final org.springframework.ldap.core.ContextSource contextSource;

  private final javax.naming.directory.SearchControls searchControls;

  private java.lang.String searchBase;

  private final java.lang.String searchFilter;

  public org.springframework.security.ldap.search.FilterBasedLdapUserSearch(java.lang.String, java.lang.String, org.springframework.ldap.core.support.BaseLdapPathContextSource);
    Code:
       0: aload_0
       1: invokespecial #1                  // Method java/lang/Object."<init>":()V
       4: aload_0
       5: new           #2                  // class javax/naming/directory/SearchControls
       8: dup
       9: invokespecial #3                  // Method javax/naming/directory/SearchControls."<init>":()V
      12: putfield      #4                  // Field searchControls:Ljavax/naming/directory/SearchControls;
      15: aload_0
      16: ldc           #5                  // String
      18: putfield      #6                  // Field searchBase:Ljava/lang/String;
      21: aload_3
      22: ldc           #7                  // String contextSource must not be null
      24: invokestatic  #8                  // Method org/springframework/util/Assert.notNull:(Ljava/lang/Object;Ljava/lang/String;)V
      27: aload_2
      28: ldc           #9                  // String searchFilter must not be null.
      30: invokestatic  #8                  // Method org/springframework/util/Assert.notNull:(Ljava/lang/Object;Ljava/lang/String;)V
      33: aload_1
      34: ldc           #10                 // String searchBase must not be null (an empty string is acceptable).
      36: invokestatic  #8                  // Method org/springframework/util/Assert.notNull:(Ljava/lang/Object;Ljava/lang/String;)V
      39: aload_0
      40: aload_2
      41: putfield      #11                 // Field searchFilter:Ljava/lang/String;
      44: aload_0
      45: aload_3
      46: putfield      #12                 // Field contextSource:Lorg/springframework/ldap/core/ContextSource;
      49: aload_0
      50: aload_1
      51: putfield      #6                  // Field searchBase:Ljava/lang/String;
      54: aload_0
      55: iconst_1
      56: invokevirtual #13                 // Method setSearchSubtree:(Z)V
      59: aload_1
      60: invokevirtual #14                 // Method java/lang/String.length:()I
      63: ifne          98
      66: getstatic     #15                 // Field logger:Lorg/apache/commons/logging/Log;
      69: new           #16                 // class java/lang/StringBuilder
      72: dup
      73: invokespecial #17                 // Method java/lang/StringBuilder."<init>":()V
      76: ldc           #18                 // String SearchBase not set. Searches will be performed from the root:
      78: invokevirtual #19                 // Method java/lang/StringBuilder.append:(Ljava/lang/String;)Ljava/lang/StringBuilder;
      81: aload_3
      82: invokeinterface #20,  1           // InterfaceMethod org/springframework/ldap/core/support/BaseLdapPathContextSource.getBaseLdapPath:()Lorg/springframework/ldap/core/DistinguishedName;
      87: invokevirtual #21                 // Method java/lang/StringBuilder.append:(Ljava/lang/Object;)Ljava/lang/StringBuilder;
      90: invokevirtual #22                 // Method java/lang/StringBuilder.toString:()Ljava/lang/String;
      93: invokeinterface #23,  2           // InterfaceMethod org/apache/commons/logging/Log.info:(Ljava/lang/Object;)V
      98: return

  public org.springframework.ldap.core.DirContextOperations searchForUser(java.lang.String);
    Code:
       0: getstatic     #15                 // Field logger:Lorg/apache/commons/logging/Log;
       3: invokeinterface #24,  1           // InterfaceMethod org/apache/commons/logging/Log.isDebugEnabled:()Z
       8: ifeq          47
      11: getstatic     #15                 // Field logger:Lorg/apache/commons/logging/Log;
      14: new           #16                 // class java/lang/StringBuilder
      17: dup
      18: invokespecial #17                 // Method java/lang/StringBuilder."<init>":()V
      21: ldc           #25                 // String Searching for user \'
      23: invokevirtual #19                 // Method java/lang/StringBuilder.append:(Ljava/lang/String;)Ljava/lang/StringBuilder;
      26: aload_1
      27: invokevirtual #19                 // Method java/lang/StringBuilder.append:(Ljava/lang/String;)Ljava/lang/StringBuilder;
      30: ldc           #26                 // String \', with user search
      32: invokevirtual #19                 // Method java/lang/StringBuilder.append:(Ljava/lang/String;)Ljava/lang/StringBuilder;
      35: aload_0
      36: invokevirtual #21                 // Method java/lang/StringBuilder.append:(Ljava/lang/Object;)Ljava/lang/StringBuilder;
      39: invokevirtual #22                 // Method java/lang/StringBuilder.toString:()Ljava/lang/String;
      42: invokeinterface #27,  2           // InterfaceMethod org/apache/commons/logging/Log.debug:(Ljava/lang/Object;)V
      47: new           #28                 // class org/springframework/security/ldap/SpringSecurityLdapTemplate
      50: dup
      51: aload_0
      52: getfield      #12                 // Field contextSource:Lorg/springframework/ldap/core/ContextSource;
      55: invokespecial #29                 // Method org/springframework/security/ldap/SpringSecurityLdapTemplate."<init>":(Lorg/springframework/ldap/core/ContextSource;)V
      58: astore_2
      59: aload_2
      60: aload_0
      61: getfield      #4                  // Field searchControls:Ljavax/naming/directory/SearchControls;
      64: invokevirtual #30                 // Method org/springframework/security/ldap/SpringSecurityLdapTemplate.setSearchControls:(Ljavax/naming/directory/SearchControls;)V
      67: aload_2
      68: aload_0
      69: getfield      #6                  // Field searchBase:Ljava/lang/String;
      72: aload_0
      73: getfield      #11                 // Field searchFilter:Ljava/lang/String;
      76: iconst_1
      77: anewarray     #31                 // class java/lang/String
      80: dup
      81: iconst_0
      82: aload_1
      83: aastore
      84: invokevirtual #32                 // Method org/springframework/security/ldap/SpringSecurityLdapTemplate.searchForSingleEntry:(Ljava/lang/String;Ljava/lang/String;[Ljava/lang/Object;)Lorg/springframework/ldap/core/DirContextOperations;
      87: areturn
      88: astore_3
      89: aload_3
      90: invokevirtual #34                 // Method org/springframework/dao/IncorrectResultSizeDataAccessException.getActualSize:()I
      93: ifne          128
      96: new           #35                 // class org/springframework/security/core/userdetails/UsernameNotFoundException
      99: dup
     100: new           #16                 // class java/lang/StringBuilder
     103: dup
     104: invokespecial #17                 // Method java/lang/StringBuilder."<init>":()V
     107: ldc           #36                 // String User
     109: invokevirtual #19                 // Method java/lang/StringBuilder.append:(Ljava/lang/String;)Ljava/lang/StringBuilder;
     112: aload_1
     113: invokevirtual #19                 // Method java/lang/StringBuilder.append:(Ljava/lang/String;)Ljava/lang/StringBuilder;
     116: ldc           #37                 // String  not found in directory.
     118: invokevirtual #19                 // Method java/lang/StringBuilder.append:(Ljava/lang/String;)Ljava/lang/StringBuilder;
     121: invokevirtual #22                 // Method java/lang/StringBuilder.toString:()Ljava/lang/String;
     124: invokespecial #38                 // Method org/springframework/security/core/userdetails/UsernameNotFoundException."<init>":(Ljava/lang/String;)V
     127: athrow
     128: aload_3
     129: athrow
    Exception table:
       from    to  target type
          67    87    88   Class org/springframework/dao/IncorrectResultSizeDataAccessException

  public void setDerefLinkFlag(boolean);
    Code:
       0: aload_0
       1: getfield      #4                  // Field searchControls:Ljavax/naming/directory/SearchControls;
       4: iload_1
       5: invokevirtual #39                 // Method javax/naming/directory/SearchControls.setDerefLinkFlag:(Z)V
       8: return

  public void setSearchSubtree(boolean);
    Code:
       0: aload_0
       1: getfield      #4                  // Field searchControls:Ljavax/naming/directory/SearchControls;
       4: iload_1
       5: ifeq          12
       8: iconst_2
       9: goto          13
      12: iconst_1
      13: invokevirtual #40                 // Method javax/naming/directory/SearchControls.setSearchScope:(I)V
      16: return

  public void setSearchTimeLimit(int);
    Code:
       0: aload_0
       1: getfield      #4                  // Field searchControls:Ljavax/naming/directory/SearchControls;
       4: iload_1
       5: invokevirtual #41                 // Method javax/naming/directory/SearchControls.setTimeLimit:(I)V
       8: return

  public void setReturningAttributes(java.lang.String[]);
    Code:
       0: aload_0
       1: getfield      #4                  // Field searchControls:Ljavax/naming/directory/SearchControls;
       4: aload_1
       5: invokevirtual #42                 // Method javax/naming/directory/SearchControls.setReturningAttributes:([Ljava/lang/String;)V
       8: return

  public java.lang.String toString();
    Code:
       0: new           #16                 // class java/lang/StringBuilder
       3: dup
       4: invokespecial #17                 // Method java/lang/StringBuilder."<init>":()V
       7: astore_1
       8: aload_1
       9: ldc           #43                 // String [ searchFilter: \'
      11: invokevirtual #19                 // Method java/lang/StringBuilder.append:(Ljava/lang/String;)Ljava/lang/StringBuilder;
      14: aload_0
      15: getfield      #11                 // Field searchFilter:Ljava/lang/String;
      18: invokevirtual #19                 // Method java/lang/StringBuilder.append:(Ljava/lang/String;)Ljava/lang/StringBuilder;
      21: ldc           #44                 // String \',
      23: invokevirtual #19                 // Method java/lang/StringBuilder.append:(Ljava/lang/String;)Ljava/lang/StringBuilder;
      26: pop
      27: aload_1
      28: ldc           #45                 // String searchBase: \'
      30: invokevirtual #19                 // Method java/lang/StringBuilder.append:(Ljava/lang/String;)Ljava/lang/StringBuilder;
      33: aload_0
      34: getfield      #6                  // Field searchBase:Ljava/lang/String;
      37: invokevirtual #19                 // Method java/lang/StringBuilder.append:(Ljava/lang/String;)Ljava/lang/StringBuilder;
      40: ldc           #46                 // String \'
      42: invokevirtual #19                 // Method java/lang/StringBuilder.append:(Ljava/lang/String;)Ljava/lang/StringBuilder;
      45: pop
      46: aload_1
      47: ldc           #47                 // String , scope:
      49: invokevirtual #19                 // Method java/lang/StringBuilder.append:(Ljava/lang/String;)Ljava/lang/StringBuilder;
      52: aload_0
      53: getfield      #4                  // Field searchControls:Ljavax/naming/directory/SearchControls;
      56: invokevirtual #48                 // Method javax/naming/directory/SearchControls.getSearchScope:()I
      59: iconst_2
      60: if_icmpne     68
      63: ldc           #49                 // String subtree
      65: goto          70
      68: ldc           #50                 // String single-level,
      70: invokevirtual #19                 // Method java/lang/StringBuilder.append:(Ljava/lang/String;)Ljava/lang/StringBuilder;
      73: pop
      74: aload_1
      75: ldc           #51                 // String , searchTimeLimit:
      77: invokevirtual #19                 // Method java/lang/StringBuilder.append:(Ljava/lang/String;)Ljava/lang/StringBuilder;
      80: aload_0
      81: getfield      #4                  // Field searchControls:Ljavax/naming/directory/SearchControls;
      84: invokevirtual #52                 // Method javax/naming/directory/SearchControls.getTimeLimit:()I
      87: invokevirtual #53                 // Method java/lang/StringBuilder.append:(I)Ljava/lang/StringBuilder;
      90: pop
      91: aload_1
      92: ldc           #54                 // String , derefLinkFlag:
      94: invokevirtual #19                 // Method java/lang/StringBuilder.append:(Ljava/lang/String;)Ljava/lang/StringBuilder;
      97: aload_0
      98: getfield      #4                  // Field searchControls:Ljavax/naming/directory/SearchControls;
     101: invokevirtual #55                 // Method javax/naming/directory/SearchControls.getDerefLinkFlag:()Z
     104: invokevirtual #56                 // Method java/lang/StringBuilder.append:(Z)Ljava/lang/StringBuilder;
     107: ldc           #57                 // String  ]
     109: invokevirtual #19                 // Method java/lang/StringBuilder.append:(Ljava/lang/String;)Ljava/lang/StringBuilder;
     112: pop
     113: aload_1
     114: invokevirtual #22                 // Method java/lang/StringBuilder.toString:()Ljava/lang/String;
     117: areturn

  static {};
    Code:
       0: ldc           #58                 // class org/springframework/security/ldap/search/FilterBasedLdapUserSearch
       2: invokestatic  #59                 // Method org/apache/commons/logging/LogFactory.getLog:(Ljava/lang/Class;)Lorg/apache/commons/logging/Log;
       5: putstatic     #15                 // Field logger:Lorg/apache/commons/logging/Log;
       8: return
}
