Compiled from "HttpBackOffUnsuccessfulResponseHandler.java"
public interface com.google.api.client.http.HttpBackOffUnsuccessfulResponseHandler$BackOffRequired {
  public static final com.google.api.client.http.HttpBackOffUnsuccessfulResponseHandler$BackOffRequired ALWAYS;

  public static final com.google.api.client.http.HttpBackOffUnsuccessfulResponseHandler$BackOffRequired ON_SERVER_ERROR;

  public abstract boolean isRequired(com.google.api.client.http.HttpResponse);

  static {};
    Code:
       0: new           #13                 // class com/google/api/client/http/HttpBackOffUnsuccessfulResponseHandler$BackOffRequired$1
       3: dup
       4: invokespecial #23                 // Method com/google/api/client/http/HttpBackOffUnsuccessfulResponseHandler$BackOffRequired$1."<init>":()V
       7: putstatic     #25                 // Field ALWAYS:Lcom/google/api/client/http/HttpBackOffUnsuccessfulResponseHandler$BackOffRequired;
      10: new           #11                 // class com/google/api/client/http/HttpBackOffUnsuccessfulResponseHandler$BackOffRequired$2
      13: dup
      14: invokespecial #26                 // Method com/google/api/client/http/HttpBackOffUnsuccessfulResponseHandler$BackOffRequired$2."<init>":()V
      17: putstatic     #28                 // Field ON_SERVER_ERROR:Lcom/google/api/client/http/HttpBackOffUnsuccessfulResponseHandler$BackOffRequired;
      20: return
}
