Compiled from "HttpResponseException.java"
public class com.google.api.client.http.HttpResponseException$Builder {
  int statusCode;

  java.lang.String statusMessage;

  com.google.api.client.http.HttpHeaders headers;

  java.lang.String content;

  java.lang.String message;

  public com.google.api.client.http.HttpResponseException$Builder(int, java.lang.String, com.google.api.client.http.HttpHeaders);
    Code:
       0: aload_0
       1: invokespecial #21                 // Method java/lang/Object."<init>":()V
       4: aload_0
       5: iload_1
       6: invokevirtual #25                 // Method setStatusCode:(I)Lcom/google/api/client/http/HttpResponseException$Builder;
       9: pop
      10: aload_0
      11: aload_2
      12: invokevirtual #29                 // Method setStatusMessage:(Ljava/lang/String;)Lcom/google/api/client/http/HttpResponseException$Builder;
      15: pop
      16: aload_0
      17: aload_3
      18: invokevirtual #33                 // Method setHeaders:(Lcom/google/api/client/http/HttpHeaders;)Lcom/google/api/client/http/HttpResponseException$Builder;
      21: pop
      22: return

  public com.google.api.client.http.HttpResponseException$Builder(com.google.api.client.http.HttpResponse);
    Code:
       0: aload_0
       1: aload_1
       2: invokevirtual #44                 // Method com/google/api/client/http/HttpResponse.getStatusCode:()I
       5: aload_1
       6: invokevirtual #48                 // Method com/google/api/client/http/HttpResponse.getStatusMessage:()Ljava/lang/String;
       9: aload_1
      10: invokevirtual #52                 // Method com/google/api/client/http/HttpResponse.getHeaders:()Lcom/google/api/client/http/HttpHeaders;
      13: invokespecial #54                 // Method "<init>":(ILjava/lang/String;Lcom/google/api/client/http/HttpHeaders;)V
      16: aload_0
      17: aload_1
      18: invokevirtual #57                 // Method com/google/api/client/http/HttpResponse.parseAsString:()Ljava/lang/String;
      21: putfield      #59                 // Field content:Ljava/lang/String;
      24: aload_0
      25: getfield      #59                 // Field content:Ljava/lang/String;
      28: invokevirtual #64                 // Method java/lang/String.length:()I
      31: ifne          39
      34: aload_0
      35: aconst_null
      36: putfield      #59                 // Field content:Ljava/lang/String;
      39: goto          47
      42: astore_2
      43: aload_2
      44: invokevirtual #67                 // Method java/io/IOException.printStackTrace:()V
      47: aload_1
      48: invokestatic  #71                 // Method com/google/api/client/http/HttpResponseException.computeMessageBuffer:(Lcom/google/api/client/http/HttpResponse;)Ljava/lang/StringBuilder;
      51: astore_2
      52: aload_0
      53: getfield      #59                 // Field content:Ljava/lang/String;
      56: ifnull        74
      59: aload_2
      60: getstatic     #76                 // Field com/google/api/client/util/StringUtils.LINE_SEPARATOR:Ljava/lang/String;
      63: invokevirtual #82                 // Method java/lang/StringBuilder.append:(Ljava/lang/String;)Ljava/lang/StringBuilder;
      66: aload_0
      67: getfield      #59                 // Field content:Ljava/lang/String;
      70: invokevirtual #82                 // Method java/lang/StringBuilder.append:(Ljava/lang/String;)Ljava/lang/StringBuilder;
      73: pop
      74: aload_0
      75: aload_2
      76: invokevirtual #85                 // Method java/lang/StringBuilder.toString:()Ljava/lang/String;
      79: putfield      #87                 // Field message:Ljava/lang/String;
      82: return
    Exception table:
       from    to  target type
          16    39    42   Class java/io/IOException

  public final java.lang.String getMessage();
    Code:
       0: aload_0
       1: getfield      #87                 // Field message:Ljava/lang/String;
       4: areturn

  public com.google.api.client.http.HttpResponseException$Builder setMessage(java.lang.String);
    Code:
       0: aload_0
       1: aload_1
       2: putfield      #87                 // Field message:Ljava/lang/String;
       5: aload_0
       6: areturn

  public final int getStatusCode();
    Code:
       0: aload_0
       1: getfield      #97                 // Field statusCode:I
       4: ireturn

  public com.google.api.client.http.HttpResponseException$Builder setStatusCode(int);
    Code:
       0: iload_1
       1: iflt          8
       4: iconst_1
       5: goto          9
       8: iconst_0
       9: invokestatic  #103                // Method com/google/api/client/util/Preconditions.checkArgument:(Z)V
      12: aload_0
      13: iload_1
      14: putfield      #97                 // Field statusCode:I
      17: aload_0
      18: areturn

  public final java.lang.String getStatusMessage();
    Code:
       0: aload_0
       1: getfield      #105                // Field statusMessage:Ljava/lang/String;
       4: areturn

  public com.google.api.client.http.HttpResponseException$Builder setStatusMessage(java.lang.String);
    Code:
       0: aload_0
       1: aload_1
       2: putfield      #105                // Field statusMessage:Ljava/lang/String;
       5: aload_0
       6: areturn

  public com.google.api.client.http.HttpHeaders getHeaders();
    Code:
       0: aload_0
       1: getfield      #107                // Field headers:Lcom/google/api/client/http/HttpHeaders;
       4: areturn

  public com.google.api.client.http.HttpResponseException$Builder setHeaders(com.google.api.client.http.HttpHeaders);
    Code:
       0: aload_0
       1: aload_1
       2: invokestatic  #111                // Method com/google/api/client/util/Preconditions.checkNotNull:(Ljava/lang/Object;)Ljava/lang/Object;
       5: checkcast     #113                // class com/google/api/client/http/HttpHeaders
       8: putfield      #107                // Field headers:Lcom/google/api/client/http/HttpHeaders;
      11: aload_0
      12: areturn

  public final java.lang.String getContent();
    Code:
       0: aload_0
       1: getfield      #59                 // Field content:Ljava/lang/String;
       4: areturn

  public com.google.api.client.http.HttpResponseException$Builder setContent(java.lang.String);
    Code:
       0: aload_0
       1: aload_1
       2: putfield      #59                 // Field content:Ljava/lang/String;
       5: aload_0
       6: areturn

  public com.google.api.client.http.HttpResponseException build();
    Code:
       0: new           #7                  // class com/google/api/client/http/HttpResponseException
       3: dup
       4: aload_0
       5: invokespecial #120                // Method com/google/api/client/http/HttpResponseException."<init>":(Lcom/google/api/client/http/HttpResponseException$Builder;)V
       8: areturn
}
