Compiled from "ParserImpl.java"
public class io.dekorate.deps.snakeyaml.parser.ParserImpl implements io.dekorate.deps.snakeyaml.parser.Parser {
  private static final java.util.Map<java.lang.String, java.lang.String> DEFAULT_TAGS;

  protected final io.dekorate.deps.snakeyaml.scanner.Scanner scanner;

  private io.dekorate.deps.snakeyaml.events.Event currentEvent;

  private final io.dekorate.deps.snakeyaml.util.ArrayStack<io.dekorate.deps.snakeyaml.parser.Production> states;

  private final io.dekorate.deps.snakeyaml.util.ArrayStack<io.dekorate.deps.snakeyaml.error.Mark> marks;

  private io.dekorate.deps.snakeyaml.parser.Production state;

  private io.dekorate.deps.snakeyaml.parser.VersionTagsTuple directives;

  public io.dekorate.deps.snakeyaml.parser.ParserImpl(io.dekorate.deps.snakeyaml.reader.StreamReader);
    Code:
       0: aload_0
       1: new           #112                // class io/dekorate/deps/snakeyaml/scanner/ScannerImpl
       4: dup
       5: aload_1
       6: invokespecial #114                // Method io/dekorate/deps/snakeyaml/scanner/ScannerImpl."<init>":(Lio/dekorate/deps/snakeyaml/reader/StreamReader;)V
       9: invokespecial #117                // Method "<init>":(Lio/dekorate/deps/snakeyaml/scanner/Scanner;)V
      12: return

  public io.dekorate.deps.snakeyaml.parser.ParserImpl(io.dekorate.deps.snakeyaml.scanner.Scanner);
    Code:
       0: aload_0
       1: invokespecial #124                // Method java/lang/Object."<init>":()V
       4: aload_0
       5: aload_1
       6: putfield      #126                // Field scanner:Lio/dekorate/deps/snakeyaml/scanner/Scanner;
       9: aload_0
      10: aconst_null
      11: putfield      #128                // Field currentEvent:Lio/dekorate/deps/snakeyaml/events/Event;
      14: aload_0
      15: new           #130                // class io/dekorate/deps/snakeyaml/parser/VersionTagsTuple
      18: dup
      19: aconst_null
      20: new           #132                // class java/util/HashMap
      23: dup
      24: getstatic     #134                // Field DEFAULT_TAGS:Ljava/util/Map;
      27: invokespecial #137                // Method java/util/HashMap."<init>":(Ljava/util/Map;)V
      30: invokespecial #140                // Method io/dekorate/deps/snakeyaml/parser/VersionTagsTuple."<init>":(Lio/dekorate/deps/snakeyaml/DumperOptions$Version;Ljava/util/Map;)V
      33: putfield      #142                // Field directives:Lio/dekorate/deps/snakeyaml/parser/VersionTagsTuple;
      36: aload_0
      37: new           #144                // class io/dekorate/deps/snakeyaml/util/ArrayStack
      40: dup
      41: bipush        100
      43: invokespecial #147                // Method io/dekorate/deps/snakeyaml/util/ArrayStack."<init>":(I)V
      46: putfield      #149                // Field states:Lio/dekorate/deps/snakeyaml/util/ArrayStack;
      49: aload_0
      50: new           #144                // class io/dekorate/deps/snakeyaml/util/ArrayStack
      53: dup
      54: bipush        10
      56: invokespecial #147                // Method io/dekorate/deps/snakeyaml/util/ArrayStack."<init>":(I)V
      59: putfield      #151                // Field marks:Lio/dekorate/deps/snakeyaml/util/ArrayStack;
      62: aload_0
      63: new           #71                 // class io/dekorate/deps/snakeyaml/parser/ParserImpl$ParseStreamStart
      66: dup
      67: aload_0
      68: aconst_null
      69: invokespecial #154                // Method io/dekorate/deps/snakeyaml/parser/ParserImpl$ParseStreamStart."<init>":(Lio/dekorate/deps/snakeyaml/parser/ParserImpl;Lio/dekorate/deps/snakeyaml/parser/ParserImpl$1;)V
      72: putfield      #156                // Field state:Lio/dekorate/deps/snakeyaml/parser/Production;
      75: return

  public boolean checkEvent(io.dekorate.deps.snakeyaml.events.Event$ID);
    Code:
       0: aload_0
       1: invokevirtual #162                // Method peekEvent:()Lio/dekorate/deps/snakeyaml/events/Event;
       4: pop
       5: aload_0
       6: getfield      #128                // Field currentEvent:Lio/dekorate/deps/snakeyaml/events/Event;
       9: ifnull        27
      12: aload_0
      13: getfield      #128                // Field currentEvent:Lio/dekorate/deps/snakeyaml/events/Event;
      16: aload_1
      17: invokevirtual #165                // Method io/dekorate/deps/snakeyaml/events/Event.is:(Lio/dekorate/deps/snakeyaml/events/Event$ID;)Z
      20: ifeq          27
      23: iconst_1
      24: goto          28
      27: iconst_0
      28: ireturn

  public io.dekorate.deps.snakeyaml.events.Event peekEvent();
    Code:
       0: aload_0
       1: getfield      #128                // Field currentEvent:Lio/dekorate/deps/snakeyaml/events/Event;
       4: ifnonnull     27
       7: aload_0
       8: getfield      #156                // Field state:Lio/dekorate/deps/snakeyaml/parser/Production;
      11: ifnull        27
      14: aload_0
      15: aload_0
      16: getfield      #156                // Field state:Lio/dekorate/deps/snakeyaml/parser/Production;
      19: invokeinterface #172,  1          // InterfaceMethod io/dekorate/deps/snakeyaml/parser/Production.produce:()Lio/dekorate/deps/snakeyaml/events/Event;
      24: putfield      #128                // Field currentEvent:Lio/dekorate/deps/snakeyaml/events/Event;
      27: aload_0
      28: getfield      #128                // Field currentEvent:Lio/dekorate/deps/snakeyaml/events/Event;
      31: areturn

  public io.dekorate.deps.snakeyaml.events.Event getEvent();
    Code:
       0: aload_0
       1: invokevirtual #162                // Method peekEvent:()Lio/dekorate/deps/snakeyaml/events/Event;
       4: pop
       5: aload_0
       6: getfield      #128                // Field currentEvent:Lio/dekorate/deps/snakeyaml/events/Event;
       9: astore_1
      10: aload_0
      11: aconst_null
      12: putfield      #128                // Field currentEvent:Lio/dekorate/deps/snakeyaml/events/Event;
      15: aload_1
      16: areturn

  private io.dekorate.deps.snakeyaml.parser.VersionTagsTuple processDirectives();
    Code:
       0: aconst_null
       1: astore_1
       2: new           #132                // class java/util/HashMap
       5: dup
       6: invokespecial #177                // Method java/util/HashMap."<init>":()V
       9: astore_2
      10: aload_0
      11: getfield      #126                // Field scanner:Lio/dekorate/deps/snakeyaml/scanner/Scanner;
      14: iconst_1
      15: anewarray     #84                 // class io/dekorate/deps/snakeyaml/tokens/Token$ID
      18: dup
      19: iconst_0
      20: getstatic     #181                // Field io/dekorate/deps/snakeyaml/tokens/Token$ID.Directive:Lio/dekorate/deps/snakeyaml/tokens/Token$ID;
      23: aastore
      24: invokeinterface #187,  2          // InterfaceMethod io/dekorate/deps/snakeyaml/scanner/Scanner.checkToken:([Lio/dekorate/deps/snakeyaml/tokens/Token$ID;)Z
      29: ifeq          269
      32: aload_0
      33: getfield      #126                // Field scanner:Lio/dekorate/deps/snakeyaml/scanner/Scanner;
      36: invokeinterface #191,  1          // InterfaceMethod io/dekorate/deps/snakeyaml/scanner/Scanner.getToken:()Lio/dekorate/deps/snakeyaml/tokens/Token;
      41: checkcast     #193                // class io/dekorate/deps/snakeyaml/tokens/DirectiveToken
      44: astore_3
      45: aload_3
      46: invokevirtual #197                // Method io/dekorate/deps/snakeyaml/tokens/DirectiveToken.getName:()Ljava/lang/String;
      49: ldc           #199                // String YAML
      51: invokevirtual #205                // Method java/lang/String.equals:(Ljava/lang/Object;)Z
      54: ifeq          170
      57: aload_1
      58: ifnull        77
      61: new           #207                // class io/dekorate/deps/snakeyaml/parser/ParserException
      64: dup
      65: aconst_null
      66: aconst_null
      67: ldc           #209                // String found duplicate YAML directive
      69: aload_3
      70: invokevirtual #213                // Method io/dekorate/deps/snakeyaml/tokens/DirectiveToken.getStartMark:()Lio/dekorate/deps/snakeyaml/error/Mark;
      73: invokespecial #216                // Method io/dekorate/deps/snakeyaml/parser/ParserException."<init>":(Ljava/lang/String;Lio/dekorate/deps/snakeyaml/error/Mark;Ljava/lang/String;Lio/dekorate/deps/snakeyaml/error/Mark;)V
      76: athrow
      77: aload_3
      78: invokevirtual #220                // Method io/dekorate/deps/snakeyaml/tokens/DirectiveToken.getValue:()Ljava/util/List;
      81: astore        4
      83: aload         4
      85: iconst_0
      86: invokeinterface #226,  2          // InterfaceMethod java/util/List.get:(I)Ljava/lang/Object;
      91: checkcast     #228                // class java/lang/Integer
      94: astore        5
      96: aload         5
      98: invokevirtual #232                // Method java/lang/Integer.intValue:()I
     101: iconst_1
     102: if_icmpeq     121
     105: new           #207                // class io/dekorate/deps/snakeyaml/parser/ParserException
     108: dup
     109: aconst_null
     110: aconst_null
     111: ldc           #234                // String found incompatible YAML document (version 1.* is required)
     113: aload_3
     114: invokevirtual #213                // Method io/dekorate/deps/snakeyaml/tokens/DirectiveToken.getStartMark:()Lio/dekorate/deps/snakeyaml/error/Mark;
     117: invokespecial #216                // Method io/dekorate/deps/snakeyaml/parser/ParserException."<init>":(Ljava/lang/String;Lio/dekorate/deps/snakeyaml/error/Mark;Ljava/lang/String;Lio/dekorate/deps/snakeyaml/error/Mark;)V
     120: athrow
     121: aload         4
     123: iconst_1
     124: invokeinterface #226,  2          // InterfaceMethod java/util/List.get:(I)Ljava/lang/Object;
     129: checkcast     #228                // class java/lang/Integer
     132: astore        6
     134: aload         6
     136: invokevirtual #232                // Method java/lang/Integer.intValue:()I
     139: lookupswitch  { // 1
                     0: 156
               default: 163
          }
     156: getstatic     #238                // Field io/dekorate/deps/snakeyaml/DumperOptions$Version.V1_0:Lio/dekorate/deps/snakeyaml/DumperOptions$Version;
     159: astore_1
     160: goto          167
     163: getstatic     #241                // Field io/dekorate/deps/snakeyaml/DumperOptions$Version.V1_1:Lio/dekorate/deps/snakeyaml/DumperOptions$Version;
     166: astore_1
     167: goto          266
     170: aload_3
     171: invokevirtual #197                // Method io/dekorate/deps/snakeyaml/tokens/DirectiveToken.getName:()Ljava/lang/String;
     174: ldc           #243                // String TAG
     176: invokevirtual #205                // Method java/lang/String.equals:(Ljava/lang/Object;)Z
     179: ifeq          266
     182: aload_3
     183: invokevirtual #220                // Method io/dekorate/deps/snakeyaml/tokens/DirectiveToken.getValue:()Ljava/util/List;
     186: astore        4
     188: aload         4
     190: iconst_0
     191: invokeinterface #226,  2          // InterfaceMethod java/util/List.get:(I)Ljava/lang/Object;
     196: checkcast     #201                // class java/lang/String
     199: astore        5
     201: aload         4
     203: iconst_1
     204: invokeinterface #226,  2          // InterfaceMethod java/util/List.get:(I)Ljava/lang/Object;
     209: checkcast     #201                // class java/lang/String
     212: astore        6
     214: aload_2
     215: aload         5
     217: invokevirtual #246                // Method java/util/HashMap.containsKey:(Ljava/lang/Object;)Z
     220: ifeq          257
     223: new           #207                // class io/dekorate/deps/snakeyaml/parser/ParserException
     226: dup
     227: aconst_null
     228: aconst_null
     229: new           #248                // class java/lang/StringBuilder
     232: dup
     233: invokespecial #249                // Method java/lang/StringBuilder."<init>":()V
     236: ldc           #251                // String duplicate tag handle
     238: invokevirtual #255                // Method java/lang/StringBuilder.append:(Ljava/lang/String;)Ljava/lang/StringBuilder;
     241: aload         5
     243: invokevirtual #255                // Method java/lang/StringBuilder.append:(Ljava/lang/String;)Ljava/lang/StringBuilder;
     246: invokevirtual #258                // Method java/lang/StringBuilder.toString:()Ljava/lang/String;
     249: aload_3
     250: invokevirtual #213                // Method io/dekorate/deps/snakeyaml/tokens/DirectiveToken.getStartMark:()Lio/dekorate/deps/snakeyaml/error/Mark;
     253: invokespecial #216                // Method io/dekorate/deps/snakeyaml/parser/ParserException."<init>":(Ljava/lang/String;Lio/dekorate/deps/snakeyaml/error/Mark;Ljava/lang/String;Lio/dekorate/deps/snakeyaml/error/Mark;)V
     256: athrow
     257: aload_2
     258: aload         5
     260: aload         6
     262: invokevirtual #262                // Method java/util/HashMap.put:(Ljava/lang/Object;Ljava/lang/Object;)Ljava/lang/Object;
     265: pop
     266: goto          10
     269: aload_1
     270: ifnonnull     280
     273: aload_2
     274: invokevirtual #266                // Method java/util/HashMap.isEmpty:()Z
     277: ifne          356
     280: getstatic     #134                // Field DEFAULT_TAGS:Ljava/util/Map;
     283: invokeinterface #272,  1          // InterfaceMethod java/util/Map.keySet:()Ljava/util/Set;
     288: invokeinterface #278,  1          // InterfaceMethod java/util/Set.iterator:()Ljava/util/Iterator;
     293: astore_3
     294: aload_3
     295: invokeinterface #283,  1          // InterfaceMethod java/util/Iterator.hasNext:()Z
     300: ifeq          343
     303: aload_3
     304: invokeinterface #287,  1          // InterfaceMethod java/util/Iterator.next:()Ljava/lang/Object;
     309: checkcast     #201                // class java/lang/String
     312: astore        4
     314: aload_2
     315: aload         4
     317: invokevirtual #246                // Method java/util/HashMap.containsKey:(Ljava/lang/Object;)Z
     320: ifne          340
     323: aload_2
     324: aload         4
     326: getstatic     #134                // Field DEFAULT_TAGS:Ljava/util/Map;
     329: aload         4
     331: invokeinterface #290,  2          // InterfaceMethod java/util/Map.get:(Ljava/lang/Object;)Ljava/lang/Object;
     336: invokevirtual #262                // Method java/util/HashMap.put:(Ljava/lang/Object;Ljava/lang/Object;)Ljava/lang/Object;
     339: pop
     340: goto          294
     343: aload_0
     344: new           #130                // class io/dekorate/deps/snakeyaml/parser/VersionTagsTuple
     347: dup
     348: aload_1
     349: aload_2
     350: invokespecial #140                // Method io/dekorate/deps/snakeyaml/parser/VersionTagsTuple."<init>":(Lio/dekorate/deps/snakeyaml/DumperOptions$Version;Ljava/util/Map;)V
     353: putfield      #142                // Field directives:Lio/dekorate/deps/snakeyaml/parser/VersionTagsTuple;
     356: aload_0
     357: getfield      #142                // Field directives:Lio/dekorate/deps/snakeyaml/parser/VersionTagsTuple;
     360: areturn

  private io.dekorate.deps.snakeyaml.events.Event parseFlowNode();
    Code:
       0: aload_0
       1: iconst_0
       2: iconst_0
       3: invokespecial #313                // Method parseNode:(ZZ)Lio/dekorate/deps/snakeyaml/events/Event;
       6: areturn

  private io.dekorate.deps.snakeyaml.events.Event parseBlockNodeOrIndentlessSequence();
    Code:
       0: aload_0
       1: iconst_1
       2: iconst_1
       3: invokespecial #313                // Method parseNode:(ZZ)Lio/dekorate/deps/snakeyaml/events/Event;
       6: areturn

  private io.dekorate.deps.snakeyaml.events.Event parseNode(boolean, boolean);
    Code:
       0: aconst_null
       1: astore        4
       3: aconst_null
       4: astore        5
       6: aconst_null
       7: astore        6
       9: aload_0
      10: getfield      #126                // Field scanner:Lio/dekorate/deps/snakeyaml/scanner/Scanner;
      13: iconst_1
      14: anewarray     #84                 // class io/dekorate/deps/snakeyaml/tokens/Token$ID
      17: dup
      18: iconst_0
      19: getstatic     #317                // Field io/dekorate/deps/snakeyaml/tokens/Token$ID.Alias:Lio/dekorate/deps/snakeyaml/tokens/Token$ID;
      22: aastore
      23: invokeinterface #187,  2          // InterfaceMethod io/dekorate/deps/snakeyaml/scanner/Scanner.checkToken:([Lio/dekorate/deps/snakeyaml/tokens/Token$ID;)Z
      28: ifeq          85
      31: aload_0
      32: getfield      #126                // Field scanner:Lio/dekorate/deps/snakeyaml/scanner/Scanner;
      35: invokeinterface #191,  1          // InterfaceMethod io/dekorate/deps/snakeyaml/scanner/Scanner.getToken:()Lio/dekorate/deps/snakeyaml/tokens/Token;
      40: checkcast     #319                // class io/dekorate/deps/snakeyaml/tokens/AliasToken
      43: astore        7
      45: new           #321                // class io/dekorate/deps/snakeyaml/events/AliasEvent
      48: dup
      49: aload         7
      51: invokevirtual #323                // Method io/dekorate/deps/snakeyaml/tokens/AliasToken.getValue:()Ljava/lang/String;
      54: aload         7
      56: invokevirtual #324                // Method io/dekorate/deps/snakeyaml/tokens/AliasToken.getStartMark:()Lio/dekorate/deps/snakeyaml/error/Mark;
      59: aload         7
      61: invokevirtual #327                // Method io/dekorate/deps/snakeyaml/tokens/AliasToken.getEndMark:()Lio/dekorate/deps/snakeyaml/error/Mark;
      64: invokespecial #330                // Method io/dekorate/deps/snakeyaml/events/AliasEvent."<init>":(Ljava/lang/String;Lio/dekorate/deps/snakeyaml/error/Mark;Lio/dekorate/deps/snakeyaml/error/Mark;)V
      67: astore_3
      68: aload_0
      69: aload_0
      70: getfield      #149                // Field states:Lio/dekorate/deps/snakeyaml/util/ArrayStack;
      73: invokevirtual #333                // Method io/dekorate/deps/snakeyaml/util/ArrayStack.pop:()Ljava/lang/Object;
      76: checkcast     #169                // class io/dekorate/deps/snakeyaml/parser/Production
      79: putfield      #156                // Field state:Lio/dekorate/deps/snakeyaml/parser/Production;
      82: goto          1183
      85: aconst_null
      86: astore        7
      88: aconst_null
      89: astore        8
      91: aload_0
      92: getfield      #126                // Field scanner:Lio/dekorate/deps/snakeyaml/scanner/Scanner;
      95: iconst_1
      96: anewarray     #84                 // class io/dekorate/deps/snakeyaml/tokens/Token$ID
      99: dup
     100: iconst_0
     101: getstatic     #338                // Field io/dekorate/deps/snakeyaml/tokens/Token$ID.Anchor:Lio/dekorate/deps/snakeyaml/tokens/Token$ID;
     104: aastore
     105: invokeinterface #187,  2          // InterfaceMethod io/dekorate/deps/snakeyaml/scanner/Scanner.checkToken:([Lio/dekorate/deps/snakeyaml/tokens/Token$ID;)Z
     110: ifeq          208
     113: aload_0
     114: getfield      #126                // Field scanner:Lio/dekorate/deps/snakeyaml/scanner/Scanner;
     117: invokeinterface #191,  1          // InterfaceMethod io/dekorate/deps/snakeyaml/scanner/Scanner.getToken:()Lio/dekorate/deps/snakeyaml/tokens/Token;
     122: checkcast     #340                // class io/dekorate/deps/snakeyaml/tokens/AnchorToken
     125: astore        9
     127: aload         9
     129: invokevirtual #341                // Method io/dekorate/deps/snakeyaml/tokens/AnchorToken.getStartMark:()Lio/dekorate/deps/snakeyaml/error/Mark;
     132: astore        4
     134: aload         9
     136: invokevirtual #342                // Method io/dekorate/deps/snakeyaml/tokens/AnchorToken.getEndMark:()Lio/dekorate/deps/snakeyaml/error/Mark;
     139: astore        5
     141: aload         9
     143: invokevirtual #343                // Method io/dekorate/deps/snakeyaml/tokens/AnchorToken.getValue:()Ljava/lang/String;
     146: astore        7
     148: aload_0
     149: getfield      #126                // Field scanner:Lio/dekorate/deps/snakeyaml/scanner/Scanner;
     152: iconst_1
     153: anewarray     #84                 // class io/dekorate/deps/snakeyaml/tokens/Token$ID
     156: dup
     157: iconst_0
     158: getstatic     #346                // Field io/dekorate/deps/snakeyaml/tokens/Token$ID.Tag:Lio/dekorate/deps/snakeyaml/tokens/Token$ID;
     161: aastore
     162: invokeinterface #187,  2          // InterfaceMethod io/dekorate/deps/snakeyaml/scanner/Scanner.checkToken:([Lio/dekorate/deps/snakeyaml/tokens/Token$ID;)Z
     167: ifeq          205
     170: aload_0
     171: getfield      #126                // Field scanner:Lio/dekorate/deps/snakeyaml/scanner/Scanner;
     174: invokeinterface #191,  1          // InterfaceMethod io/dekorate/deps/snakeyaml/scanner/Scanner.getToken:()Lio/dekorate/deps/snakeyaml/tokens/Token;
     179: checkcast     #348                // class io/dekorate/deps/snakeyaml/tokens/TagToken
     182: astore        10
     184: aload         10
     186: invokevirtual #349                // Method io/dekorate/deps/snakeyaml/tokens/TagToken.getStartMark:()Lio/dekorate/deps/snakeyaml/error/Mark;
     189: astore        6
     191: aload         10
     193: invokevirtual #350                // Method io/dekorate/deps/snakeyaml/tokens/TagToken.getEndMark:()Lio/dekorate/deps/snakeyaml/error/Mark;
     196: astore        5
     198: aload         10
     200: invokevirtual #353                // Method io/dekorate/deps/snakeyaml/tokens/TagToken.getValue:()Lio/dekorate/deps/snakeyaml/tokens/TagTuple;
     203: astore        8
     205: goto          319
     208: aload_0
     209: getfield      #126                // Field scanner:Lio/dekorate/deps/snakeyaml/scanner/Scanner;
     212: iconst_1
     213: anewarray     #84                 // class io/dekorate/deps/snakeyaml/tokens/Token$ID
     216: dup
     217: iconst_0
     218: getstatic     #346                // Field io/dekorate/deps/snakeyaml/tokens/Token$ID.Tag:Lio/dekorate/deps/snakeyaml/tokens/Token$ID;
     221: aastore
     222: invokeinterface #187,  2          // InterfaceMethod io/dekorate/deps/snakeyaml/scanner/Scanner.checkToken:([Lio/dekorate/deps/snakeyaml/tokens/Token$ID;)Z
     227: ifeq          319
     230: aload_0
     231: getfield      #126                // Field scanner:Lio/dekorate/deps/snakeyaml/scanner/Scanner;
     234: invokeinterface #191,  1          // InterfaceMethod io/dekorate/deps/snakeyaml/scanner/Scanner.getToken:()Lio/dekorate/deps/snakeyaml/tokens/Token;
     239: checkcast     #348                // class io/dekorate/deps/snakeyaml/tokens/TagToken
     242: astore        9
     244: aload         9
     246: invokevirtual #349                // Method io/dekorate/deps/snakeyaml/tokens/TagToken.getStartMark:()Lio/dekorate/deps/snakeyaml/error/Mark;
     249: astore        4
     251: aload         4
     253: astore        6
     255: aload         9
     257: invokevirtual #350                // Method io/dekorate/deps/snakeyaml/tokens/TagToken.getEndMark:()Lio/dekorate/deps/snakeyaml/error/Mark;
     260: astore        5
     262: aload         9
     264: invokevirtual #353                // Method io/dekorate/deps/snakeyaml/tokens/TagToken.getValue:()Lio/dekorate/deps/snakeyaml/tokens/TagTuple;
     267: astore        8
     269: aload_0
     270: getfield      #126                // Field scanner:Lio/dekorate/deps/snakeyaml/scanner/Scanner;
     273: iconst_1
     274: anewarray     #84                 // class io/dekorate/deps/snakeyaml/tokens/Token$ID
     277: dup
     278: iconst_0
     279: getstatic     #338                // Field io/dekorate/deps/snakeyaml/tokens/Token$ID.Anchor:Lio/dekorate/deps/snakeyaml/tokens/Token$ID;
     282: aastore
     283: invokeinterface #187,  2          // InterfaceMethod io/dekorate/deps/snakeyaml/scanner/Scanner.checkToken:([Lio/dekorate/deps/snakeyaml/tokens/Token$ID;)Z
     288: ifeq          319
     291: aload_0
     292: getfield      #126                // Field scanner:Lio/dekorate/deps/snakeyaml/scanner/Scanner;
     295: invokeinterface #191,  1          // InterfaceMethod io/dekorate/deps/snakeyaml/scanner/Scanner.getToken:()Lio/dekorate/deps/snakeyaml/tokens/Token;
     300: checkcast     #340                // class io/dekorate/deps/snakeyaml/tokens/AnchorToken
     303: astore        10
     305: aload         10
     307: invokevirtual #342                // Method io/dekorate/deps/snakeyaml/tokens/AnchorToken.getEndMark:()Lio/dekorate/deps/snakeyaml/error/Mark;
     310: astore        5
     312: aload         10
     314: invokevirtual #343                // Method io/dekorate/deps/snakeyaml/tokens/AnchorToken.getValue:()Ljava/lang/String;
     317: astore        7
     319: aconst_null
     320: astore        9
     322: aload         8
     324: ifnull        443
     327: aload         8
     329: invokevirtual #358                // Method io/dekorate/deps/snakeyaml/tokens/TagTuple.getHandle:()Ljava/lang/String;
     332: astore        10
     334: aload         8
     336: invokevirtual #361                // Method io/dekorate/deps/snakeyaml/tokens/TagTuple.getSuffix:()Ljava/lang/String;
     339: astore        11
     341: aload         10
     343: ifnull        439
     346: aload_0
     347: getfield      #142                // Field directives:Lio/dekorate/deps/snakeyaml/parser/VersionTagsTuple;
     350: invokevirtual #365                // Method io/dekorate/deps/snakeyaml/parser/VersionTagsTuple.getTags:()Ljava/util/Map;
     353: aload         10
     355: invokeinterface #366,  2          // InterfaceMethod java/util/Map.containsKey:(Ljava/lang/Object;)Z
     360: ifne          399
     363: new           #207                // class io/dekorate/deps/snakeyaml/parser/ParserException
     366: dup
     367: ldc_w         #368                // String while parsing a node
     370: aload         4
     372: new           #248                // class java/lang/StringBuilder
     375: dup
     376: invokespecial #249                // Method java/lang/StringBuilder."<init>":()V
     379: ldc_w         #370                // String found undefined tag handle
     382: invokevirtual #255                // Method java/lang/StringBuilder.append:(Ljava/lang/String;)Ljava/lang/StringBuilder;
     385: aload         10
     387: invokevirtual #255                // Method java/lang/StringBuilder.append:(Ljava/lang/String;)Ljava/lang/StringBuilder;
     390: invokevirtual #258                // Method java/lang/StringBuilder.toString:()Ljava/lang/String;
     393: aload         6
     395: invokespecial #216                // Method io/dekorate/deps/snakeyaml/parser/ParserException."<init>":(Ljava/lang/String;Lio/dekorate/deps/snakeyaml/error/Mark;Ljava/lang/String;Lio/dekorate/deps/snakeyaml/error/Mark;)V
     398: athrow
     399: new           #248                // class java/lang/StringBuilder
     402: dup
     403: invokespecial #249                // Method java/lang/StringBuilder."<init>":()V
     406: aload_0
     407: getfield      #142                // Field directives:Lio/dekorate/deps/snakeyaml/parser/VersionTagsTuple;
     410: invokevirtual #365                // Method io/dekorate/deps/snakeyaml/parser/VersionTagsTuple.getTags:()Ljava/util/Map;
     413: aload         10
     415: invokeinterface #290,  2          // InterfaceMethod java/util/Map.get:(Ljava/lang/Object;)Ljava/lang/Object;
     420: checkcast     #201                // class java/lang/String
     423: invokevirtual #255                // Method java/lang/StringBuilder.append:(Ljava/lang/String;)Ljava/lang/StringBuilder;
     426: aload         11
     428: invokevirtual #255                // Method java/lang/StringBuilder.append:(Ljava/lang/String;)Ljava/lang/StringBuilder;
     431: invokevirtual #258                // Method java/lang/StringBuilder.toString:()Ljava/lang/String;
     434: astore        9
     436: goto          443
     439: aload         11
     441: astore        9
     443: aload         4
     445: ifnonnull     466
     448: aload_0
     449: getfield      #126                // Field scanner:Lio/dekorate/deps/snakeyaml/scanner/Scanner;
     452: invokeinterface #373,  1          // InterfaceMethod io/dekorate/deps/snakeyaml/scanner/Scanner.peekToken:()Lio/dekorate/deps/snakeyaml/tokens/Token;
     457: invokevirtual #374                // Method io/dekorate/deps/snakeyaml/tokens/Token.getStartMark:()Lio/dekorate/deps/snakeyaml/error/Mark;
     460: astore        4
     462: aload         4
     464: astore        5
     466: aconst_null
     467: astore_3
     468: aload         9
     470: ifnull        484
     473: aload         9
     475: ldc_w         #376                // String !
     478: invokevirtual #205                // Method java/lang/String.equals:(Ljava/lang/Object;)Z
     481: ifeq          488
     484: iconst_1
     485: goto          489
     488: iconst_0
     489: istore        10
     491: iload_2
     492: ifeq          568
     495: aload_0
     496: getfield      #126                // Field scanner:Lio/dekorate/deps/snakeyaml/scanner/Scanner;
     499: iconst_1
     500: anewarray     #84                 // class io/dekorate/deps/snakeyaml/tokens/Token$ID
     503: dup
     504: iconst_0
     505: getstatic     #379                // Field io/dekorate/deps/snakeyaml/tokens/Token$ID.BlockEntry:Lio/dekorate/deps/snakeyaml/tokens/Token$ID;
     508: aastore
     509: invokeinterface #187,  2          // InterfaceMethod io/dekorate/deps/snakeyaml/scanner/Scanner.checkToken:([Lio/dekorate/deps/snakeyaml/tokens/Token$ID;)Z
     514: ifeq          568
     517: aload_0
     518: getfield      #126                // Field scanner:Lio/dekorate/deps/snakeyaml/scanner/Scanner;
     521: invokeinterface #373,  1          // InterfaceMethod io/dekorate/deps/snakeyaml/scanner/Scanner.peekToken:()Lio/dekorate/deps/snakeyaml/tokens/Token;
     526: invokevirtual #380                // Method io/dekorate/deps/snakeyaml/tokens/Token.getEndMark:()Lio/dekorate/deps/snakeyaml/error/Mark;
     529: astore        5
     531: new           #382                // class io/dekorate/deps/snakeyaml/events/SequenceStartEvent
     534: dup
     535: aload         7
     537: aload         9
     539: iload         10
     541: aload         4
     543: aload         5
     545: getstatic     #386                // Field io/dekorate/deps/snakeyaml/DumperOptions$FlowStyle.BLOCK:Lio/dekorate/deps/snakeyaml/DumperOptions$FlowStyle;
     548: invokespecial #389                // Method io/dekorate/deps/snakeyaml/events/SequenceStartEvent."<init>":(Ljava/lang/String;Ljava/lang/String;ZLio/dekorate/deps/snakeyaml/error/Mark;Lio/dekorate/deps/snakeyaml/error/Mark;Lio/dekorate/deps/snakeyaml/DumperOptions$FlowStyle;)V
     551: astore_3
     552: aload_0
     553: new           #47                 // class io/dekorate/deps/snakeyaml/parser/ParserImpl$ParseIndentlessSequenceEntry
     556: dup
     557: aload_0
     558: aconst_null
     559: invokespecial #390                // Method io/dekorate/deps/snakeyaml/parser/ParserImpl$ParseIndentlessSequenceEntry."<init>":(Lio/dekorate/deps/snakeyaml/parser/ParserImpl;Lio/dekorate/deps/snakeyaml/parser/ParserImpl$1;)V
     562: putfield      #156                // Field state:Lio/dekorate/deps/snakeyaml/parser/Production;
     565: goto          1183
     568: aload_0
     569: getfield      #126                // Field scanner:Lio/dekorate/deps/snakeyaml/scanner/Scanner;
     572: iconst_1
     573: anewarray     #84                 // class io/dekorate/deps/snakeyaml/tokens/Token$ID
     576: dup
     577: iconst_0
     578: getstatic     #393                // Field io/dekorate/deps/snakeyaml/tokens/Token$ID.Scalar:Lio/dekorate/deps/snakeyaml/tokens/Token$ID;
     581: aastore
     582: invokeinterface #187,  2          // InterfaceMethod io/dekorate/deps/snakeyaml/scanner/Scanner.checkToken:([Lio/dekorate/deps/snakeyaml/tokens/Token$ID;)Z
     587: ifeq          724
     590: aload_0
     591: getfield      #126                // Field scanner:Lio/dekorate/deps/snakeyaml/scanner/Scanner;
     594: invokeinterface #191,  1          // InterfaceMethod io/dekorate/deps/snakeyaml/scanner/Scanner.getToken:()Lio/dekorate/deps/snakeyaml/tokens/Token;
     599: checkcast     #395                // class io/dekorate/deps/snakeyaml/tokens/ScalarToken
     602: astore        11
     604: aload         11
     606: invokevirtual #396                // Method io/dekorate/deps/snakeyaml/tokens/ScalarToken.getEndMark:()Lio/dekorate/deps/snakeyaml/error/Mark;
     609: astore        5
     611: aload         11
     613: invokevirtual #399                // Method io/dekorate/deps/snakeyaml/tokens/ScalarToken.getPlain:()Z
     616: ifeq          624
     619: aload         9
     621: ifnull        635
     624: ldc_w         #376                // String !
     627: aload         9
     629: invokevirtual #205                // Method java/lang/String.equals:(Ljava/lang/Object;)Z
     632: ifeq          649
     635: new           #401                // class io/dekorate/deps/snakeyaml/events/ImplicitTuple
     638: dup
     639: iconst_1
     640: iconst_0
     641: invokespecial #404                // Method io/dekorate/deps/snakeyaml/events/ImplicitTuple."<init>":(ZZ)V
     644: astore        12
     646: goto          679
     649: aload         9
     651: ifnonnull     668
     654: new           #401                // class io/dekorate/deps/snakeyaml/events/ImplicitTuple
     657: dup
     658: iconst_0
     659: iconst_1
     660: invokespecial #404                // Method io/dekorate/deps/snakeyaml/events/ImplicitTuple."<init>":(ZZ)V
     663: astore        12
     665: goto          679
     668: new           #401                // class io/dekorate/deps/snakeyaml/events/ImplicitTuple
     671: dup
     672: iconst_0
     673: iconst_0
     674: invokespecial #404                // Method io/dekorate/deps/snakeyaml/events/ImplicitTuple."<init>":(ZZ)V
     677: astore        12
     679: new           #406                // class io/dekorate/deps/snakeyaml/events/ScalarEvent
     682: dup
     683: aload         7
     685: aload         9
     687: aload         12
     689: aload         11
     691: invokevirtual #407                // Method io/dekorate/deps/snakeyaml/tokens/ScalarToken.getValue:()Ljava/lang/String;
     694: aload         4
     696: aload         5
     698: aload         11
     700: invokevirtual #411                // Method io/dekorate/deps/snakeyaml/tokens/ScalarToken.getStyle:()Lio/dekorate/deps/snakeyaml/DumperOptions$ScalarStyle;
     703: invokespecial #414                // Method io/dekorate/deps/snakeyaml/events/ScalarEvent."<init>":(Ljava/lang/String;Ljava/lang/String;Lio/dekorate/deps/snakeyaml/events/ImplicitTuple;Ljava/lang/String;Lio/dekorate/deps/snakeyaml/error/Mark;Lio/dekorate/deps/snakeyaml/error/Mark;Lio/dekorate/deps/snakeyaml/DumperOptions$ScalarStyle;)V
     706: astore_3
     707: aload_0
     708: aload_0
     709: getfield      #149                // Field states:Lio/dekorate/deps/snakeyaml/util/ArrayStack;
     712: invokevirtual #333                // Method io/dekorate/deps/snakeyaml/util/ArrayStack.pop:()Ljava/lang/Object;
     715: checkcast     #169                // class io/dekorate/deps/snakeyaml/parser/Production
     718: putfield      #156                // Field state:Lio/dekorate/deps/snakeyaml/parser/Production;
     721: goto          1183
     724: aload_0
     725: getfield      #126                // Field scanner:Lio/dekorate/deps/snakeyaml/scanner/Scanner;
     728: iconst_1
     729: anewarray     #84                 // class io/dekorate/deps/snakeyaml/tokens/Token$ID
     732: dup
     733: iconst_0
     734: getstatic     #417                // Field io/dekorate/deps/snakeyaml/tokens/Token$ID.FlowSequenceStart:Lio/dekorate/deps/snakeyaml/tokens/Token$ID;
     737: aastore
     738: invokeinterface #187,  2          // InterfaceMethod io/dekorate/deps/snakeyaml/scanner/Scanner.checkToken:([Lio/dekorate/deps/snakeyaml/tokens/Token$ID;)Z
     743: ifeq          797
     746: aload_0
     747: getfield      #126                // Field scanner:Lio/dekorate/deps/snakeyaml/scanner/Scanner;
     750: invokeinterface #373,  1          // InterfaceMethod io/dekorate/deps/snakeyaml/scanner/Scanner.peekToken:()Lio/dekorate/deps/snakeyaml/tokens/Token;
     755: invokevirtual #380                // Method io/dekorate/deps/snakeyaml/tokens/Token.getEndMark:()Lio/dekorate/deps/snakeyaml/error/Mark;
     758: astore        5
     760: new           #382                // class io/dekorate/deps/snakeyaml/events/SequenceStartEvent
     763: dup
     764: aload         7
     766: aload         9
     768: iload         10
     770: aload         4
     772: aload         5
     774: getstatic     #420                // Field io/dekorate/deps/snakeyaml/DumperOptions$FlowStyle.FLOW:Lio/dekorate/deps/snakeyaml/DumperOptions$FlowStyle;
     777: invokespecial #389                // Method io/dekorate/deps/snakeyaml/events/SequenceStartEvent."<init>":(Ljava/lang/String;Ljava/lang/String;ZLio/dekorate/deps/snakeyaml/error/Mark;Lio/dekorate/deps/snakeyaml/error/Mark;Lio/dekorate/deps/snakeyaml/DumperOptions$FlowStyle;)V
     780: astore_3
     781: aload_0
     782: new           #35                 // class io/dekorate/deps/snakeyaml/parser/ParserImpl$ParseFlowSequenceFirstEntry
     785: dup
     786: aload_0
     787: aconst_null
     788: invokespecial #421                // Method io/dekorate/deps/snakeyaml/parser/ParserImpl$ParseFlowSequenceFirstEntry."<init>":(Lio/dekorate/deps/snakeyaml/parser/ParserImpl;Lio/dekorate/deps/snakeyaml/parser/ParserImpl$1;)V
     791: putfield      #156                // Field state:Lio/dekorate/deps/snakeyaml/parser/Production;
     794: goto          1183
     797: aload_0
     798: getfield      #126                // Field scanner:Lio/dekorate/deps/snakeyaml/scanner/Scanner;
     801: iconst_1
     802: anewarray     #84                 // class io/dekorate/deps/snakeyaml/tokens/Token$ID
     805: dup
     806: iconst_0
     807: getstatic     #424                // Field io/dekorate/deps/snakeyaml/tokens/Token$ID.FlowMappingStart:Lio/dekorate/deps/snakeyaml/tokens/Token$ID;
     810: aastore
     811: invokeinterface #187,  2          // InterfaceMethod io/dekorate/deps/snakeyaml/scanner/Scanner.checkToken:([Lio/dekorate/deps/snakeyaml/tokens/Token$ID;)Z
     816: ifeq          870
     819: aload_0
     820: getfield      #126                // Field scanner:Lio/dekorate/deps/snakeyaml/scanner/Scanner;
     823: invokeinterface #373,  1          // InterfaceMethod io/dekorate/deps/snakeyaml/scanner/Scanner.peekToken:()Lio/dekorate/deps/snakeyaml/tokens/Token;
     828: invokevirtual #380                // Method io/dekorate/deps/snakeyaml/tokens/Token.getEndMark:()Lio/dekorate/deps/snakeyaml/error/Mark;
     831: astore        5
     833: new           #426                // class io/dekorate/deps/snakeyaml/events/MappingStartEvent
     836: dup
     837: aload         7
     839: aload         9
     841: iload         10
     843: aload         4
     845: aload         5
     847: getstatic     #420                // Field io/dekorate/deps/snakeyaml/DumperOptions$FlowStyle.FLOW:Lio/dekorate/deps/snakeyaml/DumperOptions$FlowStyle;
     850: invokespecial #427                // Method io/dekorate/deps/snakeyaml/events/MappingStartEvent."<init>":(Ljava/lang/String;Ljava/lang/String;ZLio/dekorate/deps/snakeyaml/error/Mark;Lio/dekorate/deps/snakeyaml/error/Mark;Lio/dekorate/deps/snakeyaml/DumperOptions$FlowStyle;)V
     853: astore_3
     854: aload_0
     855: new           #20                 // class io/dekorate/deps/snakeyaml/parser/ParserImpl$ParseFlowMappingFirstKey
     858: dup
     859: aload_0
     860: aconst_null
     861: invokespecial #428                // Method io/dekorate/deps/snakeyaml/parser/ParserImpl$ParseFlowMappingFirstKey."<init>":(Lio/dekorate/deps/snakeyaml/parser/ParserImpl;Lio/dekorate/deps/snakeyaml/parser/ParserImpl$1;)V
     864: putfield      #156                // Field state:Lio/dekorate/deps/snakeyaml/parser/Production;
     867: goto          1183
     870: iload_1
     871: ifeq          947
     874: aload_0
     875: getfield      #126                // Field scanner:Lio/dekorate/deps/snakeyaml/scanner/Scanner;
     878: iconst_1
     879: anewarray     #84                 // class io/dekorate/deps/snakeyaml/tokens/Token$ID
     882: dup
     883: iconst_0
     884: getstatic     #431                // Field io/dekorate/deps/snakeyaml/tokens/Token$ID.BlockSequenceStart:Lio/dekorate/deps/snakeyaml/tokens/Token$ID;
     887: aastore
     888: invokeinterface #187,  2          // InterfaceMethod io/dekorate/deps/snakeyaml/scanner/Scanner.checkToken:([Lio/dekorate/deps/snakeyaml/tokens/Token$ID;)Z
     893: ifeq          947
     896: aload_0
     897: getfield      #126                // Field scanner:Lio/dekorate/deps/snakeyaml/scanner/Scanner;
     900: invokeinterface #373,  1          // InterfaceMethod io/dekorate/deps/snakeyaml/scanner/Scanner.peekToken:()Lio/dekorate/deps/snakeyaml/tokens/Token;
     905: invokevirtual #374                // Method io/dekorate/deps/snakeyaml/tokens/Token.getStartMark:()Lio/dekorate/deps/snakeyaml/error/Mark;
     908: astore        5
     910: new           #382                // class io/dekorate/deps/snakeyaml/events/SequenceStartEvent
     913: dup
     914: aload         7
     916: aload         9
     918: iload         10
     920: aload         4
     922: aload         5
     924: getstatic     #386                // Field io/dekorate/deps/snakeyaml/DumperOptions$FlowStyle.BLOCK:Lio/dekorate/deps/snakeyaml/DumperOptions$FlowStyle;
     927: invokespecial #389                // Method io/dekorate/deps/snakeyaml/events/SequenceStartEvent."<init>":(Ljava/lang/String;Ljava/lang/String;ZLio/dekorate/deps/snakeyaml/error/Mark;Lio/dekorate/deps/snakeyaml/error/Mark;Lio/dekorate/deps/snakeyaml/DumperOptions$FlowStyle;)V
     930: astore_3
     931: aload_0
     932: new           #53                 // class io/dekorate/deps/snakeyaml/parser/ParserImpl$ParseBlockSequenceFirstEntry
     935: dup
     936: aload_0
     937: aconst_null
     938: invokespecial #432                // Method io/dekorate/deps/snakeyaml/parser/ParserImpl$ParseBlockSequenceFirstEntry."<init>":(Lio/dekorate/deps/snakeyaml/parser/ParserImpl;Lio/dekorate/deps/snakeyaml/parser/ParserImpl$1;)V
     941: putfield      #156                // Field state:Lio/dekorate/deps/snakeyaml/parser/Production;
     944: goto          1183
     947: iload_1
     948: ifeq          1024
     951: aload_0
     952: getfield      #126                // Field scanner:Lio/dekorate/deps/snakeyaml/scanner/Scanner;
     955: iconst_1
     956: anewarray     #84                 // class io/dekorate/deps/snakeyaml/tokens/Token$ID
     959: dup
     960: iconst_0
     961: getstatic     #435                // Field io/dekorate/deps/snakeyaml/tokens/Token$ID.BlockMappingStart:Lio/dekorate/deps/snakeyaml/tokens/Token$ID;
     964: aastore
     965: invokeinterface #187,  2          // InterfaceMethod io/dekorate/deps/snakeyaml/scanner/Scanner.checkToken:([Lio/dekorate/deps/snakeyaml/tokens/Token$ID;)Z
     970: ifeq          1024
     973: aload_0
     974: getfield      #126                // Field scanner:Lio/dekorate/deps/snakeyaml/scanner/Scanner;
     977: invokeinterface #373,  1          // InterfaceMethod io/dekorate/deps/snakeyaml/scanner/Scanner.peekToken:()Lio/dekorate/deps/snakeyaml/tokens/Token;
     982: invokevirtual #374                // Method io/dekorate/deps/snakeyaml/tokens/Token.getStartMark:()Lio/dekorate/deps/snakeyaml/error/Mark;
     985: astore        5
     987: new           #426                // class io/dekorate/deps/snakeyaml/events/MappingStartEvent
     990: dup
     991: aload         7
     993: aload         9
     995: iload         10
     997: aload         4
     999: aload         5
    1001: getstatic     #386                // Field io/dekorate/deps/snakeyaml/DumperOptions$FlowStyle.BLOCK:Lio/dekorate/deps/snakeyaml/DumperOptions$FlowStyle;
    1004: invokespecial #427                // Method io/dekorate/deps/snakeyaml/events/MappingStartEvent."<init>":(Ljava/lang/String;Ljava/lang/String;ZLio/dekorate/deps/snakeyaml/error/Mark;Lio/dekorate/deps/snakeyaml/error/Mark;Lio/dekorate/deps/snakeyaml/DumperOptions$FlowStyle;)V
    1007: astore_3
    1008: aload_0
    1009: new           #44                 // class io/dekorate/deps/snakeyaml/parser/ParserImpl$ParseBlockMappingFirstKey
    1012: dup
    1013: aload_0
    1014: aconst_null
    1015: invokespecial #436                // Method io/dekorate/deps/snakeyaml/parser/ParserImpl$ParseBlockMappingFirstKey."<init>":(Lio/dekorate/deps/snakeyaml/parser/ParserImpl;Lio/dekorate/deps/snakeyaml/parser/ParserImpl$1;)V
    1018: putfield      #156                // Field state:Lio/dekorate/deps/snakeyaml/parser/Production;
    1021: goto          1183
    1024: aload         7
    1026: ifnonnull     1034
    1029: aload         9
    1031: ifnull        1083
    1034: new           #406                // class io/dekorate/deps/snakeyaml/events/ScalarEvent
    1037: dup
    1038: aload         7
    1040: aload         9
    1042: new           #401                // class io/dekorate/deps/snakeyaml/events/ImplicitTuple
    1045: dup
    1046: iload         10
    1048: iconst_0
    1049: invokespecial #404                // Method io/dekorate/deps/snakeyaml/events/ImplicitTuple."<init>":(ZZ)V
    1052: ldc_w         #438                // String
    1055: aload         4
    1057: aload         5
    1059: getstatic     #442                // Field io/dekorate/deps/snakeyaml/DumperOptions$ScalarStyle.PLAIN:Lio/dekorate/deps/snakeyaml/DumperOptions$ScalarStyle;
    1062: invokespecial #414                // Method io/dekorate/deps/snakeyaml/events/ScalarEvent."<init>":(Ljava/lang/String;Ljava/lang/String;Lio/dekorate/deps/snakeyaml/events/ImplicitTuple;Ljava/lang/String;Lio/dekorate/deps/snakeyaml/error/Mark;Lio/dekorate/deps/snakeyaml/error/Mark;Lio/dekorate/deps/snakeyaml/DumperOptions$ScalarStyle;)V
    1065: astore_3
    1066: aload_0
    1067: aload_0
    1068: getfield      #149                // Field states:Lio/dekorate/deps/snakeyaml/util/ArrayStack;
    1071: invokevirtual #333                // Method io/dekorate/deps/snakeyaml/util/ArrayStack.pop:()Ljava/lang/Object;
    1074: checkcast     #169                // class io/dekorate/deps/snakeyaml/parser/Production
    1077: putfield      #156                // Field state:Lio/dekorate/deps/snakeyaml/parser/Production;
    1080: goto          1183
    1083: iload_1
    1084: ifeq          1095
    1087: ldc_w         #444                // String block
    1090: astore        11
    1092: goto          1100
    1095: ldc_w         #446                // String flow
    1098: astore        11
    1100: aload_0
    1101: getfield      #126                // Field scanner:Lio/dekorate/deps/snakeyaml/scanner/Scanner;
    1104: invokeinterface #373,  1          // InterfaceMethod io/dekorate/deps/snakeyaml/scanner/Scanner.peekToken:()Lio/dekorate/deps/snakeyaml/tokens/Token;
    1109: astore        12
    1111: new           #207                // class io/dekorate/deps/snakeyaml/parser/ParserException
    1114: dup
    1115: new           #248                // class java/lang/StringBuilder
    1118: dup
    1119: invokespecial #249                // Method java/lang/StringBuilder."<init>":()V
    1122: ldc_w         #448                // String while parsing a
    1125: invokevirtual #255                // Method java/lang/StringBuilder.append:(Ljava/lang/String;)Ljava/lang/StringBuilder;
    1128: aload         11
    1130: invokevirtual #255                // Method java/lang/StringBuilder.append:(Ljava/lang/String;)Ljava/lang/StringBuilder;
    1133: ldc_w         #450                // String  node
    1136: invokevirtual #255                // Method java/lang/StringBuilder.append:(Ljava/lang/String;)Ljava/lang/StringBuilder;
    1139: invokevirtual #258                // Method java/lang/StringBuilder.toString:()Ljava/lang/String;
    1142: aload         4
    1144: new           #248                // class java/lang/StringBuilder
    1147: dup
    1148: invokespecial #249                // Method java/lang/StringBuilder."<init>":()V
    1151: ldc_w         #452                // String expected the node content, but found \'
    1154: invokevirtual #255                // Method java/lang/StringBuilder.append:(Ljava/lang/String;)Ljava/lang/StringBuilder;
    1157: aload         12
    1159: invokevirtual #456                // Method io/dekorate/deps/snakeyaml/tokens/Token.getTokenId:()Lio/dekorate/deps/snakeyaml/tokens/Token$ID;
    1162: invokevirtual #459                // Method java/lang/StringBuilder.append:(Ljava/lang/Object;)Ljava/lang/StringBuilder;
    1165: ldc_w         #461                // String \'
    1168: invokevirtual #255                // Method java/lang/StringBuilder.append:(Ljava/lang/String;)Ljava/lang/StringBuilder;
    1171: invokevirtual #258                // Method java/lang/StringBuilder.toString:()Ljava/lang/String;
    1174: aload         12
    1176: invokevirtual #374                // Method io/dekorate/deps/snakeyaml/tokens/Token.getStartMark:()Lio/dekorate/deps/snakeyaml/error/Mark;
    1179: invokespecial #216                // Method io/dekorate/deps/snakeyaml/parser/ParserException."<init>":(Ljava/lang/String;Lio/dekorate/deps/snakeyaml/error/Mark;Ljava/lang/String;Lio/dekorate/deps/snakeyaml/error/Mark;)V
    1182: athrow
    1183: aload_3
    1184: areturn

  private io.dekorate.deps.snakeyaml.events.Event processEmptyScalar(io.dekorate.deps.snakeyaml.error.Mark);
    Code:
       0: new           #406                // class io/dekorate/deps/snakeyaml/events/ScalarEvent
       3: dup
       4: aconst_null
       5: aconst_null
       6: new           #401                // class io/dekorate/deps/snakeyaml/events/ImplicitTuple
       9: dup
      10: iconst_1
      11: iconst_0
      12: invokespecial #404                // Method io/dekorate/deps/snakeyaml/events/ImplicitTuple."<init>":(ZZ)V
      15: ldc_w         #438                // String
      18: aload_1
      19: aload_1
      20: getstatic     #442                // Field io/dekorate/deps/snakeyaml/DumperOptions$ScalarStyle.PLAIN:Lio/dekorate/deps/snakeyaml/DumperOptions$ScalarStyle;
      23: invokespecial #414                // Method io/dekorate/deps/snakeyaml/events/ScalarEvent."<init>":(Ljava/lang/String;Ljava/lang/String;Lio/dekorate/deps/snakeyaml/events/ImplicitTuple;Ljava/lang/String;Lio/dekorate/deps/snakeyaml/error/Mark;Lio/dekorate/deps/snakeyaml/error/Mark;Lio/dekorate/deps/snakeyaml/DumperOptions$ScalarStyle;)V
      26: areturn

  static io.dekorate.deps.snakeyaml.parser.Production access$102(io.dekorate.deps.snakeyaml.parser.ParserImpl, io.dekorate.deps.snakeyaml.parser.Production);
    Code:
       0: aload_0
       1: aload_1
       2: dup_x1
       3: putfield      #156                // Field state:Lio/dekorate/deps/snakeyaml/parser/Production;
       6: areturn

  static io.dekorate.deps.snakeyaml.parser.VersionTagsTuple access$302(io.dekorate.deps.snakeyaml.parser.ParserImpl, io.dekorate.deps.snakeyaml.parser.VersionTagsTuple);
    Code:
       0: aload_0
       1: aload_1
       2: dup_x1
       3: putfield      #142                // Field directives:Lio/dekorate/deps/snakeyaml/parser/VersionTagsTuple;
       6: areturn

  static java.util.Map access$400();
    Code:
       0: getstatic     #134                // Field DEFAULT_TAGS:Ljava/util/Map;
       3: areturn

  static io.dekorate.deps.snakeyaml.util.ArrayStack access$600(io.dekorate.deps.snakeyaml.parser.ParserImpl);
    Code:
       0: aload_0
       1: getfield      #149                // Field states:Lio/dekorate/deps/snakeyaml/util/ArrayStack;
       4: areturn

  static io.dekorate.deps.snakeyaml.parser.VersionTagsTuple access$900(io.dekorate.deps.snakeyaml.parser.ParserImpl);
    Code:
       0: aload_0
       1: invokespecial #499                // Method processDirectives:()Lio/dekorate/deps/snakeyaml/parser/VersionTagsTuple;
       4: areturn

  static io.dekorate.deps.snakeyaml.util.ArrayStack access$1100(io.dekorate.deps.snakeyaml.parser.ParserImpl);
    Code:
       0: aload_0
       1: getfield      #151                // Field marks:Lio/dekorate/deps/snakeyaml/util/ArrayStack;
       4: areturn

  static io.dekorate.deps.snakeyaml.events.Event access$1200(io.dekorate.deps.snakeyaml.parser.ParserImpl, io.dekorate.deps.snakeyaml.error.Mark);
    Code:
       0: aload_0
       1: aload_1
       2: invokespecial #504                // Method processEmptyScalar:(Lio/dekorate/deps/snakeyaml/error/Mark;)Lio/dekorate/deps/snakeyaml/events/Event;
       5: areturn

  static io.dekorate.deps.snakeyaml.events.Event access$1300(io.dekorate.deps.snakeyaml.parser.ParserImpl, boolean, boolean);
    Code:
       0: aload_0
       1: iload_1
       2: iload_2
       3: invokespecial #313                // Method parseNode:(ZZ)Lio/dekorate/deps/snakeyaml/events/Event;
       6: areturn

  static io.dekorate.deps.snakeyaml.events.Event access$2200(io.dekorate.deps.snakeyaml.parser.ParserImpl);
    Code:
       0: aload_0
       1: invokespecial #511                // Method parseBlockNodeOrIndentlessSequence:()Lio/dekorate/deps/snakeyaml/events/Event;
       4: areturn

  static io.dekorate.deps.snakeyaml.events.Event access$2400(io.dekorate.deps.snakeyaml.parser.ParserImpl);
    Code:
       0: aload_0
       1: invokespecial #514                // Method parseFlowNode:()Lio/dekorate/deps/snakeyaml/events/Event;
       4: areturn

  static {};
    Code:
       0: new           #132                // class java/util/HashMap
       3: dup
       4: invokespecial #177                // Method java/util/HashMap."<init>":()V
       7: putstatic     #134                // Field DEFAULT_TAGS:Ljava/util/Map;
      10: getstatic     #134                // Field DEFAULT_TAGS:Ljava/util/Map;
      13: ldc_w         #376                // String !
      16: ldc_w         #376                // String !
      19: invokeinterface #516,  3          // InterfaceMethod java/util/Map.put:(Ljava/lang/Object;Ljava/lang/Object;)Ljava/lang/Object;
      24: pop
      25: getstatic     #134                // Field DEFAULT_TAGS:Ljava/util/Map;
      28: ldc_w         #518                // String !!
      31: ldc_w         #520                // String tag:yaml.org,2002:
      34: invokeinterface #516,  3          // InterfaceMethod java/util/Map.put:(Ljava/lang/Object;Ljava/lang/Object;)Ljava/lang/Object;
      39: pop
      40: return
}
