Compiled from "SubjectQuerySchemaValidator.java"
public abstract class org.opensaml.saml2.core.validator.SubjectQuerySchemaValidator<SubjectQueryType extends org.opensaml.saml2.core.SubjectQuery> extends org.opensaml.saml2.core.validator.RequestAbstractTypeSchemaValidator<SubjectQueryType> {
  public org.opensaml.saml2.core.validator.SubjectQuerySchemaValidator();
    Code:
       0: aload_0
       1: invokespecial #1                  // Method org/opensaml/saml2/core/validator/RequestAbstractTypeSchemaValidator."<init>":()V
       4: return

  public void validate(SubjectQueryType) throws org.opensaml.xml.validation.ValidationException;
    Code:
       0: aload_0
       1: aload_1
       2: invokespecial #2                  // Method org/opensaml/saml2/core/validator/RequestAbstractTypeSchemaValidator.validate:(Lorg/opensaml/saml2/core/RequestAbstractType;)V
       5: aload_0
       6: aload_1
       7: invokevirtual #3                  // Method validateSubject:(Lorg/opensaml/saml2/core/SubjectQuery;)V
      10: return

  protected void validateSubject(org.opensaml.saml2.core.SubjectQuery) throws org.opensaml.xml.validation.ValidationException;
    Code:
       0: aload_1
       1: invokeinterface #4,  1            // InterfaceMethod org/opensaml/saml2/core/SubjectQuery.getSubject:()Lorg/opensaml/saml2/core/Subject;
       6: ifnonnull     19
       9: new           #5                  // class org/opensaml/xml/validation/ValidationException
      12: dup
      13: ldc           #6                  // String Subject is required
      15: invokespecial #7                  // Method org/opensaml/xml/validation/ValidationException."<init>":(Ljava/lang/String;)V
      18: athrow
      19: return

  public void validate(org.opensaml.saml2.core.RequestAbstractType) throws org.opensaml.xml.validation.ValidationException;
    Code:
       0: aload_0
       1: aload_1
       2: checkcast     #8                  // class org/opensaml/saml2/core/SubjectQuery
       5: invokevirtual #9                  // Method validate:(Lorg/opensaml/saml2/core/SubjectQuery;)V
       8: return

  public void validate(org.opensaml.xml.XMLObject) throws org.opensaml.xml.validation.ValidationException;
    Code:
       0: aload_0
       1: aload_1
       2: checkcast     #8                  // class org/opensaml/saml2/core/SubjectQuery
       5: invokevirtual #9                  // Method validate:(Lorg/opensaml/saml2/core/SubjectQuery;)V
       8: return
}
