Compiled from "GenSetLike.scala"
public abstract class scala.collection.GenSetLike$class {
  public static boolean apply(scala.collection.GenSetLike, java.lang.Object);
    Code:
       0: aload_0
       1: aload_1
       2: invokeinterface #13,  2           // InterfaceMethod scala/collection/GenSetLike.contains:(Ljava/lang/Object;)Z
       7: ireturn

  public static java.lang.Object intersect(scala.collection.GenSetLike, scala.collection.GenSet);
    Code:
       0: aload_0
       1: aload_1
       2: invokeinterface #23,  2           // InterfaceMethod scala/collection/GenSetLike.filter:(Lscala/Function1;)Ljava/lang/Object;
       7: areturn

  public static java.lang.Object $amp(scala.collection.GenSetLike, scala.collection.GenSet);
    Code:
       0: aload_0
       1: aload_1
       2: invokeinterface #29,  2           // InterfaceMethod scala/collection/GenSetLike.intersect:(Lscala/collection/GenSet;)Ljava/lang/Object;
       7: areturn

  public static java.lang.Object $bar(scala.collection.GenSetLike, scala.collection.GenSet);
    Code:
       0: aload_0
       1: aload_1
       2: invokeinterface #33,  2           // InterfaceMethod scala/collection/GenSetLike.union:(Lscala/collection/GenSet;)Ljava/lang/Object;
       7: areturn

  public static java.lang.Object $amp$tilde(scala.collection.GenSetLike, scala.collection.GenSet);
    Code:
       0: aload_0
       1: aload_1
       2: invokeinterface #37,  2           // InterfaceMethod scala/collection/GenSetLike.diff:(Lscala/collection/GenSet;)Ljava/lang/Object;
       7: areturn

  public static boolean subsetOf(scala.collection.GenSetLike, scala.collection.GenSet);
    Code:
       0: aload_0
       1: aload_1
       2: invokeinterface #43,  2           // InterfaceMethod scala/collection/GenSetLike.forall:(Lscala/Function1;)Z
       7: ireturn

  public static boolean equals(scala.collection.GenSetLike, java.lang.Object);
    Code:
       0: aload_1
       1: instanceof    #46                 // class scala/collection/GenSet
       4: ifeq          59
       7: aload_1
       8: checkcast     #46                 // class scala/collection/GenSet
      11: astore_2
      12: aload_0
      13: aload_2
      14: if_acmpeq     50
      17: aload_2
      18: aload_0
      19: invokeinterface #49,  2           // InterfaceMethod scala/collection/GenSet.canEqual:(Ljava/lang/Object;)Z
      24: ifeq          54
      27: aload_0
      28: invokeinterface #53,  1           // InterfaceMethod scala/collection/GenSetLike.size:()I
      33: aload_2
      34: invokeinterface #54,  1           // InterfaceMethod scala/collection/GenSet.size:()I
      39: if_icmpne     54
      42: aload_0
      43: aload_2
      44: invokestatic  #57                 // Method liftedTree1$1:(Lscala/collection/GenSetLike;Lscala/collection/GenSet;)Z
      47: ifeq          54
      50: iconst_1
      51: goto          55
      54: iconst_0
      55: istore_3
      56: goto          61
      59: iconst_0
      60: istore_3
      61: iload_3
      62: ireturn

  public static int hashCode(scala.collection.GenSetLike);
    Code:
       0: getstatic     #65                 // Field scala/util/hashing/MurmurHash3$.MODULE$:Lscala/util/hashing/MurmurHash3$;
       3: aload_0
       4: invokeinterface #69,  1           // InterfaceMethod scala/collection/GenSetLike.seq:()Lscala/collection/Set;
       9: invokevirtual #73                 // Method scala/util/hashing/MurmurHash3$.setHash:(Lscala/collection/Set;)I
      12: ireturn

  private static final boolean liftedTree1$1(scala.collection.GenSetLike, scala.collection.GenSet);
    Code:
       0: aload_0
       1: aload_1
       2: invokeinterface #78,  2           // InterfaceMethod scala/collection/GenSetLike.subsetOf:(Lscala/collection/GenSet;)Z
       7: goto          12
      10: pop
      11: iconst_0
      12: ireturn
    Exception table:
       from    to  target type
           0    10    10   Class java/lang/ClassCastException

  public static void $init$(scala.collection.GenSetLike);
    Code:
       0: return
}
