Compiled from "SeqViewLike.scala"
public abstract class scala.collection.SeqViewLike$EmptyView$class {
  public static final int length(scala.collection.SeqViewLike$EmptyView);
    Code:
       0: iconst_0
       1: ireturn

  public static final scala.runtime.Nothing$ apply(scala.collection.SeqViewLike$EmptyView, int);
    Code:
       0: getstatic     #17                 // Field scala/collection/immutable/Nil$.MODULE$:Lscala/collection/immutable/Nil$;
       3: iload_1
       4: invokevirtual #20                 // Method scala/collection/immutable/Nil$.apply:(I)Ljava/lang/Object;
       7: checkcast     #22                 // class scala/runtime/Nothing$
      10: areturn

  public static void $init$(scala.collection.SeqViewLike$EmptyView);
    Code:
       0: return
}
