Compiled from "TraversableOnce.scala"
public final class scala.collection.TraversableOnce$$anon$2 extends scala.runtime.AbstractFunction1<A, java.lang.Object> {
  public scala.collection.TraversableOnce$$anon$2 apply(A);
    Code:
       0: aload_0
       1: areturn

  public java.lang.Object apply(java.lang.Object);
    Code:
       0: aload_0
       1: aload_1
       2: invokevirtual #20                 // Method apply:(Ljava/lang/Object;)Lscala/collection/TraversableOnce$$anon$2;
       5: areturn

  public scala.collection.TraversableOnce$$anon$2(scala.collection.TraversableOnce<A>);
    Code:
       0: aload_0
       1: invokespecial #26                 // Method scala/runtime/AbstractFunction1."<init>":()V
       4: return
}
