Compiled from "TraversableOnce.scala"
public abstract class scala.collection.TraversableOnce$class {
  public static scala.collection.immutable.List reversed(scala.collection.TraversableOnce);
    Code:
       0: getstatic     #13                 // Field scala/collection/immutable/Nil$.MODULE$:Lscala/collection/immutable/Nil$;
       3: invokestatic  #19                 // Method scala/runtime/ObjectRef.create:(Ljava/lang/Object;)Lscala/runtime/ObjectRef;
       6: astore_1
       7: aload_0
       8: new           #21                 // class scala/collection/TraversableOnce$$anonfun$reversed$1
      11: dup
      12: aload_0
      13: aload_1
      14: invokespecial #25                 // Method scala/collection/TraversableOnce$$anonfun$reversed$1."<init>":(Lscala/collection/TraversableOnce;Lscala/runtime/ObjectRef;)V
      17: invokeinterface #31,  2           // InterfaceMethod scala/collection/TraversableOnce.foreach:(Lscala/Function1;)V
      22: aload_1
      23: getfield      #35                 // Field scala/runtime/ObjectRef.elem:Ljava/lang/Object;
      26: checkcast     #37                 // class scala/collection/immutable/List
      29: areturn

  public static int size(scala.collection.TraversableOnce);
    Code:
       0: iconst_0
       1: invokestatic  #48                 // Method scala/runtime/IntRef.create:(I)Lscala/runtime/IntRef;
       4: astore_1
       5: aload_0
       6: new           #50                 // class scala/collection/TraversableOnce$$anonfun$size$1
       9: dup
      10: aload_0
      11: aload_1
      12: invokespecial #53                 // Method scala/collection/TraversableOnce$$anonfun$size$1."<init>":(Lscala/collection/TraversableOnce;Lscala/runtime/IntRef;)V
      15: invokeinterface #31,  2           // InterfaceMethod scala/collection/TraversableOnce.foreach:(Lscala/Function1;)V
      20: aload_1
      21: getfield      #56                 // Field scala/runtime/IntRef.elem:I
      24: ireturn

  public static boolean nonEmpty(scala.collection.TraversableOnce);
    Code:
       0: aload_0
       1: invokeinterface #64,  1           // InterfaceMethod scala/collection/TraversableOnce.isEmpty:()Z
       6: ifeq          13
       9: iconst_0
      10: goto          14
      13: iconst_1
      14: ireturn

  public static int count(scala.collection.TraversableOnce, scala.Function1);
    Code:
       0: iconst_0
       1: invokestatic  #48                 // Method scala/runtime/IntRef.create:(I)Lscala/runtime/IntRef;
       4: astore_2
       5: aload_0
       6: new           #68                 // class scala/collection/TraversableOnce$$anonfun$count$1
       9: dup
      10: aload_0
      11: aload_2
      12: aload_1
      13: invokespecial #71                 // Method scala/collection/TraversableOnce$$anonfun$count$1."<init>":(Lscala/collection/TraversableOnce;Lscala/runtime/IntRef;Lscala/Function1;)V
      16: invokeinterface #31,  2           // InterfaceMethod scala/collection/TraversableOnce.foreach:(Lscala/Function1;)V
      21: aload_2
      22: getfield      #56                 // Field scala/runtime/IntRef.elem:I
      25: ireturn

  public static scala.Option collectFirst(scala.collection.TraversableOnce, scala.PartialFunction);
    Code:
       0: new           #4                  // class java/lang/Object
       3: dup
       4: invokespecial #81                 // Method java/lang/Object."<init>":()V
       7: astore        6
       9: aload_0
      10: instanceof    #83                 // class scala/collection/Iterator
      13: ifeq          26
      16: aload_0
      17: checkcast     #83                 // class scala/collection/Iterator
      20: astore_2
      21: aload_2
      22: astore_3
      23: goto          40
      26: aload_0
      27: instanceof    #85                 // class scala/collection/GenIterable
      30: ifeq          98
      33: aload_0
      34: invokeinterface #89,  1           // InterfaceMethod scala/collection/TraversableOnce.toIterator:()Lscala/collection/Iterator;
      39: astore_3
      40: new           #91                 // class scala/collection/TraversableOnce$$anon$2
      43: dup
      44: aload_0
      45: invokespecial #94                 // Method scala/collection/TraversableOnce$$anon$2."<init>":(Lscala/collection/TraversableOnce;)V
      48: astore        4
      50: aload_3
      51: invokeinterface #97,  1           // InterfaceMethod scala/collection/Iterator.hasNext:()Z
      56: ifeq          92
      59: aload_1
      60: aload_3
      61: invokeinterface #101,  1          // InterfaceMethod scala/collection/Iterator.next:()Ljava/lang/Object;
      66: aload         4
      68: invokeinterface #107,  3          // InterfaceMethod scala/PartialFunction.applyOrElse:(Ljava/lang/Object;Lscala/Function1;)Ljava/lang/Object;
      73: astore        5
      75: aload         5
      77: aload         4
      79: if_acmpeq     50
      82: new           #109                // class scala/Some
      85: dup
      86: aload         5
      88: invokespecial #112                // Method scala/Some."<init>":(Ljava/lang/Object;)V
      91: areturn
      92: getstatic     #117                // Field scala/None$.MODULE$:Lscala/None$;
      95: goto          143
      98: aload_0
      99: aload_1
     100: new           #119                // class scala/collection/TraversableOnce$$anonfun$1
     103: dup
     104: aload_0
     105: aload         6
     107: invokespecial #122                // Method scala/collection/TraversableOnce$$anonfun$1."<init>":(Lscala/collection/TraversableOnce;Ljava/lang/Object;)V
     110: invokeinterface #126,  2          // InterfaceMethod scala/PartialFunction.runWith:(Lscala/Function1;)Lscala/Function1;
     115: invokeinterface #31,  2           // InterfaceMethod scala/collection/TraversableOnce.foreach:(Lscala/Function1;)V
     120: getstatic     #117                // Field scala/None$.MODULE$:Lscala/None$;
     123: areturn
     124: dup
     125: astore        7
     127: invokevirtual #129                // Method scala/runtime/NonLocalReturnControl.key:()Ljava/lang/Object;
     130: aload         6
     132: if_acmpne     144
     135: aload         7
     137: invokevirtual #132                // Method scala/runtime/NonLocalReturnControl.value:()Ljava/lang/Object;
     140: checkcast     #134                // class scala/Option
     143: areturn
     144: aload         7
     146: athrow
    Exception table:
       from    to  target type
           9   124   124   Class scala/runtime/NonLocalReturnControl

  public static java.lang.Object $div$colon(scala.collection.TraversableOnce, java.lang.Object, scala.Function2);
    Code:
       0: aload_0
       1: aload_1
       2: aload_2
       3: invokeinterface #144,  3          // InterfaceMethod scala/collection/TraversableOnce.foldLeft:(Ljava/lang/Object;Lscala/Function2;)Ljava/lang/Object;
       8: areturn

  public static java.lang.Object $colon$bslash(scala.collection.TraversableOnce, java.lang.Object, scala.Function2);
    Code:
       0: aload_0
       1: aload_1
       2: aload_2
       3: invokeinterface #151,  3          // InterfaceMethod scala/collection/TraversableOnce.foldRight:(Ljava/lang/Object;Lscala/Function2;)Ljava/lang/Object;
       8: areturn

  public static java.lang.Object foldLeft(scala.collection.TraversableOnce, java.lang.Object, scala.Function2);
    Code:
       0: aload_1
       1: invokestatic  #19                 // Method scala/runtime/ObjectRef.create:(Ljava/lang/Object;)Lscala/runtime/ObjectRef;
       4: astore_3
       5: aload_0
       6: new           #153                // class scala/collection/TraversableOnce$$anonfun$foldLeft$1
       9: dup
      10: aload_0
      11: aload_3
      12: aload_2
      13: invokespecial #156                // Method scala/collection/TraversableOnce$$anonfun$foldLeft$1."<init>":(Lscala/collection/TraversableOnce;Lscala/runtime/ObjectRef;Lscala/Function2;)V
      16: invokeinterface #31,  2           // InterfaceMethod scala/collection/TraversableOnce.foreach:(Lscala/Function1;)V
      21: aload_3
      22: getfield      #35                 // Field scala/runtime/ObjectRef.elem:Ljava/lang/Object;
      25: areturn

  public static java.lang.Object foldRight(scala.collection.TraversableOnce, java.lang.Object, scala.Function2);
    Code:
       0: aload_0
       1: invokeinterface #159,  1          // InterfaceMethod scala/collection/TraversableOnce.reversed:()Lscala/collection/immutable/List;
       6: aload_1
       7: new           #161                // class scala/collection/TraversableOnce$$anonfun$foldRight$1
      10: dup
      11: aload_0
      12: aload_2
      13: invokespecial #164                // Method scala/collection/TraversableOnce$$anonfun$foldRight$1."<init>":(Lscala/collection/TraversableOnce;Lscala/Function2;)V
      16: invokevirtual #165                // Method scala/collection/immutable/List.foldLeft:(Ljava/lang/Object;Lscala/Function2;)Ljava/lang/Object;
      19: areturn

  public static java.lang.Object reduceLeft(scala.collection.TraversableOnce, scala.Function2);
    Code:
       0: aload_0
       1: invokeinterface #64,  1           // InterfaceMethod scala/collection/TraversableOnce.isEmpty:()Z
       6: ifeq          19
       9: new           #169                // class java/lang/UnsupportedOperationException
      12: dup
      13: ldc           #171                // String empty.reduceLeft
      15: invokespecial #174                // Method java/lang/UnsupportedOperationException."<init>":(Ljava/lang/String;)V
      18: athrow
      19: iconst_1
      20: invokestatic  #179                // Method scala/runtime/BooleanRef.create:(Z)Lscala/runtime/BooleanRef;
      23: astore_2
      24: iconst_0
      25: invokestatic  #185                // Method scala/runtime/BoxesRunTime.boxToInteger:(I)Ljava/lang/Integer;
      28: invokestatic  #19                 // Method scala/runtime/ObjectRef.create:(Ljava/lang/Object;)Lscala/runtime/ObjectRef;
      31: astore_3
      32: aload_0
      33: new           #187                // class scala/collection/TraversableOnce$$anonfun$reduceLeft$1
      36: dup
      37: aload_0
      38: aload_2
      39: aload_3
      40: aload_1
      41: invokespecial #190                // Method scala/collection/TraversableOnce$$anonfun$reduceLeft$1."<init>":(Lscala/collection/TraversableOnce;Lscala/runtime/BooleanRef;Lscala/runtime/ObjectRef;Lscala/Function2;)V
      44: invokeinterface #31,  2           // InterfaceMethod scala/collection/TraversableOnce.foreach:(Lscala/Function1;)V
      49: aload_3
      50: getfield      #35                 // Field scala/runtime/ObjectRef.elem:Ljava/lang/Object;
      53: areturn

  public static java.lang.Object reduceRight(scala.collection.TraversableOnce, scala.Function2);
    Code:
       0: aload_0
       1: invokeinterface #64,  1           // InterfaceMethod scala/collection/TraversableOnce.isEmpty:()Z
       6: ifeq          19
       9: new           #169                // class java/lang/UnsupportedOperationException
      12: dup
      13: ldc           #196                // String empty.reduceRight
      15: invokespecial #174                // Method java/lang/UnsupportedOperationException."<init>":(Ljava/lang/String;)V
      18: athrow
      19: aload_0
      20: invokeinterface #159,  1          // InterfaceMethod scala/collection/TraversableOnce.reversed:()Lscala/collection/immutable/List;
      25: new           #198                // class scala/collection/TraversableOnce$$anonfun$reduceRight$1
      28: dup
      29: aload_0
      30: aload_1
      31: invokespecial #199                // Method scala/collection/TraversableOnce$$anonfun$reduceRight$1."<init>":(Lscala/collection/TraversableOnce;Lscala/Function2;)V
      34: invokevirtual #202                // Method scala/collection/immutable/List.reduceLeft:(Lscala/Function2;)Ljava/lang/Object;
      37: areturn

  public static scala.Option reduceLeftOption(scala.collection.TraversableOnce, scala.Function2);
    Code:
       0: aload_0
       1: invokeinterface #64,  1           // InterfaceMethod scala/collection/TraversableOnce.isEmpty:()Z
       6: ifeq          15
       9: getstatic     #117                // Field scala/None$.MODULE$:Lscala/None$;
      12: goto          29
      15: new           #109                // class scala/Some
      18: dup
      19: aload_0
      20: aload_1
      21: invokeinterface #205,  2          // InterfaceMethod scala/collection/TraversableOnce.reduceLeft:(Lscala/Function2;)Ljava/lang/Object;
      26: invokespecial #112                // Method scala/Some."<init>":(Ljava/lang/Object;)V
      29: areturn

  public static scala.Option reduceRightOption(scala.collection.TraversableOnce, scala.Function2);
    Code:
       0: aload_0
       1: invokeinterface #64,  1           // InterfaceMethod scala/collection/TraversableOnce.isEmpty:()Z
       6: ifeq          15
       9: getstatic     #117                // Field scala/None$.MODULE$:Lscala/None$;
      12: goto          29
      15: new           #109                // class scala/Some
      18: dup
      19: aload_0
      20: aload_1
      21: invokeinterface #208,  2          // InterfaceMethod scala/collection/TraversableOnce.reduceRight:(Lscala/Function2;)Ljava/lang/Object;
      26: invokespecial #112                // Method scala/Some."<init>":(Ljava/lang/Object;)V
      29: areturn

  public static java.lang.Object reduce(scala.collection.TraversableOnce, scala.Function2);
    Code:
       0: aload_0
       1: aload_1
       2: invokeinterface #205,  2          // InterfaceMethod scala/collection/TraversableOnce.reduceLeft:(Lscala/Function2;)Ljava/lang/Object;
       7: areturn

  public static scala.Option reduceOption(scala.collection.TraversableOnce, scala.Function2);
    Code:
       0: aload_0
       1: aload_1
       2: invokeinterface #213,  2          // InterfaceMethod scala/collection/TraversableOnce.reduceLeftOption:(Lscala/Function2;)Lscala/Option;
       7: areturn

  public static java.lang.Object fold(scala.collection.TraversableOnce, java.lang.Object, scala.Function2);
    Code:
       0: aload_0
       1: aload_1
       2: aload_2
       3: invokeinterface #144,  3          // InterfaceMethod scala/collection/TraversableOnce.foldLeft:(Ljava/lang/Object;Lscala/Function2;)Ljava/lang/Object;
       8: areturn

  public static java.lang.Object aggregate(scala.collection.TraversableOnce, scala.Function0, scala.Function2, scala.Function2);
    Code:
       0: aload_0
       1: aload_1
       2: invokeinterface #221,  1          // InterfaceMethod scala/Function0.apply:()Ljava/lang/Object;
       7: aload_2
       8: invokeinterface #144,  3          // InterfaceMethod scala/collection/TraversableOnce.foldLeft:(Ljava/lang/Object;Lscala/Function2;)Ljava/lang/Object;
      13: areturn

  public static java.lang.Object sum(scala.collection.TraversableOnce, scala.math.Numeric);
    Code:
       0: aload_0
       1: aload_1
       2: invokeinterface #231,  1          // InterfaceMethod scala/math/Numeric.zero:()Ljava/lang/Object;
       7: new           #233                // class scala/collection/TraversableOnce$$anonfun$sum$1
      10: dup
      11: aload_0
      12: aload_1
      13: invokespecial #236                // Method scala/collection/TraversableOnce$$anonfun$sum$1."<init>":(Lscala/collection/TraversableOnce;Lscala/math/Numeric;)V
      16: invokeinterface #144,  3          // InterfaceMethod scala/collection/TraversableOnce.foldLeft:(Ljava/lang/Object;Lscala/Function2;)Ljava/lang/Object;
      21: areturn

  public static java.lang.Object product(scala.collection.TraversableOnce, scala.math.Numeric);
    Code:
       0: aload_0
       1: aload_1
       2: invokeinterface #242,  1          // InterfaceMethod scala/math/Numeric.one:()Ljava/lang/Object;
       7: new           #244                // class scala/collection/TraversableOnce$$anonfun$product$1
      10: dup
      11: aload_0
      12: aload_1
      13: invokespecial #245                // Method scala/collection/TraversableOnce$$anonfun$product$1."<init>":(Lscala/collection/TraversableOnce;Lscala/math/Numeric;)V
      16: invokeinterface #144,  3          // InterfaceMethod scala/collection/TraversableOnce.foldLeft:(Ljava/lang/Object;Lscala/Function2;)Ljava/lang/Object;
      21: areturn

  public static java.lang.Object min(scala.collection.TraversableOnce, scala.math.Ordering);
    Code:
       0: aload_0
       1: invokeinterface #64,  1           // InterfaceMethod scala/collection/TraversableOnce.isEmpty:()Z
       6: ifeq          19
       9: new           #169                // class java/lang/UnsupportedOperationException
      12: dup
      13: ldc           #249                // String empty.min
      15: invokespecial #174                // Method java/lang/UnsupportedOperationException."<init>":(Ljava/lang/String;)V
      18: athrow
      19: aload_0
      20: new           #251                // class scala/collection/TraversableOnce$$anonfun$min$1
      23: dup
      24: aload_0
      25: aload_1
      26: invokespecial #254                // Method scala/collection/TraversableOnce$$anonfun$min$1."<init>":(Lscala/collection/TraversableOnce;Lscala/math/Ordering;)V
      29: invokeinterface #205,  2          // InterfaceMethod scala/collection/TraversableOnce.reduceLeft:(Lscala/Function2;)Ljava/lang/Object;
      34: areturn

  public static java.lang.Object max(scala.collection.TraversableOnce, scala.math.Ordering);
    Code:
       0: aload_0
       1: invokeinterface #64,  1           // InterfaceMethod scala/collection/TraversableOnce.isEmpty:()Z
       6: ifeq          20
       9: new           #169                // class java/lang/UnsupportedOperationException
      12: dup
      13: ldc_w         #259                // String empty.max
      16: invokespecial #174                // Method java/lang/UnsupportedOperationException."<init>":(Ljava/lang/String;)V
      19: athrow
      20: aload_0
      21: new           #261                // class scala/collection/TraversableOnce$$anonfun$max$1
      24: dup
      25: aload_0
      26: aload_1
      27: invokespecial #262                // Method scala/collection/TraversableOnce$$anonfun$max$1."<init>":(Lscala/collection/TraversableOnce;Lscala/math/Ordering;)V
      30: invokeinterface #205,  2          // InterfaceMethod scala/collection/TraversableOnce.reduceLeft:(Lscala/Function2;)Ljava/lang/Object;
      35: areturn

  public static java.lang.Object maxBy(scala.collection.TraversableOnce, scala.Function1, scala.math.Ordering);
    Code:
       0: aload_0
       1: invokeinterface #64,  1           // InterfaceMethod scala/collection/TraversableOnce.isEmpty:()Z
       6: ifeq          20
       9: new           #169                // class java/lang/UnsupportedOperationException
      12: dup
      13: ldc_w         #266                // String empty.maxBy
      16: invokespecial #174                // Method java/lang/UnsupportedOperationException."<init>":(Ljava/lang/String;)V
      19: athrow
      20: aconst_null
      21: invokestatic  #19                 // Method scala/runtime/ObjectRef.create:(Ljava/lang/Object;)Lscala/runtime/ObjectRef;
      24: astore_3
      25: aconst_null
      26: invokestatic  #19                 // Method scala/runtime/ObjectRef.create:(Ljava/lang/Object;)Lscala/runtime/ObjectRef;
      29: astore        4
      31: iconst_1
      32: invokestatic  #179                // Method scala/runtime/BooleanRef.create:(Z)Lscala/runtime/BooleanRef;
      35: astore        5
      37: aload_0
      38: new           #268                // class scala/collection/TraversableOnce$$anonfun$maxBy$1
      41: dup
      42: aload_0
      43: aload_3
      44: aload         4
      46: aload         5
      48: aload_1
      49: aload_2
      50: invokespecial #271                // Method scala/collection/TraversableOnce$$anonfun$maxBy$1."<init>":(Lscala/collection/TraversableOnce;Lscala/runtime/ObjectRef;Lscala/runtime/ObjectRef;Lscala/runtime/BooleanRef;Lscala/Function1;Lscala/math/Ordering;)V
      53: invokeinterface #31,  2           // InterfaceMethod scala/collection/TraversableOnce.foreach:(Lscala/Function1;)V
      58: aload         4
      60: getfield      #35                 // Field scala/runtime/ObjectRef.elem:Ljava/lang/Object;
      63: areturn

  public static java.lang.Object minBy(scala.collection.TraversableOnce, scala.Function1, scala.math.Ordering);
    Code:
       0: aload_0
       1: invokeinterface #64,  1           // InterfaceMethod scala/collection/TraversableOnce.isEmpty:()Z
       6: ifeq          20
       9: new           #169                // class java/lang/UnsupportedOperationException
      12: dup
      13: ldc_w         #277                // String empty.minBy
      16: invokespecial #174                // Method java/lang/UnsupportedOperationException."<init>":(Ljava/lang/String;)V
      19: athrow
      20: aconst_null
      21: invokestatic  #19                 // Method scala/runtime/ObjectRef.create:(Ljava/lang/Object;)Lscala/runtime/ObjectRef;
      24: astore_3
      25: aconst_null
      26: invokestatic  #19                 // Method scala/runtime/ObjectRef.create:(Ljava/lang/Object;)Lscala/runtime/ObjectRef;
      29: astore        4
      31: iconst_1
      32: invokestatic  #179                // Method scala/runtime/BooleanRef.create:(Z)Lscala/runtime/BooleanRef;
      35: astore        5
      37: aload_0
      38: new           #279                // class scala/collection/TraversableOnce$$anonfun$minBy$1
      41: dup
      42: aload_0
      43: aload_3
      44: aload         4
      46: aload         5
      48: aload_1
      49: aload_2
      50: invokespecial #280                // Method scala/collection/TraversableOnce$$anonfun$minBy$1."<init>":(Lscala/collection/TraversableOnce;Lscala/runtime/ObjectRef;Lscala/runtime/ObjectRef;Lscala/runtime/BooleanRef;Lscala/Function1;Lscala/math/Ordering;)V
      53: invokeinterface #31,  2           // InterfaceMethod scala/collection/TraversableOnce.foreach:(Lscala/Function1;)V
      58: aload         4
      60: getfield      #35                 // Field scala/runtime/ObjectRef.elem:Ljava/lang/Object;
      63: areturn

  public static void copyToBuffer(scala.collection.TraversableOnce, scala.collection.mutable.Buffer);
    Code:
       0: aload_1
       1: aload_0
       2: invokeinterface #288,  1          // InterfaceMethod scala/collection/TraversableOnce.seq:()Lscala/collection/TraversableOnce;
       7: invokeinterface #294,  2          // InterfaceMethod scala/collection/mutable/Buffer.$plus$plus$eq:(Lscala/collection/TraversableOnce;)Lscala/collection/generic/Growable;
      12: pop
      13: return

  public static void copyToArray(scala.collection.TraversableOnce, java.lang.Object, int);
    Code:
       0: aload_0
       1: aload_1
       2: iload_2
       3: getstatic     #303                // Field scala/runtime/ScalaRunTime$.MODULE$:Lscala/runtime/ScalaRunTime$;
       6: aload_1
       7: invokevirtual #307                // Method scala/runtime/ScalaRunTime$.array_length:(Ljava/lang/Object;)I
      10: iload_2
      11: isub
      12: invokeinterface #310,  4          // InterfaceMethod scala/collection/TraversableOnce.copyToArray:(Ljava/lang/Object;II)V
      17: return

  public static void copyToArray(scala.collection.TraversableOnce, java.lang.Object);
    Code:
       0: aload_0
       1: aload_1
       2: iconst_0
       3: getstatic     #303                // Field scala/runtime/ScalaRunTime$.MODULE$:Lscala/runtime/ScalaRunTime$;
       6: aload_1
       7: invokevirtual #307                // Method scala/runtime/ScalaRunTime$.array_length:(Ljava/lang/Object;)I
      10: invokeinterface #310,  4          // InterfaceMethod scala/collection/TraversableOnce.copyToArray:(Ljava/lang/Object;II)V
      15: return

  public static java.lang.Object toArray(scala.collection.TraversableOnce, scala.reflect.ClassTag);
    Code:
       0: aload_0
       1: invokeinterface #317,  1          // InterfaceMethod scala/collection/TraversableOnce.isTraversableAgain:()Z
       6: ifeq          34
       9: aload_1
      10: aload_0
      11: invokeinterface #320,  1          // InterfaceMethod scala/collection/TraversableOnce.size:()I
      16: invokeinterface #326,  2          // InterfaceMethod scala/reflect/ClassTag.newArray:(I)Ljava/lang/Object;
      21: astore_2
      22: aload_0
      23: aload_2
      24: iconst_0
      25: invokeinterface #329,  3          // InterfaceMethod scala/collection/TraversableOnce.copyToArray:(Ljava/lang/Object;I)V
      30: aload_2
      31: goto          46
      34: aload_0
      35: invokeinterface #333,  1          // InterfaceMethod scala/collection/TraversableOnce.toBuffer:()Lscala/collection/mutable/Buffer;
      40: aload_1
      41: invokeinterface #336,  2          // InterfaceMethod scala/collection/mutable/Buffer.toArray:(Lscala/reflect/ClassTag;)Ljava/lang/Object;
      46: areturn

  public static scala.collection.immutable.List toList(scala.collection.TraversableOnce);
    Code:
       0: aload_0
       1: getstatic     #344                // Field scala/collection/immutable/List$.MODULE$:Lscala/collection/immutable/List$;
       4: invokevirtual #348                // Method scala/collection/immutable/List$.canBuildFrom:()Lscala/collection/generic/CanBuildFrom;
       7: invokeinterface #352,  2          // InterfaceMethod scala/collection/TraversableOnce.to:(Lscala/collection/generic/CanBuildFrom;)Ljava/lang/Object;
      12: checkcast     #37                 // class scala/collection/immutable/List
      15: areturn

  public static scala.collection.Iterable toIterable(scala.collection.TraversableOnce);
    Code:
       0: aload_0
       1: invokeinterface #358,  1          // InterfaceMethod scala/collection/TraversableOnce.toStream:()Lscala/collection/immutable/Stream;
       6: areturn

  public static scala.collection.Seq toSeq(scala.collection.TraversableOnce);
    Code:
       0: aload_0
       1: invokeinterface #358,  1          // InterfaceMethod scala/collection/TraversableOnce.toStream:()Lscala/collection/immutable/Stream;
       6: areturn

  public static scala.collection.immutable.IndexedSeq toIndexedSeq(scala.collection.TraversableOnce);
    Code:
       0: aload_0
       1: getstatic     #367                // Field scala/Predef$.MODULE$:Lscala/Predef$;
       4: invokevirtual #370                // Method scala/Predef$.fallbackStringCanBuildFrom:()Lscala/collection/generic/CanBuildFrom;
       7: invokeinterface #352,  2          // InterfaceMethod scala/collection/TraversableOnce.to:(Lscala/collection/generic/CanBuildFrom;)Ljava/lang/Object;
      12: checkcast     #372                // class scala/collection/immutable/IndexedSeq
      15: areturn

  public static scala.collection.mutable.Buffer toBuffer(scala.collection.TraversableOnce);
    Code:
       0: aload_0
       1: getstatic     #378                // Field scala/collection/mutable/ArrayBuffer$.MODULE$:Lscala/collection/mutable/ArrayBuffer$;
       4: invokevirtual #379                // Method scala/collection/mutable/ArrayBuffer$.canBuildFrom:()Lscala/collection/generic/CanBuildFrom;
       7: invokeinterface #352,  2          // InterfaceMethod scala/collection/TraversableOnce.to:(Lscala/collection/generic/CanBuildFrom;)Ljava/lang/Object;
      12: checkcast     #290                // class scala/collection/mutable/Buffer
      15: areturn

  public static scala.collection.immutable.Set toSet(scala.collection.TraversableOnce);
    Code:
       0: aload_0
       1: getstatic     #386                // Field scala/collection/immutable/Set$.MODULE$:Lscala/collection/immutable/Set$;
       4: invokevirtual #387                // Method scala/collection/immutable/Set$.canBuildFrom:()Lscala/collection/generic/CanBuildFrom;
       7: invokeinterface #352,  2          // InterfaceMethod scala/collection/TraversableOnce.to:(Lscala/collection/generic/CanBuildFrom;)Ljava/lang/Object;
      12: checkcast     #389                // class scala/collection/immutable/Set
      15: areturn

  public static scala.collection.immutable.Vector toVector(scala.collection.TraversableOnce);
    Code:
       0: aload_0
       1: getstatic     #396                // Field scala/collection/immutable/Vector$.MODULE$:Lscala/collection/immutable/Vector$;
       4: invokevirtual #397                // Method scala/collection/immutable/Vector$.canBuildFrom:()Lscala/collection/generic/CanBuildFrom;
       7: invokeinterface #352,  2          // InterfaceMethod scala/collection/TraversableOnce.to:(Lscala/collection/generic/CanBuildFrom;)Ljava/lang/Object;
      12: checkcast     #399                // class scala/collection/immutable/Vector
      15: areturn

  public static java.lang.Object to(scala.collection.TraversableOnce, scala.collection.generic.CanBuildFrom);
    Code:
       0: aload_1
       1: invokeinterface #405,  1          // InterfaceMethod scala/collection/generic/CanBuildFrom.apply:()Lscala/collection/mutable/Builder;
       6: astore_2
       7: aload_2
       8: aload_0
       9: invokeinterface #288,  1          // InterfaceMethod scala/collection/TraversableOnce.seq:()Lscala/collection/TraversableOnce;
      14: invokeinterface #408,  2          // InterfaceMethod scala/collection/mutable/Builder.$plus$plus$eq:(Lscala/collection/TraversableOnce;)Lscala/collection/generic/Growable;
      19: pop
      20: aload_2
      21: invokeinterface #410,  1          // InterfaceMethod scala/collection/mutable/Builder.result:()Ljava/lang/Object;
      26: areturn

  public static scala.collection.immutable.Map toMap(scala.collection.TraversableOnce, scala.Predef$$less$colon$less);
    Code:
       0: getstatic     #421                // Field scala/collection/immutable/Map$.MODULE$:Lscala/collection/immutable/Map$;
       3: invokevirtual #424                // Method scala/collection/immutable/Map$.newBuilder:()Lscala/collection/mutable/Builder;
       6: astore_2
       7: aload_0
       8: new           #426                // class scala/collection/TraversableOnce$$anonfun$toMap$1
      11: dup
      12: aload_0
      13: aload_2
      14: aload_1
      15: invokespecial #429                // Method scala/collection/TraversableOnce$$anonfun$toMap$1."<init>":(Lscala/collection/TraversableOnce;Lscala/collection/mutable/Builder;Lscala/Predef$$less$colon$less;)V
      18: invokeinterface #31,  2           // InterfaceMethod scala/collection/TraversableOnce.foreach:(Lscala/Function1;)V
      23: aload_2
      24: invokeinterface #410,  1          // InterfaceMethod scala/collection/mutable/Builder.result:()Ljava/lang/Object;
      29: checkcast     #431                // class scala/collection/immutable/Map
      32: areturn

  public static java.lang.String mkString(scala.collection.TraversableOnce, java.lang.String, java.lang.String, java.lang.String);
    Code:
       0: aload_0
       1: new           #437                // class scala/collection/mutable/StringBuilder
       4: dup
       5: invokespecial #438                // Method scala/collection/mutable/StringBuilder."<init>":()V
       8: aload_1
       9: aload_2
      10: aload_3
      11: invokeinterface #442,  5          // InterfaceMethod scala/collection/TraversableOnce.addString:(Lscala/collection/mutable/StringBuilder;Ljava/lang/String;Ljava/lang/String;Ljava/lang/String;)Lscala/collection/mutable/StringBuilder;
      16: invokevirtual #446                // Method scala/collection/mutable/StringBuilder.toString:()Ljava/lang/String;
      19: areturn

  public static java.lang.String mkString(scala.collection.TraversableOnce, java.lang.String);
    Code:
       0: aload_0
       1: ldc_w         #452                // String
       4: aload_1
       5: ldc_w         #452                // String
       8: invokeinterface #455,  4          // InterfaceMethod scala/collection/TraversableOnce.mkString:(Ljava/lang/String;Ljava/lang/String;Ljava/lang/String;)Ljava/lang/String;
      13: areturn

  public static java.lang.String mkString(scala.collection.TraversableOnce);
    Code:
       0: aload_0
       1: ldc_w         #452                // String
       4: invokeinterface #459,  2          // InterfaceMethod scala/collection/TraversableOnce.mkString:(Ljava/lang/String;)Ljava/lang/String;
       9: areturn

  public static scala.collection.mutable.StringBuilder addString(scala.collection.TraversableOnce, scala.collection.mutable.StringBuilder, java.lang.String, java.lang.String, java.lang.String);
    Code:
       0: iconst_1
       1: invokestatic  #179                // Method scala/runtime/BooleanRef.create:(Z)Lscala/runtime/BooleanRef;
       4: astore        5
       6: aload_1
       7: aload_2
       8: invokevirtual #464                // Method scala/collection/mutable/StringBuilder.append:(Ljava/lang/String;)Lscala/collection/mutable/StringBuilder;
      11: pop
      12: aload_0
      13: new           #466                // class scala/collection/TraversableOnce$$anonfun$addString$1
      16: dup
      17: aload_0
      18: aload         5
      20: aload_1
      21: aload_3
      22: invokespecial #469                // Method scala/collection/TraversableOnce$$anonfun$addString$1."<init>":(Lscala/collection/TraversableOnce;Lscala/runtime/BooleanRef;Lscala/collection/mutable/StringBuilder;Ljava/lang/String;)V
      25: invokeinterface #31,  2           // InterfaceMethod scala/collection/TraversableOnce.foreach:(Lscala/Function1;)V
      30: aload_1
      31: aload         4
      33: invokevirtual #464                // Method scala/collection/mutable/StringBuilder.append:(Ljava/lang/String;)Lscala/collection/mutable/StringBuilder;
      36: pop
      37: aload_1
      38: areturn

  public static scala.collection.mutable.StringBuilder addString(scala.collection.TraversableOnce, scala.collection.mutable.StringBuilder, java.lang.String);
    Code:
       0: aload_0
       1: aload_1
       2: ldc_w         #452                // String
       5: aload_2
       6: ldc_w         #452                // String
       9: invokeinterface #442,  5          // InterfaceMethod scala/collection/TraversableOnce.addString:(Lscala/collection/mutable/StringBuilder;Ljava/lang/String;Ljava/lang/String;Ljava/lang/String;)Lscala/collection/mutable/StringBuilder;
      14: areturn

  public static scala.collection.mutable.StringBuilder addString(scala.collection.TraversableOnce, scala.collection.mutable.StringBuilder);
    Code:
       0: aload_0
       1: aload_1
       2: ldc_w         #452                // String
       5: invokeinterface #475,  3          // InterfaceMethod scala/collection/TraversableOnce.addString:(Lscala/collection/mutable/StringBuilder;Ljava/lang/String;)Lscala/collection/mutable/StringBuilder;
      10: areturn

  public static void $init$(scala.collection.TraversableOnce);
    Code:
       0: return
}
