Compiled from "ErrorMvcAutoConfiguration.java"
public class org.springframework.boot.autoconfigure.web.ErrorMvcAutoConfiguration {
  private final org.springframework.context.ApplicationContext applicationContext;

  private final org.springframework.boot.autoconfigure.web.ServerProperties serverProperties;

  private final org.springframework.boot.autoconfigure.web.ResourceProperties resourceProperties;

  private java.util.List<org.springframework.boot.autoconfigure.web.ErrorViewResolver> errorViewResolvers;

  public org.springframework.boot.autoconfigure.web.ErrorMvcAutoConfiguration(org.springframework.context.ApplicationContext, org.springframework.boot.autoconfigure.web.ServerProperties, org.springframework.boot.autoconfigure.web.ResourceProperties);
    Code:
       0: aload_0
       1: invokespecial #1                  // Method java/lang/Object."<init>":()V
       4: aload_0
       5: aload_1
       6: putfield      #2                  // Field applicationContext:Lorg/springframework/context/ApplicationContext;
       9: aload_0
      10: aload_2
      11: putfield      #3                  // Field serverProperties:Lorg/springframework/boot/autoconfigure/web/ServerProperties;
      14: aload_0
      15: aload_3
      16: putfield      #4                  // Field resourceProperties:Lorg/springframework/boot/autoconfigure/web/ResourceProperties;
      19: return

  public org.springframework.boot.autoconfigure.web.DefaultErrorAttributes errorAttributes();
    Code:
       0: new           #5                  // class org/springframework/boot/autoconfigure/web/DefaultErrorAttributes
       3: dup
       4: invokespecial #6                  // Method org/springframework/boot/autoconfigure/web/DefaultErrorAttributes."<init>":()V
       7: areturn

  public org.springframework.boot.autoconfigure.web.BasicErrorController basicErrorController(org.springframework.boot.autoconfigure.web.ErrorAttributes);
    Code:
       0: new           #7                  // class org/springframework/boot/autoconfigure/web/BasicErrorController
       3: dup
       4: aload_1
       5: aload_0
       6: getfield      #3                  // Field serverProperties:Lorg/springframework/boot/autoconfigure/web/ServerProperties;
       9: invokevirtual #8                  // Method org/springframework/boot/autoconfigure/web/ServerProperties.getError:()Lorg/springframework/boot/autoconfigure/web/ErrorProperties;
      12: aload_0
      13: getfield      #9                  // Field errorViewResolvers:Ljava/util/List;
      16: invokespecial #10                 // Method org/springframework/boot/autoconfigure/web/BasicErrorController."<init>":(Lorg/springframework/boot/autoconfigure/web/ErrorAttributes;Lorg/springframework/boot/autoconfigure/web/ErrorProperties;Ljava/util/List;)V
      19: areturn

  public org.springframework.boot.autoconfigure.web.ErrorMvcAutoConfiguration$ErrorPageCustomizer errorPageCustomizer();
    Code:
       0: new           #11                 // class org/springframework/boot/autoconfigure/web/ErrorMvcAutoConfiguration$ErrorPageCustomizer
       3: dup
       4: aload_0
       5: getfield      #3                  // Field serverProperties:Lorg/springframework/boot/autoconfigure/web/ServerProperties;
       8: invokespecial #12                 // Method org/springframework/boot/autoconfigure/web/ErrorMvcAutoConfiguration$ErrorPageCustomizer."<init>":(Lorg/springframework/boot/autoconfigure/web/ServerProperties;)V
      11: areturn

  public org.springframework.boot.autoconfigure.web.DefaultErrorViewResolver conventionErrorViewResolver();
    Code:
       0: new           #13                 // class org/springframework/boot/autoconfigure/web/DefaultErrorViewResolver
       3: dup
       4: aload_0
       5: getfield      #2                  // Field applicationContext:Lorg/springframework/context/ApplicationContext;
       8: aload_0
       9: getfield      #4                  // Field resourceProperties:Lorg/springframework/boot/autoconfigure/web/ResourceProperties;
      12: invokespecial #14                 // Method org/springframework/boot/autoconfigure/web/DefaultErrorViewResolver."<init>":(Lorg/springframework/context/ApplicationContext;Lorg/springframework/boot/autoconfigure/web/ResourceProperties;)V
      15: areturn

  public static org.springframework.boot.autoconfigure.web.ErrorMvcAutoConfiguration$PreserveErrorControllerTargetClassPostProcessor preserveErrorControllerTargetClassPostProcessor();
    Code:
       0: new           #15                 // class org/springframework/boot/autoconfigure/web/ErrorMvcAutoConfiguration$PreserveErrorControllerTargetClassPostProcessor
       3: dup
       4: invokespecial #16                 // Method org/springframework/boot/autoconfigure/web/ErrorMvcAutoConfiguration$PreserveErrorControllerTargetClassPostProcessor."<init>":()V
       7: areturn
}
