Compiled from "JacksonHttpMessageConvertersConfiguration.java"
public class org.springframework.boot.autoconfigure.web.JacksonHttpMessageConvertersConfiguration$MappingJackson2HttpMessageConverterConfiguration {
  protected org.springframework.boot.autoconfigure.web.JacksonHttpMessageConvertersConfiguration$MappingJackson2HttpMessageConverterConfiguration();
    Code:
       0: aload_0
       1: invokespecial #1                  // Method java/lang/Object."<init>":()V
       4: return

  public org.springframework.http.converter.json.MappingJackson2HttpMessageConverter mappingJackson2HttpMessageConverter(com.fasterxml.jackson.databind.ObjectMapper);
    Code:
       0: new           #2                  // class org/springframework/http/converter/json/MappingJackson2HttpMessageConverter
       3: dup
       4: aload_1
       5: invokespecial #3                  // Method org/springframework/http/converter/json/MappingJackson2HttpMessageConverter."<init>":(Lcom/fasterxml/jackson/databind/ObjectMapper;)V
       8: areturn
}
