Compiled from "ServerProperties.java"
public class org.springframework.boot.autoconfigure.web.ServerProperties$Undertow$Accesslog {
  private java.lang.Boolean enabled;

  private java.lang.String pattern;

  protected java.lang.String prefix;

  private java.lang.String suffix;

  private java.io.File dir;

  public org.springframework.boot.autoconfigure.web.ServerProperties$Undertow$Accesslog();
    Code:
       0: aload_0
       1: invokespecial #5                  // Method java/lang/Object."<init>":()V
       4: aload_0
       5: ldc           #6                  // String common
       7: putfield      #3                  // Field pattern:Ljava/lang/String;
      10: aload_0
      11: ldc           #7                  // String access_log.
      13: putfield      #8                  // Field prefix:Ljava/lang/String;
      16: aload_0
      17: ldc           #9                  // String log
      19: putfield      #2                  // Field suffix:Ljava/lang/String;
      22: aload_0
      23: new           #10                 // class java/io/File
      26: dup
      27: ldc           #11                 // String logs
      29: invokespecial #12                 // Method java/io/File."<init>":(Ljava/lang/String;)V
      32: putfield      #4                  // Field dir:Ljava/io/File;
      35: return

  public java.lang.Boolean getEnabled();
    Code:
       0: aload_0
       1: getfield      #1                  // Field enabled:Ljava/lang/Boolean;
       4: areturn

  public void setEnabled(java.lang.Boolean);
    Code:
       0: aload_0
       1: aload_1
       2: putfield      #1                  // Field enabled:Ljava/lang/Boolean;
       5: return

  public java.lang.String getPattern();
    Code:
       0: aload_0
       1: getfield      #3                  // Field pattern:Ljava/lang/String;
       4: areturn

  public void setPattern(java.lang.String);
    Code:
       0: aload_0
       1: aload_1
       2: putfield      #3                  // Field pattern:Ljava/lang/String;
       5: return

  public java.lang.String getPrefix();
    Code:
       0: aload_0
       1: getfield      #8                  // Field prefix:Ljava/lang/String;
       4: areturn

  public void setPrefix(java.lang.String);
    Code:
       0: aload_0
       1: aload_1
       2: putfield      #8                  // Field prefix:Ljava/lang/String;
       5: return

  public java.lang.String getSuffix();
    Code:
       0: aload_0
       1: getfield      #2                  // Field suffix:Ljava/lang/String;
       4: areturn

  public void setSuffix(java.lang.String);
    Code:
       0: aload_0
       1: aload_1
       2: putfield      #2                  // Field suffix:Ljava/lang/String;
       5: return

  public java.io.File getDir();
    Code:
       0: aload_0
       1: getfield      #4                  // Field dir:Ljava/io/File;
       4: areturn

  public void setDir(java.io.File);
    Code:
       0: aload_0
       1: aload_1
       2: putfield      #4                  // Field dir:Ljava/io/File;
       5: return

  static java.io.File access$300(org.springframework.boot.autoconfigure.web.ServerProperties$Undertow$Accesslog);
    Code:
       0: aload_0
       1: getfield      #4                  // Field dir:Ljava/io/File;
       4: areturn

  static java.lang.String access$400(org.springframework.boot.autoconfigure.web.ServerProperties$Undertow$Accesslog);
    Code:
       0: aload_0
       1: getfield      #3                  // Field pattern:Ljava/lang/String;
       4: areturn

  static java.lang.String access$500(org.springframework.boot.autoconfigure.web.ServerProperties$Undertow$Accesslog);
    Code:
       0: aload_0
       1: getfield      #2                  // Field suffix:Ljava/lang/String;
       4: areturn

  static java.lang.Boolean access$600(org.springframework.boot.autoconfigure.web.ServerProperties$Undertow$Accesslog);
    Code:
       0: aload_0
       1: getfield      #1                  // Field enabled:Ljava/lang/Boolean;
       4: areturn
}
