Compiled from "GetRollupCapsResponse.java"
public class org.elasticsearch.client.rollup.GetRollupCapsResponse {
  private final java.util.Map<java.lang.String, org.elasticsearch.client.rollup.RollableIndexCaps> jobs;

  public org.elasticsearch.client.rollup.GetRollupCapsResponse(java.util.Map<java.lang.String, org.elasticsearch.client.rollup.RollableIndexCaps>);
    Code:
       0: aload_0
       1: invokespecial #1                  // Method java/lang/Object."<init>":()V
       4: aload_0
       5: aload_1
       6: invokestatic  #2                  // Method java/util/Objects.requireNonNull:(Ljava/lang/Object;)Ljava/lang/Object;
       9: checkcast     #3                  // class java/util/Map
      12: invokestatic  #4                  // Method java/util/Collections.unmodifiableMap:(Ljava/util/Map;)Ljava/util/Map;
      15: putfield      #5                  // Field jobs:Ljava/util/Map;
      18: return

  public java.util.Map<java.lang.String, org.elasticsearch.client.rollup.RollableIndexCaps> getJobs();
    Code:
       0: aload_0
       1: getfield      #5                  // Field jobs:Ljava/util/Map;
       4: areturn

  public static org.elasticsearch.client.rollup.GetRollupCapsResponse fromXContent(org.elasticsearch.common.xcontent.XContentParser) throws java.io.IOException;
    Code:
       0: new           #6                  // class java/util/HashMap
       3: dup
       4: invokespecial #7                  // Method java/util/HashMap."<init>":()V
       7: astore_1
       8: aload_0
       9: invokeinterface #8,  1            // InterfaceMethod org/elasticsearch/common/xcontent/XContentParser.nextToken:()Lorg/elasticsearch/common/xcontent/XContentParser$Token;
      14: astore_2
      15: aload_2
      16: getstatic     #9                  // Field org/elasticsearch/common/xcontent/XContentParser$Token.START_OBJECT:Lorg/elasticsearch/common/xcontent/XContentParser$Token;
      19: invokevirtual #10                 // Method org/elasticsearch/common/xcontent/XContentParser$Token.equals:(Ljava/lang/Object;)Z
      22: ifeq          91
      25: aload_0
      26: invokeinterface #8,  1            // InterfaceMethod org/elasticsearch/common/xcontent/XContentParser.nextToken:()Lorg/elasticsearch/common/xcontent/XContentParser$Token;
      31: dup
      32: astore_2
      33: getstatic     #11                 // Field org/elasticsearch/common/xcontent/XContentParser$Token.END_OBJECT:Lorg/elasticsearch/common/xcontent/XContentParser$Token;
      36: if_acmpeq     91
      39: aload_2
      40: getstatic     #12                 // Field org/elasticsearch/common/xcontent/XContentParser$Token.FIELD_NAME:Lorg/elasticsearch/common/xcontent/XContentParser$Token;
      43: invokevirtual #10                 // Method org/elasticsearch/common/xcontent/XContentParser$Token.equals:(Ljava/lang/Object;)Z
      46: ifeq          25
      49: aload_0
      50: invokeinterface #13,  1           // InterfaceMethod org/elasticsearch/common/xcontent/XContentParser.currentName:()Ljava/lang/String;
      55: astore_3
      56: getstatic     #14                 // Field org/elasticsearch/client/rollup/RollableIndexCaps.PARSER:Ljava/util/function/Function;
      59: aload_3
      60: invokeinterface #15,  2           // InterfaceMethod java/util/function/Function.apply:(Ljava/lang/Object;)Ljava/lang/Object;
      65: checkcast     #16                 // class org/elasticsearch/common/xcontent/ConstructingObjectParser
      68: aload_0
      69: aconst_null
      70: invokevirtual #17                 // Method org/elasticsearch/common/xcontent/ConstructingObjectParser.apply:(Lorg/elasticsearch/common/xcontent/XContentParser;Ljava/lang/Object;)Ljava/lang/Object;
      73: checkcast     #18                 // class org/elasticsearch/client/rollup/RollableIndexCaps
      76: astore        4
      78: aload_1
      79: aload_3
      80: aload         4
      82: invokeinterface #19,  3           // InterfaceMethod java/util/Map.put:(Ljava/lang/Object;Ljava/lang/Object;)Ljava/lang/Object;
      87: pop
      88: goto          25
      91: new           #20                 // class org/elasticsearch/client/rollup/GetRollupCapsResponse
      94: dup
      95: aload_1
      96: invokespecial #21                 // Method "<init>":(Ljava/util/Map;)V
      99: areturn

  public int hashCode();
    Code:
       0: iconst_1
       1: anewarray     #22                 // class java/lang/Object
       4: dup
       5: iconst_0
       6: aload_0
       7: getfield      #5                  // Field jobs:Ljava/util/Map;
      10: aastore
      11: invokestatic  #23                 // Method java/util/Objects.hash:([Ljava/lang/Object;)I
      14: ireturn

  public boolean equals(java.lang.Object);
    Code:
       0: aload_1
       1: ifnonnull     6
       4: iconst_0
       5: ireturn
       6: aload_0
       7: invokevirtual #24                 // Method java/lang/Object.getClass:()Ljava/lang/Class;
      10: aload_1
      11: invokevirtual #24                 // Method java/lang/Object.getClass:()Ljava/lang/Class;
      14: if_acmpeq     19
      17: iconst_0
      18: ireturn
      19: aload_1
      20: checkcast     #20                 // class org/elasticsearch/client/rollup/GetRollupCapsResponse
      23: astore_2
      24: aload_0
      25: getfield      #5                  // Field jobs:Ljava/util/Map;
      28: aload_2
      29: getfield      #5                  // Field jobs:Ljava/util/Map;
      32: invokestatic  #25                 // Method java/util/Objects.equals:(Ljava/lang/Object;Ljava/lang/Object;)Z
      35: ireturn
}
