Compiled from "PutRollupJobRequest.java"
public class org.elasticsearch.client.rollup.PutRollupJobRequest implements org.elasticsearch.client.Validatable,org.elasticsearch.common.xcontent.ToXContentObject {
  private final org.elasticsearch.client.rollup.job.config.RollupJobConfig config;

  public org.elasticsearch.client.rollup.PutRollupJobRequest(org.elasticsearch.client.rollup.job.config.RollupJobConfig);
    Code:
       0: aload_0
       1: invokespecial #1                  // Method java/lang/Object."<init>":()V
       4: aload_0
       5: aload_1
       6: ldc           #2                  // String rollup job configuration is required
       8: invokestatic  #3                  // Method java/util/Objects.requireNonNull:(Ljava/lang/Object;Ljava/lang/String;)Ljava/lang/Object;
      11: checkcast     #4                  // class org/elasticsearch/client/rollup/job/config/RollupJobConfig
      14: putfield      #5                  // Field config:Lorg/elasticsearch/client/rollup/job/config/RollupJobConfig;
      17: return

  public org.elasticsearch.client.rollup.job.config.RollupJobConfig getConfig();
    Code:
       0: aload_0
       1: getfield      #5                  // Field config:Lorg/elasticsearch/client/rollup/job/config/RollupJobConfig;
       4: areturn

  public org.elasticsearch.common.xcontent.XContentBuilder toXContent(org.elasticsearch.common.xcontent.XContentBuilder, org.elasticsearch.common.xcontent.ToXContent$Params) throws java.io.IOException;
    Code:
       0: aload_0
       1: getfield      #5                  // Field config:Lorg/elasticsearch/client/rollup/job/config/RollupJobConfig;
       4: aload_1
       5: aload_2
       6: invokevirtual #6                  // Method org/elasticsearch/client/rollup/job/config/RollupJobConfig.toXContent:(Lorg/elasticsearch/common/xcontent/XContentBuilder;Lorg/elasticsearch/common/xcontent/ToXContent$Params;)Lorg/elasticsearch/common/xcontent/XContentBuilder;
       9: areturn

  public java.util.Optional<org.elasticsearch.client.ValidationException> validate();
    Code:
       0: aload_0
       1: getfield      #5                  // Field config:Lorg/elasticsearch/client/rollup/job/config/RollupJobConfig;
       4: invokevirtual #7                  // Method org/elasticsearch/client/rollup/job/config/RollupJobConfig.validate:()Ljava/util/Optional;
       7: areturn

  public boolean equals(java.lang.Object);
    Code:
       0: aload_0
       1: aload_1
       2: if_acmpne     7
       5: iconst_1
       6: ireturn
       7: aload_1
       8: ifnull        22
      11: aload_0
      12: invokevirtual #8                  // Method java/lang/Object.getClass:()Ljava/lang/Class;
      15: aload_1
      16: invokevirtual #8                  // Method java/lang/Object.getClass:()Ljava/lang/Class;
      19: if_acmpeq     24
      22: iconst_0
      23: ireturn
      24: aload_1
      25: checkcast     #9                  // class org/elasticsearch/client/rollup/PutRollupJobRequest
      28: astore_2
      29: aload_0
      30: getfield      #5                  // Field config:Lorg/elasticsearch/client/rollup/job/config/RollupJobConfig;
      33: aload_2
      34: getfield      #5                  // Field config:Lorg/elasticsearch/client/rollup/job/config/RollupJobConfig;
      37: invokestatic  #10                 // Method java/util/Objects.equals:(Ljava/lang/Object;Ljava/lang/Object;)Z
      40: ireturn

  public int hashCode();
    Code:
       0: iconst_1
       1: anewarray     #11                 // class java/lang/Object
       4: dup
       5: iconst_0
       6: aload_0
       7: getfield      #5                  // Field config:Lorg/elasticsearch/client/rollup/job/config/RollupJobConfig;
      10: aastore
      11: invokestatic  #12                 // Method java/util/Objects.hash:([Ljava/lang/Object;)I
      14: ireturn
}
