Compiled from "Http2Reset.java"
public class org.wso2.transport.http.netty.message.Http2Reset extends org.wso2.transport.http.netty.message.Http2Frame {
  private io.netty.handler.codec.http2.Http2Error error;

  public org.wso2.transport.http.netty.message.Http2Reset(int, io.netty.handler.codec.http2.Http2Error);
    Code:
       0: aload_0
       1: invokespecial #1                  // Method org/wso2/transport/http/netty/message/Http2Frame."<init>":()V
       4: aload_0
       5: iload_1
       6: invokevirtual #2                  // Method setStreamId:(I)V
       9: aload_0
      10: aload_2
      11: putfield      #3                  // Field error:Lio/netty/handler/codec/http2/Http2Error;
      14: return

  public org.wso2.transport.http.netty.message.Http2Reset(int);
    Code:
       0: aload_0
       1: invokespecial #1                  // Method org/wso2/transport/http/netty/message/Http2Frame."<init>":()V
       4: aload_0
       5: iload_1
       6: invokevirtual #2                  // Method setStreamId:(I)V
       9: aload_0
      10: getstatic     #4                  // Field io/netty/handler/codec/http2/Http2Error.REFUSED_STREAM:Lio/netty/handler/codec/http2/Http2Error;
      13: putfield      #3                  // Field error:Lio/netty/handler/codec/http2/Http2Error;
      16: return

  public io.netty.handler.codec.http2.Http2Error getError();
    Code:
       0: aload_0
       1: getfield      #3                  // Field error:Lio/netty/handler/codec/http2/Http2Error;
       4: areturn
}
