Compiled from "ShouldBeRelativePath.java"
public class org.assertj.core.error.ShouldBeRelativePath extends org.assertj.core.error.BasicErrorMessageFactory {
  public static final java.lang.String SHOULD_BE_RELATIVE_PATH;

  public static org.assertj.core.error.ErrorMessageFactory shouldBeRelativePath(java.io.File);
    Code:
       0: new           #2                  // class org/assertj/core/error/ShouldBeRelativePath
       3: dup
       4: aload_0
       5: invokespecial #16                 // Method "<init>":(Ljava/io/File;)V
       8: areturn

  public static org.assertj.core.error.ErrorMessageFactory shouldBeRelativePath(java.nio.file.Path);
    Code:
       0: new           #2                  // class org/assertj/core/error/ShouldBeRelativePath
       3: dup
       4: aload_0
       5: invokespecial #22                 // Method "<init>":(Ljava/nio/file/Path;)V
       8: areturn

  private org.assertj.core.error.ShouldBeRelativePath(java.io.File);
    Code:
       0: aload_0
       1: ldc           #9                  // String %nExpecting:%n  <%s>%nto be a relative path.
       3: iconst_1
       4: anewarray     #25                 // class java/lang/Object
       7: dup
       8: iconst_0
       9: aload_1
      10: aastore
      11: invokespecial #28                 // Method org/assertj/core/error/BasicErrorMessageFactory."<init>":(Ljava/lang/String;[Ljava/lang/Object;)V
      14: return

  private org.assertj.core.error.ShouldBeRelativePath(java.nio.file.Path);
    Code:
       0: aload_0
       1: ldc           #9                  // String %nExpecting:%n  <%s>%nto be a relative path.
       3: iconst_1
       4: anewarray     #25                 // class java/lang/Object
       7: dup
       8: iconst_0
       9: aload_1
      10: aastore
      11: invokespecial #28                 // Method org/assertj/core/error/BasicErrorMessageFactory."<init>":(Ljava/lang/String;[Ljava/lang/Object;)V
      14: return
}
