Compiled from "DocumentDepthProperties.java"
public class org.apache.cxf.staxutils.DocumentDepthProperties {
  public static final java.lang.String TOTAL_ELEMENT_COUNT;

  public static final java.lang.String INNER_ELEMENT_COUNT;

  public static final java.lang.String INNER_ELEMENT_LEVEL;

  private int elementCountThreshold;

  private int innerElementLevelThreshold;

  private int innerElementCountThreshold;

  public org.apache.cxf.staxutils.DocumentDepthProperties();
    Code:
       0: aload_0
       1: invokespecial #1                  // Method java/lang/Object."<init>":()V
       4: aload_0
       5: iconst_m1
       6: putfield      #2                  // Field elementCountThreshold:I
       9: aload_0
      10: iconst_m1
      11: putfield      #3                  // Field innerElementLevelThreshold:I
      14: aload_0
      15: iconst_m1
      16: putfield      #4                  // Field innerElementCountThreshold:I
      19: return

  public org.apache.cxf.staxutils.DocumentDepthProperties(int, int, int);
    Code:
       0: aload_0
       1: invokespecial #1                  // Method java/lang/Object."<init>":()V
       4: aload_0
       5: iconst_m1
       6: putfield      #2                  // Field elementCountThreshold:I
       9: aload_0
      10: iconst_m1
      11: putfield      #3                  // Field innerElementLevelThreshold:I
      14: aload_0
      15: iconst_m1
      16: putfield      #4                  // Field innerElementCountThreshold:I
      19: aload_0
      20: iload_1
      21: putfield      #2                  // Field elementCountThreshold:I
      24: aload_0
      25: iload_2
      26: putfield      #3                  // Field innerElementLevelThreshold:I
      29: aload_0
      30: iload_3
      31: putfield      #4                  // Field innerElementCountThreshold:I
      34: return

  public boolean isEffective();
    Code:
       0: aload_0
       1: getfield      #2                  // Field elementCountThreshold:I
       4: iconst_m1
       5: if_icmpne     24
       8: aload_0
       9: getfield      #3                  // Field innerElementLevelThreshold:I
      12: iconst_m1
      13: if_icmpne     24
      16: aload_0
      17: getfield      #4                  // Field innerElementCountThreshold:I
      20: iconst_m1
      21: if_icmpeq     28
      24: iconst_1
      25: goto          29
      28: iconst_0
      29: ireturn

  public void setElementCountThreshold(int);
    Code:
       0: aload_0
       1: iload_1
       2: putfield      #2                  // Field elementCountThreshold:I
       5: return

  public int getElementCountThreshold();
    Code:
       0: aload_0
       1: getfield      #2                  // Field elementCountThreshold:I
       4: ireturn

  public void setInnerElementLevelThreshold(int);
    Code:
       0: aload_0
       1: iload_1
       2: putfield      #3                  // Field innerElementLevelThreshold:I
       5: return

  public int getInnerElementLevelThreshold();
    Code:
       0: aload_0
       1: getfield      #3                  // Field innerElementLevelThreshold:I
       4: ireturn

  public void setInnerElementCountThreshold(int);
    Code:
       0: aload_0
       1: iload_1
       2: putfield      #4                  // Field innerElementCountThreshold:I
       5: return

  public int getInnerElementCountThreshold();
    Code:
       0: aload_0
       1: getfield      #4                  // Field innerElementCountThreshold:I
       4: ireturn
}
