Compiled from "StreamWriterContentHandler.java"
public class org.apache.cxf.staxutils.StreamWriterContentHandler implements org.xml.sax.ContentHandler,org.xml.sax.ext.LexicalHandler {
  javax.xml.stream.XMLStreamWriter writer;

  java.util.Map<java.lang.String, java.lang.String> mapping;

  boolean inCDATA;

  public org.apache.cxf.staxutils.StreamWriterContentHandler(javax.xml.stream.XMLStreamWriter);
    Code:
       0: aload_0
       1: invokespecial #1                  // Method java/lang/Object."<init>":()V
       4: aload_0
       5: new           #2                  // class java/util/LinkedHashMap
       8: dup
       9: invokespecial #3                  // Method java/util/LinkedHashMap."<init>":()V
      12: putfield      #4                  // Field mapping:Ljava/util/Map;
      15: aload_0
      16: aload_1
      17: putfield      #5                  // Field writer:Ljavax/xml/stream/XMLStreamWriter;
      20: return

  public void endDocument() throws org.xml.sax.SAXException;
    Code:
       0: return

  public void startDocument() throws org.xml.sax.SAXException;
    Code:
       0: return

  public void characters(char[], int, int) throws org.xml.sax.SAXException;
    Code:
       0: aload_0
       1: getfield      #6                  // Field inCDATA:Z
       4: ifeq          29
       7: aload_0
       8: getfield      #5                  // Field writer:Ljavax/xml/stream/XMLStreamWriter;
      11: new           #7                  // class java/lang/String
      14: dup
      15: aload_1
      16: iload_2
      17: iload_3
      18: invokespecial #8                  // Method java/lang/String."<init>":([CII)V
      21: invokeinterface #9,  2            // InterfaceMethod javax/xml/stream/XMLStreamWriter.writeCData:(Ljava/lang/String;)V
      26: goto          41
      29: aload_0
      30: getfield      #5                  // Field writer:Ljavax/xml/stream/XMLStreamWriter;
      33: aload_1
      34: iload_2
      35: iload_3
      36: invokeinterface #10,  4           // InterfaceMethod javax/xml/stream/XMLStreamWriter.writeCharacters:([CII)V
      41: goto          56
      44: astore        4
      46: new           #12                 // class org/xml/sax/SAXException
      49: dup
      50: aload         4
      52: invokespecial #13                 // Method org/xml/sax/SAXException."<init>":(Ljava/lang/Exception;)V
      55: athrow
      56: return
    Exception table:
       from    to  target type
           0    41    44   Class javax/xml/stream/XMLStreamException

  public void ignorableWhitespace(char[], int, int) throws org.xml.sax.SAXException;
    Code:
       0: aload_0
       1: getfield      #5                  // Field writer:Ljavax/xml/stream/XMLStreamWriter;
       4: aload_1
       5: iload_2
       6: iload_3
       7: invokeinterface #10,  4           // InterfaceMethod javax/xml/stream/XMLStreamWriter.writeCharacters:([CII)V
      12: goto          27
      15: astore        4
      17: new           #12                 // class org/xml/sax/SAXException
      20: dup
      21: aload         4
      23: invokespecial #13                 // Method org/xml/sax/SAXException."<init>":(Ljava/lang/Exception;)V
      26: athrow
      27: return
    Exception table:
       from    to  target type
           0    12    15   Class javax/xml/stream/XMLStreamException

  public void endPrefixMapping(java.lang.String) throws org.xml.sax.SAXException;
    Code:
       0: return

  public void skippedEntity(java.lang.String) throws org.xml.sax.SAXException;
    Code:
       0: return

  public void setDocumentLocator(org.xml.sax.Locator);
    Code:
       0: return

  public void processingInstruction(java.lang.String, java.lang.String) throws org.xml.sax.SAXException;
    Code:
       0: return

  public void startPrefixMapping(java.lang.String, java.lang.String) throws org.xml.sax.SAXException;
    Code:
       0: aload_0
       1: getfield      #4                  // Field mapping:Ljava/util/Map;
       4: aload_1
       5: aload_2
       6: invokeinterface #14,  3           // InterfaceMethod java/util/Map.put:(Ljava/lang/Object;Ljava/lang/Object;)Ljava/lang/Object;
      11: pop
      12: aload_0
      13: getfield      #5                  // Field writer:Ljavax/xml/stream/XMLStreamWriter;
      16: aload_1
      17: aload_2
      18: invokeinterface #15,  3           // InterfaceMethod javax/xml/stream/XMLStreamWriter.setPrefix:(Ljava/lang/String;Ljava/lang/String;)V
      23: goto          36
      26: astore_3
      27: new           #12                 // class org/xml/sax/SAXException
      30: dup
      31: aload_3
      32: invokespecial #13                 // Method org/xml/sax/SAXException."<init>":(Ljava/lang/Exception;)V
      35: athrow
      36: return
    Exception table:
       from    to  target type
          12    23    26   Class javax/xml/stream/XMLStreamException

  public void endElement(java.lang.String, java.lang.String, java.lang.String) throws org.xml.sax.SAXException;
    Code:
       0: aload_0
       1: getfield      #5                  // Field writer:Ljavax/xml/stream/XMLStreamWriter;
       4: invokeinterface #16,  1           // InterfaceMethod javax/xml/stream/XMLStreamWriter.writeEndElement:()V
       9: goto          24
      12: astore        4
      14: new           #12                 // class org/xml/sax/SAXException
      17: dup
      18: aload         4
      20: invokespecial #13                 // Method org/xml/sax/SAXException."<init>":(Ljava/lang/Exception;)V
      23: athrow
      24: return
    Exception table:
       from    to  target type
           0     9    12   Class javax/xml/stream/XMLStreamException

  private java.lang.String getPrefix(java.lang.String, java.lang.String);
    Code:
       0: aload_1
       1: bipush        58
       3: invokevirtual #17                 // Method java/lang/String.indexOf:(I)I
       6: istore_3
       7: iload_3
       8: iconst_m1
       9: if_icmpeq     19
      12: aload_1
      13: iconst_0
      14: iload_3
      15: invokevirtual #18                 // Method java/lang/String.substring:(II)Ljava/lang/String;
      18: areturn
      19: aload_2
      20: ifnull        33
      23: aload_2
      24: invokevirtual #19                 // Method java/lang/String.length:()I
      27: ifle          33
      30: ldc           #20                 // String
      32: areturn
      33: aconst_null
      34: areturn

  public void startElement(java.lang.String, java.lang.String, java.lang.String, org.xml.sax.Attributes) throws org.xml.sax.SAXException;
    Code:
       0: aload_0
       1: aload_3
       2: aload_1
       3: invokespecial #21                 // Method getPrefix:(Ljava/lang/String;Ljava/lang/String;)Ljava/lang/String;
       6: astore        5
       8: aload         5
      10: ifnonnull     27
      13: aload_0
      14: getfield      #5                  // Field writer:Ljavax/xml/stream/XMLStreamWriter;
      17: aload_1
      18: aload_2
      19: invokeinterface #22,  3           // InterfaceMethod javax/xml/stream/XMLStreamWriter.writeStartElement:(Ljava/lang/String;Ljava/lang/String;)V
      24: goto          40
      27: aload_0
      28: getfield      #5                  // Field writer:Ljavax/xml/stream/XMLStreamWriter;
      31: aload         5
      33: aload_2
      34: aload_1
      35: invokeinterface #23,  4           // InterfaceMethod javax/xml/stream/XMLStreamWriter.writeStartElement:(Ljava/lang/String;Ljava/lang/String;Ljava/lang/String;)V
      40: aload_0
      41: getfield      #4                  // Field mapping:Ljava/util/Map;
      44: invokeinterface #24,  1           // InterfaceMethod java/util/Map.isEmpty:()Z
      49: ifne          216
      52: aload         4
      54: ifnull        216
      57: aload         4
      59: invokeinterface #25,  1           // InterfaceMethod org/xml/sax/Attributes.getLength:()I
      64: istore        6
      66: iconst_0
      67: istore        7
      69: iload         7
      71: iload         6
      73: if_icmpge     216
      76: aload         4
      78: iload         7
      80: invokeinterface #26,  2           // InterfaceMethod org/xml/sax/Attributes.getURI:(I)Ljava/lang/String;
      85: invokestatic  #27                 // Method org/apache/cxf/common/util/StringUtils.isEmpty:(Ljava/lang/String;)Z
      88: ifne          210
      91: aload         4
      93: iload         7
      95: invokeinterface #28,  2           // InterfaceMethod org/xml/sax/Attributes.getQName:(I)Ljava/lang/String;
     100: ldc           #29                 // String xmlns
     102: invokevirtual #30                 // Method java/lang/String.startsWith:(Ljava/lang/String;)Z
     105: ifeq          210
     108: aload         4
     110: iload         7
     112: invokeinterface #28,  2           // InterfaceMethod org/xml/sax/Attributes.getQName:(I)Ljava/lang/String;
     117: astore        8
     119: aload         8
     121: bipush        58
     123: invokevirtual #17                 // Method java/lang/String.indexOf:(I)I
     126: istore        9
     128: iload         9
     130: iconst_m1
     131: if_icmpne     167
     134: aload_0
     135: getfield      #4                  // Field mapping:Ljava/util/Map;
     138: ldc           #20                 // String
     140: invokeinterface #31,  2           // InterfaceMethod java/util/Map.remove:(Ljava/lang/Object;)Ljava/lang/Object;
     145: pop
     146: aload_0
     147: getfield      #5                  // Field writer:Ljavax/xml/stream/XMLStreamWriter;
     150: aload         4
     152: iload         7
     154: invokeinterface #32,  2           // InterfaceMethod org/xml/sax/Attributes.getValue:(I)Ljava/lang/String;
     159: invokeinterface #33,  2           // InterfaceMethod javax/xml/stream/XMLStreamWriter.writeDefaultNamespace:(Ljava/lang/String;)V
     164: goto          210
     167: aload         8
     169: iload         9
     171: iconst_1
     172: iadd
     173: invokevirtual #34                 // Method java/lang/String.substring:(I)Ljava/lang/String;
     176: astore        8
     178: aload_0
     179: getfield      #4                  // Field mapping:Ljava/util/Map;
     182: aload         8
     184: invokeinterface #31,  2           // InterfaceMethod java/util/Map.remove:(Ljava/lang/Object;)Ljava/lang/Object;
     189: pop
     190: aload_0
     191: getfield      #5                  // Field writer:Ljavax/xml/stream/XMLStreamWriter;
     194: aload         8
     196: aload         4
     198: iload         7
     200: invokeinterface #32,  2           // InterfaceMethod org/xml/sax/Attributes.getValue:(I)Ljava/lang/String;
     205: invokeinterface #35,  3           // InterfaceMethod javax/xml/stream/XMLStreamWriter.writeNamespace:(Ljava/lang/String;Ljava/lang/String;)V
     210: iinc          7, 1
     213: goto          69
     216: aload_0
     217: getfield      #4                  // Field mapping:Ljava/util/Map;
     220: invokeinterface #36,  1           // InterfaceMethod java/util/Map.entrySet:()Ljava/util/Set;
     225: invokeinterface #37,  1           // InterfaceMethod java/util/Set.iterator:()Ljava/util/Iterator;
     230: astore        6
     232: aload         6
     234: invokeinterface #38,  1           // InterfaceMethod java/util/Iterator.hasNext:()Z
     239: ifeq          323
     242: aload         6
     244: invokeinterface #39,  1           // InterfaceMethod java/util/Iterator.next:()Ljava/lang/Object;
     249: checkcast     #40                 // class java/util/Map$Entry
     252: astore        7
     254: ldc           #20                 // String
     256: aload         7
     258: invokeinterface #41,  1           // InterfaceMethod java/util/Map$Entry.getKey:()Ljava/lang/Object;
     263: invokevirtual #42                 // Method java/lang/String.equals:(Ljava/lang/Object;)Z
     266: ifeq          291
     269: aload_0
     270: getfield      #5                  // Field writer:Ljavax/xml/stream/XMLStreamWriter;
     273: aload         7
     275: invokeinterface #43,  1           // InterfaceMethod java/util/Map$Entry.getValue:()Ljava/lang/Object;
     280: checkcast     #7                  // class java/lang/String
     283: invokeinterface #33,  2           // InterfaceMethod javax/xml/stream/XMLStreamWriter.writeDefaultNamespace:(Ljava/lang/String;)V
     288: goto          320
     291: aload_0
     292: getfield      #5                  // Field writer:Ljavax/xml/stream/XMLStreamWriter;
     295: aload         7
     297: invokeinterface #41,  1           // InterfaceMethod java/util/Map$Entry.getKey:()Ljava/lang/Object;
     302: checkcast     #7                  // class java/lang/String
     305: aload         7
     307: invokeinterface #43,  1           // InterfaceMethod java/util/Map$Entry.getValue:()Ljava/lang/Object;
     312: checkcast     #7                  // class java/lang/String
     315: invokeinterface #35,  3           // InterfaceMethod javax/xml/stream/XMLStreamWriter.writeNamespace:(Ljava/lang/String;Ljava/lang/String;)V
     320: goto          232
     323: aload_0
     324: getfield      #4                  // Field mapping:Ljava/util/Map;
     327: invokeinterface #44,  1           // InterfaceMethod java/util/Map.clear:()V
     332: aload         4
     334: ifnull        554
     337: aload         4
     339: invokeinterface #25,  1           // InterfaceMethod org/xml/sax/Attributes.getLength:()I
     344: istore        6
     346: iconst_0
     347: istore        7
     349: iload         7
     351: iload         6
     353: if_icmpge     554
     356: aload         4
     358: iload         7
     360: invokeinterface #26,  2           // InterfaceMethod org/xml/sax/Attributes.getURI:(I)Ljava/lang/String;
     365: invokestatic  #27                 // Method org/apache/cxf/common/util/StringUtils.isEmpty:(Ljava/lang/String;)Z
     368: ifeq          424
     371: aload         4
     373: iload         7
     375: invokeinterface #45,  2           // InterfaceMethod org/xml/sax/Attributes.getLocalName:(I)Ljava/lang/String;
     380: astore        8
     382: aload         8
     384: invokestatic  #27                 // Method org/apache/cxf/common/util/StringUtils.isEmpty:(Ljava/lang/String;)Z
     387: ifeq          401
     390: aload         4
     392: iload         7
     394: invokeinterface #28,  2           // InterfaceMethod org/xml/sax/Attributes.getQName:(I)Ljava/lang/String;
     399: astore        8
     401: aload_0
     402: getfield      #5                  // Field writer:Ljavax/xml/stream/XMLStreamWriter;
     405: aload         8
     407: aload         4
     409: iload         7
     411: invokeinterface #32,  2           // InterfaceMethod org/xml/sax/Attributes.getValue:(I)Ljava/lang/String;
     416: invokeinterface #46,  3           // InterfaceMethod javax/xml/stream/XMLStreamWriter.writeAttribute:(Ljava/lang/String;Ljava/lang/String;)V
     421: goto          548
     424: aload         4
     426: iload         7
     428: invokeinterface #28,  2           // InterfaceMethod org/xml/sax/Attributes.getQName:(I)Ljava/lang/String;
     433: astore        8
     435: aload         8
     437: ldc           #29                 // String xmlns
     439: invokevirtual #30                 // Method java/lang/String.startsWith:(Ljava/lang/String;)Z
     442: ifne          548
     445: aload         8
     447: bipush        58
     449: invokevirtual #17                 // Method java/lang/String.indexOf:(I)I
     452: iconst_m1
     453: if_icmpeq     512
     456: aload         8
     458: iconst_0
     459: aload         8
     461: bipush        58
     463: invokevirtual #17                 // Method java/lang/String.indexOf:(I)I
     466: invokevirtual #18                 // Method java/lang/String.substring:(II)Ljava/lang/String;
     469: astore        8
     471: aload_0
     472: getfield      #5                  // Field writer:Ljavax/xml/stream/XMLStreamWriter;
     475: aload         8
     477: aload         4
     479: iload         7
     481: invokeinterface #26,  2           // InterfaceMethod org/xml/sax/Attributes.getURI:(I)Ljava/lang/String;
     486: aload         4
     488: iload         7
     490: invokeinterface #45,  2           // InterfaceMethod org/xml/sax/Attributes.getLocalName:(I)Ljava/lang/String;
     495: aload         4
     497: iload         7
     499: invokeinterface #32,  2           // InterfaceMethod org/xml/sax/Attributes.getValue:(I)Ljava/lang/String;
     504: invokeinterface #47,  5           // InterfaceMethod javax/xml/stream/XMLStreamWriter.writeAttribute:(Ljava/lang/String;Ljava/lang/String;Ljava/lang/String;Ljava/lang/String;)V
     509: goto          548
     512: aload_0
     513: getfield      #5                  // Field writer:Ljavax/xml/stream/XMLStreamWriter;
     516: aload         4
     518: iload         7
     520: invokeinterface #26,  2           // InterfaceMethod org/xml/sax/Attributes.getURI:(I)Ljava/lang/String;
     525: aload         4
     527: iload         7
     529: invokeinterface #45,  2           // InterfaceMethod org/xml/sax/Attributes.getLocalName:(I)Ljava/lang/String;
     534: aload         4
     536: iload         7
     538: invokeinterface #32,  2           // InterfaceMethod org/xml/sax/Attributes.getValue:(I)Ljava/lang/String;
     543: invokeinterface #48,  4           // InterfaceMethod javax/xml/stream/XMLStreamWriter.writeAttribute:(Ljava/lang/String;Ljava/lang/String;Ljava/lang/String;)V
     548: iinc          7, 1
     551: goto          349
     554: goto          569
     557: astore        5
     559: new           #12                 // class org/xml/sax/SAXException
     562: dup
     563: aload         5
     565: invokespecial #13                 // Method org/xml/sax/SAXException."<init>":(Ljava/lang/Exception;)V
     568: athrow
     569: return
    Exception table:
       from    to  target type
           0   554   557   Class javax/xml/stream/XMLStreamException

  public void startDTD(java.lang.String, java.lang.String, java.lang.String) throws org.xml.sax.SAXException;
    Code:
       0: return

  public void endDTD() throws org.xml.sax.SAXException;
    Code:
       0: return

  public void startEntity(java.lang.String) throws org.xml.sax.SAXException;
    Code:
       0: return

  public void endEntity(java.lang.String) throws org.xml.sax.SAXException;
    Code:
       0: return

  public void startCDATA() throws org.xml.sax.SAXException;
    Code:
       0: aload_0
       1: iconst_1
       2: putfield      #6                  // Field inCDATA:Z
       5: return

  public void endCDATA() throws org.xml.sax.SAXException;
    Code:
       0: aload_0
       1: iconst_0
       2: putfield      #6                  // Field inCDATA:Z
       5: return

  public void comment(char[], int, int) throws org.xml.sax.SAXException;
    Code:
       0: aload_0
       1: getfield      #5                  // Field writer:Ljavax/xml/stream/XMLStreamWriter;
       4: new           #7                  // class java/lang/String
       7: dup
       8: aload_1
       9: iload_2
      10: iload_3
      11: invokespecial #8                  // Method java/lang/String."<init>":([CII)V
      14: invokeinterface #49,  2           // InterfaceMethod javax/xml/stream/XMLStreamWriter.writeComment:(Ljava/lang/String;)V
      19: goto          34
      22: astore        4
      24: new           #12                 // class org/xml/sax/SAXException
      27: dup
      28: aload         4
      30: invokespecial #13                 // Method org/xml/sax/SAXException."<init>":(Ljava/lang/Exception;)V
      33: athrow
      34: return
    Exception table:
       from    to  target type
           0    19    22   Class javax/xml/stream/XMLStreamException
}
