Compiled from "Util.java"
public class org.apache.tomcat.websocket.Util$DecoderMatch {
  private final java.util.List<java.lang.Class<? extends javax.websocket.Decoder>> textDecoders;

  private final java.util.List<java.lang.Class<? extends javax.websocket.Decoder>> binaryDecoders;

  private final java.lang.Class<?> target;

  public org.apache.tomcat.websocket.Util$DecoderMatch(java.lang.Class<?>, java.util.List<org.apache.tomcat.websocket.DecoderEntry>);
    Code:
       0: aload_0
       1: invokespecial #1                  // Method java/lang/Object."<init>":()V
       4: aload_0
       5: new           #2                  // class java/util/ArrayList
       8: dup
       9: invokespecial #3                  // Method java/util/ArrayList."<init>":()V
      12: putfield      #4                  // Field textDecoders:Ljava/util/List;
      15: aload_0
      16: new           #2                  // class java/util/ArrayList
      19: dup
      20: invokespecial #3                  // Method java/util/ArrayList."<init>":()V
      23: putfield      #5                  // Field binaryDecoders:Ljava/util/List;
      26: aload_0
      27: aload_1
      28: putfield      #6                  // Field target:Ljava/lang/Class;
      31: aload_2
      32: invokeinterface #7,  1            // InterfaceMethod java/util/List.iterator:()Ljava/util/Iterator;
      37: astore_3
      38: aload_3
      39: invokeinterface #8,  1            // InterfaceMethod java/util/Iterator.hasNext:()Z
      44: ifeq          213
      47: aload_3
      48: invokeinterface #9,  1            // InterfaceMethod java/util/Iterator.next:()Ljava/lang/Object;
      53: checkcast     #10                 // class org/apache/tomcat/websocket/DecoderEntry
      56: astore        4
      58: aload         4
      60: invokevirtual #11                 // Method org/apache/tomcat/websocket/DecoderEntry.getClazz:()Ljava/lang/Class;
      63: aload_1
      64: invokevirtual #12                 // Method java/lang/Class.isAssignableFrom:(Ljava/lang/Class;)Z
      67: ifeq          210
      70: ldc           #13                 // class javax/websocket/Decoder$Binary
      72: aload         4
      74: invokevirtual #14                 // Method org/apache/tomcat/websocket/DecoderEntry.getDecoderClazz:()Ljava/lang/Class;
      77: invokevirtual #12                 // Method java/lang/Class.isAssignableFrom:(Ljava/lang/Class;)Z
      80: ifeq          101
      83: aload_0
      84: getfield      #5                  // Field binaryDecoders:Ljava/util/List;
      87: aload         4
      89: invokevirtual #14                 // Method org/apache/tomcat/websocket/DecoderEntry.getDecoderClazz:()Ljava/lang/Class;
      92: invokeinterface #15,  2           // InterfaceMethod java/util/List.add:(Ljava/lang/Object;)Z
      97: pop
      98: goto          210
     101: ldc           #16                 // class javax/websocket/Decoder$BinaryStream
     103: aload         4
     105: invokevirtual #14                 // Method org/apache/tomcat/websocket/DecoderEntry.getDecoderClazz:()Ljava/lang/Class;
     108: invokevirtual #12                 // Method java/lang/Class.isAssignableFrom:(Ljava/lang/Class;)Z
     111: ifeq          132
     114: aload_0
     115: getfield      #5                  // Field binaryDecoders:Ljava/util/List;
     118: aload         4
     120: invokevirtual #14                 // Method org/apache/tomcat/websocket/DecoderEntry.getDecoderClazz:()Ljava/lang/Class;
     123: invokeinterface #15,  2           // InterfaceMethod java/util/List.add:(Ljava/lang/Object;)Z
     128: pop
     129: goto          213
     132: ldc           #17                 // class javax/websocket/Decoder$Text
     134: aload         4
     136: invokevirtual #14                 // Method org/apache/tomcat/websocket/DecoderEntry.getDecoderClazz:()Ljava/lang/Class;
     139: invokevirtual #12                 // Method java/lang/Class.isAssignableFrom:(Ljava/lang/Class;)Z
     142: ifeq          163
     145: aload_0
     146: getfield      #4                  // Field textDecoders:Ljava/util/List;
     149: aload         4
     151: invokevirtual #14                 // Method org/apache/tomcat/websocket/DecoderEntry.getDecoderClazz:()Ljava/lang/Class;
     154: invokeinterface #15,  2           // InterfaceMethod java/util/List.add:(Ljava/lang/Object;)Z
     159: pop
     160: goto          210
     163: ldc           #18                 // class javax/websocket/Decoder$TextStream
     165: aload         4
     167: invokevirtual #14                 // Method org/apache/tomcat/websocket/DecoderEntry.getDecoderClazz:()Ljava/lang/Class;
     170: invokevirtual #12                 // Method java/lang/Class.isAssignableFrom:(Ljava/lang/Class;)Z
     173: ifeq          194
     176: aload_0
     177: getfield      #4                  // Field textDecoders:Ljava/util/List;
     180: aload         4
     182: invokevirtual #14                 // Method org/apache/tomcat/websocket/DecoderEntry.getDecoderClazz:()Ljava/lang/Class;
     185: invokeinterface #15,  2           // InterfaceMethod java/util/List.add:(Ljava/lang/Object;)Z
     190: pop
     191: goto          213
     194: new           #19                 // class java/lang/IllegalArgumentException
     197: dup
     198: invokestatic  #20                 // Method org/apache/tomcat/websocket/Util.access$000:()Lorg/apache/tomcat/util/res/StringManager;
     201: ldc           #21                 // String util.unknownDecoderType
     203: invokevirtual #22                 // Method org/apache/tomcat/util/res/StringManager.getString:(Ljava/lang/String;)Ljava/lang/String;
     206: invokespecial #23                 // Method java/lang/IllegalArgumentException."<init>":(Ljava/lang/String;)V
     209: athrow
     210: goto          38
     213: return

  public java.util.List<java.lang.Class<? extends javax.websocket.Decoder>> getTextDecoders();
    Code:
       0: aload_0
       1: getfield      #4                  // Field textDecoders:Ljava/util/List;
       4: areturn

  public java.util.List<java.lang.Class<? extends javax.websocket.Decoder>> getBinaryDecoders();
    Code:
       0: aload_0
       1: getfield      #5                  // Field binaryDecoders:Ljava/util/List;
       4: areturn

  public java.lang.Class<?> getTarget();
    Code:
       0: aload_0
       1: getfield      #6                  // Field target:Ljava/lang/Class;
       4: areturn

  public boolean hasMatches();
    Code:
       0: aload_0
       1: getfield      #4                  // Field textDecoders:Ljava/util/List;
       4: invokeinterface #24,  1           // InterfaceMethod java/util/List.size:()I
       9: ifgt          24
      12: aload_0
      13: getfield      #5                  // Field binaryDecoders:Ljava/util/List;
      16: invokeinterface #24,  1           // InterfaceMethod java/util/List.size:()I
      21: ifle          28
      24: iconst_1
      25: goto          29
      28: iconst_0
      29: ireturn
}
