Compiled from "WsSession.java"
final class org.apache.tomcat.websocket.WsSession$State extends java.lang.Enum<org.apache.tomcat.websocket.WsSession$State> {
  public static final org.apache.tomcat.websocket.WsSession$State OPEN;

  public static final org.apache.tomcat.websocket.WsSession$State OUTPUT_CLOSED;

  public static final org.apache.tomcat.websocket.WsSession$State CLOSED;

  private static final org.apache.tomcat.websocket.WsSession$State[] $VALUES;

  public static org.apache.tomcat.websocket.WsSession$State[] values();
    Code:
       0: getstatic     #1                  // Field $VALUES:[Lorg/apache/tomcat/websocket/WsSession$State;
       3: invokevirtual #2                  // Method "[Lorg/apache/tomcat/websocket/WsSession$State;".clone:()Ljava/lang/Object;
       6: checkcast     #3                  // class "[Lorg/apache/tomcat/websocket/WsSession$State;"
       9: areturn

  public static org.apache.tomcat.websocket.WsSession$State valueOf(java.lang.String);
    Code:
       0: ldc           #4                  // class org/apache/tomcat/websocket/WsSession$State
       2: aload_0
       3: invokestatic  #5                  // Method java/lang/Enum.valueOf:(Ljava/lang/Class;Ljava/lang/String;)Ljava/lang/Enum;
       6: checkcast     #4                  // class org/apache/tomcat/websocket/WsSession$State
       9: areturn

  private org.apache.tomcat.websocket.WsSession$State();
    Code:
       0: aload_0
       1: aload_1
       2: iload_2
       3: invokespecial #6                  // Method java/lang/Enum."<init>":(Ljava/lang/String;I)V
       6: return

  static {};
    Code:
       0: new           #4                  // class org/apache/tomcat/websocket/WsSession$State
       3: dup
       4: ldc           #7                  // String OPEN
       6: iconst_0
       7: invokespecial #8                  // Method "<init>":(Ljava/lang/String;I)V
      10: putstatic     #9                  // Field OPEN:Lorg/apache/tomcat/websocket/WsSession$State;
      13: new           #4                  // class org/apache/tomcat/websocket/WsSession$State
      16: dup
      17: ldc           #10                 // String OUTPUT_CLOSED
      19: iconst_1
      20: invokespecial #8                  // Method "<init>":(Ljava/lang/String;I)V
      23: putstatic     #11                 // Field OUTPUT_CLOSED:Lorg/apache/tomcat/websocket/WsSession$State;
      26: new           #4                  // class org/apache/tomcat/websocket/WsSession$State
      29: dup
      30: ldc           #12                 // String CLOSED
      32: iconst_2
      33: invokespecial #8                  // Method "<init>":(Ljava/lang/String;I)V
      36: putstatic     #13                 // Field CLOSED:Lorg/apache/tomcat/websocket/WsSession$State;
      39: iconst_3
      40: anewarray     #4                  // class org/apache/tomcat/websocket/WsSession$State
      43: dup
      44: iconst_0
      45: getstatic     #9                  // Field OPEN:Lorg/apache/tomcat/websocket/WsSession$State;
      48: aastore
      49: dup
      50: iconst_1
      51: getstatic     #11                 // Field OUTPUT_CLOSED:Lorg/apache/tomcat/websocket/WsSession$State;
      54: aastore
      55: dup
      56: iconst_2
      57: getstatic     #13                 // Field CLOSED:Lorg/apache/tomcat/websocket/WsSession$State;
      60: aastore
      61: putstatic     #1                  // Field $VALUES:[Lorg/apache/tomcat/websocket/WsSession$State;
      64: return
}
