Compiled from "DoneableNodeMetricsList.java"
class io.dekorate.deps.kubernetes.api.model.metrics.v1beta1.DoneableNodeMetricsList$1 implements io.dekorate.deps.kubernetes.api.builder.Function<io.dekorate.deps.kubernetes.api.model.metrics.v1beta1.NodeMetricsList, io.dekorate.deps.kubernetes.api.model.metrics.v1beta1.NodeMetricsList> {
  final io.dekorate.deps.kubernetes.api.model.metrics.v1beta1.DoneableNodeMetricsList this$0;

  io.dekorate.deps.kubernetes.api.model.metrics.v1beta1.DoneableNodeMetricsList$1(io.dekorate.deps.kubernetes.api.model.metrics.v1beta1.DoneableNodeMetricsList);
    Code:
       0: aload_0
       1: aload_1
       2: putfield      #18                 // Field this$0:Lio/dekorate/deps/kubernetes/api/model/metrics/v1beta1/DoneableNodeMetricsList;
       5: aload_0
       6: invokespecial #21                 // Method java/lang/Object."<init>":()V
       9: return

  public io.dekorate.deps.kubernetes.api.model.metrics.v1beta1.NodeMetricsList apply(io.dekorate.deps.kubernetes.api.model.metrics.v1beta1.NodeMetricsList);
    Code:
       0: aload_1
       1: areturn

  public java.lang.Object apply(java.lang.Object);
    Code:
       0: aload_0
       1: aload_1
       2: checkcast     #30                 // class io/dekorate/deps/kubernetes/api/model/metrics/v1beta1/NodeMetricsList
       5: invokevirtual #32                 // Method apply:(Lio/dekorate/deps/kubernetes/api/model/metrics/v1beta1/NodeMetricsList;)Lio/dekorate/deps/kubernetes/api/model/metrics/v1beta1/NodeMetricsList;
       8: areturn
}
