Compiled from "AbstractOperationContext.java"
final class org.jboss.as.controller.AbstractOperationContext$ContextFlag extends java.lang.Enum<org.jboss.as.controller.AbstractOperationContext$ContextFlag> {
  public static final org.jboss.as.controller.AbstractOperationContext$ContextFlag ROLLBACK_ON_FAIL;

  public static final org.jboss.as.controller.AbstractOperationContext$ContextFlag ALLOW_RESOURCE_SERVICE_RESTART;

  private static final org.jboss.as.controller.AbstractOperationContext$ContextFlag[] $VALUES;

  public static org.jboss.as.controller.AbstractOperationContext$ContextFlag[] values();
    Code:
       0: getstatic     #1                  // Field $VALUES:[Lorg/jboss/as/controller/AbstractOperationContext$ContextFlag;
       3: invokevirtual #2                  // Method "[Lorg/jboss/as/controller/AbstractOperationContext$ContextFlag;".clone:()Ljava/lang/Object;
       6: checkcast     #3                  // class "[Lorg/jboss/as/controller/AbstractOperationContext$ContextFlag;"
       9: areturn

  public static org.jboss.as.controller.AbstractOperationContext$ContextFlag valueOf(java.lang.String);
    Code:
       0: ldc           #4                  // class org/jboss/as/controller/AbstractOperationContext$ContextFlag
       2: aload_0
       3: invokestatic  #5                  // Method java/lang/Enum.valueOf:(Ljava/lang/Class;Ljava/lang/String;)Ljava/lang/Enum;
       6: checkcast     #4                  // class org/jboss/as/controller/AbstractOperationContext$ContextFlag
       9: areturn

  private org.jboss.as.controller.AbstractOperationContext$ContextFlag();
    Code:
       0: aload_0
       1: aload_1
       2: iload_2
       3: invokespecial #6                  // Method java/lang/Enum."<init>":(Ljava/lang/String;I)V
       6: return

  static {};
    Code:
       0: new           #4                  // class org/jboss/as/controller/AbstractOperationContext$ContextFlag
       3: dup
       4: ldc           #7                  // String ROLLBACK_ON_FAIL
       6: iconst_0
       7: invokespecial #8                  // Method "<init>":(Ljava/lang/String;I)V
      10: putstatic     #9                  // Field ROLLBACK_ON_FAIL:Lorg/jboss/as/controller/AbstractOperationContext$ContextFlag;
      13: new           #4                  // class org/jboss/as/controller/AbstractOperationContext$ContextFlag
      16: dup
      17: ldc           #10                 // String ALLOW_RESOURCE_SERVICE_RESTART
      19: iconst_1
      20: invokespecial #8                  // Method "<init>":(Ljava/lang/String;I)V
      23: putstatic     #11                 // Field ALLOW_RESOURCE_SERVICE_RESTART:Lorg/jboss/as/controller/AbstractOperationContext$ContextFlag;
      26: iconst_2
      27: anewarray     #4                  // class org/jboss/as/controller/AbstractOperationContext$ContextFlag
      30: dup
      31: iconst_0
      32: getstatic     #9                  // Field ROLLBACK_ON_FAIL:Lorg/jboss/as/controller/AbstractOperationContext$ContextFlag;
      35: aastore
      36: dup
      37: iconst_1
      38: getstatic     #11                 // Field ALLOW_RESOURCE_SERVICE_RESTART:Lorg/jboss/as/controller/AbstractOperationContext$ContextFlag;
      41: aastore
      42: putstatic     #1                  // Field $VALUES:[Lorg/jboss/as/controller/AbstractOperationContext$ContextFlag;
      45: return
}
