Compiled from "AttributeParsers.java"
public interface org.jboss.as.controller.AttributeParsers {
  public static final org.jboss.as.controller.AttributeParser PROPERTIES_WRAPPED;

  public static final org.jboss.as.controller.AttributeParser PROPERTIES_UNWRAPPED;

  static {};
    Code:
       0: new           #1                  // class org/jboss/as/controller/AttributeParsers$PropertiesParser
       3: dup
       4: invokespecial #2                  // Method org/jboss/as/controller/AttributeParsers$PropertiesParser."<init>":()V
       7: putstatic     #3                  // Field PROPERTIES_WRAPPED:Lorg/jboss/as/controller/AttributeParser;
      10: new           #1                  // class org/jboss/as/controller/AttributeParsers$PropertiesParser
      13: dup
      14: iconst_0
      15: invokespecial #4                  // Method org/jboss/as/controller/AttributeParsers$PropertiesParser."<init>":(Z)V
      18: putstatic     #5                  // Field PROPERTIES_UNWRAPPED:Lorg/jboss/as/controller/AttributeParser;
      21: return
}
