Compiled from "DelegatingResourceDefinition.java"
public class org.jboss.as.controller.DelegatingResourceDefinition implements org.jboss.as.controller.ResourceDefinition {
  protected volatile org.jboss.as.controller.ResourceDefinition delegate;

  public org.jboss.as.controller.DelegatingResourceDefinition();
    Code:
       0: aload_0
       1: invokespecial #1                  // Method java/lang/Object."<init>":()V
       4: return

  protected void setDelegate(org.jboss.as.controller.ResourceDefinition);
    Code:
       0: aload_0
       1: aload_1
       2: putfield      #2                  // Field delegate:Lorg/jboss/as/controller/ResourceDefinition;
       5: return

  public void registerOperations(org.jboss.as.controller.registry.ManagementResourceRegistration);
    Code:
       0: aload_0
       1: getfield      #2                  // Field delegate:Lorg/jboss/as/controller/ResourceDefinition;
       4: aload_1
       5: invokeinterface #3,  2            // InterfaceMethod org/jboss/as/controller/ResourceDefinition.registerOperations:(Lorg/jboss/as/controller/registry/ManagementResourceRegistration;)V
      10: return

  public void registerChildren(org.jboss.as.controller.registry.ManagementResourceRegistration);
    Code:
       0: aload_0
       1: getfield      #2                  // Field delegate:Lorg/jboss/as/controller/ResourceDefinition;
       4: aload_1
       5: invokeinterface #4,  2            // InterfaceMethod org/jboss/as/controller/ResourceDefinition.registerChildren:(Lorg/jboss/as/controller/registry/ManagementResourceRegistration;)V
      10: return

  public void registerAttributes(org.jboss.as.controller.registry.ManagementResourceRegistration);
    Code:
       0: aload_0
       1: getfield      #2                  // Field delegate:Lorg/jboss/as/controller/ResourceDefinition;
       4: aload_1
       5: invokeinterface #5,  2            // InterfaceMethod org/jboss/as/controller/ResourceDefinition.registerAttributes:(Lorg/jboss/as/controller/registry/ManagementResourceRegistration;)V
      10: return

  public void registerNotifications(org.jboss.as.controller.registry.ManagementResourceRegistration);
    Code:
       0: aload_0
       1: getfield      #2                  // Field delegate:Lorg/jboss/as/controller/ResourceDefinition;
       4: aload_1
       5: invokeinterface #6,  2            // InterfaceMethod org/jboss/as/controller/ResourceDefinition.registerNotifications:(Lorg/jboss/as/controller/registry/ManagementResourceRegistration;)V
      10: return

  public void registerCapabilities(org.jboss.as.controller.registry.ManagementResourceRegistration);
    Code:
       0: aload_0
       1: getfield      #2                  // Field delegate:Lorg/jboss/as/controller/ResourceDefinition;
       4: aload_1
       5: invokeinterface #7,  2            // InterfaceMethod org/jboss/as/controller/ResourceDefinition.registerCapabilities:(Lorg/jboss/as/controller/registry/ManagementResourceRegistration;)V
      10: return

  public org.jboss.as.controller.PathElement getPathElement();
    Code:
       0: aload_0
       1: getfield      #2                  // Field delegate:Lorg/jboss/as/controller/ResourceDefinition;
       4: invokeinterface #8,  1            // InterfaceMethod org/jboss/as/controller/ResourceDefinition.getPathElement:()Lorg/jboss/as/controller/PathElement;
       9: areturn

  public org.jboss.as.controller.descriptions.DescriptionProvider getDescriptionProvider(org.jboss.as.controller.registry.ImmutableManagementResourceRegistration);
    Code:
       0: aload_0
       1: getfield      #2                  // Field delegate:Lorg/jboss/as/controller/ResourceDefinition;
       4: aload_1
       5: invokeinterface #9,  2            // InterfaceMethod org/jboss/as/controller/ResourceDefinition.getDescriptionProvider:(Lorg/jboss/as/controller/registry/ImmutableManagementResourceRegistration;)Lorg/jboss/as/controller/descriptions/DescriptionProvider;
      10: areturn

  public java.util.List<org.jboss.as.controller.access.management.AccessConstraintDefinition> getAccessConstraints();
    Code:
       0: aload_0
       1: getfield      #2                  // Field delegate:Lorg/jboss/as/controller/ResourceDefinition;
       4: ifnonnull     11
       7: invokestatic  #10                 // Method java/util/Collections.emptyList:()Ljava/util/List;
      10: areturn
      11: aload_0
      12: getfield      #2                  // Field delegate:Lorg/jboss/as/controller/ResourceDefinition;
      15: invokeinterface #11,  1           // InterfaceMethod org/jboss/as/controller/ResourceDefinition.getAccessConstraints:()Ljava/util/List;
      20: areturn

  public boolean isRuntime();
    Code:
       0: aload_0
       1: getfield      #2                  // Field delegate:Lorg/jboss/as/controller/ResourceDefinition;
       4: ifnull        17
       7: aload_0
       8: getfield      #2                  // Field delegate:Lorg/jboss/as/controller/ResourceDefinition;
      11: invokeinterface #12,  1           // InterfaceMethod org/jboss/as/controller/ResourceDefinition.isRuntime:()Z
      16: ireturn
      17: iconst_0
      18: ireturn

  public boolean isOrderedChild();
    Code:
       0: aload_0
       1: getfield      #2                  // Field delegate:Lorg/jboss/as/controller/ResourceDefinition;
       4: ifnull        17
       7: aload_0
       8: getfield      #2                  // Field delegate:Lorg/jboss/as/controller/ResourceDefinition;
      11: invokeinterface #13,  1           // InterfaceMethod org/jboss/as/controller/ResourceDefinition.isOrderedChild:()Z
      16: ireturn
      17: iconst_0
      18: ireturn
}
