Compiled from "NoopOperationStepHandler.java"
public class org.jboss.as.controller.NoopOperationStepHandler implements org.jboss.as.controller.OperationStepHandler {
  public static final org.jboss.as.controller.NoopOperationStepHandler WITH_RESULT;

  public static final org.jboss.as.controller.NoopOperationStepHandler WITHOUT_RESULT;

  private final boolean setResult;

  private org.jboss.as.controller.NoopOperationStepHandler(boolean);
    Code:
       0: aload_0
       1: invokespecial #1                  // Method java/lang/Object."<init>":()V
       4: aload_0
       5: iload_1
       6: putfield      #2                  // Field setResult:Z
       9: return

  public void execute(org.jboss.as.controller.OperationContext, org.jboss.dmr.ModelNode) throws org.jboss.as.controller.OperationFailedException;
    Code:
       0: aload_0
       1: getfield      #2                  // Field setResult:Z
       4: ifeq          14
       7: aload_1
       8: invokeinterface #3,  1            // InterfaceMethod org/jboss/as/controller/OperationContext.getResult:()Lorg/jboss/dmr/ModelNode;
      13: pop
      14: return

  static {};
    Code:
       0: new           #4                  // class org/jboss/as/controller/NoopOperationStepHandler
       3: dup
       4: iconst_1
       5: invokespecial #5                  // Method "<init>":(Z)V
       8: putstatic     #6                  // Field WITH_RESULT:Lorg/jboss/as/controller/NoopOperationStepHandler;
      11: new           #4                  // class org/jboss/as/controller/NoopOperationStepHandler
      14: dup
      15: iconst_0
      16: invokespecial #5                  // Method "<init>":(Z)V
      19: putstatic     #7                  // Field WITHOUT_RESULT:Lorg/jboss/as/controller/NoopOperationStepHandler;
      22: return
}
