Compiled from "OperationContext.java"
public interface org.jboss.as.controller.OperationContext$RollbackHandler {
  public static final org.jboss.as.controller.OperationContext$RollbackHandler NOOP_ROLLBACK_HANDLER;

  public static final org.jboss.as.controller.OperationContext$RollbackHandler REVERT_RELOAD_REQUIRED_ROLLBACK_HANDLER;

  public abstract void handleRollback(org.jboss.as.controller.OperationContext, org.jboss.dmr.ModelNode);

  static {};
    Code:
       0: new           #1                  // class org/jboss/as/controller/OperationContext$RollbackHandler$1
       3: dup
       4: invokespecial #2                  // Method org/jboss/as/controller/OperationContext$RollbackHandler$1."<init>":()V
       7: putstatic     #3                  // Field NOOP_ROLLBACK_HANDLER:Lorg/jboss/as/controller/OperationContext$RollbackHandler;
      10: new           #4                  // class org/jboss/as/controller/OperationContext$RollbackHandler$2
      13: dup
      14: invokespecial #5                  // Method org/jboss/as/controller/OperationContext$RollbackHandler$2."<init>":()V
      17: putstatic     #6                  // Field REVERT_RELOAD_REQUIRED_ROLLBACK_HANDLER:Lorg/jboss/as/controller/OperationContext$RollbackHandler;
      20: return
}
