Compiled from "ParallelBootOperationStepHandler.java"
public class org.jboss.as.controller.ParallelBootOperationStepHandler implements org.jboss.as.controller.OperationStepHandler {
  private final java.util.concurrent.Executor executor;

  private final org.jboss.as.controller.registry.ImmutableManagementResourceRegistration rootRegistration;

  private final org.jboss.as.controller.ControlledProcessState processState;

  private final org.jboss.as.controller.OperationStepHandler extraValidationStepHandler;

  private final org.jboss.as.controller.ModelControllerImpl controller;

  private final int operationId;

  private final java.util.Map<java.lang.String, java.util.List<org.jboss.as.controller.ParsedBootOp>> opsBySubsystem;

  private org.jboss.as.controller.ParsedBootOp ourOp;

  org.jboss.as.controller.ParallelBootOperationStepHandler(java.util.concurrent.ExecutorService, org.jboss.as.controller.registry.ImmutableManagementResourceRegistration, org.jboss.as.controller.ControlledProcessState, org.jboss.as.controller.ModelControllerImpl, int, org.jboss.as.controller.OperationStepHandler);
    Code:
       0: aload_0
       1: invokespecial #9                  // Method java/lang/Object."<init>":()V
       4: aload_0
       5: new           #10                 // class java/util/LinkedHashMap
       8: dup
       9: invokespecial #11                 // Method java/util/LinkedHashMap."<init>":()V
      12: putfield      #12                 // Field opsBySubsystem:Ljava/util/Map;
      15: aload_0
      16: aload_1
      17: putfield      #5                  // Field executor:Ljava/util/concurrent/Executor;
      20: aload_0
      21: aload_2
      22: putfield      #1                  // Field rootRegistration:Lorg/jboss/as/controller/registry/ImmutableManagementResourceRegistration;
      25: aload_0
      26: aload_3
      27: putfield      #3                  // Field processState:Lorg/jboss/as/controller/ControlledProcessState;
      30: aload_0
      31: aload         4
      33: putfield      #7                  // Field controller:Lorg/jboss/as/controller/ModelControllerImpl;
      36: aload_0
      37: iload         5
      39: putfield      #6                  // Field operationId:I
      42: aload_0
      43: aload         6
      45: putfield      #2                  // Field extraValidationStepHandler:Lorg/jboss/as/controller/OperationStepHandler;
      48: return

  boolean addSubsystemOperation(org.jboss.as.controller.ParsedBootOp);
    Code:
       0: aload_0
       1: aload_1
       2: getfield      #13                 // Field org/jboss/as/controller/ParsedBootOp.address:Lorg/jboss/as/controller/PathAddress;
       5: invokespecial #14                 // Method getSubsystemName:(Lorg/jboss/as/controller/PathAddress;)Ljava/lang/String;
       8: astore_2
       9: aload_2
      10: ifnull        67
      13: aload_0
      14: getfield      #12                 // Field opsBySubsystem:Ljava/util/Map;
      17: aload_2
      18: invokeinterface #15,  2           // InterfaceMethod java/util/Map.get:(Ljava/lang/Object;)Ljava/lang/Object;
      23: checkcast     #16                 // class java/util/List
      26: astore_3
      27: aload_3
      28: ifnonnull     51
      31: new           #17                 // class java/util/ArrayList
      34: dup
      35: invokespecial #18                 // Method java/util/ArrayList."<init>":()V
      38: astore_3
      39: aload_0
      40: getfield      #12                 // Field opsBySubsystem:Ljava/util/Map;
      43: aload_2
      44: aload_3
      45: invokeinterface #19,  3           // InterfaceMethod java/util/Map.put:(Ljava/lang/Object;Ljava/lang/Object;)Ljava/lang/Object;
      50: pop
      51: aload_3
      52: aload_1
      53: invokeinterface #20,  2           // InterfaceMethod java/util/List.add:(Ljava/lang/Object;)Z
      58: pop
      59: aload_0
      60: invokevirtual #21                 // Method getParsedBootOp:()Lorg/jboss/as/controller/ParsedBootOp;
      63: aload_1
      64: invokevirtual #22                 // Method org/jboss/as/controller/ParsedBootOp.addChildOperation:(Lorg/jboss/as/controller/ParsedBootOp;)V
      67: aload_2
      68: ifnull        75
      71: iconst_1
      72: goto          76
      75: iconst_0
      76: ireturn

  org.jboss.as.controller.ParsedBootOp getParsedBootOp();
    Code:
       0: aload_0
       1: getfield      #23                 // Field ourOp:Lorg/jboss/as/controller/ParsedBootOp;
       4: ifnonnull     36
       7: ldc           #24                 // String parallel-subsystem-boot
       9: new           #25                 // class org/jboss/dmr/ModelNode
      12: dup
      13: invokespecial #26                 // Method org/jboss/dmr/ModelNode."<init>":()V
      16: invokevirtual #27                 // Method org/jboss/dmr/ModelNode.setEmptyList:()Lorg/jboss/dmr/ModelNode;
      19: invokestatic  #28                 // Method org/jboss/as/controller/operations/common/Util.getEmptyOperation:(Ljava/lang/String;Lorg/jboss/dmr/ModelNode;)Lorg/jboss/dmr/ModelNode;
      22: astore_1
      23: aload_0
      24: new           #29                 // class org/jboss/as/controller/ParsedBootOp
      27: dup
      28: aload_1
      29: aload_0
      30: invokespecial #30                 // Method org/jboss/as/controller/ParsedBootOp."<init>":(Lorg/jboss/dmr/ModelNode;Lorg/jboss/as/controller/OperationStepHandler;)V
      33: putfield      #23                 // Field ourOp:Lorg/jboss/as/controller/ParsedBootOp;
      36: aload_0
      37: getfield      #23                 // Field ourOp:Lorg/jboss/as/controller/ParsedBootOp;
      40: areturn

  private java.lang.String getSubsystemName(org.jboss.as.controller.PathAddress);
    Code:
       0: aconst_null
       1: astore_2
       2: aload_1
       3: invokevirtual #31                 // Method org/jboss/as/controller/PathAddress.size:()I
       6: ifle          34
       9: ldc           #33                 // String subsystem
      11: aload_1
      12: iconst_0
      13: invokevirtual #34                 // Method org/jboss/as/controller/PathAddress.getElement:(I)Lorg/jboss/as/controller/PathElement;
      16: invokevirtual #35                 // Method org/jboss/as/controller/PathElement.getKey:()Ljava/lang/String;
      19: invokevirtual #36                 // Method java/lang/String.equals:(Ljava/lang/Object;)Z
      22: ifeq          34
      25: aload_1
      26: iconst_0
      27: invokevirtual #34                 // Method org/jboss/as/controller/PathAddress.getElement:(I)Lorg/jboss/as/controller/PathElement;
      30: invokevirtual #37                 // Method org/jboss/as/controller/PathElement.getValue:()Ljava/lang/String;
      33: astore_2
      34: aload_2
      35: areturn

  public void execute(org.jboss.as.controller.OperationContext, org.jboss.dmr.ModelNode) throws org.jboss.as.controller.OperationFailedException;
    Code:
       0: aload_1
       1: invokeinterface #38,  1           // InterfaceMethod org/jboss/as/controller/OperationContext.isNormalServer:()Z
       6: ifne          22
       9: getstatic     #39                 // Field org/jboss/as/controller/logging/ControllerLogger.ROOT_LOGGER:Lorg/jboss/as/controller/logging/ControllerLogger;
      12: aload_0
      13: invokevirtual #40                 // Method java/lang/Object.getClass:()Ljava/lang/Class;
      16: invokeinterface #41,  2           // InterfaceMethod org/jboss/as/controller/logging/ControllerLogger.fullServerBootRequired:(Ljava/lang/Class;)Ljava/lang/IllegalStateException;
      21: athrow
      22: invokestatic  #42                 // Method java/lang/System.currentTimeMillis:()J
      25: lstore_3
      26: aload_1
      27: invokeinterface #43,  1           // InterfaceMethod org/jboss/as/controller/OperationContext.getResourceRegistrationForUpdate:()Lorg/jboss/as/controller/registry/ManagementResourceRegistration;
      32: pop
      33: aload_1
      34: getstatic     #44                 // Field org/jboss/as/controller/PathAddress.EMPTY_ADDRESS:Lorg/jboss/as/controller/PathAddress;
      37: invokeinterface #45,  2           // InterfaceMethod org/jboss/as/controller/OperationContext.readResourceForUpdate:(Lorg/jboss/as/controller/PathAddress;)Lorg/jboss/as/controller/registry/Resource;
      42: astore        5
      44: aload_1
      45: invokeinterface #46,  1           // InterfaceMethod org/jboss/as/controller/OperationContext.acquireControllerLock:()V
      50: new           #10                 // class java/util/LinkedHashMap
      53: dup
      54: invokespecial #11                 // Method java/util/LinkedHashMap."<init>":()V
      57: astore        6
      59: new           #10                 // class java/util/LinkedHashMap
      62: dup
      63: invokespecial #11                 // Method java/util/LinkedHashMap."<init>":()V
      66: astore        7
      68: new           #47                 // class java/util/concurrent/CountDownLatch
      71: dup
      72: aload_0
      73: getfield      #12                 // Field opsBySubsystem:Ljava/util/Map;
      76: invokeinterface #48,  1           // InterfaceMethod java/util/Map.size:()I
      81: invokespecial #49                 // Method java/util/concurrent/CountDownLatch."<init>":(I)V
      84: astore        8
      86: new           #47                 // class java/util/concurrent/CountDownLatch
      89: dup
      90: iconst_1
      91: invokespecial #49                 // Method java/util/concurrent/CountDownLatch."<init>":(I)V
      94: astore        9
      96: new           #47                 // class java/util/concurrent/CountDownLatch
      99: dup
     100: aload_0
     101: getfield      #12                 // Field opsBySubsystem:Ljava/util/Map;
     104: invokeinterface #48,  1           // InterfaceMethod java/util/Map.size:()I
     109: invokespecial #49                 // Method java/util/concurrent/CountDownLatch."<init>":(I)V
     112: astore        10
     114: invokestatic  #50                 // Method java/lang/Thread.currentThread:()Ljava/lang/Thread;
     117: astore        11
     119: aload_1
     120: instanceof    #51                 // class org/jboss/as/controller/AbstractOperationContext
     123: ifne          135
     126: getstatic     #39                 // Field org/jboss/as/controller/logging/ControllerLogger.ROOT_LOGGER:Lorg/jboss/as/controller/logging/ControllerLogger;
     129: invokeinterface #52,  1           // InterfaceMethod org/jboss/as/controller/logging/ControllerLogger.operationContextIsNotAbstractOperationContext:()Lorg/jboss/as/controller/OperationFailedException;
     134: athrow
     135: aload_0
     136: getfield      #12                 // Field opsBySubsystem:Ljava/util/Map;
     139: invokeinterface #53,  1           // InterfaceMethod java/util/Map.entrySet:()Ljava/util/Set;
     144: invokeinterface #54,  1           // InterfaceMethod java/util/Set.iterator:()Ljava/util/Iterator;
     149: astore        12
     151: aload         12
     153: invokeinterface #55,  1           // InterfaceMethod java/util/Iterator.hasNext:()Z
     158: ifeq          292
     161: aload         12
     163: invokeinterface #56,  1           // InterfaceMethod java/util/Iterator.next:()Ljava/lang/Object;
     168: checkcast     #57                 // class java/util/Map$Entry
     171: astore        13
     173: aload         13
     175: invokeinterface #58,  1           // InterfaceMethod java/util/Map$Entry.getKey:()Ljava/lang/Object;
     180: checkcast     #59                 // class java/lang/String
     183: astore        14
     185: new           #17                 // class java/util/ArrayList
     188: dup
     189: invokespecial #18                 // Method java/util/ArrayList."<init>":()V
     192: astore        15
     194: aload         6
     196: aload         14
     198: aload         15
     200: invokeinterface #19,  3           // InterfaceMethod java/util/Map.put:(Ljava/lang/Object;Ljava/lang/Object;)Ljava/lang/Object;
     205: pop
     206: new           #60                 // class org/jboss/as/controller/ParallelBootOperationStepHandler$ParallelBootTransactionControl
     209: dup
     210: aload         8
     212: aload         9
     214: aload         10
     216: invokespecial #61                 // Method org/jboss/as/controller/ParallelBootOperationStepHandler$ParallelBootTransactionControl."<init>":(Ljava/util/concurrent/CountDownLatch;Ljava/util/concurrent/CountDownLatch;Ljava/util/concurrent/CountDownLatch;)V
     219: astore        16
     221: aload         7
     223: aload         13
     225: invokeinterface #58,  1           // InterfaceMethod java/util/Map$Entry.getKey:()Ljava/lang/Object;
     230: aload         16
     232: invokeinterface #19,  3           // InterfaceMethod java/util/Map.put:(Ljava/lang/Object;Ljava/lang/Object;)Ljava/lang/Object;
     237: pop
     238: new           #62                 // class org/jboss/as/controller/ParallelBootOperationStepHandler$ParallelBootTask
     241: dup
     242: aload_0
     243: aload         14
     245: aload         13
     247: invokeinterface #63,  1           // InterfaceMethod java/util/Map$Entry.getValue:()Ljava/lang/Object;
     252: checkcast     #16                 // class java/util/List
     255: aload_1
     256: checkcast     #64                 // class org/jboss/as/controller/OperationContextImpl
     259: aload         16
     261: aload         15
     263: aload         11
     265: aload_0
     266: getfield      #7                  // Field controller:Lorg/jboss/as/controller/ModelControllerImpl;
     269: aload_0
     270: getfield      #6                  // Field operationId:I
     273: invokespecial #65                 // Method org/jboss/as/controller/ParallelBootOperationStepHandler$ParallelBootTask."<init>":(Lorg/jboss/as/controller/ParallelBootOperationStepHandler;Ljava/lang/String;Ljava/util/List;Lorg/jboss/as/controller/OperationContextImpl;Lorg/jboss/as/controller/ParallelBootOperationStepHandler$ParallelBootTransactionControl;Ljava/util/List;Ljava/lang/Thread;Lorg/jboss/as/controller/ModelControllerImpl;I)V
     276: astore        17
     278: aload_0
     279: getfield      #5                  // Field executor:Ljava/util/concurrent/Executor;
     282: aload         17
     284: invokeinterface #66,  2           // InterfaceMethod java/util/concurrent/Executor.execute:(Ljava/lang/Runnable;)V
     289: goto          151
     292: aload         8
     294: invokevirtual #67                 // Method java/util/concurrent/CountDownLatch.await:()V
     297: aload_0
     298: aload_1
     299: aload         7
     301: getstatic     #68                 // Field org/jboss/as/controller/OperationContext$Stage.MODEL:Lorg/jboss/as/controller/OperationContext$Stage;
     304: invokespecial #4                  // Method checkForSubsystemFailures:(Lorg/jboss/as/controller/OperationContext;Ljava/util/Map;Lorg/jboss/as/controller/OperationContext$Stage;)V
     307: aload         6
     309: ldc           #69                 // String logging
     311: invokeinterface #70,  2           // InterfaceMethod java/util/Map.remove:(Ljava/lang/Object;)Ljava/lang/Object;
     316: checkcast     #16                 // class java/util/List
     319: astore        12
     321: aload         12
     323: ifnull        384
     326: aload         12
     328: invokeinterface #71,  1           // InterfaceMethod java/util/List.iterator:()Ljava/util/Iterator;
     333: astore        13
     335: aload         13
     337: invokeinterface #55,  1           // InterfaceMethod java/util/Iterator.hasNext:()Z
     342: ifeq          384
     345: aload         13
     347: invokeinterface #56,  1           // InterfaceMethod java/util/Iterator.next:()Ljava/lang/Object;
     352: checkcast     #29                 // class org/jboss/as/controller/ParsedBootOp
     355: astore        14
     357: aload_1
     358: aload         14
     360: getfield      #72                 // Field org/jboss/as/controller/ParsedBootOp.response:Lorg/jboss/dmr/ModelNode;
     363: aload         14
     365: getfield      #73                 // Field org/jboss/as/controller/ParsedBootOp.operation:Lorg/jboss/dmr/ModelNode;
     368: aload         14
     370: getfield      #74                 // Field org/jboss/as/controller/ParsedBootOp.handler:Lorg/jboss/as/controller/OperationStepHandler;
     373: getstatic     #75                 // Field org/jboss/as/controller/OperationContext$Stage.RUNTIME:Lorg/jboss/as/controller/OperationContext$Stage;
     376: invokeinterface #76,  5           // InterfaceMethod org/jboss/as/controller/OperationContext.addStep:(Lorg/jboss/dmr/ModelNode;Lorg/jboss/dmr/ModelNode;Lorg/jboss/as/controller/OperationStepHandler;Lorg/jboss/as/controller/OperationContext$Stage;)V
     381: goto          335
     384: new           #10                 // class java/util/LinkedHashMap
     387: dup
     388: invokespecial #11                 // Method java/util/LinkedHashMap."<init>":()V
     391: astore        13
     393: aload_0
     394: getfield      #12                 // Field opsBySubsystem:Ljava/util/Map;
     397: invokeinterface #77,  1           // InterfaceMethod java/util/Map.keySet:()Ljava/util/Set;
     402: invokeinterface #54,  1           // InterfaceMethod java/util/Set.iterator:()Ljava/util/Iterator;
     407: astore        14
     409: aload         14
     411: invokeinterface #55,  1           // InterfaceMethod java/util/Iterator.hasNext:()Z
     416: ifeq          467
     419: aload         14
     421: invokeinterface #56,  1           // InterfaceMethod java/util/Iterator.next:()Ljava/lang/Object;
     426: checkcast     #59                 // class java/lang/String
     429: astore        15
     431: aload         5
     433: ldc           #33                 // String subsystem
     435: aload         15
     437: invokestatic  #78                 // Method org/jboss/as/controller/PathElement.pathElement:(Ljava/lang/String;Ljava/lang/String;)Lorg/jboss/as/controller/PathElement;
     440: invokeinterface #79,  2           // InterfaceMethod org/jboss/as/controller/registry/Resource.removeChild:(Lorg/jboss/as/controller/PathElement;)Lorg/jboss/as/controller/registry/Resource;
     445: astore        16
     447: aload         16
     449: ifnull        464
     452: aload         13
     454: aload         15
     456: aload         16
     458: invokeinterface #19,  3           // InterfaceMethod java/util/Map.put:(Ljava/lang/Object;Ljava/lang/Object;)Ljava/lang/Object;
     463: pop
     464: goto          409
     467: aload         13
     469: invokeinterface #53,  1           // InterfaceMethod java/util/Map.entrySet:()Ljava/util/Set;
     474: invokeinterface #54,  1           // InterfaceMethod java/util/Set.iterator:()Ljava/util/Iterator;
     479: astore        14
     481: aload         14
     483: invokeinterface #55,  1           // InterfaceMethod java/util/Iterator.hasNext:()Z
     488: ifeq          538
     491: aload         14
     493: invokeinterface #56,  1           // InterfaceMethod java/util/Iterator.next:()Ljava/lang/Object;
     498: checkcast     #57                 // class java/util/Map$Entry
     501: astore        15
     503: aload         5
     505: ldc           #33                 // String subsystem
     507: aload         15
     509: invokeinterface #58,  1           // InterfaceMethod java/util/Map$Entry.getKey:()Ljava/lang/Object;
     514: checkcast     #59                 // class java/lang/String
     517: invokestatic  #78                 // Method org/jboss/as/controller/PathElement.pathElement:(Ljava/lang/String;Ljava/lang/String;)Lorg/jboss/as/controller/PathElement;
     520: aload         15
     522: invokeinterface #63,  1           // InterfaceMethod java/util/Map$Entry.getValue:()Ljava/lang/Object;
     527: checkcast     #80                 // class org/jboss/as/controller/registry/Resource
     530: invokeinterface #81,  3           // InterfaceMethod org/jboss/as/controller/registry/Resource.registerChild:(Lorg/jboss/as/controller/PathElement;Lorg/jboss/as/controller/registry/Resource;)V
     535: goto          481
     538: aload_1
     539: aload_0
     540: aload         6
     542: invokespecial #82                 // Method getRuntimeStep:(Ljava/util/Map;)Lorg/jboss/as/controller/OperationStepHandler;
     545: getstatic     #75                 // Field org/jboss/as/controller/OperationContext$Stage.RUNTIME:Lorg/jboss/as/controller/OperationContext$Stage;
     548: invokeinterface #83,  3           // InterfaceMethod org/jboss/as/controller/OperationContext.addStep:(Lorg/jboss/as/controller/OperationStepHandler;Lorg/jboss/as/controller/OperationContext$Stage;)V
     553: goto          592
     556: astore        12
     558: aload_1
     559: invokeinterface #85,  1           // InterfaceMethod org/jboss/as/controller/OperationContext.getFailureDescription:()Lorg/jboss/dmr/ModelNode;
     564: new           #25                 // class org/jboss/dmr/ModelNode
     567: dup
     568: invokespecial #26                 // Method org/jboss/dmr/ModelNode."<init>":()V
     571: getstatic     #39                 // Field org/jboss/as/controller/logging/ControllerLogger.ROOT_LOGGER:Lorg/jboss/as/controller/logging/ControllerLogger;
     574: invokeinterface #86,  1           // InterfaceMethod org/jboss/as/controller/logging/ControllerLogger.subsystemBootInterrupted:()Ljava/lang/String;
     579: invokevirtual #87                 // Method org/jboss/dmr/ModelNode.set:(Ljava/lang/String;)Lorg/jboss/dmr/ModelNode;
     582: invokevirtual #88                 // Method org/jboss/dmr/ModelNode.set:(Lorg/jboss/dmr/ModelNode;)Lorg/jboss/dmr/ModelNode;
     585: pop
     586: invokestatic  #50                 // Method java/lang/Thread.currentThread:()Ljava/lang/Thread;
     589: invokevirtual #89                 // Method java/lang/Thread.interrupt:()V
     592: getstatic     #90                 // Field org/jboss/as/controller/logging/ControllerLogger.MGMT_OP_LOGGER:Lorg/jboss/as/controller/logging/ControllerLogger;
     595: invokeinterface #91,  1           // InterfaceMethod org/jboss/as/controller/logging/ControllerLogger.isDebugEnabled:()Z
     600: ifeq          622
     603: invokestatic  #42                 // Method java/lang/System.currentTimeMillis:()J
     606: lload_3
     607: lsub
     608: lstore        12
     610: getstatic     #90                 // Field org/jboss/as/controller/logging/ControllerLogger.MGMT_OP_LOGGER:Lorg/jboss/as/controller/logging/ControllerLogger;
     613: ldc           #92                 // String Ran subsystem model operations in [%d] ms
     615: lload         12
     617: invokeinterface #93,  4           // InterfaceMethod org/jboss/as/controller/logging/ControllerLogger.debugf:(Ljava/lang/String;J)V
     622: aload_1
     623: new           #94                 // class org/jboss/as/controller/ParallelBootOperationStepHandler$1
     626: dup
     627: aload_0
     628: aload         7
     630: aload         9
     632: aload         10
     634: invokespecial #95                 // Method org/jboss/as/controller/ParallelBootOperationStepHandler$1."<init>":(Lorg/jboss/as/controller/ParallelBootOperationStepHandler;Ljava/util/Map;Ljava/util/concurrent/CountDownLatch;Ljava/util/concurrent/CountDownLatch;)V
     637: invokeinterface #96,  2           // InterfaceMethod org/jboss/as/controller/OperationContext.completeStep:(Lorg/jboss/as/controller/OperationContext$ResultHandler;)V
     642: return
    Exception table:
       from    to  target type
         292   553   556   Class java/lang/InterruptedException

  private void checkForSubsystemFailures(org.jboss.as.controller.OperationContext, java.util.Map<java.lang.String, org.jboss.as.controller.ParallelBootOperationStepHandler$ParallelBootTransactionControl>, org.jboss.as.controller.OperationContext$Stage);
    Code:
       0: iconst_0
       1: istore        4
       3: aload_2
       4: invokeinterface #53,  1           // InterfaceMethod java/util/Map.entrySet:()Ljava/util/Set;
       9: invokeinterface #54,  1           // InterfaceMethod java/util/Set.iterator:()Ljava/util/Iterator;
      14: astore        5
      16: aload         5
      18: invokeinterface #55,  1           // InterfaceMethod java/util/Iterator.hasNext:()Z
      23: ifeq          173
      26: aload         5
      28: invokeinterface #56,  1           // InterfaceMethod java/util/Iterator.next:()Ljava/lang/Object;
      33: checkcast     #57                 // class java/util/Map$Entry
      36: astore        6
      38: aload         6
      40: invokeinterface #63,  1           // InterfaceMethod java/util/Map$Entry.getValue:()Ljava/lang/Object;
      45: checkcast     #60                 // class org/jboss/as/controller/ParallelBootOperationStepHandler$ParallelBootTransactionControl
      48: astore        7
      50: aload         7
      52: invokestatic  #97                 // Method org/jboss/as/controller/ParallelBootOperationStepHandler$ParallelBootTransactionControl.access$100:(Lorg/jboss/as/controller/ParallelBootOperationStepHandler$ParallelBootTransactionControl;)Lorg/jboss/as/controller/ModelController$OperationTransaction;
      55: ifnonnull     152
      58: aload         7
      60: invokestatic  #98                 // Method org/jboss/as/controller/ParallelBootOperationStepHandler$ParallelBootTransactionControl.access$200:(Lorg/jboss/as/controller/ParallelBootOperationStepHandler$ParallelBootTransactionControl;)Lorg/jboss/as/controller/client/OperationResponse;
      63: invokeinterface #99,  1           // InterfaceMethod org/jboss/as/controller/client/OperationResponse.getResponseNode:()Lorg/jboss/dmr/ModelNode;
      68: ldc           #100                // String failure-description
      70: invokevirtual #101                // Method org/jboss/dmr/ModelNode.hasDefined:(Ljava/lang/String;)Z
      73: ifeq          99
      76: aload         7
      78: invokestatic  #98                 // Method org/jboss/as/controller/ParallelBootOperationStepHandler$ParallelBootTransactionControl.access$200:(Lorg/jboss/as/controller/ParallelBootOperationStepHandler$ParallelBootTransactionControl;)Lorg/jboss/as/controller/client/OperationResponse;
      81: invokeinterface #99,  1           // InterfaceMethod org/jboss/as/controller/client/OperationResponse.getResponseNode:()Lorg/jboss/dmr/ModelNode;
      86: ldc           #100                // String failure-description
      88: invokevirtual #102                // Method org/jboss/dmr/ModelNode.get:(Ljava/lang/String;)Lorg/jboss/dmr/ModelNode;
      91: invokevirtual #103                // Method org/jboss/dmr/ModelNode.toString:()Ljava/lang/String;
      94: astore        8
      96: goto          119
      99: getstatic     #39                 // Field org/jboss/as/controller/logging/ControllerLogger.ROOT_LOGGER:Lorg/jboss/as/controller/logging/ControllerLogger;
     102: aload         6
     104: invokeinterface #58,  1           // InterfaceMethod java/util/Map$Entry.getKey:()Ljava/lang/Object;
     109: checkcast     #59                 // class java/lang/String
     112: invokeinterface #104,  2          // InterfaceMethod org/jboss/as/controller/logging/ControllerLogger.subsystemBootOperationFailed:(Ljava/lang/String;)Ljava/lang/String;
     117: astore        8
     119: getstatic     #90                 // Field org/jboss/as/controller/logging/ControllerLogger.MGMT_OP_LOGGER:Lorg/jboss/as/controller/logging/ControllerLogger;
     122: aload         8
     124: invokeinterface #105,  2          // InterfaceMethod org/jboss/as/controller/logging/ControllerLogger.error:(Ljava/lang/Object;)V
     129: iload         4
     131: ifne          149
     134: aload_1
     135: invokeinterface #85,  1           // InterfaceMethod org/jboss/as/controller/OperationContext.getFailureDescription:()Lorg/jboss/dmr/ModelNode;
     140: aload         8
     142: invokevirtual #87                 // Method org/jboss/dmr/ModelNode.set:(Ljava/lang/String;)Lorg/jboss/dmr/ModelNode;
     145: pop
     146: iconst_1
     147: istore        4
     149: goto          170
     152: getstatic     #90                 // Field org/jboss/as/controller/logging/ControllerLogger.MGMT_OP_LOGGER:Lorg/jboss/as/controller/logging/ControllerLogger;
     155: ldc           #106                // String Stage %s boot ops for subsystem %s succeeded
     157: aload_3
     158: aload         6
     160: invokeinterface #58,  1           // InterfaceMethod java/util/Map$Entry.getKey:()Ljava/lang/Object;
     165: invokeinterface #107,  4          // InterfaceMethod org/jboss/as/controller/logging/ControllerLogger.debugf:(Ljava/lang/String;Ljava/lang/Object;Ljava/lang/Object;)V
     170: goto          16
     173: return

  private void notifySubsystemTransactions(java.util.Map<java.lang.String, org.jboss.as.controller.ParallelBootOperationStepHandler$ParallelBootTransactionControl>, boolean, java.util.concurrent.CountDownLatch, org.jboss.as.controller.OperationContext$Stage);
    Code:
       0: aload_1
       1: invokeinterface #53,  1           // InterfaceMethod java/util/Map.entrySet:()Ljava/util/Set;
       6: invokeinterface #54,  1           // InterfaceMethod java/util/Set.iterator:()Ljava/util/Iterator;
      11: astore        5
      13: aload         5
      15: invokeinterface #55,  1           // InterfaceMethod java/util/Iterator.hasNext:()Z
      20: ifeq          123
      23: aload         5
      25: invokeinterface #56,  1           // InterfaceMethod java/util/Iterator.next:()Ljava/lang/Object;
      30: checkcast     #57                 // class java/util/Map$Entry
      33: astore        6
      35: aload         6
      37: invokeinterface #63,  1           // InterfaceMethod java/util/Map$Entry.getValue:()Ljava/lang/Object;
      42: checkcast     #60                 // class org/jboss/as/controller/ParallelBootOperationStepHandler$ParallelBootTransactionControl
      45: astore        7
      47: aload         7
      49: invokestatic  #97                 // Method org/jboss/as/controller/ParallelBootOperationStepHandler$ParallelBootTransactionControl.access$100:(Lorg/jboss/as/controller/ParallelBootOperationStepHandler$ParallelBootTransactionControl;)Lorg/jboss/as/controller/ModelController$OperationTransaction;
      52: ifnull        120
      55: iload_2
      56: ifne          91
      59: aload         7
      61: invokestatic  #97                 // Method org/jboss/as/controller/ParallelBootOperationStepHandler$ParallelBootTransactionControl.access$100:(Lorg/jboss/as/controller/ParallelBootOperationStepHandler$ParallelBootTransactionControl;)Lorg/jboss/as/controller/ModelController$OperationTransaction;
      64: invokeinterface #108,  1          // InterfaceMethod org/jboss/as/controller/ModelController$OperationTransaction.commit:()V
      69: getstatic     #90                 // Field org/jboss/as/controller/logging/ControllerLogger.MGMT_OP_LOGGER:Lorg/jboss/as/controller/logging/ControllerLogger;
      72: ldc           #109                // String Committed transaction for %s subsystem %s stage boot operations
      74: aload         6
      76: invokeinterface #58,  1           // InterfaceMethod java/util/Map$Entry.getKey:()Ljava/lang/Object;
      81: aload         4
      83: invokeinterface #107,  4          // InterfaceMethod org/jboss/as/controller/logging/ControllerLogger.debugf:(Ljava/lang/String;Ljava/lang/Object;Ljava/lang/Object;)V
      88: goto          120
      91: aload         7
      93: invokestatic  #97                 // Method org/jboss/as/controller/ParallelBootOperationStepHandler$ParallelBootTransactionControl.access$100:(Lorg/jboss/as/controller/ParallelBootOperationStepHandler$ParallelBootTransactionControl;)Lorg/jboss/as/controller/ModelController$OperationTransaction;
      96: invokeinterface #110,  1          // InterfaceMethod org/jboss/as/controller/ModelController$OperationTransaction.rollback:()V
     101: getstatic     #90                 // Field org/jboss/as/controller/logging/ControllerLogger.MGMT_OP_LOGGER:Lorg/jboss/as/controller/logging/ControllerLogger;
     104: ldc           #111                // String Rolled back transaction for %s subsystem %s stage boot operations
     106: aload         6
     108: invokeinterface #58,  1           // InterfaceMethod java/util/Map$Entry.getKey:()Ljava/lang/Object;
     113: aload         4
     115: invokeinterface #107,  4          // InterfaceMethod org/jboss/as/controller/logging/ControllerLogger.debugf:(Ljava/lang/String;Ljava/lang/Object;Ljava/lang/Object;)V
     120: goto          13
     123: aload_3
     124: invokevirtual #112                // Method java/util/concurrent/CountDownLatch.countDown:()V
     127: return

  private org.jboss.as.controller.OperationStepHandler getRuntimeStep(java.util.Map<java.lang.String, java.util.List<org.jboss.as.controller.ParsedBootOp>>);
    Code:
       0: new           #113                // class org/jboss/as/controller/ParallelBootOperationStepHandler$2
       3: dup
       4: aload_0
       5: aload_1
       6: invokespecial #114                // Method org/jboss/as/controller/ParallelBootOperationStepHandler$2."<init>":(Lorg/jboss/as/controller/ParallelBootOperationStepHandler;Ljava/util/Map;)V
       9: areturn

  static void access$000(org.jboss.as.controller.ParallelBootOperationStepHandler, java.util.Map, boolean, java.util.concurrent.CountDownLatch, org.jboss.as.controller.OperationContext$Stage);
    Code:
       0: aload_0
       1: aload_1
       2: iload_2
       3: aload_3
       4: aload         4
       6: invokespecial #8                  // Method notifySubsystemTransactions:(Ljava/util/Map;ZLjava/util/concurrent/CountDownLatch;Lorg/jboss/as/controller/OperationContext$Stage;)V
       9: return

  static org.jboss.as.controller.ModelControllerImpl access$300(org.jboss.as.controller.ParallelBootOperationStepHandler);
    Code:
       0: aload_0
       1: getfield      #7                  // Field controller:Lorg/jboss/as/controller/ModelControllerImpl;
       4: areturn

  static int access$400(org.jboss.as.controller.ParallelBootOperationStepHandler);
    Code:
       0: aload_0
       1: getfield      #6                  // Field operationId:I
       4: ireturn

  static java.util.concurrent.Executor access$500(org.jboss.as.controller.ParallelBootOperationStepHandler);
    Code:
       0: aload_0
       1: getfield      #5                  // Field executor:Ljava/util/concurrent/Executor;
       4: areturn

  static void access$600(org.jboss.as.controller.ParallelBootOperationStepHandler, org.jboss.as.controller.OperationContext, java.util.Map, org.jboss.as.controller.OperationContext$Stage);
    Code:
       0: aload_0
       1: aload_1
       2: aload_2
       3: aload_3
       4: invokespecial #4                  // Method checkForSubsystemFailures:(Lorg/jboss/as/controller/OperationContext;Ljava/util/Map;Lorg/jboss/as/controller/OperationContext$Stage;)V
       7: return

  static org.jboss.as.controller.ControlledProcessState access$700(org.jboss.as.controller.ParallelBootOperationStepHandler);
    Code:
       0: aload_0
       1: getfield      #3                  // Field processState:Lorg/jboss/as/controller/ControlledProcessState;
       4: areturn

  static org.jboss.as.controller.OperationStepHandler access$800(org.jboss.as.controller.ParallelBootOperationStepHandler);
    Code:
       0: aload_0
       1: getfield      #2                  // Field extraValidationStepHandler:Lorg/jboss/as/controller/OperationStepHandler;
       4: areturn

  static org.jboss.as.controller.registry.ImmutableManagementResourceRegistration access$900(org.jboss.as.controller.ParallelBootOperationStepHandler);
    Code:
       0: aload_0
       1: getfield      #1                  // Field rootRegistration:Lorg/jboss/as/controller/registry/ImmutableManagementResourceRegistration;
       4: areturn
}
