Compiled from "ParsedBootOp.java"
public class org.jboss.as.controller.ParsedBootOp {
  public final org.jboss.dmr.ModelNode operation;

  public final java.lang.String operationName;

  public final org.jboss.as.controller.PathAddress address;

  public final org.jboss.as.controller.OperationStepHandler handler;

  public final org.jboss.dmr.ModelNode response;

  private java.util.List<org.jboss.dmr.ModelNode> childOperations;

  org.jboss.as.controller.ParsedBootOp(org.jboss.dmr.ModelNode);
    Code:
       0: aload_0
       1: aload_1
       2: aconst_null
       3: new           #2                  // class org/jboss/dmr/ModelNode
       6: dup
       7: invokespecial #3                  // Method org/jboss/dmr/ModelNode."<init>":()V
      10: invokespecial #4                  // Method "<init>":(Lorg/jboss/dmr/ModelNode;Lorg/jboss/as/controller/OperationStepHandler;Lorg/jboss/dmr/ModelNode;)V
      13: return

  public org.jboss.as.controller.ParsedBootOp(org.jboss.dmr.ModelNode, org.jboss.as.controller.OperationStepHandler);
    Code:
       0: aload_0
       1: aload_1
       2: aload_2
       3: new           #2                  // class org/jboss/dmr/ModelNode
       6: dup
       7: invokespecial #3                  // Method org/jboss/dmr/ModelNode."<init>":()V
      10: invokespecial #4                  // Method "<init>":(Lorg/jboss/dmr/ModelNode;Lorg/jboss/as/controller/OperationStepHandler;Lorg/jboss/dmr/ModelNode;)V
      13: return

  org.jboss.as.controller.ParsedBootOp(org.jboss.dmr.ModelNode, org.jboss.as.controller.OperationStepHandler, org.jboss.dmr.ModelNode);
    Code:
       0: aload_0
       1: invokespecial #5                  // Method java/lang/Object."<init>":()V
       4: aload_0
       5: aload_1
       6: putfield      #6                  // Field operation:Lorg/jboss/dmr/ModelNode;
       9: aload_0
      10: aload_1
      11: ldc           #7                  // String address
      13: invokevirtual #8                  // Method org/jboss/dmr/ModelNode.get:(Ljava/lang/String;)Lorg/jboss/dmr/ModelNode;
      16: invokestatic  #9                  // Method org/jboss/as/controller/PathAddress.pathAddress:(Lorg/jboss/dmr/ModelNode;)Lorg/jboss/as/controller/PathAddress;
      19: putfield      #10                 // Field address:Lorg/jboss/as/controller/PathAddress;
      22: aload_0
      23: aload_1
      24: ldc           #11                 // String operation
      26: invokevirtual #12                 // Method org/jboss/dmr/ModelNode.require:(Ljava/lang/String;)Lorg/jboss/dmr/ModelNode;
      29: invokevirtual #13                 // Method org/jboss/dmr/ModelNode.asString:()Ljava/lang/String;
      32: putfield      #14                 // Field operationName:Ljava/lang/String;
      35: aload_0
      36: aload_2
      37: putfield      #15                 // Field handler:Lorg/jboss/as/controller/OperationStepHandler;
      40: aload_0
      41: aload_3
      42: putfield      #16                 // Field response:Lorg/jboss/dmr/ModelNode;
      45: return

  public org.jboss.as.controller.ParsedBootOp(org.jboss.as.controller.ParsedBootOp, org.jboss.as.controller.OperationStepHandler);
    Code:
       0: aload_0
       1: invokespecial #5                  // Method java/lang/Object."<init>":()V
       4: aload_0
       5: aload_1
       6: getfield      #6                  // Field operation:Lorg/jboss/dmr/ModelNode;
       9: putfield      #6                  // Field operation:Lorg/jboss/dmr/ModelNode;
      12: aload_0
      13: aload_1
      14: getfield      #10                 // Field address:Lorg/jboss/as/controller/PathAddress;
      17: putfield      #10                 // Field address:Lorg/jboss/as/controller/PathAddress;
      20: aload_0
      21: aload_1
      22: getfield      #14                 // Field operationName:Ljava/lang/String;
      25: putfield      #14                 // Field operationName:Ljava/lang/String;
      28: aload_0
      29: aload_2
      30: putfield      #15                 // Field handler:Lorg/jboss/as/controller/OperationStepHandler;
      33: aload_0
      34: aload_1
      35: getfield      #16                 // Field response:Lorg/jboss/dmr/ModelNode;
      38: putfield      #16                 // Field response:Lorg/jboss/dmr/ModelNode;
      41: return

  public void addChildOperation(org.jboss.as.controller.ParsedBootOp);
    Code:
       0: aload_0
       1: getfield      #17                 // Field childOperations:Ljava/util/List;
       4: ifnonnull     18
       7: aload_0
       8: new           #18                 // class java/util/ArrayList
      11: dup
      12: invokespecial #19                 // Method java/util/ArrayList."<init>":()V
      15: putfield      #17                 // Field childOperations:Ljava/util/List;
      18: aload_0
      19: getfield      #17                 // Field childOperations:Ljava/util/List;
      22: aload_1
      23: getfield      #6                  // Field operation:Lorg/jboss/dmr/ModelNode;
      26: invokeinterface #20,  2           // InterfaceMethod java/util/List.add:(Ljava/lang/Object;)Z
      31: pop
      32: return

  boolean isExtensionAdd();
    Code:
       0: aload_0
       1: getfield      #10                 // Field address:Lorg/jboss/as/controller/PathAddress;
       4: invokevirtual #21                 // Method org/jboss/as/controller/PathAddress.size:()I
       7: iconst_1
       8: if_icmpne     46
      11: aload_0
      12: getfield      #10                 // Field address:Lorg/jboss/as/controller/PathAddress;
      15: iconst_0
      16: invokevirtual #22                 // Method org/jboss/as/controller/PathAddress.getElement:(I)Lorg/jboss/as/controller/PathElement;
      19: invokevirtual #23                 // Method org/jboss/as/controller/PathElement.getKey:()Ljava/lang/String;
      22: ldc           #24                 // String extension
      24: invokevirtual #25                 // Method java/lang/String.equals:(Ljava/lang/Object;)Z
      27: ifeq          46
      30: aload_0
      31: getfield      #14                 // Field operationName:Ljava/lang/String;
      34: ldc           #26                 // String add
      36: invokevirtual #25                 // Method java/lang/String.equals:(Ljava/lang/Object;)Z
      39: ifeq          46
      42: iconst_1
      43: goto          47
      46: iconst_0
      47: ireturn

  boolean isInterfaceOperation();
    Code:
       0: aload_0
       1: getfield      #10                 // Field address:Lorg/jboss/as/controller/PathAddress;
       4: invokevirtual #21                 // Method org/jboss/as/controller/PathAddress.size:()I
       7: ifle          33
      10: aload_0
      11: getfield      #10                 // Field address:Lorg/jboss/as/controller/PathAddress;
      14: iconst_0
      15: invokevirtual #22                 // Method org/jboss/as/controller/PathAddress.getElement:(I)Lorg/jboss/as/controller/PathElement;
      18: invokevirtual #23                 // Method org/jboss/as/controller/PathElement.getKey:()Ljava/lang/String;
      21: ldc           #27                 // String interface
      23: invokevirtual #25                 // Method java/lang/String.equals:(Ljava/lang/Object;)Z
      26: ifeq          33
      29: iconst_1
      30: goto          34
      33: iconst_0
      34: ireturn

  boolean isSocketOperation();
    Code:
       0: aload_0
       1: getfield      #10                 // Field address:Lorg/jboss/as/controller/PathAddress;
       4: invokevirtual #21                 // Method org/jboss/as/controller/PathAddress.size:()I
       7: ifle          33
      10: aload_0
      11: getfield      #10                 // Field address:Lorg/jboss/as/controller/PathAddress;
      14: iconst_0
      15: invokevirtual #22                 // Method org/jboss/as/controller/PathAddress.getElement:(I)Lorg/jboss/as/controller/PathElement;
      18: invokevirtual #23                 // Method org/jboss/as/controller/PathElement.getKey:()Ljava/lang/String;
      21: ldc           #28                 // String socket-binding-group
      23: invokevirtual #25                 // Method java/lang/String.equals:(Ljava/lang/Object;)Z
      26: ifeq          33
      29: iconst_1
      30: goto          34
      33: iconst_0
      34: ireturn

  java.util.List<org.jboss.dmr.ModelNode> getChildOperations();
    Code:
       0: aload_0
       1: getfield      #17                 // Field childOperations:Ljava/util/List;
       4: ifnonnull     13
       7: invokestatic  #29                 // Method java/util/Collections.emptyList:()Ljava/util/List;
      10: goto          17
      13: aload_0
      14: getfield      #17                 // Field childOperations:Ljava/util/List;
      17: areturn
}
