Compiled from "ReloadRequiredAddStepHandler.java"
public class org.jboss.as.controller.ReloadRequiredAddStepHandler extends org.jboss.as.controller.AbstractAddStepHandler {
  public org.jboss.as.controller.ReloadRequiredAddStepHandler(org.jboss.as.controller.AttributeDefinition...);
    Code:
       0: aload_0
       1: aload_1
       2: invokespecial #1                  // Method org/jboss/as/controller/AbstractAddStepHandler."<init>":([Lorg/jboss/as/controller/AttributeDefinition;)V
       5: return

  public org.jboss.as.controller.ReloadRequiredAddStepHandler(java.util.Collection<org.jboss.as.controller.AttributeDefinition>);
    Code:
       0: aload_0
       1: aload_1
       2: invokespecial #2                  // Method org/jboss/as/controller/AbstractAddStepHandler."<init>":(Ljava/util/Collection;)V
       5: return

  public org.jboss.as.controller.ReloadRequiredAddStepHandler(org.jboss.as.controller.capability.RuntimeCapability, org.jboss.as.controller.AttributeDefinition...);
    Code:
       0: aload_0
       1: aload_1
       2: aload_2
       3: invokespecial #3                  // Method org/jboss/as/controller/AbstractAddStepHandler."<init>":(Lorg/jboss/as/controller/capability/RuntimeCapability;[Lorg/jboss/as/controller/AttributeDefinition;)V
       6: return

  public org.jboss.as.controller.ReloadRequiredAddStepHandler(java.util.Set<org.jboss.as.controller.capability.RuntimeCapability>, java.util.Collection<org.jboss.as.controller.AttributeDefinition>);
    Code:
       0: aload_0
       1: aload_1
       2: aload_2
       3: invokespecial #4                  // Method org/jboss/as/controller/AbstractAddStepHandler."<init>":(Ljava/util/Set;Ljava/util/Collection;)V
       6: return

  public org.jboss.as.controller.ReloadRequiredAddStepHandler(org.jboss.as.controller.AbstractAddStepHandler$Parameters);
    Code:
       0: aload_0
       1: aload_1
       2: invokespecial #5                  // Method org/jboss/as/controller/AbstractAddStepHandler."<init>":(Lorg/jboss/as/controller/AbstractAddStepHandler$Parameters;)V
       5: return

  protected boolean requiresRuntime(org.jboss.as.controller.OperationContext);
    Code:
       0: aload_1
       1: invokeinterface #6,  1            // InterfaceMethod org/jboss/as/controller/OperationContext.isBooting:()Z
       6: ifne          21
       9: aload_0
      10: aload_1
      11: invokespecial #7                  // Method org/jboss/as/controller/AbstractAddStepHandler.requiresRuntime:(Lorg/jboss/as/controller/OperationContext;)Z
      14: ifeq          21
      17: iconst_1
      18: goto          22
      21: iconst_0
      22: ireturn

  protected void performRuntime(org.jboss.as.controller.OperationContext, org.jboss.dmr.ModelNode, org.jboss.as.controller.registry.Resource);
    Code:
       0: aload_1
       1: invokeinterface #8,  1            // InterfaceMethod org/jboss/as/controller/OperationContext.reloadRequired:()V
       6: return

  protected void rollbackRuntime(org.jboss.as.controller.OperationContext, org.jboss.dmr.ModelNode, org.jboss.as.controller.registry.Resource);
    Code:
       0: aload_1
       1: invokeinterface #9,  1            // InterfaceMethod org/jboss/as/controller/OperationContext.revertReloadRequired:()V
       6: return
}
