Compiled from "SimpleAttributeDefinition.java"
public class org.jboss.as.controller.SimpleAttributeDefinition extends org.jboss.as.controller.AttributeDefinition {
  public org.jboss.as.controller.SimpleAttributeDefinition(java.lang.String, org.jboss.dmr.ModelType, boolean);
    Code:
       0: aload_0
       1: aload_1
       2: aload_1
       3: aconst_null
       4: aload_2
       5: iload_3
       6: iconst_0
       7: aconst_null
       8: aconst_null
       9: aconst_null
      10: iconst_1
      11: aconst_null
      12: aconst_null
      13: aconst_null
      14: iconst_0
      15: aconst_null
      16: aconst_null
      17: aconst_null
      18: aconst_null
      19: iconst_0
      20: anewarray     #1                  // class org/jboss/as/controller/registry/AttributeAccess$Flag
      23: invokespecial #2                  // Method org/jboss/as/controller/AttributeDefinition."<init>":(Ljava/lang/String;Ljava/lang/String;Lorg/jboss/dmr/ModelNode;Lorg/jboss/dmr/ModelType;ZZLorg/jboss/as/controller/client/helpers/MeasurementUnit;Lorg/jboss/as/controller/ParameterCorrector;Lorg/jboss/as/controller/operations/validation/ParameterValidator;Z[Ljava/lang/String;[Ljava/lang/String;Lorg/jboss/as/controller/AttributeMarshaller;ZLorg/jboss/as/controller/DeprecationData;[Lorg/jboss/as/controller/access/management/AccessConstraintDefinition;Ljava/lang/Boolean;Lorg/jboss/as/controller/AttributeParser;[Lorg/jboss/as/controller/registry/AttributeAccess$Flag;)V
      26: return

  public org.jboss.as.controller.SimpleAttributeDefinition(java.lang.String, org.jboss.dmr.ModelType, boolean, org.jboss.as.controller.registry.AttributeAccess$Flag...);
    Code:
       0: aload_0
       1: aload_1
       2: aload_1
       3: aconst_null
       4: aload_2
       5: iload_3
       6: iconst_0
       7: aconst_null
       8: aconst_null
       9: aconst_null
      10: iconst_1
      11: aconst_null
      12: aconst_null
      13: aconst_null
      14: iconst_0
      15: aconst_null
      16: aconst_null
      17: aconst_null
      18: aconst_null
      19: aload         4
      21: invokespecial #2                  // Method org/jboss/as/controller/AttributeDefinition."<init>":(Ljava/lang/String;Ljava/lang/String;Lorg/jboss/dmr/ModelNode;Lorg/jboss/dmr/ModelType;ZZLorg/jboss/as/controller/client/helpers/MeasurementUnit;Lorg/jboss/as/controller/ParameterCorrector;Lorg/jboss/as/controller/operations/validation/ParameterValidator;Z[Ljava/lang/String;[Ljava/lang/String;Lorg/jboss/as/controller/AttributeMarshaller;ZLorg/jboss/as/controller/DeprecationData;[Lorg/jboss/as/controller/access/management/AccessConstraintDefinition;Ljava/lang/Boolean;Lorg/jboss/as/controller/AttributeParser;[Lorg/jboss/as/controller/registry/AttributeAccess$Flag;)V
      24: return

  public org.jboss.as.controller.SimpleAttributeDefinition(java.lang.String, org.jboss.dmr.ModelType, boolean, org.jboss.as.controller.client.helpers.MeasurementUnit);
    Code:
       0: aload_0
       1: aload_1
       2: aload_1
       3: aconst_null
       4: aload_2
       5: iload_3
       6: iconst_0
       7: aload         4
       9: aconst_null
      10: aconst_null
      11: iconst_1
      12: aconst_null
      13: aconst_null
      14: aconst_null
      15: iconst_0
      16: aconst_null
      17: aconst_null
      18: aconst_null
      19: aconst_null
      20: iconst_0
      21: anewarray     #1                  // class org/jboss/as/controller/registry/AttributeAccess$Flag
      24: invokespecial #2                  // Method org/jboss/as/controller/AttributeDefinition."<init>":(Ljava/lang/String;Ljava/lang/String;Lorg/jboss/dmr/ModelNode;Lorg/jboss/dmr/ModelType;ZZLorg/jboss/as/controller/client/helpers/MeasurementUnit;Lorg/jboss/as/controller/ParameterCorrector;Lorg/jboss/as/controller/operations/validation/ParameterValidator;Z[Ljava/lang/String;[Ljava/lang/String;Lorg/jboss/as/controller/AttributeMarshaller;ZLorg/jboss/as/controller/DeprecationData;[Lorg/jboss/as/controller/access/management/AccessConstraintDefinition;Ljava/lang/Boolean;Lorg/jboss/as/controller/AttributeParser;[Lorg/jboss/as/controller/registry/AttributeAccess$Flag;)V
      27: return

  public org.jboss.as.controller.SimpleAttributeDefinition(java.lang.String, org.jboss.dmr.ModelType, boolean, org.jboss.as.controller.client.helpers.MeasurementUnit, org.jboss.as.controller.registry.AttributeAccess$Flag...);
    Code:
       0: aload_0
       1: aload_1
       2: aload_1
       3: aconst_null
       4: aload_2
       5: iload_3
       6: iconst_0
       7: aload         4
       9: aconst_null
      10: aconst_null
      11: iconst_1
      12: aconst_null
      13: aconst_null
      14: aconst_null
      15: iconst_0
      16: aconst_null
      17: aconst_null
      18: aconst_null
      19: aconst_null
      20: aload         5
      22: invokespecial #2                  // Method org/jboss/as/controller/AttributeDefinition."<init>":(Ljava/lang/String;Ljava/lang/String;Lorg/jboss/dmr/ModelNode;Lorg/jboss/dmr/ModelType;ZZLorg/jboss/as/controller/client/helpers/MeasurementUnit;Lorg/jboss/as/controller/ParameterCorrector;Lorg/jboss/as/controller/operations/validation/ParameterValidator;Z[Ljava/lang/String;[Ljava/lang/String;Lorg/jboss/as/controller/AttributeMarshaller;ZLorg/jboss/as/controller/DeprecationData;[Lorg/jboss/as/controller/access/management/AccessConstraintDefinition;Ljava/lang/Boolean;Lorg/jboss/as/controller/AttributeParser;[Lorg/jboss/as/controller/registry/AttributeAccess$Flag;)V
      25: return

  public org.jboss.as.controller.SimpleAttributeDefinition(java.lang.String, org.jboss.dmr.ModelNode, org.jboss.dmr.ModelType, boolean);
    Code:
       0: aload_0
       1: aload_1
       2: aload_1
       3: aload_2
       4: aload_3
       5: iload         4
       7: iconst_0
       8: aconst_null
       9: aconst_null
      10: aconst_null
      11: iconst_1
      12: aconst_null
      13: aconst_null
      14: aconst_null
      15: iconst_0
      16: aconst_null
      17: aconst_null
      18: aconst_null
      19: aconst_null
      20: iconst_0
      21: anewarray     #1                  // class org/jboss/as/controller/registry/AttributeAccess$Flag
      24: invokespecial #2                  // Method org/jboss/as/controller/AttributeDefinition."<init>":(Ljava/lang/String;Ljava/lang/String;Lorg/jboss/dmr/ModelNode;Lorg/jboss/dmr/ModelType;ZZLorg/jboss/as/controller/client/helpers/MeasurementUnit;Lorg/jboss/as/controller/ParameterCorrector;Lorg/jboss/as/controller/operations/validation/ParameterValidator;Z[Ljava/lang/String;[Ljava/lang/String;Lorg/jboss/as/controller/AttributeMarshaller;ZLorg/jboss/as/controller/DeprecationData;[Lorg/jboss/as/controller/access/management/AccessConstraintDefinition;Ljava/lang/Boolean;Lorg/jboss/as/controller/AttributeParser;[Lorg/jboss/as/controller/registry/AttributeAccess$Flag;)V
      27: return

  public org.jboss.as.controller.SimpleAttributeDefinition(java.lang.String, org.jboss.dmr.ModelNode, org.jboss.dmr.ModelType, boolean, org.jboss.as.controller.registry.AttributeAccess$Flag...);
    Code:
       0: aload_0
       1: aload_1
       2: aload_1
       3: aload_2
       4: aload_3
       5: iload         4
       7: iconst_0
       8: aconst_null
       9: aconst_null
      10: aconst_null
      11: iconst_1
      12: aconst_null
      13: aconst_null
      14: aconst_null
      15: iconst_0
      16: aconst_null
      17: aconst_null
      18: aconst_null
      19: aconst_null
      20: aload         5
      22: invokespecial #2                  // Method org/jboss/as/controller/AttributeDefinition."<init>":(Ljava/lang/String;Ljava/lang/String;Lorg/jboss/dmr/ModelNode;Lorg/jboss/dmr/ModelType;ZZLorg/jboss/as/controller/client/helpers/MeasurementUnit;Lorg/jboss/as/controller/ParameterCorrector;Lorg/jboss/as/controller/operations/validation/ParameterValidator;Z[Ljava/lang/String;[Ljava/lang/String;Lorg/jboss/as/controller/AttributeMarshaller;ZLorg/jboss/as/controller/DeprecationData;[Lorg/jboss/as/controller/access/management/AccessConstraintDefinition;Ljava/lang/Boolean;Lorg/jboss/as/controller/AttributeParser;[Lorg/jboss/as/controller/registry/AttributeAccess$Flag;)V
      25: return

  protected org.jboss.as.controller.SimpleAttributeDefinition(org.jboss.as.controller.AbstractAttributeDefinitionBuilder<?, ? extends org.jboss.as.controller.SimpleAttributeDefinition>);
    Code:
       0: aload_0
       1: aload_1
       2: invokespecial #3                  // Method org/jboss/as/controller/AttributeDefinition."<init>":(Lorg/jboss/as/controller/AbstractAttributeDefinitionBuilder;)V
       5: return

  public org.jboss.dmr.ModelNode parse(java.lang.String, javax.xml.stream.XMLStreamReader) throws javax.xml.stream.XMLStreamException;
    Code:
       0: aload_0
       1: aload_0
       2: invokevirtual #4                  // Method getValidator:()Lorg/jboss/as/controller/operations/validation/ParameterValidator;
       5: aload_1
       6: invokestatic  #5                  // Method parse:(Lorg/jboss/as/controller/AttributeDefinition;Lorg/jboss/as/controller/operations/validation/ParameterValidator;Ljava/lang/String;)Lorg/jboss/dmr/ModelNode;
       9: areturn
      10: astore_3
      11: new           #7                  // class javax/xml/stream/XMLStreamException
      14: dup
      15: aload_3
      16: invokevirtual #8                  // Method org/jboss/as/controller/OperationFailedException.getFailureDescription:()Lorg/jboss/dmr/ModelNode;
      19: invokevirtual #9                  // Method org/jboss/dmr/ModelNode.toString:()Ljava/lang/String;
      22: aload_2
      23: invokeinterface #10,  1           // InterfaceMethod javax/xml/stream/XMLStreamReader.getLocation:()Ljavax/xml/stream/Location;
      28: invokespecial #11                 // Method javax/xml/stream/XMLStreamException."<init>":(Ljava/lang/String;Ljavax/xml/stream/Location;)V
      31: athrow
    Exception table:
       from    to  target type
           0     9    10   Class org/jboss/as/controller/OperationFailedException

  public void parseAndSetParameter(java.lang.String, org.jboss.dmr.ModelNode, javax.xml.stream.XMLStreamReader) throws javax.xml.stream.XMLStreamException;
    Code:
       0: aload_0
       1: aload_1
       2: aload_3
       3: invokevirtual #12                 // Method parse:(Ljava/lang/String;Ljavax/xml/stream/XMLStreamReader;)Lorg/jboss/dmr/ModelNode;
       6: astore        4
       8: aload_2
       9: aload_0
      10: invokevirtual #13                 // Method getName:()Ljava/lang/String;
      13: invokevirtual #14                 // Method org/jboss/dmr/ModelNode.get:(Ljava/lang/String;)Lorg/jboss/dmr/ModelNode;
      16: aload         4
      18: invokevirtual #15                 // Method org/jboss/dmr/ModelNode.set:(Lorg/jboss/dmr/ModelNode;)Lorg/jboss/dmr/ModelNode;
      21: pop
      22: return

  public void marshallAsAttribute(org.jboss.dmr.ModelNode, javax.xml.stream.XMLStreamWriter) throws javax.xml.stream.XMLStreamException;
    Code:
       0: aload_0
       1: aload_1
       2: iconst_1
       3: aload_2
       4: invokevirtual #16                 // Method marshallAsAttribute:(Lorg/jboss/dmr/ModelNode;ZLjavax/xml/stream/XMLStreamWriter;)V
       7: return

  public void marshallAsAttribute(org.jboss.dmr.ModelNode, boolean, javax.xml.stream.XMLStreamWriter) throws javax.xml.stream.XMLStreamException;
    Code:
       0: aload_0
       1: getfield      #17                 // Field attributeMarshaller:Lorg/jboss/as/controller/AttributeMarshaller;
       4: aload_0
       5: aload_1
       6: iload_2
       7: aload_3
       8: invokevirtual #18                 // Method org/jboss/as/controller/AttributeMarshaller.marshallAsAttribute:(Lorg/jboss/as/controller/AttributeDefinition;Lorg/jboss/dmr/ModelNode;ZLjavax/xml/stream/XMLStreamWriter;)V
      11: return

  public void marshallAsElement(org.jboss.dmr.ModelNode, boolean, javax.xml.stream.XMLStreamWriter) throws javax.xml.stream.XMLStreamException;
    Code:
       0: aload_0
       1: getfield      #17                 // Field attributeMarshaller:Lorg/jboss/as/controller/AttributeMarshaller;
       4: aload_0
       5: aload_1
       6: iload_2
       7: aload_3
       8: invokevirtual #19                 // Method org/jboss/as/controller/AttributeMarshaller.marshallAsElement:(Lorg/jboss/as/controller/AttributeDefinition;Lorg/jboss/dmr/ModelNode;ZLjavax/xml/stream/XMLStreamWriter;)V
      11: return

  static org.jboss.dmr.ModelNode parse(org.jboss.as.controller.AttributeDefinition, org.jboss.as.controller.operations.validation.ParameterValidator, java.lang.String) throws org.jboss.as.controller.OperationFailedException;
    Code:
       0: aload_2
       1: aload_0
       2: invokevirtual #20                 // Method org/jboss/as/controller/AttributeDefinition.isAllowExpression:()Z
       5: aload_0
       6: invokevirtual #21                 // Method org/jboss/as/controller/AttributeDefinition.getType:()Lorg/jboss/dmr/ModelType;
       9: invokestatic  #22                 // Method org/jboss/as/controller/parsing/ParseUtils.parseAttributeValue:(Ljava/lang/String;ZLorg/jboss/dmr/ModelType;)Lorg/jboss/dmr/ModelNode;
      12: astore_3
      13: aload_1
      14: aload_0
      15: invokevirtual #23                 // Method org/jboss/as/controller/AttributeDefinition.getXmlName:()Ljava/lang/String;
      18: aload_3
      19: invokeinterface #24,  3           // InterfaceMethod org/jboss/as/controller/operations/validation/ParameterValidator.validateParameter:(Ljava/lang/String;Lorg/jboss/dmr/ModelNode;)V
      24: aload_3
      25: areturn
}
