Compiled from "MergeOntologiesWizard.java"
public class org.protege.editor.owl.ui.ontology.wizard.merge.MergeOntologiesWizard extends org.protege.editor.core.ui.wizard.Wizard {
  private org.protege.editor.owl.ui.ontology.wizard.merge.SelectOntologiesPage selectOntologiesPage;

  private org.protege.editor.owl.ui.ontology.wizard.create.OntologyIDPanel IDPanel;

  private org.protege.editor.owl.ui.ontology.wizard.create.PhysicalLocationPanel physicalLocationPanel;

  private org.protege.editor.owl.model.OWLModelManager owlModelManager;

  private org.protege.editor.owl.ui.ontology.wizard.merge.SelectTargetOntologyPage selectTargetOntologyPage;

  private org.protege.editor.owl.ui.action.OntologyFormatPage ontologyFormatPage;

  public org.protege.editor.owl.ui.ontology.wizard.merge.MergeOntologiesWizard(org.protege.editor.owl.OWLEditorKit);
    Code:
       0: aload_0
       1: invokespecial #1                  // Method org/protege/editor/core/ui/wizard/Wizard."<init>":()V
       4: aload_0
       5: ldc           #2                  // String Create ontology wizard
       7: invokevirtual #3                  // Method setTitle:(Ljava/lang/String;)V
      10: aload_0
      11: aload_1
      12: invokevirtual #4                  // Method org/protege/editor/owl/OWLEditorKit.getModelManager:()Lorg/protege/editor/owl/model/OWLModelManager;
      15: putfield      #5                  // Field owlModelManager:Lorg/protege/editor/owl/model/OWLModelManager;
      18: aload_0
      19: ldc           #7                  // String SelectOntologiesPage
      21: aload_0
      22: new           #6                  // class org/protege/editor/owl/ui/ontology/wizard/merge/SelectOntologiesPage
      25: dup
      26: aload_1
      27: ldc           #8                  // String Select ontologies to merge
      29: invokespecial #9                  // Method org/protege/editor/owl/ui/ontology/wizard/merge/SelectOntologiesPage."<init>":(Lorg/protege/editor/owl/OWLEditorKit;Ljava/lang/String;)V
      32: dup_x1
      33: putfield      #10                 // Field selectOntologiesPage:Lorg/protege/editor/owl/ui/ontology/wizard/merge/SelectOntologiesPage;
      36: invokevirtual #11                 // Method registerWizardPanel:(Ljava/lang/Object;Lorg/protege/editor/core/ui/wizard/WizardPanel;)V
      39: aload_0
      40: getfield      #10                 // Field selectOntologiesPage:Lorg/protege/editor/owl/ui/ontology/wizard/merge/SelectOntologiesPage;
      43: ldc           #12                 // String Please select the ontologies that you want to merge into another ontology.
      45: invokevirtual #13                 // Method org/protege/editor/owl/ui/ontology/wizard/merge/SelectOntologiesPage.setInstructions:(Ljava/lang/String;)V
      48: aload_0
      49: ldc           #15                 // String MergeTypePage
      51: new           #14                 // class org/protege/editor/owl/ui/ontology/wizard/merge/MergeTypePage
      54: dup
      55: aload_1
      56: invokespecial #16                 // Method org/protege/editor/owl/ui/ontology/wizard/merge/MergeTypePage."<init>":(Lorg/protege/editor/owl/OWLEditorKit;)V
      59: invokevirtual #11                 // Method registerWizardPanel:(Ljava/lang/Object;Lorg/protege/editor/core/ui/wizard/WizardPanel;)V
      62: aload_0
      63: ldc           #18                 // String ONTOLOGY_ID_PANEL
      65: aload_0
      66: new           #17                 // class org/protege/editor/owl/ui/ontology/wizard/create/OntologyIDPanel
      69: dup
      70: aload_1
      71: invokespecial #19                 // Method org/protege/editor/owl/ui/ontology/wizard/create/OntologyIDPanel."<init>":(Lorg/protege/editor/owl/OWLEditorKit;)V
      74: dup_x1
      75: putfield      #20                 // Field IDPanel:Lorg/protege/editor/owl/ui/ontology/wizard/create/OntologyIDPanel;
      78: invokevirtual #11                 // Method registerWizardPanel:(Ljava/lang/Object;Lorg/protege/editor/core/ui/wizard/WizardPanel;)V
      81: aload_0
      82: getstatic     #21                 // Field org/protege/editor/owl/ui/ontology/wizard/create/PhysicalLocationPanel.ID:Ljava/lang/String;
      85: aload_0
      86: new           #22                 // class org/protege/editor/owl/ui/ontology/wizard/create/PhysicalLocationPanel
      89: dup
      90: aload_1
      91: invokespecial #23                 // Method org/protege/editor/owl/ui/ontology/wizard/create/PhysicalLocationPanel."<init>":(Lorg/protege/editor/core/editorkit/EditorKit;)V
      94: dup_x1
      95: putfield      #24                 // Field physicalLocationPanel:Lorg/protege/editor/owl/ui/ontology/wizard/create/PhysicalLocationPanel;
      98: invokevirtual #11                 // Method registerWizardPanel:(Ljava/lang/Object;Lorg/protege/editor/core/ui/wizard/WizardPanel;)V
     101: aload_0
     102: ldc           #26                 // String ONTOLOGY_FORMAT_PANEL
     104: aload_0
     105: new           #25                 // class org/protege/editor/owl/ui/action/OntologyFormatPage
     108: dup
     109: aload_1
     110: invokespecial #27                 // Method org/protege/editor/owl/ui/action/OntologyFormatPage."<init>":(Lorg/protege/editor/core/editorkit/EditorKit;)V
     113: dup_x1
     114: putfield      #28                 // Field ontologyFormatPage:Lorg/protege/editor/owl/ui/action/OntologyFormatPage;
     117: invokevirtual #11                 // Method registerWizardPanel:(Ljava/lang/Object;Lorg/protege/editor/core/ui/wizard/WizardPanel;)V
     120: aload_0
     121: ldc           #30                 // String SelectTargetOntologyPage
     123: aload_0
     124: new           #29                 // class org/protege/editor/owl/ui/ontology/wizard/merge/SelectTargetOntologyPage
     127: dup
     128: aload_1
     129: ldc           #31                 // String Select ontology to merge into
     131: invokespecial #32                 // Method org/protege/editor/owl/ui/ontology/wizard/merge/SelectTargetOntologyPage."<init>":(Lorg/protege/editor/owl/OWLEditorKit;Ljava/lang/String;)V
     134: dup_x1
     135: putfield      #33                 // Field selectTargetOntologyPage:Lorg/protege/editor/owl/ui/ontology/wizard/merge/SelectTargetOntologyPage;
     138: invokevirtual #11                 // Method registerWizardPanel:(Ljava/lang/Object;Lorg/protege/editor/core/ui/wizard/WizardPanel;)V
     141: aload_0
     142: getfield      #33                 // Field selectTargetOntologyPage:Lorg/protege/editor/owl/ui/ontology/wizard/merge/SelectTargetOntologyPage;
     145: ldc           #34                 // String Please select the target ontology to merge into
     147: invokevirtual #35                 // Method org/protege/editor/owl/ui/ontology/wizard/merge/SelectTargetOntologyPage.setInstructions:(Ljava/lang/String;)V
     150: aload_0
     151: ldc           #7                  // String SelectOntologiesPage
     153: invokevirtual #36                 // Method setCurrentPanel:(Ljava/lang/Object;)V
     156: return

  public java.util.Set<org.semanticweb.owlapi.model.OWLOntology> getOntologiesToMerge();
    Code:
       0: aload_0
       1: getfield      #10                 // Field selectOntologiesPage:Lorg/protege/editor/owl/ui/ontology/wizard/merge/SelectOntologiesPage;
       4: invokevirtual #37                 // Method org/protege/editor/owl/ui/ontology/wizard/merge/SelectOntologiesPage.getOntologies:()Ljava/util/Set;
       7: areturn

  public org.semanticweb.owlapi.model.OWLOntology getOntologyToMergeInto();
    Code:
       0: aload_0
       1: getfield      #33                 // Field selectTargetOntologyPage:Lorg/protege/editor/owl/ui/ontology/wizard/merge/SelectTargetOntologyPage;
       4: invokevirtual #38                 // Method org/protege/editor/owl/ui/ontology/wizard/merge/SelectTargetOntologyPage.getOntology:()Lorg/semanticweb/owlapi/model/OWLOntology;
       7: astore_1
       8: aload_1
       9: ifnonnull     73
      12: aload_0
      13: getfield      #20                 // Field IDPanel:Lorg/protege/editor/owl/ui/ontology/wizard/create/OntologyIDPanel;
      16: invokevirtual #39                 // Method org/protege/editor/owl/ui/ontology/wizard/create/OntologyIDPanel.getOntologyID:()Lorg/semanticweb/owlapi/model/OWLOntologyID;
      19: astore_2
      20: aload_0
      21: getfield      #5                  // Field owlModelManager:Lorg/protege/editor/owl/model/OWLModelManager;
      24: aload_2
      25: aload_0
      26: getfield      #24                 // Field physicalLocationPanel:Lorg/protege/editor/owl/ui/ontology/wizard/create/PhysicalLocationPanel;
      29: invokevirtual #40                 // Method org/protege/editor/owl/ui/ontology/wizard/create/PhysicalLocationPanel.getLocationURL:()Ljava/net/URI;
      32: invokeinterface #41,  3           // InterfaceMethod org/protege/editor/owl/model/OWLModelManager.createNewOntology:(Lorg/semanticweb/owlapi/model/OWLOntologyID;Ljava/net/URI;)Lorg/semanticweb/owlapi/model/OWLOntology;
      37: astore_1
      38: aload_0
      39: getfield      #5                  // Field owlModelManager:Lorg/protege/editor/owl/model/OWLModelManager;
      42: invokeinterface #42,  1           // InterfaceMethod org/protege/editor/owl/model/OWLModelManager.getOWLOntologyManager:()Lorg/semanticweb/owlapi/model/OWLOntologyManager;
      47: aload_1
      48: aload_0
      49: getfield      #28                 // Field ontologyFormatPage:Lorg/protege/editor/owl/ui/action/OntologyFormatPage;
      52: invokevirtual #43                 // Method org/protege/editor/owl/ui/action/OntologyFormatPage.getFormat:()Lorg/semanticweb/owlapi/model/OWLDocumentFormat;
      55: invokeinterface #44,  3           // InterfaceMethod org/semanticweb/owlapi/model/OWLOntologyManager.setOntologyFormat:(Lorg/semanticweb/owlapi/model/OWLOntology;Lorg/semanticweb/owlapi/model/OWLDocumentFormat;)V
      60: goto          73
      63: astore_2
      64: new           #46                 // class org/semanticweb/owlapi/model/OWLRuntimeException
      67: dup
      68: aload_2
      69: invokespecial #47                 // Method org/semanticweb/owlapi/model/OWLRuntimeException."<init>":(Ljava/lang/Throwable;)V
      72: athrow
      73: aload_1
      74: areturn
    Exception table:
       from    to  target type
          12    60    63   Class org/semanticweb/owlapi/model/OWLOntologyCreationException
}
