Compiled from "InnerJoinRecordReader.java"
public class org.apache.hadoop.mapred.join.InnerJoinRecordReader<K extends org.apache.hadoop.io.WritableComparable> extends org.apache.hadoop.mapred.join.JoinRecordReader<K> {
  static final boolean $assertionsDisabled;

  org.apache.hadoop.mapred.join.InnerJoinRecordReader(int, org.apache.hadoop.mapred.JobConf, int, java.lang.Class<? extends org.apache.hadoop.io.WritableComparator>) throws java.io.IOException;
    Code:
       0: aload_0
       1: iload_1
       2: aload_2
       3: iload_3
       4: aload         4
       6: invokespecial #1                  // Method org/apache/hadoop/mapred/join/JoinRecordReader."<init>":(ILorg/apache/hadoop/mapred/JobConf;ILjava/lang/Class;)V
       9: return

  protected boolean combine(java.lang.Object[], org.apache.hadoop.mapred.join.TupleWritable);
    Code:
       0: getstatic     #2                  // Field $assertionsDisabled:Z
       3: ifne          23
       6: aload_1
       7: arraylength
       8: aload_2
       9: invokevirtual #3                  // Method org/apache/hadoop/mapred/join/TupleWritable.size:()I
      12: if_icmpeq     23
      15: new           #4                  // class java/lang/AssertionError
      18: dup
      19: invokespecial #5                  // Method java/lang/AssertionError."<init>":()V
      22: athrow
      23: iconst_0
      24: istore_3
      25: iload_3
      26: aload_1
      27: arraylength
      28: if_icmpge     47
      31: aload_2
      32: iload_3
      33: invokevirtual #6                  // Method org/apache/hadoop/mapred/join/TupleWritable.has:(I)Z
      36: ifne          41
      39: iconst_0
      40: ireturn
      41: iinc          3, 1
      44: goto          25
      47: iconst_1
      48: ireturn

  static {};
    Code:
       0: ldc           #7                  // class org/apache/hadoop/mapred/join/InnerJoinRecordReader
       2: invokevirtual #8                  // Method java/lang/Class.desiredAssertionStatus:()Z
       5: ifne          12
       8: iconst_1
       9: goto          13
      12: iconst_0
      13: putstatic     #2                  // Field $assertionsDisabled:Z
      16: return
}
