Compiled from "ASTParser.java"
final class io.sundr.shaded.com.github.javaparser.ASTParser$GTToken extends io.sundr.shaded.com.github.javaparser.Token {
  int realKind;

  io.sundr.shaded.com.github.javaparser.ASTParser$GTToken(int, java.lang.String);
    Code:
       0: aload_0
       1: invokespecial #15                 // Method io/sundr/shaded/com/github/javaparser/Token."<init>":()V
       4: aload_0
       5: sipush        130
       8: putfield      #17                 // Field realKind:I
      11: aload_0
      12: iload_1
      13: putfield      #20                 // Field kind:I
      16: aload_0
      17: aload_2
      18: putfield      #24                 // Field image:Ljava/lang/String;
      21: return

  public static io.sundr.shaded.com.github.javaparser.Token newToken(int, java.lang.String);
    Code:
       0: new           #2                  // class io/sundr/shaded/com/github/javaparser/ASTParser$GTToken
       3: dup
       4: iload_0
       5: aload_1
       6: invokespecial #30                 // Method "<init>":(ILjava/lang/String;)V
       9: areturn
}
