Compiled from "AbstractBaseGraph.java"
final class com.google.common.graph.AbstractBaseGraph$IncidentEdgeSet$Directed<N> extends com.google.common.graph.AbstractBaseGraph$IncidentEdgeSet<N> {
  private com.google.common.graph.AbstractBaseGraph$IncidentEdgeSet$Directed(com.google.common.graph.BaseGraph<N>, N);
    Code:
       0: aload_0
       1: aload_1
       2: aload_2
       3: aconst_null
       4: invokespecial #2                  // Method com/google/common/graph/AbstractBaseGraph$IncidentEdgeSet."<init>":(Lcom/google/common/graph/BaseGraph;Ljava/lang/Object;Lcom/google/common/graph/AbstractBaseGraph$1;)V
       7: return

  public com.google.common.collect.UnmodifiableIterator<com.google.common.graph.EndpointPair<N>> iterator();
    Code:
       0: aload_0
       1: getfield      #3                  // Field graph:Lcom/google/common/graph/BaseGraph;
       4: aload_0
       5: getfield      #4                  // Field node:Ljava/lang/Object;
       8: invokeinterface #5,  2            // InterfaceMethod com/google/common/graph/BaseGraph.predecessors:(Ljava/lang/Object;)Ljava/util/Set;
      13: invokeinterface #6,  1            // InterfaceMethod java/util/Set.iterator:()Ljava/util/Iterator;
      18: new           #7                  // class com/google/common/graph/AbstractBaseGraph$IncidentEdgeSet$Directed$1
      21: dup
      22: aload_0
      23: invokespecial #8                  // Method com/google/common/graph/AbstractBaseGraph$IncidentEdgeSet$Directed$1."<init>":(Lcom/google/common/graph/AbstractBaseGraph$IncidentEdgeSet$Directed;)V
      26: invokestatic  #9                  // Method com/google/common/collect/Iterators.transform:(Ljava/util/Iterator;Lcom/google/common/base/Function;)Ljava/util/Iterator;
      29: aload_0
      30: getfield      #3                  // Field graph:Lcom/google/common/graph/BaseGraph;
      33: aload_0
      34: getfield      #4                  // Field node:Ljava/lang/Object;
      37: invokeinterface #10,  2           // InterfaceMethod com/google/common/graph/BaseGraph.successors:(Ljava/lang/Object;)Ljava/util/Set;
      42: aload_0
      43: getfield      #4                  // Field node:Ljava/lang/Object;
      46: invokestatic  #11                 // Method com/google/common/collect/ImmutableSet.of:(Ljava/lang/Object;)Lcom/google/common/collect/ImmutableSet;
      49: invokestatic  #12                 // Method com/google/common/collect/Sets.difference:(Ljava/util/Set;Ljava/util/Set;)Lcom/google/common/collect/Sets$SetView;
      52: invokevirtual #13                 // Method com/google/common/collect/Sets$SetView.iterator:()Lcom/google/common/collect/UnmodifiableIterator;
      55: new           #14                 // class com/google/common/graph/AbstractBaseGraph$IncidentEdgeSet$Directed$2
      58: dup
      59: aload_0
      60: invokespecial #15                 // Method com/google/common/graph/AbstractBaseGraph$IncidentEdgeSet$Directed$2."<init>":(Lcom/google/common/graph/AbstractBaseGraph$IncidentEdgeSet$Directed;)V
      63: invokestatic  #9                  // Method com/google/common/collect/Iterators.transform:(Ljava/util/Iterator;Lcom/google/common/base/Function;)Ljava/util/Iterator;
      66: invokestatic  #16                 // Method com/google/common/collect/Iterators.concat:(Ljava/util/Iterator;Ljava/util/Iterator;)Ljava/util/Iterator;
      69: invokestatic  #17                 // Method com/google/common/collect/Iterators.unmodifiableIterator:(Ljava/util/Iterator;)Lcom/google/common/collect/UnmodifiableIterator;
      72: areturn

  public int size();
    Code:
       0: aload_0
       1: getfield      #3                  // Field graph:Lcom/google/common/graph/BaseGraph;
       4: aload_0
       5: getfield      #4                  // Field node:Ljava/lang/Object;
       8: invokeinterface #18,  2           // InterfaceMethod com/google/common/graph/BaseGraph.inDegree:(Ljava/lang/Object;)I
      13: aload_0
      14: getfield      #3                  // Field graph:Lcom/google/common/graph/BaseGraph;
      17: aload_0
      18: getfield      #4                  // Field node:Ljava/lang/Object;
      21: invokeinterface #19,  2           // InterfaceMethod com/google/common/graph/BaseGraph.outDegree:(Ljava/lang/Object;)I
      26: iadd
      27: aload_0
      28: getfield      #3                  // Field graph:Lcom/google/common/graph/BaseGraph;
      31: aload_0
      32: getfield      #4                  // Field node:Ljava/lang/Object;
      35: invokeinterface #10,  2           // InterfaceMethod com/google/common/graph/BaseGraph.successors:(Ljava/lang/Object;)Ljava/util/Set;
      40: aload_0
      41: getfield      #4                  // Field node:Ljava/lang/Object;
      44: invokeinterface #20,  2           // InterfaceMethod java/util/Set.contains:(Ljava/lang/Object;)Z
      49: ifeq          56
      52: iconst_1
      53: goto          57
      56: iconst_0
      57: isub
      58: ireturn

  public boolean contains(java.lang.Object);
    Code:
       0: aload_1
       1: instanceof    #21                 // class com/google/common/graph/EndpointPair
       4: ifne          9
       7: iconst_0
       8: ireturn
       9: aload_1
      10: checkcast     #21                 // class com/google/common/graph/EndpointPair
      13: astore_2
      14: aload_2
      15: invokevirtual #22                 // Method com/google/common/graph/EndpointPair.isOrdered:()Z
      18: ifne          23
      21: iconst_0
      22: ireturn
      23: aload_2
      24: invokevirtual #23                 // Method com/google/common/graph/EndpointPair.source:()Ljava/lang/Object;
      27: astore_3
      28: aload_2
      29: invokevirtual #24                 // Method com/google/common/graph/EndpointPair.target:()Ljava/lang/Object;
      32: astore        4
      34: aload_0
      35: getfield      #4                  // Field node:Ljava/lang/Object;
      38: aload_3
      39: invokevirtual #25                 // Method java/lang/Object.equals:(Ljava/lang/Object;)Z
      42: ifeq          68
      45: aload_0
      46: getfield      #3                  // Field graph:Lcom/google/common/graph/BaseGraph;
      49: aload_0
      50: getfield      #4                  // Field node:Ljava/lang/Object;
      53: invokeinterface #10,  2           // InterfaceMethod com/google/common/graph/BaseGraph.successors:(Ljava/lang/Object;)Ljava/util/Set;
      58: aload         4
      60: invokeinterface #20,  2           // InterfaceMethod java/util/Set.contains:(Ljava/lang/Object;)Z
      65: ifne          102
      68: aload_0
      69: getfield      #4                  // Field node:Ljava/lang/Object;
      72: aload         4
      74: invokevirtual #25                 // Method java/lang/Object.equals:(Ljava/lang/Object;)Z
      77: ifeq          106
      80: aload_0
      81: getfield      #3                  // Field graph:Lcom/google/common/graph/BaseGraph;
      84: aload_0
      85: getfield      #4                  // Field node:Ljava/lang/Object;
      88: invokeinterface #5,  2            // InterfaceMethod com/google/common/graph/BaseGraph.predecessors:(Ljava/lang/Object;)Ljava/util/Set;
      93: aload_3
      94: invokeinterface #20,  2           // InterfaceMethod java/util/Set.contains:(Ljava/lang/Object;)Z
      99: ifeq          106
     102: iconst_1
     103: goto          107
     106: iconst_0
     107: ireturn

  public java.util.Iterator iterator();
    Code:
       0: aload_0
       1: invokevirtual #26                 // Method iterator:()Lcom/google/common/collect/UnmodifiableIterator;
       4: areturn

  com.google.common.graph.AbstractBaseGraph$IncidentEdgeSet$Directed(com.google.common.graph.BaseGraph, java.lang.Object, com.google.common.graph.AbstractBaseGraph$1);
    Code:
       0: aload_0
       1: aload_1
       2: aload_2
       3: invokespecial #1                  // Method "<init>":(Lcom/google/common/graph/BaseGraph;Ljava/lang/Object;)V
       6: return
}
