Compiled from "MultiEdgesConnecting.java"
abstract class com.google.common.graph.MultiEdgesConnecting<E> extends java.util.AbstractSet<E> {
  private final java.util.Map<E, ?> outEdgeToNode;

  private final java.lang.Object targetNode;

  com.google.common.graph.MultiEdgesConnecting(java.util.Map<E, ?>, java.lang.Object);
    Code:
       0: aload_0
       1: invokespecial #2                  // Method java/util/AbstractSet."<init>":()V
       4: aload_0
       5: aload_1
       6: invokestatic  #3                  // Method com/google/common/base/Preconditions.checkNotNull:(Ljava/lang/Object;)Ljava/lang/Object;
       9: checkcast     #4                  // class java/util/Map
      12: putfield      #5                  // Field outEdgeToNode:Ljava/util/Map;
      15: aload_0
      16: aload_2
      17: invokestatic  #3                  // Method com/google/common/base/Preconditions.checkNotNull:(Ljava/lang/Object;)Ljava/lang/Object;
      20: putfield      #1                  // Field targetNode:Ljava/lang/Object;
      23: return

  public com.google.common.collect.UnmodifiableIterator<E> iterator();
    Code:
       0: aload_0
       1: getfield      #5                  // Field outEdgeToNode:Ljava/util/Map;
       4: invokeinterface #6,  1            // InterfaceMethod java/util/Map.entrySet:()Ljava/util/Set;
       9: invokeinterface #7,  1            // InterfaceMethod java/util/Set.iterator:()Ljava/util/Iterator;
      14: astore_1
      15: new           #8                  // class com/google/common/graph/MultiEdgesConnecting$1
      18: dup
      19: aload_0
      20: aload_1
      21: invokespecial #9                  // Method com/google/common/graph/MultiEdgesConnecting$1."<init>":(Lcom/google/common/graph/MultiEdgesConnecting;Ljava/util/Iterator;)V
      24: areturn

  public boolean contains(java.lang.Object);
    Code:
       0: aload_0
       1: getfield      #1                  // Field targetNode:Ljava/lang/Object;
       4: aload_0
       5: getfield      #5                  // Field outEdgeToNode:Ljava/util/Map;
       8: aload_1
       9: invokeinterface #10,  2           // InterfaceMethod java/util/Map.get:(Ljava/lang/Object;)Ljava/lang/Object;
      14: invokevirtual #11                 // Method java/lang/Object.equals:(Ljava/lang/Object;)Z
      17: ireturn

  public java.util.Iterator iterator();
    Code:
       0: aload_0
       1: invokevirtual #12                 // Method iterator:()Lcom/google/common/collect/UnmodifiableIterator;
       4: areturn

  static java.lang.Object access$000(com.google.common.graph.MultiEdgesConnecting);
    Code:
       0: aload_0
       1: getfield      #1                  // Field targetNode:Ljava/lang/Object;
       4: areturn
}
