Compiled from "ValueExpressionImpl.java"
public final class org.apache.el.ValueExpressionImpl extends javax.el.ValueExpression implements java.io.Externalizable {
  private java.lang.Class<?> expectedType;

  private java.lang.String expr;

  private javax.el.FunctionMapper fnMapper;

  private javax.el.VariableMapper varMapper;

  private transient org.apache.el.parser.Node node;

  public org.apache.el.ValueExpressionImpl();
    Code:
       0: aload_0
       1: invokespecial #1                  // Method javax/el/ValueExpression."<init>":()V
       4: return

  public org.apache.el.ValueExpressionImpl(java.lang.String, org.apache.el.parser.Node, javax.el.FunctionMapper, javax.el.VariableMapper, java.lang.Class<?>);
    Code:
       0: aload_0
       1: invokespecial #1                  // Method javax/el/ValueExpression."<init>":()V
       4: aload_0
       5: aload_1
       6: putfield      #2                  // Field expr:Ljava/lang/String;
       9: aload_0
      10: aload_2
      11: putfield      #3                  // Field node:Lorg/apache/el/parser/Node;
      14: aload_0
      15: aload_3
      16: putfield      #4                  // Field fnMapper:Ljavax/el/FunctionMapper;
      19: aload_0
      20: aload         4
      22: putfield      #5                  // Field varMapper:Ljavax/el/VariableMapper;
      25: aload_0
      26: aload         5
      28: putfield      #6                  // Field expectedType:Ljava/lang/Class;
      31: return

  public boolean equals(java.lang.Object);
    Code:
       0: aload_1
       1: instanceof    #7                  // class org/apache/el/ValueExpressionImpl
       4: ifne          9
       7: iconst_0
       8: ireturn
       9: aload_1
      10: invokevirtual #8                  // Method java/lang/Object.hashCode:()I
      13: aload_0
      14: invokevirtual #9                  // Method hashCode:()I
      17: if_icmpeq     22
      20: iconst_0
      21: ireturn
      22: aload_0
      23: invokespecial #10                 // Method getNode:()Lorg/apache/el/parser/Node;
      26: aload_1
      27: checkcast     #7                  // class org/apache/el/ValueExpressionImpl
      30: invokespecial #10                 // Method getNode:()Lorg/apache/el/parser/Node;
      33: invokevirtual #11                 // Method java/lang/Object.equals:(Ljava/lang/Object;)Z
      36: ireturn

  public java.lang.Class<?> getExpectedType();
    Code:
       0: aload_0
       1: getfield      #6                  // Field expectedType:Ljava/lang/Class;
       4: areturn

  public java.lang.String getExpressionString();
    Code:
       0: aload_0
       1: getfield      #2                  // Field expr:Ljava/lang/String;
       4: areturn

  private org.apache.el.parser.Node getNode() throws javax.el.ELException;
    Code:
       0: aload_0
       1: getfield      #3                  // Field node:Lorg/apache/el/parser/Node;
       4: ifnonnull     18
       7: aload_0
       8: aload_0
       9: getfield      #2                  // Field expr:Ljava/lang/String;
      12: invokestatic  #12                 // Method org/apache/el/lang/ExpressionBuilder.createNode:(Ljava/lang/String;)Lorg/apache/el/parser/Node;
      15: putfield      #3                  // Field node:Lorg/apache/el/parser/Node;
      18: aload_0
      19: getfield      #3                  // Field node:Lorg/apache/el/parser/Node;
      22: areturn

  public java.lang.Class<?> getType(javax.el.ELContext) throws javax.el.PropertyNotFoundException, javax.el.ELException;
    Code:
       0: new           #13                 // class org/apache/el/lang/EvaluationContext
       3: dup
       4: aload_1
       5: aload_0
       6: getfield      #4                  // Field fnMapper:Ljavax/el/FunctionMapper;
       9: aload_0
      10: getfield      #5                  // Field varMapper:Ljavax/el/VariableMapper;
      13: invokespecial #14                 // Method org/apache/el/lang/EvaluationContext."<init>":(Ljavax/el/ELContext;Ljavax/el/FunctionMapper;Ljavax/el/VariableMapper;)V
      16: astore_2
      17: aload_1
      18: aload_0
      19: invokevirtual #15                 // Method getExpressionString:()Ljava/lang/String;
      22: invokevirtual #16                 // Method javax/el/ELContext.notifyBeforeEvaluation:(Ljava/lang/String;)V
      25: aload_0
      26: invokespecial #10                 // Method getNode:()Lorg/apache/el/parser/Node;
      29: aload_2
      30: invokeinterface #17,  2           // InterfaceMethod org/apache/el/parser/Node.getType:(Lorg/apache/el/lang/EvaluationContext;)Ljava/lang/Class;
      35: astore_3
      36: aload_1
      37: aload_0
      38: invokevirtual #15                 // Method getExpressionString:()Ljava/lang/String;
      41: invokevirtual #18                 // Method javax/el/ELContext.notifyAfterEvaluation:(Ljava/lang/String;)V
      44: aload_3
      45: areturn

  public java.lang.Object getValue(javax.el.ELContext) throws javax.el.PropertyNotFoundException, javax.el.ELException;
    Code:
       0: new           #13                 // class org/apache/el/lang/EvaluationContext
       3: dup
       4: aload_1
       5: aload_0
       6: getfield      #4                  // Field fnMapper:Ljavax/el/FunctionMapper;
       9: aload_0
      10: getfield      #5                  // Field varMapper:Ljavax/el/VariableMapper;
      13: invokespecial #14                 // Method org/apache/el/lang/EvaluationContext."<init>":(Ljavax/el/ELContext;Ljavax/el/FunctionMapper;Ljavax/el/VariableMapper;)V
      16: astore_2
      17: aload_1
      18: aload_0
      19: invokevirtual #15                 // Method getExpressionString:()Ljava/lang/String;
      22: invokevirtual #16                 // Method javax/el/ELContext.notifyBeforeEvaluation:(Ljava/lang/String;)V
      25: aload_0
      26: invokespecial #10                 // Method getNode:()Lorg/apache/el/parser/Node;
      29: aload_2
      30: invokeinterface #19,  2           // InterfaceMethod org/apache/el/parser/Node.getValue:(Lorg/apache/el/lang/EvaluationContext;)Ljava/lang/Object;
      35: astore_3
      36: aload_0
      37: getfield      #6                  // Field expectedType:Ljava/lang/Class;
      40: ifnull        53
      43: aload_1
      44: aload_3
      45: aload_0
      46: getfield      #6                  // Field expectedType:Ljava/lang/Class;
      49: invokevirtual #20                 // Method javax/el/ELContext.convertToType:(Ljava/lang/Object;Ljava/lang/Class;)Ljava/lang/Object;
      52: astore_3
      53: aload_1
      54: aload_0
      55: invokevirtual #15                 // Method getExpressionString:()Ljava/lang/String;
      58: invokevirtual #18                 // Method javax/el/ELContext.notifyAfterEvaluation:(Ljava/lang/String;)V
      61: aload_3
      62: areturn

  public int hashCode();
    Code:
       0: aload_0
       1: invokespecial #10                 // Method getNode:()Lorg/apache/el/parser/Node;
       4: invokevirtual #8                  // Method java/lang/Object.hashCode:()I
       7: ireturn

  public boolean isLiteralText();
    Code:
       0: aload_0
       1: invokespecial #10                 // Method getNode:()Lorg/apache/el/parser/Node;
       4: instanceof    #21                 // class org/apache/el/parser/AstLiteralExpression
       7: ireturn
       8: astore_1
       9: iconst_0
      10: ireturn
    Exception table:
       from    to  target type
           0     7     8   Class javax/el/ELException

  public boolean isReadOnly(javax.el.ELContext) throws javax.el.PropertyNotFoundException, javax.el.ELException;
    Code:
       0: new           #13                 // class org/apache/el/lang/EvaluationContext
       3: dup
       4: aload_1
       5: aload_0
       6: getfield      #4                  // Field fnMapper:Ljavax/el/FunctionMapper;
       9: aload_0
      10: getfield      #5                  // Field varMapper:Ljavax/el/VariableMapper;
      13: invokespecial #14                 // Method org/apache/el/lang/EvaluationContext."<init>":(Ljavax/el/ELContext;Ljavax/el/FunctionMapper;Ljavax/el/VariableMapper;)V
      16: astore_2
      17: aload_1
      18: aload_0
      19: invokevirtual #15                 // Method getExpressionString:()Ljava/lang/String;
      22: invokevirtual #16                 // Method javax/el/ELContext.notifyBeforeEvaluation:(Ljava/lang/String;)V
      25: aload_0
      26: invokespecial #10                 // Method getNode:()Lorg/apache/el/parser/Node;
      29: aload_2
      30: invokeinterface #23,  2           // InterfaceMethod org/apache/el/parser/Node.isReadOnly:(Lorg/apache/el/lang/EvaluationContext;)Z
      35: istore_3
      36: aload_1
      37: aload_0
      38: invokevirtual #15                 // Method getExpressionString:()Ljava/lang/String;
      41: invokevirtual #18                 // Method javax/el/ELContext.notifyAfterEvaluation:(Ljava/lang/String;)V
      44: iload_3
      45: ireturn

  public void readExternal(java.io.ObjectInput) throws java.io.IOException, java.lang.ClassNotFoundException;
    Code:
       0: aload_0
       1: aload_1
       2: invokeinterface #24,  1           // InterfaceMethod java/io/ObjectInput.readUTF:()Ljava/lang/String;
       7: putfield      #2                  // Field expr:Ljava/lang/String;
      10: aload_1
      11: invokeinterface #24,  1           // InterfaceMethod java/io/ObjectInput.readUTF:()Ljava/lang/String;
      16: astore_2
      17: ldc           #25                 // String
      19: aload_2
      20: invokevirtual #26                 // Method java/lang/String.equals:(Ljava/lang/Object;)Z
      23: ifne          34
      26: aload_0
      27: aload_2
      28: invokestatic  #27                 // Method org/apache/el/util/ReflectionUtil.forName:(Ljava/lang/String;)Ljava/lang/Class;
      31: putfield      #6                  // Field expectedType:Ljava/lang/Class;
      34: aload_0
      35: aload_1
      36: invokeinterface #28,  1           // InterfaceMethod java/io/ObjectInput.readObject:()Ljava/lang/Object;
      41: checkcast     #29                 // class javax/el/FunctionMapper
      44: putfield      #4                  // Field fnMapper:Ljavax/el/FunctionMapper;
      47: aload_0
      48: aload_1
      49: invokeinterface #28,  1           // InterfaceMethod java/io/ObjectInput.readObject:()Ljava/lang/Object;
      54: checkcast     #30                 // class javax/el/VariableMapper
      57: putfield      #5                  // Field varMapper:Ljavax/el/VariableMapper;
      60: return

  public void setValue(javax.el.ELContext, java.lang.Object) throws javax.el.PropertyNotFoundException, javax.el.PropertyNotWritableException, javax.el.ELException;
    Code:
       0: new           #13                 // class org/apache/el/lang/EvaluationContext
       3: dup
       4: aload_1
       5: aload_0
       6: getfield      #4                  // Field fnMapper:Ljavax/el/FunctionMapper;
       9: aload_0
      10: getfield      #5                  // Field varMapper:Ljavax/el/VariableMapper;
      13: invokespecial #14                 // Method org/apache/el/lang/EvaluationContext."<init>":(Ljavax/el/ELContext;Ljavax/el/FunctionMapper;Ljavax/el/VariableMapper;)V
      16: astore_3
      17: aload_1
      18: aload_0
      19: invokevirtual #15                 // Method getExpressionString:()Ljava/lang/String;
      22: invokevirtual #16                 // Method javax/el/ELContext.notifyBeforeEvaluation:(Ljava/lang/String;)V
      25: aload_0
      26: invokespecial #10                 // Method getNode:()Lorg/apache/el/parser/Node;
      29: aload_3
      30: aload_2
      31: invokeinterface #31,  3           // InterfaceMethod org/apache/el/parser/Node.setValue:(Lorg/apache/el/lang/EvaluationContext;Ljava/lang/Object;)V
      36: aload_1
      37: aload_0
      38: invokevirtual #15                 // Method getExpressionString:()Ljava/lang/String;
      41: invokevirtual #18                 // Method javax/el/ELContext.notifyAfterEvaluation:(Ljava/lang/String;)V
      44: return

  public void writeExternal(java.io.ObjectOutput) throws java.io.IOException;
    Code:
       0: aload_1
       1: aload_0
       2: getfield      #2                  // Field expr:Ljava/lang/String;
       5: invokeinterface #32,  2           // InterfaceMethod java/io/ObjectOutput.writeUTF:(Ljava/lang/String;)V
      10: aload_1
      11: aload_0
      12: getfield      #6                  // Field expectedType:Ljava/lang/Class;
      15: ifnull        28
      18: aload_0
      19: getfield      #6                  // Field expectedType:Ljava/lang/Class;
      22: invokevirtual #33                 // Method java/lang/Class.getName:()Ljava/lang/String;
      25: goto          30
      28: ldc           #25                 // String
      30: invokeinterface #32,  2           // InterfaceMethod java/io/ObjectOutput.writeUTF:(Ljava/lang/String;)V
      35: aload_1
      36: aload_0
      37: getfield      #4                  // Field fnMapper:Ljavax/el/FunctionMapper;
      40: invokeinterface #34,  2           // InterfaceMethod java/io/ObjectOutput.writeObject:(Ljava/lang/Object;)V
      45: aload_1
      46: aload_0
      47: getfield      #5                  // Field varMapper:Ljavax/el/VariableMapper;
      50: invokeinterface #34,  2           // InterfaceMethod java/io/ObjectOutput.writeObject:(Ljava/lang/Object;)V
      55: return

  public java.lang.String toString();
    Code:
       0: new           #35                 // class java/lang/StringBuilder
       3: dup
       4: invokespecial #36                 // Method java/lang/StringBuilder."<init>":()V
       7: ldc           #37                 // String ValueExpression[
       9: invokevirtual #38                 // Method java/lang/StringBuilder.append:(Ljava/lang/String;)Ljava/lang/StringBuilder;
      12: aload_0
      13: getfield      #2                  // Field expr:Ljava/lang/String;
      16: invokevirtual #38                 // Method java/lang/StringBuilder.append:(Ljava/lang/String;)Ljava/lang/StringBuilder;
      19: ldc           #39                 // String ]
      21: invokevirtual #38                 // Method java/lang/StringBuilder.append:(Ljava/lang/String;)Ljava/lang/StringBuilder;
      24: invokevirtual #40                 // Method java/lang/StringBuilder.toString:()Ljava/lang/String;
      27: areturn

  public javax.el.ValueReference getValueReference(javax.el.ELContext);
    Code:
       0: new           #13                 // class org/apache/el/lang/EvaluationContext
       3: dup
       4: aload_1
       5: aload_0
       6: getfield      #4                  // Field fnMapper:Ljavax/el/FunctionMapper;
       9: aload_0
      10: getfield      #5                  // Field varMapper:Ljavax/el/VariableMapper;
      13: invokespecial #14                 // Method org/apache/el/lang/EvaluationContext."<init>":(Ljavax/el/ELContext;Ljavax/el/FunctionMapper;Ljavax/el/VariableMapper;)V
      16: astore_2
      17: aload_1
      18: aload_0
      19: invokevirtual #15                 // Method getExpressionString:()Ljava/lang/String;
      22: invokevirtual #16                 // Method javax/el/ELContext.notifyBeforeEvaluation:(Ljava/lang/String;)V
      25: aload_0
      26: invokespecial #10                 // Method getNode:()Lorg/apache/el/parser/Node;
      29: aload_2
      30: invokeinterface #41,  2           // InterfaceMethod org/apache/el/parser/Node.getValueReference:(Lorg/apache/el/lang/EvaluationContext;)Ljavax/el/ValueReference;
      35: astore_3
      36: aload_1
      37: aload_0
      38: invokevirtual #15                 // Method getExpressionString:()Ljava/lang/String;
      41: invokevirtual #18                 // Method javax/el/ELContext.notifyAfterEvaluation:(Ljava/lang/String;)V
      44: aload_3
      45: areturn
}
