Compiled from "Objects.java"
public class org.modelmapper.internal.util.Objects {
  private org.modelmapper.internal.util.Objects();
    Code:
       0: aload_0
       1: invokespecial #11                 // Method java/lang/Object."<init>":()V
       4: return

  public static <T> T firstNonNull(T...);
    Code:
       0: aload_0
       1: astore_1
       2: aload_1
       3: arraylength
       4: istore_2
       5: iconst_0
       6: istore_3
       7: iload_3
       8: iload_2
       9: if_icmpge     31
      12: aload_1
      13: iload_3
      14: aaload
      15: astore        4
      17: aload         4
      19: ifnull        25
      22: aload         4
      24: areturn
      25: iinc          3, 1
      28: goto          7
      31: aconst_null
      32: areturn

  public static <T> T firstNonNull(org.modelmapper.internal.util.Callable<T>...);
    Code:
       0: aload_0
       1: astore_1
       2: aload_1
       3: arraylength
       4: istore_2
       5: iconst_0
       6: istore_3
       7: iload_3
       8: iload_2
       9: if_icmpge     40
      12: aload_1
      13: iload_3
      14: aaload
      15: astore        4
      17: aload         4
      19: invokeinterface #31,  1           // InterfaceMethod org/modelmapper/internal/util/Callable.call:()Ljava/lang/Object;
      24: astore        5
      26: aload         5
      28: ifnull        34
      31: aload         5
      33: areturn
      34: iinc          3, 1
      37: goto          7
      40: aconst_null
      41: areturn

  public static <T> org.modelmapper.internal.util.Callable<T> callable(T);
    Code:
       0: new           #7                  // class org/modelmapper/internal/util/Objects$1
       3: dup
       4: aload_0
       5: invokespecial #41                 // Method org/modelmapper/internal/util/Objects$1."<init>":(Ljava/lang/Object;)V
       8: areturn
}
