Compiled from "ToStringBuilder.java"
class org.modelmapper.internal.util.ToStringBuilder$ArrayWrapper {
  private final java.lang.Object[] array;

  org.modelmapper.internal.util.ToStringBuilder$ArrayWrapper(java.lang.Object);
    Code:
       0: aload_0
       1: invokespecial #15                 // Method java/lang/Object."<init>":()V
       4: aload_0
       5: aload_1
       6: checkcast     #16                 // class "[Ljava/lang/Object;"
       9: checkcast     #16                 // class "[Ljava/lang/Object;"
      12: putfield      #18                 // Field array:[Ljava/lang/Object;
      15: return

  public java.lang.String toString();
    Code:
       0: aload_0
       1: getfield      #18                 // Field array:[Ljava/lang/Object;
       4: invokestatic  #28                 // Method java/util/Arrays.toString:([Ljava/lang/Object;)Ljava/lang/String;
       7: areturn
}
