Compiled from "Types.java"
public final class org.modelmapper.internal.util.Types {
  private static java.lang.Class<?> JAVASSIST_PROXY_FACTORY_CLASS;

  private static java.lang.reflect.Method JAVASSIST_IS_PROXY_CLASS_METHOD;

  public org.modelmapper.internal.util.Types();
    Code:
       0: aload_0
       1: invokespecial #14                 // Method java/lang/Object."<init>":()V
       4: return

  public static <T> java.lang.Class<T> deProxy(java.lang.Class<?>);
    Code:
       0: aload_0
       1: invokevirtual #24                 // Method java/lang/Class.isInterface:()Z
       4: ifeq          9
       7: aload_0
       8: areturn
       9: aload_0
      10: invokestatic  #28                 // Method isProxied:(Ljava/lang/Class;)Z
      13: ifeq          55
      16: aload_0
      17: invokevirtual #32                 // Method java/lang/Class.getSuperclass:()Ljava/lang/Class;
      20: astore_1
      21: aload_1
      22: ldc           #4                  // class java/lang/Object
      24: invokevirtual #36                 // Method java/lang/Object.equals:(Ljava/lang/Object;)Z
      27: ifne          41
      30: aload_1
      31: ldc           #38                 // class java/lang/reflect/Proxy
      33: invokevirtual #36                 // Method java/lang/Object.equals:(Ljava/lang/Object;)Z
      36: ifne          41
      39: aload_1
      40: areturn
      41: aload_0
      42: invokevirtual #42                 // Method java/lang/Class.getInterfaces:()[Ljava/lang/Class;
      45: astore_2
      46: aload_2
      47: arraylength
      48: ifle          55
      51: aload_2
      52: iconst_0
      53: aaload
      54: areturn
      55: aload_0
      56: areturn

  public static boolean isProxied(java.lang.Class<?>);
    Code:
       0: aload_0
       1: invokevirtual #51                 // Method java/lang/Class.getName:()Ljava/lang/String;
       4: ldc           #53                 // String $ByteBuddy$
       6: invokevirtual #59                 // Method java/lang/String.contains:(Ljava/lang/CharSequence;)Z
       9: ifeq          14
      12: iconst_1
      13: ireturn
      14: aload_0
      15: invokevirtual #51                 // Method java/lang/Class.getName:()Ljava/lang/String;
      18: ldc           #61                 // String $$EnhancerBy
      20: invokevirtual #59                 // Method java/lang/String.contains:(Ljava/lang/CharSequence;)Z
      23: ifeq          28
      26: iconst_1
      27: ireturn
      28: aload_0
      29: invokestatic  #64                 // Method java/lang/reflect/Proxy.isProxyClass:(Ljava/lang/Class;)Z
      32: ifeq          37
      35: iconst_1
      36: ireturn
      37: aload_0
      38: invokestatic  #67                 // Method isProxiedByJavassist:(Ljava/lang/Class;)Z
      41: ireturn

  private static boolean isProxiedByJavassist(java.lang.Class<?>);
    Code:
       0: getstatic     #71                 // Field JAVASSIST_IS_PROXY_CLASS_METHOD:Ljava/lang/reflect/Method;
       3: ifnull        34
       6: getstatic     #71                 // Field JAVASSIST_IS_PROXY_CLASS_METHOD:Ljava/lang/reflect/Method;
       9: aconst_null
      10: iconst_1
      11: anewarray     #4                  // class java/lang/Object
      14: dup
      15: iconst_0
      16: aload_0
      17: aastore
      18: invokevirtual #77                 // Method java/lang/reflect/Method.invoke:(Ljava/lang/Object;[Ljava/lang/Object;)Ljava/lang/Object;
      21: checkcast     #79                 // class java/lang/Boolean
      24: invokevirtual #82                 // Method java/lang/Boolean.booleanValue:()Z
      27: ifeq          34
      30: iconst_1
      31: goto          35
      34: iconst_0
      35: ireturn
      36: astore_1
      37: iconst_0
      38: ireturn
    Exception table:
       from    to  target type
           0    35    36   Class java/lang/Exception

  public static boolean isGroovyType(java.lang.Class<?>);
    Code:
       0: aload_0
       1: invokevirtual #51                 // Method java/lang/Class.getName:()Ljava/lang/String;
       4: ldc           #85                 // String org.codehaus.groovy
       6: invokevirtual #89                 // Method java/lang/String.startsWith:(Ljava/lang/String;)Z
       9: ireturn

  public static boolean isInstantiable(java.lang.Class<?>);
    Code:
       0: aload_0
       1: invokevirtual #93                 // Method java/lang/Class.isEnum:()Z
       4: ifne          27
       7: aload_0
       8: ldc           #55                 // class java/lang/String
      10: invokevirtual #96                 // Method java/lang/Class.isAssignableFrom:(Ljava/lang/Class;)Z
      13: ifne          27
      16: aload_0
      17: invokestatic  #101                // Method org/modelmapper/internal/util/Primitives.isPrimitiveWrapper:(Ljava/lang/Class;)Z
      20: ifne          27
      23: iconst_1
      24: goto          28
      27: iconst_0
      28: ireturn

  public static java.lang.Class<?> rawTypeFor(java.lang.reflect.Type);
    Code:
       0: aload_0
       1: instanceof    #20                 // class java/lang/Class
       4: ifeq          12
       7: aload_0
       8: checkcast     #20                 // class java/lang/Class
      11: areturn
      12: aload_0
      13: instanceof    #105                // class java/lang/reflect/ParameterizedType
      16: ifeq          32
      19: aload_0
      20: checkcast     #105                // class java/lang/reflect/ParameterizedType
      23: invokeinterface #109,  1          // InterfaceMethod java/lang/reflect/ParameterizedType.getRawType:()Ljava/lang/reflect/Type;
      28: checkcast     #20                 // class java/lang/Class
      31: areturn
      32: aload_0
      33: instanceof    #111                // class java/lang/reflect/GenericArrayType
      36: ifeq          61
      39: aload_0
      40: checkcast     #111                // class java/lang/reflect/GenericArrayType
      43: invokeinterface #114,  1          // InterfaceMethod java/lang/reflect/GenericArrayType.getGenericComponentType:()Ljava/lang/reflect/Type;
      48: astore_1
      49: aload_1
      50: invokestatic  #116                // Method rawTypeFor:(Ljava/lang/reflect/Type;)Ljava/lang/Class;
      53: iconst_0
      54: invokestatic  #122                // Method java/lang/reflect/Array.newInstance:(Ljava/lang/Class;I)Ljava/lang/Object;
      57: invokevirtual #125                // Method java/lang/Object.getClass:()Ljava/lang/Class;
      60: areturn
      61: aload_0
      62: instanceof    #127                // class java/lang/reflect/TypeVariable
      65: ifeq          83
      68: aload_0
      69: checkcast     #127                // class java/lang/reflect/TypeVariable
      72: invokeinterface #131,  1          // InterfaceMethod java/lang/reflect/TypeVariable.getBounds:()[Ljava/lang/reflect/Type;
      77: iconst_0
      78: aaload
      79: invokestatic  #116                // Method rawTypeFor:(Ljava/lang/reflect/Type;)Ljava/lang/Class;
      82: areturn
      83: aload_0
      84: instanceof    #133                // class java/lang/reflect/WildcardType
      87: ifeq          105
      90: aload_0
      91: checkcast     #133                // class java/lang/reflect/WildcardType
      94: invokeinterface #136,  1          // InterfaceMethod java/lang/reflect/WildcardType.getUpperBounds:()[Ljava/lang/reflect/Type;
      99: iconst_0
     100: aaload
     101: invokestatic  #116                // Method rawTypeFor:(Ljava/lang/reflect/Type;)Ljava/lang/Class;
     104: areturn
     105: aload_0
     106: ifnonnull     114
     109: ldc           #138                // String null
     111: goto          121
     114: aload_0
     115: invokevirtual #125                // Method java/lang/Object.getClass:()Ljava/lang/Class;
     118: invokevirtual #51                 // Method java/lang/Class.getName:()Ljava/lang/String;
     121: astore_1
     122: new           #140                // class java/lang/IllegalArgumentException
     125: dup
     126: new           #142                // class java/lang/StringBuilder
     129: dup
     130: invokespecial #143                // Method java/lang/StringBuilder."<init>":()V
     133: ldc           #145                // String Could not determine raw type for
     135: invokevirtual #149                // Method java/lang/StringBuilder.append:(Ljava/lang/String;)Ljava/lang/StringBuilder;
     138: aload_1
     139: invokevirtual #149                // Method java/lang/StringBuilder.append:(Ljava/lang/String;)Ljava/lang/StringBuilder;
     142: invokevirtual #152                // Method java/lang/StringBuilder.toString:()Ljava/lang/String;
     145: invokespecial #155                // Method java/lang/IllegalArgumentException."<init>":(Ljava/lang/String;)V
     148: athrow

  public static java.lang.Class<?> classFor(org.modelmapper.internal.asm.Type, java.lang.ClassLoader) throws java.lang.ClassNotFoundException;
    Code:
       0: aload_0
       1: invokevirtual #169                // Method org/modelmapper/internal/asm/Type.getSort:()I
       4: tableswitch   { // 1 to 10
                     1: 60
                     2: 64
                     3: 68
                     4: 72
                     5: 76
                     6: 84
                     7: 80
                     8: 88
                     9: 92
                    10: 113
               default: 113
          }
      60: getstatic     #172                // Field java/lang/Boolean.TYPE:Ljava/lang/Class;
      63: areturn
      64: getstatic     #175                // Field java/lang/Character.TYPE:Ljava/lang/Class;
      67: areturn
      68: getstatic     #178                // Field java/lang/Byte.TYPE:Ljava/lang/Class;
      71: areturn
      72: getstatic     #181                // Field java/lang/Short.TYPE:Ljava/lang/Class;
      75: areturn
      76: getstatic     #184                // Field java/lang/Integer.TYPE:Ljava/lang/Class;
      79: areturn
      80: getstatic     #187                // Field java/lang/Long.TYPE:Ljava/lang/Class;
      83: areturn
      84: getstatic     #190                // Field java/lang/Float.TYPE:Ljava/lang/Class;
      87: areturn
      88: getstatic     #193                // Field java/lang/Double.TYPE:Ljava/lang/Class;
      91: areturn
      92: aload_0
      93: invokevirtual #197                // Method org/modelmapper/internal/asm/Type.getElementType:()Lorg/modelmapper/internal/asm/Type;
      96: aload_1
      97: invokestatic  #199                // Method classFor:(Lorg/modelmapper/internal/asm/Type;Ljava/lang/ClassLoader;)Ljava/lang/Class;
     100: aload_0
     101: invokevirtual #202                // Method org/modelmapper/internal/asm/Type.getDimensions:()I
     104: newarray       int
     106: invokestatic  #205                // Method java/lang/reflect/Array.newInstance:(Ljava/lang/Class;[I)Ljava/lang/Object;
     109: invokevirtual #125                // Method java/lang/Object.getClass:()Ljava/lang/Class;
     112: areturn
     113: aload_0
     114: invokevirtual #208                // Method org/modelmapper/internal/asm/Type.getClassName:()Ljava/lang/String;
     117: iconst_1
     118: aload_1
     119: invokestatic  #212                // Method java/lang/Class.forName:(Ljava/lang/String;ZLjava/lang/ClassLoader;)Ljava/lang/Class;
     122: areturn

  public static java.lang.String toString(java.lang.reflect.Member);
    Code:
       0: aload_0
       1: instanceof    #73                 // class java/lang/reflect/Method
       4: ifeq          49
       7: new           #142                // class java/lang/StringBuilder
      10: dup
      11: invokespecial #143                // Method java/lang/StringBuilder."<init>":()V
      14: aload_0
      15: invokeinterface #221,  1          // InterfaceMethod java/lang/reflect/Member.getDeclaringClass:()Ljava/lang/Class;
      20: invokevirtual #51                 // Method java/lang/Class.getName:()Ljava/lang/String;
      23: invokevirtual #149                // Method java/lang/StringBuilder.append:(Ljava/lang/String;)Ljava/lang/StringBuilder;
      26: ldc           #223                // String .
      28: invokevirtual #149                // Method java/lang/StringBuilder.append:(Ljava/lang/String;)Ljava/lang/StringBuilder;
      31: aload_0
      32: invokeinterface #224,  1          // InterfaceMethod java/lang/reflect/Member.getName:()Ljava/lang/String;
      37: invokevirtual #149                // Method java/lang/StringBuilder.append:(Ljava/lang/String;)Ljava/lang/StringBuilder;
      40: ldc           #226                // String ()
      42: invokevirtual #149                // Method java/lang/StringBuilder.append:(Ljava/lang/String;)Ljava/lang/StringBuilder;
      45: invokevirtual #152                // Method java/lang/StringBuilder.toString:()Ljava/lang/String;
      48: areturn
      49: aload_0
      50: instanceof    #228                // class java/lang/reflect/Field
      53: ifeq          93
      56: new           #142                // class java/lang/StringBuilder
      59: dup
      60: invokespecial #143                // Method java/lang/StringBuilder."<init>":()V
      63: aload_0
      64: invokeinterface #221,  1          // InterfaceMethod java/lang/reflect/Member.getDeclaringClass:()Ljava/lang/Class;
      69: invokevirtual #51                 // Method java/lang/Class.getName:()Ljava/lang/String;
      72: invokevirtual #149                // Method java/lang/StringBuilder.append:(Ljava/lang/String;)Ljava/lang/StringBuilder;
      75: ldc           #223                // String .
      77: invokevirtual #149                // Method java/lang/StringBuilder.append:(Ljava/lang/String;)Ljava/lang/StringBuilder;
      80: aload_0
      81: invokeinterface #224,  1          // InterfaceMethod java/lang/reflect/Member.getName:()Ljava/lang/String;
      86: invokevirtual #149                // Method java/lang/StringBuilder.append:(Ljava/lang/String;)Ljava/lang/StringBuilder;
      89: invokevirtual #152                // Method java/lang/StringBuilder.toString:()Ljava/lang/String;
      92: areturn
      93: aload_0
      94: instanceof    #230                // class java/lang/reflect/Constructor
      97: ifeq          128
     100: new           #142                // class java/lang/StringBuilder
     103: dup
     104: invokespecial #143                // Method java/lang/StringBuilder."<init>":()V
     107: aload_0
     108: invokeinterface #221,  1          // InterfaceMethod java/lang/reflect/Member.getDeclaringClass:()Ljava/lang/Class;
     113: invokevirtual #51                 // Method java/lang/Class.getName:()Ljava/lang/String;
     116: invokevirtual #149                // Method java/lang/StringBuilder.append:(Ljava/lang/String;)Ljava/lang/StringBuilder;
     119: ldc           #232                // String .<init>()
     121: invokevirtual #149                // Method java/lang/StringBuilder.append:(Ljava/lang/String;)Ljava/lang/StringBuilder;
     124: invokevirtual #152                // Method java/lang/StringBuilder.toString:()Ljava/lang/String;
     127: areturn
     128: aconst_null
     129: areturn

  public static java.lang.String toString(java.lang.reflect.Type);
    Code:
       0: aload_0
       1: instanceof    #20                 // class java/lang/Class
       4: ifeq          17
       7: aload_0
       8: checkcast     #20                 // class java/lang/Class
      11: invokevirtual #51                 // Method java/lang/Class.getName:()Ljava/lang/String;
      14: goto          21
      17: aload_0
      18: invokevirtual #236                // Method java/lang/Object.toString:()Ljava/lang/String;
      21: areturn

  public static boolean mightContainsProperties(java.lang.Class<?>);
    Code:
       0: aload_0
       1: ldc           #4                  // class java/lang/Object
       3: if_acmpeq     49
       6: aload_0
       7: ldc           #55                 // class java/lang/String
       9: if_acmpeq     49
      12: aload_0
      13: ldc           #239                // class java/util/Date
      15: if_acmpeq     49
      18: aload_0
      19: ldc           #241                // class java/util/Calendar
      21: if_acmpeq     49
      24: aload_0
      25: invokestatic  #244                // Method org/modelmapper/internal/util/Primitives.isPrimitive:(Ljava/lang/Class;)Z
      28: ifne          49
      31: aload_0
      32: invokestatic  #249                // Method org/modelmapper/internal/util/Iterables.isIterable:(Ljava/lang/Class;)Z
      35: ifne          49
      38: aload_0
      39: invokestatic  #251                // Method isGroovyType:(Ljava/lang/Class;)Z
      42: ifne          49
      45: iconst_1
      46: goto          50
      49: iconst_0
      50: ireturn

  static {};
    Code:
       0: ldc           #2                  // class org/modelmapper/internal/util/Types
       2: invokevirtual #256                // Method java/lang/Class.getClassLoader:()Ljava/lang/ClassLoader;
       5: ldc_w         #258                // String javassist.util.proxy.ProxyFactory
       8: invokevirtual #264                // Method java/lang/ClassLoader.loadClass:(Ljava/lang/String;)Ljava/lang/Class;
      11: putstatic     #266                // Field JAVASSIST_PROXY_FACTORY_CLASS:Ljava/lang/Class;
      14: getstatic     #266                // Field JAVASSIST_PROXY_FACTORY_CLASS:Ljava/lang/Class;
      17: ldc_w         #267                // String isProxyClass
      20: iconst_1
      21: anewarray     #20                 // class java/lang/Class
      24: dup
      25: iconst_0
      26: ldc           #20                 // class java/lang/Class
      28: aastore
      29: invokevirtual #271                // Method java/lang/Class.getMethod:(Ljava/lang/String;[Ljava/lang/Class;)Ljava/lang/reflect/Method;
      32: putstatic     #71                 // Field JAVASSIST_IS_PROXY_CLASS_METHOD:Ljava/lang/reflect/Method;
      35: goto          39
      38: astore_0
      39: return
    Exception table:
       from    to  target type
           0    35    38   Class java/lang/Exception
}
