Compiled from "ULongRange.kt"
final class kotlin.ranges.ULongProgressionIterator extends kotlin.collections.ULongIterator {
  private final long finalElement;

  private boolean hasNext;

  private final long step;

  private long next;

  public boolean hasNext();
    Code:
       0: aload_0
       1: getfield      #17                 // Field hasNext:Z
       4: ireturn

  public long nextULong();
    Code:
       0: aload_0
       1: getfield      #23                 // Field next:J
       4: lstore_1
       5: lload_1
       6: aload_0
       7: getfield      #25                 // Field finalElement:J
      10: lcmp
      11: ifne          40
      14: aload_0
      15: getfield      #17                 // Field hasNext:Z
      18: ifne          32
      21: new           #27                 // class java/util/NoSuchElementException
      24: dup
      25: invokespecial #31                 // Method java/util/NoSuchElementException."<init>":()V
      28: checkcast     #33                 // class java/lang/Throwable
      31: athrow
      32: aload_0
      33: iconst_0
      34: putfield      #17                 // Field hasNext:Z
      37: goto          70
      40: aload_0
      41: dup
      42: getfield      #23                 // Field next:J
      45: lstore_3
      46: aload_0
      47: getfield      #35                 // Field step:J
      50: lstore        5
      52: astore        7
      54: lload_3
      55: lload         5
      57: ladd
      58: invokestatic  #41                 // Method kotlin/ULong."constructor-impl":(J)J
      61: lstore        8
      63: aload         7
      65: lload         8
      67: putfield      #23                 // Field next:J
      70: lload_1
      71: lreturn

  private kotlin.ranges.ULongProgressionIterator(long, long, long);
    Code:
       0: aload_0
       1: invokespecial #44                 // Method kotlin/collections/ULongIterator."<init>":()V
       4: aload_0
       5: lload_3
       6: putfield      #25                 // Field finalElement:J
       9: aload_0
      10: lload         5
      12: lconst_0
      13: lcmp
      14: ifle          45
      17: lload_1
      18: lstore        7
      20: astore        9
      22: lload         7
      24: lload_3
      25: invokestatic  #50                 // Method kotlin/UnsignedKt.ulongCompare:(JJ)I
      28: istore        10
      30: aload         9
      32: iload         10
      34: ifgt          41
      37: iconst_1
      38: goto          70
      41: iconst_0
      42: goto          70
      45: lload_1
      46: lstore        7
      48: astore        9
      50: lload         7
      52: lload_3
      53: invokestatic  #50                 // Method kotlin/UnsignedKt.ulongCompare:(JJ)I
      56: istore        10
      58: aload         9
      60: iload         10
      62: iflt          69
      65: iconst_1
      66: goto          70
      69: iconst_0
      70: putfield      #17                 // Field hasNext:Z
      73: aload_0
      74: lload         5
      76: lstore        7
      78: astore        9
      80: lload         7
      82: invokestatic  #41                 // Method kotlin/ULong."constructor-impl":(J)J
      85: lstore        10
      87: aload         9
      89: lload         10
      91: putfield      #35                 // Field step:J
      94: aload_0
      95: aload_0
      96: getfield      #17                 // Field hasNext:Z
      99: ifeq          106
     102: lload_1
     103: goto          110
     106: aload_0
     107: getfield      #25                 // Field finalElement:J
     110: putfield      #23                 // Field next:J
     113: return

  public kotlin.ranges.ULongProgressionIterator(long, long, long, kotlin.jvm.internal.DefaultConstructorMarker);
    Code:
       0: aload_0
       1: lload_1
       2: lload_3
       3: lload         5
       5: invokespecial #55                 // Method "<init>":(JJJ)V
       8: return
}
