Compiled from "TimeEvictionPolicy.java"
public class org.apache.pulsar.functions.windowing.evictors.TimeEvictionPolicy<T> implements org.apache.pulsar.functions.windowing.EvictionPolicy<T, org.apache.pulsar.functions.windowing.EvictionContext> {
  private static final org.slf4j.Logger log;

  private final long windowLength;

  protected volatile org.apache.pulsar.functions.windowing.EvictionContext evictionContext;

  private long delta;

  public org.apache.pulsar.functions.windowing.evictors.TimeEvictionPolicy(long);
    Code:
       0: aload_0
       1: invokespecial #1                  // Method java/lang/Object."<init>":()V
       4: aload_0
       5: lload_1
       6: putfield      #2                  // Field windowLength:J
       9: return

  public org.apache.pulsar.functions.windowing.EvictionPolicy$Action evict(org.apache.pulsar.functions.windowing.Event<T>);
    Code:
       0: aload_0
       1: getfield      #3                  // Field evictionContext:Lorg/apache/pulsar/functions/windowing/EvictionContext;
       4: ifnonnull     13
       7: invokestatic  #4                  // Method java/lang/System.currentTimeMillis:()J
      10: goto          25
      13: aload_0
      14: getfield      #3                  // Field evictionContext:Lorg/apache/pulsar/functions/windowing/EvictionContext;
      17: invokeinterface #5,  1            // InterfaceMethod org/apache/pulsar/functions/windowing/EvictionContext.getReferenceTime:()Ljava/lang/Long;
      22: invokevirtual #6                  // Method java/lang/Long.longValue:()J
      25: lstore_2
      26: lload_2
      27: aload_1
      28: invokeinterface #7,  1            // InterfaceMethod org/apache/pulsar/functions/windowing/Event.getTimestamp:()J
      33: lsub
      34: lstore        4
      36: lload         4
      38: aload_0
      39: getfield      #2                  // Field windowLength:J
      42: aload_0
      43: getfield      #8                  // Field delta:J
      46: ladd
      47: lcmp
      48: iflt          55
      51: getstatic     #9                  // Field org/apache/pulsar/functions/windowing/EvictionPolicy$Action.EXPIRE:Lorg/apache/pulsar/functions/windowing/EvictionPolicy$Action;
      54: areturn
      55: lload         4
      57: lconst_0
      58: lcmp
      59: ifge          66
      62: getstatic     #10                 // Field org/apache/pulsar/functions/windowing/EvictionPolicy$Action.KEEP:Lorg/apache/pulsar/functions/windowing/EvictionPolicy$Action;
      65: areturn
      66: getstatic     #11                 // Field org/apache/pulsar/functions/windowing/EvictionPolicy$Action.PROCESS:Lorg/apache/pulsar/functions/windowing/EvictionPolicy$Action;
      69: areturn

  public void track(org.apache.pulsar.functions.windowing.Event<T>);
    Code:
       0: return

  public void setContext(org.apache.pulsar.functions.windowing.EvictionContext);
    Code:
       0: aload_0
       1: getfield      #3                  // Field evictionContext:Lorg/apache/pulsar/functions/windowing/EvictionContext;
       4: astore_2
       5: aload_0
       6: aload_1
       7: putfield      #3                  // Field evictionContext:Lorg/apache/pulsar/functions/windowing/EvictionContext;
      10: aload_1
      11: invokeinterface #12,  1           // InterfaceMethod org/apache/pulsar/functions/windowing/EvictionContext.getSlidingInterval:()Ljava/lang/Long;
      16: ifnull        115
      19: aload_2
      20: ifnonnull     33
      23: aload_0
      24: ldc2_w        #14                 // long 2147483647l
      27: putfield      #8                  // Field delta:J
      30: goto          115
      33: aload_0
      34: aload_1
      35: invokeinterface #5,  1            // InterfaceMethod org/apache/pulsar/functions/windowing/EvictionContext.getReferenceTime:()Ljava/lang/Long;
      40: invokevirtual #6                  // Method java/lang/Long.longValue:()J
      43: aload_2
      44: invokeinterface #5,  1            // InterfaceMethod org/apache/pulsar/functions/windowing/EvictionContext.getReferenceTime:()Ljava/lang/Long;
      49: invokevirtual #6                  // Method java/lang/Long.longValue:()J
      52: lsub
      53: aload_1
      54: invokeinterface #12,  1           // InterfaceMethod org/apache/pulsar/functions/windowing/EvictionContext.getSlidingInterval:()Ljava/lang/Long;
      59: invokevirtual #6                  // Method java/lang/Long.longValue:()J
      62: lsub
      63: putfield      #8                  // Field delta:J
      66: aload_0
      67: getfield      #8                  // Field delta:J
      70: invokestatic  #16                 // Method java/lang/Math.abs:(J)J
      73: ldc2_w        #17                 // long 100l
      76: lcmp
      77: ifle          115
      80: getstatic     #19                 // Field log:Lorg/slf4j/Logger;
      83: ldc           #20                 // String Possible clock drift or long running computation in window; Previous eviction time: %s, current eviction time: %s
      85: iconst_2
      86: anewarray     #21                 // class java/lang/Object
      89: dup
      90: iconst_0
      91: aload_2
      92: invokeinterface #5,  1            // InterfaceMethod org/apache/pulsar/functions/windowing/EvictionContext.getReferenceTime:()Ljava/lang/Long;
      97: aastore
      98: dup
      99: iconst_1
     100: aload_1
     101: invokeinterface #5,  1            // InterfaceMethod org/apache/pulsar/functions/windowing/EvictionContext.getReferenceTime:()Ljava/lang/Long;
     106: aastore
     107: invokestatic  #22                 // Method java/lang/String.format:(Ljava/lang/String;[Ljava/lang/Object;)Ljava/lang/String;
     110: invokeinterface #23,  2           // InterfaceMethod org/slf4j/Logger.warn:(Ljava/lang/String;)V
     115: return

  public org.apache.pulsar.functions.windowing.EvictionContext getContext();
    Code:
       0: aload_0
       1: getfield      #3                  // Field evictionContext:Lorg/apache/pulsar/functions/windowing/EvictionContext;
       4: areturn

  public void reset();
    Code:
       0: return

  public org.apache.pulsar.functions.windowing.EvictionContext getState();
    Code:
       0: aload_0
       1: getfield      #3                  // Field evictionContext:Lorg/apache/pulsar/functions/windowing/EvictionContext;
       4: areturn

  public void restoreState(org.apache.pulsar.functions.windowing.EvictionContext);
    Code:
       0: aload_0
       1: aload_1
       2: putfield      #3                  // Field evictionContext:Lorg/apache/pulsar/functions/windowing/EvictionContext;
       5: return

  public java.lang.String toString();
    Code:
       0: new           #24                 // class java/lang/StringBuilder
       3: dup
       4: invokespecial #25                 // Method java/lang/StringBuilder."<init>":()V
       7: ldc           #26                 // String TimeEvictionPolicy{windowLength=
       9: invokevirtual #27                 // Method java/lang/StringBuilder.append:(Ljava/lang/String;)Ljava/lang/StringBuilder;
      12: aload_0
      13: getfield      #2                  // Field windowLength:J
      16: invokevirtual #28                 // Method java/lang/StringBuilder.append:(J)Ljava/lang/StringBuilder;
      19: ldc           #29                 // String , evictionContext=
      21: invokevirtual #27                 // Method java/lang/StringBuilder.append:(Ljava/lang/String;)Ljava/lang/StringBuilder;
      24: aload_0
      25: getfield      #3                  // Field evictionContext:Lorg/apache/pulsar/functions/windowing/EvictionContext;
      28: invokevirtual #30                 // Method java/lang/StringBuilder.append:(Ljava/lang/Object;)Ljava/lang/StringBuilder;
      31: bipush        125
      33: invokevirtual #31                 // Method java/lang/StringBuilder.append:(C)Ljava/lang/StringBuilder;
      36: invokevirtual #32                 // Method java/lang/StringBuilder.toString:()Ljava/lang/String;
      39: areturn

  public void restoreState(java.lang.Object);
    Code:
       0: aload_0
       1: aload_1
       2: checkcast     #33                 // class org/apache/pulsar/functions/windowing/EvictionContext
       5: invokevirtual #34                 // Method restoreState:(Lorg/apache/pulsar/functions/windowing/EvictionContext;)V
       8: return

  public java.lang.Object getState();
    Code:
       0: aload_0
       1: invokevirtual #35                 // Method getState:()Lorg/apache/pulsar/functions/windowing/EvictionContext;
       4: areturn

  static {};
    Code:
       0: ldc           #36                 // class org/apache/pulsar/functions/windowing/evictors/TimeEvictionPolicy
       2: invokestatic  #37                 // Method org/slf4j/LoggerFactory.getLogger:(Ljava/lang/Class;)Lorg/slf4j/Logger;
       5: putstatic     #19                 // Field log:Lorg/slf4j/Logger;
       8: return
}
