Compiled from "HttpUrlExtensions.kt"
public final class no.nav.security.mock.oauth2.extensions.HttpUrlExtensionsKt {
  public static final boolean isWellKnownUrl(okhttp3.HttpUrl);
    Code:
       0: aload_0
       1: ldc           #9                  // String <this>
       3: invokestatic  #15                 // Method kotlin/jvm/internal/Intrinsics.checkNotNullParameter:(Ljava/lang/Object;Ljava/lang/String;)V
       6: aload_0
       7: ldc           #17                 // String /.well-known/oauth-authorization-server
       9: invokestatic  #21                 // Method endsWith:(Lokhttp3/HttpUrl;Ljava/lang/String;)Z
      12: ifne          24
      15: aload_0
      16: ldc           #23                 // String /.well-known/openid-configuration
      18: invokestatic  #21                 // Method endsWith:(Lokhttp3/HttpUrl;Ljava/lang/String;)Z
      21: ifeq          28
      24: iconst_1
      25: goto          29
      28: iconst_0
      29: ireturn

  public static final boolean isAuthorizationEndpointUrl(okhttp3.HttpUrl);
    Code:
       0: aload_0
       1: ldc           #9                  // String <this>
       3: invokestatic  #15                 // Method kotlin/jvm/internal/Intrinsics.checkNotNullParameter:(Ljava/lang/Object;Ljava/lang/String;)V
       6: aload_0
       7: ldc           #28                 // String /authorize
       9: invokestatic  #21                 // Method endsWith:(Lokhttp3/HttpUrl;Ljava/lang/String;)Z
      12: ireturn

  public static final boolean isTokenEndpointUrl(okhttp3.HttpUrl);
    Code:
       0: aload_0
       1: ldc           #9                  // String <this>
       3: invokestatic  #15                 // Method kotlin/jvm/internal/Intrinsics.checkNotNullParameter:(Ljava/lang/Object;Ljava/lang/String;)V
       6: aload_0
       7: ldc           #32                 // String /token
       9: invokestatic  #21                 // Method endsWith:(Lokhttp3/HttpUrl;Ljava/lang/String;)Z
      12: ireturn

  public static final boolean isEndSessionEndpointUrl(okhttp3.HttpUrl);
    Code:
       0: aload_0
       1: ldc           #9                  // String <this>
       3: invokestatic  #15                 // Method kotlin/jvm/internal/Intrinsics.checkNotNullParameter:(Ljava/lang/Object;Ljava/lang/String;)V
       6: aload_0
       7: ldc           #36                 // String /endsession
       9: invokestatic  #21                 // Method endsWith:(Lokhttp3/HttpUrl;Ljava/lang/String;)Z
      12: ireturn

  public static final boolean isJwksUrl(okhttp3.HttpUrl);
    Code:
       0: aload_0
       1: ldc           #9                  // String <this>
       3: invokestatic  #15                 // Method kotlin/jvm/internal/Intrinsics.checkNotNullParameter:(Ljava/lang/Object;Ljava/lang/String;)V
       6: aload_0
       7: ldc           #40                 // String /jwks
       9: invokestatic  #21                 // Method endsWith:(Lokhttp3/HttpUrl;Ljava/lang/String;)Z
      12: ireturn

  public static final boolean isUserInfoUrl(okhttp3.HttpUrl);
    Code:
       0: aload_0
       1: ldc           #9                  // String <this>
       3: invokestatic  #15                 // Method kotlin/jvm/internal/Intrinsics.checkNotNullParameter:(Ljava/lang/Object;Ljava/lang/String;)V
       6: aload_0
       7: ldc           #44                 // String /userinfo
       9: invokestatic  #21                 // Method endsWith:(Lokhttp3/HttpUrl;Ljava/lang/String;)Z
      12: ireturn

  public static final boolean isIntrospectUrl(okhttp3.HttpUrl);
    Code:
       0: aload_0
       1: ldc           #9                  // String <this>
       3: invokestatic  #15                 // Method kotlin/jvm/internal/Intrinsics.checkNotNullParameter:(Ljava/lang/Object;Ljava/lang/String;)V
       6: aload_0
       7: ldc           #48                 // String /introspect
       9: invokestatic  #21                 // Method endsWith:(Lokhttp3/HttpUrl;Ljava/lang/String;)Z
      12: ireturn

  public static final boolean isDebuggerUrl(okhttp3.HttpUrl);
    Code:
       0: aload_0
       1: ldc           #9                  // String <this>
       3: invokestatic  #15                 // Method kotlin/jvm/internal/Intrinsics.checkNotNullParameter:(Ljava/lang/Object;Ljava/lang/String;)V
       6: aload_0
       7: ldc           #52                 // String /debugger
       9: invokestatic  #21                 // Method endsWith:(Lokhttp3/HttpUrl;Ljava/lang/String;)Z
      12: ireturn

  public static final boolean isDebuggerCallbackUrl(okhttp3.HttpUrl);
    Code:
       0: aload_0
       1: ldc           #9                  // String <this>
       3: invokestatic  #15                 // Method kotlin/jvm/internal/Intrinsics.checkNotNullParameter:(Ljava/lang/Object;Ljava/lang/String;)V
       6: aload_0
       7: ldc           #56                 // String /debugger/callback
       9: invokestatic  #21                 // Method endsWith:(Lokhttp3/HttpUrl;Ljava/lang/String;)Z
      12: ireturn

  public static final okhttp3.HttpUrl toOAuth2AuthorizationServerMetadataUrl(okhttp3.HttpUrl);
    Code:
       0: aload_0
       1: ldc           #9                  // String <this>
       3: invokestatic  #15                 // Method kotlin/jvm/internal/Intrinsics.checkNotNullParameter:(Ljava/lang/Object;Ljava/lang/String;)V
       6: aload_0
       7: ldc           #17                 // String /.well-known/oauth-authorization-server
       9: invokestatic  #63                 // Method issuer:(Lokhttp3/HttpUrl;Ljava/lang/String;)Lokhttp3/HttpUrl;
      12: areturn

  public static final okhttp3.HttpUrl toWellKnownUrl(okhttp3.HttpUrl);
    Code:
       0: aload_0
       1: ldc           #9                  // String <this>
       3: invokestatic  #15                 // Method kotlin/jvm/internal/Intrinsics.checkNotNullParameter:(Ljava/lang/Object;Ljava/lang/String;)V
       6: aload_0
       7: ldc           #23                 // String /.well-known/openid-configuration
       9: invokestatic  #63                 // Method issuer:(Lokhttp3/HttpUrl;Ljava/lang/String;)Lokhttp3/HttpUrl;
      12: areturn

  public static final okhttp3.HttpUrl toAuthorizationEndpointUrl(okhttp3.HttpUrl);
    Code:
       0: aload_0
       1: ldc           #9                  // String <this>
       3: invokestatic  #15                 // Method kotlin/jvm/internal/Intrinsics.checkNotNullParameter:(Ljava/lang/Object;Ljava/lang/String;)V
       6: aload_0
       7: ldc           #28                 // String /authorize
       9: invokestatic  #63                 // Method issuer:(Lokhttp3/HttpUrl;Ljava/lang/String;)Lokhttp3/HttpUrl;
      12: areturn

  public static final okhttp3.HttpUrl toEndSessionEndpointUrl(okhttp3.HttpUrl);
    Code:
       0: aload_0
       1: ldc           #9                  // String <this>
       3: invokestatic  #15                 // Method kotlin/jvm/internal/Intrinsics.checkNotNullParameter:(Ljava/lang/Object;Ljava/lang/String;)V
       6: aload_0
       7: ldc           #36                 // String /endsession
       9: invokestatic  #63                 // Method issuer:(Lokhttp3/HttpUrl;Ljava/lang/String;)Lokhttp3/HttpUrl;
      12: areturn

  public static final okhttp3.HttpUrl toRevocationEndpointUrl(okhttp3.HttpUrl);
    Code:
       0: aload_0
       1: ldc           #9                  // String <this>
       3: invokestatic  #15                 // Method kotlin/jvm/internal/Intrinsics.checkNotNullParameter:(Ljava/lang/Object;Ljava/lang/String;)V
       6: aload_0
       7: ldc           #73                 // String /revoke
       9: invokestatic  #63                 // Method issuer:(Lokhttp3/HttpUrl;Ljava/lang/String;)Lokhttp3/HttpUrl;
      12: areturn

  public static final okhttp3.HttpUrl toTokenEndpointUrl(okhttp3.HttpUrl);
    Code:
       0: aload_0
       1: ldc           #9                  // String <this>
       3: invokestatic  #15                 // Method kotlin/jvm/internal/Intrinsics.checkNotNullParameter:(Ljava/lang/Object;Ljava/lang/String;)V
       6: aload_0
       7: ldc           #32                 // String /token
       9: invokestatic  #63                 // Method issuer:(Lokhttp3/HttpUrl;Ljava/lang/String;)Lokhttp3/HttpUrl;
      12: areturn

  public static final okhttp3.HttpUrl toJwksUrl(okhttp3.HttpUrl);
    Code:
       0: aload_0
       1: ldc           #9                  // String <this>
       3: invokestatic  #15                 // Method kotlin/jvm/internal/Intrinsics.checkNotNullParameter:(Ljava/lang/Object;Ljava/lang/String;)V
       6: aload_0
       7: ldc           #40                 // String /jwks
       9: invokestatic  #63                 // Method issuer:(Lokhttp3/HttpUrl;Ljava/lang/String;)Lokhttp3/HttpUrl;
      12: areturn

  public static final okhttp3.HttpUrl toIssuerUrl(okhttp3.HttpUrl);
    Code:
       0: aload_0
       1: ldc           #9                  // String <this>
       3: invokestatic  #15                 // Method kotlin/jvm/internal/Intrinsics.checkNotNullParameter:(Ljava/lang/Object;Ljava/lang/String;)V
       6: aload_0
       7: aconst_null
       8: iconst_1
       9: aconst_null
      10: invokestatic  #83                 // Method issuer$default:(Lokhttp3/HttpUrl;Ljava/lang/String;ILjava/lang/Object;)Lokhttp3/HttpUrl;
      13: areturn

  public static final okhttp3.HttpUrl toUserInfoUrl(okhttp3.HttpUrl);
    Code:
       0: aload_0
       1: ldc           #9                  // String <this>
       3: invokestatic  #15                 // Method kotlin/jvm/internal/Intrinsics.checkNotNullParameter:(Ljava/lang/Object;Ljava/lang/String;)V
       6: aload_0
       7: ldc           #44                 // String /userinfo
       9: invokestatic  #63                 // Method issuer:(Lokhttp3/HttpUrl;Ljava/lang/String;)Lokhttp3/HttpUrl;
      12: areturn

  public static final okhttp3.HttpUrl toIntrospectUrl(okhttp3.HttpUrl);
    Code:
       0: aload_0
       1: ldc           #9                  // String <this>
       3: invokestatic  #15                 // Method kotlin/jvm/internal/Intrinsics.checkNotNullParameter:(Ljava/lang/Object;Ljava/lang/String;)V
       6: aload_0
       7: ldc           #48                 // String /introspect
       9: invokestatic  #63                 // Method issuer:(Lokhttp3/HttpUrl;Ljava/lang/String;)Lokhttp3/HttpUrl;
      12: areturn

  public static final okhttp3.HttpUrl toDebuggerUrl(okhttp3.HttpUrl);
    Code:
       0: aload_0
       1: ldc           #9                  // String <this>
       3: invokestatic  #15                 // Method kotlin/jvm/internal/Intrinsics.checkNotNullParameter:(Ljava/lang/Object;Ljava/lang/String;)V
       6: aload_0
       7: ldc           #52                 // String /debugger
       9: invokestatic  #63                 // Method issuer:(Lokhttp3/HttpUrl;Ljava/lang/String;)Lokhttp3/HttpUrl;
      12: areturn

  public static final okhttp3.HttpUrl toDebuggerCallbackUrl(okhttp3.HttpUrl);
    Code:
       0: aload_0
       1: ldc           #9                  // String <this>
       3: invokestatic  #15                 // Method kotlin/jvm/internal/Intrinsics.checkNotNullParameter:(Ljava/lang/Object;Ljava/lang/String;)V
       6: aload_0
       7: ldc           #56                 // String /debugger/callback
       9: invokestatic  #63                 // Method issuer:(Lokhttp3/HttpUrl;Ljava/lang/String;)Lokhttp3/HttpUrl;
      12: areturn

  public static final java.lang.String issuerId(okhttp3.HttpUrl);
    Code:
       0: aload_0
       1: ldc           #9                  // String <this>
       3: invokestatic  #15                 // Method kotlin/jvm/internal/Intrinsics.checkNotNullParameter:(Ljava/lang/Object;Ljava/lang/String;)V
       6: aload_0
       7: invokevirtual #100                // Method okhttp3/HttpUrl.pathSegments:()Ljava/util/List;
      10: checkcast     #102                // class java/lang/Iterable
      13: ldc           #104                // String /
      15: checkcast     #106                // class java/lang/CharSequence
      18: aconst_null
      19: aconst_null
      20: iconst_0
      21: aconst_null
      22: aconst_null
      23: bipush        62
      25: aconst_null
      26: invokestatic  #112                // Method kotlin/collections/CollectionsKt.joinToString$default:(Ljava/lang/Iterable;Ljava/lang/CharSequence;Ljava/lang/CharSequence;Ljava/lang/CharSequence;ILjava/lang/CharSequence;Lkotlin/jvm/functions/Function1;ILjava/lang/Object;)Ljava/lang/String;
      29: invokestatic  #116                // Method trimPath:(Ljava/lang/String;)Ljava/lang/String;
      32: astore_1
      33: getstatic     #122                // Field no/nav/security/mock/oauth2/extensions/OAuth2Endpoints.INSTANCE:Lno/nav/security/mock/oauth2/extensions/OAuth2Endpoints;
      36: invokevirtual #125                // Method no/nav/security/mock/oauth2/extensions/OAuth2Endpoints.getAll:()Ljava/util/List;
      39: checkcast     #102                // class java/lang/Iterable
      42: astore_2
      43: iconst_0
      44: istore_3
      45: aload_2
      46: invokeinterface #129,  1          // InterfaceMethod java/lang/Iterable.iterator:()Ljava/util/Iterator;
      51: astore        4
      53: aload         4
      55: invokeinterface #135,  1          // InterfaceMethod java/util/Iterator.hasNext:()Z
      60: ifeq          109
      63: aload         4
      65: invokeinterface #139,  1          // InterfaceMethod java/util/Iterator.next:()Ljava/lang/Object;
      70: astore        5
      72: aload         5
      74: checkcast     #141                // class java/lang/String
      77: astore        6
      79: iconst_0
      80: istore        7
      82: aload_1
      83: aload         6
      85: iconst_0
      86: iconst_2
      87: aconst_null
      88: invokestatic  #147                // Method kotlin/text/StringsKt.endsWith$default:(Ljava/lang/String;Ljava/lang/String;ZILjava/lang/Object;)Z
      91: ifeq          104
      94: aload_1
      95: aload         6
      97: aconst_null
      98: iconst_2
      99: aconst_null
     100: invokestatic  #151                // Method kotlin/text/StringsKt.substringBefore$default:(Ljava/lang/String;Ljava/lang/String;Ljava/lang/String;ILjava/lang/Object;)Ljava/lang/String;
     103: areturn
     104: nop
     105: nop
     106: goto          53
     109: nop
     110: aload_1
     111: areturn

  public static final okhttp3.HttpUrl$Builder removeAllEncodedQueryParams(okhttp3.HttpUrl$Builder, java.lang.String...);
    Code:
       0: aload_0
       1: ldc           #9                  // String <this>
       3: invokestatic  #15                 // Method kotlin/jvm/internal/Intrinsics.checkNotNullParameter:(Ljava/lang/Object;Ljava/lang/String;)V
       6: aload_1
       7: ldc           #166                // String params
       9: invokestatic  #15                 // Method kotlin/jvm/internal/Intrinsics.checkNotNullParameter:(Ljava/lang/Object;Ljava/lang/String;)V
      12: aload_0
      13: astore_2
      14: aload_2
      15: astore_3
      16: iconst_0
      17: istore        4
      19: aload_1
      20: astore        5
      22: iconst_0
      23: istore        6
      25: iconst_0
      26: istore        7
      28: aload         5
      30: arraylength
      31: istore        8
      33: iload         7
      35: iload         8
      37: if_icmpge     68
      40: aload         5
      42: iload         7
      44: aaload
      45: astore        9
      47: aload         9
      49: astore        10
      51: iconst_0
      52: istore        11
      54: aload_3
      55: aload         10
      57: invokevirtual #172                // Method okhttp3/HttpUrl$Builder.removeAllEncodedQueryParameters:(Ljava/lang/String;)Lokhttp3/HttpUrl$Builder;
      60: pop
      61: nop
      62: iinc          7, 1
      65: goto          33
      68: nop
      69: nop
      70: aload_2
      71: areturn

  public static final boolean endsWith(okhttp3.HttpUrl, java.lang.String);
    Code:
       0: aload_0
       1: ldc           #9                  // String <this>
       3: invokestatic  #15                 // Method kotlin/jvm/internal/Intrinsics.checkNotNullParameter:(Ljava/lang/Object;Ljava/lang/String;)V
       6: aload_1
       7: ldc           #181                // String path
       9: invokestatic  #15                 // Method kotlin/jvm/internal/Intrinsics.checkNotNullParameter:(Ljava/lang/Object;Ljava/lang/String;)V
      12: aload_0
      13: invokevirtual #100                // Method okhttp3/HttpUrl.pathSegments:()Ljava/util/List;
      16: checkcast     #102                // class java/lang/Iterable
      19: ldc           #104                // String /
      21: checkcast     #106                // class java/lang/CharSequence
      24: aconst_null
      25: aconst_null
      26: iconst_0
      27: aconst_null
      28: aconst_null
      29: bipush        62
      31: aconst_null
      32: invokestatic  #112                // Method kotlin/collections/CollectionsKt.joinToString$default:(Ljava/lang/Iterable;Ljava/lang/CharSequence;Ljava/lang/CharSequence;Ljava/lang/CharSequence;ILjava/lang/CharSequence;Lkotlin/jvm/functions/Function1;ILjava/lang/Object;)Ljava/lang/String;
      35: aload_1
      36: invokestatic  #116                // Method trimPath:(Ljava/lang/String;)Ljava/lang/String;
      39: iconst_0
      40: iconst_2
      41: aconst_null
      42: invokestatic  #147                // Method kotlin/text/StringsKt.endsWith$default:(Ljava/lang/String;Ljava/lang/String;ZILjava/lang/Object;)Z
      45: ireturn

  private static final java.lang.String trimPath(java.lang.String);
    Code:
       0: aload_0
       1: ldc           #104                // String /
       3: checkcast     #106                // class java/lang/CharSequence
       6: invokestatic  #186                // Method kotlin/text/StringsKt.removePrefix:(Ljava/lang/String;Ljava/lang/CharSequence;)Ljava/lang/String;
       9: ldc           #104                // String /
      11: checkcast     #106                // class java/lang/CharSequence
      14: invokestatic  #189                // Method kotlin/text/StringsKt.removeSuffix:(Ljava/lang/String;Ljava/lang/CharSequence;)Ljava/lang/String;
      17: areturn

  private static final okhttp3.HttpUrl issuer(okhttp3.HttpUrl, java.lang.String);
    Code:
       0: aload_0
       1: invokestatic  #193                // Method baseUrl:(Lokhttp3/HttpUrl;)Lokhttp3/HttpUrl;
       4: astore_2
       5: iconst_0
       6: istore_3
       7: aload_2
       8: iconst_2
       9: anewarray     #141                // class java/lang/String
      12: astore        4
      14: aload         4
      16: iconst_0
      17: aload_0
      18: invokestatic  #195                // Method issuerId:(Lokhttp3/HttpUrl;)Ljava/lang/String;
      21: aastore
      22: aload         4
      24: iconst_1
      25: aload_1
      26: aastore
      27: aload         4
      29: invokestatic  #199                // Method joinPaths:([Ljava/lang/String;)Ljava/lang/String;
      32: invokevirtual #203                // Method okhttp3/HttpUrl.resolve:(Ljava/lang/String;)Lokhttp3/HttpUrl;
      35: dup
      36: ifnonnull     57
      39: pop
      40: new           #205                // class no/nav/security/mock/oauth2/OAuth2Exception
      43: dup
      44: getstatic     #211                // Field com/nimbusds/oauth2/sdk/OAuth2Error.INVALID_REQUEST:Lcom/nimbusds/oauth2/sdk/ErrorObject;
      47: aload_1
      48: invokedynamic #222,  0            // InvokeDynamic #0:makeConcatWithConstants:(Ljava/lang/String;)Ljava/lang/String;
      53: invokespecial #226                // Method no/nav/security/mock/oauth2/OAuth2Exception."<init>":(Lcom/nimbusds/oauth2/sdk/ErrorObject;Ljava/lang/String;)V
      56: athrow
      57: nop
      58: nop
      59: areturn

  static okhttp3.HttpUrl issuer$default(okhttp3.HttpUrl, java.lang.String, int, java.lang.Object);
    Code:
       0: iload_2
       1: iconst_1
       2: iand
       3: ifeq          9
       6: ldc           #230                // String
       8: astore_1
       9: aload_0
      10: aload_1
      11: invokestatic  #63                 // Method issuer:(Lokhttp3/HttpUrl;Ljava/lang/String;)Lokhttp3/HttpUrl;
      14: areturn

  private static final java.lang.String joinPaths(java.lang.String...);
    Code:
       0: aload_0
       1: astore_1
       2: iconst_0
       3: istore_2
       4: aload_1
       5: astore_3
       6: new           #232                // class java/util/ArrayList
       9: dup
      10: invokespecial #235                // Method java/util/ArrayList."<init>":()V
      13: checkcast     #237                // class java/util/Collection
      16: astore        4
      18: iconst_0
      19: istore        5
      21: iconst_0
      22: istore        6
      24: aload_3
      25: arraylength
      26: istore        7
      28: iload         6
      30: iload         7
      32: if_icmpge     86
      35: aload_3
      36: iload         6
      38: aaload
      39: astore        8
      41: aload         8
      43: astore        9
      45: iconst_0
      46: istore        10
      48: aload         9
      50: checkcast     #106                // class java/lang/CharSequence
      53: invokeinterface #241,  1          // InterfaceMethod java/lang/CharSequence.length:()I
      58: ifle          65
      61: iconst_1
      62: goto          66
      65: iconst_0
      66: nop
      67: ifeq          80
      70: aload         4
      72: aload         8
      74: invokeinterface #245,  2          // InterfaceMethod java/util/Collection.add:(Ljava/lang/Object;)Z
      79: pop
      80: iinc          6, 1
      83: goto          28
      86: aload         4
      88: checkcast     #247                // class java/util/List
      91: nop
      92: checkcast     #102                // class java/lang/Iterable
      95: ldc           #104                // String /
      97: checkcast     #106                // class java/lang/CharSequence
     100: aconst_null
     101: aconst_null
     102: iconst_0
     103: aconst_null
     104: getstatic     #252                // Field no/nav/security/mock/oauth2/extensions/HttpUrlExtensionsKt$joinPaths$2.INSTANCE:Lno/nav/security/mock/oauth2/extensions/HttpUrlExtensionsKt$joinPaths$2;
     107: checkcast     #254                // class kotlin/jvm/functions/Function1
     110: bipush        30
     112: aconst_null
     113: invokestatic  #112                // Method kotlin/collections/CollectionsKt.joinToString$default:(Ljava/lang/Iterable;Ljava/lang/CharSequence;Ljava/lang/CharSequence;Ljava/lang/CharSequence;ILjava/lang/CharSequence;Lkotlin/jvm/functions/Function1;ILjava/lang/Object;)Ljava/lang/String;
     116: areturn

  private static final okhttp3.HttpUrl baseUrl(okhttp3.HttpUrl);
    Code:
       0: new           #168                // class okhttp3/HttpUrl$Builder
       3: dup
       4: invokespecial #263                // Method okhttp3/HttpUrl$Builder."<init>":()V
       7: aload_0
       8: invokevirtual #267                // Method okhttp3/HttpUrl.scheme:()Ljava/lang/String;
      11: invokevirtual #269                // Method okhttp3/HttpUrl$Builder.scheme:(Ljava/lang/String;)Lokhttp3/HttpUrl$Builder;
      14: aload_0
      15: invokevirtual #272                // Method okhttp3/HttpUrl.host:()Ljava/lang/String;
      18: invokevirtual #274                // Method okhttp3/HttpUrl$Builder.host:(Ljava/lang/String;)Lokhttp3/HttpUrl$Builder;
      21: aload_0
      22: invokevirtual #277                // Method okhttp3/HttpUrl.port:()I
      25: invokevirtual #280                // Method okhttp3/HttpUrl$Builder.port:(I)Lokhttp3/HttpUrl$Builder;
      28: invokevirtual #284                // Method okhttp3/HttpUrl$Builder.build:()Lokhttp3/HttpUrl;
      31: areturn

  public static final java.lang.String access$trimPath(java.lang.String);
    Code:
       0: aload_0
       1: invokestatic  #116                // Method trimPath:(Ljava/lang/String;)Ljava/lang/String;
       4: areturn
}
