Compiled from "RelatesToType.java"
public class org.apache.cxf.ws.addressing.RelatesToType {
  protected java.lang.String value;

  protected java.lang.String relationshipType;

  private java.util.Map<javax.xml.namespace.QName, java.lang.String> otherAttributes;

  public org.apache.cxf.ws.addressing.RelatesToType();
    Code:
       0: aload_0
       1: invokespecial #1                  // Method java/lang/Object."<init>":()V
       4: aload_0
       5: new           #2                  // class java/util/HashMap
       8: dup
       9: invokespecial #3                  // Method java/util/HashMap."<init>":()V
      12: putfield      #4                  // Field otherAttributes:Ljava/util/Map;
      15: return

  public java.lang.String getValue();
    Code:
       0: aload_0
       1: getfield      #5                  // Field value:Ljava/lang/String;
       4: areturn

  public void setValue(java.lang.String);
    Code:
       0: aload_0
       1: aload_1
       2: putfield      #5                  // Field value:Ljava/lang/String;
       5: return

  public java.lang.String getRelationshipType();
    Code:
       0: aload_0
       1: getfield      #6                  // Field relationshipType:Ljava/lang/String;
       4: ifnonnull     10
       7: ldc           #7                  // String http://www.w3.org/2005/08/addressing/reply
       9: areturn
      10: aload_0
      11: getfield      #6                  // Field relationshipType:Ljava/lang/String;
      14: areturn

  public void setRelationshipType(java.lang.String);
    Code:
       0: aload_0
       1: aload_1
       2: putfield      #6                  // Field relationshipType:Ljava/lang/String;
       5: return

  public java.util.Map<javax.xml.namespace.QName, java.lang.String> getOtherAttributes();
    Code:
       0: aload_0
       1: getfield      #4                  // Field otherAttributes:Ljava/util/Map;
       4: areturn
}
