Compiled from "PriorityNetworkDispatchPolicy.java"
public class org.apache.activemq.broker.region.policy.PriorityNetworkDispatchPolicy extends org.apache.activemq.broker.region.policy.SimpleDispatchPolicy {
  private static final org.slf4j.Logger LOG;

  public org.apache.activemq.broker.region.policy.PriorityNetworkDispatchPolicy();
    Code:
       0: aload_0
       1: invokespecial #1                  // Method org/apache/activemq/broker/region/policy/SimpleDispatchPolicy."<init>":()V
       4: return

  public boolean dispatch(org.apache.activemq.broker.region.MessageReference, org.apache.activemq.filter.MessageEvaluationContext, java.util.List<org.apache.activemq.broker.region.Subscription>) throws java.lang.Exception;
    Code:
       0: new           #2                  // class java/util/ArrayList
       3: dup
       4: invokespecial #3                  // Method java/util/ArrayList."<init>":()V
       7: astore        4
       9: aload_3
      10: dup
      11: astore        5
      13: monitorenter
      14: aload_3
      15: invokeinterface #4,  1            // InterfaceMethod java/util/List.iterator:()Ljava/util/Iterator;
      20: astore        6
      22: aload         6
      24: invokeinterface #5,  1            // InterfaceMethod java/util/Iterator.hasNext:()Z
      29: ifeq          241
      32: aload         6
      34: invokeinterface #6,  1            // InterfaceMethod java/util/Iterator.next:()Ljava/lang/Object;
      39: checkcast     #7                  // class org/apache/activemq/broker/region/Subscription
      42: astore        7
      44: aload         7
      46: invokeinterface #8,  1            // InterfaceMethod org/apache/activemq/broker/region/Subscription.getConsumerInfo:()Lorg/apache/activemq/command/ConsumerInfo;
      51: astore        8
      53: aload         8
      55: invokevirtual #9                  // Method org/apache/activemq/command/ConsumerInfo.isNetworkSubscription:()Z
      58: ifeq          228
      61: iconst_1
      62: istore        9
      64: aload         4
      66: invokeinterface #10,  1           // InterfaceMethod java/util/List.iterator:()Ljava/util/Iterator;
      71: astore        10
      73: aload         10
      75: invokeinterface #5,  1            // InterfaceMethod java/util/Iterator.hasNext:()Z
      80: ifeq          210
      83: aload         10
      85: invokeinterface #6,  1            // InterfaceMethod java/util/Iterator.next:()Ljava/lang/Object;
      90: checkcast     #7                  // class org/apache/activemq/broker/region/Subscription
      93: astore        11
      95: aload_0
      96: aload         11
      98: aload         8
     100: invokespecial #11                 // Method matches:(Lorg/apache/activemq/broker/region/Subscription;Lorg/apache/activemq/command/ConsumerInfo;)Z
     103: ifeq          207
     106: aload_0
     107: aload         11
     109: aload         8
     111: invokespecial #12                 // Method hasLowerPriority:(Lorg/apache/activemq/broker/region/Subscription;Lorg/apache/activemq/command/ConsumerInfo;)Z
     114: ifeq          127
     117: aload         10
     119: invokeinterface #13,  1           // InterfaceMethod java/util/Iterator.remove:()V
     124: goto          207
     127: iconst_0
     128: istore        9
     130: getstatic     #14                 // Field LOG:Lorg/slf4j/Logger;
     133: ldc           #15                 // String ignoring lower priority: {} [{}, {}] in favour of: {} [{}, {}]
     135: bipush        6
     137: anewarray     #16                 // class java/lang/Object
     140: dup
     141: iconst_0
     142: aload         11
     144: aastore
     145: dup
     146: iconst_1
     147: aload         11
     149: invokeinterface #8,  1            // InterfaceMethod org/apache/activemq/broker/region/Subscription.getConsumerInfo:()Lorg/apache/activemq/command/ConsumerInfo;
     154: invokevirtual #17                 // Method org/apache/activemq/command/ConsumerInfo.getNetworkConsumerIds:()Ljava/util/List;
     157: aastore
     158: dup
     159: iconst_2
     160: aload         11
     162: invokeinterface #8,  1            // InterfaceMethod org/apache/activemq/broker/region/Subscription.getConsumerInfo:()Lorg/apache/activemq/command/ConsumerInfo;
     167: invokevirtual #17                 // Method org/apache/activemq/command/ConsumerInfo.getNetworkConsumerIds:()Ljava/util/List;
     170: aastore
     171: dup
     172: iconst_3
     173: aload         7
     175: aastore
     176: dup
     177: iconst_4
     178: aload         7
     180: invokeinterface #8,  1            // InterfaceMethod org/apache/activemq/broker/region/Subscription.getConsumerInfo:()Lorg/apache/activemq/command/ConsumerInfo;
     185: invokevirtual #17                 // Method org/apache/activemq/command/ConsumerInfo.getNetworkConsumerIds:()Ljava/util/List;
     188: aastore
     189: dup
     190: iconst_5
     191: aload         7
     193: invokeinterface #8,  1            // InterfaceMethod org/apache/activemq/broker/region/Subscription.getConsumerInfo:()Lorg/apache/activemq/command/ConsumerInfo;
     198: invokevirtual #17                 // Method org/apache/activemq/command/ConsumerInfo.getNetworkConsumerIds:()Ljava/util/List;
     201: aastore
     202: invokeinterface #18,  3           // InterfaceMethod org/slf4j/Logger.debug:(Ljava/lang/String;[Ljava/lang/Object;)V
     207: goto          73
     210: iload         9
     212: ifeq          225
     215: aload         4
     217: aload         7
     219: invokeinterface #19,  2           // InterfaceMethod java/util/List.add:(Ljava/lang/Object;)Z
     224: pop
     225: goto          238
     228: aload         4
     230: aload         7
     232: invokeinterface #19,  2           // InterfaceMethod java/util/List.add:(Ljava/lang/Object;)Z
     237: pop
     238: goto          22
     241: aload         5
     243: monitorexit
     244: goto          255
     247: astore        12
     249: aload         5
     251: monitorexit
     252: aload         12
     254: athrow
     255: aload_0
     256: aload_1
     257: aload_2
     258: aload         4
     260: invokespecial #20                 // Method org/apache/activemq/broker/region/policy/SimpleDispatchPolicy.dispatch:(Lorg/apache/activemq/broker/region/MessageReference;Lorg/apache/activemq/filter/MessageEvaluationContext;Ljava/util/List;)Z
     263: ireturn
    Exception table:
       from    to  target type
          14   244   247   any
         247   252   247   any

  private boolean hasLowerPriority(org.apache.activemq.broker.region.Subscription, org.apache.activemq.command.ConsumerInfo);
    Code:
       0: aload_1
       1: invokeinterface #8,  1            // InterfaceMethod org/apache/activemq/broker/region/Subscription.getConsumerInfo:()Lorg/apache/activemq/command/ConsumerInfo;
       6: invokevirtual #21                 // Method org/apache/activemq/command/ConsumerInfo.getPriority:()B
       9: aload_2
      10: invokevirtual #21                 // Method org/apache/activemq/command/ConsumerInfo.getPriority:()B
      13: if_icmpge     20
      16: iconst_1
      17: goto          21
      20: iconst_0
      21: ireturn

  private boolean matches(org.apache.activemq.broker.region.Subscription, org.apache.activemq.command.ConsumerInfo);
    Code:
       0: iconst_0
       1: istore_3
       2: aload_1
       3: invokeinterface #8,  1            // InterfaceMethod org/apache/activemq/broker/region/Subscription.getConsumerInfo:()Lorg/apache/activemq/command/ConsumerInfo;
       8: invokevirtual #17                 // Method org/apache/activemq/command/ConsumerInfo.getNetworkConsumerIds:()Ljava/util/List;
      11: invokeinterface #4,  1            // InterfaceMethod java/util/List.iterator:()Ljava/util/Iterator;
      16: astore        4
      18: aload         4
      20: invokeinterface #5,  1            // InterfaceMethod java/util/Iterator.hasNext:()Z
      25: ifeq          94
      28: aload         4
      30: invokeinterface #6,  1            // InterfaceMethod java/util/Iterator.next:()Ljava/lang/Object;
      35: checkcast     #22                 // class org/apache/activemq/command/ConsumerId
      38: astore        5
      40: aload_2
      41: invokevirtual #17                 // Method org/apache/activemq/command/ConsumerInfo.getNetworkConsumerIds:()Ljava/util/List;
      44: invokeinterface #4,  1            // InterfaceMethod java/util/List.iterator:()Ljava/util/Iterator;
      49: astore        6
      51: aload         6
      53: invokeinterface #5,  1            // InterfaceMethod java/util/Iterator.hasNext:()Z
      58: ifeq          91
      61: aload         6
      63: invokeinterface #6,  1            // InterfaceMethod java/util/Iterator.next:()Ljava/lang/Object;
      68: checkcast     #22                 // class org/apache/activemq/command/ConsumerId
      71: astore        7
      73: aload         5
      75: aload         7
      77: invokevirtual #23                 // Method org/apache/activemq/command/ConsumerId.equals:(Ljava/lang/Object;)Z
      80: ifeq          88
      83: iconst_1
      84: istore_3
      85: goto          91
      88: goto          51
      91: goto          18
      94: iload_3
      95: ireturn

  static {};
    Code:
       0: ldc_w         #24                 // class org/apache/activemq/broker/region/policy/PriorityNetworkDispatchPolicy
       3: invokestatic  #25                 // Method org/slf4j/LoggerFactory.getLogger:(Ljava/lang/Class;)Lorg/slf4j/Logger;
       6: putstatic     #14                 // Field LOG:Lorg/slf4j/Logger;
       9: return
}
