Compiled from "StorePendingQueueMessageStoragePolicy.java"
public class org.apache.activemq.broker.region.policy.StorePendingQueueMessageStoragePolicy implements org.apache.activemq.broker.region.policy.PendingQueueMessageStoragePolicy {
  public org.apache.activemq.broker.region.policy.StorePendingQueueMessageStoragePolicy();
    Code:
       0: aload_0
       1: invokespecial #1                  // Method java/lang/Object."<init>":()V
       4: return

  public org.apache.activemq.broker.region.cursors.PendingMessageCursor getQueuePendingMessageCursor(org.apache.activemq.broker.Broker, org.apache.activemq.broker.region.Queue);
    Code:
       0: new           #2                  // class org/apache/activemq/broker/region/cursors/StoreQueueCursor
       3: dup
       4: aload_1
       5: aload_2
       6: invokespecial #3                  // Method org/apache/activemq/broker/region/cursors/StoreQueueCursor."<init>":(Lorg/apache/activemq/broker/Broker;Lorg/apache/activemq/broker/region/Queue;)V
       9: areturn
}
