Compiled from "DefaultDependencyResolver.java"
public class com.google.javascript.jscomp.deps.DefaultDependencyResolver implements com.google.javascript.jscomp.deps.DependencyResolver {
  static final java.lang.String CLOSURE_BASE;

  static final java.lang.String CLOSURE_BASE_PROVIDE;

  private final java.util.List<com.google.javascript.jscomp.deps.DependencyFile> depsFiles;

  private final boolean strictRequires;

  private static java.util.logging.Logger logger;

  public com.google.javascript.jscomp.deps.DefaultDependencyResolver(java.util.List<com.google.javascript.jscomp.deps.DependencyFile>, boolean);
    Code:
       0: aload_0
       1: invokespecial #1                  // Method java/lang/Object."<init>":()V
       4: aload_0
       5: aload_1
       6: putfield      #2                  // Field depsFiles:Ljava/util/List;
       9: aload_0
      10: iload_2
      11: putfield      #3                  // Field strictRequires:Z
      14: return

  public java.util.List<java.lang.String> getDependencies(java.lang.String) throws com.google.javascript.jscomp.deps.ServiceException;
    Code:
       0: aload_0
       1: aload_0
       2: aload_1
       3: iconst_1
       4: invokespecial #4                  // Method parseRequires:(Ljava/lang/String;Z)Ljava/util/Collection;
       7: invokevirtual #5                  // Method getDependencies:(Ljava/util/Collection;)Ljava/util/List;
      10: areturn

  public java.util.List<java.lang.String> getDependencies(java.util.Collection<java.lang.String>) throws com.google.javascript.jscomp.deps.ServiceException;
    Code:
       0: aload_0
       1: aload_1
       2: invokestatic  #6                  // Method com/google/common/collect/Sets.newHashSet:()Ljava/util/HashSet;
       5: invokevirtual #7                  // Method getDependencies:(Ljava/util/Collection;Ljava/util/Set;)Ljava/util/List;
       8: areturn

  public java.util.List<java.lang.String> getDependencies(java.lang.String, java.util.Set<java.lang.String>, boolean) throws com.google.javascript.jscomp.deps.ServiceException;
    Code:
       0: aload_0
       1: aload_0
       2: aload_1
       3: iload_3
       4: invokespecial #4                  // Method parseRequires:(Ljava/lang/String;Z)Ljava/util/Collection;
       7: aload_2
       8: invokevirtual #7                  // Method getDependencies:(Ljava/util/Collection;Ljava/util/Set;)Ljava/util/List;
      11: areturn

  public java.util.List<java.lang.String> getDependencies(java.util.Collection<java.lang.String>, java.util.Set<java.lang.String>) throws com.google.javascript.jscomp.deps.ServiceException;
    Code:
       0: invokestatic  #8                  // Method com/google/common/collect/Lists.newArrayList:()Ljava/util/ArrayList;
       3: astore_3
       4: aload_0
       5: getfield      #2                  // Field depsFiles:Ljava/util/List;
       8: invokeinterface #9,  1            // InterfaceMethod java/util/List.iterator:()Ljava/util/Iterator;
      13: astore        4
      15: aload         4
      17: invokeinterface #10,  1           // InterfaceMethod java/util/Iterator.hasNext:()Z
      22: ifeq          45
      25: aload         4
      27: invokeinterface #11,  1           // InterfaceMethod java/util/Iterator.next:()Ljava/lang/Object;
      32: checkcast     #12                 // class com/google/javascript/jscomp/deps/DependencyFile
      35: astore        5
      37: aload         5
      39: invokevirtual #13                 // Method com/google/javascript/jscomp/deps/DependencyFile.ensureUpToDate:()V
      42: goto          15
      45: aload_1
      46: invokeinterface #14,  1           // InterfaceMethod java/util/Collection.iterator:()Ljava/util/Iterator;
      51: astore        4
      53: aload         4
      55: invokeinterface #10,  1           // InterfaceMethod java/util/Iterator.hasNext:()Z
      60: ifeq          86
      63: aload         4
      65: invokeinterface #11,  1           // InterfaceMethod java/util/Iterator.next:()Ljava/lang/Object;
      70: checkcast     #15                 // class java/lang/String
      73: astore        5
      75: aload_0
      76: aload         5
      78: aload_2
      79: aload_3
      80: invokespecial #16                 // Method addDependency:(Ljava/lang/String;Ljava/util/Set;Ljava/util/List;)V
      83: goto          53
      86: aload_3
      87: areturn

  private void addDependency(java.lang.String, java.util.Set<java.lang.String>, java.util.List<java.lang.String>) throws com.google.javascript.jscomp.deps.ServiceException;
    Code:
       0: aload_0
       1: aload_1
       2: invokespecial #17                 // Method getDependencyInfo:(Ljava/lang/String;)Lcom/google/javascript/jscomp/deps/DependencyInfo;
       5: astore        4
       7: aload         4
       9: ifnonnull     46
      12: aload_0
      13: getfield      #3                  // Field strictRequires:Z
      16: ifeq          137
      19: new           #18                 // class com/google/javascript/jscomp/deps/ServiceException
      22: dup
      23: new           #19                 // class java/lang/StringBuilder
      26: dup
      27: invokespecial #20                 // Method java/lang/StringBuilder."<init>":()V
      30: ldc           #21                 // String Unknown require of
      32: invokevirtual #22                 // Method java/lang/StringBuilder.append:(Ljava/lang/String;)Ljava/lang/StringBuilder;
      35: aload_1
      36: invokevirtual #22                 // Method java/lang/StringBuilder.append:(Ljava/lang/String;)Ljava/lang/StringBuilder;
      39: invokevirtual #23                 // Method java/lang/StringBuilder.toString:()Ljava/lang/String;
      42: invokespecial #24                 // Method com/google/javascript/jscomp/deps/ServiceException."<init>":(Ljava/lang/String;)V
      45: athrow
      46: aload_2
      47: aload         4
      49: invokeinterface #25,  1           // InterfaceMethod com/google/javascript/jscomp/deps/DependencyInfo.getProvides:()Ljava/util/Collection;
      54: invokeinterface #26,  2           // InterfaceMethod java/util/Set.containsAll:(Ljava/util/Collection;)Z
      59: ifne          137
      62: aload_2
      63: aload         4
      65: invokeinterface #25,  1           // InterfaceMethod com/google/javascript/jscomp/deps/DependencyInfo.getProvides:()Ljava/util/Collection;
      70: invokeinterface #27,  2           // InterfaceMethod java/util/Set.addAll:(Ljava/util/Collection;)Z
      75: pop
      76: aload         4
      78: invokeinterface #28,  1           // InterfaceMethod com/google/javascript/jscomp/deps/DependencyInfo.getRequires:()Ljava/util/Collection;
      83: invokeinterface #14,  1           // InterfaceMethod java/util/Collection.iterator:()Ljava/util/Iterator;
      88: astore        5
      90: aload         5
      92: invokeinterface #10,  1           // InterfaceMethod java/util/Iterator.hasNext:()Z
      97: ifeq          123
     100: aload         5
     102: invokeinterface #11,  1           // InterfaceMethod java/util/Iterator.next:()Ljava/lang/Object;
     107: checkcast     #15                 // class java/lang/String
     110: astore        6
     112: aload_0
     113: aload         6
     115: aload_2
     116: aload_3
     117: invokespecial #16                 // Method addDependency:(Ljava/lang/String;Ljava/util/Set;Ljava/util/List;)V
     120: goto          90
     123: aload_3
     124: aload         4
     126: invokeinterface #29,  1           // InterfaceMethod com/google/javascript/jscomp/deps/DependencyInfo.getPathRelativeToClosureBase:()Ljava/lang/String;
     131: invokeinterface #30,  2           // InterfaceMethod java/util/List.add:(Ljava/lang/Object;)Z
     136: pop
     137: return

  private java.util.Collection<java.lang.String> parseRequires(java.lang.String, boolean);
    Code:
       0: new           #31                 // class com/google/javascript/jscomp/LoggerErrorManager
       3: dup
       4: getstatic     #32                 // Field logger:Ljava/util/logging/Logger;
       7: invokespecial #33                 // Method com/google/javascript/jscomp/LoggerErrorManager."<init>":(Ljava/util/logging/Logger;)V
      10: astore_3
      11: new           #34                 // class com/google/javascript/jscomp/deps/JsFileParser
      14: dup
      15: aload_3
      16: invokespecial #35                 // Method com/google/javascript/jscomp/deps/JsFileParser."<init>":(Lcom/google/javascript/jscomp/ErrorManager;)V
      19: astore        4
      21: aload         4
      23: ldc           #36                 // String <unknown path>
      25: ldc           #36                 // String <unknown path>
      27: aload_1
      28: invokevirtual #37                 // Method com/google/javascript/jscomp/deps/JsFileParser.parseFile:(Ljava/lang/String;Ljava/lang/String;Ljava/lang/String;)Lcom/google/javascript/jscomp/deps/DependencyInfo;
      31: astore        5
      33: invokestatic  #8                  // Method com/google/common/collect/Lists.newArrayList:()Ljava/util/ArrayList;
      36: astore        6
      38: iload_2
      39: ifeq          52
      42: aload         6
      44: ldc           #39                 // String goog
      46: invokeinterface #30,  2           // InterfaceMethod java/util/List.add:(Ljava/lang/Object;)Z
      51: pop
      52: aload         6
      54: aload         5
      56: invokeinterface #28,  1           // InterfaceMethod com/google/javascript/jscomp/deps/DependencyInfo.getRequires:()Ljava/util/Collection;
      61: invokeinterface #40,  2           // InterfaceMethod java/util/List.addAll:(Ljava/util/Collection;)Z
      66: pop
      67: aload_3
      68: invokeinterface #41,  1           // InterfaceMethod com/google/javascript/jscomp/ErrorManager.generateReport:()V
      73: aload         6
      75: areturn

  private com.google.javascript.jscomp.deps.DependencyInfo getDependencyInfo(java.lang.String);
    Code:
       0: aload_0
       1: getfield      #2                  // Field depsFiles:Ljava/util/List;
       4: invokeinterface #9,  1            // InterfaceMethod java/util/List.iterator:()Ljava/util/Iterator;
       9: astore_2
      10: aload_2
      11: invokeinterface #10,  1           // InterfaceMethod java/util/Iterator.hasNext:()Z
      16: ifeq          47
      19: aload_2
      20: invokeinterface #11,  1           // InterfaceMethod java/util/Iterator.next:()Ljava/lang/Object;
      25: checkcast     #12                 // class com/google/javascript/jscomp/deps/DependencyFile
      28: astore_3
      29: aload_3
      30: aload_1
      31: invokevirtual #42                 // Method com/google/javascript/jscomp/deps/DependencyFile.getDependencyInfo:(Ljava/lang/String;)Lcom/google/javascript/jscomp/deps/DependencyInfo;
      34: astore        4
      36: aload         4
      38: ifnull        44
      41: aload         4
      43: areturn
      44: goto          10
      47: aconst_null
      48: areturn

  public java.util.Collection getDependencies(java.util.Collection, java.util.Set) throws com.google.javascript.jscomp.deps.ServiceException;
    Code:
       0: aload_0
       1: aload_1
       2: aload_2
       3: invokevirtual #7                  // Method getDependencies:(Ljava/util/Collection;Ljava/util/Set;)Ljava/util/List;
       6: areturn

  public java.util.Collection getDependencies(java.lang.String, java.util.Set, boolean) throws com.google.javascript.jscomp.deps.ServiceException;
    Code:
       0: aload_0
       1: aload_1
       2: aload_2
       3: iload_3
       4: invokevirtual #43                 // Method getDependencies:(Ljava/lang/String;Ljava/util/Set;Z)Ljava/util/List;
       7: areturn

  public java.util.Collection getDependencies(java.util.Collection) throws com.google.javascript.jscomp.deps.ServiceException;
    Code:
       0: aload_0
       1: aload_1
       2: invokevirtual #5                  // Method getDependencies:(Ljava/util/Collection;)Ljava/util/List;
       5: areturn

  public java.util.Collection getDependencies(java.lang.String) throws com.google.javascript.jscomp.deps.ServiceException;
    Code:
       0: aload_0
       1: aload_1
       2: invokevirtual #44                 // Method getDependencies:(Ljava/lang/String;)Ljava/util/List;
       5: areturn

  static {};
    Code:
       0: ldc           #38                 // class com/google/javascript/jscomp/deps/DefaultDependencyResolver
       2: invokevirtual #45                 // Method java/lang/Class.getName:()Ljava/lang/String;
       5: invokestatic  #46                 // Method java/util/logging/Logger.getLogger:(Ljava/lang/String;)Ljava/util/logging/Logger;
       8: putstatic     #32                 // Field logger:Ljava/util/logging/Logger;
      11: return
}
