Compiled from "ResourceAdminServiceClient.java"
public class org.wso2.esb.integration.common.clients.registry.ResourceAdminServiceClient {
  private static final org.apache.commons.logging.Log log;

  private final java.lang.String serviceName;

  private org.wso2.carbon.registry.resource.stub.ResourceAdminServiceStub resourceAdminServiceStub;

  private static final java.lang.String MEDIA_TYPE_WSDL;

  private static final java.lang.String MEDIA_TYPE_WADL;

  private static final java.lang.String MEDIA_TYPE_SCHEMA;

  private static final java.lang.String MEDIA_TYPE_POLICY;

  private static final java.lang.String MEDIA_TYPE_GOVERNANCE_ARCHIVE;

  public org.wso2.esb.integration.common.clients.registry.ResourceAdminServiceClient(java.lang.String, java.lang.String) throws org.apache.axis2.AxisFault;
    Code:
       0: aload_0
       1: invokespecial #1                  // Method java/lang/Object."<init>":()V
       4: aload_0
       5: ldc           #2                  // String ResourceAdminService
       7: putfield      #3                  // Field serviceName:Ljava/lang/String;
      10: new           #4                  // class java/lang/StringBuilder
      13: dup
      14: invokespecial #5                  // Method java/lang/StringBuilder."<init>":()V
      17: aload_1
      18: invokevirtual #6                  // Method java/lang/StringBuilder.append:(Ljava/lang/String;)Ljava/lang/StringBuilder;
      21: ldc           #2                  // String ResourceAdminService
      23: invokevirtual #6                  // Method java/lang/StringBuilder.append:(Ljava/lang/String;)Ljava/lang/StringBuilder;
      26: invokevirtual #8                  // Method java/lang/StringBuilder.toString:()Ljava/lang/String;
      29: astore_3
      30: aload_0
      31: new           #9                  // class org/wso2/carbon/registry/resource/stub/ResourceAdminServiceStub
      34: dup
      35: aload_3
      36: invokespecial #10                 // Method org/wso2/carbon/registry/resource/stub/ResourceAdminServiceStub."<init>":(Ljava/lang/String;)V
      39: putfield      #11                 // Field resourceAdminServiceStub:Lorg/wso2/carbon/registry/resource/stub/ResourceAdminServiceStub;
      42: aload_2
      43: aload_0
      44: getfield      #11                 // Field resourceAdminServiceStub:Lorg/wso2/carbon/registry/resource/stub/ResourceAdminServiceStub;
      47: invokestatic  #12                 // Method org/wso2/esb/integration/common/clients/client/utils/AuthenticateStub.authenticateStub:(Ljava/lang/String;Lorg/apache/axis2/client/Stub;)V
      50: return

  public org.wso2.esb.integration.common.clients.registry.ResourceAdminServiceClient(java.lang.String, java.lang.String, java.lang.String) throws org.apache.axis2.AxisFault;
    Code:
       0: aload_0
       1: invokespecial #1                  // Method java/lang/Object."<init>":()V
       4: aload_0
       5: ldc           #2                  // String ResourceAdminService
       7: putfield      #3                  // Field serviceName:Ljava/lang/String;
      10: new           #4                  // class java/lang/StringBuilder
      13: dup
      14: invokespecial #5                  // Method java/lang/StringBuilder."<init>":()V
      17: aload_1
      18: invokevirtual #6                  // Method java/lang/StringBuilder.append:(Ljava/lang/String;)Ljava/lang/StringBuilder;
      21: ldc           #2                  // String ResourceAdminService
      23: invokevirtual #6                  // Method java/lang/StringBuilder.append:(Ljava/lang/String;)Ljava/lang/StringBuilder;
      26: invokevirtual #8                  // Method java/lang/StringBuilder.toString:()Ljava/lang/String;
      29: astore        4
      31: aload_0
      32: new           #9                  // class org/wso2/carbon/registry/resource/stub/ResourceAdminServiceStub
      35: dup
      36: aload         4
      38: invokespecial #10                 // Method org/wso2/carbon/registry/resource/stub/ResourceAdminServiceStub."<init>":(Ljava/lang/String;)V
      41: putfield      #11                 // Field resourceAdminServiceStub:Lorg/wso2/carbon/registry/resource/stub/ResourceAdminServiceStub;
      44: aload_2
      45: aload_3
      46: aload_0
      47: getfield      #11                 // Field resourceAdminServiceStub:Lorg/wso2/carbon/registry/resource/stub/ResourceAdminServiceStub;
      50: invokestatic  #13                 // Method org/wso2/esb/integration/common/clients/client/utils/AuthenticateStub.authenticateStub:(Ljava/lang/String;Ljava/lang/String;Lorg/apache/axis2/client/Stub;)V
      53: return

  public boolean addResource(java.lang.String, java.lang.String, java.lang.String, javax.activation.DataHandler) throws org.wso2.carbon.registry.resource.stub.ResourceAdminServiceExceptionException, java.rmi.RemoteException;
    Code:
       0: getstatic     #14                 // Field log:Lorg/apache/commons/logging/Log;
       3: invokeinterface #15,  1           // InterfaceMethod org/apache/commons/logging/Log.isDebugEnabled:()Z
       8: ifeq          65
      11: getstatic     #14                 // Field log:Lorg/apache/commons/logging/Log;
      14: new           #4                  // class java/lang/StringBuilder
      17: dup
      18: invokespecial #5                  // Method java/lang/StringBuilder."<init>":()V
      21: ldc           #16                 // String Destination Path :
      23: invokevirtual #6                  // Method java/lang/StringBuilder.append:(Ljava/lang/String;)Ljava/lang/StringBuilder;
      26: aload_1
      27: invokevirtual #6                  // Method java/lang/StringBuilder.append:(Ljava/lang/String;)Ljava/lang/StringBuilder;
      30: invokevirtual #8                  // Method java/lang/StringBuilder.toString:()Ljava/lang/String;
      33: invokeinterface #17,  2           // InterfaceMethod org/apache/commons/logging/Log.debug:(Ljava/lang/Object;)V
      38: getstatic     #14                 // Field log:Lorg/apache/commons/logging/Log;
      41: new           #4                  // class java/lang/StringBuilder
      44: dup
      45: invokespecial #5                  // Method java/lang/StringBuilder."<init>":()V
      48: ldc           #18                 // String Media Type :
      50: invokevirtual #6                  // Method java/lang/StringBuilder.append:(Ljava/lang/String;)Ljava/lang/StringBuilder;
      53: aload_2
      54: invokevirtual #6                  // Method java/lang/StringBuilder.append:(Ljava/lang/String;)Ljava/lang/StringBuilder;
      57: invokevirtual #8                  // Method java/lang/StringBuilder.toString:()Ljava/lang/String;
      60: invokeinterface #17,  2           // InterfaceMethod org/apache/commons/logging/Log.debug:(Ljava/lang/Object;)V
      65: aload_0
      66: getfield      #11                 // Field resourceAdminServiceStub:Lorg/wso2/carbon/registry/resource/stub/ResourceAdminServiceStub;
      69: aload_1
      70: aload_2
      71: aload_3
      72: aload         4
      74: aconst_null
      75: aconst_null
      76: invokevirtual #19                 // Method org/wso2/carbon/registry/resource/stub/ResourceAdminServiceStub.addResource:(Ljava/lang/String;Ljava/lang/String;Ljava/lang/String;Ljavax/activation/DataHandler;Ljava/lang/String;[Lorg/wso2/carbon/registry/resource/stub/services/ArrayOfString;)Z
      79: ireturn

  public org.wso2.carbon.registry.resource.stub.common.xsd.ResourceData[] getResource(java.lang.String) throws org.wso2.carbon.registry.resource.stub.ResourceAdminServiceExceptionException, java.rmi.RemoteException;
    Code:
       0: aload_0
       1: getfield      #11                 // Field resourceAdminServiceStub:Lorg/wso2/carbon/registry/resource/stub/ResourceAdminServiceStub;
       4: iconst_1
       5: anewarray     #20                 // class java/lang/String
       8: dup
       9: iconst_0
      10: aload_1
      11: aastore
      12: invokevirtual #21                 // Method org/wso2/carbon/registry/resource/stub/ResourceAdminServiceStub.getResourceData:([Ljava/lang/String;)[Lorg/wso2/carbon/registry/resource/stub/common/xsd/ResourceData;
      15: astore_2
      16: aload_2
      17: areturn

  public org.wso2.carbon.registry.resource.stub.beans.xsd.CollectionContentBean getCollectionContent(java.lang.String) throws java.rmi.RemoteException, org.wso2.carbon.registry.resource.stub.ResourceAdminServiceExceptionException;
    Code:
       0: aload_0
       1: getfield      #11                 // Field resourceAdminServiceStub:Lorg/wso2/carbon/registry/resource/stub/ResourceAdminServiceStub;
       4: aload_1
       5: invokevirtual #22                 // Method org/wso2/carbon/registry/resource/stub/ResourceAdminServiceStub.getCollectionContent:(Ljava/lang/String;)Lorg/wso2/carbon/registry/resource/stub/beans/xsd/CollectionContentBean;
       8: astore_2
       9: goto          74
      12: astore_3
      13: getstatic     #14                 // Field log:Lorg/apache/commons/logging/Log;
      16: new           #4                  // class java/lang/StringBuilder
      19: dup
      20: invokespecial #5                  // Method java/lang/StringBuilder."<init>":()V
      23: ldc           #24                 // String Resource getting failed due to RemoteException :
      25: invokevirtual #6                  // Method java/lang/StringBuilder.append:(Ljava/lang/String;)Ljava/lang/StringBuilder;
      28: aload_3
      29: invokevirtual #25                 // Method java/lang/StringBuilder.append:(Ljava/lang/Object;)Ljava/lang/StringBuilder;
      32: invokevirtual #8                  // Method java/lang/StringBuilder.toString:()Ljava/lang/String;
      35: invokeinterface #26,  2           // InterfaceMethod org/apache/commons/logging/Log.error:(Ljava/lang/Object;)V
      40: new           #23                 // class java/rmi/RemoteException
      43: dup
      44: ldc           #27                 // String Resource getting failed due to RemoteException :
      46: aload_3
      47: invokespecial #28                 // Method java/rmi/RemoteException."<init>":(Ljava/lang/String;Ljava/lang/Throwable;)V
      50: athrow
      51: astore_3
      52: getstatic     #14                 // Field log:Lorg/apache/commons/logging/Log;
      55: ldc           #30                 // String Resource getting failed due to ResourceAdminServiceExceptionException :
      57: aload_3
      58: invokeinterface #31,  3           // InterfaceMethod org/apache/commons/logging/Log.error:(Ljava/lang/Object;Ljava/lang/Throwable;)V
      63: new           #29                 // class org/wso2/carbon/registry/resource/stub/ResourceAdminServiceExceptionException
      66: dup
      67: ldc           #32                 // String Resource getting failed due to ResourceAdminServiceExceptionException:
      69: aload_3
      70: invokespecial #33                 // Method org/wso2/carbon/registry/resource/stub/ResourceAdminServiceExceptionException."<init>":(Ljava/lang/String;Ljava/lang/Throwable;)V
      73: athrow
      74: aload_2
      75: areturn
    Exception table:
       from    to  target type
           0     9    12   Class java/rmi/RemoteException
           0     9    51   Class org/wso2/carbon/registry/resource/stub/ResourceAdminServiceExceptionException

  public boolean deleteResource(java.lang.String) throws org.wso2.carbon.registry.resource.stub.ResourceAdminServiceExceptionException, java.rmi.RemoteException;
    Code:
       0: aload_0
       1: getfield      #11                 // Field resourceAdminServiceStub:Lorg/wso2/carbon/registry/resource/stub/ResourceAdminServiceStub;
       4: aload_1
       5: invokevirtual #34                 // Method org/wso2/carbon/registry/resource/stub/ResourceAdminServiceStub.delete:(Ljava/lang/String;)Z
       8: ireturn

  public void addWSDL(java.lang.String, javax.activation.DataHandler) throws org.wso2.carbon.registry.resource.stub.ResourceAdminServiceExceptionException, java.rmi.RemoteException;
    Code:
       0: aload_2
       1: invokevirtual #35                 // Method javax/activation/DataHandler.getName:()Ljava/lang/String;
       4: aload_2
       5: invokevirtual #35                 // Method javax/activation/DataHandler.getName:()Ljava/lang/String;
       8: bipush        47
      10: invokevirtual #36                 // Method java/lang/String.lastIndexOf:(I)I
      13: iconst_1
      14: iadd
      15: invokevirtual #37                 // Method java/lang/String.substring:(I)Ljava/lang/String;
      18: astore_3
      19: getstatic     #14                 // Field log:Lorg/apache/commons/logging/Log;
      22: aload_3
      23: invokeinterface #17,  2           // InterfaceMethod org/apache/commons/logging/Log.debug:(Ljava/lang/Object;)V
      28: aload_0
      29: getfield      #11                 // Field resourceAdminServiceStub:Lorg/wso2/carbon/registry/resource/stub/ResourceAdminServiceStub;
      32: new           #4                  // class java/lang/StringBuilder
      35: dup
      36: invokespecial #5                  // Method java/lang/StringBuilder."<init>":()V
      39: ldc           #38                 // String /
      41: invokevirtual #6                  // Method java/lang/StringBuilder.append:(Ljava/lang/String;)Ljava/lang/StringBuilder;
      44: aload_3
      45: invokevirtual #6                  // Method java/lang/StringBuilder.append:(Ljava/lang/String;)Ljava/lang/StringBuilder;
      48: invokevirtual #8                  // Method java/lang/StringBuilder.toString:()Ljava/lang/String;
      51: ldc           #39                 // String application/wsdl+xml
      53: aload_1
      54: aload_2
      55: aconst_null
      56: aconst_null
      57: invokevirtual #19                 // Method org/wso2/carbon/registry/resource/stub/ResourceAdminServiceStub.addResource:(Ljava/lang/String;Ljava/lang/String;Ljava/lang/String;Ljavax/activation/DataHandler;Ljava/lang/String;[Lorg/wso2/carbon/registry/resource/stub/services/ArrayOfString;)Z
      60: pop
      61: return

  public void addWADL(java.lang.String, javax.activation.DataHandler) throws org.wso2.carbon.registry.resource.stub.ResourceAdminServiceExceptionException, java.rmi.RemoteException;
    Code:
       0: aload_2
       1: invokevirtual #35                 // Method javax/activation/DataHandler.getName:()Ljava/lang/String;
       4: aload_2
       5: invokevirtual #35                 // Method javax/activation/DataHandler.getName:()Ljava/lang/String;
       8: bipush        47
      10: invokevirtual #36                 // Method java/lang/String.lastIndexOf:(I)I
      13: iconst_1
      14: iadd
      15: invokevirtual #37                 // Method java/lang/String.substring:(I)Ljava/lang/String;
      18: astore_3
      19: getstatic     #14                 // Field log:Lorg/apache/commons/logging/Log;
      22: aload_3
      23: invokeinterface #17,  2           // InterfaceMethod org/apache/commons/logging/Log.debug:(Ljava/lang/Object;)V
      28: aload_0
      29: getfield      #11                 // Field resourceAdminServiceStub:Lorg/wso2/carbon/registry/resource/stub/ResourceAdminServiceStub;
      32: new           #4                  // class java/lang/StringBuilder
      35: dup
      36: invokespecial #5                  // Method java/lang/StringBuilder."<init>":()V
      39: ldc           #38                 // String /
      41: invokevirtual #6                  // Method java/lang/StringBuilder.append:(Ljava/lang/String;)Ljava/lang/StringBuilder;
      44: aload_3
      45: invokevirtual #6                  // Method java/lang/StringBuilder.append:(Ljava/lang/String;)Ljava/lang/StringBuilder;
      48: invokevirtual #8                  // Method java/lang/StringBuilder.toString:()Ljava/lang/String;
      51: ldc           #40                 // String application/wadl+xml
      53: aload_1
      54: aload_2
      55: aconst_null
      56: aconst_null
      57: invokevirtual #19                 // Method org/wso2/carbon/registry/resource/stub/ResourceAdminServiceStub.addResource:(Ljava/lang/String;Ljava/lang/String;Ljava/lang/String;Ljavax/activation/DataHandler;Ljava/lang/String;[Lorg/wso2/carbon/registry/resource/stub/services/ArrayOfString;)Z
      60: pop
      61: return

  public void addWSDL(java.lang.String, java.lang.String, java.lang.String) throws org.wso2.carbon.registry.resource.stub.ResourceAdminServiceExceptionException, java.rmi.RemoteException;
    Code:
       0: aload_0
       1: getfield      #11                 // Field resourceAdminServiceStub:Lorg/wso2/carbon/registry/resource/stub/ResourceAdminServiceStub;
       4: ldc           #38                 // String /
       6: aload_1
       7: ldc           #39                 // String application/wsdl+xml
       9: aload_2
      10: aload_3
      11: aconst_null
      12: aconst_null
      13: invokevirtual #41                 // Method org/wso2/carbon/registry/resource/stub/ResourceAdminServiceStub.importResource:(Ljava/lang/String;Ljava/lang/String;Ljava/lang/String;Ljava/lang/String;Ljava/lang/String;Ljava/lang/String;[Lorg/wso2/carbon/registry/resource/stub/services/ArrayOfString;)Z
      16: pop
      17: return

  public void addWADL(java.lang.String, java.lang.String, java.lang.String) throws org.wso2.carbon.registry.resource.stub.ResourceAdminServiceExceptionException, java.rmi.RemoteException;
    Code:
       0: aload_0
       1: getfield      #11                 // Field resourceAdminServiceStub:Lorg/wso2/carbon/registry/resource/stub/ResourceAdminServiceStub;
       4: ldc           #38                 // String /
       6: aload_1
       7: ldc           #40                 // String application/wadl+xml
       9: aload_2
      10: aload_3
      11: aconst_null
      12: aconst_null
      13: invokevirtual #41                 // Method org/wso2/carbon/registry/resource/stub/ResourceAdminServiceStub.importResource:(Ljava/lang/String;Ljava/lang/String;Ljava/lang/String;Ljava/lang/String;Ljava/lang/String;Ljava/lang/String;[Lorg/wso2/carbon/registry/resource/stub/services/ArrayOfString;)Z
      16: pop
      17: return

  public void addSchema(java.lang.String, javax.activation.DataHandler) throws org.wso2.carbon.registry.resource.stub.ResourceAdminServiceExceptionException, java.rmi.RemoteException;
    Code:
       0: aload_2
       1: invokevirtual #35                 // Method javax/activation/DataHandler.getName:()Ljava/lang/String;
       4: aload_2
       5: invokevirtual #35                 // Method javax/activation/DataHandler.getName:()Ljava/lang/String;
       8: bipush        47
      10: invokevirtual #36                 // Method java/lang/String.lastIndexOf:(I)I
      13: iconst_1
      14: iadd
      15: invokevirtual #37                 // Method java/lang/String.substring:(I)Ljava/lang/String;
      18: astore_3
      19: aload_0
      20: getfield      #11                 // Field resourceAdminServiceStub:Lorg/wso2/carbon/registry/resource/stub/ResourceAdminServiceStub;
      23: new           #4                  // class java/lang/StringBuilder
      26: dup
      27: invokespecial #5                  // Method java/lang/StringBuilder."<init>":()V
      30: ldc           #38                 // String /
      32: invokevirtual #6                  // Method java/lang/StringBuilder.append:(Ljava/lang/String;)Ljava/lang/StringBuilder;
      35: aload_3
      36: invokevirtual #6                  // Method java/lang/StringBuilder.append:(Ljava/lang/String;)Ljava/lang/StringBuilder;
      39: invokevirtual #8                  // Method java/lang/StringBuilder.toString:()Ljava/lang/String;
      42: ldc           #42                 // String application/x-xsd+xml
      44: aload_1
      45: aload_2
      46: aconst_null
      47: aconst_null
      48: invokevirtual #19                 // Method org/wso2/carbon/registry/resource/stub/ResourceAdminServiceStub.addResource:(Ljava/lang/String;Ljava/lang/String;Ljava/lang/String;Ljavax/activation/DataHandler;Ljava/lang/String;[Lorg/wso2/carbon/registry/resource/stub/services/ArrayOfString;)Z
      51: pop
      52: return

  public void addSchema(java.lang.String, java.lang.String, java.lang.String) throws org.wso2.carbon.registry.resource.stub.ResourceAdminServiceExceptionException, java.rmi.RemoteException;
    Code:
       0: aload_0
       1: getfield      #11                 // Field resourceAdminServiceStub:Lorg/wso2/carbon/registry/resource/stub/ResourceAdminServiceStub;
       4: ldc           #38                 // String /
       6: aload_1
       7: ldc           #42                 // String application/x-xsd+xml
       9: aload_2
      10: aload_3
      11: aconst_null
      12: aconst_null
      13: invokevirtual #41                 // Method org/wso2/carbon/registry/resource/stub/ResourceAdminServiceStub.importResource:(Ljava/lang/String;Ljava/lang/String;Ljava/lang/String;Ljava/lang/String;Ljava/lang/String;Ljava/lang/String;[Lorg/wso2/carbon/registry/resource/stub/services/ArrayOfString;)Z
      16: pop
      17: return

  public void addPolicy(java.lang.String, javax.activation.DataHandler) throws org.wso2.carbon.registry.resource.stub.ResourceAdminServiceExceptionException, java.rmi.RemoteException;
    Code:
       0: aload_2
       1: invokevirtual #35                 // Method javax/activation/DataHandler.getName:()Ljava/lang/String;
       4: aload_2
       5: invokevirtual #35                 // Method javax/activation/DataHandler.getName:()Ljava/lang/String;
       8: bipush        47
      10: invokevirtual #36                 // Method java/lang/String.lastIndexOf:(I)I
      13: iconst_1
      14: iadd
      15: invokevirtual #37                 // Method java/lang/String.substring:(I)Ljava/lang/String;
      18: astore_3
      19: aload_0
      20: getfield      #11                 // Field resourceAdminServiceStub:Lorg/wso2/carbon/registry/resource/stub/ResourceAdminServiceStub;
      23: new           #4                  // class java/lang/StringBuilder
      26: dup
      27: invokespecial #5                  // Method java/lang/StringBuilder."<init>":()V
      30: ldc           #38                 // String /
      32: invokevirtual #6                  // Method java/lang/StringBuilder.append:(Ljava/lang/String;)Ljava/lang/StringBuilder;
      35: aload_3
      36: invokevirtual #6                  // Method java/lang/StringBuilder.append:(Ljava/lang/String;)Ljava/lang/StringBuilder;
      39: invokevirtual #8                  // Method java/lang/StringBuilder.toString:()Ljava/lang/String;
      42: ldc           #43                 // String application/policy+xml
      44: aload_1
      45: aload_2
      46: aconst_null
      47: aconst_null
      48: invokevirtual #19                 // Method org/wso2/carbon/registry/resource/stub/ResourceAdminServiceStub.addResource:(Ljava/lang/String;Ljava/lang/String;Ljava/lang/String;Ljavax/activation/DataHandler;Ljava/lang/String;[Lorg/wso2/carbon/registry/resource/stub/services/ArrayOfString;)Z
      51: pop
      52: return

  public void addPolicy(java.lang.String, java.lang.String, java.lang.String) throws org.wso2.carbon.registry.resource.stub.ResourceAdminServiceExceptionException, java.rmi.RemoteException;
    Code:
       0: aload_0
       1: getfield      #11                 // Field resourceAdminServiceStub:Lorg/wso2/carbon/registry/resource/stub/ResourceAdminServiceStub;
       4: ldc           #38                 // String /
       6: aload_1
       7: ldc           #43                 // String application/policy+xml
       9: aload_2
      10: aload_3
      11: aconst_null
      12: aconst_null
      13: invokevirtual #41                 // Method org/wso2/carbon/registry/resource/stub/ResourceAdminServiceStub.importResource:(Ljava/lang/String;Ljava/lang/String;Ljava/lang/String;Ljava/lang/String;Ljava/lang/String;Ljava/lang/String;[Lorg/wso2/carbon/registry/resource/stub/services/ArrayOfString;)Z
      16: pop
      17: return

  public void uploadArtifact(java.lang.String, javax.activation.DataHandler) throws org.wso2.carbon.registry.resource.stub.ResourceAdminServiceExceptionException, java.rmi.RemoteException;
    Code:
       0: aload_2
       1: invokevirtual #35                 // Method javax/activation/DataHandler.getName:()Ljava/lang/String;
       4: aload_2
       5: invokevirtual #35                 // Method javax/activation/DataHandler.getName:()Ljava/lang/String;
       8: bipush        47
      10: invokevirtual #36                 // Method java/lang/String.lastIndexOf:(I)I
      13: iconst_1
      14: iadd
      15: invokevirtual #37                 // Method java/lang/String.substring:(I)Ljava/lang/String;
      18: astore_3
      19: aload_0
      20: getfield      #11                 // Field resourceAdminServiceStub:Lorg/wso2/carbon/registry/resource/stub/ResourceAdminServiceStub;
      23: new           #4                  // class java/lang/StringBuilder
      26: dup
      27: invokespecial #5                  // Method java/lang/StringBuilder."<init>":()V
      30: ldc           #38                 // String /
      32: invokevirtual #6                  // Method java/lang/StringBuilder.append:(Ljava/lang/String;)Ljava/lang/StringBuilder;
      35: aload_3
      36: invokevirtual #6                  // Method java/lang/StringBuilder.append:(Ljava/lang/String;)Ljava/lang/StringBuilder;
      39: invokevirtual #8                  // Method java/lang/StringBuilder.toString:()Ljava/lang/String;
      42: ldc           #44                 // String application/vnd.wso2.governance-archive
      44: aload_1
      45: aload_2
      46: aconst_null
      47: aconst_null
      48: invokevirtual #19                 // Method org/wso2/carbon/registry/resource/stub/ResourceAdminServiceStub.addResource:(Ljava/lang/String;Ljava/lang/String;Ljava/lang/String;Ljavax/activation/DataHandler;Ljava/lang/String;[Lorg/wso2/carbon/registry/resource/stub/services/ArrayOfString;)Z
      51: pop
      52: return

  public java.lang.String addCollection(java.lang.String, java.lang.String, java.lang.String, java.lang.String) throws org.wso2.carbon.registry.resource.stub.ResourceAdminServiceExceptionException, java.rmi.RemoteException;
    Code:
       0: aload_0
       1: getfield      #11                 // Field resourceAdminServiceStub:Lorg/wso2/carbon/registry/resource/stub/ResourceAdminServiceStub;
       4: aload_1
       5: aload_2
       6: aload_3
       7: aload         4
       9: invokevirtual #45                 // Method org/wso2/carbon/registry/resource/stub/ResourceAdminServiceStub.addCollection:(Ljava/lang/String;Ljava/lang/String;Ljava/lang/String;Ljava/lang/String;)Ljava/lang/String;
      12: areturn

  public void addSymbolicLink(java.lang.String, java.lang.String, java.lang.String) throws org.wso2.carbon.registry.resource.stub.ResourceAdminServiceExceptionException, java.rmi.RemoteException;
    Code:
       0: aload_0
       1: getfield      #11                 // Field resourceAdminServiceStub:Lorg/wso2/carbon/registry/resource/stub/ResourceAdminServiceStub;
       4: aload_1
       5: aload_2
       6: aload_3
       7: invokevirtual #46                 // Method org/wso2/carbon/registry/resource/stub/ResourceAdminServiceStub.addSymbolicLink:(Ljava/lang/String;Ljava/lang/String;Ljava/lang/String;)V
      10: return

  public void addTextResource(java.lang.String, java.lang.String, java.lang.String, java.lang.String, java.lang.String) throws java.rmi.RemoteException, org.wso2.carbon.registry.resource.stub.ResourceAdminServiceExceptionException;
    Code:
       0: aload_0
       1: getfield      #11                 // Field resourceAdminServiceStub:Lorg/wso2/carbon/registry/resource/stub/ResourceAdminServiceStub;
       4: aload_1
       5: aload_2
       6: aload_3
       7: aload         4
       9: aload         5
      11: invokevirtual #47                 // Method org/wso2/carbon/registry/resource/stub/ResourceAdminServiceStub.addTextResource:(Ljava/lang/String;Ljava/lang/String;Ljava/lang/String;Ljava/lang/String;Ljava/lang/String;)Z
      14: pop
      15: return

  public void addResourcePermission(java.lang.String, java.lang.String, java.lang.String, java.lang.String) throws java.rmi.RemoteException, org.wso2.carbon.registry.resource.stub.ResourceAdminServiceResourceServiceExceptionException;
    Code:
       0: aload_0
       1: getfield      #11                 // Field resourceAdminServiceStub:Lorg/wso2/carbon/registry/resource/stub/ResourceAdminServiceStub;
       4: aload_1
       5: aload_2
       6: aload_3
       7: aload         4
       9: invokevirtual #48                 // Method org/wso2/carbon/registry/resource/stub/ResourceAdminServiceStub.addRolePermission:(Ljava/lang/String;Ljava/lang/String;Ljava/lang/String;Ljava/lang/String;)Z
      12: pop
      13: return

  public java.lang.String getProperty(java.lang.String, java.lang.String) throws java.rmi.RemoteException, org.wso2.carbon.registry.resource.stub.ResourceAdminServiceExceptionException;
    Code:
       0: aload_0
       1: getfield      #11                 // Field resourceAdminServiceStub:Lorg/wso2/carbon/registry/resource/stub/ResourceAdminServiceStub;
       4: aload_1
       5: aload_2
       6: invokevirtual #49                 // Method org/wso2/carbon/registry/resource/stub/ResourceAdminServiceStub.getProperty:(Ljava/lang/String;Ljava/lang/String;)Ljava/lang/String;
       9: areturn

  public org.wso2.carbon.registry.resource.stub.beans.xsd.MetadataBean getMetadata(java.lang.String) throws java.rmi.RemoteException, org.wso2.carbon.registry.resource.stub.ResourceAdminServiceExceptionException;
    Code:
       0: aload_0
       1: getfield      #11                 // Field resourceAdminServiceStub:Lorg/wso2/carbon/registry/resource/stub/ResourceAdminServiceStub;
       4: aload_1
       5: invokevirtual #50                 // Method org/wso2/carbon/registry/resource/stub/ResourceAdminServiceStub.getMetadata:(Ljava/lang/String;)Lorg/wso2/carbon/registry/resource/stub/beans/xsd/MetadataBean;
       8: areturn

  public org.wso2.carbon.registry.resource.stub.beans.xsd.ContentBean getResourceContent(java.lang.String) throws java.rmi.RemoteException, org.wso2.carbon.registry.resource.stub.ResourceAdminServiceExceptionException;
    Code:
       0: aload_0
       1: getfield      #11                 // Field resourceAdminServiceStub:Lorg/wso2/carbon/registry/resource/stub/ResourceAdminServiceStub;
       4: aload_1
       5: invokevirtual #51                 // Method org/wso2/carbon/registry/resource/stub/ResourceAdminServiceStub.getContentBean:(Ljava/lang/String;)Lorg/wso2/carbon/registry/resource/stub/beans/xsd/ContentBean;
       8: areturn

  public org.wso2.carbon.registry.resource.stub.common.xsd.ResourceData[] getResourceData(java.lang.String) throws java.rmi.RemoteException, org.wso2.carbon.registry.resource.stub.ResourceAdminServiceExceptionException;
    Code:
       0: iconst_1
       1: anewarray     #20                 // class java/lang/String
       4: dup
       5: iconst_0
       6: aload_1
       7: aastore
       8: astore_2
       9: aload_0
      10: getfield      #11                 // Field resourceAdminServiceStub:Lorg/wso2/carbon/registry/resource/stub/ResourceAdminServiceStub;
      13: aload_2
      14: invokevirtual #21                 // Method org/wso2/carbon/registry/resource/stub/ResourceAdminServiceStub.getResourceData:([Ljava/lang/String;)[Lorg/wso2/carbon/registry/resource/stub/common/xsd/ResourceData;
      17: areturn

  public java.lang.String getHumanReadableMediaTypes() throws java.lang.Exception;
    Code:
       0: aload_0
       1: getfield      #11                 // Field resourceAdminServiceStub:Lorg/wso2/carbon/registry/resource/stub/ResourceAdminServiceStub;
       4: invokevirtual #52                 // Method org/wso2/carbon/registry/resource/stub/ResourceAdminServiceStub.getHumanReadableMediaTypes:()Ljava/lang/String;
       7: areturn
       8: astore_1
       9: ldc           #54                 // String get human readable media type error
      11: astore_2
      12: new           #53                 // class java/lang/Exception
      15: dup
      16: aload_2
      17: aload_1
      18: invokespecial #55                 // Method java/lang/Exception."<init>":(Ljava/lang/String;Ljava/lang/Throwable;)V
      21: athrow
    Exception table:
       from    to  target type
           0     7     8   Class java/lang/Exception

  public java.lang.String getMimeTypeFromHuman(java.lang.String) throws java.lang.Exception;
    Code:
       0: aload_0
       1: getfield      #11                 // Field resourceAdminServiceStub:Lorg/wso2/carbon/registry/resource/stub/ResourceAdminServiceStub;
       4: aload_1
       5: invokevirtual #56                 // Method org/wso2/carbon/registry/resource/stub/ResourceAdminServiceStub.getMimeTypeFromHuman:(Ljava/lang/String;)Ljava/lang/String;
       8: areturn
       9: astore_2
      10: ldc           #54                 // String get human readable media type error
      12: astore_3
      13: new           #53                 // class java/lang/Exception
      16: dup
      17: aload_3
      18: aload_2
      19: invokespecial #55                 // Method java/lang/Exception."<init>":(Ljava/lang/String;Ljava/lang/Throwable;)V
      22: athrow
    Exception table:
       from    to  target type
           0     8     9   Class java/lang/Exception

  public void updateTextContent(java.lang.String, java.lang.String) throws java.rmi.RemoteException, org.wso2.carbon.registry.resource.stub.ResourceAdminServiceExceptionException;
    Code:
       0: aload_0
       1: getfield      #11                 // Field resourceAdminServiceStub:Lorg/wso2/carbon/registry/resource/stub/ResourceAdminServiceStub;
       4: aload_1
       5: aload_2
       6: invokevirtual #57                 // Method org/wso2/carbon/registry/resource/stub/ResourceAdminServiceStub.updateTextContent:(Ljava/lang/String;Ljava/lang/String;)Z
       9: pop
      10: goto          97
      13: astore_3
      14: getstatic     #14                 // Field log:Lorg/apache/commons/logging/Log;
      17: new           #4                  // class java/lang/StringBuilder
      20: dup
      21: invokespecial #5                  // Method java/lang/StringBuilder."<init>":()V
      24: ldc           #58                 // String Cannot edit the content of the resource :
      26: invokevirtual #6                  // Method java/lang/StringBuilder.append:(Ljava/lang/String;)Ljava/lang/StringBuilder;
      29: aload_3
      30: invokevirtual #59                 // Method java/rmi/RemoteException.getMessage:()Ljava/lang/String;
      33: invokevirtual #6                  // Method java/lang/StringBuilder.append:(Ljava/lang/String;)Ljava/lang/StringBuilder;
      36: invokevirtual #8                  // Method java/lang/StringBuilder.toString:()Ljava/lang/String;
      39: invokeinterface #26,  2           // InterfaceMethod org/apache/commons/logging/Log.error:(Ljava/lang/Object;)V
      44: new           #23                 // class java/rmi/RemoteException
      47: dup
      48: ldc           #60                 // String Edit content error :
      50: aload_3
      51: invokespecial #28                 // Method java/rmi/RemoteException."<init>":(Ljava/lang/String;Ljava/lang/Throwable;)V
      54: athrow
      55: astore_3
      56: getstatic     #14                 // Field log:Lorg/apache/commons/logging/Log;
      59: new           #4                  // class java/lang/StringBuilder
      62: dup
      63: invokespecial #5                  // Method java/lang/StringBuilder."<init>":()V
      66: ldc           #58                 // String Cannot edit the content of the resource :
      68: invokevirtual #6                  // Method java/lang/StringBuilder.append:(Ljava/lang/String;)Ljava/lang/StringBuilder;
      71: aload_3
      72: invokevirtual #61                 // Method org/wso2/carbon/registry/resource/stub/ResourceAdminServiceExceptionException.getMessage:()Ljava/lang/String;
      75: invokevirtual #6                  // Method java/lang/StringBuilder.append:(Ljava/lang/String;)Ljava/lang/StringBuilder;
      78: invokevirtual #8                  // Method java/lang/StringBuilder.toString:()Ljava/lang/String;
      81: invokeinterface #26,  2           // InterfaceMethod org/apache/commons/logging/Log.error:(Ljava/lang/Object;)V
      86: new           #29                 // class org/wso2/carbon/registry/resource/stub/ResourceAdminServiceExceptionException
      89: dup
      90: ldc           #62                 // String Get version error :
      92: aload_3
      93: invokespecial #33                 // Method org/wso2/carbon/registry/resource/stub/ResourceAdminServiceExceptionException."<init>":(Ljava/lang/String;Ljava/lang/Throwable;)V
      96: athrow
      97: return
    Exception table:
       from    to  target type
           0    10    13   Class java/rmi/RemoteException
           0    10    55   Class org/wso2/carbon/registry/resource/stub/ResourceAdminServiceExceptionException

  public void copyResource(java.lang.String, java.lang.String, java.lang.String, java.lang.String) throws java.rmi.RemoteException, org.wso2.carbon.registry.resource.stub.ResourceAdminServiceExceptionException;
    Code:
       0: aload_0
       1: getfield      #11                 // Field resourceAdminServiceStub:Lorg/wso2/carbon/registry/resource/stub/ResourceAdminServiceStub;
       4: aload_1
       5: aload_2
       6: aload_3
       7: aload         4
       9: invokevirtual #63                 // Method org/wso2/carbon/registry/resource/stub/ResourceAdminServiceStub.copyResource:(Ljava/lang/String;Ljava/lang/String;Ljava/lang/String;Ljava/lang/String;)Z
      12: pop
      13: goto          64
      16: astore        5
      18: getstatic     #14                 // Field log:Lorg/apache/commons/logging/Log;
      21: ldc           #64                 // String Copy resource error
      23: invokeinterface #26,  2           // InterfaceMethod org/apache/commons/logging/Log.error:(Ljava/lang/Object;)V
      28: new           #23                 // class java/rmi/RemoteException
      31: dup
      32: ldc           #64                 // String Copy resource error
      34: aload         5
      36: invokespecial #28                 // Method java/rmi/RemoteException."<init>":(Ljava/lang/String;Ljava/lang/Throwable;)V
      39: athrow
      40: astore        5
      42: getstatic     #14                 // Field log:Lorg/apache/commons/logging/Log;
      45: ldc           #65                 // String Copy resource error
      47: invokeinterface #26,  2           // InterfaceMethod org/apache/commons/logging/Log.error:(Ljava/lang/Object;)V
      52: new           #29                 // class org/wso2/carbon/registry/resource/stub/ResourceAdminServiceExceptionException
      55: dup
      56: ldc           #65                 // String Copy resource error
      58: aload         5
      60: invokespecial #33                 // Method org/wso2/carbon/registry/resource/stub/ResourceAdminServiceExceptionException."<init>":(Ljava/lang/String;Ljava/lang/Throwable;)V
      63: athrow
      64: return
    Exception table:
       from    to  target type
           0    13    16   Class java/rmi/RemoteException
           0    13    40   Class org/wso2/carbon/registry/resource/stub/ResourceAdminServiceExceptionException

  public void moveResource(java.lang.String, java.lang.String, java.lang.String, java.lang.String) throws java.rmi.RemoteException, org.wso2.carbon.registry.resource.stub.ResourceAdminServiceExceptionException;
    Code:
       0: aload_0
       1: getfield      #11                 // Field resourceAdminServiceStub:Lorg/wso2/carbon/registry/resource/stub/ResourceAdminServiceStub;
       4: aload_1
       5: aload_2
       6: aload_3
       7: aload         4
       9: invokevirtual #66                 // Method org/wso2/carbon/registry/resource/stub/ResourceAdminServiceStub.moveResource:(Ljava/lang/String;Ljava/lang/String;Ljava/lang/String;Ljava/lang/String;)Z
      12: pop
      13: goto          64
      16: astore        5
      18: getstatic     #14                 // Field log:Lorg/apache/commons/logging/Log;
      21: ldc           #67                 // String Move resource error
      23: invokeinterface #26,  2           // InterfaceMethod org/apache/commons/logging/Log.error:(Ljava/lang/Object;)V
      28: new           #23                 // class java/rmi/RemoteException
      31: dup
      32: ldc           #64                 // String Copy resource error
      34: aload         5
      36: invokespecial #28                 // Method java/rmi/RemoteException."<init>":(Ljava/lang/String;Ljava/lang/Throwable;)V
      39: athrow
      40: astore        5
      42: getstatic     #14                 // Field log:Lorg/apache/commons/logging/Log;
      45: ldc           #68                 // String Move resource error
      47: invokeinterface #26,  2           // InterfaceMethod org/apache/commons/logging/Log.error:(Ljava/lang/Object;)V
      52: new           #29                 // class org/wso2/carbon/registry/resource/stub/ResourceAdminServiceExceptionException
      55: dup
      56: ldc           #65                 // String Copy resource error
      58: aload         5
      60: invokespecial #33                 // Method org/wso2/carbon/registry/resource/stub/ResourceAdminServiceExceptionException."<init>":(Ljava/lang/String;Ljava/lang/Throwable;)V
      63: athrow
      64: return
    Exception table:
       from    to  target type
           0    13    16   Class java/rmi/RemoteException
           0    13    40   Class org/wso2/carbon/registry/resource/stub/ResourceAdminServiceExceptionException

  public org.wso2.carbon.registry.resource.stub.beans.xsd.VersionPath[] getVersionPaths(java.lang.String) throws java.rmi.RemoteException, org.wso2.carbon.registry.resource.stub.ResourceAdminServiceExceptionException;
    Code:
       0: aconst_null
       1: astore_2
       2: aload_0
       3: getfield      #11                 // Field resourceAdminServiceStub:Lorg/wso2/carbon/registry/resource/stub/ResourceAdminServiceStub;
       6: aload_1
       7: invokevirtual #69                 // Method org/wso2/carbon/registry/resource/stub/ResourceAdminServiceStub.getVersionsBean:(Ljava/lang/String;)Lorg/wso2/carbon/registry/resource/stub/beans/xsd/VersionsBean;
      10: astore_3
      11: aload_3
      12: invokevirtual #70                 // Method org/wso2/carbon/registry/resource/stub/beans/xsd/VersionsBean.getVersionPaths:()[Lorg/wso2/carbon/registry/resource/stub/beans/xsd/VersionPath;
      15: astore_2
      16: goto          103
      19: astore_3
      20: getstatic     #14                 // Field log:Lorg/apache/commons/logging/Log;
      23: new           #4                  // class java/lang/StringBuilder
      26: dup
      27: invokespecial #5                  // Method java/lang/StringBuilder."<init>":()V
      30: ldc           #71                 // String No versions for created path :
      32: invokevirtual #6                  // Method java/lang/StringBuilder.append:(Ljava/lang/String;)Ljava/lang/StringBuilder;
      35: aload_3
      36: invokevirtual #59                 // Method java/rmi/RemoteException.getMessage:()Ljava/lang/String;
      39: invokevirtual #6                  // Method java/lang/StringBuilder.append:(Ljava/lang/String;)Ljava/lang/StringBuilder;
      42: invokevirtual #8                  // Method java/lang/StringBuilder.toString:()Ljava/lang/String;
      45: invokeinterface #26,  2           // InterfaceMethod org/apache/commons/logging/Log.error:(Ljava/lang/Object;)V
      50: new           #23                 // class java/rmi/RemoteException
      53: dup
      54: ldc           #62                 // String Get version error :
      56: aload_3
      57: invokespecial #28                 // Method java/rmi/RemoteException."<init>":(Ljava/lang/String;Ljava/lang/Throwable;)V
      60: athrow
      61: astore_3
      62: getstatic     #14                 // Field log:Lorg/apache/commons/logging/Log;
      65: new           #4                  // class java/lang/StringBuilder
      68: dup
      69: invokespecial #5                  // Method java/lang/StringBuilder."<init>":()V
      72: ldc           #62                 // String Get version error :
      74: invokevirtual #6                  // Method java/lang/StringBuilder.append:(Ljava/lang/String;)Ljava/lang/StringBuilder;
      77: aload_3
      78: invokevirtual #61                 // Method org/wso2/carbon/registry/resource/stub/ResourceAdminServiceExceptionException.getMessage:()Ljava/lang/String;
      81: invokevirtual #6                  // Method java/lang/StringBuilder.append:(Ljava/lang/String;)Ljava/lang/StringBuilder;
      84: invokevirtual #8                  // Method java/lang/StringBuilder.toString:()Ljava/lang/String;
      87: invokeinterface #26,  2           // InterfaceMethod org/apache/commons/logging/Log.error:(Ljava/lang/Object;)V
      92: new           #29                 // class org/wso2/carbon/registry/resource/stub/ResourceAdminServiceExceptionException
      95: dup
      96: ldc           #62                 // String Get version error :
      98: aload_3
      99: invokespecial #33                 // Method org/wso2/carbon/registry/resource/stub/ResourceAdminServiceExceptionException."<init>":(Ljava/lang/String;Ljava/lang/Throwable;)V
     102: athrow
     103: aload_2
     104: areturn
    Exception table:
       from    to  target type
           2    16    19   Class java/rmi/RemoteException
           2    16    61   Class org/wso2/carbon/registry/resource/stub/ResourceAdminServiceExceptionException

  public org.wso2.carbon.registry.resource.stub.beans.xsd.VersionsBean getVersionsBean(java.lang.String) throws java.rmi.RemoteException, org.wso2.carbon.registry.resource.stub.ResourceAdminServiceExceptionException;
    Code:
       0: aload_0
       1: getfield      #11                 // Field resourceAdminServiceStub:Lorg/wso2/carbon/registry/resource/stub/ResourceAdminServiceStub;
       4: aload_1
       5: invokevirtual #69                 // Method org/wso2/carbon/registry/resource/stub/ResourceAdminServiceStub.getVersionsBean:(Ljava/lang/String;)Lorg/wso2/carbon/registry/resource/stub/beans/xsd/VersionsBean;
       8: areturn
       9: astore_2
      10: getstatic     #14                 // Field log:Lorg/apache/commons/logging/Log;
      13: new           #4                  // class java/lang/StringBuilder
      16: dup
      17: invokespecial #5                  // Method java/lang/StringBuilder."<init>":()V
      20: ldc           #72                 // String Get version bean fails:
      22: invokevirtual #6                  // Method java/lang/StringBuilder.append:(Ljava/lang/String;)Ljava/lang/StringBuilder;
      25: aload_2
      26: invokevirtual #59                 // Method java/rmi/RemoteException.getMessage:()Ljava/lang/String;
      29: invokevirtual #6                  // Method java/lang/StringBuilder.append:(Ljava/lang/String;)Ljava/lang/StringBuilder;
      32: invokevirtual #8                  // Method java/lang/StringBuilder.toString:()Ljava/lang/String;
      35: invokeinterface #26,  2           // InterfaceMethod org/apache/commons/logging/Log.error:(Ljava/lang/Object;)V
      40: new           #23                 // class java/rmi/RemoteException
      43: dup
      44: ldc           #73                 // String Get version bean fails:
      46: aload_2
      47: invokespecial #28                 // Method java/rmi/RemoteException."<init>":(Ljava/lang/String;Ljava/lang/Throwable;)V
      50: athrow
      51: astore_2
      52: getstatic     #14                 // Field log:Lorg/apache/commons/logging/Log;
      55: new           #4                  // class java/lang/StringBuilder
      58: dup
      59: invokespecial #5                  // Method java/lang/StringBuilder."<init>":()V
      62: ldc           #73                 // String Get version bean fails:
      64: invokevirtual #6                  // Method java/lang/StringBuilder.append:(Ljava/lang/String;)Ljava/lang/StringBuilder;
      67: aload_2
      68: invokevirtual #61                 // Method org/wso2/carbon/registry/resource/stub/ResourceAdminServiceExceptionException.getMessage:()Ljava/lang/String;
      71: invokevirtual #6                  // Method java/lang/StringBuilder.append:(Ljava/lang/String;)Ljava/lang/StringBuilder;
      74: invokevirtual #8                  // Method java/lang/StringBuilder.toString:()Ljava/lang/String;
      77: invokeinterface #26,  2           // InterfaceMethod org/apache/commons/logging/Log.error:(Ljava/lang/Object;)V
      82: new           #29                 // class org/wso2/carbon/registry/resource/stub/ResourceAdminServiceExceptionException
      85: dup
      86: ldc           #74                 // String Get version bean fails:  :
      88: aload_2
      89: invokespecial #33                 // Method org/wso2/carbon/registry/resource/stub/ResourceAdminServiceExceptionException."<init>":(Ljava/lang/String;Ljava/lang/Throwable;)V
      92: athrow
    Exception table:
       from    to  target type
           0     8     9   Class java/rmi/RemoteException
           0     8    51   Class org/wso2/carbon/registry/resource/stub/ResourceAdminServiceExceptionException

  public void createVersion(java.lang.String) throws java.rmi.RemoteException, org.wso2.carbon.registry.resource.stub.ResourceAdminServiceExceptionException;
    Code:
       0: aload_0
       1: getfield      #11                 // Field resourceAdminServiceStub:Lorg/wso2/carbon/registry/resource/stub/ResourceAdminServiceStub;
       4: aload_1
       5: invokevirtual #75                 // Method org/wso2/carbon/registry/resource/stub/ResourceAdminServiceStub.createVersion:(Ljava/lang/String;)Z
       8: pop
       9: goto          96
      12: astore_2
      13: getstatic     #14                 // Field log:Lorg/apache/commons/logging/Log;
      16: new           #4                  // class java/lang/StringBuilder
      19: dup
      20: invokespecial #5                  // Method java/lang/StringBuilder."<init>":()V
      23: ldc           #76                 // String Create version error :
      25: invokevirtual #6                  // Method java/lang/StringBuilder.append:(Ljava/lang/String;)Ljava/lang/StringBuilder;
      28: aload_2
      29: invokevirtual #59                 // Method java/rmi/RemoteException.getMessage:()Ljava/lang/String;
      32: invokevirtual #6                  // Method java/lang/StringBuilder.append:(Ljava/lang/String;)Ljava/lang/StringBuilder;
      35: invokevirtual #8                  // Method java/lang/StringBuilder.toString:()Ljava/lang/String;
      38: invokeinterface #26,  2           // InterfaceMethod org/apache/commons/logging/Log.error:(Ljava/lang/Object;)V
      43: new           #23                 // class java/rmi/RemoteException
      46: dup
      47: ldc           #76                 // String Create version error :
      49: aload_2
      50: invokespecial #28                 // Method java/rmi/RemoteException."<init>":(Ljava/lang/String;Ljava/lang/Throwable;)V
      53: athrow
      54: astore_2
      55: getstatic     #14                 // Field log:Lorg/apache/commons/logging/Log;
      58: new           #4                  // class java/lang/StringBuilder
      61: dup
      62: invokespecial #5                  // Method java/lang/StringBuilder."<init>":()V
      65: ldc           #76                 // String Create version error :
      67: invokevirtual #6                  // Method java/lang/StringBuilder.append:(Ljava/lang/String;)Ljava/lang/StringBuilder;
      70: aload_2
      71: invokevirtual #61                 // Method org/wso2/carbon/registry/resource/stub/ResourceAdminServiceExceptionException.getMessage:()Ljava/lang/String;
      74: invokevirtual #6                  // Method java/lang/StringBuilder.append:(Ljava/lang/String;)Ljava/lang/StringBuilder;
      77: invokevirtual #8                  // Method java/lang/StringBuilder.toString:()Ljava/lang/String;
      80: invokeinterface #26,  2           // InterfaceMethod org/apache/commons/logging/Log.error:(Ljava/lang/Object;)V
      85: new           #29                 // class org/wso2/carbon/registry/resource/stub/ResourceAdminServiceExceptionException
      88: dup
      89: ldc           #76                 // String Create version error :
      91: aload_2
      92: invokespecial #33                 // Method org/wso2/carbon/registry/resource/stub/ResourceAdminServiceExceptionException."<init>":(Ljava/lang/String;Ljava/lang/Throwable;)V
      95: athrow
      96: return
    Exception table:
       from    to  target type
           0     9    12   Class java/rmi/RemoteException
           0     9    54   Class org/wso2/carbon/registry/resource/stub/ResourceAdminServiceExceptionException

  public void deleteVersionHistory(java.lang.String, java.lang.String) throws java.rmi.RemoteException, org.wso2.carbon.registry.resource.stub.ResourceAdminServiceExceptionException;
    Code:
       0: aload_0
       1: getfield      #11                 // Field resourceAdminServiceStub:Lorg/wso2/carbon/registry/resource/stub/ResourceAdminServiceStub;
       4: aload_1
       5: aload_2
       6: invokevirtual #77                 // Method org/wso2/carbon/registry/resource/stub/ResourceAdminServiceStub.deleteVersionHistory:(Ljava/lang/String;Ljava/lang/String;)Z
       9: pop
      10: goto          97
      13: astore_3
      14: getstatic     #14                 // Field log:Lorg/apache/commons/logging/Log;
      17: new           #4                  // class java/lang/StringBuilder
      20: dup
      21: invokespecial #5                  // Method java/lang/StringBuilder."<init>":()V
      24: ldc           #78                 // String No versions to delete :
      26: invokevirtual #6                  // Method java/lang/StringBuilder.append:(Ljava/lang/String;)Ljava/lang/StringBuilder;
      29: aload_3
      30: invokevirtual #59                 // Method java/rmi/RemoteException.getMessage:()Ljava/lang/String;
      33: invokevirtual #6                  // Method java/lang/StringBuilder.append:(Ljava/lang/String;)Ljava/lang/StringBuilder;
      36: invokevirtual #8                  // Method java/lang/StringBuilder.toString:()Ljava/lang/String;
      39: invokeinterface #26,  2           // InterfaceMethod org/apache/commons/logging/Log.error:(Ljava/lang/Object;)V
      44: new           #23                 // class java/rmi/RemoteException
      47: dup
      48: ldc           #79                 // String Delete version error :
      50: aload_3
      51: invokespecial #28                 // Method java/rmi/RemoteException."<init>":(Ljava/lang/String;Ljava/lang/Throwable;)V
      54: athrow
      55: astore_3
      56: getstatic     #14                 // Field log:Lorg/apache/commons/logging/Log;
      59: new           #4                  // class java/lang/StringBuilder
      62: dup
      63: invokespecial #5                  // Method java/lang/StringBuilder."<init>":()V
      66: ldc           #79                 // String Delete version error :
      68: invokevirtual #6                  // Method java/lang/StringBuilder.append:(Ljava/lang/String;)Ljava/lang/StringBuilder;
      71: aload_3
      72: invokevirtual #61                 // Method org/wso2/carbon/registry/resource/stub/ResourceAdminServiceExceptionException.getMessage:()Ljava/lang/String;
      75: invokevirtual #6                  // Method java/lang/StringBuilder.append:(Ljava/lang/String;)Ljava/lang/StringBuilder;
      78: invokevirtual #8                  // Method java/lang/StringBuilder.toString:()Ljava/lang/String;
      81: invokeinterface #26,  2           // InterfaceMethod org/apache/commons/logging/Log.error:(Ljava/lang/Object;)V
      86: new           #29                 // class org/wso2/carbon/registry/resource/stub/ResourceAdminServiceExceptionException
      89: dup
      90: ldc           #79                 // String Delete version error :
      92: aload_3
      93: invokespecial #33                 // Method org/wso2/carbon/registry/resource/stub/ResourceAdminServiceExceptionException."<init>":(Ljava/lang/String;Ljava/lang/Throwable;)V
      96: athrow
      97: return
    Exception table:
       from    to  target type
           0    10    13   Class java/rmi/RemoteException
           0    10    55   Class org/wso2/carbon/registry/resource/stub/ResourceAdminServiceExceptionException

  public boolean restoreVersion(java.lang.String) throws java.rmi.RemoteException, org.wso2.carbon.registry.resource.stub.ResourceAdminServiceExceptionException;
    Code:
       0: iconst_0
       1: istore_2
       2: aload_0
       3: getfield      #11                 // Field resourceAdminServiceStub:Lorg/wso2/carbon/registry/resource/stub/ResourceAdminServiceStub;
       6: aload_1
       7: invokevirtual #80                 // Method org/wso2/carbon/registry/resource/stub/ResourceAdminServiceStub.restoreVersion:(Ljava/lang/String;)Z
      10: istore_2
      11: goto          98
      14: astore_3
      15: getstatic     #14                 // Field log:Lorg/apache/commons/logging/Log;
      18: new           #4                  // class java/lang/StringBuilder
      21: dup
      22: invokespecial #5                  // Method java/lang/StringBuilder."<init>":()V
      25: ldc           #81                 // String No versions to restore :
      27: invokevirtual #6                  // Method java/lang/StringBuilder.append:(Ljava/lang/String;)Ljava/lang/StringBuilder;
      30: aload_3
      31: invokevirtual #59                 // Method java/rmi/RemoteException.getMessage:()Ljava/lang/String;
      34: invokevirtual #6                  // Method java/lang/StringBuilder.append:(Ljava/lang/String;)Ljava/lang/StringBuilder;
      37: invokevirtual #8                  // Method java/lang/StringBuilder.toString:()Ljava/lang/String;
      40: invokeinterface #26,  2           // InterfaceMethod org/apache/commons/logging/Log.error:(Ljava/lang/Object;)V
      45: new           #23                 // class java/rmi/RemoteException
      48: dup
      49: ldc           #82                 // String Restore version error :
      51: aload_3
      52: invokespecial #28                 // Method java/rmi/RemoteException."<init>":(Ljava/lang/String;Ljava/lang/Throwable;)V
      55: athrow
      56: astore_3
      57: getstatic     #14                 // Field log:Lorg/apache/commons/logging/Log;
      60: new           #4                  // class java/lang/StringBuilder
      63: dup
      64: invokespecial #5                  // Method java/lang/StringBuilder."<init>":()V
      67: ldc           #82                 // String Restore version error :
      69: invokevirtual #6                  // Method java/lang/StringBuilder.append:(Ljava/lang/String;)Ljava/lang/StringBuilder;
      72: aload_3
      73: invokevirtual #61                 // Method org/wso2/carbon/registry/resource/stub/ResourceAdminServiceExceptionException.getMessage:()Ljava/lang/String;
      76: invokevirtual #6                  // Method java/lang/StringBuilder.append:(Ljava/lang/String;)Ljava/lang/StringBuilder;
      79: invokevirtual #8                  // Method java/lang/StringBuilder.toString:()Ljava/lang/String;
      82: invokeinterface #26,  2           // InterfaceMethod org/apache/commons/logging/Log.error:(Ljava/lang/Object;)V
      87: new           #29                 // class org/wso2/carbon/registry/resource/stub/ResourceAdminServiceExceptionException
      90: dup
      91: ldc           #82                 // String Restore version error :
      93: aload_3
      94: invokespecial #33                 // Method org/wso2/carbon/registry/resource/stub/ResourceAdminServiceExceptionException."<init>":(Ljava/lang/String;Ljava/lang/Throwable;)V
      97: athrow
      98: iload_2
      99: ireturn
    Exception table:
       from    to  target type
           2    11    14   Class java/rmi/RemoteException
           2    11    56   Class org/wso2/carbon/registry/resource/stub/ResourceAdminServiceExceptionException

  public java.lang.String getTextContent(java.lang.String) throws java.rmi.RemoteException, org.wso2.carbon.registry.resource.stub.ResourceAdminServiceExceptionException;
    Code:
       0: aconst_null
       1: astore_2
       2: aload_0
       3: getfield      #11                 // Field resourceAdminServiceStub:Lorg/wso2/carbon/registry/resource/stub/ResourceAdminServiceStub;
       6: aload_1
       7: invokevirtual #83                 // Method org/wso2/carbon/registry/resource/stub/ResourceAdminServiceStub.getTextContent:(Ljava/lang/String;)Ljava/lang/String;
      10: astore_2
      11: goto          98
      14: astore_3
      15: getstatic     #14                 // Field log:Lorg/apache/commons/logging/Log;
      18: new           #4                  // class java/lang/StringBuilder
      21: dup
      22: invokespecial #5                  // Method java/lang/StringBuilder."<init>":()V
      25: ldc           #84                 // String Unable get content :
      27: invokevirtual #6                  // Method java/lang/StringBuilder.append:(Ljava/lang/String;)Ljava/lang/StringBuilder;
      30: aload_3
      31: invokevirtual #59                 // Method java/rmi/RemoteException.getMessage:()Ljava/lang/String;
      34: invokevirtual #6                  // Method java/lang/StringBuilder.append:(Ljava/lang/String;)Ljava/lang/StringBuilder;
      37: invokevirtual #8                  // Method java/lang/StringBuilder.toString:()Ljava/lang/String;
      40: invokeinterface #26,  2           // InterfaceMethod org/apache/commons/logging/Log.error:(Ljava/lang/Object;)V
      45: new           #23                 // class java/rmi/RemoteException
      48: dup
      49: ldc           #82                 // String Restore version error :
      51: aload_3
      52: invokespecial #28                 // Method java/rmi/RemoteException."<init>":(Ljava/lang/String;Ljava/lang/Throwable;)V
      55: athrow
      56: astore_3
      57: getstatic     #14                 // Field log:Lorg/apache/commons/logging/Log;
      60: new           #4                  // class java/lang/StringBuilder
      63: dup
      64: invokespecial #5                  // Method java/lang/StringBuilder."<init>":()V
      67: ldc           #85                 // String GetTextContent Error :
      69: invokevirtual #6                  // Method java/lang/StringBuilder.append:(Ljava/lang/String;)Ljava/lang/StringBuilder;
      72: aload_3
      73: invokevirtual #61                 // Method org/wso2/carbon/registry/resource/stub/ResourceAdminServiceExceptionException.getMessage:()Ljava/lang/String;
      76: invokevirtual #6                  // Method java/lang/StringBuilder.append:(Ljava/lang/String;)Ljava/lang/StringBuilder;
      79: invokevirtual #8                  // Method java/lang/StringBuilder.toString:()Ljava/lang/String;
      82: invokeinterface #26,  2           // InterfaceMethod org/apache/commons/logging/Log.error:(Ljava/lang/Object;)V
      87: new           #29                 // class org/wso2/carbon/registry/resource/stub/ResourceAdminServiceExceptionException
      90: dup
      91: ldc           #86                 // String GetTextContent Error :
      93: aload_3
      94: invokespecial #33                 // Method org/wso2/carbon/registry/resource/stub/ResourceAdminServiceExceptionException."<init>":(Ljava/lang/String;Ljava/lang/Throwable;)V
      97: athrow
      98: aload_2
      99: areturn
    Exception table:
       from    to  target type
           2    11    14   Class java/rmi/RemoteException
           2    11    56   Class org/wso2/carbon/registry/resource/stub/ResourceAdminServiceExceptionException

  public org.wso2.carbon.registry.resource.stub.beans.xsd.PermissionBean getPermission(java.lang.String) throws java.lang.Exception;
    Code:
       0: aload_0
       1: getfield      #11                 // Field resourceAdminServiceStub:Lorg/wso2/carbon/registry/resource/stub/ResourceAdminServiceStub;
       4: aload_1
       5: invokevirtual #87                 // Method org/wso2/carbon/registry/resource/stub/ResourceAdminServiceStub.getPermissions:(Ljava/lang/String;)Lorg/wso2/carbon/registry/resource/stub/beans/xsd/PermissionBean;
       8: areturn
       9: astore_2
      10: getstatic     #14                 // Field log:Lorg/apache/commons/logging/Log;
      13: new           #4                  // class java/lang/StringBuilder
      16: dup
      17: invokespecial #5                  // Method java/lang/StringBuilder."<init>":()V
      20: ldc           #88                 // String Unable to get permission :
      22: invokevirtual #6                  // Method java/lang/StringBuilder.append:(Ljava/lang/String;)Ljava/lang/StringBuilder;
      25: aload_2
      26: invokevirtual #89                 // Method java/lang/Exception.getMessage:()Ljava/lang/String;
      29: invokevirtual #6                  // Method java/lang/StringBuilder.append:(Ljava/lang/String;)Ljava/lang/StringBuilder;
      32: invokevirtual #8                  // Method java/lang/StringBuilder.toString:()Ljava/lang/String;
      35: invokeinterface #26,  2           // InterfaceMethod org/apache/commons/logging/Log.error:(Ljava/lang/Object;)V
      40: new           #53                 // class java/lang/Exception
      43: dup
      44: ldc           #88                 // String Unable to get permission :
      46: aload_2
      47: invokespecial #55                 // Method java/lang/Exception."<init>":(Ljava/lang/String;Ljava/lang/Throwable;)V
      50: athrow
    Exception table:
       from    to  target type
           0     8     9   Class java/lang/Exception

  public void renameResource(java.lang.String, java.lang.String, java.lang.String) throws java.rmi.RemoteException, org.wso2.carbon.registry.resource.stub.ResourceAdminServiceExceptionException;
    Code:
       0: aload_0
       1: getfield      #11                 // Field resourceAdminServiceStub:Lorg/wso2/carbon/registry/resource/stub/ResourceAdminServiceStub;
       4: aload_1
       5: aload_2
       6: aload_3
       7: invokevirtual #90                 // Method org/wso2/carbon/registry/resource/stub/ResourceAdminServiceStub.renameResource:(Ljava/lang/String;Ljava/lang/String;Ljava/lang/String;)Z
      10: pop
      11: goto          62
      14: astore        4
      16: getstatic     #14                 // Field log:Lorg/apache/commons/logging/Log;
      19: ldc           #91                 // String Rename resource error
      21: invokeinterface #26,  2           // InterfaceMethod org/apache/commons/logging/Log.error:(Ljava/lang/Object;)V
      26: new           #23                 // class java/rmi/RemoteException
      29: dup
      30: ldc           #91                 // String Rename resource error
      32: aload         4
      34: invokespecial #28                 // Method java/rmi/RemoteException."<init>":(Ljava/lang/String;Ljava/lang/Throwable;)V
      37: athrow
      38: astore        4
      40: getstatic     #14                 // Field log:Lorg/apache/commons/logging/Log;
      43: ldc           #92                 // String Rename resource error
      45: invokeinterface #26,  2           // InterfaceMethod org/apache/commons/logging/Log.error:(Ljava/lang/Object;)V
      50: new           #29                 // class org/wso2/carbon/registry/resource/stub/ResourceAdminServiceExceptionException
      53: dup
      54: ldc           #92                 // String Rename resource error
      56: aload         4
      58: invokespecial #33                 // Method org/wso2/carbon/registry/resource/stub/ResourceAdminServiceExceptionException."<init>":(Ljava/lang/String;Ljava/lang/Throwable;)V
      61: athrow
      62: return
    Exception table:
       from    to  target type
           0    11    14   Class java/rmi/RemoteException
           0    11    38   Class org/wso2/carbon/registry/resource/stub/ResourceAdminServiceExceptionException

  public boolean addExtension(java.lang.String, javax.activation.DataHandler) throws java.rmi.RemoteException, org.wso2.carbon.registry.resource.stub.ResourceAdminServiceExceptionException;
    Code:
       0: aload_0
       1: getfield      #11                 // Field resourceAdminServiceStub:Lorg/wso2/carbon/registry/resource/stub/ResourceAdminServiceStub;
       4: aload_1
       5: aload_2
       6: invokevirtual #93                 // Method org/wso2/carbon/registry/resource/stub/ResourceAdminServiceStub.addExtension:(Ljava/lang/String;Ljavax/activation/DataHandler;)Z
       9: ireturn
      10: astore_3
      11: getstatic     #14                 // Field log:Lorg/apache/commons/logging/Log;
      14: ldc           #94                 // String Add extension error
      16: invokeinterface #26,  2           // InterfaceMethod org/apache/commons/logging/Log.error:(Ljava/lang/Object;)V
      21: new           #23                 // class java/rmi/RemoteException
      24: dup
      25: ldc           #91                 // String Rename resource error
      27: aload_3
      28: invokespecial #28                 // Method java/rmi/RemoteException."<init>":(Ljava/lang/String;Ljava/lang/Throwable;)V
      31: athrow
      32: astore_3
      33: getstatic     #14                 // Field log:Lorg/apache/commons/logging/Log;
      36: ldc           #95                 // String Add Extension error
      38: invokeinterface #26,  2           // InterfaceMethod org/apache/commons/logging/Log.error:(Ljava/lang/Object;)V
      43: new           #29                 // class org/wso2/carbon/registry/resource/stub/ResourceAdminServiceExceptionException
      46: dup
      47: ldc           #92                 // String Rename resource error
      49: aload_3
      50: invokespecial #33                 // Method org/wso2/carbon/registry/resource/stub/ResourceAdminServiceExceptionException."<init>":(Ljava/lang/String;Ljava/lang/Throwable;)V
      53: athrow
    Exception table:
       from    to  target type
           0     9    10   Class java/rmi/RemoteException
           0     9    32   Class org/wso2/carbon/registry/resource/stub/ResourceAdminServiceExceptionException

  public boolean removeExtension(java.lang.String) throws java.rmi.RemoteException, org.wso2.carbon.registry.resource.stub.ResourceAdminServiceExceptionException;
    Code:
       0: aload_0
       1: getfield      #11                 // Field resourceAdminServiceStub:Lorg/wso2/carbon/registry/resource/stub/ResourceAdminServiceStub;
       4: aload_1
       5: invokevirtual #96                 // Method org/wso2/carbon/registry/resource/stub/ResourceAdminServiceStub.removeExtension:(Ljava/lang/String;)Z
       8: ireturn
       9: astore_2
      10: getstatic     #14                 // Field log:Lorg/apache/commons/logging/Log;
      13: ldc           #97                 // String Remove extension error
      15: invokeinterface #26,  2           // InterfaceMethod org/apache/commons/logging/Log.error:(Ljava/lang/Object;)V
      20: new           #23                 // class java/rmi/RemoteException
      23: dup
      24: ldc           #98                 // String Remove resource error
      26: aload_2
      27: invokespecial #28                 // Method java/rmi/RemoteException."<init>":(Ljava/lang/String;Ljava/lang/Throwable;)V
      30: athrow
      31: astore_2
      32: getstatic     #14                 // Field log:Lorg/apache/commons/logging/Log;
      35: ldc           #99                 // String Remove Extension error
      37: invokeinterface #26,  2           // InterfaceMethod org/apache/commons/logging/Log.error:(Ljava/lang/Object;)V
      42: new           #29                 // class org/wso2/carbon/registry/resource/stub/ResourceAdminServiceExceptionException
      45: dup
      46: ldc           #100                // String Remove resource error
      48: aload_2
      49: invokespecial #33                 // Method org/wso2/carbon/registry/resource/stub/ResourceAdminServiceExceptionException."<init>":(Ljava/lang/String;Ljava/lang/Throwable;)V
      52: athrow
    Exception table:
       from    to  target type
           0     8     9   Class java/rmi/RemoteException
           0     8    31   Class org/wso2/carbon/registry/resource/stub/ResourceAdminServiceExceptionException

  public java.lang.String[] listExtensions() throws java.rmi.RemoteException, org.wso2.carbon.registry.resource.stub.ResourceAdminServiceExceptionException;
    Code:
       0: aload_0
       1: getfield      #11                 // Field resourceAdminServiceStub:Lorg/wso2/carbon/registry/resource/stub/ResourceAdminServiceStub;
       4: invokevirtual #101                // Method org/wso2/carbon/registry/resource/stub/ResourceAdminServiceStub.listExtensions:()[Ljava/lang/String;
       7: areturn
       8: astore_1
       9: getstatic     #14                 // Field log:Lorg/apache/commons/logging/Log;
      12: ldc           #102                // String List extensions error
      14: invokeinterface #26,  2           // InterfaceMethod org/apache/commons/logging/Log.error:(Ljava/lang/Object;)V
      19: new           #23                 // class java/rmi/RemoteException
      22: dup
      23: ldc           #102                // String List extensions error
      25: aload_1
      26: invokespecial #28                 // Method java/rmi/RemoteException."<init>":(Ljava/lang/String;Ljava/lang/Throwable;)V
      29: athrow
      30: astore_1
      31: getstatic     #14                 // Field log:Lorg/apache/commons/logging/Log;
      34: ldc           #102                // String List extensions error
      36: invokeinterface #26,  2           // InterfaceMethod org/apache/commons/logging/Log.error:(Ljava/lang/Object;)V
      41: new           #29                 // class org/wso2/carbon/registry/resource/stub/ResourceAdminServiceExceptionException
      44: dup
      45: ldc           #102                // String List extensions error
      47: aload_1
      48: invokespecial #33                 // Method org/wso2/carbon/registry/resource/stub/ResourceAdminServiceExceptionException."<init>":(Ljava/lang/String;Ljava/lang/Throwable;)V
      51: athrow
    Exception table:
       from    to  target type
           0     7     8   Class java/rmi/RemoteException
           0     7    30   Class org/wso2/carbon/registry/resource/stub/ResourceAdminServiceExceptionException

  public void setDescription(java.lang.String, java.lang.String) throws java.rmi.RemoteException, org.wso2.carbon.registry.info.stub.RegistryExceptionException;
    Code:
       0: aload_0
       1: getfield      #11                 // Field resourceAdminServiceStub:Lorg/wso2/carbon/registry/resource/stub/ResourceAdminServiceStub;
       4: aload_1
       5: aload_2
       6: invokevirtual #103                // Method org/wso2/carbon/registry/resource/stub/ResourceAdminServiceStub.setDescription:(Ljava/lang/String;Ljava/lang/String;)V
       9: goto          100
      12: astore_3
      13: new           #4                  // class java/lang/StringBuilder
      16: dup
      17: invokespecial #5                  // Method java/lang/StringBuilder."<init>":()V
      20: ldc           #104                // String Unable set description for the path -
      22: invokevirtual #6                  // Method java/lang/StringBuilder.append:(Ljava/lang/String;)Ljava/lang/StringBuilder;
      25: aload_1
      26: invokevirtual #6                  // Method java/lang/StringBuilder.append:(Ljava/lang/String;)Ljava/lang/StringBuilder;
      29: invokevirtual #8                  // Method java/lang/StringBuilder.toString:()Ljava/lang/String;
      32: astore        4
      34: getstatic     #14                 // Field log:Lorg/apache/commons/logging/Log;
      37: aload         4
      39: aload_3
      40: invokeinterface #31,  3           // InterfaceMethod org/apache/commons/logging/Log.error:(Ljava/lang/Object;Ljava/lang/Throwable;)V
      45: new           #23                 // class java/rmi/RemoteException
      48: dup
      49: ldc           #102                // String List extensions error
      51: aload_3
      52: invokespecial #28                 // Method java/rmi/RemoteException."<init>":(Ljava/lang/String;Ljava/lang/Throwable;)V
      55: athrow
      56: astore_3
      57: new           #4                  // class java/lang/StringBuilder
      60: dup
      61: invokespecial #5                  // Method java/lang/StringBuilder."<init>":()V
      64: ldc           #104                // String Unable set description for the path -
      66: invokevirtual #6                  // Method java/lang/StringBuilder.append:(Ljava/lang/String;)Ljava/lang/StringBuilder;
      69: aload_1
      70: invokevirtual #6                  // Method java/lang/StringBuilder.append:(Ljava/lang/String;)Ljava/lang/StringBuilder;
      73: invokevirtual #8                  // Method java/lang/StringBuilder.toString:()Ljava/lang/String;
      76: astore        4
      78: getstatic     #14                 // Field log:Lorg/apache/commons/logging/Log;
      81: aload         4
      83: aload_3
      84: invokeinterface #31,  3           // InterfaceMethod org/apache/commons/logging/Log.error:(Ljava/lang/Object;Ljava/lang/Throwable;)V
      89: new           #105                // class org/wso2/carbon/registry/info/stub/RegistryExceptionException
      92: dup
      93: aload         4
      95: aload_3
      96: invokespecial #106                // Method org/wso2/carbon/registry/info/stub/RegistryExceptionException."<init>":(Ljava/lang/String;Ljava/lang/Throwable;)V
      99: athrow
     100: return
    Exception table:
       from    to  target type
           0     9    12   Class java/rmi/RemoteException
           0     9    56   Class org/wso2/carbon/registry/resource/stub/ResourceAdminServiceExceptionException

  public org.wso2.carbon.registry.resource.stub.beans.xsd.ContentDownloadBean getContentDownloadBean(java.lang.String) throws java.rmi.RemoteException, org.wso2.carbon.registry.info.stub.RegistryExceptionException;
    Code:
       0: aload_0
       1: getfield      #11                 // Field resourceAdminServiceStub:Lorg/wso2/carbon/registry/resource/stub/ResourceAdminServiceStub;
       4: aload_1
       5: invokevirtual #107                // Method org/wso2/carbon/registry/resource/stub/ResourceAdminServiceStub.getContentDownloadBean:(Ljava/lang/String;)Lorg/wso2/carbon/registry/resource/stub/beans/xsd/ContentDownloadBean;
       8: areturn
       9: astore_2
      10: new           #4                  // class java/lang/StringBuilder
      13: dup
      14: invokespecial #5                  // Method java/lang/StringBuilder."<init>":()V
      17: ldc           #108                // String Unable to retrieve content download bean -
      19: invokevirtual #6                  // Method java/lang/StringBuilder.append:(Ljava/lang/String;)Ljava/lang/StringBuilder;
      22: aload_1
      23: invokevirtual #6                  // Method java/lang/StringBuilder.append:(Ljava/lang/String;)Ljava/lang/StringBuilder;
      26: invokevirtual #8                  // Method java/lang/StringBuilder.toString:()Ljava/lang/String;
      29: astore_3
      30: getstatic     #14                 // Field log:Lorg/apache/commons/logging/Log;
      33: aload_3
      34: aload_2
      35: invokeinterface #31,  3           // InterfaceMethod org/apache/commons/logging/Log.error:(Ljava/lang/Object;Ljava/lang/Throwable;)V
      40: new           #23                 // class java/rmi/RemoteException
      43: dup
      44: aload_3
      45: aload_2
      46: invokespecial #28                 // Method java/rmi/RemoteException."<init>":(Ljava/lang/String;Ljava/lang/Throwable;)V
      49: athrow
      50: astore_2
      51: new           #4                  // class java/lang/StringBuilder
      54: dup
      55: invokespecial #5                  // Method java/lang/StringBuilder."<init>":()V
      58: ldc           #108                // String Unable to retrieve content download bean -
      60: invokevirtual #6                  // Method java/lang/StringBuilder.append:(Ljava/lang/String;)Ljava/lang/StringBuilder;
      63: aload_1
      64: invokevirtual #6                  // Method java/lang/StringBuilder.append:(Ljava/lang/String;)Ljava/lang/StringBuilder;
      67: invokevirtual #8                  // Method java/lang/StringBuilder.toString:()Ljava/lang/String;
      70: astore_3
      71: getstatic     #14                 // Field log:Lorg/apache/commons/logging/Log;
      74: aload_3
      75: aload_2
      76: invokeinterface #31,  3           // InterfaceMethod org/apache/commons/logging/Log.error:(Ljava/lang/Object;Ljava/lang/Throwable;)V
      81: new           #105                // class org/wso2/carbon/registry/info/stub/RegistryExceptionException
      84: dup
      85: aload_3
      86: aload_2
      87: invokespecial #106                // Method org/wso2/carbon/registry/info/stub/RegistryExceptionException."<init>":(Ljava/lang/String;Ljava/lang/Throwable;)V
      90: athrow
    Exception table:
       from    to  target type
           0     8     9   Class java/rmi/RemoteException
           0     8    50   Class org/wso2/carbon/registry/resource/stub/ResourceAdminServiceExceptionException

  public boolean importResource(java.lang.String, java.lang.String, java.lang.String, java.lang.String, java.lang.String, java.lang.String) throws java.rmi.RemoteException, org.wso2.carbon.registry.info.stub.RegistryExceptionException;
    Code:
       0: aload_0
       1: getfield      #11                 // Field resourceAdminServiceStub:Lorg/wso2/carbon/registry/resource/stub/ResourceAdminServiceStub;
       4: aload_1
       5: aload_2
       6: aload_3
       7: aload         4
       9: aload         5
      11: aload         6
      13: aconst_null
      14: invokevirtual #41                 // Method org/wso2/carbon/registry/resource/stub/ResourceAdminServiceStub.importResource:(Ljava/lang/String;Ljava/lang/String;Ljava/lang/String;Ljava/lang/String;Ljava/lang/String;Ljava/lang/String;[Lorg/wso2/carbon/registry/resource/stub/services/ArrayOfString;)Z
      17: ireturn
      18: astore        7
      20: ldc           #109                // String Unable to import resource
      22: astore        8
      24: getstatic     #14                 // Field log:Lorg/apache/commons/logging/Log;
      27: aload         8
      29: aload         7
      31: invokeinterface #31,  3           // InterfaceMethod org/apache/commons/logging/Log.error:(Ljava/lang/Object;Ljava/lang/Throwable;)V
      36: new           #23                 // class java/rmi/RemoteException
      39: dup
      40: aload         8
      42: aload         7
      44: invokespecial #28                 // Method java/rmi/RemoteException."<init>":(Ljava/lang/String;Ljava/lang/Throwable;)V
      47: athrow
      48: astore        7
      50: ldc           #109                // String Unable to import resource
      52: astore        8
      54: getstatic     #14                 // Field log:Lorg/apache/commons/logging/Log;
      57: aload         8
      59: aload         7
      61: invokeinterface #31,  3           // InterfaceMethod org/apache/commons/logging/Log.error:(Ljava/lang/Object;Ljava/lang/Throwable;)V
      66: new           #105                // class org/wso2/carbon/registry/info/stub/RegistryExceptionException
      69: dup
      70: aload         8
      72: aload         7
      74: invokespecial #106                // Method org/wso2/carbon/registry/info/stub/RegistryExceptionException."<init>":(Ljava/lang/String;Ljava/lang/Throwable;)V
      77: athrow
    Exception table:
       from    to  target type
           0    17    18   Class java/rmi/RemoteException
           0    17    48   Class org/wso2/carbon/registry/resource/stub/ResourceAdminServiceExceptionException

  public org.wso2.carbon.registry.resource.stub.beans.xsd.ResourceTreeEntryBean getResourceTreeEntryBean(java.lang.String) throws java.rmi.RemoteException, org.wso2.carbon.registry.info.stub.RegistryExceptionException;
    Code:
       0: aload_0
       1: getfield      #11                 // Field resourceAdminServiceStub:Lorg/wso2/carbon/registry/resource/stub/ResourceAdminServiceStub;
       4: aload_1
       5: invokevirtual #110                // Method org/wso2/carbon/registry/resource/stub/ResourceAdminServiceStub.getResourceTreeEntry:(Ljava/lang/String;)Lorg/wso2/carbon/registry/resource/stub/beans/xsd/ResourceTreeEntryBean;
       8: areturn
       9: astore_2
      10: ldc           #111                // String Unable get resource tree entry
      12: astore_3
      13: getstatic     #14                 // Field log:Lorg/apache/commons/logging/Log;
      16: aload_3
      17: aload_2
      18: invokeinterface #31,  3           // InterfaceMethod org/apache/commons/logging/Log.error:(Ljava/lang/Object;Ljava/lang/Throwable;)V
      23: new           #23                 // class java/rmi/RemoteException
      26: dup
      27: aload_3
      28: aload_2
      29: invokespecial #28                 // Method java/rmi/RemoteException."<init>":(Ljava/lang/String;Ljava/lang/Throwable;)V
      32: athrow
      33: astore_2
      34: ldc           #111                // String Unable get resource tree entry
      36: astore_3
      37: getstatic     #14                 // Field log:Lorg/apache/commons/logging/Log;
      40: aload_3
      41: aload_2
      42: invokeinterface #31,  3           // InterfaceMethod org/apache/commons/logging/Log.error:(Ljava/lang/Object;Ljava/lang/Throwable;)V
      47: new           #105                // class org/wso2/carbon/registry/info/stub/RegistryExceptionException
      50: dup
      51: aload_3
      52: aload_2
      53: invokespecial #106                // Method org/wso2/carbon/registry/info/stub/RegistryExceptionException."<init>":(Ljava/lang/String;Ljava/lang/Throwable;)V
      56: athrow
    Exception table:
       from    to  target type
           0     8     9   Class java/rmi/RemoteException
           0     8    33   Class org/wso2/carbon/registry/resource/stub/ResourceAdminServiceExceptionException

  static {};
    Code:
       0: ldc           #7                  // class org/wso2/esb/integration/common/clients/registry/ResourceAdminServiceClient
       2: invokestatic  #112                // Method org/apache/commons/logging/LogFactory.getLog:(Ljava/lang/Class;)Lorg/apache/commons/logging/Log;
       5: putstatic     #14                 // Field log:Lorg/apache/commons/logging/Log;
       8: return
}
