Compiled from "MultithreadEventExecutorGroup.java"
final class io.netty.util.concurrent.MultithreadEventExecutorGroup$GenericEventExecutorChooser implements io.netty.util.concurrent.MultithreadEventExecutorGroup$EventExecutorChooser {
  final io.netty.util.concurrent.MultithreadEventExecutorGroup this$0;

  private io.netty.util.concurrent.MultithreadEventExecutorGroup$GenericEventExecutorChooser(io.netty.util.concurrent.MultithreadEventExecutorGroup);
    Code:
       0: aload_0
       1: aload_1
       2: putfield      #2                  // Field this$0:Lio/netty/util/concurrent/MultithreadEventExecutorGroup;
       5: aload_0
       6: invokespecial #3                  // Method java/lang/Object."<init>":()V
       9: return

  public io.netty.util.concurrent.EventExecutor next();
    Code:
       0: aload_0
       1: getfield      #2                  // Field this$0:Lio/netty/util/concurrent/MultithreadEventExecutorGroup;
       4: invokestatic  #4                  // Method io/netty/util/concurrent/MultithreadEventExecutorGroup.access$300:(Lio/netty/util/concurrent/MultithreadEventExecutorGroup;)[Lio/netty/util/concurrent/EventExecutor;
       7: aload_0
       8: getfield      #2                  // Field this$0:Lio/netty/util/concurrent/MultithreadEventExecutorGroup;
      11: invokestatic  #5                  // Method io/netty/util/concurrent/MultithreadEventExecutorGroup.access$500:(Lio/netty/util/concurrent/MultithreadEventExecutorGroup;)Ljava/util/concurrent/atomic/AtomicInteger;
      14: invokevirtual #6                  // Method java/util/concurrent/atomic/AtomicInteger.getAndIncrement:()I
      17: aload_0
      18: getfield      #2                  // Field this$0:Lio/netty/util/concurrent/MultithreadEventExecutorGroup;
      21: invokestatic  #4                  // Method io/netty/util/concurrent/MultithreadEventExecutorGroup.access$300:(Lio/netty/util/concurrent/MultithreadEventExecutorGroup;)[Lio/netty/util/concurrent/EventExecutor;
      24: arraylength
      25: irem
      26: invokestatic  #7                  // Method java/lang/Math.abs:(I)I
      29: aaload
      30: areturn

  io.netty.util.concurrent.MultithreadEventExecutorGroup$GenericEventExecutorChooser(io.netty.util.concurrent.MultithreadEventExecutorGroup, io.netty.util.concurrent.MultithreadEventExecutorGroup$1);
    Code:
       0: aload_0
       1: aload_1
       2: invokespecial #1                  // Method "<init>":(Lio/netty/util/concurrent/MultithreadEventExecutorGroup;)V
       5: return
}
