Compiled from "PlugInConsumer.java"
public interface org.wildfly.swarm.config.management.security_realm.PlugInConsumer<T extends org.wildfly.swarm.config.management.security_realm.PlugIn<T>> {
  public abstract void accept(T);

  public default org.wildfly.swarm.config.management.security_realm.PlugInConsumer<T> andThen(org.wildfly.swarm.config.management.security_realm.PlugInConsumer<T>);
    Code:
       0: aload_0
       1: aload_1
       2: invokedynamic #1,  0              // InvokeDynamic #0:accept:(Lorg/wildfly/swarm/config/management/security_realm/PlugInConsumer;Lorg/wildfly/swarm/config/management/security_realm/PlugInConsumer;)Lorg/wildfly/swarm/config/management/security_realm/PlugInConsumer;
       7: areturn

  private void lambda$andThen$101(org.wildfly.swarm.config.management.security_realm.PlugInConsumer, org.wildfly.swarm.config.management.security_realm.PlugIn);
    Code:
       0: aload_0
       1: aload_2
       2: invokeinterface #2,  2            // InterfaceMethod accept:(Lorg/wildfly/swarm/config/management/security_realm/PlugIn;)V
       7: aload_1
       8: aload_2
       9: invokeinterface #2,  2            // InterfaceMethod accept:(Lorg/wildfly/swarm/config/management/security_realm/PlugIn;)V
      14: return
}
