Compiled from "PlugInAuthorizationConsumer.java"
public interface org.wildfly.swarm.config.management.security_realm.PlugInAuthorizationConsumer<T extends org.wildfly.swarm.config.management.security_realm.PlugInAuthorization<T>> {
  public abstract void accept(T);

  public default org.wildfly.swarm.config.management.security_realm.PlugInAuthorizationConsumer<T> andThen(org.wildfly.swarm.config.management.security_realm.PlugInAuthorizationConsumer<T>);
    Code:
       0: aload_0
       1: aload_1
       2: invokedynamic #1,  0              // InvokeDynamic #0:accept:(Lorg/wildfly/swarm/config/management/security_realm/PlugInAuthorizationConsumer;Lorg/wildfly/swarm/config/management/security_realm/PlugInAuthorizationConsumer;)Lorg/wildfly/swarm/config/management/security_realm/PlugInAuthorizationConsumer;
       7: areturn

  private void lambda$andThen$111(org.wildfly.swarm.config.management.security_realm.PlugInAuthorizationConsumer, org.wildfly.swarm.config.management.security_realm.PlugInAuthorization);
    Code:
       0: aload_0
       1: aload_2
       2: invokeinterface #2,  2            // InterfaceMethod accept:(Lorg/wildfly/swarm/config/management/security_realm/PlugInAuthorization;)V
       7: aload_1
       8: aload_2
       9: invokeinterface #2,  2            // InterfaceMethod accept:(Lorg/wildfly/swarm/config/management/security_realm/PlugInAuthorization;)V
      14: return
}
