Compiled from "AutoValue_NetFlowV9Packet.java"
final class org.graylog.plugins.netflow.v9.AutoValue_NetFlowV9Packet extends org.graylog.plugins.netflow.v9.NetFlowV9Packet {
  private final org.graylog.plugins.netflow.v9.NetFlowV9Header header;

  private final com.google.common.collect.ImmutableList<org.graylog.plugins.netflow.v9.NetFlowV9Template> templates;

  private final org.graylog.plugins.netflow.v9.NetFlowV9OptionTemplate optionTemplate;

  private final com.google.common.collect.ImmutableList<org.graylog.plugins.netflow.v9.NetFlowV9BaseRecord> records;

  private final long dataLength;

  org.graylog.plugins.netflow.v9.AutoValue_NetFlowV9Packet(org.graylog.plugins.netflow.v9.NetFlowV9Header, com.google.common.collect.ImmutableList<org.graylog.plugins.netflow.v9.NetFlowV9Template>, org.graylog.plugins.netflow.v9.NetFlowV9OptionTemplate, com.google.common.collect.ImmutableList<org.graylog.plugins.netflow.v9.NetFlowV9BaseRecord>, long);
    Code:
       0: aload_0
       1: invokespecial #1                  // Method org/graylog/plugins/netflow/v9/NetFlowV9Packet."<init>":()V
       4: aload_1
       5: ifnonnull     18
       8: new           #2                  // class java/lang/NullPointerException
      11: dup
      12: ldc           #3                  // String Null header
      14: invokespecial #4                  // Method java/lang/NullPointerException."<init>":(Ljava/lang/String;)V
      17: athrow
      18: aload_0
      19: aload_1
      20: putfield      #5                  // Field header:Lorg/graylog/plugins/netflow/v9/NetFlowV9Header;
      23: aload_2
      24: ifnonnull     37
      27: new           #2                  // class java/lang/NullPointerException
      30: dup
      31: ldc           #6                  // String Null templates
      33: invokespecial #4                  // Method java/lang/NullPointerException."<init>":(Ljava/lang/String;)V
      36: athrow
      37: aload_0
      38: aload_2
      39: putfield      #7                  // Field templates:Lcom/google/common/collect/ImmutableList;
      42: aload_0
      43: aload_3
      44: putfield      #8                  // Field optionTemplate:Lorg/graylog/plugins/netflow/v9/NetFlowV9OptionTemplate;
      47: aload         4
      49: ifnonnull     62
      52: new           #2                  // class java/lang/NullPointerException
      55: dup
      56: ldc           #9                  // String Null records
      58: invokespecial #4                  // Method java/lang/NullPointerException."<init>":(Ljava/lang/String;)V
      61: athrow
      62: aload_0
      63: aload         4
      65: putfield      #10                 // Field records:Lcom/google/common/collect/ImmutableList;
      68: aload_0
      69: lload         5
      71: putfield      #11                 // Field dataLength:J
      74: return

  public org.graylog.plugins.netflow.v9.NetFlowV9Header header();
    Code:
       0: aload_0
       1: getfield      #5                  // Field header:Lorg/graylog/plugins/netflow/v9/NetFlowV9Header;
       4: areturn

  public com.google.common.collect.ImmutableList<org.graylog.plugins.netflow.v9.NetFlowV9Template> templates();
    Code:
       0: aload_0
       1: getfield      #7                  // Field templates:Lcom/google/common/collect/ImmutableList;
       4: areturn

  public org.graylog.plugins.netflow.v9.NetFlowV9OptionTemplate optionTemplate();
    Code:
       0: aload_0
       1: getfield      #8                  // Field optionTemplate:Lorg/graylog/plugins/netflow/v9/NetFlowV9OptionTemplate;
       4: areturn

  public com.google.common.collect.ImmutableList<org.graylog.plugins.netflow.v9.NetFlowV9BaseRecord> records();
    Code:
       0: aload_0
       1: getfield      #10                 // Field records:Lcom/google/common/collect/ImmutableList;
       4: areturn

  public long dataLength();
    Code:
       0: aload_0
       1: getfield      #11                 // Field dataLength:J
       4: lreturn

  public boolean equals(java.lang.Object);
    Code:
       0: aload_1
       1: aload_0
       2: if_acmpne     7
       5: iconst_1
       6: ireturn
       7: aload_1
       8: instanceof    #12                 // class org/graylog/plugins/netflow/v9/NetFlowV9Packet
      11: ifeq          110
      14: aload_1
      15: checkcast     #12                 // class org/graylog/plugins/netflow/v9/NetFlowV9Packet
      18: astore_2
      19: aload_0
      20: getfield      #5                  // Field header:Lorg/graylog/plugins/netflow/v9/NetFlowV9Header;
      23: aload_2
      24: invokevirtual #13                 // Method org/graylog/plugins/netflow/v9/NetFlowV9Packet.header:()Lorg/graylog/plugins/netflow/v9/NetFlowV9Header;
      27: invokevirtual #14                 // Method java/lang/Object.equals:(Ljava/lang/Object;)Z
      30: ifeq          108
      33: aload_0
      34: getfield      #7                  // Field templates:Lcom/google/common/collect/ImmutableList;
      37: aload_2
      38: invokevirtual #15                 // Method org/graylog/plugins/netflow/v9/NetFlowV9Packet.templates:()Lcom/google/common/collect/ImmutableList;
      41: invokevirtual #16                 // Method com/google/common/collect/ImmutableList.equals:(Ljava/lang/Object;)Z
      44: ifeq          108
      47: aload_0
      48: getfield      #8                  // Field optionTemplate:Lorg/graylog/plugins/netflow/v9/NetFlowV9OptionTemplate;
      51: ifnonnull     64
      54: aload_2
      55: invokevirtual #17                 // Method org/graylog/plugins/netflow/v9/NetFlowV9Packet.optionTemplate:()Lorg/graylog/plugins/netflow/v9/NetFlowV9OptionTemplate;
      58: ifnonnull     108
      61: goto          78
      64: aload_0
      65: getfield      #8                  // Field optionTemplate:Lorg/graylog/plugins/netflow/v9/NetFlowV9OptionTemplate;
      68: aload_2
      69: invokevirtual #17                 // Method org/graylog/plugins/netflow/v9/NetFlowV9Packet.optionTemplate:()Lorg/graylog/plugins/netflow/v9/NetFlowV9OptionTemplate;
      72: invokevirtual #14                 // Method java/lang/Object.equals:(Ljava/lang/Object;)Z
      75: ifeq          108
      78: aload_0
      79: getfield      #10                 // Field records:Lcom/google/common/collect/ImmutableList;
      82: aload_2
      83: invokevirtual #18                 // Method org/graylog/plugins/netflow/v9/NetFlowV9Packet.records:()Lcom/google/common/collect/ImmutableList;
      86: invokevirtual #16                 // Method com/google/common/collect/ImmutableList.equals:(Ljava/lang/Object;)Z
      89: ifeq          108
      92: aload_0
      93: getfield      #11                 // Field dataLength:J
      96: aload_2
      97: invokevirtual #19                 // Method org/graylog/plugins/netflow/v9/NetFlowV9Packet.dataLength:()J
     100: lcmp
     101: ifne          108
     104: iconst_1
     105: goto          109
     108: iconst_0
     109: ireturn
     110: iconst_0
     111: ireturn

  public int hashCode();
    Code:
       0: iconst_1
       1: istore_1
       2: iload_1
       3: ldc           #20                 // int 1000003
       5: imul
       6: istore_1
       7: iload_1
       8: aload_0
       9: getfield      #5                  // Field header:Lorg/graylog/plugins/netflow/v9/NetFlowV9Header;
      12: invokevirtual #21                 // Method java/lang/Object.hashCode:()I
      15: ixor
      16: istore_1
      17: iload_1
      18: ldc           #20                 // int 1000003
      20: imul
      21: istore_1
      22: iload_1
      23: aload_0
      24: getfield      #7                  // Field templates:Lcom/google/common/collect/ImmutableList;
      27: invokevirtual #22                 // Method com/google/common/collect/ImmutableList.hashCode:()I
      30: ixor
      31: istore_1
      32: iload_1
      33: ldc           #20                 // int 1000003
      35: imul
      36: istore_1
      37: iload_1
      38: aload_0
      39: getfield      #8                  // Field optionTemplate:Lorg/graylog/plugins/netflow/v9/NetFlowV9OptionTemplate;
      42: ifnonnull     49
      45: iconst_0
      46: goto          56
      49: aload_0
      50: getfield      #8                  // Field optionTemplate:Lorg/graylog/plugins/netflow/v9/NetFlowV9OptionTemplate;
      53: invokevirtual #21                 // Method java/lang/Object.hashCode:()I
      56: ixor
      57: istore_1
      58: iload_1
      59: ldc           #20                 // int 1000003
      61: imul
      62: istore_1
      63: iload_1
      64: aload_0
      65: getfield      #10                 // Field records:Lcom/google/common/collect/ImmutableList;
      68: invokevirtual #22                 // Method com/google/common/collect/ImmutableList.hashCode:()I
      71: ixor
      72: istore_1
      73: iload_1
      74: ldc           #20                 // int 1000003
      76: imul
      77: istore_1
      78: iload_1
      79: aload_0
      80: getfield      #11                 // Field dataLength:J
      83: bipush        32
      85: lushr
      86: aload_0
      87: getfield      #11                 // Field dataLength:J
      90: lxor
      91: l2i
      92: ixor
      93: istore_1
      94: iload_1
      95: ireturn
}
