Compiled from "SessionRestoringHandler.java"
class io.undertow.servlet.handlers.SessionRestoringHandler$2 implements java.security.PrivilegedAction<java.lang.Void> {
  final java.lang.ClassLoader val$classLoader;

  final io.undertow.servlet.handlers.SessionRestoringHandler this$0;

  io.undertow.servlet.handlers.SessionRestoringHandler$2(io.undertow.servlet.handlers.SessionRestoringHandler, java.lang.ClassLoader);
    Code:
       0: aload_0
       1: aload_1
       2: putfield      #1                  // Field this$0:Lio/undertow/servlet/handlers/SessionRestoringHandler;
       5: aload_0
       6: aload_2
       7: putfield      #2                  // Field val$classLoader:Ljava/lang/ClassLoader;
      10: aload_0
      11: invokespecial #3                  // Method java/lang/Object."<init>":()V
      14: return

  public java.lang.Void run();
    Code:
       0: invokestatic  #4                  // Method java/lang/Thread.currentThread:()Ljava/lang/Thread;
       3: aload_0
       4: getfield      #2                  // Field val$classLoader:Ljava/lang/ClassLoader;
       7: invokevirtual #5                  // Method java/lang/Thread.setContextClassLoader:(Ljava/lang/ClassLoader;)V
      10: aconst_null
      11: areturn

  public java.lang.Object run();
    Code:
       0: aload_0
       1: invokevirtual #6                  // Method run:()Ljava/lang/Void;
       4: areturn
}
