Compiled from "ByteStreams.java"
final class com.google.common.io.ByteStreams$4 implements com.google.common.io.InputSupplier<java.io.InputStream> {
  final com.google.common.io.InputSupplier val$supplier;

  final long val$offset;

  final long val$length;

  com.google.common.io.ByteStreams$4(com.google.common.io.InputSupplier, long, long);
    Code:
       0: aload_0
       1: aload_1
       2: putfield      #1                  // Field val$supplier:Lcom/google/common/io/InputSupplier;
       5: aload_0
       6: lload_2
       7: putfield      #2                  // Field val$offset:J
      10: aload_0
      11: lload         4
      13: putfield      #3                  // Field val$length:J
      16: aload_0
      17: invokespecial #4                  // Method java/lang/Object."<init>":()V
      20: return

  public java.io.InputStream getInput() throws java.io.IOException;
    Code:
       0: aload_0
       1: getfield      #1                  // Field val$supplier:Lcom/google/common/io/InputSupplier;
       4: invokeinterface #5,  1            // InterfaceMethod com/google/common/io/InputSupplier.getInput:()Ljava/lang/Object;
       9: checkcast     #6                  // class java/io/InputStream
      12: astore_1
      13: aload_0
      14: getfield      #2                  // Field val$offset:J
      17: lconst_0
      18: lcmp
      19: ifle          40
      22: aload_1
      23: aload_0
      24: getfield      #2                  // Field val$offset:J
      27: invokestatic  #7                  // Method com/google/common/io/ByteStreams.skipFully:(Ljava/io/InputStream;J)V
      30: goto          40
      33: astore_2
      34: aload_1
      35: invokestatic  #9                  // Method com/google/common/io/Closeables.closeQuietly:(Ljava/io/Closeable;)V
      38: aload_2
      39: athrow
      40: new           #10                 // class com/google/common/io/LimitInputStream
      43: dup
      44: aload_1
      45: aload_0
      46: getfield      #3                  // Field val$length:J
      49: invokespecial #11                 // Method com/google/common/io/LimitInputStream."<init>":(Ljava/io/InputStream;J)V
      52: areturn
    Exception table:
       from    to  target type
          22    30    33   Class java/io/IOException

  public java.lang.Object getInput() throws java.io.IOException;
    Code:
       0: aload_0
       1: invokevirtual #12                 // Method getInput:()Ljava/io/InputStream;
       4: areturn
}
