Compiled from "AsyncWebSocketHttpServerExchange.java"
class io.undertow.websockets.spi.AsyncWebSocketHttpServerExchange$1 implements io.undertow.io.IoCallback {
  final org.xnio.FutureResult val$future;

  final io.undertow.websockets.spi.AsyncWebSocketHttpServerExchange this$0;

  io.undertow.websockets.spi.AsyncWebSocketHttpServerExchange$1(io.undertow.websockets.spi.AsyncWebSocketHttpServerExchange, org.xnio.FutureResult);
    Code:
       0: aload_0
       1: aload_1
       2: putfield      #1                  // Field this$0:Lio/undertow/websockets/spi/AsyncWebSocketHttpServerExchange;
       5: aload_0
       6: aload_2
       7: putfield      #2                  // Field val$future:Lorg/xnio/FutureResult;
      10: aload_0
      11: invokespecial #3                  // Method java/lang/Object."<init>":()V
      14: return

  public void onComplete(io.undertow.server.HttpServerExchange, io.undertow.io.Sender);
    Code:
       0: aload_0
       1: getfield      #2                  // Field val$future:Lorg/xnio/FutureResult;
       4: aconst_null
       5: invokevirtual #4                  // Method org/xnio/FutureResult.setResult:(Ljava/lang/Object;)Z
       8: pop
       9: return

  public void onException(io.undertow.server.HttpServerExchange, io.undertow.io.Sender, java.io.IOException);
    Code:
       0: getstatic     #5                  // Field io/undertow/UndertowLogger.REQUEST_IO_LOGGER:Lio/undertow/UndertowLogger;
       3: aload_3
       4: invokeinterface #6,  2            // InterfaceMethod io/undertow/UndertowLogger.ioException:(Ljava/io/IOException;)V
       9: aload_0
      10: getfield      #2                  // Field val$future:Lorg/xnio/FutureResult;
      13: aload_3
      14: invokevirtual #7                  // Method org/xnio/FutureResult.setException:(Ljava/io/IOException;)Z
      17: pop
      18: return
}
