Compiled from "InterTypeConstructorDeclarationImpl.java"
public class org.aspectj.internal.lang.reflect.InterTypeConstructorDeclarationImpl extends org.aspectj.internal.lang.reflect.InterTypeDeclarationImpl implements org.aspectj.lang.reflect.InterTypeConstructorDeclaration {
  private java.lang.reflect.Method baseMethod;

  public org.aspectj.internal.lang.reflect.InterTypeConstructorDeclarationImpl(org.aspectj.lang.reflect.AjType<?>, java.lang.String, int, java.lang.reflect.Method);
    Code:
       0: aload_0
       1: aload_1
       2: aload_2
       3: iload_3
       4: invokespecial #1                  // Method org/aspectj/internal/lang/reflect/InterTypeDeclarationImpl."<init>":(Lorg/aspectj/lang/reflect/AjType;Ljava/lang/String;I)V
       7: aload_0
       8: aload         4
      10: putfield      #2                  // Field baseMethod:Ljava/lang/reflect/Method;
      13: return

  public org.aspectj.lang.reflect.AjType<?>[] getParameterTypes();
    Code:
       0: aload_0
       1: getfield      #2                  // Field baseMethod:Ljava/lang/reflect/Method;
       4: invokevirtual #3                  // Method java/lang/reflect/Method.getParameterTypes:()[Ljava/lang/Class;
       7: astore_1
       8: aload_1
       9: arraylength
      10: iconst_1
      11: isub
      12: anewarray     #4                  // class org/aspectj/lang/reflect/AjType
      15: astore_2
      16: iconst_1
      17: istore_3
      18: iload_3
      19: aload_1
      20: arraylength
      21: if_icmpge     41
      24: aload_2
      25: iload_3
      26: iconst_1
      27: isub
      28: aload_1
      29: iload_3
      30: aaload
      31: invokestatic  #5                  // Method org/aspectj/lang/reflect/AjTypeSystem.getAjType:(Ljava/lang/Class;)Lorg/aspectj/lang/reflect/AjType;
      34: aastore
      35: iinc          3, 1
      38: goto          18
      41: aload_2
      42: areturn

  public java.lang.reflect.Type[] getGenericParameterTypes();
    Code:
       0: aload_0
       1: getfield      #2                  // Field baseMethod:Ljava/lang/reflect/Method;
       4: invokevirtual #6                  // Method java/lang/reflect/Method.getGenericParameterTypes:()[Ljava/lang/reflect/Type;
       7: astore_1
       8: aload_1
       9: arraylength
      10: iconst_1
      11: isub
      12: anewarray     #4                  // class org/aspectj/lang/reflect/AjType
      15: astore_2
      16: iconst_1
      17: istore_3
      18: iload_3
      19: aload_1
      20: arraylength
      21: if_icmpge     64
      24: aload_1
      25: iload_3
      26: aaload
      27: instanceof    #7                  // class java/lang/Class
      30: ifeq          50
      33: aload_2
      34: iload_3
      35: iconst_1
      36: isub
      37: aload_1
      38: iload_3
      39: aaload
      40: checkcast     #7                  // class java/lang/Class
      43: invokestatic  #5                  // Method org/aspectj/lang/reflect/AjTypeSystem.getAjType:(Ljava/lang/Class;)Lorg/aspectj/lang/reflect/AjType;
      46: aastore
      47: goto          58
      50: aload_2
      51: iload_3
      52: iconst_1
      53: isub
      54: aload_1
      55: iload_3
      56: aaload
      57: aastore
      58: iinc          3, 1
      61: goto          18
      64: aload_2
      65: areturn

  public org.aspectj.lang.reflect.AjType<?>[] getExceptionTypes();
    Code:
       0: aload_0
       1: getfield      #2                  // Field baseMethod:Ljava/lang/reflect/Method;
       4: invokevirtual #8                  // Method java/lang/reflect/Method.getExceptionTypes:()[Ljava/lang/Class;
       7: astore_1
       8: aload_1
       9: arraylength
      10: anewarray     #4                  // class org/aspectj/lang/reflect/AjType
      13: astore_2
      14: iconst_0
      15: istore_3
      16: iload_3
      17: aload_1
      18: arraylength
      19: if_icmpge     37
      22: aload_2
      23: iload_3
      24: aload_1
      25: iload_3
      26: aaload
      27: invokestatic  #5                  // Method org/aspectj/lang/reflect/AjTypeSystem.getAjType:(Ljava/lang/Class;)Lorg/aspectj/lang/reflect/AjType;
      30: aastore
      31: iinc          3, 1
      34: goto          16
      37: aload_2
      38: areturn

  public java.lang.String toString();
    Code:
       0: new           #9                  // class java/lang/StringBuffer
       3: dup
       4: invokespecial #10                 // Method java/lang/StringBuffer."<init>":()V
       7: astore_1
       8: aload_1
       9: aload_0
      10: invokevirtual #11                 // Method getModifiers:()I
      13: invokestatic  #12                 // Method java/lang/reflect/Modifier.toString:(I)Ljava/lang/String;
      16: invokevirtual #13                 // Method java/lang/StringBuffer.append:(Ljava/lang/String;)Ljava/lang/StringBuffer;
      19: pop
      20: aload_1
      21: ldc           #14                 // String
      23: invokevirtual #13                 // Method java/lang/StringBuffer.append:(Ljava/lang/String;)Ljava/lang/StringBuffer;
      26: pop
      27: aload_1
      28: aload_0
      29: getfield      #15                 // Field targetTypeName:Ljava/lang/String;
      32: invokevirtual #13                 // Method java/lang/StringBuffer.append:(Ljava/lang/String;)Ljava/lang/StringBuffer;
      35: pop
      36: aload_1
      37: ldc           #16                 // String .new
      39: invokevirtual #13                 // Method java/lang/StringBuffer.append:(Ljava/lang/String;)Ljava/lang/StringBuffer;
      42: pop
      43: aload_1
      44: ldc           #17                 // String (
      46: invokevirtual #13                 // Method java/lang/StringBuffer.append:(Ljava/lang/String;)Ljava/lang/StringBuffer;
      49: pop
      50: aload_0
      51: invokevirtual #18                 // Method getParameterTypes:()[Lorg/aspectj/lang/reflect/AjType;
      54: astore_2
      55: iconst_0
      56: istore_3
      57: iload_3
      58: aload_2
      59: arraylength
      60: iconst_1
      61: isub
      62: if_icmpge     89
      65: aload_1
      66: aload_2
      67: iload_3
      68: aaload
      69: invokevirtual #19                 // Method java/lang/Object.toString:()Ljava/lang/String;
      72: invokevirtual #13                 // Method java/lang/StringBuffer.append:(Ljava/lang/String;)Ljava/lang/StringBuffer;
      75: pop
      76: aload_1
      77: ldc           #20                 // String ,
      79: invokevirtual #13                 // Method java/lang/StringBuffer.append:(Ljava/lang/String;)Ljava/lang/StringBuffer;
      82: pop
      83: iinc          3, 1
      86: goto          57
      89: aload_2
      90: arraylength
      91: ifle          108
      94: aload_1
      95: aload_2
      96: aload_2
      97: arraylength
      98: iconst_1
      99: isub
     100: aaload
     101: invokevirtual #19                 // Method java/lang/Object.toString:()Ljava/lang/String;
     104: invokevirtual #13                 // Method java/lang/StringBuffer.append:(Ljava/lang/String;)Ljava/lang/StringBuffer;
     107: pop
     108: aload_1
     109: ldc           #21                 // String )
     111: invokevirtual #13                 // Method java/lang/StringBuffer.append:(Ljava/lang/String;)Ljava/lang/StringBuffer;
     114: pop
     115: aload_1
     116: invokevirtual #22                 // Method java/lang/StringBuffer.toString:()Ljava/lang/String;
     119: areturn
}
