Compiled from "CharRange.java"
class org.sonar.api.internal.apachecommons.lang.CharRange$CharacterIterator implements java.util.Iterator {
  private char current;

  private final org.sonar.api.internal.apachecommons.lang.CharRange range;

  private boolean hasNext;

  private org.sonar.api.internal.apachecommons.lang.CharRange$CharacterIterator(org.sonar.api.internal.apachecommons.lang.CharRange);
    Code:
       0: aload_0
       1: invokespecial #23                 // Method java/lang/Object."<init>":()V
       4: aload_0
       5: aload_1
       6: putfield      #25                 // Field range:Lorg/sonar/api/internal/apachecommons/lang/CharRange;
       9: aload_0
      10: iconst_1
      11: putfield      #27                 // Field hasNext:Z
      14: aload_0
      15: getfield      #25                 // Field range:Lorg/sonar/api/internal/apachecommons/lang/CharRange;
      18: invokestatic  #31                 // Method org/sonar/api/internal/apachecommons/lang/CharRange.access$100:(Lorg/sonar/api/internal/apachecommons/lang/CharRange;)Z
      21: ifeq          79
      24: aload_0
      25: getfield      #25                 // Field range:Lorg/sonar/api/internal/apachecommons/lang/CharRange;
      28: invokestatic  #35                 // Method org/sonar/api/internal/apachecommons/lang/CharRange.access$200:(Lorg/sonar/api/internal/apachecommons/lang/CharRange;)C
      31: ifne          71
      34: aload_0
      35: getfield      #25                 // Field range:Lorg/sonar/api/internal/apachecommons/lang/CharRange;
      38: invokestatic  #38                 // Method org/sonar/api/internal/apachecommons/lang/CharRange.access$300:(Lorg/sonar/api/internal/apachecommons/lang/CharRange;)C
      41: ldc           #39                 // int 65535
      43: if_icmpne     54
      46: aload_0
      47: iconst_0
      48: putfield      #27                 // Field hasNext:Z
      51: goto          90
      54: aload_0
      55: aload_0
      56: getfield      #25                 // Field range:Lorg/sonar/api/internal/apachecommons/lang/CharRange;
      59: invokestatic  #38                 // Method org/sonar/api/internal/apachecommons/lang/CharRange.access$300:(Lorg/sonar/api/internal/apachecommons/lang/CharRange;)C
      62: iconst_1
      63: iadd
      64: i2c
      65: putfield      #41                 // Field current:C
      68: goto          90
      71: aload_0
      72: iconst_0
      73: putfield      #41                 // Field current:C
      76: goto          90
      79: aload_0
      80: aload_0
      81: getfield      #25                 // Field range:Lorg/sonar/api/internal/apachecommons/lang/CharRange;
      84: invokestatic  #35                 // Method org/sonar/api/internal/apachecommons/lang/CharRange.access$200:(Lorg/sonar/api/internal/apachecommons/lang/CharRange;)C
      87: putfield      #41                 // Field current:C
      90: return

  private void prepareNext();
    Code:
       0: aload_0
       1: getfield      #25                 // Field range:Lorg/sonar/api/internal/apachecommons/lang/CharRange;
       4: invokestatic  #31                 // Method org/sonar/api/internal/apachecommons/lang/CharRange.access$100:(Lorg/sonar/api/internal/apachecommons/lang/CharRange;)Z
       7: ifeq          94
      10: aload_0
      11: getfield      #41                 // Field current:C
      14: ldc           #39                 // int 65535
      16: if_icmpne     27
      19: aload_0
      20: iconst_0
      21: putfield      #27                 // Field hasNext:Z
      24: goto          127
      27: aload_0
      28: getfield      #41                 // Field current:C
      31: iconst_1
      32: iadd
      33: aload_0
      34: getfield      #25                 // Field range:Lorg/sonar/api/internal/apachecommons/lang/CharRange;
      37: invokestatic  #35                 // Method org/sonar/api/internal/apachecommons/lang/CharRange.access$200:(Lorg/sonar/api/internal/apachecommons/lang/CharRange;)C
      40: if_icmpne     80
      43: aload_0
      44: getfield      #25                 // Field range:Lorg/sonar/api/internal/apachecommons/lang/CharRange;
      47: invokestatic  #38                 // Method org/sonar/api/internal/apachecommons/lang/CharRange.access$300:(Lorg/sonar/api/internal/apachecommons/lang/CharRange;)C
      50: ldc           #39                 // int 65535
      52: if_icmpne     63
      55: aload_0
      56: iconst_0
      57: putfield      #27                 // Field hasNext:Z
      60: goto          127
      63: aload_0
      64: aload_0
      65: getfield      #25                 // Field range:Lorg/sonar/api/internal/apachecommons/lang/CharRange;
      68: invokestatic  #38                 // Method org/sonar/api/internal/apachecommons/lang/CharRange.access$300:(Lorg/sonar/api/internal/apachecommons/lang/CharRange;)C
      71: iconst_1
      72: iadd
      73: i2c
      74: putfield      #41                 // Field current:C
      77: goto          127
      80: aload_0
      81: aload_0
      82: getfield      #41                 // Field current:C
      85: iconst_1
      86: iadd
      87: i2c
      88: putfield      #41                 // Field current:C
      91: goto          127
      94: aload_0
      95: getfield      #41                 // Field current:C
      98: aload_0
      99: getfield      #25                 // Field range:Lorg/sonar/api/internal/apachecommons/lang/CharRange;
     102: invokestatic  #38                 // Method org/sonar/api/internal/apachecommons/lang/CharRange.access$300:(Lorg/sonar/api/internal/apachecommons/lang/CharRange;)C
     105: if_icmpge     122
     108: aload_0
     109: aload_0
     110: getfield      #41                 // Field current:C
     113: iconst_1
     114: iadd
     115: i2c
     116: putfield      #41                 // Field current:C
     119: goto          127
     122: aload_0
     123: iconst_0
     124: putfield      #27                 // Field hasNext:Z
     127: return

  public boolean hasNext();
    Code:
       0: aload_0
       1: getfield      #27                 // Field hasNext:Z
       4: ireturn

  public java.lang.Object next();
    Code:
       0: aload_0
       1: getfield      #27                 // Field hasNext:Z
       4: ifne          15
       7: new           #50                 // class java/util/NoSuchElementException
      10: dup
      11: invokespecial #51                 // Method java/util/NoSuchElementException."<init>":()V
      14: athrow
      15: aload_0
      16: getfield      #41                 // Field current:C
      19: istore_1
      20: aload_0
      21: invokespecial #53                 // Method prepareNext:()V
      24: new           #55                 // class java/lang/Character
      27: dup
      28: iload_1
      29: invokespecial #58                 // Method java/lang/Character."<init>":(C)V
      32: areturn

  public void remove();
    Code:
       0: new           #62                 // class java/lang/UnsupportedOperationException
       3: dup
       4: invokespecial #63                 // Method java/lang/UnsupportedOperationException."<init>":()V
       7: athrow

  org.sonar.api.internal.apachecommons.lang.CharRange$CharacterIterator(org.sonar.api.internal.apachecommons.lang.CharRange, org.sonar.api.internal.apachecommons.lang.CharRange$1);
    Code:
       0: aload_0
       1: aload_1
       2: invokespecial #66                 // Method "<init>":(Lorg/sonar/api/internal/apachecommons/lang/CharRange;)V
       5: return
}
