Compiled from "TomcatMetrics.java"
class io.micrometer.core.instrument.binder.tomcat.TomcatMetrics$1 implements javax.management.NotificationListener {
  final java.util.function.BiConsumer val$perObject;

  final io.micrometer.core.instrument.binder.tomcat.TomcatMetrics this$0;

  io.micrometer.core.instrument.binder.tomcat.TomcatMetrics$1();
    Code:
       0: aload_0
       1: aload_1
       2: putfield      #1                  // Field this$0:Lio/micrometer/core/instrument/binder/tomcat/TomcatMetrics;
       5: aload_0
       6: aload_2
       7: putfield      #7                  // Field val$perObject:Ljava/util/function/BiConsumer;
      10: aload_0
      11: invokespecial #11                 // Method java/lang/Object."<init>":()V
      14: return

  public void handleNotification(javax.management.Notification, java.lang.Object);
    Code:
       0: aload_1
       1: checkcast     #17                 // class javax/management/MBeanServerNotification
       4: astore_3
       5: aload_3
       6: invokevirtual #19                 // Method javax/management/MBeanServerNotification.getMBeanName:()Ljavax/management/ObjectName;
       9: astore        4
      11: aload_0
      12: getfield      #7                  // Field val$perObject:Ljava/util/function/BiConsumer;
      15: aload         4
      17: aload_0
      18: getfield      #1                  // Field this$0:Lio/micrometer/core/instrument/binder/tomcat/TomcatMetrics;
      21: invokestatic  #23                 // Method io/micrometer/core/instrument/binder/tomcat/TomcatMetrics.access$000:(Lio/micrometer/core/instrument/binder/tomcat/TomcatMetrics;)Ljava/lang/Iterable;
      24: aload_0
      25: getfield      #1                  // Field this$0:Lio/micrometer/core/instrument/binder/tomcat/TomcatMetrics;
      28: aload         4
      30: invokestatic  #29                 // Method io/micrometer/core/instrument/binder/tomcat/TomcatMetrics.access$100:(Lio/micrometer/core/instrument/binder/tomcat/TomcatMetrics;Ljavax/management/ObjectName;)Ljava/lang/Iterable;
      33: invokestatic  #33                 // Method io/micrometer/core/instrument/Tags.concat:(Ljava/lang/Iterable;Ljava/lang/Iterable;)Lio/micrometer/core/instrument/Tags;
      36: invokeinterface #39,  3           // InterfaceMethod java/util/function/BiConsumer.accept:(Ljava/lang/Object;Ljava/lang/Object;)V
      41: aload_0
      42: getfield      #1                  // Field this$0:Lio/micrometer/core/instrument/binder/tomcat/TomcatMetrics;
      45: invokestatic  #45                 // Method io/micrometer/core/instrument/binder/tomcat/TomcatMetrics.access$200:(Lio/micrometer/core/instrument/binder/tomcat/TomcatMetrics;)Ljavax/management/MBeanServer;
      48: getstatic     #49                 // Field javax/management/MBeanServerDelegate.DELEGATE_NAME:Ljavax/management/ObjectName;
      51: aload_0
      52: invokeinterface #55,  3           // InterfaceMethod javax/management/MBeanServer.removeNotificationListener:(Ljavax/management/ObjectName;Ljavax/management/NotificationListener;)V
      57: aload_0
      58: getfield      #1                  // Field this$0:Lio/micrometer/core/instrument/binder/tomcat/TomcatMetrics;
      61: invokestatic  #61                 // Method io/micrometer/core/instrument/binder/tomcat/TomcatMetrics.access$300:(Lio/micrometer/core/instrument/binder/tomcat/TomcatMetrics;)Ljava/util/Set;
      64: aload_0
      65: invokeinterface #65,  2           // InterfaceMethod java/util/Set.remove:(Ljava/lang/Object;)Z
      70: pop
      71: goto          86
      74: astore        5
      76: new           #75                 // class java/lang/RuntimeException
      79: dup
      80: aload         5
      82: invokespecial #77                 // Method java/lang/RuntimeException."<init>":(Ljava/lang/Throwable;)V
      85: athrow
      86: return
    Exception table:
       from    to  target type
          41    71    74   Class javax/management/InstanceNotFoundException
          41    71    74   Class javax/management/ListenerNotFoundException
}
