Compiled from "IOTrio.java"
public class io.kubernetes.client.custom.IOTrio {
  private java.io.InputStream stdout;

  private java.io.InputStream stderr;

  private java.io.OutputStream stdin;

  private final java.util.Collection<java.util.function.BiConsumer<java.lang.Integer, java.lang.Long>> closeHandlers;

  public io.kubernetes.client.custom.IOTrio();
    Code:
       0: aload_0
       1: invokespecial #1                  // Method java/lang/Object."<init>":()V
       4: aload_0
       5: new           #2                  // class java/util/ArrayList
       8: dup
       9: invokespecial #3                  // Method java/util/ArrayList."<init>":()V
      12: putfield      #4                  // Field closeHandlers:Ljava/util/Collection;
      15: return

  public java.io.InputStream getStdout();
    Code:
       0: aload_0
       1: getfield      #5                  // Field stdout:Ljava/io/InputStream;
       4: areturn

  public void setStdout(java.io.InputStream);
    Code:
       0: aload_0
       1: aload_1
       2: putfield      #5                  // Field stdout:Ljava/io/InputStream;
       5: return

  public java.io.InputStream getStderr();
    Code:
       0: aload_0
       1: getfield      #6                  // Field stderr:Ljava/io/InputStream;
       4: areturn

  public void setStderr(java.io.InputStream);
    Code:
       0: aload_0
       1: aload_1
       2: putfield      #6                  // Field stderr:Ljava/io/InputStream;
       5: return

  public java.io.OutputStream getStdin();
    Code:
       0: aload_0
       1: getfield      #7                  // Field stdin:Ljava/io/OutputStream;
       4: areturn

  public void setStdin(java.io.OutputStream);
    Code:
       0: aload_0
       1: aload_1
       2: putfield      #7                  // Field stdin:Ljava/io/OutputStream;
       5: return

  public void onClose(java.util.function.BiConsumer<java.lang.Integer, java.lang.Long>);
    Code:
       0: aload_0
       1: getfield      #4                  // Field closeHandlers:Ljava/util/Collection;
       4: aload_1
       5: invokeinterface #8,  2            // InterfaceMethod java/util/Collection.add:(Ljava/lang/Object;)Z
      10: pop
      11: return

  public void close(int, long);
    Code:
       0: aload_0
       1: getfield      #4                  // Field closeHandlers:Ljava/util/Collection;
       4: iload_1
       5: lload_2
       6: invokedynamic #9,  0              // InvokeDynamic #0:accept:(IJ)Ljava/util/function/Consumer;
      11: invokeinterface #10,  2           // InterfaceMethod java/util/Collection.forEach:(Ljava/util/function/Consumer;)V
      16: return

  private static void lambda$close$0(int, long, java.util.function.BiConsumer);
    Code:
       0: aload_3
       1: iload_0
       2: invokestatic  #11                 // Method java/lang/Integer.valueOf:(I)Ljava/lang/Integer;
       5: lload_1
       6: invokestatic  #12                 // Method java/lang/Long.valueOf:(J)Ljava/lang/Long;
       9: invokeinterface #13,  3           // InterfaceMethod java/util/function/BiConsumer.accept:(Ljava/lang/Object;Ljava/lang/Object;)V
      14: return
}
