Compiled from "JMSBridgeImpl.java"
class org.apache.activemq.artemis.jms.bridge.impl.JMSBridgeImpl$BridgeExceptionListener implements javax.jms.ExceptionListener {
  boolean ha;

  org.apache.activemq.artemis.jms.bridge.impl.JMSBridgeImpl$BridgeFailoverListener failoverListener;

  private final boolean isSource;

  final org.apache.activemq.artemis.jms.bridge.impl.JMSBridgeImpl this$0;

  public org.apache.activemq.artemis.jms.bridge.impl.JMSBridgeImpl$BridgeExceptionListener(org.apache.activemq.artemis.jms.bridge.impl.JMSBridgeImpl, boolean, org.apache.activemq.artemis.jms.bridge.impl.JMSBridgeImpl$BridgeFailoverListener, boolean);
    Code:
       0: aload_0
       1: aload_1
       2: putfield      #1                  // Field this$0:Lorg/apache/activemq/artemis/jms/bridge/impl/JMSBridgeImpl;
       5: aload_0
       6: invokespecial #2                  // Method java/lang/Object."<init>":()V
       9: aload_0
      10: iload_2
      11: putfield      #3                  // Field ha:Z
      14: aload_0
      15: aload_3
      16: putfield      #4                  // Field failoverListener:Lorg/apache/activemq/artemis/jms/bridge/impl/JMSBridgeImpl$BridgeFailoverListener;
      19: aload_0
      20: iload         4
      22: putfield      #5                  // Field isSource:Z
      25: return

  public void onException(javax.jms.JMSException);
    Code:
       0: aload_0
       1: getfield      #1                  // Field this$0:Lorg/apache/activemq/artemis/jms/bridge/impl/JMSBridgeImpl;
       4: invokestatic  #6                  // Method org/apache/activemq/artemis/jms/bridge/impl/JMSBridgeImpl.access$500:(Lorg/apache/activemq/artemis/jms/bridge/impl/JMSBridgeImpl;)Z
       7: ifeq          11
      10: return
      11: getstatic     #7                  // Field org/apache/activemq/artemis/jms/bridge/ActiveMQJMSBridgeLogger.LOGGER:Lorg/apache/activemq/artemis/jms/bridge/ActiveMQJMSBridgeLogger;
      14: aload_1
      15: invokeinterface #8,  2            // InterfaceMethod org/apache/activemq/artemis/jms/bridge/ActiveMQJMSBridgeLogger.bridgeFailure:(Ljava/lang/Exception;)V
      20: aload_0
      21: getfield      #5                  // Field isSource:Z
      24: ifeq          39
      27: aload_0
      28: getfield      #1                  // Field this$0:Lorg/apache/activemq/artemis/jms/bridge/impl/JMSBridgeImpl;
      31: iconst_0
      32: invokestatic  #9                  // Method org/apache/activemq/artemis/jms/bridge/impl/JMSBridgeImpl.access$1702:(Lorg/apache/activemq/artemis/jms/bridge/impl/JMSBridgeImpl;Z)Z
      35: pop
      36: goto          48
      39: aload_0
      40: getfield      #1                  // Field this$0:Lorg/apache/activemq/artemis/jms/bridge/impl/JMSBridgeImpl;
      43: iconst_0
      44: invokestatic  #10                 // Method org/apache/activemq/artemis/jms/bridge/impl/JMSBridgeImpl.access$1802:(Lorg/apache/activemq/artemis/jms/bridge/impl/JMSBridgeImpl;Z)Z
      47: pop
      48: aload_0
      49: getfield      #1                  // Field this$0:Lorg/apache/activemq/artemis/jms/bridge/impl/JMSBridgeImpl;
      52: invokestatic  #11                 // Method org/apache/activemq/artemis/jms/bridge/impl/JMSBridgeImpl.access$600:(Lorg/apache/activemq/artemis/jms/bridge/impl/JMSBridgeImpl;)Ljava/lang/Object;
      55: dup
      56: astore_2
      57: monitorenter
      58: aload_0
      59: getfield      #1                  // Field this$0:Lorg/apache/activemq/artemis/jms/bridge/impl/JMSBridgeImpl;
      62: invokestatic  #6                  // Method org/apache/activemq/artemis/jms/bridge/impl/JMSBridgeImpl.access$500:(Lorg/apache/activemq/artemis/jms/bridge/impl/JMSBridgeImpl;)Z
      65: ifeq          71
      68: aload_2
      69: monitorexit
      70: return
      71: aload_0
      72: getfield      #1                  // Field this$0:Lorg/apache/activemq/artemis/jms/bridge/impl/JMSBridgeImpl;
      75: invokestatic  #12                 // Method org/apache/activemq/artemis/jms/bridge/impl/JMSBridgeImpl.access$800:(Lorg/apache/activemq/artemis/jms/bridge/impl/JMSBridgeImpl;)Z
      78: ifeq          100
      81: invokestatic  #13                 // Method org/apache/activemq/artemis/jms/bridge/impl/JMSBridgeImpl.access$1000:()Z
      84: ifeq          148
      87: getstatic     #7                  // Field org/apache/activemq/artemis/jms/bridge/ActiveMQJMSBridgeLogger.LOGGER:Lorg/apache/activemq/artemis/jms/bridge/ActiveMQJMSBridgeLogger;
      90: ldc           #14                 // String Failure recovery already in progress
      92: invokeinterface #15,  2           // InterfaceMethod org/apache/activemq/artemis/jms/bridge/ActiveMQJMSBridgeLogger.trace:(Ljava/lang/Object;)V
      97: goto          148
     100: iconst_1
     101: istore_3
     102: aload_0
     103: getfield      #3                  // Field ha:Z
     106: ifeq          125
     109: aload_0
     110: getfield      #4                  // Field failoverListener:Lorg/apache/activemq/artemis/jms/bridge/impl/JMSBridgeImpl$BridgeFailoverListener;
     113: invokevirtual #16                 // Method org/apache/activemq/artemis/jms/bridge/impl/JMSBridgeImpl$BridgeFailoverListener.waitForFailover:()Z
     116: ifne          123
     119: iconst_1
     120: goto          124
     123: iconst_0
     124: istore_3
     125: iload_3
     126: ifeq          148
     129: aload_0
     130: getfield      #1                  // Field this$0:Lorg/apache/activemq/artemis/jms/bridge/impl/JMSBridgeImpl;
     133: new           #17                 // class org/apache/activemq/artemis/jms/bridge/impl/JMSBridgeImpl$FailureHandler
     136: dup
     137: aload_0
     138: getfield      #1                  // Field this$0:Lorg/apache/activemq/artemis/jms/bridge/impl/JMSBridgeImpl;
     141: aconst_null
     142: invokespecial #18                 // Method org/apache/activemq/artemis/jms/bridge/impl/JMSBridgeImpl$FailureHandler."<init>":(Lorg/apache/activemq/artemis/jms/bridge/impl/JMSBridgeImpl;Lorg/apache/activemq/artemis/jms/bridge/impl/JMSBridgeImpl$1;)V
     145: invokestatic  #19                 // Method org/apache/activemq/artemis/jms/bridge/impl/JMSBridgeImpl.access$2500:(Lorg/apache/activemq/artemis/jms/bridge/impl/JMSBridgeImpl;Ljava/lang/Runnable;)V
     148: aload_2
     149: monitorexit
     150: goto          160
     153: astore        4
     155: aload_2
     156: monitorexit
     157: aload         4
     159: athrow
     160: return
    Exception table:
       from    to  target type
          58    70   153   any
          71   150   153   any
         153   157   153   any
}
