Compiled from "TransactionTable.java"
class org.infinispan.transaction.impl.TransactionTable$3 implements java.lang.Runnable {
  final org.infinispan.transaction.impl.TransactionTable this$0;

  org.infinispan.transaction.impl.TransactionTable$3(org.infinispan.transaction.impl.TransactionTable);
    Code:
       0: aload_0
       1: aload_1
       2: putfield      #1                  // Field this$0:Lorg/infinispan/transaction/impl/TransactionTable;
       5: aload_0
       6: invokespecial #2                  // Method java/lang/Object."<init>":()V
       9: return

  public void run();
    Code:
       0: aload_0
       1: getfield      #1                  // Field this$0:Lorg/infinispan/transaction/impl/TransactionTable;
       4: invokevirtual #3                  // Method org/infinispan/transaction/impl/TransactionTable.cleanupTimedOutTransactions:()V
       7: return
}
