Compiled from "MongoDocument.scala"
public abstract class net.liftweb.mongodb.MongoDocumentMeta$class {
  public static java.lang.Object create(net.liftweb.mongodb.MongoDocumentMeta, com.mongodb.DBObject);
    Code:
       0: aload_0
       1: checkcast     #8                  // class net/liftweb/mongodb/JsonObjectMeta
       4: getstatic     #14                 // Field net/liftweb/mongodb/JObjectParser$.MODULE$:Lnet/liftweb/mongodb/JObjectParser$;
       7: aload_0
       8: invokeinterface #20,  1           // InterfaceMethod net/liftweb/mongodb/JsonFormats._formats:()Lnet/liftweb/json/Formats;
      13: astore_3
      14: astore_2
      15: aload_2
      16: aload_1
      17: aload_3
      18: invokevirtual #24                 // Method net/liftweb/mongodb/JObjectParser$.net$liftweb$mongodb$JObjectParser$$serialize:(Ljava/lang/Object;Lnet/liftweb/json/Formats;)Lnet/liftweb/json/JsonAST$JValue;
      21: checkcast     #26                 // class net/liftweb/json/JsonAST$JObject
      24: aload_0
      25: invokeinterface #20,  1           // InterfaceMethod net/liftweb/mongodb/JsonFormats._formats:()Lnet/liftweb/json/Formats;
      30: invokevirtual #29                 // Method net/liftweb/mongodb/JsonObjectMeta.create:(Lnet/liftweb/json/JsonAST$JObject;Lnet/liftweb/json/Formats;)Ljava/lang/Object;
      33: areturn

  public static scala.Option find(net.liftweb.mongodb.MongoDocumentMeta, com.mongodb.DBObject);
    Code:
       0: getstatic     #41                 // Field net/liftweb/mongodb/MongoDB$.MODULE$:Lnet/liftweb/mongodb/MongoDB$;
       3: aload_0
       4: invokeinterface #47,  1           // InterfaceMethod net/liftweb/mongodb/MongoMeta.mongoIdentifier:()Lnet/liftweb/mongodb/MongoIdentifier;
       9: aload_0
      10: invokeinterface #51,  1           // InterfaceMethod net/liftweb/mongodb/MongoMeta.collectionName:()Ljava/lang/String;
      15: new           #53                 // class net/liftweb/mongodb/MongoDocumentMeta$$anonfun$find$1
      18: dup
      19: aload_0
      20: aload_1
      21: invokespecial #57                 // Method net/liftweb/mongodb/MongoDocumentMeta$$anonfun$find$1."<init>":(Lnet/liftweb/mongodb/MongoDocumentMeta;Lcom/mongodb/DBObject;)V
      24: invokevirtual #61                 // Method net/liftweb/mongodb/MongoDB$.useCollection:(Lnet/liftweb/mongodb/MongoIdentifier;Ljava/lang/String;Lscala/Function1;)Ljava/lang/Object;
      27: checkcast     #63                 // class scala/Option
      30: areturn

  public static scala.Option find(net.liftweb.mongodb.MongoDocumentMeta, java.lang.String);
    Code:
       0: aload_1
       1: invokestatic  #71                 // Method org/bson/types/ObjectId.isValid:(Ljava/lang/String;)Z
       4: ifeq          33
       7: aload_0
       8: new           #73                 // class com/mongodb/BasicDBObject
      11: dup
      12: ldc           #75                 // String _id
      14: new           #67                 // class org/bson/types/ObjectId
      17: dup
      18: aload_1
      19: invokespecial #78                 // Method org/bson/types/ObjectId."<init>":(Ljava/lang/String;)V
      22: invokespecial #81                 // Method com/mongodb/BasicDBObject."<init>":(Ljava/lang/String;Ljava/lang/Object;)V
      25: invokeinterface #86,  2           // InterfaceMethod net/liftweb/mongodb/MongoDocumentMeta.find:(Lcom/mongodb/DBObject;)Lscala/Option;
      30: goto          49
      33: aload_0
      34: new           #73                 // class com/mongodb/BasicDBObject
      37: dup
      38: ldc           #75                 // String _id
      40: aload_1
      41: invokespecial #81                 // Method com/mongodb/BasicDBObject."<init>":(Ljava/lang/String;Ljava/lang/Object;)V
      44: invokeinterface #86,  2           // InterfaceMethod net/liftweb/mongodb/MongoDocumentMeta.find:(Lcom/mongodb/DBObject;)Lscala/Option;
      49: areturn

  public static scala.Option find(net.liftweb.mongodb.MongoDocumentMeta, org.bson.types.ObjectId);
    Code:
       0: aload_0
       1: new           #73                 // class com/mongodb/BasicDBObject
       4: dup
       5: ldc           #75                 // String _id
       7: aload_1
       8: invokespecial #81                 // Method com/mongodb/BasicDBObject."<init>":(Ljava/lang/String;Ljava/lang/Object;)V
      11: invokeinterface #86,  2           // InterfaceMethod net/liftweb/mongodb/MongoDocumentMeta.find:(Lcom/mongodb/DBObject;)Lscala/Option;
      16: areturn

  public static scala.Option find(net.liftweb.mongodb.MongoDocumentMeta, java.util.UUID);
    Code:
       0: aload_0
       1: new           #73                 // class com/mongodb/BasicDBObject
       4: dup
       5: ldc           #75                 // String _id
       7: aload_1
       8: invokespecial #81                 // Method com/mongodb/BasicDBObject."<init>":(Ljava/lang/String;Ljava/lang/Object;)V
      11: invokeinterface #86,  2           // InterfaceMethod net/liftweb/mongodb/MongoDocumentMeta.find:(Lcom/mongodb/DBObject;)Lscala/Option;
      16: areturn

  public static scala.Option find(net.liftweb.mongodb.MongoDocumentMeta, java.lang.String, java.lang.Object);
    Code:
       0: aload_0
       1: new           #73                 // class com/mongodb/BasicDBObject
       4: dup
       5: aload_1
       6: aload_2
       7: invokespecial #81                 // Method com/mongodb/BasicDBObject."<init>":(Ljava/lang/String;Ljava/lang/Object;)V
      10: invokeinterface #86,  2           // InterfaceMethod net/liftweb/mongodb/MongoDocumentMeta.find:(Lcom/mongodb/DBObject;)Lscala/Option;
      15: areturn

  public static scala.Option find(net.liftweb.mongodb.MongoDocumentMeta, net.liftweb.json.JsonAST$JObject);
    Code:
       0: aload_0
       1: aload_0
       2: invokeinterface #20,  1           // InterfaceMethod net/liftweb/mongodb/JsonFormats._formats:()Lnet/liftweb/json/Formats;
       7: astore_3
       8: getstatic     #104                // Field net/liftweb/mongodb/JObjectParser$Parser$.MODULE$:Lnet/liftweb/mongodb/JObjectParser$Parser$;
      11: astore_2
      12: aload_2
      13: aload_1
      14: invokevirtual #108                // Method net/liftweb/json/JsonAST$JObject.obj:()Lscala/collection/immutable/List;
      17: aload_3
      18: invokevirtual #112                // Method net/liftweb/mongodb/JObjectParser$Parser$.net$liftweb$mongodb$JObjectParser$Parser$$parseObject:(Lscala/collection/immutable/List;Lnet/liftweb/json/Formats;)Lcom/mongodb/BasicDBObject;
      21: invokeinterface #86,  2           // InterfaceMethod net/liftweb/mongodb/MongoDocumentMeta.find:(Lcom/mongodb/DBObject;)Lscala/Option;
      26: areturn

  public static scala.collection.immutable.List findAll(net.liftweb.mongodb.MongoDocumentMeta);
    Code:
       0: getstatic     #41                 // Field net/liftweb/mongodb/MongoDB$.MODULE$:Lnet/liftweb/mongodb/MongoDB$;
       3: aload_0
       4: invokeinterface #47,  1           // InterfaceMethod net/liftweb/mongodb/MongoMeta.mongoIdentifier:()Lnet/liftweb/mongodb/MongoIdentifier;
       9: aload_0
      10: invokeinterface #51,  1           // InterfaceMethod net/liftweb/mongodb/MongoMeta.collectionName:()Ljava/lang/String;
      15: new           #118                // class net/liftweb/mongodb/MongoDocumentMeta$$anonfun$findAll$1
      18: dup
      19: aload_0
      20: invokespecial #121                // Method net/liftweb/mongodb/MongoDocumentMeta$$anonfun$findAll$1."<init>":(Lnet/liftweb/mongodb/MongoDocumentMeta;)V
      23: invokevirtual #61                 // Method net/liftweb/mongodb/MongoDB$.useCollection:(Lnet/liftweb/mongodb/MongoIdentifier;Ljava/lang/String;Lscala/Function1;)Ljava/lang/Object;
      26: checkcast     #123                // class scala/collection/immutable/List
      29: areturn

  public static scala.collection.immutable.List findAll(net.liftweb.mongodb.MongoDocumentMeta, com.mongodb.DBObject, scala.Option, scala.collection.Seq);
    Code:
       0: aload_3
       1: invokeinterface #129,  1          // InterfaceMethod scala/collection/TraversableOnce.toList:()Lscala/collection/immutable/List;
       6: astore        4
       8: getstatic     #41                 // Field net/liftweb/mongodb/MongoDB$.MODULE$:Lnet/liftweb/mongodb/MongoDB$;
      11: aload_0
      12: invokeinterface #47,  1           // InterfaceMethod net/liftweb/mongodb/MongoMeta.mongoIdentifier:()Lnet/liftweb/mongodb/MongoIdentifier;
      17: aload_0
      18: invokeinterface #51,  1           // InterfaceMethod net/liftweb/mongodb/MongoMeta.collectionName:()Ljava/lang/String;
      23: new           #131                // class net/liftweb/mongodb/MongoDocumentMeta$$anonfun$findAll$2
      26: dup
      27: aload_0
      28: aload_1
      29: aload_2
      30: aload         4
      32: invokespecial #134                // Method net/liftweb/mongodb/MongoDocumentMeta$$anonfun$findAll$2."<init>":(Lnet/liftweb/mongodb/MongoDocumentMeta;Lcom/mongodb/DBObject;Lscala/Option;Lscala/collection/immutable/List;)V
      35: invokevirtual #61                 // Method net/liftweb/mongodb/MongoDB$.useCollection:(Lnet/liftweb/mongodb/MongoIdentifier;Ljava/lang/String;Lscala/Function1;)Ljava/lang/Object;
      38: checkcast     #123                // class scala/collection/immutable/List
      41: areturn

  public static scala.collection.immutable.List findAll(net.liftweb.mongodb.MongoDocumentMeta, com.mongodb.DBObject, scala.collection.Seq);
    Code:
       0: aload_0
       1: aload_1
       2: getstatic     #147                // Field scala/None$.MODULE$:Lscala/None$;
       5: aload_2
       6: invokeinterface #150,  4          // InterfaceMethod net/liftweb/mongodb/MongoDocumentMeta.findAll:(Lcom/mongodb/DBObject;Lscala/Option;Lscala/collection/Seq;)Lscala/collection/immutable/List;
      11: areturn

  public static scala.collection.immutable.List findAll(net.liftweb.mongodb.MongoDocumentMeta, com.mongodb.DBObject, com.mongodb.DBObject, scala.collection.Seq);
    Code:
       0: aload_0
       1: aload_1
       2: new           #154                // class scala/Some
       5: dup
       6: aload_2
       7: invokespecial #157                // Method scala/Some."<init>":(Ljava/lang/Object;)V
      10: aload_3
      11: invokeinterface #150,  4          // InterfaceMethod net/liftweb/mongodb/MongoDocumentMeta.findAll:(Lcom/mongodb/DBObject;Lscala/Option;Lscala/collection/Seq;)Lscala/collection/immutable/List;
      16: areturn

  public static scala.collection.immutable.List findAll(net.liftweb.mongodb.MongoDocumentMeta, net.liftweb.json.JsonAST$JObject, scala.collection.Seq);
    Code:
       0: aload_0
       1: aload_0
       2: invokeinterface #20,  1           // InterfaceMethod net/liftweb/mongodb/JsonFormats._formats:()Lnet/liftweb/json/Formats;
       7: astore        4
       9: getstatic     #104                // Field net/liftweb/mongodb/JObjectParser$Parser$.MODULE$:Lnet/liftweb/mongodb/JObjectParser$Parser$;
      12: astore_3
      13: aload_3
      14: aload_1
      15: invokevirtual #108                // Method net/liftweb/json/JsonAST$JObject.obj:()Lscala/collection/immutable/List;
      18: aload         4
      20: invokevirtual #112                // Method net/liftweb/mongodb/JObjectParser$Parser$.net$liftweb$mongodb$JObjectParser$Parser$$parseObject:(Lscala/collection/immutable/List;Lnet/liftweb/json/Formats;)Lcom/mongodb/BasicDBObject;
      23: getstatic     #147                // Field scala/None$.MODULE$:Lscala/None$;
      26: aload_2
      27: invokeinterface #150,  4          // InterfaceMethod net/liftweb/mongodb/MongoDocumentMeta.findAll:(Lcom/mongodb/DBObject;Lscala/Option;Lscala/collection/Seq;)Lscala/collection/immutable/List;
      32: areturn

  public static scala.collection.immutable.List findAll(net.liftweb.mongodb.MongoDocumentMeta, net.liftweb.json.JsonAST$JObject, net.liftweb.json.JsonAST$JObject, scala.collection.Seq);
    Code:
       0: aload_0
       1: aload_0
       2: invokeinterface #20,  1           // InterfaceMethod net/liftweb/mongodb/JsonFormats._formats:()Lnet/liftweb/json/Formats;
       7: astore        5
       9: getstatic     #104                // Field net/liftweb/mongodb/JObjectParser$Parser$.MODULE$:Lnet/liftweb/mongodb/JObjectParser$Parser$;
      12: astore        4
      14: aload         4
      16: aload_1
      17: invokevirtual #108                // Method net/liftweb/json/JsonAST$JObject.obj:()Lscala/collection/immutable/List;
      20: aload         5
      22: invokevirtual #112                // Method net/liftweb/mongodb/JObjectParser$Parser$.net$liftweb$mongodb$JObjectParser$Parser$$parseObject:(Lscala/collection/immutable/List;Lnet/liftweb/json/Formats;)Lcom/mongodb/BasicDBObject;
      25: new           #154                // class scala/Some
      28: dup
      29: aload_0
      30: invokeinterface #20,  1           // InterfaceMethod net/liftweb/mongodb/JsonFormats._formats:()Lnet/liftweb/json/Formats;
      35: astore        7
      37: getstatic     #104                // Field net/liftweb/mongodb/JObjectParser$Parser$.MODULE$:Lnet/liftweb/mongodb/JObjectParser$Parser$;
      40: astore        6
      42: aload         6
      44: aload_2
      45: invokevirtual #108                // Method net/liftweb/json/JsonAST$JObject.obj:()Lscala/collection/immutable/List;
      48: aload         7
      50: invokevirtual #112                // Method net/liftweb/mongodb/JObjectParser$Parser$.net$liftweb$mongodb$JObjectParser$Parser$$parseObject:(Lscala/collection/immutable/List;Lnet/liftweb/json/Formats;)Lcom/mongodb/BasicDBObject;
      53: invokespecial #157                // Method scala/Some."<init>":(Ljava/lang/Object;)V
      56: aload_3
      57: invokeinterface #150,  4          // InterfaceMethod net/liftweb/mongodb/MongoDocumentMeta.findAll:(Lcom/mongodb/DBObject;Lscala/Option;Lscala/collection/Seq;)Lscala/collection/immutable/List;
      62: areturn

  public static scala.collection.immutable.List findAll(net.liftweb.mongodb.MongoDocumentMeta, java.lang.String, java.lang.Object, scala.collection.Seq);
    Code:
       0: aload_0
       1: new           #73                 // class com/mongodb/BasicDBObject
       4: dup
       5: aload_1
       6: aload_2
       7: invokespecial #81                 // Method com/mongodb/BasicDBObject."<init>":(Ljava/lang/String;Ljava/lang/Object;)V
      10: getstatic     #147                // Field scala/None$.MODULE$:Lscala/None$;
      13: aload_3
      14: invokeinterface #150,  4          // InterfaceMethod net/liftweb/mongodb/MongoDocumentMeta.findAll:(Lcom/mongodb/DBObject;Lscala/Option;Lscala/collection/Seq;)Lscala/collection/immutable/List;
      19: areturn

  public static scala.collection.immutable.List findAll(net.liftweb.mongodb.MongoDocumentMeta, java.lang.String, java.lang.Object, net.liftweb.json.JsonAST$JObject, scala.collection.Seq);
    Code:
       0: aload_0
       1: new           #73                 // class com/mongodb/BasicDBObject
       4: dup
       5: aload_1
       6: aload_2
       7: invokespecial #81                 // Method com/mongodb/BasicDBObject."<init>":(Ljava/lang/String;Ljava/lang/Object;)V
      10: new           #154                // class scala/Some
      13: dup
      14: aload_0
      15: invokeinterface #20,  1           // InterfaceMethod net/liftweb/mongodb/JsonFormats._formats:()Lnet/liftweb/json/Formats;
      20: astore        6
      22: getstatic     #104                // Field net/liftweb/mongodb/JObjectParser$Parser$.MODULE$:Lnet/liftweb/mongodb/JObjectParser$Parser$;
      25: astore        5
      27: aload         5
      29: aload_3
      30: invokevirtual #108                // Method net/liftweb/json/JsonAST$JObject.obj:()Lscala/collection/immutable/List;
      33: aload         6
      35: invokevirtual #112                // Method net/liftweb/mongodb/JObjectParser$Parser$.net$liftweb$mongodb$JObjectParser$Parser$$parseObject:(Lscala/collection/immutable/List;Lnet/liftweb/json/Formats;)Lcom/mongodb/BasicDBObject;
      38: invokespecial #157                // Method scala/Some."<init>":(Ljava/lang/Object;)V
      41: aload         4
      43: invokeinterface #150,  4          // InterfaceMethod net/liftweb/mongodb/MongoDocumentMeta.findAll:(Lcom/mongodb/DBObject;Lscala/Option;Lscala/collection/Seq;)Lscala/collection/immutable/List;
      48: areturn

  public static void save(net.liftweb.mongodb.MongoDocumentMeta, java.lang.Object);
    Code:
       0: getstatic     #41                 // Field net/liftweb/mongodb/MongoDB$.MODULE$:Lnet/liftweb/mongodb/MongoDB$;
       3: aload_0
       4: invokeinterface #47,  1           // InterfaceMethod net/liftweb/mongodb/MongoMeta.mongoIdentifier:()Lnet/liftweb/mongodb/MongoIdentifier;
       9: new           #167                // class net/liftweb/mongodb/MongoDocumentMeta$$anonfun$save$1
      12: dup
      13: aload_0
      14: aload_1
      15: invokespecial #169                // Method net/liftweb/mongodb/MongoDocumentMeta$$anonfun$save$1."<init>":(Lnet/liftweb/mongodb/MongoDocumentMeta;Ljava/lang/Object;)V
      18: invokevirtual #173                // Method net/liftweb/mongodb/MongoDB$.use:(Lnet/liftweb/mongodb/MongoIdentifier;Lscala/Function1;)Ljava/lang/Object;
      21: pop
      22: return

  public static void save(net.liftweb.mongodb.MongoDocumentMeta, java.lang.Object, com.mongodb.DB);
    Code:
       0: aload_2
       1: aload_0
       2: invokeinterface #51,  1           // InterfaceMethod net/liftweb/mongodb/MongoMeta.collectionName:()Ljava/lang/String;
       7: invokevirtual #181                // Method com/mongodb/DB.getCollection:(Ljava/lang/String;)Lcom/mongodb/DBCollection;
      10: aload_0
      11: checkcast     #8                  // class net/liftweb/mongodb/JsonObjectMeta
      14: aload_1
      15: aload_0
      16: invokeinterface #20,  1           // InterfaceMethod net/liftweb/mongodb/JsonFormats._formats:()Lnet/liftweb/json/Formats;
      21: invokevirtual #185                // Method net/liftweb/mongodb/JsonObjectMeta.toJObject:(Ljava/lang/Object;Lnet/liftweb/json/Formats;)Lnet/liftweb/json/JsonAST$JObject;
      24: aload_0
      25: invokeinterface #20,  1           // InterfaceMethod net/liftweb/mongodb/JsonFormats._formats:()Lnet/liftweb/json/Formats;
      30: astore        5
      32: astore        4
      34: getstatic     #104                // Field net/liftweb/mongodb/JObjectParser$Parser$.MODULE$:Lnet/liftweb/mongodb/JObjectParser$Parser$;
      37: astore_3
      38: aload_3
      39: aload         4
      41: invokevirtual #108                // Method net/liftweb/json/JsonAST$JObject.obj:()Lscala/collection/immutable/List;
      44: aload         5
      46: invokevirtual #112                // Method net/liftweb/mongodb/JObjectParser$Parser$.net$liftweb$mongodb$JObjectParser$Parser$$parseObject:(Lscala/collection/immutable/List;Lnet/liftweb/json/Formats;)Lcom/mongodb/BasicDBObject;
      49: invokevirtual #190                // Method com/mongodb/DBCollection.save:(Lcom/mongodb/DBObject;)Lcom/mongodb/WriteResult;
      52: pop
      53: return

  public static void update(net.liftweb.mongodb.MongoDocumentMeta, net.liftweb.json.JsonAST$JObject, java.lang.Object, com.mongodb.DB, scala.collection.Seq);
    Code:
       0: aload_0
       1: aload_1
       2: aload_0
       3: checkcast     #8                  // class net/liftweb/mongodb/JsonObjectMeta
       6: aload_2
       7: aload_0
       8: invokeinterface #20,  1           // InterfaceMethod net/liftweb/mongodb/JsonFormats._formats:()Lnet/liftweb/json/Formats;
      13: invokevirtual #185                // Method net/liftweb/mongodb/JsonObjectMeta.toJObject:(Ljava/lang/Object;Lnet/liftweb/json/Formats;)Lnet/liftweb/json/JsonAST$JObject;
      16: aload_3
      17: aload         4
      19: invokeinterface #198,  5          // InterfaceMethod net/liftweb/mongodb/MongoMeta.update:(Lnet/liftweb/json/JsonAST$JObject;Lnet/liftweb/json/JsonAST$JObject;Lcom/mongodb/DB;Lscala/collection/Seq;)V
      24: return

  public static void update(net.liftweb.mongodb.MongoDocumentMeta, net.liftweb.json.JsonAST$JObject, java.lang.Object, scala.collection.Seq);
    Code:
       0: getstatic     #41                 // Field net/liftweb/mongodb/MongoDB$.MODULE$:Lnet/liftweb/mongodb/MongoDB$;
       3: aload_0
       4: invokeinterface #47,  1           // InterfaceMethod net/liftweb/mongodb/MongoMeta.mongoIdentifier:()Lnet/liftweb/mongodb/MongoIdentifier;
       9: new           #202                // class net/liftweb/mongodb/MongoDocumentMeta$$anonfun$update$1
      12: dup
      13: aload_0
      14: aload_1
      15: aload_2
      16: aload_3
      17: invokespecial #204                // Method net/liftweb/mongodb/MongoDocumentMeta$$anonfun$update$1."<init>":(Lnet/liftweb/mongodb/MongoDocumentMeta;Lnet/liftweb/json/JsonAST$JObject;Ljava/lang/Object;Lscala/collection/Seq;)V
      20: invokevirtual #173                // Method net/liftweb/mongodb/MongoDB$.use:(Lnet/liftweb/mongodb/MongoIdentifier;Lscala/Function1;)Ljava/lang/Object;
      23: pop
      24: return

  public static void $init$(net.liftweb.mongodb.MongoDocumentMeta);
    Code:
       0: return
}
