Compiled from "ORBBase.java"
public class com.arjuna.orbportability.internal.orbspecific.orb.implementations.ORBBase implements com.arjuna.orbportability.orb.core.ORBImple {
  protected org.omg.CORBA.ORB _orb;

  protected boolean _init;

  public synchronized boolean initialised();
    Code:
       0: aload_0
       1: getfield      #1                  // Field _init:Z
       4: ireturn

  public synchronized void init() throws org.omg.CORBA.SystemException;
    Code:
       0: aload_0
       1: getfield      #1                  // Field _init:Z
       4: ifne          19
       7: aload_0
       8: invokestatic  #2                  // Method org/omg/CORBA/ORB.init:()Lorg/omg/CORBA/ORB;
      11: putfield      #3                  // Field _orb:Lorg/omg/CORBA/ORB;
      14: aload_0
      15: iconst_1
      16: putfield      #1                  // Field _init:Z
      19: return

  public synchronized void init(java.applet.Applet, java.util.Properties) throws org.omg.CORBA.SystemException;
    Code:
       0: aload_0
       1: getfield      #1                  // Field _init:Z
       4: ifne          21
       7: aload_0
       8: aload_1
       9: aload_2
      10: invokestatic  #4                  // Method org/omg/CORBA/ORB.init:(Ljava/applet/Applet;Ljava/util/Properties;)Lorg/omg/CORBA/ORB;
      13: putfield      #3                  // Field _orb:Lorg/omg/CORBA/ORB;
      16: aload_0
      17: iconst_1
      18: putfield      #1                  // Field _init:Z
      21: return

  public synchronized void init(java.lang.String[], java.util.Properties) throws org.omg.CORBA.SystemException;
    Code:
       0: aload_0
       1: getfield      #1                  // Field _init:Z
       4: ifne          21
       7: aload_0
       8: aload_1
       9: aload_2
      10: invokestatic  #5                  // Method org/omg/CORBA/ORB.init:([Ljava/lang/String;Ljava/util/Properties;)Lorg/omg/CORBA/ORB;
      13: putfield      #3                  // Field _orb:Lorg/omg/CORBA/ORB;
      16: aload_0
      17: iconst_1
      18: putfield      #1                  // Field _init:Z
      21: return

  public synchronized void shutdown() throws org.omg.CORBA.SystemException;
    Code:
       0: aload_0
       1: iconst_0
       2: invokevirtual #6                  // Method shutdown:(Z)V
       5: return

  public synchronized void shutdown(boolean) throws org.omg.CORBA.SystemException;
    Code:
       0: aload_0
       1: getfield      #1                  // Field _init:Z
       4: ifeq          36
       7: ldc           #7                  // class com/arjuna/orbportability/common/OrbPortabilityEnvironmentBean
       9: invokestatic  #8                  // Method com/arjuna/common/internal/util/propertyservice/BeanPopulator.getDefaultInstance:(Ljava/lang/Class;)Ljava/lang/Object;
      12: checkcast     #7                  // class com/arjuna/orbportability/common/OrbPortabilityEnvironmentBean
      15: astore_2
      16: aload_2
      17: invokevirtual #9                  // Method com/arjuna/orbportability/common/OrbPortabilityEnvironmentBean.isShutdownWrappedOrb:()Z
      20: ifeq          36
      23: aload_0
      24: getfield      #3                  // Field _orb:Lorg/omg/CORBA/ORB;
      27: iload_1
      28: invokevirtual #10                 // Method org/omg/CORBA/ORB.shutdown:(Z)V
      31: aload_0
      32: iconst_0
      33: putfield      #1                  // Field _init:Z
      36: return

  public synchronized void destroy() throws org.omg.CORBA.SystemException;
    Code:
       0: aload_0
       1: invokevirtual #11                 // Method shutdown:()V
       4: return

  public synchronized org.omg.CORBA.ORB orb() throws org.omg.CORBA.SystemException;
    Code:
       0: aload_0
       1: getfield      #3                  // Field _orb:Lorg/omg/CORBA/ORB;
       4: areturn

  public synchronized void orb(org.omg.CORBA.ORB) throws org.omg.CORBA.SystemException;
    Code:
       0: aload_0
       1: aload_1
       2: putfield      #3                  // Field _orb:Lorg/omg/CORBA/ORB;
       5: aload_0
       6: iconst_1
       7: putfield      #1                  // Field _init:Z
      10: return

  protected com.arjuna.orbportability.internal.orbspecific.orb.implementations.ORBBase();
    Code:
       0: aload_0
       1: invokespecial #12                 // Method java/lang/Object."<init>":()V
       4: aload_0
       5: aconst_null
       6: putfield      #3                  // Field _orb:Lorg/omg/CORBA/ORB;
       9: aload_0
      10: iconst_0
      11: putfield      #1                  // Field _init:Z
      14: return
}
