Compiled from "JavaSecuredFile.java"
public class jnr.posix.JavaSecuredFile extends java.io.File {
  public jnr.posix.JavaSecuredFile(java.lang.String);
    Code:
       0: aload_0
       1: aload_1
       2: invokespecial #1                  // Method java/io/File."<init>":(Ljava/lang/String;)V
       5: return

  public jnr.posix.JavaSecuredFile(java.lang.String, java.lang.String);
    Code:
       0: aload_0
       1: aload_1
       2: aload_2
       3: invokespecial #2                  // Method java/io/File."<init>":(Ljava/lang/String;Ljava/lang/String;)V
       6: return

  public jnr.posix.JavaSecuredFile(java.io.File, java.lang.String);
    Code:
       0: aload_0
       1: aload_1
       2: aload_2
       3: invokespecial #3                  // Method java/io/File."<init>":(Ljava/io/File;Ljava/lang/String;)V
       6: return

  public jnr.posix.JavaSecuredFile(java.net.URI);
    Code:
       0: aload_0
       1: aload_1
       2: invokespecial #4                  // Method java/io/File."<init>":(Ljava/net/URI;)V
       5: return

  public java.io.File getParentFile();
    Code:
       0: aload_0
       1: invokevirtual #5                  // Method getParent:()Ljava/lang/String;
       4: astore_1
       5: aload_1
       6: ifnonnull     13
       9: aconst_null
      10: goto          21
      13: new           #6                  // class jnr/posix/JavaSecuredFile
      16: dup
      17: aload_1
      18: invokespecial #7                  // Method "<init>":(Ljava/lang/String;)V
      21: areturn

  public java.io.File getAbsoluteFile();
    Code:
       0: aload_0
       1: invokevirtual #8                  // Method getAbsolutePath:()Ljava/lang/String;
       4: astore_1
       5: aload_1
       6: ifnonnull     13
       9: aconst_null
      10: goto          21
      13: new           #6                  // class jnr/posix/JavaSecuredFile
      16: dup
      17: aload_1
      18: invokespecial #7                  // Method "<init>":(Ljava/lang/String;)V
      21: areturn

  public java.io.File getCanonicalFile() throws java.io.IOException;
    Code:
       0: aload_0
       1: invokevirtual #9                  // Method getCanonicalPath:()Ljava/lang/String;
       4: astore_1
       5: aload_1
       6: ifnonnull     13
       9: aconst_null
      10: goto          21
      13: new           #6                  // class jnr/posix/JavaSecuredFile
      16: dup
      17: aload_1
      18: invokespecial #7                  // Method "<init>":(Ljava/lang/String;)V
      21: areturn

  public boolean canRead();
    Code:
       0: aload_0
       1: invokespecial #10                 // Method java/io/File.canRead:()Z
       4: ireturn
       5: astore_1
       6: iconst_0
       7: ireturn
    Exception table:
       from    to  target type
           0     4     5   Class java/lang/SecurityException

  public boolean canWrite();
    Code:
       0: aload_0
       1: invokespecial #12                 // Method java/io/File.canWrite:()Z
       4: ireturn
       5: astore_1
       6: iconst_0
       7: ireturn
    Exception table:
       from    to  target type
           0     4     5   Class java/lang/SecurityException

  public boolean exists();
    Code:
       0: aload_0
       1: invokespecial #13                 // Method java/io/File.exists:()Z
       4: ireturn
       5: astore_1
       6: iconst_0
       7: ireturn
    Exception table:
       from    to  target type
           0     4     5   Class java/lang/SecurityException

  public boolean isDirectory();
    Code:
       0: aload_0
       1: invokespecial #14                 // Method java/io/File.isDirectory:()Z
       4: ireturn
       5: astore_1
       6: iconst_0
       7: ireturn
    Exception table:
       from    to  target type
           0     4     5   Class java/lang/SecurityException

  public boolean isFile();
    Code:
       0: aload_0
       1: invokespecial #15                 // Method java/io/File.isFile:()Z
       4: ireturn
       5: astore_1
       6: iconst_0
       7: ireturn
    Exception table:
       from    to  target type
           0     4     5   Class java/lang/SecurityException

  public boolean isHidden();
    Code:
       0: aload_0
       1: invokespecial #16                 // Method java/io/File.isHidden:()Z
       4: ireturn
       5: astore_1
       6: iconst_0
       7: ireturn
    Exception table:
       from    to  target type
           0     4     5   Class java/lang/SecurityException

  public boolean delete();
    Code:
       0: aload_0
       1: invokespecial #17                 // Method java/io/File.delete:()Z
       4: ireturn
       5: astore_1
       6: iconst_0
       7: ireturn
    Exception table:
       from    to  target type
           0     4     5   Class java/lang/SecurityException

  public boolean mkdir();
    Code:
       0: aload_0
       1: invokespecial #18                 // Method java/io/File.mkdir:()Z
       4: ireturn
       5: astore_1
       6: iconst_0
       7: ireturn
    Exception table:
       from    to  target type
           0     4     5   Class java/lang/SecurityException

  public boolean mkdirs();
    Code:
       0: aload_0
       1: invokespecial #19                 // Method java/io/File.mkdirs:()Z
       4: ireturn
       5: astore_1
       6: iconst_0
       7: ireturn
    Exception table:
       from    to  target type
           0     4     5   Class java/lang/SecurityException

  public boolean renameTo(java.io.File);
    Code:
       0: aload_0
       1: aload_1
       2: invokespecial #20                 // Method java/io/File.renameTo:(Ljava/io/File;)Z
       5: ireturn
       6: astore_2
       7: iconst_0
       8: ireturn
    Exception table:
       from    to  target type
           0     5     6   Class java/lang/SecurityException

  public boolean setLastModified(long);
    Code:
       0: aload_0
       1: lload_1
       2: invokespecial #21                 // Method java/io/File.setLastModified:(J)Z
       5: ireturn
       6: astore_3
       7: iconst_0
       8: ireturn
    Exception table:
       from    to  target type
           0     5     6   Class java/lang/SecurityException

  public boolean setReadOnly();
    Code:
       0: aload_0
       1: invokespecial #22                 // Method java/io/File.setReadOnly:()Z
       4: ireturn
       5: astore_1
       6: iconst_0
       7: ireturn
    Exception table:
       from    to  target type
           0     4     5   Class java/lang/SecurityException

  public java.lang.String getCanonicalPath() throws java.io.IOException;
    Code:
       0: aload_0
       1: invokespecial #23                 // Method java/io/File.getCanonicalPath:()Ljava/lang/String;
       4: areturn
       5: astore_1
       6: new           #24                 // class java/io/IOException
       9: dup
      10: aload_1
      11: invokespecial #25                 // Method java/io/IOException."<init>":(Ljava/lang/Throwable;)V
      14: athrow
    Exception table:
       from    to  target type
           0     4     5   Class java/lang/SecurityException

  public boolean createNewFile() throws java.io.IOException;
    Code:
       0: aload_0
       1: invokespecial #26                 // Method java/io/File.createNewFile:()Z
       4: ireturn
       5: astore_1
       6: new           #24                 // class java/io/IOException
       9: dup
      10: aload_1
      11: invokespecial #25                 // Method java/io/IOException."<init>":(Ljava/lang/Throwable;)V
      14: athrow
    Exception table:
       from    to  target type
           0     4     5   Class java/lang/SecurityException

  public java.lang.String[] list();
    Code:
       0: aload_0
       1: invokespecial #27                 // Method java/io/File.list:()[Ljava/lang/String;
       4: areturn
       5: astore_1
       6: aconst_null
       7: areturn
    Exception table:
       from    to  target type
           0     4     5   Class java/lang/SecurityException

  public java.lang.String[] list(java.io.FilenameFilter);
    Code:
       0: aload_0
       1: aload_1
       2: invokespecial #28                 // Method java/io/File.list:(Ljava/io/FilenameFilter;)[Ljava/lang/String;
       5: areturn
       6: astore_2
       7: aconst_null
       8: areturn
    Exception table:
       from    to  target type
           0     5     6   Class java/lang/SecurityException

  public java.io.File[] listFiles();
    Code:
       0: aload_0
       1: invokespecial #29                 // Method java/io/File.listFiles:()[Ljava/io/File;
       4: areturn
       5: astore_1
       6: aconst_null
       7: areturn
    Exception table:
       from    to  target type
           0     4     5   Class java/lang/SecurityException

  public java.io.File[] listFiles(java.io.FileFilter);
    Code:
       0: aload_0
       1: aload_1
       2: invokespecial #30                 // Method java/io/File.listFiles:(Ljava/io/FileFilter;)[Ljava/io/File;
       5: areturn
       6: astore_2
       7: aconst_null
       8: areturn
    Exception table:
       from    to  target type
           0     5     6   Class java/lang/SecurityException

  public long lastModified();
    Code:
       0: aload_0
       1: invokespecial #31                 // Method java/io/File.lastModified:()J
       4: lreturn
       5: astore_1
       6: lconst_0
       7: lreturn
    Exception table:
       from    to  target type
           0     4     5   Class java/lang/SecurityException

  public long length();
    Code:
       0: aload_0
       1: invokespecial #32                 // Method java/io/File.length:()J
       4: lreturn
       5: astore_1
       6: lconst_0
       7: lreturn
    Exception table:
       from    to  target type
           0     4     5   Class java/lang/SecurityException
}
