Compiled from "MacOSSocketMacros.java"
public class jnr.posix.MacOSSocketMacros implements jnr.posix.SocketMacros {
  public static final jnr.posix.SocketMacros INSTANCE;

  public jnr.posix.MacOSSocketMacros();
    Code:
       0: aload_0
       1: invokespecial #1                  // Method java/lang/Object."<init>":()V
       4: return

  public int __DARWIN_ALIGN32(int);
    Code:
       0: iload_1
       1: iconst_3
       2: iadd
       3: bipush        -4
       5: iand
       6: ireturn

  public int CMSG_SPACE(int);
    Code:
       0: aload_0
       1: getstatic     #2                  // Field jnr/posix/MacOSCmsgHdr.layout:Ljnr/posix/MacOSCmsgHdr$Layout;
       4: invokevirtual #3                  // Method jnr/posix/MacOSCmsgHdr$Layout.size:()I
       7: invokevirtual #4                  // Method __DARWIN_ALIGN32:(I)I
      10: aload_0
      11: iload_1
      12: invokevirtual #4                  // Method __DARWIN_ALIGN32:(I)I
      15: iadd
      16: ireturn

  public int CMSG_LEN(int);
    Code:
       0: aload_0
       1: getstatic     #2                  // Field jnr/posix/MacOSCmsgHdr.layout:Ljnr/posix/MacOSCmsgHdr$Layout;
       4: invokevirtual #3                  // Method jnr/posix/MacOSCmsgHdr$Layout.size:()I
       7: invokevirtual #4                  // Method __DARWIN_ALIGN32:(I)I
      10: iload_1
      11: iadd
      12: ireturn

  public jnr.ffi.Pointer CMSG_DATA(jnr.ffi.Pointer);
    Code:
       0: aload_1
       1: aload_0
       2: getstatic     #2                  // Field jnr/posix/MacOSCmsgHdr.layout:Ljnr/posix/MacOSCmsgHdr$Layout;
       5: invokevirtual #3                  // Method jnr/posix/MacOSCmsgHdr$Layout.size:()I
       8: invokevirtual #4                  // Method __DARWIN_ALIGN32:(I)I
      11: i2l
      12: invokevirtual #5                  // Method jnr/ffi/Pointer.slice:(J)Ljnr/ffi/Pointer;
      15: areturn

  static {};
    Code:
       0: new           #6                  // class jnr/posix/MacOSSocketMacros
       3: dup
       4: invokespecial #7                  // Method "<init>":()V
       7: putstatic     #8                  // Field INSTANCE:Ljnr/posix/SocketMacros;
      10: return
}
