Compiled from "ResultType.java"
public class jnr.ffi.provider.ResultType extends jnr.ffi.provider.FromNativeType {
  public jnr.ffi.provider.ResultType(java.lang.Class, jnr.ffi.NativeType, java.util.Collection<java.lang.annotation.Annotation>, jnr.ffi.mapper.FromNativeConverter, jnr.ffi.mapper.FromNativeContext);
    Code:
       0: aload_0
       1: aload_1
       2: aload_2
       3: aload_3
       4: aload         4
       6: aload         5
       8: invokespecial #1                  // Method jnr/ffi/provider/FromNativeType."<init>":(Ljava/lang/Class;Ljnr/ffi/NativeType;Ljava/util/Collection;Ljnr/ffi/mapper/FromNativeConverter;Ljnr/ffi/mapper/FromNativeContext;)V
      11: return
}
