Compiled from "MappingTests.java"
public class org.jresearch.commons.gwt.client.model.ref.MappingTests {
  protected static final java.util.Random rnd;

  public org.jresearch.commons.gwt.client.model.ref.MappingTests();
    Code:
       0: aload_0
       1: invokespecial #1                  // Method java/lang/Object."<init>":()V
       4: return

  public static <S extends java.lang.Enum<S>, G extends java.lang.Enum<G>> void checkEnums(java.lang.Class<S>, java.lang.Class<G>);
    Code:
       0: aload_0
       1: invokestatic  #2                  // Method java/util/EnumSet.allOf:(Ljava/lang/Class;)Ljava/util/EnumSet;
       4: astore_2
       5: aload_2
       6: invokevirtual #3                  // Method java/util/EnumSet.size:()I
       9: i2l
      10: aload_1
      11: invokestatic  #2                  // Method java/util/EnumSet.allOf:(Ljava/lang/Class;)Ljava/util/EnumSet;
      14: invokevirtual #3                  // Method java/util/EnumSet.size:()I
      17: i2l
      18: invokestatic  #4                  // Method org/junit/Assert.assertEquals:(JJ)V
      21: aload_2
      22: invokevirtual #5                  // Method java/util/EnumSet.iterator:()Ljava/util/Iterator;
      25: astore_3
      26: aload_3
      27: invokeinterface #6,  1            // InterfaceMethod java/util/Iterator.hasNext:()Z
      32: ifeq          61
      35: aload_3
      36: invokeinterface #7,  1            // InterfaceMethod java/util/Iterator.next:()Ljava/lang/Object;
      41: checkcast     #8                  // class java/lang/Enum
      44: astore        4
      46: aload_1
      47: aload         4
      49: invokevirtual #9                  // Method java/lang/Enum.name:()Ljava/lang/String;
      52: invokestatic  #10                 // Method java/lang/Enum.valueOf:(Ljava/lang/Class;Ljava/lang/String;)Ljava/lang/Enum;
      55: invokestatic  #11                 // Method org/junit/Assert.assertNotNull:(Ljava/lang/Object;)V
      58: goto          26
      61: return

  public static void checkDomainAttributes(java.util.Collection<org.jresearch.commons.base.ref.manager.api.obj.AttributeValueDto>, java.util.Collection<org.jresearch.commons.base.ref.manager.api.obj.AttributeValueDto>);
    Code:
       0: aload_0
       1: invokeinterface #12,  1           // InterfaceMethod java/util/Collection.size:()I
       6: i2l
       7: aload_1
       8: invokeinterface #12,  1           // InterfaceMethod java/util/Collection.size:()I
      13: i2l
      14: invokestatic  #4                  // Method org/junit/Assert.assertEquals:(JJ)V
      17: aload_0
      18: invokeinterface #13,  1           // InterfaceMethod java/util/Collection.iterator:()Ljava/util/Iterator;
      23: astore_2
      24: aload_2
      25: invokeinterface #6,  1            // InterfaceMethod java/util/Iterator.hasNext:()Z
      30: ifeq          56
      33: aload_2
      34: invokeinterface #7,  1            // InterfaceMethod java/util/Iterator.next:()Ljava/lang/Object;
      39: checkcast     #14                 // class org/jresearch/commons/base/ref/manager/api/obj/AttributeValueDto
      42: astore_3
      43: aload_1
      44: aload_3
      45: invokeinterface #15,  2           // InterfaceMethod java/util/Collection.contains:(Ljava/lang/Object;)Z
      50: invokestatic  #16                 // Method org/junit/Assert.assertTrue:(Z)V
      53: goto          24
      56: return

  public static void checktBusinessTypes(java.util.Set<org.jresearch.commons.base.ref.manager.api.obj.IBusinessType>, java.util.Set<org.jresearch.commons.base.ref.manager.api.obj.IBusinessType>);
    Code:
       0: aload_0
       1: invokeinterface #17,  1           // InterfaceMethod java/util/Set.size:()I
       6: i2l
       7: aload_1
       8: invokeinterface #17,  1           // InterfaceMethod java/util/Set.size:()I
      13: i2l
      14: invokestatic  #4                  // Method org/junit/Assert.assertEquals:(JJ)V
      17: aload_0
      18: invokeinterface #18,  1           // InterfaceMethod java/util/Set.iterator:()Ljava/util/Iterator;
      23: astore_2
      24: aload_2
      25: invokeinterface #6,  1            // InterfaceMethod java/util/Iterator.hasNext:()Z
      30: ifeq          56
      33: aload_2
      34: invokeinterface #7,  1            // InterfaceMethod java/util/Iterator.next:()Ljava/lang/Object;
      39: checkcast     #19                 // class org/jresearch/commons/base/ref/manager/api/obj/IBusinessType
      42: astore_3
      43: aload_1
      44: aload_3
      45: invokeinterface #20,  2           // InterfaceMethod java/util/Set.contains:(Ljava/lang/Object;)Z
      50: invokestatic  #16                 // Method org/junit/Assert.assertTrue:(Z)V
      53: goto          24
      56: return

  public static void checkLocalizedText(java.util.Collection<org.jresearch.commons.base.localiztion.manager.api.obj.ILocalizedText>, java.util.Collection<org.jresearch.commons.base.localiztion.manager.api.obj.ILocalizedText>);
    Code:
       0: aload_0
       1: invokeinterface #12,  1           // InterfaceMethod java/util/Collection.size:()I
       6: i2l
       7: aload_1
       8: invokeinterface #12,  1           // InterfaceMethod java/util/Collection.size:()I
      13: i2l
      14: invokestatic  #4                  // Method org/junit/Assert.assertEquals:(JJ)V
      17: aload_0
      18: invokeinterface #13,  1           // InterfaceMethod java/util/Collection.iterator:()Ljava/util/Iterator;
      23: astore_2
      24: aload_2
      25: invokeinterface #6,  1            // InterfaceMethod java/util/Iterator.hasNext:()Z
      30: ifeq          56
      33: aload_2
      34: invokeinterface #7,  1            // InterfaceMethod java/util/Iterator.next:()Ljava/lang/Object;
      39: checkcast     #21                 // class org/jresearch/commons/base/localiztion/manager/api/obj/ILocalizedText
      42: astore_3
      43: aload_1
      44: aload_3
      45: invokeinterface #15,  2           // InterfaceMethod java/util/Collection.contains:(Ljava/lang/Object;)Z
      50: invokestatic  #16                 // Method org/junit/Assert.assertTrue:(Z)V
      53: goto          24
      56: return

  public static void check(org.jresearch.commons.base.ref.manager.api.obj.IBusinessType, org.jresearch.commons.base.ref.manager.api.obj.IBusinessType);
    Code:
       0: aload_0
       1: ifnonnull     9
       4: aload_1
       5: ifnonnull     9
       8: return
       9: aload_0
      10: ifnull        17
      13: aload_1
      14: ifnonnull     22
      17: iconst_0
      18: invokestatic  #16                 // Method org/junit/Assert.assertTrue:(Z)V
      21: return
      22: aload_0
      23: invokeinterface #22,  1           // InterfaceMethod org/jresearch/commons/base/ref/manager/api/obj/IBusinessType.getDescriptions:()Ljava/util/Collection;
      28: aload_1
      29: invokeinterface #23,  1           // InterfaceMethod org/jresearch/commons/base/ref/manager/api/obj/IBusinessType.getNames:()Ljava/util/Collection;
      34: invokestatic  #24                 // Method checkLocalizedText:(Ljava/util/Collection;Ljava/util/Collection;)V
      37: aload_0
      38: invokeinterface #25,  1           // InterfaceMethod org/jresearch/commons/base/ref/manager/api/obj/IBusinessType.getId:()Ljava/lang/Long;
      43: aload_1
      44: invokeinterface #25,  1           // InterfaceMethod org/jresearch/commons/base/ref/manager/api/obj/IBusinessType.getId:()Ljava/lang/Long;
      49: invokestatic  #26                 // Method org/junit/Assert.assertEquals:(Ljava/lang/Object;Ljava/lang/Object;)V
      52: aload_0
      53: invokeinterface #27,  1           // InterfaceMethod org/jresearch/commons/base/ref/manager/api/obj/IBusinessType.getMaxValue:()Ljava/lang/Long;
      58: aload_1
      59: invokeinterface #27,  1           // InterfaceMethod org/jresearch/commons/base/ref/manager/api/obj/IBusinessType.getMaxValue:()Ljava/lang/Long;
      64: invokestatic  #26                 // Method org/junit/Assert.assertEquals:(Ljava/lang/Object;Ljava/lang/Object;)V
      67: aload_0
      68: invokeinterface #28,  1           // InterfaceMethod org/jresearch/commons/base/ref/manager/api/obj/IBusinessType.getMinValue:()Ljava/lang/Long;
      73: aload_1
      74: invokeinterface #28,  1           // InterfaceMethod org/jresearch/commons/base/ref/manager/api/obj/IBusinessType.getMinValue:()Ljava/lang/Long;
      79: invokestatic  #26                 // Method org/junit/Assert.assertEquals:(Ljava/lang/Object;Ljava/lang/Object;)V
      82: aload_0
      83: invokeinterface #29,  1           // InterfaceMethod org/jresearch/commons/base/ref/manager/api/obj/IBusinessType.getRegularExpression:()Ljava/lang/String;
      88: aload_1
      89: invokeinterface #29,  1           // InterfaceMethod org/jresearch/commons/base/ref/manager/api/obj/IBusinessType.getRegularExpression:()Ljava/lang/String;
      94: invokestatic  #26                 // Method org/junit/Assert.assertEquals:(Ljava/lang/Object;Ljava/lang/Object;)V
      97: aload_0
      98: invokeinterface #30,  1           // InterfaceMethod org/jresearch/commons/base/ref/manager/api/obj/IBusinessType.getValidValues:()Ljava/util/List;
     103: aload_1
     104: invokeinterface #30,  1           // InterfaceMethod org/jresearch/commons/base/ref/manager/api/obj/IBusinessType.getValidValues:()Ljava/util/List;
     109: invokestatic  #31                 // Method checkValidValues:(Ljava/util/List;Ljava/util/List;)V
     112: aload_0
     113: invokeinterface #32,  1           // InterfaceMethod org/jresearch/commons/base/ref/manager/api/obj/IBusinessType.getCode:()Ljava/lang/String;
     118: aload_1
     119: invokeinterface #32,  1           // InterfaceMethod org/jresearch/commons/base/ref/manager/api/obj/IBusinessType.getCode:()Ljava/lang/String;
     124: invokestatic  #26                 // Method org/junit/Assert.assertEquals:(Ljava/lang/Object;Ljava/lang/Object;)V
     127: aload_0
     128: invokeinterface #23,  1           // InterfaceMethod org/jresearch/commons/base/ref/manager/api/obj/IBusinessType.getNames:()Ljava/util/Collection;
     133: aload_1
     134: invokeinterface #23,  1           // InterfaceMethod org/jresearch/commons/base/ref/manager/api/obj/IBusinessType.getNames:()Ljava/util/Collection;
     139: invokestatic  #24                 // Method checkLocalizedText:(Ljava/util/Collection;Ljava/util/Collection;)V
     142: return

  public static void checkValidValues(java.util.List<org.jresearch.commons.base.ref.manager.api.obj.RefAttributeValueDto>, java.util.List<org.jresearch.commons.base.ref.manager.api.obj.RefAttributeValueDto>);
    Code:
       0: aload_0
       1: invokeinterface #33,  1           // InterfaceMethod java/util/List.size:()I
       6: i2l
       7: aload_1
       8: invokeinterface #33,  1           // InterfaceMethod java/util/List.size:()I
      13: i2l
      14: invokestatic  #4                  // Method org/junit/Assert.assertEquals:(JJ)V
      17: aload_0
      18: invokeinterface #34,  1           // InterfaceMethod java/util/List.iterator:()Ljava/util/Iterator;
      23: astore_2
      24: aload_2
      25: invokeinterface #6,  1            // InterfaceMethod java/util/Iterator.hasNext:()Z
      30: ifeq          56
      33: aload_2
      34: invokeinterface #7,  1            // InterfaceMethod java/util/Iterator.next:()Ljava/lang/Object;
      39: checkcast     #35                 // class org/jresearch/commons/base/ref/manager/api/obj/RefAttributeValueDto
      42: astore_3
      43: aload_1
      44: aload_3
      45: invokeinterface #36,  2           // InterfaceMethod java/util/List.contains:(Ljava/lang/Object;)Z
      50: invokestatic  #16                 // Method org/junit/Assert.assertTrue:(Z)V
      53: goto          24
      56: return

  public static void check(org.jresearch.commons.base.ref.manager.api.obj.IParamType, org.jresearch.commons.base.ref.manager.api.obj.IParamType);
    Code:
       0: aload_0
       1: ifnonnull     9
       4: aload_1
       5: ifnonnull     9
       8: return
       9: aload_0
      10: ifnull        17
      13: aload_1
      14: ifnonnull     22
      17: iconst_0
      18: invokestatic  #16                 // Method org/junit/Assert.assertTrue:(Z)V
      21: return
      22: aload_0
      23: invokeinterface #37,  1           // InterfaceMethod org/jresearch/commons/base/ref/manager/api/obj/IParamType.getCode:()Ljava/lang/String;
      28: aload_1
      29: invokeinterface #37,  1           // InterfaceMethod org/jresearch/commons/base/ref/manager/api/obj/IParamType.getCode:()Ljava/lang/String;
      34: invokestatic  #26                 // Method org/junit/Assert.assertEquals:(Ljava/lang/Object;Ljava/lang/Object;)V
      37: aload_0
      38: invokeinterface #38,  1           // InterfaceMethod org/jresearch/commons/base/ref/manager/api/obj/IParamType.getNames:()Ljava/util/Collection;
      43: aload_1
      44: invokeinterface #38,  1           // InterfaceMethod org/jresearch/commons/base/ref/manager/api/obj/IParamType.getNames:()Ljava/util/Collection;
      49: invokestatic  #24                 // Method checkLocalizedText:(Ljava/util/Collection;Ljava/util/Collection;)V
      52: return

  public static java.util.Collection<org.jresearch.commons.base.ref.manager.api.obj.AttributeValueDto> createDomainAttributes();
    Code:
       0: new           #39                 // class java/util/HashSet
       3: dup
       4: invokespecial #40                 // Method java/util/HashSet."<init>":()V
       7: astore_0
       8: aload_0
       9: invokestatic  #41                 // Method createBaseAttributeValue:()Lorg/jresearch/commons/base/ref/manager/api/obj/AttributeValueDto;
      12: invokevirtual #42                 // Method java/util/HashSet.add:(Ljava/lang/Object;)Z
      15: pop
      16: aload_0
      17: invokestatic  #41                 // Method createBaseAttributeValue:()Lorg/jresearch/commons/base/ref/manager/api/obj/AttributeValueDto;
      20: invokevirtual #42                 // Method java/util/HashSet.add:(Ljava/lang/Object;)Z
      23: pop
      24: aload_0
      25: areturn

  public static org.jresearch.commons.base.ref.manager.api.obj.RefAttributeValueDto createRefAttributeValue();
    Code:
       0: new           #35                 // class org/jresearch/commons/base/ref/manager/api/obj/RefAttributeValueDto
       3: dup
       4: invokespecial #43                 // Method org/jresearch/commons/base/ref/manager/api/obj/RefAttributeValueDto."<init>":()V
       7: astore_0
       8: aload_0
       9: invokestatic  #44                 // Method createBusinessType:()Lorg/jresearch/commons/base/ref/manager/api/obj/IBusinessType;
      12: invokevirtual #45                 // Method org/jresearch/commons/base/ref/manager/api/obj/RefAttributeValueDto.setBusinessType:(Lorg/jresearch/commons/base/ref/manager/api/obj/IBusinessType;)V
      15: aload_0
      16: invokestatic  #46                 // Method createId:()Ljava/lang/Long;
      19: invokevirtual #47                 // Method org/jresearch/commons/base/ref/manager/api/obj/RefAttributeValueDto.setId:(Ljava/lang/Long;)V
      22: aload_0
      23: ldc           #48                 // String stringBaseValue
      25: invokevirtual #49                 // Method org/jresearch/commons/base/ref/manager/api/obj/RefAttributeValueDto.setStringValue:(Ljava/lang/String;)V
      28: aload_0
      29: invokestatic  #50                 // Method createValidValue:()Lorg/jresearch/commons/base/ref/manager/api/obj/ValidValueDto;
      32: invokevirtual #51                 // Method org/jresearch/commons/base/ref/manager/api/obj/RefAttributeValueDto.setValue:(Lorg/jresearch/commons/base/ref/manager/api/obj/ValidValueDto;)V
      35: aload_0
      36: areturn

  public static org.jresearch.commons.base.ref.manager.api.obj.ValidValueDto createValidValue();
    Code:
       0: new           #52                 // class org/jresearch/commons/base/ref/manager/api/obj/ValidValueDto
       3: dup
       4: invokespecial #53                 // Method org/jresearch/commons/base/ref/manager/api/obj/ValidValueDto."<init>":()V
       7: astore_0
       8: aload_0
       9: invokestatic  #46                 // Method createId:()Ljava/lang/Long;
      12: invokevirtual #54                 // Method org/jresearch/commons/base/ref/manager/api/obj/ValidValueDto.setId:(Ljava/lang/Long;)V
      15: aload_0
      16: ldc           #55                 // String TT
      18: invokevirtual #56                 // Method org/jresearch/commons/base/ref/manager/api/obj/ValidValueDto.setInd:(Ljava/lang/String;)V
      21: aload_0
      22: invokestatic  #57                 // Method createI18Text1:()Lorg/jresearch/commons/base/localiztion/manager/api/obj/ILocalizedText;
      25: invokevirtual #58                 // Method org/jresearch/commons/base/ref/manager/api/obj/ValidValueDto.putName:(Lorg/jresearch/commons/base/localiztion/manager/api/obj/ILocalizedText;)V
      28: aload_0
      29: invokestatic  #59                 // Method createI18Text2:()Lorg/jresearch/commons/base/localiztion/manager/api/obj/ILocalizedText;
      32: invokevirtual #58                 // Method org/jresearch/commons/base/ref/manager/api/obj/ValidValueDto.putName:(Lorg/jresearch/commons/base/localiztion/manager/api/obj/ILocalizedText;)V
      35: aload_0
      36: areturn

  public static org.jresearch.commons.base.ref.manager.api.obj.AttributeValueDto createBaseAttributeValue();
    Code:
       0: new           #14                 // class org/jresearch/commons/base/ref/manager/api/obj/AttributeValueDto
       3: dup
       4: invokespecial #60                 // Method org/jresearch/commons/base/ref/manager/api/obj/AttributeValueDto."<init>":()V
       7: astore_0
       8: aload_0
       9: invokestatic  #44                 // Method createBusinessType:()Lorg/jresearch/commons/base/ref/manager/api/obj/IBusinessType;
      12: invokevirtual #61                 // Method org/jresearch/commons/base/ref/manager/api/obj/AttributeValueDto.setBusinessType:(Lorg/jresearch/commons/base/ref/manager/api/obj/IBusinessType;)V
      15: aload_0
      16: invokestatic  #46                 // Method createId:()Ljava/lang/Long;
      19: invokevirtual #62                 // Method org/jresearch/commons/base/ref/manager/api/obj/AttributeValueDto.setId:(Ljava/lang/Long;)V
      22: aload_0
      23: ldc           #48                 // String stringBaseValue
      25: invokevirtual #63                 // Method org/jresearch/commons/base/ref/manager/api/obj/AttributeValueDto.setStringValue:(Ljava/lang/String;)V
      28: aload_0
      29: areturn

  public static java.util.Set<org.jresearch.commons.base.ref.manager.api.obj.IBusinessType> createBusinessTypes();
    Code:
       0: new           #39                 // class java/util/HashSet
       3: dup
       4: invokespecial #40                 // Method java/util/HashSet."<init>":()V
       7: astore_0
       8: aload_0
       9: invokestatic  #44                 // Method createBusinessType:()Lorg/jresearch/commons/base/ref/manager/api/obj/IBusinessType;
      12: invokevirtual #42                 // Method java/util/HashSet.add:(Ljava/lang/Object;)Z
      15: pop
      16: aload_0
      17: areturn

  public static org.jresearch.commons.base.ref.manager.api.obj.IBusinessType createBusinessType();
    Code:
       0: new           #64                 // class java/lang/StringBuilder
       3: dup
       4: invokespecial #65                 // Method java/lang/StringBuilder."<init>":()V
       7: ldc           #66                 // String T
       9: invokevirtual #67                 // Method java/lang/StringBuilder.append:(Ljava/lang/String;)Ljava/lang/StringBuilder;
      12: getstatic     #68                 // Field rnd:Ljava/util/Random;
      15: invokevirtual #69                 // Method java/util/Random.nextLong:()J
      18: invokevirtual #70                 // Method java/lang/StringBuilder.append:(J)Ljava/lang/StringBuilder;
      21: invokevirtual #71                 // Method java/lang/StringBuilder.toString:()Ljava/lang/String;
      24: invokestatic  #72                 // Method createBusinessType:(Ljava/lang/String;)Lorg/jresearch/commons/base/ref/manager/api/obj/IBusinessType;
      27: areturn

  public static org.jresearch.commons.base.ref.manager.api.obj.IBusinessType createBusinessType(java.lang.String);
    Code:
       0: new           #73                 // class org/jresearch/commons/base/manager/impl/dto/ref/BusinessTypeDto
       3: dup
       4: invokespecial #74                 // Method org/jresearch/commons/base/manager/impl/dto/ref/BusinessTypeDto."<init>":()V
       7: astore_1
       8: aload_1
       9: invokestatic  #46                 // Method createId:()Ljava/lang/Long;
      12: invokevirtual #75                 // Method org/jresearch/commons/base/manager/impl/dto/ref/BusinessTypeDto.setId:(Ljava/lang/Long;)V
      15: aload_1
      16: iconst_1
      17: invokevirtual #76                 // Method org/jresearch/commons/base/manager/impl/dto/ref/BusinessTypeDto.setMandatory:(Z)V
      20: aload_1
      21: aload_0
      22: invokevirtual #77                 // Method org/jresearch/commons/base/manager/impl/dto/ref/BusinessTypeDto.setCode:(Ljava/lang/String;)V
      25: aload_1
      26: ldc2_w        #78                 // long 5l
      29: invokestatic  #80                 // Method java/lang/Long.valueOf:(J)Ljava/lang/Long;
      32: invokevirtual #81                 // Method org/jresearch/commons/base/manager/impl/dto/ref/BusinessTypeDto.setMinValue:(Ljava/lang/Long;)V
      35: aload_1
      36: invokestatic  #57                 // Method createI18Text1:()Lorg/jresearch/commons/base/localiztion/manager/api/obj/ILocalizedText;
      39: invokevirtual #82                 // Method org/jresearch/commons/base/manager/impl/dto/ref/BusinessTypeDto.putName:(Lorg/jresearch/commons/base/localiztion/manager/api/obj/ILocalizedText;)V
      42: aload_1
      43: invokestatic  #59                 // Method createI18Text2:()Lorg/jresearch/commons/base/localiztion/manager/api/obj/ILocalizedText;
      46: invokevirtual #82                 // Method org/jresearch/commons/base/manager/impl/dto/ref/BusinessTypeDto.putName:(Lorg/jresearch/commons/base/localiztion/manager/api/obj/ILocalizedText;)V
      49: aload_1
      50: invokestatic  #57                 // Method createI18Text1:()Lorg/jresearch/commons/base/localiztion/manager/api/obj/ILocalizedText;
      53: invokevirtual #83                 // Method org/jresearch/commons/base/manager/impl/dto/ref/BusinessTypeDto.putDescription:(Lorg/jresearch/commons/base/localiztion/manager/api/obj/ILocalizedText;)V
      56: aload_1
      57: invokestatic  #59                 // Method createI18Text2:()Lorg/jresearch/commons/base/localiztion/manager/api/obj/ILocalizedText;
      60: invokevirtual #83                 // Method org/jresearch/commons/base/manager/impl/dto/ref/BusinessTypeDto.putDescription:(Lorg/jresearch/commons/base/localiztion/manager/api/obj/ILocalizedText;)V
      63: aload_1
      64: iconst_1
      65: invokevirtual #84                 // Method org/jresearch/commons/base/manager/impl/dto/ref/BusinessTypeDto.setUserAttribute:(Z)V
      68: aload_1
      69: areturn

  public static org.jresearch.commons.base.localiztion.manager.api.obj.ILocalizedText createI18Text1();
    Code:
       0: new           #85                 // class org/jresearch/commons/base/manager/api/dto/ref/LocalizedTextDto
       3: dup
       4: invokespecial #86                 // Method org/jresearch/commons/base/manager/api/dto/ref/LocalizedTextDto."<init>":()V
       7: astore_0
       8: aload_0
       9: getstatic     #87                 // Field java/util/Locale.KOREAN:Ljava/util/Locale;
      12: invokevirtual #88                 // Method org/jresearch/commons/base/manager/api/dto/ref/LocalizedTextDto.setLocale:(Ljava/util/Locale;)V
      15: aload_0
      16: ldc           #89                 // String STK
      18: invokevirtual #90                 // Method org/jresearch/commons/base/manager/api/dto/ref/LocalizedTextDto.setValue:(Ljava/lang/String;)V
      21: aload_0
      22: areturn

  public static org.jresearch.commons.base.localiztion.manager.api.obj.ILocalizedText createI18Text2();
    Code:
       0: new           #85                 // class org/jresearch/commons/base/manager/api/dto/ref/LocalizedTextDto
       3: dup
       4: invokespecial #86                 // Method org/jresearch/commons/base/manager/api/dto/ref/LocalizedTextDto."<init>":()V
       7: astore_0
       8: aload_0
       9: getstatic     #91                 // Field java/util/Locale.CHINA:Ljava/util/Locale;
      12: invokevirtual #88                 // Method org/jresearch/commons/base/manager/api/dto/ref/LocalizedTextDto.setLocale:(Ljava/util/Locale;)V
      15: aload_0
      16: ldc           #92                 // String BiBiku
      18: invokevirtual #90                 // Method org/jresearch/commons/base/manager/api/dto/ref/LocalizedTextDto.setValue:(Ljava/lang/String;)V
      21: aload_0
      22: areturn

  public static java.lang.Long createId();
    Code:
       0: getstatic     #68                 // Field rnd:Ljava/util/Random;
       3: invokevirtual #69                 // Method java/util/Random.nextLong:()J
       6: invokestatic  #80                 // Method java/lang/Long.valueOf:(J)Ljava/lang/Long;
       9: areturn

  static {};
    Code:
       0: new           #93                 // class java/util/Random
       3: dup
       4: invokestatic  #94                 // Method java/lang/System.nanoTime:()J
       7: invokespecial #95                 // Method java/util/Random."<init>":(J)V
      10: putstatic     #68                 // Field rnd:Ljava/util/Random;
      13: return
}
