Compiled from "TLS.java"
public class org.apache.tomcat.util.compat.TLS {
  private static final boolean tlsv13Available;

  public org.apache.tomcat.util.compat.TLS();
    Code:
       0: aload_0
       1: invokespecial #1                  // Method java/lang/Object."<init>":()V
       4: return

  public static boolean isTlsv13Available();
    Code:
       0: getstatic     #2                  // Field tlsv13Available:Z
       3: ireturn

  static {};
    Code:
       0: iconst_0
       1: istore_0
       2: ldc           #4                  // String TLSv1.3
       4: invokestatic  #5                  // Method javax/net/ssl/SSLContext.getInstance:(Ljava/lang/String;)Ljavax/net/ssl/SSLContext;
       7: pop
       8: iconst_1
       9: istore_0
      10: goto          14
      13: astore_1
      14: iload_0
      15: putstatic     #2                  // Field tlsv13Available:Z
      18: return
    Exception table:
       from    to  target type
           2    10    13   Class java/security/NoSuchAlgorithmException
}
