Compiled from "TermWrapperJsonString.java"
public class nl.vpro.domain.classification.bind.TermWrapperJsonString$Serializer extends com.fasterxml.jackson.databind.JsonSerializer<nl.vpro.domain.classification.bind.AbstractTermWrapper> {
  public nl.vpro.domain.classification.bind.TermWrapperJsonString$Serializer();
    Code:
       0: aload_0
       1: invokespecial #1                  // Method com/fasterxml/jackson/databind/JsonSerializer."<init>":()V
       4: return

  public void serialize(nl.vpro.domain.classification.bind.AbstractTermWrapper, com.fasterxml.jackson.core.JsonGenerator, com.fasterxml.jackson.databind.SerializerProvider) throws java.io.IOException;
    Code:
       0: aload_2
       1: aload_1
       2: invokevirtual #2                  // Method nl/vpro/domain/classification/bind/AbstractTermWrapper.getName:()Ljava/lang/String;
       5: invokevirtual #3                  // Method com/fasterxml/jackson/core/JsonGenerator.writeString:(Ljava/lang/String;)V
       8: return

  public void serialize(java.lang.Object, com.fasterxml.jackson.core.JsonGenerator, com.fasterxml.jackson.databind.SerializerProvider) throws java.io.IOException;
    Code:
       0: aload_0
       1: aload_1
       2: checkcast     #4                  // class nl/vpro/domain/classification/bind/AbstractTermWrapper
       5: aload_2
       6: aload_3
       7: invokevirtual #5                  // Method serialize:(Lnl/vpro/domain/classification/bind/AbstractTermWrapper;Lcom/fasterxml/jackson/core/JsonGenerator;Lcom/fasterxml/jackson/databind/SerializerProvider;)V
      10: return
}
