Compiled from "UpdateDSLCodeGen2_2.java"
public class info.archinnov.achilles.internals.codegen.dsl.update.cassandra2_2.UpdateDSLCodeGen2_2 extends info.archinnov.achilles.internals.codegen.dsl.update.UpdateDSLCodeGen implements info.archinnov.achilles.internals.codegen.dsl.JSONFunctionCallSupport {
  public info.archinnov.achilles.internals.codegen.dsl.update.cassandra2_2.UpdateDSLCodeGen2_2();
    Code:
       0: aload_0
       1: invokespecial #1                  // Method info/archinnov/achilles/internals/codegen/dsl/update/UpdateDSLCodeGen."<init>":()V
       4: return

  protected void augmentUpdateRelationClass(info.archinnov.achilles.internals.codegen.dsl.update.UpdateDSLCodeGen$ParentSignature, info.archinnov.achilles.internals.parser.FieldParser$FieldMetaSignature, com.squareup.javapoet.TypeName, info.archinnov.achilles.internals.codegen.dsl.AbstractDSLCodeGen$ReturnType);
    Code:
       0: aload_0
       1: aload_1
       2: aload_2
       3: aload_3
       4: aload         4
       6: invokevirtual #2                  // Method buildSetFromJSONToRelationClass:(Linfo/archinnov/achilles/internals/codegen/dsl/update/UpdateDSLCodeGen$ParentSignature;Linfo/archinnov/achilles/internals/parser/FieldParser$FieldMetaSignature;Lcom/squareup/javapoet/TypeName;Linfo/archinnov/achilles/internals/codegen/dsl/AbstractDSLCodeGen$ReturnType;)V
       9: return
}
