Compiled from "LinkedListImpl.java"
public class org.apache.activemq.artemis.utils.LinkedListImpl<E> implements org.apache.activemq.artemis.utils.LinkedList<E> {
  private static final int INITIAL_ITERATOR_ARRAY_SIZE;

  private final org.apache.activemq.artemis.utils.LinkedListImpl$Node<E> head;

  private org.apache.activemq.artemis.utils.LinkedListImpl$Node<E> tail;

  private int size;

  private volatile org.apache.activemq.artemis.utils.LinkedListImpl<E>.Iterator[] iters;

  private int numIters;

  private int nextIndex;

  public org.apache.activemq.artemis.utils.LinkedListImpl();
    Code:
       0: aload_0
       1: invokespecial #5                  // Method java/lang/Object."<init>":()V
       4: aload_0
       5: new           #6                  // class org/apache/activemq/artemis/utils/LinkedListImpl$Node
       8: dup
       9: aconst_null
      10: invokespecial #7                  // Method org/apache/activemq/artemis/utils/LinkedListImpl$Node."<init>":(Ljava/lang/Object;)V
      13: putfield      #4                  // Field head:Lorg/apache/activemq/artemis/utils/LinkedListImpl$Node;
      16: aload_0
      17: aconst_null
      18: putfield      #8                  // Field tail:Lorg/apache/activemq/artemis/utils/LinkedListImpl$Node;
      21: aload_0
      22: aload_0
      23: bipush        10
      25: invokespecial #10                 // Method createIteratorArray:(I)[Lorg/apache/activemq/artemis/utils/LinkedListImpl$Iterator;
      28: putfield      #11                 // Field iters:[Lorg/apache/activemq/artemis/utils/LinkedListImpl$Iterator;
      31: return

  public void addHead(E);
    Code:
       0: new           #6                  // class org/apache/activemq/artemis/utils/LinkedListImpl$Node
       3: dup
       4: aload_1
       5: invokespecial #7                  // Method org/apache/activemq/artemis/utils/LinkedListImpl$Node."<init>":(Ljava/lang/Object;)V
       8: astore_2
       9: aload_2
      10: aload_0
      11: getfield      #4                  // Field head:Lorg/apache/activemq/artemis/utils/LinkedListImpl$Node;
      14: getfield      #12                 // Field org/apache/activemq/artemis/utils/LinkedListImpl$Node.next:Lorg/apache/activemq/artemis/utils/LinkedListImpl$Node;
      17: putfield      #12                 // Field org/apache/activemq/artemis/utils/LinkedListImpl$Node.next:Lorg/apache/activemq/artemis/utils/LinkedListImpl$Node;
      20: aload_2
      21: aload_0
      22: getfield      #4                  // Field head:Lorg/apache/activemq/artemis/utils/LinkedListImpl$Node;
      25: putfield      #13                 // Field org/apache/activemq/artemis/utils/LinkedListImpl$Node.prev:Lorg/apache/activemq/artemis/utils/LinkedListImpl$Node;
      28: aload_0
      29: getfield      #4                  // Field head:Lorg/apache/activemq/artemis/utils/LinkedListImpl$Node;
      32: aload_2
      33: putfield      #12                 // Field org/apache/activemq/artemis/utils/LinkedListImpl$Node.next:Lorg/apache/activemq/artemis/utils/LinkedListImpl$Node;
      36: aload_0
      37: getfield      #14                 // Field size:I
      40: ifne          51
      43: aload_0
      44: aload_2
      45: putfield      #8                  // Field tail:Lorg/apache/activemq/artemis/utils/LinkedListImpl$Node;
      48: goto          59
      51: aload_2
      52: getfield      #12                 // Field org/apache/activemq/artemis/utils/LinkedListImpl$Node.next:Lorg/apache/activemq/artemis/utils/LinkedListImpl$Node;
      55: aload_2
      56: putfield      #13                 // Field org/apache/activemq/artemis/utils/LinkedListImpl$Node.prev:Lorg/apache/activemq/artemis/utils/LinkedListImpl$Node;
      59: aload_0
      60: dup
      61: getfield      #14                 // Field size:I
      64: iconst_1
      65: iadd
      66: putfield      #14                 // Field size:I
      69: return

  public void addTail(E);
    Code:
       0: aload_0
       1: getfield      #14                 // Field size:I
       4: ifne          15
       7: aload_0
       8: aload_1
       9: invokevirtual #15                 // Method addHead:(Ljava/lang/Object;)V
      12: goto          55
      15: new           #6                  // class org/apache/activemq/artemis/utils/LinkedListImpl$Node
      18: dup
      19: aload_1
      20: invokespecial #7                  // Method org/apache/activemq/artemis/utils/LinkedListImpl$Node."<init>":(Ljava/lang/Object;)V
      23: astore_2
      24: aload_2
      25: aload_0
      26: getfield      #8                  // Field tail:Lorg/apache/activemq/artemis/utils/LinkedListImpl$Node;
      29: putfield      #13                 // Field org/apache/activemq/artemis/utils/LinkedListImpl$Node.prev:Lorg/apache/activemq/artemis/utils/LinkedListImpl$Node;
      32: aload_0
      33: getfield      #8                  // Field tail:Lorg/apache/activemq/artemis/utils/LinkedListImpl$Node;
      36: aload_2
      37: putfield      #12                 // Field org/apache/activemq/artemis/utils/LinkedListImpl$Node.next:Lorg/apache/activemq/artemis/utils/LinkedListImpl$Node;
      40: aload_0
      41: aload_2
      42: putfield      #8                  // Field tail:Lorg/apache/activemq/artemis/utils/LinkedListImpl$Node;
      45: aload_0
      46: dup
      47: getfield      #14                 // Field size:I
      50: iconst_1
      51: iadd
      52: putfield      #14                 // Field size:I
      55: return

  public E poll();
    Code:
       0: aload_0
       1: getfield      #4                  // Field head:Lorg/apache/activemq/artemis/utils/LinkedListImpl$Node;
       4: getfield      #12                 // Field org/apache/activemq/artemis/utils/LinkedListImpl$Node.next:Lorg/apache/activemq/artemis/utils/LinkedListImpl$Node;
       7: astore_1
       8: aload_1
       9: ifnull        25
      12: aload_0
      13: aload_0
      14: getfield      #4                  // Field head:Lorg/apache/activemq/artemis/utils/LinkedListImpl$Node;
      17: invokespecial #2                  // Method removeAfter:(Lorg/apache/activemq/artemis/utils/LinkedListImpl$Node;)V
      20: aload_1
      21: getfield      #16                 // Field org/apache/activemq/artemis/utils/LinkedListImpl$Node.val:Ljava/lang/Object;
      24: areturn
      25: aconst_null
      26: areturn

  public void clear();
    Code:
       0: aload_0
       1: aload_0
       2: getfield      #4                  // Field head:Lorg/apache/activemq/artemis/utils/LinkedListImpl$Node;
       5: aconst_null
       6: dup_x1
       7: putfield      #12                 // Field org/apache/activemq/artemis/utils/LinkedListImpl$Node.next:Lorg/apache/activemq/artemis/utils/LinkedListImpl$Node;
      10: putfield      #8                  // Field tail:Lorg/apache/activemq/artemis/utils/LinkedListImpl$Node;
      13: aload_0
      14: iconst_0
      15: putfield      #14                 // Field size:I
      18: return

  public int size();
    Code:
       0: aload_0
       1: getfield      #14                 // Field size:I
       4: ireturn

  public org.apache.activemq.artemis.utils.LinkedListIterator<E> iterator();
    Code:
       0: new           #17                 // class org/apache/activemq/artemis/utils/LinkedListImpl$Iterator
       3: dup
       4: aload_0
       5: invokespecial #18                 // Method org/apache/activemq/artemis/utils/LinkedListImpl$Iterator."<init>":(Lorg/apache/activemq/artemis/utils/LinkedListImpl;)V
       8: areturn

  public java.lang.String toString();
    Code:
       0: new           #19                 // class java/lang/StringBuilder
       3: dup
       4: ldc           #20                 // String LinkedListImpl [
       6: invokespecial #21                 // Method java/lang/StringBuilder."<init>":(Ljava/lang/String;)V
       9: astore_1
      10: aload_0
      11: getfield      #4                  // Field head:Lorg/apache/activemq/artemis/utils/LinkedListImpl$Node;
      14: astore_2
      15: aload_2
      16: ifnull        50
      19: aload_1
      20: aload_2
      21: invokevirtual #22                 // Method org/apache/activemq/artemis/utils/LinkedListImpl$Node.toString:()Ljava/lang/String;
      24: invokevirtual #23                 // Method java/lang/StringBuilder.append:(Ljava/lang/String;)Ljava/lang/StringBuilder;
      27: pop
      28: aload_2
      29: getfield      #12                 // Field org/apache/activemq/artemis/utils/LinkedListImpl$Node.next:Lorg/apache/activemq/artemis/utils/LinkedListImpl$Node;
      32: ifnull        42
      35: aload_1
      36: ldc           #24                 // String ,
      38: invokevirtual #23                 // Method java/lang/StringBuilder.append:(Ljava/lang/String;)Ljava/lang/StringBuilder;
      41: pop
      42: aload_2
      43: getfield      #12                 // Field org/apache/activemq/artemis/utils/LinkedListImpl$Node.next:Lorg/apache/activemq/artemis/utils/LinkedListImpl$Node;
      46: astore_2
      47: goto          15
      50: aload_1
      51: invokevirtual #25                 // Method java/lang/StringBuilder.toString:()Ljava/lang/String;
      54: areturn

  public int numIters();
    Code:
       0: aload_0
       1: getfield      #26                 // Field numIters:I
       4: ireturn

  private org.apache.activemq.artemis.utils.LinkedListImpl<E>.Iterator[] createIteratorArray(int);
    Code:
       0: ldc           #17                 // class org/apache/activemq/artemis/utils/LinkedListImpl$Iterator
       2: iload_1
       3: invokestatic  #27                 // Method java/lang/reflect/Array.newInstance:(Ljava/lang/Class;I)Ljava/lang/Object;
       6: checkcast     #28                 // class "[Lorg/apache/activemq/artemis/utils/LinkedListImpl$Iterator;"
       9: checkcast     #28                 // class "[Lorg/apache/activemq/artemis/utils/LinkedListImpl$Iterator;"
      12: areturn

  private void removeAfter(org.apache.activemq.artemis.utils.LinkedListImpl$Node<E>);
    Code:
       0: aload_1
       1: getfield      #12                 // Field org/apache/activemq/artemis/utils/LinkedListImpl$Node.next:Lorg/apache/activemq/artemis/utils/LinkedListImpl$Node;
       4: astore_2
       5: aload_1
       6: aload_2
       7: getfield      #12                 // Field org/apache/activemq/artemis/utils/LinkedListImpl$Node.next:Lorg/apache/activemq/artemis/utils/LinkedListImpl$Node;
      10: putfield      #12                 // Field org/apache/activemq/artemis/utils/LinkedListImpl$Node.next:Lorg/apache/activemq/artemis/utils/LinkedListImpl$Node;
      13: aload_2
      14: getfield      #12                 // Field org/apache/activemq/artemis/utils/LinkedListImpl$Node.next:Lorg/apache/activemq/artemis/utils/LinkedListImpl$Node;
      17: ifnull        28
      20: aload_2
      21: getfield      #12                 // Field org/apache/activemq/artemis/utils/LinkedListImpl$Node.next:Lorg/apache/activemq/artemis/utils/LinkedListImpl$Node;
      24: aload_1
      25: putfield      #13                 // Field org/apache/activemq/artemis/utils/LinkedListImpl$Node.prev:Lorg/apache/activemq/artemis/utils/LinkedListImpl$Node;
      28: aload_2
      29: aload_0
      30: getfield      #8                  // Field tail:Lorg/apache/activemq/artemis/utils/LinkedListImpl$Node;
      33: if_acmpne     41
      36: aload_0
      37: aload_1
      38: putfield      #8                  // Field tail:Lorg/apache/activemq/artemis/utils/LinkedListImpl$Node;
      41: aload_0
      42: dup
      43: getfield      #14                 // Field size:I
      46: iconst_1
      47: isub
      48: putfield      #14                 // Field size:I
      51: aload_2
      52: getfield      #29                 // Field org/apache/activemq/artemis/utils/LinkedListImpl$Node.iterCount:I
      55: ifeq          63
      58: aload_0
      59: aload_2
      60: invokespecial #30                 // Method nudgeIterators:(Lorg/apache/activemq/artemis/utils/LinkedListImpl$Node;)V
      63: aload_2
      64: aload_2
      65: aconst_null
      66: dup_x1
      67: putfield      #13                 // Field org/apache/activemq/artemis/utils/LinkedListImpl$Node.prev:Lorg/apache/activemq/artemis/utils/LinkedListImpl$Node;
      70: putfield      #12                 // Field org/apache/activemq/artemis/utils/LinkedListImpl$Node.next:Lorg/apache/activemq/artemis/utils/LinkedListImpl$Node;
      73: return

  private synchronized void nudgeIterators(org.apache.activemq.artemis.utils.LinkedListImpl$Node<E>);
    Code:
       0: iconst_0
       1: istore_2
       2: iload_2
       3: aload_0
       4: getfield      #26                 // Field numIters:I
       7: if_icmpge     32
      10: aload_0
      11: getfield      #11                 // Field iters:[Lorg/apache/activemq/artemis/utils/LinkedListImpl$Iterator;
      14: iload_2
      15: aaload
      16: astore_3
      17: aload_3
      18: ifnull        26
      21: aload_3
      22: aload_1
      23: invokevirtual #31                 // Method org/apache/activemq/artemis/utils/LinkedListImpl$Iterator.nudged:(Lorg/apache/activemq/artemis/utils/LinkedListImpl$Node;)V
      26: iinc          2, 1
      29: goto          2
      32: return

  private synchronized void addIter(org.apache.activemq.artemis.utils.LinkedListImpl<E>.Iterator);
    Code:
       0: aload_0
       1: getfield      #26                 // Field numIters:I
       4: aload_0
       5: getfield      #11                 // Field iters:[Lorg/apache/activemq/artemis/utils/LinkedListImpl$Iterator;
       8: arraylength
       9: if_icmpne     22
      12: aload_0
      13: iconst_2
      14: aload_0
      15: getfield      #26                 // Field numIters:I
      18: imul
      19: invokespecial #32                 // Method resize:(I)V
      22: aload_0
      23: getfield      #11                 // Field iters:[Lorg/apache/activemq/artemis/utils/LinkedListImpl$Iterator;
      26: aload_0
      27: dup
      28: getfield      #33                 // Field nextIndex:I
      31: dup_x1
      32: iconst_1
      33: iadd
      34: putfield      #33                 // Field nextIndex:I
      37: aload_1
      38: aastore
      39: aload_0
      40: dup
      41: getfield      #26                 // Field numIters:I
      44: iconst_1
      45: iadd
      46: putfield      #26                 // Field numIters:I
      49: return

  private synchronized void resize(int);
    Code:
       0: aload_0
       1: iload_1
       2: invokespecial #10                 // Method createIteratorArray:(I)[Lorg/apache/activemq/artemis/utils/LinkedListImpl$Iterator;
       5: astore_2
       6: aload_0
       7: getfield      #11                 // Field iters:[Lorg/apache/activemq/artemis/utils/LinkedListImpl$Iterator;
      10: iconst_0
      11: aload_2
      12: iconst_0
      13: aload_0
      14: getfield      #26                 // Field numIters:I
      17: invokestatic  #34                 // Method java/lang/System.arraycopy:(Ljava/lang/Object;ILjava/lang/Object;II)V
      20: aload_0
      21: aload_2
      22: putfield      #11                 // Field iters:[Lorg/apache/activemq/artemis/utils/LinkedListImpl$Iterator;
      25: return

  private synchronized void removeIter(org.apache.activemq.artemis.utils.LinkedListImpl<E>.Iterator);
    Code:
       0: iconst_0
       1: istore_2
       2: iload_2
       3: aload_0
       4: getfield      #26                 // Field numIters:I
       7: if_icmpge     118
      10: aload_1
      11: aload_0
      12: getfield      #11                 // Field iters:[Lorg/apache/activemq/artemis/utils/LinkedListImpl$Iterator;
      15: iload_2
      16: aaload
      17: if_acmpne     112
      20: aload_0
      21: getfield      #11                 // Field iters:[Lorg/apache/activemq/artemis/utils/LinkedListImpl$Iterator;
      24: iload_2
      25: aconst_null
      26: aastore
      27: iload_2
      28: aload_0
      29: getfield      #26                 // Field numIters:I
      32: iconst_1
      33: isub
      34: if_icmpeq     60
      37: aload_0
      38: getfield      #11                 // Field iters:[Lorg/apache/activemq/artemis/utils/LinkedListImpl$Iterator;
      41: iload_2
      42: iconst_1
      43: iadd
      44: aload_0
      45: getfield      #11                 // Field iters:[Lorg/apache/activemq/artemis/utils/LinkedListImpl$Iterator;
      48: iload_2
      49: aload_0
      50: getfield      #26                 // Field numIters:I
      53: iload_2
      54: isub
      55: iconst_1
      56: isub
      57: invokestatic  #34                 // Method java/lang/System.arraycopy:(Ljava/lang/Object;ILjava/lang/Object;II)V
      60: aload_0
      61: dup
      62: getfield      #26                 // Field numIters:I
      65: iconst_1
      66: isub
      67: putfield      #26                 // Field numIters:I
      70: aload_0
      71: getfield      #26                 // Field numIters:I
      74: bipush        10
      76: if_icmplt     101
      79: aload_0
      80: getfield      #26                 // Field numIters:I
      83: aload_0
      84: getfield      #11                 // Field iters:[Lorg/apache/activemq/artemis/utils/LinkedListImpl$Iterator;
      87: arraylength
      88: iconst_2
      89: idiv
      90: if_icmpne     101
      93: aload_0
      94: aload_0
      95: getfield      #26                 // Field numIters:I
      98: invokespecial #32                 // Method resize:(I)V
     101: aload_0
     102: dup
     103: getfield      #33                 // Field nextIndex:I
     106: iconst_1
     107: isub
     108: putfield      #33                 // Field nextIndex:I
     111: return
     112: iinc          2, 1
     115: goto          2
     118: new           #35                 // class java/lang/IllegalStateException
     121: dup
     122: ldc           #36                 // String Cannot find iter to remove
     124: invokespecial #37                 // Method java/lang/IllegalStateException."<init>":(Ljava/lang/String;)V
     127: athrow

  static org.apache.activemq.artemis.utils.LinkedListImpl$Node access$000(org.apache.activemq.artemis.utils.LinkedListImpl);
    Code:
       0: aload_0
       1: getfield      #4                  // Field head:Lorg/apache/activemq/artemis/utils/LinkedListImpl$Node;
       4: areturn

  static void access$100(org.apache.activemq.artemis.utils.LinkedListImpl, org.apache.activemq.artemis.utils.LinkedListImpl$Iterator);
    Code:
       0: aload_0
       1: aload_1
       2: invokespecial #3                  // Method addIter:(Lorg/apache/activemq/artemis/utils/LinkedListImpl$Iterator;)V
       5: return

  static void access$200(org.apache.activemq.artemis.utils.LinkedListImpl, org.apache.activemq.artemis.utils.LinkedListImpl$Node);
    Code:
       0: aload_0
       1: aload_1
       2: invokespecial #2                  // Method removeAfter:(Lorg/apache/activemq/artemis/utils/LinkedListImpl$Node;)V
       5: return

  static void access$300(org.apache.activemq.artemis.utils.LinkedListImpl, org.apache.activemq.artemis.utils.LinkedListImpl$Iterator);
    Code:
       0: aload_0
       1: aload_1
       2: invokespecial #1                  // Method removeIter:(Lorg/apache/activemq/artemis/utils/LinkedListImpl$Iterator;)V
       5: return
}
