Compiled from "SimpleIDGenerator.java"
public class org.apache.activemq.artemis.utils.SimpleIDGenerator implements org.apache.activemq.artemis.utils.IDGenerator {
  private long idSequence;

  private boolean wrapped;

  public org.apache.activemq.artemis.utils.SimpleIDGenerator(long);
    Code:
       0: aload_0
       1: invokespecial #1                  // Method java/lang/Object."<init>":()V
       4: aload_0
       5: lload_1
       6: putfield      #2                  // Field idSequence:J
       9: return

  public synchronized long generateID();
    Code:
       0: aload_0
       1: dup
       2: getfield      #2                  // Field idSequence:J
       5: dup2_x1
       6: lconst_1
       7: ladd
       8: putfield      #2                  // Field idSequence:J
      11: lstore_1
      12: aload_0
      13: getfield      #2                  // Field idSequence:J
      16: ldc2_w        #4                  // long -9223372036854775808l
      19: lcmp
      20: ifne          28
      23: aload_0
      24: iconst_1
      25: putfield      #6                  // Field wrapped:Z
      28: aload_0
      29: getfield      #6                  // Field wrapped:Z
      32: ifeq          45
      35: new           #7                  // class java/lang/IllegalStateException
      38: dup
      39: ldc           #8                  // String Exhausted ids to use!
      41: invokespecial #9                  // Method java/lang/IllegalStateException."<init>":(Ljava/lang/String;)V
      44: athrow
      45: lload_1
      46: lreturn

  public synchronized long getCurrentID();
    Code:
       0: aload_0
       1: getfield      #2                  // Field idSequence:J
       4: lreturn
}
