Compiled from "HibernatePersistence.java"
public class org.hibernate.ejb.HibernatePersistence extends org.hibernate.jpa.HibernatePersistenceProvider implements javax.persistence.spi.PersistenceProvider,org.hibernate.ejb.AvailableSettings {
  private static final org.hibernate.jpa.internal.EntityManagerMessageLogger log;

  public org.hibernate.ejb.HibernatePersistence();
    Code:
       0: aload_0
       1: invokespecial #1                  // Method org/hibernate/jpa/HibernatePersistenceProvider."<init>":()V
       4: return

  public javax.persistence.EntityManagerFactory createEntityManagerFactory(java.lang.String, java.util.Map);
    Code:
       0: aload_0
       1: invokevirtual #2                  // Method logDeprecation:()V
       4: aload_0
       5: aload_1
       6: aload_2
       7: invokespecial #3                  // Method org/hibernate/jpa/HibernatePersistenceProvider.createEntityManagerFactory:(Ljava/lang/String;Ljava/util/Map;)Ljavax/persistence/EntityManagerFactory;
      10: areturn

  protected void logDeprecation();
    Code:
       0: getstatic     #4                  // Field log:Lorg/hibernate/jpa/internal/EntityManagerMessageLogger;
       3: ldc           #5                  // class org/hibernate/ejb/HibernatePersistence
       5: invokevirtual #6                  // Method java/lang/Class.getName:()Ljava/lang/String;
       8: ldc           #7                  // class org/hibernate/jpa/HibernatePersistenceProvider
      10: invokevirtual #6                  // Method java/lang/Class.getName:()Ljava/lang/String;
      13: invokeinterface #8,  3            // InterfaceMethod org/hibernate/jpa/internal/EntityManagerMessageLogger.deprecatedPersistenceProvider:(Ljava/lang/String;Ljava/lang/String;)V
      18: return

  public javax.persistence.EntityManagerFactory createContainerEntityManagerFactory(javax.persistence.spi.PersistenceUnitInfo, java.util.Map);
    Code:
       0: aload_0
       1: invokevirtual #2                  // Method logDeprecation:()V
       4: aload_0
       5: aload_1
       6: aload_2
       7: invokespecial #9                  // Method org/hibernate/jpa/HibernatePersistenceProvider.createContainerEntityManagerFactory:(Ljavax/persistence/spi/PersistenceUnitInfo;Ljava/util/Map;)Ljavax/persistence/EntityManagerFactory;
      10: areturn

  public void generateSchema(javax.persistence.spi.PersistenceUnitInfo, java.util.Map);
    Code:
       0: aload_0
       1: invokevirtual #2                  // Method logDeprecation:()V
       4: aload_0
       5: aload_1
       6: aload_2
       7: invokespecial #10                 // Method org/hibernate/jpa/HibernatePersistenceProvider.generateSchema:(Ljavax/persistence/spi/PersistenceUnitInfo;Ljava/util/Map;)V
      10: return

  public boolean generateSchema(java.lang.String, java.util.Map);
    Code:
       0: aload_0
       1: invokevirtual #2                  // Method logDeprecation:()V
       4: aload_0
       5: aload_1
       6: aload_2
       7: invokespecial #11                 // Method org/hibernate/jpa/HibernatePersistenceProvider.generateSchema:(Ljava/lang/String;Ljava/util/Map;)Z
      10: ireturn

  public javax.persistence.spi.ProviderUtil getProviderUtil();
    Code:
       0: aload_0
       1: invokespecial #12                 // Method org/hibernate/jpa/HibernatePersistenceProvider.getProviderUtil:()Ljavax/persistence/spi/ProviderUtil;
       4: areturn

  protected org.hibernate.jpa.boot.spi.EntityManagerFactoryBuilder getEntityManagerFactoryBuilderOrNull(java.lang.String, java.util.Map, java.lang.ClassLoader);
    Code:
       0: aload_0
       1: invokevirtual #2                  // Method logDeprecation:()V
       4: aload_0
       5: aload_1
       6: aload_2
       7: aload_3
       8: invokespecial #13                 // Method org/hibernate/jpa/HibernatePersistenceProvider.getEntityManagerFactoryBuilderOrNull:(Ljava/lang/String;Ljava/util/Map;Ljava/lang/ClassLoader;)Lorg/hibernate/jpa/boot/spi/EntityManagerFactoryBuilder;
      11: areturn

  protected org.hibernate.jpa.boot.spi.EntityManagerFactoryBuilder getEntityManagerFactoryBuilderOrNull(java.lang.String, java.util.Map);
    Code:
       0: aload_0
       1: invokevirtual #2                  // Method logDeprecation:()V
       4: aload_0
       5: aload_1
       6: aload_2
       7: invokespecial #14                 // Method org/hibernate/jpa/HibernatePersistenceProvider.getEntityManagerFactoryBuilderOrNull:(Ljava/lang/String;Ljava/util/Map;)Lorg/hibernate/jpa/boot/spi/EntityManagerFactoryBuilder;
      10: areturn

  static {};
    Code:
       0: ldc           #5                  // class org/hibernate/ejb/HibernatePersistence
       2: invokestatic  #15                 // Method org/hibernate/jpa/internal/HEMLogging.messageLogger:(Ljava/lang/Class;)Lorg/hibernate/jpa/internal/EntityManagerMessageLogger;
       5: putstatic     #4                  // Field log:Lorg/hibernate/jpa/internal/EntityManagerMessageLogger;
       8: return
}
