Compiled from "UrlAuthorizationConfigurer.java"
public class org.springframework.security.config.annotation.web.configurers.UrlAuthorizationConfigurer$AuthorizedUrl {
  private final java.util.List<? extends org.springframework.security.web.util.matcher.RequestMatcher> requestMatchers;

  final org.springframework.security.config.annotation.web.configurers.UrlAuthorizationConfigurer this$0;

  private org.springframework.security.config.annotation.web.configurers.UrlAuthorizationConfigurer$AuthorizedUrl(java.util.List<? extends org.springframework.security.web.util.matcher.RequestMatcher>);
    Code:
       0: aload_0
       1: aload_1
       2: putfield      #2                  // Field this$0:Lorg/springframework/security/config/annotation/web/configurers/UrlAuthorizationConfigurer;
       5: aload_0
       6: invokespecial #3                  // Method java/lang/Object."<init>":()V
       9: aload_2
      10: ldc           #4                  // String requestMatchers must contain at least one value
      12: invokestatic  #5                  // Method org/springframework/util/Assert.notEmpty:(Ljava/util/Collection;Ljava/lang/String;)V
      15: aload_0
      16: aload_2
      17: putfield      #6                  // Field requestMatchers:Ljava/util/List;
      20: return

  public org.springframework.security.config.annotation.web.configurers.UrlAuthorizationConfigurer<H>.StandardInterceptUrlRegistry hasRole(java.lang.String);
    Code:
       0: aload_0
       1: iconst_1
       2: anewarray     #7                  // class java/lang/String
       5: dup
       6: iconst_0
       7: aload_1
       8: invokestatic  #8                  // Method org/springframework/security/config/annotation/web/configurers/UrlAuthorizationConfigurer.access$300:(Ljava/lang/String;)Ljava/lang/String;
      11: aastore
      12: invokevirtual #9                  // Method access:([Ljava/lang/String;)Lorg/springframework/security/config/annotation/web/configurers/UrlAuthorizationConfigurer$StandardInterceptUrlRegistry;
      15: areturn

  public org.springframework.security.config.annotation.web.configurers.UrlAuthorizationConfigurer<H>.StandardInterceptUrlRegistry hasAnyRole(java.lang.String...);
    Code:
       0: aload_0
       1: aload_1
       2: invokestatic  #10                 // Method org/springframework/security/config/annotation/web/configurers/UrlAuthorizationConfigurer.access$400:([Ljava/lang/String;)[Ljava/lang/String;
       5: invokevirtual #9                  // Method access:([Ljava/lang/String;)Lorg/springframework/security/config/annotation/web/configurers/UrlAuthorizationConfigurer$StandardInterceptUrlRegistry;
       8: areturn

  public org.springframework.security.config.annotation.web.configurers.UrlAuthorizationConfigurer<H>.StandardInterceptUrlRegistry hasAuthority(java.lang.String);
    Code:
       0: aload_0
       1: iconst_1
       2: anewarray     #7                  // class java/lang/String
       5: dup
       6: iconst_0
       7: aload_1
       8: aastore
       9: invokevirtual #9                  // Method access:([Ljava/lang/String;)Lorg/springframework/security/config/annotation/web/configurers/UrlAuthorizationConfigurer$StandardInterceptUrlRegistry;
      12: areturn

  public org.springframework.security.config.annotation.web.configurers.UrlAuthorizationConfigurer<H>.StandardInterceptUrlRegistry hasAnyAuthority(java.lang.String...);
    Code:
       0: aload_0
       1: aload_1
       2: invokestatic  #11                 // Method org/springframework/security/config/annotation/web/configurers/UrlAuthorizationConfigurer.access$500:([Ljava/lang/String;)[Ljava/lang/String;
       5: invokevirtual #9                  // Method access:([Ljava/lang/String;)Lorg/springframework/security/config/annotation/web/configurers/UrlAuthorizationConfigurer$StandardInterceptUrlRegistry;
       8: areturn

  public org.springframework.security.config.annotation.web.configurers.UrlAuthorizationConfigurer<H>.StandardInterceptUrlRegistry anonymous();
    Code:
       0: aload_0
       1: ldc           #12                 // String ANONYMOUS
       3: invokevirtual #13                 // Method hasRole:(Ljava/lang/String;)Lorg/springframework/security/config/annotation/web/configurers/UrlAuthorizationConfigurer$StandardInterceptUrlRegistry;
       6: areturn

  public org.springframework.security.config.annotation.web.configurers.UrlAuthorizationConfigurer<H>.StandardInterceptUrlRegistry access(java.lang.String...);
    Code:
       0: aload_0
       1: getfield      #2                  // Field this$0:Lorg/springframework/security/config/annotation/web/configurers/UrlAuthorizationConfigurer;
       4: aload_0
       5: getfield      #6                  // Field requestMatchers:Ljava/util/List;
       8: aload_1
       9: invokestatic  #14                 // Method org/springframework/security/access/SecurityConfig.createList:([Ljava/lang/String;)Ljava/util/List;
      12: invokestatic  #15                 // Method org/springframework/security/config/annotation/web/configurers/UrlAuthorizationConfigurer.access$600:(Lorg/springframework/security/config/annotation/web/configurers/UrlAuthorizationConfigurer;Ljava/lang/Iterable;Ljava/util/Collection;)Lorg/springframework/security/config/annotation/web/configurers/UrlAuthorizationConfigurer$StandardInterceptUrlRegistry;
      15: pop
      16: aload_0
      17: getfield      #2                  // Field this$0:Lorg/springframework/security/config/annotation/web/configurers/UrlAuthorizationConfigurer;
      20: invokestatic  #16                 // Method org/springframework/security/config/annotation/web/configurers/UrlAuthorizationConfigurer.access$700:(Lorg/springframework/security/config/annotation/web/configurers/UrlAuthorizationConfigurer;)Lorg/springframework/security/config/annotation/web/configurers/UrlAuthorizationConfigurer$StandardInterceptUrlRegistry;
      23: areturn

  protected java.util.List<? extends org.springframework.security.web.util.matcher.RequestMatcher> getMatchers();
    Code:
       0: aload_0
       1: getfield      #6                  // Field requestMatchers:Ljava/util/List;
       4: areturn

  org.springframework.security.config.annotation.web.configurers.UrlAuthorizationConfigurer$AuthorizedUrl(org.springframework.security.config.annotation.web.configurers.UrlAuthorizationConfigurer, java.util.List, org.springframework.security.config.annotation.web.configurers.UrlAuthorizationConfigurer$1);
    Code:
       0: aload_0
       1: aload_1
       2: aload_2
       3: invokespecial #1                  // Method "<init>":(Lorg/springframework/security/config/annotation/web/configurers/UrlAuthorizationConfigurer;Ljava/util/List;)V
       6: return
}
