Compiled from "LockModeTypeHelper.java"
public final class org.hibernate.jpa.internal.util.LockModeTypeHelper {
  private org.hibernate.jpa.internal.util.LockModeTypeHelper();
    Code:
       0: aload_0
       1: invokespecial #1                  // Method java/lang/Object."<init>":()V
       4: return

  public static javax.persistence.LockModeType getLockModeType(org.hibernate.LockMode);
    Code:
       0: aload_0
       1: invokestatic  #2                  // Method org/hibernate/internal/util/LockModeConverter.convertToLockModeType:(Lorg/hibernate/LockMode;)Ljavax/persistence/LockModeType;
       4: areturn

  public static org.hibernate.LockMode getLockMode(javax.persistence.LockModeType);
    Code:
       0: aload_0
       1: invokestatic  #3                  // Method org/hibernate/internal/util/LockModeConverter.convertToLockMode:(Ljavax/persistence/LockModeType;)Lorg/hibernate/LockMode;
       4: areturn

  public static org.hibernate.LockMode interpretLockMode(java.lang.Object);
    Code:
       0: aload_0
       1: ifnonnull     8
       4: getstatic     #4                  // Field org/hibernate/LockMode.NONE:Lorg/hibernate/LockMode;
       7: areturn
       8: ldc           #5                  // class org/hibernate/LockMode
      10: aload_0
      11: invokevirtual #6                  // Method java/lang/Class.isInstance:(Ljava/lang/Object;)Z
      14: ifeq          22
      17: aload_0
      18: checkcast     #5                  // class org/hibernate/LockMode
      21: areturn
      22: ldc           #7                  // class javax/persistence/LockModeType
      24: aload_0
      25: invokevirtual #6                  // Method java/lang/Class.isInstance:(Ljava/lang/Object;)Z
      28: ifeq          39
      31: aload_0
      32: checkcast     #7                  // class javax/persistence/LockModeType
      35: invokestatic  #8                  // Method getLockMode:(Ljavax/persistence/LockModeType;)Lorg/hibernate/LockMode;
      38: areturn
      39: ldc           #9                  // class java/lang/String
      41: aload_0
      42: invokevirtual #6                  // Method java/lang/Class.isInstance:(Ljava/lang/Object;)Z
      45: ifeq          81
      48: aload_0
      49: checkcast     #9                  // class java/lang/String
      52: invokestatic  #10                 // Method org/hibernate/LockMode.valueOf:(Ljava/lang/String;)Lorg/hibernate/LockMode;
      55: astore_1
      56: aload_1
      57: ifnonnull     75
      60: aload_0
      61: checkcast     #9                  // class java/lang/String
      64: invokestatic  #11                 // Method javax/persistence/LockModeType.valueOf:(Ljava/lang/String;)Ljavax/persistence/LockModeType;
      67: invokestatic  #8                  // Method getLockMode:(Ljavax/persistence/LockModeType;)Lorg/hibernate/LockMode;
      70: astore_1
      71: goto          75
      74: astore_2
      75: aload_1
      76: ifnull        81
      79: aload_1
      80: areturn
      81: new           #13                 // class java/lang/IllegalArgumentException
      84: dup
      85: new           #14                 // class java/lang/StringBuilder
      88: dup
      89: invokespecial #15                 // Method java/lang/StringBuilder."<init>":()V
      92: ldc           #16                 // String Unknown lock mode source :
      94: invokevirtual #17                 // Method java/lang/StringBuilder.append:(Ljava/lang/String;)Ljava/lang/StringBuilder;
      97: aload_0
      98: invokevirtual #18                 // Method java/lang/StringBuilder.append:(Ljava/lang/Object;)Ljava/lang/StringBuilder;
     101: invokevirtual #19                 // Method java/lang/StringBuilder.toString:()Ljava/lang/String;
     104: invokespecial #20                 // Method java/lang/IllegalArgumentException."<init>":(Ljava/lang/String;)V
     107: athrow
    Exception table:
       from    to  target type
          60    71    74   Class java/lang/Exception
}
