Compiled from "TypeProxy.java"
public class org.modelmapper.internal.bytebuddy.implementation.auxiliary.TypeProxy$MethodCall implements org.modelmapper.internal.bytebuddy.implementation.Implementation {
  private final org.modelmapper.internal.bytebuddy.implementation.MethodAccessorFactory methodAccessorFactory;

  final org.modelmapper.internal.bytebuddy.implementation.auxiliary.TypeProxy this$0;

  protected org.modelmapper.internal.bytebuddy.implementation.auxiliary.TypeProxy$MethodCall(org.modelmapper.internal.bytebuddy.implementation.auxiliary.TypeProxy, org.modelmapper.internal.bytebuddy.implementation.MethodAccessorFactory);
    Code:
       0: aload_0
       1: aload_1
       2: putfield      #42                 // Field this$0:Lorg/modelmapper/internal/bytebuddy/implementation/auxiliary/TypeProxy;
       5: aload_0
       6: invokespecial #45                 // Method java/lang/Object."<init>":()V
       9: aload_0
      10: aload_2
      11: putfield      #47                 // Field methodAccessorFactory:Lorg/modelmapper/internal/bytebuddy/implementation/MethodAccessorFactory;
      14: return

  public org.modelmapper.internal.bytebuddy.dynamic.scaffold.InstrumentedType prepare(org.modelmapper.internal.bytebuddy.dynamic.scaffold.InstrumentedType);
    Code:
       0: aload_1
       1: new           #26                 // class org/modelmapper/internal/bytebuddy/description/field/FieldDescription$Token
       4: dup
       5: ldc           #53                 // String target
       7: bipush        65
       9: aload_0
      10: getfield      #42                 // Field this$0:Lorg/modelmapper/internal/bytebuddy/implementation/auxiliary/TypeProxy;
      13: invokestatic  #57                 // Method org/modelmapper/internal/bytebuddy/implementation/auxiliary/TypeProxy.access$200:(Lorg/modelmapper/internal/bytebuddy/implementation/auxiliary/TypeProxy;)Lorg/modelmapper/internal/bytebuddy/implementation/Implementation$Target;
      16: invokeinterface #61,  1           // InterfaceMethod org/modelmapper/internal/bytebuddy/implementation/Implementation$Target.getInstrumentedType:()Lorg/modelmapper/internal/bytebuddy/description/type/TypeDescription;
      21: invokeinterface #65,  1           // InterfaceMethod org/modelmapper/internal/bytebuddy/description/type/TypeDescription.asGenericType:()Lorg/modelmapper/internal/bytebuddy/description/type/TypeDescription$Generic;
      26: invokespecial #68                 // Method org/modelmapper/internal/bytebuddy/description/field/FieldDescription$Token."<init>":(Ljava/lang/String;ILorg/modelmapper/internal/bytebuddy/description/type/TypeDescription$Generic;)V
      29: invokeinterface #74,  2           // InterfaceMethod org/modelmapper/internal/bytebuddy/dynamic/scaffold/InstrumentedType.withField:(Lorg/modelmapper/internal/bytebuddy/description/field/FieldDescription$Token;)Lorg/modelmapper/internal/bytebuddy/dynamic/scaffold/InstrumentedType;
      34: areturn

  public org.modelmapper.internal.bytebuddy.implementation.bytecode.ByteCodeAppender appender(org.modelmapper.internal.bytebuddy.implementation.Implementation$Target);
    Code:
       0: new           #15                 // class org/modelmapper/internal/bytebuddy/implementation/auxiliary/TypeProxy$MethodCall$Appender
       3: dup
       4: aload_0
       5: aload_1
       6: invokeinterface #61,  1           // InterfaceMethod org/modelmapper/internal/bytebuddy/implementation/Implementation$Target.getInstrumentedType:()Lorg/modelmapper/internal/bytebuddy/description/type/TypeDescription;
      11: invokespecial #81                 // Method org/modelmapper/internal/bytebuddy/implementation/auxiliary/TypeProxy$MethodCall$Appender."<init>":(Lorg/modelmapper/internal/bytebuddy/implementation/auxiliary/TypeProxy$MethodCall;Lorg/modelmapper/internal/bytebuddy/description/type/TypeDescription;)V
      14: areturn

  static org.modelmapper.internal.bytebuddy.implementation.MethodAccessorFactory access$500(org.modelmapper.internal.bytebuddy.implementation.auxiliary.TypeProxy$MethodCall);
    Code:
       0: aload_0
       1: getfield      #47                 // Field methodAccessorFactory:Lorg/modelmapper/internal/bytebuddy/implementation/MethodAccessorFactory;
       4: areturn

  public boolean equals(java.lang.Object);
    Code:
       0: aload_0
       1: aload_1
       2: if_acmpne     7
       5: iconst_1
       6: ireturn
       7: aload_1
       8: ifnonnull     13
      11: iconst_0
      12: ireturn
      13: aload_0
      14: invokevirtual #92                 // Method java/lang/Object.getClass:()Ljava/lang/Class;
      17: aload_1
      18: invokevirtual #92                 // Method java/lang/Object.getClass:()Ljava/lang/Class;
      21: if_acmpeq     26
      24: iconst_0
      25: ireturn
      26: aload_0
      27: getfield      #47                 // Field methodAccessorFactory:Lorg/modelmapper/internal/bytebuddy/implementation/MethodAccessorFactory;
      30: aload_1
      31: checkcast     #2                  // class org/modelmapper/internal/bytebuddy/implementation/auxiliary/TypeProxy$MethodCall
      34: getfield      #47                 // Field methodAccessorFactory:Lorg/modelmapper/internal/bytebuddy/implementation/MethodAccessorFactory;
      37: invokeinterface #96,  2           // InterfaceMethod org/modelmapper/internal/bytebuddy/implementation/MethodAccessorFactory.equals:(Ljava/lang/Object;)Z
      42: ifne          47
      45: iconst_0
      46: ireturn
      47: aload_0
      48: getfield      #42                 // Field this$0:Lorg/modelmapper/internal/bytebuddy/implementation/auxiliary/TypeProxy;
      51: aload_1
      52: checkcast     #2                  // class org/modelmapper/internal/bytebuddy/implementation/auxiliary/TypeProxy$MethodCall
      55: getfield      #42                 // Field this$0:Lorg/modelmapper/internal/bytebuddy/implementation/auxiliary/TypeProxy;
      58: invokevirtual #97                 // Method org/modelmapper/internal/bytebuddy/implementation/auxiliary/TypeProxy.equals:(Ljava/lang/Object;)Z
      61: ifne          66
      64: iconst_0
      65: ireturn
      66: iconst_1
      67: ireturn

  public int hashCode();
    Code:
       0: bipush        17
       2: bipush        31
       4: imul
       5: aload_0
       6: getfield      #47                 // Field methodAccessorFactory:Lorg/modelmapper/internal/bytebuddy/implementation/MethodAccessorFactory;
       9: invokeinterface #101,  1          // InterfaceMethod org/modelmapper/internal/bytebuddy/implementation/MethodAccessorFactory.hashCode:()I
      14: iadd
      15: bipush        31
      17: imul
      18: aload_0
      19: getfield      #42                 // Field this$0:Lorg/modelmapper/internal/bytebuddy/implementation/auxiliary/TypeProxy;
      22: invokevirtual #102                // Method org/modelmapper/internal/bytebuddy/implementation/auxiliary/TypeProxy.hashCode:()I
      25: iadd
      26: ireturn
}
