Compiled from "TypeProxy.java"
public class org.modelmapper.internal.bytebuddy.implementation.auxiliary.TypeProxy implements org.modelmapper.internal.bytebuddy.implementation.auxiliary.AuxiliaryType {
  public static final java.lang.String REFLECTION_METHOD;

  public static final java.lang.String INSTANCE_FIELD;

  private final org.modelmapper.internal.bytebuddy.description.type.TypeDescription proxiedType;

  private final org.modelmapper.internal.bytebuddy.implementation.Implementation$Target implementationTarget;

  private final org.modelmapper.internal.bytebuddy.implementation.auxiliary.TypeProxy$InvocationFactory invocationFactory;

  private final boolean ignoreFinalizer;

  private final boolean serializableProxy;

  public org.modelmapper.internal.bytebuddy.implementation.auxiliary.TypeProxy(org.modelmapper.internal.bytebuddy.description.type.TypeDescription, org.modelmapper.internal.bytebuddy.implementation.Implementation$Target, org.modelmapper.internal.bytebuddy.implementation.auxiliary.TypeProxy$InvocationFactory, boolean, boolean);
    Code:
       0: aload_0
       1: invokespecial #101                // Method java/lang/Object."<init>":()V
       4: aload_0
       5: aload_1
       6: putfield      #103                // Field proxiedType:Lorg/modelmapper/internal/bytebuddy/description/type/TypeDescription;
       9: aload_0
      10: aload_2
      11: putfield      #105                // Field implementationTarget:Lorg/modelmapper/internal/bytebuddy/implementation/Implementation$Target;
      14: aload_0
      15: aload_3
      16: putfield      #107                // Field invocationFactory:Lorg/modelmapper/internal/bytebuddy/implementation/auxiliary/TypeProxy$InvocationFactory;
      19: aload_0
      20: iload         4
      22: putfield      #109                // Field ignoreFinalizer:Z
      25: aload_0
      26: iload         5
      28: putfield      #111                // Field serializableProxy:Z
      31: return

  public org.modelmapper.internal.bytebuddy.dynamic.DynamicType make(java.lang.String, org.modelmapper.internal.bytebuddy.ClassFileVersion, org.modelmapper.internal.bytebuddy.implementation.MethodAccessorFactory);
    Code:
       0: new           #116                // class org/modelmapper/internal/bytebuddy/ByteBuddy
       3: dup
       4: aload_2
       5: invokespecial #119                // Method org/modelmapper/internal/bytebuddy/ByteBuddy."<init>":(Lorg/modelmapper/internal/bytebuddy/ClassFileVersion;)V
       8: aload_0
       9: getfield      #109                // Field ignoreFinalizer:Z
      12: ifeq          21
      15: invokestatic  #125                // Method org/modelmapper/internal/bytebuddy/matcher/ElementMatchers.isFinalizer:()Lorg/modelmapper/internal/bytebuddy/matcher/ElementMatcher$Junction;
      18: goto          24
      21: invokestatic  #128                // Method org/modelmapper/internal/bytebuddy/matcher/ElementMatchers.none:()Lorg/modelmapper/internal/bytebuddy/matcher/ElementMatcher$Junction;
      24: invokevirtual #138                // Method org/modelmapper/internal/bytebuddy/ByteBuddy.ignore:(Lorg/modelmapper/internal/bytebuddy/matcher/ElementMatcher;)Lorg/modelmapper/internal/bytebuddy/ByteBuddy;
      27: aload_0
      28: getfield      #103                // Field proxiedType:Lorg/modelmapper/internal/bytebuddy/description/type/TypeDescription;
      31: invokevirtual #142                // Method org/modelmapper/internal/bytebuddy/ByteBuddy.subclass:(Lorg/modelmapper/internal/bytebuddy/description/type/TypeDefinition;)Lorg/modelmapper/internal/bytebuddy/dynamic/DynamicType$Builder;
      34: aload_1
      35: invokeinterface #146,  2          // InterfaceMethod org/modelmapper/internal/bytebuddy/dynamic/DynamicType$Builder.name:(Ljava/lang/String;)Lorg/modelmapper/internal/bytebuddy/dynamic/DynamicType$Builder;
      40: getstatic     #150                // Field DEFAULT_TYPE_MODIFIER:[Lorg/modelmapper/internal/bytebuddy/description/modifier/ModifierContributor$ForType;
      43: invokeinterface #154,  2          // InterfaceMethod org/modelmapper/internal/bytebuddy/dynamic/DynamicType$Builder.modifiers:([Lorg/modelmapper/internal/bytebuddy/description/modifier/ModifierContributor$ForType;)Lorg/modelmapper/internal/bytebuddy/dynamic/DynamicType$Builder;
      48: aload_0
      49: getfield      #111                // Field serializableProxy:Z
      52: ifeq          67
      55: iconst_1
      56: anewarray     #156                // class java/lang/Class
      59: dup
      60: iconst_0
      61: ldc           #158                // class java/io/Serializable
      63: aastore
      64: goto          71
      67: iconst_0
      68: anewarray     #156                // class java/lang/Class
      71: invokeinterface #164,  2          // InterfaceMethod org/modelmapper/internal/bytebuddy/dynamic/DynamicType$Builder.implement:([Ljava/lang/reflect/Type;)Lorg/modelmapper/internal/bytebuddy/dynamic/DynamicType$Builder$MethodDefinition$ImplementationDefinition$Optional;
      76: invokestatic  #167                // Method org/modelmapper/internal/bytebuddy/matcher/ElementMatchers.any:()Lorg/modelmapper/internal/bytebuddy/matcher/ElementMatcher$Junction;
      79: invokeinterface #171,  2          // InterfaceMethod org/modelmapper/internal/bytebuddy/dynamic/DynamicType$Builder$MethodDefinition$ImplementationDefinition$Optional.method:(Lorg/modelmapper/internal/bytebuddy/matcher/ElementMatcher;)Lorg/modelmapper/internal/bytebuddy/dynamic/DynamicType$Builder$MethodDefinition$ImplementationDefinition;
      84: new           #12                 // class org/modelmapper/internal/bytebuddy/implementation/auxiliary/TypeProxy$MethodCall
      87: dup
      88: aload_0
      89: aload_3
      90: invokespecial #174                // Method org/modelmapper/internal/bytebuddy/implementation/auxiliary/TypeProxy$MethodCall."<init>":(Lorg/modelmapper/internal/bytebuddy/implementation/auxiliary/TypeProxy;Lorg/modelmapper/internal/bytebuddy/implementation/MethodAccessorFactory;)V
      93: invokeinterface #178,  2          // InterfaceMethod org/modelmapper/internal/bytebuddy/dynamic/DynamicType$Builder$MethodDefinition$ImplementationDefinition.intercept:(Lorg/modelmapper/internal/bytebuddy/implementation/Implementation;)Lorg/modelmapper/internal/bytebuddy/dynamic/DynamicType$Builder$MethodDefinition$ReceiverTypeDefinition;
      98: ldc           #84                 // String make
     100: ldc           #180                // class org/modelmapper/internal/bytebuddy/dynamic/TargetType
     102: iconst_1
     103: anewarray     #43                 // class org/modelmapper/internal/bytebuddy/description/modifier/ModifierContributor$ForMethod
     106: dup
     107: iconst_0
     108: getstatic     #186                // Field org/modelmapper/internal/bytebuddy/description/modifier/Ownership.STATIC:Lorg/modelmapper/internal/bytebuddy/description/modifier/Ownership;
     111: aastore
     112: invokeinterface #190,  4          // InterfaceMethod org/modelmapper/internal/bytebuddy/dynamic/DynamicType$Builder$MethodDefinition$ReceiverTypeDefinition.defineMethod:(Ljava/lang/String;Ljava/lang/reflect/Type;[Lorg/modelmapper/internal/bytebuddy/description/modifier/ModifierContributor$ForMethod;)Lorg/modelmapper/internal/bytebuddy/dynamic/DynamicType$Builder$MethodDefinition$ParameterDefinition$Initial;
     117: getstatic     #194                // Field org/modelmapper/internal/bytebuddy/implementation/auxiliary/TypeProxy$SilentConstruction.INSTANCE:Lorg/modelmapper/internal/bytebuddy/implementation/auxiliary/TypeProxy$SilentConstruction;
     120: invokeinterface #195,  2          // InterfaceMethod org/modelmapper/internal/bytebuddy/dynamic/DynamicType$Builder$MethodDefinition$ParameterDefinition$Initial.intercept:(Lorg/modelmapper/internal/bytebuddy/implementation/Implementation;)Lorg/modelmapper/internal/bytebuddy/dynamic/DynamicType$Builder$MethodDefinition$ReceiverTypeDefinition;
     125: invokeinterface #198,  1          // InterfaceMethod org/modelmapper/internal/bytebuddy/dynamic/DynamicType$Builder$MethodDefinition$ReceiverTypeDefinition.make:()Lorg/modelmapper/internal/bytebuddy/dynamic/DynamicType$Unloaded;
     130: areturn

  static org.modelmapper.internal.bytebuddy.implementation.Implementation$Target access$200(org.modelmapper.internal.bytebuddy.implementation.auxiliary.TypeProxy);
    Code:
       0: aload_0
       1: getfield      #105                // Field implementationTarget:Lorg/modelmapper/internal/bytebuddy/implementation/Implementation$Target;
       4: areturn

  static org.modelmapper.internal.bytebuddy.description.type.TypeDescription access$300(org.modelmapper.internal.bytebuddy.implementation.auxiliary.TypeProxy);
    Code:
       0: aload_0
       1: getfield      #103                // Field proxiedType:Lorg/modelmapper/internal/bytebuddy/description/type/TypeDescription;
       4: areturn

  static org.modelmapper.internal.bytebuddy.implementation.auxiliary.TypeProxy$InvocationFactory access$400(org.modelmapper.internal.bytebuddy.implementation.auxiliary.TypeProxy);
    Code:
       0: aload_0
       1: getfield      #107                // Field invocationFactory:Lorg/modelmapper/internal/bytebuddy/implementation/auxiliary/TypeProxy$InvocationFactory;
       4: areturn

  public boolean equals(java.lang.Object);
    Code:
       0: aload_0
       1: aload_1
       2: if_acmpne     7
       5: iconst_1
       6: ireturn
       7: aload_1
       8: ifnonnull     13
      11: iconst_0
      12: ireturn
      13: aload_0
      14: invokevirtual #216                // Method java/lang/Object.getClass:()Ljava/lang/Class;
      17: aload_1
      18: invokevirtual #216                // Method java/lang/Object.getClass:()Ljava/lang/Class;
      21: if_acmpeq     26
      24: iconst_0
      25: ireturn
      26: aload_0
      27: getfield      #103                // Field proxiedType:Lorg/modelmapper/internal/bytebuddy/description/type/TypeDescription;
      30: aload_1
      31: checkcast     #2                  // class org/modelmapper/internal/bytebuddy/implementation/auxiliary/TypeProxy
      34: getfield      #103                // Field proxiedType:Lorg/modelmapper/internal/bytebuddy/description/type/TypeDescription;
      37: invokeinterface #220,  2          // InterfaceMethod org/modelmapper/internal/bytebuddy/description/type/TypeDescription.equals:(Ljava/lang/Object;)Z
      42: ifne          47
      45: iconst_0
      46: ireturn
      47: aload_0
      48: getfield      #105                // Field implementationTarget:Lorg/modelmapper/internal/bytebuddy/implementation/Implementation$Target;
      51: aload_1
      52: checkcast     #2                  // class org/modelmapper/internal/bytebuddy/implementation/auxiliary/TypeProxy
      55: getfield      #105                // Field implementationTarget:Lorg/modelmapper/internal/bytebuddy/implementation/Implementation$Target;
      58: invokeinterface #221,  2          // InterfaceMethod org/modelmapper/internal/bytebuddy/implementation/Implementation$Target.equals:(Ljava/lang/Object;)Z
      63: ifne          68
      66: iconst_0
      67: ireturn
      68: aload_0
      69: getfield      #107                // Field invocationFactory:Lorg/modelmapper/internal/bytebuddy/implementation/auxiliary/TypeProxy$InvocationFactory;
      72: aload_1
      73: checkcast     #2                  // class org/modelmapper/internal/bytebuddy/implementation/auxiliary/TypeProxy
      76: getfield      #107                // Field invocationFactory:Lorg/modelmapper/internal/bytebuddy/implementation/auxiliary/TypeProxy$InvocationFactory;
      79: invokeinterface #222,  2          // InterfaceMethod org/modelmapper/internal/bytebuddy/implementation/auxiliary/TypeProxy$InvocationFactory.equals:(Ljava/lang/Object;)Z
      84: ifne          89
      87: iconst_0
      88: ireturn
      89: aload_0
      90: getfield      #109                // Field ignoreFinalizer:Z
      93: aload_1
      94: checkcast     #2                  // class org/modelmapper/internal/bytebuddy/implementation/auxiliary/TypeProxy
      97: getfield      #109                // Field ignoreFinalizer:Z
     100: if_icmpeq     105
     103: iconst_0
     104: ireturn
     105: aload_0
     106: getfield      #111                // Field serializableProxy:Z
     109: aload_1
     110: checkcast     #2                  // class org/modelmapper/internal/bytebuddy/implementation/auxiliary/TypeProxy
     113: getfield      #111                // Field serializableProxy:Z
     116: if_icmpeq     121
     119: iconst_0
     120: ireturn
     121: iconst_1
     122: ireturn

  public int hashCode();
    Code:
       0: bipush        17
       2: bipush        31
       4: imul
       5: aload_0
       6: getfield      #103                // Field proxiedType:Lorg/modelmapper/internal/bytebuddy/description/type/TypeDescription;
       9: invokeinterface #226,  1          // InterfaceMethod org/modelmapper/internal/bytebuddy/description/type/TypeDescription.hashCode:()I
      14: iadd
      15: bipush        31
      17: imul
      18: aload_0
      19: getfield      #105                // Field implementationTarget:Lorg/modelmapper/internal/bytebuddy/implementation/Implementation$Target;
      22: invokeinterface #227,  1          // InterfaceMethod org/modelmapper/internal/bytebuddy/implementation/Implementation$Target.hashCode:()I
      27: iadd
      28: bipush        31
      30: imul
      31: aload_0
      32: getfield      #107                // Field invocationFactory:Lorg/modelmapper/internal/bytebuddy/implementation/auxiliary/TypeProxy$InvocationFactory;
      35: invokeinterface #228,  1          // InterfaceMethod org/modelmapper/internal/bytebuddy/implementation/auxiliary/TypeProxy$InvocationFactory.hashCode:()I
      40: iadd
      41: bipush        31
      43: imul
      44: aload_0
      45: getfield      #109                // Field ignoreFinalizer:Z
      48: iadd
      49: bipush        31
      51: imul
      52: aload_0
      53: getfield      #111                // Field serializableProxy:Z
      56: iadd
      57: ireturn
}
