Compiled from "Context.java"
public class org.apache.cxf.aegis.Context {
  private org.apache.cxf.aegis.AegisContext globalContext;

  private java.util.Collection<org.apache.cxf.message.Attachment> attachments;

  private org.apache.cxf.interceptor.Fault fault;

  private java.util.Map<java.lang.Class<?>, java.lang.Object> properties;

  private java.util.Map<java.lang.String, java.lang.Object> namedProperties;

  public org.apache.cxf.aegis.Context(org.apache.cxf.aegis.AegisContext);
    Code:
       0: aload_0
       1: invokespecial #1                  // Method java/lang/Object."<init>":()V
       4: aload_0
       5: aload_1
       6: putfield      #2                  // Field globalContext:Lorg/apache/cxf/aegis/AegisContext;
       9: aload_0
      10: new           #3                  // class java/util/HashMap
      13: dup
      14: invokespecial #4                  // Method java/util/HashMap."<init>":()V
      17: putfield      #5                  // Field properties:Ljava/util/Map;
      20: aload_0
      21: new           #3                  // class java/util/HashMap
      24: dup
      25: invokespecial #4                  // Method java/util/HashMap."<init>":()V
      28: putfield      #6                  // Field namedProperties:Ljava/util/Map;
      31: return

  public org.apache.cxf.aegis.type.TypeMapping getTypeMapping();
    Code:
       0: aload_0
       1: getfield      #2                  // Field globalContext:Lorg/apache/cxf/aegis/AegisContext;
       4: invokevirtual #7                  // Method org/apache/cxf/aegis/AegisContext.getTypeMapping:()Lorg/apache/cxf/aegis/type/TypeMapping;
       7: areturn

  public java.util.Collection<org.apache.cxf.message.Attachment> getAttachments();
    Code:
       0: aload_0
       1: getfield      #8                  // Field attachments:Ljava/util/Collection;
       4: areturn

  public void setAttachments(java.util.Collection<org.apache.cxf.message.Attachment>);
    Code:
       0: aload_0
       1: aload_1
       2: putfield      #8                  // Field attachments:Ljava/util/Collection;
       5: return

  public boolean isWriteXsiTypes();
    Code:
       0: aload_0
       1: getfield      #2                  // Field globalContext:Lorg/apache/cxf/aegis/AegisContext;
       4: invokevirtual #9                  // Method org/apache/cxf/aegis/AegisContext.isWriteXsiTypes:()Z
       7: ireturn

  public boolean isReadXsiTypes();
    Code:
       0: aload_0
       1: getfield      #2                  // Field globalContext:Lorg/apache/cxf/aegis/AegisContext;
       4: invokevirtual #10                 // Method org/apache/cxf/aegis/AegisContext.isReadXsiTypes:()Z
       7: ireturn

  public void setFault(org.apache.cxf.interceptor.Fault);
    Code:
       0: aload_0
       1: aload_1
       2: putfield      #11                 // Field fault:Lorg/apache/cxf/interceptor/Fault;
       5: return

  public org.apache.cxf.interceptor.Fault getFault();
    Code:
       0: aload_0
       1: getfield      #11                 // Field fault:Lorg/apache/cxf/interceptor/Fault;
       4: areturn

  public org.apache.cxf.aegis.AegisContext getGlobalContext();
    Code:
       0: aload_0
       1: getfield      #2                  // Field globalContext:Lorg/apache/cxf/aegis/AegisContext;
       4: areturn

  public boolean isMtomEnabled();
    Code:
       0: aload_0
       1: getfield      #2                  // Field globalContext:Lorg/apache/cxf/aegis/AegisContext;
       4: invokevirtual #12                 // Method org/apache/cxf/aegis/AegisContext.isMtomEnabled:()Z
       7: ireturn

  public <T> T getProperty(java.lang.Class<T>);
    Code:
       0: aload_1
       1: aload_0
       2: getfield      #5                  // Field properties:Ljava/util/Map;
       5: aload_1
       6: invokeinterface #13,  2           // InterfaceMethod java/util/Map.get:(Ljava/lang/Object;)Ljava/lang/Object;
      11: invokevirtual #14                 // Method java/lang/Class.cast:(Ljava/lang/Object;)Ljava/lang/Object;
      14: areturn

  public void setProperty(java.lang.Object);
    Code:
       0: aload_0
       1: getfield      #5                  // Field properties:Ljava/util/Map;
       4: aload_1
       5: invokevirtual #15                 // Method java/lang/Object.getClass:()Ljava/lang/Class;
       8: aload_1
       9: invokeinterface #16,  3           // InterfaceMethod java/util/Map.put:(Ljava/lang/Object;Ljava/lang/Object;)Ljava/lang/Object;
      14: pop
      15: return

  public void setProperty(java.lang.String, java.lang.Object);
    Code:
       0: aload_0
       1: getfield      #6                  // Field namedProperties:Ljava/util/Map;
       4: aload_1
       5: aload_2
       6: invokeinterface #16,  3           // InterfaceMethod java/util/Map.put:(Ljava/lang/Object;Ljava/lang/Object;)Ljava/lang/Object;
      11: pop
      12: return

  public <T> T getProperty(java.lang.String, java.lang.Class<T>);
    Code:
       0: aload_2
       1: aload_0
       2: getfield      #6                  // Field namedProperties:Ljava/util/Map;
       5: aload_1
       6: invokeinterface #13,  2           // InterfaceMethod java/util/Map.get:(Ljava/lang/Object;)Ljava/lang/Object;
      11: invokevirtual #14                 // Method java/lang/Class.cast:(Ljava/lang/Object;)Ljava/lang/Object;
      14: areturn
}
