Compiled from "Ss7Layer.java"
public final class org.mobicents.protocols.ss7.oam.common.jmxss7.Ss7Layer extends java.lang.Enum<org.mobicents.protocols.ss7.oam.common.jmxss7.Ss7Layer> implements org.mobicents.protocols.ss7.oam.common.jmx.MBeanLayer {
  public static final org.mobicents.protocols.ss7.oam.common.jmxss7.Ss7Layer SCTP;

  public static final org.mobicents.protocols.ss7.oam.common.jmxss7.Ss7Layer M3UA;

  public static final org.mobicents.protocols.ss7.oam.common.jmxss7.Ss7Layer SCCP;

  public static final org.mobicents.protocols.ss7.oam.common.jmxss7.Ss7Layer TCAP;

  public static final org.mobicents.protocols.ss7.oam.common.jmxss7.Ss7Layer LINKSET;

  public static final org.mobicents.protocols.ss7.oam.common.jmxss7.Ss7Layer SMSC_GW;

  public static final org.mobicents.protocols.ss7.oam.common.jmxss7.Ss7Layer USSD_GW;

  private final java.lang.String name;

  public static final java.lang.String NAME_SCTP;

  public static final java.lang.String NAME_M3UA;

  public static final java.lang.String NAME_SCCP;

  public static final java.lang.String NAME_TCAP;

  public static final java.lang.String NAME_LINKSET;

  public static final java.lang.String NAME_SMSC_GW;

  public static final java.lang.String NAME_USSD_GW;

  private static final org.mobicents.protocols.ss7.oam.common.jmxss7.Ss7Layer[] $VALUES;

  public static org.mobicents.protocols.ss7.oam.common.jmxss7.Ss7Layer[] values();
    Code:
       0: getstatic     #1                  // Field $VALUES:[Lorg/mobicents/protocols/ss7/oam/common/jmxss7/Ss7Layer;
       3: invokevirtual #2                  // Method "[Lorg/mobicents/protocols/ss7/oam/common/jmxss7/Ss7Layer;".clone:()Ljava/lang/Object;
       6: checkcast     #3                  // class "[Lorg/mobicents/protocols/ss7/oam/common/jmxss7/Ss7Layer;"
       9: areturn

  public static org.mobicents.protocols.ss7.oam.common.jmxss7.Ss7Layer valueOf(java.lang.String);
    Code:
       0: ldc_w         #4                  // class org/mobicents/protocols/ss7/oam/common/jmxss7/Ss7Layer
       3: aload_0
       4: invokestatic  #5                  // Method java/lang/Enum.valueOf:(Ljava/lang/Class;Ljava/lang/String;)Ljava/lang/Enum;
       7: checkcast     #4                  // class org/mobicents/protocols/ss7/oam/common/jmxss7/Ss7Layer
      10: areturn

  private org.mobicents.protocols.ss7.oam.common.jmxss7.Ss7Layer(java.lang.String);
    Code:
       0: aload_0
       1: aload_1
       2: iload_2
       3: invokespecial #6                  // Method java/lang/Enum."<init>":(Ljava/lang/String;I)V
       6: aload_0
       7: aload_3
       8: putfield      #7                  // Field name:Ljava/lang/String;
      11: return

  public java.lang.String getName();
    Code:
       0: aload_0
       1: getfield      #7                  // Field name:Ljava/lang/String;
       4: areturn

  public static org.mobicents.protocols.ss7.oam.common.jmx.MBeanLayer getInstance(java.lang.String);
    Code:
       0: ldc           #8                  // String SCTP
       2: aload_0
       3: invokevirtual #9                  // Method java/lang/String.equals:(Ljava/lang/Object;)Z
       6: ifeq          13
       9: getstatic     #10                 // Field SCTP:Lorg/mobicents/protocols/ss7/oam/common/jmxss7/Ss7Layer;
      12: areturn
      13: ldc           #11                 // String M3UA
      15: aload_0
      16: invokevirtual #9                  // Method java/lang/String.equals:(Ljava/lang/Object;)Z
      19: ifeq          26
      22: getstatic     #12                 // Field M3UA:Lorg/mobicents/protocols/ss7/oam/common/jmxss7/Ss7Layer;
      25: areturn
      26: ldc           #13                 // String SCCP
      28: aload_0
      29: invokevirtual #9                  // Method java/lang/String.equals:(Ljava/lang/Object;)Z
      32: ifeq          39
      35: getstatic     #14                 // Field SCCP:Lorg/mobicents/protocols/ss7/oam/common/jmxss7/Ss7Layer;
      38: areturn
      39: ldc           #15                 // String TCAP
      41: aload_0
      42: invokevirtual #9                  // Method java/lang/String.equals:(Ljava/lang/Object;)Z
      45: ifeq          52
      48: getstatic     #16                 // Field TCAP:Lorg/mobicents/protocols/ss7/oam/common/jmxss7/Ss7Layer;
      51: areturn
      52: ldc           #17                 // String LINKSET
      54: aload_0
      55: invokevirtual #9                  // Method java/lang/String.equals:(Ljava/lang/Object;)Z
      58: ifeq          65
      61: getstatic     #18                 // Field LINKSET:Lorg/mobicents/protocols/ss7/oam/common/jmxss7/Ss7Layer;
      64: areturn
      65: ldc           #19                 // String SMSC_GW
      67: aload_0
      68: invokevirtual #9                  // Method java/lang/String.equals:(Ljava/lang/Object;)Z
      71: ifeq          78
      74: getstatic     #20                 // Field SMSC_GW:Lorg/mobicents/protocols/ss7/oam/common/jmxss7/Ss7Layer;
      77: areturn
      78: ldc           #21                 // String USSD_GW
      80: aload_0
      81: invokevirtual #9                  // Method java/lang/String.equals:(Ljava/lang/Object;)Z
      84: ifeq          91
      87: getstatic     #22                 // Field USSD_GW:Lorg/mobicents/protocols/ss7/oam/common/jmxss7/Ss7Layer;
      90: areturn
      91: aconst_null
      92: areturn

  static {};
    Code:
       0: new           #4                  // class org/mobicents/protocols/ss7/oam/common/jmxss7/Ss7Layer
       3: dup
       4: ldc           #8                  // String SCTP
       6: iconst_0
       7: ldc           #8                  // String SCTP
       9: invokespecial #23                 // Method "<init>":(Ljava/lang/String;ILjava/lang/String;)V
      12: putstatic     #10                 // Field SCTP:Lorg/mobicents/protocols/ss7/oam/common/jmxss7/Ss7Layer;
      15: new           #4                  // class org/mobicents/protocols/ss7/oam/common/jmxss7/Ss7Layer
      18: dup
      19: ldc           #11                 // String M3UA
      21: iconst_1
      22: ldc           #11                 // String M3UA
      24: invokespecial #23                 // Method "<init>":(Ljava/lang/String;ILjava/lang/String;)V
      27: putstatic     #12                 // Field M3UA:Lorg/mobicents/protocols/ss7/oam/common/jmxss7/Ss7Layer;
      30: new           #4                  // class org/mobicents/protocols/ss7/oam/common/jmxss7/Ss7Layer
      33: dup
      34: ldc           #13                 // String SCCP
      36: iconst_2
      37: ldc           #13                 // String SCCP
      39: invokespecial #23                 // Method "<init>":(Ljava/lang/String;ILjava/lang/String;)V
      42: putstatic     #14                 // Field SCCP:Lorg/mobicents/protocols/ss7/oam/common/jmxss7/Ss7Layer;
      45: new           #4                  // class org/mobicents/protocols/ss7/oam/common/jmxss7/Ss7Layer
      48: dup
      49: ldc           #15                 // String TCAP
      51: iconst_3
      52: ldc           #15                 // String TCAP
      54: invokespecial #23                 // Method "<init>":(Ljava/lang/String;ILjava/lang/String;)V
      57: putstatic     #16                 // Field TCAP:Lorg/mobicents/protocols/ss7/oam/common/jmxss7/Ss7Layer;
      60: new           #4                  // class org/mobicents/protocols/ss7/oam/common/jmxss7/Ss7Layer
      63: dup
      64: ldc           #17                 // String LINKSET
      66: iconst_4
      67: ldc           #17                 // String LINKSET
      69: invokespecial #23                 // Method "<init>":(Ljava/lang/String;ILjava/lang/String;)V
      72: putstatic     #18                 // Field LINKSET:Lorg/mobicents/protocols/ss7/oam/common/jmxss7/Ss7Layer;
      75: new           #4                  // class org/mobicents/protocols/ss7/oam/common/jmxss7/Ss7Layer
      78: dup
      79: ldc           #19                 // String SMSC_GW
      81: iconst_5
      82: ldc           #19                 // String SMSC_GW
      84: invokespecial #23                 // Method "<init>":(Ljava/lang/String;ILjava/lang/String;)V
      87: putstatic     #20                 // Field SMSC_GW:Lorg/mobicents/protocols/ss7/oam/common/jmxss7/Ss7Layer;
      90: new           #4                  // class org/mobicents/protocols/ss7/oam/common/jmxss7/Ss7Layer
      93: dup
      94: ldc           #21                 // String USSD_GW
      96: bipush        6
      98: ldc           #21                 // String USSD_GW
     100: invokespecial #23                 // Method "<init>":(Ljava/lang/String;ILjava/lang/String;)V
     103: putstatic     #22                 // Field USSD_GW:Lorg/mobicents/protocols/ss7/oam/common/jmxss7/Ss7Layer;
     106: bipush        7
     108: anewarray     #4                  // class org/mobicents/protocols/ss7/oam/common/jmxss7/Ss7Layer
     111: dup
     112: iconst_0
     113: getstatic     #10                 // Field SCTP:Lorg/mobicents/protocols/ss7/oam/common/jmxss7/Ss7Layer;
     116: aastore
     117: dup
     118: iconst_1
     119: getstatic     #12                 // Field M3UA:Lorg/mobicents/protocols/ss7/oam/common/jmxss7/Ss7Layer;
     122: aastore
     123: dup
     124: iconst_2
     125: getstatic     #14                 // Field SCCP:Lorg/mobicents/protocols/ss7/oam/common/jmxss7/Ss7Layer;
     128: aastore
     129: dup
     130: iconst_3
     131: getstatic     #16                 // Field TCAP:Lorg/mobicents/protocols/ss7/oam/common/jmxss7/Ss7Layer;
     134: aastore
     135: dup
     136: iconst_4
     137: getstatic     #18                 // Field LINKSET:Lorg/mobicents/protocols/ss7/oam/common/jmxss7/Ss7Layer;
     140: aastore
     141: dup
     142: iconst_5
     143: getstatic     #20                 // Field SMSC_GW:Lorg/mobicents/protocols/ss7/oam/common/jmxss7/Ss7Layer;
     146: aastore
     147: dup
     148: bipush        6
     150: getstatic     #22                 // Field USSD_GW:Lorg/mobicents/protocols/ss7/oam/common/jmxss7/Ss7Layer;
     153: aastore
     154: putstatic     #1                  // Field $VALUES:[Lorg/mobicents/protocols/ss7/oam/common/jmxss7/Ss7Layer;
     157: return
}
