Compiled from "UploadPipe.java"
public class io.vertx.up.uca.micro.discovery.multipart.UploadPipe implements io.vertx.up.uca.micro.discovery.multipart.Pipe<org.apache.http.HttpResponse> {
  private static final io.vertx.up.log.Annal LOGGER;

  private final transient io.vertx.ext.web.RoutingContext context;

  private final transient io.vertx.servicediscovery.ServiceReference reference;

  private final transient io.vertx.core.http.RequestOptions options;

  private final transient io.vertx.core.http.HttpServerRequest request;

  private final transient io.vertx.core.http.HttpServerResponse response;

  private io.vertx.up.uca.micro.discovery.multipart.UploadPipe(io.vertx.ext.web.RoutingContext, io.vertx.servicediscovery.ServiceReference, io.vertx.core.http.RequestOptions);
    Code:
       0: aload_0
       1: invokespecial #1                  // Method java/lang/Object."<init>":()V
       4: aload_0
       5: aload_1
       6: putfield      #2                  // Field context:Lio/vertx/ext/web/RoutingContext;
       9: aload_0
      10: aload_1
      11: invokeinterface #3,  1            // InterfaceMethod io/vertx/ext/web/RoutingContext.request:()Lio/vertx/core/http/HttpServerRequest;
      16: putfield      #4                  // Field request:Lio/vertx/core/http/HttpServerRequest;
      19: aload_0
      20: aload_1
      21: invokeinterface #5,  1            // InterfaceMethod io/vertx/ext/web/RoutingContext.response:()Lio/vertx/core/http/HttpServerResponse;
      26: putfield      #6                  // Field response:Lio/vertx/core/http/HttpServerResponse;
      29: aload_0
      30: aload_2
      31: putfield      #7                  // Field reference:Lio/vertx/servicediscovery/ServiceReference;
      34: aload_0
      35: aload_3
      36: putfield      #8                  // Field options:Lio/vertx/core/http/RequestOptions;
      39: return

  public static io.vertx.up.uca.micro.discovery.multipart.UploadPipe create(io.vertx.ext.web.RoutingContext, io.vertx.servicediscovery.ServiceReference, io.vertx.core.http.RequestOptions);
    Code:
       0: new           #9                  // class io/vertx/up/uca/micro/discovery/multipart/UploadPipe
       3: dup
       4: aload_0
       5: aload_1
       6: aload_2
       7: invokespecial #10                 // Method "<init>":(Lio/vertx/ext/web/RoutingContext;Lio/vertx/servicediscovery/ServiceReference;Lio/vertx/core/http/RequestOptions;)V
      10: areturn

  public void doRequest(io.vertx.core.Handler<org.apache.http.HttpResponse>);
    Code:
       0: getstatic     #11                 // Field io/vertx/core/http/HttpMethod.POST:Lio/vertx/core/http/HttpMethod;
       3: aload_0
       4: getfield      #4                  // Field request:Lio/vertx/core/http/HttpServerRequest;
       7: invokeinterface #12,  1           // InterfaceMethod io/vertx/core/http/HttpServerRequest.method:()Lio/vertx/core/http/HttpMethod;
      12: if_acmpne     69
      15: aload_0
      16: getfield      #4                  // Field request:Lio/vertx/core/http/HttpServerRequest;
      19: invokeinterface #13,  1           // InterfaceMethod io/vertx/core/http/HttpServerRequest.isExpectMultipart:()Z
      24: ifeq          69
      27: aload_0
      28: invokespecial #14                 // Method getFile:()Lio/vertx/ext/web/FileUpload;
      31: astore_2
      32: aconst_null
      33: aload_2
      34: if_acmpne     60
      37: aload_0
      38: invokevirtual #15                 // Method java/lang/Object.getClass:()Ljava/lang/Class;
      41: aload_0
      42: getfield      #2                  // Field context:Lio/vertx/ext/web/RoutingContext;
      45: new           #16                 // class java/lang/RuntimeException
      48: dup
      49: ldc           #17                 // String Upload file missing...
      51: invokespecial #18                 // Method java/lang/RuntimeException."<init>":(Ljava/lang/String;)V
      54: invokestatic  #19                 // Method io/vertx/up/uca/micro/discovery/InOut.sync500Error:(Ljava/lang/Class;Lio/vertx/ext/web/RoutingContext;Ljava/lang/Throwable;)V
      57: goto          66
      60: aload_0
      61: aload_2
      62: aload_1
      63: invokespecial #20                 // Method executeUpload:(Lio/vertx/ext/web/FileUpload;Lio/vertx/core/Handler;)V
      66: goto          80
      69: aload_0
      70: invokevirtual #15                 // Method java/lang/Object.getClass:()Ljava/lang/Class;
      73: aload_0
      74: getfield      #2                  // Field context:Lio/vertx/ext/web/RoutingContext;
      77: invokestatic  #21                 // Method io/vertx/up/uca/micro/discovery/InOut.sync405Error:(Ljava/lang/Class;Lio/vertx/ext/web/RoutingContext;)V
      80: return

  private void executeUpload(io.vertx.ext.web.FileUpload, io.vertx.core.Handler<org.apache.http.HttpResponse>);
    Code:
       0: aload_1
       1: invokeinterface #22,  1           // InterfaceMethod io/vertx/ext/web/FileUpload.uploadedFileName:()Ljava/lang/String;
       6: astore_3
       7: new           #23                 // class java/io/File
      10: dup
      11: aload_3
      12: invokespecial #24                 // Method java/io/File."<init>":(Ljava/lang/String;)V
      15: astore        4
      17: aload         4
      19: invokevirtual #25                 // Method java/io/File.exists:()Z
      22: ifeq          148
      25: invokestatic  #26                 // Method org/apache/http/impl/client/HttpClients.createDefault:()Lorg/apache/http/impl/client/CloseableHttpClient;
      28: astore        5
      30: aload_0
      31: invokespecial #27                 // Method remoteUri:()Ljava/lang/String;
      34: astore        6
      36: new           #28                 // class org/apache/http/client/methods/HttpPost
      39: dup
      40: aload         6
      42: invokespecial #29                 // Method org/apache/http/client/methods/HttpPost."<init>":(Ljava/lang/String;)V
      45: astore        7
      47: aload_0
      48: aload         7
      50: invokespecial #30                 // Method processHeaders:(Lorg/apache/http/client/methods/HttpPost;)V
      53: aload_0
      54: aload         7
      56: aload_1
      57: aload         4
      59: invokespecial #31                 // Method processMultipart:(Lorg/apache/http/client/methods/HttpPost;Lio/vertx/ext/web/FileUpload;Ljava/io/File;)V
      62: aload         7
      64: invokevirtual #32                 // Method org/apache/http/client/methods/HttpPost.getAllHeaders:()[Lorg/apache/http/Header;
      67: astore        8
      69: aload         8
      71: arraylength
      72: istore        9
      74: iconst_0
      75: istore        10
      77: iload         10
      79: iload         9
      81: if_icmpge     131
      84: aload         8
      86: iload         10
      88: aaload
      89: astore        11
      91: getstatic     #33                 // Field LOGGER:Lio/vertx/up/log/Annal;
      94: ldc           #34                 // String Normalized header: key = {0}, value = {1}.
      96: iconst_2
      97: anewarray     #35                 // class java/lang/Object
     100: dup
     101: iconst_0
     102: aload         11
     104: invokeinterface #36,  1           // InterfaceMethod org/apache/http/Header.getName:()Ljava/lang/String;
     109: aastore
     110: dup
     111: iconst_1
     112: aload         11
     114: invokeinterface #37,  1           // InterfaceMethod org/apache/http/Header.getValue:()Ljava/lang/String;
     119: aastore
     120: invokeinterface #38,  3           // InterfaceMethod io/vertx/up/log/Annal.info:(Ljava/lang/String;[Ljava/lang/Object;)V
     125: iinc          10, 1
     128: goto          77
     131: aload         5
     133: aload         7
     135: invokevirtual #39                 // Method org/apache/http/impl/client/CloseableHttpClient.execute:(Lorg/apache/http/client/methods/HttpUriRequest;)Lorg/apache/http/client/methods/CloseableHttpResponse;
     138: astore        8
     140: aload_2
     141: aload         8
     143: invokeinterface #40,  2           // InterfaceMethod io/vertx/core/Handler.handle:(Ljava/lang/Object;)V
     148: goto          168
     151: astore_3
     152: aload_3
     153: invokevirtual #42                 // Method java/lang/Exception.printStackTrace:()V
     156: aload_0
     157: invokevirtual #15                 // Method java/lang/Object.getClass:()Ljava/lang/Class;
     160: aload_0
     161: getfield      #2                  // Field context:Lio/vertx/ext/web/RoutingContext;
     164: aload_3
     165: invokestatic  #19                 // Method io/vertx/up/uca/micro/discovery/InOut.sync500Error:(Ljava/lang/Class;Lio/vertx/ext/web/RoutingContext;Ljava/lang/Throwable;)V
     168: return
    Exception table:
       from    to  target type
           0   148   151   Class java/lang/Exception

  private java.lang.String remoteUri();
    Code:
       0: aload_0
       1: getfield      #2                  // Field context:Lio/vertx/ext/web/RoutingContext;
       4: invokestatic  #43                 // Method io/vertx/up/uca/micro/discovery/InOut.normalizeUri:(Lio/vertx/ext/web/RoutingContext;)Ljava/lang/String;
       7: astore_1
       8: new           #44                 // class java/lang/StringBuilder
      11: dup
      12: invokespecial #45                 // Method java/lang/StringBuilder."<init>":()V
      15: astore_2
      16: aload_2
      17: ldc           #46                 // String http://
      19: invokevirtual #47                 // Method java/lang/StringBuilder.append:(Ljava/lang/String;)Ljava/lang/StringBuilder;
      22: aload_0
      23: getfield      #8                  // Field options:Lio/vertx/core/http/RequestOptions;
      26: invokevirtual #48                 // Method io/vertx/core/http/RequestOptions.getHost:()Ljava/lang/String;
      29: invokevirtual #47                 // Method java/lang/StringBuilder.append:(Ljava/lang/String;)Ljava/lang/StringBuilder;
      32: pop
      33: aload_2
      34: ldc           #49                 // String :
      36: invokevirtual #47                 // Method java/lang/StringBuilder.append:(Ljava/lang/String;)Ljava/lang/StringBuilder;
      39: aload_0
      40: getfield      #8                  // Field options:Lio/vertx/core/http/RequestOptions;
      43: invokevirtual #50                 // Method io/vertx/core/http/RequestOptions.getPort:()I
      46: invokevirtual #51                 // Method java/lang/StringBuilder.append:(I)Ljava/lang/StringBuilder;
      49: pop
      50: aload_2
      51: aload_1
      52: invokevirtual #47                 // Method java/lang/StringBuilder.append:(Ljava/lang/String;)Ljava/lang/StringBuilder;
      55: pop
      56: aload_2
      57: invokevirtual #52                 // Method java/lang/StringBuilder.toString:()Ljava/lang/String;
      60: astore_3
      61: getstatic     #33                 // Field LOGGER:Lio/vertx/up/log/Annal;
      64: ldc           #53                 // String Multipart redirect uri: {0}
      66: iconst_1
      67: anewarray     #35                 // class java/lang/Object
      70: dup
      71: iconst_0
      72: aload_3
      73: aastore
      74: invokeinterface #38,  3           // InterfaceMethod io/vertx/up/log/Annal.info:(Ljava/lang/String;[Ljava/lang/Object;)V
      79: aload_3
      80: areturn

  private void processMultipart(org.apache.http.client.methods.HttpPost, io.vertx.ext.web.FileUpload, java.io.File);
    Code:
       0: aload_2
       1: invokeinterface #54,  1           // InterfaceMethod io/vertx/ext/web/FileUpload.contentType:()Ljava/lang/String;
       6: invokestatic  #55                 // Method org/apache/http/entity/ContentType.create:(Ljava/lang/String;)Lorg/apache/http/entity/ContentType;
       9: astore        4
      11: getstatic     #33                 // Field LOGGER:Lio/vertx/up/log/Annal;
      14: ldc           #56                 // String Read file from file system: {0}
      16: iconst_1
      17: anewarray     #35                 // class java/lang/Object
      20: dup
      21: iconst_0
      22: aload_3
      23: invokevirtual #57                 // Method java/io/File.getAbsolutePath:()Ljava/lang/String;
      26: aastore
      27: invokeinterface #38,  3           // InterfaceMethod io/vertx/up/log/Annal.info:(Ljava/lang/String;[Ljava/lang/Object;)V
      32: new           #58                 // class org/apache/http/entity/mime/content/FileBody
      35: dup
      36: aload_3
      37: aload         4
      39: invokespecial #59                 // Method org/apache/http/entity/mime/content/FileBody."<init>":(Ljava/io/File;Lorg/apache/http/entity/ContentType;)V
      42: astore        5
      44: invokestatic  #60                 // Method org/apache/http/entity/mime/MultipartEntityBuilder.create:()Lorg/apache/http/entity/mime/MultipartEntityBuilder;
      47: astore        6
      49: aload         6
      51: getstatic     #61                 // Field org/apache/http/entity/mime/HttpMultipartMode.BROWSER_COMPATIBLE:Lorg/apache/http/entity/mime/HttpMultipartMode;
      54: invokevirtual #62                 // Method org/apache/http/entity/mime/MultipartEntityBuilder.setMode:(Lorg/apache/http/entity/mime/HttpMultipartMode;)Lorg/apache/http/entity/mime/MultipartEntityBuilder;
      57: pop
      58: new           #44                 // class java/lang/StringBuilder
      61: dup
      62: invokespecial #45                 // Method java/lang/StringBuilder."<init>":()V
      65: ldc           #63                 // String form-data; name=\"file\"; filename=\"
      67: invokevirtual #47                 // Method java/lang/StringBuilder.append:(Ljava/lang/String;)Ljava/lang/StringBuilder;
      70: aload_2
      71: invokeinterface #64,  1           // InterfaceMethod io/vertx/ext/web/FileUpload.fileName:()Ljava/lang/String;
      76: invokevirtual #47                 // Method java/lang/StringBuilder.append:(Ljava/lang/String;)Ljava/lang/StringBuilder;
      79: ldc           #65                 // String
      81: invokevirtual #47                 // Method java/lang/StringBuilder.append:(Ljava/lang/String;)Ljava/lang/StringBuilder;
      84: invokevirtual #52                 // Method java/lang/StringBuilder.toString:()Ljava/lang/String;
      87: astore        7
      89: invokestatic  #66                 // Method org/apache/http/entity/mime/FormBodyPartBuilder.create:()Lorg/apache/http/entity/mime/FormBodyPartBuilder;
      92: ldc           #67                 // String file
      94: invokevirtual #68                 // Method org/apache/http/entity/mime/FormBodyPartBuilder.setName:(Ljava/lang/String;)Lorg/apache/http/entity/mime/FormBodyPartBuilder;
      97: ldc           #69                 // String Content-Type
      99: aload_2
     100: invokeinterface #54,  1           // InterfaceMethod io/vertx/ext/web/FileUpload.contentType:()Ljava/lang/String;
     105: invokevirtual #70                 // Method org/apache/http/entity/mime/FormBodyPartBuilder.addField:(Ljava/lang/String;Ljava/lang/String;)Lorg/apache/http/entity/mime/FormBodyPartBuilder;
     108: ldc           #71                 // String Content-Transfer-Encoding
     110: aload_2
     111: invokeinterface #72,  1           // InterfaceMethod io/vertx/ext/web/FileUpload.contentTransferEncoding:()Ljava/lang/String;
     116: invokevirtual #70                 // Method org/apache/http/entity/mime/FormBodyPartBuilder.addField:(Ljava/lang/String;Ljava/lang/String;)Lorg/apache/http/entity/mime/FormBodyPartBuilder;
     119: ldc           #73                 // String Content-Disposition
     121: aload         7
     123: invokevirtual #70                 // Method org/apache/http/entity/mime/FormBodyPartBuilder.addField:(Ljava/lang/String;Ljava/lang/String;)Lorg/apache/http/entity/mime/FormBodyPartBuilder;
     126: aload         5
     128: invokevirtual #74                 // Method org/apache/http/entity/mime/FormBodyPartBuilder.setBody:(Lorg/apache/http/entity/mime/content/ContentBody;)Lorg/apache/http/entity/mime/FormBodyPartBuilder;
     131: invokevirtual #75                 // Method org/apache/http/entity/mime/FormBodyPartBuilder.build:()Lorg/apache/http/entity/mime/FormBodyPart;
     134: astore        8
     136: aload         6
     138: aload         8
     140: invokevirtual #76                 // Method org/apache/http/entity/mime/MultipartEntityBuilder.addPart:(Lorg/apache/http/entity/mime/FormBodyPart;)Lorg/apache/http/entity/mime/MultipartEntityBuilder;
     143: pop
     144: aload         6
     146: invokevirtual #77                 // Method org/apache/http/entity/mime/MultipartEntityBuilder.build:()Lorg/apache/http/HttpEntity;
     149: astore        9
     151: aload_1
     152: aload         9
     154: invokevirtual #78                 // Method org/apache/http/client/methods/HttpPost.setEntity:(Lorg/apache/http/HttpEntity;)V
     157: return

  private void processHeaders(org.apache.http.client.methods.HttpPost);
    Code:
       0: aload_0
       1: getfield      #4                  // Field request:Lio/vertx/core/http/HttpServerRequest;
       4: invokeinterface #79,  1           // InterfaceMethod io/vertx/core/http/HttpServerRequest.headers:()Lio/vertx/core/MultiMap;
       9: invokedynamic #80,  0             // InvokeDynamic #0:accept:()Ljava/util/function/Consumer;
      14: invokeinterface #81,  2           // InterfaceMethod io/vertx/core/MultiMap.forEach:(Ljava/util/function/Consumer;)V
      19: aload_0
      20: aload_1
      21: getstatic     #82                 // Field io/vertx/core/http/HttpHeaders.AUTHORIZATION:Ljava/lang/CharSequence;
      24: invokespecial #83                 // Method processHeader:(Lorg/apache/http/client/methods/HttpPost;Ljava/lang/CharSequence;)V
      27: aload_0
      28: aload_1
      29: getstatic     #84                 // Field io/vertx/core/http/HttpHeaders.CACHE_CONTROL:Ljava/lang/CharSequence;
      32: invokespecial #83                 // Method processHeader:(Lorg/apache/http/client/methods/HttpPost;Ljava/lang/CharSequence;)V
      35: aload_0
      36: aload_1
      37: getstatic     #85                 // Field io/vertx/core/http/HttpHeaders.ACCEPT:Ljava/lang/CharSequence;
      40: invokespecial #83                 // Method processHeader:(Lorg/apache/http/client/methods/HttpPost;Ljava/lang/CharSequence;)V
      43: aload_0
      44: aload_1
      45: getstatic     #86                 // Field io/vertx/core/http/HttpHeaders.CONNECTION:Ljava/lang/CharSequence;
      48: invokespecial #83                 // Method processHeader:(Lorg/apache/http/client/methods/HttpPost;Ljava/lang/CharSequence;)V
      51: aload_0
      52: aload_1
      53: getstatic     #87                 // Field io/vertx/core/http/HttpHeaders.ACCEPT_ENCODING:Ljava/lang/CharSequence;
      56: invokespecial #83                 // Method processHeader:(Lorg/apache/http/client/methods/HttpPost;Ljava/lang/CharSequence;)V
      59: return

  private void processHeader(org.apache.http.client.methods.HttpPost, java.lang.CharSequence);
    Code:
       0: aload_0
       1: getfield      #4                  // Field request:Lio/vertx/core/http/HttpServerRequest;
       4: invokeinterface #79,  1           // InterfaceMethod io/vertx/core/http/HttpServerRequest.headers:()Lio/vertx/core/MultiMap;
       9: aload_2
      10: invokeinterface #88,  2           // InterfaceMethod io/vertx/core/MultiMap.contains:(Ljava/lang/CharSequence;)Z
      15: ifeq          43
      18: aload_1
      19: aload_2
      20: invokeinterface #89,  1           // InterfaceMethod java/lang/CharSequence.toString:()Ljava/lang/String;
      25: aload_0
      26: getfield      #4                  // Field request:Lio/vertx/core/http/HttpServerRequest;
      29: invokeinterface #79,  1           // InterfaceMethod io/vertx/core/http/HttpServerRequest.headers:()Lio/vertx/core/MultiMap;
      34: aload_2
      35: invokeinterface #90,  2           // InterfaceMethod io/vertx/core/MultiMap.get:(Ljava/lang/CharSequence;)Ljava/lang/String;
      40: invokevirtual #91                 // Method org/apache/http/client/methods/HttpPost.setHeader:(Ljava/lang/String;Ljava/lang/String;)V
      43: return

  private io.vertx.ext.web.FileUpload getFile();
    Code:
       0: aload_0
       1: getfield      #2                  // Field context:Lio/vertx/ext/web/RoutingContext;
       4: invokeinterface #92,  1           // InterfaceMethod io/vertx/ext/web/RoutingContext.fileUploads:()Ljava/util/Set;
       9: astore_1
      10: aload_1
      11: invokeinterface #93,  1           // InterfaceMethod java/util/Set.isEmpty:()Z
      16: ifeq          21
      19: aconst_null
      20: areturn
      21: aload_1
      22: invokeinterface #94,  1           // InterfaceMethod java/util/Set.iterator:()Ljava/util/Iterator;
      27: invokeinterface #95,  1           // InterfaceMethod java/util/Iterator.next:()Ljava/lang/Object;
      32: checkcast     #96                 // class io/vertx/ext/web/FileUpload
      35: areturn

  private static void lambda$processHeaders$0(java.util.Map$Entry);
    Code:
       0: getstatic     #33                 // Field LOGGER:Lio/vertx/up/log/Annal;
       3: ldc           #97                 // String Client header: {0} = {1}
       5: iconst_2
       6: anewarray     #35                 // class java/lang/Object
       9: dup
      10: iconst_0
      11: aload_0
      12: invokeinterface #98,  1           // InterfaceMethod java/util/Map$Entry.getKey:()Ljava/lang/Object;
      17: aastore
      18: dup
      19: iconst_1
      20: aload_0
      21: invokeinterface #99,  1           // InterfaceMethod java/util/Map$Entry.getValue:()Ljava/lang/Object;
      26: aastore
      27: invokeinterface #38,  3           // InterfaceMethod io/vertx/up/log/Annal.info:(Ljava/lang/String;[Ljava/lang/Object;)V
      32: return

  static {};
    Code:
       0: ldc           #9                  // class io/vertx/up/uca/micro/discovery/multipart/UploadPipe
       2: invokestatic  #100                // InterfaceMethod io/vertx/up/log/Annal.get:(Ljava/lang/Class;)Lio/vertx/up/log/Annal;
       5: putstatic     #33                 // Field LOGGER:Lio/vertx/up/log/Annal;
       8: return
}
