Compiled from "Regex.kt"
final class kotlin.text.Regex$Serialized implements java.io.Serializable {
  public static final kotlin.text.Regex$Serialized$Companion Companion;

  private final java.lang.String pattern;

  private final int flags;

  private static final long serialVersionUID;

  public kotlin.text.Regex$Serialized(java.lang.String, int);
    Code:
       0: aload_1
       1: ldc           #11                 // String pattern
       3: invokestatic  #17                 // Method kotlin/jvm/internal/Intrinsics.checkNotNullParameter:(Ljava/lang/Object;Ljava/lang/String;)V
       6: aload_0
       7: invokespecial #20                 // Method java/lang/Object."<init>":()V
      10: aload_0
      11: aload_1
      12: putfield      #23                 // Field pattern:Ljava/lang/String;
      15: aload_0
      16: iload_2
      17: putfield      #27                 // Field flags:I
      20: return

  public final java.lang.String getPattern();
    Code:
       0: aload_0
       1: getfield      #23                 // Field pattern:Ljava/lang/String;
       4: areturn

  public final int getFlags();
    Code:
       0: aload_0
       1: getfield      #27                 // Field flags:I
       4: ireturn

  private final java.lang.Object readResolve();
    Code:
       0: new           #37                 // class kotlin/text/Regex
       3: dup
       4: aload_0
       5: getfield      #23                 // Field pattern:Ljava/lang/String;
       8: aload_0
       9: getfield      #27                 // Field flags:I
      12: invokestatic  #43                 // Method java/util/regex/Pattern.compile:(Ljava/lang/String;I)Ljava/util/regex/Pattern;
      15: astore_1
      16: aload_1
      17: ldc           #45                 // String compile(pattern, flags)
      19: invokestatic  #48                 // Method kotlin/jvm/internal/Intrinsics.checkNotNullExpressionValue:(Ljava/lang/Object;Ljava/lang/String;)V
      22: aload_1
      23: invokespecial #51                 // Method kotlin/text/Regex."<init>":(Ljava/util/regex/Pattern;)V
      26: areturn

  static {};
    Code:
       0: new           #54                 // class kotlin/text/Regex$Serialized$Companion
       3: dup
       4: aconst_null
       5: invokespecial #57                 // Method kotlin/text/Regex$Serialized$Companion."<init>":(Lkotlin/jvm/internal/DefaultConstructorMarker;)V
       8: putstatic     #61                 // Field Companion:Lkotlin/text/Regex$Serialized$Companion;
      11: return
}
