Compiled from "AbstractServerSocketAppender.java"
class ch.qos.logback.core.net.server.AbstractServerSocketAppender$1 implements ch.qos.logback.core.net.server.ClientVisitor<ch.qos.logback.core.net.server.RemoteReceiverClient> {
  final java.io.Serializable val$serEvent;

  final ch.qos.logback.core.net.server.AbstractServerSocketAppender this$0;

  ch.qos.logback.core.net.server.AbstractServerSocketAppender$1(ch.qos.logback.core.net.server.AbstractServerSocketAppender, java.io.Serializable);
    Code:
       0: aload_0
       1: aload_1
       2: putfield      #1                  // Field this$0:Lch/qos/logback/core/net/server/AbstractServerSocketAppender;
       5: aload_0
       6: aload_2
       7: putfield      #2                  // Field val$serEvent:Ljava/io/Serializable;
      10: aload_0
      11: invokespecial #3                  // Method java/lang/Object."<init>":()V
      14: return

  public void visit(ch.qos.logback.core.net.server.RemoteReceiverClient);
    Code:
       0: aload_1
       1: aload_0
       2: getfield      #2                  // Field val$serEvent:Ljava/io/Serializable;
       5: invokeinterface #4,  2            // InterfaceMethod ch/qos/logback/core/net/server/RemoteReceiverClient.offer:(Ljava/io/Serializable;)Z
      10: pop
      11: return

  public void visit(ch.qos.logback.core.net.server.Client);
    Code:
       0: aload_0
       1: aload_1
       2: checkcast     #5                  // class ch/qos/logback/core/net/server/RemoteReceiverClient
       5: invokevirtual #6                  // Method visit:(Lch/qos/logback/core/net/server/RemoteReceiverClient;)V
       8: return
}
