Compiled from "CreateLicenseConversionTaskForResourceRequest.java"
public interface software.amazon.awssdk.services.licensemanager.model.CreateLicenseConversionTaskForResourceRequest$Builder extends software.amazon.awssdk.services.licensemanager.model.LicenseManagerRequest$Builder, software.amazon.awssdk.core.SdkPojo, software.amazon.awssdk.utils.builder.CopyableBuilder<software.amazon.awssdk.services.licensemanager.model.CreateLicenseConversionTaskForResourceRequest$Builder, software.amazon.awssdk.services.licensemanager.model.CreateLicenseConversionTaskForResourceRequest> {
  public abstract software.amazon.awssdk.services.licensemanager.model.CreateLicenseConversionTaskForResourceRequest$Builder resourceArn(java.lang.String);

  public abstract software.amazon.awssdk.services.licensemanager.model.CreateLicenseConversionTaskForResourceRequest$Builder sourceLicenseContext(software.amazon.awssdk.services.licensemanager.model.LicenseConversionContext);

  public default software.amazon.awssdk.services.licensemanager.model.CreateLicenseConversionTaskForResourceRequest$Builder sourceLicenseContext(java.util.function.Consumer<software.amazon.awssdk.services.licensemanager.model.LicenseConversionContext$Builder>);
    Code:
       0: aload_0
       1: invokestatic  #1                  // Method software/amazon/awssdk/services/licensemanager/model/LicenseConversionContext.builder:()Lsoftware/amazon/awssdk/services/licensemanager/model/LicenseConversionContext$Builder;
       4: aload_1
       5: invokeinterface #2,  2            // InterfaceMethod software/amazon/awssdk/services/licensemanager/model/LicenseConversionContext$Builder.applyMutation:(Ljava/util/function/Consumer;)Lsoftware/amazon/awssdk/utils/builder/SdkBuilder;
      10: checkcast     #3                  // class software/amazon/awssdk/services/licensemanager/model/LicenseConversionContext$Builder
      13: invokeinterface #4,  1            // InterfaceMethod software/amazon/awssdk/services/licensemanager/model/LicenseConversionContext$Builder.build:()Ljava/lang/Object;
      18: checkcast     #5                  // class software/amazon/awssdk/services/licensemanager/model/LicenseConversionContext
      21: invokeinterface #6,  2            // InterfaceMethod sourceLicenseContext:(Lsoftware/amazon/awssdk/services/licensemanager/model/LicenseConversionContext;)Lsoftware/amazon/awssdk/services/licensemanager/model/CreateLicenseConversionTaskForResourceRequest$Builder;
      26: areturn

  public abstract software.amazon.awssdk.services.licensemanager.model.CreateLicenseConversionTaskForResourceRequest$Builder destinationLicenseContext(software.amazon.awssdk.services.licensemanager.model.LicenseConversionContext);

  public default software.amazon.awssdk.services.licensemanager.model.CreateLicenseConversionTaskForResourceRequest$Builder destinationLicenseContext(java.util.function.Consumer<software.amazon.awssdk.services.licensemanager.model.LicenseConversionContext$Builder>);
    Code:
       0: aload_0
       1: invokestatic  #1                  // Method software/amazon/awssdk/services/licensemanager/model/LicenseConversionContext.builder:()Lsoftware/amazon/awssdk/services/licensemanager/model/LicenseConversionContext$Builder;
       4: aload_1
       5: invokeinterface #2,  2            // InterfaceMethod software/amazon/awssdk/services/licensemanager/model/LicenseConversionContext$Builder.applyMutation:(Ljava/util/function/Consumer;)Lsoftware/amazon/awssdk/utils/builder/SdkBuilder;
      10: checkcast     #3                  // class software/amazon/awssdk/services/licensemanager/model/LicenseConversionContext$Builder
      13: invokeinterface #4,  1            // InterfaceMethod software/amazon/awssdk/services/licensemanager/model/LicenseConversionContext$Builder.build:()Ljava/lang/Object;
      18: checkcast     #5                  // class software/amazon/awssdk/services/licensemanager/model/LicenseConversionContext
      21: invokeinterface #7,  2            // InterfaceMethod destinationLicenseContext:(Lsoftware/amazon/awssdk/services/licensemanager/model/LicenseConversionContext;)Lsoftware/amazon/awssdk/services/licensemanager/model/CreateLicenseConversionTaskForResourceRequest$Builder;
      26: areturn

  public abstract software.amazon.awssdk.services.licensemanager.model.CreateLicenseConversionTaskForResourceRequest$Builder overrideConfiguration(software.amazon.awssdk.awscore.AwsRequestOverrideConfiguration);

  public abstract software.amazon.awssdk.services.licensemanager.model.CreateLicenseConversionTaskForResourceRequest$Builder overrideConfiguration(java.util.function.Consumer<software.amazon.awssdk.awscore.AwsRequestOverrideConfiguration$Builder>);

  public default software.amazon.awssdk.awscore.AwsRequest$Builder overrideConfiguration(java.util.function.Consumer);
    Code:
       0: aload_0
       1: aload_1
       2: invokeinterface #8,  2            // InterfaceMethod overrideConfiguration:(Ljava/util/function/Consumer;)Lsoftware/amazon/awssdk/services/licensemanager/model/CreateLicenseConversionTaskForResourceRequest$Builder;
       7: areturn

  public default software.amazon.awssdk.awscore.AwsRequest$Builder overrideConfiguration(software.amazon.awssdk.awscore.AwsRequestOverrideConfiguration);
    Code:
       0: aload_0
       1: aload_1
       2: invokeinterface #9,  2            // InterfaceMethod overrideConfiguration:(Lsoftware/amazon/awssdk/awscore/AwsRequestOverrideConfiguration;)Lsoftware/amazon/awssdk/services/licensemanager/model/CreateLicenseConversionTaskForResourceRequest$Builder;
       7: areturn
}
