Compiled from "GetLicenseUsageResponse.java"
public interface software.amazon.awssdk.services.licensemanager.model.GetLicenseUsageResponse$Builder extends software.amazon.awssdk.services.licensemanager.model.LicenseManagerResponse$Builder, software.amazon.awssdk.core.SdkPojo, software.amazon.awssdk.utils.builder.CopyableBuilder<software.amazon.awssdk.services.licensemanager.model.GetLicenseUsageResponse$Builder, software.amazon.awssdk.services.licensemanager.model.GetLicenseUsageResponse> {
  public abstract software.amazon.awssdk.services.licensemanager.model.GetLicenseUsageResponse$Builder licenseUsage(software.amazon.awssdk.services.licensemanager.model.LicenseUsage);

  public default software.amazon.awssdk.services.licensemanager.model.GetLicenseUsageResponse$Builder licenseUsage(java.util.function.Consumer<software.amazon.awssdk.services.licensemanager.model.LicenseUsage$Builder>);
    Code:
       0: aload_0
       1: invokestatic  #1                  // Method software/amazon/awssdk/services/licensemanager/model/LicenseUsage.builder:()Lsoftware/amazon/awssdk/services/licensemanager/model/LicenseUsage$Builder;
       4: aload_1
       5: invokeinterface #2,  2            // InterfaceMethod software/amazon/awssdk/services/licensemanager/model/LicenseUsage$Builder.applyMutation:(Ljava/util/function/Consumer;)Lsoftware/amazon/awssdk/utils/builder/SdkBuilder;
      10: checkcast     #3                  // class software/amazon/awssdk/services/licensemanager/model/LicenseUsage$Builder
      13: invokeinterface #4,  1            // InterfaceMethod software/amazon/awssdk/services/licensemanager/model/LicenseUsage$Builder.build:()Ljava/lang/Object;
      18: checkcast     #5                  // class software/amazon/awssdk/services/licensemanager/model/LicenseUsage
      21: invokeinterface #6,  2            // InterfaceMethod licenseUsage:(Lsoftware/amazon/awssdk/services/licensemanager/model/LicenseUsage;)Lsoftware/amazon/awssdk/services/licensemanager/model/GetLicenseUsageResponse$Builder;
      26: areturn
}
