Compiled from "GetServiceSettingsResponse.java"
public interface software.amazon.awssdk.services.licensemanager.model.GetServiceSettingsResponse$Builder extends software.amazon.awssdk.services.licensemanager.model.LicenseManagerResponse$Builder, software.amazon.awssdk.core.SdkPojo, software.amazon.awssdk.utils.builder.CopyableBuilder<software.amazon.awssdk.services.licensemanager.model.GetServiceSettingsResponse$Builder, software.amazon.awssdk.services.licensemanager.model.GetServiceSettingsResponse> {
  public abstract software.amazon.awssdk.services.licensemanager.model.GetServiceSettingsResponse$Builder s3BucketArn(java.lang.String);

  public abstract software.amazon.awssdk.services.licensemanager.model.GetServiceSettingsResponse$Builder snsTopicArn(java.lang.String);

  public abstract software.amazon.awssdk.services.licensemanager.model.GetServiceSettingsResponse$Builder organizationConfiguration(software.amazon.awssdk.services.licensemanager.model.OrganizationConfiguration);

  public default software.amazon.awssdk.services.licensemanager.model.GetServiceSettingsResponse$Builder organizationConfiguration(java.util.function.Consumer<software.amazon.awssdk.services.licensemanager.model.OrganizationConfiguration$Builder>);
    Code:
       0: aload_0
       1: invokestatic  #1                  // Method software/amazon/awssdk/services/licensemanager/model/OrganizationConfiguration.builder:()Lsoftware/amazon/awssdk/services/licensemanager/model/OrganizationConfiguration$Builder;
       4: aload_1
       5: invokeinterface #2,  2            // InterfaceMethod software/amazon/awssdk/services/licensemanager/model/OrganizationConfiguration$Builder.applyMutation:(Ljava/util/function/Consumer;)Lsoftware/amazon/awssdk/utils/builder/SdkBuilder;
      10: checkcast     #3                  // class software/amazon/awssdk/services/licensemanager/model/OrganizationConfiguration$Builder
      13: invokeinterface #4,  1            // InterfaceMethod software/amazon/awssdk/services/licensemanager/model/OrganizationConfiguration$Builder.build:()Ljava/lang/Object;
      18: checkcast     #5                  // class software/amazon/awssdk/services/licensemanager/model/OrganizationConfiguration
      21: invokeinterface #6,  2            // InterfaceMethod organizationConfiguration:(Lsoftware/amazon/awssdk/services/licensemanager/model/OrganizationConfiguration;)Lsoftware/amazon/awssdk/services/licensemanager/model/GetServiceSettingsResponse$Builder;
      26: areturn

  public abstract software.amazon.awssdk.services.licensemanager.model.GetServiceSettingsResponse$Builder enableCrossAccountsDiscovery(java.lang.Boolean);

  public abstract software.amazon.awssdk.services.licensemanager.model.GetServiceSettingsResponse$Builder licenseManagerResourceShareArn(java.lang.String);
}
