Compiled from "ReportGenerator.java"
public final class software.amazon.awssdk.services.licensemanager.model.ReportGenerator implements software.amazon.awssdk.core.SdkPojo, java.io.Serializable, software.amazon.awssdk.utils.builder.ToCopyableBuilder<software.amazon.awssdk.services.licensemanager.model.ReportGenerator$Builder, software.amazon.awssdk.services.licensemanager.model.ReportGenerator> {
  private static final software.amazon.awssdk.core.SdkField<java.lang.String> REPORT_GENERATOR_NAME_FIELD;

  private static final software.amazon.awssdk.core.SdkField<java.util.List<java.lang.String>> REPORT_TYPE_FIELD;

  private static final software.amazon.awssdk.core.SdkField<software.amazon.awssdk.services.licensemanager.model.ReportContext> REPORT_CONTEXT_FIELD;

  private static final software.amazon.awssdk.core.SdkField<software.amazon.awssdk.services.licensemanager.model.ReportFrequency> REPORT_FREQUENCY_FIELD;

  private static final software.amazon.awssdk.core.SdkField<java.lang.String> LICENSE_MANAGER_REPORT_GENERATOR_ARN_FIELD;

  private static final software.amazon.awssdk.core.SdkField<java.lang.String> LAST_RUN_STATUS_FIELD;

  private static final software.amazon.awssdk.core.SdkField<java.lang.String> LAST_RUN_FAILURE_REASON_FIELD;

  private static final software.amazon.awssdk.core.SdkField<java.lang.String> LAST_REPORT_GENERATION_TIME_FIELD;

  private static final software.amazon.awssdk.core.SdkField<java.lang.String> REPORT_CREATOR_ACCOUNT_FIELD;

  private static final software.amazon.awssdk.core.SdkField<java.lang.String> DESCRIPTION_FIELD;

  private static final software.amazon.awssdk.core.SdkField<software.amazon.awssdk.services.licensemanager.model.S3Location> S3_LOCATION_FIELD;

  private static final software.amazon.awssdk.core.SdkField<java.lang.String> CREATE_TIME_FIELD;

  private static final software.amazon.awssdk.core.SdkField<java.util.List<software.amazon.awssdk.services.licensemanager.model.Tag>> TAGS_FIELD;

  private static final java.util.List<software.amazon.awssdk.core.SdkField<?>> SDK_FIELDS;

  private static final long serialVersionUID;

  private final java.lang.String reportGeneratorName;

  private final java.util.List<java.lang.String> reportType;

  private final software.amazon.awssdk.services.licensemanager.model.ReportContext reportContext;

  private final software.amazon.awssdk.services.licensemanager.model.ReportFrequency reportFrequency;

  private final java.lang.String licenseManagerReportGeneratorArn;

  private final java.lang.String lastRunStatus;

  private final java.lang.String lastRunFailureReason;

  private final java.lang.String lastReportGenerationTime;

  private final java.lang.String reportCreatorAccount;

  private final java.lang.String description;

  private final software.amazon.awssdk.services.licensemanager.model.S3Location s3Location;

  private final java.lang.String createTime;

  private final java.util.List<software.amazon.awssdk.services.licensemanager.model.Tag> tags;

  private software.amazon.awssdk.services.licensemanager.model.ReportGenerator(software.amazon.awssdk.services.licensemanager.model.ReportGenerator$BuilderImpl);
    Code:
       0: aload_0
       1: invokespecial #16                 // Method java/lang/Object."<init>":()V
       4: aload_0
       5: aload_1
       6: invokestatic  #17                 // Method software/amazon/awssdk/services/licensemanager/model/ReportGenerator$BuilderImpl.access$000:(Lsoftware/amazon/awssdk/services/licensemanager/model/ReportGenerator$BuilderImpl;)Ljava/lang/String;
       9: putfield      #15                 // Field reportGeneratorName:Ljava/lang/String;
      12: aload_0
      13: aload_1
      14: invokestatic  #18                 // Method software/amazon/awssdk/services/licensemanager/model/ReportGenerator$BuilderImpl.access$100:(Lsoftware/amazon/awssdk/services/licensemanager/model/ReportGenerator$BuilderImpl;)Ljava/util/List;
      17: putfield      #14                 // Field reportType:Ljava/util/List;
      20: aload_0
      21: aload_1
      22: invokestatic  #19                 // Method software/amazon/awssdk/services/licensemanager/model/ReportGenerator$BuilderImpl.access$200:(Lsoftware/amazon/awssdk/services/licensemanager/model/ReportGenerator$BuilderImpl;)Lsoftware/amazon/awssdk/services/licensemanager/model/ReportContext;
      25: putfield      #13                 // Field reportContext:Lsoftware/amazon/awssdk/services/licensemanager/model/ReportContext;
      28: aload_0
      29: aload_1
      30: invokestatic  #20                 // Method software/amazon/awssdk/services/licensemanager/model/ReportGenerator$BuilderImpl.access$300:(Lsoftware/amazon/awssdk/services/licensemanager/model/ReportGenerator$BuilderImpl;)Lsoftware/amazon/awssdk/services/licensemanager/model/ReportFrequency;
      33: putfield      #12                 // Field reportFrequency:Lsoftware/amazon/awssdk/services/licensemanager/model/ReportFrequency;
      36: aload_0
      37: aload_1
      38: invokestatic  #21                 // Method software/amazon/awssdk/services/licensemanager/model/ReportGenerator$BuilderImpl.access$400:(Lsoftware/amazon/awssdk/services/licensemanager/model/ReportGenerator$BuilderImpl;)Ljava/lang/String;
      41: putfield      #11                 // Field licenseManagerReportGeneratorArn:Ljava/lang/String;
      44: aload_0
      45: aload_1
      46: invokestatic  #22                 // Method software/amazon/awssdk/services/licensemanager/model/ReportGenerator$BuilderImpl.access$500:(Lsoftware/amazon/awssdk/services/licensemanager/model/ReportGenerator$BuilderImpl;)Ljava/lang/String;
      49: putfield      #10                 // Field lastRunStatus:Ljava/lang/String;
      52: aload_0
      53: aload_1
      54: invokestatic  #23                 // Method software/amazon/awssdk/services/licensemanager/model/ReportGenerator$BuilderImpl.access$600:(Lsoftware/amazon/awssdk/services/licensemanager/model/ReportGenerator$BuilderImpl;)Ljava/lang/String;
      57: putfield      #9                  // Field lastRunFailureReason:Ljava/lang/String;
      60: aload_0
      61: aload_1
      62: invokestatic  #24                 // Method software/amazon/awssdk/services/licensemanager/model/ReportGenerator$BuilderImpl.access$700:(Lsoftware/amazon/awssdk/services/licensemanager/model/ReportGenerator$BuilderImpl;)Ljava/lang/String;
      65: putfield      #8                  // Field lastReportGenerationTime:Ljava/lang/String;
      68: aload_0
      69: aload_1
      70: invokestatic  #25                 // Method software/amazon/awssdk/services/licensemanager/model/ReportGenerator$BuilderImpl.access$800:(Lsoftware/amazon/awssdk/services/licensemanager/model/ReportGenerator$BuilderImpl;)Ljava/lang/String;
      73: putfield      #7                  // Field reportCreatorAccount:Ljava/lang/String;
      76: aload_0
      77: aload_1
      78: invokestatic  #26                 // Method software/amazon/awssdk/services/licensemanager/model/ReportGenerator$BuilderImpl.access$900:(Lsoftware/amazon/awssdk/services/licensemanager/model/ReportGenerator$BuilderImpl;)Ljava/lang/String;
      81: putfield      #6                  // Field description:Ljava/lang/String;
      84: aload_0
      85: aload_1
      86: invokestatic  #27                 // Method software/amazon/awssdk/services/licensemanager/model/ReportGenerator$BuilderImpl.access$1000:(Lsoftware/amazon/awssdk/services/licensemanager/model/ReportGenerator$BuilderImpl;)Lsoftware/amazon/awssdk/services/licensemanager/model/S3Location;
      89: putfield      #5                  // Field s3Location:Lsoftware/amazon/awssdk/services/licensemanager/model/S3Location;
      92: aload_0
      93: aload_1
      94: invokestatic  #28                 // Method software/amazon/awssdk/services/licensemanager/model/ReportGenerator$BuilderImpl.access$1100:(Lsoftware/amazon/awssdk/services/licensemanager/model/ReportGenerator$BuilderImpl;)Ljava/lang/String;
      97: putfield      #4                  // Field createTime:Ljava/lang/String;
     100: aload_0
     101: aload_1
     102: invokestatic  #29                 // Method software/amazon/awssdk/services/licensemanager/model/ReportGenerator$BuilderImpl.access$1200:(Lsoftware/amazon/awssdk/services/licensemanager/model/ReportGenerator$BuilderImpl;)Ljava/util/List;
     105: putfield      #3                  // Field tags:Ljava/util/List;
     108: return

  public final java.lang.String reportGeneratorName();
    Code:
       0: aload_0
       1: getfield      #15                 // Field reportGeneratorName:Ljava/lang/String;
       4: areturn

  public final java.util.List<software.amazon.awssdk.services.licensemanager.model.ReportType> reportType();
    Code:
       0: aload_0
       1: getfield      #14                 // Field reportType:Ljava/util/List;
       4: invokestatic  #30                 // Method software/amazon/awssdk/services/licensemanager/model/ReportTypeListCopier.copyStringToEnum:(Ljava/util/Collection;)Ljava/util/List;
       7: areturn

  public final boolean hasReportType();
    Code:
       0: aload_0
       1: getfield      #14                 // Field reportType:Ljava/util/List;
       4: ifnull        21
       7: aload_0
       8: getfield      #14                 // Field reportType:Ljava/util/List;
      11: instanceof    #31                 // class software/amazon/awssdk/core/util/SdkAutoConstructList
      14: ifne          21
      17: iconst_1
      18: goto          22
      21: iconst_0
      22: ireturn

  public final java.util.List<java.lang.String> reportTypeAsStrings();
    Code:
       0: aload_0
       1: getfield      #14                 // Field reportType:Ljava/util/List;
       4: areturn

  public final software.amazon.awssdk.services.licensemanager.model.ReportContext reportContext();
    Code:
       0: aload_0
       1: getfield      #13                 // Field reportContext:Lsoftware/amazon/awssdk/services/licensemanager/model/ReportContext;
       4: areturn

  public final software.amazon.awssdk.services.licensemanager.model.ReportFrequency reportFrequency();
    Code:
       0: aload_0
       1: getfield      #12                 // Field reportFrequency:Lsoftware/amazon/awssdk/services/licensemanager/model/ReportFrequency;
       4: areturn

  public final java.lang.String licenseManagerReportGeneratorArn();
    Code:
       0: aload_0
       1: getfield      #11                 // Field licenseManagerReportGeneratorArn:Ljava/lang/String;
       4: areturn

  public final java.lang.String lastRunStatus();
    Code:
       0: aload_0
       1: getfield      #10                 // Field lastRunStatus:Ljava/lang/String;
       4: areturn

  public final java.lang.String lastRunFailureReason();
    Code:
       0: aload_0
       1: getfield      #9                  // Field lastRunFailureReason:Ljava/lang/String;
       4: areturn

  public final java.lang.String lastReportGenerationTime();
    Code:
       0: aload_0
       1: getfield      #8                  // Field lastReportGenerationTime:Ljava/lang/String;
       4: areturn

  public final java.lang.String reportCreatorAccount();
    Code:
       0: aload_0
       1: getfield      #7                  // Field reportCreatorAccount:Ljava/lang/String;
       4: areturn

  public final java.lang.String description();
    Code:
       0: aload_0
       1: getfield      #6                  // Field description:Ljava/lang/String;
       4: areturn

  public final software.amazon.awssdk.services.licensemanager.model.S3Location s3Location();
    Code:
       0: aload_0
       1: getfield      #5                  // Field s3Location:Lsoftware/amazon/awssdk/services/licensemanager/model/S3Location;
       4: areturn

  public final java.lang.String createTime();
    Code:
       0: aload_0
       1: getfield      #4                  // Field createTime:Ljava/lang/String;
       4: areturn

  public final boolean hasTags();
    Code:
       0: aload_0
       1: getfield      #3                  // Field tags:Ljava/util/List;
       4: ifnull        21
       7: aload_0
       8: getfield      #3                  // Field tags:Ljava/util/List;
      11: instanceof    #31                 // class software/amazon/awssdk/core/util/SdkAutoConstructList
      14: ifne          21
      17: iconst_1
      18: goto          22
      21: iconst_0
      22: ireturn

  public final java.util.List<software.amazon.awssdk.services.licensemanager.model.Tag> tags();
    Code:
       0: aload_0
       1: getfield      #3                  // Field tags:Ljava/util/List;
       4: areturn

  public software.amazon.awssdk.services.licensemanager.model.ReportGenerator$Builder toBuilder();
    Code:
       0: new           #32                 // class software/amazon/awssdk/services/licensemanager/model/ReportGenerator$BuilderImpl
       3: dup
       4: aload_0
       5: aconst_null
       6: invokespecial #33                 // Method software/amazon/awssdk/services/licensemanager/model/ReportGenerator$BuilderImpl."<init>":(Lsoftware/amazon/awssdk/services/licensemanager/model/ReportGenerator;Lsoftware/amazon/awssdk/services/licensemanager/model/ReportGenerator$1;)V
       9: areturn

  public static software.amazon.awssdk.services.licensemanager.model.ReportGenerator$Builder builder();
    Code:
       0: new           #32                 // class software/amazon/awssdk/services/licensemanager/model/ReportGenerator$BuilderImpl
       3: dup
       4: aconst_null
       5: invokespecial #34                 // Method software/amazon/awssdk/services/licensemanager/model/ReportGenerator$BuilderImpl."<init>":(Lsoftware/amazon/awssdk/services/licensemanager/model/ReportGenerator$1;)V
       8: areturn

  public static java.lang.Class<? extends software.amazon.awssdk.services.licensemanager.model.ReportGenerator$Builder> serializableBuilderClass();
    Code:
       0: ldc           #32                 // class software/amazon/awssdk/services/licensemanager/model/ReportGenerator$BuilderImpl
       2: areturn

  public final int hashCode();
    Code:
       0: iconst_1
       1: istore_1
       2: bipush        31
       4: iload_1
       5: imul
       6: aload_0
       7: invokevirtual #35                 // Method reportGeneratorName:()Ljava/lang/String;
      10: invokestatic  #36                 // Method java/util/Objects.hashCode:(Ljava/lang/Object;)I
      13: iadd
      14: istore_1
      15: bipush        31
      17: iload_1
      18: imul
      19: aload_0
      20: invokevirtual #37                 // Method hasReportType:()Z
      23: ifeq          33
      26: aload_0
      27: invokevirtual #38                 // Method reportTypeAsStrings:()Ljava/util/List;
      30: goto          34
      33: aconst_null
      34: invokestatic  #36                 // Method java/util/Objects.hashCode:(Ljava/lang/Object;)I
      37: iadd
      38: istore_1
      39: bipush        31
      41: iload_1
      42: imul
      43: aload_0
      44: invokevirtual #39                 // Method reportContext:()Lsoftware/amazon/awssdk/services/licensemanager/model/ReportContext;
      47: invokestatic  #36                 // Method java/util/Objects.hashCode:(Ljava/lang/Object;)I
      50: iadd
      51: istore_1
      52: bipush        31
      54: iload_1
      55: imul
      56: aload_0
      57: invokevirtual #40                 // Method reportFrequency:()Lsoftware/amazon/awssdk/services/licensemanager/model/ReportFrequency;
      60: invokestatic  #36                 // Method java/util/Objects.hashCode:(Ljava/lang/Object;)I
      63: iadd
      64: istore_1
      65: bipush        31
      67: iload_1
      68: imul
      69: aload_0
      70: invokevirtual #41                 // Method licenseManagerReportGeneratorArn:()Ljava/lang/String;
      73: invokestatic  #36                 // Method java/util/Objects.hashCode:(Ljava/lang/Object;)I
      76: iadd
      77: istore_1
      78: bipush        31
      80: iload_1
      81: imul
      82: aload_0
      83: invokevirtual #42                 // Method lastRunStatus:()Ljava/lang/String;
      86: invokestatic  #36                 // Method java/util/Objects.hashCode:(Ljava/lang/Object;)I
      89: iadd
      90: istore_1
      91: bipush        31
      93: iload_1
      94: imul
      95: aload_0
      96: invokevirtual #43                 // Method lastRunFailureReason:()Ljava/lang/String;
      99: invokestatic  #36                 // Method java/util/Objects.hashCode:(Ljava/lang/Object;)I
     102: iadd
     103: istore_1
     104: bipush        31
     106: iload_1
     107: imul
     108: aload_0
     109: invokevirtual #44                 // Method lastReportGenerationTime:()Ljava/lang/String;
     112: invokestatic  #36                 // Method java/util/Objects.hashCode:(Ljava/lang/Object;)I
     115: iadd
     116: istore_1
     117: bipush        31
     119: iload_1
     120: imul
     121: aload_0
     122: invokevirtual #45                 // Method reportCreatorAccount:()Ljava/lang/String;
     125: invokestatic  #36                 // Method java/util/Objects.hashCode:(Ljava/lang/Object;)I
     128: iadd
     129: istore_1
     130: bipush        31
     132: iload_1
     133: imul
     134: aload_0
     135: invokevirtual #46                 // Method description:()Ljava/lang/String;
     138: invokestatic  #36                 // Method java/util/Objects.hashCode:(Ljava/lang/Object;)I
     141: iadd
     142: istore_1
     143: bipush        31
     145: iload_1
     146: imul
     147: aload_0
     148: invokevirtual #47                 // Method s3Location:()Lsoftware/amazon/awssdk/services/licensemanager/model/S3Location;
     151: invokestatic  #36                 // Method java/util/Objects.hashCode:(Ljava/lang/Object;)I
     154: iadd
     155: istore_1
     156: bipush        31
     158: iload_1
     159: imul
     160: aload_0
     161: invokevirtual #48                 // Method createTime:()Ljava/lang/String;
     164: invokestatic  #36                 // Method java/util/Objects.hashCode:(Ljava/lang/Object;)I
     167: iadd
     168: istore_1
     169: bipush        31
     171: iload_1
     172: imul
     173: aload_0
     174: invokevirtual #49                 // Method hasTags:()Z
     177: ifeq          187
     180: aload_0
     181: invokevirtual #50                 // Method tags:()Ljava/util/List;
     184: goto          188
     187: aconst_null
     188: invokestatic  #36                 // Method java/util/Objects.hashCode:(Ljava/lang/Object;)I
     191: iadd
     192: istore_1
     193: iload_1
     194: ireturn

  public final boolean equals(java.lang.Object);
    Code:
       0: aload_0
       1: aload_1
       2: invokevirtual #51                 // Method equalsBySdkFields:(Ljava/lang/Object;)Z
       5: ireturn

  public final boolean equalsBySdkFields(java.lang.Object);
    Code:
       0: aload_0
       1: aload_1
       2: if_acmpne     7
       5: iconst_1
       6: ireturn
       7: aload_1
       8: ifnonnull     13
      11: iconst_0
      12: ireturn
      13: aload_1
      14: instanceof    #52                 // class software/amazon/awssdk/services/licensemanager/model/ReportGenerator
      17: ifne          22
      20: iconst_0
      21: ireturn
      22: aload_1
      23: checkcast     #52                 // class software/amazon/awssdk/services/licensemanager/model/ReportGenerator
      26: astore_2
      27: aload_0
      28: invokevirtual #35                 // Method reportGeneratorName:()Ljava/lang/String;
      31: aload_2
      32: invokevirtual #35                 // Method reportGeneratorName:()Ljava/lang/String;
      35: invokestatic  #53                 // Method java/util/Objects.equals:(Ljava/lang/Object;Ljava/lang/Object;)Z
      38: ifeq          235
      41: aload_0
      42: invokevirtual #37                 // Method hasReportType:()Z
      45: aload_2
      46: invokevirtual #37                 // Method hasReportType:()Z
      49: if_icmpne     235
      52: aload_0
      53: invokevirtual #38                 // Method reportTypeAsStrings:()Ljava/util/List;
      56: aload_2
      57: invokevirtual #38                 // Method reportTypeAsStrings:()Ljava/util/List;
      60: invokestatic  #53                 // Method java/util/Objects.equals:(Ljava/lang/Object;Ljava/lang/Object;)Z
      63: ifeq          235
      66: aload_0
      67: invokevirtual #39                 // Method reportContext:()Lsoftware/amazon/awssdk/services/licensemanager/model/ReportContext;
      70: aload_2
      71: invokevirtual #39                 // Method reportContext:()Lsoftware/amazon/awssdk/services/licensemanager/model/ReportContext;
      74: invokestatic  #53                 // Method java/util/Objects.equals:(Ljava/lang/Object;Ljava/lang/Object;)Z
      77: ifeq          235
      80: aload_0
      81: invokevirtual #40                 // Method reportFrequency:()Lsoftware/amazon/awssdk/services/licensemanager/model/ReportFrequency;
      84: aload_2
      85: invokevirtual #40                 // Method reportFrequency:()Lsoftware/amazon/awssdk/services/licensemanager/model/ReportFrequency;
      88: invokestatic  #53                 // Method java/util/Objects.equals:(Ljava/lang/Object;Ljava/lang/Object;)Z
      91: ifeq          235
      94: aload_0
      95: invokevirtual #41                 // Method licenseManagerReportGeneratorArn:()Ljava/lang/String;
      98: aload_2
      99: invokevirtual #41                 // Method licenseManagerReportGeneratorArn:()Ljava/lang/String;
     102: invokestatic  #53                 // Method java/util/Objects.equals:(Ljava/lang/Object;Ljava/lang/Object;)Z
     105: ifeq          235
     108: aload_0
     109: invokevirtual #42                 // Method lastRunStatus:()Ljava/lang/String;
     112: aload_2
     113: invokevirtual #42                 // Method lastRunStatus:()Ljava/lang/String;
     116: invokestatic  #53                 // Method java/util/Objects.equals:(Ljava/lang/Object;Ljava/lang/Object;)Z
     119: ifeq          235
     122: aload_0
     123: invokevirtual #43                 // Method lastRunFailureReason:()Ljava/lang/String;
     126: aload_2
     127: invokevirtual #43                 // Method lastRunFailureReason:()Ljava/lang/String;
     130: invokestatic  #53                 // Method java/util/Objects.equals:(Ljava/lang/Object;Ljava/lang/Object;)Z
     133: ifeq          235
     136: aload_0
     137: invokevirtual #44                 // Method lastReportGenerationTime:()Ljava/lang/String;
     140: aload_2
     141: invokevirtual #44                 // Method lastReportGenerationTime:()Ljava/lang/String;
     144: invokestatic  #53                 // Method java/util/Objects.equals:(Ljava/lang/Object;Ljava/lang/Object;)Z
     147: ifeq          235
     150: aload_0
     151: invokevirtual #45                 // Method reportCreatorAccount:()Ljava/lang/String;
     154: aload_2
     155: invokevirtual #45                 // Method reportCreatorAccount:()Ljava/lang/String;
     158: invokestatic  #53                 // Method java/util/Objects.equals:(Ljava/lang/Object;Ljava/lang/Object;)Z
     161: ifeq          235
     164: aload_0
     165: invokevirtual #46                 // Method description:()Ljava/lang/String;
     168: aload_2
     169: invokevirtual #46                 // Method description:()Ljava/lang/String;
     172: invokestatic  #53                 // Method java/util/Objects.equals:(Ljava/lang/Object;Ljava/lang/Object;)Z
     175: ifeq          235
     178: aload_0
     179: invokevirtual #47                 // Method s3Location:()Lsoftware/amazon/awssdk/services/licensemanager/model/S3Location;
     182: aload_2
     183: invokevirtual #47                 // Method s3Location:()Lsoftware/amazon/awssdk/services/licensemanager/model/S3Location;
     186: invokestatic  #53                 // Method java/util/Objects.equals:(Ljava/lang/Object;Ljava/lang/Object;)Z
     189: ifeq          235
     192: aload_0
     193: invokevirtual #48                 // Method createTime:()Ljava/lang/String;
     196: aload_2
     197: invokevirtual #48                 // Method createTime:()Ljava/lang/String;
     200: invokestatic  #53                 // Method java/util/Objects.equals:(Ljava/lang/Object;Ljava/lang/Object;)Z
     203: ifeq          235
     206: aload_0
     207: invokevirtual #49                 // Method hasTags:()Z
     210: aload_2
     211: invokevirtual #49                 // Method hasTags:()Z
     214: if_icmpne     235
     217: aload_0
     218: invokevirtual #50                 // Method tags:()Ljava/util/List;
     221: aload_2
     222: invokevirtual #50                 // Method tags:()Ljava/util/List;
     225: invokestatic  #53                 // Method java/util/Objects.equals:(Ljava/lang/Object;Ljava/lang/Object;)Z
     228: ifeq          235
     231: iconst_1
     232: goto          236
     235: iconst_0
     236: ireturn

  public final java.lang.String toString();
    Code:
       0: ldc           #54                 // String ReportGenerator
       2: invokestatic  #55                 // Method software/amazon/awssdk/utils/ToString.builder:(Ljava/lang/String;)Lsoftware/amazon/awssdk/utils/ToString;
       5: ldc           #56                 // String ReportGeneratorName
       7: aload_0
       8: invokevirtual #35                 // Method reportGeneratorName:()Ljava/lang/String;
      11: invokevirtual #57                 // Method software/amazon/awssdk/utils/ToString.add:(Ljava/lang/String;Ljava/lang/Object;)Lsoftware/amazon/awssdk/utils/ToString;
      14: ldc           #58                 // String ReportType
      16: aload_0
      17: invokevirtual #37                 // Method hasReportType:()Z
      20: ifeq          30
      23: aload_0
      24: invokevirtual #38                 // Method reportTypeAsStrings:()Ljava/util/List;
      27: goto          31
      30: aconst_null
      31: invokevirtual #57                 // Method software/amazon/awssdk/utils/ToString.add:(Ljava/lang/String;Ljava/lang/Object;)Lsoftware/amazon/awssdk/utils/ToString;
      34: ldc           #59                 // String ReportContext
      36: aload_0
      37: invokevirtual #39                 // Method reportContext:()Lsoftware/amazon/awssdk/services/licensemanager/model/ReportContext;
      40: invokevirtual #57                 // Method software/amazon/awssdk/utils/ToString.add:(Ljava/lang/String;Ljava/lang/Object;)Lsoftware/amazon/awssdk/utils/ToString;
      43: ldc           #60                 // String ReportFrequency
      45: aload_0
      46: invokevirtual #40                 // Method reportFrequency:()Lsoftware/amazon/awssdk/services/licensemanager/model/ReportFrequency;
      49: invokevirtual #57                 // Method software/amazon/awssdk/utils/ToString.add:(Ljava/lang/String;Ljava/lang/Object;)Lsoftware/amazon/awssdk/utils/ToString;
      52: ldc           #61                 // String LicenseManagerReportGeneratorArn
      54: aload_0
      55: invokevirtual #41                 // Method licenseManagerReportGeneratorArn:()Ljava/lang/String;
      58: invokevirtual #57                 // Method software/amazon/awssdk/utils/ToString.add:(Ljava/lang/String;Ljava/lang/Object;)Lsoftware/amazon/awssdk/utils/ToString;
      61: ldc           #62                 // String LastRunStatus
      63: aload_0
      64: invokevirtual #42                 // Method lastRunStatus:()Ljava/lang/String;
      67: invokevirtual #57                 // Method software/amazon/awssdk/utils/ToString.add:(Ljava/lang/String;Ljava/lang/Object;)Lsoftware/amazon/awssdk/utils/ToString;
      70: ldc           #63                 // String LastRunFailureReason
      72: aload_0
      73: invokevirtual #43                 // Method lastRunFailureReason:()Ljava/lang/String;
      76: invokevirtual #57                 // Method software/amazon/awssdk/utils/ToString.add:(Ljava/lang/String;Ljava/lang/Object;)Lsoftware/amazon/awssdk/utils/ToString;
      79: ldc           #64                 // String LastReportGenerationTime
      81: aload_0
      82: invokevirtual #44                 // Method lastReportGenerationTime:()Ljava/lang/String;
      85: invokevirtual #57                 // Method software/amazon/awssdk/utils/ToString.add:(Ljava/lang/String;Ljava/lang/Object;)Lsoftware/amazon/awssdk/utils/ToString;
      88: ldc           #65                 // String ReportCreatorAccount
      90: aload_0
      91: invokevirtual #45                 // Method reportCreatorAccount:()Ljava/lang/String;
      94: invokevirtual #57                 // Method software/amazon/awssdk/utils/ToString.add:(Ljava/lang/String;Ljava/lang/Object;)Lsoftware/amazon/awssdk/utils/ToString;
      97: ldc           #66                 // String Description
      99: aload_0
     100: invokevirtual #46                 // Method description:()Ljava/lang/String;
     103: invokevirtual #57                 // Method software/amazon/awssdk/utils/ToString.add:(Ljava/lang/String;Ljava/lang/Object;)Lsoftware/amazon/awssdk/utils/ToString;
     106: ldc           #67                 // String S3Location
     108: aload_0
     109: invokevirtual #47                 // Method s3Location:()Lsoftware/amazon/awssdk/services/licensemanager/model/S3Location;
     112: invokevirtual #57                 // Method software/amazon/awssdk/utils/ToString.add:(Ljava/lang/String;Ljava/lang/Object;)Lsoftware/amazon/awssdk/utils/ToString;
     115: ldc           #68                 // String CreateTime
     117: aload_0
     118: invokevirtual #48                 // Method createTime:()Ljava/lang/String;
     121: invokevirtual #57                 // Method software/amazon/awssdk/utils/ToString.add:(Ljava/lang/String;Ljava/lang/Object;)Lsoftware/amazon/awssdk/utils/ToString;
     124: ldc           #69                 // String Tags
     126: aload_0
     127: invokevirtual #49                 // Method hasTags:()Z
     130: ifeq          140
     133: aload_0
     134: invokevirtual #50                 // Method tags:()Ljava/util/List;
     137: goto          141
     140: aconst_null
     141: invokevirtual #57                 // Method software/amazon/awssdk/utils/ToString.add:(Ljava/lang/String;Ljava/lang/Object;)Lsoftware/amazon/awssdk/utils/ToString;
     144: invokevirtual #70                 // Method software/amazon/awssdk/utils/ToString.build:()Ljava/lang/String;
     147: areturn

  public final <T> java.util.Optional<T> getValueForField(java.lang.String, java.lang.Class<T>);
    Code:
       0: aload_1
       1: astore_3
       2: iconst_m1
       3: istore        4
       5: aload_3
       6: invokevirtual #71                 // Method java/lang/String.hashCode:()I
       9: lookupswitch  { // 13
           -1937400054: 124
           -1808897977: 199
           -1689091371: 246
           -1537069447: 214
            -932289015: 294
            -737485265: 230
            -370115922: 139
             -56677412: 262
               2598969: 310
             109486696: 169
             823731018: 184
             849071637: 278
             862332347: 154
               default: 323
          }
     124: aload_3
     125: ldc           #56                 // String ReportGeneratorName
     127: invokevirtual #72                 // Method java/lang/String.equals:(Ljava/lang/Object;)Z
     130: ifeq          323
     133: iconst_0
     134: istore        4
     136: goto          323
     139: aload_3
     140: ldc           #58                 // String ReportType
     142: invokevirtual #72                 // Method java/lang/String.equals:(Ljava/lang/Object;)Z
     145: ifeq          323
     148: iconst_1
     149: istore        4
     151: goto          323
     154: aload_3
     155: ldc           #59                 // String ReportContext
     157: invokevirtual #72                 // Method java/lang/String.equals:(Ljava/lang/Object;)Z
     160: ifeq          323
     163: iconst_2
     164: istore        4
     166: goto          323
     169: aload_3
     170: ldc           #60                 // String ReportFrequency
     172: invokevirtual #72                 // Method java/lang/String.equals:(Ljava/lang/Object;)Z
     175: ifeq          323
     178: iconst_3
     179: istore        4
     181: goto          323
     184: aload_3
     185: ldc           #61                 // String LicenseManagerReportGeneratorArn
     187: invokevirtual #72                 // Method java/lang/String.equals:(Ljava/lang/Object;)Z
     190: ifeq          323
     193: iconst_4
     194: istore        4
     196: goto          323
     199: aload_3
     200: ldc           #62                 // String LastRunStatus
     202: invokevirtual #72                 // Method java/lang/String.equals:(Ljava/lang/Object;)Z
     205: ifeq          323
     208: iconst_5
     209: istore        4
     211: goto          323
     214: aload_3
     215: ldc           #63                 // String LastRunFailureReason
     217: invokevirtual #72                 // Method java/lang/String.equals:(Ljava/lang/Object;)Z
     220: ifeq          323
     223: bipush        6
     225: istore        4
     227: goto          323
     230: aload_3
     231: ldc           #64                 // String LastReportGenerationTime
     233: invokevirtual #72                 // Method java/lang/String.equals:(Ljava/lang/Object;)Z
     236: ifeq          323
     239: bipush        7
     241: istore        4
     243: goto          323
     246: aload_3
     247: ldc           #65                 // String ReportCreatorAccount
     249: invokevirtual #72                 // Method java/lang/String.equals:(Ljava/lang/Object;)Z
     252: ifeq          323
     255: bipush        8
     257: istore        4
     259: goto          323
     262: aload_3
     263: ldc           #66                 // String Description
     265: invokevirtual #72                 // Method java/lang/String.equals:(Ljava/lang/Object;)Z
     268: ifeq          323
     271: bipush        9
     273: istore        4
     275: goto          323
     278: aload_3
     279: ldc           #67                 // String S3Location
     281: invokevirtual #72                 // Method java/lang/String.equals:(Ljava/lang/Object;)Z
     284: ifeq          323
     287: bipush        10
     289: istore        4
     291: goto          323
     294: aload_3
     295: ldc           #68                 // String CreateTime
     297: invokevirtual #72                 // Method java/lang/String.equals:(Ljava/lang/Object;)Z
     300: ifeq          323
     303: bipush        11
     305: istore        4
     307: goto          323
     310: aload_3
     311: ldc           #69                 // String Tags
     313: invokevirtual #72                 // Method java/lang/String.equals:(Ljava/lang/Object;)Z
     316: ifeq          323
     319: bipush        12
     321: istore        4
     323: iload         4
     325: tableswitch   { // 0 to 12
                     0: 392
                     1: 404
                     2: 416
                     3: 428
                     4: 440
                     5: 452
                     6: 464
                     7: 476
                     8: 488
                     9: 500
                    10: 512
                    11: 524
                    12: 536
               default: 548
          }
     392: aload_2
     393: aload_0
     394: invokevirtual #35                 // Method reportGeneratorName:()Ljava/lang/String;
     397: invokevirtual #73                 // Method java/lang/Class.cast:(Ljava/lang/Object;)Ljava/lang/Object;
     400: invokestatic  #74                 // Method java/util/Optional.ofNullable:(Ljava/lang/Object;)Ljava/util/Optional;
     403: areturn
     404: aload_2
     405: aload_0
     406: invokevirtual #38                 // Method reportTypeAsStrings:()Ljava/util/List;
     409: invokevirtual #73                 // Method java/lang/Class.cast:(Ljava/lang/Object;)Ljava/lang/Object;
     412: invokestatic  #74                 // Method java/util/Optional.ofNullable:(Ljava/lang/Object;)Ljava/util/Optional;
     415: areturn
     416: aload_2
     417: aload_0
     418: invokevirtual #39                 // Method reportContext:()Lsoftware/amazon/awssdk/services/licensemanager/model/ReportContext;
     421: invokevirtual #73                 // Method java/lang/Class.cast:(Ljava/lang/Object;)Ljava/lang/Object;
     424: invokestatic  #74                 // Method java/util/Optional.ofNullable:(Ljava/lang/Object;)Ljava/util/Optional;
     427: areturn
     428: aload_2
     429: aload_0
     430: invokevirtual #40                 // Method reportFrequency:()Lsoftware/amazon/awssdk/services/licensemanager/model/ReportFrequency;
     433: invokevirtual #73                 // Method java/lang/Class.cast:(Ljava/lang/Object;)Ljava/lang/Object;
     436: invokestatic  #74                 // Method java/util/Optional.ofNullable:(Ljava/lang/Object;)Ljava/util/Optional;
     439: areturn
     440: aload_2
     441: aload_0
     442: invokevirtual #41                 // Method licenseManagerReportGeneratorArn:()Ljava/lang/String;
     445: invokevirtual #73                 // Method java/lang/Class.cast:(Ljava/lang/Object;)Ljava/lang/Object;
     448: invokestatic  #74                 // Method java/util/Optional.ofNullable:(Ljava/lang/Object;)Ljava/util/Optional;
     451: areturn
     452: aload_2
     453: aload_0
     454: invokevirtual #42                 // Method lastRunStatus:()Ljava/lang/String;
     457: invokevirtual #73                 // Method java/lang/Class.cast:(Ljava/lang/Object;)Ljava/lang/Object;
     460: invokestatic  #74                 // Method java/util/Optional.ofNullable:(Ljava/lang/Object;)Ljava/util/Optional;
     463: areturn
     464: aload_2
     465: aload_0
     466: invokevirtual #43                 // Method lastRunFailureReason:()Ljava/lang/String;
     469: invokevirtual #73                 // Method java/lang/Class.cast:(Ljava/lang/Object;)Ljava/lang/Object;
     472: invokestatic  #74                 // Method java/util/Optional.ofNullable:(Ljava/lang/Object;)Ljava/util/Optional;
     475: areturn
     476: aload_2
     477: aload_0
     478: invokevirtual #44                 // Method lastReportGenerationTime:()Ljava/lang/String;
     481: invokevirtual #73                 // Method java/lang/Class.cast:(Ljava/lang/Object;)Ljava/lang/Object;
     484: invokestatic  #74                 // Method java/util/Optional.ofNullable:(Ljava/lang/Object;)Ljava/util/Optional;
     487: areturn
     488: aload_2
     489: aload_0
     490: invokevirtual #45                 // Method reportCreatorAccount:()Ljava/lang/String;
     493: invokevirtual #73                 // Method java/lang/Class.cast:(Ljava/lang/Object;)Ljava/lang/Object;
     496: invokestatic  #74                 // Method java/util/Optional.ofNullable:(Ljava/lang/Object;)Ljava/util/Optional;
     499: areturn
     500: aload_2
     501: aload_0
     502: invokevirtual #46                 // Method description:()Ljava/lang/String;
     505: invokevirtual #73                 // Method java/lang/Class.cast:(Ljava/lang/Object;)Ljava/lang/Object;
     508: invokestatic  #74                 // Method java/util/Optional.ofNullable:(Ljava/lang/Object;)Ljava/util/Optional;
     511: areturn
     512: aload_2
     513: aload_0
     514: invokevirtual #47                 // Method s3Location:()Lsoftware/amazon/awssdk/services/licensemanager/model/S3Location;
     517: invokevirtual #73                 // Method java/lang/Class.cast:(Ljava/lang/Object;)Ljava/lang/Object;
     520: invokestatic  #74                 // Method java/util/Optional.ofNullable:(Ljava/lang/Object;)Ljava/util/Optional;
     523: areturn
     524: aload_2
     525: aload_0
     526: invokevirtual #48                 // Method createTime:()Ljava/lang/String;
     529: invokevirtual #73                 // Method java/lang/Class.cast:(Ljava/lang/Object;)Ljava/lang/Object;
     532: invokestatic  #74                 // Method java/util/Optional.ofNullable:(Ljava/lang/Object;)Ljava/util/Optional;
     535: areturn
     536: aload_2
     537: aload_0
     538: invokevirtual #50                 // Method tags:()Ljava/util/List;
     541: invokevirtual #73                 // Method java/lang/Class.cast:(Ljava/lang/Object;)Ljava/lang/Object;
     544: invokestatic  #74                 // Method java/util/Optional.ofNullable:(Ljava/lang/Object;)Ljava/util/Optional;
     547: areturn
     548: invokestatic  #75                 // Method java/util/Optional.empty:()Ljava/util/Optional;
     551: areturn

  public final java.util.List<software.amazon.awssdk.core.SdkField<?>> sdkFields();
    Code:
       0: getstatic     #1                  // Field SDK_FIELDS:Ljava/util/List;
       3: areturn

  private static <T> java.util.function.Function<java.lang.Object, T> getter(java.util.function.Function<software.amazon.awssdk.services.licensemanager.model.ReportGenerator, T>);
    Code:
       0: aload_0
       1: invokedynamic #76,  0             // InvokeDynamic #0:apply:(Ljava/util/function/Function;)Ljava/util/function/Function;
       6: areturn

  private static <T> java.util.function.BiConsumer<java.lang.Object, T> setter(java.util.function.BiConsumer<software.amazon.awssdk.services.licensemanager.model.ReportGenerator$Builder, T>);
    Code:
       0: aload_0
       1: invokedynamic #77,  0             // InvokeDynamic #1:accept:(Ljava/util/function/BiConsumer;)Ljava/util/function/BiConsumer;
       6: areturn

  public software.amazon.awssdk.utils.builder.CopyableBuilder toBuilder();
    Code:
       0: aload_0
       1: invokevirtual #78                 // Method toBuilder:()Lsoftware/amazon/awssdk/services/licensemanager/model/ReportGenerator$Builder;
       4: areturn

  private static void lambda$setter$1(java.util.function.BiConsumer, java.lang.Object, java.lang.Object);
    Code:
       0: aload_0
       1: aload_1
       2: checkcast     #79                 // class software/amazon/awssdk/services/licensemanager/model/ReportGenerator$Builder
       5: aload_2
       6: invokeinterface #80,  3           // InterfaceMethod java/util/function/BiConsumer.accept:(Ljava/lang/Object;Ljava/lang/Object;)V
      11: return

  private static java.lang.Object lambda$getter$0(java.util.function.Function, java.lang.Object);
    Code:
       0: aload_0
       1: aload_1
       2: checkcast     #52                 // class software/amazon/awssdk/services/licensemanager/model/ReportGenerator
       5: invokeinterface #81,  2           // InterfaceMethod java/util/function/Function.apply:(Ljava/lang/Object;)Ljava/lang/Object;
      10: areturn

  static java.lang.String access$1500(software.amazon.awssdk.services.licensemanager.model.ReportGenerator);
    Code:
       0: aload_0
       1: getfield      #15                 // Field reportGeneratorName:Ljava/lang/String;
       4: areturn

  static java.util.List access$1600(software.amazon.awssdk.services.licensemanager.model.ReportGenerator);
    Code:
       0: aload_0
       1: getfield      #14                 // Field reportType:Ljava/util/List;
       4: areturn

  static software.amazon.awssdk.services.licensemanager.model.ReportContext access$1700(software.amazon.awssdk.services.licensemanager.model.ReportGenerator);
    Code:
       0: aload_0
       1: getfield      #13                 // Field reportContext:Lsoftware/amazon/awssdk/services/licensemanager/model/ReportContext;
       4: areturn

  static software.amazon.awssdk.services.licensemanager.model.ReportFrequency access$1800(software.amazon.awssdk.services.licensemanager.model.ReportGenerator);
    Code:
       0: aload_0
       1: getfield      #12                 // Field reportFrequency:Lsoftware/amazon/awssdk/services/licensemanager/model/ReportFrequency;
       4: areturn

  static java.lang.String access$1900(software.amazon.awssdk.services.licensemanager.model.ReportGenerator);
    Code:
       0: aload_0
       1: getfield      #11                 // Field licenseManagerReportGeneratorArn:Ljava/lang/String;
       4: areturn

  static java.lang.String access$2000(software.amazon.awssdk.services.licensemanager.model.ReportGenerator);
    Code:
       0: aload_0
       1: getfield      #10                 // Field lastRunStatus:Ljava/lang/String;
       4: areturn

  static java.lang.String access$2100(software.amazon.awssdk.services.licensemanager.model.ReportGenerator);
    Code:
       0: aload_0
       1: getfield      #9                  // Field lastRunFailureReason:Ljava/lang/String;
       4: areturn

  static java.lang.String access$2200(software.amazon.awssdk.services.licensemanager.model.ReportGenerator);
    Code:
       0: aload_0
       1: getfield      #8                  // Field lastReportGenerationTime:Ljava/lang/String;
       4: areturn

  static java.lang.String access$2300(software.amazon.awssdk.services.licensemanager.model.ReportGenerator);
    Code:
       0: aload_0
       1: getfield      #7                  // Field reportCreatorAccount:Ljava/lang/String;
       4: areturn

  static java.lang.String access$2400(software.amazon.awssdk.services.licensemanager.model.ReportGenerator);
    Code:
       0: aload_0
       1: getfield      #6                  // Field description:Ljava/lang/String;
       4: areturn

  static software.amazon.awssdk.services.licensemanager.model.S3Location access$2500(software.amazon.awssdk.services.licensemanager.model.ReportGenerator);
    Code:
       0: aload_0
       1: getfield      #5                  // Field s3Location:Lsoftware/amazon/awssdk/services/licensemanager/model/S3Location;
       4: areturn

  static java.lang.String access$2600(software.amazon.awssdk.services.licensemanager.model.ReportGenerator);
    Code:
       0: aload_0
       1: getfield      #4                  // Field createTime:Ljava/lang/String;
       4: areturn

  static java.util.List access$2700(software.amazon.awssdk.services.licensemanager.model.ReportGenerator);
    Code:
       0: aload_0
       1: getfield      #3                  // Field tags:Ljava/util/List;
       4: areturn

  software.amazon.awssdk.services.licensemanager.model.ReportGenerator(software.amazon.awssdk.services.licensemanager.model.ReportGenerator$BuilderImpl, software.amazon.awssdk.services.licensemanager.model.ReportGenerator$1);
    Code:
       0: aload_0
       1: aload_1
       2: invokespecial #2                  // Method "<init>":(Lsoftware/amazon/awssdk/services/licensemanager/model/ReportGenerator$BuilderImpl;)V
       5: return

  static java.util.List access$2900();
    Code:
       0: getstatic     #1                  // Field SDK_FIELDS:Ljava/util/List;
       3: areturn

  static {};
    Code:
       0: getstatic     #82                 // Field software/amazon/awssdk/core/protocol/MarshallingType.STRING:Lsoftware/amazon/awssdk/core/protocol/MarshallingType;
       3: invokestatic  #83                 // Method software/amazon/awssdk/core/SdkField.builder:(Lsoftware/amazon/awssdk/core/protocol/MarshallingType;)Lsoftware/amazon/awssdk/core/SdkField$Builder;
       6: ldc           #56                 // String ReportGeneratorName
       8: invokevirtual #84                 // Method software/amazon/awssdk/core/SdkField$Builder.memberName:(Ljava/lang/String;)Lsoftware/amazon/awssdk/core/SdkField$Builder;
      11: invokedynamic #85,  0             // InvokeDynamic #2:apply:()Ljava/util/function/Function;
      16: invokestatic  #86                 // Method getter:(Ljava/util/function/Function;)Ljava/util/function/Function;
      19: invokevirtual #87                 // Method software/amazon/awssdk/core/SdkField$Builder.getter:(Ljava/util/function/Function;)Lsoftware/amazon/awssdk/core/SdkField$Builder;
      22: invokedynamic #88,  0             // InvokeDynamic #3:accept:()Ljava/util/function/BiConsumer;
      27: invokestatic  #89                 // Method setter:(Ljava/util/function/BiConsumer;)Ljava/util/function/BiConsumer;
      30: invokevirtual #90                 // Method software/amazon/awssdk/core/SdkField$Builder.setter:(Ljava/util/function/BiConsumer;)Lsoftware/amazon/awssdk/core/SdkField$Builder;
      33: iconst_1
      34: anewarray     #91                 // class software/amazon/awssdk/core/traits/Trait
      37: dup
      38: iconst_0
      39: invokestatic  #92                 // Method software/amazon/awssdk/core/traits/LocationTrait.builder:()Lsoftware/amazon/awssdk/core/traits/LocationTrait$Builder;
      42: getstatic     #93                 // Field software/amazon/awssdk/core/protocol/MarshallLocation.PAYLOAD:Lsoftware/amazon/awssdk/core/protocol/MarshallLocation;
      45: invokevirtual #94                 // Method software/amazon/awssdk/core/traits/LocationTrait$Builder.location:(Lsoftware/amazon/awssdk/core/protocol/MarshallLocation;)Lsoftware/amazon/awssdk/core/traits/LocationTrait$Builder;
      48: ldc           #56                 // String ReportGeneratorName
      50: invokevirtual #95                 // Method software/amazon/awssdk/core/traits/LocationTrait$Builder.locationName:(Ljava/lang/String;)Lsoftware/amazon/awssdk/core/traits/LocationTrait$Builder;
      53: invokevirtual #96                 // Method software/amazon/awssdk/core/traits/LocationTrait$Builder.build:()Lsoftware/amazon/awssdk/core/traits/LocationTrait;
      56: aastore
      57: invokevirtual #97                 // Method software/amazon/awssdk/core/SdkField$Builder.traits:([Lsoftware/amazon/awssdk/core/traits/Trait;)Lsoftware/amazon/awssdk/core/SdkField$Builder;
      60: invokevirtual #98                 // Method software/amazon/awssdk/core/SdkField$Builder.build:()Lsoftware/amazon/awssdk/core/SdkField;
      63: putstatic     #99                 // Field REPORT_GENERATOR_NAME_FIELD:Lsoftware/amazon/awssdk/core/SdkField;
      66: getstatic     #100                // Field software/amazon/awssdk/core/protocol/MarshallingType.LIST:Lsoftware/amazon/awssdk/core/protocol/MarshallingType;
      69: invokestatic  #83                 // Method software/amazon/awssdk/core/SdkField.builder:(Lsoftware/amazon/awssdk/core/protocol/MarshallingType;)Lsoftware/amazon/awssdk/core/SdkField$Builder;
      72: ldc           #58                 // String ReportType
      74: invokevirtual #84                 // Method software/amazon/awssdk/core/SdkField$Builder.memberName:(Ljava/lang/String;)Lsoftware/amazon/awssdk/core/SdkField$Builder;
      77: invokedynamic #101,  0            // InvokeDynamic #4:apply:()Ljava/util/function/Function;
      82: invokestatic  #86                 // Method getter:(Ljava/util/function/Function;)Ljava/util/function/Function;
      85: invokevirtual #87                 // Method software/amazon/awssdk/core/SdkField$Builder.getter:(Ljava/util/function/Function;)Lsoftware/amazon/awssdk/core/SdkField$Builder;
      88: invokedynamic #102,  0            // InvokeDynamic #5:accept:()Ljava/util/function/BiConsumer;
      93: invokestatic  #89                 // Method setter:(Ljava/util/function/BiConsumer;)Ljava/util/function/BiConsumer;
      96: invokevirtual #90                 // Method software/amazon/awssdk/core/SdkField$Builder.setter:(Ljava/util/function/BiConsumer;)Lsoftware/amazon/awssdk/core/SdkField$Builder;
      99: iconst_2
     100: anewarray     #91                 // class software/amazon/awssdk/core/traits/Trait
     103: dup
     104: iconst_0
     105: invokestatic  #92                 // Method software/amazon/awssdk/core/traits/LocationTrait.builder:()Lsoftware/amazon/awssdk/core/traits/LocationTrait$Builder;
     108: getstatic     #93                 // Field software/amazon/awssdk/core/protocol/MarshallLocation.PAYLOAD:Lsoftware/amazon/awssdk/core/protocol/MarshallLocation;
     111: invokevirtual #94                 // Method software/amazon/awssdk/core/traits/LocationTrait$Builder.location:(Lsoftware/amazon/awssdk/core/protocol/MarshallLocation;)Lsoftware/amazon/awssdk/core/traits/LocationTrait$Builder;
     114: ldc           #58                 // String ReportType
     116: invokevirtual #95                 // Method software/amazon/awssdk/core/traits/LocationTrait$Builder.locationName:(Ljava/lang/String;)Lsoftware/amazon/awssdk/core/traits/LocationTrait$Builder;
     119: invokevirtual #96                 // Method software/amazon/awssdk/core/traits/LocationTrait$Builder.build:()Lsoftware/amazon/awssdk/core/traits/LocationTrait;
     122: aastore
     123: dup
     124: iconst_1
     125: invokestatic  #103                // Method software/amazon/awssdk/core/traits/ListTrait.builder:()Lsoftware/amazon/awssdk/core/traits/ListTrait$Builder;
     128: aconst_null
     129: invokevirtual #104                // Method software/amazon/awssdk/core/traits/ListTrait$Builder.memberLocationName:(Ljava/lang/String;)Lsoftware/amazon/awssdk/core/traits/ListTrait$Builder;
     132: getstatic     #82                 // Field software/amazon/awssdk/core/protocol/MarshallingType.STRING:Lsoftware/amazon/awssdk/core/protocol/MarshallingType;
     135: invokestatic  #83                 // Method software/amazon/awssdk/core/SdkField.builder:(Lsoftware/amazon/awssdk/core/protocol/MarshallingType;)Lsoftware/amazon/awssdk/core/SdkField$Builder;
     138: iconst_1
     139: anewarray     #91                 // class software/amazon/awssdk/core/traits/Trait
     142: dup
     143: iconst_0
     144: invokestatic  #92                 // Method software/amazon/awssdk/core/traits/LocationTrait.builder:()Lsoftware/amazon/awssdk/core/traits/LocationTrait$Builder;
     147: getstatic     #93                 // Field software/amazon/awssdk/core/protocol/MarshallLocation.PAYLOAD:Lsoftware/amazon/awssdk/core/protocol/MarshallLocation;
     150: invokevirtual #94                 // Method software/amazon/awssdk/core/traits/LocationTrait$Builder.location:(Lsoftware/amazon/awssdk/core/protocol/MarshallLocation;)Lsoftware/amazon/awssdk/core/traits/LocationTrait$Builder;
     153: ldc           #105                // String member
     155: invokevirtual #95                 // Method software/amazon/awssdk/core/traits/LocationTrait$Builder.locationName:(Ljava/lang/String;)Lsoftware/amazon/awssdk/core/traits/LocationTrait$Builder;
     158: invokevirtual #96                 // Method software/amazon/awssdk/core/traits/LocationTrait$Builder.build:()Lsoftware/amazon/awssdk/core/traits/LocationTrait;
     161: aastore
     162: invokevirtual #97                 // Method software/amazon/awssdk/core/SdkField$Builder.traits:([Lsoftware/amazon/awssdk/core/traits/Trait;)Lsoftware/amazon/awssdk/core/SdkField$Builder;
     165: invokevirtual #98                 // Method software/amazon/awssdk/core/SdkField$Builder.build:()Lsoftware/amazon/awssdk/core/SdkField;
     168: invokevirtual #106                // Method software/amazon/awssdk/core/traits/ListTrait$Builder.memberFieldInfo:(Lsoftware/amazon/awssdk/core/SdkField;)Lsoftware/amazon/awssdk/core/traits/ListTrait$Builder;
     171: invokevirtual #107                // Method software/amazon/awssdk/core/traits/ListTrait$Builder.build:()Lsoftware/amazon/awssdk/core/traits/ListTrait;
     174: aastore
     175: invokevirtual #97                 // Method software/amazon/awssdk/core/SdkField$Builder.traits:([Lsoftware/amazon/awssdk/core/traits/Trait;)Lsoftware/amazon/awssdk/core/SdkField$Builder;
     178: invokevirtual #98                 // Method software/amazon/awssdk/core/SdkField$Builder.build:()Lsoftware/amazon/awssdk/core/SdkField;
     181: putstatic     #108                // Field REPORT_TYPE_FIELD:Lsoftware/amazon/awssdk/core/SdkField;
     184: getstatic     #109                // Field software/amazon/awssdk/core/protocol/MarshallingType.SDK_POJO:Lsoftware/amazon/awssdk/core/protocol/MarshallingType;
     187: invokestatic  #83                 // Method software/amazon/awssdk/core/SdkField.builder:(Lsoftware/amazon/awssdk/core/protocol/MarshallingType;)Lsoftware/amazon/awssdk/core/SdkField$Builder;
     190: ldc           #59                 // String ReportContext
     192: invokevirtual #84                 // Method software/amazon/awssdk/core/SdkField$Builder.memberName:(Ljava/lang/String;)Lsoftware/amazon/awssdk/core/SdkField$Builder;
     195: invokedynamic #110,  0            // InvokeDynamic #6:apply:()Ljava/util/function/Function;
     200: invokestatic  #86                 // Method getter:(Ljava/util/function/Function;)Ljava/util/function/Function;
     203: invokevirtual #87                 // Method software/amazon/awssdk/core/SdkField$Builder.getter:(Ljava/util/function/Function;)Lsoftware/amazon/awssdk/core/SdkField$Builder;
     206: invokedynamic #111,  0            // InvokeDynamic #7:accept:()Ljava/util/function/BiConsumer;
     211: invokestatic  #89                 // Method setter:(Ljava/util/function/BiConsumer;)Ljava/util/function/BiConsumer;
     214: invokevirtual #90                 // Method software/amazon/awssdk/core/SdkField$Builder.setter:(Ljava/util/function/BiConsumer;)Lsoftware/amazon/awssdk/core/SdkField$Builder;
     217: invokedynamic #112,  0            // InvokeDynamic #8:get:()Ljava/util/function/Supplier;
     222: invokevirtual #113                // Method software/amazon/awssdk/core/SdkField$Builder.constructor:(Ljava/util/function/Supplier;)Lsoftware/amazon/awssdk/core/SdkField$Builder;
     225: iconst_1
     226: anewarray     #91                 // class software/amazon/awssdk/core/traits/Trait
     229: dup
     230: iconst_0
     231: invokestatic  #92                 // Method software/amazon/awssdk/core/traits/LocationTrait.builder:()Lsoftware/amazon/awssdk/core/traits/LocationTrait$Builder;
     234: getstatic     #93                 // Field software/amazon/awssdk/core/protocol/MarshallLocation.PAYLOAD:Lsoftware/amazon/awssdk/core/protocol/MarshallLocation;
     237: invokevirtual #94                 // Method software/amazon/awssdk/core/traits/LocationTrait$Builder.location:(Lsoftware/amazon/awssdk/core/protocol/MarshallLocation;)Lsoftware/amazon/awssdk/core/traits/LocationTrait$Builder;
     240: ldc           #59                 // String ReportContext
     242: invokevirtual #95                 // Method software/amazon/awssdk/core/traits/LocationTrait$Builder.locationName:(Ljava/lang/String;)Lsoftware/amazon/awssdk/core/traits/LocationTrait$Builder;
     245: invokevirtual #96                 // Method software/amazon/awssdk/core/traits/LocationTrait$Builder.build:()Lsoftware/amazon/awssdk/core/traits/LocationTrait;
     248: aastore
     249: invokevirtual #97                 // Method software/amazon/awssdk/core/SdkField$Builder.traits:([Lsoftware/amazon/awssdk/core/traits/Trait;)Lsoftware/amazon/awssdk/core/SdkField$Builder;
     252: invokevirtual #98                 // Method software/amazon/awssdk/core/SdkField$Builder.build:()Lsoftware/amazon/awssdk/core/SdkField;
     255: putstatic     #114                // Field REPORT_CONTEXT_FIELD:Lsoftware/amazon/awssdk/core/SdkField;
     258: getstatic     #109                // Field software/amazon/awssdk/core/protocol/MarshallingType.SDK_POJO:Lsoftware/amazon/awssdk/core/protocol/MarshallingType;
     261: invokestatic  #83                 // Method software/amazon/awssdk/core/SdkField.builder:(Lsoftware/amazon/awssdk/core/protocol/MarshallingType;)Lsoftware/amazon/awssdk/core/SdkField$Builder;
     264: ldc           #60                 // String ReportFrequency
     266: invokevirtual #84                 // Method software/amazon/awssdk/core/SdkField$Builder.memberName:(Ljava/lang/String;)Lsoftware/amazon/awssdk/core/SdkField$Builder;
     269: invokedynamic #115,  0            // InvokeDynamic #9:apply:()Ljava/util/function/Function;
     274: invokestatic  #86                 // Method getter:(Ljava/util/function/Function;)Ljava/util/function/Function;
     277: invokevirtual #87                 // Method software/amazon/awssdk/core/SdkField$Builder.getter:(Ljava/util/function/Function;)Lsoftware/amazon/awssdk/core/SdkField$Builder;
     280: invokedynamic #116,  0            // InvokeDynamic #10:accept:()Ljava/util/function/BiConsumer;
     285: invokestatic  #89                 // Method setter:(Ljava/util/function/BiConsumer;)Ljava/util/function/BiConsumer;
     288: invokevirtual #90                 // Method software/amazon/awssdk/core/SdkField$Builder.setter:(Ljava/util/function/BiConsumer;)Lsoftware/amazon/awssdk/core/SdkField$Builder;
     291: invokedynamic #117,  0            // InvokeDynamic #11:get:()Ljava/util/function/Supplier;
     296: invokevirtual #113                // Method software/amazon/awssdk/core/SdkField$Builder.constructor:(Ljava/util/function/Supplier;)Lsoftware/amazon/awssdk/core/SdkField$Builder;
     299: iconst_1
     300: anewarray     #91                 // class software/amazon/awssdk/core/traits/Trait
     303: dup
     304: iconst_0
     305: invokestatic  #92                 // Method software/amazon/awssdk/core/traits/LocationTrait.builder:()Lsoftware/amazon/awssdk/core/traits/LocationTrait$Builder;
     308: getstatic     #93                 // Field software/amazon/awssdk/core/protocol/MarshallLocation.PAYLOAD:Lsoftware/amazon/awssdk/core/protocol/MarshallLocation;
     311: invokevirtual #94                 // Method software/amazon/awssdk/core/traits/LocationTrait$Builder.location:(Lsoftware/amazon/awssdk/core/protocol/MarshallLocation;)Lsoftware/amazon/awssdk/core/traits/LocationTrait$Builder;
     314: ldc           #60                 // String ReportFrequency
     316: invokevirtual #95                 // Method software/amazon/awssdk/core/traits/LocationTrait$Builder.locationName:(Ljava/lang/String;)Lsoftware/amazon/awssdk/core/traits/LocationTrait$Builder;
     319: invokevirtual #96                 // Method software/amazon/awssdk/core/traits/LocationTrait$Builder.build:()Lsoftware/amazon/awssdk/core/traits/LocationTrait;
     322: aastore
     323: invokevirtual #97                 // Method software/amazon/awssdk/core/SdkField$Builder.traits:([Lsoftware/amazon/awssdk/core/traits/Trait;)Lsoftware/amazon/awssdk/core/SdkField$Builder;
     326: invokevirtual #98                 // Method software/amazon/awssdk/core/SdkField$Builder.build:()Lsoftware/amazon/awssdk/core/SdkField;
     329: putstatic     #118                // Field REPORT_FREQUENCY_FIELD:Lsoftware/amazon/awssdk/core/SdkField;
     332: getstatic     #82                 // Field software/amazon/awssdk/core/protocol/MarshallingType.STRING:Lsoftware/amazon/awssdk/core/protocol/MarshallingType;
     335: invokestatic  #83                 // Method software/amazon/awssdk/core/SdkField.builder:(Lsoftware/amazon/awssdk/core/protocol/MarshallingType;)Lsoftware/amazon/awssdk/core/SdkField$Builder;
     338: ldc           #61                 // String LicenseManagerReportGeneratorArn
     340: invokevirtual #84                 // Method software/amazon/awssdk/core/SdkField$Builder.memberName:(Ljava/lang/String;)Lsoftware/amazon/awssdk/core/SdkField$Builder;
     343: invokedynamic #119,  0            // InvokeDynamic #12:apply:()Ljava/util/function/Function;
     348: invokestatic  #86                 // Method getter:(Ljava/util/function/Function;)Ljava/util/function/Function;
     351: invokevirtual #87                 // Method software/amazon/awssdk/core/SdkField$Builder.getter:(Ljava/util/function/Function;)Lsoftware/amazon/awssdk/core/SdkField$Builder;
     354: invokedynamic #120,  0            // InvokeDynamic #13:accept:()Ljava/util/function/BiConsumer;
     359: invokestatic  #89                 // Method setter:(Ljava/util/function/BiConsumer;)Ljava/util/function/BiConsumer;
     362: invokevirtual #90                 // Method software/amazon/awssdk/core/SdkField$Builder.setter:(Ljava/util/function/BiConsumer;)Lsoftware/amazon/awssdk/core/SdkField$Builder;
     365: iconst_1
     366: anewarray     #91                 // class software/amazon/awssdk/core/traits/Trait
     369: dup
     370: iconst_0
     371: invokestatic  #92                 // Method software/amazon/awssdk/core/traits/LocationTrait.builder:()Lsoftware/amazon/awssdk/core/traits/LocationTrait$Builder;
     374: getstatic     #93                 // Field software/amazon/awssdk/core/protocol/MarshallLocation.PAYLOAD:Lsoftware/amazon/awssdk/core/protocol/MarshallLocation;
     377: invokevirtual #94                 // Method software/amazon/awssdk/core/traits/LocationTrait$Builder.location:(Lsoftware/amazon/awssdk/core/protocol/MarshallLocation;)Lsoftware/amazon/awssdk/core/traits/LocationTrait$Builder;
     380: ldc           #61                 // String LicenseManagerReportGeneratorArn
     382: invokevirtual #95                 // Method software/amazon/awssdk/core/traits/LocationTrait$Builder.locationName:(Ljava/lang/String;)Lsoftware/amazon/awssdk/core/traits/LocationTrait$Builder;
     385: invokevirtual #96                 // Method software/amazon/awssdk/core/traits/LocationTrait$Builder.build:()Lsoftware/amazon/awssdk/core/traits/LocationTrait;
     388: aastore
     389: invokevirtual #97                 // Method software/amazon/awssdk/core/SdkField$Builder.traits:([Lsoftware/amazon/awssdk/core/traits/Trait;)Lsoftware/amazon/awssdk/core/SdkField$Builder;
     392: invokevirtual #98                 // Method software/amazon/awssdk/core/SdkField$Builder.build:()Lsoftware/amazon/awssdk/core/SdkField;
     395: putstatic     #121                // Field LICENSE_MANAGER_REPORT_GENERATOR_ARN_FIELD:Lsoftware/amazon/awssdk/core/SdkField;
     398: getstatic     #82                 // Field software/amazon/awssdk/core/protocol/MarshallingType.STRING:Lsoftware/amazon/awssdk/core/protocol/MarshallingType;
     401: invokestatic  #83                 // Method software/amazon/awssdk/core/SdkField.builder:(Lsoftware/amazon/awssdk/core/protocol/MarshallingType;)Lsoftware/amazon/awssdk/core/SdkField$Builder;
     404: ldc           #62                 // String LastRunStatus
     406: invokevirtual #84                 // Method software/amazon/awssdk/core/SdkField$Builder.memberName:(Ljava/lang/String;)Lsoftware/amazon/awssdk/core/SdkField$Builder;
     409: invokedynamic #122,  0            // InvokeDynamic #14:apply:()Ljava/util/function/Function;
     414: invokestatic  #86                 // Method getter:(Ljava/util/function/Function;)Ljava/util/function/Function;
     417: invokevirtual #87                 // Method software/amazon/awssdk/core/SdkField$Builder.getter:(Ljava/util/function/Function;)Lsoftware/amazon/awssdk/core/SdkField$Builder;
     420: invokedynamic #123,  0            // InvokeDynamic #15:accept:()Ljava/util/function/BiConsumer;
     425: invokestatic  #89                 // Method setter:(Ljava/util/function/BiConsumer;)Ljava/util/function/BiConsumer;
     428: invokevirtual #90                 // Method software/amazon/awssdk/core/SdkField$Builder.setter:(Ljava/util/function/BiConsumer;)Lsoftware/amazon/awssdk/core/SdkField$Builder;
     431: iconst_1
     432: anewarray     #91                 // class software/amazon/awssdk/core/traits/Trait
     435: dup
     436: iconst_0
     437: invokestatic  #92                 // Method software/amazon/awssdk/core/traits/LocationTrait.builder:()Lsoftware/amazon/awssdk/core/traits/LocationTrait$Builder;
     440: getstatic     #93                 // Field software/amazon/awssdk/core/protocol/MarshallLocation.PAYLOAD:Lsoftware/amazon/awssdk/core/protocol/MarshallLocation;
     443: invokevirtual #94                 // Method software/amazon/awssdk/core/traits/LocationTrait$Builder.location:(Lsoftware/amazon/awssdk/core/protocol/MarshallLocation;)Lsoftware/amazon/awssdk/core/traits/LocationTrait$Builder;
     446: ldc           #62                 // String LastRunStatus
     448: invokevirtual #95                 // Method software/amazon/awssdk/core/traits/LocationTrait$Builder.locationName:(Ljava/lang/String;)Lsoftware/amazon/awssdk/core/traits/LocationTrait$Builder;
     451: invokevirtual #96                 // Method software/amazon/awssdk/core/traits/LocationTrait$Builder.build:()Lsoftware/amazon/awssdk/core/traits/LocationTrait;
     454: aastore
     455: invokevirtual #97                 // Method software/amazon/awssdk/core/SdkField$Builder.traits:([Lsoftware/amazon/awssdk/core/traits/Trait;)Lsoftware/amazon/awssdk/core/SdkField$Builder;
     458: invokevirtual #98                 // Method software/amazon/awssdk/core/SdkField$Builder.build:()Lsoftware/amazon/awssdk/core/SdkField;
     461: putstatic     #124                // Field LAST_RUN_STATUS_FIELD:Lsoftware/amazon/awssdk/core/SdkField;
     464: getstatic     #82                 // Field software/amazon/awssdk/core/protocol/MarshallingType.STRING:Lsoftware/amazon/awssdk/core/protocol/MarshallingType;
     467: invokestatic  #83                 // Method software/amazon/awssdk/core/SdkField.builder:(Lsoftware/amazon/awssdk/core/protocol/MarshallingType;)Lsoftware/amazon/awssdk/core/SdkField$Builder;
     470: ldc           #63                 // String LastRunFailureReason
     472: invokevirtual #84                 // Method software/amazon/awssdk/core/SdkField$Builder.memberName:(Ljava/lang/String;)Lsoftware/amazon/awssdk/core/SdkField$Builder;
     475: invokedynamic #125,  0            // InvokeDynamic #16:apply:()Ljava/util/function/Function;
     480: invokestatic  #86                 // Method getter:(Ljava/util/function/Function;)Ljava/util/function/Function;
     483: invokevirtual #87                 // Method software/amazon/awssdk/core/SdkField$Builder.getter:(Ljava/util/function/Function;)Lsoftware/amazon/awssdk/core/SdkField$Builder;
     486: invokedynamic #126,  0            // InvokeDynamic #17:accept:()Ljava/util/function/BiConsumer;
     491: invokestatic  #89                 // Method setter:(Ljava/util/function/BiConsumer;)Ljava/util/function/BiConsumer;
     494: invokevirtual #90                 // Method software/amazon/awssdk/core/SdkField$Builder.setter:(Ljava/util/function/BiConsumer;)Lsoftware/amazon/awssdk/core/SdkField$Builder;
     497: iconst_1
     498: anewarray     #91                 // class software/amazon/awssdk/core/traits/Trait
     501: dup
     502: iconst_0
     503: invokestatic  #92                 // Method software/amazon/awssdk/core/traits/LocationTrait.builder:()Lsoftware/amazon/awssdk/core/traits/LocationTrait$Builder;
     506: getstatic     #93                 // Field software/amazon/awssdk/core/protocol/MarshallLocation.PAYLOAD:Lsoftware/amazon/awssdk/core/protocol/MarshallLocation;
     509: invokevirtual #94                 // Method software/amazon/awssdk/core/traits/LocationTrait$Builder.location:(Lsoftware/amazon/awssdk/core/protocol/MarshallLocation;)Lsoftware/amazon/awssdk/core/traits/LocationTrait$Builder;
     512: ldc           #63                 // String LastRunFailureReason
     514: invokevirtual #95                 // Method software/amazon/awssdk/core/traits/LocationTrait$Builder.locationName:(Ljava/lang/String;)Lsoftware/amazon/awssdk/core/traits/LocationTrait$Builder;
     517: invokevirtual #96                 // Method software/amazon/awssdk/core/traits/LocationTrait$Builder.build:()Lsoftware/amazon/awssdk/core/traits/LocationTrait;
     520: aastore
     521: invokevirtual #97                 // Method software/amazon/awssdk/core/SdkField$Builder.traits:([Lsoftware/amazon/awssdk/core/traits/Trait;)Lsoftware/amazon/awssdk/core/SdkField$Builder;
     524: invokevirtual #98                 // Method software/amazon/awssdk/core/SdkField$Builder.build:()Lsoftware/amazon/awssdk/core/SdkField;
     527: putstatic     #127                // Field LAST_RUN_FAILURE_REASON_FIELD:Lsoftware/amazon/awssdk/core/SdkField;
     530: getstatic     #82                 // Field software/amazon/awssdk/core/protocol/MarshallingType.STRING:Lsoftware/amazon/awssdk/core/protocol/MarshallingType;
     533: invokestatic  #83                 // Method software/amazon/awssdk/core/SdkField.builder:(Lsoftware/amazon/awssdk/core/protocol/MarshallingType;)Lsoftware/amazon/awssdk/core/SdkField$Builder;
     536: ldc           #64                 // String LastReportGenerationTime
     538: invokevirtual #84                 // Method software/amazon/awssdk/core/SdkField$Builder.memberName:(Ljava/lang/String;)Lsoftware/amazon/awssdk/core/SdkField$Builder;
     541: invokedynamic #128,  0            // InvokeDynamic #18:apply:()Ljava/util/function/Function;
     546: invokestatic  #86                 // Method getter:(Ljava/util/function/Function;)Ljava/util/function/Function;
     549: invokevirtual #87                 // Method software/amazon/awssdk/core/SdkField$Builder.getter:(Ljava/util/function/Function;)Lsoftware/amazon/awssdk/core/SdkField$Builder;
     552: invokedynamic #129,  0            // InvokeDynamic #19:accept:()Ljava/util/function/BiConsumer;
     557: invokestatic  #89                 // Method setter:(Ljava/util/function/BiConsumer;)Ljava/util/function/BiConsumer;
     560: invokevirtual #90                 // Method software/amazon/awssdk/core/SdkField$Builder.setter:(Ljava/util/function/BiConsumer;)Lsoftware/amazon/awssdk/core/SdkField$Builder;
     563: iconst_1
     564: anewarray     #91                 // class software/amazon/awssdk/core/traits/Trait
     567: dup
     568: iconst_0
     569: invokestatic  #92                 // Method software/amazon/awssdk/core/traits/LocationTrait.builder:()Lsoftware/amazon/awssdk/core/traits/LocationTrait$Builder;
     572: getstatic     #93                 // Field software/amazon/awssdk/core/protocol/MarshallLocation.PAYLOAD:Lsoftware/amazon/awssdk/core/protocol/MarshallLocation;
     575: invokevirtual #94                 // Method software/amazon/awssdk/core/traits/LocationTrait$Builder.location:(Lsoftware/amazon/awssdk/core/protocol/MarshallLocation;)Lsoftware/amazon/awssdk/core/traits/LocationTrait$Builder;
     578: ldc           #64                 // String LastReportGenerationTime
     580: invokevirtual #95                 // Method software/amazon/awssdk/core/traits/LocationTrait$Builder.locationName:(Ljava/lang/String;)Lsoftware/amazon/awssdk/core/traits/LocationTrait$Builder;
     583: invokevirtual #96                 // Method software/amazon/awssdk/core/traits/LocationTrait$Builder.build:()Lsoftware/amazon/awssdk/core/traits/LocationTrait;
     586: aastore
     587: invokevirtual #97                 // Method software/amazon/awssdk/core/SdkField$Builder.traits:([Lsoftware/amazon/awssdk/core/traits/Trait;)Lsoftware/amazon/awssdk/core/SdkField$Builder;
     590: invokevirtual #98                 // Method software/amazon/awssdk/core/SdkField$Builder.build:()Lsoftware/amazon/awssdk/core/SdkField;
     593: putstatic     #130                // Field LAST_REPORT_GENERATION_TIME_FIELD:Lsoftware/amazon/awssdk/core/SdkField;
     596: getstatic     #82                 // Field software/amazon/awssdk/core/protocol/MarshallingType.STRING:Lsoftware/amazon/awssdk/core/protocol/MarshallingType;
     599: invokestatic  #83                 // Method software/amazon/awssdk/core/SdkField.builder:(Lsoftware/amazon/awssdk/core/protocol/MarshallingType;)Lsoftware/amazon/awssdk/core/SdkField$Builder;
     602: ldc           #65                 // String ReportCreatorAccount
     604: invokevirtual #84                 // Method software/amazon/awssdk/core/SdkField$Builder.memberName:(Ljava/lang/String;)Lsoftware/amazon/awssdk/core/SdkField$Builder;
     607: invokedynamic #131,  0            // InvokeDynamic #20:apply:()Ljava/util/function/Function;
     612: invokestatic  #86                 // Method getter:(Ljava/util/function/Function;)Ljava/util/function/Function;
     615: invokevirtual #87                 // Method software/amazon/awssdk/core/SdkField$Builder.getter:(Ljava/util/function/Function;)Lsoftware/amazon/awssdk/core/SdkField$Builder;
     618: invokedynamic #132,  0            // InvokeDynamic #21:accept:()Ljava/util/function/BiConsumer;
     623: invokestatic  #89                 // Method setter:(Ljava/util/function/BiConsumer;)Ljava/util/function/BiConsumer;
     626: invokevirtual #90                 // Method software/amazon/awssdk/core/SdkField$Builder.setter:(Ljava/util/function/BiConsumer;)Lsoftware/amazon/awssdk/core/SdkField$Builder;
     629: iconst_1
     630: anewarray     #91                 // class software/amazon/awssdk/core/traits/Trait
     633: dup
     634: iconst_0
     635: invokestatic  #92                 // Method software/amazon/awssdk/core/traits/LocationTrait.builder:()Lsoftware/amazon/awssdk/core/traits/LocationTrait$Builder;
     638: getstatic     #93                 // Field software/amazon/awssdk/core/protocol/MarshallLocation.PAYLOAD:Lsoftware/amazon/awssdk/core/protocol/MarshallLocation;
     641: invokevirtual #94                 // Method software/amazon/awssdk/core/traits/LocationTrait$Builder.location:(Lsoftware/amazon/awssdk/core/protocol/MarshallLocation;)Lsoftware/amazon/awssdk/core/traits/LocationTrait$Builder;
     644: ldc           #65                 // String ReportCreatorAccount
     646: invokevirtual #95                 // Method software/amazon/awssdk/core/traits/LocationTrait$Builder.locationName:(Ljava/lang/String;)Lsoftware/amazon/awssdk/core/traits/LocationTrait$Builder;
     649: invokevirtual #96                 // Method software/amazon/awssdk/core/traits/LocationTrait$Builder.build:()Lsoftware/amazon/awssdk/core/traits/LocationTrait;
     652: aastore
     653: invokevirtual #97                 // Method software/amazon/awssdk/core/SdkField$Builder.traits:([Lsoftware/amazon/awssdk/core/traits/Trait;)Lsoftware/amazon/awssdk/core/SdkField$Builder;
     656: invokevirtual #98                 // Method software/amazon/awssdk/core/SdkField$Builder.build:()Lsoftware/amazon/awssdk/core/SdkField;
     659: putstatic     #133                // Field REPORT_CREATOR_ACCOUNT_FIELD:Lsoftware/amazon/awssdk/core/SdkField;
     662: getstatic     #82                 // Field software/amazon/awssdk/core/protocol/MarshallingType.STRING:Lsoftware/amazon/awssdk/core/protocol/MarshallingType;
     665: invokestatic  #83                 // Method software/amazon/awssdk/core/SdkField.builder:(Lsoftware/amazon/awssdk/core/protocol/MarshallingType;)Lsoftware/amazon/awssdk/core/SdkField$Builder;
     668: ldc           #66                 // String Description
     670: invokevirtual #84                 // Method software/amazon/awssdk/core/SdkField$Builder.memberName:(Ljava/lang/String;)Lsoftware/amazon/awssdk/core/SdkField$Builder;
     673: invokedynamic #134,  0            // InvokeDynamic #22:apply:()Ljava/util/function/Function;
     678: invokestatic  #86                 // Method getter:(Ljava/util/function/Function;)Ljava/util/function/Function;
     681: invokevirtual #87                 // Method software/amazon/awssdk/core/SdkField$Builder.getter:(Ljava/util/function/Function;)Lsoftware/amazon/awssdk/core/SdkField$Builder;
     684: invokedynamic #135,  0            // InvokeDynamic #23:accept:()Ljava/util/function/BiConsumer;
     689: invokestatic  #89                 // Method setter:(Ljava/util/function/BiConsumer;)Ljava/util/function/BiConsumer;
     692: invokevirtual #90                 // Method software/amazon/awssdk/core/SdkField$Builder.setter:(Ljava/util/function/BiConsumer;)Lsoftware/amazon/awssdk/core/SdkField$Builder;
     695: iconst_1
     696: anewarray     #91                 // class software/amazon/awssdk/core/traits/Trait
     699: dup
     700: iconst_0
     701: invokestatic  #92                 // Method software/amazon/awssdk/core/traits/LocationTrait.builder:()Lsoftware/amazon/awssdk/core/traits/LocationTrait$Builder;
     704: getstatic     #93                 // Field software/amazon/awssdk/core/protocol/MarshallLocation.PAYLOAD:Lsoftware/amazon/awssdk/core/protocol/MarshallLocation;
     707: invokevirtual #94                 // Method software/amazon/awssdk/core/traits/LocationTrait$Builder.location:(Lsoftware/amazon/awssdk/core/protocol/MarshallLocation;)Lsoftware/amazon/awssdk/core/traits/LocationTrait$Builder;
     710: ldc           #66                 // String Description
     712: invokevirtual #95                 // Method software/amazon/awssdk/core/traits/LocationTrait$Builder.locationName:(Ljava/lang/String;)Lsoftware/amazon/awssdk/core/traits/LocationTrait$Builder;
     715: invokevirtual #96                 // Method software/amazon/awssdk/core/traits/LocationTrait$Builder.build:()Lsoftware/amazon/awssdk/core/traits/LocationTrait;
     718: aastore
     719: invokevirtual #97                 // Method software/amazon/awssdk/core/SdkField$Builder.traits:([Lsoftware/amazon/awssdk/core/traits/Trait;)Lsoftware/amazon/awssdk/core/SdkField$Builder;
     722: invokevirtual #98                 // Method software/amazon/awssdk/core/SdkField$Builder.build:()Lsoftware/amazon/awssdk/core/SdkField;
     725: putstatic     #136                // Field DESCRIPTION_FIELD:Lsoftware/amazon/awssdk/core/SdkField;
     728: getstatic     #109                // Field software/amazon/awssdk/core/protocol/MarshallingType.SDK_POJO:Lsoftware/amazon/awssdk/core/protocol/MarshallingType;
     731: invokestatic  #83                 // Method software/amazon/awssdk/core/SdkField.builder:(Lsoftware/amazon/awssdk/core/protocol/MarshallingType;)Lsoftware/amazon/awssdk/core/SdkField$Builder;
     734: ldc           #67                 // String S3Location
     736: invokevirtual #84                 // Method software/amazon/awssdk/core/SdkField$Builder.memberName:(Ljava/lang/String;)Lsoftware/amazon/awssdk/core/SdkField$Builder;
     739: invokedynamic #137,  0            // InvokeDynamic #24:apply:()Ljava/util/function/Function;
     744: invokestatic  #86                 // Method getter:(Ljava/util/function/Function;)Ljava/util/function/Function;
     747: invokevirtual #87                 // Method software/amazon/awssdk/core/SdkField$Builder.getter:(Ljava/util/function/Function;)Lsoftware/amazon/awssdk/core/SdkField$Builder;
     750: invokedynamic #138,  0            // InvokeDynamic #25:accept:()Ljava/util/function/BiConsumer;
     755: invokestatic  #89                 // Method setter:(Ljava/util/function/BiConsumer;)Ljava/util/function/BiConsumer;
     758: invokevirtual #90                 // Method software/amazon/awssdk/core/SdkField$Builder.setter:(Ljava/util/function/BiConsumer;)Lsoftware/amazon/awssdk/core/SdkField$Builder;
     761: invokedynamic #139,  0            // InvokeDynamic #26:get:()Ljava/util/function/Supplier;
     766: invokevirtual #113                // Method software/amazon/awssdk/core/SdkField$Builder.constructor:(Ljava/util/function/Supplier;)Lsoftware/amazon/awssdk/core/SdkField$Builder;
     769: iconst_1
     770: anewarray     #91                 // class software/amazon/awssdk/core/traits/Trait
     773: dup
     774: iconst_0
     775: invokestatic  #92                 // Method software/amazon/awssdk/core/traits/LocationTrait.builder:()Lsoftware/amazon/awssdk/core/traits/LocationTrait$Builder;
     778: getstatic     #93                 // Field software/amazon/awssdk/core/protocol/MarshallLocation.PAYLOAD:Lsoftware/amazon/awssdk/core/protocol/MarshallLocation;
     781: invokevirtual #94                 // Method software/amazon/awssdk/core/traits/LocationTrait$Builder.location:(Lsoftware/amazon/awssdk/core/protocol/MarshallLocation;)Lsoftware/amazon/awssdk/core/traits/LocationTrait$Builder;
     784: ldc           #67                 // String S3Location
     786: invokevirtual #95                 // Method software/amazon/awssdk/core/traits/LocationTrait$Builder.locationName:(Ljava/lang/String;)Lsoftware/amazon/awssdk/core/traits/LocationTrait$Builder;
     789: invokevirtual #96                 // Method software/amazon/awssdk/core/traits/LocationTrait$Builder.build:()Lsoftware/amazon/awssdk/core/traits/LocationTrait;
     792: aastore
     793: invokevirtual #97                 // Method software/amazon/awssdk/core/SdkField$Builder.traits:([Lsoftware/amazon/awssdk/core/traits/Trait;)Lsoftware/amazon/awssdk/core/SdkField$Builder;
     796: invokevirtual #98                 // Method software/amazon/awssdk/core/SdkField$Builder.build:()Lsoftware/amazon/awssdk/core/SdkField;
     799: putstatic     #140                // Field S3_LOCATION_FIELD:Lsoftware/amazon/awssdk/core/SdkField;
     802: getstatic     #82                 // Field software/amazon/awssdk/core/protocol/MarshallingType.STRING:Lsoftware/amazon/awssdk/core/protocol/MarshallingType;
     805: invokestatic  #83                 // Method software/amazon/awssdk/core/SdkField.builder:(Lsoftware/amazon/awssdk/core/protocol/MarshallingType;)Lsoftware/amazon/awssdk/core/SdkField$Builder;
     808: ldc           #68                 // String CreateTime
     810: invokevirtual #84                 // Method software/amazon/awssdk/core/SdkField$Builder.memberName:(Ljava/lang/String;)Lsoftware/amazon/awssdk/core/SdkField$Builder;
     813: invokedynamic #141,  0            // InvokeDynamic #27:apply:()Ljava/util/function/Function;
     818: invokestatic  #86                 // Method getter:(Ljava/util/function/Function;)Ljava/util/function/Function;
     821: invokevirtual #87                 // Method software/amazon/awssdk/core/SdkField$Builder.getter:(Ljava/util/function/Function;)Lsoftware/amazon/awssdk/core/SdkField$Builder;
     824: invokedynamic #142,  0            // InvokeDynamic #28:accept:()Ljava/util/function/BiConsumer;
     829: invokestatic  #89                 // Method setter:(Ljava/util/function/BiConsumer;)Ljava/util/function/BiConsumer;
     832: invokevirtual #90                 // Method software/amazon/awssdk/core/SdkField$Builder.setter:(Ljava/util/function/BiConsumer;)Lsoftware/amazon/awssdk/core/SdkField$Builder;
     835: iconst_1
     836: anewarray     #91                 // class software/amazon/awssdk/core/traits/Trait
     839: dup
     840: iconst_0
     841: invokestatic  #92                 // Method software/amazon/awssdk/core/traits/LocationTrait.builder:()Lsoftware/amazon/awssdk/core/traits/LocationTrait$Builder;
     844: getstatic     #93                 // Field software/amazon/awssdk/core/protocol/MarshallLocation.PAYLOAD:Lsoftware/amazon/awssdk/core/protocol/MarshallLocation;
     847: invokevirtual #94                 // Method software/amazon/awssdk/core/traits/LocationTrait$Builder.location:(Lsoftware/amazon/awssdk/core/protocol/MarshallLocation;)Lsoftware/amazon/awssdk/core/traits/LocationTrait$Builder;
     850: ldc           #68                 // String CreateTime
     852: invokevirtual #95                 // Method software/amazon/awssdk/core/traits/LocationTrait$Builder.locationName:(Ljava/lang/String;)Lsoftware/amazon/awssdk/core/traits/LocationTrait$Builder;
     855: invokevirtual #96                 // Method software/amazon/awssdk/core/traits/LocationTrait$Builder.build:()Lsoftware/amazon/awssdk/core/traits/LocationTrait;
     858: aastore
     859: invokevirtual #97                 // Method software/amazon/awssdk/core/SdkField$Builder.traits:([Lsoftware/amazon/awssdk/core/traits/Trait;)Lsoftware/amazon/awssdk/core/SdkField$Builder;
     862: invokevirtual #98                 // Method software/amazon/awssdk/core/SdkField$Builder.build:()Lsoftware/amazon/awssdk/core/SdkField;
     865: putstatic     #143                // Field CREATE_TIME_FIELD:Lsoftware/amazon/awssdk/core/SdkField;
     868: getstatic     #100                // Field software/amazon/awssdk/core/protocol/MarshallingType.LIST:Lsoftware/amazon/awssdk/core/protocol/MarshallingType;
     871: invokestatic  #83                 // Method software/amazon/awssdk/core/SdkField.builder:(Lsoftware/amazon/awssdk/core/protocol/MarshallingType;)Lsoftware/amazon/awssdk/core/SdkField$Builder;
     874: ldc           #69                 // String Tags
     876: invokevirtual #84                 // Method software/amazon/awssdk/core/SdkField$Builder.memberName:(Ljava/lang/String;)Lsoftware/amazon/awssdk/core/SdkField$Builder;
     879: invokedynamic #144,  0            // InvokeDynamic #29:apply:()Ljava/util/function/Function;
     884: invokestatic  #86                 // Method getter:(Ljava/util/function/Function;)Ljava/util/function/Function;
     887: invokevirtual #87                 // Method software/amazon/awssdk/core/SdkField$Builder.getter:(Ljava/util/function/Function;)Lsoftware/amazon/awssdk/core/SdkField$Builder;
     890: invokedynamic #145,  0            // InvokeDynamic #30:accept:()Ljava/util/function/BiConsumer;
     895: invokestatic  #89                 // Method setter:(Ljava/util/function/BiConsumer;)Ljava/util/function/BiConsumer;
     898: invokevirtual #90                 // Method software/amazon/awssdk/core/SdkField$Builder.setter:(Ljava/util/function/BiConsumer;)Lsoftware/amazon/awssdk/core/SdkField$Builder;
     901: iconst_2
     902: anewarray     #91                 // class software/amazon/awssdk/core/traits/Trait
     905: dup
     906: iconst_0
     907: invokestatic  #92                 // Method software/amazon/awssdk/core/traits/LocationTrait.builder:()Lsoftware/amazon/awssdk/core/traits/LocationTrait$Builder;
     910: getstatic     #93                 // Field software/amazon/awssdk/core/protocol/MarshallLocation.PAYLOAD:Lsoftware/amazon/awssdk/core/protocol/MarshallLocation;
     913: invokevirtual #94                 // Method software/amazon/awssdk/core/traits/LocationTrait$Builder.location:(Lsoftware/amazon/awssdk/core/protocol/MarshallLocation;)Lsoftware/amazon/awssdk/core/traits/LocationTrait$Builder;
     916: ldc           #69                 // String Tags
     918: invokevirtual #95                 // Method software/amazon/awssdk/core/traits/LocationTrait$Builder.locationName:(Ljava/lang/String;)Lsoftware/amazon/awssdk/core/traits/LocationTrait$Builder;
     921: invokevirtual #96                 // Method software/amazon/awssdk/core/traits/LocationTrait$Builder.build:()Lsoftware/amazon/awssdk/core/traits/LocationTrait;
     924: aastore
     925: dup
     926: iconst_1
     927: invokestatic  #103                // Method software/amazon/awssdk/core/traits/ListTrait.builder:()Lsoftware/amazon/awssdk/core/traits/ListTrait$Builder;
     930: aconst_null
     931: invokevirtual #104                // Method software/amazon/awssdk/core/traits/ListTrait$Builder.memberLocationName:(Ljava/lang/String;)Lsoftware/amazon/awssdk/core/traits/ListTrait$Builder;
     934: getstatic     #109                // Field software/amazon/awssdk/core/protocol/MarshallingType.SDK_POJO:Lsoftware/amazon/awssdk/core/protocol/MarshallingType;
     937: invokestatic  #83                 // Method software/amazon/awssdk/core/SdkField.builder:(Lsoftware/amazon/awssdk/core/protocol/MarshallingType;)Lsoftware/amazon/awssdk/core/SdkField$Builder;
     940: invokedynamic #146,  0            // InvokeDynamic #31:get:()Ljava/util/function/Supplier;
     945: invokevirtual #113                // Method software/amazon/awssdk/core/SdkField$Builder.constructor:(Ljava/util/function/Supplier;)Lsoftware/amazon/awssdk/core/SdkField$Builder;
     948: iconst_1
     949: anewarray     #91                 // class software/amazon/awssdk/core/traits/Trait
     952: dup
     953: iconst_0
     954: invokestatic  #92                 // Method software/amazon/awssdk/core/traits/LocationTrait.builder:()Lsoftware/amazon/awssdk/core/traits/LocationTrait$Builder;
     957: getstatic     #93                 // Field software/amazon/awssdk/core/protocol/MarshallLocation.PAYLOAD:Lsoftware/amazon/awssdk/core/protocol/MarshallLocation;
     960: invokevirtual #94                 // Method software/amazon/awssdk/core/traits/LocationTrait$Builder.location:(Lsoftware/amazon/awssdk/core/protocol/MarshallLocation;)Lsoftware/amazon/awssdk/core/traits/LocationTrait$Builder;
     963: ldc           #105                // String member
     965: invokevirtual #95                 // Method software/amazon/awssdk/core/traits/LocationTrait$Builder.locationName:(Ljava/lang/String;)Lsoftware/amazon/awssdk/core/traits/LocationTrait$Builder;
     968: invokevirtual #96                 // Method software/amazon/awssdk/core/traits/LocationTrait$Builder.build:()Lsoftware/amazon/awssdk/core/traits/LocationTrait;
     971: aastore
     972: invokevirtual #97                 // Method software/amazon/awssdk/core/SdkField$Builder.traits:([Lsoftware/amazon/awssdk/core/traits/Trait;)Lsoftware/amazon/awssdk/core/SdkField$Builder;
     975: invokevirtual #98                 // Method software/amazon/awssdk/core/SdkField$Builder.build:()Lsoftware/amazon/awssdk/core/SdkField;
     978: invokevirtual #106                // Method software/amazon/awssdk/core/traits/ListTrait$Builder.memberFieldInfo:(Lsoftware/amazon/awssdk/core/SdkField;)Lsoftware/amazon/awssdk/core/traits/ListTrait$Builder;
     981: invokevirtual #107                // Method software/amazon/awssdk/core/traits/ListTrait$Builder.build:()Lsoftware/amazon/awssdk/core/traits/ListTrait;
     984: aastore
     985: invokevirtual #97                 // Method software/amazon/awssdk/core/SdkField$Builder.traits:([Lsoftware/amazon/awssdk/core/traits/Trait;)Lsoftware/amazon/awssdk/core/SdkField$Builder;
     988: invokevirtual #98                 // Method software/amazon/awssdk/core/SdkField$Builder.build:()Lsoftware/amazon/awssdk/core/SdkField;
     991: putstatic     #147                // Field TAGS_FIELD:Lsoftware/amazon/awssdk/core/SdkField;
     994: bipush        13
     996: anewarray     #148                // class software/amazon/awssdk/core/SdkField
     999: dup
    1000: iconst_0
    1001: getstatic     #99                 // Field REPORT_GENERATOR_NAME_FIELD:Lsoftware/amazon/awssdk/core/SdkField;
    1004: aastore
    1005: dup
    1006: iconst_1
    1007: getstatic     #108                // Field REPORT_TYPE_FIELD:Lsoftware/amazon/awssdk/core/SdkField;
    1010: aastore
    1011: dup
    1012: iconst_2
    1013: getstatic     #114                // Field REPORT_CONTEXT_FIELD:Lsoftware/amazon/awssdk/core/SdkField;
    1016: aastore
    1017: dup
    1018: iconst_3
    1019: getstatic     #118                // Field REPORT_FREQUENCY_FIELD:Lsoftware/amazon/awssdk/core/SdkField;
    1022: aastore
    1023: dup
    1024: iconst_4
    1025: getstatic     #121                // Field LICENSE_MANAGER_REPORT_GENERATOR_ARN_FIELD:Lsoftware/amazon/awssdk/core/SdkField;
    1028: aastore
    1029: dup
    1030: iconst_5
    1031: getstatic     #124                // Field LAST_RUN_STATUS_FIELD:Lsoftware/amazon/awssdk/core/SdkField;
    1034: aastore
    1035: dup
    1036: bipush        6
    1038: getstatic     #127                // Field LAST_RUN_FAILURE_REASON_FIELD:Lsoftware/amazon/awssdk/core/SdkField;
    1041: aastore
    1042: dup
    1043: bipush        7
    1045: getstatic     #130                // Field LAST_REPORT_GENERATION_TIME_FIELD:Lsoftware/amazon/awssdk/core/SdkField;
    1048: aastore
    1049: dup
    1050: bipush        8
    1052: getstatic     #133                // Field REPORT_CREATOR_ACCOUNT_FIELD:Lsoftware/amazon/awssdk/core/SdkField;
    1055: aastore
    1056: dup
    1057: bipush        9
    1059: getstatic     #136                // Field DESCRIPTION_FIELD:Lsoftware/amazon/awssdk/core/SdkField;
    1062: aastore
    1063: dup
    1064: bipush        10
    1066: getstatic     #140                // Field S3_LOCATION_FIELD:Lsoftware/amazon/awssdk/core/SdkField;
    1069: aastore
    1070: dup
    1071: bipush        11
    1073: getstatic     #143                // Field CREATE_TIME_FIELD:Lsoftware/amazon/awssdk/core/SdkField;
    1076: aastore
    1077: dup
    1078: bipush        12
    1080: getstatic     #147                // Field TAGS_FIELD:Lsoftware/amazon/awssdk/core/SdkField;
    1083: aastore
    1084: invokestatic  #149                // Method java/util/Arrays.asList:([Ljava/lang/Object;)Ljava/util/List;
    1087: invokestatic  #150                // Method java/util/Collections.unmodifiableList:(Ljava/util/List;)Ljava/util/List;
    1090: putstatic     #1                  // Field SDK_FIELDS:Ljava/util/List;
    1093: return
}
