Compiled from "UpdateLicenseManagerReportGeneratorRequest.java"
final class software.amazon.awssdk.services.licensemanager.model.UpdateLicenseManagerReportGeneratorRequest$BuilderImpl extends software.amazon.awssdk.services.licensemanager.model.LicenseManagerRequest$BuilderImpl implements software.amazon.awssdk.services.licensemanager.model.UpdateLicenseManagerReportGeneratorRequest$Builder {
  private java.lang.String licenseManagerReportGeneratorArn;

  private java.lang.String reportGeneratorName;

  private java.util.List<java.lang.String> type;

  private software.amazon.awssdk.services.licensemanager.model.ReportContext reportContext;

  private software.amazon.awssdk.services.licensemanager.model.ReportFrequency reportFrequency;

  private java.lang.String clientToken;

  private java.lang.String description;

  private software.amazon.awssdk.services.licensemanager.model.UpdateLicenseManagerReportGeneratorRequest$BuilderImpl();
    Code:
       0: aload_0
       1: invokespecial #10                 // Method software/amazon/awssdk/services/licensemanager/model/LicenseManagerRequest$BuilderImpl."<init>":()V
       4: aload_0
       5: invokestatic  #11                 // Method software/amazon/awssdk/core/util/DefaultSdkAutoConstructList.getInstance:()Lsoftware/amazon/awssdk/core/util/DefaultSdkAutoConstructList;
       8: putfield      #7                  // Field type:Ljava/util/List;
      11: return

  private software.amazon.awssdk.services.licensemanager.model.UpdateLicenseManagerReportGeneratorRequest$BuilderImpl(software.amazon.awssdk.services.licensemanager.model.UpdateLicenseManagerReportGeneratorRequest);
    Code:
       0: aload_0
       1: aload_1
       2: invokespecial #12                 // Method software/amazon/awssdk/services/licensemanager/model/LicenseManagerRequest$BuilderImpl."<init>":(Lsoftware/amazon/awssdk/services/licensemanager/model/LicenseManagerRequest;)V
       5: aload_0
       6: invokestatic  #11                 // Method software/amazon/awssdk/core/util/DefaultSdkAutoConstructList.getInstance:()Lsoftware/amazon/awssdk/core/util/DefaultSdkAutoConstructList;
       9: putfield      #7                  // Field type:Ljava/util/List;
      12: aload_0
      13: aload_1
      14: invokestatic  #13                 // Method software/amazon/awssdk/services/licensemanager/model/UpdateLicenseManagerReportGeneratorRequest.access$900:(Lsoftware/amazon/awssdk/services/licensemanager/model/UpdateLicenseManagerReportGeneratorRequest;)Ljava/lang/String;
      17: invokevirtual #14                 // Method licenseManagerReportGeneratorArn:(Ljava/lang/String;)Lsoftware/amazon/awssdk/services/licensemanager/model/UpdateLicenseManagerReportGeneratorRequest$Builder;
      20: pop
      21: aload_0
      22: aload_1
      23: invokestatic  #15                 // Method software/amazon/awssdk/services/licensemanager/model/UpdateLicenseManagerReportGeneratorRequest.access$1000:(Lsoftware/amazon/awssdk/services/licensemanager/model/UpdateLicenseManagerReportGeneratorRequest;)Ljava/lang/String;
      26: invokevirtual #16                 // Method reportGeneratorName:(Ljava/lang/String;)Lsoftware/amazon/awssdk/services/licensemanager/model/UpdateLicenseManagerReportGeneratorRequest$Builder;
      29: pop
      30: aload_0
      31: aload_1
      32: invokestatic  #17                 // Method software/amazon/awssdk/services/licensemanager/model/UpdateLicenseManagerReportGeneratorRequest.access$1100:(Lsoftware/amazon/awssdk/services/licensemanager/model/UpdateLicenseManagerReportGeneratorRequest;)Ljava/util/List;
      35: invokevirtual #18                 // Method typeWithStrings:(Ljava/util/Collection;)Lsoftware/amazon/awssdk/services/licensemanager/model/UpdateLicenseManagerReportGeneratorRequest$Builder;
      38: pop
      39: aload_0
      40: aload_1
      41: invokestatic  #19                 // Method software/amazon/awssdk/services/licensemanager/model/UpdateLicenseManagerReportGeneratorRequest.access$1200:(Lsoftware/amazon/awssdk/services/licensemanager/model/UpdateLicenseManagerReportGeneratorRequest;)Lsoftware/amazon/awssdk/services/licensemanager/model/ReportContext;
      44: invokevirtual #20                 // Method reportContext:(Lsoftware/amazon/awssdk/services/licensemanager/model/ReportContext;)Lsoftware/amazon/awssdk/services/licensemanager/model/UpdateLicenseManagerReportGeneratorRequest$Builder;
      47: pop
      48: aload_0
      49: aload_1
      50: invokestatic  #21                 // Method software/amazon/awssdk/services/licensemanager/model/UpdateLicenseManagerReportGeneratorRequest.access$1300:(Lsoftware/amazon/awssdk/services/licensemanager/model/UpdateLicenseManagerReportGeneratorRequest;)Lsoftware/amazon/awssdk/services/licensemanager/model/ReportFrequency;
      53: invokevirtual #22                 // Method reportFrequency:(Lsoftware/amazon/awssdk/services/licensemanager/model/ReportFrequency;)Lsoftware/amazon/awssdk/services/licensemanager/model/UpdateLicenseManagerReportGeneratorRequest$Builder;
      56: pop
      57: aload_0
      58: aload_1
      59: invokestatic  #23                 // Method software/amazon/awssdk/services/licensemanager/model/UpdateLicenseManagerReportGeneratorRequest.access$1400:(Lsoftware/amazon/awssdk/services/licensemanager/model/UpdateLicenseManagerReportGeneratorRequest;)Ljava/lang/String;
      62: invokevirtual #24                 // Method clientToken:(Ljava/lang/String;)Lsoftware/amazon/awssdk/services/licensemanager/model/UpdateLicenseManagerReportGeneratorRequest$Builder;
      65: pop
      66: aload_0
      67: aload_1
      68: invokestatic  #25                 // Method software/amazon/awssdk/services/licensemanager/model/UpdateLicenseManagerReportGeneratorRequest.access$1500:(Lsoftware/amazon/awssdk/services/licensemanager/model/UpdateLicenseManagerReportGeneratorRequest;)Ljava/lang/String;
      71: invokevirtual #26                 // Method description:(Ljava/lang/String;)Lsoftware/amazon/awssdk/services/licensemanager/model/UpdateLicenseManagerReportGeneratorRequest$Builder;
      74: pop
      75: return

  public final java.lang.String getLicenseManagerReportGeneratorArn();
    Code:
       0: aload_0
       1: getfield      #9                  // Field licenseManagerReportGeneratorArn:Ljava/lang/String;
       4: areturn

  public final void setLicenseManagerReportGeneratorArn(java.lang.String);
    Code:
       0: aload_0
       1: aload_1
       2: putfield      #9                  // Field licenseManagerReportGeneratorArn:Ljava/lang/String;
       5: return

  public final software.amazon.awssdk.services.licensemanager.model.UpdateLicenseManagerReportGeneratorRequest$Builder licenseManagerReportGeneratorArn(java.lang.String);
    Code:
       0: aload_0
       1: aload_1
       2: putfield      #9                  // Field licenseManagerReportGeneratorArn:Ljava/lang/String;
       5: aload_0
       6: areturn

  public final java.lang.String getReportGeneratorName();
    Code:
       0: aload_0
       1: getfield      #8                  // Field reportGeneratorName:Ljava/lang/String;
       4: areturn

  public final void setReportGeneratorName(java.lang.String);
    Code:
       0: aload_0
       1: aload_1
       2: putfield      #8                  // Field reportGeneratorName:Ljava/lang/String;
       5: return

  public final software.amazon.awssdk.services.licensemanager.model.UpdateLicenseManagerReportGeneratorRequest$Builder reportGeneratorName(java.lang.String);
    Code:
       0: aload_0
       1: aload_1
       2: putfield      #8                  // Field reportGeneratorName:Ljava/lang/String;
       5: aload_0
       6: areturn

  public final java.util.Collection<java.lang.String> getType();
    Code:
       0: aload_0
       1: getfield      #7                  // Field type:Ljava/util/List;
       4: instanceof    #27                 // class software/amazon/awssdk/core/util/SdkAutoConstructList
       7: ifeq          12
      10: aconst_null
      11: areturn
      12: aload_0
      13: getfield      #7                  // Field type:Ljava/util/List;
      16: areturn

  public final void setType(java.util.Collection<java.lang.String>);
    Code:
       0: aload_0
       1: aload_1
       2: invokestatic  #28                 // Method software/amazon/awssdk/services/licensemanager/model/ReportTypeListCopier.copy:(Ljava/util/Collection;)Ljava/util/List;
       5: putfield      #7                  // Field type:Ljava/util/List;
       8: return

  public final software.amazon.awssdk.services.licensemanager.model.UpdateLicenseManagerReportGeneratorRequest$Builder typeWithStrings(java.util.Collection<java.lang.String>);
    Code:
       0: aload_0
       1: aload_1
       2: invokestatic  #28                 // Method software/amazon/awssdk/services/licensemanager/model/ReportTypeListCopier.copy:(Ljava/util/Collection;)Ljava/util/List;
       5: putfield      #7                  // Field type:Ljava/util/List;
       8: aload_0
       9: areturn

  public final software.amazon.awssdk.services.licensemanager.model.UpdateLicenseManagerReportGeneratorRequest$Builder typeWithStrings(java.lang.String...);
    Code:
       0: aload_0
       1: aload_1
       2: invokestatic  #29                 // Method java/util/Arrays.asList:([Ljava/lang/Object;)Ljava/util/List;
       5: invokevirtual #18                 // Method typeWithStrings:(Ljava/util/Collection;)Lsoftware/amazon/awssdk/services/licensemanager/model/UpdateLicenseManagerReportGeneratorRequest$Builder;
       8: pop
       9: aload_0
      10: areturn

  public final software.amazon.awssdk.services.licensemanager.model.UpdateLicenseManagerReportGeneratorRequest$Builder type(java.util.Collection<software.amazon.awssdk.services.licensemanager.model.ReportType>);
    Code:
       0: aload_0
       1: aload_1
       2: invokestatic  #30                 // Method software/amazon/awssdk/services/licensemanager/model/ReportTypeListCopier.copyEnumToString:(Ljava/util/Collection;)Ljava/util/List;
       5: putfield      #7                  // Field type:Ljava/util/List;
       8: aload_0
       9: areturn

  public final software.amazon.awssdk.services.licensemanager.model.UpdateLicenseManagerReportGeneratorRequest$Builder type(software.amazon.awssdk.services.licensemanager.model.ReportType...);
    Code:
       0: aload_0
       1: aload_1
       2: invokestatic  #29                 // Method java/util/Arrays.asList:([Ljava/lang/Object;)Ljava/util/List;
       5: invokevirtual #31                 // Method type:(Ljava/util/Collection;)Lsoftware/amazon/awssdk/services/licensemanager/model/UpdateLicenseManagerReportGeneratorRequest$Builder;
       8: pop
       9: aload_0
      10: areturn

  public final software.amazon.awssdk.services.licensemanager.model.ReportContext$Builder getReportContext();
    Code:
       0: aload_0
       1: getfield      #6                  // Field reportContext:Lsoftware/amazon/awssdk/services/licensemanager/model/ReportContext;
       4: ifnull        17
       7: aload_0
       8: getfield      #6                  // Field reportContext:Lsoftware/amazon/awssdk/services/licensemanager/model/ReportContext;
      11: invokevirtual #32                 // Method software/amazon/awssdk/services/licensemanager/model/ReportContext.toBuilder:()Lsoftware/amazon/awssdk/services/licensemanager/model/ReportContext$Builder;
      14: goto          18
      17: aconst_null
      18: areturn

  public final void setReportContext(software.amazon.awssdk.services.licensemanager.model.ReportContext$BuilderImpl);
    Code:
       0: aload_0
       1: aload_1
       2: ifnull        12
       5: aload_1
       6: invokevirtual #33                 // Method software/amazon/awssdk/services/licensemanager/model/ReportContext$BuilderImpl.build:()Lsoftware/amazon/awssdk/services/licensemanager/model/ReportContext;
       9: goto          13
      12: aconst_null
      13: putfield      #6                  // Field reportContext:Lsoftware/amazon/awssdk/services/licensemanager/model/ReportContext;
      16: return

  public final software.amazon.awssdk.services.licensemanager.model.UpdateLicenseManagerReportGeneratorRequest$Builder reportContext(software.amazon.awssdk.services.licensemanager.model.ReportContext);
    Code:
       0: aload_0
       1: aload_1
       2: putfield      #6                  // Field reportContext:Lsoftware/amazon/awssdk/services/licensemanager/model/ReportContext;
       5: aload_0
       6: areturn

  public final software.amazon.awssdk.services.licensemanager.model.ReportFrequency$Builder getReportFrequency();
    Code:
       0: aload_0
       1: getfield      #5                  // Field reportFrequency:Lsoftware/amazon/awssdk/services/licensemanager/model/ReportFrequency;
       4: ifnull        17
       7: aload_0
       8: getfield      #5                  // Field reportFrequency:Lsoftware/amazon/awssdk/services/licensemanager/model/ReportFrequency;
      11: invokevirtual #34                 // Method software/amazon/awssdk/services/licensemanager/model/ReportFrequency.toBuilder:()Lsoftware/amazon/awssdk/services/licensemanager/model/ReportFrequency$Builder;
      14: goto          18
      17: aconst_null
      18: areturn

  public final void setReportFrequency(software.amazon.awssdk.services.licensemanager.model.ReportFrequency$BuilderImpl);
    Code:
       0: aload_0
       1: aload_1
       2: ifnull        12
       5: aload_1
       6: invokevirtual #35                 // Method software/amazon/awssdk/services/licensemanager/model/ReportFrequency$BuilderImpl.build:()Lsoftware/amazon/awssdk/services/licensemanager/model/ReportFrequency;
       9: goto          13
      12: aconst_null
      13: putfield      #5                  // Field reportFrequency:Lsoftware/amazon/awssdk/services/licensemanager/model/ReportFrequency;
      16: return

  public final software.amazon.awssdk.services.licensemanager.model.UpdateLicenseManagerReportGeneratorRequest$Builder reportFrequency(software.amazon.awssdk.services.licensemanager.model.ReportFrequency);
    Code:
       0: aload_0
       1: aload_1
       2: putfield      #5                  // Field reportFrequency:Lsoftware/amazon/awssdk/services/licensemanager/model/ReportFrequency;
       5: aload_0
       6: areturn

  public final java.lang.String getClientToken();
    Code:
       0: aload_0
       1: getfield      #4                  // Field clientToken:Ljava/lang/String;
       4: areturn

  public final void setClientToken(java.lang.String);
    Code:
       0: aload_0
       1: aload_1
       2: putfield      #4                  // Field clientToken:Ljava/lang/String;
       5: return

  public final software.amazon.awssdk.services.licensemanager.model.UpdateLicenseManagerReportGeneratorRequest$Builder clientToken(java.lang.String);
    Code:
       0: aload_0
       1: aload_1
       2: putfield      #4                  // Field clientToken:Ljava/lang/String;
       5: aload_0
       6: areturn

  public final java.lang.String getDescription();
    Code:
       0: aload_0
       1: getfield      #3                  // Field description:Ljava/lang/String;
       4: areturn

  public final void setDescription(java.lang.String);
    Code:
       0: aload_0
       1: aload_1
       2: putfield      #3                  // Field description:Ljava/lang/String;
       5: return

  public final software.amazon.awssdk.services.licensemanager.model.UpdateLicenseManagerReportGeneratorRequest$Builder description(java.lang.String);
    Code:
       0: aload_0
       1: aload_1
       2: putfield      #3                  // Field description:Ljava/lang/String;
       5: aload_0
       6: areturn

  public software.amazon.awssdk.services.licensemanager.model.UpdateLicenseManagerReportGeneratorRequest$Builder overrideConfiguration(software.amazon.awssdk.awscore.AwsRequestOverrideConfiguration);
    Code:
       0: aload_0
       1: aload_1
       2: invokespecial #36                 // Method software/amazon/awssdk/services/licensemanager/model/LicenseManagerRequest$BuilderImpl.overrideConfiguration:(Lsoftware/amazon/awssdk/awscore/AwsRequestOverrideConfiguration;)Lsoftware/amazon/awssdk/awscore/AwsRequest$Builder;
       5: pop
       6: aload_0
       7: areturn

  public software.amazon.awssdk.services.licensemanager.model.UpdateLicenseManagerReportGeneratorRequest$Builder overrideConfiguration(java.util.function.Consumer<software.amazon.awssdk.awscore.AwsRequestOverrideConfiguration$Builder>);
    Code:
       0: aload_0
       1: aload_1
       2: invokespecial #37                 // Method software/amazon/awssdk/services/licensemanager/model/LicenseManagerRequest$BuilderImpl.overrideConfiguration:(Ljava/util/function/Consumer;)Lsoftware/amazon/awssdk/awscore/AwsRequest$Builder;
       5: pop
       6: aload_0
       7: areturn

  public software.amazon.awssdk.services.licensemanager.model.UpdateLicenseManagerReportGeneratorRequest build();
    Code:
       0: new           #38                 // class software/amazon/awssdk/services/licensemanager/model/UpdateLicenseManagerReportGeneratorRequest
       3: dup
       4: aload_0
       5: aconst_null
       6: invokespecial #39                 // Method software/amazon/awssdk/services/licensemanager/model/UpdateLicenseManagerReportGeneratorRequest."<init>":(Lsoftware/amazon/awssdk/services/licensemanager/model/UpdateLicenseManagerReportGeneratorRequest$BuilderImpl;Lsoftware/amazon/awssdk/services/licensemanager/model/UpdateLicenseManagerReportGeneratorRequest$1;)V
       9: areturn

  public java.util.List<software.amazon.awssdk.core.SdkField<?>> sdkFields();
    Code:
       0: invokestatic  #40                 // Method software/amazon/awssdk/services/licensemanager/model/UpdateLicenseManagerReportGeneratorRequest.access$1700:()Ljava/util/List;
       3: areturn

  public software.amazon.awssdk.services.licensemanager.model.LicenseManagerRequest build();
    Code:
       0: aload_0
       1: invokevirtual #41                 // Method build:()Lsoftware/amazon/awssdk/services/licensemanager/model/UpdateLicenseManagerReportGeneratorRequest;
       4: areturn

  public software.amazon.awssdk.awscore.AwsRequest build();
    Code:
       0: aload_0
       1: invokevirtual #41                 // Method build:()Lsoftware/amazon/awssdk/services/licensemanager/model/UpdateLicenseManagerReportGeneratorRequest;
       4: areturn

  public software.amazon.awssdk.awscore.AwsRequest$Builder overrideConfiguration(java.util.function.Consumer);
    Code:
       0: aload_0
       1: aload_1
       2: invokevirtual #42                 // Method overrideConfiguration:(Ljava/util/function/Consumer;)Lsoftware/amazon/awssdk/services/licensemanager/model/UpdateLicenseManagerReportGeneratorRequest$Builder;
       5: areturn

  public software.amazon.awssdk.awscore.AwsRequest$Builder overrideConfiguration(software.amazon.awssdk.awscore.AwsRequestOverrideConfiguration);
    Code:
       0: aload_0
       1: aload_1
       2: invokevirtual #43                 // Method overrideConfiguration:(Lsoftware/amazon/awssdk/awscore/AwsRequestOverrideConfiguration;)Lsoftware/amazon/awssdk/services/licensemanager/model/UpdateLicenseManagerReportGeneratorRequest$Builder;
       5: areturn

  public software.amazon.awssdk.core.SdkRequest build();
    Code:
       0: aload_0
       1: invokevirtual #41                 // Method build:()Lsoftware/amazon/awssdk/services/licensemanager/model/UpdateLicenseManagerReportGeneratorRequest;
       4: areturn

  public java.lang.Object build();
    Code:
       0: aload_0
       1: invokevirtual #41                 // Method build:()Lsoftware/amazon/awssdk/services/licensemanager/model/UpdateLicenseManagerReportGeneratorRequest;
       4: areturn

  static java.lang.String access$000(software.amazon.awssdk.services.licensemanager.model.UpdateLicenseManagerReportGeneratorRequest$BuilderImpl);
    Code:
       0: aload_0
       1: getfield      #9                  // Field licenseManagerReportGeneratorArn:Ljava/lang/String;
       4: areturn

  static java.lang.String access$100(software.amazon.awssdk.services.licensemanager.model.UpdateLicenseManagerReportGeneratorRequest$BuilderImpl);
    Code:
       0: aload_0
       1: getfield      #8                  // Field reportGeneratorName:Ljava/lang/String;
       4: areturn

  static java.util.List access$200(software.amazon.awssdk.services.licensemanager.model.UpdateLicenseManagerReportGeneratorRequest$BuilderImpl);
    Code:
       0: aload_0
       1: getfield      #7                  // Field type:Ljava/util/List;
       4: areturn

  static software.amazon.awssdk.services.licensemanager.model.ReportContext access$300(software.amazon.awssdk.services.licensemanager.model.UpdateLicenseManagerReportGeneratorRequest$BuilderImpl);
    Code:
       0: aload_0
       1: getfield      #6                  // Field reportContext:Lsoftware/amazon/awssdk/services/licensemanager/model/ReportContext;
       4: areturn

  static software.amazon.awssdk.services.licensemanager.model.ReportFrequency access$400(software.amazon.awssdk.services.licensemanager.model.UpdateLicenseManagerReportGeneratorRequest$BuilderImpl);
    Code:
       0: aload_0
       1: getfield      #5                  // Field reportFrequency:Lsoftware/amazon/awssdk/services/licensemanager/model/ReportFrequency;
       4: areturn

  static java.lang.String access$500(software.amazon.awssdk.services.licensemanager.model.UpdateLicenseManagerReportGeneratorRequest$BuilderImpl);
    Code:
       0: aload_0
       1: getfield      #4                  // Field clientToken:Ljava/lang/String;
       4: areturn

  static java.lang.String access$600(software.amazon.awssdk.services.licensemanager.model.UpdateLicenseManagerReportGeneratorRequest$BuilderImpl);
    Code:
       0: aload_0
       1: getfield      #3                  // Field description:Ljava/lang/String;
       4: areturn

  software.amazon.awssdk.services.licensemanager.model.UpdateLicenseManagerReportGeneratorRequest$BuilderImpl(software.amazon.awssdk.services.licensemanager.model.UpdateLicenseManagerReportGeneratorRequest, software.amazon.awssdk.services.licensemanager.model.UpdateLicenseManagerReportGeneratorRequest$1);
    Code:
       0: aload_0
       1: aload_1
       2: invokespecial #2                  // Method "<init>":(Lsoftware/amazon/awssdk/services/licensemanager/model/UpdateLicenseManagerReportGeneratorRequest;)V
       5: return

  software.amazon.awssdk.services.licensemanager.model.UpdateLicenseManagerReportGeneratorRequest$BuilderImpl(software.amazon.awssdk.services.licensemanager.model.UpdateLicenseManagerReportGeneratorRequest$1);
    Code:
       0: aload_0
       1: invokespecial #1                  // Method "<init>":()V
       4: return
}
