Compiled from "SerqlTupleExprRenderer.java"
class org.eclipse.rdf4j.queryrender.serql.SerqlTupleExprRenderer extends org.eclipse.rdf4j.queryrender.BaseTupleExprRenderer {
  private java.lang.StringBuffer mBuffer;

  private java.lang.StringBuffer mJoinBuffer;

  private org.eclipse.rdf4j.query.algebra.ValueExpr mFilter;

  private final org.eclipse.rdf4j.queryrender.serql.SerqlValueExprRenderer mValueExprRenderer;

  org.eclipse.rdf4j.queryrender.serql.SerqlTupleExprRenderer();
    Code:
       0: aload_0
       1: invokespecial #1                  // Method org/eclipse/rdf4j/queryrender/BaseTupleExprRenderer."<init>":()V
       4: aload_0
       5: new           #2                  // class java/lang/StringBuffer
       8: dup
       9: invokespecial #3                  // Method java/lang/StringBuffer."<init>":()V
      12: putfield      #4                  // Field mBuffer:Ljava/lang/StringBuffer;
      15: aload_0
      16: new           #2                  // class java/lang/StringBuffer
      19: dup
      20: invokespecial #3                  // Method java/lang/StringBuffer."<init>":()V
      23: putfield      #5                  // Field mJoinBuffer:Ljava/lang/StringBuffer;
      26: aload_0
      27: new           #6                  // class org/eclipse/rdf4j/queryrender/serql/SerqlValueExprRenderer
      30: dup
      31: invokespecial #7                  // Method org/eclipse/rdf4j/queryrender/serql/SerqlValueExprRenderer."<init>":()V
      34: putfield      #8                  // Field mValueExprRenderer:Lorg/eclipse/rdf4j/queryrender/serql/SerqlValueExprRenderer;
      37: return

  public void reset();
    Code:
       0: aload_0
       1: invokespecial #9                  // Method org/eclipse/rdf4j/queryrender/BaseTupleExprRenderer.reset:()V
       4: aload_0
       5: aconst_null
       6: putfield      #10                 // Field mFilter:Lorg/eclipse/rdf4j/query/algebra/ValueExpr;
       9: aload_0
      10: new           #2                  // class java/lang/StringBuffer
      13: dup
      14: invokespecial #3                  // Method java/lang/StringBuffer."<init>":()V
      17: putfield      #4                  // Field mBuffer:Ljava/lang/StringBuffer;
      20: aload_0
      21: new           #2                  // class java/lang/StringBuffer
      24: dup
      25: invokespecial #3                  // Method java/lang/StringBuffer."<init>":()V
      28: putfield      #5                  // Field mJoinBuffer:Ljava/lang/StringBuffer;
      31: return

  public java.lang.String render(org.eclipse.rdf4j.query.algebra.TupleExpr) throws java.lang.Exception;
    Code:
       0: aload_1
       1: aload_0
       2: invokeinterface #11,  2           // InterfaceMethod org/eclipse/rdf4j/query/algebra/TupleExpr.visit:(Lorg/eclipse/rdf4j/query/algebra/QueryModelVisitor;)V
       7: aload_0
       8: getfield      #4                  // Field mBuffer:Ljava/lang/StringBuffer;
      11: invokevirtual #12                 // Method java/lang/StringBuffer.length:()I
      14: ifle          25
      17: aload_0
      18: getfield      #4                  // Field mBuffer:Ljava/lang/StringBuffer;
      21: invokevirtual #13                 // Method java/lang/StringBuffer.toString:()Ljava/lang/String;
      24: areturn
      25: iconst_1
      26: istore_2
      27: new           #14                 // class java/lang/StringBuilder
      30: dup
      31: invokespecial #15                 // Method java/lang/StringBuilder."<init>":()V
      34: astore_3
      35: aload_0
      36: getfield      #16                 // Field mProjection:Ljava/util/List;
      39: invokeinterface #17,  1           // InterfaceMethod java/util/List.isEmpty:()Z
      44: ifne          423
      47: aload_0
      48: invokevirtual #18                 // Method isSelect:()Z
      51: ifeq          64
      54: aload_3
      55: ldc           #19                 // String select
      57: invokevirtual #20                 // Method java/lang/StringBuilder.append:(Ljava/lang/String;)Ljava/lang/StringBuilder;
      60: pop
      61: goto          71
      64: aload_3
      65: ldc           #21                 // String construct
      67: invokevirtual #20                 // Method java/lang/StringBuilder.append:(Ljava/lang/String;)Ljava/lang/StringBuilder;
      70: pop
      71: aload_0
      72: getfield      #22                 // Field mDistinct:Z
      75: ifeq          85
      78: aload_3
      79: ldc           #23                 // String distinct
      81: invokevirtual #20                 // Method java/lang/StringBuilder.append:(Ljava/lang/String;)Ljava/lang/StringBuilder;
      84: pop
      85: aload_0
      86: getfield      #24                 // Field mReduced:Z
      89: ifeq          106
      92: aload_0
      93: invokevirtual #18                 // Method isSelect:()Z
      96: ifeq          106
      99: aload_3
     100: ldc           #25                 // String reduced
     102: invokevirtual #20                 // Method java/lang/StringBuilder.append:(Ljava/lang/String;)Ljava/lang/StringBuilder;
     105: pop
     106: iconst_1
     107: istore_2
     108: aload_0
     109: invokevirtual #18                 // Method isSelect:()Z
     112: ifne          122
     115: aload_3
     116: ldc           #26                 // String \n
     118: invokevirtual #20                 // Method java/lang/StringBuilder.append:(Ljava/lang/String;)Ljava/lang/StringBuilder;
     121: pop
     122: aload_0
     123: getfield      #16                 // Field mProjection:Ljava/util/List;
     126: invokeinterface #27,  1           // InterfaceMethod java/util/List.iterator:()Ljava/util/Iterator;
     131: astore        4
     133: aload         4
     135: invokeinterface #28,  1           // InterfaceMethod java/util/Iterator.hasNext:()Z
     140: ifeq          416
     143: aload         4
     145: invokeinterface #29,  1           // InterfaceMethod java/util/Iterator.next:()Ljava/lang/Object;
     150: checkcast     #30                 // class org/eclipse/rdf4j/query/algebra/ProjectionElemList
     153: astore        5
     155: aload         5
     157: invokestatic  #31                 // Method isSPOElemList:(Lorg/eclipse/rdf4j/query/algebra/ProjectionElemList;)Z
     160: ifeq          197
     163: iload_2
     164: ifne          177
     167: aload_3
     168: ldc           #32                 // String ,\n
     170: invokevirtual #20                 // Method java/lang/StringBuilder.append:(Ljava/lang/String;)Ljava/lang/StringBuilder;
     173: pop
     174: goto          179
     177: iconst_0
     178: istore_2
     179: aload_3
     180: aload_0
     181: aload_0
     182: aload         5
     184: invokevirtual #33                 // Method toStatementPattern:(Lorg/eclipse/rdf4j/query/algebra/ProjectionElemList;)Lorg/eclipse/rdf4j/query/algebra/StatementPattern;
     187: invokespecial #34                 // Method renderPattern:(Lorg/eclipse/rdf4j/query/algebra/StatementPattern;)Ljava/lang/String;
     190: invokevirtual #20                 // Method java/lang/StringBuilder.append:(Ljava/lang/String;)Ljava/lang/StringBuilder;
     193: pop
     194: goto          413
     197: aload         5
     199: invokevirtual #35                 // Method org/eclipse/rdf4j/query/algebra/ProjectionElemList.getElements:()Ljava/util/List;
     202: invokeinterface #27,  1           // InterfaceMethod java/util/List.iterator:()Ljava/util/Iterator;
     207: astore        6
     209: aload         6
     211: invokeinterface #28,  1           // InterfaceMethod java/util/Iterator.hasNext:()Z
     216: ifeq          413
     219: aload         6
     221: invokeinterface #29,  1           // InterfaceMethod java/util/Iterator.next:()Ljava/lang/Object;
     226: checkcast     #36                 // class org/eclipse/rdf4j/query/algebra/ProjectionElem
     229: astore        7
     231: iload_2
     232: ifne          245
     235: aload_3
     236: ldc           #37                 // String ,
     238: invokevirtual #20                 // Method java/lang/StringBuilder.append:(Ljava/lang/String;)Ljava/lang/StringBuilder;
     241: pop
     242: goto          247
     245: iconst_0
     246: istore_2
     247: aload_3
     248: aload_0
     249: getfield      #38                 // Field mExtensions:Ljava/util/Map;
     252: aload         7
     254: invokevirtual #39                 // Method org/eclipse/rdf4j/query/algebra/ProjectionElem.getSourceName:()Ljava/lang/String;
     257: invokeinterface #40,  2           // InterfaceMethod java/util/Map.containsKey:(Ljava/lang/Object;)Z
     262: ifeq          292
     265: aload_0
     266: getfield      #8                  // Field mValueExprRenderer:Lorg/eclipse/rdf4j/queryrender/serql/SerqlValueExprRenderer;
     269: aload_0
     270: getfield      #38                 // Field mExtensions:Ljava/util/Map;
     273: aload         7
     275: invokevirtual #39                 // Method org/eclipse/rdf4j/query/algebra/ProjectionElem.getSourceName:()Ljava/lang/String;
     278: invokeinterface #41,  2           // InterfaceMethod java/util/Map.get:(Ljava/lang/Object;)Ljava/lang/Object;
     283: checkcast     #42                 // class org/eclipse/rdf4j/query/algebra/ValueExpr
     286: invokevirtual #43                 // Method org/eclipse/rdf4j/queryrender/serql/SerqlValueExprRenderer.render:(Lorg/eclipse/rdf4j/query/algebra/ValueExpr;)Ljava/lang/String;
     289: goto          297
     292: aload         7
     294: invokevirtual #39                 // Method org/eclipse/rdf4j/query/algebra/ProjectionElem.getSourceName:()Ljava/lang/String;
     297: invokevirtual #20                 // Method java/lang/StringBuilder.append:(Ljava/lang/String;)Ljava/lang/StringBuilder;
     300: pop
     301: aload         7
     303: invokevirtual #39                 // Method org/eclipse/rdf4j/query/algebra/ProjectionElem.getSourceName:()Ljava/lang/String;
     306: aload         7
     308: invokevirtual #44                 // Method org/eclipse/rdf4j/query/algebra/ProjectionElem.getTargetName:()Ljava/lang/String;
     311: invokevirtual #45                 // Method java/lang/String.equals:(Ljava/lang/Object;)Z
     314: ifeq          351
     317: aload_0
     318: getfield      #38                 // Field mExtensions:Ljava/util/Map;
     321: aload         7
     323: invokevirtual #44                 // Method org/eclipse/rdf4j/query/algebra/ProjectionElem.getTargetName:()Ljava/lang/String;
     326: invokeinterface #40,  2           // InterfaceMethod java/util/Map.containsKey:(Ljava/lang/Object;)Z
     331: ifeq          410
     334: aload_0
     335: getfield      #38                 // Field mExtensions:Ljava/util/Map;
     338: aload         7
     340: invokevirtual #39                 // Method org/eclipse/rdf4j/query/algebra/ProjectionElem.getSourceName:()Ljava/lang/String;
     343: invokeinterface #40,  2           // InterfaceMethod java/util/Map.containsKey:(Ljava/lang/Object;)Z
     348: ifne          410
     351: aload_3
     352: ldc           #46                 // String  as
     354: invokevirtual #20                 // Method java/lang/StringBuilder.append:(Ljava/lang/String;)Ljava/lang/StringBuilder;
     357: aload_0
     358: getfield      #38                 // Field mExtensions:Ljava/util/Map;
     361: aload         7
     363: invokevirtual #44                 // Method org/eclipse/rdf4j/query/algebra/ProjectionElem.getTargetName:()Ljava/lang/String;
     366: invokeinterface #40,  2           // InterfaceMethod java/util/Map.containsKey:(Ljava/lang/Object;)Z
     371: ifeq          401
     374: aload_0
     375: getfield      #8                  // Field mValueExprRenderer:Lorg/eclipse/rdf4j/queryrender/serql/SerqlValueExprRenderer;
     378: aload_0
     379: getfield      #38                 // Field mExtensions:Ljava/util/Map;
     382: aload         7
     384: invokevirtual #44                 // Method org/eclipse/rdf4j/query/algebra/ProjectionElem.getTargetName:()Ljava/lang/String;
     387: invokeinterface #41,  2           // InterfaceMethod java/util/Map.get:(Ljava/lang/Object;)Ljava/lang/Object;
     392: checkcast     #42                 // class org/eclipse/rdf4j/query/algebra/ValueExpr
     395: invokevirtual #43                 // Method org/eclipse/rdf4j/queryrender/serql/SerqlValueExprRenderer.render:(Lorg/eclipse/rdf4j/query/algebra/ValueExpr;)Ljava/lang/String;
     398: goto          406
     401: aload         7
     403: invokevirtual #44                 // Method org/eclipse/rdf4j/query/algebra/ProjectionElem.getTargetName:()Ljava/lang/String;
     406: invokevirtual #20                 // Method java/lang/StringBuilder.append:(Ljava/lang/String;)Ljava/lang/StringBuilder;
     409: pop
     410: goto          209
     413: goto          133
     416: aload_3
     417: ldc           #26                 // String \n
     419: invokevirtual #20                 // Method java/lang/StringBuilder.append:(Ljava/lang/String;)Ljava/lang/StringBuilder;
     422: pop
     423: aload_0
     424: getfield      #5                  // Field mJoinBuffer:Ljava/lang/StringBuffer;
     427: invokevirtual #12                 // Method java/lang/StringBuffer.length:()I
     430: ifle          467
     433: aload_0
     434: getfield      #5                  // Field mJoinBuffer:Ljava/lang/StringBuffer;
     437: aload_0
     438: getfield      #5                  // Field mJoinBuffer:Ljava/lang/StringBuffer;
     441: ldc           #47                 // String ,
     443: invokevirtual #48                 // Method java/lang/StringBuffer.lastIndexOf:(Ljava/lang/String;)I
     446: bipush        32
     448: invokevirtual #49                 // Method java/lang/StringBuffer.setCharAt:(IC)V
     451: aload_3
     452: ldc           #50                 // String from\n
     454: invokevirtual #20                 // Method java/lang/StringBuilder.append:(Ljava/lang/String;)Ljava/lang/StringBuilder;
     457: pop
     458: aload_3
     459: aload_0
     460: getfield      #5                  // Field mJoinBuffer:Ljava/lang/StringBuffer;
     463: invokevirtual #51                 // Method java/lang/StringBuilder.append:(Ljava/lang/StringBuffer;)Ljava/lang/StringBuilder;
     466: pop
     467: aload_0
     468: getfield      #10                 // Field mFilter:Lorg/eclipse/rdf4j/query/algebra/ValueExpr;
     471: ifnull        497
     474: aload_3
     475: ldc           #52                 // String where\n
     477: invokevirtual #20                 // Method java/lang/StringBuilder.append:(Ljava/lang/String;)Ljava/lang/StringBuilder;
     480: pop
     481: aload_3
     482: aload_0
     483: getfield      #8                  // Field mValueExprRenderer:Lorg/eclipse/rdf4j/queryrender/serql/SerqlValueExprRenderer;
     486: aload_0
     487: getfield      #10                 // Field mFilter:Lorg/eclipse/rdf4j/query/algebra/ValueExpr;
     490: invokevirtual #43                 // Method org/eclipse/rdf4j/queryrender/serql/SerqlValueExprRenderer.render:(Lorg/eclipse/rdf4j/query/algebra/ValueExpr;)Ljava/lang/String;
     493: invokevirtual #20                 // Method java/lang/StringBuilder.append:(Ljava/lang/String;)Ljava/lang/StringBuilder;
     496: pop
     497: aload_0
     498: getfield      #53                 // Field mOrdering:Ljava/util/List;
     501: invokeinterface #17,  1           // InterfaceMethod java/util/List.isEmpty:()Z
     506: ifne          612
     509: aload_3
     510: ldc           #54                 // String \norder by
     512: invokevirtual #20                 // Method java/lang/StringBuilder.append:(Ljava/lang/String;)Ljava/lang/StringBuilder;
     515: pop
     516: iconst_1
     517: istore_2
     518: aload_0
     519: getfield      #53                 // Field mOrdering:Ljava/util/List;
     522: invokeinterface #27,  1           // InterfaceMethod java/util/List.iterator:()Ljava/util/Iterator;
     527: astore        4
     529: aload         4
     531: invokeinterface #28,  1           // InterfaceMethod java/util/Iterator.hasNext:()Z
     536: ifeq          612
     539: aload         4
     541: invokeinterface #29,  1           // InterfaceMethod java/util/Iterator.next:()Ljava/lang/Object;
     546: checkcast     #55                 // class org/eclipse/rdf4j/query/algebra/OrderElem
     549: astore        5
     551: iload_2
     552: ifne          565
     555: aload_3
     556: ldc           #37                 // String ,
     558: invokevirtual #20                 // Method java/lang/StringBuilder.append:(Ljava/lang/String;)Ljava/lang/StringBuilder;
     561: pop
     562: goto          567
     565: iconst_0
     566: istore_2
     567: aload_3
     568: aload         5
     570: invokevirtual #56                 // Method org/eclipse/rdf4j/query/algebra/OrderElem.getExpr:()Lorg/eclipse/rdf4j/query/algebra/ValueExpr;
     573: invokevirtual #57                 // Method java/lang/StringBuilder.append:(Ljava/lang/Object;)Ljava/lang/StringBuilder;
     576: pop
     577: aload_3
     578: ldc           #58                 // String
     580: invokevirtual #20                 // Method java/lang/StringBuilder.append:(Ljava/lang/String;)Ljava/lang/StringBuilder;
     583: pop
     584: aload         5
     586: invokevirtual #59                 // Method org/eclipse/rdf4j/query/algebra/OrderElem.isAscending:()Z
     589: ifeq          602
     592: aload_3
     593: ldc           #60                 // String asc
     595: invokevirtual #20                 // Method java/lang/StringBuilder.append:(Ljava/lang/String;)Ljava/lang/StringBuilder;
     598: pop
     599: goto          609
     602: aload_3
     603: ldc           #61                 // String desc
     605: invokevirtual #20                 // Method java/lang/StringBuilder.append:(Ljava/lang/String;)Ljava/lang/StringBuilder;
     608: pop
     609: goto          529
     612: aload_0
     613: getfield      #62                 // Field mLimit:J
     616: ldc2_w        #63                 // long -1l
     619: lcmp
     620: ifeq          637
     623: aload_3
     624: ldc           #65                 // String \nlimit
     626: invokevirtual #20                 // Method java/lang/StringBuilder.append:(Ljava/lang/String;)Ljava/lang/StringBuilder;
     629: aload_0
     630: getfield      #62                 // Field mLimit:J
     633: invokevirtual #66                 // Method java/lang/StringBuilder.append:(J)Ljava/lang/StringBuilder;
     636: pop
     637: aload_0
     638: getfield      #67                 // Field mOffset:J
     641: ldc2_w        #63                 // long -1l
     644: lcmp
     645: ifeq          662
     648: aload_3
     649: ldc           #68                 // String \noffset
     651: invokevirtual #20                 // Method java/lang/StringBuilder.append:(Ljava/lang/String;)Ljava/lang/StringBuilder;
     654: aload_0
     655: getfield      #67                 // Field mOffset:J
     658: invokevirtual #66                 // Method java/lang/StringBuilder.append:(J)Ljava/lang/StringBuilder;
     661: pop
     662: aload_3
     663: invokevirtual #69                 // Method java/lang/StringBuilder.toString:()Ljava/lang/String;
     666: areturn

  private java.lang.String renderTupleExpr(org.eclipse.rdf4j.query.algebra.TupleExpr) throws java.lang.Exception;
    Code:
       0: new           #70                 // class org/eclipse/rdf4j/queryrender/serql/SerqlTupleExprRenderer
       3: dup
       4: invokespecial #71                 // Method "<init>":()V
       7: astore_2
       8: aload_2
       9: new           #72                 // class java/util/ArrayList
      12: dup
      13: aload_0
      14: getfield      #16                 // Field mProjection:Ljava/util/List;
      17: invokespecial #73                 // Method java/util/ArrayList."<init>":(Ljava/util/Collection;)V
      20: putfield      #16                 // Field mProjection:Ljava/util/List;
      23: aload_2
      24: aload_0
      25: getfield      #22                 // Field mDistinct:Z
      28: putfield      #22                 // Field mDistinct:Z
      31: aload_2
      32: aload_0
      33: getfield      #24                 // Field mReduced:Z
      36: putfield      #24                 // Field mReduced:Z
      39: aload_2
      40: new           #74                 // class java/util/HashMap
      43: dup
      44: aload_0
      45: getfield      #38                 // Field mExtensions:Ljava/util/Map;
      48: invokespecial #75                 // Method java/util/HashMap."<init>":(Ljava/util/Map;)V
      51: putfield      #38                 // Field mExtensions:Ljava/util/Map;
      54: aload_2
      55: new           #72                 // class java/util/ArrayList
      58: dup
      59: aload_0
      60: getfield      #53                 // Field mOrdering:Ljava/util/List;
      63: invokespecial #73                 // Method java/util/ArrayList."<init>":(Ljava/util/Collection;)V
      66: putfield      #53                 // Field mOrdering:Ljava/util/List;
      69: aload_2
      70: aload_0
      71: getfield      #62                 // Field mLimit:J
      74: putfield      #62                 // Field mLimit:J
      77: aload_2
      78: aload_0
      79: getfield      #67                 // Field mOffset:J
      82: putfield      #67                 // Field mOffset:J
      85: aload_2
      86: aload_1
      87: invokevirtual #76                 // Method render:(Lorg/eclipse/rdf4j/query/algebra/TupleExpr;)Ljava/lang/String;
      90: areturn

  public void meet(org.eclipse.rdf4j.query.algebra.Union) throws java.lang.Exception;
    Code:
       0: aload_0
       1: aload_1
       2: invokevirtual #77                 // Method org/eclipse/rdf4j/query/algebra/Union.getLeftArg:()Lorg/eclipse/rdf4j/query/algebra/TupleExpr;
       5: invokespecial #78                 // Method renderTupleExpr:(Lorg/eclipse/rdf4j/query/algebra/TupleExpr;)Ljava/lang/String;
       8: astore_2
       9: aload_0
      10: aload_1
      11: invokevirtual #79                 // Method org/eclipse/rdf4j/query/algebra/Union.getRightArg:()Lorg/eclipse/rdf4j/query/algebra/TupleExpr;
      14: invokespecial #78                 // Method renderTupleExpr:(Lorg/eclipse/rdf4j/query/algebra/TupleExpr;)Ljava/lang/String;
      17: astore_3
      18: aload_0
      19: getfield      #4                  // Field mBuffer:Ljava/lang/StringBuffer;
      22: aload_2
      23: invokevirtual #80                 // Method java/lang/StringBuffer.append:(Ljava/lang/String;)Ljava/lang/StringBuffer;
      26: ldc           #81                 // String \nunion\n
      28: invokevirtual #80                 // Method java/lang/StringBuffer.append:(Ljava/lang/String;)Ljava/lang/StringBuffer;
      31: aload_3
      32: invokevirtual #80                 // Method java/lang/StringBuffer.append:(Ljava/lang/String;)Ljava/lang/StringBuffer;
      35: pop
      36: return

  public void meet(org.eclipse.rdf4j.query.algebra.Difference) throws java.lang.Exception;
    Code:
       0: aload_0
       1: aload_1
       2: invokevirtual #82                 // Method org/eclipse/rdf4j/query/algebra/Difference.getLeftArg:()Lorg/eclipse/rdf4j/query/algebra/TupleExpr;
       5: invokespecial #78                 // Method renderTupleExpr:(Lorg/eclipse/rdf4j/query/algebra/TupleExpr;)Ljava/lang/String;
       8: astore_2
       9: aload_0
      10: aload_1
      11: invokevirtual #83                 // Method org/eclipse/rdf4j/query/algebra/Difference.getRightArg:()Lorg/eclipse/rdf4j/query/algebra/TupleExpr;
      14: invokespecial #78                 // Method renderTupleExpr:(Lorg/eclipse/rdf4j/query/algebra/TupleExpr;)Ljava/lang/String;
      17: astore_3
      18: aload_0
      19: getfield      #4                  // Field mBuffer:Ljava/lang/StringBuffer;
      22: aload_2
      23: invokevirtual #80                 // Method java/lang/StringBuffer.append:(Ljava/lang/String;)Ljava/lang/StringBuffer;
      26: ldc           #84                 // String \nminus\n
      28: invokevirtual #80                 // Method java/lang/StringBuffer.append:(Ljava/lang/String;)Ljava/lang/StringBuffer;
      31: aload_3
      32: invokevirtual #80                 // Method java/lang/StringBuffer.append:(Ljava/lang/String;)Ljava/lang/StringBuffer;
      35: pop
      36: return

  public void meet(org.eclipse.rdf4j.query.algebra.Intersection) throws java.lang.Exception;
    Code:
       0: aload_0
       1: aload_1
       2: invokevirtual #85                 // Method org/eclipse/rdf4j/query/algebra/Intersection.getLeftArg:()Lorg/eclipse/rdf4j/query/algebra/TupleExpr;
       5: invokespecial #78                 // Method renderTupleExpr:(Lorg/eclipse/rdf4j/query/algebra/TupleExpr;)Ljava/lang/String;
       8: astore_2
       9: aload_0
      10: aload_1
      11: invokevirtual #86                 // Method org/eclipse/rdf4j/query/algebra/Intersection.getRightArg:()Lorg/eclipse/rdf4j/query/algebra/TupleExpr;
      14: invokespecial #78                 // Method renderTupleExpr:(Lorg/eclipse/rdf4j/query/algebra/TupleExpr;)Ljava/lang/String;
      17: astore_3
      18: aload_0
      19: getfield      #4                  // Field mBuffer:Ljava/lang/StringBuffer;
      22: aload_2
      23: invokevirtual #80                 // Method java/lang/StringBuffer.append:(Ljava/lang/String;)Ljava/lang/StringBuffer;
      26: ldc           #87                 // String \nintersection\n
      28: invokevirtual #80                 // Method java/lang/StringBuffer.append:(Ljava/lang/String;)Ljava/lang/StringBuffer;
      31: aload_3
      32: invokevirtual #80                 // Method java/lang/StringBuffer.append:(Ljava/lang/String;)Ljava/lang/StringBuffer;
      35: pop
      36: return

  private java.lang.String renderPattern(org.eclipse.rdf4j.query.algebra.StatementPattern) throws java.lang.Exception;
    Code:
       0: new           #14                 // class java/lang/StringBuilder
       3: dup
       4: invokespecial #15                 // Method java/lang/StringBuilder."<init>":()V
       7: ldc           #88                 // String {
       9: invokevirtual #20                 // Method java/lang/StringBuilder.append:(Ljava/lang/String;)Ljava/lang/StringBuilder;
      12: aload_0
      13: aload_1
      14: invokevirtual #89                 // Method org/eclipse/rdf4j/query/algebra/StatementPattern.getSubjectVar:()Lorg/eclipse/rdf4j/query/algebra/Var;
      17: invokevirtual #90                 // Method renderValueExpr:(Lorg/eclipse/rdf4j/query/algebra/ValueExpr;)Ljava/lang/String;
      20: invokevirtual #20                 // Method java/lang/StringBuilder.append:(Ljava/lang/String;)Ljava/lang/StringBuilder;
      23: ldc           #91                 // String }
      25: invokevirtual #20                 // Method java/lang/StringBuilder.append:(Ljava/lang/String;)Ljava/lang/StringBuilder;
      28: aload_0
      29: aload_1
      30: invokevirtual #92                 // Method org/eclipse/rdf4j/query/algebra/StatementPattern.getPredicateVar:()Lorg/eclipse/rdf4j/query/algebra/Var;
      33: invokevirtual #90                 // Method renderValueExpr:(Lorg/eclipse/rdf4j/query/algebra/ValueExpr;)Ljava/lang/String;
      36: invokevirtual #20                 // Method java/lang/StringBuilder.append:(Ljava/lang/String;)Ljava/lang/StringBuilder;
      39: ldc           #93                 // String  {
      41: invokevirtual #20                 // Method java/lang/StringBuilder.append:(Ljava/lang/String;)Ljava/lang/StringBuilder;
      44: aload_0
      45: aload_1
      46: invokevirtual #94                 // Method org/eclipse/rdf4j/query/algebra/StatementPattern.getObjectVar:()Lorg/eclipse/rdf4j/query/algebra/Var;
      49: invokevirtual #90                 // Method renderValueExpr:(Lorg/eclipse/rdf4j/query/algebra/ValueExpr;)Ljava/lang/String;
      52: invokevirtual #20                 // Method java/lang/StringBuilder.append:(Ljava/lang/String;)Ljava/lang/StringBuilder;
      55: ldc           #91                 // String }
      57: invokevirtual #20                 // Method java/lang/StringBuilder.append:(Ljava/lang/String;)Ljava/lang/StringBuilder;
      60: invokevirtual #69                 // Method java/lang/StringBuilder.toString:()Ljava/lang/String;
      63: areturn

  protected java.lang.String renderValueExpr(org.eclipse.rdf4j.query.algebra.ValueExpr) throws java.lang.Exception;
    Code:
       0: aload_0
       1: getfield      #8                  // Field mValueExprRenderer:Lorg/eclipse/rdf4j/queryrender/serql/SerqlValueExprRenderer;
       4: aload_1
       5: invokevirtual #43                 // Method org/eclipse/rdf4j/queryrender/serql/SerqlValueExprRenderer.render:(Lorg/eclipse/rdf4j/query/algebra/ValueExpr;)Ljava/lang/String;
       8: areturn

  public void meet(org.eclipse.rdf4j.query.algebra.Join) throws java.lang.Exception;
    Code:
       0: aload_1
       1: invokevirtual #95                 // Method org/eclipse/rdf4j/query/algebra/Join.getLeftArg:()Lorg/eclipse/rdf4j/query/algebra/TupleExpr;
       4: aload_0
       5: invokeinterface #11,  2           // InterfaceMethod org/eclipse/rdf4j/query/algebra/TupleExpr.visit:(Lorg/eclipse/rdf4j/query/algebra/QueryModelVisitor;)V
      10: aload_1
      11: invokevirtual #96                 // Method org/eclipse/rdf4j/query/algebra/Join.getRightArg:()Lorg/eclipse/rdf4j/query/algebra/TupleExpr;
      14: aload_0
      15: invokeinterface #11,  2           // InterfaceMethod org/eclipse/rdf4j/query/algebra/TupleExpr.visit:(Lorg/eclipse/rdf4j/query/algebra/QueryModelVisitor;)V
      20: return

  public void meet(org.eclipse.rdf4j.query.algebra.LeftJoin) throws java.lang.Exception;
    Code:
       0: aload_1
       1: invokevirtual #97                 // Method org/eclipse/rdf4j/query/algebra/LeftJoin.getLeftArg:()Lorg/eclipse/rdf4j/query/algebra/TupleExpr;
       4: aload_0
       5: invokeinterface #11,  2           // InterfaceMethod org/eclipse/rdf4j/query/algebra/TupleExpr.visit:(Lorg/eclipse/rdf4j/query/algebra/QueryModelVisitor;)V
      10: aload_0
      11: getfield      #5                  // Field mJoinBuffer:Ljava/lang/StringBuffer;
      14: ldc           #98                 // String  [
      16: invokevirtual #80                 // Method java/lang/StringBuffer.append:(Ljava/lang/String;)Ljava/lang/StringBuffer;
      19: pop
      20: aload_1
      21: invokevirtual #99                 // Method org/eclipse/rdf4j/query/algebra/LeftJoin.getRightArg:()Lorg/eclipse/rdf4j/query/algebra/TupleExpr;
      24: aload_0
      25: invokeinterface #11,  2           // InterfaceMethod org/eclipse/rdf4j/query/algebra/TupleExpr.visit:(Lorg/eclipse/rdf4j/query/algebra/QueryModelVisitor;)V
      30: aload_1
      31: invokevirtual #100                // Method org/eclipse/rdf4j/query/algebra/LeftJoin.getCondition:()Lorg/eclipse/rdf4j/query/algebra/ValueExpr;
      34: ifnull        53
      37: aload_0
      38: getfield      #5                  // Field mJoinBuffer:Ljava/lang/StringBuffer;
      41: aload_0
      42: aload_1
      43: invokevirtual #100                // Method org/eclipse/rdf4j/query/algebra/LeftJoin.getCondition:()Lorg/eclipse/rdf4j/query/algebra/ValueExpr;
      46: invokevirtual #90                 // Method renderValueExpr:(Lorg/eclipse/rdf4j/query/algebra/ValueExpr;)Ljava/lang/String;
      49: invokevirtual #80                 // Method java/lang/StringBuffer.append:(Ljava/lang/String;)Ljava/lang/StringBuffer;
      52: pop
      53: aload_0
      54: getfield      #5                  // Field mJoinBuffer:Ljava/lang/StringBuffer;
      57: aload_0
      58: getfield      #5                  // Field mJoinBuffer:Ljava/lang/StringBuffer;
      61: ldc           #47                 // String ,
      63: invokevirtual #48                 // Method java/lang/StringBuffer.lastIndexOf:(Ljava/lang/String;)I
      66: bipush        32
      68: invokevirtual #49                 // Method java/lang/StringBuffer.setCharAt:(IC)V
      71: aload_0
      72: getfield      #5                  // Field mJoinBuffer:Ljava/lang/StringBuffer;
      75: ldc           #101                // String ],
      77: invokevirtual #80                 // Method java/lang/StringBuffer.append:(Ljava/lang/String;)Ljava/lang/StringBuffer;
      80: pop
      81: return

  public void meet(org.eclipse.rdf4j.query.algebra.StatementPattern) throws java.lang.Exception;
    Code:
       0: aload_0
       1: getfield      #5                  // Field mJoinBuffer:Ljava/lang/StringBuffer;
       4: aload_0
       5: aload_1
       6: invokespecial #34                 // Method renderPattern:(Lorg/eclipse/rdf4j/query/algebra/StatementPattern;)Ljava/lang/String;
       9: invokevirtual #80                 // Method java/lang/StringBuffer.append:(Ljava/lang/String;)Ljava/lang/StringBuffer;
      12: ldc           #32                 // String ,\n
      14: invokevirtual #80                 // Method java/lang/StringBuffer.append:(Ljava/lang/String;)Ljava/lang/StringBuffer;
      17: pop
      18: return

  public void meet(org.eclipse.rdf4j.query.algebra.Filter) throws java.lang.Exception;
    Code:
       0: aload_0
       1: getfield      #10                 // Field mFilter:Lorg/eclipse/rdf4j/query/algebra/ValueExpr;
       4: ifnonnull     18
       7: aload_0
       8: aload_1
       9: invokevirtual #102                // Method org/eclipse/rdf4j/query/algebra/Filter.getCondition:()Lorg/eclipse/rdf4j/query/algebra/ValueExpr;
      12: putfield      #10                 // Field mFilter:Lorg/eclipse/rdf4j/query/algebra/ValueExpr;
      15: goto          37
      18: aload_0
      19: new           #103                // class org/eclipse/rdf4j/query/algebra/And
      22: dup
      23: aload_0
      24: getfield      #10                 // Field mFilter:Lorg/eclipse/rdf4j/query/algebra/ValueExpr;
      27: aload_1
      28: invokevirtual #102                // Method org/eclipse/rdf4j/query/algebra/Filter.getCondition:()Lorg/eclipse/rdf4j/query/algebra/ValueExpr;
      31: invokespecial #104                // Method org/eclipse/rdf4j/query/algebra/And."<init>":(Lorg/eclipse/rdf4j/query/algebra/ValueExpr;Lorg/eclipse/rdf4j/query/algebra/ValueExpr;)V
      34: putfield      #10                 // Field mFilter:Lorg/eclipse/rdf4j/query/algebra/ValueExpr;
      37: aload_1
      38: aload_0
      39: invokevirtual #105                // Method org/eclipse/rdf4j/query/algebra/Filter.visitChildren:(Lorg/eclipse/rdf4j/query/algebra/QueryModelVisitor;)V
      42: return
}
