Compiled from "ProcessEngineConfigurationBuildItem.java"
public final class org.camunda.bpm.quarkus.engine.extension.deployment.impl.ProcessEngineConfigurationBuildItem extends io.quarkus.builder.item.SimpleBuildItem {
  protected io.quarkus.runtime.RuntimeValue<org.camunda.bpm.engine.impl.cfg.ProcessEngineConfigurationImpl> processEngineConfiguration;

  public org.camunda.bpm.quarkus.engine.extension.deployment.impl.ProcessEngineConfigurationBuildItem(io.quarkus.runtime.RuntimeValue<org.camunda.bpm.engine.impl.cfg.ProcessEngineConfigurationImpl>);
    Code:
       0: aload_0
       1: invokespecial #1                  // Method io/quarkus/builder/item/SimpleBuildItem."<init>":()V
       4: aload_0
       5: aload_1
       6: putfield      #2                  // Field processEngineConfiguration:Lio/quarkus/runtime/RuntimeValue;
       9: return

  public io.quarkus.runtime.RuntimeValue<org.camunda.bpm.engine.impl.cfg.ProcessEngineConfigurationImpl> getProcessEngineConfiguration();
    Code:
       0: aload_0
       1: getfield      #2                  // Field processEngineConfiguration:Lio/quarkus/runtime/RuntimeValue;
       4: areturn
}
