Compiled from "LocalArtifactRegistration.java"
public class org.sonatype.aether.repository.LocalArtifactRegistration {
  private org.sonatype.aether.artifact.Artifact artifact;

  private org.sonatype.aether.repository.RemoteRepository repository;

  private java.util.Collection<java.lang.String> contexts;

  public org.sonatype.aether.repository.LocalArtifactRegistration();
    Code:
       0: aload_0
       1: invokespecial #1                  // Method java/lang/Object."<init>":()V
       4: aload_0
       5: invokestatic  #2                  // Method java/util/Collections.emptyList:()Ljava/util/List;
       8: putfield      #3                  // Field contexts:Ljava/util/Collection;
      11: return

  public org.sonatype.aether.repository.LocalArtifactRegistration(org.sonatype.aether.artifact.Artifact);
    Code:
       0: aload_0
       1: invokespecial #1                  // Method java/lang/Object."<init>":()V
       4: aload_0
       5: invokestatic  #2                  // Method java/util/Collections.emptyList:()Ljava/util/List;
       8: putfield      #3                  // Field contexts:Ljava/util/Collection;
      11: aload_0
      12: aload_1
      13: invokevirtual #4                  // Method setArtifact:(Lorg/sonatype/aether/artifact/Artifact;)Lorg/sonatype/aether/repository/LocalArtifactRegistration;
      16: pop
      17: return

  public org.sonatype.aether.repository.LocalArtifactRegistration(org.sonatype.aether.artifact.Artifact, org.sonatype.aether.repository.RemoteRepository, java.util.Collection<java.lang.String>);
    Code:
       0: aload_0
       1: invokespecial #1                  // Method java/lang/Object."<init>":()V
       4: aload_0
       5: invokestatic  #2                  // Method java/util/Collections.emptyList:()Ljava/util/List;
       8: putfield      #3                  // Field contexts:Ljava/util/Collection;
      11: aload_0
      12: aload_1
      13: invokevirtual #4                  // Method setArtifact:(Lorg/sonatype/aether/artifact/Artifact;)Lorg/sonatype/aether/repository/LocalArtifactRegistration;
      16: pop
      17: aload_0
      18: aload_2
      19: invokevirtual #5                  // Method setRepository:(Lorg/sonatype/aether/repository/RemoteRepository;)Lorg/sonatype/aether/repository/LocalArtifactRegistration;
      22: pop
      23: aload_0
      24: aload_3
      25: invokevirtual #6                  // Method setContexts:(Ljava/util/Collection;)Lorg/sonatype/aether/repository/LocalArtifactRegistration;
      28: pop
      29: return

  public org.sonatype.aether.artifact.Artifact getArtifact();
    Code:
       0: aload_0
       1: getfield      #7                  // Field artifact:Lorg/sonatype/aether/artifact/Artifact;
       4: areturn

  public org.sonatype.aether.repository.LocalArtifactRegistration setArtifact(org.sonatype.aether.artifact.Artifact);
    Code:
       0: aload_0
       1: aload_1
       2: putfield      #7                  // Field artifact:Lorg/sonatype/aether/artifact/Artifact;
       5: aload_0
       6: areturn

  public org.sonatype.aether.repository.RemoteRepository getRepository();
    Code:
       0: aload_0
       1: getfield      #8                  // Field repository:Lorg/sonatype/aether/repository/RemoteRepository;
       4: areturn

  public org.sonatype.aether.repository.LocalArtifactRegistration setRepository(org.sonatype.aether.repository.RemoteRepository);
    Code:
       0: aload_0
       1: aload_1
       2: putfield      #8                  // Field repository:Lorg/sonatype/aether/repository/RemoteRepository;
       5: aload_0
       6: areturn

  public java.util.Collection<java.lang.String> getContexts();
    Code:
       0: aload_0
       1: getfield      #3                  // Field contexts:Ljava/util/Collection;
       4: areturn

  public org.sonatype.aether.repository.LocalArtifactRegistration setContexts(java.util.Collection<java.lang.String>);
    Code:
       0: aload_1
       1: ifnull        12
       4: aload_0
       5: aload_1
       6: putfield      #3                  // Field contexts:Ljava/util/Collection;
       9: goto          19
      12: aload_0
      13: invokestatic  #2                  // Method java/util/Collections.emptyList:()Ljava/util/List;
      16: putfield      #3                  // Field contexts:Ljava/util/Collection;
      19: aload_0
      20: areturn
}
