Compiled from "OAuth2MethodSecurityConfiguration.java"
public class org.springframework.boot.autoconfigure.security.oauth2.method.OAuth2MethodSecurityConfiguration implements org.springframework.beans.factory.config.BeanFactoryPostProcessor,org.springframework.context.ApplicationContextAware {
  private org.springframework.context.ApplicationContext applicationContext;

  public org.springframework.boot.autoconfigure.security.oauth2.method.OAuth2MethodSecurityConfiguration();
    Code:
       0: aload_0
       1: invokespecial #1                  // Method java/lang/Object."<init>":()V
       4: return

  public void setApplicationContext(org.springframework.context.ApplicationContext) throws org.springframework.beans.BeansException;
    Code:
       0: aload_0
       1: aload_1
       2: putfield      #2                  // Field applicationContext:Lorg/springframework/context/ApplicationContext;
       5: return

  public void postProcessBeanFactory(org.springframework.beans.factory.config.ConfigurableListableBeanFactory) throws org.springframework.beans.BeansException;
    Code:
       0: new           #3                  // class org/springframework/boot/autoconfigure/security/oauth2/method/OAuth2MethodSecurityConfiguration$OAuth2ExpressionHandlerInjectionPostProcessor
       3: dup
       4: aload_0
       5: getfield      #2                  // Field applicationContext:Lorg/springframework/context/ApplicationContext;
       8: invokespecial #4                  // Method org/springframework/boot/autoconfigure/security/oauth2/method/OAuth2MethodSecurityConfiguration$OAuth2ExpressionHandlerInjectionPostProcessor."<init>":(Lorg/springframework/context/ApplicationContext;)V
      11: astore_2
      12: aload_1
      13: aload_2
      14: invokeinterface #5,  2            // InterfaceMethod org/springframework/beans/factory/config/ConfigurableListableBeanFactory.addBeanPostProcessor:(Lorg/springframework/beans/factory/config/BeanPostProcessor;)V
      19: return
}
