Compiled from "PackratParsers.scala"
public final class scala.util.parsing.combinator.PackratParsers$$anonfun$scala$util$parsing$combinator$PackratParsers$$setupLR$2 extends scala.runtime.AbstractFunction1<scala.util.parsing.combinator.PackratParsers$LR, scala.Option<scala.runtime.BoxedUnit>> implements scala.Serializable {
  public static final long serialVersionUID;

  private final scala.util.parsing.combinator.PackratParsers$LR recDetect$1;

  public final scala.Option<scala.runtime.BoxedUnit> apply(scala.util.parsing.combinator.PackratParsers$LR);
    Code:
       0: aload_1
       1: aload_0
       2: getfield      #20                 // Field recDetect$1:Lscala/util/parsing/combinator/PackratParsers$LR;
       5: invokevirtual #26                 // Method scala/util/parsing/combinator/PackratParsers$LR.head:()Lscala/Option;
       8: invokevirtual #30                 // Method scala/util/parsing/combinator/PackratParsers$LR.head_$eq:(Lscala/Option;)V
      11: aload_0
      12: getfield      #20                 // Field recDetect$1:Lscala/util/parsing/combinator/PackratParsers$LR;
      15: invokevirtual #26                 // Method scala/util/parsing/combinator/PackratParsers$LR.head:()Lscala/Option;
      18: new           #32                 // class scala/util/parsing/combinator/PackratParsers$$anonfun$scala$util$parsing$combinator$PackratParsers$$setupLR$2$$anonfun$apply$1
      21: dup
      22: aload_0
      23: aload_1
      24: invokespecial #36                 // Method scala/util/parsing/combinator/PackratParsers$$anonfun$scala$util$parsing$combinator$PackratParsers$$setupLR$2$$anonfun$apply$1."<init>":(Lscala/util/parsing/combinator/PackratParsers$$anonfun$scala$util$parsing$combinator$PackratParsers$$setupLR$2;Lscala/util/parsing/combinator/PackratParsers$LR;)V
      27: invokevirtual #42                 // Method scala/Option.map:(Lscala/Function1;)Lscala/Option;
      30: areturn

  public final java.lang.Object apply(java.lang.Object);
    Code:
       0: aload_0
       1: aload_1
       2: checkcast     #22                 // class scala/util/parsing/combinator/PackratParsers$LR
       5: invokevirtual #48                 // Method apply:(Lscala/util/parsing/combinator/PackratParsers$LR;)Lscala/Option;
       8: areturn

  public scala.util.parsing.combinator.PackratParsers$$anonfun$scala$util$parsing$combinator$PackratParsers$$setupLR$2(scala.util.parsing.combinator.PackratParsers, scala.util.parsing.combinator.PackratParsers$LR);
    Code:
       0: aload_0
       1: aload_2
       2: putfield      #20                 // Field recDetect$1:Lscala/util/parsing/combinator/PackratParsers$LR;
       5: aload_0
       6: invokespecial #54                 // Method scala/runtime/AbstractFunction1."<init>":()V
       9: return
}
