Compiled from "AhcClient.java"
public class org.sonatype.spice.zapper.client.ahc.AhcClient extends org.sonatype.spice.zapper.internal.transport.AbstractClient<org.sonatype.spice.zapper.client.ahc.AhcTrack> implements java.util.concurrent.Executor {
  private final com.ning.http.client.AsyncHttpClient asyncHttpClient;

  private final com.ning.http.client.Realm realm;

  private final com.ning.http.client.ProxyServer proxyServer;

  public org.sonatype.spice.zapper.client.ahc.AhcClient(org.sonatype.spice.zapper.Parameters, java.lang.String, com.ning.http.client.AsyncHttpClient);
    Code:
       0: aload_0
       1: aload_1
       2: aload_2
       3: aload_3
       4: aconst_null
       5: aconst_null
       6: invokespecial #1                  // Method "<init>":(Lorg/sonatype/spice/zapper/Parameters;Ljava/lang/String;Lcom/ning/http/client/AsyncHttpClient;Lcom/ning/http/client/Realm;Lcom/ning/http/client/ProxyServer;)V
       9: return

  public org.sonatype.spice.zapper.client.ahc.AhcClient(org.sonatype.spice.zapper.Parameters, java.lang.String, com.ning.http.client.AsyncHttpClient, com.ning.http.client.Realm, com.ning.http.client.ProxyServer);
    Code:
       0: aload_0
       1: aload_1
       2: aload_2
       3: invokespecial #2                  // Method org/sonatype/spice/zapper/internal/transport/AbstractClient."<init>":(Lorg/sonatype/spice/zapper/Parameters;Ljava/lang/String;)V
       6: aload_0
       7: aload_3
       8: ldc_w         #3                  // class com/ning/http/client/AsyncHttpClient
      11: invokestatic  #4                  // Method org/sonatype/spice/zapper/internal/Check.notNull:(Ljava/lang/Object;Ljava/lang/Class;)Ljava/lang/Object;
      14: checkcast     #3                  // class com/ning/http/client/AsyncHttpClient
      17: putfield      #5                  // Field asyncHttpClient:Lcom/ning/http/client/AsyncHttpClient;
      20: aload_0
      21: aload         4
      23: putfield      #6                  // Field realm:Lcom/ning/http/client/Realm;
      26: aload_0
      27: aload         5
      29: putfield      #7                  // Field proxyServer:Lcom/ning/http/client/ProxyServer;
      32: return

  public void close();
    Code:
       0: aload_0
       1: getfield      #5                  // Field asyncHttpClient:Lcom/ning/http/client/AsyncHttpClient;
       4: invokevirtual #8                  // Method com/ning/http/client/AsyncHttpClient.close:()V
       7: return

  protected void doUpload(org.sonatype.spice.zapper.internal.Transfer, org.sonatype.spice.zapper.internal.Protocol, int) throws java.io.IOException;
    Code:
       0: iload_3
       1: anewarray     #9                  // class org/sonatype/spice/zapper/client/ahc/AhcTrack
       4: astore        4
       6: iconst_0
       7: istore        5
       9: iload         5
      11: iload_3
      12: if_icmpge     68
      15: aload         4
      17: iload         5
      19: new           #9                  // class org/sonatype/spice/zapper/client/ahc/AhcTrack
      22: dup
      23: new           #10                 // class org/sonatype/spice/zapper/internal/transport/TrackIdentifier
      26: dup
      27: new           #11                 // class java/lang/StringBuilder
      30: dup
      31: invokespecial #12                 // Method java/lang/StringBuilder."<init>":()V
      34: ldc           #13                 // String T
      36: invokevirtual #14                 // Method java/lang/StringBuilder.append:(Ljava/lang/String;)Ljava/lang/StringBuilder;
      39: iload         5
      41: invokestatic  #15                 // Method java/lang/String.valueOf:(I)Ljava/lang/String;
      44: invokevirtual #14                 // Method java/lang/StringBuilder.append:(Ljava/lang/String;)Ljava/lang/StringBuilder;
      47: invokevirtual #16                 // Method java/lang/StringBuilder.toString:()Ljava/lang/String;
      50: invokespecial #17                 // Method org/sonatype/spice/zapper/internal/transport/TrackIdentifier."<init>":(Ljava/lang/String;)V
      53: aload_0
      54: aload_1
      55: invokevirtual #18                 // Method org/sonatype/spice/zapper/internal/Transfer.getPayloadSupplier:()Lorg/sonatype/spice/zapper/internal/PayloadSupplier;
      58: invokespecial #19                 // Method org/sonatype/spice/zapper/client/ahc/AhcTrack."<init>":(Lorg/sonatype/spice/zapper/internal/transport/TrackIdentifier;Lorg/sonatype/spice/zapper/client/ahc/AhcClient;Lorg/sonatype/spice/zapper/internal/PayloadSupplier;)V
      61: aastore
      62: iinc          5, 1
      65: goto          9
      68: iload_3
      69: anewarray     #20                 // class java/io/IOException
      72: astore        5
      74: iconst_1
      75: istore        6
      77: iconst_0
      78: istore        7
      80: iload         7
      82: iload_3
      83: if_icmpge     127
      86: aload         4
      88: iload         7
      90: aaload
      91: invokevirtual #21                 // Method org/sonatype/spice/zapper/client/ahc/AhcTrack.waitUntilDone:()V
      94: aload         4
      96: iload         7
      98: aaload
      99: invokevirtual #22                 // Method org/sonatype/spice/zapper/client/ahc/AhcTrack.getException:()Ljava/io/IOException;
     102: ifnull        121
     105: iconst_0
     106: istore        6
     108: aload         5
     110: iload         7
     112: aload         4
     114: iload         7
     116: aaload
     117: invokevirtual #22                 // Method org/sonatype/spice/zapper/client/ahc/AhcTrack.getException:()Ljava/io/IOException;
     120: aastore
     121: iinc          7, 1
     124: goto          80
     127: iload         6
     129: ifne          144
     132: new           #23                 // class org/sonatype/spice/zapper/AggregatingIOException
     135: dup
     136: ldc           #24                 // String Upload failed.
     138: aload         5
     140: invokespecial #25                 // Method org/sonatype/spice/zapper/AggregatingIOException."<init>":(Ljava/lang/String;[Ljava/io/IOException;)V
     143: athrow
     144: return

  public org.sonatype.spice.zapper.internal.transport.State upload(org.sonatype.spice.zapper.internal.Payload, org.sonatype.spice.zapper.client.ahc.AhcTrack) throws java.io.IOException;
    Code:
       0: new           #11                 // class java/lang/StringBuilder
       3: dup
       4: invokespecial #12                 // Method java/lang/StringBuilder."<init>":()V
       7: aload_0
       8: invokevirtual #26                 // Method getRemoteUrl:()Ljava/lang/String;
      11: invokevirtual #14                 // Method java/lang/StringBuilder.append:(Ljava/lang/String;)Ljava/lang/StringBuilder;
      14: aload_1
      15: invokeinterface #27,  1           // InterfaceMethod org/sonatype/spice/zapper/internal/Payload.getPath:()Lorg/sonatype/spice/zapper/Path;
      20: invokevirtual #28                 // Method org/sonatype/spice/zapper/Path.stringValue:()Ljava/lang/String;
      23: invokevirtual #14                 // Method java/lang/StringBuilder.append:(Ljava/lang/String;)Ljava/lang/StringBuilder;
      26: invokevirtual #16                 // Method java/lang/StringBuilder.toString:()Ljava/lang/String;
      29: astore_3
      30: aload_0
      31: getfield      #5                  // Field asyncHttpClient:Lcom/ning/http/client/AsyncHttpClient;
      34: aload_3
      35: invokevirtual #29                 // Method com/ning/http/client/AsyncHttpClient.preparePut:(Ljava/lang/String;)Lcom/ning/http/client/AsyncHttpClient$BoundRequestBuilder;
      38: new           #30                 // class org/sonatype/spice/zapper/client/ahc/ZapperBodyGenerator
      41: dup
      42: aload_1
      43: invokespecial #31                 // Method org/sonatype/spice/zapper/client/ahc/ZapperBodyGenerator."<init>":(Lorg/sonatype/spice/zapper/internal/Payload;)V
      46: invokevirtual #32                 // Method com/ning/http/client/AsyncHttpClient$BoundRequestBuilder.setBody:(Lcom/ning/http/client/BodyGenerator;)Lcom/ning/http/client/RequestBuilderBase;
      49: checkcast     #33                 // class com/ning/http/client/AsyncHttpClient$BoundRequestBuilder
      52: ldc           #34                 // String X-Zapper-Transfer-ID
      54: aload_1
      55: invokeinterface #35,  1           // InterfaceMethod org/sonatype/spice/zapper/internal/Payload.getTransferIdentifier:()Lorg/sonatype/spice/zapper/internal/TransferIdentifier;
      60: invokevirtual #36                 // Method org/sonatype/spice/zapper/internal/TransferIdentifier.stringValue:()Ljava/lang/String;
      63: invokevirtual #37                 // Method com/ning/http/client/AsyncHttpClient$BoundRequestBuilder.setHeader:(Ljava/lang/String;Ljava/lang/String;)Lcom/ning/http/client/AsyncHttpClient$BoundRequestBuilder;
      66: astore        4
      68: aload_0
      69: getfield      #6                  // Field realm:Lcom/ning/http/client/Realm;
      72: ifnull        85
      75: aload         4
      77: aload_0
      78: getfield      #6                  // Field realm:Lcom/ning/http/client/Realm;
      81: invokevirtual #38                 // Method com/ning/http/client/AsyncHttpClient$BoundRequestBuilder.setRealm:(Lcom/ning/http/client/Realm;)Lcom/ning/http/client/RequestBuilderBase;
      84: pop
      85: aload_0
      86: getfield      #7                  // Field proxyServer:Lcom/ning/http/client/ProxyServer;
      89: ifnull        102
      92: aload         4
      94: aload_0
      95: getfield      #7                  // Field proxyServer:Lcom/ning/http/client/ProxyServer;
      98: invokevirtual #39                 // Method com/ning/http/client/AsyncHttpClient$BoundRequestBuilder.setProxyServer:(Lcom/ning/http/client/ProxyServer;)Lcom/ning/http/client/RequestBuilderBase;
     101: pop
     102: aload_0
     103: getfield      #5                  // Field asyncHttpClient:Lcom/ning/http/client/AsyncHttpClient;
     106: aload         4
     108: invokevirtual #40                 // Method com/ning/http/client/AsyncHttpClient$BoundRequestBuilder.build:()Lcom/ning/http/client/Request;
     111: invokevirtual #41                 // Method com/ning/http/client/AsyncHttpClient.executeRequest:(Lcom/ning/http/client/Request;)Lcom/ning/http/client/ListenableFuture;
     114: astore        5
     116: aload_2
     117: aload         5
     119: invokevirtual #42                 // Method org/sonatype/spice/zapper/client/ahc/AhcTrack.setListenableFuture:(Lcom/ning/http/client/ListenableFuture;)V
     122: aload         5
     124: aload_2
     125: aload_0
     126: invokeinterface #43,  3           // InterfaceMethod com/ning/http/client/ListenableFuture.addListener:(Ljava/lang/Runnable;Ljava/util/concurrent/Executor;)Lcom/ning/http/client/ListenableFuture;
     131: pop
     132: getstatic     #44                 // Field org/sonatype/spice/zapper/internal/transport/State.SUCCESS:Lorg/sonatype/spice/zapper/internal/transport/State;
     135: areturn

  public org.sonatype.spice.zapper.internal.transport.State upload(org.sonatype.spice.zapper.internal.Payload) throws java.io.IOException;
    Code:
       0: new           #11                 // class java/lang/StringBuilder
       3: dup
       4: invokespecial #12                 // Method java/lang/StringBuilder."<init>":()V
       7: aload_0
       8: invokevirtual #26                 // Method getRemoteUrl:()Ljava/lang/String;
      11: invokevirtual #14                 // Method java/lang/StringBuilder.append:(Ljava/lang/String;)Ljava/lang/StringBuilder;
      14: aload_1
      15: invokeinterface #27,  1           // InterfaceMethod org/sonatype/spice/zapper/internal/Payload.getPath:()Lorg/sonatype/spice/zapper/Path;
      20: invokevirtual #28                 // Method org/sonatype/spice/zapper/Path.stringValue:()Ljava/lang/String;
      23: invokevirtual #14                 // Method java/lang/StringBuilder.append:(Ljava/lang/String;)Ljava/lang/StringBuilder;
      26: invokevirtual #16                 // Method java/lang/StringBuilder.toString:()Ljava/lang/String;
      29: astore_2
      30: aload_0
      31: getfield      #5                  // Field asyncHttpClient:Lcom/ning/http/client/AsyncHttpClient;
      34: aload_2
      35: invokevirtual #29                 // Method com/ning/http/client/AsyncHttpClient.preparePut:(Ljava/lang/String;)Lcom/ning/http/client/AsyncHttpClient$BoundRequestBuilder;
      38: new           #30                 // class org/sonatype/spice/zapper/client/ahc/ZapperBodyGenerator
      41: dup
      42: aload_1
      43: invokespecial #31                 // Method org/sonatype/spice/zapper/client/ahc/ZapperBodyGenerator."<init>":(Lorg/sonatype/spice/zapper/internal/Payload;)V
      46: invokevirtual #32                 // Method com/ning/http/client/AsyncHttpClient$BoundRequestBuilder.setBody:(Lcom/ning/http/client/BodyGenerator;)Lcom/ning/http/client/RequestBuilderBase;
      49: checkcast     #33                 // class com/ning/http/client/AsyncHttpClient$BoundRequestBuilder
      52: ldc           #34                 // String X-Zapper-Transfer-ID
      54: aload_1
      55: invokeinterface #35,  1           // InterfaceMethod org/sonatype/spice/zapper/internal/Payload.getTransferIdentifier:()Lorg/sonatype/spice/zapper/internal/TransferIdentifier;
      60: invokevirtual #36                 // Method org/sonatype/spice/zapper/internal/TransferIdentifier.stringValue:()Ljava/lang/String;
      63: invokevirtual #37                 // Method com/ning/http/client/AsyncHttpClient$BoundRequestBuilder.setHeader:(Ljava/lang/String;Ljava/lang/String;)Lcom/ning/http/client/AsyncHttpClient$BoundRequestBuilder;
      66: astore_3
      67: aload_0
      68: getfield      #6                  // Field realm:Lcom/ning/http/client/Realm;
      71: ifnull        83
      74: aload_3
      75: aload_0
      76: getfield      #6                  // Field realm:Lcom/ning/http/client/Realm;
      79: invokevirtual #38                 // Method com/ning/http/client/AsyncHttpClient$BoundRequestBuilder.setRealm:(Lcom/ning/http/client/Realm;)Lcom/ning/http/client/RequestBuilderBase;
      82: pop
      83: aload_0
      84: getfield      #7                  // Field proxyServer:Lcom/ning/http/client/ProxyServer;
      87: ifnull        99
      90: aload_3
      91: aload_0
      92: getfield      #7                  // Field proxyServer:Lcom/ning/http/client/ProxyServer;
      95: invokevirtual #39                 // Method com/ning/http/client/AsyncHttpClient$BoundRequestBuilder.setProxyServer:(Lcom/ning/http/client/ProxyServer;)Lcom/ning/http/client/RequestBuilderBase;
      98: pop
      99: aload_0
     100: getfield      #5                  // Field asyncHttpClient:Lcom/ning/http/client/AsyncHttpClient;
     103: aload_3
     104: invokevirtual #40                 // Method com/ning/http/client/AsyncHttpClient$BoundRequestBuilder.build:()Lcom/ning/http/client/Request;
     107: invokevirtual #41                 // Method com/ning/http/client/AsyncHttpClient.executeRequest:(Lcom/ning/http/client/Request;)Lcom/ning/http/client/ListenableFuture;
     110: astore        4
     112: aload         4
     114: invokeinterface #45,  1           // InterfaceMethod com/ning/http/client/ListenableFuture.get:()Ljava/lang/Object;
     119: checkcast     #46                 // class com/ning/http/client/Response
     122: astore        5
     124: goto          147
     127: astore        6
     129: getstatic     #48                 // Field org/sonatype/spice/zapper/internal/transport/State.FAILURE:Lorg/sonatype/spice/zapper/internal/transport/State;
     132: areturn
     133: astore        6
     135: new           #20                 // class java/io/IOException
     138: dup
     139: ldc           #50                 // String Execution failed!
     141: aload         6
     143: invokespecial #51                 // Method java/io/IOException."<init>":(Ljava/lang/String;Ljava/lang/Throwable;)V
     146: athrow
     147: aload         5
     149: invokeinterface #52,  1           // InterfaceMethod com/ning/http/client/Response.getStatusCode:()I
     154: sipush        199
     157: if_icmple     173
     160: aload         5
     162: invokeinterface #52,  1           // InterfaceMethod com/ning/http/client/Response.getStatusCode:()I
     167: sipush        299
     170: if_icmplt     213
     173: new           #20                 // class java/io/IOException
     176: dup
     177: ldc           #53                 // String Unexpected server response: %s %s
     179: iconst_2
     180: anewarray     #54                 // class java/lang/Object
     183: dup
     184: iconst_0
     185: aload         5
     187: invokeinterface #52,  1           // InterfaceMethod com/ning/http/client/Response.getStatusCode:()I
     192: invokestatic  #55                 // Method java/lang/Integer.valueOf:(I)Ljava/lang/Integer;
     195: aastore
     196: dup
     197: iconst_1
     198: aload         5
     200: invokeinterface #56,  1           // InterfaceMethod com/ning/http/client/Response.getStatusText:()Ljava/lang/String;
     205: aastore
     206: invokestatic  #57                 // Method java/lang/String.format:(Ljava/lang/String;[Ljava/lang/Object;)Ljava/lang/String;
     209: invokespecial #58                 // Method java/io/IOException."<init>":(Ljava/lang/String;)V
     212: athrow
     213: getstatic     #44                 // Field org/sonatype/spice/zapper/internal/transport/State.SUCCESS:Lorg/sonatype/spice/zapper/internal/transport/State;
     216: areturn
    Exception table:
       from    to  target type
         112   124   127   Class java/lang/InterruptedException
         112   124   133   Class java/util/concurrent/ExecutionException

  public void execute(java.lang.Runnable);
    Code:
       0: aload_1
       1: invokeinterface #59,  1           // InterfaceMethod java/lang/Runnable.run:()V
       6: return

  public org.sonatype.spice.zapper.internal.transport.State upload(org.sonatype.spice.zapper.internal.Payload, org.sonatype.spice.zapper.internal.transport.Track) throws java.io.IOException;
    Code:
       0: aload_0
       1: aload_1
       2: aload_2
       3: checkcast     #9                  // class org/sonatype/spice/zapper/client/ahc/AhcTrack
       6: invokevirtual #60                 // Method upload:(Lorg/sonatype/spice/zapper/internal/Payload;Lorg/sonatype/spice/zapper/client/ahc/AhcTrack;)Lorg/sonatype/spice/zapper/internal/transport/State;
       9: areturn
}
