Compiled from "DataSourceDefinitionDescriptorProcessor.java"
public class org.jboss.as.connector.deployers.datasource.DataSourceDefinitionDescriptorProcessor extends org.jboss.as.ee.resource.definition.ResourceDefinitionDescriptorProcessor {
  public org.jboss.as.connector.deployers.datasource.DataSourceDefinitionDescriptorProcessor();
    Code:
       0: aload_0
       1: invokespecial #1                  // Method org/jboss/as/ee/resource/definition/ResourceDefinitionDescriptorProcessor."<init>":()V
       4: return

  protected void processEnvironment(org.jboss.metadata.javaee.spec.RemoteEnvironment, org.jboss.as.ee.resource.definition.ResourceDefinitionDescriptorProcessor$ResourceDefinitionInjectionSources) throws org.jboss.as.server.deployment.DeploymentUnitProcessingException;
    Code:
       0: aload_1
       1: invokeinterface #2,  1            // InterfaceMethod org/jboss/metadata/javaee/spec/RemoteEnvironment.getDataSources:()Lorg/jboss/metadata/javaee/spec/DataSourcesMetaData;
       6: astore_3
       7: aload_3
       8: ifnull        52
      11: aload_3
      12: invokevirtual #3                  // Method org/jboss/metadata/javaee/spec/DataSourcesMetaData.iterator:()Ljava/util/Iterator;
      15: astore        4
      17: aload         4
      19: invokeinterface #4,  1            // InterfaceMethod java/util/Iterator.hasNext:()Z
      24: ifeq          52
      27: aload         4
      29: invokeinterface #5,  1            // InterfaceMethod java/util/Iterator.next:()Ljava/lang/Object;
      34: checkcast     #6                  // class org/jboss/metadata/javaee/spec/DataSourceMetaData
      37: astore        5
      39: aload_2
      40: aload_0
      41: aload         5
      43: invokespecial #7                  // Method getResourceDefinitionInjectionSource:(Lorg/jboss/metadata/javaee/spec/DataSourceMetaData;)Lorg/jboss/as/ee/resource/definition/ResourceDefinitionInjectionSource;
      46: invokevirtual #8                  // Method org/jboss/as/ee/resource/definition/ResourceDefinitionDescriptorProcessor$ResourceDefinitionInjectionSources.addResourceDefinitionInjectionSource:(Lorg/jboss/as/ee/resource/definition/ResourceDefinitionInjectionSource;)V
      49: goto          17
      52: return

  private org.jboss.as.ee.resource.definition.ResourceDefinitionInjectionSource getResourceDefinitionInjectionSource(org.jboss.metadata.javaee.spec.DataSourceMetaData);
    Code:
       0: aload_1
       1: invokevirtual #9                  // Method org/jboss/metadata/javaee/spec/DataSourceMetaData.getName:()Ljava/lang/String;
       4: astore_2
       5: aload_2
       6: ifnull        16
       9: aload_2
      10: invokevirtual #10                 // Method java/lang/String.isEmpty:()Z
      13: ifeq          29
      16: getstatic     #11                 // Field org/jboss/as/ee/logging/EeLogger.ROOT_LOGGER:Lorg/jboss/as/ee/logging/EeLogger;
      19: ldc           #12                 // String <data-source>
      21: ldc           #13                 // String name
      23: invokeinterface #14,  3           // InterfaceMethod org/jboss/as/ee/logging/EeLogger.elementAttributeMissing:(Ljava/lang/String;Ljava/lang/String;)Ljava/lang/IllegalArgumentException;
      28: athrow
      29: new           #15                 // class org/jboss/as/connector/deployers/datasource/DataSourceDefinitionInjectionSource
      32: dup
      33: aload_2
      34: invokespecial #16                 // Method org/jboss/as/connector/deployers/datasource/DataSourceDefinitionInjectionSource."<init>":(Ljava/lang/String;)V
      37: astore_3
      38: aload_1
      39: invokevirtual #17                 // Method org/jboss/metadata/javaee/spec/DataSourceMetaData.getClassName:()Ljava/lang/String;
      42: astore        4
      44: aload         4
      46: ifnull        62
      49: aload         4
      51: ldc           #18                 // class java/lang/Object
      53: invokevirtual #19                 // Method java/lang/Class.getName:()Ljava/lang/String;
      56: invokevirtual #20                 // Method java/lang/String.equals:(Ljava/lang/Object;)Z
      59: ifeq          75
      62: getstatic     #11                 // Field org/jboss/as/ee/logging/EeLogger.ROOT_LOGGER:Lorg/jboss/as/ee/logging/EeLogger;
      65: ldc           #12                 // String <data-source>
      67: ldc           #21                 // String className
      69: invokeinterface #14,  3           // InterfaceMethod org/jboss/as/ee/logging/EeLogger.elementAttributeMissing:(Ljava/lang/String;Ljava/lang/String;)Ljava/lang/IllegalArgumentException;
      74: athrow
      75: aload_3
      76: aload         4
      78: invokevirtual #22                 // Method org/jboss/as/connector/deployers/datasource/DataSourceDefinitionInjectionSource.setClassName:(Ljava/lang/String;)V
      81: aload_3
      82: aload_1
      83: invokevirtual #23                 // Method org/jboss/metadata/javaee/spec/DataSourceMetaData.getDatabaseName:()Ljava/lang/String;
      86: invokevirtual #24                 // Method org/jboss/as/connector/deployers/datasource/DataSourceDefinitionInjectionSource.setDatabaseName:(Ljava/lang/String;)V
      89: aload_1
      90: invokevirtual #25                 // Method org/jboss/metadata/javaee/spec/DataSourceMetaData.getDescriptions:()Lorg/jboss/annotation/javaee/Descriptions;
      93: ifnull        107
      96: aload_3
      97: aload_1
      98: invokevirtual #25                 // Method org/jboss/metadata/javaee/spec/DataSourceMetaData.getDescriptions:()Lorg/jboss/annotation/javaee/Descriptions;
     101: invokevirtual #26                 // Method java/lang/Object.toString:()Ljava/lang/String;
     104: invokevirtual #27                 // Method org/jboss/as/connector/deployers/datasource/DataSourceDefinitionInjectionSource.setDescription:(Ljava/lang/String;)V
     107: aload_3
     108: aload_1
     109: invokevirtual #28                 // Method org/jboss/metadata/javaee/spec/DataSourceMetaData.getInitialPoolSize:()I
     112: invokevirtual #29                 // Method org/jboss/as/connector/deployers/datasource/DataSourceDefinitionInjectionSource.setInitialPoolSize:(I)V
     115: aload_1
     116: invokevirtual #30                 // Method org/jboss/metadata/javaee/spec/DataSourceMetaData.getIsolationLevel:()Lorg/jboss/metadata/javaee/spec/IsolationLevelType;
     119: ifnull        133
     122: aload_3
     123: aload_1
     124: invokevirtual #30                 // Method org/jboss/metadata/javaee/spec/DataSourceMetaData.getIsolationLevel:()Lorg/jboss/metadata/javaee/spec/IsolationLevelType;
     127: invokevirtual #31                 // Method org/jboss/metadata/javaee/spec/IsolationLevelType.ordinal:()I
     130: invokevirtual #32                 // Method org/jboss/as/connector/deployers/datasource/DataSourceDefinitionInjectionSource.setIsolationLevel:(I)V
     133: aload_3
     134: aload_1
     135: invokevirtual #33                 // Method org/jboss/metadata/javaee/spec/DataSourceMetaData.getLoginTimeout:()I
     138: invokevirtual #34                 // Method org/jboss/as/connector/deployers/datasource/DataSourceDefinitionInjectionSource.setLoginTimeout:(I)V
     141: aload_3
     142: aload_1
     143: invokevirtual #35                 // Method org/jboss/metadata/javaee/spec/DataSourceMetaData.getMaxIdleTime:()I
     146: invokevirtual #36                 // Method org/jboss/as/connector/deployers/datasource/DataSourceDefinitionInjectionSource.setMaxIdleTime:(I)V
     149: aload_3
     150: aload_1
     151: invokevirtual #37                 // Method org/jboss/metadata/javaee/spec/DataSourceMetaData.getMaxStatements:()I
     154: invokevirtual #38                 // Method org/jboss/as/connector/deployers/datasource/DataSourceDefinitionInjectionSource.setMaxStatements:(I)V
     157: aload_3
     158: aload_1
     159: invokevirtual #39                 // Method org/jboss/metadata/javaee/spec/DataSourceMetaData.getMaxPoolSize:()I
     162: invokevirtual #40                 // Method org/jboss/as/connector/deployers/datasource/DataSourceDefinitionInjectionSource.setMaxPoolSize:(I)V
     165: aload_3
     166: aload_1
     167: invokevirtual #41                 // Method org/jboss/metadata/javaee/spec/DataSourceMetaData.getMinPoolSize:()I
     170: invokevirtual #42                 // Method org/jboss/as/connector/deployers/datasource/DataSourceDefinitionInjectionSource.setMinPoolSize:(I)V
     173: aload_3
     174: aload_1
     175: invokevirtual #28                 // Method org/jboss/metadata/javaee/spec/DataSourceMetaData.getInitialPoolSize:()I
     178: invokevirtual #29                 // Method org/jboss/as/connector/deployers/datasource/DataSourceDefinitionInjectionSource.setInitialPoolSize:(I)V
     181: aload_3
     182: aload_1
     183: invokevirtual #43                 // Method org/jboss/metadata/javaee/spec/DataSourceMetaData.getPassword:()Ljava/lang/String;
     186: invokevirtual #44                 // Method org/jboss/as/connector/deployers/datasource/DataSourceDefinitionInjectionSource.setPassword:(Ljava/lang/String;)V
     189: aload_3
     190: aload_1
     191: invokevirtual #45                 // Method org/jboss/metadata/javaee/spec/DataSourceMetaData.getPortNumber:()I
     194: invokevirtual #46                 // Method org/jboss/as/connector/deployers/datasource/DataSourceDefinitionInjectionSource.setPortNumber:(I)V
     197: aload_3
     198: aload_1
     199: invokevirtual #47                 // Method org/jboss/metadata/javaee/spec/DataSourceMetaData.getProperties:()Lorg/jboss/metadata/javaee/spec/PropertiesMetaData;
     202: invokevirtual #48                 // Method org/jboss/as/connector/deployers/datasource/DataSourceDefinitionInjectionSource.addProperties:(Lorg/jboss/metadata/javaee/spec/PropertiesMetaData;)V
     205: aload_3
     206: aload_1
     207: invokevirtual #49                 // Method org/jboss/metadata/javaee/spec/DataSourceMetaData.getServerName:()Ljava/lang/String;
     210: invokevirtual #50                 // Method org/jboss/as/connector/deployers/datasource/DataSourceDefinitionInjectionSource.setServerName:(Ljava/lang/String;)V
     213: aload_3
     214: aload_1
     215: invokevirtual #51                 // Method org/jboss/metadata/javaee/spec/DataSourceMetaData.getTransactional:()Z
     218: invokevirtual #52                 // Method org/jboss/as/connector/deployers/datasource/DataSourceDefinitionInjectionSource.setTransactional:(Z)V
     221: aload_3
     222: aload_1
     223: invokevirtual #53                 // Method org/jboss/metadata/javaee/spec/DataSourceMetaData.getUrl:()Ljava/lang/String;
     226: invokevirtual #54                 // Method org/jboss/as/connector/deployers/datasource/DataSourceDefinitionInjectionSource.setUrl:(Ljava/lang/String;)V
     229: aload_3
     230: aload_1
     231: invokevirtual #55                 // Method org/jboss/metadata/javaee/spec/DataSourceMetaData.getUser:()Ljava/lang/String;
     234: invokevirtual #56                 // Method org/jboss/as/connector/deployers/datasource/DataSourceDefinitionInjectionSource.setUser:(Ljava/lang/String;)V
     237: aload_3
     238: areturn
}
