Compiled from "S3CryptoModuleAEStrict.java"
class com.amazonaws.services.s3.internal.crypto.S3CryptoModuleAEStrict extends com.amazonaws.services.s3.internal.crypto.S3CryptoModuleAE {
  com.amazonaws.services.s3.internal.crypto.S3CryptoModuleAEStrict(com.amazonaws.services.kms.AWSKMSClient, com.amazonaws.services.s3.internal.S3Direct, com.amazonaws.auth.AWSCredentialsProvider, com.amazonaws.services.s3.model.EncryptionMaterialsProvider, com.amazonaws.services.s3.model.CryptoConfiguration);
    Code:
       0: aload_0
       1: aload_1
       2: aload_2
       3: aload_3
       4: aload         4
       6: aload         5
       8: invokespecial #1                  // Method com/amazonaws/services/s3/internal/crypto/S3CryptoModuleAE."<init>":(Lcom/amazonaws/services/kms/AWSKMSClient;Lcom/amazonaws/services/s3/internal/S3Direct;Lcom/amazonaws/auth/AWSCredentialsProvider;Lcom/amazonaws/services/s3/model/EncryptionMaterialsProvider;Lcom/amazonaws/services/s3/model/CryptoConfiguration;)V
      11: aload         5
      13: invokevirtual #2                  // Method com/amazonaws/services/s3/model/CryptoConfiguration.getCryptoMode:()Lcom/amazonaws/services/s3/model/CryptoMode;
      16: getstatic     #3                  // Field com/amazonaws/services/s3/model/CryptoMode.StrictAuthenticatedEncryption:Lcom/amazonaws/services/s3/model/CryptoMode;
      19: if_acmpeq     30
      22: new           #4                  // class java/lang/IllegalArgumentException
      25: dup
      26: invokespecial #5                  // Method java/lang/IllegalArgumentException."<init>":()V
      29: athrow
      30: return

  protected final boolean isStrict();
    Code:
       0: iconst_1
       1: ireturn

  protected void securityCheck(com.amazonaws.services.s3.internal.crypto.ContentCryptoMaterial, com.amazonaws.services.s3.internal.crypto.S3ObjectWrapper);
    Code:
       0: getstatic     #6                  // Field com/amazonaws/services/s3/internal/crypto/ContentCryptoScheme.AES_GCM:Lcom/amazonaws/services/s3/internal/crypto/ContentCryptoScheme;
       3: aload_1
       4: invokevirtual #7                  // Method com/amazonaws/services/s3/internal/crypto/ContentCryptoMaterial.getContentCryptoScheme:()Lcom/amazonaws/services/s3/internal/crypto/ContentCryptoScheme;
       7: invokevirtual #8                  // Method java/lang/Object.equals:(Ljava/lang/Object;)Z
      10: ifne          60
      13: new           #9                  // class java/lang/SecurityException
      16: dup
      17: new           #10                 // class java/lang/StringBuilder
      20: dup
      21: invokespecial #11                 // Method java/lang/StringBuilder."<init>":()V
      24: ldc           #12                 // String S3 object [bucket:
      26: invokevirtual #13                 // Method java/lang/StringBuilder.append:(Ljava/lang/String;)Ljava/lang/StringBuilder;
      29: aload_2
      30: invokevirtual #14                 // Method com/amazonaws/services/s3/internal/crypto/S3ObjectWrapper.getBucketName:()Ljava/lang/String;
      33: invokevirtual #13                 // Method java/lang/StringBuilder.append:(Ljava/lang/String;)Ljava/lang/StringBuilder;
      36: ldc           #15                 // String , key:
      38: invokevirtual #13                 // Method java/lang/StringBuilder.append:(Ljava/lang/String;)Ljava/lang/StringBuilder;
      41: aload_2
      42: invokevirtual #16                 // Method com/amazonaws/services/s3/internal/crypto/S3ObjectWrapper.getKey:()Ljava/lang/String;
      45: invokevirtual #13                 // Method java/lang/StringBuilder.append:(Ljava/lang/String;)Ljava/lang/StringBuilder;
      48: ldc           #17                 // String ] not encrypted using authenticated encryption
      50: invokevirtual #13                 // Method java/lang/StringBuilder.append:(Ljava/lang/String;)Ljava/lang/StringBuilder;
      53: invokevirtual #18                 // Method java/lang/StringBuilder.toString:()Ljava/lang/String;
      56: invokespecial #19                 // Method java/lang/SecurityException."<init>":(Ljava/lang/String;)V
      59: athrow
      60: return
}
