Compiled from "SAXParseable.java"
public class org.kohsuke.rngom.parse.xml.SAXParseable implements org.kohsuke.rngom.parse.Parseable {
  private final org.xml.sax.InputSource in;

  final org.kohsuke.rngom.xml.sax.XMLReaderCreator xrc;

  final org.xml.sax.ErrorHandler eh;

  public org.kohsuke.rngom.parse.xml.SAXParseable(org.xml.sax.InputSource, org.xml.sax.ErrorHandler, org.kohsuke.rngom.xml.sax.XMLReaderCreator);
    Code:
       0: aload_0
       1: invokespecial #1                  // Method java/lang/Object."<init>":()V
       4: aload_0
       5: aload_3
       6: putfield      #2                  // Field xrc:Lorg/kohsuke/rngom/xml/sax/XMLReaderCreator;
       9: aload_0
      10: aload_2
      11: putfield      #3                  // Field eh:Lorg/xml/sax/ErrorHandler;
      14: aload_0
      15: aload_1
      16: putfield      #4                  // Field in:Lorg/xml/sax/InputSource;
      19: return

  public org.kohsuke.rngom.parse.xml.SAXParseable(org.xml.sax.InputSource, org.xml.sax.ErrorHandler);
    Code:
       0: aload_0
       1: aload_1
       2: aload_2
       3: new           #5                  // class org/kohsuke/rngom/xml/sax/JAXPXMLReaderCreator
       6: dup
       7: invokespecial #6                  // Method org/kohsuke/rngom/xml/sax/JAXPXMLReaderCreator."<init>":()V
      10: invokespecial #7                  // Method "<init>":(Lorg/xml/sax/InputSource;Lorg/xml/sax/ErrorHandler;Lorg/kohsuke/rngom/xml/sax/XMLReaderCreator;)V
      13: return

  public org.kohsuke.rngom.ast.om.ParsedPattern parse(org.kohsuke.rngom.ast.builder.SchemaBuilder) throws org.kohsuke.rngom.ast.builder.BuildException, org.kohsuke.rngom.parse.IllegalSchemaException;
    Code:
       0: aload_0
       1: getfield      #2                  // Field xrc:Lorg/kohsuke/rngom/xml/sax/XMLReaderCreator;
       4: invokeinterface #8,  1            // InterfaceMethod org/kohsuke/rngom/xml/sax/XMLReaderCreator.createXMLReader:()Lorg/xml/sax/XMLReader;
       9: astore_2
      10: new           #9                  // class org/kohsuke/rngom/parse/xml/SchemaParser
      13: dup
      14: aload_0
      15: aload_2
      16: aload_0
      17: getfield      #3                  // Field eh:Lorg/xml/sax/ErrorHandler;
      20: aload_1
      21: aconst_null
      22: aconst_null
      23: ldc           #10                 // String
      25: invokespecial #11                 // Method org/kohsuke/rngom/parse/xml/SchemaParser."<init>":(Lorg/kohsuke/rngom/parse/xml/SAXParseable;Lorg/xml/sax/XMLReader;Lorg/xml/sax/ErrorHandler;Lorg/kohsuke/rngom/ast/builder/SchemaBuilder;Lorg/kohsuke/rngom/ast/builder/IncludedGrammar;Lorg/kohsuke/rngom/ast/builder/Scope;Ljava/lang/String;)V
      28: astore_3
      29: aload_2
      30: aload_0
      31: getfield      #4                  // Field in:Lorg/xml/sax/InputSource;
      34: invokeinterface #12,  2           // InterfaceMethod org/xml/sax/XMLReader.parse:(Lorg/xml/sax/InputSource;)V
      39: aload_3
      40: invokevirtual #13                 // Method org/kohsuke/rngom/parse/xml/SchemaParser.getParsedPattern:()Lorg/kohsuke/rngom/ast/om/ParsedPattern;
      43: astore        4
      45: aload_1
      46: aload         4
      48: invokeinterface #14,  2           // InterfaceMethod org/kohsuke/rngom/ast/builder/SchemaBuilder.expandPattern:(Lorg/kohsuke/rngom/ast/om/ParsedPattern;)Lorg/kohsuke/rngom/ast/om/ParsedPattern;
      53: areturn
      54: astore_2
      55: aload_2
      56: invokestatic  #16                 // Method toBuildException:(Lorg/xml/sax/SAXException;)Lorg/kohsuke/rngom/ast/builder/BuildException;
      59: athrow
      60: astore_2
      61: new           #18                 // class org/kohsuke/rngom/ast/builder/BuildException
      64: dup
      65: aload_2
      66: invokespecial #19                 // Method org/kohsuke/rngom/ast/builder/BuildException."<init>":(Ljava/lang/Throwable;)V
      69: athrow
    Exception table:
       from    to  target type
           0    53    54   Class org/xml/sax/SAXException
           0    53    60   Class java/io/IOException

  public org.kohsuke.rngom.ast.om.ParsedPattern parseInclude(java.lang.String, org.kohsuke.rngom.ast.builder.SchemaBuilder, org.kohsuke.rngom.ast.builder.IncludedGrammar, java.lang.String) throws org.kohsuke.rngom.ast.builder.BuildException, org.kohsuke.rngom.parse.IllegalSchemaException;
    Code:
       0: aload_0
       1: getfield      #2                  // Field xrc:Lorg/kohsuke/rngom/xml/sax/XMLReaderCreator;
       4: invokeinterface #8,  1            // InterfaceMethod org/kohsuke/rngom/xml/sax/XMLReaderCreator.createXMLReader:()Lorg/xml/sax/XMLReader;
       9: astore        5
      11: new           #9                  // class org/kohsuke/rngom/parse/xml/SchemaParser
      14: dup
      15: aload_0
      16: aload         5
      18: aload_0
      19: getfield      #3                  // Field eh:Lorg/xml/sax/ErrorHandler;
      22: aload_2
      23: aload_3
      24: aload_3
      25: aload         4
      27: invokespecial #11                 // Method org/kohsuke/rngom/parse/xml/SchemaParser."<init>":(Lorg/kohsuke/rngom/parse/xml/SAXParseable;Lorg/xml/sax/XMLReader;Lorg/xml/sax/ErrorHandler;Lorg/kohsuke/rngom/ast/builder/SchemaBuilder;Lorg/kohsuke/rngom/ast/builder/IncludedGrammar;Lorg/kohsuke/rngom/ast/builder/Scope;Ljava/lang/String;)V
      30: astore        6
      32: aload         5
      34: aload         5
      36: aload_1
      37: invokestatic  #20                 // Method makeInputSource:(Lorg/xml/sax/XMLReader;Ljava/lang/String;)Lorg/xml/sax/InputSource;
      40: invokeinterface #12,  2           // InterfaceMethod org/xml/sax/XMLReader.parse:(Lorg/xml/sax/InputSource;)V
      45: aload         6
      47: invokevirtual #13                 // Method org/kohsuke/rngom/parse/xml/SchemaParser.getParsedPattern:()Lorg/kohsuke/rngom/ast/om/ParsedPattern;
      50: areturn
      51: astore        5
      53: aload         5
      55: invokestatic  #16                 // Method toBuildException:(Lorg/xml/sax/SAXException;)Lorg/kohsuke/rngom/ast/builder/BuildException;
      58: athrow
      59: astore        5
      61: new           #18                 // class org/kohsuke/rngom/ast/builder/BuildException
      64: dup
      65: aload         5
      67: invokespecial #19                 // Method org/kohsuke/rngom/ast/builder/BuildException."<init>":(Ljava/lang/Throwable;)V
      70: athrow
    Exception table:
       from    to  target type
           0    50    51   Class org/xml/sax/SAXException
           0    50    59   Class java/io/IOException

  public org.kohsuke.rngom.ast.om.ParsedPattern parseExternal(java.lang.String, org.kohsuke.rngom.ast.builder.SchemaBuilder, org.kohsuke.rngom.ast.builder.Scope, java.lang.String) throws org.kohsuke.rngom.ast.builder.BuildException, org.kohsuke.rngom.parse.IllegalSchemaException;
    Code:
       0: aload_0
       1: getfield      #2                  // Field xrc:Lorg/kohsuke/rngom/xml/sax/XMLReaderCreator;
       4: invokeinterface #8,  1            // InterfaceMethod org/kohsuke/rngom/xml/sax/XMLReaderCreator.createXMLReader:()Lorg/xml/sax/XMLReader;
       9: astore        5
      11: new           #9                  // class org/kohsuke/rngom/parse/xml/SchemaParser
      14: dup
      15: aload_0
      16: aload         5
      18: aload_0
      19: getfield      #3                  // Field eh:Lorg/xml/sax/ErrorHandler;
      22: aload_2
      23: aconst_null
      24: aload_3
      25: aload         4
      27: invokespecial #11                 // Method org/kohsuke/rngom/parse/xml/SchemaParser."<init>":(Lorg/kohsuke/rngom/parse/xml/SAXParseable;Lorg/xml/sax/XMLReader;Lorg/xml/sax/ErrorHandler;Lorg/kohsuke/rngom/ast/builder/SchemaBuilder;Lorg/kohsuke/rngom/ast/builder/IncludedGrammar;Lorg/kohsuke/rngom/ast/builder/Scope;Ljava/lang/String;)V
      30: astore        6
      32: aload         5
      34: aload         5
      36: aload_1
      37: invokestatic  #20                 // Method makeInputSource:(Lorg/xml/sax/XMLReader;Ljava/lang/String;)Lorg/xml/sax/InputSource;
      40: invokeinterface #12,  2           // InterfaceMethod org/xml/sax/XMLReader.parse:(Lorg/xml/sax/InputSource;)V
      45: aload         6
      47: invokevirtual #13                 // Method org/kohsuke/rngom/parse/xml/SchemaParser.getParsedPattern:()Lorg/kohsuke/rngom/ast/om/ParsedPattern;
      50: areturn
      51: astore        5
      53: aload         5
      55: invokestatic  #16                 // Method toBuildException:(Lorg/xml/sax/SAXException;)Lorg/kohsuke/rngom/ast/builder/BuildException;
      58: athrow
      59: astore        5
      61: new           #18                 // class org/kohsuke/rngom/ast/builder/BuildException
      64: dup
      65: aload         5
      67: invokespecial #19                 // Method org/kohsuke/rngom/ast/builder/BuildException."<init>":(Ljava/lang/Throwable;)V
      70: athrow
    Exception table:
       from    to  target type
           0    50    51   Class org/xml/sax/SAXException
           0    50    59   Class java/io/IOException

  private static org.xml.sax.InputSource makeInputSource(org.xml.sax.XMLReader, java.lang.String) throws java.io.IOException, org.xml.sax.SAXException;
    Code:
       0: aload_0
       1: invokeinterface #21,  1           // InterfaceMethod org/xml/sax/XMLReader.getEntityResolver:()Lorg/xml/sax/EntityResolver;
       6: astore_2
       7: aload_2
       8: ifnull        26
      11: aload_2
      12: aconst_null
      13: aload_1
      14: invokeinterface #22,  3           // InterfaceMethod org/xml/sax/EntityResolver.resolveEntity:(Ljava/lang/String;Ljava/lang/String;)Lorg/xml/sax/InputSource;
      19: astore_3
      20: aload_3
      21: ifnull        26
      24: aload_3
      25: areturn
      26: new           #23                 // class org/xml/sax/InputSource
      29: dup
      30: aload_1
      31: invokespecial #24                 // Method org/xml/sax/InputSource."<init>":(Ljava/lang/String;)V
      34: areturn

  static org.kohsuke.rngom.ast.builder.BuildException toBuildException(org.xml.sax.SAXException);
    Code:
       0: aload_0
       1: invokevirtual #25                 // Method org/xml/sax/SAXException.getException:()Ljava/lang/Exception;
       4: astore_1
       5: aload_1
       6: instanceof    #18                 // class org/kohsuke/rngom/ast/builder/BuildException
       9: ifeq          17
      12: aload_1
      13: checkcast     #18                 // class org/kohsuke/rngom/ast/builder/BuildException
      16: athrow
      17: new           #18                 // class org/kohsuke/rngom/ast/builder/BuildException
      20: dup
      21: aload_0
      22: invokespecial #19                 // Method org/kohsuke/rngom/ast/builder/BuildException."<init>":(Ljava/lang/Throwable;)V
      25: athrow
}
