Compiled from "ReactiveCloudFoundrySecurityService.java"
class org.springframework.boot.actuate.autoconfigure.cloudfoundry.reactive.ReactiveCloudFoundrySecurityService {
  private static final org.springframework.core.ParameterizedTypeReference<java.util.Map<java.lang.String, java.lang.Object>> STRING_OBJECT_MAP;

  private final org.springframework.web.reactive.function.client.WebClient webClient;

  private final java.lang.String cloudControllerUrl;

  private reactor.core.publisher.Mono<java.lang.String> uaaUrl;

  org.springframework.boot.actuate.autoconfigure.cloudfoundry.reactive.ReactiveCloudFoundrySecurityService(org.springframework.web.reactive.function.client.WebClient$Builder, java.lang.String, boolean);
    Code:
       0: aload_0
       1: invokespecial #1                  // Method java/lang/Object."<init>":()V
       4: aload_1
       5: ldc           #2                  // String Webclient must not be null
       7: invokestatic  #3                  // Method org/springframework/util/Assert.notNull:(Ljava/lang/Object;Ljava/lang/String;)V
      10: aload_2
      11: ldc           #4                  // String CloudControllerUrl must not be null
      13: invokestatic  #3                  // Method org/springframework/util/Assert.notNull:(Ljava/lang/Object;Ljava/lang/String;)V
      16: iload_3
      17: ifeq          31
      20: aload_1
      21: aload_0
      22: invokevirtual #5                  // Method buildTrustAllSslConnector:()Lorg/springframework/http/client/reactive/ReactorClientHttpConnector;
      25: invokeinterface #6,  2            // InterfaceMethod org/springframework/web/reactive/function/client/WebClient$Builder.clientConnector:(Lorg/springframework/http/client/reactive/ClientHttpConnector;)Lorg/springframework/web/reactive/function/client/WebClient$Builder;
      30: pop
      31: aload_0
      32: aload_1
      33: invokeinterface #7,  1            // InterfaceMethod org/springframework/web/reactive/function/client/WebClient$Builder.build:()Lorg/springframework/web/reactive/function/client/WebClient;
      38: putfield      #8                  // Field webClient:Lorg/springframework/web/reactive/function/client/WebClient;
      41: aload_0
      42: aload_2
      43: putfield      #9                  // Field cloudControllerUrl:Ljava/lang/String;
      46: return

  protected org.springframework.http.client.reactive.ReactorClientHttpConnector buildTrustAllSslConnector();
    Code:
       0: invokestatic  #10                 // Method reactor/netty/http/client/HttpClient.create:()Lreactor/netty/http/client/HttpClient;
       3: aload_0
       4: invokedynamic #11,  0             // InvokeDynamic #0:accept:(Lorg/springframework/boot/actuate/autoconfigure/cloudfoundry/reactive/ReactiveCloudFoundrySecurityService;)Ljava/util/function/Consumer;
       9: invokevirtual #12                 // Method reactor/netty/http/client/HttpClient.secure:(Ljava/util/function/Consumer;)Lreactor/netty/http/client/HttpClient;
      12: astore_1
      13: new           #13                 // class org/springframework/http/client/reactive/ReactorClientHttpConnector
      16: dup
      17: aload_1
      18: invokespecial #14                 // Method org/springframework/http/client/reactive/ReactorClientHttpConnector."<init>":(Lreactor/netty/http/client/HttpClient;)V
      21: areturn

  private io.netty.handler.ssl.SslContextBuilder createSslContext();
    Code:
       0: invokestatic  #15                 // Method io/netty/handler/ssl/SslContextBuilder.forClient:()Lio/netty/handler/ssl/SslContextBuilder;
       3: getstatic     #16                 // Field io/netty/handler/ssl/SslProvider.JDK:Lio/netty/handler/ssl/SslProvider;
       6: invokevirtual #17                 // Method io/netty/handler/ssl/SslContextBuilder.sslProvider:(Lio/netty/handler/ssl/SslProvider;)Lio/netty/handler/ssl/SslContextBuilder;
       9: getstatic     #18                 // Field io/netty/handler/ssl/util/InsecureTrustManagerFactory.INSTANCE:Ljavax/net/ssl/TrustManagerFactory;
      12: invokevirtual #19                 // Method io/netty/handler/ssl/SslContextBuilder.trustManager:(Ljavax/net/ssl/TrustManagerFactory;)Lio/netty/handler/ssl/SslContextBuilder;
      15: areturn

  public reactor.core.publisher.Mono<org.springframework.boot.actuate.autoconfigure.cloudfoundry.AccessLevel> getAccessLevel(java.lang.String, java.lang.String) throws org.springframework.boot.actuate.autoconfigure.cloudfoundry.CloudFoundryAuthorizationException;
    Code:
       0: aload_0
       1: aload_2
       2: invokespecial #20                 // Method getPermissionsUri:(Ljava/lang/String;)Ljava/lang/String;
       5: astore_3
       6: aload_0
       7: getfield      #8                  // Field webClient:Lorg/springframework/web/reactive/function/client/WebClient;
      10: invokeinterface #21,  1           // InterfaceMethod org/springframework/web/reactive/function/client/WebClient.get:()Lorg/springframework/web/reactive/function/client/WebClient$RequestHeadersUriSpec;
      15: aload_3
      16: iconst_0
      17: anewarray     #22                 // class java/lang/Object
      20: invokeinterface #23,  3           // InterfaceMethod org/springframework/web/reactive/function/client/WebClient$RequestHeadersUriSpec.uri:(Ljava/lang/String;[Ljava/lang/Object;)Lorg/springframework/web/reactive/function/client/WebClient$RequestHeadersSpec;
      25: ldc           #24                 // String Authorization
      27: iconst_1
      28: anewarray     #25                 // class java/lang/String
      31: dup
      32: iconst_0
      33: new           #26                 // class java/lang/StringBuilder
      36: dup
      37: invokespecial #27                 // Method java/lang/StringBuilder."<init>":()V
      40: ldc           #28                 // String bearer
      42: invokevirtual #29                 // Method java/lang/StringBuilder.append:(Ljava/lang/String;)Ljava/lang/StringBuilder;
      45: aload_1
      46: invokevirtual #29                 // Method java/lang/StringBuilder.append:(Ljava/lang/String;)Ljava/lang/StringBuilder;
      49: invokevirtual #30                 // Method java/lang/StringBuilder.toString:()Ljava/lang/String;
      52: aastore
      53: invokeinterface #31,  3           // InterfaceMethod org/springframework/web/reactive/function/client/WebClient$RequestHeadersSpec.header:(Ljava/lang/String;[Ljava/lang/String;)Lorg/springframework/web/reactive/function/client/WebClient$RequestHeadersSpec;
      58: invokeinterface #32,  1           // InterfaceMethod org/springframework/web/reactive/function/client/WebClient$RequestHeadersSpec.retrieve:()Lorg/springframework/web/reactive/function/client/WebClient$ResponseSpec;
      63: ldc           #33                 // class java/util/Map
      65: invokeinterface #34,  2           // InterfaceMethod org/springframework/web/reactive/function/client/WebClient$ResponseSpec.bodyToMono:(Ljava/lang/Class;)Lreactor/core/publisher/Mono;
      70: aload_0
      71: invokedynamic #35,  0             // InvokeDynamic #1:apply:(Lorg/springframework/boot/actuate/autoconfigure/cloudfoundry/reactive/ReactiveCloudFoundrySecurityService;)Ljava/util/function/Function;
      76: invokevirtual #36                 // Method reactor/core/publisher/Mono.map:(Ljava/util/function/Function;)Lreactor/core/publisher/Mono;
      79: aload_0
      80: invokedynamic #37,  0             // InvokeDynamic #2:apply:(Lorg/springframework/boot/actuate/autoconfigure/cloudfoundry/reactive/ReactiveCloudFoundrySecurityService;)Ljava/util/function/Function;
      85: invokevirtual #38                 // Method reactor/core/publisher/Mono.onErrorMap:(Ljava/util/function/Function;)Lreactor/core/publisher/Mono;
      88: areturn

  private java.lang.Throwable mapError(java.lang.Throwable);
    Code:
       0: aload_1
       1: instanceof    #39                 // class org/springframework/web/reactive/function/client/WebClientResponseException
       4: ifeq          59
       7: aload_1
       8: checkcast     #39                 // class org/springframework/web/reactive/function/client/WebClientResponseException
      11: invokevirtual #40                 // Method org/springframework/web/reactive/function/client/WebClientResponseException.getStatusCode:()Lorg/springframework/http/HttpStatus;
      14: astore_2
      15: aload_2
      16: getstatic     #41                 // Field org/springframework/http/HttpStatus.FORBIDDEN:Lorg/springframework/http/HttpStatus;
      19: invokevirtual #42                 // Method org/springframework/http/HttpStatus.equals:(Ljava/lang/Object;)Z
      22: ifeq          38
      25: new           #43                 // class org/springframework/boot/actuate/autoconfigure/cloudfoundry/CloudFoundryAuthorizationException
      28: dup
      29: getstatic     #44                 // Field org/springframework/boot/actuate/autoconfigure/cloudfoundry/CloudFoundryAuthorizationException$Reason.ACCESS_DENIED:Lorg/springframework/boot/actuate/autoconfigure/cloudfoundry/CloudFoundryAuthorizationException$Reason;
      32: ldc           #45                 // String Access denied
      34: invokespecial #46                 // Method org/springframework/boot/actuate/autoconfigure/cloudfoundry/CloudFoundryAuthorizationException."<init>":(Lorg/springframework/boot/actuate/autoconfigure/cloudfoundry/CloudFoundryAuthorizationException$Reason;Ljava/lang/String;)V
      37: areturn
      38: aload_2
      39: invokevirtual #47                 // Method org/springframework/http/HttpStatus.is4xxClientError:()Z
      42: ifeq          59
      45: new           #43                 // class org/springframework/boot/actuate/autoconfigure/cloudfoundry/CloudFoundryAuthorizationException
      48: dup
      49: getstatic     #48                 // Field org/springframework/boot/actuate/autoconfigure/cloudfoundry/CloudFoundryAuthorizationException$Reason.INVALID_TOKEN:Lorg/springframework/boot/actuate/autoconfigure/cloudfoundry/CloudFoundryAuthorizationException$Reason;
      52: ldc           #49                 // String Invalid token
      54: aload_1
      55: invokespecial #50                 // Method org/springframework/boot/actuate/autoconfigure/cloudfoundry/CloudFoundryAuthorizationException."<init>":(Lorg/springframework/boot/actuate/autoconfigure/cloudfoundry/CloudFoundryAuthorizationException$Reason;Ljava/lang/String;Ljava/lang/Throwable;)V
      58: areturn
      59: new           #43                 // class org/springframework/boot/actuate/autoconfigure/cloudfoundry/CloudFoundryAuthorizationException
      62: dup
      63: getstatic     #51                 // Field org/springframework/boot/actuate/autoconfigure/cloudfoundry/CloudFoundryAuthorizationException$Reason.SERVICE_UNAVAILABLE:Lorg/springframework/boot/actuate/autoconfigure/cloudfoundry/CloudFoundryAuthorizationException$Reason;
      66: ldc           #52                 // String Cloud controller not reachable
      68: invokespecial #46                 // Method org/springframework/boot/actuate/autoconfigure/cloudfoundry/CloudFoundryAuthorizationException."<init>":(Lorg/springframework/boot/actuate/autoconfigure/cloudfoundry/CloudFoundryAuthorizationException$Reason;Ljava/lang/String;)V
      71: areturn

  private org.springframework.boot.actuate.autoconfigure.cloudfoundry.AccessLevel getAccessLevel(java.util.Map<?, ?>);
    Code:
       0: getstatic     #53                 // Field java/lang/Boolean.TRUE:Ljava/lang/Boolean;
       3: aload_1
       4: ldc           #54                 // String read_sensitive_data
       6: invokeinterface #55,  2           // InterfaceMethod java/util/Map.get:(Ljava/lang/Object;)Ljava/lang/Object;
      11: invokevirtual #56                 // Method java/lang/Boolean.equals:(Ljava/lang/Object;)Z
      14: ifeq          21
      17: getstatic     #57                 // Field org/springframework/boot/actuate/autoconfigure/cloudfoundry/AccessLevel.FULL:Lorg/springframework/boot/actuate/autoconfigure/cloudfoundry/AccessLevel;
      20: areturn
      21: getstatic     #58                 // Field org/springframework/boot/actuate/autoconfigure/cloudfoundry/AccessLevel.RESTRICTED:Lorg/springframework/boot/actuate/autoconfigure/cloudfoundry/AccessLevel;
      24: areturn

  private java.lang.String getPermissionsUri(java.lang.String);
    Code:
       0: new           #26                 // class java/lang/StringBuilder
       3: dup
       4: invokespecial #27                 // Method java/lang/StringBuilder."<init>":()V
       7: aload_0
       8: getfield      #9                  // Field cloudControllerUrl:Ljava/lang/String;
      11: invokevirtual #29                 // Method java/lang/StringBuilder.append:(Ljava/lang/String;)Ljava/lang/StringBuilder;
      14: ldc           #59                 // String /v2/apps/
      16: invokevirtual #29                 // Method java/lang/StringBuilder.append:(Ljava/lang/String;)Ljava/lang/StringBuilder;
      19: aload_1
      20: invokevirtual #29                 // Method java/lang/StringBuilder.append:(Ljava/lang/String;)Ljava/lang/StringBuilder;
      23: ldc           #60                 // String /permissions
      25: invokevirtual #29                 // Method java/lang/StringBuilder.append:(Ljava/lang/String;)Ljava/lang/StringBuilder;
      28: invokevirtual #30                 // Method java/lang/StringBuilder.toString:()Ljava/lang/String;
      31: areturn

  public reactor.core.publisher.Mono<java.util.Map<java.lang.String, java.lang.String>> fetchTokenKeys();
    Code:
       0: aload_0
       1: invokevirtual #61                 // Method getUaaUrl:()Lreactor/core/publisher/Mono;
       4: aload_0
       5: invokedynamic #62,  0             // InvokeDynamic #3:apply:(Lorg/springframework/boot/actuate/autoconfigure/cloudfoundry/reactive/ReactiveCloudFoundrySecurityService;)Ljava/util/function/Function;
      10: invokevirtual #63                 // Method reactor/core/publisher/Mono.flatMap:(Ljava/util/function/Function;)Lreactor/core/publisher/Mono;
      13: areturn

  private reactor.core.publisher.Mono<? extends java.util.Map<java.lang.String, java.lang.String>> fetchTokenKeys(java.lang.String);
    Code:
       0: aload_0
       1: getfield      #8                  // Field webClient:Lorg/springframework/web/reactive/function/client/WebClient;
       4: invokeinterface #21,  1           // InterfaceMethod org/springframework/web/reactive/function/client/WebClient.get:()Lorg/springframework/web/reactive/function/client/WebClient$RequestHeadersUriSpec;
       9: new           #26                 // class java/lang/StringBuilder
      12: dup
      13: invokespecial #27                 // Method java/lang/StringBuilder."<init>":()V
      16: aload_1
      17: invokevirtual #29                 // Method java/lang/StringBuilder.append:(Ljava/lang/String;)Ljava/lang/StringBuilder;
      20: ldc           #64                 // String /token_keys
      22: invokevirtual #29                 // Method java/lang/StringBuilder.append:(Ljava/lang/String;)Ljava/lang/StringBuilder;
      25: invokevirtual #30                 // Method java/lang/StringBuilder.toString:()Ljava/lang/String;
      28: iconst_0
      29: anewarray     #22                 // class java/lang/Object
      32: invokeinterface #23,  3           // InterfaceMethod org/springframework/web/reactive/function/client/WebClient$RequestHeadersUriSpec.uri:(Ljava/lang/String;[Ljava/lang/Object;)Lorg/springframework/web/reactive/function/client/WebClient$RequestHeadersSpec;
      37: astore_2
      38: aload_2
      39: invokeinterface #32,  1           // InterfaceMethod org/springframework/web/reactive/function/client/WebClient$RequestHeadersSpec.retrieve:()Lorg/springframework/web/reactive/function/client/WebClient$ResponseSpec;
      44: getstatic     #65                 // Field STRING_OBJECT_MAP:Lorg/springframework/core/ParameterizedTypeReference;
      47: invokeinterface #66,  2           // InterfaceMethod org/springframework/web/reactive/function/client/WebClient$ResponseSpec.bodyToMono:(Lorg/springframework/core/ParameterizedTypeReference;)Lreactor/core/publisher/Mono;
      52: aload_0
      53: invokedynamic #67,  0             // InvokeDynamic #4:apply:(Lorg/springframework/boot/actuate/autoconfigure/cloudfoundry/reactive/ReactiveCloudFoundrySecurityService;)Ljava/util/function/Function;
      58: invokevirtual #36                 // Method reactor/core/publisher/Mono.map:(Ljava/util/function/Function;)Lreactor/core/publisher/Mono;
      61: invokedynamic #68,  0             // InvokeDynamic #5:apply:()Ljava/util/function/Function;
      66: invokevirtual #38                 // Method reactor/core/publisher/Mono.onErrorMap:(Ljava/util/function/Function;)Lreactor/core/publisher/Mono;
      69: areturn

  private java.util.Map<java.lang.String, java.lang.String> extractTokenKeys(java.util.Map<java.lang.String, java.lang.Object>);
    Code:
       0: new           #69                 // class java/util/HashMap
       3: dup
       4: invokespecial #70                 // Method java/util/HashMap."<init>":()V
       7: astore_2
       8: aload_1
       9: ldc           #71                 // String keys
      11: invokeinterface #55,  2           // InterfaceMethod java/util/Map.get:(Ljava/lang/Object;)Ljava/lang/Object;
      16: checkcast     #72                 // class java/util/List
      19: invokeinterface #73,  1           // InterfaceMethod java/util/List.iterator:()Ljava/util/Iterator;
      24: astore_3
      25: aload_3
      26: invokeinterface #74,  1           // InterfaceMethod java/util/Iterator.hasNext:()Z
      31: ifeq          83
      34: aload_3
      35: invokeinterface #75,  1           // InterfaceMethod java/util/Iterator.next:()Ljava/lang/Object;
      40: astore        4
      42: aload         4
      44: checkcast     #33                 // class java/util/Map
      47: astore        5
      49: aload_2
      50: aload         5
      52: ldc           #76                 // String kid
      54: invokeinterface #55,  2           // InterfaceMethod java/util/Map.get:(Ljava/lang/Object;)Ljava/lang/Object;
      59: checkcast     #25                 // class java/lang/String
      62: aload         5
      64: ldc           #77                 // String value
      66: invokeinterface #55,  2           // InterfaceMethod java/util/Map.get:(Ljava/lang/Object;)Ljava/lang/Object;
      71: checkcast     #25                 // class java/lang/String
      74: invokeinterface #78,  3           // InterfaceMethod java/util/Map.put:(Ljava/lang/Object;Ljava/lang/Object;)Ljava/lang/Object;
      79: pop
      80: goto          25
      83: aload_2
      84: areturn

  public reactor.core.publisher.Mono<java.lang.String> getUaaUrl();
    Code:
       0: aload_0
       1: aload_0
       2: getfield      #8                  // Field webClient:Lorg/springframework/web/reactive/function/client/WebClient;
       5: invokeinterface #21,  1           // InterfaceMethod org/springframework/web/reactive/function/client/WebClient.get:()Lorg/springframework/web/reactive/function/client/WebClient$RequestHeadersUriSpec;
      10: new           #26                 // class java/lang/StringBuilder
      13: dup
      14: invokespecial #27                 // Method java/lang/StringBuilder."<init>":()V
      17: aload_0
      18: getfield      #9                  // Field cloudControllerUrl:Ljava/lang/String;
      21: invokevirtual #29                 // Method java/lang/StringBuilder.append:(Ljava/lang/String;)Ljava/lang/StringBuilder;
      24: ldc           #79                 // String /info
      26: invokevirtual #29                 // Method java/lang/StringBuilder.append:(Ljava/lang/String;)Ljava/lang/StringBuilder;
      29: invokevirtual #30                 // Method java/lang/StringBuilder.toString:()Ljava/lang/String;
      32: iconst_0
      33: anewarray     #22                 // class java/lang/Object
      36: invokeinterface #23,  3           // InterfaceMethod org/springframework/web/reactive/function/client/WebClient$RequestHeadersUriSpec.uri:(Ljava/lang/String;[Ljava/lang/Object;)Lorg/springframework/web/reactive/function/client/WebClient$RequestHeadersSpec;
      41: invokeinterface #32,  1           // InterfaceMethod org/springframework/web/reactive/function/client/WebClient$RequestHeadersSpec.retrieve:()Lorg/springframework/web/reactive/function/client/WebClient$ResponseSpec;
      46: ldc           #33                 // class java/util/Map
      48: invokeinterface #34,  2           // InterfaceMethod org/springframework/web/reactive/function/client/WebClient$ResponseSpec.bodyToMono:(Ljava/lang/Class;)Lreactor/core/publisher/Mono;
      53: invokedynamic #80,  0             // InvokeDynamic #6:apply:()Ljava/util/function/Function;
      58: invokevirtual #36                 // Method reactor/core/publisher/Mono.map:(Ljava/util/function/Function;)Lreactor/core/publisher/Mono;
      61: invokevirtual #81                 // Method reactor/core/publisher/Mono.cache:()Lreactor/core/publisher/Mono;
      64: invokedynamic #82,  0             // InvokeDynamic #7:apply:()Ljava/util/function/Function;
      69: invokevirtual #38                 // Method reactor/core/publisher/Mono.onErrorMap:(Ljava/util/function/Function;)Lreactor/core/publisher/Mono;
      72: putfield      #83                 // Field uaaUrl:Lreactor/core/publisher/Mono;
      75: aload_0
      76: getfield      #83                 // Field uaaUrl:Lreactor/core/publisher/Mono;
      79: areturn

  private static java.lang.Throwable lambda$getUaaUrl$3(java.lang.Throwable);
    Code:
       0: new           #43                 // class org/springframework/boot/actuate/autoconfigure/cloudfoundry/CloudFoundryAuthorizationException
       3: dup
       4: getstatic     #51                 // Field org/springframework/boot/actuate/autoconfigure/cloudfoundry/CloudFoundryAuthorizationException$Reason.SERVICE_UNAVAILABLE:Lorg/springframework/boot/actuate/autoconfigure/cloudfoundry/CloudFoundryAuthorizationException$Reason;
       7: ldc           #84                 // String Unable to fetch token keys from UAA.
       9: invokespecial #46                 // Method org/springframework/boot/actuate/autoconfigure/cloudfoundry/CloudFoundryAuthorizationException."<init>":(Lorg/springframework/boot/actuate/autoconfigure/cloudfoundry/CloudFoundryAuthorizationException$Reason;Ljava/lang/String;)V
      12: areturn

  private static java.lang.String lambda$getUaaUrl$2(java.util.Map);
    Code:
       0: aload_0
       1: ldc           #85                 // String token_endpoint
       3: invokeinterface #55,  2           // InterfaceMethod java/util/Map.get:(Ljava/lang/Object;)Ljava/lang/Object;
       8: checkcast     #25                 // class java/lang/String
      11: areturn

  private static java.lang.Throwable lambda$fetchTokenKeys$1(java.lang.Throwable);
    Code:
       0: new           #43                 // class org/springframework/boot/actuate/autoconfigure/cloudfoundry/CloudFoundryAuthorizationException
       3: dup
       4: getstatic     #51                 // Field org/springframework/boot/actuate/autoconfigure/cloudfoundry/CloudFoundryAuthorizationException$Reason.SERVICE_UNAVAILABLE:Lorg/springframework/boot/actuate/autoconfigure/cloudfoundry/CloudFoundryAuthorizationException$Reason;
       7: aload_0
       8: invokevirtual #86                 // Method java/lang/Throwable.getMessage:()Ljava/lang/String;
      11: invokespecial #46                 // Method org/springframework/boot/actuate/autoconfigure/cloudfoundry/CloudFoundryAuthorizationException."<init>":(Lorg/springframework/boot/actuate/autoconfigure/cloudfoundry/CloudFoundryAuthorizationException$Reason;Ljava/lang/String;)V
      14: areturn

  private void lambda$buildTrustAllSslConnector$0(reactor.netty.tcp.SslProvider$SslContextSpec);
    Code:
       0: aload_1
       1: aload_0
       2: invokespecial #87                 // Method createSslContext:()Lio/netty/handler/ssl/SslContextBuilder;
       5: invokeinterface #88,  2           // InterfaceMethod reactor/netty/tcp/SslProvider$SslContextSpec.sslContext:(Lio/netty/handler/ssl/SslContextBuilder;)Lreactor/netty/tcp/SslProvider$DefaultConfigurationSpec;
      10: pop
      11: return

  static {};
    Code:
       0: new           #89                 // class org/springframework/boot/actuate/autoconfigure/cloudfoundry/reactive/ReactiveCloudFoundrySecurityService$1
       3: dup
       4: invokespecial #90                 // Method org/springframework/boot/actuate/autoconfigure/cloudfoundry/reactive/ReactiveCloudFoundrySecurityService$1."<init>":()V
       7: putstatic     #65                 // Field STRING_OBJECT_MAP:Lorg/springframework/core/ParameterizedTypeReference;
      10: return
}
