Compiled from "TraceZuulAutoConfiguration.java"
public class org.springframework.cloud.sleuth.instrument.zuul.TraceZuulAutoConfiguration {
  public org.springframework.cloud.sleuth.instrument.zuul.TraceZuulAutoConfiguration();
    Code:
       0: aload_0
       1: invokespecial #1                  // Method java/lang/Object."<init>":()V
       4: return

  org.springframework.cloud.sleuth.instrument.zuul.TracePostZuulFilter tracePostZuulFilter(brave.http.HttpTracing);
    Code:
       0: new           #2                  // class org/springframework/cloud/sleuth/instrument/zuul/TracePostZuulFilter
       3: dup
       4: aload_1
       5: invokespecial #3                  // Method org/springframework/cloud/sleuth/instrument/zuul/TracePostZuulFilter."<init>":(Lbrave/http/HttpTracing;)V
       8: areturn

  static org.springframework.cloud.sleuth.instrument.zuul.TraceZuulHandlerMappingBeanPostProcessor traceHandlerMappingBeanPostProcessor(org.springframework.beans.factory.BeanFactory);
    Code:
       0: new           #4                  // class org/springframework/cloud/sleuth/instrument/zuul/TraceZuulHandlerMappingBeanPostProcessor
       3: dup
       4: aload_0
       5: invokespecial #5                  // Method org/springframework/cloud/sleuth/instrument/zuul/TraceZuulHandlerMappingBeanPostProcessor."<init>":(Lorg/springframework/beans/factory/BeanFactory;)V
       8: areturn
}
