Compiled from "ParameterMetadata.java"
public final class org.springframework.data.rest.core.mapping.ParameterMetadata {
  private final java.lang.String name;

  private final org.springframework.data.rest.core.mapping.ResourceDescription description;

  public org.springframework.data.rest.core.mapping.ParameterMetadata(org.springframework.core.MethodParameter, java.lang.String);
    Code:
       0: aload_0
       1: invokespecial #1                  // Method java/lang/Object."<init>":()V
       4: aload_0
       5: aload_1
       6: invokevirtual #2                  // Method org/springframework/core/MethodParameter.getParameterName:()Ljava/lang/String;
       9: putfield      #3                  // Field name:Ljava/lang/String;
      12: aload_0
      13: getfield      #3                  // Field name:Ljava/lang/String;
      16: ldc           #4                  // String Parameter name must not be null or empty!
      18: invokestatic  #5                  // Method org/springframework/util/Assert.hasText:(Ljava/lang/String;Ljava/lang/String;)V
      21: aload_2
      22: ldc           #6                  // String Method rel must not be null!
      24: invokestatic  #5                  // Method org/springframework/util/Assert.hasText:(Ljava/lang/String;Ljava/lang/String;)V
      27: aload_2
      28: ldc           #7                  // String .
      30: invokevirtual #8                  // Method java/lang/String.concat:(Ljava/lang/String;)Ljava/lang/String;
      33: aload_0
      34: getfield      #3                  // Field name:Ljava/lang/String;
      37: invokevirtual #8                  // Method java/lang/String.concat:(Ljava/lang/String;)Ljava/lang/String;
      40: aload_1
      41: invokevirtual #9                  // Method org/springframework/core/MethodParameter.getParameterType:()Ljava/lang/Class;
      44: invokestatic  #10                 // Method org/springframework/data/rest/core/mapping/TypedResourceDescription.defaultFor:(Ljava/lang/String;Ljava/lang/Class;)Lorg/springframework/data/rest/core/mapping/ResourceDescription;
      47: astore_3
      48: aload_1
      49: ldc           #11                 // class org/springframework/data/rest/core/annotation/Description
      51: invokevirtual #12                 // Method org/springframework/core/MethodParameter.getParameterAnnotation:(Ljava/lang/Class;)Ljava/lang/annotation/Annotation;
      54: checkcast     #11                 // class org/springframework/data/rest/core/annotation/Description
      57: astore        4
      59: aload_0
      60: aload         4
      62: ifnonnull     69
      65: aload_3
      66: goto          79
      69: new           #13                 // class org/springframework/data/rest/core/mapping/AnnotationBasedResourceDescription
      72: dup
      73: aload         4
      75: aload_3
      76: invokespecial #14                 // Method org/springframework/data/rest/core/mapping/AnnotationBasedResourceDescription."<init>":(Lorg/springframework/data/rest/core/annotation/Description;Lorg/springframework/data/rest/core/mapping/ResourceDescription;)V
      79: putfield      #15                 // Field description:Lorg/springframework/data/rest/core/mapping/ResourceDescription;
      82: return

  public java.lang.String getName();
    Code:
       0: aload_0
       1: getfield      #3                  // Field name:Ljava/lang/String;
       4: areturn

  public org.springframework.data.rest.core.mapping.ResourceDescription getDescription();
    Code:
       0: aload_0
       1: getfield      #15                 // Field description:Lorg/springframework/data/rest/core/mapping/ResourceDescription;
       4: areturn

  public boolean equals(java.lang.Object);
    Code:
       0: aload_0
       1: aload_1
       2: if_acmpne     7
       5: iconst_1
       6: ireturn
       7: aload_1
       8: instanceof    #16                 // class org/springframework/data/rest/core/mapping/ParameterMetadata
      11: ifne          16
      14: iconst_0
      15: ireturn
      16: aload_1
      17: checkcast     #16                 // class org/springframework/data/rest/core/mapping/ParameterMetadata
      20: astore_2
      21: aload_0
      22: getfield      #3                  // Field name:Ljava/lang/String;
      25: aload_2
      26: getfield      #3                  // Field name:Ljava/lang/String;
      29: invokevirtual #17                 // Method java/lang/String.equals:(Ljava/lang/Object;)Z
      32: ifeq          53
      35: aload_0
      36: getfield      #15                 // Field description:Lorg/springframework/data/rest/core/mapping/ResourceDescription;
      39: aload_2
      40: getfield      #15                 // Field description:Lorg/springframework/data/rest/core/mapping/ResourceDescription;
      43: invokevirtual #18                 // Method java/lang/Object.equals:(Ljava/lang/Object;)Z
      46: ifeq          53
      49: iconst_1
      50: goto          54
      53: iconst_0
      54: ireturn

  public int hashCode();
    Code:
       0: bipush        17
       2: istore_1
       3: iload_1
       4: bipush        31
       6: aload_0
       7: getfield      #3                  // Field name:Ljava/lang/String;
      10: invokevirtual #19                 // Method java/lang/String.hashCode:()I
      13: imul
      14: iadd
      15: istore_1
      16: iload_1
      17: bipush        31
      19: aload_0
      20: getfield      #15                 // Field description:Lorg/springframework/data/rest/core/mapping/ResourceDescription;
      23: invokevirtual #20                 // Method java/lang/Object.hashCode:()I
      26: imul
      27: iadd
      28: istore_1
      29: iload_1
      30: ireturn
}
