Compiled from "CreateCloudFormationTemplateResponse.java"
final class software.amazon.awssdk.services.serverlessapplicationrepository.model.CreateCloudFormationTemplateResponse$BuilderImpl extends software.amazon.awssdk.services.serverlessapplicationrepository.model.ServerlessApplicationRepositoryResponse$BuilderImpl implements software.amazon.awssdk.services.serverlessapplicationrepository.model.CreateCloudFormationTemplateResponse$Builder {
  private java.lang.String applicationId;

  private java.lang.String creationTime;

  private java.lang.String expirationTime;

  private java.lang.String semanticVersion;

  private java.lang.String status;

  private java.lang.String templateId;

  private java.lang.String templateUrl;

  private software.amazon.awssdk.services.serverlessapplicationrepository.model.CreateCloudFormationTemplateResponse$BuilderImpl();
    Code:
       0: aload_0
       1: invokespecial #10                 // Method software/amazon/awssdk/services/serverlessapplicationrepository/model/ServerlessApplicationRepositoryResponse$BuilderImpl."<init>":()V
       4: return

  private software.amazon.awssdk.services.serverlessapplicationrepository.model.CreateCloudFormationTemplateResponse$BuilderImpl(software.amazon.awssdk.services.serverlessapplicationrepository.model.CreateCloudFormationTemplateResponse);
    Code:
       0: aload_0
       1: aload_1
       2: invokespecial #11                 // Method software/amazon/awssdk/services/serverlessapplicationrepository/model/ServerlessApplicationRepositoryResponse$BuilderImpl."<init>":(Lsoftware/amazon/awssdk/services/serverlessapplicationrepository/model/ServerlessApplicationRepositoryResponse;)V
       5: aload_0
       6: aload_1
       7: invokestatic  #12                 // Method software/amazon/awssdk/services/serverlessapplicationrepository/model/CreateCloudFormationTemplateResponse.access$900:(Lsoftware/amazon/awssdk/services/serverlessapplicationrepository/model/CreateCloudFormationTemplateResponse;)Ljava/lang/String;
      10: invokevirtual #13                 // Method applicationId:(Ljava/lang/String;)Lsoftware/amazon/awssdk/services/serverlessapplicationrepository/model/CreateCloudFormationTemplateResponse$Builder;
      13: pop
      14: aload_0
      15: aload_1
      16: invokestatic  #14                 // Method software/amazon/awssdk/services/serverlessapplicationrepository/model/CreateCloudFormationTemplateResponse.access$1000:(Lsoftware/amazon/awssdk/services/serverlessapplicationrepository/model/CreateCloudFormationTemplateResponse;)Ljava/lang/String;
      19: invokevirtual #15                 // Method creationTime:(Ljava/lang/String;)Lsoftware/amazon/awssdk/services/serverlessapplicationrepository/model/CreateCloudFormationTemplateResponse$Builder;
      22: pop
      23: aload_0
      24: aload_1
      25: invokestatic  #16                 // Method software/amazon/awssdk/services/serverlessapplicationrepository/model/CreateCloudFormationTemplateResponse.access$1100:(Lsoftware/amazon/awssdk/services/serverlessapplicationrepository/model/CreateCloudFormationTemplateResponse;)Ljava/lang/String;
      28: invokevirtual #17                 // Method expirationTime:(Ljava/lang/String;)Lsoftware/amazon/awssdk/services/serverlessapplicationrepository/model/CreateCloudFormationTemplateResponse$Builder;
      31: pop
      32: aload_0
      33: aload_1
      34: invokestatic  #18                 // Method software/amazon/awssdk/services/serverlessapplicationrepository/model/CreateCloudFormationTemplateResponse.access$1200:(Lsoftware/amazon/awssdk/services/serverlessapplicationrepository/model/CreateCloudFormationTemplateResponse;)Ljava/lang/String;
      37: invokevirtual #19                 // Method semanticVersion:(Ljava/lang/String;)Lsoftware/amazon/awssdk/services/serverlessapplicationrepository/model/CreateCloudFormationTemplateResponse$Builder;
      40: pop
      41: aload_0
      42: aload_1
      43: invokestatic  #20                 // Method software/amazon/awssdk/services/serverlessapplicationrepository/model/CreateCloudFormationTemplateResponse.access$1300:(Lsoftware/amazon/awssdk/services/serverlessapplicationrepository/model/CreateCloudFormationTemplateResponse;)Ljava/lang/String;
      46: invokevirtual #21                 // Method status:(Ljava/lang/String;)Lsoftware/amazon/awssdk/services/serverlessapplicationrepository/model/CreateCloudFormationTemplateResponse$Builder;
      49: pop
      50: aload_0
      51: aload_1
      52: invokestatic  #22                 // Method software/amazon/awssdk/services/serverlessapplicationrepository/model/CreateCloudFormationTemplateResponse.access$1400:(Lsoftware/amazon/awssdk/services/serverlessapplicationrepository/model/CreateCloudFormationTemplateResponse;)Ljava/lang/String;
      55: invokevirtual #23                 // Method templateId:(Ljava/lang/String;)Lsoftware/amazon/awssdk/services/serverlessapplicationrepository/model/CreateCloudFormationTemplateResponse$Builder;
      58: pop
      59: aload_0
      60: aload_1
      61: invokestatic  #24                 // Method software/amazon/awssdk/services/serverlessapplicationrepository/model/CreateCloudFormationTemplateResponse.access$1500:(Lsoftware/amazon/awssdk/services/serverlessapplicationrepository/model/CreateCloudFormationTemplateResponse;)Ljava/lang/String;
      64: invokevirtual #25                 // Method templateUrl:(Ljava/lang/String;)Lsoftware/amazon/awssdk/services/serverlessapplicationrepository/model/CreateCloudFormationTemplateResponse$Builder;
      67: pop
      68: return

  public final java.lang.String getApplicationId();
    Code:
       0: aload_0
       1: getfield      #9                  // Field applicationId:Ljava/lang/String;
       4: areturn

  public final software.amazon.awssdk.services.serverlessapplicationrepository.model.CreateCloudFormationTemplateResponse$Builder applicationId(java.lang.String);
    Code:
       0: aload_0
       1: aload_1
       2: putfield      #9                  // Field applicationId:Ljava/lang/String;
       5: aload_0
       6: areturn

  public final void setApplicationId(java.lang.String);
    Code:
       0: aload_0
       1: aload_1
       2: putfield      #9                  // Field applicationId:Ljava/lang/String;
       5: return

  public final java.lang.String getCreationTime();
    Code:
       0: aload_0
       1: getfield      #8                  // Field creationTime:Ljava/lang/String;
       4: areturn

  public final software.amazon.awssdk.services.serverlessapplicationrepository.model.CreateCloudFormationTemplateResponse$Builder creationTime(java.lang.String);
    Code:
       0: aload_0
       1: aload_1
       2: putfield      #8                  // Field creationTime:Ljava/lang/String;
       5: aload_0
       6: areturn

  public final void setCreationTime(java.lang.String);
    Code:
       0: aload_0
       1: aload_1
       2: putfield      #8                  // Field creationTime:Ljava/lang/String;
       5: return

  public final java.lang.String getExpirationTime();
    Code:
       0: aload_0
       1: getfield      #7                  // Field expirationTime:Ljava/lang/String;
       4: areturn

  public final software.amazon.awssdk.services.serverlessapplicationrepository.model.CreateCloudFormationTemplateResponse$Builder expirationTime(java.lang.String);
    Code:
       0: aload_0
       1: aload_1
       2: putfield      #7                  // Field expirationTime:Ljava/lang/String;
       5: aload_0
       6: areturn

  public final void setExpirationTime(java.lang.String);
    Code:
       0: aload_0
       1: aload_1
       2: putfield      #7                  // Field expirationTime:Ljava/lang/String;
       5: return

  public final java.lang.String getSemanticVersion();
    Code:
       0: aload_0
       1: getfield      #6                  // Field semanticVersion:Ljava/lang/String;
       4: areturn

  public final software.amazon.awssdk.services.serverlessapplicationrepository.model.CreateCloudFormationTemplateResponse$Builder semanticVersion(java.lang.String);
    Code:
       0: aload_0
       1: aload_1
       2: putfield      #6                  // Field semanticVersion:Ljava/lang/String;
       5: aload_0
       6: areturn

  public final void setSemanticVersion(java.lang.String);
    Code:
       0: aload_0
       1: aload_1
       2: putfield      #6                  // Field semanticVersion:Ljava/lang/String;
       5: return

  public final java.lang.String getStatus();
    Code:
       0: aload_0
       1: getfield      #5                  // Field status:Ljava/lang/String;
       4: areturn

  public final software.amazon.awssdk.services.serverlessapplicationrepository.model.CreateCloudFormationTemplateResponse$Builder status(java.lang.String);
    Code:
       0: aload_0
       1: aload_1
       2: putfield      #5                  // Field status:Ljava/lang/String;
       5: aload_0
       6: areturn

  public final software.amazon.awssdk.services.serverlessapplicationrepository.model.CreateCloudFormationTemplateResponse$Builder status(software.amazon.awssdk.services.serverlessapplicationrepository.model.Status);
    Code:
       0: aload_0
       1: aload_1
       2: ifnonnull     9
       5: aconst_null
       6: goto          13
       9: aload_1
      10: invokevirtual #26                 // Method software/amazon/awssdk/services/serverlessapplicationrepository/model/Status.toString:()Ljava/lang/String;
      13: invokevirtual #21                 // Method status:(Ljava/lang/String;)Lsoftware/amazon/awssdk/services/serverlessapplicationrepository/model/CreateCloudFormationTemplateResponse$Builder;
      16: pop
      17: aload_0
      18: areturn

  public final void setStatus(java.lang.String);
    Code:
       0: aload_0
       1: aload_1
       2: putfield      #5                  // Field status:Ljava/lang/String;
       5: return

  public final java.lang.String getTemplateId();
    Code:
       0: aload_0
       1: getfield      #4                  // Field templateId:Ljava/lang/String;
       4: areturn

  public final software.amazon.awssdk.services.serverlessapplicationrepository.model.CreateCloudFormationTemplateResponse$Builder templateId(java.lang.String);
    Code:
       0: aload_0
       1: aload_1
       2: putfield      #4                  // Field templateId:Ljava/lang/String;
       5: aload_0
       6: areturn

  public final void setTemplateId(java.lang.String);
    Code:
       0: aload_0
       1: aload_1
       2: putfield      #4                  // Field templateId:Ljava/lang/String;
       5: return

  public final java.lang.String getTemplateUrl();
    Code:
       0: aload_0
       1: getfield      #3                  // Field templateUrl:Ljava/lang/String;
       4: areturn

  public final software.amazon.awssdk.services.serverlessapplicationrepository.model.CreateCloudFormationTemplateResponse$Builder templateUrl(java.lang.String);
    Code:
       0: aload_0
       1: aload_1
       2: putfield      #3                  // Field templateUrl:Ljava/lang/String;
       5: aload_0
       6: areturn

  public final void setTemplateUrl(java.lang.String);
    Code:
       0: aload_0
       1: aload_1
       2: putfield      #3                  // Field templateUrl:Ljava/lang/String;
       5: return

  public software.amazon.awssdk.services.serverlessapplicationrepository.model.CreateCloudFormationTemplateResponse build();
    Code:
       0: new           #27                 // class software/amazon/awssdk/services/serverlessapplicationrepository/model/CreateCloudFormationTemplateResponse
       3: dup
       4: aload_0
       5: aconst_null
       6: invokespecial #28                 // Method software/amazon/awssdk/services/serverlessapplicationrepository/model/CreateCloudFormationTemplateResponse."<init>":(Lsoftware/amazon/awssdk/services/serverlessapplicationrepository/model/CreateCloudFormationTemplateResponse$BuilderImpl;Lsoftware/amazon/awssdk/services/serverlessapplicationrepository/model/CreateCloudFormationTemplateResponse$1;)V
       9: areturn

  public java.util.List<software.amazon.awssdk.core.SdkField<?>> sdkFields();
    Code:
       0: invokestatic  #29                 // Method software/amazon/awssdk/services/serverlessapplicationrepository/model/CreateCloudFormationTemplateResponse.access$1700:()Ljava/util/List;
       3: areturn

  public software.amazon.awssdk.services.serverlessapplicationrepository.model.ServerlessApplicationRepositoryResponse build();
    Code:
       0: aload_0
       1: invokevirtual #30                 // Method build:()Lsoftware/amazon/awssdk/services/serverlessapplicationrepository/model/CreateCloudFormationTemplateResponse;
       4: areturn

  public software.amazon.awssdk.awscore.AwsResponse build();
    Code:
       0: aload_0
       1: invokevirtual #30                 // Method build:()Lsoftware/amazon/awssdk/services/serverlessapplicationrepository/model/CreateCloudFormationTemplateResponse;
       4: areturn

  public software.amazon.awssdk.core.SdkResponse build();
    Code:
       0: aload_0
       1: invokevirtual #30                 // Method build:()Lsoftware/amazon/awssdk/services/serverlessapplicationrepository/model/CreateCloudFormationTemplateResponse;
       4: areturn

  public java.lang.Object build();
    Code:
       0: aload_0
       1: invokevirtual #30                 // Method build:()Lsoftware/amazon/awssdk/services/serverlessapplicationrepository/model/CreateCloudFormationTemplateResponse;
       4: areturn

  static java.lang.String access$000(software.amazon.awssdk.services.serverlessapplicationrepository.model.CreateCloudFormationTemplateResponse$BuilderImpl);
    Code:
       0: aload_0
       1: getfield      #9                  // Field applicationId:Ljava/lang/String;
       4: areturn

  static java.lang.String access$100(software.amazon.awssdk.services.serverlessapplicationrepository.model.CreateCloudFormationTemplateResponse$BuilderImpl);
    Code:
       0: aload_0
       1: getfield      #8                  // Field creationTime:Ljava/lang/String;
       4: areturn

  static java.lang.String access$200(software.amazon.awssdk.services.serverlessapplicationrepository.model.CreateCloudFormationTemplateResponse$BuilderImpl);
    Code:
       0: aload_0
       1: getfield      #7                  // Field expirationTime:Ljava/lang/String;
       4: areturn

  static java.lang.String access$300(software.amazon.awssdk.services.serverlessapplicationrepository.model.CreateCloudFormationTemplateResponse$BuilderImpl);
    Code:
       0: aload_0
       1: getfield      #6                  // Field semanticVersion:Ljava/lang/String;
       4: areturn

  static java.lang.String access$400(software.amazon.awssdk.services.serverlessapplicationrepository.model.CreateCloudFormationTemplateResponse$BuilderImpl);
    Code:
       0: aload_0
       1: getfield      #5                  // Field status:Ljava/lang/String;
       4: areturn

  static java.lang.String access$500(software.amazon.awssdk.services.serverlessapplicationrepository.model.CreateCloudFormationTemplateResponse$BuilderImpl);
    Code:
       0: aload_0
       1: getfield      #4                  // Field templateId:Ljava/lang/String;
       4: areturn

  static java.lang.String access$600(software.amazon.awssdk.services.serverlessapplicationrepository.model.CreateCloudFormationTemplateResponse$BuilderImpl);
    Code:
       0: aload_0
       1: getfield      #3                  // Field templateUrl:Ljava/lang/String;
       4: areturn

  software.amazon.awssdk.services.serverlessapplicationrepository.model.CreateCloudFormationTemplateResponse$BuilderImpl(software.amazon.awssdk.services.serverlessapplicationrepository.model.CreateCloudFormationTemplateResponse, software.amazon.awssdk.services.serverlessapplicationrepository.model.CreateCloudFormationTemplateResponse$1);
    Code:
       0: aload_0
       1: aload_1
       2: invokespecial #2                  // Method "<init>":(Lsoftware/amazon/awssdk/services/serverlessapplicationrepository/model/CreateCloudFormationTemplateResponse;)V
       5: return

  software.amazon.awssdk.services.serverlessapplicationrepository.model.CreateCloudFormationTemplateResponse$BuilderImpl(software.amazon.awssdk.services.serverlessapplicationrepository.model.CreateCloudFormationTemplateResponse$1);
    Code:
       0: aload_0
       1: invokespecial #1                  // Method "<init>":()V
       4: return
}
