Compiled from "SanityChecker.java"
public interface ch.qos.logback.core.joran.sanity.SanityChecker {
  public abstract void check(ch.qos.logback.core.model.Model);

  public default void deepFindAllModelsOfType(java.lang.Class<? extends ch.qos.logback.core.model.Model>, java.util.List<ch.qos.logback.core.model.Model>, ch.qos.logback.core.model.Model);
    Code:
       0: aload_1
       1: aload_3
       2: invokevirtual #1                  // Method java/lang/Class.isInstance:(Ljava/lang/Object;)Z
       5: ifeq          16
       8: aload_2
       9: aload_3
      10: invokeinterface #7,  2            // InterfaceMethod java/util/List.add:(Ljava/lang/Object;)Z
      15: pop
      16: aload_3
      17: invokevirtual #12                 // Method ch/qos/logback/core/model/Model.getSubModels:()Ljava/util/List;
      20: invokeinterface #18,  1           // InterfaceMethod java/util/List.iterator:()Ljava/util/Iterator;
      25: astore        4
      27: aload         4
      29: invokeinterface #22,  1           // InterfaceMethod java/util/Iterator.hasNext:()Z
      34: ifeq          62
      37: aload         4
      39: invokeinterface #28,  1           // InterfaceMethod java/util/Iterator.next:()Ljava/lang/Object;
      44: checkcast     #13                 // class ch/qos/logback/core/model/Model
      47: astore        5
      49: aload_0
      50: aload_1
      51: aload_2
      52: aload         5
      54: invokeinterface #32,  4           // InterfaceMethod deepFindAllModelsOfType:(Ljava/lang/Class;Ljava/util/List;Lch/qos/logback/core/model/Model;)V
      59: goto          27
      62: return

  public default java.util.List<ch.qos.logback.core.joran.sanity.Pair<ch.qos.logback.core.model.Model, ch.qos.logback.core.model.Model>> deepFindNestedSubModelsOfType(java.lang.Class<? extends ch.qos.logback.core.model.Model>, java.util.List<? extends ch.qos.logback.core.model.Model>);
    Code:
       0: new           #38                 // class java/util/ArrayList
       3: dup
       4: invokespecial #40                 // Method java/util/ArrayList."<init>":()V
       7: astore_3
       8: aload_2
       9: invokeinterface #18,  1           // InterfaceMethod java/util/List.iterator:()Ljava/util/Iterator;
      14: astore        4
      16: aload         4
      18: invokeinterface #22,  1           // InterfaceMethod java/util/Iterator.hasNext:()Z
      23: ifeq          89
      26: aload         4
      28: invokeinterface #28,  1           // InterfaceMethod java/util/Iterator.next:()Ljava/lang/Object;
      33: checkcast     #13                 // class ch/qos/logback/core/model/Model
      36: astore        5
      38: new           #38                 // class java/util/ArrayList
      41: dup
      42: invokespecial #40                 // Method java/util/ArrayList."<init>":()V
      45: astore        6
      47: aload         5
      49: invokevirtual #12                 // Method ch/qos/logback/core/model/Model.getSubModels:()Ljava/util/List;
      52: invokeinterface #44,  1           // InterfaceMethod java/util/List.stream:()Ljava/util/stream/Stream;
      57: aload_0
      58: aload_1
      59: aload         6
      61: invokedynamic #48,  0             // InvokeDynamic #0:accept:(Lch/qos/logback/core/joran/sanity/SanityChecker;Ljava/lang/Class;Ljava/util/List;)Ljava/util/function/Consumer;
      66: invokeinterface #52,  2           // InterfaceMethod java/util/stream/Stream.forEach:(Ljava/util/function/Consumer;)V
      71: aload         6
      73: aload_3
      74: aload         5
      76: invokedynamic #58,  0             // InvokeDynamic #1:accept:(Ljava/util/List;Lch/qos/logback/core/model/Model;)Ljava/util/function/Consumer;
      81: invokeinterface #61,  2           // InterfaceMethod java/util/List.forEach:(Ljava/util/function/Consumer;)V
      86: goto          16
      89: aload_3
      90: areturn

  private static void lambda$deepFindNestedSubModelsOfType$1(java.util.List, ch.qos.logback.core.model.Model, ch.qos.logback.core.model.Model);
    Code:
       0: aload_0
       1: new           #62                 // class ch/qos/logback/core/joran/sanity/Pair
       4: dup
       5: aload_1
       6: aload_2
       7: invokespecial #64                 // Method ch/qos/logback/core/joran/sanity/Pair."<init>":(Ljava/lang/Object;Ljava/lang/Object;)V
      10: invokeinterface #7,  2            // InterfaceMethod java/util/List.add:(Ljava/lang/Object;)Z
      15: pop
      16: return

  private void lambda$deepFindNestedSubModelsOfType$0(java.lang.Class, java.util.List, ch.qos.logback.core.model.Model);
    Code:
       0: aload_0
       1: aload_1
       2: aload_2
       3: aload_3
       4: invokeinterface #32,  4           // InterfaceMethod deepFindAllModelsOfType:(Ljava/lang/Class;Ljava/util/List;Lch/qos/logback/core/model/Model;)V
       9: return
}
