Compiled from "LazyURLInputStream.java"
class org.apache.jena.shared.wg.LazyURLInputStream extends org.apache.jena.shared.wg.LazyInputStream {
  private java.net.URL url;

  org.apache.jena.shared.wg.LazyURLInputStream(java.net.URL);
    Code:
       0: aload_0
       1: invokespecial #1                  // Method org/apache/jena/shared/wg/LazyInputStream."<init>":()V
       4: aload_0
       5: aload_1
       6: putfield      #2                  // Field url:Ljava/net/URL;
       9: return

  java.io.InputStream open() throws java.io.IOException;
    Code:
       0: aload_0
       1: getfield      #2                  // Field url:Ljava/net/URL;
       4: invokevirtual #3                  // Method java/net/URL.openConnection:()Ljava/net/URLConnection;
       7: astore_1
       8: aload_1
       9: invokevirtual #4                  // Method java/net/URLConnection.getInputStream:()Ljava/io/InputStream;
      12: areturn
}
