Compiled from "SetRepositoryPolicyRequest.kt"
public final class aws.sdk.kotlin.services.ecrpublic.model.SetRepositoryPolicyRequest$Builder {
  private boolean force;

  private java.lang.String policyText;

  private java.lang.String registryId;

  private java.lang.String repositoryName;

  public final boolean getForce();
    Code:
       0: aload_0
       1: getfield      #10                 // Field force:Z
       4: ireturn

  public final void setForce(boolean);
    Code:
       0: aload_0
       1: iload_1
       2: putfield      #10                 // Field force:Z
       5: return

  public final java.lang.String getPolicyText();
    Code:
       0: aload_0
       1: getfield      #22                 // Field policyText:Ljava/lang/String;
       4: areturn

  public final void setPolicyText(java.lang.String);
    Code:
       0: aload_0
       1: aload_1
       2: putfield      #22                 // Field policyText:Ljava/lang/String;
       5: return

  public final java.lang.String getRegistryId();
    Code:
       0: aload_0
       1: getfield      #28                 // Field registryId:Ljava/lang/String;
       4: areturn

  public final void setRegistryId(java.lang.String);
    Code:
       0: aload_0
       1: aload_1
       2: putfield      #28                 // Field registryId:Ljava/lang/String;
       5: return

  public final java.lang.String getRepositoryName();
    Code:
       0: aload_0
       1: getfield      #33                 // Field repositoryName:Ljava/lang/String;
       4: areturn

  public final void setRepositoryName(java.lang.String);
    Code:
       0: aload_0
       1: aload_1
       2: putfield      #33                 // Field repositoryName:Ljava/lang/String;
       5: return

  public aws.sdk.kotlin.services.ecrpublic.model.SetRepositoryPolicyRequest$Builder();
    Code:
       0: aload_0
       1: invokespecial #39                 // Method java/lang/Object."<init>":()V
       4: return

  public aws.sdk.kotlin.services.ecrpublic.model.SetRepositoryPolicyRequest$Builder(aws.sdk.kotlin.services.ecrpublic.model.SetRepositoryPolicyRequest);
    Code:
       0: aload_1
       1: ldc           #43                 // String x
       3: invokestatic  #49                 // Method kotlin/jvm/internal/Intrinsics.checkNotNullParameter:(Ljava/lang/Object;Ljava/lang/String;)V
       6: aload_0
       7: invokespecial #50                 // Method "<init>":()V
      10: aload_0
      11: aload_1
      12: invokevirtual #54                 // Method aws/sdk/kotlin/services/ecrpublic/model/SetRepositoryPolicyRequest.getForce:()Z
      15: putfield      #10                 // Field force:Z
      18: aload_0
      19: aload_1
      20: invokevirtual #56                 // Method aws/sdk/kotlin/services/ecrpublic/model/SetRepositoryPolicyRequest.getPolicyText:()Ljava/lang/String;
      23: putfield      #22                 // Field policyText:Ljava/lang/String;
      26: aload_0
      27: aload_1
      28: invokevirtual #58                 // Method aws/sdk/kotlin/services/ecrpublic/model/SetRepositoryPolicyRequest.getRegistryId:()Ljava/lang/String;
      31: putfield      #28                 // Field registryId:Ljava/lang/String;
      34: aload_0
      35: aload_1
      36: invokevirtual #60                 // Method aws/sdk/kotlin/services/ecrpublic/model/SetRepositoryPolicyRequest.getRepositoryName:()Ljava/lang/String;
      39: putfield      #33                 // Field repositoryName:Ljava/lang/String;
      42: return

  public final aws.sdk.kotlin.services.ecrpublic.model.SetRepositoryPolicyRequest build();
    Code:
       0: new           #52                 // class aws/sdk/kotlin/services/ecrpublic/model/SetRepositoryPolicyRequest
       3: dup
       4: aload_0
       5: aconst_null
       6: invokespecial #66                 // Method aws/sdk/kotlin/services/ecrpublic/model/SetRepositoryPolicyRequest."<init>":(Laws/sdk/kotlin/services/ecrpublic/model/SetRepositoryPolicyRequest$Builder;Lkotlin/jvm/internal/DefaultConstructorMarker;)V
       9: areturn
}
