Compiled from "DefaultLicenseManagerAsyncClientBuilder.java"
final class software.amazon.awssdk.services.licensemanager.DefaultLicenseManagerAsyncClientBuilder extends software.amazon.awssdk.services.licensemanager.DefaultLicenseManagerBaseClientBuilder<software.amazon.awssdk.services.licensemanager.LicenseManagerAsyncClientBuilder, software.amazon.awssdk.services.licensemanager.LicenseManagerAsyncClient> implements software.amazon.awssdk.services.licensemanager.LicenseManagerAsyncClientBuilder {
  software.amazon.awssdk.services.licensemanager.DefaultLicenseManagerAsyncClientBuilder();
    Code:
       0: aload_0
       1: invokespecial #1                  // Method software/amazon/awssdk/services/licensemanager/DefaultLicenseManagerBaseClientBuilder."<init>":()V
       4: return

  public software.amazon.awssdk.services.licensemanager.DefaultLicenseManagerAsyncClientBuilder endpointProvider(software.amazon.awssdk.services.licensemanager.endpoints.LicenseManagerEndpointProvider);
    Code:
       0: aload_0
       1: getfield      #2                  // Field clientConfiguration:Lsoftware/amazon/awssdk/core/client/config/SdkClientConfiguration$Builder;
       4: getstatic     #3                  // Field software/amazon/awssdk/core/client/config/SdkClientOption.ENDPOINT_PROVIDER:Lsoftware/amazon/awssdk/core/client/config/SdkClientOption;
       7: aload_1
       8: invokevirtual #4                  // Method software/amazon/awssdk/core/client/config/SdkClientConfiguration$Builder.option:(Lsoftware/amazon/awssdk/core/client/config/ClientOption;Ljava/lang/Object;)Lsoftware/amazon/awssdk/core/client/config/SdkClientConfiguration$Builder;
      11: pop
      12: aload_0
      13: areturn

  protected final software.amazon.awssdk.services.licensemanager.LicenseManagerAsyncClient buildClient();
    Code:
       0: aload_0
       1: invokespecial #5                  // Method software/amazon/awssdk/services/licensemanager/DefaultLicenseManagerBaseClientBuilder.asyncClientConfiguration:()Lsoftware/amazon/awssdk/core/client/config/SdkClientConfiguration;
       4: astore_1
       5: aload_0
       6: pop
       7: aload_1
       8: invokestatic  #6                  // Method validateClientOptions:(Lsoftware/amazon/awssdk/core/client/config/SdkClientConfiguration;)V
      11: aload_0
      12: aload_1
      13: invokespecial #7                  // Method initializeServiceClientConfig:(Lsoftware/amazon/awssdk/core/client/config/SdkClientConfiguration;)Lsoftware/amazon/awssdk/services/licensemanager/LicenseManagerServiceClientConfiguration;
      16: astore_2
      17: new           #8                  // class software/amazon/awssdk/services/licensemanager/DefaultLicenseManagerAsyncClient
      20: dup
      21: aload_2
      22: aload_1
      23: invokespecial #9                  // Method software/amazon/awssdk/services/licensemanager/DefaultLicenseManagerAsyncClient."<init>":(Lsoftware/amazon/awssdk/services/licensemanager/LicenseManagerServiceClientConfiguration;Lsoftware/amazon/awssdk/core/client/config/SdkClientConfiguration;)V
      26: astore_3
      27: aload_3
      28: areturn

  private software.amazon.awssdk.services.licensemanager.LicenseManagerServiceClientConfiguration initializeServiceClientConfig(software.amazon.awssdk.core.client.config.SdkClientConfiguration);
    Code:
       0: aconst_null
       1: astore_2
       2: getstatic     #10                 // Field java/lang/Boolean.TRUE:Ljava/lang/Boolean;
       5: aload_1
       6: getstatic     #11                 // Field software/amazon/awssdk/core/client/config/SdkClientOption.ENDPOINT_OVERRIDDEN:Lsoftware/amazon/awssdk/core/client/config/SdkClientOption;
       9: invokevirtual #12                 // Method software/amazon/awssdk/core/client/config/SdkClientConfiguration.option:(Lsoftware/amazon/awssdk/core/client/config/ClientOption;)Ljava/lang/Object;
      12: invokevirtual #13                 // Method java/lang/Boolean.equals:(Ljava/lang/Object;)Z
      15: ifeq          29
      18: aload_1
      19: getstatic     #14                 // Field software/amazon/awssdk/core/client/config/SdkClientOption.ENDPOINT:Lsoftware/amazon/awssdk/core/client/config/SdkClientOption;
      22: invokevirtual #12                 // Method software/amazon/awssdk/core/client/config/SdkClientConfiguration.option:(Lsoftware/amazon/awssdk/core/client/config/ClientOption;)Ljava/lang/Object;
      25: checkcast     #15                 // class java/net/URI
      28: astore_2
      29: invokestatic  #16                 // Method software/amazon/awssdk/services/licensemanager/LicenseManagerServiceClientConfiguration.builder:()Lsoftware/amazon/awssdk/services/licensemanager/LicenseManagerServiceClientConfiguration$Builder;
      32: aload_0
      33: invokevirtual #17                 // Method overrideConfiguration:()Lsoftware/amazon/awssdk/core/client/config/ClientOverrideConfiguration;
      36: invokeinterface #18,  2           // InterfaceMethod software/amazon/awssdk/services/licensemanager/LicenseManagerServiceClientConfiguration$Builder.overrideConfiguration:(Lsoftware/amazon/awssdk/core/client/config/ClientOverrideConfiguration;)Lsoftware/amazon/awssdk/services/licensemanager/LicenseManagerServiceClientConfiguration$Builder;
      41: aload_1
      42: getstatic     #19                 // Field software/amazon/awssdk/awscore/client/config/AwsClientOption.AWS_REGION:Lsoftware/amazon/awssdk/awscore/client/config/AwsClientOption;
      45: invokevirtual #12                 // Method software/amazon/awssdk/core/client/config/SdkClientConfiguration.option:(Lsoftware/amazon/awssdk/core/client/config/ClientOption;)Ljava/lang/Object;
      48: checkcast     #20                 // class software/amazon/awssdk/regions/Region
      51: invokeinterface #21,  2           // InterfaceMethod software/amazon/awssdk/services/licensemanager/LicenseManagerServiceClientConfiguration$Builder.region:(Lsoftware/amazon/awssdk/regions/Region;)Lsoftware/amazon/awssdk/services/licensemanager/LicenseManagerServiceClientConfiguration$Builder;
      56: aload_2
      57: invokeinterface #22,  2           // InterfaceMethod software/amazon/awssdk/services/licensemanager/LicenseManagerServiceClientConfiguration$Builder.endpointOverride:(Ljava/net/URI;)Lsoftware/amazon/awssdk/services/licensemanager/LicenseManagerServiceClientConfiguration$Builder;
      62: aload_1
      63: getstatic     #3                  // Field software/amazon/awssdk/core/client/config/SdkClientOption.ENDPOINT_PROVIDER:Lsoftware/amazon/awssdk/core/client/config/SdkClientOption;
      66: invokevirtual #12                 // Method software/amazon/awssdk/core/client/config/SdkClientConfiguration.option:(Lsoftware/amazon/awssdk/core/client/config/ClientOption;)Ljava/lang/Object;
      69: checkcast     #23                 // class software/amazon/awssdk/endpoints/EndpointProvider
      72: invokeinterface #24,  2           // InterfaceMethod software/amazon/awssdk/services/licensemanager/LicenseManagerServiceClientConfiguration$Builder.endpointProvider:(Lsoftware/amazon/awssdk/endpoints/EndpointProvider;)Lsoftware/amazon/awssdk/services/licensemanager/LicenseManagerServiceClientConfiguration$Builder;
      77: invokeinterface #25,  1           // InterfaceMethod software/amazon/awssdk/services/licensemanager/LicenseManagerServiceClientConfiguration$Builder.build:()Lsoftware/amazon/awssdk/services/licensemanager/LicenseManagerServiceClientConfiguration;
      82: areturn

  protected java.lang.Object buildClient();
    Code:
       0: aload_0
       1: invokevirtual #26                 // Method buildClient:()Lsoftware/amazon/awssdk/services/licensemanager/LicenseManagerAsyncClient;
       4: areturn

  public software.amazon.awssdk.core.client.builder.SdkAsyncClientBuilder httpClientBuilder(software.amazon.awssdk.http.async.SdkAsyncHttpClient$Builder);
    Code:
       0: aload_0
       1: aload_1
       2: invokespecial #27                 // Method software/amazon/awssdk/services/licensemanager/DefaultLicenseManagerBaseClientBuilder.httpClientBuilder:(Lsoftware/amazon/awssdk/http/async/SdkAsyncHttpClient$Builder;)Lsoftware/amazon/awssdk/core/client/builder/SdkClientBuilder;
       5: checkcast     #28                 // class software/amazon/awssdk/core/client/builder/SdkAsyncClientBuilder
       8: areturn

  public software.amazon.awssdk.core.client.builder.SdkAsyncClientBuilder httpClient(software.amazon.awssdk.http.async.SdkAsyncHttpClient);
    Code:
       0: aload_0
       1: aload_1
       2: invokespecial #29                 // Method software/amazon/awssdk/services/licensemanager/DefaultLicenseManagerBaseClientBuilder.httpClient:(Lsoftware/amazon/awssdk/http/async/SdkAsyncHttpClient;)Lsoftware/amazon/awssdk/core/client/builder/SdkClientBuilder;
       5: checkcast     #28                 // class software/amazon/awssdk/core/client/builder/SdkAsyncClientBuilder
       8: areturn

  public software.amazon.awssdk.core.client.builder.SdkAsyncClientBuilder asyncConfiguration(software.amazon.awssdk.core.client.config.ClientAsyncConfiguration);
    Code:
       0: aload_0
       1: aload_1
       2: invokespecial #30                 // Method software/amazon/awssdk/services/licensemanager/DefaultLicenseManagerBaseClientBuilder.asyncConfiguration:(Lsoftware/amazon/awssdk/core/client/config/ClientAsyncConfiguration;)Lsoftware/amazon/awssdk/core/client/builder/SdkClientBuilder;
       5: checkcast     #28                 // class software/amazon/awssdk/core/client/builder/SdkAsyncClientBuilder
       8: areturn

  public software.amazon.awssdk.services.licensemanager.LicenseManagerBaseClientBuilder endpointProvider(software.amazon.awssdk.services.licensemanager.endpoints.LicenseManagerEndpointProvider);
    Code:
       0: aload_0
       1: aload_1
       2: invokevirtual #31                 // Method endpointProvider:(Lsoftware/amazon/awssdk/services/licensemanager/endpoints/LicenseManagerEndpointProvider;)Lsoftware/amazon/awssdk/services/licensemanager/DefaultLicenseManagerAsyncClientBuilder;
       5: areturn
}
