Compiled from "SecurityContextTokenValidatorImpl.java"
class org.apache.wss4j.stax.validate.SecurityContextTokenValidatorImpl$1 extends org.apache.xml.security.stax.impl.securityToken.AbstractInboundSecurityToken {
  final java.lang.String val$identifier;

  final org.apache.wss4j.stax.validate.TokenContext val$tokenContext;

  final org.apache.wss4j.binding.wssc.AbstractSecurityContextTokenType val$securityContextTokenType;

  final org.apache.wss4j.stax.validate.SecurityContextTokenValidatorImpl this$0;

  org.apache.wss4j.stax.validate.SecurityContextTokenValidatorImpl$1(org.apache.wss4j.stax.validate.SecurityContextTokenValidatorImpl, org.apache.xml.security.stax.ext.InboundSecurityContext, java.lang.String, org.apache.xml.security.stax.securityToken.SecurityTokenConstants$KeyIdentifier, boolean, java.lang.String, org.apache.wss4j.stax.validate.TokenContext, org.apache.wss4j.binding.wssc.AbstractSecurityContextTokenType);
    Code:
       0: aload_0
       1: aload_1
       2: putfield      #1                  // Field this$0:Lorg/apache/wss4j/stax/validate/SecurityContextTokenValidatorImpl;
       5: aload_0
       6: aload         6
       8: putfield      #2                  // Field val$identifier:Ljava/lang/String;
      11: aload_0
      12: aload         7
      14: putfield      #3                  // Field val$tokenContext:Lorg/apache/wss4j/stax/validate/TokenContext;
      17: aload_0
      18: aload         8
      20: putfield      #4                  // Field val$securityContextTokenType:Lorg/apache/wss4j/binding/wssc/AbstractSecurityContextTokenType;
      23: aload_0
      24: aload_2
      25: aload_3
      26: aload         4
      28: iload         5
      30: invokespecial #5                  // Method org/apache/xml/security/stax/impl/securityToken/AbstractInboundSecurityToken."<init>":(Lorg/apache/xml/security/stax/ext/InboundSecurityContext;Ljava/lang/String;Lorg/apache/xml/security/stax/securityToken/SecurityTokenConstants$KeyIdentifier;Z)V
      33: return

  public boolean isAsymmetric();
    Code:
       0: iconst_0
       1: ireturn

  public java.security.Key getKey(java.lang.String, org.apache.xml.security.stax.ext.XMLSecurityConstants$AlgorithmUsage, java.lang.String) throws org.apache.xml.security.exceptions.XMLSecurityException;
    Code:
       0: aload_0
       1: invokevirtual #6                  // Method getSecretKey:()Ljava/util/Map;
       4: aload_1
       5: invokeinterface #7,  2            // InterfaceMethod java/util/Map.get:(Ljava/lang/Object;)Ljava/lang/Object;
      10: checkcast     #8                  // class java/security/Key
      13: astore        4
      15: aload         4
      17: ifnull        23
      20: aload         4
      22: areturn
      23: new           #9                  // class org/apache/wss4j/common/ext/WSPasswordCallback
      26: dup
      27: aload_0
      28: getfield      #2                  // Field val$identifier:Ljava/lang/String;
      31: bipush        6
      33: invokespecial #10                 // Method org/apache/wss4j/common/ext/WSPasswordCallback."<init>":(Ljava/lang/String;I)V
      36: astore        5
      38: aload_0
      39: getfield      #3                  // Field val$tokenContext:Lorg/apache/wss4j/stax/validate/TokenContext;
      42: invokevirtual #11                 // Method org/apache/wss4j/stax/validate/TokenContext.getWssSecurityProperties:()Lorg/apache/wss4j/stax/ext/WSSSecurityProperties;
      45: invokevirtual #12                 // Method org/apache/wss4j/stax/ext/WSSSecurityProperties.getCallbackHandler:()Ljavax/security/auth/callback/CallbackHandler;
      48: aload         5
      50: aconst_null
      51: invokestatic  #13                 // Method org/apache/wss4j/stax/utils/WSSUtils.doSecretKeyCallback:(Ljavax/security/auth/callback/CallbackHandler;Ljavax/security/auth/callback/Callback;Ljava/lang/String;)V
      54: aload         5
      56: invokevirtual #14                 // Method org/apache/wss4j/common/ext/WSPasswordCallback.getKey:()[B
      59: ifnonnull     89
      62: new           #15                 // class org/apache/wss4j/common/ext/WSSecurityException
      65: dup
      66: getstatic     #16                 // Field org/apache/wss4j/common/ext/WSSecurityException$ErrorCode.SECURITY_TOKEN_UNAVAILABLE:Lorg/apache/wss4j/common/ext/WSSecurityException$ErrorCode;
      69: ldc           #17                 // String noKey
      71: iconst_1
      72: anewarray     #18                 // class java/lang/Object
      75: dup
      76: iconst_0
      77: aload_0
      78: getfield      #4                  // Field val$securityContextTokenType:Lorg/apache/wss4j/binding/wssc/AbstractSecurityContextTokenType;
      81: invokevirtual #19                 // Method org/apache/wss4j/binding/wssc/AbstractSecurityContextTokenType.getId:()Ljava/lang/String;
      84: aastore
      85: invokespecial #20                 // Method org/apache/wss4j/common/ext/WSSecurityException."<init>":(Lorg/apache/wss4j/common/ext/WSSecurityException$ErrorCode;Ljava/lang/String;[Ljava/lang/Object;)V
      88: athrow
      89: aload_1
      90: invokestatic  #21                 // Method org/apache/xml/security/algorithms/JCEMapper.getJCEKeyAlgorithmFromURI:(Ljava/lang/String;)Ljava/lang/String;
      93: astore        6
      95: new           #22                 // class javax/crypto/spec/SecretKeySpec
      98: dup
      99: aload         5
     101: invokevirtual #14                 // Method org/apache/wss4j/common/ext/WSPasswordCallback.getKey:()[B
     104: aload         6
     106: invokespecial #23                 // Method javax/crypto/spec/SecretKeySpec."<init>":([BLjava/lang/String;)V
     109: astore        4
     111: aload_0
     112: aload_1
     113: aload         4
     115: invokevirtual #24                 // Method setSecretKey:(Ljava/lang/String;Ljava/security/Key;)V
     118: aload         4
     120: areturn

  public org.apache.xml.security.stax.securityToken.SecurityTokenConstants$TokenType getTokenType();
    Code:
       0: getstatic     #25                 // Field org/apache/wss4j/stax/securityToken/WSSecurityTokenConstants.SecurityContextToken:Lorg/apache/xml/security/stax/securityToken/SecurityTokenConstants$TokenType;
       3: areturn
}
