Compiled from "ClassMetadata.java"
public interface org.springframework.core.type.ClassMetadata {
  public abstract java.lang.String getClassName();

  public abstract boolean isInterface();

  public abstract boolean isAnnotation();

  public abstract boolean isAbstract();

  public default boolean isConcrete();
    Code:
       0: aload_0
       1: invokeinterface #1,  1            // InterfaceMethod isInterface:()Z
       6: ifne          22
       9: aload_0
      10: invokeinterface #2,  1            // InterfaceMethod isAbstract:()Z
      15: ifne          22
      18: iconst_1
      19: goto          23
      22: iconst_0
      23: ireturn

  public abstract boolean isFinal();

  public abstract boolean isIndependent();

  public default boolean hasEnclosingClass();
    Code:
       0: aload_0
       1: invokeinterface #3,  1            // InterfaceMethod getEnclosingClassName:()Ljava/lang/String;
       6: ifnull        13
       9: iconst_1
      10: goto          14
      13: iconst_0
      14: ireturn

  public abstract java.lang.String getEnclosingClassName();

  public default boolean hasSuperClass();
    Code:
       0: aload_0
       1: invokeinterface #4,  1            // InterfaceMethod getSuperClassName:()Ljava/lang/String;
       6: ifnull        13
       9: iconst_1
      10: goto          14
      13: iconst_0
      14: ireturn

  public abstract java.lang.String getSuperClassName();

  public abstract java.lang.String[] getInterfaceNames();

  public abstract java.lang.String[] getMemberClassNames();
}
