Compiled from "MD5Digest.java"
public class org.postgresql.util.MD5Digest {
  private org.postgresql.util.MD5Digest();
    Code:
       0: aload_0
       1: invokespecial #1                  // Method java/lang/Object."<init>":()V
       4: return

  public static byte[] encode(byte[], byte[], byte[]);
    Code:
       0: bipush        35
       2: newarray       byte
       4: astore        6
       6: ldc           #2                  // String MD5
       8: invokestatic  #3                  // Method java/security/MessageDigest.getInstance:(Ljava/lang/String;)Ljava/security/MessageDigest;
      11: astore_3
      12: aload_3
      13: aload_1
      14: invokevirtual #4                  // Method java/security/MessageDigest.update:([B)V
      17: aload_3
      18: aload_0
      19: invokevirtual #4                  // Method java/security/MessageDigest.update:([B)V
      22: aload_3
      23: invokevirtual #5                  // Method java/security/MessageDigest.digest:()[B
      26: astore        4
      28: aload         4
      30: aload         6
      32: iconst_0
      33: invokestatic  #6                  // Method bytesToHex:([B[BI)V
      36: aload_3
      37: aload         6
      39: iconst_0
      40: bipush        32
      42: invokevirtual #7                  // Method java/security/MessageDigest.update:([BII)V
      45: aload_3
      46: aload_2
      47: invokevirtual #4                  // Method java/security/MessageDigest.update:([B)V
      50: aload_3
      51: invokevirtual #5                  // Method java/security/MessageDigest.digest:()[B
      54: astore        5
      56: aload         5
      58: aload         6
      60: iconst_3
      61: invokestatic  #6                  // Method bytesToHex:([B[BI)V
      64: aload         6
      66: iconst_0
      67: bipush        109
      69: bastore
      70: aload         6
      72: iconst_1
      73: bipush        100
      75: bastore
      76: aload         6
      78: iconst_2
      79: bipush        53
      81: bastore
      82: goto          87
      85: astore        7
      87: aload         6
      89: areturn
    Exception table:
       from    to  target type
           6    82    85   Class java/lang/Exception

  private static void bytesToHex(byte[], byte[], int);
    Code:
       0: bipush        16
       2: newarray       char
       4: dup
       5: iconst_0
       6: bipush        48
       8: castore
       9: dup
      10: iconst_1
      11: bipush        49
      13: castore
      14: dup
      15: iconst_2
      16: bipush        50
      18: castore
      19: dup
      20: iconst_3
      21: bipush        51
      23: castore
      24: dup
      25: iconst_4
      26: bipush        52
      28: castore
      29: dup
      30: iconst_5
      31: bipush        53
      33: castore
      34: dup
      35: bipush        6
      37: bipush        54
      39: castore
      40: dup
      41: bipush        7
      43: bipush        55
      45: castore
      46: dup
      47: bipush        8
      49: bipush        56
      51: castore
      52: dup
      53: bipush        9
      55: bipush        57
      57: castore
      58: dup
      59: bipush        10
      61: bipush        97
      63: castore
      64: dup
      65: bipush        11
      67: bipush        98
      69: castore
      70: dup
      71: bipush        12
      73: bipush        99
      75: castore
      76: dup
      77: bipush        13
      79: bipush        100
      81: castore
      82: dup
      83: bipush        14
      85: bipush        101
      87: castore
      88: dup
      89: bipush        15
      91: bipush        102
      93: castore
      94: astore_3
      95: iload_2
      96: istore        7
      98: iconst_0
      99: istore        4
     101: iload         4
     103: bipush        16
     105: if_icmpge     161
     108: aload_0
     109: iload         4
     111: baload
     112: sipush        255
     115: iand
     116: istore        5
     118: iload         5
     120: iconst_4
     121: ishr
     122: istore        6
     124: aload_1
     125: iload         7
     127: iinc          7, 1
     130: aload_3
     131: iload         6
     133: caload
     134: i2b
     135: bastore
     136: iload         5
     138: bipush        15
     140: iand
     141: istore        6
     143: aload_1
     144: iload         7
     146: iinc          7, 1
     149: aload_3
     150: iload         6
     152: caload
     153: i2b
     154: bastore
     155: iinc          4, 1
     158: goto          101
     161: return
}
