Compiled from "LettuceFactories.java"
public class io.lettuce.core.internal.LettuceFactories {
  private static final int ARRAY_QUEUE_THRESHOLD;

  public io.lettuce.core.internal.LettuceFactories();
    Code:
       0: aload_0
       1: invokespecial #1                  // Method java/lang/Object."<init>":()V
       4: return

  public static <T> java.util.Queue<T> newConcurrentQueue(int);
    Code:
       0: iload_0
       1: ldc           #3                  // int 2147483647
       3: if_icmpne     14
       6: new           #4                  // class java/util/concurrent/ConcurrentLinkedDeque
       9: dup
      10: invokespecial #5                  // Method java/util/concurrent/ConcurrentLinkedDeque."<init>":()V
      13: areturn
      14: iload_0
      15: getstatic     #6                  // Field ARRAY_QUEUE_THRESHOLD:I
      18: if_icmple     32
      21: new           #7                  // class java/util/concurrent/LinkedBlockingQueue
      24: dup
      25: iload_0
      26: invokespecial #8                  // Method java/util/concurrent/LinkedBlockingQueue."<init>":(I)V
      29: goto          40
      32: new           #9                  // class java/util/concurrent/ArrayBlockingQueue
      35: dup
      36: iload_0
      37: invokespecial #10                 // Method java/util/concurrent/ArrayBlockingQueue."<init>":(I)V
      40: areturn

  public static <T> java.util.Deque<T> newSpScQueue();
    Code:
       0: new           #11                 // class java/util/ArrayDeque
       3: dup
       4: invokespecial #12                 // Method java/util/ArrayDeque."<init>":()V
       7: areturn

  public static <T> java.util.concurrent.LinkedBlockingQueue<T> newBlockingQueue();
    Code:
       0: new           #7                  // class java/util/concurrent/LinkedBlockingQueue
       3: dup
       4: invokespecial #13                 // Method java/util/concurrent/LinkedBlockingQueue."<init>":()V
       7: areturn

  static {};
    Code:
       0: ldc           #14                 // String io.lettuce.core.LettuceFactories.array-queue-threshold
       2: ldc           #15                 // int 200000
       4: invokestatic  #16                 // Method java/lang/Integer.getInteger:(Ljava/lang/String;I)Ljava/lang/Integer;
       7: invokevirtual #17                 // Method java/lang/Integer.intValue:()I
      10: putstatic     #6                  // Field ARRAY_QUEUE_THRESHOLD:I
      13: return
}
