Compiled from "CreateTable.java"
public class cloud.agileframework.elasticsearch.proxy.create.model.CreateTable$CreateTableBuilder {
  private cloud.agileframework.elasticsearch.proxy.create.model.Mappings mappings;

  cloud.agileframework.elasticsearch.proxy.create.model.CreateTable$CreateTableBuilder();
    Code:
       0: aload_0
       1: invokespecial #1                  // Method java/lang/Object."<init>":()V
       4: return

  public cloud.agileframework.elasticsearch.proxy.create.model.CreateTable$CreateTableBuilder mappings(cloud.agileframework.elasticsearch.proxy.create.model.Mappings);
    Code:
       0: aload_0
       1: aload_1
       2: putfield      #2                  // Field mappings:Lcloud/agileframework/elasticsearch/proxy/create/model/Mappings;
       5: aload_0
       6: areturn

  public cloud.agileframework.elasticsearch.proxy.create.model.CreateTable build();
    Code:
       0: new           #3                  // class cloud/agileframework/elasticsearch/proxy/create/model/CreateTable
       3: dup
       4: aload_0
       5: getfield      #2                  // Field mappings:Lcloud/agileframework/elasticsearch/proxy/create/model/Mappings;
       8: invokespecial #4                  // Method cloud/agileframework/elasticsearch/proxy/create/model/CreateTable."<init>":(Lcloud/agileframework/elasticsearch/proxy/create/model/Mappings;)V
      11: areturn

  public java.lang.String toString();
    Code:
       0: new           #5                  // class java/lang/StringBuilder
       3: dup
       4: invokespecial #6                  // Method java/lang/StringBuilder."<init>":()V
       7: ldc           #7                  // String CreateTable.CreateTableBuilder(mappings=
       9: invokevirtual #8                  // Method java/lang/StringBuilder.append:(Ljava/lang/String;)Ljava/lang/StringBuilder;
      12: aload_0
      13: getfield      #2                  // Field mappings:Lcloud/agileframework/elasticsearch/proxy/create/model/Mappings;
      16: invokevirtual #9                  // Method java/lang/StringBuilder.append:(Ljava/lang/Object;)Ljava/lang/StringBuilder;
      19: ldc           #10                 // String )
      21: invokevirtual #8                  // Method java/lang/StringBuilder.append:(Ljava/lang/String;)Ljava/lang/StringBuilder;
      24: invokevirtual #11                 // Method java/lang/StringBuilder.toString:()Ljava/lang/String;
      27: areturn
}
