Compiled from "DOMStAXParserConfiguration.java"
final class org.apache.axiom.om.impl.dom.factory.DOMStAXParserConfiguration implements org.apache.axiom.om.util.StAXParserConfiguration {
  private final boolean coalescing;

  private final boolean expandEntityReferences;

  public org.apache.axiom.om.impl.dom.factory.DOMStAXParserConfiguration(boolean, boolean);
    Code:
       0: aload_0
       1: invokespecial #14                 // Method java/lang/Object."<init>":()V
       4: aload_0
       5: iload_1
       6: putfield      #17                 // Field coalescing:Z
       9: aload_0
      10: iload_2
      11: putfield      #19                 // Field expandEntityReferences:Z
      14: return

  public javax.xml.stream.XMLInputFactory configure(javax.xml.stream.XMLInputFactory, org.apache.axiom.util.stax.dialect.StAXDialect);
    Code:
       0: aload_0
       1: getfield      #17                 // Field coalescing:Z
       4: ifne          18
       7: getstatic     #27                 // Field org/apache/axiom/om/util/StAXParserConfiguration.PRESERVE_CDATA_SECTIONS:Lorg/apache/axiom/om/util/StAXParserConfiguration;
      10: aload_1
      11: aload_2
      12: invokeinterface #31,  3           // InterfaceMethod org/apache/axiom/om/util/StAXParserConfiguration.configure:(Ljavax/xml/stream/XMLInputFactory;Lorg/apache/axiom/util/stax/dialect/StAXDialect;)Ljavax/xml/stream/XMLInputFactory;
      17: astore_1
      18: aload_1
      19: ldc           #33                 // String javax.xml.stream.isReplacingEntityReferences
      21: aload_0
      22: getfield      #19                 // Field expandEntityReferences:Z
      25: invokestatic  #35                 // Method java/lang/Boolean.valueOf:(Z)Ljava/lang/Boolean;
      28: invokevirtual #41                 // Method javax/xml/stream/XMLInputFactory.setProperty:(Ljava/lang/String;Ljava/lang/Object;)V
      31: aload_1
      32: areturn

  public int hashCode();
    Code:
       0: aload_0
       1: getfield      #17                 // Field coalescing:Z
       4: ifeq          11
       7: iconst_1
       8: goto          12
      11: iconst_0
      12: aload_0
      13: getfield      #19                 // Field expandEntityReferences:Z
      16: ifeq          23
      19: iconst_2
      20: goto          24
      23: iconst_0
      24: ior
      25: ireturn

  public boolean equals(java.lang.Object);
    Code:
       0: aload_1
       1: aload_0
       2: if_acmpne     7
       5: iconst_1
       6: ireturn
       7: aload_1
       8: instanceof    #1                  // class org/apache/axiom/om/impl/dom/factory/DOMStAXParserConfiguration
      11: ifeq          45
      14: aload_1
      15: checkcast     #1                  // class org/apache/axiom/om/impl/dom/factory/DOMStAXParserConfiguration
      18: astore_2
      19: aload_2
      20: getfield      #17                 // Field coalescing:Z
      23: aload_0
      24: getfield      #17                 // Field coalescing:Z
      27: if_icmpne     43
      30: aload_2
      31: getfield      #19                 // Field expandEntityReferences:Z
      34: aload_0
      35: getfield      #19                 // Field expandEntityReferences:Z
      38: if_icmpne     43
      41: iconst_1
      42: ireturn
      43: iconst_0
      44: ireturn
      45: iconst_0
      46: ireturn

  public java.lang.String toString();
    Code:
       0: new           #60                 // class java/lang/StringBuilder
       3: dup
       4: ldc           #62                 // String DOM(coalescing=
       6: invokespecial #64                 // Method java/lang/StringBuilder."<init>":(Ljava/lang/String;)V
       9: aload_0
      10: getfield      #17                 // Field coalescing:Z
      13: invokevirtual #67                 // Method java/lang/StringBuilder.append:(Z)Ljava/lang/StringBuilder;
      16: ldc           #71                 // String ,expandEntityReferences=
      18: invokevirtual #73                 // Method java/lang/StringBuilder.append:(Ljava/lang/String;)Ljava/lang/StringBuilder;
      21: aload_0
      22: getfield      #19                 // Field expandEntityReferences:Z
      25: invokevirtual #67                 // Method java/lang/StringBuilder.append:(Z)Ljava/lang/StringBuilder;
      28: ldc           #76                 // String )
      30: invokevirtual #73                 // Method java/lang/StringBuilder.append:(Ljava/lang/String;)Ljava/lang/StringBuilder;
      33: invokevirtual #78                 // Method java/lang/StringBuilder.toString:()Ljava/lang/String;
      36: areturn
}
