Compiled from "FileInputFormat.java"
class org.apache.hadoop.mapred.FileInputFormat$NodeInfo {
  final org.apache.hadoop.net.Node node;

  final java.util.Set<java.lang.Integer> blockIds;

  final java.util.Set<org.apache.hadoop.mapred.FileInputFormat$NodeInfo> leaves;

  private long value;

  org.apache.hadoop.mapred.FileInputFormat$NodeInfo(org.apache.hadoop.net.Node);
    Code:
       0: aload_0
       1: invokespecial #1                  // Method java/lang/Object."<init>":()V
       4: aload_0
       5: aload_1
       6: putfield      #2                  // Field node:Lorg/apache/hadoop/net/Node;
       9: aload_0
      10: new           #3                  // class java/util/HashSet
      13: dup
      14: invokespecial #4                  // Method java/util/HashSet."<init>":()V
      17: putfield      #5                  // Field blockIds:Ljava/util/Set;
      20: aload_0
      21: new           #3                  // class java/util/HashSet
      24: dup
      25: invokespecial #4                  // Method java/util/HashSet."<init>":()V
      28: putfield      #6                  // Field leaves:Ljava/util/Set;
      31: return

  long getValue();
    Code:
       0: aload_0
       1: getfield      #7                  // Field value:J
       4: lreturn

  void addValue(int, long);
    Code:
       0: aload_0
       1: getfield      #5                  // Field blockIds:Ljava/util/Set;
       4: iload_1
       5: invokestatic  #8                  // Method java/lang/Integer.valueOf:(I)Ljava/lang/Integer;
       8: invokeinterface #9,  2            // InterfaceMethod java/util/Set.add:(Ljava/lang/Object;)Z
      13: iconst_1
      14: if_icmpne     27
      17: aload_0
      18: dup
      19: getfield      #7                  // Field value:J
      22: lload_2
      23: ladd
      24: putfield      #7                  // Field value:J
      27: return

  java.util.Set<org.apache.hadoop.mapred.FileInputFormat$NodeInfo> getLeaves();
    Code:
       0: aload_0
       1: getfield      #6                  // Field leaves:Ljava/util/Set;
       4: areturn

  void addLeaf(org.apache.hadoop.mapred.FileInputFormat$NodeInfo);
    Code:
       0: aload_0
       1: getfield      #6                  // Field leaves:Ljava/util/Set;
       4: aload_1
       5: invokeinterface #9,  2            // InterfaceMethod java/util/Set.add:(Ljava/lang/Object;)Z
      10: pop
      11: return
}
