Compiled from "MapOutputCollector.java"
public class org.apache.hadoop.mapred.MapOutputCollector$Context {
  private final org.apache.hadoop.mapred.MapTask mapTask;

  private final org.apache.hadoop.mapred.JobConf jobConf;

  private final org.apache.hadoop.mapred.Task$TaskReporter reporter;

  public org.apache.hadoop.mapred.MapOutputCollector$Context(org.apache.hadoop.mapred.MapTask, org.apache.hadoop.mapred.JobConf, org.apache.hadoop.mapred.Task$TaskReporter);
    Code:
       0: aload_0
       1: invokespecial #1                  // Method java/lang/Object."<init>":()V
       4: aload_0
       5: aload_1
       6: putfield      #2                  // Field mapTask:Lorg/apache/hadoop/mapred/MapTask;
       9: aload_0
      10: aload_2
      11: putfield      #3                  // Field jobConf:Lorg/apache/hadoop/mapred/JobConf;
      14: aload_0
      15: aload_3
      16: putfield      #4                  // Field reporter:Lorg/apache/hadoop/mapred/Task$TaskReporter;
      19: return

  public org.apache.hadoop.mapred.MapTask getMapTask();
    Code:
       0: aload_0
       1: getfield      #2                  // Field mapTask:Lorg/apache/hadoop/mapred/MapTask;
       4: areturn

  public org.apache.hadoop.mapred.JobConf getJobConf();
    Code:
       0: aload_0
       1: getfield      #3                  // Field jobConf:Lorg/apache/hadoop/mapred/JobConf;
       4: areturn

  public org.apache.hadoop.mapred.Task$TaskReporter getReporter();
    Code:
       0: aload_0
       1: getfield      #4                  // Field reporter:Lorg/apache/hadoop/mapred/Task$TaskReporter;
       4: areturn
}
