Compiled from "StatisticsCollector.java"
class org.apache.hadoop.mapred.StatisticsCollector$1 extends java.util.TimerTask {
  final org.apache.hadoop.mapred.StatisticsCollector this$0;

  org.apache.hadoop.mapred.StatisticsCollector$1(org.apache.hadoop.mapred.StatisticsCollector);
    Code:
       0: aload_0
       1: aload_1
       2: putfield      #1                  // Field this$0:Lorg/apache/hadoop/mapred/StatisticsCollector;
       5: aload_0
       6: invokespecial #2                  // Method java/util/TimerTask."<init>":()V
       9: return

  public void run();
    Code:
       0: aload_0
       1: getfield      #1                  // Field this$0:Lorg/apache/hadoop/mapred/StatisticsCollector;
       4: invokevirtual #3                  // Method org/apache/hadoop/mapred/StatisticsCollector.update:()V
       7: return
}
