Compiled from "Http2Connection.java"
public final class io.dekorate.deps.okhttp3.internal.http2.Http2Connection implements java.io.Closeable {
  static final int OKHTTP_CLIENT_WINDOW_SIZE;

  private static final java.util.concurrent.ExecutorService listenerExecutor;

  final boolean client;

  final io.dekorate.deps.okhttp3.internal.http2.Http2Connection$Listener listener;

  final java.util.Map<java.lang.Integer, io.dekorate.deps.okhttp3.internal.http2.Http2Stream> streams;

  final java.lang.String hostname;

  int lastGoodStreamId;

  int nextStreamId;

  boolean shutdown;

  private final java.util.concurrent.ScheduledExecutorService writerExecutor;

  private final java.util.concurrent.ExecutorService pushExecutor;

  final io.dekorate.deps.okhttp3.internal.http2.PushObserver pushObserver;

  private boolean awaitingPong;

  long unacknowledgedBytesRead;

  long bytesLeftInWriteWindow;

  io.dekorate.deps.okhttp3.internal.http2.Settings okHttpSettings;

  final io.dekorate.deps.okhttp3.internal.http2.Settings peerSettings;

  final java.net.Socket socket;

  final io.dekorate.deps.okhttp3.internal.http2.Http2Writer writer;

  final io.dekorate.deps.okhttp3.internal.http2.Http2Connection$ReaderRunnable readerRunnable;

  final java.util.Set<java.lang.Integer> currentPushRequests;

  static final boolean $assertionsDisabled;

  io.dekorate.deps.okhttp3.internal.http2.Http2Connection(io.dekorate.deps.okhttp3.internal.http2.Http2Connection$Builder);
    Code:
       0: aload_0
       1: invokespecial #75                 // Method java/lang/Object."<init>":()V
       4: aload_0
       5: new           #77                 // class java/util/LinkedHashMap
       8: dup
       9: invokespecial #78                 // Method java/util/LinkedHashMap."<init>":()V
      12: putfield      #80                 // Field streams:Ljava/util/Map;
      15: aload_0
      16: lconst_0
      17: putfield      #82                 // Field unacknowledgedBytesRead:J
      20: aload_0
      21: new           #84                 // class io/dekorate/deps/okhttp3/internal/http2/Settings
      24: dup
      25: invokespecial #85                 // Method io/dekorate/deps/okhttp3/internal/http2/Settings."<init>":()V
      28: putfield      #87                 // Field okHttpSettings:Lio/dekorate/deps/okhttp3/internal/http2/Settings;
      31: aload_0
      32: new           #84                 // class io/dekorate/deps/okhttp3/internal/http2/Settings
      35: dup
      36: invokespecial #85                 // Method io/dekorate/deps/okhttp3/internal/http2/Settings."<init>":()V
      39: putfield      #89                 // Field peerSettings:Lio/dekorate/deps/okhttp3/internal/http2/Settings;
      42: aload_0
      43: new           #91                 // class java/util/LinkedHashSet
      46: dup
      47: invokespecial #92                 // Method java/util/LinkedHashSet."<init>":()V
      50: putfield      #94                 // Field currentPushRequests:Ljava/util/Set;
      53: aload_0
      54: aload_1
      55: getfield      #96                 // Field io/dekorate/deps/okhttp3/internal/http2/Http2Connection$Builder.pushObserver:Lio/dekorate/deps/okhttp3/internal/http2/PushObserver;
      58: putfield      #97                 // Field pushObserver:Lio/dekorate/deps/okhttp3/internal/http2/PushObserver;
      61: aload_0
      62: aload_1
      63: getfield      #99                 // Field io/dekorate/deps/okhttp3/internal/http2/Http2Connection$Builder.client:Z
      66: putfield      #100                // Field client:Z
      69: aload_0
      70: aload_1
      71: getfield      #102                // Field io/dekorate/deps/okhttp3/internal/http2/Http2Connection$Builder.listener:Lio/dekorate/deps/okhttp3/internal/http2/Http2Connection$Listener;
      74: putfield      #103                // Field listener:Lio/dekorate/deps/okhttp3/internal/http2/Http2Connection$Listener;
      77: aload_0
      78: aload_1
      79: getfield      #99                 // Field io/dekorate/deps/okhttp3/internal/http2/Http2Connection$Builder.client:Z
      82: ifeq          89
      85: iconst_1
      86: goto          90
      89: iconst_2
      90: putfield      #105                // Field nextStreamId:I
      93: aload_1
      94: getfield      #99                 // Field io/dekorate/deps/okhttp3/internal/http2/Http2Connection$Builder.client:Z
      97: ifeq          110
     100: aload_0
     101: dup
     102: getfield      #105                // Field nextStreamId:I
     105: iconst_2
     106: iadd
     107: putfield      #105                // Field nextStreamId:I
     110: aload_1
     111: getfield      #99                 // Field io/dekorate/deps/okhttp3/internal/http2/Http2Connection$Builder.client:Z
     114: ifeq          129
     117: aload_0
     118: getfield      #87                 // Field okHttpSettings:Lio/dekorate/deps/okhttp3/internal/http2/Settings;
     121: bipush        7
     123: ldc           #34                 // int 16777216
     125: invokevirtual #109                // Method io/dekorate/deps/okhttp3/internal/http2/Settings.set:(II)Lio/dekorate/deps/okhttp3/internal/http2/Settings;
     128: pop
     129: aload_0
     130: aload_1
     131: getfield      #111                // Field io/dekorate/deps/okhttp3/internal/http2/Http2Connection$Builder.hostname:Ljava/lang/String;
     134: putfield      #112                // Field hostname:Ljava/lang/String;
     137: aload_0
     138: new           #114                // class java/util/concurrent/ScheduledThreadPoolExecutor
     141: dup
     142: iconst_1
     143: ldc           #116                // String OkHttp %s Writer
     145: iconst_1
     146: anewarray     #4                  // class java/lang/Object
     149: dup
     150: iconst_0
     151: aload_0
     152: getfield      #112                // Field hostname:Ljava/lang/String;
     155: aastore
     156: invokestatic  #122                // Method io/dekorate/deps/okhttp3/internal/Util.format:(Ljava/lang/String;[Ljava/lang/Object;)Ljava/lang/String;
     159: iconst_0
     160: invokestatic  #126                // Method io/dekorate/deps/okhttp3/internal/Util.threadFactory:(Ljava/lang/String;Z)Ljava/util/concurrent/ThreadFactory;
     163: invokespecial #129                // Method java/util/concurrent/ScheduledThreadPoolExecutor."<init>":(ILjava/util/concurrent/ThreadFactory;)V
     166: putfield      #131                // Field writerExecutor:Ljava/util/concurrent/ScheduledExecutorService;
     169: aload_1
     170: getfield      #134                // Field io/dekorate/deps/okhttp3/internal/http2/Http2Connection$Builder.pingIntervalMillis:I
     173: ifeq          210
     176: aload_0
     177: getfield      #131                // Field writerExecutor:Ljava/util/concurrent/ScheduledExecutorService;
     180: new           #18                 // class io/dekorate/deps/okhttp3/internal/http2/Http2Connection$PingRunnable
     183: dup
     184: aload_0
     185: iconst_0
     186: iconst_0
     187: iconst_0
     188: invokespecial #137                // Method io/dekorate/deps/okhttp3/internal/http2/Http2Connection$PingRunnable."<init>":(Lio/dekorate/deps/okhttp3/internal/http2/Http2Connection;ZII)V
     191: aload_1
     192: getfield      #134                // Field io/dekorate/deps/okhttp3/internal/http2/Http2Connection$Builder.pingIntervalMillis:I
     195: i2l
     196: aload_1
     197: getfield      #134                // Field io/dekorate/deps/okhttp3/internal/http2/Http2Connection$Builder.pingIntervalMillis:I
     200: i2l
     201: getstatic     #143                // Field java/util/concurrent/TimeUnit.MILLISECONDS:Ljava/util/concurrent/TimeUnit;
     204: invokeinterface #149,  7          // InterfaceMethod java/util/concurrent/ScheduledExecutorService.scheduleAtFixedRate:(Ljava/lang/Runnable;JJLjava/util/concurrent/TimeUnit;)Ljava/util/concurrent/ScheduledFuture;
     209: pop
     210: aload_0
     211: new           #151                // class java/util/concurrent/ThreadPoolExecutor
     214: dup
     215: iconst_0
     216: iconst_1
     217: ldc2_w        #152                // long 60l
     220: getstatic     #156                // Field java/util/concurrent/TimeUnit.SECONDS:Ljava/util/concurrent/TimeUnit;
     223: new           #158                // class java/util/concurrent/LinkedBlockingQueue
     226: dup
     227: invokespecial #159                // Method java/util/concurrent/LinkedBlockingQueue."<init>":()V
     230: ldc           #161                // String OkHttp %s Push Observer
     232: iconst_1
     233: anewarray     #4                  // class java/lang/Object
     236: dup
     237: iconst_0
     238: aload_0
     239: getfield      #112                // Field hostname:Ljava/lang/String;
     242: aastore
     243: invokestatic  #122                // Method io/dekorate/deps/okhttp3/internal/Util.format:(Ljava/lang/String;[Ljava/lang/Object;)Ljava/lang/String;
     246: iconst_1
     247: invokestatic  #126                // Method io/dekorate/deps/okhttp3/internal/Util.threadFactory:(Ljava/lang/String;Z)Ljava/util/concurrent/ThreadFactory;
     250: invokespecial #164                // Method java/util/concurrent/ThreadPoolExecutor."<init>":(IIJLjava/util/concurrent/TimeUnit;Ljava/util/concurrent/BlockingQueue;Ljava/util/concurrent/ThreadFactory;)V
     253: putfield      #166                // Field pushExecutor:Ljava/util/concurrent/ExecutorService;
     256: aload_0
     257: getfield      #89                 // Field peerSettings:Lio/dekorate/deps/okhttp3/internal/http2/Settings;
     260: bipush        7
     262: ldc           #167                // int 65535
     264: invokevirtual #109                // Method io/dekorate/deps/okhttp3/internal/http2/Settings.set:(II)Lio/dekorate/deps/okhttp3/internal/http2/Settings;
     267: pop
     268: aload_0
     269: getfield      #89                 // Field peerSettings:Lio/dekorate/deps/okhttp3/internal/http2/Settings;
     272: iconst_5
     273: sipush        16384
     276: invokevirtual #109                // Method io/dekorate/deps/okhttp3/internal/http2/Settings.set:(II)Lio/dekorate/deps/okhttp3/internal/http2/Settings;
     279: pop
     280: aload_0
     281: aload_0
     282: getfield      #89                 // Field peerSettings:Lio/dekorate/deps/okhttp3/internal/http2/Settings;
     285: invokevirtual #171                // Method io/dekorate/deps/okhttp3/internal/http2/Settings.getInitialWindowSize:()I
     288: i2l
     289: putfield      #173                // Field bytesLeftInWriteWindow:J
     292: aload_0
     293: aload_1
     294: getfield      #175                // Field io/dekorate/deps/okhttp3/internal/http2/Http2Connection$Builder.socket:Ljava/net/Socket;
     297: putfield      #176                // Field socket:Ljava/net/Socket;
     300: aload_0
     301: new           #178                // class io/dekorate/deps/okhttp3/internal/http2/Http2Writer
     304: dup
     305: aload_1
     306: getfield      #182                // Field io/dekorate/deps/okhttp3/internal/http2/Http2Connection$Builder.sink:Lio/dekorate/deps/okio/BufferedSink;
     309: aload_0
     310: getfield      #100                // Field client:Z
     313: invokespecial #185                // Method io/dekorate/deps/okhttp3/internal/http2/Http2Writer."<init>":(Lio/dekorate/deps/okio/BufferedSink;Z)V
     316: putfield      #187                // Field writer:Lio/dekorate/deps/okhttp3/internal/http2/Http2Writer;
     319: aload_0
     320: new           #12                 // class io/dekorate/deps/okhttp3/internal/http2/Http2Connection$ReaderRunnable
     323: dup
     324: aload_0
     325: new           #189                // class io/dekorate/deps/okhttp3/internal/http2/Http2Reader
     328: dup
     329: aload_1
     330: getfield      #193                // Field io/dekorate/deps/okhttp3/internal/http2/Http2Connection$Builder.source:Lio/dekorate/deps/okio/BufferedSource;
     333: aload_0
     334: getfield      #100                // Field client:Z
     337: invokespecial #196                // Method io/dekorate/deps/okhttp3/internal/http2/Http2Reader."<init>":(Lio/dekorate/deps/okio/BufferedSource;Z)V
     340: invokespecial #199                // Method io/dekorate/deps/okhttp3/internal/http2/Http2Connection$ReaderRunnable."<init>":(Lio/dekorate/deps/okhttp3/internal/http2/Http2Connection;Lio/dekorate/deps/okhttp3/internal/http2/Http2Reader;)V
     343: putfield      #201                // Field readerRunnable:Lio/dekorate/deps/okhttp3/internal/http2/Http2Connection$ReaderRunnable;
     346: return

  public io.dekorate.deps.okhttp3.Protocol getProtocol();
    Code:
       0: getstatic     #213                // Field io/dekorate/deps/okhttp3/Protocol.HTTP_2:Lio/dekorate/deps/okhttp3/Protocol;
       3: areturn

  public synchronized int openStreamCount();
    Code:
       0: aload_0
       1: getfield      #80                 // Field streams:Ljava/util/Map;
       4: invokeinterface #219,  1          // InterfaceMethod java/util/Map.size:()I
       9: ireturn

  synchronized io.dekorate.deps.okhttp3.internal.http2.Http2Stream getStream(int);
    Code:
       0: aload_0
       1: getfield      #80                 // Field streams:Ljava/util/Map;
       4: iload_1
       5: invokestatic  #227                // Method java/lang/Integer.valueOf:(I)Ljava/lang/Integer;
       8: invokeinterface #231,  2          // InterfaceMethod java/util/Map.get:(Ljava/lang/Object;)Ljava/lang/Object;
      13: checkcast     #233                // class io/dekorate/deps/okhttp3/internal/http2/Http2Stream
      16: areturn

  synchronized io.dekorate.deps.okhttp3.internal.http2.Http2Stream removeStream(int);
    Code:
       0: aload_0
       1: getfield      #80                 // Field streams:Ljava/util/Map;
       4: iload_1
       5: invokestatic  #227                // Method java/lang/Integer.valueOf:(I)Ljava/lang/Integer;
       8: invokeinterface #238,  2          // InterfaceMethod java/util/Map.remove:(Ljava/lang/Object;)Ljava/lang/Object;
      13: checkcast     #233                // class io/dekorate/deps/okhttp3/internal/http2/Http2Stream
      16: astore_2
      17: aload_0
      18: invokevirtual #241                // Method java/lang/Object.notifyAll:()V
      21: aload_2
      22: areturn

  public synchronized int maxConcurrentStreams();
    Code:
       0: aload_0
       1: getfield      #89                 // Field peerSettings:Lio/dekorate/deps/okhttp3/internal/http2/Settings;
       4: ldc           #246                // int 2147483647
       6: invokevirtual #250                // Method io/dekorate/deps/okhttp3/internal/http2/Settings.getMaxConcurrentStreams:(I)I
       9: ireturn

  synchronized void updateConnectionFlowControl(long);
    Code:
       0: aload_0
       1: dup
       2: getfield      #82                 // Field unacknowledgedBytesRead:J
       5: lload_1
       6: ladd
       7: putfield      #82                 // Field unacknowledgedBytesRead:J
      10: aload_0
      11: getfield      #82                 // Field unacknowledgedBytesRead:J
      14: aload_0
      15: getfield      #87                 // Field okHttpSettings:Lio/dekorate/deps/okhttp3/internal/http2/Settings;
      18: invokevirtual #171                // Method io/dekorate/deps/okhttp3/internal/http2/Settings.getInitialWindowSize:()I
      21: iconst_2
      22: idiv
      23: i2l
      24: lcmp
      25: iflt          42
      28: aload_0
      29: iconst_0
      30: aload_0
      31: getfield      #82                 // Field unacknowledgedBytesRead:J
      34: invokevirtual #256                // Method writeWindowUpdateLater:(IJ)V
      37: aload_0
      38: lconst_0
      39: putfield      #82                 // Field unacknowledgedBytesRead:J
      42: return

  public io.dekorate.deps.okhttp3.internal.http2.Http2Stream pushStream(int, java.util.List<io.dekorate.deps.okhttp3.internal.http2.Header>, boolean) throws java.io.IOException;
    Code:
       0: aload_0
       1: getfield      #100                // Field client:Z
       4: ifeq          18
       7: new           #264                // class java/lang/IllegalStateException
      10: dup
      11: ldc_w         #266                // String Client cannot push requests.
      14: invokespecial #269                // Method java/lang/IllegalStateException."<init>":(Ljava/lang/String;)V
      17: athrow
      18: aload_0
      19: iload_1
      20: aload_2
      21: iload_3
      22: invokespecial #272                // Method newStream:(ILjava/util/List;Z)Lio/dekorate/deps/okhttp3/internal/http2/Http2Stream;
      25: areturn

  public io.dekorate.deps.okhttp3.internal.http2.Http2Stream newStream(java.util.List<io.dekorate.deps.okhttp3.internal.http2.Header>, boolean) throws java.io.IOException;
    Code:
       0: aload_0
       1: iconst_0
       2: aload_1
       3: iload_2
       4: invokespecial #272                // Method newStream:(ILjava/util/List;Z)Lio/dekorate/deps/okhttp3/internal/http2/Http2Stream;
       7: areturn

  private io.dekorate.deps.okhttp3.internal.http2.Http2Stream newStream(int, java.util.List<io.dekorate.deps.okhttp3.internal.http2.Header>, boolean) throws java.io.IOException;
    Code:
       0: iload_3
       1: ifne          8
       4: iconst_1
       5: goto          9
       8: iconst_0
       9: istore        4
      11: iconst_0
      12: istore        5
      14: aload_0
      15: getfield      #187                // Field writer:Lio/dekorate/deps/okhttp3/internal/http2/Http2Writer;
      18: dup
      19: astore        9
      21: monitorenter
      22: aload_0
      23: dup
      24: astore        10
      26: monitorenter
      27: aload_0
      28: getfield      #105                // Field nextStreamId:I
      31: ldc_w         #280                // int 1073741823
      34: if_icmple     44
      37: aload_0
      38: getstatic     #286                // Field io/dekorate/deps/okhttp3/internal/http2/ErrorCode.REFUSED_STREAM:Lio/dekorate/deps/okhttp3/internal/http2/ErrorCode;
      41: invokevirtual #289                // Method shutdown:(Lio/dekorate/deps/okhttp3/internal/http2/ErrorCode;)V
      44: aload_0
      45: getfield      #293                // Field shutdown:Z
      48: ifeq          59
      51: new           #295                // class io/dekorate/deps/okhttp3/internal/http2/ConnectionShutdownException
      54: dup
      55: invokespecial #296                // Method io/dekorate/deps/okhttp3/internal/http2/ConnectionShutdownException."<init>":()V
      58: athrow
      59: aload_0
      60: getfield      #105                // Field nextStreamId:I
      63: istore        8
      65: aload_0
      66: dup
      67: getfield      #105                // Field nextStreamId:I
      70: iconst_2
      71: iadd
      72: putfield      #105                // Field nextStreamId:I
      75: new           #233                // class io/dekorate/deps/okhttp3/internal/http2/Http2Stream
      78: dup
      79: iload         8
      81: aload_0
      82: iload         4
      84: iload         5
      86: aconst_null
      87: invokespecial #299                // Method io/dekorate/deps/okhttp3/internal/http2/Http2Stream."<init>":(ILio/dekorate/deps/okhttp3/internal/http2/Http2Connection;ZZLio/dekorate/deps/okhttp3/Headers;)V
      90: astore        7
      92: iload_3
      93: ifeq          115
      96: aload_0
      97: getfield      #173                // Field bytesLeftInWriteWindow:J
     100: lconst_0
     101: lcmp
     102: ifeq          115
     105: aload         7
     107: getfield      #300                // Field io/dekorate/deps/okhttp3/internal/http2/Http2Stream.bytesLeftInWriteWindow:J
     110: lconst_0
     111: lcmp
     112: ifne          119
     115: iconst_1
     116: goto          120
     119: iconst_0
     120: istore        6
     122: aload         7
     124: invokevirtual #304                // Method io/dekorate/deps/okhttp3/internal/http2/Http2Stream.isOpen:()Z
     127: ifeq          147
     130: aload_0
     131: getfield      #80                 // Field streams:Ljava/util/Map;
     134: iload         8
     136: invokestatic  #227                // Method java/lang/Integer.valueOf:(I)Ljava/lang/Integer;
     139: aload         7
     141: invokeinterface #308,  3          // InterfaceMethod java/util/Map.put:(Ljava/lang/Object;Ljava/lang/Object;)Ljava/lang/Object;
     146: pop
     147: aload         10
     149: monitorexit
     150: goto          161
     153: astore        11
     155: aload         10
     157: monitorexit
     158: aload         11
     160: athrow
     161: iload_1
     162: ifne          181
     165: aload_0
     166: getfield      #187                // Field writer:Lio/dekorate/deps/okhttp3/internal/http2/Http2Writer;
     169: iload         4
     171: iload         8
     173: iload_1
     174: aload_2
     175: invokevirtual #314                // Method io/dekorate/deps/okhttp3/internal/http2/Http2Writer.synStream:(ZIILjava/util/List;)V
     178: goto          210
     181: aload_0
     182: getfield      #100                // Field client:Z
     185: ifeq          199
     188: new           #316                // class java/lang/IllegalArgumentException
     191: dup
     192: ldc_w         #318                // String client streams shouldn\'t have associated stream IDs
     195: invokespecial #319                // Method java/lang/IllegalArgumentException."<init>":(Ljava/lang/String;)V
     198: athrow
     199: aload_0
     200: getfield      #187                // Field writer:Lio/dekorate/deps/okhttp3/internal/http2/Http2Writer;
     203: iload_1
     204: iload         8
     206: aload_2
     207: invokevirtual #323                // Method io/dekorate/deps/okhttp3/internal/http2/Http2Writer.pushPromise:(IILjava/util/List;)V
     210: aload         9
     212: monitorexit
     213: goto          224
     216: astore        12
     218: aload         9
     220: monitorexit
     221: aload         12
     223: athrow
     224: iload         6
     226: ifeq          236
     229: aload_0
     230: getfield      #187                // Field writer:Lio/dekorate/deps/okhttp3/internal/http2/Http2Writer;
     233: invokevirtual #326                // Method io/dekorate/deps/okhttp3/internal/http2/Http2Writer.flush:()V
     236: aload         7
     238: areturn
    Exception table:
       from    to  target type
          27   150   153   any
         153   158   153   any
          22   213   216   any
         216   221   216   any

  void writeSynReply(int, boolean, java.util.List<io.dekorate.deps.okhttp3.internal.http2.Header>) throws java.io.IOException;
    Code:
       0: aload_0
       1: getfield      #187                // Field writer:Lio/dekorate/deps/okhttp3/internal/http2/Http2Writer;
       4: iload_2
       5: iload_1
       6: aload_3
       7: invokevirtual #336                // Method io/dekorate/deps/okhttp3/internal/http2/Http2Writer.synReply:(ZILjava/util/List;)V
      10: return

  public void writeData(int, boolean, io.dekorate.deps.okio.Buffer, long) throws java.io.IOException;
    Code:
       0: lload         4
       2: lconst_0
       3: lcmp
       4: ifne          19
       7: aload_0
       8: getfield      #187                // Field writer:Lio/dekorate/deps/okhttp3/internal/http2/Http2Writer;
      11: iload_2
      12: iload_1
      13: aload_3
      14: iconst_0
      15: invokevirtual #345                // Method io/dekorate/deps/okhttp3/internal/http2/Http2Writer.data:(ZILio/dekorate/deps/okio/Buffer;I)V
      18: return
      19: lload         4
      21: lconst_0
      22: lcmp
      23: ifle          183
      26: aload_0
      27: dup
      28: astore        7
      30: monitorenter
      31: aload_0
      32: getfield      #173                // Field bytesLeftInWriteWindow:J
      35: lconst_0
      36: lcmp
      37: ifgt          74
      40: aload_0
      41: getfield      #80                 // Field streams:Ljava/util/Map;
      44: iload_1
      45: invokestatic  #227                // Method java/lang/Integer.valueOf:(I)Ljava/lang/Integer;
      48: invokeinterface #349,  2          // InterfaceMethod java/util/Map.containsKey:(Ljava/lang/Object;)Z
      53: ifne          67
      56: new           #262                // class java/io/IOException
      59: dup
      60: ldc_w         #351                // String stream closed
      63: invokespecial #352                // Method java/io/IOException."<init>":(Ljava/lang/String;)V
      66: athrow
      67: aload_0
      68: invokevirtual #355                // Method java/lang/Object.wait:()V
      71: goto          31
      74: goto          93
      77: astore        8
      79: invokestatic  #361                // Method java/lang/Thread.currentThread:()Ljava/lang/Thread;
      82: invokevirtual #364                // Method java/lang/Thread.interrupt:()V
      85: new           #366                // class java/io/InterruptedIOException
      88: dup
      89: invokespecial #367                // Method java/io/InterruptedIOException."<init>":()V
      92: athrow
      93: lload         4
      95: aload_0
      96: getfield      #173                // Field bytesLeftInWriteWindow:J
      99: invokestatic  #373                // Method java/lang/Math.min:(JJ)J
     102: l2i
     103: istore        6
     105: iload         6
     107: aload_0
     108: getfield      #187                // Field writer:Lio/dekorate/deps/okhttp3/internal/http2/Http2Writer;
     111: invokevirtual #376                // Method io/dekorate/deps/okhttp3/internal/http2/Http2Writer.maxDataLength:()I
     114: invokestatic  #379                // Method java/lang/Math.min:(II)I
     117: istore        6
     119: aload_0
     120: dup
     121: getfield      #173                // Field bytesLeftInWriteWindow:J
     124: iload         6
     126: i2l
     127: lsub
     128: putfield      #173                // Field bytesLeftInWriteWindow:J
     131: aload         7
     133: monitorexit
     134: goto          145
     137: astore        9
     139: aload         7
     141: monitorexit
     142: aload         9
     144: athrow
     145: lload         4
     147: iload         6
     149: i2l
     150: lsub
     151: lstore        4
     153: aload_0
     154: getfield      #187                // Field writer:Lio/dekorate/deps/okhttp3/internal/http2/Http2Writer;
     157: iload_2
     158: ifeq          172
     161: lload         4
     163: lconst_0
     164: lcmp
     165: ifne          172
     168: iconst_1
     169: goto          173
     172: iconst_0
     173: iload_1
     174: aload_3
     175: iload         6
     177: invokevirtual #345                // Method io/dekorate/deps/okhttp3/internal/http2/Http2Writer.data:(ZILio/dekorate/deps/okio/Buffer;I)V
     180: goto          19
     183: return
    Exception table:
       from    to  target type
          31    74    77   Class java/lang/InterruptedException
          31   134   137   any
         137   142   137   any

  void writeSynResetLater(int, io.dekorate.deps.okhttp3.internal.http2.ErrorCode);
    Code:
       0: aload_0
       1: getfield      #131                // Field writerExecutor:Ljava/util/concurrent/ScheduledExecutorService;
       4: new           #31                 // class io/dekorate/deps/okhttp3/internal/http2/Http2Connection$1
       7: dup
       8: aload_0
       9: ldc_w         #393                // String OkHttp %s stream %d
      12: iconst_2
      13: anewarray     #4                  // class java/lang/Object
      16: dup
      17: iconst_0
      18: aload_0
      19: getfield      #112                // Field hostname:Ljava/lang/String;
      22: aastore
      23: dup
      24: iconst_1
      25: iload_1
      26: invokestatic  #227                // Method java/lang/Integer.valueOf:(I)Ljava/lang/Integer;
      29: aastore
      30: iload_1
      31: aload_2
      32: invokespecial #396                // Method io/dekorate/deps/okhttp3/internal/http2/Http2Connection$1."<init>":(Lio/dekorate/deps/okhttp3/internal/http2/Http2Connection;Ljava/lang/String;[Ljava/lang/Object;ILio/dekorate/deps/okhttp3/internal/http2/ErrorCode;)V
      35: invokeinterface #400,  2          // InterfaceMethod java/util/concurrent/ScheduledExecutorService.execute:(Ljava/lang/Runnable;)V
      40: goto          44
      43: astore_3
      44: return
    Exception table:
       from    to  target type
           0    40    43   Class java/util/concurrent/RejectedExecutionException

  void writeSynReset(int, io.dekorate.deps.okhttp3.internal.http2.ErrorCode) throws java.io.IOException;
    Code:
       0: aload_0
       1: getfield      #187                // Field writer:Lio/dekorate/deps/okhttp3/internal/http2/Http2Writer;
       4: iload_1
       5: aload_2
       6: invokevirtual #405                // Method io/dekorate/deps/okhttp3/internal/http2/Http2Writer.rstStream:(ILio/dekorate/deps/okhttp3/internal/http2/ErrorCode;)V
       9: return

  void writeWindowUpdateLater(int, long);
    Code:
       0: aload_0
       1: getfield      #131                // Field writerExecutor:Ljava/util/concurrent/ScheduledExecutorService;
       4: new           #29                 // class io/dekorate/deps/okhttp3/internal/http2/Http2Connection$2
       7: dup
       8: aload_0
       9: ldc_w         #408                // String OkHttp Window Update %s stream %d
      12: iconst_2
      13: anewarray     #4                  // class java/lang/Object
      16: dup
      17: iconst_0
      18: aload_0
      19: getfield      #112                // Field hostname:Ljava/lang/String;
      22: aastore
      23: dup
      24: iconst_1
      25: iload_1
      26: invokestatic  #227                // Method java/lang/Integer.valueOf:(I)Ljava/lang/Integer;
      29: aastore
      30: iload_1
      31: lload_2
      32: invokespecial #411                // Method io/dekorate/deps/okhttp3/internal/http2/Http2Connection$2."<init>":(Lio/dekorate/deps/okhttp3/internal/http2/Http2Connection;Ljava/lang/String;[Ljava/lang/Object;IJ)V
      35: invokeinterface #400,  2          // InterfaceMethod java/util/concurrent/ScheduledExecutorService.execute:(Ljava/lang/Runnable;)V
      40: goto          45
      43: astore        4
      45: return
    Exception table:
       from    to  target type
           0    40    43   Class java/util/concurrent/RejectedExecutionException

  void writePing(boolean, int, int);
    Code:
       0: iload_1
       1: ifne          44
       4: aload_0
       5: dup
       6: astore        5
       8: monitorenter
       9: aload_0
      10: getfield      #415                // Field awaitingPong:Z
      13: istore        4
      15: aload_0
      16: iconst_1
      17: putfield      #415                // Field awaitingPong:Z
      20: aload         5
      22: monitorexit
      23: goto          34
      26: astore        6
      28: aload         5
      30: monitorexit
      31: aload         6
      33: athrow
      34: iload         4
      36: ifeq          44
      39: aload_0
      40: invokespecial #418                // Method failConnection:()V
      43: return
      44: aload_0
      45: getfield      #187                // Field writer:Lio/dekorate/deps/okhttp3/internal/http2/Http2Writer;
      48: iload_1
      49: iload_2
      50: iload_3
      51: invokevirtual #421                // Method io/dekorate/deps/okhttp3/internal/http2/Http2Writer.ping:(ZII)V
      54: goto          63
      57: astore        4
      59: aload_0
      60: invokespecial #418                // Method failConnection:()V
      63: return
    Exception table:
       from    to  target type
           9    23    26   any
          26    31    26   any
          44    54    57   Class java/io/IOException

  void writePingAndAwaitPong() throws java.lang.InterruptedException;
    Code:
       0: aload_0
       1: iconst_0
       2: ldc_w         #428                // int 1330343787
       5: ldc_w         #429                // int -257978967
       8: invokevirtual #431                // Method writePing:(ZII)V
      11: aload_0
      12: invokevirtual #434                // Method awaitPong:()V
      15: return

  synchronized void awaitPong() throws java.lang.InterruptedException;
    Code:
       0: aload_0
       1: getfield      #415                // Field awaitingPong:Z
       4: ifeq          14
       7: aload_0
       8: invokevirtual #355                // Method java/lang/Object.wait:()V
      11: goto          0
      14: return

  public void flush() throws java.io.IOException;
    Code:
       0: aload_0
       1: getfield      #187                // Field writer:Lio/dekorate/deps/okhttp3/internal/http2/Http2Writer;
       4: invokevirtual #326                // Method io/dekorate/deps/okhttp3/internal/http2/Http2Writer.flush:()V
       7: return

  public void shutdown(io.dekorate.deps.okhttp3.internal.http2.ErrorCode) throws java.io.IOException;
    Code:
       0: aload_0
       1: getfield      #187                // Field writer:Lio/dekorate/deps/okhttp3/internal/http2/Http2Writer;
       4: dup
       5: astore_2
       6: monitorenter
       7: aload_0
       8: dup
       9: astore        4
      11: monitorenter
      12: aload_0
      13: getfield      #293                // Field shutdown:Z
      16: ifeq          25
      19: aload         4
      21: monitorexit
      22: aload_2
      23: monitorexit
      24: return
      25: aload_0
      26: iconst_1
      27: putfield      #293                // Field shutdown:Z
      30: aload_0
      31: getfield      #436                // Field lastGoodStreamId:I
      34: istore_3
      35: aload         4
      37: monitorexit
      38: goto          49
      41: astore        5
      43: aload         4
      45: monitorexit
      46: aload         5
      48: athrow
      49: aload_0
      50: getfield      #187                // Field writer:Lio/dekorate/deps/okhttp3/internal/http2/Http2Writer;
      53: iload_3
      54: aload_1
      55: getstatic     #440                // Field io/dekorate/deps/okhttp3/internal/Util.EMPTY_BYTE_ARRAY:[B
      58: invokevirtual #444                // Method io/dekorate/deps/okhttp3/internal/http2/Http2Writer.goAway:(ILio/dekorate/deps/okhttp3/internal/http2/ErrorCode;[B)V
      61: aload_2
      62: monitorexit
      63: goto          73
      66: astore        6
      68: aload_2
      69: monitorexit
      70: aload         6
      72: athrow
      73: return
    Exception table:
       from    to  target type
          12    22    41   any
          25    38    41   any
          41    46    41   any
           7    24    66   any
          25    63    66   any
          66    70    66   any

  public void close() throws java.io.IOException;
    Code:
       0: aload_0
       1: getstatic     #448                // Field io/dekorate/deps/okhttp3/internal/http2/ErrorCode.NO_ERROR:Lio/dekorate/deps/okhttp3/internal/http2/ErrorCode;
       4: getstatic     #451                // Field io/dekorate/deps/okhttp3/internal/http2/ErrorCode.CANCEL:Lio/dekorate/deps/okhttp3/internal/http2/ErrorCode;
       7: invokevirtual #454                // Method close:(Lio/dekorate/deps/okhttp3/internal/http2/ErrorCode;Lio/dekorate/deps/okhttp3/internal/http2/ErrorCode;)V
      10: return

  void close(io.dekorate.deps.okhttp3.internal.http2.ErrorCode, io.dekorate.deps.okhttp3.internal.http2.ErrorCode) throws java.io.IOException;
    Code:
       0: getstatic     #456                // Field $assertionsDisabled:Z
       3: ifne          21
       6: aload_0
       7: invokestatic  #459                // Method java/lang/Thread.holdsLock:(Ljava/lang/Object;)Z
      10: ifeq          21
      13: new           #461                // class java/lang/AssertionError
      16: dup
      17: invokespecial #462                // Method java/lang/AssertionError."<init>":()V
      20: athrow
      21: aconst_null
      22: astore_3
      23: aload_0
      24: aload_1
      25: invokevirtual #289                // Method shutdown:(Lio/dekorate/deps/okhttp3/internal/http2/ErrorCode;)V
      28: goto          36
      31: astore        4
      33: aload         4
      35: astore_3
      36: aconst_null
      37: astore        4
      39: aload_0
      40: dup
      41: astore        5
      43: monitorenter
      44: aload_0
      45: getfield      #80                 // Field streams:Ljava/util/Map;
      48: invokeinterface #465,  1          // InterfaceMethod java/util/Map.isEmpty:()Z
      53: ifne          96
      56: aload_0
      57: getfield      #80                 // Field streams:Ljava/util/Map;
      60: invokeinterface #469,  1          // InterfaceMethod java/util/Map.values:()Ljava/util/Collection;
      65: aload_0
      66: getfield      #80                 // Field streams:Ljava/util/Map;
      69: invokeinterface #219,  1          // InterfaceMethod java/util/Map.size:()I
      74: anewarray     #233                // class io/dekorate/deps/okhttp3/internal/http2/Http2Stream
      77: invokeinterface #475,  2          // InterfaceMethod java/util/Collection.toArray:([Ljava/lang/Object;)[Ljava/lang/Object;
      82: checkcast     #477                // class "[Lio/dekorate/deps/okhttp3/internal/http2/Http2Stream;"
      85: astore        4
      87: aload_0
      88: getfield      #80                 // Field streams:Ljava/util/Map;
      91: invokeinterface #480,  1          // InterfaceMethod java/util/Map.clear:()V
      96: aload         5
      98: monitorexit
      99: goto          110
     102: astore        6
     104: aload         5
     106: monitorexit
     107: aload         6
     109: athrow
     110: aload         4
     112: ifnull        165
     115: aload         4
     117: astore        5
     119: aload         5
     121: arraylength
     122: istore        6
     124: iconst_0
     125: istore        7
     127: iload         7
     129: iload         6
     131: if_icmpge     165
     134: aload         5
     136: iload         7
     138: aaload
     139: astore        8
     141: aload         8
     143: aload_2
     144: invokevirtual #482                // Method io/dekorate/deps/okhttp3/internal/http2/Http2Stream.close:(Lio/dekorate/deps/okhttp3/internal/http2/ErrorCode;)V
     147: goto          159
     150: astore        9
     152: aload_3
     153: ifnull        159
     156: aload         9
     158: astore_3
     159: iinc          7, 1
     162: goto          127
     165: aload_0
     166: getfield      #187                // Field writer:Lio/dekorate/deps/okhttp3/internal/http2/Http2Writer;
     169: invokevirtual #484                // Method io/dekorate/deps/okhttp3/internal/http2/Http2Writer.close:()V
     172: goto          184
     175: astore        5
     177: aload_3
     178: ifnonnull     184
     181: aload         5
     183: astore_3
     184: aload_0
     185: getfield      #176                // Field socket:Ljava/net/Socket;
     188: invokevirtual #487                // Method java/net/Socket.close:()V
     191: goto          199
     194: astore        5
     196: aload         5
     198: astore_3
     199: aload_0
     200: getfield      #131                // Field writerExecutor:Ljava/util/concurrent/ScheduledExecutorService;
     203: invokeinterface #489,  1          // InterfaceMethod java/util/concurrent/ScheduledExecutorService.shutdown:()V
     208: aload_0
     209: getfield      #166                // Field pushExecutor:Ljava/util/concurrent/ExecutorService;
     212: invokeinterface #492,  1          // InterfaceMethod java/util/concurrent/ExecutorService.shutdown:()V
     217: aload_3
     218: ifnull        223
     221: aload_3
     222: athrow
     223: return
    Exception table:
       from    to  target type
          23    28    31   Class java/io/IOException
          44    99   102   any
         102   107   102   any
         141   147   150   Class java/io/IOException
         165   172   175   Class java/io/IOException
         184   191   194   Class java/io/IOException

  private void failConnection();
    Code:
       0: aload_0
       1: getstatic     #499                // Field io/dekorate/deps/okhttp3/internal/http2/ErrorCode.PROTOCOL_ERROR:Lio/dekorate/deps/okhttp3/internal/http2/ErrorCode;
       4: getstatic     #499                // Field io/dekorate/deps/okhttp3/internal/http2/ErrorCode.PROTOCOL_ERROR:Lio/dekorate/deps/okhttp3/internal/http2/ErrorCode;
       7: invokevirtual #454                // Method close:(Lio/dekorate/deps/okhttp3/internal/http2/ErrorCode;Lio/dekorate/deps/okhttp3/internal/http2/ErrorCode;)V
      10: goto          14
      13: astore_1
      14: return
    Exception table:
       from    to  target type
           0    10    13   Class java/io/IOException

  public void start() throws java.io.IOException;
    Code:
       0: aload_0
       1: iconst_1
       2: invokevirtual #503                // Method start:(Z)V
       5: return

  void start(boolean) throws java.io.IOException;
    Code:
       0: iload_1
       1: ifeq          49
       4: aload_0
       5: getfield      #187                // Field writer:Lio/dekorate/deps/okhttp3/internal/http2/Http2Writer;
       8: invokevirtual #506                // Method io/dekorate/deps/okhttp3/internal/http2/Http2Writer.connectionPreface:()V
      11: aload_0
      12: getfield      #187                // Field writer:Lio/dekorate/deps/okhttp3/internal/http2/Http2Writer;
      15: aload_0
      16: getfield      #87                 // Field okHttpSettings:Lio/dekorate/deps/okhttp3/internal/http2/Settings;
      19: invokevirtual #510                // Method io/dekorate/deps/okhttp3/internal/http2/Http2Writer.settings:(Lio/dekorate/deps/okhttp3/internal/http2/Settings;)V
      22: aload_0
      23: getfield      #87                 // Field okHttpSettings:Lio/dekorate/deps/okhttp3/internal/http2/Settings;
      26: invokevirtual #171                // Method io/dekorate/deps/okhttp3/internal/http2/Settings.getInitialWindowSize:()I
      29: istore_2
      30: iload_2
      31: ldc           #167                // int 65535
      33: if_icmpeq     49
      36: aload_0
      37: getfield      #187                // Field writer:Lio/dekorate/deps/okhttp3/internal/http2/Http2Writer;
      40: iconst_0
      41: iload_2
      42: ldc           #167                // int 65535
      44: isub
      45: i2l
      46: invokevirtual #513                // Method io/dekorate/deps/okhttp3/internal/http2/Http2Writer.windowUpdate:(IJ)V
      49: new           #357                // class java/lang/Thread
      52: dup
      53: aload_0
      54: getfield      #201                // Field readerRunnable:Lio/dekorate/deps/okhttp3/internal/http2/Http2Connection$ReaderRunnable;
      57: invokespecial #515                // Method java/lang/Thread."<init>":(Ljava/lang/Runnable;)V
      60: invokevirtual #517                // Method java/lang/Thread.start:()V
      63: return

  public void setSettings(io.dekorate.deps.okhttp3.internal.http2.Settings) throws java.io.IOException;
    Code:
       0: aload_0
       1: getfield      #187                // Field writer:Lio/dekorate/deps/okhttp3/internal/http2/Http2Writer;
       4: dup
       5: astore_2
       6: monitorenter
       7: aload_0
       8: dup
       9: astore_3
      10: monitorenter
      11: aload_0
      12: getfield      #293                // Field shutdown:Z
      15: ifeq          26
      18: new           #295                // class io/dekorate/deps/okhttp3/internal/http2/ConnectionShutdownException
      21: dup
      22: invokespecial #296                // Method io/dekorate/deps/okhttp3/internal/http2/ConnectionShutdownException."<init>":()V
      25: athrow
      26: aload_0
      27: getfield      #87                 // Field okHttpSettings:Lio/dekorate/deps/okhttp3/internal/http2/Settings;
      30: aload_1
      31: invokevirtual #523                // Method io/dekorate/deps/okhttp3/internal/http2/Settings.merge:(Lio/dekorate/deps/okhttp3/internal/http2/Settings;)V
      34: aload_3
      35: monitorexit
      36: goto          46
      39: astore        4
      41: aload_3
      42: monitorexit
      43: aload         4
      45: athrow
      46: aload_0
      47: getfield      #187                // Field writer:Lio/dekorate/deps/okhttp3/internal/http2/Http2Writer;
      50: aload_1
      51: invokevirtual #510                // Method io/dekorate/deps/okhttp3/internal/http2/Http2Writer.settings:(Lio/dekorate/deps/okhttp3/internal/http2/Settings;)V
      54: aload_2
      55: monitorexit
      56: goto          66
      59: astore        5
      61: aload_2
      62: monitorexit
      63: aload         5
      65: athrow
      66: return
    Exception table:
       from    to  target type
          11    36    39   any
          39    43    39   any
           7    56    59   any
          59    63    59   any

  public synchronized boolean isShutdown();
    Code:
       0: aload_0
       1: getfield      #293                // Field shutdown:Z
       4: ireturn

  boolean pushedStream(int);
    Code:
       0: iload_1
       1: ifeq          14
       4: iload_1
       5: iconst_1
       6: iand
       7: ifne          14
      10: iconst_1
      11: goto          15
      14: iconst_0
      15: ireturn

  void pushRequestLater(int, java.util.List<io.dekorate.deps.okhttp3.internal.http2.Header>);
    Code:
       0: aload_0
       1: dup
       2: astore_3
       3: monitorenter
       4: aload_0
       5: getfield      #94                 // Field currentPushRequests:Ljava/util/Set;
       8: iload_1
       9: invokestatic  #227                // Method java/lang/Integer.valueOf:(I)Ljava/lang/Integer;
      12: invokeinterface #534,  2          // InterfaceMethod java/util/Set.contains:(Ljava/lang/Object;)Z
      17: ifeq          31
      20: aload_0
      21: iload_1
      22: getstatic     #499                // Field io/dekorate/deps/okhttp3/internal/http2/ErrorCode.PROTOCOL_ERROR:Lio/dekorate/deps/okhttp3/internal/http2/ErrorCode;
      25: invokevirtual #536                // Method writeSynResetLater:(ILio/dekorate/deps/okhttp3/internal/http2/ErrorCode;)V
      28: aload_3
      29: monitorexit
      30: return
      31: aload_0
      32: getfield      #94                 // Field currentPushRequests:Ljava/util/Set;
      35: iload_1
      36: invokestatic  #227                // Method java/lang/Integer.valueOf:(I)Ljava/lang/Integer;
      39: invokeinterface #539,  2          // InterfaceMethod java/util/Set.add:(Ljava/lang/Object;)Z
      44: pop
      45: aload_3
      46: monitorexit
      47: goto          57
      50: astore        4
      52: aload_3
      53: monitorexit
      54: aload         4
      56: athrow
      57: aload_0
      58: new           #27                 // class io/dekorate/deps/okhttp3/internal/http2/Http2Connection$3
      61: dup
      62: aload_0
      63: ldc_w         #541                // String OkHttp %s Push Request[%s]
      66: iconst_2
      67: anewarray     #4                  // class java/lang/Object
      70: dup
      71: iconst_0
      72: aload_0
      73: getfield      #112                // Field hostname:Ljava/lang/String;
      76: aastore
      77: dup
      78: iconst_1
      79: iload_1
      80: invokestatic  #227                // Method java/lang/Integer.valueOf:(I)Ljava/lang/Integer;
      83: aastore
      84: iload_1
      85: aload_2
      86: invokespecial #544                // Method io/dekorate/deps/okhttp3/internal/http2/Http2Connection$3."<init>":(Lio/dekorate/deps/okhttp3/internal/http2/Http2Connection;Ljava/lang/String;[Ljava/lang/Object;ILjava/util/List;)V
      89: invokespecial #548                // Method pushExecutorExecute:(Lio/dekorate/deps/okhttp3/internal/NamedRunnable;)V
      92: goto          96
      95: astore_3
      96: return
    Exception table:
       from    to  target type
           4    30    50   any
          31    47    50   any
          50    54    50   any
          57    92    95   Class java/util/concurrent/RejectedExecutionException

  void pushHeadersLater(int, java.util.List<io.dekorate.deps.okhttp3.internal.http2.Header>, boolean);
    Code:
       0: aload_0
       1: new           #25                 // class io/dekorate/deps/okhttp3/internal/http2/Http2Connection$4
       4: dup
       5: aload_0
       6: ldc_w         #553                // String OkHttp %s Push Headers[%s]
       9: iconst_2
      10: anewarray     #4                  // class java/lang/Object
      13: dup
      14: iconst_0
      15: aload_0
      16: getfield      #112                // Field hostname:Ljava/lang/String;
      19: aastore
      20: dup
      21: iconst_1
      22: iload_1
      23: invokestatic  #227                // Method java/lang/Integer.valueOf:(I)Ljava/lang/Integer;
      26: aastore
      27: iload_1
      28: aload_2
      29: iload_3
      30: invokespecial #556                // Method io/dekorate/deps/okhttp3/internal/http2/Http2Connection$4."<init>":(Lio/dekorate/deps/okhttp3/internal/http2/Http2Connection;Ljava/lang/String;[Ljava/lang/Object;ILjava/util/List;Z)V
      33: invokespecial #548                // Method pushExecutorExecute:(Lio/dekorate/deps/okhttp3/internal/NamedRunnable;)V
      36: goto          41
      39: astore        4
      41: return
    Exception table:
       from    to  target type
           0    36    39   Class java/util/concurrent/RejectedExecutionException

  void pushDataLater(int, io.dekorate.deps.okio.BufferedSource, int, boolean) throws java.io.IOException;
    Code:
       0: new           #381                // class io/dekorate/deps/okio/Buffer
       3: dup
       4: invokespecial #559                // Method io/dekorate/deps/okio/Buffer."<init>":()V
       7: astore        5
       9: aload_2
      10: iload_3
      11: i2l
      12: invokeinterface #564,  3          // InterfaceMethod io/dekorate/deps/okio/BufferedSource.require:(J)V
      17: aload_2
      18: aload         5
      20: iload_3
      21: i2l
      22: invokeinterface #567,  4          // InterfaceMethod io/dekorate/deps/okio/BufferedSource.read:(Lio/dekorate/deps/okio/Buffer;J)J
      27: pop2
      28: aload         5
      30: invokevirtual #570                // Method io/dekorate/deps/okio/Buffer.size:()J
      33: iload_3
      34: i2l
      35: lcmp
      36: ifeq          75
      39: new           #262                // class java/io/IOException
      42: dup
      43: new           #572                // class java/lang/StringBuilder
      46: dup
      47: invokespecial #573                // Method java/lang/StringBuilder."<init>":()V
      50: aload         5
      52: invokevirtual #570                // Method io/dekorate/deps/okio/Buffer.size:()J
      55: invokevirtual #577                // Method java/lang/StringBuilder.append:(J)Ljava/lang/StringBuilder;
      58: ldc_w         #579                // String  !=
      61: invokevirtual #582                // Method java/lang/StringBuilder.append:(Ljava/lang/String;)Ljava/lang/StringBuilder;
      64: iload_3
      65: invokevirtual #585                // Method java/lang/StringBuilder.append:(I)Ljava/lang/StringBuilder;
      68: invokevirtual #589                // Method java/lang/StringBuilder.toString:()Ljava/lang/String;
      71: invokespecial #352                // Method java/io/IOException."<init>":(Ljava/lang/String;)V
      74: athrow
      75: aload_0
      76: new           #23                 // class io/dekorate/deps/okhttp3/internal/http2/Http2Connection$5
      79: dup
      80: aload_0
      81: ldc_w         #591                // String OkHttp %s Push Data[%s]
      84: iconst_2
      85: anewarray     #4                  // class java/lang/Object
      88: dup
      89: iconst_0
      90: aload_0
      91: getfield      #112                // Field hostname:Ljava/lang/String;
      94: aastore
      95: dup
      96: iconst_1
      97: iload_1
      98: invokestatic  #227                // Method java/lang/Integer.valueOf:(I)Ljava/lang/Integer;
     101: aastore
     102: iload_1
     103: aload         5
     105: iload_3
     106: iload         4
     108: invokespecial #594                // Method io/dekorate/deps/okhttp3/internal/http2/Http2Connection$5."<init>":(Lio/dekorate/deps/okhttp3/internal/http2/Http2Connection;Ljava/lang/String;[Ljava/lang/Object;ILio/dekorate/deps/okio/Buffer;IZ)V
     111: invokespecial #548                // Method pushExecutorExecute:(Lio/dekorate/deps/okhttp3/internal/NamedRunnable;)V
     114: return

  void pushResetLater(int, io.dekorate.deps.okhttp3.internal.http2.ErrorCode);
    Code:
       0: aload_0
       1: new           #21                 // class io/dekorate/deps/okhttp3/internal/http2/Http2Connection$6
       4: dup
       5: aload_0
       6: ldc_w         #597                // String OkHttp %s Push Reset[%s]
       9: iconst_2
      10: anewarray     #4                  // class java/lang/Object
      13: dup
      14: iconst_0
      15: aload_0
      16: getfield      #112                // Field hostname:Ljava/lang/String;
      19: aastore
      20: dup
      21: iconst_1
      22: iload_1
      23: invokestatic  #227                // Method java/lang/Integer.valueOf:(I)Ljava/lang/Integer;
      26: aastore
      27: iload_1
      28: aload_2
      29: invokespecial #598                // Method io/dekorate/deps/okhttp3/internal/http2/Http2Connection$6."<init>":(Lio/dekorate/deps/okhttp3/internal/http2/Http2Connection;Ljava/lang/String;[Ljava/lang/Object;ILio/dekorate/deps/okhttp3/internal/http2/ErrorCode;)V
      32: invokespecial #548                // Method pushExecutorExecute:(Lio/dekorate/deps/okhttp3/internal/NamedRunnable;)V
      35: return

  private synchronized void pushExecutorExecute(io.dekorate.deps.okhttp3.internal.NamedRunnable);
    Code:
       0: aload_0
       1: invokevirtual #600                // Method isShutdown:()Z
       4: ifne          17
       7: aload_0
       8: getfield      #166                // Field pushExecutor:Ljava/util/concurrent/ExecutorService;
      11: aload_1
      12: invokeinterface #601,  2          // InterfaceMethod java/util/concurrent/ExecutorService.execute:(Ljava/lang/Runnable;)V
      17: return

  static void access$000(io.dekorate.deps.okhttp3.internal.http2.Http2Connection);
    Code:
       0: aload_0
       1: invokespecial #418                // Method failConnection:()V
       4: return

  static java.util.concurrent.ExecutorService access$100();
    Code:
       0: getstatic     #610                // Field listenerExecutor:Ljava/util/concurrent/ExecutorService;
       3: areturn

  static java.util.concurrent.ScheduledExecutorService access$200(io.dekorate.deps.okhttp3.internal.http2.Http2Connection);
    Code:
       0: aload_0
       1: getfield      #131                // Field writerExecutor:Ljava/util/concurrent/ScheduledExecutorService;
       4: areturn

  static boolean access$302(io.dekorate.deps.okhttp3.internal.http2.Http2Connection, boolean);
    Code:
       0: aload_0
       1: iload_1
       2: dup_x1
       3: putfield      #415                // Field awaitingPong:Z
       6: ireturn

  static {};
    Code:
       0: ldc           #2                  // class io/dekorate/deps/okhttp3/internal/http2/Http2Connection
       2: invokevirtual #621                // Method java/lang/Class.desiredAssertionStatus:()Z
       5: ifne          12
       8: iconst_1
       9: goto          13
      12: iconst_0
      13: putstatic     #456                // Field $assertionsDisabled:Z
      16: new           #151                // class java/util/concurrent/ThreadPoolExecutor
      19: dup
      20: iconst_0
      21: ldc           #246                // int 2147483647
      23: ldc2_w        #152                // long 60l
      26: getstatic     #156                // Field java/util/concurrent/TimeUnit.SECONDS:Ljava/util/concurrent/TimeUnit;
      29: new           #623                // class java/util/concurrent/SynchronousQueue
      32: dup
      33: invokespecial #624                // Method java/util/concurrent/SynchronousQueue."<init>":()V
      36: ldc_w         #626                // String OkHttp Http2Connection
      39: iconst_1
      40: invokestatic  #126                // Method io/dekorate/deps/okhttp3/internal/Util.threadFactory:(Ljava/lang/String;Z)Ljava/util/concurrent/ThreadFactory;
      43: invokespecial #164                // Method java/util/concurrent/ThreadPoolExecutor."<init>":(IIJLjava/util/concurrent/TimeUnit;Ljava/util/concurrent/BlockingQueue;Ljava/util/concurrent/ThreadFactory;)V
      46: putstatic     #610                // Field listenerExecutor:Ljava/util/concurrent/ExecutorService;
      49: return
}
