Compiled from "RepositoryEntityLinks.java"
public class org.springframework.data.rest.webmvc.support.RepositoryEntityLinks extends org.springframework.hateoas.core.AbstractEntityLinks {
  private final org.springframework.data.repository.support.Repositories repositories;

  private final org.springframework.data.rest.core.mapping.ResourceMappings mappings;

  private final org.springframework.data.rest.core.config.RepositoryRestConfiguration config;

  private final org.springframework.data.rest.webmvc.support.PagingAndSortingTemplateVariables templateVariables;

  private final org.springframework.data.rest.core.util.Java8PluginRegistry<org.springframework.data.rest.webmvc.spi.BackendIdConverter, java.lang.Class<?>> idConverters;

  public boolean supports(java.lang.Class<?>);
    Code:
       0: aload_0
       1: getfield      #1                  // Field repositories:Lorg/springframework/data/repository/support/Repositories;
       4: aload_1
       5: invokevirtual #2                  // Method org/springframework/data/repository/support/Repositories.hasRepositoryFor:(Ljava/lang/Class;)Z
       8: ireturn

  public org.springframework.hateoas.LinkBuilder linkFor(java.lang.Class<?>);
    Code:
       0: aload_0
       1: getfield      #3                  // Field mappings:Lorg/springframework/data/rest/core/mapping/ResourceMappings;
       4: aload_1
       5: invokeinterface #4,  2            // InterfaceMethod org/springframework/data/rest/core/mapping/ResourceMappings.getMetadataFor:(Ljava/lang/Class;)Lorg/springframework/data/rest/core/mapping/ResourceMetadata;
      10: astore_2
      11: new           #5                  // class org/springframework/data/rest/webmvc/support/RepositoryLinkBuilder
      14: dup
      15: aload_2
      16: new           #6                  // class org/springframework/data/rest/webmvc/BaseUri
      19: dup
      20: aload_0
      21: getfield      #7                  // Field config:Lorg/springframework/data/rest/core/config/RepositoryRestConfiguration;
      24: invokevirtual #8                  // Method org/springframework/data/rest/core/config/RepositoryRestConfiguration.getBaseUri:()Ljava/net/URI;
      27: invokespecial #9                  // Method org/springframework/data/rest/webmvc/BaseUri."<init>":(Ljava/net/URI;)V
      30: invokespecial #10                 // Method org/springframework/data/rest/webmvc/support/RepositoryLinkBuilder."<init>":(Lorg/springframework/data/rest/core/mapping/ResourceMetadata;Lorg/springframework/data/rest/webmvc/BaseUri;)V
      33: areturn

  public org.springframework.hateoas.LinkBuilder linkFor(java.lang.Class<?>, java.lang.Object...);
    Code:
       0: aload_0
       1: aload_1
       2: invokevirtual #11                 // Method linkFor:(Ljava/lang/Class;)Lorg/springframework/hateoas/LinkBuilder;
       5: areturn

  public org.springframework.hateoas.Link linkToPagedResource(java.lang.Class<?>, org.springframework.data.domain.Pageable);
    Code:
       0: aload_0
       1: getfield      #3                  // Field mappings:Lorg/springframework/data/rest/core/mapping/ResourceMappings;
       4: aload_1
       5: invokeinterface #4,  2            // InterfaceMethod org/springframework/data/rest/core/mapping/ResourceMappings.getMetadataFor:(Ljava/lang/Class;)Lorg/springframework/data/rest/core/mapping/ResourceMetadata;
      10: astore_3
      11: aload_0
      12: aload_1
      13: invokevirtual #11                 // Method linkFor:(Ljava/lang/Class;)Lorg/springframework/hateoas/LinkBuilder;
      16: invokevirtual #12                 // Method java/lang/Object.toString:()Ljava/lang/String;
      19: astore        4
      21: aload_0
      22: aload         4
      24: aload_3
      25: aload_2
      26: invokespecial #13                 // Method prepareUri:(Ljava/lang/String;Lorg/springframework/data/rest/core/mapping/ResourceMapping;Lorg/springframework/data/domain/Pageable;)Lorg/springframework/web/util/UriComponents;
      29: astore        5
      31: aload_0
      32: aload         5
      34: aload_3
      35: aload_2
      36: invokespecial #14                 // Method getTemplateVariables:(Lorg/springframework/web/util/UriComponents;Lorg/springframework/data/rest/core/mapping/ResourceMapping;Lorg/springframework/data/domain/Pageable;)Lorg/springframework/hateoas/TemplateVariables;
      39: aload_0
      40: aload_1
      41: invokespecial #15                 // Method getProjectionVariable:(Ljava/lang/Class;)Lorg/springframework/hateoas/TemplateVariables;
      44: invokevirtual #16                 // Method org/springframework/hateoas/TemplateVariables.concat:(Lorg/springframework/hateoas/TemplateVariables;)Lorg/springframework/hateoas/TemplateVariables;
      47: astore        6
      49: new           #17                 // class org/springframework/hateoas/Link
      52: dup
      53: new           #18                 // class org/springframework/hateoas/UriTemplate
      56: dup
      57: aload         4
      59: aload         6
      61: invokespecial #19                 // Method org/springframework/hateoas/UriTemplate."<init>":(Ljava/lang/String;Lorg/springframework/hateoas/TemplateVariables;)V
      64: aload_3
      65: invokeinterface #20,  1           // InterfaceMethod org/springframework/data/rest/core/mapping/ResourceMetadata.getRel:()Ljava/lang/String;
      70: invokespecial #21                 // Method org/springframework/hateoas/Link."<init>":(Lorg/springframework/hateoas/UriTemplate;Ljava/lang/String;)V
      73: areturn

  public org.springframework.hateoas.Link linkToCollectionResource(java.lang.Class<?>);
    Code:
       0: aload_0
       1: aload_1
       2: aconst_null
       3: invokevirtual #22                 // Method linkToPagedResource:(Ljava/lang/Class;Lorg/springframework/data/domain/Pageable;)Lorg/springframework/hateoas/Link;
       6: areturn

  public org.springframework.hateoas.Link linkToSingleResource(java.lang.Class<?>, java.lang.Object);
    Code:
       0: ldc           #23                 // class java/io/Serializable
       2: aload_2
       3: ldc           #24                 // String Id must be assignable to Serializable!
       5: invokestatic  #25                 // Method org/springframework/util/Assert.isInstanceOf:(Ljava/lang/Class;Ljava/lang/Object;Ljava/lang/String;)V
       8: aload_0
       9: getfield      #3                  // Field mappings:Lorg/springframework/data/rest/core/mapping/ResourceMappings;
      12: aload_1
      13: invokeinterface #4,  2            // InterfaceMethod org/springframework/data/rest/core/mapping/ResourceMappings.getMetadataFor:(Ljava/lang/Class;)Lorg/springframework/data/rest/core/mapping/ResourceMetadata;
      18: astore_3
      19: aload_0
      20: getfield      #26                 // Field idConverters:Lorg/springframework/data/rest/core/util/Java8PluginRegistry;
      23: aload_1
      24: invokevirtual #27                 // Method org/springframework/data/rest/core/util/Java8PluginRegistry.getPluginFor:(Ljava/lang/Object;)Ljava/util/Optional;
      27: getstatic     #28                 // Field org/springframework/data/rest/webmvc/spi/BackendIdConverter$DefaultIdConverter.INSTANCE:Lorg/springframework/data/rest/webmvc/spi/BackendIdConverter$DefaultIdConverter;
      30: invokevirtual #29                 // Method java/util/Optional.orElse:(Ljava/lang/Object;)Ljava/lang/Object;
      33: checkcast     #30                 // class org/springframework/data/rest/webmvc/spi/BackendIdConverter
      36: aload_2
      37: checkcast     #23                 // class java/io/Serializable
      40: aload_1
      41: invokeinterface #31,  3           // InterfaceMethod org/springframework/data/rest/webmvc/spi/BackendIdConverter.toRequestId:(Ljava/io/Serializable;Ljava/lang/Class;)Ljava/lang/String;
      46: astore        4
      48: aload_0
      49: aload_1
      50: invokevirtual #11                 // Method linkFor:(Ljava/lang/Class;)Lorg/springframework/hateoas/LinkBuilder;
      53: aload         4
      55: invokeinterface #32,  2           // InterfaceMethod org/springframework/hateoas/LinkBuilder.slash:(Ljava/lang/Object;)Lorg/springframework/hateoas/LinkBuilder;
      60: aload_3
      61: invokeinterface #33,  1           // InterfaceMethod org/springframework/data/rest/core/mapping/ResourceMetadata.getItemResourceRel:()Ljava/lang/String;
      66: invokeinterface #34,  2           // InterfaceMethod org/springframework/hateoas/LinkBuilder.withRel:(Ljava/lang/String;)Lorg/springframework/hateoas/Link;
      71: astore        5
      73: new           #17                 // class org/springframework/hateoas/Link
      76: dup
      77: new           #18                 // class org/springframework/hateoas/UriTemplate
      80: dup
      81: aload         5
      83: invokevirtual #35                 // Method org/springframework/hateoas/Link.getHref:()Ljava/lang/String;
      86: aload_0
      87: aload_1
      88: invokespecial #15                 // Method getProjectionVariable:(Ljava/lang/Class;)Lorg/springframework/hateoas/TemplateVariables;
      91: invokespecial #19                 // Method org/springframework/hateoas/UriTemplate."<init>":(Ljava/lang/String;Lorg/springframework/hateoas/TemplateVariables;)V
      94: invokevirtual #36                 // Method org/springframework/hateoas/UriTemplate.toString:()Ljava/lang/String;
      97: aload_3
      98: invokeinterface #33,  1           // InterfaceMethod org/springframework/data/rest/core/mapping/ResourceMetadata.getItemResourceRel:()Ljava/lang/String;
     103: invokespecial #37                 // Method org/springframework/hateoas/Link."<init>":(Ljava/lang/String;Ljava/lang/String;)V
     106: areturn

  public org.springframework.hateoas.Links linksToSearchResources(java.lang.Class<?>);
    Code:
       0: aload_0
       1: aload_1
       2: aconst_null
       3: aconst_null
       4: invokespecial #38                 // Method linksToSearchResources:(Ljava/lang/Class;Lorg/springframework/data/domain/Pageable;Lorg/springframework/data/domain/Sort;)Lorg/springframework/hateoas/Links;
       7: areturn

  public org.springframework.hateoas.Links linksToSearchResources(java.lang.Class<?>, org.springframework.data.domain.Pageable);
    Code:
       0: aload_0
       1: aload_1
       2: aload_2
       3: aconst_null
       4: invokespecial #38                 // Method linksToSearchResources:(Ljava/lang/Class;Lorg/springframework/data/domain/Pageable;Lorg/springframework/data/domain/Sort;)Lorg/springframework/hateoas/Links;
       7: areturn

  public org.springframework.hateoas.Links linksToSearchResources(java.lang.Class<?>, org.springframework.data.domain.Sort);
    Code:
       0: aload_0
       1: aload_1
       2: aconst_null
       3: aload_2
       4: invokespecial #38                 // Method linksToSearchResources:(Ljava/lang/Class;Lorg/springframework/data/domain/Pageable;Lorg/springframework/data/domain/Sort;)Lorg/springframework/hateoas/Links;
       7: areturn

  public org.springframework.hateoas.Link linkToSearchResource(java.lang.Class<?>, java.lang.String);
    Code:
       0: aload_0
       1: aload_1
       2: aload_2
       3: aconst_null
       4: aconst_null
       5: invokespecial #39                 // Method getSearchResourceLinkFor:(Ljava/lang/Class;Ljava/lang/String;Lorg/springframework/data/domain/Pageable;Lorg/springframework/data/domain/Sort;)Lorg/springframework/hateoas/Link;
       8: areturn

  public org.springframework.hateoas.Link linkToSearchResource(java.lang.Class<?>, java.lang.String, org.springframework.data.domain.Pageable);
    Code:
       0: aload_0
       1: aload_1
       2: aload_2
       3: aload_3
       4: aconst_null
       5: invokespecial #39                 // Method getSearchResourceLinkFor:(Ljava/lang/Class;Ljava/lang/String;Lorg/springframework/data/domain/Pageable;Lorg/springframework/data/domain/Sort;)Lorg/springframework/hateoas/Link;
       8: areturn

  public org.springframework.hateoas.Link linkToSearchResource(java.lang.Class<?>, java.lang.String, org.springframework.data.domain.Sort);
    Code:
       0: aload_0
       1: aload_1
       2: aload_2
       3: aconst_null
       4: aload_3
       5: invokespecial #39                 // Method getSearchResourceLinkFor:(Ljava/lang/Class;Ljava/lang/String;Lorg/springframework/data/domain/Pageable;Lorg/springframework/data/domain/Sort;)Lorg/springframework/hateoas/Link;
       8: areturn

  private org.springframework.hateoas.Links linksToSearchResources(java.lang.Class<?>, org.springframework.data.domain.Pageable, org.springframework.data.domain.Sort);
    Code:
       0: new           #40                 // class java/util/ArrayList
       3: dup
       4: invokespecial #41                 // Method java/util/ArrayList."<init>":()V
       7: astore        4
       9: aload_0
      10: getfield      #3                  // Field mappings:Lorg/springframework/data/rest/core/mapping/ResourceMappings;
      13: aload_1
      14: invokeinterface #42,  2           // InterfaceMethod org/springframework/data/rest/core/mapping/ResourceMappings.getSearchResourceMappings:(Ljava/lang/Class;)Lorg/springframework/data/rest/core/mapping/SearchResourceMappings;
      19: astore        5
      21: aload         5
      23: invokevirtual #43                 // Method org/springframework/data/rest/core/mapping/SearchResourceMappings.getExportedMappings:()Ljava/lang/Iterable;
      26: invokeinterface #44,  1           // InterfaceMethod java/lang/Iterable.iterator:()Ljava/util/Iterator;
      31: astore        6
      33: aload         6
      35: invokeinterface #45,  1           // InterfaceMethod java/util/Iterator.hasNext:()Z
      40: ifeq          80
      43: aload         6
      45: invokeinterface #46,  1           // InterfaceMethod java/util/Iterator.next:()Ljava/lang/Object;
      50: checkcast     #47                 // class org/springframework/data/rest/core/mapping/MethodResourceMapping
      53: astore        7
      55: aload         4
      57: aload_0
      58: aload_1
      59: aload         7
      61: invokeinterface #48,  1           // InterfaceMethod org/springframework/data/rest/core/mapping/MethodResourceMapping.getRel:()Ljava/lang/String;
      66: aload_2
      67: aload_3
      68: invokespecial #39                 // Method getSearchResourceLinkFor:(Ljava/lang/Class;Ljava/lang/String;Lorg/springframework/data/domain/Pageable;Lorg/springframework/data/domain/Sort;)Lorg/springframework/hateoas/Link;
      71: invokeinterface #49,  2           // InterfaceMethod java/util/List.add:(Ljava/lang/Object;)Z
      76: pop
      77: goto          33
      80: new           #50                 // class org/springframework/hateoas/Links
      83: dup
      84: aload         4
      86: invokespecial #51                 // Method org/springframework/hateoas/Links."<init>":(Ljava/util/List;)V
      89: areturn

  private org.springframework.hateoas.Link getSearchResourceLinkFor(java.lang.Class<?>, java.lang.String, org.springframework.data.domain.Pageable, org.springframework.data.domain.Sort);
    Code:
       0: aload_1
       1: ldc           #52                 // String Domain type must not be null!
       3: invokestatic  #53                 // Method org/springframework/util/Assert.notNull:(Ljava/lang/Object;Ljava/lang/String;)V
       6: aload_2
       7: ldc           #54                 // String Relation name must not be null or empty!
       9: invokestatic  #55                 // Method org/springframework/util/Assert.hasText:(Ljava/lang/String;Ljava/lang/String;)V
      12: aload_0
      13: getfield      #3                  // Field mappings:Lorg/springframework/data/rest/core/mapping/ResourceMappings;
      16: aload_1
      17: invokeinterface #42,  2           // InterfaceMethod org/springframework/data/rest/core/mapping/ResourceMappings.getSearchResourceMappings:(Ljava/lang/Class;)Lorg/springframework/data/rest/core/mapping/SearchResourceMappings;
      22: astore        5
      24: aload         5
      26: aload_2
      27: invokevirtual #56                 // Method org/springframework/data/rest/core/mapping/SearchResourceMappings.getExportedMethodMappingForRel:(Ljava/lang/String;)Lorg/springframework/data/rest/core/mapping/MethodResourceMapping;
      30: astore        6
      32: aload         6
      34: ifnonnull     39
      37: aconst_null
      38: areturn
      39: aload_0
      40: aload_1
      41: invokevirtual #11                 // Method linkFor:(Ljava/lang/Class;)Lorg/springframework/hateoas/LinkBuilder;
      44: aload_0
      45: getfield      #3                  // Field mappings:Lorg/springframework/data/rest/core/mapping/ResourceMappings;
      48: aload_1
      49: invokeinterface #42,  2           // InterfaceMethod org/springframework/data/rest/core/mapping/ResourceMappings.getSearchResourceMappings:(Ljava/lang/Class;)Lorg/springframework/data/rest/core/mapping/SearchResourceMappings;
      54: invokevirtual #57                 // Method org/springframework/data/rest/core/mapping/SearchResourceMappings.getPath:()Lorg/springframework/data/rest/core/Path;
      57: invokeinterface #32,  2           // InterfaceMethod org/springframework/hateoas/LinkBuilder.slash:(Ljava/lang/Object;)Lorg/springframework/hateoas/LinkBuilder;
      62: aload         6
      64: invokeinterface #58,  1           // InterfaceMethod org/springframework/data/rest/core/mapping/MethodResourceMapping.getPath:()Lorg/springframework/data/rest/core/Path;
      69: invokeinterface #32,  2           // InterfaceMethod org/springframework/hateoas/LinkBuilder.slash:(Ljava/lang/Object;)Lorg/springframework/hateoas/LinkBuilder;
      74: astore        7
      76: aload_0
      77: aload         7
      79: invokevirtual #12                 // Method java/lang/Object.toString:()Ljava/lang/String;
      82: aload         6
      84: aload_3
      85: aload         4
      87: invokespecial #59                 // Method prepareUri:(Ljava/lang/String;Lorg/springframework/data/rest/core/mapping/MethodResourceMapping;Lorg/springframework/data/domain/Pageable;Lorg/springframework/data/domain/Sort;)Lorg/springframework/web/util/UriComponents;
      90: astore        8
      92: aload_0
      93: aload         6
      95: invokespecial #60                 // Method getParameterVariables:(Lorg/springframework/data/rest/core/mapping/MethodResourceMapping;)Lorg/springframework/hateoas/TemplateVariables;
      98: aload_0
      99: aload         8
     101: aload         6
     103: aload_3
     104: aload         4
     106: invokespecial #61                 // Method getTemplateVariables:(Lorg/springframework/web/util/UriComponents;Lorg/springframework/data/rest/core/mapping/MethodResourceMapping;Lorg/springframework/data/domain/Pageable;Lorg/springframework/data/domain/Sort;)Lorg/springframework/hateoas/TemplateVariables;
     109: invokevirtual #16                 // Method org/springframework/hateoas/TemplateVariables.concat:(Lorg/springframework/hateoas/TemplateVariables;)Lorg/springframework/hateoas/TemplateVariables;
     112: aload_0
     113: aload         6
     115: invokeinterface #62,  1           // InterfaceMethod org/springframework/data/rest/core/mapping/MethodResourceMapping.getReturnedDomainType:()Ljava/lang/Class;
     120: invokespecial #15                 // Method getProjectionVariable:(Ljava/lang/Class;)Lorg/springframework/hateoas/TemplateVariables;
     123: invokevirtual #16                 // Method org/springframework/hateoas/TemplateVariables.concat:(Lorg/springframework/hateoas/TemplateVariables;)Lorg/springframework/hateoas/TemplateVariables;
     126: astore        9
     128: new           #17                 // class org/springframework/hateoas/Link
     131: dup
     132: new           #18                 // class org/springframework/hateoas/UriTemplate
     135: dup
     136: aload         8
     138: invokevirtual #63                 // Method org/springframework/web/util/UriComponents.toString:()Ljava/lang/String;
     141: aload         9
     143: invokespecial #19                 // Method org/springframework/hateoas/UriTemplate."<init>":(Ljava/lang/String;Lorg/springframework/hateoas/TemplateVariables;)V
     146: aload         6
     148: invokeinterface #48,  1           // InterfaceMethod org/springframework/data/rest/core/mapping/MethodResourceMapping.getRel:()Ljava/lang/String;
     153: invokespecial #21                 // Method org/springframework/hateoas/Link."<init>":(Lorg/springframework/hateoas/UriTemplate;Ljava/lang/String;)V
     156: areturn

  private org.springframework.hateoas.TemplateVariables getTemplateVariables(org.springframework.web.util.UriComponents, org.springframework.data.rest.core.mapping.ResourceMapping, org.springframework.data.domain.Pageable);
    Code:
       0: aload_2
       1: invokeinterface #64,  1           // InterfaceMethod org/springframework/data/rest/core/mapping/ResourceMapping.isPagingResource:()Z
       6: ifeq          21
       9: aload_0
      10: getfield      #65                 // Field templateVariables:Lorg/springframework/data/rest/webmvc/support/PagingAndSortingTemplateVariables;
      13: aconst_null
      14: aload_1
      15: invokeinterface #66,  3           // InterfaceMethod org/springframework/data/rest/webmvc/support/PagingAndSortingTemplateVariables.getPaginationTemplateVariables:(Lorg/springframework/core/MethodParameter;Lorg/springframework/web/util/UriComponents;)Lorg/springframework/hateoas/TemplateVariables;
      20: areturn
      21: getstatic     #67                 // Field org/springframework/hateoas/TemplateVariables.NONE:Lorg/springframework/hateoas/TemplateVariables;
      24: areturn

  private org.springframework.hateoas.TemplateVariables getTemplateVariables(org.springframework.web.util.UriComponents, org.springframework.data.rest.core.mapping.MethodResourceMapping, org.springframework.data.domain.Pageable, org.springframework.data.domain.Sort);
    Code:
       0: aload_2
       1: invokeinterface #68,  1           // InterfaceMethod org/springframework/data/rest/core/mapping/MethodResourceMapping.isSortableResource:()Z
       6: ifeq          21
       9: aload_0
      10: getfield      #65                 // Field templateVariables:Lorg/springframework/data/rest/webmvc/support/PagingAndSortingTemplateVariables;
      13: aconst_null
      14: aload_1
      15: invokeinterface #69,  3           // InterfaceMethod org/springframework/data/rest/webmvc/support/PagingAndSortingTemplateVariables.getSortTemplateVariables:(Lorg/springframework/core/MethodParameter;Lorg/springframework/web/util/UriComponents;)Lorg/springframework/hateoas/TemplateVariables;
      20: areturn
      21: aload_0
      22: aload_1
      23: aload_2
      24: aload_3
      25: invokespecial #14                 // Method getTemplateVariables:(Lorg/springframework/web/util/UriComponents;Lorg/springframework/data/rest/core/mapping/ResourceMapping;Lorg/springframework/data/domain/Pageable;)Lorg/springframework/hateoas/TemplateVariables;
      28: areturn

  private org.springframework.hateoas.TemplateVariables getProjectionVariable(java.lang.Class<?>);
    Code:
       0: aload_0
       1: getfield      #7                  // Field config:Lorg/springframework/data/rest/core/config/RepositoryRestConfiguration;
       4: invokevirtual #70                 // Method org/springframework/data/rest/core/config/RepositoryRestConfiguration.getProjectionConfiguration:()Lorg/springframework/data/rest/core/config/ProjectionDefinitionConfiguration;
       7: astore_2
       8: aload_2
       9: aload_1
      10: invokevirtual #71                 // Method org/springframework/data/rest/core/config/ProjectionDefinitionConfiguration.hasProjectionFor:(Ljava/lang/Class;)Z
      13: ifeq          45
      16: new           #72                 // class org/springframework/hateoas/TemplateVariables
      19: dup
      20: iconst_1
      21: anewarray     #73                 // class org/springframework/hateoas/TemplateVariable
      24: dup
      25: iconst_0
      26: new           #73                 // class org/springframework/hateoas/TemplateVariable
      29: dup
      30: aload_2
      31: invokevirtual #74                 // Method org/springframework/data/rest/core/config/ProjectionDefinitionConfiguration.getParameterName:()Ljava/lang/String;
      34: getstatic     #75                 // Field org/springframework/hateoas/TemplateVariable$VariableType.REQUEST_PARAM:Lorg/springframework/hateoas/TemplateVariable$VariableType;
      37: invokespecial #76                 // Method org/springframework/hateoas/TemplateVariable."<init>":(Ljava/lang/String;Lorg/springframework/hateoas/TemplateVariable$VariableType;)V
      40: aastore
      41: invokespecial #77                 // Method org/springframework/hateoas/TemplateVariables."<init>":([Lorg/springframework/hateoas/TemplateVariable;)V
      44: areturn
      45: getstatic     #67                 // Field org/springframework/hateoas/TemplateVariables.NONE:Lorg/springframework/hateoas/TemplateVariables;
      48: areturn

  private org.springframework.hateoas.TemplateVariables getParameterVariables(org.springframework.data.rest.core.mapping.MethodResourceMapping);
    Code:
       0: new           #40                 // class java/util/ArrayList
       3: dup
       4: invokespecial #41                 // Method java/util/ArrayList."<init>":()V
       7: astore_2
       8: aload_1
       9: invokeinterface #78,  1           // InterfaceMethod org/springframework/data/rest/core/mapping/MethodResourceMapping.getParametersMetadata:()Lorg/springframework/data/rest/core/mapping/ParametersMetadata;
      14: invokevirtual #79                 // Method org/springframework/data/rest/core/mapping/ParametersMetadata.iterator:()Ljava/util/Iterator;
      17: astore_3
      18: aload_3
      19: invokeinterface #45,  1           // InterfaceMethod java/util/Iterator.hasNext:()Z
      24: ifeq          63
      27: aload_3
      28: invokeinterface #46,  1           // InterfaceMethod java/util/Iterator.next:()Ljava/lang/Object;
      33: checkcast     #80                 // class org/springframework/data/rest/core/mapping/ParameterMetadata
      36: astore        4
      38: aload_2
      39: new           #73                 // class org/springframework/hateoas/TemplateVariable
      42: dup
      43: aload         4
      45: invokevirtual #81                 // Method org/springframework/data/rest/core/mapping/ParameterMetadata.getName:()Ljava/lang/String;
      48: getstatic     #75                 // Field org/springframework/hateoas/TemplateVariable$VariableType.REQUEST_PARAM:Lorg/springframework/hateoas/TemplateVariable$VariableType;
      51: invokespecial #76                 // Method org/springframework/hateoas/TemplateVariable."<init>":(Ljava/lang/String;Lorg/springframework/hateoas/TemplateVariable$VariableType;)V
      54: invokeinterface #49,  2           // InterfaceMethod java/util/List.add:(Ljava/lang/Object;)Z
      59: pop
      60: goto          18
      63: new           #72                 // class org/springframework/hateoas/TemplateVariables
      66: dup
      67: aload_2
      68: invokespecial #82                 // Method org/springframework/hateoas/TemplateVariables."<init>":(Ljava/util/List;)V
      71: areturn

  private org.springframework.web.util.UriComponents prepareUri(java.lang.String, org.springframework.data.rest.core.mapping.MethodResourceMapping, org.springframework.data.domain.Pageable, org.springframework.data.domain.Sort);
    Code:
       0: aload_2
       1: invokeinterface #68,  1           // InterfaceMethod org/springframework/data/rest/core/mapping/MethodResourceMapping.isSortableResource:()Z
       6: ifeq          35
       9: aload_1
      10: invokestatic  #83                 // Method org/springframework/web/util/UriComponentsBuilder.fromUriString:(Ljava/lang/String;)Lorg/springframework/web/util/UriComponentsBuilder;
      13: astore        5
      15: aload_0
      16: getfield      #65                 // Field templateVariables:Lorg/springframework/data/rest/webmvc/support/PagingAndSortingTemplateVariables;
      19: aload         5
      21: aconst_null
      22: aload         4
      24: invokeinterface #84,  4           // InterfaceMethod org/springframework/data/rest/webmvc/support/PagingAndSortingTemplateVariables.enhance:(Lorg/springframework/web/util/UriComponentsBuilder;Lorg/springframework/core/MethodParameter;Ljava/lang/Object;)V
      29: aload         5
      31: invokevirtual #85                 // Method org/springframework/web/util/UriComponentsBuilder.build:()Lorg/springframework/web/util/UriComponents;
      34: areturn
      35: aload_0
      36: aload_1
      37: aload_2
      38: aload_3
      39: invokespecial #13                 // Method prepareUri:(Ljava/lang/String;Lorg/springframework/data/rest/core/mapping/ResourceMapping;Lorg/springframework/data/domain/Pageable;)Lorg/springframework/web/util/UriComponents;
      42: areturn

  private org.springframework.web.util.UriComponents prepareUri(java.lang.String, org.springframework.data.rest.core.mapping.ResourceMapping, org.springframework.data.domain.Pageable);
    Code:
       0: aload_1
       1: invokestatic  #83                 // Method org/springframework/web/util/UriComponentsBuilder.fromUriString:(Ljava/lang/String;)Lorg/springframework/web/util/UriComponentsBuilder;
       4: astore        4
       6: aload_2
       7: invokeinterface #64,  1           // InterfaceMethod org/springframework/data/rest/core/mapping/ResourceMapping.isPagingResource:()Z
      12: ifeq          28
      15: aload_0
      16: getfield      #65                 // Field templateVariables:Lorg/springframework/data/rest/webmvc/support/PagingAndSortingTemplateVariables;
      19: aload         4
      21: aconst_null
      22: aload_3
      23: invokeinterface #84,  4           // InterfaceMethod org/springframework/data/rest/webmvc/support/PagingAndSortingTemplateVariables.enhance:(Lorg/springframework/web/util/UriComponentsBuilder;Lorg/springframework/core/MethodParameter;Ljava/lang/Object;)V
      28: aload         4
      30: invokevirtual #85                 // Method org/springframework/web/util/UriComponentsBuilder.build:()Lorg/springframework/web/util/UriComponents;
      33: areturn

  public org.springframework.data.rest.webmvc.support.RepositoryEntityLinks(org.springframework.data.repository.support.Repositories, org.springframework.data.rest.core.mapping.ResourceMappings, org.springframework.data.rest.core.config.RepositoryRestConfiguration, org.springframework.data.rest.webmvc.support.PagingAndSortingTemplateVariables, org.springframework.data.rest.core.util.Java8PluginRegistry<org.springframework.data.rest.webmvc.spi.BackendIdConverter, java.lang.Class<?>>);
    Code:
       0: aload_0
       1: invokespecial #86                 // Method org/springframework/hateoas/core/AbstractEntityLinks."<init>":()V
       4: aload_1
       5: ifnonnull     18
       8: new           #87                 // class java/lang/IllegalArgumentException
      11: dup
      12: ldc           #88                 // String repositories is marked non-null but is null
      14: invokespecial #89                 // Method java/lang/IllegalArgumentException."<init>":(Ljava/lang/String;)V
      17: athrow
      18: aload_2
      19: ifnonnull     32
      22: new           #87                 // class java/lang/IllegalArgumentException
      25: dup
      26: ldc           #90                 // String mappings is marked non-null but is null
      28: invokespecial #89                 // Method java/lang/IllegalArgumentException."<init>":(Ljava/lang/String;)V
      31: athrow
      32: aload_3
      33: ifnonnull     46
      36: new           #87                 // class java/lang/IllegalArgumentException
      39: dup
      40: ldc           #91                 // String config is marked non-null but is null
      42: invokespecial #89                 // Method java/lang/IllegalArgumentException."<init>":(Ljava/lang/String;)V
      45: athrow
      46: aload         4
      48: ifnonnull     61
      51: new           #87                 // class java/lang/IllegalArgumentException
      54: dup
      55: ldc           #92                 // String templateVariables is marked non-null but is null
      57: invokespecial #89                 // Method java/lang/IllegalArgumentException."<init>":(Ljava/lang/String;)V
      60: athrow
      61: aload         5
      63: ifnonnull     76
      66: new           #87                 // class java/lang/IllegalArgumentException
      69: dup
      70: ldc           #93                 // String idConverters is marked non-null but is null
      72: invokespecial #89                 // Method java/lang/IllegalArgumentException."<init>":(Ljava/lang/String;)V
      75: athrow
      76: aload_0
      77: aload_1
      78: putfield      #1                  // Field repositories:Lorg/springframework/data/repository/support/Repositories;
      81: aload_0
      82: aload_2
      83: putfield      #3                  // Field mappings:Lorg/springframework/data/rest/core/mapping/ResourceMappings;
      86: aload_0
      87: aload_3
      88: putfield      #7                  // Field config:Lorg/springframework/data/rest/core/config/RepositoryRestConfiguration;
      91: aload_0
      92: aload         4
      94: putfield      #65                 // Field templateVariables:Lorg/springframework/data/rest/webmvc/support/PagingAndSortingTemplateVariables;
      97: aload_0
      98: aload         5
     100: putfield      #26                 // Field idConverters:Lorg/springframework/data/rest/core/util/Java8PluginRegistry;
     103: return

  public boolean supports(java.lang.Object);
    Code:
       0: aload_0
       1: aload_1
       2: checkcast     #94                 // class java/lang/Class
       5: invokevirtual #95                 // Method supports:(Ljava/lang/Class;)Z
       8: ireturn
}
