Compiled from "LRUSoftCache.java"
public class org.apache.camel.util.LRUSoftCache<K, V> extends org.apache.camel.util.LRUCache<K, V> {
  public org.apache.camel.util.LRUSoftCache(int);
    Code:
       0: aload_0
       1: bipush        16
       3: iload_1
       4: invokespecial #11                 // Method "<init>":(II)V
       7: return

  public org.apache.camel.util.LRUSoftCache(int, int);
    Code:
       0: aload_0
       1: iload_1
       2: iload_2
       3: iconst_0
       4: invokespecial #19                 // Method "<init>":(IIZ)V
       7: return

  public org.apache.camel.util.LRUSoftCache(int, int, boolean);
    Code:
       0: aload_0
       1: iload_1
       2: iload_2
       3: iload_3
       4: iconst_1
       5: iconst_0
       6: iconst_0
       7: invokespecial #23                 // Method org/apache/camel/util/LRUCache."<init>":(IIZZZZ)V
      10: return

  public java.lang.String toString();
    Code:
       0: new           #29                 // class java/lang/StringBuilder
       3: dup
       4: invokespecial #32                 // Method java/lang/StringBuilder."<init>":()V
       7: ldc           #34                 // String LRUSoftCache@
       9: invokevirtual #38                 // Method java/lang/StringBuilder.append:(Ljava/lang/String;)Ljava/lang/StringBuilder;
      12: aload_0
      13: invokestatic  #44                 // Method org/apache/camel/util/ObjectHelper.getIdentityHashCode:(Ljava/lang/Object;)Ljava/lang/String;
      16: invokevirtual #38                 // Method java/lang/StringBuilder.append:(Ljava/lang/String;)Ljava/lang/StringBuilder;
      19: invokevirtual #46                 // Method java/lang/StringBuilder.toString:()Ljava/lang/String;
      22: areturn
}
