Compiled from "DependencyInfo.java"
public final class org.jboss.modules.management.DependencyInfo {
  private final java.lang.String dependencyType;

  private final java.lang.String exportFilter;

  private final java.lang.String importFilter;

  private final org.jboss.modules.management.ModuleLoaderMXBean moduleLoader;

  private final java.lang.String moduleName;

  private final boolean optional;

  private final java.lang.String localLoader;

  private final java.util.List<java.lang.String> localLoaderPaths;

  public org.jboss.modules.management.DependencyInfo(java.lang.String, java.lang.String, java.lang.String, org.jboss.modules.management.ModuleLoaderMXBean, java.lang.String, boolean, java.lang.String, java.util.List<java.lang.String>);
    Code:
       0: aload_0
       1: invokespecial #1                  // Method java/lang/Object."<init>":()V
       4: aload_0
       5: aload_1
       6: putfield      #2                  // Field dependencyType:Ljava/lang/String;
       9: aload_0
      10: aload_2
      11: putfield      #3                  // Field exportFilter:Ljava/lang/String;
      14: aload_0
      15: aload_3
      16: putfield      #4                  // Field importFilter:Ljava/lang/String;
      19: aload_0
      20: aload         4
      22: putfield      #5                  // Field moduleLoader:Lorg/jboss/modules/management/ModuleLoaderMXBean;
      25: aload_0
      26: aload         5
      28: putfield      #6                  // Field moduleName:Ljava/lang/String;
      31: aload_0
      32: iload         6
      34: putfield      #7                  // Field optional:Z
      37: aload_0
      38: aload         7
      40: putfield      #8                  // Field localLoader:Ljava/lang/String;
      43: aload_0
      44: aload         8
      46: putfield      #9                  // Field localLoaderPaths:Ljava/util/List;
      49: return

  public java.lang.String getDependencyType();
    Code:
       0: aload_0
       1: getfield      #2                  // Field dependencyType:Ljava/lang/String;
       4: areturn

  public java.lang.String getExportFilter();
    Code:
       0: aload_0
       1: getfield      #3                  // Field exportFilter:Ljava/lang/String;
       4: areturn

  public java.lang.String getImportFilter();
    Code:
       0: aload_0
       1: getfield      #4                  // Field importFilter:Ljava/lang/String;
       4: areturn

  public org.jboss.modules.management.ModuleLoaderMXBean getModuleLoader();
    Code:
       0: aload_0
       1: getfield      #5                  // Field moduleLoader:Lorg/jboss/modules/management/ModuleLoaderMXBean;
       4: areturn

  public java.lang.String getModuleName();
    Code:
       0: aload_0
       1: getfield      #6                  // Field moduleName:Ljava/lang/String;
       4: areturn

  public boolean isOptional();
    Code:
       0: aload_0
       1: getfield      #7                  // Field optional:Z
       4: ireturn

  public java.lang.String getLocalLoader();
    Code:
       0: aload_0
       1: getfield      #8                  // Field localLoader:Ljava/lang/String;
       4: areturn

  public java.util.List<java.lang.String> getLocalLoaderPaths();
    Code:
       0: aload_0
       1: getfield      #9                  // Field localLoaderPaths:Ljava/util/List;
       4: areturn
}
