Compiled from "Checksum.java"
public class org.jreleaser.cli.Checksum extends org.jreleaser.cli.AbstractPlatformAwareModelCommand {
  org.jreleaser.cli.Checksum$Composite composite;

  public org.jreleaser.cli.Checksum();
    Code:
       0: aload_0
       1: invokespecial #1                  // Method org/jreleaser/cli/AbstractPlatformAwareModelCommand."<init>":()V
       4: return

  protected void doExecute(org.jreleaser.model.internal.JReleaserContext);
    Code:
       0: aconst_null
       1: aload_0
       2: getfield      #2                  // Field composite:Lorg/jreleaser/cli/Checksum$Composite;
       5: if_acmpeq     38
       8: aload_1
       9: aload_0
      10: aload_0
      11: getfield      #2                  // Field composite:Lorg/jreleaser/cli/Checksum$Composite;
      14: invokevirtual #3                  // Method org/jreleaser/cli/Checksum$Composite.includedDistributions:()[Ljava/lang/String;
      17: invokevirtual #4                  // Method collectEntries:([Ljava/lang/String;)Ljava/util/List;
      20: invokevirtual #5                  // Method org/jreleaser/model/internal/JReleaserContext.setIncludedDistributions:(Ljava/util/List;)V
      23: aload_1
      24: aload_0
      25: aload_0
      26: getfield      #2                  // Field composite:Lorg/jreleaser/cli/Checksum$Composite;
      29: invokevirtual #6                  // Method org/jreleaser/cli/Checksum$Composite.excludedDistributions:()[Ljava/lang/String;
      32: invokevirtual #4                  // Method collectEntries:([Ljava/lang/String;)Ljava/util/List;
      35: invokevirtual #7                  // Method org/jreleaser/model/internal/JReleaserContext.setExcludedDistributions:(Ljava/util/List;)V
      38: aload_1
      39: invokestatic  #8                  // Method org/jreleaser/workflow/Workflows.checksum:(Lorg/jreleaser/model/internal/JReleaserContext;)Lorg/jreleaser/workflow/Workflow;
      42: invokeinterface #9,  1            // InterfaceMethod org/jreleaser/workflow/Workflow.execute:()V
      47: return
}
