Compiled from "DOMSemantics.java"
public final class org.apache.axiom.dom.DOMSemantics implements org.apache.axiom.core.Semantics {
  private static final java.util.Set<org.apache.axiom.core.NodeType> parentNodeTypes;

  public static final org.apache.axiom.dom.DOMSemantics INSTANCE;

  public static final org.apache.axiom.core.AttributeMatcher DOM1_ATTRIBUTE_MATCHER;

  public static final org.apache.axiom.core.AttributeMatcher DOM2_ATTRIBUTE_MATCHER;

  public static final org.apache.axiom.core.AttributeMatcher NAMESPACE_DECLARATION_MATCHER;

  public static final org.apache.axiom.core.ClonePolicy<java.lang.Void> DEEP_CLONE;

  public static final org.apache.axiom.core.ClonePolicy<java.lang.Void> SHALLOW_CLONE;

  static {};
    Code:
       0: getstatic     #24                 // Field org/apache/axiom/core/NodeType.DOCUMENT:Lorg/apache/axiom/core/NodeType;
       3: getstatic     #30                 // Field org/apache/axiom/core/NodeType.NS_AWARE_ELEMENT:Lorg/apache/axiom/core/NodeType;
       6: getstatic     #33                 // Field org/apache/axiom/core/NodeType.NS_UNAWARE_ELEMENT:Lorg/apache/axiom/core/NodeType;
       9: getstatic     #36                 // Field org/apache/axiom/core/NodeType.DOCUMENT_FRAGMENT:Lorg/apache/axiom/core/NodeType;
      12: invokestatic  #39                 // Method java/util/EnumSet.of:(Ljava/lang/Enum;Ljava/lang/Enum;Ljava/lang/Enum;Ljava/lang/Enum;)Ljava/util/EnumSet;
      15: putstatic     #45                 // Field parentNodeTypes:Ljava/util/Set;
      18: new           #1                  // class org/apache/axiom/dom/DOMSemantics
      21: dup
      22: invokespecial #47                 // Method "<init>":()V
      25: putstatic     #50                 // Field INSTANCE:Lorg/apache/axiom/dom/DOMSemantics;
      28: new           #52                 // class org/apache/axiom/dom/DOMSemantics$1
      31: dup
      32: invokespecial #54                 // Method org/apache/axiom/dom/DOMSemantics$1."<init>":()V
      35: putstatic     #55                 // Field DOM1_ATTRIBUTE_MATCHER:Lorg/apache/axiom/core/AttributeMatcher;
      38: new           #57                 // class org/apache/axiom/core/NSAwareAttributeMatcher
      41: dup
      42: getstatic     #50                 // Field INSTANCE:Lorg/apache/axiom/dom/DOMSemantics;
      45: iconst_1
      46: iconst_1
      47: invokespecial #59                 // Method org/apache/axiom/core/NSAwareAttributeMatcher."<init>":(Lorg/apache/axiom/core/Semantics;ZZ)V
      50: putstatic     #62                 // Field DOM2_ATTRIBUTE_MATCHER:Lorg/apache/axiom/core/AttributeMatcher;
      53: new           #64                 // class org/apache/axiom/core/NamespaceDeclarationMatcher
      56: dup
      57: getstatic     #50                 // Field INSTANCE:Lorg/apache/axiom/dom/DOMSemantics;
      60: invokespecial #66                 // Method org/apache/axiom/core/NamespaceDeclarationMatcher."<init>":(Lorg/apache/axiom/core/Semantics;)V
      63: putstatic     #69                 // Field NAMESPACE_DECLARATION_MATCHER:Lorg/apache/axiom/core/AttributeMatcher;
      66: new           #71                 // class org/apache/axiom/dom/DOMSemantics$2
      69: dup
      70: invokespecial #73                 // Method org/apache/axiom/dom/DOMSemantics$2."<init>":()V
      73: putstatic     #74                 // Field DEEP_CLONE:Lorg/apache/axiom/core/ClonePolicy;
      76: new           #76                 // class org/apache/axiom/dom/DOMSemantics$3
      79: dup
      80: invokespecial #78                 // Method org/apache/axiom/dom/DOMSemantics$3."<init>":()V
      83: putstatic     #79                 // Field SHALLOW_CLONE:Lorg/apache/axiom/core/ClonePolicy;
      86: return

  private org.apache.axiom.dom.DOMSemantics();
    Code:
       0: aload_0
       1: invokespecial #84                 // Method java/lang/Object."<init>":()V
       4: return

  public org.apache.axiom.core.DetachPolicy getDetachPolicy();
    Code:
       0: getstatic     #88                 // Field org/apache/axiom/core/DetachPolicy.SAME_DOCUMENT:Lorg/apache/axiom/core/DetachPolicy;
       3: areturn

  public boolean isUseStrictNamespaceLookup();
    Code:
       0: iconst_0
       1: ireturn

  public boolean isParentNode(org.apache.axiom.core.NodeType);
    Code:
       0: getstatic     #45                 // Field parentNodeTypes:Ljava/util/Set;
       3: aload_1
       4: invokeinterface #98,  2           // InterfaceMethod java/util/Set.contains:(Ljava/lang/Object;)Z
       9: ireturn

  public java.lang.RuntimeException toUncheckedException(org.apache.axiom.core.CoreModelException);
    Code:
       0: new           #107                // class java/lang/IllegalArgumentException
       3: dup
       4: new           #109                // class java/lang/StringBuilder
       7: dup
       8: ldc           #111                // String Don\'t know how to translate
      10: invokespecial #113                // Method java/lang/StringBuilder."<init>":(Ljava/lang/String;)V
      13: aload_1
      14: invokevirtual #116                // Method java/lang/Object.getClass:()Ljava/lang/Class;
      17: invokevirtual #120                // Method java/lang/Class.getName:()Ljava/lang/String;
      20: invokevirtual #126                // Method java/lang/StringBuilder.append:(Ljava/lang/String;)Ljava/lang/StringBuilder;
      23: invokevirtual #130                // Method java/lang/StringBuilder.toString:()Ljava/lang/String;
      26: invokespecial #133                // Method java/lang/IllegalArgumentException."<init>":(Ljava/lang/String;)V
      29: athrow
}
