Compiled from "SubConfig.kt"
public abstract class nz.co.trademe.konfigure.SubConfig implements nz.co.trademe.konfigure.api.ConfigRegistry {
  private final nz.co.trademe.konfigure.api.ConfigRegistry parent;

  public nz.co.trademe.konfigure.SubConfig(nz.co.trademe.konfigure.api.ConfigRegistry);
    Code:
       0: aload_1
       1: ldc           #11                 // String parent
       3: invokestatic  #17                 // Method kotlin/jvm/internal/Intrinsics.checkNotNullParameter:(Ljava/lang/Object;Ljava/lang/String;)V
       6: aload_0
       7: invokespecial #20                 // Method java/lang/Object."<init>":()V
      10: aload_0
      11: aload_1
      12: putfield      #23                 // Field parent:Lnz/co/trademe/konfigure/api/ConfigRegistry;
      15: return

  public nz.co.trademe.konfigure.api.ConfigRegistry getParent();
    Code:
       0: aload_0
       1: getfield      #23                 // Field parent:Lnz/co/trademe/konfigure/api/ConfigRegistry;
       4: areturn

  public <T> T getValueOf(nz.co.trademe.konfigure.model.ConfigItem<T>, kotlin.reflect.KClass<T>);
    Code:
       0: aload_1
       1: ldc           #32                 // String item
       3: invokestatic  #17                 // Method kotlin/jvm/internal/Intrinsics.checkNotNullParameter:(Ljava/lang/Object;Ljava/lang/String;)V
       6: aload_2
       7: ldc           #34                 // String itemClass
       9: invokestatic  #17                 // Method kotlin/jvm/internal/Intrinsics.checkNotNullParameter:(Ljava/lang/Object;Ljava/lang/String;)V
      12: aload_0
      13: getfield      #23                 // Field parent:Lnz/co/trademe/konfigure/api/ConfigRegistry;
      16: aload_1
      17: aload_2
      18: invokeinterface #36,  3           // InterfaceMethod nz/co/trademe/konfigure/api/ConfigRegistry.getValueOf:(Lnz/co/trademe/konfigure/model/ConfigItem;Lkotlin/reflect/KClass;)Ljava/lang/Object;
      23: areturn

  public <T> void registerItem(nz.co.trademe.konfigure.model.ConfigItem<T>);
    Code:
       0: aload_1
       1: ldc           #32                 // String item
       3: invokestatic  #17                 // Method kotlin/jvm/internal/Intrinsics.checkNotNullParameter:(Ljava/lang/Object;Ljava/lang/String;)V
       6: aload_0
       7: getfield      #23                 // Field parent:Lnz/co/trademe/konfigure/api/ConfigRegistry;
      10: aload_1
      11: invokeinterface #43,  2           // InterfaceMethod nz/co/trademe/konfigure/api/ConfigRegistry.registerItem:(Lnz/co/trademe/konfigure/model/ConfigItem;)V
      16: return

  public <T> void setValueOf(nz.co.trademe.konfigure.model.ConfigItem<T>, kotlin.reflect.KClass<T>, T);
    Code:
       0: aload_1
       1: ldc           #32                 // String item
       3: invokestatic  #17                 // Method kotlin/jvm/internal/Intrinsics.checkNotNullParameter:(Ljava/lang/Object;Ljava/lang/String;)V
       6: aload_2
       7: ldc           #34                 // String itemClass
       9: invokestatic  #17                 // Method kotlin/jvm/internal/Intrinsics.checkNotNullParameter:(Ljava/lang/Object;Ljava/lang/String;)V
      12: aload_3
      13: ldc           #48                 // String newValue
      15: invokestatic  #17                 // Method kotlin/jvm/internal/Intrinsics.checkNotNullParameter:(Ljava/lang/Object;Ljava/lang/String;)V
      18: aload_0
      19: getfield      #23                 // Field parent:Lnz/co/trademe/konfigure/api/ConfigRegistry;
      22: aload_1
      23: aload_2
      24: aload_3
      25: invokeinterface #50,  4           // InterfaceMethod nz/co/trademe/konfigure/api/ConfigRegistry.setValueOf:(Lnz/co/trademe/konfigure/model/ConfigItem;Lkotlin/reflect/KClass;Ljava/lang/Object;)V
      30: return

  public abstract java.lang.String getGroup();
}
