Compiled from "DistributedPubSubMessageSerializer.scala"
public final class akka.cluster.pubsub.protobuf.DistributedPubSubMessageSerializer$$anonfun$1 extends scala.runtime.AbstractFunction1<byte[], akka.cluster.pubsub.DistributedPubSubMediator$Internal$Status> implements scala.Serializable {
  public static final long serialVersionUID;

  private final akka.cluster.pubsub.protobuf.DistributedPubSubMessageSerializer $outer;

  public final akka.cluster.pubsub.DistributedPubSubMediator$Internal$Status apply(byte[]);
    Code:
       0: aload_0
       1: getfield      #20                 // Field $outer:Lakka/cluster/pubsub/protobuf/DistributedPubSubMessageSerializer;
       4: aload_1
       5: invokevirtual #23                 // Method akka/cluster/pubsub/protobuf/DistributedPubSubMessageSerializer.akka$cluster$pubsub$protobuf$DistributedPubSubMessageSerializer$$statusFromBinary:([B)Lakka/cluster/pubsub/DistributedPubSubMediator$Internal$Status;
       8: areturn

  public final java.lang.Object apply(java.lang.Object);
    Code:
       0: aload_0
       1: aload_1
       2: checkcast     #29                 // class "[B"
       5: invokevirtual #31                 // Method apply:([B)Lakka/cluster/pubsub/DistributedPubSubMediator$Internal$Status;
       8: areturn

  public akka.cluster.pubsub.protobuf.DistributedPubSubMessageSerializer$$anonfun$1(akka.cluster.pubsub.protobuf.DistributedPubSubMessageSerializer);
    Code:
       0: aload_1
       1: ifnonnull     6
       4: aconst_null
       5: athrow
       6: aload_0
       7: aload_1
       8: putfield      #20                 // Field $outer:Lakka/cluster/pubsub/protobuf/DistributedPubSubMessageSerializer;
      11: aload_0
      12: invokespecial #38                 // Method scala/runtime/AbstractFunction1."<init>":()V
      15: return
}
