Compiled from "Settings.java"
public final class org.sonarsource.sonarlint.shaded.org.sonarqube.ws.Settings$Field$Builder extends com.google.protobuf.GeneratedMessageV3$Builder<org.sonarsource.sonarlint.shaded.org.sonarqube.ws.Settings$Field$Builder> implements org.sonarsource.sonarlint.shaded.org.sonarqube.ws.Settings$FieldOrBuilder {
  private int bitField0_;

  private java.lang.Object key_;

  private java.lang.Object name_;

  private java.lang.Object description_;

  private int type_;

  private com.google.protobuf.LazyStringList options_;

  public static final com.google.protobuf.Descriptors$Descriptor getDescriptor();
    Code:
       0: invokestatic  #69                 // Method org/sonarsource/sonarlint/shaded/org/sonarqube/ws/Settings.access$7700:()Lcom/google/protobuf/Descriptors$Descriptor;
       3: areturn

  protected com.google.protobuf.GeneratedMessageV3$FieldAccessorTable internalGetFieldAccessorTable();
    Code:
       0: invokestatic  #74                 // Method org/sonarsource/sonarlint/shaded/org/sonarqube/ws/Settings.access$7800:()Lcom/google/protobuf/GeneratedMessageV3$FieldAccessorTable;
       3: ldc           #20                 // class org/sonarsource/sonarlint/shaded/org/sonarqube/ws/Settings$Field
       5: ldc           #2                  // class org/sonarsource/sonarlint/shaded/org/sonarqube/ws/Settings$Field$Builder
       7: invokevirtual #78                 // Method com/google/protobuf/GeneratedMessageV3$FieldAccessorTable.ensureFieldAccessorsInitialized:(Ljava/lang/Class;Ljava/lang/Class;)Lcom/google/protobuf/GeneratedMessageV3$FieldAccessorTable;
      10: areturn

  private org.sonarsource.sonarlint.shaded.org.sonarqube.ws.Settings$Field$Builder();
    Code:
       0: aload_0
       1: invokespecial #84                 // Method com/google/protobuf/GeneratedMessageV3$Builder."<init>":()V
       4: aload_0
       5: ldc           #86                 // String
       7: putfield      #88                 // Field key_:Ljava/lang/Object;
      10: aload_0
      11: ldc           #86                 // String
      13: putfield      #90                 // Field name_:Ljava/lang/Object;
      16: aload_0
      17: ldc           #86                 // String
      19: putfield      #92                 // Field description_:Ljava/lang/Object;
      22: aload_0
      23: iconst_0
      24: putfield      #94                 // Field type_:I
      27: aload_0
      28: getstatic     #99                 // Field com/google/protobuf/LazyStringArrayList.EMPTY:Lcom/google/protobuf/LazyStringList;
      31: putfield      #101                // Field options_:Lcom/google/protobuf/LazyStringList;
      34: aload_0
      35: invokespecial #104                // Method maybeForceBuilderInitialization:()V
      38: return

  private org.sonarsource.sonarlint.shaded.org.sonarqube.ws.Settings$Field$Builder(com.google.protobuf.GeneratedMessageV3$BuilderParent);
    Code:
       0: aload_0
       1: aload_1
       2: invokespecial #107                // Method com/google/protobuf/GeneratedMessageV3$Builder."<init>":(Lcom/google/protobuf/GeneratedMessageV3$BuilderParent;)V
       5: aload_0
       6: ldc           #86                 // String
       8: putfield      #88                 // Field key_:Ljava/lang/Object;
      11: aload_0
      12: ldc           #86                 // String
      14: putfield      #90                 // Field name_:Ljava/lang/Object;
      17: aload_0
      18: ldc           #86                 // String
      20: putfield      #92                 // Field description_:Ljava/lang/Object;
      23: aload_0
      24: iconst_0
      25: putfield      #94                 // Field type_:I
      28: aload_0
      29: getstatic     #99                 // Field com/google/protobuf/LazyStringArrayList.EMPTY:Lcom/google/protobuf/LazyStringList;
      32: putfield      #101                // Field options_:Lcom/google/protobuf/LazyStringList;
      35: aload_0
      36: invokespecial #104                // Method maybeForceBuilderInitialization:()V
      39: return

  private void maybeForceBuilderInitialization();
    Code:
       0: invokestatic  #113                // Method org/sonarsource/sonarlint/shaded/org/sonarqube/ws/Settings$Field.access$8100:()Z
       3: ifeq          6
       6: return

  public org.sonarsource.sonarlint.shaded.org.sonarqube.ws.Settings$Field$Builder clear();
    Code:
       0: aload_0
       1: invokespecial #118                // Method com/google/protobuf/GeneratedMessageV3$Builder.clear:()Lcom/google/protobuf/GeneratedMessageV3$Builder;
       4: pop
       5: aload_0
       6: ldc           #86                 // String
       8: putfield      #88                 // Field key_:Ljava/lang/Object;
      11: aload_0
      12: ldc           #86                 // String
      14: putfield      #90                 // Field name_:Ljava/lang/Object;
      17: aload_0
      18: ldc           #86                 // String
      20: putfield      #92                 // Field description_:Ljava/lang/Object;
      23: aload_0
      24: iconst_0
      25: putfield      #94                 // Field type_:I
      28: aload_0
      29: getstatic     #99                 // Field com/google/protobuf/LazyStringArrayList.EMPTY:Lcom/google/protobuf/LazyStringList;
      32: putfield      #101                // Field options_:Lcom/google/protobuf/LazyStringList;
      35: aload_0
      36: aload_0
      37: getfield      #120                // Field bitField0_:I
      40: bipush        -2
      42: iand
      43: putfield      #120                // Field bitField0_:I
      46: aload_0
      47: areturn

  public com.google.protobuf.Descriptors$Descriptor getDescriptorForType();
    Code:
       0: invokestatic  #69                 // Method org/sonarsource/sonarlint/shaded/org/sonarqube/ws/Settings.access$7700:()Lcom/google/protobuf/Descriptors$Descriptor;
       3: areturn

  public org.sonarsource.sonarlint.shaded.org.sonarqube.ws.Settings$Field getDefaultInstanceForType();
    Code:
       0: invokestatic  #126                // Method org/sonarsource/sonarlint/shaded/org/sonarqube/ws/Settings$Field.getDefaultInstance:()Lorg/sonarsource/sonarlint/shaded/org/sonarqube/ws/Settings$Field;
       3: areturn

  public org.sonarsource.sonarlint.shaded.org.sonarqube.ws.Settings$Field build();
    Code:
       0: aload_0
       1: invokevirtual #130                // Method buildPartial:()Lorg/sonarsource/sonarlint/shaded/org/sonarqube/ws/Settings$Field;
       4: astore_1
       5: aload_1
       6: invokevirtual #133                // Method org/sonarsource/sonarlint/shaded/org/sonarqube/ws/Settings$Field.isInitialized:()Z
       9: ifne          17
      12: aload_1
      13: invokestatic  #137                // Method newUninitializedMessageException:(Lcom/google/protobuf/Message;)Lcom/google/protobuf/UninitializedMessageException;
      16: athrow
      17: aload_1
      18: areturn

  public org.sonarsource.sonarlint.shaded.org.sonarqube.ws.Settings$Field buildPartial();
    Code:
       0: new           #20                 // class org/sonarsource/sonarlint/shaded/org/sonarqube/ws/Settings$Field
       3: dup
       4: aload_0
       5: aconst_null
       6: invokespecial #142                // Method org/sonarsource/sonarlint/shaded/org/sonarqube/ws/Settings$Field."<init>":(Lcom/google/protobuf/GeneratedMessageV3$Builder;Lorg/sonarsource/sonarlint/shaded/org/sonarqube/ws/Settings$1;)V
       9: astore_1
      10: aload_0
      11: getfield      #120                // Field bitField0_:I
      14: istore_2
      15: aload_1
      16: aload_0
      17: getfield      #88                 // Field key_:Ljava/lang/Object;
      20: invokestatic  #146                // Method org/sonarsource/sonarlint/shaded/org/sonarqube/ws/Settings$Field.access$8302:(Lorg/sonarsource/sonarlint/shaded/org/sonarqube/ws/Settings$Field;Ljava/lang/Object;)Ljava/lang/Object;
      23: pop
      24: aload_1
      25: aload_0
      26: getfield      #90                 // Field name_:Ljava/lang/Object;
      29: invokestatic  #149                // Method org/sonarsource/sonarlint/shaded/org/sonarqube/ws/Settings$Field.access$8402:(Lorg/sonarsource/sonarlint/shaded/org/sonarqube/ws/Settings$Field;Ljava/lang/Object;)Ljava/lang/Object;
      32: pop
      33: aload_1
      34: aload_0
      35: getfield      #92                 // Field description_:Ljava/lang/Object;
      38: invokestatic  #152                // Method org/sonarsource/sonarlint/shaded/org/sonarqube/ws/Settings$Field.access$8502:(Lorg/sonarsource/sonarlint/shaded/org/sonarqube/ws/Settings$Field;Ljava/lang/Object;)Ljava/lang/Object;
      41: pop
      42: aload_1
      43: aload_0
      44: getfield      #94                 // Field type_:I
      47: invokestatic  #156                // Method org/sonarsource/sonarlint/shaded/org/sonarqube/ws/Settings$Field.access$8602:(Lorg/sonarsource/sonarlint/shaded/org/sonarqube/ws/Settings$Field;I)I
      50: pop
      51: aload_0
      52: getfield      #120                // Field bitField0_:I
      55: iconst_1
      56: iand
      57: ifeq          84
      60: aload_0
      61: aload_0
      62: getfield      #101                // Field options_:Lcom/google/protobuf/LazyStringList;
      65: invokeinterface #162,  1          // InterfaceMethod com/google/protobuf/LazyStringList.getUnmodifiableView:()Lcom/google/protobuf/LazyStringList;
      70: putfield      #101                // Field options_:Lcom/google/protobuf/LazyStringList;
      73: aload_0
      74: aload_0
      75: getfield      #120                // Field bitField0_:I
      78: bipush        -2
      80: iand
      81: putfield      #120                // Field bitField0_:I
      84: aload_1
      85: aload_0
      86: getfield      #101                // Field options_:Lcom/google/protobuf/LazyStringList;
      89: invokestatic  #166                // Method org/sonarsource/sonarlint/shaded/org/sonarqube/ws/Settings$Field.access$8702:(Lorg/sonarsource/sonarlint/shaded/org/sonarqube/ws/Settings$Field;Lcom/google/protobuf/LazyStringList;)Lcom/google/protobuf/LazyStringList;
      92: pop
      93: aload_0
      94: invokevirtual #169                // Method onBuilt:()V
      97: aload_1
      98: areturn

  public org.sonarsource.sonarlint.shaded.org.sonarqube.ws.Settings$Field$Builder clone();
    Code:
       0: aload_0
       1: invokespecial #173                // Method com/google/protobuf/GeneratedMessageV3$Builder.clone:()Lcom/google/protobuf/GeneratedMessageV3$Builder;
       4: checkcast     #2                  // class org/sonarsource/sonarlint/shaded/org/sonarqube/ws/Settings$Field$Builder
       7: areturn

  public org.sonarsource.sonarlint.shaded.org.sonarqube.ws.Settings$Field$Builder setField(com.google.protobuf.Descriptors$FieldDescriptor, java.lang.Object);
    Code:
       0: aload_0
       1: aload_1
       2: aload_2
       3: invokespecial #178                // Method com/google/protobuf/GeneratedMessageV3$Builder.setField:(Lcom/google/protobuf/Descriptors$FieldDescriptor;Ljava/lang/Object;)Lcom/google/protobuf/GeneratedMessageV3$Builder;
       6: checkcast     #2                  // class org/sonarsource/sonarlint/shaded/org/sonarqube/ws/Settings$Field$Builder
       9: areturn

  public org.sonarsource.sonarlint.shaded.org.sonarqube.ws.Settings$Field$Builder clearField(com.google.protobuf.Descriptors$FieldDescriptor);
    Code:
       0: aload_0
       1: aload_1
       2: invokespecial #186                // Method com/google/protobuf/GeneratedMessageV3$Builder.clearField:(Lcom/google/protobuf/Descriptors$FieldDescriptor;)Lcom/google/protobuf/GeneratedMessageV3$Builder;
       5: checkcast     #2                  // class org/sonarsource/sonarlint/shaded/org/sonarqube/ws/Settings$Field$Builder
       8: areturn

  public org.sonarsource.sonarlint.shaded.org.sonarqube.ws.Settings$Field$Builder clearOneof(com.google.protobuf.Descriptors$OneofDescriptor);
    Code:
       0: aload_0
       1: aload_1
       2: invokespecial #191                // Method com/google/protobuf/GeneratedMessageV3$Builder.clearOneof:(Lcom/google/protobuf/Descriptors$OneofDescriptor;)Lcom/google/protobuf/GeneratedMessageV3$Builder;
       5: checkcast     #2                  // class org/sonarsource/sonarlint/shaded/org/sonarqube/ws/Settings$Field$Builder
       8: areturn

  public org.sonarsource.sonarlint.shaded.org.sonarqube.ws.Settings$Field$Builder setRepeatedField(com.google.protobuf.Descriptors$FieldDescriptor, int, java.lang.Object);
    Code:
       0: aload_0
       1: aload_1
       2: iload_2
       3: aload_3
       4: invokespecial #198                // Method com/google/protobuf/GeneratedMessageV3$Builder.setRepeatedField:(Lcom/google/protobuf/Descriptors$FieldDescriptor;ILjava/lang/Object;)Lcom/google/protobuf/GeneratedMessageV3$Builder;
       7: checkcast     #2                  // class org/sonarsource/sonarlint/shaded/org/sonarqube/ws/Settings$Field$Builder
      10: areturn

  public org.sonarsource.sonarlint.shaded.org.sonarqube.ws.Settings$Field$Builder addRepeatedField(com.google.protobuf.Descriptors$FieldDescriptor, java.lang.Object);
    Code:
       0: aload_0
       1: aload_1
       2: aload_2
       3: invokespecial #202                // Method com/google/protobuf/GeneratedMessageV3$Builder.addRepeatedField:(Lcom/google/protobuf/Descriptors$FieldDescriptor;Ljava/lang/Object;)Lcom/google/protobuf/GeneratedMessageV3$Builder;
       6: checkcast     #2                  // class org/sonarsource/sonarlint/shaded/org/sonarqube/ws/Settings$Field$Builder
       9: areturn

  public org.sonarsource.sonarlint.shaded.org.sonarqube.ws.Settings$Field$Builder mergeFrom(com.google.protobuf.Message);
    Code:
       0: aload_1
       1: instanceof    #20                 // class org/sonarsource/sonarlint/shaded/org/sonarqube/ws/Settings$Field
       4: ifeq          16
       7: aload_0
       8: aload_1
       9: checkcast     #20                 // class org/sonarsource/sonarlint/shaded/org/sonarqube/ws/Settings$Field
      12: invokevirtual #207                // Method mergeFrom:(Lorg/sonarsource/sonarlint/shaded/org/sonarqube/ws/Settings$Field;)Lorg/sonarsource/sonarlint/shaded/org/sonarqube/ws/Settings$Field$Builder;
      15: areturn
      16: aload_0
      17: aload_1
      18: invokespecial #210                // Method com/google/protobuf/GeneratedMessageV3$Builder.mergeFrom:(Lcom/google/protobuf/Message;)Lcom/google/protobuf/AbstractMessage$Builder;
      21: pop
      22: aload_0
      23: areturn

  public org.sonarsource.sonarlint.shaded.org.sonarqube.ws.Settings$Field$Builder mergeFrom(org.sonarsource.sonarlint.shaded.org.sonarqube.ws.Settings$Field);
    Code:
       0: aload_1
       1: invokestatic  #126                // Method org/sonarsource/sonarlint/shaded/org/sonarqube/ws/Settings$Field.getDefaultInstance:()Lorg/sonarsource/sonarlint/shaded/org/sonarqube/ws/Settings$Field;
       4: if_acmpne     9
       7: aload_0
       8: areturn
       9: aload_1
      10: invokevirtual #216                // Method org/sonarsource/sonarlint/shaded/org/sonarqube/ws/Settings$Field.getKey:()Ljava/lang/String;
      13: invokevirtual #221                // Method java/lang/String.isEmpty:()Z
      16: ifne          31
      19: aload_0
      20: aload_1
      21: invokestatic  #225                // Method org/sonarsource/sonarlint/shaded/org/sonarqube/ws/Settings$Field.access$8300:(Lorg/sonarsource/sonarlint/shaded/org/sonarqube/ws/Settings$Field;)Ljava/lang/Object;
      24: putfield      #88                 // Field key_:Ljava/lang/Object;
      27: aload_0
      28: invokevirtual #228                // Method onChanged:()V
      31: aload_1
      32: invokevirtual #231                // Method org/sonarsource/sonarlint/shaded/org/sonarqube/ws/Settings$Field.getName:()Ljava/lang/String;
      35: invokevirtual #221                // Method java/lang/String.isEmpty:()Z
      38: ifne          53
      41: aload_0
      42: aload_1
      43: invokestatic  #234                // Method org/sonarsource/sonarlint/shaded/org/sonarqube/ws/Settings$Field.access$8400:(Lorg/sonarsource/sonarlint/shaded/org/sonarqube/ws/Settings$Field;)Ljava/lang/Object;
      46: putfield      #90                 // Field name_:Ljava/lang/Object;
      49: aload_0
      50: invokevirtual #228                // Method onChanged:()V
      53: aload_1
      54: invokevirtual #237                // Method org/sonarsource/sonarlint/shaded/org/sonarqube/ws/Settings$Field.getDescription:()Ljava/lang/String;
      57: invokevirtual #221                // Method java/lang/String.isEmpty:()Z
      60: ifne          75
      63: aload_0
      64: aload_1
      65: invokestatic  #240                // Method org/sonarsource/sonarlint/shaded/org/sonarqube/ws/Settings$Field.access$8500:(Lorg/sonarsource/sonarlint/shaded/org/sonarqube/ws/Settings$Field;)Ljava/lang/Object;
      68: putfield      #92                 // Field description_:Ljava/lang/Object;
      71: aload_0
      72: invokevirtual #228                // Method onChanged:()V
      75: aload_1
      76: invokestatic  #244                // Method org/sonarsource/sonarlint/shaded/org/sonarqube/ws/Settings$Field.access$8600:(Lorg/sonarsource/sonarlint/shaded/org/sonarqube/ws/Settings$Field;)I
      79: ifeq          91
      82: aload_0
      83: aload_1
      84: invokevirtual #248                // Method org/sonarsource/sonarlint/shaded/org/sonarqube/ws/Settings$Field.getTypeValue:()I
      87: invokevirtual #252                // Method setTypeValue:(I)Lorg/sonarsource/sonarlint/shaded/org/sonarqube/ws/Settings$Field$Builder;
      90: pop
      91: aload_1
      92: invokestatic  #256                // Method org/sonarsource/sonarlint/shaded/org/sonarqube/ws/Settings$Field.access$8700:(Lorg/sonarsource/sonarlint/shaded/org/sonarqube/ws/Settings$Field;)Lcom/google/protobuf/LazyStringList;
      95: invokeinterface #257,  1          // InterfaceMethod com/google/protobuf/LazyStringList.isEmpty:()Z
     100: ifne          159
     103: aload_0
     104: getfield      #101                // Field options_:Lcom/google/protobuf/LazyStringList;
     107: invokeinterface #257,  1          // InterfaceMethod com/google/protobuf/LazyStringList.isEmpty:()Z
     112: ifeq          137
     115: aload_0
     116: aload_1
     117: invokestatic  #256                // Method org/sonarsource/sonarlint/shaded/org/sonarqube/ws/Settings$Field.access$8700:(Lorg/sonarsource/sonarlint/shaded/org/sonarqube/ws/Settings$Field;)Lcom/google/protobuf/LazyStringList;
     120: putfield      #101                // Field options_:Lcom/google/protobuf/LazyStringList;
     123: aload_0
     124: aload_0
     125: getfield      #120                // Field bitField0_:I
     128: bipush        -2
     130: iand
     131: putfield      #120                // Field bitField0_:I
     134: goto          155
     137: aload_0
     138: invokespecial #260                // Method ensureOptionsIsMutable:()V
     141: aload_0
     142: getfield      #101                // Field options_:Lcom/google/protobuf/LazyStringList;
     145: aload_1
     146: invokestatic  #256                // Method org/sonarsource/sonarlint/shaded/org/sonarqube/ws/Settings$Field.access$8700:(Lorg/sonarsource/sonarlint/shaded/org/sonarqube/ws/Settings$Field;)Lcom/google/protobuf/LazyStringList;
     149: invokeinterface #264,  2          // InterfaceMethod com/google/protobuf/LazyStringList.addAll:(Ljava/util/Collection;)Z
     154: pop
     155: aload_0
     156: invokevirtual #228                // Method onChanged:()V
     159: aload_0
     160: aload_1
     161: invokestatic  #268                // Method org/sonarsource/sonarlint/shaded/org/sonarqube/ws/Settings$Field.access$8800:(Lorg/sonarsource/sonarlint/shaded/org/sonarqube/ws/Settings$Field;)Lcom/google/protobuf/UnknownFieldSet;
     164: invokevirtual #272                // Method mergeUnknownFields:(Lcom/google/protobuf/UnknownFieldSet;)Lorg/sonarsource/sonarlint/shaded/org/sonarqube/ws/Settings$Field$Builder;
     167: pop
     168: aload_0
     169: invokevirtual #228                // Method onChanged:()V
     172: aload_0
     173: areturn

  public final boolean isInitialized();
    Code:
       0: iconst_1
       1: ireturn

  public org.sonarsource.sonarlint.shaded.org.sonarqube.ws.Settings$Field$Builder mergeFrom(com.google.protobuf.CodedInputStream, com.google.protobuf.ExtensionRegistryLite) throws java.io.IOException;
    Code:
       0: aconst_null
       1: astore_3
       2: invokestatic  #281                // Method org/sonarsource/sonarlint/shaded/org/sonarqube/ws/Settings$Field.access$8900:()Lcom/google/protobuf/Parser;
       5: aload_1
       6: aload_2
       7: invokeinterface #287,  3          // InterfaceMethod com/google/protobuf/Parser.parsePartialFrom:(Lcom/google/protobuf/CodedInputStream;Lcom/google/protobuf/ExtensionRegistryLite;)Ljava/lang/Object;
      12: checkcast     #20                 // class org/sonarsource/sonarlint/shaded/org/sonarqube/ws/Settings$Field
      15: astore_3
      16: aload_3
      17: ifnull        61
      20: aload_0
      21: aload_3
      22: invokevirtual #207                // Method mergeFrom:(Lorg/sonarsource/sonarlint/shaded/org/sonarqube/ws/Settings$Field;)Lorg/sonarsource/sonarlint/shaded/org/sonarqube/ws/Settings$Field$Builder;
      25: pop
      26: goto          61
      29: astore        4
      31: aload         4
      33: invokevirtual #295                // Method com/google/protobuf/InvalidProtocolBufferException.getUnfinishedMessage:()Lcom/google/protobuf/MessageLite;
      36: checkcast     #20                 // class org/sonarsource/sonarlint/shaded/org/sonarqube/ws/Settings$Field
      39: astore_3
      40: aload         4
      42: invokevirtual #299                // Method com/google/protobuf/InvalidProtocolBufferException.unwrapIOException:()Ljava/io/IOException;
      45: athrow
      46: astore        5
      48: aload_3
      49: ifnull        58
      52: aload_0
      53: aload_3
      54: invokevirtual #207                // Method mergeFrom:(Lorg/sonarsource/sonarlint/shaded/org/sonarqube/ws/Settings$Field;)Lorg/sonarsource/sonarlint/shaded/org/sonarqube/ws/Settings$Field$Builder;
      57: pop
      58: aload         5
      60: athrow
      61: aload_0
      62: areturn
    Exception table:
       from    to  target type
           2    16    29   Class com/google/protobuf/InvalidProtocolBufferException
           2    16    46   any
          29    48    46   any

  public java.lang.String getKey();
    Code:
       0: aload_0
       1: getfield      #88                 // Field key_:Ljava/lang/Object;
       4: astore_1
       5: aload_1
       6: instanceof    #218                // class java/lang/String
       9: ifne          29
      12: aload_1
      13: checkcast     #310                // class com/google/protobuf/ByteString
      16: astore_2
      17: aload_2
      18: invokevirtual #313                // Method com/google/protobuf/ByteString.toStringUtf8:()Ljava/lang/String;
      21: astore_3
      22: aload_0
      23: aload_3
      24: putfield      #88                 // Field key_:Ljava/lang/Object;
      27: aload_3
      28: areturn
      29: aload_1
      30: checkcast     #218                // class java/lang/String
      33: areturn

  public com.google.protobuf.ByteString getKeyBytes();
    Code:
       0: aload_0
       1: getfield      #88                 // Field key_:Ljava/lang/Object;
       4: astore_1
       5: aload_1
       6: instanceof    #218                // class java/lang/String
       9: ifeq          27
      12: aload_1
      13: checkcast     #218                // class java/lang/String
      16: invokestatic  #326                // Method com/google/protobuf/ByteString.copyFromUtf8:(Ljava/lang/String;)Lcom/google/protobuf/ByteString;
      19: astore_2
      20: aload_0
      21: aload_2
      22: putfield      #88                 // Field key_:Ljava/lang/Object;
      25: aload_2
      26: areturn
      27: aload_1
      28: checkcast     #310                // class com/google/protobuf/ByteString
      31: areturn

  public org.sonarsource.sonarlint.shaded.org.sonarqube.ws.Settings$Field$Builder setKey(java.lang.String);
    Code:
       0: aload_1
       1: ifnonnull     12
       4: new           #331                // class java/lang/NullPointerException
       7: dup
       8: invokespecial #332                // Method java/lang/NullPointerException."<init>":()V
      11: athrow
      12: aload_0
      13: aload_1
      14: putfield      #88                 // Field key_:Ljava/lang/Object;
      17: aload_0
      18: invokevirtual #228                // Method onChanged:()V
      21: aload_0
      22: areturn

  public org.sonarsource.sonarlint.shaded.org.sonarqube.ws.Settings$Field$Builder clearKey();
    Code:
       0: aload_0
       1: invokestatic  #126                // Method org/sonarsource/sonarlint/shaded/org/sonarqube/ws/Settings$Field.getDefaultInstance:()Lorg/sonarsource/sonarlint/shaded/org/sonarqube/ws/Settings$Field;
       4: invokevirtual #216                // Method org/sonarsource/sonarlint/shaded/org/sonarqube/ws/Settings$Field.getKey:()Ljava/lang/String;
       7: putfield      #88                 // Field key_:Ljava/lang/Object;
      10: aload_0
      11: invokevirtual #228                // Method onChanged:()V
      14: aload_0
      15: areturn

  public org.sonarsource.sonarlint.shaded.org.sonarqube.ws.Settings$Field$Builder setKeyBytes(com.google.protobuf.ByteString);
    Code:
       0: aload_1
       1: ifnonnull     12
       4: new           #331                // class java/lang/NullPointerException
       7: dup
       8: invokespecial #332                // Method java/lang/NullPointerException."<init>":()V
      11: athrow
      12: aload_1
      13: invokestatic  #339                // Method org/sonarsource/sonarlint/shaded/org/sonarqube/ws/Settings$Field.access$9000:(Lcom/google/protobuf/ByteString;)V
      16: aload_0
      17: aload_1
      18: putfield      #88                 // Field key_:Ljava/lang/Object;
      21: aload_0
      22: invokevirtual #228                // Method onChanged:()V
      25: aload_0
      26: areturn

  public java.lang.String getName();
    Code:
       0: aload_0
       1: getfield      #90                 // Field name_:Ljava/lang/Object;
       4: astore_1
       5: aload_1
       6: instanceof    #218                // class java/lang/String
       9: ifne          29
      12: aload_1
      13: checkcast     #310                // class com/google/protobuf/ByteString
      16: astore_2
      17: aload_2
      18: invokevirtual #313                // Method com/google/protobuf/ByteString.toStringUtf8:()Ljava/lang/String;
      21: astore_3
      22: aload_0
      23: aload_3
      24: putfield      #90                 // Field name_:Ljava/lang/Object;
      27: aload_3
      28: areturn
      29: aload_1
      30: checkcast     #218                // class java/lang/String
      33: areturn

  public com.google.protobuf.ByteString getNameBytes();
    Code:
       0: aload_0
       1: getfield      #90                 // Field name_:Ljava/lang/Object;
       4: astore_1
       5: aload_1
       6: instanceof    #218                // class java/lang/String
       9: ifeq          27
      12: aload_1
      13: checkcast     #218                // class java/lang/String
      16: invokestatic  #326                // Method com/google/protobuf/ByteString.copyFromUtf8:(Ljava/lang/String;)Lcom/google/protobuf/ByteString;
      19: astore_2
      20: aload_0
      21: aload_2
      22: putfield      #90                 // Field name_:Ljava/lang/Object;
      25: aload_2
      26: areturn
      27: aload_1
      28: checkcast     #310                // class com/google/protobuf/ByteString
      31: areturn

  public org.sonarsource.sonarlint.shaded.org.sonarqube.ws.Settings$Field$Builder setName(java.lang.String);
    Code:
       0: aload_1
       1: ifnonnull     12
       4: new           #331                // class java/lang/NullPointerException
       7: dup
       8: invokespecial #332                // Method java/lang/NullPointerException."<init>":()V
      11: athrow
      12: aload_0
      13: aload_1
      14: putfield      #90                 // Field name_:Ljava/lang/Object;
      17: aload_0
      18: invokevirtual #228                // Method onChanged:()V
      21: aload_0
      22: areturn

  public org.sonarsource.sonarlint.shaded.org.sonarqube.ws.Settings$Field$Builder clearName();
    Code:
       0: aload_0
       1: invokestatic  #126                // Method org/sonarsource/sonarlint/shaded/org/sonarqube/ws/Settings$Field.getDefaultInstance:()Lorg/sonarsource/sonarlint/shaded/org/sonarqube/ws/Settings$Field;
       4: invokevirtual #231                // Method org/sonarsource/sonarlint/shaded/org/sonarqube/ws/Settings$Field.getName:()Ljava/lang/String;
       7: putfield      #90                 // Field name_:Ljava/lang/Object;
      10: aload_0
      11: invokevirtual #228                // Method onChanged:()V
      14: aload_0
      15: areturn

  public org.sonarsource.sonarlint.shaded.org.sonarqube.ws.Settings$Field$Builder setNameBytes(com.google.protobuf.ByteString);
    Code:
       0: aload_1
       1: ifnonnull     12
       4: new           #331                // class java/lang/NullPointerException
       7: dup
       8: invokespecial #332                // Method java/lang/NullPointerException."<init>":()V
      11: athrow
      12: aload_1
      13: invokestatic  #346                // Method org/sonarsource/sonarlint/shaded/org/sonarqube/ws/Settings$Field.access$9100:(Lcom/google/protobuf/ByteString;)V
      16: aload_0
      17: aload_1
      18: putfield      #90                 // Field name_:Ljava/lang/Object;
      21: aload_0
      22: invokevirtual #228                // Method onChanged:()V
      25: aload_0
      26: areturn

  public java.lang.String getDescription();
    Code:
       0: aload_0
       1: getfield      #92                 // Field description_:Ljava/lang/Object;
       4: astore_1
       5: aload_1
       6: instanceof    #218                // class java/lang/String
       9: ifne          29
      12: aload_1
      13: checkcast     #310                // class com/google/protobuf/ByteString
      16: astore_2
      17: aload_2
      18: invokevirtual #313                // Method com/google/protobuf/ByteString.toStringUtf8:()Ljava/lang/String;
      21: astore_3
      22: aload_0
      23: aload_3
      24: putfield      #92                 // Field description_:Ljava/lang/Object;
      27: aload_3
      28: areturn
      29: aload_1
      30: checkcast     #218                // class java/lang/String
      33: areturn

  public com.google.protobuf.ByteString getDescriptionBytes();
    Code:
       0: aload_0
       1: getfield      #92                 // Field description_:Ljava/lang/Object;
       4: astore_1
       5: aload_1
       6: instanceof    #218                // class java/lang/String
       9: ifeq          27
      12: aload_1
      13: checkcast     #218                // class java/lang/String
      16: invokestatic  #326                // Method com/google/protobuf/ByteString.copyFromUtf8:(Ljava/lang/String;)Lcom/google/protobuf/ByteString;
      19: astore_2
      20: aload_0
      21: aload_2
      22: putfield      #92                 // Field description_:Ljava/lang/Object;
      25: aload_2
      26: areturn
      27: aload_1
      28: checkcast     #310                // class com/google/protobuf/ByteString
      31: areturn

  public org.sonarsource.sonarlint.shaded.org.sonarqube.ws.Settings$Field$Builder setDescription(java.lang.String);
    Code:
       0: aload_1
       1: ifnonnull     12
       4: new           #331                // class java/lang/NullPointerException
       7: dup
       8: invokespecial #332                // Method java/lang/NullPointerException."<init>":()V
      11: athrow
      12: aload_0
      13: aload_1
      14: putfield      #92                 // Field description_:Ljava/lang/Object;
      17: aload_0
      18: invokevirtual #228                // Method onChanged:()V
      21: aload_0
      22: areturn

  public org.sonarsource.sonarlint.shaded.org.sonarqube.ws.Settings$Field$Builder clearDescription();
    Code:
       0: aload_0
       1: invokestatic  #126                // Method org/sonarsource/sonarlint/shaded/org/sonarqube/ws/Settings$Field.getDefaultInstance:()Lorg/sonarsource/sonarlint/shaded/org/sonarqube/ws/Settings$Field;
       4: invokevirtual #237                // Method org/sonarsource/sonarlint/shaded/org/sonarqube/ws/Settings$Field.getDescription:()Ljava/lang/String;
       7: putfield      #92                 // Field description_:Ljava/lang/Object;
      10: aload_0
      11: invokevirtual #228                // Method onChanged:()V
      14: aload_0
      15: areturn

  public org.sonarsource.sonarlint.shaded.org.sonarqube.ws.Settings$Field$Builder setDescriptionBytes(com.google.protobuf.ByteString);
    Code:
       0: aload_1
       1: ifnonnull     12
       4: new           #331                // class java/lang/NullPointerException
       7: dup
       8: invokespecial #332                // Method java/lang/NullPointerException."<init>":()V
      11: athrow
      12: aload_1
      13: invokestatic  #353                // Method org/sonarsource/sonarlint/shaded/org/sonarqube/ws/Settings$Field.access$9200:(Lcom/google/protobuf/ByteString;)V
      16: aload_0
      17: aload_1
      18: putfield      #92                 // Field description_:Ljava/lang/Object;
      21: aload_0
      22: invokevirtual #228                // Method onChanged:()V
      25: aload_0
      26: areturn

  public int getTypeValue();
    Code:
       0: aload_0
       1: getfield      #94                 // Field type_:I
       4: ireturn

  public org.sonarsource.sonarlint.shaded.org.sonarqube.ws.Settings$Field$Builder setTypeValue(int);
    Code:
       0: aload_0
       1: iload_1
       2: putfield      #94                 // Field type_:I
       5: aload_0
       6: invokevirtual #228                // Method onChanged:()V
       9: aload_0
      10: areturn

  public org.sonarsource.sonarlint.shaded.org.sonarqube.ws.Settings$Type getType();
    Code:
       0: aload_0
       1: getfield      #94                 // Field type_:I
       4: invokestatic  #359                // Method org/sonarsource/sonarlint/shaded/org/sonarqube/ws/Settings$Type.valueOf:(I)Lorg/sonarsource/sonarlint/shaded/org/sonarqube/ws/Settings$Type;
       7: astore_1
       8: aload_1
       9: ifnonnull     18
      12: getstatic     #363                // Field org/sonarsource/sonarlint/shaded/org/sonarqube/ws/Settings$Type.UNRECOGNIZED:Lorg/sonarsource/sonarlint/shaded/org/sonarqube/ws/Settings$Type;
      15: goto          19
      18: aload_1
      19: areturn

  public org.sonarsource.sonarlint.shaded.org.sonarqube.ws.Settings$Field$Builder setType(org.sonarsource.sonarlint.shaded.org.sonarqube.ws.Settings$Type);
    Code:
       0: aload_1
       1: ifnonnull     12
       4: new           #331                // class java/lang/NullPointerException
       7: dup
       8: invokespecial #332                // Method java/lang/NullPointerException."<init>":()V
      11: athrow
      12: aload_0
      13: aload_1
      14: invokevirtual #368                // Method org/sonarsource/sonarlint/shaded/org/sonarqube/ws/Settings$Type.getNumber:()I
      17: putfield      #94                 // Field type_:I
      20: aload_0
      21: invokevirtual #228                // Method onChanged:()V
      24: aload_0
      25: areturn

  public org.sonarsource.sonarlint.shaded.org.sonarqube.ws.Settings$Field$Builder clearType();
    Code:
       0: aload_0
       1: iconst_0
       2: putfield      #94                 // Field type_:I
       5: aload_0
       6: invokevirtual #228                // Method onChanged:()V
       9: aload_0
      10: areturn

  private void ensureOptionsIsMutable();
    Code:
       0: aload_0
       1: getfield      #120                // Field bitField0_:I
       4: iconst_1
       5: iand
       6: ifne          34
       9: aload_0
      10: new           #96                 // class com/google/protobuf/LazyStringArrayList
      13: dup
      14: aload_0
      15: getfield      #101                // Field options_:Lcom/google/protobuf/LazyStringList;
      18: invokespecial #372                // Method com/google/protobuf/LazyStringArrayList."<init>":(Lcom/google/protobuf/LazyStringList;)V
      21: putfield      #101                // Field options_:Lcom/google/protobuf/LazyStringList;
      24: aload_0
      25: dup
      26: getfield      #120                // Field bitField0_:I
      29: iconst_1
      30: ior
      31: putfield      #120                // Field bitField0_:I
      34: return

  public com.google.protobuf.ProtocolStringList getOptionsList();
    Code:
       0: aload_0
       1: getfield      #101                // Field options_:Lcom/google/protobuf/LazyStringList;
       4: invokeinterface #162,  1          // InterfaceMethod com/google/protobuf/LazyStringList.getUnmodifiableView:()Lcom/google/protobuf/LazyStringList;
       9: areturn

  public int getOptionsCount();
    Code:
       0: aload_0
       1: getfield      #101                // Field options_:Lcom/google/protobuf/LazyStringList;
       4: invokeinterface #378,  1          // InterfaceMethod com/google/protobuf/LazyStringList.size:()I
       9: ireturn

  public java.lang.String getOptions(int);
    Code:
       0: aload_0
       1: getfield      #101                // Field options_:Lcom/google/protobuf/LazyStringList;
       4: iload_1
       5: invokeinterface #384,  2          // InterfaceMethod com/google/protobuf/LazyStringList.get:(I)Ljava/lang/Object;
      10: checkcast     #218                // class java/lang/String
      13: areturn

  public com.google.protobuf.ByteString getOptionsBytes(int);
    Code:
       0: aload_0
       1: getfield      #101                // Field options_:Lcom/google/protobuf/LazyStringList;
       4: iload_1
       5: invokeinterface #389,  2          // InterfaceMethod com/google/protobuf/LazyStringList.getByteString:(I)Lcom/google/protobuf/ByteString;
      10: areturn

  public org.sonarsource.sonarlint.shaded.org.sonarqube.ws.Settings$Field$Builder setOptions(int, java.lang.String);
    Code:
       0: aload_2
       1: ifnonnull     12
       4: new           #331                // class java/lang/NullPointerException
       7: dup
       8: invokespecial #332                // Method java/lang/NullPointerException."<init>":()V
      11: athrow
      12: aload_0
      13: invokespecial #260                // Method ensureOptionsIsMutable:()V
      16: aload_0
      17: getfield      #101                // Field options_:Lcom/google/protobuf/LazyStringList;
      20: iload_1
      21: aload_2
      22: invokeinterface #395,  3          // InterfaceMethod com/google/protobuf/LazyStringList.set:(ILjava/lang/Object;)Ljava/lang/Object;
      27: pop
      28: aload_0
      29: invokevirtual #228                // Method onChanged:()V
      32: aload_0
      33: areturn

  public org.sonarsource.sonarlint.shaded.org.sonarqube.ws.Settings$Field$Builder addOptions(java.lang.String);
    Code:
       0: aload_1
       1: ifnonnull     12
       4: new           #331                // class java/lang/NullPointerException
       7: dup
       8: invokespecial #332                // Method java/lang/NullPointerException."<init>":()V
      11: athrow
      12: aload_0
      13: invokespecial #260                // Method ensureOptionsIsMutable:()V
      16: aload_0
      17: getfield      #101                // Field options_:Lcom/google/protobuf/LazyStringList;
      20: aload_1
      21: invokeinterface #400,  2          // InterfaceMethod com/google/protobuf/LazyStringList.add:(Ljava/lang/Object;)Z
      26: pop
      27: aload_0
      28: invokevirtual #228                // Method onChanged:()V
      31: aload_0
      32: areturn

  public org.sonarsource.sonarlint.shaded.org.sonarqube.ws.Settings$Field$Builder addAllOptions(java.lang.Iterable<java.lang.String>);
    Code:
       0: aload_0
       1: invokespecial #260                // Method ensureOptionsIsMutable:()V
       4: aload_1
       5: aload_0
       6: getfield      #101                // Field options_:Lcom/google/protobuf/LazyStringList;
       9: invokestatic  #406                // Method com/google/protobuf/AbstractMessageLite$Builder.addAll:(Ljava/lang/Iterable;Ljava/util/List;)V
      12: aload_0
      13: invokevirtual #228                // Method onChanged:()V
      16: aload_0
      17: areturn

  public org.sonarsource.sonarlint.shaded.org.sonarqube.ws.Settings$Field$Builder clearOptions();
    Code:
       0: aload_0
       1: getstatic     #99                 // Field com/google/protobuf/LazyStringArrayList.EMPTY:Lcom/google/protobuf/LazyStringList;
       4: putfield      #101                // Field options_:Lcom/google/protobuf/LazyStringList;
       7: aload_0
       8: aload_0
       9: getfield      #120                // Field bitField0_:I
      12: bipush        -2
      14: iand
      15: putfield      #120                // Field bitField0_:I
      18: aload_0
      19: invokevirtual #228                // Method onChanged:()V
      22: aload_0
      23: areturn

  public org.sonarsource.sonarlint.shaded.org.sonarqube.ws.Settings$Field$Builder addOptionsBytes(com.google.protobuf.ByteString);
    Code:
       0: aload_1
       1: ifnonnull     12
       4: new           #331                // class java/lang/NullPointerException
       7: dup
       8: invokespecial #332                // Method java/lang/NullPointerException."<init>":()V
      11: athrow
      12: aload_1
      13: invokestatic  #414                // Method org/sonarsource/sonarlint/shaded/org/sonarqube/ws/Settings$Field.access$9300:(Lcom/google/protobuf/ByteString;)V
      16: aload_0
      17: invokespecial #260                // Method ensureOptionsIsMutable:()V
      20: aload_0
      21: getfield      #101                // Field options_:Lcom/google/protobuf/LazyStringList;
      24: aload_1
      25: invokeinterface #416,  2          // InterfaceMethod com/google/protobuf/LazyStringList.add:(Lcom/google/protobuf/ByteString;)V
      30: aload_0
      31: invokevirtual #228                // Method onChanged:()V
      34: aload_0
      35: areturn

  public final org.sonarsource.sonarlint.shaded.org.sonarqube.ws.Settings$Field$Builder setUnknownFields(com.google.protobuf.UnknownFieldSet);
    Code:
       0: aload_0
       1: aload_1
       2: invokespecial #420                // Method com/google/protobuf/GeneratedMessageV3$Builder.setUnknownFields:(Lcom/google/protobuf/UnknownFieldSet;)Lcom/google/protobuf/GeneratedMessageV3$Builder;
       5: checkcast     #2                  // class org/sonarsource/sonarlint/shaded/org/sonarqube/ws/Settings$Field$Builder
       8: areturn

  public final org.sonarsource.sonarlint.shaded.org.sonarqube.ws.Settings$Field$Builder mergeUnknownFields(com.google.protobuf.UnknownFieldSet);
    Code:
       0: aload_0
       1: aload_1
       2: invokespecial #424                // Method com/google/protobuf/GeneratedMessageV3$Builder.mergeUnknownFields:(Lcom/google/protobuf/UnknownFieldSet;)Lcom/google/protobuf/GeneratedMessageV3$Builder;
       5: checkcast     #2                  // class org/sonarsource/sonarlint/shaded/org/sonarqube/ws/Settings$Field$Builder
       8: areturn

  public com.google.protobuf.GeneratedMessageV3$Builder mergeUnknownFields(com.google.protobuf.UnknownFieldSet);
    Code:
       0: aload_0
       1: aload_1
       2: invokevirtual #272                // Method mergeUnknownFields:(Lcom/google/protobuf/UnknownFieldSet;)Lorg/sonarsource/sonarlint/shaded/org/sonarqube/ws/Settings$Field$Builder;
       5: areturn

  public com.google.protobuf.GeneratedMessageV3$Builder setUnknownFields(com.google.protobuf.UnknownFieldSet);
    Code:
       0: aload_0
       1: aload_1
       2: invokevirtual #426                // Method setUnknownFields:(Lcom/google/protobuf/UnknownFieldSet;)Lorg/sonarsource/sonarlint/shaded/org/sonarqube/ws/Settings$Field$Builder;
       5: areturn

  public com.google.protobuf.GeneratedMessageV3$Builder addRepeatedField(com.google.protobuf.Descriptors$FieldDescriptor, java.lang.Object);
    Code:
       0: aload_0
       1: aload_1
       2: aload_2
       3: invokevirtual #428                // Method addRepeatedField:(Lcom/google/protobuf/Descriptors$FieldDescriptor;Ljava/lang/Object;)Lorg/sonarsource/sonarlint/shaded/org/sonarqube/ws/Settings$Field$Builder;
       6: areturn

  public com.google.protobuf.GeneratedMessageV3$Builder setRepeatedField(com.google.protobuf.Descriptors$FieldDescriptor, int, java.lang.Object);
    Code:
       0: aload_0
       1: aload_1
       2: iload_2
       3: aload_3
       4: invokevirtual #430                // Method setRepeatedField:(Lcom/google/protobuf/Descriptors$FieldDescriptor;ILjava/lang/Object;)Lorg/sonarsource/sonarlint/shaded/org/sonarqube/ws/Settings$Field$Builder;
       7: areturn

  public com.google.protobuf.GeneratedMessageV3$Builder clearOneof(com.google.protobuf.Descriptors$OneofDescriptor);
    Code:
       0: aload_0
       1: aload_1
       2: invokevirtual #432                // Method clearOneof:(Lcom/google/protobuf/Descriptors$OneofDescriptor;)Lorg/sonarsource/sonarlint/shaded/org/sonarqube/ws/Settings$Field$Builder;
       5: areturn

  public com.google.protobuf.GeneratedMessageV3$Builder clearField(com.google.protobuf.Descriptors$FieldDescriptor);
    Code:
       0: aload_0
       1: aload_1
       2: invokevirtual #434                // Method clearField:(Lcom/google/protobuf/Descriptors$FieldDescriptor;)Lorg/sonarsource/sonarlint/shaded/org/sonarqube/ws/Settings$Field$Builder;
       5: areturn

  public com.google.protobuf.GeneratedMessageV3$Builder setField(com.google.protobuf.Descriptors$FieldDescriptor, java.lang.Object);
    Code:
       0: aload_0
       1: aload_1
       2: aload_2
       3: invokevirtual #436                // Method setField:(Lcom/google/protobuf/Descriptors$FieldDescriptor;Ljava/lang/Object;)Lorg/sonarsource/sonarlint/shaded/org/sonarqube/ws/Settings$Field$Builder;
       6: areturn

  public com.google.protobuf.GeneratedMessageV3$Builder clear();
    Code:
       0: aload_0
       1: invokevirtual #438                // Method clear:()Lorg/sonarsource/sonarlint/shaded/org/sonarqube/ws/Settings$Field$Builder;
       4: areturn

  public com.google.protobuf.GeneratedMessageV3$Builder clone();
    Code:
       0: aload_0
       1: invokevirtual #440                // Method clone:()Lorg/sonarsource/sonarlint/shaded/org/sonarqube/ws/Settings$Field$Builder;
       4: areturn

  public com.google.protobuf.AbstractMessage$Builder mergeUnknownFields(com.google.protobuf.UnknownFieldSet);
    Code:
       0: aload_0
       1: aload_1
       2: invokevirtual #272                // Method mergeUnknownFields:(Lcom/google/protobuf/UnknownFieldSet;)Lorg/sonarsource/sonarlint/shaded/org/sonarqube/ws/Settings$Field$Builder;
       5: areturn

  public com.google.protobuf.AbstractMessage$Builder mergeFrom(com.google.protobuf.CodedInputStream, com.google.protobuf.ExtensionRegistryLite) throws java.io.IOException;
    Code:
       0: aload_0
       1: aload_1
       2: aload_2
       3: invokevirtual #444                // Method mergeFrom:(Lcom/google/protobuf/CodedInputStream;Lcom/google/protobuf/ExtensionRegistryLite;)Lorg/sonarsource/sonarlint/shaded/org/sonarqube/ws/Settings$Field$Builder;
       6: areturn

  public com.google.protobuf.AbstractMessage$Builder mergeFrom(com.google.protobuf.Message);
    Code:
       0: aload_0
       1: aload_1
       2: invokevirtual #446                // Method mergeFrom:(Lcom/google/protobuf/Message;)Lorg/sonarsource/sonarlint/shaded/org/sonarqube/ws/Settings$Field$Builder;
       5: areturn

  public com.google.protobuf.AbstractMessage$Builder clear();
    Code:
       0: aload_0
       1: invokevirtual #438                // Method clear:()Lorg/sonarsource/sonarlint/shaded/org/sonarqube/ws/Settings$Field$Builder;
       4: areturn

  public com.google.protobuf.AbstractMessage$Builder clearOneof(com.google.protobuf.Descriptors$OneofDescriptor);
    Code:
       0: aload_0
       1: aload_1
       2: invokevirtual #432                // Method clearOneof:(Lcom/google/protobuf/Descriptors$OneofDescriptor;)Lorg/sonarsource/sonarlint/shaded/org/sonarqube/ws/Settings$Field$Builder;
       5: areturn

  public com.google.protobuf.AbstractMessage$Builder clone();
    Code:
       0: aload_0
       1: invokevirtual #440                // Method clone:()Lorg/sonarsource/sonarlint/shaded/org/sonarqube/ws/Settings$Field$Builder;
       4: areturn

  public com.google.protobuf.Message$Builder mergeUnknownFields(com.google.protobuf.UnknownFieldSet);
    Code:
       0: aload_0
       1: aload_1
       2: invokevirtual #272                // Method mergeUnknownFields:(Lcom/google/protobuf/UnknownFieldSet;)Lorg/sonarsource/sonarlint/shaded/org/sonarqube/ws/Settings$Field$Builder;
       5: areturn

  public com.google.protobuf.Message$Builder setUnknownFields(com.google.protobuf.UnknownFieldSet);
    Code:
       0: aload_0
       1: aload_1
       2: invokevirtual #426                // Method setUnknownFields:(Lcom/google/protobuf/UnknownFieldSet;)Lorg/sonarsource/sonarlint/shaded/org/sonarqube/ws/Settings$Field$Builder;
       5: areturn

  public com.google.protobuf.Message$Builder addRepeatedField(com.google.protobuf.Descriptors$FieldDescriptor, java.lang.Object);
    Code:
       0: aload_0
       1: aload_1
       2: aload_2
       3: invokevirtual #428                // Method addRepeatedField:(Lcom/google/protobuf/Descriptors$FieldDescriptor;Ljava/lang/Object;)Lorg/sonarsource/sonarlint/shaded/org/sonarqube/ws/Settings$Field$Builder;
       6: areturn

  public com.google.protobuf.Message$Builder setRepeatedField(com.google.protobuf.Descriptors$FieldDescriptor, int, java.lang.Object);
    Code:
       0: aload_0
       1: aload_1
       2: iload_2
       3: aload_3
       4: invokevirtual #430                // Method setRepeatedField:(Lcom/google/protobuf/Descriptors$FieldDescriptor;ILjava/lang/Object;)Lorg/sonarsource/sonarlint/shaded/org/sonarqube/ws/Settings$Field$Builder;
       7: areturn

  public com.google.protobuf.Message$Builder clearOneof(com.google.protobuf.Descriptors$OneofDescriptor);
    Code:
       0: aload_0
       1: aload_1
       2: invokevirtual #432                // Method clearOneof:(Lcom/google/protobuf/Descriptors$OneofDescriptor;)Lorg/sonarsource/sonarlint/shaded/org/sonarqube/ws/Settings$Field$Builder;
       5: areturn

  public com.google.protobuf.Message$Builder clearField(com.google.protobuf.Descriptors$FieldDescriptor);
    Code:
       0: aload_0
       1: aload_1
       2: invokevirtual #434                // Method clearField:(Lcom/google/protobuf/Descriptors$FieldDescriptor;)Lorg/sonarsource/sonarlint/shaded/org/sonarqube/ws/Settings$Field$Builder;
       5: areturn

  public com.google.protobuf.Message$Builder setField(com.google.protobuf.Descriptors$FieldDescriptor, java.lang.Object);
    Code:
       0: aload_0
       1: aload_1
       2: aload_2
       3: invokevirtual #436                // Method setField:(Lcom/google/protobuf/Descriptors$FieldDescriptor;Ljava/lang/Object;)Lorg/sonarsource/sonarlint/shaded/org/sonarqube/ws/Settings$Field$Builder;
       6: areturn

  public com.google.protobuf.Message$Builder mergeFrom(com.google.protobuf.CodedInputStream, com.google.protobuf.ExtensionRegistryLite) throws java.io.IOException;
    Code:
       0: aload_0
       1: aload_1
       2: aload_2
       3: invokevirtual #444                // Method mergeFrom:(Lcom/google/protobuf/CodedInputStream;Lcom/google/protobuf/ExtensionRegistryLite;)Lorg/sonarsource/sonarlint/shaded/org/sonarqube/ws/Settings$Field$Builder;
       6: areturn

  public com.google.protobuf.Message$Builder clone();
    Code:
       0: aload_0
       1: invokevirtual #440                // Method clone:()Lorg/sonarsource/sonarlint/shaded/org/sonarqube/ws/Settings$Field$Builder;
       4: areturn

  public com.google.protobuf.Message buildPartial();
    Code:
       0: aload_0
       1: invokevirtual #130                // Method buildPartial:()Lorg/sonarsource/sonarlint/shaded/org/sonarqube/ws/Settings$Field;
       4: areturn

  public com.google.protobuf.Message build();
    Code:
       0: aload_0
       1: invokevirtual #458                // Method build:()Lorg/sonarsource/sonarlint/shaded/org/sonarqube/ws/Settings$Field;
       4: areturn

  public com.google.protobuf.Message$Builder mergeFrom(com.google.protobuf.Message);
    Code:
       0: aload_0
       1: aload_1
       2: invokevirtual #446                // Method mergeFrom:(Lcom/google/protobuf/Message;)Lorg/sonarsource/sonarlint/shaded/org/sonarqube/ws/Settings$Field$Builder;
       5: areturn

  public com.google.protobuf.Message$Builder clear();
    Code:
       0: aload_0
       1: invokevirtual #438                // Method clear:()Lorg/sonarsource/sonarlint/shaded/org/sonarqube/ws/Settings$Field$Builder;
       4: areturn

  public com.google.protobuf.MessageLite$Builder mergeFrom(com.google.protobuf.CodedInputStream, com.google.protobuf.ExtensionRegistryLite) throws java.io.IOException;
    Code:
       0: aload_0
       1: aload_1
       2: aload_2
       3: invokevirtual #444                // Method mergeFrom:(Lcom/google/protobuf/CodedInputStream;Lcom/google/protobuf/ExtensionRegistryLite;)Lorg/sonarsource/sonarlint/shaded/org/sonarqube/ws/Settings$Field$Builder;
       6: areturn

  public com.google.protobuf.MessageLite$Builder clone();
    Code:
       0: aload_0
       1: invokevirtual #440                // Method clone:()Lorg/sonarsource/sonarlint/shaded/org/sonarqube/ws/Settings$Field$Builder;
       4: areturn

  public com.google.protobuf.MessageLite buildPartial();
    Code:
       0: aload_0
       1: invokevirtual #130                // Method buildPartial:()Lorg/sonarsource/sonarlint/shaded/org/sonarqube/ws/Settings$Field;
       4: areturn

  public com.google.protobuf.MessageLite build();
    Code:
       0: aload_0
       1: invokevirtual #458                // Method build:()Lorg/sonarsource/sonarlint/shaded/org/sonarqube/ws/Settings$Field;
       4: areturn

  public com.google.protobuf.MessageLite$Builder clear();
    Code:
       0: aload_0
       1: invokevirtual #438                // Method clear:()Lorg/sonarsource/sonarlint/shaded/org/sonarqube/ws/Settings$Field$Builder;
       4: areturn

  public com.google.protobuf.MessageLite getDefaultInstanceForType();
    Code:
       0: aload_0
       1: invokevirtual #463                // Method getDefaultInstanceForType:()Lorg/sonarsource/sonarlint/shaded/org/sonarqube/ws/Settings$Field;
       4: areturn

  public com.google.protobuf.Message getDefaultInstanceForType();
    Code:
       0: aload_0
       1: invokevirtual #463                // Method getDefaultInstanceForType:()Lorg/sonarsource/sonarlint/shaded/org/sonarqube/ws/Settings$Field;
       4: areturn

  public com.google.protobuf.AbstractMessageLite$Builder mergeFrom(com.google.protobuf.CodedInputStream, com.google.protobuf.ExtensionRegistryLite) throws java.io.IOException;
    Code:
       0: aload_0
       1: aload_1
       2: aload_2
       3: invokevirtual #444                // Method mergeFrom:(Lcom/google/protobuf/CodedInputStream;Lcom/google/protobuf/ExtensionRegistryLite;)Lorg/sonarsource/sonarlint/shaded/org/sonarqube/ws/Settings$Field$Builder;
       6: areturn

  public com.google.protobuf.AbstractMessageLite$Builder clone();
    Code:
       0: aload_0
       1: invokevirtual #440                // Method clone:()Lorg/sonarsource/sonarlint/shaded/org/sonarqube/ws/Settings$Field$Builder;
       4: areturn

  public java.lang.Object clone() throws java.lang.CloneNotSupportedException;
    Code:
       0: aload_0
       1: invokevirtual #440                // Method clone:()Lorg/sonarsource/sonarlint/shaded/org/sonarqube/ws/Settings$Field$Builder;
       4: areturn

  public java.util.List getOptionsList();
    Code:
       0: aload_0
       1: invokevirtual #471                // Method getOptionsList:()Lcom/google/protobuf/ProtocolStringList;
       4: areturn

  org.sonarsource.sonarlint.shaded.org.sonarqube.ws.Settings$Field$Builder(org.sonarsource.sonarlint.shaded.org.sonarqube.ws.Settings$1);
    Code:
       0: aload_0
       1: invokespecial #473                // Method "<init>":()V
       4: return

  org.sonarsource.sonarlint.shaded.org.sonarqube.ws.Settings$Field$Builder(com.google.protobuf.GeneratedMessageV3$BuilderParent, org.sonarsource.sonarlint.shaded.org.sonarqube.ws.Settings$1);
    Code:
       0: aload_0
       1: aload_1
       2: invokespecial #477                // Method "<init>":(Lcom/google/protobuf/GeneratedMessageV3$BuilderParent;)V
       5: return
}
