Compiled from "MessageSelectorChain.java"
public class org.springframework.integration.selector.MessageSelectorChain implements org.springframework.integration.core.MessageSelector {
  private volatile org.springframework.integration.selector.MessageSelectorChain$VotingStrategy votingStrategy;

  private final java.util.List<org.springframework.integration.core.MessageSelector> selectors;

  public org.springframework.integration.selector.MessageSelectorChain();
    Code:
       0: aload_0
       1: invokespecial #1                  // Method java/lang/Object."<init>":()V
       4: aload_0
       5: getstatic     #2                  // Field org/springframework/integration/selector/MessageSelectorChain$VotingStrategy.ALL:Lorg/springframework/integration/selector/MessageSelectorChain$VotingStrategy;
       8: putfield      #3                  // Field votingStrategy:Lorg/springframework/integration/selector/MessageSelectorChain$VotingStrategy;
      11: aload_0
      12: new           #4                  // class java/util/concurrent/CopyOnWriteArrayList
      15: dup
      16: invokespecial #5                  // Method java/util/concurrent/CopyOnWriteArrayList."<init>":()V
      19: putfield      #6                  // Field selectors:Ljava/util/List;
      22: return

  public void setVotingStrategy(org.springframework.integration.selector.MessageSelectorChain$VotingStrategy);
    Code:
       0: aload_1
       1: ldc           #7                  // String votingStrategy must not be null
       3: invokestatic  #8                  // Method org/springframework/util/Assert.notNull:(Ljava/lang/Object;Ljava/lang/String;)V
       6: aload_0
       7: aload_1
       8: putfield      #3                  // Field votingStrategy:Lorg/springframework/integration/selector/MessageSelectorChain$VotingStrategy;
      11: return

  public void add(org.springframework.integration.core.MessageSelector);
    Code:
       0: aload_0
       1: getfield      #6                  // Field selectors:Ljava/util/List;
       4: aload_1
       5: invokeinterface #9,  2            // InterfaceMethod java/util/List.add:(Ljava/lang/Object;)Z
      10: pop
      11: return

  public void add(int, org.springframework.integration.core.MessageSelector);
    Code:
       0: aload_0
       1: getfield      #6                  // Field selectors:Ljava/util/List;
       4: iload_1
       5: aload_2
       6: invokeinterface #10,  3           // InterfaceMethod java/util/List.add:(ILjava/lang/Object;)V
      11: return

  public void setSelectors(java.util.List<org.springframework.integration.core.MessageSelector>);
    Code:
       0: aload_1
       1: ldc           #11                 // String selectors must not be empty
       3: invokestatic  #12                 // Method org/springframework/util/Assert.notEmpty:(Ljava/util/Collection;Ljava/lang/String;)V
       6: aload_0
       7: getfield      #6                  // Field selectors:Ljava/util/List;
      10: dup
      11: astore_2
      12: monitorenter
      13: aload_0
      14: getfield      #6                  // Field selectors:Ljava/util/List;
      17: invokeinterface #13,  1           // InterfaceMethod java/util/List.clear:()V
      22: aload_0
      23: getfield      #6                  // Field selectors:Ljava/util/List;
      26: aload_1
      27: invokeinterface #14,  2           // InterfaceMethod java/util/List.addAll:(Ljava/util/Collection;)Z
      32: pop
      33: aload_2
      34: monitorexit
      35: goto          43
      38: astore_3
      39: aload_2
      40: monitorexit
      41: aload_3
      42: athrow
      43: return
    Exception table:
       from    to  target type
          13    35    38   any
          38    41    38   any

  public final boolean accept(org.springframework.messaging.Message<?>);
    Code:
       0: iconst_0
       1: istore_2
       2: iconst_0
       3: istore_3
       4: aload_0
       5: getfield      #6                  // Field selectors:Ljava/util/List;
       8: invokeinterface #15,  1           // InterfaceMethod java/util/List.iterator:()Ljava/util/Iterator;
      13: astore        4
      15: aload         4
      17: invokeinterface #16,  1           // InterfaceMethod java/util/Iterator.hasNext:()Z
      22: ifeq          90
      25: aload         4
      27: invokeinterface #17,  1           // InterfaceMethod java/util/Iterator.next:()Ljava/lang/Object;
      32: checkcast     #18                 // class org/springframework/integration/core/MessageSelector
      35: astore        5
      37: iinc          2, 1
      40: aload         5
      42: aload_1
      43: invokeinterface #19,  2           // InterfaceMethod org/springframework/integration/core/MessageSelector.accept:(Lorg/springframework/messaging/Message;)Z
      48: ifeq          72
      51: aload_0
      52: getfield      #3                  // Field votingStrategy:Lorg/springframework/integration/selector/MessageSelectorChain$VotingStrategy;
      55: getstatic     #20                 // Field org/springframework/integration/selector/MessageSelectorChain$VotingStrategy.ANY:Lorg/springframework/integration/selector/MessageSelectorChain$VotingStrategy;
      58: invokevirtual #21                 // Method org/springframework/integration/selector/MessageSelectorChain$VotingStrategy.equals:(Ljava/lang/Object;)Z
      61: ifeq          66
      64: iconst_1
      65: ireturn
      66: iinc          3, 1
      69: goto          87
      72: aload_0
      73: getfield      #3                  // Field votingStrategy:Lorg/springframework/integration/selector/MessageSelectorChain$VotingStrategy;
      76: getstatic     #2                  // Field org/springframework/integration/selector/MessageSelectorChain$VotingStrategy.ALL:Lorg/springframework/integration/selector/MessageSelectorChain$VotingStrategy;
      79: invokevirtual #21                 // Method org/springframework/integration/selector/MessageSelectorChain$VotingStrategy.equals:(Ljava/lang/Object;)Z
      82: ifeq          87
      85: iconst_0
      86: ireturn
      87: goto          15
      90: aload_0
      91: iload_3
      92: iload_2
      93: invokespecial #22                 // Method decide:(II)Z
      96: ireturn

  private boolean decide(int, int);
    Code:
       0: iload_1
       1: ifne          6
       4: iconst_0
       5: ireturn
       6: getstatic     #23                 // Field org/springframework/integration/selector/MessageSelectorChain$1.$SwitchMap$org$springframework$integration$selector$MessageSelectorChain$VotingStrategy:[I
       9: aload_0
      10: getfield      #3                  // Field votingStrategy:Lorg/springframework/integration/selector/MessageSelectorChain$VotingStrategy;
      13: invokevirtual #24                 // Method org/springframework/integration/selector/MessageSelectorChain$VotingStrategy.ordinal:()I
      16: iaload
      17: tableswitch   { // 1 to 4
                     1: 48
                     2: 50
                     3: 61
                     4: 74
               default: 87
          }
      48: iconst_1
      49: ireturn
      50: iload_1
      51: iload_2
      52: if_icmpne     59
      55: iconst_1
      56: goto          60
      59: iconst_0
      60: ireturn
      61: iconst_2
      62: iload_1
      63: imul
      64: iload_2
      65: if_icmple     72
      68: iconst_1
      69: goto          73
      72: iconst_0
      73: ireturn
      74: iconst_2
      75: iload_1
      76: imul
      77: iload_2
      78: if_icmplt     85
      81: iconst_1
      82: goto          86
      85: iconst_0
      86: ireturn
      87: new           #25                 // class java/lang/IllegalArgumentException
      90: dup
      91: new           #26                 // class java/lang/StringBuilder
      94: dup
      95: invokespecial #27                 // Method java/lang/StringBuilder."<init>":()V
      98: ldc           #28                 // String unsupported voting strategy
     100: invokevirtual #29                 // Method java/lang/StringBuilder.append:(Ljava/lang/String;)Ljava/lang/StringBuilder;
     103: aload_0
     104: getfield      #3                  // Field votingStrategy:Lorg/springframework/integration/selector/MessageSelectorChain$VotingStrategy;
     107: invokevirtual #30                 // Method java/lang/StringBuilder.append:(Ljava/lang/Object;)Ljava/lang/StringBuilder;
     110: invokevirtual #31                 // Method java/lang/StringBuilder.toString:()Ljava/lang/String;
     113: invokespecial #32                 // Method java/lang/IllegalArgumentException."<init>":(Ljava/lang/String;)V
     116: athrow

  public boolean accept(java.lang.Object);
    Code:
       0: aload_0
       1: aload_1
       2: checkcast     #33                 // class org/springframework/messaging/Message
       5: invokevirtual #34                 // Method accept:(Lorg/springframework/messaging/Message;)Z
       8: ireturn
}
