Compiled from "JFunction2$mcIDD$sp.java"
public interface scala.compat.java8.JFunction2$mcIDD$sp extends scala.compat.java8.JFunction2 {
  public abstract int apply$mcIDD$sp(double, double);

  public default java.lang.Object apply(java.lang.Object, java.lang.Object);
    Code:
       0: aload_0
       1: aload_1
       2: invokestatic  #1                  // Method scala/runtime/BoxesRunTime.unboxToDouble:(Ljava/lang/Object;)D
       5: aload_2
       6: invokestatic  #1                  // Method scala/runtime/BoxesRunTime.unboxToDouble:(Ljava/lang/Object;)D
       9: invokeinterface #2,  5            // InterfaceMethod apply$mcIDD$sp:(DD)I
      14: invokestatic  #3                  // Method scala/runtime/BoxesRunTime.boxToInteger:(I)Ljava/lang/Integer;
      17: areturn
}
