Compiled from "ForkChannelTransport.java"
public class org.jboss.as.connector.services.workmanager.transport.ForkChannelTransport extends org.jboss.jca.core.workmanager.transport.remote.jgroups.JGroupsTransport implements org.jgroups.blocks.RpcDispatcher$Marshaller {
  private final org.wildfly.clustering.jgroups.spi.ChannelFactory factory;

  public org.jboss.as.connector.services.workmanager.transport.ForkChannelTransport(org.wildfly.clustering.jgroups.spi.ChannelFactory);
    Code:
       0: aload_0
       1: invokespecial #1                  // Method org/jboss/jca/core/workmanager/transport/remote/jgroups/JGroupsTransport."<init>":()V
       4: aload_0
       5: aload_1
       6: putfield      #2                  // Field factory:Lorg/wildfly/clustering/jgroups/spi/ChannelFactory;
       9: return

  protected org.jgroups.blocks.RpcDispatcher createRpcDispatcher();
    Code:
       0: aload_0
       1: invokespecial #3                  // Method org/jboss/jca/core/workmanager/transport/remote/jgroups/JGroupsTransport.createRpcDispatcher:()Lorg/jgroups/blocks/RpcDispatcher;
       4: astore_1
       5: aload_1
       6: aload_0
       7: invokevirtual #4                  // Method org/jgroups/blocks/RpcDispatcher.setResponseMarshaller:(Lorg/jgroups/blocks/RpcDispatcher$Marshaller;)V
      10: aload_1
      11: areturn

  public org.jgroups.util.Buffer objectToBuffer(java.lang.Object) throws java.lang.Exception;
    Code:
       0: new           #5                  // class org/jgroups/util/Buffer
       3: dup
       4: aload_1
       5: invokestatic  #6                  // Method org/jgroups/util/Util.objectToByteBuffer:(Ljava/lang/Object;)[B
       8: invokespecial #7                  // Method org/jgroups/util/Buffer."<init>":([B)V
      11: areturn

  public java.lang.Object objectFromBuffer(byte[], int, int) throws java.lang.Exception;
    Code:
       0: aload_0
       1: getfield      #2                  // Field factory:Lorg/wildfly/clustering/jgroups/spi/ChannelFactory;
       4: aload_1
       5: iload_2
       6: iload_3
       7: invokestatic  #8                  // Method java/nio/ByteBuffer.wrap:([BII)Ljava/nio/ByteBuffer;
      10: invokeinterface #9,  2            // InterfaceMethod org/wildfly/clustering/jgroups/spi/ChannelFactory.isUnknownForkResponse:(Ljava/nio/ByteBuffer;)Z
      15: ifeq          22
      18: aconst_null
      19: goto          28
      22: aload_1
      23: iload_2
      24: iload_3
      25: invokestatic  #10                 // Method org/jgroups/util/Util.objectFromByteBuffer:([BII)Ljava/lang/Object;
      28: areturn
}
