Compiled from "MessageProvider.java"
final class com.vladsch.flexmark.util.options.MessageProvider$1 implements com.vladsch.flexmark.util.options.MessageProvider {
  com.vladsch.flexmark.util.options.MessageProvider$1();
    Code:
       0: aload_0
       1: invokespecial #1                  // Method java/lang/Object."<init>":()V
       4: return

  public java.lang.String message(java.lang.String, java.lang.String, java.lang.Object...);
    Code:
       0: aload_3
       1: arraylength
       2: ifle          22
       5: aload_2
       6: bipush        123
       8: invokevirtual #2                  // Method java/lang/String.indexOf:(I)I
      11: iflt          22
      14: aload_2
      15: aload_3
      16: invokestatic  #3                  // Method java/text/MessageFormat.format:(Ljava/lang/String;[Ljava/lang/Object;)Ljava/lang/String;
      19: goto          23
      22: aload_2
      23: areturn
}
