Compiled from "OS.java"
public final class net.openhft.chronicle.core.OS extends java.lang.Enum<net.openhft.chronicle.core.OS> {
  public static final java.lang.String TMP;

  public static final java.lang.String USER_DIR;

  public static final java.lang.String USER_HOME;

  public static final java.lang.Exception TIME_LIMIT;

  public static final java.lang.String TARGET;

  static final net.openhft.chronicle.core.ClassLocal<java.lang.invoke.MethodHandle> MAP0_MH;

  private static final java.lang.String HOST_NAME;

  private static final java.lang.String USER_NAME;

  private static final int MAP_RO;

  private static final int MAP_RW;

  private static final int MAP_PV;

  private static final boolean IS64BIT;

  private static final java.util.concurrent.atomic.AtomicInteger PROCESS_ID;

  private static final java.lang.String OS;

  private static final boolean IS_LINUX;

  private static final boolean IS_MAC;

  private static final boolean IS_WIN;

  private static final boolean IS_WIN10;

  private static final java.util.concurrent.atomic.AtomicLong memoryMapped;

  private static final java.lang.invoke.MethodHandle UNMAPP0_MH;

  private static final java.lang.invoke.MethodHandle READ0_MH;

  private static final java.lang.invoke.MethodHandle WRITE0_MH;

  private static final java.lang.invoke.MethodHandle WRITE0_MH2;

  public static final int SAFE_PAGE_SIZE;

  private static int PAGE_SIZE;

  private static int MAP_ALIGNMENT;

  private static final net.openhft.chronicle.core.OS[] $VALUES;

  static final boolean $assertionsDisabled;

  public static net.openhft.chronicle.core.OS[] values();
    Code:
       0: getstatic     #1                  // Field $VALUES:[Lnet/openhft/chronicle/core/OS;
       3: invokevirtual #2                  // Method "[Lnet/openhft/chronicle/core/OS;".clone:()Ljava/lang/Object;
       6: checkcast     #3                  // class "[Lnet/openhft/chronicle/core/OS;"
       9: areturn

  public static net.openhft.chronicle.core.OS valueOf(java.lang.String);
    Code:
       0: ldc           #4                  // class net/openhft/chronicle/core/OS
       2: aload_0
       3: invokestatic  #5                  // Method java/lang/Enum.valueOf:(Ljava/lang/Class;Ljava/lang/String;)Ljava/lang/Enum;
       6: checkcast     #4                  // class net/openhft/chronicle/core/OS
       9: areturn

  private net.openhft.chronicle.core.OS();
    Code:
       0: aload_0
       1: aload_1
       2: iload_2
       3: invokespecial #6                  // Method java/lang/Enum."<init>":(Ljava/lang/String;I)V
       6: return

  private static java.lang.String findTarget();
    Code:
       0: ldc           #7                  // String project.build.directory
       2: invokestatic  #8                  // Method java/lang/System.getProperty:(Ljava/lang/String;)Ljava/lang/String;
       5: astore_0
       6: aload_0
       7: ifnull        12
      10: aload_0
      11: areturn
      12: new           #9                  // class java/io/File
      15: dup
      16: ldc           #10                 // String user.dir
      18: invokestatic  #8                  // Method java/lang/System.getProperty:(Ljava/lang/String;)Ljava/lang/String;
      21: invokespecial #11                 // Method java/io/File."<init>":(Ljava/lang/String;)V
      24: astore_1
      25: aload_1
      26: ifnull        83
      29: new           #9                  // class java/io/File
      32: dup
      33: aload_1
      34: ldc           #12                 // String target
      36: invokespecial #13                 // Method java/io/File."<init>":(Ljava/io/File;Ljava/lang/String;)V
      39: astore_2
      40: aload_2
      41: invokevirtual #14                 // Method java/io/File.exists:()Z
      44: ifeq          52
      47: aload_2
      48: invokevirtual #15                 // Method java/io/File.getAbsolutePath:()Ljava/lang/String;
      51: areturn
      52: new           #9                  // class java/io/File
      55: dup
      56: aload_1
      57: ldc           #16                 // String build
      59: invokespecial #13                 // Method java/io/File."<init>":(Ljava/io/File;Ljava/lang/String;)V
      62: astore_3
      63: aload_3
      64: invokevirtual #14                 // Method java/io/File.exists:()Z
      67: ifeq          75
      70: aload_3
      71: invokevirtual #15                 // Method java/io/File.getAbsolutePath:()Ljava/lang/String;
      74: areturn
      75: aload_1
      76: invokevirtual #17                 // Method java/io/File.getParentFile:()Ljava/io/File;
      79: astore_1
      80: goto          25
      83: new           #18                 // class java/lang/StringBuilder
      86: dup
      87: invokespecial #19                 // Method java/lang/StringBuilder."<init>":()V
      90: getstatic     #20                 // Field TMP:Ljava/lang/String;
      93: invokevirtual #21                 // Method java/lang/StringBuilder.append:(Ljava/lang/String;)Ljava/lang/StringBuilder;
      96: ldc           #22                 // String /target
      98: invokevirtual #21                 // Method java/lang/StringBuilder.append:(Ljava/lang/String;)Ljava/lang/StringBuilder;
     101: invokevirtual #23                 // Method java/lang/StringBuilder.toString:()Ljava/lang/String;
     104: areturn

  public static java.lang.String findDir(java.lang.String) throws java.io.FileNotFoundException;
    Code:
       0: ldc           #24                 // String java.class.path
       2: invokestatic  #8                  // Method java/lang/System.getProperty:(Ljava/lang/String;)Ljava/lang/String;
       5: ldc           #25                 // String :
       7: invokevirtual #26                 // Method java/lang/String.split:(Ljava/lang/String;)[Ljava/lang/String;
      10: astore_1
      11: aload_1
      12: arraylength
      13: istore_2
      14: iconst_0
      15: istore_3
      16: iload_3
      17: iload_2
      18: if_icmpge     59
      21: aload_1
      22: iload_3
      23: aaload
      24: astore        4
      26: aload         4
      28: aload_0
      29: invokevirtual #27                 // Method java/lang/String.endsWith:(Ljava/lang/String;)Z
      32: ifeq          53
      35: new           #9                  // class java/io/File
      38: dup
      39: aload         4
      41: invokespecial #11                 // Method java/io/File."<init>":(Ljava/lang/String;)V
      44: invokevirtual #28                 // Method java/io/File.isDirectory:()Z
      47: ifeq          53
      50: aload         4
      52: areturn
      53: iinc          3, 1
      56: goto          16
      59: new           #29                 // class java/io/FileNotFoundException
      62: dup
      63: aload_0
      64: invokespecial #30                 // Method java/io/FileNotFoundException."<init>":(Ljava/lang/String;)V
      67: athrow

  public static java.io.File findFile(java.lang.String...);
    Code:
       0: new           #9                  // class java/io/File
       3: dup
       4: ldc           #31                 // String .
       6: invokespecial #11                 // Method java/io/File."<init>":(Ljava/lang/String;)V
       9: invokevirtual #32                 // Method java/io/File.getAbsoluteFile:()Ljava/io/File;
      12: astore_1
      13: iconst_0
      14: istore_2
      15: iload_2
      16: aload_0
      17: arraylength
      18: iconst_1
      19: isub
      20: if_icmpge     50
      23: new           #9                  // class java/io/File
      26: dup
      27: aload_1
      28: aload_0
      29: iload_2
      30: aaload
      31: invokespecial #13                 // Method java/io/File."<init>":(Ljava/io/File;Ljava/lang/String;)V
      34: astore_3
      35: aload_3
      36: invokevirtual #28                 // Method java/io/File.isDirectory:()Z
      39: ifeq          44
      42: aload_3
      43: astore_1
      44: iinc          2, 1
      47: goto          15
      50: new           #9                  // class java/io/File
      53: dup
      54: aload_1
      55: aload_0
      56: aload_0
      57: arraylength
      58: iconst_1
      59: isub
      60: aaload
      61: invokespecial #13                 // Method java/io/File."<init>":(Ljava/io/File;Ljava/lang/String;)V
      64: areturn

  public static java.lang.String getHostName();
    Code:
       0: getstatic     #33                 // Field HOST_NAME:Ljava/lang/String;
       3: areturn

  public static java.lang.String getUserName();
    Code:
       0: getstatic     #34                 // Field USER_NAME:Ljava/lang/String;
       3: areturn

  public static java.lang.String getTarget();
    Code:
       0: getstatic     #35                 // Field TARGET:Ljava/lang/String;
       3: areturn

  private static java.lang.String getHostName0();
    Code:
       0: invokestatic  #36                 // Method java/net/InetAddress.getLocalHost:()Ljava/net/InetAddress;
       3: invokevirtual #37                 // Method java/net/InetAddress.getHostName:()Ljava/lang/String;
       6: areturn
       7: astore_0
       8: ldc           #39                 // String localhost
      10: areturn
    Exception table:
       from    to  target type
           0     6     7   Class java/net/UnknownHostException

  public static net.openhft.chronicle.core.Memory memory();
    Code:
       0: getstatic     #40                 // Field net/openhft/chronicle/core/UnsafeMemory.INSTANCE:Lnet/openhft/chronicle/core/UnsafeMemory;
       3: areturn

  public static long pageAlign(long);
    Code:
       0: invokestatic  #41                 // Method pageSize:()I
       3: i2l
       4: lconst_1
       5: lsub
       6: lstore_2
       7: lload_0
       8: lload_2
       9: ladd
      10: lload_2
      11: ldc2_w        #42                 // long -1l
      14: lxor
      15: land
      16: lreturn

  public static int pageSize();
    Code:
       0: getstatic     #44                 // Field PAGE_SIZE:I
       3: ifne          17
       6: invokestatic  #45                 // Method memory:()Lnet/openhft/chronicle/core/Memory;
       9: invokeinterface #46,  1           // InterfaceMethod net/openhft/chronicle/core/Memory.pageSize:()I
      14: putstatic     #44                 // Field PAGE_SIZE:I
      17: getstatic     #44                 // Field PAGE_SIZE:I
      20: ireturn

  public static long mapAlign(long);
    Code:
       0: invokestatic  #47                 // Method mapAlignment:()J
       3: l2i
       4: istore_2
       5: lload_0
       6: iload_2
       7: i2l
       8: ladd
       9: lconst_1
      10: lsub
      11: iload_2
      12: i2l
      13: ldiv
      14: iload_2
      15: i2l
      16: lmul
      17: lreturn

  public static long mapAlignment();
    Code:
       0: getstatic     #48                 // Field MAP_ALIGNMENT:I
       3: ifne          23
       6: invokestatic  #49                 // Method isWindows:()Z
       9: ifeq          17
      12: ldc           #50                 // int 65536
      14: goto          20
      17: invokestatic  #41                 // Method pageSize:()I
      20: putstatic     #48                 // Field MAP_ALIGNMENT:I
      23: getstatic     #48                 // Field MAP_ALIGNMENT:I
      26: i2l
      27: lreturn

  public static boolean is64Bit();
    Code:
       0: getstatic     #51                 // Field IS64BIT:Z
       3: ireturn

  private static boolean is64Bit0();
    Code:
       0: ldc           #52                 // String com.ibm.vm.bitmode
       2: invokestatic  #8                  // Method java/lang/System.getProperty:(Ljava/lang/String;)Ljava/lang/String;
       5: astore_0
       6: aload_0
       7: ifnull        17
      10: ldc           #53                 // String 64
      12: aload_0
      13: invokevirtual #54                 // Method java/lang/String.equals:(Ljava/lang/Object;)Z
      16: ireturn
      17: ldc           #55                 // String sun.arch.data.model
      19: invokestatic  #8                  // Method java/lang/System.getProperty:(Ljava/lang/String;)Ljava/lang/String;
      22: astore_0
      23: aload_0
      24: ifnull        34
      27: ldc           #53                 // String 64
      29: aload_0
      30: invokevirtual #54                 // Method java/lang/String.equals:(Ljava/lang/Object;)Z
      33: ireturn
      34: ldc           #56                 // String java.vm.version
      36: invokestatic  #8                  // Method java/lang/System.getProperty:(Ljava/lang/String;)Ljava/lang/String;
      39: astore_0
      40: aload_0
      41: ifnull        57
      44: aload_0
      45: ldc           #57                 // String _64
      47: invokevirtual #58                 // Method java/lang/String.contains:(Ljava/lang/CharSequence;)Z
      50: ifeq          57
      53: iconst_1
      54: goto          58
      57: iconst_0
      58: ireturn

  public static int getProcessId();
    Code:
       0: getstatic     #59                 // Field PROCESS_ID:Ljava/util/concurrent/atomic/AtomicInteger;
       3: invokevirtual #60                 // Method java/util/concurrent/atomic/AtomicInteger.get:()I
       6: istore_0
       7: iload_0
       8: ifne          22
      11: getstatic     #59                 // Field PROCESS_ID:Ljava/util/concurrent/atomic/AtomicInteger;
      14: invokestatic  #61                 // Method getProcessId0:()I
      17: dup
      18: istore_0
      19: invokevirtual #62                 // Method java/util/concurrent/atomic/AtomicInteger.set:(I)V
      22: iload_0
      23: ireturn

  private static int getProcessId0();
    Code:
       0: aconst_null
       1: astore_0
       2: new           #9                  // class java/io/File
       5: dup
       6: ldc           #63                 // String /proc/self
       8: invokespecial #11                 // Method java/io/File."<init>":(Ljava/lang/String;)V
      11: astore_1
      12: aload_1
      13: invokevirtual #14                 // Method java/io/File.exists:()Z
      16: ifeq          27
      19: aload_1
      20: invokevirtual #64                 // Method java/io/File.getCanonicalFile:()Ljava/io/File;
      23: invokevirtual #65                 // Method java/io/File.getName:()Ljava/lang/String;
      26: astore_0
      27: goto          31
      30: astore_2
      31: aload_0
      32: ifnonnull     52
      35: invokestatic  #67                 // Method java/lang/management/ManagementFactory.getRuntimeMXBean:()Ljava/lang/management/RuntimeMXBean;
      38: invokeinterface #68,  1           // InterfaceMethod java/lang/management/RuntimeMXBean.getName:()Ljava/lang/String;
      43: ldc           #69                 // String @
      45: iconst_0
      46: invokevirtual #70                 // Method java/lang/String.split:(Ljava/lang/String;I)[Ljava/lang/String;
      49: iconst_0
      50: aaload
      51: astore_0
      52: aload_0
      53: ifnull        62
      56: aload_0
      57: invokestatic  #71                 // Method java/lang/Integer.parseInt:(Ljava/lang/String;)I
      60: ireturn
      61: astore_2
      62: invokestatic  #73                 // Method java/util/concurrent/ThreadLocalRandom.current:()Ljava/util/concurrent/ThreadLocalRandom;
      65: iconst_2
      66: ldc           #50                 // int 65536
      68: invokevirtual #74                 // Method java/util/concurrent/ThreadLocalRandom.nextInt:(II)I
      71: istore_2
      72: invokestatic  #75                 // Method net/openhft/chronicle/core/Jvm.warn:()Lnet/openhft/chronicle/core/onoes/ExceptionHandler;
      75: ldc           #4                  // class net/openhft/chronicle/core/OS
      77: new           #18                 // class java/lang/StringBuilder
      80: dup
      81: invokespecial #19                 // Method java/lang/StringBuilder."<init>":()V
      84: ldc           #76                 // String Unable to determine PID, picked a random number=
      86: invokevirtual #21                 // Method java/lang/StringBuilder.append:(Ljava/lang/String;)Ljava/lang/StringBuilder;
      89: iload_2
      90: invokevirtual #77                 // Method java/lang/StringBuilder.append:(I)Ljava/lang/StringBuilder;
      93: invokevirtual #23                 // Method java/lang/StringBuilder.toString:()Ljava/lang/String;
      96: invokeinterface #78,  3           // InterfaceMethod net/openhft/chronicle/core/onoes/ExceptionHandler.on:(Ljava/lang/Class;Ljava/lang/String;)V
     101: iload_2
     102: ireturn
    Exception table:
       from    to  target type
          12    27    30   Class java/io/IOException
          56    60    61   Class java/lang/NumberFormatException

  public static boolean isWindows();
    Code:
       0: getstatic     #79                 // Field IS_WIN:Z
       3: ireturn

  public static boolean isMacOSX();
    Code:
       0: getstatic     #80                 // Field IS_MAC:Z
       3: ireturn

  public static boolean isLinux();
    Code:
       0: getstatic     #81                 // Field IS_LINUX:Z
       3: ireturn

  public static long getPidMax() throws java.lang.NumberFormatException;
    Code:
       0: invokestatic  #82                 // Method isLinux:()Z
       3: ifeq          143
       6: new           #9                  // class java/io/File
       9: dup
      10: ldc           #83                 // String /proc/sys/kernel/pid_max
      12: invokespecial #11                 // Method java/io/File."<init>":(Ljava/lang/String;)V
      15: astore_0
      16: aload_0
      17: invokevirtual #84                 // Method java/io/File.canRead:()Z
      20: ifeq          140
      23: new           #85                 // class java/util/Scanner
      26: dup
      27: aload_0
      28: invokespecial #86                 // Method java/util/Scanner."<init>":(Ljava/io/File;)V
      31: astore_1
      32: aconst_null
      33: astore_2
      34: aload_1
      35: invokevirtual #87                 // Method java/util/Scanner.nextLong:()J
      38: lconst_1
      39: invokestatic  #88                 // Method net/openhft/chronicle/core/Maths.nextPower2:(JJ)J
      42: lstore_3
      43: aload_1
      44: ifnull        73
      47: aload_2
      48: ifnull        69
      51: aload_1
      52: invokevirtual #89                 // Method java/util/Scanner.close:()V
      55: goto          73
      58: astore        5
      60: aload_2
      61: aload         5
      63: invokevirtual #91                 // Method java/lang/Throwable.addSuppressed:(Ljava/lang/Throwable;)V
      66: goto          73
      69: aload_1
      70: invokevirtual #89                 // Method java/util/Scanner.close:()V
      73: lload_3
      74: lreturn
      75: astore_3
      76: aload_3
      77: astore_2
      78: aload_3
      79: athrow
      80: astore        6
      82: aload_1
      83: ifnull        112
      86: aload_2
      87: ifnull        108
      90: aload_1
      91: invokevirtual #89                 // Method java/util/Scanner.close:()V
      94: goto          112
      97: astore        7
      99: aload_2
     100: aload         7
     102: invokevirtual #91                 // Method java/lang/Throwable.addSuppressed:(Ljava/lang/Throwable;)V
     105: goto          112
     108: aload_1
     109: invokevirtual #89                 // Method java/util/Scanner.close:()V
     112: aload         6
     114: athrow
     115: astore_1
     116: invokestatic  #92                 // Method net/openhft/chronicle/core/Jvm.debug:()Lnet/openhft/chronicle/core/onoes/ExceptionHandler;
     119: ldc           #4                  // class net/openhft/chronicle/core/OS
     121: aload_1
     122: invokeinterface #93,  3           // InterfaceMethod net/openhft/chronicle/core/onoes/ExceptionHandler.on:(Ljava/lang/Class;Ljava/lang/Throwable;)V
     127: goto          140
     130: astore_1
     131: new           #95                 // class java/lang/AssertionError
     134: dup
     135: aload_1
     136: invokespecial #96                 // Method java/lang/AssertionError."<init>":(Ljava/lang/Object;)V
     139: athrow
     140: goto          153
     143: invokestatic  #97                 // Method isMacOSX:()Z
     146: ifeq          153
     149: ldc2_w        #98                 // long 16777216l
     152: lreturn
     153: getstatic     #100                // Field IS_WIN10:Z
     156: ifeq          165
     159: ldc2_w        #101                // long 4294967296l
     162: goto          168
     165: ldc2_w        #103                // long 65536l
     168: lreturn
    Exception table:
       from    to  target type
          51    55    58   Class java/lang/Throwable
          34    43    75   Class java/lang/Throwable
          34    43    80   any
          90    94    97   Class java/lang/Throwable
          75    82    80   any
          23    73   115   Class java/io/FileNotFoundException
          75   115   115   Class java/io/FileNotFoundException
          23    73   130   Class java/lang/IllegalArgumentException
          75   115   130   Class java/lang/IllegalArgumentException

  public static long map(java.nio.channels.FileChannel, java.nio.channels.FileChannel$MapMode, long, long) throws java.io.IOException, java.lang.IllegalArgumentException;
    Code:
       0: invokestatic  #49                 // Method isWindows:()Z
       3: ifeq          51
       6: lload         4
       8: ldc2_w        #101                // long 4294967296l
      11: lcmp
      12: ifle          51
      15: new           #94                 // class java/lang/IllegalArgumentException
      18: dup
      19: new           #18                 // class java/lang/StringBuilder
      22: dup
      23: invokespecial #19                 // Method java/lang/StringBuilder."<init>":()V
      26: ldc           #105                // String Mapping more than 4096 MiB is unusable on Windows, size =
      28: invokevirtual #21                 // Method java/lang/StringBuilder.append:(Ljava/lang/String;)Ljava/lang/StringBuilder;
      31: lload         4
      33: bipush        20
      35: lshr
      36: invokevirtual #106                // Method java/lang/StringBuilder.append:(J)Ljava/lang/StringBuilder;
      39: ldc           #107                // String  MiB
      41: invokevirtual #21                 // Method java/lang/StringBuilder.append:(Ljava/lang/String;)Ljava/lang/StringBuilder;
      44: invokevirtual #23                 // Method java/lang/StringBuilder.toString:()Ljava/lang/String;
      47: invokespecial #108                // Method java/lang/IllegalArgumentException."<init>":(Ljava/lang/String;)V
      50: athrow
      51: aload_0
      52: aload_1
      53: invokestatic  #109                // Method imodeFor:(Ljava/nio/channels/FileChannel$MapMode;)I
      56: lload_2
      57: invokestatic  #110                // Method mapAlign:(J)J
      60: lload         4
      62: invokestatic  #111                // Method pageAlign:(J)J
      65: invokestatic  #112                // Method map0:(Ljava/nio/channels/FileChannel;IJJ)J
      68: lreturn

  private static long invokeFileChannelMap0(java.lang.invoke.MethodHandle, java.nio.channels.FileChannel, int, long, long, net.openhft.chronicle.core.util.ThrowingFunction<java.lang.OutOfMemoryError, java.lang.Long, java.io.IOException>) throws java.io.IOException;
    Code:
       0: invokestatic  #113                // Method net/openhft/chronicle/core/Jvm.isJava14Plus:()Z
       3: ifeq          20
       6: aload_0
       7: aload_1
       8: checkcast     #114                // class sun/nio/ch/FileChannelImpl
      11: iload_2
      12: lload_3
      13: lload         5
      15: iconst_0
      16: invokevirtual #115                // Method java/lang/invoke/MethodHandle.invokeExact:(Lsun/nio/ch/FileChannelImpl;IJJZ)J
      19: lreturn
      20: aload_0
      21: aload_1
      22: checkcast     #114                // class sun/nio/ch/FileChannelImpl
      25: iload_2
      26: lload_3
      27: lload         5
      29: invokevirtual #116                // Method java/lang/invoke/MethodHandle.invokeExact:(Lsun/nio/ch/FileChannelImpl;IJJ)J
      32: lreturn
      33: astore        8
      35: new           #95                 // class java/lang/AssertionError
      38: dup
      39: ldc           #118                // String Method map0 is not accessible
      41: aload         8
      43: invokespecial #119                // Method java/lang/AssertionError."<init>":(Ljava/lang/String;Ljava/lang/Throwable;)V
      46: athrow
      47: astore        8
      49: aload         8
      51: instanceof    #120                // class java/lang/OutOfMemoryError
      54: ifeq          76
      57: aload         7
      59: aload         8
      61: checkcast     #120                // class java/lang/OutOfMemoryError
      64: invokeinterface #121,  2          // InterfaceMethod net/openhft/chronicle/core/util/ThrowingFunction.apply:(Ljava/lang/Object;)Ljava/lang/Object;
      69: checkcast     #122                // class java/lang/Long
      72: invokevirtual #123                // Method java/lang/Long.longValue:()J
      75: lreturn
      76: aload         8
      78: instanceof    #66                 // class java/io/IOException
      81: ifeq          90
      84: aload         8
      86: checkcast     #66                 // class java/io/IOException
      89: athrow
      90: new           #66                 // class java/io/IOException
      93: dup
      94: aload         8
      96: invokespecial #124                // Method java/io/IOException."<init>":(Ljava/lang/Throwable;)V
      99: athrow
    Exception table:
       from    to  target type
           0    19    33   Class java/lang/IllegalAccessException
          20    32    33   Class java/lang/IllegalAccessException
           0    19    47   Class java/lang/Throwable
          20    32    47   Class java/lang/Throwable

  static long map0(java.nio.channels.FileChannel, int, long, long) throws java.io.IOException;
    Code:
       0: getstatic     #125                // Field MAP0_MH:Lnet/openhft/chronicle/core/ClassLocal;
       3: aload_0
       4: invokevirtual #126                // Method java/lang/Object.getClass:()Ljava/lang/Class;
       7: invokevirtual #127                // Method net/openhft/chronicle/core/ClassLocal.get:(Ljava/lang/Class;)Ljava/lang/Object;
      10: checkcast     #128                // class java/lang/invoke/MethodHandle
      13: astore        6
      15: aload         6
      17: aload_0
      18: iload_1
      19: lload_2
      20: lload         4
      22: aload         6
      24: aload_0
      25: iload_1
      26: lload_2
      27: lload         4
      29: invokedynamic #129,  0            // InvokeDynamic #0:apply:(Ljava/lang/invoke/MethodHandle;Ljava/nio/channels/FileChannel;IJJ)Lnet/openhft/chronicle/core/util/ThrowingFunction;
      34: invokestatic  #130                // Method invokeFileChannelMap0:(Ljava/lang/invoke/MethodHandle;Ljava/nio/channels/FileChannel;IJJLnet/openhft/chronicle/core/util/ThrowingFunction;)J
      37: lstore        7
      39: getstatic     #131                // Field memoryMapped:Ljava/util/concurrent/atomic/AtomicLong;
      42: lload         4
      44: invokevirtual #132                // Method java/util/concurrent/atomic/AtomicLong.addAndGet:(J)J
      47: pop2
      48: lload         7
      50: lreturn

  public static void unmap(long, long) throws java.io.IOException;
    Code:
       0: lload_2
       1: invokestatic  #111                // Method pageAlign:(J)J
       4: lstore        4
       6: getstatic     #133                // Field UNMAPP0_MH:Ljava/lang/invoke/MethodHandle;
       9: lload_0
      10: lload         4
      12: invokevirtual #134                // Method java/lang/invoke/MethodHandle.invokeExact:(JJ)I
      15: istore        6
      17: getstatic     #131                // Field memoryMapped:Ljava/util/concurrent/atomic/AtomicLong;
      20: lload         4
      22: lneg
      23: invokevirtual #132                // Method java/util/concurrent/atomic/AtomicLong.addAndGet:(J)J
      26: pop2
      27: goto          38
      30: astore        4
      32: aload         4
      34: invokestatic  #135                // Method asAnIOException:(Ljava/lang/Throwable;)Ljava/io/IOException;
      37: athrow
      38: return
    Exception table:
       from    to  target type
           0    27    30   Class java/lang/Throwable

  public static long memoryMapped();
    Code:
       0: getstatic     #131                // Field memoryMapped:Ljava/util/concurrent/atomic/AtomicLong;
       3: invokevirtual #136                // Method java/util/concurrent/atomic/AtomicLong.get:()J
       6: lreturn

  private static java.io.IOException asAnIOException(java.lang.Throwable);
    Code:
       0: aload_0
       1: instanceof    #137                // class java/lang/reflect/InvocationTargetException
       4: ifeq          12
       7: aload_0
       8: invokevirtual #138                // Method java/lang/Throwable.getCause:()Ljava/lang/Throwable;
      11: astore_0
      12: aload_0
      13: instanceof    #66                 // class java/io/IOException
      16: ifeq          24
      19: aload_0
      20: checkcast     #66                 // class java/io/IOException
      23: areturn
      24: new           #66                 // class java/io/IOException
      27: dup
      28: aload_0
      29: invokespecial #124                // Method java/io/IOException."<init>":(Ljava/lang/Throwable;)V
      32: areturn

  static int imodeFor(java.nio.channels.FileChannel$MapMode);
    Code:
       0: iconst_m1
       1: istore_1
       2: getstatic     #139                // Field java/nio/channels/FileChannel$MapMode.READ_ONLY:Ljava/nio/channels/FileChannel$MapMode;
       5: aload_0
       6: invokevirtual #140                // Method java/lang/Object.equals:(Ljava/lang/Object;)Z
       9: ifeq          17
      12: iconst_0
      13: istore_1
      14: goto          44
      17: getstatic     #141                // Field java/nio/channels/FileChannel$MapMode.READ_WRITE:Ljava/nio/channels/FileChannel$MapMode;
      20: aload_0
      21: invokevirtual #140                // Method java/lang/Object.equals:(Ljava/lang/Object;)Z
      24: ifeq          32
      27: iconst_1
      28: istore_1
      29: goto          44
      32: getstatic     #142                // Field java/nio/channels/FileChannel$MapMode.PRIVATE:Ljava/nio/channels/FileChannel$MapMode;
      35: aload_0
      36: invokevirtual #140                // Method java/lang/Object.equals:(Ljava/lang/Object;)Z
      39: ifeq          44
      42: iconst_2
      43: istore_1
      44: getstatic     #143                // Field $assertionsDisabled:Z
      47: ifne          62
      50: iload_1
      51: ifge          62
      54: new           #95                 // class java/lang/AssertionError
      57: dup
      58: invokespecial #144                // Method java/lang/AssertionError."<init>":()V
      61: athrow
      62: iload_1
      63: ireturn

  public static long spaceUsed(java.lang.String);
    Code:
       0: new           #9                  // class java/io/File
       3: dup
       4: aload_0
       5: invokespecial #11                 // Method java/io/File."<init>":(Ljava/lang/String;)V
       8: invokestatic  #145                // Method spaceUsed:(Ljava/io/File;)J
      11: lreturn

  private static long spaceUsed(java.io.File);
    Code:
       0: invokestatic  #49                 // Method isWindows:()Z
       3: ifne          58
       6: iconst_3
       7: anewarray     #146                // class java/lang/String
      10: dup
      11: iconst_0
      12: ldc           #147                // String du
      14: aastore
      15: dup
      16: iconst_1
      17: ldc           #148                // String -ks
      19: aastore
      20: dup
      21: iconst_2
      22: aload_0
      23: invokevirtual #15                 // Method java/io/File.getAbsolutePath:()Ljava/lang/String;
      26: aastore
      27: invokestatic  #149                // Method run:([Ljava/lang/String;)Ljava/lang/String;
      30: astore_1
      31: aload_1
      32: iconst_0
      33: aload_1
      34: bipush        9
      36: invokevirtual #150                // Method java/lang/String.indexOf:(I)I
      39: invokevirtual #151                // Method java/lang/String.substring:(II)Ljava/lang/String;
      42: invokestatic  #152                // Method java/lang/Long.parseLong:(Ljava/lang/String;)J
      45: lreturn
      46: astore_1
      47: invokestatic  #75                 // Method net/openhft/chronicle/core/Jvm.warn:()Lnet/openhft/chronicle/core/onoes/ExceptionHandler;
      50: ldc           #4                  // class net/openhft/chronicle/core/OS
      52: aload_1
      53: invokeinterface #93,  3           // InterfaceMethod net/openhft/chronicle/core/onoes/ExceptionHandler.on:(Ljava/lang/Class;Ljava/lang/Throwable;)V
      58: aload_0
      59: invokevirtual #154                // Method java/io/File.length:()J
      62: lreturn
    Exception table:
       from    to  target type
           6    45    46   Class java/io/IOException
           6    45    46   Class java/lang/NumberFormatException

  private static java.lang.String run(java.lang.String...) throws java.io.IOException;
    Code:
       0: new           #155                // class java/lang/ProcessBuilder
       3: dup
       4: aload_0
       5: invokespecial #156                // Method java/lang/ProcessBuilder."<init>":([Ljava/lang/String;)V
       8: astore_1
       9: aload_1
      10: iconst_1
      11: invokevirtual #157                // Method java/lang/ProcessBuilder.redirectErrorStream:(Z)Ljava/lang/ProcessBuilder;
      14: pop
      15: aload_1
      16: invokevirtual #158                // Method java/lang/ProcessBuilder.start:()Ljava/lang/Process;
      19: astore_2
      20: new           #159                // class java/io/StringWriter
      23: dup
      24: invokespecial #160                // Method java/io/StringWriter."<init>":()V
      27: astore_3
      28: sipush        1024
      31: newarray       char
      33: astore        4
      35: new           #161                // class java/io/InputStreamReader
      38: dup
      39: aload_2
      40: invokevirtual #162                // Method java/lang/Process.getInputStream:()Ljava/io/InputStream;
      43: invokespecial #163                // Method java/io/InputStreamReader."<init>":(Ljava/io/InputStream;)V
      46: astore        5
      48: aconst_null
      49: astore        6
      51: aload         5
      53: aload         4
      55: invokevirtual #164                // Method java/io/Reader.read:([C)I
      58: dup
      59: istore        7
      61: ifle          76
      64: aload_3
      65: aload         4
      67: iconst_0
      68: iload         7
      70: invokevirtual #165                // Method java/io/StringWriter.write:([CII)V
      73: goto          51
      76: aload         5
      78: ifnull        163
      81: aload         6
      83: ifnull        106
      86: aload         5
      88: invokevirtual #166                // Method java/io/Reader.close:()V
      91: goto          163
      94: astore        7
      96: aload         6
      98: aload         7
     100: invokevirtual #91                 // Method java/lang/Throwable.addSuppressed:(Ljava/lang/Throwable;)V
     103: goto          163
     106: aload         5
     108: invokevirtual #166                // Method java/io/Reader.close:()V
     111: goto          163
     114: astore        7
     116: aload         7
     118: astore        6
     120: aload         7
     122: athrow
     123: astore        8
     125: aload         5
     127: ifnull        160
     130: aload         6
     132: ifnull        155
     135: aload         5
     137: invokevirtual #166                // Method java/io/Reader.close:()V
     140: goto          160
     143: astore        9
     145: aload         6
     147: aload         9
     149: invokevirtual #91                 // Method java/lang/Throwable.addSuppressed:(Ljava/lang/Throwable;)V
     152: goto          160
     155: aload         5
     157: invokevirtual #166                // Method java/io/Reader.close:()V
     160: aload         8
     162: athrow
     163: aload_3
     164: invokevirtual #167                // Method java/io/StringWriter.toString:()Ljava/lang/String;
     167: areturn
    Exception table:
       from    to  target type
          86    91    94   Class java/lang/Throwable
          51    76   114   Class java/lang/Throwable
          51    76   123   any
         135   140   143   Class java/lang/Throwable
         114   125   123   any

  public static java.lang.String userDir();
    Code:
       0: getstatic     #168                // Field USER_DIR:Ljava/lang/String;
       3: areturn

  public static int read0(java.io.FileDescriptor, long, int) throws java.io.IOException;
    Code:
       0: getstatic     #169                // Field READ0_MH:Ljava/lang/invoke/MethodHandle;
       3: aload_0
       4: lload_1
       5: iload_3
       6: invokevirtual #170                // Method java/lang/invoke/MethodHandle.invokeExact:(Ljava/io/FileDescriptor;JI)I
       9: ireturn
      10: astore        4
      12: aload         4
      14: athrow
      15: astore        4
      17: new           #66                 // class java/io/IOException
      20: dup
      21: aload         4
      23: invokespecial #124                // Method java/io/IOException."<init>":(Ljava/lang/Throwable;)V
      26: athrow
    Exception table:
       from    to  target type
           0     9    10   Class java/io/IOException
           0     9    15   Class java/lang/Throwable

  public static int write0(java.io.FileDescriptor, long, int) throws java.io.IOException;
    Code:
       0: getstatic     #171                // Field WRITE0_MH2:Ljava/lang/invoke/MethodHandle;
       3: ifnonnull     16
       6: getstatic     #172                // Field WRITE0_MH:Ljava/lang/invoke/MethodHandle;
       9: aload_0
      10: lload_1
      11: iload_3
      12: invokevirtual #170                // Method java/lang/invoke/MethodHandle.invokeExact:(Ljava/io/FileDescriptor;JI)I
      15: ireturn
      16: getstatic     #171                // Field WRITE0_MH2:Ljava/lang/invoke/MethodHandle;
      19: aload_0
      20: lload_1
      21: iload_3
      22: iconst_0
      23: invokevirtual #173                // Method java/lang/invoke/MethodHandle.invokeExact:(Ljava/io/FileDescriptor;JIZ)I
      26: ireturn
      27: astore        4
      29: aload         4
      31: athrow
      32: astore        4
      34: new           #66                 // class java/io/IOException
      37: dup
      38: aload         4
      40: invokespecial #124                // Method java/io/IOException."<init>":(Ljava/lang/Throwable;)V
      43: athrow
    Exception table:
       from    to  target type
           0    15    27   Class java/io/IOException
          16    26    27   Class java/io/IOException
           0    15    32   Class java/lang/Throwable
          16    26    32   Class java/lang/Throwable

  private static java.lang.Long lambda$map0$2(java.lang.invoke.MethodHandle, java.nio.channels.FileChannel, int, long, long, java.lang.OutOfMemoryError) throws java.io.IOException;
    Code:
       0: invokestatic  #174                // Method java/lang/System.gc:()V
       3: ldc2_w        #175                // long 100l
       6: invokestatic  #177                // Method net/openhft/chronicle/core/Jvm.pause:(J)V
       9: aload_0
      10: aload_1
      11: iload_2
      12: lload_3
      13: lload         5
      15: invokedynamic #178,  0            // InvokeDynamic #1:apply:()Lnet/openhft/chronicle/core/util/ThrowingFunction;
      20: invokestatic  #130                // Method invokeFileChannelMap0:(Ljava/lang/invoke/MethodHandle;Ljava/nio/channels/FileChannel;IJJLnet/openhft/chronicle/core/util/ThrowingFunction;)J
      23: invokestatic  #179                // Method java/lang/Long.valueOf:(J)Ljava/lang/Long;
      26: areturn

  private static java.lang.Long lambda$null$1(java.lang.OutOfMemoryError) throws java.io.IOException;
    Code:
       0: new           #66                 // class java/io/IOException
       3: dup
       4: ldc           #180                // String Map failed
       6: aload_0
       7: invokespecial #181                // Method java/io/IOException."<init>":(Ljava/lang/String;Ljava/lang/Throwable;)V
      10: athrow

  private static java.lang.invoke.MethodHandle lambda$static$0(java.lang.Class);
    Code:
       0: invokestatic  #113                // Method net/openhft/chronicle/core/Jvm.isJava14Plus:()Z
       3: ifeq          44
       6: aload_0
       7: ldc           #182                // String map0
       9: iconst_4
      10: anewarray     #183                // class java/lang/Class
      13: dup
      14: iconst_0
      15: getstatic     #184                // Field java/lang/Integer.TYPE:Ljava/lang/Class;
      18: aastore
      19: dup
      20: iconst_1
      21: getstatic     #185                // Field java/lang/Long.TYPE:Ljava/lang/Class;
      24: aastore
      25: dup
      26: iconst_2
      27: getstatic     #185                // Field java/lang/Long.TYPE:Ljava/lang/Class;
      30: aastore
      31: dup
      32: iconst_3
      33: getstatic     #186                // Field java/lang/Boolean.TYPE:Ljava/lang/Class;
      36: aastore
      37: invokestatic  #187                // Method net/openhft/chronicle/core/Jvm.getMethod:(Ljava/lang/Class;Ljava/lang/String;[Ljava/lang/Class;)Ljava/lang/reflect/Method;
      40: astore_1
      41: goto          73
      44: aload_0
      45: ldc           #182                // String map0
      47: iconst_3
      48: anewarray     #183                // class java/lang/Class
      51: dup
      52: iconst_0
      53: getstatic     #184                // Field java/lang/Integer.TYPE:Ljava/lang/Class;
      56: aastore
      57: dup
      58: iconst_1
      59: getstatic     #185                // Field java/lang/Long.TYPE:Ljava/lang/Class;
      62: aastore
      63: dup
      64: iconst_2
      65: getstatic     #185                // Field java/lang/Long.TYPE:Ljava/lang/Class;
      68: aastore
      69: invokestatic  #187                // Method net/openhft/chronicle/core/Jvm.getMethod:(Ljava/lang/Class;Ljava/lang/String;[Ljava/lang/Class;)Ljava/lang/reflect/Method;
      72: astore_1
      73: invokestatic  #188                // Method java/lang/invoke/MethodHandles.lookup:()Ljava/lang/invoke/MethodHandles$Lookup;
      76: aload_1
      77: invokevirtual #189                // Method java/lang/invoke/MethodHandles$Lookup.unreflect:(Ljava/lang/reflect/Method;)Ljava/lang/invoke/MethodHandle;
      80: areturn
      81: astore_1
      82: new           #95                 // class java/lang/AssertionError
      85: dup
      86: aload_1
      87: invokespecial #96                 // Method java/lang/AssertionError."<init>":(Ljava/lang/Object;)V
      90: athrow
    Exception table:
       from    to  target type
           0    80    81   Class java/lang/IllegalAccessException

  static {};
    Code:
       0: ldc           #4                  // class net/openhft/chronicle/core/OS
       2: invokevirtual #190                // Method java/lang/Class.desiredAssertionStatus:()Z
       5: ifne          12
       8: iconst_1
       9: goto          13
      12: iconst_0
      13: putstatic     #143                // Field $assertionsDisabled:Z
      16: iconst_0
      17: anewarray     #4                  // class net/openhft/chronicle/core/OS
      20: putstatic     #1                  // Field $VALUES:[Lnet/openhft/chronicle/core/OS;
      23: ldc           #191                // String java.io.tmpdir
      25: invokestatic  #8                  // Method java/lang/System.getProperty:(Ljava/lang/String;)Ljava/lang/String;
      28: putstatic     #20                 // Field TMP:Ljava/lang/String;
      31: ldc           #10                 // String user.dir
      33: invokestatic  #8                  // Method java/lang/System.getProperty:(Ljava/lang/String;)Ljava/lang/String;
      36: putstatic     #168                // Field USER_DIR:Ljava/lang/String;
      39: ldc           #192                // String user.home
      41: invokestatic  #8                  // Method java/lang/System.getProperty:(Ljava/lang/String;)Ljava/lang/String;
      44: putstatic     #193                // Field USER_HOME:Ljava/lang/String;
      47: new           #194                // class javax/naming/TimeLimitExceededException
      50: dup
      51: invokespecial #195                // Method javax/naming/TimeLimitExceededException."<init>":()V
      54: putstatic     #196                // Field TIME_LIMIT:Ljava/lang/Exception;
      57: invokestatic  #197                // Method findTarget:()Ljava/lang/String;
      60: putstatic     #35                 // Field TARGET:Ljava/lang/String;
      63: invokedynamic #198,  0            // InvokeDynamic #2:apply:()Ljava/util/function/Function;
      68: invokestatic  #199                // Method net/openhft/chronicle/core/ClassLocal.withInitial:(Ljava/util/function/Function;)Lnet/openhft/chronicle/core/ClassLocal;
      71: putstatic     #125                // Field MAP0_MH:Lnet/openhft/chronicle/core/ClassLocal;
      74: invokestatic  #200                // Method getHostName0:()Ljava/lang/String;
      77: putstatic     #33                 // Field HOST_NAME:Ljava/lang/String;
      80: ldc           #201                // String user.name
      82: invokestatic  #8                  // Method java/lang/System.getProperty:(Ljava/lang/String;)Ljava/lang/String;
      85: putstatic     #34                 // Field USER_NAME:Ljava/lang/String;
      88: invokestatic  #202                // Method is64Bit0:()Z
      91: putstatic     #51                 // Field IS64BIT:Z
      94: new           #203                // class java/util/concurrent/atomic/AtomicInteger
      97: dup
      98: invokespecial #204                // Method java/util/concurrent/atomic/AtomicInteger."<init>":()V
     101: putstatic     #59                 // Field PROCESS_ID:Ljava/util/concurrent/atomic/AtomicInteger;
     104: ldc           #205                // String os.name
     106: invokestatic  #8                  // Method java/lang/System.getProperty:(Ljava/lang/String;)Ljava/lang/String;
     109: invokevirtual #206                // Method java/lang/String.toLowerCase:()Ljava/lang/String;
     112: putstatic     #207                // Field OS:Ljava/lang/String;
     115: getstatic     #207                // Field OS:Ljava/lang/String;
     118: ldc           #208                // String linux
     120: invokevirtual #209                // Method java/lang/String.startsWith:(Ljava/lang/String;)Z
     123: putstatic     #81                 // Field IS_LINUX:Z
     126: getstatic     #207                // Field OS:Ljava/lang/String;
     129: ldc           #210                // String mac
     131: invokevirtual #58                 // Method java/lang/String.contains:(Ljava/lang/CharSequence;)Z
     134: putstatic     #80                 // Field IS_MAC:Z
     137: getstatic     #207                // Field OS:Ljava/lang/String;
     140: ldc           #211                // String win
     142: invokevirtual #209                // Method java/lang/String.startsWith:(Ljava/lang/String;)Z
     145: putstatic     #79                 // Field IS_WIN:Z
     148: getstatic     #207                // Field OS:Ljava/lang/String;
     151: ldc           #212                // String windows 10
     153: invokevirtual #54                 // Method java/lang/String.equals:(Ljava/lang/Object;)Z
     156: putstatic     #100                // Field IS_WIN10:Z
     159: new           #213                // class java/util/concurrent/atomic/AtomicLong
     162: dup
     163: invokespecial #214                // Method java/util/concurrent/atomic/AtomicLong."<init>":()V
     166: putstatic     #131                // Field memoryMapped:Ljava/util/concurrent/atomic/AtomicLong;
     169: invokestatic  #92                 // Method net/openhft/chronicle/core/Jvm.debug:()Lnet/openhft/chronicle/core/onoes/ExceptionHandler;
     172: pop
     173: ldc           #114                // class sun/nio/ch/FileChannelImpl
     175: ldc           #215                // String unmap0
     177: iconst_2
     178: anewarray     #183                // class java/lang/Class
     181: dup
     182: iconst_0
     183: getstatic     #185                // Field java/lang/Long.TYPE:Ljava/lang/Class;
     186: aastore
     187: dup
     188: iconst_1
     189: getstatic     #185                // Field java/lang/Long.TYPE:Ljava/lang/Class;
     192: aastore
     193: invokestatic  #187                // Method net/openhft/chronicle/core/Jvm.getMethod:(Ljava/lang/Class;Ljava/lang/String;[Ljava/lang/Class;)Ljava/lang/reflect/Method;
     196: astore_0
     197: invokestatic  #188                // Method java/lang/invoke/MethodHandles.lookup:()Ljava/lang/invoke/MethodHandles$Lookup;
     200: aload_0
     201: invokevirtual #189                // Method java/lang/invoke/MethodHandles$Lookup.unreflect:(Ljava/lang/reflect/Method;)Ljava/lang/invoke/MethodHandle;
     204: putstatic     #133                // Field UNMAPP0_MH:Ljava/lang/invoke/MethodHandle;
     207: ldc           #216                // String sun.nio.ch.FileDispatcherImpl
     209: invokestatic  #217                // Method java/lang/Class.forName:(Ljava/lang/String;)Ljava/lang/Class;
     212: astore_1
     213: aload_1
     214: ldc           #218                // String read0
     216: iconst_3
     217: anewarray     #183                // class java/lang/Class
     220: dup
     221: iconst_0
     222: ldc           #219                // class java/io/FileDescriptor
     224: aastore
     225: dup
     226: iconst_1
     227: getstatic     #185                // Field java/lang/Long.TYPE:Ljava/lang/Class;
     230: aastore
     231: dup
     232: iconst_2
     233: getstatic     #184                // Field java/lang/Integer.TYPE:Ljava/lang/Class;
     236: aastore
     237: invokestatic  #187                // Method net/openhft/chronicle/core/Jvm.getMethod:(Ljava/lang/Class;Ljava/lang/String;[Ljava/lang/Class;)Ljava/lang/reflect/Method;
     240: astore_2
     241: invokestatic  #188                // Method java/lang/invoke/MethodHandles.lookup:()Ljava/lang/invoke/MethodHandles$Lookup;
     244: aload_2
     245: invokevirtual #189                // Method java/lang/invoke/MethodHandles$Lookup.unreflect:(Ljava/lang/reflect/Method;)Ljava/lang/invoke/MethodHandle;
     248: putstatic     #169                // Field READ0_MH:Ljava/lang/invoke/MethodHandle;
     251: aconst_null
     252: astore_3
     253: aconst_null
     254: astore        4
     256: aload_1
     257: ldc           #220                // String write0
     259: iconst_3
     260: anewarray     #183                // class java/lang/Class
     263: dup
     264: iconst_0
     265: ldc           #219                // class java/io/FileDescriptor
     267: aastore
     268: dup
     269: iconst_1
     270: getstatic     #185                // Field java/lang/Long.TYPE:Ljava/lang/Class;
     273: aastore
     274: dup
     275: iconst_2
     276: getstatic     #184                // Field java/lang/Integer.TYPE:Ljava/lang/Class;
     279: aastore
     280: invokestatic  #187                // Method net/openhft/chronicle/core/Jvm.getMethod:(Ljava/lang/Class;Ljava/lang/String;[Ljava/lang/Class;)Ljava/lang/reflect/Method;
     283: astore        5
     285: invokestatic  #188                // Method java/lang/invoke/MethodHandles.lookup:()Ljava/lang/invoke/MethodHandles$Lookup;
     288: aload         5
     290: invokevirtual #189                // Method java/lang/invoke/MethodHandles$Lookup.unreflect:(Ljava/lang/reflect/Method;)Ljava/lang/invoke/MethodHandle;
     293: astore_3
     294: goto          344
     297: astore        5
     299: aload_1
     300: ldc           #220                // String write0
     302: iconst_4
     303: anewarray     #183                // class java/lang/Class
     306: dup
     307: iconst_0
     308: ldc           #219                // class java/io/FileDescriptor
     310: aastore
     311: dup
     312: iconst_1
     313: getstatic     #185                // Field java/lang/Long.TYPE:Ljava/lang/Class;
     316: aastore
     317: dup
     318: iconst_2
     319: getstatic     #184                // Field java/lang/Integer.TYPE:Ljava/lang/Class;
     322: aastore
     323: dup
     324: iconst_3
     325: getstatic     #186                // Field java/lang/Boolean.TYPE:Ljava/lang/Class;
     328: aastore
     329: invokestatic  #187                // Method net/openhft/chronicle/core/Jvm.getMethod:(Ljava/lang/Class;Ljava/lang/String;[Ljava/lang/Class;)Ljava/lang/reflect/Method;
     332: astore        6
     334: invokestatic  #188                // Method java/lang/invoke/MethodHandles.lookup:()Ljava/lang/invoke/MethodHandles$Lookup;
     337: aload         6
     339: invokevirtual #189                // Method java/lang/invoke/MethodHandles$Lookup.unreflect:(Ljava/lang/reflect/Method;)Ljava/lang/invoke/MethodHandle;
     342: astore        4
     344: aload_3
     345: putstatic     #172                // Field WRITE0_MH:Ljava/lang/invoke/MethodHandle;
     348: aload         4
     350: putstatic     #171                // Field WRITE0_MH2:Ljava/lang/invoke/MethodHandle;
     353: getstatic     #196                // Field TIME_LIMIT:Ljava/lang/Exception;
     356: iconst_0
     357: anewarray     #221                // class java/lang/StackTraceElement
     360: invokevirtual #222                // Method java/lang/Exception.setStackTrace:([Ljava/lang/StackTraceElement;)V
     363: goto          376
     366: astore_0
     367: new           #95                 // class java/lang/AssertionError
     370: dup
     371: aload_0
     372: invokespecial #96                 // Method java/lang/AssertionError."<init>":(Ljava/lang/Object;)V
     375: athrow
     376: return
    Exception table:
       from    to  target type
         256   294   297   Class java/lang/AssertionError
         173   363   366   Class java/lang/IllegalAccessException
         173   363   366   Class java/lang/ClassNotFoundException
}
