public class nu.xom.jaxen.function.FalseFunction implements nu.xom.jaxen.Function {
  public nu.xom.jaxen.function.FalseFunction();
    Code:
       0: aload_0
       1: invokespecial #10                 // Method java/lang/Object."<init>":()V
       4: return

  public java.lang.Object call(nu.xom.jaxen.Context, java.util.List) throws nu.xom.jaxen.FunctionCallException;
    Code:
       0: aload_2
       1: invokeinterface #20,  1           // InterfaceMethod java/util/List.size:()I
       6: ifne          13
       9: invokestatic  #24                 // Method evaluate:()Ljava/lang/Boolean;
      12: areturn
      13: new           #14                 // class nu/xom/jaxen/FunctionCallException
      16: dup
      17: ldc           #26                 // String false() requires no arguments.
      19: invokespecial #29                 // Method nu/xom/jaxen/FunctionCallException."<init>":(Ljava/lang/String;)V
      22: athrow

  public static java.lang.Boolean evaluate();
    Code:
       0: getstatic     #35                 // Field java/lang/Boolean.FALSE:Ljava/lang/Boolean;
       3: areturn
}
