class org.bouncycastle.cert.jcajce.NamedCertHelper extends org.bouncycastle.cert.jcajce.CertHelper {
  private final java.lang.String providerName;

  org.bouncycastle.cert.jcajce.NamedCertHelper(java.lang.String);
    Code:
       0: aload_0
       1: invokespecial #25                 // Method org/bouncycastle/cert/jcajce/CertHelper."<init>":()V
       4: aload_0
       5: aload_1
       6: putfield      #23                 // Field providerName:Ljava/lang/String;
       9: return

  protected java.security.cert.CertificateFactory createCertificateFactory(java.lang.String) throws java.security.cert.CertificateException, java.security.NoSuchProviderException;
    Code:
       0: aload_1
       1: aload_0
       2: getfield      #23                 // Field providerName:Ljava/lang/String;
       5: invokestatic  #24                 // Method java/security/cert/CertificateFactory.getInstance:(Ljava/lang/String;Ljava/lang/String;)Ljava/security/cert/CertificateFactory;
       8: areturn
}
