Compiled from "DefaultConfigurationBuilder.java"
public class org.apache.logging.log4j.core.config.builder.impl.DefaultConfigurationBuilder<T extends org.apache.logging.log4j.core.config.builder.impl.BuiltConfiguration> implements org.apache.logging.log4j.core.config.builder.api.ConfigurationBuilder<T> {
  private static final java.lang.String INDENT;

  private final org.apache.logging.log4j.core.config.builder.api.Component root;

  private org.apache.logging.log4j.core.config.builder.api.Component loggers;

  private org.apache.logging.log4j.core.config.builder.api.Component appenders;

  private org.apache.logging.log4j.core.config.builder.api.Component filters;

  private org.apache.logging.log4j.core.config.builder.api.Component properties;

  private org.apache.logging.log4j.core.config.builder.api.Component customLevels;

  private org.apache.logging.log4j.core.config.builder.api.Component scripts;

  private final java.lang.Class<T> clazz;

  private org.apache.logging.log4j.core.config.ConfigurationSource source;

  private int monitorInterval;

  private org.apache.logging.log4j.Level level;

  private java.lang.String verbosity;

  private java.lang.String destination;

  private java.lang.String packages;

  private java.lang.String shutdownFlag;

  private long shutdownTimeoutMillis;

  private java.lang.String advertiser;

  private org.apache.logging.log4j.core.LoggerContext loggerContext;

  private java.lang.String name;

  public static void formatXml(javax.xml.transform.Source, javax.xml.transform.Result) throws javax.xml.transform.TransformerConfigurationException, javax.xml.transform.TransformerFactoryConfigurationError, javax.xml.transform.TransformerException;
    Code:
       0: invokestatic  #1                  // Method javax/xml/transform/TransformerFactory.newInstance:()Ljavax/xml/transform/TransformerFactory;
       3: invokevirtual #2                  // Method javax/xml/transform/TransformerFactory.newTransformer:()Ljavax/xml/transform/Transformer;
       6: astore_2
       7: aload_2
       8: ldc           #3                  // String {http://xml.apache.org/xslt}indent-amount
      10: ldc           #5                  // String
      12: invokevirtual #6                  // Method java/lang/String.length:()I
      15: invokestatic  #7                  // Method java/lang/Integer.toString:(I)Ljava/lang/String;
      18: invokevirtual #8                  // Method javax/xml/transform/Transformer.setOutputProperty:(Ljava/lang/String;Ljava/lang/String;)V
      21: aload_2
      22: ldc           #10                 // String indent
      24: ldc           #11                 // String yes
      26: invokevirtual #8                  // Method javax/xml/transform/Transformer.setOutputProperty:(Ljava/lang/String;Ljava/lang/String;)V
      29: aload_2
      30: aload_0
      31: aload_1
      32: invokevirtual #12                 // Method javax/xml/transform/Transformer.transform:(Ljavax/xml/transform/Source;Ljavax/xml/transform/Result;)V
      35: return

  public org.apache.logging.log4j.core.config.builder.impl.DefaultConfigurationBuilder();
    Code:
       0: aload_0
       1: ldc           #13                 // class org/apache/logging/log4j/core/config/builder/impl/BuiltConfiguration
       3: invokespecial #14                 // Method "<init>":(Ljava/lang/Class;)V
       6: aload_0
       7: getfield      #15                 // Field root:Lorg/apache/logging/log4j/core/config/builder/api/Component;
      10: ldc           #16                 // String name
      12: ldc           #17                 // String Built
      14: invokevirtual #18                 // Method org/apache/logging/log4j/core/config/builder/api/Component.addAttribute:(Ljava/lang/String;Ljava/lang/String;)Ljava/lang/String;
      17: pop
      18: return

  public org.apache.logging.log4j.core.config.builder.impl.DefaultConfigurationBuilder(java.lang.Class<T>);
    Code:
       0: aload_0
       1: invokespecial #19                 // Method java/lang/Object."<init>":()V
       4: aload_0
       5: new           #20                 // class org/apache/logging/log4j/core/config/builder/api/Component
       8: dup
       9: invokespecial #21                 // Method org/apache/logging/log4j/core/config/builder/api/Component."<init>":()V
      12: putfield      #15                 // Field root:Lorg/apache/logging/log4j/core/config/builder/api/Component;
      15: aload_1
      16: ifnonnull     29
      19: new           #22                 // class java/lang/IllegalArgumentException
      22: dup
      23: ldc           #23                 // String A Configuration class must be provided
      25: invokespecial #24                 // Method java/lang/IllegalArgumentException."<init>":(Ljava/lang/String;)V
      28: athrow
      29: aload_0
      30: aload_1
      31: putfield      #25                 // Field clazz:Ljava/lang/Class;
      34: aload_0
      35: getfield      #15                 // Field root:Lorg/apache/logging/log4j/core/config/builder/api/Component;
      38: invokevirtual #26                 // Method org/apache/logging/log4j/core/config/builder/api/Component.getComponents:()Ljava/util/List;
      41: astore_2
      42: aload_0
      43: new           #20                 // class org/apache/logging/log4j/core/config/builder/api/Component
      46: dup
      47: ldc           #27                 // String Properties
      49: invokespecial #28                 // Method org/apache/logging/log4j/core/config/builder/api/Component."<init>":(Ljava/lang/String;)V
      52: putfield      #29                 // Field properties:Lorg/apache/logging/log4j/core/config/builder/api/Component;
      55: aload_2
      56: aload_0
      57: getfield      #29                 // Field properties:Lorg/apache/logging/log4j/core/config/builder/api/Component;
      60: invokeinterface #30,  2           // InterfaceMethod java/util/List.add:(Ljava/lang/Object;)Z
      65: pop
      66: aload_0
      67: new           #20                 // class org/apache/logging/log4j/core/config/builder/api/Component
      70: dup
      71: ldc           #31                 // String Scripts
      73: invokespecial #28                 // Method org/apache/logging/log4j/core/config/builder/api/Component."<init>":(Ljava/lang/String;)V
      76: putfield      #32                 // Field scripts:Lorg/apache/logging/log4j/core/config/builder/api/Component;
      79: aload_2
      80: aload_0
      81: getfield      #32                 // Field scripts:Lorg/apache/logging/log4j/core/config/builder/api/Component;
      84: invokeinterface #30,  2           // InterfaceMethod java/util/List.add:(Ljava/lang/Object;)Z
      89: pop
      90: aload_0
      91: new           #20                 // class org/apache/logging/log4j/core/config/builder/api/Component
      94: dup
      95: ldc           #33                 // String CustomLevels
      97: invokespecial #28                 // Method org/apache/logging/log4j/core/config/builder/api/Component."<init>":(Ljava/lang/String;)V
     100: putfield      #34                 // Field customLevels:Lorg/apache/logging/log4j/core/config/builder/api/Component;
     103: aload_2
     104: aload_0
     105: getfield      #34                 // Field customLevels:Lorg/apache/logging/log4j/core/config/builder/api/Component;
     108: invokeinterface #30,  2           // InterfaceMethod java/util/List.add:(Ljava/lang/Object;)Z
     113: pop
     114: aload_0
     115: new           #20                 // class org/apache/logging/log4j/core/config/builder/api/Component
     118: dup
     119: ldc           #35                 // String Filters
     121: invokespecial #28                 // Method org/apache/logging/log4j/core/config/builder/api/Component."<init>":(Ljava/lang/String;)V
     124: putfield      #36                 // Field filters:Lorg/apache/logging/log4j/core/config/builder/api/Component;
     127: aload_2
     128: aload_0
     129: getfield      #36                 // Field filters:Lorg/apache/logging/log4j/core/config/builder/api/Component;
     132: invokeinterface #30,  2           // InterfaceMethod java/util/List.add:(Ljava/lang/Object;)Z
     137: pop
     138: aload_0
     139: new           #20                 // class org/apache/logging/log4j/core/config/builder/api/Component
     142: dup
     143: ldc           #37                 // String Appenders
     145: invokespecial #28                 // Method org/apache/logging/log4j/core/config/builder/api/Component."<init>":(Ljava/lang/String;)V
     148: putfield      #38                 // Field appenders:Lorg/apache/logging/log4j/core/config/builder/api/Component;
     151: aload_2
     152: aload_0
     153: getfield      #38                 // Field appenders:Lorg/apache/logging/log4j/core/config/builder/api/Component;
     156: invokeinterface #30,  2           // InterfaceMethod java/util/List.add:(Ljava/lang/Object;)Z
     161: pop
     162: aload_0
     163: new           #20                 // class org/apache/logging/log4j/core/config/builder/api/Component
     166: dup
     167: ldc           #39                 // String Loggers
     169: invokespecial #28                 // Method org/apache/logging/log4j/core/config/builder/api/Component."<init>":(Ljava/lang/String;)V
     172: putfield      #40                 // Field loggers:Lorg/apache/logging/log4j/core/config/builder/api/Component;
     175: aload_2
     176: aload_0
     177: getfield      #40                 // Field loggers:Lorg/apache/logging/log4j/core/config/builder/api/Component;
     180: invokeinterface #30,  2           // InterfaceMethod java/util/List.add:(Ljava/lang/Object;)Z
     185: pop
     186: return

  protected org.apache.logging.log4j.core.config.builder.api.ConfigurationBuilder<T> add(org.apache.logging.log4j.core.config.builder.api.Component, org.apache.logging.log4j.core.config.builder.api.ComponentBuilder<?>);
    Code:
       0: aload_1
       1: invokevirtual #26                 // Method org/apache/logging/log4j/core/config/builder/api/Component.getComponents:()Ljava/util/List;
       4: aload_2
       5: invokeinterface #41,  1           // InterfaceMethod org/apache/logging/log4j/core/config/builder/api/ComponentBuilder.build:()Ljava/lang/Object;
      10: invokeinterface #30,  2           // InterfaceMethod java/util/List.add:(Ljava/lang/Object;)Z
      15: pop
      16: aload_0
      17: areturn

  public org.apache.logging.log4j.core.config.builder.api.ConfigurationBuilder<T> add(org.apache.logging.log4j.core.config.builder.api.AppenderComponentBuilder);
    Code:
       0: aload_0
       1: aload_0
       2: getfield      #38                 // Field appenders:Lorg/apache/logging/log4j/core/config/builder/api/Component;
       5: aload_1
       6: invokevirtual #42                 // Method add:(Lorg/apache/logging/log4j/core/config/builder/api/Component;Lorg/apache/logging/log4j/core/config/builder/api/ComponentBuilder;)Lorg/apache/logging/log4j/core/config/builder/api/ConfigurationBuilder;
       9: areturn

  public org.apache.logging.log4j.core.config.builder.api.ConfigurationBuilder<T> add(org.apache.logging.log4j.core.config.builder.api.CustomLevelComponentBuilder);
    Code:
       0: aload_0
       1: aload_0
       2: getfield      #34                 // Field customLevels:Lorg/apache/logging/log4j/core/config/builder/api/Component;
       5: aload_1
       6: invokevirtual #42                 // Method add:(Lorg/apache/logging/log4j/core/config/builder/api/Component;Lorg/apache/logging/log4j/core/config/builder/api/ComponentBuilder;)Lorg/apache/logging/log4j/core/config/builder/api/ConfigurationBuilder;
       9: areturn

  public org.apache.logging.log4j.core.config.builder.api.ConfigurationBuilder<T> add(org.apache.logging.log4j.core.config.builder.api.FilterComponentBuilder);
    Code:
       0: aload_0
       1: aload_0
       2: getfield      #36                 // Field filters:Lorg/apache/logging/log4j/core/config/builder/api/Component;
       5: aload_1
       6: invokevirtual #42                 // Method add:(Lorg/apache/logging/log4j/core/config/builder/api/Component;Lorg/apache/logging/log4j/core/config/builder/api/ComponentBuilder;)Lorg/apache/logging/log4j/core/config/builder/api/ConfigurationBuilder;
       9: areturn

  public org.apache.logging.log4j.core.config.builder.api.ConfigurationBuilder<T> add(org.apache.logging.log4j.core.config.builder.api.ScriptComponentBuilder);
    Code:
       0: aload_0
       1: aload_0
       2: getfield      #32                 // Field scripts:Lorg/apache/logging/log4j/core/config/builder/api/Component;
       5: aload_1
       6: invokevirtual #42                 // Method add:(Lorg/apache/logging/log4j/core/config/builder/api/Component;Lorg/apache/logging/log4j/core/config/builder/api/ComponentBuilder;)Lorg/apache/logging/log4j/core/config/builder/api/ConfigurationBuilder;
       9: areturn

  public org.apache.logging.log4j.core.config.builder.api.ConfigurationBuilder<T> add(org.apache.logging.log4j.core.config.builder.api.ScriptFileComponentBuilder);
    Code:
       0: aload_0
       1: aload_0
       2: getfield      #32                 // Field scripts:Lorg/apache/logging/log4j/core/config/builder/api/Component;
       5: aload_1
       6: invokevirtual #42                 // Method add:(Lorg/apache/logging/log4j/core/config/builder/api/Component;Lorg/apache/logging/log4j/core/config/builder/api/ComponentBuilder;)Lorg/apache/logging/log4j/core/config/builder/api/ConfigurationBuilder;
       9: areturn

  public org.apache.logging.log4j.core.config.builder.api.ConfigurationBuilder<T> add(org.apache.logging.log4j.core.config.builder.api.LoggerComponentBuilder);
    Code:
       0: aload_0
       1: aload_0
       2: getfield      #40                 // Field loggers:Lorg/apache/logging/log4j/core/config/builder/api/Component;
       5: aload_1
       6: invokevirtual #42                 // Method add:(Lorg/apache/logging/log4j/core/config/builder/api/Component;Lorg/apache/logging/log4j/core/config/builder/api/ComponentBuilder;)Lorg/apache/logging/log4j/core/config/builder/api/ConfigurationBuilder;
       9: areturn

  public org.apache.logging.log4j.core.config.builder.api.ConfigurationBuilder<T> add(org.apache.logging.log4j.core.config.builder.api.RootLoggerComponentBuilder);
    Code:
       0: aload_0
       1: getfield      #40                 // Field loggers:Lorg/apache/logging/log4j/core/config/builder/api/Component;
       4: invokevirtual #26                 // Method org/apache/logging/log4j/core/config/builder/api/Component.getComponents:()Ljava/util/List;
       7: invokeinterface #43,  1           // InterfaceMethod java/util/List.iterator:()Ljava/util/Iterator;
      12: astore_2
      13: aload_2
      14: invokeinterface #44,  1           // InterfaceMethod java/util/Iterator.hasNext:()Z
      19: ifeq          57
      22: aload_2
      23: invokeinterface #45,  1           // InterfaceMethod java/util/Iterator.next:()Ljava/lang/Object;
      28: checkcast     #20                 // class org/apache/logging/log4j/core/config/builder/api/Component
      31: astore_3
      32: aload_3
      33: invokevirtual #46                 // Method org/apache/logging/log4j/core/config/builder/api/Component.getPluginType:()Ljava/lang/String;
      36: ldc           #48                 // String root
      38: invokevirtual #49                 // Method java/lang/String.equals:(Ljava/lang/Object;)Z
      41: ifeq          54
      44: new           #50                 // class org/apache/logging/log4j/core/config/ConfigurationException
      47: dup
      48: ldc           #51                 // String Root Logger was previously defined
      50: invokespecial #52                 // Method org/apache/logging/log4j/core/config/ConfigurationException."<init>":(Ljava/lang/String;)V
      53: athrow
      54: goto          13
      57: aload_0
      58: aload_0
      59: getfield      #40                 // Field loggers:Lorg/apache/logging/log4j/core/config/builder/api/Component;
      62: aload_1
      63: invokevirtual #42                 // Method add:(Lorg/apache/logging/log4j/core/config/builder/api/Component;Lorg/apache/logging/log4j/core/config/builder/api/ComponentBuilder;)Lorg/apache/logging/log4j/core/config/builder/api/ConfigurationBuilder;
      66: areturn

  public org.apache.logging.log4j.core.config.builder.api.ConfigurationBuilder<T> addProperty(java.lang.String, java.lang.String);
    Code:
       0: aload_0
       1: getfield      #29                 // Field properties:Lorg/apache/logging/log4j/core/config/builder/api/Component;
       4: aload_0
       5: aload_1
       6: ldc           #53                 // String Property
       8: aload_2
       9: invokevirtual #54                 // Method newComponent:(Ljava/lang/String;Ljava/lang/String;Ljava/lang/String;)Lorg/apache/logging/log4j/core/config/builder/api/ComponentBuilder;
      12: invokeinterface #41,  1           // InterfaceMethod org/apache/logging/log4j/core/config/builder/api/ComponentBuilder.build:()Ljava/lang/Object;
      17: checkcast     #20                 // class org/apache/logging/log4j/core/config/builder/api/Component
      20: invokevirtual #55                 // Method org/apache/logging/log4j/core/config/builder/api/Component.addComponent:(Lorg/apache/logging/log4j/core/config/builder/api/Component;)V
      23: aload_0
      24: areturn

  public T build();
    Code:
       0: aload_0
       1: iconst_1
       2: invokevirtual #56                 // Method build:(Z)Lorg/apache/logging/log4j/core/config/builder/impl/BuiltConfiguration;
       5: areturn

  public T build(boolean);
    Code:
       0: aload_0
       1: getfield      #57                 // Field source:Lorg/apache/logging/log4j/core/config/ConfigurationSource;
       4: ifnonnull     14
       7: aload_0
       8: getstatic     #58                 // Field org/apache/logging/log4j/core/config/ConfigurationSource.NULL_SOURCE:Lorg/apache/logging/log4j/core/config/ConfigurationSource;
      11: putfield      #57                 // Field source:Lorg/apache/logging/log4j/core/config/ConfigurationSource;
      14: aload_0
      15: getfield      #25                 // Field clazz:Ljava/lang/Class;
      18: iconst_3
      19: anewarray     #59                 // class java/lang/Class
      22: dup
      23: iconst_0
      24: ldc           #60                 // class org/apache/logging/log4j/core/LoggerContext
      26: aastore
      27: dup
      28: iconst_1
      29: ldc           #61                 // class org/apache/logging/log4j/core/config/ConfigurationSource
      31: aastore
      32: dup
      33: iconst_2
      34: ldc           #20                 // class org/apache/logging/log4j/core/config/builder/api/Component
      36: aastore
      37: invokevirtual #62                 // Method java/lang/Class.getConstructor:([Ljava/lang/Class;)Ljava/lang/reflect/Constructor;
      40: astore_3
      41: aload_3
      42: iconst_3
      43: anewarray     #63                 // class java/lang/Object
      46: dup
      47: iconst_0
      48: aload_0
      49: getfield      #64                 // Field loggerContext:Lorg/apache/logging/log4j/core/LoggerContext;
      52: aastore
      53: dup
      54: iconst_1
      55: aload_0
      56: getfield      #57                 // Field source:Lorg/apache/logging/log4j/core/config/ConfigurationSource;
      59: aastore
      60: dup
      61: iconst_2
      62: aload_0
      63: getfield      #15                 // Field root:Lorg/apache/logging/log4j/core/config/builder/api/Component;
      66: aastore
      67: invokevirtual #65                 // Method java/lang/reflect/Constructor.newInstance:([Ljava/lang/Object;)Ljava/lang/Object;
      70: checkcast     #13                 // class org/apache/logging/log4j/core/config/builder/impl/BuiltConfiguration
      73: astore_2
      74: aload_2
      75: invokevirtual #66                 // Method org/apache/logging/log4j/core/config/builder/impl/BuiltConfiguration.getRootNode:()Lorg/apache/logging/log4j/core/config/Node;
      78: invokevirtual #67                 // Method org/apache/logging/log4j/core/config/Node.getAttributes:()Ljava/util/Map;
      81: aload_0
      82: getfield      #15                 // Field root:Lorg/apache/logging/log4j/core/config/builder/api/Component;
      85: invokevirtual #68                 // Method org/apache/logging/log4j/core/config/builder/api/Component.getAttributes:()Ljava/util/Map;
      88: invokeinterface #69,  2           // InterfaceMethod java/util/Map.putAll:(Ljava/util/Map;)V
      93: aload_0
      94: getfield      #70                 // Field name:Ljava/lang/String;
      97: ifnull        108
     100: aload_2
     101: aload_0
     102: getfield      #70                 // Field name:Ljava/lang/String;
     105: invokevirtual #71                 // Method org/apache/logging/log4j/core/config/builder/impl/BuiltConfiguration.setName:(Ljava/lang/String;)V
     108: aload_0
     109: getfield      #72                 // Field level:Lorg/apache/logging/log4j/Level;
     112: ifnull        127
     115: aload_2
     116: invokevirtual #73                 // Method org/apache/logging/log4j/core/config/builder/impl/BuiltConfiguration.getStatusConfiguration:()Lorg/apache/logging/log4j/core/config/status/StatusConfiguration;
     119: aload_0
     120: getfield      #72                 // Field level:Lorg/apache/logging/log4j/Level;
     123: invokevirtual #74                 // Method org/apache/logging/log4j/core/config/status/StatusConfiguration.withStatus:(Lorg/apache/logging/log4j/Level;)Lorg/apache/logging/log4j/core/config/status/StatusConfiguration;
     126: pop
     127: aload_0
     128: getfield      #75                 // Field verbosity:Ljava/lang/String;
     131: ifnull        146
     134: aload_2
     135: invokevirtual #73                 // Method org/apache/logging/log4j/core/config/builder/impl/BuiltConfiguration.getStatusConfiguration:()Lorg/apache/logging/log4j/core/config/status/StatusConfiguration;
     138: aload_0
     139: getfield      #75                 // Field verbosity:Ljava/lang/String;
     142: invokevirtual #76                 // Method org/apache/logging/log4j/core/config/status/StatusConfiguration.withVerbosity:(Ljava/lang/String;)Lorg/apache/logging/log4j/core/config/status/StatusConfiguration;
     145: pop
     146: aload_0
     147: getfield      #77                 // Field destination:Ljava/lang/String;
     150: ifnull        165
     153: aload_2
     154: invokevirtual #73                 // Method org/apache/logging/log4j/core/config/builder/impl/BuiltConfiguration.getStatusConfiguration:()Lorg/apache/logging/log4j/core/config/status/StatusConfiguration;
     157: aload_0
     158: getfield      #77                 // Field destination:Ljava/lang/String;
     161: invokevirtual #78                 // Method org/apache/logging/log4j/core/config/status/StatusConfiguration.withDestination:(Ljava/lang/String;)Lorg/apache/logging/log4j/core/config/status/StatusConfiguration;
     164: pop
     165: aload_0
     166: getfield      #79                 // Field packages:Ljava/lang/String;
     169: ifnull        180
     172: aload_2
     173: aload_0
     174: getfield      #79                 // Field packages:Ljava/lang/String;
     177: invokevirtual #80                 // Method org/apache/logging/log4j/core/config/builder/impl/BuiltConfiguration.setPluginPackages:(Ljava/lang/String;)V
     180: aload_0
     181: getfield      #81                 // Field shutdownFlag:Ljava/lang/String;
     184: ifnull        195
     187: aload_2
     188: aload_0
     189: getfield      #81                 // Field shutdownFlag:Ljava/lang/String;
     192: invokevirtual #82                 // Method org/apache/logging/log4j/core/config/builder/impl/BuiltConfiguration.setShutdownHook:(Ljava/lang/String;)V
     195: aload_0
     196: getfield      #83                 // Field shutdownTimeoutMillis:J
     199: lconst_0
     200: lcmp
     201: ifle          212
     204: aload_2
     205: aload_0
     206: getfield      #83                 // Field shutdownTimeoutMillis:J
     209: invokevirtual #84                 // Method org/apache/logging/log4j/core/config/builder/impl/BuiltConfiguration.setShutdownTimeoutMillis:(J)V
     212: aload_0
     213: getfield      #85                 // Field advertiser:Ljava/lang/String;
     216: ifnull        231
     219: aload_2
     220: aload_0
     221: getfield      #85                 // Field advertiser:Ljava/lang/String;
     224: aload_0
     225: getfield      #57                 // Field source:Lorg/apache/logging/log4j/core/config/ConfigurationSource;
     228: invokevirtual #86                 // Method org/apache/logging/log4j/core/config/builder/impl/BuiltConfiguration.createAdvertiser:(Ljava/lang/String;Lorg/apache/logging/log4j/core/config/ConfigurationSource;)V
     231: aload_2
     232: aload_0
     233: getfield      #87                 // Field monitorInterval:I
     236: invokevirtual #88                 // Method org/apache/logging/log4j/core/config/builder/impl/BuiltConfiguration.setMonitorInterval:(I)V
     239: goto          254
     242: astore_3
     243: new           #22                 // class java/lang/IllegalArgumentException
     246: dup
     247: ldc           #90                 // String Invalid Configuration class specified
     249: aload_3
     250: invokespecial #91                 // Method java/lang/IllegalArgumentException."<init>":(Ljava/lang/String;Ljava/lang/Throwable;)V
     253: athrow
     254: aload_2
     255: invokevirtual #73                 // Method org/apache/logging/log4j/core/config/builder/impl/BuiltConfiguration.getStatusConfiguration:()Lorg/apache/logging/log4j/core/config/status/StatusConfiguration;
     258: invokevirtual #92                 // Method org/apache/logging/log4j/core/config/status/StatusConfiguration.initialize:()V
     261: iload_1
     262: ifeq          269
     265: aload_2
     266: invokevirtual #93                 // Method org/apache/logging/log4j/core/config/builder/impl/BuiltConfiguration.initialize:()V
     269: aload_2
     270: areturn
    Exception table:
       from    to  target type
           0   239   242   Class java/lang/Exception

  private java.lang.String formatXml(java.lang.String) throws javax.xml.transform.TransformerConfigurationException, javax.xml.transform.TransformerException, javax.xml.transform.TransformerFactoryConfigurationError;
    Code:
       0: new           #94                 // class java/io/StringWriter
       3: dup
       4: invokespecial #95                 // Method java/io/StringWriter."<init>":()V
       7: astore_2
       8: new           #96                 // class javax/xml/transform/stream/StreamSource
      11: dup
      12: new           #97                 // class java/io/StringReader
      15: dup
      16: aload_1
      17: invokespecial #98                 // Method java/io/StringReader."<init>":(Ljava/lang/String;)V
      20: invokespecial #99                 // Method javax/xml/transform/stream/StreamSource."<init>":(Ljava/io/Reader;)V
      23: new           #100                // class javax/xml/transform/stream/StreamResult
      26: dup
      27: aload_2
      28: invokespecial #101                // Method javax/xml/transform/stream/StreamResult."<init>":(Ljava/io/Writer;)V
      31: invokestatic  #102                // Method formatXml:(Ljavax/xml/transform/Source;Ljavax/xml/transform/Result;)V
      34: aload_2
      35: invokevirtual #103                // Method java/io/StringWriter.toString:()Ljava/lang/String;
      38: areturn

  public void writeXmlConfiguration(java.io.OutputStream) throws java.io.IOException;
    Code:
       0: invokestatic  #104                // Method javax/xml/stream/XMLOutputFactory.newInstance:()Ljavax/xml/stream/XMLOutputFactory;
       3: aload_1
       4: invokevirtual #105                // Method javax/xml/stream/XMLOutputFactory.createXMLStreamWriter:(Ljava/io/OutputStream;)Ljavax/xml/stream/XMLStreamWriter;
       7: astore_2
       8: aload_0
       9: aload_2
      10: invokespecial #106                // Method writeXmlConfiguration:(Ljavax/xml/stream/XMLStreamWriter;)V
      13: aload_2
      14: invokeinterface #107,  1          // InterfaceMethod javax/xml/stream/XMLStreamWriter.close:()V
      19: goto          45
      22: astore_2
      23: aload_2
      24: invokevirtual #109                // Method javax/xml/stream/XMLStreamException.getNestedException:()Ljava/lang/Throwable;
      27: instanceof    #110                // class java/io/IOException
      30: ifeq          41
      33: aload_2
      34: invokevirtual #109                // Method javax/xml/stream/XMLStreamException.getNestedException:()Ljava/lang/Throwable;
      37: checkcast     #110                // class java/io/IOException
      40: athrow
      41: aload_2
      42: invokestatic  #111                // Method org/apache/logging/log4j/core/util/Throwables.rethrow:(Ljava/lang/Throwable;)V
      45: return
    Exception table:
       from    to  target type
           0    19    22   Class javax/xml/stream/XMLStreamException

  public java.lang.String toXmlConfiguration();
    Code:
       0: new           #94                 // class java/io/StringWriter
       3: dup
       4: invokespecial #95                 // Method java/io/StringWriter."<init>":()V
       7: astore_1
       8: invokestatic  #104                // Method javax/xml/stream/XMLOutputFactory.newInstance:()Ljavax/xml/stream/XMLOutputFactory;
      11: aload_1
      12: invokevirtual #112                // Method javax/xml/stream/XMLOutputFactory.createXMLStreamWriter:(Ljava/io/Writer;)Ljavax/xml/stream/XMLStreamWriter;
      15: astore_2
      16: aload_0
      17: aload_2
      18: invokespecial #106                // Method writeXmlConfiguration:(Ljavax/xml/stream/XMLStreamWriter;)V
      21: aload_2
      22: invokeinterface #107,  1          // InterfaceMethod javax/xml/stream/XMLStreamWriter.close:()V
      27: aload_0
      28: aload_1
      29: invokevirtual #103                // Method java/io/StringWriter.toString:()Ljava/lang/String;
      32: invokespecial #113                // Method formatXml:(Ljava/lang/String;)Ljava/lang/String;
      35: areturn
      36: astore_2
      37: aload_2
      38: invokestatic  #111                // Method org/apache/logging/log4j/core/util/Throwables.rethrow:(Ljava/lang/Throwable;)V
      41: aload_1
      42: invokevirtual #103                // Method java/io/StringWriter.toString:()Ljava/lang/String;
      45: areturn
    Exception table:
       from    to  target type
           8    35    36   Class javax/xml/stream/XMLStreamException
           8    35    36   Class javax/xml/transform/TransformerException

  private void writeXmlConfiguration(javax.xml.stream.XMLStreamWriter) throws javax.xml.stream.XMLStreamException;
    Code:
       0: aload_1
       1: invokeinterface #115,  1          // InterfaceMethod javax/xml/stream/XMLStreamWriter.writeStartDocument:()V
       6: aload_1
       7: ldc           #116                // String Configuration
       9: invokeinterface #117,  2          // InterfaceMethod javax/xml/stream/XMLStreamWriter.writeStartElement:(Ljava/lang/String;)V
      14: aload_0
      15: getfield      #70                 // Field name:Ljava/lang/String;
      18: ifnull        33
      21: aload_1
      22: ldc           #16                 // String name
      24: aload_0
      25: getfield      #70                 // Field name:Ljava/lang/String;
      28: invokeinterface #118,  3          // InterfaceMethod javax/xml/stream/XMLStreamWriter.writeAttribute:(Ljava/lang/String;Ljava/lang/String;)V
      33: aload_0
      34: getfield      #72                 // Field level:Lorg/apache/logging/log4j/Level;
      37: ifnull        55
      40: aload_1
      41: ldc           #119                // String status
      43: aload_0
      44: getfield      #72                 // Field level:Lorg/apache/logging/log4j/Level;
      47: invokevirtual #120                // Method org/apache/logging/log4j/Level.name:()Ljava/lang/String;
      50: invokeinterface #118,  3          // InterfaceMethod javax/xml/stream/XMLStreamWriter.writeAttribute:(Ljava/lang/String;Ljava/lang/String;)V
      55: aload_0
      56: getfield      #75                 // Field verbosity:Ljava/lang/String;
      59: ifnull        74
      62: aload_1
      63: ldc           #121                // String verbose
      65: aload_0
      66: getfield      #75                 // Field verbosity:Ljava/lang/String;
      69: invokeinterface #118,  3          // InterfaceMethod javax/xml/stream/XMLStreamWriter.writeAttribute:(Ljava/lang/String;Ljava/lang/String;)V
      74: aload_0
      75: getfield      #77                 // Field destination:Ljava/lang/String;
      78: ifnull        93
      81: aload_1
      82: ldc           #122                // String dest
      84: aload_0
      85: getfield      #77                 // Field destination:Ljava/lang/String;
      88: invokeinterface #118,  3          // InterfaceMethod javax/xml/stream/XMLStreamWriter.writeAttribute:(Ljava/lang/String;Ljava/lang/String;)V
      93: aload_0
      94: getfield      #79                 // Field packages:Ljava/lang/String;
      97: ifnull        112
     100: aload_1
     101: ldc           #123                // String packages
     103: aload_0
     104: getfield      #79                 // Field packages:Ljava/lang/String;
     107: invokeinterface #118,  3          // InterfaceMethod javax/xml/stream/XMLStreamWriter.writeAttribute:(Ljava/lang/String;Ljava/lang/String;)V
     112: aload_0
     113: getfield      #81                 // Field shutdownFlag:Ljava/lang/String;
     116: ifnull        131
     119: aload_1
     120: ldc           #124                // String shutdownHook
     122: aload_0
     123: getfield      #81                 // Field shutdownFlag:Ljava/lang/String;
     126: invokeinterface #118,  3          // InterfaceMethod javax/xml/stream/XMLStreamWriter.writeAttribute:(Ljava/lang/String;Ljava/lang/String;)V
     131: aload_0
     132: getfield      #83                 // Field shutdownTimeoutMillis:J
     135: lconst_0
     136: lcmp
     137: ifle          155
     140: aload_1
     141: ldc           #125                // String shutdownTimeout
     143: aload_0
     144: getfield      #83                 // Field shutdownTimeoutMillis:J
     147: invokestatic  #126                // Method java/lang/String.valueOf:(J)Ljava/lang/String;
     150: invokeinterface #118,  3          // InterfaceMethod javax/xml/stream/XMLStreamWriter.writeAttribute:(Ljava/lang/String;Ljava/lang/String;)V
     155: aload_0
     156: getfield      #85                 // Field advertiser:Ljava/lang/String;
     159: ifnull        174
     162: aload_1
     163: ldc           #127                // String advertiser
     165: aload_0
     166: getfield      #85                 // Field advertiser:Ljava/lang/String;
     169: invokeinterface #118,  3          // InterfaceMethod javax/xml/stream/XMLStreamWriter.writeAttribute:(Ljava/lang/String;Ljava/lang/String;)V
     174: aload_0
     175: getfield      #87                 // Field monitorInterval:I
     178: ifle          196
     181: aload_1
     182: ldc           #128                // String monitorInterval
     184: aload_0
     185: getfield      #87                 // Field monitorInterval:I
     188: invokestatic  #129                // Method java/lang/String.valueOf:(I)Ljava/lang/String;
     191: invokeinterface #118,  3          // InterfaceMethod javax/xml/stream/XMLStreamWriter.writeAttribute:(Ljava/lang/String;Ljava/lang/String;)V
     196: aload_0
     197: aload_1
     198: aload_0
     199: getfield      #29                 // Field properties:Lorg/apache/logging/log4j/core/config/builder/api/Component;
     202: invokespecial #130                // Method writeXmlSection:(Ljavax/xml/stream/XMLStreamWriter;Lorg/apache/logging/log4j/core/config/builder/api/Component;)V
     205: aload_0
     206: aload_1
     207: aload_0
     208: getfield      #32                 // Field scripts:Lorg/apache/logging/log4j/core/config/builder/api/Component;
     211: invokespecial #130                // Method writeXmlSection:(Ljavax/xml/stream/XMLStreamWriter;Lorg/apache/logging/log4j/core/config/builder/api/Component;)V
     214: aload_0
     215: aload_1
     216: aload_0
     217: getfield      #34                 // Field customLevels:Lorg/apache/logging/log4j/core/config/builder/api/Component;
     220: invokespecial #130                // Method writeXmlSection:(Ljavax/xml/stream/XMLStreamWriter;Lorg/apache/logging/log4j/core/config/builder/api/Component;)V
     223: aload_0
     224: getfield      #36                 // Field filters:Lorg/apache/logging/log4j/core/config/builder/api/Component;
     227: invokevirtual #26                 // Method org/apache/logging/log4j/core/config/builder/api/Component.getComponents:()Ljava/util/List;
     230: invokeinterface #131,  1          // InterfaceMethod java/util/List.size:()I
     235: iconst_1
     236: if_icmpne     263
     239: aload_0
     240: aload_1
     241: aload_0
     242: getfield      #36                 // Field filters:Lorg/apache/logging/log4j/core/config/builder/api/Component;
     245: invokevirtual #26                 // Method org/apache/logging/log4j/core/config/builder/api/Component.getComponents:()Ljava/util/List;
     248: iconst_0
     249: invokeinterface #132,  2          // InterfaceMethod java/util/List.get:(I)Ljava/lang/Object;
     254: checkcast     #20                 // class org/apache/logging/log4j/core/config/builder/api/Component
     257: invokespecial #133                // Method writeXmlComponent:(Ljavax/xml/stream/XMLStreamWriter;Lorg/apache/logging/log4j/core/config/builder/api/Component;)V
     260: goto          288
     263: aload_0
     264: getfield      #36                 // Field filters:Lorg/apache/logging/log4j/core/config/builder/api/Component;
     267: invokevirtual #26                 // Method org/apache/logging/log4j/core/config/builder/api/Component.getComponents:()Ljava/util/List;
     270: invokeinterface #131,  1          // InterfaceMethod java/util/List.size:()I
     275: iconst_1
     276: if_icmple     288
     279: aload_0
     280: aload_1
     281: aload_0
     282: getfield      #36                 // Field filters:Lorg/apache/logging/log4j/core/config/builder/api/Component;
     285: invokespecial #130                // Method writeXmlSection:(Ljavax/xml/stream/XMLStreamWriter;Lorg/apache/logging/log4j/core/config/builder/api/Component;)V
     288: aload_0
     289: aload_1
     290: aload_0
     291: getfield      #38                 // Field appenders:Lorg/apache/logging/log4j/core/config/builder/api/Component;
     294: invokespecial #130                // Method writeXmlSection:(Ljavax/xml/stream/XMLStreamWriter;Lorg/apache/logging/log4j/core/config/builder/api/Component;)V
     297: aload_0
     298: aload_1
     299: aload_0
     300: getfield      #40                 // Field loggers:Lorg/apache/logging/log4j/core/config/builder/api/Component;
     303: invokespecial #130                // Method writeXmlSection:(Ljavax/xml/stream/XMLStreamWriter;Lorg/apache/logging/log4j/core/config/builder/api/Component;)V
     306: aload_1
     307: invokeinterface #134,  1          // InterfaceMethod javax/xml/stream/XMLStreamWriter.writeEndElement:()V
     312: aload_1
     313: invokeinterface #135,  1          // InterfaceMethod javax/xml/stream/XMLStreamWriter.writeEndDocument:()V
     318: return

  private void writeXmlSection(javax.xml.stream.XMLStreamWriter, org.apache.logging.log4j.core.config.builder.api.Component) throws javax.xml.stream.XMLStreamException;
    Code:
       0: aload_2
       1: invokevirtual #68                 // Method org/apache/logging/log4j/core/config/builder/api/Component.getAttributes:()Ljava/util/Map;
       4: invokeinterface #136,  1          // InterfaceMethod java/util/Map.isEmpty:()Z
       9: ifeq          31
      12: aload_2
      13: invokevirtual #26                 // Method org/apache/logging/log4j/core/config/builder/api/Component.getComponents:()Ljava/util/List;
      16: invokeinterface #137,  1          // InterfaceMethod java/util/List.isEmpty:()Z
      21: ifeq          31
      24: aload_2
      25: invokevirtual #138                // Method org/apache/logging/log4j/core/config/builder/api/Component.getValue:()Ljava/lang/String;
      28: ifnull        37
      31: aload_0
      32: aload_1
      33: aload_2
      34: invokespecial #133                // Method writeXmlComponent:(Ljavax/xml/stream/XMLStreamWriter;Lorg/apache/logging/log4j/core/config/builder/api/Component;)V
      37: return

  private void writeXmlComponent(javax.xml.stream.XMLStreamWriter, org.apache.logging.log4j.core.config.builder.api.Component) throws javax.xml.stream.XMLStreamException;
    Code:
       0: aload_2
       1: invokevirtual #26                 // Method org/apache/logging/log4j/core/config/builder/api/Component.getComponents:()Ljava/util/List;
       4: invokeinterface #137,  1          // InterfaceMethod java/util/List.isEmpty:()Z
       9: ifeq          19
      12: aload_2
      13: invokevirtual #138                // Method org/apache/logging/log4j/core/config/builder/api/Component.getValue:()Ljava/lang/String;
      16: ifnull        101
      19: aload_1
      20: aload_2
      21: invokevirtual #46                 // Method org/apache/logging/log4j/core/config/builder/api/Component.getPluginType:()Ljava/lang/String;
      24: invokeinterface #117,  2          // InterfaceMethod javax/xml/stream/XMLStreamWriter.writeStartElement:(Ljava/lang/String;)V
      29: aload_0
      30: aload_1
      31: aload_2
      32: invokespecial #139                // Method writeXmlAttributes:(Ljavax/xml/stream/XMLStreamWriter;Lorg/apache/logging/log4j/core/config/builder/api/Component;)V
      35: aload_2
      36: invokevirtual #26                 // Method org/apache/logging/log4j/core/config/builder/api/Component.getComponents:()Ljava/util/List;
      39: invokeinterface #43,  1           // InterfaceMethod java/util/List.iterator:()Ljava/util/Iterator;
      44: astore_3
      45: aload_3
      46: invokeinterface #44,  1           // InterfaceMethod java/util/Iterator.hasNext:()Z
      51: ifeq          75
      54: aload_3
      55: invokeinterface #45,  1           // InterfaceMethod java/util/Iterator.next:()Ljava/lang/Object;
      60: checkcast     #20                 // class org/apache/logging/log4j/core/config/builder/api/Component
      63: astore        4
      65: aload_0
      66: aload_1
      67: aload         4
      69: invokespecial #133                // Method writeXmlComponent:(Ljavax/xml/stream/XMLStreamWriter;Lorg/apache/logging/log4j/core/config/builder/api/Component;)V
      72: goto          45
      75: aload_2
      76: invokevirtual #138                // Method org/apache/logging/log4j/core/config/builder/api/Component.getValue:()Ljava/lang/String;
      79: ifnull        92
      82: aload_1
      83: aload_2
      84: invokevirtual #138                // Method org/apache/logging/log4j/core/config/builder/api/Component.getValue:()Ljava/lang/String;
      87: invokeinterface #140,  2          // InterfaceMethod javax/xml/stream/XMLStreamWriter.writeCharacters:(Ljava/lang/String;)V
      92: aload_1
      93: invokeinterface #134,  1          // InterfaceMethod javax/xml/stream/XMLStreamWriter.writeEndElement:()V
      98: goto          117
     101: aload_1
     102: aload_2
     103: invokevirtual #46                 // Method org/apache/logging/log4j/core/config/builder/api/Component.getPluginType:()Ljava/lang/String;
     106: invokeinterface #141,  2          // InterfaceMethod javax/xml/stream/XMLStreamWriter.writeEmptyElement:(Ljava/lang/String;)V
     111: aload_0
     112: aload_1
     113: aload_2
     114: invokespecial #139                // Method writeXmlAttributes:(Ljavax/xml/stream/XMLStreamWriter;Lorg/apache/logging/log4j/core/config/builder/api/Component;)V
     117: return

  private void writeXmlAttributes(javax.xml.stream.XMLStreamWriter, org.apache.logging.log4j.core.config.builder.api.Component) throws javax.xml.stream.XMLStreamException;
    Code:
       0: aload_2
       1: invokevirtual #68                 // Method org/apache/logging/log4j/core/config/builder/api/Component.getAttributes:()Ljava/util/Map;
       4: invokeinterface #142,  1          // InterfaceMethod java/util/Map.entrySet:()Ljava/util/Set;
       9: invokeinterface #143,  1          // InterfaceMethod java/util/Set.iterator:()Ljava/util/Iterator;
      14: astore_3
      15: aload_3
      16: invokeinterface #44,  1           // InterfaceMethod java/util/Iterator.hasNext:()Z
      21: ifeq          64
      24: aload_3
      25: invokeinterface #45,  1           // InterfaceMethod java/util/Iterator.next:()Ljava/lang/Object;
      30: checkcast     #144                // class java/util/Map$Entry
      33: astore        4
      35: aload_1
      36: aload         4
      38: invokeinterface #145,  1          // InterfaceMethod java/util/Map$Entry.getKey:()Ljava/lang/Object;
      43: checkcast     #146                // class java/lang/String
      46: aload         4
      48: invokeinterface #147,  1          // InterfaceMethod java/util/Map$Entry.getValue:()Ljava/lang/Object;
      53: checkcast     #146                // class java/lang/String
      56: invokeinterface #118,  3          // InterfaceMethod javax/xml/stream/XMLStreamWriter.writeAttribute:(Ljava/lang/String;Ljava/lang/String;)V
      61: goto          15
      64: return

  public org.apache.logging.log4j.core.config.builder.api.ScriptComponentBuilder newScript(java.lang.String, java.lang.String, java.lang.String);
    Code:
       0: new           #148                // class org/apache/logging/log4j/core/config/builder/impl/DefaultScriptComponentBuilder
       3: dup
       4: aload_0
       5: aload_1
       6: aload_2
       7: aload_3
       8: invokespecial #149                // Method org/apache/logging/log4j/core/config/builder/impl/DefaultScriptComponentBuilder."<init>":(Lorg/apache/logging/log4j/core/config/builder/impl/DefaultConfigurationBuilder;Ljava/lang/String;Ljava/lang/String;Ljava/lang/String;)V
      11: areturn

  public org.apache.logging.log4j.core.config.builder.api.ScriptFileComponentBuilder newScriptFile(java.lang.String);
    Code:
       0: new           #150                // class org/apache/logging/log4j/core/config/builder/impl/DefaultScriptFileComponentBuilder
       3: dup
       4: aload_0
       5: aload_1
       6: aload_1
       7: invokespecial #151                // Method org/apache/logging/log4j/core/config/builder/impl/DefaultScriptFileComponentBuilder."<init>":(Lorg/apache/logging/log4j/core/config/builder/impl/DefaultConfigurationBuilder;Ljava/lang/String;Ljava/lang/String;)V
      10: areturn

  public org.apache.logging.log4j.core.config.builder.api.ScriptFileComponentBuilder newScriptFile(java.lang.String, java.lang.String);
    Code:
       0: new           #150                // class org/apache/logging/log4j/core/config/builder/impl/DefaultScriptFileComponentBuilder
       3: dup
       4: aload_0
       5: aload_1
       6: aload_2
       7: invokespecial #151                // Method org/apache/logging/log4j/core/config/builder/impl/DefaultScriptFileComponentBuilder."<init>":(Lorg/apache/logging/log4j/core/config/builder/impl/DefaultConfigurationBuilder;Ljava/lang/String;Ljava/lang/String;)V
      10: areturn

  public org.apache.logging.log4j.core.config.builder.api.AppenderComponentBuilder newAppender(java.lang.String, java.lang.String);
    Code:
       0: new           #152                // class org/apache/logging/log4j/core/config/builder/impl/DefaultAppenderComponentBuilder
       3: dup
       4: aload_0
       5: aload_1
       6: aload_2
       7: invokespecial #153                // Method org/apache/logging/log4j/core/config/builder/impl/DefaultAppenderComponentBuilder."<init>":(Lorg/apache/logging/log4j/core/config/builder/impl/DefaultConfigurationBuilder;Ljava/lang/String;Ljava/lang/String;)V
      10: areturn

  public org.apache.logging.log4j.core.config.builder.api.AppenderRefComponentBuilder newAppenderRef(java.lang.String);
    Code:
       0: new           #154                // class org/apache/logging/log4j/core/config/builder/impl/DefaultAppenderRefComponentBuilder
       3: dup
       4: aload_0
       5: aload_1
       6: invokespecial #155                // Method org/apache/logging/log4j/core/config/builder/impl/DefaultAppenderRefComponentBuilder."<init>":(Lorg/apache/logging/log4j/core/config/builder/impl/DefaultConfigurationBuilder;Ljava/lang/String;)V
       9: areturn

  public org.apache.logging.log4j.core.config.builder.api.LoggerComponentBuilder newAsyncLogger(java.lang.String);
    Code:
       0: new           #156                // class org/apache/logging/log4j/core/config/builder/impl/DefaultLoggerComponentBuilder
       3: dup
       4: aload_0
       5: aload_1
       6: aconst_null
       7: ldc           #157                // String AsyncLogger
       9: invokespecial #158                // Method org/apache/logging/log4j/core/config/builder/impl/DefaultLoggerComponentBuilder."<init>":(Lorg/apache/logging/log4j/core/config/builder/impl/DefaultConfigurationBuilder;Ljava/lang/String;Ljava/lang/String;Ljava/lang/String;)V
      12: areturn

  public org.apache.logging.log4j.core.config.builder.api.LoggerComponentBuilder newAsyncLogger(java.lang.String, boolean);
    Code:
       0: new           #156                // class org/apache/logging/log4j/core/config/builder/impl/DefaultLoggerComponentBuilder
       3: dup
       4: aload_0
       5: aload_1
       6: aconst_null
       7: ldc           #157                // String AsyncLogger
       9: iload_2
      10: invokespecial #159                // Method org/apache/logging/log4j/core/config/builder/impl/DefaultLoggerComponentBuilder."<init>":(Lorg/apache/logging/log4j/core/config/builder/impl/DefaultConfigurationBuilder;Ljava/lang/String;Ljava/lang/String;Ljava/lang/String;Z)V
      13: areturn

  public org.apache.logging.log4j.core.config.builder.api.LoggerComponentBuilder newAsyncLogger(java.lang.String, org.apache.logging.log4j.Level);
    Code:
       0: new           #156                // class org/apache/logging/log4j/core/config/builder/impl/DefaultLoggerComponentBuilder
       3: dup
       4: aload_0
       5: aload_1
       6: aload_2
       7: invokevirtual #160                // Method org/apache/logging/log4j/Level.toString:()Ljava/lang/String;
      10: ldc           #157                // String AsyncLogger
      12: invokespecial #158                // Method org/apache/logging/log4j/core/config/builder/impl/DefaultLoggerComponentBuilder."<init>":(Lorg/apache/logging/log4j/core/config/builder/impl/DefaultConfigurationBuilder;Ljava/lang/String;Ljava/lang/String;Ljava/lang/String;)V
      15: areturn

  public org.apache.logging.log4j.core.config.builder.api.LoggerComponentBuilder newAsyncLogger(java.lang.String, org.apache.logging.log4j.Level, boolean);
    Code:
       0: new           #156                // class org/apache/logging/log4j/core/config/builder/impl/DefaultLoggerComponentBuilder
       3: dup
       4: aload_0
       5: aload_1
       6: aload_2
       7: invokevirtual #160                // Method org/apache/logging/log4j/Level.toString:()Ljava/lang/String;
      10: ldc           #157                // String AsyncLogger
      12: iload_3
      13: invokespecial #159                // Method org/apache/logging/log4j/core/config/builder/impl/DefaultLoggerComponentBuilder."<init>":(Lorg/apache/logging/log4j/core/config/builder/impl/DefaultConfigurationBuilder;Ljava/lang/String;Ljava/lang/String;Ljava/lang/String;Z)V
      16: areturn

  public org.apache.logging.log4j.core.config.builder.api.LoggerComponentBuilder newAsyncLogger(java.lang.String, java.lang.String);
    Code:
       0: new           #156                // class org/apache/logging/log4j/core/config/builder/impl/DefaultLoggerComponentBuilder
       3: dup
       4: aload_0
       5: aload_1
       6: aload_2
       7: ldc           #157                // String AsyncLogger
       9: invokespecial #158                // Method org/apache/logging/log4j/core/config/builder/impl/DefaultLoggerComponentBuilder."<init>":(Lorg/apache/logging/log4j/core/config/builder/impl/DefaultConfigurationBuilder;Ljava/lang/String;Ljava/lang/String;Ljava/lang/String;)V
      12: areturn

  public org.apache.logging.log4j.core.config.builder.api.LoggerComponentBuilder newAsyncLogger(java.lang.String, java.lang.String, boolean);
    Code:
       0: new           #156                // class org/apache/logging/log4j/core/config/builder/impl/DefaultLoggerComponentBuilder
       3: dup
       4: aload_0
       5: aload_1
       6: aload_2
       7: ldc           #157                // String AsyncLogger
       9: iload_3
      10: invokespecial #159                // Method org/apache/logging/log4j/core/config/builder/impl/DefaultLoggerComponentBuilder."<init>":(Lorg/apache/logging/log4j/core/config/builder/impl/DefaultConfigurationBuilder;Ljava/lang/String;Ljava/lang/String;Ljava/lang/String;Z)V
      13: areturn

  public org.apache.logging.log4j.core.config.builder.api.RootLoggerComponentBuilder newAsyncRootLogger();
    Code:
       0: new           #161                // class org/apache/logging/log4j/core/config/builder/impl/DefaultRootLoggerComponentBuilder
       3: dup
       4: aload_0
       5: ldc           #162                // String AsyncRoot
       7: invokespecial #163                // Method org/apache/logging/log4j/core/config/builder/impl/DefaultRootLoggerComponentBuilder."<init>":(Lorg/apache/logging/log4j/core/config/builder/impl/DefaultConfigurationBuilder;Ljava/lang/String;)V
      10: areturn

  public org.apache.logging.log4j.core.config.builder.api.RootLoggerComponentBuilder newAsyncRootLogger(boolean);
    Code:
       0: new           #161                // class org/apache/logging/log4j/core/config/builder/impl/DefaultRootLoggerComponentBuilder
       3: dup
       4: aload_0
       5: aconst_null
       6: ldc           #162                // String AsyncRoot
       8: iload_1
       9: invokespecial #164                // Method org/apache/logging/log4j/core/config/builder/impl/DefaultRootLoggerComponentBuilder."<init>":(Lorg/apache/logging/log4j/core/config/builder/impl/DefaultConfigurationBuilder;Ljava/lang/String;Ljava/lang/String;Z)V
      12: areturn

  public org.apache.logging.log4j.core.config.builder.api.RootLoggerComponentBuilder newAsyncRootLogger(org.apache.logging.log4j.Level);
    Code:
       0: new           #161                // class org/apache/logging/log4j/core/config/builder/impl/DefaultRootLoggerComponentBuilder
       3: dup
       4: aload_0
       5: aload_1
       6: invokevirtual #160                // Method org/apache/logging/log4j/Level.toString:()Ljava/lang/String;
       9: ldc           #162                // String AsyncRoot
      11: invokespecial #165                // Method org/apache/logging/log4j/core/config/builder/impl/DefaultRootLoggerComponentBuilder."<init>":(Lorg/apache/logging/log4j/core/config/builder/impl/DefaultConfigurationBuilder;Ljava/lang/String;Ljava/lang/String;)V
      14: areturn

  public org.apache.logging.log4j.core.config.builder.api.RootLoggerComponentBuilder newAsyncRootLogger(org.apache.logging.log4j.Level, boolean);
    Code:
       0: new           #161                // class org/apache/logging/log4j/core/config/builder/impl/DefaultRootLoggerComponentBuilder
       3: dup
       4: aload_0
       5: aload_1
       6: invokevirtual #160                // Method org/apache/logging/log4j/Level.toString:()Ljava/lang/String;
       9: ldc           #162                // String AsyncRoot
      11: iload_2
      12: invokespecial #164                // Method org/apache/logging/log4j/core/config/builder/impl/DefaultRootLoggerComponentBuilder."<init>":(Lorg/apache/logging/log4j/core/config/builder/impl/DefaultConfigurationBuilder;Ljava/lang/String;Ljava/lang/String;Z)V
      15: areturn

  public org.apache.logging.log4j.core.config.builder.api.RootLoggerComponentBuilder newAsyncRootLogger(java.lang.String);
    Code:
       0: new           #161                // class org/apache/logging/log4j/core/config/builder/impl/DefaultRootLoggerComponentBuilder
       3: dup
       4: aload_0
       5: aload_1
       6: ldc           #162                // String AsyncRoot
       8: invokespecial #165                // Method org/apache/logging/log4j/core/config/builder/impl/DefaultRootLoggerComponentBuilder."<init>":(Lorg/apache/logging/log4j/core/config/builder/impl/DefaultConfigurationBuilder;Ljava/lang/String;Ljava/lang/String;)V
      11: areturn

  public org.apache.logging.log4j.core.config.builder.api.RootLoggerComponentBuilder newAsyncRootLogger(java.lang.String, boolean);
    Code:
       0: new           #161                // class org/apache/logging/log4j/core/config/builder/impl/DefaultRootLoggerComponentBuilder
       3: dup
       4: aload_0
       5: aload_1
       6: ldc           #162                // String AsyncRoot
       8: iload_2
       9: invokespecial #164                // Method org/apache/logging/log4j/core/config/builder/impl/DefaultRootLoggerComponentBuilder."<init>":(Lorg/apache/logging/log4j/core/config/builder/impl/DefaultConfigurationBuilder;Ljava/lang/String;Ljava/lang/String;Z)V
      12: areturn

  public <B extends org.apache.logging.log4j.core.config.builder.api.ComponentBuilder<B>> org.apache.logging.log4j.core.config.builder.api.ComponentBuilder<B> newComponent(java.lang.String);
    Code:
       0: new           #166                // class org/apache/logging/log4j/core/config/builder/impl/DefaultComponentBuilder
       3: dup
       4: aload_0
       5: aload_1
       6: invokespecial #167                // Method org/apache/logging/log4j/core/config/builder/impl/DefaultComponentBuilder."<init>":(Lorg/apache/logging/log4j/core/config/builder/api/ConfigurationBuilder;Ljava/lang/String;)V
       9: areturn

  public <B extends org.apache.logging.log4j.core.config.builder.api.ComponentBuilder<B>> org.apache.logging.log4j.core.config.builder.api.ComponentBuilder<B> newComponent(java.lang.String, java.lang.String);
    Code:
       0: new           #166                // class org/apache/logging/log4j/core/config/builder/impl/DefaultComponentBuilder
       3: dup
       4: aload_0
       5: aload_1
       6: aload_2
       7: invokespecial #168                // Method org/apache/logging/log4j/core/config/builder/impl/DefaultComponentBuilder."<init>":(Lorg/apache/logging/log4j/core/config/builder/api/ConfigurationBuilder;Ljava/lang/String;Ljava/lang/String;)V
      10: areturn

  public <B extends org.apache.logging.log4j.core.config.builder.api.ComponentBuilder<B>> org.apache.logging.log4j.core.config.builder.api.ComponentBuilder<B> newComponent(java.lang.String, java.lang.String, java.lang.String);
    Code:
       0: new           #166                // class org/apache/logging/log4j/core/config/builder/impl/DefaultComponentBuilder
       3: dup
       4: aload_0
       5: aload_1
       6: aload_2
       7: aload_3
       8: invokespecial #169                // Method org/apache/logging/log4j/core/config/builder/impl/DefaultComponentBuilder."<init>":(Lorg/apache/logging/log4j/core/config/builder/api/ConfigurationBuilder;Ljava/lang/String;Ljava/lang/String;Ljava/lang/String;)V
      11: areturn

  public org.apache.logging.log4j.core.config.builder.api.PropertyComponentBuilder newProperty(java.lang.String, java.lang.String);
    Code:
       0: new           #170                // class org/apache/logging/log4j/core/config/builder/impl/DefaultPropertyComponentBuilder
       3: dup
       4: aload_0
       5: aload_1
       6: aload_2
       7: invokespecial #171                // Method org/apache/logging/log4j/core/config/builder/impl/DefaultPropertyComponentBuilder."<init>":(Lorg/apache/logging/log4j/core/config/builder/impl/DefaultConfigurationBuilder;Ljava/lang/String;Ljava/lang/String;)V
      10: areturn

  public org.apache.logging.log4j.core.config.builder.api.KeyValuePairComponentBuilder newKeyValuePair(java.lang.String, java.lang.String);
    Code:
       0: new           #172                // class org/apache/logging/log4j/core/config/builder/impl/DefaultKeyValuePairComponentBuilder
       3: dup
       4: aload_0
       5: aload_1
       6: aload_2
       7: invokespecial #173                // Method org/apache/logging/log4j/core/config/builder/impl/DefaultKeyValuePairComponentBuilder."<init>":(Lorg/apache/logging/log4j/core/config/builder/impl/DefaultConfigurationBuilder;Ljava/lang/String;Ljava/lang/String;)V
      10: areturn

  public org.apache.logging.log4j.core.config.builder.api.CustomLevelComponentBuilder newCustomLevel(java.lang.String, int);
    Code:
       0: new           #174                // class org/apache/logging/log4j/core/config/builder/impl/DefaultCustomLevelComponentBuilder
       3: dup
       4: aload_0
       5: aload_1
       6: iload_2
       7: invokespecial #175                // Method org/apache/logging/log4j/core/config/builder/impl/DefaultCustomLevelComponentBuilder."<init>":(Lorg/apache/logging/log4j/core/config/builder/impl/DefaultConfigurationBuilder;Ljava/lang/String;I)V
      10: areturn

  public org.apache.logging.log4j.core.config.builder.api.FilterComponentBuilder newFilter(java.lang.String, org.apache.logging.log4j.core.Filter$Result, org.apache.logging.log4j.core.Filter$Result);
    Code:
       0: new           #176                // class org/apache/logging/log4j/core/config/builder/impl/DefaultFilterComponentBuilder
       3: dup
       4: aload_0
       5: aload_1
       6: aload_2
       7: invokevirtual #177                // Method org/apache/logging/log4j/core/Filter$Result.name:()Ljava/lang/String;
      10: aload_3
      11: invokevirtual #177                // Method org/apache/logging/log4j/core/Filter$Result.name:()Ljava/lang/String;
      14: invokespecial #178                // Method org/apache/logging/log4j/core/config/builder/impl/DefaultFilterComponentBuilder."<init>":(Lorg/apache/logging/log4j/core/config/builder/impl/DefaultConfigurationBuilder;Ljava/lang/String;Ljava/lang/String;Ljava/lang/String;)V
      17: areturn

  public org.apache.logging.log4j.core.config.builder.api.FilterComponentBuilder newFilter(java.lang.String, java.lang.String, java.lang.String);
    Code:
       0: new           #176                // class org/apache/logging/log4j/core/config/builder/impl/DefaultFilterComponentBuilder
       3: dup
       4: aload_0
       5: aload_1
       6: aload_2
       7: aload_3
       8: invokespecial #178                // Method org/apache/logging/log4j/core/config/builder/impl/DefaultFilterComponentBuilder."<init>":(Lorg/apache/logging/log4j/core/config/builder/impl/DefaultConfigurationBuilder;Ljava/lang/String;Ljava/lang/String;Ljava/lang/String;)V
      11: areturn

  public org.apache.logging.log4j.core.config.builder.api.LayoutComponentBuilder newLayout(java.lang.String);
    Code:
       0: new           #179                // class org/apache/logging/log4j/core/config/builder/impl/DefaultLayoutComponentBuilder
       3: dup
       4: aload_0
       5: aload_1
       6: invokespecial #180                // Method org/apache/logging/log4j/core/config/builder/impl/DefaultLayoutComponentBuilder."<init>":(Lorg/apache/logging/log4j/core/config/builder/impl/DefaultConfigurationBuilder;Ljava/lang/String;)V
       9: areturn

  public org.apache.logging.log4j.core.config.builder.api.LoggerComponentBuilder newLogger(java.lang.String);
    Code:
       0: new           #156                // class org/apache/logging/log4j/core/config/builder/impl/DefaultLoggerComponentBuilder
       3: dup
       4: aload_0
       5: aload_1
       6: aconst_null
       7: invokespecial #181                // Method org/apache/logging/log4j/core/config/builder/impl/DefaultLoggerComponentBuilder."<init>":(Lorg/apache/logging/log4j/core/config/builder/impl/DefaultConfigurationBuilder;Ljava/lang/String;Ljava/lang/String;)V
      10: areturn

  public org.apache.logging.log4j.core.config.builder.api.LoggerComponentBuilder newLogger(java.lang.String, boolean);
    Code:
       0: new           #156                // class org/apache/logging/log4j/core/config/builder/impl/DefaultLoggerComponentBuilder
       3: dup
       4: aload_0
       5: aload_1
       6: aconst_null
       7: iload_2
       8: invokespecial #182                // Method org/apache/logging/log4j/core/config/builder/impl/DefaultLoggerComponentBuilder."<init>":(Lorg/apache/logging/log4j/core/config/builder/impl/DefaultConfigurationBuilder;Ljava/lang/String;Ljava/lang/String;Z)V
      11: areturn

  public org.apache.logging.log4j.core.config.builder.api.LoggerComponentBuilder newLogger(java.lang.String, org.apache.logging.log4j.Level);
    Code:
       0: new           #156                // class org/apache/logging/log4j/core/config/builder/impl/DefaultLoggerComponentBuilder
       3: dup
       4: aload_0
       5: aload_1
       6: aload_2
       7: invokevirtual #160                // Method org/apache/logging/log4j/Level.toString:()Ljava/lang/String;
      10: invokespecial #181                // Method org/apache/logging/log4j/core/config/builder/impl/DefaultLoggerComponentBuilder."<init>":(Lorg/apache/logging/log4j/core/config/builder/impl/DefaultConfigurationBuilder;Ljava/lang/String;Ljava/lang/String;)V
      13: areturn

  public org.apache.logging.log4j.core.config.builder.api.LoggerComponentBuilder newLogger(java.lang.String, org.apache.logging.log4j.Level, boolean);
    Code:
       0: new           #156                // class org/apache/logging/log4j/core/config/builder/impl/DefaultLoggerComponentBuilder
       3: dup
       4: aload_0
       5: aload_1
       6: aload_2
       7: invokevirtual #160                // Method org/apache/logging/log4j/Level.toString:()Ljava/lang/String;
      10: iload_3
      11: invokespecial #182                // Method org/apache/logging/log4j/core/config/builder/impl/DefaultLoggerComponentBuilder."<init>":(Lorg/apache/logging/log4j/core/config/builder/impl/DefaultConfigurationBuilder;Ljava/lang/String;Ljava/lang/String;Z)V
      14: areturn

  public org.apache.logging.log4j.core.config.builder.api.LoggerComponentBuilder newLogger(java.lang.String, java.lang.String);
    Code:
       0: new           #156                // class org/apache/logging/log4j/core/config/builder/impl/DefaultLoggerComponentBuilder
       3: dup
       4: aload_0
       5: aload_1
       6: aload_2
       7: invokespecial #181                // Method org/apache/logging/log4j/core/config/builder/impl/DefaultLoggerComponentBuilder."<init>":(Lorg/apache/logging/log4j/core/config/builder/impl/DefaultConfigurationBuilder;Ljava/lang/String;Ljava/lang/String;)V
      10: areturn

  public org.apache.logging.log4j.core.config.builder.api.LoggerComponentBuilder newLogger(java.lang.String, java.lang.String, boolean);
    Code:
       0: new           #156                // class org/apache/logging/log4j/core/config/builder/impl/DefaultLoggerComponentBuilder
       3: dup
       4: aload_0
       5: aload_1
       6: aload_2
       7: iload_3
       8: invokespecial #182                // Method org/apache/logging/log4j/core/config/builder/impl/DefaultLoggerComponentBuilder."<init>":(Lorg/apache/logging/log4j/core/config/builder/impl/DefaultConfigurationBuilder;Ljava/lang/String;Ljava/lang/String;Z)V
      11: areturn

  public org.apache.logging.log4j.core.config.builder.api.RootLoggerComponentBuilder newRootLogger();
    Code:
       0: new           #161                // class org/apache/logging/log4j/core/config/builder/impl/DefaultRootLoggerComponentBuilder
       3: dup
       4: aload_0
       5: aconst_null
       6: invokespecial #163                // Method org/apache/logging/log4j/core/config/builder/impl/DefaultRootLoggerComponentBuilder."<init>":(Lorg/apache/logging/log4j/core/config/builder/impl/DefaultConfigurationBuilder;Ljava/lang/String;)V
       9: areturn

  public org.apache.logging.log4j.core.config.builder.api.RootLoggerComponentBuilder newRootLogger(boolean);
    Code:
       0: new           #161                // class org/apache/logging/log4j/core/config/builder/impl/DefaultRootLoggerComponentBuilder
       3: dup
       4: aload_0
       5: aconst_null
       6: iload_1
       7: invokespecial #183                // Method org/apache/logging/log4j/core/config/builder/impl/DefaultRootLoggerComponentBuilder."<init>":(Lorg/apache/logging/log4j/core/config/builder/impl/DefaultConfigurationBuilder;Ljava/lang/String;Z)V
      10: areturn

  public org.apache.logging.log4j.core.config.builder.api.RootLoggerComponentBuilder newRootLogger(org.apache.logging.log4j.Level);
    Code:
       0: new           #161                // class org/apache/logging/log4j/core/config/builder/impl/DefaultRootLoggerComponentBuilder
       3: dup
       4: aload_0
       5: aload_1
       6: invokevirtual #160                // Method org/apache/logging/log4j/Level.toString:()Ljava/lang/String;
       9: invokespecial #163                // Method org/apache/logging/log4j/core/config/builder/impl/DefaultRootLoggerComponentBuilder."<init>":(Lorg/apache/logging/log4j/core/config/builder/impl/DefaultConfigurationBuilder;Ljava/lang/String;)V
      12: areturn

  public org.apache.logging.log4j.core.config.builder.api.RootLoggerComponentBuilder newRootLogger(org.apache.logging.log4j.Level, boolean);
    Code:
       0: new           #161                // class org/apache/logging/log4j/core/config/builder/impl/DefaultRootLoggerComponentBuilder
       3: dup
       4: aload_0
       5: aload_1
       6: invokevirtual #160                // Method org/apache/logging/log4j/Level.toString:()Ljava/lang/String;
       9: iload_2
      10: invokespecial #183                // Method org/apache/logging/log4j/core/config/builder/impl/DefaultRootLoggerComponentBuilder."<init>":(Lorg/apache/logging/log4j/core/config/builder/impl/DefaultConfigurationBuilder;Ljava/lang/String;Z)V
      13: areturn

  public org.apache.logging.log4j.core.config.builder.api.RootLoggerComponentBuilder newRootLogger(java.lang.String);
    Code:
       0: new           #161                // class org/apache/logging/log4j/core/config/builder/impl/DefaultRootLoggerComponentBuilder
       3: dup
       4: aload_0
       5: aload_1
       6: invokespecial #163                // Method org/apache/logging/log4j/core/config/builder/impl/DefaultRootLoggerComponentBuilder."<init>":(Lorg/apache/logging/log4j/core/config/builder/impl/DefaultConfigurationBuilder;Ljava/lang/String;)V
       9: areturn

  public org.apache.logging.log4j.core.config.builder.api.RootLoggerComponentBuilder newRootLogger(java.lang.String, boolean);
    Code:
       0: new           #161                // class org/apache/logging/log4j/core/config/builder/impl/DefaultRootLoggerComponentBuilder
       3: dup
       4: aload_0
       5: aload_1
       6: iload_2
       7: invokespecial #183                // Method org/apache/logging/log4j/core/config/builder/impl/DefaultRootLoggerComponentBuilder."<init>":(Lorg/apache/logging/log4j/core/config/builder/impl/DefaultConfigurationBuilder;Ljava/lang/String;Z)V
      10: areturn

  public org.apache.logging.log4j.core.config.builder.api.ConfigurationBuilder<T> setAdvertiser(java.lang.String);
    Code:
       0: aload_0
       1: aload_1
       2: putfield      #85                 // Field advertiser:Ljava/lang/String;
       5: aload_0
       6: areturn

  public org.apache.logging.log4j.core.config.builder.api.ConfigurationBuilder<T> setConfigurationName(java.lang.String);
    Code:
       0: aload_0
       1: aload_1
       2: putfield      #70                 // Field name:Ljava/lang/String;
       5: aload_0
       6: areturn

  public org.apache.logging.log4j.core.config.builder.api.ConfigurationBuilder<T> setConfigurationSource(org.apache.logging.log4j.core.config.ConfigurationSource);
    Code:
       0: aload_0
       1: aload_1
       2: putfield      #57                 // Field source:Lorg/apache/logging/log4j/core/config/ConfigurationSource;
       5: aload_0
       6: areturn

  public org.apache.logging.log4j.core.config.builder.api.ConfigurationBuilder<T> setMonitorInterval(java.lang.String);
    Code:
       0: aload_0
       1: aload_1
       2: invokestatic  #184                // Method org/apache/logging/log4j/core/util/Integers.parseInt:(Ljava/lang/String;)I
       5: putfield      #87                 // Field monitorInterval:I
       8: aload_0
       9: areturn

  public org.apache.logging.log4j.core.config.builder.api.ConfigurationBuilder<T> setPackages(java.lang.String);
    Code:
       0: aload_0
       1: aload_1
       2: putfield      #79                 // Field packages:Ljava/lang/String;
       5: aload_0
       6: areturn

  public org.apache.logging.log4j.core.config.builder.api.ConfigurationBuilder<T> setShutdownHook(java.lang.String);
    Code:
       0: aload_0
       1: aload_1
       2: putfield      #81                 // Field shutdownFlag:Ljava/lang/String;
       5: aload_0
       6: areturn

  public org.apache.logging.log4j.core.config.builder.api.ConfigurationBuilder<T> setShutdownTimeout(long, java.util.concurrent.TimeUnit);
    Code:
       0: aload_0
       1: aload_3
       2: lload_1
       3: invokevirtual #185                // Method java/util/concurrent/TimeUnit.toMillis:(J)J
       6: putfield      #83                 // Field shutdownTimeoutMillis:J
       9: aload_0
      10: areturn

  public org.apache.logging.log4j.core.config.builder.api.ConfigurationBuilder<T> setStatusLevel(org.apache.logging.log4j.Level);
    Code:
       0: aload_0
       1: aload_1
       2: putfield      #72                 // Field level:Lorg/apache/logging/log4j/Level;
       5: aload_0
       6: areturn

  public org.apache.logging.log4j.core.config.builder.api.ConfigurationBuilder<T> setVerbosity(java.lang.String);
    Code:
       0: aload_0
       1: aload_1
       2: putfield      #75                 // Field verbosity:Ljava/lang/String;
       5: aload_0
       6: areturn

  public org.apache.logging.log4j.core.config.builder.api.ConfigurationBuilder<T> setDestination(java.lang.String);
    Code:
       0: aload_0
       1: aload_1
       2: putfield      #77                 // Field destination:Ljava/lang/String;
       5: aload_0
       6: areturn

  public void setLoggerContext(org.apache.logging.log4j.core.LoggerContext);
    Code:
       0: aload_0
       1: aload_1
       2: putfield      #64                 // Field loggerContext:Lorg/apache/logging/log4j/core/LoggerContext;
       5: return

  public org.apache.logging.log4j.core.config.builder.api.ConfigurationBuilder<T> addRootProperty(java.lang.String, java.lang.String);
    Code:
       0: aload_0
       1: getfield      #15                 // Field root:Lorg/apache/logging/log4j/core/config/builder/api/Component;
       4: invokevirtual #68                 // Method org/apache/logging/log4j/core/config/builder/api/Component.getAttributes:()Ljava/util/Map;
       7: aload_1
       8: aload_2
       9: invokeinterface #186,  3          // InterfaceMethod java/util/Map.put:(Ljava/lang/Object;Ljava/lang/Object;)Ljava/lang/Object;
      14: pop
      15: aload_0
      16: areturn

  public org.apache.logging.log4j.core.config.Configuration build(boolean);
    Code:
       0: aload_0
       1: iload_1
       2: invokevirtual #56                 // Method build:(Z)Lorg/apache/logging/log4j/core/config/builder/impl/BuiltConfiguration;
       5: areturn

  public java.lang.Object build();
    Code:
       0: aload_0
       1: invokevirtual #187                // Method build:()Lorg/apache/logging/log4j/core/config/builder/impl/BuiltConfiguration;
       4: areturn
}
