Compiled from "JsonEncoder.java"
public class ch.qos.logback.classic.encoder.JsonEncoder extends ch.qos.logback.core.encoder.EncoderBase<ch.qos.logback.classic.spi.ILoggingEvent> {
  static final boolean DO_NOT_ADD_QUOTE_KEY;

  static final boolean ADD_QUOTE_KEY;

  static int DEFAULT_SIZE;

  static int DEFAULT_SIZE_WITH_THROWABLE;

  static byte[] EMPTY_BYTES;

  public static final java.lang.String CONTEXT_ATTR_NAME;

  public static final java.lang.String NAME_ATTR_NAME;

  public static final java.lang.String BIRTHDATE_ATTR_NAME;

  public static final java.lang.String CONTEXT_PROPERTIES_ATTR_NAME;

  public static final java.lang.String TIMESTAMP_ATTR_NAME;

  public static final java.lang.String NANOSECONDS_ATTR_NAME;

  public static final java.lang.String SEQUENCE_NUMBER_ATTR_NAME;

  public static final java.lang.String LEVEL_ATTR_NAME;

  public static final java.lang.String MARKERS_ATTR_NAME;

  public static final java.lang.String THREAD_NAME_ATTR_NAME;

  public static final java.lang.String MDC_ATTR_NAME;

  public static final java.lang.String LOGGER_ATTR_NAME;

  public static final java.lang.String MESSAGE_ATTR_NAME;

  public static final java.lang.String ARGUMENT_ARRAY_ATTR_NAME;

  public static final java.lang.String KEY_VALUE_PAIRS_ATTR_NAME;

  public static final java.lang.String THROWABLE_ATTR_NAME;

  private static final java.lang.String CLASS_NAME_ATTR_NAME;

  private static final java.lang.String METHOD_NAME_ATTR_NAME;

  private static final java.lang.String FILE_NAME_ATTR_NAME;

  private static final java.lang.String LINE_NUMBER_ATTR_NAME;

  private static final java.lang.String STEP_ARRAY_NAME_ATTRIBUTE;

  private static final char OPEN_OBJ;

  private static final char CLOSE_OBJ;

  private static final char OPEN_ARRAY;

  private static final char CLOSE_ARRAY;

  private static final char QUOTE;

  private static final char SP;

  private static final char ENTRY_SEPARATOR;

  private static final java.lang.String COL_SP;

  private static final java.lang.String QUOTE_COL;

  private static final char VALUE_SEPARATOR;

  public ch.qos.logback.classic.encoder.JsonEncoder();
    Code:
       0: aload_0
       1: invokespecial #5                  // Method ch/qos/logback/core/encoder/EncoderBase."<init>":()V
       4: return

  public byte[] headerBytes();
    Code:
       0: getstatic     #11                 // Field EMPTY_BYTES:[B
       3: areturn

  public byte[] encode(ch.qos.logback.classic.spi.ILoggingEvent);
    Code:
       0: aload_1
       1: invokeinterface #17,  1           // InterfaceMethod ch/qos/logback/classic/spi/ILoggingEvent.getThrowableProxy:()Lch/qos/logback/classic/spi/IThrowableProxy;
       6: ifnonnull     15
       9: getstatic     #23                 // Field DEFAULT_SIZE:I
      12: goto          18
      15: getstatic     #27                 // Field DEFAULT_SIZE_WITH_THROWABLE:I
      18: istore_2
      19: new           #30                 // class java/lang/StringBuilder
      22: dup
      23: iload_2
      24: invokespecial #32                 // Method java/lang/StringBuilder."<init>":(I)V
      27: astore_3
      28: aload_3
      29: bipush        123
      31: invokevirtual #35                 // Method java/lang/StringBuilder.append:(C)Ljava/lang/StringBuilder;
      34: pop
      35: aload_0
      36: aload_3
      37: ldc           #39                 // String sequenceNumber
      39: aload_1
      40: invokeinterface #41,  1           // InterfaceMethod ch/qos/logback/classic/spi/ILoggingEvent.getSequenceNumber:()J
      45: invokevirtual #45                 // Method appenderMemberWithLongValue:(Ljava/lang/StringBuilder;Ljava/lang/String;J)V
      48: aload_3
      49: bipush        44
      51: invokevirtual #35                 // Method java/lang/StringBuilder.append:(C)Ljava/lang/StringBuilder;
      54: pop
      55: aload_0
      56: aload_3
      57: ldc           #49                 // String timestamp
      59: aload_1
      60: invokeinterface #51,  1           // InterfaceMethod ch/qos/logback/classic/spi/ILoggingEvent.getTimeStamp:()J
      65: invokevirtual #45                 // Method appenderMemberWithLongValue:(Ljava/lang/StringBuilder;Ljava/lang/String;J)V
      68: aload_3
      69: bipush        44
      71: invokevirtual #35                 // Method java/lang/StringBuilder.append:(C)Ljava/lang/StringBuilder;
      74: pop
      75: aload_0
      76: aload_3
      77: ldc           #54                 // String nanoseconds
      79: aload_1
      80: invokeinterface #56,  1           // InterfaceMethod ch/qos/logback/classic/spi/ILoggingEvent.getNanoseconds:()I
      85: i2l
      86: invokevirtual #45                 // Method appenderMemberWithLongValue:(Ljava/lang/StringBuilder;Ljava/lang/String;J)V
      89: aload_3
      90: bipush        44
      92: invokevirtual #35                 // Method java/lang/StringBuilder.append:(C)Ljava/lang/StringBuilder;
      95: pop
      96: aload_1
      97: invokeinterface #60,  1           // InterfaceMethod ch/qos/logback/classic/spi/ILoggingEvent.getLevel:()Lch/qos/logback/classic/Level;
     102: ifnull        117
     105: aload_1
     106: invokeinterface #60,  1           // InterfaceMethod ch/qos/logback/classic/spi/ILoggingEvent.getLevel:()Lch/qos/logback/classic/Level;
     111: getfield      #64                 // Field ch/qos/logback/classic/Level.levelStr:Ljava/lang/String;
     114: goto          119
     117: ldc           #70                 // String null
     119: astore        4
     121: aload_0
     122: aload_3
     123: ldc           #72                 // String level
     125: aload         4
     127: invokevirtual #74                 // Method appenderMember:(Ljava/lang/StringBuilder;Ljava/lang/String;Ljava/lang/String;)V
     130: aload_3
     131: bipush        44
     133: invokevirtual #35                 // Method java/lang/StringBuilder.append:(C)Ljava/lang/StringBuilder;
     136: pop
     137: aload_0
     138: aload_3
     139: ldc           #78                 // String threadName
     141: aload_0
     142: aload_1
     143: invokeinterface #80,  1           // InterfaceMethod ch/qos/logback/classic/spi/ILoggingEvent.getThreadName:()Ljava/lang/String;
     148: invokevirtual #84                 // Method jsonEscape:(Ljava/lang/String;)Ljava/lang/String;
     151: invokevirtual #74                 // Method appenderMember:(Ljava/lang/StringBuilder;Ljava/lang/String;Ljava/lang/String;)V
     154: aload_3
     155: bipush        44
     157: invokevirtual #35                 // Method java/lang/StringBuilder.append:(C)Ljava/lang/StringBuilder;
     160: pop
     161: aload_0
     162: aload_3
     163: ldc           #88                 // String loggerName
     165: aload_1
     166: invokeinterface #90,  1           // InterfaceMethod ch/qos/logback/classic/spi/ILoggingEvent.getLoggerName:()Ljava/lang/String;
     171: invokevirtual #74                 // Method appenderMember:(Ljava/lang/StringBuilder;Ljava/lang/String;Ljava/lang/String;)V
     174: aload_3
     175: bipush        44
     177: invokevirtual #35                 // Method java/lang/StringBuilder.append:(C)Ljava/lang/StringBuilder;
     180: pop
     181: aload_0
     182: aload_3
     183: aload_1
     184: invokeinterface #93,  1           // InterfaceMethod ch/qos/logback/classic/spi/ILoggingEvent.getLoggerContextVO:()Lch/qos/logback/classic/spi/LoggerContextVO;
     189: invokevirtual #97                 // Method appendLoggerContext:(Ljava/lang/StringBuilder;Lch/qos/logback/classic/spi/LoggerContextVO;)V
     192: aload_3
     193: bipush        44
     195: invokevirtual #35                 // Method java/lang/StringBuilder.append:(C)Ljava/lang/StringBuilder;
     198: pop
     199: aload_0
     200: aload_3
     201: aload_1
     202: invokevirtual #101                // Method appendMarkers:(Ljava/lang/StringBuilder;Lch/qos/logback/classic/spi/ILoggingEvent;)V
     205: aload_0
     206: aload_3
     207: aload_1
     208: invokevirtual #105                // Method appendMDC:(Ljava/lang/StringBuilder;Lch/qos/logback/classic/spi/ILoggingEvent;)V
     211: aload_0
     212: aload_3
     213: aload_1
     214: invokevirtual #108                // Method appendKeyValuePairs:(Ljava/lang/StringBuilder;Lch/qos/logback/classic/spi/ILoggingEvent;)V
     217: aload_0
     218: aload_3
     219: ldc           #111                // String message
     221: aload_0
     222: aload_1
     223: invokeinterface #113,  1          // InterfaceMethod ch/qos/logback/classic/spi/ILoggingEvent.getMessage:()Ljava/lang/String;
     228: invokevirtual #84                 // Method jsonEscape:(Ljava/lang/String;)Ljava/lang/String;
     231: invokevirtual #74                 // Method appenderMember:(Ljava/lang/StringBuilder;Ljava/lang/String;Ljava/lang/String;)V
     234: aload_3
     235: bipush        44
     237: invokevirtual #35                 // Method java/lang/StringBuilder.append:(C)Ljava/lang/StringBuilder;
     240: pop
     241: aload_0
     242: aload_3
     243: aload_1
     244: invokevirtual #116                // Method appendArgumentArray:(Ljava/lang/StringBuilder;Lch/qos/logback/classic/spi/ILoggingEvent;)V
     247: aload_0
     248: aload_3
     249: aload_1
     250: invokevirtual #119                // Method appendThrowableProxy:(Ljava/lang/StringBuilder;Lch/qos/logback/classic/spi/ILoggingEvent;)V
     253: aload_3
     254: bipush        125
     256: invokevirtual #35                 // Method java/lang/StringBuilder.append:(C)Ljava/lang/StringBuilder;
     259: pop
     260: aload_3
     261: bipush        10
     263: invokevirtual #35                 // Method java/lang/StringBuilder.append:(C)Ljava/lang/StringBuilder;
     266: pop
     267: aload_3
     268: invokevirtual #122                // Method java/lang/StringBuilder.toString:()Ljava/lang/String;
     271: getstatic     #125                // Field ch/qos/logback/core/CoreConstants.UTF_8_CHARSET:Ljava/nio/charset/Charset;
     274: invokevirtual #129                // Method java/lang/String.getBytes:(Ljava/nio/charset/Charset;)[B
     277: areturn

  private void appendLoggerContext(java.lang.StringBuilder, ch.qos.logback.classic.spi.LoggerContextVO);
    Code:
       0: aload_1
       1: bipush        34
       3: invokevirtual #35                 // Method java/lang/StringBuilder.append:(C)Ljava/lang/StringBuilder;
       6: ldc           #135                // String context
       8: invokevirtual #137                // Method java/lang/StringBuilder.append:(Ljava/lang/String;)Ljava/lang/StringBuilder;
      11: ldc           #140                // String \":
      13: invokevirtual #137                // Method java/lang/StringBuilder.append:(Ljava/lang/String;)Ljava/lang/StringBuilder;
      16: pop
      17: aload_2
      18: ifnonnull     29
      21: aload_1
      22: ldc           #70                 // String null
      24: invokevirtual #137                // Method java/lang/StringBuilder.append:(Ljava/lang/String;)Ljava/lang/StringBuilder;
      27: pop
      28: return
      29: aload_1
      30: bipush        123
      32: invokevirtual #35                 // Method java/lang/StringBuilder.append:(C)Ljava/lang/StringBuilder;
      35: pop
      36: aload_0
      37: aload_1
      38: ldc           #142                // String name
      40: aload_0
      41: aload_2
      42: invokevirtual #144                // Method ch/qos/logback/classic/spi/LoggerContextVO.getName:()Ljava/lang/String;
      45: invokevirtual #149                // Method nullSafeStr:(Ljava/lang/String;)Ljava/lang/String;
      48: invokevirtual #74                 // Method appenderMember:(Ljava/lang/StringBuilder;Ljava/lang/String;Ljava/lang/String;)V
      51: aload_1
      52: bipush        44
      54: invokevirtual #35                 // Method java/lang/StringBuilder.append:(C)Ljava/lang/StringBuilder;
      57: pop
      58: aload_0
      59: aload_1
      60: ldc           #152                // String birthdate
      62: aload_2
      63: invokevirtual #154                // Method ch/qos/logback/classic/spi/LoggerContextVO.getBirthTime:()J
      66: invokevirtual #45                 // Method appenderMemberWithLongValue:(Ljava/lang/StringBuilder;Ljava/lang/String;J)V
      69: aload_1
      70: bipush        44
      72: invokevirtual #35                 // Method java/lang/StringBuilder.append:(C)Ljava/lang/StringBuilder;
      75: pop
      76: aload_0
      77: aload_1
      78: ldc           #157                // String properties
      80: aload_2
      81: invokevirtual #159                // Method ch/qos/logback/classic/spi/LoggerContextVO.getPropertyMap:()Ljava/util/Map;
      84: invokevirtual #163                // Method appendMap:(Ljava/lang/StringBuilder;Ljava/lang/String;Ljava/util/Map;)V
      87: aload_1
      88: bipush        125
      90: invokevirtual #35                 // Method java/lang/StringBuilder.append:(C)Ljava/lang/StringBuilder;
      93: pop
      94: return

  private void appendMap(java.lang.StringBuilder, java.lang.String, java.util.Map<java.lang.String, java.lang.String>);
    Code:
       0: aload_1
       1: bipush        34
       3: invokevirtual #35                 // Method java/lang/StringBuilder.append:(C)Ljava/lang/StringBuilder;
       6: aload_2
       7: invokevirtual #137                // Method java/lang/StringBuilder.append:(Ljava/lang/String;)Ljava/lang/StringBuilder;
      10: ldc           #140                // String \":
      12: invokevirtual #137                // Method java/lang/StringBuilder.append:(Ljava/lang/String;)Ljava/lang/StringBuilder;
      15: pop
      16: aload_3
      17: ifnonnull     28
      20: aload_1
      21: ldc           #70                 // String null
      23: invokevirtual #137                // Method java/lang/StringBuilder.append:(Ljava/lang/String;)Ljava/lang/StringBuilder;
      26: pop
      27: return
      28: aload_1
      29: bipush        123
      31: invokevirtual #35                 // Method java/lang/StringBuilder.append:(C)Ljava/lang/StringBuilder;
      34: pop
      35: iconst_0
      36: istore        4
      38: aload_3
      39: invokeinterface #167,  1          // InterfaceMethod java/util/Map.entrySet:()Ljava/util/Set;
      44: astore        5
      46: aload         5
      48: invokeinterface #173,  1          // InterfaceMethod java/util/Set.iterator:()Ljava/util/Iterator;
      53: astore        6
      55: aload         6
      57: invokeinterface #179,  1          // InterfaceMethod java/util/Iterator.hasNext:()Z
      62: ifeq          122
      65: aload         6
      67: invokeinterface #185,  1          // InterfaceMethod java/util/Iterator.next:()Ljava/lang/Object;
      72: checkcast     #189                // class java/util/Map$Entry
      75: astore        7
      77: iload         4
      79: ifeq          89
      82: aload_1
      83: bipush        44
      85: invokevirtual #35                 // Method java/lang/StringBuilder.append:(C)Ljava/lang/StringBuilder;
      88: pop
      89: iconst_1
      90: istore        4
      92: aload_0
      93: aload_1
      94: aload_0
      95: aload         7
      97: invokeinterface #191,  1          // InterfaceMethod java/util/Map$Entry.getKey:()Ljava/lang/Object;
     102: invokevirtual #194                // Method jsonEscapedToString:(Ljava/lang/Object;)Ljava/lang/String;
     105: aload_0
     106: aload         7
     108: invokeinterface #198,  1          // InterfaceMethod java/util/Map$Entry.getValue:()Ljava/lang/Object;
     113: invokevirtual #194                // Method jsonEscapedToString:(Ljava/lang/Object;)Ljava/lang/String;
     116: invokevirtual #74                 // Method appenderMember:(Ljava/lang/StringBuilder;Ljava/lang/String;Ljava/lang/String;)V
     119: goto          55
     122: aload_1
     123: bipush        125
     125: invokevirtual #35                 // Method java/lang/StringBuilder.append:(C)Ljava/lang/StringBuilder;
     128: pop
     129: return

  private void appendThrowableProxy(java.lang.StringBuilder, ch.qos.logback.classic.spi.ILoggingEvent);
    Code:
       0: aload_2
       1: invokeinterface #17,  1           // InterfaceMethod ch/qos/logback/classic/spi/ILoggingEvent.getThrowableProxy:()Lch/qos/logback/classic/spi/IThrowableProxy;
       6: astore_3
       7: aload_1
       8: bipush        34
      10: invokevirtual #35                 // Method java/lang/StringBuilder.append:(C)Ljava/lang/StringBuilder;
      13: ldc           #201                // String throwable
      15: invokevirtual #137                // Method java/lang/StringBuilder.append:(Ljava/lang/String;)Ljava/lang/StringBuilder;
      18: ldc           #140                // String \":
      20: invokevirtual #137                // Method java/lang/StringBuilder.append:(Ljava/lang/String;)Ljava/lang/StringBuilder;
      23: pop
      24: aload_3
      25: ifnonnull     36
      28: aload_1
      29: ldc           #70                 // String null
      31: invokevirtual #137                // Method java/lang/StringBuilder.append:(Ljava/lang/String;)Ljava/lang/StringBuilder;
      34: pop
      35: return
      36: aload_1
      37: bipush        123
      39: invokevirtual #35                 // Method java/lang/StringBuilder.append:(C)Ljava/lang/StringBuilder;
      42: pop
      43: aload_0
      44: aload_1
      45: ldc           #203                // String className
      47: aload_0
      48: aload_3
      49: invokeinterface #205,  1          // InterfaceMethod ch/qos/logback/classic/spi/IThrowableProxy.getClassName:()Ljava/lang/String;
      54: invokevirtual #149                // Method nullSafeStr:(Ljava/lang/String;)Ljava/lang/String;
      57: invokevirtual #74                 // Method appenderMember:(Ljava/lang/StringBuilder;Ljava/lang/String;Ljava/lang/String;)V
      60: aload_1
      61: bipush        44
      63: invokevirtual #35                 // Method java/lang/StringBuilder.append:(C)Ljava/lang/StringBuilder;
      66: pop
      67: aload_0
      68: aload_1
      69: ldc           #111                // String message
      71: aload_0
      72: aload_3
      73: invokeinterface #210,  1          // InterfaceMethod ch/qos/logback/classic/spi/IThrowableProxy.getMessage:()Ljava/lang/String;
      78: invokevirtual #84                 // Method jsonEscape:(Ljava/lang/String;)Ljava/lang/String;
      81: invokevirtual #74                 // Method appenderMember:(Ljava/lang/StringBuilder;Ljava/lang/String;Ljava/lang/String;)V
      84: aload_1
      85: bipush        44
      87: invokevirtual #35                 // Method java/lang/StringBuilder.append:(C)Ljava/lang/StringBuilder;
      90: pop
      91: aload_3
      92: invokeinterface #211,  1          // InterfaceMethod ch/qos/logback/classic/spi/IThrowableProxy.getStackTraceElementProxyArray:()[Lch/qos/logback/classic/spi/StackTraceElementProxy;
      97: astore        4
      99: aload_1
     100: bipush        34
     102: invokevirtual #35                 // Method java/lang/StringBuilder.append:(C)Ljava/lang/StringBuilder;
     105: ldc           #215                // String stepArray
     107: invokevirtual #137                // Method java/lang/StringBuilder.append:(Ljava/lang/String;)Ljava/lang/StringBuilder;
     110: ldc           #140                // String \":
     112: invokevirtual #137                // Method java/lang/StringBuilder.append:(Ljava/lang/String;)Ljava/lang/StringBuilder;
     115: bipush        91
     117: invokevirtual #35                 // Method java/lang/StringBuilder.append:(C)Ljava/lang/StringBuilder;
     120: pop
     121: aload         4
     123: ifnull        132
     126: aload         4
     128: arraylength
     129: goto          133
     132: iconst_0
     133: istore        5
     135: iconst_0
     136: istore        6
     138: iload         6
     140: iload         5
     142: if_icmpge     272
     145: iload         6
     147: ifeq          157
     150: aload_1
     151: bipush        44
     153: invokevirtual #35                 // Method java/lang/StringBuilder.append:(C)Ljava/lang/StringBuilder;
     156: pop
     157: aload         4
     159: iload         6
     161: aaload
     162: astore        7
     164: aload_1
     165: bipush        123
     167: invokevirtual #35                 // Method java/lang/StringBuilder.append:(C)Ljava/lang/StringBuilder;
     170: pop
     171: aload         7
     173: invokevirtual #217                // Method ch/qos/logback/classic/spi/StackTraceElementProxy.getStackTraceElement:()Ljava/lang/StackTraceElement;
     176: astore        8
     178: aload_0
     179: aload_1
     180: ldc           #203                // String className
     182: aload_0
     183: aload         8
     185: invokevirtual #223                // Method java/lang/StackTraceElement.getClassName:()Ljava/lang/String;
     188: invokevirtual #149                // Method nullSafeStr:(Ljava/lang/String;)Ljava/lang/String;
     191: invokevirtual #74                 // Method appenderMember:(Ljava/lang/StringBuilder;Ljava/lang/String;Ljava/lang/String;)V
     194: aload_1
     195: bipush        44
     197: invokevirtual #35                 // Method java/lang/StringBuilder.append:(C)Ljava/lang/StringBuilder;
     200: pop
     201: aload_0
     202: aload_1
     203: ldc           #226                // String methodName
     205: aload_0
     206: aload         8
     208: invokevirtual #228                // Method java/lang/StackTraceElement.getMethodName:()Ljava/lang/String;
     211: invokevirtual #149                // Method nullSafeStr:(Ljava/lang/String;)Ljava/lang/String;
     214: invokevirtual #74                 // Method appenderMember:(Ljava/lang/StringBuilder;Ljava/lang/String;Ljava/lang/String;)V
     217: aload_1
     218: bipush        44
     220: invokevirtual #35                 // Method java/lang/StringBuilder.append:(C)Ljava/lang/StringBuilder;
     223: pop
     224: aload_0
     225: aload_1
     226: ldc           #231                // String fileName
     228: aload_0
     229: aload         8
     231: invokevirtual #233                // Method java/lang/StackTraceElement.getFileName:()Ljava/lang/String;
     234: invokevirtual #149                // Method nullSafeStr:(Ljava/lang/String;)Ljava/lang/String;
     237: invokevirtual #74                 // Method appenderMember:(Ljava/lang/StringBuilder;Ljava/lang/String;Ljava/lang/String;)V
     240: aload_1
     241: bipush        44
     243: invokevirtual #35                 // Method java/lang/StringBuilder.append:(C)Ljava/lang/StringBuilder;
     246: pop
     247: aload_0
     248: aload_1
     249: ldc           #236                // String lineNumber
     251: aload         8
     253: invokevirtual #238                // Method java/lang/StackTraceElement.getLineNumber:()I
     256: invokevirtual #241                // Method appenderMemberWithIntValue:(Ljava/lang/StringBuilder;Ljava/lang/String;I)V
     259: aload_1
     260: bipush        125
     262: invokevirtual #35                 // Method java/lang/StringBuilder.append:(C)Ljava/lang/StringBuilder;
     265: pop
     266: iinc          6, 1
     269: goto          138
     272: aload_1
     273: bipush        93
     275: invokevirtual #35                 // Method java/lang/StringBuilder.append:(C)Ljava/lang/StringBuilder;
     278: pop
     279: aload_1
     280: bipush        125
     282: invokevirtual #35                 // Method java/lang/StringBuilder.append:(C)Ljava/lang/StringBuilder;
     285: pop
     286: return

  private void appenderMember(java.lang.StringBuilder, java.lang.String, java.lang.String);
    Code:
       0: aload_1
       1: bipush        34
       3: invokevirtual #35                 // Method java/lang/StringBuilder.append:(C)Ljava/lang/StringBuilder;
       6: aload_2
       7: invokevirtual #137                // Method java/lang/StringBuilder.append:(Ljava/lang/String;)Ljava/lang/StringBuilder;
      10: ldc           #140                // String \":
      12: invokevirtual #137                // Method java/lang/StringBuilder.append:(Ljava/lang/String;)Ljava/lang/StringBuilder;
      15: bipush        34
      17: invokevirtual #35                 // Method java/lang/StringBuilder.append:(C)Ljava/lang/StringBuilder;
      20: aload_3
      21: invokevirtual #137                // Method java/lang/StringBuilder.append:(Ljava/lang/String;)Ljava/lang/StringBuilder;
      24: bipush        34
      26: invokevirtual #35                 // Method java/lang/StringBuilder.append:(C)Ljava/lang/StringBuilder;
      29: pop
      30: return

  private void appenderMemberWithIntValue(java.lang.StringBuilder, java.lang.String, int);
    Code:
       0: aload_1
       1: bipush        34
       3: invokevirtual #35                 // Method java/lang/StringBuilder.append:(C)Ljava/lang/StringBuilder;
       6: aload_2
       7: invokevirtual #137                // Method java/lang/StringBuilder.append:(Ljava/lang/String;)Ljava/lang/StringBuilder;
      10: ldc           #140                // String \":
      12: invokevirtual #137                // Method java/lang/StringBuilder.append:(Ljava/lang/String;)Ljava/lang/StringBuilder;
      15: iload_3
      16: invokevirtual #245                // Method java/lang/StringBuilder.append:(I)Ljava/lang/StringBuilder;
      19: pop
      20: return

  private void appenderMemberWithLongValue(java.lang.StringBuilder, java.lang.String, long);
    Code:
       0: aload_1
       1: bipush        34
       3: invokevirtual #35                 // Method java/lang/StringBuilder.append:(C)Ljava/lang/StringBuilder;
       6: aload_2
       7: invokevirtual #137                // Method java/lang/StringBuilder.append:(Ljava/lang/String;)Ljava/lang/StringBuilder;
      10: ldc           #140                // String \":
      12: invokevirtual #137                // Method java/lang/StringBuilder.append:(Ljava/lang/String;)Ljava/lang/StringBuilder;
      15: lload_3
      16: invokevirtual #248                // Method java/lang/StringBuilder.append:(J)Ljava/lang/StringBuilder;
      19: pop
      20: return

  private void appendKeyValuePairs(java.lang.StringBuilder, ch.qos.logback.classic.spi.ILoggingEvent);
    Code:
       0: aload_2
       1: invokeinterface #251,  1          // InterfaceMethod ch/qos/logback/classic/spi/ILoggingEvent.getKeyValuePairs:()Ljava/util/List;
       6: astore_3
       7: aload_3
       8: ifnull        20
      11: aload_3
      12: invokeinterface #255,  1          // InterfaceMethod java/util/List.isEmpty:()Z
      17: ifeq          21
      20: return
      21: aload_1
      22: bipush        34
      24: invokevirtual #35                 // Method java/lang/StringBuilder.append:(C)Ljava/lang/StringBuilder;
      27: ldc_w         #260                // String kvpList
      30: invokevirtual #137                // Method java/lang/StringBuilder.append:(Ljava/lang/String;)Ljava/lang/StringBuilder;
      33: ldc           #140                // String \":
      35: invokevirtual #137                // Method java/lang/StringBuilder.append:(Ljava/lang/String;)Ljava/lang/StringBuilder;
      38: bipush        32
      40: invokevirtual #35                 // Method java/lang/StringBuilder.append:(C)Ljava/lang/StringBuilder;
      43: bipush        91
      45: invokevirtual #35                 // Method java/lang/StringBuilder.append:(C)Ljava/lang/StringBuilder;
      48: pop
      49: aload_3
      50: invokeinterface #262,  1          // InterfaceMethod java/util/List.size:()I
      55: istore        4
      57: iconst_0
      58: istore        5
      60: iload         5
      62: iload         4
      64: if_icmpge     135
      67: iload         5
      69: ifeq          79
      72: aload_1
      73: bipush        44
      75: invokevirtual #35                 // Method java/lang/StringBuilder.append:(C)Ljava/lang/StringBuilder;
      78: pop
      79: aload_3
      80: iload         5
      82: invokeinterface #265,  2          // InterfaceMethod java/util/List.get:(I)Ljava/lang/Object;
      87: checkcast     #269                // class org/slf4j/event/KeyValuePair
      90: astore        6
      92: aload_1
      93: bipush        123
      95: invokevirtual #35                 // Method java/lang/StringBuilder.append:(C)Ljava/lang/StringBuilder;
      98: pop
      99: aload_0
     100: aload_1
     101: aload_0
     102: aload         6
     104: getfield      #271                // Field org/slf4j/event/KeyValuePair.key:Ljava/lang/String;
     107: invokevirtual #194                // Method jsonEscapedToString:(Ljava/lang/Object;)Ljava/lang/String;
     110: aload_0
     111: aload         6
     113: getfield      #274                // Field org/slf4j/event/KeyValuePair.value:Ljava/lang/Object;
     116: invokevirtual #194                // Method jsonEscapedToString:(Ljava/lang/Object;)Ljava/lang/String;
     119: invokevirtual #74                 // Method appenderMember:(Ljava/lang/StringBuilder;Ljava/lang/String;Ljava/lang/String;)V
     122: aload_1
     123: bipush        125
     125: invokevirtual #35                 // Method java/lang/StringBuilder.append:(C)Ljava/lang/StringBuilder;
     128: pop
     129: iinc          5, 1
     132: goto          60
     135: aload_1
     136: bipush        93
     138: invokevirtual #35                 // Method java/lang/StringBuilder.append:(C)Ljava/lang/StringBuilder;
     141: pop
     142: aload_1
     143: bipush        44
     145: invokevirtual #35                 // Method java/lang/StringBuilder.append:(C)Ljava/lang/StringBuilder;
     148: pop
     149: return

  private void appendArgumentArray(java.lang.StringBuilder, ch.qos.logback.classic.spi.ILoggingEvent);
    Code:
       0: aload_2
       1: invokeinterface #278,  1          // InterfaceMethod ch/qos/logback/classic/spi/ILoggingEvent.getArgumentArray:()[Ljava/lang/Object;
       6: astore_3
       7: aload_3
       8: ifnonnull     12
      11: return
      12: aload_1
      13: bipush        34
      15: invokevirtual #35                 // Method java/lang/StringBuilder.append:(C)Ljava/lang/StringBuilder;
      18: ldc_w         #282                // String arguments
      21: invokevirtual #137                // Method java/lang/StringBuilder.append:(Ljava/lang/String;)Ljava/lang/StringBuilder;
      24: ldc           #140                // String \":
      26: invokevirtual #137                // Method java/lang/StringBuilder.append:(Ljava/lang/String;)Ljava/lang/StringBuilder;
      29: bipush        32
      31: invokevirtual #35                 // Method java/lang/StringBuilder.append:(C)Ljava/lang/StringBuilder;
      34: bipush        91
      36: invokevirtual #35                 // Method java/lang/StringBuilder.append:(C)Ljava/lang/StringBuilder;
      39: pop
      40: aload_3
      41: arraylength
      42: istore        4
      44: iconst_0
      45: istore        5
      47: iload         5
      49: iload         4
      51: if_icmpge     95
      54: iload         5
      56: ifeq          66
      59: aload_1
      60: bipush        44
      62: invokevirtual #35                 // Method java/lang/StringBuilder.append:(C)Ljava/lang/StringBuilder;
      65: pop
      66: aload_1
      67: bipush        34
      69: invokevirtual #35                 // Method java/lang/StringBuilder.append:(C)Ljava/lang/StringBuilder;
      72: aload_0
      73: aload_3
      74: iload         5
      76: aaload
      77: invokevirtual #194                // Method jsonEscapedToString:(Ljava/lang/Object;)Ljava/lang/String;
      80: invokevirtual #137                // Method java/lang/StringBuilder.append:(Ljava/lang/String;)Ljava/lang/StringBuilder;
      83: bipush        34
      85: invokevirtual #35                 // Method java/lang/StringBuilder.append:(C)Ljava/lang/StringBuilder;
      88: pop
      89: iinc          5, 1
      92: goto          47
      95: aload_1
      96: bipush        93
      98: invokevirtual #35                 // Method java/lang/StringBuilder.append:(C)Ljava/lang/StringBuilder;
     101: pop
     102: aload_1
     103: bipush        44
     105: invokevirtual #35                 // Method java/lang/StringBuilder.append:(C)Ljava/lang/StringBuilder;
     108: pop
     109: return

  private void appendMarkers(java.lang.StringBuilder, ch.qos.logback.classic.spi.ILoggingEvent);
    Code:
       0: aload_2
       1: invokeinterface #284,  1          // InterfaceMethod ch/qos/logback/classic/spi/ILoggingEvent.getMarkerList:()Ljava/util/List;
       6: astore_3
       7: aload_3
       8: ifnonnull     12
      11: return
      12: aload_1
      13: bipush        34
      15: invokevirtual #35                 // Method java/lang/StringBuilder.append:(C)Ljava/lang/StringBuilder;
      18: ldc_w         #287                // String markers
      21: invokevirtual #137                // Method java/lang/StringBuilder.append:(Ljava/lang/String;)Ljava/lang/StringBuilder;
      24: ldc           #140                // String \":
      26: invokevirtual #137                // Method java/lang/StringBuilder.append:(Ljava/lang/String;)Ljava/lang/StringBuilder;
      29: bipush        32
      31: invokevirtual #35                 // Method java/lang/StringBuilder.append:(C)Ljava/lang/StringBuilder;
      34: bipush        91
      36: invokevirtual #35                 // Method java/lang/StringBuilder.append:(C)Ljava/lang/StringBuilder;
      39: pop
      40: aload_3
      41: invokeinterface #262,  1          // InterfaceMethod java/util/List.size:()I
      46: istore        4
      48: iconst_0
      49: istore        5
      51: iload         5
      53: iload         4
      55: if_icmpge     103
      58: iload         5
      60: ifeq          70
      63: aload_1
      64: bipush        44
      66: invokevirtual #35                 // Method java/lang/StringBuilder.append:(C)Ljava/lang/StringBuilder;
      69: pop
      70: aload_1
      71: bipush        34
      73: invokevirtual #35                 // Method java/lang/StringBuilder.append:(C)Ljava/lang/StringBuilder;
      76: aload_0
      77: aload_3
      78: iload         5
      80: invokeinterface #265,  2          // InterfaceMethod java/util/List.get:(I)Ljava/lang/Object;
      85: invokevirtual #194                // Method jsonEscapedToString:(Ljava/lang/Object;)Ljava/lang/String;
      88: invokevirtual #137                // Method java/lang/StringBuilder.append:(Ljava/lang/String;)Ljava/lang/StringBuilder;
      91: bipush        34
      93: invokevirtual #35                 // Method java/lang/StringBuilder.append:(C)Ljava/lang/StringBuilder;
      96: pop
      97: iinc          5, 1
     100: goto          51
     103: aload_1
     104: bipush        93
     106: invokevirtual #35                 // Method java/lang/StringBuilder.append:(C)Ljava/lang/StringBuilder;
     109: pop
     110: aload_1
     111: bipush        44
     113: invokevirtual #35                 // Method java/lang/StringBuilder.append:(C)Ljava/lang/StringBuilder;
     116: pop
     117: return

  private java.lang.String jsonEscapedToString(java.lang.Object);
    Code:
       0: aload_1
       1: ifnonnull     7
       4: ldc           #70                 // String null
       6: areturn
       7: aload_1
       8: invokevirtual #289                // Method java/lang/Object.toString:()Ljava/lang/String;
      11: invokestatic  #292                // Method ch/qos/logback/core/encoder/JsonEscapeUtil.jsonEscapeString:(Ljava/lang/String;)Ljava/lang/String;
      14: areturn

  private java.lang.String nullSafeStr(java.lang.String);
    Code:
       0: aload_1
       1: ifnonnull     7
       4: ldc           #70                 // String null
       6: areturn
       7: aload_1
       8: areturn

  private java.lang.String jsonEscape(java.lang.String);
    Code:
       0: aload_1
       1: ifnonnull     7
       4: ldc           #70                 // String null
       6: areturn
       7: aload_1
       8: invokestatic  #292                // Method ch/qos/logback/core/encoder/JsonEscapeUtil.jsonEscapeString:(Ljava/lang/String;)Ljava/lang/String;
      11: areturn

  private void appendMDC(java.lang.StringBuilder, ch.qos.logback.classic.spi.ILoggingEvent);
    Code:
       0: aload_2
       1: invokeinterface #297,  1          // InterfaceMethod ch/qos/logback/classic/spi/ILoggingEvent.getMDCPropertyMap:()Ljava/util/Map;
       6: astore_3
       7: aload_1
       8: bipush        34
      10: invokevirtual #35                 // Method java/lang/StringBuilder.append:(C)Ljava/lang/StringBuilder;
      13: ldc_w         #300                // String mdc
      16: invokevirtual #137                // Method java/lang/StringBuilder.append:(Ljava/lang/String;)Ljava/lang/StringBuilder;
      19: ldc           #140                // String \":
      21: invokevirtual #137                // Method java/lang/StringBuilder.append:(Ljava/lang/String;)Ljava/lang/StringBuilder;
      24: bipush        32
      26: invokevirtual #35                 // Method java/lang/StringBuilder.append:(C)Ljava/lang/StringBuilder;
      29: bipush        123
      31: invokevirtual #35                 // Method java/lang/StringBuilder.append:(C)Ljava/lang/StringBuilder;
      34: pop
      35: aload_0
      36: aload_3
      37: invokevirtual #302                // Method isNotEmptyMap:(Ljava/util/Map;)Z
      40: ifeq          130
      43: aload_3
      44: invokeinterface #167,  1          // InterfaceMethod java/util/Map.entrySet:()Ljava/util/Set;
      49: astore        4
      51: iconst_0
      52: istore        5
      54: aload         4
      56: invokeinterface #173,  1          // InterfaceMethod java/util/Set.iterator:()Ljava/util/Iterator;
      61: astore        6
      63: aload         6
      65: invokeinterface #179,  1          // InterfaceMethod java/util/Iterator.hasNext:()Z
      70: ifeq          130
      73: aload         6
      75: invokeinterface #185,  1          // InterfaceMethod java/util/Iterator.next:()Ljava/lang/Object;
      80: checkcast     #189                // class java/util/Map$Entry
      83: astore        7
      85: iload         5
      87: ifeq          97
      90: aload_1
      91: bipush        44
      93: invokevirtual #35                 // Method java/lang/StringBuilder.append:(C)Ljava/lang/StringBuilder;
      96: pop
      97: aload_0
      98: aload_1
      99: aload_0
     100: aload         7
     102: invokeinterface #191,  1          // InterfaceMethod java/util/Map$Entry.getKey:()Ljava/lang/Object;
     107: invokevirtual #194                // Method jsonEscapedToString:(Ljava/lang/Object;)Ljava/lang/String;
     110: aload_0
     111: aload         7
     113: invokeinterface #198,  1          // InterfaceMethod java/util/Map$Entry.getValue:()Ljava/lang/Object;
     118: invokevirtual #194                // Method jsonEscapedToString:(Ljava/lang/Object;)Ljava/lang/String;
     121: invokevirtual #74                 // Method appenderMember:(Ljava/lang/StringBuilder;Ljava/lang/String;Ljava/lang/String;)V
     124: iinc          5, 1
     127: goto          63
     130: aload_1
     131: bipush        125
     133: invokevirtual #35                 // Method java/lang/StringBuilder.append:(C)Ljava/lang/StringBuilder;
     136: pop
     137: aload_1
     138: bipush        44
     140: invokevirtual #35                 // Method java/lang/StringBuilder.append:(C)Ljava/lang/StringBuilder;
     143: pop
     144: return

  boolean isNotEmptyMap(java.util.Map);
    Code:
       0: aload_1
       1: ifnonnull     6
       4: iconst_0
       5: ireturn
       6: aload_1
       7: invokeinterface #306,  1          // InterfaceMethod java/util/Map.isEmpty:()Z
      12: ifne          19
      15: iconst_1
      16: goto          20
      19: iconst_0
      20: ireturn

  public byte[] footerBytes();
    Code:
       0: getstatic     #11                 // Field EMPTY_BYTES:[B
       3: areturn

  public byte[] encode(java.lang.Object);
    Code:
       0: aload_0
       1: aload_1
       2: checkcast     #18                 // class ch/qos/logback/classic/spi/ILoggingEvent
       5: invokevirtual #307                // Method encode:(Lch/qos/logback/classic/spi/ILoggingEvent;)[B
       8: areturn

  static {};
    Code:
       0: sipush        1024
       3: putstatic     #23                 // Field DEFAULT_SIZE:I
       6: getstatic     #23                 // Field DEFAULT_SIZE:I
       9: bipush        8
      11: imul
      12: putstatic     #27                 // Field DEFAULT_SIZE_WITH_THROWABLE:I
      15: iconst_0
      16: newarray       byte
      18: putstatic     #11                 // Field EMPTY_BYTES:[B
      21: return
}
