Compiled from "PlexusSpaceModule.java"
public final class org.sonatype.guice.plexus.shim.PlexusSpaceModule implements com.google.inject.Module {
  private final org.sonatype.guice.bean.reflect.ClassSpace space;

  public org.sonatype.guice.plexus.shim.PlexusSpaceModule(org.sonatype.guice.bean.reflect.ClassSpace);
    Code:
       0: aload_0
       1: invokespecial #1                  // Method java/lang/Object."<init>":()V
       4: aload_0
       5: aload_1
       6: putfield      #2                  // Field space:Lorg/sonatype/guice/bean/reflect/ClassSpace;
       9: return

  public void configure(com.google.inject.Binder);
    Code:
       0: new           #3                  // class org/sonatype/guice/plexus/shim/PlexusSpaceModule$ParameterizedContext
       3: dup
       4: invokespecial #4                  // Method org/sonatype/guice/plexus/shim/PlexusSpaceModule$ParameterizedContext."<init>":()V
       7: astore_2
       8: aload_1
       9: ldc_w         #5                  // class org/codehaus/plexus/context/Context
      12: invokeinterface #6,  2            // InterfaceMethod com/google/inject/Binder.bind:(Ljava/lang/Class;)Lcom/google/inject/binder/AnnotatedBindingBuilder;
      17: aload_2
      18: invokeinterface #7,  2            // InterfaceMethod com/google/inject/binder/AnnotatedBindingBuilder.toInstance:(Ljava/lang/Object;)V
      23: aload_0
      24: getfield      #2                  // Field space:Lorg/sonatype/guice/bean/reflect/ClassSpace;
      27: ldc           #8                  // String org.slf4j.ILoggerFactory
      29: invokeinterface #9,  2            // InterfaceMethod org/sonatype/guice/bean/reflect/ClassSpace.deferLoadClass:(Ljava/lang/String;)Lorg/sonatype/guice/bean/reflect/DeferredClass;
      34: invokeinterface #10,  1           // InterfaceMethod org/sonatype/guice/bean/reflect/DeferredClass.asProvider:()Lorg/sonatype/guice/bean/reflect/DeferredProvider;
      39: astore_3
      40: aload_1
      41: aload_3
      42: invokeinterface #11,  2           // InterfaceMethod com/google/inject/Binder.requestInjection:(Ljava/lang/Object;)V
      47: aload_1
      48: ldc_w         #12                 // class org/sonatype/guice/plexus/config/PlexusBeanConverter
      51: invokeinterface #6,  2            // InterfaceMethod com/google/inject/Binder.bind:(Ljava/lang/Class;)Lcom/google/inject/binder/AnnotatedBindingBuilder;
      56: ldc_w         #13                 // class org/sonatype/guice/plexus/converters/PlexusXmlBeanConverter
      59: invokeinterface #14,  2           // InterfaceMethod com/google/inject/binder/AnnotatedBindingBuilder.to:(Ljava/lang/Class;)Lcom/google/inject/binder/ScopedBindingBuilder;
      64: pop
      65: aload_1
      66: ldc_w         #15                 // class org/sonatype/guice/plexus/config/PlexusBeanLocator
      69: invokeinterface #6,  2            // InterfaceMethod com/google/inject/Binder.bind:(Ljava/lang/Class;)Lcom/google/inject/binder/AnnotatedBindingBuilder;
      74: ldc_w         #16                 // class org/sonatype/guice/plexus/locators/DefaultPlexusBeanLocator
      77: invokeinterface #14,  2           // InterfaceMethod com/google/inject/binder/AnnotatedBindingBuilder.to:(Ljava/lang/Class;)Lcom/google/inject/binder/ScopedBindingBuilder;
      82: pop
      83: aload_1
      84: ldc_w         #17                 // class org/codehaus/plexus/PlexusContainer
      87: invokeinterface #6,  2            // InterfaceMethod com/google/inject/Binder.bind:(Ljava/lang/Class;)Lcom/google/inject/binder/AnnotatedBindingBuilder;
      92: ldc_w         #18                 // class org/sonatype/guice/plexus/shim/PseudoPlexusContainer
      95: invokeinterface #14,  2           // InterfaceMethod com/google/inject/binder/AnnotatedBindingBuilder.to:(Ljava/lang/Class;)Lcom/google/inject/binder/ScopedBindingBuilder;
     100: pop
     101: new           #19                 // class org/sonatype/guice/plexus/lifecycles/PlexusLifecycleManager
     104: dup
     105: aload_1
     106: ldc_w         #5                  // class org/codehaus/plexus/context/Context
     109: invokeinterface #20,  2           // InterfaceMethod com/google/inject/Binder.getProvider:(Ljava/lang/Class;)Lcom/google/inject/Provider;
     114: aload_1
     115: ldc_w         #21                 // class org/codehaus/plexus/logging/LoggerManager
     118: invokeinterface #20,  2           // InterfaceMethod com/google/inject/Binder.getProvider:(Ljava/lang/Class;)Lcom/google/inject/Provider;
     123: aload_3
     124: invokespecial #22                 // Method org/sonatype/guice/plexus/lifecycles/PlexusLifecycleManager."<init>":(Ljavax/inject/Provider;Ljavax/inject/Provider;Ljavax/inject/Provider;)V
     127: astore        4
     129: aload_1
     130: ldc_w         #23                 // class org/sonatype/guice/plexus/binders/PlexusBeanManager
     133: invokeinterface #6,  2            // InterfaceMethod com/google/inject/Binder.bind:(Ljava/lang/Class;)Lcom/google/inject/binder/AnnotatedBindingBuilder;
     138: aload         4
     140: invokeinterface #7,  2            // InterfaceMethod com/google/inject/binder/AnnotatedBindingBuilder.toInstance:(Ljava/lang/Object;)V
     145: new           #24                 // class org/sonatype/guice/plexus/binders/PlexusXmlBeanModule
     148: dup
     149: aload_0
     150: getfield      #2                  // Field space:Lorg/sonatype/guice/bean/reflect/ClassSpace;
     153: new           #25                 // class org/codehaus/plexus/context/ContextMapAdapter
     156: dup
     157: aload_2
     158: invokespecial #26                 // Method org/codehaus/plexus/context/ContextMapAdapter."<init>":(Lorg/codehaus/plexus/context/Context;)V
     161: invokespecial #27                 // Method org/sonatype/guice/plexus/binders/PlexusXmlBeanModule."<init>":(Lorg/sonatype/guice/bean/reflect/ClassSpace;Ljava/util/Map;)V
     164: astore        5
     166: aload_1
     167: new           #28                 // class org/sonatype/guice/plexus/binders/PlexusBindingModule
     170: dup
     171: aload         4
     173: iconst_1
     174: anewarray     #29                 // class org/sonatype/guice/plexus/config/PlexusBeanModule
     177: dup
     178: iconst_0
     179: aload         5
     181: aastore
     182: invokespecial #30                 // Method org/sonatype/guice/plexus/binders/PlexusBindingModule."<init>":(Lorg/sonatype/guice/plexus/binders/PlexusBeanManager;[Lorg/sonatype/guice/plexus/config/PlexusBeanModule;)V
     185: invokeinterface #31,  2           // InterfaceMethod com/google/inject/Binder.install:(Lcom/google/inject/Module;)V
     190: return
}
