Compiled from "ArrayUtil.java"
public final class org.agrona.collections.ArrayUtil {
  public static final int UNKNOWN_INDEX;

  public org.agrona.collections.ArrayUtil();
    Code:
       0: aload_0
       1: invokespecial #1                  // Method java/lang/Object."<init>":()V
       4: return

  public static <T> T[] add(T[], T);
    Code:
       0: aload_0
       1: arraylength
       2: istore_2
       3: aload_0
       4: iload_2
       5: iconst_1
       6: iadd
       7: invokestatic  #2                  // Method java/util/Arrays.copyOf:([Ljava/lang/Object;I)[Ljava/lang/Object;
      10: astore_3
      11: aload_3
      12: iload_2
      13: aload_1
      14: aastore
      15: aload_3
      16: areturn

  public static <T> T[] remove(T[], T);
    Code:
       0: aload_0
       1: arraylength
       2: istore_2
       3: iconst_m1
       4: istore_3
       5: iconst_0
       6: istore        4
       8: iload         4
      10: iload_2
      11: if_icmpge     31
      14: aload_0
      15: iload         4
      17: aaload
      18: aload_1
      19: if_acmpne     25
      22: iload         4
      24: istore_3
      25: iinc          4, 1
      28: goto          8
      31: aload_0
      32: iload_3
      33: invokestatic  #4                  // Method remove:([Ljava/lang/Object;I)[Ljava/lang/Object;
      36: areturn

  public static <T> T[] remove(T[], int);
    Code:
       0: iload_1
       1: iconst_m1
       2: if_icmpne     7
       5: aload_0
       6: areturn
       7: aload_0
       8: arraylength
       9: istore_2
      10: iload_2
      11: iconst_1
      12: isub
      13: istore_3
      14: aload_0
      15: iload_3
      16: invokestatic  #5                  // Method newArray:([Ljava/lang/Object;I)[Ljava/lang/Object;
      19: astore        4
      21: iconst_0
      22: istore        5
      24: iconst_0
      25: istore        6
      27: iload         5
      29: iload_2
      30: if_icmpge     57
      33: iload_1
      34: iload         5
      36: if_icmpeq     51
      39: aload         4
      41: iload         6
      43: iinc          6, 1
      46: aload_0
      47: iload         5
      49: aaload
      50: aastore
      51: iinc          5, 1
      54: goto          27
      57: aload         4
      59: areturn

  public static <T> T[] newArray(T[], int);
    Code:
       0: aload_0
       1: invokevirtual #6                  // Method java/lang/Object.getClass:()Ljava/lang/Class;
       4: invokevirtual #7                  // Method java/lang/Class.getComponentType:()Ljava/lang/Class;
       7: iload_1
       8: invokestatic  #8                  // Method java/lang/reflect/Array.newInstance:(Ljava/lang/Class;I)Ljava/lang/Object;
      11: checkcast     #9                  // class "[Ljava/lang/Object;"
      14: checkcast     #9                  // class "[Ljava/lang/Object;"
      17: areturn

  public static <T> T[] ensureCapacity(T[], int);
    Code:
       0: aload_0
       1: astore_2
       2: aload_0
       3: arraylength
       4: iload_1
       5: if_icmpge     14
       8: aload_0
       9: iload_1
      10: invokestatic  #2                  // Method java/util/Arrays.copyOf:([Ljava/lang/Object;I)[Ljava/lang/Object;
      13: astore_2
      14: aload_2
      15: areturn
}
