Compiled from "UnmodifiableCollectionView.java"
public class org.agrona.collections.UnmodifiableCollectionView<V, E> extends java.util.AbstractCollection<V> {
  private final org.agrona.collections.UnmodifiableCollectionView<V, E>.ReusableIterator iterator;

  private final java.util.function.Function<E, V> viewer;

  private final java.util.Collection<E> elements;

  public org.agrona.collections.UnmodifiableCollectionView(java.util.function.Function<E, V>, java.util.Collection<E>);
    Code:
       0: aload_0
       1: invokespecial #3                  // Method java/util/AbstractCollection."<init>":()V
       4: aload_0
       5: new           #4                  // class org/agrona/collections/UnmodifiableCollectionView$ReusableIterator
       8: dup
       9: aload_0
      10: aconst_null
      11: invokespecial #5                  // Method org/agrona/collections/UnmodifiableCollectionView$ReusableIterator."<init>":(Lorg/agrona/collections/UnmodifiableCollectionView;Lorg/agrona/collections/UnmodifiableCollectionView$1;)V
      14: putfield      #6                  // Field iterator:Lorg/agrona/collections/UnmodifiableCollectionView$ReusableIterator;
      17: aload_0
      18: aload_1
      19: putfield      #2                  // Field viewer:Ljava/util/function/Function;
      22: aload_0
      23: aload_2
      24: putfield      #1                  // Field elements:Ljava/util/Collection;
      27: return

  public int size();
    Code:
       0: aload_0
       1: getfield      #1                  // Field elements:Ljava/util/Collection;
       4: invokeinterface #7,  1            // InterfaceMethod java/util/Collection.size:()I
       9: ireturn

  public java.util.Iterator<V> iterator();
    Code:
       0: aload_0
       1: getfield      #6                  // Field iterator:Lorg/agrona/collections/UnmodifiableCollectionView$ReusableIterator;
       4: invokestatic  #8                  // Method org/agrona/collections/UnmodifiableCollectionView$ReusableIterator.access$100:(Lorg/agrona/collections/UnmodifiableCollectionView$ReusableIterator;)Lorg/agrona/collections/UnmodifiableCollectionView$ReusableIterator;
       7: areturn

  static java.util.function.Function access$200(org.agrona.collections.UnmodifiableCollectionView);
    Code:
       0: aload_0
       1: getfield      #2                  // Field viewer:Ljava/util/function/Function;
       4: areturn

  static java.util.Collection access$300(org.agrona.collections.UnmodifiableCollectionView);
    Code:
       0: aload_0
       1: getfield      #1                  // Field elements:Ljava/util/Collection;
       4: areturn
}
