Compiled from "HOTPGenerator.java"
public class org.cryptacular.generator.HOTPGenerator extends org.cryptacular.generator.AbstractOTPGenerator {
  public org.cryptacular.generator.HOTPGenerator();
    Code:
       0: aload_0
       1: invokespecial #1                  // Method org/cryptacular/generator/AbstractOTPGenerator."<init>":()V
       4: return

  public int generate(byte[], long);
    Code:
       0: aload_0
       1: aload_1
       2: lload_2
       3: invokevirtual #2                  // Method generateInternal:([BJ)I
       6: ireturn

  protected org.bouncycastle.crypto.Digest getDigest();
    Code:
       0: new           #3                  // class org/bouncycastle/crypto/digests/SHA1Digest
       3: dup
       4: invokespecial #4                  // Method org/bouncycastle/crypto/digests/SHA1Digest."<init>":()V
       7: areturn
}
