Compiled from "V1beta1Batch.java"
public final class io.kubernetes.client.proto.V1beta1Batch {
  private static final com.google.protobuf.Descriptors$Descriptor internal_static_k8s_io_api_batch_v1beta1_CronJob_descriptor;

  private static final com.google.protobuf.GeneratedMessageV3$FieldAccessorTable internal_static_k8s_io_api_batch_v1beta1_CronJob_fieldAccessorTable;

  private static final com.google.protobuf.Descriptors$Descriptor internal_static_k8s_io_api_batch_v1beta1_CronJobList_descriptor;

  private static final com.google.protobuf.GeneratedMessageV3$FieldAccessorTable internal_static_k8s_io_api_batch_v1beta1_CronJobList_fieldAccessorTable;

  private static final com.google.protobuf.Descriptors$Descriptor internal_static_k8s_io_api_batch_v1beta1_CronJobSpec_descriptor;

  private static final com.google.protobuf.GeneratedMessageV3$FieldAccessorTable internal_static_k8s_io_api_batch_v1beta1_CronJobSpec_fieldAccessorTable;

  private static final com.google.protobuf.Descriptors$Descriptor internal_static_k8s_io_api_batch_v1beta1_CronJobStatus_descriptor;

  private static final com.google.protobuf.GeneratedMessageV3$FieldAccessorTable internal_static_k8s_io_api_batch_v1beta1_CronJobStatus_fieldAccessorTable;

  private static final com.google.protobuf.Descriptors$Descriptor internal_static_k8s_io_api_batch_v1beta1_JobTemplate_descriptor;

  private static final com.google.protobuf.GeneratedMessageV3$FieldAccessorTable internal_static_k8s_io_api_batch_v1beta1_JobTemplate_fieldAccessorTable;

  private static final com.google.protobuf.Descriptors$Descriptor internal_static_k8s_io_api_batch_v1beta1_JobTemplateSpec_descriptor;

  private static final com.google.protobuf.GeneratedMessageV3$FieldAccessorTable internal_static_k8s_io_api_batch_v1beta1_JobTemplateSpec_fieldAccessorTable;

  private static com.google.protobuf.Descriptors$FileDescriptor descriptor;

  private io.kubernetes.client.proto.V1beta1Batch();
    Code:
       0: aload_0
       1: invokespecial #14                 // Method java/lang/Object."<init>":()V
       4: return

  public static void registerAllExtensions(com.google.protobuf.ExtensionRegistryLite);
    Code:
       0: return

  public static void registerAllExtensions(com.google.protobuf.ExtensionRegistry);
    Code:
       0: aload_0
       1: invokestatic  #15                 // Method registerAllExtensions:(Lcom/google/protobuf/ExtensionRegistryLite;)V
       4: return

  public static com.google.protobuf.Descriptors$FileDescriptor getDescriptor();
    Code:
       0: getstatic     #1                  // Field descriptor:Lcom/google/protobuf/Descriptors$FileDescriptor;
       3: areturn

  static com.google.protobuf.Descriptors$Descriptor access$000();
    Code:
       0: getstatic     #13                 // Field internal_static_k8s_io_api_batch_v1beta1_CronJob_descriptor:Lcom/google/protobuf/Descriptors$Descriptor;
       3: areturn

  static com.google.protobuf.GeneratedMessageV3$FieldAccessorTable access$100();
    Code:
       0: getstatic     #12                 // Field internal_static_k8s_io_api_batch_v1beta1_CronJob_fieldAccessorTable:Lcom/google/protobuf/GeneratedMessageV3$FieldAccessorTable;
       3: areturn

  static com.google.protobuf.Descriptors$Descriptor access$1200();
    Code:
       0: getstatic     #11                 // Field internal_static_k8s_io_api_batch_v1beta1_CronJobList_descriptor:Lcom/google/protobuf/Descriptors$Descriptor;
       3: areturn

  static com.google.protobuf.GeneratedMessageV3$FieldAccessorTable access$1300();
    Code:
       0: getstatic     #10                 // Field internal_static_k8s_io_api_batch_v1beta1_CronJobList_fieldAccessorTable:Lcom/google/protobuf/GeneratedMessageV3$FieldAccessorTable;
       3: areturn

  static com.google.protobuf.Descriptors$Descriptor access$2400();
    Code:
       0: getstatic     #9                  // Field internal_static_k8s_io_api_batch_v1beta1_CronJobSpec_descriptor:Lcom/google/protobuf/Descriptors$Descriptor;
       3: areturn

  static com.google.protobuf.GeneratedMessageV3$FieldAccessorTable access$2500();
    Code:
       0: getstatic     #8                  // Field internal_static_k8s_io_api_batch_v1beta1_CronJobSpec_fieldAccessorTable:Lcom/google/protobuf/GeneratedMessageV3$FieldAccessorTable;
       3: areturn

  static com.google.protobuf.Descriptors$Descriptor access$4000();
    Code:
       0: getstatic     #7                  // Field internal_static_k8s_io_api_batch_v1beta1_CronJobStatus_descriptor:Lcom/google/protobuf/Descriptors$Descriptor;
       3: areturn

  static com.google.protobuf.GeneratedMessageV3$FieldAccessorTable access$4100();
    Code:
       0: getstatic     #6                  // Field internal_static_k8s_io_api_batch_v1beta1_CronJobStatus_fieldAccessorTable:Lcom/google/protobuf/GeneratedMessageV3$FieldAccessorTable;
       3: areturn

  static com.google.protobuf.Descriptors$Descriptor access$5200();
    Code:
       0: getstatic     #5                  // Field internal_static_k8s_io_api_batch_v1beta1_JobTemplate_descriptor:Lcom/google/protobuf/Descriptors$Descriptor;
       3: areturn

  static com.google.protobuf.GeneratedMessageV3$FieldAccessorTable access$5300();
    Code:
       0: getstatic     #4                  // Field internal_static_k8s_io_api_batch_v1beta1_JobTemplate_fieldAccessorTable:Lcom/google/protobuf/GeneratedMessageV3$FieldAccessorTable;
       3: areturn

  static com.google.protobuf.Descriptors$Descriptor access$6300();
    Code:
       0: getstatic     #3                  // Field internal_static_k8s_io_api_batch_v1beta1_JobTemplateSpec_descriptor:Lcom/google/protobuf/Descriptors$Descriptor;
       3: areturn

  static com.google.protobuf.GeneratedMessageV3$FieldAccessorTable access$6400();
    Code:
       0: getstatic     #2                  // Field internal_static_k8s_io_api_batch_v1beta1_JobTemplateSpec_fieldAccessorTable:Lcom/google/protobuf/GeneratedMessageV3$FieldAccessorTable;
       3: areturn

  static com.google.protobuf.Descriptors$FileDescriptor access$7402(com.google.protobuf.Descriptors$FileDescriptor);
    Code:
       0: aload_0
       1: dup
       2: putstatic     #1                  // Field descriptor:Lcom/google/protobuf/Descriptors$FileDescriptor;
       5: areturn

  static {};
    Code:
       0: iconst_1
       1: anewarray     #16                 // class java/lang/String
       4: dup
       5: iconst_0
       6: ldc           #17                 // String \n(k8s.io/api/batch/v1beta1/generated.proto\u0012\u0018k8s.io.api.batch.v1beta1\u001a#k8s.io/api/batch/v1/generated.proto\u001a\"k8s.io/api/core/v1/generated.proto\u001a4k8s.io/apimachinery/pkg/apis/meta/v1/generated.proto\u001a/k8s.io/apimachinery/pkg/runtime/generated.proto\u001a6k8s.io/apimachinery/pkg/runtime/schema/generated.proto\"»\u0001\n\u0007CronJob\u0012B\n\bmetadata\u0018\u0001 \u0001(\u000b20.k8s.io.apimachinery.pkg.apis.meta.v1.ObjectMeta\u00123\n\u0004spec\u0018\u0002 \u0001(\u000b2%.k8s.io.api.batch.v1beta1.CronJobSpec\u00127\n\u0006status\u0018\u0003 \u0001(\u000b2\'.k8s.io.api.batch.v1beta1.CronJobStatus\"\u0081\u0001\n\u000bCronJobList\u0012@\n\bmetadata\u0018\u0001 \u0001(\u000b2..k8s.io.apimachinery.pkg.apis.meta.v1.ListMeta\u00120\n\u0005items\u0018\u0002 \u0003(\u000b2!.k8s.io.api.batch.v1beta1.CronJob\"ð\u0001\n\u000bCronJobSpec\u0012\u0010\n\bschedule\u0018\u0001 \u0001(\t\u0012\u001f\n\u0017startingDeadlineSeconds\u0018\u0002 \u0001(\u0003\u0012\u0019\n\u0011concurrencyPolicy\u0018\u0003 \u0001(\t\u0012\u000f\n\u0007suspend\u0018\u0004 \u0001(\b\u0012>\n\u000bjobTemplate\u0018\u0005 \u0001(\u000b2).k8s.io.api.batch.v1beta1.JobTemplateSpec\u0012\"\n\u001asuccessfulJobsHistoryLimit\u0018\u0006 \u0001(\u0005\u0012\u001e\n\u0016failedJobsHistoryLimit\u0018\u0007 \u0001(\u0005\"\u008a\u0001\n\rCronJobStatus\u00123\n\u0006active\u0018\u0001 \u0003(\u000b2#.k8s.io.api.core.v1.ObjectReference\u0012D\n\u0010lastScheduleTime\u0018\u0004 \u0001(\u000b2*.k8s.io.apimachinery.pkg.apis.meta.v1.Time\"\u008e\u0001\n\u000bJobTemplate\u0012B\n\bmetadata\u0018\u0001 \u0001(\u000b20.k8s.io.apimachinery.pkg.apis.meta.v1.ObjectMeta\u0012;\n\btemplate\u0018\u0002 \u0001(\u000b2).k8s.io.api.batch.v1beta1.JobTemplateSpec\"\u0081\u0001\n\u000fJobTemplateSpec\u0012B\n\bmetadata\u0018\u0001 \u0001(\u000b20.k8s.io.apimachinery.pkg.apis.meta.v1.ObjectMeta\u0012*\n\u0004spec\u0018\u0002 \u0001(\u000b2\u001c.k8s.io.api.batch.v1.JobSpecB3\n\u001aio.kubernetes.client.protoB\fV1beta1BatchZ\u0007v1beta1
       8: aastore
       9: astore_0
      10: new           #18                 // class io/kubernetes/client/proto/V1beta1Batch$1
      13: dup
      14: invokespecial #19                 // Method io/kubernetes/client/proto/V1beta1Batch$1."<init>":()V
      17: astore_1
      18: aload_0
      19: iconst_5
      20: anewarray     #20                 // class com/google/protobuf/Descriptors$FileDescriptor
      23: dup
      24: iconst_0
      25: invokestatic  #21                 // Method io/kubernetes/client/proto/V1Batch.getDescriptor:()Lcom/google/protobuf/Descriptors$FileDescriptor;
      28: aastore
      29: dup
      30: iconst_1
      31: invokestatic  #22                 // Method io/kubernetes/client/proto/V1.getDescriptor:()Lcom/google/protobuf/Descriptors$FileDescriptor;
      34: aastore
      35: dup
      36: iconst_2
      37: invokestatic  #23                 // Method io/kubernetes/client/proto/Meta.getDescriptor:()Lcom/google/protobuf/Descriptors$FileDescriptor;
      40: aastore
      41: dup
      42: iconst_3
      43: invokestatic  #24                 // Method io/kubernetes/client/proto/Runtime.getDescriptor:()Lcom/google/protobuf/Descriptors$FileDescriptor;
      46: aastore
      47: dup
      48: iconst_4
      49: invokestatic  #25                 // Method io/kubernetes/client/proto/RuntimeSchema.getDescriptor:()Lcom/google/protobuf/Descriptors$FileDescriptor;
      52: aastore
      53: aload_1
      54: invokestatic  #26                 // Method com/google/protobuf/Descriptors$FileDescriptor.internalBuildGeneratedFileFrom:([Ljava/lang/String;[Lcom/google/protobuf/Descriptors$FileDescriptor;Lcom/google/protobuf/Descriptors$FileDescriptor$InternalDescriptorAssigner;)V
      57: invokestatic  #27                 // Method getDescriptor:()Lcom/google/protobuf/Descriptors$FileDescriptor;
      60: invokevirtual #28                 // Method com/google/protobuf/Descriptors$FileDescriptor.getMessageTypes:()Ljava/util/List;
      63: iconst_0
      64: invokeinterface #29,  2           // InterfaceMethod java/util/List.get:(I)Ljava/lang/Object;
      69: checkcast     #30                 // class com/google/protobuf/Descriptors$Descriptor
      72: putstatic     #13                 // Field internal_static_k8s_io_api_batch_v1beta1_CronJob_descriptor:Lcom/google/protobuf/Descriptors$Descriptor;
      75: new           #31                 // class com/google/protobuf/GeneratedMessageV3$FieldAccessorTable
      78: dup
      79: getstatic     #13                 // Field internal_static_k8s_io_api_batch_v1beta1_CronJob_descriptor:Lcom/google/protobuf/Descriptors$Descriptor;
      82: iconst_3
      83: anewarray     #16                 // class java/lang/String
      86: dup
      87: iconst_0
      88: ldc           #32                 // String Metadata
      90: aastore
      91: dup
      92: iconst_1
      93: ldc           #33                 // String Spec
      95: aastore
      96: dup
      97: iconst_2
      98: ldc           #34                 // String Status
     100: aastore
     101: invokespecial #35                 // Method com/google/protobuf/GeneratedMessageV3$FieldAccessorTable."<init>":(Lcom/google/protobuf/Descriptors$Descriptor;[Ljava/lang/String;)V
     104: putstatic     #12                 // Field internal_static_k8s_io_api_batch_v1beta1_CronJob_fieldAccessorTable:Lcom/google/protobuf/GeneratedMessageV3$FieldAccessorTable;
     107: invokestatic  #27                 // Method getDescriptor:()Lcom/google/protobuf/Descriptors$FileDescriptor;
     110: invokevirtual #28                 // Method com/google/protobuf/Descriptors$FileDescriptor.getMessageTypes:()Ljava/util/List;
     113: iconst_1
     114: invokeinterface #29,  2           // InterfaceMethod java/util/List.get:(I)Ljava/lang/Object;
     119: checkcast     #30                 // class com/google/protobuf/Descriptors$Descriptor
     122: putstatic     #11                 // Field internal_static_k8s_io_api_batch_v1beta1_CronJobList_descriptor:Lcom/google/protobuf/Descriptors$Descriptor;
     125: new           #31                 // class com/google/protobuf/GeneratedMessageV3$FieldAccessorTable
     128: dup
     129: getstatic     #11                 // Field internal_static_k8s_io_api_batch_v1beta1_CronJobList_descriptor:Lcom/google/protobuf/Descriptors$Descriptor;
     132: iconst_2
     133: anewarray     #16                 // class java/lang/String
     136: dup
     137: iconst_0
     138: ldc           #32                 // String Metadata
     140: aastore
     141: dup
     142: iconst_1
     143: ldc           #36                 // String Items
     145: aastore
     146: invokespecial #35                 // Method com/google/protobuf/GeneratedMessageV3$FieldAccessorTable."<init>":(Lcom/google/protobuf/Descriptors$Descriptor;[Ljava/lang/String;)V
     149: putstatic     #10                 // Field internal_static_k8s_io_api_batch_v1beta1_CronJobList_fieldAccessorTable:Lcom/google/protobuf/GeneratedMessageV3$FieldAccessorTable;
     152: invokestatic  #27                 // Method getDescriptor:()Lcom/google/protobuf/Descriptors$FileDescriptor;
     155: invokevirtual #28                 // Method com/google/protobuf/Descriptors$FileDescriptor.getMessageTypes:()Ljava/util/List;
     158: iconst_2
     159: invokeinterface #29,  2           // InterfaceMethod java/util/List.get:(I)Ljava/lang/Object;
     164: checkcast     #30                 // class com/google/protobuf/Descriptors$Descriptor
     167: putstatic     #9                  // Field internal_static_k8s_io_api_batch_v1beta1_CronJobSpec_descriptor:Lcom/google/protobuf/Descriptors$Descriptor;
     170: new           #31                 // class com/google/protobuf/GeneratedMessageV3$FieldAccessorTable
     173: dup
     174: getstatic     #9                  // Field internal_static_k8s_io_api_batch_v1beta1_CronJobSpec_descriptor:Lcom/google/protobuf/Descriptors$Descriptor;
     177: bipush        7
     179: anewarray     #16                 // class java/lang/String
     182: dup
     183: iconst_0
     184: ldc           #37                 // String Schedule
     186: aastore
     187: dup
     188: iconst_1
     189: ldc           #38                 // String StartingDeadlineSeconds
     191: aastore
     192: dup
     193: iconst_2
     194: ldc           #39                 // String ConcurrencyPolicy
     196: aastore
     197: dup
     198: iconst_3
     199: ldc           #40                 // String Suspend
     201: aastore
     202: dup
     203: iconst_4
     204: ldc           #41                 // String JobTemplate
     206: aastore
     207: dup
     208: iconst_5
     209: ldc           #42                 // String SuccessfulJobsHistoryLimit
     211: aastore
     212: dup
     213: bipush        6
     215: ldc           #43                 // String FailedJobsHistoryLimit
     217: aastore
     218: invokespecial #35                 // Method com/google/protobuf/GeneratedMessageV3$FieldAccessorTable."<init>":(Lcom/google/protobuf/Descriptors$Descriptor;[Ljava/lang/String;)V
     221: putstatic     #8                  // Field internal_static_k8s_io_api_batch_v1beta1_CronJobSpec_fieldAccessorTable:Lcom/google/protobuf/GeneratedMessageV3$FieldAccessorTable;
     224: invokestatic  #27                 // Method getDescriptor:()Lcom/google/protobuf/Descriptors$FileDescriptor;
     227: invokevirtual #28                 // Method com/google/protobuf/Descriptors$FileDescriptor.getMessageTypes:()Ljava/util/List;
     230: iconst_3
     231: invokeinterface #29,  2           // InterfaceMethod java/util/List.get:(I)Ljava/lang/Object;
     236: checkcast     #30                 // class com/google/protobuf/Descriptors$Descriptor
     239: putstatic     #7                  // Field internal_static_k8s_io_api_batch_v1beta1_CronJobStatus_descriptor:Lcom/google/protobuf/Descriptors$Descriptor;
     242: new           #31                 // class com/google/protobuf/GeneratedMessageV3$FieldAccessorTable
     245: dup
     246: getstatic     #7                  // Field internal_static_k8s_io_api_batch_v1beta1_CronJobStatus_descriptor:Lcom/google/protobuf/Descriptors$Descriptor;
     249: iconst_2
     250: anewarray     #16                 // class java/lang/String
     253: dup
     254: iconst_0
     255: ldc           #44                 // String Active
     257: aastore
     258: dup
     259: iconst_1
     260: ldc           #45                 // String LastScheduleTime
     262: aastore
     263: invokespecial #35                 // Method com/google/protobuf/GeneratedMessageV3$FieldAccessorTable."<init>":(Lcom/google/protobuf/Descriptors$Descriptor;[Ljava/lang/String;)V
     266: putstatic     #6                  // Field internal_static_k8s_io_api_batch_v1beta1_CronJobStatus_fieldAccessorTable:Lcom/google/protobuf/GeneratedMessageV3$FieldAccessorTable;
     269: invokestatic  #27                 // Method getDescriptor:()Lcom/google/protobuf/Descriptors$FileDescriptor;
     272: invokevirtual #28                 // Method com/google/protobuf/Descriptors$FileDescriptor.getMessageTypes:()Ljava/util/List;
     275: iconst_4
     276: invokeinterface #29,  2           // InterfaceMethod java/util/List.get:(I)Ljava/lang/Object;
     281: checkcast     #30                 // class com/google/protobuf/Descriptors$Descriptor
     284: putstatic     #5                  // Field internal_static_k8s_io_api_batch_v1beta1_JobTemplate_descriptor:Lcom/google/protobuf/Descriptors$Descriptor;
     287: new           #31                 // class com/google/protobuf/GeneratedMessageV3$FieldAccessorTable
     290: dup
     291: getstatic     #5                  // Field internal_static_k8s_io_api_batch_v1beta1_JobTemplate_descriptor:Lcom/google/protobuf/Descriptors$Descriptor;
     294: iconst_2
     295: anewarray     #16                 // class java/lang/String
     298: dup
     299: iconst_0
     300: ldc           #32                 // String Metadata
     302: aastore
     303: dup
     304: iconst_1
     305: ldc           #46                 // String Template
     307: aastore
     308: invokespecial #35                 // Method com/google/protobuf/GeneratedMessageV3$FieldAccessorTable."<init>":(Lcom/google/protobuf/Descriptors$Descriptor;[Ljava/lang/String;)V
     311: putstatic     #4                  // Field internal_static_k8s_io_api_batch_v1beta1_JobTemplate_fieldAccessorTable:Lcom/google/protobuf/GeneratedMessageV3$FieldAccessorTable;
     314: invokestatic  #27                 // Method getDescriptor:()Lcom/google/protobuf/Descriptors$FileDescriptor;
     317: invokevirtual #28                 // Method com/google/protobuf/Descriptors$FileDescriptor.getMessageTypes:()Ljava/util/List;
     320: iconst_5
     321: invokeinterface #29,  2           // InterfaceMethod java/util/List.get:(I)Ljava/lang/Object;
     326: checkcast     #30                 // class com/google/protobuf/Descriptors$Descriptor
     329: putstatic     #3                  // Field internal_static_k8s_io_api_batch_v1beta1_JobTemplateSpec_descriptor:Lcom/google/protobuf/Descriptors$Descriptor;
     332: new           #31                 // class com/google/protobuf/GeneratedMessageV3$FieldAccessorTable
     335: dup
     336: getstatic     #3                  // Field internal_static_k8s_io_api_batch_v1beta1_JobTemplateSpec_descriptor:Lcom/google/protobuf/Descriptors$Descriptor;
     339: iconst_2
     340: anewarray     #16                 // class java/lang/String
     343: dup
     344: iconst_0
     345: ldc           #32                 // String Metadata
     347: aastore
     348: dup
     349: iconst_1
     350: ldc           #33                 // String Spec
     352: aastore
     353: invokespecial #35                 // Method com/google/protobuf/GeneratedMessageV3$FieldAccessorTable."<init>":(Lcom/google/protobuf/Descriptors$Descriptor;[Ljava/lang/String;)V
     356: putstatic     #2                  // Field internal_static_k8s_io_api_batch_v1beta1_JobTemplateSpec_fieldAccessorTable:Lcom/google/protobuf/GeneratedMessageV3$FieldAccessorTable;
     359: invokestatic  #21                 // Method io/kubernetes/client/proto/V1Batch.getDescriptor:()Lcom/google/protobuf/Descriptors$FileDescriptor;
     362: pop
     363: invokestatic  #22                 // Method io/kubernetes/client/proto/V1.getDescriptor:()Lcom/google/protobuf/Descriptors$FileDescriptor;
     366: pop
     367: invokestatic  #23                 // Method io/kubernetes/client/proto/Meta.getDescriptor:()Lcom/google/protobuf/Descriptors$FileDescriptor;
     370: pop
     371: invokestatic  #24                 // Method io/kubernetes/client/proto/Runtime.getDescriptor:()Lcom/google/protobuf/Descriptors$FileDescriptor;
     374: pop
     375: invokestatic  #25                 // Method io/kubernetes/client/proto/RuntimeSchema.getDescriptor:()Lcom/google/protobuf/Descriptors$FileDescriptor;
     378: pop
     379: return
}
