Compiled from "V1beta1Admission.java"
public final class io.kubernetes.client.proto.V1beta1Admission {
  private static final com.google.protobuf.Descriptors$Descriptor internal_static_k8s_io_api_admission_v1beta1_AdmissionRequest_descriptor;

  private static final com.google.protobuf.GeneratedMessageV3$FieldAccessorTable internal_static_k8s_io_api_admission_v1beta1_AdmissionRequest_fieldAccessorTable;

  private static final com.google.protobuf.Descriptors$Descriptor internal_static_k8s_io_api_admission_v1beta1_AdmissionResponse_descriptor;

  private static final com.google.protobuf.GeneratedMessageV3$FieldAccessorTable internal_static_k8s_io_api_admission_v1beta1_AdmissionResponse_fieldAccessorTable;

  private static final com.google.protobuf.Descriptors$Descriptor internal_static_k8s_io_api_admission_v1beta1_AdmissionResponse_AuditAnnotationsEntry_descriptor;

  private static final com.google.protobuf.GeneratedMessageV3$FieldAccessorTable internal_static_k8s_io_api_admission_v1beta1_AdmissionResponse_AuditAnnotationsEntry_fieldAccessorTable;

  private static final com.google.protobuf.Descriptors$Descriptor internal_static_k8s_io_api_admission_v1beta1_AdmissionReview_descriptor;

  private static final com.google.protobuf.GeneratedMessageV3$FieldAccessorTable internal_static_k8s_io_api_admission_v1beta1_AdmissionReview_fieldAccessorTable;

  private static com.google.protobuf.Descriptors$FileDescriptor descriptor;

  private io.kubernetes.client.proto.V1beta1Admission();
    Code:
       0: aload_0
       1: invokespecial #9                  // Method java/lang/Object."<init>":()V
       4: return

  public static void registerAllExtensions(com.google.protobuf.ExtensionRegistryLite);
    Code:
       0: return

  public static void registerAllExtensions(com.google.protobuf.ExtensionRegistry);
    Code:
       0: aload_0
       1: invokestatic  #10                 // Method registerAllExtensions:(Lcom/google/protobuf/ExtensionRegistryLite;)V
       4: return

  public static com.google.protobuf.Descriptors$FileDescriptor getDescriptor();
    Code:
       0: getstatic     #1                  // Field descriptor:Lcom/google/protobuf/Descriptors$FileDescriptor;
       3: areturn

  static com.google.protobuf.Descriptors$Descriptor access$000();
    Code:
       0: getstatic     #8                  // Field internal_static_k8s_io_api_admission_v1beta1_AdmissionRequest_descriptor:Lcom/google/protobuf/Descriptors$Descriptor;
       3: areturn

  static com.google.protobuf.GeneratedMessageV3$FieldAccessorTable access$100();
    Code:
       0: getstatic     #7                  // Field internal_static_k8s_io_api_admission_v1beta1_AdmissionRequest_fieldAccessorTable:Lcom/google/protobuf/GeneratedMessageV3$FieldAccessorTable;
       3: areturn

  static com.google.protobuf.Descriptors$Descriptor access$2000();
    Code:
       0: getstatic     #6                  // Field internal_static_k8s_io_api_admission_v1beta1_AdmissionResponse_descriptor:Lcom/google/protobuf/Descriptors$Descriptor;
       3: areturn

  static com.google.protobuf.GeneratedMessageV3$FieldAccessorTable access$2100();
    Code:
       0: getstatic     #5                  // Field internal_static_k8s_io_api_admission_v1beta1_AdmissionResponse_fieldAccessorTable:Lcom/google/protobuf/GeneratedMessageV3$FieldAccessorTable;
       3: areturn

  static com.google.protobuf.Descriptors$Descriptor access$2200();
    Code:
       0: getstatic     #4                  // Field internal_static_k8s_io_api_admission_v1beta1_AdmissionResponse_AuditAnnotationsEntry_descriptor:Lcom/google/protobuf/Descriptors$Descriptor;
       3: areturn

  static com.google.protobuf.Descriptors$Descriptor access$3700();
    Code:
       0: getstatic     #3                  // Field internal_static_k8s_io_api_admission_v1beta1_AdmissionReview_descriptor:Lcom/google/protobuf/Descriptors$Descriptor;
       3: areturn

  static com.google.protobuf.GeneratedMessageV3$FieldAccessorTable access$3800();
    Code:
       0: getstatic     #2                  // Field internal_static_k8s_io_api_admission_v1beta1_AdmissionReview_fieldAccessorTable:Lcom/google/protobuf/GeneratedMessageV3$FieldAccessorTable;
       3: areturn

  static com.google.protobuf.Descriptors$FileDescriptor access$4802(com.google.protobuf.Descriptors$FileDescriptor);
    Code:
       0: aload_0
       1: dup
       2: putstatic     #1                  // Field descriptor:Lcom/google/protobuf/Descriptors$FileDescriptor;
       5: areturn

  static {};
    Code:
       0: iconst_1
       1: anewarray     #11                 // class java/lang/String
       4: dup
       5: iconst_0
       6: ldc           #12                 // String \n,k8s.io/api/admission/v1beta1/generated.proto\u0012\u001ck8s.io.api.admission.v1beta1\u001a,k8s.io/api/authentication/v1/generated.proto\u001a4k8s.io/apimachinery/pkg/apis/meta/v1/generated.proto\u001a/k8s.io/apimachinery/pkg/runtime/generated.proto\u001a6k8s.io/apimachinery/pkg/runtime/schema/generated.proto\"Ç\u0003\n\u0010AdmissionRequest\u0012\u000b\n\u0003uid\u0018\u0001 \u0001(\t\u0012D\n\u0004kind\u0018\u0002 \u0001(\u000b26.k8s.io.apimachinery.pkg.apis.meta.v1.GroupVersionKind\u0012L\n\bresource\u0018\u0003 \u0001(\u000b2:.k8s.io.apimachinery.pkg.apis.meta.v1.GroupVersionResource\u0012\u0013\n\u000bsubResource\u0018\u0004 \u0001(\t\u0012\f\n\u0004name\u0018\u0005 \u0001(\t\u0012\u0011\n\tnamespace\u0018\u0006 \u0001(\t\u0012\u0011\n\toperation\u0018\u0007 \u0001(\t\u00128\n\buserInfo\u0018\b \u0001(\u000b2&.k8s.io.api.authentication.v1.UserInfo\u0012=\n\u0006object\u0018\t \u0001(\u000b2-.k8s.io.apimachinery.pkg.runtime.RawExtension\u0012@\n\toldObject\u0018\n \u0001(\u000b2-.k8s.io.apimachinery.pkg.runtime.RawExtension\u0012\u000e\n\u0006dryRun\u0018\u000b \u0001(\b\"«\u0002\n\u0011AdmissionResponse\u0012\u000b\n\u0003uid\u0018\u0001 \u0001(\t\u0012\u000f\n\u0007allowed\u0018\u0002 \u0001(\b\u0012<\n\u0006status\u0018\u0003 \u0001(\u000b2,.k8s.io.apimachinery.pkg.apis.meta.v1.Status\u0012\r\n\u0005patch\u0018\u0004 \u0001(\f\u0012\u0011\n\tpatchType\u0018\u0005 \u0001(\t\u0012_\n\u0010auditAnnotations\u0018\u0006 \u0003(\u000b2E.k8s.io.api.admission.v1beta1.AdmissionResponse.AuditAnnotationsEntry\u001a7\n\u0015AuditAnnotationsEntry\u0012\u000b\n\u0003key\u0018\u0001 \u0001(\t\u0012\r\n\u0005value\u0018\u0002 \u0001(\t:\u00028\u0001\"\u0095\u0001\n\u000fAdmissionReview\u0012?\n\u0007request\u0018\u0001 \u0001(\u000b2..k8s.io.api.admission.v1beta1.AdmissionRequest\u0012A\n\bresponse\u0018\u0002 \u0001(\u000b2/.k8s.io.api.admission.v1beta1.AdmissionResponseB7\n\u001aio.kubernetes.client.protoB\u0010V1beta1AdmissionZ\u0007v1beta1
       8: aastore
       9: astore_0
      10: new           #13                 // class io/kubernetes/client/proto/V1beta1Admission$1
      13: dup
      14: invokespecial #14                 // Method io/kubernetes/client/proto/V1beta1Admission$1."<init>":()V
      17: astore_1
      18: aload_0
      19: iconst_4
      20: anewarray     #15                 // class com/google/protobuf/Descriptors$FileDescriptor
      23: dup
      24: iconst_0
      25: invokestatic  #16                 // Method io/kubernetes/client/proto/V1Authentication.getDescriptor:()Lcom/google/protobuf/Descriptors$FileDescriptor;
      28: aastore
      29: dup
      30: iconst_1
      31: invokestatic  #17                 // Method io/kubernetes/client/proto/Meta.getDescriptor:()Lcom/google/protobuf/Descriptors$FileDescriptor;
      34: aastore
      35: dup
      36: iconst_2
      37: invokestatic  #18                 // Method io/kubernetes/client/proto/Runtime.getDescriptor:()Lcom/google/protobuf/Descriptors$FileDescriptor;
      40: aastore
      41: dup
      42: iconst_3
      43: invokestatic  #19                 // Method io/kubernetes/client/proto/RuntimeSchema.getDescriptor:()Lcom/google/protobuf/Descriptors$FileDescriptor;
      46: aastore
      47: aload_1
      48: invokestatic  #20                 // Method com/google/protobuf/Descriptors$FileDescriptor.internalBuildGeneratedFileFrom:([Ljava/lang/String;[Lcom/google/protobuf/Descriptors$FileDescriptor;Lcom/google/protobuf/Descriptors$FileDescriptor$InternalDescriptorAssigner;)V
      51: invokestatic  #21                 // Method getDescriptor:()Lcom/google/protobuf/Descriptors$FileDescriptor;
      54: invokevirtual #22                 // Method com/google/protobuf/Descriptors$FileDescriptor.getMessageTypes:()Ljava/util/List;
      57: iconst_0
      58: invokeinterface #23,  2           // InterfaceMethod java/util/List.get:(I)Ljava/lang/Object;
      63: checkcast     #24                 // class com/google/protobuf/Descriptors$Descriptor
      66: putstatic     #8                  // Field internal_static_k8s_io_api_admission_v1beta1_AdmissionRequest_descriptor:Lcom/google/protobuf/Descriptors$Descriptor;
      69: new           #25                 // class com/google/protobuf/GeneratedMessageV3$FieldAccessorTable
      72: dup
      73: getstatic     #8                  // Field internal_static_k8s_io_api_admission_v1beta1_AdmissionRequest_descriptor:Lcom/google/protobuf/Descriptors$Descriptor;
      76: bipush        11
      78: anewarray     #11                 // class java/lang/String
      81: dup
      82: iconst_0
      83: ldc           #26                 // String Uid
      85: aastore
      86: dup
      87: iconst_1
      88: ldc           #27                 // String Kind
      90: aastore
      91: dup
      92: iconst_2
      93: ldc           #28                 // String Resource
      95: aastore
      96: dup
      97: iconst_3
      98: ldc           #29                 // String SubResource
     100: aastore
     101: dup
     102: iconst_4
     103: ldc           #30                 // String Name
     105: aastore
     106: dup
     107: iconst_5
     108: ldc           #31                 // String Namespace
     110: aastore
     111: dup
     112: bipush        6
     114: ldc           #32                 // String Operation
     116: aastore
     117: dup
     118: bipush        7
     120: ldc           #33                 // String UserInfo
     122: aastore
     123: dup
     124: bipush        8
     126: ldc           #34                 // String Object
     128: aastore
     129: dup
     130: bipush        9
     132: ldc           #35                 // String OldObject
     134: aastore
     135: dup
     136: bipush        10
     138: ldc           #36                 // String DryRun
     140: aastore
     141: invokespecial #37                 // Method com/google/protobuf/GeneratedMessageV3$FieldAccessorTable."<init>":(Lcom/google/protobuf/Descriptors$Descriptor;[Ljava/lang/String;)V
     144: putstatic     #7                  // Field internal_static_k8s_io_api_admission_v1beta1_AdmissionRequest_fieldAccessorTable:Lcom/google/protobuf/GeneratedMessageV3$FieldAccessorTable;
     147: invokestatic  #21                 // Method getDescriptor:()Lcom/google/protobuf/Descriptors$FileDescriptor;
     150: invokevirtual #22                 // Method com/google/protobuf/Descriptors$FileDescriptor.getMessageTypes:()Ljava/util/List;
     153: iconst_1
     154: invokeinterface #23,  2           // InterfaceMethod java/util/List.get:(I)Ljava/lang/Object;
     159: checkcast     #24                 // class com/google/protobuf/Descriptors$Descriptor
     162: putstatic     #6                  // Field internal_static_k8s_io_api_admission_v1beta1_AdmissionResponse_descriptor:Lcom/google/protobuf/Descriptors$Descriptor;
     165: new           #25                 // class com/google/protobuf/GeneratedMessageV3$FieldAccessorTable
     168: dup
     169: getstatic     #6                  // Field internal_static_k8s_io_api_admission_v1beta1_AdmissionResponse_descriptor:Lcom/google/protobuf/Descriptors$Descriptor;
     172: bipush        6
     174: anewarray     #11                 // class java/lang/String
     177: dup
     178: iconst_0
     179: ldc           #26                 // String Uid
     181: aastore
     182: dup
     183: iconst_1
     184: ldc           #38                 // String Allowed
     186: aastore
     187: dup
     188: iconst_2
     189: ldc           #39                 // String Status
     191: aastore
     192: dup
     193: iconst_3
     194: ldc           #40                 // String Patch
     196: aastore
     197: dup
     198: iconst_4
     199: ldc           #41                 // String PatchType
     201: aastore
     202: dup
     203: iconst_5
     204: ldc           #42                 // String AuditAnnotations
     206: aastore
     207: invokespecial #37                 // Method com/google/protobuf/GeneratedMessageV3$FieldAccessorTable."<init>":(Lcom/google/protobuf/Descriptors$Descriptor;[Ljava/lang/String;)V
     210: putstatic     #5                  // Field internal_static_k8s_io_api_admission_v1beta1_AdmissionResponse_fieldAccessorTable:Lcom/google/protobuf/GeneratedMessageV3$FieldAccessorTable;
     213: getstatic     #6                  // Field internal_static_k8s_io_api_admission_v1beta1_AdmissionResponse_descriptor:Lcom/google/protobuf/Descriptors$Descriptor;
     216: invokevirtual #43                 // Method com/google/protobuf/Descriptors$Descriptor.getNestedTypes:()Ljava/util/List;
     219: iconst_0
     220: invokeinterface #23,  2           // InterfaceMethod java/util/List.get:(I)Ljava/lang/Object;
     225: checkcast     #24                 // class com/google/protobuf/Descriptors$Descriptor
     228: putstatic     #4                  // Field internal_static_k8s_io_api_admission_v1beta1_AdmissionResponse_AuditAnnotationsEntry_descriptor:Lcom/google/protobuf/Descriptors$Descriptor;
     231: new           #25                 // class com/google/protobuf/GeneratedMessageV3$FieldAccessorTable
     234: dup
     235: getstatic     #4                  // Field internal_static_k8s_io_api_admission_v1beta1_AdmissionResponse_AuditAnnotationsEntry_descriptor:Lcom/google/protobuf/Descriptors$Descriptor;
     238: iconst_2
     239: anewarray     #11                 // class java/lang/String
     242: dup
     243: iconst_0
     244: ldc           #44                 // String Key
     246: aastore
     247: dup
     248: iconst_1
     249: ldc           #45                 // String Value
     251: aastore
     252: invokespecial #37                 // Method com/google/protobuf/GeneratedMessageV3$FieldAccessorTable."<init>":(Lcom/google/protobuf/Descriptors$Descriptor;[Ljava/lang/String;)V
     255: putstatic     #46                 // Field internal_static_k8s_io_api_admission_v1beta1_AdmissionResponse_AuditAnnotationsEntry_fieldAccessorTable:Lcom/google/protobuf/GeneratedMessageV3$FieldAccessorTable;
     258: invokestatic  #21                 // Method getDescriptor:()Lcom/google/protobuf/Descriptors$FileDescriptor;
     261: invokevirtual #22                 // Method com/google/protobuf/Descriptors$FileDescriptor.getMessageTypes:()Ljava/util/List;
     264: iconst_2
     265: invokeinterface #23,  2           // InterfaceMethod java/util/List.get:(I)Ljava/lang/Object;
     270: checkcast     #24                 // class com/google/protobuf/Descriptors$Descriptor
     273: putstatic     #3                  // Field internal_static_k8s_io_api_admission_v1beta1_AdmissionReview_descriptor:Lcom/google/protobuf/Descriptors$Descriptor;
     276: new           #25                 // class com/google/protobuf/GeneratedMessageV3$FieldAccessorTable
     279: dup
     280: getstatic     #3                  // Field internal_static_k8s_io_api_admission_v1beta1_AdmissionReview_descriptor:Lcom/google/protobuf/Descriptors$Descriptor;
     283: iconst_2
     284: anewarray     #11                 // class java/lang/String
     287: dup
     288: iconst_0
     289: ldc           #47                 // String Request
     291: aastore
     292: dup
     293: iconst_1
     294: ldc           #48                 // String Response
     296: aastore
     297: invokespecial #37                 // Method com/google/protobuf/GeneratedMessageV3$FieldAccessorTable."<init>":(Lcom/google/protobuf/Descriptors$Descriptor;[Ljava/lang/String;)V
     300: putstatic     #2                  // Field internal_static_k8s_io_api_admission_v1beta1_AdmissionReview_fieldAccessorTable:Lcom/google/protobuf/GeneratedMessageV3$FieldAccessorTable;
     303: invokestatic  #16                 // Method io/kubernetes/client/proto/V1Authentication.getDescriptor:()Lcom/google/protobuf/Descriptors$FileDescriptor;
     306: pop
     307: invokestatic  #17                 // Method io/kubernetes/client/proto/Meta.getDescriptor:()Lcom/google/protobuf/Descriptors$FileDescriptor;
     310: pop
     311: invokestatic  #18                 // Method io/kubernetes/client/proto/Runtime.getDescriptor:()Lcom/google/protobuf/Descriptors$FileDescriptor;
     314: pop
     315: invokestatic  #19                 // Method io/kubernetes/client/proto/RuntimeSchema.getDescriptor:()Lcom/google/protobuf/Descriptors$FileDescriptor;
     318: pop
     319: return
}
