Compiled from "HttpTestUtils.java"
public class software.amazon.awssdk.http.HttpTestUtils {
  private software.amazon.awssdk.http.HttpTestUtils();
    Code:
       0: aload_0
       1: invokespecial #1                  // Method java/lang/Object."<init>":()V
       4: return

  public static com.github.tomakehurst.wiremock.WireMockServer createSelfSignedServer();
    Code:
       0: ldc           #2                  // class software/amazon/awssdk/http/SdkHttpClientTestSuite
       2: ldc           #3                  // String /selfSigned.jks
       4: invokevirtual #4                  // Method java/lang/Class.getResource:(Ljava/lang/String;)Ljava/net/URL;
       7: astore_0
       8: new           #5                  // class com/github/tomakehurst/wiremock/WireMockServer
      11: dup
      12: invokestatic  #6                  // Method com/github/tomakehurst/wiremock/core/WireMockConfiguration.wireMockConfig:()Lcom/github/tomakehurst/wiremock/core/WireMockConfiguration;
      15: invokevirtual #7                  // Method com/github/tomakehurst/wiremock/core/WireMockConfiguration.dynamicHttpsPort:()Lcom/github/tomakehurst/wiremock/core/WireMockConfiguration;
      18: aload_0
      19: invokevirtual #8                  // Method java/net/URL.toString:()Ljava/lang/String;
      22: invokevirtual #9                  // Method com/github/tomakehurst/wiremock/core/WireMockConfiguration.keystorePath:(Ljava/lang/String;)Lcom/github/tomakehurst/wiremock/core/WireMockConfiguration;
      25: ldc           #10                 // String changeit
      27: invokevirtual #11                 // Method com/github/tomakehurst/wiremock/core/WireMockConfiguration.keystorePassword:(Ljava/lang/String;)Lcom/github/tomakehurst/wiremock/core/WireMockConfiguration;
      30: ldc           #10                 // String changeit
      32: invokevirtual #12                 // Method com/github/tomakehurst/wiremock/core/WireMockConfiguration.keyManagerPassword:(Ljava/lang/String;)Lcom/github/tomakehurst/wiremock/core/WireMockConfiguration;
      35: ldc           #13                 // String jks
      37: invokevirtual #14                 // Method com/github/tomakehurst/wiremock/core/WireMockConfiguration.keystoreType:(Ljava/lang/String;)Lcom/github/tomakehurst/wiremock/core/WireMockConfiguration;
      40: invokespecial #15                 // Method com/github/tomakehurst/wiremock/WireMockServer."<init>":(Lcom/github/tomakehurst/wiremock/core/Options;)V
      43: areturn

  public static java.security.KeyStore getSelfSignedKeyStore() throws java.lang.Exception;
    Code:
       0: ldc           #2                  // class software/amazon/awssdk/http/SdkHttpClientTestSuite
       2: ldc           #3                  // String /selfSigned.jks
       4: invokevirtual #4                  // Method java/lang/Class.getResource:(Ljava/lang/String;)Ljava/net/URL;
       7: astore_0
       8: ldc           #13                 // String jks
      10: invokestatic  #16                 // Method java/security/KeyStore.getInstance:(Ljava/lang/String;)Ljava/security/KeyStore;
      13: astore_1
      14: aload_0
      15: invokevirtual #17                 // Method java/net/URL.openStream:()Ljava/io/InputStream;
      18: astore_2
      19: aconst_null
      20: astore_3
      21: aload_1
      22: aload_2
      23: ldc           #10                 // String changeit
      25: invokevirtual #18                 // Method java/lang/String.toCharArray:()[C
      28: invokevirtual #19                 // Method java/security/KeyStore.load:(Ljava/io/InputStream;[C)V
      31: aload_2
      32: ifnull        107
      35: aload_3
      36: ifnull        57
      39: aload_2
      40: invokevirtual #20                 // Method java/io/InputStream.close:()V
      43: goto          107
      46: astore        4
      48: aload_3
      49: aload         4
      51: invokevirtual #22                 // Method java/lang/Throwable.addSuppressed:(Ljava/lang/Throwable;)V
      54: goto          107
      57: aload_2
      58: invokevirtual #20                 // Method java/io/InputStream.close:()V
      61: goto          107
      64: astore        4
      66: aload         4
      68: astore_3
      69: aload         4
      71: athrow
      72: astore        5
      74: aload_2
      75: ifnull        104
      78: aload_3
      79: ifnull        100
      82: aload_2
      83: invokevirtual #20                 // Method java/io/InputStream.close:()V
      86: goto          104
      89: astore        6
      91: aload_3
      92: aload         6
      94: invokevirtual #22                 // Method java/lang/Throwable.addSuppressed:(Ljava/lang/Throwable;)V
      97: goto          104
     100: aload_2
     101: invokevirtual #20                 // Method java/io/InputStream.close:()V
     104: aload         5
     106: athrow
     107: aload_1
     108: areturn
    Exception table:
       from    to  target type
          39    43    46   Class java/lang/Throwable
          21    31    64   Class java/lang/Throwable
          21    31    72   any
          82    86    89   Class java/lang/Throwable
          64    74    72   any

  public static java.util.concurrent.CompletableFuture<byte[]> sendGetRequest(int, software.amazon.awssdk.http.async.SdkAsyncHttpClient);
    Code:
       0: iload_0
       1: aload_1
       2: getstatic     #23                 // Field software/amazon/awssdk/http/SdkHttpMethod.GET:Lsoftware/amazon/awssdk/http/SdkHttpMethod;
       5: invokestatic  #24                 // Method sendRequest:(ILsoftware/amazon/awssdk/http/async/SdkAsyncHttpClient;Lsoftware/amazon/awssdk/http/SdkHttpMethod;)Ljava/util/concurrent/CompletableFuture;
       8: areturn

  public static java.util.concurrent.CompletableFuture<byte[]> sendHeadRequest(int, software.amazon.awssdk.http.async.SdkAsyncHttpClient);
    Code:
       0: iload_0
       1: aload_1
       2: getstatic     #25                 // Field software/amazon/awssdk/http/SdkHttpMethod.HEAD:Lsoftware/amazon/awssdk/http/SdkHttpMethod;
       5: invokestatic  #24                 // Method sendRequest:(ILsoftware/amazon/awssdk/http/async/SdkAsyncHttpClient;Lsoftware/amazon/awssdk/http/SdkHttpMethod;)Ljava/util/concurrent/CompletableFuture;
       8: areturn

  private static java.util.concurrent.CompletableFuture<byte[]> sendRequest(int, software.amazon.awssdk.http.async.SdkAsyncHttpClient, software.amazon.awssdk.http.SdkHttpMethod);
    Code:
       0: invokestatic  #26                 // InterfaceMethod software/amazon/awssdk/http/SdkHttpFullRequest.builder:()Lsoftware/amazon/awssdk/http/SdkHttpFullRequest$Builder;
       3: aload_2
       4: invokeinterface #27,  2           // InterfaceMethod software/amazon/awssdk/http/SdkHttpFullRequest$Builder.method:(Lsoftware/amazon/awssdk/http/SdkHttpMethod;)Lsoftware/amazon/awssdk/http/SdkHttpFullRequest$Builder;
       9: ldc           #28                 // String https
      11: invokeinterface #29,  2           // InterfaceMethod software/amazon/awssdk/http/SdkHttpFullRequest$Builder.protocol:(Ljava/lang/String;)Lsoftware/amazon/awssdk/http/SdkHttpFullRequest$Builder;
      16: ldc           #30                 // String 127.0.0.1
      18: invokeinterface #31,  2           // InterfaceMethod software/amazon/awssdk/http/SdkHttpFullRequest$Builder.host:(Ljava/lang/String;)Lsoftware/amazon/awssdk/http/SdkHttpFullRequest$Builder;
      23: iload_0
      24: invokestatic  #32                 // Method java/lang/Integer.valueOf:(I)Ljava/lang/Integer;
      27: invokeinterface #33,  2           // InterfaceMethod software/amazon/awssdk/http/SdkHttpFullRequest$Builder.port:(Ljava/lang/Integer;)Lsoftware/amazon/awssdk/http/SdkHttpFullRequest$Builder;
      32: invokeinterface #34,  1           // InterfaceMethod software/amazon/awssdk/http/SdkHttpFullRequest$Builder.build:()Lsoftware/amazon/awssdk/http/SdkHttpFullRequest;
      37: astore_3
      38: aload_1
      39: aload_3
      40: invokestatic  #35                 // Method sendRequest:(Lsoftware/amazon/awssdk/http/async/SdkAsyncHttpClient;Lsoftware/amazon/awssdk/http/SdkHttpFullRequest;)Ljava/util/concurrent/CompletableFuture;
      43: areturn

  public static java.util.concurrent.CompletableFuture<byte[]> sendRequest(software.amazon.awssdk.http.async.SdkAsyncHttpClient, software.amazon.awssdk.http.SdkHttpFullRequest);
    Code:
       0: new           #36                 // class java/io/ByteArrayOutputStream
       3: dup
       4: invokespecial #37                 // Method java/io/ByteArrayOutputStream."<init>":()V
       7: astore_2
       8: new           #38                 // class java/util/concurrent/atomic/AtomicBoolean
      11: dup
      12: iconst_0
      13: invokespecial #39                 // Method java/util/concurrent/atomic/AtomicBoolean."<init>":(Z)V
      16: astore_3
      17: aload_0
      18: invokestatic  #40                 // Method software/amazon/awssdk/http/async/AsyncExecuteRequest.builder:()Lsoftware/amazon/awssdk/http/async/AsyncExecuteRequest$Builder;
      21: new           #41                 // class software/amazon/awssdk/http/HttpTestUtils$1
      24: dup
      25: aload_3
      26: aload_2
      27: invokespecial #42                 // Method software/amazon/awssdk/http/HttpTestUtils$1."<init>":(Ljava/util/concurrent/atomic/AtomicBoolean;Ljava/io/ByteArrayOutputStream;)V
      30: invokeinterface #43,  2           // InterfaceMethod software/amazon/awssdk/http/async/AsyncExecuteRequest$Builder.responseHandler:(Lsoftware/amazon/awssdk/http/async/SdkAsyncHttpResponseHandler;)Lsoftware/amazon/awssdk/http/async/AsyncExecuteRequest$Builder;
      35: aload_1
      36: invokeinterface #44,  2           // InterfaceMethod software/amazon/awssdk/http/async/AsyncExecuteRequest$Builder.request:(Lsoftware/amazon/awssdk/http/SdkHttpRequest;)Lsoftware/amazon/awssdk/http/async/AsyncExecuteRequest$Builder;
      41: new           #45                 // class software/amazon/awssdk/http/EmptyPublisher
      44: dup
      45: invokespecial #46                 // Method software/amazon/awssdk/http/EmptyPublisher."<init>":()V
      48: invokeinterface #47,  2           // InterfaceMethod software/amazon/awssdk/http/async/AsyncExecuteRequest$Builder.requestContentPublisher:(Lsoftware/amazon/awssdk/http/async/SdkHttpContentPublisher;)Lsoftware/amazon/awssdk/http/async/AsyncExecuteRequest$Builder;
      53: invokeinterface #48,  1           // InterfaceMethod software/amazon/awssdk/http/async/AsyncExecuteRequest$Builder.build:()Lsoftware/amazon/awssdk/http/async/AsyncExecuteRequest;
      58: invokeinterface #49,  2           // InterfaceMethod software/amazon/awssdk/http/async/SdkAsyncHttpClient.execute:(Lsoftware/amazon/awssdk/http/async/AsyncExecuteRequest;)Ljava/util/concurrent/CompletableFuture;
      63: aload_3
      64: aload_2
      65: invokedynamic #50,  0             // InvokeDynamic #0:apply:(Ljava/util/concurrent/atomic/AtomicBoolean;Ljava/io/ByteArrayOutputStream;)Ljava/util/function/Function;
      70: invokevirtual #51                 // Method java/util/concurrent/CompletableFuture.thenApply:(Ljava/util/function/Function;)Ljava/util/concurrent/CompletableFuture;
      73: areturn

  public static software.amazon.awssdk.http.async.SdkHttpContentPublisher createProvider(java.lang.String);
    Code:
       0: aload_0
       1: invokestatic  #52                 // Method splitStringBySize:(Ljava/lang/String;)Ljava/util/Collection;
       4: invokeinterface #53,  1           // InterfaceMethod java/util/Collection.stream:()Ljava/util/stream/Stream;
       9: invokedynamic #54,  0             // InvokeDynamic #1:apply:()Ljava/util/function/Function;
      14: invokeinterface #55,  2           // InterfaceMethod java/util/stream/Stream.map:(Ljava/util/function/Function;)Ljava/util/stream/Stream;
      19: astore_1
      20: new           #56                 // class software/amazon/awssdk/http/HttpTestUtils$2
      23: dup
      24: aload_0
      25: aload_1
      26: invokespecial #57                 // Method software/amazon/awssdk/http/HttpTestUtils$2."<init>":(Ljava/lang/String;Ljava/util/stream/Stream;)V
      29: areturn

  public static java.util.Collection<java.lang.String> splitStringBySize(java.lang.String);
    Code:
       0: aload_0
       1: invokestatic  #58                 // Method software/amazon/awssdk/utils/StringUtils.isBlank:(Ljava/lang/CharSequence;)Z
       4: ifeq          11
       7: invokestatic  #59                 // Method java/util/Collections.emptyList:()Ljava/util/List;
      10: areturn
      11: new           #60                 // class java/util/ArrayList
      14: dup
      15: invokespecial #61                 // Method java/util/ArrayList."<init>":()V
      18: astore_1
      19: iconst_0
      20: istore_2
      21: iload_2
      22: aload_0
      23: invokevirtual #62                 // Method java/lang/String.length:()I
      26: sipush        1000
      29: idiv
      30: if_icmpgt     67
      33: aload_1
      34: aload_0
      35: iload_2
      36: sipush        1000
      39: imul
      40: iload_2
      41: iconst_1
      42: iadd
      43: sipush        1000
      46: imul
      47: aload_0
      48: invokevirtual #62                 // Method java/lang/String.length:()I
      51: invokestatic  #63                 // Method java/lang/Math.min:(II)I
      54: invokevirtual #64                 // Method java/lang/String.substring:(II)Ljava/lang/String;
      57: invokevirtual #65                 // Method java/util/ArrayList.add:(Ljava/lang/Object;)Z
      60: pop
      61: iinc          2, 1
      64: goto          21
      67: aload_1
      68: areturn

  private static java.nio.ByteBuffer lambda$createProvider$1(java.lang.String);
    Code:
       0: aload_0
       1: getstatic     #66                 // Field java/nio/charset/StandardCharsets.UTF_8:Ljava/nio/charset/Charset;
       4: invokevirtual #67                 // Method java/lang/String.getBytes:(Ljava/nio/charset/Charset;)[B
       7: invokestatic  #68                 // Method java/nio/ByteBuffer.wrap:([B)Ljava/nio/ByteBuffer;
      10: areturn

  private static byte[] lambda$sendRequest$0(java.util.concurrent.atomic.AtomicBoolean, java.io.ByteArrayOutputStream, java.lang.Void);
    Code:
       0: aload_0
       1: invokevirtual #69                 // Method java/util/concurrent/atomic/AtomicBoolean.get:()Z
       4: ifeq          14
       7: aload_1
       8: invokevirtual #70                 // Method java/io/ByteArrayOutputStream.toByteArray:()[B
      11: goto          15
      14: aconst_null
      15: areturn
}
