Compiled from "RecordingResponseHandler.java"
class software.amazon.awssdk.http.RecordingResponseHandler$1 extends software.amazon.awssdk.http.async.SimpleSubscriber {
  final software.amazon.awssdk.http.RecordingResponseHandler this$0;

  software.amazon.awssdk.http.RecordingResponseHandler$1(software.amazon.awssdk.http.RecordingResponseHandler, java.util.function.Consumer);
    Code:
       0: aload_0
       1: aload_1
       2: putfield      #1                  // Field this$0:Lsoftware/amazon/awssdk/http/RecordingResponseHandler;
       5: aload_0
       6: aload_2
       7: invokespecial #2                  // Method software/amazon/awssdk/http/async/SimpleSubscriber."<init>":(Ljava/util/function/Consumer;)V
      10: return

  public void onError(java.lang.Throwable);
    Code:
       0: aload_0
       1: getfield      #1                  // Field this$0:Lsoftware/amazon/awssdk/http/RecordingResponseHandler;
       4: invokestatic  #3                  // Method software/amazon/awssdk/http/RecordingResponseHandler.access$000:(Lsoftware/amazon/awssdk/http/RecordingResponseHandler;)Ljava/util/concurrent/CompletableFuture;
       7: aload_1
       8: invokevirtual #4                  // Method java/util/concurrent/CompletableFuture.completeExceptionally:(Ljava/lang/Throwable;)Z
      11: pop
      12: return

  public void onComplete();
    Code:
       0: aload_0
       1: getfield      #1                  // Field this$0:Lsoftware/amazon/awssdk/http/RecordingResponseHandler;
       4: invokestatic  #3                  // Method software/amazon/awssdk/http/RecordingResponseHandler.access$000:(Lsoftware/amazon/awssdk/http/RecordingResponseHandler;)Ljava/util/concurrent/CompletableFuture;
       7: aconst_null
       8: invokevirtual #5                  // Method java/util/concurrent/CompletableFuture.complete:(Ljava/lang/Object;)Z
      11: pop
      12: return
}
