Compiled from "AllergyIntolerance.java"
public class org.hl7.fhir.dstu3.model.AllergyIntolerance extends org.hl7.fhir.dstu3.model.DomainResource {
  protected java.util.List<org.hl7.fhir.dstu3.model.Identifier> identifier;

  protected org.hl7.fhir.dstu3.model.Enumeration<org.hl7.fhir.dstu3.model.AllergyIntolerance$AllergyIntoleranceClinicalStatus> clinicalStatus;

  protected org.hl7.fhir.dstu3.model.Enumeration<org.hl7.fhir.dstu3.model.AllergyIntolerance$AllergyIntoleranceVerificationStatus> verificationStatus;

  protected org.hl7.fhir.dstu3.model.Enumeration<org.hl7.fhir.dstu3.model.AllergyIntolerance$AllergyIntoleranceType> type;

  protected java.util.List<org.hl7.fhir.dstu3.model.Enumeration<org.hl7.fhir.dstu3.model.AllergyIntolerance$AllergyIntoleranceCategory>> category;

  protected org.hl7.fhir.dstu3.model.Enumeration<org.hl7.fhir.dstu3.model.AllergyIntolerance$AllergyIntoleranceCriticality> criticality;

  protected org.hl7.fhir.dstu3.model.CodeableConcept code;

  protected org.hl7.fhir.dstu3.model.Reference patient;

  protected org.hl7.fhir.dstu3.model.Patient patientTarget;

  protected org.hl7.fhir.dstu3.model.Type onset;

  protected org.hl7.fhir.dstu3.model.DateTimeType assertedDate;

  protected org.hl7.fhir.dstu3.model.Reference recorder;

  protected org.hl7.fhir.dstu3.model.Resource recorderTarget;

  protected org.hl7.fhir.dstu3.model.Reference asserter;

  protected org.hl7.fhir.dstu3.model.Resource asserterTarget;

  protected org.hl7.fhir.dstu3.model.DateTimeType lastOccurrence;

  protected java.util.List<org.hl7.fhir.dstu3.model.Annotation> note;

  protected java.util.List<org.hl7.fhir.dstu3.model.AllergyIntolerance$AllergyIntoleranceReactionComponent> reaction;

  private static final long serialVersionUID;

  public static final java.lang.String SP_SEVERITY;

  public static final ca.uhn.fhir.rest.gclient.TokenClientParam SEVERITY;

  public static final java.lang.String SP_DATE;

  public static final ca.uhn.fhir.rest.gclient.DateClientParam DATE;

  public static final java.lang.String SP_IDENTIFIER;

  public static final ca.uhn.fhir.rest.gclient.TokenClientParam IDENTIFIER;

  public static final java.lang.String SP_MANIFESTATION;

  public static final ca.uhn.fhir.rest.gclient.TokenClientParam MANIFESTATION;

  public static final java.lang.String SP_RECORDER;

  public static final ca.uhn.fhir.rest.gclient.ReferenceClientParam RECORDER;

  public static final ca.uhn.fhir.model.api.Include INCLUDE_RECORDER;

  public static final java.lang.String SP_CODE;

  public static final ca.uhn.fhir.rest.gclient.TokenClientParam CODE;

  public static final java.lang.String SP_VERIFICATION_STATUS;

  public static final ca.uhn.fhir.rest.gclient.TokenClientParam VERIFICATION_STATUS;

  public static final java.lang.String SP_CRITICALITY;

  public static final ca.uhn.fhir.rest.gclient.TokenClientParam CRITICALITY;

  public static final java.lang.String SP_CLINICAL_STATUS;

  public static final ca.uhn.fhir.rest.gclient.TokenClientParam CLINICAL_STATUS;

  public static final java.lang.String SP_TYPE;

  public static final ca.uhn.fhir.rest.gclient.TokenClientParam TYPE;

  public static final java.lang.String SP_ONSET;

  public static final ca.uhn.fhir.rest.gclient.DateClientParam ONSET;

  public static final java.lang.String SP_ROUTE;

  public static final ca.uhn.fhir.rest.gclient.TokenClientParam ROUTE;

  public static final java.lang.String SP_ASSERTER;

  public static final ca.uhn.fhir.rest.gclient.ReferenceClientParam ASSERTER;

  public static final ca.uhn.fhir.model.api.Include INCLUDE_ASSERTER;

  public static final java.lang.String SP_PATIENT;

  public static final ca.uhn.fhir.rest.gclient.ReferenceClientParam PATIENT;

  public static final ca.uhn.fhir.model.api.Include INCLUDE_PATIENT;

  public static final java.lang.String SP_CATEGORY;

  public static final ca.uhn.fhir.rest.gclient.TokenClientParam CATEGORY;

  public static final java.lang.String SP_LAST_DATE;

  public static final ca.uhn.fhir.rest.gclient.DateClientParam LAST_DATE;

  public org.hl7.fhir.dstu3.model.AllergyIntolerance();
    Code:
       0: aload_0
       1: invokespecial #1                  // Method org/hl7/fhir/dstu3/model/DomainResource."<init>":()V
       4: return

  public org.hl7.fhir.dstu3.model.AllergyIntolerance(org.hl7.fhir.dstu3.model.Enumeration<org.hl7.fhir.dstu3.model.AllergyIntolerance$AllergyIntoleranceVerificationStatus>, org.hl7.fhir.dstu3.model.Reference);
    Code:
       0: aload_0
       1: invokespecial #1                  // Method org/hl7/fhir/dstu3/model/DomainResource."<init>":()V
       4: aload_0
       5: aload_1
       6: putfield      #2                  // Field verificationStatus:Lorg/hl7/fhir/dstu3/model/Enumeration;
       9: aload_0
      10: aload_2
      11: putfield      #3                  // Field patient:Lorg/hl7/fhir/dstu3/model/Reference;
      14: return

  public java.util.List<org.hl7.fhir.dstu3.model.Identifier> getIdentifier();
    Code:
       0: aload_0
       1: getfield      #4                  // Field identifier:Ljava/util/List;
       4: ifnonnull     18
       7: aload_0
       8: new           #5                  // class java/util/ArrayList
      11: dup
      12: invokespecial #6                  // Method java/util/ArrayList."<init>":()V
      15: putfield      #4                  // Field identifier:Ljava/util/List;
      18: aload_0
      19: getfield      #4                  // Field identifier:Ljava/util/List;
      22: areturn

  public org.hl7.fhir.dstu3.model.AllergyIntolerance setIdentifier(java.util.List<org.hl7.fhir.dstu3.model.Identifier>);
    Code:
       0: aload_0
       1: aload_1
       2: putfield      #4                  // Field identifier:Ljava/util/List;
       5: aload_0
       6: areturn

  public boolean hasIdentifier();
    Code:
       0: aload_0
       1: getfield      #4                  // Field identifier:Ljava/util/List;
       4: ifnonnull     9
       7: iconst_0
       8: ireturn
       9: aload_0
      10: getfield      #4                  // Field identifier:Ljava/util/List;
      13: invokeinterface #7,  1            // InterfaceMethod java/util/List.iterator:()Ljava/util/Iterator;
      18: astore_1
      19: aload_1
      20: invokeinterface #8,  1            // InterfaceMethod java/util/Iterator.hasNext:()Z
      25: ifeq          50
      28: aload_1
      29: invokeinterface #9,  1            // InterfaceMethod java/util/Iterator.next:()Ljava/lang/Object;
      34: checkcast     #10                 // class org/hl7/fhir/dstu3/model/Identifier
      37: astore_2
      38: aload_2
      39: invokevirtual #11                 // Method org/hl7/fhir/dstu3/model/Identifier.isEmpty:()Z
      42: ifne          47
      45: iconst_1
      46: ireturn
      47: goto          19
      50: iconst_0
      51: ireturn

  public org.hl7.fhir.dstu3.model.Identifier addIdentifier();
    Code:
       0: new           #10                 // class org/hl7/fhir/dstu3/model/Identifier
       3: dup
       4: invokespecial #12                 // Method org/hl7/fhir/dstu3/model/Identifier."<init>":()V
       7: astore_1
       8: aload_0
       9: getfield      #4                  // Field identifier:Ljava/util/List;
      12: ifnonnull     26
      15: aload_0
      16: new           #5                  // class java/util/ArrayList
      19: dup
      20: invokespecial #6                  // Method java/util/ArrayList."<init>":()V
      23: putfield      #4                  // Field identifier:Ljava/util/List;
      26: aload_0
      27: getfield      #4                  // Field identifier:Ljava/util/List;
      30: aload_1
      31: invokeinterface #13,  2           // InterfaceMethod java/util/List.add:(Ljava/lang/Object;)Z
      36: pop
      37: aload_1
      38: areturn

  public org.hl7.fhir.dstu3.model.AllergyIntolerance addIdentifier(org.hl7.fhir.dstu3.model.Identifier);
    Code:
       0: aload_1
       1: ifnonnull     6
       4: aload_0
       5: areturn
       6: aload_0
       7: getfield      #4                  // Field identifier:Ljava/util/List;
      10: ifnonnull     24
      13: aload_0
      14: new           #5                  // class java/util/ArrayList
      17: dup
      18: invokespecial #6                  // Method java/util/ArrayList."<init>":()V
      21: putfield      #4                  // Field identifier:Ljava/util/List;
      24: aload_0
      25: getfield      #4                  // Field identifier:Ljava/util/List;
      28: aload_1
      29: invokeinterface #13,  2           // InterfaceMethod java/util/List.add:(Ljava/lang/Object;)Z
      34: pop
      35: aload_0
      36: areturn

  public org.hl7.fhir.dstu3.model.Identifier getIdentifierFirstRep();
    Code:
       0: aload_0
       1: invokevirtual #14                 // Method getIdentifier:()Ljava/util/List;
       4: invokeinterface #15,  1           // InterfaceMethod java/util/List.isEmpty:()Z
       9: ifeq          17
      12: aload_0
      13: invokevirtual #16                 // Method addIdentifier:()Lorg/hl7/fhir/dstu3/model/Identifier;
      16: pop
      17: aload_0
      18: invokevirtual #14                 // Method getIdentifier:()Ljava/util/List;
      21: iconst_0
      22: invokeinterface #17,  2           // InterfaceMethod java/util/List.get:(I)Ljava/lang/Object;
      27: checkcast     #10                 // class org/hl7/fhir/dstu3/model/Identifier
      30: areturn

  public org.hl7.fhir.dstu3.model.Enumeration<org.hl7.fhir.dstu3.model.AllergyIntolerance$AllergyIntoleranceClinicalStatus> getClinicalStatusElement();
    Code:
       0: aload_0
       1: getfield      #18                 // Field clinicalStatus:Lorg/hl7/fhir/dstu3/model/Enumeration;
       4: ifnonnull     47
       7: invokestatic  #19                 // Method org/hl7/fhir/dstu3/model/Configuration.errorOnAutoCreate:()Z
      10: ifeq          23
      13: new           #20                 // class java/lang/Error
      16: dup
      17: ldc           #21                 // String Attempt to auto-create AllergyIntolerance.clinicalStatus
      19: invokespecial #22                 // Method java/lang/Error."<init>":(Ljava/lang/String;)V
      22: athrow
      23: invokestatic  #23                 // Method org/hl7/fhir/dstu3/model/Configuration.doAutoCreate:()Z
      26: ifeq          47
      29: aload_0
      30: new           #24                 // class org/hl7/fhir/dstu3/model/Enumeration
      33: dup
      34: new           #25                 // class org/hl7/fhir/dstu3/model/AllergyIntolerance$AllergyIntoleranceClinicalStatusEnumFactory
      37: dup
      38: invokespecial #26                 // Method org/hl7/fhir/dstu3/model/AllergyIntolerance$AllergyIntoleranceClinicalStatusEnumFactory."<init>":()V
      41: invokespecial #27                 // Method org/hl7/fhir/dstu3/model/Enumeration."<init>":(Lorg/hl7/fhir/dstu3/model/EnumFactory;)V
      44: putfield      #18                 // Field clinicalStatus:Lorg/hl7/fhir/dstu3/model/Enumeration;
      47: aload_0
      48: getfield      #18                 // Field clinicalStatus:Lorg/hl7/fhir/dstu3/model/Enumeration;
      51: areturn

  public boolean hasClinicalStatusElement();
    Code:
       0: aload_0
       1: getfield      #18                 // Field clinicalStatus:Lorg/hl7/fhir/dstu3/model/Enumeration;
       4: ifnull        21
       7: aload_0
       8: getfield      #18                 // Field clinicalStatus:Lorg/hl7/fhir/dstu3/model/Enumeration;
      11: invokevirtual #28                 // Method org/hl7/fhir/dstu3/model/Enumeration.isEmpty:()Z
      14: ifne          21
      17: iconst_1
      18: goto          22
      21: iconst_0
      22: ireturn

  public boolean hasClinicalStatus();
    Code:
       0: aload_0
       1: getfield      #18                 // Field clinicalStatus:Lorg/hl7/fhir/dstu3/model/Enumeration;
       4: ifnull        21
       7: aload_0
       8: getfield      #18                 // Field clinicalStatus:Lorg/hl7/fhir/dstu3/model/Enumeration;
      11: invokevirtual #28                 // Method org/hl7/fhir/dstu3/model/Enumeration.isEmpty:()Z
      14: ifne          21
      17: iconst_1
      18: goto          22
      21: iconst_0
      22: ireturn

  public org.hl7.fhir.dstu3.model.AllergyIntolerance setClinicalStatusElement(org.hl7.fhir.dstu3.model.Enumeration<org.hl7.fhir.dstu3.model.AllergyIntolerance$AllergyIntoleranceClinicalStatus>);
    Code:
       0: aload_0
       1: aload_1
       2: putfield      #18                 // Field clinicalStatus:Lorg/hl7/fhir/dstu3/model/Enumeration;
       5: aload_0
       6: areturn

  public org.hl7.fhir.dstu3.model.AllergyIntolerance$AllergyIntoleranceClinicalStatus getClinicalStatus();
    Code:
       0: aload_0
       1: getfield      #18                 // Field clinicalStatus:Lorg/hl7/fhir/dstu3/model/Enumeration;
       4: ifnonnull     11
       7: aconst_null
       8: goto          21
      11: aload_0
      12: getfield      #18                 // Field clinicalStatus:Lorg/hl7/fhir/dstu3/model/Enumeration;
      15: invokevirtual #29                 // Method org/hl7/fhir/dstu3/model/Enumeration.getValue:()Ljava/lang/Object;
      18: checkcast     #30                 // class org/hl7/fhir/dstu3/model/AllergyIntolerance$AllergyIntoleranceClinicalStatus
      21: areturn

  public org.hl7.fhir.dstu3.model.AllergyIntolerance setClinicalStatus(org.hl7.fhir.dstu3.model.AllergyIntolerance$AllergyIntoleranceClinicalStatus);
    Code:
       0: aload_1
       1: ifnonnull     12
       4: aload_0
       5: aconst_null
       6: putfield      #18                 // Field clinicalStatus:Lorg/hl7/fhir/dstu3/model/Enumeration;
       9: goto          46
      12: aload_0
      13: getfield      #18                 // Field clinicalStatus:Lorg/hl7/fhir/dstu3/model/Enumeration;
      16: ifnonnull     37
      19: aload_0
      20: new           #24                 // class org/hl7/fhir/dstu3/model/Enumeration
      23: dup
      24: new           #25                 // class org/hl7/fhir/dstu3/model/AllergyIntolerance$AllergyIntoleranceClinicalStatusEnumFactory
      27: dup
      28: invokespecial #26                 // Method org/hl7/fhir/dstu3/model/AllergyIntolerance$AllergyIntoleranceClinicalStatusEnumFactory."<init>":()V
      31: invokespecial #27                 // Method org/hl7/fhir/dstu3/model/Enumeration."<init>":(Lorg/hl7/fhir/dstu3/model/EnumFactory;)V
      34: putfield      #18                 // Field clinicalStatus:Lorg/hl7/fhir/dstu3/model/Enumeration;
      37: aload_0
      38: getfield      #18                 // Field clinicalStatus:Lorg/hl7/fhir/dstu3/model/Enumeration;
      41: aload_1
      42: invokevirtual #31                 // Method org/hl7/fhir/dstu3/model/Enumeration.setValue:(Ljava/lang/Object;)Lorg/hl7/fhir/dstu3/model/PrimitiveType;
      45: pop
      46: aload_0
      47: areturn

  public org.hl7.fhir.dstu3.model.Enumeration<org.hl7.fhir.dstu3.model.AllergyIntolerance$AllergyIntoleranceVerificationStatus> getVerificationStatusElement();
    Code:
       0: aload_0
       1: getfield      #2                  // Field verificationStatus:Lorg/hl7/fhir/dstu3/model/Enumeration;
       4: ifnonnull     47
       7: invokestatic  #19                 // Method org/hl7/fhir/dstu3/model/Configuration.errorOnAutoCreate:()Z
      10: ifeq          23
      13: new           #20                 // class java/lang/Error
      16: dup
      17: ldc           #32                 // String Attempt to auto-create AllergyIntolerance.verificationStatus
      19: invokespecial #22                 // Method java/lang/Error."<init>":(Ljava/lang/String;)V
      22: athrow
      23: invokestatic  #23                 // Method org/hl7/fhir/dstu3/model/Configuration.doAutoCreate:()Z
      26: ifeq          47
      29: aload_0
      30: new           #24                 // class org/hl7/fhir/dstu3/model/Enumeration
      33: dup
      34: new           #33                 // class org/hl7/fhir/dstu3/model/AllergyIntolerance$AllergyIntoleranceVerificationStatusEnumFactory
      37: dup
      38: invokespecial #34                 // Method org/hl7/fhir/dstu3/model/AllergyIntolerance$AllergyIntoleranceVerificationStatusEnumFactory."<init>":()V
      41: invokespecial #27                 // Method org/hl7/fhir/dstu3/model/Enumeration."<init>":(Lorg/hl7/fhir/dstu3/model/EnumFactory;)V
      44: putfield      #2                  // Field verificationStatus:Lorg/hl7/fhir/dstu3/model/Enumeration;
      47: aload_0
      48: getfield      #2                  // Field verificationStatus:Lorg/hl7/fhir/dstu3/model/Enumeration;
      51: areturn

  public boolean hasVerificationStatusElement();
    Code:
       0: aload_0
       1: getfield      #2                  // Field verificationStatus:Lorg/hl7/fhir/dstu3/model/Enumeration;
       4: ifnull        21
       7: aload_0
       8: getfield      #2                  // Field verificationStatus:Lorg/hl7/fhir/dstu3/model/Enumeration;
      11: invokevirtual #28                 // Method org/hl7/fhir/dstu3/model/Enumeration.isEmpty:()Z
      14: ifne          21
      17: iconst_1
      18: goto          22
      21: iconst_0
      22: ireturn

  public boolean hasVerificationStatus();
    Code:
       0: aload_0
       1: getfield      #2                  // Field verificationStatus:Lorg/hl7/fhir/dstu3/model/Enumeration;
       4: ifnull        21
       7: aload_0
       8: getfield      #2                  // Field verificationStatus:Lorg/hl7/fhir/dstu3/model/Enumeration;
      11: invokevirtual #28                 // Method org/hl7/fhir/dstu3/model/Enumeration.isEmpty:()Z
      14: ifne          21
      17: iconst_1
      18: goto          22
      21: iconst_0
      22: ireturn

  public org.hl7.fhir.dstu3.model.AllergyIntolerance setVerificationStatusElement(org.hl7.fhir.dstu3.model.Enumeration<org.hl7.fhir.dstu3.model.AllergyIntolerance$AllergyIntoleranceVerificationStatus>);
    Code:
       0: aload_0
       1: aload_1
       2: putfield      #2                  // Field verificationStatus:Lorg/hl7/fhir/dstu3/model/Enumeration;
       5: aload_0
       6: areturn

  public org.hl7.fhir.dstu3.model.AllergyIntolerance$AllergyIntoleranceVerificationStatus getVerificationStatus();
    Code:
       0: aload_0
       1: getfield      #2                  // Field verificationStatus:Lorg/hl7/fhir/dstu3/model/Enumeration;
       4: ifnonnull     11
       7: aconst_null
       8: goto          21
      11: aload_0
      12: getfield      #2                  // Field verificationStatus:Lorg/hl7/fhir/dstu3/model/Enumeration;
      15: invokevirtual #29                 // Method org/hl7/fhir/dstu3/model/Enumeration.getValue:()Ljava/lang/Object;
      18: checkcast     #35                 // class org/hl7/fhir/dstu3/model/AllergyIntolerance$AllergyIntoleranceVerificationStatus
      21: areturn

  public org.hl7.fhir.dstu3.model.AllergyIntolerance setVerificationStatus(org.hl7.fhir.dstu3.model.AllergyIntolerance$AllergyIntoleranceVerificationStatus);
    Code:
       0: aload_0
       1: getfield      #2                  // Field verificationStatus:Lorg/hl7/fhir/dstu3/model/Enumeration;
       4: ifnonnull     25
       7: aload_0
       8: new           #24                 // class org/hl7/fhir/dstu3/model/Enumeration
      11: dup
      12: new           #33                 // class org/hl7/fhir/dstu3/model/AllergyIntolerance$AllergyIntoleranceVerificationStatusEnumFactory
      15: dup
      16: invokespecial #34                 // Method org/hl7/fhir/dstu3/model/AllergyIntolerance$AllergyIntoleranceVerificationStatusEnumFactory."<init>":()V
      19: invokespecial #27                 // Method org/hl7/fhir/dstu3/model/Enumeration."<init>":(Lorg/hl7/fhir/dstu3/model/EnumFactory;)V
      22: putfield      #2                  // Field verificationStatus:Lorg/hl7/fhir/dstu3/model/Enumeration;
      25: aload_0
      26: getfield      #2                  // Field verificationStatus:Lorg/hl7/fhir/dstu3/model/Enumeration;
      29: aload_1
      30: invokevirtual #31                 // Method org/hl7/fhir/dstu3/model/Enumeration.setValue:(Ljava/lang/Object;)Lorg/hl7/fhir/dstu3/model/PrimitiveType;
      33: pop
      34: aload_0
      35: areturn

  public org.hl7.fhir.dstu3.model.Enumeration<org.hl7.fhir.dstu3.model.AllergyIntolerance$AllergyIntoleranceType> getTypeElement();
    Code:
       0: aload_0
       1: getfield      #36                 // Field type:Lorg/hl7/fhir/dstu3/model/Enumeration;
       4: ifnonnull     47
       7: invokestatic  #19                 // Method org/hl7/fhir/dstu3/model/Configuration.errorOnAutoCreate:()Z
      10: ifeq          23
      13: new           #20                 // class java/lang/Error
      16: dup
      17: ldc           #37                 // String Attempt to auto-create AllergyIntolerance.type
      19: invokespecial #22                 // Method java/lang/Error."<init>":(Ljava/lang/String;)V
      22: athrow
      23: invokestatic  #23                 // Method org/hl7/fhir/dstu3/model/Configuration.doAutoCreate:()Z
      26: ifeq          47
      29: aload_0
      30: new           #24                 // class org/hl7/fhir/dstu3/model/Enumeration
      33: dup
      34: new           #38                 // class org/hl7/fhir/dstu3/model/AllergyIntolerance$AllergyIntoleranceTypeEnumFactory
      37: dup
      38: invokespecial #39                 // Method org/hl7/fhir/dstu3/model/AllergyIntolerance$AllergyIntoleranceTypeEnumFactory."<init>":()V
      41: invokespecial #27                 // Method org/hl7/fhir/dstu3/model/Enumeration."<init>":(Lorg/hl7/fhir/dstu3/model/EnumFactory;)V
      44: putfield      #36                 // Field type:Lorg/hl7/fhir/dstu3/model/Enumeration;
      47: aload_0
      48: getfield      #36                 // Field type:Lorg/hl7/fhir/dstu3/model/Enumeration;
      51: areturn

  public boolean hasTypeElement();
    Code:
       0: aload_0
       1: getfield      #36                 // Field type:Lorg/hl7/fhir/dstu3/model/Enumeration;
       4: ifnull        21
       7: aload_0
       8: getfield      #36                 // Field type:Lorg/hl7/fhir/dstu3/model/Enumeration;
      11: invokevirtual #28                 // Method org/hl7/fhir/dstu3/model/Enumeration.isEmpty:()Z
      14: ifne          21
      17: iconst_1
      18: goto          22
      21: iconst_0
      22: ireturn

  public boolean hasType();
    Code:
       0: aload_0
       1: getfield      #36                 // Field type:Lorg/hl7/fhir/dstu3/model/Enumeration;
       4: ifnull        21
       7: aload_0
       8: getfield      #36                 // Field type:Lorg/hl7/fhir/dstu3/model/Enumeration;
      11: invokevirtual #28                 // Method org/hl7/fhir/dstu3/model/Enumeration.isEmpty:()Z
      14: ifne          21
      17: iconst_1
      18: goto          22
      21: iconst_0
      22: ireturn

  public org.hl7.fhir.dstu3.model.AllergyIntolerance setTypeElement(org.hl7.fhir.dstu3.model.Enumeration<org.hl7.fhir.dstu3.model.AllergyIntolerance$AllergyIntoleranceType>);
    Code:
       0: aload_0
       1: aload_1
       2: putfield      #36                 // Field type:Lorg/hl7/fhir/dstu3/model/Enumeration;
       5: aload_0
       6: areturn

  public org.hl7.fhir.dstu3.model.AllergyIntolerance$AllergyIntoleranceType getType();
    Code:
       0: aload_0
       1: getfield      #36                 // Field type:Lorg/hl7/fhir/dstu3/model/Enumeration;
       4: ifnonnull     11
       7: aconst_null
       8: goto          21
      11: aload_0
      12: getfield      #36                 // Field type:Lorg/hl7/fhir/dstu3/model/Enumeration;
      15: invokevirtual #29                 // Method org/hl7/fhir/dstu3/model/Enumeration.getValue:()Ljava/lang/Object;
      18: checkcast     #40                 // class org/hl7/fhir/dstu3/model/AllergyIntolerance$AllergyIntoleranceType
      21: areturn

  public org.hl7.fhir.dstu3.model.AllergyIntolerance setType(org.hl7.fhir.dstu3.model.AllergyIntolerance$AllergyIntoleranceType);
    Code:
       0: aload_1
       1: ifnonnull     12
       4: aload_0
       5: aconst_null
       6: putfield      #36                 // Field type:Lorg/hl7/fhir/dstu3/model/Enumeration;
       9: goto          46
      12: aload_0
      13: getfield      #36                 // Field type:Lorg/hl7/fhir/dstu3/model/Enumeration;
      16: ifnonnull     37
      19: aload_0
      20: new           #24                 // class org/hl7/fhir/dstu3/model/Enumeration
      23: dup
      24: new           #38                 // class org/hl7/fhir/dstu3/model/AllergyIntolerance$AllergyIntoleranceTypeEnumFactory
      27: dup
      28: invokespecial #39                 // Method org/hl7/fhir/dstu3/model/AllergyIntolerance$AllergyIntoleranceTypeEnumFactory."<init>":()V
      31: invokespecial #27                 // Method org/hl7/fhir/dstu3/model/Enumeration."<init>":(Lorg/hl7/fhir/dstu3/model/EnumFactory;)V
      34: putfield      #36                 // Field type:Lorg/hl7/fhir/dstu3/model/Enumeration;
      37: aload_0
      38: getfield      #36                 // Field type:Lorg/hl7/fhir/dstu3/model/Enumeration;
      41: aload_1
      42: invokevirtual #31                 // Method org/hl7/fhir/dstu3/model/Enumeration.setValue:(Ljava/lang/Object;)Lorg/hl7/fhir/dstu3/model/PrimitiveType;
      45: pop
      46: aload_0
      47: areturn

  public java.util.List<org.hl7.fhir.dstu3.model.Enumeration<org.hl7.fhir.dstu3.model.AllergyIntolerance$AllergyIntoleranceCategory>> getCategory();
    Code:
       0: aload_0
       1: getfield      #41                 // Field category:Ljava/util/List;
       4: ifnonnull     18
       7: aload_0
       8: new           #5                  // class java/util/ArrayList
      11: dup
      12: invokespecial #6                  // Method java/util/ArrayList."<init>":()V
      15: putfield      #41                 // Field category:Ljava/util/List;
      18: aload_0
      19: getfield      #41                 // Field category:Ljava/util/List;
      22: areturn

  public org.hl7.fhir.dstu3.model.AllergyIntolerance setCategory(java.util.List<org.hl7.fhir.dstu3.model.Enumeration<org.hl7.fhir.dstu3.model.AllergyIntolerance$AllergyIntoleranceCategory>>);
    Code:
       0: aload_0
       1: aload_1
       2: putfield      #41                 // Field category:Ljava/util/List;
       5: aload_0
       6: areturn

  public boolean hasCategory();
    Code:
       0: aload_0
       1: getfield      #41                 // Field category:Ljava/util/List;
       4: ifnonnull     9
       7: iconst_0
       8: ireturn
       9: aload_0
      10: getfield      #41                 // Field category:Ljava/util/List;
      13: invokeinterface #7,  1            // InterfaceMethod java/util/List.iterator:()Ljava/util/Iterator;
      18: astore_1
      19: aload_1
      20: invokeinterface #8,  1            // InterfaceMethod java/util/Iterator.hasNext:()Z
      25: ifeq          50
      28: aload_1
      29: invokeinterface #9,  1            // InterfaceMethod java/util/Iterator.next:()Ljava/lang/Object;
      34: checkcast     #24                 // class org/hl7/fhir/dstu3/model/Enumeration
      37: astore_2
      38: aload_2
      39: invokevirtual #28                 // Method org/hl7/fhir/dstu3/model/Enumeration.isEmpty:()Z
      42: ifne          47
      45: iconst_1
      46: ireturn
      47: goto          19
      50: iconst_0
      51: ireturn

  public org.hl7.fhir.dstu3.model.Enumeration<org.hl7.fhir.dstu3.model.AllergyIntolerance$AllergyIntoleranceCategory> addCategoryElement();
    Code:
       0: new           #24                 // class org/hl7/fhir/dstu3/model/Enumeration
       3: dup
       4: new           #42                 // class org/hl7/fhir/dstu3/model/AllergyIntolerance$AllergyIntoleranceCategoryEnumFactory
       7: dup
       8: invokespecial #43                 // Method org/hl7/fhir/dstu3/model/AllergyIntolerance$AllergyIntoleranceCategoryEnumFactory."<init>":()V
      11: invokespecial #27                 // Method org/hl7/fhir/dstu3/model/Enumeration."<init>":(Lorg/hl7/fhir/dstu3/model/EnumFactory;)V
      14: astore_1
      15: aload_0
      16: getfield      #41                 // Field category:Ljava/util/List;
      19: ifnonnull     33
      22: aload_0
      23: new           #5                  // class java/util/ArrayList
      26: dup
      27: invokespecial #6                  // Method java/util/ArrayList."<init>":()V
      30: putfield      #41                 // Field category:Ljava/util/List;
      33: aload_0
      34: getfield      #41                 // Field category:Ljava/util/List;
      37: aload_1
      38: invokeinterface #13,  2           // InterfaceMethod java/util/List.add:(Ljava/lang/Object;)Z
      43: pop
      44: aload_1
      45: areturn

  public org.hl7.fhir.dstu3.model.AllergyIntolerance addCategory(org.hl7.fhir.dstu3.model.AllergyIntolerance$AllergyIntoleranceCategory);
    Code:
       0: new           #24                 // class org/hl7/fhir/dstu3/model/Enumeration
       3: dup
       4: new           #42                 // class org/hl7/fhir/dstu3/model/AllergyIntolerance$AllergyIntoleranceCategoryEnumFactory
       7: dup
       8: invokespecial #43                 // Method org/hl7/fhir/dstu3/model/AllergyIntolerance$AllergyIntoleranceCategoryEnumFactory."<init>":()V
      11: invokespecial #27                 // Method org/hl7/fhir/dstu3/model/Enumeration."<init>":(Lorg/hl7/fhir/dstu3/model/EnumFactory;)V
      14: astore_2
      15: aload_2
      16: aload_1
      17: invokevirtual #31                 // Method org/hl7/fhir/dstu3/model/Enumeration.setValue:(Ljava/lang/Object;)Lorg/hl7/fhir/dstu3/model/PrimitiveType;
      20: pop
      21: aload_0
      22: getfield      #41                 // Field category:Ljava/util/List;
      25: ifnonnull     39
      28: aload_0
      29: new           #5                  // class java/util/ArrayList
      32: dup
      33: invokespecial #6                  // Method java/util/ArrayList."<init>":()V
      36: putfield      #41                 // Field category:Ljava/util/List;
      39: aload_0
      40: getfield      #41                 // Field category:Ljava/util/List;
      43: aload_2
      44: invokeinterface #13,  2           // InterfaceMethod java/util/List.add:(Ljava/lang/Object;)Z
      49: pop
      50: aload_0
      51: areturn

  public boolean hasCategory(org.hl7.fhir.dstu3.model.AllergyIntolerance$AllergyIntoleranceCategory);
    Code:
       0: aload_0
       1: getfield      #41                 // Field category:Ljava/util/List;
       4: ifnonnull     9
       7: iconst_0
       8: ireturn
       9: aload_0
      10: getfield      #41                 // Field category:Ljava/util/List;
      13: invokeinterface #7,  1            // InterfaceMethod java/util/List.iterator:()Ljava/util/Iterator;
      18: astore_2
      19: aload_2
      20: invokeinterface #8,  1            // InterfaceMethod java/util/Iterator.hasNext:()Z
      25: ifeq          57
      28: aload_2
      29: invokeinterface #9,  1            // InterfaceMethod java/util/Iterator.next:()Ljava/lang/Object;
      34: checkcast     #24                 // class org/hl7/fhir/dstu3/model/Enumeration
      37: astore_3
      38: aload_3
      39: invokevirtual #29                 // Method org/hl7/fhir/dstu3/model/Enumeration.getValue:()Ljava/lang/Object;
      42: checkcast     #44                 // class org/hl7/fhir/dstu3/model/AllergyIntolerance$AllergyIntoleranceCategory
      45: aload_1
      46: invokevirtual #45                 // Method org/hl7/fhir/dstu3/model/AllergyIntolerance$AllergyIntoleranceCategory.equals:(Ljava/lang/Object;)Z
      49: ifeq          54
      52: iconst_1
      53: ireturn
      54: goto          19
      57: iconst_0
      58: ireturn

  public org.hl7.fhir.dstu3.model.Enumeration<org.hl7.fhir.dstu3.model.AllergyIntolerance$AllergyIntoleranceCriticality> getCriticalityElement();
    Code:
       0: aload_0
       1: getfield      #46                 // Field criticality:Lorg/hl7/fhir/dstu3/model/Enumeration;
       4: ifnonnull     47
       7: invokestatic  #19                 // Method org/hl7/fhir/dstu3/model/Configuration.errorOnAutoCreate:()Z
      10: ifeq          23
      13: new           #20                 // class java/lang/Error
      16: dup
      17: ldc           #47                 // String Attempt to auto-create AllergyIntolerance.criticality
      19: invokespecial #22                 // Method java/lang/Error."<init>":(Ljava/lang/String;)V
      22: athrow
      23: invokestatic  #23                 // Method org/hl7/fhir/dstu3/model/Configuration.doAutoCreate:()Z
      26: ifeq          47
      29: aload_0
      30: new           #24                 // class org/hl7/fhir/dstu3/model/Enumeration
      33: dup
      34: new           #48                 // class org/hl7/fhir/dstu3/model/AllergyIntolerance$AllergyIntoleranceCriticalityEnumFactory
      37: dup
      38: invokespecial #49                 // Method org/hl7/fhir/dstu3/model/AllergyIntolerance$AllergyIntoleranceCriticalityEnumFactory."<init>":()V
      41: invokespecial #27                 // Method org/hl7/fhir/dstu3/model/Enumeration."<init>":(Lorg/hl7/fhir/dstu3/model/EnumFactory;)V
      44: putfield      #46                 // Field criticality:Lorg/hl7/fhir/dstu3/model/Enumeration;
      47: aload_0
      48: getfield      #46                 // Field criticality:Lorg/hl7/fhir/dstu3/model/Enumeration;
      51: areturn

  public boolean hasCriticalityElement();
    Code:
       0: aload_0
       1: getfield      #46                 // Field criticality:Lorg/hl7/fhir/dstu3/model/Enumeration;
       4: ifnull        21
       7: aload_0
       8: getfield      #46                 // Field criticality:Lorg/hl7/fhir/dstu3/model/Enumeration;
      11: invokevirtual #28                 // Method org/hl7/fhir/dstu3/model/Enumeration.isEmpty:()Z
      14: ifne          21
      17: iconst_1
      18: goto          22
      21: iconst_0
      22: ireturn

  public boolean hasCriticality();
    Code:
       0: aload_0
       1: getfield      #46                 // Field criticality:Lorg/hl7/fhir/dstu3/model/Enumeration;
       4: ifnull        21
       7: aload_0
       8: getfield      #46                 // Field criticality:Lorg/hl7/fhir/dstu3/model/Enumeration;
      11: invokevirtual #28                 // Method org/hl7/fhir/dstu3/model/Enumeration.isEmpty:()Z
      14: ifne          21
      17: iconst_1
      18: goto          22
      21: iconst_0
      22: ireturn

  public org.hl7.fhir.dstu3.model.AllergyIntolerance setCriticalityElement(org.hl7.fhir.dstu3.model.Enumeration<org.hl7.fhir.dstu3.model.AllergyIntolerance$AllergyIntoleranceCriticality>);
    Code:
       0: aload_0
       1: aload_1
       2: putfield      #46                 // Field criticality:Lorg/hl7/fhir/dstu3/model/Enumeration;
       5: aload_0
       6: areturn

  public org.hl7.fhir.dstu3.model.AllergyIntolerance$AllergyIntoleranceCriticality getCriticality();
    Code:
       0: aload_0
       1: getfield      #46                 // Field criticality:Lorg/hl7/fhir/dstu3/model/Enumeration;
       4: ifnonnull     11
       7: aconst_null
       8: goto          21
      11: aload_0
      12: getfield      #46                 // Field criticality:Lorg/hl7/fhir/dstu3/model/Enumeration;
      15: invokevirtual #29                 // Method org/hl7/fhir/dstu3/model/Enumeration.getValue:()Ljava/lang/Object;
      18: checkcast     #50                 // class org/hl7/fhir/dstu3/model/AllergyIntolerance$AllergyIntoleranceCriticality
      21: areturn

  public org.hl7.fhir.dstu3.model.AllergyIntolerance setCriticality(org.hl7.fhir.dstu3.model.AllergyIntolerance$AllergyIntoleranceCriticality);
    Code:
       0: aload_1
       1: ifnonnull     12
       4: aload_0
       5: aconst_null
       6: putfield      #46                 // Field criticality:Lorg/hl7/fhir/dstu3/model/Enumeration;
       9: goto          46
      12: aload_0
      13: getfield      #46                 // Field criticality:Lorg/hl7/fhir/dstu3/model/Enumeration;
      16: ifnonnull     37
      19: aload_0
      20: new           #24                 // class org/hl7/fhir/dstu3/model/Enumeration
      23: dup
      24: new           #48                 // class org/hl7/fhir/dstu3/model/AllergyIntolerance$AllergyIntoleranceCriticalityEnumFactory
      27: dup
      28: invokespecial #49                 // Method org/hl7/fhir/dstu3/model/AllergyIntolerance$AllergyIntoleranceCriticalityEnumFactory."<init>":()V
      31: invokespecial #27                 // Method org/hl7/fhir/dstu3/model/Enumeration."<init>":(Lorg/hl7/fhir/dstu3/model/EnumFactory;)V
      34: putfield      #46                 // Field criticality:Lorg/hl7/fhir/dstu3/model/Enumeration;
      37: aload_0
      38: getfield      #46                 // Field criticality:Lorg/hl7/fhir/dstu3/model/Enumeration;
      41: aload_1
      42: invokevirtual #31                 // Method org/hl7/fhir/dstu3/model/Enumeration.setValue:(Ljava/lang/Object;)Lorg/hl7/fhir/dstu3/model/PrimitiveType;
      45: pop
      46: aload_0
      47: areturn

  public org.hl7.fhir.dstu3.model.CodeableConcept getCode();
    Code:
       0: aload_0
       1: getfield      #51                 // Field code:Lorg/hl7/fhir/dstu3/model/CodeableConcept;
       4: ifnonnull     40
       7: invokestatic  #19                 // Method org/hl7/fhir/dstu3/model/Configuration.errorOnAutoCreate:()Z
      10: ifeq          23
      13: new           #20                 // class java/lang/Error
      16: dup
      17: ldc           #52                 // String Attempt to auto-create AllergyIntolerance.code
      19: invokespecial #22                 // Method java/lang/Error."<init>":(Ljava/lang/String;)V
      22: athrow
      23: invokestatic  #23                 // Method org/hl7/fhir/dstu3/model/Configuration.doAutoCreate:()Z
      26: ifeq          40
      29: aload_0
      30: new           #53                 // class org/hl7/fhir/dstu3/model/CodeableConcept
      33: dup
      34: invokespecial #54                 // Method org/hl7/fhir/dstu3/model/CodeableConcept."<init>":()V
      37: putfield      #51                 // Field code:Lorg/hl7/fhir/dstu3/model/CodeableConcept;
      40: aload_0
      41: getfield      #51                 // Field code:Lorg/hl7/fhir/dstu3/model/CodeableConcept;
      44: areturn

  public boolean hasCode();
    Code:
       0: aload_0
       1: getfield      #51                 // Field code:Lorg/hl7/fhir/dstu3/model/CodeableConcept;
       4: ifnull        21
       7: aload_0
       8: getfield      #51                 // Field code:Lorg/hl7/fhir/dstu3/model/CodeableConcept;
      11: invokevirtual #55                 // Method org/hl7/fhir/dstu3/model/CodeableConcept.isEmpty:()Z
      14: ifne          21
      17: iconst_1
      18: goto          22
      21: iconst_0
      22: ireturn

  public org.hl7.fhir.dstu3.model.AllergyIntolerance setCode(org.hl7.fhir.dstu3.model.CodeableConcept);
    Code:
       0: aload_0
       1: aload_1
       2: putfield      #51                 // Field code:Lorg/hl7/fhir/dstu3/model/CodeableConcept;
       5: aload_0
       6: areturn

  public org.hl7.fhir.dstu3.model.Reference getPatient();
    Code:
       0: aload_0
       1: getfield      #3                  // Field patient:Lorg/hl7/fhir/dstu3/model/Reference;
       4: ifnonnull     40
       7: invokestatic  #19                 // Method org/hl7/fhir/dstu3/model/Configuration.errorOnAutoCreate:()Z
      10: ifeq          23
      13: new           #20                 // class java/lang/Error
      16: dup
      17: ldc           #56                 // String Attempt to auto-create AllergyIntolerance.patient
      19: invokespecial #22                 // Method java/lang/Error."<init>":(Ljava/lang/String;)V
      22: athrow
      23: invokestatic  #23                 // Method org/hl7/fhir/dstu3/model/Configuration.doAutoCreate:()Z
      26: ifeq          40
      29: aload_0
      30: new           #57                 // class org/hl7/fhir/dstu3/model/Reference
      33: dup
      34: invokespecial #58                 // Method org/hl7/fhir/dstu3/model/Reference."<init>":()V
      37: putfield      #3                  // Field patient:Lorg/hl7/fhir/dstu3/model/Reference;
      40: aload_0
      41: getfield      #3                  // Field patient:Lorg/hl7/fhir/dstu3/model/Reference;
      44: areturn

  public boolean hasPatient();
    Code:
       0: aload_0
       1: getfield      #3                  // Field patient:Lorg/hl7/fhir/dstu3/model/Reference;
       4: ifnull        21
       7: aload_0
       8: getfield      #3                  // Field patient:Lorg/hl7/fhir/dstu3/model/Reference;
      11: invokevirtual #59                 // Method org/hl7/fhir/dstu3/model/Reference.isEmpty:()Z
      14: ifne          21
      17: iconst_1
      18: goto          22
      21: iconst_0
      22: ireturn

  public org.hl7.fhir.dstu3.model.AllergyIntolerance setPatient(org.hl7.fhir.dstu3.model.Reference);
    Code:
       0: aload_0
       1: aload_1
       2: putfield      #3                  // Field patient:Lorg/hl7/fhir/dstu3/model/Reference;
       5: aload_0
       6: areturn

  public org.hl7.fhir.dstu3.model.Patient getPatientTarget();
    Code:
       0: aload_0
       1: getfield      #60                 // Field patientTarget:Lorg/hl7/fhir/dstu3/model/Patient;
       4: ifnonnull     40
       7: invokestatic  #19                 // Method org/hl7/fhir/dstu3/model/Configuration.errorOnAutoCreate:()Z
      10: ifeq          23
      13: new           #20                 // class java/lang/Error
      16: dup
      17: ldc           #56                 // String Attempt to auto-create AllergyIntolerance.patient
      19: invokespecial #22                 // Method java/lang/Error."<init>":(Ljava/lang/String;)V
      22: athrow
      23: invokestatic  #23                 // Method org/hl7/fhir/dstu3/model/Configuration.doAutoCreate:()Z
      26: ifeq          40
      29: aload_0
      30: new           #61                 // class org/hl7/fhir/dstu3/model/Patient
      33: dup
      34: invokespecial #62                 // Method org/hl7/fhir/dstu3/model/Patient."<init>":()V
      37: putfield      #60                 // Field patientTarget:Lorg/hl7/fhir/dstu3/model/Patient;
      40: aload_0
      41: getfield      #60                 // Field patientTarget:Lorg/hl7/fhir/dstu3/model/Patient;
      44: areturn

  public org.hl7.fhir.dstu3.model.AllergyIntolerance setPatientTarget(org.hl7.fhir.dstu3.model.Patient);
    Code:
       0: aload_0
       1: aload_1
       2: putfield      #60                 // Field patientTarget:Lorg/hl7/fhir/dstu3/model/Patient;
       5: aload_0
       6: areturn

  public org.hl7.fhir.dstu3.model.Type getOnset();
    Code:
       0: aload_0
       1: getfield      #63                 // Field onset:Lorg/hl7/fhir/dstu3/model/Type;
       4: areturn

  public org.hl7.fhir.dstu3.model.DateTimeType getOnsetDateTimeType() throws org.hl7.fhir.exceptions.FHIRException;
    Code:
       0: aload_0
       1: getfield      #63                 // Field onset:Lorg/hl7/fhir/dstu3/model/Type;
       4: ifnonnull     9
       7: aconst_null
       8: areturn
       9: aload_0
      10: getfield      #63                 // Field onset:Lorg/hl7/fhir/dstu3/model/Type;
      13: instanceof    #64                 // class org/hl7/fhir/dstu3/model/DateTimeType
      16: ifne          60
      19: new           #65                 // class org/hl7/fhir/exceptions/FHIRException
      22: dup
      23: new           #66                 // class java/lang/StringBuilder
      26: dup
      27: invokespecial #67                 // Method java/lang/StringBuilder."<init>":()V
      30: ldc           #68                 // String Type mismatch: the type DateTimeType was expected, but
      32: invokevirtual #69                 // Method java/lang/StringBuilder.append:(Ljava/lang/String;)Ljava/lang/StringBuilder;
      35: aload_0
      36: getfield      #63                 // Field onset:Lorg/hl7/fhir/dstu3/model/Type;
      39: invokevirtual #70                 // Method java/lang/Object.getClass:()Ljava/lang/Class;
      42: invokevirtual #71                 // Method java/lang/Class.getName:()Ljava/lang/String;
      45: invokevirtual #69                 // Method java/lang/StringBuilder.append:(Ljava/lang/String;)Ljava/lang/StringBuilder;
      48: ldc           #72                 // String  was encountered
      50: invokevirtual #69                 // Method java/lang/StringBuilder.append:(Ljava/lang/String;)Ljava/lang/StringBuilder;
      53: invokevirtual #73                 // Method java/lang/StringBuilder.toString:()Ljava/lang/String;
      56: invokespecial #74                 // Method org/hl7/fhir/exceptions/FHIRException."<init>":(Ljava/lang/String;)V
      59: athrow
      60: aload_0
      61: getfield      #63                 // Field onset:Lorg/hl7/fhir/dstu3/model/Type;
      64: checkcast     #64                 // class org/hl7/fhir/dstu3/model/DateTimeType
      67: areturn

  public boolean hasOnsetDateTimeType();
    Code:
       0: aload_0
       1: ifnull        18
       4: aload_0
       5: getfield      #63                 // Field onset:Lorg/hl7/fhir/dstu3/model/Type;
       8: instanceof    #64                 // class org/hl7/fhir/dstu3/model/DateTimeType
      11: ifeq          18
      14: iconst_1
      15: goto          19
      18: iconst_0
      19: ireturn

  public org.hl7.fhir.dstu3.model.Age getOnsetAge() throws org.hl7.fhir.exceptions.FHIRException;
    Code:
       0: aload_0
       1: getfield      #63                 // Field onset:Lorg/hl7/fhir/dstu3/model/Type;
       4: ifnonnull     9
       7: aconst_null
       8: areturn
       9: aload_0
      10: getfield      #63                 // Field onset:Lorg/hl7/fhir/dstu3/model/Type;
      13: instanceof    #75                 // class org/hl7/fhir/dstu3/model/Age
      16: ifne          60
      19: new           #65                 // class org/hl7/fhir/exceptions/FHIRException
      22: dup
      23: new           #66                 // class java/lang/StringBuilder
      26: dup
      27: invokespecial #67                 // Method java/lang/StringBuilder."<init>":()V
      30: ldc           #76                 // String Type mismatch: the type Age was expected, but
      32: invokevirtual #69                 // Method java/lang/StringBuilder.append:(Ljava/lang/String;)Ljava/lang/StringBuilder;
      35: aload_0
      36: getfield      #63                 // Field onset:Lorg/hl7/fhir/dstu3/model/Type;
      39: invokevirtual #70                 // Method java/lang/Object.getClass:()Ljava/lang/Class;
      42: invokevirtual #71                 // Method java/lang/Class.getName:()Ljava/lang/String;
      45: invokevirtual #69                 // Method java/lang/StringBuilder.append:(Ljava/lang/String;)Ljava/lang/StringBuilder;
      48: ldc           #72                 // String  was encountered
      50: invokevirtual #69                 // Method java/lang/StringBuilder.append:(Ljava/lang/String;)Ljava/lang/StringBuilder;
      53: invokevirtual #73                 // Method java/lang/StringBuilder.toString:()Ljava/lang/String;
      56: invokespecial #74                 // Method org/hl7/fhir/exceptions/FHIRException."<init>":(Ljava/lang/String;)V
      59: athrow
      60: aload_0
      61: getfield      #63                 // Field onset:Lorg/hl7/fhir/dstu3/model/Type;
      64: checkcast     #75                 // class org/hl7/fhir/dstu3/model/Age
      67: areturn

  public boolean hasOnsetAge();
    Code:
       0: aload_0
       1: ifnull        18
       4: aload_0
       5: getfield      #63                 // Field onset:Lorg/hl7/fhir/dstu3/model/Type;
       8: instanceof    #75                 // class org/hl7/fhir/dstu3/model/Age
      11: ifeq          18
      14: iconst_1
      15: goto          19
      18: iconst_0
      19: ireturn

  public org.hl7.fhir.dstu3.model.Period getOnsetPeriod() throws org.hl7.fhir.exceptions.FHIRException;
    Code:
       0: aload_0
       1: getfield      #63                 // Field onset:Lorg/hl7/fhir/dstu3/model/Type;
       4: ifnonnull     9
       7: aconst_null
       8: areturn
       9: aload_0
      10: getfield      #63                 // Field onset:Lorg/hl7/fhir/dstu3/model/Type;
      13: instanceof    #77                 // class org/hl7/fhir/dstu3/model/Period
      16: ifne          60
      19: new           #65                 // class org/hl7/fhir/exceptions/FHIRException
      22: dup
      23: new           #66                 // class java/lang/StringBuilder
      26: dup
      27: invokespecial #67                 // Method java/lang/StringBuilder."<init>":()V
      30: ldc           #78                 // String Type mismatch: the type Period was expected, but
      32: invokevirtual #69                 // Method java/lang/StringBuilder.append:(Ljava/lang/String;)Ljava/lang/StringBuilder;
      35: aload_0
      36: getfield      #63                 // Field onset:Lorg/hl7/fhir/dstu3/model/Type;
      39: invokevirtual #70                 // Method java/lang/Object.getClass:()Ljava/lang/Class;
      42: invokevirtual #71                 // Method java/lang/Class.getName:()Ljava/lang/String;
      45: invokevirtual #69                 // Method java/lang/StringBuilder.append:(Ljava/lang/String;)Ljava/lang/StringBuilder;
      48: ldc           #72                 // String  was encountered
      50: invokevirtual #69                 // Method java/lang/StringBuilder.append:(Ljava/lang/String;)Ljava/lang/StringBuilder;
      53: invokevirtual #73                 // Method java/lang/StringBuilder.toString:()Ljava/lang/String;
      56: invokespecial #74                 // Method org/hl7/fhir/exceptions/FHIRException."<init>":(Ljava/lang/String;)V
      59: athrow
      60: aload_0
      61: getfield      #63                 // Field onset:Lorg/hl7/fhir/dstu3/model/Type;
      64: checkcast     #77                 // class org/hl7/fhir/dstu3/model/Period
      67: areturn

  public boolean hasOnsetPeriod();
    Code:
       0: aload_0
       1: ifnull        18
       4: aload_0
       5: getfield      #63                 // Field onset:Lorg/hl7/fhir/dstu3/model/Type;
       8: instanceof    #77                 // class org/hl7/fhir/dstu3/model/Period
      11: ifeq          18
      14: iconst_1
      15: goto          19
      18: iconst_0
      19: ireturn

  public org.hl7.fhir.dstu3.model.Range getOnsetRange() throws org.hl7.fhir.exceptions.FHIRException;
    Code:
       0: aload_0
       1: getfield      #63                 // Field onset:Lorg/hl7/fhir/dstu3/model/Type;
       4: ifnonnull     9
       7: aconst_null
       8: areturn
       9: aload_0
      10: getfield      #63                 // Field onset:Lorg/hl7/fhir/dstu3/model/Type;
      13: instanceof    #79                 // class org/hl7/fhir/dstu3/model/Range
      16: ifne          60
      19: new           #65                 // class org/hl7/fhir/exceptions/FHIRException
      22: dup
      23: new           #66                 // class java/lang/StringBuilder
      26: dup
      27: invokespecial #67                 // Method java/lang/StringBuilder."<init>":()V
      30: ldc           #80                 // String Type mismatch: the type Range was expected, but
      32: invokevirtual #69                 // Method java/lang/StringBuilder.append:(Ljava/lang/String;)Ljava/lang/StringBuilder;
      35: aload_0
      36: getfield      #63                 // Field onset:Lorg/hl7/fhir/dstu3/model/Type;
      39: invokevirtual #70                 // Method java/lang/Object.getClass:()Ljava/lang/Class;
      42: invokevirtual #71                 // Method java/lang/Class.getName:()Ljava/lang/String;
      45: invokevirtual #69                 // Method java/lang/StringBuilder.append:(Ljava/lang/String;)Ljava/lang/StringBuilder;
      48: ldc           #72                 // String  was encountered
      50: invokevirtual #69                 // Method java/lang/StringBuilder.append:(Ljava/lang/String;)Ljava/lang/StringBuilder;
      53: invokevirtual #73                 // Method java/lang/StringBuilder.toString:()Ljava/lang/String;
      56: invokespecial #74                 // Method org/hl7/fhir/exceptions/FHIRException."<init>":(Ljava/lang/String;)V
      59: athrow
      60: aload_0
      61: getfield      #63                 // Field onset:Lorg/hl7/fhir/dstu3/model/Type;
      64: checkcast     #79                 // class org/hl7/fhir/dstu3/model/Range
      67: areturn

  public boolean hasOnsetRange();
    Code:
       0: aload_0
       1: ifnull        18
       4: aload_0
       5: getfield      #63                 // Field onset:Lorg/hl7/fhir/dstu3/model/Type;
       8: instanceof    #79                 // class org/hl7/fhir/dstu3/model/Range
      11: ifeq          18
      14: iconst_1
      15: goto          19
      18: iconst_0
      19: ireturn

  public org.hl7.fhir.dstu3.model.StringType getOnsetStringType() throws org.hl7.fhir.exceptions.FHIRException;
    Code:
       0: aload_0
       1: getfield      #63                 // Field onset:Lorg/hl7/fhir/dstu3/model/Type;
       4: ifnonnull     9
       7: aconst_null
       8: areturn
       9: aload_0
      10: getfield      #63                 // Field onset:Lorg/hl7/fhir/dstu3/model/Type;
      13: instanceof    #81                 // class org/hl7/fhir/dstu3/model/StringType
      16: ifne          60
      19: new           #65                 // class org/hl7/fhir/exceptions/FHIRException
      22: dup
      23: new           #66                 // class java/lang/StringBuilder
      26: dup
      27: invokespecial #67                 // Method java/lang/StringBuilder."<init>":()V
      30: ldc           #82                 // String Type mismatch: the type StringType was expected, but
      32: invokevirtual #69                 // Method java/lang/StringBuilder.append:(Ljava/lang/String;)Ljava/lang/StringBuilder;
      35: aload_0
      36: getfield      #63                 // Field onset:Lorg/hl7/fhir/dstu3/model/Type;
      39: invokevirtual #70                 // Method java/lang/Object.getClass:()Ljava/lang/Class;
      42: invokevirtual #71                 // Method java/lang/Class.getName:()Ljava/lang/String;
      45: invokevirtual #69                 // Method java/lang/StringBuilder.append:(Ljava/lang/String;)Ljava/lang/StringBuilder;
      48: ldc           #72                 // String  was encountered
      50: invokevirtual #69                 // Method java/lang/StringBuilder.append:(Ljava/lang/String;)Ljava/lang/StringBuilder;
      53: invokevirtual #73                 // Method java/lang/StringBuilder.toString:()Ljava/lang/String;
      56: invokespecial #74                 // Method org/hl7/fhir/exceptions/FHIRException."<init>":(Ljava/lang/String;)V
      59: athrow
      60: aload_0
      61: getfield      #63                 // Field onset:Lorg/hl7/fhir/dstu3/model/Type;
      64: checkcast     #81                 // class org/hl7/fhir/dstu3/model/StringType
      67: areturn

  public boolean hasOnsetStringType();
    Code:
       0: aload_0
       1: ifnull        18
       4: aload_0
       5: getfield      #63                 // Field onset:Lorg/hl7/fhir/dstu3/model/Type;
       8: instanceof    #81                 // class org/hl7/fhir/dstu3/model/StringType
      11: ifeq          18
      14: iconst_1
      15: goto          19
      18: iconst_0
      19: ireturn

  public boolean hasOnset();
    Code:
       0: aload_0
       1: getfield      #63                 // Field onset:Lorg/hl7/fhir/dstu3/model/Type;
       4: ifnull        21
       7: aload_0
       8: getfield      #63                 // Field onset:Lorg/hl7/fhir/dstu3/model/Type;
      11: invokevirtual #83                 // Method org/hl7/fhir/dstu3/model/Type.isEmpty:()Z
      14: ifne          21
      17: iconst_1
      18: goto          22
      21: iconst_0
      22: ireturn

  public org.hl7.fhir.dstu3.model.AllergyIntolerance setOnset(org.hl7.fhir.dstu3.model.Type) throws org.hl7.fhir.exceptions.FHIRFormatError;
    Code:
       0: aload_1
       1: ifnull        69
       4: aload_1
       5: instanceof    #64                 // class org/hl7/fhir/dstu3/model/DateTimeType
       8: ifne          69
      11: aload_1
      12: instanceof    #75                 // class org/hl7/fhir/dstu3/model/Age
      15: ifne          69
      18: aload_1
      19: instanceof    #77                 // class org/hl7/fhir/dstu3/model/Period
      22: ifne          69
      25: aload_1
      26: instanceof    #79                 // class org/hl7/fhir/dstu3/model/Range
      29: ifne          69
      32: aload_1
      33: instanceof    #81                 // class org/hl7/fhir/dstu3/model/StringType
      36: ifne          69
      39: new           #84                 // class org/hl7/fhir/exceptions/FHIRFormatError
      42: dup
      43: new           #66                 // class java/lang/StringBuilder
      46: dup
      47: invokespecial #67                 // Method java/lang/StringBuilder."<init>":()V
      50: ldc           #85                 // String Not the right type for AllergyIntolerance.onset[x]:
      52: invokevirtual #69                 // Method java/lang/StringBuilder.append:(Ljava/lang/String;)Ljava/lang/StringBuilder;
      55: aload_1
      56: invokevirtual #86                 // Method org/hl7/fhir/dstu3/model/Type.fhirType:()Ljava/lang/String;
      59: invokevirtual #69                 // Method java/lang/StringBuilder.append:(Ljava/lang/String;)Ljava/lang/StringBuilder;
      62: invokevirtual #73                 // Method java/lang/StringBuilder.toString:()Ljava/lang/String;
      65: invokespecial #87                 // Method org/hl7/fhir/exceptions/FHIRFormatError."<init>":(Ljava/lang/String;)V
      68: athrow
      69: aload_0
      70: aload_1
      71: putfield      #63                 // Field onset:Lorg/hl7/fhir/dstu3/model/Type;
      74: aload_0
      75: areturn

  public org.hl7.fhir.dstu3.model.DateTimeType getAssertedDateElement();
    Code:
       0: aload_0
       1: getfield      #88                 // Field assertedDate:Lorg/hl7/fhir/dstu3/model/DateTimeType;
       4: ifnonnull     40
       7: invokestatic  #19                 // Method org/hl7/fhir/dstu3/model/Configuration.errorOnAutoCreate:()Z
      10: ifeq          23
      13: new           #20                 // class java/lang/Error
      16: dup
      17: ldc           #89                 // String Attempt to auto-create AllergyIntolerance.assertedDate
      19: invokespecial #22                 // Method java/lang/Error."<init>":(Ljava/lang/String;)V
      22: athrow
      23: invokestatic  #23                 // Method org/hl7/fhir/dstu3/model/Configuration.doAutoCreate:()Z
      26: ifeq          40
      29: aload_0
      30: new           #64                 // class org/hl7/fhir/dstu3/model/DateTimeType
      33: dup
      34: invokespecial #90                 // Method org/hl7/fhir/dstu3/model/DateTimeType."<init>":()V
      37: putfield      #88                 // Field assertedDate:Lorg/hl7/fhir/dstu3/model/DateTimeType;
      40: aload_0
      41: getfield      #88                 // Field assertedDate:Lorg/hl7/fhir/dstu3/model/DateTimeType;
      44: areturn

  public boolean hasAssertedDateElement();
    Code:
       0: aload_0
       1: getfield      #88                 // Field assertedDate:Lorg/hl7/fhir/dstu3/model/DateTimeType;
       4: ifnull        21
       7: aload_0
       8: getfield      #88                 // Field assertedDate:Lorg/hl7/fhir/dstu3/model/DateTimeType;
      11: invokevirtual #91                 // Method org/hl7/fhir/dstu3/model/DateTimeType.isEmpty:()Z
      14: ifne          21
      17: iconst_1
      18: goto          22
      21: iconst_0
      22: ireturn

  public boolean hasAssertedDate();
    Code:
       0: aload_0
       1: getfield      #88                 // Field assertedDate:Lorg/hl7/fhir/dstu3/model/DateTimeType;
       4: ifnull        21
       7: aload_0
       8: getfield      #88                 // Field assertedDate:Lorg/hl7/fhir/dstu3/model/DateTimeType;
      11: invokevirtual #91                 // Method org/hl7/fhir/dstu3/model/DateTimeType.isEmpty:()Z
      14: ifne          21
      17: iconst_1
      18: goto          22
      21: iconst_0
      22: ireturn

  public org.hl7.fhir.dstu3.model.AllergyIntolerance setAssertedDateElement(org.hl7.fhir.dstu3.model.DateTimeType);
    Code:
       0: aload_0
       1: aload_1
       2: putfield      #88                 // Field assertedDate:Lorg/hl7/fhir/dstu3/model/DateTimeType;
       5: aload_0
       6: areturn

  public java.util.Date getAssertedDate();
    Code:
       0: aload_0
       1: getfield      #88                 // Field assertedDate:Lorg/hl7/fhir/dstu3/model/DateTimeType;
       4: ifnonnull     11
       7: aconst_null
       8: goto          21
      11: aload_0
      12: getfield      #88                 // Field assertedDate:Lorg/hl7/fhir/dstu3/model/DateTimeType;
      15: invokevirtual #92                 // Method org/hl7/fhir/dstu3/model/DateTimeType.getValue:()Ljava/lang/Object;
      18: checkcast     #93                 // class java/util/Date
      21: areturn

  public org.hl7.fhir.dstu3.model.AllergyIntolerance setAssertedDate(java.util.Date);
    Code:
       0: aload_1
       1: ifnonnull     12
       4: aload_0
       5: aconst_null
       6: putfield      #88                 // Field assertedDate:Lorg/hl7/fhir/dstu3/model/DateTimeType;
       9: goto          39
      12: aload_0
      13: getfield      #88                 // Field assertedDate:Lorg/hl7/fhir/dstu3/model/DateTimeType;
      16: ifnonnull     30
      19: aload_0
      20: new           #64                 // class org/hl7/fhir/dstu3/model/DateTimeType
      23: dup
      24: invokespecial #90                 // Method org/hl7/fhir/dstu3/model/DateTimeType."<init>":()V
      27: putfield      #88                 // Field assertedDate:Lorg/hl7/fhir/dstu3/model/DateTimeType;
      30: aload_0
      31: getfield      #88                 // Field assertedDate:Lorg/hl7/fhir/dstu3/model/DateTimeType;
      34: aload_1
      35: invokevirtual #94                 // Method org/hl7/fhir/dstu3/model/DateTimeType.setValue:(Ljava/util/Date;)Lorg/hl7/fhir/dstu3/model/BaseDateTimeType;
      38: pop
      39: aload_0
      40: areturn

  public org.hl7.fhir.dstu3.model.Reference getRecorder();
    Code:
       0: aload_0
       1: getfield      #95                 // Field recorder:Lorg/hl7/fhir/dstu3/model/Reference;
       4: ifnonnull     40
       7: invokestatic  #19                 // Method org/hl7/fhir/dstu3/model/Configuration.errorOnAutoCreate:()Z
      10: ifeq          23
      13: new           #20                 // class java/lang/Error
      16: dup
      17: ldc           #96                 // String Attempt to auto-create AllergyIntolerance.recorder
      19: invokespecial #22                 // Method java/lang/Error."<init>":(Ljava/lang/String;)V
      22: athrow
      23: invokestatic  #23                 // Method org/hl7/fhir/dstu3/model/Configuration.doAutoCreate:()Z
      26: ifeq          40
      29: aload_0
      30: new           #57                 // class org/hl7/fhir/dstu3/model/Reference
      33: dup
      34: invokespecial #58                 // Method org/hl7/fhir/dstu3/model/Reference."<init>":()V
      37: putfield      #95                 // Field recorder:Lorg/hl7/fhir/dstu3/model/Reference;
      40: aload_0
      41: getfield      #95                 // Field recorder:Lorg/hl7/fhir/dstu3/model/Reference;
      44: areturn

  public boolean hasRecorder();
    Code:
       0: aload_0
       1: getfield      #95                 // Field recorder:Lorg/hl7/fhir/dstu3/model/Reference;
       4: ifnull        21
       7: aload_0
       8: getfield      #95                 // Field recorder:Lorg/hl7/fhir/dstu3/model/Reference;
      11: invokevirtual #59                 // Method org/hl7/fhir/dstu3/model/Reference.isEmpty:()Z
      14: ifne          21
      17: iconst_1
      18: goto          22
      21: iconst_0
      22: ireturn

  public org.hl7.fhir.dstu3.model.AllergyIntolerance setRecorder(org.hl7.fhir.dstu3.model.Reference);
    Code:
       0: aload_0
       1: aload_1
       2: putfield      #95                 // Field recorder:Lorg/hl7/fhir/dstu3/model/Reference;
       5: aload_0
       6: areturn

  public org.hl7.fhir.dstu3.model.Resource getRecorderTarget();
    Code:
       0: aload_0
       1: getfield      #97                 // Field recorderTarget:Lorg/hl7/fhir/dstu3/model/Resource;
       4: areturn

  public org.hl7.fhir.dstu3.model.AllergyIntolerance setRecorderTarget(org.hl7.fhir.dstu3.model.Resource);
    Code:
       0: aload_0
       1: aload_1
       2: putfield      #97                 // Field recorderTarget:Lorg/hl7/fhir/dstu3/model/Resource;
       5: aload_0
       6: areturn

  public org.hl7.fhir.dstu3.model.Reference getAsserter();
    Code:
       0: aload_0
       1: getfield      #98                 // Field asserter:Lorg/hl7/fhir/dstu3/model/Reference;
       4: ifnonnull     40
       7: invokestatic  #19                 // Method org/hl7/fhir/dstu3/model/Configuration.errorOnAutoCreate:()Z
      10: ifeq          23
      13: new           #20                 // class java/lang/Error
      16: dup
      17: ldc           #99                 // String Attempt to auto-create AllergyIntolerance.asserter
      19: invokespecial #22                 // Method java/lang/Error."<init>":(Ljava/lang/String;)V
      22: athrow
      23: invokestatic  #23                 // Method org/hl7/fhir/dstu3/model/Configuration.doAutoCreate:()Z
      26: ifeq          40
      29: aload_0
      30: new           #57                 // class org/hl7/fhir/dstu3/model/Reference
      33: dup
      34: invokespecial #58                 // Method org/hl7/fhir/dstu3/model/Reference."<init>":()V
      37: putfield      #98                 // Field asserter:Lorg/hl7/fhir/dstu3/model/Reference;
      40: aload_0
      41: getfield      #98                 // Field asserter:Lorg/hl7/fhir/dstu3/model/Reference;
      44: areturn

  public boolean hasAsserter();
    Code:
       0: aload_0
       1: getfield      #98                 // Field asserter:Lorg/hl7/fhir/dstu3/model/Reference;
       4: ifnull        21
       7: aload_0
       8: getfield      #98                 // Field asserter:Lorg/hl7/fhir/dstu3/model/Reference;
      11: invokevirtual #59                 // Method org/hl7/fhir/dstu3/model/Reference.isEmpty:()Z
      14: ifne          21
      17: iconst_1
      18: goto          22
      21: iconst_0
      22: ireturn

  public org.hl7.fhir.dstu3.model.AllergyIntolerance setAsserter(org.hl7.fhir.dstu3.model.Reference);
    Code:
       0: aload_0
       1: aload_1
       2: putfield      #98                 // Field asserter:Lorg/hl7/fhir/dstu3/model/Reference;
       5: aload_0
       6: areturn

  public org.hl7.fhir.dstu3.model.Resource getAsserterTarget();
    Code:
       0: aload_0
       1: getfield      #100                // Field asserterTarget:Lorg/hl7/fhir/dstu3/model/Resource;
       4: areturn

  public org.hl7.fhir.dstu3.model.AllergyIntolerance setAsserterTarget(org.hl7.fhir.dstu3.model.Resource);
    Code:
       0: aload_0
       1: aload_1
       2: putfield      #100                // Field asserterTarget:Lorg/hl7/fhir/dstu3/model/Resource;
       5: aload_0
       6: areturn

  public org.hl7.fhir.dstu3.model.DateTimeType getLastOccurrenceElement();
    Code:
       0: aload_0
       1: getfield      #101                // Field lastOccurrence:Lorg/hl7/fhir/dstu3/model/DateTimeType;
       4: ifnonnull     40
       7: invokestatic  #19                 // Method org/hl7/fhir/dstu3/model/Configuration.errorOnAutoCreate:()Z
      10: ifeq          23
      13: new           #20                 // class java/lang/Error
      16: dup
      17: ldc           #102                // String Attempt to auto-create AllergyIntolerance.lastOccurrence
      19: invokespecial #22                 // Method java/lang/Error."<init>":(Ljava/lang/String;)V
      22: athrow
      23: invokestatic  #23                 // Method org/hl7/fhir/dstu3/model/Configuration.doAutoCreate:()Z
      26: ifeq          40
      29: aload_0
      30: new           #64                 // class org/hl7/fhir/dstu3/model/DateTimeType
      33: dup
      34: invokespecial #90                 // Method org/hl7/fhir/dstu3/model/DateTimeType."<init>":()V
      37: putfield      #101                // Field lastOccurrence:Lorg/hl7/fhir/dstu3/model/DateTimeType;
      40: aload_0
      41: getfield      #101                // Field lastOccurrence:Lorg/hl7/fhir/dstu3/model/DateTimeType;
      44: areturn

  public boolean hasLastOccurrenceElement();
    Code:
       0: aload_0
       1: getfield      #101                // Field lastOccurrence:Lorg/hl7/fhir/dstu3/model/DateTimeType;
       4: ifnull        21
       7: aload_0
       8: getfield      #101                // Field lastOccurrence:Lorg/hl7/fhir/dstu3/model/DateTimeType;
      11: invokevirtual #91                 // Method org/hl7/fhir/dstu3/model/DateTimeType.isEmpty:()Z
      14: ifne          21
      17: iconst_1
      18: goto          22
      21: iconst_0
      22: ireturn

  public boolean hasLastOccurrence();
    Code:
       0: aload_0
       1: getfield      #101                // Field lastOccurrence:Lorg/hl7/fhir/dstu3/model/DateTimeType;
       4: ifnull        21
       7: aload_0
       8: getfield      #101                // Field lastOccurrence:Lorg/hl7/fhir/dstu3/model/DateTimeType;
      11: invokevirtual #91                 // Method org/hl7/fhir/dstu3/model/DateTimeType.isEmpty:()Z
      14: ifne          21
      17: iconst_1
      18: goto          22
      21: iconst_0
      22: ireturn

  public org.hl7.fhir.dstu3.model.AllergyIntolerance setLastOccurrenceElement(org.hl7.fhir.dstu3.model.DateTimeType);
    Code:
       0: aload_0
       1: aload_1
       2: putfield      #101                // Field lastOccurrence:Lorg/hl7/fhir/dstu3/model/DateTimeType;
       5: aload_0
       6: areturn

  public java.util.Date getLastOccurrence();
    Code:
       0: aload_0
       1: getfield      #101                // Field lastOccurrence:Lorg/hl7/fhir/dstu3/model/DateTimeType;
       4: ifnonnull     11
       7: aconst_null
       8: goto          21
      11: aload_0
      12: getfield      #101                // Field lastOccurrence:Lorg/hl7/fhir/dstu3/model/DateTimeType;
      15: invokevirtual #92                 // Method org/hl7/fhir/dstu3/model/DateTimeType.getValue:()Ljava/lang/Object;
      18: checkcast     #93                 // class java/util/Date
      21: areturn

  public org.hl7.fhir.dstu3.model.AllergyIntolerance setLastOccurrence(java.util.Date);
    Code:
       0: aload_1
       1: ifnonnull     12
       4: aload_0
       5: aconst_null
       6: putfield      #101                // Field lastOccurrence:Lorg/hl7/fhir/dstu3/model/DateTimeType;
       9: goto          39
      12: aload_0
      13: getfield      #101                // Field lastOccurrence:Lorg/hl7/fhir/dstu3/model/DateTimeType;
      16: ifnonnull     30
      19: aload_0
      20: new           #64                 // class org/hl7/fhir/dstu3/model/DateTimeType
      23: dup
      24: invokespecial #90                 // Method org/hl7/fhir/dstu3/model/DateTimeType."<init>":()V
      27: putfield      #101                // Field lastOccurrence:Lorg/hl7/fhir/dstu3/model/DateTimeType;
      30: aload_0
      31: getfield      #101                // Field lastOccurrence:Lorg/hl7/fhir/dstu3/model/DateTimeType;
      34: aload_1
      35: invokevirtual #94                 // Method org/hl7/fhir/dstu3/model/DateTimeType.setValue:(Ljava/util/Date;)Lorg/hl7/fhir/dstu3/model/BaseDateTimeType;
      38: pop
      39: aload_0
      40: areturn

  public java.util.List<org.hl7.fhir.dstu3.model.Annotation> getNote();
    Code:
       0: aload_0
       1: getfield      #103                // Field note:Ljava/util/List;
       4: ifnonnull     18
       7: aload_0
       8: new           #5                  // class java/util/ArrayList
      11: dup
      12: invokespecial #6                  // Method java/util/ArrayList."<init>":()V
      15: putfield      #103                // Field note:Ljava/util/List;
      18: aload_0
      19: getfield      #103                // Field note:Ljava/util/List;
      22: areturn

  public org.hl7.fhir.dstu3.model.AllergyIntolerance setNote(java.util.List<org.hl7.fhir.dstu3.model.Annotation>);
    Code:
       0: aload_0
       1: aload_1
       2: putfield      #103                // Field note:Ljava/util/List;
       5: aload_0
       6: areturn

  public boolean hasNote();
    Code:
       0: aload_0
       1: getfield      #103                // Field note:Ljava/util/List;
       4: ifnonnull     9
       7: iconst_0
       8: ireturn
       9: aload_0
      10: getfield      #103                // Field note:Ljava/util/List;
      13: invokeinterface #7,  1            // InterfaceMethod java/util/List.iterator:()Ljava/util/Iterator;
      18: astore_1
      19: aload_1
      20: invokeinterface #8,  1            // InterfaceMethod java/util/Iterator.hasNext:()Z
      25: ifeq          50
      28: aload_1
      29: invokeinterface #9,  1            // InterfaceMethod java/util/Iterator.next:()Ljava/lang/Object;
      34: checkcast     #104                // class org/hl7/fhir/dstu3/model/Annotation
      37: astore_2
      38: aload_2
      39: invokevirtual #105                // Method org/hl7/fhir/dstu3/model/Annotation.isEmpty:()Z
      42: ifne          47
      45: iconst_1
      46: ireturn
      47: goto          19
      50: iconst_0
      51: ireturn

  public org.hl7.fhir.dstu3.model.Annotation addNote();
    Code:
       0: new           #104                // class org/hl7/fhir/dstu3/model/Annotation
       3: dup
       4: invokespecial #106                // Method org/hl7/fhir/dstu3/model/Annotation."<init>":()V
       7: astore_1
       8: aload_0
       9: getfield      #103                // Field note:Ljava/util/List;
      12: ifnonnull     26
      15: aload_0
      16: new           #5                  // class java/util/ArrayList
      19: dup
      20: invokespecial #6                  // Method java/util/ArrayList."<init>":()V
      23: putfield      #103                // Field note:Ljava/util/List;
      26: aload_0
      27: getfield      #103                // Field note:Ljava/util/List;
      30: aload_1
      31: invokeinterface #13,  2           // InterfaceMethod java/util/List.add:(Ljava/lang/Object;)Z
      36: pop
      37: aload_1
      38: areturn

  public org.hl7.fhir.dstu3.model.AllergyIntolerance addNote(org.hl7.fhir.dstu3.model.Annotation);
    Code:
       0: aload_1
       1: ifnonnull     6
       4: aload_0
       5: areturn
       6: aload_0
       7: getfield      #103                // Field note:Ljava/util/List;
      10: ifnonnull     24
      13: aload_0
      14: new           #5                  // class java/util/ArrayList
      17: dup
      18: invokespecial #6                  // Method java/util/ArrayList."<init>":()V
      21: putfield      #103                // Field note:Ljava/util/List;
      24: aload_0
      25: getfield      #103                // Field note:Ljava/util/List;
      28: aload_1
      29: invokeinterface #13,  2           // InterfaceMethod java/util/List.add:(Ljava/lang/Object;)Z
      34: pop
      35: aload_0
      36: areturn

  public org.hl7.fhir.dstu3.model.Annotation getNoteFirstRep();
    Code:
       0: aload_0
       1: invokevirtual #107                // Method getNote:()Ljava/util/List;
       4: invokeinterface #15,  1           // InterfaceMethod java/util/List.isEmpty:()Z
       9: ifeq          17
      12: aload_0
      13: invokevirtual #108                // Method addNote:()Lorg/hl7/fhir/dstu3/model/Annotation;
      16: pop
      17: aload_0
      18: invokevirtual #107                // Method getNote:()Ljava/util/List;
      21: iconst_0
      22: invokeinterface #17,  2           // InterfaceMethod java/util/List.get:(I)Ljava/lang/Object;
      27: checkcast     #104                // class org/hl7/fhir/dstu3/model/Annotation
      30: areturn

  public java.util.List<org.hl7.fhir.dstu3.model.AllergyIntolerance$AllergyIntoleranceReactionComponent> getReaction();
    Code:
       0: aload_0
       1: getfield      #109                // Field reaction:Ljava/util/List;
       4: ifnonnull     18
       7: aload_0
       8: new           #5                  // class java/util/ArrayList
      11: dup
      12: invokespecial #6                  // Method java/util/ArrayList."<init>":()V
      15: putfield      #109                // Field reaction:Ljava/util/List;
      18: aload_0
      19: getfield      #109                // Field reaction:Ljava/util/List;
      22: areturn

  public org.hl7.fhir.dstu3.model.AllergyIntolerance setReaction(java.util.List<org.hl7.fhir.dstu3.model.AllergyIntolerance$AllergyIntoleranceReactionComponent>);
    Code:
       0: aload_0
       1: aload_1
       2: putfield      #109                // Field reaction:Ljava/util/List;
       5: aload_0
       6: areturn

  public boolean hasReaction();
    Code:
       0: aload_0
       1: getfield      #109                // Field reaction:Ljava/util/List;
       4: ifnonnull     9
       7: iconst_0
       8: ireturn
       9: aload_0
      10: getfield      #109                // Field reaction:Ljava/util/List;
      13: invokeinterface #7,  1            // InterfaceMethod java/util/List.iterator:()Ljava/util/Iterator;
      18: astore_1
      19: aload_1
      20: invokeinterface #8,  1            // InterfaceMethod java/util/Iterator.hasNext:()Z
      25: ifeq          50
      28: aload_1
      29: invokeinterface #9,  1            // InterfaceMethod java/util/Iterator.next:()Ljava/lang/Object;
      34: checkcast     #110                // class org/hl7/fhir/dstu3/model/AllergyIntolerance$AllergyIntoleranceReactionComponent
      37: astore_2
      38: aload_2
      39: invokevirtual #111                // Method org/hl7/fhir/dstu3/model/AllergyIntolerance$AllergyIntoleranceReactionComponent.isEmpty:()Z
      42: ifne          47
      45: iconst_1
      46: ireturn
      47: goto          19
      50: iconst_0
      51: ireturn

  public org.hl7.fhir.dstu3.model.AllergyIntolerance$AllergyIntoleranceReactionComponent addReaction();
    Code:
       0: new           #110                // class org/hl7/fhir/dstu3/model/AllergyIntolerance$AllergyIntoleranceReactionComponent
       3: dup
       4: invokespecial #112                // Method org/hl7/fhir/dstu3/model/AllergyIntolerance$AllergyIntoleranceReactionComponent."<init>":()V
       7: astore_1
       8: aload_0
       9: getfield      #109                // Field reaction:Ljava/util/List;
      12: ifnonnull     26
      15: aload_0
      16: new           #5                  // class java/util/ArrayList
      19: dup
      20: invokespecial #6                  // Method java/util/ArrayList."<init>":()V
      23: putfield      #109                // Field reaction:Ljava/util/List;
      26: aload_0
      27: getfield      #109                // Field reaction:Ljava/util/List;
      30: aload_1
      31: invokeinterface #13,  2           // InterfaceMethod java/util/List.add:(Ljava/lang/Object;)Z
      36: pop
      37: aload_1
      38: areturn

  public org.hl7.fhir.dstu3.model.AllergyIntolerance addReaction(org.hl7.fhir.dstu3.model.AllergyIntolerance$AllergyIntoleranceReactionComponent);
    Code:
       0: aload_1
       1: ifnonnull     6
       4: aload_0
       5: areturn
       6: aload_0
       7: getfield      #109                // Field reaction:Ljava/util/List;
      10: ifnonnull     24
      13: aload_0
      14: new           #5                  // class java/util/ArrayList
      17: dup
      18: invokespecial #6                  // Method java/util/ArrayList."<init>":()V
      21: putfield      #109                // Field reaction:Ljava/util/List;
      24: aload_0
      25: getfield      #109                // Field reaction:Ljava/util/List;
      28: aload_1
      29: invokeinterface #13,  2           // InterfaceMethod java/util/List.add:(Ljava/lang/Object;)Z
      34: pop
      35: aload_0
      36: areturn

  public org.hl7.fhir.dstu3.model.AllergyIntolerance$AllergyIntoleranceReactionComponent getReactionFirstRep();
    Code:
       0: aload_0
       1: invokevirtual #113                // Method getReaction:()Ljava/util/List;
       4: invokeinterface #15,  1           // InterfaceMethod java/util/List.isEmpty:()Z
       9: ifeq          17
      12: aload_0
      13: invokevirtual #114                // Method addReaction:()Lorg/hl7/fhir/dstu3/model/AllergyIntolerance$AllergyIntoleranceReactionComponent;
      16: pop
      17: aload_0
      18: invokevirtual #113                // Method getReaction:()Ljava/util/List;
      21: iconst_0
      22: invokeinterface #17,  2           // InterfaceMethod java/util/List.get:(I)Ljava/lang/Object;
      27: checkcast     #110                // class org/hl7/fhir/dstu3/model/AllergyIntolerance$AllergyIntoleranceReactionComponent
      30: areturn

  protected void listChildren(java.util.List<org.hl7.fhir.dstu3.model.Property>);
    Code:
       0: aload_0
       1: aload_1
       2: invokespecial #115                // Method org/hl7/fhir/dstu3/model/DomainResource.listChildren:(Ljava/util/List;)V
       5: aload_1
       6: new           #116                // class org/hl7/fhir/dstu3/model/Property
       9: dup
      10: ldc           #117                // String identifier
      12: ldc           #118                // String Identifier
      14: ldc           #119                // String This records identifiers associated with this allergy/intolerance concern that are defined by business processes and/or used to refer to it when a direct URL reference to the resource itself is not appropriate (e.g. in CDA documents, or in written / printed documentation).
      16: iconst_0
      17: ldc           #121                // int 2147483647
      19: aload_0
      20: getfield      #4                  // Field identifier:Ljava/util/List;
      23: invokespecial #122                // Method org/hl7/fhir/dstu3/model/Property."<init>":(Ljava/lang/String;Ljava/lang/String;Ljava/lang/String;IILjava/util/List;)V
      26: invokeinterface #13,  2           // InterfaceMethod java/util/List.add:(Ljava/lang/Object;)Z
      31: pop
      32: aload_1
      33: new           #116                // class org/hl7/fhir/dstu3/model/Property
      36: dup
      37: ldc           #123                // String clinicalStatus
      39: ldc           #124                // String code
      41: ldc           #125                // String The clinical status of the allergy or intolerance.
      43: iconst_0
      44: iconst_1
      45: aload_0
      46: getfield      #18                 // Field clinicalStatus:Lorg/hl7/fhir/dstu3/model/Enumeration;
      49: invokespecial #126                // Method org/hl7/fhir/dstu3/model/Property."<init>":(Ljava/lang/String;Ljava/lang/String;Ljava/lang/String;IILorg/hl7/fhir/dstu3/model/Base;)V
      52: invokeinterface #13,  2           // InterfaceMethod java/util/List.add:(Ljava/lang/Object;)Z
      57: pop
      58: aload_1
      59: new           #116                // class org/hl7/fhir/dstu3/model/Property
      62: dup
      63: ldc           #127                // String verificationStatus
      65: ldc           #124                // String code
      67: ldc           #128                // String Assertion about certainty associated with the propensity, or potential risk, of a reaction to the identified substance (including pharmaceutical product).
      69: iconst_0
      70: iconst_1
      71: aload_0
      72: getfield      #2                  // Field verificationStatus:Lorg/hl7/fhir/dstu3/model/Enumeration;
      75: invokespecial #126                // Method org/hl7/fhir/dstu3/model/Property."<init>":(Ljava/lang/String;Ljava/lang/String;Ljava/lang/String;IILorg/hl7/fhir/dstu3/model/Base;)V
      78: invokeinterface #13,  2           // InterfaceMethod java/util/List.add:(Ljava/lang/Object;)Z
      83: pop
      84: aload_1
      85: new           #116                // class org/hl7/fhir/dstu3/model/Property
      88: dup
      89: ldc           #129                // String type
      91: ldc           #124                // String code
      93: ldc           #130                // String Identification of the underlying physiological mechanism for the reaction risk.
      95: iconst_0
      96: iconst_1
      97: aload_0
      98: getfield      #36                 // Field type:Lorg/hl7/fhir/dstu3/model/Enumeration;
     101: invokespecial #126                // Method org/hl7/fhir/dstu3/model/Property."<init>":(Ljava/lang/String;Ljava/lang/String;Ljava/lang/String;IILorg/hl7/fhir/dstu3/model/Base;)V
     104: invokeinterface #13,  2           // InterfaceMethod java/util/List.add:(Ljava/lang/Object;)Z
     109: pop
     110: aload_1
     111: new           #116                // class org/hl7/fhir/dstu3/model/Property
     114: dup
     115: ldc           #131                // String category
     117: ldc           #124                // String code
     119: ldc           #132                // String Category of the identified substance.
     121: iconst_0
     122: ldc           #121                // int 2147483647
     124: aload_0
     125: getfield      #41                 // Field category:Ljava/util/List;
     128: invokespecial #122                // Method org/hl7/fhir/dstu3/model/Property."<init>":(Ljava/lang/String;Ljava/lang/String;Ljava/lang/String;IILjava/util/List;)V
     131: invokeinterface #13,  2           // InterfaceMethod java/util/List.add:(Ljava/lang/Object;)Z
     136: pop
     137: aload_1
     138: new           #116                // class org/hl7/fhir/dstu3/model/Property
     141: dup
     142: ldc           #133                // String criticality
     144: ldc           #124                // String code
     146: ldc           #134                // String Estimate of the potential clinical harm, or seriousness, of the reaction to the identified substance.
     148: iconst_0
     149: iconst_1
     150: aload_0
     151: getfield      #46                 // Field criticality:Lorg/hl7/fhir/dstu3/model/Enumeration;
     154: invokespecial #126                // Method org/hl7/fhir/dstu3/model/Property."<init>":(Ljava/lang/String;Ljava/lang/String;Ljava/lang/String;IILorg/hl7/fhir/dstu3/model/Base;)V
     157: invokeinterface #13,  2           // InterfaceMethod java/util/List.add:(Ljava/lang/Object;)Z
     162: pop
     163: aload_1
     164: new           #116                // class org/hl7/fhir/dstu3/model/Property
     167: dup
     168: ldc           #124                // String code
     170: ldc           #135                // String CodeableConcept
     172: ldc           #136                // String Code for an allergy or intolerance statement (either a positive or a negated/excluded statement).  This may be a code for a substance or pharmaceutical product that is considered to be responsible for the adverse reaction risk (e.g., \"Latex\"), an allergy or intolerance condition (e.g., \"Latex allergy\"), or a negated/excluded code for a specific substance or class (e.g., \"No latex allergy\") or a general or categorical negated statement (e.g.,  \"No known allergy\", \"No known drug allergies\").
     174: iconst_0
     175: iconst_1
     176: aload_0
     177: getfield      #51                 // Field code:Lorg/hl7/fhir/dstu3/model/CodeableConcept;
     180: invokespecial #126                // Method org/hl7/fhir/dstu3/model/Property."<init>":(Ljava/lang/String;Ljava/lang/String;Ljava/lang/String;IILorg/hl7/fhir/dstu3/model/Base;)V
     183: invokeinterface #13,  2           // InterfaceMethod java/util/List.add:(Ljava/lang/Object;)Z
     188: pop
     189: aload_1
     190: new           #116                // class org/hl7/fhir/dstu3/model/Property
     193: dup
     194: ldc           #137                // String patient
     196: ldc           #138                // String Reference(Patient)
     198: ldc           #139                // String The patient who has the allergy or intolerance.
     200: iconst_0
     201: iconst_1
     202: aload_0
     203: getfield      #3                  // Field patient:Lorg/hl7/fhir/dstu3/model/Reference;
     206: invokespecial #126                // Method org/hl7/fhir/dstu3/model/Property."<init>":(Ljava/lang/String;Ljava/lang/String;Ljava/lang/String;IILorg/hl7/fhir/dstu3/model/Base;)V
     209: invokeinterface #13,  2           // InterfaceMethod java/util/List.add:(Ljava/lang/Object;)Z
     214: pop
     215: aload_1
     216: new           #116                // class org/hl7/fhir/dstu3/model/Property
     219: dup
     220: ldc           #140                // String onset[x]
     222: ldc           #141                // String dateTime|Age|Period|Range|string
     224: ldc           #142                // String Estimated or actual date,  date-time, or age when allergy or intolerance was identified.
     226: iconst_0
     227: iconst_1
     228: aload_0
     229: getfield      #63                 // Field onset:Lorg/hl7/fhir/dstu3/model/Type;
     232: invokespecial #126                // Method org/hl7/fhir/dstu3/model/Property."<init>":(Ljava/lang/String;Ljava/lang/String;Ljava/lang/String;IILorg/hl7/fhir/dstu3/model/Base;)V
     235: invokeinterface #13,  2           // InterfaceMethod java/util/List.add:(Ljava/lang/Object;)Z
     240: pop
     241: aload_1
     242: new           #116                // class org/hl7/fhir/dstu3/model/Property
     245: dup
     246: ldc           #143                // String assertedDate
     248: ldc           #144                // String dateTime
     250: ldc           #145                // String The date on which the existance of the AllergyIntolerance was first asserted or acknowledged.
     252: iconst_0
     253: iconst_1
     254: aload_0
     255: getfield      #88                 // Field assertedDate:Lorg/hl7/fhir/dstu3/model/DateTimeType;
     258: invokespecial #126                // Method org/hl7/fhir/dstu3/model/Property."<init>":(Ljava/lang/String;Ljava/lang/String;Ljava/lang/String;IILorg/hl7/fhir/dstu3/model/Base;)V
     261: invokeinterface #13,  2           // InterfaceMethod java/util/List.add:(Ljava/lang/Object;)Z
     266: pop
     267: aload_1
     268: new           #116                // class org/hl7/fhir/dstu3/model/Property
     271: dup
     272: ldc           #146                // String recorder
     274: ldc           #147                // String Reference(Practitioner|Patient)
     276: ldc           #148                // String Individual who recorded the record and takes responsibility for its content.
     278: iconst_0
     279: iconst_1
     280: aload_0
     281: getfield      #95                 // Field recorder:Lorg/hl7/fhir/dstu3/model/Reference;
     284: invokespecial #126                // Method org/hl7/fhir/dstu3/model/Property."<init>":(Ljava/lang/String;Ljava/lang/String;Ljava/lang/String;IILorg/hl7/fhir/dstu3/model/Base;)V
     287: invokeinterface #13,  2           // InterfaceMethod java/util/List.add:(Ljava/lang/Object;)Z
     292: pop
     293: aload_1
     294: new           #116                // class org/hl7/fhir/dstu3/model/Property
     297: dup
     298: ldc           #149                // String asserter
     300: ldc           #150                // String Reference(Patient|RelatedPerson|Practitioner)
     302: ldc           #151                // String The source of the information about the allergy that is recorded.
     304: iconst_0
     305: iconst_1
     306: aload_0
     307: getfield      #98                 // Field asserter:Lorg/hl7/fhir/dstu3/model/Reference;
     310: invokespecial #126                // Method org/hl7/fhir/dstu3/model/Property."<init>":(Ljava/lang/String;Ljava/lang/String;Ljava/lang/String;IILorg/hl7/fhir/dstu3/model/Base;)V
     313: invokeinterface #13,  2           // InterfaceMethod java/util/List.add:(Ljava/lang/Object;)Z
     318: pop
     319: aload_1
     320: new           #116                // class org/hl7/fhir/dstu3/model/Property
     323: dup
     324: ldc           #152                // String lastOccurrence
     326: ldc           #144                // String dateTime
     328: ldc           #153                // String Represents the date and/or time of the last known occurrence of a reaction event.
     330: iconst_0
     331: iconst_1
     332: aload_0
     333: getfield      #101                // Field lastOccurrence:Lorg/hl7/fhir/dstu3/model/DateTimeType;
     336: invokespecial #126                // Method org/hl7/fhir/dstu3/model/Property."<init>":(Ljava/lang/String;Ljava/lang/String;Ljava/lang/String;IILorg/hl7/fhir/dstu3/model/Base;)V
     339: invokeinterface #13,  2           // InterfaceMethod java/util/List.add:(Ljava/lang/Object;)Z
     344: pop
     345: aload_1
     346: new           #116                // class org/hl7/fhir/dstu3/model/Property
     349: dup
     350: ldc           #154                // String note
     352: ldc           #155                // String Annotation
     354: ldc           #156                // String Additional narrative about the propensity for the Adverse Reaction, not captured in other fields.
     356: iconst_0
     357: ldc           #121                // int 2147483647
     359: aload_0
     360: getfield      #103                // Field note:Ljava/util/List;
     363: invokespecial #122                // Method org/hl7/fhir/dstu3/model/Property."<init>":(Ljava/lang/String;Ljava/lang/String;Ljava/lang/String;IILjava/util/List;)V
     366: invokeinterface #13,  2           // InterfaceMethod java/util/List.add:(Ljava/lang/Object;)Z
     371: pop
     372: aload_1
     373: new           #116                // class org/hl7/fhir/dstu3/model/Property
     376: dup
     377: ldc           #157                // String reaction
     379: ldc           #158                // String
     381: ldc           #159                // String Details about each adverse reaction event linked to exposure to the identified substance.
     383: iconst_0
     384: ldc           #121                // int 2147483647
     386: aload_0
     387: getfield      #109                // Field reaction:Ljava/util/List;
     390: invokespecial #122                // Method org/hl7/fhir/dstu3/model/Property."<init>":(Ljava/lang/String;Ljava/lang/String;Ljava/lang/String;IILjava/util/List;)V
     393: invokeinterface #13,  2           // InterfaceMethod java/util/List.add:(Ljava/lang/Object;)Z
     398: pop
     399: return

  public org.hl7.fhir.dstu3.model.Property getNamedProperty(int, java.lang.String, boolean) throws org.hl7.fhir.exceptions.FHIRException;
    Code:
       0: iload_1
       1: lookupswitch  { // 21
           -1886241828: 402
           -1886216323: 342
           -1701663010: 382
           -1618432855: 180
           -1608054609: 282
           -1545082428: 422
           -1445342188: 462
            -867509719: 583
            -842509843: 221
            -799233858: 502
            -791418107: 322
            -462853915: 201
            -373242253: 522
            -186664742: 442
            -174231629: 482
               3059181: 302
               3387378: 562
               3575610: 241
              50511102: 261
             105901603: 362
            1896977671: 542
               default: 604
          }
     180: new           #116                // class org/hl7/fhir/dstu3/model/Property
     183: dup
     184: ldc           #117                // String identifier
     186: ldc           #118                // String Identifier
     188: ldc           #119                // String This records identifiers associated with this allergy/intolerance concern that are defined by business processes and/or used to refer to it when a direct URL reference to the resource itself is not appropriate (e.g. in CDA documents, or in written / printed documentation).
     190: iconst_0
     191: ldc           #121                // int 2147483647
     193: aload_0
     194: getfield      #4                  // Field identifier:Ljava/util/List;
     197: invokespecial #122                // Method org/hl7/fhir/dstu3/model/Property."<init>":(Ljava/lang/String;Ljava/lang/String;Ljava/lang/String;IILjava/util/List;)V
     200: areturn
     201: new           #116                // class org/hl7/fhir/dstu3/model/Property
     204: dup
     205: ldc           #123                // String clinicalStatus
     207: ldc           #124                // String code
     209: ldc           #125                // String The clinical status of the allergy or intolerance.
     211: iconst_0
     212: iconst_1
     213: aload_0
     214: getfield      #18                 // Field clinicalStatus:Lorg/hl7/fhir/dstu3/model/Enumeration;
     217: invokespecial #126                // Method org/hl7/fhir/dstu3/model/Property."<init>":(Ljava/lang/String;Ljava/lang/String;Ljava/lang/String;IILorg/hl7/fhir/dstu3/model/Base;)V
     220: areturn
     221: new           #116                // class org/hl7/fhir/dstu3/model/Property
     224: dup
     225: ldc           #127                // String verificationStatus
     227: ldc           #124                // String code
     229: ldc           #128                // String Assertion about certainty associated with the propensity, or potential risk, of a reaction to the identified substance (including pharmaceutical product).
     231: iconst_0
     232: iconst_1
     233: aload_0
     234: getfield      #2                  // Field verificationStatus:Lorg/hl7/fhir/dstu3/model/Enumeration;
     237: invokespecial #126                // Method org/hl7/fhir/dstu3/model/Property."<init>":(Ljava/lang/String;Ljava/lang/String;Ljava/lang/String;IILorg/hl7/fhir/dstu3/model/Base;)V
     240: areturn
     241: new           #116                // class org/hl7/fhir/dstu3/model/Property
     244: dup
     245: ldc           #129                // String type
     247: ldc           #124                // String code
     249: ldc           #130                // String Identification of the underlying physiological mechanism for the reaction risk.
     251: iconst_0
     252: iconst_1
     253: aload_0
     254: getfield      #36                 // Field type:Lorg/hl7/fhir/dstu3/model/Enumeration;
     257: invokespecial #126                // Method org/hl7/fhir/dstu3/model/Property."<init>":(Ljava/lang/String;Ljava/lang/String;Ljava/lang/String;IILorg/hl7/fhir/dstu3/model/Base;)V
     260: areturn
     261: new           #116                // class org/hl7/fhir/dstu3/model/Property
     264: dup
     265: ldc           #131                // String category
     267: ldc           #124                // String code
     269: ldc           #132                // String Category of the identified substance.
     271: iconst_0
     272: ldc           #121                // int 2147483647
     274: aload_0
     275: getfield      #41                 // Field category:Ljava/util/List;
     278: invokespecial #122                // Method org/hl7/fhir/dstu3/model/Property."<init>":(Ljava/lang/String;Ljava/lang/String;Ljava/lang/String;IILjava/util/List;)V
     281: areturn
     282: new           #116                // class org/hl7/fhir/dstu3/model/Property
     285: dup
     286: ldc           #133                // String criticality
     288: ldc           #124                // String code
     290: ldc           #134                // String Estimate of the potential clinical harm, or seriousness, of the reaction to the identified substance.
     292: iconst_0
     293: iconst_1
     294: aload_0
     295: getfield      #46                 // Field criticality:Lorg/hl7/fhir/dstu3/model/Enumeration;
     298: invokespecial #126                // Method org/hl7/fhir/dstu3/model/Property."<init>":(Ljava/lang/String;Ljava/lang/String;Ljava/lang/String;IILorg/hl7/fhir/dstu3/model/Base;)V
     301: areturn
     302: new           #116                // class org/hl7/fhir/dstu3/model/Property
     305: dup
     306: ldc           #124                // String code
     308: ldc           #135                // String CodeableConcept
     310: ldc           #136                // String Code for an allergy or intolerance statement (either a positive or a negated/excluded statement).  This may be a code for a substance or pharmaceutical product that is considered to be responsible for the adverse reaction risk (e.g., \"Latex\"), an allergy or intolerance condition (e.g., \"Latex allergy\"), or a negated/excluded code for a specific substance or class (e.g., \"No latex allergy\") or a general or categorical negated statement (e.g.,  \"No known allergy\", \"No known drug allergies\").
     312: iconst_0
     313: iconst_1
     314: aload_0
     315: getfield      #51                 // Field code:Lorg/hl7/fhir/dstu3/model/CodeableConcept;
     318: invokespecial #126                // Method org/hl7/fhir/dstu3/model/Property."<init>":(Ljava/lang/String;Ljava/lang/String;Ljava/lang/String;IILorg/hl7/fhir/dstu3/model/Base;)V
     321: areturn
     322: new           #116                // class org/hl7/fhir/dstu3/model/Property
     325: dup
     326: ldc           #137                // String patient
     328: ldc           #138                // String Reference(Patient)
     330: ldc           #139                // String The patient who has the allergy or intolerance.
     332: iconst_0
     333: iconst_1
     334: aload_0
     335: getfield      #3                  // Field patient:Lorg/hl7/fhir/dstu3/model/Reference;
     338: invokespecial #126                // Method org/hl7/fhir/dstu3/model/Property."<init>":(Ljava/lang/String;Ljava/lang/String;Ljava/lang/String;IILorg/hl7/fhir/dstu3/model/Base;)V
     341: areturn
     342: new           #116                // class org/hl7/fhir/dstu3/model/Property
     345: dup
     346: ldc           #140                // String onset[x]
     348: ldc           #141                // String dateTime|Age|Period|Range|string
     350: ldc           #142                // String Estimated or actual date,  date-time, or age when allergy or intolerance was identified.
     352: iconst_0
     353: iconst_1
     354: aload_0
     355: getfield      #63                 // Field onset:Lorg/hl7/fhir/dstu3/model/Type;
     358: invokespecial #126                // Method org/hl7/fhir/dstu3/model/Property."<init>":(Ljava/lang/String;Ljava/lang/String;Ljava/lang/String;IILorg/hl7/fhir/dstu3/model/Base;)V
     361: areturn
     362: new           #116                // class org/hl7/fhir/dstu3/model/Property
     365: dup
     366: ldc           #140                // String onset[x]
     368: ldc           #141                // String dateTime|Age|Period|Range|string
     370: ldc           #142                // String Estimated or actual date,  date-time, or age when allergy or intolerance was identified.
     372: iconst_0
     373: iconst_1
     374: aload_0
     375: getfield      #63                 // Field onset:Lorg/hl7/fhir/dstu3/model/Type;
     378: invokespecial #126                // Method org/hl7/fhir/dstu3/model/Property."<init>":(Ljava/lang/String;Ljava/lang/String;Ljava/lang/String;IILorg/hl7/fhir/dstu3/model/Base;)V
     381: areturn
     382: new           #116                // class org/hl7/fhir/dstu3/model/Property
     385: dup
     386: ldc           #140                // String onset[x]
     388: ldc           #141                // String dateTime|Age|Period|Range|string
     390: ldc           #142                // String Estimated or actual date,  date-time, or age when allergy or intolerance was identified.
     392: iconst_0
     393: iconst_1
     394: aload_0
     395: getfield      #63                 // Field onset:Lorg/hl7/fhir/dstu3/model/Type;
     398: invokespecial #126                // Method org/hl7/fhir/dstu3/model/Property."<init>":(Ljava/lang/String;Ljava/lang/String;Ljava/lang/String;IILorg/hl7/fhir/dstu3/model/Base;)V
     401: areturn
     402: new           #116                // class org/hl7/fhir/dstu3/model/Property
     405: dup
     406: ldc           #140                // String onset[x]
     408: ldc           #141                // String dateTime|Age|Period|Range|string
     410: ldc           #142                // String Estimated or actual date,  date-time, or age when allergy or intolerance was identified.
     412: iconst_0
     413: iconst_1
     414: aload_0
     415: getfield      #63                 // Field onset:Lorg/hl7/fhir/dstu3/model/Type;
     418: invokespecial #126                // Method org/hl7/fhir/dstu3/model/Property."<init>":(Ljava/lang/String;Ljava/lang/String;Ljava/lang/String;IILorg/hl7/fhir/dstu3/model/Base;)V
     421: areturn
     422: new           #116                // class org/hl7/fhir/dstu3/model/Property
     425: dup
     426: ldc           #140                // String onset[x]
     428: ldc           #141                // String dateTime|Age|Period|Range|string
     430: ldc           #142                // String Estimated or actual date,  date-time, or age when allergy or intolerance was identified.
     432: iconst_0
     433: iconst_1
     434: aload_0
     435: getfield      #63                 // Field onset:Lorg/hl7/fhir/dstu3/model/Type;
     438: invokespecial #126                // Method org/hl7/fhir/dstu3/model/Property."<init>":(Ljava/lang/String;Ljava/lang/String;Ljava/lang/String;IILorg/hl7/fhir/dstu3/model/Base;)V
     441: areturn
     442: new           #116                // class org/hl7/fhir/dstu3/model/Property
     445: dup
     446: ldc           #140                // String onset[x]
     448: ldc           #141                // String dateTime|Age|Period|Range|string
     450: ldc           #142                // String Estimated or actual date,  date-time, or age when allergy or intolerance was identified.
     452: iconst_0
     453: iconst_1
     454: aload_0
     455: getfield      #63                 // Field onset:Lorg/hl7/fhir/dstu3/model/Type;
     458: invokespecial #126                // Method org/hl7/fhir/dstu3/model/Property."<init>":(Ljava/lang/String;Ljava/lang/String;Ljava/lang/String;IILorg/hl7/fhir/dstu3/model/Base;)V
     461: areturn
     462: new           #116                // class org/hl7/fhir/dstu3/model/Property
     465: dup
     466: ldc           #140                // String onset[x]
     468: ldc           #141                // String dateTime|Age|Period|Range|string
     470: ldc           #142                // String Estimated or actual date,  date-time, or age when allergy or intolerance was identified.
     472: iconst_0
     473: iconst_1
     474: aload_0
     475: getfield      #63                 // Field onset:Lorg/hl7/fhir/dstu3/model/Type;
     478: invokespecial #126                // Method org/hl7/fhir/dstu3/model/Property."<init>":(Ljava/lang/String;Ljava/lang/String;Ljava/lang/String;IILorg/hl7/fhir/dstu3/model/Base;)V
     481: areturn
     482: new           #116                // class org/hl7/fhir/dstu3/model/Property
     485: dup
     486: ldc           #143                // String assertedDate
     488: ldc           #144                // String dateTime
     490: ldc           #145                // String The date on which the existance of the AllergyIntolerance was first asserted or acknowledged.
     492: iconst_0
     493: iconst_1
     494: aload_0
     495: getfield      #88                 // Field assertedDate:Lorg/hl7/fhir/dstu3/model/DateTimeType;
     498: invokespecial #126                // Method org/hl7/fhir/dstu3/model/Property."<init>":(Ljava/lang/String;Ljava/lang/String;Ljava/lang/String;IILorg/hl7/fhir/dstu3/model/Base;)V
     501: areturn
     502: new           #116                // class org/hl7/fhir/dstu3/model/Property
     505: dup
     506: ldc           #146                // String recorder
     508: ldc           #147                // String Reference(Practitioner|Patient)
     510: ldc           #148                // String Individual who recorded the record and takes responsibility for its content.
     512: iconst_0
     513: iconst_1
     514: aload_0
     515: getfield      #95                 // Field recorder:Lorg/hl7/fhir/dstu3/model/Reference;
     518: invokespecial #126                // Method org/hl7/fhir/dstu3/model/Property."<init>":(Ljava/lang/String;Ljava/lang/String;Ljava/lang/String;IILorg/hl7/fhir/dstu3/model/Base;)V
     521: areturn
     522: new           #116                // class org/hl7/fhir/dstu3/model/Property
     525: dup
     526: ldc           #149                // String asserter
     528: ldc           #150                // String Reference(Patient|RelatedPerson|Practitioner)
     530: ldc           #151                // String The source of the information about the allergy that is recorded.
     532: iconst_0
     533: iconst_1
     534: aload_0
     535: getfield      #98                 // Field asserter:Lorg/hl7/fhir/dstu3/model/Reference;
     538: invokespecial #126                // Method org/hl7/fhir/dstu3/model/Property."<init>":(Ljava/lang/String;Ljava/lang/String;Ljava/lang/String;IILorg/hl7/fhir/dstu3/model/Base;)V
     541: areturn
     542: new           #116                // class org/hl7/fhir/dstu3/model/Property
     545: dup
     546: ldc           #152                // String lastOccurrence
     548: ldc           #144                // String dateTime
     550: ldc           #153                // String Represents the date and/or time of the last known occurrence of a reaction event.
     552: iconst_0
     553: iconst_1
     554: aload_0
     555: getfield      #101                // Field lastOccurrence:Lorg/hl7/fhir/dstu3/model/DateTimeType;
     558: invokespecial #126                // Method org/hl7/fhir/dstu3/model/Property."<init>":(Ljava/lang/String;Ljava/lang/String;Ljava/lang/String;IILorg/hl7/fhir/dstu3/model/Base;)V
     561: areturn
     562: new           #116                // class org/hl7/fhir/dstu3/model/Property
     565: dup
     566: ldc           #154                // String note
     568: ldc           #155                // String Annotation
     570: ldc           #156                // String Additional narrative about the propensity for the Adverse Reaction, not captured in other fields.
     572: iconst_0
     573: ldc           #121                // int 2147483647
     575: aload_0
     576: getfield      #103                // Field note:Ljava/util/List;
     579: invokespecial #122                // Method org/hl7/fhir/dstu3/model/Property."<init>":(Ljava/lang/String;Ljava/lang/String;Ljava/lang/String;IILjava/util/List;)V
     582: areturn
     583: new           #116                // class org/hl7/fhir/dstu3/model/Property
     586: dup
     587: ldc           #157                // String reaction
     589: ldc           #158                // String
     591: ldc           #159                // String Details about each adverse reaction event linked to exposure to the identified substance.
     593: iconst_0
     594: ldc           #121                // int 2147483647
     596: aload_0
     597: getfield      #109                // Field reaction:Ljava/util/List;
     600: invokespecial #122                // Method org/hl7/fhir/dstu3/model/Property."<init>":(Ljava/lang/String;Ljava/lang/String;Ljava/lang/String;IILjava/util/List;)V
     603: areturn
     604: aload_0
     605: iload_1
     606: aload_2
     607: iload_3
     608: invokespecial #160                // Method org/hl7/fhir/dstu3/model/DomainResource.getNamedProperty:(ILjava/lang/String;Z)Lorg/hl7/fhir/dstu3/model/Property;
     611: areturn

  public org.hl7.fhir.dstu3.model.Base[] getProperty(int, java.lang.String, boolean) throws org.hl7.fhir.exceptions.FHIRException;
    Code:
       0: iload_1
       1: lookupswitch  { // 15
           -1618432855: 132
           -1608054609: 288
            -867509719: 535
            -842509843: 197
            -799233858: 418
            -791418107: 340
            -462853915: 171
            -373242253: 444
            -174231629: 392
               3059181: 314
               3387378: 496
               3575610: 223
              50511102: 249
             105901603: 366
            1896977671: 470
               default: 574
          }
     132: aload_0
     133: getfield      #4                  // Field identifier:Ljava/util/List;
     136: ifnonnull     146
     139: iconst_0
     140: anewarray     #161                // class org/hl7/fhir/dstu3/model/Base
     143: goto          170
     146: aload_0
     147: getfield      #4                  // Field identifier:Ljava/util/List;
     150: aload_0
     151: getfield      #4                  // Field identifier:Ljava/util/List;
     154: invokeinterface #162,  1          // InterfaceMethod java/util/List.size:()I
     159: anewarray     #161                // class org/hl7/fhir/dstu3/model/Base
     162: invokeinterface #163,  2          // InterfaceMethod java/util/List.toArray:([Ljava/lang/Object;)[Ljava/lang/Object;
     167: checkcast     #164                // class "[Lorg/hl7/fhir/dstu3/model/Base;"
     170: areturn
     171: aload_0
     172: getfield      #18                 // Field clinicalStatus:Lorg/hl7/fhir/dstu3/model/Enumeration;
     175: ifnonnull     185
     178: iconst_0
     179: anewarray     #161                // class org/hl7/fhir/dstu3/model/Base
     182: goto          196
     185: iconst_1
     186: anewarray     #161                // class org/hl7/fhir/dstu3/model/Base
     189: dup
     190: iconst_0
     191: aload_0
     192: getfield      #18                 // Field clinicalStatus:Lorg/hl7/fhir/dstu3/model/Enumeration;
     195: aastore
     196: areturn
     197: aload_0
     198: getfield      #2                  // Field verificationStatus:Lorg/hl7/fhir/dstu3/model/Enumeration;
     201: ifnonnull     211
     204: iconst_0
     205: anewarray     #161                // class org/hl7/fhir/dstu3/model/Base
     208: goto          222
     211: iconst_1
     212: anewarray     #161                // class org/hl7/fhir/dstu3/model/Base
     215: dup
     216: iconst_0
     217: aload_0
     218: getfield      #2                  // Field verificationStatus:Lorg/hl7/fhir/dstu3/model/Enumeration;
     221: aastore
     222: areturn
     223: aload_0
     224: getfield      #36                 // Field type:Lorg/hl7/fhir/dstu3/model/Enumeration;
     227: ifnonnull     237
     230: iconst_0
     231: anewarray     #161                // class org/hl7/fhir/dstu3/model/Base
     234: goto          248
     237: iconst_1
     238: anewarray     #161                // class org/hl7/fhir/dstu3/model/Base
     241: dup
     242: iconst_0
     243: aload_0
     244: getfield      #36                 // Field type:Lorg/hl7/fhir/dstu3/model/Enumeration;
     247: aastore
     248: areturn
     249: aload_0
     250: getfield      #41                 // Field category:Ljava/util/List;
     253: ifnonnull     263
     256: iconst_0
     257: anewarray     #161                // class org/hl7/fhir/dstu3/model/Base
     260: goto          287
     263: aload_0
     264: getfield      #41                 // Field category:Ljava/util/List;
     267: aload_0
     268: getfield      #41                 // Field category:Ljava/util/List;
     271: invokeinterface #162,  1          // InterfaceMethod java/util/List.size:()I
     276: anewarray     #161                // class org/hl7/fhir/dstu3/model/Base
     279: invokeinterface #163,  2          // InterfaceMethod java/util/List.toArray:([Ljava/lang/Object;)[Ljava/lang/Object;
     284: checkcast     #164                // class "[Lorg/hl7/fhir/dstu3/model/Base;"
     287: areturn
     288: aload_0
     289: getfield      #46                 // Field criticality:Lorg/hl7/fhir/dstu3/model/Enumeration;
     292: ifnonnull     302
     295: iconst_0
     296: anewarray     #161                // class org/hl7/fhir/dstu3/model/Base
     299: goto          313
     302: iconst_1
     303: anewarray     #161                // class org/hl7/fhir/dstu3/model/Base
     306: dup
     307: iconst_0
     308: aload_0
     309: getfield      #46                 // Field criticality:Lorg/hl7/fhir/dstu3/model/Enumeration;
     312: aastore
     313: areturn
     314: aload_0
     315: getfield      #51                 // Field code:Lorg/hl7/fhir/dstu3/model/CodeableConcept;
     318: ifnonnull     328
     321: iconst_0
     322: anewarray     #161                // class org/hl7/fhir/dstu3/model/Base
     325: goto          339
     328: iconst_1
     329: anewarray     #161                // class org/hl7/fhir/dstu3/model/Base
     332: dup
     333: iconst_0
     334: aload_0
     335: getfield      #51                 // Field code:Lorg/hl7/fhir/dstu3/model/CodeableConcept;
     338: aastore
     339: areturn
     340: aload_0
     341: getfield      #3                  // Field patient:Lorg/hl7/fhir/dstu3/model/Reference;
     344: ifnonnull     354
     347: iconst_0
     348: anewarray     #161                // class org/hl7/fhir/dstu3/model/Base
     351: goto          365
     354: iconst_1
     355: anewarray     #161                // class org/hl7/fhir/dstu3/model/Base
     358: dup
     359: iconst_0
     360: aload_0
     361: getfield      #3                  // Field patient:Lorg/hl7/fhir/dstu3/model/Reference;
     364: aastore
     365: areturn
     366: aload_0
     367: getfield      #63                 // Field onset:Lorg/hl7/fhir/dstu3/model/Type;
     370: ifnonnull     380
     373: iconst_0
     374: anewarray     #161                // class org/hl7/fhir/dstu3/model/Base
     377: goto          391
     380: iconst_1
     381: anewarray     #161                // class org/hl7/fhir/dstu3/model/Base
     384: dup
     385: iconst_0
     386: aload_0
     387: getfield      #63                 // Field onset:Lorg/hl7/fhir/dstu3/model/Type;
     390: aastore
     391: areturn
     392: aload_0
     393: getfield      #88                 // Field assertedDate:Lorg/hl7/fhir/dstu3/model/DateTimeType;
     396: ifnonnull     406
     399: iconst_0
     400: anewarray     #161                // class org/hl7/fhir/dstu3/model/Base
     403: goto          417
     406: iconst_1
     407: anewarray     #161                // class org/hl7/fhir/dstu3/model/Base
     410: dup
     411: iconst_0
     412: aload_0
     413: getfield      #88                 // Field assertedDate:Lorg/hl7/fhir/dstu3/model/DateTimeType;
     416: aastore
     417: areturn
     418: aload_0
     419: getfield      #95                 // Field recorder:Lorg/hl7/fhir/dstu3/model/Reference;
     422: ifnonnull     432
     425: iconst_0
     426: anewarray     #161                // class org/hl7/fhir/dstu3/model/Base
     429: goto          443
     432: iconst_1
     433: anewarray     #161                // class org/hl7/fhir/dstu3/model/Base
     436: dup
     437: iconst_0
     438: aload_0
     439: getfield      #95                 // Field recorder:Lorg/hl7/fhir/dstu3/model/Reference;
     442: aastore
     443: areturn
     444: aload_0
     445: getfield      #98                 // Field asserter:Lorg/hl7/fhir/dstu3/model/Reference;
     448: ifnonnull     458
     451: iconst_0
     452: anewarray     #161                // class org/hl7/fhir/dstu3/model/Base
     455: goto          469
     458: iconst_1
     459: anewarray     #161                // class org/hl7/fhir/dstu3/model/Base
     462: dup
     463: iconst_0
     464: aload_0
     465: getfield      #98                 // Field asserter:Lorg/hl7/fhir/dstu3/model/Reference;
     468: aastore
     469: areturn
     470: aload_0
     471: getfield      #101                // Field lastOccurrence:Lorg/hl7/fhir/dstu3/model/DateTimeType;
     474: ifnonnull     484
     477: iconst_0
     478: anewarray     #161                // class org/hl7/fhir/dstu3/model/Base
     481: goto          495
     484: iconst_1
     485: anewarray     #161                // class org/hl7/fhir/dstu3/model/Base
     488: dup
     489: iconst_0
     490: aload_0
     491: getfield      #101                // Field lastOccurrence:Lorg/hl7/fhir/dstu3/model/DateTimeType;
     494: aastore
     495: areturn
     496: aload_0
     497: getfield      #103                // Field note:Ljava/util/List;
     500: ifnonnull     510
     503: iconst_0
     504: anewarray     #161                // class org/hl7/fhir/dstu3/model/Base
     507: goto          534
     510: aload_0
     511: getfield      #103                // Field note:Ljava/util/List;
     514: aload_0
     515: getfield      #103                // Field note:Ljava/util/List;
     518: invokeinterface #162,  1          // InterfaceMethod java/util/List.size:()I
     523: anewarray     #161                // class org/hl7/fhir/dstu3/model/Base
     526: invokeinterface #163,  2          // InterfaceMethod java/util/List.toArray:([Ljava/lang/Object;)[Ljava/lang/Object;
     531: checkcast     #164                // class "[Lorg/hl7/fhir/dstu3/model/Base;"
     534: areturn
     535: aload_0
     536: getfield      #109                // Field reaction:Ljava/util/List;
     539: ifnonnull     549
     542: iconst_0
     543: anewarray     #161                // class org/hl7/fhir/dstu3/model/Base
     546: goto          573
     549: aload_0
     550: getfield      #109                // Field reaction:Ljava/util/List;
     553: aload_0
     554: getfield      #109                // Field reaction:Ljava/util/List;
     557: invokeinterface #162,  1          // InterfaceMethod java/util/List.size:()I
     562: anewarray     #161                // class org/hl7/fhir/dstu3/model/Base
     565: invokeinterface #163,  2          // InterfaceMethod java/util/List.toArray:([Ljava/lang/Object;)[Ljava/lang/Object;
     570: checkcast     #164                // class "[Lorg/hl7/fhir/dstu3/model/Base;"
     573: areturn
     574: aload_0
     575: iload_1
     576: aload_2
     577: iload_3
     578: invokespecial #165                // Method org/hl7/fhir/dstu3/model/DomainResource.getProperty:(ILjava/lang/String;Z)[Lorg/hl7/fhir/dstu3/model/Base;
     581: areturn

  public org.hl7.fhir.dstu3.model.Base setProperty(int, java.lang.String, org.hl7.fhir.dstu3.model.Base) throws org.hl7.fhir.exceptions.FHIRException;
    Code:
       0: iload_1
       1: lookupswitch  { // 15
           -1618432855: 132
           -1608054609: 259
            -867509719: 379
            -842509843: 175
            -799233858: 329
            -791418107: 296
            -462853915: 149
            -373242253: 340
            -174231629: 318
               3059181: 285
               3387378: 362
               3575610: 201
              50511102: 227
             105901603: 307
            1896977671: 351
               default: 395
          }
     132: aload_0
     133: invokevirtual #14                 // Method getIdentifier:()Ljava/util/List;
     136: aload_0
     137: aload_3
     138: invokevirtual #166                // Method castToIdentifier:(Lorg/hl7/fhir/dstu3/model/Base;)Lorg/hl7/fhir/dstu3/model/Identifier;
     141: invokeinterface #13,  2           // InterfaceMethod java/util/List.add:(Ljava/lang/Object;)Z
     146: pop
     147: aload_3
     148: areturn
     149: new           #25                 // class org/hl7/fhir/dstu3/model/AllergyIntolerance$AllergyIntoleranceClinicalStatusEnumFactory
     152: dup
     153: invokespecial #26                 // Method org/hl7/fhir/dstu3/model/AllergyIntolerance$AllergyIntoleranceClinicalStatusEnumFactory."<init>":()V
     156: aload_0
     157: aload_3
     158: invokevirtual #167                // Method castToCode:(Lorg/hl7/fhir/dstu3/model/Base;)Lorg/hl7/fhir/dstu3/model/CodeType;
     161: invokevirtual #168                // Method org/hl7/fhir/dstu3/model/AllergyIntolerance$AllergyIntoleranceClinicalStatusEnumFactory.fromType:(Lorg/hl7/fhir/dstu3/model/Base;)Lorg/hl7/fhir/dstu3/model/Enumeration;
     164: astore_3
     165: aload_0
     166: aload_3
     167: checkcast     #24                 // class org/hl7/fhir/dstu3/model/Enumeration
     170: putfield      #18                 // Field clinicalStatus:Lorg/hl7/fhir/dstu3/model/Enumeration;
     173: aload_3
     174: areturn
     175: new           #33                 // class org/hl7/fhir/dstu3/model/AllergyIntolerance$AllergyIntoleranceVerificationStatusEnumFactory
     178: dup
     179: invokespecial #34                 // Method org/hl7/fhir/dstu3/model/AllergyIntolerance$AllergyIntoleranceVerificationStatusEnumFactory."<init>":()V
     182: aload_0
     183: aload_3
     184: invokevirtual #167                // Method castToCode:(Lorg/hl7/fhir/dstu3/model/Base;)Lorg/hl7/fhir/dstu3/model/CodeType;
     187: invokevirtual #169                // Method org/hl7/fhir/dstu3/model/AllergyIntolerance$AllergyIntoleranceVerificationStatusEnumFactory.fromType:(Lorg/hl7/fhir/dstu3/model/Base;)Lorg/hl7/fhir/dstu3/model/Enumeration;
     190: astore_3
     191: aload_0
     192: aload_3
     193: checkcast     #24                 // class org/hl7/fhir/dstu3/model/Enumeration
     196: putfield      #2                  // Field verificationStatus:Lorg/hl7/fhir/dstu3/model/Enumeration;
     199: aload_3
     200: areturn
     201: new           #38                 // class org/hl7/fhir/dstu3/model/AllergyIntolerance$AllergyIntoleranceTypeEnumFactory
     204: dup
     205: invokespecial #39                 // Method org/hl7/fhir/dstu3/model/AllergyIntolerance$AllergyIntoleranceTypeEnumFactory."<init>":()V
     208: aload_0
     209: aload_3
     210: invokevirtual #167                // Method castToCode:(Lorg/hl7/fhir/dstu3/model/Base;)Lorg/hl7/fhir/dstu3/model/CodeType;
     213: invokevirtual #170                // Method org/hl7/fhir/dstu3/model/AllergyIntolerance$AllergyIntoleranceTypeEnumFactory.fromType:(Lorg/hl7/fhir/dstu3/model/Base;)Lorg/hl7/fhir/dstu3/model/Enumeration;
     216: astore_3
     217: aload_0
     218: aload_3
     219: checkcast     #24                 // class org/hl7/fhir/dstu3/model/Enumeration
     222: putfield      #36                 // Field type:Lorg/hl7/fhir/dstu3/model/Enumeration;
     225: aload_3
     226: areturn
     227: new           #42                 // class org/hl7/fhir/dstu3/model/AllergyIntolerance$AllergyIntoleranceCategoryEnumFactory
     230: dup
     231: invokespecial #43                 // Method org/hl7/fhir/dstu3/model/AllergyIntolerance$AllergyIntoleranceCategoryEnumFactory."<init>":()V
     234: aload_0
     235: aload_3
     236: invokevirtual #167                // Method castToCode:(Lorg/hl7/fhir/dstu3/model/Base;)Lorg/hl7/fhir/dstu3/model/CodeType;
     239: invokevirtual #171                // Method org/hl7/fhir/dstu3/model/AllergyIntolerance$AllergyIntoleranceCategoryEnumFactory.fromType:(Lorg/hl7/fhir/dstu3/model/Base;)Lorg/hl7/fhir/dstu3/model/Enumeration;
     242: astore_3
     243: aload_0
     244: invokevirtual #172                // Method getCategory:()Ljava/util/List;
     247: aload_3
     248: checkcast     #24                 // class org/hl7/fhir/dstu3/model/Enumeration
     251: invokeinterface #13,  2           // InterfaceMethod java/util/List.add:(Ljava/lang/Object;)Z
     256: pop
     257: aload_3
     258: areturn
     259: new           #48                 // class org/hl7/fhir/dstu3/model/AllergyIntolerance$AllergyIntoleranceCriticalityEnumFactory
     262: dup
     263: invokespecial #49                 // Method org/hl7/fhir/dstu3/model/AllergyIntolerance$AllergyIntoleranceCriticalityEnumFactory."<init>":()V
     266: aload_0
     267: aload_3
     268: invokevirtual #167                // Method castToCode:(Lorg/hl7/fhir/dstu3/model/Base;)Lorg/hl7/fhir/dstu3/model/CodeType;
     271: invokevirtual #173                // Method org/hl7/fhir/dstu3/model/AllergyIntolerance$AllergyIntoleranceCriticalityEnumFactory.fromType:(Lorg/hl7/fhir/dstu3/model/Base;)Lorg/hl7/fhir/dstu3/model/Enumeration;
     274: astore_3
     275: aload_0
     276: aload_3
     277: checkcast     #24                 // class org/hl7/fhir/dstu3/model/Enumeration
     280: putfield      #46                 // Field criticality:Lorg/hl7/fhir/dstu3/model/Enumeration;
     283: aload_3
     284: areturn
     285: aload_0
     286: aload_0
     287: aload_3
     288: invokevirtual #174                // Method castToCodeableConcept:(Lorg/hl7/fhir/dstu3/model/Base;)Lorg/hl7/fhir/dstu3/model/CodeableConcept;
     291: putfield      #51                 // Field code:Lorg/hl7/fhir/dstu3/model/CodeableConcept;
     294: aload_3
     295: areturn
     296: aload_0
     297: aload_0
     298: aload_3
     299: invokevirtual #175                // Method castToReference:(Lorg/hl7/fhir/dstu3/model/Base;)Lorg/hl7/fhir/dstu3/model/Reference;
     302: putfield      #3                  // Field patient:Lorg/hl7/fhir/dstu3/model/Reference;
     305: aload_3
     306: areturn
     307: aload_0
     308: aload_0
     309: aload_3
     310: invokevirtual #176                // Method castToType:(Lorg/hl7/fhir/dstu3/model/Base;)Lorg/hl7/fhir/dstu3/model/Type;
     313: putfield      #63                 // Field onset:Lorg/hl7/fhir/dstu3/model/Type;
     316: aload_3
     317: areturn
     318: aload_0
     319: aload_0
     320: aload_3
     321: invokevirtual #177                // Method castToDateTime:(Lorg/hl7/fhir/dstu3/model/Base;)Lorg/hl7/fhir/dstu3/model/DateTimeType;
     324: putfield      #88                 // Field assertedDate:Lorg/hl7/fhir/dstu3/model/DateTimeType;
     327: aload_3
     328: areturn
     329: aload_0
     330: aload_0
     331: aload_3
     332: invokevirtual #175                // Method castToReference:(Lorg/hl7/fhir/dstu3/model/Base;)Lorg/hl7/fhir/dstu3/model/Reference;
     335: putfield      #95                 // Field recorder:Lorg/hl7/fhir/dstu3/model/Reference;
     338: aload_3
     339: areturn
     340: aload_0
     341: aload_0
     342: aload_3
     343: invokevirtual #175                // Method castToReference:(Lorg/hl7/fhir/dstu3/model/Base;)Lorg/hl7/fhir/dstu3/model/Reference;
     346: putfield      #98                 // Field asserter:Lorg/hl7/fhir/dstu3/model/Reference;
     349: aload_3
     350: areturn
     351: aload_0
     352: aload_0
     353: aload_3
     354: invokevirtual #177                // Method castToDateTime:(Lorg/hl7/fhir/dstu3/model/Base;)Lorg/hl7/fhir/dstu3/model/DateTimeType;
     357: putfield      #101                // Field lastOccurrence:Lorg/hl7/fhir/dstu3/model/DateTimeType;
     360: aload_3
     361: areturn
     362: aload_0
     363: invokevirtual #107                // Method getNote:()Ljava/util/List;
     366: aload_0
     367: aload_3
     368: invokevirtual #178                // Method castToAnnotation:(Lorg/hl7/fhir/dstu3/model/Base;)Lorg/hl7/fhir/dstu3/model/Annotation;
     371: invokeinterface #13,  2           // InterfaceMethod java/util/List.add:(Ljava/lang/Object;)Z
     376: pop
     377: aload_3
     378: areturn
     379: aload_0
     380: invokevirtual #113                // Method getReaction:()Ljava/util/List;
     383: aload_3
     384: checkcast     #110                // class org/hl7/fhir/dstu3/model/AllergyIntolerance$AllergyIntoleranceReactionComponent
     387: invokeinterface #13,  2           // InterfaceMethod java/util/List.add:(Ljava/lang/Object;)Z
     392: pop
     393: aload_3
     394: areturn
     395: aload_0
     396: iload_1
     397: aload_2
     398: aload_3
     399: invokespecial #179                // Method org/hl7/fhir/dstu3/model/DomainResource.setProperty:(ILjava/lang/String;Lorg/hl7/fhir/dstu3/model/Base;)Lorg/hl7/fhir/dstu3/model/Base;
     402: areturn

  public org.hl7.fhir.dstu3.model.Base setProperty(java.lang.String, org.hl7.fhir.dstu3.model.Base) throws org.hl7.fhir.exceptions.FHIRException;
    Code:
       0: aload_1
       1: ldc           #117                // String identifier
       3: invokevirtual #180                // Method java/lang/String.equals:(Ljava/lang/Object;)Z
       6: ifeq          27
       9: aload_0
      10: invokevirtual #14                 // Method getIdentifier:()Ljava/util/List;
      13: aload_0
      14: aload_2
      15: invokevirtual #166                // Method castToIdentifier:(Lorg/hl7/fhir/dstu3/model/Base;)Lorg/hl7/fhir/dstu3/model/Identifier;
      18: invokeinterface #13,  2           // InterfaceMethod java/util/List.add:(Ljava/lang/Object;)Z
      23: pop
      24: goto          420
      27: aload_1
      28: ldc           #123                // String clinicalStatus
      30: invokevirtual #180                // Method java/lang/String.equals:(Ljava/lang/Object;)Z
      33: ifeq          63
      36: new           #25                 // class org/hl7/fhir/dstu3/model/AllergyIntolerance$AllergyIntoleranceClinicalStatusEnumFactory
      39: dup
      40: invokespecial #26                 // Method org/hl7/fhir/dstu3/model/AllergyIntolerance$AllergyIntoleranceClinicalStatusEnumFactory."<init>":()V
      43: aload_0
      44: aload_2
      45: invokevirtual #167                // Method castToCode:(Lorg/hl7/fhir/dstu3/model/Base;)Lorg/hl7/fhir/dstu3/model/CodeType;
      48: invokevirtual #168                // Method org/hl7/fhir/dstu3/model/AllergyIntolerance$AllergyIntoleranceClinicalStatusEnumFactory.fromType:(Lorg/hl7/fhir/dstu3/model/Base;)Lorg/hl7/fhir/dstu3/model/Enumeration;
      51: astore_2
      52: aload_0
      53: aload_2
      54: checkcast     #24                 // class org/hl7/fhir/dstu3/model/Enumeration
      57: putfield      #18                 // Field clinicalStatus:Lorg/hl7/fhir/dstu3/model/Enumeration;
      60: goto          420
      63: aload_1
      64: ldc           #127                // String verificationStatus
      66: invokevirtual #180                // Method java/lang/String.equals:(Ljava/lang/Object;)Z
      69: ifeq          99
      72: new           #33                 // class org/hl7/fhir/dstu3/model/AllergyIntolerance$AllergyIntoleranceVerificationStatusEnumFactory
      75: dup
      76: invokespecial #34                 // Method org/hl7/fhir/dstu3/model/AllergyIntolerance$AllergyIntoleranceVerificationStatusEnumFactory."<init>":()V
      79: aload_0
      80: aload_2
      81: invokevirtual #167                // Method castToCode:(Lorg/hl7/fhir/dstu3/model/Base;)Lorg/hl7/fhir/dstu3/model/CodeType;
      84: invokevirtual #169                // Method org/hl7/fhir/dstu3/model/AllergyIntolerance$AllergyIntoleranceVerificationStatusEnumFactory.fromType:(Lorg/hl7/fhir/dstu3/model/Base;)Lorg/hl7/fhir/dstu3/model/Enumeration;
      87: astore_2
      88: aload_0
      89: aload_2
      90: checkcast     #24                 // class org/hl7/fhir/dstu3/model/Enumeration
      93: putfield      #2                  // Field verificationStatus:Lorg/hl7/fhir/dstu3/model/Enumeration;
      96: goto          420
      99: aload_1
     100: ldc           #129                // String type
     102: invokevirtual #180                // Method java/lang/String.equals:(Ljava/lang/Object;)Z
     105: ifeq          135
     108: new           #38                 // class org/hl7/fhir/dstu3/model/AllergyIntolerance$AllergyIntoleranceTypeEnumFactory
     111: dup
     112: invokespecial #39                 // Method org/hl7/fhir/dstu3/model/AllergyIntolerance$AllergyIntoleranceTypeEnumFactory."<init>":()V
     115: aload_0
     116: aload_2
     117: invokevirtual #167                // Method castToCode:(Lorg/hl7/fhir/dstu3/model/Base;)Lorg/hl7/fhir/dstu3/model/CodeType;
     120: invokevirtual #170                // Method org/hl7/fhir/dstu3/model/AllergyIntolerance$AllergyIntoleranceTypeEnumFactory.fromType:(Lorg/hl7/fhir/dstu3/model/Base;)Lorg/hl7/fhir/dstu3/model/Enumeration;
     123: astore_2
     124: aload_0
     125: aload_2
     126: checkcast     #24                 // class org/hl7/fhir/dstu3/model/Enumeration
     129: putfield      #36                 // Field type:Lorg/hl7/fhir/dstu3/model/Enumeration;
     132: goto          420
     135: aload_1
     136: ldc           #131                // String category
     138: invokevirtual #180                // Method java/lang/String.equals:(Ljava/lang/Object;)Z
     141: ifeq          177
     144: new           #42                 // class org/hl7/fhir/dstu3/model/AllergyIntolerance$AllergyIntoleranceCategoryEnumFactory
     147: dup
     148: invokespecial #43                 // Method org/hl7/fhir/dstu3/model/AllergyIntolerance$AllergyIntoleranceCategoryEnumFactory."<init>":()V
     151: aload_0
     152: aload_2
     153: invokevirtual #167                // Method castToCode:(Lorg/hl7/fhir/dstu3/model/Base;)Lorg/hl7/fhir/dstu3/model/CodeType;
     156: invokevirtual #171                // Method org/hl7/fhir/dstu3/model/AllergyIntolerance$AllergyIntoleranceCategoryEnumFactory.fromType:(Lorg/hl7/fhir/dstu3/model/Base;)Lorg/hl7/fhir/dstu3/model/Enumeration;
     159: astore_2
     160: aload_0
     161: invokevirtual #172                // Method getCategory:()Ljava/util/List;
     164: aload_2
     165: checkcast     #24                 // class org/hl7/fhir/dstu3/model/Enumeration
     168: invokeinterface #13,  2           // InterfaceMethod java/util/List.add:(Ljava/lang/Object;)Z
     173: pop
     174: goto          420
     177: aload_1
     178: ldc           #133                // String criticality
     180: invokevirtual #180                // Method java/lang/String.equals:(Ljava/lang/Object;)Z
     183: ifeq          213
     186: new           #48                 // class org/hl7/fhir/dstu3/model/AllergyIntolerance$AllergyIntoleranceCriticalityEnumFactory
     189: dup
     190: invokespecial #49                 // Method org/hl7/fhir/dstu3/model/AllergyIntolerance$AllergyIntoleranceCriticalityEnumFactory."<init>":()V
     193: aload_0
     194: aload_2
     195: invokevirtual #167                // Method castToCode:(Lorg/hl7/fhir/dstu3/model/Base;)Lorg/hl7/fhir/dstu3/model/CodeType;
     198: invokevirtual #173                // Method org/hl7/fhir/dstu3/model/AllergyIntolerance$AllergyIntoleranceCriticalityEnumFactory.fromType:(Lorg/hl7/fhir/dstu3/model/Base;)Lorg/hl7/fhir/dstu3/model/Enumeration;
     201: astore_2
     202: aload_0
     203: aload_2
     204: checkcast     #24                 // class org/hl7/fhir/dstu3/model/Enumeration
     207: putfield      #46                 // Field criticality:Lorg/hl7/fhir/dstu3/model/Enumeration;
     210: goto          420
     213: aload_1
     214: ldc           #124                // String code
     216: invokevirtual #180                // Method java/lang/String.equals:(Ljava/lang/Object;)Z
     219: ifeq          234
     222: aload_0
     223: aload_0
     224: aload_2
     225: invokevirtual #174                // Method castToCodeableConcept:(Lorg/hl7/fhir/dstu3/model/Base;)Lorg/hl7/fhir/dstu3/model/CodeableConcept;
     228: putfield      #51                 // Field code:Lorg/hl7/fhir/dstu3/model/CodeableConcept;
     231: goto          420
     234: aload_1
     235: ldc           #137                // String patient
     237: invokevirtual #180                // Method java/lang/String.equals:(Ljava/lang/Object;)Z
     240: ifeq          255
     243: aload_0
     244: aload_0
     245: aload_2
     246: invokevirtual #175                // Method castToReference:(Lorg/hl7/fhir/dstu3/model/Base;)Lorg/hl7/fhir/dstu3/model/Reference;
     249: putfield      #3                  // Field patient:Lorg/hl7/fhir/dstu3/model/Reference;
     252: goto          420
     255: aload_1
     256: ldc           #140                // String onset[x]
     258: invokevirtual #180                // Method java/lang/String.equals:(Ljava/lang/Object;)Z
     261: ifeq          276
     264: aload_0
     265: aload_0
     266: aload_2
     267: invokevirtual #176                // Method castToType:(Lorg/hl7/fhir/dstu3/model/Base;)Lorg/hl7/fhir/dstu3/model/Type;
     270: putfield      #63                 // Field onset:Lorg/hl7/fhir/dstu3/model/Type;
     273: goto          420
     276: aload_1
     277: ldc           #143                // String assertedDate
     279: invokevirtual #180                // Method java/lang/String.equals:(Ljava/lang/Object;)Z
     282: ifeq          297
     285: aload_0
     286: aload_0
     287: aload_2
     288: invokevirtual #177                // Method castToDateTime:(Lorg/hl7/fhir/dstu3/model/Base;)Lorg/hl7/fhir/dstu3/model/DateTimeType;
     291: putfield      #88                 // Field assertedDate:Lorg/hl7/fhir/dstu3/model/DateTimeType;
     294: goto          420
     297: aload_1
     298: ldc           #146                // String recorder
     300: invokevirtual #180                // Method java/lang/String.equals:(Ljava/lang/Object;)Z
     303: ifeq          318
     306: aload_0
     307: aload_0
     308: aload_2
     309: invokevirtual #175                // Method castToReference:(Lorg/hl7/fhir/dstu3/model/Base;)Lorg/hl7/fhir/dstu3/model/Reference;
     312: putfield      #95                 // Field recorder:Lorg/hl7/fhir/dstu3/model/Reference;
     315: goto          420
     318: aload_1
     319: ldc           #149                // String asserter
     321: invokevirtual #180                // Method java/lang/String.equals:(Ljava/lang/Object;)Z
     324: ifeq          339
     327: aload_0
     328: aload_0
     329: aload_2
     330: invokevirtual #175                // Method castToReference:(Lorg/hl7/fhir/dstu3/model/Base;)Lorg/hl7/fhir/dstu3/model/Reference;
     333: putfield      #98                 // Field asserter:Lorg/hl7/fhir/dstu3/model/Reference;
     336: goto          420
     339: aload_1
     340: ldc           #152                // String lastOccurrence
     342: invokevirtual #180                // Method java/lang/String.equals:(Ljava/lang/Object;)Z
     345: ifeq          360
     348: aload_0
     349: aload_0
     350: aload_2
     351: invokevirtual #177                // Method castToDateTime:(Lorg/hl7/fhir/dstu3/model/Base;)Lorg/hl7/fhir/dstu3/model/DateTimeType;
     354: putfield      #101                // Field lastOccurrence:Lorg/hl7/fhir/dstu3/model/DateTimeType;
     357: goto          420
     360: aload_1
     361: ldc           #154                // String note
     363: invokevirtual #180                // Method java/lang/String.equals:(Ljava/lang/Object;)Z
     366: ifeq          387
     369: aload_0
     370: invokevirtual #107                // Method getNote:()Ljava/util/List;
     373: aload_0
     374: aload_2
     375: invokevirtual #178                // Method castToAnnotation:(Lorg/hl7/fhir/dstu3/model/Base;)Lorg/hl7/fhir/dstu3/model/Annotation;
     378: invokeinterface #13,  2           // InterfaceMethod java/util/List.add:(Ljava/lang/Object;)Z
     383: pop
     384: goto          420
     387: aload_1
     388: ldc           #157                // String reaction
     390: invokevirtual #180                // Method java/lang/String.equals:(Ljava/lang/Object;)Z
     393: ifeq          413
     396: aload_0
     397: invokevirtual #113                // Method getReaction:()Ljava/util/List;
     400: aload_2
     401: checkcast     #110                // class org/hl7/fhir/dstu3/model/AllergyIntolerance$AllergyIntoleranceReactionComponent
     404: invokeinterface #13,  2           // InterfaceMethod java/util/List.add:(Ljava/lang/Object;)Z
     409: pop
     410: goto          420
     413: aload_0
     414: aload_1
     415: aload_2
     416: invokespecial #181                // Method org/hl7/fhir/dstu3/model/DomainResource.setProperty:(Ljava/lang/String;Lorg/hl7/fhir/dstu3/model/Base;)Lorg/hl7/fhir/dstu3/model/Base;
     419: areturn
     420: aload_2
     421: areturn

  public org.hl7.fhir.dstu3.model.Base makeProperty(int, java.lang.String) throws org.hl7.fhir.exceptions.FHIRException;
    Code:
       0: iload_1
       1: lookupswitch  { // 16
           -1886216323: 180
           -1618432855: 140
           -1608054609: 165
            -867509719: 215
            -842509843: 150
            -799233858: 195
            -791418107: 175
            -462853915: 145
            -373242253: 200
            -174231629: 190
               3059181: 170
               3387378: 210
               3575610: 155
              50511102: 160
             105901603: 185
            1896977671: 205
               default: 220
          }
     140: aload_0
     141: invokevirtual #16                 // Method addIdentifier:()Lorg/hl7/fhir/dstu3/model/Identifier;
     144: areturn
     145: aload_0
     146: invokevirtual #182                // Method getClinicalStatusElement:()Lorg/hl7/fhir/dstu3/model/Enumeration;
     149: areturn
     150: aload_0
     151: invokevirtual #183                // Method getVerificationStatusElement:()Lorg/hl7/fhir/dstu3/model/Enumeration;
     154: areturn
     155: aload_0
     156: invokevirtual #184                // Method getTypeElement:()Lorg/hl7/fhir/dstu3/model/Enumeration;
     159: areturn
     160: aload_0
     161: invokevirtual #185                // Method addCategoryElement:()Lorg/hl7/fhir/dstu3/model/Enumeration;
     164: areturn
     165: aload_0
     166: invokevirtual #186                // Method getCriticalityElement:()Lorg/hl7/fhir/dstu3/model/Enumeration;
     169: areturn
     170: aload_0
     171: invokevirtual #187                // Method getCode:()Lorg/hl7/fhir/dstu3/model/CodeableConcept;
     174: areturn
     175: aload_0
     176: invokevirtual #188                // Method getPatient:()Lorg/hl7/fhir/dstu3/model/Reference;
     179: areturn
     180: aload_0
     181: invokevirtual #189                // Method getOnset:()Lorg/hl7/fhir/dstu3/model/Type;
     184: areturn
     185: aload_0
     186: invokevirtual #189                // Method getOnset:()Lorg/hl7/fhir/dstu3/model/Type;
     189: areturn
     190: aload_0
     191: invokevirtual #190                // Method getAssertedDateElement:()Lorg/hl7/fhir/dstu3/model/DateTimeType;
     194: areturn
     195: aload_0
     196: invokevirtual #191                // Method getRecorder:()Lorg/hl7/fhir/dstu3/model/Reference;
     199: areturn
     200: aload_0
     201: invokevirtual #192                // Method getAsserter:()Lorg/hl7/fhir/dstu3/model/Reference;
     204: areturn
     205: aload_0
     206: invokevirtual #193                // Method getLastOccurrenceElement:()Lorg/hl7/fhir/dstu3/model/DateTimeType;
     209: areturn
     210: aload_0
     211: invokevirtual #108                // Method addNote:()Lorg/hl7/fhir/dstu3/model/Annotation;
     214: areturn
     215: aload_0
     216: invokevirtual #114                // Method addReaction:()Lorg/hl7/fhir/dstu3/model/AllergyIntolerance$AllergyIntoleranceReactionComponent;
     219: areturn
     220: aload_0
     221: iload_1
     222: aload_2
     223: invokespecial #194                // Method org/hl7/fhir/dstu3/model/DomainResource.makeProperty:(ILjava/lang/String;)Lorg/hl7/fhir/dstu3/model/Base;
     226: areturn

  public java.lang.String[] getTypesForProperty(int, java.lang.String) throws org.hl7.fhir.exceptions.FHIRException;
    Code:
       0: iload_1
       1: lookupswitch  { // 15
           -1618432855: 132
           -1608054609: 182
            -867509719: 292
            -842509843: 152
            -799233858: 252
            -791418107: 202
            -462853915: 142
            -373242253: 262
            -174231629: 242
               3059181: 192
               3387378: 282
               3575610: 162
              50511102: 172
             105901603: 212
            1896977671: 272
               default: 297
          }
     132: iconst_1
     133: anewarray     #195                // class java/lang/String
     136: dup
     137: iconst_0
     138: ldc           #118                // String Identifier
     140: aastore
     141: areturn
     142: iconst_1
     143: anewarray     #195                // class java/lang/String
     146: dup
     147: iconst_0
     148: ldc           #124                // String code
     150: aastore
     151: areturn
     152: iconst_1
     153: anewarray     #195                // class java/lang/String
     156: dup
     157: iconst_0
     158: ldc           #124                // String code
     160: aastore
     161: areturn
     162: iconst_1
     163: anewarray     #195                // class java/lang/String
     166: dup
     167: iconst_0
     168: ldc           #124                // String code
     170: aastore
     171: areturn
     172: iconst_1
     173: anewarray     #195                // class java/lang/String
     176: dup
     177: iconst_0
     178: ldc           #124                // String code
     180: aastore
     181: areturn
     182: iconst_1
     183: anewarray     #195                // class java/lang/String
     186: dup
     187: iconst_0
     188: ldc           #124                // String code
     190: aastore
     191: areturn
     192: iconst_1
     193: anewarray     #195                // class java/lang/String
     196: dup
     197: iconst_0
     198: ldc           #135                // String CodeableConcept
     200: aastore
     201: areturn
     202: iconst_1
     203: anewarray     #195                // class java/lang/String
     206: dup
     207: iconst_0
     208: ldc           #196                // String Reference
     210: aastore
     211: areturn
     212: iconst_5
     213: anewarray     #195                // class java/lang/String
     216: dup
     217: iconst_0
     218: ldc           #144                // String dateTime
     220: aastore
     221: dup
     222: iconst_1
     223: ldc           #197                // String Age
     225: aastore
     226: dup
     227: iconst_2
     228: ldc           #198                // String Period
     230: aastore
     231: dup
     232: iconst_3
     233: ldc           #199                // String Range
     235: aastore
     236: dup
     237: iconst_4
     238: ldc           #200                // String string
     240: aastore
     241: areturn
     242: iconst_1
     243: anewarray     #195                // class java/lang/String
     246: dup
     247: iconst_0
     248: ldc           #144                // String dateTime
     250: aastore
     251: areturn
     252: iconst_1
     253: anewarray     #195                // class java/lang/String
     256: dup
     257: iconst_0
     258: ldc           #196                // String Reference
     260: aastore
     261: areturn
     262: iconst_1
     263: anewarray     #195                // class java/lang/String
     266: dup
     267: iconst_0
     268: ldc           #196                // String Reference
     270: aastore
     271: areturn
     272: iconst_1
     273: anewarray     #195                // class java/lang/String
     276: dup
     277: iconst_0
     278: ldc           #144                // String dateTime
     280: aastore
     281: areturn
     282: iconst_1
     283: anewarray     #195                // class java/lang/String
     286: dup
     287: iconst_0
     288: ldc           #155                // String Annotation
     290: aastore
     291: areturn
     292: iconst_0
     293: anewarray     #195                // class java/lang/String
     296: areturn
     297: aload_0
     298: iload_1
     299: aload_2
     300: invokespecial #201                // Method org/hl7/fhir/dstu3/model/DomainResource.getTypesForProperty:(ILjava/lang/String;)[Ljava/lang/String;
     303: areturn

  public org.hl7.fhir.dstu3.model.Base addChild(java.lang.String) throws org.hl7.fhir.exceptions.FHIRException;
    Code:
       0: aload_1
       1: ldc           #117                // String identifier
       3: invokevirtual #180                // Method java/lang/String.equals:(Ljava/lang/Object;)Z
       6: ifeq          14
       9: aload_0
      10: invokevirtual #16                 // Method addIdentifier:()Lorg/hl7/fhir/dstu3/model/Identifier;
      13: areturn
      14: aload_1
      15: ldc           #123                // String clinicalStatus
      17: invokevirtual #180                // Method java/lang/String.equals:(Ljava/lang/Object;)Z
      20: ifeq          33
      23: new           #65                 // class org/hl7/fhir/exceptions/FHIRException
      26: dup
      27: ldc           #202                // String Cannot call addChild on a primitive type AllergyIntolerance.clinicalStatus
      29: invokespecial #74                 // Method org/hl7/fhir/exceptions/FHIRException."<init>":(Ljava/lang/String;)V
      32: athrow
      33: aload_1
      34: ldc           #127                // String verificationStatus
      36: invokevirtual #180                // Method java/lang/String.equals:(Ljava/lang/Object;)Z
      39: ifeq          52
      42: new           #65                 // class org/hl7/fhir/exceptions/FHIRException
      45: dup
      46: ldc           #203                // String Cannot call addChild on a primitive type AllergyIntolerance.verificationStatus
      48: invokespecial #74                 // Method org/hl7/fhir/exceptions/FHIRException."<init>":(Ljava/lang/String;)V
      51: athrow
      52: aload_1
      53: ldc           #129                // String type
      55: invokevirtual #180                // Method java/lang/String.equals:(Ljava/lang/Object;)Z
      58: ifeq          71
      61: new           #65                 // class org/hl7/fhir/exceptions/FHIRException
      64: dup
      65: ldc           #204                // String Cannot call addChild on a primitive type AllergyIntolerance.type
      67: invokespecial #74                 // Method org/hl7/fhir/exceptions/FHIRException."<init>":(Ljava/lang/String;)V
      70: athrow
      71: aload_1
      72: ldc           #131                // String category
      74: invokevirtual #180                // Method java/lang/String.equals:(Ljava/lang/Object;)Z
      77: ifeq          90
      80: new           #65                 // class org/hl7/fhir/exceptions/FHIRException
      83: dup
      84: ldc           #205                // String Cannot call addChild on a primitive type AllergyIntolerance.category
      86: invokespecial #74                 // Method org/hl7/fhir/exceptions/FHIRException."<init>":(Ljava/lang/String;)V
      89: athrow
      90: aload_1
      91: ldc           #133                // String criticality
      93: invokevirtual #180                // Method java/lang/String.equals:(Ljava/lang/Object;)Z
      96: ifeq          109
      99: new           #65                 // class org/hl7/fhir/exceptions/FHIRException
     102: dup
     103: ldc           #206                // String Cannot call addChild on a primitive type AllergyIntolerance.criticality
     105: invokespecial #74                 // Method org/hl7/fhir/exceptions/FHIRException."<init>":(Ljava/lang/String;)V
     108: athrow
     109: aload_1
     110: ldc           #124                // String code
     112: invokevirtual #180                // Method java/lang/String.equals:(Ljava/lang/Object;)Z
     115: ifeq          134
     118: aload_0
     119: new           #53                 // class org/hl7/fhir/dstu3/model/CodeableConcept
     122: dup
     123: invokespecial #54                 // Method org/hl7/fhir/dstu3/model/CodeableConcept."<init>":()V
     126: putfield      #51                 // Field code:Lorg/hl7/fhir/dstu3/model/CodeableConcept;
     129: aload_0
     130: getfield      #51                 // Field code:Lorg/hl7/fhir/dstu3/model/CodeableConcept;
     133: areturn
     134: aload_1
     135: ldc           #137                // String patient
     137: invokevirtual #180                // Method java/lang/String.equals:(Ljava/lang/Object;)Z
     140: ifeq          159
     143: aload_0
     144: new           #57                 // class org/hl7/fhir/dstu3/model/Reference
     147: dup
     148: invokespecial #58                 // Method org/hl7/fhir/dstu3/model/Reference."<init>":()V
     151: putfield      #3                  // Field patient:Lorg/hl7/fhir/dstu3/model/Reference;
     154: aload_0
     155: getfield      #3                  // Field patient:Lorg/hl7/fhir/dstu3/model/Reference;
     158: areturn
     159: aload_1
     160: ldc           #207                // String onsetDateTime
     162: invokevirtual #180                // Method java/lang/String.equals:(Ljava/lang/Object;)Z
     165: ifeq          184
     168: aload_0
     169: new           #64                 // class org/hl7/fhir/dstu3/model/DateTimeType
     172: dup
     173: invokespecial #90                 // Method org/hl7/fhir/dstu3/model/DateTimeType."<init>":()V
     176: putfield      #63                 // Field onset:Lorg/hl7/fhir/dstu3/model/Type;
     179: aload_0
     180: getfield      #63                 // Field onset:Lorg/hl7/fhir/dstu3/model/Type;
     183: areturn
     184: aload_1
     185: ldc           #208                // String onsetAge
     187: invokevirtual #180                // Method java/lang/String.equals:(Ljava/lang/Object;)Z
     190: ifeq          209
     193: aload_0
     194: new           #75                 // class org/hl7/fhir/dstu3/model/Age
     197: dup
     198: invokespecial #209                // Method org/hl7/fhir/dstu3/model/Age."<init>":()V
     201: putfield      #63                 // Field onset:Lorg/hl7/fhir/dstu3/model/Type;
     204: aload_0
     205: getfield      #63                 // Field onset:Lorg/hl7/fhir/dstu3/model/Type;
     208: areturn
     209: aload_1
     210: ldc           #210                // String onsetPeriod
     212: invokevirtual #180                // Method java/lang/String.equals:(Ljava/lang/Object;)Z
     215: ifeq          234
     218: aload_0
     219: new           #77                 // class org/hl7/fhir/dstu3/model/Period
     222: dup
     223: invokespecial #211                // Method org/hl7/fhir/dstu3/model/Period."<init>":()V
     226: putfield      #63                 // Field onset:Lorg/hl7/fhir/dstu3/model/Type;
     229: aload_0
     230: getfield      #63                 // Field onset:Lorg/hl7/fhir/dstu3/model/Type;
     233: areturn
     234: aload_1
     235: ldc           #212                // String onsetRange
     237: invokevirtual #180                // Method java/lang/String.equals:(Ljava/lang/Object;)Z
     240: ifeq          259
     243: aload_0
     244: new           #79                 // class org/hl7/fhir/dstu3/model/Range
     247: dup
     248: invokespecial #213                // Method org/hl7/fhir/dstu3/model/Range."<init>":()V
     251: putfield      #63                 // Field onset:Lorg/hl7/fhir/dstu3/model/Type;
     254: aload_0
     255: getfield      #63                 // Field onset:Lorg/hl7/fhir/dstu3/model/Type;
     258: areturn
     259: aload_1
     260: ldc           #214                // String onsetString
     262: invokevirtual #180                // Method java/lang/String.equals:(Ljava/lang/Object;)Z
     265: ifeq          284
     268: aload_0
     269: new           #81                 // class org/hl7/fhir/dstu3/model/StringType
     272: dup
     273: invokespecial #215                // Method org/hl7/fhir/dstu3/model/StringType."<init>":()V
     276: putfield      #63                 // Field onset:Lorg/hl7/fhir/dstu3/model/Type;
     279: aload_0
     280: getfield      #63                 // Field onset:Lorg/hl7/fhir/dstu3/model/Type;
     283: areturn
     284: aload_1
     285: ldc           #143                // String assertedDate
     287: invokevirtual #180                // Method java/lang/String.equals:(Ljava/lang/Object;)Z
     290: ifeq          303
     293: new           #65                 // class org/hl7/fhir/exceptions/FHIRException
     296: dup
     297: ldc           #216                // String Cannot call addChild on a primitive type AllergyIntolerance.assertedDate
     299: invokespecial #74                 // Method org/hl7/fhir/exceptions/FHIRException."<init>":(Ljava/lang/String;)V
     302: athrow
     303: aload_1
     304: ldc           #146                // String recorder
     306: invokevirtual #180                // Method java/lang/String.equals:(Ljava/lang/Object;)Z
     309: ifeq          328
     312: aload_0
     313: new           #57                 // class org/hl7/fhir/dstu3/model/Reference
     316: dup
     317: invokespecial #58                 // Method org/hl7/fhir/dstu3/model/Reference."<init>":()V
     320: putfield      #95                 // Field recorder:Lorg/hl7/fhir/dstu3/model/Reference;
     323: aload_0
     324: getfield      #95                 // Field recorder:Lorg/hl7/fhir/dstu3/model/Reference;
     327: areturn
     328: aload_1
     329: ldc           #149                // String asserter
     331: invokevirtual #180                // Method java/lang/String.equals:(Ljava/lang/Object;)Z
     334: ifeq          353
     337: aload_0
     338: new           #57                 // class org/hl7/fhir/dstu3/model/Reference
     341: dup
     342: invokespecial #58                 // Method org/hl7/fhir/dstu3/model/Reference."<init>":()V
     345: putfield      #98                 // Field asserter:Lorg/hl7/fhir/dstu3/model/Reference;
     348: aload_0
     349: getfield      #98                 // Field asserter:Lorg/hl7/fhir/dstu3/model/Reference;
     352: areturn
     353: aload_1
     354: ldc           #152                // String lastOccurrence
     356: invokevirtual #180                // Method java/lang/String.equals:(Ljava/lang/Object;)Z
     359: ifeq          372
     362: new           #65                 // class org/hl7/fhir/exceptions/FHIRException
     365: dup
     366: ldc           #217                // String Cannot call addChild on a primitive type AllergyIntolerance.lastOccurrence
     368: invokespecial #74                 // Method org/hl7/fhir/exceptions/FHIRException."<init>":(Ljava/lang/String;)V
     371: athrow
     372: aload_1
     373: ldc           #154                // String note
     375: invokevirtual #180                // Method java/lang/String.equals:(Ljava/lang/Object;)Z
     378: ifeq          386
     381: aload_0
     382: invokevirtual #108                // Method addNote:()Lorg/hl7/fhir/dstu3/model/Annotation;
     385: areturn
     386: aload_1
     387: ldc           #157                // String reaction
     389: invokevirtual #180                // Method java/lang/String.equals:(Ljava/lang/Object;)Z
     392: ifeq          400
     395: aload_0
     396: invokevirtual #114                // Method addReaction:()Lorg/hl7/fhir/dstu3/model/AllergyIntolerance$AllergyIntoleranceReactionComponent;
     399: areturn
     400: aload_0
     401: aload_1
     402: invokespecial #218                // Method org/hl7/fhir/dstu3/model/DomainResource.addChild:(Ljava/lang/String;)Lorg/hl7/fhir/dstu3/model/Base;
     405: areturn

  public java.lang.String fhirType();
    Code:
       0: ldc           #219                // String AllergyIntolerance
       2: areturn

  public org.hl7.fhir.dstu3.model.AllergyIntolerance copy();
    Code:
       0: new           #220                // class org/hl7/fhir/dstu3/model/AllergyIntolerance
       3: dup
       4: invokespecial #221                // Method "<init>":()V
       7: astore_1
       8: aload_0
       9: aload_1
      10: invokevirtual #222                // Method copyValues:(Lorg/hl7/fhir/dstu3/model/DomainResource;)V
      13: aload_0
      14: getfield      #4                  // Field identifier:Ljava/util/List;
      17: ifnull        77
      20: aload_1
      21: new           #5                  // class java/util/ArrayList
      24: dup
      25: invokespecial #6                  // Method java/util/ArrayList."<init>":()V
      28: putfield      #4                  // Field identifier:Ljava/util/List;
      31: aload_0
      32: getfield      #4                  // Field identifier:Ljava/util/List;
      35: invokeinterface #7,  1            // InterfaceMethod java/util/List.iterator:()Ljava/util/Iterator;
      40: astore_2
      41: aload_2
      42: invokeinterface #8,  1            // InterfaceMethod java/util/Iterator.hasNext:()Z
      47: ifeq          77
      50: aload_2
      51: invokeinterface #9,  1            // InterfaceMethod java/util/Iterator.next:()Ljava/lang/Object;
      56: checkcast     #10                 // class org/hl7/fhir/dstu3/model/Identifier
      59: astore_3
      60: aload_1
      61: getfield      #4                  // Field identifier:Ljava/util/List;
      64: aload_3
      65: invokevirtual #223                // Method org/hl7/fhir/dstu3/model/Identifier.copy:()Lorg/hl7/fhir/dstu3/model/Identifier;
      68: invokeinterface #13,  2           // InterfaceMethod java/util/List.add:(Ljava/lang/Object;)Z
      73: pop
      74: goto          41
      77: aload_1
      78: aload_0
      79: getfield      #18                 // Field clinicalStatus:Lorg/hl7/fhir/dstu3/model/Enumeration;
      82: ifnonnull     89
      85: aconst_null
      86: goto          96
      89: aload_0
      90: getfield      #18                 // Field clinicalStatus:Lorg/hl7/fhir/dstu3/model/Enumeration;
      93: invokevirtual #224                // Method org/hl7/fhir/dstu3/model/Enumeration.copy:()Lorg/hl7/fhir/dstu3/model/Enumeration;
      96: putfield      #18                 // Field clinicalStatus:Lorg/hl7/fhir/dstu3/model/Enumeration;
      99: aload_1
     100: aload_0
     101: getfield      #2                  // Field verificationStatus:Lorg/hl7/fhir/dstu3/model/Enumeration;
     104: ifnonnull     111
     107: aconst_null
     108: goto          118
     111: aload_0
     112: getfield      #2                  // Field verificationStatus:Lorg/hl7/fhir/dstu3/model/Enumeration;
     115: invokevirtual #224                // Method org/hl7/fhir/dstu3/model/Enumeration.copy:()Lorg/hl7/fhir/dstu3/model/Enumeration;
     118: putfield      #2                  // Field verificationStatus:Lorg/hl7/fhir/dstu3/model/Enumeration;
     121: aload_1
     122: aload_0
     123: getfield      #36                 // Field type:Lorg/hl7/fhir/dstu3/model/Enumeration;
     126: ifnonnull     133
     129: aconst_null
     130: goto          140
     133: aload_0
     134: getfield      #36                 // Field type:Lorg/hl7/fhir/dstu3/model/Enumeration;
     137: invokevirtual #224                // Method org/hl7/fhir/dstu3/model/Enumeration.copy:()Lorg/hl7/fhir/dstu3/model/Enumeration;
     140: putfield      #36                 // Field type:Lorg/hl7/fhir/dstu3/model/Enumeration;
     143: aload_0
     144: getfield      #41                 // Field category:Ljava/util/List;
     147: ifnull        207
     150: aload_1
     151: new           #5                  // class java/util/ArrayList
     154: dup
     155: invokespecial #6                  // Method java/util/ArrayList."<init>":()V
     158: putfield      #41                 // Field category:Ljava/util/List;
     161: aload_0
     162: getfield      #41                 // Field category:Ljava/util/List;
     165: invokeinterface #7,  1            // InterfaceMethod java/util/List.iterator:()Ljava/util/Iterator;
     170: astore_2
     171: aload_2
     172: invokeinterface #8,  1            // InterfaceMethod java/util/Iterator.hasNext:()Z
     177: ifeq          207
     180: aload_2
     181: invokeinterface #9,  1            // InterfaceMethod java/util/Iterator.next:()Ljava/lang/Object;
     186: checkcast     #24                 // class org/hl7/fhir/dstu3/model/Enumeration
     189: astore_3
     190: aload_1
     191: getfield      #41                 // Field category:Ljava/util/List;
     194: aload_3
     195: invokevirtual #224                // Method org/hl7/fhir/dstu3/model/Enumeration.copy:()Lorg/hl7/fhir/dstu3/model/Enumeration;
     198: invokeinterface #13,  2           // InterfaceMethod java/util/List.add:(Ljava/lang/Object;)Z
     203: pop
     204: goto          171
     207: aload_1
     208: aload_0
     209: getfield      #46                 // Field criticality:Lorg/hl7/fhir/dstu3/model/Enumeration;
     212: ifnonnull     219
     215: aconst_null
     216: goto          226
     219: aload_0
     220: getfield      #46                 // Field criticality:Lorg/hl7/fhir/dstu3/model/Enumeration;
     223: invokevirtual #224                // Method org/hl7/fhir/dstu3/model/Enumeration.copy:()Lorg/hl7/fhir/dstu3/model/Enumeration;
     226: putfield      #46                 // Field criticality:Lorg/hl7/fhir/dstu3/model/Enumeration;
     229: aload_1
     230: aload_0
     231: getfield      #51                 // Field code:Lorg/hl7/fhir/dstu3/model/CodeableConcept;
     234: ifnonnull     241
     237: aconst_null
     238: goto          248
     241: aload_0
     242: getfield      #51                 // Field code:Lorg/hl7/fhir/dstu3/model/CodeableConcept;
     245: invokevirtual #225                // Method org/hl7/fhir/dstu3/model/CodeableConcept.copy:()Lorg/hl7/fhir/dstu3/model/CodeableConcept;
     248: putfield      #51                 // Field code:Lorg/hl7/fhir/dstu3/model/CodeableConcept;
     251: aload_1
     252: aload_0
     253: getfield      #3                  // Field patient:Lorg/hl7/fhir/dstu3/model/Reference;
     256: ifnonnull     263
     259: aconst_null
     260: goto          270
     263: aload_0
     264: getfield      #3                  // Field patient:Lorg/hl7/fhir/dstu3/model/Reference;
     267: invokevirtual #226                // Method org/hl7/fhir/dstu3/model/Reference.copy:()Lorg/hl7/fhir/dstu3/model/Reference;
     270: putfield      #3                  // Field patient:Lorg/hl7/fhir/dstu3/model/Reference;
     273: aload_1
     274: aload_0
     275: getfield      #63                 // Field onset:Lorg/hl7/fhir/dstu3/model/Type;
     278: ifnonnull     285
     281: aconst_null
     282: goto          292
     285: aload_0
     286: getfield      #63                 // Field onset:Lorg/hl7/fhir/dstu3/model/Type;
     289: invokevirtual #227                // Method org/hl7/fhir/dstu3/model/Type.copy:()Lorg/hl7/fhir/dstu3/model/Type;
     292: putfield      #63                 // Field onset:Lorg/hl7/fhir/dstu3/model/Type;
     295: aload_1
     296: aload_0
     297: getfield      #88                 // Field assertedDate:Lorg/hl7/fhir/dstu3/model/DateTimeType;
     300: ifnonnull     307
     303: aconst_null
     304: goto          314
     307: aload_0
     308: getfield      #88                 // Field assertedDate:Lorg/hl7/fhir/dstu3/model/DateTimeType;
     311: invokevirtual #228                // Method org/hl7/fhir/dstu3/model/DateTimeType.copy:()Lorg/hl7/fhir/dstu3/model/DateTimeType;
     314: putfield      #88                 // Field assertedDate:Lorg/hl7/fhir/dstu3/model/DateTimeType;
     317: aload_1
     318: aload_0
     319: getfield      #95                 // Field recorder:Lorg/hl7/fhir/dstu3/model/Reference;
     322: ifnonnull     329
     325: aconst_null
     326: goto          336
     329: aload_0
     330: getfield      #95                 // Field recorder:Lorg/hl7/fhir/dstu3/model/Reference;
     333: invokevirtual #226                // Method org/hl7/fhir/dstu3/model/Reference.copy:()Lorg/hl7/fhir/dstu3/model/Reference;
     336: putfield      #95                 // Field recorder:Lorg/hl7/fhir/dstu3/model/Reference;
     339: aload_1
     340: aload_0
     341: getfield      #98                 // Field asserter:Lorg/hl7/fhir/dstu3/model/Reference;
     344: ifnonnull     351
     347: aconst_null
     348: goto          358
     351: aload_0
     352: getfield      #98                 // Field asserter:Lorg/hl7/fhir/dstu3/model/Reference;
     355: invokevirtual #226                // Method org/hl7/fhir/dstu3/model/Reference.copy:()Lorg/hl7/fhir/dstu3/model/Reference;
     358: putfield      #98                 // Field asserter:Lorg/hl7/fhir/dstu3/model/Reference;
     361: aload_1
     362: aload_0
     363: getfield      #101                // Field lastOccurrence:Lorg/hl7/fhir/dstu3/model/DateTimeType;
     366: ifnonnull     373
     369: aconst_null
     370: goto          380
     373: aload_0
     374: getfield      #101                // Field lastOccurrence:Lorg/hl7/fhir/dstu3/model/DateTimeType;
     377: invokevirtual #228                // Method org/hl7/fhir/dstu3/model/DateTimeType.copy:()Lorg/hl7/fhir/dstu3/model/DateTimeType;
     380: putfield      #101                // Field lastOccurrence:Lorg/hl7/fhir/dstu3/model/DateTimeType;
     383: aload_0
     384: getfield      #103                // Field note:Ljava/util/List;
     387: ifnull        447
     390: aload_1
     391: new           #5                  // class java/util/ArrayList
     394: dup
     395: invokespecial #6                  // Method java/util/ArrayList."<init>":()V
     398: putfield      #103                // Field note:Ljava/util/List;
     401: aload_0
     402: getfield      #103                // Field note:Ljava/util/List;
     405: invokeinterface #7,  1            // InterfaceMethod java/util/List.iterator:()Ljava/util/Iterator;
     410: astore_2
     411: aload_2
     412: invokeinterface #8,  1            // InterfaceMethod java/util/Iterator.hasNext:()Z
     417: ifeq          447
     420: aload_2
     421: invokeinterface #9,  1            // InterfaceMethod java/util/Iterator.next:()Ljava/lang/Object;
     426: checkcast     #104                // class org/hl7/fhir/dstu3/model/Annotation
     429: astore_3
     430: aload_1
     431: getfield      #103                // Field note:Ljava/util/List;
     434: aload_3
     435: invokevirtual #229                // Method org/hl7/fhir/dstu3/model/Annotation.copy:()Lorg/hl7/fhir/dstu3/model/Annotation;
     438: invokeinterface #13,  2           // InterfaceMethod java/util/List.add:(Ljava/lang/Object;)Z
     443: pop
     444: goto          411
     447: aload_0
     448: getfield      #109                // Field reaction:Ljava/util/List;
     451: ifnull        511
     454: aload_1
     455: new           #5                  // class java/util/ArrayList
     458: dup
     459: invokespecial #6                  // Method java/util/ArrayList."<init>":()V
     462: putfield      #109                // Field reaction:Ljava/util/List;
     465: aload_0
     466: getfield      #109                // Field reaction:Ljava/util/List;
     469: invokeinterface #7,  1            // InterfaceMethod java/util/List.iterator:()Ljava/util/Iterator;
     474: astore_2
     475: aload_2
     476: invokeinterface #8,  1            // InterfaceMethod java/util/Iterator.hasNext:()Z
     481: ifeq          511
     484: aload_2
     485: invokeinterface #9,  1            // InterfaceMethod java/util/Iterator.next:()Ljava/lang/Object;
     490: checkcast     #110                // class org/hl7/fhir/dstu3/model/AllergyIntolerance$AllergyIntoleranceReactionComponent
     493: astore_3
     494: aload_1
     495: getfield      #109                // Field reaction:Ljava/util/List;
     498: aload_3
     499: invokevirtual #230                // Method org/hl7/fhir/dstu3/model/AllergyIntolerance$AllergyIntoleranceReactionComponent.copy:()Lorg/hl7/fhir/dstu3/model/AllergyIntolerance$AllergyIntoleranceReactionComponent;
     502: invokeinterface #13,  2           // InterfaceMethod java/util/List.add:(Ljava/lang/Object;)Z
     507: pop
     508: goto          475
     511: aload_1
     512: areturn

  protected org.hl7.fhir.dstu3.model.AllergyIntolerance typedCopy();
    Code:
       0: aload_0
       1: invokevirtual #231                // Method copy:()Lorg/hl7/fhir/dstu3/model/AllergyIntolerance;
       4: areturn

  public boolean equalsDeep(org.hl7.fhir.dstu3.model.Base);
    Code:
       0: aload_0
       1: aload_1
       2: invokespecial #232                // Method org/hl7/fhir/dstu3/model/DomainResource.equalsDeep:(Lorg/hl7/fhir/dstu3/model/Base;)Z
       5: ifne          10
       8: iconst_0
       9: ireturn
      10: aload_1
      11: instanceof    #220                // class org/hl7/fhir/dstu3/model/AllergyIntolerance
      14: ifne          19
      17: iconst_0
      18: ireturn
      19: aload_1
      20: checkcast     #220                // class org/hl7/fhir/dstu3/model/AllergyIntolerance
      23: astore_2
      24: aload_0
      25: getfield      #4                  // Field identifier:Ljava/util/List;
      28: aload_2
      29: getfield      #4                  // Field identifier:Ljava/util/List;
      32: iconst_1
      33: invokestatic  #233                // Method compareDeep:(Ljava/util/List;Ljava/util/List;Z)Z
      36: ifeq          253
      39: aload_0
      40: getfield      #18                 // Field clinicalStatus:Lorg/hl7/fhir/dstu3/model/Enumeration;
      43: aload_2
      44: getfield      #18                 // Field clinicalStatus:Lorg/hl7/fhir/dstu3/model/Enumeration;
      47: iconst_1
      48: invokestatic  #234                // Method compareDeep:(Lorg/hl7/fhir/dstu3/model/Base;Lorg/hl7/fhir/dstu3/model/Base;Z)Z
      51: ifeq          253
      54: aload_0
      55: getfield      #2                  // Field verificationStatus:Lorg/hl7/fhir/dstu3/model/Enumeration;
      58: aload_2
      59: getfield      #2                  // Field verificationStatus:Lorg/hl7/fhir/dstu3/model/Enumeration;
      62: iconst_1
      63: invokestatic  #234                // Method compareDeep:(Lorg/hl7/fhir/dstu3/model/Base;Lorg/hl7/fhir/dstu3/model/Base;Z)Z
      66: ifeq          253
      69: aload_0
      70: getfield      #36                 // Field type:Lorg/hl7/fhir/dstu3/model/Enumeration;
      73: aload_2
      74: getfield      #36                 // Field type:Lorg/hl7/fhir/dstu3/model/Enumeration;
      77: iconst_1
      78: invokestatic  #234                // Method compareDeep:(Lorg/hl7/fhir/dstu3/model/Base;Lorg/hl7/fhir/dstu3/model/Base;Z)Z
      81: ifeq          253
      84: aload_0
      85: getfield      #41                 // Field category:Ljava/util/List;
      88: aload_2
      89: getfield      #41                 // Field category:Ljava/util/List;
      92: iconst_1
      93: invokestatic  #233                // Method compareDeep:(Ljava/util/List;Ljava/util/List;Z)Z
      96: ifeq          253
      99: aload_0
     100: getfield      #46                 // Field criticality:Lorg/hl7/fhir/dstu3/model/Enumeration;
     103: aload_2
     104: getfield      #46                 // Field criticality:Lorg/hl7/fhir/dstu3/model/Enumeration;
     107: iconst_1
     108: invokestatic  #234                // Method compareDeep:(Lorg/hl7/fhir/dstu3/model/Base;Lorg/hl7/fhir/dstu3/model/Base;Z)Z
     111: ifeq          253
     114: aload_0
     115: getfield      #51                 // Field code:Lorg/hl7/fhir/dstu3/model/CodeableConcept;
     118: aload_2
     119: getfield      #51                 // Field code:Lorg/hl7/fhir/dstu3/model/CodeableConcept;
     122: iconst_1
     123: invokestatic  #234                // Method compareDeep:(Lorg/hl7/fhir/dstu3/model/Base;Lorg/hl7/fhir/dstu3/model/Base;Z)Z
     126: ifeq          253
     129: aload_0
     130: getfield      #3                  // Field patient:Lorg/hl7/fhir/dstu3/model/Reference;
     133: aload_2
     134: getfield      #3                  // Field patient:Lorg/hl7/fhir/dstu3/model/Reference;
     137: iconst_1
     138: invokestatic  #234                // Method compareDeep:(Lorg/hl7/fhir/dstu3/model/Base;Lorg/hl7/fhir/dstu3/model/Base;Z)Z
     141: ifeq          253
     144: aload_0
     145: getfield      #63                 // Field onset:Lorg/hl7/fhir/dstu3/model/Type;
     148: aload_2
     149: getfield      #63                 // Field onset:Lorg/hl7/fhir/dstu3/model/Type;
     152: iconst_1
     153: invokestatic  #234                // Method compareDeep:(Lorg/hl7/fhir/dstu3/model/Base;Lorg/hl7/fhir/dstu3/model/Base;Z)Z
     156: ifeq          253
     159: aload_0
     160: getfield      #88                 // Field assertedDate:Lorg/hl7/fhir/dstu3/model/DateTimeType;
     163: aload_2
     164: getfield      #88                 // Field assertedDate:Lorg/hl7/fhir/dstu3/model/DateTimeType;
     167: iconst_1
     168: invokestatic  #234                // Method compareDeep:(Lorg/hl7/fhir/dstu3/model/Base;Lorg/hl7/fhir/dstu3/model/Base;Z)Z
     171: ifeq          253
     174: aload_0
     175: getfield      #95                 // Field recorder:Lorg/hl7/fhir/dstu3/model/Reference;
     178: aload_2
     179: getfield      #95                 // Field recorder:Lorg/hl7/fhir/dstu3/model/Reference;
     182: iconst_1
     183: invokestatic  #234                // Method compareDeep:(Lorg/hl7/fhir/dstu3/model/Base;Lorg/hl7/fhir/dstu3/model/Base;Z)Z
     186: ifeq          253
     189: aload_0
     190: getfield      #98                 // Field asserter:Lorg/hl7/fhir/dstu3/model/Reference;
     193: aload_2
     194: getfield      #98                 // Field asserter:Lorg/hl7/fhir/dstu3/model/Reference;
     197: iconst_1
     198: invokestatic  #234                // Method compareDeep:(Lorg/hl7/fhir/dstu3/model/Base;Lorg/hl7/fhir/dstu3/model/Base;Z)Z
     201: ifeq          253
     204: aload_0
     205: getfield      #101                // Field lastOccurrence:Lorg/hl7/fhir/dstu3/model/DateTimeType;
     208: aload_2
     209: getfield      #101                // Field lastOccurrence:Lorg/hl7/fhir/dstu3/model/DateTimeType;
     212: iconst_1
     213: invokestatic  #234                // Method compareDeep:(Lorg/hl7/fhir/dstu3/model/Base;Lorg/hl7/fhir/dstu3/model/Base;Z)Z
     216: ifeq          253
     219: aload_0
     220: getfield      #103                // Field note:Ljava/util/List;
     223: aload_2
     224: getfield      #103                // Field note:Ljava/util/List;
     227: iconst_1
     228: invokestatic  #233                // Method compareDeep:(Ljava/util/List;Ljava/util/List;Z)Z
     231: ifeq          253
     234: aload_0
     235: getfield      #109                // Field reaction:Ljava/util/List;
     238: aload_2
     239: getfield      #109                // Field reaction:Ljava/util/List;
     242: iconst_1
     243: invokestatic  #233                // Method compareDeep:(Ljava/util/List;Ljava/util/List;Z)Z
     246: ifeq          253
     249: iconst_1
     250: goto          254
     253: iconst_0
     254: ireturn

  public boolean equalsShallow(org.hl7.fhir.dstu3.model.Base);
    Code:
       0: aload_0
       1: aload_1
       2: invokespecial #235                // Method org/hl7/fhir/dstu3/model/DomainResource.equalsShallow:(Lorg/hl7/fhir/dstu3/model/Base;)Z
       5: ifne          10
       8: iconst_0
       9: ireturn
      10: aload_1
      11: instanceof    #220                // class org/hl7/fhir/dstu3/model/AllergyIntolerance
      14: ifne          19
      17: iconst_0
      18: ireturn
      19: aload_1
      20: checkcast     #220                // class org/hl7/fhir/dstu3/model/AllergyIntolerance
      23: astore_2
      24: aload_0
      25: getfield      #18                 // Field clinicalStatus:Lorg/hl7/fhir/dstu3/model/Enumeration;
      28: aload_2
      29: getfield      #18                 // Field clinicalStatus:Lorg/hl7/fhir/dstu3/model/Enumeration;
      32: iconst_1
      33: invokestatic  #236                // Method compareValues:(Lorg/hl7/fhir/dstu3/model/PrimitiveType;Lorg/hl7/fhir/dstu3/model/PrimitiveType;Z)Z
      36: ifeq          133
      39: aload_0
      40: getfield      #2                  // Field verificationStatus:Lorg/hl7/fhir/dstu3/model/Enumeration;
      43: aload_2
      44: getfield      #2                  // Field verificationStatus:Lorg/hl7/fhir/dstu3/model/Enumeration;
      47: iconst_1
      48: invokestatic  #236                // Method compareValues:(Lorg/hl7/fhir/dstu3/model/PrimitiveType;Lorg/hl7/fhir/dstu3/model/PrimitiveType;Z)Z
      51: ifeq          133
      54: aload_0
      55: getfield      #36                 // Field type:Lorg/hl7/fhir/dstu3/model/Enumeration;
      58: aload_2
      59: getfield      #36                 // Field type:Lorg/hl7/fhir/dstu3/model/Enumeration;
      62: iconst_1
      63: invokestatic  #236                // Method compareValues:(Lorg/hl7/fhir/dstu3/model/PrimitiveType;Lorg/hl7/fhir/dstu3/model/PrimitiveType;Z)Z
      66: ifeq          133
      69: aload_0
      70: getfield      #41                 // Field category:Ljava/util/List;
      73: aload_2
      74: getfield      #41                 // Field category:Ljava/util/List;
      77: iconst_1
      78: invokestatic  #237                // Method compareValues:(Ljava/util/List;Ljava/util/List;Z)Z
      81: ifeq          133
      84: aload_0
      85: getfield      #46                 // Field criticality:Lorg/hl7/fhir/dstu3/model/Enumeration;
      88: aload_2
      89: getfield      #46                 // Field criticality:Lorg/hl7/fhir/dstu3/model/Enumeration;
      92: iconst_1
      93: invokestatic  #236                // Method compareValues:(Lorg/hl7/fhir/dstu3/model/PrimitiveType;Lorg/hl7/fhir/dstu3/model/PrimitiveType;Z)Z
      96: ifeq          133
      99: aload_0
     100: getfield      #88                 // Field assertedDate:Lorg/hl7/fhir/dstu3/model/DateTimeType;
     103: aload_2
     104: getfield      #88                 // Field assertedDate:Lorg/hl7/fhir/dstu3/model/DateTimeType;
     107: iconst_1
     108: invokestatic  #236                // Method compareValues:(Lorg/hl7/fhir/dstu3/model/PrimitiveType;Lorg/hl7/fhir/dstu3/model/PrimitiveType;Z)Z
     111: ifeq          133
     114: aload_0
     115: getfield      #101                // Field lastOccurrence:Lorg/hl7/fhir/dstu3/model/DateTimeType;
     118: aload_2
     119: getfield      #101                // Field lastOccurrence:Lorg/hl7/fhir/dstu3/model/DateTimeType;
     122: iconst_1
     123: invokestatic  #236                // Method compareValues:(Lorg/hl7/fhir/dstu3/model/PrimitiveType;Lorg/hl7/fhir/dstu3/model/PrimitiveType;Z)Z
     126: ifeq          133
     129: iconst_1
     130: goto          134
     133: iconst_0
     134: ireturn

  public boolean isEmpty();
    Code:
       0: aload_0
       1: invokespecial #238                // Method org/hl7/fhir/dstu3/model/DomainResource.isEmpty:()Z
       4: ifeq          136
       7: bipush        15
       9: anewarray     #239                // class java/lang/Object
      12: dup
      13: iconst_0
      14: aload_0
      15: getfield      #4                  // Field identifier:Ljava/util/List;
      18: aastore
      19: dup
      20: iconst_1
      21: aload_0
      22: getfield      #18                 // Field clinicalStatus:Lorg/hl7/fhir/dstu3/model/Enumeration;
      25: aastore
      26: dup
      27: iconst_2
      28: aload_0
      29: getfield      #2                  // Field verificationStatus:Lorg/hl7/fhir/dstu3/model/Enumeration;
      32: aastore
      33: dup
      34: iconst_3
      35: aload_0
      36: getfield      #36                 // Field type:Lorg/hl7/fhir/dstu3/model/Enumeration;
      39: aastore
      40: dup
      41: iconst_4
      42: aload_0
      43: getfield      #41                 // Field category:Ljava/util/List;
      46: aastore
      47: dup
      48: iconst_5
      49: aload_0
      50: getfield      #46                 // Field criticality:Lorg/hl7/fhir/dstu3/model/Enumeration;
      53: aastore
      54: dup
      55: bipush        6
      57: aload_0
      58: getfield      #51                 // Field code:Lorg/hl7/fhir/dstu3/model/CodeableConcept;
      61: aastore
      62: dup
      63: bipush        7
      65: aload_0
      66: getfield      #3                  // Field patient:Lorg/hl7/fhir/dstu3/model/Reference;
      69: aastore
      70: dup
      71: bipush        8
      73: aload_0
      74: getfield      #63                 // Field onset:Lorg/hl7/fhir/dstu3/model/Type;
      77: aastore
      78: dup
      79: bipush        9
      81: aload_0
      82: getfield      #88                 // Field assertedDate:Lorg/hl7/fhir/dstu3/model/DateTimeType;
      85: aastore
      86: dup
      87: bipush        10
      89: aload_0
      90: getfield      #95                 // Field recorder:Lorg/hl7/fhir/dstu3/model/Reference;
      93: aastore
      94: dup
      95: bipush        11
      97: aload_0
      98: getfield      #98                 // Field asserter:Lorg/hl7/fhir/dstu3/model/Reference;
     101: aastore
     102: dup
     103: bipush        12
     105: aload_0
     106: getfield      #101                // Field lastOccurrence:Lorg/hl7/fhir/dstu3/model/DateTimeType;
     109: aastore
     110: dup
     111: bipush        13
     113: aload_0
     114: getfield      #103                // Field note:Ljava/util/List;
     117: aastore
     118: dup
     119: bipush        14
     121: aload_0
     122: getfield      #109                // Field reaction:Ljava/util/List;
     125: aastore
     126: invokestatic  #240                // Method ca/uhn/fhir/util/ElementUtil.isEmpty:([Ljava/lang/Object;)Z
     129: ifeq          136
     132: iconst_1
     133: goto          137
     136: iconst_0
     137: ireturn

  public org.hl7.fhir.dstu3.model.ResourceType getResourceType();
    Code:
       0: getstatic     #241                // Field org/hl7/fhir/dstu3/model/ResourceType.AllergyIntolerance:Lorg/hl7/fhir/dstu3/model/ResourceType;
       3: areturn

  public org.hl7.fhir.dstu3.model.DomainResource copy();
    Code:
       0: aload_0
       1: invokevirtual #231                // Method copy:()Lorg/hl7/fhir/dstu3/model/AllergyIntolerance;
       4: areturn

  public org.hl7.fhir.dstu3.model.Resource copy();
    Code:
       0: aload_0
       1: invokevirtual #231                // Method copy:()Lorg/hl7/fhir/dstu3/model/AllergyIntolerance;
       4: areturn

  static {};
    Code:
       0: new           #242                // class ca/uhn/fhir/rest/gclient/TokenClientParam
       3: dup
       4: ldc           #243                // String severity
       6: invokespecial #244                // Method ca/uhn/fhir/rest/gclient/TokenClientParam."<init>":(Ljava/lang/String;)V
       9: putstatic     #245                // Field SEVERITY:Lca/uhn/fhir/rest/gclient/TokenClientParam;
      12: new           #246                // class ca/uhn/fhir/rest/gclient/DateClientParam
      15: dup
      16: ldc           #247                // String date
      18: invokespecial #248                // Method ca/uhn/fhir/rest/gclient/DateClientParam."<init>":(Ljava/lang/String;)V
      21: putstatic     #249                // Field DATE:Lca/uhn/fhir/rest/gclient/DateClientParam;
      24: new           #242                // class ca/uhn/fhir/rest/gclient/TokenClientParam
      27: dup
      28: ldc           #117                // String identifier
      30: invokespecial #244                // Method ca/uhn/fhir/rest/gclient/TokenClientParam."<init>":(Ljava/lang/String;)V
      33: putstatic     #250                // Field IDENTIFIER:Lca/uhn/fhir/rest/gclient/TokenClientParam;
      36: new           #242                // class ca/uhn/fhir/rest/gclient/TokenClientParam
      39: dup
      40: ldc           #251                // String manifestation
      42: invokespecial #244                // Method ca/uhn/fhir/rest/gclient/TokenClientParam."<init>":(Ljava/lang/String;)V
      45: putstatic     #252                // Field MANIFESTATION:Lca/uhn/fhir/rest/gclient/TokenClientParam;
      48: new           #253                // class ca/uhn/fhir/rest/gclient/ReferenceClientParam
      51: dup
      52: ldc           #146                // String recorder
      54: invokespecial #254                // Method ca/uhn/fhir/rest/gclient/ReferenceClientParam."<init>":(Ljava/lang/String;)V
      57: putstatic     #255                // Field RECORDER:Lca/uhn/fhir/rest/gclient/ReferenceClientParam;
      60: new           #256                // class ca/uhn/fhir/model/api/Include
      63: dup
      64: ldc_w         #257                // String AllergyIntolerance:recorder
      67: invokespecial #258                // Method ca/uhn/fhir/model/api/Include."<init>":(Ljava/lang/String;)V
      70: invokevirtual #259                // Method ca/uhn/fhir/model/api/Include.toLocked:()Lca/uhn/fhir/model/api/Include;
      73: putstatic     #260                // Field INCLUDE_RECORDER:Lca/uhn/fhir/model/api/Include;
      76: new           #242                // class ca/uhn/fhir/rest/gclient/TokenClientParam
      79: dup
      80: ldc           #124                // String code
      82: invokespecial #244                // Method ca/uhn/fhir/rest/gclient/TokenClientParam."<init>":(Ljava/lang/String;)V
      85: putstatic     #261                // Field CODE:Lca/uhn/fhir/rest/gclient/TokenClientParam;
      88: new           #242                // class ca/uhn/fhir/rest/gclient/TokenClientParam
      91: dup
      92: ldc_w         #262                // String verification-status
      95: invokespecial #244                // Method ca/uhn/fhir/rest/gclient/TokenClientParam."<init>":(Ljava/lang/String;)V
      98: putstatic     #263                // Field VERIFICATION_STATUS:Lca/uhn/fhir/rest/gclient/TokenClientParam;
     101: new           #242                // class ca/uhn/fhir/rest/gclient/TokenClientParam
     104: dup
     105: ldc           #133                // String criticality
     107: invokespecial #244                // Method ca/uhn/fhir/rest/gclient/TokenClientParam."<init>":(Ljava/lang/String;)V
     110: putstatic     #264                // Field CRITICALITY:Lca/uhn/fhir/rest/gclient/TokenClientParam;
     113: new           #242                // class ca/uhn/fhir/rest/gclient/TokenClientParam
     116: dup
     117: ldc_w         #265                // String clinical-status
     120: invokespecial #244                // Method ca/uhn/fhir/rest/gclient/TokenClientParam."<init>":(Ljava/lang/String;)V
     123: putstatic     #266                // Field CLINICAL_STATUS:Lca/uhn/fhir/rest/gclient/TokenClientParam;
     126: new           #242                // class ca/uhn/fhir/rest/gclient/TokenClientParam
     129: dup
     130: ldc           #129                // String type
     132: invokespecial #244                // Method ca/uhn/fhir/rest/gclient/TokenClientParam."<init>":(Ljava/lang/String;)V
     135: putstatic     #267                // Field TYPE:Lca/uhn/fhir/rest/gclient/TokenClientParam;
     138: new           #246                // class ca/uhn/fhir/rest/gclient/DateClientParam
     141: dup
     142: ldc_w         #268                // String onset
     145: invokespecial #248                // Method ca/uhn/fhir/rest/gclient/DateClientParam."<init>":(Ljava/lang/String;)V
     148: putstatic     #269                // Field ONSET:Lca/uhn/fhir/rest/gclient/DateClientParam;
     151: new           #242                // class ca/uhn/fhir/rest/gclient/TokenClientParam
     154: dup
     155: ldc_w         #270                // String route
     158: invokespecial #244                // Method ca/uhn/fhir/rest/gclient/TokenClientParam."<init>":(Ljava/lang/String;)V
     161: putstatic     #271                // Field ROUTE:Lca/uhn/fhir/rest/gclient/TokenClientParam;
     164: new           #253                // class ca/uhn/fhir/rest/gclient/ReferenceClientParam
     167: dup
     168: ldc           #149                // String asserter
     170: invokespecial #254                // Method ca/uhn/fhir/rest/gclient/ReferenceClientParam."<init>":(Ljava/lang/String;)V
     173: putstatic     #272                // Field ASSERTER:Lca/uhn/fhir/rest/gclient/ReferenceClientParam;
     176: new           #256                // class ca/uhn/fhir/model/api/Include
     179: dup
     180: ldc_w         #273                // String AllergyIntolerance:asserter
     183: invokespecial #258                // Method ca/uhn/fhir/model/api/Include."<init>":(Ljava/lang/String;)V
     186: invokevirtual #259                // Method ca/uhn/fhir/model/api/Include.toLocked:()Lca/uhn/fhir/model/api/Include;
     189: putstatic     #274                // Field INCLUDE_ASSERTER:Lca/uhn/fhir/model/api/Include;
     192: new           #253                // class ca/uhn/fhir/rest/gclient/ReferenceClientParam
     195: dup
     196: ldc           #137                // String patient
     198: invokespecial #254                // Method ca/uhn/fhir/rest/gclient/ReferenceClientParam."<init>":(Ljava/lang/String;)V
     201: putstatic     #275                // Field PATIENT:Lca/uhn/fhir/rest/gclient/ReferenceClientParam;
     204: new           #256                // class ca/uhn/fhir/model/api/Include
     207: dup
     208: ldc_w         #276                // String AllergyIntolerance:patient
     211: invokespecial #258                // Method ca/uhn/fhir/model/api/Include."<init>":(Ljava/lang/String;)V
     214: invokevirtual #259                // Method ca/uhn/fhir/model/api/Include.toLocked:()Lca/uhn/fhir/model/api/Include;
     217: putstatic     #277                // Field INCLUDE_PATIENT:Lca/uhn/fhir/model/api/Include;
     220: new           #242                // class ca/uhn/fhir/rest/gclient/TokenClientParam
     223: dup
     224: ldc           #131                // String category
     226: invokespecial #244                // Method ca/uhn/fhir/rest/gclient/TokenClientParam."<init>":(Ljava/lang/String;)V
     229: putstatic     #278                // Field CATEGORY:Lca/uhn/fhir/rest/gclient/TokenClientParam;
     232: new           #246                // class ca/uhn/fhir/rest/gclient/DateClientParam
     235: dup
     236: ldc_w         #279                // String last-date
     239: invokespecial #248                // Method ca/uhn/fhir/rest/gclient/DateClientParam."<init>":(Ljava/lang/String;)V
     242: putstatic     #280                // Field LAST_DATE:Lca/uhn/fhir/rest/gclient/DateClientParam;
     245: return
}
