Compiled from "ChargeItem.java"
public final class org.hl7.fhir.dstu3.model.ChargeItem$ChargeItemStatus extends java.lang.Enum<org.hl7.fhir.dstu3.model.ChargeItem$ChargeItemStatus> {
  public static final org.hl7.fhir.dstu3.model.ChargeItem$ChargeItemStatus PLANNED;

  public static final org.hl7.fhir.dstu3.model.ChargeItem$ChargeItemStatus BILLABLE;

  public static final org.hl7.fhir.dstu3.model.ChargeItem$ChargeItemStatus NOTBILLABLE;

  public static final org.hl7.fhir.dstu3.model.ChargeItem$ChargeItemStatus ABORTED;

  public static final org.hl7.fhir.dstu3.model.ChargeItem$ChargeItemStatus BILLED;

  public static final org.hl7.fhir.dstu3.model.ChargeItem$ChargeItemStatus ENTEREDINERROR;

  public static final org.hl7.fhir.dstu3.model.ChargeItem$ChargeItemStatus UNKNOWN;

  public static final org.hl7.fhir.dstu3.model.ChargeItem$ChargeItemStatus NULL;

  private static final org.hl7.fhir.dstu3.model.ChargeItem$ChargeItemStatus[] $VALUES;

  public static org.hl7.fhir.dstu3.model.ChargeItem$ChargeItemStatus[] values();
    Code:
       0: getstatic     #1                  // Field $VALUES:[Lorg/hl7/fhir/dstu3/model/ChargeItem$ChargeItemStatus;
       3: invokevirtual #2                  // Method "[Lorg/hl7/fhir/dstu3/model/ChargeItem$ChargeItemStatus;".clone:()Ljava/lang/Object;
       6: checkcast     #3                  // class "[Lorg/hl7/fhir/dstu3/model/ChargeItem$ChargeItemStatus;"
       9: areturn

  public static org.hl7.fhir.dstu3.model.ChargeItem$ChargeItemStatus valueOf(java.lang.String);
    Code:
       0: ldc           #4                  // class org/hl7/fhir/dstu3/model/ChargeItem$ChargeItemStatus
       2: aload_0
       3: invokestatic  #5                  // Method java/lang/Enum.valueOf:(Ljava/lang/Class;Ljava/lang/String;)Ljava/lang/Enum;
       6: checkcast     #4                  // class org/hl7/fhir/dstu3/model/ChargeItem$ChargeItemStatus
       9: areturn

  private org.hl7.fhir.dstu3.model.ChargeItem$ChargeItemStatus();
    Code:
       0: aload_0
       1: aload_1
       2: iload_2
       3: invokespecial #6                  // Method java/lang/Enum."<init>":(Ljava/lang/String;I)V
       6: return

  public static org.hl7.fhir.dstu3.model.ChargeItem$ChargeItemStatus fromCode(java.lang.String) throws org.hl7.fhir.exceptions.FHIRException;
    Code:
       0: aload_0
       1: ifnull        13
       4: ldc           #7                  // String
       6: aload_0
       7: invokevirtual #8                  // Method java/lang/String.equals:(Ljava/lang/Object;)Z
      10: ifeq          15
      13: aconst_null
      14: areturn
      15: ldc           #9                  // String planned
      17: aload_0
      18: invokevirtual #8                  // Method java/lang/String.equals:(Ljava/lang/Object;)Z
      21: ifeq          28
      24: getstatic     #10                 // Field PLANNED:Lorg/hl7/fhir/dstu3/model/ChargeItem$ChargeItemStatus;
      27: areturn
      28: ldc           #11                 // String billable
      30: aload_0
      31: invokevirtual #8                  // Method java/lang/String.equals:(Ljava/lang/Object;)Z
      34: ifeq          41
      37: getstatic     #12                 // Field BILLABLE:Lorg/hl7/fhir/dstu3/model/ChargeItem$ChargeItemStatus;
      40: areturn
      41: ldc           #13                 // String not-billable
      43: aload_0
      44: invokevirtual #8                  // Method java/lang/String.equals:(Ljava/lang/Object;)Z
      47: ifeq          54
      50: getstatic     #14                 // Field NOTBILLABLE:Lorg/hl7/fhir/dstu3/model/ChargeItem$ChargeItemStatus;
      53: areturn
      54: ldc           #15                 // String aborted
      56: aload_0
      57: invokevirtual #8                  // Method java/lang/String.equals:(Ljava/lang/Object;)Z
      60: ifeq          67
      63: getstatic     #16                 // Field ABORTED:Lorg/hl7/fhir/dstu3/model/ChargeItem$ChargeItemStatus;
      66: areturn
      67: ldc           #17                 // String billed
      69: aload_0
      70: invokevirtual #8                  // Method java/lang/String.equals:(Ljava/lang/Object;)Z
      73: ifeq          80
      76: getstatic     #18                 // Field BILLED:Lorg/hl7/fhir/dstu3/model/ChargeItem$ChargeItemStatus;
      79: areturn
      80: ldc           #19                 // String entered-in-error
      82: aload_0
      83: invokevirtual #8                  // Method java/lang/String.equals:(Ljava/lang/Object;)Z
      86: ifeq          93
      89: getstatic     #20                 // Field ENTEREDINERROR:Lorg/hl7/fhir/dstu3/model/ChargeItem$ChargeItemStatus;
      92: areturn
      93: ldc           #21                 // String unknown
      95: aload_0
      96: invokevirtual #8                  // Method java/lang/String.equals:(Ljava/lang/Object;)Z
      99: ifeq          106
     102: getstatic     #22                 // Field UNKNOWN:Lorg/hl7/fhir/dstu3/model/ChargeItem$ChargeItemStatus;
     105: areturn
     106: invokestatic  #23                 // Method org/hl7/fhir/dstu3/model/Configuration.isAcceptInvalidEnums:()Z
     109: ifeq          114
     112: aconst_null
     113: areturn
     114: new           #24                 // class org/hl7/fhir/exceptions/FHIRException
     117: dup
     118: new           #25                 // class java/lang/StringBuilder
     121: dup
     122: invokespecial #26                 // Method java/lang/StringBuilder."<init>":()V
     125: ldc           #27                 // String Unknown ChargeItemStatus code \'
     127: invokevirtual #28                 // Method java/lang/StringBuilder.append:(Ljava/lang/String;)Ljava/lang/StringBuilder;
     130: aload_0
     131: invokevirtual #28                 // Method java/lang/StringBuilder.append:(Ljava/lang/String;)Ljava/lang/StringBuilder;
     134: ldc           #29                 // String \'
     136: invokevirtual #28                 // Method java/lang/StringBuilder.append:(Ljava/lang/String;)Ljava/lang/StringBuilder;
     139: invokevirtual #30                 // Method java/lang/StringBuilder.toString:()Ljava/lang/String;
     142: invokespecial #31                 // Method org/hl7/fhir/exceptions/FHIRException."<init>":(Ljava/lang/String;)V
     145: athrow

  public java.lang.String toCode();
    Code:
       0: getstatic     #32                 // Field org/hl7/fhir/dstu3/model/ChargeItem$1.$SwitchMap$org$hl7$fhir$dstu3$model$ChargeItem$ChargeItemStatus:[I
       3: aload_0
       4: invokevirtual #33                 // Method ordinal:()I
       7: iaload
       8: tableswitch   { // 1 to 8
                     1: 56
                     2: 59
                     3: 62
                     4: 65
                     5: 68
                     6: 71
                     7: 74
                     8: 77
               default: 79
          }
      56: ldc           #9                  // String planned
      58: areturn
      59: ldc           #11                 // String billable
      61: areturn
      62: ldc           #13                 // String not-billable
      64: areturn
      65: ldc           #15                 // String aborted
      67: areturn
      68: ldc           #17                 // String billed
      70: areturn
      71: ldc           #19                 // String entered-in-error
      73: areturn
      74: ldc           #21                 // String unknown
      76: areturn
      77: aconst_null
      78: areturn
      79: ldc           #34                 // String ?
      81: areturn

  public java.lang.String getSystem();
    Code:
       0: getstatic     #32                 // Field org/hl7/fhir/dstu3/model/ChargeItem$1.$SwitchMap$org$hl7$fhir$dstu3$model$ChargeItem$ChargeItemStatus:[I
       3: aload_0
       4: invokevirtual #33                 // Method ordinal:()I
       7: iaload
       8: tableswitch   { // 1 to 8
                     1: 56
                     2: 59
                     3: 62
                     4: 65
                     5: 68
                     6: 71
                     7: 74
                     8: 77
               default: 79
          }
      56: ldc           #35                 // String http://hl7.org/fhir/chargeitem-status
      58: areturn
      59: ldc           #35                 // String http://hl7.org/fhir/chargeitem-status
      61: areturn
      62: ldc           #35                 // String http://hl7.org/fhir/chargeitem-status
      64: areturn
      65: ldc           #35                 // String http://hl7.org/fhir/chargeitem-status
      67: areturn
      68: ldc           #35                 // String http://hl7.org/fhir/chargeitem-status
      70: areturn
      71: ldc           #35                 // String http://hl7.org/fhir/chargeitem-status
      73: areturn
      74: ldc           #35                 // String http://hl7.org/fhir/chargeitem-status
      76: areturn
      77: aconst_null
      78: areturn
      79: ldc           #34                 // String ?
      81: areturn

  public java.lang.String getDefinition();
    Code:
       0: getstatic     #32                 // Field org/hl7/fhir/dstu3/model/ChargeItem$1.$SwitchMap$org$hl7$fhir$dstu3$model$ChargeItem$ChargeItemStatus:[I
       3: aload_0
       4: invokevirtual #33                 // Method ordinal:()I
       7: iaload
       8: tableswitch   { // 1 to 8
                     1: 56
                     2: 59
                     3: 62
                     4: 65
                     5: 68
                     6: 71
                     7: 74
                     8: 77
               default: 79
          }
      56: ldc           #36                 // String The charge item has been entered, but the charged service is not  yet complete, so it shall not be billed yet but might be used in the context of pre-authorization
      58: areturn
      59: ldc           #37                 // String The charge item is ready for billing
      61: areturn
      62: ldc           #38                 // String The charge item has been determined to be not billable (e.g. due to rules associated with the billing code)
      64: areturn
      65: ldc           #39                 // String The processing of the charge was aborted
      67: areturn
      68: ldc           #40                 // String The charge item has been billed (e.g. a billing engine has generated financial transactions by applying the associated ruled for the charge item to the context of the Encounter, and placed them into Claims/Invoices
      70: areturn
      71: ldc           #41                 // String The charge item has been entered in error and should not be processed for billing
      73: areturn
      74: ldc           #42                 // String The authoring system does not know which of the status values currently applies for this charge item  Note: This concept is not to be used for \"other\" - one of the listed statuses is presumed to apply, it\'s just not known which one.
      76: areturn
      77: aconst_null
      78: areturn
      79: ldc           #34                 // String ?
      81: areturn

  public java.lang.String getDisplay();
    Code:
       0: getstatic     #32                 // Field org/hl7/fhir/dstu3/model/ChargeItem$1.$SwitchMap$org$hl7$fhir$dstu3$model$ChargeItem$ChargeItemStatus:[I
       3: aload_0
       4: invokevirtual #33                 // Method ordinal:()I
       7: iaload
       8: tableswitch   { // 1 to 8
                     1: 56
                     2: 59
                     3: 62
                     4: 65
                     5: 68
                     6: 71
                     7: 74
                     8: 77
               default: 79
          }
      56: ldc           #43                 // String Planned
      58: areturn
      59: ldc           #44                 // String Billable
      61: areturn
      62: ldc           #45                 // String Not billable
      64: areturn
      65: ldc           #46                 // String Aborted
      67: areturn
      68: ldc           #47                 // String Billed
      70: areturn
      71: ldc           #48                 // String Entered in Error
      73: areturn
      74: ldc           #49                 // String Unknown
      76: areturn
      77: aconst_null
      78: areturn
      79: ldc           #34                 // String ?
      81: areturn

  static {};
    Code:
       0: new           #4                  // class org/hl7/fhir/dstu3/model/ChargeItem$ChargeItemStatus
       3: dup
       4: ldc           #50                 // String PLANNED
       6: iconst_0
       7: invokespecial #51                 // Method "<init>":(Ljava/lang/String;I)V
      10: putstatic     #10                 // Field PLANNED:Lorg/hl7/fhir/dstu3/model/ChargeItem$ChargeItemStatus;
      13: new           #4                  // class org/hl7/fhir/dstu3/model/ChargeItem$ChargeItemStatus
      16: dup
      17: ldc           #52                 // String BILLABLE
      19: iconst_1
      20: invokespecial #51                 // Method "<init>":(Ljava/lang/String;I)V
      23: putstatic     #12                 // Field BILLABLE:Lorg/hl7/fhir/dstu3/model/ChargeItem$ChargeItemStatus;
      26: new           #4                  // class org/hl7/fhir/dstu3/model/ChargeItem$ChargeItemStatus
      29: dup
      30: ldc           #53                 // String NOTBILLABLE
      32: iconst_2
      33: invokespecial #51                 // Method "<init>":(Ljava/lang/String;I)V
      36: putstatic     #14                 // Field NOTBILLABLE:Lorg/hl7/fhir/dstu3/model/ChargeItem$ChargeItemStatus;
      39: new           #4                  // class org/hl7/fhir/dstu3/model/ChargeItem$ChargeItemStatus
      42: dup
      43: ldc           #54                 // String ABORTED
      45: iconst_3
      46: invokespecial #51                 // Method "<init>":(Ljava/lang/String;I)V
      49: putstatic     #16                 // Field ABORTED:Lorg/hl7/fhir/dstu3/model/ChargeItem$ChargeItemStatus;
      52: new           #4                  // class org/hl7/fhir/dstu3/model/ChargeItem$ChargeItemStatus
      55: dup
      56: ldc           #55                 // String BILLED
      58: iconst_4
      59: invokespecial #51                 // Method "<init>":(Ljava/lang/String;I)V
      62: putstatic     #18                 // Field BILLED:Lorg/hl7/fhir/dstu3/model/ChargeItem$ChargeItemStatus;
      65: new           #4                  // class org/hl7/fhir/dstu3/model/ChargeItem$ChargeItemStatus
      68: dup
      69: ldc           #56                 // String ENTEREDINERROR
      71: iconst_5
      72: invokespecial #51                 // Method "<init>":(Ljava/lang/String;I)V
      75: putstatic     #20                 // Field ENTEREDINERROR:Lorg/hl7/fhir/dstu3/model/ChargeItem$ChargeItemStatus;
      78: new           #4                  // class org/hl7/fhir/dstu3/model/ChargeItem$ChargeItemStatus
      81: dup
      82: ldc           #57                 // String UNKNOWN
      84: bipush        6
      86: invokespecial #51                 // Method "<init>":(Ljava/lang/String;I)V
      89: putstatic     #22                 // Field UNKNOWN:Lorg/hl7/fhir/dstu3/model/ChargeItem$ChargeItemStatus;
      92: new           #4                  // class org/hl7/fhir/dstu3/model/ChargeItem$ChargeItemStatus
      95: dup
      96: ldc           #58                 // String NULL
      98: bipush        7
     100: invokespecial #51                 // Method "<init>":(Ljava/lang/String;I)V
     103: putstatic     #59                 // Field NULL:Lorg/hl7/fhir/dstu3/model/ChargeItem$ChargeItemStatus;
     106: bipush        8
     108: anewarray     #4                  // class org/hl7/fhir/dstu3/model/ChargeItem$ChargeItemStatus
     111: dup
     112: iconst_0
     113: getstatic     #10                 // Field PLANNED:Lorg/hl7/fhir/dstu3/model/ChargeItem$ChargeItemStatus;
     116: aastore
     117: dup
     118: iconst_1
     119: getstatic     #12                 // Field BILLABLE:Lorg/hl7/fhir/dstu3/model/ChargeItem$ChargeItemStatus;
     122: aastore
     123: dup
     124: iconst_2
     125: getstatic     #14                 // Field NOTBILLABLE:Lorg/hl7/fhir/dstu3/model/ChargeItem$ChargeItemStatus;
     128: aastore
     129: dup
     130: iconst_3
     131: getstatic     #16                 // Field ABORTED:Lorg/hl7/fhir/dstu3/model/ChargeItem$ChargeItemStatus;
     134: aastore
     135: dup
     136: iconst_4
     137: getstatic     #18                 // Field BILLED:Lorg/hl7/fhir/dstu3/model/ChargeItem$ChargeItemStatus;
     140: aastore
     141: dup
     142: iconst_5
     143: getstatic     #20                 // Field ENTEREDINERROR:Lorg/hl7/fhir/dstu3/model/ChargeItem$ChargeItemStatus;
     146: aastore
     147: dup
     148: bipush        6
     150: getstatic     #22                 // Field UNKNOWN:Lorg/hl7/fhir/dstu3/model/ChargeItem$ChargeItemStatus;
     153: aastore
     154: dup
     155: bipush        7
     157: getstatic     #59                 // Field NULL:Lorg/hl7/fhir/dstu3/model/ChargeItem$ChargeItemStatus;
     160: aastore
     161: putstatic     #1                  // Field $VALUES:[Lorg/hl7/fhir/dstu3/model/ChargeItem$ChargeItemStatus;
     164: return
}
