Compiled from "ClaimResponse.java"
public class org.hl7.fhir.dstu3.model.ClaimResponse$ItemComponent extends org.hl7.fhir.dstu3.model.BackboneElement implements org.hl7.fhir.instance.model.api.IBaseBackboneElement {
  protected org.hl7.fhir.dstu3.model.PositiveIntType sequenceLinkId;

  protected java.util.List<org.hl7.fhir.dstu3.model.PositiveIntType> noteNumber;

  protected java.util.List<org.hl7.fhir.dstu3.model.ClaimResponse$AdjudicationComponent> adjudication;

  protected java.util.List<org.hl7.fhir.dstu3.model.ClaimResponse$ItemDetailComponent> detail;

  private static final long serialVersionUID;

  public org.hl7.fhir.dstu3.model.ClaimResponse$ItemComponent();
    Code:
       0: aload_0
       1: invokespecial #1                  // Method org/hl7/fhir/dstu3/model/BackboneElement."<init>":()V
       4: return

  public org.hl7.fhir.dstu3.model.ClaimResponse$ItemComponent(org.hl7.fhir.dstu3.model.PositiveIntType);
    Code:
       0: aload_0
       1: invokespecial #1                  // Method org/hl7/fhir/dstu3/model/BackboneElement."<init>":()V
       4: aload_0
       5: aload_1
       6: putfield      #2                  // Field sequenceLinkId:Lorg/hl7/fhir/dstu3/model/PositiveIntType;
       9: return

  public org.hl7.fhir.dstu3.model.PositiveIntType getSequenceLinkIdElement();
    Code:
       0: aload_0
       1: getfield      #2                  // Field sequenceLinkId:Lorg/hl7/fhir/dstu3/model/PositiveIntType;
       4: ifnonnull     40
       7: invokestatic  #3                  // Method org/hl7/fhir/dstu3/model/Configuration.errorOnAutoCreate:()Z
      10: ifeq          23
      13: new           #4                  // class java/lang/Error
      16: dup
      17: ldc           #5                  // String Attempt to auto-create ItemComponent.sequenceLinkId
      19: invokespecial #6                  // Method java/lang/Error."<init>":(Ljava/lang/String;)V
      22: athrow
      23: invokestatic  #7                  // Method org/hl7/fhir/dstu3/model/Configuration.doAutoCreate:()Z
      26: ifeq          40
      29: aload_0
      30: new           #8                  // class org/hl7/fhir/dstu3/model/PositiveIntType
      33: dup
      34: invokespecial #9                  // Method org/hl7/fhir/dstu3/model/PositiveIntType."<init>":()V
      37: putfield      #2                  // Field sequenceLinkId:Lorg/hl7/fhir/dstu3/model/PositiveIntType;
      40: aload_0
      41: getfield      #2                  // Field sequenceLinkId:Lorg/hl7/fhir/dstu3/model/PositiveIntType;
      44: areturn

  public boolean hasSequenceLinkIdElement();
    Code:
       0: aload_0
       1: getfield      #2                  // Field sequenceLinkId:Lorg/hl7/fhir/dstu3/model/PositiveIntType;
       4: ifnull        21
       7: aload_0
       8: getfield      #2                  // Field sequenceLinkId:Lorg/hl7/fhir/dstu3/model/PositiveIntType;
      11: invokevirtual #10                 // Method org/hl7/fhir/dstu3/model/PositiveIntType.isEmpty:()Z
      14: ifne          21
      17: iconst_1
      18: goto          22
      21: iconst_0
      22: ireturn

  public boolean hasSequenceLinkId();
    Code:
       0: aload_0
       1: getfield      #2                  // Field sequenceLinkId:Lorg/hl7/fhir/dstu3/model/PositiveIntType;
       4: ifnull        21
       7: aload_0
       8: getfield      #2                  // Field sequenceLinkId:Lorg/hl7/fhir/dstu3/model/PositiveIntType;
      11: invokevirtual #10                 // Method org/hl7/fhir/dstu3/model/PositiveIntType.isEmpty:()Z
      14: ifne          21
      17: iconst_1
      18: goto          22
      21: iconst_0
      22: ireturn

  public org.hl7.fhir.dstu3.model.ClaimResponse$ItemComponent setSequenceLinkIdElement(org.hl7.fhir.dstu3.model.PositiveIntType);
    Code:
       0: aload_0
       1: aload_1
       2: putfield      #2                  // Field sequenceLinkId:Lorg/hl7/fhir/dstu3/model/PositiveIntType;
       5: aload_0
       6: areturn

  public int getSequenceLinkId();
    Code:
       0: aload_0
       1: getfield      #2                  // Field sequenceLinkId:Lorg/hl7/fhir/dstu3/model/PositiveIntType;
       4: ifnull        17
       7: aload_0
       8: getfield      #2                  // Field sequenceLinkId:Lorg/hl7/fhir/dstu3/model/PositiveIntType;
      11: invokevirtual #10                 // Method org/hl7/fhir/dstu3/model/PositiveIntType.isEmpty:()Z
      14: ifeq          21
      17: iconst_0
      18: goto          34
      21: aload_0
      22: getfield      #2                  // Field sequenceLinkId:Lorg/hl7/fhir/dstu3/model/PositiveIntType;
      25: invokevirtual #11                 // Method org/hl7/fhir/dstu3/model/PositiveIntType.getValue:()Ljava/lang/Object;
      28: checkcast     #12                 // class java/lang/Integer
      31: invokevirtual #13                 // Method java/lang/Integer.intValue:()I
      34: ireturn

  public org.hl7.fhir.dstu3.model.ClaimResponse$ItemComponent setSequenceLinkId(int);
    Code:
       0: aload_0
       1: getfield      #2                  // Field sequenceLinkId:Lorg/hl7/fhir/dstu3/model/PositiveIntType;
       4: ifnonnull     18
       7: aload_0
       8: new           #8                  // class org/hl7/fhir/dstu3/model/PositiveIntType
      11: dup
      12: invokespecial #9                  // Method org/hl7/fhir/dstu3/model/PositiveIntType."<init>":()V
      15: putfield      #2                  // Field sequenceLinkId:Lorg/hl7/fhir/dstu3/model/PositiveIntType;
      18: aload_0
      19: getfield      #2                  // Field sequenceLinkId:Lorg/hl7/fhir/dstu3/model/PositiveIntType;
      22: iload_1
      23: invokestatic  #14                 // Method java/lang/Integer.valueOf:(I)Ljava/lang/Integer;
      26: invokevirtual #15                 // Method org/hl7/fhir/dstu3/model/PositiveIntType.setValue:(Ljava/lang/Object;)Lorg/hl7/fhir/dstu3/model/PrimitiveType;
      29: pop
      30: aload_0
      31: areturn

  public java.util.List<org.hl7.fhir.dstu3.model.PositiveIntType> getNoteNumber();
    Code:
       0: aload_0
       1: getfield      #16                 // Field noteNumber:Ljava/util/List;
       4: ifnonnull     18
       7: aload_0
       8: new           #17                 // class java/util/ArrayList
      11: dup
      12: invokespecial #18                 // Method java/util/ArrayList."<init>":()V
      15: putfield      #16                 // Field noteNumber:Ljava/util/List;
      18: aload_0
      19: getfield      #16                 // Field noteNumber:Ljava/util/List;
      22: areturn

  public org.hl7.fhir.dstu3.model.ClaimResponse$ItemComponent setNoteNumber(java.util.List<org.hl7.fhir.dstu3.model.PositiveIntType>);
    Code:
       0: aload_0
       1: aload_1
       2: putfield      #16                 // Field noteNumber:Ljava/util/List;
       5: aload_0
       6: areturn

  public boolean hasNoteNumber();
    Code:
       0: aload_0
       1: getfield      #16                 // Field noteNumber:Ljava/util/List;
       4: ifnonnull     9
       7: iconst_0
       8: ireturn
       9: aload_0
      10: getfield      #16                 // Field noteNumber:Ljava/util/List;
      13: invokeinterface #19,  1           // InterfaceMethod java/util/List.iterator:()Ljava/util/Iterator;
      18: astore_1
      19: aload_1
      20: invokeinterface #20,  1           // InterfaceMethod java/util/Iterator.hasNext:()Z
      25: ifeq          50
      28: aload_1
      29: invokeinterface #21,  1           // InterfaceMethod java/util/Iterator.next:()Ljava/lang/Object;
      34: checkcast     #8                  // class org/hl7/fhir/dstu3/model/PositiveIntType
      37: astore_2
      38: aload_2
      39: invokevirtual #10                 // Method org/hl7/fhir/dstu3/model/PositiveIntType.isEmpty:()Z
      42: ifne          47
      45: iconst_1
      46: ireturn
      47: goto          19
      50: iconst_0
      51: ireturn

  public org.hl7.fhir.dstu3.model.PositiveIntType addNoteNumberElement();
    Code:
       0: new           #8                  // class org/hl7/fhir/dstu3/model/PositiveIntType
       3: dup
       4: invokespecial #9                  // Method org/hl7/fhir/dstu3/model/PositiveIntType."<init>":()V
       7: astore_1
       8: aload_0
       9: getfield      #16                 // Field noteNumber:Ljava/util/List;
      12: ifnonnull     26
      15: aload_0
      16: new           #17                 // class java/util/ArrayList
      19: dup
      20: invokespecial #18                 // Method java/util/ArrayList."<init>":()V
      23: putfield      #16                 // Field noteNumber:Ljava/util/List;
      26: aload_0
      27: getfield      #16                 // Field noteNumber:Ljava/util/List;
      30: aload_1
      31: invokeinterface #22,  2           // InterfaceMethod java/util/List.add:(Ljava/lang/Object;)Z
      36: pop
      37: aload_1
      38: areturn

  public org.hl7.fhir.dstu3.model.ClaimResponse$ItemComponent addNoteNumber(int);
    Code:
       0: new           #8                  // class org/hl7/fhir/dstu3/model/PositiveIntType
       3: dup
       4: invokespecial #9                  // Method org/hl7/fhir/dstu3/model/PositiveIntType."<init>":()V
       7: astore_2
       8: aload_2
       9: iload_1
      10: invokestatic  #14                 // Method java/lang/Integer.valueOf:(I)Ljava/lang/Integer;
      13: invokevirtual #15                 // Method org/hl7/fhir/dstu3/model/PositiveIntType.setValue:(Ljava/lang/Object;)Lorg/hl7/fhir/dstu3/model/PrimitiveType;
      16: pop
      17: aload_0
      18: getfield      #16                 // Field noteNumber:Ljava/util/List;
      21: ifnonnull     35
      24: aload_0
      25: new           #17                 // class java/util/ArrayList
      28: dup
      29: invokespecial #18                 // Method java/util/ArrayList."<init>":()V
      32: putfield      #16                 // Field noteNumber:Ljava/util/List;
      35: aload_0
      36: getfield      #16                 // Field noteNumber:Ljava/util/List;
      39: aload_2
      40: invokeinterface #22,  2           // InterfaceMethod java/util/List.add:(Ljava/lang/Object;)Z
      45: pop
      46: aload_0
      47: areturn

  public boolean hasNoteNumber(int);
    Code:
       0: aload_0
       1: getfield      #16                 // Field noteNumber:Ljava/util/List;
       4: ifnonnull     9
       7: iconst_0
       8: ireturn
       9: aload_0
      10: getfield      #16                 // Field noteNumber:Ljava/util/List;
      13: invokeinterface #19,  1           // InterfaceMethod java/util/List.iterator:()Ljava/util/Iterator;
      18: astore_2
      19: aload_2
      20: invokeinterface #20,  1           // InterfaceMethod java/util/Iterator.hasNext:()Z
      25: ifeq          60
      28: aload_2
      29: invokeinterface #21,  1           // InterfaceMethod java/util/Iterator.next:()Ljava/lang/Object;
      34: checkcast     #8                  // class org/hl7/fhir/dstu3/model/PositiveIntType
      37: astore_3
      38: aload_3
      39: invokevirtual #11                 // Method org/hl7/fhir/dstu3/model/PositiveIntType.getValue:()Ljava/lang/Object;
      42: checkcast     #12                 // class java/lang/Integer
      45: iload_1
      46: invokestatic  #14                 // Method java/lang/Integer.valueOf:(I)Ljava/lang/Integer;
      49: invokevirtual #23                 // Method java/lang/Integer.equals:(Ljava/lang/Object;)Z
      52: ifeq          57
      55: iconst_1
      56: ireturn
      57: goto          19
      60: iconst_0
      61: ireturn

  public java.util.List<org.hl7.fhir.dstu3.model.ClaimResponse$AdjudicationComponent> getAdjudication();
    Code:
       0: aload_0
       1: getfield      #24                 // Field adjudication:Ljava/util/List;
       4: ifnonnull     18
       7: aload_0
       8: new           #17                 // class java/util/ArrayList
      11: dup
      12: invokespecial #18                 // Method java/util/ArrayList."<init>":()V
      15: putfield      #24                 // Field adjudication:Ljava/util/List;
      18: aload_0
      19: getfield      #24                 // Field adjudication:Ljava/util/List;
      22: areturn

  public org.hl7.fhir.dstu3.model.ClaimResponse$ItemComponent setAdjudication(java.util.List<org.hl7.fhir.dstu3.model.ClaimResponse$AdjudicationComponent>);
    Code:
       0: aload_0
       1: aload_1
       2: putfield      #24                 // Field adjudication:Ljava/util/List;
       5: aload_0
       6: areturn

  public boolean hasAdjudication();
    Code:
       0: aload_0
       1: getfield      #24                 // Field adjudication:Ljava/util/List;
       4: ifnonnull     9
       7: iconst_0
       8: ireturn
       9: aload_0
      10: getfield      #24                 // Field adjudication:Ljava/util/List;
      13: invokeinterface #19,  1           // InterfaceMethod java/util/List.iterator:()Ljava/util/Iterator;
      18: astore_1
      19: aload_1
      20: invokeinterface #20,  1           // InterfaceMethod java/util/Iterator.hasNext:()Z
      25: ifeq          50
      28: aload_1
      29: invokeinterface #21,  1           // InterfaceMethod java/util/Iterator.next:()Ljava/lang/Object;
      34: checkcast     #25                 // class org/hl7/fhir/dstu3/model/ClaimResponse$AdjudicationComponent
      37: astore_2
      38: aload_2
      39: invokevirtual #26                 // Method org/hl7/fhir/dstu3/model/ClaimResponse$AdjudicationComponent.isEmpty:()Z
      42: ifne          47
      45: iconst_1
      46: ireturn
      47: goto          19
      50: iconst_0
      51: ireturn

  public org.hl7.fhir.dstu3.model.ClaimResponse$AdjudicationComponent addAdjudication();
    Code:
       0: new           #25                 // class org/hl7/fhir/dstu3/model/ClaimResponse$AdjudicationComponent
       3: dup
       4: invokespecial #27                 // Method org/hl7/fhir/dstu3/model/ClaimResponse$AdjudicationComponent."<init>":()V
       7: astore_1
       8: aload_0
       9: getfield      #24                 // Field adjudication:Ljava/util/List;
      12: ifnonnull     26
      15: aload_0
      16: new           #17                 // class java/util/ArrayList
      19: dup
      20: invokespecial #18                 // Method java/util/ArrayList."<init>":()V
      23: putfield      #24                 // Field adjudication:Ljava/util/List;
      26: aload_0
      27: getfield      #24                 // Field adjudication:Ljava/util/List;
      30: aload_1
      31: invokeinterface #22,  2           // InterfaceMethod java/util/List.add:(Ljava/lang/Object;)Z
      36: pop
      37: aload_1
      38: areturn

  public org.hl7.fhir.dstu3.model.ClaimResponse$ItemComponent addAdjudication(org.hl7.fhir.dstu3.model.ClaimResponse$AdjudicationComponent);
    Code:
       0: aload_1
       1: ifnonnull     6
       4: aload_0
       5: areturn
       6: aload_0
       7: getfield      #24                 // Field adjudication:Ljava/util/List;
      10: ifnonnull     24
      13: aload_0
      14: new           #17                 // class java/util/ArrayList
      17: dup
      18: invokespecial #18                 // Method java/util/ArrayList."<init>":()V
      21: putfield      #24                 // Field adjudication:Ljava/util/List;
      24: aload_0
      25: getfield      #24                 // Field adjudication:Ljava/util/List;
      28: aload_1
      29: invokeinterface #22,  2           // InterfaceMethod java/util/List.add:(Ljava/lang/Object;)Z
      34: pop
      35: aload_0
      36: areturn

  public org.hl7.fhir.dstu3.model.ClaimResponse$AdjudicationComponent getAdjudicationFirstRep();
    Code:
       0: aload_0
       1: invokevirtual #28                 // Method getAdjudication:()Ljava/util/List;
       4: invokeinterface #29,  1           // InterfaceMethod java/util/List.isEmpty:()Z
       9: ifeq          17
      12: aload_0
      13: invokevirtual #30                 // Method addAdjudication:()Lorg/hl7/fhir/dstu3/model/ClaimResponse$AdjudicationComponent;
      16: pop
      17: aload_0
      18: invokevirtual #28                 // Method getAdjudication:()Ljava/util/List;
      21: iconst_0
      22: invokeinterface #31,  2           // InterfaceMethod java/util/List.get:(I)Ljava/lang/Object;
      27: checkcast     #25                 // class org/hl7/fhir/dstu3/model/ClaimResponse$AdjudicationComponent
      30: areturn

  public java.util.List<org.hl7.fhir.dstu3.model.ClaimResponse$ItemDetailComponent> getDetail();
    Code:
       0: aload_0
       1: getfield      #32                 // Field detail:Ljava/util/List;
       4: ifnonnull     18
       7: aload_0
       8: new           #17                 // class java/util/ArrayList
      11: dup
      12: invokespecial #18                 // Method java/util/ArrayList."<init>":()V
      15: putfield      #32                 // Field detail:Ljava/util/List;
      18: aload_0
      19: getfield      #32                 // Field detail:Ljava/util/List;
      22: areturn

  public org.hl7.fhir.dstu3.model.ClaimResponse$ItemComponent setDetail(java.util.List<org.hl7.fhir.dstu3.model.ClaimResponse$ItemDetailComponent>);
    Code:
       0: aload_0
       1: aload_1
       2: putfield      #32                 // Field detail:Ljava/util/List;
       5: aload_0
       6: areturn

  public boolean hasDetail();
    Code:
       0: aload_0
       1: getfield      #32                 // Field detail:Ljava/util/List;
       4: ifnonnull     9
       7: iconst_0
       8: ireturn
       9: aload_0
      10: getfield      #32                 // Field detail:Ljava/util/List;
      13: invokeinterface #19,  1           // InterfaceMethod java/util/List.iterator:()Ljava/util/Iterator;
      18: astore_1
      19: aload_1
      20: invokeinterface #20,  1           // InterfaceMethod java/util/Iterator.hasNext:()Z
      25: ifeq          50
      28: aload_1
      29: invokeinterface #21,  1           // InterfaceMethod java/util/Iterator.next:()Ljava/lang/Object;
      34: checkcast     #33                 // class org/hl7/fhir/dstu3/model/ClaimResponse$ItemDetailComponent
      37: astore_2
      38: aload_2
      39: invokevirtual #34                 // Method org/hl7/fhir/dstu3/model/ClaimResponse$ItemDetailComponent.isEmpty:()Z
      42: ifne          47
      45: iconst_1
      46: ireturn
      47: goto          19
      50: iconst_0
      51: ireturn

  public org.hl7.fhir.dstu3.model.ClaimResponse$ItemDetailComponent addDetail();
    Code:
       0: new           #33                 // class org/hl7/fhir/dstu3/model/ClaimResponse$ItemDetailComponent
       3: dup
       4: invokespecial #35                 // Method org/hl7/fhir/dstu3/model/ClaimResponse$ItemDetailComponent."<init>":()V
       7: astore_1
       8: aload_0
       9: getfield      #32                 // Field detail:Ljava/util/List;
      12: ifnonnull     26
      15: aload_0
      16: new           #17                 // class java/util/ArrayList
      19: dup
      20: invokespecial #18                 // Method java/util/ArrayList."<init>":()V
      23: putfield      #32                 // Field detail:Ljava/util/List;
      26: aload_0
      27: getfield      #32                 // Field detail:Ljava/util/List;
      30: aload_1
      31: invokeinterface #22,  2           // InterfaceMethod java/util/List.add:(Ljava/lang/Object;)Z
      36: pop
      37: aload_1
      38: areturn

  public org.hl7.fhir.dstu3.model.ClaimResponse$ItemComponent addDetail(org.hl7.fhir.dstu3.model.ClaimResponse$ItemDetailComponent);
    Code:
       0: aload_1
       1: ifnonnull     6
       4: aload_0
       5: areturn
       6: aload_0
       7: getfield      #32                 // Field detail:Ljava/util/List;
      10: ifnonnull     24
      13: aload_0
      14: new           #17                 // class java/util/ArrayList
      17: dup
      18: invokespecial #18                 // Method java/util/ArrayList."<init>":()V
      21: putfield      #32                 // Field detail:Ljava/util/List;
      24: aload_0
      25: getfield      #32                 // Field detail:Ljava/util/List;
      28: aload_1
      29: invokeinterface #22,  2           // InterfaceMethod java/util/List.add:(Ljava/lang/Object;)Z
      34: pop
      35: aload_0
      36: areturn

  public org.hl7.fhir.dstu3.model.ClaimResponse$ItemDetailComponent getDetailFirstRep();
    Code:
       0: aload_0
       1: invokevirtual #36                 // Method getDetail:()Ljava/util/List;
       4: invokeinterface #29,  1           // InterfaceMethod java/util/List.isEmpty:()Z
       9: ifeq          17
      12: aload_0
      13: invokevirtual #37                 // Method addDetail:()Lorg/hl7/fhir/dstu3/model/ClaimResponse$ItemDetailComponent;
      16: pop
      17: aload_0
      18: invokevirtual #36                 // Method getDetail:()Ljava/util/List;
      21: iconst_0
      22: invokeinterface #31,  2           // InterfaceMethod java/util/List.get:(I)Ljava/lang/Object;
      27: checkcast     #33                 // class org/hl7/fhir/dstu3/model/ClaimResponse$ItemDetailComponent
      30: areturn

  protected void listChildren(java.util.List<org.hl7.fhir.dstu3.model.Property>);
    Code:
       0: aload_0
       1: aload_1
       2: invokespecial #38                 // Method org/hl7/fhir/dstu3/model/BackboneElement.listChildren:(Ljava/util/List;)V
       5: aload_1
       6: new           #39                 // class org/hl7/fhir/dstu3/model/Property
       9: dup
      10: ldc           #40                 // String sequenceLinkId
      12: ldc           #41                 // String positiveInt
      14: ldc           #42                 // String A service line number.
      16: iconst_0
      17: iconst_1
      18: aload_0
      19: getfield      #2                  // Field sequenceLinkId:Lorg/hl7/fhir/dstu3/model/PositiveIntType;
      22: invokespecial #43                 // Method org/hl7/fhir/dstu3/model/Property."<init>":(Ljava/lang/String;Ljava/lang/String;Ljava/lang/String;IILorg/hl7/fhir/dstu3/model/Base;)V
      25: invokeinterface #22,  2           // InterfaceMethod java/util/List.add:(Ljava/lang/Object;)Z
      30: pop
      31: aload_1
      32: new           #39                 // class org/hl7/fhir/dstu3/model/Property
      35: dup
      36: ldc           #44                 // String noteNumber
      38: ldc           #41                 // String positiveInt
      40: ldc           #45                 // String A list of note references to the notes provided below.
      42: iconst_0
      43: ldc           #46                 // int 2147483647
      45: aload_0
      46: getfield      #16                 // Field noteNumber:Ljava/util/List;
      49: invokespecial #47                 // Method org/hl7/fhir/dstu3/model/Property."<init>":(Ljava/lang/String;Ljava/lang/String;Ljava/lang/String;IILjava/util/List;)V
      52: invokeinterface #22,  2           // InterfaceMethod java/util/List.add:(Ljava/lang/Object;)Z
      57: pop
      58: aload_1
      59: new           #39                 // class org/hl7/fhir/dstu3/model/Property
      62: dup
      63: ldc           #48                 // String adjudication
      65: ldc           #49                 // String
      67: ldc           #50                 // String The adjudication results.
      69: iconst_0
      70: ldc           #46                 // int 2147483647
      72: aload_0
      73: getfield      #24                 // Field adjudication:Ljava/util/List;
      76: invokespecial #47                 // Method org/hl7/fhir/dstu3/model/Property."<init>":(Ljava/lang/String;Ljava/lang/String;Ljava/lang/String;IILjava/util/List;)V
      79: invokeinterface #22,  2           // InterfaceMethod java/util/List.add:(Ljava/lang/Object;)Z
      84: pop
      85: aload_1
      86: new           #39                 // class org/hl7/fhir/dstu3/model/Property
      89: dup
      90: ldc           #51                 // String detail
      92: ldc           #49                 // String
      94: ldc           #52                 // String The second tier service adjudications for submitted services.
      96: iconst_0
      97: ldc           #46                 // int 2147483647
      99: aload_0
     100: getfield      #32                 // Field detail:Ljava/util/List;
     103: invokespecial #47                 // Method org/hl7/fhir/dstu3/model/Property."<init>":(Ljava/lang/String;Ljava/lang/String;Ljava/lang/String;IILjava/util/List;)V
     106: invokeinterface #22,  2           // InterfaceMethod java/util/List.add:(Ljava/lang/Object;)Z
     111: pop
     112: return

  public org.hl7.fhir.dstu3.model.Property getNamedProperty(int, java.lang.String, boolean) throws org.hl7.fhir.exceptions.FHIRException;
    Code:
       0: iload_1
       1: lookupswitch  { // 4
           -1422298666: 44
           -1335224239: 106
           -1110033957: 64
            -231349275: 85
               default: 127
          }
      44: new           #39                 // class org/hl7/fhir/dstu3/model/Property
      47: dup
      48: ldc           #40                 // String sequenceLinkId
      50: ldc           #41                 // String positiveInt
      52: ldc           #42                 // String A service line number.
      54: iconst_0
      55: iconst_1
      56: aload_0
      57: getfield      #2                  // Field sequenceLinkId:Lorg/hl7/fhir/dstu3/model/PositiveIntType;
      60: invokespecial #43                 // Method org/hl7/fhir/dstu3/model/Property."<init>":(Ljava/lang/String;Ljava/lang/String;Ljava/lang/String;IILorg/hl7/fhir/dstu3/model/Base;)V
      63: areturn
      64: new           #39                 // class org/hl7/fhir/dstu3/model/Property
      67: dup
      68: ldc           #44                 // String noteNumber
      70: ldc           #41                 // String positiveInt
      72: ldc           #45                 // String A list of note references to the notes provided below.
      74: iconst_0
      75: ldc           #46                 // int 2147483647
      77: aload_0
      78: getfield      #16                 // Field noteNumber:Ljava/util/List;
      81: invokespecial #47                 // Method org/hl7/fhir/dstu3/model/Property."<init>":(Ljava/lang/String;Ljava/lang/String;Ljava/lang/String;IILjava/util/List;)V
      84: areturn
      85: new           #39                 // class org/hl7/fhir/dstu3/model/Property
      88: dup
      89: ldc           #48                 // String adjudication
      91: ldc           #49                 // String
      93: ldc           #50                 // String The adjudication results.
      95: iconst_0
      96: ldc           #46                 // int 2147483647
      98: aload_0
      99: getfield      #24                 // Field adjudication:Ljava/util/List;
     102: invokespecial #47                 // Method org/hl7/fhir/dstu3/model/Property."<init>":(Ljava/lang/String;Ljava/lang/String;Ljava/lang/String;IILjava/util/List;)V
     105: areturn
     106: new           #39                 // class org/hl7/fhir/dstu3/model/Property
     109: dup
     110: ldc           #51                 // String detail
     112: ldc           #49                 // String
     114: ldc           #52                 // String The second tier service adjudications for submitted services.
     116: iconst_0
     117: ldc           #46                 // int 2147483647
     119: aload_0
     120: getfield      #32                 // Field detail:Ljava/util/List;
     123: invokespecial #47                 // Method org/hl7/fhir/dstu3/model/Property."<init>":(Ljava/lang/String;Ljava/lang/String;Ljava/lang/String;IILjava/util/List;)V
     126: areturn
     127: aload_0
     128: iload_1
     129: aload_2
     130: iload_3
     131: invokespecial #53                 // Method org/hl7/fhir/dstu3/model/BackboneElement.getNamedProperty:(ILjava/lang/String;Z)Lorg/hl7/fhir/dstu3/model/Property;
     134: areturn

  public org.hl7.fhir.dstu3.model.Base[] getProperty(int, java.lang.String, boolean) throws org.hl7.fhir.exceptions.FHIRException;
    Code:
       0: iload_1
       1: lookupswitch  { // 4
           -1422298666: 44
           -1335224239: 148
           -1110033957: 70
            -231349275: 109
               default: 187
          }
      44: aload_0
      45: getfield      #2                  // Field sequenceLinkId:Lorg/hl7/fhir/dstu3/model/PositiveIntType;
      48: ifnonnull     58
      51: iconst_0
      52: anewarray     #54                 // class org/hl7/fhir/dstu3/model/Base
      55: goto          69
      58: iconst_1
      59: anewarray     #54                 // class org/hl7/fhir/dstu3/model/Base
      62: dup
      63: iconst_0
      64: aload_0
      65: getfield      #2                  // Field sequenceLinkId:Lorg/hl7/fhir/dstu3/model/PositiveIntType;
      68: aastore
      69: areturn
      70: aload_0
      71: getfield      #16                 // Field noteNumber:Ljava/util/List;
      74: ifnonnull     84
      77: iconst_0
      78: anewarray     #54                 // class org/hl7/fhir/dstu3/model/Base
      81: goto          108
      84: aload_0
      85: getfield      #16                 // Field noteNumber:Ljava/util/List;
      88: aload_0
      89: getfield      #16                 // Field noteNumber:Ljava/util/List;
      92: invokeinterface #55,  1           // InterfaceMethod java/util/List.size:()I
      97: anewarray     #54                 // class org/hl7/fhir/dstu3/model/Base
     100: invokeinterface #56,  2           // InterfaceMethod java/util/List.toArray:([Ljava/lang/Object;)[Ljava/lang/Object;
     105: checkcast     #57                 // class "[Lorg/hl7/fhir/dstu3/model/Base;"
     108: areturn
     109: aload_0
     110: getfield      #24                 // Field adjudication:Ljava/util/List;
     113: ifnonnull     123
     116: iconst_0
     117: anewarray     #54                 // class org/hl7/fhir/dstu3/model/Base
     120: goto          147
     123: aload_0
     124: getfield      #24                 // Field adjudication:Ljava/util/List;
     127: aload_0
     128: getfield      #24                 // Field adjudication:Ljava/util/List;
     131: invokeinterface #55,  1           // InterfaceMethod java/util/List.size:()I
     136: anewarray     #54                 // class org/hl7/fhir/dstu3/model/Base
     139: invokeinterface #56,  2           // InterfaceMethod java/util/List.toArray:([Ljava/lang/Object;)[Ljava/lang/Object;
     144: checkcast     #57                 // class "[Lorg/hl7/fhir/dstu3/model/Base;"
     147: areturn
     148: aload_0
     149: getfield      #32                 // Field detail:Ljava/util/List;
     152: ifnonnull     162
     155: iconst_0
     156: anewarray     #54                 // class org/hl7/fhir/dstu3/model/Base
     159: goto          186
     162: aload_0
     163: getfield      #32                 // Field detail:Ljava/util/List;
     166: aload_0
     167: getfield      #32                 // Field detail:Ljava/util/List;
     170: invokeinterface #55,  1           // InterfaceMethod java/util/List.size:()I
     175: anewarray     #54                 // class org/hl7/fhir/dstu3/model/Base
     178: invokeinterface #56,  2           // InterfaceMethod java/util/List.toArray:([Ljava/lang/Object;)[Ljava/lang/Object;
     183: checkcast     #57                 // class "[Lorg/hl7/fhir/dstu3/model/Base;"
     186: areturn
     187: aload_0
     188: iload_1
     189: aload_2
     190: iload_3
     191: invokespecial #58                 // Method org/hl7/fhir/dstu3/model/BackboneElement.getProperty:(ILjava/lang/String;Z)[Lorg/hl7/fhir/dstu3/model/Base;
     194: areturn

  public org.hl7.fhir.dstu3.model.Base setProperty(int, java.lang.String, org.hl7.fhir.dstu3.model.Base) throws org.hl7.fhir.exceptions.FHIRException;
    Code:
       0: iload_1
       1: lookupswitch  { // 4
           -1422298666: 44
           -1335224239: 88
           -1110033957: 55
            -231349275: 72
               default: 104
          }
      44: aload_0
      45: aload_0
      46: aload_3
      47: invokevirtual #59                 // Method castToPositiveInt:(Lorg/hl7/fhir/dstu3/model/Base;)Lorg/hl7/fhir/dstu3/model/PositiveIntType;
      50: putfield      #2                  // Field sequenceLinkId:Lorg/hl7/fhir/dstu3/model/PositiveIntType;
      53: aload_3
      54: areturn
      55: aload_0
      56: invokevirtual #60                 // Method getNoteNumber:()Ljava/util/List;
      59: aload_0
      60: aload_3
      61: invokevirtual #59                 // Method castToPositiveInt:(Lorg/hl7/fhir/dstu3/model/Base;)Lorg/hl7/fhir/dstu3/model/PositiveIntType;
      64: invokeinterface #22,  2           // InterfaceMethod java/util/List.add:(Ljava/lang/Object;)Z
      69: pop
      70: aload_3
      71: areturn
      72: aload_0
      73: invokevirtual #28                 // Method getAdjudication:()Ljava/util/List;
      76: aload_3
      77: checkcast     #25                 // class org/hl7/fhir/dstu3/model/ClaimResponse$AdjudicationComponent
      80: invokeinterface #22,  2           // InterfaceMethod java/util/List.add:(Ljava/lang/Object;)Z
      85: pop
      86: aload_3
      87: areturn
      88: aload_0
      89: invokevirtual #36                 // Method getDetail:()Ljava/util/List;
      92: aload_3
      93: checkcast     #33                 // class org/hl7/fhir/dstu3/model/ClaimResponse$ItemDetailComponent
      96: invokeinterface #22,  2           // InterfaceMethod java/util/List.add:(Ljava/lang/Object;)Z
     101: pop
     102: aload_3
     103: areturn
     104: aload_0
     105: iload_1
     106: aload_2
     107: aload_3
     108: invokespecial #61                 // Method org/hl7/fhir/dstu3/model/BackboneElement.setProperty:(ILjava/lang/String;Lorg/hl7/fhir/dstu3/model/Base;)Lorg/hl7/fhir/dstu3/model/Base;
     111: areturn

  public org.hl7.fhir.dstu3.model.Base setProperty(java.lang.String, org.hl7.fhir.dstu3.model.Base) throws org.hl7.fhir.exceptions.FHIRException;
    Code:
       0: aload_1
       1: ldc           #40                 // String sequenceLinkId
       3: invokevirtual #62                 // Method java/lang/String.equals:(Ljava/lang/Object;)Z
       6: ifeq          21
       9: aload_0
      10: aload_0
      11: aload_2
      12: invokevirtual #59                 // Method castToPositiveInt:(Lorg/hl7/fhir/dstu3/model/Base;)Lorg/hl7/fhir/dstu3/model/PositiveIntType;
      15: putfield      #2                  // Field sequenceLinkId:Lorg/hl7/fhir/dstu3/model/PositiveIntType;
      18: goto          107
      21: aload_1
      22: ldc           #44                 // String noteNumber
      24: invokevirtual #62                 // Method java/lang/String.equals:(Ljava/lang/Object;)Z
      27: ifeq          48
      30: aload_0
      31: invokevirtual #60                 // Method getNoteNumber:()Ljava/util/List;
      34: aload_0
      35: aload_2
      36: invokevirtual #59                 // Method castToPositiveInt:(Lorg/hl7/fhir/dstu3/model/Base;)Lorg/hl7/fhir/dstu3/model/PositiveIntType;
      39: invokeinterface #22,  2           // InterfaceMethod java/util/List.add:(Ljava/lang/Object;)Z
      44: pop
      45: goto          107
      48: aload_1
      49: ldc           #48                 // String adjudication
      51: invokevirtual #62                 // Method java/lang/String.equals:(Ljava/lang/Object;)Z
      54: ifeq          74
      57: aload_0
      58: invokevirtual #28                 // Method getAdjudication:()Ljava/util/List;
      61: aload_2
      62: checkcast     #25                 // class org/hl7/fhir/dstu3/model/ClaimResponse$AdjudicationComponent
      65: invokeinterface #22,  2           // InterfaceMethod java/util/List.add:(Ljava/lang/Object;)Z
      70: pop
      71: goto          107
      74: aload_1
      75: ldc           #51                 // String detail
      77: invokevirtual #62                 // Method java/lang/String.equals:(Ljava/lang/Object;)Z
      80: ifeq          100
      83: aload_0
      84: invokevirtual #36                 // Method getDetail:()Ljava/util/List;
      87: aload_2
      88: checkcast     #33                 // class org/hl7/fhir/dstu3/model/ClaimResponse$ItemDetailComponent
      91: invokeinterface #22,  2           // InterfaceMethod java/util/List.add:(Ljava/lang/Object;)Z
      96: pop
      97: goto          107
     100: aload_0
     101: aload_1
     102: aload_2
     103: invokespecial #63                 // Method org/hl7/fhir/dstu3/model/BackboneElement.setProperty:(Ljava/lang/String;Lorg/hl7/fhir/dstu3/model/Base;)Lorg/hl7/fhir/dstu3/model/Base;
     106: areturn
     107: aload_2
     108: areturn

  public org.hl7.fhir.dstu3.model.Base makeProperty(int, java.lang.String) throws org.hl7.fhir.exceptions.FHIRException;
    Code:
       0: iload_1
       1: lookupswitch  { // 4
           -1422298666: 44
           -1335224239: 59
           -1110033957: 49
            -231349275: 54
               default: 64
          }
      44: aload_0
      45: invokevirtual #64                 // Method getSequenceLinkIdElement:()Lorg/hl7/fhir/dstu3/model/PositiveIntType;
      48: areturn
      49: aload_0
      50: invokevirtual #65                 // Method addNoteNumberElement:()Lorg/hl7/fhir/dstu3/model/PositiveIntType;
      53: areturn
      54: aload_0
      55: invokevirtual #30                 // Method addAdjudication:()Lorg/hl7/fhir/dstu3/model/ClaimResponse$AdjudicationComponent;
      58: areturn
      59: aload_0
      60: invokevirtual #37                 // Method addDetail:()Lorg/hl7/fhir/dstu3/model/ClaimResponse$ItemDetailComponent;
      63: areturn
      64: aload_0
      65: iload_1
      66: aload_2
      67: invokespecial #66                 // Method org/hl7/fhir/dstu3/model/BackboneElement.makeProperty:(ILjava/lang/String;)Lorg/hl7/fhir/dstu3/model/Base;
      70: areturn

  public java.lang.String[] getTypesForProperty(int, java.lang.String) throws org.hl7.fhir.exceptions.FHIRException;
    Code:
       0: iload_1
       1: lookupswitch  { // 4
           -1422298666: 44
           -1335224239: 69
           -1110033957: 54
            -231349275: 64
               default: 74
          }
      44: iconst_1
      45: anewarray     #67                 // class java/lang/String
      48: dup
      49: iconst_0
      50: ldc           #41                 // String positiveInt
      52: aastore
      53: areturn
      54: iconst_1
      55: anewarray     #67                 // class java/lang/String
      58: dup
      59: iconst_0
      60: ldc           #41                 // String positiveInt
      62: aastore
      63: areturn
      64: iconst_0
      65: anewarray     #67                 // class java/lang/String
      68: areturn
      69: iconst_0
      70: anewarray     #67                 // class java/lang/String
      73: areturn
      74: aload_0
      75: iload_1
      76: aload_2
      77: invokespecial #68                 // Method org/hl7/fhir/dstu3/model/BackboneElement.getTypesForProperty:(ILjava/lang/String;)[Ljava/lang/String;
      80: areturn

  public org.hl7.fhir.dstu3.model.Base addChild(java.lang.String) throws org.hl7.fhir.exceptions.FHIRException;
    Code:
       0: aload_1
       1: ldc           #40                 // String sequenceLinkId
       3: invokevirtual #62                 // Method java/lang/String.equals:(Ljava/lang/Object;)Z
       6: ifeq          19
       9: new           #69                 // class org/hl7/fhir/exceptions/FHIRException
      12: dup
      13: ldc           #70                 // String Cannot call addChild on a primitive type ClaimResponse.sequenceLinkId
      15: invokespecial #71                 // Method org/hl7/fhir/exceptions/FHIRException."<init>":(Ljava/lang/String;)V
      18: athrow
      19: aload_1
      20: ldc           #44                 // String noteNumber
      22: invokevirtual #62                 // Method java/lang/String.equals:(Ljava/lang/Object;)Z
      25: ifeq          38
      28: new           #69                 // class org/hl7/fhir/exceptions/FHIRException
      31: dup
      32: ldc           #72                 // String Cannot call addChild on a primitive type ClaimResponse.noteNumber
      34: invokespecial #71                 // Method org/hl7/fhir/exceptions/FHIRException."<init>":(Ljava/lang/String;)V
      37: athrow
      38: aload_1
      39: ldc           #48                 // String adjudication
      41: invokevirtual #62                 // Method java/lang/String.equals:(Ljava/lang/Object;)Z
      44: ifeq          52
      47: aload_0
      48: invokevirtual #30                 // Method addAdjudication:()Lorg/hl7/fhir/dstu3/model/ClaimResponse$AdjudicationComponent;
      51: areturn
      52: aload_1
      53: ldc           #51                 // String detail
      55: invokevirtual #62                 // Method java/lang/String.equals:(Ljava/lang/Object;)Z
      58: ifeq          66
      61: aload_0
      62: invokevirtual #37                 // Method addDetail:()Lorg/hl7/fhir/dstu3/model/ClaimResponse$ItemDetailComponent;
      65: areturn
      66: aload_0
      67: aload_1
      68: invokespecial #73                 // Method org/hl7/fhir/dstu3/model/BackboneElement.addChild:(Ljava/lang/String;)Lorg/hl7/fhir/dstu3/model/Base;
      71: areturn

  public org.hl7.fhir.dstu3.model.ClaimResponse$ItemComponent copy();
    Code:
       0: new           #74                 // class org/hl7/fhir/dstu3/model/ClaimResponse$ItemComponent
       3: dup
       4: invokespecial #75                 // Method "<init>":()V
       7: astore_1
       8: aload_0
       9: aload_1
      10: invokevirtual #76                 // Method copyValues:(Lorg/hl7/fhir/dstu3/model/BackboneElement;)V
      13: aload_1
      14: aload_0
      15: getfield      #2                  // Field sequenceLinkId:Lorg/hl7/fhir/dstu3/model/PositiveIntType;
      18: ifnonnull     25
      21: aconst_null
      22: goto          32
      25: aload_0
      26: getfield      #2                  // Field sequenceLinkId:Lorg/hl7/fhir/dstu3/model/PositiveIntType;
      29: invokevirtual #77                 // Method org/hl7/fhir/dstu3/model/PositiveIntType.copy:()Lorg/hl7/fhir/dstu3/model/PositiveIntType;
      32: putfield      #2                  // Field sequenceLinkId:Lorg/hl7/fhir/dstu3/model/PositiveIntType;
      35: aload_0
      36: getfield      #16                 // Field noteNumber:Ljava/util/List;
      39: ifnull        99
      42: aload_1
      43: new           #17                 // class java/util/ArrayList
      46: dup
      47: invokespecial #18                 // Method java/util/ArrayList."<init>":()V
      50: putfield      #16                 // Field noteNumber:Ljava/util/List;
      53: aload_0
      54: getfield      #16                 // Field noteNumber:Ljava/util/List;
      57: invokeinterface #19,  1           // InterfaceMethod java/util/List.iterator:()Ljava/util/Iterator;
      62: astore_2
      63: aload_2
      64: invokeinterface #20,  1           // InterfaceMethod java/util/Iterator.hasNext:()Z
      69: ifeq          99
      72: aload_2
      73: invokeinterface #21,  1           // InterfaceMethod java/util/Iterator.next:()Ljava/lang/Object;
      78: checkcast     #8                  // class org/hl7/fhir/dstu3/model/PositiveIntType
      81: astore_3
      82: aload_1
      83: getfield      #16                 // Field noteNumber:Ljava/util/List;
      86: aload_3
      87: invokevirtual #77                 // Method org/hl7/fhir/dstu3/model/PositiveIntType.copy:()Lorg/hl7/fhir/dstu3/model/PositiveIntType;
      90: invokeinterface #22,  2           // InterfaceMethod java/util/List.add:(Ljava/lang/Object;)Z
      95: pop
      96: goto          63
      99: aload_0
     100: getfield      #24                 // Field adjudication:Ljava/util/List;
     103: ifnull        163
     106: aload_1
     107: new           #17                 // class java/util/ArrayList
     110: dup
     111: invokespecial #18                 // Method java/util/ArrayList."<init>":()V
     114: putfield      #24                 // Field adjudication:Ljava/util/List;
     117: aload_0
     118: getfield      #24                 // Field adjudication:Ljava/util/List;
     121: invokeinterface #19,  1           // InterfaceMethod java/util/List.iterator:()Ljava/util/Iterator;
     126: astore_2
     127: aload_2
     128: invokeinterface #20,  1           // InterfaceMethod java/util/Iterator.hasNext:()Z
     133: ifeq          163
     136: aload_2
     137: invokeinterface #21,  1           // InterfaceMethod java/util/Iterator.next:()Ljava/lang/Object;
     142: checkcast     #25                 // class org/hl7/fhir/dstu3/model/ClaimResponse$AdjudicationComponent
     145: astore_3
     146: aload_1
     147: getfield      #24                 // Field adjudication:Ljava/util/List;
     150: aload_3
     151: invokevirtual #78                 // Method org/hl7/fhir/dstu3/model/ClaimResponse$AdjudicationComponent.copy:()Lorg/hl7/fhir/dstu3/model/ClaimResponse$AdjudicationComponent;
     154: invokeinterface #22,  2           // InterfaceMethod java/util/List.add:(Ljava/lang/Object;)Z
     159: pop
     160: goto          127
     163: aload_0
     164: getfield      #32                 // Field detail:Ljava/util/List;
     167: ifnull        227
     170: aload_1
     171: new           #17                 // class java/util/ArrayList
     174: dup
     175: invokespecial #18                 // Method java/util/ArrayList."<init>":()V
     178: putfield      #32                 // Field detail:Ljava/util/List;
     181: aload_0
     182: getfield      #32                 // Field detail:Ljava/util/List;
     185: invokeinterface #19,  1           // InterfaceMethod java/util/List.iterator:()Ljava/util/Iterator;
     190: astore_2
     191: aload_2
     192: invokeinterface #20,  1           // InterfaceMethod java/util/Iterator.hasNext:()Z
     197: ifeq          227
     200: aload_2
     201: invokeinterface #21,  1           // InterfaceMethod java/util/Iterator.next:()Ljava/lang/Object;
     206: checkcast     #33                 // class org/hl7/fhir/dstu3/model/ClaimResponse$ItemDetailComponent
     209: astore_3
     210: aload_1
     211: getfield      #32                 // Field detail:Ljava/util/List;
     214: aload_3
     215: invokevirtual #79                 // Method org/hl7/fhir/dstu3/model/ClaimResponse$ItemDetailComponent.copy:()Lorg/hl7/fhir/dstu3/model/ClaimResponse$ItemDetailComponent;
     218: invokeinterface #22,  2           // InterfaceMethod java/util/List.add:(Ljava/lang/Object;)Z
     223: pop
     224: goto          191
     227: aload_1
     228: areturn

  public boolean equalsDeep(org.hl7.fhir.dstu3.model.Base);
    Code:
       0: aload_0
       1: aload_1
       2: invokespecial #80                 // Method org/hl7/fhir/dstu3/model/BackboneElement.equalsDeep:(Lorg/hl7/fhir/dstu3/model/Base;)Z
       5: ifne          10
       8: iconst_0
       9: ireturn
      10: aload_1
      11: instanceof    #74                 // class org/hl7/fhir/dstu3/model/ClaimResponse$ItemComponent
      14: ifne          19
      17: iconst_0
      18: ireturn
      19: aload_1
      20: checkcast     #74                 // class org/hl7/fhir/dstu3/model/ClaimResponse$ItemComponent
      23: astore_2
      24: aload_0
      25: getfield      #2                  // Field sequenceLinkId:Lorg/hl7/fhir/dstu3/model/PositiveIntType;
      28: aload_2
      29: getfield      #2                  // Field sequenceLinkId:Lorg/hl7/fhir/dstu3/model/PositiveIntType;
      32: iconst_1
      33: invokestatic  #81                 // Method compareDeep:(Lorg/hl7/fhir/dstu3/model/Base;Lorg/hl7/fhir/dstu3/model/Base;Z)Z
      36: ifeq          88
      39: aload_0
      40: getfield      #16                 // Field noteNumber:Ljava/util/List;
      43: aload_2
      44: getfield      #16                 // Field noteNumber:Ljava/util/List;
      47: iconst_1
      48: invokestatic  #82                 // Method compareDeep:(Ljava/util/List;Ljava/util/List;Z)Z
      51: ifeq          88
      54: aload_0
      55: getfield      #24                 // Field adjudication:Ljava/util/List;
      58: aload_2
      59: getfield      #24                 // Field adjudication:Ljava/util/List;
      62: iconst_1
      63: invokestatic  #82                 // Method compareDeep:(Ljava/util/List;Ljava/util/List;Z)Z
      66: ifeq          88
      69: aload_0
      70: getfield      #32                 // Field detail:Ljava/util/List;
      73: aload_2
      74: getfield      #32                 // Field detail:Ljava/util/List;
      77: iconst_1
      78: invokestatic  #82                 // Method compareDeep:(Ljava/util/List;Ljava/util/List;Z)Z
      81: ifeq          88
      84: iconst_1
      85: goto          89
      88: iconst_0
      89: ireturn

  public boolean equalsShallow(org.hl7.fhir.dstu3.model.Base);
    Code:
       0: aload_0
       1: aload_1
       2: invokespecial #83                 // Method org/hl7/fhir/dstu3/model/BackboneElement.equalsShallow:(Lorg/hl7/fhir/dstu3/model/Base;)Z
       5: ifne          10
       8: iconst_0
       9: ireturn
      10: aload_1
      11: instanceof    #74                 // class org/hl7/fhir/dstu3/model/ClaimResponse$ItemComponent
      14: ifne          19
      17: iconst_0
      18: ireturn
      19: aload_1
      20: checkcast     #74                 // class org/hl7/fhir/dstu3/model/ClaimResponse$ItemComponent
      23: astore_2
      24: aload_0
      25: getfield      #2                  // Field sequenceLinkId:Lorg/hl7/fhir/dstu3/model/PositiveIntType;
      28: aload_2
      29: getfield      #2                  // Field sequenceLinkId:Lorg/hl7/fhir/dstu3/model/PositiveIntType;
      32: iconst_1
      33: invokestatic  #84                 // Method compareValues:(Lorg/hl7/fhir/dstu3/model/PrimitiveType;Lorg/hl7/fhir/dstu3/model/PrimitiveType;Z)Z
      36: ifeq          58
      39: aload_0
      40: getfield      #16                 // Field noteNumber:Ljava/util/List;
      43: aload_2
      44: getfield      #16                 // Field noteNumber:Ljava/util/List;
      47: iconst_1
      48: invokestatic  #85                 // Method compareValues:(Ljava/util/List;Ljava/util/List;Z)Z
      51: ifeq          58
      54: iconst_1
      55: goto          59
      58: iconst_0
      59: ireturn

  public boolean isEmpty();
    Code:
       0: aload_0
       1: invokespecial #86                 // Method org/hl7/fhir/dstu3/model/BackboneElement.isEmpty:()Z
       4: ifeq          49
       7: iconst_4
       8: anewarray     #87                 // class java/lang/Object
      11: dup
      12: iconst_0
      13: aload_0
      14: getfield      #2                  // Field sequenceLinkId:Lorg/hl7/fhir/dstu3/model/PositiveIntType;
      17: aastore
      18: dup
      19: iconst_1
      20: aload_0
      21: getfield      #16                 // Field noteNumber:Ljava/util/List;
      24: aastore
      25: dup
      26: iconst_2
      27: aload_0
      28: getfield      #24                 // Field adjudication:Ljava/util/List;
      31: aastore
      32: dup
      33: iconst_3
      34: aload_0
      35: getfield      #32                 // Field detail:Ljava/util/List;
      38: aastore
      39: invokestatic  #88                 // Method ca/uhn/fhir/util/ElementUtil.isEmpty:([Ljava/lang/Object;)Z
      42: ifeq          49
      45: iconst_1
      46: goto          50
      49: iconst_0
      50: ireturn

  public java.lang.String fhirType();
    Code:
       0: ldc           #89                 // String ClaimResponse.item
       2: areturn

  public org.hl7.fhir.dstu3.model.BackboneElement copy();
    Code:
       0: aload_0
       1: invokevirtual #90                 // Method copy:()Lorg/hl7/fhir/dstu3/model/ClaimResponse$ItemComponent;
       4: areturn

  public org.hl7.fhir.dstu3.model.Element copy();
    Code:
       0: aload_0
       1: invokevirtual #90                 // Method copy:()Lorg/hl7/fhir/dstu3/model/ClaimResponse$ItemComponent;
       4: areturn
}
