Compiled from "ClaimResponse.java"
public class org.hl7.fhir.dstu3.model.ClaimResponse$InsuranceComponent extends org.hl7.fhir.dstu3.model.BackboneElement implements org.hl7.fhir.instance.model.api.IBaseBackboneElement {
  protected org.hl7.fhir.dstu3.model.PositiveIntType sequence;

  protected org.hl7.fhir.dstu3.model.BooleanType focal;

  protected org.hl7.fhir.dstu3.model.Reference coverage;

  protected org.hl7.fhir.dstu3.model.Coverage coverageTarget;

  protected org.hl7.fhir.dstu3.model.StringType businessArrangement;

  protected java.util.List<org.hl7.fhir.dstu3.model.StringType> preAuthRef;

  protected org.hl7.fhir.dstu3.model.Reference claimResponse;

  protected org.hl7.fhir.dstu3.model.ClaimResponse claimResponseTarget;

  private static final long serialVersionUID;

  public org.hl7.fhir.dstu3.model.ClaimResponse$InsuranceComponent();
    Code:
       0: aload_0
       1: invokespecial #1                  // Method org/hl7/fhir/dstu3/model/BackboneElement."<init>":()V
       4: return

  public org.hl7.fhir.dstu3.model.ClaimResponse$InsuranceComponent(org.hl7.fhir.dstu3.model.PositiveIntType, org.hl7.fhir.dstu3.model.BooleanType, org.hl7.fhir.dstu3.model.Reference);
    Code:
       0: aload_0
       1: invokespecial #1                  // Method org/hl7/fhir/dstu3/model/BackboneElement."<init>":()V
       4: aload_0
       5: aload_1
       6: putfield      #2                  // Field sequence:Lorg/hl7/fhir/dstu3/model/PositiveIntType;
       9: aload_0
      10: aload_2
      11: putfield      #3                  // Field focal:Lorg/hl7/fhir/dstu3/model/BooleanType;
      14: aload_0
      15: aload_3
      16: putfield      #4                  // Field coverage:Lorg/hl7/fhir/dstu3/model/Reference;
      19: return

  public org.hl7.fhir.dstu3.model.PositiveIntType getSequenceElement();
    Code:
       0: aload_0
       1: getfield      #2                  // Field sequence:Lorg/hl7/fhir/dstu3/model/PositiveIntType;
       4: ifnonnull     40
       7: invokestatic  #5                  // Method org/hl7/fhir/dstu3/model/Configuration.errorOnAutoCreate:()Z
      10: ifeq          23
      13: new           #6                  // class java/lang/Error
      16: dup
      17: ldc           #7                  // String Attempt to auto-create InsuranceComponent.sequence
      19: invokespecial #8                  // Method java/lang/Error."<init>":(Ljava/lang/String;)V
      22: athrow
      23: invokestatic  #9                  // Method org/hl7/fhir/dstu3/model/Configuration.doAutoCreate:()Z
      26: ifeq          40
      29: aload_0
      30: new           #10                 // class org/hl7/fhir/dstu3/model/PositiveIntType
      33: dup
      34: invokespecial #11                 // Method org/hl7/fhir/dstu3/model/PositiveIntType."<init>":()V
      37: putfield      #2                  // Field sequence:Lorg/hl7/fhir/dstu3/model/PositiveIntType;
      40: aload_0
      41: getfield      #2                  // Field sequence:Lorg/hl7/fhir/dstu3/model/PositiveIntType;
      44: areturn

  public boolean hasSequenceElement();
    Code:
       0: aload_0
       1: getfield      #2                  // Field sequence:Lorg/hl7/fhir/dstu3/model/PositiveIntType;
       4: ifnull        21
       7: aload_0
       8: getfield      #2                  // Field sequence:Lorg/hl7/fhir/dstu3/model/PositiveIntType;
      11: invokevirtual #12                 // Method org/hl7/fhir/dstu3/model/PositiveIntType.isEmpty:()Z
      14: ifne          21
      17: iconst_1
      18: goto          22
      21: iconst_0
      22: ireturn

  public boolean hasSequence();
    Code:
       0: aload_0
       1: getfield      #2                  // Field sequence:Lorg/hl7/fhir/dstu3/model/PositiveIntType;
       4: ifnull        21
       7: aload_0
       8: getfield      #2                  // Field sequence:Lorg/hl7/fhir/dstu3/model/PositiveIntType;
      11: invokevirtual #12                 // Method org/hl7/fhir/dstu3/model/PositiveIntType.isEmpty:()Z
      14: ifne          21
      17: iconst_1
      18: goto          22
      21: iconst_0
      22: ireturn

  public org.hl7.fhir.dstu3.model.ClaimResponse$InsuranceComponent setSequenceElement(org.hl7.fhir.dstu3.model.PositiveIntType);
    Code:
       0: aload_0
       1: aload_1
       2: putfield      #2                  // Field sequence:Lorg/hl7/fhir/dstu3/model/PositiveIntType;
       5: aload_0
       6: areturn

  public int getSequence();
    Code:
       0: aload_0
       1: getfield      #2                  // Field sequence:Lorg/hl7/fhir/dstu3/model/PositiveIntType;
       4: ifnull        17
       7: aload_0
       8: getfield      #2                  // Field sequence:Lorg/hl7/fhir/dstu3/model/PositiveIntType;
      11: invokevirtual #12                 // Method org/hl7/fhir/dstu3/model/PositiveIntType.isEmpty:()Z
      14: ifeq          21
      17: iconst_0
      18: goto          34
      21: aload_0
      22: getfield      #2                  // Field sequence:Lorg/hl7/fhir/dstu3/model/PositiveIntType;
      25: invokevirtual #13                 // Method org/hl7/fhir/dstu3/model/PositiveIntType.getValue:()Ljava/lang/Object;
      28: checkcast     #14                 // class java/lang/Integer
      31: invokevirtual #15                 // Method java/lang/Integer.intValue:()I
      34: ireturn

  public org.hl7.fhir.dstu3.model.ClaimResponse$InsuranceComponent setSequence(int);
    Code:
       0: aload_0
       1: getfield      #2                  // Field sequence:Lorg/hl7/fhir/dstu3/model/PositiveIntType;
       4: ifnonnull     18
       7: aload_0
       8: new           #10                 // class org/hl7/fhir/dstu3/model/PositiveIntType
      11: dup
      12: invokespecial #11                 // Method org/hl7/fhir/dstu3/model/PositiveIntType."<init>":()V
      15: putfield      #2                  // Field sequence:Lorg/hl7/fhir/dstu3/model/PositiveIntType;
      18: aload_0
      19: getfield      #2                  // Field sequence:Lorg/hl7/fhir/dstu3/model/PositiveIntType;
      22: iload_1
      23: invokestatic  #16                 // Method java/lang/Integer.valueOf:(I)Ljava/lang/Integer;
      26: invokevirtual #17                 // Method org/hl7/fhir/dstu3/model/PositiveIntType.setValue:(Ljava/lang/Object;)Lorg/hl7/fhir/dstu3/model/PrimitiveType;
      29: pop
      30: aload_0
      31: areturn

  public org.hl7.fhir.dstu3.model.BooleanType getFocalElement();
    Code:
       0: aload_0
       1: getfield      #3                  // Field focal:Lorg/hl7/fhir/dstu3/model/BooleanType;
       4: ifnonnull     40
       7: invokestatic  #5                  // Method org/hl7/fhir/dstu3/model/Configuration.errorOnAutoCreate:()Z
      10: ifeq          23
      13: new           #6                  // class java/lang/Error
      16: dup
      17: ldc           #18                 // String Attempt to auto-create InsuranceComponent.focal
      19: invokespecial #8                  // Method java/lang/Error."<init>":(Ljava/lang/String;)V
      22: athrow
      23: invokestatic  #9                  // Method org/hl7/fhir/dstu3/model/Configuration.doAutoCreate:()Z
      26: ifeq          40
      29: aload_0
      30: new           #19                 // class org/hl7/fhir/dstu3/model/BooleanType
      33: dup
      34: invokespecial #20                 // Method org/hl7/fhir/dstu3/model/BooleanType."<init>":()V
      37: putfield      #3                  // Field focal:Lorg/hl7/fhir/dstu3/model/BooleanType;
      40: aload_0
      41: getfield      #3                  // Field focal:Lorg/hl7/fhir/dstu3/model/BooleanType;
      44: areturn

  public boolean hasFocalElement();
    Code:
       0: aload_0
       1: getfield      #3                  // Field focal:Lorg/hl7/fhir/dstu3/model/BooleanType;
       4: ifnull        21
       7: aload_0
       8: getfield      #3                  // Field focal:Lorg/hl7/fhir/dstu3/model/BooleanType;
      11: invokevirtual #21                 // Method org/hl7/fhir/dstu3/model/BooleanType.isEmpty:()Z
      14: ifne          21
      17: iconst_1
      18: goto          22
      21: iconst_0
      22: ireturn

  public boolean hasFocal();
    Code:
       0: aload_0
       1: getfield      #3                  // Field focal:Lorg/hl7/fhir/dstu3/model/BooleanType;
       4: ifnull        21
       7: aload_0
       8: getfield      #3                  // Field focal:Lorg/hl7/fhir/dstu3/model/BooleanType;
      11: invokevirtual #21                 // Method org/hl7/fhir/dstu3/model/BooleanType.isEmpty:()Z
      14: ifne          21
      17: iconst_1
      18: goto          22
      21: iconst_0
      22: ireturn

  public org.hl7.fhir.dstu3.model.ClaimResponse$InsuranceComponent setFocalElement(org.hl7.fhir.dstu3.model.BooleanType);
    Code:
       0: aload_0
       1: aload_1
       2: putfield      #3                  // Field focal:Lorg/hl7/fhir/dstu3/model/BooleanType;
       5: aload_0
       6: areturn

  public boolean getFocal();
    Code:
       0: aload_0
       1: getfield      #3                  // Field focal:Lorg/hl7/fhir/dstu3/model/BooleanType;
       4: ifnull        17
       7: aload_0
       8: getfield      #3                  // Field focal:Lorg/hl7/fhir/dstu3/model/BooleanType;
      11: invokevirtual #21                 // Method org/hl7/fhir/dstu3/model/BooleanType.isEmpty:()Z
      14: ifeq          21
      17: iconst_0
      18: goto          34
      21: aload_0
      22: getfield      #3                  // Field focal:Lorg/hl7/fhir/dstu3/model/BooleanType;
      25: invokevirtual #22                 // Method org/hl7/fhir/dstu3/model/BooleanType.getValue:()Ljava/lang/Object;
      28: checkcast     #23                 // class java/lang/Boolean
      31: invokevirtual #24                 // Method java/lang/Boolean.booleanValue:()Z
      34: ireturn

  public org.hl7.fhir.dstu3.model.ClaimResponse$InsuranceComponent setFocal(boolean);
    Code:
       0: aload_0
       1: getfield      #3                  // Field focal:Lorg/hl7/fhir/dstu3/model/BooleanType;
       4: ifnonnull     18
       7: aload_0
       8: new           #19                 // class org/hl7/fhir/dstu3/model/BooleanType
      11: dup
      12: invokespecial #20                 // Method org/hl7/fhir/dstu3/model/BooleanType."<init>":()V
      15: putfield      #3                  // Field focal:Lorg/hl7/fhir/dstu3/model/BooleanType;
      18: aload_0
      19: getfield      #3                  // Field focal:Lorg/hl7/fhir/dstu3/model/BooleanType;
      22: iload_1
      23: invokestatic  #25                 // Method java/lang/Boolean.valueOf:(Z)Ljava/lang/Boolean;
      26: invokevirtual #26                 // Method org/hl7/fhir/dstu3/model/BooleanType.setValue:(Ljava/lang/Object;)Lorg/hl7/fhir/dstu3/model/PrimitiveType;
      29: pop
      30: aload_0
      31: areturn

  public org.hl7.fhir.dstu3.model.Reference getCoverage();
    Code:
       0: aload_0
       1: getfield      #4                  // Field coverage:Lorg/hl7/fhir/dstu3/model/Reference;
       4: ifnonnull     40
       7: invokestatic  #5                  // Method org/hl7/fhir/dstu3/model/Configuration.errorOnAutoCreate:()Z
      10: ifeq          23
      13: new           #6                  // class java/lang/Error
      16: dup
      17: ldc           #27                 // String Attempt to auto-create InsuranceComponent.coverage
      19: invokespecial #8                  // Method java/lang/Error."<init>":(Ljava/lang/String;)V
      22: athrow
      23: invokestatic  #9                  // Method org/hl7/fhir/dstu3/model/Configuration.doAutoCreate:()Z
      26: ifeq          40
      29: aload_0
      30: new           #28                 // class org/hl7/fhir/dstu3/model/Reference
      33: dup
      34: invokespecial #29                 // Method org/hl7/fhir/dstu3/model/Reference."<init>":()V
      37: putfield      #4                  // Field coverage:Lorg/hl7/fhir/dstu3/model/Reference;
      40: aload_0
      41: getfield      #4                  // Field coverage:Lorg/hl7/fhir/dstu3/model/Reference;
      44: areturn

  public boolean hasCoverage();
    Code:
       0: aload_0
       1: getfield      #4                  // Field coverage:Lorg/hl7/fhir/dstu3/model/Reference;
       4: ifnull        21
       7: aload_0
       8: getfield      #4                  // Field coverage:Lorg/hl7/fhir/dstu3/model/Reference;
      11: invokevirtual #30                 // Method org/hl7/fhir/dstu3/model/Reference.isEmpty:()Z
      14: ifne          21
      17: iconst_1
      18: goto          22
      21: iconst_0
      22: ireturn

  public org.hl7.fhir.dstu3.model.ClaimResponse$InsuranceComponent setCoverage(org.hl7.fhir.dstu3.model.Reference);
    Code:
       0: aload_0
       1: aload_1
       2: putfield      #4                  // Field coverage:Lorg/hl7/fhir/dstu3/model/Reference;
       5: aload_0
       6: areturn

  public org.hl7.fhir.dstu3.model.Coverage getCoverageTarget();
    Code:
       0: aload_0
       1: getfield      #31                 // Field coverageTarget:Lorg/hl7/fhir/dstu3/model/Coverage;
       4: ifnonnull     40
       7: invokestatic  #5                  // Method org/hl7/fhir/dstu3/model/Configuration.errorOnAutoCreate:()Z
      10: ifeq          23
      13: new           #6                  // class java/lang/Error
      16: dup
      17: ldc           #27                 // String Attempt to auto-create InsuranceComponent.coverage
      19: invokespecial #8                  // Method java/lang/Error."<init>":(Ljava/lang/String;)V
      22: athrow
      23: invokestatic  #9                  // Method org/hl7/fhir/dstu3/model/Configuration.doAutoCreate:()Z
      26: ifeq          40
      29: aload_0
      30: new           #32                 // class org/hl7/fhir/dstu3/model/Coverage
      33: dup
      34: invokespecial #33                 // Method org/hl7/fhir/dstu3/model/Coverage."<init>":()V
      37: putfield      #31                 // Field coverageTarget:Lorg/hl7/fhir/dstu3/model/Coverage;
      40: aload_0
      41: getfield      #31                 // Field coverageTarget:Lorg/hl7/fhir/dstu3/model/Coverage;
      44: areturn

  public org.hl7.fhir.dstu3.model.ClaimResponse$InsuranceComponent setCoverageTarget(org.hl7.fhir.dstu3.model.Coverage);
    Code:
       0: aload_0
       1: aload_1
       2: putfield      #31                 // Field coverageTarget:Lorg/hl7/fhir/dstu3/model/Coverage;
       5: aload_0
       6: areturn

  public org.hl7.fhir.dstu3.model.StringType getBusinessArrangementElement();
    Code:
       0: aload_0
       1: getfield      #34                 // Field businessArrangement:Lorg/hl7/fhir/dstu3/model/StringType;
       4: ifnonnull     40
       7: invokestatic  #5                  // Method org/hl7/fhir/dstu3/model/Configuration.errorOnAutoCreate:()Z
      10: ifeq          23
      13: new           #6                  // class java/lang/Error
      16: dup
      17: ldc           #35                 // String Attempt to auto-create InsuranceComponent.businessArrangement
      19: invokespecial #8                  // Method java/lang/Error."<init>":(Ljava/lang/String;)V
      22: athrow
      23: invokestatic  #9                  // Method org/hl7/fhir/dstu3/model/Configuration.doAutoCreate:()Z
      26: ifeq          40
      29: aload_0
      30: new           #36                 // class org/hl7/fhir/dstu3/model/StringType
      33: dup
      34: invokespecial #37                 // Method org/hl7/fhir/dstu3/model/StringType."<init>":()V
      37: putfield      #34                 // Field businessArrangement:Lorg/hl7/fhir/dstu3/model/StringType;
      40: aload_0
      41: getfield      #34                 // Field businessArrangement:Lorg/hl7/fhir/dstu3/model/StringType;
      44: areturn

  public boolean hasBusinessArrangementElement();
    Code:
       0: aload_0
       1: getfield      #34                 // Field businessArrangement:Lorg/hl7/fhir/dstu3/model/StringType;
       4: ifnull        21
       7: aload_0
       8: getfield      #34                 // Field businessArrangement:Lorg/hl7/fhir/dstu3/model/StringType;
      11: invokevirtual #38                 // Method org/hl7/fhir/dstu3/model/StringType.isEmpty:()Z
      14: ifne          21
      17: iconst_1
      18: goto          22
      21: iconst_0
      22: ireturn

  public boolean hasBusinessArrangement();
    Code:
       0: aload_0
       1: getfield      #34                 // Field businessArrangement:Lorg/hl7/fhir/dstu3/model/StringType;
       4: ifnull        21
       7: aload_0
       8: getfield      #34                 // Field businessArrangement:Lorg/hl7/fhir/dstu3/model/StringType;
      11: invokevirtual #38                 // Method org/hl7/fhir/dstu3/model/StringType.isEmpty:()Z
      14: ifne          21
      17: iconst_1
      18: goto          22
      21: iconst_0
      22: ireturn

  public org.hl7.fhir.dstu3.model.ClaimResponse$InsuranceComponent setBusinessArrangementElement(org.hl7.fhir.dstu3.model.StringType);
    Code:
       0: aload_0
       1: aload_1
       2: putfield      #34                 // Field businessArrangement:Lorg/hl7/fhir/dstu3/model/StringType;
       5: aload_0
       6: areturn

  public java.lang.String getBusinessArrangement();
    Code:
       0: aload_0
       1: getfield      #34                 // Field businessArrangement:Lorg/hl7/fhir/dstu3/model/StringType;
       4: ifnonnull     11
       7: aconst_null
       8: goto          21
      11: aload_0
      12: getfield      #34                 // Field businessArrangement:Lorg/hl7/fhir/dstu3/model/StringType;
      15: invokevirtual #39                 // Method org/hl7/fhir/dstu3/model/StringType.getValue:()Ljava/lang/Object;
      18: checkcast     #40                 // class java/lang/String
      21: areturn

  public org.hl7.fhir.dstu3.model.ClaimResponse$InsuranceComponent setBusinessArrangement(java.lang.String);
    Code:
       0: aload_1
       1: invokestatic  #41                 // Method org/hl7/fhir/utilities/Utilities.noString:(Ljava/lang/String;)Z
       4: ifeq          15
       7: aload_0
       8: aconst_null
       9: putfield      #34                 // Field businessArrangement:Lorg/hl7/fhir/dstu3/model/StringType;
      12: goto          42
      15: aload_0
      16: getfield      #34                 // Field businessArrangement:Lorg/hl7/fhir/dstu3/model/StringType;
      19: ifnonnull     33
      22: aload_0
      23: new           #36                 // class org/hl7/fhir/dstu3/model/StringType
      26: dup
      27: invokespecial #37                 // Method org/hl7/fhir/dstu3/model/StringType."<init>":()V
      30: putfield      #34                 // Field businessArrangement:Lorg/hl7/fhir/dstu3/model/StringType;
      33: aload_0
      34: getfield      #34                 // Field businessArrangement:Lorg/hl7/fhir/dstu3/model/StringType;
      37: aload_1
      38: invokevirtual #42                 // Method org/hl7/fhir/dstu3/model/StringType.setValue:(Ljava/lang/Object;)Lorg/hl7/fhir/dstu3/model/PrimitiveType;
      41: pop
      42: aload_0
      43: areturn

  public java.util.List<org.hl7.fhir.dstu3.model.StringType> getPreAuthRef();
    Code:
       0: aload_0
       1: getfield      #43                 // Field preAuthRef:Ljava/util/List;
       4: ifnonnull     18
       7: aload_0
       8: new           #44                 // class java/util/ArrayList
      11: dup
      12: invokespecial #45                 // Method java/util/ArrayList."<init>":()V
      15: putfield      #43                 // Field preAuthRef:Ljava/util/List;
      18: aload_0
      19: getfield      #43                 // Field preAuthRef:Ljava/util/List;
      22: areturn

  public org.hl7.fhir.dstu3.model.ClaimResponse$InsuranceComponent setPreAuthRef(java.util.List<org.hl7.fhir.dstu3.model.StringType>);
    Code:
       0: aload_0
       1: aload_1
       2: putfield      #43                 // Field preAuthRef:Ljava/util/List;
       5: aload_0
       6: areturn

  public boolean hasPreAuthRef();
    Code:
       0: aload_0
       1: getfield      #43                 // Field preAuthRef:Ljava/util/List;
       4: ifnonnull     9
       7: iconst_0
       8: ireturn
       9: aload_0
      10: getfield      #43                 // Field preAuthRef:Ljava/util/List;
      13: invokeinterface #46,  1           // InterfaceMethod java/util/List.iterator:()Ljava/util/Iterator;
      18: astore_1
      19: aload_1
      20: invokeinterface #47,  1           // InterfaceMethod java/util/Iterator.hasNext:()Z
      25: ifeq          50
      28: aload_1
      29: invokeinterface #48,  1           // InterfaceMethod java/util/Iterator.next:()Ljava/lang/Object;
      34: checkcast     #36                 // class org/hl7/fhir/dstu3/model/StringType
      37: astore_2
      38: aload_2
      39: invokevirtual #38                 // Method org/hl7/fhir/dstu3/model/StringType.isEmpty:()Z
      42: ifne          47
      45: iconst_1
      46: ireturn
      47: goto          19
      50: iconst_0
      51: ireturn

  public org.hl7.fhir.dstu3.model.StringType addPreAuthRefElement();
    Code:
       0: new           #36                 // class org/hl7/fhir/dstu3/model/StringType
       3: dup
       4: invokespecial #37                 // Method org/hl7/fhir/dstu3/model/StringType."<init>":()V
       7: astore_1
       8: aload_0
       9: getfield      #43                 // Field preAuthRef:Ljava/util/List;
      12: ifnonnull     26
      15: aload_0
      16: new           #44                 // class java/util/ArrayList
      19: dup
      20: invokespecial #45                 // Method java/util/ArrayList."<init>":()V
      23: putfield      #43                 // Field preAuthRef:Ljava/util/List;
      26: aload_0
      27: getfield      #43                 // Field preAuthRef:Ljava/util/List;
      30: aload_1
      31: invokeinterface #49,  2           // InterfaceMethod java/util/List.add:(Ljava/lang/Object;)Z
      36: pop
      37: aload_1
      38: areturn

  public org.hl7.fhir.dstu3.model.ClaimResponse$InsuranceComponent addPreAuthRef(java.lang.String);
    Code:
       0: new           #36                 // class org/hl7/fhir/dstu3/model/StringType
       3: dup
       4: invokespecial #37                 // Method org/hl7/fhir/dstu3/model/StringType."<init>":()V
       7: astore_2
       8: aload_2
       9: aload_1
      10: invokevirtual #42                 // Method org/hl7/fhir/dstu3/model/StringType.setValue:(Ljava/lang/Object;)Lorg/hl7/fhir/dstu3/model/PrimitiveType;
      13: pop
      14: aload_0
      15: getfield      #43                 // Field preAuthRef:Ljava/util/List;
      18: ifnonnull     32
      21: aload_0
      22: new           #44                 // class java/util/ArrayList
      25: dup
      26: invokespecial #45                 // Method java/util/ArrayList."<init>":()V
      29: putfield      #43                 // Field preAuthRef:Ljava/util/List;
      32: aload_0
      33: getfield      #43                 // Field preAuthRef:Ljava/util/List;
      36: aload_2
      37: invokeinterface #49,  2           // InterfaceMethod java/util/List.add:(Ljava/lang/Object;)Z
      42: pop
      43: aload_0
      44: areturn

  public boolean hasPreAuthRef(java.lang.String);
    Code:
       0: aload_0
       1: getfield      #43                 // Field preAuthRef:Ljava/util/List;
       4: ifnonnull     9
       7: iconst_0
       8: ireturn
       9: aload_0
      10: getfield      #43                 // Field preAuthRef:Ljava/util/List;
      13: invokeinterface #46,  1           // InterfaceMethod java/util/List.iterator:()Ljava/util/Iterator;
      18: astore_2
      19: aload_2
      20: invokeinterface #47,  1           // InterfaceMethod java/util/Iterator.hasNext:()Z
      25: ifeq          57
      28: aload_2
      29: invokeinterface #48,  1           // InterfaceMethod java/util/Iterator.next:()Ljava/lang/Object;
      34: checkcast     #36                 // class org/hl7/fhir/dstu3/model/StringType
      37: astore_3
      38: aload_3
      39: invokevirtual #39                 // Method org/hl7/fhir/dstu3/model/StringType.getValue:()Ljava/lang/Object;
      42: checkcast     #40                 // class java/lang/String
      45: aload_1
      46: invokevirtual #50                 // Method java/lang/String.equals:(Ljava/lang/Object;)Z
      49: ifeq          54
      52: iconst_1
      53: ireturn
      54: goto          19
      57: iconst_0
      58: ireturn

  public org.hl7.fhir.dstu3.model.Reference getClaimResponse();
    Code:
       0: aload_0
       1: getfield      #51                 // Field claimResponse:Lorg/hl7/fhir/dstu3/model/Reference;
       4: ifnonnull     40
       7: invokestatic  #5                  // Method org/hl7/fhir/dstu3/model/Configuration.errorOnAutoCreate:()Z
      10: ifeq          23
      13: new           #6                  // class java/lang/Error
      16: dup
      17: ldc           #52                 // String Attempt to auto-create InsuranceComponent.claimResponse
      19: invokespecial #8                  // Method java/lang/Error."<init>":(Ljava/lang/String;)V
      22: athrow
      23: invokestatic  #9                  // Method org/hl7/fhir/dstu3/model/Configuration.doAutoCreate:()Z
      26: ifeq          40
      29: aload_0
      30: new           #28                 // class org/hl7/fhir/dstu3/model/Reference
      33: dup
      34: invokespecial #29                 // Method org/hl7/fhir/dstu3/model/Reference."<init>":()V
      37: putfield      #51                 // Field claimResponse:Lorg/hl7/fhir/dstu3/model/Reference;
      40: aload_0
      41: getfield      #51                 // Field claimResponse:Lorg/hl7/fhir/dstu3/model/Reference;
      44: areturn

  public boolean hasClaimResponse();
    Code:
       0: aload_0
       1: getfield      #51                 // Field claimResponse:Lorg/hl7/fhir/dstu3/model/Reference;
       4: ifnull        21
       7: aload_0
       8: getfield      #51                 // Field claimResponse:Lorg/hl7/fhir/dstu3/model/Reference;
      11: invokevirtual #30                 // Method org/hl7/fhir/dstu3/model/Reference.isEmpty:()Z
      14: ifne          21
      17: iconst_1
      18: goto          22
      21: iconst_0
      22: ireturn

  public org.hl7.fhir.dstu3.model.ClaimResponse$InsuranceComponent setClaimResponse(org.hl7.fhir.dstu3.model.Reference);
    Code:
       0: aload_0
       1: aload_1
       2: putfield      #51                 // Field claimResponse:Lorg/hl7/fhir/dstu3/model/Reference;
       5: aload_0
       6: areturn

  public org.hl7.fhir.dstu3.model.ClaimResponse getClaimResponseTarget();
    Code:
       0: aload_0
       1: getfield      #53                 // Field claimResponseTarget:Lorg/hl7/fhir/dstu3/model/ClaimResponse;
       4: ifnonnull     40
       7: invokestatic  #5                  // Method org/hl7/fhir/dstu3/model/Configuration.errorOnAutoCreate:()Z
      10: ifeq          23
      13: new           #6                  // class java/lang/Error
      16: dup
      17: ldc           #52                 // String Attempt to auto-create InsuranceComponent.claimResponse
      19: invokespecial #8                  // Method java/lang/Error."<init>":(Ljava/lang/String;)V
      22: athrow
      23: invokestatic  #9                  // Method org/hl7/fhir/dstu3/model/Configuration.doAutoCreate:()Z
      26: ifeq          40
      29: aload_0
      30: new           #54                 // class org/hl7/fhir/dstu3/model/ClaimResponse
      33: dup
      34: invokespecial #55                 // Method org/hl7/fhir/dstu3/model/ClaimResponse."<init>":()V
      37: putfield      #53                 // Field claimResponseTarget:Lorg/hl7/fhir/dstu3/model/ClaimResponse;
      40: aload_0
      41: getfield      #53                 // Field claimResponseTarget:Lorg/hl7/fhir/dstu3/model/ClaimResponse;
      44: areturn

  public org.hl7.fhir.dstu3.model.ClaimResponse$InsuranceComponent setClaimResponseTarget(org.hl7.fhir.dstu3.model.ClaimResponse);
    Code:
       0: aload_0
       1: aload_1
       2: putfield      #53                 // Field claimResponseTarget:Lorg/hl7/fhir/dstu3/model/ClaimResponse;
       5: aload_0
       6: areturn

  protected void listChildren(java.util.List<org.hl7.fhir.dstu3.model.Property>);
    Code:
       0: aload_0
       1: aload_1
       2: invokespecial #56                 // Method org/hl7/fhir/dstu3/model/BackboneElement.listChildren:(Ljava/util/List;)V
       5: aload_1
       6: new           #57                 // class org/hl7/fhir/dstu3/model/Property
       9: dup
      10: ldc           #58                 // String sequence
      12: ldc           #59                 // String positiveInt
      14: ldc           #60                 // String A service line item.
      16: iconst_0
      17: iconst_1
      18: aload_0
      19: getfield      #2                  // Field sequence:Lorg/hl7/fhir/dstu3/model/PositiveIntType;
      22: invokespecial #61                 // Method org/hl7/fhir/dstu3/model/Property."<init>":(Ljava/lang/String;Ljava/lang/String;Ljava/lang/String;IILorg/hl7/fhir/dstu3/model/Base;)V
      25: invokeinterface #49,  2           // InterfaceMethod java/util/List.add:(Ljava/lang/Object;)Z
      30: pop
      31: aload_1
      32: new           #57                 // class org/hl7/fhir/dstu3/model/Property
      35: dup
      36: ldc           #62                 // String focal
      38: ldc           #63                 // String boolean
      40: ldc           #64                 // String The instance number of the Coverage which is the focus for adjudication. The Coverage against which the claim is to be adjudicated.
      42: iconst_0
      43: iconst_1
      44: aload_0
      45: getfield      #3                  // Field focal:Lorg/hl7/fhir/dstu3/model/BooleanType;
      48: invokespecial #61                 // Method org/hl7/fhir/dstu3/model/Property."<init>":(Ljava/lang/String;Ljava/lang/String;Ljava/lang/String;IILorg/hl7/fhir/dstu3/model/Base;)V
      51: invokeinterface #49,  2           // InterfaceMethod java/util/List.add:(Ljava/lang/Object;)Z
      56: pop
      57: aload_1
      58: new           #57                 // class org/hl7/fhir/dstu3/model/Property
      61: dup
      62: ldc           #65                 // String coverage
      64: ldc           #66                 // String Reference(Coverage)
      66: ldc           #67                 // String Reference to the program or plan identification, underwriter or payor.
      68: iconst_0
      69: iconst_1
      70: aload_0
      71: getfield      #4                  // Field coverage:Lorg/hl7/fhir/dstu3/model/Reference;
      74: invokespecial #61                 // Method org/hl7/fhir/dstu3/model/Property."<init>":(Ljava/lang/String;Ljava/lang/String;Ljava/lang/String;IILorg/hl7/fhir/dstu3/model/Base;)V
      77: invokeinterface #49,  2           // InterfaceMethod java/util/List.add:(Ljava/lang/Object;)Z
      82: pop
      83: aload_1
      84: new           #57                 // class org/hl7/fhir/dstu3/model/Property
      87: dup
      88: ldc           #68                 // String businessArrangement
      90: ldc           #69                 // String string
      92: ldc           #70                 // String The contract number of a business agreement which describes the terms and conditions.
      94: iconst_0
      95: iconst_1
      96: aload_0
      97: getfield      #34                 // Field businessArrangement:Lorg/hl7/fhir/dstu3/model/StringType;
     100: invokespecial #61                 // Method org/hl7/fhir/dstu3/model/Property."<init>":(Ljava/lang/String;Ljava/lang/String;Ljava/lang/String;IILorg/hl7/fhir/dstu3/model/Base;)V
     103: invokeinterface #49,  2           // InterfaceMethod java/util/List.add:(Ljava/lang/Object;)Z
     108: pop
     109: aload_1
     110: new           #57                 // class org/hl7/fhir/dstu3/model/Property
     113: dup
     114: ldc           #71                 // String preAuthRef
     116: ldc           #69                 // String string
     118: ldc           #72                 // String A list of references from the Insurer to which these services pertain.
     120: iconst_0
     121: ldc           #73                 // int 2147483647
     123: aload_0
     124: getfield      #43                 // Field preAuthRef:Ljava/util/List;
     127: invokespecial #74                 // Method org/hl7/fhir/dstu3/model/Property."<init>":(Ljava/lang/String;Ljava/lang/String;Ljava/lang/String;IILjava/util/List;)V
     130: invokeinterface #49,  2           // InterfaceMethod java/util/List.add:(Ljava/lang/Object;)Z
     135: pop
     136: aload_1
     137: new           #57                 // class org/hl7/fhir/dstu3/model/Property
     140: dup
     141: ldc           #75                 // String claimResponse
     143: ldc           #76                 // String Reference(ClaimResponse)
     145: ldc           #77                 // String The Coverages adjudication details.
     147: iconst_0
     148: iconst_1
     149: aload_0
     150: getfield      #51                 // Field claimResponse:Lorg/hl7/fhir/dstu3/model/Reference;
     153: invokespecial #61                 // Method org/hl7/fhir/dstu3/model/Property."<init>":(Ljava/lang/String;Ljava/lang/String;Ljava/lang/String;IILorg/hl7/fhir/dstu3/model/Base;)V
     156: invokeinterface #49,  2           // InterfaceMethod java/util/List.add:(Ljava/lang/Object;)Z
     161: pop
     162: return

  public org.hl7.fhir.dstu3.model.Property getNamedProperty(int, java.lang.String, boolean) throws org.hl7.fhir.exceptions.FHIRException;
    Code:
       0: iload_1
       1: lookupswitch  { // 6
            -351767064: 100
              97604197: 80
             259920682: 120
             522246568: 140
             689513629: 161
            1349547969: 60
               default: 181
          }
      60: new           #57                 // class org/hl7/fhir/dstu3/model/Property
      63: dup
      64: ldc           #58                 // String sequence
      66: ldc           #59                 // String positiveInt
      68: ldc           #60                 // String A service line item.
      70: iconst_0
      71: iconst_1
      72: aload_0
      73: getfield      #2                  // Field sequence:Lorg/hl7/fhir/dstu3/model/PositiveIntType;
      76: invokespecial #61                 // Method org/hl7/fhir/dstu3/model/Property."<init>":(Ljava/lang/String;Ljava/lang/String;Ljava/lang/String;IILorg/hl7/fhir/dstu3/model/Base;)V
      79: areturn
      80: new           #57                 // class org/hl7/fhir/dstu3/model/Property
      83: dup
      84: ldc           #62                 // String focal
      86: ldc           #63                 // String boolean
      88: ldc           #64                 // String The instance number of the Coverage which is the focus for adjudication. The Coverage against which the claim is to be adjudicated.
      90: iconst_0
      91: iconst_1
      92: aload_0
      93: getfield      #3                  // Field focal:Lorg/hl7/fhir/dstu3/model/BooleanType;
      96: invokespecial #61                 // Method org/hl7/fhir/dstu3/model/Property."<init>":(Ljava/lang/String;Ljava/lang/String;Ljava/lang/String;IILorg/hl7/fhir/dstu3/model/Base;)V
      99: areturn
     100: new           #57                 // class org/hl7/fhir/dstu3/model/Property
     103: dup
     104: ldc           #65                 // String coverage
     106: ldc           #66                 // String Reference(Coverage)
     108: ldc           #67                 // String Reference to the program or plan identification, underwriter or payor.
     110: iconst_0
     111: iconst_1
     112: aload_0
     113: getfield      #4                  // Field coverage:Lorg/hl7/fhir/dstu3/model/Reference;
     116: invokespecial #61                 // Method org/hl7/fhir/dstu3/model/Property."<init>":(Ljava/lang/String;Ljava/lang/String;Ljava/lang/String;IILorg/hl7/fhir/dstu3/model/Base;)V
     119: areturn
     120: new           #57                 // class org/hl7/fhir/dstu3/model/Property
     123: dup
     124: ldc           #68                 // String businessArrangement
     126: ldc           #69                 // String string
     128: ldc           #70                 // String The contract number of a business agreement which describes the terms and conditions.
     130: iconst_0
     131: iconst_1
     132: aload_0
     133: getfield      #34                 // Field businessArrangement:Lorg/hl7/fhir/dstu3/model/StringType;
     136: invokespecial #61                 // Method org/hl7/fhir/dstu3/model/Property."<init>":(Ljava/lang/String;Ljava/lang/String;Ljava/lang/String;IILorg/hl7/fhir/dstu3/model/Base;)V
     139: areturn
     140: new           #57                 // class org/hl7/fhir/dstu3/model/Property
     143: dup
     144: ldc           #71                 // String preAuthRef
     146: ldc           #69                 // String string
     148: ldc           #72                 // String A list of references from the Insurer to which these services pertain.
     150: iconst_0
     151: ldc           #73                 // int 2147483647
     153: aload_0
     154: getfield      #43                 // Field preAuthRef:Ljava/util/List;
     157: invokespecial #74                 // Method org/hl7/fhir/dstu3/model/Property."<init>":(Ljava/lang/String;Ljava/lang/String;Ljava/lang/String;IILjava/util/List;)V
     160: areturn
     161: new           #57                 // class org/hl7/fhir/dstu3/model/Property
     164: dup
     165: ldc           #75                 // String claimResponse
     167: ldc           #76                 // String Reference(ClaimResponse)
     169: ldc           #77                 // String The Coverages adjudication details.
     171: iconst_0
     172: iconst_1
     173: aload_0
     174: getfield      #51                 // Field claimResponse:Lorg/hl7/fhir/dstu3/model/Reference;
     177: invokespecial #61                 // Method org/hl7/fhir/dstu3/model/Property."<init>":(Ljava/lang/String;Ljava/lang/String;Ljava/lang/String;IILorg/hl7/fhir/dstu3/model/Base;)V
     180: areturn
     181: aload_0
     182: iload_1
     183: aload_2
     184: iload_3
     185: invokespecial #78                 // Method org/hl7/fhir/dstu3/model/BackboneElement.getNamedProperty:(ILjava/lang/String;Z)Lorg/hl7/fhir/dstu3/model/Property;
     188: areturn

  public org.hl7.fhir.dstu3.model.Base[] getProperty(int, java.lang.String, boolean) throws org.hl7.fhir.exceptions.FHIRException;
    Code:
       0: iload_1
       1: lookupswitch  { // 6
            -351767064: 112
              97604197: 86
             259920682: 138
             522246568: 164
             689513629: 203
            1349547969: 60
               default: 229
          }
      60: aload_0
      61: getfield      #2                  // Field sequence:Lorg/hl7/fhir/dstu3/model/PositiveIntType;
      64: ifnonnull     74
      67: iconst_0
      68: anewarray     #79                 // class org/hl7/fhir/dstu3/model/Base
      71: goto          85
      74: iconst_1
      75: anewarray     #79                 // class org/hl7/fhir/dstu3/model/Base
      78: dup
      79: iconst_0
      80: aload_0
      81: getfield      #2                  // Field sequence:Lorg/hl7/fhir/dstu3/model/PositiveIntType;
      84: aastore
      85: areturn
      86: aload_0
      87: getfield      #3                  // Field focal:Lorg/hl7/fhir/dstu3/model/BooleanType;
      90: ifnonnull     100
      93: iconst_0
      94: anewarray     #79                 // class org/hl7/fhir/dstu3/model/Base
      97: goto          111
     100: iconst_1
     101: anewarray     #79                 // class org/hl7/fhir/dstu3/model/Base
     104: dup
     105: iconst_0
     106: aload_0
     107: getfield      #3                  // Field focal:Lorg/hl7/fhir/dstu3/model/BooleanType;
     110: aastore
     111: areturn
     112: aload_0
     113: getfield      #4                  // Field coverage:Lorg/hl7/fhir/dstu3/model/Reference;
     116: ifnonnull     126
     119: iconst_0
     120: anewarray     #79                 // class org/hl7/fhir/dstu3/model/Base
     123: goto          137
     126: iconst_1
     127: anewarray     #79                 // class org/hl7/fhir/dstu3/model/Base
     130: dup
     131: iconst_0
     132: aload_0
     133: getfield      #4                  // Field coverage:Lorg/hl7/fhir/dstu3/model/Reference;
     136: aastore
     137: areturn
     138: aload_0
     139: getfield      #34                 // Field businessArrangement:Lorg/hl7/fhir/dstu3/model/StringType;
     142: ifnonnull     152
     145: iconst_0
     146: anewarray     #79                 // class org/hl7/fhir/dstu3/model/Base
     149: goto          163
     152: iconst_1
     153: anewarray     #79                 // class org/hl7/fhir/dstu3/model/Base
     156: dup
     157: iconst_0
     158: aload_0
     159: getfield      #34                 // Field businessArrangement:Lorg/hl7/fhir/dstu3/model/StringType;
     162: aastore
     163: areturn
     164: aload_0
     165: getfield      #43                 // Field preAuthRef:Ljava/util/List;
     168: ifnonnull     178
     171: iconst_0
     172: anewarray     #79                 // class org/hl7/fhir/dstu3/model/Base
     175: goto          202
     178: aload_0
     179: getfield      #43                 // Field preAuthRef:Ljava/util/List;
     182: aload_0
     183: getfield      #43                 // Field preAuthRef:Ljava/util/List;
     186: invokeinterface #80,  1           // InterfaceMethod java/util/List.size:()I
     191: anewarray     #79                 // class org/hl7/fhir/dstu3/model/Base
     194: invokeinterface #81,  2           // InterfaceMethod java/util/List.toArray:([Ljava/lang/Object;)[Ljava/lang/Object;
     199: checkcast     #82                 // class "[Lorg/hl7/fhir/dstu3/model/Base;"
     202: areturn
     203: aload_0
     204: getfield      #51                 // Field claimResponse:Lorg/hl7/fhir/dstu3/model/Reference;
     207: ifnonnull     217
     210: iconst_0
     211: anewarray     #79                 // class org/hl7/fhir/dstu3/model/Base
     214: goto          228
     217: iconst_1
     218: anewarray     #79                 // class org/hl7/fhir/dstu3/model/Base
     221: dup
     222: iconst_0
     223: aload_0
     224: getfield      #51                 // Field claimResponse:Lorg/hl7/fhir/dstu3/model/Reference;
     227: aastore
     228: areturn
     229: aload_0
     230: iload_1
     231: aload_2
     232: iload_3
     233: invokespecial #83                 // Method org/hl7/fhir/dstu3/model/BackboneElement.getProperty:(ILjava/lang/String;Z)[Lorg/hl7/fhir/dstu3/model/Base;
     236: areturn

  public org.hl7.fhir.dstu3.model.Base setProperty(int, java.lang.String, org.hl7.fhir.dstu3.model.Base) throws org.hl7.fhir.exceptions.FHIRException;
    Code:
       0: iload_1
       1: lookupswitch  { // 6
            -351767064: 82
              97604197: 71
             259920682: 93
             522246568: 104
             689513629: 121
            1349547969: 60
               default: 132
          }
      60: aload_0
      61: aload_0
      62: aload_3
      63: invokevirtual #84                 // Method castToPositiveInt:(Lorg/hl7/fhir/dstu3/model/Base;)Lorg/hl7/fhir/dstu3/model/PositiveIntType;
      66: putfield      #2                  // Field sequence:Lorg/hl7/fhir/dstu3/model/PositiveIntType;
      69: aload_3
      70: areturn
      71: aload_0
      72: aload_0
      73: aload_3
      74: invokevirtual #85                 // Method castToBoolean:(Lorg/hl7/fhir/dstu3/model/Base;)Lorg/hl7/fhir/dstu3/model/BooleanType;
      77: putfield      #3                  // Field focal:Lorg/hl7/fhir/dstu3/model/BooleanType;
      80: aload_3
      81: areturn
      82: aload_0
      83: aload_0
      84: aload_3
      85: invokevirtual #86                 // Method castToReference:(Lorg/hl7/fhir/dstu3/model/Base;)Lorg/hl7/fhir/dstu3/model/Reference;
      88: putfield      #4                  // Field coverage:Lorg/hl7/fhir/dstu3/model/Reference;
      91: aload_3
      92: areturn
      93: aload_0
      94: aload_0
      95: aload_3
      96: invokevirtual #87                 // Method castToString:(Lorg/hl7/fhir/dstu3/model/Base;)Lorg/hl7/fhir/dstu3/model/StringType;
      99: putfield      #34                 // Field businessArrangement:Lorg/hl7/fhir/dstu3/model/StringType;
     102: aload_3
     103: areturn
     104: aload_0
     105: invokevirtual #88                 // Method getPreAuthRef:()Ljava/util/List;
     108: aload_0
     109: aload_3
     110: invokevirtual #87                 // Method castToString:(Lorg/hl7/fhir/dstu3/model/Base;)Lorg/hl7/fhir/dstu3/model/StringType;
     113: invokeinterface #49,  2           // InterfaceMethod java/util/List.add:(Ljava/lang/Object;)Z
     118: pop
     119: aload_3
     120: areturn
     121: aload_0
     122: aload_0
     123: aload_3
     124: invokevirtual #86                 // Method castToReference:(Lorg/hl7/fhir/dstu3/model/Base;)Lorg/hl7/fhir/dstu3/model/Reference;
     127: putfield      #51                 // Field claimResponse:Lorg/hl7/fhir/dstu3/model/Reference;
     130: aload_3
     131: areturn
     132: aload_0
     133: iload_1
     134: aload_2
     135: aload_3
     136: invokespecial #89                 // Method org/hl7/fhir/dstu3/model/BackboneElement.setProperty:(ILjava/lang/String;Lorg/hl7/fhir/dstu3/model/Base;)Lorg/hl7/fhir/dstu3/model/Base;
     139: areturn

  public org.hl7.fhir.dstu3.model.Base setProperty(java.lang.String, org.hl7.fhir.dstu3.model.Base) throws org.hl7.fhir.exceptions.FHIRException;
    Code:
       0: aload_1
       1: ldc           #58                 // String sequence
       3: invokevirtual #50                 // Method java/lang/String.equals:(Ljava/lang/Object;)Z
       6: ifeq          21
       9: aload_0
      10: aload_0
      11: aload_2
      12: invokevirtual #84                 // Method castToPositiveInt:(Lorg/hl7/fhir/dstu3/model/Base;)Lorg/hl7/fhir/dstu3/model/PositiveIntType;
      15: putfield      #2                  // Field sequence:Lorg/hl7/fhir/dstu3/model/PositiveIntType;
      18: goto          139
      21: aload_1
      22: ldc           #62                 // String focal
      24: invokevirtual #50                 // Method java/lang/String.equals:(Ljava/lang/Object;)Z
      27: ifeq          42
      30: aload_0
      31: aload_0
      32: aload_2
      33: invokevirtual #85                 // Method castToBoolean:(Lorg/hl7/fhir/dstu3/model/Base;)Lorg/hl7/fhir/dstu3/model/BooleanType;
      36: putfield      #3                  // Field focal:Lorg/hl7/fhir/dstu3/model/BooleanType;
      39: goto          139
      42: aload_1
      43: ldc           #65                 // String coverage
      45: invokevirtual #50                 // Method java/lang/String.equals:(Ljava/lang/Object;)Z
      48: ifeq          63
      51: aload_0
      52: aload_0
      53: aload_2
      54: invokevirtual #86                 // Method castToReference:(Lorg/hl7/fhir/dstu3/model/Base;)Lorg/hl7/fhir/dstu3/model/Reference;
      57: putfield      #4                  // Field coverage:Lorg/hl7/fhir/dstu3/model/Reference;
      60: goto          139
      63: aload_1
      64: ldc           #68                 // String businessArrangement
      66: invokevirtual #50                 // Method java/lang/String.equals:(Ljava/lang/Object;)Z
      69: ifeq          84
      72: aload_0
      73: aload_0
      74: aload_2
      75: invokevirtual #87                 // Method castToString:(Lorg/hl7/fhir/dstu3/model/Base;)Lorg/hl7/fhir/dstu3/model/StringType;
      78: putfield      #34                 // Field businessArrangement:Lorg/hl7/fhir/dstu3/model/StringType;
      81: goto          139
      84: aload_1
      85: ldc           #71                 // String preAuthRef
      87: invokevirtual #50                 // Method java/lang/String.equals:(Ljava/lang/Object;)Z
      90: ifeq          111
      93: aload_0
      94: invokevirtual #88                 // Method getPreAuthRef:()Ljava/util/List;
      97: aload_0
      98: aload_2
      99: invokevirtual #87                 // Method castToString:(Lorg/hl7/fhir/dstu3/model/Base;)Lorg/hl7/fhir/dstu3/model/StringType;
     102: invokeinterface #49,  2           // InterfaceMethod java/util/List.add:(Ljava/lang/Object;)Z
     107: pop
     108: goto          139
     111: aload_1
     112: ldc           #75                 // String claimResponse
     114: invokevirtual #50                 // Method java/lang/String.equals:(Ljava/lang/Object;)Z
     117: ifeq          132
     120: aload_0
     121: aload_0
     122: aload_2
     123: invokevirtual #86                 // Method castToReference:(Lorg/hl7/fhir/dstu3/model/Base;)Lorg/hl7/fhir/dstu3/model/Reference;
     126: putfield      #51                 // Field claimResponse:Lorg/hl7/fhir/dstu3/model/Reference;
     129: goto          139
     132: aload_0
     133: aload_1
     134: aload_2
     135: invokespecial #90                 // Method org/hl7/fhir/dstu3/model/BackboneElement.setProperty:(Ljava/lang/String;Lorg/hl7/fhir/dstu3/model/Base;)Lorg/hl7/fhir/dstu3/model/Base;
     138: areturn
     139: aload_2
     140: areturn

  public org.hl7.fhir.dstu3.model.Base makeProperty(int, java.lang.String) throws org.hl7.fhir.exceptions.FHIRException;
    Code:
       0: iload_1
       1: lookupswitch  { // 6
            -351767064: 70
              97604197: 65
             259920682: 75
             522246568: 80
             689513629: 85
            1349547969: 60
               default: 90
          }
      60: aload_0
      61: invokevirtual #91                 // Method getSequenceElement:()Lorg/hl7/fhir/dstu3/model/PositiveIntType;
      64: areturn
      65: aload_0
      66: invokevirtual #92                 // Method getFocalElement:()Lorg/hl7/fhir/dstu3/model/BooleanType;
      69: areturn
      70: aload_0
      71: invokevirtual #93                 // Method getCoverage:()Lorg/hl7/fhir/dstu3/model/Reference;
      74: areturn
      75: aload_0
      76: invokevirtual #94                 // Method getBusinessArrangementElement:()Lorg/hl7/fhir/dstu3/model/StringType;
      79: areturn
      80: aload_0
      81: invokevirtual #95                 // Method addPreAuthRefElement:()Lorg/hl7/fhir/dstu3/model/StringType;
      84: areturn
      85: aload_0
      86: invokevirtual #96                 // Method getClaimResponse:()Lorg/hl7/fhir/dstu3/model/Reference;
      89: areturn
      90: aload_0
      91: iload_1
      92: aload_2
      93: invokespecial #97                 // Method org/hl7/fhir/dstu3/model/BackboneElement.makeProperty:(ILjava/lang/String;)Lorg/hl7/fhir/dstu3/model/Base;
      96: areturn

  public java.lang.String[] getTypesForProperty(int, java.lang.String) throws org.hl7.fhir.exceptions.FHIRException;
    Code:
       0: iload_1
       1: lookupswitch  { // 6
            -351767064: 80
              97604197: 70
             259920682: 90
             522246568: 100
             689513629: 110
            1349547969: 60
               default: 120
          }
      60: iconst_1
      61: anewarray     #40                 // class java/lang/String
      64: dup
      65: iconst_0
      66: ldc           #59                 // String positiveInt
      68: aastore
      69: areturn
      70: iconst_1
      71: anewarray     #40                 // class java/lang/String
      74: dup
      75: iconst_0
      76: ldc           #63                 // String boolean
      78: aastore
      79: areturn
      80: iconst_1
      81: anewarray     #40                 // class java/lang/String
      84: dup
      85: iconst_0
      86: ldc           #98                 // String Reference
      88: aastore
      89: areturn
      90: iconst_1
      91: anewarray     #40                 // class java/lang/String
      94: dup
      95: iconst_0
      96: ldc           #69                 // String string
      98: aastore
      99: areturn
     100: iconst_1
     101: anewarray     #40                 // class java/lang/String
     104: dup
     105: iconst_0
     106: ldc           #69                 // String string
     108: aastore
     109: areturn
     110: iconst_1
     111: anewarray     #40                 // class java/lang/String
     114: dup
     115: iconst_0
     116: ldc           #98                 // String Reference
     118: aastore
     119: areturn
     120: aload_0
     121: iload_1
     122: aload_2
     123: invokespecial #99                 // Method org/hl7/fhir/dstu3/model/BackboneElement.getTypesForProperty:(ILjava/lang/String;)[Ljava/lang/String;
     126: areturn

  public org.hl7.fhir.dstu3.model.Base addChild(java.lang.String) throws org.hl7.fhir.exceptions.FHIRException;
    Code:
       0: aload_1
       1: ldc           #58                 // String sequence
       3: invokevirtual #50                 // Method java/lang/String.equals:(Ljava/lang/Object;)Z
       6: ifeq          19
       9: new           #100                // class org/hl7/fhir/exceptions/FHIRException
      12: dup
      13: ldc           #101                // String Cannot call addChild on a primitive type ClaimResponse.sequence
      15: invokespecial #102                // Method org/hl7/fhir/exceptions/FHIRException."<init>":(Ljava/lang/String;)V
      18: athrow
      19: aload_1
      20: ldc           #62                 // String focal
      22: invokevirtual #50                 // Method java/lang/String.equals:(Ljava/lang/Object;)Z
      25: ifeq          38
      28: new           #100                // class org/hl7/fhir/exceptions/FHIRException
      31: dup
      32: ldc           #103                // String Cannot call addChild on a primitive type ClaimResponse.focal
      34: invokespecial #102                // Method org/hl7/fhir/exceptions/FHIRException."<init>":(Ljava/lang/String;)V
      37: athrow
      38: aload_1
      39: ldc           #65                 // String coverage
      41: invokevirtual #50                 // Method java/lang/String.equals:(Ljava/lang/Object;)Z
      44: ifeq          63
      47: aload_0
      48: new           #28                 // class org/hl7/fhir/dstu3/model/Reference
      51: dup
      52: invokespecial #29                 // Method org/hl7/fhir/dstu3/model/Reference."<init>":()V
      55: putfield      #4                  // Field coverage:Lorg/hl7/fhir/dstu3/model/Reference;
      58: aload_0
      59: getfield      #4                  // Field coverage:Lorg/hl7/fhir/dstu3/model/Reference;
      62: areturn
      63: aload_1
      64: ldc           #68                 // String businessArrangement
      66: invokevirtual #50                 // Method java/lang/String.equals:(Ljava/lang/Object;)Z
      69: ifeq          82
      72: new           #100                // class org/hl7/fhir/exceptions/FHIRException
      75: dup
      76: ldc           #104                // String Cannot call addChild on a primitive type ClaimResponse.businessArrangement
      78: invokespecial #102                // Method org/hl7/fhir/exceptions/FHIRException."<init>":(Ljava/lang/String;)V
      81: athrow
      82: aload_1
      83: ldc           #71                 // String preAuthRef
      85: invokevirtual #50                 // Method java/lang/String.equals:(Ljava/lang/Object;)Z
      88: ifeq          101
      91: new           #100                // class org/hl7/fhir/exceptions/FHIRException
      94: dup
      95: ldc           #105                // String Cannot call addChild on a primitive type ClaimResponse.preAuthRef
      97: invokespecial #102                // Method org/hl7/fhir/exceptions/FHIRException."<init>":(Ljava/lang/String;)V
     100: athrow
     101: aload_1
     102: ldc           #75                 // String claimResponse
     104: invokevirtual #50                 // Method java/lang/String.equals:(Ljava/lang/Object;)Z
     107: ifeq          126
     110: aload_0
     111: new           #28                 // class org/hl7/fhir/dstu3/model/Reference
     114: dup
     115: invokespecial #29                 // Method org/hl7/fhir/dstu3/model/Reference."<init>":()V
     118: putfield      #51                 // Field claimResponse:Lorg/hl7/fhir/dstu3/model/Reference;
     121: aload_0
     122: getfield      #51                 // Field claimResponse:Lorg/hl7/fhir/dstu3/model/Reference;
     125: areturn
     126: aload_0
     127: aload_1
     128: invokespecial #106                // Method org/hl7/fhir/dstu3/model/BackboneElement.addChild:(Ljava/lang/String;)Lorg/hl7/fhir/dstu3/model/Base;
     131: areturn

  public org.hl7.fhir.dstu3.model.ClaimResponse$InsuranceComponent copy();
    Code:
       0: new           #107                // class org/hl7/fhir/dstu3/model/ClaimResponse$InsuranceComponent
       3: dup
       4: invokespecial #108                // Method "<init>":()V
       7: astore_1
       8: aload_0
       9: aload_1
      10: invokevirtual #109                // Method copyValues:(Lorg/hl7/fhir/dstu3/model/BackboneElement;)V
      13: aload_1
      14: aload_0
      15: getfield      #2                  // Field sequence:Lorg/hl7/fhir/dstu3/model/PositiveIntType;
      18: ifnonnull     25
      21: aconst_null
      22: goto          32
      25: aload_0
      26: getfield      #2                  // Field sequence:Lorg/hl7/fhir/dstu3/model/PositiveIntType;
      29: invokevirtual #110                // Method org/hl7/fhir/dstu3/model/PositiveIntType.copy:()Lorg/hl7/fhir/dstu3/model/PositiveIntType;
      32: putfield      #2                  // Field sequence:Lorg/hl7/fhir/dstu3/model/PositiveIntType;
      35: aload_1
      36: aload_0
      37: getfield      #3                  // Field focal:Lorg/hl7/fhir/dstu3/model/BooleanType;
      40: ifnonnull     47
      43: aconst_null
      44: goto          54
      47: aload_0
      48: getfield      #3                  // Field focal:Lorg/hl7/fhir/dstu3/model/BooleanType;
      51: invokevirtual #111                // Method org/hl7/fhir/dstu3/model/BooleanType.copy:()Lorg/hl7/fhir/dstu3/model/BooleanType;
      54: putfield      #3                  // Field focal:Lorg/hl7/fhir/dstu3/model/BooleanType;
      57: aload_1
      58: aload_0
      59: getfield      #4                  // Field coverage:Lorg/hl7/fhir/dstu3/model/Reference;
      62: ifnonnull     69
      65: aconst_null
      66: goto          76
      69: aload_0
      70: getfield      #4                  // Field coverage:Lorg/hl7/fhir/dstu3/model/Reference;
      73: invokevirtual #112                // Method org/hl7/fhir/dstu3/model/Reference.copy:()Lorg/hl7/fhir/dstu3/model/Reference;
      76: putfield      #4                  // Field coverage:Lorg/hl7/fhir/dstu3/model/Reference;
      79: aload_1
      80: aload_0
      81: getfield      #34                 // Field businessArrangement:Lorg/hl7/fhir/dstu3/model/StringType;
      84: ifnonnull     91
      87: aconst_null
      88: goto          98
      91: aload_0
      92: getfield      #34                 // Field businessArrangement:Lorg/hl7/fhir/dstu3/model/StringType;
      95: invokevirtual #113                // Method org/hl7/fhir/dstu3/model/StringType.copy:()Lorg/hl7/fhir/dstu3/model/StringType;
      98: putfield      #34                 // Field businessArrangement:Lorg/hl7/fhir/dstu3/model/StringType;
     101: aload_0
     102: getfield      #43                 // Field preAuthRef:Ljava/util/List;
     105: ifnull        165
     108: aload_1
     109: new           #44                 // class java/util/ArrayList
     112: dup
     113: invokespecial #45                 // Method java/util/ArrayList."<init>":()V
     116: putfield      #43                 // Field preAuthRef:Ljava/util/List;
     119: aload_0
     120: getfield      #43                 // Field preAuthRef:Ljava/util/List;
     123: invokeinterface #46,  1           // InterfaceMethod java/util/List.iterator:()Ljava/util/Iterator;
     128: astore_2
     129: aload_2
     130: invokeinterface #47,  1           // InterfaceMethod java/util/Iterator.hasNext:()Z
     135: ifeq          165
     138: aload_2
     139: invokeinterface #48,  1           // InterfaceMethod java/util/Iterator.next:()Ljava/lang/Object;
     144: checkcast     #36                 // class org/hl7/fhir/dstu3/model/StringType
     147: astore_3
     148: aload_1
     149: getfield      #43                 // Field preAuthRef:Ljava/util/List;
     152: aload_3
     153: invokevirtual #113                // Method org/hl7/fhir/dstu3/model/StringType.copy:()Lorg/hl7/fhir/dstu3/model/StringType;
     156: invokeinterface #49,  2           // InterfaceMethod java/util/List.add:(Ljava/lang/Object;)Z
     161: pop
     162: goto          129
     165: aload_1
     166: aload_0
     167: getfield      #51                 // Field claimResponse:Lorg/hl7/fhir/dstu3/model/Reference;
     170: ifnonnull     177
     173: aconst_null
     174: goto          184
     177: aload_0
     178: getfield      #51                 // Field claimResponse:Lorg/hl7/fhir/dstu3/model/Reference;
     181: invokevirtual #112                // Method org/hl7/fhir/dstu3/model/Reference.copy:()Lorg/hl7/fhir/dstu3/model/Reference;
     184: putfield      #51                 // Field claimResponse:Lorg/hl7/fhir/dstu3/model/Reference;
     187: aload_1
     188: areturn

  public boolean equalsDeep(org.hl7.fhir.dstu3.model.Base);
    Code:
       0: aload_0
       1: aload_1
       2: invokespecial #114                // Method org/hl7/fhir/dstu3/model/BackboneElement.equalsDeep:(Lorg/hl7/fhir/dstu3/model/Base;)Z
       5: ifne          10
       8: iconst_0
       9: ireturn
      10: aload_1
      11: instanceof    #107                // class org/hl7/fhir/dstu3/model/ClaimResponse$InsuranceComponent
      14: ifne          19
      17: iconst_0
      18: ireturn
      19: aload_1
      20: checkcast     #107                // class org/hl7/fhir/dstu3/model/ClaimResponse$InsuranceComponent
      23: astore_2
      24: aload_0
      25: getfield      #2                  // Field sequence:Lorg/hl7/fhir/dstu3/model/PositiveIntType;
      28: aload_2
      29: getfield      #2                  // Field sequence:Lorg/hl7/fhir/dstu3/model/PositiveIntType;
      32: iconst_1
      33: invokestatic  #115                // Method compareDeep:(Lorg/hl7/fhir/dstu3/model/Base;Lorg/hl7/fhir/dstu3/model/Base;Z)Z
      36: ifeq          118
      39: aload_0
      40: getfield      #3                  // Field focal:Lorg/hl7/fhir/dstu3/model/BooleanType;
      43: aload_2
      44: getfield      #3                  // Field focal:Lorg/hl7/fhir/dstu3/model/BooleanType;
      47: iconst_1
      48: invokestatic  #115                // Method compareDeep:(Lorg/hl7/fhir/dstu3/model/Base;Lorg/hl7/fhir/dstu3/model/Base;Z)Z
      51: ifeq          118
      54: aload_0
      55: getfield      #4                  // Field coverage:Lorg/hl7/fhir/dstu3/model/Reference;
      58: aload_2
      59: getfield      #4                  // Field coverage:Lorg/hl7/fhir/dstu3/model/Reference;
      62: iconst_1
      63: invokestatic  #115                // Method compareDeep:(Lorg/hl7/fhir/dstu3/model/Base;Lorg/hl7/fhir/dstu3/model/Base;Z)Z
      66: ifeq          118
      69: aload_0
      70: getfield      #34                 // Field businessArrangement:Lorg/hl7/fhir/dstu3/model/StringType;
      73: aload_2
      74: getfield      #34                 // Field businessArrangement:Lorg/hl7/fhir/dstu3/model/StringType;
      77: iconst_1
      78: invokestatic  #115                // Method compareDeep:(Lorg/hl7/fhir/dstu3/model/Base;Lorg/hl7/fhir/dstu3/model/Base;Z)Z
      81: ifeq          118
      84: aload_0
      85: getfield      #43                 // Field preAuthRef:Ljava/util/List;
      88: aload_2
      89: getfield      #43                 // Field preAuthRef:Ljava/util/List;
      92: iconst_1
      93: invokestatic  #116                // Method compareDeep:(Ljava/util/List;Ljava/util/List;Z)Z
      96: ifeq          118
      99: aload_0
     100: getfield      #51                 // Field claimResponse:Lorg/hl7/fhir/dstu3/model/Reference;
     103: aload_2
     104: getfield      #51                 // Field claimResponse:Lorg/hl7/fhir/dstu3/model/Reference;
     107: iconst_1
     108: invokestatic  #115                // Method compareDeep:(Lorg/hl7/fhir/dstu3/model/Base;Lorg/hl7/fhir/dstu3/model/Base;Z)Z
     111: ifeq          118
     114: iconst_1
     115: goto          119
     118: iconst_0
     119: ireturn

  public boolean equalsShallow(org.hl7.fhir.dstu3.model.Base);
    Code:
       0: aload_0
       1: aload_1
       2: invokespecial #117                // Method org/hl7/fhir/dstu3/model/BackboneElement.equalsShallow:(Lorg/hl7/fhir/dstu3/model/Base;)Z
       5: ifne          10
       8: iconst_0
       9: ireturn
      10: aload_1
      11: instanceof    #107                // class org/hl7/fhir/dstu3/model/ClaimResponse$InsuranceComponent
      14: ifne          19
      17: iconst_0
      18: ireturn
      19: aload_1
      20: checkcast     #107                // class org/hl7/fhir/dstu3/model/ClaimResponse$InsuranceComponent
      23: astore_2
      24: aload_0
      25: getfield      #2                  // Field sequence:Lorg/hl7/fhir/dstu3/model/PositiveIntType;
      28: aload_2
      29: getfield      #2                  // Field sequence:Lorg/hl7/fhir/dstu3/model/PositiveIntType;
      32: iconst_1
      33: invokestatic  #118                // Method compareValues:(Lorg/hl7/fhir/dstu3/model/PrimitiveType;Lorg/hl7/fhir/dstu3/model/PrimitiveType;Z)Z
      36: ifeq          88
      39: aload_0
      40: getfield      #3                  // Field focal:Lorg/hl7/fhir/dstu3/model/BooleanType;
      43: aload_2
      44: getfield      #3                  // Field focal:Lorg/hl7/fhir/dstu3/model/BooleanType;
      47: iconst_1
      48: invokestatic  #118                // Method compareValues:(Lorg/hl7/fhir/dstu3/model/PrimitiveType;Lorg/hl7/fhir/dstu3/model/PrimitiveType;Z)Z
      51: ifeq          88
      54: aload_0
      55: getfield      #34                 // Field businessArrangement:Lorg/hl7/fhir/dstu3/model/StringType;
      58: aload_2
      59: getfield      #34                 // Field businessArrangement:Lorg/hl7/fhir/dstu3/model/StringType;
      62: iconst_1
      63: invokestatic  #118                // Method compareValues:(Lorg/hl7/fhir/dstu3/model/PrimitiveType;Lorg/hl7/fhir/dstu3/model/PrimitiveType;Z)Z
      66: ifeq          88
      69: aload_0
      70: getfield      #43                 // Field preAuthRef:Ljava/util/List;
      73: aload_2
      74: getfield      #43                 // Field preAuthRef:Ljava/util/List;
      77: iconst_1
      78: invokestatic  #119                // Method compareValues:(Ljava/util/List;Ljava/util/List;Z)Z
      81: ifeq          88
      84: iconst_1
      85: goto          89
      88: iconst_0
      89: ireturn

  public boolean isEmpty();
    Code:
       0: aload_0
       1: invokespecial #120                // Method org/hl7/fhir/dstu3/model/BackboneElement.isEmpty:()Z
       4: ifeq          64
       7: bipush        6
       9: anewarray     #121                // class java/lang/Object
      12: dup
      13: iconst_0
      14: aload_0
      15: getfield      #2                  // Field sequence:Lorg/hl7/fhir/dstu3/model/PositiveIntType;
      18: aastore
      19: dup
      20: iconst_1
      21: aload_0
      22: getfield      #3                  // Field focal:Lorg/hl7/fhir/dstu3/model/BooleanType;
      25: aastore
      26: dup
      27: iconst_2
      28: aload_0
      29: getfield      #4                  // Field coverage:Lorg/hl7/fhir/dstu3/model/Reference;
      32: aastore
      33: dup
      34: iconst_3
      35: aload_0
      36: getfield      #34                 // Field businessArrangement:Lorg/hl7/fhir/dstu3/model/StringType;
      39: aastore
      40: dup
      41: iconst_4
      42: aload_0
      43: getfield      #43                 // Field preAuthRef:Ljava/util/List;
      46: aastore
      47: dup
      48: iconst_5
      49: aload_0
      50: getfield      #51                 // Field claimResponse:Lorg/hl7/fhir/dstu3/model/Reference;
      53: aastore
      54: invokestatic  #122                // Method ca/uhn/fhir/util/ElementUtil.isEmpty:([Ljava/lang/Object;)Z
      57: ifeq          64
      60: iconst_1
      61: goto          65
      64: iconst_0
      65: ireturn

  public java.lang.String fhirType();
    Code:
       0: ldc           #123                // String ClaimResponse.insurance
       2: areturn

  public org.hl7.fhir.dstu3.model.BackboneElement copy();
    Code:
       0: aload_0
       1: invokevirtual #124                // Method copy:()Lorg/hl7/fhir/dstu3/model/ClaimResponse$InsuranceComponent;
       4: areturn

  public org.hl7.fhir.dstu3.model.Element copy();
    Code:
       0: aload_0
       1: invokevirtual #124                // Method copy:()Lorg/hl7/fhir/dstu3/model/ClaimResponse$InsuranceComponent;
       4: areturn
}
