Compiled from "CodeSystem.java"
public class org.hl7.fhir.dstu3.model.CodeSystem$CodeSystemFilterComponent extends org.hl7.fhir.dstu3.model.BackboneElement implements org.hl7.fhir.instance.model.api.IBaseBackboneElement {
  protected org.hl7.fhir.dstu3.model.CodeType code;

  protected org.hl7.fhir.dstu3.model.StringType description;

  protected java.util.List<org.hl7.fhir.dstu3.model.Enumeration<org.hl7.fhir.dstu3.model.CodeSystem$FilterOperator>> operator;

  protected org.hl7.fhir.dstu3.model.StringType value;

  private static final long serialVersionUID;

  public org.hl7.fhir.dstu3.model.CodeSystem$CodeSystemFilterComponent();
    Code:
       0: aload_0
       1: invokespecial #1                  // Method org/hl7/fhir/dstu3/model/BackboneElement."<init>":()V
       4: return

  public org.hl7.fhir.dstu3.model.CodeSystem$CodeSystemFilterComponent(org.hl7.fhir.dstu3.model.CodeType, org.hl7.fhir.dstu3.model.StringType);
    Code:
       0: aload_0
       1: invokespecial #1                  // Method org/hl7/fhir/dstu3/model/BackboneElement."<init>":()V
       4: aload_0
       5: aload_1
       6: putfield      #2                  // Field code:Lorg/hl7/fhir/dstu3/model/CodeType;
       9: aload_0
      10: aload_2
      11: putfield      #3                  // Field value:Lorg/hl7/fhir/dstu3/model/StringType;
      14: return

  public org.hl7.fhir.dstu3.model.CodeType getCodeElement();
    Code:
       0: aload_0
       1: getfield      #2                  // Field code:Lorg/hl7/fhir/dstu3/model/CodeType;
       4: ifnonnull     40
       7: invokestatic  #4                  // Method org/hl7/fhir/dstu3/model/Configuration.errorOnAutoCreate:()Z
      10: ifeq          23
      13: new           #5                  // class java/lang/Error
      16: dup
      17: ldc           #6                  // String Attempt to auto-create CodeSystemFilterComponent.code
      19: invokespecial #7                  // Method java/lang/Error."<init>":(Ljava/lang/String;)V
      22: athrow
      23: invokestatic  #8                  // Method org/hl7/fhir/dstu3/model/Configuration.doAutoCreate:()Z
      26: ifeq          40
      29: aload_0
      30: new           #9                  // class org/hl7/fhir/dstu3/model/CodeType
      33: dup
      34: invokespecial #10                 // Method org/hl7/fhir/dstu3/model/CodeType."<init>":()V
      37: putfield      #2                  // Field code:Lorg/hl7/fhir/dstu3/model/CodeType;
      40: aload_0
      41: getfield      #2                  // Field code:Lorg/hl7/fhir/dstu3/model/CodeType;
      44: areturn

  public boolean hasCodeElement();
    Code:
       0: aload_0
       1: getfield      #2                  // Field code:Lorg/hl7/fhir/dstu3/model/CodeType;
       4: ifnull        21
       7: aload_0
       8: getfield      #2                  // Field code:Lorg/hl7/fhir/dstu3/model/CodeType;
      11: invokevirtual #11                 // Method org/hl7/fhir/dstu3/model/CodeType.isEmpty:()Z
      14: ifne          21
      17: iconst_1
      18: goto          22
      21: iconst_0
      22: ireturn

  public boolean hasCode();
    Code:
       0: aload_0
       1: getfield      #2                  // Field code:Lorg/hl7/fhir/dstu3/model/CodeType;
       4: ifnull        21
       7: aload_0
       8: getfield      #2                  // Field code:Lorg/hl7/fhir/dstu3/model/CodeType;
      11: invokevirtual #11                 // Method org/hl7/fhir/dstu3/model/CodeType.isEmpty:()Z
      14: ifne          21
      17: iconst_1
      18: goto          22
      21: iconst_0
      22: ireturn

  public org.hl7.fhir.dstu3.model.CodeSystem$CodeSystemFilterComponent setCodeElement(org.hl7.fhir.dstu3.model.CodeType);
    Code:
       0: aload_0
       1: aload_1
       2: putfield      #2                  // Field code:Lorg/hl7/fhir/dstu3/model/CodeType;
       5: aload_0
       6: areturn

  public java.lang.String getCode();
    Code:
       0: aload_0
       1: getfield      #2                  // Field code:Lorg/hl7/fhir/dstu3/model/CodeType;
       4: ifnonnull     11
       7: aconst_null
       8: goto          21
      11: aload_0
      12: getfield      #2                  // Field code:Lorg/hl7/fhir/dstu3/model/CodeType;
      15: invokevirtual #12                 // Method org/hl7/fhir/dstu3/model/CodeType.getValue:()Ljava/lang/Object;
      18: checkcast     #13                 // class java/lang/String
      21: areturn

  public org.hl7.fhir.dstu3.model.CodeSystem$CodeSystemFilterComponent setCode(java.lang.String);
    Code:
       0: aload_0
       1: getfield      #2                  // Field code:Lorg/hl7/fhir/dstu3/model/CodeType;
       4: ifnonnull     18
       7: aload_0
       8: new           #9                  // class org/hl7/fhir/dstu3/model/CodeType
      11: dup
      12: invokespecial #10                 // Method org/hl7/fhir/dstu3/model/CodeType."<init>":()V
      15: putfield      #2                  // Field code:Lorg/hl7/fhir/dstu3/model/CodeType;
      18: aload_0
      19: getfield      #2                  // Field code:Lorg/hl7/fhir/dstu3/model/CodeType;
      22: aload_1
      23: invokevirtual #14                 // Method org/hl7/fhir/dstu3/model/CodeType.setValue:(Ljava/lang/Object;)Lorg/hl7/fhir/dstu3/model/PrimitiveType;
      26: pop
      27: aload_0
      28: areturn

  public org.hl7.fhir.dstu3.model.StringType getDescriptionElement();
    Code:
       0: aload_0
       1: getfield      #15                 // Field description:Lorg/hl7/fhir/dstu3/model/StringType;
       4: ifnonnull     40
       7: invokestatic  #4                  // Method org/hl7/fhir/dstu3/model/Configuration.errorOnAutoCreate:()Z
      10: ifeq          23
      13: new           #5                  // class java/lang/Error
      16: dup
      17: ldc           #16                 // String Attempt to auto-create CodeSystemFilterComponent.description
      19: invokespecial #7                  // Method java/lang/Error."<init>":(Ljava/lang/String;)V
      22: athrow
      23: invokestatic  #8                  // Method org/hl7/fhir/dstu3/model/Configuration.doAutoCreate:()Z
      26: ifeq          40
      29: aload_0
      30: new           #17                 // class org/hl7/fhir/dstu3/model/StringType
      33: dup
      34: invokespecial #18                 // Method org/hl7/fhir/dstu3/model/StringType."<init>":()V
      37: putfield      #15                 // Field description:Lorg/hl7/fhir/dstu3/model/StringType;
      40: aload_0
      41: getfield      #15                 // Field description:Lorg/hl7/fhir/dstu3/model/StringType;
      44: areturn

  public boolean hasDescriptionElement();
    Code:
       0: aload_0
       1: getfield      #15                 // Field description:Lorg/hl7/fhir/dstu3/model/StringType;
       4: ifnull        21
       7: aload_0
       8: getfield      #15                 // Field description:Lorg/hl7/fhir/dstu3/model/StringType;
      11: invokevirtual #19                 // Method org/hl7/fhir/dstu3/model/StringType.isEmpty:()Z
      14: ifne          21
      17: iconst_1
      18: goto          22
      21: iconst_0
      22: ireturn

  public boolean hasDescription();
    Code:
       0: aload_0
       1: getfield      #15                 // Field description:Lorg/hl7/fhir/dstu3/model/StringType;
       4: ifnull        21
       7: aload_0
       8: getfield      #15                 // Field description:Lorg/hl7/fhir/dstu3/model/StringType;
      11: invokevirtual #19                 // Method org/hl7/fhir/dstu3/model/StringType.isEmpty:()Z
      14: ifne          21
      17: iconst_1
      18: goto          22
      21: iconst_0
      22: ireturn

  public org.hl7.fhir.dstu3.model.CodeSystem$CodeSystemFilterComponent setDescriptionElement(org.hl7.fhir.dstu3.model.StringType);
    Code:
       0: aload_0
       1: aload_1
       2: putfield      #15                 // Field description:Lorg/hl7/fhir/dstu3/model/StringType;
       5: aload_0
       6: areturn

  public java.lang.String getDescription();
    Code:
       0: aload_0
       1: getfield      #15                 // Field description:Lorg/hl7/fhir/dstu3/model/StringType;
       4: ifnonnull     11
       7: aconst_null
       8: goto          21
      11: aload_0
      12: getfield      #15                 // Field description:Lorg/hl7/fhir/dstu3/model/StringType;
      15: invokevirtual #20                 // Method org/hl7/fhir/dstu3/model/StringType.getValue:()Ljava/lang/Object;
      18: checkcast     #13                 // class java/lang/String
      21: areturn

  public org.hl7.fhir.dstu3.model.CodeSystem$CodeSystemFilterComponent setDescription(java.lang.String);
    Code:
       0: aload_1
       1: invokestatic  #21                 // Method org/hl7/fhir/utilities/Utilities.noString:(Ljava/lang/String;)Z
       4: ifeq          15
       7: aload_0
       8: aconst_null
       9: putfield      #15                 // Field description:Lorg/hl7/fhir/dstu3/model/StringType;
      12: goto          42
      15: aload_0
      16: getfield      #15                 // Field description:Lorg/hl7/fhir/dstu3/model/StringType;
      19: ifnonnull     33
      22: aload_0
      23: new           #17                 // class org/hl7/fhir/dstu3/model/StringType
      26: dup
      27: invokespecial #18                 // Method org/hl7/fhir/dstu3/model/StringType."<init>":()V
      30: putfield      #15                 // Field description:Lorg/hl7/fhir/dstu3/model/StringType;
      33: aload_0
      34: getfield      #15                 // Field description:Lorg/hl7/fhir/dstu3/model/StringType;
      37: aload_1
      38: invokevirtual #22                 // Method org/hl7/fhir/dstu3/model/StringType.setValue:(Ljava/lang/Object;)Lorg/hl7/fhir/dstu3/model/PrimitiveType;
      41: pop
      42: aload_0
      43: areturn

  public java.util.List<org.hl7.fhir.dstu3.model.Enumeration<org.hl7.fhir.dstu3.model.CodeSystem$FilterOperator>> getOperator();
    Code:
       0: aload_0
       1: getfield      #23                 // Field operator:Ljava/util/List;
       4: ifnonnull     18
       7: aload_0
       8: new           #24                 // class java/util/ArrayList
      11: dup
      12: invokespecial #25                 // Method java/util/ArrayList."<init>":()V
      15: putfield      #23                 // Field operator:Ljava/util/List;
      18: aload_0
      19: getfield      #23                 // Field operator:Ljava/util/List;
      22: areturn

  public org.hl7.fhir.dstu3.model.CodeSystem$CodeSystemFilterComponent setOperator(java.util.List<org.hl7.fhir.dstu3.model.Enumeration<org.hl7.fhir.dstu3.model.CodeSystem$FilterOperator>>);
    Code:
       0: aload_0
       1: aload_1
       2: putfield      #23                 // Field operator:Ljava/util/List;
       5: aload_0
       6: areturn

  public boolean hasOperator();
    Code:
       0: aload_0
       1: getfield      #23                 // Field operator:Ljava/util/List;
       4: ifnonnull     9
       7: iconst_0
       8: ireturn
       9: aload_0
      10: getfield      #23                 // Field operator:Ljava/util/List;
      13: invokeinterface #26,  1           // InterfaceMethod java/util/List.iterator:()Ljava/util/Iterator;
      18: astore_1
      19: aload_1
      20: invokeinterface #27,  1           // InterfaceMethod java/util/Iterator.hasNext:()Z
      25: ifeq          50
      28: aload_1
      29: invokeinterface #28,  1           // InterfaceMethod java/util/Iterator.next:()Ljava/lang/Object;
      34: checkcast     #29                 // class org/hl7/fhir/dstu3/model/Enumeration
      37: astore_2
      38: aload_2
      39: invokevirtual #30                 // Method org/hl7/fhir/dstu3/model/Enumeration.isEmpty:()Z
      42: ifne          47
      45: iconst_1
      46: ireturn
      47: goto          19
      50: iconst_0
      51: ireturn

  public org.hl7.fhir.dstu3.model.Enumeration<org.hl7.fhir.dstu3.model.CodeSystem$FilterOperator> addOperatorElement();
    Code:
       0: new           #29                 // class org/hl7/fhir/dstu3/model/Enumeration
       3: dup
       4: new           #31                 // class org/hl7/fhir/dstu3/model/CodeSystem$FilterOperatorEnumFactory
       7: dup
       8: invokespecial #32                 // Method org/hl7/fhir/dstu3/model/CodeSystem$FilterOperatorEnumFactory."<init>":()V
      11: invokespecial #33                 // Method org/hl7/fhir/dstu3/model/Enumeration."<init>":(Lorg/hl7/fhir/dstu3/model/EnumFactory;)V
      14: astore_1
      15: aload_0
      16: getfield      #23                 // Field operator:Ljava/util/List;
      19: ifnonnull     33
      22: aload_0
      23: new           #24                 // class java/util/ArrayList
      26: dup
      27: invokespecial #25                 // Method java/util/ArrayList."<init>":()V
      30: putfield      #23                 // Field operator:Ljava/util/List;
      33: aload_0
      34: getfield      #23                 // Field operator:Ljava/util/List;
      37: aload_1
      38: invokeinterface #34,  2           // InterfaceMethod java/util/List.add:(Ljava/lang/Object;)Z
      43: pop
      44: aload_1
      45: areturn

  public org.hl7.fhir.dstu3.model.CodeSystem$CodeSystemFilterComponent addOperator(org.hl7.fhir.dstu3.model.CodeSystem$FilterOperator);
    Code:
       0: new           #29                 // class org/hl7/fhir/dstu3/model/Enumeration
       3: dup
       4: new           #31                 // class org/hl7/fhir/dstu3/model/CodeSystem$FilterOperatorEnumFactory
       7: dup
       8: invokespecial #32                 // Method org/hl7/fhir/dstu3/model/CodeSystem$FilterOperatorEnumFactory."<init>":()V
      11: invokespecial #33                 // Method org/hl7/fhir/dstu3/model/Enumeration."<init>":(Lorg/hl7/fhir/dstu3/model/EnumFactory;)V
      14: astore_2
      15: aload_2
      16: aload_1
      17: invokevirtual #35                 // Method org/hl7/fhir/dstu3/model/Enumeration.setValue:(Ljava/lang/Object;)Lorg/hl7/fhir/dstu3/model/PrimitiveType;
      20: pop
      21: aload_0
      22: getfield      #23                 // Field operator:Ljava/util/List;
      25: ifnonnull     39
      28: aload_0
      29: new           #24                 // class java/util/ArrayList
      32: dup
      33: invokespecial #25                 // Method java/util/ArrayList."<init>":()V
      36: putfield      #23                 // Field operator:Ljava/util/List;
      39: aload_0
      40: getfield      #23                 // Field operator:Ljava/util/List;
      43: aload_2
      44: invokeinterface #34,  2           // InterfaceMethod java/util/List.add:(Ljava/lang/Object;)Z
      49: pop
      50: aload_0
      51: areturn

  public boolean hasOperator(org.hl7.fhir.dstu3.model.CodeSystem$FilterOperator);
    Code:
       0: aload_0
       1: getfield      #23                 // Field operator:Ljava/util/List;
       4: ifnonnull     9
       7: iconst_0
       8: ireturn
       9: aload_0
      10: getfield      #23                 // Field operator:Ljava/util/List;
      13: invokeinterface #26,  1           // InterfaceMethod java/util/List.iterator:()Ljava/util/Iterator;
      18: astore_2
      19: aload_2
      20: invokeinterface #27,  1           // InterfaceMethod java/util/Iterator.hasNext:()Z
      25: ifeq          57
      28: aload_2
      29: invokeinterface #28,  1           // InterfaceMethod java/util/Iterator.next:()Ljava/lang/Object;
      34: checkcast     #29                 // class org/hl7/fhir/dstu3/model/Enumeration
      37: astore_3
      38: aload_3
      39: invokevirtual #36                 // Method org/hl7/fhir/dstu3/model/Enumeration.getValue:()Ljava/lang/Object;
      42: checkcast     #37                 // class org/hl7/fhir/dstu3/model/CodeSystem$FilterOperator
      45: aload_1
      46: invokevirtual #38                 // Method org/hl7/fhir/dstu3/model/CodeSystem$FilterOperator.equals:(Ljava/lang/Object;)Z
      49: ifeq          54
      52: iconst_1
      53: ireturn
      54: goto          19
      57: iconst_0
      58: ireturn

  public org.hl7.fhir.dstu3.model.StringType getValueElement();
    Code:
       0: aload_0
       1: getfield      #3                  // Field value:Lorg/hl7/fhir/dstu3/model/StringType;
       4: ifnonnull     40
       7: invokestatic  #4                  // Method org/hl7/fhir/dstu3/model/Configuration.errorOnAutoCreate:()Z
      10: ifeq          23
      13: new           #5                  // class java/lang/Error
      16: dup
      17: ldc           #39                 // String Attempt to auto-create CodeSystemFilterComponent.value
      19: invokespecial #7                  // Method java/lang/Error."<init>":(Ljava/lang/String;)V
      22: athrow
      23: invokestatic  #8                  // Method org/hl7/fhir/dstu3/model/Configuration.doAutoCreate:()Z
      26: ifeq          40
      29: aload_0
      30: new           #17                 // class org/hl7/fhir/dstu3/model/StringType
      33: dup
      34: invokespecial #18                 // Method org/hl7/fhir/dstu3/model/StringType."<init>":()V
      37: putfield      #3                  // Field value:Lorg/hl7/fhir/dstu3/model/StringType;
      40: aload_0
      41: getfield      #3                  // Field value:Lorg/hl7/fhir/dstu3/model/StringType;
      44: areturn

  public boolean hasValueElement();
    Code:
       0: aload_0
       1: getfield      #3                  // Field value:Lorg/hl7/fhir/dstu3/model/StringType;
       4: ifnull        21
       7: aload_0
       8: getfield      #3                  // Field value:Lorg/hl7/fhir/dstu3/model/StringType;
      11: invokevirtual #19                 // Method org/hl7/fhir/dstu3/model/StringType.isEmpty:()Z
      14: ifne          21
      17: iconst_1
      18: goto          22
      21: iconst_0
      22: ireturn

  public boolean hasValue();
    Code:
       0: aload_0
       1: getfield      #3                  // Field value:Lorg/hl7/fhir/dstu3/model/StringType;
       4: ifnull        21
       7: aload_0
       8: getfield      #3                  // Field value:Lorg/hl7/fhir/dstu3/model/StringType;
      11: invokevirtual #19                 // Method org/hl7/fhir/dstu3/model/StringType.isEmpty:()Z
      14: ifne          21
      17: iconst_1
      18: goto          22
      21: iconst_0
      22: ireturn

  public org.hl7.fhir.dstu3.model.CodeSystem$CodeSystemFilterComponent setValueElement(org.hl7.fhir.dstu3.model.StringType);
    Code:
       0: aload_0
       1: aload_1
       2: putfield      #3                  // Field value:Lorg/hl7/fhir/dstu3/model/StringType;
       5: aload_0
       6: areturn

  public java.lang.String getValue();
    Code:
       0: aload_0
       1: getfield      #3                  // Field value:Lorg/hl7/fhir/dstu3/model/StringType;
       4: ifnonnull     11
       7: aconst_null
       8: goto          21
      11: aload_0
      12: getfield      #3                  // Field value:Lorg/hl7/fhir/dstu3/model/StringType;
      15: invokevirtual #20                 // Method org/hl7/fhir/dstu3/model/StringType.getValue:()Ljava/lang/Object;
      18: checkcast     #13                 // class java/lang/String
      21: areturn

  public org.hl7.fhir.dstu3.model.CodeSystem$CodeSystemFilterComponent setValue(java.lang.String);
    Code:
       0: aload_0
       1: getfield      #3                  // Field value:Lorg/hl7/fhir/dstu3/model/StringType;
       4: ifnonnull     18
       7: aload_0
       8: new           #17                 // class org/hl7/fhir/dstu3/model/StringType
      11: dup
      12: invokespecial #18                 // Method org/hl7/fhir/dstu3/model/StringType."<init>":()V
      15: putfield      #3                  // Field value:Lorg/hl7/fhir/dstu3/model/StringType;
      18: aload_0
      19: getfield      #3                  // Field value:Lorg/hl7/fhir/dstu3/model/StringType;
      22: aload_1
      23: invokevirtual #22                 // Method org/hl7/fhir/dstu3/model/StringType.setValue:(Ljava/lang/Object;)Lorg/hl7/fhir/dstu3/model/PrimitiveType;
      26: pop
      27: aload_0
      28: areturn

  protected void listChildren(java.util.List<org.hl7.fhir.dstu3.model.Property>);
    Code:
       0: aload_0
       1: aload_1
       2: invokespecial #40                 // Method org/hl7/fhir/dstu3/model/BackboneElement.listChildren:(Ljava/util/List;)V
       5: aload_1
       6: new           #41                 // class org/hl7/fhir/dstu3/model/Property
       9: dup
      10: ldc           #42                 // String code
      12: ldc           #42                 // String code
      14: ldc           #43                 // String The code that identifies this filter when it is used in the instance.
      16: iconst_0
      17: iconst_1
      18: aload_0
      19: getfield      #2                  // Field code:Lorg/hl7/fhir/dstu3/model/CodeType;
      22: invokespecial #44                 // Method org/hl7/fhir/dstu3/model/Property."<init>":(Ljava/lang/String;Ljava/lang/String;Ljava/lang/String;IILorg/hl7/fhir/dstu3/model/Base;)V
      25: invokeinterface #34,  2           // InterfaceMethod java/util/List.add:(Ljava/lang/Object;)Z
      30: pop
      31: aload_1
      32: new           #41                 // class org/hl7/fhir/dstu3/model/Property
      35: dup
      36: ldc           #45                 // String description
      38: ldc           #46                 // String string
      40: ldc           #47                 // String A description of how or why the filter is used.
      42: iconst_0
      43: iconst_1
      44: aload_0
      45: getfield      #15                 // Field description:Lorg/hl7/fhir/dstu3/model/StringType;
      48: invokespecial #44                 // Method org/hl7/fhir/dstu3/model/Property."<init>":(Ljava/lang/String;Ljava/lang/String;Ljava/lang/String;IILorg/hl7/fhir/dstu3/model/Base;)V
      51: invokeinterface #34,  2           // InterfaceMethod java/util/List.add:(Ljava/lang/Object;)Z
      56: pop
      57: aload_1
      58: new           #41                 // class org/hl7/fhir/dstu3/model/Property
      61: dup
      62: ldc           #48                 // String operator
      64: ldc           #42                 // String code
      66: ldc           #49                 // String A list of operators that can be used with the filter.
      68: iconst_0
      69: ldc           #51                 // int 2147483647
      71: aload_0
      72: getfield      #23                 // Field operator:Ljava/util/List;
      75: invokespecial #52                 // Method org/hl7/fhir/dstu3/model/Property."<init>":(Ljava/lang/String;Ljava/lang/String;Ljava/lang/String;IILjava/util/List;)V
      78: invokeinterface #34,  2           // InterfaceMethod java/util/List.add:(Ljava/lang/Object;)Z
      83: pop
      84: aload_1
      85: new           #41                 // class org/hl7/fhir/dstu3/model/Property
      88: dup
      89: ldc           #53                 // String value
      91: ldc           #46                 // String string
      93: ldc           #54                 // String A description of what the value for the filter should be.
      95: iconst_0
      96: iconst_1
      97: aload_0
      98: getfield      #3                  // Field value:Lorg/hl7/fhir/dstu3/model/StringType;
     101: invokespecial #44                 // Method org/hl7/fhir/dstu3/model/Property."<init>":(Ljava/lang/String;Ljava/lang/String;Ljava/lang/String;IILorg/hl7/fhir/dstu3/model/Base;)V
     104: invokeinterface #34,  2           // InterfaceMethod java/util/List.add:(Ljava/lang/Object;)Z
     109: pop
     110: return

  public org.hl7.fhir.dstu3.model.Property getNamedProperty(int, java.lang.String, boolean) throws org.hl7.fhir.exceptions.FHIRException;
    Code:
       0: iload_1
       1: lookupswitch  { // 4
           -1724546052: 64
            -500553564: 84
               3059181: 44
             111972721: 105
               default: 125
          }
      44: new           #41                 // class org/hl7/fhir/dstu3/model/Property
      47: dup
      48: ldc           #42                 // String code
      50: ldc           #42                 // String code
      52: ldc           #43                 // String The code that identifies this filter when it is used in the instance.
      54: iconst_0
      55: iconst_1
      56: aload_0
      57: getfield      #2                  // Field code:Lorg/hl7/fhir/dstu3/model/CodeType;
      60: invokespecial #44                 // Method org/hl7/fhir/dstu3/model/Property."<init>":(Ljava/lang/String;Ljava/lang/String;Ljava/lang/String;IILorg/hl7/fhir/dstu3/model/Base;)V
      63: areturn
      64: new           #41                 // class org/hl7/fhir/dstu3/model/Property
      67: dup
      68: ldc           #45                 // String description
      70: ldc           #46                 // String string
      72: ldc           #47                 // String A description of how or why the filter is used.
      74: iconst_0
      75: iconst_1
      76: aload_0
      77: getfield      #15                 // Field description:Lorg/hl7/fhir/dstu3/model/StringType;
      80: invokespecial #44                 // Method org/hl7/fhir/dstu3/model/Property."<init>":(Ljava/lang/String;Ljava/lang/String;Ljava/lang/String;IILorg/hl7/fhir/dstu3/model/Base;)V
      83: areturn
      84: new           #41                 // class org/hl7/fhir/dstu3/model/Property
      87: dup
      88: ldc           #48                 // String operator
      90: ldc           #42                 // String code
      92: ldc           #49                 // String A list of operators that can be used with the filter.
      94: iconst_0
      95: ldc           #51                 // int 2147483647
      97: aload_0
      98: getfield      #23                 // Field operator:Ljava/util/List;
     101: invokespecial #52                 // Method org/hl7/fhir/dstu3/model/Property."<init>":(Ljava/lang/String;Ljava/lang/String;Ljava/lang/String;IILjava/util/List;)V
     104: areturn
     105: new           #41                 // class org/hl7/fhir/dstu3/model/Property
     108: dup
     109: ldc           #53                 // String value
     111: ldc           #46                 // String string
     113: ldc           #54                 // String A description of what the value for the filter should be.
     115: iconst_0
     116: iconst_1
     117: aload_0
     118: getfield      #3                  // Field value:Lorg/hl7/fhir/dstu3/model/StringType;
     121: invokespecial #44                 // Method org/hl7/fhir/dstu3/model/Property."<init>":(Ljava/lang/String;Ljava/lang/String;Ljava/lang/String;IILorg/hl7/fhir/dstu3/model/Base;)V
     124: areturn
     125: aload_0
     126: iload_1
     127: aload_2
     128: iload_3
     129: invokespecial #55                 // Method org/hl7/fhir/dstu3/model/BackboneElement.getNamedProperty:(ILjava/lang/String;Z)Lorg/hl7/fhir/dstu3/model/Property;
     132: areturn

  public org.hl7.fhir.dstu3.model.Base[] getProperty(int, java.lang.String, boolean) throws org.hl7.fhir.exceptions.FHIRException;
    Code:
       0: iload_1
       1: lookupswitch  { // 4
           -1724546052: 70
            -500553564: 96
               3059181: 44
             111972721: 135
               default: 161
          }
      44: aload_0
      45: getfield      #2                  // Field code:Lorg/hl7/fhir/dstu3/model/CodeType;
      48: ifnonnull     58
      51: iconst_0
      52: anewarray     #56                 // class org/hl7/fhir/dstu3/model/Base
      55: goto          69
      58: iconst_1
      59: anewarray     #56                 // class org/hl7/fhir/dstu3/model/Base
      62: dup
      63: iconst_0
      64: aload_0
      65: getfield      #2                  // Field code:Lorg/hl7/fhir/dstu3/model/CodeType;
      68: aastore
      69: areturn
      70: aload_0
      71: getfield      #15                 // Field description:Lorg/hl7/fhir/dstu3/model/StringType;
      74: ifnonnull     84
      77: iconst_0
      78: anewarray     #56                 // class org/hl7/fhir/dstu3/model/Base
      81: goto          95
      84: iconst_1
      85: anewarray     #56                 // class org/hl7/fhir/dstu3/model/Base
      88: dup
      89: iconst_0
      90: aload_0
      91: getfield      #15                 // Field description:Lorg/hl7/fhir/dstu3/model/StringType;
      94: aastore
      95: areturn
      96: aload_0
      97: getfield      #23                 // Field operator:Ljava/util/List;
     100: ifnonnull     110
     103: iconst_0
     104: anewarray     #56                 // class org/hl7/fhir/dstu3/model/Base
     107: goto          134
     110: aload_0
     111: getfield      #23                 // Field operator:Ljava/util/List;
     114: aload_0
     115: getfield      #23                 // Field operator:Ljava/util/List;
     118: invokeinterface #57,  1           // InterfaceMethod java/util/List.size:()I
     123: anewarray     #56                 // class org/hl7/fhir/dstu3/model/Base
     126: invokeinterface #58,  2           // InterfaceMethod java/util/List.toArray:([Ljava/lang/Object;)[Ljava/lang/Object;
     131: checkcast     #59                 // class "[Lorg/hl7/fhir/dstu3/model/Base;"
     134: areturn
     135: aload_0
     136: getfield      #3                  // Field value:Lorg/hl7/fhir/dstu3/model/StringType;
     139: ifnonnull     149
     142: iconst_0
     143: anewarray     #56                 // class org/hl7/fhir/dstu3/model/Base
     146: goto          160
     149: iconst_1
     150: anewarray     #56                 // class org/hl7/fhir/dstu3/model/Base
     153: dup
     154: iconst_0
     155: aload_0
     156: getfield      #3                  // Field value:Lorg/hl7/fhir/dstu3/model/StringType;
     159: aastore
     160: areturn
     161: aload_0
     162: iload_1
     163: aload_2
     164: iload_3
     165: invokespecial #60                 // Method org/hl7/fhir/dstu3/model/BackboneElement.getProperty:(ILjava/lang/String;Z)[Lorg/hl7/fhir/dstu3/model/Base;
     168: areturn

  public org.hl7.fhir.dstu3.model.Base setProperty(int, java.lang.String, org.hl7.fhir.dstu3.model.Base) throws org.hl7.fhir.exceptions.FHIRException;
    Code:
       0: iload_1
       1: lookupswitch  { // 4
           -1724546052: 55
            -500553564: 66
               3059181: 44
             111972721: 98
               default: 109
          }
      44: aload_0
      45: aload_0
      46: aload_3
      47: invokevirtual #61                 // Method castToCode:(Lorg/hl7/fhir/dstu3/model/Base;)Lorg/hl7/fhir/dstu3/model/CodeType;
      50: putfield      #2                  // Field code:Lorg/hl7/fhir/dstu3/model/CodeType;
      53: aload_3
      54: areturn
      55: aload_0
      56: aload_0
      57: aload_3
      58: invokevirtual #62                 // Method castToString:(Lorg/hl7/fhir/dstu3/model/Base;)Lorg/hl7/fhir/dstu3/model/StringType;
      61: putfield      #15                 // Field description:Lorg/hl7/fhir/dstu3/model/StringType;
      64: aload_3
      65: areturn
      66: new           #31                 // class org/hl7/fhir/dstu3/model/CodeSystem$FilterOperatorEnumFactory
      69: dup
      70: invokespecial #32                 // Method org/hl7/fhir/dstu3/model/CodeSystem$FilterOperatorEnumFactory."<init>":()V
      73: aload_0
      74: aload_3
      75: invokevirtual #61                 // Method castToCode:(Lorg/hl7/fhir/dstu3/model/Base;)Lorg/hl7/fhir/dstu3/model/CodeType;
      78: invokevirtual #63                 // Method org/hl7/fhir/dstu3/model/CodeSystem$FilterOperatorEnumFactory.fromType:(Lorg/hl7/fhir/dstu3/model/Base;)Lorg/hl7/fhir/dstu3/model/Enumeration;
      81: astore_3
      82: aload_0
      83: invokevirtual #64                 // Method getOperator:()Ljava/util/List;
      86: aload_3
      87: checkcast     #29                 // class org/hl7/fhir/dstu3/model/Enumeration
      90: invokeinterface #34,  2           // InterfaceMethod java/util/List.add:(Ljava/lang/Object;)Z
      95: pop
      96: aload_3
      97: areturn
      98: aload_0
      99: aload_0
     100: aload_3
     101: invokevirtual #62                 // Method castToString:(Lorg/hl7/fhir/dstu3/model/Base;)Lorg/hl7/fhir/dstu3/model/StringType;
     104: putfield      #3                  // Field value:Lorg/hl7/fhir/dstu3/model/StringType;
     107: aload_3
     108: areturn
     109: aload_0
     110: iload_1
     111: aload_2
     112: aload_3
     113: invokespecial #65                 // Method org/hl7/fhir/dstu3/model/BackboneElement.setProperty:(ILjava/lang/String;Lorg/hl7/fhir/dstu3/model/Base;)Lorg/hl7/fhir/dstu3/model/Base;
     116: areturn

  public org.hl7.fhir.dstu3.model.Base setProperty(java.lang.String, org.hl7.fhir.dstu3.model.Base) throws org.hl7.fhir.exceptions.FHIRException;
    Code:
       0: aload_1
       1: ldc           #42                 // String code
       3: invokevirtual #66                 // Method java/lang/String.equals:(Ljava/lang/Object;)Z
       6: ifeq          21
       9: aload_0
      10: aload_0
      11: aload_2
      12: invokevirtual #61                 // Method castToCode:(Lorg/hl7/fhir/dstu3/model/Base;)Lorg/hl7/fhir/dstu3/model/CodeType;
      15: putfield      #2                  // Field code:Lorg/hl7/fhir/dstu3/model/CodeType;
      18: goto          112
      21: aload_1
      22: ldc           #45                 // String description
      24: invokevirtual #66                 // Method java/lang/String.equals:(Ljava/lang/Object;)Z
      27: ifeq          42
      30: aload_0
      31: aload_0
      32: aload_2
      33: invokevirtual #62                 // Method castToString:(Lorg/hl7/fhir/dstu3/model/Base;)Lorg/hl7/fhir/dstu3/model/StringType;
      36: putfield      #15                 // Field description:Lorg/hl7/fhir/dstu3/model/StringType;
      39: goto          112
      42: aload_1
      43: ldc           #48                 // String operator
      45: invokevirtual #66                 // Method java/lang/String.equals:(Ljava/lang/Object;)Z
      48: ifeq          84
      51: new           #31                 // class org/hl7/fhir/dstu3/model/CodeSystem$FilterOperatorEnumFactory
      54: dup
      55: invokespecial #32                 // Method org/hl7/fhir/dstu3/model/CodeSystem$FilterOperatorEnumFactory."<init>":()V
      58: aload_0
      59: aload_2
      60: invokevirtual #61                 // Method castToCode:(Lorg/hl7/fhir/dstu3/model/Base;)Lorg/hl7/fhir/dstu3/model/CodeType;
      63: invokevirtual #63                 // Method org/hl7/fhir/dstu3/model/CodeSystem$FilterOperatorEnumFactory.fromType:(Lorg/hl7/fhir/dstu3/model/Base;)Lorg/hl7/fhir/dstu3/model/Enumeration;
      66: astore_2
      67: aload_0
      68: invokevirtual #64                 // Method getOperator:()Ljava/util/List;
      71: aload_2
      72: checkcast     #29                 // class org/hl7/fhir/dstu3/model/Enumeration
      75: invokeinterface #34,  2           // InterfaceMethod java/util/List.add:(Ljava/lang/Object;)Z
      80: pop
      81: goto          112
      84: aload_1
      85: ldc           #53                 // String value
      87: invokevirtual #66                 // Method java/lang/String.equals:(Ljava/lang/Object;)Z
      90: ifeq          105
      93: aload_0
      94: aload_0
      95: aload_2
      96: invokevirtual #62                 // Method castToString:(Lorg/hl7/fhir/dstu3/model/Base;)Lorg/hl7/fhir/dstu3/model/StringType;
      99: putfield      #3                  // Field value:Lorg/hl7/fhir/dstu3/model/StringType;
     102: goto          112
     105: aload_0
     106: aload_1
     107: aload_2
     108: invokespecial #67                 // Method org/hl7/fhir/dstu3/model/BackboneElement.setProperty:(Ljava/lang/String;Lorg/hl7/fhir/dstu3/model/Base;)Lorg/hl7/fhir/dstu3/model/Base;
     111: areturn
     112: aload_2
     113: areturn

  public org.hl7.fhir.dstu3.model.Base makeProperty(int, java.lang.String) throws org.hl7.fhir.exceptions.FHIRException;
    Code:
       0: iload_1
       1: lookupswitch  { // 4
           -1724546052: 49
            -500553564: 54
               3059181: 44
             111972721: 59
               default: 64
          }
      44: aload_0
      45: invokevirtual #68                 // Method getCodeElement:()Lorg/hl7/fhir/dstu3/model/CodeType;
      48: areturn
      49: aload_0
      50: invokevirtual #69                 // Method getDescriptionElement:()Lorg/hl7/fhir/dstu3/model/StringType;
      53: areturn
      54: aload_0
      55: invokevirtual #70                 // Method addOperatorElement:()Lorg/hl7/fhir/dstu3/model/Enumeration;
      58: areturn
      59: aload_0
      60: invokevirtual #71                 // Method getValueElement:()Lorg/hl7/fhir/dstu3/model/StringType;
      63: areturn
      64: aload_0
      65: iload_1
      66: aload_2
      67: invokespecial #72                 // Method org/hl7/fhir/dstu3/model/BackboneElement.makeProperty:(ILjava/lang/String;)Lorg/hl7/fhir/dstu3/model/Base;
      70: areturn

  public java.lang.String[] getTypesForProperty(int, java.lang.String) throws org.hl7.fhir.exceptions.FHIRException;
    Code:
       0: iload_1
       1: lookupswitch  { // 4
           -1724546052: 54
            -500553564: 64
               3059181: 44
             111972721: 74
               default: 84
          }
      44: iconst_1
      45: anewarray     #13                 // class java/lang/String
      48: dup
      49: iconst_0
      50: ldc           #42                 // String code
      52: aastore
      53: areturn
      54: iconst_1
      55: anewarray     #13                 // class java/lang/String
      58: dup
      59: iconst_0
      60: ldc           #46                 // String string
      62: aastore
      63: areturn
      64: iconst_1
      65: anewarray     #13                 // class java/lang/String
      68: dup
      69: iconst_0
      70: ldc           #42                 // String code
      72: aastore
      73: areturn
      74: iconst_1
      75: anewarray     #13                 // class java/lang/String
      78: dup
      79: iconst_0
      80: ldc           #46                 // String string
      82: aastore
      83: areturn
      84: aload_0
      85: iload_1
      86: aload_2
      87: invokespecial #73                 // Method org/hl7/fhir/dstu3/model/BackboneElement.getTypesForProperty:(ILjava/lang/String;)[Ljava/lang/String;
      90: areturn

  public org.hl7.fhir.dstu3.model.Base addChild(java.lang.String) throws org.hl7.fhir.exceptions.FHIRException;
    Code:
       0: aload_1
       1: ldc           #42                 // String code
       3: invokevirtual #66                 // Method java/lang/String.equals:(Ljava/lang/Object;)Z
       6: ifeq          19
       9: new           #74                 // class org/hl7/fhir/exceptions/FHIRException
      12: dup
      13: ldc           #75                 // String Cannot call addChild on a primitive type CodeSystem.code
      15: invokespecial #76                 // Method org/hl7/fhir/exceptions/FHIRException."<init>":(Ljava/lang/String;)V
      18: athrow
      19: aload_1
      20: ldc           #45                 // String description
      22: invokevirtual #66                 // Method java/lang/String.equals:(Ljava/lang/Object;)Z
      25: ifeq          38
      28: new           #74                 // class org/hl7/fhir/exceptions/FHIRException
      31: dup
      32: ldc           #77                 // String Cannot call addChild on a primitive type CodeSystem.description
      34: invokespecial #76                 // Method org/hl7/fhir/exceptions/FHIRException."<init>":(Ljava/lang/String;)V
      37: athrow
      38: aload_1
      39: ldc           #48                 // String operator
      41: invokevirtual #66                 // Method java/lang/String.equals:(Ljava/lang/Object;)Z
      44: ifeq          57
      47: new           #74                 // class org/hl7/fhir/exceptions/FHIRException
      50: dup
      51: ldc           #78                 // String Cannot call addChild on a primitive type CodeSystem.operator
      53: invokespecial #76                 // Method org/hl7/fhir/exceptions/FHIRException."<init>":(Ljava/lang/String;)V
      56: athrow
      57: aload_1
      58: ldc           #53                 // String value
      60: invokevirtual #66                 // Method java/lang/String.equals:(Ljava/lang/Object;)Z
      63: ifeq          76
      66: new           #74                 // class org/hl7/fhir/exceptions/FHIRException
      69: dup
      70: ldc           #79                 // String Cannot call addChild on a primitive type CodeSystem.value
      72: invokespecial #76                 // Method org/hl7/fhir/exceptions/FHIRException."<init>":(Ljava/lang/String;)V
      75: athrow
      76: aload_0
      77: aload_1
      78: invokespecial #80                 // Method org/hl7/fhir/dstu3/model/BackboneElement.addChild:(Ljava/lang/String;)Lorg/hl7/fhir/dstu3/model/Base;
      81: areturn

  public org.hl7.fhir.dstu3.model.CodeSystem$CodeSystemFilterComponent copy();
    Code:
       0: new           #81                 // class org/hl7/fhir/dstu3/model/CodeSystem$CodeSystemFilterComponent
       3: dup
       4: invokespecial #82                 // Method "<init>":()V
       7: astore_1
       8: aload_0
       9: aload_1
      10: invokevirtual #83                 // Method copyValues:(Lorg/hl7/fhir/dstu3/model/BackboneElement;)V
      13: aload_1
      14: aload_0
      15: getfield      #2                  // Field code:Lorg/hl7/fhir/dstu3/model/CodeType;
      18: ifnonnull     25
      21: aconst_null
      22: goto          32
      25: aload_0
      26: getfield      #2                  // Field code:Lorg/hl7/fhir/dstu3/model/CodeType;
      29: invokevirtual #84                 // Method org/hl7/fhir/dstu3/model/CodeType.copy:()Lorg/hl7/fhir/dstu3/model/CodeType;
      32: putfield      #2                  // Field code:Lorg/hl7/fhir/dstu3/model/CodeType;
      35: aload_1
      36: aload_0
      37: getfield      #15                 // Field description:Lorg/hl7/fhir/dstu3/model/StringType;
      40: ifnonnull     47
      43: aconst_null
      44: goto          54
      47: aload_0
      48: getfield      #15                 // Field description:Lorg/hl7/fhir/dstu3/model/StringType;
      51: invokevirtual #85                 // Method org/hl7/fhir/dstu3/model/StringType.copy:()Lorg/hl7/fhir/dstu3/model/StringType;
      54: putfield      #15                 // Field description:Lorg/hl7/fhir/dstu3/model/StringType;
      57: aload_0
      58: getfield      #23                 // Field operator:Ljava/util/List;
      61: ifnull        121
      64: aload_1
      65: new           #24                 // class java/util/ArrayList
      68: dup
      69: invokespecial #25                 // Method java/util/ArrayList."<init>":()V
      72: putfield      #23                 // Field operator:Ljava/util/List;
      75: aload_0
      76: getfield      #23                 // Field operator:Ljava/util/List;
      79: invokeinterface #26,  1           // InterfaceMethod java/util/List.iterator:()Ljava/util/Iterator;
      84: astore_2
      85: aload_2
      86: invokeinterface #27,  1           // InterfaceMethod java/util/Iterator.hasNext:()Z
      91: ifeq          121
      94: aload_2
      95: invokeinterface #28,  1           // InterfaceMethod java/util/Iterator.next:()Ljava/lang/Object;
     100: checkcast     #29                 // class org/hl7/fhir/dstu3/model/Enumeration
     103: astore_3
     104: aload_1
     105: getfield      #23                 // Field operator:Ljava/util/List;
     108: aload_3
     109: invokevirtual #86                 // Method org/hl7/fhir/dstu3/model/Enumeration.copy:()Lorg/hl7/fhir/dstu3/model/Enumeration;
     112: invokeinterface #34,  2           // InterfaceMethod java/util/List.add:(Ljava/lang/Object;)Z
     117: pop
     118: goto          85
     121: aload_1
     122: aload_0
     123: getfield      #3                  // Field value:Lorg/hl7/fhir/dstu3/model/StringType;
     126: ifnonnull     133
     129: aconst_null
     130: goto          140
     133: aload_0
     134: getfield      #3                  // Field value:Lorg/hl7/fhir/dstu3/model/StringType;
     137: invokevirtual #85                 // Method org/hl7/fhir/dstu3/model/StringType.copy:()Lorg/hl7/fhir/dstu3/model/StringType;
     140: putfield      #3                  // Field value:Lorg/hl7/fhir/dstu3/model/StringType;
     143: aload_1
     144: areturn

  public boolean equalsDeep(org.hl7.fhir.dstu3.model.Base);
    Code:
       0: aload_0
       1: aload_1
       2: invokespecial #87                 // Method org/hl7/fhir/dstu3/model/BackboneElement.equalsDeep:(Lorg/hl7/fhir/dstu3/model/Base;)Z
       5: ifne          10
       8: iconst_0
       9: ireturn
      10: aload_1
      11: instanceof    #81                 // class org/hl7/fhir/dstu3/model/CodeSystem$CodeSystemFilterComponent
      14: ifne          19
      17: iconst_0
      18: ireturn
      19: aload_1
      20: checkcast     #81                 // class org/hl7/fhir/dstu3/model/CodeSystem$CodeSystemFilterComponent
      23: astore_2
      24: aload_0
      25: getfield      #2                  // Field code:Lorg/hl7/fhir/dstu3/model/CodeType;
      28: aload_2
      29: getfield      #2                  // Field code:Lorg/hl7/fhir/dstu3/model/CodeType;
      32: iconst_1
      33: invokestatic  #88                 // Method compareDeep:(Lorg/hl7/fhir/dstu3/model/Base;Lorg/hl7/fhir/dstu3/model/Base;Z)Z
      36: ifeq          88
      39: aload_0
      40: getfield      #15                 // Field description:Lorg/hl7/fhir/dstu3/model/StringType;
      43: aload_2
      44: getfield      #15                 // Field description:Lorg/hl7/fhir/dstu3/model/StringType;
      47: iconst_1
      48: invokestatic  #88                 // Method compareDeep:(Lorg/hl7/fhir/dstu3/model/Base;Lorg/hl7/fhir/dstu3/model/Base;Z)Z
      51: ifeq          88
      54: aload_0
      55: getfield      #23                 // Field operator:Ljava/util/List;
      58: aload_2
      59: getfield      #23                 // Field operator:Ljava/util/List;
      62: iconst_1
      63: invokestatic  #89                 // Method compareDeep:(Ljava/util/List;Ljava/util/List;Z)Z
      66: ifeq          88
      69: aload_0
      70: getfield      #3                  // Field value:Lorg/hl7/fhir/dstu3/model/StringType;
      73: aload_2
      74: getfield      #3                  // Field value:Lorg/hl7/fhir/dstu3/model/StringType;
      77: iconst_1
      78: invokestatic  #88                 // Method compareDeep:(Lorg/hl7/fhir/dstu3/model/Base;Lorg/hl7/fhir/dstu3/model/Base;Z)Z
      81: ifeq          88
      84: iconst_1
      85: goto          89
      88: iconst_0
      89: ireturn

  public boolean equalsShallow(org.hl7.fhir.dstu3.model.Base);
    Code:
       0: aload_0
       1: aload_1
       2: invokespecial #90                 // Method org/hl7/fhir/dstu3/model/BackboneElement.equalsShallow:(Lorg/hl7/fhir/dstu3/model/Base;)Z
       5: ifne          10
       8: iconst_0
       9: ireturn
      10: aload_1
      11: instanceof    #81                 // class org/hl7/fhir/dstu3/model/CodeSystem$CodeSystemFilterComponent
      14: ifne          19
      17: iconst_0
      18: ireturn
      19: aload_1
      20: checkcast     #81                 // class org/hl7/fhir/dstu3/model/CodeSystem$CodeSystemFilterComponent
      23: astore_2
      24: aload_0
      25: getfield      #2                  // Field code:Lorg/hl7/fhir/dstu3/model/CodeType;
      28: aload_2
      29: getfield      #2                  // Field code:Lorg/hl7/fhir/dstu3/model/CodeType;
      32: iconst_1
      33: invokestatic  #91                 // Method compareValues:(Lorg/hl7/fhir/dstu3/model/PrimitiveType;Lorg/hl7/fhir/dstu3/model/PrimitiveType;Z)Z
      36: ifeq          88
      39: aload_0
      40: getfield      #15                 // Field description:Lorg/hl7/fhir/dstu3/model/StringType;
      43: aload_2
      44: getfield      #15                 // Field description:Lorg/hl7/fhir/dstu3/model/StringType;
      47: iconst_1
      48: invokestatic  #91                 // Method compareValues:(Lorg/hl7/fhir/dstu3/model/PrimitiveType;Lorg/hl7/fhir/dstu3/model/PrimitiveType;Z)Z
      51: ifeq          88
      54: aload_0
      55: getfield      #23                 // Field operator:Ljava/util/List;
      58: aload_2
      59: getfield      #23                 // Field operator:Ljava/util/List;
      62: iconst_1
      63: invokestatic  #92                 // Method compareValues:(Ljava/util/List;Ljava/util/List;Z)Z
      66: ifeq          88
      69: aload_0
      70: getfield      #3                  // Field value:Lorg/hl7/fhir/dstu3/model/StringType;
      73: aload_2
      74: getfield      #3                  // Field value:Lorg/hl7/fhir/dstu3/model/StringType;
      77: iconst_1
      78: invokestatic  #91                 // Method compareValues:(Lorg/hl7/fhir/dstu3/model/PrimitiveType;Lorg/hl7/fhir/dstu3/model/PrimitiveType;Z)Z
      81: ifeq          88
      84: iconst_1
      85: goto          89
      88: iconst_0
      89: ireturn

  public boolean isEmpty();
    Code:
       0: aload_0
       1: invokespecial #93                 // Method org/hl7/fhir/dstu3/model/BackboneElement.isEmpty:()Z
       4: ifeq          49
       7: iconst_4
       8: anewarray     #94                 // class java/lang/Object
      11: dup
      12: iconst_0
      13: aload_0
      14: getfield      #2                  // Field code:Lorg/hl7/fhir/dstu3/model/CodeType;
      17: aastore
      18: dup
      19: iconst_1
      20: aload_0
      21: getfield      #15                 // Field description:Lorg/hl7/fhir/dstu3/model/StringType;
      24: aastore
      25: dup
      26: iconst_2
      27: aload_0
      28: getfield      #23                 // Field operator:Ljava/util/List;
      31: aastore
      32: dup
      33: iconst_3
      34: aload_0
      35: getfield      #3                  // Field value:Lorg/hl7/fhir/dstu3/model/StringType;
      38: aastore
      39: invokestatic  #95                 // Method ca/uhn/fhir/util/ElementUtil.isEmpty:([Ljava/lang/Object;)Z
      42: ifeq          49
      45: iconst_1
      46: goto          50
      49: iconst_0
      50: ireturn

  public java.lang.String fhirType();
    Code:
       0: ldc           #96                 // String CodeSystem.filter
       2: areturn

  public org.hl7.fhir.dstu3.model.BackboneElement copy();
    Code:
       0: aload_0
       1: invokevirtual #97                 // Method copy:()Lorg/hl7/fhir/dstu3/model/CodeSystem$CodeSystemFilterComponent;
       4: areturn

  public org.hl7.fhir.dstu3.model.Element copy();
    Code:
       0: aload_0
       1: invokevirtual #97                 // Method copy:()Lorg/hl7/fhir/dstu3/model/CodeSystem$CodeSystemFilterComponent;
       4: areturn
}
