Compiled from "Encounter.java"
public class org.hl7.fhir.dstu3.model.Encounter extends org.hl7.fhir.dstu3.model.DomainResource {
  protected java.util.List<org.hl7.fhir.dstu3.model.Identifier> identifier;

  protected org.hl7.fhir.dstu3.model.Enumeration<org.hl7.fhir.dstu3.model.Encounter$EncounterStatus> status;

  protected java.util.List<org.hl7.fhir.dstu3.model.Encounter$StatusHistoryComponent> statusHistory;

  protected org.hl7.fhir.dstu3.model.Coding class_;

  protected java.util.List<org.hl7.fhir.dstu3.model.Encounter$ClassHistoryComponent> classHistory;

  protected java.util.List<org.hl7.fhir.dstu3.model.CodeableConcept> type;

  protected org.hl7.fhir.dstu3.model.CodeableConcept priority;

  protected org.hl7.fhir.dstu3.model.Reference subject;

  protected org.hl7.fhir.dstu3.model.Resource subjectTarget;

  protected java.util.List<org.hl7.fhir.dstu3.model.Reference> episodeOfCare;

  protected java.util.List<org.hl7.fhir.dstu3.model.EpisodeOfCare> episodeOfCareTarget;

  protected java.util.List<org.hl7.fhir.dstu3.model.Reference> incomingReferral;

  protected java.util.List<org.hl7.fhir.dstu3.model.ReferralRequest> incomingReferralTarget;

  protected java.util.List<org.hl7.fhir.dstu3.model.Encounter$EncounterParticipantComponent> participant;

  protected org.hl7.fhir.dstu3.model.Reference appointment;

  protected org.hl7.fhir.dstu3.model.Appointment appointmentTarget;

  protected org.hl7.fhir.dstu3.model.Period period;

  protected org.hl7.fhir.dstu3.model.Duration length;

  protected java.util.List<org.hl7.fhir.dstu3.model.CodeableConcept> reason;

  protected java.util.List<org.hl7.fhir.dstu3.model.Encounter$DiagnosisComponent> diagnosis;

  protected java.util.List<org.hl7.fhir.dstu3.model.Reference> account;

  protected java.util.List<org.hl7.fhir.dstu3.model.Account> accountTarget;

  protected org.hl7.fhir.dstu3.model.Encounter$EncounterHospitalizationComponent hospitalization;

  protected java.util.List<org.hl7.fhir.dstu3.model.Encounter$EncounterLocationComponent> location;

  protected org.hl7.fhir.dstu3.model.Reference serviceProvider;

  protected org.hl7.fhir.dstu3.model.Organization serviceProviderTarget;

  protected org.hl7.fhir.dstu3.model.Reference partOf;

  protected org.hl7.fhir.dstu3.model.Encounter partOfTarget;

  private static final long serialVersionUID;

  public static final java.lang.String SP_DATE;

  public static final ca.uhn.fhir.rest.gclient.DateClientParam DATE;

  public static final java.lang.String SP_IDENTIFIER;

  public static final ca.uhn.fhir.rest.gclient.TokenClientParam IDENTIFIER;

  public static final java.lang.String SP_REASON;

  public static final ca.uhn.fhir.rest.gclient.TokenClientParam REASON;

  public static final java.lang.String SP_EPISODEOFCARE;

  public static final ca.uhn.fhir.rest.gclient.ReferenceClientParam EPISODEOFCARE;

  public static final ca.uhn.fhir.model.api.Include INCLUDE_EPISODEOFCARE;

  public static final java.lang.String SP_PARTICIPANT_TYPE;

  public static final ca.uhn.fhir.rest.gclient.TokenClientParam PARTICIPANT_TYPE;

  public static final java.lang.String SP_INCOMINGREFERRAL;

  public static final ca.uhn.fhir.rest.gclient.ReferenceClientParam INCOMINGREFERRAL;

  public static final ca.uhn.fhir.model.api.Include INCLUDE_INCOMINGREFERRAL;

  public static final java.lang.String SP_PRACTITIONER;

  public static final ca.uhn.fhir.rest.gclient.ReferenceClientParam PRACTITIONER;

  public static final ca.uhn.fhir.model.api.Include INCLUDE_PRACTITIONER;

  public static final java.lang.String SP_SUBJECT;

  public static final ca.uhn.fhir.rest.gclient.ReferenceClientParam SUBJECT;

  public static final ca.uhn.fhir.model.api.Include INCLUDE_SUBJECT;

  public static final java.lang.String SP_LENGTH;

  public static final ca.uhn.fhir.rest.gclient.NumberClientParam LENGTH;

  public static final java.lang.String SP_DIAGNOSIS;

  public static final ca.uhn.fhir.rest.gclient.ReferenceClientParam DIAGNOSIS;

  public static final ca.uhn.fhir.model.api.Include INCLUDE_DIAGNOSIS;

  public static final java.lang.String SP_APPOINTMENT;

  public static final ca.uhn.fhir.rest.gclient.ReferenceClientParam APPOINTMENT;

  public static final ca.uhn.fhir.model.api.Include INCLUDE_APPOINTMENT;

  public static final java.lang.String SP_PART_OF;

  public static final ca.uhn.fhir.rest.gclient.ReferenceClientParam PART_OF;

  public static final ca.uhn.fhir.model.api.Include INCLUDE_PART_OF;

  public static final java.lang.String SP_TYPE;

  public static final ca.uhn.fhir.rest.gclient.TokenClientParam TYPE;

  public static final java.lang.String SP_PARTICIPANT;

  public static final ca.uhn.fhir.rest.gclient.ReferenceClientParam PARTICIPANT;

  public static final ca.uhn.fhir.model.api.Include INCLUDE_PARTICIPANT;

  public static final java.lang.String SP_PATIENT;

  public static final ca.uhn.fhir.rest.gclient.ReferenceClientParam PATIENT;

  public static final ca.uhn.fhir.model.api.Include INCLUDE_PATIENT;

  public static final java.lang.String SP_LOCATION_PERIOD;

  public static final ca.uhn.fhir.rest.gclient.DateClientParam LOCATION_PERIOD;

  public static final java.lang.String SP_LOCATION;

  public static final ca.uhn.fhir.rest.gclient.ReferenceClientParam LOCATION;

  public static final ca.uhn.fhir.model.api.Include INCLUDE_LOCATION;

  public static final java.lang.String SP_SERVICE_PROVIDER;

  public static final ca.uhn.fhir.rest.gclient.ReferenceClientParam SERVICE_PROVIDER;

  public static final ca.uhn.fhir.model.api.Include INCLUDE_SERVICE_PROVIDER;

  public static final java.lang.String SP_SPECIAL_ARRANGEMENT;

  public static final ca.uhn.fhir.rest.gclient.TokenClientParam SPECIAL_ARRANGEMENT;

  public static final java.lang.String SP_CLASS;

  public static final ca.uhn.fhir.rest.gclient.TokenClientParam CLASS;

  public static final java.lang.String SP_STATUS;

  public static final ca.uhn.fhir.rest.gclient.TokenClientParam STATUS;

  public org.hl7.fhir.dstu3.model.Encounter();
    Code:
       0: aload_0
       1: invokespecial #1                  // Method org/hl7/fhir/dstu3/model/DomainResource."<init>":()V
       4: return

  public org.hl7.fhir.dstu3.model.Encounter(org.hl7.fhir.dstu3.model.Enumeration<org.hl7.fhir.dstu3.model.Encounter$EncounterStatus>);
    Code:
       0: aload_0
       1: invokespecial #1                  // Method org/hl7/fhir/dstu3/model/DomainResource."<init>":()V
       4: aload_0
       5: aload_1
       6: putfield      #2                  // Field status:Lorg/hl7/fhir/dstu3/model/Enumeration;
       9: return

  public java.util.List<org.hl7.fhir.dstu3.model.Identifier> getIdentifier();
    Code:
       0: aload_0
       1: getfield      #3                  // Field identifier:Ljava/util/List;
       4: ifnonnull     18
       7: aload_0
       8: new           #4                  // class java/util/ArrayList
      11: dup
      12: invokespecial #5                  // Method java/util/ArrayList."<init>":()V
      15: putfield      #3                  // Field identifier:Ljava/util/List;
      18: aload_0
      19: getfield      #3                  // Field identifier:Ljava/util/List;
      22: areturn

  public org.hl7.fhir.dstu3.model.Encounter setIdentifier(java.util.List<org.hl7.fhir.dstu3.model.Identifier>);
    Code:
       0: aload_0
       1: aload_1
       2: putfield      #3                  // Field identifier:Ljava/util/List;
       5: aload_0
       6: areturn

  public boolean hasIdentifier();
    Code:
       0: aload_0
       1: getfield      #3                  // Field identifier:Ljava/util/List;
       4: ifnonnull     9
       7: iconst_0
       8: ireturn
       9: aload_0
      10: getfield      #3                  // Field identifier:Ljava/util/List;
      13: invokeinterface #6,  1            // InterfaceMethod java/util/List.iterator:()Ljava/util/Iterator;
      18: astore_1
      19: aload_1
      20: invokeinterface #7,  1            // InterfaceMethod java/util/Iterator.hasNext:()Z
      25: ifeq          50
      28: aload_1
      29: invokeinterface #8,  1            // InterfaceMethod java/util/Iterator.next:()Ljava/lang/Object;
      34: checkcast     #9                  // class org/hl7/fhir/dstu3/model/Identifier
      37: astore_2
      38: aload_2
      39: invokevirtual #10                 // Method org/hl7/fhir/dstu3/model/Identifier.isEmpty:()Z
      42: ifne          47
      45: iconst_1
      46: ireturn
      47: goto          19
      50: iconst_0
      51: ireturn

  public org.hl7.fhir.dstu3.model.Identifier addIdentifier();
    Code:
       0: new           #9                  // class org/hl7/fhir/dstu3/model/Identifier
       3: dup
       4: invokespecial #11                 // Method org/hl7/fhir/dstu3/model/Identifier."<init>":()V
       7: astore_1
       8: aload_0
       9: getfield      #3                  // Field identifier:Ljava/util/List;
      12: ifnonnull     26
      15: aload_0
      16: new           #4                  // class java/util/ArrayList
      19: dup
      20: invokespecial #5                  // Method java/util/ArrayList."<init>":()V
      23: putfield      #3                  // Field identifier:Ljava/util/List;
      26: aload_0
      27: getfield      #3                  // Field identifier:Ljava/util/List;
      30: aload_1
      31: invokeinterface #12,  2           // InterfaceMethod java/util/List.add:(Ljava/lang/Object;)Z
      36: pop
      37: aload_1
      38: areturn

  public org.hl7.fhir.dstu3.model.Encounter addIdentifier(org.hl7.fhir.dstu3.model.Identifier);
    Code:
       0: aload_1
       1: ifnonnull     6
       4: aload_0
       5: areturn
       6: aload_0
       7: getfield      #3                  // Field identifier:Ljava/util/List;
      10: ifnonnull     24
      13: aload_0
      14: new           #4                  // class java/util/ArrayList
      17: dup
      18: invokespecial #5                  // Method java/util/ArrayList."<init>":()V
      21: putfield      #3                  // Field identifier:Ljava/util/List;
      24: aload_0
      25: getfield      #3                  // Field identifier:Ljava/util/List;
      28: aload_1
      29: invokeinterface #12,  2           // InterfaceMethod java/util/List.add:(Ljava/lang/Object;)Z
      34: pop
      35: aload_0
      36: areturn

  public org.hl7.fhir.dstu3.model.Identifier getIdentifierFirstRep();
    Code:
       0: aload_0
       1: invokevirtual #13                 // Method getIdentifier:()Ljava/util/List;
       4: invokeinterface #14,  1           // InterfaceMethod java/util/List.isEmpty:()Z
       9: ifeq          17
      12: aload_0
      13: invokevirtual #15                 // Method addIdentifier:()Lorg/hl7/fhir/dstu3/model/Identifier;
      16: pop
      17: aload_0
      18: invokevirtual #13                 // Method getIdentifier:()Ljava/util/List;
      21: iconst_0
      22: invokeinterface #16,  2           // InterfaceMethod java/util/List.get:(I)Ljava/lang/Object;
      27: checkcast     #9                  // class org/hl7/fhir/dstu3/model/Identifier
      30: areturn

  public org.hl7.fhir.dstu3.model.Enumeration<org.hl7.fhir.dstu3.model.Encounter$EncounterStatus> getStatusElement();
    Code:
       0: aload_0
       1: getfield      #2                  // Field status:Lorg/hl7/fhir/dstu3/model/Enumeration;
       4: ifnonnull     47
       7: invokestatic  #17                 // Method org/hl7/fhir/dstu3/model/Configuration.errorOnAutoCreate:()Z
      10: ifeq          23
      13: new           #18                 // class java/lang/Error
      16: dup
      17: ldc           #19                 // String Attempt to auto-create Encounter.status
      19: invokespecial #20                 // Method java/lang/Error."<init>":(Ljava/lang/String;)V
      22: athrow
      23: invokestatic  #21                 // Method org/hl7/fhir/dstu3/model/Configuration.doAutoCreate:()Z
      26: ifeq          47
      29: aload_0
      30: new           #22                 // class org/hl7/fhir/dstu3/model/Enumeration
      33: dup
      34: new           #23                 // class org/hl7/fhir/dstu3/model/Encounter$EncounterStatusEnumFactory
      37: dup
      38: invokespecial #24                 // Method org/hl7/fhir/dstu3/model/Encounter$EncounterStatusEnumFactory."<init>":()V
      41: invokespecial #25                 // Method org/hl7/fhir/dstu3/model/Enumeration."<init>":(Lorg/hl7/fhir/dstu3/model/EnumFactory;)V
      44: putfield      #2                  // Field status:Lorg/hl7/fhir/dstu3/model/Enumeration;
      47: aload_0
      48: getfield      #2                  // Field status:Lorg/hl7/fhir/dstu3/model/Enumeration;
      51: areturn

  public boolean hasStatusElement();
    Code:
       0: aload_0
       1: getfield      #2                  // Field status:Lorg/hl7/fhir/dstu3/model/Enumeration;
       4: ifnull        21
       7: aload_0
       8: getfield      #2                  // Field status:Lorg/hl7/fhir/dstu3/model/Enumeration;
      11: invokevirtual #26                 // Method org/hl7/fhir/dstu3/model/Enumeration.isEmpty:()Z
      14: ifne          21
      17: iconst_1
      18: goto          22
      21: iconst_0
      22: ireturn

  public boolean hasStatus();
    Code:
       0: aload_0
       1: getfield      #2                  // Field status:Lorg/hl7/fhir/dstu3/model/Enumeration;
       4: ifnull        21
       7: aload_0
       8: getfield      #2                  // Field status:Lorg/hl7/fhir/dstu3/model/Enumeration;
      11: invokevirtual #26                 // Method org/hl7/fhir/dstu3/model/Enumeration.isEmpty:()Z
      14: ifne          21
      17: iconst_1
      18: goto          22
      21: iconst_0
      22: ireturn

  public org.hl7.fhir.dstu3.model.Encounter setStatusElement(org.hl7.fhir.dstu3.model.Enumeration<org.hl7.fhir.dstu3.model.Encounter$EncounterStatus>);
    Code:
       0: aload_0
       1: aload_1
       2: putfield      #2                  // Field status:Lorg/hl7/fhir/dstu3/model/Enumeration;
       5: aload_0
       6: areturn

  public org.hl7.fhir.dstu3.model.Encounter$EncounterStatus getStatus();
    Code:
       0: aload_0
       1: getfield      #2                  // Field status:Lorg/hl7/fhir/dstu3/model/Enumeration;
       4: ifnonnull     11
       7: aconst_null
       8: goto          21
      11: aload_0
      12: getfield      #2                  // Field status:Lorg/hl7/fhir/dstu3/model/Enumeration;
      15: invokevirtual #27                 // Method org/hl7/fhir/dstu3/model/Enumeration.getValue:()Ljava/lang/Object;
      18: checkcast     #28                 // class org/hl7/fhir/dstu3/model/Encounter$EncounterStatus
      21: areturn

  public org.hl7.fhir.dstu3.model.Encounter setStatus(org.hl7.fhir.dstu3.model.Encounter$EncounterStatus);
    Code:
       0: aload_0
       1: getfield      #2                  // Field status:Lorg/hl7/fhir/dstu3/model/Enumeration;
       4: ifnonnull     25
       7: aload_0
       8: new           #22                 // class org/hl7/fhir/dstu3/model/Enumeration
      11: dup
      12: new           #23                 // class org/hl7/fhir/dstu3/model/Encounter$EncounterStatusEnumFactory
      15: dup
      16: invokespecial #24                 // Method org/hl7/fhir/dstu3/model/Encounter$EncounterStatusEnumFactory."<init>":()V
      19: invokespecial #25                 // Method org/hl7/fhir/dstu3/model/Enumeration."<init>":(Lorg/hl7/fhir/dstu3/model/EnumFactory;)V
      22: putfield      #2                  // Field status:Lorg/hl7/fhir/dstu3/model/Enumeration;
      25: aload_0
      26: getfield      #2                  // Field status:Lorg/hl7/fhir/dstu3/model/Enumeration;
      29: aload_1
      30: invokevirtual #29                 // Method org/hl7/fhir/dstu3/model/Enumeration.setValue:(Ljava/lang/Object;)Lorg/hl7/fhir/dstu3/model/PrimitiveType;
      33: pop
      34: aload_0
      35: areturn

  public java.util.List<org.hl7.fhir.dstu3.model.Encounter$StatusHistoryComponent> getStatusHistory();
    Code:
       0: aload_0
       1: getfield      #30                 // Field statusHistory:Ljava/util/List;
       4: ifnonnull     18
       7: aload_0
       8: new           #4                  // class java/util/ArrayList
      11: dup
      12: invokespecial #5                  // Method java/util/ArrayList."<init>":()V
      15: putfield      #30                 // Field statusHistory:Ljava/util/List;
      18: aload_0
      19: getfield      #30                 // Field statusHistory:Ljava/util/List;
      22: areturn

  public org.hl7.fhir.dstu3.model.Encounter setStatusHistory(java.util.List<org.hl7.fhir.dstu3.model.Encounter$StatusHistoryComponent>);
    Code:
       0: aload_0
       1: aload_1
       2: putfield      #30                 // Field statusHistory:Ljava/util/List;
       5: aload_0
       6: areturn

  public boolean hasStatusHistory();
    Code:
       0: aload_0
       1: getfield      #30                 // Field statusHistory:Ljava/util/List;
       4: ifnonnull     9
       7: iconst_0
       8: ireturn
       9: aload_0
      10: getfield      #30                 // Field statusHistory:Ljava/util/List;
      13: invokeinterface #6,  1            // InterfaceMethod java/util/List.iterator:()Ljava/util/Iterator;
      18: astore_1
      19: aload_1
      20: invokeinterface #7,  1            // InterfaceMethod java/util/Iterator.hasNext:()Z
      25: ifeq          50
      28: aload_1
      29: invokeinterface #8,  1            // InterfaceMethod java/util/Iterator.next:()Ljava/lang/Object;
      34: checkcast     #31                 // class org/hl7/fhir/dstu3/model/Encounter$StatusHistoryComponent
      37: astore_2
      38: aload_2
      39: invokevirtual #32                 // Method org/hl7/fhir/dstu3/model/Encounter$StatusHistoryComponent.isEmpty:()Z
      42: ifne          47
      45: iconst_1
      46: ireturn
      47: goto          19
      50: iconst_0
      51: ireturn

  public org.hl7.fhir.dstu3.model.Encounter$StatusHistoryComponent addStatusHistory();
    Code:
       0: new           #31                 // class org/hl7/fhir/dstu3/model/Encounter$StatusHistoryComponent
       3: dup
       4: invokespecial #33                 // Method org/hl7/fhir/dstu3/model/Encounter$StatusHistoryComponent."<init>":()V
       7: astore_1
       8: aload_0
       9: getfield      #30                 // Field statusHistory:Ljava/util/List;
      12: ifnonnull     26
      15: aload_0
      16: new           #4                  // class java/util/ArrayList
      19: dup
      20: invokespecial #5                  // Method java/util/ArrayList."<init>":()V
      23: putfield      #30                 // Field statusHistory:Ljava/util/List;
      26: aload_0
      27: getfield      #30                 // Field statusHistory:Ljava/util/List;
      30: aload_1
      31: invokeinterface #12,  2           // InterfaceMethod java/util/List.add:(Ljava/lang/Object;)Z
      36: pop
      37: aload_1
      38: areturn

  public org.hl7.fhir.dstu3.model.Encounter addStatusHistory(org.hl7.fhir.dstu3.model.Encounter$StatusHistoryComponent);
    Code:
       0: aload_1
       1: ifnonnull     6
       4: aload_0
       5: areturn
       6: aload_0
       7: getfield      #30                 // Field statusHistory:Ljava/util/List;
      10: ifnonnull     24
      13: aload_0
      14: new           #4                  // class java/util/ArrayList
      17: dup
      18: invokespecial #5                  // Method java/util/ArrayList."<init>":()V
      21: putfield      #30                 // Field statusHistory:Ljava/util/List;
      24: aload_0
      25: getfield      #30                 // Field statusHistory:Ljava/util/List;
      28: aload_1
      29: invokeinterface #12,  2           // InterfaceMethod java/util/List.add:(Ljava/lang/Object;)Z
      34: pop
      35: aload_0
      36: areturn

  public org.hl7.fhir.dstu3.model.Encounter$StatusHistoryComponent getStatusHistoryFirstRep();
    Code:
       0: aload_0
       1: invokevirtual #34                 // Method getStatusHistory:()Ljava/util/List;
       4: invokeinterface #14,  1           // InterfaceMethod java/util/List.isEmpty:()Z
       9: ifeq          17
      12: aload_0
      13: invokevirtual #35                 // Method addStatusHistory:()Lorg/hl7/fhir/dstu3/model/Encounter$StatusHistoryComponent;
      16: pop
      17: aload_0
      18: invokevirtual #34                 // Method getStatusHistory:()Ljava/util/List;
      21: iconst_0
      22: invokeinterface #16,  2           // InterfaceMethod java/util/List.get:(I)Ljava/lang/Object;
      27: checkcast     #31                 // class org/hl7/fhir/dstu3/model/Encounter$StatusHistoryComponent
      30: areturn

  public org.hl7.fhir.dstu3.model.Coding getClass_();
    Code:
       0: aload_0
       1: getfield      #36                 // Field class_:Lorg/hl7/fhir/dstu3/model/Coding;
       4: ifnonnull     40
       7: invokestatic  #17                 // Method org/hl7/fhir/dstu3/model/Configuration.errorOnAutoCreate:()Z
      10: ifeq          23
      13: new           #18                 // class java/lang/Error
      16: dup
      17: ldc           #37                 // String Attempt to auto-create Encounter.class_
      19: invokespecial #20                 // Method java/lang/Error."<init>":(Ljava/lang/String;)V
      22: athrow
      23: invokestatic  #21                 // Method org/hl7/fhir/dstu3/model/Configuration.doAutoCreate:()Z
      26: ifeq          40
      29: aload_0
      30: new           #38                 // class org/hl7/fhir/dstu3/model/Coding
      33: dup
      34: invokespecial #39                 // Method org/hl7/fhir/dstu3/model/Coding."<init>":()V
      37: putfield      #36                 // Field class_:Lorg/hl7/fhir/dstu3/model/Coding;
      40: aload_0
      41: getfield      #36                 // Field class_:Lorg/hl7/fhir/dstu3/model/Coding;
      44: areturn

  public boolean hasClass_();
    Code:
       0: aload_0
       1: getfield      #36                 // Field class_:Lorg/hl7/fhir/dstu3/model/Coding;
       4: ifnull        21
       7: aload_0
       8: getfield      #36                 // Field class_:Lorg/hl7/fhir/dstu3/model/Coding;
      11: invokevirtual #40                 // Method org/hl7/fhir/dstu3/model/Coding.isEmpty:()Z
      14: ifne          21
      17: iconst_1
      18: goto          22
      21: iconst_0
      22: ireturn

  public org.hl7.fhir.dstu3.model.Encounter setClass_(org.hl7.fhir.dstu3.model.Coding);
    Code:
       0: aload_0
       1: aload_1
       2: putfield      #36                 // Field class_:Lorg/hl7/fhir/dstu3/model/Coding;
       5: aload_0
       6: areturn

  public java.util.List<org.hl7.fhir.dstu3.model.Encounter$ClassHistoryComponent> getClassHistory();
    Code:
       0: aload_0
       1: getfield      #41                 // Field classHistory:Ljava/util/List;
       4: ifnonnull     18
       7: aload_0
       8: new           #4                  // class java/util/ArrayList
      11: dup
      12: invokespecial #5                  // Method java/util/ArrayList."<init>":()V
      15: putfield      #41                 // Field classHistory:Ljava/util/List;
      18: aload_0
      19: getfield      #41                 // Field classHistory:Ljava/util/List;
      22: areturn

  public org.hl7.fhir.dstu3.model.Encounter setClassHistory(java.util.List<org.hl7.fhir.dstu3.model.Encounter$ClassHistoryComponent>);
    Code:
       0: aload_0
       1: aload_1
       2: putfield      #41                 // Field classHistory:Ljava/util/List;
       5: aload_0
       6: areturn

  public boolean hasClassHistory();
    Code:
       0: aload_0
       1: getfield      #41                 // Field classHistory:Ljava/util/List;
       4: ifnonnull     9
       7: iconst_0
       8: ireturn
       9: aload_0
      10: getfield      #41                 // Field classHistory:Ljava/util/List;
      13: invokeinterface #6,  1            // InterfaceMethod java/util/List.iterator:()Ljava/util/Iterator;
      18: astore_1
      19: aload_1
      20: invokeinterface #7,  1            // InterfaceMethod java/util/Iterator.hasNext:()Z
      25: ifeq          50
      28: aload_1
      29: invokeinterface #8,  1            // InterfaceMethod java/util/Iterator.next:()Ljava/lang/Object;
      34: checkcast     #42                 // class org/hl7/fhir/dstu3/model/Encounter$ClassHistoryComponent
      37: astore_2
      38: aload_2
      39: invokevirtual #43                 // Method org/hl7/fhir/dstu3/model/Encounter$ClassHistoryComponent.isEmpty:()Z
      42: ifne          47
      45: iconst_1
      46: ireturn
      47: goto          19
      50: iconst_0
      51: ireturn

  public org.hl7.fhir.dstu3.model.Encounter$ClassHistoryComponent addClassHistory();
    Code:
       0: new           #42                 // class org/hl7/fhir/dstu3/model/Encounter$ClassHistoryComponent
       3: dup
       4: invokespecial #44                 // Method org/hl7/fhir/dstu3/model/Encounter$ClassHistoryComponent."<init>":()V
       7: astore_1
       8: aload_0
       9: getfield      #41                 // Field classHistory:Ljava/util/List;
      12: ifnonnull     26
      15: aload_0
      16: new           #4                  // class java/util/ArrayList
      19: dup
      20: invokespecial #5                  // Method java/util/ArrayList."<init>":()V
      23: putfield      #41                 // Field classHistory:Ljava/util/List;
      26: aload_0
      27: getfield      #41                 // Field classHistory:Ljava/util/List;
      30: aload_1
      31: invokeinterface #12,  2           // InterfaceMethod java/util/List.add:(Ljava/lang/Object;)Z
      36: pop
      37: aload_1
      38: areturn

  public org.hl7.fhir.dstu3.model.Encounter addClassHistory(org.hl7.fhir.dstu3.model.Encounter$ClassHistoryComponent);
    Code:
       0: aload_1
       1: ifnonnull     6
       4: aload_0
       5: areturn
       6: aload_0
       7: getfield      #41                 // Field classHistory:Ljava/util/List;
      10: ifnonnull     24
      13: aload_0
      14: new           #4                  // class java/util/ArrayList
      17: dup
      18: invokespecial #5                  // Method java/util/ArrayList."<init>":()V
      21: putfield      #41                 // Field classHistory:Ljava/util/List;
      24: aload_0
      25: getfield      #41                 // Field classHistory:Ljava/util/List;
      28: aload_1
      29: invokeinterface #12,  2           // InterfaceMethod java/util/List.add:(Ljava/lang/Object;)Z
      34: pop
      35: aload_0
      36: areturn

  public org.hl7.fhir.dstu3.model.Encounter$ClassHistoryComponent getClassHistoryFirstRep();
    Code:
       0: aload_0
       1: invokevirtual #45                 // Method getClassHistory:()Ljava/util/List;
       4: invokeinterface #14,  1           // InterfaceMethod java/util/List.isEmpty:()Z
       9: ifeq          17
      12: aload_0
      13: invokevirtual #46                 // Method addClassHistory:()Lorg/hl7/fhir/dstu3/model/Encounter$ClassHistoryComponent;
      16: pop
      17: aload_0
      18: invokevirtual #45                 // Method getClassHistory:()Ljava/util/List;
      21: iconst_0
      22: invokeinterface #16,  2           // InterfaceMethod java/util/List.get:(I)Ljava/lang/Object;
      27: checkcast     #42                 // class org/hl7/fhir/dstu3/model/Encounter$ClassHistoryComponent
      30: areturn

  public java.util.List<org.hl7.fhir.dstu3.model.CodeableConcept> getType();
    Code:
       0: aload_0
       1: getfield      #47                 // Field type:Ljava/util/List;
       4: ifnonnull     18
       7: aload_0
       8: new           #4                  // class java/util/ArrayList
      11: dup
      12: invokespecial #5                  // Method java/util/ArrayList."<init>":()V
      15: putfield      #47                 // Field type:Ljava/util/List;
      18: aload_0
      19: getfield      #47                 // Field type:Ljava/util/List;
      22: areturn

  public org.hl7.fhir.dstu3.model.Encounter setType(java.util.List<org.hl7.fhir.dstu3.model.CodeableConcept>);
    Code:
       0: aload_0
       1: aload_1
       2: putfield      #47                 // Field type:Ljava/util/List;
       5: aload_0
       6: areturn

  public boolean hasType();
    Code:
       0: aload_0
       1: getfield      #47                 // Field type:Ljava/util/List;
       4: ifnonnull     9
       7: iconst_0
       8: ireturn
       9: aload_0
      10: getfield      #47                 // Field type:Ljava/util/List;
      13: invokeinterface #6,  1            // InterfaceMethod java/util/List.iterator:()Ljava/util/Iterator;
      18: astore_1
      19: aload_1
      20: invokeinterface #7,  1            // InterfaceMethod java/util/Iterator.hasNext:()Z
      25: ifeq          50
      28: aload_1
      29: invokeinterface #8,  1            // InterfaceMethod java/util/Iterator.next:()Ljava/lang/Object;
      34: checkcast     #48                 // class org/hl7/fhir/dstu3/model/CodeableConcept
      37: astore_2
      38: aload_2
      39: invokevirtual #49                 // Method org/hl7/fhir/dstu3/model/CodeableConcept.isEmpty:()Z
      42: ifne          47
      45: iconst_1
      46: ireturn
      47: goto          19
      50: iconst_0
      51: ireturn

  public org.hl7.fhir.dstu3.model.CodeableConcept addType();
    Code:
       0: new           #48                 // class org/hl7/fhir/dstu3/model/CodeableConcept
       3: dup
       4: invokespecial #50                 // Method org/hl7/fhir/dstu3/model/CodeableConcept."<init>":()V
       7: astore_1
       8: aload_0
       9: getfield      #47                 // Field type:Ljava/util/List;
      12: ifnonnull     26
      15: aload_0
      16: new           #4                  // class java/util/ArrayList
      19: dup
      20: invokespecial #5                  // Method java/util/ArrayList."<init>":()V
      23: putfield      #47                 // Field type:Ljava/util/List;
      26: aload_0
      27: getfield      #47                 // Field type:Ljava/util/List;
      30: aload_1
      31: invokeinterface #12,  2           // InterfaceMethod java/util/List.add:(Ljava/lang/Object;)Z
      36: pop
      37: aload_1
      38: areturn

  public org.hl7.fhir.dstu3.model.Encounter addType(org.hl7.fhir.dstu3.model.CodeableConcept);
    Code:
       0: aload_1
       1: ifnonnull     6
       4: aload_0
       5: areturn
       6: aload_0
       7: getfield      #47                 // Field type:Ljava/util/List;
      10: ifnonnull     24
      13: aload_0
      14: new           #4                  // class java/util/ArrayList
      17: dup
      18: invokespecial #5                  // Method java/util/ArrayList."<init>":()V
      21: putfield      #47                 // Field type:Ljava/util/List;
      24: aload_0
      25: getfield      #47                 // Field type:Ljava/util/List;
      28: aload_1
      29: invokeinterface #12,  2           // InterfaceMethod java/util/List.add:(Ljava/lang/Object;)Z
      34: pop
      35: aload_0
      36: areturn

  public org.hl7.fhir.dstu3.model.CodeableConcept getTypeFirstRep();
    Code:
       0: aload_0
       1: invokevirtual #51                 // Method getType:()Ljava/util/List;
       4: invokeinterface #14,  1           // InterfaceMethod java/util/List.isEmpty:()Z
       9: ifeq          17
      12: aload_0
      13: invokevirtual #52                 // Method addType:()Lorg/hl7/fhir/dstu3/model/CodeableConcept;
      16: pop
      17: aload_0
      18: invokevirtual #51                 // Method getType:()Ljava/util/List;
      21: iconst_0
      22: invokeinterface #16,  2           // InterfaceMethod java/util/List.get:(I)Ljava/lang/Object;
      27: checkcast     #48                 // class org/hl7/fhir/dstu3/model/CodeableConcept
      30: areturn

  public org.hl7.fhir.dstu3.model.CodeableConcept getPriority();
    Code:
       0: aload_0
       1: getfield      #53                 // Field priority:Lorg/hl7/fhir/dstu3/model/CodeableConcept;
       4: ifnonnull     40
       7: invokestatic  #17                 // Method org/hl7/fhir/dstu3/model/Configuration.errorOnAutoCreate:()Z
      10: ifeq          23
      13: new           #18                 // class java/lang/Error
      16: dup
      17: ldc           #54                 // String Attempt to auto-create Encounter.priority
      19: invokespecial #20                 // Method java/lang/Error."<init>":(Ljava/lang/String;)V
      22: athrow
      23: invokestatic  #21                 // Method org/hl7/fhir/dstu3/model/Configuration.doAutoCreate:()Z
      26: ifeq          40
      29: aload_0
      30: new           #48                 // class org/hl7/fhir/dstu3/model/CodeableConcept
      33: dup
      34: invokespecial #50                 // Method org/hl7/fhir/dstu3/model/CodeableConcept."<init>":()V
      37: putfield      #53                 // Field priority:Lorg/hl7/fhir/dstu3/model/CodeableConcept;
      40: aload_0
      41: getfield      #53                 // Field priority:Lorg/hl7/fhir/dstu3/model/CodeableConcept;
      44: areturn

  public boolean hasPriority();
    Code:
       0: aload_0
       1: getfield      #53                 // Field priority:Lorg/hl7/fhir/dstu3/model/CodeableConcept;
       4: ifnull        21
       7: aload_0
       8: getfield      #53                 // Field priority:Lorg/hl7/fhir/dstu3/model/CodeableConcept;
      11: invokevirtual #49                 // Method org/hl7/fhir/dstu3/model/CodeableConcept.isEmpty:()Z
      14: ifne          21
      17: iconst_1
      18: goto          22
      21: iconst_0
      22: ireturn

  public org.hl7.fhir.dstu3.model.Encounter setPriority(org.hl7.fhir.dstu3.model.CodeableConcept);
    Code:
       0: aload_0
       1: aload_1
       2: putfield      #53                 // Field priority:Lorg/hl7/fhir/dstu3/model/CodeableConcept;
       5: aload_0
       6: areturn

  public org.hl7.fhir.dstu3.model.Reference getSubject();
    Code:
       0: aload_0
       1: getfield      #55                 // Field subject:Lorg/hl7/fhir/dstu3/model/Reference;
       4: ifnonnull     40
       7: invokestatic  #17                 // Method org/hl7/fhir/dstu3/model/Configuration.errorOnAutoCreate:()Z
      10: ifeq          23
      13: new           #18                 // class java/lang/Error
      16: dup
      17: ldc           #56                 // String Attempt to auto-create Encounter.subject
      19: invokespecial #20                 // Method java/lang/Error."<init>":(Ljava/lang/String;)V
      22: athrow
      23: invokestatic  #21                 // Method org/hl7/fhir/dstu3/model/Configuration.doAutoCreate:()Z
      26: ifeq          40
      29: aload_0
      30: new           #57                 // class org/hl7/fhir/dstu3/model/Reference
      33: dup
      34: invokespecial #58                 // Method org/hl7/fhir/dstu3/model/Reference."<init>":()V
      37: putfield      #55                 // Field subject:Lorg/hl7/fhir/dstu3/model/Reference;
      40: aload_0
      41: getfield      #55                 // Field subject:Lorg/hl7/fhir/dstu3/model/Reference;
      44: areturn

  public boolean hasSubject();
    Code:
       0: aload_0
       1: getfield      #55                 // Field subject:Lorg/hl7/fhir/dstu3/model/Reference;
       4: ifnull        21
       7: aload_0
       8: getfield      #55                 // Field subject:Lorg/hl7/fhir/dstu3/model/Reference;
      11: invokevirtual #59                 // Method org/hl7/fhir/dstu3/model/Reference.isEmpty:()Z
      14: ifne          21
      17: iconst_1
      18: goto          22
      21: iconst_0
      22: ireturn

  public org.hl7.fhir.dstu3.model.Encounter setSubject(org.hl7.fhir.dstu3.model.Reference);
    Code:
       0: aload_0
       1: aload_1
       2: putfield      #55                 // Field subject:Lorg/hl7/fhir/dstu3/model/Reference;
       5: aload_0
       6: areturn

  public org.hl7.fhir.dstu3.model.Resource getSubjectTarget();
    Code:
       0: aload_0
       1: getfield      #60                 // Field subjectTarget:Lorg/hl7/fhir/dstu3/model/Resource;
       4: areturn

  public org.hl7.fhir.dstu3.model.Encounter setSubjectTarget(org.hl7.fhir.dstu3.model.Resource);
    Code:
       0: aload_0
       1: aload_1
       2: putfield      #60                 // Field subjectTarget:Lorg/hl7/fhir/dstu3/model/Resource;
       5: aload_0
       6: areturn

  public java.util.List<org.hl7.fhir.dstu3.model.Reference> getEpisodeOfCare();
    Code:
       0: aload_0
       1: getfield      #61                 // Field episodeOfCare:Ljava/util/List;
       4: ifnonnull     18
       7: aload_0
       8: new           #4                  // class java/util/ArrayList
      11: dup
      12: invokespecial #5                  // Method java/util/ArrayList."<init>":()V
      15: putfield      #61                 // Field episodeOfCare:Ljava/util/List;
      18: aload_0
      19: getfield      #61                 // Field episodeOfCare:Ljava/util/List;
      22: areturn

  public org.hl7.fhir.dstu3.model.Encounter setEpisodeOfCare(java.util.List<org.hl7.fhir.dstu3.model.Reference>);
    Code:
       0: aload_0
       1: aload_1
       2: putfield      #61                 // Field episodeOfCare:Ljava/util/List;
       5: aload_0
       6: areturn

  public boolean hasEpisodeOfCare();
    Code:
       0: aload_0
       1: getfield      #61                 // Field episodeOfCare:Ljava/util/List;
       4: ifnonnull     9
       7: iconst_0
       8: ireturn
       9: aload_0
      10: getfield      #61                 // Field episodeOfCare:Ljava/util/List;
      13: invokeinterface #6,  1            // InterfaceMethod java/util/List.iterator:()Ljava/util/Iterator;
      18: astore_1
      19: aload_1
      20: invokeinterface #7,  1            // InterfaceMethod java/util/Iterator.hasNext:()Z
      25: ifeq          50
      28: aload_1
      29: invokeinterface #8,  1            // InterfaceMethod java/util/Iterator.next:()Ljava/lang/Object;
      34: checkcast     #57                 // class org/hl7/fhir/dstu3/model/Reference
      37: astore_2
      38: aload_2
      39: invokevirtual #59                 // Method org/hl7/fhir/dstu3/model/Reference.isEmpty:()Z
      42: ifne          47
      45: iconst_1
      46: ireturn
      47: goto          19
      50: iconst_0
      51: ireturn

  public org.hl7.fhir.dstu3.model.Reference addEpisodeOfCare();
    Code:
       0: new           #57                 // class org/hl7/fhir/dstu3/model/Reference
       3: dup
       4: invokespecial #58                 // Method org/hl7/fhir/dstu3/model/Reference."<init>":()V
       7: astore_1
       8: aload_0
       9: getfield      #61                 // Field episodeOfCare:Ljava/util/List;
      12: ifnonnull     26
      15: aload_0
      16: new           #4                  // class java/util/ArrayList
      19: dup
      20: invokespecial #5                  // Method java/util/ArrayList."<init>":()V
      23: putfield      #61                 // Field episodeOfCare:Ljava/util/List;
      26: aload_0
      27: getfield      #61                 // Field episodeOfCare:Ljava/util/List;
      30: aload_1
      31: invokeinterface #12,  2           // InterfaceMethod java/util/List.add:(Ljava/lang/Object;)Z
      36: pop
      37: aload_1
      38: areturn

  public org.hl7.fhir.dstu3.model.Encounter addEpisodeOfCare(org.hl7.fhir.dstu3.model.Reference);
    Code:
       0: aload_1
       1: ifnonnull     6
       4: aload_0
       5: areturn
       6: aload_0
       7: getfield      #61                 // Field episodeOfCare:Ljava/util/List;
      10: ifnonnull     24
      13: aload_0
      14: new           #4                  // class java/util/ArrayList
      17: dup
      18: invokespecial #5                  // Method java/util/ArrayList."<init>":()V
      21: putfield      #61                 // Field episodeOfCare:Ljava/util/List;
      24: aload_0
      25: getfield      #61                 // Field episodeOfCare:Ljava/util/List;
      28: aload_1
      29: invokeinterface #12,  2           // InterfaceMethod java/util/List.add:(Ljava/lang/Object;)Z
      34: pop
      35: aload_0
      36: areturn

  public org.hl7.fhir.dstu3.model.Reference getEpisodeOfCareFirstRep();
    Code:
       0: aload_0
       1: invokevirtual #62                 // Method getEpisodeOfCare:()Ljava/util/List;
       4: invokeinterface #14,  1           // InterfaceMethod java/util/List.isEmpty:()Z
       9: ifeq          17
      12: aload_0
      13: invokevirtual #63                 // Method addEpisodeOfCare:()Lorg/hl7/fhir/dstu3/model/Reference;
      16: pop
      17: aload_0
      18: invokevirtual #62                 // Method getEpisodeOfCare:()Ljava/util/List;
      21: iconst_0
      22: invokeinterface #16,  2           // InterfaceMethod java/util/List.get:(I)Ljava/lang/Object;
      27: checkcast     #57                 // class org/hl7/fhir/dstu3/model/Reference
      30: areturn

  public java.util.List<org.hl7.fhir.dstu3.model.EpisodeOfCare> getEpisodeOfCareTarget();
    Code:
       0: aload_0
       1: getfield      #64                 // Field episodeOfCareTarget:Ljava/util/List;
       4: ifnonnull     18
       7: aload_0
       8: new           #4                  // class java/util/ArrayList
      11: dup
      12: invokespecial #5                  // Method java/util/ArrayList."<init>":()V
      15: putfield      #64                 // Field episodeOfCareTarget:Ljava/util/List;
      18: aload_0
      19: getfield      #64                 // Field episodeOfCareTarget:Ljava/util/List;
      22: areturn

  public org.hl7.fhir.dstu3.model.EpisodeOfCare addEpisodeOfCareTarget();
    Code:
       0: new           #65                 // class org/hl7/fhir/dstu3/model/EpisodeOfCare
       3: dup
       4: invokespecial #66                 // Method org/hl7/fhir/dstu3/model/EpisodeOfCare."<init>":()V
       7: astore_1
       8: aload_0
       9: getfield      #64                 // Field episodeOfCareTarget:Ljava/util/List;
      12: ifnonnull     26
      15: aload_0
      16: new           #4                  // class java/util/ArrayList
      19: dup
      20: invokespecial #5                  // Method java/util/ArrayList."<init>":()V
      23: putfield      #64                 // Field episodeOfCareTarget:Ljava/util/List;
      26: aload_0
      27: getfield      #64                 // Field episodeOfCareTarget:Ljava/util/List;
      30: aload_1
      31: invokeinterface #12,  2           // InterfaceMethod java/util/List.add:(Ljava/lang/Object;)Z
      36: pop
      37: aload_1
      38: areturn

  public java.util.List<org.hl7.fhir.dstu3.model.Reference> getIncomingReferral();
    Code:
       0: aload_0
       1: getfield      #67                 // Field incomingReferral:Ljava/util/List;
       4: ifnonnull     18
       7: aload_0
       8: new           #4                  // class java/util/ArrayList
      11: dup
      12: invokespecial #5                  // Method java/util/ArrayList."<init>":()V
      15: putfield      #67                 // Field incomingReferral:Ljava/util/List;
      18: aload_0
      19: getfield      #67                 // Field incomingReferral:Ljava/util/List;
      22: areturn

  public org.hl7.fhir.dstu3.model.Encounter setIncomingReferral(java.util.List<org.hl7.fhir.dstu3.model.Reference>);
    Code:
       0: aload_0
       1: aload_1
       2: putfield      #67                 // Field incomingReferral:Ljava/util/List;
       5: aload_0
       6: areturn

  public boolean hasIncomingReferral();
    Code:
       0: aload_0
       1: getfield      #67                 // Field incomingReferral:Ljava/util/List;
       4: ifnonnull     9
       7: iconst_0
       8: ireturn
       9: aload_0
      10: getfield      #67                 // Field incomingReferral:Ljava/util/List;
      13: invokeinterface #6,  1            // InterfaceMethod java/util/List.iterator:()Ljava/util/Iterator;
      18: astore_1
      19: aload_1
      20: invokeinterface #7,  1            // InterfaceMethod java/util/Iterator.hasNext:()Z
      25: ifeq          50
      28: aload_1
      29: invokeinterface #8,  1            // InterfaceMethod java/util/Iterator.next:()Ljava/lang/Object;
      34: checkcast     #57                 // class org/hl7/fhir/dstu3/model/Reference
      37: astore_2
      38: aload_2
      39: invokevirtual #59                 // Method org/hl7/fhir/dstu3/model/Reference.isEmpty:()Z
      42: ifne          47
      45: iconst_1
      46: ireturn
      47: goto          19
      50: iconst_0
      51: ireturn

  public org.hl7.fhir.dstu3.model.Reference addIncomingReferral();
    Code:
       0: new           #57                 // class org/hl7/fhir/dstu3/model/Reference
       3: dup
       4: invokespecial #58                 // Method org/hl7/fhir/dstu3/model/Reference."<init>":()V
       7: astore_1
       8: aload_0
       9: getfield      #67                 // Field incomingReferral:Ljava/util/List;
      12: ifnonnull     26
      15: aload_0
      16: new           #4                  // class java/util/ArrayList
      19: dup
      20: invokespecial #5                  // Method java/util/ArrayList."<init>":()V
      23: putfield      #67                 // Field incomingReferral:Ljava/util/List;
      26: aload_0
      27: getfield      #67                 // Field incomingReferral:Ljava/util/List;
      30: aload_1
      31: invokeinterface #12,  2           // InterfaceMethod java/util/List.add:(Ljava/lang/Object;)Z
      36: pop
      37: aload_1
      38: areturn

  public org.hl7.fhir.dstu3.model.Encounter addIncomingReferral(org.hl7.fhir.dstu3.model.Reference);
    Code:
       0: aload_1
       1: ifnonnull     6
       4: aload_0
       5: areturn
       6: aload_0
       7: getfield      #67                 // Field incomingReferral:Ljava/util/List;
      10: ifnonnull     24
      13: aload_0
      14: new           #4                  // class java/util/ArrayList
      17: dup
      18: invokespecial #5                  // Method java/util/ArrayList."<init>":()V
      21: putfield      #67                 // Field incomingReferral:Ljava/util/List;
      24: aload_0
      25: getfield      #67                 // Field incomingReferral:Ljava/util/List;
      28: aload_1
      29: invokeinterface #12,  2           // InterfaceMethod java/util/List.add:(Ljava/lang/Object;)Z
      34: pop
      35: aload_0
      36: areturn

  public org.hl7.fhir.dstu3.model.Reference getIncomingReferralFirstRep();
    Code:
       0: aload_0
       1: invokevirtual #68                 // Method getIncomingReferral:()Ljava/util/List;
       4: invokeinterface #14,  1           // InterfaceMethod java/util/List.isEmpty:()Z
       9: ifeq          17
      12: aload_0
      13: invokevirtual #69                 // Method addIncomingReferral:()Lorg/hl7/fhir/dstu3/model/Reference;
      16: pop
      17: aload_0
      18: invokevirtual #68                 // Method getIncomingReferral:()Ljava/util/List;
      21: iconst_0
      22: invokeinterface #16,  2           // InterfaceMethod java/util/List.get:(I)Ljava/lang/Object;
      27: checkcast     #57                 // class org/hl7/fhir/dstu3/model/Reference
      30: areturn

  public java.util.List<org.hl7.fhir.dstu3.model.ReferralRequest> getIncomingReferralTarget();
    Code:
       0: aload_0
       1: getfield      #70                 // Field incomingReferralTarget:Ljava/util/List;
       4: ifnonnull     18
       7: aload_0
       8: new           #4                  // class java/util/ArrayList
      11: dup
      12: invokespecial #5                  // Method java/util/ArrayList."<init>":()V
      15: putfield      #70                 // Field incomingReferralTarget:Ljava/util/List;
      18: aload_0
      19: getfield      #70                 // Field incomingReferralTarget:Ljava/util/List;
      22: areturn

  public org.hl7.fhir.dstu3.model.ReferralRequest addIncomingReferralTarget();
    Code:
       0: new           #71                 // class org/hl7/fhir/dstu3/model/ReferralRequest
       3: dup
       4: invokespecial #72                 // Method org/hl7/fhir/dstu3/model/ReferralRequest."<init>":()V
       7: astore_1
       8: aload_0
       9: getfield      #70                 // Field incomingReferralTarget:Ljava/util/List;
      12: ifnonnull     26
      15: aload_0
      16: new           #4                  // class java/util/ArrayList
      19: dup
      20: invokespecial #5                  // Method java/util/ArrayList."<init>":()V
      23: putfield      #70                 // Field incomingReferralTarget:Ljava/util/List;
      26: aload_0
      27: getfield      #70                 // Field incomingReferralTarget:Ljava/util/List;
      30: aload_1
      31: invokeinterface #12,  2           // InterfaceMethod java/util/List.add:(Ljava/lang/Object;)Z
      36: pop
      37: aload_1
      38: areturn

  public java.util.List<org.hl7.fhir.dstu3.model.Encounter$EncounterParticipantComponent> getParticipant();
    Code:
       0: aload_0
       1: getfield      #73                 // Field participant:Ljava/util/List;
       4: ifnonnull     18
       7: aload_0
       8: new           #4                  // class java/util/ArrayList
      11: dup
      12: invokespecial #5                  // Method java/util/ArrayList."<init>":()V
      15: putfield      #73                 // Field participant:Ljava/util/List;
      18: aload_0
      19: getfield      #73                 // Field participant:Ljava/util/List;
      22: areturn

  public org.hl7.fhir.dstu3.model.Encounter setParticipant(java.util.List<org.hl7.fhir.dstu3.model.Encounter$EncounterParticipantComponent>);
    Code:
       0: aload_0
       1: aload_1
       2: putfield      #73                 // Field participant:Ljava/util/List;
       5: aload_0
       6: areturn

  public boolean hasParticipant();
    Code:
       0: aload_0
       1: getfield      #73                 // Field participant:Ljava/util/List;
       4: ifnonnull     9
       7: iconst_0
       8: ireturn
       9: aload_0
      10: getfield      #73                 // Field participant:Ljava/util/List;
      13: invokeinterface #6,  1            // InterfaceMethod java/util/List.iterator:()Ljava/util/Iterator;
      18: astore_1
      19: aload_1
      20: invokeinterface #7,  1            // InterfaceMethod java/util/Iterator.hasNext:()Z
      25: ifeq          50
      28: aload_1
      29: invokeinterface #8,  1            // InterfaceMethod java/util/Iterator.next:()Ljava/lang/Object;
      34: checkcast     #74                 // class org/hl7/fhir/dstu3/model/Encounter$EncounterParticipantComponent
      37: astore_2
      38: aload_2
      39: invokevirtual #75                 // Method org/hl7/fhir/dstu3/model/Encounter$EncounterParticipantComponent.isEmpty:()Z
      42: ifne          47
      45: iconst_1
      46: ireturn
      47: goto          19
      50: iconst_0
      51: ireturn

  public org.hl7.fhir.dstu3.model.Encounter$EncounterParticipantComponent addParticipant();
    Code:
       0: new           #74                 // class org/hl7/fhir/dstu3/model/Encounter$EncounterParticipantComponent
       3: dup
       4: invokespecial #76                 // Method org/hl7/fhir/dstu3/model/Encounter$EncounterParticipantComponent."<init>":()V
       7: astore_1
       8: aload_0
       9: getfield      #73                 // Field participant:Ljava/util/List;
      12: ifnonnull     26
      15: aload_0
      16: new           #4                  // class java/util/ArrayList
      19: dup
      20: invokespecial #5                  // Method java/util/ArrayList."<init>":()V
      23: putfield      #73                 // Field participant:Ljava/util/List;
      26: aload_0
      27: getfield      #73                 // Field participant:Ljava/util/List;
      30: aload_1
      31: invokeinterface #12,  2           // InterfaceMethod java/util/List.add:(Ljava/lang/Object;)Z
      36: pop
      37: aload_1
      38: areturn

  public org.hl7.fhir.dstu3.model.Encounter addParticipant(org.hl7.fhir.dstu3.model.Encounter$EncounterParticipantComponent);
    Code:
       0: aload_1
       1: ifnonnull     6
       4: aload_0
       5: areturn
       6: aload_0
       7: getfield      #73                 // Field participant:Ljava/util/List;
      10: ifnonnull     24
      13: aload_0
      14: new           #4                  // class java/util/ArrayList
      17: dup
      18: invokespecial #5                  // Method java/util/ArrayList."<init>":()V
      21: putfield      #73                 // Field participant:Ljava/util/List;
      24: aload_0
      25: getfield      #73                 // Field participant:Ljava/util/List;
      28: aload_1
      29: invokeinterface #12,  2           // InterfaceMethod java/util/List.add:(Ljava/lang/Object;)Z
      34: pop
      35: aload_0
      36: areturn

  public org.hl7.fhir.dstu3.model.Encounter$EncounterParticipantComponent getParticipantFirstRep();
    Code:
       0: aload_0
       1: invokevirtual #77                 // Method getParticipant:()Ljava/util/List;
       4: invokeinterface #14,  1           // InterfaceMethod java/util/List.isEmpty:()Z
       9: ifeq          17
      12: aload_0
      13: invokevirtual #78                 // Method addParticipant:()Lorg/hl7/fhir/dstu3/model/Encounter$EncounterParticipantComponent;
      16: pop
      17: aload_0
      18: invokevirtual #77                 // Method getParticipant:()Ljava/util/List;
      21: iconst_0
      22: invokeinterface #16,  2           // InterfaceMethod java/util/List.get:(I)Ljava/lang/Object;
      27: checkcast     #74                 // class org/hl7/fhir/dstu3/model/Encounter$EncounterParticipantComponent
      30: areturn

  public org.hl7.fhir.dstu3.model.Reference getAppointment();
    Code:
       0: aload_0
       1: getfield      #79                 // Field appointment:Lorg/hl7/fhir/dstu3/model/Reference;
       4: ifnonnull     40
       7: invokestatic  #17                 // Method org/hl7/fhir/dstu3/model/Configuration.errorOnAutoCreate:()Z
      10: ifeq          23
      13: new           #18                 // class java/lang/Error
      16: dup
      17: ldc           #80                 // String Attempt to auto-create Encounter.appointment
      19: invokespecial #20                 // Method java/lang/Error."<init>":(Ljava/lang/String;)V
      22: athrow
      23: invokestatic  #21                 // Method org/hl7/fhir/dstu3/model/Configuration.doAutoCreate:()Z
      26: ifeq          40
      29: aload_0
      30: new           #57                 // class org/hl7/fhir/dstu3/model/Reference
      33: dup
      34: invokespecial #58                 // Method org/hl7/fhir/dstu3/model/Reference."<init>":()V
      37: putfield      #79                 // Field appointment:Lorg/hl7/fhir/dstu3/model/Reference;
      40: aload_0
      41: getfield      #79                 // Field appointment:Lorg/hl7/fhir/dstu3/model/Reference;
      44: areturn

  public boolean hasAppointment();
    Code:
       0: aload_0
       1: getfield      #79                 // Field appointment:Lorg/hl7/fhir/dstu3/model/Reference;
       4: ifnull        21
       7: aload_0
       8: getfield      #79                 // Field appointment:Lorg/hl7/fhir/dstu3/model/Reference;
      11: invokevirtual #59                 // Method org/hl7/fhir/dstu3/model/Reference.isEmpty:()Z
      14: ifne          21
      17: iconst_1
      18: goto          22
      21: iconst_0
      22: ireturn

  public org.hl7.fhir.dstu3.model.Encounter setAppointment(org.hl7.fhir.dstu3.model.Reference);
    Code:
       0: aload_0
       1: aload_1
       2: putfield      #79                 // Field appointment:Lorg/hl7/fhir/dstu3/model/Reference;
       5: aload_0
       6: areturn

  public org.hl7.fhir.dstu3.model.Appointment getAppointmentTarget();
    Code:
       0: aload_0
       1: getfield      #81                 // Field appointmentTarget:Lorg/hl7/fhir/dstu3/model/Appointment;
       4: ifnonnull     40
       7: invokestatic  #17                 // Method org/hl7/fhir/dstu3/model/Configuration.errorOnAutoCreate:()Z
      10: ifeq          23
      13: new           #18                 // class java/lang/Error
      16: dup
      17: ldc           #80                 // String Attempt to auto-create Encounter.appointment
      19: invokespecial #20                 // Method java/lang/Error."<init>":(Ljava/lang/String;)V
      22: athrow
      23: invokestatic  #21                 // Method org/hl7/fhir/dstu3/model/Configuration.doAutoCreate:()Z
      26: ifeq          40
      29: aload_0
      30: new           #82                 // class org/hl7/fhir/dstu3/model/Appointment
      33: dup
      34: invokespecial #83                 // Method org/hl7/fhir/dstu3/model/Appointment."<init>":()V
      37: putfield      #81                 // Field appointmentTarget:Lorg/hl7/fhir/dstu3/model/Appointment;
      40: aload_0
      41: getfield      #81                 // Field appointmentTarget:Lorg/hl7/fhir/dstu3/model/Appointment;
      44: areturn

  public org.hl7.fhir.dstu3.model.Encounter setAppointmentTarget(org.hl7.fhir.dstu3.model.Appointment);
    Code:
       0: aload_0
       1: aload_1
       2: putfield      #81                 // Field appointmentTarget:Lorg/hl7/fhir/dstu3/model/Appointment;
       5: aload_0
       6: areturn

  public org.hl7.fhir.dstu3.model.Period getPeriod();
    Code:
       0: aload_0
       1: getfield      #84                 // Field period:Lorg/hl7/fhir/dstu3/model/Period;
       4: ifnonnull     40
       7: invokestatic  #17                 // Method org/hl7/fhir/dstu3/model/Configuration.errorOnAutoCreate:()Z
      10: ifeq          23
      13: new           #18                 // class java/lang/Error
      16: dup
      17: ldc           #85                 // String Attempt to auto-create Encounter.period
      19: invokespecial #20                 // Method java/lang/Error."<init>":(Ljava/lang/String;)V
      22: athrow
      23: invokestatic  #21                 // Method org/hl7/fhir/dstu3/model/Configuration.doAutoCreate:()Z
      26: ifeq          40
      29: aload_0
      30: new           #86                 // class org/hl7/fhir/dstu3/model/Period
      33: dup
      34: invokespecial #87                 // Method org/hl7/fhir/dstu3/model/Period."<init>":()V
      37: putfield      #84                 // Field period:Lorg/hl7/fhir/dstu3/model/Period;
      40: aload_0
      41: getfield      #84                 // Field period:Lorg/hl7/fhir/dstu3/model/Period;
      44: areturn

  public boolean hasPeriod();
    Code:
       0: aload_0
       1: getfield      #84                 // Field period:Lorg/hl7/fhir/dstu3/model/Period;
       4: ifnull        21
       7: aload_0
       8: getfield      #84                 // Field period:Lorg/hl7/fhir/dstu3/model/Period;
      11: invokevirtual #88                 // Method org/hl7/fhir/dstu3/model/Period.isEmpty:()Z
      14: ifne          21
      17: iconst_1
      18: goto          22
      21: iconst_0
      22: ireturn

  public org.hl7.fhir.dstu3.model.Encounter setPeriod(org.hl7.fhir.dstu3.model.Period);
    Code:
       0: aload_0
       1: aload_1
       2: putfield      #84                 // Field period:Lorg/hl7/fhir/dstu3/model/Period;
       5: aload_0
       6: areturn

  public org.hl7.fhir.dstu3.model.Duration getLength();
    Code:
       0: aload_0
       1: getfield      #89                 // Field length:Lorg/hl7/fhir/dstu3/model/Duration;
       4: ifnonnull     40
       7: invokestatic  #17                 // Method org/hl7/fhir/dstu3/model/Configuration.errorOnAutoCreate:()Z
      10: ifeq          23
      13: new           #18                 // class java/lang/Error
      16: dup
      17: ldc           #90                 // String Attempt to auto-create Encounter.length
      19: invokespecial #20                 // Method java/lang/Error."<init>":(Ljava/lang/String;)V
      22: athrow
      23: invokestatic  #21                 // Method org/hl7/fhir/dstu3/model/Configuration.doAutoCreate:()Z
      26: ifeq          40
      29: aload_0
      30: new           #91                 // class org/hl7/fhir/dstu3/model/Duration
      33: dup
      34: invokespecial #92                 // Method org/hl7/fhir/dstu3/model/Duration."<init>":()V
      37: putfield      #89                 // Field length:Lorg/hl7/fhir/dstu3/model/Duration;
      40: aload_0
      41: getfield      #89                 // Field length:Lorg/hl7/fhir/dstu3/model/Duration;
      44: areturn

  public boolean hasLength();
    Code:
       0: aload_0
       1: getfield      #89                 // Field length:Lorg/hl7/fhir/dstu3/model/Duration;
       4: ifnull        21
       7: aload_0
       8: getfield      #89                 // Field length:Lorg/hl7/fhir/dstu3/model/Duration;
      11: invokevirtual #93                 // Method org/hl7/fhir/dstu3/model/Duration.isEmpty:()Z
      14: ifne          21
      17: iconst_1
      18: goto          22
      21: iconst_0
      22: ireturn

  public org.hl7.fhir.dstu3.model.Encounter setLength(org.hl7.fhir.dstu3.model.Duration);
    Code:
       0: aload_0
       1: aload_1
       2: putfield      #89                 // Field length:Lorg/hl7/fhir/dstu3/model/Duration;
       5: aload_0
       6: areturn

  public java.util.List<org.hl7.fhir.dstu3.model.CodeableConcept> getReason();
    Code:
       0: aload_0
       1: getfield      #94                 // Field reason:Ljava/util/List;
       4: ifnonnull     18
       7: aload_0
       8: new           #4                  // class java/util/ArrayList
      11: dup
      12: invokespecial #5                  // Method java/util/ArrayList."<init>":()V
      15: putfield      #94                 // Field reason:Ljava/util/List;
      18: aload_0
      19: getfield      #94                 // Field reason:Ljava/util/List;
      22: areturn

  public org.hl7.fhir.dstu3.model.Encounter setReason(java.util.List<org.hl7.fhir.dstu3.model.CodeableConcept>);
    Code:
       0: aload_0
       1: aload_1
       2: putfield      #94                 // Field reason:Ljava/util/List;
       5: aload_0
       6: areturn

  public boolean hasReason();
    Code:
       0: aload_0
       1: getfield      #94                 // Field reason:Ljava/util/List;
       4: ifnonnull     9
       7: iconst_0
       8: ireturn
       9: aload_0
      10: getfield      #94                 // Field reason:Ljava/util/List;
      13: invokeinterface #6,  1            // InterfaceMethod java/util/List.iterator:()Ljava/util/Iterator;
      18: astore_1
      19: aload_1
      20: invokeinterface #7,  1            // InterfaceMethod java/util/Iterator.hasNext:()Z
      25: ifeq          50
      28: aload_1
      29: invokeinterface #8,  1            // InterfaceMethod java/util/Iterator.next:()Ljava/lang/Object;
      34: checkcast     #48                 // class org/hl7/fhir/dstu3/model/CodeableConcept
      37: astore_2
      38: aload_2
      39: invokevirtual #49                 // Method org/hl7/fhir/dstu3/model/CodeableConcept.isEmpty:()Z
      42: ifne          47
      45: iconst_1
      46: ireturn
      47: goto          19
      50: iconst_0
      51: ireturn

  public org.hl7.fhir.dstu3.model.CodeableConcept addReason();
    Code:
       0: new           #48                 // class org/hl7/fhir/dstu3/model/CodeableConcept
       3: dup
       4: invokespecial #50                 // Method org/hl7/fhir/dstu3/model/CodeableConcept."<init>":()V
       7: astore_1
       8: aload_0
       9: getfield      #94                 // Field reason:Ljava/util/List;
      12: ifnonnull     26
      15: aload_0
      16: new           #4                  // class java/util/ArrayList
      19: dup
      20: invokespecial #5                  // Method java/util/ArrayList."<init>":()V
      23: putfield      #94                 // Field reason:Ljava/util/List;
      26: aload_0
      27: getfield      #94                 // Field reason:Ljava/util/List;
      30: aload_1
      31: invokeinterface #12,  2           // InterfaceMethod java/util/List.add:(Ljava/lang/Object;)Z
      36: pop
      37: aload_1
      38: areturn

  public org.hl7.fhir.dstu3.model.Encounter addReason(org.hl7.fhir.dstu3.model.CodeableConcept);
    Code:
       0: aload_1
       1: ifnonnull     6
       4: aload_0
       5: areturn
       6: aload_0
       7: getfield      #94                 // Field reason:Ljava/util/List;
      10: ifnonnull     24
      13: aload_0
      14: new           #4                  // class java/util/ArrayList
      17: dup
      18: invokespecial #5                  // Method java/util/ArrayList."<init>":()V
      21: putfield      #94                 // Field reason:Ljava/util/List;
      24: aload_0
      25: getfield      #94                 // Field reason:Ljava/util/List;
      28: aload_1
      29: invokeinterface #12,  2           // InterfaceMethod java/util/List.add:(Ljava/lang/Object;)Z
      34: pop
      35: aload_0
      36: areturn

  public org.hl7.fhir.dstu3.model.CodeableConcept getReasonFirstRep();
    Code:
       0: aload_0
       1: invokevirtual #95                 // Method getReason:()Ljava/util/List;
       4: invokeinterface #14,  1           // InterfaceMethod java/util/List.isEmpty:()Z
       9: ifeq          17
      12: aload_0
      13: invokevirtual #96                 // Method addReason:()Lorg/hl7/fhir/dstu3/model/CodeableConcept;
      16: pop
      17: aload_0
      18: invokevirtual #95                 // Method getReason:()Ljava/util/List;
      21: iconst_0
      22: invokeinterface #16,  2           // InterfaceMethod java/util/List.get:(I)Ljava/lang/Object;
      27: checkcast     #48                 // class org/hl7/fhir/dstu3/model/CodeableConcept
      30: areturn

  public java.util.List<org.hl7.fhir.dstu3.model.Encounter$DiagnosisComponent> getDiagnosis();
    Code:
       0: aload_0
       1: getfield      #97                 // Field diagnosis:Ljava/util/List;
       4: ifnonnull     18
       7: aload_0
       8: new           #4                  // class java/util/ArrayList
      11: dup
      12: invokespecial #5                  // Method java/util/ArrayList."<init>":()V
      15: putfield      #97                 // Field diagnosis:Ljava/util/List;
      18: aload_0
      19: getfield      #97                 // Field diagnosis:Ljava/util/List;
      22: areturn

  public org.hl7.fhir.dstu3.model.Encounter setDiagnosis(java.util.List<org.hl7.fhir.dstu3.model.Encounter$DiagnosisComponent>);
    Code:
       0: aload_0
       1: aload_1
       2: putfield      #97                 // Field diagnosis:Ljava/util/List;
       5: aload_0
       6: areturn

  public boolean hasDiagnosis();
    Code:
       0: aload_0
       1: getfield      #97                 // Field diagnosis:Ljava/util/List;
       4: ifnonnull     9
       7: iconst_0
       8: ireturn
       9: aload_0
      10: getfield      #97                 // Field diagnosis:Ljava/util/List;
      13: invokeinterface #6,  1            // InterfaceMethod java/util/List.iterator:()Ljava/util/Iterator;
      18: astore_1
      19: aload_1
      20: invokeinterface #7,  1            // InterfaceMethod java/util/Iterator.hasNext:()Z
      25: ifeq          50
      28: aload_1
      29: invokeinterface #8,  1            // InterfaceMethod java/util/Iterator.next:()Ljava/lang/Object;
      34: checkcast     #98                 // class org/hl7/fhir/dstu3/model/Encounter$DiagnosisComponent
      37: astore_2
      38: aload_2
      39: invokevirtual #99                 // Method org/hl7/fhir/dstu3/model/Encounter$DiagnosisComponent.isEmpty:()Z
      42: ifne          47
      45: iconst_1
      46: ireturn
      47: goto          19
      50: iconst_0
      51: ireturn

  public org.hl7.fhir.dstu3.model.Encounter$DiagnosisComponent addDiagnosis();
    Code:
       0: new           #98                 // class org/hl7/fhir/dstu3/model/Encounter$DiagnosisComponent
       3: dup
       4: invokespecial #100                // Method org/hl7/fhir/dstu3/model/Encounter$DiagnosisComponent."<init>":()V
       7: astore_1
       8: aload_0
       9: getfield      #97                 // Field diagnosis:Ljava/util/List;
      12: ifnonnull     26
      15: aload_0
      16: new           #4                  // class java/util/ArrayList
      19: dup
      20: invokespecial #5                  // Method java/util/ArrayList."<init>":()V
      23: putfield      #97                 // Field diagnosis:Ljava/util/List;
      26: aload_0
      27: getfield      #97                 // Field diagnosis:Ljava/util/List;
      30: aload_1
      31: invokeinterface #12,  2           // InterfaceMethod java/util/List.add:(Ljava/lang/Object;)Z
      36: pop
      37: aload_1
      38: areturn

  public org.hl7.fhir.dstu3.model.Encounter addDiagnosis(org.hl7.fhir.dstu3.model.Encounter$DiagnosisComponent);
    Code:
       0: aload_1
       1: ifnonnull     6
       4: aload_0
       5: areturn
       6: aload_0
       7: getfield      #97                 // Field diagnosis:Ljava/util/List;
      10: ifnonnull     24
      13: aload_0
      14: new           #4                  // class java/util/ArrayList
      17: dup
      18: invokespecial #5                  // Method java/util/ArrayList."<init>":()V
      21: putfield      #97                 // Field diagnosis:Ljava/util/List;
      24: aload_0
      25: getfield      #97                 // Field diagnosis:Ljava/util/List;
      28: aload_1
      29: invokeinterface #12,  2           // InterfaceMethod java/util/List.add:(Ljava/lang/Object;)Z
      34: pop
      35: aload_0
      36: areturn

  public org.hl7.fhir.dstu3.model.Encounter$DiagnosisComponent getDiagnosisFirstRep();
    Code:
       0: aload_0
       1: invokevirtual #101                // Method getDiagnosis:()Ljava/util/List;
       4: invokeinterface #14,  1           // InterfaceMethod java/util/List.isEmpty:()Z
       9: ifeq          17
      12: aload_0
      13: invokevirtual #102                // Method addDiagnosis:()Lorg/hl7/fhir/dstu3/model/Encounter$DiagnosisComponent;
      16: pop
      17: aload_0
      18: invokevirtual #101                // Method getDiagnosis:()Ljava/util/List;
      21: iconst_0
      22: invokeinterface #16,  2           // InterfaceMethod java/util/List.get:(I)Ljava/lang/Object;
      27: checkcast     #98                 // class org/hl7/fhir/dstu3/model/Encounter$DiagnosisComponent
      30: areturn

  public java.util.List<org.hl7.fhir.dstu3.model.Reference> getAccount();
    Code:
       0: aload_0
       1: getfield      #103                // Field account:Ljava/util/List;
       4: ifnonnull     18
       7: aload_0
       8: new           #4                  // class java/util/ArrayList
      11: dup
      12: invokespecial #5                  // Method java/util/ArrayList."<init>":()V
      15: putfield      #103                // Field account:Ljava/util/List;
      18: aload_0
      19: getfield      #103                // Field account:Ljava/util/List;
      22: areturn

  public org.hl7.fhir.dstu3.model.Encounter setAccount(java.util.List<org.hl7.fhir.dstu3.model.Reference>);
    Code:
       0: aload_0
       1: aload_1
       2: putfield      #103                // Field account:Ljava/util/List;
       5: aload_0
       6: areturn

  public boolean hasAccount();
    Code:
       0: aload_0
       1: getfield      #103                // Field account:Ljava/util/List;
       4: ifnonnull     9
       7: iconst_0
       8: ireturn
       9: aload_0
      10: getfield      #103                // Field account:Ljava/util/List;
      13: invokeinterface #6,  1            // InterfaceMethod java/util/List.iterator:()Ljava/util/Iterator;
      18: astore_1
      19: aload_1
      20: invokeinterface #7,  1            // InterfaceMethod java/util/Iterator.hasNext:()Z
      25: ifeq          50
      28: aload_1
      29: invokeinterface #8,  1            // InterfaceMethod java/util/Iterator.next:()Ljava/lang/Object;
      34: checkcast     #57                 // class org/hl7/fhir/dstu3/model/Reference
      37: astore_2
      38: aload_2
      39: invokevirtual #59                 // Method org/hl7/fhir/dstu3/model/Reference.isEmpty:()Z
      42: ifne          47
      45: iconst_1
      46: ireturn
      47: goto          19
      50: iconst_0
      51: ireturn

  public org.hl7.fhir.dstu3.model.Reference addAccount();
    Code:
       0: new           #57                 // class org/hl7/fhir/dstu3/model/Reference
       3: dup
       4: invokespecial #58                 // Method org/hl7/fhir/dstu3/model/Reference."<init>":()V
       7: astore_1
       8: aload_0
       9: getfield      #103                // Field account:Ljava/util/List;
      12: ifnonnull     26
      15: aload_0
      16: new           #4                  // class java/util/ArrayList
      19: dup
      20: invokespecial #5                  // Method java/util/ArrayList."<init>":()V
      23: putfield      #103                // Field account:Ljava/util/List;
      26: aload_0
      27: getfield      #103                // Field account:Ljava/util/List;
      30: aload_1
      31: invokeinterface #12,  2           // InterfaceMethod java/util/List.add:(Ljava/lang/Object;)Z
      36: pop
      37: aload_1
      38: areturn

  public org.hl7.fhir.dstu3.model.Encounter addAccount(org.hl7.fhir.dstu3.model.Reference);
    Code:
       0: aload_1
       1: ifnonnull     6
       4: aload_0
       5: areturn
       6: aload_0
       7: getfield      #103                // Field account:Ljava/util/List;
      10: ifnonnull     24
      13: aload_0
      14: new           #4                  // class java/util/ArrayList
      17: dup
      18: invokespecial #5                  // Method java/util/ArrayList."<init>":()V
      21: putfield      #103                // Field account:Ljava/util/List;
      24: aload_0
      25: getfield      #103                // Field account:Ljava/util/List;
      28: aload_1
      29: invokeinterface #12,  2           // InterfaceMethod java/util/List.add:(Ljava/lang/Object;)Z
      34: pop
      35: aload_0
      36: areturn

  public org.hl7.fhir.dstu3.model.Reference getAccountFirstRep();
    Code:
       0: aload_0
       1: invokevirtual #104                // Method getAccount:()Ljava/util/List;
       4: invokeinterface #14,  1           // InterfaceMethod java/util/List.isEmpty:()Z
       9: ifeq          17
      12: aload_0
      13: invokevirtual #105                // Method addAccount:()Lorg/hl7/fhir/dstu3/model/Reference;
      16: pop
      17: aload_0
      18: invokevirtual #104                // Method getAccount:()Ljava/util/List;
      21: iconst_0
      22: invokeinterface #16,  2           // InterfaceMethod java/util/List.get:(I)Ljava/lang/Object;
      27: checkcast     #57                 // class org/hl7/fhir/dstu3/model/Reference
      30: areturn

  public java.util.List<org.hl7.fhir.dstu3.model.Account> getAccountTarget();
    Code:
       0: aload_0
       1: getfield      #106                // Field accountTarget:Ljava/util/List;
       4: ifnonnull     18
       7: aload_0
       8: new           #4                  // class java/util/ArrayList
      11: dup
      12: invokespecial #5                  // Method java/util/ArrayList."<init>":()V
      15: putfield      #106                // Field accountTarget:Ljava/util/List;
      18: aload_0
      19: getfield      #106                // Field accountTarget:Ljava/util/List;
      22: areturn

  public org.hl7.fhir.dstu3.model.Account addAccountTarget();
    Code:
       0: new           #107                // class org/hl7/fhir/dstu3/model/Account
       3: dup
       4: invokespecial #108                // Method org/hl7/fhir/dstu3/model/Account."<init>":()V
       7: astore_1
       8: aload_0
       9: getfield      #106                // Field accountTarget:Ljava/util/List;
      12: ifnonnull     26
      15: aload_0
      16: new           #4                  // class java/util/ArrayList
      19: dup
      20: invokespecial #5                  // Method java/util/ArrayList."<init>":()V
      23: putfield      #106                // Field accountTarget:Ljava/util/List;
      26: aload_0
      27: getfield      #106                // Field accountTarget:Ljava/util/List;
      30: aload_1
      31: invokeinterface #12,  2           // InterfaceMethod java/util/List.add:(Ljava/lang/Object;)Z
      36: pop
      37: aload_1
      38: areturn

  public org.hl7.fhir.dstu3.model.Encounter$EncounterHospitalizationComponent getHospitalization();
    Code:
       0: aload_0
       1: getfield      #109                // Field hospitalization:Lorg/hl7/fhir/dstu3/model/Encounter$EncounterHospitalizationComponent;
       4: ifnonnull     40
       7: invokestatic  #17                 // Method org/hl7/fhir/dstu3/model/Configuration.errorOnAutoCreate:()Z
      10: ifeq          23
      13: new           #18                 // class java/lang/Error
      16: dup
      17: ldc           #110                // String Attempt to auto-create Encounter.hospitalization
      19: invokespecial #20                 // Method java/lang/Error."<init>":(Ljava/lang/String;)V
      22: athrow
      23: invokestatic  #21                 // Method org/hl7/fhir/dstu3/model/Configuration.doAutoCreate:()Z
      26: ifeq          40
      29: aload_0
      30: new           #111                // class org/hl7/fhir/dstu3/model/Encounter$EncounterHospitalizationComponent
      33: dup
      34: invokespecial #112                // Method org/hl7/fhir/dstu3/model/Encounter$EncounterHospitalizationComponent."<init>":()V
      37: putfield      #109                // Field hospitalization:Lorg/hl7/fhir/dstu3/model/Encounter$EncounterHospitalizationComponent;
      40: aload_0
      41: getfield      #109                // Field hospitalization:Lorg/hl7/fhir/dstu3/model/Encounter$EncounterHospitalizationComponent;
      44: areturn

  public boolean hasHospitalization();
    Code:
       0: aload_0
       1: getfield      #109                // Field hospitalization:Lorg/hl7/fhir/dstu3/model/Encounter$EncounterHospitalizationComponent;
       4: ifnull        21
       7: aload_0
       8: getfield      #109                // Field hospitalization:Lorg/hl7/fhir/dstu3/model/Encounter$EncounterHospitalizationComponent;
      11: invokevirtual #113                // Method org/hl7/fhir/dstu3/model/Encounter$EncounterHospitalizationComponent.isEmpty:()Z
      14: ifne          21
      17: iconst_1
      18: goto          22
      21: iconst_0
      22: ireturn

  public org.hl7.fhir.dstu3.model.Encounter setHospitalization(org.hl7.fhir.dstu3.model.Encounter$EncounterHospitalizationComponent);
    Code:
       0: aload_0
       1: aload_1
       2: putfield      #109                // Field hospitalization:Lorg/hl7/fhir/dstu3/model/Encounter$EncounterHospitalizationComponent;
       5: aload_0
       6: areturn

  public java.util.List<org.hl7.fhir.dstu3.model.Encounter$EncounterLocationComponent> getLocation();
    Code:
       0: aload_0
       1: getfield      #114                // Field location:Ljava/util/List;
       4: ifnonnull     18
       7: aload_0
       8: new           #4                  // class java/util/ArrayList
      11: dup
      12: invokespecial #5                  // Method java/util/ArrayList."<init>":()V
      15: putfield      #114                // Field location:Ljava/util/List;
      18: aload_0
      19: getfield      #114                // Field location:Ljava/util/List;
      22: areturn

  public org.hl7.fhir.dstu3.model.Encounter setLocation(java.util.List<org.hl7.fhir.dstu3.model.Encounter$EncounterLocationComponent>);
    Code:
       0: aload_0
       1: aload_1
       2: putfield      #114                // Field location:Ljava/util/List;
       5: aload_0
       6: areturn

  public boolean hasLocation();
    Code:
       0: aload_0
       1: getfield      #114                // Field location:Ljava/util/List;
       4: ifnonnull     9
       7: iconst_0
       8: ireturn
       9: aload_0
      10: getfield      #114                // Field location:Ljava/util/List;
      13: invokeinterface #6,  1            // InterfaceMethod java/util/List.iterator:()Ljava/util/Iterator;
      18: astore_1
      19: aload_1
      20: invokeinterface #7,  1            // InterfaceMethod java/util/Iterator.hasNext:()Z
      25: ifeq          50
      28: aload_1
      29: invokeinterface #8,  1            // InterfaceMethod java/util/Iterator.next:()Ljava/lang/Object;
      34: checkcast     #115                // class org/hl7/fhir/dstu3/model/Encounter$EncounterLocationComponent
      37: astore_2
      38: aload_2
      39: invokevirtual #116                // Method org/hl7/fhir/dstu3/model/Encounter$EncounterLocationComponent.isEmpty:()Z
      42: ifne          47
      45: iconst_1
      46: ireturn
      47: goto          19
      50: iconst_0
      51: ireturn

  public org.hl7.fhir.dstu3.model.Encounter$EncounterLocationComponent addLocation();
    Code:
       0: new           #115                // class org/hl7/fhir/dstu3/model/Encounter$EncounterLocationComponent
       3: dup
       4: invokespecial #117                // Method org/hl7/fhir/dstu3/model/Encounter$EncounterLocationComponent."<init>":()V
       7: astore_1
       8: aload_0
       9: getfield      #114                // Field location:Ljava/util/List;
      12: ifnonnull     26
      15: aload_0
      16: new           #4                  // class java/util/ArrayList
      19: dup
      20: invokespecial #5                  // Method java/util/ArrayList."<init>":()V
      23: putfield      #114                // Field location:Ljava/util/List;
      26: aload_0
      27: getfield      #114                // Field location:Ljava/util/List;
      30: aload_1
      31: invokeinterface #12,  2           // InterfaceMethod java/util/List.add:(Ljava/lang/Object;)Z
      36: pop
      37: aload_1
      38: areturn

  public org.hl7.fhir.dstu3.model.Encounter addLocation(org.hl7.fhir.dstu3.model.Encounter$EncounterLocationComponent);
    Code:
       0: aload_1
       1: ifnonnull     6
       4: aload_0
       5: areturn
       6: aload_0
       7: getfield      #114                // Field location:Ljava/util/List;
      10: ifnonnull     24
      13: aload_0
      14: new           #4                  // class java/util/ArrayList
      17: dup
      18: invokespecial #5                  // Method java/util/ArrayList."<init>":()V
      21: putfield      #114                // Field location:Ljava/util/List;
      24: aload_0
      25: getfield      #114                // Field location:Ljava/util/List;
      28: aload_1
      29: invokeinterface #12,  2           // InterfaceMethod java/util/List.add:(Ljava/lang/Object;)Z
      34: pop
      35: aload_0
      36: areturn

  public org.hl7.fhir.dstu3.model.Encounter$EncounterLocationComponent getLocationFirstRep();
    Code:
       0: aload_0
       1: invokevirtual #118                // Method getLocation:()Ljava/util/List;
       4: invokeinterface #14,  1           // InterfaceMethod java/util/List.isEmpty:()Z
       9: ifeq          17
      12: aload_0
      13: invokevirtual #119                // Method addLocation:()Lorg/hl7/fhir/dstu3/model/Encounter$EncounterLocationComponent;
      16: pop
      17: aload_0
      18: invokevirtual #118                // Method getLocation:()Ljava/util/List;
      21: iconst_0
      22: invokeinterface #16,  2           // InterfaceMethod java/util/List.get:(I)Ljava/lang/Object;
      27: checkcast     #115                // class org/hl7/fhir/dstu3/model/Encounter$EncounterLocationComponent
      30: areturn

  public org.hl7.fhir.dstu3.model.Reference getServiceProvider();
    Code:
       0: aload_0
       1: getfield      #120                // Field serviceProvider:Lorg/hl7/fhir/dstu3/model/Reference;
       4: ifnonnull     40
       7: invokestatic  #17                 // Method org/hl7/fhir/dstu3/model/Configuration.errorOnAutoCreate:()Z
      10: ifeq          23
      13: new           #18                 // class java/lang/Error
      16: dup
      17: ldc           #121                // String Attempt to auto-create Encounter.serviceProvider
      19: invokespecial #20                 // Method java/lang/Error."<init>":(Ljava/lang/String;)V
      22: athrow
      23: invokestatic  #21                 // Method org/hl7/fhir/dstu3/model/Configuration.doAutoCreate:()Z
      26: ifeq          40
      29: aload_0
      30: new           #57                 // class org/hl7/fhir/dstu3/model/Reference
      33: dup
      34: invokespecial #58                 // Method org/hl7/fhir/dstu3/model/Reference."<init>":()V
      37: putfield      #120                // Field serviceProvider:Lorg/hl7/fhir/dstu3/model/Reference;
      40: aload_0
      41: getfield      #120                // Field serviceProvider:Lorg/hl7/fhir/dstu3/model/Reference;
      44: areturn

  public boolean hasServiceProvider();
    Code:
       0: aload_0
       1: getfield      #120                // Field serviceProvider:Lorg/hl7/fhir/dstu3/model/Reference;
       4: ifnull        21
       7: aload_0
       8: getfield      #120                // Field serviceProvider:Lorg/hl7/fhir/dstu3/model/Reference;
      11: invokevirtual #59                 // Method org/hl7/fhir/dstu3/model/Reference.isEmpty:()Z
      14: ifne          21
      17: iconst_1
      18: goto          22
      21: iconst_0
      22: ireturn

  public org.hl7.fhir.dstu3.model.Encounter setServiceProvider(org.hl7.fhir.dstu3.model.Reference);
    Code:
       0: aload_0
       1: aload_1
       2: putfield      #120                // Field serviceProvider:Lorg/hl7/fhir/dstu3/model/Reference;
       5: aload_0
       6: areturn

  public org.hl7.fhir.dstu3.model.Organization getServiceProviderTarget();
    Code:
       0: aload_0
       1: getfield      #122                // Field serviceProviderTarget:Lorg/hl7/fhir/dstu3/model/Organization;
       4: ifnonnull     40
       7: invokestatic  #17                 // Method org/hl7/fhir/dstu3/model/Configuration.errorOnAutoCreate:()Z
      10: ifeq          23
      13: new           #18                 // class java/lang/Error
      16: dup
      17: ldc           #121                // String Attempt to auto-create Encounter.serviceProvider
      19: invokespecial #20                 // Method java/lang/Error."<init>":(Ljava/lang/String;)V
      22: athrow
      23: invokestatic  #21                 // Method org/hl7/fhir/dstu3/model/Configuration.doAutoCreate:()Z
      26: ifeq          40
      29: aload_0
      30: new           #123                // class org/hl7/fhir/dstu3/model/Organization
      33: dup
      34: invokespecial #124                // Method org/hl7/fhir/dstu3/model/Organization."<init>":()V
      37: putfield      #122                // Field serviceProviderTarget:Lorg/hl7/fhir/dstu3/model/Organization;
      40: aload_0
      41: getfield      #122                // Field serviceProviderTarget:Lorg/hl7/fhir/dstu3/model/Organization;
      44: areturn

  public org.hl7.fhir.dstu3.model.Encounter setServiceProviderTarget(org.hl7.fhir.dstu3.model.Organization);
    Code:
       0: aload_0
       1: aload_1
       2: putfield      #122                // Field serviceProviderTarget:Lorg/hl7/fhir/dstu3/model/Organization;
       5: aload_0
       6: areturn

  public org.hl7.fhir.dstu3.model.Reference getPartOf();
    Code:
       0: aload_0
       1: getfield      #125                // Field partOf:Lorg/hl7/fhir/dstu3/model/Reference;
       4: ifnonnull     40
       7: invokestatic  #17                 // Method org/hl7/fhir/dstu3/model/Configuration.errorOnAutoCreate:()Z
      10: ifeq          23
      13: new           #18                 // class java/lang/Error
      16: dup
      17: ldc           #126                // String Attempt to auto-create Encounter.partOf
      19: invokespecial #20                 // Method java/lang/Error."<init>":(Ljava/lang/String;)V
      22: athrow
      23: invokestatic  #21                 // Method org/hl7/fhir/dstu3/model/Configuration.doAutoCreate:()Z
      26: ifeq          40
      29: aload_0
      30: new           #57                 // class org/hl7/fhir/dstu3/model/Reference
      33: dup
      34: invokespecial #58                 // Method org/hl7/fhir/dstu3/model/Reference."<init>":()V
      37: putfield      #125                // Field partOf:Lorg/hl7/fhir/dstu3/model/Reference;
      40: aload_0
      41: getfield      #125                // Field partOf:Lorg/hl7/fhir/dstu3/model/Reference;
      44: areturn

  public boolean hasPartOf();
    Code:
       0: aload_0
       1: getfield      #125                // Field partOf:Lorg/hl7/fhir/dstu3/model/Reference;
       4: ifnull        21
       7: aload_0
       8: getfield      #125                // Field partOf:Lorg/hl7/fhir/dstu3/model/Reference;
      11: invokevirtual #59                 // Method org/hl7/fhir/dstu3/model/Reference.isEmpty:()Z
      14: ifne          21
      17: iconst_1
      18: goto          22
      21: iconst_0
      22: ireturn

  public org.hl7.fhir.dstu3.model.Encounter setPartOf(org.hl7.fhir.dstu3.model.Reference);
    Code:
       0: aload_0
       1: aload_1
       2: putfield      #125                // Field partOf:Lorg/hl7/fhir/dstu3/model/Reference;
       5: aload_0
       6: areturn

  public org.hl7.fhir.dstu3.model.Encounter getPartOfTarget();
    Code:
       0: aload_0
       1: getfield      #127                // Field partOfTarget:Lorg/hl7/fhir/dstu3/model/Encounter;
       4: ifnonnull     40
       7: invokestatic  #17                 // Method org/hl7/fhir/dstu3/model/Configuration.errorOnAutoCreate:()Z
      10: ifeq          23
      13: new           #18                 // class java/lang/Error
      16: dup
      17: ldc           #126                // String Attempt to auto-create Encounter.partOf
      19: invokespecial #20                 // Method java/lang/Error."<init>":(Ljava/lang/String;)V
      22: athrow
      23: invokestatic  #21                 // Method org/hl7/fhir/dstu3/model/Configuration.doAutoCreate:()Z
      26: ifeq          40
      29: aload_0
      30: new           #128                // class org/hl7/fhir/dstu3/model/Encounter
      33: dup
      34: invokespecial #129                // Method "<init>":()V
      37: putfield      #127                // Field partOfTarget:Lorg/hl7/fhir/dstu3/model/Encounter;
      40: aload_0
      41: getfield      #127                // Field partOfTarget:Lorg/hl7/fhir/dstu3/model/Encounter;
      44: areturn

  public org.hl7.fhir.dstu3.model.Encounter setPartOfTarget(org.hl7.fhir.dstu3.model.Encounter);
    Code:
       0: aload_0
       1: aload_1
       2: putfield      #127                // Field partOfTarget:Lorg/hl7/fhir/dstu3/model/Encounter;
       5: aload_0
       6: areturn

  protected void listChildren(java.util.List<org.hl7.fhir.dstu3.model.Property>);
    Code:
       0: aload_0
       1: aload_1
       2: invokespecial #130                // Method org/hl7/fhir/dstu3/model/DomainResource.listChildren:(Ljava/util/List;)V
       5: aload_1
       6: new           #131                // class org/hl7/fhir/dstu3/model/Property
       9: dup
      10: ldc           #132                // String identifier
      12: ldc           #133                // String Identifier
      14: ldc           #134                // String Identifier(s) by which this encounter is known.
      16: iconst_0
      17: ldc           #136                // int 2147483647
      19: aload_0
      20: getfield      #3                  // Field identifier:Ljava/util/List;
      23: invokespecial #137                // Method org/hl7/fhir/dstu3/model/Property."<init>":(Ljava/lang/String;Ljava/lang/String;Ljava/lang/String;IILjava/util/List;)V
      26: invokeinterface #12,  2           // InterfaceMethod java/util/List.add:(Ljava/lang/Object;)Z
      31: pop
      32: aload_1
      33: new           #131                // class org/hl7/fhir/dstu3/model/Property
      36: dup
      37: ldc           #138                // String status
      39: ldc           #139                // String code
      41: ldc           #140                // String planned | arrived | triaged | in-progress | onleave | finished | cancelled +.
      43: iconst_0
      44: iconst_1
      45: aload_0
      46: getfield      #2                  // Field status:Lorg/hl7/fhir/dstu3/model/Enumeration;
      49: invokespecial #141                // Method org/hl7/fhir/dstu3/model/Property."<init>":(Ljava/lang/String;Ljava/lang/String;Ljava/lang/String;IILorg/hl7/fhir/dstu3/model/Base;)V
      52: invokeinterface #12,  2           // InterfaceMethod java/util/List.add:(Ljava/lang/Object;)Z
      57: pop
      58: aload_1
      59: new           #131                // class org/hl7/fhir/dstu3/model/Property
      62: dup
      63: ldc           #142                // String statusHistory
      65: ldc           #143                // String
      67: ldc           #144                // String The status history permits the encounter resource to contain the status history without needing to read through the historical versions of the resource, or even have the server store them.
      69: iconst_0
      70: ldc           #136                // int 2147483647
      72: aload_0
      73: getfield      #30                 // Field statusHistory:Ljava/util/List;
      76: invokespecial #137                // Method org/hl7/fhir/dstu3/model/Property."<init>":(Ljava/lang/String;Ljava/lang/String;Ljava/lang/String;IILjava/util/List;)V
      79: invokeinterface #12,  2           // InterfaceMethod java/util/List.add:(Ljava/lang/Object;)Z
      84: pop
      85: aload_1
      86: new           #131                // class org/hl7/fhir/dstu3/model/Property
      89: dup
      90: ldc           #145                // String class
      92: ldc           #146                // String Coding
      94: ldc           #147                // String inpatient | outpatient | ambulatory | emergency +.
      96: iconst_0
      97: iconst_1
      98: aload_0
      99: getfield      #36                 // Field class_:Lorg/hl7/fhir/dstu3/model/Coding;
     102: invokespecial #141                // Method org/hl7/fhir/dstu3/model/Property."<init>":(Ljava/lang/String;Ljava/lang/String;Ljava/lang/String;IILorg/hl7/fhir/dstu3/model/Base;)V
     105: invokeinterface #12,  2           // InterfaceMethod java/util/List.add:(Ljava/lang/Object;)Z
     110: pop
     111: aload_1
     112: new           #131                // class org/hl7/fhir/dstu3/model/Property
     115: dup
     116: ldc           #148                // String classHistory
     118: ldc           #143                // String
     120: ldc           #149                // String The class history permits the tracking of the encounters transitions without needing to go  through the resource history.\n\nThis would be used for a case where an admission starts of as an emergency encounter, then transisions into an inpatient scenario. Doing this and not restarting a new encounter ensures that any lab/diagnostic results can more easily follow the patient and not require re-processing and not get lost or cancelled during a kindof discharge from emergency to inpatient.
     122: iconst_0
     123: ldc           #136                // int 2147483647
     125: aload_0
     126: getfield      #41                 // Field classHistory:Ljava/util/List;
     129: invokespecial #137                // Method org/hl7/fhir/dstu3/model/Property."<init>":(Ljava/lang/String;Ljava/lang/String;Ljava/lang/String;IILjava/util/List;)V
     132: invokeinterface #12,  2           // InterfaceMethod java/util/List.add:(Ljava/lang/Object;)Z
     137: pop
     138: aload_1
     139: new           #131                // class org/hl7/fhir/dstu3/model/Property
     142: dup
     143: ldc           #150                // String type
     145: ldc           #151                // String CodeableConcept
     147: ldc           #152                // String Specific type of encounter (e.g. e-mail consultation, surgical day-care, skilled nursing, rehabilitation).
     149: iconst_0
     150: ldc           #136                // int 2147483647
     152: aload_0
     153: getfield      #47                 // Field type:Ljava/util/List;
     156: invokespecial #137                // Method org/hl7/fhir/dstu3/model/Property."<init>":(Ljava/lang/String;Ljava/lang/String;Ljava/lang/String;IILjava/util/List;)V
     159: invokeinterface #12,  2           // InterfaceMethod java/util/List.add:(Ljava/lang/Object;)Z
     164: pop
     165: aload_1
     166: new           #131                // class org/hl7/fhir/dstu3/model/Property
     169: dup
     170: ldc           #153                // String priority
     172: ldc           #151                // String CodeableConcept
     174: ldc           #154                // String Indicates the urgency of the encounter.
     176: iconst_0
     177: iconst_1
     178: aload_0
     179: getfield      #53                 // Field priority:Lorg/hl7/fhir/dstu3/model/CodeableConcept;
     182: invokespecial #141                // Method org/hl7/fhir/dstu3/model/Property."<init>":(Ljava/lang/String;Ljava/lang/String;Ljava/lang/String;IILorg/hl7/fhir/dstu3/model/Base;)V
     185: invokeinterface #12,  2           // InterfaceMethod java/util/List.add:(Ljava/lang/Object;)Z
     190: pop
     191: aload_1
     192: new           #131                // class org/hl7/fhir/dstu3/model/Property
     195: dup
     196: ldc           #155                // String subject
     198: ldc           #156                // String Reference(Patient|Group)
     200: ldc           #157                // String The patient ro group present at the encounter.
     202: iconst_0
     203: iconst_1
     204: aload_0
     205: getfield      #55                 // Field subject:Lorg/hl7/fhir/dstu3/model/Reference;
     208: invokespecial #141                // Method org/hl7/fhir/dstu3/model/Property."<init>":(Ljava/lang/String;Ljava/lang/String;Ljava/lang/String;IILorg/hl7/fhir/dstu3/model/Base;)V
     211: invokeinterface #12,  2           // InterfaceMethod java/util/List.add:(Ljava/lang/Object;)Z
     216: pop
     217: aload_1
     218: new           #131                // class org/hl7/fhir/dstu3/model/Property
     221: dup
     222: ldc           #158                // String episodeOfCare
     224: ldc           #159                // String Reference(EpisodeOfCare)
     226: ldc           #160                // String Where a specific encounter should be classified as a part of a specific episode(s) of care this field should be used. This association can facilitate grouping of related encounters together for a specific purpose, such as government reporting, issue tracking, association via a common problem.  The association is recorded on the encounter as these are typically created after the episode of care, and grouped on entry rather than editing the episode of care to append another encounter to it (the episode of care could span years).
     228: iconst_0
     229: ldc           #136                // int 2147483647
     231: aload_0
     232: getfield      #61                 // Field episodeOfCare:Ljava/util/List;
     235: invokespecial #137                // Method org/hl7/fhir/dstu3/model/Property."<init>":(Ljava/lang/String;Ljava/lang/String;Ljava/lang/String;IILjava/util/List;)V
     238: invokeinterface #12,  2           // InterfaceMethod java/util/List.add:(Ljava/lang/Object;)Z
     243: pop
     244: aload_1
     245: new           #131                // class org/hl7/fhir/dstu3/model/Property
     248: dup
     249: ldc           #161                // String incomingReferral
     251: ldc           #162                // String Reference(ReferralRequest)
     253: ldc           #163                // String The referral request this encounter satisfies (incoming referral).
     255: iconst_0
     256: ldc           #136                // int 2147483647
     258: aload_0
     259: getfield      #67                 // Field incomingReferral:Ljava/util/List;
     262: invokespecial #137                // Method org/hl7/fhir/dstu3/model/Property."<init>":(Ljava/lang/String;Ljava/lang/String;Ljava/lang/String;IILjava/util/List;)V
     265: invokeinterface #12,  2           // InterfaceMethod java/util/List.add:(Ljava/lang/Object;)Z
     270: pop
     271: aload_1
     272: new           #131                // class org/hl7/fhir/dstu3/model/Property
     275: dup
     276: ldc           #164                // String participant
     278: ldc           #143                // String
     280: ldc           #165                // String Thelist ofpeopleresponsible for providing the service.
     282: iconst_0
     283: ldc           #136                // int 2147483647
     285: aload_0
     286: getfield      #73                 // Field participant:Ljava/util/List;
     289: invokespecial #137                // Method org/hl7/fhir/dstu3/model/Property."<init>":(Ljava/lang/String;Ljava/lang/String;Ljava/lang/String;IILjava/util/List;)V
     292: invokeinterface #12,  2           // InterfaceMethod java/util/List.add:(Ljava/lang/Object;)Z
     297: pop
     298: aload_1
     299: new           #131                // class org/hl7/fhir/dstu3/model/Property
     302: dup
     303: ldc           #166                // String appointment
     305: ldc           #167                // String Reference(Appointment)
     307: ldc           #168                // String The appointment that scheduled this encounter.
     309: iconst_0
     310: iconst_1
     311: aload_0
     312: getfield      #79                 // Field appointment:Lorg/hl7/fhir/dstu3/model/Reference;
     315: invokespecial #141                // Method org/hl7/fhir/dstu3/model/Property."<init>":(Ljava/lang/String;Ljava/lang/String;Ljava/lang/String;IILorg/hl7/fhir/dstu3/model/Base;)V
     318: invokeinterface #12,  2           // InterfaceMethod java/util/List.add:(Ljava/lang/Object;)Z
     323: pop
     324: aload_1
     325: new           #131                // class org/hl7/fhir/dstu3/model/Property
     328: dup
     329: ldc           #169                // String period
     331: ldc           #170                // String Period
     333: ldc           #171                // String The start and end time of the encounter.
     335: iconst_0
     336: iconst_1
     337: aload_0
     338: getfield      #84                 // Field period:Lorg/hl7/fhir/dstu3/model/Period;
     341: invokespecial #141                // Method org/hl7/fhir/dstu3/model/Property."<init>":(Ljava/lang/String;Ljava/lang/String;Ljava/lang/String;IILorg/hl7/fhir/dstu3/model/Base;)V
     344: invokeinterface #12,  2           // InterfaceMethod java/util/List.add:(Ljava/lang/Object;)Z
     349: pop
     350: aload_1
     351: new           #131                // class org/hl7/fhir/dstu3/model/Property
     354: dup
     355: ldc           #172                // String length
     357: ldc           #173                // String Duration
     359: ldc           #174                // String Quantity of time the encounter lasted. This excludes the time during leaves of absence.
     361: iconst_0
     362: iconst_1
     363: aload_0
     364: getfield      #89                 // Field length:Lorg/hl7/fhir/dstu3/model/Duration;
     367: invokespecial #141                // Method org/hl7/fhir/dstu3/model/Property."<init>":(Ljava/lang/String;Ljava/lang/String;Ljava/lang/String;IILorg/hl7/fhir/dstu3/model/Base;)V
     370: invokeinterface #12,  2           // InterfaceMethod java/util/List.add:(Ljava/lang/Object;)Z
     375: pop
     376: aload_1
     377: new           #131                // class org/hl7/fhir/dstu3/model/Property
     380: dup
     381: ldc           #175                // String reason
     383: ldc           #151                // String CodeableConcept
     385: ldc           #176                // String Reason the encounter takes place, expressed as a code. For admissions, this can be used for a coded admission diagnosis.
     387: iconst_0
     388: ldc           #136                // int 2147483647
     390: aload_0
     391: getfield      #94                 // Field reason:Ljava/util/List;
     394: invokespecial #137                // Method org/hl7/fhir/dstu3/model/Property."<init>":(Ljava/lang/String;Ljava/lang/String;Ljava/lang/String;IILjava/util/List;)V
     397: invokeinterface #12,  2           // InterfaceMethod java/util/List.add:(Ljava/lang/Object;)Z
     402: pop
     403: aload_1
     404: new           #131                // class org/hl7/fhir/dstu3/model/Property
     407: dup
     408: ldc           #177                // String diagnosis
     410: ldc           #143                // String
     412: ldc           #178                // String The list of diagnosis relevant to this encounter.
     414: iconst_0
     415: ldc           #136                // int 2147483647
     417: aload_0
     418: getfield      #97                 // Field diagnosis:Ljava/util/List;
     421: invokespecial #137                // Method org/hl7/fhir/dstu3/model/Property."<init>":(Ljava/lang/String;Ljava/lang/String;Ljava/lang/String;IILjava/util/List;)V
     424: invokeinterface #12,  2           // InterfaceMethod java/util/List.add:(Ljava/lang/Object;)Z
     429: pop
     430: aload_1
     431: new           #131                // class org/hl7/fhir/dstu3/model/Property
     434: dup
     435: ldc           #179                // String account
     437: ldc           #180                // String Reference(Account)
     439: ldc           #181                // String The set of accounts that may be used for billing for this Encounter.
     441: iconst_0
     442: ldc           #136                // int 2147483647
     444: aload_0
     445: getfield      #103                // Field account:Ljava/util/List;
     448: invokespecial #137                // Method org/hl7/fhir/dstu3/model/Property."<init>":(Ljava/lang/String;Ljava/lang/String;Ljava/lang/String;IILjava/util/List;)V
     451: invokeinterface #12,  2           // InterfaceMethod java/util/List.add:(Ljava/lang/Object;)Z
     456: pop
     457: aload_1
     458: new           #131                // class org/hl7/fhir/dstu3/model/Property
     461: dup
     462: ldc           #182                // String hospitalization
     464: ldc           #143                // String
     466: ldc           #183                // String Details about the admission to a healthcare service.
     468: iconst_0
     469: iconst_1
     470: aload_0
     471: getfield      #109                // Field hospitalization:Lorg/hl7/fhir/dstu3/model/Encounter$EncounterHospitalizationComponent;
     474: invokespecial #141                // Method org/hl7/fhir/dstu3/model/Property."<init>":(Ljava/lang/String;Ljava/lang/String;Ljava/lang/String;IILorg/hl7/fhir/dstu3/model/Base;)V
     477: invokeinterface #12,  2           // InterfaceMethod java/util/List.add:(Ljava/lang/Object;)Z
     482: pop
     483: aload_1
     484: new           #131                // class org/hl7/fhir/dstu3/model/Property
     487: dup
     488: ldc           #184                // String location
     490: ldc           #143                // String
     492: ldc           #185                // String List of locations where  the patient has been during this encounter.
     494: iconst_0
     495: ldc           #136                // int 2147483647
     497: aload_0
     498: getfield      #114                // Field location:Ljava/util/List;
     501: invokespecial #137                // Method org/hl7/fhir/dstu3/model/Property."<init>":(Ljava/lang/String;Ljava/lang/String;Ljava/lang/String;IILjava/util/List;)V
     504: invokeinterface #12,  2           // InterfaceMethod java/util/List.add:(Ljava/lang/Object;)Z
     509: pop
     510: aload_1
     511: new           #131                // class org/hl7/fhir/dstu3/model/Property
     514: dup
     515: ldc           #186                // String serviceProvider
     517: ldc           #187                // String Reference(Organization)
     519: ldc           #188                // String An organization that is in charge of maintaining the information of this Encounter (e.g. who maintains the report or the master service catalog item, etc.). This MAY be the same as the organization on the Patient record, however it could be different. This MAY not be not the Service Delivery Location\'s Organization.
     521: iconst_0
     522: iconst_1
     523: aload_0
     524: getfield      #120                // Field serviceProvider:Lorg/hl7/fhir/dstu3/model/Reference;
     527: invokespecial #141                // Method org/hl7/fhir/dstu3/model/Property."<init>":(Ljava/lang/String;Ljava/lang/String;Ljava/lang/String;IILorg/hl7/fhir/dstu3/model/Base;)V
     530: invokeinterface #12,  2           // InterfaceMethod java/util/List.add:(Ljava/lang/Object;)Z
     535: pop
     536: aload_1
     537: new           #131                // class org/hl7/fhir/dstu3/model/Property
     540: dup
     541: ldc           #189                // String partOf
     543: ldc           #190                // String Reference(Encounter)
     545: ldc           #191                // String Another Encounter of which this encounter is a part of (administratively or in time).
     547: iconst_0
     548: iconst_1
     549: aload_0
     550: getfield      #125                // Field partOf:Lorg/hl7/fhir/dstu3/model/Reference;
     553: invokespecial #141                // Method org/hl7/fhir/dstu3/model/Property."<init>":(Ljava/lang/String;Ljava/lang/String;Ljava/lang/String;IILorg/hl7/fhir/dstu3/model/Base;)V
     556: invokeinterface #12,  2           // InterfaceMethod java/util/List.add:(Ljava/lang/Object;)Z
     561: pop
     562: return

  public org.hl7.fhir.dstu3.model.Property getNamedProperty(int, java.lang.String, boolean) throws org.hl7.fhir.exceptions.FHIRException;
    Code:
       0: iload_1
       1: lookupswitch  { // 21
           -1892140189: 344
           -1867885268: 324
           -1618432855: 180
           -1474995297: 407
           -1258204701: 365
           -1177318867: 509
           -1165461084: 304
           -1106363674: 447
            -995410646: 591
            -991726143: 427
            -986695614: 221
            -934964668: 467
            -892481550: 201
               3575610: 283
              94742904: 242
             243182534: 571
             767422259: 386
             962575356: 262
            1057894634: 530
            1196993265: 488
            1901043637: 550
               default: 611
          }
     180: new           #131                // class org/hl7/fhir/dstu3/model/Property
     183: dup
     184: ldc           #132                // String identifier
     186: ldc           #133                // String Identifier
     188: ldc           #134                // String Identifier(s) by which this encounter is known.
     190: iconst_0
     191: ldc           #136                // int 2147483647
     193: aload_0
     194: getfield      #3                  // Field identifier:Ljava/util/List;
     197: invokespecial #137                // Method org/hl7/fhir/dstu3/model/Property."<init>":(Ljava/lang/String;Ljava/lang/String;Ljava/lang/String;IILjava/util/List;)V
     200: areturn
     201: new           #131                // class org/hl7/fhir/dstu3/model/Property
     204: dup
     205: ldc           #138                // String status
     207: ldc           #139                // String code
     209: ldc           #140                // String planned | arrived | triaged | in-progress | onleave | finished | cancelled +.
     211: iconst_0
     212: iconst_1
     213: aload_0
     214: getfield      #2                  // Field status:Lorg/hl7/fhir/dstu3/model/Enumeration;
     217: invokespecial #141                // Method org/hl7/fhir/dstu3/model/Property."<init>":(Ljava/lang/String;Ljava/lang/String;Ljava/lang/String;IILorg/hl7/fhir/dstu3/model/Base;)V
     220: areturn
     221: new           #131                // class org/hl7/fhir/dstu3/model/Property
     224: dup
     225: ldc           #142                // String statusHistory
     227: ldc           #143                // String
     229: ldc           #144                // String The status history permits the encounter resource to contain the status history without needing to read through the historical versions of the resource, or even have the server store them.
     231: iconst_0
     232: ldc           #136                // int 2147483647
     234: aload_0
     235: getfield      #30                 // Field statusHistory:Ljava/util/List;
     238: invokespecial #137                // Method org/hl7/fhir/dstu3/model/Property."<init>":(Ljava/lang/String;Ljava/lang/String;Ljava/lang/String;IILjava/util/List;)V
     241: areturn
     242: new           #131                // class org/hl7/fhir/dstu3/model/Property
     245: dup
     246: ldc           #145                // String class
     248: ldc           #146                // String Coding
     250: ldc           #147                // String inpatient | outpatient | ambulatory | emergency +.
     252: iconst_0
     253: iconst_1
     254: aload_0
     255: getfield      #36                 // Field class_:Lorg/hl7/fhir/dstu3/model/Coding;
     258: invokespecial #141                // Method org/hl7/fhir/dstu3/model/Property."<init>":(Ljava/lang/String;Ljava/lang/String;Ljava/lang/String;IILorg/hl7/fhir/dstu3/model/Base;)V
     261: areturn
     262: new           #131                // class org/hl7/fhir/dstu3/model/Property
     265: dup
     266: ldc           #148                // String classHistory
     268: ldc           #143                // String
     270: ldc           #149                // String The class history permits the tracking of the encounters transitions without needing to go  through the resource history.\n\nThis would be used for a case where an admission starts of as an emergency encounter, then transisions into an inpatient scenario. Doing this and not restarting a new encounter ensures that any lab/diagnostic results can more easily follow the patient and not require re-processing and not get lost or cancelled during a kindof discharge from emergency to inpatient.
     272: iconst_0
     273: ldc           #136                // int 2147483647
     275: aload_0
     276: getfield      #41                 // Field classHistory:Ljava/util/List;
     279: invokespecial #137                // Method org/hl7/fhir/dstu3/model/Property."<init>":(Ljava/lang/String;Ljava/lang/String;Ljava/lang/String;IILjava/util/List;)V
     282: areturn
     283: new           #131                // class org/hl7/fhir/dstu3/model/Property
     286: dup
     287: ldc           #150                // String type
     289: ldc           #151                // String CodeableConcept
     291: ldc           #152                // String Specific type of encounter (e.g. e-mail consultation, surgical day-care, skilled nursing, rehabilitation).
     293: iconst_0
     294: ldc           #136                // int 2147483647
     296: aload_0
     297: getfield      #47                 // Field type:Ljava/util/List;
     300: invokespecial #137                // Method org/hl7/fhir/dstu3/model/Property."<init>":(Ljava/lang/String;Ljava/lang/String;Ljava/lang/String;IILjava/util/List;)V
     303: areturn
     304: new           #131                // class org/hl7/fhir/dstu3/model/Property
     307: dup
     308: ldc           #153                // String priority
     310: ldc           #151                // String CodeableConcept
     312: ldc           #154                // String Indicates the urgency of the encounter.
     314: iconst_0
     315: iconst_1
     316: aload_0
     317: getfield      #53                 // Field priority:Lorg/hl7/fhir/dstu3/model/CodeableConcept;
     320: invokespecial #141                // Method org/hl7/fhir/dstu3/model/Property."<init>":(Ljava/lang/String;Ljava/lang/String;Ljava/lang/String;IILorg/hl7/fhir/dstu3/model/Base;)V
     323: areturn
     324: new           #131                // class org/hl7/fhir/dstu3/model/Property
     327: dup
     328: ldc           #155                // String subject
     330: ldc           #156                // String Reference(Patient|Group)
     332: ldc           #157                // String The patient ro group present at the encounter.
     334: iconst_0
     335: iconst_1
     336: aload_0
     337: getfield      #55                 // Field subject:Lorg/hl7/fhir/dstu3/model/Reference;
     340: invokespecial #141                // Method org/hl7/fhir/dstu3/model/Property."<init>":(Ljava/lang/String;Ljava/lang/String;Ljava/lang/String;IILorg/hl7/fhir/dstu3/model/Base;)V
     343: areturn
     344: new           #131                // class org/hl7/fhir/dstu3/model/Property
     347: dup
     348: ldc           #158                // String episodeOfCare
     350: ldc           #159                // String Reference(EpisodeOfCare)
     352: ldc           #160                // String Where a specific encounter should be classified as a part of a specific episode(s) of care this field should be used. This association can facilitate grouping of related encounters together for a specific purpose, such as government reporting, issue tracking, association via a common problem.  The association is recorded on the encounter as these are typically created after the episode of care, and grouped on entry rather than editing the episode of care to append another encounter to it (the episode of care could span years).
     354: iconst_0
     355: ldc           #136                // int 2147483647
     357: aload_0
     358: getfield      #61                 // Field episodeOfCare:Ljava/util/List;
     361: invokespecial #137                // Method org/hl7/fhir/dstu3/model/Property."<init>":(Ljava/lang/String;Ljava/lang/String;Ljava/lang/String;IILjava/util/List;)V
     364: areturn
     365: new           #131                // class org/hl7/fhir/dstu3/model/Property
     368: dup
     369: ldc           #161                // String incomingReferral
     371: ldc           #162                // String Reference(ReferralRequest)
     373: ldc           #163                // String The referral request this encounter satisfies (incoming referral).
     375: iconst_0
     376: ldc           #136                // int 2147483647
     378: aload_0
     379: getfield      #67                 // Field incomingReferral:Ljava/util/List;
     382: invokespecial #137                // Method org/hl7/fhir/dstu3/model/Property."<init>":(Ljava/lang/String;Ljava/lang/String;Ljava/lang/String;IILjava/util/List;)V
     385: areturn
     386: new           #131                // class org/hl7/fhir/dstu3/model/Property
     389: dup
     390: ldc           #164                // String participant
     392: ldc           #143                // String
     394: ldc           #165                // String Thelist ofpeopleresponsible for providing the service.
     396: iconst_0
     397: ldc           #136                // int 2147483647
     399: aload_0
     400: getfield      #73                 // Field participant:Ljava/util/List;
     403: invokespecial #137                // Method org/hl7/fhir/dstu3/model/Property."<init>":(Ljava/lang/String;Ljava/lang/String;Ljava/lang/String;IILjava/util/List;)V
     406: areturn
     407: new           #131                // class org/hl7/fhir/dstu3/model/Property
     410: dup
     411: ldc           #166                // String appointment
     413: ldc           #167                // String Reference(Appointment)
     415: ldc           #168                // String The appointment that scheduled this encounter.
     417: iconst_0
     418: iconst_1
     419: aload_0
     420: getfield      #79                 // Field appointment:Lorg/hl7/fhir/dstu3/model/Reference;
     423: invokespecial #141                // Method org/hl7/fhir/dstu3/model/Property."<init>":(Ljava/lang/String;Ljava/lang/String;Ljava/lang/String;IILorg/hl7/fhir/dstu3/model/Base;)V
     426: areturn
     427: new           #131                // class org/hl7/fhir/dstu3/model/Property
     430: dup
     431: ldc           #169                // String period
     433: ldc           #170                // String Period
     435: ldc           #171                // String The start and end time of the encounter.
     437: iconst_0
     438: iconst_1
     439: aload_0
     440: getfield      #84                 // Field period:Lorg/hl7/fhir/dstu3/model/Period;
     443: invokespecial #141                // Method org/hl7/fhir/dstu3/model/Property."<init>":(Ljava/lang/String;Ljava/lang/String;Ljava/lang/String;IILorg/hl7/fhir/dstu3/model/Base;)V
     446: areturn
     447: new           #131                // class org/hl7/fhir/dstu3/model/Property
     450: dup
     451: ldc           #172                // String length
     453: ldc           #173                // String Duration
     455: ldc           #174                // String Quantity of time the encounter lasted. This excludes the time during leaves of absence.
     457: iconst_0
     458: iconst_1
     459: aload_0
     460: getfield      #89                 // Field length:Lorg/hl7/fhir/dstu3/model/Duration;
     463: invokespecial #141                // Method org/hl7/fhir/dstu3/model/Property."<init>":(Ljava/lang/String;Ljava/lang/String;Ljava/lang/String;IILorg/hl7/fhir/dstu3/model/Base;)V
     466: areturn
     467: new           #131                // class org/hl7/fhir/dstu3/model/Property
     470: dup
     471: ldc           #175                // String reason
     473: ldc           #151                // String CodeableConcept
     475: ldc           #176                // String Reason the encounter takes place, expressed as a code. For admissions, this can be used for a coded admission diagnosis.
     477: iconst_0
     478: ldc           #136                // int 2147483647
     480: aload_0
     481: getfield      #94                 // Field reason:Ljava/util/List;
     484: invokespecial #137                // Method org/hl7/fhir/dstu3/model/Property."<init>":(Ljava/lang/String;Ljava/lang/String;Ljava/lang/String;IILjava/util/List;)V
     487: areturn
     488: new           #131                // class org/hl7/fhir/dstu3/model/Property
     491: dup
     492: ldc           #177                // String diagnosis
     494: ldc           #143                // String
     496: ldc           #178                // String The list of diagnosis relevant to this encounter.
     498: iconst_0
     499: ldc           #136                // int 2147483647
     501: aload_0
     502: getfield      #97                 // Field diagnosis:Ljava/util/List;
     505: invokespecial #137                // Method org/hl7/fhir/dstu3/model/Property."<init>":(Ljava/lang/String;Ljava/lang/String;Ljava/lang/String;IILjava/util/List;)V
     508: areturn
     509: new           #131                // class org/hl7/fhir/dstu3/model/Property
     512: dup
     513: ldc           #179                // String account
     515: ldc           #180                // String Reference(Account)
     517: ldc           #181                // String The set of accounts that may be used for billing for this Encounter.
     519: iconst_0
     520: ldc           #136                // int 2147483647
     522: aload_0
     523: getfield      #103                // Field account:Ljava/util/List;
     526: invokespecial #137                // Method org/hl7/fhir/dstu3/model/Property."<init>":(Ljava/lang/String;Ljava/lang/String;Ljava/lang/String;IILjava/util/List;)V
     529: areturn
     530: new           #131                // class org/hl7/fhir/dstu3/model/Property
     533: dup
     534: ldc           #182                // String hospitalization
     536: ldc           #143                // String
     538: ldc           #183                // String Details about the admission to a healthcare service.
     540: iconst_0
     541: iconst_1
     542: aload_0
     543: getfield      #109                // Field hospitalization:Lorg/hl7/fhir/dstu3/model/Encounter$EncounterHospitalizationComponent;
     546: invokespecial #141                // Method org/hl7/fhir/dstu3/model/Property."<init>":(Ljava/lang/String;Ljava/lang/String;Ljava/lang/String;IILorg/hl7/fhir/dstu3/model/Base;)V
     549: areturn
     550: new           #131                // class org/hl7/fhir/dstu3/model/Property
     553: dup
     554: ldc           #184                // String location
     556: ldc           #143                // String
     558: ldc           #185                // String List of locations where  the patient has been during this encounter.
     560: iconst_0
     561: ldc           #136                // int 2147483647
     563: aload_0
     564: getfield      #114                // Field location:Ljava/util/List;
     567: invokespecial #137                // Method org/hl7/fhir/dstu3/model/Property."<init>":(Ljava/lang/String;Ljava/lang/String;Ljava/lang/String;IILjava/util/List;)V
     570: areturn
     571: new           #131                // class org/hl7/fhir/dstu3/model/Property
     574: dup
     575: ldc           #186                // String serviceProvider
     577: ldc           #187                // String Reference(Organization)
     579: ldc           #188                // String An organization that is in charge of maintaining the information of this Encounter (e.g. who maintains the report or the master service catalog item, etc.). This MAY be the same as the organization on the Patient record, however it could be different. This MAY not be not the Service Delivery Location\'s Organization.
     581: iconst_0
     582: iconst_1
     583: aload_0
     584: getfield      #120                // Field serviceProvider:Lorg/hl7/fhir/dstu3/model/Reference;
     587: invokespecial #141                // Method org/hl7/fhir/dstu3/model/Property."<init>":(Ljava/lang/String;Ljava/lang/String;Ljava/lang/String;IILorg/hl7/fhir/dstu3/model/Base;)V
     590: areturn
     591: new           #131                // class org/hl7/fhir/dstu3/model/Property
     594: dup
     595: ldc           #189                // String partOf
     597: ldc           #190                // String Reference(Encounter)
     599: ldc           #191                // String Another Encounter of which this encounter is a part of (administratively or in time).
     601: iconst_0
     602: iconst_1
     603: aload_0
     604: getfield      #125                // Field partOf:Lorg/hl7/fhir/dstu3/model/Reference;
     607: invokespecial #141                // Method org/hl7/fhir/dstu3/model/Property."<init>":(Ljava/lang/String;Ljava/lang/String;Ljava/lang/String;IILorg/hl7/fhir/dstu3/model/Base;)V
     610: areturn
     611: aload_0
     612: iload_1
     613: aload_2
     614: iload_3
     615: invokespecial #192                // Method org/hl7/fhir/dstu3/model/DomainResource.getNamedProperty:(ILjava/lang/String;Z)Lorg/hl7/fhir/dstu3/model/Property;
     618: areturn

  public org.hl7.fhir.dstu3.model.Base[] getProperty(int, java.lang.String, boolean) throws org.hl7.fhir.exceptions.FHIRException;
    Code:
       0: iload_1
       1: lookupswitch  { // 21
           -1892140189: 440
           -1867885268: 414
           -1618432855: 180
           -1474995297: 557
           -1258204701: 479
           -1177318867: 713
           -1165461084: 388
           -1106363674: 609
            -995410646: 843
            -991726143: 583
            -986695614: 245
            -934964668: 635
            -892481550: 219
               3575610: 349
              94742904: 284
             243182534: 817
             767422259: 518
             962575356: 310
            1057894634: 752
            1196993265: 674
            1901043637: 778
               default: 869
          }
     180: aload_0
     181: getfield      #3                  // Field identifier:Ljava/util/List;
     184: ifnonnull     194
     187: iconst_0
     188: anewarray     #193                // class org/hl7/fhir/dstu3/model/Base
     191: goto          218
     194: aload_0
     195: getfield      #3                  // Field identifier:Ljava/util/List;
     198: aload_0
     199: getfield      #3                  // Field identifier:Ljava/util/List;
     202: invokeinterface #194,  1          // InterfaceMethod java/util/List.size:()I
     207: anewarray     #193                // class org/hl7/fhir/dstu3/model/Base
     210: invokeinterface #195,  2          // InterfaceMethod java/util/List.toArray:([Ljava/lang/Object;)[Ljava/lang/Object;
     215: checkcast     #196                // class "[Lorg/hl7/fhir/dstu3/model/Base;"
     218: areturn
     219: aload_0
     220: getfield      #2                  // Field status:Lorg/hl7/fhir/dstu3/model/Enumeration;
     223: ifnonnull     233
     226: iconst_0
     227: anewarray     #193                // class org/hl7/fhir/dstu3/model/Base
     230: goto          244
     233: iconst_1
     234: anewarray     #193                // class org/hl7/fhir/dstu3/model/Base
     237: dup
     238: iconst_0
     239: aload_0
     240: getfield      #2                  // Field status:Lorg/hl7/fhir/dstu3/model/Enumeration;
     243: aastore
     244: areturn
     245: aload_0
     246: getfield      #30                 // Field statusHistory:Ljava/util/List;
     249: ifnonnull     259
     252: iconst_0
     253: anewarray     #193                // class org/hl7/fhir/dstu3/model/Base
     256: goto          283
     259: aload_0
     260: getfield      #30                 // Field statusHistory:Ljava/util/List;
     263: aload_0
     264: getfield      #30                 // Field statusHistory:Ljava/util/List;
     267: invokeinterface #194,  1          // InterfaceMethod java/util/List.size:()I
     272: anewarray     #193                // class org/hl7/fhir/dstu3/model/Base
     275: invokeinterface #195,  2          // InterfaceMethod java/util/List.toArray:([Ljava/lang/Object;)[Ljava/lang/Object;
     280: checkcast     #196                // class "[Lorg/hl7/fhir/dstu3/model/Base;"
     283: areturn
     284: aload_0
     285: getfield      #36                 // Field class_:Lorg/hl7/fhir/dstu3/model/Coding;
     288: ifnonnull     298
     291: iconst_0
     292: anewarray     #193                // class org/hl7/fhir/dstu3/model/Base
     295: goto          309
     298: iconst_1
     299: anewarray     #193                // class org/hl7/fhir/dstu3/model/Base
     302: dup
     303: iconst_0
     304: aload_0
     305: getfield      #36                 // Field class_:Lorg/hl7/fhir/dstu3/model/Coding;
     308: aastore
     309: areturn
     310: aload_0
     311: getfield      #41                 // Field classHistory:Ljava/util/List;
     314: ifnonnull     324
     317: iconst_0
     318: anewarray     #193                // class org/hl7/fhir/dstu3/model/Base
     321: goto          348
     324: aload_0
     325: getfield      #41                 // Field classHistory:Ljava/util/List;
     328: aload_0
     329: getfield      #41                 // Field classHistory:Ljava/util/List;
     332: invokeinterface #194,  1          // InterfaceMethod java/util/List.size:()I
     337: anewarray     #193                // class org/hl7/fhir/dstu3/model/Base
     340: invokeinterface #195,  2          // InterfaceMethod java/util/List.toArray:([Ljava/lang/Object;)[Ljava/lang/Object;
     345: checkcast     #196                // class "[Lorg/hl7/fhir/dstu3/model/Base;"
     348: areturn
     349: aload_0
     350: getfield      #47                 // Field type:Ljava/util/List;
     353: ifnonnull     363
     356: iconst_0
     357: anewarray     #193                // class org/hl7/fhir/dstu3/model/Base
     360: goto          387
     363: aload_0
     364: getfield      #47                 // Field type:Ljava/util/List;
     367: aload_0
     368: getfield      #47                 // Field type:Ljava/util/List;
     371: invokeinterface #194,  1          // InterfaceMethod java/util/List.size:()I
     376: anewarray     #193                // class org/hl7/fhir/dstu3/model/Base
     379: invokeinterface #195,  2          // InterfaceMethod java/util/List.toArray:([Ljava/lang/Object;)[Ljava/lang/Object;
     384: checkcast     #196                // class "[Lorg/hl7/fhir/dstu3/model/Base;"
     387: areturn
     388: aload_0
     389: getfield      #53                 // Field priority:Lorg/hl7/fhir/dstu3/model/CodeableConcept;
     392: ifnonnull     402
     395: iconst_0
     396: anewarray     #193                // class org/hl7/fhir/dstu3/model/Base
     399: goto          413
     402: iconst_1
     403: anewarray     #193                // class org/hl7/fhir/dstu3/model/Base
     406: dup
     407: iconst_0
     408: aload_0
     409: getfield      #53                 // Field priority:Lorg/hl7/fhir/dstu3/model/CodeableConcept;
     412: aastore
     413: areturn
     414: aload_0
     415: getfield      #55                 // Field subject:Lorg/hl7/fhir/dstu3/model/Reference;
     418: ifnonnull     428
     421: iconst_0
     422: anewarray     #193                // class org/hl7/fhir/dstu3/model/Base
     425: goto          439
     428: iconst_1
     429: anewarray     #193                // class org/hl7/fhir/dstu3/model/Base
     432: dup
     433: iconst_0
     434: aload_0
     435: getfield      #55                 // Field subject:Lorg/hl7/fhir/dstu3/model/Reference;
     438: aastore
     439: areturn
     440: aload_0
     441: getfield      #61                 // Field episodeOfCare:Ljava/util/List;
     444: ifnonnull     454
     447: iconst_0
     448: anewarray     #193                // class org/hl7/fhir/dstu3/model/Base
     451: goto          478
     454: aload_0
     455: getfield      #61                 // Field episodeOfCare:Ljava/util/List;
     458: aload_0
     459: getfield      #61                 // Field episodeOfCare:Ljava/util/List;
     462: invokeinterface #194,  1          // InterfaceMethod java/util/List.size:()I
     467: anewarray     #193                // class org/hl7/fhir/dstu3/model/Base
     470: invokeinterface #195,  2          // InterfaceMethod java/util/List.toArray:([Ljava/lang/Object;)[Ljava/lang/Object;
     475: checkcast     #196                // class "[Lorg/hl7/fhir/dstu3/model/Base;"
     478: areturn
     479: aload_0
     480: getfield      #67                 // Field incomingReferral:Ljava/util/List;
     483: ifnonnull     493
     486: iconst_0
     487: anewarray     #193                // class org/hl7/fhir/dstu3/model/Base
     490: goto          517
     493: aload_0
     494: getfield      #67                 // Field incomingReferral:Ljava/util/List;
     497: aload_0
     498: getfield      #67                 // Field incomingReferral:Ljava/util/List;
     501: invokeinterface #194,  1          // InterfaceMethod java/util/List.size:()I
     506: anewarray     #193                // class org/hl7/fhir/dstu3/model/Base
     509: invokeinterface #195,  2          // InterfaceMethod java/util/List.toArray:([Ljava/lang/Object;)[Ljava/lang/Object;
     514: checkcast     #196                // class "[Lorg/hl7/fhir/dstu3/model/Base;"
     517: areturn
     518: aload_0
     519: getfield      #73                 // Field participant:Ljava/util/List;
     522: ifnonnull     532
     525: iconst_0
     526: anewarray     #193                // class org/hl7/fhir/dstu3/model/Base
     529: goto          556
     532: aload_0
     533: getfield      #73                 // Field participant:Ljava/util/List;
     536: aload_0
     537: getfield      #73                 // Field participant:Ljava/util/List;
     540: invokeinterface #194,  1          // InterfaceMethod java/util/List.size:()I
     545: anewarray     #193                // class org/hl7/fhir/dstu3/model/Base
     548: invokeinterface #195,  2          // InterfaceMethod java/util/List.toArray:([Ljava/lang/Object;)[Ljava/lang/Object;
     553: checkcast     #196                // class "[Lorg/hl7/fhir/dstu3/model/Base;"
     556: areturn
     557: aload_0
     558: getfield      #79                 // Field appointment:Lorg/hl7/fhir/dstu3/model/Reference;
     561: ifnonnull     571
     564: iconst_0
     565: anewarray     #193                // class org/hl7/fhir/dstu3/model/Base
     568: goto          582
     571: iconst_1
     572: anewarray     #193                // class org/hl7/fhir/dstu3/model/Base
     575: dup
     576: iconst_0
     577: aload_0
     578: getfield      #79                 // Field appointment:Lorg/hl7/fhir/dstu3/model/Reference;
     581: aastore
     582: areturn
     583: aload_0
     584: getfield      #84                 // Field period:Lorg/hl7/fhir/dstu3/model/Period;
     587: ifnonnull     597
     590: iconst_0
     591: anewarray     #193                // class org/hl7/fhir/dstu3/model/Base
     594: goto          608
     597: iconst_1
     598: anewarray     #193                // class org/hl7/fhir/dstu3/model/Base
     601: dup
     602: iconst_0
     603: aload_0
     604: getfield      #84                 // Field period:Lorg/hl7/fhir/dstu3/model/Period;
     607: aastore
     608: areturn
     609: aload_0
     610: getfield      #89                 // Field length:Lorg/hl7/fhir/dstu3/model/Duration;
     613: ifnonnull     623
     616: iconst_0
     617: anewarray     #193                // class org/hl7/fhir/dstu3/model/Base
     620: goto          634
     623: iconst_1
     624: anewarray     #193                // class org/hl7/fhir/dstu3/model/Base
     627: dup
     628: iconst_0
     629: aload_0
     630: getfield      #89                 // Field length:Lorg/hl7/fhir/dstu3/model/Duration;
     633: aastore
     634: areturn
     635: aload_0
     636: getfield      #94                 // Field reason:Ljava/util/List;
     639: ifnonnull     649
     642: iconst_0
     643: anewarray     #193                // class org/hl7/fhir/dstu3/model/Base
     646: goto          673
     649: aload_0
     650: getfield      #94                 // Field reason:Ljava/util/List;
     653: aload_0
     654: getfield      #94                 // Field reason:Ljava/util/List;
     657: invokeinterface #194,  1          // InterfaceMethod java/util/List.size:()I
     662: anewarray     #193                // class org/hl7/fhir/dstu3/model/Base
     665: invokeinterface #195,  2          // InterfaceMethod java/util/List.toArray:([Ljava/lang/Object;)[Ljava/lang/Object;
     670: checkcast     #196                // class "[Lorg/hl7/fhir/dstu3/model/Base;"
     673: areturn
     674: aload_0
     675: getfield      #97                 // Field diagnosis:Ljava/util/List;
     678: ifnonnull     688
     681: iconst_0
     682: anewarray     #193                // class org/hl7/fhir/dstu3/model/Base
     685: goto          712
     688: aload_0
     689: getfield      #97                 // Field diagnosis:Ljava/util/List;
     692: aload_0
     693: getfield      #97                 // Field diagnosis:Ljava/util/List;
     696: invokeinterface #194,  1          // InterfaceMethod java/util/List.size:()I
     701: anewarray     #193                // class org/hl7/fhir/dstu3/model/Base
     704: invokeinterface #195,  2          // InterfaceMethod java/util/List.toArray:([Ljava/lang/Object;)[Ljava/lang/Object;
     709: checkcast     #196                // class "[Lorg/hl7/fhir/dstu3/model/Base;"
     712: areturn
     713: aload_0
     714: getfield      #103                // Field account:Ljava/util/List;
     717: ifnonnull     727
     720: iconst_0
     721: anewarray     #193                // class org/hl7/fhir/dstu3/model/Base
     724: goto          751
     727: aload_0
     728: getfield      #103                // Field account:Ljava/util/List;
     731: aload_0
     732: getfield      #103                // Field account:Ljava/util/List;
     735: invokeinterface #194,  1          // InterfaceMethod java/util/List.size:()I
     740: anewarray     #193                // class org/hl7/fhir/dstu3/model/Base
     743: invokeinterface #195,  2          // InterfaceMethod java/util/List.toArray:([Ljava/lang/Object;)[Ljava/lang/Object;
     748: checkcast     #196                // class "[Lorg/hl7/fhir/dstu3/model/Base;"
     751: areturn
     752: aload_0
     753: getfield      #109                // Field hospitalization:Lorg/hl7/fhir/dstu3/model/Encounter$EncounterHospitalizationComponent;
     756: ifnonnull     766
     759: iconst_0
     760: anewarray     #193                // class org/hl7/fhir/dstu3/model/Base
     763: goto          777
     766: iconst_1
     767: anewarray     #193                // class org/hl7/fhir/dstu3/model/Base
     770: dup
     771: iconst_0
     772: aload_0
     773: getfield      #109                // Field hospitalization:Lorg/hl7/fhir/dstu3/model/Encounter$EncounterHospitalizationComponent;
     776: aastore
     777: areturn
     778: aload_0
     779: getfield      #114                // Field location:Ljava/util/List;
     782: ifnonnull     792
     785: iconst_0
     786: anewarray     #193                // class org/hl7/fhir/dstu3/model/Base
     789: goto          816
     792: aload_0
     793: getfield      #114                // Field location:Ljava/util/List;
     796: aload_0
     797: getfield      #114                // Field location:Ljava/util/List;
     800: invokeinterface #194,  1          // InterfaceMethod java/util/List.size:()I
     805: anewarray     #193                // class org/hl7/fhir/dstu3/model/Base
     808: invokeinterface #195,  2          // InterfaceMethod java/util/List.toArray:([Ljava/lang/Object;)[Ljava/lang/Object;
     813: checkcast     #196                // class "[Lorg/hl7/fhir/dstu3/model/Base;"
     816: areturn
     817: aload_0
     818: getfield      #120                // Field serviceProvider:Lorg/hl7/fhir/dstu3/model/Reference;
     821: ifnonnull     831
     824: iconst_0
     825: anewarray     #193                // class org/hl7/fhir/dstu3/model/Base
     828: goto          842
     831: iconst_1
     832: anewarray     #193                // class org/hl7/fhir/dstu3/model/Base
     835: dup
     836: iconst_0
     837: aload_0
     838: getfield      #120                // Field serviceProvider:Lorg/hl7/fhir/dstu3/model/Reference;
     841: aastore
     842: areturn
     843: aload_0
     844: getfield      #125                // Field partOf:Lorg/hl7/fhir/dstu3/model/Reference;
     847: ifnonnull     857
     850: iconst_0
     851: anewarray     #193                // class org/hl7/fhir/dstu3/model/Base
     854: goto          868
     857: iconst_1
     858: anewarray     #193                // class org/hl7/fhir/dstu3/model/Base
     861: dup
     862: iconst_0
     863: aload_0
     864: getfield      #125                // Field partOf:Lorg/hl7/fhir/dstu3/model/Reference;
     867: aastore
     868: areturn
     869: aload_0
     870: iload_1
     871: aload_2
     872: iload_3
     873: invokespecial #197                // Method org/hl7/fhir/dstu3/model/DomainResource.getProperty:(ILjava/lang/String;Z)[Lorg/hl7/fhir/dstu3/model/Base;
     876: areturn

  public org.hl7.fhir.dstu3.model.Base setProperty(int, java.lang.String, org.hl7.fhir.dstu3.model.Base) throws org.hl7.fhir.exceptions.FHIRException;
    Code:
       0: iload_1
       1: lookupswitch  { // 21
           -1892140189: 305
           -1867885268: 294
           -1618432855: 180
           -1474995297: 355
           -1258204701: 322
           -1177318867: 421
           -1165461084: 283
           -1106363674: 377
            -995410646: 475
            -991726143: 366
            -986695614: 223
            -934964668: 388
            -892481550: 197
               3575610: 266
              94742904: 239
             243182534: 464
             767422259: 339
             962575356: 250
            1057894634: 438
            1196993265: 405
            1901043637: 448
               default: 486
          }
     180: aload_0
     181: invokevirtual #13                 // Method getIdentifier:()Ljava/util/List;
     184: aload_0
     185: aload_3
     186: invokevirtual #198                // Method castToIdentifier:(Lorg/hl7/fhir/dstu3/model/Base;)Lorg/hl7/fhir/dstu3/model/Identifier;
     189: invokeinterface #12,  2           // InterfaceMethod java/util/List.add:(Ljava/lang/Object;)Z
     194: pop
     195: aload_3
     196: areturn
     197: new           #23                 // class org/hl7/fhir/dstu3/model/Encounter$EncounterStatusEnumFactory
     200: dup
     201: invokespecial #24                 // Method org/hl7/fhir/dstu3/model/Encounter$EncounterStatusEnumFactory."<init>":()V
     204: aload_0
     205: aload_3
     206: invokevirtual #199                // Method castToCode:(Lorg/hl7/fhir/dstu3/model/Base;)Lorg/hl7/fhir/dstu3/model/CodeType;
     209: invokevirtual #200                // Method org/hl7/fhir/dstu3/model/Encounter$EncounterStatusEnumFactory.fromType:(Lorg/hl7/fhir/dstu3/model/Base;)Lorg/hl7/fhir/dstu3/model/Enumeration;
     212: astore_3
     213: aload_0
     214: aload_3
     215: checkcast     #22                 // class org/hl7/fhir/dstu3/model/Enumeration
     218: putfield      #2                  // Field status:Lorg/hl7/fhir/dstu3/model/Enumeration;
     221: aload_3
     222: areturn
     223: aload_0
     224: invokevirtual #34                 // Method getStatusHistory:()Ljava/util/List;
     227: aload_3
     228: checkcast     #31                 // class org/hl7/fhir/dstu3/model/Encounter$StatusHistoryComponent
     231: invokeinterface #12,  2           // InterfaceMethod java/util/List.add:(Ljava/lang/Object;)Z
     236: pop
     237: aload_3
     238: areturn
     239: aload_0
     240: aload_0
     241: aload_3
     242: invokevirtual #201                // Method castToCoding:(Lorg/hl7/fhir/dstu3/model/Base;)Lorg/hl7/fhir/dstu3/model/Coding;
     245: putfield      #36                 // Field class_:Lorg/hl7/fhir/dstu3/model/Coding;
     248: aload_3
     249: areturn
     250: aload_0
     251: invokevirtual #45                 // Method getClassHistory:()Ljava/util/List;
     254: aload_3
     255: checkcast     #42                 // class org/hl7/fhir/dstu3/model/Encounter$ClassHistoryComponent
     258: invokeinterface #12,  2           // InterfaceMethod java/util/List.add:(Ljava/lang/Object;)Z
     263: pop
     264: aload_3
     265: areturn
     266: aload_0
     267: invokevirtual #51                 // Method getType:()Ljava/util/List;
     270: aload_0
     271: aload_3
     272: invokevirtual #202                // Method castToCodeableConcept:(Lorg/hl7/fhir/dstu3/model/Base;)Lorg/hl7/fhir/dstu3/model/CodeableConcept;
     275: invokeinterface #12,  2           // InterfaceMethod java/util/List.add:(Ljava/lang/Object;)Z
     280: pop
     281: aload_3
     282: areturn
     283: aload_0
     284: aload_0
     285: aload_3
     286: invokevirtual #202                // Method castToCodeableConcept:(Lorg/hl7/fhir/dstu3/model/Base;)Lorg/hl7/fhir/dstu3/model/CodeableConcept;
     289: putfield      #53                 // Field priority:Lorg/hl7/fhir/dstu3/model/CodeableConcept;
     292: aload_3
     293: areturn
     294: aload_0
     295: aload_0
     296: aload_3
     297: invokevirtual #203                // Method castToReference:(Lorg/hl7/fhir/dstu3/model/Base;)Lorg/hl7/fhir/dstu3/model/Reference;
     300: putfield      #55                 // Field subject:Lorg/hl7/fhir/dstu3/model/Reference;
     303: aload_3
     304: areturn
     305: aload_0
     306: invokevirtual #62                 // Method getEpisodeOfCare:()Ljava/util/List;
     309: aload_0
     310: aload_3
     311: invokevirtual #203                // Method castToReference:(Lorg/hl7/fhir/dstu3/model/Base;)Lorg/hl7/fhir/dstu3/model/Reference;
     314: invokeinterface #12,  2           // InterfaceMethod java/util/List.add:(Ljava/lang/Object;)Z
     319: pop
     320: aload_3
     321: areturn
     322: aload_0
     323: invokevirtual #68                 // Method getIncomingReferral:()Ljava/util/List;
     326: aload_0
     327: aload_3
     328: invokevirtual #203                // Method castToReference:(Lorg/hl7/fhir/dstu3/model/Base;)Lorg/hl7/fhir/dstu3/model/Reference;
     331: invokeinterface #12,  2           // InterfaceMethod java/util/List.add:(Ljava/lang/Object;)Z
     336: pop
     337: aload_3
     338: areturn
     339: aload_0
     340: invokevirtual #77                 // Method getParticipant:()Ljava/util/List;
     343: aload_3
     344: checkcast     #74                 // class org/hl7/fhir/dstu3/model/Encounter$EncounterParticipantComponent
     347: invokeinterface #12,  2           // InterfaceMethod java/util/List.add:(Ljava/lang/Object;)Z
     352: pop
     353: aload_3
     354: areturn
     355: aload_0
     356: aload_0
     357: aload_3
     358: invokevirtual #203                // Method castToReference:(Lorg/hl7/fhir/dstu3/model/Base;)Lorg/hl7/fhir/dstu3/model/Reference;
     361: putfield      #79                 // Field appointment:Lorg/hl7/fhir/dstu3/model/Reference;
     364: aload_3
     365: areturn
     366: aload_0
     367: aload_0
     368: aload_3
     369: invokevirtual #204                // Method castToPeriod:(Lorg/hl7/fhir/dstu3/model/Base;)Lorg/hl7/fhir/dstu3/model/Period;
     372: putfield      #84                 // Field period:Lorg/hl7/fhir/dstu3/model/Period;
     375: aload_3
     376: areturn
     377: aload_0
     378: aload_0
     379: aload_3
     380: invokevirtual #205                // Method castToDuration:(Lorg/hl7/fhir/dstu3/model/Base;)Lorg/hl7/fhir/dstu3/model/Duration;
     383: putfield      #89                 // Field length:Lorg/hl7/fhir/dstu3/model/Duration;
     386: aload_3
     387: areturn
     388: aload_0
     389: invokevirtual #95                 // Method getReason:()Ljava/util/List;
     392: aload_0
     393: aload_3
     394: invokevirtual #202                // Method castToCodeableConcept:(Lorg/hl7/fhir/dstu3/model/Base;)Lorg/hl7/fhir/dstu3/model/CodeableConcept;
     397: invokeinterface #12,  2           // InterfaceMethod java/util/List.add:(Ljava/lang/Object;)Z
     402: pop
     403: aload_3
     404: areturn
     405: aload_0
     406: invokevirtual #101                // Method getDiagnosis:()Ljava/util/List;
     409: aload_3
     410: checkcast     #98                 // class org/hl7/fhir/dstu3/model/Encounter$DiagnosisComponent
     413: invokeinterface #12,  2           // InterfaceMethod java/util/List.add:(Ljava/lang/Object;)Z
     418: pop
     419: aload_3
     420: areturn
     421: aload_0
     422: invokevirtual #104                // Method getAccount:()Ljava/util/List;
     425: aload_0
     426: aload_3
     427: invokevirtual #203                // Method castToReference:(Lorg/hl7/fhir/dstu3/model/Base;)Lorg/hl7/fhir/dstu3/model/Reference;
     430: invokeinterface #12,  2           // InterfaceMethod java/util/List.add:(Ljava/lang/Object;)Z
     435: pop
     436: aload_3
     437: areturn
     438: aload_0
     439: aload_3
     440: checkcast     #111                // class org/hl7/fhir/dstu3/model/Encounter$EncounterHospitalizationComponent
     443: putfield      #109                // Field hospitalization:Lorg/hl7/fhir/dstu3/model/Encounter$EncounterHospitalizationComponent;
     446: aload_3
     447: areturn
     448: aload_0
     449: invokevirtual #118                // Method getLocation:()Ljava/util/List;
     452: aload_3
     453: checkcast     #115                // class org/hl7/fhir/dstu3/model/Encounter$EncounterLocationComponent
     456: invokeinterface #12,  2           // InterfaceMethod java/util/List.add:(Ljava/lang/Object;)Z
     461: pop
     462: aload_3
     463: areturn
     464: aload_0
     465: aload_0
     466: aload_3
     467: invokevirtual #203                // Method castToReference:(Lorg/hl7/fhir/dstu3/model/Base;)Lorg/hl7/fhir/dstu3/model/Reference;
     470: putfield      #120                // Field serviceProvider:Lorg/hl7/fhir/dstu3/model/Reference;
     473: aload_3
     474: areturn
     475: aload_0
     476: aload_0
     477: aload_3
     478: invokevirtual #203                // Method castToReference:(Lorg/hl7/fhir/dstu3/model/Base;)Lorg/hl7/fhir/dstu3/model/Reference;
     481: putfield      #125                // Field partOf:Lorg/hl7/fhir/dstu3/model/Reference;
     484: aload_3
     485: areturn
     486: aload_0
     487: iload_1
     488: aload_2
     489: aload_3
     490: invokespecial #206                // Method org/hl7/fhir/dstu3/model/DomainResource.setProperty:(ILjava/lang/String;Lorg/hl7/fhir/dstu3/model/Base;)Lorg/hl7/fhir/dstu3/model/Base;
     493: areturn

  public org.hl7.fhir.dstu3.model.Base setProperty(java.lang.String, org.hl7.fhir.dstu3.model.Base) throws org.hl7.fhir.exceptions.FHIRException;
    Code:
       0: aload_1
       1: ldc           #132                // String identifier
       3: invokevirtual #207                // Method java/lang/String.equals:(Ljava/lang/Object;)Z
       6: ifeq          27
       9: aload_0
      10: invokevirtual #13                 // Method getIdentifier:()Ljava/util/List;
      13: aload_0
      14: aload_2
      15: invokevirtual #198                // Method castToIdentifier:(Lorg/hl7/fhir/dstu3/model/Base;)Lorg/hl7/fhir/dstu3/model/Identifier;
      18: invokeinterface #12,  2           // InterfaceMethod java/util/List.add:(Ljava/lang/Object;)Z
      23: pop
      24: goto          523
      27: aload_1
      28: ldc           #138                // String status
      30: invokevirtual #207                // Method java/lang/String.equals:(Ljava/lang/Object;)Z
      33: ifeq          63
      36: new           #23                 // class org/hl7/fhir/dstu3/model/Encounter$EncounterStatusEnumFactory
      39: dup
      40: invokespecial #24                 // Method org/hl7/fhir/dstu3/model/Encounter$EncounterStatusEnumFactory."<init>":()V
      43: aload_0
      44: aload_2
      45: invokevirtual #199                // Method castToCode:(Lorg/hl7/fhir/dstu3/model/Base;)Lorg/hl7/fhir/dstu3/model/CodeType;
      48: invokevirtual #200                // Method org/hl7/fhir/dstu3/model/Encounter$EncounterStatusEnumFactory.fromType:(Lorg/hl7/fhir/dstu3/model/Base;)Lorg/hl7/fhir/dstu3/model/Enumeration;
      51: astore_2
      52: aload_0
      53: aload_2
      54: checkcast     #22                 // class org/hl7/fhir/dstu3/model/Enumeration
      57: putfield      #2                  // Field status:Lorg/hl7/fhir/dstu3/model/Enumeration;
      60: goto          523
      63: aload_1
      64: ldc           #142                // String statusHistory
      66: invokevirtual #207                // Method java/lang/String.equals:(Ljava/lang/Object;)Z
      69: ifeq          89
      72: aload_0
      73: invokevirtual #34                 // Method getStatusHistory:()Ljava/util/List;
      76: aload_2
      77: checkcast     #31                 // class org/hl7/fhir/dstu3/model/Encounter$StatusHistoryComponent
      80: invokeinterface #12,  2           // InterfaceMethod java/util/List.add:(Ljava/lang/Object;)Z
      85: pop
      86: goto          523
      89: aload_1
      90: ldc           #145                // String class
      92: invokevirtual #207                // Method java/lang/String.equals:(Ljava/lang/Object;)Z
      95: ifeq          110
      98: aload_0
      99: aload_0
     100: aload_2
     101: invokevirtual #201                // Method castToCoding:(Lorg/hl7/fhir/dstu3/model/Base;)Lorg/hl7/fhir/dstu3/model/Coding;
     104: putfield      #36                 // Field class_:Lorg/hl7/fhir/dstu3/model/Coding;
     107: goto          523
     110: aload_1
     111: ldc           #148                // String classHistory
     113: invokevirtual #207                // Method java/lang/String.equals:(Ljava/lang/Object;)Z
     116: ifeq          136
     119: aload_0
     120: invokevirtual #45                 // Method getClassHistory:()Ljava/util/List;
     123: aload_2
     124: checkcast     #42                 // class org/hl7/fhir/dstu3/model/Encounter$ClassHistoryComponent
     127: invokeinterface #12,  2           // InterfaceMethod java/util/List.add:(Ljava/lang/Object;)Z
     132: pop
     133: goto          523
     136: aload_1
     137: ldc           #150                // String type
     139: invokevirtual #207                // Method java/lang/String.equals:(Ljava/lang/Object;)Z
     142: ifeq          163
     145: aload_0
     146: invokevirtual #51                 // Method getType:()Ljava/util/List;
     149: aload_0
     150: aload_2
     151: invokevirtual #202                // Method castToCodeableConcept:(Lorg/hl7/fhir/dstu3/model/Base;)Lorg/hl7/fhir/dstu3/model/CodeableConcept;
     154: invokeinterface #12,  2           // InterfaceMethod java/util/List.add:(Ljava/lang/Object;)Z
     159: pop
     160: goto          523
     163: aload_1
     164: ldc           #153                // String priority
     166: invokevirtual #207                // Method java/lang/String.equals:(Ljava/lang/Object;)Z
     169: ifeq          184
     172: aload_0
     173: aload_0
     174: aload_2
     175: invokevirtual #202                // Method castToCodeableConcept:(Lorg/hl7/fhir/dstu3/model/Base;)Lorg/hl7/fhir/dstu3/model/CodeableConcept;
     178: putfield      #53                 // Field priority:Lorg/hl7/fhir/dstu3/model/CodeableConcept;
     181: goto          523
     184: aload_1
     185: ldc           #155                // String subject
     187: invokevirtual #207                // Method java/lang/String.equals:(Ljava/lang/Object;)Z
     190: ifeq          205
     193: aload_0
     194: aload_0
     195: aload_2
     196: invokevirtual #203                // Method castToReference:(Lorg/hl7/fhir/dstu3/model/Base;)Lorg/hl7/fhir/dstu3/model/Reference;
     199: putfield      #55                 // Field subject:Lorg/hl7/fhir/dstu3/model/Reference;
     202: goto          523
     205: aload_1
     206: ldc           #158                // String episodeOfCare
     208: invokevirtual #207                // Method java/lang/String.equals:(Ljava/lang/Object;)Z
     211: ifeq          232
     214: aload_0
     215: invokevirtual #62                 // Method getEpisodeOfCare:()Ljava/util/List;
     218: aload_0
     219: aload_2
     220: invokevirtual #203                // Method castToReference:(Lorg/hl7/fhir/dstu3/model/Base;)Lorg/hl7/fhir/dstu3/model/Reference;
     223: invokeinterface #12,  2           // InterfaceMethod java/util/List.add:(Ljava/lang/Object;)Z
     228: pop
     229: goto          523
     232: aload_1
     233: ldc           #161                // String incomingReferral
     235: invokevirtual #207                // Method java/lang/String.equals:(Ljava/lang/Object;)Z
     238: ifeq          259
     241: aload_0
     242: invokevirtual #68                 // Method getIncomingReferral:()Ljava/util/List;
     245: aload_0
     246: aload_2
     247: invokevirtual #203                // Method castToReference:(Lorg/hl7/fhir/dstu3/model/Base;)Lorg/hl7/fhir/dstu3/model/Reference;
     250: invokeinterface #12,  2           // InterfaceMethod java/util/List.add:(Ljava/lang/Object;)Z
     255: pop
     256: goto          523
     259: aload_1
     260: ldc           #164                // String participant
     262: invokevirtual #207                // Method java/lang/String.equals:(Ljava/lang/Object;)Z
     265: ifeq          285
     268: aload_0
     269: invokevirtual #77                 // Method getParticipant:()Ljava/util/List;
     272: aload_2
     273: checkcast     #74                 // class org/hl7/fhir/dstu3/model/Encounter$EncounterParticipantComponent
     276: invokeinterface #12,  2           // InterfaceMethod java/util/List.add:(Ljava/lang/Object;)Z
     281: pop
     282: goto          523
     285: aload_1
     286: ldc           #166                // String appointment
     288: invokevirtual #207                // Method java/lang/String.equals:(Ljava/lang/Object;)Z
     291: ifeq          306
     294: aload_0
     295: aload_0
     296: aload_2
     297: invokevirtual #203                // Method castToReference:(Lorg/hl7/fhir/dstu3/model/Base;)Lorg/hl7/fhir/dstu3/model/Reference;
     300: putfield      #79                 // Field appointment:Lorg/hl7/fhir/dstu3/model/Reference;
     303: goto          523
     306: aload_1
     307: ldc           #169                // String period
     309: invokevirtual #207                // Method java/lang/String.equals:(Ljava/lang/Object;)Z
     312: ifeq          327
     315: aload_0
     316: aload_0
     317: aload_2
     318: invokevirtual #204                // Method castToPeriod:(Lorg/hl7/fhir/dstu3/model/Base;)Lorg/hl7/fhir/dstu3/model/Period;
     321: putfield      #84                 // Field period:Lorg/hl7/fhir/dstu3/model/Period;
     324: goto          523
     327: aload_1
     328: ldc           #172                // String length
     330: invokevirtual #207                // Method java/lang/String.equals:(Ljava/lang/Object;)Z
     333: ifeq          348
     336: aload_0
     337: aload_0
     338: aload_2
     339: invokevirtual #205                // Method castToDuration:(Lorg/hl7/fhir/dstu3/model/Base;)Lorg/hl7/fhir/dstu3/model/Duration;
     342: putfield      #89                 // Field length:Lorg/hl7/fhir/dstu3/model/Duration;
     345: goto          523
     348: aload_1
     349: ldc           #175                // String reason
     351: invokevirtual #207                // Method java/lang/String.equals:(Ljava/lang/Object;)Z
     354: ifeq          375
     357: aload_0
     358: invokevirtual #95                 // Method getReason:()Ljava/util/List;
     361: aload_0
     362: aload_2
     363: invokevirtual #202                // Method castToCodeableConcept:(Lorg/hl7/fhir/dstu3/model/Base;)Lorg/hl7/fhir/dstu3/model/CodeableConcept;
     366: invokeinterface #12,  2           // InterfaceMethod java/util/List.add:(Ljava/lang/Object;)Z
     371: pop
     372: goto          523
     375: aload_1
     376: ldc           #177                // String diagnosis
     378: invokevirtual #207                // Method java/lang/String.equals:(Ljava/lang/Object;)Z
     381: ifeq          401
     384: aload_0
     385: invokevirtual #101                // Method getDiagnosis:()Ljava/util/List;
     388: aload_2
     389: checkcast     #98                 // class org/hl7/fhir/dstu3/model/Encounter$DiagnosisComponent
     392: invokeinterface #12,  2           // InterfaceMethod java/util/List.add:(Ljava/lang/Object;)Z
     397: pop
     398: goto          523
     401: aload_1
     402: ldc           #179                // String account
     404: invokevirtual #207                // Method java/lang/String.equals:(Ljava/lang/Object;)Z
     407: ifeq          428
     410: aload_0
     411: invokevirtual #104                // Method getAccount:()Ljava/util/List;
     414: aload_0
     415: aload_2
     416: invokevirtual #203                // Method castToReference:(Lorg/hl7/fhir/dstu3/model/Base;)Lorg/hl7/fhir/dstu3/model/Reference;
     419: invokeinterface #12,  2           // InterfaceMethod java/util/List.add:(Ljava/lang/Object;)Z
     424: pop
     425: goto          523
     428: aload_1
     429: ldc           #182                // String hospitalization
     431: invokevirtual #207                // Method java/lang/String.equals:(Ljava/lang/Object;)Z
     434: ifeq          448
     437: aload_0
     438: aload_2
     439: checkcast     #111                // class org/hl7/fhir/dstu3/model/Encounter$EncounterHospitalizationComponent
     442: putfield      #109                // Field hospitalization:Lorg/hl7/fhir/dstu3/model/Encounter$EncounterHospitalizationComponent;
     445: goto          523
     448: aload_1
     449: ldc           #184                // String location
     451: invokevirtual #207                // Method java/lang/String.equals:(Ljava/lang/Object;)Z
     454: ifeq          474
     457: aload_0
     458: invokevirtual #118                // Method getLocation:()Ljava/util/List;
     461: aload_2
     462: checkcast     #115                // class org/hl7/fhir/dstu3/model/Encounter$EncounterLocationComponent
     465: invokeinterface #12,  2           // InterfaceMethod java/util/List.add:(Ljava/lang/Object;)Z
     470: pop
     471: goto          523
     474: aload_1
     475: ldc           #186                // String serviceProvider
     477: invokevirtual #207                // Method java/lang/String.equals:(Ljava/lang/Object;)Z
     480: ifeq          495
     483: aload_0
     484: aload_0
     485: aload_2
     486: invokevirtual #203                // Method castToReference:(Lorg/hl7/fhir/dstu3/model/Base;)Lorg/hl7/fhir/dstu3/model/Reference;
     489: putfield      #120                // Field serviceProvider:Lorg/hl7/fhir/dstu3/model/Reference;
     492: goto          523
     495: aload_1
     496: ldc           #189                // String partOf
     498: invokevirtual #207                // Method java/lang/String.equals:(Ljava/lang/Object;)Z
     501: ifeq          516
     504: aload_0
     505: aload_0
     506: aload_2
     507: invokevirtual #203                // Method castToReference:(Lorg/hl7/fhir/dstu3/model/Base;)Lorg/hl7/fhir/dstu3/model/Reference;
     510: putfield      #125                // Field partOf:Lorg/hl7/fhir/dstu3/model/Reference;
     513: goto          523
     516: aload_0
     517: aload_1
     518: aload_2
     519: invokespecial #208                // Method org/hl7/fhir/dstu3/model/DomainResource.setProperty:(Ljava/lang/String;Lorg/hl7/fhir/dstu3/model/Base;)Lorg/hl7/fhir/dstu3/model/Base;
     522: areturn
     523: aload_2
     524: areturn

  public org.hl7.fhir.dstu3.model.Base makeProperty(int, java.lang.String) throws org.hl7.fhir.exceptions.FHIRException;
    Code:
       0: iload_1
       1: lookupswitch  { // 21
           -1892140189: 220
           -1867885268: 215
           -1618432855: 180
           -1474995297: 235
           -1258204701: 225
           -1177318867: 260
           -1165461084: 210
           -1106363674: 245
            -995410646: 280
            -991726143: 240
            -986695614: 190
            -934964668: 250
            -892481550: 185
               3575610: 205
              94742904: 195
             243182534: 275
             767422259: 230
             962575356: 200
            1057894634: 265
            1196993265: 255
            1901043637: 270
               default: 285
          }
     180: aload_0
     181: invokevirtual #15                 // Method addIdentifier:()Lorg/hl7/fhir/dstu3/model/Identifier;
     184: areturn
     185: aload_0
     186: invokevirtual #209                // Method getStatusElement:()Lorg/hl7/fhir/dstu3/model/Enumeration;
     189: areturn
     190: aload_0
     191: invokevirtual #35                 // Method addStatusHistory:()Lorg/hl7/fhir/dstu3/model/Encounter$StatusHistoryComponent;
     194: areturn
     195: aload_0
     196: invokevirtual #210                // Method getClass_:()Lorg/hl7/fhir/dstu3/model/Coding;
     199: areturn
     200: aload_0
     201: invokevirtual #46                 // Method addClassHistory:()Lorg/hl7/fhir/dstu3/model/Encounter$ClassHistoryComponent;
     204: areturn
     205: aload_0
     206: invokevirtual #52                 // Method addType:()Lorg/hl7/fhir/dstu3/model/CodeableConcept;
     209: areturn
     210: aload_0
     211: invokevirtual #211                // Method getPriority:()Lorg/hl7/fhir/dstu3/model/CodeableConcept;
     214: areturn
     215: aload_0
     216: invokevirtual #212                // Method getSubject:()Lorg/hl7/fhir/dstu3/model/Reference;
     219: areturn
     220: aload_0
     221: invokevirtual #63                 // Method addEpisodeOfCare:()Lorg/hl7/fhir/dstu3/model/Reference;
     224: areturn
     225: aload_0
     226: invokevirtual #69                 // Method addIncomingReferral:()Lorg/hl7/fhir/dstu3/model/Reference;
     229: areturn
     230: aload_0
     231: invokevirtual #78                 // Method addParticipant:()Lorg/hl7/fhir/dstu3/model/Encounter$EncounterParticipantComponent;
     234: areturn
     235: aload_0
     236: invokevirtual #213                // Method getAppointment:()Lorg/hl7/fhir/dstu3/model/Reference;
     239: areturn
     240: aload_0
     241: invokevirtual #214                // Method getPeriod:()Lorg/hl7/fhir/dstu3/model/Period;
     244: areturn
     245: aload_0
     246: invokevirtual #215                // Method getLength:()Lorg/hl7/fhir/dstu3/model/Duration;
     249: areturn
     250: aload_0
     251: invokevirtual #96                 // Method addReason:()Lorg/hl7/fhir/dstu3/model/CodeableConcept;
     254: areturn
     255: aload_0
     256: invokevirtual #102                // Method addDiagnosis:()Lorg/hl7/fhir/dstu3/model/Encounter$DiagnosisComponent;
     259: areturn
     260: aload_0
     261: invokevirtual #105                // Method addAccount:()Lorg/hl7/fhir/dstu3/model/Reference;
     264: areturn
     265: aload_0
     266: invokevirtual #216                // Method getHospitalization:()Lorg/hl7/fhir/dstu3/model/Encounter$EncounterHospitalizationComponent;
     269: areturn
     270: aload_0
     271: invokevirtual #119                // Method addLocation:()Lorg/hl7/fhir/dstu3/model/Encounter$EncounterLocationComponent;
     274: areturn
     275: aload_0
     276: invokevirtual #217                // Method getServiceProvider:()Lorg/hl7/fhir/dstu3/model/Reference;
     279: areturn
     280: aload_0
     281: invokevirtual #218                // Method getPartOf:()Lorg/hl7/fhir/dstu3/model/Reference;
     284: areturn
     285: aload_0
     286: iload_1
     287: aload_2
     288: invokespecial #219                // Method org/hl7/fhir/dstu3/model/DomainResource.makeProperty:(ILjava/lang/String;)Lorg/hl7/fhir/dstu3/model/Base;
     291: areturn

  public java.lang.String[] getTypesForProperty(int, java.lang.String) throws org.hl7.fhir.exceptions.FHIRException;
    Code:
       0: iload_1
       1: lookupswitch  { // 21
           -1892140189: 250
           -1867885268: 240
           -1618432855: 180
           -1474995297: 275
           -1258204701: 260
           -1177318867: 320
           -1165461084: 230
           -1106363674: 295
            -995410646: 350
            -991726143: 285
            -986695614: 200
            -934964668: 305
            -892481550: 190
               3575610: 220
              94742904: 205
             243182534: 340
             767422259: 270
             962575356: 215
            1057894634: 330
            1196993265: 315
            1901043637: 335
               default: 360
          }
     180: iconst_1
     181: anewarray     #220                // class java/lang/String
     184: dup
     185: iconst_0
     186: ldc           #133                // String Identifier
     188: aastore
     189: areturn
     190: iconst_1
     191: anewarray     #220                // class java/lang/String
     194: dup
     195: iconst_0
     196: ldc           #139                // String code
     198: aastore
     199: areturn
     200: iconst_0
     201: anewarray     #220                // class java/lang/String
     204: areturn
     205: iconst_1
     206: anewarray     #220                // class java/lang/String
     209: dup
     210: iconst_0
     211: ldc           #146                // String Coding
     213: aastore
     214: areturn
     215: iconst_0
     216: anewarray     #220                // class java/lang/String
     219: areturn
     220: iconst_1
     221: anewarray     #220                // class java/lang/String
     224: dup
     225: iconst_0
     226: ldc           #151                // String CodeableConcept
     228: aastore
     229: areturn
     230: iconst_1
     231: anewarray     #220                // class java/lang/String
     234: dup
     235: iconst_0
     236: ldc           #151                // String CodeableConcept
     238: aastore
     239: areturn
     240: iconst_1
     241: anewarray     #220                // class java/lang/String
     244: dup
     245: iconst_0
     246: ldc           #221                // String Reference
     248: aastore
     249: areturn
     250: iconst_1
     251: anewarray     #220                // class java/lang/String
     254: dup
     255: iconst_0
     256: ldc           #221                // String Reference
     258: aastore
     259: areturn
     260: iconst_1
     261: anewarray     #220                // class java/lang/String
     264: dup
     265: iconst_0
     266: ldc           #221                // String Reference
     268: aastore
     269: areturn
     270: iconst_0
     271: anewarray     #220                // class java/lang/String
     274: areturn
     275: iconst_1
     276: anewarray     #220                // class java/lang/String
     279: dup
     280: iconst_0
     281: ldc           #221                // String Reference
     283: aastore
     284: areturn
     285: iconst_1
     286: anewarray     #220                // class java/lang/String
     289: dup
     290: iconst_0
     291: ldc           #170                // String Period
     293: aastore
     294: areturn
     295: iconst_1
     296: anewarray     #220                // class java/lang/String
     299: dup
     300: iconst_0
     301: ldc           #173                // String Duration
     303: aastore
     304: areturn
     305: iconst_1
     306: anewarray     #220                // class java/lang/String
     309: dup
     310: iconst_0
     311: ldc           #151                // String CodeableConcept
     313: aastore
     314: areturn
     315: iconst_0
     316: anewarray     #220                // class java/lang/String
     319: areturn
     320: iconst_1
     321: anewarray     #220                // class java/lang/String
     324: dup
     325: iconst_0
     326: ldc           #221                // String Reference
     328: aastore
     329: areturn
     330: iconst_0
     331: anewarray     #220                // class java/lang/String
     334: areturn
     335: iconst_0
     336: anewarray     #220                // class java/lang/String
     339: areturn
     340: iconst_1
     341: anewarray     #220                // class java/lang/String
     344: dup
     345: iconst_0
     346: ldc           #221                // String Reference
     348: aastore
     349: areturn
     350: iconst_1
     351: anewarray     #220                // class java/lang/String
     354: dup
     355: iconst_0
     356: ldc           #221                // String Reference
     358: aastore
     359: areturn
     360: aload_0
     361: iload_1
     362: aload_2
     363: invokespecial #222                // Method org/hl7/fhir/dstu3/model/DomainResource.getTypesForProperty:(ILjava/lang/String;)[Ljava/lang/String;
     366: areturn

  public org.hl7.fhir.dstu3.model.Base addChild(java.lang.String) throws org.hl7.fhir.exceptions.FHIRException;
    Code:
       0: aload_1
       1: ldc           #132                // String identifier
       3: invokevirtual #207                // Method java/lang/String.equals:(Ljava/lang/Object;)Z
       6: ifeq          14
       9: aload_0
      10: invokevirtual #15                 // Method addIdentifier:()Lorg/hl7/fhir/dstu3/model/Identifier;
      13: areturn
      14: aload_1
      15: ldc           #138                // String status
      17: invokevirtual #207                // Method java/lang/String.equals:(Ljava/lang/Object;)Z
      20: ifeq          33
      23: new           #223                // class org/hl7/fhir/exceptions/FHIRException
      26: dup
      27: ldc           #224                // String Cannot call addChild on a primitive type Encounter.status
      29: invokespecial #225                // Method org/hl7/fhir/exceptions/FHIRException."<init>":(Ljava/lang/String;)V
      32: athrow
      33: aload_1
      34: ldc           #142                // String statusHistory
      36: invokevirtual #207                // Method java/lang/String.equals:(Ljava/lang/Object;)Z
      39: ifeq          47
      42: aload_0
      43: invokevirtual #35                 // Method addStatusHistory:()Lorg/hl7/fhir/dstu3/model/Encounter$StatusHistoryComponent;
      46: areturn
      47: aload_1
      48: ldc           #145                // String class
      50: invokevirtual #207                // Method java/lang/String.equals:(Ljava/lang/Object;)Z
      53: ifeq          72
      56: aload_0
      57: new           #38                 // class org/hl7/fhir/dstu3/model/Coding
      60: dup
      61: invokespecial #39                 // Method org/hl7/fhir/dstu3/model/Coding."<init>":()V
      64: putfield      #36                 // Field class_:Lorg/hl7/fhir/dstu3/model/Coding;
      67: aload_0
      68: getfield      #36                 // Field class_:Lorg/hl7/fhir/dstu3/model/Coding;
      71: areturn
      72: aload_1
      73: ldc           #148                // String classHistory
      75: invokevirtual #207                // Method java/lang/String.equals:(Ljava/lang/Object;)Z
      78: ifeq          86
      81: aload_0
      82: invokevirtual #46                 // Method addClassHistory:()Lorg/hl7/fhir/dstu3/model/Encounter$ClassHistoryComponent;
      85: areturn
      86: aload_1
      87: ldc           #150                // String type
      89: invokevirtual #207                // Method java/lang/String.equals:(Ljava/lang/Object;)Z
      92: ifeq          100
      95: aload_0
      96: invokevirtual #52                 // Method addType:()Lorg/hl7/fhir/dstu3/model/CodeableConcept;
      99: areturn
     100: aload_1
     101: ldc           #153                // String priority
     103: invokevirtual #207                // Method java/lang/String.equals:(Ljava/lang/Object;)Z
     106: ifeq          125
     109: aload_0
     110: new           #48                 // class org/hl7/fhir/dstu3/model/CodeableConcept
     113: dup
     114: invokespecial #50                 // Method org/hl7/fhir/dstu3/model/CodeableConcept."<init>":()V
     117: putfield      #53                 // Field priority:Lorg/hl7/fhir/dstu3/model/CodeableConcept;
     120: aload_0
     121: getfield      #53                 // Field priority:Lorg/hl7/fhir/dstu3/model/CodeableConcept;
     124: areturn
     125: aload_1
     126: ldc           #155                // String subject
     128: invokevirtual #207                // Method java/lang/String.equals:(Ljava/lang/Object;)Z
     131: ifeq          150
     134: aload_0
     135: new           #57                 // class org/hl7/fhir/dstu3/model/Reference
     138: dup
     139: invokespecial #58                 // Method org/hl7/fhir/dstu3/model/Reference."<init>":()V
     142: putfield      #55                 // Field subject:Lorg/hl7/fhir/dstu3/model/Reference;
     145: aload_0
     146: getfield      #55                 // Field subject:Lorg/hl7/fhir/dstu3/model/Reference;
     149: areturn
     150: aload_1
     151: ldc           #158                // String episodeOfCare
     153: invokevirtual #207                // Method java/lang/String.equals:(Ljava/lang/Object;)Z
     156: ifeq          164
     159: aload_0
     160: invokevirtual #63                 // Method addEpisodeOfCare:()Lorg/hl7/fhir/dstu3/model/Reference;
     163: areturn
     164: aload_1
     165: ldc           #161                // String incomingReferral
     167: invokevirtual #207                // Method java/lang/String.equals:(Ljava/lang/Object;)Z
     170: ifeq          178
     173: aload_0
     174: invokevirtual #69                 // Method addIncomingReferral:()Lorg/hl7/fhir/dstu3/model/Reference;
     177: areturn
     178: aload_1
     179: ldc           #164                // String participant
     181: invokevirtual #207                // Method java/lang/String.equals:(Ljava/lang/Object;)Z
     184: ifeq          192
     187: aload_0
     188: invokevirtual #78                 // Method addParticipant:()Lorg/hl7/fhir/dstu3/model/Encounter$EncounterParticipantComponent;
     191: areturn
     192: aload_1
     193: ldc           #166                // String appointment
     195: invokevirtual #207                // Method java/lang/String.equals:(Ljava/lang/Object;)Z
     198: ifeq          217
     201: aload_0
     202: new           #57                 // class org/hl7/fhir/dstu3/model/Reference
     205: dup
     206: invokespecial #58                 // Method org/hl7/fhir/dstu3/model/Reference."<init>":()V
     209: putfield      #79                 // Field appointment:Lorg/hl7/fhir/dstu3/model/Reference;
     212: aload_0
     213: getfield      #79                 // Field appointment:Lorg/hl7/fhir/dstu3/model/Reference;
     216: areturn
     217: aload_1
     218: ldc           #169                // String period
     220: invokevirtual #207                // Method java/lang/String.equals:(Ljava/lang/Object;)Z
     223: ifeq          242
     226: aload_0
     227: new           #86                 // class org/hl7/fhir/dstu3/model/Period
     230: dup
     231: invokespecial #87                 // Method org/hl7/fhir/dstu3/model/Period."<init>":()V
     234: putfield      #84                 // Field period:Lorg/hl7/fhir/dstu3/model/Period;
     237: aload_0
     238: getfield      #84                 // Field period:Lorg/hl7/fhir/dstu3/model/Period;
     241: areturn
     242: aload_1
     243: ldc           #172                // String length
     245: invokevirtual #207                // Method java/lang/String.equals:(Ljava/lang/Object;)Z
     248: ifeq          267
     251: aload_0
     252: new           #91                 // class org/hl7/fhir/dstu3/model/Duration
     255: dup
     256: invokespecial #92                 // Method org/hl7/fhir/dstu3/model/Duration."<init>":()V
     259: putfield      #89                 // Field length:Lorg/hl7/fhir/dstu3/model/Duration;
     262: aload_0
     263: getfield      #89                 // Field length:Lorg/hl7/fhir/dstu3/model/Duration;
     266: areturn
     267: aload_1
     268: ldc           #175                // String reason
     270: invokevirtual #207                // Method java/lang/String.equals:(Ljava/lang/Object;)Z
     273: ifeq          281
     276: aload_0
     277: invokevirtual #96                 // Method addReason:()Lorg/hl7/fhir/dstu3/model/CodeableConcept;
     280: areturn
     281: aload_1
     282: ldc           #177                // String diagnosis
     284: invokevirtual #207                // Method java/lang/String.equals:(Ljava/lang/Object;)Z
     287: ifeq          295
     290: aload_0
     291: invokevirtual #102                // Method addDiagnosis:()Lorg/hl7/fhir/dstu3/model/Encounter$DiagnosisComponent;
     294: areturn
     295: aload_1
     296: ldc           #179                // String account
     298: invokevirtual #207                // Method java/lang/String.equals:(Ljava/lang/Object;)Z
     301: ifeq          309
     304: aload_0
     305: invokevirtual #105                // Method addAccount:()Lorg/hl7/fhir/dstu3/model/Reference;
     308: areturn
     309: aload_1
     310: ldc           #182                // String hospitalization
     312: invokevirtual #207                // Method java/lang/String.equals:(Ljava/lang/Object;)Z
     315: ifeq          334
     318: aload_0
     319: new           #111                // class org/hl7/fhir/dstu3/model/Encounter$EncounterHospitalizationComponent
     322: dup
     323: invokespecial #112                // Method org/hl7/fhir/dstu3/model/Encounter$EncounterHospitalizationComponent."<init>":()V
     326: putfield      #109                // Field hospitalization:Lorg/hl7/fhir/dstu3/model/Encounter$EncounterHospitalizationComponent;
     329: aload_0
     330: getfield      #109                // Field hospitalization:Lorg/hl7/fhir/dstu3/model/Encounter$EncounterHospitalizationComponent;
     333: areturn
     334: aload_1
     335: ldc           #184                // String location
     337: invokevirtual #207                // Method java/lang/String.equals:(Ljava/lang/Object;)Z
     340: ifeq          348
     343: aload_0
     344: invokevirtual #119                // Method addLocation:()Lorg/hl7/fhir/dstu3/model/Encounter$EncounterLocationComponent;
     347: areturn
     348: aload_1
     349: ldc           #186                // String serviceProvider
     351: invokevirtual #207                // Method java/lang/String.equals:(Ljava/lang/Object;)Z
     354: ifeq          373
     357: aload_0
     358: new           #57                 // class org/hl7/fhir/dstu3/model/Reference
     361: dup
     362: invokespecial #58                 // Method org/hl7/fhir/dstu3/model/Reference."<init>":()V
     365: putfield      #120                // Field serviceProvider:Lorg/hl7/fhir/dstu3/model/Reference;
     368: aload_0
     369: getfield      #120                // Field serviceProvider:Lorg/hl7/fhir/dstu3/model/Reference;
     372: areturn
     373: aload_1
     374: ldc           #189                // String partOf
     376: invokevirtual #207                // Method java/lang/String.equals:(Ljava/lang/Object;)Z
     379: ifeq          398
     382: aload_0
     383: new           #57                 // class org/hl7/fhir/dstu3/model/Reference
     386: dup
     387: invokespecial #58                 // Method org/hl7/fhir/dstu3/model/Reference."<init>":()V
     390: putfield      #125                // Field partOf:Lorg/hl7/fhir/dstu3/model/Reference;
     393: aload_0
     394: getfield      #125                // Field partOf:Lorg/hl7/fhir/dstu3/model/Reference;
     397: areturn
     398: aload_0
     399: aload_1
     400: invokespecial #226                // Method org/hl7/fhir/dstu3/model/DomainResource.addChild:(Ljava/lang/String;)Lorg/hl7/fhir/dstu3/model/Base;
     403: areturn

  public java.lang.String fhirType();
    Code:
       0: ldc           #227                // String Encounter
       2: areturn

  public org.hl7.fhir.dstu3.model.Encounter copy();
    Code:
       0: new           #128                // class org/hl7/fhir/dstu3/model/Encounter
       3: dup
       4: invokespecial #129                // Method "<init>":()V
       7: astore_1
       8: aload_0
       9: aload_1
      10: invokevirtual #228                // Method copyValues:(Lorg/hl7/fhir/dstu3/model/DomainResource;)V
      13: aload_0
      14: getfield      #3                  // Field identifier:Ljava/util/List;
      17: ifnull        77
      20: aload_1
      21: new           #4                  // class java/util/ArrayList
      24: dup
      25: invokespecial #5                  // Method java/util/ArrayList."<init>":()V
      28: putfield      #3                  // Field identifier:Ljava/util/List;
      31: aload_0
      32: getfield      #3                  // Field identifier:Ljava/util/List;
      35: invokeinterface #6,  1            // InterfaceMethod java/util/List.iterator:()Ljava/util/Iterator;
      40: astore_2
      41: aload_2
      42: invokeinterface #7,  1            // InterfaceMethod java/util/Iterator.hasNext:()Z
      47: ifeq          77
      50: aload_2
      51: invokeinterface #8,  1            // InterfaceMethod java/util/Iterator.next:()Ljava/lang/Object;
      56: checkcast     #9                  // class org/hl7/fhir/dstu3/model/Identifier
      59: astore_3
      60: aload_1
      61: getfield      #3                  // Field identifier:Ljava/util/List;
      64: aload_3
      65: invokevirtual #229                // Method org/hl7/fhir/dstu3/model/Identifier.copy:()Lorg/hl7/fhir/dstu3/model/Identifier;
      68: invokeinterface #12,  2           // InterfaceMethod java/util/List.add:(Ljava/lang/Object;)Z
      73: pop
      74: goto          41
      77: aload_1
      78: aload_0
      79: getfield      #2                  // Field status:Lorg/hl7/fhir/dstu3/model/Enumeration;
      82: ifnonnull     89
      85: aconst_null
      86: goto          96
      89: aload_0
      90: getfield      #2                  // Field status:Lorg/hl7/fhir/dstu3/model/Enumeration;
      93: invokevirtual #230                // Method org/hl7/fhir/dstu3/model/Enumeration.copy:()Lorg/hl7/fhir/dstu3/model/Enumeration;
      96: putfield      #2                  // Field status:Lorg/hl7/fhir/dstu3/model/Enumeration;
      99: aload_0
     100: getfield      #30                 // Field statusHistory:Ljava/util/List;
     103: ifnull        163
     106: aload_1
     107: new           #4                  // class java/util/ArrayList
     110: dup
     111: invokespecial #5                  // Method java/util/ArrayList."<init>":()V
     114: putfield      #30                 // Field statusHistory:Ljava/util/List;
     117: aload_0
     118: getfield      #30                 // Field statusHistory:Ljava/util/List;
     121: invokeinterface #6,  1            // InterfaceMethod java/util/List.iterator:()Ljava/util/Iterator;
     126: astore_2
     127: aload_2
     128: invokeinterface #7,  1            // InterfaceMethod java/util/Iterator.hasNext:()Z
     133: ifeq          163
     136: aload_2
     137: invokeinterface #8,  1            // InterfaceMethod java/util/Iterator.next:()Ljava/lang/Object;
     142: checkcast     #31                 // class org/hl7/fhir/dstu3/model/Encounter$StatusHistoryComponent
     145: astore_3
     146: aload_1
     147: getfield      #30                 // Field statusHistory:Ljava/util/List;
     150: aload_3
     151: invokevirtual #231                // Method org/hl7/fhir/dstu3/model/Encounter$StatusHistoryComponent.copy:()Lorg/hl7/fhir/dstu3/model/Encounter$StatusHistoryComponent;
     154: invokeinterface #12,  2           // InterfaceMethod java/util/List.add:(Ljava/lang/Object;)Z
     159: pop
     160: goto          127
     163: aload_1
     164: aload_0
     165: getfield      #36                 // Field class_:Lorg/hl7/fhir/dstu3/model/Coding;
     168: ifnonnull     175
     171: aconst_null
     172: goto          182
     175: aload_0
     176: getfield      #36                 // Field class_:Lorg/hl7/fhir/dstu3/model/Coding;
     179: invokevirtual #232                // Method org/hl7/fhir/dstu3/model/Coding.copy:()Lorg/hl7/fhir/dstu3/model/Coding;
     182: putfield      #36                 // Field class_:Lorg/hl7/fhir/dstu3/model/Coding;
     185: aload_0
     186: getfield      #41                 // Field classHistory:Ljava/util/List;
     189: ifnull        249
     192: aload_1
     193: new           #4                  // class java/util/ArrayList
     196: dup
     197: invokespecial #5                  // Method java/util/ArrayList."<init>":()V
     200: putfield      #41                 // Field classHistory:Ljava/util/List;
     203: aload_0
     204: getfield      #41                 // Field classHistory:Ljava/util/List;
     207: invokeinterface #6,  1            // InterfaceMethod java/util/List.iterator:()Ljava/util/Iterator;
     212: astore_2
     213: aload_2
     214: invokeinterface #7,  1            // InterfaceMethod java/util/Iterator.hasNext:()Z
     219: ifeq          249
     222: aload_2
     223: invokeinterface #8,  1            // InterfaceMethod java/util/Iterator.next:()Ljava/lang/Object;
     228: checkcast     #42                 // class org/hl7/fhir/dstu3/model/Encounter$ClassHistoryComponent
     231: astore_3
     232: aload_1
     233: getfield      #41                 // Field classHistory:Ljava/util/List;
     236: aload_3
     237: invokevirtual #233                // Method org/hl7/fhir/dstu3/model/Encounter$ClassHistoryComponent.copy:()Lorg/hl7/fhir/dstu3/model/Encounter$ClassHistoryComponent;
     240: invokeinterface #12,  2           // InterfaceMethod java/util/List.add:(Ljava/lang/Object;)Z
     245: pop
     246: goto          213
     249: aload_0
     250: getfield      #47                 // Field type:Ljava/util/List;
     253: ifnull        313
     256: aload_1
     257: new           #4                  // class java/util/ArrayList
     260: dup
     261: invokespecial #5                  // Method java/util/ArrayList."<init>":()V
     264: putfield      #47                 // Field type:Ljava/util/List;
     267: aload_0
     268: getfield      #47                 // Field type:Ljava/util/List;
     271: invokeinterface #6,  1            // InterfaceMethod java/util/List.iterator:()Ljava/util/Iterator;
     276: astore_2
     277: aload_2
     278: invokeinterface #7,  1            // InterfaceMethod java/util/Iterator.hasNext:()Z
     283: ifeq          313
     286: aload_2
     287: invokeinterface #8,  1            // InterfaceMethod java/util/Iterator.next:()Ljava/lang/Object;
     292: checkcast     #48                 // class org/hl7/fhir/dstu3/model/CodeableConcept
     295: astore_3
     296: aload_1
     297: getfield      #47                 // Field type:Ljava/util/List;
     300: aload_3
     301: invokevirtual #234                // Method org/hl7/fhir/dstu3/model/CodeableConcept.copy:()Lorg/hl7/fhir/dstu3/model/CodeableConcept;
     304: invokeinterface #12,  2           // InterfaceMethod java/util/List.add:(Ljava/lang/Object;)Z
     309: pop
     310: goto          277
     313: aload_1
     314: aload_0
     315: getfield      #53                 // Field priority:Lorg/hl7/fhir/dstu3/model/CodeableConcept;
     318: ifnonnull     325
     321: aconst_null
     322: goto          332
     325: aload_0
     326: getfield      #53                 // Field priority:Lorg/hl7/fhir/dstu3/model/CodeableConcept;
     329: invokevirtual #234                // Method org/hl7/fhir/dstu3/model/CodeableConcept.copy:()Lorg/hl7/fhir/dstu3/model/CodeableConcept;
     332: putfield      #53                 // Field priority:Lorg/hl7/fhir/dstu3/model/CodeableConcept;
     335: aload_1
     336: aload_0
     337: getfield      #55                 // Field subject:Lorg/hl7/fhir/dstu3/model/Reference;
     340: ifnonnull     347
     343: aconst_null
     344: goto          354
     347: aload_0
     348: getfield      #55                 // Field subject:Lorg/hl7/fhir/dstu3/model/Reference;
     351: invokevirtual #235                // Method org/hl7/fhir/dstu3/model/Reference.copy:()Lorg/hl7/fhir/dstu3/model/Reference;
     354: putfield      #55                 // Field subject:Lorg/hl7/fhir/dstu3/model/Reference;
     357: aload_0
     358: getfield      #61                 // Field episodeOfCare:Ljava/util/List;
     361: ifnull        421
     364: aload_1
     365: new           #4                  // class java/util/ArrayList
     368: dup
     369: invokespecial #5                  // Method java/util/ArrayList."<init>":()V
     372: putfield      #61                 // Field episodeOfCare:Ljava/util/List;
     375: aload_0
     376: getfield      #61                 // Field episodeOfCare:Ljava/util/List;
     379: invokeinterface #6,  1            // InterfaceMethod java/util/List.iterator:()Ljava/util/Iterator;
     384: astore_2
     385: aload_2
     386: invokeinterface #7,  1            // InterfaceMethod java/util/Iterator.hasNext:()Z
     391: ifeq          421
     394: aload_2
     395: invokeinterface #8,  1            // InterfaceMethod java/util/Iterator.next:()Ljava/lang/Object;
     400: checkcast     #57                 // class org/hl7/fhir/dstu3/model/Reference
     403: astore_3
     404: aload_1
     405: getfield      #61                 // Field episodeOfCare:Ljava/util/List;
     408: aload_3
     409: invokevirtual #235                // Method org/hl7/fhir/dstu3/model/Reference.copy:()Lorg/hl7/fhir/dstu3/model/Reference;
     412: invokeinterface #12,  2           // InterfaceMethod java/util/List.add:(Ljava/lang/Object;)Z
     417: pop
     418: goto          385
     421: aload_0
     422: getfield      #67                 // Field incomingReferral:Ljava/util/List;
     425: ifnull        485
     428: aload_1
     429: new           #4                  // class java/util/ArrayList
     432: dup
     433: invokespecial #5                  // Method java/util/ArrayList."<init>":()V
     436: putfield      #67                 // Field incomingReferral:Ljava/util/List;
     439: aload_0
     440: getfield      #67                 // Field incomingReferral:Ljava/util/List;
     443: invokeinterface #6,  1            // InterfaceMethod java/util/List.iterator:()Ljava/util/Iterator;
     448: astore_2
     449: aload_2
     450: invokeinterface #7,  1            // InterfaceMethod java/util/Iterator.hasNext:()Z
     455: ifeq          485
     458: aload_2
     459: invokeinterface #8,  1            // InterfaceMethod java/util/Iterator.next:()Ljava/lang/Object;
     464: checkcast     #57                 // class org/hl7/fhir/dstu3/model/Reference
     467: astore_3
     468: aload_1
     469: getfield      #67                 // Field incomingReferral:Ljava/util/List;
     472: aload_3
     473: invokevirtual #235                // Method org/hl7/fhir/dstu3/model/Reference.copy:()Lorg/hl7/fhir/dstu3/model/Reference;
     476: invokeinterface #12,  2           // InterfaceMethod java/util/List.add:(Ljava/lang/Object;)Z
     481: pop
     482: goto          449
     485: aload_0
     486: getfield      #73                 // Field participant:Ljava/util/List;
     489: ifnull        549
     492: aload_1
     493: new           #4                  // class java/util/ArrayList
     496: dup
     497: invokespecial #5                  // Method java/util/ArrayList."<init>":()V
     500: putfield      #73                 // Field participant:Ljava/util/List;
     503: aload_0
     504: getfield      #73                 // Field participant:Ljava/util/List;
     507: invokeinterface #6,  1            // InterfaceMethod java/util/List.iterator:()Ljava/util/Iterator;
     512: astore_2
     513: aload_2
     514: invokeinterface #7,  1            // InterfaceMethod java/util/Iterator.hasNext:()Z
     519: ifeq          549
     522: aload_2
     523: invokeinterface #8,  1            // InterfaceMethod java/util/Iterator.next:()Ljava/lang/Object;
     528: checkcast     #74                 // class org/hl7/fhir/dstu3/model/Encounter$EncounterParticipantComponent
     531: astore_3
     532: aload_1
     533: getfield      #73                 // Field participant:Ljava/util/List;
     536: aload_3
     537: invokevirtual #236                // Method org/hl7/fhir/dstu3/model/Encounter$EncounterParticipantComponent.copy:()Lorg/hl7/fhir/dstu3/model/Encounter$EncounterParticipantComponent;
     540: invokeinterface #12,  2           // InterfaceMethod java/util/List.add:(Ljava/lang/Object;)Z
     545: pop
     546: goto          513
     549: aload_1
     550: aload_0
     551: getfield      #79                 // Field appointment:Lorg/hl7/fhir/dstu3/model/Reference;
     554: ifnonnull     561
     557: aconst_null
     558: goto          568
     561: aload_0
     562: getfield      #79                 // Field appointment:Lorg/hl7/fhir/dstu3/model/Reference;
     565: invokevirtual #235                // Method org/hl7/fhir/dstu3/model/Reference.copy:()Lorg/hl7/fhir/dstu3/model/Reference;
     568: putfield      #79                 // Field appointment:Lorg/hl7/fhir/dstu3/model/Reference;
     571: aload_1
     572: aload_0
     573: getfield      #84                 // Field period:Lorg/hl7/fhir/dstu3/model/Period;
     576: ifnonnull     583
     579: aconst_null
     580: goto          590
     583: aload_0
     584: getfield      #84                 // Field period:Lorg/hl7/fhir/dstu3/model/Period;
     587: invokevirtual #237                // Method org/hl7/fhir/dstu3/model/Period.copy:()Lorg/hl7/fhir/dstu3/model/Period;
     590: putfield      #84                 // Field period:Lorg/hl7/fhir/dstu3/model/Period;
     593: aload_1
     594: aload_0
     595: getfield      #89                 // Field length:Lorg/hl7/fhir/dstu3/model/Duration;
     598: ifnonnull     605
     601: aconst_null
     602: goto          612
     605: aload_0
     606: getfield      #89                 // Field length:Lorg/hl7/fhir/dstu3/model/Duration;
     609: invokevirtual #238                // Method org/hl7/fhir/dstu3/model/Duration.copy:()Lorg/hl7/fhir/dstu3/model/Duration;
     612: putfield      #89                 // Field length:Lorg/hl7/fhir/dstu3/model/Duration;
     615: aload_0
     616: getfield      #94                 // Field reason:Ljava/util/List;
     619: ifnull        679
     622: aload_1
     623: new           #4                  // class java/util/ArrayList
     626: dup
     627: invokespecial #5                  // Method java/util/ArrayList."<init>":()V
     630: putfield      #94                 // Field reason:Ljava/util/List;
     633: aload_0
     634: getfield      #94                 // Field reason:Ljava/util/List;
     637: invokeinterface #6,  1            // InterfaceMethod java/util/List.iterator:()Ljava/util/Iterator;
     642: astore_2
     643: aload_2
     644: invokeinterface #7,  1            // InterfaceMethod java/util/Iterator.hasNext:()Z
     649: ifeq          679
     652: aload_2
     653: invokeinterface #8,  1            // InterfaceMethod java/util/Iterator.next:()Ljava/lang/Object;
     658: checkcast     #48                 // class org/hl7/fhir/dstu3/model/CodeableConcept
     661: astore_3
     662: aload_1
     663: getfield      #94                 // Field reason:Ljava/util/List;
     666: aload_3
     667: invokevirtual #234                // Method org/hl7/fhir/dstu3/model/CodeableConcept.copy:()Lorg/hl7/fhir/dstu3/model/CodeableConcept;
     670: invokeinterface #12,  2           // InterfaceMethod java/util/List.add:(Ljava/lang/Object;)Z
     675: pop
     676: goto          643
     679: aload_0
     680: getfield      #97                 // Field diagnosis:Ljava/util/List;
     683: ifnull        743
     686: aload_1
     687: new           #4                  // class java/util/ArrayList
     690: dup
     691: invokespecial #5                  // Method java/util/ArrayList."<init>":()V
     694: putfield      #97                 // Field diagnosis:Ljava/util/List;
     697: aload_0
     698: getfield      #97                 // Field diagnosis:Ljava/util/List;
     701: invokeinterface #6,  1            // InterfaceMethod java/util/List.iterator:()Ljava/util/Iterator;
     706: astore_2
     707: aload_2
     708: invokeinterface #7,  1            // InterfaceMethod java/util/Iterator.hasNext:()Z
     713: ifeq          743
     716: aload_2
     717: invokeinterface #8,  1            // InterfaceMethod java/util/Iterator.next:()Ljava/lang/Object;
     722: checkcast     #98                 // class org/hl7/fhir/dstu3/model/Encounter$DiagnosisComponent
     725: astore_3
     726: aload_1
     727: getfield      #97                 // Field diagnosis:Ljava/util/List;
     730: aload_3
     731: invokevirtual #239                // Method org/hl7/fhir/dstu3/model/Encounter$DiagnosisComponent.copy:()Lorg/hl7/fhir/dstu3/model/Encounter$DiagnosisComponent;
     734: invokeinterface #12,  2           // InterfaceMethod java/util/List.add:(Ljava/lang/Object;)Z
     739: pop
     740: goto          707
     743: aload_0
     744: getfield      #103                // Field account:Ljava/util/List;
     747: ifnull        807
     750: aload_1
     751: new           #4                  // class java/util/ArrayList
     754: dup
     755: invokespecial #5                  // Method java/util/ArrayList."<init>":()V
     758: putfield      #103                // Field account:Ljava/util/List;
     761: aload_0
     762: getfield      #103                // Field account:Ljava/util/List;
     765: invokeinterface #6,  1            // InterfaceMethod java/util/List.iterator:()Ljava/util/Iterator;
     770: astore_2
     771: aload_2
     772: invokeinterface #7,  1            // InterfaceMethod java/util/Iterator.hasNext:()Z
     777: ifeq          807
     780: aload_2
     781: invokeinterface #8,  1            // InterfaceMethod java/util/Iterator.next:()Ljava/lang/Object;
     786: checkcast     #57                 // class org/hl7/fhir/dstu3/model/Reference
     789: astore_3
     790: aload_1
     791: getfield      #103                // Field account:Ljava/util/List;
     794: aload_3
     795: invokevirtual #235                // Method org/hl7/fhir/dstu3/model/Reference.copy:()Lorg/hl7/fhir/dstu3/model/Reference;
     798: invokeinterface #12,  2           // InterfaceMethod java/util/List.add:(Ljava/lang/Object;)Z
     803: pop
     804: goto          771
     807: aload_1
     808: aload_0
     809: getfield      #109                // Field hospitalization:Lorg/hl7/fhir/dstu3/model/Encounter$EncounterHospitalizationComponent;
     812: ifnonnull     819
     815: aconst_null
     816: goto          826
     819: aload_0
     820: getfield      #109                // Field hospitalization:Lorg/hl7/fhir/dstu3/model/Encounter$EncounterHospitalizationComponent;
     823: invokevirtual #240                // Method org/hl7/fhir/dstu3/model/Encounter$EncounterHospitalizationComponent.copy:()Lorg/hl7/fhir/dstu3/model/Encounter$EncounterHospitalizationComponent;
     826: putfield      #109                // Field hospitalization:Lorg/hl7/fhir/dstu3/model/Encounter$EncounterHospitalizationComponent;
     829: aload_0
     830: getfield      #114                // Field location:Ljava/util/List;
     833: ifnull        893
     836: aload_1
     837: new           #4                  // class java/util/ArrayList
     840: dup
     841: invokespecial #5                  // Method java/util/ArrayList."<init>":()V
     844: putfield      #114                // Field location:Ljava/util/List;
     847: aload_0
     848: getfield      #114                // Field location:Ljava/util/List;
     851: invokeinterface #6,  1            // InterfaceMethod java/util/List.iterator:()Ljava/util/Iterator;
     856: astore_2
     857: aload_2
     858: invokeinterface #7,  1            // InterfaceMethod java/util/Iterator.hasNext:()Z
     863: ifeq          893
     866: aload_2
     867: invokeinterface #8,  1            // InterfaceMethod java/util/Iterator.next:()Ljava/lang/Object;
     872: checkcast     #115                // class org/hl7/fhir/dstu3/model/Encounter$EncounterLocationComponent
     875: astore_3
     876: aload_1
     877: getfield      #114                // Field location:Ljava/util/List;
     880: aload_3
     881: invokevirtual #241                // Method org/hl7/fhir/dstu3/model/Encounter$EncounterLocationComponent.copy:()Lorg/hl7/fhir/dstu3/model/Encounter$EncounterLocationComponent;
     884: invokeinterface #12,  2           // InterfaceMethod java/util/List.add:(Ljava/lang/Object;)Z
     889: pop
     890: goto          857
     893: aload_1
     894: aload_0
     895: getfield      #120                // Field serviceProvider:Lorg/hl7/fhir/dstu3/model/Reference;
     898: ifnonnull     905
     901: aconst_null
     902: goto          912
     905: aload_0
     906: getfield      #120                // Field serviceProvider:Lorg/hl7/fhir/dstu3/model/Reference;
     909: invokevirtual #235                // Method org/hl7/fhir/dstu3/model/Reference.copy:()Lorg/hl7/fhir/dstu3/model/Reference;
     912: putfield      #120                // Field serviceProvider:Lorg/hl7/fhir/dstu3/model/Reference;
     915: aload_1
     916: aload_0
     917: getfield      #125                // Field partOf:Lorg/hl7/fhir/dstu3/model/Reference;
     920: ifnonnull     927
     923: aconst_null
     924: goto          934
     927: aload_0
     928: getfield      #125                // Field partOf:Lorg/hl7/fhir/dstu3/model/Reference;
     931: invokevirtual #235                // Method org/hl7/fhir/dstu3/model/Reference.copy:()Lorg/hl7/fhir/dstu3/model/Reference;
     934: putfield      #125                // Field partOf:Lorg/hl7/fhir/dstu3/model/Reference;
     937: aload_1
     938: areturn

  protected org.hl7.fhir.dstu3.model.Encounter typedCopy();
    Code:
       0: aload_0
       1: invokevirtual #242                // Method copy:()Lorg/hl7/fhir/dstu3/model/Encounter;
       4: areturn

  public boolean equalsDeep(org.hl7.fhir.dstu3.model.Base);
    Code:
       0: aload_0
       1: aload_1
       2: invokespecial #243                // Method org/hl7/fhir/dstu3/model/DomainResource.equalsDeep:(Lorg/hl7/fhir/dstu3/model/Base;)Z
       5: ifne          10
       8: iconst_0
       9: ireturn
      10: aload_1
      11: instanceof    #128                // class org/hl7/fhir/dstu3/model/Encounter
      14: ifne          19
      17: iconst_0
      18: ireturn
      19: aload_1
      20: checkcast     #128                // class org/hl7/fhir/dstu3/model/Encounter
      23: astore_2
      24: aload_0
      25: getfield      #3                  // Field identifier:Ljava/util/List;
      28: aload_2
      29: getfield      #3                  // Field identifier:Ljava/util/List;
      32: iconst_1
      33: invokestatic  #244                // Method compareDeep:(Ljava/util/List;Ljava/util/List;Z)Z
      36: ifeq          343
      39: aload_0
      40: getfield      #2                  // Field status:Lorg/hl7/fhir/dstu3/model/Enumeration;
      43: aload_2
      44: getfield      #2                  // Field status:Lorg/hl7/fhir/dstu3/model/Enumeration;
      47: iconst_1
      48: invokestatic  #245                // Method compareDeep:(Lorg/hl7/fhir/dstu3/model/Base;Lorg/hl7/fhir/dstu3/model/Base;Z)Z
      51: ifeq          343
      54: aload_0
      55: getfield      #30                 // Field statusHistory:Ljava/util/List;
      58: aload_2
      59: getfield      #30                 // Field statusHistory:Ljava/util/List;
      62: iconst_1
      63: invokestatic  #244                // Method compareDeep:(Ljava/util/List;Ljava/util/List;Z)Z
      66: ifeq          343
      69: aload_0
      70: getfield      #36                 // Field class_:Lorg/hl7/fhir/dstu3/model/Coding;
      73: aload_2
      74: getfield      #36                 // Field class_:Lorg/hl7/fhir/dstu3/model/Coding;
      77: iconst_1
      78: invokestatic  #245                // Method compareDeep:(Lorg/hl7/fhir/dstu3/model/Base;Lorg/hl7/fhir/dstu3/model/Base;Z)Z
      81: ifeq          343
      84: aload_0
      85: getfield      #41                 // Field classHistory:Ljava/util/List;
      88: aload_2
      89: getfield      #41                 // Field classHistory:Ljava/util/List;
      92: iconst_1
      93: invokestatic  #244                // Method compareDeep:(Ljava/util/List;Ljava/util/List;Z)Z
      96: ifeq          343
      99: aload_0
     100: getfield      #47                 // Field type:Ljava/util/List;
     103: aload_2
     104: getfield      #47                 // Field type:Ljava/util/List;
     107: iconst_1
     108: invokestatic  #244                // Method compareDeep:(Ljava/util/List;Ljava/util/List;Z)Z
     111: ifeq          343
     114: aload_0
     115: getfield      #53                 // Field priority:Lorg/hl7/fhir/dstu3/model/CodeableConcept;
     118: aload_2
     119: getfield      #53                 // Field priority:Lorg/hl7/fhir/dstu3/model/CodeableConcept;
     122: iconst_1
     123: invokestatic  #245                // Method compareDeep:(Lorg/hl7/fhir/dstu3/model/Base;Lorg/hl7/fhir/dstu3/model/Base;Z)Z
     126: ifeq          343
     129: aload_0
     130: getfield      #55                 // Field subject:Lorg/hl7/fhir/dstu3/model/Reference;
     133: aload_2
     134: getfield      #55                 // Field subject:Lorg/hl7/fhir/dstu3/model/Reference;
     137: iconst_1
     138: invokestatic  #245                // Method compareDeep:(Lorg/hl7/fhir/dstu3/model/Base;Lorg/hl7/fhir/dstu3/model/Base;Z)Z
     141: ifeq          343
     144: aload_0
     145: getfield      #61                 // Field episodeOfCare:Ljava/util/List;
     148: aload_2
     149: getfield      #61                 // Field episodeOfCare:Ljava/util/List;
     152: iconst_1
     153: invokestatic  #244                // Method compareDeep:(Ljava/util/List;Ljava/util/List;Z)Z
     156: ifeq          343
     159: aload_0
     160: getfield      #67                 // Field incomingReferral:Ljava/util/List;
     163: aload_2
     164: getfield      #67                 // Field incomingReferral:Ljava/util/List;
     167: iconst_1
     168: invokestatic  #244                // Method compareDeep:(Ljava/util/List;Ljava/util/List;Z)Z
     171: ifeq          343
     174: aload_0
     175: getfield      #73                 // Field participant:Ljava/util/List;
     178: aload_2
     179: getfield      #73                 // Field participant:Ljava/util/List;
     182: iconst_1
     183: invokestatic  #244                // Method compareDeep:(Ljava/util/List;Ljava/util/List;Z)Z
     186: ifeq          343
     189: aload_0
     190: getfield      #79                 // Field appointment:Lorg/hl7/fhir/dstu3/model/Reference;
     193: aload_2
     194: getfield      #79                 // Field appointment:Lorg/hl7/fhir/dstu3/model/Reference;
     197: iconst_1
     198: invokestatic  #245                // Method compareDeep:(Lorg/hl7/fhir/dstu3/model/Base;Lorg/hl7/fhir/dstu3/model/Base;Z)Z
     201: ifeq          343
     204: aload_0
     205: getfield      #84                 // Field period:Lorg/hl7/fhir/dstu3/model/Period;
     208: aload_2
     209: getfield      #84                 // Field period:Lorg/hl7/fhir/dstu3/model/Period;
     212: iconst_1
     213: invokestatic  #245                // Method compareDeep:(Lorg/hl7/fhir/dstu3/model/Base;Lorg/hl7/fhir/dstu3/model/Base;Z)Z
     216: ifeq          343
     219: aload_0
     220: getfield      #89                 // Field length:Lorg/hl7/fhir/dstu3/model/Duration;
     223: aload_2
     224: getfield      #89                 // Field length:Lorg/hl7/fhir/dstu3/model/Duration;
     227: iconst_1
     228: invokestatic  #245                // Method compareDeep:(Lorg/hl7/fhir/dstu3/model/Base;Lorg/hl7/fhir/dstu3/model/Base;Z)Z
     231: ifeq          343
     234: aload_0
     235: getfield      #94                 // Field reason:Ljava/util/List;
     238: aload_2
     239: getfield      #94                 // Field reason:Ljava/util/List;
     242: iconst_1
     243: invokestatic  #244                // Method compareDeep:(Ljava/util/List;Ljava/util/List;Z)Z
     246: ifeq          343
     249: aload_0
     250: getfield      #97                 // Field diagnosis:Ljava/util/List;
     253: aload_2
     254: getfield      #97                 // Field diagnosis:Ljava/util/List;
     257: iconst_1
     258: invokestatic  #244                // Method compareDeep:(Ljava/util/List;Ljava/util/List;Z)Z
     261: ifeq          343
     264: aload_0
     265: getfield      #103                // Field account:Ljava/util/List;
     268: aload_2
     269: getfield      #103                // Field account:Ljava/util/List;
     272: iconst_1
     273: invokestatic  #244                // Method compareDeep:(Ljava/util/List;Ljava/util/List;Z)Z
     276: ifeq          343
     279: aload_0
     280: getfield      #109                // Field hospitalization:Lorg/hl7/fhir/dstu3/model/Encounter$EncounterHospitalizationComponent;
     283: aload_2
     284: getfield      #109                // Field hospitalization:Lorg/hl7/fhir/dstu3/model/Encounter$EncounterHospitalizationComponent;
     287: iconst_1
     288: invokestatic  #245                // Method compareDeep:(Lorg/hl7/fhir/dstu3/model/Base;Lorg/hl7/fhir/dstu3/model/Base;Z)Z
     291: ifeq          343
     294: aload_0
     295: getfield      #114                // Field location:Ljava/util/List;
     298: aload_2
     299: getfield      #114                // Field location:Ljava/util/List;
     302: iconst_1
     303: invokestatic  #244                // Method compareDeep:(Ljava/util/List;Ljava/util/List;Z)Z
     306: ifeq          343
     309: aload_0
     310: getfield      #120                // Field serviceProvider:Lorg/hl7/fhir/dstu3/model/Reference;
     313: aload_2
     314: getfield      #120                // Field serviceProvider:Lorg/hl7/fhir/dstu3/model/Reference;
     317: iconst_1
     318: invokestatic  #245                // Method compareDeep:(Lorg/hl7/fhir/dstu3/model/Base;Lorg/hl7/fhir/dstu3/model/Base;Z)Z
     321: ifeq          343
     324: aload_0
     325: getfield      #125                // Field partOf:Lorg/hl7/fhir/dstu3/model/Reference;
     328: aload_2
     329: getfield      #125                // Field partOf:Lorg/hl7/fhir/dstu3/model/Reference;
     332: iconst_1
     333: invokestatic  #245                // Method compareDeep:(Lorg/hl7/fhir/dstu3/model/Base;Lorg/hl7/fhir/dstu3/model/Base;Z)Z
     336: ifeq          343
     339: iconst_1
     340: goto          344
     343: iconst_0
     344: ireturn

  public boolean equalsShallow(org.hl7.fhir.dstu3.model.Base);
    Code:
       0: aload_0
       1: aload_1
       2: invokespecial #246                // Method org/hl7/fhir/dstu3/model/DomainResource.equalsShallow:(Lorg/hl7/fhir/dstu3/model/Base;)Z
       5: ifne          10
       8: iconst_0
       9: ireturn
      10: aload_1
      11: instanceof    #128                // class org/hl7/fhir/dstu3/model/Encounter
      14: ifne          19
      17: iconst_0
      18: ireturn
      19: aload_1
      20: checkcast     #128                // class org/hl7/fhir/dstu3/model/Encounter
      23: astore_2
      24: aload_0
      25: getfield      #2                  // Field status:Lorg/hl7/fhir/dstu3/model/Enumeration;
      28: aload_2
      29: getfield      #2                  // Field status:Lorg/hl7/fhir/dstu3/model/Enumeration;
      32: iconst_1
      33: invokestatic  #247                // Method compareValues:(Lorg/hl7/fhir/dstu3/model/PrimitiveType;Lorg/hl7/fhir/dstu3/model/PrimitiveType;Z)Z
      36: ireturn

  public boolean isEmpty();
    Code:
       0: aload_0
       1: invokespecial #248                // Method org/hl7/fhir/dstu3/model/DomainResource.isEmpty:()Z
       4: ifeq          184
       7: bipush        21
       9: anewarray     #249                // class java/lang/Object
      12: dup
      13: iconst_0
      14: aload_0
      15: getfield      #3                  // Field identifier:Ljava/util/List;
      18: aastore
      19: dup
      20: iconst_1
      21: aload_0
      22: getfield      #2                  // Field status:Lorg/hl7/fhir/dstu3/model/Enumeration;
      25: aastore
      26: dup
      27: iconst_2
      28: aload_0
      29: getfield      #30                 // Field statusHistory:Ljava/util/List;
      32: aastore
      33: dup
      34: iconst_3
      35: aload_0
      36: getfield      #36                 // Field class_:Lorg/hl7/fhir/dstu3/model/Coding;
      39: aastore
      40: dup
      41: iconst_4
      42: aload_0
      43: getfield      #41                 // Field classHistory:Ljava/util/List;
      46: aastore
      47: dup
      48: iconst_5
      49: aload_0
      50: getfield      #47                 // Field type:Ljava/util/List;
      53: aastore
      54: dup
      55: bipush        6
      57: aload_0
      58: getfield      #53                 // Field priority:Lorg/hl7/fhir/dstu3/model/CodeableConcept;
      61: aastore
      62: dup
      63: bipush        7
      65: aload_0
      66: getfield      #55                 // Field subject:Lorg/hl7/fhir/dstu3/model/Reference;
      69: aastore
      70: dup
      71: bipush        8
      73: aload_0
      74: getfield      #61                 // Field episodeOfCare:Ljava/util/List;
      77: aastore
      78: dup
      79: bipush        9
      81: aload_0
      82: getfield      #67                 // Field incomingReferral:Ljava/util/List;
      85: aastore
      86: dup
      87: bipush        10
      89: aload_0
      90: getfield      #73                 // Field participant:Ljava/util/List;
      93: aastore
      94: dup
      95: bipush        11
      97: aload_0
      98: getfield      #79                 // Field appointment:Lorg/hl7/fhir/dstu3/model/Reference;
     101: aastore
     102: dup
     103: bipush        12
     105: aload_0
     106: getfield      #84                 // Field period:Lorg/hl7/fhir/dstu3/model/Period;
     109: aastore
     110: dup
     111: bipush        13
     113: aload_0
     114: getfield      #89                 // Field length:Lorg/hl7/fhir/dstu3/model/Duration;
     117: aastore
     118: dup
     119: bipush        14
     121: aload_0
     122: getfield      #94                 // Field reason:Ljava/util/List;
     125: aastore
     126: dup
     127: bipush        15
     129: aload_0
     130: getfield      #97                 // Field diagnosis:Ljava/util/List;
     133: aastore
     134: dup
     135: bipush        16
     137: aload_0
     138: getfield      #103                // Field account:Ljava/util/List;
     141: aastore
     142: dup
     143: bipush        17
     145: aload_0
     146: getfield      #109                // Field hospitalization:Lorg/hl7/fhir/dstu3/model/Encounter$EncounterHospitalizationComponent;
     149: aastore
     150: dup
     151: bipush        18
     153: aload_0
     154: getfield      #114                // Field location:Ljava/util/List;
     157: aastore
     158: dup
     159: bipush        19
     161: aload_0
     162: getfield      #120                // Field serviceProvider:Lorg/hl7/fhir/dstu3/model/Reference;
     165: aastore
     166: dup
     167: bipush        20
     169: aload_0
     170: getfield      #125                // Field partOf:Lorg/hl7/fhir/dstu3/model/Reference;
     173: aastore
     174: invokestatic  #250                // Method ca/uhn/fhir/util/ElementUtil.isEmpty:([Ljava/lang/Object;)Z
     177: ifeq          184
     180: iconst_1
     181: goto          185
     184: iconst_0
     185: ireturn

  public org.hl7.fhir.dstu3.model.ResourceType getResourceType();
    Code:
       0: getstatic     #251                // Field org/hl7/fhir/dstu3/model/ResourceType.Encounter:Lorg/hl7/fhir/dstu3/model/ResourceType;
       3: areturn

  public org.hl7.fhir.dstu3.model.DomainResource copy();
    Code:
       0: aload_0
       1: invokevirtual #242                // Method copy:()Lorg/hl7/fhir/dstu3/model/Encounter;
       4: areturn

  public org.hl7.fhir.dstu3.model.Resource copy();
    Code:
       0: aload_0
       1: invokevirtual #242                // Method copy:()Lorg/hl7/fhir/dstu3/model/Encounter;
       4: areturn

  static {};
    Code:
       0: new           #252                // class ca/uhn/fhir/rest/gclient/DateClientParam
       3: dup
       4: ldc           #253                // String date
       6: invokespecial #254                // Method ca/uhn/fhir/rest/gclient/DateClientParam."<init>":(Ljava/lang/String;)V
       9: putstatic     #255                // Field DATE:Lca/uhn/fhir/rest/gclient/DateClientParam;
      12: new           #256                // class ca/uhn/fhir/rest/gclient/TokenClientParam
      15: dup
      16: ldc           #132                // String identifier
      18: invokespecial #257                // Method ca/uhn/fhir/rest/gclient/TokenClientParam."<init>":(Ljava/lang/String;)V
      21: putstatic     #258                // Field IDENTIFIER:Lca/uhn/fhir/rest/gclient/TokenClientParam;
      24: new           #256                // class ca/uhn/fhir/rest/gclient/TokenClientParam
      27: dup
      28: ldc           #175                // String reason
      30: invokespecial #257                // Method ca/uhn/fhir/rest/gclient/TokenClientParam."<init>":(Ljava/lang/String;)V
      33: putstatic     #259                // Field REASON:Lca/uhn/fhir/rest/gclient/TokenClientParam;
      36: new           #260                // class ca/uhn/fhir/rest/gclient/ReferenceClientParam
      39: dup
      40: ldc_w         #261                // String episodeofcare
      43: invokespecial #262                // Method ca/uhn/fhir/rest/gclient/ReferenceClientParam."<init>":(Ljava/lang/String;)V
      46: putstatic     #263                // Field EPISODEOFCARE:Lca/uhn/fhir/rest/gclient/ReferenceClientParam;
      49: new           #264                // class ca/uhn/fhir/model/api/Include
      52: dup
      53: ldc_w         #265                // String Encounter:episodeofcare
      56: invokespecial #266                // Method ca/uhn/fhir/model/api/Include."<init>":(Ljava/lang/String;)V
      59: invokevirtual #267                // Method ca/uhn/fhir/model/api/Include.toLocked:()Lca/uhn/fhir/model/api/Include;
      62: putstatic     #268                // Field INCLUDE_EPISODEOFCARE:Lca/uhn/fhir/model/api/Include;
      65: new           #256                // class ca/uhn/fhir/rest/gclient/TokenClientParam
      68: dup
      69: ldc_w         #269                // String participant-type
      72: invokespecial #257                // Method ca/uhn/fhir/rest/gclient/TokenClientParam."<init>":(Ljava/lang/String;)V
      75: putstatic     #270                // Field PARTICIPANT_TYPE:Lca/uhn/fhir/rest/gclient/TokenClientParam;
      78: new           #260                // class ca/uhn/fhir/rest/gclient/ReferenceClientParam
      81: dup
      82: ldc_w         #271                // String incomingreferral
      85: invokespecial #262                // Method ca/uhn/fhir/rest/gclient/ReferenceClientParam."<init>":(Ljava/lang/String;)V
      88: putstatic     #272                // Field INCOMINGREFERRAL:Lca/uhn/fhir/rest/gclient/ReferenceClientParam;
      91: new           #264                // class ca/uhn/fhir/model/api/Include
      94: dup
      95: ldc_w         #273                // String Encounter:incomingreferral
      98: invokespecial #266                // Method ca/uhn/fhir/model/api/Include."<init>":(Ljava/lang/String;)V
     101: invokevirtual #267                // Method ca/uhn/fhir/model/api/Include.toLocked:()Lca/uhn/fhir/model/api/Include;
     104: putstatic     #274                // Field INCLUDE_INCOMINGREFERRAL:Lca/uhn/fhir/model/api/Include;
     107: new           #260                // class ca/uhn/fhir/rest/gclient/ReferenceClientParam
     110: dup
     111: ldc_w         #275                // String practitioner
     114: invokespecial #262                // Method ca/uhn/fhir/rest/gclient/ReferenceClientParam."<init>":(Ljava/lang/String;)V
     117: putstatic     #276                // Field PRACTITIONER:Lca/uhn/fhir/rest/gclient/ReferenceClientParam;
     120: new           #264                // class ca/uhn/fhir/model/api/Include
     123: dup
     124: ldc_w         #277                // String Encounter:practitioner
     127: invokespecial #266                // Method ca/uhn/fhir/model/api/Include."<init>":(Ljava/lang/String;)V
     130: invokevirtual #267                // Method ca/uhn/fhir/model/api/Include.toLocked:()Lca/uhn/fhir/model/api/Include;
     133: putstatic     #278                // Field INCLUDE_PRACTITIONER:Lca/uhn/fhir/model/api/Include;
     136: new           #260                // class ca/uhn/fhir/rest/gclient/ReferenceClientParam
     139: dup
     140: ldc           #155                // String subject
     142: invokespecial #262                // Method ca/uhn/fhir/rest/gclient/ReferenceClientParam."<init>":(Ljava/lang/String;)V
     145: putstatic     #279                // Field SUBJECT:Lca/uhn/fhir/rest/gclient/ReferenceClientParam;
     148: new           #264                // class ca/uhn/fhir/model/api/Include
     151: dup
     152: ldc_w         #280                // String Encounter:subject
     155: invokespecial #266                // Method ca/uhn/fhir/model/api/Include."<init>":(Ljava/lang/String;)V
     158: invokevirtual #267                // Method ca/uhn/fhir/model/api/Include.toLocked:()Lca/uhn/fhir/model/api/Include;
     161: putstatic     #281                // Field INCLUDE_SUBJECT:Lca/uhn/fhir/model/api/Include;
     164: new           #282                // class ca/uhn/fhir/rest/gclient/NumberClientParam
     167: dup
     168: ldc           #172                // String length
     170: invokespecial #283                // Method ca/uhn/fhir/rest/gclient/NumberClientParam."<init>":(Ljava/lang/String;)V
     173: putstatic     #284                // Field LENGTH:Lca/uhn/fhir/rest/gclient/NumberClientParam;
     176: new           #260                // class ca/uhn/fhir/rest/gclient/ReferenceClientParam
     179: dup
     180: ldc           #177                // String diagnosis
     182: invokespecial #262                // Method ca/uhn/fhir/rest/gclient/ReferenceClientParam."<init>":(Ljava/lang/String;)V
     185: putstatic     #285                // Field DIAGNOSIS:Lca/uhn/fhir/rest/gclient/ReferenceClientParam;
     188: new           #264                // class ca/uhn/fhir/model/api/Include
     191: dup
     192: ldc_w         #286                // String Encounter:diagnosis
     195: invokespecial #266                // Method ca/uhn/fhir/model/api/Include."<init>":(Ljava/lang/String;)V
     198: invokevirtual #267                // Method ca/uhn/fhir/model/api/Include.toLocked:()Lca/uhn/fhir/model/api/Include;
     201: putstatic     #287                // Field INCLUDE_DIAGNOSIS:Lca/uhn/fhir/model/api/Include;
     204: new           #260                // class ca/uhn/fhir/rest/gclient/ReferenceClientParam
     207: dup
     208: ldc           #166                // String appointment
     210: invokespecial #262                // Method ca/uhn/fhir/rest/gclient/ReferenceClientParam."<init>":(Ljava/lang/String;)V
     213: putstatic     #288                // Field APPOINTMENT:Lca/uhn/fhir/rest/gclient/ReferenceClientParam;
     216: new           #264                // class ca/uhn/fhir/model/api/Include
     219: dup
     220: ldc_w         #289                // String Encounter:appointment
     223: invokespecial #266                // Method ca/uhn/fhir/model/api/Include."<init>":(Ljava/lang/String;)V
     226: invokevirtual #267                // Method ca/uhn/fhir/model/api/Include.toLocked:()Lca/uhn/fhir/model/api/Include;
     229: putstatic     #290                // Field INCLUDE_APPOINTMENT:Lca/uhn/fhir/model/api/Include;
     232: new           #260                // class ca/uhn/fhir/rest/gclient/ReferenceClientParam
     235: dup
     236: ldc_w         #291                // String part-of
     239: invokespecial #262                // Method ca/uhn/fhir/rest/gclient/ReferenceClientParam."<init>":(Ljava/lang/String;)V
     242: putstatic     #292                // Field PART_OF:Lca/uhn/fhir/rest/gclient/ReferenceClientParam;
     245: new           #264                // class ca/uhn/fhir/model/api/Include
     248: dup
     249: ldc_w         #293                // String Encounter:part-of
     252: invokespecial #266                // Method ca/uhn/fhir/model/api/Include."<init>":(Ljava/lang/String;)V
     255: invokevirtual #267                // Method ca/uhn/fhir/model/api/Include.toLocked:()Lca/uhn/fhir/model/api/Include;
     258: putstatic     #294                // Field INCLUDE_PART_OF:Lca/uhn/fhir/model/api/Include;
     261: new           #256                // class ca/uhn/fhir/rest/gclient/TokenClientParam
     264: dup
     265: ldc           #150                // String type
     267: invokespecial #257                // Method ca/uhn/fhir/rest/gclient/TokenClientParam."<init>":(Ljava/lang/String;)V
     270: putstatic     #295                // Field TYPE:Lca/uhn/fhir/rest/gclient/TokenClientParam;
     273: new           #260                // class ca/uhn/fhir/rest/gclient/ReferenceClientParam
     276: dup
     277: ldc           #164                // String participant
     279: invokespecial #262                // Method ca/uhn/fhir/rest/gclient/ReferenceClientParam."<init>":(Ljava/lang/String;)V
     282: putstatic     #296                // Field PARTICIPANT:Lca/uhn/fhir/rest/gclient/ReferenceClientParam;
     285: new           #264                // class ca/uhn/fhir/model/api/Include
     288: dup
     289: ldc_w         #297                // String Encounter:participant
     292: invokespecial #266                // Method ca/uhn/fhir/model/api/Include."<init>":(Ljava/lang/String;)V
     295: invokevirtual #267                // Method ca/uhn/fhir/model/api/Include.toLocked:()Lca/uhn/fhir/model/api/Include;
     298: putstatic     #298                // Field INCLUDE_PARTICIPANT:Lca/uhn/fhir/model/api/Include;
     301: new           #260                // class ca/uhn/fhir/rest/gclient/ReferenceClientParam
     304: dup
     305: ldc_w         #299                // String patient
     308: invokespecial #262                // Method ca/uhn/fhir/rest/gclient/ReferenceClientParam."<init>":(Ljava/lang/String;)V
     311: putstatic     #300                // Field PATIENT:Lca/uhn/fhir/rest/gclient/ReferenceClientParam;
     314: new           #264                // class ca/uhn/fhir/model/api/Include
     317: dup
     318: ldc_w         #301                // String Encounter:patient
     321: invokespecial #266                // Method ca/uhn/fhir/model/api/Include."<init>":(Ljava/lang/String;)V
     324: invokevirtual #267                // Method ca/uhn/fhir/model/api/Include.toLocked:()Lca/uhn/fhir/model/api/Include;
     327: putstatic     #302                // Field INCLUDE_PATIENT:Lca/uhn/fhir/model/api/Include;
     330: new           #252                // class ca/uhn/fhir/rest/gclient/DateClientParam
     333: dup
     334: ldc_w         #303                // String location-period
     337: invokespecial #254                // Method ca/uhn/fhir/rest/gclient/DateClientParam."<init>":(Ljava/lang/String;)V
     340: putstatic     #304                // Field LOCATION_PERIOD:Lca/uhn/fhir/rest/gclient/DateClientParam;
     343: new           #260                // class ca/uhn/fhir/rest/gclient/ReferenceClientParam
     346: dup
     347: ldc           #184                // String location
     349: invokespecial #262                // Method ca/uhn/fhir/rest/gclient/ReferenceClientParam."<init>":(Ljava/lang/String;)V
     352: putstatic     #305                // Field LOCATION:Lca/uhn/fhir/rest/gclient/ReferenceClientParam;
     355: new           #264                // class ca/uhn/fhir/model/api/Include
     358: dup
     359: ldc_w         #306                // String Encounter:location
     362: invokespecial #266                // Method ca/uhn/fhir/model/api/Include."<init>":(Ljava/lang/String;)V
     365: invokevirtual #267                // Method ca/uhn/fhir/model/api/Include.toLocked:()Lca/uhn/fhir/model/api/Include;
     368: putstatic     #307                // Field INCLUDE_LOCATION:Lca/uhn/fhir/model/api/Include;
     371: new           #260                // class ca/uhn/fhir/rest/gclient/ReferenceClientParam
     374: dup
     375: ldc_w         #308                // String service-provider
     378: invokespecial #262                // Method ca/uhn/fhir/rest/gclient/ReferenceClientParam."<init>":(Ljava/lang/String;)V
     381: putstatic     #309                // Field SERVICE_PROVIDER:Lca/uhn/fhir/rest/gclient/ReferenceClientParam;
     384: new           #264                // class ca/uhn/fhir/model/api/Include
     387: dup
     388: ldc_w         #310                // String Encounter:service-provider
     391: invokespecial #266                // Method ca/uhn/fhir/model/api/Include."<init>":(Ljava/lang/String;)V
     394: invokevirtual #267                // Method ca/uhn/fhir/model/api/Include.toLocked:()Lca/uhn/fhir/model/api/Include;
     397: putstatic     #311                // Field INCLUDE_SERVICE_PROVIDER:Lca/uhn/fhir/model/api/Include;
     400: new           #256                // class ca/uhn/fhir/rest/gclient/TokenClientParam
     403: dup
     404: ldc_w         #312                // String special-arrangement
     407: invokespecial #257                // Method ca/uhn/fhir/rest/gclient/TokenClientParam."<init>":(Ljava/lang/String;)V
     410: putstatic     #313                // Field SPECIAL_ARRANGEMENT:Lca/uhn/fhir/rest/gclient/TokenClientParam;
     413: new           #256                // class ca/uhn/fhir/rest/gclient/TokenClientParam
     416: dup
     417: ldc           #145                // String class
     419: invokespecial #257                // Method ca/uhn/fhir/rest/gclient/TokenClientParam."<init>":(Ljava/lang/String;)V
     422: putstatic     #314                // Field CLASS:Lca/uhn/fhir/rest/gclient/TokenClientParam;
     425: new           #256                // class ca/uhn/fhir/rest/gclient/TokenClientParam
     428: dup
     429: ldc           #138                // String status
     431: invokespecial #257                // Method ca/uhn/fhir/rest/gclient/TokenClientParam."<init>":(Ljava/lang/String;)V
     434: putstatic     #315                // Field STATUS:Lca/uhn/fhir/rest/gclient/TokenClientParam;
     437: return
}
