Compiled from "ExpansionProfile.java"
public final class org.hl7.fhir.dstu3.model.ExpansionProfile$SystemVersionProcessingMode extends java.lang.Enum<org.hl7.fhir.dstu3.model.ExpansionProfile$SystemVersionProcessingMode> {
  public static final org.hl7.fhir.dstu3.model.ExpansionProfile$SystemVersionProcessingMode DEFAULT;

  public static final org.hl7.fhir.dstu3.model.ExpansionProfile$SystemVersionProcessingMode CHECK;

  public static final org.hl7.fhir.dstu3.model.ExpansionProfile$SystemVersionProcessingMode OVERRIDE;

  public static final org.hl7.fhir.dstu3.model.ExpansionProfile$SystemVersionProcessingMode NULL;

  private static final org.hl7.fhir.dstu3.model.ExpansionProfile$SystemVersionProcessingMode[] $VALUES;

  public static org.hl7.fhir.dstu3.model.ExpansionProfile$SystemVersionProcessingMode[] values();
    Code:
       0: getstatic     #1                  // Field $VALUES:[Lorg/hl7/fhir/dstu3/model/ExpansionProfile$SystemVersionProcessingMode;
       3: invokevirtual #2                  // Method "[Lorg/hl7/fhir/dstu3/model/ExpansionProfile$SystemVersionProcessingMode;".clone:()Ljava/lang/Object;
       6: checkcast     #3                  // class "[Lorg/hl7/fhir/dstu3/model/ExpansionProfile$SystemVersionProcessingMode;"
       9: areturn

  public static org.hl7.fhir.dstu3.model.ExpansionProfile$SystemVersionProcessingMode valueOf(java.lang.String);
    Code:
       0: ldc           #4                  // class org/hl7/fhir/dstu3/model/ExpansionProfile$SystemVersionProcessingMode
       2: aload_0
       3: invokestatic  #5                  // Method java/lang/Enum.valueOf:(Ljava/lang/Class;Ljava/lang/String;)Ljava/lang/Enum;
       6: checkcast     #4                  // class org/hl7/fhir/dstu3/model/ExpansionProfile$SystemVersionProcessingMode
       9: areturn

  private org.hl7.fhir.dstu3.model.ExpansionProfile$SystemVersionProcessingMode();
    Code:
       0: aload_0
       1: aload_1
       2: iload_2
       3: invokespecial #6                  // Method java/lang/Enum."<init>":(Ljava/lang/String;I)V
       6: return

  public static org.hl7.fhir.dstu3.model.ExpansionProfile$SystemVersionProcessingMode fromCode(java.lang.String) throws org.hl7.fhir.exceptions.FHIRException;
    Code:
       0: aload_0
       1: ifnull        13
       4: ldc           #7                  // String
       6: aload_0
       7: invokevirtual #8                  // Method java/lang/String.equals:(Ljava/lang/Object;)Z
      10: ifeq          15
      13: aconst_null
      14: areturn
      15: ldc           #9                  // String default
      17: aload_0
      18: invokevirtual #8                  // Method java/lang/String.equals:(Ljava/lang/Object;)Z
      21: ifeq          28
      24: getstatic     #10                 // Field DEFAULT:Lorg/hl7/fhir/dstu3/model/ExpansionProfile$SystemVersionProcessingMode;
      27: areturn
      28: ldc           #11                 // String check
      30: aload_0
      31: invokevirtual #8                  // Method java/lang/String.equals:(Ljava/lang/Object;)Z
      34: ifeq          41
      37: getstatic     #12                 // Field CHECK:Lorg/hl7/fhir/dstu3/model/ExpansionProfile$SystemVersionProcessingMode;
      40: areturn
      41: ldc           #13                 // String override
      43: aload_0
      44: invokevirtual #8                  // Method java/lang/String.equals:(Ljava/lang/Object;)Z
      47: ifeq          54
      50: getstatic     #14                 // Field OVERRIDE:Lorg/hl7/fhir/dstu3/model/ExpansionProfile$SystemVersionProcessingMode;
      53: areturn
      54: invokestatic  #15                 // Method org/hl7/fhir/dstu3/model/Configuration.isAcceptInvalidEnums:()Z
      57: ifeq          62
      60: aconst_null
      61: areturn
      62: new           #16                 // class org/hl7/fhir/exceptions/FHIRException
      65: dup
      66: new           #17                 // class java/lang/StringBuilder
      69: dup
      70: invokespecial #18                 // Method java/lang/StringBuilder."<init>":()V
      73: ldc           #19                 // String Unknown SystemVersionProcessingMode code \'
      75: invokevirtual #20                 // Method java/lang/StringBuilder.append:(Ljava/lang/String;)Ljava/lang/StringBuilder;
      78: aload_0
      79: invokevirtual #20                 // Method java/lang/StringBuilder.append:(Ljava/lang/String;)Ljava/lang/StringBuilder;
      82: ldc           #21                 // String \'
      84: invokevirtual #20                 // Method java/lang/StringBuilder.append:(Ljava/lang/String;)Ljava/lang/StringBuilder;
      87: invokevirtual #22                 // Method java/lang/StringBuilder.toString:()Ljava/lang/String;
      90: invokespecial #23                 // Method org/hl7/fhir/exceptions/FHIRException."<init>":(Ljava/lang/String;)V
      93: athrow

  public java.lang.String toCode();
    Code:
       0: getstatic     #24                 // Field org/hl7/fhir/dstu3/model/ExpansionProfile$1.$SwitchMap$org$hl7$fhir$dstu3$model$ExpansionProfile$SystemVersionProcessingMode:[I
       3: aload_0
       4: invokevirtual #25                 // Method ordinal:()I
       7: iaload
       8: tableswitch   { // 1 to 4
                     1: 40
                     2: 43
                     3: 46
                     4: 49
               default: 51
          }
      40: ldc           #9                  // String default
      42: areturn
      43: ldc           #11                 // String check
      45: areturn
      46: ldc           #13                 // String override
      48: areturn
      49: aconst_null
      50: areturn
      51: ldc           #26                 // String ?
      53: areturn

  public java.lang.String getSystem();
    Code:
       0: getstatic     #24                 // Field org/hl7/fhir/dstu3/model/ExpansionProfile$1.$SwitchMap$org$hl7$fhir$dstu3$model$ExpansionProfile$SystemVersionProcessingMode:[I
       3: aload_0
       4: invokevirtual #25                 // Method ordinal:()I
       7: iaload
       8: tableswitch   { // 1 to 4
                     1: 40
                     2: 43
                     3: 46
                     4: 49
               default: 51
          }
      40: ldc           #27                 // String http://hl7.org/fhir/system-version-processing-mode
      42: areturn
      43: ldc           #27                 // String http://hl7.org/fhir/system-version-processing-mode
      45: areturn
      46: ldc           #27                 // String http://hl7.org/fhir/system-version-processing-mode
      48: areturn
      49: aconst_null
      50: areturn
      51: ldc           #26                 // String ?
      53: areturn

  public java.lang.String getDefinition();
    Code:
       0: getstatic     #24                 // Field org/hl7/fhir/dstu3/model/ExpansionProfile$1.$SwitchMap$org$hl7$fhir$dstu3$model$ExpansionProfile$SystemVersionProcessingMode:[I
       3: aload_0
       4: invokevirtual #25                 // Method ordinal:()I
       7: iaload
       8: tableswitch   { // 1 to 4
                     1: 40
                     2: 43
                     3: 46
                     4: 49
               default: 51
          }
      40: ldc           #28                 // String Use this version of the code system if a value set doesn\'t specify a version
      42: areturn
      43: ldc           #29                 // String Use this version of the code system. If a value set specifies a different version, the expansion operation should fail
      45: areturn
      46: ldc           #30                 // String Use this version of the code system irrespective of which version is specified by a value set. Note that this has obvious safety issues, in that it may result in a value set expansion giving a different list of codes that is both wrong and unsafe, and implementers should only use this capability reluctantly. It primarily exists to deal with situations where specifications have fallen into decay as time passes. If a  version is override, the version used SHALL explicitly be represented in the expansion parameters
      48: areturn
      49: aconst_null
      50: areturn
      51: ldc           #26                 // String ?
      53: areturn

  public java.lang.String getDisplay();
    Code:
       0: getstatic     #24                 // Field org/hl7/fhir/dstu3/model/ExpansionProfile$1.$SwitchMap$org$hl7$fhir$dstu3$model$ExpansionProfile$SystemVersionProcessingMode:[I
       3: aload_0
       4: invokevirtual #25                 // Method ordinal:()I
       7: iaload
       8: tableswitch   { // 1 to 4
                     1: 40
                     2: 43
                     3: 46
                     4: 49
               default: 51
          }
      40: ldc           #31                 // String Default Version
      42: areturn
      43: ldc           #32                 // String Check ValueSet Version
      45: areturn
      46: ldc           #33                 // String Override ValueSet Version
      48: areturn
      49: aconst_null
      50: areturn
      51: ldc           #26                 // String ?
      53: areturn

  static {};
    Code:
       0: new           #4                  // class org/hl7/fhir/dstu3/model/ExpansionProfile$SystemVersionProcessingMode
       3: dup
       4: ldc           #34                 // String DEFAULT
       6: iconst_0
       7: invokespecial #35                 // Method "<init>":(Ljava/lang/String;I)V
      10: putstatic     #10                 // Field DEFAULT:Lorg/hl7/fhir/dstu3/model/ExpansionProfile$SystemVersionProcessingMode;
      13: new           #4                  // class org/hl7/fhir/dstu3/model/ExpansionProfile$SystemVersionProcessingMode
      16: dup
      17: ldc           #36                 // String CHECK
      19: iconst_1
      20: invokespecial #35                 // Method "<init>":(Ljava/lang/String;I)V
      23: putstatic     #12                 // Field CHECK:Lorg/hl7/fhir/dstu3/model/ExpansionProfile$SystemVersionProcessingMode;
      26: new           #4                  // class org/hl7/fhir/dstu3/model/ExpansionProfile$SystemVersionProcessingMode
      29: dup
      30: ldc           #37                 // String OVERRIDE
      32: iconst_2
      33: invokespecial #35                 // Method "<init>":(Ljava/lang/String;I)V
      36: putstatic     #14                 // Field OVERRIDE:Lorg/hl7/fhir/dstu3/model/ExpansionProfile$SystemVersionProcessingMode;
      39: new           #4                  // class org/hl7/fhir/dstu3/model/ExpansionProfile$SystemVersionProcessingMode
      42: dup
      43: ldc           #38                 // String NULL
      45: iconst_3
      46: invokespecial #35                 // Method "<init>":(Ljava/lang/String;I)V
      49: putstatic     #39                 // Field NULL:Lorg/hl7/fhir/dstu3/model/ExpansionProfile$SystemVersionProcessingMode;
      52: iconst_4
      53: anewarray     #4                  // class org/hl7/fhir/dstu3/model/ExpansionProfile$SystemVersionProcessingMode
      56: dup
      57: iconst_0
      58: getstatic     #10                 // Field DEFAULT:Lorg/hl7/fhir/dstu3/model/ExpansionProfile$SystemVersionProcessingMode;
      61: aastore
      62: dup
      63: iconst_1
      64: getstatic     #12                 // Field CHECK:Lorg/hl7/fhir/dstu3/model/ExpansionProfile$SystemVersionProcessingMode;
      67: aastore
      68: dup
      69: iconst_2
      70: getstatic     #14                 // Field OVERRIDE:Lorg/hl7/fhir/dstu3/model/ExpansionProfile$SystemVersionProcessingMode;
      73: aastore
      74: dup
      75: iconst_3
      76: getstatic     #39                 // Field NULL:Lorg/hl7/fhir/dstu3/model/ExpansionProfile$SystemVersionProcessingMode;
      79: aastore
      80: putstatic     #1                  // Field $VALUES:[Lorg/hl7/fhir/dstu3/model/ExpansionProfile$SystemVersionProcessingMode;
      83: return
}
