Compiled from "Goal.java"
public class org.hl7.fhir.dstu3.model.Goal extends org.hl7.fhir.dstu3.model.DomainResource {
  protected java.util.List<org.hl7.fhir.dstu3.model.Identifier> identifier;

  protected org.hl7.fhir.dstu3.model.Enumeration<org.hl7.fhir.dstu3.model.Goal$GoalStatus> status;

  protected java.util.List<org.hl7.fhir.dstu3.model.CodeableConcept> category;

  protected org.hl7.fhir.dstu3.model.CodeableConcept priority;

  protected org.hl7.fhir.dstu3.model.CodeableConcept description;

  protected org.hl7.fhir.dstu3.model.Reference subject;

  protected org.hl7.fhir.dstu3.model.Resource subjectTarget;

  protected org.hl7.fhir.dstu3.model.Type start;

  protected org.hl7.fhir.dstu3.model.Goal$GoalTargetComponent target;

  protected org.hl7.fhir.dstu3.model.DateType statusDate;

  protected org.hl7.fhir.dstu3.model.StringType statusReason;

  protected org.hl7.fhir.dstu3.model.Reference expressedBy;

  protected org.hl7.fhir.dstu3.model.Resource expressedByTarget;

  protected java.util.List<org.hl7.fhir.dstu3.model.Reference> addresses;

  protected java.util.List<org.hl7.fhir.dstu3.model.Resource> addressesTarget;

  protected java.util.List<org.hl7.fhir.dstu3.model.Annotation> note;

  protected java.util.List<org.hl7.fhir.dstu3.model.CodeableConcept> outcomeCode;

  protected java.util.List<org.hl7.fhir.dstu3.model.Reference> outcomeReference;

  protected java.util.List<org.hl7.fhir.dstu3.model.Observation> outcomeReferenceTarget;

  private static final long serialVersionUID;

  public static final java.lang.String SP_IDENTIFIER;

  public static final ca.uhn.fhir.rest.gclient.TokenClientParam IDENTIFIER;

  public static final java.lang.String SP_PATIENT;

  public static final ca.uhn.fhir.rest.gclient.ReferenceClientParam PATIENT;

  public static final ca.uhn.fhir.model.api.Include INCLUDE_PATIENT;

  public static final java.lang.String SP_SUBJECT;

  public static final ca.uhn.fhir.rest.gclient.ReferenceClientParam SUBJECT;

  public static final ca.uhn.fhir.model.api.Include INCLUDE_SUBJECT;

  public static final java.lang.String SP_START_DATE;

  public static final ca.uhn.fhir.rest.gclient.DateClientParam START_DATE;

  public static final java.lang.String SP_CATEGORY;

  public static final ca.uhn.fhir.rest.gclient.TokenClientParam CATEGORY;

  public static final java.lang.String SP_TARGET_DATE;

  public static final ca.uhn.fhir.rest.gclient.DateClientParam TARGET_DATE;

  public static final java.lang.String SP_STATUS;

  public static final ca.uhn.fhir.rest.gclient.TokenClientParam STATUS;

  public org.hl7.fhir.dstu3.model.Goal();
    Code:
       0: aload_0
       1: invokespecial #1                  // Method org/hl7/fhir/dstu3/model/DomainResource."<init>":()V
       4: return

  public org.hl7.fhir.dstu3.model.Goal(org.hl7.fhir.dstu3.model.Enumeration<org.hl7.fhir.dstu3.model.Goal$GoalStatus>, org.hl7.fhir.dstu3.model.CodeableConcept);
    Code:
       0: aload_0
       1: invokespecial #1                  // Method org/hl7/fhir/dstu3/model/DomainResource."<init>":()V
       4: aload_0
       5: aload_1
       6: putfield      #2                  // Field status:Lorg/hl7/fhir/dstu3/model/Enumeration;
       9: aload_0
      10: aload_2
      11: putfield      #3                  // Field description:Lorg/hl7/fhir/dstu3/model/CodeableConcept;
      14: return

  public java.util.List<org.hl7.fhir.dstu3.model.Identifier> getIdentifier();
    Code:
       0: aload_0
       1: getfield      #4                  // Field identifier:Ljava/util/List;
       4: ifnonnull     18
       7: aload_0
       8: new           #5                  // class java/util/ArrayList
      11: dup
      12: invokespecial #6                  // Method java/util/ArrayList."<init>":()V
      15: putfield      #4                  // Field identifier:Ljava/util/List;
      18: aload_0
      19: getfield      #4                  // Field identifier:Ljava/util/List;
      22: areturn

  public org.hl7.fhir.dstu3.model.Goal setIdentifier(java.util.List<org.hl7.fhir.dstu3.model.Identifier>);
    Code:
       0: aload_0
       1: aload_1
       2: putfield      #4                  // Field identifier:Ljava/util/List;
       5: aload_0
       6: areturn

  public boolean hasIdentifier();
    Code:
       0: aload_0
       1: getfield      #4                  // Field identifier:Ljava/util/List;
       4: ifnonnull     9
       7: iconst_0
       8: ireturn
       9: aload_0
      10: getfield      #4                  // Field identifier:Ljava/util/List;
      13: invokeinterface #7,  1            // InterfaceMethod java/util/List.iterator:()Ljava/util/Iterator;
      18: astore_1
      19: aload_1
      20: invokeinterface #8,  1            // InterfaceMethod java/util/Iterator.hasNext:()Z
      25: ifeq          50
      28: aload_1
      29: invokeinterface #9,  1            // InterfaceMethod java/util/Iterator.next:()Ljava/lang/Object;
      34: checkcast     #10                 // class org/hl7/fhir/dstu3/model/Identifier
      37: astore_2
      38: aload_2
      39: invokevirtual #11                 // Method org/hl7/fhir/dstu3/model/Identifier.isEmpty:()Z
      42: ifne          47
      45: iconst_1
      46: ireturn
      47: goto          19
      50: iconst_0
      51: ireturn

  public org.hl7.fhir.dstu3.model.Identifier addIdentifier();
    Code:
       0: new           #10                 // class org/hl7/fhir/dstu3/model/Identifier
       3: dup
       4: invokespecial #12                 // Method org/hl7/fhir/dstu3/model/Identifier."<init>":()V
       7: astore_1
       8: aload_0
       9: getfield      #4                  // Field identifier:Ljava/util/List;
      12: ifnonnull     26
      15: aload_0
      16: new           #5                  // class java/util/ArrayList
      19: dup
      20: invokespecial #6                  // Method java/util/ArrayList."<init>":()V
      23: putfield      #4                  // Field identifier:Ljava/util/List;
      26: aload_0
      27: getfield      #4                  // Field identifier:Ljava/util/List;
      30: aload_1
      31: invokeinterface #13,  2           // InterfaceMethod java/util/List.add:(Ljava/lang/Object;)Z
      36: pop
      37: aload_1
      38: areturn

  public org.hl7.fhir.dstu3.model.Goal addIdentifier(org.hl7.fhir.dstu3.model.Identifier);
    Code:
       0: aload_1
       1: ifnonnull     6
       4: aload_0
       5: areturn
       6: aload_0
       7: getfield      #4                  // Field identifier:Ljava/util/List;
      10: ifnonnull     24
      13: aload_0
      14: new           #5                  // class java/util/ArrayList
      17: dup
      18: invokespecial #6                  // Method java/util/ArrayList."<init>":()V
      21: putfield      #4                  // Field identifier:Ljava/util/List;
      24: aload_0
      25: getfield      #4                  // Field identifier:Ljava/util/List;
      28: aload_1
      29: invokeinterface #13,  2           // InterfaceMethod java/util/List.add:(Ljava/lang/Object;)Z
      34: pop
      35: aload_0
      36: areturn

  public org.hl7.fhir.dstu3.model.Identifier getIdentifierFirstRep();
    Code:
       0: aload_0
       1: invokevirtual #14                 // Method getIdentifier:()Ljava/util/List;
       4: invokeinterface #15,  1           // InterfaceMethod java/util/List.isEmpty:()Z
       9: ifeq          17
      12: aload_0
      13: invokevirtual #16                 // Method addIdentifier:()Lorg/hl7/fhir/dstu3/model/Identifier;
      16: pop
      17: aload_0
      18: invokevirtual #14                 // Method getIdentifier:()Ljava/util/List;
      21: iconst_0
      22: invokeinterface #17,  2           // InterfaceMethod java/util/List.get:(I)Ljava/lang/Object;
      27: checkcast     #10                 // class org/hl7/fhir/dstu3/model/Identifier
      30: areturn

  public org.hl7.fhir.dstu3.model.Enumeration<org.hl7.fhir.dstu3.model.Goal$GoalStatus> getStatusElement();
    Code:
       0: aload_0
       1: getfield      #2                  // Field status:Lorg/hl7/fhir/dstu3/model/Enumeration;
       4: ifnonnull     47
       7: invokestatic  #18                 // Method org/hl7/fhir/dstu3/model/Configuration.errorOnAutoCreate:()Z
      10: ifeq          23
      13: new           #19                 // class java/lang/Error
      16: dup
      17: ldc           #20                 // String Attempt to auto-create Goal.status
      19: invokespecial #21                 // Method java/lang/Error."<init>":(Ljava/lang/String;)V
      22: athrow
      23: invokestatic  #22                 // Method org/hl7/fhir/dstu3/model/Configuration.doAutoCreate:()Z
      26: ifeq          47
      29: aload_0
      30: new           #23                 // class org/hl7/fhir/dstu3/model/Enumeration
      33: dup
      34: new           #24                 // class org/hl7/fhir/dstu3/model/Goal$GoalStatusEnumFactory
      37: dup
      38: invokespecial #25                 // Method org/hl7/fhir/dstu3/model/Goal$GoalStatusEnumFactory."<init>":()V
      41: invokespecial #26                 // Method org/hl7/fhir/dstu3/model/Enumeration."<init>":(Lorg/hl7/fhir/dstu3/model/EnumFactory;)V
      44: putfield      #2                  // Field status:Lorg/hl7/fhir/dstu3/model/Enumeration;
      47: aload_0
      48: getfield      #2                  // Field status:Lorg/hl7/fhir/dstu3/model/Enumeration;
      51: areturn

  public boolean hasStatusElement();
    Code:
       0: aload_0
       1: getfield      #2                  // Field status:Lorg/hl7/fhir/dstu3/model/Enumeration;
       4: ifnull        21
       7: aload_0
       8: getfield      #2                  // Field status:Lorg/hl7/fhir/dstu3/model/Enumeration;
      11: invokevirtual #27                 // Method org/hl7/fhir/dstu3/model/Enumeration.isEmpty:()Z
      14: ifne          21
      17: iconst_1
      18: goto          22
      21: iconst_0
      22: ireturn

  public boolean hasStatus();
    Code:
       0: aload_0
       1: getfield      #2                  // Field status:Lorg/hl7/fhir/dstu3/model/Enumeration;
       4: ifnull        21
       7: aload_0
       8: getfield      #2                  // Field status:Lorg/hl7/fhir/dstu3/model/Enumeration;
      11: invokevirtual #27                 // Method org/hl7/fhir/dstu3/model/Enumeration.isEmpty:()Z
      14: ifne          21
      17: iconst_1
      18: goto          22
      21: iconst_0
      22: ireturn

  public org.hl7.fhir.dstu3.model.Goal setStatusElement(org.hl7.fhir.dstu3.model.Enumeration<org.hl7.fhir.dstu3.model.Goal$GoalStatus>);
    Code:
       0: aload_0
       1: aload_1
       2: putfield      #2                  // Field status:Lorg/hl7/fhir/dstu3/model/Enumeration;
       5: aload_0
       6: areturn

  public org.hl7.fhir.dstu3.model.Goal$GoalStatus getStatus();
    Code:
       0: aload_0
       1: getfield      #2                  // Field status:Lorg/hl7/fhir/dstu3/model/Enumeration;
       4: ifnonnull     11
       7: aconst_null
       8: goto          21
      11: aload_0
      12: getfield      #2                  // Field status:Lorg/hl7/fhir/dstu3/model/Enumeration;
      15: invokevirtual #28                 // Method org/hl7/fhir/dstu3/model/Enumeration.getValue:()Ljava/lang/Object;
      18: checkcast     #29                 // class org/hl7/fhir/dstu3/model/Goal$GoalStatus
      21: areturn

  public org.hl7.fhir.dstu3.model.Goal setStatus(org.hl7.fhir.dstu3.model.Goal$GoalStatus);
    Code:
       0: aload_0
       1: getfield      #2                  // Field status:Lorg/hl7/fhir/dstu3/model/Enumeration;
       4: ifnonnull     25
       7: aload_0
       8: new           #23                 // class org/hl7/fhir/dstu3/model/Enumeration
      11: dup
      12: new           #24                 // class org/hl7/fhir/dstu3/model/Goal$GoalStatusEnumFactory
      15: dup
      16: invokespecial #25                 // Method org/hl7/fhir/dstu3/model/Goal$GoalStatusEnumFactory."<init>":()V
      19: invokespecial #26                 // Method org/hl7/fhir/dstu3/model/Enumeration."<init>":(Lorg/hl7/fhir/dstu3/model/EnumFactory;)V
      22: putfield      #2                  // Field status:Lorg/hl7/fhir/dstu3/model/Enumeration;
      25: aload_0
      26: getfield      #2                  // Field status:Lorg/hl7/fhir/dstu3/model/Enumeration;
      29: aload_1
      30: invokevirtual #30                 // Method org/hl7/fhir/dstu3/model/Enumeration.setValue:(Ljava/lang/Object;)Lorg/hl7/fhir/dstu3/model/PrimitiveType;
      33: pop
      34: aload_0
      35: areturn

  public java.util.List<org.hl7.fhir.dstu3.model.CodeableConcept> getCategory();
    Code:
       0: aload_0
       1: getfield      #31                 // Field category:Ljava/util/List;
       4: ifnonnull     18
       7: aload_0
       8: new           #5                  // class java/util/ArrayList
      11: dup
      12: invokespecial #6                  // Method java/util/ArrayList."<init>":()V
      15: putfield      #31                 // Field category:Ljava/util/List;
      18: aload_0
      19: getfield      #31                 // Field category:Ljava/util/List;
      22: areturn

  public org.hl7.fhir.dstu3.model.Goal setCategory(java.util.List<org.hl7.fhir.dstu3.model.CodeableConcept>);
    Code:
       0: aload_0
       1: aload_1
       2: putfield      #31                 // Field category:Ljava/util/List;
       5: aload_0
       6: areturn

  public boolean hasCategory();
    Code:
       0: aload_0
       1: getfield      #31                 // Field category:Ljava/util/List;
       4: ifnonnull     9
       7: iconst_0
       8: ireturn
       9: aload_0
      10: getfield      #31                 // Field category:Ljava/util/List;
      13: invokeinterface #7,  1            // InterfaceMethod java/util/List.iterator:()Ljava/util/Iterator;
      18: astore_1
      19: aload_1
      20: invokeinterface #8,  1            // InterfaceMethod java/util/Iterator.hasNext:()Z
      25: ifeq          50
      28: aload_1
      29: invokeinterface #9,  1            // InterfaceMethod java/util/Iterator.next:()Ljava/lang/Object;
      34: checkcast     #32                 // class org/hl7/fhir/dstu3/model/CodeableConcept
      37: astore_2
      38: aload_2
      39: invokevirtual #33                 // Method org/hl7/fhir/dstu3/model/CodeableConcept.isEmpty:()Z
      42: ifne          47
      45: iconst_1
      46: ireturn
      47: goto          19
      50: iconst_0
      51: ireturn

  public org.hl7.fhir.dstu3.model.CodeableConcept addCategory();
    Code:
       0: new           #32                 // class org/hl7/fhir/dstu3/model/CodeableConcept
       3: dup
       4: invokespecial #34                 // Method org/hl7/fhir/dstu3/model/CodeableConcept."<init>":()V
       7: astore_1
       8: aload_0
       9: getfield      #31                 // Field category:Ljava/util/List;
      12: ifnonnull     26
      15: aload_0
      16: new           #5                  // class java/util/ArrayList
      19: dup
      20: invokespecial #6                  // Method java/util/ArrayList."<init>":()V
      23: putfield      #31                 // Field category:Ljava/util/List;
      26: aload_0
      27: getfield      #31                 // Field category:Ljava/util/List;
      30: aload_1
      31: invokeinterface #13,  2           // InterfaceMethod java/util/List.add:(Ljava/lang/Object;)Z
      36: pop
      37: aload_1
      38: areturn

  public org.hl7.fhir.dstu3.model.Goal addCategory(org.hl7.fhir.dstu3.model.CodeableConcept);
    Code:
       0: aload_1
       1: ifnonnull     6
       4: aload_0
       5: areturn
       6: aload_0
       7: getfield      #31                 // Field category:Ljava/util/List;
      10: ifnonnull     24
      13: aload_0
      14: new           #5                  // class java/util/ArrayList
      17: dup
      18: invokespecial #6                  // Method java/util/ArrayList."<init>":()V
      21: putfield      #31                 // Field category:Ljava/util/List;
      24: aload_0
      25: getfield      #31                 // Field category:Ljava/util/List;
      28: aload_1
      29: invokeinterface #13,  2           // InterfaceMethod java/util/List.add:(Ljava/lang/Object;)Z
      34: pop
      35: aload_0
      36: areturn

  public org.hl7.fhir.dstu3.model.CodeableConcept getCategoryFirstRep();
    Code:
       0: aload_0
       1: invokevirtual #35                 // Method getCategory:()Ljava/util/List;
       4: invokeinterface #15,  1           // InterfaceMethod java/util/List.isEmpty:()Z
       9: ifeq          17
      12: aload_0
      13: invokevirtual #36                 // Method addCategory:()Lorg/hl7/fhir/dstu3/model/CodeableConcept;
      16: pop
      17: aload_0
      18: invokevirtual #35                 // Method getCategory:()Ljava/util/List;
      21: iconst_0
      22: invokeinterface #17,  2           // InterfaceMethod java/util/List.get:(I)Ljava/lang/Object;
      27: checkcast     #32                 // class org/hl7/fhir/dstu3/model/CodeableConcept
      30: areturn

  public org.hl7.fhir.dstu3.model.CodeableConcept getPriority();
    Code:
       0: aload_0
       1: getfield      #37                 // Field priority:Lorg/hl7/fhir/dstu3/model/CodeableConcept;
       4: ifnonnull     40
       7: invokestatic  #18                 // Method org/hl7/fhir/dstu3/model/Configuration.errorOnAutoCreate:()Z
      10: ifeq          23
      13: new           #19                 // class java/lang/Error
      16: dup
      17: ldc           #38                 // String Attempt to auto-create Goal.priority
      19: invokespecial #21                 // Method java/lang/Error."<init>":(Ljava/lang/String;)V
      22: athrow
      23: invokestatic  #22                 // Method org/hl7/fhir/dstu3/model/Configuration.doAutoCreate:()Z
      26: ifeq          40
      29: aload_0
      30: new           #32                 // class org/hl7/fhir/dstu3/model/CodeableConcept
      33: dup
      34: invokespecial #34                 // Method org/hl7/fhir/dstu3/model/CodeableConcept."<init>":()V
      37: putfield      #37                 // Field priority:Lorg/hl7/fhir/dstu3/model/CodeableConcept;
      40: aload_0
      41: getfield      #37                 // Field priority:Lorg/hl7/fhir/dstu3/model/CodeableConcept;
      44: areturn

  public boolean hasPriority();
    Code:
       0: aload_0
       1: getfield      #37                 // Field priority:Lorg/hl7/fhir/dstu3/model/CodeableConcept;
       4: ifnull        21
       7: aload_0
       8: getfield      #37                 // Field priority:Lorg/hl7/fhir/dstu3/model/CodeableConcept;
      11: invokevirtual #33                 // Method org/hl7/fhir/dstu3/model/CodeableConcept.isEmpty:()Z
      14: ifne          21
      17: iconst_1
      18: goto          22
      21: iconst_0
      22: ireturn

  public org.hl7.fhir.dstu3.model.Goal setPriority(org.hl7.fhir.dstu3.model.CodeableConcept);
    Code:
       0: aload_0
       1: aload_1
       2: putfield      #37                 // Field priority:Lorg/hl7/fhir/dstu3/model/CodeableConcept;
       5: aload_0
       6: areturn

  public org.hl7.fhir.dstu3.model.CodeableConcept getDescription();
    Code:
       0: aload_0
       1: getfield      #3                  // Field description:Lorg/hl7/fhir/dstu3/model/CodeableConcept;
       4: ifnonnull     40
       7: invokestatic  #18                 // Method org/hl7/fhir/dstu3/model/Configuration.errorOnAutoCreate:()Z
      10: ifeq          23
      13: new           #19                 // class java/lang/Error
      16: dup
      17: ldc           #39                 // String Attempt to auto-create Goal.description
      19: invokespecial #21                 // Method java/lang/Error."<init>":(Ljava/lang/String;)V
      22: athrow
      23: invokestatic  #22                 // Method org/hl7/fhir/dstu3/model/Configuration.doAutoCreate:()Z
      26: ifeq          40
      29: aload_0
      30: new           #32                 // class org/hl7/fhir/dstu3/model/CodeableConcept
      33: dup
      34: invokespecial #34                 // Method org/hl7/fhir/dstu3/model/CodeableConcept."<init>":()V
      37: putfield      #3                  // Field description:Lorg/hl7/fhir/dstu3/model/CodeableConcept;
      40: aload_0
      41: getfield      #3                  // Field description:Lorg/hl7/fhir/dstu3/model/CodeableConcept;
      44: areturn

  public boolean hasDescription();
    Code:
       0: aload_0
       1: getfield      #3                  // Field description:Lorg/hl7/fhir/dstu3/model/CodeableConcept;
       4: ifnull        21
       7: aload_0
       8: getfield      #3                  // Field description:Lorg/hl7/fhir/dstu3/model/CodeableConcept;
      11: invokevirtual #33                 // Method org/hl7/fhir/dstu3/model/CodeableConcept.isEmpty:()Z
      14: ifne          21
      17: iconst_1
      18: goto          22
      21: iconst_0
      22: ireturn

  public org.hl7.fhir.dstu3.model.Goal setDescription(org.hl7.fhir.dstu3.model.CodeableConcept);
    Code:
       0: aload_0
       1: aload_1
       2: putfield      #3                  // Field description:Lorg/hl7/fhir/dstu3/model/CodeableConcept;
       5: aload_0
       6: areturn

  public org.hl7.fhir.dstu3.model.Reference getSubject();
    Code:
       0: aload_0
       1: getfield      #40                 // Field subject:Lorg/hl7/fhir/dstu3/model/Reference;
       4: ifnonnull     40
       7: invokestatic  #18                 // Method org/hl7/fhir/dstu3/model/Configuration.errorOnAutoCreate:()Z
      10: ifeq          23
      13: new           #19                 // class java/lang/Error
      16: dup
      17: ldc           #41                 // String Attempt to auto-create Goal.subject
      19: invokespecial #21                 // Method java/lang/Error."<init>":(Ljava/lang/String;)V
      22: athrow
      23: invokestatic  #22                 // Method org/hl7/fhir/dstu3/model/Configuration.doAutoCreate:()Z
      26: ifeq          40
      29: aload_0
      30: new           #42                 // class org/hl7/fhir/dstu3/model/Reference
      33: dup
      34: invokespecial #43                 // Method org/hl7/fhir/dstu3/model/Reference."<init>":()V
      37: putfield      #40                 // Field subject:Lorg/hl7/fhir/dstu3/model/Reference;
      40: aload_0
      41: getfield      #40                 // Field subject:Lorg/hl7/fhir/dstu3/model/Reference;
      44: areturn

  public boolean hasSubject();
    Code:
       0: aload_0
       1: getfield      #40                 // Field subject:Lorg/hl7/fhir/dstu3/model/Reference;
       4: ifnull        21
       7: aload_0
       8: getfield      #40                 // Field subject:Lorg/hl7/fhir/dstu3/model/Reference;
      11: invokevirtual #44                 // Method org/hl7/fhir/dstu3/model/Reference.isEmpty:()Z
      14: ifne          21
      17: iconst_1
      18: goto          22
      21: iconst_0
      22: ireturn

  public org.hl7.fhir.dstu3.model.Goal setSubject(org.hl7.fhir.dstu3.model.Reference);
    Code:
       0: aload_0
       1: aload_1
       2: putfield      #40                 // Field subject:Lorg/hl7/fhir/dstu3/model/Reference;
       5: aload_0
       6: areturn

  public org.hl7.fhir.dstu3.model.Resource getSubjectTarget();
    Code:
       0: aload_0
       1: getfield      #45                 // Field subjectTarget:Lorg/hl7/fhir/dstu3/model/Resource;
       4: areturn

  public org.hl7.fhir.dstu3.model.Goal setSubjectTarget(org.hl7.fhir.dstu3.model.Resource);
    Code:
       0: aload_0
       1: aload_1
       2: putfield      #45                 // Field subjectTarget:Lorg/hl7/fhir/dstu3/model/Resource;
       5: aload_0
       6: areturn

  public org.hl7.fhir.dstu3.model.Type getStart();
    Code:
       0: aload_0
       1: getfield      #46                 // Field start:Lorg/hl7/fhir/dstu3/model/Type;
       4: areturn

  public org.hl7.fhir.dstu3.model.DateType getStartDateType() throws org.hl7.fhir.exceptions.FHIRException;
    Code:
       0: aload_0
       1: getfield      #46                 // Field start:Lorg/hl7/fhir/dstu3/model/Type;
       4: ifnonnull     9
       7: aconst_null
       8: areturn
       9: aload_0
      10: getfield      #46                 // Field start:Lorg/hl7/fhir/dstu3/model/Type;
      13: instanceof    #47                 // class org/hl7/fhir/dstu3/model/DateType
      16: ifne          60
      19: new           #48                 // class org/hl7/fhir/exceptions/FHIRException
      22: dup
      23: new           #49                 // class java/lang/StringBuilder
      26: dup
      27: invokespecial #50                 // Method java/lang/StringBuilder."<init>":()V
      30: ldc           #51                 // String Type mismatch: the type DateType was expected, but
      32: invokevirtual #52                 // Method java/lang/StringBuilder.append:(Ljava/lang/String;)Ljava/lang/StringBuilder;
      35: aload_0
      36: getfield      #46                 // Field start:Lorg/hl7/fhir/dstu3/model/Type;
      39: invokevirtual #53                 // Method java/lang/Object.getClass:()Ljava/lang/Class;
      42: invokevirtual #54                 // Method java/lang/Class.getName:()Ljava/lang/String;
      45: invokevirtual #52                 // Method java/lang/StringBuilder.append:(Ljava/lang/String;)Ljava/lang/StringBuilder;
      48: ldc           #55                 // String  was encountered
      50: invokevirtual #52                 // Method java/lang/StringBuilder.append:(Ljava/lang/String;)Ljava/lang/StringBuilder;
      53: invokevirtual #56                 // Method java/lang/StringBuilder.toString:()Ljava/lang/String;
      56: invokespecial #57                 // Method org/hl7/fhir/exceptions/FHIRException."<init>":(Ljava/lang/String;)V
      59: athrow
      60: aload_0
      61: getfield      #46                 // Field start:Lorg/hl7/fhir/dstu3/model/Type;
      64: checkcast     #47                 // class org/hl7/fhir/dstu3/model/DateType
      67: areturn

  public boolean hasStartDateType();
    Code:
       0: aload_0
       1: ifnull        18
       4: aload_0
       5: getfield      #46                 // Field start:Lorg/hl7/fhir/dstu3/model/Type;
       8: instanceof    #47                 // class org/hl7/fhir/dstu3/model/DateType
      11: ifeq          18
      14: iconst_1
      15: goto          19
      18: iconst_0
      19: ireturn

  public org.hl7.fhir.dstu3.model.CodeableConcept getStartCodeableConcept() throws org.hl7.fhir.exceptions.FHIRException;
    Code:
       0: aload_0
       1: getfield      #46                 // Field start:Lorg/hl7/fhir/dstu3/model/Type;
       4: ifnonnull     9
       7: aconst_null
       8: areturn
       9: aload_0
      10: getfield      #46                 // Field start:Lorg/hl7/fhir/dstu3/model/Type;
      13: instanceof    #32                 // class org/hl7/fhir/dstu3/model/CodeableConcept
      16: ifne          60
      19: new           #48                 // class org/hl7/fhir/exceptions/FHIRException
      22: dup
      23: new           #49                 // class java/lang/StringBuilder
      26: dup
      27: invokespecial #50                 // Method java/lang/StringBuilder."<init>":()V
      30: ldc           #58                 // String Type mismatch: the type CodeableConcept was expected, but
      32: invokevirtual #52                 // Method java/lang/StringBuilder.append:(Ljava/lang/String;)Ljava/lang/StringBuilder;
      35: aload_0
      36: getfield      #46                 // Field start:Lorg/hl7/fhir/dstu3/model/Type;
      39: invokevirtual #53                 // Method java/lang/Object.getClass:()Ljava/lang/Class;
      42: invokevirtual #54                 // Method java/lang/Class.getName:()Ljava/lang/String;
      45: invokevirtual #52                 // Method java/lang/StringBuilder.append:(Ljava/lang/String;)Ljava/lang/StringBuilder;
      48: ldc           #55                 // String  was encountered
      50: invokevirtual #52                 // Method java/lang/StringBuilder.append:(Ljava/lang/String;)Ljava/lang/StringBuilder;
      53: invokevirtual #56                 // Method java/lang/StringBuilder.toString:()Ljava/lang/String;
      56: invokespecial #57                 // Method org/hl7/fhir/exceptions/FHIRException."<init>":(Ljava/lang/String;)V
      59: athrow
      60: aload_0
      61: getfield      #46                 // Field start:Lorg/hl7/fhir/dstu3/model/Type;
      64: checkcast     #32                 // class org/hl7/fhir/dstu3/model/CodeableConcept
      67: areturn

  public boolean hasStartCodeableConcept();
    Code:
       0: aload_0
       1: ifnull        18
       4: aload_0
       5: getfield      #46                 // Field start:Lorg/hl7/fhir/dstu3/model/Type;
       8: instanceof    #32                 // class org/hl7/fhir/dstu3/model/CodeableConcept
      11: ifeq          18
      14: iconst_1
      15: goto          19
      18: iconst_0
      19: ireturn

  public boolean hasStart();
    Code:
       0: aload_0
       1: getfield      #46                 // Field start:Lorg/hl7/fhir/dstu3/model/Type;
       4: ifnull        21
       7: aload_0
       8: getfield      #46                 // Field start:Lorg/hl7/fhir/dstu3/model/Type;
      11: invokevirtual #59                 // Method org/hl7/fhir/dstu3/model/Type.isEmpty:()Z
      14: ifne          21
      17: iconst_1
      18: goto          22
      21: iconst_0
      22: ireturn

  public org.hl7.fhir.dstu3.model.Goal setStart(org.hl7.fhir.dstu3.model.Type) throws org.hl7.fhir.exceptions.FHIRFormatError;
    Code:
       0: aload_1
       1: ifnull        48
       4: aload_1
       5: instanceof    #47                 // class org/hl7/fhir/dstu3/model/DateType
       8: ifne          48
      11: aload_1
      12: instanceof    #32                 // class org/hl7/fhir/dstu3/model/CodeableConcept
      15: ifne          48
      18: new           #60                 // class org/hl7/fhir/exceptions/FHIRFormatError
      21: dup
      22: new           #49                 // class java/lang/StringBuilder
      25: dup
      26: invokespecial #50                 // Method java/lang/StringBuilder."<init>":()V
      29: ldc           #61                 // String Not the right type for Goal.start[x]:
      31: invokevirtual #52                 // Method java/lang/StringBuilder.append:(Ljava/lang/String;)Ljava/lang/StringBuilder;
      34: aload_1
      35: invokevirtual #62                 // Method org/hl7/fhir/dstu3/model/Type.fhirType:()Ljava/lang/String;
      38: invokevirtual #52                 // Method java/lang/StringBuilder.append:(Ljava/lang/String;)Ljava/lang/StringBuilder;
      41: invokevirtual #56                 // Method java/lang/StringBuilder.toString:()Ljava/lang/String;
      44: invokespecial #63                 // Method org/hl7/fhir/exceptions/FHIRFormatError."<init>":(Ljava/lang/String;)V
      47: athrow
      48: aload_0
      49: aload_1
      50: putfield      #46                 // Field start:Lorg/hl7/fhir/dstu3/model/Type;
      53: aload_0
      54: areturn

  public org.hl7.fhir.dstu3.model.Goal$GoalTargetComponent getTarget();
    Code:
       0: aload_0
       1: getfield      #64                 // Field target:Lorg/hl7/fhir/dstu3/model/Goal$GoalTargetComponent;
       4: ifnonnull     40
       7: invokestatic  #18                 // Method org/hl7/fhir/dstu3/model/Configuration.errorOnAutoCreate:()Z
      10: ifeq          23
      13: new           #19                 // class java/lang/Error
      16: dup
      17: ldc           #65                 // String Attempt to auto-create Goal.target
      19: invokespecial #21                 // Method java/lang/Error."<init>":(Ljava/lang/String;)V
      22: athrow
      23: invokestatic  #22                 // Method org/hl7/fhir/dstu3/model/Configuration.doAutoCreate:()Z
      26: ifeq          40
      29: aload_0
      30: new           #66                 // class org/hl7/fhir/dstu3/model/Goal$GoalTargetComponent
      33: dup
      34: invokespecial #67                 // Method org/hl7/fhir/dstu3/model/Goal$GoalTargetComponent."<init>":()V
      37: putfield      #64                 // Field target:Lorg/hl7/fhir/dstu3/model/Goal$GoalTargetComponent;
      40: aload_0
      41: getfield      #64                 // Field target:Lorg/hl7/fhir/dstu3/model/Goal$GoalTargetComponent;
      44: areturn

  public boolean hasTarget();
    Code:
       0: aload_0
       1: getfield      #64                 // Field target:Lorg/hl7/fhir/dstu3/model/Goal$GoalTargetComponent;
       4: ifnull        21
       7: aload_0
       8: getfield      #64                 // Field target:Lorg/hl7/fhir/dstu3/model/Goal$GoalTargetComponent;
      11: invokevirtual #68                 // Method org/hl7/fhir/dstu3/model/Goal$GoalTargetComponent.isEmpty:()Z
      14: ifne          21
      17: iconst_1
      18: goto          22
      21: iconst_0
      22: ireturn

  public org.hl7.fhir.dstu3.model.Goal setTarget(org.hl7.fhir.dstu3.model.Goal$GoalTargetComponent);
    Code:
       0: aload_0
       1: aload_1
       2: putfield      #64                 // Field target:Lorg/hl7/fhir/dstu3/model/Goal$GoalTargetComponent;
       5: aload_0
       6: areturn

  public org.hl7.fhir.dstu3.model.DateType getStatusDateElement();
    Code:
       0: aload_0
       1: getfield      #69                 // Field statusDate:Lorg/hl7/fhir/dstu3/model/DateType;
       4: ifnonnull     40
       7: invokestatic  #18                 // Method org/hl7/fhir/dstu3/model/Configuration.errorOnAutoCreate:()Z
      10: ifeq          23
      13: new           #19                 // class java/lang/Error
      16: dup
      17: ldc           #70                 // String Attempt to auto-create Goal.statusDate
      19: invokespecial #21                 // Method java/lang/Error."<init>":(Ljava/lang/String;)V
      22: athrow
      23: invokestatic  #22                 // Method org/hl7/fhir/dstu3/model/Configuration.doAutoCreate:()Z
      26: ifeq          40
      29: aload_0
      30: new           #47                 // class org/hl7/fhir/dstu3/model/DateType
      33: dup
      34: invokespecial #71                 // Method org/hl7/fhir/dstu3/model/DateType."<init>":()V
      37: putfield      #69                 // Field statusDate:Lorg/hl7/fhir/dstu3/model/DateType;
      40: aload_0
      41: getfield      #69                 // Field statusDate:Lorg/hl7/fhir/dstu3/model/DateType;
      44: areturn

  public boolean hasStatusDateElement();
    Code:
       0: aload_0
       1: getfield      #69                 // Field statusDate:Lorg/hl7/fhir/dstu3/model/DateType;
       4: ifnull        21
       7: aload_0
       8: getfield      #69                 // Field statusDate:Lorg/hl7/fhir/dstu3/model/DateType;
      11: invokevirtual #72                 // Method org/hl7/fhir/dstu3/model/DateType.isEmpty:()Z
      14: ifne          21
      17: iconst_1
      18: goto          22
      21: iconst_0
      22: ireturn

  public boolean hasStatusDate();
    Code:
       0: aload_0
       1: getfield      #69                 // Field statusDate:Lorg/hl7/fhir/dstu3/model/DateType;
       4: ifnull        21
       7: aload_0
       8: getfield      #69                 // Field statusDate:Lorg/hl7/fhir/dstu3/model/DateType;
      11: invokevirtual #72                 // Method org/hl7/fhir/dstu3/model/DateType.isEmpty:()Z
      14: ifne          21
      17: iconst_1
      18: goto          22
      21: iconst_0
      22: ireturn

  public org.hl7.fhir.dstu3.model.Goal setStatusDateElement(org.hl7.fhir.dstu3.model.DateType);
    Code:
       0: aload_0
       1: aload_1
       2: putfield      #69                 // Field statusDate:Lorg/hl7/fhir/dstu3/model/DateType;
       5: aload_0
       6: areturn

  public java.util.Date getStatusDate();
    Code:
       0: aload_0
       1: getfield      #69                 // Field statusDate:Lorg/hl7/fhir/dstu3/model/DateType;
       4: ifnonnull     11
       7: aconst_null
       8: goto          21
      11: aload_0
      12: getfield      #69                 // Field statusDate:Lorg/hl7/fhir/dstu3/model/DateType;
      15: invokevirtual #73                 // Method org/hl7/fhir/dstu3/model/DateType.getValue:()Ljava/lang/Object;
      18: checkcast     #74                 // class java/util/Date
      21: areturn

  public org.hl7.fhir.dstu3.model.Goal setStatusDate(java.util.Date);
    Code:
       0: aload_1
       1: ifnonnull     12
       4: aload_0
       5: aconst_null
       6: putfield      #69                 // Field statusDate:Lorg/hl7/fhir/dstu3/model/DateType;
       9: goto          39
      12: aload_0
      13: getfield      #69                 // Field statusDate:Lorg/hl7/fhir/dstu3/model/DateType;
      16: ifnonnull     30
      19: aload_0
      20: new           #47                 // class org/hl7/fhir/dstu3/model/DateType
      23: dup
      24: invokespecial #71                 // Method org/hl7/fhir/dstu3/model/DateType."<init>":()V
      27: putfield      #69                 // Field statusDate:Lorg/hl7/fhir/dstu3/model/DateType;
      30: aload_0
      31: getfield      #69                 // Field statusDate:Lorg/hl7/fhir/dstu3/model/DateType;
      34: aload_1
      35: invokevirtual #75                 // Method org/hl7/fhir/dstu3/model/DateType.setValue:(Ljava/util/Date;)Lorg/hl7/fhir/dstu3/model/BaseDateTimeType;
      38: pop
      39: aload_0
      40: areturn

  public org.hl7.fhir.dstu3.model.StringType getStatusReasonElement();
    Code:
       0: aload_0
       1: getfield      #76                 // Field statusReason:Lorg/hl7/fhir/dstu3/model/StringType;
       4: ifnonnull     40
       7: invokestatic  #18                 // Method org/hl7/fhir/dstu3/model/Configuration.errorOnAutoCreate:()Z
      10: ifeq          23
      13: new           #19                 // class java/lang/Error
      16: dup
      17: ldc           #77                 // String Attempt to auto-create Goal.statusReason
      19: invokespecial #21                 // Method java/lang/Error."<init>":(Ljava/lang/String;)V
      22: athrow
      23: invokestatic  #22                 // Method org/hl7/fhir/dstu3/model/Configuration.doAutoCreate:()Z
      26: ifeq          40
      29: aload_0
      30: new           #78                 // class org/hl7/fhir/dstu3/model/StringType
      33: dup
      34: invokespecial #79                 // Method org/hl7/fhir/dstu3/model/StringType."<init>":()V
      37: putfield      #76                 // Field statusReason:Lorg/hl7/fhir/dstu3/model/StringType;
      40: aload_0
      41: getfield      #76                 // Field statusReason:Lorg/hl7/fhir/dstu3/model/StringType;
      44: areturn

  public boolean hasStatusReasonElement();
    Code:
       0: aload_0
       1: getfield      #76                 // Field statusReason:Lorg/hl7/fhir/dstu3/model/StringType;
       4: ifnull        21
       7: aload_0
       8: getfield      #76                 // Field statusReason:Lorg/hl7/fhir/dstu3/model/StringType;
      11: invokevirtual #80                 // Method org/hl7/fhir/dstu3/model/StringType.isEmpty:()Z
      14: ifne          21
      17: iconst_1
      18: goto          22
      21: iconst_0
      22: ireturn

  public boolean hasStatusReason();
    Code:
       0: aload_0
       1: getfield      #76                 // Field statusReason:Lorg/hl7/fhir/dstu3/model/StringType;
       4: ifnull        21
       7: aload_0
       8: getfield      #76                 // Field statusReason:Lorg/hl7/fhir/dstu3/model/StringType;
      11: invokevirtual #80                 // Method org/hl7/fhir/dstu3/model/StringType.isEmpty:()Z
      14: ifne          21
      17: iconst_1
      18: goto          22
      21: iconst_0
      22: ireturn

  public org.hl7.fhir.dstu3.model.Goal setStatusReasonElement(org.hl7.fhir.dstu3.model.StringType);
    Code:
       0: aload_0
       1: aload_1
       2: putfield      #76                 // Field statusReason:Lorg/hl7/fhir/dstu3/model/StringType;
       5: aload_0
       6: areturn

  public java.lang.String getStatusReason();
    Code:
       0: aload_0
       1: getfield      #76                 // Field statusReason:Lorg/hl7/fhir/dstu3/model/StringType;
       4: ifnonnull     11
       7: aconst_null
       8: goto          21
      11: aload_0
      12: getfield      #76                 // Field statusReason:Lorg/hl7/fhir/dstu3/model/StringType;
      15: invokevirtual #81                 // Method org/hl7/fhir/dstu3/model/StringType.getValue:()Ljava/lang/Object;
      18: checkcast     #82                 // class java/lang/String
      21: areturn

  public org.hl7.fhir.dstu3.model.Goal setStatusReason(java.lang.String);
    Code:
       0: aload_1
       1: invokestatic  #83                 // Method org/hl7/fhir/utilities/Utilities.noString:(Ljava/lang/String;)Z
       4: ifeq          15
       7: aload_0
       8: aconst_null
       9: putfield      #76                 // Field statusReason:Lorg/hl7/fhir/dstu3/model/StringType;
      12: goto          42
      15: aload_0
      16: getfield      #76                 // Field statusReason:Lorg/hl7/fhir/dstu3/model/StringType;
      19: ifnonnull     33
      22: aload_0
      23: new           #78                 // class org/hl7/fhir/dstu3/model/StringType
      26: dup
      27: invokespecial #79                 // Method org/hl7/fhir/dstu3/model/StringType."<init>":()V
      30: putfield      #76                 // Field statusReason:Lorg/hl7/fhir/dstu3/model/StringType;
      33: aload_0
      34: getfield      #76                 // Field statusReason:Lorg/hl7/fhir/dstu3/model/StringType;
      37: aload_1
      38: invokevirtual #84                 // Method org/hl7/fhir/dstu3/model/StringType.setValue:(Ljava/lang/Object;)Lorg/hl7/fhir/dstu3/model/PrimitiveType;
      41: pop
      42: aload_0
      43: areturn

  public org.hl7.fhir.dstu3.model.Reference getExpressedBy();
    Code:
       0: aload_0
       1: getfield      #85                 // Field expressedBy:Lorg/hl7/fhir/dstu3/model/Reference;
       4: ifnonnull     40
       7: invokestatic  #18                 // Method org/hl7/fhir/dstu3/model/Configuration.errorOnAutoCreate:()Z
      10: ifeq          23
      13: new           #19                 // class java/lang/Error
      16: dup
      17: ldc           #86                 // String Attempt to auto-create Goal.expressedBy
      19: invokespecial #21                 // Method java/lang/Error."<init>":(Ljava/lang/String;)V
      22: athrow
      23: invokestatic  #22                 // Method org/hl7/fhir/dstu3/model/Configuration.doAutoCreate:()Z
      26: ifeq          40
      29: aload_0
      30: new           #42                 // class org/hl7/fhir/dstu3/model/Reference
      33: dup
      34: invokespecial #43                 // Method org/hl7/fhir/dstu3/model/Reference."<init>":()V
      37: putfield      #85                 // Field expressedBy:Lorg/hl7/fhir/dstu3/model/Reference;
      40: aload_0
      41: getfield      #85                 // Field expressedBy:Lorg/hl7/fhir/dstu3/model/Reference;
      44: areturn

  public boolean hasExpressedBy();
    Code:
       0: aload_0
       1: getfield      #85                 // Field expressedBy:Lorg/hl7/fhir/dstu3/model/Reference;
       4: ifnull        21
       7: aload_0
       8: getfield      #85                 // Field expressedBy:Lorg/hl7/fhir/dstu3/model/Reference;
      11: invokevirtual #44                 // Method org/hl7/fhir/dstu3/model/Reference.isEmpty:()Z
      14: ifne          21
      17: iconst_1
      18: goto          22
      21: iconst_0
      22: ireturn

  public org.hl7.fhir.dstu3.model.Goal setExpressedBy(org.hl7.fhir.dstu3.model.Reference);
    Code:
       0: aload_0
       1: aload_1
       2: putfield      #85                 // Field expressedBy:Lorg/hl7/fhir/dstu3/model/Reference;
       5: aload_0
       6: areturn

  public org.hl7.fhir.dstu3.model.Resource getExpressedByTarget();
    Code:
       0: aload_0
       1: getfield      #87                 // Field expressedByTarget:Lorg/hl7/fhir/dstu3/model/Resource;
       4: areturn

  public org.hl7.fhir.dstu3.model.Goal setExpressedByTarget(org.hl7.fhir.dstu3.model.Resource);
    Code:
       0: aload_0
       1: aload_1
       2: putfield      #87                 // Field expressedByTarget:Lorg/hl7/fhir/dstu3/model/Resource;
       5: aload_0
       6: areturn

  public java.util.List<org.hl7.fhir.dstu3.model.Reference> getAddresses();
    Code:
       0: aload_0
       1: getfield      #88                 // Field addresses:Ljava/util/List;
       4: ifnonnull     18
       7: aload_0
       8: new           #5                  // class java/util/ArrayList
      11: dup
      12: invokespecial #6                  // Method java/util/ArrayList."<init>":()V
      15: putfield      #88                 // Field addresses:Ljava/util/List;
      18: aload_0
      19: getfield      #88                 // Field addresses:Ljava/util/List;
      22: areturn

  public org.hl7.fhir.dstu3.model.Goal setAddresses(java.util.List<org.hl7.fhir.dstu3.model.Reference>);
    Code:
       0: aload_0
       1: aload_1
       2: putfield      #88                 // Field addresses:Ljava/util/List;
       5: aload_0
       6: areturn

  public boolean hasAddresses();
    Code:
       0: aload_0
       1: getfield      #88                 // Field addresses:Ljava/util/List;
       4: ifnonnull     9
       7: iconst_0
       8: ireturn
       9: aload_0
      10: getfield      #88                 // Field addresses:Ljava/util/List;
      13: invokeinterface #7,  1            // InterfaceMethod java/util/List.iterator:()Ljava/util/Iterator;
      18: astore_1
      19: aload_1
      20: invokeinterface #8,  1            // InterfaceMethod java/util/Iterator.hasNext:()Z
      25: ifeq          50
      28: aload_1
      29: invokeinterface #9,  1            // InterfaceMethod java/util/Iterator.next:()Ljava/lang/Object;
      34: checkcast     #42                 // class org/hl7/fhir/dstu3/model/Reference
      37: astore_2
      38: aload_2
      39: invokevirtual #44                 // Method org/hl7/fhir/dstu3/model/Reference.isEmpty:()Z
      42: ifne          47
      45: iconst_1
      46: ireturn
      47: goto          19
      50: iconst_0
      51: ireturn

  public org.hl7.fhir.dstu3.model.Reference addAddresses();
    Code:
       0: new           #42                 // class org/hl7/fhir/dstu3/model/Reference
       3: dup
       4: invokespecial #43                 // Method org/hl7/fhir/dstu3/model/Reference."<init>":()V
       7: astore_1
       8: aload_0
       9: getfield      #88                 // Field addresses:Ljava/util/List;
      12: ifnonnull     26
      15: aload_0
      16: new           #5                  // class java/util/ArrayList
      19: dup
      20: invokespecial #6                  // Method java/util/ArrayList."<init>":()V
      23: putfield      #88                 // Field addresses:Ljava/util/List;
      26: aload_0
      27: getfield      #88                 // Field addresses:Ljava/util/List;
      30: aload_1
      31: invokeinterface #13,  2           // InterfaceMethod java/util/List.add:(Ljava/lang/Object;)Z
      36: pop
      37: aload_1
      38: areturn

  public org.hl7.fhir.dstu3.model.Goal addAddresses(org.hl7.fhir.dstu3.model.Reference);
    Code:
       0: aload_1
       1: ifnonnull     6
       4: aload_0
       5: areturn
       6: aload_0
       7: getfield      #88                 // Field addresses:Ljava/util/List;
      10: ifnonnull     24
      13: aload_0
      14: new           #5                  // class java/util/ArrayList
      17: dup
      18: invokespecial #6                  // Method java/util/ArrayList."<init>":()V
      21: putfield      #88                 // Field addresses:Ljava/util/List;
      24: aload_0
      25: getfield      #88                 // Field addresses:Ljava/util/List;
      28: aload_1
      29: invokeinterface #13,  2           // InterfaceMethod java/util/List.add:(Ljava/lang/Object;)Z
      34: pop
      35: aload_0
      36: areturn

  public org.hl7.fhir.dstu3.model.Reference getAddressesFirstRep();
    Code:
       0: aload_0
       1: invokevirtual #89                 // Method getAddresses:()Ljava/util/List;
       4: invokeinterface #15,  1           // InterfaceMethod java/util/List.isEmpty:()Z
       9: ifeq          17
      12: aload_0
      13: invokevirtual #90                 // Method addAddresses:()Lorg/hl7/fhir/dstu3/model/Reference;
      16: pop
      17: aload_0
      18: invokevirtual #89                 // Method getAddresses:()Ljava/util/List;
      21: iconst_0
      22: invokeinterface #17,  2           // InterfaceMethod java/util/List.get:(I)Ljava/lang/Object;
      27: checkcast     #42                 // class org/hl7/fhir/dstu3/model/Reference
      30: areturn

  public java.util.List<org.hl7.fhir.dstu3.model.Resource> getAddressesTarget();
    Code:
       0: aload_0
       1: getfield      #91                 // Field addressesTarget:Ljava/util/List;
       4: ifnonnull     18
       7: aload_0
       8: new           #5                  // class java/util/ArrayList
      11: dup
      12: invokespecial #6                  // Method java/util/ArrayList."<init>":()V
      15: putfield      #91                 // Field addressesTarget:Ljava/util/List;
      18: aload_0
      19: getfield      #91                 // Field addressesTarget:Ljava/util/List;
      22: areturn

  public java.util.List<org.hl7.fhir.dstu3.model.Annotation> getNote();
    Code:
       0: aload_0
       1: getfield      #92                 // Field note:Ljava/util/List;
       4: ifnonnull     18
       7: aload_0
       8: new           #5                  // class java/util/ArrayList
      11: dup
      12: invokespecial #6                  // Method java/util/ArrayList."<init>":()V
      15: putfield      #92                 // Field note:Ljava/util/List;
      18: aload_0
      19: getfield      #92                 // Field note:Ljava/util/List;
      22: areturn

  public org.hl7.fhir.dstu3.model.Goal setNote(java.util.List<org.hl7.fhir.dstu3.model.Annotation>);
    Code:
       0: aload_0
       1: aload_1
       2: putfield      #92                 // Field note:Ljava/util/List;
       5: aload_0
       6: areturn

  public boolean hasNote();
    Code:
       0: aload_0
       1: getfield      #92                 // Field note:Ljava/util/List;
       4: ifnonnull     9
       7: iconst_0
       8: ireturn
       9: aload_0
      10: getfield      #92                 // Field note:Ljava/util/List;
      13: invokeinterface #7,  1            // InterfaceMethod java/util/List.iterator:()Ljava/util/Iterator;
      18: astore_1
      19: aload_1
      20: invokeinterface #8,  1            // InterfaceMethod java/util/Iterator.hasNext:()Z
      25: ifeq          50
      28: aload_1
      29: invokeinterface #9,  1            // InterfaceMethod java/util/Iterator.next:()Ljava/lang/Object;
      34: checkcast     #93                 // class org/hl7/fhir/dstu3/model/Annotation
      37: astore_2
      38: aload_2
      39: invokevirtual #94                 // Method org/hl7/fhir/dstu3/model/Annotation.isEmpty:()Z
      42: ifne          47
      45: iconst_1
      46: ireturn
      47: goto          19
      50: iconst_0
      51: ireturn

  public org.hl7.fhir.dstu3.model.Annotation addNote();
    Code:
       0: new           #93                 // class org/hl7/fhir/dstu3/model/Annotation
       3: dup
       4: invokespecial #95                 // Method org/hl7/fhir/dstu3/model/Annotation."<init>":()V
       7: astore_1
       8: aload_0
       9: getfield      #92                 // Field note:Ljava/util/List;
      12: ifnonnull     26
      15: aload_0
      16: new           #5                  // class java/util/ArrayList
      19: dup
      20: invokespecial #6                  // Method java/util/ArrayList."<init>":()V
      23: putfield      #92                 // Field note:Ljava/util/List;
      26: aload_0
      27: getfield      #92                 // Field note:Ljava/util/List;
      30: aload_1
      31: invokeinterface #13,  2           // InterfaceMethod java/util/List.add:(Ljava/lang/Object;)Z
      36: pop
      37: aload_1
      38: areturn

  public org.hl7.fhir.dstu3.model.Goal addNote(org.hl7.fhir.dstu3.model.Annotation);
    Code:
       0: aload_1
       1: ifnonnull     6
       4: aload_0
       5: areturn
       6: aload_0
       7: getfield      #92                 // Field note:Ljava/util/List;
      10: ifnonnull     24
      13: aload_0
      14: new           #5                  // class java/util/ArrayList
      17: dup
      18: invokespecial #6                  // Method java/util/ArrayList."<init>":()V
      21: putfield      #92                 // Field note:Ljava/util/List;
      24: aload_0
      25: getfield      #92                 // Field note:Ljava/util/List;
      28: aload_1
      29: invokeinterface #13,  2           // InterfaceMethod java/util/List.add:(Ljava/lang/Object;)Z
      34: pop
      35: aload_0
      36: areturn

  public org.hl7.fhir.dstu3.model.Annotation getNoteFirstRep();
    Code:
       0: aload_0
       1: invokevirtual #96                 // Method getNote:()Ljava/util/List;
       4: invokeinterface #15,  1           // InterfaceMethod java/util/List.isEmpty:()Z
       9: ifeq          17
      12: aload_0
      13: invokevirtual #97                 // Method addNote:()Lorg/hl7/fhir/dstu3/model/Annotation;
      16: pop
      17: aload_0
      18: invokevirtual #96                 // Method getNote:()Ljava/util/List;
      21: iconst_0
      22: invokeinterface #17,  2           // InterfaceMethod java/util/List.get:(I)Ljava/lang/Object;
      27: checkcast     #93                 // class org/hl7/fhir/dstu3/model/Annotation
      30: areturn

  public java.util.List<org.hl7.fhir.dstu3.model.CodeableConcept> getOutcomeCode();
    Code:
       0: aload_0
       1: getfield      #98                 // Field outcomeCode:Ljava/util/List;
       4: ifnonnull     18
       7: aload_0
       8: new           #5                  // class java/util/ArrayList
      11: dup
      12: invokespecial #6                  // Method java/util/ArrayList."<init>":()V
      15: putfield      #98                 // Field outcomeCode:Ljava/util/List;
      18: aload_0
      19: getfield      #98                 // Field outcomeCode:Ljava/util/List;
      22: areturn

  public org.hl7.fhir.dstu3.model.Goal setOutcomeCode(java.util.List<org.hl7.fhir.dstu3.model.CodeableConcept>);
    Code:
       0: aload_0
       1: aload_1
       2: putfield      #98                 // Field outcomeCode:Ljava/util/List;
       5: aload_0
       6: areturn

  public boolean hasOutcomeCode();
    Code:
       0: aload_0
       1: getfield      #98                 // Field outcomeCode:Ljava/util/List;
       4: ifnonnull     9
       7: iconst_0
       8: ireturn
       9: aload_0
      10: getfield      #98                 // Field outcomeCode:Ljava/util/List;
      13: invokeinterface #7,  1            // InterfaceMethod java/util/List.iterator:()Ljava/util/Iterator;
      18: astore_1
      19: aload_1
      20: invokeinterface #8,  1            // InterfaceMethod java/util/Iterator.hasNext:()Z
      25: ifeq          50
      28: aload_1
      29: invokeinterface #9,  1            // InterfaceMethod java/util/Iterator.next:()Ljava/lang/Object;
      34: checkcast     #32                 // class org/hl7/fhir/dstu3/model/CodeableConcept
      37: astore_2
      38: aload_2
      39: invokevirtual #33                 // Method org/hl7/fhir/dstu3/model/CodeableConcept.isEmpty:()Z
      42: ifne          47
      45: iconst_1
      46: ireturn
      47: goto          19
      50: iconst_0
      51: ireturn

  public org.hl7.fhir.dstu3.model.CodeableConcept addOutcomeCode();
    Code:
       0: new           #32                 // class org/hl7/fhir/dstu3/model/CodeableConcept
       3: dup
       4: invokespecial #34                 // Method org/hl7/fhir/dstu3/model/CodeableConcept."<init>":()V
       7: astore_1
       8: aload_0
       9: getfield      #98                 // Field outcomeCode:Ljava/util/List;
      12: ifnonnull     26
      15: aload_0
      16: new           #5                  // class java/util/ArrayList
      19: dup
      20: invokespecial #6                  // Method java/util/ArrayList."<init>":()V
      23: putfield      #98                 // Field outcomeCode:Ljava/util/List;
      26: aload_0
      27: getfield      #98                 // Field outcomeCode:Ljava/util/List;
      30: aload_1
      31: invokeinterface #13,  2           // InterfaceMethod java/util/List.add:(Ljava/lang/Object;)Z
      36: pop
      37: aload_1
      38: areturn

  public org.hl7.fhir.dstu3.model.Goal addOutcomeCode(org.hl7.fhir.dstu3.model.CodeableConcept);
    Code:
       0: aload_1
       1: ifnonnull     6
       4: aload_0
       5: areturn
       6: aload_0
       7: getfield      #98                 // Field outcomeCode:Ljava/util/List;
      10: ifnonnull     24
      13: aload_0
      14: new           #5                  // class java/util/ArrayList
      17: dup
      18: invokespecial #6                  // Method java/util/ArrayList."<init>":()V
      21: putfield      #98                 // Field outcomeCode:Ljava/util/List;
      24: aload_0
      25: getfield      #98                 // Field outcomeCode:Ljava/util/List;
      28: aload_1
      29: invokeinterface #13,  2           // InterfaceMethod java/util/List.add:(Ljava/lang/Object;)Z
      34: pop
      35: aload_0
      36: areturn

  public org.hl7.fhir.dstu3.model.CodeableConcept getOutcomeCodeFirstRep();
    Code:
       0: aload_0
       1: invokevirtual #99                 // Method getOutcomeCode:()Ljava/util/List;
       4: invokeinterface #15,  1           // InterfaceMethod java/util/List.isEmpty:()Z
       9: ifeq          17
      12: aload_0
      13: invokevirtual #100                // Method addOutcomeCode:()Lorg/hl7/fhir/dstu3/model/CodeableConcept;
      16: pop
      17: aload_0
      18: invokevirtual #99                 // Method getOutcomeCode:()Ljava/util/List;
      21: iconst_0
      22: invokeinterface #17,  2           // InterfaceMethod java/util/List.get:(I)Ljava/lang/Object;
      27: checkcast     #32                 // class org/hl7/fhir/dstu3/model/CodeableConcept
      30: areturn

  public java.util.List<org.hl7.fhir.dstu3.model.Reference> getOutcomeReference();
    Code:
       0: aload_0
       1: getfield      #101                // Field outcomeReference:Ljava/util/List;
       4: ifnonnull     18
       7: aload_0
       8: new           #5                  // class java/util/ArrayList
      11: dup
      12: invokespecial #6                  // Method java/util/ArrayList."<init>":()V
      15: putfield      #101                // Field outcomeReference:Ljava/util/List;
      18: aload_0
      19: getfield      #101                // Field outcomeReference:Ljava/util/List;
      22: areturn

  public org.hl7.fhir.dstu3.model.Goal setOutcomeReference(java.util.List<org.hl7.fhir.dstu3.model.Reference>);
    Code:
       0: aload_0
       1: aload_1
       2: putfield      #101                // Field outcomeReference:Ljava/util/List;
       5: aload_0
       6: areturn

  public boolean hasOutcomeReference();
    Code:
       0: aload_0
       1: getfield      #101                // Field outcomeReference:Ljava/util/List;
       4: ifnonnull     9
       7: iconst_0
       8: ireturn
       9: aload_0
      10: getfield      #101                // Field outcomeReference:Ljava/util/List;
      13: invokeinterface #7,  1            // InterfaceMethod java/util/List.iterator:()Ljava/util/Iterator;
      18: astore_1
      19: aload_1
      20: invokeinterface #8,  1            // InterfaceMethod java/util/Iterator.hasNext:()Z
      25: ifeq          50
      28: aload_1
      29: invokeinterface #9,  1            // InterfaceMethod java/util/Iterator.next:()Ljava/lang/Object;
      34: checkcast     #42                 // class org/hl7/fhir/dstu3/model/Reference
      37: astore_2
      38: aload_2
      39: invokevirtual #44                 // Method org/hl7/fhir/dstu3/model/Reference.isEmpty:()Z
      42: ifne          47
      45: iconst_1
      46: ireturn
      47: goto          19
      50: iconst_0
      51: ireturn

  public org.hl7.fhir.dstu3.model.Reference addOutcomeReference();
    Code:
       0: new           #42                 // class org/hl7/fhir/dstu3/model/Reference
       3: dup
       4: invokespecial #43                 // Method org/hl7/fhir/dstu3/model/Reference."<init>":()V
       7: astore_1
       8: aload_0
       9: getfield      #101                // Field outcomeReference:Ljava/util/List;
      12: ifnonnull     26
      15: aload_0
      16: new           #5                  // class java/util/ArrayList
      19: dup
      20: invokespecial #6                  // Method java/util/ArrayList."<init>":()V
      23: putfield      #101                // Field outcomeReference:Ljava/util/List;
      26: aload_0
      27: getfield      #101                // Field outcomeReference:Ljava/util/List;
      30: aload_1
      31: invokeinterface #13,  2           // InterfaceMethod java/util/List.add:(Ljava/lang/Object;)Z
      36: pop
      37: aload_1
      38: areturn

  public org.hl7.fhir.dstu3.model.Goal addOutcomeReference(org.hl7.fhir.dstu3.model.Reference);
    Code:
       0: aload_1
       1: ifnonnull     6
       4: aload_0
       5: areturn
       6: aload_0
       7: getfield      #101                // Field outcomeReference:Ljava/util/List;
      10: ifnonnull     24
      13: aload_0
      14: new           #5                  // class java/util/ArrayList
      17: dup
      18: invokespecial #6                  // Method java/util/ArrayList."<init>":()V
      21: putfield      #101                // Field outcomeReference:Ljava/util/List;
      24: aload_0
      25: getfield      #101                // Field outcomeReference:Ljava/util/List;
      28: aload_1
      29: invokeinterface #13,  2           // InterfaceMethod java/util/List.add:(Ljava/lang/Object;)Z
      34: pop
      35: aload_0
      36: areturn

  public org.hl7.fhir.dstu3.model.Reference getOutcomeReferenceFirstRep();
    Code:
       0: aload_0
       1: invokevirtual #102                // Method getOutcomeReference:()Ljava/util/List;
       4: invokeinterface #15,  1           // InterfaceMethod java/util/List.isEmpty:()Z
       9: ifeq          17
      12: aload_0
      13: invokevirtual #103                // Method addOutcomeReference:()Lorg/hl7/fhir/dstu3/model/Reference;
      16: pop
      17: aload_0
      18: invokevirtual #102                // Method getOutcomeReference:()Ljava/util/List;
      21: iconst_0
      22: invokeinterface #17,  2           // InterfaceMethod java/util/List.get:(I)Ljava/lang/Object;
      27: checkcast     #42                 // class org/hl7/fhir/dstu3/model/Reference
      30: areturn

  public java.util.List<org.hl7.fhir.dstu3.model.Observation> getOutcomeReferenceTarget();
    Code:
       0: aload_0
       1: getfield      #104                // Field outcomeReferenceTarget:Ljava/util/List;
       4: ifnonnull     18
       7: aload_0
       8: new           #5                  // class java/util/ArrayList
      11: dup
      12: invokespecial #6                  // Method java/util/ArrayList."<init>":()V
      15: putfield      #104                // Field outcomeReferenceTarget:Ljava/util/List;
      18: aload_0
      19: getfield      #104                // Field outcomeReferenceTarget:Ljava/util/List;
      22: areturn

  public org.hl7.fhir.dstu3.model.Observation addOutcomeReferenceTarget();
    Code:
       0: new           #105                // class org/hl7/fhir/dstu3/model/Observation
       3: dup
       4: invokespecial #106                // Method org/hl7/fhir/dstu3/model/Observation."<init>":()V
       7: astore_1
       8: aload_0
       9: getfield      #104                // Field outcomeReferenceTarget:Ljava/util/List;
      12: ifnonnull     26
      15: aload_0
      16: new           #5                  // class java/util/ArrayList
      19: dup
      20: invokespecial #6                  // Method java/util/ArrayList."<init>":()V
      23: putfield      #104                // Field outcomeReferenceTarget:Ljava/util/List;
      26: aload_0
      27: getfield      #104                // Field outcomeReferenceTarget:Ljava/util/List;
      30: aload_1
      31: invokeinterface #13,  2           // InterfaceMethod java/util/List.add:(Ljava/lang/Object;)Z
      36: pop
      37: aload_1
      38: areturn

  protected void listChildren(java.util.List<org.hl7.fhir.dstu3.model.Property>);
    Code:
       0: aload_0
       1: aload_1
       2: invokespecial #107                // Method org/hl7/fhir/dstu3/model/DomainResource.listChildren:(Ljava/util/List;)V
       5: aload_1
       6: new           #108                // class org/hl7/fhir/dstu3/model/Property
       9: dup
      10: ldc           #109                // String identifier
      12: ldc           #110                // String Identifier
      14: ldc           #111                // String This records identifiers associated with this care plan that are defined by business processes and/or used to refer to it when a direct URL reference to the resource itself is not appropriate (e.g. in CDA documents, or in written / printed documentation).
      16: iconst_0
      17: ldc           #113                // int 2147483647
      19: aload_0
      20: getfield      #4                  // Field identifier:Ljava/util/List;
      23: invokespecial #114                // Method org/hl7/fhir/dstu3/model/Property."<init>":(Ljava/lang/String;Ljava/lang/String;Ljava/lang/String;IILjava/util/List;)V
      26: invokeinterface #13,  2           // InterfaceMethod java/util/List.add:(Ljava/lang/Object;)Z
      31: pop
      32: aload_1
      33: new           #108                // class org/hl7/fhir/dstu3/model/Property
      36: dup
      37: ldc           #115                // String status
      39: ldc           #116                // String code
      41: ldc           #117                // String Indicates whether the goal has been reached and is still considered relevant.
      43: iconst_0
      44: iconst_1
      45: aload_0
      46: getfield      #2                  // Field status:Lorg/hl7/fhir/dstu3/model/Enumeration;
      49: invokespecial #118                // Method org/hl7/fhir/dstu3/model/Property."<init>":(Ljava/lang/String;Ljava/lang/String;Ljava/lang/String;IILorg/hl7/fhir/dstu3/model/Base;)V
      52: invokeinterface #13,  2           // InterfaceMethod java/util/List.add:(Ljava/lang/Object;)Z
      57: pop
      58: aload_1
      59: new           #108                // class org/hl7/fhir/dstu3/model/Property
      62: dup
      63: ldc           #119                // String category
      65: ldc           #120                // String CodeableConcept
      67: ldc           #121                // String Indicates a category the goal falls within.
      69: iconst_0
      70: ldc           #113                // int 2147483647
      72: aload_0
      73: getfield      #31                 // Field category:Ljava/util/List;
      76: invokespecial #114                // Method org/hl7/fhir/dstu3/model/Property."<init>":(Ljava/lang/String;Ljava/lang/String;Ljava/lang/String;IILjava/util/List;)V
      79: invokeinterface #13,  2           // InterfaceMethod java/util/List.add:(Ljava/lang/Object;)Z
      84: pop
      85: aload_1
      86: new           #108                // class org/hl7/fhir/dstu3/model/Property
      89: dup
      90: ldc           #122                // String priority
      92: ldc           #120                // String CodeableConcept
      94: ldc           #123                // String Identifies the mutually agreed level of importance associated with reaching/sustaining the goal.
      96: iconst_0
      97: iconst_1
      98: aload_0
      99: getfield      #37                 // Field priority:Lorg/hl7/fhir/dstu3/model/CodeableConcept;
     102: invokespecial #118                // Method org/hl7/fhir/dstu3/model/Property."<init>":(Ljava/lang/String;Ljava/lang/String;Ljava/lang/String;IILorg/hl7/fhir/dstu3/model/Base;)V
     105: invokeinterface #13,  2           // InterfaceMethod java/util/List.add:(Ljava/lang/Object;)Z
     110: pop
     111: aload_1
     112: new           #108                // class org/hl7/fhir/dstu3/model/Property
     115: dup
     116: ldc           #124                // String description
     118: ldc           #120                // String CodeableConcept
     120: ldc           #125                // String Human-readable and/or coded description of a specific desired objective of care, such as \"control blood pressure\" or \"negotiate an obstacle course\" or \"dance with child at wedding\".
     122: iconst_0
     123: iconst_1
     124: aload_0
     125: getfield      #3                  // Field description:Lorg/hl7/fhir/dstu3/model/CodeableConcept;
     128: invokespecial #118                // Method org/hl7/fhir/dstu3/model/Property."<init>":(Ljava/lang/String;Ljava/lang/String;Ljava/lang/String;IILorg/hl7/fhir/dstu3/model/Base;)V
     131: invokeinterface #13,  2           // InterfaceMethod java/util/List.add:(Ljava/lang/Object;)Z
     136: pop
     137: aload_1
     138: new           #108                // class org/hl7/fhir/dstu3/model/Property
     141: dup
     142: ldc           #126                // String subject
     144: ldc           #127                // String Reference(Patient|Group|Organization)
     146: ldc           #128                // String Identifies the patient, group or organization for whom the goal is being established.
     148: iconst_0
     149: iconst_1
     150: aload_0
     151: getfield      #40                 // Field subject:Lorg/hl7/fhir/dstu3/model/Reference;
     154: invokespecial #118                // Method org/hl7/fhir/dstu3/model/Property."<init>":(Ljava/lang/String;Ljava/lang/String;Ljava/lang/String;IILorg/hl7/fhir/dstu3/model/Base;)V
     157: invokeinterface #13,  2           // InterfaceMethod java/util/List.add:(Ljava/lang/Object;)Z
     162: pop
     163: aload_1
     164: new           #108                // class org/hl7/fhir/dstu3/model/Property
     167: dup
     168: ldc           #129                // String start[x]
     170: ldc           #130                // String date|CodeableConcept
     172: ldc           #131                // String The date or event after which the goal should begin being pursued.
     174: iconst_0
     175: iconst_1
     176: aload_0
     177: getfield      #46                 // Field start:Lorg/hl7/fhir/dstu3/model/Type;
     180: invokespecial #118                // Method org/hl7/fhir/dstu3/model/Property."<init>":(Ljava/lang/String;Ljava/lang/String;Ljava/lang/String;IILorg/hl7/fhir/dstu3/model/Base;)V
     183: invokeinterface #13,  2           // InterfaceMethod java/util/List.add:(Ljava/lang/Object;)Z
     188: pop
     189: aload_1
     190: new           #108                // class org/hl7/fhir/dstu3/model/Property
     193: dup
     194: ldc           #132                // String target
     196: ldc           #133                // String
     198: ldc           #134                // String Indicates what should be done by when.
     200: iconst_0
     201: iconst_1
     202: aload_0
     203: getfield      #64                 // Field target:Lorg/hl7/fhir/dstu3/model/Goal$GoalTargetComponent;
     206: invokespecial #118                // Method org/hl7/fhir/dstu3/model/Property."<init>":(Ljava/lang/String;Ljava/lang/String;Ljava/lang/String;IILorg/hl7/fhir/dstu3/model/Base;)V
     209: invokeinterface #13,  2           // InterfaceMethod java/util/List.add:(Ljava/lang/Object;)Z
     214: pop
     215: aload_1
     216: new           #108                // class org/hl7/fhir/dstu3/model/Property
     219: dup
     220: ldc           #135                // String statusDate
     222: ldc           #136                // String date
     224: ldc           #137                // String Identifies when the current status.  I.e. When initially created, when achieved, when cancelled, etc.
     226: iconst_0
     227: iconst_1
     228: aload_0
     229: getfield      #69                 // Field statusDate:Lorg/hl7/fhir/dstu3/model/DateType;
     232: invokespecial #118                // Method org/hl7/fhir/dstu3/model/Property."<init>":(Ljava/lang/String;Ljava/lang/String;Ljava/lang/String;IILorg/hl7/fhir/dstu3/model/Base;)V
     235: invokeinterface #13,  2           // InterfaceMethod java/util/List.add:(Ljava/lang/Object;)Z
     240: pop
     241: aload_1
     242: new           #108                // class org/hl7/fhir/dstu3/model/Property
     245: dup
     246: ldc           #138                // String statusReason
     248: ldc           #139                // String string
     250: ldc           #140                // String Captures the reason for the current status.
     252: iconst_0
     253: iconst_1
     254: aload_0
     255: getfield      #76                 // Field statusReason:Lorg/hl7/fhir/dstu3/model/StringType;
     258: invokespecial #118                // Method org/hl7/fhir/dstu3/model/Property."<init>":(Ljava/lang/String;Ljava/lang/String;Ljava/lang/String;IILorg/hl7/fhir/dstu3/model/Base;)V
     261: invokeinterface #13,  2           // InterfaceMethod java/util/List.add:(Ljava/lang/Object;)Z
     266: pop
     267: aload_1
     268: new           #108                // class org/hl7/fhir/dstu3/model/Property
     271: dup
     272: ldc           #141                // String expressedBy
     274: ldc           #142                // String Reference(Patient|Practitioner|RelatedPerson)
     276: ldc           #143                // String Indicates whose goal this is - patient goal, practitioner goal, etc.
     278: iconst_0
     279: iconst_1
     280: aload_0
     281: getfield      #85                 // Field expressedBy:Lorg/hl7/fhir/dstu3/model/Reference;
     284: invokespecial #118                // Method org/hl7/fhir/dstu3/model/Property."<init>":(Ljava/lang/String;Ljava/lang/String;Ljava/lang/String;IILorg/hl7/fhir/dstu3/model/Base;)V
     287: invokeinterface #13,  2           // InterfaceMethod java/util/List.add:(Ljava/lang/Object;)Z
     292: pop
     293: aload_1
     294: new           #108                // class org/hl7/fhir/dstu3/model/Property
     297: dup
     298: ldc           #144                // String addresses
     300: ldc           #145                // String Reference(Condition|Observation|MedicationStatement|NutritionOrder|ProcedureRequest|RiskAssessment)
     302: ldc           #146                // String The identified conditions and other health record elements that are intended to be addressed by the goal.
     304: iconst_0
     305: ldc           #113                // int 2147483647
     307: aload_0
     308: getfield      #88                 // Field addresses:Ljava/util/List;
     311: invokespecial #114                // Method org/hl7/fhir/dstu3/model/Property."<init>":(Ljava/lang/String;Ljava/lang/String;Ljava/lang/String;IILjava/util/List;)V
     314: invokeinterface #13,  2           // InterfaceMethod java/util/List.add:(Ljava/lang/Object;)Z
     319: pop
     320: aload_1
     321: new           #108                // class org/hl7/fhir/dstu3/model/Property
     324: dup
     325: ldc           #147                // String note
     327: ldc           #148                // String Annotation
     329: ldc           #149                // String Any comments related to the goal.
     331: iconst_0
     332: ldc           #113                // int 2147483647
     334: aload_0
     335: getfield      #92                 // Field note:Ljava/util/List;
     338: invokespecial #114                // Method org/hl7/fhir/dstu3/model/Property."<init>":(Ljava/lang/String;Ljava/lang/String;Ljava/lang/String;IILjava/util/List;)V
     341: invokeinterface #13,  2           // InterfaceMethod java/util/List.add:(Ljava/lang/Object;)Z
     346: pop
     347: aload_1
     348: new           #108                // class org/hl7/fhir/dstu3/model/Property
     351: dup
     352: ldc           #150                // String outcomeCode
     354: ldc           #120                // String CodeableConcept
     356: ldc           #151                // String Identifies the change (or lack of change) at the point when the status of the goal is assessed.
     358: iconst_0
     359: ldc           #113                // int 2147483647
     361: aload_0
     362: getfield      #98                 // Field outcomeCode:Ljava/util/List;
     365: invokespecial #114                // Method org/hl7/fhir/dstu3/model/Property."<init>":(Ljava/lang/String;Ljava/lang/String;Ljava/lang/String;IILjava/util/List;)V
     368: invokeinterface #13,  2           // InterfaceMethod java/util/List.add:(Ljava/lang/Object;)Z
     373: pop
     374: aload_1
     375: new           #108                // class org/hl7/fhir/dstu3/model/Property
     378: dup
     379: ldc           #152                // String outcomeReference
     381: ldc           #153                // String Reference(Observation)
     383: ldc           #154                // String Details of what\'s changed (or not changed).
     385: iconst_0
     386: ldc           #113                // int 2147483647
     388: aload_0
     389: getfield      #101                // Field outcomeReference:Ljava/util/List;
     392: invokespecial #114                // Method org/hl7/fhir/dstu3/model/Property."<init>":(Ljava/lang/String;Ljava/lang/String;Ljava/lang/String;IILjava/util/List;)V
     395: invokeinterface #13,  2           // InterfaceMethod java/util/List.add:(Ljava/lang/Object;)Z
     400: pop
     401: return

  public org.hl7.fhir.dstu3.model.Property getNamedProperty(int, java.lang.String, boolean) throws org.hl7.fhir.exceptions.FHIRException;
    Code:
       0: iload_1
       1: lookupswitch  { // 18
           -2129778896: 318
           -1867885268: 258
           -1758833953: 338
           -1724546052: 238
           -1618432855: 156
           -1165461084: 218
            -892481550: 177
            -880905839: 358
            -782273511: 501
               3387378: 459
              50511102: 197
             109757538: 298
             175423686: 418
             247524032: 378
             874544034: 438
            1062482015: 480
            1316793566: 278
            2051346646: 398
               default: 522
          }
     156: new           #108                // class org/hl7/fhir/dstu3/model/Property
     159: dup
     160: ldc           #109                // String identifier
     162: ldc           #110                // String Identifier
     164: ldc           #111                // String This records identifiers associated with this care plan that are defined by business processes and/or used to refer to it when a direct URL reference to the resource itself is not appropriate (e.g. in CDA documents, or in written / printed documentation).
     166: iconst_0
     167: ldc           #113                // int 2147483647
     169: aload_0
     170: getfield      #4                  // Field identifier:Ljava/util/List;
     173: invokespecial #114                // Method org/hl7/fhir/dstu3/model/Property."<init>":(Ljava/lang/String;Ljava/lang/String;Ljava/lang/String;IILjava/util/List;)V
     176: areturn
     177: new           #108                // class org/hl7/fhir/dstu3/model/Property
     180: dup
     181: ldc           #115                // String status
     183: ldc           #116                // String code
     185: ldc           #117                // String Indicates whether the goal has been reached and is still considered relevant.
     187: iconst_0
     188: iconst_1
     189: aload_0
     190: getfield      #2                  // Field status:Lorg/hl7/fhir/dstu3/model/Enumeration;
     193: invokespecial #118                // Method org/hl7/fhir/dstu3/model/Property."<init>":(Ljava/lang/String;Ljava/lang/String;Ljava/lang/String;IILorg/hl7/fhir/dstu3/model/Base;)V
     196: areturn
     197: new           #108                // class org/hl7/fhir/dstu3/model/Property
     200: dup
     201: ldc           #119                // String category
     203: ldc           #120                // String CodeableConcept
     205: ldc           #121                // String Indicates a category the goal falls within.
     207: iconst_0
     208: ldc           #113                // int 2147483647
     210: aload_0
     211: getfield      #31                 // Field category:Ljava/util/List;
     214: invokespecial #114                // Method org/hl7/fhir/dstu3/model/Property."<init>":(Ljava/lang/String;Ljava/lang/String;Ljava/lang/String;IILjava/util/List;)V
     217: areturn
     218: new           #108                // class org/hl7/fhir/dstu3/model/Property
     221: dup
     222: ldc           #122                // String priority
     224: ldc           #120                // String CodeableConcept
     226: ldc           #123                // String Identifies the mutually agreed level of importance associated with reaching/sustaining the goal.
     228: iconst_0
     229: iconst_1
     230: aload_0
     231: getfield      #37                 // Field priority:Lorg/hl7/fhir/dstu3/model/CodeableConcept;
     234: invokespecial #118                // Method org/hl7/fhir/dstu3/model/Property."<init>":(Ljava/lang/String;Ljava/lang/String;Ljava/lang/String;IILorg/hl7/fhir/dstu3/model/Base;)V
     237: areturn
     238: new           #108                // class org/hl7/fhir/dstu3/model/Property
     241: dup
     242: ldc           #124                // String description
     244: ldc           #120                // String CodeableConcept
     246: ldc           #125                // String Human-readable and/or coded description of a specific desired objective of care, such as \"control blood pressure\" or \"negotiate an obstacle course\" or \"dance with child at wedding\".
     248: iconst_0
     249: iconst_1
     250: aload_0
     251: getfield      #3                  // Field description:Lorg/hl7/fhir/dstu3/model/CodeableConcept;
     254: invokespecial #118                // Method org/hl7/fhir/dstu3/model/Property."<init>":(Ljava/lang/String;Ljava/lang/String;Ljava/lang/String;IILorg/hl7/fhir/dstu3/model/Base;)V
     257: areturn
     258: new           #108                // class org/hl7/fhir/dstu3/model/Property
     261: dup
     262: ldc           #126                // String subject
     264: ldc           #127                // String Reference(Patient|Group|Organization)
     266: ldc           #128                // String Identifies the patient, group or organization for whom the goal is being established.
     268: iconst_0
     269: iconst_1
     270: aload_0
     271: getfield      #40                 // Field subject:Lorg/hl7/fhir/dstu3/model/Reference;
     274: invokespecial #118                // Method org/hl7/fhir/dstu3/model/Property."<init>":(Ljava/lang/String;Ljava/lang/String;Ljava/lang/String;IILorg/hl7/fhir/dstu3/model/Base;)V
     277: areturn
     278: new           #108                // class org/hl7/fhir/dstu3/model/Property
     281: dup
     282: ldc           #129                // String start[x]
     284: ldc           #130                // String date|CodeableConcept
     286: ldc           #131                // String The date or event after which the goal should begin being pursued.
     288: iconst_0
     289: iconst_1
     290: aload_0
     291: getfield      #46                 // Field start:Lorg/hl7/fhir/dstu3/model/Type;
     294: invokespecial #118                // Method org/hl7/fhir/dstu3/model/Property."<init>":(Ljava/lang/String;Ljava/lang/String;Ljava/lang/String;IILorg/hl7/fhir/dstu3/model/Base;)V
     297: areturn
     298: new           #108                // class org/hl7/fhir/dstu3/model/Property
     301: dup
     302: ldc           #129                // String start[x]
     304: ldc           #130                // String date|CodeableConcept
     306: ldc           #131                // String The date or event after which the goal should begin being pursued.
     308: iconst_0
     309: iconst_1
     310: aload_0
     311: getfield      #46                 // Field start:Lorg/hl7/fhir/dstu3/model/Type;
     314: invokespecial #118                // Method org/hl7/fhir/dstu3/model/Property."<init>":(Ljava/lang/String;Ljava/lang/String;Ljava/lang/String;IILorg/hl7/fhir/dstu3/model/Base;)V
     317: areturn
     318: new           #108                // class org/hl7/fhir/dstu3/model/Property
     321: dup
     322: ldc           #129                // String start[x]
     324: ldc           #130                // String date|CodeableConcept
     326: ldc           #131                // String The date or event after which the goal should begin being pursued.
     328: iconst_0
     329: iconst_1
     330: aload_0
     331: getfield      #46                 // Field start:Lorg/hl7/fhir/dstu3/model/Type;
     334: invokespecial #118                // Method org/hl7/fhir/dstu3/model/Property."<init>":(Ljava/lang/String;Ljava/lang/String;Ljava/lang/String;IILorg/hl7/fhir/dstu3/model/Base;)V
     337: areturn
     338: new           #108                // class org/hl7/fhir/dstu3/model/Property
     341: dup
     342: ldc           #129                // String start[x]
     344: ldc           #130                // String date|CodeableConcept
     346: ldc           #131                // String The date or event after which the goal should begin being pursued.
     348: iconst_0
     349: iconst_1
     350: aload_0
     351: getfield      #46                 // Field start:Lorg/hl7/fhir/dstu3/model/Type;
     354: invokespecial #118                // Method org/hl7/fhir/dstu3/model/Property."<init>":(Ljava/lang/String;Ljava/lang/String;Ljava/lang/String;IILorg/hl7/fhir/dstu3/model/Base;)V
     357: areturn
     358: new           #108                // class org/hl7/fhir/dstu3/model/Property
     361: dup
     362: ldc           #132                // String target
     364: ldc           #133                // String
     366: ldc           #134                // String Indicates what should be done by when.
     368: iconst_0
     369: iconst_1
     370: aload_0
     371: getfield      #64                 // Field target:Lorg/hl7/fhir/dstu3/model/Goal$GoalTargetComponent;
     374: invokespecial #118                // Method org/hl7/fhir/dstu3/model/Property."<init>":(Ljava/lang/String;Ljava/lang/String;Ljava/lang/String;IILorg/hl7/fhir/dstu3/model/Base;)V
     377: areturn
     378: new           #108                // class org/hl7/fhir/dstu3/model/Property
     381: dup
     382: ldc           #135                // String statusDate
     384: ldc           #136                // String date
     386: ldc           #137                // String Identifies when the current status.  I.e. When initially created, when achieved, when cancelled, etc.
     388: iconst_0
     389: iconst_1
     390: aload_0
     391: getfield      #69                 // Field statusDate:Lorg/hl7/fhir/dstu3/model/DateType;
     394: invokespecial #118                // Method org/hl7/fhir/dstu3/model/Property."<init>":(Ljava/lang/String;Ljava/lang/String;Ljava/lang/String;IILorg/hl7/fhir/dstu3/model/Base;)V
     397: areturn
     398: new           #108                // class org/hl7/fhir/dstu3/model/Property
     401: dup
     402: ldc           #138                // String statusReason
     404: ldc           #139                // String string
     406: ldc           #140                // String Captures the reason for the current status.
     408: iconst_0
     409: iconst_1
     410: aload_0
     411: getfield      #76                 // Field statusReason:Lorg/hl7/fhir/dstu3/model/StringType;
     414: invokespecial #118                // Method org/hl7/fhir/dstu3/model/Property."<init>":(Ljava/lang/String;Ljava/lang/String;Ljava/lang/String;IILorg/hl7/fhir/dstu3/model/Base;)V
     417: areturn
     418: new           #108                // class org/hl7/fhir/dstu3/model/Property
     421: dup
     422: ldc           #141                // String expressedBy
     424: ldc           #142                // String Reference(Patient|Practitioner|RelatedPerson)
     426: ldc           #143                // String Indicates whose goal this is - patient goal, practitioner goal, etc.
     428: iconst_0
     429: iconst_1
     430: aload_0
     431: getfield      #85                 // Field expressedBy:Lorg/hl7/fhir/dstu3/model/Reference;
     434: invokespecial #118                // Method org/hl7/fhir/dstu3/model/Property."<init>":(Ljava/lang/String;Ljava/lang/String;Ljava/lang/String;IILorg/hl7/fhir/dstu3/model/Base;)V
     437: areturn
     438: new           #108                // class org/hl7/fhir/dstu3/model/Property
     441: dup
     442: ldc           #144                // String addresses
     444: ldc           #145                // String Reference(Condition|Observation|MedicationStatement|NutritionOrder|ProcedureRequest|RiskAssessment)
     446: ldc           #146                // String The identified conditions and other health record elements that are intended to be addressed by the goal.
     448: iconst_0
     449: ldc           #113                // int 2147483647
     451: aload_0
     452: getfield      #88                 // Field addresses:Ljava/util/List;
     455: invokespecial #114                // Method org/hl7/fhir/dstu3/model/Property."<init>":(Ljava/lang/String;Ljava/lang/String;Ljava/lang/String;IILjava/util/List;)V
     458: areturn
     459: new           #108                // class org/hl7/fhir/dstu3/model/Property
     462: dup
     463: ldc           #147                // String note
     465: ldc           #148                // String Annotation
     467: ldc           #149                // String Any comments related to the goal.
     469: iconst_0
     470: ldc           #113                // int 2147483647
     472: aload_0
     473: getfield      #92                 // Field note:Ljava/util/List;
     476: invokespecial #114                // Method org/hl7/fhir/dstu3/model/Property."<init>":(Ljava/lang/String;Ljava/lang/String;Ljava/lang/String;IILjava/util/List;)V
     479: areturn
     480: new           #108                // class org/hl7/fhir/dstu3/model/Property
     483: dup
     484: ldc           #150                // String outcomeCode
     486: ldc           #120                // String CodeableConcept
     488: ldc           #151                // String Identifies the change (or lack of change) at the point when the status of the goal is assessed.
     490: iconst_0
     491: ldc           #113                // int 2147483647
     493: aload_0
     494: getfield      #98                 // Field outcomeCode:Ljava/util/List;
     497: invokespecial #114                // Method org/hl7/fhir/dstu3/model/Property."<init>":(Ljava/lang/String;Ljava/lang/String;Ljava/lang/String;IILjava/util/List;)V
     500: areturn
     501: new           #108                // class org/hl7/fhir/dstu3/model/Property
     504: dup
     505: ldc           #152                // String outcomeReference
     507: ldc           #153                // String Reference(Observation)
     509: ldc           #154                // String Details of what\'s changed (or not changed).
     511: iconst_0
     512: ldc           #113                // int 2147483647
     514: aload_0
     515: getfield      #101                // Field outcomeReference:Ljava/util/List;
     518: invokespecial #114                // Method org/hl7/fhir/dstu3/model/Property."<init>":(Ljava/lang/String;Ljava/lang/String;Ljava/lang/String;IILjava/util/List;)V
     521: areturn
     522: aload_0
     523: iload_1
     524: aload_2
     525: iload_3
     526: invokespecial #155                // Method org/hl7/fhir/dstu3/model/DomainResource.getNamedProperty:(ILjava/lang/String;Z)Lorg/hl7/fhir/dstu3/model/Property;
     529: areturn

  public org.hl7.fhir.dstu3.model.Base[] getProperty(int, java.lang.String, boolean) throws org.hl7.fhir.exceptions.FHIRException;
    Code:
       0: iload_1
       1: lookupswitch  { // 15
           -1867885268: 288
           -1724546052: 262
           -1618432855: 132
           -1165461084: 236
            -892481550: 171
            -880905839: 340
            -782273511: 561
               3387378: 483
              50511102: 197
             109757538: 314
             175423686: 418
             247524032: 366
             874544034: 444
            1062482015: 522
            2051346646: 392
               default: 600
          }
     132: aload_0
     133: getfield      #4                  // Field identifier:Ljava/util/List;
     136: ifnonnull     146
     139: iconst_0
     140: anewarray     #156                // class org/hl7/fhir/dstu3/model/Base
     143: goto          170
     146: aload_0
     147: getfield      #4                  // Field identifier:Ljava/util/List;
     150: aload_0
     151: getfield      #4                  // Field identifier:Ljava/util/List;
     154: invokeinterface #157,  1          // InterfaceMethod java/util/List.size:()I
     159: anewarray     #156                // class org/hl7/fhir/dstu3/model/Base
     162: invokeinterface #158,  2          // InterfaceMethod java/util/List.toArray:([Ljava/lang/Object;)[Ljava/lang/Object;
     167: checkcast     #159                // class "[Lorg/hl7/fhir/dstu3/model/Base;"
     170: areturn
     171: aload_0
     172: getfield      #2                  // Field status:Lorg/hl7/fhir/dstu3/model/Enumeration;
     175: ifnonnull     185
     178: iconst_0
     179: anewarray     #156                // class org/hl7/fhir/dstu3/model/Base
     182: goto          196
     185: iconst_1
     186: anewarray     #156                // class org/hl7/fhir/dstu3/model/Base
     189: dup
     190: iconst_0
     191: aload_0
     192: getfield      #2                  // Field status:Lorg/hl7/fhir/dstu3/model/Enumeration;
     195: aastore
     196: areturn
     197: aload_0
     198: getfield      #31                 // Field category:Ljava/util/List;
     201: ifnonnull     211
     204: iconst_0
     205: anewarray     #156                // class org/hl7/fhir/dstu3/model/Base
     208: goto          235
     211: aload_0
     212: getfield      #31                 // Field category:Ljava/util/List;
     215: aload_0
     216: getfield      #31                 // Field category:Ljava/util/List;
     219: invokeinterface #157,  1          // InterfaceMethod java/util/List.size:()I
     224: anewarray     #156                // class org/hl7/fhir/dstu3/model/Base
     227: invokeinterface #158,  2          // InterfaceMethod java/util/List.toArray:([Ljava/lang/Object;)[Ljava/lang/Object;
     232: checkcast     #159                // class "[Lorg/hl7/fhir/dstu3/model/Base;"
     235: areturn
     236: aload_0
     237: getfield      #37                 // Field priority:Lorg/hl7/fhir/dstu3/model/CodeableConcept;
     240: ifnonnull     250
     243: iconst_0
     244: anewarray     #156                // class org/hl7/fhir/dstu3/model/Base
     247: goto          261
     250: iconst_1
     251: anewarray     #156                // class org/hl7/fhir/dstu3/model/Base
     254: dup
     255: iconst_0
     256: aload_0
     257: getfield      #37                 // Field priority:Lorg/hl7/fhir/dstu3/model/CodeableConcept;
     260: aastore
     261: areturn
     262: aload_0
     263: getfield      #3                  // Field description:Lorg/hl7/fhir/dstu3/model/CodeableConcept;
     266: ifnonnull     276
     269: iconst_0
     270: anewarray     #156                // class org/hl7/fhir/dstu3/model/Base
     273: goto          287
     276: iconst_1
     277: anewarray     #156                // class org/hl7/fhir/dstu3/model/Base
     280: dup
     281: iconst_0
     282: aload_0
     283: getfield      #3                  // Field description:Lorg/hl7/fhir/dstu3/model/CodeableConcept;
     286: aastore
     287: areturn
     288: aload_0
     289: getfield      #40                 // Field subject:Lorg/hl7/fhir/dstu3/model/Reference;
     292: ifnonnull     302
     295: iconst_0
     296: anewarray     #156                // class org/hl7/fhir/dstu3/model/Base
     299: goto          313
     302: iconst_1
     303: anewarray     #156                // class org/hl7/fhir/dstu3/model/Base
     306: dup
     307: iconst_0
     308: aload_0
     309: getfield      #40                 // Field subject:Lorg/hl7/fhir/dstu3/model/Reference;
     312: aastore
     313: areturn
     314: aload_0
     315: getfield      #46                 // Field start:Lorg/hl7/fhir/dstu3/model/Type;
     318: ifnonnull     328
     321: iconst_0
     322: anewarray     #156                // class org/hl7/fhir/dstu3/model/Base
     325: goto          339
     328: iconst_1
     329: anewarray     #156                // class org/hl7/fhir/dstu3/model/Base
     332: dup
     333: iconst_0
     334: aload_0
     335: getfield      #46                 // Field start:Lorg/hl7/fhir/dstu3/model/Type;
     338: aastore
     339: areturn
     340: aload_0
     341: getfield      #64                 // Field target:Lorg/hl7/fhir/dstu3/model/Goal$GoalTargetComponent;
     344: ifnonnull     354
     347: iconst_0
     348: anewarray     #156                // class org/hl7/fhir/dstu3/model/Base
     351: goto          365
     354: iconst_1
     355: anewarray     #156                // class org/hl7/fhir/dstu3/model/Base
     358: dup
     359: iconst_0
     360: aload_0
     361: getfield      #64                 // Field target:Lorg/hl7/fhir/dstu3/model/Goal$GoalTargetComponent;
     364: aastore
     365: areturn
     366: aload_0
     367: getfield      #69                 // Field statusDate:Lorg/hl7/fhir/dstu3/model/DateType;
     370: ifnonnull     380
     373: iconst_0
     374: anewarray     #156                // class org/hl7/fhir/dstu3/model/Base
     377: goto          391
     380: iconst_1
     381: anewarray     #156                // class org/hl7/fhir/dstu3/model/Base
     384: dup
     385: iconst_0
     386: aload_0
     387: getfield      #69                 // Field statusDate:Lorg/hl7/fhir/dstu3/model/DateType;
     390: aastore
     391: areturn
     392: aload_0
     393: getfield      #76                 // Field statusReason:Lorg/hl7/fhir/dstu3/model/StringType;
     396: ifnonnull     406
     399: iconst_0
     400: anewarray     #156                // class org/hl7/fhir/dstu3/model/Base
     403: goto          417
     406: iconst_1
     407: anewarray     #156                // class org/hl7/fhir/dstu3/model/Base
     410: dup
     411: iconst_0
     412: aload_0
     413: getfield      #76                 // Field statusReason:Lorg/hl7/fhir/dstu3/model/StringType;
     416: aastore
     417: areturn
     418: aload_0
     419: getfield      #85                 // Field expressedBy:Lorg/hl7/fhir/dstu3/model/Reference;
     422: ifnonnull     432
     425: iconst_0
     426: anewarray     #156                // class org/hl7/fhir/dstu3/model/Base
     429: goto          443
     432: iconst_1
     433: anewarray     #156                // class org/hl7/fhir/dstu3/model/Base
     436: dup
     437: iconst_0
     438: aload_0
     439: getfield      #85                 // Field expressedBy:Lorg/hl7/fhir/dstu3/model/Reference;
     442: aastore
     443: areturn
     444: aload_0
     445: getfield      #88                 // Field addresses:Ljava/util/List;
     448: ifnonnull     458
     451: iconst_0
     452: anewarray     #156                // class org/hl7/fhir/dstu3/model/Base
     455: goto          482
     458: aload_0
     459: getfield      #88                 // Field addresses:Ljava/util/List;
     462: aload_0
     463: getfield      #88                 // Field addresses:Ljava/util/List;
     466: invokeinterface #157,  1          // InterfaceMethod java/util/List.size:()I
     471: anewarray     #156                // class org/hl7/fhir/dstu3/model/Base
     474: invokeinterface #158,  2          // InterfaceMethod java/util/List.toArray:([Ljava/lang/Object;)[Ljava/lang/Object;
     479: checkcast     #159                // class "[Lorg/hl7/fhir/dstu3/model/Base;"
     482: areturn
     483: aload_0
     484: getfield      #92                 // Field note:Ljava/util/List;
     487: ifnonnull     497
     490: iconst_0
     491: anewarray     #156                // class org/hl7/fhir/dstu3/model/Base
     494: goto          521
     497: aload_0
     498: getfield      #92                 // Field note:Ljava/util/List;
     501: aload_0
     502: getfield      #92                 // Field note:Ljava/util/List;
     505: invokeinterface #157,  1          // InterfaceMethod java/util/List.size:()I
     510: anewarray     #156                // class org/hl7/fhir/dstu3/model/Base
     513: invokeinterface #158,  2          // InterfaceMethod java/util/List.toArray:([Ljava/lang/Object;)[Ljava/lang/Object;
     518: checkcast     #159                // class "[Lorg/hl7/fhir/dstu3/model/Base;"
     521: areturn
     522: aload_0
     523: getfield      #98                 // Field outcomeCode:Ljava/util/List;
     526: ifnonnull     536
     529: iconst_0
     530: anewarray     #156                // class org/hl7/fhir/dstu3/model/Base
     533: goto          560
     536: aload_0
     537: getfield      #98                 // Field outcomeCode:Ljava/util/List;
     540: aload_0
     541: getfield      #98                 // Field outcomeCode:Ljava/util/List;
     544: invokeinterface #157,  1          // InterfaceMethod java/util/List.size:()I
     549: anewarray     #156                // class org/hl7/fhir/dstu3/model/Base
     552: invokeinterface #158,  2          // InterfaceMethod java/util/List.toArray:([Ljava/lang/Object;)[Ljava/lang/Object;
     557: checkcast     #159                // class "[Lorg/hl7/fhir/dstu3/model/Base;"
     560: areturn
     561: aload_0
     562: getfield      #101                // Field outcomeReference:Ljava/util/List;
     565: ifnonnull     575
     568: iconst_0
     569: anewarray     #156                // class org/hl7/fhir/dstu3/model/Base
     572: goto          599
     575: aload_0
     576: getfield      #101                // Field outcomeReference:Ljava/util/List;
     579: aload_0
     580: getfield      #101                // Field outcomeReference:Ljava/util/List;
     583: invokeinterface #157,  1          // InterfaceMethod java/util/List.size:()I
     588: anewarray     #156                // class org/hl7/fhir/dstu3/model/Base
     591: invokeinterface #158,  2          // InterfaceMethod java/util/List.toArray:([Ljava/lang/Object;)[Ljava/lang/Object;
     596: checkcast     #159                // class "[Lorg/hl7/fhir/dstu3/model/Base;"
     599: areturn
     600: aload_0
     601: iload_1
     602: aload_2
     603: iload_3
     604: invokespecial #160                // Method org/hl7/fhir/dstu3/model/DomainResource.getProperty:(ILjava/lang/String;Z)[Lorg/hl7/fhir/dstu3/model/Base;
     607: areturn

  public org.hl7.fhir.dstu3.model.Base setProperty(int, java.lang.String, org.hl7.fhir.dstu3.model.Base) throws org.hl7.fhir.exceptions.FHIRException;
    Code:
       0: iload_1
       1: lookupswitch  { // 15
           -1867885268: 214
           -1724546052: 203
           -1618432855: 132
           -1165461084: 192
            -892481550: 149
            -880905839: 236
            -782273511: 330
               3387378: 296
              50511102: 175
             109757538: 225
             175423686: 268
             247524032: 246
             874544034: 279
            1062482015: 313
            2051346646: 257
               default: 347
          }
     132: aload_0
     133: invokevirtual #14                 // Method getIdentifier:()Ljava/util/List;
     136: aload_0
     137: aload_3
     138: invokevirtual #161                // Method castToIdentifier:(Lorg/hl7/fhir/dstu3/model/Base;)Lorg/hl7/fhir/dstu3/model/Identifier;
     141: invokeinterface #13,  2           // InterfaceMethod java/util/List.add:(Ljava/lang/Object;)Z
     146: pop
     147: aload_3
     148: areturn
     149: new           #24                 // class org/hl7/fhir/dstu3/model/Goal$GoalStatusEnumFactory
     152: dup
     153: invokespecial #25                 // Method org/hl7/fhir/dstu3/model/Goal$GoalStatusEnumFactory."<init>":()V
     156: aload_0
     157: aload_3
     158: invokevirtual #162                // Method castToCode:(Lorg/hl7/fhir/dstu3/model/Base;)Lorg/hl7/fhir/dstu3/model/CodeType;
     161: invokevirtual #163                // Method org/hl7/fhir/dstu3/model/Goal$GoalStatusEnumFactory.fromType:(Lorg/hl7/fhir/dstu3/model/Base;)Lorg/hl7/fhir/dstu3/model/Enumeration;
     164: astore_3
     165: aload_0
     166: aload_3
     167: checkcast     #23                 // class org/hl7/fhir/dstu3/model/Enumeration
     170: putfield      #2                  // Field status:Lorg/hl7/fhir/dstu3/model/Enumeration;
     173: aload_3
     174: areturn
     175: aload_0
     176: invokevirtual #35                 // Method getCategory:()Ljava/util/List;
     179: aload_0
     180: aload_3
     181: invokevirtual #164                // Method castToCodeableConcept:(Lorg/hl7/fhir/dstu3/model/Base;)Lorg/hl7/fhir/dstu3/model/CodeableConcept;
     184: invokeinterface #13,  2           // InterfaceMethod java/util/List.add:(Ljava/lang/Object;)Z
     189: pop
     190: aload_3
     191: areturn
     192: aload_0
     193: aload_0
     194: aload_3
     195: invokevirtual #164                // Method castToCodeableConcept:(Lorg/hl7/fhir/dstu3/model/Base;)Lorg/hl7/fhir/dstu3/model/CodeableConcept;
     198: putfield      #37                 // Field priority:Lorg/hl7/fhir/dstu3/model/CodeableConcept;
     201: aload_3
     202: areturn
     203: aload_0
     204: aload_0
     205: aload_3
     206: invokevirtual #164                // Method castToCodeableConcept:(Lorg/hl7/fhir/dstu3/model/Base;)Lorg/hl7/fhir/dstu3/model/CodeableConcept;
     209: putfield      #3                  // Field description:Lorg/hl7/fhir/dstu3/model/CodeableConcept;
     212: aload_3
     213: areturn
     214: aload_0
     215: aload_0
     216: aload_3
     217: invokevirtual #165                // Method castToReference:(Lorg/hl7/fhir/dstu3/model/Base;)Lorg/hl7/fhir/dstu3/model/Reference;
     220: putfield      #40                 // Field subject:Lorg/hl7/fhir/dstu3/model/Reference;
     223: aload_3
     224: areturn
     225: aload_0
     226: aload_0
     227: aload_3
     228: invokevirtual #166                // Method castToType:(Lorg/hl7/fhir/dstu3/model/Base;)Lorg/hl7/fhir/dstu3/model/Type;
     231: putfield      #46                 // Field start:Lorg/hl7/fhir/dstu3/model/Type;
     234: aload_3
     235: areturn
     236: aload_0
     237: aload_3
     238: checkcast     #66                 // class org/hl7/fhir/dstu3/model/Goal$GoalTargetComponent
     241: putfield      #64                 // Field target:Lorg/hl7/fhir/dstu3/model/Goal$GoalTargetComponent;
     244: aload_3
     245: areturn
     246: aload_0
     247: aload_0
     248: aload_3
     249: invokevirtual #167                // Method castToDate:(Lorg/hl7/fhir/dstu3/model/Base;)Lorg/hl7/fhir/dstu3/model/DateType;
     252: putfield      #69                 // Field statusDate:Lorg/hl7/fhir/dstu3/model/DateType;
     255: aload_3
     256: areturn
     257: aload_0
     258: aload_0
     259: aload_3
     260: invokevirtual #168                // Method castToString:(Lorg/hl7/fhir/dstu3/model/Base;)Lorg/hl7/fhir/dstu3/model/StringType;
     263: putfield      #76                 // Field statusReason:Lorg/hl7/fhir/dstu3/model/StringType;
     266: aload_3
     267: areturn
     268: aload_0
     269: aload_0
     270: aload_3
     271: invokevirtual #165                // Method castToReference:(Lorg/hl7/fhir/dstu3/model/Base;)Lorg/hl7/fhir/dstu3/model/Reference;
     274: putfield      #85                 // Field expressedBy:Lorg/hl7/fhir/dstu3/model/Reference;
     277: aload_3
     278: areturn
     279: aload_0
     280: invokevirtual #89                 // Method getAddresses:()Ljava/util/List;
     283: aload_0
     284: aload_3
     285: invokevirtual #165                // Method castToReference:(Lorg/hl7/fhir/dstu3/model/Base;)Lorg/hl7/fhir/dstu3/model/Reference;
     288: invokeinterface #13,  2           // InterfaceMethod java/util/List.add:(Ljava/lang/Object;)Z
     293: pop
     294: aload_3
     295: areturn
     296: aload_0
     297: invokevirtual #96                 // Method getNote:()Ljava/util/List;
     300: aload_0
     301: aload_3
     302: invokevirtual #169                // Method castToAnnotation:(Lorg/hl7/fhir/dstu3/model/Base;)Lorg/hl7/fhir/dstu3/model/Annotation;
     305: invokeinterface #13,  2           // InterfaceMethod java/util/List.add:(Ljava/lang/Object;)Z
     310: pop
     311: aload_3
     312: areturn
     313: aload_0
     314: invokevirtual #99                 // Method getOutcomeCode:()Ljava/util/List;
     317: aload_0
     318: aload_3
     319: invokevirtual #164                // Method castToCodeableConcept:(Lorg/hl7/fhir/dstu3/model/Base;)Lorg/hl7/fhir/dstu3/model/CodeableConcept;
     322: invokeinterface #13,  2           // InterfaceMethod java/util/List.add:(Ljava/lang/Object;)Z
     327: pop
     328: aload_3
     329: areturn
     330: aload_0
     331: invokevirtual #102                // Method getOutcomeReference:()Ljava/util/List;
     334: aload_0
     335: aload_3
     336: invokevirtual #165                // Method castToReference:(Lorg/hl7/fhir/dstu3/model/Base;)Lorg/hl7/fhir/dstu3/model/Reference;
     339: invokeinterface #13,  2           // InterfaceMethod java/util/List.add:(Ljava/lang/Object;)Z
     344: pop
     345: aload_3
     346: areturn
     347: aload_0
     348: iload_1
     349: aload_2
     350: aload_3
     351: invokespecial #170                // Method org/hl7/fhir/dstu3/model/DomainResource.setProperty:(ILjava/lang/String;Lorg/hl7/fhir/dstu3/model/Base;)Lorg/hl7/fhir/dstu3/model/Base;
     354: areturn

  public org.hl7.fhir.dstu3.model.Base setProperty(java.lang.String, org.hl7.fhir.dstu3.model.Base) throws org.hl7.fhir.exceptions.FHIRException;
    Code:
       0: aload_1
       1: ldc           #109                // String identifier
       3: invokevirtual #171                // Method java/lang/String.equals:(Ljava/lang/Object;)Z
       6: ifeq          27
       9: aload_0
      10: invokevirtual #14                 // Method getIdentifier:()Ljava/util/List;
      13: aload_0
      14: aload_2
      15: invokevirtual #161                // Method castToIdentifier:(Lorg/hl7/fhir/dstu3/model/Base;)Lorg/hl7/fhir/dstu3/model/Identifier;
      18: invokeinterface #13,  2           // InterfaceMethod java/util/List.add:(Ljava/lang/Object;)Z
      23: pop
      24: goto          372
      27: aload_1
      28: ldc           #115                // String status
      30: invokevirtual #171                // Method java/lang/String.equals:(Ljava/lang/Object;)Z
      33: ifeq          63
      36: new           #24                 // class org/hl7/fhir/dstu3/model/Goal$GoalStatusEnumFactory
      39: dup
      40: invokespecial #25                 // Method org/hl7/fhir/dstu3/model/Goal$GoalStatusEnumFactory."<init>":()V
      43: aload_0
      44: aload_2
      45: invokevirtual #162                // Method castToCode:(Lorg/hl7/fhir/dstu3/model/Base;)Lorg/hl7/fhir/dstu3/model/CodeType;
      48: invokevirtual #163                // Method org/hl7/fhir/dstu3/model/Goal$GoalStatusEnumFactory.fromType:(Lorg/hl7/fhir/dstu3/model/Base;)Lorg/hl7/fhir/dstu3/model/Enumeration;
      51: astore_2
      52: aload_0
      53: aload_2
      54: checkcast     #23                 // class org/hl7/fhir/dstu3/model/Enumeration
      57: putfield      #2                  // Field status:Lorg/hl7/fhir/dstu3/model/Enumeration;
      60: goto          372
      63: aload_1
      64: ldc           #119                // String category
      66: invokevirtual #171                // Method java/lang/String.equals:(Ljava/lang/Object;)Z
      69: ifeq          90
      72: aload_0
      73: invokevirtual #35                 // Method getCategory:()Ljava/util/List;
      76: aload_0
      77: aload_2
      78: invokevirtual #164                // Method castToCodeableConcept:(Lorg/hl7/fhir/dstu3/model/Base;)Lorg/hl7/fhir/dstu3/model/CodeableConcept;
      81: invokeinterface #13,  2           // InterfaceMethod java/util/List.add:(Ljava/lang/Object;)Z
      86: pop
      87: goto          372
      90: aload_1
      91: ldc           #122                // String priority
      93: invokevirtual #171                // Method java/lang/String.equals:(Ljava/lang/Object;)Z
      96: ifeq          111
      99: aload_0
     100: aload_0
     101: aload_2
     102: invokevirtual #164                // Method castToCodeableConcept:(Lorg/hl7/fhir/dstu3/model/Base;)Lorg/hl7/fhir/dstu3/model/CodeableConcept;
     105: putfield      #37                 // Field priority:Lorg/hl7/fhir/dstu3/model/CodeableConcept;
     108: goto          372
     111: aload_1
     112: ldc           #124                // String description
     114: invokevirtual #171                // Method java/lang/String.equals:(Ljava/lang/Object;)Z
     117: ifeq          132
     120: aload_0
     121: aload_0
     122: aload_2
     123: invokevirtual #164                // Method castToCodeableConcept:(Lorg/hl7/fhir/dstu3/model/Base;)Lorg/hl7/fhir/dstu3/model/CodeableConcept;
     126: putfield      #3                  // Field description:Lorg/hl7/fhir/dstu3/model/CodeableConcept;
     129: goto          372
     132: aload_1
     133: ldc           #126                // String subject
     135: invokevirtual #171                // Method java/lang/String.equals:(Ljava/lang/Object;)Z
     138: ifeq          153
     141: aload_0
     142: aload_0
     143: aload_2
     144: invokevirtual #165                // Method castToReference:(Lorg/hl7/fhir/dstu3/model/Base;)Lorg/hl7/fhir/dstu3/model/Reference;
     147: putfield      #40                 // Field subject:Lorg/hl7/fhir/dstu3/model/Reference;
     150: goto          372
     153: aload_1
     154: ldc           #129                // String start[x]
     156: invokevirtual #171                // Method java/lang/String.equals:(Ljava/lang/Object;)Z
     159: ifeq          174
     162: aload_0
     163: aload_0
     164: aload_2
     165: invokevirtual #166                // Method castToType:(Lorg/hl7/fhir/dstu3/model/Base;)Lorg/hl7/fhir/dstu3/model/Type;
     168: putfield      #46                 // Field start:Lorg/hl7/fhir/dstu3/model/Type;
     171: goto          372
     174: aload_1
     175: ldc           #132                // String target
     177: invokevirtual #171                // Method java/lang/String.equals:(Ljava/lang/Object;)Z
     180: ifeq          194
     183: aload_0
     184: aload_2
     185: checkcast     #66                 // class org/hl7/fhir/dstu3/model/Goal$GoalTargetComponent
     188: putfield      #64                 // Field target:Lorg/hl7/fhir/dstu3/model/Goal$GoalTargetComponent;
     191: goto          372
     194: aload_1
     195: ldc           #135                // String statusDate
     197: invokevirtual #171                // Method java/lang/String.equals:(Ljava/lang/Object;)Z
     200: ifeq          215
     203: aload_0
     204: aload_0
     205: aload_2
     206: invokevirtual #167                // Method castToDate:(Lorg/hl7/fhir/dstu3/model/Base;)Lorg/hl7/fhir/dstu3/model/DateType;
     209: putfield      #69                 // Field statusDate:Lorg/hl7/fhir/dstu3/model/DateType;
     212: goto          372
     215: aload_1
     216: ldc           #138                // String statusReason
     218: invokevirtual #171                // Method java/lang/String.equals:(Ljava/lang/Object;)Z
     221: ifeq          236
     224: aload_0
     225: aload_0
     226: aload_2
     227: invokevirtual #168                // Method castToString:(Lorg/hl7/fhir/dstu3/model/Base;)Lorg/hl7/fhir/dstu3/model/StringType;
     230: putfield      #76                 // Field statusReason:Lorg/hl7/fhir/dstu3/model/StringType;
     233: goto          372
     236: aload_1
     237: ldc           #141                // String expressedBy
     239: invokevirtual #171                // Method java/lang/String.equals:(Ljava/lang/Object;)Z
     242: ifeq          257
     245: aload_0
     246: aload_0
     247: aload_2
     248: invokevirtual #165                // Method castToReference:(Lorg/hl7/fhir/dstu3/model/Base;)Lorg/hl7/fhir/dstu3/model/Reference;
     251: putfield      #85                 // Field expressedBy:Lorg/hl7/fhir/dstu3/model/Reference;
     254: goto          372
     257: aload_1
     258: ldc           #144                // String addresses
     260: invokevirtual #171                // Method java/lang/String.equals:(Ljava/lang/Object;)Z
     263: ifeq          284
     266: aload_0
     267: invokevirtual #89                 // Method getAddresses:()Ljava/util/List;
     270: aload_0
     271: aload_2
     272: invokevirtual #165                // Method castToReference:(Lorg/hl7/fhir/dstu3/model/Base;)Lorg/hl7/fhir/dstu3/model/Reference;
     275: invokeinterface #13,  2           // InterfaceMethod java/util/List.add:(Ljava/lang/Object;)Z
     280: pop
     281: goto          372
     284: aload_1
     285: ldc           #147                // String note
     287: invokevirtual #171                // Method java/lang/String.equals:(Ljava/lang/Object;)Z
     290: ifeq          311
     293: aload_0
     294: invokevirtual #96                 // Method getNote:()Ljava/util/List;
     297: aload_0
     298: aload_2
     299: invokevirtual #169                // Method castToAnnotation:(Lorg/hl7/fhir/dstu3/model/Base;)Lorg/hl7/fhir/dstu3/model/Annotation;
     302: invokeinterface #13,  2           // InterfaceMethod java/util/List.add:(Ljava/lang/Object;)Z
     307: pop
     308: goto          372
     311: aload_1
     312: ldc           #150                // String outcomeCode
     314: invokevirtual #171                // Method java/lang/String.equals:(Ljava/lang/Object;)Z
     317: ifeq          338
     320: aload_0
     321: invokevirtual #99                 // Method getOutcomeCode:()Ljava/util/List;
     324: aload_0
     325: aload_2
     326: invokevirtual #164                // Method castToCodeableConcept:(Lorg/hl7/fhir/dstu3/model/Base;)Lorg/hl7/fhir/dstu3/model/CodeableConcept;
     329: invokeinterface #13,  2           // InterfaceMethod java/util/List.add:(Ljava/lang/Object;)Z
     334: pop
     335: goto          372
     338: aload_1
     339: ldc           #152                // String outcomeReference
     341: invokevirtual #171                // Method java/lang/String.equals:(Ljava/lang/Object;)Z
     344: ifeq          365
     347: aload_0
     348: invokevirtual #102                // Method getOutcomeReference:()Ljava/util/List;
     351: aload_0
     352: aload_2
     353: invokevirtual #165                // Method castToReference:(Lorg/hl7/fhir/dstu3/model/Base;)Lorg/hl7/fhir/dstu3/model/Reference;
     356: invokeinterface #13,  2           // InterfaceMethod java/util/List.add:(Ljava/lang/Object;)Z
     361: pop
     362: goto          372
     365: aload_0
     366: aload_1
     367: aload_2
     368: invokespecial #172                // Method org/hl7/fhir/dstu3/model/DomainResource.setProperty:(Ljava/lang/String;Lorg/hl7/fhir/dstu3/model/Base;)Lorg/hl7/fhir/dstu3/model/Base;
     371: areturn
     372: aload_2
     373: areturn

  public org.hl7.fhir.dstu3.model.Base makeProperty(int, java.lang.String) throws org.hl7.fhir.exceptions.FHIRException;
    Code:
       0: iload_1
       1: lookupswitch  { // 16
           -1867885268: 165
           -1724546052: 160
           -1618432855: 140
           -1165461084: 155
            -892481550: 145
            -880905839: 180
            -782273511: 215
               3387378: 205
              50511102: 150
             109757538: 175
             175423686: 195
             247524032: 185
             874544034: 200
            1062482015: 210
            1316793566: 170
            2051346646: 190
               default: 220
          }
     140: aload_0
     141: invokevirtual #16                 // Method addIdentifier:()Lorg/hl7/fhir/dstu3/model/Identifier;
     144: areturn
     145: aload_0
     146: invokevirtual #173                // Method getStatusElement:()Lorg/hl7/fhir/dstu3/model/Enumeration;
     149: areturn
     150: aload_0
     151: invokevirtual #36                 // Method addCategory:()Lorg/hl7/fhir/dstu3/model/CodeableConcept;
     154: areturn
     155: aload_0
     156: invokevirtual #174                // Method getPriority:()Lorg/hl7/fhir/dstu3/model/CodeableConcept;
     159: areturn
     160: aload_0
     161: invokevirtual #175                // Method getDescription:()Lorg/hl7/fhir/dstu3/model/CodeableConcept;
     164: areturn
     165: aload_0
     166: invokevirtual #176                // Method getSubject:()Lorg/hl7/fhir/dstu3/model/Reference;
     169: areturn
     170: aload_0
     171: invokevirtual #177                // Method getStart:()Lorg/hl7/fhir/dstu3/model/Type;
     174: areturn
     175: aload_0
     176: invokevirtual #177                // Method getStart:()Lorg/hl7/fhir/dstu3/model/Type;
     179: areturn
     180: aload_0
     181: invokevirtual #178                // Method getTarget:()Lorg/hl7/fhir/dstu3/model/Goal$GoalTargetComponent;
     184: areturn
     185: aload_0
     186: invokevirtual #179                // Method getStatusDateElement:()Lorg/hl7/fhir/dstu3/model/DateType;
     189: areturn
     190: aload_0
     191: invokevirtual #180                // Method getStatusReasonElement:()Lorg/hl7/fhir/dstu3/model/StringType;
     194: areturn
     195: aload_0
     196: invokevirtual #181                // Method getExpressedBy:()Lorg/hl7/fhir/dstu3/model/Reference;
     199: areturn
     200: aload_0
     201: invokevirtual #90                 // Method addAddresses:()Lorg/hl7/fhir/dstu3/model/Reference;
     204: areturn
     205: aload_0
     206: invokevirtual #97                 // Method addNote:()Lorg/hl7/fhir/dstu3/model/Annotation;
     209: areturn
     210: aload_0
     211: invokevirtual #100                // Method addOutcomeCode:()Lorg/hl7/fhir/dstu3/model/CodeableConcept;
     214: areturn
     215: aload_0
     216: invokevirtual #103                // Method addOutcomeReference:()Lorg/hl7/fhir/dstu3/model/Reference;
     219: areturn
     220: aload_0
     221: iload_1
     222: aload_2
     223: invokespecial #182                // Method org/hl7/fhir/dstu3/model/DomainResource.makeProperty:(ILjava/lang/String;)Lorg/hl7/fhir/dstu3/model/Base;
     226: areturn

  public java.lang.String[] getTypesForProperty(int, java.lang.String) throws org.hl7.fhir.exceptions.FHIRException;
    Code:
       0: iload_1
       1: lookupswitch  { // 15
           -1867885268: 182
           -1724546052: 172
           -1618432855: 132
           -1165461084: 162
            -892481550: 142
            -880905839: 207
            -782273511: 272
               3387378: 252
              50511102: 152
             109757538: 192
             175423686: 232
             247524032: 212
             874544034: 242
            1062482015: 262
            2051346646: 222
               default: 282
          }
     132: iconst_1
     133: anewarray     #82                 // class java/lang/String
     136: dup
     137: iconst_0
     138: ldc           #110                // String Identifier
     140: aastore
     141: areturn
     142: iconst_1
     143: anewarray     #82                 // class java/lang/String
     146: dup
     147: iconst_0
     148: ldc           #116                // String code
     150: aastore
     151: areturn
     152: iconst_1
     153: anewarray     #82                 // class java/lang/String
     156: dup
     157: iconst_0
     158: ldc           #120                // String CodeableConcept
     160: aastore
     161: areturn
     162: iconst_1
     163: anewarray     #82                 // class java/lang/String
     166: dup
     167: iconst_0
     168: ldc           #120                // String CodeableConcept
     170: aastore
     171: areturn
     172: iconst_1
     173: anewarray     #82                 // class java/lang/String
     176: dup
     177: iconst_0
     178: ldc           #120                // String CodeableConcept
     180: aastore
     181: areturn
     182: iconst_1
     183: anewarray     #82                 // class java/lang/String
     186: dup
     187: iconst_0
     188: ldc           #183                // String Reference
     190: aastore
     191: areturn
     192: iconst_2
     193: anewarray     #82                 // class java/lang/String
     196: dup
     197: iconst_0
     198: ldc           #136                // String date
     200: aastore
     201: dup
     202: iconst_1
     203: ldc           #120                // String CodeableConcept
     205: aastore
     206: areturn
     207: iconst_0
     208: anewarray     #82                 // class java/lang/String
     211: areturn
     212: iconst_1
     213: anewarray     #82                 // class java/lang/String
     216: dup
     217: iconst_0
     218: ldc           #136                // String date
     220: aastore
     221: areturn
     222: iconst_1
     223: anewarray     #82                 // class java/lang/String
     226: dup
     227: iconst_0
     228: ldc           #139                // String string
     230: aastore
     231: areturn
     232: iconst_1
     233: anewarray     #82                 // class java/lang/String
     236: dup
     237: iconst_0
     238: ldc           #183                // String Reference
     240: aastore
     241: areturn
     242: iconst_1
     243: anewarray     #82                 // class java/lang/String
     246: dup
     247: iconst_0
     248: ldc           #183                // String Reference
     250: aastore
     251: areturn
     252: iconst_1
     253: anewarray     #82                 // class java/lang/String
     256: dup
     257: iconst_0
     258: ldc           #148                // String Annotation
     260: aastore
     261: areturn
     262: iconst_1
     263: anewarray     #82                 // class java/lang/String
     266: dup
     267: iconst_0
     268: ldc           #120                // String CodeableConcept
     270: aastore
     271: areturn
     272: iconst_1
     273: anewarray     #82                 // class java/lang/String
     276: dup
     277: iconst_0
     278: ldc           #183                // String Reference
     280: aastore
     281: areturn
     282: aload_0
     283: iload_1
     284: aload_2
     285: invokespecial #184                // Method org/hl7/fhir/dstu3/model/DomainResource.getTypesForProperty:(ILjava/lang/String;)[Ljava/lang/String;
     288: areturn

  public org.hl7.fhir.dstu3.model.Base addChild(java.lang.String) throws org.hl7.fhir.exceptions.FHIRException;
    Code:
       0: aload_1
       1: ldc           #109                // String identifier
       3: invokevirtual #171                // Method java/lang/String.equals:(Ljava/lang/Object;)Z
       6: ifeq          14
       9: aload_0
      10: invokevirtual #16                 // Method addIdentifier:()Lorg/hl7/fhir/dstu3/model/Identifier;
      13: areturn
      14: aload_1
      15: ldc           #115                // String status
      17: invokevirtual #171                // Method java/lang/String.equals:(Ljava/lang/Object;)Z
      20: ifeq          33
      23: new           #48                 // class org/hl7/fhir/exceptions/FHIRException
      26: dup
      27: ldc           #185                // String Cannot call addChild on a primitive type Goal.status
      29: invokespecial #57                 // Method org/hl7/fhir/exceptions/FHIRException."<init>":(Ljava/lang/String;)V
      32: athrow
      33: aload_1
      34: ldc           #119                // String category
      36: invokevirtual #171                // Method java/lang/String.equals:(Ljava/lang/Object;)Z
      39: ifeq          47
      42: aload_0
      43: invokevirtual #36                 // Method addCategory:()Lorg/hl7/fhir/dstu3/model/CodeableConcept;
      46: areturn
      47: aload_1
      48: ldc           #122                // String priority
      50: invokevirtual #171                // Method java/lang/String.equals:(Ljava/lang/Object;)Z
      53: ifeq          72
      56: aload_0
      57: new           #32                 // class org/hl7/fhir/dstu3/model/CodeableConcept
      60: dup
      61: invokespecial #34                 // Method org/hl7/fhir/dstu3/model/CodeableConcept."<init>":()V
      64: putfield      #37                 // Field priority:Lorg/hl7/fhir/dstu3/model/CodeableConcept;
      67: aload_0
      68: getfield      #37                 // Field priority:Lorg/hl7/fhir/dstu3/model/CodeableConcept;
      71: areturn
      72: aload_1
      73: ldc           #124                // String description
      75: invokevirtual #171                // Method java/lang/String.equals:(Ljava/lang/Object;)Z
      78: ifeq          97
      81: aload_0
      82: new           #32                 // class org/hl7/fhir/dstu3/model/CodeableConcept
      85: dup
      86: invokespecial #34                 // Method org/hl7/fhir/dstu3/model/CodeableConcept."<init>":()V
      89: putfield      #3                  // Field description:Lorg/hl7/fhir/dstu3/model/CodeableConcept;
      92: aload_0
      93: getfield      #3                  // Field description:Lorg/hl7/fhir/dstu3/model/CodeableConcept;
      96: areturn
      97: aload_1
      98: ldc           #126                // String subject
     100: invokevirtual #171                // Method java/lang/String.equals:(Ljava/lang/Object;)Z
     103: ifeq          122
     106: aload_0
     107: new           #42                 // class org/hl7/fhir/dstu3/model/Reference
     110: dup
     111: invokespecial #43                 // Method org/hl7/fhir/dstu3/model/Reference."<init>":()V
     114: putfield      #40                 // Field subject:Lorg/hl7/fhir/dstu3/model/Reference;
     117: aload_0
     118: getfield      #40                 // Field subject:Lorg/hl7/fhir/dstu3/model/Reference;
     121: areturn
     122: aload_1
     123: ldc           #186                // String startDate
     125: invokevirtual #171                // Method java/lang/String.equals:(Ljava/lang/Object;)Z
     128: ifeq          147
     131: aload_0
     132: new           #47                 // class org/hl7/fhir/dstu3/model/DateType
     135: dup
     136: invokespecial #71                 // Method org/hl7/fhir/dstu3/model/DateType."<init>":()V
     139: putfield      #46                 // Field start:Lorg/hl7/fhir/dstu3/model/Type;
     142: aload_0
     143: getfield      #46                 // Field start:Lorg/hl7/fhir/dstu3/model/Type;
     146: areturn
     147: aload_1
     148: ldc           #187                // String startCodeableConcept
     150: invokevirtual #171                // Method java/lang/String.equals:(Ljava/lang/Object;)Z
     153: ifeq          172
     156: aload_0
     157: new           #32                 // class org/hl7/fhir/dstu3/model/CodeableConcept
     160: dup
     161: invokespecial #34                 // Method org/hl7/fhir/dstu3/model/CodeableConcept."<init>":()V
     164: putfield      #46                 // Field start:Lorg/hl7/fhir/dstu3/model/Type;
     167: aload_0
     168: getfield      #46                 // Field start:Lorg/hl7/fhir/dstu3/model/Type;
     171: areturn
     172: aload_1
     173: ldc           #132                // String target
     175: invokevirtual #171                // Method java/lang/String.equals:(Ljava/lang/Object;)Z
     178: ifeq          197
     181: aload_0
     182: new           #66                 // class org/hl7/fhir/dstu3/model/Goal$GoalTargetComponent
     185: dup
     186: invokespecial #67                 // Method org/hl7/fhir/dstu3/model/Goal$GoalTargetComponent."<init>":()V
     189: putfield      #64                 // Field target:Lorg/hl7/fhir/dstu3/model/Goal$GoalTargetComponent;
     192: aload_0
     193: getfield      #64                 // Field target:Lorg/hl7/fhir/dstu3/model/Goal$GoalTargetComponent;
     196: areturn
     197: aload_1
     198: ldc           #135                // String statusDate
     200: invokevirtual #171                // Method java/lang/String.equals:(Ljava/lang/Object;)Z
     203: ifeq          216
     206: new           #48                 // class org/hl7/fhir/exceptions/FHIRException
     209: dup
     210: ldc           #188                // String Cannot call addChild on a primitive type Goal.statusDate
     212: invokespecial #57                 // Method org/hl7/fhir/exceptions/FHIRException."<init>":(Ljava/lang/String;)V
     215: athrow
     216: aload_1
     217: ldc           #138                // String statusReason
     219: invokevirtual #171                // Method java/lang/String.equals:(Ljava/lang/Object;)Z
     222: ifeq          235
     225: new           #48                 // class org/hl7/fhir/exceptions/FHIRException
     228: dup
     229: ldc           #189                // String Cannot call addChild on a primitive type Goal.statusReason
     231: invokespecial #57                 // Method org/hl7/fhir/exceptions/FHIRException."<init>":(Ljava/lang/String;)V
     234: athrow
     235: aload_1
     236: ldc           #141                // String expressedBy
     238: invokevirtual #171                // Method java/lang/String.equals:(Ljava/lang/Object;)Z
     241: ifeq          260
     244: aload_0
     245: new           #42                 // class org/hl7/fhir/dstu3/model/Reference
     248: dup
     249: invokespecial #43                 // Method org/hl7/fhir/dstu3/model/Reference."<init>":()V
     252: putfield      #85                 // Field expressedBy:Lorg/hl7/fhir/dstu3/model/Reference;
     255: aload_0
     256: getfield      #85                 // Field expressedBy:Lorg/hl7/fhir/dstu3/model/Reference;
     259: areturn
     260: aload_1
     261: ldc           #144                // String addresses
     263: invokevirtual #171                // Method java/lang/String.equals:(Ljava/lang/Object;)Z
     266: ifeq          274
     269: aload_0
     270: invokevirtual #90                 // Method addAddresses:()Lorg/hl7/fhir/dstu3/model/Reference;
     273: areturn
     274: aload_1
     275: ldc           #147                // String note
     277: invokevirtual #171                // Method java/lang/String.equals:(Ljava/lang/Object;)Z
     280: ifeq          288
     283: aload_0
     284: invokevirtual #97                 // Method addNote:()Lorg/hl7/fhir/dstu3/model/Annotation;
     287: areturn
     288: aload_1
     289: ldc           #150                // String outcomeCode
     291: invokevirtual #171                // Method java/lang/String.equals:(Ljava/lang/Object;)Z
     294: ifeq          302
     297: aload_0
     298: invokevirtual #100                // Method addOutcomeCode:()Lorg/hl7/fhir/dstu3/model/CodeableConcept;
     301: areturn
     302: aload_1
     303: ldc           #152                // String outcomeReference
     305: invokevirtual #171                // Method java/lang/String.equals:(Ljava/lang/Object;)Z
     308: ifeq          316
     311: aload_0
     312: invokevirtual #103                // Method addOutcomeReference:()Lorg/hl7/fhir/dstu3/model/Reference;
     315: areturn
     316: aload_0
     317: aload_1
     318: invokespecial #190                // Method org/hl7/fhir/dstu3/model/DomainResource.addChild:(Ljava/lang/String;)Lorg/hl7/fhir/dstu3/model/Base;
     321: areturn

  public java.lang.String fhirType();
    Code:
       0: ldc           #191                // String Goal
       2: areturn

  public org.hl7.fhir.dstu3.model.Goal copy();
    Code:
       0: new           #192                // class org/hl7/fhir/dstu3/model/Goal
       3: dup
       4: invokespecial #193                // Method "<init>":()V
       7: astore_1
       8: aload_0
       9: aload_1
      10: invokevirtual #194                // Method copyValues:(Lorg/hl7/fhir/dstu3/model/DomainResource;)V
      13: aload_0
      14: getfield      #4                  // Field identifier:Ljava/util/List;
      17: ifnull        77
      20: aload_1
      21: new           #5                  // class java/util/ArrayList
      24: dup
      25: invokespecial #6                  // Method java/util/ArrayList."<init>":()V
      28: putfield      #4                  // Field identifier:Ljava/util/List;
      31: aload_0
      32: getfield      #4                  // Field identifier:Ljava/util/List;
      35: invokeinterface #7,  1            // InterfaceMethod java/util/List.iterator:()Ljava/util/Iterator;
      40: astore_2
      41: aload_2
      42: invokeinterface #8,  1            // InterfaceMethod java/util/Iterator.hasNext:()Z
      47: ifeq          77
      50: aload_2
      51: invokeinterface #9,  1            // InterfaceMethod java/util/Iterator.next:()Ljava/lang/Object;
      56: checkcast     #10                 // class org/hl7/fhir/dstu3/model/Identifier
      59: astore_3
      60: aload_1
      61: getfield      #4                  // Field identifier:Ljava/util/List;
      64: aload_3
      65: invokevirtual #195                // Method org/hl7/fhir/dstu3/model/Identifier.copy:()Lorg/hl7/fhir/dstu3/model/Identifier;
      68: invokeinterface #13,  2           // InterfaceMethod java/util/List.add:(Ljava/lang/Object;)Z
      73: pop
      74: goto          41
      77: aload_1
      78: aload_0
      79: getfield      #2                  // Field status:Lorg/hl7/fhir/dstu3/model/Enumeration;
      82: ifnonnull     89
      85: aconst_null
      86: goto          96
      89: aload_0
      90: getfield      #2                  // Field status:Lorg/hl7/fhir/dstu3/model/Enumeration;
      93: invokevirtual #196                // Method org/hl7/fhir/dstu3/model/Enumeration.copy:()Lorg/hl7/fhir/dstu3/model/Enumeration;
      96: putfield      #2                  // Field status:Lorg/hl7/fhir/dstu3/model/Enumeration;
      99: aload_0
     100: getfield      #31                 // Field category:Ljava/util/List;
     103: ifnull        163
     106: aload_1
     107: new           #5                  // class java/util/ArrayList
     110: dup
     111: invokespecial #6                  // Method java/util/ArrayList."<init>":()V
     114: putfield      #31                 // Field category:Ljava/util/List;
     117: aload_0
     118: getfield      #31                 // Field category:Ljava/util/List;
     121: invokeinterface #7,  1            // InterfaceMethod java/util/List.iterator:()Ljava/util/Iterator;
     126: astore_2
     127: aload_2
     128: invokeinterface #8,  1            // InterfaceMethod java/util/Iterator.hasNext:()Z
     133: ifeq          163
     136: aload_2
     137: invokeinterface #9,  1            // InterfaceMethod java/util/Iterator.next:()Ljava/lang/Object;
     142: checkcast     #32                 // class org/hl7/fhir/dstu3/model/CodeableConcept
     145: astore_3
     146: aload_1
     147: getfield      #31                 // Field category:Ljava/util/List;
     150: aload_3
     151: invokevirtual #197                // Method org/hl7/fhir/dstu3/model/CodeableConcept.copy:()Lorg/hl7/fhir/dstu3/model/CodeableConcept;
     154: invokeinterface #13,  2           // InterfaceMethod java/util/List.add:(Ljava/lang/Object;)Z
     159: pop
     160: goto          127
     163: aload_1
     164: aload_0
     165: getfield      #37                 // Field priority:Lorg/hl7/fhir/dstu3/model/CodeableConcept;
     168: ifnonnull     175
     171: aconst_null
     172: goto          182
     175: aload_0
     176: getfield      #37                 // Field priority:Lorg/hl7/fhir/dstu3/model/CodeableConcept;
     179: invokevirtual #197                // Method org/hl7/fhir/dstu3/model/CodeableConcept.copy:()Lorg/hl7/fhir/dstu3/model/CodeableConcept;
     182: putfield      #37                 // Field priority:Lorg/hl7/fhir/dstu3/model/CodeableConcept;
     185: aload_1
     186: aload_0
     187: getfield      #3                  // Field description:Lorg/hl7/fhir/dstu3/model/CodeableConcept;
     190: ifnonnull     197
     193: aconst_null
     194: goto          204
     197: aload_0
     198: getfield      #3                  // Field description:Lorg/hl7/fhir/dstu3/model/CodeableConcept;
     201: invokevirtual #197                // Method org/hl7/fhir/dstu3/model/CodeableConcept.copy:()Lorg/hl7/fhir/dstu3/model/CodeableConcept;
     204: putfield      #3                  // Field description:Lorg/hl7/fhir/dstu3/model/CodeableConcept;
     207: aload_1
     208: aload_0
     209: getfield      #40                 // Field subject:Lorg/hl7/fhir/dstu3/model/Reference;
     212: ifnonnull     219
     215: aconst_null
     216: goto          226
     219: aload_0
     220: getfield      #40                 // Field subject:Lorg/hl7/fhir/dstu3/model/Reference;
     223: invokevirtual #198                // Method org/hl7/fhir/dstu3/model/Reference.copy:()Lorg/hl7/fhir/dstu3/model/Reference;
     226: putfield      #40                 // Field subject:Lorg/hl7/fhir/dstu3/model/Reference;
     229: aload_1
     230: aload_0
     231: getfield      #46                 // Field start:Lorg/hl7/fhir/dstu3/model/Type;
     234: ifnonnull     241
     237: aconst_null
     238: goto          248
     241: aload_0
     242: getfield      #46                 // Field start:Lorg/hl7/fhir/dstu3/model/Type;
     245: invokevirtual #199                // Method org/hl7/fhir/dstu3/model/Type.copy:()Lorg/hl7/fhir/dstu3/model/Type;
     248: putfield      #46                 // Field start:Lorg/hl7/fhir/dstu3/model/Type;
     251: aload_1
     252: aload_0
     253: getfield      #64                 // Field target:Lorg/hl7/fhir/dstu3/model/Goal$GoalTargetComponent;
     256: ifnonnull     263
     259: aconst_null
     260: goto          270
     263: aload_0
     264: getfield      #64                 // Field target:Lorg/hl7/fhir/dstu3/model/Goal$GoalTargetComponent;
     267: invokevirtual #200                // Method org/hl7/fhir/dstu3/model/Goal$GoalTargetComponent.copy:()Lorg/hl7/fhir/dstu3/model/Goal$GoalTargetComponent;
     270: putfield      #64                 // Field target:Lorg/hl7/fhir/dstu3/model/Goal$GoalTargetComponent;
     273: aload_1
     274: aload_0
     275: getfield      #69                 // Field statusDate:Lorg/hl7/fhir/dstu3/model/DateType;
     278: ifnonnull     285
     281: aconst_null
     282: goto          292
     285: aload_0
     286: getfield      #69                 // Field statusDate:Lorg/hl7/fhir/dstu3/model/DateType;
     289: invokevirtual #201                // Method org/hl7/fhir/dstu3/model/DateType.copy:()Lorg/hl7/fhir/dstu3/model/DateType;
     292: putfield      #69                 // Field statusDate:Lorg/hl7/fhir/dstu3/model/DateType;
     295: aload_1
     296: aload_0
     297: getfield      #76                 // Field statusReason:Lorg/hl7/fhir/dstu3/model/StringType;
     300: ifnonnull     307
     303: aconst_null
     304: goto          314
     307: aload_0
     308: getfield      #76                 // Field statusReason:Lorg/hl7/fhir/dstu3/model/StringType;
     311: invokevirtual #202                // Method org/hl7/fhir/dstu3/model/StringType.copy:()Lorg/hl7/fhir/dstu3/model/StringType;
     314: putfield      #76                 // Field statusReason:Lorg/hl7/fhir/dstu3/model/StringType;
     317: aload_1
     318: aload_0
     319: getfield      #85                 // Field expressedBy:Lorg/hl7/fhir/dstu3/model/Reference;
     322: ifnonnull     329
     325: aconst_null
     326: goto          336
     329: aload_0
     330: getfield      #85                 // Field expressedBy:Lorg/hl7/fhir/dstu3/model/Reference;
     333: invokevirtual #198                // Method org/hl7/fhir/dstu3/model/Reference.copy:()Lorg/hl7/fhir/dstu3/model/Reference;
     336: putfield      #85                 // Field expressedBy:Lorg/hl7/fhir/dstu3/model/Reference;
     339: aload_0
     340: getfield      #88                 // Field addresses:Ljava/util/List;
     343: ifnull        403
     346: aload_1
     347: new           #5                  // class java/util/ArrayList
     350: dup
     351: invokespecial #6                  // Method java/util/ArrayList."<init>":()V
     354: putfield      #88                 // Field addresses:Ljava/util/List;
     357: aload_0
     358: getfield      #88                 // Field addresses:Ljava/util/List;
     361: invokeinterface #7,  1            // InterfaceMethod java/util/List.iterator:()Ljava/util/Iterator;
     366: astore_2
     367: aload_2
     368: invokeinterface #8,  1            // InterfaceMethod java/util/Iterator.hasNext:()Z
     373: ifeq          403
     376: aload_2
     377: invokeinterface #9,  1            // InterfaceMethod java/util/Iterator.next:()Ljava/lang/Object;
     382: checkcast     #42                 // class org/hl7/fhir/dstu3/model/Reference
     385: astore_3
     386: aload_1
     387: getfield      #88                 // Field addresses:Ljava/util/List;
     390: aload_3
     391: invokevirtual #198                // Method org/hl7/fhir/dstu3/model/Reference.copy:()Lorg/hl7/fhir/dstu3/model/Reference;
     394: invokeinterface #13,  2           // InterfaceMethod java/util/List.add:(Ljava/lang/Object;)Z
     399: pop
     400: goto          367
     403: aload_0
     404: getfield      #92                 // Field note:Ljava/util/List;
     407: ifnull        467
     410: aload_1
     411: new           #5                  // class java/util/ArrayList
     414: dup
     415: invokespecial #6                  // Method java/util/ArrayList."<init>":()V
     418: putfield      #92                 // Field note:Ljava/util/List;
     421: aload_0
     422: getfield      #92                 // Field note:Ljava/util/List;
     425: invokeinterface #7,  1            // InterfaceMethod java/util/List.iterator:()Ljava/util/Iterator;
     430: astore_2
     431: aload_2
     432: invokeinterface #8,  1            // InterfaceMethod java/util/Iterator.hasNext:()Z
     437: ifeq          467
     440: aload_2
     441: invokeinterface #9,  1            // InterfaceMethod java/util/Iterator.next:()Ljava/lang/Object;
     446: checkcast     #93                 // class org/hl7/fhir/dstu3/model/Annotation
     449: astore_3
     450: aload_1
     451: getfield      #92                 // Field note:Ljava/util/List;
     454: aload_3
     455: invokevirtual #203                // Method org/hl7/fhir/dstu3/model/Annotation.copy:()Lorg/hl7/fhir/dstu3/model/Annotation;
     458: invokeinterface #13,  2           // InterfaceMethod java/util/List.add:(Ljava/lang/Object;)Z
     463: pop
     464: goto          431
     467: aload_0
     468: getfield      #98                 // Field outcomeCode:Ljava/util/List;
     471: ifnull        531
     474: aload_1
     475: new           #5                  // class java/util/ArrayList
     478: dup
     479: invokespecial #6                  // Method java/util/ArrayList."<init>":()V
     482: putfield      #98                 // Field outcomeCode:Ljava/util/List;
     485: aload_0
     486: getfield      #98                 // Field outcomeCode:Ljava/util/List;
     489: invokeinterface #7,  1            // InterfaceMethod java/util/List.iterator:()Ljava/util/Iterator;
     494: astore_2
     495: aload_2
     496: invokeinterface #8,  1            // InterfaceMethod java/util/Iterator.hasNext:()Z
     501: ifeq          531
     504: aload_2
     505: invokeinterface #9,  1            // InterfaceMethod java/util/Iterator.next:()Ljava/lang/Object;
     510: checkcast     #32                 // class org/hl7/fhir/dstu3/model/CodeableConcept
     513: astore_3
     514: aload_1
     515: getfield      #98                 // Field outcomeCode:Ljava/util/List;
     518: aload_3
     519: invokevirtual #197                // Method org/hl7/fhir/dstu3/model/CodeableConcept.copy:()Lorg/hl7/fhir/dstu3/model/CodeableConcept;
     522: invokeinterface #13,  2           // InterfaceMethod java/util/List.add:(Ljava/lang/Object;)Z
     527: pop
     528: goto          495
     531: aload_0
     532: getfield      #101                // Field outcomeReference:Ljava/util/List;
     535: ifnull        595
     538: aload_1
     539: new           #5                  // class java/util/ArrayList
     542: dup
     543: invokespecial #6                  // Method java/util/ArrayList."<init>":()V
     546: putfield      #101                // Field outcomeReference:Ljava/util/List;
     549: aload_0
     550: getfield      #101                // Field outcomeReference:Ljava/util/List;
     553: invokeinterface #7,  1            // InterfaceMethod java/util/List.iterator:()Ljava/util/Iterator;
     558: astore_2
     559: aload_2
     560: invokeinterface #8,  1            // InterfaceMethod java/util/Iterator.hasNext:()Z
     565: ifeq          595
     568: aload_2
     569: invokeinterface #9,  1            // InterfaceMethod java/util/Iterator.next:()Ljava/lang/Object;
     574: checkcast     #42                 // class org/hl7/fhir/dstu3/model/Reference
     577: astore_3
     578: aload_1
     579: getfield      #101                // Field outcomeReference:Ljava/util/List;
     582: aload_3
     583: invokevirtual #198                // Method org/hl7/fhir/dstu3/model/Reference.copy:()Lorg/hl7/fhir/dstu3/model/Reference;
     586: invokeinterface #13,  2           // InterfaceMethod java/util/List.add:(Ljava/lang/Object;)Z
     591: pop
     592: goto          559
     595: aload_1
     596: areturn

  protected org.hl7.fhir.dstu3.model.Goal typedCopy();
    Code:
       0: aload_0
       1: invokevirtual #204                // Method copy:()Lorg/hl7/fhir/dstu3/model/Goal;
       4: areturn

  public boolean equalsDeep(org.hl7.fhir.dstu3.model.Base);
    Code:
       0: aload_0
       1: aload_1
       2: invokespecial #205                // Method org/hl7/fhir/dstu3/model/DomainResource.equalsDeep:(Lorg/hl7/fhir/dstu3/model/Base;)Z
       5: ifne          10
       8: iconst_0
       9: ireturn
      10: aload_1
      11: instanceof    #192                // class org/hl7/fhir/dstu3/model/Goal
      14: ifne          19
      17: iconst_0
      18: ireturn
      19: aload_1
      20: checkcast     #192                // class org/hl7/fhir/dstu3/model/Goal
      23: astore_2
      24: aload_0
      25: getfield      #4                  // Field identifier:Ljava/util/List;
      28: aload_2
      29: getfield      #4                  // Field identifier:Ljava/util/List;
      32: iconst_1
      33: invokestatic  #206                // Method compareDeep:(Ljava/util/List;Ljava/util/List;Z)Z
      36: ifeq          253
      39: aload_0
      40: getfield      #2                  // Field status:Lorg/hl7/fhir/dstu3/model/Enumeration;
      43: aload_2
      44: getfield      #2                  // Field status:Lorg/hl7/fhir/dstu3/model/Enumeration;
      47: iconst_1
      48: invokestatic  #207                // Method compareDeep:(Lorg/hl7/fhir/dstu3/model/Base;Lorg/hl7/fhir/dstu3/model/Base;Z)Z
      51: ifeq          253
      54: aload_0
      55: getfield      #31                 // Field category:Ljava/util/List;
      58: aload_2
      59: getfield      #31                 // Field category:Ljava/util/List;
      62: iconst_1
      63: invokestatic  #206                // Method compareDeep:(Ljava/util/List;Ljava/util/List;Z)Z
      66: ifeq          253
      69: aload_0
      70: getfield      #37                 // Field priority:Lorg/hl7/fhir/dstu3/model/CodeableConcept;
      73: aload_2
      74: getfield      #37                 // Field priority:Lorg/hl7/fhir/dstu3/model/CodeableConcept;
      77: iconst_1
      78: invokestatic  #207                // Method compareDeep:(Lorg/hl7/fhir/dstu3/model/Base;Lorg/hl7/fhir/dstu3/model/Base;Z)Z
      81: ifeq          253
      84: aload_0
      85: getfield      #3                  // Field description:Lorg/hl7/fhir/dstu3/model/CodeableConcept;
      88: aload_2
      89: getfield      #3                  // Field description:Lorg/hl7/fhir/dstu3/model/CodeableConcept;
      92: iconst_1
      93: invokestatic  #207                // Method compareDeep:(Lorg/hl7/fhir/dstu3/model/Base;Lorg/hl7/fhir/dstu3/model/Base;Z)Z
      96: ifeq          253
      99: aload_0
     100: getfield      #40                 // Field subject:Lorg/hl7/fhir/dstu3/model/Reference;
     103: aload_2
     104: getfield      #40                 // Field subject:Lorg/hl7/fhir/dstu3/model/Reference;
     107: iconst_1
     108: invokestatic  #207                // Method compareDeep:(Lorg/hl7/fhir/dstu3/model/Base;Lorg/hl7/fhir/dstu3/model/Base;Z)Z
     111: ifeq          253
     114: aload_0
     115: getfield      #46                 // Field start:Lorg/hl7/fhir/dstu3/model/Type;
     118: aload_2
     119: getfield      #46                 // Field start:Lorg/hl7/fhir/dstu3/model/Type;
     122: iconst_1
     123: invokestatic  #207                // Method compareDeep:(Lorg/hl7/fhir/dstu3/model/Base;Lorg/hl7/fhir/dstu3/model/Base;Z)Z
     126: ifeq          253
     129: aload_0
     130: getfield      #64                 // Field target:Lorg/hl7/fhir/dstu3/model/Goal$GoalTargetComponent;
     133: aload_2
     134: getfield      #64                 // Field target:Lorg/hl7/fhir/dstu3/model/Goal$GoalTargetComponent;
     137: iconst_1
     138: invokestatic  #207                // Method compareDeep:(Lorg/hl7/fhir/dstu3/model/Base;Lorg/hl7/fhir/dstu3/model/Base;Z)Z
     141: ifeq          253
     144: aload_0
     145: getfield      #69                 // Field statusDate:Lorg/hl7/fhir/dstu3/model/DateType;
     148: aload_2
     149: getfield      #69                 // Field statusDate:Lorg/hl7/fhir/dstu3/model/DateType;
     152: iconst_1
     153: invokestatic  #207                // Method compareDeep:(Lorg/hl7/fhir/dstu3/model/Base;Lorg/hl7/fhir/dstu3/model/Base;Z)Z
     156: ifeq          253
     159: aload_0
     160: getfield      #76                 // Field statusReason:Lorg/hl7/fhir/dstu3/model/StringType;
     163: aload_2
     164: getfield      #76                 // Field statusReason:Lorg/hl7/fhir/dstu3/model/StringType;
     167: iconst_1
     168: invokestatic  #207                // Method compareDeep:(Lorg/hl7/fhir/dstu3/model/Base;Lorg/hl7/fhir/dstu3/model/Base;Z)Z
     171: ifeq          253
     174: aload_0
     175: getfield      #85                 // Field expressedBy:Lorg/hl7/fhir/dstu3/model/Reference;
     178: aload_2
     179: getfield      #85                 // Field expressedBy:Lorg/hl7/fhir/dstu3/model/Reference;
     182: iconst_1
     183: invokestatic  #207                // Method compareDeep:(Lorg/hl7/fhir/dstu3/model/Base;Lorg/hl7/fhir/dstu3/model/Base;Z)Z
     186: ifeq          253
     189: aload_0
     190: getfield      #88                 // Field addresses:Ljava/util/List;
     193: aload_2
     194: getfield      #88                 // Field addresses:Ljava/util/List;
     197: iconst_1
     198: invokestatic  #206                // Method compareDeep:(Ljava/util/List;Ljava/util/List;Z)Z
     201: ifeq          253
     204: aload_0
     205: getfield      #92                 // Field note:Ljava/util/List;
     208: aload_2
     209: getfield      #92                 // Field note:Ljava/util/List;
     212: iconst_1
     213: invokestatic  #206                // Method compareDeep:(Ljava/util/List;Ljava/util/List;Z)Z
     216: ifeq          253
     219: aload_0
     220: getfield      #98                 // Field outcomeCode:Ljava/util/List;
     223: aload_2
     224: getfield      #98                 // Field outcomeCode:Ljava/util/List;
     227: iconst_1
     228: invokestatic  #206                // Method compareDeep:(Ljava/util/List;Ljava/util/List;Z)Z
     231: ifeq          253
     234: aload_0
     235: getfield      #101                // Field outcomeReference:Ljava/util/List;
     238: aload_2
     239: getfield      #101                // Field outcomeReference:Ljava/util/List;
     242: iconst_1
     243: invokestatic  #206                // Method compareDeep:(Ljava/util/List;Ljava/util/List;Z)Z
     246: ifeq          253
     249: iconst_1
     250: goto          254
     253: iconst_0
     254: ireturn

  public boolean equalsShallow(org.hl7.fhir.dstu3.model.Base);
    Code:
       0: aload_0
       1: aload_1
       2: invokespecial #208                // Method org/hl7/fhir/dstu3/model/DomainResource.equalsShallow:(Lorg/hl7/fhir/dstu3/model/Base;)Z
       5: ifne          10
       8: iconst_0
       9: ireturn
      10: aload_1
      11: instanceof    #192                // class org/hl7/fhir/dstu3/model/Goal
      14: ifne          19
      17: iconst_0
      18: ireturn
      19: aload_1
      20: checkcast     #192                // class org/hl7/fhir/dstu3/model/Goal
      23: astore_2
      24: aload_0
      25: getfield      #2                  // Field status:Lorg/hl7/fhir/dstu3/model/Enumeration;
      28: aload_2
      29: getfield      #2                  // Field status:Lorg/hl7/fhir/dstu3/model/Enumeration;
      32: iconst_1
      33: invokestatic  #209                // Method compareValues:(Lorg/hl7/fhir/dstu3/model/PrimitiveType;Lorg/hl7/fhir/dstu3/model/PrimitiveType;Z)Z
      36: ifeq          73
      39: aload_0
      40: getfield      #69                 // Field statusDate:Lorg/hl7/fhir/dstu3/model/DateType;
      43: aload_2
      44: getfield      #69                 // Field statusDate:Lorg/hl7/fhir/dstu3/model/DateType;
      47: iconst_1
      48: invokestatic  #209                // Method compareValues:(Lorg/hl7/fhir/dstu3/model/PrimitiveType;Lorg/hl7/fhir/dstu3/model/PrimitiveType;Z)Z
      51: ifeq          73
      54: aload_0
      55: getfield      #76                 // Field statusReason:Lorg/hl7/fhir/dstu3/model/StringType;
      58: aload_2
      59: getfield      #76                 // Field statusReason:Lorg/hl7/fhir/dstu3/model/StringType;
      62: iconst_1
      63: invokestatic  #209                // Method compareValues:(Lorg/hl7/fhir/dstu3/model/PrimitiveType;Lorg/hl7/fhir/dstu3/model/PrimitiveType;Z)Z
      66: ifeq          73
      69: iconst_1
      70: goto          74
      73: iconst_0
      74: ireturn

  public boolean isEmpty();
    Code:
       0: aload_0
       1: invokespecial #210                // Method org/hl7/fhir/dstu3/model/DomainResource.isEmpty:()Z
       4: ifeq          136
       7: bipush        15
       9: anewarray     #211                // class java/lang/Object
      12: dup
      13: iconst_0
      14: aload_0
      15: getfield      #4                  // Field identifier:Ljava/util/List;
      18: aastore
      19: dup
      20: iconst_1
      21: aload_0
      22: getfield      #2                  // Field status:Lorg/hl7/fhir/dstu3/model/Enumeration;
      25: aastore
      26: dup
      27: iconst_2
      28: aload_0
      29: getfield      #31                 // Field category:Ljava/util/List;
      32: aastore
      33: dup
      34: iconst_3
      35: aload_0
      36: getfield      #37                 // Field priority:Lorg/hl7/fhir/dstu3/model/CodeableConcept;
      39: aastore
      40: dup
      41: iconst_4
      42: aload_0
      43: getfield      #3                  // Field description:Lorg/hl7/fhir/dstu3/model/CodeableConcept;
      46: aastore
      47: dup
      48: iconst_5
      49: aload_0
      50: getfield      #40                 // Field subject:Lorg/hl7/fhir/dstu3/model/Reference;
      53: aastore
      54: dup
      55: bipush        6
      57: aload_0
      58: getfield      #46                 // Field start:Lorg/hl7/fhir/dstu3/model/Type;
      61: aastore
      62: dup
      63: bipush        7
      65: aload_0
      66: getfield      #64                 // Field target:Lorg/hl7/fhir/dstu3/model/Goal$GoalTargetComponent;
      69: aastore
      70: dup
      71: bipush        8
      73: aload_0
      74: getfield      #69                 // Field statusDate:Lorg/hl7/fhir/dstu3/model/DateType;
      77: aastore
      78: dup
      79: bipush        9
      81: aload_0
      82: getfield      #76                 // Field statusReason:Lorg/hl7/fhir/dstu3/model/StringType;
      85: aastore
      86: dup
      87: bipush        10
      89: aload_0
      90: getfield      #85                 // Field expressedBy:Lorg/hl7/fhir/dstu3/model/Reference;
      93: aastore
      94: dup
      95: bipush        11
      97: aload_0
      98: getfield      #88                 // Field addresses:Ljava/util/List;
     101: aastore
     102: dup
     103: bipush        12
     105: aload_0
     106: getfield      #92                 // Field note:Ljava/util/List;
     109: aastore
     110: dup
     111: bipush        13
     113: aload_0
     114: getfield      #98                 // Field outcomeCode:Ljava/util/List;
     117: aastore
     118: dup
     119: bipush        14
     121: aload_0
     122: getfield      #101                // Field outcomeReference:Ljava/util/List;
     125: aastore
     126: invokestatic  #212                // Method ca/uhn/fhir/util/ElementUtil.isEmpty:([Ljava/lang/Object;)Z
     129: ifeq          136
     132: iconst_1
     133: goto          137
     136: iconst_0
     137: ireturn

  public org.hl7.fhir.dstu3.model.ResourceType getResourceType();
    Code:
       0: getstatic     #213                // Field org/hl7/fhir/dstu3/model/ResourceType.Goal:Lorg/hl7/fhir/dstu3/model/ResourceType;
       3: areturn

  public org.hl7.fhir.dstu3.model.DomainResource copy();
    Code:
       0: aload_0
       1: invokevirtual #204                // Method copy:()Lorg/hl7/fhir/dstu3/model/Goal;
       4: areturn

  public org.hl7.fhir.dstu3.model.Resource copy();
    Code:
       0: aload_0
       1: invokevirtual #204                // Method copy:()Lorg/hl7/fhir/dstu3/model/Goal;
       4: areturn

  static {};
    Code:
       0: new           #214                // class ca/uhn/fhir/rest/gclient/TokenClientParam
       3: dup
       4: ldc           #109                // String identifier
       6: invokespecial #215                // Method ca/uhn/fhir/rest/gclient/TokenClientParam."<init>":(Ljava/lang/String;)V
       9: putstatic     #216                // Field IDENTIFIER:Lca/uhn/fhir/rest/gclient/TokenClientParam;
      12: new           #217                // class ca/uhn/fhir/rest/gclient/ReferenceClientParam
      15: dup
      16: ldc           #218                // String patient
      18: invokespecial #219                // Method ca/uhn/fhir/rest/gclient/ReferenceClientParam."<init>":(Ljava/lang/String;)V
      21: putstatic     #220                // Field PATIENT:Lca/uhn/fhir/rest/gclient/ReferenceClientParam;
      24: new           #221                // class ca/uhn/fhir/model/api/Include
      27: dup
      28: ldc           #222                // String Goal:patient
      30: invokespecial #223                // Method ca/uhn/fhir/model/api/Include."<init>":(Ljava/lang/String;)V
      33: invokevirtual #224                // Method ca/uhn/fhir/model/api/Include.toLocked:()Lca/uhn/fhir/model/api/Include;
      36: putstatic     #225                // Field INCLUDE_PATIENT:Lca/uhn/fhir/model/api/Include;
      39: new           #217                // class ca/uhn/fhir/rest/gclient/ReferenceClientParam
      42: dup
      43: ldc           #126                // String subject
      45: invokespecial #219                // Method ca/uhn/fhir/rest/gclient/ReferenceClientParam."<init>":(Ljava/lang/String;)V
      48: putstatic     #226                // Field SUBJECT:Lca/uhn/fhir/rest/gclient/ReferenceClientParam;
      51: new           #221                // class ca/uhn/fhir/model/api/Include
      54: dup
      55: ldc           #227                // String Goal:subject
      57: invokespecial #223                // Method ca/uhn/fhir/model/api/Include."<init>":(Ljava/lang/String;)V
      60: invokevirtual #224                // Method ca/uhn/fhir/model/api/Include.toLocked:()Lca/uhn/fhir/model/api/Include;
      63: putstatic     #228                // Field INCLUDE_SUBJECT:Lca/uhn/fhir/model/api/Include;
      66: new           #229                // class ca/uhn/fhir/rest/gclient/DateClientParam
      69: dup
      70: ldc           #230                // String start-date
      72: invokespecial #231                // Method ca/uhn/fhir/rest/gclient/DateClientParam."<init>":(Ljava/lang/String;)V
      75: putstatic     #232                // Field START_DATE:Lca/uhn/fhir/rest/gclient/DateClientParam;
      78: new           #214                // class ca/uhn/fhir/rest/gclient/TokenClientParam
      81: dup
      82: ldc           #119                // String category
      84: invokespecial #215                // Method ca/uhn/fhir/rest/gclient/TokenClientParam."<init>":(Ljava/lang/String;)V
      87: putstatic     #233                // Field CATEGORY:Lca/uhn/fhir/rest/gclient/TokenClientParam;
      90: new           #229                // class ca/uhn/fhir/rest/gclient/DateClientParam
      93: dup
      94: ldc           #234                // String target-date
      96: invokespecial #231                // Method ca/uhn/fhir/rest/gclient/DateClientParam."<init>":(Ljava/lang/String;)V
      99: putstatic     #235                // Field TARGET_DATE:Lca/uhn/fhir/rest/gclient/DateClientParam;
     102: new           #214                // class ca/uhn/fhir/rest/gclient/TokenClientParam
     105: dup
     106: ldc           #115                // String status
     108: invokespecial #215                // Method ca/uhn/fhir/rest/gclient/TokenClientParam."<init>":(Ljava/lang/String;)V
     111: putstatic     #236                // Field STATUS:Lca/uhn/fhir/rest/gclient/TokenClientParam;
     114: return
}
