Compiled from "GraphDefinition.java"
public class org.hl7.fhir.dstu3.model.GraphDefinition$GraphDefinitionLinkComponent extends org.hl7.fhir.dstu3.model.BackboneElement implements org.hl7.fhir.instance.model.api.IBaseBackboneElement {
  protected org.hl7.fhir.dstu3.model.StringType path;

  protected org.hl7.fhir.dstu3.model.StringType sliceName;

  protected org.hl7.fhir.dstu3.model.IntegerType min;

  protected org.hl7.fhir.dstu3.model.StringType max;

  protected org.hl7.fhir.dstu3.model.StringType description;

  protected java.util.List<org.hl7.fhir.dstu3.model.GraphDefinition$GraphDefinitionLinkTargetComponent> target;

  private static final long serialVersionUID;

  public org.hl7.fhir.dstu3.model.GraphDefinition$GraphDefinitionLinkComponent();
    Code:
       0: aload_0
       1: invokespecial #1                  // Method org/hl7/fhir/dstu3/model/BackboneElement."<init>":()V
       4: return

  public org.hl7.fhir.dstu3.model.GraphDefinition$GraphDefinitionLinkComponent(org.hl7.fhir.dstu3.model.StringType);
    Code:
       0: aload_0
       1: invokespecial #1                  // Method org/hl7/fhir/dstu3/model/BackboneElement."<init>":()V
       4: aload_0
       5: aload_1
       6: putfield      #2                  // Field path:Lorg/hl7/fhir/dstu3/model/StringType;
       9: return

  public org.hl7.fhir.dstu3.model.StringType getPathElement();
    Code:
       0: aload_0
       1: getfield      #2                  // Field path:Lorg/hl7/fhir/dstu3/model/StringType;
       4: ifnonnull     40
       7: invokestatic  #3                  // Method org/hl7/fhir/dstu3/model/Configuration.errorOnAutoCreate:()Z
      10: ifeq          23
      13: new           #4                  // class java/lang/Error
      16: dup
      17: ldc           #5                  // String Attempt to auto-create GraphDefinitionLinkComponent.path
      19: invokespecial #6                  // Method java/lang/Error."<init>":(Ljava/lang/String;)V
      22: athrow
      23: invokestatic  #7                  // Method org/hl7/fhir/dstu3/model/Configuration.doAutoCreate:()Z
      26: ifeq          40
      29: aload_0
      30: new           #8                  // class org/hl7/fhir/dstu3/model/StringType
      33: dup
      34: invokespecial #9                  // Method org/hl7/fhir/dstu3/model/StringType."<init>":()V
      37: putfield      #2                  // Field path:Lorg/hl7/fhir/dstu3/model/StringType;
      40: aload_0
      41: getfield      #2                  // Field path:Lorg/hl7/fhir/dstu3/model/StringType;
      44: areturn

  public boolean hasPathElement();
    Code:
       0: aload_0
       1: getfield      #2                  // Field path:Lorg/hl7/fhir/dstu3/model/StringType;
       4: ifnull        21
       7: aload_0
       8: getfield      #2                  // Field path:Lorg/hl7/fhir/dstu3/model/StringType;
      11: invokevirtual #10                 // Method org/hl7/fhir/dstu3/model/StringType.isEmpty:()Z
      14: ifne          21
      17: iconst_1
      18: goto          22
      21: iconst_0
      22: ireturn

  public boolean hasPath();
    Code:
       0: aload_0
       1: getfield      #2                  // Field path:Lorg/hl7/fhir/dstu3/model/StringType;
       4: ifnull        21
       7: aload_0
       8: getfield      #2                  // Field path:Lorg/hl7/fhir/dstu3/model/StringType;
      11: invokevirtual #10                 // Method org/hl7/fhir/dstu3/model/StringType.isEmpty:()Z
      14: ifne          21
      17: iconst_1
      18: goto          22
      21: iconst_0
      22: ireturn

  public org.hl7.fhir.dstu3.model.GraphDefinition$GraphDefinitionLinkComponent setPathElement(org.hl7.fhir.dstu3.model.StringType);
    Code:
       0: aload_0
       1: aload_1
       2: putfield      #2                  // Field path:Lorg/hl7/fhir/dstu3/model/StringType;
       5: aload_0
       6: areturn

  public java.lang.String getPath();
    Code:
       0: aload_0
       1: getfield      #2                  // Field path:Lorg/hl7/fhir/dstu3/model/StringType;
       4: ifnonnull     11
       7: aconst_null
       8: goto          21
      11: aload_0
      12: getfield      #2                  // Field path:Lorg/hl7/fhir/dstu3/model/StringType;
      15: invokevirtual #11                 // Method org/hl7/fhir/dstu3/model/StringType.getValue:()Ljava/lang/Object;
      18: checkcast     #12                 // class java/lang/String
      21: areturn

  public org.hl7.fhir.dstu3.model.GraphDefinition$GraphDefinitionLinkComponent setPath(java.lang.String);
    Code:
       0: aload_0
       1: getfield      #2                  // Field path:Lorg/hl7/fhir/dstu3/model/StringType;
       4: ifnonnull     18
       7: aload_0
       8: new           #8                  // class org/hl7/fhir/dstu3/model/StringType
      11: dup
      12: invokespecial #9                  // Method org/hl7/fhir/dstu3/model/StringType."<init>":()V
      15: putfield      #2                  // Field path:Lorg/hl7/fhir/dstu3/model/StringType;
      18: aload_0
      19: getfield      #2                  // Field path:Lorg/hl7/fhir/dstu3/model/StringType;
      22: aload_1
      23: invokevirtual #13                 // Method org/hl7/fhir/dstu3/model/StringType.setValue:(Ljava/lang/Object;)Lorg/hl7/fhir/dstu3/model/PrimitiveType;
      26: pop
      27: aload_0
      28: areturn

  public org.hl7.fhir.dstu3.model.StringType getSliceNameElement();
    Code:
       0: aload_0
       1: getfield      #14                 // Field sliceName:Lorg/hl7/fhir/dstu3/model/StringType;
       4: ifnonnull     40
       7: invokestatic  #3                  // Method org/hl7/fhir/dstu3/model/Configuration.errorOnAutoCreate:()Z
      10: ifeq          23
      13: new           #4                  // class java/lang/Error
      16: dup
      17: ldc           #15                 // String Attempt to auto-create GraphDefinitionLinkComponent.sliceName
      19: invokespecial #6                  // Method java/lang/Error."<init>":(Ljava/lang/String;)V
      22: athrow
      23: invokestatic  #7                  // Method org/hl7/fhir/dstu3/model/Configuration.doAutoCreate:()Z
      26: ifeq          40
      29: aload_0
      30: new           #8                  // class org/hl7/fhir/dstu3/model/StringType
      33: dup
      34: invokespecial #9                  // Method org/hl7/fhir/dstu3/model/StringType."<init>":()V
      37: putfield      #14                 // Field sliceName:Lorg/hl7/fhir/dstu3/model/StringType;
      40: aload_0
      41: getfield      #14                 // Field sliceName:Lorg/hl7/fhir/dstu3/model/StringType;
      44: areturn

  public boolean hasSliceNameElement();
    Code:
       0: aload_0
       1: getfield      #14                 // Field sliceName:Lorg/hl7/fhir/dstu3/model/StringType;
       4: ifnull        21
       7: aload_0
       8: getfield      #14                 // Field sliceName:Lorg/hl7/fhir/dstu3/model/StringType;
      11: invokevirtual #10                 // Method org/hl7/fhir/dstu3/model/StringType.isEmpty:()Z
      14: ifne          21
      17: iconst_1
      18: goto          22
      21: iconst_0
      22: ireturn

  public boolean hasSliceName();
    Code:
       0: aload_0
       1: getfield      #14                 // Field sliceName:Lorg/hl7/fhir/dstu3/model/StringType;
       4: ifnull        21
       7: aload_0
       8: getfield      #14                 // Field sliceName:Lorg/hl7/fhir/dstu3/model/StringType;
      11: invokevirtual #10                 // Method org/hl7/fhir/dstu3/model/StringType.isEmpty:()Z
      14: ifne          21
      17: iconst_1
      18: goto          22
      21: iconst_0
      22: ireturn

  public org.hl7.fhir.dstu3.model.GraphDefinition$GraphDefinitionLinkComponent setSliceNameElement(org.hl7.fhir.dstu3.model.StringType);
    Code:
       0: aload_0
       1: aload_1
       2: putfield      #14                 // Field sliceName:Lorg/hl7/fhir/dstu3/model/StringType;
       5: aload_0
       6: areturn

  public java.lang.String getSliceName();
    Code:
       0: aload_0
       1: getfield      #14                 // Field sliceName:Lorg/hl7/fhir/dstu3/model/StringType;
       4: ifnonnull     11
       7: aconst_null
       8: goto          21
      11: aload_0
      12: getfield      #14                 // Field sliceName:Lorg/hl7/fhir/dstu3/model/StringType;
      15: invokevirtual #11                 // Method org/hl7/fhir/dstu3/model/StringType.getValue:()Ljava/lang/Object;
      18: checkcast     #12                 // class java/lang/String
      21: areturn

  public org.hl7.fhir.dstu3.model.GraphDefinition$GraphDefinitionLinkComponent setSliceName(java.lang.String);
    Code:
       0: aload_1
       1: invokestatic  #16                 // Method org/hl7/fhir/utilities/Utilities.noString:(Ljava/lang/String;)Z
       4: ifeq          15
       7: aload_0
       8: aconst_null
       9: putfield      #14                 // Field sliceName:Lorg/hl7/fhir/dstu3/model/StringType;
      12: goto          42
      15: aload_0
      16: getfield      #14                 // Field sliceName:Lorg/hl7/fhir/dstu3/model/StringType;
      19: ifnonnull     33
      22: aload_0
      23: new           #8                  // class org/hl7/fhir/dstu3/model/StringType
      26: dup
      27: invokespecial #9                  // Method org/hl7/fhir/dstu3/model/StringType."<init>":()V
      30: putfield      #14                 // Field sliceName:Lorg/hl7/fhir/dstu3/model/StringType;
      33: aload_0
      34: getfield      #14                 // Field sliceName:Lorg/hl7/fhir/dstu3/model/StringType;
      37: aload_1
      38: invokevirtual #13                 // Method org/hl7/fhir/dstu3/model/StringType.setValue:(Ljava/lang/Object;)Lorg/hl7/fhir/dstu3/model/PrimitiveType;
      41: pop
      42: aload_0
      43: areturn

  public org.hl7.fhir.dstu3.model.IntegerType getMinElement();
    Code:
       0: aload_0
       1: getfield      #17                 // Field min:Lorg/hl7/fhir/dstu3/model/IntegerType;
       4: ifnonnull     40
       7: invokestatic  #3                  // Method org/hl7/fhir/dstu3/model/Configuration.errorOnAutoCreate:()Z
      10: ifeq          23
      13: new           #4                  // class java/lang/Error
      16: dup
      17: ldc           #18                 // String Attempt to auto-create GraphDefinitionLinkComponent.min
      19: invokespecial #6                  // Method java/lang/Error."<init>":(Ljava/lang/String;)V
      22: athrow
      23: invokestatic  #7                  // Method org/hl7/fhir/dstu3/model/Configuration.doAutoCreate:()Z
      26: ifeq          40
      29: aload_0
      30: new           #19                 // class org/hl7/fhir/dstu3/model/IntegerType
      33: dup
      34: invokespecial #20                 // Method org/hl7/fhir/dstu3/model/IntegerType."<init>":()V
      37: putfield      #17                 // Field min:Lorg/hl7/fhir/dstu3/model/IntegerType;
      40: aload_0
      41: getfield      #17                 // Field min:Lorg/hl7/fhir/dstu3/model/IntegerType;
      44: areturn

  public boolean hasMinElement();
    Code:
       0: aload_0
       1: getfield      #17                 // Field min:Lorg/hl7/fhir/dstu3/model/IntegerType;
       4: ifnull        21
       7: aload_0
       8: getfield      #17                 // Field min:Lorg/hl7/fhir/dstu3/model/IntegerType;
      11: invokevirtual #21                 // Method org/hl7/fhir/dstu3/model/IntegerType.isEmpty:()Z
      14: ifne          21
      17: iconst_1
      18: goto          22
      21: iconst_0
      22: ireturn

  public boolean hasMin();
    Code:
       0: aload_0
       1: getfield      #17                 // Field min:Lorg/hl7/fhir/dstu3/model/IntegerType;
       4: ifnull        21
       7: aload_0
       8: getfield      #17                 // Field min:Lorg/hl7/fhir/dstu3/model/IntegerType;
      11: invokevirtual #21                 // Method org/hl7/fhir/dstu3/model/IntegerType.isEmpty:()Z
      14: ifne          21
      17: iconst_1
      18: goto          22
      21: iconst_0
      22: ireturn

  public org.hl7.fhir.dstu3.model.GraphDefinition$GraphDefinitionLinkComponent setMinElement(org.hl7.fhir.dstu3.model.IntegerType);
    Code:
       0: aload_0
       1: aload_1
       2: putfield      #17                 // Field min:Lorg/hl7/fhir/dstu3/model/IntegerType;
       5: aload_0
       6: areturn

  public int getMin();
    Code:
       0: aload_0
       1: getfield      #17                 // Field min:Lorg/hl7/fhir/dstu3/model/IntegerType;
       4: ifnull        17
       7: aload_0
       8: getfield      #17                 // Field min:Lorg/hl7/fhir/dstu3/model/IntegerType;
      11: invokevirtual #21                 // Method org/hl7/fhir/dstu3/model/IntegerType.isEmpty:()Z
      14: ifeq          21
      17: iconst_0
      18: goto          34
      21: aload_0
      22: getfield      #17                 // Field min:Lorg/hl7/fhir/dstu3/model/IntegerType;
      25: invokevirtual #22                 // Method org/hl7/fhir/dstu3/model/IntegerType.getValue:()Ljava/lang/Object;
      28: checkcast     #23                 // class java/lang/Integer
      31: invokevirtual #24                 // Method java/lang/Integer.intValue:()I
      34: ireturn

  public org.hl7.fhir.dstu3.model.GraphDefinition$GraphDefinitionLinkComponent setMin(int);
    Code:
       0: aload_0
       1: getfield      #17                 // Field min:Lorg/hl7/fhir/dstu3/model/IntegerType;
       4: ifnonnull     18
       7: aload_0
       8: new           #19                 // class org/hl7/fhir/dstu3/model/IntegerType
      11: dup
      12: invokespecial #20                 // Method org/hl7/fhir/dstu3/model/IntegerType."<init>":()V
      15: putfield      #17                 // Field min:Lorg/hl7/fhir/dstu3/model/IntegerType;
      18: aload_0
      19: getfield      #17                 // Field min:Lorg/hl7/fhir/dstu3/model/IntegerType;
      22: iload_1
      23: invokestatic  #25                 // Method java/lang/Integer.valueOf:(I)Ljava/lang/Integer;
      26: invokevirtual #26                 // Method org/hl7/fhir/dstu3/model/IntegerType.setValue:(Ljava/lang/Object;)Lorg/hl7/fhir/dstu3/model/PrimitiveType;
      29: pop
      30: aload_0
      31: areturn

  public org.hl7.fhir.dstu3.model.StringType getMaxElement();
    Code:
       0: aload_0
       1: getfield      #27                 // Field max:Lorg/hl7/fhir/dstu3/model/StringType;
       4: ifnonnull     40
       7: invokestatic  #3                  // Method org/hl7/fhir/dstu3/model/Configuration.errorOnAutoCreate:()Z
      10: ifeq          23
      13: new           #4                  // class java/lang/Error
      16: dup
      17: ldc           #28                 // String Attempt to auto-create GraphDefinitionLinkComponent.max
      19: invokespecial #6                  // Method java/lang/Error."<init>":(Ljava/lang/String;)V
      22: athrow
      23: invokestatic  #7                  // Method org/hl7/fhir/dstu3/model/Configuration.doAutoCreate:()Z
      26: ifeq          40
      29: aload_0
      30: new           #8                  // class org/hl7/fhir/dstu3/model/StringType
      33: dup
      34: invokespecial #9                  // Method org/hl7/fhir/dstu3/model/StringType."<init>":()V
      37: putfield      #27                 // Field max:Lorg/hl7/fhir/dstu3/model/StringType;
      40: aload_0
      41: getfield      #27                 // Field max:Lorg/hl7/fhir/dstu3/model/StringType;
      44: areturn

  public boolean hasMaxElement();
    Code:
       0: aload_0
       1: getfield      #27                 // Field max:Lorg/hl7/fhir/dstu3/model/StringType;
       4: ifnull        21
       7: aload_0
       8: getfield      #27                 // Field max:Lorg/hl7/fhir/dstu3/model/StringType;
      11: invokevirtual #10                 // Method org/hl7/fhir/dstu3/model/StringType.isEmpty:()Z
      14: ifne          21
      17: iconst_1
      18: goto          22
      21: iconst_0
      22: ireturn

  public boolean hasMax();
    Code:
       0: aload_0
       1: getfield      #27                 // Field max:Lorg/hl7/fhir/dstu3/model/StringType;
       4: ifnull        21
       7: aload_0
       8: getfield      #27                 // Field max:Lorg/hl7/fhir/dstu3/model/StringType;
      11: invokevirtual #10                 // Method org/hl7/fhir/dstu3/model/StringType.isEmpty:()Z
      14: ifne          21
      17: iconst_1
      18: goto          22
      21: iconst_0
      22: ireturn

  public org.hl7.fhir.dstu3.model.GraphDefinition$GraphDefinitionLinkComponent setMaxElement(org.hl7.fhir.dstu3.model.StringType);
    Code:
       0: aload_0
       1: aload_1
       2: putfield      #27                 // Field max:Lorg/hl7/fhir/dstu3/model/StringType;
       5: aload_0
       6: areturn

  public java.lang.String getMax();
    Code:
       0: aload_0
       1: getfield      #27                 // Field max:Lorg/hl7/fhir/dstu3/model/StringType;
       4: ifnonnull     11
       7: aconst_null
       8: goto          21
      11: aload_0
      12: getfield      #27                 // Field max:Lorg/hl7/fhir/dstu3/model/StringType;
      15: invokevirtual #11                 // Method org/hl7/fhir/dstu3/model/StringType.getValue:()Ljava/lang/Object;
      18: checkcast     #12                 // class java/lang/String
      21: areturn

  public org.hl7.fhir.dstu3.model.GraphDefinition$GraphDefinitionLinkComponent setMax(java.lang.String);
    Code:
       0: aload_1
       1: invokestatic  #16                 // Method org/hl7/fhir/utilities/Utilities.noString:(Ljava/lang/String;)Z
       4: ifeq          15
       7: aload_0
       8: aconst_null
       9: putfield      #27                 // Field max:Lorg/hl7/fhir/dstu3/model/StringType;
      12: goto          42
      15: aload_0
      16: getfield      #27                 // Field max:Lorg/hl7/fhir/dstu3/model/StringType;
      19: ifnonnull     33
      22: aload_0
      23: new           #8                  // class org/hl7/fhir/dstu3/model/StringType
      26: dup
      27: invokespecial #9                  // Method org/hl7/fhir/dstu3/model/StringType."<init>":()V
      30: putfield      #27                 // Field max:Lorg/hl7/fhir/dstu3/model/StringType;
      33: aload_0
      34: getfield      #27                 // Field max:Lorg/hl7/fhir/dstu3/model/StringType;
      37: aload_1
      38: invokevirtual #13                 // Method org/hl7/fhir/dstu3/model/StringType.setValue:(Ljava/lang/Object;)Lorg/hl7/fhir/dstu3/model/PrimitiveType;
      41: pop
      42: aload_0
      43: areturn

  public org.hl7.fhir.dstu3.model.StringType getDescriptionElement();
    Code:
       0: aload_0
       1: getfield      #29                 // Field description:Lorg/hl7/fhir/dstu3/model/StringType;
       4: ifnonnull     40
       7: invokestatic  #3                  // Method org/hl7/fhir/dstu3/model/Configuration.errorOnAutoCreate:()Z
      10: ifeq          23
      13: new           #4                  // class java/lang/Error
      16: dup
      17: ldc           #30                 // String Attempt to auto-create GraphDefinitionLinkComponent.description
      19: invokespecial #6                  // Method java/lang/Error."<init>":(Ljava/lang/String;)V
      22: athrow
      23: invokestatic  #7                  // Method org/hl7/fhir/dstu3/model/Configuration.doAutoCreate:()Z
      26: ifeq          40
      29: aload_0
      30: new           #8                  // class org/hl7/fhir/dstu3/model/StringType
      33: dup
      34: invokespecial #9                  // Method org/hl7/fhir/dstu3/model/StringType."<init>":()V
      37: putfield      #29                 // Field description:Lorg/hl7/fhir/dstu3/model/StringType;
      40: aload_0
      41: getfield      #29                 // Field description:Lorg/hl7/fhir/dstu3/model/StringType;
      44: areturn

  public boolean hasDescriptionElement();
    Code:
       0: aload_0
       1: getfield      #29                 // Field description:Lorg/hl7/fhir/dstu3/model/StringType;
       4: ifnull        21
       7: aload_0
       8: getfield      #29                 // Field description:Lorg/hl7/fhir/dstu3/model/StringType;
      11: invokevirtual #10                 // Method org/hl7/fhir/dstu3/model/StringType.isEmpty:()Z
      14: ifne          21
      17: iconst_1
      18: goto          22
      21: iconst_0
      22: ireturn

  public boolean hasDescription();
    Code:
       0: aload_0
       1: getfield      #29                 // Field description:Lorg/hl7/fhir/dstu3/model/StringType;
       4: ifnull        21
       7: aload_0
       8: getfield      #29                 // Field description:Lorg/hl7/fhir/dstu3/model/StringType;
      11: invokevirtual #10                 // Method org/hl7/fhir/dstu3/model/StringType.isEmpty:()Z
      14: ifne          21
      17: iconst_1
      18: goto          22
      21: iconst_0
      22: ireturn

  public org.hl7.fhir.dstu3.model.GraphDefinition$GraphDefinitionLinkComponent setDescriptionElement(org.hl7.fhir.dstu3.model.StringType);
    Code:
       0: aload_0
       1: aload_1
       2: putfield      #29                 // Field description:Lorg/hl7/fhir/dstu3/model/StringType;
       5: aload_0
       6: areturn

  public java.lang.String getDescription();
    Code:
       0: aload_0
       1: getfield      #29                 // Field description:Lorg/hl7/fhir/dstu3/model/StringType;
       4: ifnonnull     11
       7: aconst_null
       8: goto          21
      11: aload_0
      12: getfield      #29                 // Field description:Lorg/hl7/fhir/dstu3/model/StringType;
      15: invokevirtual #11                 // Method org/hl7/fhir/dstu3/model/StringType.getValue:()Ljava/lang/Object;
      18: checkcast     #12                 // class java/lang/String
      21: areturn

  public org.hl7.fhir.dstu3.model.GraphDefinition$GraphDefinitionLinkComponent setDescription(java.lang.String);
    Code:
       0: aload_1
       1: invokestatic  #16                 // Method org/hl7/fhir/utilities/Utilities.noString:(Ljava/lang/String;)Z
       4: ifeq          15
       7: aload_0
       8: aconst_null
       9: putfield      #29                 // Field description:Lorg/hl7/fhir/dstu3/model/StringType;
      12: goto          42
      15: aload_0
      16: getfield      #29                 // Field description:Lorg/hl7/fhir/dstu3/model/StringType;
      19: ifnonnull     33
      22: aload_0
      23: new           #8                  // class org/hl7/fhir/dstu3/model/StringType
      26: dup
      27: invokespecial #9                  // Method org/hl7/fhir/dstu3/model/StringType."<init>":()V
      30: putfield      #29                 // Field description:Lorg/hl7/fhir/dstu3/model/StringType;
      33: aload_0
      34: getfield      #29                 // Field description:Lorg/hl7/fhir/dstu3/model/StringType;
      37: aload_1
      38: invokevirtual #13                 // Method org/hl7/fhir/dstu3/model/StringType.setValue:(Ljava/lang/Object;)Lorg/hl7/fhir/dstu3/model/PrimitiveType;
      41: pop
      42: aload_0
      43: areturn

  public java.util.List<org.hl7.fhir.dstu3.model.GraphDefinition$GraphDefinitionLinkTargetComponent> getTarget();
    Code:
       0: aload_0
       1: getfield      #31                 // Field target:Ljava/util/List;
       4: ifnonnull     18
       7: aload_0
       8: new           #32                 // class java/util/ArrayList
      11: dup
      12: invokespecial #33                 // Method java/util/ArrayList."<init>":()V
      15: putfield      #31                 // Field target:Ljava/util/List;
      18: aload_0
      19: getfield      #31                 // Field target:Ljava/util/List;
      22: areturn

  public org.hl7.fhir.dstu3.model.GraphDefinition$GraphDefinitionLinkComponent setTarget(java.util.List<org.hl7.fhir.dstu3.model.GraphDefinition$GraphDefinitionLinkTargetComponent>);
    Code:
       0: aload_0
       1: aload_1
       2: putfield      #31                 // Field target:Ljava/util/List;
       5: aload_0
       6: areturn

  public boolean hasTarget();
    Code:
       0: aload_0
       1: getfield      #31                 // Field target:Ljava/util/List;
       4: ifnonnull     9
       7: iconst_0
       8: ireturn
       9: aload_0
      10: getfield      #31                 // Field target:Ljava/util/List;
      13: invokeinterface #34,  1           // InterfaceMethod java/util/List.iterator:()Ljava/util/Iterator;
      18: astore_1
      19: aload_1
      20: invokeinterface #35,  1           // InterfaceMethod java/util/Iterator.hasNext:()Z
      25: ifeq          50
      28: aload_1
      29: invokeinterface #36,  1           // InterfaceMethod java/util/Iterator.next:()Ljava/lang/Object;
      34: checkcast     #37                 // class org/hl7/fhir/dstu3/model/GraphDefinition$GraphDefinitionLinkTargetComponent
      37: astore_2
      38: aload_2
      39: invokevirtual #38                 // Method org/hl7/fhir/dstu3/model/GraphDefinition$GraphDefinitionLinkTargetComponent.isEmpty:()Z
      42: ifne          47
      45: iconst_1
      46: ireturn
      47: goto          19
      50: iconst_0
      51: ireturn

  public org.hl7.fhir.dstu3.model.GraphDefinition$GraphDefinitionLinkTargetComponent addTarget();
    Code:
       0: new           #37                 // class org/hl7/fhir/dstu3/model/GraphDefinition$GraphDefinitionLinkTargetComponent
       3: dup
       4: invokespecial #39                 // Method org/hl7/fhir/dstu3/model/GraphDefinition$GraphDefinitionLinkTargetComponent."<init>":()V
       7: astore_1
       8: aload_0
       9: getfield      #31                 // Field target:Ljava/util/List;
      12: ifnonnull     26
      15: aload_0
      16: new           #32                 // class java/util/ArrayList
      19: dup
      20: invokespecial #33                 // Method java/util/ArrayList."<init>":()V
      23: putfield      #31                 // Field target:Ljava/util/List;
      26: aload_0
      27: getfield      #31                 // Field target:Ljava/util/List;
      30: aload_1
      31: invokeinterface #40,  2           // InterfaceMethod java/util/List.add:(Ljava/lang/Object;)Z
      36: pop
      37: aload_1
      38: areturn

  public org.hl7.fhir.dstu3.model.GraphDefinition$GraphDefinitionLinkComponent addTarget(org.hl7.fhir.dstu3.model.GraphDefinition$GraphDefinitionLinkTargetComponent);
    Code:
       0: aload_1
       1: ifnonnull     6
       4: aload_0
       5: areturn
       6: aload_0
       7: getfield      #31                 // Field target:Ljava/util/List;
      10: ifnonnull     24
      13: aload_0
      14: new           #32                 // class java/util/ArrayList
      17: dup
      18: invokespecial #33                 // Method java/util/ArrayList."<init>":()V
      21: putfield      #31                 // Field target:Ljava/util/List;
      24: aload_0
      25: getfield      #31                 // Field target:Ljava/util/List;
      28: aload_1
      29: invokeinterface #40,  2           // InterfaceMethod java/util/List.add:(Ljava/lang/Object;)Z
      34: pop
      35: aload_0
      36: areturn

  public org.hl7.fhir.dstu3.model.GraphDefinition$GraphDefinitionLinkTargetComponent getTargetFirstRep();
    Code:
       0: aload_0
       1: invokevirtual #41                 // Method getTarget:()Ljava/util/List;
       4: invokeinterface #42,  1           // InterfaceMethod java/util/List.isEmpty:()Z
       9: ifeq          17
      12: aload_0
      13: invokevirtual #43                 // Method addTarget:()Lorg/hl7/fhir/dstu3/model/GraphDefinition$GraphDefinitionLinkTargetComponent;
      16: pop
      17: aload_0
      18: invokevirtual #41                 // Method getTarget:()Ljava/util/List;
      21: iconst_0
      22: invokeinterface #44,  2           // InterfaceMethod java/util/List.get:(I)Ljava/lang/Object;
      27: checkcast     #37                 // class org/hl7/fhir/dstu3/model/GraphDefinition$GraphDefinitionLinkTargetComponent
      30: areturn

  protected void listChildren(java.util.List<org.hl7.fhir.dstu3.model.Property>);
    Code:
       0: aload_0
       1: aload_1
       2: invokespecial #45                 // Method org/hl7/fhir/dstu3/model/BackboneElement.listChildren:(Ljava/util/List;)V
       5: aload_1
       6: new           #46                 // class org/hl7/fhir/dstu3/model/Property
       9: dup
      10: ldc           #47                 // String path
      12: ldc           #48                 // String string
      14: ldc           #49                 // String Path in the resource that contains the link.
      16: iconst_0
      17: iconst_1
      18: aload_0
      19: getfield      #2                  // Field path:Lorg/hl7/fhir/dstu3/model/StringType;
      22: invokespecial #50                 // Method org/hl7/fhir/dstu3/model/Property."<init>":(Ljava/lang/String;Ljava/lang/String;Ljava/lang/String;IILorg/hl7/fhir/dstu3/model/Base;)V
      25: invokeinterface #40,  2           // InterfaceMethod java/util/List.add:(Ljava/lang/Object;)Z
      30: pop
      31: aload_1
      32: new           #46                 // class org/hl7/fhir/dstu3/model/Property
      35: dup
      36: ldc           #51                 // String sliceName
      38: ldc           #48                 // String string
      40: ldc           #52                 // String Which slice (if profiled).
      42: iconst_0
      43: iconst_1
      44: aload_0
      45: getfield      #14                 // Field sliceName:Lorg/hl7/fhir/dstu3/model/StringType;
      48: invokespecial #50                 // Method org/hl7/fhir/dstu3/model/Property."<init>":(Ljava/lang/String;Ljava/lang/String;Ljava/lang/String;IILorg/hl7/fhir/dstu3/model/Base;)V
      51: invokeinterface #40,  2           // InterfaceMethod java/util/List.add:(Ljava/lang/Object;)Z
      56: pop
      57: aload_1
      58: new           #46                 // class org/hl7/fhir/dstu3/model/Property
      61: dup
      62: ldc           #53                 // String min
      64: ldc           #54                 // String integer
      66: ldc           #55                 // String Minimum occurrences for this link.
      68: iconst_0
      69: iconst_1
      70: aload_0
      71: getfield      #17                 // Field min:Lorg/hl7/fhir/dstu3/model/IntegerType;
      74: invokespecial #50                 // Method org/hl7/fhir/dstu3/model/Property."<init>":(Ljava/lang/String;Ljava/lang/String;Ljava/lang/String;IILorg/hl7/fhir/dstu3/model/Base;)V
      77: invokeinterface #40,  2           // InterfaceMethod java/util/List.add:(Ljava/lang/Object;)Z
      82: pop
      83: aload_1
      84: new           #46                 // class org/hl7/fhir/dstu3/model/Property
      87: dup
      88: ldc           #56                 // String max
      90: ldc           #48                 // String string
      92: ldc           #57                 // String Maximum occurrences for this link.
      94: iconst_0
      95: iconst_1
      96: aload_0
      97: getfield      #27                 // Field max:Lorg/hl7/fhir/dstu3/model/StringType;
     100: invokespecial #50                 // Method org/hl7/fhir/dstu3/model/Property."<init>":(Ljava/lang/String;Ljava/lang/String;Ljava/lang/String;IILorg/hl7/fhir/dstu3/model/Base;)V
     103: invokeinterface #40,  2           // InterfaceMethod java/util/List.add:(Ljava/lang/Object;)Z
     108: pop
     109: aload_1
     110: new           #46                 // class org/hl7/fhir/dstu3/model/Property
     113: dup
     114: ldc           #58                 // String description
     116: ldc           #48                 // String string
     118: ldc           #59                 // String Information about why this link is of interest in this graph definition.
     120: iconst_0
     121: iconst_1
     122: aload_0
     123: getfield      #29                 // Field description:Lorg/hl7/fhir/dstu3/model/StringType;
     126: invokespecial #50                 // Method org/hl7/fhir/dstu3/model/Property."<init>":(Ljava/lang/String;Ljava/lang/String;Ljava/lang/String;IILorg/hl7/fhir/dstu3/model/Base;)V
     129: invokeinterface #40,  2           // InterfaceMethod java/util/List.add:(Ljava/lang/Object;)Z
     134: pop
     135: aload_1
     136: new           #46                 // class org/hl7/fhir/dstu3/model/Property
     139: dup
     140: ldc           #60                 // String target
     142: ldc           #61                 // String
     144: ldc           #62                 // String Potential target for the link.
     146: iconst_0
     147: ldc           #63                 // int 2147483647
     149: aload_0
     150: getfield      #31                 // Field target:Ljava/util/List;
     153: invokespecial #64                 // Method org/hl7/fhir/dstu3/model/Property."<init>":(Ljava/lang/String;Ljava/lang/String;Ljava/lang/String;IILjava/util/List;)V
     156: invokeinterface #40,  2           // InterfaceMethod java/util/List.add:(Ljava/lang/Object;)Z
     161: pop
     162: return

  public org.hl7.fhir.dstu3.model.Property getNamedProperty(int, java.lang.String, boolean) throws org.hl7.fhir.exceptions.FHIRException;
    Code:
       0: iload_1
       1: lookupswitch  { // 6
           -1724546052: 140
            -880905839: 160
            -825289923: 80
                107876: 120
                108114: 100
               3433509: 60
               default: 181
          }
      60: new           #46                 // class org/hl7/fhir/dstu3/model/Property
      63: dup
      64: ldc           #47                 // String path
      66: ldc           #48                 // String string
      68: ldc           #49                 // String Path in the resource that contains the link.
      70: iconst_0
      71: iconst_1
      72: aload_0
      73: getfield      #2                  // Field path:Lorg/hl7/fhir/dstu3/model/StringType;
      76: invokespecial #50                 // Method org/hl7/fhir/dstu3/model/Property."<init>":(Ljava/lang/String;Ljava/lang/String;Ljava/lang/String;IILorg/hl7/fhir/dstu3/model/Base;)V
      79: areturn
      80: new           #46                 // class org/hl7/fhir/dstu3/model/Property
      83: dup
      84: ldc           #51                 // String sliceName
      86: ldc           #48                 // String string
      88: ldc           #52                 // String Which slice (if profiled).
      90: iconst_0
      91: iconst_1
      92: aload_0
      93: getfield      #14                 // Field sliceName:Lorg/hl7/fhir/dstu3/model/StringType;
      96: invokespecial #50                 // Method org/hl7/fhir/dstu3/model/Property."<init>":(Ljava/lang/String;Ljava/lang/String;Ljava/lang/String;IILorg/hl7/fhir/dstu3/model/Base;)V
      99: areturn
     100: new           #46                 // class org/hl7/fhir/dstu3/model/Property
     103: dup
     104: ldc           #53                 // String min
     106: ldc           #54                 // String integer
     108: ldc           #55                 // String Minimum occurrences for this link.
     110: iconst_0
     111: iconst_1
     112: aload_0
     113: getfield      #17                 // Field min:Lorg/hl7/fhir/dstu3/model/IntegerType;
     116: invokespecial #50                 // Method org/hl7/fhir/dstu3/model/Property."<init>":(Ljava/lang/String;Ljava/lang/String;Ljava/lang/String;IILorg/hl7/fhir/dstu3/model/Base;)V
     119: areturn
     120: new           #46                 // class org/hl7/fhir/dstu3/model/Property
     123: dup
     124: ldc           #56                 // String max
     126: ldc           #48                 // String string
     128: ldc           #57                 // String Maximum occurrences for this link.
     130: iconst_0
     131: iconst_1
     132: aload_0
     133: getfield      #27                 // Field max:Lorg/hl7/fhir/dstu3/model/StringType;
     136: invokespecial #50                 // Method org/hl7/fhir/dstu3/model/Property."<init>":(Ljava/lang/String;Ljava/lang/String;Ljava/lang/String;IILorg/hl7/fhir/dstu3/model/Base;)V
     139: areturn
     140: new           #46                 // class org/hl7/fhir/dstu3/model/Property
     143: dup
     144: ldc           #58                 // String description
     146: ldc           #48                 // String string
     148: ldc           #59                 // String Information about why this link is of interest in this graph definition.
     150: iconst_0
     151: iconst_1
     152: aload_0
     153: getfield      #29                 // Field description:Lorg/hl7/fhir/dstu3/model/StringType;
     156: invokespecial #50                 // Method org/hl7/fhir/dstu3/model/Property."<init>":(Ljava/lang/String;Ljava/lang/String;Ljava/lang/String;IILorg/hl7/fhir/dstu3/model/Base;)V
     159: areturn
     160: new           #46                 // class org/hl7/fhir/dstu3/model/Property
     163: dup
     164: ldc           #60                 // String target
     166: ldc           #61                 // String
     168: ldc           #62                 // String Potential target for the link.
     170: iconst_0
     171: ldc           #63                 // int 2147483647
     173: aload_0
     174: getfield      #31                 // Field target:Ljava/util/List;
     177: invokespecial #64                 // Method org/hl7/fhir/dstu3/model/Property."<init>":(Ljava/lang/String;Ljava/lang/String;Ljava/lang/String;IILjava/util/List;)V
     180: areturn
     181: aload_0
     182: iload_1
     183: aload_2
     184: iload_3
     185: invokespecial #65                 // Method org/hl7/fhir/dstu3/model/BackboneElement.getNamedProperty:(ILjava/lang/String;Z)Lorg/hl7/fhir/dstu3/model/Property;
     188: areturn

  public org.hl7.fhir.dstu3.model.Base[] getProperty(int, java.lang.String, boolean) throws org.hl7.fhir.exceptions.FHIRException;
    Code:
       0: iload_1
       1: lookupswitch  { // 6
           -1724546052: 164
            -880905839: 190
            -825289923: 86
                107876: 138
                108114: 112
               3433509: 60
               default: 229
          }
      60: aload_0
      61: getfield      #2                  // Field path:Lorg/hl7/fhir/dstu3/model/StringType;
      64: ifnonnull     74
      67: iconst_0
      68: anewarray     #66                 // class org/hl7/fhir/dstu3/model/Base
      71: goto          85
      74: iconst_1
      75: anewarray     #66                 // class org/hl7/fhir/dstu3/model/Base
      78: dup
      79: iconst_0
      80: aload_0
      81: getfield      #2                  // Field path:Lorg/hl7/fhir/dstu3/model/StringType;
      84: aastore
      85: areturn
      86: aload_0
      87: getfield      #14                 // Field sliceName:Lorg/hl7/fhir/dstu3/model/StringType;
      90: ifnonnull     100
      93: iconst_0
      94: anewarray     #66                 // class org/hl7/fhir/dstu3/model/Base
      97: goto          111
     100: iconst_1
     101: anewarray     #66                 // class org/hl7/fhir/dstu3/model/Base
     104: dup
     105: iconst_0
     106: aload_0
     107: getfield      #14                 // Field sliceName:Lorg/hl7/fhir/dstu3/model/StringType;
     110: aastore
     111: areturn
     112: aload_0
     113: getfield      #17                 // Field min:Lorg/hl7/fhir/dstu3/model/IntegerType;
     116: ifnonnull     126
     119: iconst_0
     120: anewarray     #66                 // class org/hl7/fhir/dstu3/model/Base
     123: goto          137
     126: iconst_1
     127: anewarray     #66                 // class org/hl7/fhir/dstu3/model/Base
     130: dup
     131: iconst_0
     132: aload_0
     133: getfield      #17                 // Field min:Lorg/hl7/fhir/dstu3/model/IntegerType;
     136: aastore
     137: areturn
     138: aload_0
     139: getfield      #27                 // Field max:Lorg/hl7/fhir/dstu3/model/StringType;
     142: ifnonnull     152
     145: iconst_0
     146: anewarray     #66                 // class org/hl7/fhir/dstu3/model/Base
     149: goto          163
     152: iconst_1
     153: anewarray     #66                 // class org/hl7/fhir/dstu3/model/Base
     156: dup
     157: iconst_0
     158: aload_0
     159: getfield      #27                 // Field max:Lorg/hl7/fhir/dstu3/model/StringType;
     162: aastore
     163: areturn
     164: aload_0
     165: getfield      #29                 // Field description:Lorg/hl7/fhir/dstu3/model/StringType;
     168: ifnonnull     178
     171: iconst_0
     172: anewarray     #66                 // class org/hl7/fhir/dstu3/model/Base
     175: goto          189
     178: iconst_1
     179: anewarray     #66                 // class org/hl7/fhir/dstu3/model/Base
     182: dup
     183: iconst_0
     184: aload_0
     185: getfield      #29                 // Field description:Lorg/hl7/fhir/dstu3/model/StringType;
     188: aastore
     189: areturn
     190: aload_0
     191: getfield      #31                 // Field target:Ljava/util/List;
     194: ifnonnull     204
     197: iconst_0
     198: anewarray     #66                 // class org/hl7/fhir/dstu3/model/Base
     201: goto          228
     204: aload_0
     205: getfield      #31                 // Field target:Ljava/util/List;
     208: aload_0
     209: getfield      #31                 // Field target:Ljava/util/List;
     212: invokeinterface #67,  1           // InterfaceMethod java/util/List.size:()I
     217: anewarray     #66                 // class org/hl7/fhir/dstu3/model/Base
     220: invokeinterface #68,  2           // InterfaceMethod java/util/List.toArray:([Ljava/lang/Object;)[Ljava/lang/Object;
     225: checkcast     #69                 // class "[Lorg/hl7/fhir/dstu3/model/Base;"
     228: areturn
     229: aload_0
     230: iload_1
     231: aload_2
     232: iload_3
     233: invokespecial #70                 // Method org/hl7/fhir/dstu3/model/BackboneElement.getProperty:(ILjava/lang/String;Z)[Lorg/hl7/fhir/dstu3/model/Base;
     236: areturn

  public org.hl7.fhir.dstu3.model.Base setProperty(int, java.lang.String, org.hl7.fhir.dstu3.model.Base) throws org.hl7.fhir.exceptions.FHIRException;
    Code:
       0: iload_1
       1: lookupswitch  { // 6
           -1724546052: 104
            -880905839: 115
            -825289923: 71
                107876: 93
                108114: 82
               3433509: 60
               default: 131
          }
      60: aload_0
      61: aload_0
      62: aload_3
      63: invokevirtual #71                 // Method castToString:(Lorg/hl7/fhir/dstu3/model/Base;)Lorg/hl7/fhir/dstu3/model/StringType;
      66: putfield      #2                  // Field path:Lorg/hl7/fhir/dstu3/model/StringType;
      69: aload_3
      70: areturn
      71: aload_0
      72: aload_0
      73: aload_3
      74: invokevirtual #71                 // Method castToString:(Lorg/hl7/fhir/dstu3/model/Base;)Lorg/hl7/fhir/dstu3/model/StringType;
      77: putfield      #14                 // Field sliceName:Lorg/hl7/fhir/dstu3/model/StringType;
      80: aload_3
      81: areturn
      82: aload_0
      83: aload_0
      84: aload_3
      85: invokevirtual #72                 // Method castToInteger:(Lorg/hl7/fhir/dstu3/model/Base;)Lorg/hl7/fhir/dstu3/model/IntegerType;
      88: putfield      #17                 // Field min:Lorg/hl7/fhir/dstu3/model/IntegerType;
      91: aload_3
      92: areturn
      93: aload_0
      94: aload_0
      95: aload_3
      96: invokevirtual #71                 // Method castToString:(Lorg/hl7/fhir/dstu3/model/Base;)Lorg/hl7/fhir/dstu3/model/StringType;
      99: putfield      #27                 // Field max:Lorg/hl7/fhir/dstu3/model/StringType;
     102: aload_3
     103: areturn
     104: aload_0
     105: aload_0
     106: aload_3
     107: invokevirtual #71                 // Method castToString:(Lorg/hl7/fhir/dstu3/model/Base;)Lorg/hl7/fhir/dstu3/model/StringType;
     110: putfield      #29                 // Field description:Lorg/hl7/fhir/dstu3/model/StringType;
     113: aload_3
     114: areturn
     115: aload_0
     116: invokevirtual #41                 // Method getTarget:()Ljava/util/List;
     119: aload_3
     120: checkcast     #37                 // class org/hl7/fhir/dstu3/model/GraphDefinition$GraphDefinitionLinkTargetComponent
     123: invokeinterface #40,  2           // InterfaceMethod java/util/List.add:(Ljava/lang/Object;)Z
     128: pop
     129: aload_3
     130: areturn
     131: aload_0
     132: iload_1
     133: aload_2
     134: aload_3
     135: invokespecial #73                 // Method org/hl7/fhir/dstu3/model/BackboneElement.setProperty:(ILjava/lang/String;Lorg/hl7/fhir/dstu3/model/Base;)Lorg/hl7/fhir/dstu3/model/Base;
     138: areturn

  public org.hl7.fhir.dstu3.model.Base setProperty(java.lang.String, org.hl7.fhir.dstu3.model.Base) throws org.hl7.fhir.exceptions.FHIRException;
    Code:
       0: aload_1
       1: ldc           #47                 // String path
       3: invokevirtual #74                 // Method java/lang/String.equals:(Ljava/lang/Object;)Z
       6: ifeq          21
       9: aload_0
      10: aload_0
      11: aload_2
      12: invokevirtual #71                 // Method castToString:(Lorg/hl7/fhir/dstu3/model/Base;)Lorg/hl7/fhir/dstu3/model/StringType;
      15: putfield      #2                  // Field path:Lorg/hl7/fhir/dstu3/model/StringType;
      18: goto          138
      21: aload_1
      22: ldc           #51                 // String sliceName
      24: invokevirtual #74                 // Method java/lang/String.equals:(Ljava/lang/Object;)Z
      27: ifeq          42
      30: aload_0
      31: aload_0
      32: aload_2
      33: invokevirtual #71                 // Method castToString:(Lorg/hl7/fhir/dstu3/model/Base;)Lorg/hl7/fhir/dstu3/model/StringType;
      36: putfield      #14                 // Field sliceName:Lorg/hl7/fhir/dstu3/model/StringType;
      39: goto          138
      42: aload_1
      43: ldc           #53                 // String min
      45: invokevirtual #74                 // Method java/lang/String.equals:(Ljava/lang/Object;)Z
      48: ifeq          63
      51: aload_0
      52: aload_0
      53: aload_2
      54: invokevirtual #72                 // Method castToInteger:(Lorg/hl7/fhir/dstu3/model/Base;)Lorg/hl7/fhir/dstu3/model/IntegerType;
      57: putfield      #17                 // Field min:Lorg/hl7/fhir/dstu3/model/IntegerType;
      60: goto          138
      63: aload_1
      64: ldc           #56                 // String max
      66: invokevirtual #74                 // Method java/lang/String.equals:(Ljava/lang/Object;)Z
      69: ifeq          84
      72: aload_0
      73: aload_0
      74: aload_2
      75: invokevirtual #71                 // Method castToString:(Lorg/hl7/fhir/dstu3/model/Base;)Lorg/hl7/fhir/dstu3/model/StringType;
      78: putfield      #27                 // Field max:Lorg/hl7/fhir/dstu3/model/StringType;
      81: goto          138
      84: aload_1
      85: ldc           #58                 // String description
      87: invokevirtual #74                 // Method java/lang/String.equals:(Ljava/lang/Object;)Z
      90: ifeq          105
      93: aload_0
      94: aload_0
      95: aload_2
      96: invokevirtual #71                 // Method castToString:(Lorg/hl7/fhir/dstu3/model/Base;)Lorg/hl7/fhir/dstu3/model/StringType;
      99: putfield      #29                 // Field description:Lorg/hl7/fhir/dstu3/model/StringType;
     102: goto          138
     105: aload_1
     106: ldc           #60                 // String target
     108: invokevirtual #74                 // Method java/lang/String.equals:(Ljava/lang/Object;)Z
     111: ifeq          131
     114: aload_0
     115: invokevirtual #41                 // Method getTarget:()Ljava/util/List;
     118: aload_2
     119: checkcast     #37                 // class org/hl7/fhir/dstu3/model/GraphDefinition$GraphDefinitionLinkTargetComponent
     122: invokeinterface #40,  2           // InterfaceMethod java/util/List.add:(Ljava/lang/Object;)Z
     127: pop
     128: goto          138
     131: aload_0
     132: aload_1
     133: aload_2
     134: invokespecial #75                 // Method org/hl7/fhir/dstu3/model/BackboneElement.setProperty:(Ljava/lang/String;Lorg/hl7/fhir/dstu3/model/Base;)Lorg/hl7/fhir/dstu3/model/Base;
     137: areturn
     138: aload_2
     139: areturn

  public org.hl7.fhir.dstu3.model.Base makeProperty(int, java.lang.String) throws org.hl7.fhir.exceptions.FHIRException;
    Code:
       0: iload_1
       1: lookupswitch  { // 6
           -1724546052: 80
            -880905839: 85
            -825289923: 65
                107876: 75
                108114: 70
               3433509: 60
               default: 90
          }
      60: aload_0
      61: invokevirtual #76                 // Method getPathElement:()Lorg/hl7/fhir/dstu3/model/StringType;
      64: areturn
      65: aload_0
      66: invokevirtual #77                 // Method getSliceNameElement:()Lorg/hl7/fhir/dstu3/model/StringType;
      69: areturn
      70: aload_0
      71: invokevirtual #78                 // Method getMinElement:()Lorg/hl7/fhir/dstu3/model/IntegerType;
      74: areturn
      75: aload_0
      76: invokevirtual #79                 // Method getMaxElement:()Lorg/hl7/fhir/dstu3/model/StringType;
      79: areturn
      80: aload_0
      81: invokevirtual #80                 // Method getDescriptionElement:()Lorg/hl7/fhir/dstu3/model/StringType;
      84: areturn
      85: aload_0
      86: invokevirtual #43                 // Method addTarget:()Lorg/hl7/fhir/dstu3/model/GraphDefinition$GraphDefinitionLinkTargetComponent;
      89: areturn
      90: aload_0
      91: iload_1
      92: aload_2
      93: invokespecial #81                 // Method org/hl7/fhir/dstu3/model/BackboneElement.makeProperty:(ILjava/lang/String;)Lorg/hl7/fhir/dstu3/model/Base;
      96: areturn

  public java.lang.String[] getTypesForProperty(int, java.lang.String) throws org.hl7.fhir.exceptions.FHIRException;
    Code:
       0: iload_1
       1: lookupswitch  { // 6
           -1724546052: 100
            -880905839: 110
            -825289923: 70
                107876: 90
                108114: 80
               3433509: 60
               default: 115
          }
      60: iconst_1
      61: anewarray     #12                 // class java/lang/String
      64: dup
      65: iconst_0
      66: ldc           #48                 // String string
      68: aastore
      69: areturn
      70: iconst_1
      71: anewarray     #12                 // class java/lang/String
      74: dup
      75: iconst_0
      76: ldc           #48                 // String string
      78: aastore
      79: areturn
      80: iconst_1
      81: anewarray     #12                 // class java/lang/String
      84: dup
      85: iconst_0
      86: ldc           #54                 // String integer
      88: aastore
      89: areturn
      90: iconst_1
      91: anewarray     #12                 // class java/lang/String
      94: dup
      95: iconst_0
      96: ldc           #48                 // String string
      98: aastore
      99: areturn
     100: iconst_1
     101: anewarray     #12                 // class java/lang/String
     104: dup
     105: iconst_0
     106: ldc           #48                 // String string
     108: aastore
     109: areturn
     110: iconst_0
     111: anewarray     #12                 // class java/lang/String
     114: areturn
     115: aload_0
     116: iload_1
     117: aload_2
     118: invokespecial #82                 // Method org/hl7/fhir/dstu3/model/BackboneElement.getTypesForProperty:(ILjava/lang/String;)[Ljava/lang/String;
     121: areturn

  public org.hl7.fhir.dstu3.model.Base addChild(java.lang.String) throws org.hl7.fhir.exceptions.FHIRException;
    Code:
       0: aload_1
       1: ldc           #47                 // String path
       3: invokevirtual #74                 // Method java/lang/String.equals:(Ljava/lang/Object;)Z
       6: ifeq          19
       9: new           #83                 // class org/hl7/fhir/exceptions/FHIRException
      12: dup
      13: ldc           #84                 // String Cannot call addChild on a primitive type GraphDefinition.path
      15: invokespecial #85                 // Method org/hl7/fhir/exceptions/FHIRException."<init>":(Ljava/lang/String;)V
      18: athrow
      19: aload_1
      20: ldc           #51                 // String sliceName
      22: invokevirtual #74                 // Method java/lang/String.equals:(Ljava/lang/Object;)Z
      25: ifeq          38
      28: new           #83                 // class org/hl7/fhir/exceptions/FHIRException
      31: dup
      32: ldc           #86                 // String Cannot call addChild on a primitive type GraphDefinition.sliceName
      34: invokespecial #85                 // Method org/hl7/fhir/exceptions/FHIRException."<init>":(Ljava/lang/String;)V
      37: athrow
      38: aload_1
      39: ldc           #53                 // String min
      41: invokevirtual #74                 // Method java/lang/String.equals:(Ljava/lang/Object;)Z
      44: ifeq          57
      47: new           #83                 // class org/hl7/fhir/exceptions/FHIRException
      50: dup
      51: ldc           #87                 // String Cannot call addChild on a primitive type GraphDefinition.min
      53: invokespecial #85                 // Method org/hl7/fhir/exceptions/FHIRException."<init>":(Ljava/lang/String;)V
      56: athrow
      57: aload_1
      58: ldc           #56                 // String max
      60: invokevirtual #74                 // Method java/lang/String.equals:(Ljava/lang/Object;)Z
      63: ifeq          76
      66: new           #83                 // class org/hl7/fhir/exceptions/FHIRException
      69: dup
      70: ldc           #88                 // String Cannot call addChild on a primitive type GraphDefinition.max
      72: invokespecial #85                 // Method org/hl7/fhir/exceptions/FHIRException."<init>":(Ljava/lang/String;)V
      75: athrow
      76: aload_1
      77: ldc           #58                 // String description
      79: invokevirtual #74                 // Method java/lang/String.equals:(Ljava/lang/Object;)Z
      82: ifeq          95
      85: new           #83                 // class org/hl7/fhir/exceptions/FHIRException
      88: dup
      89: ldc           #89                 // String Cannot call addChild on a primitive type GraphDefinition.description
      91: invokespecial #85                 // Method org/hl7/fhir/exceptions/FHIRException."<init>":(Ljava/lang/String;)V
      94: athrow
      95: aload_1
      96: ldc           #60                 // String target
      98: invokevirtual #74                 // Method java/lang/String.equals:(Ljava/lang/Object;)Z
     101: ifeq          109
     104: aload_0
     105: invokevirtual #43                 // Method addTarget:()Lorg/hl7/fhir/dstu3/model/GraphDefinition$GraphDefinitionLinkTargetComponent;
     108: areturn
     109: aload_0
     110: aload_1
     111: invokespecial #90                 // Method org/hl7/fhir/dstu3/model/BackboneElement.addChild:(Ljava/lang/String;)Lorg/hl7/fhir/dstu3/model/Base;
     114: areturn

  public org.hl7.fhir.dstu3.model.GraphDefinition$GraphDefinitionLinkComponent copy();
    Code:
       0: new           #91                 // class org/hl7/fhir/dstu3/model/GraphDefinition$GraphDefinitionLinkComponent
       3: dup
       4: invokespecial #92                 // Method "<init>":()V
       7: astore_1
       8: aload_0
       9: aload_1
      10: invokevirtual #93                 // Method copyValues:(Lorg/hl7/fhir/dstu3/model/BackboneElement;)V
      13: aload_1
      14: aload_0
      15: getfield      #2                  // Field path:Lorg/hl7/fhir/dstu3/model/StringType;
      18: ifnonnull     25
      21: aconst_null
      22: goto          32
      25: aload_0
      26: getfield      #2                  // Field path:Lorg/hl7/fhir/dstu3/model/StringType;
      29: invokevirtual #94                 // Method org/hl7/fhir/dstu3/model/StringType.copy:()Lorg/hl7/fhir/dstu3/model/StringType;
      32: putfield      #2                  // Field path:Lorg/hl7/fhir/dstu3/model/StringType;
      35: aload_1
      36: aload_0
      37: getfield      #14                 // Field sliceName:Lorg/hl7/fhir/dstu3/model/StringType;
      40: ifnonnull     47
      43: aconst_null
      44: goto          54
      47: aload_0
      48: getfield      #14                 // Field sliceName:Lorg/hl7/fhir/dstu3/model/StringType;
      51: invokevirtual #94                 // Method org/hl7/fhir/dstu3/model/StringType.copy:()Lorg/hl7/fhir/dstu3/model/StringType;
      54: putfield      #14                 // Field sliceName:Lorg/hl7/fhir/dstu3/model/StringType;
      57: aload_1
      58: aload_0
      59: getfield      #17                 // Field min:Lorg/hl7/fhir/dstu3/model/IntegerType;
      62: ifnonnull     69
      65: aconst_null
      66: goto          76
      69: aload_0
      70: getfield      #17                 // Field min:Lorg/hl7/fhir/dstu3/model/IntegerType;
      73: invokevirtual #95                 // Method org/hl7/fhir/dstu3/model/IntegerType.copy:()Lorg/hl7/fhir/dstu3/model/IntegerType;
      76: putfield      #17                 // Field min:Lorg/hl7/fhir/dstu3/model/IntegerType;
      79: aload_1
      80: aload_0
      81: getfield      #27                 // Field max:Lorg/hl7/fhir/dstu3/model/StringType;
      84: ifnonnull     91
      87: aconst_null
      88: goto          98
      91: aload_0
      92: getfield      #27                 // Field max:Lorg/hl7/fhir/dstu3/model/StringType;
      95: invokevirtual #94                 // Method org/hl7/fhir/dstu3/model/StringType.copy:()Lorg/hl7/fhir/dstu3/model/StringType;
      98: putfield      #27                 // Field max:Lorg/hl7/fhir/dstu3/model/StringType;
     101: aload_1
     102: aload_0
     103: getfield      #29                 // Field description:Lorg/hl7/fhir/dstu3/model/StringType;
     106: ifnonnull     113
     109: aconst_null
     110: goto          120
     113: aload_0
     114: getfield      #29                 // Field description:Lorg/hl7/fhir/dstu3/model/StringType;
     117: invokevirtual #94                 // Method org/hl7/fhir/dstu3/model/StringType.copy:()Lorg/hl7/fhir/dstu3/model/StringType;
     120: putfield      #29                 // Field description:Lorg/hl7/fhir/dstu3/model/StringType;
     123: aload_0
     124: getfield      #31                 // Field target:Ljava/util/List;
     127: ifnull        187
     130: aload_1
     131: new           #32                 // class java/util/ArrayList
     134: dup
     135: invokespecial #33                 // Method java/util/ArrayList."<init>":()V
     138: putfield      #31                 // Field target:Ljava/util/List;
     141: aload_0
     142: getfield      #31                 // Field target:Ljava/util/List;
     145: invokeinterface #34,  1           // InterfaceMethod java/util/List.iterator:()Ljava/util/Iterator;
     150: astore_2
     151: aload_2
     152: invokeinterface #35,  1           // InterfaceMethod java/util/Iterator.hasNext:()Z
     157: ifeq          187
     160: aload_2
     161: invokeinterface #36,  1           // InterfaceMethod java/util/Iterator.next:()Ljava/lang/Object;
     166: checkcast     #37                 // class org/hl7/fhir/dstu3/model/GraphDefinition$GraphDefinitionLinkTargetComponent
     169: astore_3
     170: aload_1
     171: getfield      #31                 // Field target:Ljava/util/List;
     174: aload_3
     175: invokevirtual #96                 // Method org/hl7/fhir/dstu3/model/GraphDefinition$GraphDefinitionLinkTargetComponent.copy:()Lorg/hl7/fhir/dstu3/model/GraphDefinition$GraphDefinitionLinkTargetComponent;
     178: invokeinterface #40,  2           // InterfaceMethod java/util/List.add:(Ljava/lang/Object;)Z
     183: pop
     184: goto          151
     187: aload_1
     188: areturn

  public boolean equalsDeep(org.hl7.fhir.dstu3.model.Base);
    Code:
       0: aload_0
       1: aload_1
       2: invokespecial #97                 // Method org/hl7/fhir/dstu3/model/BackboneElement.equalsDeep:(Lorg/hl7/fhir/dstu3/model/Base;)Z
       5: ifne          10
       8: iconst_0
       9: ireturn
      10: aload_1
      11: instanceof    #91                 // class org/hl7/fhir/dstu3/model/GraphDefinition$GraphDefinitionLinkComponent
      14: ifne          19
      17: iconst_0
      18: ireturn
      19: aload_1
      20: checkcast     #91                 // class org/hl7/fhir/dstu3/model/GraphDefinition$GraphDefinitionLinkComponent
      23: astore_2
      24: aload_0
      25: getfield      #2                  // Field path:Lorg/hl7/fhir/dstu3/model/StringType;
      28: aload_2
      29: getfield      #2                  // Field path:Lorg/hl7/fhir/dstu3/model/StringType;
      32: iconst_1
      33: invokestatic  #98                 // Method compareDeep:(Lorg/hl7/fhir/dstu3/model/Base;Lorg/hl7/fhir/dstu3/model/Base;Z)Z
      36: ifeq          118
      39: aload_0
      40: getfield      #14                 // Field sliceName:Lorg/hl7/fhir/dstu3/model/StringType;
      43: aload_2
      44: getfield      #14                 // Field sliceName:Lorg/hl7/fhir/dstu3/model/StringType;
      47: iconst_1
      48: invokestatic  #98                 // Method compareDeep:(Lorg/hl7/fhir/dstu3/model/Base;Lorg/hl7/fhir/dstu3/model/Base;Z)Z
      51: ifeq          118
      54: aload_0
      55: getfield      #17                 // Field min:Lorg/hl7/fhir/dstu3/model/IntegerType;
      58: aload_2
      59: getfield      #17                 // Field min:Lorg/hl7/fhir/dstu3/model/IntegerType;
      62: iconst_1
      63: invokestatic  #98                 // Method compareDeep:(Lorg/hl7/fhir/dstu3/model/Base;Lorg/hl7/fhir/dstu3/model/Base;Z)Z
      66: ifeq          118
      69: aload_0
      70: getfield      #27                 // Field max:Lorg/hl7/fhir/dstu3/model/StringType;
      73: aload_2
      74: getfield      #27                 // Field max:Lorg/hl7/fhir/dstu3/model/StringType;
      77: iconst_1
      78: invokestatic  #98                 // Method compareDeep:(Lorg/hl7/fhir/dstu3/model/Base;Lorg/hl7/fhir/dstu3/model/Base;Z)Z
      81: ifeq          118
      84: aload_0
      85: getfield      #29                 // Field description:Lorg/hl7/fhir/dstu3/model/StringType;
      88: aload_2
      89: getfield      #29                 // Field description:Lorg/hl7/fhir/dstu3/model/StringType;
      92: iconst_1
      93: invokestatic  #98                 // Method compareDeep:(Lorg/hl7/fhir/dstu3/model/Base;Lorg/hl7/fhir/dstu3/model/Base;Z)Z
      96: ifeq          118
      99: aload_0
     100: getfield      #31                 // Field target:Ljava/util/List;
     103: aload_2
     104: getfield      #31                 // Field target:Ljava/util/List;
     107: iconst_1
     108: invokestatic  #99                 // Method compareDeep:(Ljava/util/List;Ljava/util/List;Z)Z
     111: ifeq          118
     114: iconst_1
     115: goto          119
     118: iconst_0
     119: ireturn

  public boolean equalsShallow(org.hl7.fhir.dstu3.model.Base);
    Code:
       0: aload_0
       1: aload_1
       2: invokespecial #100                // Method org/hl7/fhir/dstu3/model/BackboneElement.equalsShallow:(Lorg/hl7/fhir/dstu3/model/Base;)Z
       5: ifne          10
       8: iconst_0
       9: ireturn
      10: aload_1
      11: instanceof    #91                 // class org/hl7/fhir/dstu3/model/GraphDefinition$GraphDefinitionLinkComponent
      14: ifne          19
      17: iconst_0
      18: ireturn
      19: aload_1
      20: checkcast     #91                 // class org/hl7/fhir/dstu3/model/GraphDefinition$GraphDefinitionLinkComponent
      23: astore_2
      24: aload_0
      25: getfield      #2                  // Field path:Lorg/hl7/fhir/dstu3/model/StringType;
      28: aload_2
      29: getfield      #2                  // Field path:Lorg/hl7/fhir/dstu3/model/StringType;
      32: iconst_1
      33: invokestatic  #101                // Method compareValues:(Lorg/hl7/fhir/dstu3/model/PrimitiveType;Lorg/hl7/fhir/dstu3/model/PrimitiveType;Z)Z
      36: ifeq          103
      39: aload_0
      40: getfield      #14                 // Field sliceName:Lorg/hl7/fhir/dstu3/model/StringType;
      43: aload_2
      44: getfield      #14                 // Field sliceName:Lorg/hl7/fhir/dstu3/model/StringType;
      47: iconst_1
      48: invokestatic  #101                // Method compareValues:(Lorg/hl7/fhir/dstu3/model/PrimitiveType;Lorg/hl7/fhir/dstu3/model/PrimitiveType;Z)Z
      51: ifeq          103
      54: aload_0
      55: getfield      #17                 // Field min:Lorg/hl7/fhir/dstu3/model/IntegerType;
      58: aload_2
      59: getfield      #17                 // Field min:Lorg/hl7/fhir/dstu3/model/IntegerType;
      62: iconst_1
      63: invokestatic  #101                // Method compareValues:(Lorg/hl7/fhir/dstu3/model/PrimitiveType;Lorg/hl7/fhir/dstu3/model/PrimitiveType;Z)Z
      66: ifeq          103
      69: aload_0
      70: getfield      #27                 // Field max:Lorg/hl7/fhir/dstu3/model/StringType;
      73: aload_2
      74: getfield      #27                 // Field max:Lorg/hl7/fhir/dstu3/model/StringType;
      77: iconst_1
      78: invokestatic  #101                // Method compareValues:(Lorg/hl7/fhir/dstu3/model/PrimitiveType;Lorg/hl7/fhir/dstu3/model/PrimitiveType;Z)Z
      81: ifeq          103
      84: aload_0
      85: getfield      #29                 // Field description:Lorg/hl7/fhir/dstu3/model/StringType;
      88: aload_2
      89: getfield      #29                 // Field description:Lorg/hl7/fhir/dstu3/model/StringType;
      92: iconst_1
      93: invokestatic  #101                // Method compareValues:(Lorg/hl7/fhir/dstu3/model/PrimitiveType;Lorg/hl7/fhir/dstu3/model/PrimitiveType;Z)Z
      96: ifeq          103
      99: iconst_1
     100: goto          104
     103: iconst_0
     104: ireturn

  public boolean isEmpty();
    Code:
       0: aload_0
       1: invokespecial #102                // Method org/hl7/fhir/dstu3/model/BackboneElement.isEmpty:()Z
       4: ifeq          64
       7: bipush        6
       9: anewarray     #103                // class java/lang/Object
      12: dup
      13: iconst_0
      14: aload_0
      15: getfield      #2                  // Field path:Lorg/hl7/fhir/dstu3/model/StringType;
      18: aastore
      19: dup
      20: iconst_1
      21: aload_0
      22: getfield      #14                 // Field sliceName:Lorg/hl7/fhir/dstu3/model/StringType;
      25: aastore
      26: dup
      27: iconst_2
      28: aload_0
      29: getfield      #17                 // Field min:Lorg/hl7/fhir/dstu3/model/IntegerType;
      32: aastore
      33: dup
      34: iconst_3
      35: aload_0
      36: getfield      #27                 // Field max:Lorg/hl7/fhir/dstu3/model/StringType;
      39: aastore
      40: dup
      41: iconst_4
      42: aload_0
      43: getfield      #29                 // Field description:Lorg/hl7/fhir/dstu3/model/StringType;
      46: aastore
      47: dup
      48: iconst_5
      49: aload_0
      50: getfield      #31                 // Field target:Ljava/util/List;
      53: aastore
      54: invokestatic  #104                // Method ca/uhn/fhir/util/ElementUtil.isEmpty:([Ljava/lang/Object;)Z
      57: ifeq          64
      60: iconst_1
      61: goto          65
      64: iconst_0
      65: ireturn

  public java.lang.String fhirType();
    Code:
       0: ldc           #105                // String GraphDefinition.link
       2: areturn

  public org.hl7.fhir.dstu3.model.BackboneElement copy();
    Code:
       0: aload_0
       1: invokevirtual #106                // Method copy:()Lorg/hl7/fhir/dstu3/model/GraphDefinition$GraphDefinitionLinkComponent;
       4: areturn

  public org.hl7.fhir.dstu3.model.Element copy();
    Code:
       0: aload_0
       1: invokevirtual #106                // Method copy:()Lorg/hl7/fhir/dstu3/model/GraphDefinition$GraphDefinitionLinkComponent;
       4: areturn
}
