Compiled from "ImmunizationRecommendation.java"
public class org.hl7.fhir.dstu3.model.ImmunizationRecommendation$ImmunizationRecommendationRecommendationComponent extends org.hl7.fhir.dstu3.model.BackboneElement implements org.hl7.fhir.instance.model.api.IBaseBackboneElement {
  protected org.hl7.fhir.dstu3.model.DateTimeType date;

  protected org.hl7.fhir.dstu3.model.CodeableConcept vaccineCode;

  protected org.hl7.fhir.dstu3.model.CodeableConcept targetDisease;

  protected org.hl7.fhir.dstu3.model.PositiveIntType doseNumber;

  protected org.hl7.fhir.dstu3.model.CodeableConcept forecastStatus;

  protected java.util.List<org.hl7.fhir.dstu3.model.ImmunizationRecommendation$ImmunizationRecommendationRecommendationDateCriterionComponent> dateCriterion;

  protected org.hl7.fhir.dstu3.model.ImmunizationRecommendation$ImmunizationRecommendationRecommendationProtocolComponent protocol;

  protected java.util.List<org.hl7.fhir.dstu3.model.Reference> supportingImmunization;

  protected java.util.List<org.hl7.fhir.dstu3.model.Immunization> supportingImmunizationTarget;

  protected java.util.List<org.hl7.fhir.dstu3.model.Reference> supportingPatientInformation;

  protected java.util.List<org.hl7.fhir.dstu3.model.Resource> supportingPatientInformationTarget;

  private static final long serialVersionUID;

  public org.hl7.fhir.dstu3.model.ImmunizationRecommendation$ImmunizationRecommendationRecommendationComponent();
    Code:
       0: aload_0
       1: invokespecial #1                  // Method org/hl7/fhir/dstu3/model/BackboneElement."<init>":()V
       4: return

  public org.hl7.fhir.dstu3.model.ImmunizationRecommendation$ImmunizationRecommendationRecommendationComponent(org.hl7.fhir.dstu3.model.DateTimeType, org.hl7.fhir.dstu3.model.CodeableConcept);
    Code:
       0: aload_0
       1: invokespecial #1                  // Method org/hl7/fhir/dstu3/model/BackboneElement."<init>":()V
       4: aload_0
       5: aload_1
       6: putfield      #2                  // Field date:Lorg/hl7/fhir/dstu3/model/DateTimeType;
       9: aload_0
      10: aload_2
      11: putfield      #3                  // Field forecastStatus:Lorg/hl7/fhir/dstu3/model/CodeableConcept;
      14: return

  public org.hl7.fhir.dstu3.model.DateTimeType getDateElement();
    Code:
       0: aload_0
       1: getfield      #2                  // Field date:Lorg/hl7/fhir/dstu3/model/DateTimeType;
       4: ifnonnull     40
       7: invokestatic  #4                  // Method org/hl7/fhir/dstu3/model/Configuration.errorOnAutoCreate:()Z
      10: ifeq          23
      13: new           #5                  // class java/lang/Error
      16: dup
      17: ldc           #6                  // String Attempt to auto-create ImmunizationRecommendationRecommendationComponent.date
      19: invokespecial #7                  // Method java/lang/Error."<init>":(Ljava/lang/String;)V
      22: athrow
      23: invokestatic  #8                  // Method org/hl7/fhir/dstu3/model/Configuration.doAutoCreate:()Z
      26: ifeq          40
      29: aload_0
      30: new           #9                  // class org/hl7/fhir/dstu3/model/DateTimeType
      33: dup
      34: invokespecial #10                 // Method org/hl7/fhir/dstu3/model/DateTimeType."<init>":()V
      37: putfield      #2                  // Field date:Lorg/hl7/fhir/dstu3/model/DateTimeType;
      40: aload_0
      41: getfield      #2                  // Field date:Lorg/hl7/fhir/dstu3/model/DateTimeType;
      44: areturn

  public boolean hasDateElement();
    Code:
       0: aload_0
       1: getfield      #2                  // Field date:Lorg/hl7/fhir/dstu3/model/DateTimeType;
       4: ifnull        21
       7: aload_0
       8: getfield      #2                  // Field date:Lorg/hl7/fhir/dstu3/model/DateTimeType;
      11: invokevirtual #11                 // Method org/hl7/fhir/dstu3/model/DateTimeType.isEmpty:()Z
      14: ifne          21
      17: iconst_1
      18: goto          22
      21: iconst_0
      22: ireturn

  public boolean hasDate();
    Code:
       0: aload_0
       1: getfield      #2                  // Field date:Lorg/hl7/fhir/dstu3/model/DateTimeType;
       4: ifnull        21
       7: aload_0
       8: getfield      #2                  // Field date:Lorg/hl7/fhir/dstu3/model/DateTimeType;
      11: invokevirtual #11                 // Method org/hl7/fhir/dstu3/model/DateTimeType.isEmpty:()Z
      14: ifne          21
      17: iconst_1
      18: goto          22
      21: iconst_0
      22: ireturn

  public org.hl7.fhir.dstu3.model.ImmunizationRecommendation$ImmunizationRecommendationRecommendationComponent setDateElement(org.hl7.fhir.dstu3.model.DateTimeType);
    Code:
       0: aload_0
       1: aload_1
       2: putfield      #2                  // Field date:Lorg/hl7/fhir/dstu3/model/DateTimeType;
       5: aload_0
       6: areturn

  public java.util.Date getDate();
    Code:
       0: aload_0
       1: getfield      #2                  // Field date:Lorg/hl7/fhir/dstu3/model/DateTimeType;
       4: ifnonnull     11
       7: aconst_null
       8: goto          21
      11: aload_0
      12: getfield      #2                  // Field date:Lorg/hl7/fhir/dstu3/model/DateTimeType;
      15: invokevirtual #12                 // Method org/hl7/fhir/dstu3/model/DateTimeType.getValue:()Ljava/lang/Object;
      18: checkcast     #13                 // class java/util/Date
      21: areturn

  public org.hl7.fhir.dstu3.model.ImmunizationRecommendation$ImmunizationRecommendationRecommendationComponent setDate(java.util.Date);
    Code:
       0: aload_0
       1: getfield      #2                  // Field date:Lorg/hl7/fhir/dstu3/model/DateTimeType;
       4: ifnonnull     18
       7: aload_0
       8: new           #9                  // class org/hl7/fhir/dstu3/model/DateTimeType
      11: dup
      12: invokespecial #10                 // Method org/hl7/fhir/dstu3/model/DateTimeType."<init>":()V
      15: putfield      #2                  // Field date:Lorg/hl7/fhir/dstu3/model/DateTimeType;
      18: aload_0
      19: getfield      #2                  // Field date:Lorg/hl7/fhir/dstu3/model/DateTimeType;
      22: aload_1
      23: invokevirtual #14                 // Method org/hl7/fhir/dstu3/model/DateTimeType.setValue:(Ljava/util/Date;)Lorg/hl7/fhir/dstu3/model/BaseDateTimeType;
      26: pop
      27: aload_0
      28: areturn

  public org.hl7.fhir.dstu3.model.CodeableConcept getVaccineCode();
    Code:
       0: aload_0
       1: getfield      #15                 // Field vaccineCode:Lorg/hl7/fhir/dstu3/model/CodeableConcept;
       4: ifnonnull     40
       7: invokestatic  #4                  // Method org/hl7/fhir/dstu3/model/Configuration.errorOnAutoCreate:()Z
      10: ifeq          23
      13: new           #5                  // class java/lang/Error
      16: dup
      17: ldc           #16                 // String Attempt to auto-create ImmunizationRecommendationRecommendationComponent.vaccineCode
      19: invokespecial #7                  // Method java/lang/Error."<init>":(Ljava/lang/String;)V
      22: athrow
      23: invokestatic  #8                  // Method org/hl7/fhir/dstu3/model/Configuration.doAutoCreate:()Z
      26: ifeq          40
      29: aload_0
      30: new           #17                 // class org/hl7/fhir/dstu3/model/CodeableConcept
      33: dup
      34: invokespecial #18                 // Method org/hl7/fhir/dstu3/model/CodeableConcept."<init>":()V
      37: putfield      #15                 // Field vaccineCode:Lorg/hl7/fhir/dstu3/model/CodeableConcept;
      40: aload_0
      41: getfield      #15                 // Field vaccineCode:Lorg/hl7/fhir/dstu3/model/CodeableConcept;
      44: areturn

  public boolean hasVaccineCode();
    Code:
       0: aload_0
       1: getfield      #15                 // Field vaccineCode:Lorg/hl7/fhir/dstu3/model/CodeableConcept;
       4: ifnull        21
       7: aload_0
       8: getfield      #15                 // Field vaccineCode:Lorg/hl7/fhir/dstu3/model/CodeableConcept;
      11: invokevirtual #19                 // Method org/hl7/fhir/dstu3/model/CodeableConcept.isEmpty:()Z
      14: ifne          21
      17: iconst_1
      18: goto          22
      21: iconst_0
      22: ireturn

  public org.hl7.fhir.dstu3.model.ImmunizationRecommendation$ImmunizationRecommendationRecommendationComponent setVaccineCode(org.hl7.fhir.dstu3.model.CodeableConcept);
    Code:
       0: aload_0
       1: aload_1
       2: putfield      #15                 // Field vaccineCode:Lorg/hl7/fhir/dstu3/model/CodeableConcept;
       5: aload_0
       6: areturn

  public org.hl7.fhir.dstu3.model.CodeableConcept getTargetDisease();
    Code:
       0: aload_0
       1: getfield      #20                 // Field targetDisease:Lorg/hl7/fhir/dstu3/model/CodeableConcept;
       4: ifnonnull     40
       7: invokestatic  #4                  // Method org/hl7/fhir/dstu3/model/Configuration.errorOnAutoCreate:()Z
      10: ifeq          23
      13: new           #5                  // class java/lang/Error
      16: dup
      17: ldc           #21                 // String Attempt to auto-create ImmunizationRecommendationRecommendationComponent.targetDisease
      19: invokespecial #7                  // Method java/lang/Error."<init>":(Ljava/lang/String;)V
      22: athrow
      23: invokestatic  #8                  // Method org/hl7/fhir/dstu3/model/Configuration.doAutoCreate:()Z
      26: ifeq          40
      29: aload_0
      30: new           #17                 // class org/hl7/fhir/dstu3/model/CodeableConcept
      33: dup
      34: invokespecial #18                 // Method org/hl7/fhir/dstu3/model/CodeableConcept."<init>":()V
      37: putfield      #20                 // Field targetDisease:Lorg/hl7/fhir/dstu3/model/CodeableConcept;
      40: aload_0
      41: getfield      #20                 // Field targetDisease:Lorg/hl7/fhir/dstu3/model/CodeableConcept;
      44: areturn

  public boolean hasTargetDisease();
    Code:
       0: aload_0
       1: getfield      #20                 // Field targetDisease:Lorg/hl7/fhir/dstu3/model/CodeableConcept;
       4: ifnull        21
       7: aload_0
       8: getfield      #20                 // Field targetDisease:Lorg/hl7/fhir/dstu3/model/CodeableConcept;
      11: invokevirtual #19                 // Method org/hl7/fhir/dstu3/model/CodeableConcept.isEmpty:()Z
      14: ifne          21
      17: iconst_1
      18: goto          22
      21: iconst_0
      22: ireturn

  public org.hl7.fhir.dstu3.model.ImmunizationRecommendation$ImmunizationRecommendationRecommendationComponent setTargetDisease(org.hl7.fhir.dstu3.model.CodeableConcept);
    Code:
       0: aload_0
       1: aload_1
       2: putfield      #20                 // Field targetDisease:Lorg/hl7/fhir/dstu3/model/CodeableConcept;
       5: aload_0
       6: areturn

  public org.hl7.fhir.dstu3.model.PositiveIntType getDoseNumberElement();
    Code:
       0: aload_0
       1: getfield      #22                 // Field doseNumber:Lorg/hl7/fhir/dstu3/model/PositiveIntType;
       4: ifnonnull     40
       7: invokestatic  #4                  // Method org/hl7/fhir/dstu3/model/Configuration.errorOnAutoCreate:()Z
      10: ifeq          23
      13: new           #5                  // class java/lang/Error
      16: dup
      17: ldc           #23                 // String Attempt to auto-create ImmunizationRecommendationRecommendationComponent.doseNumber
      19: invokespecial #7                  // Method java/lang/Error."<init>":(Ljava/lang/String;)V
      22: athrow
      23: invokestatic  #8                  // Method org/hl7/fhir/dstu3/model/Configuration.doAutoCreate:()Z
      26: ifeq          40
      29: aload_0
      30: new           #24                 // class org/hl7/fhir/dstu3/model/PositiveIntType
      33: dup
      34: invokespecial #25                 // Method org/hl7/fhir/dstu3/model/PositiveIntType."<init>":()V
      37: putfield      #22                 // Field doseNumber:Lorg/hl7/fhir/dstu3/model/PositiveIntType;
      40: aload_0
      41: getfield      #22                 // Field doseNumber:Lorg/hl7/fhir/dstu3/model/PositiveIntType;
      44: areturn

  public boolean hasDoseNumberElement();
    Code:
       0: aload_0
       1: getfield      #22                 // Field doseNumber:Lorg/hl7/fhir/dstu3/model/PositiveIntType;
       4: ifnull        21
       7: aload_0
       8: getfield      #22                 // Field doseNumber:Lorg/hl7/fhir/dstu3/model/PositiveIntType;
      11: invokevirtual #26                 // Method org/hl7/fhir/dstu3/model/PositiveIntType.isEmpty:()Z
      14: ifne          21
      17: iconst_1
      18: goto          22
      21: iconst_0
      22: ireturn

  public boolean hasDoseNumber();
    Code:
       0: aload_0
       1: getfield      #22                 // Field doseNumber:Lorg/hl7/fhir/dstu3/model/PositiveIntType;
       4: ifnull        21
       7: aload_0
       8: getfield      #22                 // Field doseNumber:Lorg/hl7/fhir/dstu3/model/PositiveIntType;
      11: invokevirtual #26                 // Method org/hl7/fhir/dstu3/model/PositiveIntType.isEmpty:()Z
      14: ifne          21
      17: iconst_1
      18: goto          22
      21: iconst_0
      22: ireturn

  public org.hl7.fhir.dstu3.model.ImmunizationRecommendation$ImmunizationRecommendationRecommendationComponent setDoseNumberElement(org.hl7.fhir.dstu3.model.PositiveIntType);
    Code:
       0: aload_0
       1: aload_1
       2: putfield      #22                 // Field doseNumber:Lorg/hl7/fhir/dstu3/model/PositiveIntType;
       5: aload_0
       6: areturn

  public int getDoseNumber();
    Code:
       0: aload_0
       1: getfield      #22                 // Field doseNumber:Lorg/hl7/fhir/dstu3/model/PositiveIntType;
       4: ifnull        17
       7: aload_0
       8: getfield      #22                 // Field doseNumber:Lorg/hl7/fhir/dstu3/model/PositiveIntType;
      11: invokevirtual #26                 // Method org/hl7/fhir/dstu3/model/PositiveIntType.isEmpty:()Z
      14: ifeq          21
      17: iconst_0
      18: goto          34
      21: aload_0
      22: getfield      #22                 // Field doseNumber:Lorg/hl7/fhir/dstu3/model/PositiveIntType;
      25: invokevirtual #27                 // Method org/hl7/fhir/dstu3/model/PositiveIntType.getValue:()Ljava/lang/Object;
      28: checkcast     #28                 // class java/lang/Integer
      31: invokevirtual #29                 // Method java/lang/Integer.intValue:()I
      34: ireturn

  public org.hl7.fhir.dstu3.model.ImmunizationRecommendation$ImmunizationRecommendationRecommendationComponent setDoseNumber(int);
    Code:
       0: aload_0
       1: getfield      #22                 // Field doseNumber:Lorg/hl7/fhir/dstu3/model/PositiveIntType;
       4: ifnonnull     18
       7: aload_0
       8: new           #24                 // class org/hl7/fhir/dstu3/model/PositiveIntType
      11: dup
      12: invokespecial #25                 // Method org/hl7/fhir/dstu3/model/PositiveIntType."<init>":()V
      15: putfield      #22                 // Field doseNumber:Lorg/hl7/fhir/dstu3/model/PositiveIntType;
      18: aload_0
      19: getfield      #22                 // Field doseNumber:Lorg/hl7/fhir/dstu3/model/PositiveIntType;
      22: iload_1
      23: invokestatic  #30                 // Method java/lang/Integer.valueOf:(I)Ljava/lang/Integer;
      26: invokevirtual #31                 // Method org/hl7/fhir/dstu3/model/PositiveIntType.setValue:(Ljava/lang/Object;)Lorg/hl7/fhir/dstu3/model/PrimitiveType;
      29: pop
      30: aload_0
      31: areturn

  public org.hl7.fhir.dstu3.model.CodeableConcept getForecastStatus();
    Code:
       0: aload_0
       1: getfield      #3                  // Field forecastStatus:Lorg/hl7/fhir/dstu3/model/CodeableConcept;
       4: ifnonnull     40
       7: invokestatic  #4                  // Method org/hl7/fhir/dstu3/model/Configuration.errorOnAutoCreate:()Z
      10: ifeq          23
      13: new           #5                  // class java/lang/Error
      16: dup
      17: ldc           #32                 // String Attempt to auto-create ImmunizationRecommendationRecommendationComponent.forecastStatus
      19: invokespecial #7                  // Method java/lang/Error."<init>":(Ljava/lang/String;)V
      22: athrow
      23: invokestatic  #8                  // Method org/hl7/fhir/dstu3/model/Configuration.doAutoCreate:()Z
      26: ifeq          40
      29: aload_0
      30: new           #17                 // class org/hl7/fhir/dstu3/model/CodeableConcept
      33: dup
      34: invokespecial #18                 // Method org/hl7/fhir/dstu3/model/CodeableConcept."<init>":()V
      37: putfield      #3                  // Field forecastStatus:Lorg/hl7/fhir/dstu3/model/CodeableConcept;
      40: aload_0
      41: getfield      #3                  // Field forecastStatus:Lorg/hl7/fhir/dstu3/model/CodeableConcept;
      44: areturn

  public boolean hasForecastStatus();
    Code:
       0: aload_0
       1: getfield      #3                  // Field forecastStatus:Lorg/hl7/fhir/dstu3/model/CodeableConcept;
       4: ifnull        21
       7: aload_0
       8: getfield      #3                  // Field forecastStatus:Lorg/hl7/fhir/dstu3/model/CodeableConcept;
      11: invokevirtual #19                 // Method org/hl7/fhir/dstu3/model/CodeableConcept.isEmpty:()Z
      14: ifne          21
      17: iconst_1
      18: goto          22
      21: iconst_0
      22: ireturn

  public org.hl7.fhir.dstu3.model.ImmunizationRecommendation$ImmunizationRecommendationRecommendationComponent setForecastStatus(org.hl7.fhir.dstu3.model.CodeableConcept);
    Code:
       0: aload_0
       1: aload_1
       2: putfield      #3                  // Field forecastStatus:Lorg/hl7/fhir/dstu3/model/CodeableConcept;
       5: aload_0
       6: areturn

  public java.util.List<org.hl7.fhir.dstu3.model.ImmunizationRecommendation$ImmunizationRecommendationRecommendationDateCriterionComponent> getDateCriterion();
    Code:
       0: aload_0
       1: getfield      #33                 // Field dateCriterion:Ljava/util/List;
       4: ifnonnull     18
       7: aload_0
       8: new           #34                 // class java/util/ArrayList
      11: dup
      12: invokespecial #35                 // Method java/util/ArrayList."<init>":()V
      15: putfield      #33                 // Field dateCriterion:Ljava/util/List;
      18: aload_0
      19: getfield      #33                 // Field dateCriterion:Ljava/util/List;
      22: areturn

  public org.hl7.fhir.dstu3.model.ImmunizationRecommendation$ImmunizationRecommendationRecommendationComponent setDateCriterion(java.util.List<org.hl7.fhir.dstu3.model.ImmunizationRecommendation$ImmunizationRecommendationRecommendationDateCriterionComponent>);
    Code:
       0: aload_0
       1: aload_1
       2: putfield      #33                 // Field dateCriterion:Ljava/util/List;
       5: aload_0
       6: areturn

  public boolean hasDateCriterion();
    Code:
       0: aload_0
       1: getfield      #33                 // Field dateCriterion:Ljava/util/List;
       4: ifnonnull     9
       7: iconst_0
       8: ireturn
       9: aload_0
      10: getfield      #33                 // Field dateCriterion:Ljava/util/List;
      13: invokeinterface #36,  1           // InterfaceMethod java/util/List.iterator:()Ljava/util/Iterator;
      18: astore_1
      19: aload_1
      20: invokeinterface #37,  1           // InterfaceMethod java/util/Iterator.hasNext:()Z
      25: ifeq          50
      28: aload_1
      29: invokeinterface #38,  1           // InterfaceMethod java/util/Iterator.next:()Ljava/lang/Object;
      34: checkcast     #39                 // class org/hl7/fhir/dstu3/model/ImmunizationRecommendation$ImmunizationRecommendationRecommendationDateCriterionComponent
      37: astore_2
      38: aload_2
      39: invokevirtual #40                 // Method org/hl7/fhir/dstu3/model/ImmunizationRecommendation$ImmunizationRecommendationRecommendationDateCriterionComponent.isEmpty:()Z
      42: ifne          47
      45: iconst_1
      46: ireturn
      47: goto          19
      50: iconst_0
      51: ireturn

  public org.hl7.fhir.dstu3.model.ImmunizationRecommendation$ImmunizationRecommendationRecommendationDateCriterionComponent addDateCriterion();
    Code:
       0: new           #39                 // class org/hl7/fhir/dstu3/model/ImmunizationRecommendation$ImmunizationRecommendationRecommendationDateCriterionComponent
       3: dup
       4: invokespecial #41                 // Method org/hl7/fhir/dstu3/model/ImmunizationRecommendation$ImmunizationRecommendationRecommendationDateCriterionComponent."<init>":()V
       7: astore_1
       8: aload_0
       9: getfield      #33                 // Field dateCriterion:Ljava/util/List;
      12: ifnonnull     26
      15: aload_0
      16: new           #34                 // class java/util/ArrayList
      19: dup
      20: invokespecial #35                 // Method java/util/ArrayList."<init>":()V
      23: putfield      #33                 // Field dateCriterion:Ljava/util/List;
      26: aload_0
      27: getfield      #33                 // Field dateCriterion:Ljava/util/List;
      30: aload_1
      31: invokeinterface #42,  2           // InterfaceMethod java/util/List.add:(Ljava/lang/Object;)Z
      36: pop
      37: aload_1
      38: areturn

  public org.hl7.fhir.dstu3.model.ImmunizationRecommendation$ImmunizationRecommendationRecommendationComponent addDateCriterion(org.hl7.fhir.dstu3.model.ImmunizationRecommendation$ImmunizationRecommendationRecommendationDateCriterionComponent);
    Code:
       0: aload_1
       1: ifnonnull     6
       4: aload_0
       5: areturn
       6: aload_0
       7: getfield      #33                 // Field dateCriterion:Ljava/util/List;
      10: ifnonnull     24
      13: aload_0
      14: new           #34                 // class java/util/ArrayList
      17: dup
      18: invokespecial #35                 // Method java/util/ArrayList."<init>":()V
      21: putfield      #33                 // Field dateCriterion:Ljava/util/List;
      24: aload_0
      25: getfield      #33                 // Field dateCriterion:Ljava/util/List;
      28: aload_1
      29: invokeinterface #42,  2           // InterfaceMethod java/util/List.add:(Ljava/lang/Object;)Z
      34: pop
      35: aload_0
      36: areturn

  public org.hl7.fhir.dstu3.model.ImmunizationRecommendation$ImmunizationRecommendationRecommendationDateCriterionComponent getDateCriterionFirstRep();
    Code:
       0: aload_0
       1: invokevirtual #43                 // Method getDateCriterion:()Ljava/util/List;
       4: invokeinterface #44,  1           // InterfaceMethod java/util/List.isEmpty:()Z
       9: ifeq          17
      12: aload_0
      13: invokevirtual #45                 // Method addDateCriterion:()Lorg/hl7/fhir/dstu3/model/ImmunizationRecommendation$ImmunizationRecommendationRecommendationDateCriterionComponent;
      16: pop
      17: aload_0
      18: invokevirtual #43                 // Method getDateCriterion:()Ljava/util/List;
      21: iconst_0
      22: invokeinterface #46,  2           // InterfaceMethod java/util/List.get:(I)Ljava/lang/Object;
      27: checkcast     #39                 // class org/hl7/fhir/dstu3/model/ImmunizationRecommendation$ImmunizationRecommendationRecommendationDateCriterionComponent
      30: areturn

  public org.hl7.fhir.dstu3.model.ImmunizationRecommendation$ImmunizationRecommendationRecommendationProtocolComponent getProtocol();
    Code:
       0: aload_0
       1: getfield      #47                 // Field protocol:Lorg/hl7/fhir/dstu3/model/ImmunizationRecommendation$ImmunizationRecommendationRecommendationProtocolComponent;
       4: ifnonnull     40
       7: invokestatic  #4                  // Method org/hl7/fhir/dstu3/model/Configuration.errorOnAutoCreate:()Z
      10: ifeq          23
      13: new           #5                  // class java/lang/Error
      16: dup
      17: ldc           #48                 // String Attempt to auto-create ImmunizationRecommendationRecommendationComponent.protocol
      19: invokespecial #7                  // Method java/lang/Error."<init>":(Ljava/lang/String;)V
      22: athrow
      23: invokestatic  #8                  // Method org/hl7/fhir/dstu3/model/Configuration.doAutoCreate:()Z
      26: ifeq          40
      29: aload_0
      30: new           #49                 // class org/hl7/fhir/dstu3/model/ImmunizationRecommendation$ImmunizationRecommendationRecommendationProtocolComponent
      33: dup
      34: invokespecial #50                 // Method org/hl7/fhir/dstu3/model/ImmunizationRecommendation$ImmunizationRecommendationRecommendationProtocolComponent."<init>":()V
      37: putfield      #47                 // Field protocol:Lorg/hl7/fhir/dstu3/model/ImmunizationRecommendation$ImmunizationRecommendationRecommendationProtocolComponent;
      40: aload_0
      41: getfield      #47                 // Field protocol:Lorg/hl7/fhir/dstu3/model/ImmunizationRecommendation$ImmunizationRecommendationRecommendationProtocolComponent;
      44: areturn

  public boolean hasProtocol();
    Code:
       0: aload_0
       1: getfield      #47                 // Field protocol:Lorg/hl7/fhir/dstu3/model/ImmunizationRecommendation$ImmunizationRecommendationRecommendationProtocolComponent;
       4: ifnull        21
       7: aload_0
       8: getfield      #47                 // Field protocol:Lorg/hl7/fhir/dstu3/model/ImmunizationRecommendation$ImmunizationRecommendationRecommendationProtocolComponent;
      11: invokevirtual #51                 // Method org/hl7/fhir/dstu3/model/ImmunizationRecommendation$ImmunizationRecommendationRecommendationProtocolComponent.isEmpty:()Z
      14: ifne          21
      17: iconst_1
      18: goto          22
      21: iconst_0
      22: ireturn

  public org.hl7.fhir.dstu3.model.ImmunizationRecommendation$ImmunizationRecommendationRecommendationComponent setProtocol(org.hl7.fhir.dstu3.model.ImmunizationRecommendation$ImmunizationRecommendationRecommendationProtocolComponent);
    Code:
       0: aload_0
       1: aload_1
       2: putfield      #47                 // Field protocol:Lorg/hl7/fhir/dstu3/model/ImmunizationRecommendation$ImmunizationRecommendationRecommendationProtocolComponent;
       5: aload_0
       6: areturn

  public java.util.List<org.hl7.fhir.dstu3.model.Reference> getSupportingImmunization();
    Code:
       0: aload_0
       1: getfield      #52                 // Field supportingImmunization:Ljava/util/List;
       4: ifnonnull     18
       7: aload_0
       8: new           #34                 // class java/util/ArrayList
      11: dup
      12: invokespecial #35                 // Method java/util/ArrayList."<init>":()V
      15: putfield      #52                 // Field supportingImmunization:Ljava/util/List;
      18: aload_0
      19: getfield      #52                 // Field supportingImmunization:Ljava/util/List;
      22: areturn

  public org.hl7.fhir.dstu3.model.ImmunizationRecommendation$ImmunizationRecommendationRecommendationComponent setSupportingImmunization(java.util.List<org.hl7.fhir.dstu3.model.Reference>);
    Code:
       0: aload_0
       1: aload_1
       2: putfield      #52                 // Field supportingImmunization:Ljava/util/List;
       5: aload_0
       6: areturn

  public boolean hasSupportingImmunization();
    Code:
       0: aload_0
       1: getfield      #52                 // Field supportingImmunization:Ljava/util/List;
       4: ifnonnull     9
       7: iconst_0
       8: ireturn
       9: aload_0
      10: getfield      #52                 // Field supportingImmunization:Ljava/util/List;
      13: invokeinterface #36,  1           // InterfaceMethod java/util/List.iterator:()Ljava/util/Iterator;
      18: astore_1
      19: aload_1
      20: invokeinterface #37,  1           // InterfaceMethod java/util/Iterator.hasNext:()Z
      25: ifeq          50
      28: aload_1
      29: invokeinterface #38,  1           // InterfaceMethod java/util/Iterator.next:()Ljava/lang/Object;
      34: checkcast     #53                 // class org/hl7/fhir/dstu3/model/Reference
      37: astore_2
      38: aload_2
      39: invokevirtual #54                 // Method org/hl7/fhir/dstu3/model/Reference.isEmpty:()Z
      42: ifne          47
      45: iconst_1
      46: ireturn
      47: goto          19
      50: iconst_0
      51: ireturn

  public org.hl7.fhir.dstu3.model.Reference addSupportingImmunization();
    Code:
       0: new           #53                 // class org/hl7/fhir/dstu3/model/Reference
       3: dup
       4: invokespecial #55                 // Method org/hl7/fhir/dstu3/model/Reference."<init>":()V
       7: astore_1
       8: aload_0
       9: getfield      #52                 // Field supportingImmunization:Ljava/util/List;
      12: ifnonnull     26
      15: aload_0
      16: new           #34                 // class java/util/ArrayList
      19: dup
      20: invokespecial #35                 // Method java/util/ArrayList."<init>":()V
      23: putfield      #52                 // Field supportingImmunization:Ljava/util/List;
      26: aload_0
      27: getfield      #52                 // Field supportingImmunization:Ljava/util/List;
      30: aload_1
      31: invokeinterface #42,  2           // InterfaceMethod java/util/List.add:(Ljava/lang/Object;)Z
      36: pop
      37: aload_1
      38: areturn

  public org.hl7.fhir.dstu3.model.ImmunizationRecommendation$ImmunizationRecommendationRecommendationComponent addSupportingImmunization(org.hl7.fhir.dstu3.model.Reference);
    Code:
       0: aload_1
       1: ifnonnull     6
       4: aload_0
       5: areturn
       6: aload_0
       7: getfield      #52                 // Field supportingImmunization:Ljava/util/List;
      10: ifnonnull     24
      13: aload_0
      14: new           #34                 // class java/util/ArrayList
      17: dup
      18: invokespecial #35                 // Method java/util/ArrayList."<init>":()V
      21: putfield      #52                 // Field supportingImmunization:Ljava/util/List;
      24: aload_0
      25: getfield      #52                 // Field supportingImmunization:Ljava/util/List;
      28: aload_1
      29: invokeinterface #42,  2           // InterfaceMethod java/util/List.add:(Ljava/lang/Object;)Z
      34: pop
      35: aload_0
      36: areturn

  public org.hl7.fhir.dstu3.model.Reference getSupportingImmunizationFirstRep();
    Code:
       0: aload_0
       1: invokevirtual #56                 // Method getSupportingImmunization:()Ljava/util/List;
       4: invokeinterface #44,  1           // InterfaceMethod java/util/List.isEmpty:()Z
       9: ifeq          17
      12: aload_0
      13: invokevirtual #57                 // Method addSupportingImmunization:()Lorg/hl7/fhir/dstu3/model/Reference;
      16: pop
      17: aload_0
      18: invokevirtual #56                 // Method getSupportingImmunization:()Ljava/util/List;
      21: iconst_0
      22: invokeinterface #46,  2           // InterfaceMethod java/util/List.get:(I)Ljava/lang/Object;
      27: checkcast     #53                 // class org/hl7/fhir/dstu3/model/Reference
      30: areturn

  public java.util.List<org.hl7.fhir.dstu3.model.Immunization> getSupportingImmunizationTarget();
    Code:
       0: aload_0
       1: getfield      #58                 // Field supportingImmunizationTarget:Ljava/util/List;
       4: ifnonnull     18
       7: aload_0
       8: new           #34                 // class java/util/ArrayList
      11: dup
      12: invokespecial #35                 // Method java/util/ArrayList."<init>":()V
      15: putfield      #58                 // Field supportingImmunizationTarget:Ljava/util/List;
      18: aload_0
      19: getfield      #58                 // Field supportingImmunizationTarget:Ljava/util/List;
      22: areturn

  public org.hl7.fhir.dstu3.model.Immunization addSupportingImmunizationTarget();
    Code:
       0: new           #59                 // class org/hl7/fhir/dstu3/model/Immunization
       3: dup
       4: invokespecial #60                 // Method org/hl7/fhir/dstu3/model/Immunization."<init>":()V
       7: astore_1
       8: aload_0
       9: getfield      #58                 // Field supportingImmunizationTarget:Ljava/util/List;
      12: ifnonnull     26
      15: aload_0
      16: new           #34                 // class java/util/ArrayList
      19: dup
      20: invokespecial #35                 // Method java/util/ArrayList."<init>":()V
      23: putfield      #58                 // Field supportingImmunizationTarget:Ljava/util/List;
      26: aload_0
      27: getfield      #58                 // Field supportingImmunizationTarget:Ljava/util/List;
      30: aload_1
      31: invokeinterface #42,  2           // InterfaceMethod java/util/List.add:(Ljava/lang/Object;)Z
      36: pop
      37: aload_1
      38: areturn

  public java.util.List<org.hl7.fhir.dstu3.model.Reference> getSupportingPatientInformation();
    Code:
       0: aload_0
       1: getfield      #61                 // Field supportingPatientInformation:Ljava/util/List;
       4: ifnonnull     18
       7: aload_0
       8: new           #34                 // class java/util/ArrayList
      11: dup
      12: invokespecial #35                 // Method java/util/ArrayList."<init>":()V
      15: putfield      #61                 // Field supportingPatientInformation:Ljava/util/List;
      18: aload_0
      19: getfield      #61                 // Field supportingPatientInformation:Ljava/util/List;
      22: areturn

  public org.hl7.fhir.dstu3.model.ImmunizationRecommendation$ImmunizationRecommendationRecommendationComponent setSupportingPatientInformation(java.util.List<org.hl7.fhir.dstu3.model.Reference>);
    Code:
       0: aload_0
       1: aload_1
       2: putfield      #61                 // Field supportingPatientInformation:Ljava/util/List;
       5: aload_0
       6: areturn

  public boolean hasSupportingPatientInformation();
    Code:
       0: aload_0
       1: getfield      #61                 // Field supportingPatientInformation:Ljava/util/List;
       4: ifnonnull     9
       7: iconst_0
       8: ireturn
       9: aload_0
      10: getfield      #61                 // Field supportingPatientInformation:Ljava/util/List;
      13: invokeinterface #36,  1           // InterfaceMethod java/util/List.iterator:()Ljava/util/Iterator;
      18: astore_1
      19: aload_1
      20: invokeinterface #37,  1           // InterfaceMethod java/util/Iterator.hasNext:()Z
      25: ifeq          50
      28: aload_1
      29: invokeinterface #38,  1           // InterfaceMethod java/util/Iterator.next:()Ljava/lang/Object;
      34: checkcast     #53                 // class org/hl7/fhir/dstu3/model/Reference
      37: astore_2
      38: aload_2
      39: invokevirtual #54                 // Method org/hl7/fhir/dstu3/model/Reference.isEmpty:()Z
      42: ifne          47
      45: iconst_1
      46: ireturn
      47: goto          19
      50: iconst_0
      51: ireturn

  public org.hl7.fhir.dstu3.model.Reference addSupportingPatientInformation();
    Code:
       0: new           #53                 // class org/hl7/fhir/dstu3/model/Reference
       3: dup
       4: invokespecial #55                 // Method org/hl7/fhir/dstu3/model/Reference."<init>":()V
       7: astore_1
       8: aload_0
       9: getfield      #61                 // Field supportingPatientInformation:Ljava/util/List;
      12: ifnonnull     26
      15: aload_0
      16: new           #34                 // class java/util/ArrayList
      19: dup
      20: invokespecial #35                 // Method java/util/ArrayList."<init>":()V
      23: putfield      #61                 // Field supportingPatientInformation:Ljava/util/List;
      26: aload_0
      27: getfield      #61                 // Field supportingPatientInformation:Ljava/util/List;
      30: aload_1
      31: invokeinterface #42,  2           // InterfaceMethod java/util/List.add:(Ljava/lang/Object;)Z
      36: pop
      37: aload_1
      38: areturn

  public org.hl7.fhir.dstu3.model.ImmunizationRecommendation$ImmunizationRecommendationRecommendationComponent addSupportingPatientInformation(org.hl7.fhir.dstu3.model.Reference);
    Code:
       0: aload_1
       1: ifnonnull     6
       4: aload_0
       5: areturn
       6: aload_0
       7: getfield      #61                 // Field supportingPatientInformation:Ljava/util/List;
      10: ifnonnull     24
      13: aload_0
      14: new           #34                 // class java/util/ArrayList
      17: dup
      18: invokespecial #35                 // Method java/util/ArrayList."<init>":()V
      21: putfield      #61                 // Field supportingPatientInformation:Ljava/util/List;
      24: aload_0
      25: getfield      #61                 // Field supportingPatientInformation:Ljava/util/List;
      28: aload_1
      29: invokeinterface #42,  2           // InterfaceMethod java/util/List.add:(Ljava/lang/Object;)Z
      34: pop
      35: aload_0
      36: areturn

  public org.hl7.fhir.dstu3.model.Reference getSupportingPatientInformationFirstRep();
    Code:
       0: aload_0
       1: invokevirtual #62                 // Method getSupportingPatientInformation:()Ljava/util/List;
       4: invokeinterface #44,  1           // InterfaceMethod java/util/List.isEmpty:()Z
       9: ifeq          17
      12: aload_0
      13: invokevirtual #63                 // Method addSupportingPatientInformation:()Lorg/hl7/fhir/dstu3/model/Reference;
      16: pop
      17: aload_0
      18: invokevirtual #62                 // Method getSupportingPatientInformation:()Ljava/util/List;
      21: iconst_0
      22: invokeinterface #46,  2           // InterfaceMethod java/util/List.get:(I)Ljava/lang/Object;
      27: checkcast     #53                 // class org/hl7/fhir/dstu3/model/Reference
      30: areturn

  public java.util.List<org.hl7.fhir.dstu3.model.Resource> getSupportingPatientInformationTarget();
    Code:
       0: aload_0
       1: getfield      #64                 // Field supportingPatientInformationTarget:Ljava/util/List;
       4: ifnonnull     18
       7: aload_0
       8: new           #34                 // class java/util/ArrayList
      11: dup
      12: invokespecial #35                 // Method java/util/ArrayList."<init>":()V
      15: putfield      #64                 // Field supportingPatientInformationTarget:Ljava/util/List;
      18: aload_0
      19: getfield      #64                 // Field supportingPatientInformationTarget:Ljava/util/List;
      22: areturn

  protected void listChildren(java.util.List<org.hl7.fhir.dstu3.model.Property>);
    Code:
       0: aload_0
       1: aload_1
       2: invokespecial #65                 // Method org/hl7/fhir/dstu3/model/BackboneElement.listChildren:(Ljava/util/List;)V
       5: aload_1
       6: new           #66                 // class org/hl7/fhir/dstu3/model/Property
       9: dup
      10: ldc           #67                 // String date
      12: ldc           #68                 // String dateTime
      14: ldc           #69                 // String The date the immunization recommendation was created.
      16: iconst_0
      17: iconst_1
      18: aload_0
      19: getfield      #2                  // Field date:Lorg/hl7/fhir/dstu3/model/DateTimeType;
      22: invokespecial #70                 // Method org/hl7/fhir/dstu3/model/Property."<init>":(Ljava/lang/String;Ljava/lang/String;Ljava/lang/String;IILorg/hl7/fhir/dstu3/model/Base;)V
      25: invokeinterface #42,  2           // InterfaceMethod java/util/List.add:(Ljava/lang/Object;)Z
      30: pop
      31: aload_1
      32: new           #66                 // class org/hl7/fhir/dstu3/model/Property
      35: dup
      36: ldc           #71                 // String vaccineCode
      38: ldc           #72                 // String CodeableConcept
      40: ldc           #73                 // String Vaccine that pertains to the recommendation.
      42: iconst_0
      43: iconst_1
      44: aload_0
      45: getfield      #15                 // Field vaccineCode:Lorg/hl7/fhir/dstu3/model/CodeableConcept;
      48: invokespecial #70                 // Method org/hl7/fhir/dstu3/model/Property."<init>":(Ljava/lang/String;Ljava/lang/String;Ljava/lang/String;IILorg/hl7/fhir/dstu3/model/Base;)V
      51: invokeinterface #42,  2           // InterfaceMethod java/util/List.add:(Ljava/lang/Object;)Z
      56: pop
      57: aload_1
      58: new           #66                 // class org/hl7/fhir/dstu3/model/Property
      61: dup
      62: ldc           #74                 // String targetDisease
      64: ldc           #72                 // String CodeableConcept
      66: ldc           #75                 // String The targeted disease for the recommendation.
      68: iconst_0
      69: iconst_1
      70: aload_0
      71: getfield      #20                 // Field targetDisease:Lorg/hl7/fhir/dstu3/model/CodeableConcept;
      74: invokespecial #70                 // Method org/hl7/fhir/dstu3/model/Property."<init>":(Ljava/lang/String;Ljava/lang/String;Ljava/lang/String;IILorg/hl7/fhir/dstu3/model/Base;)V
      77: invokeinterface #42,  2           // InterfaceMethod java/util/List.add:(Ljava/lang/Object;)Z
      82: pop
      83: aload_1
      84: new           #66                 // class org/hl7/fhir/dstu3/model/Property
      87: dup
      88: ldc           #76                 // String doseNumber
      90: ldc           #77                 // String positiveInt
      92: ldc           #78                 // String The next recommended dose number (e.g. dose 2 is the next recommended dose).
      94: iconst_0
      95: iconst_1
      96: aload_0
      97: getfield      #22                 // Field doseNumber:Lorg/hl7/fhir/dstu3/model/PositiveIntType;
     100: invokespecial #70                 // Method org/hl7/fhir/dstu3/model/Property."<init>":(Ljava/lang/String;Ljava/lang/String;Ljava/lang/String;IILorg/hl7/fhir/dstu3/model/Base;)V
     103: invokeinterface #42,  2           // InterfaceMethod java/util/List.add:(Ljava/lang/Object;)Z
     108: pop
     109: aload_1
     110: new           #66                 // class org/hl7/fhir/dstu3/model/Property
     113: dup
     114: ldc           #79                 // String forecastStatus
     116: ldc           #72                 // String CodeableConcept
     118: ldc           #80                 // String Vaccine administration status.
     120: iconst_0
     121: iconst_1
     122: aload_0
     123: getfield      #3                  // Field forecastStatus:Lorg/hl7/fhir/dstu3/model/CodeableConcept;
     126: invokespecial #70                 // Method org/hl7/fhir/dstu3/model/Property."<init>":(Ljava/lang/String;Ljava/lang/String;Ljava/lang/String;IILorg/hl7/fhir/dstu3/model/Base;)V
     129: invokeinterface #42,  2           // InterfaceMethod java/util/List.add:(Ljava/lang/Object;)Z
     134: pop
     135: aload_1
     136: new           #66                 // class org/hl7/fhir/dstu3/model/Property
     139: dup
     140: ldc           #81                 // String dateCriterion
     142: ldc           #82                 // String
     144: ldc           #83                 // String Vaccine date recommendations.  For example, earliest date to administer, latest date to administer, etc.
     146: iconst_0
     147: ldc           #84                 // int 2147483647
     149: aload_0
     150: getfield      #33                 // Field dateCriterion:Ljava/util/List;
     153: invokespecial #85                 // Method org/hl7/fhir/dstu3/model/Property."<init>":(Ljava/lang/String;Ljava/lang/String;Ljava/lang/String;IILjava/util/List;)V
     156: invokeinterface #42,  2           // InterfaceMethod java/util/List.add:(Ljava/lang/Object;)Z
     161: pop
     162: aload_1
     163: new           #66                 // class org/hl7/fhir/dstu3/model/Property
     166: dup
     167: ldc           #86                 // String protocol
     169: ldc           #82                 // String
     171: ldc           #87                 // String Contains information about the protocol under which the vaccine was administered.
     173: iconst_0
     174: iconst_1
     175: aload_0
     176: getfield      #47                 // Field protocol:Lorg/hl7/fhir/dstu3/model/ImmunizationRecommendation$ImmunizationRecommendationRecommendationProtocolComponent;
     179: invokespecial #70                 // Method org/hl7/fhir/dstu3/model/Property."<init>":(Ljava/lang/String;Ljava/lang/String;Ljava/lang/String;IILorg/hl7/fhir/dstu3/model/Base;)V
     182: invokeinterface #42,  2           // InterfaceMethod java/util/List.add:(Ljava/lang/Object;)Z
     187: pop
     188: aload_1
     189: new           #66                 // class org/hl7/fhir/dstu3/model/Property
     192: dup
     193: ldc           #88                 // String supportingImmunization
     195: ldc           #89                 // String Reference(Immunization)
     197: ldc           #90                 // String Immunization event history that supports the status and recommendation.
     199: iconst_0
     200: ldc           #84                 // int 2147483647
     202: aload_0
     203: getfield      #52                 // Field supportingImmunization:Ljava/util/List;
     206: invokespecial #85                 // Method org/hl7/fhir/dstu3/model/Property."<init>":(Ljava/lang/String;Ljava/lang/String;Ljava/lang/String;IILjava/util/List;)V
     209: invokeinterface #42,  2           // InterfaceMethod java/util/List.add:(Ljava/lang/Object;)Z
     214: pop
     215: aload_1
     216: new           #66                 // class org/hl7/fhir/dstu3/model/Property
     219: dup
     220: ldc           #91                 // String supportingPatientInformation
     222: ldc           #92                 // String Reference(Observation|AllergyIntolerance)
     224: ldc           #93                 // String Patient Information that supports the status and recommendation.  This includes patient observations, adverse reactions and allergy/intolerance information.
     226: iconst_0
     227: ldc           #84                 // int 2147483647
     229: aload_0
     230: getfield      #61                 // Field supportingPatientInformation:Ljava/util/List;
     233: invokespecial #85                 // Method org/hl7/fhir/dstu3/model/Property."<init>":(Ljava/lang/String;Ljava/lang/String;Ljava/lang/String;IILjava/util/List;)V
     236: invokeinterface #42,  2           // InterfaceMethod java/util/List.add:(Ljava/lang/Object;)Z
     241: pop
     242: return

  public org.hl7.fhir.dstu3.model.Property getNamedProperty(int, java.lang.String, boolean) throws org.hl7.fhir.exceptions.FHIRException;
    Code:
       0: iload_1
       1: lookupswitch  { // 9
           -1234160646: 246
            -989163880: 205
            -887709242: 144
            -319593813: 124
               3076014: 84
             664556354: 104
            1171592021: 225
            1904598477: 164
            2087518867: 184
               default: 267
          }
      84: new           #66                 // class org/hl7/fhir/dstu3/model/Property
      87: dup
      88: ldc           #67                 // String date
      90: ldc           #68                 // String dateTime
      92: ldc           #69                 // String The date the immunization recommendation was created.
      94: iconst_0
      95: iconst_1
      96: aload_0
      97: getfield      #2                  // Field date:Lorg/hl7/fhir/dstu3/model/DateTimeType;
     100: invokespecial #70                 // Method org/hl7/fhir/dstu3/model/Property."<init>":(Ljava/lang/String;Ljava/lang/String;Ljava/lang/String;IILorg/hl7/fhir/dstu3/model/Base;)V
     103: areturn
     104: new           #66                 // class org/hl7/fhir/dstu3/model/Property
     107: dup
     108: ldc           #71                 // String vaccineCode
     110: ldc           #72                 // String CodeableConcept
     112: ldc           #73                 // String Vaccine that pertains to the recommendation.
     114: iconst_0
     115: iconst_1
     116: aload_0
     117: getfield      #15                 // Field vaccineCode:Lorg/hl7/fhir/dstu3/model/CodeableConcept;
     120: invokespecial #70                 // Method org/hl7/fhir/dstu3/model/Property."<init>":(Ljava/lang/String;Ljava/lang/String;Ljava/lang/String;IILorg/hl7/fhir/dstu3/model/Base;)V
     123: areturn
     124: new           #66                 // class org/hl7/fhir/dstu3/model/Property
     127: dup
     128: ldc           #74                 // String targetDisease
     130: ldc           #72                 // String CodeableConcept
     132: ldc           #75                 // String The targeted disease for the recommendation.
     134: iconst_0
     135: iconst_1
     136: aload_0
     137: getfield      #20                 // Field targetDisease:Lorg/hl7/fhir/dstu3/model/CodeableConcept;
     140: invokespecial #70                 // Method org/hl7/fhir/dstu3/model/Property."<init>":(Ljava/lang/String;Ljava/lang/String;Ljava/lang/String;IILorg/hl7/fhir/dstu3/model/Base;)V
     143: areturn
     144: new           #66                 // class org/hl7/fhir/dstu3/model/Property
     147: dup
     148: ldc           #76                 // String doseNumber
     150: ldc           #77                 // String positiveInt
     152: ldc           #78                 // String The next recommended dose number (e.g. dose 2 is the next recommended dose).
     154: iconst_0
     155: iconst_1
     156: aload_0
     157: getfield      #22                 // Field doseNumber:Lorg/hl7/fhir/dstu3/model/PositiveIntType;
     160: invokespecial #70                 // Method org/hl7/fhir/dstu3/model/Property."<init>":(Ljava/lang/String;Ljava/lang/String;Ljava/lang/String;IILorg/hl7/fhir/dstu3/model/Base;)V
     163: areturn
     164: new           #66                 // class org/hl7/fhir/dstu3/model/Property
     167: dup
     168: ldc           #79                 // String forecastStatus
     170: ldc           #72                 // String CodeableConcept
     172: ldc           #80                 // String Vaccine administration status.
     174: iconst_0
     175: iconst_1
     176: aload_0
     177: getfield      #3                  // Field forecastStatus:Lorg/hl7/fhir/dstu3/model/CodeableConcept;
     180: invokespecial #70                 // Method org/hl7/fhir/dstu3/model/Property."<init>":(Ljava/lang/String;Ljava/lang/String;Ljava/lang/String;IILorg/hl7/fhir/dstu3/model/Base;)V
     183: areturn
     184: new           #66                 // class org/hl7/fhir/dstu3/model/Property
     187: dup
     188: ldc           #81                 // String dateCriterion
     190: ldc           #82                 // String
     192: ldc           #83                 // String Vaccine date recommendations.  For example, earliest date to administer, latest date to administer, etc.
     194: iconst_0
     195: ldc           #84                 // int 2147483647
     197: aload_0
     198: getfield      #33                 // Field dateCriterion:Ljava/util/List;
     201: invokespecial #85                 // Method org/hl7/fhir/dstu3/model/Property."<init>":(Ljava/lang/String;Ljava/lang/String;Ljava/lang/String;IILjava/util/List;)V
     204: areturn
     205: new           #66                 // class org/hl7/fhir/dstu3/model/Property
     208: dup
     209: ldc           #86                 // String protocol
     211: ldc           #82                 // String
     213: ldc           #87                 // String Contains information about the protocol under which the vaccine was administered.
     215: iconst_0
     216: iconst_1
     217: aload_0
     218: getfield      #47                 // Field protocol:Lorg/hl7/fhir/dstu3/model/ImmunizationRecommendation$ImmunizationRecommendationRecommendationProtocolComponent;
     221: invokespecial #70                 // Method org/hl7/fhir/dstu3/model/Property."<init>":(Ljava/lang/String;Ljava/lang/String;Ljava/lang/String;IILorg/hl7/fhir/dstu3/model/Base;)V
     224: areturn
     225: new           #66                 // class org/hl7/fhir/dstu3/model/Property
     228: dup
     229: ldc           #88                 // String supportingImmunization
     231: ldc           #89                 // String Reference(Immunization)
     233: ldc           #90                 // String Immunization event history that supports the status and recommendation.
     235: iconst_0
     236: ldc           #84                 // int 2147483647
     238: aload_0
     239: getfield      #52                 // Field supportingImmunization:Ljava/util/List;
     242: invokespecial #85                 // Method org/hl7/fhir/dstu3/model/Property."<init>":(Ljava/lang/String;Ljava/lang/String;Ljava/lang/String;IILjava/util/List;)V
     245: areturn
     246: new           #66                 // class org/hl7/fhir/dstu3/model/Property
     249: dup
     250: ldc           #91                 // String supportingPatientInformation
     252: ldc           #92                 // String Reference(Observation|AllergyIntolerance)
     254: ldc           #93                 // String Patient Information that supports the status and recommendation.  This includes patient observations, adverse reactions and allergy/intolerance information.
     256: iconst_0
     257: ldc           #84                 // int 2147483647
     259: aload_0
     260: getfield      #61                 // Field supportingPatientInformation:Ljava/util/List;
     263: invokespecial #85                 // Method org/hl7/fhir/dstu3/model/Property."<init>":(Ljava/lang/String;Ljava/lang/String;Ljava/lang/String;IILjava/util/List;)V
     266: areturn
     267: aload_0
     268: iload_1
     269: aload_2
     270: iload_3
     271: invokespecial #94                 // Method org/hl7/fhir/dstu3/model/BackboneElement.getNamedProperty:(ILjava/lang/String;Z)Lorg/hl7/fhir/dstu3/model/Property;
     274: areturn

  public org.hl7.fhir.dstu3.model.Base[] getProperty(int, java.lang.String, boolean) throws org.hl7.fhir.exceptions.FHIRException;
    Code:
       0: iload_1
       1: lookupswitch  { // 9
           -1234160646: 318
            -989163880: 253
            -887709242: 162
            -319593813: 136
               3076014: 84
             664556354: 110
            1171592021: 279
            1904598477: 188
            2087518867: 214
               default: 357
          }
      84: aload_0
      85: getfield      #2                  // Field date:Lorg/hl7/fhir/dstu3/model/DateTimeType;
      88: ifnonnull     98
      91: iconst_0
      92: anewarray     #95                 // class org/hl7/fhir/dstu3/model/Base
      95: goto          109
      98: iconst_1
      99: anewarray     #95                 // class org/hl7/fhir/dstu3/model/Base
     102: dup
     103: iconst_0
     104: aload_0
     105: getfield      #2                  // Field date:Lorg/hl7/fhir/dstu3/model/DateTimeType;
     108: aastore
     109: areturn
     110: aload_0
     111: getfield      #15                 // Field vaccineCode:Lorg/hl7/fhir/dstu3/model/CodeableConcept;
     114: ifnonnull     124
     117: iconst_0
     118: anewarray     #95                 // class org/hl7/fhir/dstu3/model/Base
     121: goto          135
     124: iconst_1
     125: anewarray     #95                 // class org/hl7/fhir/dstu3/model/Base
     128: dup
     129: iconst_0
     130: aload_0
     131: getfield      #15                 // Field vaccineCode:Lorg/hl7/fhir/dstu3/model/CodeableConcept;
     134: aastore
     135: areturn
     136: aload_0
     137: getfield      #20                 // Field targetDisease:Lorg/hl7/fhir/dstu3/model/CodeableConcept;
     140: ifnonnull     150
     143: iconst_0
     144: anewarray     #95                 // class org/hl7/fhir/dstu3/model/Base
     147: goto          161
     150: iconst_1
     151: anewarray     #95                 // class org/hl7/fhir/dstu3/model/Base
     154: dup
     155: iconst_0
     156: aload_0
     157: getfield      #20                 // Field targetDisease:Lorg/hl7/fhir/dstu3/model/CodeableConcept;
     160: aastore
     161: areturn
     162: aload_0
     163: getfield      #22                 // Field doseNumber:Lorg/hl7/fhir/dstu3/model/PositiveIntType;
     166: ifnonnull     176
     169: iconst_0
     170: anewarray     #95                 // class org/hl7/fhir/dstu3/model/Base
     173: goto          187
     176: iconst_1
     177: anewarray     #95                 // class org/hl7/fhir/dstu3/model/Base
     180: dup
     181: iconst_0
     182: aload_0
     183: getfield      #22                 // Field doseNumber:Lorg/hl7/fhir/dstu3/model/PositiveIntType;
     186: aastore
     187: areturn
     188: aload_0
     189: getfield      #3                  // Field forecastStatus:Lorg/hl7/fhir/dstu3/model/CodeableConcept;
     192: ifnonnull     202
     195: iconst_0
     196: anewarray     #95                 // class org/hl7/fhir/dstu3/model/Base
     199: goto          213
     202: iconst_1
     203: anewarray     #95                 // class org/hl7/fhir/dstu3/model/Base
     206: dup
     207: iconst_0
     208: aload_0
     209: getfield      #3                  // Field forecastStatus:Lorg/hl7/fhir/dstu3/model/CodeableConcept;
     212: aastore
     213: areturn
     214: aload_0
     215: getfield      #33                 // Field dateCriterion:Ljava/util/List;
     218: ifnonnull     228
     221: iconst_0
     222: anewarray     #95                 // class org/hl7/fhir/dstu3/model/Base
     225: goto          252
     228: aload_0
     229: getfield      #33                 // Field dateCriterion:Ljava/util/List;
     232: aload_0
     233: getfield      #33                 // Field dateCriterion:Ljava/util/List;
     236: invokeinterface #96,  1           // InterfaceMethod java/util/List.size:()I
     241: anewarray     #95                 // class org/hl7/fhir/dstu3/model/Base
     244: invokeinterface #97,  2           // InterfaceMethod java/util/List.toArray:([Ljava/lang/Object;)[Ljava/lang/Object;
     249: checkcast     #98                 // class "[Lorg/hl7/fhir/dstu3/model/Base;"
     252: areturn
     253: aload_0
     254: getfield      #47                 // Field protocol:Lorg/hl7/fhir/dstu3/model/ImmunizationRecommendation$ImmunizationRecommendationRecommendationProtocolComponent;
     257: ifnonnull     267
     260: iconst_0
     261: anewarray     #95                 // class org/hl7/fhir/dstu3/model/Base
     264: goto          278
     267: iconst_1
     268: anewarray     #95                 // class org/hl7/fhir/dstu3/model/Base
     271: dup
     272: iconst_0
     273: aload_0
     274: getfield      #47                 // Field protocol:Lorg/hl7/fhir/dstu3/model/ImmunizationRecommendation$ImmunizationRecommendationRecommendationProtocolComponent;
     277: aastore
     278: areturn
     279: aload_0
     280: getfield      #52                 // Field supportingImmunization:Ljava/util/List;
     283: ifnonnull     293
     286: iconst_0
     287: anewarray     #95                 // class org/hl7/fhir/dstu3/model/Base
     290: goto          317
     293: aload_0
     294: getfield      #52                 // Field supportingImmunization:Ljava/util/List;
     297: aload_0
     298: getfield      #52                 // Field supportingImmunization:Ljava/util/List;
     301: invokeinterface #96,  1           // InterfaceMethod java/util/List.size:()I
     306: anewarray     #95                 // class org/hl7/fhir/dstu3/model/Base
     309: invokeinterface #97,  2           // InterfaceMethod java/util/List.toArray:([Ljava/lang/Object;)[Ljava/lang/Object;
     314: checkcast     #98                 // class "[Lorg/hl7/fhir/dstu3/model/Base;"
     317: areturn
     318: aload_0
     319: getfield      #61                 // Field supportingPatientInformation:Ljava/util/List;
     322: ifnonnull     332
     325: iconst_0
     326: anewarray     #95                 // class org/hl7/fhir/dstu3/model/Base
     329: goto          356
     332: aload_0
     333: getfield      #61                 // Field supportingPatientInformation:Ljava/util/List;
     336: aload_0
     337: getfield      #61                 // Field supportingPatientInformation:Ljava/util/List;
     340: invokeinterface #96,  1           // InterfaceMethod java/util/List.size:()I
     345: anewarray     #95                 // class org/hl7/fhir/dstu3/model/Base
     348: invokeinterface #97,  2           // InterfaceMethod java/util/List.toArray:([Ljava/lang/Object;)[Ljava/lang/Object;
     353: checkcast     #98                 // class "[Lorg/hl7/fhir/dstu3/model/Base;"
     356: areturn
     357: aload_0
     358: iload_1
     359: aload_2
     360: iload_3
     361: invokespecial #99                 // Method org/hl7/fhir/dstu3/model/BackboneElement.getProperty:(ILjava/lang/String;Z)[Lorg/hl7/fhir/dstu3/model/Base;
     364: areturn

  public org.hl7.fhir.dstu3.model.Base setProperty(int, java.lang.String, org.hl7.fhir.dstu3.model.Base) throws org.hl7.fhir.exceptions.FHIRException;
    Code:
       0: iload_1
       1: lookupswitch  { // 9
           -1234160646: 182
            -989163880: 155
            -887709242: 117
            -319593813: 106
               3076014: 84
             664556354: 95
            1171592021: 165
            1904598477: 128
            2087518867: 139
               default: 199
          }
      84: aload_0
      85: aload_0
      86: aload_3
      87: invokevirtual #100                // Method castToDateTime:(Lorg/hl7/fhir/dstu3/model/Base;)Lorg/hl7/fhir/dstu3/model/DateTimeType;
      90: putfield      #2                  // Field date:Lorg/hl7/fhir/dstu3/model/DateTimeType;
      93: aload_3
      94: areturn
      95: aload_0
      96: aload_0
      97: aload_3
      98: invokevirtual #101                // Method castToCodeableConcept:(Lorg/hl7/fhir/dstu3/model/Base;)Lorg/hl7/fhir/dstu3/model/CodeableConcept;
     101: putfield      #15                 // Field vaccineCode:Lorg/hl7/fhir/dstu3/model/CodeableConcept;
     104: aload_3
     105: areturn
     106: aload_0
     107: aload_0
     108: aload_3
     109: invokevirtual #101                // Method castToCodeableConcept:(Lorg/hl7/fhir/dstu3/model/Base;)Lorg/hl7/fhir/dstu3/model/CodeableConcept;
     112: putfield      #20                 // Field targetDisease:Lorg/hl7/fhir/dstu3/model/CodeableConcept;
     115: aload_3
     116: areturn
     117: aload_0
     118: aload_0
     119: aload_3
     120: invokevirtual #102                // Method castToPositiveInt:(Lorg/hl7/fhir/dstu3/model/Base;)Lorg/hl7/fhir/dstu3/model/PositiveIntType;
     123: putfield      #22                 // Field doseNumber:Lorg/hl7/fhir/dstu3/model/PositiveIntType;
     126: aload_3
     127: areturn
     128: aload_0
     129: aload_0
     130: aload_3
     131: invokevirtual #101                // Method castToCodeableConcept:(Lorg/hl7/fhir/dstu3/model/Base;)Lorg/hl7/fhir/dstu3/model/CodeableConcept;
     134: putfield      #3                  // Field forecastStatus:Lorg/hl7/fhir/dstu3/model/CodeableConcept;
     137: aload_3
     138: areturn
     139: aload_0
     140: invokevirtual #43                 // Method getDateCriterion:()Ljava/util/List;
     143: aload_3
     144: checkcast     #39                 // class org/hl7/fhir/dstu3/model/ImmunizationRecommendation$ImmunizationRecommendationRecommendationDateCriterionComponent
     147: invokeinterface #42,  2           // InterfaceMethod java/util/List.add:(Ljava/lang/Object;)Z
     152: pop
     153: aload_3
     154: areturn
     155: aload_0
     156: aload_3
     157: checkcast     #49                 // class org/hl7/fhir/dstu3/model/ImmunizationRecommendation$ImmunizationRecommendationRecommendationProtocolComponent
     160: putfield      #47                 // Field protocol:Lorg/hl7/fhir/dstu3/model/ImmunizationRecommendation$ImmunizationRecommendationRecommendationProtocolComponent;
     163: aload_3
     164: areturn
     165: aload_0
     166: invokevirtual #56                 // Method getSupportingImmunization:()Ljava/util/List;
     169: aload_0
     170: aload_3
     171: invokevirtual #103                // Method castToReference:(Lorg/hl7/fhir/dstu3/model/Base;)Lorg/hl7/fhir/dstu3/model/Reference;
     174: invokeinterface #42,  2           // InterfaceMethod java/util/List.add:(Ljava/lang/Object;)Z
     179: pop
     180: aload_3
     181: areturn
     182: aload_0
     183: invokevirtual #62                 // Method getSupportingPatientInformation:()Ljava/util/List;
     186: aload_0
     187: aload_3
     188: invokevirtual #103                // Method castToReference:(Lorg/hl7/fhir/dstu3/model/Base;)Lorg/hl7/fhir/dstu3/model/Reference;
     191: invokeinterface #42,  2           // InterfaceMethod java/util/List.add:(Ljava/lang/Object;)Z
     196: pop
     197: aload_3
     198: areturn
     199: aload_0
     200: iload_1
     201: aload_2
     202: aload_3
     203: invokespecial #104                // Method org/hl7/fhir/dstu3/model/BackboneElement.setProperty:(ILjava/lang/String;Lorg/hl7/fhir/dstu3/model/Base;)Lorg/hl7/fhir/dstu3/model/Base;
     206: areturn

  public org.hl7.fhir.dstu3.model.Base setProperty(java.lang.String, org.hl7.fhir.dstu3.model.Base) throws org.hl7.fhir.exceptions.FHIRException;
    Code:
       0: aload_1
       1: ldc           #67                 // String date
       3: invokevirtual #105                // Method java/lang/String.equals:(Ljava/lang/Object;)Z
       6: ifeq          21
       9: aload_0
      10: aload_0
      11: aload_2
      12: invokevirtual #100                // Method castToDateTime:(Lorg/hl7/fhir/dstu3/model/Base;)Lorg/hl7/fhir/dstu3/model/DateTimeType;
      15: putfield      #2                  // Field date:Lorg/hl7/fhir/dstu3/model/DateTimeType;
      18: goto          212
      21: aload_1
      22: ldc           #71                 // String vaccineCode
      24: invokevirtual #105                // Method java/lang/String.equals:(Ljava/lang/Object;)Z
      27: ifeq          42
      30: aload_0
      31: aload_0
      32: aload_2
      33: invokevirtual #101                // Method castToCodeableConcept:(Lorg/hl7/fhir/dstu3/model/Base;)Lorg/hl7/fhir/dstu3/model/CodeableConcept;
      36: putfield      #15                 // Field vaccineCode:Lorg/hl7/fhir/dstu3/model/CodeableConcept;
      39: goto          212
      42: aload_1
      43: ldc           #74                 // String targetDisease
      45: invokevirtual #105                // Method java/lang/String.equals:(Ljava/lang/Object;)Z
      48: ifeq          63
      51: aload_0
      52: aload_0
      53: aload_2
      54: invokevirtual #101                // Method castToCodeableConcept:(Lorg/hl7/fhir/dstu3/model/Base;)Lorg/hl7/fhir/dstu3/model/CodeableConcept;
      57: putfield      #20                 // Field targetDisease:Lorg/hl7/fhir/dstu3/model/CodeableConcept;
      60: goto          212
      63: aload_1
      64: ldc           #76                 // String doseNumber
      66: invokevirtual #105                // Method java/lang/String.equals:(Ljava/lang/Object;)Z
      69: ifeq          84
      72: aload_0
      73: aload_0
      74: aload_2
      75: invokevirtual #102                // Method castToPositiveInt:(Lorg/hl7/fhir/dstu3/model/Base;)Lorg/hl7/fhir/dstu3/model/PositiveIntType;
      78: putfield      #22                 // Field doseNumber:Lorg/hl7/fhir/dstu3/model/PositiveIntType;
      81: goto          212
      84: aload_1
      85: ldc           #79                 // String forecastStatus
      87: invokevirtual #105                // Method java/lang/String.equals:(Ljava/lang/Object;)Z
      90: ifeq          105
      93: aload_0
      94: aload_0
      95: aload_2
      96: invokevirtual #101                // Method castToCodeableConcept:(Lorg/hl7/fhir/dstu3/model/Base;)Lorg/hl7/fhir/dstu3/model/CodeableConcept;
      99: putfield      #3                  // Field forecastStatus:Lorg/hl7/fhir/dstu3/model/CodeableConcept;
     102: goto          212
     105: aload_1
     106: ldc           #81                 // String dateCriterion
     108: invokevirtual #105                // Method java/lang/String.equals:(Ljava/lang/Object;)Z
     111: ifeq          131
     114: aload_0
     115: invokevirtual #43                 // Method getDateCriterion:()Ljava/util/List;
     118: aload_2
     119: checkcast     #39                 // class org/hl7/fhir/dstu3/model/ImmunizationRecommendation$ImmunizationRecommendationRecommendationDateCriterionComponent
     122: invokeinterface #42,  2           // InterfaceMethod java/util/List.add:(Ljava/lang/Object;)Z
     127: pop
     128: goto          212
     131: aload_1
     132: ldc           #86                 // String protocol
     134: invokevirtual #105                // Method java/lang/String.equals:(Ljava/lang/Object;)Z
     137: ifeq          151
     140: aload_0
     141: aload_2
     142: checkcast     #49                 // class org/hl7/fhir/dstu3/model/ImmunizationRecommendation$ImmunizationRecommendationRecommendationProtocolComponent
     145: putfield      #47                 // Field protocol:Lorg/hl7/fhir/dstu3/model/ImmunizationRecommendation$ImmunizationRecommendationRecommendationProtocolComponent;
     148: goto          212
     151: aload_1
     152: ldc           #88                 // String supportingImmunization
     154: invokevirtual #105                // Method java/lang/String.equals:(Ljava/lang/Object;)Z
     157: ifeq          178
     160: aload_0
     161: invokevirtual #56                 // Method getSupportingImmunization:()Ljava/util/List;
     164: aload_0
     165: aload_2
     166: invokevirtual #103                // Method castToReference:(Lorg/hl7/fhir/dstu3/model/Base;)Lorg/hl7/fhir/dstu3/model/Reference;
     169: invokeinterface #42,  2           // InterfaceMethod java/util/List.add:(Ljava/lang/Object;)Z
     174: pop
     175: goto          212
     178: aload_1
     179: ldc           #91                 // String supportingPatientInformation
     181: invokevirtual #105                // Method java/lang/String.equals:(Ljava/lang/Object;)Z
     184: ifeq          205
     187: aload_0
     188: invokevirtual #62                 // Method getSupportingPatientInformation:()Ljava/util/List;
     191: aload_0
     192: aload_2
     193: invokevirtual #103                // Method castToReference:(Lorg/hl7/fhir/dstu3/model/Base;)Lorg/hl7/fhir/dstu3/model/Reference;
     196: invokeinterface #42,  2           // InterfaceMethod java/util/List.add:(Ljava/lang/Object;)Z
     201: pop
     202: goto          212
     205: aload_0
     206: aload_1
     207: aload_2
     208: invokespecial #106                // Method org/hl7/fhir/dstu3/model/BackboneElement.setProperty:(Ljava/lang/String;Lorg/hl7/fhir/dstu3/model/Base;)Lorg/hl7/fhir/dstu3/model/Base;
     211: areturn
     212: aload_2
     213: areturn

  public org.hl7.fhir.dstu3.model.Base makeProperty(int, java.lang.String) throws org.hl7.fhir.exceptions.FHIRException;
    Code:
       0: iload_1
       1: lookupswitch  { // 9
           -1234160646: 124
            -989163880: 114
            -887709242: 99
            -319593813: 94
               3076014: 84
             664556354: 89
            1171592021: 119
            1904598477: 104
            2087518867: 109
               default: 129
          }
      84: aload_0
      85: invokevirtual #107                // Method getDateElement:()Lorg/hl7/fhir/dstu3/model/DateTimeType;
      88: areturn
      89: aload_0
      90: invokevirtual #108                // Method getVaccineCode:()Lorg/hl7/fhir/dstu3/model/CodeableConcept;
      93: areturn
      94: aload_0
      95: invokevirtual #109                // Method getTargetDisease:()Lorg/hl7/fhir/dstu3/model/CodeableConcept;
      98: areturn
      99: aload_0
     100: invokevirtual #110                // Method getDoseNumberElement:()Lorg/hl7/fhir/dstu3/model/PositiveIntType;
     103: areturn
     104: aload_0
     105: invokevirtual #111                // Method getForecastStatus:()Lorg/hl7/fhir/dstu3/model/CodeableConcept;
     108: areturn
     109: aload_0
     110: invokevirtual #45                 // Method addDateCriterion:()Lorg/hl7/fhir/dstu3/model/ImmunizationRecommendation$ImmunizationRecommendationRecommendationDateCriterionComponent;
     113: areturn
     114: aload_0
     115: invokevirtual #112                // Method getProtocol:()Lorg/hl7/fhir/dstu3/model/ImmunizationRecommendation$ImmunizationRecommendationRecommendationProtocolComponent;
     118: areturn
     119: aload_0
     120: invokevirtual #57                 // Method addSupportingImmunization:()Lorg/hl7/fhir/dstu3/model/Reference;
     123: areturn
     124: aload_0
     125: invokevirtual #63                 // Method addSupportingPatientInformation:()Lorg/hl7/fhir/dstu3/model/Reference;
     128: areturn
     129: aload_0
     130: iload_1
     131: aload_2
     132: invokespecial #113                // Method org/hl7/fhir/dstu3/model/BackboneElement.makeProperty:(ILjava/lang/String;)Lorg/hl7/fhir/dstu3/model/Base;
     135: areturn

  public java.lang.String[] getTypesForProperty(int, java.lang.String) throws org.hl7.fhir.exceptions.FHIRException;
    Code:
       0: iload_1
       1: lookupswitch  { // 9
           -1234160646: 154
            -989163880: 139
            -887709242: 114
            -319593813: 104
               3076014: 84
             664556354: 94
            1171592021: 144
            1904598477: 124
            2087518867: 134
               default: 164
          }
      84: iconst_1
      85: anewarray     #114                // class java/lang/String
      88: dup
      89: iconst_0
      90: ldc           #68                 // String dateTime
      92: aastore
      93: areturn
      94: iconst_1
      95: anewarray     #114                // class java/lang/String
      98: dup
      99: iconst_0
     100: ldc           #72                 // String CodeableConcept
     102: aastore
     103: areturn
     104: iconst_1
     105: anewarray     #114                // class java/lang/String
     108: dup
     109: iconst_0
     110: ldc           #72                 // String CodeableConcept
     112: aastore
     113: areturn
     114: iconst_1
     115: anewarray     #114                // class java/lang/String
     118: dup
     119: iconst_0
     120: ldc           #77                 // String positiveInt
     122: aastore
     123: areturn
     124: iconst_1
     125: anewarray     #114                // class java/lang/String
     128: dup
     129: iconst_0
     130: ldc           #72                 // String CodeableConcept
     132: aastore
     133: areturn
     134: iconst_0
     135: anewarray     #114                // class java/lang/String
     138: areturn
     139: iconst_0
     140: anewarray     #114                // class java/lang/String
     143: areturn
     144: iconst_1
     145: anewarray     #114                // class java/lang/String
     148: dup
     149: iconst_0
     150: ldc           #115                // String Reference
     152: aastore
     153: areturn
     154: iconst_1
     155: anewarray     #114                // class java/lang/String
     158: dup
     159: iconst_0
     160: ldc           #115                // String Reference
     162: aastore
     163: areturn
     164: aload_0
     165: iload_1
     166: aload_2
     167: invokespecial #116                // Method org/hl7/fhir/dstu3/model/BackboneElement.getTypesForProperty:(ILjava/lang/String;)[Ljava/lang/String;
     170: areturn

  public org.hl7.fhir.dstu3.model.Base addChild(java.lang.String) throws org.hl7.fhir.exceptions.FHIRException;
    Code:
       0: aload_1
       1: ldc           #67                 // String date
       3: invokevirtual #105                // Method java/lang/String.equals:(Ljava/lang/Object;)Z
       6: ifeq          19
       9: new           #117                // class org/hl7/fhir/exceptions/FHIRException
      12: dup
      13: ldc           #118                // String Cannot call addChild on a primitive type ImmunizationRecommendation.date
      15: invokespecial #119                // Method org/hl7/fhir/exceptions/FHIRException."<init>":(Ljava/lang/String;)V
      18: athrow
      19: aload_1
      20: ldc           #71                 // String vaccineCode
      22: invokevirtual #105                // Method java/lang/String.equals:(Ljava/lang/Object;)Z
      25: ifeq          44
      28: aload_0
      29: new           #17                 // class org/hl7/fhir/dstu3/model/CodeableConcept
      32: dup
      33: invokespecial #18                 // Method org/hl7/fhir/dstu3/model/CodeableConcept."<init>":()V
      36: putfield      #15                 // Field vaccineCode:Lorg/hl7/fhir/dstu3/model/CodeableConcept;
      39: aload_0
      40: getfield      #15                 // Field vaccineCode:Lorg/hl7/fhir/dstu3/model/CodeableConcept;
      43: areturn
      44: aload_1
      45: ldc           #74                 // String targetDisease
      47: invokevirtual #105                // Method java/lang/String.equals:(Ljava/lang/Object;)Z
      50: ifeq          69
      53: aload_0
      54: new           #17                 // class org/hl7/fhir/dstu3/model/CodeableConcept
      57: dup
      58: invokespecial #18                 // Method org/hl7/fhir/dstu3/model/CodeableConcept."<init>":()V
      61: putfield      #20                 // Field targetDisease:Lorg/hl7/fhir/dstu3/model/CodeableConcept;
      64: aload_0
      65: getfield      #20                 // Field targetDisease:Lorg/hl7/fhir/dstu3/model/CodeableConcept;
      68: areturn
      69: aload_1
      70: ldc           #76                 // String doseNumber
      72: invokevirtual #105                // Method java/lang/String.equals:(Ljava/lang/Object;)Z
      75: ifeq          88
      78: new           #117                // class org/hl7/fhir/exceptions/FHIRException
      81: dup
      82: ldc           #120                // String Cannot call addChild on a primitive type ImmunizationRecommendation.doseNumber
      84: invokespecial #119                // Method org/hl7/fhir/exceptions/FHIRException."<init>":(Ljava/lang/String;)V
      87: athrow
      88: aload_1
      89: ldc           #79                 // String forecastStatus
      91: invokevirtual #105                // Method java/lang/String.equals:(Ljava/lang/Object;)Z
      94: ifeq          113
      97: aload_0
      98: new           #17                 // class org/hl7/fhir/dstu3/model/CodeableConcept
     101: dup
     102: invokespecial #18                 // Method org/hl7/fhir/dstu3/model/CodeableConcept."<init>":()V
     105: putfield      #3                  // Field forecastStatus:Lorg/hl7/fhir/dstu3/model/CodeableConcept;
     108: aload_0
     109: getfield      #3                  // Field forecastStatus:Lorg/hl7/fhir/dstu3/model/CodeableConcept;
     112: areturn
     113: aload_1
     114: ldc           #81                 // String dateCriterion
     116: invokevirtual #105                // Method java/lang/String.equals:(Ljava/lang/Object;)Z
     119: ifeq          127
     122: aload_0
     123: invokevirtual #45                 // Method addDateCriterion:()Lorg/hl7/fhir/dstu3/model/ImmunizationRecommendation$ImmunizationRecommendationRecommendationDateCriterionComponent;
     126: areturn
     127: aload_1
     128: ldc           #86                 // String protocol
     130: invokevirtual #105                // Method java/lang/String.equals:(Ljava/lang/Object;)Z
     133: ifeq          152
     136: aload_0
     137: new           #49                 // class org/hl7/fhir/dstu3/model/ImmunizationRecommendation$ImmunizationRecommendationRecommendationProtocolComponent
     140: dup
     141: invokespecial #50                 // Method org/hl7/fhir/dstu3/model/ImmunizationRecommendation$ImmunizationRecommendationRecommendationProtocolComponent."<init>":()V
     144: putfield      #47                 // Field protocol:Lorg/hl7/fhir/dstu3/model/ImmunizationRecommendation$ImmunizationRecommendationRecommendationProtocolComponent;
     147: aload_0
     148: getfield      #47                 // Field protocol:Lorg/hl7/fhir/dstu3/model/ImmunizationRecommendation$ImmunizationRecommendationRecommendationProtocolComponent;
     151: areturn
     152: aload_1
     153: ldc           #88                 // String supportingImmunization
     155: invokevirtual #105                // Method java/lang/String.equals:(Ljava/lang/Object;)Z
     158: ifeq          166
     161: aload_0
     162: invokevirtual #57                 // Method addSupportingImmunization:()Lorg/hl7/fhir/dstu3/model/Reference;
     165: areturn
     166: aload_1
     167: ldc           #91                 // String supportingPatientInformation
     169: invokevirtual #105                // Method java/lang/String.equals:(Ljava/lang/Object;)Z
     172: ifeq          180
     175: aload_0
     176: invokevirtual #63                 // Method addSupportingPatientInformation:()Lorg/hl7/fhir/dstu3/model/Reference;
     179: areturn
     180: aload_0
     181: aload_1
     182: invokespecial #121                // Method org/hl7/fhir/dstu3/model/BackboneElement.addChild:(Ljava/lang/String;)Lorg/hl7/fhir/dstu3/model/Base;
     185: areturn

  public org.hl7.fhir.dstu3.model.ImmunizationRecommendation$ImmunizationRecommendationRecommendationComponent copy();
    Code:
       0: new           #122                // class org/hl7/fhir/dstu3/model/ImmunizationRecommendation$ImmunizationRecommendationRecommendationComponent
       3: dup
       4: invokespecial #123                // Method "<init>":()V
       7: astore_1
       8: aload_0
       9: aload_1
      10: invokevirtual #124                // Method copyValues:(Lorg/hl7/fhir/dstu3/model/BackboneElement;)V
      13: aload_1
      14: aload_0
      15: getfield      #2                  // Field date:Lorg/hl7/fhir/dstu3/model/DateTimeType;
      18: ifnonnull     25
      21: aconst_null
      22: goto          32
      25: aload_0
      26: getfield      #2                  // Field date:Lorg/hl7/fhir/dstu3/model/DateTimeType;
      29: invokevirtual #125                // Method org/hl7/fhir/dstu3/model/DateTimeType.copy:()Lorg/hl7/fhir/dstu3/model/DateTimeType;
      32: putfield      #2                  // Field date:Lorg/hl7/fhir/dstu3/model/DateTimeType;
      35: aload_1
      36: aload_0
      37: getfield      #15                 // Field vaccineCode:Lorg/hl7/fhir/dstu3/model/CodeableConcept;
      40: ifnonnull     47
      43: aconst_null
      44: goto          54
      47: aload_0
      48: getfield      #15                 // Field vaccineCode:Lorg/hl7/fhir/dstu3/model/CodeableConcept;
      51: invokevirtual #126                // Method org/hl7/fhir/dstu3/model/CodeableConcept.copy:()Lorg/hl7/fhir/dstu3/model/CodeableConcept;
      54: putfield      #15                 // Field vaccineCode:Lorg/hl7/fhir/dstu3/model/CodeableConcept;
      57: aload_1
      58: aload_0
      59: getfield      #20                 // Field targetDisease:Lorg/hl7/fhir/dstu3/model/CodeableConcept;
      62: ifnonnull     69
      65: aconst_null
      66: goto          76
      69: aload_0
      70: getfield      #20                 // Field targetDisease:Lorg/hl7/fhir/dstu3/model/CodeableConcept;
      73: invokevirtual #126                // Method org/hl7/fhir/dstu3/model/CodeableConcept.copy:()Lorg/hl7/fhir/dstu3/model/CodeableConcept;
      76: putfield      #20                 // Field targetDisease:Lorg/hl7/fhir/dstu3/model/CodeableConcept;
      79: aload_1
      80: aload_0
      81: getfield      #22                 // Field doseNumber:Lorg/hl7/fhir/dstu3/model/PositiveIntType;
      84: ifnonnull     91
      87: aconst_null
      88: goto          98
      91: aload_0
      92: getfield      #22                 // Field doseNumber:Lorg/hl7/fhir/dstu3/model/PositiveIntType;
      95: invokevirtual #127                // Method org/hl7/fhir/dstu3/model/PositiveIntType.copy:()Lorg/hl7/fhir/dstu3/model/PositiveIntType;
      98: putfield      #22                 // Field doseNumber:Lorg/hl7/fhir/dstu3/model/PositiveIntType;
     101: aload_1
     102: aload_0
     103: getfield      #3                  // Field forecastStatus:Lorg/hl7/fhir/dstu3/model/CodeableConcept;
     106: ifnonnull     113
     109: aconst_null
     110: goto          120
     113: aload_0
     114: getfield      #3                  // Field forecastStatus:Lorg/hl7/fhir/dstu3/model/CodeableConcept;
     117: invokevirtual #126                // Method org/hl7/fhir/dstu3/model/CodeableConcept.copy:()Lorg/hl7/fhir/dstu3/model/CodeableConcept;
     120: putfield      #3                  // Field forecastStatus:Lorg/hl7/fhir/dstu3/model/CodeableConcept;
     123: aload_0
     124: getfield      #33                 // Field dateCriterion:Ljava/util/List;
     127: ifnull        187
     130: aload_1
     131: new           #34                 // class java/util/ArrayList
     134: dup
     135: invokespecial #35                 // Method java/util/ArrayList."<init>":()V
     138: putfield      #33                 // Field dateCriterion:Ljava/util/List;
     141: aload_0
     142: getfield      #33                 // Field dateCriterion:Ljava/util/List;
     145: invokeinterface #36,  1           // InterfaceMethod java/util/List.iterator:()Ljava/util/Iterator;
     150: astore_2
     151: aload_2
     152: invokeinterface #37,  1           // InterfaceMethod java/util/Iterator.hasNext:()Z
     157: ifeq          187
     160: aload_2
     161: invokeinterface #38,  1           // InterfaceMethod java/util/Iterator.next:()Ljava/lang/Object;
     166: checkcast     #39                 // class org/hl7/fhir/dstu3/model/ImmunizationRecommendation$ImmunizationRecommendationRecommendationDateCriterionComponent
     169: astore_3
     170: aload_1
     171: getfield      #33                 // Field dateCriterion:Ljava/util/List;
     174: aload_3
     175: invokevirtual #128                // Method org/hl7/fhir/dstu3/model/ImmunizationRecommendation$ImmunizationRecommendationRecommendationDateCriterionComponent.copy:()Lorg/hl7/fhir/dstu3/model/ImmunizationRecommendation$ImmunizationRecommendationRecommendationDateCriterionComponent;
     178: invokeinterface #42,  2           // InterfaceMethod java/util/List.add:(Ljava/lang/Object;)Z
     183: pop
     184: goto          151
     187: aload_1
     188: aload_0
     189: getfield      #47                 // Field protocol:Lorg/hl7/fhir/dstu3/model/ImmunizationRecommendation$ImmunizationRecommendationRecommendationProtocolComponent;
     192: ifnonnull     199
     195: aconst_null
     196: goto          206
     199: aload_0
     200: getfield      #47                 // Field protocol:Lorg/hl7/fhir/dstu3/model/ImmunizationRecommendation$ImmunizationRecommendationRecommendationProtocolComponent;
     203: invokevirtual #129                // Method org/hl7/fhir/dstu3/model/ImmunizationRecommendation$ImmunizationRecommendationRecommendationProtocolComponent.copy:()Lorg/hl7/fhir/dstu3/model/ImmunizationRecommendation$ImmunizationRecommendationRecommendationProtocolComponent;
     206: putfield      #47                 // Field protocol:Lorg/hl7/fhir/dstu3/model/ImmunizationRecommendation$ImmunizationRecommendationRecommendationProtocolComponent;
     209: aload_0
     210: getfield      #52                 // Field supportingImmunization:Ljava/util/List;
     213: ifnull        273
     216: aload_1
     217: new           #34                 // class java/util/ArrayList
     220: dup
     221: invokespecial #35                 // Method java/util/ArrayList."<init>":()V
     224: putfield      #52                 // Field supportingImmunization:Ljava/util/List;
     227: aload_0
     228: getfield      #52                 // Field supportingImmunization:Ljava/util/List;
     231: invokeinterface #36,  1           // InterfaceMethod java/util/List.iterator:()Ljava/util/Iterator;
     236: astore_2
     237: aload_2
     238: invokeinterface #37,  1           // InterfaceMethod java/util/Iterator.hasNext:()Z
     243: ifeq          273
     246: aload_2
     247: invokeinterface #38,  1           // InterfaceMethod java/util/Iterator.next:()Ljava/lang/Object;
     252: checkcast     #53                 // class org/hl7/fhir/dstu3/model/Reference
     255: astore_3
     256: aload_1
     257: getfield      #52                 // Field supportingImmunization:Ljava/util/List;
     260: aload_3
     261: invokevirtual #130                // Method org/hl7/fhir/dstu3/model/Reference.copy:()Lorg/hl7/fhir/dstu3/model/Reference;
     264: invokeinterface #42,  2           // InterfaceMethod java/util/List.add:(Ljava/lang/Object;)Z
     269: pop
     270: goto          237
     273: aload_0
     274: getfield      #61                 // Field supportingPatientInformation:Ljava/util/List;
     277: ifnull        337
     280: aload_1
     281: new           #34                 // class java/util/ArrayList
     284: dup
     285: invokespecial #35                 // Method java/util/ArrayList."<init>":()V
     288: putfield      #61                 // Field supportingPatientInformation:Ljava/util/List;
     291: aload_0
     292: getfield      #61                 // Field supportingPatientInformation:Ljava/util/List;
     295: invokeinterface #36,  1           // InterfaceMethod java/util/List.iterator:()Ljava/util/Iterator;
     300: astore_2
     301: aload_2
     302: invokeinterface #37,  1           // InterfaceMethod java/util/Iterator.hasNext:()Z
     307: ifeq          337
     310: aload_2
     311: invokeinterface #38,  1           // InterfaceMethod java/util/Iterator.next:()Ljava/lang/Object;
     316: checkcast     #53                 // class org/hl7/fhir/dstu3/model/Reference
     319: astore_3
     320: aload_1
     321: getfield      #61                 // Field supportingPatientInformation:Ljava/util/List;
     324: aload_3
     325: invokevirtual #130                // Method org/hl7/fhir/dstu3/model/Reference.copy:()Lorg/hl7/fhir/dstu3/model/Reference;
     328: invokeinterface #42,  2           // InterfaceMethod java/util/List.add:(Ljava/lang/Object;)Z
     333: pop
     334: goto          301
     337: aload_1
     338: areturn

  public boolean equalsDeep(org.hl7.fhir.dstu3.model.Base);
    Code:
       0: aload_0
       1: aload_1
       2: invokespecial #131                // Method org/hl7/fhir/dstu3/model/BackboneElement.equalsDeep:(Lorg/hl7/fhir/dstu3/model/Base;)Z
       5: ifne          10
       8: iconst_0
       9: ireturn
      10: aload_1
      11: instanceof    #122                // class org/hl7/fhir/dstu3/model/ImmunizationRecommendation$ImmunizationRecommendationRecommendationComponent
      14: ifne          19
      17: iconst_0
      18: ireturn
      19: aload_1
      20: checkcast     #122                // class org/hl7/fhir/dstu3/model/ImmunizationRecommendation$ImmunizationRecommendationRecommendationComponent
      23: astore_2
      24: aload_0
      25: getfield      #2                  // Field date:Lorg/hl7/fhir/dstu3/model/DateTimeType;
      28: aload_2
      29: getfield      #2                  // Field date:Lorg/hl7/fhir/dstu3/model/DateTimeType;
      32: iconst_1
      33: invokestatic  #132                // Method compareDeep:(Lorg/hl7/fhir/dstu3/model/Base;Lorg/hl7/fhir/dstu3/model/Base;Z)Z
      36: ifeq          163
      39: aload_0
      40: getfield      #15                 // Field vaccineCode:Lorg/hl7/fhir/dstu3/model/CodeableConcept;
      43: aload_2
      44: getfield      #15                 // Field vaccineCode:Lorg/hl7/fhir/dstu3/model/CodeableConcept;
      47: iconst_1
      48: invokestatic  #132                // Method compareDeep:(Lorg/hl7/fhir/dstu3/model/Base;Lorg/hl7/fhir/dstu3/model/Base;Z)Z
      51: ifeq          163
      54: aload_0
      55: getfield      #20                 // Field targetDisease:Lorg/hl7/fhir/dstu3/model/CodeableConcept;
      58: aload_2
      59: getfield      #20                 // Field targetDisease:Lorg/hl7/fhir/dstu3/model/CodeableConcept;
      62: iconst_1
      63: invokestatic  #132                // Method compareDeep:(Lorg/hl7/fhir/dstu3/model/Base;Lorg/hl7/fhir/dstu3/model/Base;Z)Z
      66: ifeq          163
      69: aload_0
      70: getfield      #22                 // Field doseNumber:Lorg/hl7/fhir/dstu3/model/PositiveIntType;
      73: aload_2
      74: getfield      #22                 // Field doseNumber:Lorg/hl7/fhir/dstu3/model/PositiveIntType;
      77: iconst_1
      78: invokestatic  #132                // Method compareDeep:(Lorg/hl7/fhir/dstu3/model/Base;Lorg/hl7/fhir/dstu3/model/Base;Z)Z
      81: ifeq          163
      84: aload_0
      85: getfield      #3                  // Field forecastStatus:Lorg/hl7/fhir/dstu3/model/CodeableConcept;
      88: aload_2
      89: getfield      #3                  // Field forecastStatus:Lorg/hl7/fhir/dstu3/model/CodeableConcept;
      92: iconst_1
      93: invokestatic  #132                // Method compareDeep:(Lorg/hl7/fhir/dstu3/model/Base;Lorg/hl7/fhir/dstu3/model/Base;Z)Z
      96: ifeq          163
      99: aload_0
     100: getfield      #33                 // Field dateCriterion:Ljava/util/List;
     103: aload_2
     104: getfield      #33                 // Field dateCriterion:Ljava/util/List;
     107: iconst_1
     108: invokestatic  #133                // Method compareDeep:(Ljava/util/List;Ljava/util/List;Z)Z
     111: ifeq          163
     114: aload_0
     115: getfield      #47                 // Field protocol:Lorg/hl7/fhir/dstu3/model/ImmunizationRecommendation$ImmunizationRecommendationRecommendationProtocolComponent;
     118: aload_2
     119: getfield      #47                 // Field protocol:Lorg/hl7/fhir/dstu3/model/ImmunizationRecommendation$ImmunizationRecommendationRecommendationProtocolComponent;
     122: iconst_1
     123: invokestatic  #132                // Method compareDeep:(Lorg/hl7/fhir/dstu3/model/Base;Lorg/hl7/fhir/dstu3/model/Base;Z)Z
     126: ifeq          163
     129: aload_0
     130: getfield      #52                 // Field supportingImmunization:Ljava/util/List;
     133: aload_2
     134: getfield      #52                 // Field supportingImmunization:Ljava/util/List;
     137: iconst_1
     138: invokestatic  #133                // Method compareDeep:(Ljava/util/List;Ljava/util/List;Z)Z
     141: ifeq          163
     144: aload_0
     145: getfield      #61                 // Field supportingPatientInformation:Ljava/util/List;
     148: aload_2
     149: getfield      #61                 // Field supportingPatientInformation:Ljava/util/List;
     152: iconst_1
     153: invokestatic  #133                // Method compareDeep:(Ljava/util/List;Ljava/util/List;Z)Z
     156: ifeq          163
     159: iconst_1
     160: goto          164
     163: iconst_0
     164: ireturn

  public boolean equalsShallow(org.hl7.fhir.dstu3.model.Base);
    Code:
       0: aload_0
       1: aload_1
       2: invokespecial #134                // Method org/hl7/fhir/dstu3/model/BackboneElement.equalsShallow:(Lorg/hl7/fhir/dstu3/model/Base;)Z
       5: ifne          10
       8: iconst_0
       9: ireturn
      10: aload_1
      11: instanceof    #122                // class org/hl7/fhir/dstu3/model/ImmunizationRecommendation$ImmunizationRecommendationRecommendationComponent
      14: ifne          19
      17: iconst_0
      18: ireturn
      19: aload_1
      20: checkcast     #122                // class org/hl7/fhir/dstu3/model/ImmunizationRecommendation$ImmunizationRecommendationRecommendationComponent
      23: astore_2
      24: aload_0
      25: getfield      #2                  // Field date:Lorg/hl7/fhir/dstu3/model/DateTimeType;
      28: aload_2
      29: getfield      #2                  // Field date:Lorg/hl7/fhir/dstu3/model/DateTimeType;
      32: iconst_1
      33: invokestatic  #135                // Method compareValues:(Lorg/hl7/fhir/dstu3/model/PrimitiveType;Lorg/hl7/fhir/dstu3/model/PrimitiveType;Z)Z
      36: ifeq          58
      39: aload_0
      40: getfield      #22                 // Field doseNumber:Lorg/hl7/fhir/dstu3/model/PositiveIntType;
      43: aload_2
      44: getfield      #22                 // Field doseNumber:Lorg/hl7/fhir/dstu3/model/PositiveIntType;
      47: iconst_1
      48: invokestatic  #135                // Method compareValues:(Lorg/hl7/fhir/dstu3/model/PrimitiveType;Lorg/hl7/fhir/dstu3/model/PrimitiveType;Z)Z
      51: ifeq          58
      54: iconst_1
      55: goto          59
      58: iconst_0
      59: ireturn

  public boolean isEmpty();
    Code:
       0: aload_0
       1: invokespecial #136                // Method org/hl7/fhir/dstu3/model/BackboneElement.isEmpty:()Z
       4: ifeq          88
       7: bipush        9
       9: anewarray     #137                // class java/lang/Object
      12: dup
      13: iconst_0
      14: aload_0
      15: getfield      #2                  // Field date:Lorg/hl7/fhir/dstu3/model/DateTimeType;
      18: aastore
      19: dup
      20: iconst_1
      21: aload_0
      22: getfield      #15                 // Field vaccineCode:Lorg/hl7/fhir/dstu3/model/CodeableConcept;
      25: aastore
      26: dup
      27: iconst_2
      28: aload_0
      29: getfield      #20                 // Field targetDisease:Lorg/hl7/fhir/dstu3/model/CodeableConcept;
      32: aastore
      33: dup
      34: iconst_3
      35: aload_0
      36: getfield      #22                 // Field doseNumber:Lorg/hl7/fhir/dstu3/model/PositiveIntType;
      39: aastore
      40: dup
      41: iconst_4
      42: aload_0
      43: getfield      #3                  // Field forecastStatus:Lorg/hl7/fhir/dstu3/model/CodeableConcept;
      46: aastore
      47: dup
      48: iconst_5
      49: aload_0
      50: getfield      #33                 // Field dateCriterion:Ljava/util/List;
      53: aastore
      54: dup
      55: bipush        6
      57: aload_0
      58: getfield      #47                 // Field protocol:Lorg/hl7/fhir/dstu3/model/ImmunizationRecommendation$ImmunizationRecommendationRecommendationProtocolComponent;
      61: aastore
      62: dup
      63: bipush        7
      65: aload_0
      66: getfield      #52                 // Field supportingImmunization:Ljava/util/List;
      69: aastore
      70: dup
      71: bipush        8
      73: aload_0
      74: getfield      #61                 // Field supportingPatientInformation:Ljava/util/List;
      77: aastore
      78: invokestatic  #138                // Method ca/uhn/fhir/util/ElementUtil.isEmpty:([Ljava/lang/Object;)Z
      81: ifeq          88
      84: iconst_1
      85: goto          89
      88: iconst_0
      89: ireturn

  public java.lang.String fhirType();
    Code:
       0: ldc           #139                // String ImmunizationRecommendation.recommendation
       2: areturn

  public org.hl7.fhir.dstu3.model.BackboneElement copy();
    Code:
       0: aload_0
       1: invokevirtual #140                // Method copy:()Lorg/hl7/fhir/dstu3/model/ImmunizationRecommendation$ImmunizationRecommendationRecommendationComponent;
       4: areturn

  public org.hl7.fhir.dstu3.model.Element copy();
    Code:
       0: aload_0
       1: invokevirtual #140                // Method copy:()Lorg/hl7/fhir/dstu3/model/ImmunizationRecommendation$ImmunizationRecommendationRecommendationComponent;
       4: areturn
}
