Compiled from "MedicationRequest.java"
public final class org.hl7.fhir.dstu3.model.MedicationRequest$MedicationRequestIntent extends java.lang.Enum<org.hl7.fhir.dstu3.model.MedicationRequest$MedicationRequestIntent> {
  public static final org.hl7.fhir.dstu3.model.MedicationRequest$MedicationRequestIntent PROPOSAL;

  public static final org.hl7.fhir.dstu3.model.MedicationRequest$MedicationRequestIntent PLAN;

  public static final org.hl7.fhir.dstu3.model.MedicationRequest$MedicationRequestIntent ORDER;

  public static final org.hl7.fhir.dstu3.model.MedicationRequest$MedicationRequestIntent INSTANCEORDER;

  public static final org.hl7.fhir.dstu3.model.MedicationRequest$MedicationRequestIntent NULL;

  private static final org.hl7.fhir.dstu3.model.MedicationRequest$MedicationRequestIntent[] $VALUES;

  public static org.hl7.fhir.dstu3.model.MedicationRequest$MedicationRequestIntent[] values();
    Code:
       0: getstatic     #1                  // Field $VALUES:[Lorg/hl7/fhir/dstu3/model/MedicationRequest$MedicationRequestIntent;
       3: invokevirtual #2                  // Method "[Lorg/hl7/fhir/dstu3/model/MedicationRequest$MedicationRequestIntent;".clone:()Ljava/lang/Object;
       6: checkcast     #3                  // class "[Lorg/hl7/fhir/dstu3/model/MedicationRequest$MedicationRequestIntent;"
       9: areturn

  public static org.hl7.fhir.dstu3.model.MedicationRequest$MedicationRequestIntent valueOf(java.lang.String);
    Code:
       0: ldc           #4                  // class org/hl7/fhir/dstu3/model/MedicationRequest$MedicationRequestIntent
       2: aload_0
       3: invokestatic  #5                  // Method java/lang/Enum.valueOf:(Ljava/lang/Class;Ljava/lang/String;)Ljava/lang/Enum;
       6: checkcast     #4                  // class org/hl7/fhir/dstu3/model/MedicationRequest$MedicationRequestIntent
       9: areturn

  private org.hl7.fhir.dstu3.model.MedicationRequest$MedicationRequestIntent();
    Code:
       0: aload_0
       1: aload_1
       2: iload_2
       3: invokespecial #6                  // Method java/lang/Enum."<init>":(Ljava/lang/String;I)V
       6: return

  public static org.hl7.fhir.dstu3.model.MedicationRequest$MedicationRequestIntent fromCode(java.lang.String) throws org.hl7.fhir.exceptions.FHIRException;
    Code:
       0: aload_0
       1: ifnull        13
       4: ldc           #7                  // String
       6: aload_0
       7: invokevirtual #8                  // Method java/lang/String.equals:(Ljava/lang/Object;)Z
      10: ifeq          15
      13: aconst_null
      14: areturn
      15: ldc           #9                  // String proposal
      17: aload_0
      18: invokevirtual #8                  // Method java/lang/String.equals:(Ljava/lang/Object;)Z
      21: ifeq          28
      24: getstatic     #10                 // Field PROPOSAL:Lorg/hl7/fhir/dstu3/model/MedicationRequest$MedicationRequestIntent;
      27: areturn
      28: ldc           #11                 // String plan
      30: aload_0
      31: invokevirtual #8                  // Method java/lang/String.equals:(Ljava/lang/Object;)Z
      34: ifeq          41
      37: getstatic     #12                 // Field PLAN:Lorg/hl7/fhir/dstu3/model/MedicationRequest$MedicationRequestIntent;
      40: areturn
      41: ldc           #13                 // String order
      43: aload_0
      44: invokevirtual #8                  // Method java/lang/String.equals:(Ljava/lang/Object;)Z
      47: ifeq          54
      50: getstatic     #14                 // Field ORDER:Lorg/hl7/fhir/dstu3/model/MedicationRequest$MedicationRequestIntent;
      53: areturn
      54: ldc           #15                 // String instance-order
      56: aload_0
      57: invokevirtual #8                  // Method java/lang/String.equals:(Ljava/lang/Object;)Z
      60: ifeq          67
      63: getstatic     #16                 // Field INSTANCEORDER:Lorg/hl7/fhir/dstu3/model/MedicationRequest$MedicationRequestIntent;
      66: areturn
      67: invokestatic  #17                 // Method org/hl7/fhir/dstu3/model/Configuration.isAcceptInvalidEnums:()Z
      70: ifeq          75
      73: aconst_null
      74: areturn
      75: new           #18                 // class org/hl7/fhir/exceptions/FHIRException
      78: dup
      79: new           #19                 // class java/lang/StringBuilder
      82: dup
      83: invokespecial #20                 // Method java/lang/StringBuilder."<init>":()V
      86: ldc           #21                 // String Unknown MedicationRequestIntent code \'
      88: invokevirtual #22                 // Method java/lang/StringBuilder.append:(Ljava/lang/String;)Ljava/lang/StringBuilder;
      91: aload_0
      92: invokevirtual #22                 // Method java/lang/StringBuilder.append:(Ljava/lang/String;)Ljava/lang/StringBuilder;
      95: ldc           #23                 // String \'
      97: invokevirtual #22                 // Method java/lang/StringBuilder.append:(Ljava/lang/String;)Ljava/lang/StringBuilder;
     100: invokevirtual #24                 // Method java/lang/StringBuilder.toString:()Ljava/lang/String;
     103: invokespecial #25                 // Method org/hl7/fhir/exceptions/FHIRException."<init>":(Ljava/lang/String;)V
     106: athrow

  public java.lang.String toCode();
    Code:
       0: getstatic     #26                 // Field org/hl7/fhir/dstu3/model/MedicationRequest$1.$SwitchMap$org$hl7$fhir$dstu3$model$MedicationRequest$MedicationRequestIntent:[I
       3: aload_0
       4: invokevirtual #27                 // Method ordinal:()I
       7: iaload
       8: tableswitch   { // 1 to 5
                     1: 44
                     2: 47
                     3: 50
                     4: 53
                     5: 56
               default: 58
          }
      44: ldc           #9                  // String proposal
      46: areturn
      47: ldc           #11                 // String plan
      49: areturn
      50: ldc           #13                 // String order
      52: areturn
      53: ldc           #15                 // String instance-order
      55: areturn
      56: aconst_null
      57: areturn
      58: ldc           #28                 // String ?
      60: areturn

  public java.lang.String getSystem();
    Code:
       0: getstatic     #26                 // Field org/hl7/fhir/dstu3/model/MedicationRequest$1.$SwitchMap$org$hl7$fhir$dstu3$model$MedicationRequest$MedicationRequestIntent:[I
       3: aload_0
       4: invokevirtual #27                 // Method ordinal:()I
       7: iaload
       8: tableswitch   { // 1 to 5
                     1: 44
                     2: 47
                     3: 50
                     4: 53
                     5: 56
               default: 58
          }
      44: ldc           #29                 // String http://hl7.org/fhir/medication-request-intent
      46: areturn
      47: ldc           #29                 // String http://hl7.org/fhir/medication-request-intent
      49: areturn
      50: ldc           #29                 // String http://hl7.org/fhir/medication-request-intent
      52: areturn
      53: ldc           #29                 // String http://hl7.org/fhir/medication-request-intent
      55: areturn
      56: aconst_null
      57: areturn
      58: ldc           #28                 // String ?
      60: areturn

  public java.lang.String getDefinition();
    Code:
       0: getstatic     #26                 // Field org/hl7/fhir/dstu3/model/MedicationRequest$1.$SwitchMap$org$hl7$fhir$dstu3$model$MedicationRequest$MedicationRequestIntent:[I
       3: aload_0
       4: invokevirtual #27                 // Method ordinal:()I
       7: iaload
       8: tableswitch   { // 1 to 5
                     1: 44
                     2: 47
                     3: 50
                     4: 53
                     5: 56
               default: 58
          }
      44: ldc           #30                 // String The request is a suggestion made by someone/something that doesn\'t have an intention to ensure it occurs and without providing an authorization to act
      46: areturn
      47: ldc           #31                 // String The request represents an intension to ensure something occurs without providing an authorization for others to act
      49: areturn
      50: ldc           #32                 // String The request represents a request/demand and authorization for action
      52: areturn
      53: ldc           #33                 // String The request represents an instance for the particular order, for example a medication administration record.
      55: areturn
      56: aconst_null
      57: areturn
      58: ldc           #28                 // String ?
      60: areturn

  public java.lang.String getDisplay();
    Code:
       0: getstatic     #26                 // Field org/hl7/fhir/dstu3/model/MedicationRequest$1.$SwitchMap$org$hl7$fhir$dstu3$model$MedicationRequest$MedicationRequestIntent:[I
       3: aload_0
       4: invokevirtual #27                 // Method ordinal:()I
       7: iaload
       8: tableswitch   { // 1 to 5
                     1: 44
                     2: 47
                     3: 50
                     4: 53
                     5: 56
               default: 58
          }
      44: ldc           #34                 // String Proposal
      46: areturn
      47: ldc           #35                 // String Plan
      49: areturn
      50: ldc           #36                 // String Order
      52: areturn
      53: ldc           #37                 // String Instance Order
      55: areturn
      56: aconst_null
      57: areturn
      58: ldc           #28                 // String ?
      60: areturn

  static {};
    Code:
       0: new           #4                  // class org/hl7/fhir/dstu3/model/MedicationRequest$MedicationRequestIntent
       3: dup
       4: ldc           #38                 // String PROPOSAL
       6: iconst_0
       7: invokespecial #39                 // Method "<init>":(Ljava/lang/String;I)V
      10: putstatic     #10                 // Field PROPOSAL:Lorg/hl7/fhir/dstu3/model/MedicationRequest$MedicationRequestIntent;
      13: new           #4                  // class org/hl7/fhir/dstu3/model/MedicationRequest$MedicationRequestIntent
      16: dup
      17: ldc           #40                 // String PLAN
      19: iconst_1
      20: invokespecial #39                 // Method "<init>":(Ljava/lang/String;I)V
      23: putstatic     #12                 // Field PLAN:Lorg/hl7/fhir/dstu3/model/MedicationRequest$MedicationRequestIntent;
      26: new           #4                  // class org/hl7/fhir/dstu3/model/MedicationRequest$MedicationRequestIntent
      29: dup
      30: ldc           #41                 // String ORDER
      32: iconst_2
      33: invokespecial #39                 // Method "<init>":(Ljava/lang/String;I)V
      36: putstatic     #14                 // Field ORDER:Lorg/hl7/fhir/dstu3/model/MedicationRequest$MedicationRequestIntent;
      39: new           #4                  // class org/hl7/fhir/dstu3/model/MedicationRequest$MedicationRequestIntent
      42: dup
      43: ldc           #42                 // String INSTANCEORDER
      45: iconst_3
      46: invokespecial #39                 // Method "<init>":(Ljava/lang/String;I)V
      49: putstatic     #16                 // Field INSTANCEORDER:Lorg/hl7/fhir/dstu3/model/MedicationRequest$MedicationRequestIntent;
      52: new           #4                  // class org/hl7/fhir/dstu3/model/MedicationRequest$MedicationRequestIntent
      55: dup
      56: ldc           #43                 // String NULL
      58: iconst_4
      59: invokespecial #39                 // Method "<init>":(Ljava/lang/String;I)V
      62: putstatic     #44                 // Field NULL:Lorg/hl7/fhir/dstu3/model/MedicationRequest$MedicationRequestIntent;
      65: iconst_5
      66: anewarray     #4                  // class org/hl7/fhir/dstu3/model/MedicationRequest$MedicationRequestIntent
      69: dup
      70: iconst_0
      71: getstatic     #10                 // Field PROPOSAL:Lorg/hl7/fhir/dstu3/model/MedicationRequest$MedicationRequestIntent;
      74: aastore
      75: dup
      76: iconst_1
      77: getstatic     #12                 // Field PLAN:Lorg/hl7/fhir/dstu3/model/MedicationRequest$MedicationRequestIntent;
      80: aastore
      81: dup
      82: iconst_2
      83: getstatic     #14                 // Field ORDER:Lorg/hl7/fhir/dstu3/model/MedicationRequest$MedicationRequestIntent;
      86: aastore
      87: dup
      88: iconst_3
      89: getstatic     #16                 // Field INSTANCEORDER:Lorg/hl7/fhir/dstu3/model/MedicationRequest$MedicationRequestIntent;
      92: aastore
      93: dup
      94: iconst_4
      95: getstatic     #44                 // Field NULL:Lorg/hl7/fhir/dstu3/model/MedicationRequest$MedicationRequestIntent;
      98: aastore
      99: putstatic     #1                  // Field $VALUES:[Lorg/hl7/fhir/dstu3/model/MedicationRequest$MedicationRequestIntent;
     102: return
}
