Compiled from "MedicationRequest.java"
public final class org.hl7.fhir.dstu3.model.MedicationRequest$MedicationRequestStatus extends java.lang.Enum<org.hl7.fhir.dstu3.model.MedicationRequest$MedicationRequestStatus> {
  public static final org.hl7.fhir.dstu3.model.MedicationRequest$MedicationRequestStatus ACTIVE;

  public static final org.hl7.fhir.dstu3.model.MedicationRequest$MedicationRequestStatus ONHOLD;

  public static final org.hl7.fhir.dstu3.model.MedicationRequest$MedicationRequestStatus CANCELLED;

  public static final org.hl7.fhir.dstu3.model.MedicationRequest$MedicationRequestStatus COMPLETED;

  public static final org.hl7.fhir.dstu3.model.MedicationRequest$MedicationRequestStatus ENTEREDINERROR;

  public static final org.hl7.fhir.dstu3.model.MedicationRequest$MedicationRequestStatus STOPPED;

  public static final org.hl7.fhir.dstu3.model.MedicationRequest$MedicationRequestStatus DRAFT;

  public static final org.hl7.fhir.dstu3.model.MedicationRequest$MedicationRequestStatus UNKNOWN;

  public static final org.hl7.fhir.dstu3.model.MedicationRequest$MedicationRequestStatus NULL;

  private static final org.hl7.fhir.dstu3.model.MedicationRequest$MedicationRequestStatus[] $VALUES;

  public static org.hl7.fhir.dstu3.model.MedicationRequest$MedicationRequestStatus[] values();
    Code:
       0: getstatic     #1                  // Field $VALUES:[Lorg/hl7/fhir/dstu3/model/MedicationRequest$MedicationRequestStatus;
       3: invokevirtual #2                  // Method "[Lorg/hl7/fhir/dstu3/model/MedicationRequest$MedicationRequestStatus;".clone:()Ljava/lang/Object;
       6: checkcast     #3                  // class "[Lorg/hl7/fhir/dstu3/model/MedicationRequest$MedicationRequestStatus;"
       9: areturn

  public static org.hl7.fhir.dstu3.model.MedicationRequest$MedicationRequestStatus valueOf(java.lang.String);
    Code:
       0: ldc           #4                  // class org/hl7/fhir/dstu3/model/MedicationRequest$MedicationRequestStatus
       2: aload_0
       3: invokestatic  #5                  // Method java/lang/Enum.valueOf:(Ljava/lang/Class;Ljava/lang/String;)Ljava/lang/Enum;
       6: checkcast     #4                  // class org/hl7/fhir/dstu3/model/MedicationRequest$MedicationRequestStatus
       9: areturn

  private org.hl7.fhir.dstu3.model.MedicationRequest$MedicationRequestStatus();
    Code:
       0: aload_0
       1: aload_1
       2: iload_2
       3: invokespecial #6                  // Method java/lang/Enum."<init>":(Ljava/lang/String;I)V
       6: return

  public static org.hl7.fhir.dstu3.model.MedicationRequest$MedicationRequestStatus fromCode(java.lang.String) throws org.hl7.fhir.exceptions.FHIRException;
    Code:
       0: aload_0
       1: ifnull        13
       4: ldc           #7                  // String
       6: aload_0
       7: invokevirtual #8                  // Method java/lang/String.equals:(Ljava/lang/Object;)Z
      10: ifeq          15
      13: aconst_null
      14: areturn
      15: ldc           #9                  // String active
      17: aload_0
      18: invokevirtual #8                  // Method java/lang/String.equals:(Ljava/lang/Object;)Z
      21: ifeq          28
      24: getstatic     #10                 // Field ACTIVE:Lorg/hl7/fhir/dstu3/model/MedicationRequest$MedicationRequestStatus;
      27: areturn
      28: ldc           #11                 // String on-hold
      30: aload_0
      31: invokevirtual #8                  // Method java/lang/String.equals:(Ljava/lang/Object;)Z
      34: ifeq          41
      37: getstatic     #12                 // Field ONHOLD:Lorg/hl7/fhir/dstu3/model/MedicationRequest$MedicationRequestStatus;
      40: areturn
      41: ldc           #13                 // String cancelled
      43: aload_0
      44: invokevirtual #8                  // Method java/lang/String.equals:(Ljava/lang/Object;)Z
      47: ifeq          54
      50: getstatic     #14                 // Field CANCELLED:Lorg/hl7/fhir/dstu3/model/MedicationRequest$MedicationRequestStatus;
      53: areturn
      54: ldc           #15                 // String completed
      56: aload_0
      57: invokevirtual #8                  // Method java/lang/String.equals:(Ljava/lang/Object;)Z
      60: ifeq          67
      63: getstatic     #16                 // Field COMPLETED:Lorg/hl7/fhir/dstu3/model/MedicationRequest$MedicationRequestStatus;
      66: areturn
      67: ldc           #17                 // String entered-in-error
      69: aload_0
      70: invokevirtual #8                  // Method java/lang/String.equals:(Ljava/lang/Object;)Z
      73: ifeq          80
      76: getstatic     #18                 // Field ENTEREDINERROR:Lorg/hl7/fhir/dstu3/model/MedicationRequest$MedicationRequestStatus;
      79: areturn
      80: ldc           #19                 // String stopped
      82: aload_0
      83: invokevirtual #8                  // Method java/lang/String.equals:(Ljava/lang/Object;)Z
      86: ifeq          93
      89: getstatic     #20                 // Field STOPPED:Lorg/hl7/fhir/dstu3/model/MedicationRequest$MedicationRequestStatus;
      92: areturn
      93: ldc           #21                 // String draft
      95: aload_0
      96: invokevirtual #8                  // Method java/lang/String.equals:(Ljava/lang/Object;)Z
      99: ifeq          106
     102: getstatic     #22                 // Field DRAFT:Lorg/hl7/fhir/dstu3/model/MedicationRequest$MedicationRequestStatus;
     105: areturn
     106: ldc           #23                 // String unknown
     108: aload_0
     109: invokevirtual #8                  // Method java/lang/String.equals:(Ljava/lang/Object;)Z
     112: ifeq          119
     115: getstatic     #24                 // Field UNKNOWN:Lorg/hl7/fhir/dstu3/model/MedicationRequest$MedicationRequestStatus;
     118: areturn
     119: invokestatic  #25                 // Method org/hl7/fhir/dstu3/model/Configuration.isAcceptInvalidEnums:()Z
     122: ifeq          127
     125: aconst_null
     126: areturn
     127: new           #26                 // class org/hl7/fhir/exceptions/FHIRException
     130: dup
     131: new           #27                 // class java/lang/StringBuilder
     134: dup
     135: invokespecial #28                 // Method java/lang/StringBuilder."<init>":()V
     138: ldc           #29                 // String Unknown MedicationRequestStatus code \'
     140: invokevirtual #30                 // Method java/lang/StringBuilder.append:(Ljava/lang/String;)Ljava/lang/StringBuilder;
     143: aload_0
     144: invokevirtual #30                 // Method java/lang/StringBuilder.append:(Ljava/lang/String;)Ljava/lang/StringBuilder;
     147: ldc           #31                 // String \'
     149: invokevirtual #30                 // Method java/lang/StringBuilder.append:(Ljava/lang/String;)Ljava/lang/StringBuilder;
     152: invokevirtual #32                 // Method java/lang/StringBuilder.toString:()Ljava/lang/String;
     155: invokespecial #33                 // Method org/hl7/fhir/exceptions/FHIRException."<init>":(Ljava/lang/String;)V
     158: athrow

  public java.lang.String toCode();
    Code:
       0: getstatic     #34                 // Field org/hl7/fhir/dstu3/model/MedicationRequest$1.$SwitchMap$org$hl7$fhir$dstu3$model$MedicationRequest$MedicationRequestStatus:[I
       3: aload_0
       4: invokevirtual #35                 // Method ordinal:()I
       7: iaload
       8: tableswitch   { // 1 to 9
                     1: 60
                     2: 63
                     3: 66
                     4: 69
                     5: 72
                     6: 75
                     7: 78
                     8: 81
                     9: 84
               default: 86
          }
      60: ldc           #9                  // String active
      62: areturn
      63: ldc           #11                 // String on-hold
      65: areturn
      66: ldc           #13                 // String cancelled
      68: areturn
      69: ldc           #15                 // String completed
      71: areturn
      72: ldc           #17                 // String entered-in-error
      74: areturn
      75: ldc           #19                 // String stopped
      77: areturn
      78: ldc           #21                 // String draft
      80: areturn
      81: ldc           #23                 // String unknown
      83: areturn
      84: aconst_null
      85: areturn
      86: ldc           #36                 // String ?
      88: areturn

  public java.lang.String getSystem();
    Code:
       0: getstatic     #34                 // Field org/hl7/fhir/dstu3/model/MedicationRequest$1.$SwitchMap$org$hl7$fhir$dstu3$model$MedicationRequest$MedicationRequestStatus:[I
       3: aload_0
       4: invokevirtual #35                 // Method ordinal:()I
       7: iaload
       8: tableswitch   { // 1 to 9
                     1: 60
                     2: 63
                     3: 66
                     4: 69
                     5: 72
                     6: 75
                     7: 78
                     8: 81
                     9: 84
               default: 86
          }
      60: ldc           #37                 // String http://hl7.org/fhir/medication-request-status
      62: areturn
      63: ldc           #37                 // String http://hl7.org/fhir/medication-request-status
      65: areturn
      66: ldc           #37                 // String http://hl7.org/fhir/medication-request-status
      68: areturn
      69: ldc           #37                 // String http://hl7.org/fhir/medication-request-status
      71: areturn
      72: ldc           #37                 // String http://hl7.org/fhir/medication-request-status
      74: areturn
      75: ldc           #37                 // String http://hl7.org/fhir/medication-request-status
      77: areturn
      78: ldc           #37                 // String http://hl7.org/fhir/medication-request-status
      80: areturn
      81: ldc           #37                 // String http://hl7.org/fhir/medication-request-status
      83: areturn
      84: aconst_null
      85: areturn
      86: ldc           #36                 // String ?
      88: areturn

  public java.lang.String getDefinition();
    Code:
       0: getstatic     #34                 // Field org/hl7/fhir/dstu3/model/MedicationRequest$1.$SwitchMap$org$hl7$fhir$dstu3$model$MedicationRequest$MedicationRequestStatus:[I
       3: aload_0
       4: invokevirtual #35                 // Method ordinal:()I
       7: iaload
       8: tableswitch   { // 1 to 9
                     1: 60
                     2: 63
                     3: 66
                     4: 69
                     5: 72
                     6: 75
                     7: 78
                     8: 81
                     9: 84
               default: 86
          }
      60: ldc           #38                 // String The prescription is \'actionable\', but not all actions that are implied by it have occurred yet.
      62: areturn
      63: ldc           #39                 // String Actions implied by the prescription are to be temporarily halted, but are expected to continue later.  May also be called \"suspended\".
      65: areturn
      66: ldc           #40                 // String The prescription has been withdrawn.
      68: areturn
      69: ldc           #41                 // String All actions that are implied by the prescription have occurred.
      71: areturn
      72: ldc           #42                 // String The prescription was entered in error.
      74: areturn
      75: ldc           #43                 // String Actions implied by the prescription are to be permanently halted, before all of them occurred.
      77: areturn
      78: ldc           #44                 // String The prescription is not yet \'actionable\', i.e. it is a work in progress, requires sign-off or verification, and needs to be run through decision support process.
      80: areturn
      81: ldc           #45                 // String The authoring system does not know which of the status values currently applies for this request
      83: areturn
      84: aconst_null
      85: areturn
      86: ldc           #36                 // String ?
      88: areturn

  public java.lang.String getDisplay();
    Code:
       0: getstatic     #34                 // Field org/hl7/fhir/dstu3/model/MedicationRequest$1.$SwitchMap$org$hl7$fhir$dstu3$model$MedicationRequest$MedicationRequestStatus:[I
       3: aload_0
       4: invokevirtual #35                 // Method ordinal:()I
       7: iaload
       8: tableswitch   { // 1 to 9
                     1: 60
                     2: 63
                     3: 66
                     4: 69
                     5: 72
                     6: 75
                     7: 78
                     8: 81
                     9: 84
               default: 86
          }
      60: ldc           #46                 // String Active
      62: areturn
      63: ldc           #47                 // String On Hold
      65: areturn
      66: ldc           #48                 // String Cancelled
      68: areturn
      69: ldc           #49                 // String Completed
      71: areturn
      72: ldc           #50                 // String Entered In Error
      74: areturn
      75: ldc           #51                 // String Stopped
      77: areturn
      78: ldc           #52                 // String Draft
      80: areturn
      81: ldc           #53                 // String Unknown
      83: areturn
      84: aconst_null
      85: areturn
      86: ldc           #36                 // String ?
      88: areturn

  static {};
    Code:
       0: new           #4                  // class org/hl7/fhir/dstu3/model/MedicationRequest$MedicationRequestStatus
       3: dup
       4: ldc           #54                 // String ACTIVE
       6: iconst_0
       7: invokespecial #55                 // Method "<init>":(Ljava/lang/String;I)V
      10: putstatic     #10                 // Field ACTIVE:Lorg/hl7/fhir/dstu3/model/MedicationRequest$MedicationRequestStatus;
      13: new           #4                  // class org/hl7/fhir/dstu3/model/MedicationRequest$MedicationRequestStatus
      16: dup
      17: ldc           #56                 // String ONHOLD
      19: iconst_1
      20: invokespecial #55                 // Method "<init>":(Ljava/lang/String;I)V
      23: putstatic     #12                 // Field ONHOLD:Lorg/hl7/fhir/dstu3/model/MedicationRequest$MedicationRequestStatus;
      26: new           #4                  // class org/hl7/fhir/dstu3/model/MedicationRequest$MedicationRequestStatus
      29: dup
      30: ldc           #57                 // String CANCELLED
      32: iconst_2
      33: invokespecial #55                 // Method "<init>":(Ljava/lang/String;I)V
      36: putstatic     #14                 // Field CANCELLED:Lorg/hl7/fhir/dstu3/model/MedicationRequest$MedicationRequestStatus;
      39: new           #4                  // class org/hl7/fhir/dstu3/model/MedicationRequest$MedicationRequestStatus
      42: dup
      43: ldc           #58                 // String COMPLETED
      45: iconst_3
      46: invokespecial #55                 // Method "<init>":(Ljava/lang/String;I)V
      49: putstatic     #16                 // Field COMPLETED:Lorg/hl7/fhir/dstu3/model/MedicationRequest$MedicationRequestStatus;
      52: new           #4                  // class org/hl7/fhir/dstu3/model/MedicationRequest$MedicationRequestStatus
      55: dup
      56: ldc           #59                 // String ENTEREDINERROR
      58: iconst_4
      59: invokespecial #55                 // Method "<init>":(Ljava/lang/String;I)V
      62: putstatic     #18                 // Field ENTEREDINERROR:Lorg/hl7/fhir/dstu3/model/MedicationRequest$MedicationRequestStatus;
      65: new           #4                  // class org/hl7/fhir/dstu3/model/MedicationRequest$MedicationRequestStatus
      68: dup
      69: ldc           #60                 // String STOPPED
      71: iconst_5
      72: invokespecial #55                 // Method "<init>":(Ljava/lang/String;I)V
      75: putstatic     #20                 // Field STOPPED:Lorg/hl7/fhir/dstu3/model/MedicationRequest$MedicationRequestStatus;
      78: new           #4                  // class org/hl7/fhir/dstu3/model/MedicationRequest$MedicationRequestStatus
      81: dup
      82: ldc           #61                 // String DRAFT
      84: bipush        6
      86: invokespecial #55                 // Method "<init>":(Ljava/lang/String;I)V
      89: putstatic     #22                 // Field DRAFT:Lorg/hl7/fhir/dstu3/model/MedicationRequest$MedicationRequestStatus;
      92: new           #4                  // class org/hl7/fhir/dstu3/model/MedicationRequest$MedicationRequestStatus
      95: dup
      96: ldc           #62                 // String UNKNOWN
      98: bipush        7
     100: invokespecial #55                 // Method "<init>":(Ljava/lang/String;I)V
     103: putstatic     #24                 // Field UNKNOWN:Lorg/hl7/fhir/dstu3/model/MedicationRequest$MedicationRequestStatus;
     106: new           #4                  // class org/hl7/fhir/dstu3/model/MedicationRequest$MedicationRequestStatus
     109: dup
     110: ldc           #63                 // String NULL
     112: bipush        8
     114: invokespecial #55                 // Method "<init>":(Ljava/lang/String;I)V
     117: putstatic     #64                 // Field NULL:Lorg/hl7/fhir/dstu3/model/MedicationRequest$MedicationRequestStatus;
     120: bipush        9
     122: anewarray     #4                  // class org/hl7/fhir/dstu3/model/MedicationRequest$MedicationRequestStatus
     125: dup
     126: iconst_0
     127: getstatic     #10                 // Field ACTIVE:Lorg/hl7/fhir/dstu3/model/MedicationRequest$MedicationRequestStatus;
     130: aastore
     131: dup
     132: iconst_1
     133: getstatic     #12                 // Field ONHOLD:Lorg/hl7/fhir/dstu3/model/MedicationRequest$MedicationRequestStatus;
     136: aastore
     137: dup
     138: iconst_2
     139: getstatic     #14                 // Field CANCELLED:Lorg/hl7/fhir/dstu3/model/MedicationRequest$MedicationRequestStatus;
     142: aastore
     143: dup
     144: iconst_3
     145: getstatic     #16                 // Field COMPLETED:Lorg/hl7/fhir/dstu3/model/MedicationRequest$MedicationRequestStatus;
     148: aastore
     149: dup
     150: iconst_4
     151: getstatic     #18                 // Field ENTEREDINERROR:Lorg/hl7/fhir/dstu3/model/MedicationRequest$MedicationRequestStatus;
     154: aastore
     155: dup
     156: iconst_5
     157: getstatic     #20                 // Field STOPPED:Lorg/hl7/fhir/dstu3/model/MedicationRequest$MedicationRequestStatus;
     160: aastore
     161: dup
     162: bipush        6
     164: getstatic     #22                 // Field DRAFT:Lorg/hl7/fhir/dstu3/model/MedicationRequest$MedicationRequestStatus;
     167: aastore
     168: dup
     169: bipush        7
     171: getstatic     #24                 // Field UNKNOWN:Lorg/hl7/fhir/dstu3/model/MedicationRequest$MedicationRequestStatus;
     174: aastore
     175: dup
     176: bipush        8
     178: getstatic     #64                 // Field NULL:Lorg/hl7/fhir/dstu3/model/MedicationRequest$MedicationRequestStatus;
     181: aastore
     182: putstatic     #1                  // Field $VALUES:[Lorg/hl7/fhir/dstu3/model/MedicationRequest$MedicationRequestStatus;
     185: return
}
