Compiled from "OperationOutcome.java"
class org.hl7.fhir.dstu3.model.OperationOutcome$1 {
  static final int[] $SwitchMap$org$hl7$fhir$dstu3$model$OperationOutcome$IssueSeverity;

  static final int[] $SwitchMap$org$hl7$fhir$dstu3$model$OperationOutcome$IssueType;

  static {};
    Code:
       0: invokestatic  #1                  // Method org/hl7/fhir/dstu3/model/OperationOutcome$IssueType.values:()[Lorg/hl7/fhir/dstu3/model/OperationOutcome$IssueType;
       3: arraylength
       4: newarray       int
       6: putstatic     #2                  // Field $SwitchMap$org$hl7$fhir$dstu3$model$OperationOutcome$IssueType:[I
       9: getstatic     #2                  // Field $SwitchMap$org$hl7$fhir$dstu3$model$OperationOutcome$IssueType:[I
      12: getstatic     #3                  // Field org/hl7/fhir/dstu3/model/OperationOutcome$IssueType.INVALID:Lorg/hl7/fhir/dstu3/model/OperationOutcome$IssueType;
      15: invokevirtual #4                  // Method org/hl7/fhir/dstu3/model/OperationOutcome$IssueType.ordinal:()I
      18: iconst_1
      19: iastore
      20: goto          24
      23: astore_0
      24: getstatic     #2                  // Field $SwitchMap$org$hl7$fhir$dstu3$model$OperationOutcome$IssueType:[I
      27: getstatic     #6                  // Field org/hl7/fhir/dstu3/model/OperationOutcome$IssueType.STRUCTURE:Lorg/hl7/fhir/dstu3/model/OperationOutcome$IssueType;
      30: invokevirtual #4                  // Method org/hl7/fhir/dstu3/model/OperationOutcome$IssueType.ordinal:()I
      33: iconst_2
      34: iastore
      35: goto          39
      38: astore_0
      39: getstatic     #2                  // Field $SwitchMap$org$hl7$fhir$dstu3$model$OperationOutcome$IssueType:[I
      42: getstatic     #7                  // Field org/hl7/fhir/dstu3/model/OperationOutcome$IssueType.REQUIRED:Lorg/hl7/fhir/dstu3/model/OperationOutcome$IssueType;
      45: invokevirtual #4                  // Method org/hl7/fhir/dstu3/model/OperationOutcome$IssueType.ordinal:()I
      48: iconst_3
      49: iastore
      50: goto          54
      53: astore_0
      54: getstatic     #2                  // Field $SwitchMap$org$hl7$fhir$dstu3$model$OperationOutcome$IssueType:[I
      57: getstatic     #8                  // Field org/hl7/fhir/dstu3/model/OperationOutcome$IssueType.VALUE:Lorg/hl7/fhir/dstu3/model/OperationOutcome$IssueType;
      60: invokevirtual #4                  // Method org/hl7/fhir/dstu3/model/OperationOutcome$IssueType.ordinal:()I
      63: iconst_4
      64: iastore
      65: goto          69
      68: astore_0
      69: getstatic     #2                  // Field $SwitchMap$org$hl7$fhir$dstu3$model$OperationOutcome$IssueType:[I
      72: getstatic     #9                  // Field org/hl7/fhir/dstu3/model/OperationOutcome$IssueType.INVARIANT:Lorg/hl7/fhir/dstu3/model/OperationOutcome$IssueType;
      75: invokevirtual #4                  // Method org/hl7/fhir/dstu3/model/OperationOutcome$IssueType.ordinal:()I
      78: iconst_5
      79: iastore
      80: goto          84
      83: astore_0
      84: getstatic     #2                  // Field $SwitchMap$org$hl7$fhir$dstu3$model$OperationOutcome$IssueType:[I
      87: getstatic     #10                 // Field org/hl7/fhir/dstu3/model/OperationOutcome$IssueType.SECURITY:Lorg/hl7/fhir/dstu3/model/OperationOutcome$IssueType;
      90: invokevirtual #4                  // Method org/hl7/fhir/dstu3/model/OperationOutcome$IssueType.ordinal:()I
      93: bipush        6
      95: iastore
      96: goto          100
      99: astore_0
     100: getstatic     #2                  // Field $SwitchMap$org$hl7$fhir$dstu3$model$OperationOutcome$IssueType:[I
     103: getstatic     #11                 // Field org/hl7/fhir/dstu3/model/OperationOutcome$IssueType.LOGIN:Lorg/hl7/fhir/dstu3/model/OperationOutcome$IssueType;
     106: invokevirtual #4                  // Method org/hl7/fhir/dstu3/model/OperationOutcome$IssueType.ordinal:()I
     109: bipush        7
     111: iastore
     112: goto          116
     115: astore_0
     116: getstatic     #2                  // Field $SwitchMap$org$hl7$fhir$dstu3$model$OperationOutcome$IssueType:[I
     119: getstatic     #12                 // Field org/hl7/fhir/dstu3/model/OperationOutcome$IssueType.UNKNOWN:Lorg/hl7/fhir/dstu3/model/OperationOutcome$IssueType;
     122: invokevirtual #4                  // Method org/hl7/fhir/dstu3/model/OperationOutcome$IssueType.ordinal:()I
     125: bipush        8
     127: iastore
     128: goto          132
     131: astore_0
     132: getstatic     #2                  // Field $SwitchMap$org$hl7$fhir$dstu3$model$OperationOutcome$IssueType:[I
     135: getstatic     #13                 // Field org/hl7/fhir/dstu3/model/OperationOutcome$IssueType.EXPIRED:Lorg/hl7/fhir/dstu3/model/OperationOutcome$IssueType;
     138: invokevirtual #4                  // Method org/hl7/fhir/dstu3/model/OperationOutcome$IssueType.ordinal:()I
     141: bipush        9
     143: iastore
     144: goto          148
     147: astore_0
     148: getstatic     #2                  // Field $SwitchMap$org$hl7$fhir$dstu3$model$OperationOutcome$IssueType:[I
     151: getstatic     #14                 // Field org/hl7/fhir/dstu3/model/OperationOutcome$IssueType.FORBIDDEN:Lorg/hl7/fhir/dstu3/model/OperationOutcome$IssueType;
     154: invokevirtual #4                  // Method org/hl7/fhir/dstu3/model/OperationOutcome$IssueType.ordinal:()I
     157: bipush        10
     159: iastore
     160: goto          164
     163: astore_0
     164: getstatic     #2                  // Field $SwitchMap$org$hl7$fhir$dstu3$model$OperationOutcome$IssueType:[I
     167: getstatic     #15                 // Field org/hl7/fhir/dstu3/model/OperationOutcome$IssueType.SUPPRESSED:Lorg/hl7/fhir/dstu3/model/OperationOutcome$IssueType;
     170: invokevirtual #4                  // Method org/hl7/fhir/dstu3/model/OperationOutcome$IssueType.ordinal:()I
     173: bipush        11
     175: iastore
     176: goto          180
     179: astore_0
     180: getstatic     #2                  // Field $SwitchMap$org$hl7$fhir$dstu3$model$OperationOutcome$IssueType:[I
     183: getstatic     #16                 // Field org/hl7/fhir/dstu3/model/OperationOutcome$IssueType.PROCESSING:Lorg/hl7/fhir/dstu3/model/OperationOutcome$IssueType;
     186: invokevirtual #4                  // Method org/hl7/fhir/dstu3/model/OperationOutcome$IssueType.ordinal:()I
     189: bipush        12
     191: iastore
     192: goto          196
     195: astore_0
     196: getstatic     #2                  // Field $SwitchMap$org$hl7$fhir$dstu3$model$OperationOutcome$IssueType:[I
     199: getstatic     #17                 // Field org/hl7/fhir/dstu3/model/OperationOutcome$IssueType.NOTSUPPORTED:Lorg/hl7/fhir/dstu3/model/OperationOutcome$IssueType;
     202: invokevirtual #4                  // Method org/hl7/fhir/dstu3/model/OperationOutcome$IssueType.ordinal:()I
     205: bipush        13
     207: iastore
     208: goto          212
     211: astore_0
     212: getstatic     #2                  // Field $SwitchMap$org$hl7$fhir$dstu3$model$OperationOutcome$IssueType:[I
     215: getstatic     #18                 // Field org/hl7/fhir/dstu3/model/OperationOutcome$IssueType.DUPLICATE:Lorg/hl7/fhir/dstu3/model/OperationOutcome$IssueType;
     218: invokevirtual #4                  // Method org/hl7/fhir/dstu3/model/OperationOutcome$IssueType.ordinal:()I
     221: bipush        14
     223: iastore
     224: goto          228
     227: astore_0
     228: getstatic     #2                  // Field $SwitchMap$org$hl7$fhir$dstu3$model$OperationOutcome$IssueType:[I
     231: getstatic     #19                 // Field org/hl7/fhir/dstu3/model/OperationOutcome$IssueType.NOTFOUND:Lorg/hl7/fhir/dstu3/model/OperationOutcome$IssueType;
     234: invokevirtual #4                  // Method org/hl7/fhir/dstu3/model/OperationOutcome$IssueType.ordinal:()I
     237: bipush        15
     239: iastore
     240: goto          244
     243: astore_0
     244: getstatic     #2                  // Field $SwitchMap$org$hl7$fhir$dstu3$model$OperationOutcome$IssueType:[I
     247: getstatic     #20                 // Field org/hl7/fhir/dstu3/model/OperationOutcome$IssueType.TOOLONG:Lorg/hl7/fhir/dstu3/model/OperationOutcome$IssueType;
     250: invokevirtual #4                  // Method org/hl7/fhir/dstu3/model/OperationOutcome$IssueType.ordinal:()I
     253: bipush        16
     255: iastore
     256: goto          260
     259: astore_0
     260: getstatic     #2                  // Field $SwitchMap$org$hl7$fhir$dstu3$model$OperationOutcome$IssueType:[I
     263: getstatic     #21                 // Field org/hl7/fhir/dstu3/model/OperationOutcome$IssueType.CODEINVALID:Lorg/hl7/fhir/dstu3/model/OperationOutcome$IssueType;
     266: invokevirtual #4                  // Method org/hl7/fhir/dstu3/model/OperationOutcome$IssueType.ordinal:()I
     269: bipush        17
     271: iastore
     272: goto          276
     275: astore_0
     276: getstatic     #2                  // Field $SwitchMap$org$hl7$fhir$dstu3$model$OperationOutcome$IssueType:[I
     279: getstatic     #22                 // Field org/hl7/fhir/dstu3/model/OperationOutcome$IssueType.EXTENSION:Lorg/hl7/fhir/dstu3/model/OperationOutcome$IssueType;
     282: invokevirtual #4                  // Method org/hl7/fhir/dstu3/model/OperationOutcome$IssueType.ordinal:()I
     285: bipush        18
     287: iastore
     288: goto          292
     291: astore_0
     292: getstatic     #2                  // Field $SwitchMap$org$hl7$fhir$dstu3$model$OperationOutcome$IssueType:[I
     295: getstatic     #23                 // Field org/hl7/fhir/dstu3/model/OperationOutcome$IssueType.TOOCOSTLY:Lorg/hl7/fhir/dstu3/model/OperationOutcome$IssueType;
     298: invokevirtual #4                  // Method org/hl7/fhir/dstu3/model/OperationOutcome$IssueType.ordinal:()I
     301: bipush        19
     303: iastore
     304: goto          308
     307: astore_0
     308: getstatic     #2                  // Field $SwitchMap$org$hl7$fhir$dstu3$model$OperationOutcome$IssueType:[I
     311: getstatic     #24                 // Field org/hl7/fhir/dstu3/model/OperationOutcome$IssueType.BUSINESSRULE:Lorg/hl7/fhir/dstu3/model/OperationOutcome$IssueType;
     314: invokevirtual #4                  // Method org/hl7/fhir/dstu3/model/OperationOutcome$IssueType.ordinal:()I
     317: bipush        20
     319: iastore
     320: goto          324
     323: astore_0
     324: getstatic     #2                  // Field $SwitchMap$org$hl7$fhir$dstu3$model$OperationOutcome$IssueType:[I
     327: getstatic     #25                 // Field org/hl7/fhir/dstu3/model/OperationOutcome$IssueType.CONFLICT:Lorg/hl7/fhir/dstu3/model/OperationOutcome$IssueType;
     330: invokevirtual #4                  // Method org/hl7/fhir/dstu3/model/OperationOutcome$IssueType.ordinal:()I
     333: bipush        21
     335: iastore
     336: goto          340
     339: astore_0
     340: getstatic     #2                  // Field $SwitchMap$org$hl7$fhir$dstu3$model$OperationOutcome$IssueType:[I
     343: getstatic     #26                 // Field org/hl7/fhir/dstu3/model/OperationOutcome$IssueType.INCOMPLETE:Lorg/hl7/fhir/dstu3/model/OperationOutcome$IssueType;
     346: invokevirtual #4                  // Method org/hl7/fhir/dstu3/model/OperationOutcome$IssueType.ordinal:()I
     349: bipush        22
     351: iastore
     352: goto          356
     355: astore_0
     356: getstatic     #2                  // Field $SwitchMap$org$hl7$fhir$dstu3$model$OperationOutcome$IssueType:[I
     359: getstatic     #27                 // Field org/hl7/fhir/dstu3/model/OperationOutcome$IssueType.TRANSIENT:Lorg/hl7/fhir/dstu3/model/OperationOutcome$IssueType;
     362: invokevirtual #4                  // Method org/hl7/fhir/dstu3/model/OperationOutcome$IssueType.ordinal:()I
     365: bipush        23
     367: iastore
     368: goto          372
     371: astore_0
     372: getstatic     #2                  // Field $SwitchMap$org$hl7$fhir$dstu3$model$OperationOutcome$IssueType:[I
     375: getstatic     #28                 // Field org/hl7/fhir/dstu3/model/OperationOutcome$IssueType.LOCKERROR:Lorg/hl7/fhir/dstu3/model/OperationOutcome$IssueType;
     378: invokevirtual #4                  // Method org/hl7/fhir/dstu3/model/OperationOutcome$IssueType.ordinal:()I
     381: bipush        24
     383: iastore
     384: goto          388
     387: astore_0
     388: getstatic     #2                  // Field $SwitchMap$org$hl7$fhir$dstu3$model$OperationOutcome$IssueType:[I
     391: getstatic     #29                 // Field org/hl7/fhir/dstu3/model/OperationOutcome$IssueType.NOSTORE:Lorg/hl7/fhir/dstu3/model/OperationOutcome$IssueType;
     394: invokevirtual #4                  // Method org/hl7/fhir/dstu3/model/OperationOutcome$IssueType.ordinal:()I
     397: bipush        25
     399: iastore
     400: goto          404
     403: astore_0
     404: getstatic     #2                  // Field $SwitchMap$org$hl7$fhir$dstu3$model$OperationOutcome$IssueType:[I
     407: getstatic     #30                 // Field org/hl7/fhir/dstu3/model/OperationOutcome$IssueType.EXCEPTION:Lorg/hl7/fhir/dstu3/model/OperationOutcome$IssueType;
     410: invokevirtual #4                  // Method org/hl7/fhir/dstu3/model/OperationOutcome$IssueType.ordinal:()I
     413: bipush        26
     415: iastore
     416: goto          420
     419: astore_0
     420: getstatic     #2                  // Field $SwitchMap$org$hl7$fhir$dstu3$model$OperationOutcome$IssueType:[I
     423: getstatic     #31                 // Field org/hl7/fhir/dstu3/model/OperationOutcome$IssueType.TIMEOUT:Lorg/hl7/fhir/dstu3/model/OperationOutcome$IssueType;
     426: invokevirtual #4                  // Method org/hl7/fhir/dstu3/model/OperationOutcome$IssueType.ordinal:()I
     429: bipush        27
     431: iastore
     432: goto          436
     435: astore_0
     436: getstatic     #2                  // Field $SwitchMap$org$hl7$fhir$dstu3$model$OperationOutcome$IssueType:[I
     439: getstatic     #32                 // Field org/hl7/fhir/dstu3/model/OperationOutcome$IssueType.THROTTLED:Lorg/hl7/fhir/dstu3/model/OperationOutcome$IssueType;
     442: invokevirtual #4                  // Method org/hl7/fhir/dstu3/model/OperationOutcome$IssueType.ordinal:()I
     445: bipush        28
     447: iastore
     448: goto          452
     451: astore_0
     452: getstatic     #2                  // Field $SwitchMap$org$hl7$fhir$dstu3$model$OperationOutcome$IssueType:[I
     455: getstatic     #33                 // Field org/hl7/fhir/dstu3/model/OperationOutcome$IssueType.INFORMATIONAL:Lorg/hl7/fhir/dstu3/model/OperationOutcome$IssueType;
     458: invokevirtual #4                  // Method org/hl7/fhir/dstu3/model/OperationOutcome$IssueType.ordinal:()I
     461: bipush        29
     463: iastore
     464: goto          468
     467: astore_0
     468: getstatic     #2                  // Field $SwitchMap$org$hl7$fhir$dstu3$model$OperationOutcome$IssueType:[I
     471: getstatic     #34                 // Field org/hl7/fhir/dstu3/model/OperationOutcome$IssueType.NULL:Lorg/hl7/fhir/dstu3/model/OperationOutcome$IssueType;
     474: invokevirtual #4                  // Method org/hl7/fhir/dstu3/model/OperationOutcome$IssueType.ordinal:()I
     477: bipush        30
     479: iastore
     480: goto          484
     483: astore_0
     484: invokestatic  #35                 // Method org/hl7/fhir/dstu3/model/OperationOutcome$IssueSeverity.values:()[Lorg/hl7/fhir/dstu3/model/OperationOutcome$IssueSeverity;
     487: arraylength
     488: newarray       int
     490: putstatic     #36                 // Field $SwitchMap$org$hl7$fhir$dstu3$model$OperationOutcome$IssueSeverity:[I
     493: getstatic     #36                 // Field $SwitchMap$org$hl7$fhir$dstu3$model$OperationOutcome$IssueSeverity:[I
     496: getstatic     #37                 // Field org/hl7/fhir/dstu3/model/OperationOutcome$IssueSeverity.FATAL:Lorg/hl7/fhir/dstu3/model/OperationOutcome$IssueSeverity;
     499: invokevirtual #38                 // Method org/hl7/fhir/dstu3/model/OperationOutcome$IssueSeverity.ordinal:()I
     502: iconst_1
     503: iastore
     504: goto          508
     507: astore_0
     508: getstatic     #36                 // Field $SwitchMap$org$hl7$fhir$dstu3$model$OperationOutcome$IssueSeverity:[I
     511: getstatic     #39                 // Field org/hl7/fhir/dstu3/model/OperationOutcome$IssueSeverity.ERROR:Lorg/hl7/fhir/dstu3/model/OperationOutcome$IssueSeverity;
     514: invokevirtual #38                 // Method org/hl7/fhir/dstu3/model/OperationOutcome$IssueSeverity.ordinal:()I
     517: iconst_2
     518: iastore
     519: goto          523
     522: astore_0
     523: getstatic     #36                 // Field $SwitchMap$org$hl7$fhir$dstu3$model$OperationOutcome$IssueSeverity:[I
     526: getstatic     #40                 // Field org/hl7/fhir/dstu3/model/OperationOutcome$IssueSeverity.WARNING:Lorg/hl7/fhir/dstu3/model/OperationOutcome$IssueSeverity;
     529: invokevirtual #38                 // Method org/hl7/fhir/dstu3/model/OperationOutcome$IssueSeverity.ordinal:()I
     532: iconst_3
     533: iastore
     534: goto          538
     537: astore_0
     538: getstatic     #36                 // Field $SwitchMap$org$hl7$fhir$dstu3$model$OperationOutcome$IssueSeverity:[I
     541: getstatic     #41                 // Field org/hl7/fhir/dstu3/model/OperationOutcome$IssueSeverity.INFORMATION:Lorg/hl7/fhir/dstu3/model/OperationOutcome$IssueSeverity;
     544: invokevirtual #38                 // Method org/hl7/fhir/dstu3/model/OperationOutcome$IssueSeverity.ordinal:()I
     547: iconst_4
     548: iastore
     549: goto          553
     552: astore_0
     553: getstatic     #36                 // Field $SwitchMap$org$hl7$fhir$dstu3$model$OperationOutcome$IssueSeverity:[I
     556: getstatic     #42                 // Field org/hl7/fhir/dstu3/model/OperationOutcome$IssueSeverity.NULL:Lorg/hl7/fhir/dstu3/model/OperationOutcome$IssueSeverity;
     559: invokevirtual #38                 // Method org/hl7/fhir/dstu3/model/OperationOutcome$IssueSeverity.ordinal:()I
     562: iconst_5
     563: iastore
     564: goto          568
     567: astore_0
     568: return
    Exception table:
       from    to  target type
           9    20    23   Class java/lang/NoSuchFieldError
          24    35    38   Class java/lang/NoSuchFieldError
          39    50    53   Class java/lang/NoSuchFieldError
          54    65    68   Class java/lang/NoSuchFieldError
          69    80    83   Class java/lang/NoSuchFieldError
          84    96    99   Class java/lang/NoSuchFieldError
         100   112   115   Class java/lang/NoSuchFieldError
         116   128   131   Class java/lang/NoSuchFieldError
         132   144   147   Class java/lang/NoSuchFieldError
         148   160   163   Class java/lang/NoSuchFieldError
         164   176   179   Class java/lang/NoSuchFieldError
         180   192   195   Class java/lang/NoSuchFieldError
         196   208   211   Class java/lang/NoSuchFieldError
         212   224   227   Class java/lang/NoSuchFieldError
         228   240   243   Class java/lang/NoSuchFieldError
         244   256   259   Class java/lang/NoSuchFieldError
         260   272   275   Class java/lang/NoSuchFieldError
         276   288   291   Class java/lang/NoSuchFieldError
         292   304   307   Class java/lang/NoSuchFieldError
         308   320   323   Class java/lang/NoSuchFieldError
         324   336   339   Class java/lang/NoSuchFieldError
         340   352   355   Class java/lang/NoSuchFieldError
         356   368   371   Class java/lang/NoSuchFieldError
         372   384   387   Class java/lang/NoSuchFieldError
         388   400   403   Class java/lang/NoSuchFieldError
         404   416   419   Class java/lang/NoSuchFieldError
         420   432   435   Class java/lang/NoSuchFieldError
         436   448   451   Class java/lang/NoSuchFieldError
         452   464   467   Class java/lang/NoSuchFieldError
         468   480   483   Class java/lang/NoSuchFieldError
         493   504   507   Class java/lang/NoSuchFieldError
         508   519   522   Class java/lang/NoSuchFieldError
         523   534   537   Class java/lang/NoSuchFieldError
         538   549   552   Class java/lang/NoSuchFieldError
         553   564   567   Class java/lang/NoSuchFieldError
}
