Compiled from "TestScript.java"
class org.hl7.fhir.dstu3.model.TestScript$1 {
  static final int[] $SwitchMap$org$hl7$fhir$dstu3$model$TestScript$ContentType;

  static final int[] $SwitchMap$org$hl7$fhir$dstu3$model$TestScript$AssertionDirectionType;

  static final int[] $SwitchMap$org$hl7$fhir$dstu3$model$TestScript$AssertionOperatorType;

  static final int[] $SwitchMap$org$hl7$fhir$dstu3$model$TestScript$TestScriptRequestMethodCode;

  static final int[] $SwitchMap$org$hl7$fhir$dstu3$model$TestScript$AssertionResponseTypes;

  static {};
    Code:
       0: invokestatic  #1                  // Method org/hl7/fhir/dstu3/model/TestScript$AssertionResponseTypes.values:()[Lorg/hl7/fhir/dstu3/model/TestScript$AssertionResponseTypes;
       3: arraylength
       4: newarray       int
       6: putstatic     #2                  // Field $SwitchMap$org$hl7$fhir$dstu3$model$TestScript$AssertionResponseTypes:[I
       9: getstatic     #2                  // Field $SwitchMap$org$hl7$fhir$dstu3$model$TestScript$AssertionResponseTypes:[I
      12: getstatic     #3                  // Field org/hl7/fhir/dstu3/model/TestScript$AssertionResponseTypes.OKAY:Lorg/hl7/fhir/dstu3/model/TestScript$AssertionResponseTypes;
      15: invokevirtual #4                  // Method org/hl7/fhir/dstu3/model/TestScript$AssertionResponseTypes.ordinal:()I
      18: iconst_1
      19: iastore
      20: goto          24
      23: astore_0
      24: getstatic     #2                  // Field $SwitchMap$org$hl7$fhir$dstu3$model$TestScript$AssertionResponseTypes:[I
      27: getstatic     #6                  // Field org/hl7/fhir/dstu3/model/TestScript$AssertionResponseTypes.CREATED:Lorg/hl7/fhir/dstu3/model/TestScript$AssertionResponseTypes;
      30: invokevirtual #4                  // Method org/hl7/fhir/dstu3/model/TestScript$AssertionResponseTypes.ordinal:()I
      33: iconst_2
      34: iastore
      35: goto          39
      38: astore_0
      39: getstatic     #2                  // Field $SwitchMap$org$hl7$fhir$dstu3$model$TestScript$AssertionResponseTypes:[I
      42: getstatic     #7                  // Field org/hl7/fhir/dstu3/model/TestScript$AssertionResponseTypes.NOCONTENT:Lorg/hl7/fhir/dstu3/model/TestScript$AssertionResponseTypes;
      45: invokevirtual #4                  // Method org/hl7/fhir/dstu3/model/TestScript$AssertionResponseTypes.ordinal:()I
      48: iconst_3
      49: iastore
      50: goto          54
      53: astore_0
      54: getstatic     #2                  // Field $SwitchMap$org$hl7$fhir$dstu3$model$TestScript$AssertionResponseTypes:[I
      57: getstatic     #8                  // Field org/hl7/fhir/dstu3/model/TestScript$AssertionResponseTypes.NOTMODIFIED:Lorg/hl7/fhir/dstu3/model/TestScript$AssertionResponseTypes;
      60: invokevirtual #4                  // Method org/hl7/fhir/dstu3/model/TestScript$AssertionResponseTypes.ordinal:()I
      63: iconst_4
      64: iastore
      65: goto          69
      68: astore_0
      69: getstatic     #2                  // Field $SwitchMap$org$hl7$fhir$dstu3$model$TestScript$AssertionResponseTypes:[I
      72: getstatic     #9                  // Field org/hl7/fhir/dstu3/model/TestScript$AssertionResponseTypes.BAD:Lorg/hl7/fhir/dstu3/model/TestScript$AssertionResponseTypes;
      75: invokevirtual #4                  // Method org/hl7/fhir/dstu3/model/TestScript$AssertionResponseTypes.ordinal:()I
      78: iconst_5
      79: iastore
      80: goto          84
      83: astore_0
      84: getstatic     #2                  // Field $SwitchMap$org$hl7$fhir$dstu3$model$TestScript$AssertionResponseTypes:[I
      87: getstatic     #10                 // Field org/hl7/fhir/dstu3/model/TestScript$AssertionResponseTypes.FORBIDDEN:Lorg/hl7/fhir/dstu3/model/TestScript$AssertionResponseTypes;
      90: invokevirtual #4                  // Method org/hl7/fhir/dstu3/model/TestScript$AssertionResponseTypes.ordinal:()I
      93: bipush        6
      95: iastore
      96: goto          100
      99: astore_0
     100: getstatic     #2                  // Field $SwitchMap$org$hl7$fhir$dstu3$model$TestScript$AssertionResponseTypes:[I
     103: getstatic     #11                 // Field org/hl7/fhir/dstu3/model/TestScript$AssertionResponseTypes.NOTFOUND:Lorg/hl7/fhir/dstu3/model/TestScript$AssertionResponseTypes;
     106: invokevirtual #4                  // Method org/hl7/fhir/dstu3/model/TestScript$AssertionResponseTypes.ordinal:()I
     109: bipush        7
     111: iastore
     112: goto          116
     115: astore_0
     116: getstatic     #2                  // Field $SwitchMap$org$hl7$fhir$dstu3$model$TestScript$AssertionResponseTypes:[I
     119: getstatic     #12                 // Field org/hl7/fhir/dstu3/model/TestScript$AssertionResponseTypes.METHODNOTALLOWED:Lorg/hl7/fhir/dstu3/model/TestScript$AssertionResponseTypes;
     122: invokevirtual #4                  // Method org/hl7/fhir/dstu3/model/TestScript$AssertionResponseTypes.ordinal:()I
     125: bipush        8
     127: iastore
     128: goto          132
     131: astore_0
     132: getstatic     #2                  // Field $SwitchMap$org$hl7$fhir$dstu3$model$TestScript$AssertionResponseTypes:[I
     135: getstatic     #13                 // Field org/hl7/fhir/dstu3/model/TestScript$AssertionResponseTypes.CONFLICT:Lorg/hl7/fhir/dstu3/model/TestScript$AssertionResponseTypes;
     138: invokevirtual #4                  // Method org/hl7/fhir/dstu3/model/TestScript$AssertionResponseTypes.ordinal:()I
     141: bipush        9
     143: iastore
     144: goto          148
     147: astore_0
     148: getstatic     #2                  // Field $SwitchMap$org$hl7$fhir$dstu3$model$TestScript$AssertionResponseTypes:[I
     151: getstatic     #14                 // Field org/hl7/fhir/dstu3/model/TestScript$AssertionResponseTypes.GONE:Lorg/hl7/fhir/dstu3/model/TestScript$AssertionResponseTypes;
     154: invokevirtual #4                  // Method org/hl7/fhir/dstu3/model/TestScript$AssertionResponseTypes.ordinal:()I
     157: bipush        10
     159: iastore
     160: goto          164
     163: astore_0
     164: getstatic     #2                  // Field $SwitchMap$org$hl7$fhir$dstu3$model$TestScript$AssertionResponseTypes:[I
     167: getstatic     #15                 // Field org/hl7/fhir/dstu3/model/TestScript$AssertionResponseTypes.PRECONDITIONFAILED:Lorg/hl7/fhir/dstu3/model/TestScript$AssertionResponseTypes;
     170: invokevirtual #4                  // Method org/hl7/fhir/dstu3/model/TestScript$AssertionResponseTypes.ordinal:()I
     173: bipush        11
     175: iastore
     176: goto          180
     179: astore_0
     180: getstatic     #2                  // Field $SwitchMap$org$hl7$fhir$dstu3$model$TestScript$AssertionResponseTypes:[I
     183: getstatic     #16                 // Field org/hl7/fhir/dstu3/model/TestScript$AssertionResponseTypes.UNPROCESSABLE:Lorg/hl7/fhir/dstu3/model/TestScript$AssertionResponseTypes;
     186: invokevirtual #4                  // Method org/hl7/fhir/dstu3/model/TestScript$AssertionResponseTypes.ordinal:()I
     189: bipush        12
     191: iastore
     192: goto          196
     195: astore_0
     196: getstatic     #2                  // Field $SwitchMap$org$hl7$fhir$dstu3$model$TestScript$AssertionResponseTypes:[I
     199: getstatic     #17                 // Field org/hl7/fhir/dstu3/model/TestScript$AssertionResponseTypes.NULL:Lorg/hl7/fhir/dstu3/model/TestScript$AssertionResponseTypes;
     202: invokevirtual #4                  // Method org/hl7/fhir/dstu3/model/TestScript$AssertionResponseTypes.ordinal:()I
     205: bipush        13
     207: iastore
     208: goto          212
     211: astore_0
     212: invokestatic  #18                 // Method org/hl7/fhir/dstu3/model/TestScript$TestScriptRequestMethodCode.values:()[Lorg/hl7/fhir/dstu3/model/TestScript$TestScriptRequestMethodCode;
     215: arraylength
     216: newarray       int
     218: putstatic     #19                 // Field $SwitchMap$org$hl7$fhir$dstu3$model$TestScript$TestScriptRequestMethodCode:[I
     221: getstatic     #19                 // Field $SwitchMap$org$hl7$fhir$dstu3$model$TestScript$TestScriptRequestMethodCode:[I
     224: getstatic     #20                 // Field org/hl7/fhir/dstu3/model/TestScript$TestScriptRequestMethodCode.DELETE:Lorg/hl7/fhir/dstu3/model/TestScript$TestScriptRequestMethodCode;
     227: invokevirtual #21                 // Method org/hl7/fhir/dstu3/model/TestScript$TestScriptRequestMethodCode.ordinal:()I
     230: iconst_1
     231: iastore
     232: goto          236
     235: astore_0
     236: getstatic     #19                 // Field $SwitchMap$org$hl7$fhir$dstu3$model$TestScript$TestScriptRequestMethodCode:[I
     239: getstatic     #22                 // Field org/hl7/fhir/dstu3/model/TestScript$TestScriptRequestMethodCode.GET:Lorg/hl7/fhir/dstu3/model/TestScript$TestScriptRequestMethodCode;
     242: invokevirtual #21                 // Method org/hl7/fhir/dstu3/model/TestScript$TestScriptRequestMethodCode.ordinal:()I
     245: iconst_2
     246: iastore
     247: goto          251
     250: astore_0
     251: getstatic     #19                 // Field $SwitchMap$org$hl7$fhir$dstu3$model$TestScript$TestScriptRequestMethodCode:[I
     254: getstatic     #23                 // Field org/hl7/fhir/dstu3/model/TestScript$TestScriptRequestMethodCode.OPTIONS:Lorg/hl7/fhir/dstu3/model/TestScript$TestScriptRequestMethodCode;
     257: invokevirtual #21                 // Method org/hl7/fhir/dstu3/model/TestScript$TestScriptRequestMethodCode.ordinal:()I
     260: iconst_3
     261: iastore
     262: goto          266
     265: astore_0
     266: getstatic     #19                 // Field $SwitchMap$org$hl7$fhir$dstu3$model$TestScript$TestScriptRequestMethodCode:[I
     269: getstatic     #24                 // Field org/hl7/fhir/dstu3/model/TestScript$TestScriptRequestMethodCode.PATCH:Lorg/hl7/fhir/dstu3/model/TestScript$TestScriptRequestMethodCode;
     272: invokevirtual #21                 // Method org/hl7/fhir/dstu3/model/TestScript$TestScriptRequestMethodCode.ordinal:()I
     275: iconst_4
     276: iastore
     277: goto          281
     280: astore_0
     281: getstatic     #19                 // Field $SwitchMap$org$hl7$fhir$dstu3$model$TestScript$TestScriptRequestMethodCode:[I
     284: getstatic     #25                 // Field org/hl7/fhir/dstu3/model/TestScript$TestScriptRequestMethodCode.POST:Lorg/hl7/fhir/dstu3/model/TestScript$TestScriptRequestMethodCode;
     287: invokevirtual #21                 // Method org/hl7/fhir/dstu3/model/TestScript$TestScriptRequestMethodCode.ordinal:()I
     290: iconst_5
     291: iastore
     292: goto          296
     295: astore_0
     296: getstatic     #19                 // Field $SwitchMap$org$hl7$fhir$dstu3$model$TestScript$TestScriptRequestMethodCode:[I
     299: getstatic     #26                 // Field org/hl7/fhir/dstu3/model/TestScript$TestScriptRequestMethodCode.PUT:Lorg/hl7/fhir/dstu3/model/TestScript$TestScriptRequestMethodCode;
     302: invokevirtual #21                 // Method org/hl7/fhir/dstu3/model/TestScript$TestScriptRequestMethodCode.ordinal:()I
     305: bipush        6
     307: iastore
     308: goto          312
     311: astore_0
     312: getstatic     #19                 // Field $SwitchMap$org$hl7$fhir$dstu3$model$TestScript$TestScriptRequestMethodCode:[I
     315: getstatic     #27                 // Field org/hl7/fhir/dstu3/model/TestScript$TestScriptRequestMethodCode.NULL:Lorg/hl7/fhir/dstu3/model/TestScript$TestScriptRequestMethodCode;
     318: invokevirtual #21                 // Method org/hl7/fhir/dstu3/model/TestScript$TestScriptRequestMethodCode.ordinal:()I
     321: bipush        7
     323: iastore
     324: goto          328
     327: astore_0
     328: invokestatic  #28                 // Method org/hl7/fhir/dstu3/model/TestScript$AssertionOperatorType.values:()[Lorg/hl7/fhir/dstu3/model/TestScript$AssertionOperatorType;
     331: arraylength
     332: newarray       int
     334: putstatic     #29                 // Field $SwitchMap$org$hl7$fhir$dstu3$model$TestScript$AssertionOperatorType:[I
     337: getstatic     #29                 // Field $SwitchMap$org$hl7$fhir$dstu3$model$TestScript$AssertionOperatorType:[I
     340: getstatic     #30                 // Field org/hl7/fhir/dstu3/model/TestScript$AssertionOperatorType.EQUALS:Lorg/hl7/fhir/dstu3/model/TestScript$AssertionOperatorType;
     343: invokevirtual #31                 // Method org/hl7/fhir/dstu3/model/TestScript$AssertionOperatorType.ordinal:()I
     346: iconst_1
     347: iastore
     348: goto          352
     351: astore_0
     352: getstatic     #29                 // Field $SwitchMap$org$hl7$fhir$dstu3$model$TestScript$AssertionOperatorType:[I
     355: getstatic     #32                 // Field org/hl7/fhir/dstu3/model/TestScript$AssertionOperatorType.NOTEQUALS:Lorg/hl7/fhir/dstu3/model/TestScript$AssertionOperatorType;
     358: invokevirtual #31                 // Method org/hl7/fhir/dstu3/model/TestScript$AssertionOperatorType.ordinal:()I
     361: iconst_2
     362: iastore
     363: goto          367
     366: astore_0
     367: getstatic     #29                 // Field $SwitchMap$org$hl7$fhir$dstu3$model$TestScript$AssertionOperatorType:[I
     370: getstatic     #33                 // Field org/hl7/fhir/dstu3/model/TestScript$AssertionOperatorType.IN:Lorg/hl7/fhir/dstu3/model/TestScript$AssertionOperatorType;
     373: invokevirtual #31                 // Method org/hl7/fhir/dstu3/model/TestScript$AssertionOperatorType.ordinal:()I
     376: iconst_3
     377: iastore
     378: goto          382
     381: astore_0
     382: getstatic     #29                 // Field $SwitchMap$org$hl7$fhir$dstu3$model$TestScript$AssertionOperatorType:[I
     385: getstatic     #34                 // Field org/hl7/fhir/dstu3/model/TestScript$AssertionOperatorType.NOTIN:Lorg/hl7/fhir/dstu3/model/TestScript$AssertionOperatorType;
     388: invokevirtual #31                 // Method org/hl7/fhir/dstu3/model/TestScript$AssertionOperatorType.ordinal:()I
     391: iconst_4
     392: iastore
     393: goto          397
     396: astore_0
     397: getstatic     #29                 // Field $SwitchMap$org$hl7$fhir$dstu3$model$TestScript$AssertionOperatorType:[I
     400: getstatic     #35                 // Field org/hl7/fhir/dstu3/model/TestScript$AssertionOperatorType.GREATERTHAN:Lorg/hl7/fhir/dstu3/model/TestScript$AssertionOperatorType;
     403: invokevirtual #31                 // Method org/hl7/fhir/dstu3/model/TestScript$AssertionOperatorType.ordinal:()I
     406: iconst_5
     407: iastore
     408: goto          412
     411: astore_0
     412: getstatic     #29                 // Field $SwitchMap$org$hl7$fhir$dstu3$model$TestScript$AssertionOperatorType:[I
     415: getstatic     #36                 // Field org/hl7/fhir/dstu3/model/TestScript$AssertionOperatorType.LESSTHAN:Lorg/hl7/fhir/dstu3/model/TestScript$AssertionOperatorType;
     418: invokevirtual #31                 // Method org/hl7/fhir/dstu3/model/TestScript$AssertionOperatorType.ordinal:()I
     421: bipush        6
     423: iastore
     424: goto          428
     427: astore_0
     428: getstatic     #29                 // Field $SwitchMap$org$hl7$fhir$dstu3$model$TestScript$AssertionOperatorType:[I
     431: getstatic     #37                 // Field org/hl7/fhir/dstu3/model/TestScript$AssertionOperatorType.EMPTY:Lorg/hl7/fhir/dstu3/model/TestScript$AssertionOperatorType;
     434: invokevirtual #31                 // Method org/hl7/fhir/dstu3/model/TestScript$AssertionOperatorType.ordinal:()I
     437: bipush        7
     439: iastore
     440: goto          444
     443: astore_0
     444: getstatic     #29                 // Field $SwitchMap$org$hl7$fhir$dstu3$model$TestScript$AssertionOperatorType:[I
     447: getstatic     #38                 // Field org/hl7/fhir/dstu3/model/TestScript$AssertionOperatorType.NOTEMPTY:Lorg/hl7/fhir/dstu3/model/TestScript$AssertionOperatorType;
     450: invokevirtual #31                 // Method org/hl7/fhir/dstu3/model/TestScript$AssertionOperatorType.ordinal:()I
     453: bipush        8
     455: iastore
     456: goto          460
     459: astore_0
     460: getstatic     #29                 // Field $SwitchMap$org$hl7$fhir$dstu3$model$TestScript$AssertionOperatorType:[I
     463: getstatic     #39                 // Field org/hl7/fhir/dstu3/model/TestScript$AssertionOperatorType.CONTAINS:Lorg/hl7/fhir/dstu3/model/TestScript$AssertionOperatorType;
     466: invokevirtual #31                 // Method org/hl7/fhir/dstu3/model/TestScript$AssertionOperatorType.ordinal:()I
     469: bipush        9
     471: iastore
     472: goto          476
     475: astore_0
     476: getstatic     #29                 // Field $SwitchMap$org$hl7$fhir$dstu3$model$TestScript$AssertionOperatorType:[I
     479: getstatic     #40                 // Field org/hl7/fhir/dstu3/model/TestScript$AssertionOperatorType.NOTCONTAINS:Lorg/hl7/fhir/dstu3/model/TestScript$AssertionOperatorType;
     482: invokevirtual #31                 // Method org/hl7/fhir/dstu3/model/TestScript$AssertionOperatorType.ordinal:()I
     485: bipush        10
     487: iastore
     488: goto          492
     491: astore_0
     492: getstatic     #29                 // Field $SwitchMap$org$hl7$fhir$dstu3$model$TestScript$AssertionOperatorType:[I
     495: getstatic     #41                 // Field org/hl7/fhir/dstu3/model/TestScript$AssertionOperatorType.EVAL:Lorg/hl7/fhir/dstu3/model/TestScript$AssertionOperatorType;
     498: invokevirtual #31                 // Method org/hl7/fhir/dstu3/model/TestScript$AssertionOperatorType.ordinal:()I
     501: bipush        11
     503: iastore
     504: goto          508
     507: astore_0
     508: getstatic     #29                 // Field $SwitchMap$org$hl7$fhir$dstu3$model$TestScript$AssertionOperatorType:[I
     511: getstatic     #42                 // Field org/hl7/fhir/dstu3/model/TestScript$AssertionOperatorType.NULL:Lorg/hl7/fhir/dstu3/model/TestScript$AssertionOperatorType;
     514: invokevirtual #31                 // Method org/hl7/fhir/dstu3/model/TestScript$AssertionOperatorType.ordinal:()I
     517: bipush        12
     519: iastore
     520: goto          524
     523: astore_0
     524: invokestatic  #43                 // Method org/hl7/fhir/dstu3/model/TestScript$AssertionDirectionType.values:()[Lorg/hl7/fhir/dstu3/model/TestScript$AssertionDirectionType;
     527: arraylength
     528: newarray       int
     530: putstatic     #44                 // Field $SwitchMap$org$hl7$fhir$dstu3$model$TestScript$AssertionDirectionType:[I
     533: getstatic     #44                 // Field $SwitchMap$org$hl7$fhir$dstu3$model$TestScript$AssertionDirectionType:[I
     536: getstatic     #45                 // Field org/hl7/fhir/dstu3/model/TestScript$AssertionDirectionType.RESPONSE:Lorg/hl7/fhir/dstu3/model/TestScript$AssertionDirectionType;
     539: invokevirtual #46                 // Method org/hl7/fhir/dstu3/model/TestScript$AssertionDirectionType.ordinal:()I
     542: iconst_1
     543: iastore
     544: goto          548
     547: astore_0
     548: getstatic     #44                 // Field $SwitchMap$org$hl7$fhir$dstu3$model$TestScript$AssertionDirectionType:[I
     551: getstatic     #47                 // Field org/hl7/fhir/dstu3/model/TestScript$AssertionDirectionType.REQUEST:Lorg/hl7/fhir/dstu3/model/TestScript$AssertionDirectionType;
     554: invokevirtual #46                 // Method org/hl7/fhir/dstu3/model/TestScript$AssertionDirectionType.ordinal:()I
     557: iconst_2
     558: iastore
     559: goto          563
     562: astore_0
     563: getstatic     #44                 // Field $SwitchMap$org$hl7$fhir$dstu3$model$TestScript$AssertionDirectionType:[I
     566: getstatic     #48                 // Field org/hl7/fhir/dstu3/model/TestScript$AssertionDirectionType.NULL:Lorg/hl7/fhir/dstu3/model/TestScript$AssertionDirectionType;
     569: invokevirtual #46                 // Method org/hl7/fhir/dstu3/model/TestScript$AssertionDirectionType.ordinal:()I
     572: iconst_3
     573: iastore
     574: goto          578
     577: astore_0
     578: invokestatic  #49                 // Method org/hl7/fhir/dstu3/model/TestScript$ContentType.values:()[Lorg/hl7/fhir/dstu3/model/TestScript$ContentType;
     581: arraylength
     582: newarray       int
     584: putstatic     #50                 // Field $SwitchMap$org$hl7$fhir$dstu3$model$TestScript$ContentType:[I
     587: getstatic     #50                 // Field $SwitchMap$org$hl7$fhir$dstu3$model$TestScript$ContentType:[I
     590: getstatic     #51                 // Field org/hl7/fhir/dstu3/model/TestScript$ContentType.XML:Lorg/hl7/fhir/dstu3/model/TestScript$ContentType;
     593: invokevirtual #52                 // Method org/hl7/fhir/dstu3/model/TestScript$ContentType.ordinal:()I
     596: iconst_1
     597: iastore
     598: goto          602
     601: astore_0
     602: getstatic     #50                 // Field $SwitchMap$org$hl7$fhir$dstu3$model$TestScript$ContentType:[I
     605: getstatic     #53                 // Field org/hl7/fhir/dstu3/model/TestScript$ContentType.JSON:Lorg/hl7/fhir/dstu3/model/TestScript$ContentType;
     608: invokevirtual #52                 // Method org/hl7/fhir/dstu3/model/TestScript$ContentType.ordinal:()I
     611: iconst_2
     612: iastore
     613: goto          617
     616: astore_0
     617: getstatic     #50                 // Field $SwitchMap$org$hl7$fhir$dstu3$model$TestScript$ContentType:[I
     620: getstatic     #54                 // Field org/hl7/fhir/dstu3/model/TestScript$ContentType.TTL:Lorg/hl7/fhir/dstu3/model/TestScript$ContentType;
     623: invokevirtual #52                 // Method org/hl7/fhir/dstu3/model/TestScript$ContentType.ordinal:()I
     626: iconst_3
     627: iastore
     628: goto          632
     631: astore_0
     632: getstatic     #50                 // Field $SwitchMap$org$hl7$fhir$dstu3$model$TestScript$ContentType:[I
     635: getstatic     #55                 // Field org/hl7/fhir/dstu3/model/TestScript$ContentType.NONE:Lorg/hl7/fhir/dstu3/model/TestScript$ContentType;
     638: invokevirtual #52                 // Method org/hl7/fhir/dstu3/model/TestScript$ContentType.ordinal:()I
     641: iconst_4
     642: iastore
     643: goto          647
     646: astore_0
     647: getstatic     #50                 // Field $SwitchMap$org$hl7$fhir$dstu3$model$TestScript$ContentType:[I
     650: getstatic     #56                 // Field org/hl7/fhir/dstu3/model/TestScript$ContentType.NULL:Lorg/hl7/fhir/dstu3/model/TestScript$ContentType;
     653: invokevirtual #52                 // Method org/hl7/fhir/dstu3/model/TestScript$ContentType.ordinal:()I
     656: iconst_5
     657: iastore
     658: goto          662
     661: astore_0
     662: return
    Exception table:
       from    to  target type
           9    20    23   Class java/lang/NoSuchFieldError
          24    35    38   Class java/lang/NoSuchFieldError
          39    50    53   Class java/lang/NoSuchFieldError
          54    65    68   Class java/lang/NoSuchFieldError
          69    80    83   Class java/lang/NoSuchFieldError
          84    96    99   Class java/lang/NoSuchFieldError
         100   112   115   Class java/lang/NoSuchFieldError
         116   128   131   Class java/lang/NoSuchFieldError
         132   144   147   Class java/lang/NoSuchFieldError
         148   160   163   Class java/lang/NoSuchFieldError
         164   176   179   Class java/lang/NoSuchFieldError
         180   192   195   Class java/lang/NoSuchFieldError
         196   208   211   Class java/lang/NoSuchFieldError
         221   232   235   Class java/lang/NoSuchFieldError
         236   247   250   Class java/lang/NoSuchFieldError
         251   262   265   Class java/lang/NoSuchFieldError
         266   277   280   Class java/lang/NoSuchFieldError
         281   292   295   Class java/lang/NoSuchFieldError
         296   308   311   Class java/lang/NoSuchFieldError
         312   324   327   Class java/lang/NoSuchFieldError
         337   348   351   Class java/lang/NoSuchFieldError
         352   363   366   Class java/lang/NoSuchFieldError
         367   378   381   Class java/lang/NoSuchFieldError
         382   393   396   Class java/lang/NoSuchFieldError
         397   408   411   Class java/lang/NoSuchFieldError
         412   424   427   Class java/lang/NoSuchFieldError
         428   440   443   Class java/lang/NoSuchFieldError
         444   456   459   Class java/lang/NoSuchFieldError
         460   472   475   Class java/lang/NoSuchFieldError
         476   488   491   Class java/lang/NoSuchFieldError
         492   504   507   Class java/lang/NoSuchFieldError
         508   520   523   Class java/lang/NoSuchFieldError
         533   544   547   Class java/lang/NoSuchFieldError
         548   559   562   Class java/lang/NoSuchFieldError
         563   574   577   Class java/lang/NoSuchFieldError
         587   598   601   Class java/lang/NoSuchFieldError
         602   613   616   Class java/lang/NoSuchFieldError
         617   628   631   Class java/lang/NoSuchFieldError
         632   643   646   Class java/lang/NoSuchFieldError
         647   658   661   Class java/lang/NoSuchFieldError
}
